Workbook

Sheet Instruções
C3: =TODAY() -> 45954
B7: 1. Instruções
B9: 1. Alterar apenas o que está assinalado a amarelo.
B10: Nota: No campo ref_date, colocar plica no início da data, de modo a manter o formato texto.
C12: Info | F12: Table_name | G12: Table as-is | H12: Table to-be | I12: Chave1 | J12: Chave2
C13: schema as-is (prod.) | D13: cd_loan_tapes_bce | F13: ENTTY | G13: lt003_entity | H13: lt003_entity | I13: entty_id
C14: schema to-be (testes) | D14: bu_loantape_work | F14: INSTR_ENTTY | G14: lt005_instr_ent | H14: lt005_instr_ent | I14: instrmnt_id | J14: entty_id
C15: ref_date | D15: 2024-09-30 | F15: INSTR_PRTCTN | G15: lt006_instr_prot | H15: lt006_instr_prot | I15: instrmnt_id | J15: prtctn_id
C16: nome_perimetro | D16: Individual Corporativo | F16: INSTRMNT | G16: lt002_instrument | H16: lt002_instrument | I16: instrmnt_id
C17: segmento | D17: ESTR | F17: PRTCTN | G17: lt004_protection | H17: lt004_protection | I17: prtctn_id
C18: ambito_1 | D18: PM
C19: ambito_2 | D19: PM | F19: Tipologia testes
C20: filtro_f_1 | D20: ="ref_date='"&$D$15&"' AND nome_perimetro='"&$D$16&"' AND segmento='"&$D$17&"' AND ambito='"&$D$18&"' AND entidade='00100' " -> ref_date='2024-09-30' AND nome_perimetro='Individual Corporativo' AND segmento='ESTR' AND ambito='PM' AND entidade='00100' | F20: Validação campos
C21: filtro_f_2 | D21: ="ref_date='"&$D$15&"' AND nome_perimetro='"&$D$16&"' AND segmento='"&$D$17&"' AND ambito='"&$D$18&"' AND entidade='00100' " -> ref_date='2024-09-30' AND nome_perimetro='Individual Corporativo' AND segmento='ESTR' AND ambito='PM' AND entidade='00100' | F21: Validação universo
B23: 2. Executar, no HUE, as linhas da coluna Union all por blocos > correr cada bloco de 30 em 30.

Sheet Testes regressivos
C3: =TODAY() -> 45954
F7: as_is | G7: to_be
B8: Table_name | C8: Table as-is | D8: Table to-be | E8: Column_name | F8: Column_name_1 | G8: Column_name_2 | H8: Universo_1 | I8: Universo_2 | J8: Metodologia de cruzamento | K8: Condição | L8: Query 1 | M8: Tipologia testes | N8: Query 2 | O8: Union all | P8: Contagem
B9: ENTTY | C9: =_xlfn.CONCAT(Instruções!$D$13,".",VLOOKUP(B9,Instruções!$F$12:$H$17,2,0)) -> cd_loan_tapes_bce.lt003_entity | D9: =_xlfn.CONCAT(Instruções!$D$14,".",VLOOKUP(B9,Instruções!$F$12:$H$17,3,0)) -> bu_loantape_work.lt003_entity | E9: accntng_frmwrk_sl | F9: =E9&"_"&$F$7 -> accntng_frmwrk_sl_as_is | G9: =E9&"_"&$G$7 -> accntng_frmwrk_sl_to_be | H9: =IF(VLOOKUP(B9,Instruções!$F$13:$J$17,5,0)="", "(SELECT "&VLOOKUP(B9,Instruções!$F$13:$J$17,4,0)&" as "&VLOOKUP(B9,Instruções!$F$13:$J$17,4,0)&"_"&$F$2&", "&E9&" as "&F9&" FROM "&C9&" WHERE "&Instruções!$D$20&") A ", "(SELECT "&VLOOKUP(B9,Instruções!$F$13:$J$17,4,0)&" as "&VLOOKUP(B9,Instruções!$F$13:$J$17,4,0)&"_"&$F$2&", "&VLOOKUP(B9,Instruções!$F$13:$J$17,5,0)&" as "&VLOOKUP(B9,Instruções!$F$13:$J$17,5,0)&"_"&$F$2&","&E9&" as "&F9&" FROM "&C9&" WHERE "&Instruções!$D$20&") A ") -> (SELECT entty_id as entty_id_, accntng_frmwrk_sl as accntng_frmwrk_sl_as_is FROM cd_loan_tapes_bce.lt003_entity WHERE ref_date='2024-09-30' AND nome_perimetro='Individual Corporativo' AND segmento='ESTR' AND ambito='PM' AND entidade='00100' ) A | I9: =IF(VLOOKUP(B9,Instruções!$F$13:$J$17,5,0)="", "(SELECT "&VLOOKUP(B9,Instruções!$F$13:$J$17,4,0)&" as "&VLOOKUP(B9,Instruções!$F$13:$J$17,4,0)&"_"&$G$2&", "&E9&" as "&G9&" FROM "&D9&" WHERE "&Instruções!$D$21&") B ", "(SELECT "&VLOOKUP(B9,Instruções!$F$13:$J$17,4,0)&" as "&VLOOKUP(B9,Instruções!$F$13:$J$17,4,0)&"_"&$G$2&", "&VLOOKUP(B9,Instruções!$F$13:$J$17,5,0)&" as "&VLOOKUP(B9,Instruções!$F$13:$J$17,5,0)&"_"&$G$2&","&E9&" as "&G9&" FROM "&D9&" WHERE "&Instruções!$D$21&") B ") -> (SELECT entty_id as entty_id_, accntng_frmwrk_sl as accntng_frmwrk_sl_to_be FROM bu_loantape_work.lt003_entity WHERE ref_date='2024-09-30' AND nome_perimetro='Individual Corporativo' AND segmento='ESTR' AND ambito='PM' AND entidade='00100' ) B | J9: =+IF(VLOOKUP(B9,Instruções!$F$13:$J$17,5,0)="", "ON "&VLOOKUP(B9,Instruções!$F$13:$J$17,4,0)&"_"&$F$7&"="&VLOOKUP(B9,Instruções!$F$13:$J$17,4,0)&"_"&$G$7&" ", "ON "&VLOOKUP(B9,Instruções!$F$13:$J$17,4,0)&"_"&$F$7&"="&VLOOKUP(B9,Instruções!$F$13:$J$17,4,0)&"_"&$G$7&" AND "&VLOOKUP(B9,Instruções!$F$13:$J$17,5,0)&"_"&$F$7&"="&VLOOKUP(B9,Instruções!$F$13:$J$17,5,0)&"_"&$G$7&" ") -> ON entty_id_as_is=entty_id_to_be | K9: ="WHERE coalesce(cast("&F9&" AS string),'')<>coalesce(cast("&G9&" AS string),'') " -> WHERE coalesce(cast(accntng_frmwrk_sl_as_is AS string),'')<>coalesce(cast(accntng_frmwrk_sl_to_be AS string),'') | L9: ="SELECT count(*) AS NUM_REG_DIF FROM "&H9&" Inner join "&I9&J9&K9 -> SELECT count(*) AS NUM_REG_DIF FROM (SELECT entty_id as entty_id_, accntng_frmwrk_sl as accntng_frmwrk_sl_as_is FROM cd_loan_tapes_bce.lt003_entity WHERE ref_date='2024-09-30' AND nome_perimetro='Individual Corporativo' AND segmento='ESTR' AND ambito='PM' AND entidade='00100' ) A Inner join (SELECT entty_id as entty_id_, accntng_frmwrk_sl as accntng_frmwrk_sl_to_be FROM bu_loantape_work.lt003_entity WHERE ref_date='2024-09-30' AND nome_perimetro='Individual Corporativo' AND segmento='ESTR' AND ambito='PM' AND entidade='00100' ) B ON entty_id_as_is=entty_id_to_be WHERE coalesce(cast(accntng_frmwrk_sl_as_is AS string),'')<>coalesce(cast(accntng_frmwrk_sl_to_be AS string),'') | M9: Validação de campos | N9: ="SELECT 'Validação de campos' as tipologia_teste, '"&VLOOKUP(B9,Instruções!$F$13:$J$17,3,0)&"' AS TABELA, '"&E9&"' AS CAMPO, '"&Instruções!$D$15&"' as ref_date, coalesce(NUM_REG_DIF, 0) AS NUM_REG_DIF FROM ("&L9&") A " -> SELECT 'Validação de campos' as tipologia_teste, 'lt003_entity' AS TABELA, 'accntng_frmwrk_sl' AS CAMPO, '2024-09-30' as ref_date, coalesce(NUM_REG_DIF, 0) AS NUM_REG_DIF FROM (SELECT count(*) AS NUM_REG_DIF FROM (SELECT entty_id as entty_id_, accntng_frmwrk_sl as accntng_frmwrk_sl_as_is FROM cd_loan_tapes_bce.lt003_entity WHERE ref_date='2024-09-30' AND nome_perimetro='Individual Corporativo' AND segmento='ESTR' AND ambito='PM' AND entidade='00100' ) A Inner join (SELECT entty_id as entty_id_, accntng_frmwrk_sl as accntng_frmwrk_sl_to_be FROM bu_loantape_work.lt003_entity WHERE ref_date='2024-09-30' AND nome_perimetro='Individual Corporativo' AND segmento='ESTR' AND ambito='PM' AND entidade='00100' ) B ON entty_id_as_is=entty_id_to_be WHERE coalesce(cast(accntng_frmwrk_sl_as_is AS string),'')<>coalesce(cast(accntng_frmwrk_sl_to_be AS string),'') ) A | O9: =IF(O10="",N9,N9&$O$8) -> SELECT 'Validação de campos' as tipologia_teste, 'lt003_entity' AS TABELA, 'accntng_frmwrk_sl' AS CAMPO, '2024-09-30' as ref_date, coalesce(NUM_REG_DIF, 0) AS NUM_REG_DIF FROM (SELECT count(*) AS NUM_REG_DIF FROM (SELECT entty_id as entty_id_, accntng_frmwrk_sl as accntng_frmwrk_sl_as_is FROM cd_loan_tapes_bce.lt003_entity WHERE ref_date='2024-09-30' AND nome_perimetro='Individual Corporativo' AND segmento='ESTR' AND ambito='PM' AND entidade='00100' ) A Inner join (SELECT entty_id as entty_id_, accntng_frmwrk_sl as accntng_frmwrk_sl_to_be FROM bu_loantape_work.lt003_entity WHERE ref_date='2024-09-30' AND nome_perimetro='Individual Corporativo' AND segmento='ESTR' AND ambito='PM' AND entidade='00100' ) B ON entty_id_as_is=entty_id_to_be WHERE coalesce(cast(accntng_frmwrk_sl_as_is AS string),'')<>coalesce(cast(accntng_frmwrk_sl_to_be AS string),'') ) A Union all | P9: 1
B10: ENTTY | C10: =_xlfn.CONCAT(Instruções!$D$13,".",VLOOKUP(B10,Instruções!$F$12:$H$17,2,0)) -> cd_loan_tapes_bce.lt003_entity | D10: =_xlfn.CONCAT(Instruções!$D$14,".",VLOOKUP(B10,Instruções!$F$12:$H$17,3,0)) -> bu_loantape_work.lt003_entity | E10: annl_trnvr_le | F10: =E10&"_"&$F$7 -> annl_trnvr_le_as_is | G10: =E10&"_"&$G$7 -> annl_trnvr_le_to_be | H10: =IF(VLOOKUP(B10,Instruções!$F$13:$J$17,5,0)="", "(SELECT "&VLOOKUP(B10,Instruções!$F$13:$J$17,4,0)&" as "&VLOOKUP(B10,Instruções!$F$13:$J$17,4,0)&"_"&$F$2&", "&E10&" as "&F10&" FROM "&C10&" WHERE "&Instruções!$D$20&") A ", "(SELECT "&VLOOKUP(B10,Instruções!$F$13:$J$17,4,0)&" as "&VLOOKUP(B10,Instruções!$F$13:$J$17,4,0)&"_"&$F$2&", "&VLOOKUP(B10,Instruções!$F$13:$J$17,5,0)&" as "&VLOOKUP(B10,Instruções!$F$13:$J$17,5,0)&"_"&$F$2&","&E10&" as "&F10&" FROM "&C10&" WHERE "&Instruções!$D$20&") A ") -> (SELECT entty_id as entty_id_, annl_trnvr_le as annl_trnvr_le_as_is FROM cd_loan_tapes_bce.lt003_entity WHERE ref_date='2024-09-30' AND nome_perimetro='Individual Corporativo' AND segmento='ESTR' AND ambito='PM' AND entidade='00100' ) A | I10: =IF(VLOOKUP(B10,Instruções!$F$13:$J$17,5,0)="", "(SELECT "&VLOOKUP(B10,Instruções!$F$13:$J$17,4,0)&" as "&VLOOKUP(B10,Instruções!$F$13:$J$17,4,0)&"_"&$G$2&", "&E10&" as "&G10&" FROM "&D10&" WHERE "&Instruções!$D$21&") B ", "(SELECT "&VLOOKUP(B10,Instruções!$F$13:$J$17,4,0)&" as "&VLOOKUP(B10,Instruções!$F$13:$J$17,4,0)&"_"&$G$2&", "&VLOOKUP(B10,Instruções!$F$13:$J$17,5,0)&" as "&VLOOKUP(B10,Instruções!$F$13:$J$17,5,0)&"_"&$G$2&","&E10&" as "&G10&" FROM "&D10&" WHERE "&Instruções!$D$21&") B ") -> (SELECT entty_id as entty_id_, annl_trnvr_le as annl_trnvr_le_to_be FROM bu_loantape_work.lt003_entity WHERE ref_date='2024-09-30' AND nome_perimetro='Individual Corporativo' AND segmento='ESTR' AND ambito='PM' AND entidade='00100' ) B | J10: =+IF(VLOOKUP(B10,Instruções!$F$13:$J$17,5,0)="", "ON "&VLOOKUP(B10,Instruções!$F$13:$J$17,4,0)&"_"&$F$7&"="&VLOOKUP(B10,Instruções!$F$13:$J$17,4,0)&"_"&$G$7&" ", "ON "&VLOOKUP(B10,Instruções!$F$13:$J$17,4,0)&"_"&$F$7&"="&VLOOKUP(B10,Instruções!$F$13:$J$17,4,0)&"_"&$G$7&" AND "&VLOOKUP(B10,Instruções!$F$13:$J$17,5,0)&"_"&$F$7&"="&VLOOKUP(B10,Instruções!$F$13:$J$17,5,0)&"_"&$G$7&" ") -> ON entty_id_as_is=entty_id_to_be | K10: ="WHERE coalesce(cast("&F10&" AS string),'')<>coalesce(cast("&G10&" AS string),'') " -> WHERE coalesce(cast(annl_trnvr_le_as_is AS string),'')<>coalesce(cast(annl_trnvr_le_to_be AS string),'') | L10: ="SELECT count(*) AS NUM_REG_DIF FROM "&H10&" Inner join "&I10&J10&K10 -> SELECT count(*) AS NUM_REG_DIF FROM (SELECT entty_id as entty_id_, annl_trnvr_le as annl_trnvr_le_as_is FROM cd_loan_tapes_bce.lt003_entity WHERE ref_date='2024-09-30' AND nome_perimetro='Individual Corporativo' AND segmento='ESTR' AND ambito='PM' AND entidade='00100' ) A Inner join (SELECT entty_id as entty_id_, annl_trnvr_le as annl_trnvr_le_to_be FROM bu_loantape_work.lt003_entity WHERE ref_date='2024-09-30' AND nome_perimetro='Individual Corporativo' AND segmento='ESTR' AND ambito='PM' AND entidade='00100' ) B ON entty_id_as_is=entty_id_to_be WHERE coalesce(cast(annl_trnvr_le_as_is AS string),'')<>coalesce(cast(annl_trnvr_le_to_be AS string),'') | M10: Validação de campos | N10: ="SELECT 'Validação de campos' as tipologia_teste, '"&VLOOKUP(B10,Instruções!$F$13:$J$17,3,0)&"' AS TABELA, '"&E10&"' AS CAMPO, '"&Instruções!$D$15&"' as ref_date, coalesce(NUM_REG_DIF, 0) AS NUM_REG_DIF FROM ("&L10&") A " -> SELECT 'Validação de campos' as tipologia_teste, 'lt003_entity' AS TABELA, 'annl_trnvr_le' AS CAMPO, '2024-09-30' as ref_date, coalesce(NUM_REG_DIF, 0) AS NUM_REG_DIF FROM (SELECT count(*) AS NUM_REG_DIF FROM (SELECT entty_id as entty_id_, annl_trnvr_le as annl_trnvr_le_as_is FROM cd_loan_tapes_bce.lt003_entity WHERE ref_date='2024-09-30' AND nome_perimetro='Individual Corporativo' AND segmento='ESTR' AND ambito='PM' AND entidade='00100' ) A Inner join (SELECT entty_id as entty_id_, annl_trnvr_le as annl_trnvr_le_to_be FROM bu_loantape_work.lt003_entity WHERE ref_date='2024-09-30' AND nome_perimetro='Individual Corporativo' AND segmento='ESTR' AND ambito='PM' AND entidade='00100' ) B ON entty_id_as_is=entty_id_to_be WHERE coalesce(cast(annl_trnvr_le_as_is AS string),'')<>coalesce(cast(annl_trnvr_le_to_be AS string),'') ) A | O10: =IF(O11="",N10,N10&$O$8) -> SELECT 'Validação de campos' as tipologia_teste, 'lt003_entity' AS TABELA, 'annl_trnvr_le' AS CAMPO, '2024-09-30' as ref_date, coalesce(NUM_REG_DIF, 0) AS NUM_REG_DIF FROM (SELECT count(*) AS NUM_REG_DIF FROM (SELECT entty_id as entty_id_, annl_trnvr_le as annl_trnvr_le_as_is FROM cd_loan_tapes_bce.lt003_entity WHERE ref_date='2024-09-30' AND nome_perimetro='Individual Corporativo' AND segmento='ESTR' AND ambito='PM' AND entidade='00100' ) A Inner join (SELECT entty_id as entty_id_, annl_trnvr_le as annl_trnvr_le_to_be FROM bu_loantape_work.lt003_entity WHERE ref_date='2024-09-30' AND nome_perimetro='Individual Corporativo' AND segmento='ESTR' AND ambito='PM' AND entidade='00100' ) B ON entty_id_as_is=entty_id_to_be WHERE coalesce(cast(annl_trnvr_le_as_is AS string),'')<>coalesce(cast(annl_trnvr_le_to_be AS string),'') ) A Union all | P10: =+P9+1 -> 2
B11: ENTTY | C11: =_xlfn.CONCAT(Instruções!$D$13,".",VLOOKUP(B11,Instruções!$F$12:$H$17,2,0)) -> cd_loan_tapes_bce.lt003_entity | D11: =_xlfn.CONCAT(Instruções!$D$14,".",VLOOKUP(B11,Instruções!$F$12:$H$17,3,0)) -> bu_loantape_work.lt003_entity | E11: annl_trnvr_le_bdr | F11: =E11&"_"&$F$7 -> annl_trnvr_le_bdr_as_is | G11: =E11&"_"&$G$7 -> annl_trnvr_le_bdr_to_be | H11: =IF(VLOOKUP(B11,Instruções!$F$13:$J$17,5,0)="", "(SELECT "&VLOOKUP(B11,Instruções!$F$13:$J$17,4,0)&" as "&VLOOKUP(B11,Instruções!$F$13:$J$17,4,0)&"_"&$F$2&", "&E11&" as "&F11&" FROM "&C11&" WHERE "&Instruções!$D$20&") A ", "(SELECT "&VLOOKUP(B11,Instruções!$F$13:$J$17,4,0)&" as "&VLOOKUP(B11,Instruções!$F$13:$J$17,4,0)&"_"&$F$2&", "&VLOOKUP(B11,Instruções!$F$13:$J$17,5,0)&" as "&VLOOKUP(B11,Instruções!$F$13:$J$17,5,0)&"_"&$F$2&","&E11&" as "&F11&" FROM "&C11&" WHERE "&Instruções!$D$20&") A ") -> (SELECT entty_id as entty_id_, annl_trnvr_le_bdr as annl_trnvr_le_bdr_as_is FROM cd_loan_tapes_bce.lt003_entity WHERE ref_date='2024-09-30' AND nome_perimetro='Individual Corporativo' AND segmento='ESTR' AND ambito='PM' AND entidade='00100' ) A | I11: =IF(VLOOKUP(B11,Instruções!$F$13:$J$17,5,0)="", "(SELECT "&VLOOKUP(B11,Instruções!$F$13:$J$17,4,0)&" as "&VLOOKUP(B11,Instruções!$F$13:$J$17,4,0)&"_"&$G$2&", "&E11&" as "&G11&" FROM "&D11&" WHERE "&Instruções!$D$21&") B ", "(SELECT "&VLOOKUP(B11,Instruções!$F$13:$J$17,4,0)&" as "&VLOOKUP(B11,Instruções!$F$13:$J$17,4,0)&"_"&$G$2&", "&VLOOKUP(B11,Instruções!$F$13:$J$17,5,0)&" as "&VLOOKUP(B11,Instruções!$F$13:$J$17,5,0)&"_"&$G$2&","&E11&" as "&G11&" FROM "&D11&" WHERE "&Instruções!$D$21&") B ") -> (SELECT entty_id as entty_id_, annl_trnvr_le_bdr as annl_trnvr_le_bdr_to_be FROM bu_loantape_work.lt003_entity WHERE ref_date='2024-09-30' AND nome_perimetro='Individual Corporativo' AND segmento='ESTR' AND ambito='PM' AND entidade='00100' ) B | J11: =+IF(VLOOKUP(B11,Instruções!$F$13:$J$17,5,0)="", "ON "&VLOOKUP(B11,Instruções!$F$13:$J$17,4,0)&"_"&$F$7&"="&VLOOKUP(B11,Instruções!$F$13:$J$17,4,0)&"_"&$G$7&" ", "ON "&VLOOKUP(B11,Instruções!$F$13:$J$17,4,0)&"_"&$F$7&"="&VLOOKUP(B11,Instruções!$F$13:$J$17,4,0)&"_"&$G$7&" AND "&VLOOKUP(B11,Instruções!$F$13:$J$17,5,0)&"_"&$F$7&"="&VLOOKUP(B11,Instruções!$F$13:$J$17,5,0)&"_"&$G$7&" ") -> ON entty_id_as_is=entty_id_to_be | K11: ="WHERE coalesce(cast("&F11&" AS string),'')<>coalesce(cast("&G11&" AS string),'') " -> WHERE coalesce(cast(annl_trnvr_le_bdr_as_is AS string),'')<>coalesce(cast(annl_trnvr_le_bdr_to_be AS string),'') | L11: ="SELECT count(*) AS NUM_REG_DIF FROM "&H11&" Inner join "&I11&J11&K11 -> SELECT count(*) AS NUM_REG_DIF FROM (SELECT entty_id as entty_id_, annl_trnvr_le_bdr as annl_trnvr_le_bdr_as_is FROM cd_loan_tapes_bce.lt003_entity WHERE ref_date='2024-09-30' AND nome_perimetro='Individual Corporativo' AND segmento='ESTR' AND ambito='PM' AND entidade='00100' ) A Inner join (SELECT entty_id as entty_id_, annl_trnvr_le_bdr as annl_trnvr_le_bdr_to_be FROM bu_loantape_work.lt003_entity WHERE ref_date='2024-09-30' AND nome_perimetro='Individual Corporativo' AND segmento='ESTR' AND ambito='PM' AND entidade='00100' ) B ON entty_id_as_is=entty_id_to_be WHERE coalesce(cast(annl_trnvr_le_bdr_as_is AS string),'')<>coalesce(cast(annl_trnvr_le_bdr_to_be AS string),'') | M11: Validação de campos | N11: ="SELECT 'Validação de campos' as tipologia_teste, '"&VLOOKUP(B11,Instruções!$F$13:$J$17,3,0)&"' AS TABELA, '"&E11&"' AS CAMPO, '"&Instruções!$D$15&"' as ref_date, coalesce(NUM_REG_DIF, 0) AS NUM_REG_DIF FROM ("&L11&") A " -> SELECT 'Validação de campos' as tipologia_teste, 'lt003_entity' AS TABELA, 'annl_trnvr_le_bdr' AS CAMPO, '2024-09-30' as ref_date, coalesce(NUM_REG_DIF, 0) AS NUM_REG_DIF FROM (SELECT count(*) AS NUM_REG_DIF FROM (SELECT entty_id as entty_id_, annl_trnvr_le_bdr as annl_trnvr_le_bdr_as_is FROM cd_loan_tapes_bce.lt003_entity WHERE ref_date='2024-09-30' AND nome_perimetro='Individual Corporativo' AND segmento='ESTR' AND ambito='PM' AND entidade='00100' ) A Inner join (SELECT entty_id as entty_id_, annl_trnvr_le_bdr as annl_trnvr_le_bdr_to_be FROM bu_loantape_work.lt003_entity WHERE ref_date='2024-09-30' AND nome_perimetro='Individual Corporativo' AND segmento='ESTR' AND ambito='PM' AND entidade='00100' ) B ON entty_id_as_is=entty_id_to_be WHERE coalesce(cast(annl_trnvr_le_bdr_as_is AS string),'')<>coalesce(cast(annl_trnvr_le_bdr_to_be AS string),'') ) A | O11: =IF(O12="",N11,N11&$O$8) -> SELECT 'Validação de campos' as tipologia_teste, 'lt003_entity' AS TABELA, 'annl_trnvr_le_bdr' AS CAMPO, '2024-09-30' as ref_date, coalesce(NUM_REG_DIF, 0) AS NUM_REG_DIF FROM (SELECT count(*) AS NUM_REG_DIF FROM (SELECT entty_id as entty_id_, annl_trnvr_le_bdr as annl_trnvr_le_bdr_as_is FROM cd_loan_tapes_bce.lt003_entity WHERE ref_date='2024-09-30' AND nome_perimetro='Individual Corporativo' AND segmento='ESTR' AND ambito='PM' AND entidade='00100' ) A Inner join (SELECT entty_id as entty_id_, annl_trnvr_le_bdr as annl_trnvr_le_bdr_to_be FROM bu_loantape_work.lt003_entity WHERE ref_date='2024-09-30' AND nome_perimetro='Individual Corporativo' AND segmento='ESTR' AND ambito='PM' AND entidade='00100' ) B ON entty_id_as_is=entty_id_to_be WHERE coalesce(cast(annl_trnvr_le_bdr_as_is AS string),'')<>coalesce(cast(annl_trnvr_le_bdr_to_be AS string),'') ) A Union all | P11: =+P10+1 -> 3
B12: ENTTY | C12: =_xlfn.CONCAT(Instruções!$D$13,".",VLOOKUP(B12,Instruções!$F$12:$H$17,2,0)) -> cd_loan_tapes_bce.lt003_entity | D12: =_xlfn.CONCAT(Instruções!$D$14,".",VLOOKUP(B12,Instruções!$F$12:$H$17,3,0)) -> bu_loantape_work.lt003_entity | E12: annl_trnvr_prvs | F12: =E12&"_"&$F$7 -> annl_trnvr_prvs_as_is | G12: =E12&"_"&$G$7 -> annl_trnvr_prvs_to_be | H12: =IF(VLOOKUP(B12,Instruções!$F$13:$J$17,5,0)="", "(SELECT "&VLOOKUP(B12,Instruções!$F$13:$J$17,4,0)&" as "&VLOOKUP(B12,Instruções!$F$13:$J$17,4,0)&"_"&$F$2&", "&E12&" as "&F12&" FROM "&C12&" WHERE "&Instruções!$D$20&") A ", "(SELECT "&VLOOKUP(B12,Instruções!$F$13:$J$17,4,0)&" as "&VLOOKUP(B12,Instruções!$F$13:$J$17,4,0)&"_"&$F$2&", "&VLOOKUP(B12,Instruções!$F$13:$J$17,5,0)&" as "&VLOOKUP(B12,Instruções!$F$13:$J$17,5,0)&"_"&$F$2&","&E12&" as "&F12&" FROM "&C12&" WHERE "&Instruções!$D$20&") A ") -> (SELECT entty_id as entty_id_, annl_trnvr_prvs as annl_trnvr_prvs_as_is FROM cd_loan_tapes_bce.lt003_entity WHERE ref_date='2024-09-30' AND nome_perimetro='Individual Corporativo' AND segmento='ESTR' AND ambito='PM' AND entidade='00100' ) A | I12: =IF(VLOOKUP(B12,Instruções!$F$13:$J$17,5,0)="", "(SELECT "&VLOOKUP(B12,Instruções!$F$13:$J$17,4,0)&" as "&VLOOKUP(B12,Instruções!$F$13:$J$17,4,0)&"_"&$G$2&", "&E12&" as "&G12&" FROM "&D12&" WHERE "&Instruções!$D$21&") B ", "(SELECT "&VLOOKUP(B12,Instruções!$F$13:$J$17,4,0)&" as "&VLOOKUP(B12,Instruções!$F$13:$J$17,4,0)&"_"&$G$2&", "&VLOOKUP(B12,Instruções!$F$13:$J$17,5,0)&" as "&VLOOKUP(B12,Instruções!$F$13:$J$17,5,0)&"_"&$G$2&","&E12&" as "&G12&" FROM "&D12&" WHERE "&Instruções!$D$21&") B ") -> (SELECT entty_id as entty_id_, annl_trnvr_prvs as annl_trnvr_prvs_to_be FROM bu_loantape_work.lt003_entity WHERE ref_date='2024-09-30' AND nome_perimetro='Individual Corporativo' AND segmento='ESTR' AND ambito='PM' AND entidade='00100' ) B | J12: =+IF(VLOOKUP(B12,Instruções!$F$13:$J$17,5,0)="", "ON "&VLOOKUP(B12,Instruções!$F$13:$J$17,4,0)&"_"&$F$7&"="&VLOOKUP(B12,Instruções!$F$13:$J$17,4,0)&"_"&$G$7&" ", "ON "&VLOOKUP(B12,Instruções!$F$13:$J$17,4,0)&"_"&$F$7&"="&VLOOKUP(B12,Instruções!$F$13:$J$17,4,0)&"_"&$G$7&" AND "&VLOOKUP(B12,Instruções!$F$13:$J$17,5,0)&"_"&$F$7&"="&VLOOKUP(B12,Instruções!$F$13:$J$17,5,0)&"_"&$G$7&" ") -> ON entty_id_as_is=entty_id_to_be | K12: ="WHERE coalesce(cast("&F12&" AS string),'')<>coalesce(cast("&G12&" AS string),'') " -> WHERE coalesce(cast(annl_trnvr_prvs_as_is AS string),'')<>coalesce(cast(annl_trnvr_prvs_to_be AS string),'') | L12: ="SELECT count(*) AS NUM_REG_DIF FROM "&H12&" Inner join "&I12&J12&K12 -> SELECT count(*) AS NUM_REG_DIF FROM (SELECT entty_id as entty_id_, annl_trnvr_prvs as annl_trnvr_prvs_as_is FROM cd_loan_tapes_bce.lt003_entity WHERE ref_date='2024-09-30' AND nome_perimetro='Individual Corporativo' AND segmento='ESTR' AND ambito='PM' AND entidade='00100' ) A Inner join (SELECT entty_id as entty_id_, annl_trnvr_prvs as annl_trnvr_prvs_to_be FROM bu_loantape_work.lt003_entity WHERE ref_date='2024-09-30' AND nome_perimetro='Individual Corporativo' AND segmento='ESTR' AND ambito='PM' AND entidade='00100' ) B ON entty_id_as_is=entty_id_to_be WHERE coalesce(cast(annl_trnvr_prvs_as_is AS string),'')<>coalesce(cast(annl_trnvr_prvs_to_be AS string),'') | M12: Validação de campos | N12: ="SELECT 'Validação de campos' as tipologia_teste, '"&VLOOKUP(B12,Instruções!$F$13:$J$17,3,0)&"' AS TABELA, '"&E12&"' AS CAMPO, '"&Instruções!$D$15&"' as ref_date, coalesce(NUM_REG_DIF, 0) AS NUM_REG_DIF FROM ("&L12&") A " -> SELECT 'Validação de campos' as tipologia_teste, 'lt003_entity' AS TABELA, 'annl_trnvr_prvs' AS CAMPO, '2024-09-30' as ref_date, coalesce(NUM_REG_DIF, 0) AS NUM_REG_DIF FROM (SELECT count(*) AS NUM_REG_DIF FROM (SELECT entty_id as entty_id_, annl_trnvr_prvs as annl_trnvr_prvs_as_is FROM cd_loan_tapes_bce.lt003_entity WHERE ref_date='2024-09-30' AND nome_perimetro='Individual Corporativo' AND segmento='ESTR' AND ambito='PM' AND entidade='00100' ) A Inner join (SELECT entty_id as entty_id_, annl_trnvr_prvs as annl_trnvr_prvs_to_be FROM bu_loantape_work.lt003_entity WHERE ref_date='2024-09-30' AND nome_perimetro='Individual Corporativo' AND segmento='ESTR' AND ambito='PM' AND entidade='00100' ) B ON entty_id_as_is=entty_id_to_be WHERE coalesce(cast(annl_trnvr_prvs_as_is AS string),'')<>coalesce(cast(annl_trnvr_prvs_to_be AS string),'') ) A | O12: =IF(O13="",N12,N12&$O$8) -> SELECT 'Validação de campos' as tipologia_teste, 'lt003_entity' AS TABELA, 'annl_trnvr_prvs' AS CAMPO, '2024-09-30' as ref_date, coalesce(NUM_REG_DIF, 0) AS NUM_REG_DIF FROM (SELECT count(*) AS NUM_REG_DIF FROM (SELECT entty_id as entty_id_, annl_trnvr_prvs as annl_trnvr_prvs_as_is FROM cd_loan_tapes_bce.lt003_entity WHERE ref_date='2024-09-30' AND nome_perimetro='Individual Corporativo' AND segmento='ESTR' AND ambito='PM' AND entidade='00100' ) A Inner join (SELECT entty_id as entty_id_, annl_trnvr_prvs as annl_trnvr_prvs_to_be FROM bu_loantape_work.lt003_entity WHERE ref_date='2024-09-30' AND nome_perimetro='Individual Corporativo' AND segmento='ESTR' AND ambito='PM' AND entidade='00100' ) B ON entty_id_as_is=entty_id_to_be WHERE coalesce(cast(annl_trnvr_prvs_as_is AS string),'')<>coalesce(cast(annl_trnvr_prvs_to_be AS string),'') ) A Union all | P12: =+P11+1 -> 4
B13: ENTTY | C13: =_xlfn.CONCAT(Instruções!$D$13,".",VLOOKUP(B13,Instruções!$F$12:$H$17,2,0)) -> cd_loan_tapes_bce.lt003_entity | D13: =_xlfn.CONCAT(Instruções!$D$14,".",VLOOKUP(B13,Instruções!$F$12:$H$17,3,0)) -> bu_loantape_work.lt003_entity | E13: annl_trnvr_prvs_bdr | F13: =E13&"_"&$F$7 -> annl_trnvr_prvs_bdr_as_is | G13: =E13&"_"&$G$7 -> annl_trnvr_prvs_bdr_to_be | H13: =IF(VLOOKUP(B13,Instruções!$F$13:$J$17,5,0)="", "(SELECT "&VLOOKUP(B13,Instruções!$F$13:$J$17,4,0)&" as "&VLOOKUP(B13,Instruções!$F$13:$J$17,4,0)&"_"&$F$2&", "&E13&" as "&F13&" FROM "&C13&" WHERE "&Instruções!$D$20&") A ", "(SELECT "&VLOOKUP(B13,Instruções!$F$13:$J$17,4,0)&" as "&VLOOKUP(B13,Instruções!$F$13:$J$17,4,0)&"_"&$F$2&", "&VLOOKUP(B13,Instruções!$F$13:$J$17,5,0)&" as "&VLOOKUP(B13,Instruções!$F$13:$J$17,5,0)&"_"&$F$2&","&E13&" as "&F13&" FROM "&C13&" WHERE "&Instruções!$D$20&") A ") -> (SELECT entty_id as entty_id_, annl_trnvr_prvs_bdr as annl_trnvr_prvs_bdr_as_is FROM cd_loan_tapes_bce.lt003_entity WHERE ref_date='2024-09-30' AND nome_perimetro='Individual Corporativo' AND segmento='ESTR' AND ambito='PM' AND entidade='00100' ) A | I13: =IF(VLOOKUP(B13,Instruções!$F$13:$J$17,5,0)="", "(SELECT "&VLOOKUP(B13,Instruções!$F$13:$J$17,4,0)&" as "&VLOOKUP(B13,Instruções!$F$13:$J$17,4,0)&"_"&$G$2&", "&E13&" as "&G13&" FROM "&D13&" WHERE "&Instruções!$D$21&") B ", "(SELECT "&VLOOKUP(B13,Instruções!$F$13:$J$17,4,0)&" as "&VLOOKUP(B13,Instruções!$F$13:$J$17,4,0)&"_"&$G$2&", "&VLOOKUP(B13,Instruções!$F$13:$J$17,5,0)&" as "&VLOOKUP(B13,Instruções!$F$13:$J$17,5,0)&"_"&$G$2&","&E13&" as "&G13&" FROM "&D13&" WHERE "&Instruções!$D$21&") B ") -> (SELECT entty_id as entty_id_, annl_trnvr_prvs_bdr as annl_trnvr_prvs_bdr_to_be FROM bu_loantape_work.lt003_entity WHERE ref_date='2024-09-30' AND nome_perimetro='Individual Corporativo' AND segmento='ESTR' AND ambito='PM' AND entidade='00100' ) B | J13: =+IF(VLOOKUP(B13,Instruções!$F$13:$J$17,5,0)="", "ON "&VLOOKUP(B13,Instruções!$F$13:$J$17,4,0)&"_"&$F$7&"="&VLOOKUP(B13,Instruções!$F$13:$J$17,4,0)&"_"&$G$7&" ", "ON "&VLOOKUP(B13,Instruções!$F$13:$J$17,4,0)&"_"&$F$7&"="&VLOOKUP(B13,Instruções!$F$13:$J$17,4,0)&"_"&$G$7&" AND "&VLOOKUP(B13,Instruções!$F$13:$J$17,5,0)&"_"&$F$7&"="&VLOOKUP(B13,Instruções!$F$13:$J$17,5,0)&"_"&$G$7&" ") -> ON entty_id_as_is=entty_id_to_be | K13: ="WHERE coalesce(cast("&F13&" AS string),'')<>coalesce(cast("&G13&" AS string),'') " -> WHERE coalesce(cast(annl_trnvr_prvs_bdr_as_is AS string),'')<>coalesce(cast(annl_trnvr_prvs_bdr_to_be AS string),'') | L13: ="SELECT count(*) AS NUM_REG_DIF FROM "&H13&" Inner join "&I13&J13&K13 -> SELECT count(*) AS NUM_REG_DIF FROM (SELECT entty_id as entty_id_, annl_trnvr_prvs_bdr as annl_trnvr_prvs_bdr_as_is FROM cd_loan_tapes_bce.lt003_entity WHERE ref_date='2024-09-30' AND nome_perimetro='Individual Corporativo' AND segmento='ESTR' AND ambito='PM' AND entidade='00100' ) A Inner join (SELECT entty_id as entty_id_, annl_trnvr_prvs_bdr as annl_trnvr_prvs_bdr_to_be FROM bu_loantape_work.lt003_entity WHERE ref_date='2024-09-30' AND nome_perimetro='Individual Corporativo' AND segmento='ESTR' AND ambito='PM' AND entidade='00100' ) B ON entty_id_as_is=entty_id_to_be WHERE coalesce(cast(annl_trnvr_prvs_bdr_as_is AS string),'')<>coalesce(cast(annl_trnvr_prvs_bdr_to_be AS string),'') | M13: Validação de campos | N13: ="SELECT 'Validação de campos' as tipologia_teste, '"&VLOOKUP(B13,Instruções!$F$13:$J$17,3,0)&"' AS TABELA, '"&E13&"' AS CAMPO, '"&Instruções!$D$15&"' as ref_date, coalesce(NUM_REG_DIF, 0) AS NUM_REG_DIF FROM ("&L13&") A " -> SELECT 'Validação de campos' as tipologia_teste, 'lt003_entity' AS TABELA, 'annl_trnvr_prvs_bdr' AS CAMPO, '2024-09-30' as ref_date, coalesce(NUM_REG_DIF, 0) AS NUM_REG_DIF FROM (SELECT count(*) AS NUM_REG_DIF FROM (SELECT entty_id as entty_id_, annl_trnvr_prvs_bdr as annl_trnvr_prvs_bdr_as_is FROM cd_loan_tapes_bce.lt003_entity WHERE ref_date='2024-09-30' AND nome_perimetro='Individual Corporativo' AND segmento='ESTR' AND ambito='PM' AND entidade='00100' ) A Inner join (SELECT entty_id as entty_id_, annl_trnvr_prvs_bdr as annl_trnvr_prvs_bdr_to_be FROM bu_loantape_work.lt003_entity WHERE ref_date='2024-09-30' AND nome_perimetro='Individual Corporativo' AND segmento='ESTR' AND ambito='PM' AND entidade='00100' ) B ON entty_id_as_is=entty_id_to_be WHERE coalesce(cast(annl_trnvr_prvs_bdr_as_is AS string),'')<>coalesce(cast(annl_trnvr_prvs_bdr_to_be AS string),'') ) A | O13: =IF(O14="",N13,N13&$O$8) -> SELECT 'Validação de campos' as tipologia_teste, 'lt003_entity' AS TABELA, 'annl_trnvr_prvs_bdr' AS CAMPO, '2024-09-30' as ref_date, coalesce(NUM_REG_DIF, 0) AS NUM_REG_DIF FROM (SELECT count(*) AS NUM_REG_DIF FROM (SELECT entty_id as entty_id_, annl_trnvr_prvs_bdr as annl_trnvr_prvs_bdr_as_is FROM cd_loan_tapes_bce.lt003_entity WHERE ref_date='2024-09-30' AND nome_perimetro='Individual Corporativo' AND segmento='ESTR' AND ambito='PM' AND entidade='00100' ) A Inner join (SELECT entty_id as entty_id_, annl_trnvr_prvs_bdr as annl_trnvr_prvs_bdr_to_be FROM bu_loantape_work.lt003_entity WHERE ref_date='2024-09-30' AND nome_perimetro='Individual Corporativo' AND segmento='ESTR' AND ambito='PM' AND entidade='00100' ) B ON entty_id_as_is=entty_id_to_be WHERE coalesce(cast(annl_trnvr_prvs_bdr_as_is AS string),'')<>coalesce(cast(annl_trnvr_prvs_bdr_to_be AS string),'') ) A Union all | P13: =+P12+1 -> 5
B14: ENTTY | C14: =_xlfn.CONCAT(Instruções!$D$13,".",VLOOKUP(B14,Instruções!$F$12:$H$17,2,0)) -> cd_loan_tapes_bce.lt003_entity | D14: =_xlfn.CONCAT(Instruções!$D$14,".",VLOOKUP(B14,Instruções!$F$12:$H$17,3,0)) -> bu_loantape_work.lt003_entity | E14: capex | F14: =E14&"_"&$F$7 -> capex_as_is | G14: =E14&"_"&$G$7 -> capex_to_be | H14: =IF(VLOOKUP(B14,Instruções!$F$13:$J$17,5,0)="", "(SELECT "&VLOOKUP(B14,Instruções!$F$13:$J$17,4,0)&" as "&VLOOKUP(B14,Instruções!$F$13:$J$17,4,0)&"_"&$F$2&", "&E14&" as "&F14&" FROM "&C14&" WHERE "&Instruções!$D$20&") A ", "(SELECT "&VLOOKUP(B14,Instruções!$F$13:$J$17,4,0)&" as "&VLOOKUP(B14,Instruções!$F$13:$J$17,4,0)&"_"&$F$2&", "&VLOOKUP(B14,Instruções!$F$13:$J$17,5,0)&" as "&VLOOKUP(B14,Instruções!$F$13:$J$17,5,0)&"_"&$F$2&","&E14&" as "&F14&" FROM "&C14&" WHERE "&Instruções!$D$20&") A ") -> (SELECT entty_id as entty_id_, capex as capex_as_is FROM cd_loan_tapes_bce.lt003_entity WHERE ref_date='2024-09-30' AND nome_perimetro='Individual Corporativo' AND segmento='ESTR' AND ambito='PM' AND entidade='00100' ) A | I14: =IF(VLOOKUP(B14,Instruções!$F$13:$J$17,5,0)="", "(SELECT "&VLOOKUP(B14,Instruções!$F$13:$J$17,4,0)&" as "&VLOOKUP(B14,Instruções!$F$13:$J$17,4,0)&"_"&$G$2&", "&E14&" as "&G14&" FROM "&D14&" WHERE "&Instruções!$D$21&") B ", "(SELECT "&VLOOKUP(B14,Instruções!$F$13:$J$17,4,0)&" as "&VLOOKUP(B14,Instruções!$F$13:$J$17,4,0)&"_"&$G$2&", "&VLOOKUP(B14,Instruções!$F$13:$J$17,5,0)&" as "&VLOOKUP(B14,Instruções!$F$13:$J$17,5,0)&"_"&$G$2&","&E14&" as "&G14&" FROM "&D14&" WHERE "&Instruções!$D$21&") B ") -> (SELECT entty_id as entty_id_, capex as capex_to_be FROM bu_loantape_work.lt003_entity WHERE ref_date='2024-09-30' AND nome_perimetro='Individual Corporativo' AND segmento='ESTR' AND ambito='PM' AND entidade='00100' ) B | J14: =+IF(VLOOKUP(B14,Instruções!$F$13:$J$17,5,0)="", "ON "&VLOOKUP(B14,Instruções!$F$13:$J$17,4,0)&"_"&$F$7&"="&VLOOKUP(B14,Instruções!$F$13:$J$17,4,0)&"_"&$G$7&" ", "ON "&VLOOKUP(B14,Instruções!$F$13:$J$17,4,0)&"_"&$F$7&"="&VLOOKUP(B14,Instruções!$F$13:$J$17,4,0)&"_"&$G$7&" AND "&VLOOKUP(B14,Instruções!$F$13:$J$17,5,0)&"_"&$F$7&"="&VLOOKUP(B14,Instruções!$F$13:$J$17,5,0)&"_"&$G$7&" ") -> ON entty_id_as_is=entty_id_to_be | K14: ="WHERE coalesce(cast("&F14&" AS string),'')<>coalesce(cast("&G14&" AS string),'') " -> WHERE coalesce(cast(capex_as_is AS string),'')<>coalesce(cast(capex_to_be AS string),'') | L14: ="SELECT count(*) AS NUM_REG_DIF FROM "&H14&" Inner join "&I14&J14&K14 -> SELECT count(*) AS NUM_REG_DIF FROM (SELECT entty_id as entty_id_, capex as capex_as_is FROM cd_loan_tapes_bce.lt003_entity WHERE ref_date='2024-09-30' AND nome_perimetro='Individual Corporativo' AND segmento='ESTR' AND ambito='PM' AND entidade='00100' ) A Inner join (SELECT entty_id as entty_id_, capex as capex_to_be FROM bu_loantape_work.lt003_entity WHERE ref_date='2024-09-30' AND nome_perimetro='Individual Corporativo' AND segmento='ESTR' AND ambito='PM' AND entidade='00100' ) B ON entty_id_as_is=entty_id_to_be WHERE coalesce(cast(capex_as_is AS string),'')<>coalesce(cast(capex_to_be AS string),'') | M14: Validação de campos | N14: ="SELECT 'Validação de campos' as tipologia_teste, '"&VLOOKUP(B14,Instruções!$F$13:$J$17,3,0)&"' AS TABELA, '"&E14&"' AS CAMPO, '"&Instruções!$D$15&"' as ref_date, coalesce(NUM_REG_DIF, 0) AS NUM_REG_DIF FROM ("&L14&") A " -> SELECT 'Validação de campos' as tipologia_teste, 'lt003_entity' AS TABELA, 'capex' AS CAMPO, '2024-09-30' as ref_date, coalesce(NUM_REG_DIF, 0) AS NUM_REG_DIF FROM (SELECT count(*) AS NUM_REG_DIF FROM (SELECT entty_id as entty_id_, capex as capex_as_is FROM cd_loan_tapes_bce.lt003_entity WHERE ref_date='2024-09-30' AND nome_perimetro='Individual Corporativo' AND segmento='ESTR' AND ambito='PM' AND entidade='00100' ) A Inner join (SELECT entty_id as entty_id_, capex as capex_to_be FROM bu_loantape_work.lt003_entity WHERE ref_date='2024-09-30' AND nome_perimetro='Individual Corporativo' AND segmento='ESTR' AND ambito='PM' AND entidade='00100' ) B ON entty_id_as_is=entty_id_to_be WHERE coalesce(cast(capex_as_is AS string),'')<>coalesce(cast(capex_to_be AS string),'') ) A | O14: =IF(O15="",N14,N14&$O$8) -> SELECT 'Validação de campos' as tipologia_teste, 'lt003_entity' AS TABELA, 'capex' AS CAMPO, '2024-09-30' as ref_date, coalesce(NUM_REG_DIF, 0) AS NUM_REG_DIF FROM (SELECT count(*) AS NUM_REG_DIF FROM (SELECT entty_id as entty_id_, capex as capex_as_is FROM cd_loan_tapes_bce.lt003_entity WHERE ref_date='2024-09-30' AND nome_perimetro='Individual Corporativo' AND segmento='ESTR' AND ambito='PM' AND entidade='00100' ) A Inner join (SELECT entty_id as entty_id_, capex as capex_to_be FROM bu_loantape_work.lt003_entity WHERE ref_date='2024-09-30' AND nome_perimetro='Individual Corporativo' AND segmento='ESTR' AND ambito='PM' AND entidade='00100' ) B ON entty_id_as_is=entty_id_to_be WHERE coalesce(cast(capex_as_is AS string),'')<>coalesce(cast(capex_to_be AS string),'') ) A Union all | P14: =+P13+1 -> 6
B15: ENTTY | C15: =_xlfn.CONCAT(Instruções!$D$13,".",VLOOKUP(B15,Instruções!$F$12:$H$17,2,0)) -> cd_loan_tapes_bce.lt003_entity | D15: =_xlfn.CONCAT(Instruções!$D$14,".",VLOOKUP(B15,Instruções!$F$12:$H$17,3,0)) -> bu_loantape_work.lt003_entity | E15: capex_prvs | F15: =E15&"_"&$F$7 -> capex_prvs_as_is | G15: =E15&"_"&$G$7 -> capex_prvs_to_be | H15: =IF(VLOOKUP(B15,Instruções!$F$13:$J$17,5,0)="", "(SELECT "&VLOOKUP(B15,Instruções!$F$13:$J$17,4,0)&" as "&VLOOKUP(B15,Instruções!$F$13:$J$17,4,0)&"_"&$F$2&", "&E15&" as "&F15&" FROM "&C15&" WHERE "&Instruções!$D$20&") A ", "(SELECT "&VLOOKUP(B15,Instruções!$F$13:$J$17,4,0)&" as "&VLOOKUP(B15,Instruções!$F$13:$J$17,4,0)&"_"&$F$2&", "&VLOOKUP(B15,Instruções!$F$13:$J$17,5,0)&" as "&VLOOKUP(B15,Instruções!$F$13:$J$17,5,0)&"_"&$F$2&","&E15&" as "&F15&" FROM "&C15&" WHERE "&Instruções!$D$20&") A ") -> (SELECT entty_id as entty_id_, capex_prvs as capex_prvs_as_is FROM cd_loan_tapes_bce.lt003_entity WHERE ref_date='2024-09-30' AND nome_perimetro='Individual Corporativo' AND segmento='ESTR' AND ambito='PM' AND entidade='00100' ) A | I15: =IF(VLOOKUP(B15,Instruções!$F$13:$J$17,5,0)="", "(SELECT "&VLOOKUP(B15,Instruções!$F$13:$J$17,4,0)&" as "&VLOOKUP(B15,Instruções!$F$13:$J$17,4,0)&"_"&$G$2&", "&E15&" as "&G15&" FROM "&D15&" WHERE "&Instruções!$D$21&") B ", "(SELECT "&VLOOKUP(B15,Instruções!$F$13:$J$17,4,0)&" as "&VLOOKUP(B15,Instruções!$F$13:$J$17,4,0)&"_"&$G$2&", "&VLOOKUP(B15,Instruções!$F$13:$J$17,5,0)&" as "&VLOOKUP(B15,Instruções!$F$13:$J$17,5,0)&"_"&$G$2&","&E15&" as "&G15&" FROM "&D15&" WHERE "&Instruções!$D$21&") B ") -> (SELECT entty_id as entty_id_, capex_prvs as capex_prvs_to_be FROM bu_loantape_work.lt003_entity WHERE ref_date='2024-09-30' AND nome_perimetro='Individual Corporativo' AND segmento='ESTR' AND ambito='PM' AND entidade='00100' ) B | J15: =+IF(VLOOKUP(B15,Instruções!$F$13:$J$17,5,0)="", "ON "&VLOOKUP(B15,Instruções!$F$13:$J$17,4,0)&"_"&$F$7&"="&VLOOKUP(B15,Instruções!$F$13:$J$17,4,0)&"_"&$G$7&" ", "ON "&VLOOKUP(B15,Instruções!$F$13:$J$17,4,0)&"_"&$F$7&"="&VLOOKUP(B15,Instruções!$F$13:$J$17,4,0)&"_"&$G$7&" AND "&VLOOKUP(B15,Instruções!$F$13:$J$17,5,0)&"_"&$F$7&"="&VLOOKUP(B15,Instruções!$F$13:$J$17,5,0)&"_"&$G$7&" ") -> ON entty_id_as_is=entty_id_to_be | K15: ="WHERE coalesce(cast("&F15&" AS string),'')<>coalesce(cast("&G15&" AS string),'') " -> WHERE coalesce(cast(capex_prvs_as_is AS string),'')<>coalesce(cast(capex_prvs_to_be AS string),'') | L15: ="SELECT count(*) AS NUM_REG_DIF FROM "&H15&" Inner join "&I15&J15&K15 -> SELECT count(*) AS NUM_REG_DIF FROM (SELECT entty_id as entty_id_, capex_prvs as capex_prvs_as_is FROM cd_loan_tapes_bce.lt003_entity WHERE ref_date='2024-09-30' AND nome_perimetro='Individual Corporativo' AND segmento='ESTR' AND ambito='PM' AND entidade='00100' ) A Inner join (SELECT entty_id as entty_id_, capex_prvs as capex_prvs_to_be FROM bu_loantape_work.lt003_entity WHERE ref_date='2024-09-30' AND nome_perimetro='Individual Corporativo' AND segmento='ESTR' AND ambito='PM' AND entidade='00100' ) B ON entty_id_as_is=entty_id_to_be WHERE coalesce(cast(capex_prvs_as_is AS string),'')<>coalesce(cast(capex_prvs_to_be AS string),'') | M15: Validação de campos | N15: ="SELECT 'Validação de campos' as tipologia_teste, '"&VLOOKUP(B15,Instruções!$F$13:$J$17,3,0)&"' AS TABELA, '"&E15&"' AS CAMPO, '"&Instruções!$D$15&"' as ref_date, coalesce(NUM_REG_DIF, 0) AS NUM_REG_DIF FROM ("&L15&") A " -> SELECT 'Validação de campos' as tipologia_teste, 'lt003_entity' AS TABELA, 'capex_prvs' AS CAMPO, '2024-09-30' as ref_date, coalesce(NUM_REG_DIF, 0) AS NUM_REG_DIF FROM (SELECT count(*) AS NUM_REG_DIF FROM (SELECT entty_id as entty_id_, capex_prvs as capex_prvs_as_is FROM cd_loan_tapes_bce.lt003_entity WHERE ref_date='2024-09-30' AND nome_perimetro='Individual Corporativo' AND segmento='ESTR' AND ambito='PM' AND entidade='00100' ) A Inner join (SELECT entty_id as entty_id_, capex_prvs as capex_prvs_to_be FROM bu_loantape_work.lt003_entity WHERE ref_date='2024-09-30' AND nome_perimetro='Individual Corporativo' AND segmento='ESTR' AND ambito='PM' AND entidade='00100' ) B ON entty_id_as_is=entty_id_to_be WHERE coalesce(cast(capex_prvs_as_is AS string),'')<>coalesce(cast(capex_prvs_to_be AS string),'') ) A | O15: =IF(O16="",N15,N15&$O$8) -> SELECT 'Validação de campos' as tipologia_teste, 'lt003_entity' AS TABELA, 'capex_prvs' AS CAMPO, '2024-09-30' as ref_date, coalesce(NUM_REG_DIF, 0) AS NUM_REG_DIF FROM (SELECT count(*) AS NUM_REG_DIF FROM (SELECT entty_id as entty_id_, capex_prvs as capex_prvs_as_is FROM cd_loan_tapes_bce.lt003_entity WHERE ref_date='2024-09-30' AND nome_perimetro='Individual Corporativo' AND segmento='ESTR' AND ambito='PM' AND entidade='00100' ) A Inner join (SELECT entty_id as entty_id_, capex_prvs as capex_prvs_to_be FROM bu_loantape_work.lt003_entity WHERE ref_date='2024-09-30' AND nome_perimetro='Individual Corporativo' AND segmento='ESTR' AND ambito='PM' AND entidade='00100' ) B ON entty_id_as_is=entty_id_to_be WHERE coalesce(cast(capex_prvs_as_is AS string),'')<>coalesce(cast(capex_prvs_to_be AS string),'') ) A Union all | P15: =+P14+1 -> 7
B16: ENTTY | C16: =_xlfn.CONCAT(Instruções!$D$13,".",VLOOKUP(B16,Instruções!$F$12:$H$17,2,0)) -> cd_loan_tapes_bce.lt003_entity | D16: =_xlfn.CONCAT(Instruções!$D$14,".",VLOOKUP(B16,Instruções!$F$12:$H$17,3,0)) -> bu_loantape_work.lt003_entity | E16: cllctn_md | F16: =E16&"_"&$F$7 -> cllctn_md_as_is | G16: =E16&"_"&$G$7 -> cllctn_md_to_be | H16: =IF(VLOOKUP(B16,Instruções!$F$13:$J$17,5,0)="", "(SELECT "&VLOOKUP(B16,Instruções!$F$13:$J$17,4,0)&" as "&VLOOKUP(B16,Instruções!$F$13:$J$17,4,0)&"_"&$F$2&", "&E16&" as "&F16&" FROM "&C16&" WHERE "&Instruções!$D$20&") A ", "(SELECT "&VLOOKUP(B16,Instruções!$F$13:$J$17,4,0)&" as "&VLOOKUP(B16,Instruções!$F$13:$J$17,4,0)&"_"&$F$2&", "&VLOOKUP(B16,Instruções!$F$13:$J$17,5,0)&" as "&VLOOKUP(B16,Instruções!$F$13:$J$17,5,0)&"_"&$F$2&","&E16&" as "&F16&" FROM "&C16&" WHERE "&Instruções!$D$20&") A ") -> (SELECT entty_id as entty_id_, cllctn_md as cllctn_md_as_is FROM cd_loan_tapes_bce.lt003_entity WHERE ref_date='2024-09-30' AND nome_perimetro='Individual Corporativo' AND segmento='ESTR' AND ambito='PM' AND entidade='00100' ) A | I16: =IF(VLOOKUP(B16,Instruções!$F$13:$J$17,5,0)="", "(SELECT "&VLOOKUP(B16,Instruções!$F$13:$J$17,4,0)&" as "&VLOOKUP(B16,Instruções!$F$13:$J$17,4,0)&"_"&$G$2&", "&E16&" as "&G16&" FROM "&D16&" WHERE "&Instruções!$D$21&") B ", "(SELECT "&VLOOKUP(B16,Instruções!$F$13:$J$17,4,0)&" as "&VLOOKUP(B16,Instruções!$F$13:$J$17,4,0)&"_"&$G$2&", "&VLOOKUP(B16,Instruções!$F$13:$J$17,5,0)&" as "&VLOOKUP(B16,Instruções!$F$13:$J$17,5,0)&"_"&$G$2&","&E16&" as "&G16&" FROM "&D16&" WHERE "&Instruções!$D$21&") B ") -> (SELECT entty_id as entty_id_, cllctn_md as cllctn_md_to_be FROM bu_loantape_work.lt003_entity WHERE ref_date='2024-09-30' AND nome_perimetro='Individual Corporativo' AND segmento='ESTR' AND ambito='PM' AND entidade='00100' ) B | J16: =+IF(VLOOKUP(B16,Instruções!$F$13:$J$17,5,0)="", "ON "&VLOOKUP(B16,Instruções!$F$13:$J$17,4,0)&"_"&$F$7&"="&VLOOKUP(B16,Instruções!$F$13:$J$17,4,0)&"_"&$G$7&" ", "ON "&VLOOKUP(B16,Instruções!$F$13:$J$17,4,0)&"_"&$F$7&"="&VLOOKUP(B16,Instruções!$F$13:$J$17,4,0)&"_"&$G$7&" AND "&VLOOKUP(B16,Instruções!$F$13:$J$17,5,0)&"_"&$F$7&"="&VLOOKUP(B16,Instruções!$F$13:$J$17,5,0)&"_"&$G$7&" ") -> ON entty_id_as_is=entty_id_to_be | K16: ="WHERE coalesce(cast("&F16&" AS string),'')<>coalesce(cast("&G16&" AS string),'') " -> WHERE coalesce(cast(cllctn_md_as_is AS string),'')<>coalesce(cast(cllctn_md_to_be AS string),'') | L16: ="SELECT count(*) AS NUM_REG_DIF FROM "&H16&" Inner join "&I16&J16&K16 -> SELECT count(*) AS NUM_REG_DIF FROM (SELECT entty_id as entty_id_, cllctn_md as cllctn_md_as_is FROM cd_loan_tapes_bce.lt003_entity WHERE ref_date='2024-09-30' AND nome_perimetro='Individual Corporativo' AND segmento='ESTR' AND ambito='PM' AND entidade='00100' ) A Inner join (SELECT entty_id as entty_id_, cllctn_md as cllctn_md_to_be FROM bu_loantape_work.lt003_entity WHERE ref_date='2024-09-30' AND nome_perimetro='Individual Corporativo' AND segmento='ESTR' AND ambito='PM' AND entidade='00100' ) B ON entty_id_as_is=entty_id_to_be WHERE coalesce(cast(cllctn_md_as_is AS string),'')<>coalesce(cast(cllctn_md_to_be AS string),'') | M16: Validação de campos | N16: ="SELECT 'Validação de campos' as tipologia_teste, '"&VLOOKUP(B16,Instruções!$F$13:$J$17,3,0)&"' AS TABELA, '"&E16&"' AS CAMPO, '"&Instruções!$D$15&"' as ref_date, coalesce(NUM_REG_DIF, 0) AS NUM_REG_DIF FROM ("&L16&") A " -> SELECT 'Validação de campos' as tipologia_teste, 'lt003_entity' AS TABELA, 'cllctn_md' AS CAMPO, '2024-09-30' as ref_date, coalesce(NUM_REG_DIF, 0) AS NUM_REG_DIF FROM (SELECT count(*) AS NUM_REG_DIF FROM (SELECT entty_id as entty_id_, cllctn_md as cllctn_md_as_is FROM cd_loan_tapes_bce.lt003_entity WHERE ref_date='2024-09-30' AND nome_perimetro='Individual Corporativo' AND segmento='ESTR' AND ambito='PM' AND entidade='00100' ) A Inner join (SELECT entty_id as entty_id_, cllctn_md as cllctn_md_to_be FROM bu_loantape_work.lt003_entity WHERE ref_date='2024-09-30' AND nome_perimetro='Individual Corporativo' AND segmento='ESTR' AND ambito='PM' AND entidade='00100' ) B ON entty_id_as_is=entty_id_to_be WHERE coalesce(cast(cllctn_md_as_is AS string),'')<>coalesce(cast(cllctn_md_to_be AS string),'') ) A | O16: =IF(O17="",N16,N16&$O$8) -> SELECT 'Validação de campos' as tipologia_teste, 'lt003_entity' AS TABELA, 'cllctn_md' AS CAMPO, '2024-09-30' as ref_date, coalesce(NUM_REG_DIF, 0) AS NUM_REG_DIF FROM (SELECT count(*) AS NUM_REG_DIF FROM (SELECT entty_id as entty_id_, cllctn_md as cllctn_md_as_is FROM cd_loan_tapes_bce.lt003_entity WHERE ref_date='2024-09-30' AND nome_perimetro='Individual Corporativo' AND segmento='ESTR' AND ambito='PM' AND entidade='00100' ) A Inner join (SELECT entty_id as entty_id_, cllctn_md as cllctn_md_to_be FROM bu_loantape_work.lt003_entity WHERE ref_date='2024-09-30' AND nome_perimetro='Individual Corporativo' AND segmento='ESTR' AND ambito='PM' AND entidade='00100' ) B ON entty_id_as_is=entty_id_to_be WHERE coalesce(cast(cllctn_md_as_is AS string),'')<>coalesce(cast(cllctn_md_to_be AS string),'') ) A Union all | P16: =+P15+1 -> 8
B17: ENTTY | C17: =_xlfn.CONCAT(Instruções!$D$13,".",VLOOKUP(B17,Instruções!$F$12:$H$17,2,0)) -> cd_loan_tapes_bce.lt003_entity | D17: =_xlfn.CONCAT(Instruções!$D$14,".",VLOOKUP(B17,Instruções!$F$12:$H$17,3,0)) -> bu_loantape_work.lt003_entity | E17: cntry | F17: =E17&"_"&$F$7 -> cntry_as_is | G17: =E17&"_"&$G$7 -> cntry_to_be | H17: =IF(VLOOKUP(B17,Instruções!$F$13:$J$17,5,0)="", "(SELECT "&VLOOKUP(B17,Instruções!$F$13:$J$17,4,0)&" as "&VLOOKUP(B17,Instruções!$F$13:$J$17,4,0)&"_"&$F$2&", "&E17&" as "&F17&" FROM "&C17&" WHERE "&Instruções!$D$20&") A ", "(SELECT "&VLOOKUP(B17,Instruções!$F$13:$J$17,4,0)&" as "&VLOOKUP(B17,Instruções!$F$13:$J$17,4,0)&"_"&$F$2&", "&VLOOKUP(B17,Instruções!$F$13:$J$17,5,0)&" as "&VLOOKUP(B17,Instruções!$F$13:$J$17,5,0)&"_"&$F$2&","&E17&" as "&F17&" FROM "&C17&" WHERE "&Instruções!$D$20&") A ") -> (SELECT entty_id as entty_id_, cntry as cntry_as_is FROM cd_loan_tapes_bce.lt003_entity WHERE ref_date='2024-09-30' AND nome_perimetro='Individual Corporativo' AND segmento='ESTR' AND ambito='PM' AND entidade='00100' ) A | I17: =IF(VLOOKUP(B17,Instruções!$F$13:$J$17,5,0)="", "(SELECT "&VLOOKUP(B17,Instruções!$F$13:$J$17,4,0)&" as "&VLOOKUP(B17,Instruções!$F$13:$J$17,4,0)&"_"&$G$2&", "&E17&" as "&G17&" FROM "&D17&" WHERE "&Instruções!$D$21&") B ", "(SELECT "&VLOOKUP(B17,Instruções!$F$13:$J$17,4,0)&" as "&VLOOKUP(B17,Instruções!$F$13:$J$17,4,0)&"_"&$G$2&", "&VLOOKUP(B17,Instruções!$F$13:$J$17,5,0)&" as "&VLOOKUP(B17,Instruções!$F$13:$J$17,5,0)&"_"&$G$2&","&E17&" as "&G17&" FROM "&D17&" WHERE "&Instruções!$D$21&") B ") -> (SELECT entty_id as entty_id_, cntry as cntry_to_be FROM bu_loantape_work.lt003_entity WHERE ref_date='2024-09-30' AND nome_perimetro='Individual Corporativo' AND segmento='ESTR' AND ambito='PM' AND entidade='00100' ) B | J17: =+IF(VLOOKUP(B17,Instruções!$F$13:$J$17,5,0)="", "ON "&VLOOKUP(B17,Instruções!$F$13:$J$17,4,0)&"_"&$F$7&"="&VLOOKUP(B17,Instruções!$F$13:$J$17,4,0)&"_"&$G$7&" ", "ON "&VLOOKUP(B17,Instruções!$F$13:$J$17,4,0)&"_"&$F$7&"="&VLOOKUP(B17,Instruções!$F$13:$J$17,4,0)&"_"&$G$7&" AND "&VLOOKUP(B17,Instruções!$F$13:$J$17,5,0)&"_"&$F$7&"="&VLOOKUP(B17,Instruções!$F$13:$J$17,5,0)&"_"&$G$7&" ") -> ON entty_id_as_is=entty_id_to_be | K17: ="WHERE coalesce(cast("&F17&" AS string),'')<>coalesce(cast("&G17&" AS string),'') " -> WHERE coalesce(cast(cntry_as_is AS string),'')<>coalesce(cast(cntry_to_be AS string),'') | L17: ="SELECT count(*) AS NUM_REG_DIF FROM "&H17&" Inner join "&I17&J17&K17 -> SELECT count(*) AS NUM_REG_DIF FROM (SELECT entty_id as entty_id_, cntry as cntry_as_is FROM cd_loan_tapes_bce.lt003_entity WHERE ref_date='2024-09-30' AND nome_perimetro='Individual Corporativo' AND segmento='ESTR' AND ambito='PM' AND entidade='00100' ) A Inner join (SELECT entty_id as entty_id_, cntry as cntry_to_be FROM bu_loantape_work.lt003_entity WHERE ref_date='2024-09-30' AND nome_perimetro='Individual Corporativo' AND segmento='ESTR' AND ambito='PM' AND entidade='00100' ) B ON entty_id_as_is=entty_id_to_be WHERE coalesce(cast(cntry_as_is AS string),'')<>coalesce(cast(cntry_to_be AS string),'') | M17: Validação de campos | N17: ="SELECT 'Validação de campos' as tipologia_teste, '"&VLOOKUP(B17,Instruções!$F$13:$J$17,3,0)&"' AS TABELA, '"&E17&"' AS CAMPO, '"&Instruções!$D$15&"' as ref_date, coalesce(NUM_REG_DIF, 0) AS NUM_REG_DIF FROM ("&L17&") A " -> SELECT 'Validação de campos' as tipologia_teste, 'lt003_entity' AS TABELA, 'cntry' AS CAMPO, '2024-09-30' as ref_date, coalesce(NUM_REG_DIF, 0) AS NUM_REG_DIF FROM (SELECT count(*) AS NUM_REG_DIF FROM (SELECT entty_id as entty_id_, cntry as cntry_as_is FROM cd_loan_tapes_bce.lt003_entity WHERE ref_date='2024-09-30' AND nome_perimetro='Individual Corporativo' AND segmento='ESTR' AND ambito='PM' AND entidade='00100' ) A Inner join (SELECT entty_id as entty_id_, cntry as cntry_to_be FROM bu_loantape_work.lt003_entity WHERE ref_date='2024-09-30' AND nome_perimetro='Individual Corporativo' AND segmento='ESTR' AND ambito='PM' AND entidade='00100' ) B ON entty_id_as_is=entty_id_to_be WHERE coalesce(cast(cntry_as_is AS string),'')<>coalesce(cast(cntry_to_be AS string),'') ) A | O17: =IF(O18="",N17,N17&$O$8) -> SELECT 'Validação de campos' as tipologia_teste, 'lt003_entity' AS TABELA, 'cntry' AS CAMPO, '2024-09-30' as ref_date, coalesce(NUM_REG_DIF, 0) AS NUM_REG_DIF FROM (SELECT count(*) AS NUM_REG_DIF FROM (SELECT entty_id as entty_id_, cntry as cntry_as_is FROM cd_loan_tapes_bce.lt003_entity WHERE ref_date='2024-09-30' AND nome_perimetro='Individual Corporativo' AND segmento='ESTR' AND ambito='PM' AND entidade='00100' ) A Inner join (SELECT entty_id as entty_id_, cntry as cntry_to_be FROM bu_loantape_work.lt003_entity WHERE ref_date='2024-09-30' AND nome_perimetro='Individual Corporativo' AND segmento='ESTR' AND ambito='PM' AND entidade='00100' ) B ON entty_id_as_is=entty_id_to_be WHERE coalesce(cast(cntry_as_is AS string),'')<>coalesce(cast(cntry_to_be AS string),'') ) A Union all | P17: =+P16+1 -> 9
B18: ENTTY | C18: =_xlfn.CONCAT(Instruções!$D$13,".",VLOOKUP(B18,Instruções!$F$12:$H$17,2,0)) -> cd_loan_tapes_bce.lt003_entity | D18: =_xlfn.CONCAT(Instruções!$D$14,".",VLOOKUP(B18,Instruções!$F$12:$H$17,3,0)) -> bu_loantape_work.lt003_entity | E18: cod_soc | F18: =E18&"_"&$F$7 -> cod_soc_as_is | G18: =E18&"_"&$G$7 -> cod_soc_to_be | H18: =IF(VLOOKUP(B18,Instruções!$F$13:$J$17,5,0)="", "(SELECT "&VLOOKUP(B18,Instruções!$F$13:$J$17,4,0)&" as "&VLOOKUP(B18,Instruções!$F$13:$J$17,4,0)&"_"&$F$2&", "&E18&" as "&F18&" FROM "&C18&" WHERE "&Instruções!$D$20&") A ", "(SELECT "&VLOOKUP(B18,Instruções!$F$13:$J$17,4,0)&" as "&VLOOKUP(B18,Instruções!$F$13:$J$17,4,0)&"_"&$F$2&", "&VLOOKUP(B18,Instruções!$F$13:$J$17,5,0)&" as "&VLOOKUP(B18,Instruções!$F$13:$J$17,5,0)&"_"&$F$2&","&E18&" as "&F18&" FROM "&C18&" WHERE "&Instruções!$D$20&") A ") -> (SELECT entty_id as entty_id_, cod_soc as cod_soc_as_is FROM cd_loan_tapes_bce.lt003_entity WHERE ref_date='2024-09-30' AND nome_perimetro='Individual Corporativo' AND segmento='ESTR' AND ambito='PM' AND entidade='00100' ) A | I18: =IF(VLOOKUP(B18,Instruções!$F$13:$J$17,5,0)="", "(SELECT "&VLOOKUP(B18,Instruções!$F$13:$J$17,4,0)&" as "&VLOOKUP(B18,Instruções!$F$13:$J$17,4,0)&"_"&$G$2&", "&E18&" as "&G18&" FROM "&D18&" WHERE "&Instruções!$D$21&") B ", "(SELECT "&VLOOKUP(B18,Instruções!$F$13:$J$17,4,0)&" as "&VLOOKUP(B18,Instruções!$F$13:$J$17,4,0)&"_"&$G$2&", "&VLOOKUP(B18,Instruções!$F$13:$J$17,5,0)&" as "&VLOOKUP(B18,Instruções!$F$13:$J$17,5,0)&"_"&$G$2&","&E18&" as "&G18&" FROM "&D18&" WHERE "&Instruções!$D$21&") B ") -> (SELECT entty_id as entty_id_, cod_soc as cod_soc_to_be FROM bu_loantape_work.lt003_entity WHERE ref_date='2024-09-30' AND nome_perimetro='Individual Corporativo' AND segmento='ESTR' AND ambito='PM' AND entidade='00100' ) B | J18: =+IF(VLOOKUP(B18,Instruções!$F$13:$J$17,5,0)="", "ON "&VLOOKUP(B18,Instruções!$F$13:$J$17,4,0)&"_"&$F$7&"="&VLOOKUP(B18,Instruções!$F$13:$J$17,4,0)&"_"&$G$7&" ", "ON "&VLOOKUP(B18,Instruções!$F$13:$J$17,4,0)&"_"&$F$7&"="&VLOOKUP(B18,Instruções!$F$13:$J$17,4,0)&"_"&$G$7&" AND "&VLOOKUP(B18,Instruções!$F$13:$J$17,5,0)&"_"&$F$7&"="&VLOOKUP(B18,Instruções!$F$13:$J$17,5,0)&"_"&$G$7&" ") -> ON entty_id_as_is=entty_id_to_be | K18: ="WHERE coalesce(cast("&F18&" AS string),'')<>coalesce(cast("&G18&" AS string),'') " -> WHERE coalesce(cast(cod_soc_as_is AS string),'')<>coalesce(cast(cod_soc_to_be AS string),'') | L18: ="SELECT count(*) AS NUM_REG_DIF FROM "&H18&" Inner join "&I18&J18&K18 -> SELECT count(*) AS NUM_REG_DIF FROM (SELECT entty_id as entty_id_, cod_soc as cod_soc_as_is FROM cd_loan_tapes_bce.lt003_entity WHERE ref_date='2024-09-30' AND nome_perimetro='Individual Corporativo' AND segmento='ESTR' AND ambito='PM' AND entidade='00100' ) A Inner join (SELECT entty_id as entty_id_, cod_soc as cod_soc_to_be FROM bu_loantape_work.lt003_entity WHERE ref_date='2024-09-30' AND nome_perimetro='Individual Corporativo' AND segmento='ESTR' AND ambito='PM' AND entidade='00100' ) B ON entty_id_as_is=entty_id_to_be WHERE coalesce(cast(cod_soc_as_is AS string),'')<>coalesce(cast(cod_soc_to_be AS string),'') | M18: Validação de campos | N18: ="SELECT 'Validação de campos' as tipologia_teste, '"&VLOOKUP(B18,Instruções!$F$13:$J$17,3,0)&"' AS TABELA, '"&E18&"' AS CAMPO, '"&Instruções!$D$15&"' as ref_date, coalesce(NUM_REG_DIF, 0) AS NUM_REG_DIF FROM ("&L18&") A " -> SELECT 'Validação de campos' as tipologia_teste, 'lt003_entity' AS TABELA, 'cod_soc' AS CAMPO, '2024-09-30' as ref_date, coalesce(NUM_REG_DIF, 0) AS NUM_REG_DIF FROM (SELECT count(*) AS NUM_REG_DIF FROM (SELECT entty_id as entty_id_, cod_soc as cod_soc_as_is FROM cd_loan_tapes_bce.lt003_entity WHERE ref_date='2024-09-30' AND nome_perimetro='Individual Corporativo' AND segmento='ESTR' AND ambito='PM' AND entidade='00100' ) A Inner join (SELECT entty_id as entty_id_, cod_soc as cod_soc_to_be FROM bu_loantape_work.lt003_entity WHERE ref_date='2024-09-30' AND nome_perimetro='Individual Corporativo' AND segmento='ESTR' AND ambito='PM' AND entidade='00100' ) B ON entty_id_as_is=entty_id_to_be WHERE coalesce(cast(cod_soc_as_is AS string),'')<>coalesce(cast(cod_soc_to_be AS string),'') ) A | O18: =IF(O19="",N18,N18&$O$8) -> SELECT 'Validação de campos' as tipologia_teste, 'lt003_entity' AS TABELA, 'cod_soc' AS CAMPO, '2024-09-30' as ref_date, coalesce(NUM_REG_DIF, 0) AS NUM_REG_DIF FROM (SELECT count(*) AS NUM_REG_DIF FROM (SELECT entty_id as entty_id_, cod_soc as cod_soc_as_is FROM cd_loan_tapes_bce.lt003_entity WHERE ref_date='2024-09-30' AND nome_perimetro='Individual Corporativo' AND segmento='ESTR' AND ambito='PM' AND entidade='00100' ) A Inner join (SELECT entty_id as entty_id_, cod_soc as cod_soc_to_be FROM bu_loantape_work.lt003_entity WHERE ref_date='2024-09-30' AND nome_perimetro='Individual Corporativo' AND segmento='ESTR' AND ambito='PM' AND entidade='00100' ) B ON entty_id_as_is=entty_id_to_be WHERE coalesce(cast(cod_soc_as_is AS string),'')<>coalesce(cast(cod_soc_to_be AS string),'') ) A Union all | P18: =+P17+1 -> 10
B19: ENTTY | C19: =_xlfn.CONCAT(Instruções!$D$13,".",VLOOKUP(B19,Instruções!$F$12:$H$17,2,0)) -> cd_loan_tapes_bce.lt003_entity | D19: =_xlfn.CONCAT(Instruções!$D$14,".",VLOOKUP(B19,Instruções!$F$12:$H$17,3,0)) -> bu_loantape_work.lt003_entity | E19: cr_flg | F19: =E19&"_"&$F$7 -> cr_flg_as_is | G19: =E19&"_"&$G$7 -> cr_flg_to_be | H19: =IF(VLOOKUP(B19,Instruções!$F$13:$J$17,5,0)="", "(SELECT "&VLOOKUP(B19,Instruções!$F$13:$J$17,4,0)&" as "&VLOOKUP(B19,Instruções!$F$13:$J$17,4,0)&"_"&$F$2&", "&E19&" as "&F19&" FROM "&C19&" WHERE "&Instruções!$D$20&") A ", "(SELECT "&VLOOKUP(B19,Instruções!$F$13:$J$17,4,0)&" as "&VLOOKUP(B19,Instruções!$F$13:$J$17,4,0)&"_"&$F$2&", "&VLOOKUP(B19,Instruções!$F$13:$J$17,5,0)&" as "&VLOOKUP(B19,Instruções!$F$13:$J$17,5,0)&"_"&$F$2&","&E19&" as "&F19&" FROM "&C19&" WHERE "&Instruções!$D$20&") A ") -> (SELECT entty_id as entty_id_, cr_flg as cr_flg_as_is FROM cd_loan_tapes_bce.lt003_entity WHERE ref_date='2024-09-30' AND nome_perimetro='Individual Corporativo' AND segmento='ESTR' AND ambito='PM' AND entidade='00100' ) A | I19: =IF(VLOOKUP(B19,Instruções!$F$13:$J$17,5,0)="", "(SELECT "&VLOOKUP(B19,Instruções!$F$13:$J$17,4,0)&" as "&VLOOKUP(B19,Instruções!$F$13:$J$17,4,0)&"_"&$G$2&", "&E19&" as "&G19&" FROM "&D19&" WHERE "&Instruções!$D$21&") B ", "(SELECT "&VLOOKUP(B19,Instruções!$F$13:$J$17,4,0)&" as "&VLOOKUP(B19,Instruções!$F$13:$J$17,4,0)&"_"&$G$2&", "&VLOOKUP(B19,Instruções!$F$13:$J$17,5,0)&" as "&VLOOKUP(B19,Instruções!$F$13:$J$17,5,0)&"_"&$G$2&","&E19&" as "&G19&" FROM "&D19&" WHERE "&Instruções!$D$21&") B ") -> (SELECT entty_id as entty_id_, cr_flg as cr_flg_to_be FROM bu_loantape_work.lt003_entity WHERE ref_date='2024-09-30' AND nome_perimetro='Individual Corporativo' AND segmento='ESTR' AND ambito='PM' AND entidade='00100' ) B | J19: =+IF(VLOOKUP(B19,Instruções!$F$13:$J$17,5,0)="", "ON "&VLOOKUP(B19,Instruções!$F$13:$J$17,4,0)&"_"&$F$7&"="&VLOOKUP(B19,Instruções!$F$13:$J$17,4,0)&"_"&$G$7&" ", "ON "&VLOOKUP(B19,Instruções!$F$13:$J$17,4,0)&"_"&$F$7&"="&VLOOKUP(B19,Instruções!$F$13:$J$17,4,0)&"_"&$G$7&" AND "&VLOOKUP(B19,Instruções!$F$13:$J$17,5,0)&"_"&$F$7&"="&VLOOKUP(B19,Instruções!$F$13:$J$17,5,0)&"_"&$G$7&" ") -> ON entty_id_as_is=entty_id_to_be | K19: ="WHERE coalesce(cast("&F19&" AS string),'')<>coalesce(cast("&G19&" AS string),'') " -> WHERE coalesce(cast(cr_flg_as_is AS string),'')<>coalesce(cast(cr_flg_to_be AS string),'') | L19: ="SELECT count(*) AS NUM_REG_DIF FROM "&H19&" Inner join "&I19&J19&K19 -> SELECT count(*) AS NUM_REG_DIF FROM (SELECT entty_id as entty_id_, cr_flg as cr_flg_as_is FROM cd_loan_tapes_bce.lt003_entity WHERE ref_date='2024-09-30' AND nome_perimetro='Individual Corporativo' AND segmento='ESTR' AND ambito='PM' AND entidade='00100' ) A Inner join (SELECT entty_id as entty_id_, cr_flg as cr_flg_to_be FROM bu_loantape_work.lt003_entity WHERE ref_date='2024-09-30' AND nome_perimetro='Individual Corporativo' AND segmento='ESTR' AND ambito='PM' AND entidade='00100' ) B ON entty_id_as_is=entty_id_to_be WHERE coalesce(cast(cr_flg_as_is AS string),'')<>coalesce(cast(cr_flg_to_be AS string),'') | M19: Validação de campos | N19: ="SELECT 'Validação de campos' as tipologia_teste, '"&VLOOKUP(B19,Instruções!$F$13:$J$17,3,0)&"' AS TABELA, '"&E19&"' AS CAMPO, '"&Instruções!$D$15&"' as ref_date, coalesce(NUM_REG_DIF, 0) AS NUM_REG_DIF FROM ("&L19&") A " -> SELECT 'Validação de campos' as tipologia_teste, 'lt003_entity' AS TABELA, 'cr_flg' AS CAMPO, '2024-09-30' as ref_date, coalesce(NUM_REG_DIF, 0) AS NUM_REG_DIF FROM (SELECT count(*) AS NUM_REG_DIF FROM (SELECT entty_id as entty_id_, cr_flg as cr_flg_as_is FROM cd_loan_tapes_bce.lt003_entity WHERE ref_date='2024-09-30' AND nome_perimetro='Individual Corporativo' AND segmento='ESTR' AND ambito='PM' AND entidade='00100' ) A Inner join (SELECT entty_id as entty_id_, cr_flg as cr_flg_to_be FROM bu_loantape_work.lt003_entity WHERE ref_date='2024-09-30' AND nome_perimetro='Individual Corporativo' AND segmento='ESTR' AND ambito='PM' AND entidade='00100' ) B ON entty_id_as_is=entty_id_to_be WHERE coalesce(cast(cr_flg_as_is AS string),'')<>coalesce(cast(cr_flg_to_be AS string),'') ) A | O19: =IF(O20="",N19,N19&$O$8) -> SELECT 'Validação de campos' as tipologia_teste, 'lt003_entity' AS TABELA, 'cr_flg' AS CAMPO, '2024-09-30' as ref_date, coalesce(NUM_REG_DIF, 0) AS NUM_REG_DIF FROM (SELECT count(*) AS NUM_REG_DIF FROM (SELECT entty_id as entty_id_, cr_flg as cr_flg_as_is FROM cd_loan_tapes_bce.lt003_entity WHERE ref_date='2024-09-30' AND nome_perimetro='Individual Corporativo' AND segmento='ESTR' AND ambito='PM' AND entidade='00100' ) A Inner join (SELECT entty_id as entty_id_, cr_flg as cr_flg_to_be FROM bu_loantape_work.lt003_entity WHERE ref_date='2024-09-30' AND nome_perimetro='Individual Corporativo' AND segmento='ESTR' AND ambito='PM' AND entidade='00100' ) B ON entty_id_as_is=entty_id_to_be WHERE coalesce(cast(cr_flg_as_is AS string),'')<>coalesce(cast(cr_flg_to_be AS string),'') ) A Union all | P19: =+P18+1 -> 11
B20: ENTTY | C20: =_xlfn.CONCAT(Instruções!$D$13,".",VLOOKUP(B20,Instruções!$F$12:$H$17,2,0)) -> cd_loan_tapes_bce.lt003_entity | D20: =_xlfn.CONCAT(Instruções!$D$14,".",VLOOKUP(B20,Instruções!$F$12:$H$17,3,0)) -> bu_loantape_work.lt003_entity | E20: csh | F20: =E20&"_"&$F$7 -> csh_as_is | G20: =E20&"_"&$G$7 -> csh_to_be | H20: =IF(VLOOKUP(B20,Instruções!$F$13:$J$17,5,0)="", "(SELECT "&VLOOKUP(B20,Instruções!$F$13:$J$17,4,0)&" as "&VLOOKUP(B20,Instruções!$F$13:$J$17,4,0)&"_"&$F$2&", "&E20&" as "&F20&" FROM "&C20&" WHERE "&Instruções!$D$20&") A ", "(SELECT "&VLOOKUP(B20,Instruções!$F$13:$J$17,4,0)&" as "&VLOOKUP(B20,Instruções!$F$13:$J$17,4,0)&"_"&$F$2&", "&VLOOKUP(B20,Instruções!$F$13:$J$17,5,0)&" as "&VLOOKUP(B20,Instruções!$F$13:$J$17,5,0)&"_"&$F$2&","&E20&" as "&F20&" FROM "&C20&" WHERE "&Instruções!$D$20&") A ") -> (SELECT entty_id as entty_id_, csh as csh_as_is FROM cd_loan_tapes_bce.lt003_entity WHERE ref_date='2024-09-30' AND nome_perimetro='Individual Corporativo' AND segmento='ESTR' AND ambito='PM' AND entidade='00100' ) A | I20: =IF(VLOOKUP(B20,Instruções!$F$13:$J$17,5,0)="", "(SELECT "&VLOOKUP(B20,Instruções!$F$13:$J$17,4,0)&" as "&VLOOKUP(B20,Instruções!$F$13:$J$17,4,0)&"_"&$G$2&", "&E20&" as "&G20&" FROM "&D20&" WHERE "&Instruções!$D$21&") B ", "(SELECT "&VLOOKUP(B20,Instruções!$F$13:$J$17,4,0)&" as "&VLOOKUP(B20,Instruções!$F$13:$J$17,4,0)&"_"&$G$2&", "&VLOOKUP(B20,Instruções!$F$13:$J$17,5,0)&" as "&VLOOKUP(B20,Instruções!$F$13:$J$17,5,0)&"_"&$G$2&","&E20&" as "&G20&" FROM "&D20&" WHERE "&Instruções!$D$21&") B ") -> (SELECT entty_id as entty_id_, csh as csh_to_be FROM bu_loantape_work.lt003_entity WHERE ref_date='2024-09-30' AND nome_perimetro='Individual Corporativo' AND segmento='ESTR' AND ambito='PM' AND entidade='00100' ) B | J20: =+IF(VLOOKUP(B20,Instruções!$F$13:$J$17,5,0)="", "ON "&VLOOKUP(B20,Instruções!$F$13:$J$17,4,0)&"_"&$F$7&"="&VLOOKUP(B20,Instruções!$F$13:$J$17,4,0)&"_"&$G$7&" ", "ON "&VLOOKUP(B20,Instruções!$F$13:$J$17,4,0)&"_"&$F$7&"="&VLOOKUP(B20,Instruções!$F$13:$J$17,4,0)&"_"&$G$7&" AND "&VLOOKUP(B20,Instruções!$F$13:$J$17,5,0)&"_"&$F$7&"="&VLOOKUP(B20,Instruções!$F$13:$J$17,5,0)&"_"&$G$7&" ") -> ON entty_id_as_is=entty_id_to_be | K20: ="WHERE coalesce(cast("&F20&" AS string),'')<>coalesce(cast("&G20&" AS string),'') " -> WHERE coalesce(cast(csh_as_is AS string),'')<>coalesce(cast(csh_to_be AS string),'') | L20: ="SELECT count(*) AS NUM_REG_DIF FROM "&H20&" Inner join "&I20&J20&K20 -> SELECT count(*) AS NUM_REG_DIF FROM (SELECT entty_id as entty_id_, csh as csh_as_is FROM cd_loan_tapes_bce.lt003_entity WHERE ref_date='2024-09-30' AND nome_perimetro='Individual Corporativo' AND segmento='ESTR' AND ambito='PM' AND entidade='00100' ) A Inner join (SELECT entty_id as entty_id_, csh as csh_to_be FROM bu_loantape_work.lt003_entity WHERE ref_date='2024-09-30' AND nome_perimetro='Individual Corporativo' AND segmento='ESTR' AND ambito='PM' AND entidade='00100' ) B ON entty_id_as_is=entty_id_to_be WHERE coalesce(cast(csh_as_is AS string),'')<>coalesce(cast(csh_to_be AS string),'') | M20: Validação de campos | N20: ="SELECT 'Validação de campos' as tipologia_teste, '"&VLOOKUP(B20,Instruções!$F$13:$J$17,3,0)&"' AS TABELA, '"&E20&"' AS CAMPO, '"&Instruções!$D$15&"' as ref_date, coalesce(NUM_REG_DIF, 0) AS NUM_REG_DIF FROM ("&L20&") A " -> SELECT 'Validação de campos' as tipologia_teste, 'lt003_entity' AS TABELA, 'csh' AS CAMPO, '2024-09-30' as ref_date, coalesce(NUM_REG_DIF, 0) AS NUM_REG_DIF FROM (SELECT count(*) AS NUM_REG_DIF FROM (SELECT entty_id as entty_id_, csh as csh_as_is FROM cd_loan_tapes_bce.lt003_entity WHERE ref_date='2024-09-30' AND nome_perimetro='Individual Corporativo' AND segmento='ESTR' AND ambito='PM' AND entidade='00100' ) A Inner join (SELECT entty_id as entty_id_, csh as csh_to_be FROM bu_loantape_work.lt003_entity WHERE ref_date='2024-09-30' AND nome_perimetro='Individual Corporativo' AND segmento='ESTR' AND ambito='PM' AND entidade='00100' ) B ON entty_id_as_is=entty_id_to_be WHERE coalesce(cast(csh_as_is AS string),'')<>coalesce(cast(csh_to_be AS string),'') ) A | O20: =IF(O21="",N20,N20&$O$8) -> SELECT 'Validação de campos' as tipologia_teste, 'lt003_entity' AS TABELA, 'csh' AS CAMPO, '2024-09-30' as ref_date, coalesce(NUM_REG_DIF, 0) AS NUM_REG_DIF FROM (SELECT count(*) AS NUM_REG_DIF FROM (SELECT entty_id as entty_id_, csh as csh_as_is FROM cd_loan_tapes_bce.lt003_entity WHERE ref_date='2024-09-30' AND nome_perimetro='Individual Corporativo' AND segmento='ESTR' AND ambito='PM' AND entidade='00100' ) A Inner join (SELECT entty_id as entty_id_, csh as csh_to_be FROM bu_loantape_work.lt003_entity WHERE ref_date='2024-09-30' AND nome_perimetro='Individual Corporativo' AND segmento='ESTR' AND ambito='PM' AND entidade='00100' ) B ON entty_id_as_is=entty_id_to_be WHERE coalesce(cast(csh_as_is AS string),'')<>coalesce(cast(csh_to_be AS string),'') ) A Union all | P20: =+P19+1 -> 12
B21: ENTTY | C21: =_xlfn.CONCAT(Instruções!$D$13,".",VLOOKUP(B21,Instruções!$F$12:$H$17,2,0)) -> cd_loan_tapes_bce.lt003_entity | D21: =_xlfn.CONCAT(Instruções!$D$14,".",VLOOKUP(B21,Instruções!$F$12:$H$17,3,0)) -> bu_loantape_work.lt003_entity | E21: csh_prvs | F21: =E21&"_"&$F$7 -> csh_prvs_as_is | G21: =E21&"_"&$G$7 -> csh_prvs_to_be | H21: =IF(VLOOKUP(B21,Instruções!$F$13:$J$17,5,0)="", "(SELECT "&VLOOKUP(B21,Instruções!$F$13:$J$17,4,0)&" as "&VLOOKUP(B21,Instruções!$F$13:$J$17,4,0)&"_"&$F$2&", "&E21&" as "&F21&" FROM "&C21&" WHERE "&Instruções!$D$20&") A ", "(SELECT "&VLOOKUP(B21,Instruções!$F$13:$J$17,4,0)&" as "&VLOOKUP(B21,Instruções!$F$13:$J$17,4,0)&"_"&$F$2&", "&VLOOKUP(B21,Instruções!$F$13:$J$17,5,0)&" as "&VLOOKUP(B21,Instruções!$F$13:$J$17,5,0)&"_"&$F$2&","&E21&" as "&F21&" FROM "&C21&" WHERE "&Instruções!$D$20&") A ") -> (SELECT entty_id as entty_id_, csh_prvs as csh_prvs_as_is FROM cd_loan_tapes_bce.lt003_entity WHERE ref_date='2024-09-30' AND nome_perimetro='Individual Corporativo' AND segmento='ESTR' AND ambito='PM' AND entidade='00100' ) A | I21: =IF(VLOOKUP(B21,Instruções!$F$13:$J$17,5,0)="", "(SELECT "&VLOOKUP(B21,Instruções!$F$13:$J$17,4,0)&" as "&VLOOKUP(B21,Instruções!$F$13:$J$17,4,0)&"_"&$G$2&", "&E21&" as "&G21&" FROM "&D21&" WHERE "&Instruções!$D$21&") B ", "(SELECT "&VLOOKUP(B21,Instruções!$F$13:$J$17,4,0)&" as "&VLOOKUP(B21,Instruções!$F$13:$J$17,4,0)&"_"&$G$2&", "&VLOOKUP(B21,Instruções!$F$13:$J$17,5,0)&" as "&VLOOKUP(B21,Instruções!$F$13:$J$17,5,0)&"_"&$G$2&","&E21&" as "&G21&" FROM "&D21&" WHERE "&Instruções!$D$21&") B ") -> (SELECT entty_id as entty_id_, csh_prvs as csh_prvs_to_be FROM bu_loantape_work.lt003_entity WHERE ref_date='2024-09-30' AND nome_perimetro='Individual Corporativo' AND segmento='ESTR' AND ambito='PM' AND entidade='00100' ) B | J21: =+IF(VLOOKUP(B21,Instruções!$F$13:$J$17,5,0)="", "ON "&VLOOKUP(B21,Instruções!$F$13:$J$17,4,0)&"_"&$F$7&"="&VLOOKUP(B21,Instruções!$F$13:$J$17,4,0)&"_"&$G$7&" ", "ON "&VLOOKUP(B21,Instruções!$F$13:$J$17,4,0)&"_"&$F$7&"="&VLOOKUP(B21,Instruções!$F$13:$J$17,4,0)&"_"&$G$7&" AND "&VLOOKUP(B21,Instruções!$F$13:$J$17,5,0)&"_"&$F$7&"="&VLOOKUP(B21,Instruções!$F$13:$J$17,5,0)&"_"&$G$7&" ") -> ON entty_id_as_is=entty_id_to_be | K21: ="WHERE coalesce(cast("&F21&" AS string),'')<>coalesce(cast("&G21&" AS string),'') " -> WHERE coalesce(cast(csh_prvs_as_is AS string),'')<>coalesce(cast(csh_prvs_to_be AS string),'') | L21: ="SELECT count(*) AS NUM_REG_DIF FROM "&H21&" Inner join "&I21&J21&K21 -> SELECT count(*) AS NUM_REG_DIF FROM (SELECT entty_id as entty_id_, csh_prvs as csh_prvs_as_is FROM cd_loan_tapes_bce.lt003_entity WHERE ref_date='2024-09-30' AND nome_perimetro='Individual Corporativo' AND segmento='ESTR' AND ambito='PM' AND entidade='00100' ) A Inner join (SELECT entty_id as entty_id_, csh_prvs as csh_prvs_to_be FROM bu_loantape_work.lt003_entity WHERE ref_date='2024-09-30' AND nome_perimetro='Individual Corporativo' AND segmento='ESTR' AND ambito='PM' AND entidade='00100' ) B ON entty_id_as_is=entty_id_to_be WHERE coalesce(cast(csh_prvs_as_is AS string),'')<>coalesce(cast(csh_prvs_to_be AS string),'') | M21: Validação de campos | N21: ="SELECT 'Validação de campos' as tipologia_teste, '"&VLOOKUP(B21,Instruções!$F$13:$J$17,3,0)&"' AS TABELA, '"&E21&"' AS CAMPO, '"&Instruções!$D$15&"' as ref_date, coalesce(NUM_REG_DIF, 0) AS NUM_REG_DIF FROM ("&L21&") A " -> SELECT 'Validação de campos' as tipologia_teste, 'lt003_entity' AS TABELA, 'csh_prvs' AS CAMPO, '2024-09-30' as ref_date, coalesce(NUM_REG_DIF, 0) AS NUM_REG_DIF FROM (SELECT count(*) AS NUM_REG_DIF FROM (SELECT entty_id as entty_id_, csh_prvs as csh_prvs_as_is FROM cd_loan_tapes_bce.lt003_entity WHERE ref_date='2024-09-30' AND nome_perimetro='Individual Corporativo' AND segmento='ESTR' AND ambito='PM' AND entidade='00100' ) A Inner join (SELECT entty_id as entty_id_, csh_prvs as csh_prvs_to_be FROM bu_loantape_work.lt003_entity WHERE ref_date='2024-09-30' AND nome_perimetro='Individual Corporativo' AND segmento='ESTR' AND ambito='PM' AND entidade='00100' ) B ON entty_id_as_is=entty_id_to_be WHERE coalesce(cast(csh_prvs_as_is AS string),'')<>coalesce(cast(csh_prvs_to_be AS string),'') ) A | O21: =IF(O22="",N21,N21&$O$8) -> SELECT 'Validação de campos' as tipologia_teste, 'lt003_entity' AS TABELA, 'csh_prvs' AS CAMPO, '2024-09-30' as ref_date, coalesce(NUM_REG_DIF, 0) AS NUM_REG_DIF FROM (SELECT count(*) AS NUM_REG_DIF FROM (SELECT entty_id as entty_id_, csh_prvs as csh_prvs_as_is FROM cd_loan_tapes_bce.lt003_entity WHERE ref_date='2024-09-30' AND nome_perimetro='Individual Corporativo' AND segmento='ESTR' AND ambito='PM' AND entidade='00100' ) A Inner join (SELECT entty_id as entty_id_, csh_prvs as csh_prvs_to_be FROM bu_loantape_work.lt003_entity WHERE ref_date='2024-09-30' AND nome_perimetro='Individual Corporativo' AND segmento='ESTR' AND ambito='PM' AND entidade='00100' ) B ON entty_id_as_is=entty_id_to_be WHERE coalesce(cast(csh_prvs_as_is AS string),'')<>coalesce(cast(csh_prvs_to_be AS string),'') ) A Union all | P21: =+P20+1 -> 13
... B60: ENTTY | C60: =_xlfn.CONCAT(Instruções!$D$13,".",VLOOKUP(B60,Instruções!$F$12:$H$17,2,0)) -> cd_loan_tapes_bce.lt003_entity | D60: =_xlfn.CONCAT(Instruções!$D$14,".",VLOOKUP(B60,Instruções!$F$12:$H$17,3,0)) -> bu_loantape_work.lt003_entity | E60: flln_ang_nrrw_dfntn | F60: =E60&"_"&$F$7 -> flln_ang_nrrw_dfntn_as_is | G60: =E60&"_"&$G$7 -> flln_ang_nrrw_dfntn_to_be | H60: =IF(VLOOKUP(B60,Instruções!$F$13:$J$17,5,0)="", "(SELECT "&VLOOKUP(B60,Instruções!$F$13:$J$17,4,0)&" as "&VLOOKUP(B60,Instruções!$F$13:$J$17,4,0)&"_"&$F$2&", "&E60&" as "&F60&" FROM "&C60&" WHERE "&Instruções!$D$20&") A ", "(SELECT "&VLOOKUP(B60,Instruções!$F$13:$J$17,4,0)&" as "&VLOOKUP(B60,Instruções!$F$13:$J$17,4,0)&"_"&$F$2&", "&VLOOKUP(B60,Instruções!$F$13:$J$17,5,0)&" as "&VLOOKUP(B60,Instruções!$F$13:$J$17,5,0)&"_"&$F$2&","&E60&" as "&F60&" FROM "&C60&" WHERE "&Instruções!$D$20&") A ") -> (SELECT entty_id as entty_id_, flln_ang_nrrw_dfntn as flln_ang_nrrw_dfntn_as_is FROM cd_loan_tapes_bce.lt003_entity WHERE ref_date='2024-09-30' AND nome_perimetro='Individual Corporativo' AND segmento='ESTR' AND ambito='PM' AND entidade='00100' ) A | I60: =IF(VLOOKUP(B60,Instruções!$F$13:$J$17,5,0)="", "(SELECT "&VLOOKUP(B60,Instruções!$F$13:$J$17,4,0)&" as "&VLOOKUP(B60,Instruções!$F$13:$J$17,4,0)&"_"&$G$2&", "&E60&" as "&G60&" FROM "&D60&" WHERE "&Instruções!$D$21&") B ", "(SELECT "&VLOOKUP(B60,Instruções!$F$13:$J$17,4,0)&" as "&VLOOKUP(B60,Instruções!$F$13:$J$17,4,0)&"_"&$G$2&", "&VLOOKUP(B60,Instruções!$F$13:$J$17,5,0)&" as "&VLOOKUP(B60,Instruções!$F$13:$J$17,5,0)&"_"&$G$2&","&E60&" as "&G60&" FROM "&D60&" WHERE "&Instruções!$D$21&") B ") -> (SELECT entty_id as entty_id_, flln_ang_nrrw_dfntn as flln_ang_nrrw_dfntn_to_be FROM bu_loantape_work.lt003_entity WHERE ref_date='2024-09-30' AND nome_perimetro='Individual Corporativo' AND segmento='ESTR' AND ambito='PM' AND entidade='00100' ) B | J60: =+IF(VLOOKUP(B60,Instruções!$F$13:$J$17,5,0)="", "ON "&VLOOKUP(B60,Instruções!$F$13:$J$17,4,0)&"_"&$F$7&"="&VLOOKUP(B60,Instruções!$F$13:$J$17,4,0)&"_"&$G$7&" ", "ON "&VLOOKUP(B60,Instruções!$F$13:$J$17,4,0)&"_"&$F$7&"="&VLOOKUP(B60,Instruções!$F$13:$J$17,4,0)&"_"&$G$7&" AND "&VLOOKUP(B60,Instruções!$F$13:$J$17,5,0)&"_"&$F$7&"="&VLOOKUP(B60,Instruções!$F$13:$J$17,5,0)&"_"&$G$7&" ") -> ON entty_id_as_is=entty_id_to_be | K60: ="WHERE coalesce(cast("&F60&" AS string),'')<>coalesce(cast("&G60&" AS string),'') " -> WHERE coalesce(cast(flln_ang_nrrw_dfntn_as_is AS string),'')<>coalesce(cast(flln_ang_nrrw_dfntn_to_be AS string),'') | L60: ="SELECT count(*) AS NUM_REG_DIF FROM "&H60&" Inner join "&I60&J60&K60 -> SELECT count(*) AS NUM_REG_DIF FROM (SELECT entty_id as entty_id_, flln_ang_nrrw_dfntn as flln_ang_nrrw_dfntn_as_is FROM cd_loan_tapes_bce.lt003_entity WHERE ref_date='2024-09-30' AND nome_perimetro='Individual Corporativo' AND segmento='ESTR' AND ambito='PM' AND entidade='00100' ) A Inner join (SELECT entty_id as entty_id_, flln_ang_nrrw_dfntn as flln_ang_nrrw_dfntn_to_be FROM bu_loantape_work.lt003_entity WHERE ref_date='2024-09-30' AND nome_perimetro='Individual Corporativo' AND segmento='ESTR' AND ambito='PM' AND entidade='00100' ) B ON entty_id_as_is=entty_id_to_be WHERE coalesce(cast(flln_ang_nrrw_dfntn_as_is AS string),'')<>coalesce(cast(flln_ang_nrrw_dfntn_to_be AS string),'') | M60: Validação de campos | N60: ="SELECT 'Validação de campos' as tipologia_teste, '"&VLOOKUP(B60,Instruções!$F$13:$J$17,3,0)&"' AS TABELA, '"&E60&"' AS CAMPO, '"&Instruções!$D$15&"' as ref_date, coalesce(NUM_REG_DIF, 0) AS NUM_REG_DIF FROM ("&L60&") A " -> SELECT 'Validação de campos' as tipologia_teste, 'lt003_entity' AS TABELA, 'flln_ang_nrrw_dfntn' AS CAMPO, '2024-09-30' as ref_date, coalesce(NUM_REG_DIF, 0) AS NUM_REG_DIF FROM (SELECT count(*) AS NUM_REG_DIF FROM (SELECT entty_id as entty_id_, flln_ang_nrrw_dfntn as flln_ang_nrrw_dfntn_as_is FROM cd_loan_tapes_bce.lt003_entity WHERE ref_date='2024-09-30' AND nome_perimetro='Individual Corporativo' AND segmento='ESTR' AND ambito='PM' AND entidade='00100' ) A Inner join (SELECT entty_id as entty_id_, flln_ang_nrrw_dfntn as flln_ang_nrrw_dfntn_to_be FROM bu_loantape_work.lt003_entity WHERE ref_date='2024-09-30' AND nome_perimetro='Individual Corporativo' AND segmento='ESTR' AND ambito='PM' AND entidade='00100' ) B ON entty_id_as_is=entty_id_to_be WHERE coalesce(cast(flln_ang_nrrw_dfntn_as_is AS string),'')<>coalesce(cast(flln_ang_nrrw_dfntn_to_be AS string),'') ) A | O60: =IF(O61="",N60,N60&$O$8) -> SELECT 'Validação de campos' as tipologia_teste, 'lt003_entity' AS TABELA, 'flln_ang_nrrw_dfntn' AS CAMPO, '2024-09-30' as ref_date, coalesce(NUM_REG_DIF, 0) AS NUM_REG_DIF FROM (SELECT count(*) AS NUM_REG_DIF FROM (SELECT entty_id as entty_id_, flln_ang_nrrw_dfntn as flln_ang_nrrw_dfntn_as_is FROM cd_loan_tapes_bce.lt003_entity WHERE ref_date='2024-09-30' AND nome_perimetro='Individual Corporativo' AND segmento='ESTR' AND ambito='PM' AND entidade='00100' ) A Inner join (SELECT entty_id as entty_id_, flln_ang_nrrw_dfntn as flln_ang_nrrw_dfntn_to_be FROM bu_loantape_work.lt003_entity WHERE ref_date='2024-09-30' AND nome_perimetro='Individual Corporativo' AND segmento='ESTR' AND ambito='PM' AND entidade='00100' ) B ON entty_id_as_is=entty_id_to_be WHERE coalesce(cast(flln_ang_nrrw_dfntn_as_is AS string),'')<>coalesce(cast(flln_ang_nrrw_dfntn_to_be AS string),'') ) A Union all | P60: =+P59+1 -> 1
B61: ENTTY | C61: =_xlfn.CONCAT(Instruções!$D$13,".",VLOOKUP(B61,Instruções!$F$12:$H$17,2,0)) -> cd_loan_tapes_bce.lt003_entity | D61: =_xlfn.CONCAT(Instruções!$D$14,".",VLOOKUP(B61,Instruções!$F$12:$H$17,3,0)) -> bu_loantape_work.lt003_entity | E61: fr_csh_flw | F61: =E61&"_"&$F$7 -> fr_csh_flw_as_is | G61: =E61&"_"&$G$7 -> fr_csh_flw_to_be | H61: =IF(VLOOKUP(B61,Instruções!$F$13:$J$17,5,0)="", "(SELECT "&VLOOKUP(B61,Instruções!$F$13:$J$17,4,0)&" as "&VLOOKUP(B61,Instruções!$F$13:$J$17,4,0)&"_"&$F$2&", "&E61&" as "&F61&" FROM "&C61&" WHERE "&Instruções!$D$20&") A ", "(SELECT "&VLOOKUP(B61,Instruções!$F$13:$J$17,4,0)&" as "&VLOOKUP(B61,Instruções!$F$13:$J$17,4,0)&"_"&$F$2&", "&VLOOKUP(B61,Instruções!$F$13:$J$17,5,0)&" as "&VLOOKUP(B61,Instruções!$F$13:$J$17,5,0)&"_"&$F$2&","&E61&" as "&F61&" FROM "&C61&" WHERE "&Instruções!$D$20&") A ") -> (SELECT entty_id as entty_id_, fr_csh_flw as fr_csh_flw_as_is FROM cd_loan_tapes_bce.lt003_entity WHERE ref_date='2024-09-30' AND nome_perimetro='Individual Corporativo' AND segmento='ESTR' AND ambito='PM' AND entidade='00100' ) A | I61: =IF(VLOOKUP(B61,Instruções!$F$13:$J$17,5,0)="", "(SELECT "&VLOOKUP(B61,Instruções!$F$13:$J$17,4,0)&" as "&VLOOKUP(B61,Instruções!$F$13:$J$17,4,0)&"_"&$G$2&", "&E61&" as "&G61&" FROM "&D61&" WHERE "&Instruções!$D$21&") B ", "(SELECT "&VLOOKUP(B61,Instruções!$F$13:$J$17,4,0)&" as "&VLOOKUP(B61,Instruções!$F$13:$J$17,4,0)&"_"&$G$2&", "&VLOOKUP(B61,Instruções!$F$13:$J$17,5,0)&" as "&VLOOKUP(B61,Instruções!$F$13:$J$17,5,0)&"_"&$G$2&","&E61&" as "&G61&" FROM "&D61&" WHERE "&Instruções!$D$21&") B ") -> (SELECT entty_id as entty_id_, fr_csh_flw as fr_csh_flw_to_be FROM bu_loantape_work.lt003_entity WHERE ref_date='2024-09-30' AND nome_perimetro='Individual Corporativo' AND segmento='ESTR' AND ambito='PM' AND entidade='00100' ) B | J61: =+IF(VLOOKUP(B61,Instruções!$F$13:$J$17,5,0)="", "ON "&VLOOKUP(B61,Instruções!$F$13:$J$17,4,0)&"_"&$F$7&"="&VLOOKUP(B61,Instruções!$F$13:$J$17,4,0)&"_"&$G$7&" ", "ON "&VLOOKUP(B61,Instruções!$F$13:$J$17,4,0)&"_"&$F$7&"="&VLOOKUP(B61,Instruções!$F$13:$J$17,4,0)&"_"&$G$7&" AND "&VLOOKUP(B61,Instruções!$F$13:$J$17,5,0)&"_"&$F$7&"="&VLOOKUP(B61,Instruções!$F$13:$J$17,5,0)&"_"&$G$7&" ") -> ON entty_id_as_is=entty_id_to_be | K61: ="WHERE coalesce(cast("&F61&" AS string),'')<>coalesce(cast("&G61&" AS string),'') " -> WHERE coalesce(cast(fr_csh_flw_as_is AS string),'')<>coalesce(cast(fr_csh_flw_to_be AS string),'') | L61: ="SELECT count(*) AS NUM_REG_DIF FROM "&H61&" Inner join "&I61&J61&K61 -> SELECT count(*) AS NUM_REG_DIF FROM (SELECT entty_id as entty_id_, fr_csh_flw as fr_csh_flw_as_is FROM cd_loan_tapes_bce.lt003_entity WHERE ref_date='2024-09-30' AND nome_perimetro='Individual Corporativo' AND segmento='ESTR' AND ambito='PM' AND entidade='00100' ) A Inner join (SELECT entty_id as entty_id_, fr_csh_flw as fr_csh_flw_to_be FROM bu_loantape_work.lt003_entity WHERE ref_date='2024-09-30' AND nome_perimetro='Individual Corporativo' AND segmento='ESTR' AND ambito='PM' AND entidade='00100' ) B ON entty_id_as_is=entty_id_to_be WHERE coalesce(cast(fr_csh_flw_as_is AS string),'')<>coalesce(cast(fr_csh_flw_to_be AS string),'') | M61: Validação de campos | N61: ="SELECT 'Validação de campos' as tipologia_teste, '"&VLOOKUP(B61,Instruções!$F$13:$J$17,3,0)&"' AS TABELA, '"&E61&"' AS CAMPO, '"&Instruções!$D$15&"' as ref_date, coalesce(NUM_REG_DIF, 0) AS NUM_REG_DIF FROM ("&L61&") A " -> SELECT 'Validação de campos' as tipologia_teste, 'lt003_entity' AS TABELA, 'fr_csh_flw' AS CAMPO, '2024-09-30' as ref_date, coalesce(NUM_REG_DIF, 0) AS NUM_REG_DIF FROM (SELECT count(*) AS NUM_REG_DIF FROM (SELECT entty_id as entty_id_, fr_csh_flw as fr_csh_flw_as_is FROM cd_loan_tapes_bce.lt003_entity WHERE ref_date='2024-09-30' AND nome_perimetro='Individual Corporativo' AND segmento='ESTR' AND ambito='PM' AND entidade='00100' ) A Inner join (SELECT entty_id as entty_id_, fr_csh_flw as fr_csh_flw_to_be FROM bu_loantape_work.lt003_entity WHERE ref_date='2024-09-30' AND nome_perimetro='Individual Corporativo' AND segmento='ESTR' AND ambito='PM' AND entidade='00100' ) B ON entty_id_as_is=entty_id_to_be WHERE coalesce(cast(fr_csh_flw_as_is AS string),'')<>coalesce(cast(fr_csh_flw_to_be AS string),'') ) A | O61: =IF(O62="",N61,N61&$O$8) -> SELECT 'Validação de campos' as tipologia_teste, 'lt003_entity' AS TABELA, 'fr_csh_flw' AS CAMPO, '2024-09-30' as ref_date, coalesce(NUM_REG_DIF, 0) AS NUM_REG_DIF FROM (SELECT count(*) AS NUM_REG_DIF FROM (SELECT entty_id as entty_id_, fr_csh_flw as fr_csh_flw_as_is FROM cd_loan_tapes_bce.lt003_entity WHERE ref_date='2024-09-30' AND nome_perimetro='Individual Corporativo' AND segmento='ESTR' AND ambito='PM' AND entidade='00100' ) A Inner join (SELECT entty_id as entty_id_, fr_csh_flw as fr_csh_flw_to_be FROM bu_loantape_work.lt003_entity WHERE ref_date='2024-09-30' AND nome_perimetro='Individual Corporativo' AND segmento='ESTR' AND ambito='PM' AND entidade='00100' ) B ON entty_id_as_is=entty_id_to_be WHERE coalesce(cast(fr_csh_flw_as_is AS string),'')<>coalesce(cast(fr_csh_flw_to_be AS string),'') ) A Union all | P61: =P60+1 -> 2
B62: ENTTY | C62: =_xlfn.CONCAT(Instruções!$D$13,".",VLOOKUP(B62,Instruções!$F$12:$H$17,2,0)) -> cd_loan_tapes_bce.lt003_entity | D62: =_xlfn.CONCAT(Instruções!$D$14,".",VLOOKUP(B62,Instruções!$F$12:$H$17,3,0)) -> bu_loantape_work.lt003_entity | E62: fr_csh_flw_t1 | F62: =E62&"_"&$F$7 -> fr_csh_flw_t1_as_is | G62: =E62&"_"&$G$7 -> fr_csh_flw_t1_to_be | H62: =IF(VLOOKUP(B62,Instruções!$F$13:$J$17,5,0)="", "(SELECT "&VLOOKUP(B62,Instruções!$F$13:$J$17,4,0)&" as "&VLOOKUP(B62,Instruções!$F$13:$J$17,4,0)&"_"&$F$2&", "&E62&" as "&F62&" FROM "&C62&" WHERE "&Instruções!$D$20&") A ", "(SELECT "&VLOOKUP(B62,Instruções!$F$13:$J$17,4,0)&" as "&VLOOKUP(B62,Instruções!$F$13:$J$17,4,0)&"_"&$F$2&", "&VLOOKUP(B62,Instruções!$F$13:$J$17,5,0)&" as "&VLOOKUP(B62,Instruções!$F$13:$J$17,5,0)&"_"&$F$2&","&E62&" as "&F62&" FROM "&C62&" WHERE "&Instruções!$D$20&") A ") -> (SELECT entty_id as entty_id_, fr_csh_flw_t1 as fr_csh_flw_t1_as_is FROM cd_loan_tapes_bce.lt003_entity WHERE ref_date='2024-09-30' AND nome_perimetro='Individual Corporativo' AND segmento='ESTR' AND ambito='PM' AND entidade='00100' ) A | I62: =IF(VLOOKUP(B62,Instruções!$F$13:$J$17,5,0)="", "(SELECT "&VLOOKUP(B62,Instruções!$F$13:$J$17,4,0)&" as "&VLOOKUP(B62,Instruções!$F$13:$J$17,4,0)&"_"&$G$2&", "&E62&" as "&G62&" FROM "&D62&" WHERE "&Instruções!$D$21&") B ", "(SELECT "&VLOOKUP(B62,Instruções!$F$13:$J$17,4,0)&" as "&VLOOKUP(B62,Instruções!$F$13:$J$17,4,0)&"_"&$G$2&", "&VLOOKUP(B62,Instruções!$F$13:$J$17,5,0)&" as "&VLOOKUP(B62,Instruções!$F$13:$J$17,5,0)&"_"&$G$2&","&E62&" as "&G62&" FROM "&D62&" WHERE "&Instruções!$D$21&") B ") -> (SELECT entty_id as entty_id_, fr_csh_flw_t1 as fr_csh_flw_t1_to_be FROM bu_loantape_work.lt003_entity WHERE ref_date='2024-09-30' AND nome_perimetro='Individual Corporativo' AND segmento='ESTR' AND ambito='PM' AND entidade='00100' ) B | J62: =+IF(VLOOKUP(B62,Instruções!$F$13:$J$17,5,0)="", "ON "&VLOOKUP(B62,Instruções!$F$13:$J$17,4,0)&"_"&$F$7&"="&VLOOKUP(B62,Instruções!$F$13:$J$17,4,0)&"_"&$G$7&" ", "ON "&VLOOKUP(B62,Instruções!$F$13:$J$17,4,0)&"_"&$F$7&"="&VLOOKUP(B62,Instruções!$F$13:$J$17,4,0)&"_"&$G$7&" AND "&VLOOKUP(B62,Instruções!$F$13:$J$17,5,0)&"_"&$F$7&"="&VLOOKUP(B62,Instruções!$F$13:$J$17,5,0)&"_"&$G$7&" ") -> ON entty_id_as_is=entty_id_to_be | K62: ="WHERE coalesce(cast("&F62&" AS string),'')<>coalesce(cast("&G62&" AS string),'') " -> WHERE coalesce(cast(fr_csh_flw_t1_as_is AS string),'')<>coalesce(cast(fr_csh_flw_t1_to_be AS string),'') | L62: ="SELECT count(*) AS NUM_REG_DIF FROM "&H62&" Inner join "&I62&J62&K62 -> SELECT count(*) AS NUM_REG_DIF FROM (SELECT entty_id as entty_id_, fr_csh_flw_t1 as fr_csh_flw_t1_as_is FROM cd_loan_tapes_bce.lt003_entity WHERE ref_date='2024-09-30' AND nome_perimetro='Individual Corporativo' AND segmento='ESTR' AND ambito='PM' AND entidade='00100' ) A Inner join (SELECT entty_id as entty_id_, fr_csh_flw_t1 as fr_csh_flw_t1_to_be FROM bu_loantape_work.lt003_entity WHERE ref_date='2024-09-30' AND nome_perimetro='Individual Corporativo' AND segmento='ESTR' AND ambito='PM' AND entidade='00100' ) B ON entty_id_as_is=entty_id_to_be WHERE coalesce(cast(fr_csh_flw_t1_as_is AS string),'')<>coalesce(cast(fr_csh_flw_t1_to_be AS string),'') | M62: Validação de campos | N62: ="SELECT 'Validação de campos' as tipologia_teste, '"&VLOOKUP(B62,Instruções!$F$13:$J$17,3,0)&"' AS TABELA, '"&E62&"' AS CAMPO, '"&Instruções!$D$15&"' as ref_date, coalesce(NUM_REG_DIF, 0) AS NUM_REG_DIF FROM ("&L62&") A " -> SELECT 'Validação de campos' as tipologia_teste, 'lt003_entity' AS TABELA, 'fr_csh_flw_t1' AS CAMPO, '2024-09-30' as ref_date, coalesce(NUM_REG_DIF, 0) AS NUM_REG_DIF FROM (SELECT count(*) AS NUM_REG_DIF FROM (SELECT entty_id as entty_id_, fr_csh_flw_t1 as fr_csh_flw_t1_as_is FROM cd_loan_tapes_bce.lt003_entity WHERE ref_date='2024-09-30' AND nome_perimetro='Individual Corporativo' AND segmento='ESTR' AND ambito='PM' AND entidade='00100' ) A Inner join (SELECT entty_id as entty_id_, fr_csh_flw_t1 as fr_csh_flw_t1_to_be FROM bu_loantape_work.lt003_entity WHERE ref_date='2024-09-30' AND nome_perimetro='Individual Corporativo' AND segmento='ESTR' AND ambito='PM' AND entidade='00100' ) B ON entty_id_as_is=entty_id_to_be WHERE coalesce(cast(fr_csh_flw_t1_as_is AS string),'')<>coalesce(cast(fr_csh_flw_t1_to_be AS string),'') ) A | O62: =IF(O63="",N62,N62&$O$8) -> SELECT 'Validação de campos' as tipologia_teste, 'lt003_entity' AS TABELA, 'fr_csh_flw_t1' AS CAMPO, '2024-09-30' as ref_date, coalesce(NUM_REG_DIF, 0) AS NUM_REG_DIF FROM (SELECT count(*) AS NUM_REG_DIF FROM (SELECT entty_id as entty_id_, fr_csh_flw_t1 as fr_csh_flw_t1_as_is FROM cd_loan_tapes_bce.lt003_entity WHERE ref_date='2024-09-30' AND nome_perimetro='Individual Corporativo' AND segmento='ESTR' AND ambito='PM' AND entidade='00100' ) A Inner join (SELECT entty_id as entty_id_, fr_csh_flw_t1 as fr_csh_flw_t1_to_be FROM bu_loantape_work.lt003_entity WHERE ref_date='2024-09-30' AND nome_perimetro='Individual Corporativo' AND segmento='ESTR' AND ambito='PM' AND entidade='00100' ) B ON entty_id_as_is=entty_id_to_be WHERE coalesce(cast(fr_csh_flw_t1_as_is AS string),'')<>coalesce(cast(fr_csh_flw_t1_to_be AS string),'') ) A Union all | P62: =P61+1 -> 3
B63: ENTTY | C63: =_xlfn.CONCAT(Instruções!$D$13,".",VLOOKUP(B63,Instruções!$F$12:$H$17,2,0)) -> cd_loan_tapes_bce.lt003_entity | D63: =_xlfn.CONCAT(Instruções!$D$14,".",VLOOKUP(B63,Instruções!$F$12:$H$17,3,0)) -> bu_loantape_work.lt003_entity | E63: fr_csh_flw_t2 | F63: =E63&"_"&$F$7 -> fr_csh_flw_t2_as_is | G63: =E63&"_"&$G$7 -> fr_csh_flw_t2_to_be | H63: =IF(VLOOKUP(B63,Instruções!$F$13:$J$17,5,0)="", "(SELECT "&VLOOKUP(B63,Instruções!$F$13:$J$17,4,0)&" as "&VLOOKUP(B63,Instruções!$F$13:$J$17,4,0)&"_"&$F$2&", "&E63&" as "&F63&" FROM "&C63&" WHERE "&Instruções!$D$20&") A ", "(SELECT "&VLOOKUP(B63,Instruções!$F$13:$J$17,4,0)&" as "&VLOOKUP(B63,Instruções!$F$13:$J$17,4,0)&"_"&$F$2&", "&VLOOKUP(B63,Instruções!$F$13:$J$17,5,0)&" as "&VLOOKUP(B63,Instruções!$F$13:$J$17,5,0)&"_"&$F$2&","&E63&" as "&F63&" FROM "&C63&" WHERE "&Instruções!$D$20&") A ") -> (SELECT entty_id as entty_id_, fr_csh_flw_t2 as fr_csh_flw_t2_as_is FROM cd_loan_tapes_bce.lt003_entity WHERE ref_date='2024-09-30' AND nome_perimetro='Individual Corporativo' AND segmento='ESTR' AND ambito='PM' AND entidade='00100' ) A | I63: =IF(VLOOKUP(B63,Instruções!$F$13:$J$17,5,0)="", "(SELECT "&VLOOKUP(B63,Instruções!$F$13:$J$17,4,0)&" as "&VLOOKUP(B63,Instruções!$F$13:$J$17,4,0)&"_"&$G$2&", "&E63&" as "&G63&" FROM "&D63&" WHERE "&Instruções!$D$21&") B ", "(SELECT "&VLOOKUP(B63,Instruções!$F$13:$J$17,4,0)&" as "&VLOOKUP(B63,Instruções!$F$13:$J$17,4,0)&"_"&$G$2&", "&VLOOKUP(B63,Instruções!$F$13:$J$17,5,0)&" as "&VLOOKUP(B63,Instruções!$F$13:$J$17,5,0)&"_"&$G$2&","&E63&" as "&G63&" FROM "&D63&" WHERE "&Instruções!$D$21&") B ") -> (SELECT entty_id as entty_id_, fr_csh_flw_t2 as fr_csh_flw_t2_to_be FROM bu_loantape_work.lt003_entity WHERE ref_date='2024-09-30' AND nome_perimetro='Individual Corporativo' AND segmento='ESTR' AND ambito='PM' AND entidade='00100' ) B | J63: =+IF(VLOOKUP(B63,Instruções!$F$13:$J$17,5,0)="", "ON "&VLOOKUP(B63,Instruções!$F$13:$J$17,4,0)&"_"&$F$7&"="&VLOOKUP(B63,Instruções!$F$13:$J$17,4,0)&"_"&$G$7&" ", "ON "&VLOOKUP(B63,Instruções!$F$13:$J$17,4,0)&"_"&$F$7&"="&VLOOKUP(B63,Instruções!$F$13:$J$17,4,0)&"_"&$G$7&" AND "&VLOOKUP(B63,Instruções!$F$13:$J$17,5,0)&"_"&$F$7&"="&VLOOKUP(B63,Instruções!$F$13:$J$17,5,0)&"_"&$G$7&" ") -> ON entty_id_as_is=entty_id_to_be | K63: ="WHERE coalesce(cast("&F63&" AS string),'')<>coalesce(cast("&G63&" AS string),'') " -> WHERE coalesce(cast(fr_csh_flw_t2_as_is AS string),'')<>coalesce(cast(fr_csh_flw_t2_to_be AS string),'') | L63: ="SELECT count(*) AS NUM_REG_DIF FROM "&H63&" Inner join "&I63&J63&K63 -> SELECT count(*) AS NUM_REG_DIF FROM (SELECT entty_id as entty_id_, fr_csh_flw_t2 as fr_csh_flw_t2_as_is FROM cd_loan_tapes_bce.lt003_entity WHERE ref_date='2024-09-30' AND nome_perimetro='Individual Corporativo' AND segmento='ESTR' AND ambito='PM' AND entidade='00100' ) A Inner join (SELECT entty_id as entty_id_, fr_csh_flw_t2 as fr_csh_flw_t2_to_be FROM bu_loantape_work.lt003_entity WHERE ref_date='2024-09-30' AND nome_perimetro='Individual Corporativo' AND segmento='ESTR' AND ambito='PM' AND entidade='00100' ) B ON entty_id_as_is=entty_id_to_be WHERE coalesce(cast(fr_csh_flw_t2_as_is AS string),'')<>coalesce(cast(fr_csh_flw_t2_to_be AS string),'') | M63: Validação de campos | N63: ="SELECT 'Validação de campos' as tipologia_teste, '"&VLOOKUP(B63,Instruções!$F$13:$J$17,3,0)&"' AS TABELA, '"&E63&"' AS CAMPO, '"&Instruções!$D$15&"' as ref_date, coalesce(NUM_REG_DIF, 0) AS NUM_REG_DIF FROM ("&L63&") A " -> SELECT 'Validação de campos' as tipologia_teste, 'lt003_entity' AS TABELA, 'fr_csh_flw_t2' AS CAMPO, '2024-09-30' as ref_date, coalesce(NUM_REG_DIF, 0) AS NUM_REG_DIF FROM (SELECT count(*) AS NUM_REG_DIF FROM (SELECT entty_id as entty_id_, fr_csh_flw_t2 as fr_csh_flw_t2_as_is FROM cd_loan_tapes_bce.lt003_entity WHERE ref_date='2024-09-30' AND nome_perimetro='Individual Corporativo' AND segmento='ESTR' AND ambito='PM' AND entidade='00100' ) A Inner join (SELECT entty_id as entty_id_, fr_csh_flw_t2 as fr_csh_flw_t2_to_be FROM bu_loantape_work.lt003_entity WHERE ref_date='2024-09-30' AND nome_perimetro='Individual Corporativo' AND segmento='ESTR' AND ambito='PM' AND entidade='00100' ) B ON entty_id_as_is=entty_id_to_be WHERE coalesce(cast(fr_csh_flw_t2_as_is AS string),'')<>coalesce(cast(fr_csh_flw_t2_to_be AS string),'') ) A | O63: =IF(O64="",N63,N63&$O$8) -> SELECT 'Validação de campos' as tipologia_teste, 'lt003_entity' AS TABELA, 'fr_csh_flw_t2' AS CAMPO, '2024-09-30' as ref_date, coalesce(NUM_REG_DIF, 0) AS NUM_REG_DIF FROM (SELECT count(*) AS NUM_REG_DIF FROM (SELECT entty_id as entty_id_, fr_csh_flw_t2 as fr_csh_flw_t2_as_is FROM cd_loan_tapes_bce.lt003_entity WHERE ref_date='2024-09-30' AND nome_perimetro='Individual Corporativo' AND segmento='ESTR' AND ambito='PM' AND entidade='00100' ) A Inner join (SELECT entty_id as entty_id_, fr_csh_flw_t2 as fr_csh_flw_t2_to_be FROM bu_loantape_work.lt003_entity WHERE ref_date='2024-09-30' AND nome_perimetro='Individual Corporativo' AND segmento='ESTR' AND ambito='PM' AND entidade='00100' ) B ON entty_id_as_is=entty_id_to_be WHERE coalesce(cast(fr_csh_flw_t2_as_is AS string),'')<>coalesce(cast(fr_csh_flw_t2_to_be AS string),'') ) A Union all | P63: =P62+1 -> 4
B64: ENTTY | C64: =_xlfn.CONCAT(Instruções!$D$13,".",VLOOKUP(B64,Instruções!$F$12:$H$17,2,0)) -> cd_loan_tapes_bce.lt003_entity | D64: =_xlfn.CONCAT(Instruções!$D$14,".",VLOOKUP(B64,Instruções!$F$12:$H$17,3,0)) -> bu_loantape_work.lt003_entity | E64: fr_csh_flw_t3 | F64: =E64&"_"&$F$7 -> fr_csh_flw_t3_as_is | G64: =E64&"_"&$G$7 -> fr_csh_flw_t3_to_be | H64: =IF(VLOOKUP(B64,Instruções!$F$13:$J$17,5,0)="", "(SELECT "&VLOOKUP(B64,Instruções!$F$13:$J$17,4,0)&" as "&VLOOKUP(B64,Instruções!$F$13:$J$17,4,0)&"_"&$F$2&", "&E64&" as "&F64&" FROM "&C64&" WHERE "&Instruções!$D$20&") A ", "(SELECT "&VLOOKUP(B64,Instruções!$F$13:$J$17,4,0)&" as "&VLOOKUP(B64,Instruções!$F$13:$J$17,4,0)&"_"&$F$2&", "&VLOOKUP(B64,Instruções!$F$13:$J$17,5,0)&" as "&VLOOKUP(B64,Instruções!$F$13:$J$17,5,0)&"_"&$F$2&","&E64&" as "&F64&" FROM "&C64&" WHERE "&Instruções!$D$20&") A ") -> (SELECT entty_id as entty_id_, fr_csh_flw_t3 as fr_csh_flw_t3_as_is FROM cd_loan_tapes_bce.lt003_entity WHERE ref_date='2024-09-30' AND nome_perimetro='Individual Corporativo' AND segmento='ESTR' AND ambito='PM' AND entidade='00100' ) A | I64: =IF(VLOOKUP(B64,Instruções!$F$13:$J$17,5,0)="", "(SELECT "&VLOOKUP(B64,Instruções!$F$13:$J$17,4,0)&" as "&VLOOKUP(B64,Instruções!$F$13:$J$17,4,0)&"_"&$G$2&", "&E64&" as "&G64&" FROM "&D64&" WHERE "&Instruções!$D$21&") B ", "(SELECT "&VLOOKUP(B64,Instruções!$F$13:$J$17,4,0)&" as "&VLOOKUP(B64,Instruções!$F$13:$J$17,4,0)&"_"&$G$2&", "&VLOOKUP(B64,Instruções!$F$13:$J$17,5,0)&" as "&VLOOKUP(B64,Instruções!$F$13:$J$17,5,0)&"_"&$G$2&","&E64&" as "&G64&" FROM "&D64&" WHERE "&Instruções!$D$21&") B ") -> (SELECT entty_id as entty_id_, fr_csh_flw_t3 as fr_csh_flw_t3_to_be FROM bu_loantape_work.lt003_entity WHERE ref_date='2024-09-30' AND nome_perimetro='Individual Corporativo' AND segmento='ESTR' AND ambito='PM' AND entidade='00100' ) B | J64: =+IF(VLOOKUP(B64,Instruções!$F$13:$J$17,5,0)="", "ON "&VLOOKUP(B64,Instruções!$F$13:$J$17,4,0)&"_"&$F$7&"="&VLOOKUP(B64,Instruções!$F$13:$J$17,4,0)&"_"&$G$7&" ", "ON "&VLOOKUP(B64,Instruções!$F$13:$J$17,4,0)&"_"&$F$7&"="&VLOOKUP(B64,Instruções!$F$13:$J$17,4,0)&"_"&$G$7&" AND "&VLOOKUP(B64,Instruções!$F$13:$J$17,5,0)&"_"&$F$7&"="&VLOOKUP(B64,Instruções!$F$13:$J$17,5,0)&"_"&$G$7&" ") -> ON entty_id_as_is=entty_id_to_be | K64: ="WHERE coalesce(cast("&F64&" AS string),'')<>coalesce(cast("&G64&" AS string),'') " -> WHERE coalesce(cast(fr_csh_flw_t3_as_is AS string),'')<>coalesce(cast(fr_csh_flw_t3_to_be AS string),'') | L64: ="SELECT count(*) AS NUM_REG_DIF FROM "&H64&" Inner join "&I64&J64&K64 -> SELECT count(*) AS NUM_REG_DIF FROM (SELECT entty_id as entty_id_, fr_csh_flw_t3 as fr_csh_flw_t3_as_is FROM cd_loan_tapes_bce.lt003_entity WHERE ref_date='2024-09-30' AND nome_perimetro='Individual Corporativo' AND segmento='ESTR' AND ambito='PM' AND entidade='00100' ) A Inner join (SELECT entty_id as entty_id_, fr_csh_flw_t3 as fr_csh_flw_t3_to_be FROM bu_loantape_work.lt003_entity WHERE ref_date='2024-09-30' AND nome_perimetro='Individual Corporativo' AND segmento='ESTR' AND ambito='PM' AND entidade='00100' ) B ON entty_id_as_is=entty_id_to_be WHERE coalesce(cast(fr_csh_flw_t3_as_is AS string),'')<>coalesce(cast(fr_csh_flw_t3_to_be AS string),'') | M64: Validação de campos | N64: ="SELECT 'Validação de campos' as tipologia_teste, '"&VLOOKUP(B64,Instruções!$F$13:$J$17,3,0)&"' AS TABELA, '"&E64&"' AS CAMPO, '"&Instruções!$D$15&"' as ref_date, coalesce(NUM_REG_DIF, 0) AS NUM_REG_DIF FROM ("&L64&") A " -> SELECT 'Validação de campos' as tipologia_teste, 'lt003_entity' AS TABELA, 'fr_csh_flw_t3' AS CAMPO, '2024-09-30' as ref_date, coalesce(NUM_REG_DIF, 0) AS NUM_REG_DIF FROM (SELECT count(*) AS NUM_REG_DIF FROM (SELECT entty_id as entty_id_, fr_csh_flw_t3 as fr_csh_flw_t3_as_is FROM cd_loan_tapes_bce.lt003_entity WHERE ref_date='2024-09-30' AND nome_perimetro='Individual Corporativo' AND segmento='ESTR' AND ambito='PM' AND entidade='00100' ) A Inner join (SELECT entty_id as entty_id_, fr_csh_flw_t3 as fr_csh_flw_t3_to_be FROM bu_loantape_work.lt003_entity WHERE ref_date='2024-09-30' AND nome_perimetro='Individual Corporativo' AND segmento='ESTR' AND ambito='PM' AND entidade='00100' ) B ON entty_id_as_is=entty_id_to_be WHERE coalesce(cast(fr_csh_flw_t3_as_is AS string),'')<>coalesce(cast(fr_csh_flw_t3_to_be AS string),'') ) A | O64: =IF(O65="",N64,N64&$O$8) -> SELECT 'Validação de campos' as tipologia_teste, 'lt003_entity' AS TABELA, 'fr_csh_flw_t3' AS CAMPO, '2024-09-30' as ref_date, coalesce(NUM_REG_DIF, 0) AS NUM_REG_DIF FROM (SELECT count(*) AS NUM_REG_DIF FROM (SELECT entty_id as entty_id_, fr_csh_flw_t3 as fr_csh_flw_t3_as_is FROM cd_loan_tapes_bce.lt003_entity WHERE ref_date='2024-09-30' AND nome_perimetro='Individual Corporativo' AND segmento='ESTR' AND ambito='PM' AND entidade='00100' ) A Inner join (SELECT entty_id as entty_id_, fr_csh_flw_t3 as fr_csh_flw_t3_to_be FROM bu_loantape_work.lt003_entity WHERE ref_date='2024-09-30' AND nome_perimetro='Individual Corporativo' AND segmento='ESTR' AND ambito='PM' AND entidade='00100' ) B ON entty_id_as_is=entty_id_to_be WHERE coalesce(cast(fr_csh_flw_t3_as_is AS string),'')<>coalesce(cast(fr_csh_flw_t3_to_be AS string),'') ) A Union all | P64: =P63+1 -> 5
B65: ENTTY | C65: =_xlfn.CONCAT(Instruções!$D$13,".",VLOOKUP(B65,Instruções!$F$12:$H$17,2,0)) -> cd_loan_tapes_bce.lt003_entity | D65: =_xlfn.CONCAT(Instruções!$D$14,".",VLOOKUP(B65,Instruções!$F$12:$H$17,3,0)) -> bu_loantape_work.lt003_entity | E65: gcc_prnt_id | F65: =E65&"_"&$F$7 -> gcc_prnt_id_as_is | G65: =E65&"_"&$G$7 -> gcc_prnt_id_to_be | H65: =IF(VLOOKUP(B65,Instruções!$F$13:$J$17,5,0)="", "(SELECT "&VLOOKUP(B65,Instruções!$F$13:$J$17,4,0)&" as "&VLOOKUP(B65,Instruções!$F$13:$J$17,4,0)&"_"&$F$2&", "&E65&" as "&F65&" FROM "&C65&" WHERE "&Instruções!$D$20&") A ", "(SELECT "&VLOOKUP(B65,Instruções!$F$13:$J$17,4,0)&" as "&VLOOKUP(B65,Instruções!$F$13:$J$17,4,0)&"_"&$F$2&", "&VLOOKUP(B65,Instruções!$F$13:$J$17,5,0)&" as "&VLOOKUP(B65,Instruções!$F$13:$J$17,5,0)&"_"&$F$2&","&E65&" as "&F65&" FROM "&C65&" WHERE "&Instruções!$D$20&") A ") -> (SELECT entty_id as entty_id_, gcc_prnt_id as gcc_prnt_id_as_is FROM cd_loan_tapes_bce.lt003_entity WHERE ref_date='2024-09-30' AND nome_perimetro='Individual Corporativo' AND segmento='ESTR' AND ambito='PM' AND entidade='00100' ) A | I65: =IF(VLOOKUP(B65,Instruções!$F$13:$J$17,5,0)="", "(SELECT "&VLOOKUP(B65,Instruções!$F$13:$J$17,4,0)&" as "&VLOOKUP(B65,Instruções!$F$13:$J$17,4,0)&"_"&$G$2&", "&E65&" as "&G65&" FROM "&D65&" WHERE "&Instruções!$D$21&") B ", "(SELECT "&VLOOKUP(B65,Instruções!$F$13:$J$17,4,0)&" as "&VLOOKUP(B65,Instruções!$F$13:$J$17,4,0)&"_"&$G$2&", "&VLOOKUP(B65,Instruções!$F$13:$J$17,5,0)&" as "&VLOOKUP(B65,Instruções!$F$13:$J$17,5,0)&"_"&$G$2&","&E65&" as "&G65&" FROM "&D65&" WHERE "&Instruções!$D$21&") B ") -> (SELECT entty_id as entty_id_, gcc_prnt_id as gcc_prnt_id_to_be FROM bu_loantape_work.lt003_entity WHERE ref_date='2024-09-30' AND nome_perimetro='Individual Corporativo' AND segmento='ESTR' AND ambito='PM' AND entidade='00100' ) B | J65: =+IF(VLOOKUP(B65,Instruções!$F$13:$J$17,5,0)="", "ON "&VLOOKUP(B65,Instruções!$F$13:$J$17,4,0)&"_"&$F$7&"="&VLOOKUP(B65,Instruções!$F$13:$J$17,4,0)&"_"&$G$7&" ", "ON "&VLOOKUP(B65,Instruções!$F$13:$J$17,4,0)&"_"&$F$7&"="&VLOOKUP(B65,Instruções!$F$13:$J$17,4,0)&"_"&$G$7&" AND "&VLOOKUP(B65,Instruções!$F$13:$J$17,5,0)&"_"&$F$7&"="&VLOOKUP(B65,Instruções!$F$13:$J$17,5,0)&"_"&$G$7&" ") -> ON entty_id_as_is=entty_id_to_be | K65: ="WHERE coalesce(cast("&F65&" AS string),'')<>coalesce(cast("&G65&" AS string),'') " -> WHERE coalesce(cast(gcc_prnt_id_as_is AS string),'')<>coalesce(cast(gcc_prnt_id_to_be AS string),'') | L65: ="SELECT count(*) AS NUM_REG_DIF FROM "&H65&" Inner join "&I65&J65&K65 -> SELECT count(*) AS NUM_REG_DIF FROM (SELECT entty_id as entty_id_, gcc_prnt_id as gcc_prnt_id_as_is FROM cd_loan_tapes_bce.lt003_entity WHERE ref_date='2024-09-30' AND nome_perimetro='Individual Corporativo' AND segmento='ESTR' AND ambito='PM' AND entidade='00100' ) A Inner join (SELECT entty_id as entty_id_, gcc_prnt_id as gcc_prnt_id_to_be FROM bu_loantape_work.lt003_entity WHERE ref_date='2024-09-30' AND nome_perimetro='Individual Corporativo' AND segmento='ESTR' AND ambito='PM' AND entidade='00100' ) B ON entty_id_as_is=entty_id_to_be WHERE coalesce(cast(gcc_prnt_id_as_is AS string),'')<>coalesce(cast(gcc_prnt_id_to_be AS string),'') | M65: Validação de campos | N65: ="SELECT 'Validação de campos' as tipologia_teste, '"&VLOOKUP(B65,Instruções!$F$13:$J$17,3,0)&"' AS TABELA, '"&E65&"' AS CAMPO, '"&Instruções!$D$15&"' as ref_date, coalesce(NUM_REG_DIF, 0) AS NUM_REG_DIF FROM ("&L65&") A " -> SELECT 'Validação de campos' as tipologia_teste, 'lt003_entity' AS TABELA, 'gcc_prnt_id' AS CAMPO, '2024-09-30' as ref_date, coalesce(NUM_REG_DIF, 0) AS NUM_REG_DIF FROM (SELECT count(*) AS NUM_REG_DIF FROM (SELECT entty_id as entty_id_, gcc_prnt_id as gcc_prnt_id_as_is FROM cd_loan_tapes_bce.lt003_entity WHERE ref_date='2024-09-30' AND nome_perimetro='Individual Corporativo' AND segmento='ESTR' AND ambito='PM' AND entidade='00100' ) A Inner join (SELECT entty_id as entty_id_, gcc_prnt_id as gcc_prnt_id_to_be FROM bu_loantape_work.lt003_entity WHERE ref_date='2024-09-30' AND nome_perimetro='Individual Corporativo' AND segmento='ESTR' AND ambito='PM' AND entidade='00100' ) B ON entty_id_as_is=entty_id_to_be WHERE coalesce(cast(gcc_prnt_id_as_is AS string),'')<>coalesce(cast(gcc_prnt_id_to_be AS string),'') ) A | O65: =IF(O66="",N65,N65&$O$8) -> SELECT 'Validação de campos' as tipologia_teste, 'lt003_entity' AS TABELA, 'gcc_prnt_id' AS CAMPO, '2024-09-30' as ref_date, coalesce(NUM_REG_DIF, 0) AS NUM_REG_DIF FROM (SELECT count(*) AS NUM_REG_DIF FROM (SELECT entty_id as entty_id_, gcc_prnt_id as gcc_prnt_id_as_is FROM cd_loan_tapes_bce.lt003_entity WHERE ref_date='2024-09-30' AND nome_perimetro='Individual Corporativo' AND segmento='ESTR' AND ambito='PM' AND entidade='00100' ) A Inner join (SELECT entty_id as entty_id_, gcc_prnt_id as gcc_prnt_id_to_be FROM bu_loantape_work.lt003_entity WHERE ref_date='2024-09-30' AND nome_perimetro='Individual Corporativo' AND segmento='ESTR' AND ambito='PM' AND entidade='00100' ) B ON entty_id_as_is=entty_id_to_be WHERE coalesce(cast(gcc_prnt_id_as_is AS string),'')<>coalesce(cast(gcc_prnt_id_to_be AS string),'') ) A Union all | P65: =P64+1 -> 6
B66: ENTTY | C66: =_xlfn.CONCAT(Instruções!$D$13,".",VLOOKUP(B66,Instruções!$F$12:$H$17,2,0)) -> cd_loan_tapes_bce.lt003_entity | D66: =_xlfn.CONCAT(Instruções!$D$14,".",VLOOKUP(B66,Instruções!$F$12:$H$17,3,0)) -> bu_loantape_work.lt003_entity | E66: gcc_prnt_nm | F66: =E66&"_"&$F$7 -> gcc_prnt_nm_as_is | G66: =E66&"_"&$G$7 -> gcc_prnt_nm_to_be | H66: =IF(VLOOKUP(B66,Instruções!$F$13:$J$17,5,0)="", "(SELECT "&VLOOKUP(B66,Instruções!$F$13:$J$17,4,0)&" as "&VLOOKUP(B66,Instruções!$F$13:$J$17,4,0)&"_"&$F$2&", "&E66&" as "&F66&" FROM "&C66&" WHERE "&Instruções!$D$20&") A ", "(SELECT "&VLOOKUP(B66,Instruções!$F$13:$J$17,4,0)&" as "&VLOOKUP(B66,Instruções!$F$13:$J$17,4,0)&"_"&$F$2&", "&VLOOKUP(B66,Instruções!$F$13:$J$17,5,0)&" as "&VLOOKUP(B66,Instruções!$F$13:$J$17,5,0)&"_"&$F$2&","&E66&" as "&F66&" FROM "&C66&" WHERE "&Instruções!$D$20&") A ") -> (SELECT entty_id as entty_id_, gcc_prnt_nm as gcc_prnt_nm_as_is FROM cd_loan_tapes_bce.lt003_entity WHERE ref_date='2024-09-30' AND nome_perimetro='Individual Corporativo' AND segmento='ESTR' AND ambito='PM' AND entidade='00100' ) A | I66: =IF(VLOOKUP(B66,Instruções!$F$13:$J$17,5,0)="", "(SELECT "&VLOOKUP(B66,Instruções!$F$13:$J$17,4,0)&" as "&VLOOKUP(B66,Instruções!$F$13:$J$17,4,0)&"_"&$G$2&", "&E66&" as "&G66&" FROM "&D66&" WHERE "&Instruções!$D$21&") B ", "(SELECT "&VLOOKUP(B66,Instruções!$F$13:$J$17,4,0)&" as "&VLOOKUP(B66,Instruções!$F$13:$J$17,4,0)&"_"&$G$2&", "&VLOOKUP(B66,Instruções!$F$13:$J$17,5,0)&" as "&VLOOKUP(B66,Instruções!$F$13:$J$17,5,0)&"_"&$G$2&","&E66&" as "&G66&" FROM "&D66&" WHERE "&Instruções!$D$21&") B ") -> (SELECT entty_id as entty_id_, gcc_prnt_nm as gcc_prnt_nm_to_be FROM bu_loantape_work.lt003_entity WHERE ref_date='2024-09-30' AND nome_perimetro='Individual Corporativo' AND segmento='ESTR' AND ambito='PM' AND entidade='00100' ) B | J66: =+IF(VLOOKUP(B66,Instruções!$F$13:$J$17,5,0)="", "ON "&VLOOKUP(B66,Instruções!$F$13:$J$17,4,0)&"_"&$F$7&"="&VLOOKUP(B66,Instruções!$F$13:$J$17,4,0)&"_"&$G$7&" ", "ON "&VLOOKUP(B66,Instruções!$F$13:$J$17,4,0)&"_"&$F$7&"="&VLOOKUP(B66,Instruções!$F$13:$J$17,4,0)&"_"&$G$7&" AND "&VLOOKUP(B66,Instruções!$F$13:$J$17,5,0)&"_"&$F$7&"="&VLOOKUP(B66,Instruções!$F$13:$J$17,5,0)&"_"&$G$7&" ") -> ON entty_id_as_is=entty_id_to_be | K66: ="WHERE coalesce(cast("&F66&" AS string),'')<>coalesce(cast("&G66&" AS string),'') " -> WHERE coalesce(cast(gcc_prnt_nm_as_is AS string),'')<>coalesce(cast(gcc_prnt_nm_to_be AS string),'') | L66: ="SELECT count(*) AS NUM_REG_DIF FROM "&H66&" Inner join "&I66&J66&K66 -> SELECT count(*) AS NUM_REG_DIF FROM (SELECT entty_id as entty_id_, gcc_prnt_nm as gcc_prnt_nm_as_is FROM cd_loan_tapes_bce.lt003_entity WHERE ref_date='2024-09-30' AND nome_perimetro='Individual Corporativo' AND segmento='ESTR' AND ambito='PM' AND entidade='00100' ) A Inner join (SELECT entty_id as entty_id_, gcc_prnt_nm as gcc_prnt_nm_to_be FROM bu_loantape_work.lt003_entity WHERE ref_date='2024-09-30' AND nome_perimetro='Individual Corporativo' AND segmento='ESTR' AND ambito='PM' AND entidade='00100' ) B ON entty_id_as_is=entty_id_to_be WHERE coalesce(cast(gcc_prnt_nm_as_is AS string),'')<>coalesce(cast(gcc_prnt_nm_to_be AS string),'') | M66: Validação de campos | N66: ="SELECT 'Validação de campos' as tipologia_teste, '"&VLOOKUP(B66,Instruções!$F$13:$J$17,3,0)&"' AS TABELA, '"&E66&"' AS CAMPO, '"&Instruções!$D$15&"' as ref_date, coalesce(NUM_REG_DIF, 0) AS NUM_REG_DIF FROM ("&L66&") A " -> SELECT 'Validação de campos' as tipologia_teste, 'lt003_entity' AS TABELA, 'gcc_prnt_nm' AS CAMPO, '2024-09-30' as ref_date, coalesce(NUM_REG_DIF, 0) AS NUM_REG_DIF FROM (SELECT count(*) AS NUM_REG_DIF FROM (SELECT entty_id as entty_id_, gcc_prnt_nm as gcc_prnt_nm_as_is FROM cd_loan_tapes_bce.lt003_entity WHERE ref_date='2024-09-30' AND nome_perimetro='Individual Corporativo' AND segmento='ESTR' AND ambito='PM' AND entidade='00100' ) A Inner join (SELECT entty_id as entty_id_, gcc_prnt_nm as gcc_prnt_nm_to_be FROM bu_loantape_work.lt003_entity WHERE ref_date='2024-09-30' AND nome_perimetro='Individual Corporativo' AND segmento='ESTR' AND ambito='PM' AND entidade='00100' ) B ON entty_id_as_is=entty_id_to_be WHERE coalesce(cast(gcc_prnt_nm_as_is AS string),'')<>coalesce(cast(gcc_prnt_nm_to_be AS string),'') ) A | O66: =IF(O67="",N66,N66&$O$8) -> SELECT 'Validação de campos' as tipologia_teste, 'lt003_entity' AS TABELA, 'gcc_prnt_nm' AS CAMPO, '2024-09-30' as ref_date, coalesce(NUM_REG_DIF, 0) AS NUM_REG_DIF FROM (SELECT count(*) AS NUM_REG_DIF FROM (SELECT entty_id as entty_id_, gcc_prnt_nm as gcc_prnt_nm_as_is FROM cd_loan_tapes_bce.lt003_entity WHERE ref_date='2024-09-30' AND nome_perimetro='Individual Corporativo' AND segmento='ESTR' AND ambito='PM' AND entidade='00100' ) A Inner join (SELECT entty_id as entty_id_, gcc_prnt_nm as gcc_prnt_nm_to_be FROM bu_loantape_work.lt003_entity WHERE ref_date='2024-09-30' AND nome_perimetro='Individual Corporativo' AND segmento='ESTR' AND ambito='PM' AND entidade='00100' ) B ON entty_id_as_is=entty_id_to_be WHERE coalesce(cast(gcc_prnt_nm_as_is AS string),'')<>coalesce(cast(gcc_prnt_nm_to_be AS string),'') ) A Union all | P66: =P65+1 -> 7
B67: ENTTY | C67: =_xlfn.CONCAT(Instruções!$D$13,".",VLOOKUP(B67,Instruções!$F$12:$H$17,2,0)) -> cd_loan_tapes_bce.lt003_entity | D67: =_xlfn.CONCAT(Instruções!$D$14,".",VLOOKUP(B67,Instruções!$F$12:$H$17,3,0)) -> bu_loantape_work.lt003_entity | E67: gdwill | F67: =E67&"_"&$F$7 -> gdwill_as_is | G67: =E67&"_"&$G$7 -> gdwill_to_be | H67: =IF(VLOOKUP(B67,Instruções!$F$13:$J$17,5,0)="", "(SELECT "&VLOOKUP(B67,Instruções!$F$13:$J$17,4,0)&" as "&VLOOKUP(B67,Instruções!$F$13:$J$17,4,0)&"_"&$F$2&", "&E67&" as "&F67&" FROM "&C67&" WHERE "&Instruções!$D$20&") A ", "(SELECT "&VLOOKUP(B67,Instruções!$F$13:$J$17,4,0)&" as "&VLOOKUP(B67,Instruções!$F$13:$J$17,4,0)&"_"&$F$2&", "&VLOOKUP(B67,Instruções!$F$13:$J$17,5,0)&" as "&VLOOKUP(B67,Instruções!$F$13:$J$17,5,0)&"_"&$F$2&","&E67&" as "&F67&" FROM "&C67&" WHERE "&Instruções!$D$20&") A ") -> (SELECT entty_id as entty_id_, gdwill as gdwill_as_is FROM cd_loan_tapes_bce.lt003_entity WHERE ref_date='2024-09-30' AND nome_perimetro='Individual Corporativo' AND segmento='ESTR' AND ambito='PM' AND entidade='00100' ) A | I67: =IF(VLOOKUP(B67,Instruções!$F$13:$J$17,5,0)="", "(SELECT "&VLOOKUP(B67,Instruções!$F$13:$J$17,4,0)&" as "&VLOOKUP(B67,Instruções!$F$13:$J$17,4,0)&"_"&$G$2&", "&E67&" as "&G67&" FROM "&D67&" WHERE "&Instruções!$D$21&") B ", "(SELECT "&VLOOKUP(B67,Instruções!$F$13:$J$17,4,0)&" as "&VLOOKUP(B67,Instruções!$F$13:$J$17,4,0)&"_"&$G$2&", "&VLOOKUP(B67,Instruções!$F$13:$J$17,5,0)&" as "&VLOOKUP(B67,Instruções!$F$13:$J$17,5,0)&"_"&$G$2&","&E67&" as "&G67&" FROM "&D67&" WHERE "&Instruções!$D$21&") B ") -> (SELECT entty_id as entty_id_, gdwill as gdwill_to_be FROM bu_loantape_work.lt003_entity WHERE ref_date='2024-09-30' AND nome_perimetro='Individual Corporativo' AND segmento='ESTR' AND ambito='PM' AND entidade='00100' ) B | J67: =+IF(VLOOKUP(B67,Instruções!$F$13:$J$17,5,0)="", "ON "&VLOOKUP(B67,Instruções!$F$13:$J$17,4,0)&"_"&$F$7&"="&VLOOKUP(B67,Instruções!$F$13:$J$17,4,0)&"_"&$G$7&" ", "ON "&VLOOKUP(B67,Instruções!$F$13:$J$17,4,0)&"_"&$F$7&"="&VLOOKUP(B67,Instruções!$F$13:$J$17,4,0)&"_"&$G$7&" AND "&VLOOKUP(B67,Instruções!$F$13:$J$17,5,0)&"_"&$F$7&"="&VLOOKUP(B67,Instruções!$F$13:$J$17,5,0)&"_"&$G$7&" ") -> ON entty_id_as_is=entty_id_to_be | K67: ="WHERE coalesce(cast("&F67&" AS string),'')<>coalesce(cast("&G67&" AS string),'') " -> WHERE coalesce(cast(gdwill_as_is AS string),'')<>coalesce(cast(gdwill_to_be AS string),'') | L67: ="SELECT count(*) AS NUM_REG_DIF FROM "&H67&" Inner join "&I67&J67&K67 -> SELECT count(*) AS NUM_REG_DIF FROM (SELECT entty_id as entty_id_, gdwill as gdwill_as_is FROM cd_loan_tapes_bce.lt003_entity WHERE ref_date='2024-09-30' AND nome_perimetro='Individual Corporativo' AND segmento='ESTR' AND ambito='PM' AND entidade='00100' ) A Inner join (SELECT entty_id as entty_id_, gdwill as gdwill_to_be FROM bu_loantape_work.lt003_entity WHERE ref_date='2024-09-30' AND nome_perimetro='Individual Corporativo' AND segmento='ESTR' AND ambito='PM' AND entidade='00100' ) B ON entty_id_as_is=entty_id_to_be WHERE coalesce(cast(gdwill_as_is AS string),'')<>coalesce(cast(gdwill_to_be AS string),'') | M67: Validação de campos | N67: ="SELECT 'Validação de campos' as tipologia_teste, '"&VLOOKUP(B67,Instruções!$F$13:$J$17,3,0)&"' AS TABELA, '"&E67&"' AS CAMPO, '"&Instruções!$D$15&"' as ref_date, coalesce(NUM_REG_DIF, 0) AS NUM_REG_DIF FROM ("&L67&") A " -> SELECT 'Validação de campos' as tipologia_teste, 'lt003_entity' AS TABELA, 'gdwill' AS CAMPO, '2024-09-30' as ref_date, coalesce(NUM_REG_DIF, 0) AS NUM_REG_DIF FROM (SELECT count(*) AS NUM_REG_DIF FROM (SELECT entty_id as entty_id_, gdwill as gdwill_as_is FROM cd_loan_tapes_bce.lt003_entity WHERE ref_date='2024-09-30' AND nome_perimetro='Individual Corporativo' AND segmento='ESTR' AND ambito='PM' AND entidade='00100' ) A Inner join (SELECT entty_id as entty_id_, gdwill as gdwill_to_be FROM bu_loantape_work.lt003_entity WHERE ref_date='2024-09-30' AND nome_perimetro='Individual Corporativo' AND segmento='ESTR' AND ambito='PM' AND entidade='00100' ) B ON entty_id_as_is=entty_id_to_be WHERE coalesce(cast(gdwill_as_is AS string),'')<>coalesce(cast(gdwill_to_be AS string),'') ) A | O67: =IF(O68="",N67,N67&$O$8) -> SELECT 'Validação de campos' as tipologia_teste, 'lt003_entity' AS TABELA, 'gdwill' AS CAMPO, '2024-09-30' as ref_date, coalesce(NUM_REG_DIF, 0) AS NUM_REG_DIF FROM (SELECT count(*) AS NUM_REG_DIF FROM (SELECT entty_id as entty_id_, gdwill as gdwill_as_is FROM cd_loan_tapes_bce.lt003_entity WHERE ref_date='2024-09-30' AND nome_perimetro='Individual Corporativo' AND segmento='ESTR' AND ambito='PM' AND entidade='00100' ) A Inner join (SELECT entty_id as entty_id_, gdwill as gdwill_to_be FROM bu_loantape_work.lt003_entity WHERE ref_date='2024-09-30' AND nome_perimetro='Individual Corporativo' AND segmento='ESTR' AND ambito='PM' AND entidade='00100' ) B ON entty_id_as_is=entty_id_to_be WHERE coalesce(cast(gdwill_as_is AS string),'')<>coalesce(cast(gdwill_to_be AS string),'') ) A Union all | P67: =P66+1 -> 8
B68: ENTTY | C68: =_xlfn.CONCAT(Instruções!$D$13,".",VLOOKUP(B68,Instruções!$F$12:$H$17,2,0)) -> cd_loan_tapes_bce.lt003_entity | D68: =_xlfn.CONCAT(Instruções!$D$14,".",VLOOKUP(B68,Instruções!$F$12:$H$17,3,0)) -> bu_loantape_work.lt003_entity | E68: gdwill_prvs | F68: =E68&"_"&$F$7 -> gdwill_prvs_as_is | G68: =E68&"_"&$G$7 -> gdwill_prvs_to_be | H68: =IF(VLOOKUP(B68,Instruções!$F$13:$J$17,5,0)="", "(SELECT "&VLOOKUP(B68,Instruções!$F$13:$J$17,4,0)&" as "&VLOOKUP(B68,Instruções!$F$13:$J$17,4,0)&"_"&$F$2&", "&E68&" as "&F68&" FROM "&C68&" WHERE "&Instruções!$D$20&") A ", "(SELECT "&VLOOKUP(B68,Instruções!$F$13:$J$17,4,0)&" as "&VLOOKUP(B68,Instruções!$F$13:$J$17,4,0)&"_"&$F$2&", "&VLOOKUP(B68,Instruções!$F$13:$J$17,5,0)&" as "&VLOOKUP(B68,Instruções!$F$13:$J$17,5,0)&"_"&$F$2&","&E68&" as "&F68&" FROM "&C68&" WHERE "&Instruções!$D$20&") A ") -> (SELECT entty_id as entty_id_, gdwill_prvs as gdwill_prvs_as_is FROM cd_loan_tapes_bce.lt003_entity WHERE ref_date='2024-09-30' AND nome_perimetro='Individual Corporativo' AND segmento='ESTR' AND ambito='PM' AND entidade='00100' ) A | I68: =IF(VLOOKUP(B68,Instruções!$F$13:$J$17,5,0)="", "(SELECT "&VLOOKUP(B68,Instruções!$F$13:$J$17,4,0)&" as "&VLOOKUP(B68,Instruções!$F$13:$J$17,4,0)&"_"&$G$2&", "&E68&" as "&G68&" FROM "&D68&" WHERE "&Instruções!$D$21&") B ", "(SELECT "&VLOOKUP(B68,Instruções!$F$13:$J$17,4,0)&" as "&VLOOKUP(B68,Instruções!$F$13:$J$17,4,0)&"_"&$G$2&", "&VLOOKUP(B68,Instruções!$F$13:$J$17,5,0)&" as "&VLOOKUP(B68,Instruções!$F$13:$J$17,5,0)&"_"&$G$2&","&E68&" as "&G68&" FROM "&D68&" WHERE "&Instruções!$D$21&") B ") -> (SELECT entty_id as entty_id_, gdwill_prvs as gdwill_prvs_to_be FROM bu_loantape_work.lt003_entity WHERE ref_date='2024-09-30' AND nome_perimetro='Individual Corporativo' AND segmento='ESTR' AND ambito='PM' AND entidade='00100' ) B | J68: =+IF(VLOOKUP(B68,Instruções!$F$13:$J$17,5,0)="", "ON "&VLOOKUP(B68,Instruções!$F$13:$J$17,4,0)&"_"&$F$7&"="&VLOOKUP(B68,Instruções!$F$13:$J$17,4,0)&"_"&$G$7&" ", "ON "&VLOOKUP(B68,Instruções!$F$13:$J$17,4,0)&"_"&$F$7&"="&VLOOKUP(B68,Instruções!$F$13:$J$17,4,0)&"_"&$G$7&" AND "&VLOOKUP(B68,Instruções!$F$13:$J$17,5,0)&"_"&$F$7&"="&VLOOKUP(B68,Instruções!$F$13:$J$17,5,0)&"_"&$G$7&" ") -> ON entty_id_as_is=entty_id_to_be | K68: ="WHERE coalesce(cast("&F68&" AS string),'')<>coalesce(cast("&G68&" AS string),'') " -> WHERE coalesce(cast(gdwill_prvs_as_is AS string),'')<>coalesce(cast(gdwill_prvs_to_be AS string),'') | L68: ="SELECT count(*) AS NUM_REG_DIF FROM "&H68&" Inner join "&I68&J68&K68 -> SELECT count(*) AS NUM_REG_DIF FROM (SELECT entty_id as entty_id_, gdwill_prvs as gdwill_prvs_as_is FROM cd_loan_tapes_bce.lt003_entity WHERE ref_date='2024-09-30' AND nome_perimetro='Individual Corporativo' AND segmento='ESTR' AND ambito='PM' AND entidade='00100' ) A Inner join (SELECT entty_id as entty_id_, gdwill_prvs as gdwill_prvs_to_be FROM bu_loantape_work.lt003_entity WHERE ref_date='2024-09-30' AND nome_perimetro='Individual Corporativo' AND segmento='ESTR' AND ambito='PM' AND entidade='00100' ) B ON entty_id_as_is=entty_id_to_be WHERE coalesce(cast(gdwill_prvs_as_is AS string),'')<>coalesce(cast(gdwill_prvs_to_be AS string),'') | M68: Validação de campos | N68: ="SELECT 'Validação de campos' as tipologia_teste, '"&VLOOKUP(B68,Instruções!$F$13:$J$17,3,0)&"' AS TABELA, '"&E68&"' AS CAMPO, '"&Instruções!$D$15&"' as ref_date, coalesce(NUM_REG_DIF, 0) AS NUM_REG_DIF FROM ("&L68&") A " -> SELECT 'Validação de campos' as tipologia_teste, 'lt003_entity' AS TABELA, 'gdwill_prvs' AS CAMPO, '2024-09-30' as ref_date, coalesce(NUM_REG_DIF, 0) AS NUM_REG_DIF FROM (SELECT count(*) AS NUM_REG_DIF FROM (SELECT entty_id as entty_id_, gdwill_prvs as gdwill_prvs_as_is FROM cd_loan_tapes_bce.lt003_entity WHERE ref_date='2024-09-30' AND nome_perimetro='Individual Corporativo' AND segmento='ESTR' AND ambito='PM' AND entidade='00100' ) A Inner join (SELECT entty_id as entty_id_, gdwill_prvs as gdwill_prvs_to_be FROM bu_loantape_work.lt003_entity WHERE ref_date='2024-09-30' AND nome_perimetro='Individual Corporativo' AND segmento='ESTR' AND ambito='PM' AND entidade='00100' ) B ON entty_id_as_is=entty_id_to_be WHERE coalesce(cast(gdwill_prvs_as_is AS string),'')<>coalesce(cast(gdwill_prvs_to_be AS string),'') ) A | O68: =IF(O69="",N68,N68&$O$8) -> SELECT 'Validação de campos' as tipologia_teste, 'lt003_entity' AS TABELA, 'gdwill_prvs' AS CAMPO, '2024-09-30' as ref_date, coalesce(NUM_REG_DIF, 0) AS NUM_REG_DIF FROM (SELECT count(*) AS NUM_REG_DIF FROM (SELECT entty_id as entty_id_, gdwill_prvs as gdwill_prvs_as_is FROM cd_loan_tapes_bce.lt003_entity WHERE ref_date='2024-09-30' AND nome_perimetro='Individual Corporativo' AND segmento='ESTR' AND ambito='PM' AND entidade='00100' ) A Inner join (SELECT entty_id as entty_id_, gdwill_prvs as gdwill_prvs_to_be FROM bu_loantape_work.lt003_entity WHERE ref_date='2024-09-30' AND nome_perimetro='Individual Corporativo' AND segmento='ESTR' AND ambito='PM' AND entidade='00100' ) B ON entty_id_as_is=entty_id_to_be WHERE coalesce(cast(gdwill_prvs_as_is AS string),'')<>coalesce(cast(gdwill_prvs_to_be AS string),'') ) A Union all | P68: =P67+1 -> 9
B69: ENTTY | C69: =_xlfn.CONCAT(Instruções!$D$13,".",VLOOKUP(B69,Instruções!$F$12:$H$17,2,0)) -> cd_loan_tapes_bce.lt003_entity | D69: =_xlfn.CONCAT(Instruções!$D$14,".",VLOOKUP(B69,Instruções!$F$12:$H$17,3,0)) -> bu_loantape_work.lt003_entity | E69: grp_ebitda | F69: =E69&"_"&$F$7 -> grp_ebitda_as_is | G69: =E69&"_"&$G$7 -> grp_ebitda_to_be | H69: =IF(VLOOKUP(B69,Instruções!$F$13:$J$17,5,0)="", "(SELECT "&VLOOKUP(B69,Instruções!$F$13:$J$17,4,0)&" as "&VLOOKUP(B69,Instruções!$F$13:$J$17,4,0)&"_"&$F$2&", "&E69&" as "&F69&" FROM "&C69&" WHERE "&Instruções!$D$20&") A ", "(SELECT "&VLOOKUP(B69,Instruções!$F$13:$J$17,4,0)&" as "&VLOOKUP(B69,Instruções!$F$13:$J$17,4,0)&"_"&$F$2&", "&VLOOKUP(B69,Instruções!$F$13:$J$17,5,0)&" as "&VLOOKUP(B69,Instruções!$F$13:$J$17,5,0)&"_"&$F$2&","&E69&" as "&F69&" FROM "&C69&" WHERE "&Instruções!$D$20&") A ") -> (SELECT entty_id as entty_id_, grp_ebitda as grp_ebitda_as_is FROM cd_loan_tapes_bce.lt003_entity WHERE ref_date='2024-09-30' AND nome_perimetro='Individual Corporativo' AND segmento='ESTR' AND ambito='PM' AND entidade='00100' ) A | I69: =IF(VLOOKUP(B69,Instruções!$F$13:$J$17,5,0)="", "(SELECT "&VLOOKUP(B69,Instruções!$F$13:$J$17,4,0)&" as "&VLOOKUP(B69,Instruções!$F$13:$J$17,4,0)&"_"&$G$2&", "&E69&" as "&G69&" FROM "&D69&" WHERE "&Instruções!$D$21&") B ", "(SELECT "&VLOOKUP(B69,Instruções!$F$13:$J$17,4,0)&" as "&VLOOKUP(B69,Instruções!$F$13:$J$17,4,0)&"_"&$G$2&", "&VLOOKUP(B69,Instruções!$F$13:$J$17,5,0)&" as "&VLOOKUP(B69,Instruções!$F$13:$J$17,5,0)&"_"&$G$2&","&E69&" as "&G69&" FROM "&D69&" WHERE "&Instruções!$D$21&") B ") -> (SELECT entty_id as entty_id_, grp_ebitda as grp_ebitda_to_be FROM bu_loantape_work.lt003_entity WHERE ref_date='2024-09-30' AND nome_perimetro='Individual Corporativo' AND segmento='ESTR' AND ambito='PM' AND entidade='00100' ) B | J69: =+IF(VLOOKUP(B69,Instruções!$F$13:$J$17,5,0)="", "ON "&VLOOKUP(B69,Instruções!$F$13:$J$17,4,0)&"_"&$F$7&"="&VLOOKUP(B69,Instruções!$F$13:$J$17,4,0)&"_"&$G$7&" ", "ON "&VLOOKUP(B69,Instruções!$F$13:$J$17,4,0)&"_"&$F$7&"="&VLOOKUP(B69,Instruções!$F$13:$J$17,4,0)&"_"&$G$7&" AND "&VLOOKUP(B69,Instruções!$F$13:$J$17,5,0)&"_"&$F$7&"="&VLOOKUP(B69,Instruções!$F$13:$J$17,5,0)&"_"&$G$7&" ") -> ON entty_id_as_is=entty_id_to_be | K69: ="WHERE coalesce(cast("&F69&" AS string),'')<>coalesce(cast("&G69&" AS string),'') " -> WHERE coalesce(cast(grp_ebitda_as_is AS string),'')<>coalesce(cast(grp_ebitda_to_be AS string),'') | L69: ="SELECT count(*) AS NUM_REG_DIF FROM "&H69&" Inner join "&I69&J69&K69 -> SELECT count(*) AS NUM_REG_DIF FROM (SELECT entty_id as entty_id_, grp_ebitda as grp_ebitda_as_is FROM cd_loan_tapes_bce.lt003_entity WHERE ref_date='2024-09-30' AND nome_perimetro='Individual Corporativo' AND segmento='ESTR' AND ambito='PM' AND entidade='00100' ) A Inner join (SELECT entty_id as entty_id_, grp_ebitda as grp_ebitda_to_be FROM bu_loantape_work.lt003_entity WHERE ref_date='2024-09-30' AND nome_perimetro='Individual Corporativo' AND segmento='ESTR' AND ambito='PM' AND entidade='00100' ) B ON entty_id_as_is=entty_id_to_be WHERE coalesce(cast(grp_ebitda_as_is AS string),'')<>coalesce(cast(grp_ebitda_to_be AS string),'') | M69: Validação de campos | N69: ="SELECT 'Validação de campos' as tipologia_teste, '"&VLOOKUP(B69,Instruções!$F$13:$J$17,3,0)&"' AS TABELA, '"&E69&"' AS CAMPO, '"&Instruções!$D$15&"' as ref_date, coalesce(NUM_REG_DIF, 0) AS NUM_REG_DIF FROM ("&L69&") A " -> SELECT 'Validação de campos' as tipologia_teste, 'lt003_entity' AS TABELA, 'grp_ebitda' AS CAMPO, '2024-09-30' as ref_date, coalesce(NUM_REG_DIF, 0) AS NUM_REG_DIF FROM (SELECT count(*) AS NUM_REG_DIF FROM (SELECT entty_id as entty_id_, grp_ebitda as grp_ebitda_as_is FROM cd_loan_tapes_bce.lt003_entity WHERE ref_date='2024-09-30' AND nome_perimetro='Individual Corporativo' AND segmento='ESTR' AND ambito='PM' AND entidade='00100' ) A Inner join (SELECT entty_id as entty_id_, grp_ebitda as grp_ebitda_to_be FROM bu_loantape_work.lt003_entity WHERE ref_date='2024-09-30' AND nome_perimetro='Individual Corporativo' AND segmento='ESTR' AND ambito='PM' AND entidade='00100' ) B ON entty_id_as_is=entty_id_to_be WHERE coalesce(cast(grp_ebitda_as_is AS string),'')<>coalesce(cast(grp_ebitda_to_be AS string),'') ) A | O69: =IF(O70="",N69,N69&$O$8) -> SELECT 'Validação de campos' as tipologia_teste, 'lt003_entity' AS TABELA, 'grp_ebitda' AS CAMPO, '2024-09-30' as ref_date, coalesce(NUM_REG_DIF, 0) AS NUM_REG_DIF FROM (SELECT count(*) AS NUM_REG_DIF FROM (SELECT entty_id as entty_id_, grp_ebitda as grp_ebitda_as_is FROM cd_loan_tapes_bce.lt003_entity WHERE ref_date='2024-09-30' AND nome_perimetro='Individual Corporativo' AND segmento='ESTR' AND ambito='PM' AND entidade='00100' ) A Inner join (SELECT entty_id as entty_id_, grp_ebitda as grp_ebitda_to_be FROM bu_loantape_work.lt003_entity WHERE ref_date='2024-09-30' AND nome_perimetro='Individual Corporativo' AND segmento='ESTR' AND ambito='PM' AND entidade='00100' ) B ON entty_id_as_is=entty_id_to_be WHERE coalesce(cast(grp_ebitda_as_is AS string),'')<>coalesce(cast(grp_ebitda_to_be AS string),'') ) A Union all | P69: =P68+1 -> 10
B70: ENTTY | C70: =_xlfn.CONCAT(Instruções!$D$13,".",VLOOKUP(B70,Instruções!$F$12:$H$17,2,0)) -> cd_loan_tapes_bce.lt003_entity | D70: =_xlfn.CONCAT(Instruções!$D$14,".",VLOOKUP(B70,Instruções!$F$12:$H$17,3,0)) -> bu_loantape_work.lt003_entity | E70: grp_eqty | F70: =E70&"_"&$F$7 -> grp_eqty_as_is | G70: =E70&"_"&$G$7 -> grp_eqty_to_be | H70: =IF(VLOOKUP(B70,Instruções!$F$13:$J$17,5,0)="", "(SELECT "&VLOOKUP(B70,Instruções!$F$13:$J$17,4,0)&" as "&VLOOKUP(B70,Instruções!$F$13:$J$17,4,0)&"_"&$F$2&", "&E70&" as "&F70&" FROM "&C70&" WHERE "&Instruções!$D$20&") A ", "(SELECT "&VLOOKUP(B70,Instruções!$F$13:$J$17,4,0)&" as "&VLOOKUP(B70,Instruções!$F$13:$J$17,4,0)&"_"&$F$2&", "&VLOOKUP(B70,Instruções!$F$13:$J$17,5,0)&" as "&VLOOKUP(B70,Instruções!$F$13:$J$17,5,0)&"_"&$F$2&","&E70&" as "&F70&" FROM "&C70&" WHERE "&Instruções!$D$20&") A ") -> (SELECT entty_id as entty_id_, grp_eqty as grp_eqty_as_is FROM cd_loan_tapes_bce.lt003_entity WHERE ref_date='2024-09-30' AND nome_perimetro='Individual Corporativo' AND segmento='ESTR' AND ambito='PM' AND entidade='00100' ) A | I70: =IF(VLOOKUP(B70,Instruções!$F$13:$J$17,5,0)="", "(SELECT "&VLOOKUP(B70,Instruções!$F$13:$J$17,4,0)&" as "&VLOOKUP(B70,Instruções!$F$13:$J$17,4,0)&"_"&$G$2&", "&E70&" as "&G70&" FROM "&D70&" WHERE "&Instruções!$D$21&") B ", "(SELECT "&VLOOKUP(B70,Instruções!$F$13:$J$17,4,0)&" as "&VLOOKUP(B70,Instruções!$F$13:$J$17,4,0)&"_"&$G$2&", "&VLOOKUP(B70,Instruções!$F$13:$J$17,5,0)&" as "&VLOOKUP(B70,Instruções!$F$13:$J$17,5,0)&"_"&$G$2&","&E70&" as "&G70&" FROM "&D70&" WHERE "&Instruções!$D$21&") B ") -> (SELECT entty_id as entty_id_, grp_eqty as grp_eqty_to_be FROM bu_loantape_work.lt003_entity WHERE ref_date='2024-09-30' AND nome_perimetro='Individual Corporativo' AND segmento='ESTR' AND ambito='PM' AND entidade='00100' ) B | J70: =+IF(VLOOKUP(B70,Instruções!$F$13:$J$17,5,0)="", "ON "&VLOOKUP(B70,Instruções!$F$13:$J$17,4,0)&"_"&$F$7&"="&VLOOKUP(B70,Instruções!$F$13:$J$17,4,0)&"_"&$G$7&" ", "ON "&VLOOKUP(B70,Instruções!$F$13:$J$17,4,0)&"_"&$F$7&"="&VLOOKUP(B70,Instruções!$F$13:$J$17,4,0)&"_"&$G$7&" AND "&VLOOKUP(B70,Instruções!$F$13:$J$17,5,0)&"_"&$F$7&"="&VLOOKUP(B70,Instruções!$F$13:$J$17,5,0)&"_"&$G$7&" ") -> ON entty_id_as_is=entty_id_to_be | K70: ="WHERE coalesce(cast("&F70&" AS string),'')<>coalesce(cast("&G70&" AS string),'') " -> WHERE coalesce(cast(grp_eqty_as_is AS string),'')<>coalesce(cast(grp_eqty_to_be AS string),'') | L70: ="SELECT count(*) AS NUM_REG_DIF FROM "&H70&" Inner join "&I70&J70&K70 -> SELECT count(*) AS NUM_REG_DIF FROM (SELECT entty_id as entty_id_, grp_eqty as grp_eqty_as_is FROM cd_loan_tapes_bce.lt003_entity WHERE ref_date='2024-09-30' AND nome_perimetro='Individual Corporativo' AND segmento='ESTR' AND ambito='PM' AND entidade='00100' ) A Inner join (SELECT entty_id as entty_id_, grp_eqty as grp_eqty_to_be FROM bu_loantape_work.lt003_entity WHERE ref_date='2024-09-30' AND nome_perimetro='Individual Corporativo' AND segmento='ESTR' AND ambito='PM' AND entidade='00100' ) B ON entty_id_as_is=entty_id_to_be WHERE coalesce(cast(grp_eqty_as_is AS string),'')<>coalesce(cast(grp_eqty_to_be AS string),'') | M70: Validação de campos | N70: ="SELECT 'Validação de campos' as tipologia_teste, '"&VLOOKUP(B70,Instruções!$F$13:$J$17,3,0)&"' AS TABELA, '"&E70&"' AS CAMPO, '"&Instruções!$D$15&"' as ref_date, coalesce(NUM_REG_DIF, 0) AS NUM_REG_DIF FROM ("&L70&") A " -> SELECT 'Validação de campos' as tipologia_teste, 'lt003_entity' AS TABELA, 'grp_eqty' AS CAMPO, '2024-09-30' as ref_date, coalesce(NUM_REG_DIF, 0) AS NUM_REG_DIF FROM (SELECT count(*) AS NUM_REG_DIF FROM (SELECT entty_id as entty_id_, grp_eqty as grp_eqty_as_is FROM cd_loan_tapes_bce.lt003_entity WHERE ref_date='2024-09-30' AND nome_perimetro='Individual Corporativo' AND segmento='ESTR' AND ambito='PM' AND entidade='00100' ) A Inner join (SELECT entty_id as entty_id_, grp_eqty as grp_eqty_to_be FROM bu_loantape_work.lt003_entity WHERE ref_date='2024-09-30' AND nome_perimetro='Individual Corporativo' AND segmento='ESTR' AND ambito='PM' AND entidade='00100' ) B ON entty_id_as_is=entty_id_to_be WHERE coalesce(cast(grp_eqty_as_is AS string),'')<>coalesce(cast(grp_eqty_to_be AS string),'') ) A | O70: =IF(O71="",N70,N70&$O$8) -> SELECT 'Validação de campos' as tipologia_teste, 'lt003_entity' AS TABELA, 'grp_eqty' AS CAMPO, '2024-09-30' as ref_date, coalesce(NUM_REG_DIF, 0) AS NUM_REG_DIF FROM (SELECT count(*) AS NUM_REG_DIF FROM (SELECT entty_id as entty_id_, grp_eqty as grp_eqty_as_is FROM cd_loan_tapes_bce.lt003_entity WHERE ref_date='2024-09-30' AND nome_perimetro='Individual Corporativo' AND segmento='ESTR' AND ambito='PM' AND entidade='00100' ) A Inner join (SELECT entty_id as entty_id_, grp_eqty as grp_eqty_to_be FROM bu_loantape_work.lt003_entity WHERE ref_date='2024-09-30' AND nome_perimetro='Individual Corporativo' AND segmento='ESTR' AND ambito='PM' AND entidade='00100' ) B ON entty_id_as_is=entty_id_to_be WHERE coalesce(cast(grp_eqty_as_is AS string),'')<>coalesce(cast(grp_eqty_to_be AS string),'') ) A Union all | P70: =P69+1 -> 11
B71: ENTTY | C71: =_xlfn.CONCAT(Instruções!$D$13,".",VLOOKUP(B71,Instruções!$F$12:$H$17,2,0)) -> cd_loan_tapes_bce.lt003_entity | D71: =_xlfn.CONCAT(Instruções!$D$14,".",VLOOKUP(B71,Instruções!$F$12:$H$17,3,0)) -> bu_loantape_work.lt003_entity | E71: grp_nt_dbt | F71: =E71&"_"&$F$7 -> grp_nt_dbt_as_is | G71: =E71&"_"&$G$7 -> grp_nt_dbt_to_be | H71: =IF(VLOOKUP(B71,Instruções!$F$13:$J$17,5,0)="", "(SELECT "&VLOOKUP(B71,Instruções!$F$13:$J$17,4,0)&" as "&VLOOKUP(B71,Instruções!$F$13:$J$17,4,0)&"_"&$F$2&", "&E71&" as "&F71&" FROM "&C71&" WHERE "&Instruções!$D$20&") A ", "(SELECT "&VLOOKUP(B71,Instruções!$F$13:$J$17,4,0)&" as "&VLOOKUP(B71,Instruções!$F$13:$J$17,4,0)&"_"&$F$2&", "&VLOOKUP(B71,Instruções!$F$13:$J$17,5,0)&" as "&VLOOKUP(B71,Instruções!$F$13:$J$17,5,0)&"_"&$F$2&","&E71&" as "&F71&" FROM "&C71&" WHERE "&Instruções!$D$20&") A ") -> (SELECT entty_id as entty_id_, grp_nt_dbt as grp_nt_dbt_as_is FROM cd_loan_tapes_bce.lt003_entity WHERE ref_date='2024-09-30' AND nome_perimetro='Individual Corporativo' AND segmento='ESTR' AND ambito='PM' AND entidade='00100' ) A | I71: =IF(VLOOKUP(B71,Instruções!$F$13:$J$17,5,0)="", "(SELECT "&VLOOKUP(B71,Instruções!$F$13:$J$17,4,0)&" as "&VLOOKUP(B71,Instruções!$F$13:$J$17,4,0)&"_"&$G$2&", "&E71&" as "&G71&" FROM "&D71&" WHERE "&Instruções!$D$21&") B ", "(SELECT "&VLOOKUP(B71,Instruções!$F$13:$J$17,4,0)&" as "&VLOOKUP(B71,Instruções!$F$13:$J$17,4,0)&"_"&$G$2&", "&VLOOKUP(B71,Instruções!$F$13:$J$17,5,0)&" as "&VLOOKUP(B71,Instruções!$F$13:$J$17,5,0)&"_"&$G$2&","&E71&" as "&G71&" FROM "&D71&" WHERE "&Instruções!$D$21&") B ") -> (SELECT entty_id as entty_id_, grp_nt_dbt as grp_nt_dbt_to_be FROM bu_loantape_work.lt003_entity WHERE ref_date='2024-09-30' AND nome_perimetro='Individual Corporativo' AND segmento='ESTR' AND ambito='PM' AND entidade='00100' ) B | J71: =+IF(VLOOKUP(B71,Instruções!$F$13:$J$17,5,0)="", "ON "&VLOOKUP(B71,Instruções!$F$13:$J$17,4,0)&"_"&$F$7&"="&VLOOKUP(B71,Instruções!$F$13:$J$17,4,0)&"_"&$G$7&" ", "ON "&VLOOKUP(B71,Instruções!$F$13:$J$17,4,0)&"_"&$F$7&"="&VLOOKUP(B71,Instruções!$F$13:$J$17,4,0)&"_"&$G$7&" AND "&VLOOKUP(B71,Instruções!$F$13:$J$17,5,0)&"_"&$F$7&"="&VLOOKUP(B71,Instruções!$F$13:$J$17,5,0)&"_"&$G$7&" ") -> ON entty_id_as_is=entty_id_to_be | K71: ="WHERE coalesce(cast("&F71&" AS string),'')<>coalesce(cast("&G71&" AS string),'') " -> WHERE coalesce(cast(grp_nt_dbt_as_is AS string),'')<>coalesce(cast(grp_nt_dbt_to_be AS string),'') | L71: ="SELECT count(*) AS NUM_REG_DIF FROM "&H71&" Inner join "&I71&J71&K71 -> SELECT count(*) AS NUM_REG_DIF FROM (SELECT entty_id as entty_id_, grp_nt_dbt as grp_nt_dbt_as_is FROM cd_loan_tapes_bce.lt003_entity WHERE ref_date='2024-09-30' AND nome_perimetro='Individual Corporativo' AND segmento='ESTR' AND ambito='PM' AND entidade='00100' ) A Inner join (SELECT entty_id as entty_id_, grp_nt_dbt as grp_nt_dbt_to_be FROM bu_loantape_work.lt003_entity WHERE ref_date='2024-09-30' AND nome_perimetro='Individual Corporativo' AND segmento='ESTR' AND ambito='PM' AND entidade='00100' ) B ON entty_id_as_is=entty_id_to_be WHERE coalesce(cast(grp_nt_dbt_as_is AS string),'')<>coalesce(cast(grp_nt_dbt_to_be AS string),'') | M71: Validação de campos | N71: ="SELECT 'Validação de campos' as tipologia_teste, '"&VLOOKUP(B71,Instruções!$F$13:$J$17,3,0)&"' AS TABELA, '"&E71&"' AS CAMPO, '"&Instruções!$D$15&"' as ref_date, coalesce(NUM_REG_DIF, 0) AS NUM_REG_DIF FROM ("&L71&") A " -> SELECT 'Validação de campos' as tipologia_teste, 'lt003_entity' AS TABELA, 'grp_nt_dbt' AS CAMPO, '2024-09-30' as ref_date, coalesce(NUM_REG_DIF, 0) AS NUM_REG_DIF FROM (SELECT count(*) AS NUM_REG_DIF FROM (SELECT entty_id as entty_id_, grp_nt_dbt as grp_nt_dbt_as_is FROM cd_loan_tapes_bce.lt003_entity WHERE ref_date='2024-09-30' AND nome_perimetro='Individual Corporativo' AND segmento='ESTR' AND ambito='PM' AND entidade='00100' ) A Inner join (SELECT entty_id as entty_id_, grp_nt_dbt as grp_nt_dbt_to_be FROM bu_loantape_work.lt003_entity WHERE ref_date='2024-09-30' AND nome_perimetro='Individual Corporativo' AND segmento='ESTR' AND ambito='PM' AND entidade='00100' ) B ON entty_id_as_is=entty_id_to_be WHERE coalesce(cast(grp_nt_dbt_as_is AS string),'')<>coalesce(cast(grp_nt_dbt_to_be AS string),'') ) A | O71: =IF(O72="",N71,N71&$O$8) -> SELECT 'Validação de campos' as tipologia_teste, 'lt003_entity' AS TABELA, 'grp_nt_dbt' AS CAMPO, '2024-09-30' as ref_date, coalesce(NUM_REG_DIF, 0) AS NUM_REG_DIF FROM (SELECT count(*) AS NUM_REG_DIF FROM (SELECT entty_id as entty_id_, grp_nt_dbt as grp_nt_dbt_as_is FROM cd_loan_tapes_bce.lt003_entity WHERE ref_date='2024-09-30' AND nome_perimetro='Individual Corporativo' AND segmento='ESTR' AND ambito='PM' AND entidade='00100' ) A Inner join (SELECT entty_id as entty_id_, grp_nt_dbt as grp_nt_dbt_to_be FROM bu_loantape_work.lt003_entity WHERE ref_date='2024-09-30' AND nome_perimetro='Individual Corporativo' AND segmento='ESTR' AND ambito='PM' AND entidade='00100' ) B ON entty_id_as_is=entty_id_to_be WHERE coalesce(cast(grp_nt_dbt_as_is AS string),'')<>coalesce(cast(grp_nt_dbt_to_be AS string),'') ) A Union all | P71: =P70+1 -> 12
B72: ENTTY | C72: =_xlfn.CONCAT(Instruções!$D$13,".",VLOOKUP(B72,Instruções!$F$12:$H$17,2,0)) -> cd_loan_tapes_bce.lt003_entity | D72: =_xlfn.CONCAT(Instruções!$D$14,".",VLOOKUP(B72,Instruções!$F$12:$H$17,3,0)) -> bu_loantape_work.lt003_entity | E72: grp_rorac | F72: =E72&"_"&$F$7 -> grp_rorac_as_is | G72: =E72&"_"&$G$7 -> grp_rorac_to_be | H72: =IF(VLOOKUP(B72,Instruções!$F$13:$J$17,5,0)="", "(SELECT "&VLOOKUP(B72,Instruções!$F$13:$J$17,4,0)&" as "&VLOOKUP(B72,Instruções!$F$13:$J$17,4,0)&"_"&$F$2&", "&E72&" as "&F72&" FROM "&C72&" WHERE "&Instruções!$D$20&") A ", "(SELECT "&VLOOKUP(B72,Instruções!$F$13:$J$17,4,0)&" as "&VLOOKUP(B72,Instruções!$F$13:$J$17,4,0)&"_"&$F$2&", "&VLOOKUP(B72,Instruções!$F$13:$J$17,5,0)&" as "&VLOOKUP(B72,Instruções!$F$13:$J$17,5,0)&"_"&$F$2&","&E72&" as "&F72&" FROM "&C72&" WHERE "&Instruções!$D$20&") A ") -> (SELECT entty_id as entty_id_, grp_rorac as grp_rorac_as_is FROM cd_loan_tapes_bce.lt003_entity WHERE ref_date='2024-09-30' AND nome_perimetro='Individual Corporativo' AND segmento='ESTR' AND ambito='PM' AND entidade='00100' ) A | I72: =IF(VLOOKUP(B72,Instruções!$F$13:$J$17,5,0)="", "(SELECT "&VLOOKUP(B72,Instruções!$F$13:$J$17,4,0)&" as "&VLOOKUP(B72,Instruções!$F$13:$J$17,4,0)&"_"&$G$2&", "&E72&" as "&G72&" FROM "&D72&" WHERE "&Instruções!$D$21&") B ", "(SELECT "&VLOOKUP(B72,Instruções!$F$13:$J$17,4,0)&" as "&VLOOKUP(B72,Instruções!$F$13:$J$17,4,0)&"_"&$G$2&", "&VLOOKUP(B72,Instruções!$F$13:$J$17,5,0)&" as "&VLOOKUP(B72,Instruções!$F$13:$J$17,5,0)&"_"&$G$2&","&E72&" as "&G72&" FROM "&D72&" WHERE "&Instruções!$D$21&") B ") -> (SELECT entty_id as entty_id_, grp_rorac as grp_rorac_to_be FROM bu_loantape_work.lt003_entity WHERE ref_date='2024-09-30' AND nome_perimetro='Individual Corporativo' AND segmento='ESTR' AND ambito='PM' AND entidade='00100' ) B | J72: =+IF(VLOOKUP(B72,Instruções!$F$13:$J$17,5,0)="", "ON "&VLOOKUP(B72,Instruções!$F$13:$J$17,4,0)&"_"&$F$7&"="&VLOOKUP(B72,Instruções!$F$13:$J$17,4,0)&"_"&$G$7&" ", "ON "&VLOOKUP(B72,Instruções!$F$13:$J$17,4,0)&"_"&$F$7&"="&VLOOKUP(B72,Instruções!$F$13:$J$17,4,0)&"_"&$G$7&" AND "&VLOOKUP(B72,Instruções!$F$13:$J$17,5,0)&"_"&$F$7&"="&VLOOKUP(B72,Instruções!$F$13:$J$17,5,0)&"_"&$G$7&" ") -> ON entty_id_as_is=entty_id_to_be | K72: ="WHERE coalesce(cast("&F72&" AS string),'')<>coalesce(cast("&G72&" AS string),'') " -> WHERE coalesce(cast(grp_rorac_as_is AS string),'')<>coalesce(cast(grp_rorac_to_be AS string),'') | L72: ="SELECT count(*) AS NUM_REG_DIF FROM "&H72&" Inner join "&I72&J72&K72 -> SELECT count(*) AS NUM_REG_DIF FROM (SELECT entty_id as entty_id_, grp_rorac as grp_rorac_as_is FROM cd_loan_tapes_bce.lt003_entity WHERE ref_date='2024-09-30' AND nome_perimetro='Individual Corporativo' AND segmento='ESTR' AND ambito='PM' AND entidade='00100' ) A Inner join (SELECT entty_id as entty_id_, grp_rorac as grp_rorac_to_be FROM bu_loantape_work.lt003_entity WHERE ref_date='2024-09-30' AND nome_perimetro='Individual Corporativo' AND segmento='ESTR' AND ambito='PM' AND entidade='00100' ) B ON entty_id_as_is=entty_id_to_be WHERE coalesce(cast(grp_rorac_as_is AS string),'')<>coalesce(cast(grp_rorac_to_be AS string),'') | M72: Validação de campos | N72: ="SELECT 'Validação de campos' as tipologia_teste, '"&VLOOKUP(B72,Instruções!$F$13:$J$17,3,0)&"' AS TABELA, '"&E72&"' AS CAMPO, '"&Instruções!$D$15&"' as ref_date, coalesce(NUM_REG_DIF, 0) AS NUM_REG_DIF FROM ("&L72&") A " -> SELECT 'Validação de campos' as tipologia_teste, 'lt003_entity' AS TABELA, 'grp_rorac' AS CAMPO, '2024-09-30' as ref_date, coalesce(NUM_REG_DIF, 0) AS NUM_REG_DIF FROM (SELECT count(*) AS NUM_REG_DIF FROM (SELECT entty_id as entty_id_, grp_rorac as grp_rorac_as_is FROM cd_loan_tapes_bce.lt003_entity WHERE ref_date='2024-09-30' AND nome_perimetro='Individual Corporativo' AND segmento='ESTR' AND ambito='PM' AND entidade='00100' ) A Inner join (SELECT entty_id as entty_id_, grp_rorac as grp_rorac_to_be FROM bu_loantape_work.lt003_entity WHERE ref_date='2024-09-30' AND nome_perimetro='Individual Corporativo' AND segmento='ESTR' AND ambito='PM' AND entidade='00100' ) B ON entty_id_as_is=entty_id_to_be WHERE coalesce(cast(grp_rorac_as_is AS string),'')<>coalesce(cast(grp_rorac_to_be AS string),'') ) A | O72: =IF(O73="",N72,N72&$O$8) -> SELECT 'Validação de campos' as tipologia_teste, 'lt003_entity' AS TABELA, 'grp_rorac' AS CAMPO, '2024-09-30' as ref_date, coalesce(NUM_REG_DIF, 0) AS NUM_REG_DIF FROM (SELECT count(*) AS NUM_REG_DIF FROM (SELECT entty_id as entty_id_, grp_rorac as grp_rorac_as_is FROM cd_loan_tapes_bce.lt003_entity WHERE ref_date='2024-09-30' AND nome_perimetro='Individual Corporativo' AND segmento='ESTR' AND ambito='PM' AND entidade='00100' ) A Inner join (SELECT entty_id as entty_id_, grp_rorac as grp_rorac_to_be FROM bu_loantape_work.lt003_entity WHERE ref_date='2024-09-30' AND nome_perimetro='Individual Corporativo' AND segmento='ESTR' AND ambito='PM' AND entidade='00100' ) B ON entty_id_as_is=entty_id_to_be WHERE coalesce(cast(grp_rorac_as_is AS string),'')<>coalesce(cast(grp_rorac_to_be AS string),'') ) A Union all | P72: =P71+1 -> 13
... B109: ENTTY | C109: =_xlfn.CONCAT(Instruções!$D$13,".",VLOOKUP(B109,Instruções!$F$12:$H$17,2,0)) -> cd_loan_tapes_bce.lt003_entity | D109: =_xlfn.CONCAT(Instruções!$D$14,".",VLOOKUP(B109,Instruções!$F$12:$H$17,3,0)) -> bu_loantape_work.lt003_entity | E109: ttl_lvrg_rt_prvs | F109: =E109&"_"&$F$7 -> ttl_lvrg_rt_prvs_as_is | G109: =E109&"_"&$G$7 -> ttl_lvrg_rt_prvs_to_be | H109: =IF(VLOOKUP(B109,Instruções!$F$13:$J$17,5,0)="", "(SELECT "&VLOOKUP(B109,Instruções!$F$13:$J$17,4,0)&" as "&VLOOKUP(B109,Instruções!$F$13:$J$17,4,0)&"_"&$F$2&", "&E109&" as "&F109&" FROM "&C109&" WHERE "&Instruções!$D$20&") A ", "(SELECT "&VLOOKUP(B109,Instruções!$F$13:$J$17,4,0)&" as "&VLOOKUP(B109,Instruções!$F$13:$J$17,4,0)&"_"&$F$2&", "&VLOOKUP(B109,Instruções!$F$13:$J$17,5,0)&" as "&VLOOKUP(B109,Instruções!$F$13:$J$17,5,0)&"_"&$F$2&","&E109&" as "&F109&" FROM "&C109&" WHERE "&Instruções!$D$20&") A ") -> (SELECT entty_id as entty_id_, ttl_lvrg_rt_prvs as ttl_lvrg_rt_prvs_as_is FROM cd_loan_tapes_bce.lt003_entity WHERE ref_date='2024-09-30' AND nome_perimetro='Individual Corporativo' AND segmento='ESTR' AND ambito='PM' AND entidade='00100' ) A | I109: =IF(VLOOKUP(B109,Instruções!$F$13:$J$17,5,0)="", "(SELECT "&VLOOKUP(B109,Instruções!$F$13:$J$17,4,0)&" as "&VLOOKUP(B109,Instruções!$F$13:$J$17,4,0)&"_"&$G$2&", "&E109&" as "&G109&" FROM "&D109&" WHERE "&Instruções!$D$21&") B ", "(SELECT "&VLOOKUP(B109,Instruções!$F$13:$J$17,4,0)&" as "&VLOOKUP(B109,Instruções!$F$13:$J$17,4,0)&"_"&$G$2&", "&VLOOKUP(B109,Instruções!$F$13:$J$17,5,0)&" as "&VLOOKUP(B109,Instruções!$F$13:$J$17,5,0)&"_"&$G$2&","&E109&" as "&G109&" FROM "&D109&" WHERE "&Instruções!$D$21&") B ") -> (SELECT entty_id as entty_id_, ttl_lvrg_rt_prvs as ttl_lvrg_rt_prvs_to_be FROM bu_loantape_work.lt003_entity WHERE ref_date='2024-09-30' AND nome_perimetro='Individual Corporativo' AND segmento='ESTR' AND ambito='PM' AND entidade='00100' ) B | J109: =+IF(VLOOKUP(B109,Instruções!$F$13:$J$17,5,0)="", "ON "&VLOOKUP(B109,Instruções!$F$13:$J$17,4,0)&"_"&$F$7&"="&VLOOKUP(B109,Instruções!$F$13:$J$17,4,0)&"_"&$G$7&" ", "ON "&VLOOKUP(B109,Instruções!$F$13:$J$17,4,0)&"_"&$F$7&"="&VLOOKUP(B109,Instruções!$F$13:$J$17,4,0)&"_"&$G$7&" AND "&VLOOKUP(B109,Instruções!$F$13:$J$17,5,0)&"_"&$F$7&"="&VLOOKUP(B109,Instruções!$F$13:$J$17,5,0)&"_"&$G$7&" ") -> ON entty_id_as_is=entty_id_to_be | K109: ="WHERE coalesce(cast("&F109&" AS string),'')<>coalesce(cast("&G109&" AS string),'') " -> WHERE coalesce(cast(ttl_lvrg_rt_prvs_as_is AS string),'')<>coalesce(cast(ttl_lvrg_rt_prvs_to_be AS string),'') | L109: ="SELECT count(*) AS NUM_REG_DIF FROM "&H109&" Inner join "&I109&J109&K109 -> SELECT count(*) AS NUM_REG_DIF FROM (SELECT entty_id as entty_id_, ttl_lvrg_rt_prvs as ttl_lvrg_rt_prvs_as_is FROM cd_loan_tapes_bce.lt003_entity WHERE ref_date='2024-09-30' AND nome_perimetro='Individual Corporativo' AND segmento='ESTR' AND ambito='PM' AND entidade='00100' ) A Inner join (SELECT entty_id as entty_id_, ttl_lvrg_rt_prvs as ttl_lvrg_rt_prvs_to_be FROM bu_loantape_work.lt003_entity WHERE ref_date='2024-09-30' AND nome_perimetro='Individual Corporativo' AND segmento='ESTR' AND ambito='PM' AND entidade='00100' ) B ON entty_id_as_is=entty_id_to_be WHERE coalesce(cast(ttl_lvrg_rt_prvs_as_is AS string),'')<>coalesce(cast(ttl_lvrg_rt_prvs_to_be AS string),'') | M109: Validação de campos | N109: ="SELECT 'Validação de campos' as tipologia_teste, '"&VLOOKUP(B109,Instruções!$F$13:$J$17,3,0)&"' AS TABELA, '"&E109&"' AS CAMPO, '"&Instruções!$D$15&"' as ref_date, coalesce(NUM_REG_DIF, 0) AS NUM_REG_DIF FROM ("&L109&") A " -> SELECT 'Validação de campos' as tipologia_teste, 'lt003_entity' AS TABELA, 'ttl_lvrg_rt_prvs' AS CAMPO, '2024-09-30' as ref_date, coalesce(NUM_REG_DIF, 0) AS NUM_REG_DIF FROM (SELECT count(*) AS NUM_REG_DIF FROM (SELECT entty_id as entty_id_, ttl_lvrg_rt_prvs as ttl_lvrg_rt_prvs_as_is FROM cd_loan_tapes_bce.lt003_entity WHERE ref_date='2024-09-30' AND nome_perimetro='Individual Corporativo' AND segmento='ESTR' AND ambito='PM' AND entidade='00100' ) A Inner join (SELECT entty_id as entty_id_, ttl_lvrg_rt_prvs as ttl_lvrg_rt_prvs_to_be FROM bu_loantape_work.lt003_entity WHERE ref_date='2024-09-30' AND nome_perimetro='Individual Corporativo' AND segmento='ESTR' AND ambito='PM' AND entidade='00100' ) B ON entty_id_as_is=entty_id_to_be WHERE coalesce(cast(ttl_lvrg_rt_prvs_as_is AS string),'')<>coalesce(cast(ttl_lvrg_rt_prvs_to_be AS string),'') ) A | O109: =IF(O110="",N109,N109&$O$8) -> SELECT 'Validação de campos' as tipologia_teste, 'lt003_entity' AS TABELA, 'ttl_lvrg_rt_prvs' AS CAMPO, '2024-09-30' as ref_date, coalesce(NUM_REG_DIF, 0) AS NUM_REG_DIF FROM (SELECT count(*) AS NUM_REG_DIF FROM (SELECT entty_id as entty_id_, ttl_lvrg_rt_prvs as ttl_lvrg_rt_prvs_as_is FROM cd_loan_tapes_bce.lt003_entity WHERE ref_date='2024-09-30' AND nome_perimetro='Individual Corporativo' AND segmento='ESTR' AND ambito='PM' AND entidade='00100' ) A Inner join (SELECT entty_id as entty_id_, ttl_lvrg_rt_prvs as ttl_lvrg_rt_prvs_to_be FROM bu_loantape_work.lt003_entity WHERE ref_date='2024-09-30' AND nome_perimetro='Individual Corporativo' AND segmento='ESTR' AND ambito='PM' AND entidade='00100' ) B ON entty_id_as_is=entty_id_to_be WHERE coalesce(cast(ttl_lvrg_rt_prvs_as_is AS string),'')<>coalesce(cast(ttl_lvrg_rt_prvs_to_be AS string),'') ) A | P109: =P108+1 -> 50
B111: ENTTY | C111: =_xlfn.CONCAT(Instruções!$D$13,".",VLOOKUP(B111,Instruções!$F$12:$H$17,2,0)) -> cd_loan_tapes_bce.lt003_entity | D111: =_xlfn.CONCAT(Instruções!$D$14,".",VLOOKUP(B111,Instruções!$F$12:$H$17,3,0)) -> bu_loantape_work.lt003_entity | E111: ttl_prmssbl_dbt_blnc | F111: =E111&"_"&$F$7 -> ttl_prmssbl_dbt_blnc_as_is | G111: =E111&"_"&$G$7 -> ttl_prmssbl_dbt_blnc_to_be | H111: =IF(VLOOKUP(B111,Instruções!$F$13:$J$17,5,0)="", "(SELECT "&VLOOKUP(B111,Instruções!$F$13:$J$17,4,0)&" as "&VLOOKUP(B111,Instruções!$F$13:$J$17,4,0)&"_"&$F$2&", "&E111&" as "&F111&" FROM "&C111&" WHERE "&Instruções!$D$20&") A ", "(SELECT "&VLOOKUP(B111,Instruções!$F$13:$J$17,4,0)&" as "&VLOOKUP(B111,Instruções!$F$13:$J$17,4,0)&"_"&$F$2&", "&VLOOKUP(B111,Instruções!$F$13:$J$17,5,0)&" as "&VLOOKUP(B111,Instruções!$F$13:$J$17,5,0)&"_"&$F$2&","&E111&" as "&F111&" FROM "&C111&" WHERE "&Instruções!$D$20&") A ") -> (SELECT entty_id as entty_id_, ttl_prmssbl_dbt_blnc as ttl_prmssbl_dbt_blnc_as_is FROM cd_loan_tapes_bce.lt003_entity WHERE ref_date='2024-09-30' AND nome_perimetro='Individual Corporativo' AND segmento='ESTR' AND ambito='PM' AND entidade='00100' ) A | I111: =IF(VLOOKUP(B111,Instruções!$F$13:$J$17,5,0)="", "(SELECT "&VLOOKUP(B111,Instruções!$F$13:$J$17,4,0)&" as "&VLOOKUP(B111,Instruções!$F$13:$J$17,4,0)&"_"&$G$2&", "&E111&" as "&G111&" FROM "&D111&" WHERE "&Instruções!$D$21&") B ", "(SELECT "&VLOOKUP(B111,Instruções!$F$13:$J$17,4,0)&" as "&VLOOKUP(B111,Instruções!$F$13:$J$17,4,0)&"_"&$G$2&", "&VLOOKUP(B111,Instruções!$F$13:$J$17,5,0)&" as "&VLOOKUP(B111,Instruções!$F$13:$J$17,5,0)&"_"&$G$2&","&E111&" as "&G111&" FROM "&D111&" WHERE "&Instruções!$D$21&") B ") -> (SELECT entty_id as entty_id_, ttl_prmssbl_dbt_blnc as ttl_prmssbl_dbt_blnc_to_be FROM bu_loantape_work.lt003_entity WHERE ref_date='2024-09-30' AND nome_perimetro='Individual Corporativo' AND segmento='ESTR' AND ambito='PM' AND entidade='00100' ) B | J111: =+IF(VLOOKUP(B111,Instruções!$F$13:$J$17,5,0)="", "ON "&VLOOKUP(B111,Instruções!$F$13:$J$17,4,0)&"_"&$F$7&"="&VLOOKUP(B111,Instruções!$F$13:$J$17,4,0)&"_"&$G$7&" ", "ON "&VLOOKUP(B111,Instruções!$F$13:$J$17,4,0)&"_"&$F$7&"="&VLOOKUP(B111,Instruções!$F$13:$J$17,4,0)&"_"&$G$7&" AND "&VLOOKUP(B111,Instruções!$F$13:$J$17,5,0)&"_"&$F$7&"="&VLOOKUP(B111,Instruções!$F$13:$J$17,5,0)&"_"&$G$7&" ") -> ON entty_id_as_is=entty_id_to_be | K111: ="WHERE coalesce(cast("&F111&" AS string),'')<>coalesce(cast("&G111&" AS string),'') " -> WHERE coalesce(cast(ttl_prmssbl_dbt_blnc_as_is AS string),'')<>coalesce(cast(ttl_prmssbl_dbt_blnc_to_be AS string),'') | L111: ="SELECT count(*) AS NUM_REG_DIF FROM "&H111&" Inner join "&I111&J111&K111 -> SELECT count(*) AS NUM_REG_DIF FROM (SELECT entty_id as entty_id_, ttl_prmssbl_dbt_blnc as ttl_prmssbl_dbt_blnc_as_is FROM cd_loan_tapes_bce.lt003_entity WHERE ref_date='2024-09-30' AND nome_perimetro='Individual Corporativo' AND segmento='ESTR' AND ambito='PM' AND entidade='00100' ) A Inner join (SELECT entty_id as entty_id_, ttl_prmssbl_dbt_blnc as ttl_prmssbl_dbt_blnc_to_be FROM bu_loantape_work.lt003_entity WHERE ref_date='2024-09-30' AND nome_perimetro='Individual Corporativo' AND segmento='ESTR' AND ambito='PM' AND entidade='00100' ) B ON entty_id_as_is=entty_id_to_be WHERE coalesce(cast(ttl_prmssbl_dbt_blnc_as_is AS string),'')<>coalesce(cast(ttl_prmssbl_dbt_blnc_to_be AS string),'') | M111: Validação de campos | N111: ="SELECT 'Validação de campos' as tipologia_teste, '"&VLOOKUP(B111,Instruções!$F$13:$J$17,3,0)&"' AS TABELA, '"&E111&"' AS CAMPO, '"&Instruções!$D$15&"' as ref_date, coalesce(NUM_REG_DIF, 0) AS NUM_REG_DIF FROM ("&L111&") A " -> SELECT 'Validação de campos' as tipologia_teste, 'lt003_entity' AS TABELA, 'ttl_prmssbl_dbt_blnc' AS CAMPO, '2024-09-30' as ref_date, coalesce(NUM_REG_DIF, 0) AS NUM_REG_DIF FROM (SELECT count(*) AS NUM_REG_DIF FROM (SELECT entty_id as entty_id_, ttl_prmssbl_dbt_blnc as ttl_prmssbl_dbt_blnc_as_is FROM cd_loan_tapes_bce.lt003_entity WHERE ref_date='2024-09-30' AND nome_perimetro='Individual Corporativo' AND segmento='ESTR' AND ambito='PM' AND entidade='00100' ) A Inner join (SELECT entty_id as entty_id_, ttl_prmssbl_dbt_blnc as ttl_prmssbl_dbt_blnc_to_be FROM bu_loantape_work.lt003_entity WHERE ref_date='2024-09-30' AND nome_perimetro='Individual Corporativo' AND segmento='ESTR' AND ambito='PM' AND entidade='00100' ) B ON entty_id_as_is=entty_id_to_be WHERE coalesce(cast(ttl_prmssbl_dbt_blnc_as_is AS string),'')<>coalesce(cast(ttl_prmssbl_dbt_blnc_to_be AS string),'') ) A | O111: =IF(O112="",N111,N111&$O$8) -> SELECT 'Validação de campos' as tipologia_teste, 'lt003_entity' AS TABELA, 'ttl_prmssbl_dbt_blnc' AS CAMPO, '2024-09-30' as ref_date, coalesce(NUM_REG_DIF, 0) AS NUM_REG_DIF FROM (SELECT count(*) AS NUM_REG_DIF FROM (SELECT entty_id as entty_id_, ttl_prmssbl_dbt_blnc as ttl_prmssbl_dbt_blnc_as_is FROM cd_loan_tapes_bce.lt003_entity WHERE ref_date='2024-09-30' AND nome_perimetro='Individual Corporativo' AND segmento='ESTR' AND ambito='PM' AND entidade='00100' ) A Inner join (SELECT entty_id as entty_id_, ttl_prmssbl_dbt_blnc as ttl_prmssbl_dbt_blnc_to_be FROM bu_loantape_work.lt003_entity WHERE ref_date='2024-09-30' AND nome_perimetro='Individual Corporativo' AND segmento='ESTR' AND ambito='PM' AND entidade='00100' ) B ON entty_id_as_is=entty_id_to_be WHERE coalesce(cast(ttl_prmssbl_dbt_blnc_as_is AS string),'')<>coalesce(cast(ttl_prmssbl_dbt_blnc_to_be AS string),'') ) A Union all | P111: =+P110+1 -> 1
B112: ENTTY | C112: =_xlfn.CONCAT(Instruções!$D$13,".",VLOOKUP(B112,Instruções!$F$12:$H$17,2,0)) -> cd_loan_tapes_bce.lt003_entity | D112: =_xlfn.CONCAT(Instruções!$D$14,".",VLOOKUP(B112,Instruções!$F$12:$H$17,3,0)) -> bu_loantape_work.lt003_entity | E112: wtch_lst | F112: =E112&"_"&$F$7 -> wtch_lst_as_is | G112: =E112&"_"&$G$7 -> wtch_lst_to_be | H112: =IF(VLOOKUP(B112,Instruções!$F$13:$J$17,5,0)="", "(SELECT "&VLOOKUP(B112,Instruções!$F$13:$J$17,4,0)&" as "&VLOOKUP(B112,Instruções!$F$13:$J$17,4,0)&"_"&$F$2&", "&E112&" as "&F112&" FROM "&C112&" WHERE "&Instruções!$D$20&") A ", "(SELECT "&VLOOKUP(B112,Instruções!$F$13:$J$17,4,0)&" as "&VLOOKUP(B112,Instruções!$F$13:$J$17,4,0)&"_"&$F$2&", "&VLOOKUP(B112,Instruções!$F$13:$J$17,5,0)&" as "&VLOOKUP(B112,Instruções!$F$13:$J$17,5,0)&"_"&$F$2&","&E112&" as "&F112&" FROM "&C112&" WHERE "&Instruções!$D$20&") A ") -> (SELECT entty_id as entty_id_, wtch_lst as wtch_lst_as_is FROM cd_loan_tapes_bce.lt003_entity WHERE ref_date='2024-09-30' AND nome_perimetro='Individual Corporativo' AND segmento='ESTR' AND ambito='PM' AND entidade='00100' ) A | I112: =IF(VLOOKUP(B112,Instruções!$F$13:$J$17,5,0)="", "(SELECT "&VLOOKUP(B112,Instruções!$F$13:$J$17,4,0)&" as "&VLOOKUP(B112,Instruções!$F$13:$J$17,4,0)&"_"&$G$2&", "&E112&" as "&G112&" FROM "&D112&" WHERE "&Instruções!$D$21&") B ", "(SELECT "&VLOOKUP(B112,Instruções!$F$13:$J$17,4,0)&" as "&VLOOKUP(B112,Instruções!$F$13:$J$17,4,0)&"_"&$G$2&", "&VLOOKUP(B112,Instruções!$F$13:$J$17,5,0)&" as "&VLOOKUP(B112,Instruções!$F$13:$J$17,5,0)&"_"&$G$2&","&E112&" as "&G112&" FROM "&D112&" WHERE "&Instruções!$D$21&") B ") -> (SELECT entty_id as entty_id_, wtch_lst as wtch_lst_to_be FROM bu_loantape_work.lt003_entity WHERE ref_date='2024-09-30' AND nome_perimetro='Individual Corporativo' AND segmento='ESTR' AND ambito='PM' AND entidade='00100' ) B | J112: =+IF(VLOOKUP(B112,Instruções!$F$13:$J$17,5,0)="", "ON "&VLOOKUP(B112,Instruções!$F$13:$J$17,4,0)&"_"&$F$7&"="&VLOOKUP(B112,Instruções!$F$13:$J$17,4,0)&"_"&$G$7&" ", "ON "&VLOOKUP(B112,Instruções!$F$13:$J$17,4,0)&"_"&$F$7&"="&VLOOKUP(B112,Instruções!$F$13:$J$17,4,0)&"_"&$G$7&" AND "&VLOOKUP(B112,Instruções!$F$13:$J$17,5,0)&"_"&$F$7&"="&VLOOKUP(B112,Instruções!$F$13:$J$17,5,0)&"_"&$G$7&" ") -> ON entty_id_as_is=entty_id_to_be | K112: ="WHERE coalesce(cast("&F112&" AS string),'')<>coalesce(cast("&G112&" AS string),'') " -> WHERE coalesce(cast(wtch_lst_as_is AS string),'')<>coalesce(cast(wtch_lst_to_be AS string),'') | L112: ="SELECT count(*) AS NUM_REG_DIF FROM "&H112&" Inner join "&I112&J112&K112 -> SELECT count(*) AS NUM_REG_DIF FROM (SELECT entty_id as entty_id_, wtch_lst as wtch_lst_as_is FROM cd_loan_tapes_bce.lt003_entity WHERE ref_date='2024-09-30' AND nome_perimetro='Individual Corporativo' AND segmento='ESTR' AND ambito='PM' AND entidade='00100' ) A Inner join (SELECT entty_id as entty_id_, wtch_lst as wtch_lst_to_be FROM bu_loantape_work.lt003_entity WHERE ref_date='2024-09-30' AND nome_perimetro='Individual Corporativo' AND segmento='ESTR' AND ambito='PM' AND entidade='00100' ) B ON entty_id_as_is=entty_id_to_be WHERE coalesce(cast(wtch_lst_as_is AS string),'')<>coalesce(cast(wtch_lst_to_be AS string),'') | M112: Validação de campos | N112: ="SELECT 'Validação de campos' as tipologia_teste, '"&VLOOKUP(B112,Instruções!$F$13:$J$17,3,0)&"' AS TABELA, '"&E112&"' AS CAMPO, '"&Instruções!$D$15&"' as ref_date, coalesce(NUM_REG_DIF, 0) AS NUM_REG_DIF FROM ("&L112&") A " -> SELECT 'Validação de campos' as tipologia_teste, 'lt003_entity' AS TABELA, 'wtch_lst' AS CAMPO, '2024-09-30' as ref_date, coalesce(NUM_REG_DIF, 0) AS NUM_REG_DIF FROM (SELECT count(*) AS NUM_REG_DIF FROM (SELECT entty_id as entty_id_, wtch_lst as wtch_lst_as_is FROM cd_loan_tapes_bce.lt003_entity WHERE ref_date='2024-09-30' AND nome_perimetro='Individual Corporativo' AND segmento='ESTR' AND ambito='PM' AND entidade='00100' ) A Inner join (SELECT entty_id as entty_id_, wtch_lst as wtch_lst_to_be FROM bu_loantape_work.lt003_entity WHERE ref_date='2024-09-30' AND nome_perimetro='Individual Corporativo' AND segmento='ESTR' AND ambito='PM' AND entidade='00100' ) B ON entty_id_as_is=entty_id_to_be WHERE coalesce(cast(wtch_lst_as_is AS string),'')<>coalesce(cast(wtch_lst_to_be AS string),'') ) A | O112: =IF(O113="",N112,N112&$O$8) -> SELECT 'Validação de campos' as tipologia_teste, 'lt003_entity' AS TABELA, 'wtch_lst' AS CAMPO, '2024-09-30' as ref_date, coalesce(NUM_REG_DIF, 0) AS NUM_REG_DIF FROM (SELECT count(*) AS NUM_REG_DIF FROM (SELECT entty_id as entty_id_, wtch_lst as wtch_lst_as_is FROM cd_loan_tapes_bce.lt003_entity WHERE ref_date='2024-09-30' AND nome_perimetro='Individual Corporativo' AND segmento='ESTR' AND ambito='PM' AND entidade='00100' ) A Inner join (SELECT entty_id as entty_id_, wtch_lst as wtch_lst_to_be FROM bu_loantape_work.lt003_entity WHERE ref_date='2024-09-30' AND nome_perimetro='Individual Corporativo' AND segmento='ESTR' AND ambito='PM' AND entidade='00100' ) B ON entty_id_as_is=entty_id_to_be WHERE coalesce(cast(wtch_lst_as_is AS string),'')<>coalesce(cast(wtch_lst_to_be AS string),'') ) A Union all | P112: =+P111+1 -> 2
B113: INSTR_ENTTY | C113: =_xlfn.CONCAT(Instruções!$D$13,".",VLOOKUP(B113,Instruções!$F$12:$H$17,2,0)) -> cd_loan_tapes_bce.lt005_instr_ent | D113: =_xlfn.CONCAT(Instruções!$D$14,".",VLOOKUP(B113,Instruções!$F$12:$H$17,3,0)) -> bu_loantape_work.lt005_instr_ent | E113: cod_soc | F113: =E113&"_"&$F$7 -> cod_soc_as_is | G113: =E113&"_"&$G$7 -> cod_soc_to_be | H113: =IF(VLOOKUP(B113,Instruções!$F$13:$J$17,5,0)="", "(SELECT "&VLOOKUP(B113,Instruções!$F$13:$J$17,4,0)&" as "&VLOOKUP(B113,Instruções!$F$13:$J$17,4,0)&"_"&$F$2&", "&E113&" as "&F113&" FROM "&C113&" WHERE "&Instruções!$D$20&") A ", "(SELECT "&VLOOKUP(B113,Instruções!$F$13:$J$17,4,0)&" as "&VLOOKUP(B113,Instruções!$F$13:$J$17,4,0)&"_"&$F$2&", "&VLOOKUP(B113,Instruções!$F$13:$J$17,5,0)&" as "&VLOOKUP(B113,Instruções!$F$13:$J$17,5,0)&"_"&$F$2&","&E113&" as "&F113&" FROM "&C113&" WHERE "&Instruções!$D$20&") A ") -> (SELECT instrmnt_id as instrmnt_id_, entty_id as entty_id_,cod_soc as cod_soc_as_is FROM cd_loan_tapes_bce.lt005_instr_ent WHERE ref_date='2024-09-30' AND nome_perimetro='Individual Corporativo' AND segmento='ESTR' AND ambito='PM' AND entidade='00100' ) A | I113: =IF(VLOOKUP(B113,Instruções!$F$13:$J$17,5,0)="", "(SELECT "&VLOOKUP(B113,Instruções!$F$13:$J$17,4,0)&" as "&VLOOKUP(B113,Instruções!$F$13:$J$17,4,0)&"_"&$G$2&", "&E113&" as "&G113&" FROM "&D113&" WHERE "&Instruções!$D$21&") B ", "(SELECT "&VLOOKUP(B113,Instruções!$F$13:$J$17,4,0)&" as "&VLOOKUP(B113,Instruções!$F$13:$J$17,4,0)&"_"&$G$2&", "&VLOOKUP(B113,Instruções!$F$13:$J$17,5,0)&" as "&VLOOKUP(B113,Instruções!$F$13:$J$17,5,0)&"_"&$G$2&","&E113&" as "&G113&" FROM "&D113&" WHERE "&Instruções!$D$21&") B ") -> (SELECT instrmnt_id as instrmnt_id_, entty_id as entty_id_,cod_soc as cod_soc_to_be FROM bu_loantape_work.lt005_instr_ent WHERE ref_date='2024-09-30' AND nome_perimetro='Individual Corporativo' AND segmento='ESTR' AND ambito='PM' AND entidade='00100' ) B | J113: =+IF(VLOOKUP(B113,Instruções!$F$13:$J$17,5,0)="", "ON "&VLOOKUP(B113,Instruções!$F$13:$J$17,4,0)&"_"&$F$7&"="&VLOOKUP(B113,Instruções!$F$13:$J$17,4,0)&"_"&$G$7&" ", "ON "&VLOOKUP(B113,Instruções!$F$13:$J$17,4,0)&"_"&$F$7&"="&VLOOKUP(B113,Instruções!$F$13:$J$17,4,0)&"_"&$G$7&" AND "&VLOOKUP(B113,Instruções!$F$13:$J$17,5,0)&"_"&$F$7&"="&VLOOKUP(B113,Instruções!$F$13:$J$17,5,0)&"_"&$G$7&" ") -> ON instrmnt_id_as_is=instrmnt_id_to_be AND entty_id_as_is=entty_id_to_be | K113: ="WHERE coalesce(cast("&F113&" AS string),'')<>coalesce(cast("&G113&" AS string),'') " -> WHERE coalesce(cast(cod_soc_as_is AS string),'')<>coalesce(cast(cod_soc_to_be AS string),'') | L113: ="SELECT count(*) AS NUM_REG_DIF FROM "&H113&" Inner join "&I113&J113&K113 -> SELECT count(*) AS NUM_REG_DIF FROM (SELECT instrmnt_id as instrmnt_id_, entty_id as entty_id_,cod_soc as cod_soc_as_is FROM cd_loan_tapes_bce.lt005_instr_ent WHERE ref_date='2024-09-30' AND nome_perimetro='Individual Corporativo' AND segmento='ESTR' AND ambito='PM' AND entidade='00100' ) A Inner join (SELECT instrmnt_id as instrmnt_id_, entty_id as entty_id_,cod_soc as cod_soc_to_be FROM bu_loantape_work.lt005_instr_ent WHERE ref_date='2024-09-30' AND nome_perimetro='Individual Corporativo' AND segmento='ESTR' AND ambito='PM' AND entidade='00100' ) B ON instrmnt_id_as_is=instrmnt_id_to_be AND entty_id_as_is=entty_id_to_be WHERE coalesce(cast(cod_soc_as_is AS string),'')<>coalesce(cast(cod_soc_to_be AS string),'') | M113: Validação de campos | N113: ="SELECT 'Validação de campos' as tipologia_teste, '"&VLOOKUP(B113,Instruções!$F$13:$J$17,3,0)&"' AS TABELA, '"&E113&"' AS CAMPO, '"&Instruções!$D$15&"' as ref_date, coalesce(NUM_REG_DIF, 0) AS NUM_REG_DIF FROM ("&L113&") A " -> SELECT 'Validação de campos' as tipologia_teste, 'lt005_instr_ent' AS TABELA, 'cod_soc' AS CAMPO, '2024-09-30' as ref_date, coalesce(NUM_REG_DIF, 0) AS NUM_REG_DIF FROM (SELECT count(*) AS NUM_REG_DIF FROM (SELECT instrmnt_id as instrmnt_id_, entty_id as entty_id_,cod_soc as cod_soc_as_is FROM cd_loan_tapes_bce.lt005_instr_ent WHERE ref_date='2024-09-30' AND nome_perimetro='Individual Corporativo' AND segmento='ESTR' AND ambito='PM' AND entidade='00100' ) A Inner join (SELECT instrmnt_id as instrmnt_id_, entty_id as entty_id_,cod_soc as cod_soc_to_be FROM bu_loantape_work.lt005_instr_ent WHERE ref_date='2024-09-30' AND nome_perimetro='Individual Corporativo' AND segmento='ESTR' AND ambito='PM' AND entidade='00100' ) B ON instrmnt_id_as_is=instrmnt_id_to_be AND entty_id_as_is=entty_id_to_be WHERE coalesce(cast(cod_soc_as_is AS string),'')<>coalesce(cast(cod_soc_to_be AS string),'') ) A | O113: =IF(O114="",N113,N113&$O$8) -> SELECT 'Validação de campos' as tipologia_teste, 'lt005_instr_ent' AS TABELA, 'cod_soc' AS CAMPO, '2024-09-30' as ref_date, coalesce(NUM_REG_DIF, 0) AS NUM_REG_DIF FROM (SELECT count(*) AS NUM_REG_DIF FROM (SELECT instrmnt_id as instrmnt_id_, entty_id as entty_id_,cod_soc as cod_soc_as_is FROM cd_loan_tapes_bce.lt005_instr_ent WHERE ref_date='2024-09-30' AND nome_perimetro='Individual Corporativo' AND segmento='ESTR' AND ambito='PM' AND entidade='00100' ) A Inner join (SELECT instrmnt_id as instrmnt_id_, entty_id as entty_id_,cod_soc as cod_soc_to_be FROM bu_loantape_work.lt005_instr_ent WHERE ref_date='2024-09-30' AND nome_perimetro='Individual Corporativo' AND segmento='ESTR' AND ambito='PM' AND entidade='00100' ) B ON instrmnt_id_as_is=instrmnt_id_to_be AND entty_id_as_is=entty_id_to_be WHERE coalesce(cast(cod_soc_as_is AS string),'')<>coalesce(cast(cod_soc_to_be AS string),'') ) A Union all | P113: =+P112+1 -> 3
B114: INSTR_ENTTY | C114: =_xlfn.CONCAT(Instruções!$D$13,".",VLOOKUP(B114,Instruções!$F$12:$H$17,2,0)) -> cd_loan_tapes_bce.lt005_instr_ent | D114: =_xlfn.CONCAT(Instruções!$D$14,".",VLOOKUP(B114,Instruções!$F$12:$H$17,3,0)) -> bu_loantape_work.lt005_instr_ent | E114: jnt_lblty_amnt | F114: =E114&"_"&$F$7 -> jnt_lblty_amnt_as_is | G114: =E114&"_"&$G$7 -> jnt_lblty_amnt_to_be | H114: =IF(VLOOKUP(B114,Instruções!$F$13:$J$17,5,0)="", "(SELECT "&VLOOKUP(B114,Instruções!$F$13:$J$17,4,0)&" as "&VLOOKUP(B114,Instruções!$F$13:$J$17,4,0)&"_"&$F$2&", "&E114&" as "&F114&" FROM "&C114&" WHERE "&Instruções!$D$20&") A ", "(SELECT "&VLOOKUP(B114,Instruções!$F$13:$J$17,4,0)&" as "&VLOOKUP(B114,Instruções!$F$13:$J$17,4,0)&"_"&$F$2&", "&VLOOKUP(B114,Instruções!$F$13:$J$17,5,0)&" as "&VLOOKUP(B114,Instruções!$F$13:$J$17,5,0)&"_"&$F$2&","&E114&" as "&F114&" FROM "&C114&" WHERE "&Instruções!$D$20&") A ") -> (SELECT instrmnt_id as instrmnt_id_, entty_id as entty_id_,jnt_lblty_amnt as jnt_lblty_amnt_as_is FROM cd_loan_tapes_bce.lt005_instr_ent WHERE ref_date='2024-09-30' AND nome_perimetro='Individual Corporativo' AND segmento='ESTR' AND ambito='PM' AND entidade='00100' ) A | I114: =IF(VLOOKUP(B114,Instruções!$F$13:$J$17,5,0)="", "(SELECT "&VLOOKUP(B114,Instruções!$F$13:$J$17,4,0)&" as "&VLOOKUP(B114,Instruções!$F$13:$J$17,4,0)&"_"&$G$2&", "&E114&" as "&G114&" FROM "&D114&" WHERE "&Instruções!$D$21&") B ", "(SELECT "&VLOOKUP(B114,Instruções!$F$13:$J$17,4,0)&" as "&VLOOKUP(B114,Instruções!$F$13:$J$17,4,0)&"_"&$G$2&", "&VLOOKUP(B114,Instruções!$F$13:$J$17,5,0)&" as "&VLOOKUP(B114,Instruções!$F$13:$J$17,5,0)&"_"&$G$2&","&E114&" as "&G114&" FROM "&D114&" WHERE "&Instruções!$D$21&") B ") -> (SELECT instrmnt_id as instrmnt_id_, entty_id as entty_id_,jnt_lblty_amnt as jnt_lblty_amnt_to_be FROM bu_loantape_work.lt005_instr_ent WHERE ref_date='2024-09-30' AND nome_perimetro='Individual Corporativo' AND segmento='ESTR' AND ambito='PM' AND entidade='00100' ) B | J114: =+IF(VLOOKUP(B114,Instruções!$F$13:$J$17,5,0)="", "ON "&VLOOKUP(B114,Instruções!$F$13:$J$17,4,0)&"_"&$F$7&"="&VLOOKUP(B114,Instruções!$F$13:$J$17,4,0)&"_"&$G$7&" ", "ON "&VLOOKUP(B114,Instruções!$F$13:$J$17,4,0)&"_"&$F$7&"="&VLOOKUP(B114,Instruções!$F$13:$J$17,4,0)&"_"&$G$7&" AND "&VLOOKUP(B114,Instruções!$F$13:$J$17,5,0)&"_"&$F$7&"="&VLOOKUP(B114,Instruções!$F$13:$J$17,5,0)&"_"&$G$7&" ") -> ON instrmnt_id_as_is=instrmnt_id_to_be AND entty_id_as_is=entty_id_to_be | K114: ="WHERE coalesce(cast("&F114&" AS string),'')<>coalesce(cast("&G114&" AS string),'') " -> WHERE coalesce(cast(jnt_lblty_amnt_as_is AS string),'')<>coalesce(cast(jnt_lblty_amnt_to_be AS string),'') | L114: ="SELECT count(*) AS NUM_REG_DIF FROM "&H114&" Inner join "&I114&J114&K114 -> SELECT count(*) AS NUM_REG_DIF FROM (SELECT instrmnt_id as instrmnt_id_, entty_id as entty_id_,jnt_lblty_amnt as jnt_lblty_amnt_as_is FROM cd_loan_tapes_bce.lt005_instr_ent WHERE ref_date='2024-09-30' AND nome_perimetro='Individual Corporativo' AND segmento='ESTR' AND ambito='PM' AND entidade='00100' ) A Inner join (SELECT instrmnt_id as instrmnt_id_, entty_id as entty_id_,jnt_lblty_amnt as jnt_lblty_amnt_to_be FROM bu_loantape_work.lt005_instr_ent WHERE ref_date='2024-09-30' AND nome_perimetro='Individual Corporativo' AND segmento='ESTR' AND ambito='PM' AND entidade='00100' ) B ON instrmnt_id_as_is=instrmnt_id_to_be AND entty_id_as_is=entty_id_to_be WHERE coalesce(cast(jnt_lblty_amnt_as_is AS string),'')<>coalesce(cast(jnt_lblty_amnt_to_be AS string),'') | M114: Validação de campos | N114: ="SELECT 'Validação de campos' as tipologia_teste, '"&VLOOKUP(B114,Instruções!$F$13:$J$17,3,0)&"' AS TABELA, '"&E114&"' AS CAMPO, '"&Instruções!$D$15&"' as ref_date, coalesce(NUM_REG_DIF, 0) AS NUM_REG_DIF FROM ("&L114&") A " -> SELECT 'Validação de campos' as tipologia_teste, 'lt005_instr_ent' AS TABELA, 'jnt_lblty_amnt' AS CAMPO, '2024-09-30' as ref_date, coalesce(NUM_REG_DIF, 0) AS NUM_REG_DIF FROM (SELECT count(*) AS NUM_REG_DIF FROM (SELECT instrmnt_id as instrmnt_id_, entty_id as entty_id_,jnt_lblty_amnt as jnt_lblty_amnt_as_is FROM cd_loan_tapes_bce.lt005_instr_ent WHERE ref_date='2024-09-30' AND nome_perimetro='Individual Corporativo' AND segmento='ESTR' AND ambito='PM' AND entidade='00100' ) A Inner join (SELECT instrmnt_id as instrmnt_id_, entty_id as entty_id_,jnt_lblty_amnt as jnt_lblty_amnt_to_be FROM bu_loantape_work.lt005_instr_ent WHERE ref_date='2024-09-30' AND nome_perimetro='Individual Corporativo' AND segmento='ESTR' AND ambito='PM' AND entidade='00100' ) B ON instrmnt_id_as_is=instrmnt_id_to_be AND entty_id_as_is=entty_id_to_be WHERE coalesce(cast(jnt_lblty_amnt_as_is AS string),'')<>coalesce(cast(jnt_lblty_amnt_to_be AS string),'') ) A | O114: =IF(O115="",N114,N114&$O$8) -> SELECT 'Validação de campos' as tipologia_teste, 'lt005_instr_ent' AS TABELA, 'jnt_lblty_amnt' AS CAMPO, '2024-09-30' as ref_date, coalesce(NUM_REG_DIF, 0) AS NUM_REG_DIF FROM (SELECT count(*) AS NUM_REG_DIF FROM (SELECT instrmnt_id as instrmnt_id_, entty_id as entty_id_,jnt_lblty_amnt as jnt_lblty_amnt_as_is FROM cd_loan_tapes_bce.lt005_instr_ent WHERE ref_date='2024-09-30' AND nome_perimetro='Individual Corporativo' AND segmento='ESTR' AND ambito='PM' AND entidade='00100' ) A Inner join (SELECT instrmnt_id as instrmnt_id_, entty_id as entty_id_,jnt_lblty_amnt as jnt_lblty_amnt_to_be FROM bu_loantape_work.lt005_instr_ent WHERE ref_date='2024-09-30' AND nome_perimetro='Individual Corporativo' AND segmento='ESTR' AND ambito='PM' AND entidade='00100' ) B ON instrmnt_id_as_is=instrmnt_id_to_be AND entty_id_as_is=entty_id_to_be WHERE coalesce(cast(jnt_lblty_amnt_as_is AS string),'')<>coalesce(cast(jnt_lblty_amnt_to_be AS string),'') ) A Union all | P114: =+P113+1 -> 4
B115: INSTR_ENTTY | C115: =_xlfn.CONCAT(Instruções!$D$13,".",VLOOKUP(B115,Instruções!$F$12:$H$17,2,0)) -> cd_loan_tapes_bce.lt005_instr_ent | D115: =_xlfn.CONCAT(Instruções!$D$14,".",VLOOKUP(B115,Instruções!$F$12:$H$17,3,0)) -> bu_loantape_work.lt005_instr_ent | E115: mn_entty_id | F115: =E115&"_"&$F$7 -> mn_entty_id_as_is | G115: =E115&"_"&$G$7 -> mn_entty_id_to_be | H115: =IF(VLOOKUP(B115,Instruções!$F$13:$J$17,5,0)="", "(SELECT "&VLOOKUP(B115,Instruções!$F$13:$J$17,4,0)&" as "&VLOOKUP(B115,Instruções!$F$13:$J$17,4,0)&"_"&$F$2&", "&E115&" as "&F115&" FROM "&C115&" WHERE "&Instruções!$D$20&") A ", "(SELECT "&VLOOKUP(B115,Instruções!$F$13:$J$17,4,0)&" as "&VLOOKUP(B115,Instruções!$F$13:$J$17,4,0)&"_"&$F$2&", "&VLOOKUP(B115,Instruções!$F$13:$J$17,5,0)&" as "&VLOOKUP(B115,Instruções!$F$13:$J$17,5,0)&"_"&$F$2&","&E115&" as "&F115&" FROM "&C115&" WHERE "&Instruções!$D$20&") A ") -> (SELECT instrmnt_id as instrmnt_id_, entty_id as entty_id_,mn_entty_id as mn_entty_id_as_is FROM cd_loan_tapes_bce.lt005_instr_ent WHERE ref_date='2024-09-30' AND nome_perimetro='Individual Corporativo' AND segmento='ESTR' AND ambito='PM' AND entidade='00100' ) A | I115: =IF(VLOOKUP(B115,Instruções!$F$13:$J$17,5,0)="", "(SELECT "&VLOOKUP(B115,Instruções!$F$13:$J$17,4,0)&" as "&VLOOKUP(B115,Instruções!$F$13:$J$17,4,0)&"_"&$G$2&", "&E115&" as "&G115&" FROM "&D115&" WHERE "&Instruções!$D$21&") B ", "(SELECT "&VLOOKUP(B115,Instruções!$F$13:$J$17,4,0)&" as "&VLOOKUP(B115,Instruções!$F$13:$J$17,4,0)&"_"&$G$2&", "&VLOOKUP(B115,Instruções!$F$13:$J$17,5,0)&" as "&VLOOKUP(B115,Instruções!$F$13:$J$17,5,0)&"_"&$G$2&","&E115&" as "&G115&" FROM "&D115&" WHERE "&Instruções!$D$21&") B ") -> (SELECT instrmnt_id as instrmnt_id_, entty_id as entty_id_,mn_entty_id as mn_entty_id_to_be FROM bu_loantape_work.lt005_instr_ent WHERE ref_date='2024-09-30' AND nome_perimetro='Individual Corporativo' AND segmento='ESTR' AND ambito='PM' AND entidade='00100' ) B | J115: =+IF(VLOOKUP(B115,Instruções!$F$13:$J$17,5,0)="", "ON "&VLOOKUP(B115,Instruções!$F$13:$J$17,4,0)&"_"&$F$7&"="&VLOOKUP(B115,Instruções!$F$13:$J$17,4,0)&"_"&$G$7&" ", "ON "&VLOOKUP(B115,Instruções!$F$13:$J$17,4,0)&"_"&$F$7&"="&VLOOKUP(B115,Instruções!$F$13:$J$17,4,0)&"_"&$G$7&" AND "&VLOOKUP(B115,Instruções!$F$13:$J$17,5,0)&"_"&$F$7&"="&VLOOKUP(B115,Instruções!$F$13:$J$17,5,0)&"_"&$G$7&" ") -> ON instrmnt_id_as_is=instrmnt_id_to_be AND entty_id_as_is=entty_id_to_be | K115: ="WHERE coalesce(cast("&F115&" AS string),'')<>coalesce(cast("&G115&" AS string),'') " -> WHERE coalesce(cast(mn_entty_id_as_is AS string),'')<>coalesce(cast(mn_entty_id_to_be AS string),'') | L115: ="SELECT count(*) AS NUM_REG_DIF FROM "&H115&" Inner join "&I115&J115&K115 -> SELECT count(*) AS NUM_REG_DIF FROM (SELECT instrmnt_id as instrmnt_id_, entty_id as entty_id_,mn_entty_id as mn_entty_id_as_is FROM cd_loan_tapes_bce.lt005_instr_ent WHERE ref_date='2024-09-30' AND nome_perimetro='Individual Corporativo' AND segmento='ESTR' AND ambito='PM' AND entidade='00100' ) A Inner join (SELECT instrmnt_id as instrmnt_id_, entty_id as entty_id_,mn_entty_id as mn_entty_id_to_be FROM bu_loantape_work.lt005_instr_ent WHERE ref_date='2024-09-30' AND nome_perimetro='Individual Corporativo' AND segmento='ESTR' AND ambito='PM' AND entidade='00100' ) B ON instrmnt_id_as_is=instrmnt_id_to_be AND entty_id_as_is=entty_id_to_be WHERE coalesce(cast(mn_entty_id_as_is AS string),'')<>coalesce(cast(mn_entty_id_to_be AS string),'') | M115: Validação de campos | N115: ="SELECT 'Validação de campos' as tipologia_teste, '"&VLOOKUP(B115,Instruções!$F$13:$J$17,3,0)&"' AS TABELA, '"&E115&"' AS CAMPO, '"&Instruções!$D$15&"' as ref_date, coalesce(NUM_REG_DIF, 0) AS NUM_REG_DIF FROM ("&L115&") A " -> SELECT 'Validação de campos' as tipologia_teste, 'lt005_instr_ent' AS TABELA, 'mn_entty_id' AS CAMPO, '2024-09-30' as ref_date, coalesce(NUM_REG_DIF, 0) AS NUM_REG_DIF FROM (SELECT count(*) AS NUM_REG_DIF FROM (SELECT instrmnt_id as instrmnt_id_, entty_id as entty_id_,mn_entty_id as mn_entty_id_as_is FROM cd_loan_tapes_bce.lt005_instr_ent WHERE ref_date='2024-09-30' AND nome_perimetro='Individual Corporativo' AND segmento='ESTR' AND ambito='PM' AND entidade='00100' ) A Inner join (SELECT instrmnt_id as instrmnt_id_, entty_id as entty_id_,mn_entty_id as mn_entty_id_to_be FROM bu_loantape_work.lt005_instr_ent WHERE ref_date='2024-09-30' AND nome_perimetro='Individual Corporativo' AND segmento='ESTR' AND ambito='PM' AND entidade='00100' ) B ON instrmnt_id_as_is=instrmnt_id_to_be AND entty_id_as_is=entty_id_to_be WHERE coalesce(cast(mn_entty_id_as_is AS string),'')<>coalesce(cast(mn_entty_id_to_be AS string),'') ) A | O115: =IF(O116="",N115,N115&$O$8) -> SELECT 'Validação de campos' as tipologia_teste, 'lt005_instr_ent' AS TABELA, 'mn_entty_id' AS CAMPO, '2024-09-30' as ref_date, coalesce(NUM_REG_DIF, 0) AS NUM_REG_DIF FROM (SELECT count(*) AS NUM_REG_DIF FROM (SELECT instrmnt_id as instrmnt_id_, entty_id as entty_id_,mn_entty_id as mn_entty_id_as_is FROM cd_loan_tapes_bce.lt005_instr_ent WHERE ref_date='2024-09-30' AND nome_perimetro='Individual Corporativo' AND segmento='ESTR' AND ambito='PM' AND entidade='00100' ) A Inner join (SELECT instrmnt_id as instrmnt_id_, entty_id as entty_id_,mn_entty_id as mn_entty_id_to_be FROM bu_loantape_work.lt005_instr_ent WHERE ref_date='2024-09-30' AND nome_perimetro='Individual Corporativo' AND segmento='ESTR' AND ambito='PM' AND entidade='00100' ) B ON instrmnt_id_as_is=instrmnt_id_to_be AND entty_id_as_is=entty_id_to_be WHERE coalesce(cast(mn_entty_id_as_is AS string),'')<>coalesce(cast(mn_entty_id_to_be AS string),'') ) A Union all | P115: =+P114+1 -> 5
B116: INSTR_PRTCTN | C116: =_xlfn.CONCAT(Instruções!$D$13,".",VLOOKUP(B116,Instruções!$F$12:$H$17,2,0)) -> cd_loan_tapes_bce.lt006_instr_prot | D116: =_xlfn.CONCAT(Instruções!$D$14,".",VLOOKUP(B116,Instruções!$F$12:$H$17,3,0)) -> bu_loantape_work.lt006_instr_prot | E116: cod_soc | F116: =E116&"_"&$F$7 -> cod_soc_as_is | G116: =E116&"_"&$G$7 -> cod_soc_to_be | H116: =IF(VLOOKUP(B116,Instruções!$F$13:$J$17,5,0)="", "(SELECT "&VLOOKUP(B116,Instruções!$F$13:$J$17,4,0)&" as "&VLOOKUP(B116,Instruções!$F$13:$J$17,4,0)&"_"&$F$2&", "&E116&" as "&F116&" FROM "&C116&" WHERE "&Instruções!$D$20&") A ", "(SELECT "&VLOOKUP(B116,Instruções!$F$13:$J$17,4,0)&" as "&VLOOKUP(B116,Instruções!$F$13:$J$17,4,0)&"_"&$F$2&", "&VLOOKUP(B116,Instruções!$F$13:$J$17,5,0)&" as "&VLOOKUP(B116,Instruções!$F$13:$J$17,5,0)&"_"&$F$2&","&E116&" as "&F116&" FROM "&C116&" WHERE "&Instruções!$D$20&") A ") -> (SELECT instrmnt_id as instrmnt_id_, prtctn_id as prtctn_id_,cod_soc as cod_soc_as_is FROM cd_loan_tapes_bce.lt006_instr_prot WHERE ref_date='2024-09-30' AND nome_perimetro='Individual Corporativo' AND segmento='ESTR' AND ambito='PM' AND entidade='00100' ) A | I116: =IF(VLOOKUP(B116,Instruções!$F$13:$J$17,5,0)="", "(SELECT "&VLOOKUP(B116,Instruções!$F$13:$J$17,4,0)&" as "&VLOOKUP(B116,Instruções!$F$13:$J$17,4,0)&"_"&$G$2&", "&E116&" as "&G116&" FROM "&D116&" WHERE "&Instruções!$D$21&") B ", "(SELECT "&VLOOKUP(B116,Instruções!$F$13:$J$17,4,0)&" as "&VLOOKUP(B116,Instruções!$F$13:$J$17,4,0)&"_"&$G$2&", "&VLOOKUP(B116,Instruções!$F$13:$J$17,5,0)&" as "&VLOOKUP(B116,Instruções!$F$13:$J$17,5,0)&"_"&$G$2&","&E116&" as "&G116&" FROM "&D116&" WHERE "&Instruções!$D$21&") B ") -> (SELECT instrmnt_id as instrmnt_id_, prtctn_id as prtctn_id_,cod_soc as cod_soc_to_be FROM bu_loantape_work.lt006_instr_prot WHERE ref_date='2024-09-30' AND nome_perimetro='Individual Corporativo' AND segmento='ESTR' AND ambito='PM' AND entidade='00100' ) B | J116: =+IF(VLOOKUP(B116,Instruções!$F$13:$J$17,5,0)="", "ON "&VLOOKUP(B116,Instruções!$F$13:$J$17,4,0)&"_"&$F$7&"="&VLOOKUP(B116,Instruções!$F$13:$J$17,4,0)&"_"&$G$7&" ", "ON "&VLOOKUP(B116,Instruções!$F$13:$J$17,4,0)&"_"&$F$7&"="&VLOOKUP(B116,Instruções!$F$13:$J$17,4,0)&"_"&$G$7&" AND "&VLOOKUP(B116,Instruções!$F$13:$J$17,5,0)&"_"&$F$7&"="&VLOOKUP(B116,Instruções!$F$13:$J$17,5,0)&"_"&$G$7&" ") -> ON instrmnt_id_as_is=instrmnt_id_to_be AND prtctn_id_as_is=prtctn_id_to_be | K116: ="WHERE coalesce(cast("&F116&" AS string),'')<>coalesce(cast("&G116&" AS string),'') " -> WHERE coalesce(cast(cod_soc_as_is AS string),'')<>coalesce(cast(cod_soc_to_be AS string),'') | L116: ="SELECT count(*) AS NUM_REG_DIF FROM "&H116&" Inner join "&I116&J116&K116 -> SELECT count(*) AS NUM_REG_DIF FROM (SELECT instrmnt_id as instrmnt_id_, prtctn_id as prtctn_id_,cod_soc as cod_soc_as_is FROM cd_loan_tapes_bce.lt006_instr_prot WHERE ref_date='2024-09-30' AND nome_perimetro='Individual Corporativo' AND segmento='ESTR' AND ambito='PM' AND entidade='00100' ) A Inner join (SELECT instrmnt_id as instrmnt_id_, prtctn_id as prtctn_id_,cod_soc as cod_soc_to_be FROM bu_loantape_work.lt006_instr_prot WHERE ref_date='2024-09-30' AND nome_perimetro='Individual Corporativo' AND segmento='ESTR' AND ambito='PM' AND entidade='00100' ) B ON instrmnt_id_as_is=instrmnt_id_to_be AND prtctn_id_as_is=prtctn_id_to_be WHERE coalesce(cast(cod_soc_as_is AS string),'')<>coalesce(cast(cod_soc_to_be AS string),'') | M116: Validação de campos | N116: ="SELECT 'Validação de campos' as tipologia_teste, '"&VLOOKUP(B116,Instruções!$F$13:$J$17,3,0)&"' AS TABELA, '"&E116&"' AS CAMPO, '"&Instruções!$D$15&"' as ref_date, coalesce(NUM_REG_DIF, 0) AS NUM_REG_DIF FROM ("&L116&") A " -> SELECT 'Validação de campos' as tipologia_teste, 'lt006_instr_prot' AS TABELA, 'cod_soc' AS CAMPO, '2024-09-30' as ref_date, coalesce(NUM_REG_DIF, 0) AS NUM_REG_DIF FROM (SELECT count(*) AS NUM_REG_DIF FROM (SELECT instrmnt_id as instrmnt_id_, prtctn_id as prtctn_id_,cod_soc as cod_soc_as_is FROM cd_loan_tapes_bce.lt006_instr_prot WHERE ref_date='2024-09-30' AND nome_perimetro='Individual Corporativo' AND segmento='ESTR' AND ambito='PM' AND entidade='00100' ) A Inner join (SELECT instrmnt_id as instrmnt_id_, prtctn_id as prtctn_id_,cod_soc as cod_soc_to_be FROM bu_loantape_work.lt006_instr_prot WHERE ref_date='2024-09-30' AND nome_perimetro='Individual Corporativo' AND segmento='ESTR' AND ambito='PM' AND entidade='00100' ) B ON instrmnt_id_as_is=instrmnt_id_to_be AND prtctn_id_as_is=prtctn_id_to_be WHERE coalesce(cast(cod_soc_as_is AS string),'')<>coalesce(cast(cod_soc_to_be AS string),'') ) A | O116: =IF(O117="",N116,N116&$O$8) -> SELECT 'Validação de campos' as tipologia_teste, 'lt006_instr_prot' AS TABELA, 'cod_soc' AS CAMPO, '2024-09-30' as ref_date, coalesce(NUM_REG_DIF, 0) AS NUM_REG_DIF FROM (SELECT count(*) AS NUM_REG_DIF FROM (SELECT instrmnt_id as instrmnt_id_, prtctn_id as prtctn_id_,cod_soc as cod_soc_as_is FROM cd_loan_tapes_bce.lt006_instr_prot WHERE ref_date='2024-09-30' AND nome_perimetro='Individual Corporativo' AND segmento='ESTR' AND ambito='PM' AND entidade='00100' ) A Inner join (SELECT instrmnt_id as instrmnt_id_, prtctn_id as prtctn_id_,cod_soc as cod_soc_to_be FROM bu_loantape_work.lt006_instr_prot WHERE ref_date='2024-09-30' AND nome_perimetro='Individual Corporativo' AND segmento='ESTR' AND ambito='PM' AND entidade='00100' ) B ON instrmnt_id_as_is=instrmnt_id_to_be AND prtctn_id_as_is=prtctn_id_to_be WHERE coalesce(cast(cod_soc_as_is AS string),'')<>coalesce(cast(cod_soc_to_be AS string),'') ) A Union all | P116: =+P115+1 -> 6
B117: INSTR_PRTCTN | C117: =_xlfn.CONCAT(Instruções!$D$13,".",VLOOKUP(B117,Instruções!$F$12:$H$17,2,0)) -> cd_loan_tapes_bce.lt006_instr_prot | D117: =_xlfn.CONCAT(Instruções!$D$14,".",VLOOKUP(B117,Instruções!$F$12:$H$17,3,0)) -> bu_loantape_work.lt006_instr_prot | E117: prtctn_allctd_vl | F117: =E117&"_"&$F$7 -> prtctn_allctd_vl_as_is | G117: =E117&"_"&$G$7 -> prtctn_allctd_vl_to_be | H117: =IF(VLOOKUP(B117,Instruções!$F$13:$J$17,5,0)="", "(SELECT "&VLOOKUP(B117,Instruções!$F$13:$J$17,4,0)&" as "&VLOOKUP(B117,Instruções!$F$13:$J$17,4,0)&"_"&$F$2&", "&E117&" as "&F117&" FROM "&C117&" WHERE "&Instruções!$D$20&") A ", "(SELECT "&VLOOKUP(B117,Instruções!$F$13:$J$17,4,0)&" as "&VLOOKUP(B117,Instruções!$F$13:$J$17,4,0)&"_"&$F$2&", "&VLOOKUP(B117,Instruções!$F$13:$J$17,5,0)&" as "&VLOOKUP(B117,Instruções!$F$13:$J$17,5,0)&"_"&$F$2&","&E117&" as "&F117&" FROM "&C117&" WHERE "&Instruções!$D$20&") A ") -> (SELECT instrmnt_id as instrmnt_id_, prtctn_id as prtctn_id_,prtctn_allctd_vl as prtctn_allctd_vl_as_is FROM cd_loan_tapes_bce.lt006_instr_prot WHERE ref_date='2024-09-30' AND nome_perimetro='Individual Corporativo' AND segmento='ESTR' AND ambito='PM' AND entidade='00100' ) A | I117: =IF(VLOOKUP(B117,Instruções!$F$13:$J$17,5,0)="", "(SELECT "&VLOOKUP(B117,Instruções!$F$13:$J$17,4,0)&" as "&VLOOKUP(B117,Instruções!$F$13:$J$17,4,0)&"_"&$G$2&", "&E117&" as "&G117&" FROM "&D117&" WHERE "&Instruções!$D$21&") B ", "(SELECT "&VLOOKUP(B117,Instruções!$F$13:$J$17,4,0)&" as "&VLOOKUP(B117,Instruções!$F$13:$J$17,4,0)&"_"&$G$2&", "&VLOOKUP(B117,Instruções!$F$13:$J$17,5,0)&" as "&VLOOKUP(B117,Instruções!$F$13:$J$17,5,0)&"_"&$G$2&","&E117&" as "&G117&" FROM "&D117&" WHERE "&Instruções!$D$21&") B ") -> (SELECT instrmnt_id as instrmnt_id_, prtctn_id as prtctn_id_,prtctn_allctd_vl as prtctn_allctd_vl_to_be FROM bu_loantape_work.lt006_instr_prot WHERE ref_date='2024-09-30' AND nome_perimetro='Individual Corporativo' AND segmento='ESTR' AND ambito='PM' AND entidade='00100' ) B | J117: =+IF(VLOOKUP(B117,Instruções!$F$13:$J$17,5,0)="", "ON "&VLOOKUP(B117,Instruções!$F$13:$J$17,4,0)&"_"&$F$7&"="&VLOOKUP(B117,Instruções!$F$13:$J$17,4,0)&"_"&$G$7&" ", "ON "&VLOOKUP(B117,Instruções!$F$13:$J$17,4,0)&"_"&$F$7&"="&VLOOKUP(B117,Instruções!$F$13:$J$17,4,0)&"_"&$G$7&" AND "&VLOOKUP(B117,Instruções!$F$13:$J$17,5,0)&"_"&$F$7&"="&VLOOKUP(B117,Instruções!$F$13:$J$17,5,0)&"_"&$G$7&" ") -> ON instrmnt_id_as_is=instrmnt_id_to_be AND prtctn_id_as_is=prtctn_id_to_be | K117: ="WHERE coalesce(cast("&F117&" AS string),'')<>coalesce(cast("&G117&" AS string),'') " -> WHERE coalesce(cast(prtctn_allctd_vl_as_is AS string),'')<>coalesce(cast(prtctn_allctd_vl_to_be AS string),'') | L117: ="SELECT count(*) AS NUM_REG_DIF FROM "&H117&" Inner join "&I117&J117&K117 -> SELECT count(*) AS NUM_REG_DIF FROM (SELECT instrmnt_id as instrmnt_id_, prtctn_id as prtctn_id_,prtctn_allctd_vl as prtctn_allctd_vl_as_is FROM cd_loan_tapes_bce.lt006_instr_prot WHERE ref_date='2024-09-30' AND nome_perimetro='Individual Corporativo' AND segmento='ESTR' AND ambito='PM' AND entidade='00100' ) A Inner join (SELECT instrmnt_id as instrmnt_id_, prtctn_id as prtctn_id_,prtctn_allctd_vl as prtctn_allctd_vl_to_be FROM bu_loantape_work.lt006_instr_prot WHERE ref_date='2024-09-30' AND nome_perimetro='Individual Corporativo' AND segmento='ESTR' AND ambito='PM' AND entidade='00100' ) B ON instrmnt_id_as_is=instrmnt_id_to_be AND prtctn_id_as_is=prtctn_id_to_be WHERE coalesce(cast(prtctn_allctd_vl_as_is AS string),'')<>coalesce(cast(prtctn_allctd_vl_to_be AS string),'') | M117: Validação de campos | N117: ="SELECT 'Validação de campos' as tipologia_teste, '"&VLOOKUP(B117,Instruções!$F$13:$J$17,3,0)&"' AS TABELA, '"&E117&"' AS CAMPO, '"&Instruções!$D$15&"' as ref_date, coalesce(NUM_REG_DIF, 0) AS NUM_REG_DIF FROM ("&L117&") A " -> SELECT 'Validação de campos' as tipologia_teste, 'lt006_instr_prot' AS TABELA, 'prtctn_allctd_vl' AS CAMPO, '2024-09-30' as ref_date, coalesce(NUM_REG_DIF, 0) AS NUM_REG_DIF FROM (SELECT count(*) AS NUM_REG_DIF FROM (SELECT instrmnt_id as instrmnt_id_, prtctn_id as prtctn_id_,prtctn_allctd_vl as prtctn_allctd_vl_as_is FROM cd_loan_tapes_bce.lt006_instr_prot WHERE ref_date='2024-09-30' AND nome_perimetro='Individual Corporativo' AND segmento='ESTR' AND ambito='PM' AND entidade='00100' ) A Inner join (SELECT instrmnt_id as instrmnt_id_, prtctn_id as prtctn_id_,prtctn_allctd_vl as prtctn_allctd_vl_to_be FROM bu_loantape_work.lt006_instr_prot WHERE ref_date='2024-09-30' AND nome_perimetro='Individual Corporativo' AND segmento='ESTR' AND ambito='PM' AND entidade='00100' ) B ON instrmnt_id_as_is=instrmnt_id_to_be AND prtctn_id_as_is=prtctn_id_to_be WHERE coalesce(cast(prtctn_allctd_vl_as_is AS string),'')<>coalesce(cast(prtctn_allctd_vl_to_be AS string),'') ) A | O117: =IF(O118="",N117,N117&$O$8) -> SELECT 'Validação de campos' as tipologia_teste, 'lt006_instr_prot' AS TABELA, 'prtctn_allctd_vl' AS CAMPO, '2024-09-30' as ref_date, coalesce(NUM_REG_DIF, 0) AS NUM_REG_DIF FROM (SELECT count(*) AS NUM_REG_DIF FROM (SELECT instrmnt_id as instrmnt_id_, prtctn_id as prtctn_id_,prtctn_allctd_vl as prtctn_allctd_vl_as_is FROM cd_loan_tapes_bce.lt006_instr_prot WHERE ref_date='2024-09-30' AND nome_perimetro='Individual Corporativo' AND segmento='ESTR' AND ambito='PM' AND entidade='00100' ) A Inner join (SELECT instrmnt_id as instrmnt_id_, prtctn_id as prtctn_id_,prtctn_allctd_vl as prtctn_allctd_vl_to_be FROM bu_loantape_work.lt006_instr_prot WHERE ref_date='2024-09-30' AND nome_perimetro='Individual Corporativo' AND segmento='ESTR' AND ambito='PM' AND entidade='00100' ) B ON instrmnt_id_as_is=instrmnt_id_to_be AND prtctn_id_as_is=prtctn_id_to_be WHERE coalesce(cast(prtctn_allctd_vl_as_is AS string),'')<>coalesce(cast(prtctn_allctd_vl_to_be AS string),'') ) A Union all | P117: =+P116+1 -> 7
B118: INSTR_PRTCTN | C118: =_xlfn.CONCAT(Instruções!$D$13,".",VLOOKUP(B118,Instruções!$F$12:$H$17,2,0)) -> cd_loan_tapes_bce.lt006_instr_prot | D118: =_xlfn.CONCAT(Instruções!$D$14,".",VLOOKUP(B118,Instruções!$F$12:$H$17,3,0)) -> bu_loantape_work.lt006_instr_prot | E118: thrd_prty_prrty_clms | F118: =E118&"_"&$F$7 -> thrd_prty_prrty_clms_as_is | G118: =E118&"_"&$G$7 -> thrd_prty_prrty_clms_to_be | H118: =IF(VLOOKUP(B118,Instruções!$F$13:$J$17,5,0)="", "(SELECT "&VLOOKUP(B118,Instruções!$F$13:$J$17,4,0)&" as "&VLOOKUP(B118,Instruções!$F$13:$J$17,4,0)&"_"&$F$2&", "&E118&" as "&F118&" FROM "&C118&" WHERE "&Instruções!$D$20&") A ", "(SELECT "&VLOOKUP(B118,Instruções!$F$13:$J$17,4,0)&" as "&VLOOKUP(B118,Instruções!$F$13:$J$17,4,0)&"_"&$F$2&", "&VLOOKUP(B118,Instruções!$F$13:$J$17,5,0)&" as "&VLOOKUP(B118,Instruções!$F$13:$J$17,5,0)&"_"&$F$2&","&E118&" as "&F118&" FROM "&C118&" WHERE "&Instruções!$D$20&") A ") -> (SELECT instrmnt_id as instrmnt_id_, prtctn_id as prtctn_id_,thrd_prty_prrty_clms as thrd_prty_prrty_clms_as_is FROM cd_loan_tapes_bce.lt006_instr_prot WHERE ref_date='2024-09-30' AND nome_perimetro='Individual Corporativo' AND segmento='ESTR' AND ambito='PM' AND entidade='00100' ) A | I118: =IF(VLOOKUP(B118,Instruções!$F$13:$J$17,5,0)="", "(SELECT "&VLOOKUP(B118,Instruções!$F$13:$J$17,4,0)&" as "&VLOOKUP(B118,Instruções!$F$13:$J$17,4,0)&"_"&$G$2&", "&E118&" as "&G118&" FROM "&D118&" WHERE "&Instruções!$D$21&") B ", "(SELECT "&VLOOKUP(B118,Instruções!$F$13:$J$17,4,0)&" as "&VLOOKUP(B118,Instruções!$F$13:$J$17,4,0)&"_"&$G$2&", "&VLOOKUP(B118,Instruções!$F$13:$J$17,5,0)&" as "&VLOOKUP(B118,Instruções!$F$13:$J$17,5,0)&"_"&$G$2&","&E118&" as "&G118&" FROM "&D118&" WHERE "&Instruções!$D$21&") B ") -> (SELECT instrmnt_id as instrmnt_id_, prtctn_id as prtctn_id_,thrd_prty_prrty_clms as thrd_prty_prrty_clms_to_be FROM bu_loantape_work.lt006_instr_prot WHERE ref_date='2024-09-30' AND nome_perimetro='Individual Corporativo' AND segmento='ESTR' AND ambito='PM' AND entidade='00100' ) B | J118: =+IF(VLOOKUP(B118,Instruções!$F$13:$J$17,5,0)="", "ON "&VLOOKUP(B118,Instruções!$F$13:$J$17,4,0)&"_"&$F$7&"="&VLOOKUP(B118,Instruções!$F$13:$J$17,4,0)&"_"&$G$7&" ", "ON "&VLOOKUP(B118,Instruções!$F$13:$J$17,4,0)&"_"&$F$7&"="&VLOOKUP(B118,Instruções!$F$13:$J$17,4,0)&"_"&$G$7&" AND "&VLOOKUP(B118,Instruções!$F$13:$J$17,5,0)&"_"&$F$7&"="&VLOOKUP(B118,Instruções!$F$13:$J$17,5,0)&"_"&$G$7&" ") -> ON instrmnt_id_as_is=instrmnt_id_to_be AND prtctn_id_as_is=prtctn_id_to_be | K118: ="WHERE coalesce(cast("&F118&" AS string),'')<>coalesce(cast("&G118&" AS string),'') " -> WHERE coalesce(cast(thrd_prty_prrty_clms_as_is AS string),'')<>coalesce(cast(thrd_prty_prrty_clms_to_be AS string),'') | L118: ="SELECT count(*) AS NUM_REG_DIF FROM "&H118&" Inner join "&I118&J118&K118 -> SELECT count(*) AS NUM_REG_DIF FROM (SELECT instrmnt_id as instrmnt_id_, prtctn_id as prtctn_id_,thrd_prty_prrty_clms as thrd_prty_prrty_clms_as_is FROM cd_loan_tapes_bce.lt006_instr_prot WHERE ref_date='2024-09-30' AND nome_perimetro='Individual Corporativo' AND segmento='ESTR' AND ambito='PM' AND entidade='00100' ) A Inner join (SELECT instrmnt_id as instrmnt_id_, prtctn_id as prtctn_id_,thrd_prty_prrty_clms as thrd_prty_prrty_clms_to_be FROM bu_loantape_work.lt006_instr_prot WHERE ref_date='2024-09-30' AND nome_perimetro='Individual Corporativo' AND segmento='ESTR' AND ambito='PM' AND entidade='00100' ) B ON instrmnt_id_as_is=instrmnt_id_to_be AND prtctn_id_as_is=prtctn_id_to_be WHERE coalesce(cast(thrd_prty_prrty_clms_as_is AS string),'')<>coalesce(cast(thrd_prty_prrty_clms_to_be AS string),'') | M118: Validação de campos | N118: ="SELECT 'Validação de campos' as tipologia_teste, '"&VLOOKUP(B118,Instruções!$F$13:$J$17,3,0)&"' AS TABELA, '"&E118&"' AS CAMPO, '"&Instruções!$D$15&"' as ref_date, coalesce(NUM_REG_DIF, 0) AS NUM_REG_DIF FROM ("&L118&") A " -> SELECT 'Validação de campos' as tipologia_teste, 'lt006_instr_prot' AS TABELA, 'thrd_prty_prrty_clms' AS CAMPO, '2024-09-30' as ref_date, coalesce(NUM_REG_DIF, 0) AS NUM_REG_DIF FROM (SELECT count(*) AS NUM_REG_DIF FROM (SELECT instrmnt_id as instrmnt_id_, prtctn_id as prtctn_id_,thrd_prty_prrty_clms as thrd_prty_prrty_clms_as_is FROM cd_loan_tapes_bce.lt006_instr_prot WHERE ref_date='2024-09-30' AND nome_perimetro='Individual Corporativo' AND segmento='ESTR' AND ambito='PM' AND entidade='00100' ) A Inner join (SELECT instrmnt_id as instrmnt_id_, prtctn_id as prtctn_id_,thrd_prty_prrty_clms as thrd_prty_prrty_clms_to_be FROM bu_loantape_work.lt006_instr_prot WHERE ref_date='2024-09-30' AND nome_perimetro='Individual Corporativo' AND segmento='ESTR' AND ambito='PM' AND entidade='00100' ) B ON instrmnt_id_as_is=instrmnt_id_to_be AND prtctn_id_as_is=prtctn_id_to_be WHERE coalesce(cast(thrd_prty_prrty_clms_as_is AS string),'')<>coalesce(cast(thrd_prty_prrty_clms_to_be AS string),'') ) A | O118: =IF(O119="",N118,N118&$O$8) -> SELECT 'Validação de campos' as tipologia_teste, 'lt006_instr_prot' AS TABELA, 'thrd_prty_prrty_clms' AS CAMPO, '2024-09-30' as ref_date, coalesce(NUM_REG_DIF, 0) AS NUM_REG_DIF FROM (SELECT count(*) AS NUM_REG_DIF FROM (SELECT instrmnt_id as instrmnt_id_, prtctn_id as prtctn_id_,thrd_prty_prrty_clms as thrd_prty_prrty_clms_as_is FROM cd_loan_tapes_bce.lt006_instr_prot WHERE ref_date='2024-09-30' AND nome_perimetro='Individual Corporativo' AND segmento='ESTR' AND ambito='PM' AND entidade='00100' ) A Inner join (SELECT instrmnt_id as instrmnt_id_, prtctn_id as prtctn_id_,thrd_prty_prrty_clms as thrd_prty_prrty_clms_to_be FROM bu_loantape_work.lt006_instr_prot WHERE ref_date='2024-09-30' AND nome_perimetro='Individual Corporativo' AND segmento='ESTR' AND ambito='PM' AND entidade='00100' ) B ON instrmnt_id_as_is=instrmnt_id_to_be AND prtctn_id_as_is=prtctn_id_to_be WHERE coalesce(cast(thrd_prty_prrty_clms_as_is AS string),'')<>coalesce(cast(thrd_prty_prrty_clms_to_be AS string),'') ) A Union all | P118: =+P117+1 -> 8
B119: INSTRMNT | C119: =_xlfn.CONCAT(Instruções!$D$13,".",VLOOKUP(B119,Instruções!$F$12:$H$17,2,0)) -> cd_loan_tapes_bce.lt002_instrument | D119: =_xlfn.CONCAT(Instruções!$D$14,".",VLOOKUP(B119,Instruções!$F$12:$H$17,3,0)) -> bu_loantape_work.lt002_instrument | E119: accmltd_chngs_fv_cr_instrmnt | F119: =E119&"_"&$F$7 -> accmltd_chngs_fv_cr_instrmnt_as_is | G119: =E119&"_"&$G$7 -> accmltd_chngs_fv_cr_instrmnt_to_be | H119: =IF(VLOOKUP(B119,Instruções!$F$13:$J$17,5,0)="", "(SELECT "&VLOOKUP(B119,Instruções!$F$13:$J$17,4,0)&" as "&VLOOKUP(B119,Instruções!$F$13:$J$17,4,0)&"_"&$F$2&", "&E119&" as "&F119&" FROM "&C119&" WHERE "&Instruções!$D$20&") A ", "(SELECT "&VLOOKUP(B119,Instruções!$F$13:$J$17,4,0)&" as "&VLOOKUP(B119,Instruções!$F$13:$J$17,4,0)&"_"&$F$2&", "&VLOOKUP(B119,Instruções!$F$13:$J$17,5,0)&" as "&VLOOKUP(B119,Instruções!$F$13:$J$17,5,0)&"_"&$F$2&","&E119&" as "&F119&" FROM "&C119&" WHERE "&Instruções!$D$20&") A ") -> (SELECT instrmnt_id as instrmnt_id_, accmltd_chngs_fv_cr_instrmnt as accmltd_chngs_fv_cr_instrmnt_as_is FROM cd_loan_tapes_bce.lt002_instrument WHERE ref_date='2024-09-30' AND nome_perimetro='Individual Corporativo' AND segmento='ESTR' AND ambito='PM' AND entidade='00100' ) A | I119: =IF(VLOOKUP(B119,Instruções!$F$13:$J$17,5,0)="", "(SELECT "&VLOOKUP(B119,Instruções!$F$13:$J$17,4,0)&" as "&VLOOKUP(B119,Instruções!$F$13:$J$17,4,0)&"_"&$G$2&", "&E119&" as "&G119&" FROM "&D119&" WHERE "&Instruções!$D$21&") B ", "(SELECT "&VLOOKUP(B119,Instruções!$F$13:$J$17,4,0)&" as "&VLOOKUP(B119,Instruções!$F$13:$J$17,4,0)&"_"&$G$2&", "&VLOOKUP(B119,Instruções!$F$13:$J$17,5,0)&" as "&VLOOKUP(B119,Instruções!$F$13:$J$17,5,0)&"_"&$G$2&","&E119&" as "&G119&" FROM "&D119&" WHERE "&Instruções!$D$21&") B ") -> (SELECT instrmnt_id as instrmnt_id_, accmltd_chngs_fv_cr_instrmnt as accmltd_chngs_fv_cr_instrmnt_to_be FROM bu_loantape_work.lt002_instrument WHERE ref_date='2024-09-30' AND nome_perimetro='Individual Corporativo' AND segmento='ESTR' AND ambito='PM' AND entidade='00100' ) B | J119: =+IF(VLOOKUP(B119,Instruções!$F$13:$J$17,5,0)="", "ON "&VLOOKUP(B119,Instruções!$F$13:$J$17,4,0)&"_"&$F$7&"="&VLOOKUP(B119,Instruções!$F$13:$J$17,4,0)&"_"&$G$7&" ", "ON "&VLOOKUP(B119,Instruções!$F$13:$J$17,4,0)&"_"&$F$7&"="&VLOOKUP(B119,Instruções!$F$13:$J$17,4,0)&"_"&$G$7&" AND "&VLOOKUP(B119,Instruções!$F$13:$J$17,5,0)&"_"&$F$7&"="&VLOOKUP(B119,Instruções!$F$13:$J$17,5,0)&"_"&$G$7&" ") -> ON instrmnt_id_as_is=instrmnt_id_to_be | K119: ="WHERE coalesce(cast("&F119&" AS string),'')<>coalesce(cast("&G119&" AS string),'') " -> WHERE coalesce(cast(accmltd_chngs_fv_cr_instrmnt_as_is AS string),'')<>coalesce(cast(accmltd_chngs_fv_cr_instrmnt_to_be AS string),'') | L119: ="SELECT count(*) AS NUM_REG_DIF FROM "&H119&" Inner join "&I119&J119&K119 -> SELECT count(*) AS NUM_REG_DIF FROM (SELECT instrmnt_id as instrmnt_id_, accmltd_chngs_fv_cr_instrmnt as accmltd_chngs_fv_cr_instrmnt_as_is FROM cd_loan_tapes_bce.lt002_instrument WHERE ref_date='2024-09-30' AND nome_perimetro='Individual Corporativo' AND segmento='ESTR' AND ambito='PM' AND entidade='00100' ) A Inner join (SELECT instrmnt_id as instrmnt_id_, accmltd_chngs_fv_cr_instrmnt as accmltd_chngs_fv_cr_instrmnt_to_be FROM bu_loantape_work.lt002_instrument WHERE ref_date='2024-09-30' AND nome_perimetro='Individual Corporativo' AND segmento='ESTR' AND ambito='PM' AND entidade='00100' ) B ON instrmnt_id_as_is=instrmnt_id_to_be WHERE coalesce(cast(accmltd_chngs_fv_cr_instrmnt_as_is AS string),'')<>coalesce(cast(accmltd_chngs_fv_cr_instrmnt_to_be AS string),'') | M119: Validação de campos | N119: ="SELECT 'Validação de campos' as tipologia_teste, '"&VLOOKUP(B119,Instruções!$F$13:$J$17,3,0)&"' AS TABELA, '"&E119&"' AS CAMPO, '"&Instruções!$D$15&"' as ref_date, coalesce(NUM_REG_DIF, 0) AS NUM_REG_DIF FROM ("&L119&") A " -> SELECT 'Validação de campos' as tipologia_teste, 'lt002_instrument' AS TABELA, 'accmltd_chngs_fv_cr_instrmnt' AS CAMPO, '2024-09-30' as ref_date, coalesce(NUM_REG_DIF, 0) AS NUM_REG_DIF FROM (SELECT count(*) AS NUM_REG_DIF FROM (SELECT instrmnt_id as instrmnt_id_, accmltd_chngs_fv_cr_instrmnt as accmltd_chngs_fv_cr_instrmnt_as_is FROM cd_loan_tapes_bce.lt002_instrument WHERE ref_date='2024-09-30' AND nome_perimetro='Individual Corporativo' AND segmento='ESTR' AND ambito='PM' AND entidade='00100' ) A Inner join (SELECT instrmnt_id as instrmnt_id_, accmltd_chngs_fv_cr_instrmnt as accmltd_chngs_fv_cr_instrmnt_to_be FROM bu_loantape_work.lt002_instrument WHERE ref_date='2024-09-30' AND nome_perimetro='Individual Corporativo' AND segmento='ESTR' AND ambito='PM' AND entidade='00100' ) B ON instrmnt_id_as_is=instrmnt_id_to_be WHERE coalesce(cast(accmltd_chngs_fv_cr_instrmnt_as_is AS string),'')<>coalesce(cast(accmltd_chngs_fv_cr_instrmnt_to_be AS string),'') ) A | O119: =IF(O120="",N119,N119&$O$8) -> SELECT 'Validação de campos' as tipologia_teste, 'lt002_instrument' AS TABELA, 'accmltd_chngs_fv_cr_instrmnt' AS CAMPO, '2024-09-30' as ref_date, coalesce(NUM_REG_DIF, 0) AS NUM_REG_DIF FROM (SELECT count(*) AS NUM_REG_DIF FROM (SELECT instrmnt_id as instrmnt_id_, accmltd_chngs_fv_cr_instrmnt as accmltd_chngs_fv_cr_instrmnt_as_is FROM cd_loan_tapes_bce.lt002_instrument WHERE ref_date='2024-09-30' AND nome_perimetro='Individual Corporativo' AND segmento='ESTR' AND ambito='PM' AND entidade='00100' ) A Inner join (SELECT instrmnt_id as instrmnt_id_, accmltd_chngs_fv_cr_instrmnt as accmltd_chngs_fv_cr_instrmnt_to_be FROM bu_loantape_work.lt002_instrument WHERE ref_date='2024-09-30' AND nome_perimetro='Individual Corporativo' AND segmento='ESTR' AND ambito='PM' AND entidade='00100' ) B ON instrmnt_id_as_is=instrmnt_id_to_be WHERE coalesce(cast(accmltd_chngs_fv_cr_instrmnt_as_is AS string),'')<>coalesce(cast(accmltd_chngs_fv_cr_instrmnt_to_be AS string),'') ) A Union all | P119: =+P118+1 -> 9
B120: INSTRMNT | C120: =_xlfn.CONCAT(Instruções!$D$13,".",VLOOKUP(B120,Instruções!$F$12:$H$17,2,0)) -> cd_loan_tapes_bce.lt002_instrument | D120: =_xlfn.CONCAT(Instruções!$D$14,".",VLOOKUP(B120,Instruções!$F$12:$H$17,3,0)) -> bu_loantape_work.lt002_instrument | E120: accmltd_imprmnt_instrmnt | F120: =E120&"_"&$F$7 -> accmltd_imprmnt_instrmnt_as_is | G120: =E120&"_"&$G$7 -> accmltd_imprmnt_instrmnt_to_be | H120: =IF(VLOOKUP(B120,Instruções!$F$13:$J$17,5,0)="", "(SELECT "&VLOOKUP(B120,Instruções!$F$13:$J$17,4,0)&" as "&VLOOKUP(B120,Instruções!$F$13:$J$17,4,0)&"_"&$F$2&", "&E120&" as "&F120&" FROM "&C120&" WHERE "&Instruções!$D$20&") A ", "(SELECT "&VLOOKUP(B120,Instruções!$F$13:$J$17,4,0)&" as "&VLOOKUP(B120,Instruções!$F$13:$J$17,4,0)&"_"&$F$2&", "&VLOOKUP(B120,Instruções!$F$13:$J$17,5,0)&" as "&VLOOKUP(B120,Instruções!$F$13:$J$17,5,0)&"_"&$F$2&","&E120&" as "&F120&" FROM "&C120&" WHERE "&Instruções!$D$20&") A ") -> (SELECT instrmnt_id as instrmnt_id_, accmltd_imprmnt_instrmnt as accmltd_imprmnt_instrmnt_as_is FROM cd_loan_tapes_bce.lt002_instrument WHERE ref_date='2024-09-30' AND nome_perimetro='Individual Corporativo' AND segmento='ESTR' AND ambito='PM' AND entidade='00100' ) A | I120: =IF(VLOOKUP(B120,Instruções!$F$13:$J$17,5,0)="", "(SELECT "&VLOOKUP(B120,Instruções!$F$13:$J$17,4,0)&" as "&VLOOKUP(B120,Instruções!$F$13:$J$17,4,0)&"_"&$G$2&", "&E120&" as "&G120&" FROM "&D120&" WHERE "&Instruções!$D$21&") B ", "(SELECT "&VLOOKUP(B120,Instruções!$F$13:$J$17,4,0)&" as "&VLOOKUP(B120,Instruções!$F$13:$J$17,4,0)&"_"&$G$2&", "&VLOOKUP(B120,Instruções!$F$13:$J$17,5,0)&" as "&VLOOKUP(B120,Instruções!$F$13:$J$17,5,0)&"_"&$G$2&","&E120&" as "&G120&" FROM "&D120&" WHERE "&Instruções!$D$21&") B ") -> (SELECT instrmnt_id as instrmnt_id_, accmltd_imprmnt_instrmnt as accmltd_imprmnt_instrmnt_to_be FROM bu_loantape_work.lt002_instrument WHERE ref_date='2024-09-30' AND nome_perimetro='Individual Corporativo' AND segmento='ESTR' AND ambito='PM' AND entidade='00100' ) B | J120: =+IF(VLOOKUP(B120,Instruções!$F$13:$J$17,5,0)="", "ON "&VLOOKUP(B120,Instruções!$F$13:$J$17,4,0)&"_"&$F$7&"="&VLOOKUP(B120,Instruções!$F$13:$J$17,4,0)&"_"&$G$7&" ", "ON "&VLOOKUP(B120,Instruções!$F$13:$J$17,4,0)&"_"&$F$7&"="&VLOOKUP(B120,Instruções!$F$13:$J$17,4,0)&"_"&$G$7&" AND "&VLOOKUP(B120,Instruções!$F$13:$J$17,5,0)&"_"&$F$7&"="&VLOOKUP(B120,Instruções!$F$13:$J$17,5,0)&"_"&$G$7&" ") -> ON instrmnt_id_as_is=instrmnt_id_to_be | K120: ="WHERE coalesce(cast("&F120&" AS string),'')<>coalesce(cast("&G120&" AS string),'') " -> WHERE coalesce(cast(accmltd_imprmnt_instrmnt_as_is AS string),'')<>coalesce(cast(accmltd_imprmnt_instrmnt_to_be AS string),'') | L120: ="SELECT count(*) AS NUM_REG_DIF FROM "&H120&" Inner join "&I120&J120&K120 -> SELECT count(*) AS NUM_REG_DIF FROM (SELECT instrmnt_id as instrmnt_id_, accmltd_imprmnt_instrmnt as accmltd_imprmnt_instrmnt_as_is FROM cd_loan_tapes_bce.lt002_instrument WHERE ref_date='2024-09-30' AND nome_perimetro='Individual Corporativo' AND segmento='ESTR' AND ambito='PM' AND entidade='00100' ) A Inner join (SELECT instrmnt_id as instrmnt_id_, accmltd_imprmnt_instrmnt as accmltd_imprmnt_instrmnt_to_be FROM bu_loantape_work.lt002_instrument WHERE ref_date='2024-09-30' AND nome_perimetro='Individual Corporativo' AND segmento='ESTR' AND ambito='PM' AND entidade='00100' ) B ON instrmnt_id_as_is=instrmnt_id_to_be WHERE coalesce(cast(accmltd_imprmnt_instrmnt_as_is AS string),'')<>coalesce(cast(accmltd_imprmnt_instrmnt_to_be AS string),'') | M120: Validação de campos | N120: ="SELECT 'Validação de campos' as tipologia_teste, '"&VLOOKUP(B120,Instruções!$F$13:$J$17,3,0)&"' AS TABELA, '"&E120&"' AS CAMPO, '"&Instruções!$D$15&"' as ref_date, coalesce(NUM_REG_DIF, 0) AS NUM_REG_DIF FROM ("&L120&") A " -> SELECT 'Validação de campos' as tipologia_teste, 'lt002_instrument' AS TABELA, 'accmltd_imprmnt_instrmnt' AS CAMPO, '2024-09-30' as ref_date, coalesce(NUM_REG_DIF, 0) AS NUM_REG_DIF FROM (SELECT count(*) AS NUM_REG_DIF FROM (SELECT instrmnt_id as instrmnt_id_, accmltd_imprmnt_instrmnt as accmltd_imprmnt_instrmnt_as_is FROM cd_loan_tapes_bce.lt002_instrument WHERE ref_date='2024-09-30' AND nome_perimetro='Individual Corporativo' AND segmento='ESTR' AND ambito='PM' AND entidade='00100' ) A Inner join (SELECT instrmnt_id as instrmnt_id_, accmltd_imprmnt_instrmnt as accmltd_imprmnt_instrmnt_to_be FROM bu_loantape_work.lt002_instrument WHERE ref_date='2024-09-30' AND nome_perimetro='Individual Corporativo' AND segmento='ESTR' AND ambito='PM' AND entidade='00100' ) B ON instrmnt_id_as_is=instrmnt_id_to_be WHERE coalesce(cast(accmltd_imprmnt_instrmnt_as_is AS string),'')<>coalesce(cast(accmltd_imprmnt_instrmnt_to_be AS string),'') ) A | O120: =IF(O121="",N120,N120&$O$8) -> SELECT 'Validação de campos' as tipologia_teste, 'lt002_instrument' AS TABELA, 'accmltd_imprmnt_instrmnt' AS CAMPO, '2024-09-30' as ref_date, coalesce(NUM_REG_DIF, 0) AS NUM_REG_DIF FROM (SELECT count(*) AS NUM_REG_DIF FROM (SELECT instrmnt_id as instrmnt_id_, accmltd_imprmnt_instrmnt as accmltd_imprmnt_instrmnt_as_is FROM cd_loan_tapes_bce.lt002_instrument WHERE ref_date='2024-09-30' AND nome_perimetro='Individual Corporativo' AND segmento='ESTR' AND ambito='PM' AND entidade='00100' ) A Inner join (SELECT instrmnt_id as instrmnt_id_, accmltd_imprmnt_instrmnt as accmltd_imprmnt_instrmnt_to_be FROM bu_loantape_work.lt002_instrument WHERE ref_date='2024-09-30' AND nome_perimetro='Individual Corporativo' AND segmento='ESTR' AND ambito='PM' AND entidade='00100' ) B ON instrmnt_id_as_is=instrmnt_id_to_be WHERE coalesce(cast(accmltd_imprmnt_instrmnt_as_is AS string),'')<>coalesce(cast(accmltd_imprmnt_instrmnt_to_be AS string),'') ) A Union all | P120: =+P119+1 -> 10
