Workbook
Name asefadf: #REF!
Name bn: '[1]Code List'!#REF!

Sheet Sheet1
A1: LOANS Efectivo y otros depósitos a la vista / Cash balances and other deposits | B1: (All)
A2: LOANS Administraciones públicas / General governments | B2: (All)
A3: LOANS Entidades de crédito / Credit institutions | B3: (All)
A4: LOANS Otras sociedades financieras / Other financial corporations | B4: (All)
A5: LOANS Sociedad no financieras / Non financial corporations | B5: (All)
A6: LOANS Hogares / Households | B6: (All)
A7: DEBT SECURITIES | B7: (All)
A9: Row Labels | B9: Count of Data field
A10: ENTITY | B10: 85
A11: INSTR_ENTITY | B11: 5
A12: INSTR_PROTECTION | B12: 6
A13: INSTRUMENT | B13: 184
A14: PROTECTION | B14: 39
A15: Grand Total | B15: 319

Sheet READ ME - APPLICABILITY
B5: GUIDANCE ON THE APPLICABILITY OF LOAN TAPE' DATA FIELDS
B7: Corporation has performed an assessment of the applicability of data fields considering two axis:
B8: - counterparty sector (central banks, general governments, credit institutions, other financial corporations, non-financial corporations and households) and
B9: - type of product (cash and other demand deposits, debt securities and loans)
B11: As a consequence, within 'Overview' tab, columns F to M (highlighted in red) determine the applicability of data fields, considering the following rules:
B13: Possible values:
B14: - If remarked as 'Y' = Yes, it does apply, those fields might be applicable, depending on the characteristics of each instrument,entity or protection.
B16: - If remarked as 'N' = No, not applicable, it means that given the counterparty sector or the type of product we conclude that this field is not applicable and therefore,
B17: Unit shall informe these fields as 'Not applicable', with the proper format set up for each field (Date: 1111-11-11 ; Text: N/A ; Numeric: 11111111111).
B19: - If remarked as 'Corporation' = Field to be populated by Corporation, it means that the Unit will inform this field as not applicable, with the proper format
B20: set up for each field (Date: 1111-11-11 ; Text: N/A ; Numeric: 11111111111).
B22: Special case for debt securities:
... B24: given that 'Entity' table might be populated with loan information (in almost all cases, we estimate that the issuer of debt securities acquired will have direct exposures - loans as well).

Sheet Overview
B1: ID Data field / Field order | C1: Table | D1: Category | E1: Anacredit | F1: Data field | G1: Efectivo y otros depósitos a la vista / Cash balances and other deposits | H1: Bancos Centrales / Central Banks | I1: Administraciones públicas / General governments | J1: Entidades de crédito / Credit institutions | K1: Otras sociedades financieras / Other financial corporations | L1: Sociedades no financieras / Non financial corporations | M1: Hogares / Households | N1: DEBT SECURITIES (this column only applies to report the instrument table) | O1: Non-contractual balances and Accounting adjustments (this column only applies to report the instrument table) | P1: Instrument cancelled (this column only applies to report the instrument table) | Q1: Data Types | R1: Guidance on data types | S1: Default value for missing data | T1: Default value for not applicable fields to be used WHEN the field is applicable for the corresponding segment (F to L columns ) | U1: Default value for not applicable fields to be used WHEN: (1) Non-contractual balances and accounting adjustments (2) If the field is not applicable for the corresponding segment (F to L columns) | V1: Field name | W1: Field Definition / Additional Guidance | X1: BDR Status (*) Not applicable = not identified as available in BDR | Y1: BDR Definition | Z1: BDR Comments | AA1: Structural ECB Loan Tape | AB1: Green Dashboard | AC1: Pillar III ESG | AD1: Green Finance | AE1: ESG Risks | AF1: Leveraged Finance | AG1: D + 15 [Green Dashboard] | AH1: D + 18 [+ Pillar III ESG] | AI1: > D + 18 [+ ECB Loan Tape]
A2: 0 | B2: IN.061 | C2: INSTRUMENT | D2: Financial Information | E2: Y | F2: ACCMLTD_CHNGS_FV_CR_INSTRMNT | G2: N | H2: Y | I2: Y | J2: Y | K2: Y | L2: Y | M2: Y | N2: Y | O2: Y | P2: Y | Q2: FLOAT 2 decimal places | R2: Use decimal point, no thousands seperator | S2: 99999999999 | T2: 11111111111 | U2: 11111111111 | V2: Accumulated changes in fair value due to credit risk | W2: Accumulated changes in fair value due to credit risk in accordance with Part 2.46 of Annex V to Implementing Regulation (EU) No 680/2014. | X2: Not applicable | Y2: N/A | Z2: - | AA2: Y | AB2: Y | AC2: Y | AD2: N | AE2: N | AF2: N | AG2: Y | AH2: Y | AI2: Y | AJ2: N | AK2: 0
A3: 6.1. Fora âmbito | Campos concluídos - Sem necessidade de espec. | B3: IN.088 | C3: INSTRUMENT | D3: Impairment | E3: Y | F3: ACCMLTD_IMPRMNT_INSTRMNT | G3: Y | H3: Y | I3: Y | J3: Y | K3: Y | L3: Y | M3: Y | N3: Y | O3: Y | P3: Y | Q3: FLOAT 2 decimal places | R3: Use decimal point, no thousands seperator | S3: 99999999999 | T3: 11111111111 | U3: 11111111111 | V3: Sum of LLPs and other allowances | W3: The amount of loss allowances that are held against or are allocated to the instrument on the reporting reference date. This data attribute applies to instruments subject to impairment under the applied accounting standard. Under IFRS, the accumulated impairment relates to the following amounts: (i) loss allowance at an amount equal to 12-month expected credit losses; (ii) loss allowance at an amount equal to lifetime expected credit losses. Under nGAAP, the accumulated impairment relates to the following amounts: (i) loss allowance at an amount equal to specific allowances; (ii) loss allowance at an amount equal to general allowances. | X3: Not applicable | Y3: N/A | Z3: - | AA3: Y | AB3: Y | AC3: Y | AD3: N | AE3: N | AF3: Y | AG3: Y | AH3: Y | AI3: Y | AJ3: Y | AK3: 0
A4: 3. Campos em testes ou c/ incidências | B4: IN.089 | C4: INSTRUMENT | D4: Impairment | E4: N | F4: ACCMLTD_IMPRMNT_INSTRMNT_PRVS | G4: Y | H4: Y | I4: Y | J4: Y | K4: Y | L4: Y | M4: Y | N4: Y | O4: N | P4: N | Q4: FLOAT 2 decimal places | R4: Use decimal point, no thousands seperator | S4: 99999999999 | T4: 11111111111 | U4: 11111111111 | V4: Previous sum of LLPs and other allowances | W4: The amount of loss allowances that are held against or are allocated to the instrument one year before the reference date, i.e. T-1. This data attribute applies to instruments subject to impairment under the applied accounting standard. Under IFRS, the accumulated impairment relates to the following amounts: (i) loss allowance at an amount equal to 12-month expected credit losses; (ii) loss allowance at an amount equal to lifetime expected credit losses. Under nGAAP, the accumulated impairment relates to the following amounts: (i) loss allowance at an amount equal to specific allowances; (ii) loss allowance at an amount equal to general allowances. | X4: Not applicable | Y4: N/A | Z4: - | AA4: Y | AB4: N | AC4: N | AD4: N | AE4: N | AF4: Y | AG4: N | AH4: N | AI4: Y | AJ4: Y | AK4: 0
A5: 6.1. Fora âmbito | Campos concluídos - Sem necessidade de espec. | B5: IN.090 | C5: INSTRUMENT | D5: Impairment | E5: Y | F5: ACCMLTD_WRTFFS_INSTRMNT | G5: N | H5: Y | I5: Y | J5: Y | K5: Y | L5: Y | M5: Y | N5: Y | O5: N | P5: N | Q5: FLOAT 2 decimal places | R5: Use decimal point, no thousands seperator | S5: 99999999999 | T5: 11111111111 | U5: 11111111111 | V5: Accumulated write-offs | W5: Cumulative amount of principal and past due interest of any debt instrument that the institution is no longer recognising because they are considered uncollectible, independently of the portfolio in which they were included. Write-offs could be caused both by reductions in the carrying amount of financial assets recognised directly in profit or loss and by reductions in the amounts of the allowance accounts for credit losses set off against the carrying amount of financial assets. | X5: Not applicable | Y5: N/A | Z5: - | AA5: Y | AB5: N | AC5: N | AD5: N | AE5: N | AF5: Y | AG5: N | AH5: N | AI5: Y | AJ5: Y | AK5: 0
A6: 6.1. Fora âmbito | Campos concluídos - Sem necessidade de espec. | B6: IN.062 | C6: INSTRUMENT | D6: Financial Information | E6: Y | F6: ACCNTNG_CLSSFCTN | G6: Y | H6: Y | I6: Y | J6: Y | K6: Y | L6: Y | M6: Y | N6: Y | O6: Y | P6: Y | Q6: =HYPERLINK("#"&"CodeList!"&ADDRESS(2,MATCH($F6,CodeList!$2:$2,0)+1,),"Code List") -> Code List | R6: Use codes from the code list sheet | S6: 99999999999 | T6: 11111111111 | U6: 11111111111 | V6: Accounting portfolio | W6: Accounting portfolio where the instrument is recorded in accordance with the accounting standard – IFRS or national GAAP – under Regulation (EU) 2015/534 (ECB/2015/13) applied by the observed agent’s legal entity. | X6: Not applicable | Y6: N/A | Z6: - | AA6: Y | AB6: Y | AC6: Y | AD6: N | AE6: N | AF6: Y | AG6: Y | AH6: Y | AI6: Y | AJ6: Y | AK6: 0
A7: 6.4. Fora âmbito | Re-especificação de campos complexos - Dem. Fin. CIB | B7: EN.018 | C7: ENTITY | D7: Classification | E7: Y | F7: ACCNTNG_FRMWRK_SL | G7: Y | H7: Y | I7: Y | J7: Y | K7: Y | L7: Y | M7: N | Q7: =HYPERLINK("#"&"CodeList!"&ADDRESS(2,MATCH($F7,CodeList!$2:$2,0)+1,),"Code List") -> Code List | R7: Use codes from the code list sheet | S7: 99999999999 | T7: 11111111111 | U7: 11111111111 | V7: Accounting standard counterparty | W7: Accounting standard counterparty. | X7: Not applicable | Y7: N/A | Z7: - | AA7: Y | AB7: N | AC7: N | AD7: N | AE7: N | AF7: Y | AG7: N | AH7: N | AI7: Y | AJ7: Y | AK7: 0
A8: 2.2 Re-especificação de campos complexos - Resto | B8: IN.063 | C8: INSTRUMENT | D8: Financial Information | E8: Y | F8: ACCRD_INTRST_INSTRMNT | G8: N | H8: Y | I8: Y | J8: Y | K8: Y | L8: Y | M8: Y | N8: Y | O8: N | P8: N | Q8: FLOAT 2 decimal places | R8: Use decimal point, no thousands seperator | S8: 99999999999 | T8: 11111111111 | U8: 11111111111 | V8: Accrued interest balance as recognised on the balance sheet | W8: The amount of accrued interest on loans at the reporting reference date as defined in Regulation (EU) No 1071/2013 (ECB/2013/33). In accordance with the general principle of accruals accounting, interest receivable on instruments should be subject to on-balance sheet recording as it accrues (i.e. on an accruals basis) rather than when it is actually received (i.e. on a cash basis). | X8: Yes - Equivalent | Y8: JM_CAMB_SIT_BDI - E0688_INTEDEV | Z8: - | AA8: Y | AB8: N | AC8: N | AD8: N | AE8: N | AF8: Y | AG8: N | AH8: N | AI8: Y | AJ8: Y | AK8: 0
A9: 0 | B9: EN.130 | C9: ENTITY | D9: General | E9: Y | F9: ADDRSS_CTY | G9: Y | H9: Y | I9: Y | J9: Y | K9: Y | L9: Y | M9: Y | Q9: VARCHAR2(255) | R9: Free (latin) text without special characters (semicolon, quotes, …) | S9: MISS | T9: N/A | U9: N/A | V9: Address: city/town/village | W9: Unit should report in this field the city, town or village of residence of the counterparty. | X9: Not applicable | Y9: N/A | AA9: Y | AB9: N | AC9: N | AD9: N | AE9: N | AF9: N | AG9: N | AH9: N | AI9: Y | AJ9: #N/A | AK9: 0
A10: 0 | B10: EN.131 | C10: ENTITY | D10: General | E10: Y | F10: ADDRSS_STRT | G10: Y | H10: Y | I10: Y | J10: Y | K10: Y | L10: Y | M10: Y | Q10: VARCHAR2(255) | R10: Free (latin) text without special characters (semicolon, quotes, …) | S10: MISS | T10: N/A | U10: N/A | V10: Address: street | W10: Unit should report in this field the street address of residence of the counterparty, including the street number. | X10: Not applicable | Y10: N/A | AA10: Y | AB10: N | AC10: N | AD10: N | AE10: N | AF10: N | AG10: N | AH10: N | AI10: Y | AJ10: #N/A | AK10: 0
A11: #N/A | B11: PR.060 | C11: PROTECTION | D11: Collateral Insurance | E11: N | F11: AMNT_CVRD_INSRNC | G11: N | H11: Y | I11: Y | J11: Y | K11: Y | L11: Y | M11: Y | Q11: FLOAT 2 decimal places | R11: Use decimal point, no thousands seperator | S11: 99999999999 | T11: 11111111111 | U11: 11111111111 | V11: Total amount covered by the insurance | W11: Total amount covered by the insurance. If the insurance covers more than one hazard, please report the sum up of all the amounts covered by the insurance | X11: Not applicable | Y11: N/A | Z11: - | AA11: N | AB11: N | AC11: N | AD11: N | AE11: Y | AF11: N | AG11: N | AH11: N | AI11: Y | AJ11: #N/A | AK11: 0
A12: 2.2 Re-especificação de campos complexos - Resto | B12: IN.064 | C12: INSTRUMENT | D12: Financial Information | E12: N | F12: AMNT_D_AT_MTRTY | G12: N | H12: Y | I12: Y | J12: Y | K12: Y | L12: Y | M12: Y | N12: N | O12: N | P12: N | Q12: FLOAT 2 decimal places | R12: Use decimal point, no thousands seperator | S12: 99999999999 | T12: 11111111111 | U12: 11111111111 | V12: Amount due at the legal final maturity date | W12: Total amount of principal repayment to be paid at the final legal maturity date (i.e. DT_LGL_FNL_MTRTY), i.e. amount of last instalment at maturity date. | X12: Not applicable | Y12: N/A | Z12: - | AA12: Y | AB12: N | AC12: N | AD12: N | AE12: N | AF12: Y | AG12: N | AH12: N | AI12: Y | AJ12: Y | AK12: 0
A13: 6.4. Fora âmbito | Re-especificação de campos complexos - Dem. Fin. CIB | B13: EN.051 | C13: ENTITY | D13: Financial Information | E13: Y | F13: ANNL_TRNVR_LE | G13: Y | H13: Y | I13: Y | J13: Y | K13: Y | L13: Y | M13: N | Q13: FLOAT 2 decimal places | R13: Use decimal point, no thousands seperator | S13: 99999999999 | T13: 11111111111 | U13: 11111111111 | V13: Annual turnover counterparty (LE) | W13: Annual sales volume net of all discounts and sales taxes in accordance with Recommendation 2003/361/EC. Equivalent to the concept of 'total annual sales' in Article 153(4) of Regulation (EU) No 575/2013. Please report on solo entity level unless advised otherwise. | X13: Not applicable | Y13: N/A | Z13: - | AA13: Y | AB13: N | AC13: Y | AD13: N | AE13: N | AF13: Y | AG13: N | AH13: Y | AI13: Y | AJ13: Y | AK13: 0
A14: 0 | B14: EN.086 | C14: ENTITY | D14: Financial Information | E14: N | F14: ANNL_TRNVR_LE_BDR | G14: Y | H14: Y | I14: Y | J14: Y | K14: Y | L14: Y | M14: N | Q14: FLOAT 2 decimal places | R14: Use decimal point, no thousands seperator | S14: 99999999999 | T14: 11111111111 | U14: 11111111111 | V14: BDR Annual turnover counterparty (LE) | W14: BDR Annual sales volume net of all discounts and sales taxes in accordance with Recommendation 2003/361/EC. Equivalent to the concept of 'total annual sales' in Article 153(4) of Regulation (EU) No 575/2013. Please report on solo entity level unless advised otherwise. | X14: Yes - Equivalent | Y14: JM_CLIEN_JURI - G5508_IMPFACTM | Z14: - | AA14: Y | AB14: N | AC14: N | AD14: N | AE14: N | AF14: N | AG14: N | AH14: N | AI14: Y | AJ14: #N/A | AK14: 0
A15: 6.4. Fora âmbito | Re-especificação de campos complexos - Dem. Fin. CIB | B15: EN.052 | C15: ENTITY | D15: Financial Information | E15: N | F15: ANNL_TRNVR_PRVS | G15: Y | H15: Y | I15: Y | J15: Y | K15: Y | L15: Y | M15: N | Q15: FLOAT 2 decimal places | R15: Use decimal point, no thousands seperator | S15: 99999999999 | T15: 11111111111 | U15: 11111111111 | V15: Annual turnover counterparty (LE) at previous reporting | W15: Annual sales volume net of all discounts and sales taxes in accordance with Recommendation 2003/361/EC. Equivalent to the concept of 'total annual sales' in Article 153(4) of Regulation (EU) No 575/2013. Please report on solo entity level unless advised otherwise. | X15: Not applicable | Y15: N/A | Z15: - | AA15: Y | AB15: N | AC15: N | AD15: N | AE15: N | AF15: Y | AG15: N | AH15: N | AI15: Y | AJ15: Y | AK15: 0
A16: 0 | B16: EN.087 | C16: ENTITY | D16: Financial Information | E16: N | F16: ANNL_TRNVR_PRVS_BDR | G16: Y | H16: Y | I16: Y | J16: Y | K16: Y | L16: Y | M16: N | Q16: FLOAT 2 decimal places | R16: Use decimal point, no thousands seperator | S16: 99999999999 | T16: 11111111111 | U16: 11111111111 | V16: BDR Annual turnover counterparty (LE) at previous reporting | W16: BDR Annual sales volume net of all discounts and sales taxes in accordance with Recommendation 2003/361/EC. Equivalent to the concept of 'total annual sales' in Article 153(4) of Regulation (EU) No 575/2013. Please report on solo entity level unless advised otherwise. | X16: Yes - Equivalent | Y16: JM_CLIEN_JURI - G5508_IMPFACTM | Z16: To be computed using the one at previous reporting | AA16: Y | AB16: N | AC16: N | AD16: N | AE16: N | AF16: N | AG16: N | AH16: N | AI16: Y | AJ16: #N/A | AK16: 0
A17: 0 | B17: IN.125 | C17: INSTRUMENT | D17: Interest Rates | E17: Y | F17: ANNLSD_AGRD_RT | G17: Y | H17: Y | I17: Y | J17: Y | K17: Y | L17: Y | M17: Y | N17: Y | O17: N | P17: N | Q17: FLOAT 6 decimal places | R17: Use decimal point, no thousands seperator | S17: 99999999999 | T17: 11111111111 | U17: 11111111111 | V17: Interest rate at the reference date | W17: Annualised agreed rate or narrowly defined interest rate in accordance with Regulation (EU) No 1072/2013 of the European Central Bank (ECB/2013/34). | X17: Yes - Equivalent | Y17: JM_CONTR_OTROS - E0623_TIP_INT | Z17: - | AA17: Y | AB17: N | AC17: Y | AD17: N | AE17: N | AF17: N | AG17: N | AH17: Y | AI17: Y | AJ17: N | AK17: 0
A18: #N/A | B18: PR.017 | C18: PROTECTION | D18: Appraisal | E18: N | F18: APPRSL_CRRNCY | G18: N | H18: Y | I18: Y | J18: Y | K18: Y | L18: Y | M18: Y | Q18: =HYPERLINK("#"&"CodeList!"&ADDRESS(2,MATCH($F18,CodeList!$2:$2,0)+1,),"Code List") -> Code List | R18: Use codes from the code list sheet | S18: MISS | T18: N/A | U18: N/A | V18: Appraisal currency | W18: Appraisal currency. | X18: Yes - Equivalent | Y18: JM_VAL_GARA - G4134_CODDIV | Z18: - | AA18: Y | AB18: N | AC18: N | AD18: N | AE18: N | AF18: N | AG18: N | AH18: N | AI18: Y | AJ18: N | AK18: 0
A19: #N/A | B19: PR.018 | C19: PROTECTION | D19: Appraisal | E19: N | F19: APPRSR | G19: N | H19: Y | I19: Y | J19: Y | K19: Y | L19: Y | M19: Y | Q19: VARCHAR2(255) | R19: Free (latin) text without special characters (semicolon, quotes, …) | S19: MISS | T19: N/A | U19: N/A | V19: Provider of latest valuation (appraiser) | W19: Name of the appraising company. If the bank carries out the appraisal itself report "Internal". | X19: Yes - Equivalent | Y19: JM_VAL_GARA - G4134_NOMENTI | Z19: - | AA19: Y | AB19: N | AC19: N | AD19: N | AE19: N | AF19: N | AG19: N | AH19: N | AI19: Y | AJ19: N | AK19: 0
A20: 4. Campos com NOK controlos Corporativos | B20: IN.091 | C20: INSTRUMENT | D20: Impairment | E20: Y | F20: ARRRS_INSTRMNT | G20: N | H20: Y | I20: Y | J20: Y | K20: Y | L20: Y | M20: Y | N20: Y | O20: N | P20: N | Q20: FLOAT 2 decimal places | R20: Use decimal point, no thousands seperator | S20: 99999999999 | T20: 11111111111 | U20: 11111111111 | V20: Total exposure in arrears | W20: Aggregated amount of the principal, interest and any fee payment outstanding at the reporting date, which is contractually due and has not been paid (past due). | X20: Not applicable | Y20: N/A | Z20: - | AA20: Y | AB20: N | AC20: N | AD20: N | AE20: N | AF20: Y | AG20: N | AH20: N | AI20: Y | AJ20: Y | AK20: 0
A21: 0 | B21: IN.092 | C21: INSTRUMENT | D21: Impairment | E21: N | F21: ARRRS_INSTRMNT_12M | G21: N | H21: Y | I21: Y | J21: Y | K21: Y | L21: Y | M21: Y | N21: Y | O21: N | P21: N | Q21: FLOAT 2 decimal places | R21: Use decimal point, no thousands seperator | S21: 99999999999 | T21: 11111111111 | U21: 11111111111 | V21: Highest total exposure in arrears in the last 12 months before the reference date | W21: Highest aggregated amount of the principal, interest and any fee payment outstanding at a period of 12 months before the reference date, which is contractually due and has not been paid (past due). | X21: Not applicable | Y21: N/A | Z21: - | AA21: Y | AB21: N | AC21: N | AD21: N | AE21: N | AF21: N | AG21: N | AH21: N | AI21: Y | AJ21: N | AK21: 0
A22: 0 | B22: IN.155 | C22: INSTRUMENT | D22: Security characteristics | E22: Y | F22: ASST_SCRT_CLSS | G22: N | H22: N | I22: N | J22: N | K22: N | L22: N | M22: N | N22: Y | O22: N | P22: N | Q22: =HYPERLINK("#"&"CodeList!"&ADDRESS(2,MATCH($F22,CodeList!$2:$2,0)+1,),"Code List") -> Code List | R22: Use codes from the code list sheet | S22: 99999999999 | T22: 11111111111 | U22: 11111111111 | V22: Asset securitisation class | W22: To be reported if the instrument is a securitisation or covered bond. | X22: Not applicable | Y22: N/A | Z22: - | AA22: Y | AB22: N | AC22: N | AD22: N | AE22: N | AF22: N | AG22: N | AH22: N | AI22: Y | AJ22: #N/A | AK22: 0
A23: 0 | B23: IN.196 | C23: INSTRUMENT | D23: Financial Information | E23: N | F23: AVRG_BLNC | G23: Y | H23: Y | I23: Y | J23: Y | K23: Y | L23: Y | M23: Y | N23: Y | O23: N | P23: Y | Q23: FLOAT 2 decimal places | R23: Use decimal point, no thousands seperator | S23: 99999999999 | T23: 11111111111 | U23: 11111111111 | V23: Average balance | W23: The average balance is a monthly data, which is calculated at instrument level as the average of daily balances of the instrument. | X23: Not applicable | Y23: N/A | Z23: - | AA23: N | AB23: Y | AC23: N | AD23: N | AE23: N | AF23: N | AG23: Y | AH23: Y | AI23: Y | AJ23: #N/A | AK23: 0
A24: 0 | B24: IN.210 | C24: INSTRUMENT | D24: Financial Information | E24: N | F24: AVRG_BLNC_OFF_BLNC | G24: Y | H24: Y | I24: Y | J24: Y | K24: Y | L24: Y | M24: Y | N24: N | O24: N | P24: Y | Q24: FLOAT 2 decimal places | R24: Use decimal point, no thousands seperator | S24: 99999999999 | T24: 11111111111 | U24: 11111111111 | V24: Average off balance | W24: The average off balance amount is a monthly data, which is calculated at instrument level as the average of daily off balances of the instrument. | X24: Not applicable | Y24: N/A | Z24: - | AA24: N | AB24: Y | AC24: N | AD24: N | AE24: N | AF24: N | AG24: Y | AH24: Y | AI24: Y | AJ24: #N/A | AK24: 0
A25: #N/A | B25: PR.064 | C25: PROTECTION | D25: Collateral Features | E25: N | F25: BLDNG_AR | G25: N | H25: Y | I25: Y | J25: Y | K25: Y | L25: Y | M25: Y | Q25: FLOAT 6 decimal places | R25: Use decimal point, no thousands seperator | S25: 99999999999 | T25: 11111111111 | U25: 11111111111 | V25: Building Area (M2) | W25: The area of the building in square metres. | X25: Not applicable | Y25: N/A | Z25: - | AA25: N | AB25: N | AC25: Y | AD25: N | AE25: Y | AF25: N | AG25: N | AH25: Y | AI25: Y | AJ25: #N/A | AK25: 0
A26: 0 | B26: IN.248 | C26: INSTRUMENT | D26: Accounting information | E26: Y | F26: BLNC_SHT_RCGNTN | G26: Y | H26: Y | I26: Y | J26: Y | K26: Y | L26: Y | M26: Y | N26: Y | O26: N | P26: N | Q26: =HYPERLINK("#"&"CodeList!"&ADDRESS(2,MATCH($F26,CodeList!$2:$2,0)+1,),"Code List") -> Code List | R26: Use codes from the code list sheet | S26: MISS | T26: N/A | U26: N/A | V26: Balance sheet recognition | W26: Balance sheet recognition of the financial asset. This data attribute classifies the reported instruments pursuant to their balance sheet recognition in accordance with Annex III and Template 15 in Annex IV to the ITS. | X26: Not applicable | Y26: N/A | Z26: - | AA26: Y | AB26: N | AC26: N | AD26: N | AE26: N | AF26: N | AG26: N | AH26: N | AI26: Y | AJ26: #N/A | AK26: 0
A27: 6.1. Fora âmbito | Campos concluídos - Sem necessidade de espec. | B27: IN.015 | C27: INSTRUMENT | D27: Classification | E27: N | F27: BRCHD_CVNNTS | G27: N | H27: N | I27: N | J27: N | K27: Y | L27: Y | M27: N | N27: N | O27: N | P27: N | Q27: VARCHAR2(255) | R27: Free (latin) text without special characters (semicolon, quotes, …) | S27: MISS | T27: N/A | U27: N/A | V27: Breached covenants | W27: Breached covenants separated by comma (,). | X27: Not applicable | Y27: N/A | Z27: - | AA27: Y | AB27: N | AC27: N | AD27: N | AE27: N | AF27: Y | AG27: N | AH27: N | AI27: Y | AJ27: Y | AK27: 0
A28: 0 | B28: IN.202 | C28: INSTRUMENT | D28: Classification | E28: N | F28: BSNSS_AREA | G28: Y | H28: Y | I28: Y | J28: Y | K28: Y | L28: Y | M28: Y | N28: Y | O28: N | P28: Y | Q28: Code List | R28: Use codes from the code list sheet | S28: MISS | T28: Default value not allowed | U28: N/A | V28: Business Area | W28: Business areas where the instrument falls according to Management Control segmentation | X28: Not applicable | Y28: N/A | Z28: - | AA28: N | AB28: Y | AC28: N | AD28: N | AE28: N | AF28: N | AG28: Y | AH28: Y | AI28: Y | AJ28: #N/A | AK28: 0
A29: 0 | B29: IN.222 | C29: INSTRUMENT | D29: Classification | E29: N | F29: BSNSS_AREA_CCRR | G29: Y | H29: Y | I29: Y | J29: Y | K29: Y | L29: Y | M29: Y | N29: Y | O29: N | P29: Y | Q29: Code List | R29: Use codes from the code list sheet | S29: MISS | T29: Default value not allowed | U29: N/A | V29: Business Area related to CIB | W29: Business areas where the instrument falls according to Management Control segmentation | X29: Not applicable | Y29: N/A | Z29: - | AA29: N | AB29: Y | AC29: N | AD29: N | AE29: N | AF29: N | AG29: Y | AH29: Y | AI29: Y | AJ29: #N/A | AK29: 0
A30: 0 | B30: IN.209 | C30: INSTRUMENT | D30: Classification | E30: N | F30: BSNSS_AREA_DSTNTN | G30: Y | H30: Y | I30: Y | J30: Y | K30: Y | L30: Y | M30: Y | N30: Y | O30: N | P30: Y | Q30: Code List | R30: Use codes from the code list sheet | S30: MISS | T30: N/A | U30: N/A | V30: Destination Business area | W30: Entity code of the business area to which interbusiness applies (business area destination) | X30: Not applicable | Y30: N/A | Z30: - | AA30: N | AB30: Y | AC30: N | AD30: N | AE30: N | AF30: N | AG30: Y | AH30: Y | AI30: Y | AJ30: #N/A | AK30: 0
A31: 0 | B31: EN.053 | C31: ENTITY | D31: Financial Information | E31: N | F31: CAPEX | G31: Y | H31: Y | I31: Y | J31: Y | K31: Y | L31: Y | M31: N | Q31: FLOAT 2 decimal places | R31: Use decimal point, no thousands seperator | S31: 99999999999 | T31: 11111111111 | U31: 11111111111 | V31: Capital expenditures at most recent reported figures | W31: Capital expenditures at most recent reported figures. Please report on solo entity level unless advised otherwise. | X31: Not applicable | Y31: N/A | Z31: - | AA31: Y | AB31: N | AC31: N | AD31: N | AE31: N | AF31: N | AG31: N | AH31: N | AI31: Y | AJ31: N | AK31: 0
A32: 0 | B32: EN.054 | C32: ENTITY | D32: Financial Information | E32: N | F32: CAPEX_PRVS | G32: Y | H32: Y | I32: Y | J32: Y | K32: Y | L32: Y | M32: N | Q32: FLOAT 2 decimal places | R32: Use decimal point, no thousands seperator | S32: 99999999999 | T32: 11111111111 | U32: 11111111111 | V32: Capital expenditures at previous reported figures | W32: Capital expenditures at previous reported figures. Please report on solo entity level unless advised otherwise. | X32: Not applicable | Y32: N/A | Z32: - | AA32: Y | AB32: N | AC32: N | AD32: N | AE32: N | AF32: N | AG32: N | AH32: N | AI32: Y | AJ32: N | AK32: 0
A33: 6.1. Fora âmbito | Campos concluídos - Sem necessidade de espec. | B33: IN.065 | C33: INSTRUMENT | D33: Financial Information | E33: N | F33: CCF | G33: Y | H33: Y | I33: Y | J33: Y | K33: Y | L33: Y | M33: Y | N33: N | O33: N | P33: N | Q33: FLOAT 6 decimal places | R33: Use decimal point, no thousands seperator | S33: 99999999999 | T33: 11111111111 | U33: 11111111111 | V33: Credit conversion factor (CCF) according to CRR | W33: Credit conversion factor according to regulation (EU) No 575/2013. | X33: Yes - Computed | Y33: IF Contract in JM_CTO_AJ_REG THEN O9209_K2; ELSE IF Contract in JM_AMP_AJ_STD THEN T0254_CCF_SFB; ELSE IF Contract in JM_SIM_AJ_STD THEN T0256_CCF_SFB | Z33: - | AA33: Y | AB33: Y | AC33: N | AD33: N | AE33: N | AF33: Y | AG33: Y | AH33: Y | AI33: Y | AJ33: Y | AK33: 0
A34: 0 | B34: IN.016 | C34: INSTRUMENT | D34: Classification | E34: N | F34: CHNNL_ORGNTN | G34: N | H34: Y | I34: Y | J34: Y | K34: Y | L34: Y | M34: Y | N34: N | O34: N | P34: N | Q34: =HYPERLINK("#"&"CodeList!"&ADDRESS(2,MATCH($F34,CodeList!$2:$2,0)+1,),"Code List") -> Code List | R34: Use codes from the code list sheet | S34: 99999999999 | T34: 11111111111 | U34: 11111111111 | V34: Channel of origination | W34: Description of the loan origination channel. | X34: Yes - Mapping | Y34: BDR - Code List | Z34: - | AA34: Y | AB34: N | AC34: N | AD34: N | AE34: N | AF34: N | AG34: N | AH34: N | AI34: Y | AJ34: N | AK34: 0
A35: 0 | B35: EN.055 | C35: ENTITY | D35: Financial Information | E35: N | F35: CLLCTN_MD | G35: N | H35: Y | I35: Y | J35: Y | K35: Y | L35: Y | M35: Y | Q35: =HYPERLINK("#"&"CodeList!"&ADDRESS(2,MATCH($F35,CodeList!$2:$2,0)+1,),"Code List") -> Code List | R35: Use codes from the code list sheet | S35: 99999999999 | T35: 11111111111 | U35: 11111111111 | V35: Collection mode | W35: Collection mode. Hard collection would be similar to foreclosure proceedings while soft collection means to call the collateral without any legal proceedings. | X35: Not applicable | Y35: N/A | Z35: - | AA35: Y | AB35: N | AC35: N | AD35: N | AE35: N | AF35: N | AG35: N | AH35: N | AI35: Y | AJ35: N | AK35: 0
A36: 0 | B36: IN.093 | C36: INSTRUMENT | D36: Impairment | E36: Y | F36: CMLTV_RCVRS_SNC_DFLT_INSTRMNT | G36: N | H36: Y | I36: Y | J36: Y | K36: Y | L36: Y | M36: Y | N36: Y | O36: N | P36: N | Q36: FLOAT 2 decimal places | R36: Use decimal point, no thousands seperator | S36: 99999999999 | T36: 11111111111 | U36: 11111111111 | V36: Cumulative recoveries since default | W36: The total amount recovered since the date of default. | X36: Not applicable | Y36: N/A | Z36: - | AA36: Y | AB36: N | AC36: N | AD36: N | AE36: N | AF36: N | AG36: N | AH36: N | AI36: Y | AJ36: N | AK36: 0
A37: 0 | B37: IN.066 | C37: INSTRUMENT | D37: Financial Information | E37: Y | F37: CMMTMNT_INCPTN_INSTRMNT | G37: N | H37: Y | I37: Y | J37: Y | K37: Y | L37: Y | M37: Y | N37: N | O37: N | P37: N | Q37: FLOAT 2 decimal places | R37: Use decimal point, no thousands seperator | S37: 99999999999 | T37: 11111111111 | U37: 11111111111 | V37: Commitment amount at inception | W37: Observed agent’s maximum exposure to credit risk on the inception date of the instrument, without taking into account any protection held or other credit enhancements. Total commitment amount on the inception date is established during the approval process and is intended to restrict an observed agent’s amount of credit risk to a given counterparty for the relevant instrument. | X37: Yes - Computed | Y37: E0623_IMP1LIMI at inception date (G4095_FECHAPER) | Z37: - | AA37: Y | AB37: N | AC37: N | AD37: N | AE37: N | AF37: N | AG37: N | AH37: N | AI37: Y | AJ37: N | AK37: 0
A38: 0 | B38: IN.067 | C38: INSTRUMENT | D38: Financial Information | E38: N | F38: CMMTMNT_INSTRMNT | G38: N | H38: Y | I38: Y | J38: Y | K38: Y | L38: Y | M38: Y | N38: N | O38: N | P38: N | Q38: FLOAT 2 decimal places | R38: Use decimal point, no thousands seperator | S38: 99999999999 | T38: 11111111111 | U38: 11111111111 | V38: Commitment amount at reference date | W38: Observed agent’s maximum exposure to credit risk on the reference date of the instrument, without taking into account any protection held or other credit enhancements. Total commitment amount on the reference date is established during the life cycle of the loan and is intended to restrict an observed agent’s amount of credit risk to a given counterparty for the relevant instrument. | X38: Not applicable | Y38: N/A | Z38: - | AA38: Y | AB38: N | AC38: N | AD38: N | AE38: N | AF38: N | AG38: N | AH38: N | AI38: Y | AJ38: N | AK38: 0
A39: 0 | B39: IN.145 | C39: INSTRUMENT | D39: COVID19 | E39: N | F39: CMPLNT_MRTR_C19_NM | G39: N | H39: N | I39: N | J39: N | K39: N | L39: Y | M39: Y | N39: N | O39: N | P39: N | Q39: VARCHAR2(255) | R39: Free (latin) text without special characters (semicolon, quotes, …) | S39: MISS | T39: N/A | U39: N/A | V39: Internal name of EBA compliant moratoria as registered by the bank. Please report all COVID-related measures until 31 December 2022. Afterwards, please report Not Applicable default value | W39: The name of the EBA compliant moratoria. EBA/GL/2020/07 Guidelines on reporting and disclosure of exposures subject to measures applied in response to the COVID-19 crisis. Data attribute shall be reported if not waived by the competent authority according to points (a), (c), (d) or (e) of Article 19 of EBA/GL/2020/07 Guidelines on reporting and disclosure of exposures subject to measures applied in response to the COVID-19 crisis. | X39: Yes - Computed | Y39: IF G7025_MOTRENUG in (26;27;28;29) THEN R8180_DESCBARL | Z39: It is necessary to identify the link between the global encoder and the local one | AA39: Y | AB39: N | AC39: N | AD39: N | AE39: N | AF39: N | AG39: N | AH39: N | AI39: Y | AJ39: Y | AK39: 0
A40: 0 | B40: IN.233 | C40: INSTRUMENT | D40: General | E40: N | F40: CNCLLD_INSTRMNT_STTS | G40: Y | H40: Y | I40: Y | J40: Y | K40: Y | L40: Y | M40: Y | N40: Y | O40: Y | P40: Y | Q40: =HYPERLINK("#"&"CodeList!"&ADDRESS(2,MATCH($F40,CodeList!$2:$2,0)+1,),"Code List") -> Code List | R40: Use codes from the code list sheet | S40: MISS | T40: Default value not allowed | U40: Default value not allowed | V40: Cancelled instrument status | W40: This field indicates if the instrument has been cancelled or not during the month of the reference date | X40: Not applicable | Y40: N/A | Z40: - | AA40: N | AB40: Y | AC40: N | AD40: N | AE40: N | AF40: N | AG40: Y | AH40: Y | AI40: Y | AJ40: #N/A | AK40: 0
A41: 0 | B41: IN.006 | C41: INSTRUMENT | D41: Portfolio identification | E41: N | F41: CNSMPTN_FNRP18 | G41: N | H41: N | I41: N | J41: N | K41: N | L41: N | M41: Y | N41: N | O41: Y | P41: N | Q41: Y, N | R41: Boolean: Y/N | S41: Default value not allowed | T41: Default value not allowed | U41: Default value not allowed | V41: Flag of Credit for consumption | W41: Loans granted to Consumer Credit (reported in FinRep 18 rows No 170, 913, 933: “of which: credit for consumption”). | X41: Not applicable | Y41: N/A | Z41: - | AA41: Y | AB41: N | AC41: N | AD41: N | AE41: N | AF41: N | AG41: N | AH41: N | AI41: Y | AJ41: #N/A | AK41: 0
A42: #N/A | B42: PR.029 | C42: PROTECTION | D42: Collateral Features | E42: N | F42: CNSTRCTN_STTS | G42: N | H42: N | I42: N | J42: N | K42: N | L42: Y | M42: Y | Q42: =HYPERLINK("#"&"CodeList!"&ADDRESS(2,MATCH($F42,CodeList!$2:$2,0)+1,),"Code List") -> Code List | R42: Use codes from the code list sheet | S42: 99999999999 | T42: 11111111111 | U42: 11111111111 | V42: Construction status | W42: Current status of the construction progress. The term "permit" refers to the received zoning- and building permission. | X42: Yes - Mapping | Y42: BDR - Code List | Z42: - | AA42: Y | AB42: N | AC42: N | AD42: N | AE42: N | AF42: N | AG42: N | AH42: N | AI42: Y | AJ42: N | AK42: 0
A43: 0 | B43: IN.009 | C43: INSTRUMENT | D43: General | E43: Y | F43: CNTRCT_ID | G43: Y | H43: Y | I43: Y | J43: Y | K43: Y | L43: Y | M43: Y | N43: Y | O43: N | P43: N | Q43: VARCHAR2(60) | R43: Free (latin) text without special characters (semicolon, quotes, …) | S43: Default value not allowed | T43: Default value not allowed | U43: N/A | V43: Contract ID | W43: An identifier applied by the reporting agent to uniquely identify each contract. Each contract must have one contract identifier. This value will not change over time and cannot be used as the contract identifier for any other contract. | X43: Not applicable | Y43: N/A | Z43: - | AA43: Y | AB43: N | AC43: N | AD43: N | AE43: N | AF43: N | AG43: N | AH43: N | AI43: Y | AJ43: N | AK43: 0
A44: 0 | B44: IN.191 | C44: INSTRUMENT | D44: General | E44: N | F44: CNTRCT_ID_BDR | G44: Y | H44: Y | I44: Y | J44: Y | K44: Y | L44: Y | M44: Y | N44: Y | O44: N | P44: N | Q44: VARCHAR2(60) | R44: Free (latin) text without special characters (semicolon, quotes, …) | S44: MISS | T44: N/A | U44: N/A | V44: BDR Contract ID | W44: BDR internal contract identifier (CONTRA1). Each contract must have one contract identifier. This value will not change over time and cannot be used as the contract identifier for any other contract. | X44: Yes - Equivalent | Y44: CONTRA1 | Z44: - | AA44: Y | AB44: N | AC44: N | AD44: N | AE44: N | AF44: N | AG44: N | AH44: N | AI44: Y | AJ44: #N/A | AK44: 0
A45: 0 | B45: EN.115 | C45: ENTITY | D45: General | E45: N | F45: CNTRPRTY_EMSSNS_SCP1 | G45: N | H45: N | I45: N | J45: N | K45: N | L45: Y | M45: N | Q45: FLOAT 6 decimal places | R45: Use decimal point, no thousands seperator | S45: 99999999999 | T45: 11111111111 | U45: 11111111111 | V45: Counterparty's emissions scope 1 | W45: Scope 1 emissions corresponding to the Counterparty | X45: Not applicable | Y45: N/A | Z45: - | AA45: N | AB45: N | AC45: Y | AD45: N | AE45: Y | AF45: N | AG45: N | AH45: Y | AI45: Y | AJ45: #N/A | AK45: 0
A46: 0 | B46: EN.116 | C46: ENTITY | D46: General | E46: N | F46: CNTRPRTY_EMSSNS_SCP2 | G46: N | H46: N | I46: N | J46: N | K46: N | L46: Y | M46: N | Q46: FLOAT 6 decimal places | R46: Use decimal point, no thousands seperator | S46: 99999999999 | T46: 11111111111 | U46: 11111111111 | V46: Counterparty's emissions scope 2 | W46: Scope 2 emissions corresponding to the Counterparty | X46: Not applicable | Y46: N/A | Z46: - | AA46: N | AB46: N | AC46: Y | AD46: N | AE46: Y | AF46: N | AG46: N | AH46: Y | AI46: Y | AJ46: #N/A | AK46: 0
A47: 0 | B47: EN.117 | C47: ENTITY | D47: General | E47: N | F47: CNTRPRTY_EMSSNS_SCP3 | G47: N | H47: N | I47: N | J47: N | K47: N | L47: Y | M47: N | Q47: FLOAT 6 decimal places | R47: Use decimal point, no thousands seperator | S47: 99999999999 | T47: 11111111111 | U47: 11111111111 | V47: Counterparty's emissions scope 3 | W47: Scope 3 emissions corresponding to the Counterparty | X47: Not applicable | Y47: N/A | Z47: - | AA47: N | AB47: N | AC47: Y | AD47: N | AE47: Y | AF47: N | AG47: N | AH47: Y | AI47: Y | AJ47: #N/A | AK47: 0
A48: 6.1. Fora âmbito | Campos concluídos - Sem necessidade de espec. | B48: EN.002 | C48: ENTITY | D48: General | E48: Y | F48: CNTRY | G48: Y | H48: Y | I48: Y | J48: Y | K48: Y | L48: Y | M48: Y | Q48: =HYPERLINK("#"&"CodeList!"&ADDRESS(2,MATCH($F48,CodeList!$2:$2,0)+1,),"Code List") -> Code List | R48: Use codes from the code list sheet | S48: MISS | T48: N/A | U48: N/A | V48: Country of counterparty residence | W48: Country of counterparty residence. | X48: Yes - Mapping | Y48: BDR - Code List | Z48: - | AA48: Y | AB48: N | AC48: Y | AD48: N | AE48: Y | AF48: Y | AG48: N | AH48: Y | AI48: Y | AJ48: Y | AK48: 0
A49: 6.1. Fora âmbito | Campos concluídos - Sem necessidade de espec. | B49: EN.001 | C49: ENTITY | D49: Cargabal entity | E49: N | F49: COD_SOC | G49: Y | H49: Y | I49: Y | J49: Y | K49: Y | L49: Y | M49: Y | Q49: VARCHAR2(5) | R49: Free (latin) text without special characters (semicolon, quotes, …) | S49: Default value not allowed | T49: Default value not allowed | U49: Default value not allowed | V49: Entity code of the informing society. | W49: Cargabal code or internal identifier of the informing society. | X49: Not applicable | Y49: N/A | Z49: - | AA49: Y | AB49: N | AC49: Y | AD49: N | AE49: Y | AF49: Y | AG49: N | AH49: Y | AI49: Y | AJ49: #N/A | AK49: 0
A50: 6.1. Fora âmbito | Campos concluídos - Sem necessidade de espec. | B50: IE.001 | C50: INSTR_ENTITY | D50: Cargabal entity | E50: N | F50: COD_SOC | G50: Y | H50: Y | I50: Y | J50: Y | K50: Y | L50: Y | M50: Y | Q50: VARCHAR2(5) | R50: Free (latin) text without special characters (semicolon, quotes, …) | S50: Default value not allowed | T50: Default value not allowed | U50: Default value not allowed | V50: Entity code of the informing society. | W50: Cargabal code or internal identifier of the informing society. | X50: Not applicable | Y50: N/A | Z50: - | AA50: Y | AB50: N | AC50: Y | AD50: N | AE50: N | AF50: Y | AG50: N | AH50: Y | AI50: Y | AJ50: #N/A | AK50: 0
A51: 6.1. Fora âmbito | Campos concluídos - Sem necessidade de espec. | B51: IN.001 | C51: INSTRUMENT | D51: Cargabal entity | E51: N | F51: COD_SOC | G51: Y | H51: Y | I51: Y | J51: Y | K51: Y | L51: Y | M51: Y | N51: Y | O51: Y | P51: Y | Q51: VARCHAR2(5) | R51: Free (latin) text without special characters (semicolon, quotes, …) | S51: Default value not allowed | T51: Default value not allowed | U51: Default value not allowed | V51: Entity code of the informing society. | W51: Cargabal code or internal identifier of the informing society. | X51: Not applicable | Y51: N/A | Z51: - | AA51: Y | AB51: Y | AC51: Y | AD51: N | AE51: Y | AF51: Y | AG51: Y | AH51: Y | AI51: Y | AJ51: #N/A | AK51: 0
A52: #N/A | B52: IP.001 | C52: INSTR_PROTECTION | D52: General | E52: N | F52: COD_SOC | G52: N | H52: Y | I52: Y | J52: Y | K52: Y | L52: Y | M52: Y | Q52: VARCHAR2(5) | R52: Free (latin) text without special characters (semicolon, quotes, …) | S52: Default value not allowed | T52: Default value not allowed | U52: Default value not allowed | V52: Entity code of the informing society. | W52: Cargabal code or internal identifier of the informing society. | X52: Not applicable | Y52: N/A | Z52: - | AA52: Y | AB52: Y | AC52: Y | AD52: N | AE52: N | AF52: N | AG52: Y | AH52: Y | AI52: Y | AJ52: #N/A | AK52: 0
A53: #N/A | B53: PR.001 | C53: PROTECTION | D53: Cargabal entity | E53: N | F53: COD_SOC | G53: N | H53: Y | I53: Y | J53: Y | K53: Y | L53: Y | M53: Y | Q53: VARCHAR2(5) | R53: Free (latin) text without special characters (semicolon, quotes, …) | S53: Default value not allowed | T53: Default value not allowed | U53: Default value not allowed | V53: Entity code of the informing society. | W53: Cargabal code or internal identifier of the informing society. | X53: Not applicable | Y53: N/A | Z53: - | AA53: Y | AB53: Y | AC53: Y | AD53: N | AE53: Y | AF53: N | AG53: Y | AH53: Y | AI53: Y | AJ53: #N/A | AK53: 0
A54: #N/A | B54: AC.001 | C54: INSTR_ACTIVITY | D54: Cargabal entity | E54: N | F54: COD_SOC | G54: N | H54: Y | I54: Y | J54: Y | K54: Y | L54: Y | M54: Y | Q54: VARCHAR2(5) | R54: Free (latin) text without special characters (semicolon, quotes, …) | S54: Default value not allowed | T54: Default value not allowed | U54: - | V54: Entity code of the informing society. | W54: Cargabal code or internal identifier of the informing society. | X54: Not applicable | Y54: N/A | Z54: - | AA54: N | AB54: Y | AC54: Y | AD54: N | AE54: N | AF54: N | AG54: Y | AH54: Y | AI54: Y | AJ54: #N/A | AK54: 0
A55: 0 | B55: IN.208 | C55: INSTRUMENT | D55: Cargabal entity | E55: N | F55: COD_SOC_DSTNTN | G55: Y | H55: Y | I55: Y | J55: Y | K55: Y | L55: Y | M55: Y | N55: Y | O55: N | P55: Y | Q55: VARCHAR2(5) | R55: Free (latin) text without special characters (semicolon, quotes, …) | S55: Default value not allowed | T55: 00000 | U55: 00000 | V55: Cargabal identification code of the destination entity | W55: Entity code of the company to which interbusiness applies (destination society) | X55: Not applicable | Y55: N/A | Z55: - | AA55: N | AB55: Y | AC55: N | AD55: N | AE55: N | AF55: N | AG55: Y | AH55: Y | AI55: Y | AJ55: #N/A | AK55: 0
A56: 0 | B56: IN.192 | C56: INSTRUMENT | D56: Cargabal entity | E56: N | F56: COD_SOC_INTRGRP | G56: Y | H56: Y | I56: Y | J56: Y | K56: Y | L56: Y | M56: Y | N56: Y | O56: Y | P56: Y | Q56: VARCHAR2(5) | R56: Free (latin) text without special characters (semicolon, quotes, …) | S56: Default value not allowed | T56: 00000 | U56: 00000 | V56: Cargabal identification code of the intragroup exposure | W56: Cargabal identification code or internal identifier of the intragroup exposure | X56: Not applicable | Y56: N/A | Z56: - | AA56: Y | AB56: Y | AC56: N | AD56: N | AE56: N | AF56: N | AG56: Y | AH56: Y | AI56: Y | AJ56: #N/A | AK56: 0
A57: 0 | B57: IN.156 | C57: INSTRUMENT | D57: Security characteristics | E57: N | F57: CPN_CRRNCY | G57: N | H57: N | I57: N | J57: N | K57: N | L57: N | M57: N | N57: Y | O57: N | P57: N | Q57: =HYPERLINK("#"&"CodeList!"&ADDRESS(2,MATCH($F57,CodeList!$2:$2,0)+1,),"Code List") -> Code List | R57: Use codes from the code list sheet | S57: MISS | T57: N/A | U57: N/A | V57: Coupon currency | W57: Currency in which the coupon is paid. | X57: Yes - Equivalent | Y57: JM_CONTR_BIS - G4095_CODDIV | Z57: - | AA57: Y | AB57: N | AC57: N | AD57: N | AE57: N | AF57: N | AG57: N | AH57: N | AI57: Y | AJ57: #N/A | AK57: 0
A58: 0 | B58: IN.179 | C58: INSTRUMENT | D58: Security characteristics | E58: N | F58: CPN_RT_FLTNG | G58: N | H58: N | I58: N | J58: N | K58: N | L58: N | M58: N | N58: Y | O58: N | P58: N | Q58: FLOAT 6 decimal places | R58: Use decimal point, no thousands seperator | S58: 99999999999 | T58: 11111111111 | U58: 11111111111 | V58: Coupon rate (if floating). | W58: Coupon rate (if floating). | X58: Yes - Equivalent | Y58: JM_CONTR_OTROS - E0623_TIP_INTE | Z58: - | AA58: Y | AB58: N | AC58: N | AD58: N | AE58: N | AF58: N | AG58: N | AH58: N | AI58: Y | AJ58: #N/A | AK58: 0
A59: 0 | B59: IN.157 | C59: INSTRUMENT | D59: Security characteristics | E59: N | F59: CPN_RT_FXD | G59: N | H59: N | I59: N | J59: N | K59: N | L59: N | M59: N | N59: Y | O59: N | P59: N | Q59: FLOAT 6 decimal places | R59: Use decimal point, no thousands seperator | S59: 99999999999 | T59: 11111111111 | U59: 11111111111 | V59: Coupon rate (if fixed). | W59: Coupon rate (if fixed). | X59: Yes - Equivalent | Y59: JM_CONTR_OTROS - E0623_TIP_INT | Z59: - | AA59: Y | AB59: N | AC59: N | AD59: N | AE59: N | AF59: N | AG59: N | AH59: N | AI59: Y | AJ59: #N/A | AK59: 0
A60: 0 | B60: EN.019 | C60: ENTITY | D60: Classification | E60: N | F60: CR_FLG | G60: Y | H60: Y | I60: Y | J60: Y | K60: Y | L60: Y | M60: Y | Q60: Y, N | R60: Boolean: Y/N | S60: MISS | T60: N/A | U60: N/A | V60: Cure flag for entity which was classified as non-performing in the last 1.5 years and is classified as performing at the reference date | W60: The entity is to be classified on the reference date under one of the following categories: performing or non-performing, in accordance with Annex V to Implementing Regulation (EU) No 680/2014. | X60: Yes - Computed | Y60: IF H0883_IND_CURA = 1 THEN T; ELSE IF H0883_IND_CURA = 0 THEN F; THEN N/A | Z60: - | AA60: Y | AB60: N | AC60: N | AD60: N | AE60: N | AF60: N | AG60: N | AH60: N | AI60: Y | AJ60: N | AK60: 0
A61: 0 | B61: IN.003 | C61: INSTRUMENT | D61: Portfolio identification | E61: N | F61: CRE_FNRP18 | G61: N | H61: N | I61: N | J61: N | K61: N | L61: Y | M61: N | N61: Y | O61: Y | P61: N | Q61: Y, N | R61: Boolean: Y/N | S61: Default value not allowed | T61: Default value not allowed | U61: Default value not allowed | V61: Flag of CREs | W61: Loans granted to Commercial Real Estate (reported in FinRep 18 rows 140, 903, 923: “of which: loans collateralized by commercial immovable property”). | X61: Not applicable | Y61: N/A | Z61: - | AA61: Y | AB61: N | AC61: N | AD61: N | AE61: N | AF61: N | AG61: N | AH61: N | AI61: Y | AJ61: #N/A | AK61: 0
A62: #N/A | B62: PR.035 | C62: PROTECTION | D62: Financial Information | E62: N | F62: CRE_INCM_CRRNCY | G62: N | H62: N | I62: N | J62: N | K62: N | L62: Y | M62: N | Q62: =HYPERLINK("#"&"CodeList!"&ADDRESS(2,MATCH($F62,CodeList!$2:$2,0)+1,),"Code List") -> Code List | R62: Use codes from the code list sheet | S62: MISS | T62: N/A | U62: N/A | V62: Currency of annual income and expenses | W62: Currency of annual income and expenses. | X62: Not applicable | Y62: N/A | Z62: - | AA62: Y | AB62: N | AC62: N | AD62: N | AE62: N | AF62: N | AG62: N | AH62: N | AI62: Y | AJ62: N | AK62: 0
A63: #N/A | B63: PR.036 | C63: PROTECTION | D63: Financial Information | E63: N | F63: CRE_YRLY_EXPNSS | G63: N | H63: N | I63: N | J63: N | K63: N | L63: Y | M63: N | Q63: FLOAT 2 decimal places | R63: Use decimal point, no thousands seperator | S63: 99999999999 | T63: 11111111111 | U63: 11111111111 | V63: Current annual operating expenses | W63: Current annual operating expenses. | X63: Not applicable | Y63: N/A | Z63: - | AA63: Y | AB63: N | AC63: N | AD63: N | AE63: N | AF63: N | AG63: N | AH63: N | AI63: Y | AJ63: N | AK63: 0
A64: #N/A | B64: PR.037 | C64: PROTECTION | D64: Financial Information | E64: N | F64: CRE_YRLY_INCM | G64: N | H64: N | I64: N | J64: N | K64: N | L64: Y | M64: N | Q64: FLOAT 2 decimal places | R64: Use decimal point, no thousands seperator | S64: 99999999999 | T64: 11111111111 | U64: 11111111111 | V64: Current annual income | W64: Ideally based on capacities that are rented on the day following the reference date. | X64: Not applicable | Y64: N/A | Z64: - | AA64: Y | AB64: N | AC64: N | AD64: N | AE64: N | AF64: N | AG64: N | AH64: N | AI64: Y | AJ64: N | AK64: 0
A65: 0 | B65: IN.189 | C65: INSTRUMENT | D65: Indicators | E65: N | F65: CRRLTN_CFFCNT | G65: Y | H65: Y | I65: Y | J65: Y | K65: Y | L65: Y | M65: Y | N65: N | O65: N | P65: N | Q65: FLOAT 6 decimal places | R65: Use decimal point, no thousands seperator | S65: 99999999999 | T65: 11111111111 | U65: 11111111111 | V65: Coefficient of correlation (R) | W65: The coeefficient of correlation pursuant to Art. 154 Regulation (EU) No 575/2013. | X65: Mapping available in the future | Y65: N/A | Z65: This mapping will be available in BDR (JM_CTO_CATEG2) | AA65: Y | AB65: N | AC65: N | AD65: N | AE65: N | AF65: N | AG65: N | AH65: N | AI65: Y | AJ65: N | AK65: 0
A66: 6.1. Fora âmbito | Campos concluídos - Sem necessidade de espec. | B66: IN.010 | C66: INSTRUMENT | D66: General | E66: Y | F66: CRRNCY_DNMNTN | G66: Y | H66: Y | I66: Y | J66: Y | K66: Y | L66: Y | M66: Y | N66: Y | O66: N | P66: N | Q66: =HYPERLINK("#"&"CodeList!"&ADDRESS(2,MATCH($F66,CodeList!$2:$2,0)+1,),"Code List") -> Code List | R66: Use codes from the code list sheet | S66: MISS | T66: Default value not allowed | U66: N/A | V66: Currency denomination | W66: Currency denomination of instruments, in accordance with the ISO 4217 standard. | X66: Yes - Equivalent | Y66: JM_CONTR_BIS - G4095_CODDIV | Z66: - | AA66: Y | AB66: N | AC66: N | AD66: N | AE66: N | AF66: Y | AG66: N | AH66: N | AI66: Y | AJ66: Y | AK66: 0
A67: 6.1. Fora âmbito | Campos concluídos - Sem necessidade de espec. | B67: IN.068 | C67: INSTRUMENT | D67: Financial Information | E67: Y | F67: CRRYNG_AMNT_INSTRMNT | G67: Y | H67: Y | I67: Y | J67: Y | K67: Y | L67: Y | M67: Y | N67: Y | O67: Y | P67: N | Q67: FLOAT 2 decimal places | R67: Use decimal point, no thousands seperator | S67: 99999999999 | T67: 11111111111 | U67: 11111111111 | V67: Carrying amount | W67: Net carrying amount including accrued interest as laid down in Annex 5 Regulation 680/2014. | X67: Not applicable | Y67: N/A | Z67: - | AA67: Y | AB67: N | AC67: N | AD67: N | AE67: N | AF67: Y | AG67: N | AH67: N | AI67: Y | AJ67: Y | AK67: 0
A68: 0 | B68: EN.056 | C68: ENTITY | D68: Financial Information | E68: N | F68: CSH | G68: Y | H68: Y | I68: Y | J68: Y | K68: Y | L68: Y | M68: N | Q68: FLOAT 2 decimal places | R68: Use decimal point, no thousands seperator | S68: 99999999999 | T68: 11111111111 | U68: 11111111111 | V68: Cash and cash equivalents at most recent reported figures | W68: Cash and cash equivalents at most recent reported figures. Please report on solo entity level unless advised otherwise. | X68: Not applicable | Y68: N/A | Z68: - | AA68: Y | AB68: N | AC68: N | AD68: N | AE68: N | AF68: N | AG68: N | AH68: N | AI68: Y | AJ68: N | AK68: 0
A69: 0 | B69: EN.057 | C69: ENTITY | D69: Financial Information | E69: N | F69: CSH_PRVS | G69: Y | H69: Y | I69: Y | J69: Y | K69: Y | L69: Y | M69: N | Q69: FLOAT 2 decimal places | R69: Use decimal point, no thousands seperator | S69: 99999999999 | T69: 11111111111 | U69: 11111111111 | V69: Cash and cash equivalents at previous reported figures | W69: Cash and cash equivalents at previous reported figures. Please report on solo entity level unless advised otherwise. | X69: Not applicable | Y69: N/A | Z69: - | AA69: Y | AB69: N | AC69: N | AD69: N | AE69: N | AF69: N | AG69: N | AH69: N | AI69: Y | AJ69: N | AK69: 0
A70: 6.1. Fora âmbito | Campos concluídos - Sem necessidade de espec. | B70: IN.017 | C70: INSTRUMENT | D70: Classification | E70: N | F70: CSH_SWP_TRP | G70: N | H70: Y | I70: Y | J70: Y | K70: Y | L70: Y | M70: N | N70: N | O70: N | P70: N | Q70: Y, N | R70: Boolean: Y/N | S70: MISS | T70: N/A | U70: N/A | V70: Cash sweep or cash trap covenants agreed (Y/N) | W70: Report "Y" if the agreement with the debtor includes cash sweep or cash trap covenants. | X70: Not applicable | Y70: N/A | Z70: - | AA70: Y | AB70: N | AC70: N | AD70: N | AE70: N | AF70: Y | AG70: N | AH70: N | AI70: Y | AJ70: Y | AK70: 0
A71: 6.3. Fora âmbito | Fonte Manual LF | B71: IN.018 | C71: INSTRUMENT | D71: Classification | E71: N | F71: CVNNT_STTS | G71: N | H71: N | I71: N | J71: N | K71: Y | L71: Y | M71: N | N71: N | O71: N | P71: N | Q71: =HYPERLINK("#"&"CodeList!"&ADDRESS(2,MATCH($F71,CodeList!$2:$2,0)+1,),"Code List") -> Code List | R71: Use codes from the code list sheet | S71: 99999999999 | T71: 11111111111 | U71: 11111111111 | V71: Covenant status | W71: In accordance with "ECB Guidance on leveraged transactions". The term "material covenant" should be defined according to bank-internal nomenclature. | X71: Not applicable | Y71: N/A | Z71: - | AA71: Y | AB71: N | AC71: N | AD71: N | AE71: N | AF71: Y | AG71: N | AH71: N | AI71: Y | AJ71: Y | AK71: 0
A72: 6.3. Fora âmbito | Fonte Manual LF | B72: IN.019 | C72: INSTRUMENT | D72: Classification | E72: N | F72: CVNNT_TYP | G72: N | H72: N | I72: N | J72: N | K72: Y | L72: Y | M72: N | N72: N | O72: N | P72: N | Q72: =HYPERLINK("#"&"CodeList!"&ADDRESS(2,MATCH($F72,CodeList!$2:$2,0)+1,),"Code List") -> Code List | R72: Use codes from the code list sheet | S72: 99999999999 | T72: 11111111111 | U72: 11111111111 | V72: Covenant Type | W72: Type of covenant according to "ECB Guidance on leveraged transactions". | X72: Not applicable | Y72: N/A | Z72: - | AA72: Y | AB72: N | AC72: N | AD72: N | AE72: N | AF72: Y | AG72: N | AH72: N | AI72: Y | AJ72: Y | AK72: 0
A73: 6.3. Fora âmbito | Fonte Manual LF | B73: EN.078 | C73: ENTITY | D73: Indicators | E73: N | F73: DBT_RPYMNT_CPCTY_SNR_DBT | G73: N | H73: N | I73: N | J73: N | K73: Y | L73: Y | M73: N | Q73: FLOAT 6 decimal places | R73: Use decimal point, no thousands seperator | S73: 99999999999 | T73: 11111111111 | U73: 11111111111 | V73: Debt repayment capacity of senior secured debt as per ECB Guidance on leveraged transactions | W73: Under base sensitivity assessment case; In accordance with "Guidance on leveraged transactions". An adequate repayment capacity is defined as the ability of the leveraged borrower to fully amortise senior secured debt or repay at least 50% of Total Debt over a period of five to seven years. | X73: Not applicable | Y73: N/A | Z73: - | AA73: Y | AB73: N | AC73: N | AD73: N | AE73: N | AF73: Y | AG73: N | AH73: N | AI73: Y | AJ73: Y | AK73: 0
A74: 6.1. Fora âmbito | Campos concluídos - Sem necessidade de espec. | B74: EN.079 | C74: ENTITY | D74: Indicators | E74: N | F74: DBT_RPYMNT_CPCTY_TTL | G74: N | H74: N | I74: N | J74: N | K74: Y | L74: Y | M74: N | Q74: FLOAT 6 decimal places | R74: Use decimal point, no thousands seperator | S74: 99999999999 | T74: 11111111111 | U74: 11111111111 | V74: Debt repayment capacity of the total debt as per ECB Guidance on leveraged transactions | W74: Under base sensitivity assessment case; In accordance with "Guidance on leveraged transactions". An adequate repayment capacity is defined as the ability of the leveraged borrower to fully amortise senior secured debt or repay at least 50% of Total Debt over a period of five to seven years. | X74: Not applicable | Y74: N/A | Z74: - | AA74: Y | AB74: N | AC74: N | AD74: N | AE74: N | AF74: Y | AG74: N | AH74: N | AI74: Y | AJ74: Y | AK74: 0
A75: 0 | B75: EN.080 | C75: ENTITY | D75: Indicators | E75: N | F75: DBT_SRVC_RT | G75: Y | H75: Y | I75: Y | J75: Y | K75: Y | L75: Y | M75: N | Q75: FLOAT 6 decimal places | R75: Use decimal point, no thousands seperator | S75: 99999999999 | T75: 11111111111 | U75: 11111111111 | V75: Debt service coverage ratio | W75: According to internal definition. Please also add an explanatory note on sheet "Notes" on how the calculation is done. | X75: Not applicable | Y75: N/A | Z75: - | AA75: Y | AB75: N | AC75: N | AD75: N | AE75: N | AF75: N | AG75: N | AH75: N | AI75: Y | AJ75: N | AK75: 0
A76: 0 | B76: EN.081 | C76: ENTITY | D76: Indicators | E76: N | F76: DBT_SRVC_RT_12M | G76: Y | H76: Y | I76: Y | J76: Y | K76: Y | L76: Y | M76: N | Q76: FLOAT 6 decimal places | R76: Use decimal point, no thousands seperator | S76: 99999999999 | T76: 11111111111 | U76: 11111111111 | V76: Debt service coverage ratio at the most recent reported figures prior to the reference date | W76: See notes on DBT_SRVC_RT. | X76: Not applicable | Y76: N/A | Z76: - | AA76: Y | AB76: N | AC76: N | AD76: N | AE76: N | AF76: N | AG76: N | AH76: N | AI76: Y | AJ76: N | AK76: 0
A77: 0 | B77: IN.069 | C77: INSTRUMENT | D77: Financial Information | E77: N | F77: DBT_YLD | G77: N | H77: N | I77: N | J77: N | K77: N | L77: Y | M77: N | N77: N | O77: N | P77: N | Q77: FLOAT 6 decimal places | R77: Use decimal point, no thousands seperator | S77: 99999999999 | T77: 11111111111 | U77: 11111111111 | V77: Debt yield | W77: Ratio of net annual rental income divided by the total gross carrying amount which is secured by the CRE property - (see ESRB/2016/14 for details regarding the calculation of net annual rental income). | X77: Not applicable | Y77: N/A | Z77: - | AA77: Y | AB77: N | AC77: N | AD77: N | AE77: N | AF77: N | AG77: N | AH77: N | AI77: Y | AJ77: N | AK77: 0
A78: 0 | B78: EN.020 | C78: ENTITY | D78: Classification | E78: N | F78: DCSD | G78: N | H78: N | I78: N | J78: N | K78: N | L78: N | M78: Y | Q78: Y, N | R78: Boolean: Y/N | S78: MISS | T78: N/A | U78: N/A | V78: Entity deceased | W78: Indicator as to whether the Entity has passed away. The data attribute is applicable to natural persons only. | X78: Not applicable | Y78: N/A | Z78: - | AA78: Y | AB78: N | AC78: N | AD78: N | AE78: N | AF78: N | AG78: N | AH78: N | AI78: Y | AJ78: N | AK78: 0
A79: 5. Campos com outras possíveis alterações - Dependente de decisões OSI | B79: EN.021 | C79: ENTITY | D79: Classification | E79: Y | F79: DFLT_STTS | G79: Y | H79: Y | I79: Y | J79: Y | K79: Y | L79: Y | M79: Y | Q79: =HYPERLINK("#"&"CodeList!"&ADDRESS(2,MATCH($F79,CodeList!$2:$2,0)+1,),"Code List") -> Code List | R79: Use codes from the code list sheet | S79: 99999999999 | T79: 11111111111 | U79: 11111111111 | V79: Default status of the entity | W79: Identification of the default status of the counterparty. Categories describing the motives for which the counterparty can be in default in accordance with Article 178 of Regulation (EU) No 575/2013. For retail only: If default classification performed on instrument level then Entity is classified as defaulted when at least one instrument is classified as defaulted. For corporate, SME, CRE and LF: if default classification performed on instrument level then entity level is "not applicable". | X79: Not applicable | Y79: N/A | Z79: - | AA79: Y | AB79: N | AC79: N | AD79: N | AE79: N | AF79: Y | AG79: N | AH79: N | AI79: Y | AJ79: Y | AK79: 0
A80: 2.2 Re-especificação de campos complexos - Resto | B80: IN.020 | C80: INSTRUMENT | D80: Classification | E80: Y | F80: DFLT_STTS_INSTRMNT | G80: Y | H80: Y | I80: Y | J80: Y | K80: Y | L80: Y | M80: Y | N80: N | O80: Y | P80: Y | Q80: =HYPERLINK("#"&"CodeList!"&ADDRESS(2,MATCH($F80,CodeList!$2:$2,0)+1,),"Code List") -> Code List | R80: Use codes from the code list sheet | S80: 99999999999 | T80: Default value not allowed | U80: Default value not allowed | V80: Default status of the instrument | W80: Identification of the default status of the instrument. Categories describing the situations in which an instrument can be described as being at default in accordance with Article 178 of Regulation (EU) No 575/2013. | X80: Not applicable | Y80: N/A | Z80: - | AA80: Y | AB80: Y | AC80: Y | AD80: N | AE80: N | AF80: Y | AG80: Y | AH80: Y | AI80: Y | AJ80: Y | AK80: 0
A81: #N/A | B81: AC.011 | C81: INSTR_ACTIVITY | D81: General | E81: N | F81: DNSH_DTL | G81: N | H81: N | I81: Y | J81: Y | K81: Y | L81: Y | M81: Y | Q81: =HYPERLINK("#"&"CodeList!"&ADDRESS(2,MATCH($F81,CodeList!$2:$2,0)+1,),"Code List") -> Code List | R81: Use codes from the code list sheet | S81: MISS | T81: N/A | U81: N/A | V81: DNSH detail | W81: This field indicates which DNHSs are not complied by the operation. Therefore, if FLG_DNSH_CMPLNC = "No", then this field must be reported with the DNSH that the operation does not comply with. For example, if there is an operation which do not comply with DNSH1 and DNSH3, the DNSH_DTL = DNSH1, DNSH3. Units must report this field specifying the DNSHs which are not complied separated by a comma. | X81: Not applicable | Y81: N/A | Z81: - | AA81: N | AB81: N | AC81: Y | AD81: N | AE81: N | AF81: N | AG81: N | AH81: Y | AI81: Y | AJ81: #N/A | AK81: #N/A
A82: 4. Campos com NOK controlos Corporativos | B82: IN.094 | C82: INSTRUMENT | D82: Impairment | E82: N | F82: DPD | G82: N | H82: Y | I82: Y | J82: Y | K82: Y | L82: Y | M82: Y | N82: N | O82: N | P82: N | Q82: INTEGER | R82: Use integer numbers, no decimal point, no thousands seperators | S82: 99999999999 | T82: 11111111111 | U82: 11111111111 | V82: Days past due at reference date | W82: Days past due at reference date in accordance with Art 178 of Regulation (EU) No 575/2013. | X82: Yes - Equivalent | Y82: JM_OUT_CTO_ND - R9739_DIAS_ATR | Z82: - | AA82: Y | AB82: N | AC82: N | AD82: N | AE82: N | AF82: Y | AG82: N | AH82: N | AI82: Y | AJ82: Y | AK82: 0
A83: 0 | B83: IN.095 | C83: INSTRUMENT | D83: Impairment | E83: N | F83: DPD_12M | G83: N | H83: Y | I83: Y | J83: Y | K83: Y | L83: Y | M83: Y | N83: N | O83: N | P83: N | Q83: INTEGER | R83: Use integer numbers, no decimal point, no thousands seperators | S83: 99999999999 | T83: 11111111111 | U83: 11111111111 | V83: Highest number of days past due in the last 12 months | W83: Highest number of days past due within a period of 12 months prior to the reference date. | X83: Yes - Computed | Y83: Highest value included in the field R9739_DIAS_ATR in the last 12 months | Z83: - | AA83: Y | AB83: N | AC83: N | AD83: N | AE83: N | AF83: N | AG83: N | AH83: N | AI83: Y | AJ83: N | AK83: 0
A84: 0 | B84: IN.096 | C84: INSTRUMENT | D84: Impairment | E84: N | F84: DPD_12M_FRBRNC_STTS | G84: N | H84: Y | I84: Y | J84: Y | K84: Y | L84: Y | M84: Y | N84: N | O84: N | P84: N | Q84: INTEGER | R84: Use integer numbers, no decimal point, no thousands seperators | S84: 99999999999 | T84: 11111111111 | U84: 11111111111 | V84: Highest number of days past due in the 12 months prior to the most recent change of the forbearance status | W84: Highest number of days past due within a period of 12 months prior to the most recent change of the forbearance status. As regards forbearance status please refer to Part 18 of Annex V to Implementing Regulation (EU) No 680/2014. The data attribute is only to be populated for instances where a status change occured during an observation period of maximum 24month preceding the reference date. | X84: Yes - Computed | Y84: IF G7025_MOTRENUG in (1;2;3;4;15;16;21;22;25) THEN obtain the highest value included in the field R9739_DIAS_ATR in the last 12 months previous to G7025_FEC_MOD for the instrument with the most recent date included in G7025_FEC_MOD | Z84: - | AA84: Y | AB84: N | AC84: N | AD84: N | AE84: N | AF84: N | AG84: N | AH84: N | AI84: Y | AJ84: N | AK84: 0
A85: 0 | B85: IN.097 | C85: INSTRUMENT | D85: Impairment | E85: N | F85: DPD_12M_PRFRMNG_STTS | G85: N | H85: Y | I85: Y | J85: Y | K85: Y | L85: Y | M85: Y | N85: N | O85: N | P85: N | Q85: INTEGER | R85: Use integer numbers, no decimal point, no thousands seperators | S85: 99999999999 | T85: 11111111111 | U85: 11111111111 | V85: Highest number of days past due in the 12 months prior to the most recent change of performing status | W85: Highest number of days past due within a period of 12 months prior to the change of the performing status. As regards performing status please refer to Part 17 of Annex V to Implementing Regulation (EU) No 680/2014. The data attribute is only to be populated for instances where a status change occured during an observation period of maximum 24month preceding the reference date. | X85: Yes - Computed | Y85: IF R9739_FINALIND = 3 AND T1824_SITGESND in (5;6) THEN obtain the highest value included in the field R9739_DIAS_ATR in the last 12 months previous to R9739_FEC_DEF | Z85: - | AA85: Y | AB85: N | AC85: N | AD85: N | AE85: N | AF85: N | AG85: N | AH85: N | AI85: Y | AJ85: N | AK85: 0
A86: 0 | B86: IN.098 | C86: INSTRUMENT | D86: Impairment | E86: N | F86: DPD_24M_FRBRNC_STTS | G86: N | H86: Y | I86: Y | J86: Y | K86: Y | L86: Y | M86: Y | N86: N | O86: N | P86: N | Q86: INTEGER | R86: Use integer numbers, no decimal point, no thousands seperators | S86: 99999999999 | T86: 11111111111 | U86: 11111111111 | V86: Highest number of days past due in the 24 months prior to the most recent change of the forbearance status | W86: Highest number of days past due within a period of 24 months prior to the change of the forbearance status. As regards forbearance status please refer to Part 18 of Annex V to Implementing Regulation (EU) No 680/2014. The data attribute is only to be populated for instances where a status change occured during an observation period of maximum 24month preceding the reference date. | X86: Yes - Computed | Y86: IF G7025_MOTRENUG in (1;2;3;4;15;16;21;22;25) THEN obtain the highest value included in the field R9739_DIAS_ATR in the last 24 months previous to G7025_FEC_MOD for the instrument with the most recent date included in G7025_FEC_MOD | Z86: - | AA86: Y | AB86: N | AC86: N | AD86: N | AE86: N | AF86: N | AG86: N | AH86: N | AI86: Y | AJ86: N | AK86: 0
A87: 0 | B87: IN.099 | C87: INSTRUMENT | D87: Impairment | E87: N | F87: DPD_24M_PRFRMNG_STTS | G87: N | H87: Y | I87: Y | J87: Y | K87: Y | L87: Y | M87: Y | N87: N | O87: N | P87: N | Q87: INTEGER | R87: Use integer numbers, no decimal point, no thousands seperators | S87: 99999999999 | T87: 11111111111 | U87: 11111111111 | V87: Highest number of days past due in the 24 months before most recent change of performing status | W87: Highest number of days past due within a period of 24 months prior to the change of the performing status. As regards performing status please refer to Part 17 of Annex V to Implementing Regulation (EU) No 680/2014. | X87: Yes - Computed | Y87: IF R9739_FINALIND = 3 AND T1824_SITGESND in (5;6) THEN obtain the highest value included in the field R9739_DIAS_ATR in the last 24 months previous to R9739_FEC_DEF | Z87: - | AA87: Y | AB87: N | AC87: N | AD87: N | AE87: N | AF87: N | AG87: N | AH87: N | AI87: Y | AJ87: N | AK87: 0
A88: 0 | B88: IN.100 | C88: INSTRUMENT | D88: Impairment | E88: N | F88: DPD_FRBRNC_STTS | G88: N | H88: Y | I88: Y | J88: Y | K88: Y | L88: Y | M88: Y | N88: N | O88: N | P88: N | Q88: INTEGER | R88: Use integer numbers, no decimal point, no thousands seperators | S88: 99999999999 | T88: 11111111111 | U88: 11111111111 | V88: Days past due at the date of the most recent change of the forbearance status | W88: Days past due at the date of the most recent change of the forbearance status. Data attribute reported only for those instruments where any change in its classification occured during a maximum observation period of 24 month preceding the reference date. As regards forbearance status please refer to Part 18 of Annex V to Implementing Regulation (EU) No 680/2014. | X88: Yes - Computed | Y88: IF G7025_MOTRENUG in (1;2;3;4;15;16;21;22;25) THEN R9739_DIAS_ATR for the instrument with the most recent date included in G7025_FEC_MOD | Z88: - | AA88: Y | AB88: N | AC88: N | AD88: N | AE88: N | AF88: N | AG88: N | AH88: N | AI88: Y | AJ88: N | AK88: 0
A89: 0 | B89: IN.101 | C89: INSTRUMENT | D89: Impairment | E89: N | F89: DPD_PRFRMNG_STTS | G89: N | H89: Y | I89: Y | J89: Y | K89: Y | L89: Y | M89: Y | N89: N | O89: N | P89: N | Q89: INTEGER | R89: Use integer numbers, no decimal point, no thousands seperators | S89: 99999999999 | T89: 11111111111 | U89: 11111111111 | V89: Days past due at the time of the most recent change of the performing status | W89: Days past due at the time of the most recent change of the performing status. As regards performing status please refer to Part 17 of Annex V to Implementing Regulation (EU) No 680/2014. | X89: Yes - Computed | Y89: IF R9739_FINALIND = 3 AND T1824_SITGESND in (5;6) THEN R9739_DIAS_ATR | Z89: - | AA89: Y | AB89: N | AC89: N | AD89: N | AE89: N | AF89: N | AG89: N | AH89: N | AI89: Y | AJ89: N | AK89: 0
A90: 0 | B90: IN.237 | C90: INSTRUMENT | D90: Financial Information | E90: N | F90: DSTI | G90: N | H90: N | I90: N | J90: N | K90: N | L90: N | M90: Y | N90: N | O90: N | P90: N | Q90: FLOAT 6 decimal places | R90: Use decimal point, no thousands seperator | S90: 99999999999 | T90: 11111111111 | U90: 11111111111 | V90: DSTI at reference date | W90: Debt Service to Income (DSTI) as defined in Recommendation ESRB/2016/14 as amended by Recommendation ESRB/2019/3, Annex IV, i.e. ‘disposable income’ of the borrower at numerator. The income should include to the extent possible the following items: Disposable income = employee income + self-employment income (e.g. profits) + income from public pensions + income from private and occupational pensions + income from unemployment benefits + income from social transfers other than unemployment benefits + regular private transfers (such as alimonies) + gross rental income from real estate property + income from financial investments + income from private business or partnership + regular income from other sources + loan subsidies – taxes – health care/social security/medical insurance premiums + tax rebates. Debt Services is the annual debt servicing costs of the total debt of the borrower, whether or not this debt is secured by real estate, including all outstanding financial loans, granted by the bank itself or by other lenders. Income and debt information should be reported at the latest available date. If only income information at origination is available, then income at origination should be reported. | X90: Not applicable | Y90: N/A | Z90: - | AA90: Y | AB90: N | AC90: N | AD90: N | AE90: N | AF90: N | AG90: N | AH90: N | AI90: Y | AJ90: #N/A | AK90: 0
A91: 1. Novos Campos | B91: IN.262 | C91: INSTRUMENT | D91: General | E91: N | F91: DSTNTN_FNDS | G91: N | H91: N | I91: N | J91: N | K91: Y | L91: Y | M91: N | N91: Y | O91: N | P91: N | Q91: =HYPERLINK("#"&"CodeList!"&ADDRESS(2,MATCH($F91,CodeList!$2:$2,0)+1,),"Code List") -> Code List | R91: Use codes from the code list sheet | S91: MISS | T91: N/A | U91: N/A | V91: Destination of funds | W91: Destination of funds regarding leveraged finance transactions | X91: Not applicable | Y91: N/A | Z91: - | AA91: N | AB91: N | AC91: N | AD91: N | AE91: N | AF91: Y | AG91: N | AH91: N | AI91: Y | AJ91: #N/A | AK91: #N/A
A92: #N/A | B92: PR.027 | C92: PROTECTION | D92: Appraisal | E92: N | F92: DT_APPRSL_PRVS | G92: N | H92: Y | I92: Y | J92: Y | K92: Y | L92: Y | M92: Y | Q92: DATE | R92: YYYY-MM-DD | S92: 0000-00-00 | T92: 1111-11-11 | U92: 1111-11-11 | V92: Previous appraisal date | W92: Date of the appraisal previous to the most recent one available, i.e. previous to the last full appraisal (field DT_LST_FLL_APPRSL). | X92: Yes - Computed | Y92: G4134_FECHVALR HAVING G4134_FECHVALR as the previous to the most recent one | Z92: - | AA92: Y | AB92: N | AC92: N | AD92: N | AE92: N | AF92: N | AG92: N | AH92: N | AI92: Y | AJ92: N | AK92: 0
A93: 0 | B93: EN.003 | C93: ENTITY | D93: General | E93: Y | F93: DT_BRTH | G93: N | H93: N | I93: N | J93: N | K93: N | L93: Y | M93: Y | Q93: DATE | R93: YYYY-MM-DD | S93: 0000-00-00 | T93: Default value not allowed | U93: 1111-11-11 | V93: Birth date counterparty | W93: Date when the entity was born / registered. | X93: Yes - Equivalent | Y93: JM_CLIENT_BII - G4093_FECNACIM | Z93: - | AA93: Y | AB93: N | AC93: N | AD93: N | AE93: N | AF93: N | AG93: N | AH93: N | AI93: Y | AJ93: N | AK93: 0
A94: 0 | B94: IN.140 | C94: INSTRUMENT | D94: COVID19 | E94: N | F94: DT_CMPLNT_MRTR_STTS_C19 | G94: N | H94: N | I94: N | J94: N | K94: N | L94: Y | M94: Y | N94: N | O94: N | P94: N | Q94: DATE | R94: YYYY-MM-DD | S94: 0000-00-00 | T94: 1111-11-11 | U94: 1111-11-11 | V94: Date of EBA compliant moratoria status. Please report all COVID-related measures until 31 December 2022. Afterwards, please report Not Applicable default value | W94: The latest date on which the EBA moratoria status as reported in “EBA compliant moratoria status” is considered to have been established or changed. Exposures that are subject to both EBA-compliant moratoria and other COVID-19-related forbearance measures should be reported only once as EBA-compliant moratoria. Data attribute shall be reported if not waived by the competent authority according to points (a), (c), (d) or (e) of Article 19 of EBA/GL/2020/07 Guidelines on reporting and disclosure of exposures subject to measures applied in response to the COVID-19 crisis. | X94: Yes - Computed | Y94: IF G7025_MOTRENUG in (26;27;28;29) AND (G7025_FEC_BAJA = "9999-12-31" OR G7025_FEC_BAJA > "REPORTING REFERENCE DATE") THEN G7025_FEALTREL | Z94: - | AA94: Y | AB94: N | AC94: N | AD94: N | AE94: N | AF94: N | AG94: N | AH94: N | AI94: Y | AJ94: Y | AK94: 0
A95: 0 | B95: IN.141 | C95: INSTRUMENT | D95: COVID19 | E95: N | F95: DT_CMPLNT_MRTR_STTS_PRVS_C19 | G95: N | H95: N | I95: N | J95: N | K95: N | L95: Y | M95: Y | N95: N | O95: N | P95: N | Q95: DATE | R95: YYYY-MM-DD | S95: 0000-00-00 | T95: 1111-11-11 | U95: 1111-11-11 | V95: Initial date of first EBA compliant moratoria status. Please report all COVID-related measures until 31 December 2022. Afterwards, please report Not Applicable default value | W95: The date on which the previous EBA moratoria status as reported in “EBA compliant moratoria status” is considered to have been established or changed. Exposures that are subject to both EBA-compliant moratoria and other COVID-19-related forbearance measures should be reported only once as EBA-compliant moratoria. EBA/GL/2020/07 Guidelines on reporting and disclosure of exposures subject to measures applied in response to the COVID-19 crisis. Data attribute shall be reported if not waived by the competent authority according to points (a), (c), (d) or (e) of Article 19 of EBA/GL/2020/07 Guidelines on reporting and disclosure of exposures subject to measures applied in response to the COVID-19 crisis. | X95: Yes - Computed | Y95: IF G7025_MOTRENUG in (26;27;28;29) THEN MIN(G7025_FEALTREL) | Z95: - | AA95: Y | AB95: N | AC95: N | AD95: N | AE95: N | AF95: N | AG95: N | AH95: N | AI95: Y | AJ95: Y | AK95: 0
A96: #N/A | B96: PR.030 | C96: PROTECTION | D96: Collateral Features | E96: N | F96: DT_CNSTRCTN_STTS | G96: N | H96: N | I96: N | J96: N | K96: N | L96: Y | M96: Y | Q96: DATE | R96: YYYY-MM-DD | S96: 0000-00-00 | T96: 1111-11-11 | U96: 1111-11-11 | V96: Date of construction status | W96: Date of the construction status. | X96: Yes - Equivalent | Y96: JM_CONTR_OTROS - E0623_FECULTMO | Z96: - | AA96: Y | AB96: N | AC96: N | AD96: N | AE96: N | AF96: N | AG96: N | AH96: N | AI96: Y | AJ96: N | AK96: 0
A97: 5. Campos com outras possíveis alterações - Dependente de decisões OSI | B97: EN.004 | C97: ENTITY | D97: General | E97: Y | F97: DT_DFLT_STTS | G97: Y | H97: Y | I97: Y | J97: Y | K97: Y | L97: Y | M97: Y | Q97: DATE | R97: YYYY-MM-DD | S97: 0000-00-00 | T97: 1111-11-11 | U97: 1111-11-11 | V97: Date of default status | W97: The date on which the default status, as reported in the data attribute “Default status”, is considered to have arisen. If "Not in default" since inception then this attribute is to be reported equally to the inception date. If default classification performed on instrument level then Entity is classified as defaulted when at least one instrument is classified as defaulted. If more than one Instrument is classified as defaulted then the earliest date has to be provided. The definition of default is aligned with Art 178 of Regulation (EU) No 575/2013. | X97: Not applicable | Y97: N/A | Z97: - | AA97: Y | AB97: N | AC97: N | AD97: N | AE97: N | AF97: Y | AG97: N | AH97: N | AI97: Y | AJ97: Y | AK97: 0
A98: 3. Campos em testes ou c/ incidências | B98: IN.021 | C98: INSTRUMENT | D98: Classification | E98: Y | F98: DT_DFLT_STTS_INSTRMNT | G98: Y | H98: Y | I98: Y | J98: Y | K98: Y | L98: Y | M98: Y | N98: N | O98: N | P98: N | Q98: DATE | R98: YYYY-MM-DD | S98: 0000-00-00 | T98: Default value not allowed | U98: 1111-11-11 | V98: Date of default status | W98: The date on which the default status, as reported in the data attribute “Default status”, is considered to have arisen. If "Not in default" since inception then this attribute is to be reported equally to the inception date. If more than one Instrument is classified as defaulted then the earliest date has to be provided. The definition of default is aligned with Art 178 of Regulation (EU) No 575/2013. | X98: Not applicable | Y98: N/A | Z98: - | AA98: Y | AB98: N | AC98: N | AD98: N | AE98: N | AF98: Y | AG98: N | AH98: N | AI98: Y | AJ98: Y | AK98: 0
A99: 0 | B99: IN.022 | C99: INSTRUMENT | D99: Classification | E99: N | F99: DT_END_GP_PPAL | G99: N | H99: Y | I99: Y | J99: Y | K99: Y | L99: Y | M99: Y | N99: N | O99: N | P99: N | Q99: DATE | R99: YYYY-MM-DD | S99: 0000-00-00 | T99: 1111-11-11 | U99: 1111-11-11 | V99: End date of principal grace period | W99: The latest date on which the principal payment postponement ends according to the instrument agreement. The scope of the field refers to any interest only period, either due to renegotiations or interest only agreements at loan inception. | X99: Yes - Computed | Y99: IF E0623_TIPCAREN = 1 THEN E0623_FECFICAR | Z99: - | AA99: Y | AB99: N | AC99: N | AD99: N | AE99: N | AF99: N | AG99: N | AH99: N | AI99: Y | AJ99: N | AK99: 0
A100: 0 | B100: IN.150 | C100: INSTRUMENT | D100: COVID19 | E100: N | F100: DT_END_GP_PPAL_C19 | G100: N | H100: N | I100: N | J100: N | K100: N | L100: Y | M100: Y | N100: N | O100: N | P100: N | Q100: DATE | R100: YYYY-MM-DD | S100: 0000-00-00 | T100: 1111-11-11 | U100: 1111-11-11 | V100: End date of principal grace period for COVID19 related measures. Please report all COVID-related measures until 31 December 2022. Afterwards, please report Not Applicable default value | W100: The date on which the principal payment postponement ends according to the instrument agreement. EBA/GL/2020/07 Guidelines on reporting and disclosure of exposures subject to measures applied in response to the COVID-19 crisis. Data attribute shall be reported if not waived by the competent authority according to points (a), (c), (d) or (e) of Article 19 of EBA/GL/2020/07 Guidelines on reporting and disclosure of exposures subject to measures applied in response to the COVID-19 crisis. | X100: Yes - Computed | Y100: IF G7025_MOTRENUG in (26;27;28;29) AND E0623_TIPCAREN = "1" AND (G7025_FEC_BAJA is not "9999-12-31" AND G7025_FEC_BAJA < "REPORTING REFERENCE DATE") THEN MAX(G7025_FEC_BAJA); ELSE IF G7025_MOTRENUG in (26;27;28;29) AND E0623_TIPCAREN = "1" AND (G7025_FEC_BAJA is "9999-12-31" OR G7025_FEC_BAJA > "REPORTING REFERENCE DATE") THEN E0623_FECFICAR | Z100: - | AA100: Y | AB100: N | AC100: N | AD100: N | AE100: N | AF100: N | AG100: N | AH100: N | AI100: Y | AJ100: Y | AK100: 0
...

Sheet Overview (2)
E1: Table | F1: Data field | G1: Efectivo y otros depósitos a la vista / Cash balances and other deposits | H1: Bancos Centrales / Central Banks | I1: Administraciones públicas / General governments | J1: Entidades de crédito / Credit institutions | K1: Otras sociedades financieras / Other financial corporations | L1: Sociedades no financieras / Non financial corporations | M1: Hogares / Households | N1: Data Types | O1: Field name | P1: Field Definition / Additional Guidance | R1: Default value for missing data | S1: Default value for not applicable fields to be used WHEN: (1) Non-contractual balances and accounting adjustments (2) If the field is not applicable for the corresponding segment (F to L columns)
C2: 6.1. Fora âmbito | Campos concluídos - Sem necessidade de espec. | E2: ENTITY | F2: COD_SOC | G2: Y | H2: Y | I2: Y | J2: Y | K2: Y | L2: Y | M2: Y | N2: VARCHAR2(5) | O2: Entity code of the informing society. | P2: Cargabal code or internal identifier of the informing society. | R2: Default value not allowed | S2: Default value not allowed | T2: #N/A | U2: 0
C3: 6.1. Fora âmbito | Campos concluídos - Sem necessidade de espec. | E3: ENTITY | F3: CNTRY | G3: Y | H3: Y | I3: Y | J3: Y | K3: Y | L3: Y | M3: Y | N3: =HYPERLINK("#"&"CodeList!"&ADDRESS(2,MATCH($F3,CodeList!$2:$2,0)+1,),"Code List") -> Code List | O3: Country of counterparty residence | P3: Country of counterparty residence. | R3: MISS | S3: N/A | T3: Y | U3: 0
C4: 5. Campos com outras possíveis alterações - Dependente de decisões OSI | E4: ENTITY | F4: DT_DFLT_STTS | G4: Y | H4: Y | I4: Y | J4: Y | K4: Y | L4: Y | M4: Y | N4: DATE | O4: Date of default status | P4: The date on which the default status, as reported in the data attribute “Default status”, is considered to have arisen. If "Not in default" since inception then this attribute is to be reported equally to the inception date. If default classification performed on instrument level then Entity is classified as defaulted when at least one instrument is classified as defaulted. If more than one Instrument is classified as defaulted then the earliest date has to be provided. The definition of default is aligned with Art 178 of Regulation (EU) No 575/2013. | R4: 0000-00-00 | S4: 1111-11-11 | T4: Y | U4: 0
C5: 6.4. Fora âmbito | Re-especificação de campos complexos - Dem. Fin. CIB | E5: ENTITY | F5: DT_FNNCL_STTMTS | G5: Y | H5: Y | I5: Y | J5: Y | K5: Y | L5: Y | M5: N | N5: DATE | O5: Date of financial statements | P5: Date of financial statements. Please report on solo entity level unless advised otherwise. | R5: 0000-00-00 | S5: 1111-11-11 | T5: Y | U5: 0
C6: 6.4. Fora âmbito | Re-especificação de campos complexos - Dem. Fin. CIB | E6: ENTITY | F6: DT_FNNCL_STTMTS_PRVS | G6: Y | H6: Y | I6: Y | J6: Y | K6: Y | L6: Y | M6: N | N6: DATE | O6: Date of previous fiscal year financial statements | P6: Date of previous fiscal year financial statements. Please report on solo entity level unless advised otherwise. | R6: 0000-00-00 | S6: 1111-11-11 | T6: Y | U6: 0
C7: 6.1. Fora âmbito | Campos concluídos - Sem necessidade de espec. | E7: ENTITY | F7: DT_INTTN_LGL_PRCDNGS_LE | G7: Y | H7: Y | I7: Y | J7: Y | K7: Y | L7: Y | M7: Y | N7: DATE | O7: Date of initiation of legal proceedings counterparty (LE) | P7: Date of initiation of legal proceedings counterparty (LE). Only for Retail portfolios: The date when the hard collection process was initiated for given entity. If the hard collection process is defined on the level of instrument or protection and more instruments or protections with status "Other legal measures" are linked to the same entity the oldest date is reported. | R7: 0000-00-00 | S7: 1111-11-11 | T7: Y | U7: 0
C8: 5. Campos com outras possíveis alterações - Dependente de decisões OSI | E8: ENTITY | F8: DT_PRFRMNG_STTS_LE | G8: Y | H8: Y | I8: Y | J8: Y | K8: Y | L8: Y | M8: Y | N8: DATE | O8: Date of performing status | P8: The date at which the latest change of the performing status according to Part 17 of Annex V to Implementing Regulation (EU) No 680/2014 occurred. For entities performing from inception this date should be equal to inception date. | R8: 0000-00-00 | S8: 1111-11-11 | T8: Y | U8: 0
C9: 6.1. Fora âmbito | Campos concluídos - Sem necessidade de espec. | E9: ENTITY | F9: DT_RFRNC | G9: Y | H9: Y | I9: Y | J9: Y | K9: Y | L9: Y | M9: Y | N9: DATE | O9: Reference date. | P9: Reference date. The reference date can refer to end-of-month, end-of-quarter or end-of-year. The value is fixed for the entire loan tape and will be defined and communicated by the Head of Mission. | R9: Default value not allowed | S9: Default value not allowed | T9: Y | U9: 0
C10: 4. Campos com NOK controlos Corporativos | E10: ENTITY | F10: ENTTY_ID | G10: Y | H10: Y | I10: Y | J10: Y | K10: Y | L10: Y | M10: Y | N10: VARCHAR2(255) | O10: Entity ID | P10: An identifier applied by the reporting agent to uniquely identify each counterparty. Each counterparty has a unique and exclusive counterparty identifier. This means that this value will not change over time and can never be used as the counterparty identifier for any other counterparty. | R10: Default value not allowed | S10: Default value not allowed | T10: Y | U10: 0
C11: 6.1. Fora âmbito | Campos concluídos - Sem necessidade de espec. | E11: ENTITY | F11: GCC_PRNT_ID | G11: Y | H11: Y | I11: Y | J11: Y | K11: Y | L11: Y | M11: N | N11: VARCHAR2(255) | O11: Identifier for the parent entity of a group of connected clients | P11: The unique identifier of the group of connected clients according to Art 4 para. 39 of Regulation (EU) No 575/2013. If an entity is part of more than one group of connected clients please report the identifier for the most relevant. | R11: MISS | S11: N/A | T11: Y | U11: 0
C12: 6.1. Fora âmbito | Campos concluídos - Sem necessidade de espec. | E12: ENTITY | F12: GCC_PRNT_NM | G12: Y | H12: Y | I12: Y | J12: Y | K12: Y | L12: Y | M12: N | N12: VARCHAR2(255) | O12: Name of the parent entity of a group of connected clients | P12: The name of the group of connected clients according to Art 4 para. 39 of Regulation (EU) No 575/2013. If an entity is part of more than one group of connected clients please report the name for the most relevant. | R12: MISS | S12: N/A | T12: Y | U12: 0
C13: 6.1. Fora âmbito | Campos concluídos - Sem necessidade de espec. | E13: ENTITY | F13: INTRNL_SGMNT | G13: Y | H13: Y | I13: Y | J13: Y | K13: Y | L13: Y | M13: Y | N13: VARCHAR2(255) | O13: Internal code for segment/portfolio | P13: Internal classification of the bank. Segmentation of the counterpart according to bank-internal definition / nomenclature, e.g. corporate, sme, leverage finance exposure, commercial real estate spv etc.. | R13: MISS | S13: N/A | T13: Y | U13: 0
C14: 6.1. Fora âmbito | Campos concluídos - Sem necessidade de espec. | E14: ENTITY | F14: INTRNL_UNT | G14: Y | H14: Y | I14: Y | J14: Y | K14: Y | L14: Y | M14: Y | N14: VARCHAR2(255) | O14: Internal code for business line/unit | P14: Internal classification of the bank of the obligor administrating business unit, e.g. if the obligor has been transferred to the intensified loan management department it should be flagged as such. | R14: MISS | S14: N/A | T14: Y | U14: 0
C15: 6.1. Fora âmbito | Campos concluídos - Sem necessidade de espec. | E15: ENTITY | F15: LEI | G15: Y | H15: Y | I15: Y | J15: Y | K15: Y | L15: Y | M15: N | N15: VARCHAR2(20) | O15: Legal entity identifier Counterparty | P15: Legal entity identifier counterparty. | R15: MISS | S15: N/A | T15: Y | U15: 0
... C17: 2.2 Re-especificação de campos complexos - Resto | E17: ENTITY | F17: EXTRNL_RTNG_NM | G17: Y | H17: Y | I17: Y | J17: Y | K17: Y | L17: Y | M17: N | N17: VARCHAR2(255) | O17: Name of external rating agency | P17: Name of external rating agency for the external rating at the reference date. | R17: MISS | S17: N/A | T17: Y | U17: 0
C18: 6.4. Fora âmbito | Re-especificação de campos complexos - Dem. Fin. CIB | E18: ENTITY | F18: ACCNTNG_FRMWRK_SL | G18: Y | H18: Y | I18: Y | J18: Y | K18: Y | L18: Y | M18: N | N18: =HYPERLINK("#"&"CodeList!"&ADDRESS(2,MATCH($F18,CodeList!$2:$2,0)+1,),"Code List") -> Code List | O18: Accounting standard counterparty | P18: Accounting standard counterparty. | R18: 99999999999 | S18: 11111111111 | T18: Y | U18: 0
C19: 5. Campos com outras possíveis alterações - Dependente de decisões OSI | E19: ENTITY | F19: DFLT_STTS | G19: Y | H19: Y | I19: Y | J19: Y | K19: Y | L19: Y | M19: Y | N19: =HYPERLINK("#"&"CodeList!"&ADDRESS(2,MATCH($F19,CodeList!$2:$2,0)+1,),"Code List") -> Code List | O19: Default status of the entity | P19: Identification of the default status of the counterparty. Categories describing the motives for which the counterparty can be in default in accordance with Article 178 of Regulation (EU) No 575/2013. For retail only: If default classification performed on instrument level then Entity is classified as defaulted when at least one instrument is classified as defaulted. For corporate, SME, CRE and LF: if default classification performed on instrument level then entity level is "not applicable". | R19: 99999999999 | S19: 11111111111 | T19: Y | U19: 0
C20: 2.2 Re-especificação de campos complexos - Resto | E20: ENTITY | F20: DT_EXTRNL_RTNG | G20: Y | H20: Y | I20: Y | J20: Y | K20: Y | L20: Y | M20: N | N20: DATE | O20: Date of external rating | P20: Date of the most recent external rating, i.e. applicable at the reference date. | R20: 0000-00-00 | S20: 1111-11-11 | T20: Y | U20: 0
C21: 3. Campos em testes ou c/ incidências | E21: ENTITY | F21: DT_INTRNL_RTNG | G21: Y | H21: Y | I21: Y | J21: Y | K21: Y | L21: Y | M21: Y | N21: DATE | O21: Date of internal rating | P21: Date of the most recent internal rating according to Regulation (EU) No 575/2013, i.e. applicable rating as at the reference date. If the rating is assigned on instrument level then provide the rating for the instrument with the highest EAD. | R21: 0000-00-00 | S21: 1111-11-11 | T21: Y | U21: 0
C22: 6.1. Fora âmbito | Campos concluídos - Sem necessidade de espec. | E22: ENTITY | F22: ECNMC_ACTVTY | G22: N | H22: N | I22: N | J22: N | K22: Y | L22: Y | M22: N | N22: Code List | O22: Economic activity counterparty | P22: The level four NACE code in accordance with Regulation (EC) No 1893/2006 is generally reported. If the level four NACE code is not available it may be allowed to report a level three or level two NACE code. | R22: MISS | S22: N/A | T22: Y | U22: 0
C23: 2.2 Re-especificação de campos complexos - Resto | E23: ENTITY | F23: EXTRNL_RTNG | G23: Y | H23: Y | I23: Y | J23: Y | K23: Y | L23: Y | M23: N | N23: Code List | O23: External rating | P23: External rating at the reference date. | R23: 99999999999 | S23: 11111111111 | T23: Y | U23: 0
C24: 2.2 Re-especificação de campos complexos - Resto | E24: ENTITY | F24: EXTRNL_RTNG_PRVS | G24: Y | H24: Y | I24: Y | J24: Y | K24: Y | L24: Y | M24: N | N24: Code List | O24: External rating T-1 | P24: External rating one year prior to the reference date. | R24: 99999999999 | S24: 11111111111 | T24: Y | U24: 0
C25: 6.1. Fora âmbito | Campos concluídos - Sem necessidade de espec. | E25: ENTITY | F25: FLG_RQST_EMRGNCY_FNDNG | G25: N | H25: N | I25: N | J25: N | K25: Y | L25: Corporation | M25: Corporation | N25: Y, N | O25: Request by the debtor for emergency funding from the bank | P25: Report "Y" if there is a request by the debtor for emergency funding from the bank. | R25: MISS | S25: N/A | T25: Y | U25: 0
C26: 3. Campos em testes ou c/ incidências | E26: ENTITY | F26: INTRNL_RTNG | G26: Y | H26: Y | I26: Y | J26: Y | K26: Y | L26: Y | M26: Y | N26: =HYPERLINK("#"&"CodeList!"&ADDRESS(2,MATCH($F26,CodeList!$2:$2,0)+1,),"Code List") -> Code List | O26: Internal rating at reference date | P26: Internal rating at the reference date according to Regulation (EU) No 575/2013. Please also add in sheet "Code List" the list of values used, i.e. bank-internal masterscale. | R26: MISS | S26: N/A | T26: Y | U26: 0
C27: 3. Campos em testes ou c/ incidências | E27: ENTITY | F27: INTRNL_RTNG_PRVS | G27: Y | H27: Y | I27: Y | J27: Y | K27: Y | L27: Y | M27: Y | N27: =HYPERLINK("#"&"CodeList!"&ADDRESS(2,MATCH($F27,CodeList!$2:$2,0)+1,),"Code List") -> Code List | O27: Previous internal rating | P27: Internal rating according to Regulation (EU) No 575/2013 one year prior to the reference date. | R27: MISS | S27: N/A | T27: Y | U27: 0
C28: 4. Campos com NOK controlos Corporativos | E28: ENTITY | F28: LGL_PRCDNG_STTS_LE | G28: Y | H28: Y | I28: Y | J28: Y | K28: Y | L28: Y | M28: Y | N28: =HYPERLINK("#"&"CodeList!"&ADDRESS(2,MATCH($F28,CodeList!$2:$2,0)+1,),"Code List") -> Code List | O28: Legal proceedings status Counterparty (LE) | P28: Legal proceedings status Counterparty (LE). Only for Retail portfolios: Status "No legal action taken" or "Other legal measures" are possible. Status "Other legal measures" is reported when the hard collection process was initiated at the level of a given entity or at the level of any associated instrument or protection of this entity. | R28: 99999999999 | S28: Default value not allowed | T28: Y | U28: 0
C29: 6.3. Fora âmbito | Fonte Manual LF | E29: ENTITY | F29: OWND_BY_SPNSR | G29: N | H29: N | I29: N | J29: N | K29: Y | L29: Y | M29: N | N29: Y, N | O29: >50% owned by a sponsor as per ECB Guidance on leveraged transactions | P29: In accordance the ECB Guidance on Leveraged Transactions. As per point (37) of Article 4(1) of Regulation (EU) No 575/2013, a financial sponsor is deemed to be the owner if it controls or owns more than 50% of the borrower’s equity. The term “financial sponsor” refers to an investment firm that undertakes private equity investments in and/or leveraged buyouts of companies with the intention of exiting those investments on a mediumterm basis | R29: MISS | S29: N/A | T29: Y | U29: 0
C30: 6.1. Fora âmbito | Campos concluídos - Sem necessidade de espec. | E30: ENTITY | F30: PRFRMNG_STTS_LE | G30: Y | H30: Y | I30: Y | J30: Y | K30: Y | L30: Y | M30: Y | N30: =HYPERLINK("#"&"CodeList!"&ADDRESS(2,MATCH($F30,CodeList!$2:$2,0)+1,),"Code List") -> Code List | O30: Performing status | P30: Performing status. Identification of the performing status of the counterparty. Categories describing the motives for which the counterparty can be non-performing in accordance with Implementing Technical Standard (ITS) on Supervisory Reporting (Forbearance and non-performing exposures). For retail only: If performing classification performed on instrument level then Entity is classified as non-performing when at least one instrument is classified as non-performing For corporate, SME, CRE and LF: if default classification performed on instrument level then entity level is "not applicable". | R30: 99999999999 | S30: 11111111111 | T30: Y | U30: 0
C31: 3. Campos em testes ou c/ incidências | E31: ENTITY | F31: RTNG_MTHD | G31: Y | H31: Y | I31: Y | J31: Y | K31: Y | L31: Y | M31: Y | N31: =HYPERLINK("#"&"CodeList!"&ADDRESS(2,MATCH($F31,CodeList!$2:$2,0)+1,),"Code List") -> Code List | O31: Rating method | P31: Internal definition and name of the rating/scoring model. | R31: 99999999999 | S31: 11111111111 | T31: Y | U31: 0
C32: 6.1. Fora âmbito | Campos concluídos - Sem necessidade de espec. | E32: ENTITY | F32: RTNG_SCL | G32: Corporation | H32: Corporation | I32: Corporation | J32: Corporation | K32: Corporation | L32: Corporation | M32: Corporation | N32: =HYPERLINK("#"&"CodeList!"&ADDRESS(2,MATCH($F32,CodeList!$2:$2,0)+1,),"Code List") -> Code List | O32: Rating scale | P32: Internal name and definition of the rating master scale. It should be mapped to the assigned rating, i.e. INTRNL_RTNG. | R32: 99999999999 | S32: 11111111111 | T32: Y | U32: 0
C33: 6.1. Fora âmbito | Campos concluídos - Sem necessidade de espec. | E33: ENTITY | F33: WTCH_LST | G33: N | H33: Y | I33: Y | J33: Y | K33: Y | L33: Y | M33: Y | N33: Y, N | O33: Debtor on watch-list (Y/N) | P33: Report "Y" when the debtor has been added to an internal watch list. | R33: MISS | S33: N/A | T33: Y | U33: 0
C34: 6.1. Fora âmbito | Campos concluídos - Sem necessidade de espec. | E34: ENTITY | F34: GRP_EBITDA | G34: Y | H34: Y | I34: Y | J34: Y | K34: Y | L34: Y | M34: N | N34: FLOAT 2 decimal places | O34: Group's EBITDA at most recent reported figures | P34: EBITDA at latest reported figures. Please report level of the consolidated financial statement of the group accoding to the applicable accounting standard. | R34: 99999999999 | S34: 11111111111 | T34: Y | U34: 0
C35: 6.1. Fora âmbito | Campos concluídos - Sem necessidade de espec. | E35: ENTITY | F35: GRP_EQTY | G35: Y | H35: Y | I35: Y | J35: Y | K35: Y | L35: Y | M35: N | N35: FLOAT 2 decimal places | O35: Group's equity at most recent reported figures | P35: Equity at most recent reported figures. Please report level of the consolidated financial statement of the group accoding to the applicable accounting standard. | R35: 99999999999 | S35: 11111111111 | T35: Y | U35: 0
C36: 6.1. Fora âmbito | Campos concluídos - Sem necessidade de espec. | E36: ENTITY | F36: GRP_NT_DBT | G36: Y | H36: Y | I36: Y | J36: Y | K36: Y | L36: Y | M36: N | N36: FLOAT 2 decimal places | O36: Total net debt at most recent reported figures | P36: Total net debt at most recent reported figures. Please report level of the consolidated financial statement of the group accoding to the applicable accounting standard. | R36: 99999999999 | S36: 11111111111 | T36: Y | U36: 0
C37: 6.4. Fora âmbito | Re-especificação de campos complexos - Dem. Fin. CIB | E37: ENTITY | F37: ANNL_TRNVR_LE | G37: Y | H37: Y | I37: Y | J37: Y | K37: Y | L37: Y | M37: N | N37: FLOAT 2 decimal places | O37: Annual turnover counterparty (LE) | P37: Annual sales volume net of all discounts and sales taxes in accordance with Recommendation 2003/361/EC. Equivalent to the concept of 'total annual sales' in Article 153(4) of Regulation (EU) No 575/2013. Please report on solo entity level unless advised otherwise. | R37: 99999999999 | S37: 11111111111 | T37: Y | U37: 0
C38: 6.4. Fora âmbito | Re-especificação de campos complexos - Dem. Fin. CIB | E38: ENTITY | F38: ANNL_TRNVR_PRVS | G38: Y | H38: Y | I38: Y | J38: Y | K38: Y | L38: Y | M38: N | N38: FLOAT 2 decimal places | O38: Annual turnover counterparty (LE) at previous reporting | P38: Annual sales volume net of all discounts and sales taxes in accordance with Recommendation 2003/361/EC. Equivalent to the concept of 'total annual sales' in Article 153(4) of Regulation (EU) No 575/2013. Please report on solo entity level unless advised otherwise. | R38: 99999999999 | S38: 11111111111 | T38: Y | U38: 0
C39: 6.4. Fora âmbito | Re-especificação de campos complexos - Dem. Fin. CIB | E39: ENTITY | F39: EBITDA | G39: Y | H39: Y | I39: Y | J39: Y | K39: Y | L39: Y | M39: N | N39: FLOAT 2 decimal places | O39: EBITDA at latest reported figures | P39: EBITDA at latest reported figures. Please report on solo entity level unless advised otherwise. | R39: 99999999999 | S39: 11111111111 | T39: Y | U39: 0
C40: 6.4. Fora âmbito | Re-especificação de campos complexos - Dem. Fin. CIB | E40: ENTITY | F40: EBITDA_PRVS | G40: Y | H40: Y | I40: Y | J40: Y | K40: Y | L40: Y | M40: N | N40: FLOAT 2 decimal places | O40: EBITDA at previous reported figures | P40: EBITDA at previous reported figures. Please report on solo entity level unless advised otherwise. | R40: 99999999999 | S40: 11111111111 | T40: Y | U40: 0
C41: 6.4. Fora âmbito | Re-especificação de campos complexos - Dem. Fin. CIB | E41: ENTITY | F41: EQTY | G41: Y | H41: Y | I41: Y | J41: Y | K41: Y | L41: Y | M41: N | N41: FLOAT 2 decimal places | O41: Equity at most recent reported figures | P41: Equity at most recent reported figures. Please report on solo entity level unless advised otherwise. | R41: 99999999999 | S41: 11111111111 | T41: Y | U41: 0
C42: 6.4. Fora âmbito | Re-especificação de campos complexos - Dem. Fin. CIB | E42: ENTITY | F42: EQTY_PRVS | G42: Y | H42: Y | I42: Y | J42: Y | K42: Y | L42: Y | M42: N | N42: FLOAT 2 decimal places | O42: Equity at previous reported figures | P42: Equity at previous reported figures. Please report on solo entity level unless advised otherwise. | R42: 99999999999 | S42: 11111111111 | T42: Y | U42: 0
C43: 6.1. Fora âmbito | Campos concluídos - Sem necessidade de espec. | E43: ENTITY | F43: LVRG | G43: Y | H43: Y | I43: Y | J43: Y | K43: Y | L43: Y | M43: N | N43: FLOAT 6 decimal places | O43: Leverage (net debt / EBITDA) at most recent reported figures | P43: Leverage ratio calculated as net debt divided by EBITDA at most recent reported figures. | R43: 99999999999 | S43: 11111111111 | T43: Y | U43: 0
C44: 6.1. Fora âmbito | Campos concluídos - Sem necessidade de espec. | E44: ENTITY | F44: LVRG_PRVS | G44: Y | H44: Y | I44: Y | J44: Y | K44: Y | L44: Y | M44: N | N44: FLOAT 6 decimal places | O44: Leverage (net debt / EBITDA) at previous reported figures | P44: Leverage ratio calculated as net debt divided by EBITDA at previous reported figures. | R44: 99999999999 | S44: 11111111111 | T44: Y | U44: 0
C45: 6.4. Fora âmbito | Re-especificação de campos complexos - Dem. Fin. CIB | E45: ENTITY | F45: NT_INCM | G45: Y | H45: Y | I45: Y | J45: Y | K45: Y | L45: Y | M45: N | N45: FLOAT 2 decimal places | O45: Net income at most recent reported figures | P45: Net income at most recent reported figures after tax and any other social insurance deductions according to tax declaration. Please report on solo entity level unless advised otherwise. | R45: 99999999999 | S45: 11111111111 | T45: Y | U45: 0
... C55: 5. Campos com outras possíveis alterações - Dependente de decisões OSI | E55: ENTITY | F55: PD_IFRS9_12M_RD | G55: Y | H55: Y | I55: Y | J55: Y | K55: Y | L55: Y | M55: Y | N55: FLOAT 6 decimal places | O55: 12-month PD at reporting date according to IFRS 9 | P55: 12-month PD at reference date which is used by the bank for computation of stage 1 ECL or for SICR assessment if bank use 12 month proxy for staging. If the PD is calculated on instruments level please provide an EAD weighted average. | R55: 99999999999 | S55: 11111111111 | T55: Y | U55: 0
C56: 6.1. Fora âmbito | Campos concluídos - Sem necessidade de espec. | E56: ENTITY | F56: OSI_ID | G56: Corporation | H56: Corporation | I56: Corporation | J56: Corporation | K56: Corporation | L56: Corporation | M56: Corporation | N56: VARCHAR2(255) | O56: On-site inspection identifier | P56: The identifier that is used to identify an on-site inspection as is referenced in the on-site inspection notification letter head. The value typically follows the convention: "OSI-YYYY-JSTCD-01234". | R56: MISS | S56: N/A | T56: Y | U56: 0
C57: 2.2 Re-especificação de campos complexos - Resto | E57: ENTITY | F57: EC_GRP_ID | G57: Y | H57: Y | I57: Y | J57: Y | K57: Y | L57: Y | M57: N | N57: VARCHAR2(255) | O57: Economic (financial) Group ID | P57: The unit should report the unique identifier of the economic group (ultimate parent entity) of the counterparty. | R57: MISS | S57: N/A | T57: #N/A | U57: 0
C58: 2.2 Re-especificação de campos complexos - Resto | E58: ENTITY | F58: EC_GRP_NM | G58: Y | H58: Y | I58: Y | J58: Y | K58: Y | L58: Y | M58: N | N58: VARCHAR2(255) | O58: Economic (Financial) Group Name | P58: The unit should report the legal/official name of the ultimate parent entity of the counterparty’s economic group | R58: MISS | S58: N/A | T58: #N/A | U58: 0
C59: 2.2 Re-especificação de campos complexos - Resto | E59: ENTITY | F59: FR_CSH_FLW | G59: N | H59: N | I59: N | J59: N | K59: Y | L59: Y | M59: N | N59: FLOAT 2 decimal places | O59: Free Cash Flow | P59: Non-retail clients’ Free Cash Flow at reference date T+0, according to bank-internal projections. | R59: 99999999999 | S59: 11111111111 | T59: Y | U59: 0
C60: 2.2 Re-especificação de campos complexos - Resto | E60: ENTITY | F60: FR_CSH_FLW_T1 | G60: N | H60: N | I60: N | J60: N | K60: Y | L60: Y | M60: N | N60: FLOAT 2 decimal places | O60: Free Cash Flow T+1 | P60: Non-retail clients’ Free Cash Flow at reference date T+1, according to bank-internal projections. | R60: 99999999999 | S60: 11111111111 | T60: Y | U60: 0
C61: 2.2 Re-especificação de campos complexos - Resto | E61: ENTITY | F61: FR_CSH_FLW_T2 | G61: N | H61: N | I61: N | J61: N | K61: Y | L61: Y | M61: N | N61: FLOAT 2 decimal places | O61: Free Cash Flow T+2 | P61: Non-retail clients’ Free Cash Flow at reference date T+2, according to bank-internal projections. | R61: 99999999999 | S61: 11111111111 | T61: Y | U61: 0
C62: 2.2 Re-especificação de campos complexos - Resto | E62: ENTITY | F62: FR_CSH_FLW_T3 | G62: N | H62: N | I62: N | J62: N | K62: Y | L62: Y | M62: N | N62: FLOAT 2 decimal places | O62: Free Cash Flow T+3 | P62: Non-retail clients’ Free Cash Flow at reference date T+3, according to bank-internal projections. | R62: 99999999999 | S62: 11111111111 | T62: Y | U62: 0
C63: 1. Novos Campos | E63: ENTITY | F63: FLLN_ANGL_NRRW_DFNTN | G63: N | H63: N | I63: N | J63: N | K63: Y | L63: Y | M63: N | N63: Y, N | O63: Fallen Angel narrow definition | P63: Fallen Angel narrow definition refer to borrowers that lost the Investment Grade status (equivalent internal or external rating of BBB- (S&P)/BBB- (Fitch)/Baa3 (Moody’s) or above) after the origination of the exposure, i.e., fell to a non-investment grade after having been classified with an investment grade at origination. | R63: MISS | S63: N/A | T63: Y | U63: Y
C64: 1. Novos Campos | E64: ENTITY | F64: FLLN_ANGL_EXTNDD_DFNTN | G64: N | H64: N | I64: N | J64: N | K64: Y | L64: Y | M64: N | N64: Y, N | O64: Fallen Angel extended definition | P64: Fallen Angel extended definition refer to borrowers that experienced an increase of Leverage finance ratio (as per ECB Guidance on leveraged transactions; total debt vs EBITDA) due to a material deterioriation in financial performance after origination. | R64: MISS | S64: N/A | T64: Y | U64: Y
C65: 1. Novos Campos | E65: ENTITY | F65: RORAC | G65: N | H65: N | I65: N | J65: N | K65: Y | L65: Y | M65: N | N65: FLOAT 6 decimal places | O65: RORAC | P65: Return On Risk-Adjusted Capital (RORAC) of the counterparty | R65: 99999999999 | S65: 11111111111 | T65: #N/A | U65: #N/A
C66: 1. Novos Campos | E66: ENTITY | F66: GRP_RORAC | G66: N | H66: N | I66: N | J66: N | K66: Y | L66: Y | M66: N | N66: FLOAT 6 decimal places | O66: Group's RORAC | P66: Return On Risk-Adjusted Capital (RORAC) of the counterparty's economic group. | R66: 99999999999 | S66: 11111111111 | T66: #N/A | U66: #N/A
C67: 1. Novos Campos | E67: ENTITY | F67: RORWA | G67: N | H67: N | I67: N | J67: N | K67: Y | L67: Y | M67: N | N67: FLOAT 6 decimal places | O67: RoRWA | P67: Return On Risk Weighted Assets (RoRWA) of the counterparty | R67: 99999999999 | S67: 11111111111 | T67: #N/A | U67: #N/A
C68: 1. Novos Campos | E68: ENTITY | F68: GRP_RORWA | G68: N | H68: N | I68: N | J68: N | K68: Y | L68: Y | M68: N | N68: FLOAT 6 decimal places | O68: Group's RoRWA | P68: Return On Risk Weighted Assets (RoRWA) of the counterparty's economic group. | R68: 99999999999 | S68: 11111111111 | T68: #N/A | U68: #N/A
C69: 1. Novos Campos | E69: ENTITY | F69: SCAN | G69: N | H69: N | I69: N | J69: N | K69: Y | L69: Y | M69: N | N69: =HYPERLINK("#"&"CodeList!"&ADDRESS(2,MATCH($F69,CodeList!$2:$2,0)+1,),"Code List") -> #N/A | O69: SCAN | P69: SCAN of the counterparty | R69: MISS | S69: 11111111111 | T69: #N/A | U69: #N/A
C70: 1. Novos Campos | E70: ENTITY | F70: TTL_PRMSSBL_DBT_BLNC | G70: N | H70: N | I70: N | J70: N | K70: Y | L70: Y | M70: N | N70: FLOAT 2 decimal places | O70: Total permissible debt balance | P70: The term “Total Permissible Debt Balance” refers to total committed debt (including drawn and undrawn debt) plus total not committed debt. Cash should not be netted against debt. Please report on solo entity level unless advised otherwise. | R70: 99999999999 | S70: 11111111111 | T70: Y | U70: #N/A
C71: 6.1. Fora âmbito | Campos concluídos - Sem necessidade de espec. | E71: INSTR_ENTITY | F71: COD_SOC | G71: Y | H71: Y | I71: Y | J71: Y | K71: Y | L71: Y | M71: Y | N71: VARCHAR2(5) | O71: Entity code of the informing society. | P71: Cargabal code or internal identifier of the informing society. | R71: Default value not allowed | S71: Default value not allowed | T71: #N/A | U71: 0
C72: 6.1. Fora âmbito | Campos concluídos - Sem necessidade de espec. | E72: INSTR_ENTITY | F72: DT_RFRNC | G72: Y | H72: Y | I72: Y | J72: Y | K72: Y | L72: Y | M72: Y | N72: DATE | O72: Reference date | P72: Reference date. The reference date can refer to end-of-month, end-of-quarter or end-of-year. The value is fixed for the entire loan tape and will be defined and communicated by the Head of Mission. | R72: Default value not allowed | S72: Default value not allowed | T72: Y | U72: 0
C73: 4. Campos com NOK controlos Corporativos | E73: INSTR_ENTITY | F73: ENTTY_ID | G73: Y | H73: Y | I73: Y | J73: Y | K73: Y | L73: Y | M73: Y | N73: VARCHAR2(255) | O73: Entity ID | P73: An identifier applied by the reporting agent to uniquely identify each counterparty. Each counterparty has a unique and exclusive counterparty identifier. This means that this value will not change over time and can never be used as the counterparty identifier for any other counterparty. Foreign key from ENTITY table. | R73: Default value not allowed | S73: Default value not allowed | T73: Y | U73: 0
C74: 6.1. Fora âmbito | Campos concluídos - Sem necessidade de espec. | E74: INSTR_ENTITY | F74: INSTRMNT_ID | G74: Y | H74: Y | I74: Y | J74: Y | K74: Y | L74: Y | M74: Y | N74: VARCHAR2(60) | O74: Instrument ID | P74: An identifier applied by the reporting agent to uniquely identify each instrument under a single contract. Each instrument must have one instrument identifier. This value will not change over time and cannot be used as the instrument identifier for any other instrument under the same contract. Supervised Insitutions are asked to furnish the INSTRMNT_ID with the exact same value as it is reported to AnaCredit (or any similar central credit register). If this is not available, the value shall be reported as it is internally used. If an instrument is not reported to AnaCredit but requested for the purposes of the on-site inspection please provide the bank-internally used value. Foreign Key from INSTRUMENT table. | R74: Default value not allowed | S74: Default value not allowed | T74: Y | U74: 0
C75: 6.1. Fora âmbito | Campos concluídos - Sem necessidade de espec. | E75: INSTR_ENTITY | F75: JNT_LBLTY_AMNT | G75: Y | H75: Y | I75: Y | J75: Y | K75: Y | L75: Y | M75: Y | N75: FLOAT 2 decimal places | O75: Joint-liability amount | P75: Outstanding nominal amount for which each debtor is liable in relation to a single instrument where there are two or more debtors. In the case of instruments where there is only one debtor, please report "not applicable" using the respective fall-back parameters. | R75: 99999999999 | S75: 11111111111 | T75: Y | U75: 0
C76: 3. Campos em testes ou c/ incidências | E76: INSTR_ENTITY | F76: MN_ENTTY_ID | G76: N | H76: Y | I76: Y | J76: Y | K76: Y | L76: Y | M76: Y | N76: Y, N | O76: Main Entity ID | P76: Report "Y" if "Entity ID" is the main entity of the Instrument ID | R76: Default value not allowed | S76: N/A | T76: #N/A | U76: 0
C77: 6.1. Fora âmbito | Campos concluídos - Sem necessidade de espec. | E77: INSTRUMENT | F77: COD_SOC | G77: Y | H77: Y | I77: Y | J77: Y | K77: Y | L77: Y | M77: Y | N77: VARCHAR2(5) | O77: Entity code of the informing society. | P77: Cargabal code or internal identifier of the informing society. | R77: Default value not allowed | S77: Default value not allowed | T77: #N/A | U77: 0
C78: 6.1. Fora âmbito | Campos concluídos - Sem necessidade de espec. | E78: INSTRUMENT | F78: SUBPORTFOLIO_ID | G78: Y | H78: Y | I78: Y | J78: Y | K78: Y | L78: Y | M78: Y | N78: Code List | O78: Subportfolio ID | P78: The unique identifier of each requested sub-portfolio is constructed considering a coding resulting from the attributes of the sub-portfolio. | R78: Default value not allowed | S78: Default value not allowed | T78: #N/A | U78: 0
C79: 6.1. Fora âmbito | Campos concluídos - Sem necessidade de espec. | E79: INSTRUMENT | F79: DT_RFRNC | G79: Y | H79: Y | I79: Y | J79: Y | K79: Y | L79: Y | M79: Y | N79: DATE | O79: Reference date | P79: Reference date. The reference date can refer to end-of-month, end-of-quarter or end-of-year. The value is fixed for the entire loan tape and will be defined and communicated by the Head of Mission. | R79: Default value not allowed | S79: Default value not allowed | T79: Y | U79: 0
C80: 6.1. Fora âmbito | Campos concluídos - Sem necessidade de espec. | E80: INSTRUMENT | F80: INSTRMNT_ID | G80: Y | H80: Y | I80: Y | J80: Y | K80: Y | L80: Y | M80: Y | N80: VARCHAR2(60) | O80: Instrument ID | P80: An identifier applied by the reporting agent to uniquely identify each instrument under a single contract. Each instrument must have one instrument identifier. This value will not change over time and cannot be used as the instrument identifier for any other instrument under the same contract. Supervised Insitutions are asked to furnish the INSTRMNT_ID with the exact same value as it is reported to AnaCredit (or any similar central credit register). If this is not available, the value shall be reported as it is internally used. If an instrument is not reported to AnaCredit but requested for the purposes of the on-site inspection please provide the bank-internally used value. | R80: Default value not allowed | S80: Default value not allowed | T80: Y | U80: 0
C81: 6.1. Fora âmbito | Campos concluídos - Sem necessidade de espec. | E81: INSTRUMENT | F81: CRRNCY_DNMNTN | G81: Y | H81: Y | I81: Y | J81: Y | K81: Y | L81: Y | M81: Y | N81: =HYPERLINK("#"&"CodeList!"&ADDRESS(2,MATCH($F81,CodeList!$2:$2,0)+1,),"Code List") -> Code List | O81: Currency denomination | P81: Currency denomination of instruments, in accordance with the ISO 4217 standard. | R81: MISS | S81: N/A | T81: Y | U81: 0
C82: 4. Campos com NOK controlos Corporativos | E82: INSTRUMENT | F82: DT_INCPTN | G82: Y | H82: Y | I82: Y | J82: Y | K82: Y | L82: Y | M82: Y | N82: DATE | O82: Date of inception | P82: The date on which the contractual relationship originated, i.e. the date on which the contract agreement becomes binding for all parties | R82: 0000-00-00 | S82: 1111-11-11 | T82: Y | U82: 0
C83: 6.1. Fora âmbito | Campos concluídos - Sem necessidade de espec. | E83: INSTRUMENT | F83: OBSRVD_AGNT_ID | G83: Y | H83: Y | I83: Y | J83: Y | K83: Y | L83: Y | M83: Y | N83: VARCHAR2(50) | O83: Observed agent identifier | P83: Counterparty identifier for the observed agent. If there are several observed agents to be reported please separate by comma (,). | R83: Default value not allowed | S83: N/A | T83: Y | U83: 0
C84: 6.1. Fora âmbito | Campos concluídos - Sem necessidade de espec. | E84: INSTRUMENT | F84: OBSRVD_AGNT_NM | G84: Y | H84: Y | I84: Y | J84: Y | K84: Y | L84: Y | M84: Y | N84: VARCHAR2(255) | O84: Observed Agent Name | P84: Counterparty name for the observed agent. If there are several observed agents to be reported please separate by comma (,). | R84: Default value not allowed | S84: N/A | T84: Y | U84: 0
C85: 6.1. Fora âmbito | Campos concluídos - Sem necessidade de espec. | E85: INSTRUMENT | F85: BRCHD_CVNNTS | G85: N | H85: N | I85: N | J85: N | K85: Y | L85: Y | M85: N | N85: VARCHAR2(255) | O85: Breached covenants | P85: Breached covenants separated by comma (,). | R85: MISS | S85: N/A | T85: Y | U85: 0
C86: 6.1. Fora âmbito | Campos concluídos - Sem necessidade de espec. | E86: INSTRUMENT | F86: CSH_SWP_TRP | G86: N | H86: Y | I86: Y | J86: Y | K86: Y | L86: Y | M86: N | N86: Y, N | O86: Cash sweep or cash trap covenants agreed (Y/N) | P86: Report "Y" if the agreement with the debtor includes cash sweep or cash trap covenants. | R86: MISS | S86: N/A | T86: Y | U86: 0
C87: 6.3. Fora âmbito | Fonte Manual LF | E87: INSTRUMENT | F87: CVNNT_STTS | G87: N | H87: N | I87: N | J87: N | K87: Y | L87: Y | M87: N | N87: =HYPERLINK("#"&"CodeList!"&ADDRESS(2,MATCH($F87,CodeList!$2:$2,0)+1,),"Code List") -> Code List | O87: Covenant status | P87: In accordance with "ECB Guidance on leveraged transactions". The term "material covenant" should be defined according to bank-internal nomenclature. | R87: 99999999999 | S87: 11111111111 | T87: Y | U87: 0
C88: 6.3. Fora âmbito | Fonte Manual LF | E88: INSTRUMENT | F88: CVNNT_TYP | G88: N | H88: N | I88: N | J88: N | K88: Y | L88: Y | M88: N | N88: =HYPERLINK("#"&"CodeList!"&ADDRESS(2,MATCH($F88,CodeList!$2:$2,0)+1,),"Code List") -> Code List | O88: Covenant Type | P88: Type of covenant according to "ECB Guidance on leveraged transactions". | R88: 99999999999 | S88: 11111111111 | T88: Y | U88: 0
C89: 2.2 Re-especificação de campos complexos - Resto | E89: INSTRUMENT | F89: DFLT_STTS_INSTRMNT | G89: Y | H89: Y | I89: Y | J89: Y | K89: Y | L89: Y | M89: Y | N89: =HYPERLINK("#"&"CodeList!"&ADDRESS(2,MATCH($F89,CodeList!$2:$2,0)+1,),"Code List") -> Code List | O89: Default status of the instrument | P89: Identification of the default status of the instrument. Categories describing the situations in which an instrument can be described as being at default in accordance with Article 178 of Regulation (EU) No 575/2013. | R89: 99999999999 | S89: Default value not allowed | T89: Y | U89: 0
C90: 3. Campos em testes ou c/ incidências | E90: INSTRUMENT | F90: DT_DFLT_STTS_INSTRMNT | G90: Y | H90: Y | I90: Y | J90: Y | K90: Y | L90: Y | M90: Y | N90: DATE | O90: Date of default status | P90: The date on which the default status, as reported in the data attribute “Default status”, is considered to have arisen. If "Not in default" since inception then this attribute is to be reported equally to the inception date. If more than one Instrument is classified as defaulted then the earliest date has to be provided. The definition of default is aligned with Art 178 of Regulation (EU) No 575/2013. | R90: 0000-00-00 | S90: 1111-11-11 | T90: Y | U90: 0
C91: 2.2 Re-especificação de campos complexos - Resto | E91: INSTRUMENT | F91: DT_FRBRNC_STTS | G91: Y | H91: Y | I91: Y | J91: Y | K91: Y | L91: Y | M91: Y | N91: DATE | O91: Date of forbearance status | P91: Date of forbearance status. If the instrument has never been subject to forbearance measure then this date would be equal to the inception date. | R91: 0000-00-00 | S91: 1111-11-11 | T91: Y | U91: 0
C92: 3. Campos em testes ou c/ incidências | E92: INSTRUMENT | F92: DT_INTRNL_RTNG | G92: Y | H92: Y | I92: Y | J92: Y | K92: Y | L92: Y | M92: Y | N92: DATE | O92: Date of internal rating | P92: Date of the most recent internal rating according to Regulation (EU) No 575/2013, i.e. applicable rating as at the reference date. If the rating is assigned on entity level then provide the entity rating for all instruments. | R92: 0000-00-00 | S92: 1111-11-11 | T92: Y | U92: 0
C93: 6.2. Fora âmbito | Campos em testes ou c/ incidências (LT - PM) | E93: INSTRUMENT | F93: DT_PRFRMNG_STTS | G93: Y | H93: Y | I93: Y | J93: Y | K93: Y | L93: Y | M93: Y | N93: DATE | O93: Date of performing status | P93: The date on which the performing status as reported in “performing status of the instrument” is considered to have been established or changed. If the performing status is measured on debtor level the status will respectively apply to all instruments. | R93: 0000-00-00 | S93: 1111-11-11 | T93: Y | U93: 0
C94: 6.2. Fora âmbito | Campos em testes ou c/ incidências (LT - PM) | E94: INSTRUMENT | F94: DT_PRFRMNG_STTS_PRVS | G94: Y | H94: Y | I94: Y | J94: Y | K94: Y | L94: Y | M94: Y | N94: DATE | O94: Date of previous performing status | P94: The date on which the previous performing status as reported in “previous performing status of the instrument” is considered to have been established or changed within a maximum observation period of 48 month. If the performing status is measured on debtor level the status will respectively apply to all instruments. | R94: 0000-00-00 | S94: 1111-11-11 | T94: Y | U94: 0
C95: 6.1. Fora âmbito | Campos concluídos - Sem necessidade de espec. | E95: INSTRUMENT | F95: EXPSR_IN_SCP | G95: Corporation | H95: Corporation | I95: Corporation | J95: Corporation | K95: Corporation | L95: Corporation | M95: Corporation | N95: VARCHAR(5) | O95: Identification of exposure that is in scope of the on-site inspection | P95: For Residential Real Estate, Retail SME and/or Retail Other on-site missions please report "Y" or "N" for following condition: Residentia Real Estate on-site missions: Exposure flagged in FINREP, template F 18.00.a - Information on performing and non-performing exposures (I) as Households with loans collateralised by residential immovable property in row 160. For Retail other on-site missions: Exposure flagged in FINREP, template F 18.00.a - Information on performing and non-performing exposures (I) as Credit for consumption in row 170. for Retail SME on-site missions: Exposure flagged "Y" when it does not exceed EUR 1 mln and is managed as SME. For non-retail missions please indicate the row under which the exposure is reported in FINREP, template F18.00.a, e.g. Non-financial Corporations in row 120 and of which SME or CRE in row 130 or 140. | R95: MISS | S95: N/A | T95: Y | U95: 0
C96: 2.1. Re-especificação de campos complexos | Sindicados | E96: INSTRUMENT | F96: FLD_SYNDCTN | G96: N | H96: N | I96: N | J96: N | K96: Y | L96: Y | M96: N | N96: Y, N | O96: Failed syndication (as per definition according to the ECB Guidance on leveraged transactions) | P96: In accordance with "ECB Guidance on leveraged transactions". | R96: MISS | S96: N/A | T96: Y | U96: 0
C97: 6.3. Fora âmbito | Fonte Manual LF | E97: INSTRUMENT | F97: FLG_LBO | G97: N | H97: N | I97: N | J97: N | K97: Y | L97: Y | M97: N | N97: Y, N | O97: Flag for leverage buy-out transactions | P97: Flag for leverage buy-out transactions. | R97: MISS | S97: N/A | T97: Y | U97: 0
C98: 2.2 Re-especificação de campos complexos - Resto | E98: INSTRUMENT | F98: FRBRNC_STTS_INSTRMNT | G98: Y | H98: Y | I98: Y | J98: Y | K98: Y | L98: Y | M98: Y | N98: =HYPERLINK("#"&"CodeList!"&ADDRESS(2,MATCH($F98,CodeList!$2:$2,0)+1,),"Code List") -> Code List | O98: Forbearance status | P98: Identification of forborne and renegotiated instruments. | R98: 99999999999 | S98: Default value not allowed | T98: Y | U98: 0
C99: 6.2. Fora âmbito | Campos em testes ou c/ incidências (LT - PM) | E99: INSTRUMENT | F99: IMPRMNT_STTS | G99: Y | H99: Y | I99: Y | J99: Y | K99: Y | L99: Y | M99: Y | N99: =HYPERLINK("#"&"CodeList!"&ADDRESS(2,MATCH($F99,CodeList!$2:$2,0)+1,),"Code List") -> Code List | O99: Impairment status | P99: Type of impairment. | R99: 99999999999 | S99: 11111111111 | T99: Y | U99: 0
C100: 6.2. Fora âmbito | Campos em testes ou c/ incidências (LT - PM) | E100: INSTRUMENT | F100: IMPRMNT_STTS_PRVS | G100: Y | H100: Y | I100: Y | J100: Y | K100: Y | L100: Y | M100: Y | N100: =HYPERLINK("#"&"CodeList!"&ADDRESS(2,MATCH($F100,CodeList!$2:$2,0)+1,),"Code List") -> Code List | O100: Previous impairment status | P100: Type of impairment previous to the one at reference date. | R100: 99999999999 | S100: 11111111111 | T100: Y | U100: 0
C101: 3. Campos em testes ou c/ incidências | E101: INSTRUMENT | F101: INTRNL_RTNG | G101: Y | H101: Y | I101: Y | J101: Y | K101: Y | L101: Y | M101: Y | N101: =HYPERLINK("#"&"CodeList!"&ADDRESS(2,MATCH($F101,CodeList!$2:$2,0)+1,),"Code List") -> Code List | O101: Internal rating at reference date | P101: Internal rating grade at the reference date according to Regulation (EU) No 575/2013. Please also add in sheet "Code List" the list of values used for the bank-internal rating masterscale. If only the debtor is rated please report the debtor rating on all associated instruments. | R101: MISS | S101: N/A | T101: Y | U101: 0
C102: 3. Campos em testes ou c/ incidências | E102: INSTRUMENT | F102: INTRNL_RTNG_INCPTN | G102: Y | H102: Y | I102: Y | J102: Y | K102: Y | L102: Y | M102: Y | N102: =HYPERLINK("#"&"CodeList!"&ADDRESS(2,MATCH($F102,CodeList!$2:$2,0)+1,),"Code List") -> Code List | O102: Internal rating at inception | P102: Internal rating grade according to Regulation (EU) No 575/2013 at instrument origination. | R102: MISS | S102: N/A | T102: Y | U102: 0
C103: 6.1. Fora âmbito | Campos concluídos - Sem necessidade de espec. | E103: INSTRUMENT | F103: INTRNL_SGMNT | G103: Y | H103: Y | I103: Y | J103: Y | K103: Y | L103: Y | M103: Y | N103: VARCHAR2(255) | O103: Internal code for segment/portfolio | P103: Bank-internal portfolio-segmentation definition according to bank-internal nomenclature. | R103: MISS | S103: N/A | T103: Y | U103: 0
C104: 6.1. Fora âmbito | Campos concluídos - Sem necessidade de espec. | E104: INSTRUMENT | F104: INTRNL_UNT | G104: Y | H104: Y | I104: Y | J104: Y | K104: Y | L104: Y | M104: Y | N104: VARCHAR2(255) | O104: Internal code for business line/unit | P104: Internal classification of the bank of the instrument administrating business unit, e.g. if the loan has been transferred to the intensified loan management department it should be flagged as such. | R104: MISS | S104: N/A | T104: Y | U104: 0
C105: 6.2. Fora âmbito | Campos em testes ou c/ incidências (LT - PM) | E105: INSTRUMENT | F105: PRFRMNG_STTS | G105: Y | H105: Y | I105: Y | J105: Y | K105: Y | L105: Y | M105: Y | N105: =HYPERLINK("#"&"CodeList!"&ADDRESS(2,MATCH($F105,CodeList!$2:$2,0)+1,),"Code List") -> Code List | O105: Performing status | P105: The instrument is to be classified on the reference date under one of the following categories: performing or non-performing, in accordance with Implementing Regulation (EU) No 680/2014. If the performing status is measured on entity level only all instruments are to be classified according to the status on entity level. | R105: 99999999999 | S105: 11111111111 | T105: Y | U105: 0
C106: 6.2. Fora âmbito | Campos em testes ou c/ incidências (LT - PM) | E106: INSTRUMENT | F106: PRFRMNG_STTS_PRVS | G106: Y | H106: Y | I106: Y | J106: Y | K106: Y | L106: Y | M106: Y | N106: =HYPERLINK("#"&"CodeList!"&ADDRESS(2,MATCH($F106,CodeList!$2:$2,0)+1,),"Code List") -> Code List | O106: Previous performing status | P106: The instrument is to be classified differently from PRFRMNG_STTS within a maximum observation period of 48 months under one of the following categories: performing or non-performing, in accordance with Implementing Regulation (EU) No 680/2014. If the performing status is measured on entity level only all instruments are to be classified according to the status on entity level. If there is no status different from PRFMNG_STTS as at loan origination then this field is "not applicable". | R106: 99999999999 | S106: 11111111111 | T106: Y | U106: 0
C107: 6.1. Fora âmbito | Campos concluídos - Sem necessidade de espec. | E107: INSTRUMENT | F107: PRPS | G107: N | H107: Y | I107: Y | J107: Y | K107: Y | L107: Y | M107: Y | N107: =HYPERLINK("#"&"CodeList!"&ADDRESS(2,MATCH($F107,CodeList!$2:$2,0)+1,),"Code List") -> Code List | O107: Purpose | P107: Classification of instruments according to their purpose. | R107: 99999999999 | S107: 11111111111 | T107: Y | U107: 0
C108: 5. Campos com outras possíveis alterações - Dependente de decisões OSI | E108: INSTRUMENT | F108: PYMNT_INTRST_ONLY | G108: N | H108: Y | I108: Y | J108: Y | K108: Y | L108: Y | M108: Y | N108: Y, N | O108: Interest only repayment | P108: Report "Y" if the exposure is classified as interest only. | R108: MISS | S108: N/A | T108: Y | U108: 0
C109: 2.1. Re-especificação de campos complexos | Sindicados | E109: INSTRUMENT | F109: STTS_UNDRWRTTN_TRNSCTN | G109: N | H109: N | I109: N | J109: N | K109: Y | L109: Y | M109: N | N109: =HYPERLINK("#"&"CodeList!"&ADDRESS(2,MATCH($F109,CodeList!$2:$2,0)+1,),"Code List") -> Code List | O109: Status for underwritten transaction | P109: In accordance with "ECB Guidance on leveraged transactions". Data attribute to be provided only by Lead Arrangers. | R109: 99999999999 | S109: 11111111111 | T109: Y | U109: 0
C110: 2.1. Re-especificação de campos complexos | Sindicados | E110: INSTRUMENT | F110: TRNCH | G110: N | H110: N | I110: N | J110: N | K110: Y | L110: Y | M110: N | N110: =HYPERLINK("#"&"CodeList!"&ADDRESS(2,MATCH($F110,CodeList!$2:$2,0)+1,),"Code List") -> Code List | O110: Tranching / security | P110: Tranching / security. | R110: 99999999999 | S110: 11111111111 | T110: Y | U110: 0
...

Sheet CodeList
A1: Table | B1: INSTRUMENT | D1: INSTRUMENT / ENTITY | F1: INSTRUMENT / PROTECTION | H1: INSTRUMENT | J1: INSTRUMENT | L1: PROTECTION | N1: PROTECTION | P1: INSTRUMENT | R1: INSTRUMENT | T1: INSTRUMENT | V1: INSTRUMENT | X1: INSTRUMENT | Z1: INSTRUMENT | AB1: INSTRUMENT | AD1: INSTRUMENT | AF1: INSTRUMENT | AH1: INSTRUMENT | AJ1: INSTRUMENT | AL1: INSTRUMENT / ENTITY | AN1: INSTRUMENT / ENTITY | AP1: INSTRUMENT | AR1: INSTRUMENT | AT1: INSTRUMENT | AV1: INSTRUMENT | AX1: INSTRUMENT | AZ1: INSTRUMENT | BB1: INSTRUMENT | BD1: INSTRUMENT | BF1: INSTRUMENT | BH1: INSTRUMENT | BJ1: INSTRUMENT | BL1: INSTRUMENT | BN1: INSTRUMENT | BP1: INSTRUMENT | BR1: INSTRUMENT | BT1: ENTITY | BV1: PROTECTION | BX1: PROTECTION | BZ1: PROTECTION | CB1: PROTECTION | CD1: PROTECTION | CF1: PROTECTION | CH1: ENTITY | CJ1: ENTITY | CL1: ENTITY | CN1: ENTITY | CP1: ENTITY | CR1: ENTITY | CT1: ENTITY | CV1: ENTITY | CX1: ENTITY | CZ1: ENTITY | DB1: ENTITY | DD1: INSTRUMENT / ENTITY | DF1: INSTRUMENT | DH1: ENTITY | DJ1: INSTRUMENT / ENTITY | DL1: ENTITY | DN1: INSTRUMENT_C19 | DP1: INSTRUMENT_C19 | DR1: INSTRUMENT_C19 | DT1: INSTRUMENT_C19 | DV1: INSTRUMENT | DX1: INSTRUMENT | DZ1: INSTRUMENT | EB1: INSTRUMENT | ED1: INSTRUMENT | EF1: INSTRUMENT | EH1: INSTRUMENT | EJ1: INSTRUMENT | EL1: INSTRUMENT | EN1: INSTRUMENT | EP1: INSTRUMENT | ER1: INSTRUMENT | ET1: INSTRUMENT | EV1: INSTRUMENT | EX1: INSTRUMENT | EZ1: INSTRUMENT | FB1: INSTRUMENT | FD1: INSTRUMENT | FF1: INSTRUMENT | FH1: PROTECTION | FJ1: PROTECTION | FL1: PROTECTION | FN1: PROTECTION | FP1: ENTITY | FR1: INSTRUMENT | FT1: INSTRUMENT | FV1: INSTRUMENT | GC1: INSTRUMENT | GE1: INSTRUMENT | GG1: INSTRUMENT | GI1: INSTRUMENT | GK1: INSTRUMENT | GQ1: INSTRUMENT | GS1: PROTECTION | HA1: PROTECTION | HC1: PROTECTION | HE1: INSTRUMENT | HG1: ENTITY | HI1: INSTRUMENT | HK1: INSTRUMENT | HM1: INSTRUMENT | HO1: INSTRUMENT | HQ1: INSTRUMENT | HS1: INSTRUMENT | HU1: INSTRUMENT | HW1: INSTRUMENT | HY1: INSTRUMENT - PROTECTION
A2: Data field | B2: ACCNTNG_CLSSFCTN | D2: CHNNL_ORGNTN | F2: CRRNCY_DNMNTN | H2: CPN_CRRNCY | J2: VLTN_CRRNCY | L2: APPRSL_CRRNCY | N2: CRE_INCM_CRRNCY | P2: CVNNT_STTS | R2: CVNNT_TYP | T2: DFLT_STTS_INSTRMNT | V2: PRFRMNG_STTS | X2: PRFRMNG_STTS_PRVS | Z2: FRBRNC_STTS_INSTRMNT | AB2: IMPRMNT_STTS | AD2: IMPRMNT_STTS_PRVS | AF2: IMPRMNT_ASSSSMNT_MTHD | AH2: IMPRMNT_CLCLTN_MTHD | AJ2: INTRST_RT_RST_FRQNCY | AL2: LGL_PRCDNG_STTS | AN2: LGL_PRCDNG_STTS_LE | AP2: PRJCT_FNNC_LN | AR2: PRPS | AT2: PYMNT_FRQNCY | AV2: RCRS | AX2: RWA_MTHD | AZ2: SICR_ASSSSMNT_MTHD | BB2: STTS_UNDRWRTTN_TRNSCTN | BD2: SYNDCT_RL | BF2: SYNDCTN_TYP | BH2: TRNCH | BJ2: TYP_AMRTSTN | BL2: TYP_CRE_OPRTN | BN2: TYP_INSTRMNT | BP2: TYP_INTRST_RT | BR2: TYP_MRTGG | BT2: EXTRNL_RTNG / EXTRNL_RTNG_PRVS / ISSR_RTNG | BV2: CNSTRCTN_STTS | BX2: DVLPMNT_STTS | BZ2: MN_PRPS | CB2: PRTCTN_VLTN_APPRCH | CD2: TYP_PRTCTN | CF2: TYP_PRTCTN_VL | CH2: ACCNTNG_FRMWRK_SL | CJ2: CLLCTN_MD | CL2: CNTRY | CN2: RL_ESTT_CLLTRL_LCTN | CP2: CNTRY/RL_ESTT_CLLTRL_LCTN | CR2: DFLT_STTS | CT2: ECNMC_ACTVTY/GRP_ECNMC_ACTVTY/ISSR_NACE_SCTR/NACE_ESG | CV2: EMPLYMNT_STTS | CX2: ENTRPRS_SZ_LE | CZ2: PRFRMNG_STTS_LE | DB2: RTNG_MTHD | DD2: INTRNL_RTNG | DF2: INTRNL_RTNG_INCPTN | DH2: INTRNL_RTNG_PRVS | DJ2: RTNG_SCL | DL2: SNGL_PRPS_VHCL | DN2: EBA_CMPLNT_MRTR_ST_C19 | DP2: TYP_CMPLNT_MRTR_C19 | DR2: FRBRNC_STTS_C19 | DT2: SBJCT_PBLC_GRNT_SCHM_C19 | DV2: ISSR_ID_TYP | DX2: GRNTR_ID_TYP | DZ2: ISSR_CNTRY | EB2: ISSR_ESA_2010 | ED2: ISSR_RTNG | EF2: ISSR_TYP | EH2: VLTN_TYP | EJ2: INSTRMNT_CLSS | EL2: PRMRY_ASST_CLSSF | EN2: ASST_SCRT_CLSS | EP2: TYPE_OF_PLCMNT | ER2: INSTR_SNRTY_CLSS | ET2: SRCS_ENCMBRNC | EV2: LCR_BFFR_CTGRY | EX2: PRDNTL_PRTFL | EZ2: INTRNL_SGMNT_CAT_MSTA | FB2: INTRNL_SGMNT_CATGSUB | FD2: RSK_MTGTD_CCT | FF2: RSK_MTGTD_CCP | FH2: TYP_EP_SCR/TYP_EMSSNS_SCR | FJ2: EP_SCR | FL2: TYP_LBL/TYP_EMSSNS_LBL/TYP_EPC_LBL | FN2: EPC_LBL/EPC_EMSSNS_LBL | FP2: ESG_SBSCTR | FR2: BSNSS_AREA/BSNSS_AREA_DSTNTN/BSNN_AREA_CIB/BSNSS_AREA_CCRR | FT2: SSTNBL_CTGRY_TXNMY | FV2: SSTNBL_CTGRY | GC2: MNGMNT_PRDCT | GE2: ENVRNMNTL_OBJCTV | GG2: TYP_ACTVTY | GK2: LNS_CLLTRLZD_CLSSFCTN | GM2: INTRBSNSS_ADJ_COD | GO2: TYP_VHCL | GQ2: MTHD_USD_INSTRMNT_SCP_1 / MTHD_USD_INSTRMNT_SCP_2 / MTHD_USD_INSTRMNT_SCP_3 | GS2: MTHD_USD_PRTCTN_SCP_1 / MTHD_USD_PRTCTN_SCP_2 / MTHD_USD_PRTCTN_SCP_3 | GU2: RL_ESTT_CRTFCTN | GW2: DNSH_DTL | GY2: SSTNBL_INDCTR | HA2: TYP_HZRDS_INSRD | HC2: VHCL_EMSSNS_LBL | HE2: CNCLLD_INSTRMNT_STTS | HG2: PRSN_TYP | HI2: RFRNC_RT | HK2: TYP_SCRTZTN | HM2: TYP_OFF_BLNC_PRDCT | HO2: BLNC_SHT_RCGNTN | HQ2: EXCLDD_LF | HS2: US_PRCDS | HU2: TYP_FCLTY | HW2: TYP_CL | HY2: TYP_RLTN | IA2: RL_ESTT_CLMT_ZN | IC2: s | IE2: TYP_DL | IG2: DSTNTN_FNDS
DD3: The rating collected in local databases should be reported. | DF3: The rating collected in local databases should be reported. | DH3: The rating collected in local databases should be reported. | DJ3: to be populated by Corporation
A4: Code / Name | B4: ACCNTNG_CLSSFCTN_CD | C4: ACCNTNG_CLSSFCTN_NM | D4: CHNNL_ORGNTN_CD | E4: CHNNL_ORGNTN_NM | F4: CRRNCY_DNMNTN_CD | G4: CRRNCY_DNMNTN_NM | H4: CPN_CRRNCY_CD | I4: CPN_CRRNCY_NM | J4: VLTN_CRRNCY_CD | K4: VLTN_CRRNCY_NM | L4: APPRSL_CRRNCY_CD | M4: APPRSL_CRRNCY_NM | N4: CRE_INCM_CRRNCY_CD | O4: CRE_INCM_CRRNCY_NM | P4: CVNNT_STTS_CD | Q4: CVNNT_STTS_NM | R4: CVNNT_TYP_CD | S4: CVNNT_TYP_NM | T4: DFLT_STTS_INSTRMNT_CD | U4: DFLT_STTS_INSTRMNT_NM | V4: PRFRMNG_STTS_CD | W4: PRFRMNG_STTS_NM | X4: PRFRMNG_STTS_PRVS_CD | Y4: PRFRMNG_STTS_PRVS_NM | Z4: FRBRNC_STTS_CD | AA4: FRBRNC_STTS_NM | AB4: IMPRMNT_STTS_CD | AC4: IMPRMNT_STTS_NM | AD4: IMPRMNT_STTS_PRVS_CD | AE4: IMPRMNT_STTS_PRVS_NM | AF4: IMPRMNT_ASSSSMNT_MTHD_CD | AG4: IMPRMNT_ASSSSMNT_MTHD_NM | AH4: IMPRMNT_CLCLTN_MTHD_CD | AI4: IMPRMNT_CLCLTN_MTHD_NM | AJ4: INTRST_RT_RST_FRQNCY_CD | AK4: INTRST_RT_RST_FRQNCY_NM | AL4: LGL_PRCDNG_STTS_CD | AM4: LGL_PRCDNG_STTS_NM | AN4: LGL_PRCDNG_STTS_LE_CD | AO4: LGL_PRCDNG_STTS_LE_NM | AP4: PRJCT_FNNC_LN_CD | AQ4: PRJCT_FNNC_LN_NM | AR4: PRPS_CD | AS4: PRPS_NM | AT4: PYMNT_FRQNCY_CD | AU4: PYMNT_FRQNCY_NM | AV4: RCRS_CD | AW4: RCRS_NM | AX4: RWA_MTHD_CD | AY4: RWA_MTHD_ID | AZ4: SICR_ASSSSMNT_MTHD_CD | BA4: SICR_ASSSSMNT_MTHD_NM | BB4: STTS_UNDRWRTTN_TRNSCTN_CD | BC4: STTS_UNDRWRTTN_TRNSCTN_ID | BD4: SYNDCT_RL_CD | BE4: SYNDCT_RL_ID | BF4: SYNDCTN_TYP_CD | BG4: SYNDCTN_TYP_ID | BH4: TRNCH_CD | BI4: TRNCH_ID | BJ4: TYP_AMRTSTN_CD | BK4: TYP_AMRTSTN_NM | BL4: TYP_CRE_OPRTN_CD | BM4: TYP_CRE_OPRTN_NM | BN4: TYP_INSTRMNT_CD | BO4: TYP_INSTRMNT_NM | BP4: TYP_INTRST_RT_CD | BQ4: TYP_INTRST_RT_NM | BR4: TYP_MRTGG_CD | BS4: TYP_MRTGG_ID | BT4: EXTRNL_RTNG_CD | BU4: EXTRNL_RTNG_ID | BV4: CNSTRCTN_STTS_CD | BW4: CNSTRCTN_STTS_NM | BX4: DVLPMNT_STTS_CD | BY4: DVLPMNT_STTS_ID | BZ4: MN_PRPS_CD | CA4: MN_PRPS_ID | CB4: PRTCTN_VLTN_APPRCH_CD | CC4: PRTCTN_VLTN_APPRCH_NM | CD4: TYP_PRTCTN_CD | CE4: TYP_PRTCTN_NM | CF4: TYP_PRTCTN_VL_CD | CG4: TYP_PRTCTN_VL_NM | CH4: ACCNTNG_FRMWRK_CD | CI4: ACCNTNG_FRMWRK_NM | CJ4: CLLCTN_MD_CD | CK4: CLLCTN_MD_NM | CL4: CNTRY_CD | CM4: CNTRY_ID | CN4: RL_ESTT_CLLTRL_LCTN_CD | CO4: RL_ESTT_CLLTRL_LCTN_ID | CP4: CNTRY_CD | CQ4: CNTRY_ID | CR4: DFLT_STTS_CD | CS4: DFLT_STTS_ID | CT4: ECNMC_ACTVTY_CD | CU4: ECNMC_ACTVTY_NM | CV4: EMPLYMNT_STTS_CD | CW4: EMPLYMNT_STTS_ID | CX4: ENTRPRS_SZ_LE_CD | CY4: ENTRPRS_SZ_LE_ID | CZ4: PRFRMNG_STTS_LE_CD | DA4: PRFRMNG_STTS_LE_ID | DB4: RTNG_MTHD_CD | DC4: RTNG_MTHD_NM | DD4: INTRNL_RTNG | DE4: PD | DF4: INTRNL_RTNG_INCPTN | DG4: PD | DH4: INTRNL_RTNG_PRVS | DI4: PD | DJ4: RTNG_SCL_CD | DK4: RTNG_SCL_NM | DL4: SNGL_PRPS_VHCL_CD | DM4: SNGL_PRPS_VHCL_NM | DN4: EBA_CMPLNT_MRTR_ST_C19_CD | DO4: EBA_CMPLNT_MRTR_ST_C19_NM | DP4: TP_CMPLNT_MRTR_C19_CD | DQ4: TP_CMPLNT_MRTR_C19_NM | DR4: FRBRNC_STTS_C19_CD | DS4: FRBRNC_STTS_C19_NM | DT4: SBJCT_PBLC_GRNT_SCHM_C19_CD | DU4: SBJCT_PBLC_GRNT_SCHM_C19_NM | DV4: ISSR_ID_TYP_CD | DW4: ISSR_ID_TYP_NM | DX4: IGRNTR_ID_TYP_CD | DY4: IGRNTR_ID_TYP_NM | DZ4: ISSR_CNTRY_CD | EA4: ISSR_CNTRY_NM | EB4: ISSR_ESA_2010_CD | EC4: ISSR_ESA_2010_NM | ED4: ISSR_RTNG_CD | EE4: ISSR_RTNG_ID | EF4: ISSR_TYP_CD | EG4: ISSR_TYP_ID | EH4: VLTN_TYP_CD | EI4: VLTN_TYP_ID | EJ4: INSTRMNT_CLSS_CD | EK4: INSTRMNT_CLSS_ID | EL4: PRMRY_ASST_CLSSF_CD | EM4: PRMRY_ASST_CLSSF_ID | EN4: ASST_SCRT_CLSS_CD | EO4: ASST_SCRT_CLSS_ID | EP4: TYPE_OF_PLCMNT_CD | EQ4: TYPE_OF_PLCMNT_ID | ER4: INSTR_SNRTY_CLSS_CD | ES4: INSTR_SNRTY_CLSS_ID | ET4: SRCS_ENCMBRNC_CD | EU4: SRCS_ENCMBRNC_NM | EV4: LCR_BFFR_CTGRY_CD | EW4: LCR_BFFR_CTGRY_NM | EX4: PRDNTL_PRTFL_CD | EY4: PRDNTL_PRTFL_NM | EZ4: INTRNL_SGMNT_CAT_MSTA_CD | FA4: INTRNL_SGMNT_CAT_MSTA_NM | FB4: INTRNL_SGMNT_CATGSUB_CD | FC4: INTRNL_SGMNT_CATGSUB_NM | FD4: RSK_MTGTD_CCT_CD | FE4: RSK_MTGTD_CCT_NM | FF4: RSK_MTGTD_CCP_CD | FG4: RSK_MTGTD_CCP_NM | FH4: TYP_EP_SCR_CD | FI4: TYP_EP_SCR_NM | FJ4: EP_SCR_CD | FK4: EP_SCR_NM | FL4: TYP_LBL_CD | FM4: TYP_LBL_NM | FN4: EPC_LBL_CD | FO4: EPC_LBL_NM | FP4: ESG_SBSCTR_CD | FQ4: ESG_SBSCTR_NM | FR4: BSNSS_AREA_CD | FS4: BSNSS_AREA_NM | FT4: SSTNBL_CTGRY_TXNMY_CD | FU4: SSTNBL_CTGRY_TXNMY_NM | FV4: SSTNBL_CTGRY_CD | FX4: SSTNBL_CTGRY_NM | GC4: MNGMNT_PRDCT_CD | GD4: MNGMNT_PRDCT_NM | GE4: ENVRNMNTL_OBJCTV_CD | GF4: ENVRNMNTL_OBJCTV_NM | GG4: TYP_ACTVTY_CD | GH4: TYP_ACTVTY_NM | GK4: LNS_CLLTRLZD_CLSSFCTN_CD | GL4: LNS_CLLTRLZD_CLSSFCTN_NM | GM4: INTRBSNSS_ADJ_COD_CD | GN4: INTRBSNSS_ADJ_COD_NM | GO4: TYP_VHCL_CD | GP4: TYP_VHCL_NM | GQ4: MTHD_USD_INSTRMNT_SCP_1_CD | GR4: MTHD_USD_INSTRMNT_SCP_1_NM | GS4: MTHD_USD_PRTCTN_SCP_1 _CD | GT4: MTHD_USD_PRTCTN_SCP_1 _NM | GU4: RL_STT_CRTFCTN_CD | GV4: RL_STT_CRTFCTN _NM | GW4: DNSH_DTL_CD | GX4: DNSH_DTL_NM | GY4: SSTNBL_INDCTR_CD | GZ4: SSTNBL_INDCTR_NM | HA4: TYP_HZRDS_INSRD_CD | HB4: TYP_HZRDS_INSRD_NM | HC4: VHCL_EMSSNS_LBL_CD | HD4: VHCL_EMSSNS_LBL_NM | HE4: CNCLLD_INSTRMNT_STTS_CD | HF4: CNCLLD_INSTRMNT_STTS_NM | HG4: PRSN_TYP_CD | HH4: PRSN_TYP_NM | HI4: RFRNC_RT_CD | HJ4: RFRNC_RT_NM | HK4: TYP_SCRTZTN_CD | HL4: TYP_SCRTZTN_NM | HM4: TYP_OFF_BLNC_PRDCT_CD | HN4: TYP_OFF_BLNC_PRDCT_NM | HO4: BLNC_SHT_RCGNTN_CD | HP4: BLNC_SHT_RCGNTN_NM | HQ4: EXCLDD_LF_CD | HR4: EXCLDD_LF_NM | HS4: US_PRCDS_CD | HT4: US_PRCDS_NM | HU4: FCLTY_TYP_CD | HV4: FCLTY_TYP_NM | HW4: CL_TYP_CD | HX4: FCLTY_TYP_NM | HY4: TYP_RLTN_CD | HZ4: TYP_RLTN_NM | IA4: CLMTC_ZN_CD | IB4: CLMTC_ZN_NM | IC4: SCAN_CD | ID4: SCAN_NM | IE4: TYP_DL_CD | IF4: TYP_DL_NM | IG4: DSTNTN_FNDS_CD | IH4: DSTNTN_FNDS_NM
B5: Code | C5: Description | D5: Code | E5: Description | F5: Code | G5: Description | H5: Code | I5: Description | J5: Code | K5: Description | L5: Code | M5: Description | N5: Code | O5: Description | P5: Code | Q5: Description | R5: Code | S5: Description | T5: Code | U5: Description | V5: Code | W5: Description | X5: Code | Y5: Description | Z5: Code | AA5: Description | AB5: Code | AC5: Description | AD5: Code | AE5: Description | AF5: Code | AG5: Description | AH5: Code | AI5: Description | AJ5: Code | AK5: Description | AL5: Code | AM5: Description | AN5: Code | AO5: Description | AP5: Code | AQ5: Description | AR5: Code | AS5: Description | AT5: Code | AU5: Description | AV5: Code | AW5: Description | AX5: Code | AY5: Description | AZ5: Code | BA5: Description | BB5: Code | BC5: Description | BD5: Code | BE5: Description | BF5: Code | BG5: Description | BH5: Code | BI5: Description | BJ5: Code | BK5: Description | BL5: Code | BM5: Description | BN5: Code | BO5: Description | BP5: Code | BQ5: Description | BR5: Code | BS5: Description | BT5: Code | BU5: Description | BV5: Code | BW5: Description | BX5: Code | BY5: Description | BZ5: Code | CA5: Description | CB5: Code | CC5: Description | CD5: Code | CE5: Description | CF5: Code | CG5: Description | CH5: Code | CI5: Description | CJ5: Code | CK5: Description | CL5: Code | CM5: Description | CN5: Code | CO5: Description | CP5: Code | CQ5: Description | CR5: Code | CS5: Description | CT5: Code | CU5: Description | CV5: Code | CW5: Description | CX5: Code | CY5: Description | CZ5: Code | DA5: Description | DB5: Code | DC5: Description | DD5: Code | DE5: Description | DF5: Code | DG5: Description | DH5: Code | DI5: Description | DJ5: Code | DK5: Description | DL5: Code | DM5: Description | DN5: Code | DO5: Description | DP5: Code | DQ5: Description | DR5: Code | DS5: Description | DT5: Code | DU5: Description | DV5: Code | DW5: Description | DX5: Code | DY5: Description | DZ5: Code | EA5: Description | EB5: Code | EC5: Description | ED5: Code | EE5: Description | EF5: Code | EG5: Description | EH5: Code | EI5: Description | EJ5: Code | EK5: Description | EL5: Code | EM5: Description | EN5: Code | EO5: Description | EP5: Code | EQ5: Description | ER5: Code | ES5: Description | ET5: Code | EU5: Description | EV5: Code | EW5: Description | EX5: Code | EY5: Description | EZ5: Code | FA5: Description | FB5: Code | FC5: Description | FD5: Code | FE5: Description | FF5: Code | FG5: Description | FH5: Code | FI5: Description | FJ5: Code | FK5: Description | FL5: Code | FM5: Description | FN5: Code | FO5: Description | FP5: Code | FQ5: Description | FR5: Code | FS5: Description | FT5: Code | FU5: Description | FV5: Code | FW5: Description | GC5: Code | GD5: Description | GE5: Code | GF5: Description | GG5: Code | GH5: Description | GK5: Code | GL5: Description | GM5: Code | GN5: Description | GO5: Code | GP5: Description | GQ5: Code | GR5: Description | GS5: Code | GT5: Description | GU5: Code | GV5: Description | GW5: Code | GX5: Description | GY5: Code | GZ5: Description | HA5: Code | HB5: Description | HC5: Code | HD5: Description | HE5: Code | HF5: Description | HG5: Code | HH5: Description | HI5: Code | HJ5: Description | HK5: Code | HL5: Description | HM5: Code | HN5: Description | HO5: Code | HP5: Description | HQ5: Code | HR5: Description | HS5: Code | HT5: Description | HU5: Code | HV5: Description | HW5: Code | HX5: Description | HY5: Code | HZ5: Description | IA5: Code | IB5: Description | IC5: Code | ID5: Description | IE5: Code | IF5: Description | IG5: Code | IH5: Description
B6: 2 | C6: IFRS: Financial assets held for trading | D6: 1 | E6: Branch | F6: AED | G6: UAE Dirham | H6: AED | I6: UAE Dirham | J6: AED | K6: UAE Dirham | L6: AED | M6: UAE Dirham | N6: AED | O6: UAE Dirham | P6: 1 | Q6: No financial covenant to check | R6: 1 | S6: Full Covenant | T6: 14 | U6: Not in default | V6: 1 | W6: Non-performing | X6: 1 | Y6: Non-performing | Z6: 3 | AA6: Forborne: Refinanced debt | AB6: 21 | AC6: General allowances (GAAP) | AD6: 21 | AE6: General allowances (GAAP) | AF6: 1 | AG6: Collectively assessed | AH6: 1 | AI6: Specific. Going concern | AJ6: 1 | AK6: Annual | AL6: 1 | AM6: No legal actions taken | AN6: 1 | AO6: No legal actions taken | AP6: 1 | AQ6: Project finance loan | AR6: 4 | AS6: Margin lending | AT6: 1 | AU6: Annual | AV6: 1 | AW6: Recourse | AX6: 1 | AY6: IRB | AZ6: 1 | BA6: Collective approach | BB6: 1 | BC6: Underwritten or warehoused but not yet syndicated | BD6: 1 | BE6: Lead_arranger | BF6: 1 | BG6: Club_deal | BH6: 1 | BI6: Super-Senior | BJ6: 1 | BK6: French | BL6: 1 | BM6: Property development financing | BN6: 20 | BO6: Overdrafts | BP6: 1 | BQ6: Fixed | BR6: 1 | BS6: First rank fully registered mortgage | BT6: 1 | BU6: Aaa, AAA | BV6: 1 | BW6: Built | BX6: 1 | BY6: Not in construction | BZ6: 1 | CA6: Office | CB6: 1 | CC6: Counterparty estimation | CD6: 2 | CE6: Life insurance policies pledged | CF6: 1 | CG6: Fair value | CH6: 1 | CI6: National GAAP not consistent with IFRS | CJ6: 1 | CK6: Hard collection (judicial procedures engaged) | CL6: __ | CM6: Not assigned yet | CN6: __ | CO6: Not assigned yet | CP6: __ | CQ6: Not assigned yet | CR6: 14 | CS6: Not in default | CT6: A | CU6: Agriculture, forestry and fishing | CV6: 1 | CW6: Employed | CX6: 1 | CY6: Large enterprise | CZ6: 1 | DA6: Non-performing | DB6: 10 | DC6: Rating - Grandes empresas | DL6: 1 | DM6: SPV with recourse | DN6: 1 | DO6: Requested | DP6: 1 | DQ6: Legislative | DR6: 1 | DS6: Requested | DT6: 1 | DU6: Requested | DV6: BIC | DW6: BIC code | DX6: BIC | DY6: BIC code | DZ6: 1C | EA6: IMF (International Monetary Fund) | EB6: S_11 | EC6: Non-financial corporations | ED6: NR | EE6: Not rated | EF6: 1 | EG6: Other group entity | EH6: 1 | EI6: Mark-to-market | EJ6: F_31 | EK6: Short-term debt securities | EL6: D | EM6: Debt - Debt securities are negotiable financial instruments serving as evidence of a debt. They are covered by the financial assets and liabilities (financial instrument) category “debt securities” (F.3) in ESA 2010. | EN6: 1000 | EO6: Securitisation - Securitisation is the issuance of debt securities for which coupon or principal payments are backed by specified assets or by future income streams. | EP6: 1 | EQ6: Public | ES6: Guarantee level | ET6: 1 | EU6: SRCS_ENCMBRNC_NM | EV6: 1 | EW6: L1 | EX6: 1 | EY6: Trading book | EZ6: 1 | FA6: STD - Regional governments or local authorities | FB6: 1 | FC6: Covered Bonds | FD6: RMCT1 | FE6: Policy and legal risk | FF6: RMCP1 | FG6: Chronic | FH6: EPSD1 | FI6: Real | FJ6: EPSC1 | FK6: 0; <= 100 | FL6: EPCD1 | FM6: Real | FN6: EPCL1 | FO6: A | FP6: ESGS1 | FQ6: Local Governments | FR6: BA1 | FS6: Private Banking | FU6: Non financial corporations | FW6: DEDICATED PURPOSE | FX6: Green | GD6: On Balance (excluding HfT) | GE6: 22 | GF6: Climate change mitigation | GG6: 02 | GH6: Transitional activity | GK6: FMC1 | GL6: Real estate. Commercial | GM6: 99569 | GN6: Vendor Activity Chile | GO6: VEH01 | GP6: M1 - Vehicles used for the carriage of passengers and comprising not more than eight seats in addition to the driver's seat | GR6: Corporate Funding | GT6: Motor vehicle loans | GU6: ESTT01 | GV6: HQE SB v4. Certification | GW6: DNSH01 | GX6: DNSH1 - Do not significant harm to climate change mitigation objective | GY6: SSTNBL1 | GZ6: Santander Specific | HA6: HZRDS01 | HB6: Cyclone | HC6: VHCL1 | HD6: *codelist to be completed by the Unit based on the local vehicle emissions label codification | HE6: C | HF6: Cancelled | HG6: N | HH6: Natural person | HI6: ESTR-OVERNIGHT | HJ6: ESTR-OVERNIGHT | HK6: SEC01 | HL6: Traditional securitization | HM6: MC41 | HN6: Financial guarantees given | HO6: REC01 | HP6: Entirely recognised | HQ6: EXC01 | HR6: Collective investment undertaking | HS6: USP01 | HT6: LBO/M&A (exclusive purchase financing) | HU6: FCL01 | HV6: Revolving credit Facilities (RCF) | HW6: CLO01 | HX6: Direct holding of CLO | HY6: REL01 | HZ6: The guarantee is the financed asset | IA6: CLM01 | IB6: Climatic Zone α | IC6: SCN01 | ID6: Do not serve | IE6: DEL01 | IF6: Syndicated loan (includes underwritten, best effort, club deals and other syndicated loans) | IG6: DST01 | IH6: New money new customer
B7: 3 | C7: nGAAP: Trading Financial assets | D7: 2 | E7: Internet | F7: AFN | G7: Afghani | H7: AFN | I7: Afghani | J7: AFN | K7: Afghani | L7: AFN | M7: Afghani | N7: AFN | O7: Afghani | P7: 2 | Q7: In line with all financial covenants | R7: 2 | S7: Covenant loose | T7: 18 | U7: Default because both unlikely to pay and more than 90/180 days past due | V7: 11 | W7: Performing | X7: 11 | Y7: Performing | Z7: 4 | AA7: Forborne: instruments with modified interest rate below market conditions | AB7: 23 | AC7: Stage 1 (IFRS) | AD7: 23 | AE7: Stage 1 (IFRS) | AF7: 2 | AG7: Individually assessed | AH7: 2 | AI7: Specific. Gone concern | AJ7: 3 | AK7: At creditor discretion | AL7: 2 | AM7: Under judicial administration, receivership or similar measures | AN7: 2 | AO7: Under judicial administration, receivership or similar measures | AP7: 2 | AQ7: Non-project finance loan | AR7: 5 | AS7: Debt financing | AT7: 4 | AU7: Bullet | AV7: 2 | AW7: No recourse | AX7: 2 | AY7: STANDARD | AZ7: 2 | BA7: Individial approach | BB7: 2 | BC7: Syndicated or sold but not yet settled and transferred to investors | BD7: 2 | BE7: Participant | BF7: 2 | BG7: Underwriting | BH7: 2 | BI7: Senior/First Lien | BJ7: 2 | BK7: German | BL7: 2 | BM7: Property investment financing | BN7: 51 | BO7: Credit card debt | BP7: 2 | BQ7: Variable | BR7: 2 | BS7: Subordinated rank fully registered mortgage | BT7: 2 | BU7: Aa1, AA+ | BV7: 2 | BW7: In construction | BX7: 2 | BY7: In construction and not operational | BZ7: 2 | CA7: Hotel | CB7: 2 | CC7: Creditor valuation | CD7: 3 | CE7: Other physical collaterals | CF7: 2 | CG7: Long-term sustainable value | CH7: 2 | CI7: IFRS | CJ7: 2 | CK7: Soft collection (all other) | CL7: AD | CM7: Andorra | CN7: AD | CO7: Andorra | CP7: AD | CQ7: Andorra | CR7: 18 | CS7: Default because both unlikely to pay and more than 90/180 days past due | CT7: 1 | CU7: Crop and animal production, hunting and related service activities | CV7: 2 | CW7: Employed with partial support (company subsidy) | CX7: 2 | CY7: Medium enterprise | CZ7: 11 | DA7: Performing | DB7: 11 | DC7: Rating - Corporativa | DL7: 2 | DM7: SPV without recourse | DN7: 2 | DO7: Granted | DP7: 2 | DQ7: Non-Legislative | DR7: 2 | DS7: Granted | DT7: 2 | DU7: Covered | DV7: IPF | DW7: Investment/Pension fund identifier | DX7: IPF | DY7: Investment/Pension fund identifier | DZ7: 1D | EA7: WTO (World Trade Organisation) | EB7: S_11001 | EC7: Non-financial corporations - public | ED7: 1 | EE7: Aaa, AAA | EF7: 2 | EG7: Third party | EH7: 2 | EI7: Mark-to-model | EJ7: F_32 | EK7: Long-term debt securities | EL7: D.1 | EM7: Bond - Bonds and debentures are long-term debt securities that give the holders the unconditional right to fixed payments or contractually determined variable payments on a specified date or dates, that is, the earning of interest is not dependent on earnings of the debtors. Bonds and debentures also give holders the unconditional right to fixed sums as payments to the creditor on a specified date or dates. | EN7: 1100 | EO7: Asset-backed security (ABS) - A bond, created through securitisation, whose coupon payments and principal repayments are dependent on a pool of assets, either purchased in the secondary market or from the balance sheet of an original asset owner; excluding mortgages. | EP7: 2 | EQ7: Private | ER7: 1XX | ES7: Unguaranteed - In case of unguaranteed securities, there are no obligations to guarantors to make payments to the holder of the security if the issuer fails to meet the obligation to make repayments arising under the instrument secured by the guarantor. | ET7: 5 | EU7: Central bank funding - Central bank funding (of all types, including repos), in accordance with the European Banking Authority’s (EBA) implementing technical standards on asset encumbrance reporting as referred to in Article 99(5) and Article 100 of Regulation (EU) No 575/2013. | EV7: 2 | EW7: L2A | EX7: 2 | EY7: Non-trading book | EZ7: 2 | FA7: STD - Public sector entities | FB7: 4 | FC7: Exposures secured by mortgages on immovable property | FD7: RMCT2 | FE7: Technology risk | FF7: RMCP2 | FG7: Acute | FH7: EPSD2 | FI7: Estimated | FJ7: EPSC2 | FK7: > 100; <= 200 | FL7: EPCD2 | FM7: Estimated | FN7: EPCL2 | FO7: B | FP7: ESGS2 | FQ7: Sovereigns | FR7: BA2 | FS7: Individuals | FT7: SCATX01 | FU7: Non financial corporations - General purpose | FY7: Energy | GD7: Loans & advances (customers and credit institutions) | GE7: 23 | GF7: Climate change adaptation | GG7: 05 | GH7: Pure Activity | GK7: FMC2 | GL7: Real estate. Residential | GM7: 99505 | GN7: Distribution BdI to Commercial (Eng) | GO7: VEH02 | GP7: M2 - Vehicles used for the carriage of passengers, comprising more than eight seats in addition to the driver's seat, and having a maximum mass not exceeding 5 tonnes | GR7: Reported emissions | GT7: Actual vehicle - specific emissions | GU7: ESTT02 | GV7: Net Zero Energy Building CertificationTM (NZEB) | GW7: DNSH02 | GX7: DNSH2 - Do not significant harm to climate change adaptation | GY7: SSTNBL2 | GZ7: Taxonomy Specific | HA7: HZRDS02 | HB7: Winter storm | HC7: VHCL1 | HE7: M | HF7: Intramonth cancelled instrument | HG7: L | HH7: Legal person | HI7: TERM ESTR-1W | HJ7: TERM ESTR-1W | HK7: SEC02 | HL7: Synthetic securitization | HM7: MC42 | HN7: Loan commitments given | HO7: REC02 | HP7: Recognised to the extent of the institution’s continuing involvement | HQ7: EXC02 | HR7: Securitisations | HS7: USP02 | HT7: Refinancing | HU7: FCL02 | HV7: Bullet term loans | HW7: CLO02 | HX7: CLO warehousing first lien | HY7: REL02 | HZ7: The guarantee is not the financed asset | IA7: CLM02 | IB7: Climatic Zone A | IC7: SCN02 | ID7: Specialised | IE7: DEL02 | IF7: Bilateral loan | IG7: DST02 | IH7: New money existing customer
B8: 4 | C8: IFRS: Financial assets designated at fair value through profit or loss | D8: 3 | E8: Broker | F8: ALL | G8: Lek | H8: ALL | I8: Lek | J8: ALL | K8: Lek | L8: ALL | M8: Lek | N8: ALL | O8: Lek | P8: 3 | Q8: In breach with at least one non-material financial covenant | R8: 3 | S8: Covenant light | T8: 19 | U8: Default because unlikely to pay | Z8: 5 | AA8: Forborne: instruments with other modified terms and conditions | AB8: 24 | AC8: Stage 2 (IFRS) | AD8: 24 | AE8: Stage 2 (IFRS) | AH8: 3 | AI8: Specific. Other | AJ8: 8 | AK8: Monthly | AL8: 3 | AM8: Bankruptcy / insolvency | AN8: 3 | AO8: Bankruptcy / insolvency | AR8: 6 | AS8: Imports | AT8: 8 | AU8: Monthly | BB8: 3 | BC8: Final retained hold exposure (incl undrawn RCF) | BD8: 3 | BE8: Other | BF8: 3 | BG8: Best_effort | BH8: 3 | BI8: Subordinated/Second and Third Lien | BJ8: 3 | BK8: Fixed amortisation schedule | BN8: 71 | BO8: Trade receivables | BP8: 3 | BQ8: Mixed | BR8: 3 | BS8: Partly registered mortgage with registered mandate to register the remainder | BT8: 3 | BU8: Aa2, AA | BV8: 3 | BW8: Land bank without zoning permit | BX8: 3 | BY8: In construction and partially operational | BZ8: 3 | CA8: Shopping | CB8: 3 | CC8: Mark-to-market | CD8: 4 | CE8: Credit derivatives | CF8: 3 | CG8: Market value | CH8: 3 | CI8: National GAAP consistent with IFRS | CL8: AE | CM8: United Arab Emirates (the) | CN8: AE | CO8: United Arab Emirates (the) | CP8: AE | CQ8: United Arab Emirates (the) | CR8: 19 | CS8: Default because unlikely to pay | CT8: 1.1 | CU8: Growing of non-perennial crops | CV8: 3 | CW8: Protected life-time employment (civil servant) | CX8: 3 | CY8: Small enterprise | DB8: 12 | DC8: Rating - Promotores Inmobiliarios | DL8: 3 | DM8: Other type of entity | DN8: 3 | DO8: Extended | DR8: 3 | DS8: Extended | DT8: 3 | DU8: Covered_called | DV8: LEI | DW8: Legal Entity Identifier | DX8: LEI | DY8: Legal Entity Identifier | DZ8: 1E | EA8: IBRD (International Bank for Reconstruction and Development) | EB8: S_11002 | EC8: Non-financial corporations - national private | ED8: 2 | EE8: Aa1, AA+ | EL8: D.11 | EM8: Straight bond - A bond without any further special characteristics listed separately. | EN8: 1101 | EO8: Auto loans ABS - Detailed asset type breakdown of ABSs mainly in accordance with definitions of European and American Securitisation Forum. | ER8: 2XX | ES8: Government / Treasury guarantee - A guarantee is provided by the government / treasury that would oblige the guarantor to make payments to the holder of the security if the issuer fails to meet the obligation to make repayments arising under the instrument secured by the guarantor. | ET8: 6 | EU8: Exchange traded derivatives - Exchange traded derivatives in accordance with the EBA’s implementing technical standards on asset encumbrance reporting as referred to in Article 99(5) and Article 100 of Regulation (EU) No 575/2013. | EV8: 3 | EW8: L2B | EZ8: 3 | FA8: STD - Multilateral Development Banks | FB8: 5 | FC8: Commercial mortgages | FD8: RMCT3 | FE8: Reputational risk | FF8: RMCP3 | FG8: Non mitigated | FJ8: EPSC3 | FK8: > 200; <= 300 | FN8: EPCL3 | FO8: C | FP8: ESGS3 | FQ8: Investment firms | FR8: BA3 | FS8: Companies | FU8: Non financial corporations - Specific purpose | FZ8: Renewable energy | GC8: PRDCT010101 | GD8: Mortgages | GE8: 24 | GF8: Sustainable use and protection of water and marine resources | GG8: 01 | GH8: Enabling activity | GK8: FMC3 | GL8: Other real collateral | GM8: 99006 | GN8: Sales Activity Portugal | GO8: VEH03 | GP8: M3 - Vehicles used for the carriage of passengers, comprising more than eight seats in addition to the driver's seat, and having a maximum mass exceeding 5 tonnes | GQ8: IM01 | GR8: Audited emissions of the counterparty | GS8: PM01 | GT8: Based on fuel consumption | GU8: ESTT03 | GV8: Low-Carbon Buildings Climate Bond Initiative (CBI) Certification | GW8: DNSH03 | GX8: DNSH3 - Do not significant harm to sustainable use and protection of water and marine resources | GY8: SSTNBL3 | GZ8: Santander Specific & Taxonomy Specific | HA8: HZRDS03 | HB8: Hail | HC8: VHCL1 | HE8: I | HF8: Intermittent instrument | HI8: TERM ESTR-1M | HJ8: TERM ESTR-1M | HK8: SEC03 | HL8: Not securitized | HM8: MC4301 | HN8: Non-financial guarantees given (Other commitments given) | HO8: REC03 | HP8: Entirely derecognized | HQ8: EXC03 | HR8: Credit derivatives | HS8: USP03 | HT8: Recapitalization | HU8: FCL03 | HV8: Amortising term loans | HW8: CLO03 | HX8: CLO warehousing not first lien | HY8: REL03 | HZ8: The financed asset is not the instrument’s guarantee | IA8: CLM03 | IB8: Climatic Zone B | IC8: SCN03 | ID8: Intensive | IE8: DEL03 | IF8: Primary Market Purchases | IG8: DST03 | IH8: Existing money
B9: 5 | C9: nGAAP: Available-for-sale financial assets | D9: 4 | E9: Other | F9: AMD | G9: Armenian Dram | H9: AMD | I9: Armenian Dram | J9: AMD | K9: Armenian Dram | L9: AMD | M9: Armenian Dram | N9: AMD | O9: Armenian Dram | P9: 4 | Q9: In breach with at least one material financial covenant | R9: 4 | S9: No covenant | T9: 20 | U9: Default because more than 90/180 days past due | Z9: 8 | AA9: Not forborne or renegotiated | AB9: 25 | AC9: Stage 3 (IFRS) | AD9: 25 | AE9: Stage 3 (IFRS) | AH9: 4 | AI9: Mixed approaches | AJ9: 12 | AK9: Other than overnight, monthly, quarterly, half yearly, annually or at creditor discretion | AL9: 4 | AM9: Other legal measures | AN9: 4 | AO9: Other legal measures | AR9: 7 | AS9: Exports | AT9: 15 | AU9: Other than monthly, quarterly, half yearly, annually, bullet or zero coupon | BB9: 4 | BC9: Distributed and fully transferred to other lenders/investors | BF9: 4 | BG9: Other | BH9: 4 | BI9: Unsecured (senior or below) | BJ9: 4 | BK9: Bullet | BN9: 80 | BO9: Finance leases | BR9: 4 | BS9: Conditional mortgage | BT9: 4 | BU9: Aa3, AA- | BV9: 4 | BW9: Land bank building permit | BX9: 4 | BY9: Constructed and fully operational | BZ9: 4 | CA9: Leisure | CB9: 4 | CC9: Other type of valuation | CD9: 5 | CE9: Financial guarantees other than credit derivatives | CF9: 4 | CG9: Notional amount | CL9: AF | CM9: Afghanistan | CN9: AF | CO9: Afghanistan | CP9: AF | CQ9: Afghanistan | CR9: 20 | CS9: Default because more than 90/180 days past due | CT9: 1.11 | CU9: Growing of cereals (except rice), leguminous crops and oil seeds | CV9: 4 | CW9: Self-employed | CX9: 4 | CY9: Micro enterprise | DB9: 13 | DC9: Rating - Sector Público | DN9: 4 | DO9: Expired | DR9: 4 | DS9: Expired | DT9: 4 | DU9: Extended | DV9: NBR | DW9: National Business register identifier | DX9: NBR | DY9: National Business register identifier | DZ9: 1F | EA9: IDA (International Development Association) | EB9: S_11003 | EC9: Non-financial corporations - foreign controlled | ED9: 3 | EE9: Aa2, AA | EL9: D.12 | EM9: Securitisation bond - Securitisation is the issuance of debt securities for which coupon or principal payments are backed by specified assets or by future income streams. | EN9: 1102 | EO9: Consumer loans ABS - Detailed asset type breakdown of ABSs mainly in accordance with definitions of European and American Securitisation Forum. | ER9: 8XX | ES9: Other guarantee - A guarantee is provided by a non-government entity that would oblige the guarantor to make payments to the holder of the security if the issuer fails to meet the obligation to make repayments arising under the instrument secured by the guarantor. | ET9: 7 | EU9: Over-the-counter derivatives - Over-the-counter derivatives in accordance with the EBA’s implementing technical standards on asset encumbrance reporting as referred to in Article 99(5) and Article 100 of Regulation (EU) No 575/2013. | EZ9: 4 | FA9: STD - International Organisations | FB9: 11 | FC9: SPL. Project Finance | FD9: RMCT4 | FE9: Market risk | FJ9: EPSC4 | FK9: > 300; <= 400 | FN9: EPCL4 | FO9: D | FP9: ESGS4 | FQ9: Management companies | FR9: BA4 | FS9: SMEs | FT9: SCATX02 | FU9: Non financial corporations - Specific purpose - Building acquisition - Not eligible | FV9: 210101 | GA9: Solar photovoltaic - Electricity generation | GB9: A.1.1. Electricity generation using solar photovoltaic technology | GD9: Products Added value CIB | GE9: 25 | GF9: Transition to a circular economy | GK9: FMC4 | GL9: No collateral real | GM9: 99010 | GN9: Holding Peru | GO9: VEH04 | GP9: N1 - Vehicles used for the carriage of goods and having a maximum mass not exceeding 3.5 tonnes | GQ9: IM02 | GR9: Audited emissions of the group | GS9: PM02 | GT9: Based on vehicle distance | GU9: ESTT04 | GV9: Leed (Gold or above) | GW9: DNSH04 | GX9: DNSH4 - Do not significant harm to transition to a circular economy | GY9: SSTNBL4 | GZ9: Taxonomy Specific & Aligned under other criteria | HA9: HZRDS04 | HB9: Tornado | HC9: …. | HE9: N | HF9: Not cancelled | HI9: TERM ESTR-3M | HJ9: TERM ESTR-3M | HM9: MC4302 | HN9: Other commitments given, rest (Other commitments given) | HQ9: EXC04 | HR9: Trade Finance | HS9: USP04 | HT9: Other | HU9: FCL04 | HV9: High yield bond | HW9: CLO04 | HX9: Other CLOs (direct or indirect) | IA9: CLM04 | IB9: Climatic Zone C | IC9: SCN04 | ID9: Proactive | IE9: DEL04 | IF9: Secondary Markets Purchases | IG9: DST04 | IH9: Existing money with increase
B10: 6 | C10: IFRS: Financial assets at amortised cost | F10: ANG | G10: Netherlands Antillean Guilder | H10: ANG | I10: Netherlands Antillean Guilder | J10: ANG | K10: Netherlands Antillean Guilder | L10: ANG | M10: Netherlands Antillean Guilder | N10: ANG | O10: Netherlands Antillean Guilder | Z10: 9 | AA10: Renegotiated instrument without forbearance measures | AB10: 26 | AC10: Specific allowances (GAAP) | AD10: 26 | AE10: Specific allowances (GAAP) | AJ10: 16 | AK10: Overnight | AR10: 8 | AS10: Construction investment | AT10: 18 | AU10: Quarterly | BH10: 5 | BI10: Other (please specify in comments) | BJ10: 5 | BK10: Amortisation types other than French, German, Fixed amortisation schedule or bullet | BN10: 1000 | BO10: Deposits other than reverse repurchase agreements | BR10: 5 | BS10: Other - secured collateral | BT10: 5 | BU10: A1, A+ | BZ10: 5 | CA10: Parking | CB10: 5 | CC10: Third-party valuation | CD10: 7 | CE10: Other protection | CF10: 5 | CG10: Types of protection values other than notional amount, market value, fair value or long-term sustainable value | CL10: AG | CM10: Antigua and Barbuda | CN10: AG | CO10: Antigua and Barbuda | CP10: AG | CQ10: Antigua and Barbuda | CT10: 1.12 | CU10: Growing of rice | CV10: 5 | CW10: Unemployed | DB10: 14 | DC10: Rating - Entidades Financieras bancos | DT10: 5 | DU10: Expired | DV10: NCB | DW10: Identifier assigned by the National Central Bank | DX10: NCB | DY10: Identifier assigned by the National Central Bank | DZ10: 1G | EA10: ICSID (International Centre for Settlement of Investment Disputes) | EB10: S_121 | EC10: The central bank | ED10: 4 | EE10: Aa3, AA- | EL10: D.121 | EM10: Traditional securitisation - In case of traditional securitisation, the transfer of credit risk takes place by transferring the assets subject to that risk. | EN10: 1103 | EO10: Credit card receivables ABS - Detailed asset type breakdown of ABSs mainly in accordance with definitions of European and American Securitisation Forum. | ER10: 9XX | ES10: Guarantee level - No detailed information available - To be reported, in case the guarantee level is not available / applicable. | ET10: 8 | EU10: Deposits - repurchase agreements other than to central banks - Repurchase agreements other than to central banks in accordance with the EBA’s implementing technical standards on asset encumbrance reporting as referred to in Article 99(5) and Article 100 of Regulation (EU) No 575/2013. | EZ10: 6 | FA10: STD - Institutions and Corporates with a short-term credit assessment | FB10: 12 | FC10: SPL. Asset Financing | FD10: RMCT5 | FE10: Non mitigated | FJ10: EPSC5 | FK10: > 400; <= 500 | FN10: EPCL5 | FO10: E | FP10: ESGS5 | FQ10: Insurance undertakings | FR10: BA5 | FS10: Institutions | FT10: SCATX03 | FU10: Non financial corporations - Specific purpose - Building acquisition - Eligible, not aligned | FV10: 210102 | GA10: Concentrated solar power (CSP) - Electricity generation | GB10: A.1.2. Electricity generation using concentrated solar power (CSP) technology | GC10: PRDCT01010201 | GD10: Project & Acquisition Finance | GE10: 26 | GF10: Pollution prevention and control | GM10: 99809 | GN10: Shared Book NYCHILE | GO10: VEH05 | GP10: N2 - Vehicles used for the carriage of goods and having a maximum mass exceeding 3.5 tonnes but not exceeding 12 tonnes | GQ10: IM03 | GR10: Non audited emissions calculated by the counterparty | GT10: Estimated vehicle - specific emissions | GU10: ESTT05 | GV10: BREEAM ((Excellent or above where “Very good” can be acceptable with a minimum score of 70% in the Energy category) | GW10: DNSH05 | GX10: DNSH5 - Do not significant harm to pollution prevention and control | GY10: SSTNBL5 | GZ10: Aligned under other criteria | HA10: HZRDS05 | HB10: Lightning | HI10: TERM ESTR-6M | HJ10: TERM ESTR-6M | HQ10: EXC05 | HR10: Specialised Lending | HS10: USP05 | HT10: LBO Others | HU10: FCL05 | HV10: Other facilities (Capex, Mezzanine,…) | IA10: CLM05 | IB10: Climatic Zone D | IC10: SCN05 | ID10: Ordinary | IE10: DEL05 | IF10: Guarantee | IG10: DST05 | IH10: Existing money with decrease
B11: 7 | C11: nGAAP: Non-trading non-derivative financial assets measured at fair value through profit or loss | F11: AOA | G11: Kwanza | H11: AOA | I11: Kwanza | J11: AOA | K11: Kwanza | L11: AOA | M11: Kwanza | N11: AOA | O11: Kwanza | AJ11: 18 | AK11: Quarterly | AR11: 9 | AS11: Working capital facility | AT11: 19 | AU11: Semi-annually | BN11: 1001 | BO11: Revolving credit other than overdrafts and credit card debt | BR11: 6 | BS11: Other - unsecured collateral | BT11: 6 | BU11: A2, A | BZ11: 6 | CA11: Logistic | CD11: 8 | CE11: Residential real estate collateral | CL11: AI | CM11: Anguilla | CN11: AI | CO11: Anguilla | CP11: AI | CQ11: Anguilla | CT11: 1.13 | CU11: Growing of vegetables and melons, roots and tubers | CV11: 6 | CW11: Student | DB11: 37 | DC11: Rating - Ent.Financ. no bancos (fondos) | DV11: NSA | DW11: National Supervisory Authority code | DX11: NSA | DY11: National Supervisory Authority code | DZ11: 1H | EA11: UNESCO (United Nations Educational, Scientific and Cultural Organisation) | EB11: S_122 | EC11: Deposit-taking corporations except the central bank | ED11: 5 | EE11: A1, A+ | EL11: D.122 | EM11: Synthetic securitisation - In case of synthetic securitisation, the transfer of credit risk takes place by means of instruments that provide insurance against credit losses, without an actual transfer of assets taking place. | EN11: 1104 | EO11: Equipment leases ABS - Detailed asset type breakdown of ABSs mainly in accordance with definitions of European and American Securitisation Forum. | ES11: Rank level | ET11: 9 | EU11: Deposits other than repurchase agreements - Deposits other than repurchase agreements in accordance with the EBA’s implementing technical standards on asset encumbrance reporting as referred to in Article 99(5) and Article 100 of Regulation (EU) No 575/2013. | EZ11: 7 | FA11: STD - Units or shares in Collective Investment undertakings | FB11: 13 | FC11: SPL. Financing of basic products | FJ11: EPSC6 | FK11: > 500 | FN11: EPCL6 | FO11: F | FP11: ESGS6 | FQ11: Rest of other financial corporation | FR11: BA6 | FS11: Consumer | FT11: SCATX04 | FU11: Non financial corporations - Specific purpose - Building acquisition - Eligible and aligned | FV11: 210107 | GA11: Solar energy - Cogeneration heat/cool/power | GB11: A.1.17. Cogeneration of heat/cool and power from solar energy | GC11: PRDCT01010202 | GD11: Syndicated Loans | GE11: 27 | GF11: Protection and restoration of biodiversity and ecosystems. | GM11: 99228 | GN11: Corporate Trade Results Spain | GO11: VEH06 | GP11: N3 - Vehicles used for the carriage of goods and having a maximum mass exceeding 12 tonnes | GQ11: IM04 | GR11: Non audited emissions calculated by the group | GS11: PM03 | GT11: Average distance per province/state | GU11: ESTT06 | GV11: DGNB Certification (Gold or above) | GW11: DNSH06 | GX11: DNSH6 - Do not significant harm to protection and restoration of biodiversity and ecosystems. | GY11: SSTNBL6 | GZ11: Not eligible/aligned | HA11: HZRDS06 | HB11: River flood | HI11: TERM ESTR-12M | HJ11: TERM ESTR-12M | IA11: CLM06 | IB11: Climatic Zone E | IE11: DEL06 | IF11: Others
B12: 8 | C12: IFRS: Financial assets at fair value through other comprehensive income | F12: ARS | G12: Argentine Peso | H12: ARS | I12: Argentine Peso | J12: ARS | K12: Argentine Peso | L12: ARS | M12: Argentine Peso | N12: ARS | O12: Argentine Peso | AJ12: 19 | AK12: Semi-annually | AR12: 11 | AS12: Purposes other than real estate purchase, margin lending, debt financing, imports, exports, construction investment, working capital facility | AT12: 22 | AU12: Zero-coupon | BN12: 1002 | BO12: Credit lines other than revolving credit | BT12: 7 | BU12: A3, A- | BZ12: 7 | CA12: Residential | CD12: 9 | CE12: Offices and commercial premises | CL12: AL | CM12: Albania | CN12: AL | CO12: Albania | CP12: AL | CQ12: Albania | CT12: 1.14 | CU12: Growing of sugar cane | CV12: 7 | CW12: Pensioner | DB12: 38 | DC12: Rating - Ent.Fin. no bancos (no fondos) | DV12: NSI | DW12: National Statistical Institute number | DX12: NSI | DY12: National Statistical Institute number | DZ12: 1J | EA12: FAO (Food and Agriculture Organisation) | EB12: S_12201 | EC12: Deposit-taking corporations except the central bank - public | ED12: 6 | EE12: A2, A | EL12: D.129 | EM12: Other securitisation - A securitisation that is of a type not listed separately. | EN12: 1105 | EO12: Home equity loans ABS - Detailed asset type breakdown of ABSs mainly in accordance with definitions of European and American Securitisation Forum. | ER12: X1X | ES12: Subordinated - Junior level - Subordinated securities have a lower priority than the issuer’s other securities in the event of liquidation. A further differentiation can be made between Junior and Senior level with the Senior level having a higher priority. | ET12: 10 | EU12: Debt securities issued - covered bonds securities - Covered bonds securities issued in accordance with the EBA’s implementing technical standards on asset encumbrance reporting as referred to in Article 99(5) and Article 100 of Regulation (EU) No 575/2013. | EZ12: 8 | FA12: STD - Central Governments or Central Banks | FB12: 14 | FC12: SPL. Financing of root assets generators of income. | FJ12: EPSC7 | FK12: Without EP Score | FN12: EPCL7 | FO12: G | FR12: BA7 | FS12: M & A - Mergers and Acquisitions | FT12: SCATX05 | FU12: Non financial corporations - Specific purpose - Building renovation - Eligible, not aligned | FV12: 210109 | GA12: Solar thermal - Production of heat/cool | GB12: A.1.21. Production of heat/cool from solar thermal heating | GC12: PRDCT01010203 | GD12: Capital Finance | GE12: 28 | GF12: The exposure does not contribute to any of the defined objectives | GM12: 99051 | GN12: Remote book Treasury | GO12: VEH07 | GP12: L1 - A two-wheeled vehicle with an engine cylinder capacity not exceeding 50 cm3 and whatever the means of propulsion a maximum design speed not exceeding 50 km/h | GR12: Emissions based on physical activity | GS12: PM04 | GT12: Average distance per country | GU12: ESTT07 | GV12: EDGE (Advanced or Zero Carbon) | HA12: HZRDS07 | HB12: Flash flood | HI12: EURIBOR-1W | HJ12: EURIBOR-1W
B13: 9 | C13: nGAAP: Non-trading non-derivative financial assets measured at fair value to equity | F13: AUD | G13: Australian Dollar | H13: AUD | I13: Australian Dollar | J13: AUD | K13: Australian Dollar | L13: AUD | M13: Australian Dollar | N13: AUD | O13: Australian Dollar | AR13: 12 | AS13: Residential real estate purchase | BN13: 1003 | BO13: Reverse repurchase agreements | BT13: 8 | BU13: Baa1, BBB+ | BZ13: 8 | CA13: Mixed | CD13: 10 | CE13: Commercial real estate collateral | CL13: AM | CM13: Armenia | CN13: AM | CO13: Armenia | CP13: AM | CQ13: Armenia | CT13: 1.15 | CU13: Growing of tobacco | CV13: 8 | CW13: Other | DB13: 15 | DC13: Rating - Soberanos | DV13: OTHER | DW13: Other identifer type | DX13: OTHER | DY13: Other identifer type | DZ13: 1K | EA13: WHO (World Health Organisation) | EB13: S_12202 | EC13: Deposit-taking corporations except the central bank - national private | ED13: 7 | EE13: A3, A- | EL13: D.13 | EM13: Covered bond - Covered bonds are debt securities issued by a financial corporation, or fully guaranteed by a financial corporation. In case of default of the issuing or guarantor financial corporation, bond holders have a priority claim on the cover pool, in addition to their ordinary claim on the financial corporation. | EN13: 1106 | EO13: Manufactured housing leases ABS - Detailed asset type breakdown of ABSs mainly in accordance with definitions of European and American Securitisation Forum. | ER13: X2X | ES13: Subordinated - Senior level - Subordinated securities have a lower priority than the issuer’s other securities in the event of liquidation. A further differentiation can be made between Junior and Senior level with the Senior level having a higher priority. | ET13: 11 | EU13: Debt securities issued - asset-backed securities - Asset-backed securities (ABS) issued in accordance with the EBA’s implementing technical standards on asset encumbrance reporting as referred to in Article 99(5) and Article 100 of Regulation (EU) No 575/2013. | EZ13: 9 | FA13: IRB - Retail | FB13: 15 | FC13: SPL. Financing of highly volatile retail root assets | FN13: EPCL8 | FO13: Without EPC label | FR13: BA8 | FS13: ECM - Equity Capital Markets | FT13: SCATX06 | FU13: Non financial corporations - Specific purpose - Building renovation - Eligible and aligned | FV13: 210103 | GA13: Wind power - Electricity generation | GB13: A.1.3. Electricity generation from wind power | GC13: PRDCT01010204 | GD13: Asset Based Finance (ABF) | GM13: 99122 | GN13: ACS(Repayable Loans) | GO13: VEH08 | GP13: L2 - A three-wheeled vehicle of any wheel arrangement with an engine cylinder capacity not exceeding 50 cm3 and whatever the means of propulsion a maximum design speed not exceeding 50 km/h | GQ13: IM05 | GR13: Based on energy consumption | GT13: Estimated vehicle - unspecific emissions | GU13: ESTT08 | GV13: Passivhaus (Classic or above) | HA13: HZRDS08 | HB13: Storm surge | HC13: VHCL8 | HD13: Without vehicle label | HI13: EURIBOR-1M | HJ13: EURIBOR-1M
B14: 10 | C14: nGAAP: Loans and receivables | F14: AWG | G14: Aruban Florin | H14: AWG | I14: Aruban Florin | J14: AWG | K14: Aruban Florin | L14: AWG | M14: Aruban Florin | N14: AWG | O14: Aruban Florin | AR14: 13 | AS14: Commercial real estate purchase | BN14: 1004 | BO14: Loans other than overdrafts, convenience credit, extended credit, credit card credit, revolving credit other than credit card credit, reverse repurchase agreements, trade receivables and financial leases | BT14: 9 | BU14: Baa2, BBB | BZ14: 9 | CA14: Other | CD14: 12 | CE14: Securities | CL14: AO | CM14: Angola | CN14: AO | CO14: Angola | CP14: AO | CQ14: Angola | CT14: 1.16 | CU14: Growing of fibre crops | DB14: 16 | DC14: Rating - Project Finance | DV14: PS | DW14: Public sector entity identifier | DX14: PS | DY14: Public sector entity identifier | DZ14: 1L | EA14: IFAD (International Fund for Agricultural Development) | EB14: S_12203 | EC14: Deposit-taking corporations except the central bank - foreign controlled | ED14: 8 | EE14: Baa1, BBB+ | EL14: D.131 | EM14: Jumbo covered bond - Jumbo covered bonds are covered bonds issued in accordance with the requirements in Article 52(4) of Directive 2009/65/EC and with an issuing volume of at least EUR 1 billion, for which at least three market-makers provide regular bid and ask quotes. | EN14: 1107 | EO14: Small and medium-sized enterprises (SME) loans ABS - Detailed asset type breakdown of ABSs mainly in accordance with definitions of European and American Securitisation Forum. | ER14: X3X | ES14: Subordinated - No further breakdown available - Subordinated securities have a lower priority than the issuer’s other securities in the event of liquidation. A further differentiation can be made between Junior and Senior level with the Senior level having a higher priority. | ET14: 12 | EU14: Debt securities issued - other than covered bonds and ABSs - Debt securities issued other than covered bonds and ABSs in accordance with the EBA’s implementing technical standards on asset encumbrance reporting as referred to in Article 99(5) and Article 100 of Regulation (EU) No 575/2013. | EZ14: 10 | FA14: STD - Institutions | FB14: 16 | FC14: SME (Small & medium companies) | FR14: BA9 | FS14: Corporate Equity Derivatives | FT14: SCATX07 | FU14: Non financial corporations - Specific purpose - Motor vehicle loans - Eligible, not aligned | FV14: 210104 | GA14: Ocean energy technologies - Electricity generation | GB14: A.1.4. Electricity generation from ocean energy technologies | GC14: PRDCT01010205 | GD14: Leveraged Finance | GM14: 95001 | GN14: Shared Income London | GO14: VEH09 | GP14: L3 - A two-wheeled vehicle with an engine cylinder capacity in the case of a thermic engine exceeding 50 cm3 or whatever the means of propulsion a maximum design speed exceeding 50 km/h | GQ14: IM06 | GR14: Based on production | GS14: PM05 | GT14: Distance by country/state - known vehicle type | GU14: ESTT09 | GV14: PED within the top 15% | HA14: HZRDS09 | HB14: Sea level rise | HI14: EURIBOR-3M | HJ14: EURIBOR-3M
B15: 12 | C15: nGAAP: Held-to-maturity investments | F15: AZN | G15: Azerbaijanian Manat | H15: AZN | I15: Azerbaijanian Manat | J15: AZN | K15: Azerbaijanian Manat | L15: AZN | M15: Azerbaijanian Manat | N15: AZN | O15: Azerbaijanian Manat | BN15: 1005 | BO15: Debt securities | BT15: 10 | BU15: Baa3, BBB- | CD15: 13 | CE15: Gold | CL15: AQ | CM15: Antarctica | CN15: AQ | CO15: Antarctica | CP15: AQ | CQ15: Antarctica | CT15: 1.19 | CU15: Growing of other non-perennial crops | DB15: 21 | DC15: Rating - Administraciones Públicas | DV15: RIAD | DW15: RIAD Code | DX15: RIAD | DY15: RIAD Code | DZ15: 1M | EA15: IFC (International Finance Corporation) | EB15: S_123 | EC15: Money market funds (MMFs) | ED15: 9 | EE15: Baa2, BBB | EL15: D.139 | EM15: Other covered bond - Covered bonds other than jumbo covered bonds. | EN15: 1108 | EO15: Student loans ABS - Detailed asset type breakdown of ABSs mainly in accordance with definitions of European and American Securitisation Forum. | ER15: X4X | ES15: Senior - Senior securities are required to be repaid before subordinated securities. | ET15: 13 | EU15: Other sources of encumbrance - Other sources of encumbrance in accordance with the EBA’s implementing technical standards on asset encumbrance reporting as referred to in Article 99(5) and Article 100 of Regulation (EU) No 575/2013. | EZ15: 11 | FA15: IRB - Securitisation | FB15: 17 | FC15: Revolving | FR15: BA10 | FS15: Project and Acquisition Finance | FT15: SCATX08 | FU15: Non financial corporations - Specific purpose - Motor vehicle loans - Eligible and aligned | FV15: 210105 | GA15: Hydropower - Electricity generation | GB15: A.1.5. Electricity generation from hydropower | GC15: PRDCT01010206 | GD15: Export & Agency Finance | GM15: 95012 | GN15: Equity London | GO15: VEH10 | GP15: L4 - A vehicle with three wheels asymmetrically arranged in relation to the longitudinal median plane with an engine cylinder capacity in the case of a thermic engine exceeding 50 cm3 or whatever the means of propulsion a maximum design speed exceeding 50 km/h (motor cycles with sidecars) | GR15: Emissions based on economic activity | GS15: PM06 | GT15: Distance by country/state - unknown vehicle type | GU15: ESTT10 | GV15: Green Globes (Three globes or above) | HA15: HZRDS10 | HB15: Wildfire | HI15: EURIBOR-6M | HJ15: EURIBOR-6M
B16: 13 | C16: nGAAP: Non-trading non-derivative financial instruments measured at a cost-based method | F16: BAM | G16: Convertible Mark | H16: BAM | I16: Convertible Mark | J16: BAM | K16: Convertible Mark | L16: BAM | M16: Convertible Mark | N16: BAM | O16: Convertible Mark | BN16: 2001 | BO16: Guarantees | BT16: 11 | BU16: Ba1, BB+ | CD16: 15 | CE16: Currency and deposits | CL16: AR | CM16: Argentina | CN16: AR | CO16: Argentina | CP16: AR | CQ16: Argentina | CT16: 1.2 | CU16: Growing of perennial crops | DB16: 34 | DC16: Rating - Pymes | DV16: TAX | DW16: TAX Code | DX16: TAX | DY16: TAX Code | DZ16: 1N | EA16: MIGA (Multilateral Investment Guarantee Agency) | EB16: S_12301 | EC16: Money market funds (MMFs) - public | ED16: 10 | EE16: Baa3, BBB- | EL16: D.14 | EM16: Medium-term note - A debt security issued at fixed or floating rates of interest, as part of an overall medium-term note programme. Used by institutions as a source for medium-term funding. | EN16: 1109 | EO16: Whole Business Securitisation (WBS) ABS - Detailed asset type breakdown of ABSs mainly in accordance with definitions of European and American Securitisation Forum. | ER16: X5X | ES16: ABS Class - Junior - In case of Asset-backed securities, a breakdown of the tranch level is to be provided. | EZ16: 12 | FA16: Other exposures with RW = 100% | FB16: 19 | FC16: Shares | FR16: BA11 | FS16: Syndicated | FT16: SCATX09 | FU16: Non financial corporations - Specific purpose - Other purpose - Not eligible | FV16: 210106 | GA16: Geothermal energy - Electricity generation | GB16: A.1.6. Electricity generation from geothermal energy | GC16: PRDCT01010207 | GD16: Trade & Working Capital Solutions | GM16: 95016 | GN16: Shared Book Treasury NY Mex | GO16: VEH11 | GP16: L5 - A vehicle with three wheels symmetrically arranged in relation to the longitudinal median plane with an engine cylinder capacity in the case of a thermic engine exceeding 50 cm3 or whatever the means of propulsion a maximum design speed exceeding 50 km/h | GQ16: IM07 | GR16: Based on revenues | GT16: Commercial/residential real estate loans | GU16: ESTT11 | GV16: Living Building Challenges | HA16: HZRDS11 | HB16: Fire weather | HI16: EURIBOR-12M | HJ16: EURIBOR-12M
B17: 14 | C17: IFRS: Cash balances at central banks and other demand deposits | F17: BBD | G17: Barbados Dollar | H17: BBD | I17: Barbados Dollar | J17: BBD | K17: Barbados Dollar | L17: BBD | M17: Barbados Dollar | N17: BBD | O17: Barbados Dollar | BN17: 2002 | BO17: Derivatives | BT17: 12 | BU17: Ba2, BB | CD17: 16 | CE17: Loans | CL17: AS | CM17: American Samoa | CN17: AS | CO17: American Samoa | CP17: AS | CQ17: American Samoa | CT17: 1.21 | CU17: Growing of grapes | DB17: 35 | DC17: Scoring admisión Persona Física - Individuos | DV17: TRD | DW17: Trade register identifier | DX17: TRD | DY17: Trade register identifier | DZ17: 1O | EA17: UNICEF (United Nations Children Fund) | EB17: S_12302 | EC17: Money market funds (MMFs) - national private | ED17: 11 | EE17: Ba1, BB+ | EL17: D.141 | EM17: Euro medium term notes (EMTN) - A medium-term note denominated in Euro. | EN17: 1110 | EO17: Mixed ABS - An ABS that is a mix of different ABS types, e.g. combination of auto and consumer loans. | ER17: X6X | ES17: ABS Class - Mezzanine - In case of Asset-backed securities, a breakdown of the tranch level is to be provided. | EZ17: 13 | FA17: IRB - Other non-credit obligation assets | FB17: 21 | FC17: SPL. Project Finance Corporates | FR17: BA12 | FS17: Debt Capital Markets & Securitization | FT17: SCATX10 | FU17: Non financial corporations - Specific purpose - Other purpose - Eligible, not aligned | FV17: 210108 | GA17: Geothermal energy - Cogeneration heat/cool/power | GB17: A.1.18. Cogeneration of heat/cool and power from geothermal energy | GC17: PRDCT010103 | GD17: Other Loans & Advances | GM17: 99456 | GN17: Vendor Activity NY | GO17: VEH12 | GP17: L6 - A vehicle with four wheels whose unladen mass is not more than 350 kg, not including the mass of the batteries in case of electric vehicles, whose maximum design speed is not more than 45 km/h, and whose engine cylinder capacity does not exceed 50 cm3 for spark (positive) ignition engines, or whose maximum net power output does not exceed 4 kW in the case of other internal combustion engines, or whose maximum continuous rated power does not exceed 4 kW in the case of electric engines. | GQ17: IM08 | GR17: Based on assets | GT17: Actual building emissions | GU17: ESTT12 | GV17: HQE (Excellence or above) | HA17: HZRDS12 | HB17: Drought | HI17: SOFR-OVERNIGHT | HJ17: SOFR-OVERNIGHT
B18: 15 | C18: nGAAP: Other Non-trading Non-derivative Financial assets | F18: BDT | G18: Taka | H18: BDT | I18: Taka | J18: BDT | K18: Taka | L18: BDT | M18: Taka | N18: BDT | O18: Taka | BN18: 2003 | BO18: FX | BT18: 13 | BU18: Ba3, BB- | CD18: 17 | CE18: Trade receivables | CL18: AT | CM18: Austria | CN18: AT | CO18: Austria | CP18: AT | CQ18: Austria | CT18: 1.22 | CU18: Growing of tropical and subtropical fruits | DB18: 31 | DC18: Scoring admisión Persona Física - negocios | DV18: VAT | DW18: Value added tax identifier | DX18: VAT | DY18: Value added tax identifier | DZ18: 1P | EA18: UNHCR (United Nations High Commissioner for Refugees) | EB18: S_12303 | EC18: Money market funds (MMFs) - foreign controlled | ED18: 12 | EE18: Ba2, BB | EL18: D.149 | EM18: Other MTN - A medium-term note denominated in a currency other than Euro. | EN18: 1198 | EO18: Other Assets ABS - An ABS that is of a type not listed separately. | ER18: X7X | ES18: ABS Class - Senior - In case of Asset-backed securities, a breakdown of the tranch level is to be provided. | EZ18: 14 | FA18: IRB - Institutions | FB18: 22 | FC18: SPL. Asset Financing Corporates | FR18: BA13 | FS18: ACS - Asset & Capital Structuring | FT18: SCATX11 | FU18: Non financial corporations - Specific purpose - Other purpose - Eligible and aligned | FV18: 210110 | GA18: Geothermal energy - Production of heat/cool | GB18: A.1.22. Production of heat/cool from geothermal energy | GC18: PRDCT0102 | GD18: Renting / Operating Leasing | GM18: 99457 | GN18: Vendor Activity Mexico | GO18: VEH13 | GP18: L7 - A vehicle with four wheels, other than that classified for the category L6, whose unladen mass is not more than 400 kg (550 kg for vehicles intended for carrying goods), not including the mass of batteries in the case of electric vehicles and whose maximum continuous rated power does not exceed 15 kW | GR18: Project finance | GS18: PM07 | GT18: Supplier specific factors and energy consumption | GU18: ESTT13 | GV18: Minergie (Minergie-A and Standard Minergie) | HA18: HZRDS13 | HB18: Heat | HI18: TERM SOFR-1M | HJ18: TERM SOFR-1M
B19: 41 | C19: IFRS: Non-trading financial assets mandatorily at fair value through profit or loss | F19: BGN | G19: Bulgarian lev | H19: BGN | I19: Bulgarian lev | J19: BGN | K19: Bulgarian lev | L19: BGN | M19: Bulgarian lev | N19: BGN | O19: Bulgarian lev | BN19: 2004 | BO19: Security Lending | BT19: 14 | BU19: B1, B+ | CD19: 18 | CE19: Equity and investment funds shares | CL19: AU | CM19: Australia | CN19: AU | CO19: Australia | CP19: AU | CQ19: Australia | CT19: 1.23 | CU19: Growing of citrus fruits | DB19: 32 | DC19: Scoring admisión - Persona Jurídica | DZ19: 1Q | EA19: UNRWA (United Nations Relief and Works Agency for Palestine) | EB19: S_124 | EC19: Non-MMF investment funds | ED19: 13 | EE19: Ba3, BB- | EL19: D.15 | EM19: Perpetual bond - A debt security that has no stated maturity date. | EN19: 1199 | EO19: ABS - No detailed classification available - To be reported, in case it is known that the security is a ABS, but the type is unknown. | ER19: X9X | ES19: Rank level - No detailed information available - To be reported, in case the rank level is not available / applicable. | EZ19: 16 | FA19: IRB - Company | FB19: 23 | FC19: SPL. Fin. basic products Corporates | FR19: BA14 | FS19: Leveraged Finance | FU19: Credit institutions & Other financial corporations | FZ19: Renewable fuels, bioenergy and waste heat | GC19: PRDCT0103 | GD19: Bonds Portfolio | GM19: 99383 | GN19: Split Equity London to Latam | GO19: VEH14 | GP19: O1 - Trailers with a maximum mass not exceeding 0.75 tonnes | GR19: Reported emissions | GS19: PM08 | GT19: Average emission factors and energy consumption | GU19: ESTT14 | GV19: Aqua-HQE (Excellent or above) | HA19: HZRDS14 | HB19: Precipitation | HI19: TERM SOFR-3M | HJ19: TERM SOFR-3M
B20: 45 | C20: nGAAP: Cash balances at central banks and other demand deposits | F20: BHD | G20: Bahraini Dinar | H20: BHD | I20: Bahraini Dinar | J20: BHD | K20: Bahraini Dinar | L20: BHD | M20: Bahraini Dinar | N20: BHD | O20: Bahraini Dinar | BN20: 2005 | BO20: Structured Product | BT20: 15 | BU20: B2, B | CD20: 51 | CE20: Auto collateral | CL20: AW | CM20: Aruba | CN20: AW | CO20: Aruba | CP20: AW | CQ20: Aruba | CT20: 1.24 | CU20: Growing of pome fruits and stone fruits | DB20: 26 | DC20: Scoring comportamiento Persona Física - Individuos | DZ20: 1R | EA20: IAEA (International Atomic Energy Agency) | EB20: S_12401 | EC20: Non-MMF investment funds - public | ED20: 14 | EE20: B1, B+ | EL20: D.16 | EM20: Linked bond - Linked bonds have their coupon or principal payments (or both) linked to a general price index for goods and services (such as the consumer price index (CPI)), interest rate (such as the London interbank offered rate (LIBOR) or a bond yield), or asset price. | EN20: 1200 | EO20: Mortgage-backed security (MBS) - A bond, created through securitisation, whose coupon payments and principal repayments are dependent on a pool of mortgages, either purchased in the secondary market or from the balance sheet of an original asset owner. | ES20: Security level | EZ20: 17 | FA20: IRB - Central Governments or Central Banks | FB20: 24 | FC20: SPL. Fin. root assets generators Corp. | FR20: BA15 | FS20: Cash Management | FT20: SCATX12 | FU20: Credit institutions & Other financial corporations - General purpose | FV20: 210202 | GA20: Bioenergy - Electricity generation | GB20: A.1.8. Electricity generation from bioenergy | GD20: Off Balance | GM20: 99384 | GN20: Split with LATAM, Equity NY | GO20: VEH15 | GP20: O2 - Trailers with a maximum mass exceeding 0.75 tonnes, but not exceeding 3.5 tonnes | GQ20: IM09 | GR20: Verified emissions of the project | GT20: Estimated based on floor area | GU20: ESTT15 | GV20: Eco-casa (Level 1 or above) | HA20: HZRDS15 | HB20: Landslide | HI20: TERM SOFR-6M | HJ20: TERM SOFR-6M
B21: 46 | C21: nGAAP: Financial assets held for trading | F21: BIF | G21: Burundi Franc | H21: BIF | I21: Burundi Franc | J21: BIF | K21: Burundi Franc | L21: BIF | M21: Burundi Franc | N21: BIF | O21: Burundi Franc | BN21: 2006 | BO21: Equity | BT21: 16 | BU21: B3, B- | CD21: 52 | CE21: Shipping | CL21: AX | CM21: Aland Islands | CN21: AX | CO21: Aland Islands | CP21: AX | CQ21: Aland Islands | CT21: 1.25 | CU21: Growing of other tree and bush fruits and nuts | DB21: 36 | DC21: Scoring comportamiento Persona Física - negocios | DZ21: 1S | EA21: ILO (International Labour Organisation) | EB21: S_12402 | EC21: Non-MMF investment funds - national private | ED21: 15 | EE21: B2, B | EL21: D.161 | EM21: Inflation-linked bond - Detailed breakdowns by type in accordance with definitions laid down in Handbook of Securities Statistics. | EN21: 1201 | EO21: Residential mortgage-backed security (RMBS) - Detailed asset type breakdown of MBSs mainly in accordance | ER21: XX1 | ES21: Unsecured - Securities are not backed by assets, future income streams or similar. | EZ21: 18 | FA21: Other exposures with RW = 0% | FB21: 25 | FC21: SPL. Fin. highly volatile retail Corp. | FR21: BA16 | FS21: Core Funding/ Basic financing | FU21: Credit institutions & Other financial corporations - Specific purpose | FV21: 210205 | GA21: Bioenergy - Cogeneration heat/cool/power | GB21: A.1.20. Cogeneration of heat/cool and power from bioenergy | GC21: PRDCT0201 | GD21: Contingent risks | GM21: 99388 | GN21: Results Structured Finance Corporate Spain | GO21: VEH16 | GP21: O3 - Trailers with a maximum mass exceeding 3.5 tonnes, but not exceeding 10 tonnes | GQ21: IM10 | GR21: Unverified emissions reported | GS21: PM09 | GT21: Average based on EPC label and floor area | GU21: ESTT16 | GV21: NGBS (Gold or above) | HA21: HZRDS16 | HB21: Aridity | HI21: TERM SOFR-12M | HJ21: TERM SOFR-12M
B22: 47 | C22: nGAAP: Financial assets designated at fair value through profit or loss | F22: BMD | G22: Bermudian Dollar | H22: BMD | I22: Bermudian Dollar | J22: BMD | K22: Bermudian Dollar | L22: BMD | M22: Bermudian Dollar | N22: BMD | O22: Bermudian Dollar | BN22: 2007 | BO22: Fixed Income | BT22: 17 | BU22: Caa1, CCC+ | CD22: 53 | CE22: Aircraft | CL22: AZ | CM22: Azerbaijan | CN22: AZ | CO22: Azerbaijan | CP22: AZ | CQ22: Azerbaijan | CT22: 1.26 | CU22: Growing of oleaginous fruits | DB22: 33 | DC22: Scoring comportamiento - Persona Jurídica | DZ22: 1T | EA22: ITU (International Telecommunication Union) | EB22: S_12403 | EC22: Non-MMF investment funds - foreign controlled | ED22: 16 | EE22: B3, B- | EL22: D.162 | EM22: Interest rate-linked bond - Detailed breakdowns by type in accordance with definitions laid down in Handbook of Securities Statistics. | EN22: 1202 | EO22: Commercial mortgage-backed security (CMBS) - with definitions of European and American Securitisation Forum. | ER22: XX2 | ES22: Secured - Securities are backed by assets, future income streams or similar. | EZ22: 19 | FA22: Other exposures with RW = 20% | FR22: BA17 | FS22: Trade & WCS | FT22: SCATX13 | FU22: Credit institutions & Other financial corporations - Specific purpose - Not eligible | FV22: 210207 | GA22: Bioenergy - Production of heat/cool | GB22: A.1.24. Production of heat/cool from bioenergy | GC22: PRDCT0202 | GD22: Undrawn balances Committed | GM22: 99721 | GN22: Brazil Remote Book Trading | GO22: VEH17 | GP22: O4 - Trailers with a maximum mass exceeding 10 tonnes | GR22: Emissions based on physical activity | GS22: PM10 | GT22: Average based on location/building statistical and floor area | GU22: ESTT17 | GV22: Calificacion Energetica de Viviendas CEV (Rating A and B) | HA22: HZRDS17 | HB22: Rainfall soil erosion | HI22: SONIA-OVERNIGHT | HJ22: SONIA-OVERNIGHT
B23: 48 | C23: nGAAP: Non-trading financial assets mandatorily at fair value through profit or loss | F23: BND | G23: Brunei Dollar | H23: BND | I23: Brunei Dollar | J23: BND | K23: Brunei Dollar | L23: BND | M23: Brunei Dollar | N23: BND | O23: Brunei Dollar | BN23: 2008 | BO23: Repo | BT23: 18 | BU23: Caa2, CCC | CL23: BA | CM23: Bosnia and Herzegovina | CN23: BA | CO23: Bosnia and Herzegovina | CP23: BA | CQ23: Bosnia and Herzegovina | CT23: 1.27 | CU23: Growing of beverage crops | DZ23: 1U | EA23: Rest of UN Organisations n.i.e. | EB23: S_125 | EC23: Other financial intermediaries, except ICPFs | ED23: 17 | EE23: Caa1, CCC+ | EL23: D.163 | EM23: Asset-linked bond - Detailed breakdowns by type in accordance with definitions laid down in Handbook of Securities Statistics. | EN23: 1203 | EO23: Mixed MBS - An MBS that is a mix of different MBS types, e.g. combination of RMBS and CMBS. | ER23: XX9 | ES23: Security level - No detailed information available - To be reported, in case the security level is not available / applicable. | EZ23: 20 | FA23: ENC - Non Financial assets | FR23: BA18 | FS23: Export & Agency Finance | FT23: SCATX14 | FU23: Credit institutions & Other financial corporations - Specific purpose - Eligible, not aligned | FV23: 210201 | GA23: Renewable fuels- Electricity generation | GB23: A.1.7. Electricity generation from renewable non-fossil gaseous and liquid fuels | GC23: PRDCT0203 | GD23: Derivatives | GM23: 99722 | GN23: BRAZIL REMOTE BOOK MARKET MAKING | GO23: VEH18 | GP23: T - Motorised, wheeled or tracked agricultural or forestry vehicle having at least two axles and a maximum design speed of not less than 6 km/h | GQ23: IM11 | GR23: Based on energy consumption | GT23: Estimated based on number of buildings | GU23: ESTT18 | GV23: Other sustainable certification | HA23: HZRDS18 | HB23: Shoreline erosion | HI23: TERM SONIA-1M | HJ23: TERM SONIA-1M
F24: BOB | G24: Boliviano | H24: BOB | I24: Boliviano | J24: BOB | K24: Boliviano | L24: BOB | M24: Boliviano | N24: BOB | O24: Boliviano | BN24: 2009 | BO24: Cash Flow Matching | BT24: 19 | BU24: Caa3, CCC- | CL24: BB | CM24: Barbados | CN24: BB | CO24: Barbados | CP24: BB | CQ24: Barbados | CT24: 1.28 | CU24: Growing of spices, aromatic, drug and pharmaceutical crops | DZ24: 1W | EA24: World Bank Group | EB24: S_12501 | EC24: Other financial intermediaries, except ICPFs - public | ED24: 18 | EE24: Caa2, CCC | EL24: D.164 | EM24: Currency-linked bond - Detailed breakdowns by type in accordance with definitions laid down in Handbook of Securities Statistics. | EN24: 1298 | EO24: Other MBS - An MBS that is of a type not listed separately. | EZ24: 21 | FA24: ENC - Financial assets weighing 50% | FR24: BA19 | FS24: Sales Markets | FT24: SCATX15 | FU24: Credit institutions & Other financial corporations - Specific purpose - Eligible and aligned | FV24: 210204 | GA24: Renewable fuels - Cogeneration heat/cool/power | GB24: A.1.19. Cogeneration of heat/cool and power from renewable non-fossil gaseous and liquid fuels | GD24: Advisory & Facilitation services | GM24: 99603 | GN24: HongKong Income Split to Commercial Banking | GO24: VEH19 | GP24: G - Off-road vehicles | GQ24: IM12 | GR24: Based on production | GS24: PM11 | GT24: Average based on number of buildings | GU24: ESTT19 | GV24: One of the sustainable certifications listed above, but it does not comply with scoring required | HA24: HZRDS19 | HB24: Hurricanes | HI24: TERM SONIA-3M | HJ24: TERM SONIA-3M
F25: BOV | G25: Mvdol | H25: BOV | I25: Mvdol | J25: BOV | K25: Mvdol | L25: BOV | M25: Mvdol | N25: BOV | O25: Mvdol | BN25: 2011 | BO25: Commodity | BT25: 20 | BU25: Ca, CC | CL25: BD | CM25: Bangladesh | CN25: BD | CO25: Bangladesh | CP25: BD | CQ25: Bangladesh | CT25: 1.29 | CU25: Growing of other perennial crops | DZ25: 4A | EA25: All the European Union Institutions excluding the institutions of the euro area (changing composition) | EB25: S_12502 | EC25: Other financial intermediaries, except ICPFs - national private | ED25: 19 | EE25: Caa3, CCC- | EL25: D.165 | EM25: Credit-linked bond - Detailed breakdowns by type in accordance with definitions laid down in Handbook of Securities Statistics. | EN25: 1299 | EO25: MBS - No detailed classification available - To be reported, in case it is known that the security is a MBS, but the type is unknown. | ER25: Note: The (sub)categories should be provided according to the most granular level of detail possible. | EZ25: 22 | FA25: ENC - Financial assets weighing 100% | FR25: BA20 | FS25: ACPM | FU25: Households | FV25: 210206 | GA25: Renewable fuels - Production of heat/cool | GB25: A.1.23. Production of heat/cool from renewable non-fossil gaseous and liquid fuels | GC25: PRDCT0301 | GD25: Mergers & Acquisitions (M&A) | GM25: 102481 | GN25: Transfer to SLB Securities Finance books | GO25: VEH20 | GP25: S - Interchangeable towed equipment | GR25: Emissions based on economic activity | GU25: ESTT20 | GV25: Without sustainable real estate certification | HA25: HZRDS20 | HB25: Convective storms | HI25: TERM SONIA-6M | HJ25: TERM SONIA-6M
