Workbook
Name asefadf: #REF!
Name asefadf: #REF!
Name asefadf: #REF!
Name asefadf: #REF!
Name asefadf: #REF!
Name bn: #REF!
Name bn: #REF!

Sheet PlanoV1.0
H1: =I1/8/5 -> 68.2 | I1: =SUM(J1:AF1) -> 2728 | K1: =K4*8*5 -> 124 | L1: =L4*8*5 -> 124 | M1: =M4*8*5 -> 124 | N1: =N4*8*5 -> 124 | O1: =O4*8*5 -> 124 | P1: =P4*8*5 -> 124 | Q1: =Q4*8*5 -> 124 | R1: =R4*8*5 -> 124 | ... BU1: =BU4*8*5 -> 84
I2: VAL | K2: =K3-K4 -> 0 | L2: =L3-L4 -> 0 | M2: =M3-M4 -> 0 | N2: =N3-N4 -> 0 | O2: =O3-O4 -> 0 | P2: =P3-P4 -> 0 | Q2: =Q3-Q4 -> 0 | R2: =R3-R4 -> 0 | ... BA2: =BA3-BA4 -> 0 | BC2: =BC3-BC4 -> 0 | BD2: =BD3-BD4 -> 0 | BE2: =BE3-BE4 -> 0 | BF2: =BF3-BF4 -> 0 | BG2: =BG3-BG4 -> 0 | BH2: =BH3-BH4 -> 0 | BI2: =BI3-BI4 -> 0 | BJ2: =BJ3-BJ4 -> 0 | ... BU2: =BU3-BU4 -> 0
I3: FTE REAIS | K3: =SUM(K9:K226) -> 3.1 | L3: =SUM(L9:L226) -> 3.1 | M3: =SUM(M9:M226) -> 3.1 | N3: =SUM(N9:N226) -> 3.1 | O3: =SUM(O9:O226) -> 3.1 | P3: =SUM(P9:P226) -> 3.1 | Q3: =SUM(Q9:Q226) -> 3.1 | R3: =SUM(R9:R226) -> 3.1 | ... BA3: =SUM(BA9:BA226) -> 2.1 | BC3: =SUM(BC9:BC226) -> 2.1 | BD3: =SUM(BD9:BD226) -> 2.1 | BE3: =SUM(BE9:BE226) -> 2.1 | BF3: =SUM(BF9:BF226) -> 2.1 | BG3: =SUM(BG9:BG226) -> 2.1 | BH3: =SUM(BH9:BH226) -> 2.1 | BI3: =SUM(BI9:BI226) -> 2.1 | BJ3: =SUM(BJ9:BJ226) -> 2.1 | ... BU3: =SUM(BU9:BU226) -> 2.1
I4: FTE ESP. | K4: 3.1 | L4: 3.1 | M4: 3.1 | N4: 3.1 | O4: 3.1 | P4: 3.1 | Q4: 3.1 | R4: 3.1 | S4: 3.1 | T4: 3.1 | U4: 3.1 | V4: 3.1 | W4: 3.1 | X4: 3.1 | Y4: 3.1 | Z4: 3.1 | AA4: 3.1 | AB4: 3.1 | AC4: 3.1 | AD4: 3.1 | AE4: 3.1 | AF4: 3.1 | AG4: 2.1 | AH4: 2.1 | AI4: 2.1 | AJ4: 2.1 | AK4: 2.1 | AL4: 2.1 | AM4: 2.1 | AN4: 2.1 | AO4: 2.1 | AP4: 2.1 | AQ4: 2.1 | AR4: 2.1 | AS4: 2.1 | AT4: 2.1 | AU4: 2.1 | AV4: 2.1 | AW4: 2.1 | AX4: 2.1 | AY4: 2.1 | AZ4: 2.1 | BA4: 2.1 | BC4: 2.1 | BD4: 2.1 | BE4: 2.1 | BF4: 2.1 | BG4: 2.1 | BH4: 2.1 | BI4: 2.1 | BJ4: 2.1 | BK4: 2.1 | BL4: 2.1 | BM4: 2.1 | BN4: 2.1 | BO4: 2.1 | BP4: 2.1 | BQ4: 2.1 | BR4: 2.1 | BS4: 2.1 | BT4: 2.1 | BU4: 2.1
J5: Janeiro | AG5: Fevereiro | BA5: Março | BV5: Abril
J6: 45649 | K6: 45650 | L6: 45651 | M6: 45652 | N6: 45653 | O6: 45649 | P6: 45650 | Q6: 45651 | R6: 45652 | S6: 45653 | T6: 45649 | U6: 45650 | V6: 45651 | W6: 45652 | X6: 45653 | Y6: 45649 | Z6: 45650 | AA6: 45651 | AB6: 45652 | AC6: 45653 | AD6: 45649 | AE6: 45650 | AF6: 45651 | AG6: 45652 | AH6: 45653 | AI6: 45649 | AJ6: 45650 | AK6: 45651 | AL6: 45652 | AM6: 45653 | AN6: 45649 | AO6: 45650 | AP6: 45651 | AQ6: 45652 | AR6: 45653 | AS6: 45649 | AT6: 45650 | AU6: 45651 | AV6: 45652 | AW6: 45653 | AX6: 45649 | AY6: 45650 | AZ6: 45651 | BA6: 45652 | BB6: 45653 | BC6: 45649 | BD6: 45650 | BE6: 45651 | BF6: 45652 | BG6: 45653 | BH6: 45649 | BI6: 45650 | BJ6: 45651 | BK6: 45652 | BL6: 45653 | BM6: 45649 | BN6: 45650 | BO6: 45651 | BP6: 45652 | BQ6: 45653 | BR6: 45649 | BS6: 45650 | BT6: 45651 | BU6: 45652 | BV6: 45653 | BW6: 45649 | BX6: 45650 | BY6: 45651 | BZ6: 45652 | CA6: 45653 | CB6: 45649 | CC6: 45650 | CD6: 45651 | CE6: 45652 | CF6: 45653 | CG6: 45649 | CH6: 45650 | CI6: 45651 | CJ6: 45652 | CK6: 45653 | CL6: 45649 | CM6: 45650 | CN6: 45651 | CO6: 45652 | CP6: 45653 | CQ6: 45649
I7: 45657 | J7: =WORKDAY(I7,1) -> 45658 | K7: =WORKDAY(J7,1) -> 45659 | L7: =WORKDAY(K7,1) -> 45660 | M7: =WORKDAY(L7,1) -> 45663 | N7: =WORKDAY(M7,1) -> 45664 | O7: =WORKDAY(N7,1) -> 45665 | P7: =WORKDAY(O7,1) -> 45666 | Q7: =WORKDAY(P7,1) -> 45667 | ... X7: =WORKDAY(W7,1) -> 45678
F8: # Campos | G8: Duração (horas) | H8: Duração (Dias) | I8: VAL | J8: =WORKDAY(I7,1) -> 45658 | K8: =WORKDAY(J8,1) -> 45659 | L8: =WORKDAY(K8,1) -> 45660 | M8: =WORKDAY(L8,1) -> 45663 | N8: =WORKDAY(M8,1) -> 45664 | O8: =WORKDAY(N8,1) -> 45665 | P8: =WORKDAY(O8,1) -> 45666 | Q8: =WORKDAY(P8,1) -> 45667 | R8: =WORKDAY(Q8,1) -> 45670 | ... CQ8: =WORKDAY(CP8,1) -> 45777
C10: Gestão Projeto | F10: n.a. | G10: =H10*8*5 -> 0 | H10: =SUM(J10:M10) -> 0
C11: Gestão Projeto | F11: n.a. | G11: =H11*8*5 -> 12 | H11: =SUM(J11:M11) -> 0.3 | I11: =SUM(J11:M11)-H11 -> 0 | K11: 0.1 | L11: 0.1 | M11: 0.1 | N11: 0.1 | O11: 0.1 | P11: 0.1 | Q11: 0.1 | R11: 0.1 | S11: 0.1 | T11: 0.1 | U11: 0.1 | V11: 0.1 | W11: 0.1 | X11: 0.1 | Y11: 0.1 | Z11: 0.1 | AA11: 0.1 | AB11: 0.1 | AC11: 0.1 | AD11: 0.1 | AE11: 0.1 | AF11: 0.1 | AG11: 0.1 | AH11: 0.1 | AI11: 0.1 | AJ11: 0.1 | AK11: 0.1 | AL11: 0.1 | AM11: 0.1 | AN11: 0.1 | AO11: 0.1 | AP11: 0.1 | AQ11: 0.1 | AR11: 0.1 | AS11: 0.1 | AT11: 0.1 | AU11: 0.1 | AV11: 0.1 | AW11: 0.1 | AX11: 0.1 | AY11: 0.1 | AZ11: 0.1 | BA11: 0.1 | BC11: 0.1 | BD11: 0.1 | BE11: 0.1 | BF11: 0.1 | BG11: 0.1 | BH11: 0.1 | BI11: 0.1 | BJ11: 0.1 | BK11: 0.1 | BL11: 0.1 | BM11: 0.1 | BN11: 0.1 | BO11: 0.1 | BP11: 0.1 | BQ11: 0.1 | BR11: 0.1 | BS11: 0.1 | BT11: 0.1 | BU11: 0.1 | BV11: 0.1 | BW11: 0.1 | BX11: 0.1 | BY11: 0.1 | BZ11: 0.1 | CA11: 0.1 | CB11: 0.1 | CC11: 0.1 | CD11: 0.1 | CE11: 0.1 | CF11: 0.1 | CG11: 0.1 | CH11: 0.1 | CJ11: 0.1 | CK11: 0.1 | CL11: 0.1 | CM11: 0.1 | CO11: 0.1 | CP11: 0.1 | CQ11: 0.1
C12: 1. Re-especificações + Simulação + Testes + Re-testes requisitos atuais) | G12: =SUM(G13:G15) -> 128 | H12: =ROUND(SUM(H13:H15),0) -> 16
C13: MunichRe | G13: 16 | H13: =ROUNDUP(G13/8,1) -> 2 | I13: 0 | K13: 3
C14: Gloval - Tabela intermédia | G14: 16 | H14: =ROUNDUP(G14/8,1) -> 2 | I14: 0 | L14: 3
C15: Re-testes | G15: =12*8 -> 96 | H15: =ROUNDUP(G15/8,1) -> 12 | I15: 0 | M15: 3 | N15: 3 | O15: 3 | P15: 3 | Q15: 3 | R15: 3 | S15: 3 | T15: 3 | U15: 3 | V15: 3 | W15: 3 | X15: 3
C16: 2. Novos Campos (Especificação + Simulação + Testes+ Re-testes) | F16: =F17+F66 -> 68 | G16: =G17+G66+G87+G156+G225 -> #N/A | H16: =H17+H66+H87+H156+H225 -> #N/A
C17: Especificação de Requisitos - P3 | F17: =COUNTA(E18:E65) -> 48 | G17: =SUM(G18:G55) -> #N/A | H17: =ROUND(SUM(H18:H55),0) -> #N/A
B18: =Table1[[#Headers],[Especificação]] -> Especificação | C18: =D18&"_"&E18 -> ENTITY_TXNMY_ELGBL_CAPEX_W | D18: ENTITY | E18: TXNMY_ELGBL_CAPEX_W | G18: =INDEX(Table1[[Especificação]:[Total Testes]],MATCH(PlanoV1.0!C18,Table1[CONCAT],0),MATCH(PlanoV1.0!B18,Table1[[#Headers],[Especificação]:[Total Testes]],0)) -> #N/A | H18: =ROUNDUP(G18/8,1) -> #N/A | I18: =SUM(J18:CQ18)-H18 -> #N/A | Y18: 1
B19: =Table1[[#Headers],[Especificação]] -> Especificação | C19: =D19&"_"&E19 -> ENTITY_TXNMY_ELGBL_TRNVR_W | D19: ENTITY | E19: TXNMY_ELGBL_TRNVR_W | G19: =INDEX(Table1[[Especificação]:[Total Testes]],MATCH(PlanoV1.0!C19,Table1[CONCAT],0),MATCH(PlanoV1.0!B19,Table1[[#Headers],[Especificação]:[Total Testes]],0)) -> #N/A | H19: =ROUNDUP(G19/8,1) -> #N/A | I19: =SUM(J19:CQ19)-H19 -> #N/A | Z19: 0.5
B20: =Table1[[#Headers],[Especificação]] -> Especificação | C20: =D20&"_"&E20 -> ENTITY_TXNMY_ELGBL_CAPEX_P | D20: ENTITY | E20: TXNMY_ELGBL_CAPEX_P | G20: =INDEX(Table1[[Especificação]:[Total Testes]],MATCH(PlanoV1.0!C20,Table1[CONCAT],0),MATCH(PlanoV1.0!B20,Table1[[#Headers],[Especificação]:[Total Testes]],0)) -> #N/A | H20: =ROUNDUP(G20/8,1) -> #N/A | I20: =SUM(J20:CQ20)-H20 -> #N/A | Z20: 0.3
B21: =Table1[[#Headers],[Especificação]] -> Especificação | C21: =D21&"_"&E21 -> ENTITY_TXNMY_ELGBL_TRNVR_P | D21: ENTITY | E21: TXNMY_ELGBL_TRNVR_P | G21: =INDEX(Table1[[Especificação]:[Total Testes]],MATCH(PlanoV1.0!C21,Table1[CONCAT],0),MATCH(PlanoV1.0!B21,Table1[[#Headers],[Especificação]:[Total Testes]],0)) -> #N/A | H21: =ROUNDUP(G21/8,1) -> #N/A | I21: =SUM(J21:CQ21)-H21 -> #N/A | Z21: 0.2 | AA21: 0.1
B22: =Table1[[#Headers],[Especificação]] -> Especificação | C22: =D22&"_"&E22 -> ENTITY_TXNMY_ELGBL_CAPEX_B | D22: ENTITY | E22: TXNMY_ELGBL_CAPEX_B | G22: =INDEX(Table1[[Especificação]:[Total Testes]],MATCH(PlanoV1.0!C22,Table1[CONCAT],0),MATCH(PlanoV1.0!B22,Table1[[#Headers],[Especificação]:[Total Testes]],0)) -> #N/A | H22: =ROUNDUP(G22/8,1) -> #N/A | I22: =SUM(J22:CQ22)-H22 -> #N/A | AA22: 0.3
B23: =Table1[[#Headers],[Especificação]] -> Especificação | C23: =D23&"_"&E23 -> ENTITY_TXNMY_ELGBL_TRNVR_B | D23: ENTITY | E23: TXNMY_ELGBL_TRNVR_B | G23: =INDEX(Table1[[Especificação]:[Total Testes]],MATCH(PlanoV1.0!C23,Table1[CONCAT],0),MATCH(PlanoV1.0!B23,Table1[[#Headers],[Especificação]:[Total Testes]],0)) -> #N/A | H23: =ROUNDUP(G23/8,1) -> #N/A | I23: =SUM(J23:CQ23)-H23 -> #N/A | AA23: 0.3
B24: =Table1[[#Headers],[Especificação]] -> Especificação | C24: =D24&"_"&E24 -> ENTITY_TXNMY_ELGBL_CAPEX_CE | D24: ENTITY | E24: TXNMY_ELGBL_CAPEX_CE | G24: =INDEX(Table1[[Especificação]:[Total Testes]],MATCH(PlanoV1.0!C24,Table1[CONCAT],0),MATCH(PlanoV1.0!B24,Table1[[#Headers],[Especificação]:[Total Testes]],0)) -> #N/A | H24: =ROUNDUP(G24/8,1) -> #N/A | I24: =SUM(J24:CQ24)-H24 -> #N/A | AA24: 0.2
B25: =Table1[[#Headers],[Especificação]] -> Especificação | C25: =D25&"_"&E25 -> ENTITY_TXNMY_ELGBL_TRNVR_CE | D25: ENTITY | E25: TXNMY_ELGBL_TRNVR_CE | G25: =INDEX(Table1[[Especificação]:[Total Testes]],MATCH(PlanoV1.0!C25,Table1[CONCAT],0),MATCH(PlanoV1.0!B25,Table1[[#Headers],[Especificação]:[Total Testes]],0)) -> #N/A | H25: =ROUNDUP(G25/8,1) -> #N/A | I25: =SUM(J25:CQ25)-H25 -> #N/A | AA25: 0.1 | AB25: 0.1
B26: =Table1[[#Headers],[Especificação]] -> Especificação | C26: =D26&"_"&E26 -> ENTITY_PURE_CAPEX_P | D26: ENTITY | E26: PURE_CAPEX_P | G26: =INDEX(Table1[[Especificação]:[Total Testes]],MATCH(PlanoV1.0!C26,Table1[CONCAT],0),MATCH(PlanoV1.0!B26,Table1[[#Headers],[Especificação]:[Total Testes]],0)) -> #N/A | H26: =ROUNDUP(G26/8,1) -> #N/A | I26: =SUM(J26:CQ26)-H26 -> #N/A | AB26: 0.2
B27: =Table1[[#Headers],[Especificação]] -> Especificação | C27: =D27&"_"&E27 -> ENTITY_PURE_TRNVR_P | D27: ENTITY | E27: PURE_TRNVR_P | G27: =INDEX(Table1[[Especificação]:[Total Testes]],MATCH(PlanoV1.0!C27,Table1[CONCAT],0),MATCH(PlanoV1.0!B27,Table1[[#Headers],[Especificação]:[Total Testes]],0)) -> #N/A | H27: =ROUNDUP(G27/8,1) -> #N/A | I27: =SUM(J27:CQ27)-H27 -> #N/A | AB27: 0.2
B28: =Table1[[#Headers],[Especificação]] -> Especificação | C28: =D28&"_"&E28 -> ENTITY_PURE_CAPEX_B | D28: ENTITY | E28: PURE_CAPEX_B | G28: =INDEX(Table1[[Especificação]:[Total Testes]],MATCH(PlanoV1.0!C28,Table1[CONCAT],0),MATCH(PlanoV1.0!B28,Table1[[#Headers],[Especificação]:[Total Testes]],0)) -> #N/A | H28: =ROUNDUP(G28/8,1) -> #N/A | I28: =SUM(J28:CQ28)-H28 -> #N/A | AB28: 0.2
B29: =Table1[[#Headers],[Especificação]] -> Especificação | C29: =D29&"_"&E29 -> ENTITY_PURE_TRNVR_B | D29: ENTITY | E29: PURE_TRNVR_B | G29: =INDEX(Table1[[Especificação]:[Total Testes]],MATCH(PlanoV1.0!C29,Table1[CONCAT],0),MATCH(PlanoV1.0!B29,Table1[[#Headers],[Especificação]:[Total Testes]],0)) -> #N/A | H29: =ROUNDUP(G29/8,1) -> #N/A | I29: =SUM(J29:CQ29)-H29 -> #N/A | AB29: 0.2
B30: =Table1[[#Headers],[Especificação]] -> Especificação | C30: =D30&"_"&E30 -> ENTITY_PURE_CAPEX_W | D30: ENTITY | E30: PURE_CAPEX_W | G30: =INDEX(Table1[[Especificação]:[Total Testes]],MATCH(PlanoV1.0!C30,Table1[CONCAT],0),MATCH(PlanoV1.0!B30,Table1[[#Headers],[Especificação]:[Total Testes]],0)) -> #N/A | H30: =ROUNDUP(G30/8,1) -> #N/A | I30: =SUM(J30:CQ30)-H30 -> #N/A | AB30: 0.1 | AC30: 0.1
B31: =Table1[[#Headers],[Especificação]] -> Especificação | C31: =D31&"_"&E31 -> ENTITY_PURE_TRNVR_W | D31: ENTITY | E31: PURE_TRNVR_W | G31: =INDEX(Table1[[Especificação]:[Total Testes]],MATCH(PlanoV1.0!C31,Table1[CONCAT],0),MATCH(PlanoV1.0!B31,Table1[[#Headers],[Especificação]:[Total Testes]],0)) -> #N/A | H31: =ROUNDUP(G31/8,1) -> #N/A | I31: =SUM(J31:CQ31)-H31 -> #N/A | AC31: 0.2
B32: =Table1[[#Headers],[Especificação]] -> Especificação | C32: =D32&"_"&E32 -> ENTITY_PURE_CAPEX_CE | D32: ENTITY | E32: PURE_CAPEX_CE | G32: =INDEX(Table1[[Especificação]:[Total Testes]],MATCH(PlanoV1.0!C32,Table1[CONCAT],0),MATCH(PlanoV1.0!B32,Table1[[#Headers],[Especificação]:[Total Testes]],0)) -> #N/A | H32: =ROUNDUP(G32/8,1) -> #N/A | I32: =SUM(J32:CQ32)-H32 -> #N/A | AC32: 0.2
B33: =Table1[[#Headers],[Especificação]] -> Especificação | C33: =D33&"_"&E33 -> ENTITY_PURE_TRNVR_CE | D33: ENTITY | E33: PURE_TRNVR_CE | G33: =INDEX(Table1[[Especificação]:[Total Testes]],MATCH(PlanoV1.0!C33,Table1[CONCAT],0),MATCH(PlanoV1.0!B33,Table1[[#Headers],[Especificação]:[Total Testes]],0)) -> #N/A | H33: =ROUNDUP(G33/8,1) -> #N/A | I33: =SUM(J33:CQ33)-H33 -> #N/A | AC33: 0.2
B34: =Table1[[#Headers],[Especificação]] -> Especificação | C34: =D34&"_"&E34 -> ENTITY_ENBLNG_CAPEX_W | D34: ENTITY | E34: ENBLNG_CAPEX_W | G34: =INDEX(Table1[[Especificação]:[Total Testes]],MATCH(PlanoV1.0!C34,Table1[CONCAT],0),MATCH(PlanoV1.0!B34,Table1[[#Headers],[Especificação]:[Total Testes]],0)) -> #N/A | H34: =ROUNDUP(G34/8,1) -> #N/A | I34: =SUM(J34:CQ34)-H34 -> #N/A | AC34: 0.2
B35: =Table1[[#Headers],[Especificação]] -> Especificação | C35: =D35&"_"&E35 -> ENTITY_ENBLNG_TRNVR_W | D35: ENTITY | E35: ENBLNG_TRNVR_W | G35: =INDEX(Table1[[Especificação]:[Total Testes]],MATCH(PlanoV1.0!C35,Table1[CONCAT],0),MATCH(PlanoV1.0!B35,Table1[[#Headers],[Especificação]:[Total Testes]],0)) -> #N/A | H35: =ROUNDUP(G35/8,1) -> #N/A | I35: =SUM(J35:CQ35)-H35 -> #N/A | AC35: 0.1 | AD35: 0.1
B36: =Table1[[#Headers],[Especificação]] -> Especificação | C36: =D36&"_"&E36 -> ENTITY_ENBLNG_CAPEX_CE | D36: ENTITY | E36: ENBLNG_CAPEX_CE | G36: =INDEX(Table1[[Especificação]:[Total Testes]],MATCH(PlanoV1.0!C36,Table1[CONCAT],0),MATCH(PlanoV1.0!B36,Table1[[#Headers],[Especificação]:[Total Testes]],0)) -> #N/A | H36: =ROUNDUP(G36/8,1) -> #N/A | I36: =SUM(J36:CQ36)-H36 -> #N/A | AD36: 0.2
B37: =Table1[[#Headers],[Especificação]] -> Especificação | C37: =D37&"_"&E37 -> ENTITY_ENBLNG_TRNVR_CE | D37: ENTITY | E37: ENBLNG_TRNVR_CE | G37: =INDEX(Table1[[Especificação]:[Total Testes]],MATCH(PlanoV1.0!C37,Table1[CONCAT],0),MATCH(PlanoV1.0!B37,Table1[[#Headers],[Especificação]:[Total Testes]],0)) -> #N/A | H37: =ROUNDUP(G37/8,1) -> #N/A | I37: =SUM(J37:CQ37)-H37 -> #N/A | AD37: 0.2
B38: =Table1[[#Headers],[Especificação]] -> Especificação | C38: =D38&"_"&E38 -> INSTRUMENT_TYP_OFF_BLNC_PRDCT | D38: INSTRUMENT | E38: TYP_OFF_BLNC_PRDCT | G38: =INDEX(Table1[[Especificação]:[Total Testes]],MATCH(PlanoV1.0!C38,Table1[CONCAT],0),MATCH(PlanoV1.0!B38,Table1[[#Headers],[Especificação]:[Total Testes]],0)) -> 1 | H38: =ROUNDUP(G38/8,1) -> 0.2 | I38: =SUM(J38:CQ38)-H38 -> 0 | AD38: 0.2
B39: =Table1[[#Headers],[Especificação]] -> Especificação | C39: =D39&"_"&E39 -> INSTRUMENT_FLG_MNMM_SFGRDS | D39: INSTRUMENT | E39: FLG_MNMM_SFGRDS | G39: =INDEX(Table1[[Especificação]:[Total Testes]],MATCH(PlanoV1.0!C39,Table1[CONCAT],0),MATCH(PlanoV1.0!B39,Table1[[#Headers],[Especificação]:[Total Testes]],0)) -> #N/A | H39: =ROUNDUP(G39/8,1) -> #N/A | I39: =SUM(J39:CQ39)-H39 -> #N/A | Y39: 1.3
B40: =Table1[[#Headers],[Especificação]] -> Especificação | C40: =D40&"_"&E40 -> INSTR_PROTECTION_TYP_RLTN | D40: INSTR_PROTECTION | E40: TYP_RLTN | G40: =INDEX(Table1[[Especificação]:[Total Testes]],MATCH(PlanoV1.0!C40,Table1[CONCAT],0),MATCH(PlanoV1.0!B40,Table1[[#Headers],[Especificação]:[Total Testes]],0)) -> 0 | H40: =ROUNDUP(G40/8,1) -> 0 | I40: =SUM(J40:CQ40)-H40 -> 0.5 | Y40: 0.5
B41: =Table1[[#Headers],[Especificação]] -> Especificação | C41: =D41&"_"&E41 -> PROTECTION_BLDNG_AR | D41: PROTECTION | E41: BLDNG_AR | G41: =INDEX(Table1[[Especificação]:[Total Testes]],MATCH(PlanoV1.0!C41,Table1[CONCAT],0),MATCH(PlanoV1.0!B41,Table1[[#Headers],[Especificação]:[Total Testes]],0)) -> #N/A | H41: =ROUNDUP(G41/8,1) -> #N/A | I41: =SUM(J41:CQ41)-H41 -> #N/A | AD41: 0.3
B42: =Table1[[#Headers],[Especificação]] -> Especificação | C42: =D42&"_"&E42 -> PROTECTION_RL_ESTT_CRTFCTN | D42: PROTECTION | E42: RL_ESTT_CRTFCTN | G42: =INDEX(Table1[[Especificação]:[Total Testes]],MATCH(PlanoV1.0!C42,Table1[CONCAT],0),MATCH(PlanoV1.0!B42,Table1[[#Headers],[Especificação]:[Total Testes]],0)) -> #N/A | H42: =ROUNDUP(G42/8,1) -> #N/A | I42: =SUM(J42:CQ42)-H42 -> #N/A | Z42: 1
B43: =Table1[[#Headers],[Especificação]] -> Especificação | C43: =D43&"_"&E43 -> PROTECTION_TYP_VHCL | D43: PROTECTION | E43: TYP_VHCL | G43: =INDEX(Table1[[Especificação]:[Total Testes]],MATCH(PlanoV1.0!C43,Table1[CONCAT],0),MATCH(PlanoV1.0!B43,Table1[[#Headers],[Especificação]:[Total Testes]],0)) -> #N/A | H43: =ROUNDUP(G43/8,1) -> #N/A | I43: =SUM(J43:CQ43)-H43 -> #N/A | Z43: 1
B44: =Table1[[#Headers],[Especificação]] -> Especificação | C44: =D44&"_"&E44 -> PROTECTION_DT_RGSTRTN | D44: PROTECTION | E44: DT_RGSTRTN | G44: =INDEX(Table1[[Especificação]:[Total Testes]],MATCH(PlanoV1.0!C44,Table1[CONCAT],0),MATCH(PlanoV1.0!B44,Table1[[#Headers],[Especificação]:[Total Testes]],0)) -> #N/A | H44: =ROUNDUP(G44/8,1) -> #N/A | I44: =SUM(J44:CQ44)-H44 -> #N/A | AA44: 1
B45: =Table1[[#Headers],[Especificação]] -> Especificação | C45: =D45&"_"&E45 -> PROTECTION_PRMRY_ENRGY_DMND_NN_RNWBL | D45: PROTECTION | E45: PRMRY_ENRGY_DMND_NN_RNWBL | G45: =INDEX(Table1[[Especificação]:[Total Testes]],MATCH(PlanoV1.0!C45,Table1[CONCAT],0),MATCH(PlanoV1.0!B45,Table1[[#Headers],[Especificação]:[Total Testes]],0)) -> #N/A | H45: =ROUNDUP(G45/8,1) -> #N/A | I45: =SUM(J45:CQ45)-H45 -> #N/A | AB45: 1.3
B46: =Table1[[#Headers],[Especificação]] -> Especificação | C46: =D46&"_"&E46 -> PROTECTION_PRMRY_ENRGY_DMND_TTL | D46: PROTECTION | E46: PRMRY_ENRGY_DMND_TTL | G46: =INDEX(Table1[[Especificação]:[Total Testes]],MATCH(PlanoV1.0!C46,Table1[CONCAT],0),MATCH(PlanoV1.0!B46,Table1[[#Headers],[Especificação]:[Total Testes]],0)) -> #N/A | H46: =ROUNDUP(G46/8,1) -> #N/A | I46: =SUM(J46:CQ46)-H46 -> #N/A | AA46: 1
B47: =Table1[[#Headers],[Especificação]] -> Especificação | C47: =D47&"_"&E47 -> PROTECTION_PRMRY_ENRGY_DMND_RFRNC_VL | D47: PROTECTION | E47: PRMRY_ENRGY_DMND_RFRNC_VL | G47: =INDEX(Table1[[Especificação]:[Total Testes]],MATCH(PlanoV1.0!C47,Table1[CONCAT],0),MATCH(PlanoV1.0!B47,Table1[[#Headers],[Especificação]:[Total Testes]],0)) -> #N/A | H47: =ROUNDUP(G47/8,1) -> #N/A | I47: =SUM(J47:CQ47)-H47 -> #N/A | AC47: 1
B48: =Table1[[#Headers],[Especificação]] -> Especificação | C48: =D48&"_"&E48 -> PROTECTION_RL_ESTT_CLMT_ZN | D48: PROTECTION | E48: RL_ESTT_CLMT_ZN | G48: =INDEX(Table1[[Especificação]:[Total Testes]],MATCH(PlanoV1.0!C48,Table1[CONCAT],0),MATCH(PlanoV1.0!B48,Table1[[#Headers],[Especificação]:[Total Testes]],0)) -> #N/A | H48: =ROUNDUP(G48/8,1) -> #N/A | I48: =SUM(J48:CQ48)-H48 -> #N/A | AC48: 0.9 | AD48: 0.1
B49: =Table1[[#Headers],[Especificação]] -> Especificação | C49: =D49&"_"&E49 -> INSTR_ACTIVITY_COD_SOC | D49: INSTR_ACTIVITY | E49: COD_SOC | G49: =INDEX(Table1[[Especificação]:[Total Testes]],MATCH(PlanoV1.0!C49,Table1[CONCAT],0),MATCH(PlanoV1.0!B49,Table1[[#Headers],[Especificação]:[Total Testes]],0)) -> 0 | H49: =ROUNDUP(G49/8,1) -> 0 | I49: =SUM(J49:CQ49)-H49 -> 0.3 | AB49: 0.3
B50: =Table1[[#Headers],[Especificação]] -> Especificação | C50: =D50&"_"&E50 -> INSTR_ACTIVITY_DT_RFRNC | D50: INSTR_ACTIVITY | E50: DT_RFRNC | G50: =INDEX(Table1[[Especificação]:[Total Testes]],MATCH(PlanoV1.0!C50,Table1[CONCAT],0),MATCH(PlanoV1.0!B50,Table1[[#Headers],[Especificação]:[Total Testes]],0)) -> 0 | H50: =ROUNDUP(G50/8,1) -> 0 | I50: =SUM(J50:CQ50)-H50 -> 0.2 | Y50: 0.2
B51: =Table1[[#Headers],[Especificação]] -> Especificação | C51: =D51&"_"&E51 -> INSTR_ACTIVITY_INSTRMNT_ID | D51: INSTR_ACTIVITY | E51: INSTRMNT_ID | G51: =INDEX(Table1[[Especificação]:[Total Testes]],MATCH(PlanoV1.0!C51,Table1[CONCAT],0),MATCH(PlanoV1.0!B51,Table1[[#Headers],[Especificação]:[Total Testes]],0)) -> 0 | H51: =ROUNDUP(G51/8,1) -> 0 | I51: =SUM(J51:CQ51)-H51 -> 0.3 | AD51: 0.3
B52: =Table1[[#Headers],[Especificação]] -> Especificação | C52: =D52&"_"&E52 -> INSTR_ACTIVITY_PRCNTG_ACTVTY | D52: INSTR_ACTIVITY | E52: PRCNTG_ACTVTY | G52: =INDEX(Table1[[Especificação]:[Total Testes]],MATCH(PlanoV1.0!C52,Table1[CONCAT],0),MATCH(PlanoV1.0!B52,Table1[[#Headers],[Especificação]:[Total Testes]],0)) -> 1 | H52: =ROUNDUP(G52/8,1) -> 0.2 | I52: =SUM(J52:CQ52)-H52 -> 0.3 | AB52: 0.4 | AC52: 0.1
B53: =Table1[[#Headers],[Especificação]] -> Especificação | C53: =D53&"_"&E53 -> INSTR_ACTIVITY_FLG_SBSTNTL_CNTRBTN | D53: INSTR_ACTIVITY | E53: FLG_SBSTNTL_CNTRBTN | G53: =INDEX(Table1[[Especificação]:[Total Testes]],MATCH(PlanoV1.0!C53,Table1[CONCAT],0),MATCH(PlanoV1.0!B53,Table1[[#Headers],[Especificação]:[Total Testes]],0)) -> #N/A | H53: =ROUNDUP(G53/8,1) -> #N/A | I53: =SUM(J53:CQ53)-H53 -> #N/A | AD53: 0.5
B54: =Table1[[#Headers],[Especificação]] -> Especificação | C54: =D54&"_"&E54 -> INSTR_ACTIVITY_FLG_DNSH_CMPLNC | D54: INSTR_ACTIVITY | E54: FLG_DNSH_CMPLNC | G54: =INDEX(Table1[[Especificação]:[Total Testes]],MATCH(PlanoV1.0!C54,Table1[CONCAT],0),MATCH(PlanoV1.0!B54,Table1[[#Headers],[Especificação]:[Total Testes]],0)) -> #N/A | H54: =ROUNDUP(G54/8,1) -> #N/A | I54: =SUM(J54:CQ54)-H54 -> #N/A | AD54: 0.1 | AE54: 1.2
B55: =Table1[[#Headers],[Especificação]] -> Especificação | C55: =D55&"_"&E55 -> INSTR_ACTIVITY_DNSH_DTL | D55: INSTR_ACTIVITY | E55: DNSH_DTL | G55: =INDEX(Table1[[Especificação]:[Total Testes]],MATCH(PlanoV1.0!C55,Table1[CONCAT],0),MATCH(PlanoV1.0!B55,Table1[[#Headers],[Especificação]:[Total Testes]],0)) -> #N/A | H55: =ROUNDUP(G55/8,1) -> #N/A | I55: =SUM(J55:CQ55)-H55 -> #N/A | AD55: 1
B56: =Table1[[#Headers],[Especificação]] -> Especificação | C56: =D56&"_"&E56 -> INSTR_ACTIVITY_ENTTY_NM | D56: INSTR_ACTIVITY | E56: ENTTY_NM | G56: 2 | H56: =ROUNDUP(G56/8,1) -> 0.3 | I56: =SUM(J56:CQ56)-H56 -> 0 | AE56: 0.3
B57: =Table1[[#Headers],[Especificação]] -> Especificação | C57: =D57&"_"&E57 -> INSTR_ACTIVITY_EC_GRP_NM | D57: INSTR_ACTIVITY | E57: EC_GRP_NM | G57: 2 | H57: =ROUNDUP(G57/8,1) -> 0.3 | I57: =SUM(J57:CQ57)-H57 -> 0 | AE57: 0.3
B58: =Table1[[#Headers],[Especificação]] -> Especificação | C58: =D58&"_"&E58 -> INSTR_ACTIVITY_FRBRNC_STTS_INSTRMNT | D58: INSTR_ACTIVITY | E58: FRBRNC_STTS_INSTRMNT | G58: 1 | H58: =ROUNDUP(G58/8,1) -> 0.2 | I58: =SUM(J58:CQ58)-H58 -> 0 | AE58: 0.2
B59: =Table1[[#Headers],[Especificação]] -> Especificação | C59: =D59&"_"&E59 -> INSTR_ACTIVITY_IFRS9_BHVRL_MTRTY | D59: INSTR_ACTIVITY | E59: IFRS9_BHVRL_MTRTY | G59: 1 | H59: =ROUNDUP(G59/8,1) -> 0.2 | I59: =SUM(J59:CQ59)-H59 -> 0 | AE59: 0.2
B60: =Table1[[#Headers],[Especificação]] -> Especificação | C60: =D60&"_"&E60 -> INSTR_ACTIVITY_LTV | D60: INSTR_ACTIVITY | E60: LTV | G60: 1 | H60: =ROUNDUP(G60/8,1) -> 0.2 | I60: =SUM(J60:CQ60)-H60 -> 0 | AE60: 0.2
B61: =Table1[[#Headers],[Especificação]] -> Especificação | C61: =D61&"_"&E61 -> INSTR_ACTIVITY_LTV_INCPTN | D61: INSTR_ACTIVITY | E61: LTV_INCPTN | G61: 1 | H61: =ROUNDUP(G61/8,1) -> 0.2 | I61: =SUM(J61:CQ61)-H61 -> 0 | AE61: 0.2
B62: =Table1[[#Headers],[Especificação]] -> Especificação | C62: =D62&"_"&E62 -> INSTR_ACTIVITY_ANNLSD_AGRD_RT | D62: INSTR_ACTIVITY | E62: ANNLSD_AGRD_RT | G62: 1 | H62: =ROUNDUP(G62/8,1) -> 0.2 | I62: =SUM(J62:CQ62)-H62 -> 0 | AE62: 0.2
B63: =Table1[[#Headers],[Especificação]] -> Especificação | C63: =D63&"_"&E63 -> INSTR_ACTIVITY_EIR_INCPTN | D63: INSTR_ACTIVITY | E63: EIR_INCPTN | G63: 1 | H63: =ROUNDUP(G63/8,1) -> 0.2 | I63: =SUM(J63:CQ63)-H63 -> 0 | AE63: 0.2
B64: =Table1[[#Headers],[Especificação]] -> Especificação | C64: =D64&"_"&E64 -> INSTR_ACTIVITY_NW_BSNSS | D64: INSTR_ACTIVITY | E64: NW_BSNSS | G64: 8 | H64: =ROUNDUP(G64/8,1) -> 1 | I64: =SUM(J64:CQ64)-H64 -> 0 | AF64: 1
B65: =Table1[[#Headers],[Especificação]] -> Especificação | C65: =D65&"_"&E65 -> INSTR_ACTIVITY_YR_CNSTRCTN | D65: INSTR_ACTIVITY | E65: YR_CNSTRCTN | G65: 1 | H65: =ROUNDUP(G65/8,1) -> 0.2 | I65: =SUM(J65:CQ65)-H65 -> 0 | AF65: 0.2
C66: Especificação de Requisitos - ESG Risks | F66: =+COUNTA(E67:E86) -> 20 | G66: =SUM(G67:G78) -> #N/A | H66: =ROUND(SUM(H67:H78),0) -> #N/A
B67: =Table1[[#Headers],[Especificação]] -> Especificação | C67: =D67&"_"&E67 -> ENTITY_GRP_ECNMC_ACTVTY | D67: ENTITY | E67: GRP_ECNMC_ACTVTY | G67: =INDEX(Table1[[Especificação]:[Total Testes]],MATCH(PlanoV1.0!C67,Table1[CONCAT],0),MATCH(PlanoV1.0!B67,Table1[[#Headers],[Especificação]:[Total Testes]],0)) -> #N/A | H67: =ROUNDUP(G67/8,1) -> #N/A | I67: =SUM(J67:CQ67)-H67 -> #N/A | AF67: 0.3
B68: =Table1[[#Headers],[Especificação]] -> Especificação | C68: =D68&"_"&E68 -> PROTECTION_TYP_EMSSNS_LBL | D68: PROTECTION | E68: TYP_EMSSNS_LBL | G68: =INDEX(Table1[[Especificação]:[Total Testes]],MATCH(PlanoV1.0!C68,Table1[CONCAT],0),MATCH(PlanoV1.0!B68,Table1[[#Headers],[Especificação]:[Total Testes]],0)) -> #N/A | H68: =ROUNDUP(G68/8,1) -> #N/A | I68: =SUM(J68:CQ68)-H68 -> #N/A | AF68: 0.5
B69: =Table1[[#Headers],[Especificação]] -> Especificação | C69: =D69&"_"&E69 -> PROTECTION_EPC_EMSSNS_LBL | D69: PROTECTION | E69: EPC_EMSSNS_LBL | G69: =INDEX(Table1[[Especificação]:[Total Testes]],MATCH(PlanoV1.0!C69,Table1[CONCAT],0),MATCH(PlanoV1.0!B69,Table1[[#Headers],[Especificação]:[Total Testes]],0)) -> #N/A | H69: =ROUNDUP(G69/8,1) -> #N/A | I69: =SUM(J69:CQ69)-H69 -> #N/A | AG69: 0.3
B70: =Table1[[#Headers],[Especificação]] -> Especificação | C70: =D70&"_"&E70 -> PROTECTION_VHCL_EMSSNS_LBL | D70: PROTECTION | E70: VHCL_EMSSNS_LBL | G70: =INDEX(Table1[[Especificação]:[Total Testes]],MATCH(PlanoV1.0!C70,Table1[CONCAT],0),MATCH(PlanoV1.0!B70,Table1[[#Headers],[Especificação]:[Total Testes]],0)) -> #N/A | H70: =ROUNDUP(G70/8,1) -> #N/A | I70: =SUM(J70:CQ70)-H70 -> #N/A | AF70: 1
B71: =Table1[[#Headers],[Especificação]] -> Especificação | C71: =D71&"_"&E71 -> PROTECTION_TYP_EMSSNS_SCR | D71: PROTECTION | E71: TYP_EMSSNS_SCR | G71: =INDEX(Table1[[Especificação]:[Total Testes]],MATCH(PlanoV1.0!C71,Table1[CONCAT],0),MATCH(PlanoV1.0!B71,Table1[[#Headers],[Especificação]:[Total Testes]],0)) -> #N/A | H71: =ROUNDUP(G71/8,1) -> #N/A | I71: =SUM(J71:CQ71)-H71 -> #N/A | AG71: 0.3
B72: =Table1[[#Headers],[Especificação]] -> Especificação | C72: =D72&"_"&E72 -> PROTECTION_EPC_EMSSNS_SCR | D72: PROTECTION | E72: EPC_EMSSNS_SCR | G72: =INDEX(Table1[[Especificação]:[Total Testes]],MATCH(PlanoV1.0!C72,Table1[CONCAT],0),MATCH(PlanoV1.0!B72,Table1[[#Headers],[Especificação]:[Total Testes]],0)) -> #N/A | H72: =ROUNDUP(G72/8,1) -> #N/A | I72: =SUM(J72:CQ72)-H72 -> #N/A | AG72: 0.5
B73: =Table1[[#Headers],[Especificação]] -> Especificação | C73: =D73&"_"&E73 -> PROTECTION_VHCL_EMSSNS_SCR | D73: PROTECTION | E73: VHCL_EMSSNS_SCR | G73: =INDEX(Table1[[Especificação]:[Total Testes]],MATCH(PlanoV1.0!C73,Table1[CONCAT],0),MATCH(PlanoV1.0!B73,Table1[[#Headers],[Especificação]:[Total Testes]],0)) -> #N/A | H73: =ROUNDUP(G73/8,1) -> #N/A | I73: =SUM(J73:CQ73)-H73 -> #N/A | AG73: 0.9 | AH73: 0.4
B74: =Table1[[#Headers],[Especificação]] -> Especificação | C74: =D74&"_"&E74 -> PROTECTION_INSRNC_ID | D74: PROTECTION | E74: INSRNC_ID | G74: =INDEX(Table1[[Especificação]:[Total Testes]],MATCH(PlanoV1.0!C74,Table1[CONCAT],0),MATCH(PlanoV1.0!B74,Table1[[#Headers],[Especificação]:[Total Testes]],0)) -> #N/A | H74: =ROUNDUP(G74/8,1) -> #N/A | I74: =SUM(J74:CQ74)-H74 -> #N/A | AH74: 1.3
B75: =Table1[[#Headers],[Especificação]] -> Especificação | C75: =D75&"_"&E75 -> PROTECTION_TYP_HZRDS_INSRD | D75: PROTECTION | E75: TYP_HZRDS_INSRD | G75: =INDEX(Table1[[Especificação]:[Total Testes]],MATCH(PlanoV1.0!C75,Table1[CONCAT],0),MATCH(PlanoV1.0!B75,Table1[[#Headers],[Especificação]:[Total Testes]],0)) -> #N/A | H75: =ROUNDUP(G75/8,1) -> #N/A | I75: =SUM(J75:CQ75)-H75 -> #N/A | AH75: 0.3 | AI75: 0.2
B76: =Table1[[#Headers],[Especificação]] -> Especificação | C76: =D76&"_"&E76 -> PROTECTION_AMNT_CVRD_INSRNC | D76: PROTECTION | E76: AMNT_CVRD_INSRNC | G76: =INDEX(Table1[[Especificação]:[Total Testes]],MATCH(PlanoV1.0!C76,Table1[CONCAT],0),MATCH(PlanoV1.0!B76,Table1[[#Headers],[Especificação]:[Total Testes]],0)) -> #N/A | H76: =ROUNDUP(G76/8,1) -> #N/A | I76: =SUM(J76:CQ76)-H76 -> #N/A | AI76: 1.3
B77: =Table1[[#Headers],[Especificação]] -> Especificação | C77: =D77&"_"&E77 -> PROTECTION_DT_MTRTY_INSRNC | D77: PROTECTION | E77: DT_MTRTY_INSRNC | G77: =INDEX(Table1[[Especificação]:[Total Testes]],MATCH(PlanoV1.0!C77,Table1[CONCAT],0),MATCH(PlanoV1.0!B77,Table1[[#Headers],[Especificação]:[Total Testes]],0)) -> #N/A | H77: =ROUNDUP(G77/8,1) -> #N/A | I77: =SUM(J77:CQ77)-H77 -> #N/A | AI77: 0.5 | AJ77: 0.8
B78: =Table1[[#Headers],[Especificação]] -> Especificação | C78: =D78&"_"&E78 -> PROTECTION_FLG_FRST_HM | D78: PROTECTION | E78: FLG_FRST_HM | G78: =INDEX(Table1[[Especificação]:[Total Testes]],MATCH(PlanoV1.0!C78,Table1[CONCAT],0),MATCH(PlanoV1.0!B78,Table1[[#Headers],[Especificação]:[Total Testes]],0)) -> #N/A | H78: =ROUNDUP(G78/8,1) -> #N/A | I78: =SUM(J78:CQ78)-H78 -> #N/A | AJ78: 0.5
B79: =Table1[[#Headers],[Especificação]] -> Especificação | C79: =D79&"_"&E79 -> PROTECTION_INTRNL_SGMNT | D79: PROTECTION | E79: INTRNL_SGMNT | G79: 2 | H79: =ROUNDUP(G79/8,1) -> 0.3 | I79: =SUM(J79:CQ79)-H79 -> 0 | AJ79: 0.3
B80: =Table1[[#Headers],[Especificação]] -> Especificação | C80: =D80&"_"&E80 -> PROTECTION_EAD | D80: PROTECTION | E80: EAD | G80: 2 | H80: =ROUNDUP(G80/8,1) -> 0.3 | I80: =SUM(J80:CQ80)-H80 -> 0 | AJ80: 0.3
B81: =Table1[[#Headers],[Especificação]] -> Especificação | C81: =D81&"_"&E81 -> PROTECTION_OFF_BLNC_SHT_AMNT_INSTRMNT | D81: PROTECTION | E81: OFF_BLNC_SHT_AMNT_INSTRMNT | G81: 2 | H81: =ROUNDUP(G81/8,1) -> 0.3 | I81: =SUM(J81:CQ81)-H81 -> 0 | AJ81: 0.1 | AK81: 0.2
B82: =Table1[[#Headers],[Especificação]] -> Especificação | C82: =D82&"_"&E82 -> PROTECTION_INTRNL_SGMNT_CAT_MSTA | D82: PROTECTION | E82: INTRNL_SGMNT_CAT_MSTA | G82: 2 | H82: =ROUNDUP(G82/8,1) -> 0.3 | I82: =SUM(J82:CQ82)-H82 -> 0 | AK82: 0.3
B83: =Table1[[#Headers],[Especificação]] -> Especificação | C83: =D83&"_"&E83 -> PROTECTION_INTRNL_SGMNT_CATGSUB | D83: PROTECTION | E83: INTRNL_SGMNT_CATGSUB | G83: 2 | H83: =ROUNDUP(G83/8,1) -> 0.3 | I83: =SUM(J83:CQ83)-H83 -> 0 | AK83: 0.3
B84: =Table1[[#Headers],[Especificação]] -> Especificação | C84: =D84&"_"&E84 -> PROTECTION_RL_ESTT_ADDRSS | D84: PROTECTION | E84: RL_ESTT_ADDRSS | G84: =INDEX(Table1[[Especificação]:[Total Testes]],MATCH(PlanoV1.0!C84,Table1[CONCAT],0),MATCH(PlanoV1.0!B84,Table1[[#Headers],[Especificação]:[Total Testes]],0)) -> #N/A | H84: =ROUNDUP(G84/8,1) -> #N/A | I84: =SUM(J84:CQ84)-H84 -> #N/A | AK84: 0.3
B85: =Table1[[#Headers],[Especificação]] -> Especificação | C85: =D85&"_"&E85 -> PROTECTION_RL_ESTT_CLLTRL_LCTN_INT | D85: PROTECTION | E85: RL_ESTT_CLLTRL_LCTN_INT | G85: =INDEX(Table1[[Especificação]:[Total Testes]],MATCH(PlanoV1.0!C85,Table1[CONCAT],0),MATCH(PlanoV1.0!B85,Table1[[#Headers],[Especificação]:[Total Testes]],0)) -> #N/A | H85: =ROUNDUP(G85/8,1) -> #N/A | I85: =SUM(J85:CQ85)-H85 -> #N/A | AK85: 0.3
B86: =Table1[[#Headers],[Especificação]] -> Especificação | C86: =D86&"_"&E86 -> PROTECTION_RL_ESTT_CTY | D86: PROTECTION | E86: RL_ESTT_CTY | G86: =INDEX(Table1[[Especificação]:[Total Testes]],MATCH(PlanoV1.0!C86,Table1[CONCAT],0),MATCH(PlanoV1.0!B86,Table1[[#Headers],[Especificação]:[Total Testes]],0)) -> #N/A | H86: =ROUNDUP(G86/8,1) -> #N/A | I86: =SUM(J86:CQ86)-H86 -> #N/A | AK86: 0.3
C87: Simulação campos (P3 + ESG Risks) | F87: =COUNTA(E88:E155) -> 68 | G87: =SUM(G88:G137) -> #N/A | H87: =ROUND(SUM(H88:H137),0) -> #N/A
B88: =Table1[[#Headers],[Simulação]] -> Simulação | C88: =D88&"_"&E88 -> ENTITY_TXNMY_ELGBL_CAPEX_W | D88: ENTITY | E88: TXNMY_ELGBL_CAPEX_W | G88: =INDEX(Table1[[Especificação]:[Total Testes]],MATCH(PlanoV1.0!C88,Table1[CONCAT],0),MATCH(PlanoV1.0!B88,Table1[[#Headers],[Especificação]:[Total Testes]],0)) -> #N/A | H88: =ROUNDUP(G88/8,1) -> #N/A | I88: =SUM(J88:CQ88)-H88 -> #N/A | AK88: 0.3 | AL88: 0.5
B89: =Table1[[#Headers],[Simulação]] -> Simulação | C89: =D89&"_"&E89 -> ENTITY_TXNMY_ELGBL_TRNVR_W | D89: ENTITY | E89: TXNMY_ELGBL_TRNVR_W | G89: =INDEX(Table1[[Especificação]:[Total Testes]],MATCH(PlanoV1.0!C89,Table1[CONCAT],0),MATCH(PlanoV1.0!B89,Table1[[#Headers],[Especificação]:[Total Testes]],0)) -> #N/A | H89: =ROUNDUP(G89/8,1) -> #N/A | I89: =SUM(J89:CQ89)-H89 -> #N/A | AL89: 0.4
B90: =Table1[[#Headers],[Simulação]] -> Simulação | C90: =D90&"_"&E90 -> ENTITY_TXNMY_ELGBL_CAPEX_P | D90: ENTITY | E90: TXNMY_ELGBL_CAPEX_P | G90: =INDEX(Table1[[Especificação]:[Total Testes]],MATCH(PlanoV1.0!C90,Table1[CONCAT],0),MATCH(PlanoV1.0!B90,Table1[[#Headers],[Especificação]:[Total Testes]],0)) -> #N/A | H90: =ROUNDUP(G90/8,1) -> #N/A | I90: =SUM(J90:CQ90)-H90 -> #N/A | AL90: 0.2
B91: =Table1[[#Headers],[Simulação]] -> Simulação | C91: =D91&"_"&E91 -> ENTITY_TXNMY_ELGBL_TRNVR_P | D91: ENTITY | E91: TXNMY_ELGBL_TRNVR_P | G91: =INDEX(Table1[[Especificação]:[Total Testes]],MATCH(PlanoV1.0!C91,Table1[CONCAT],0),MATCH(PlanoV1.0!B91,Table1[[#Headers],[Especificação]:[Total Testes]],0)) -> #N/A | H91: =ROUNDUP(G91/8,1) -> #N/A | I91: =SUM(J91:CQ91)-H91 -> #N/A | AL91: 0.2
B92: =Table1[[#Headers],[Simulação]] -> Simulação | C92: =D92&"_"&E92 -> ENTITY_TXNMY_ELGBL_CAPEX_B | D92: ENTITY | E92: TXNMY_ELGBL_CAPEX_B | G92: =INDEX(Table1[[Especificação]:[Total Testes]],MATCH(PlanoV1.0!C92,Table1[CONCAT],0),MATCH(PlanoV1.0!B92,Table1[[#Headers],[Especificação]:[Total Testes]],0)) -> #N/A | H92: =ROUNDUP(G92/8,1) -> #N/A | I92: =SUM(J92:CQ92)-H92 -> #N/A | AL92: 0.2
B93: =Table1[[#Headers],[Simulação]] -> Simulação | C93: =D93&"_"&E93 -> ENTITY_TXNMY_ELGBL_TRNVR_B | D93: ENTITY | E93: TXNMY_ELGBL_TRNVR_B | G93: =INDEX(Table1[[Especificação]:[Total Testes]],MATCH(PlanoV1.0!C93,Table1[CONCAT],0),MATCH(PlanoV1.0!B93,Table1[[#Headers],[Especificação]:[Total Testes]],0)) -> #N/A | H93: =ROUNDUP(G93/8,1) -> #N/A | I93: =SUM(J93:CQ93)-H93 -> #N/A | AL93: 0.2
B94: =Table1[[#Headers],[Simulação]] -> Simulação | C94: =D94&"_"&E94 -> ENTITY_TXNMY_ELGBL_CAPEX_CE | D94: ENTITY | E94: TXNMY_ELGBL_CAPEX_CE | G94: =INDEX(Table1[[Especificação]:[Total Testes]],MATCH(PlanoV1.0!C94,Table1[CONCAT],0),MATCH(PlanoV1.0!B94,Table1[[#Headers],[Especificação]:[Total Testes]],0)) -> #N/A | H94: =ROUNDUP(G94/8,1) -> #N/A | I94: =SUM(J94:CQ94)-H94 -> #N/A | AL94: 0.2
B95: =Table1[[#Headers],[Simulação]] -> Simulação | C95: =D95&"_"&E95 -> ENTITY_TXNMY_ELGBL_TRNVR_CE | D95: ENTITY | E95: TXNMY_ELGBL_TRNVR_CE | G95: =INDEX(Table1[[Especificação]:[Total Testes]],MATCH(PlanoV1.0!C95,Table1[CONCAT],0),MATCH(PlanoV1.0!B95,Table1[[#Headers],[Especificação]:[Total Testes]],0)) -> #N/A | H95: =ROUNDUP(G95/8,1) -> #N/A | I95: =SUM(J95:CQ95)-H95 -> #N/A | AL95: 0.1 | AM95: 0.1
B96: =Table1[[#Headers],[Simulação]] -> Simulação | C96: =D96&"_"&E96 -> ENTITY_PURE_CAPEX_P | D96: ENTITY | E96: PURE_CAPEX_P | G96: =INDEX(Table1[[Especificação]:[Total Testes]],MATCH(PlanoV1.0!C96,Table1[CONCAT],0),MATCH(PlanoV1.0!B96,Table1[[#Headers],[Especificação]:[Total Testes]],0)) -> #N/A | H96: =ROUNDUP(G96/8,1) -> #N/A | I96: =SUM(J96:CQ96)-H96 -> #N/A | AM96: 0.2
B97: =Table1[[#Headers],[Simulação]] -> Simulação | C97: =D97&"_"&E97 -> ENTITY_PURE_TRNVR_P | D97: ENTITY | E97: PURE_TRNVR_P | G97: =INDEX(Table1[[Especificação]:[Total Testes]],MATCH(PlanoV1.0!C97,Table1[CONCAT],0),MATCH(PlanoV1.0!B97,Table1[[#Headers],[Especificação]:[Total Testes]],0)) -> #N/A | H97: =ROUNDUP(G97/8,1) -> #N/A | I97: =SUM(J97:CQ97)-H97 -> #N/A | AM97: 0.2
B98: =Table1[[#Headers],[Simulação]] -> Simulação | C98: =D98&"_"&E98 -> ENTITY_PURE_CAPEX_B | D98: ENTITY | E98: PURE_CAPEX_B | G98: =INDEX(Table1[[Especificação]:[Total Testes]],MATCH(PlanoV1.0!C98,Table1[CONCAT],0),MATCH(PlanoV1.0!B98,Table1[[#Headers],[Especificação]:[Total Testes]],0)) -> #N/A | H98: =ROUNDUP(G98/8,1) -> #N/A | I98: =SUM(J98:CQ98)-H98 -> #N/A | AM98: 0.2
B99: =Table1[[#Headers],[Simulação]] -> Simulação | C99: =D99&"_"&E99 -> ENTITY_PURE_TRNVR_B | D99: ENTITY | E99: PURE_TRNVR_B | G99: =INDEX(Table1[[Especificação]:[Total Testes]],MATCH(PlanoV1.0!C99,Table1[CONCAT],0),MATCH(PlanoV1.0!B99,Table1[[#Headers],[Especificação]:[Total Testes]],0)) -> #N/A | H99: =ROUNDUP(G99/8,1) -> #N/A | I99: =SUM(J99:CQ99)-H99 -> #N/A | AM99: 0.2
B100: =Table1[[#Headers],[Simulação]] -> Simulação | C100: =D100&"_"&E100 -> ENTITY_PURE_CAPEX_W | D100: ENTITY | E100: PURE_CAPEX_W | G100: =INDEX(Table1[[Especificação]:[Total Testes]],MATCH(PlanoV1.0!C100,Table1[CONCAT],0),MATCH(PlanoV1.0!B100,Table1[[#Headers],[Especificação]:[Total Testes]],0)) -> #N/A | H100: =ROUNDUP(G100/8,1) -> #N/A | I100: =SUM(J100:CQ100)-H100 -> #N/A | AM100: 0.2
B101: =Table1[[#Headers],[Simulação]] -> Simulação | C101: =D101&"_"&E101 -> ENTITY_PURE_TRNVR_W | D101: ENTITY | E101: PURE_TRNVR_W | G101: =INDEX(Table1[[Especificação]:[Total Testes]],MATCH(PlanoV1.0!C101,Table1[CONCAT],0),MATCH(PlanoV1.0!B101,Table1[[#Headers],[Especificação]:[Total Testes]],0)) -> #N/A | H101: =ROUNDUP(G101/8,1) -> #N/A | I101: =SUM(J101:CQ101)-H101 -> #N/A | AM101: 0.2
...

Sheet Sheet1
H1: =I1/8 -> 150.3 | I1: =SUM(J1:BU1) -> 1202.4 | K1: =K4*8 -> 24.8 | L1: =L4*8 -> 24.8 | M1: =M4*8 -> 24.8 | N1: =N4*8 -> 24.8 | O1: =O4*8 -> 24.8 | P1: =P4*8 -> 24.8 | Q1: =Q4*8 -> 24.8 | R1: =R4*8 -> 24.8 | ... BU1: =BU4*8 -> 1.6
I2: VAL | K2: =K3-K4 -> 0 | L2: =L3-L4 -> 0 | M2: =M3-M4 -> 0 | N2: =N3-N4 -> 0 | O2: =O3-O4 -> 0 | P2: =P3-P4 -> 0 | Q2: =Q3-Q4 -> 0 | R2: =R3-R4 -> 0 | ... BA2: =BA3-BA4 -> 0 | BC2: =BC3-BC4 -> 0 | BD2: =BD3-BD4 -> 0 | BE2: =BE3-BE4 -> 0 | BF2: =BF3-BF4 -> 0 | BG2: =BG3-BG4 -> 0 | BH2: =BH3-BH4 -> 0 | BI2: =BI3-BI4 -> 0 | BJ2: =BJ3-BJ4 -> 0 | ... BU2: =BU3-BU4 -> 0
I3: FTE REAIS | K3: =SUM(K9:K226) -> 3.1 | L3: =SUM(L9:L226) -> 3.1 | M3: =SUM(M9:M226) -> 3.1 | N3: =SUM(N9:N226) -> 3.1 | O3: =SUM(O9:O226) -> 3.1 | P3: =SUM(P9:P226) -> 3.1 | Q3: =SUM(Q9:Q226) -> 3.1 | R3: =SUM(R9:R226) -> 3.1 | ... BA3: =SUM(BA9:BA226) -> 2.1 | BC3: =SUM(BC9:BC226) -> 2.1 | BD3: =SUM(BD9:BD226) -> 2.1 | BE3: =SUM(BE9:BE226) -> 2.1 | BF3: =SUM(BF9:BF226) -> 2.1 | BG3: =SUM(BG9:BG226) -> 2.1 | BH3: =SUM(BH9:BH226) -> 2.1 | BI3: =SUM(BI9:BI226) -> 2.1 | BJ3: =SUM(BJ9:BJ226) -> 2.1 | ... BU3: =SUM(BU9:BU226) -> 0.2
I4: FTE ESP. | K4: 3.1 | L4: 3.1 | M4: 3.1 | N4: 3.1 | O4: 3.1 | P4: 3.1 | Q4: 3.1 | R4: 3.1 | S4: 3.1 | T4: 3.1 | U4: 3.1 | V4: 3.1 | W4: 3.1 | X4: 3.1 | Y4: 3.1 | Z4: 3.1 | AA4: 3.1 | AB4: 3.1 | AC4: 3.1 | AD4: 3.1 | AE4: 3.1 | AF4: 3.1 | AG4: 2.1 | AH4: 2.1 | AI4: 2.1 | AJ4: 2.1 | AK4: 2.1 | AL4: 2.1 | AM4: 2.1 | AN4: 2.1 | AO4: 2.1 | AP4: 2.1 | AQ4: 2.1 | AR4: 2.1 | AS4: 2.1 | AT4: 2.1 | AU4: 2.1 | AV4: 2.1 | AW4: 2.1 | AX4: 2.1 | AY4: 2.1 | AZ4: 2.1 | BA4: 2.1 | BC4: 2.1 | BD4: 2.1 | BE4: 2.1 | BF4: 2.1 | BG4: 2.1 | BH4: 2.1 | BI4: 2.1 | BJ4: 2.1 | BK4: 2.1 | BL4: 2.1 | BM4: 2.1 | BN4: 2.1 | BO4: 2.1 | BP4: 2.1 | BQ4: 2.1 | BR4: 2.1 | BS4: 2.1 | BT4: 2.1 | BU4: 0.2
G5: =G11+G12+G16 -> #N/A | H5: =H11+H12+H16 -> #N/A | J5: Janeiro | AG5: Fevereiro | BA5: Março | BV5: Abril
G6: =G5/8 -> #N/A | H6: =H5-G6 -> #N/A | J6: 45649 | K6: 45650 | L6: 45651 | M6: 45652 | N6: 45653 | O6: 45649 | P6: 45650 | Q6: 45651 | R6: 45652 | S6: 45653 | T6: 45649 | U6: 45650 | V6: 45651 | W6: 45652 | X6: 45653 | Y6: 45649 | Z6: 45650 | AA6: 45651 | AB6: 45652 | AC6: 45653 | AD6: 45649 | AE6: 45650 | AF6: 45651 | AG6: 45652 | AH6: 45653 | AI6: 45649 | AJ6: 45650 | AK6: 45651 | AL6: 45652 | AM6: 45653 | AN6: 45649 | AO6: 45650 | AP6: 45651 | AQ6: 45652 | AR6: 45653 | AS6: 45649 | AT6: 45650 | AU6: 45651 | AV6: 45652 | AW6: 45653 | AX6: 45649 | AY6: 45650 | AZ6: 45651 | BA6: 45652 | BB6: 45653 | BC6: 45649 | BD6: 45650 | BE6: 45651 | BF6: 45652 | BG6: 45653 | BH6: 45649 | BI6: 45650 | BJ6: 45651 | BK6: 45652 | BL6: 45653 | BM6: 45649 | BN6: 45650 | BO6: 45651 | BP6: 45652 | BQ6: 45653 | BR6: 45649 | BS6: 45650 | BT6: 45651 | BU6: 45652 | BV6: 45653 | BW6: 45649 | BX6: 45650 | BY6: 45651 | BZ6: 45652 | CA6: 45653 | CB6: 45649 | CC6: 45650 | CD6: 45651 | CE6: 45652 | CF6: 45653 | CG6: 45649 | CH6: 45650 | CI6: 45651 | CJ6: 45652 | CK6: 45653 | CL6: 45649 | CM6: 45650 | CN6: 45651 | CO6: 45652 | CP6: 45653 | CQ6: 45649
I7: 45657 | J7: =WORKDAY(I7,1) -> 45658 | K7: =WORKDAY(J7,1) -> 45659 | L7: =WORKDAY(K7,1) -> 45660 | M7: =WORKDAY(L7,1) -> 45663 | N7: =WORKDAY(M7,1) -> 45664 | O7: =WORKDAY(N7,1) -> 45665 | P7: =WORKDAY(O7,1) -> 45666 | Q7: =WORKDAY(P7,1) -> 45667 | ... X7: =WORKDAY(W7,1) -> 45678
F8: # Campos | G8: Duração (horas) | H8: Duração (Dias) | I8: VAL | J8: =WORKDAY(I7,1) -> 45658 | K8: =WORKDAY(J8,1) -> 45659 | L8: =WORKDAY(K8,1) -> 45660 | M8: =WORKDAY(L8,1) -> 45663 | N8: =WORKDAY(M8,1) -> 45664 | O8: =WORKDAY(N8,1) -> 45665 | P8: =WORKDAY(O8,1) -> 45666 | Q8: =WORKDAY(P8,1) -> 45667 | R8: =WORKDAY(Q8,1) -> 45670 | ... CQ8: =WORKDAY(CP8,1) -> 45777
C10: Gestão Projeto | F10: n.a. | G10: =H10*8*5 -> 0 | H10: =SUM(J10:M10) -> 0
C11: Gestão Projeto | F11: n.a. | G11: =H11*8 -> 49.6 | H11: =SUM(J11:BU11) -> 6.2 | I11: =SUM(J11:BU11)-H11 -> 0 | K11: 0.1 | L11: 0.1 | M11: 0.1 | N11: 0.1 | O11: 0.1 | P11: 0.1 | Q11: 0.1 | R11: 0.1 | S11: 0.1 | T11: 0.1 | U11: 0.1 | V11: 0.1 | W11: 0.1 | X11: 0.1 | Y11: 0.1 | Z11: 0.1 | AA11: 0.1 | AB11: 0.1 | AC11: 0.1 | AD11: 0.1 | AE11: 0.1 | AF11: 0.1 | AG11: 0.1 | AH11: 0.1 | AI11: 0.1 | AJ11: 0.1 | AK11: 0.1 | AL11: 0.1 | AM11: 0.1 | AN11: 0.1 | AO11: 0.1 | AP11: 0.1 | AQ11: 0.1 | AR11: 0.1 | AS11: 0.1 | AT11: 0.1 | AU11: 0.1 | AV11: 0.1 | AW11: 0.1 | AX11: 0.1 | AY11: 0.1 | AZ11: 0.1 | BA11: 0.1 | BC11: 0.1 | BD11: 0.1 | BE11: 0.1 | BF11: 0.1 | BG11: 0.1 | BH11: 0.1 | BI11: 0.1 | BJ11: 0.1 | BK11: 0.1 | BL11: 0.1 | BM11: 0.1 | BN11: 0.1 | BO11: 0.1 | BP11: 0.1 | BQ11: 0.1 | BR11: 0.1 | BS11: 0.1 | BT11: 0.1 | BU11: 0.1
C12: 1. Re-especificações + Simulação + Testes + Re-testes requisitos atuais) | G12: =SUM(G13:G15) -> 128 | H12: =ROUND(SUM(H13:H15),1) -> 16
C13: MunichRe | G13: 16 | H13: =ROUNDUP(G13/8,1) -> 2 | I13: 0 | K13: 3
C14: Gloval - Tabela intermédia | G14: 16 | H14: =ROUNDUP(G14/8,1) -> 2 | I14: 0 | L14: 3
C15: Re-testes | G15: =12*8 -> 96 | H15: =ROUNDUP(G15/8,1) -> 12 | I15: 0 | M15: 3 | N15: 3 | O15: 3 | P15: 3 | Q15: 3 | R15: 3 | S15: 3 | T15: 3 | U15: 3 | V15: 3 | W15: 3 | X15: 3
C16: 2. Novos Campos (Especificação + Simulação + Testes+ Re-testes) | F16: =F17+F66 -> 68 | G16: =G17+G66+G87+G156+G225 -> #N/A | H16: =H17+H66+H87+H156+H225 -> #N/A
C17: Especificação de Requisitos - P3 | F17: =COUNTA(E18:E65) -> 48 | G17: =SUM(G18:G65) -> #N/A | H17: =ROUND(SUM(H18:H65),1) -> #N/A | I17: =SUM(J17:CQ17)-H17 -> #N/A | Y17: 3 | Z17: 3 | AA17: 3 | AB17: 3 | AC17: 3 | AD17: 3 | AE17: 3 | AF17: 0.1
B18: =Table1[[#Headers],[Especificação]] -> Especificação | C18: =D18&"_"&E18 -> ENTITY_TXNMY_ELGBL_CAPEX_W | D18: ENTITY | E18: TXNMY_ELGBL_CAPEX_W | G18: =INDEX(Table1[[Especificação]:[Total Testes]],MATCH(Sheet1!C18,Table1[CONCAT],0),MATCH(Sheet1!B18,Table1[[#Headers],[Especificação]:[Total Testes]],0)) -> #N/A | H18: =ROUND(G18/8,2) -> #N/A
B19: =Table1[[#Headers],[Especificação]] -> Especificação | C19: =D19&"_"&E19 -> ENTITY_TXNMY_ELGBL_TRNVR_W | D19: ENTITY | E19: TXNMY_ELGBL_TRNVR_W | G19: =INDEX(Table1[[Especificação]:[Total Testes]],MATCH(Sheet1!C19,Table1[CONCAT],0),MATCH(Sheet1!B19,Table1[[#Headers],[Especificação]:[Total Testes]],0)) -> #N/A | H19: =ROUND(G19/8,2) -> #N/A
B20: =Table1[[#Headers],[Especificação]] -> Especificação | C20: =D20&"_"&E20 -> ENTITY_TXNMY_ELGBL_CAPEX_P | D20: ENTITY | E20: TXNMY_ELGBL_CAPEX_P | G20: =INDEX(Table1[[Especificação]:[Total Testes]],MATCH(Sheet1!C20,Table1[CONCAT],0),MATCH(Sheet1!B20,Table1[[#Headers],[Especificação]:[Total Testes]],0)) -> #N/A | H20: =ROUND(G20/8,2) -> #N/A
B21: =Table1[[#Headers],[Especificação]] -> Especificação | C21: =D21&"_"&E21 -> ENTITY_TXNMY_ELGBL_TRNVR_P | D21: ENTITY | E21: TXNMY_ELGBL_TRNVR_P | G21: =INDEX(Table1[[Especificação]:[Total Testes]],MATCH(Sheet1!C21,Table1[CONCAT],0),MATCH(Sheet1!B21,Table1[[#Headers],[Especificação]:[Total Testes]],0)) -> #N/A | H21: =ROUND(G21/8,2) -> #N/A
B22: =Table1[[#Headers],[Especificação]] -> Especificação | C22: =D22&"_"&E22 -> ENTITY_TXNMY_ELGBL_CAPEX_B | D22: ENTITY | E22: TXNMY_ELGBL_CAPEX_B | G22: =INDEX(Table1[[Especificação]:[Total Testes]],MATCH(Sheet1!C22,Table1[CONCAT],0),MATCH(Sheet1!B22,Table1[[#Headers],[Especificação]:[Total Testes]],0)) -> #N/A | H22: =ROUND(G22/8,2) -> #N/A
B23: =Table1[[#Headers],[Especificação]] -> Especificação | C23: =D23&"_"&E23 -> ENTITY_TXNMY_ELGBL_TRNVR_B | D23: ENTITY | E23: TXNMY_ELGBL_TRNVR_B | G23: =INDEX(Table1[[Especificação]:[Total Testes]],MATCH(Sheet1!C23,Table1[CONCAT],0),MATCH(Sheet1!B23,Table1[[#Headers],[Especificação]:[Total Testes]],0)) -> #N/A | H23: =ROUND(G23/8,2) -> #N/A
B24: =Table1[[#Headers],[Especificação]] -> Especificação | C24: =D24&"_"&E24 -> ENTITY_TXNMY_ELGBL_CAPEX_CE | D24: ENTITY | E24: TXNMY_ELGBL_CAPEX_CE | G24: =INDEX(Table1[[Especificação]:[Total Testes]],MATCH(Sheet1!C24,Table1[CONCAT],0),MATCH(Sheet1!B24,Table1[[#Headers],[Especificação]:[Total Testes]],0)) -> #N/A | H24: =ROUND(G24/8,2) -> #N/A
B25: =Table1[[#Headers],[Especificação]] -> Especificação | C25: =D25&"_"&E25 -> ENTITY_TXNMY_ELGBL_TRNVR_CE | D25: ENTITY | E25: TXNMY_ELGBL_TRNVR_CE | G25: =INDEX(Table1[[Especificação]:[Total Testes]],MATCH(Sheet1!C25,Table1[CONCAT],0),MATCH(Sheet1!B25,Table1[[#Headers],[Especificação]:[Total Testes]],0)) -> #N/A | H25: =ROUND(G25/8,2) -> #N/A
B26: =Table1[[#Headers],[Especificação]] -> Especificação | C26: =D26&"_"&E26 -> ENTITY_PURE_CAPEX_P | D26: ENTITY | E26: PURE_CAPEX_P | G26: =INDEX(Table1[[Especificação]:[Total Testes]],MATCH(Sheet1!C26,Table1[CONCAT],0),MATCH(Sheet1!B26,Table1[[#Headers],[Especificação]:[Total Testes]],0)) -> #N/A | H26: =ROUND(G26/8,2) -> #N/A
B27: =Table1[[#Headers],[Especificação]] -> Especificação | C27: =D27&"_"&E27 -> ENTITY_PURE_TRNVR_P | D27: ENTITY | E27: PURE_TRNVR_P | G27: =INDEX(Table1[[Especificação]:[Total Testes]],MATCH(Sheet1!C27,Table1[CONCAT],0),MATCH(Sheet1!B27,Table1[[#Headers],[Especificação]:[Total Testes]],0)) -> #N/A | H27: =ROUND(G27/8,2) -> #N/A
B28: =Table1[[#Headers],[Especificação]] -> Especificação | C28: =D28&"_"&E28 -> ENTITY_PURE_CAPEX_B | D28: ENTITY | E28: PURE_CAPEX_B | G28: =INDEX(Table1[[Especificação]:[Total Testes]],MATCH(Sheet1!C28,Table1[CONCAT],0),MATCH(Sheet1!B28,Table1[[#Headers],[Especificação]:[Total Testes]],0)) -> #N/A | H28: =ROUND(G28/8,2) -> #N/A
B29: =Table1[[#Headers],[Especificação]] -> Especificação | C29: =D29&"_"&E29 -> ENTITY_PURE_TRNVR_B | D29: ENTITY | E29: PURE_TRNVR_B | G29: =INDEX(Table1[[Especificação]:[Total Testes]],MATCH(Sheet1!C29,Table1[CONCAT],0),MATCH(Sheet1!B29,Table1[[#Headers],[Especificação]:[Total Testes]],0)) -> #N/A | H29: =ROUND(G29/8,2) -> #N/A
... B65: =Table1[[#Headers],[Especificação]] -> Especificação | C65: =D65&"_"&E65 -> PROTECTION_YR_CNSTRCTN | D65: PROTECTION | E65: YR_CNSTRCTN | G65: =INDEX(Table1[[Especificação]:[Total Testes]],MATCH(Sheet1!C65,Table1[CONCAT],0),MATCH(Sheet1!B65,Table1[[#Headers],[Especificação]:[Total Testes]],0)) -> #N/A | H65: =ROUND(G65/8,2) -> #N/A
C66: Especificação de Requisitos - ESG Risks | F66: =+COUNTA(E67:E86) -> 20 | G66: =SUM(G67:G86) -> #N/A | H66: =ROUND(SUM(H67:H86),1) -> #N/A | I66: =SUM(J66:CQ66)-H66 -> #N/A | AF66: 2.9 | AG66: 2 | AH66: 2 | AI66: 2 | AJ66: 2 | AK66: 0.5
B67: =Table1[[#Headers],[Especificação]] -> Especificação | C67: =D67&"_"&E67 -> ENTITY_GRP_ECNMC_ACTVTY | D67: ENTITY | E67: GRP_ECNMC_ACTVTY | G67: =INDEX(Table1[[Especificação]:[Total Testes]],MATCH(Sheet1!C67,Table1[CONCAT],0),MATCH(Sheet1!B67,Table1[[#Headers],[Especificação]:[Total Testes]],0)) -> #N/A | H67: =ROUND(G67/8,2) -> #N/A
B68: =Table1[[#Headers],[Especificação]] -> Especificação | C68: =D68&"_"&E68 -> PROTECTION_TYP_EMSSNS_LBL | D68: PROTECTION | E68: TYP_EMSSNS_LBL | G68: =INDEX(Table1[[Especificação]:[Total Testes]],MATCH(Sheet1!C68,Table1[CONCAT],0),MATCH(Sheet1!B68,Table1[[#Headers],[Especificação]:[Total Testes]],0)) -> #N/A | H68: =ROUND(G68/8,2) -> #N/A
B69: =Table1[[#Headers],[Especificação]] -> Especificação | C69: =D69&"_"&E69 -> PROTECTION_EPC_EMSSNS_LBL | D69: PROTECTION | E69: EPC_EMSSNS_LBL | G69: =INDEX(Table1[[Especificação]:[Total Testes]],MATCH(Sheet1!C69,Table1[CONCAT],0),MATCH(Sheet1!B69,Table1[[#Headers],[Especificação]:[Total Testes]],0)) -> #N/A | H69: =ROUND(G69/8,2) -> #N/A
B70: =Table1[[#Headers],[Especificação]] -> Especificação | C70: =D70&"_"&E70 -> PROTECTION_VHCL_EMSSNS_LBL | D70: PROTECTION | E70: VHCL_EMSSNS_LBL | G70: =INDEX(Table1[[Especificação]:[Total Testes]],MATCH(Sheet1!C70,Table1[CONCAT],0),MATCH(Sheet1!B70,Table1[[#Headers],[Especificação]:[Total Testes]],0)) -> #N/A | H70: =ROUND(G70/8,2) -> #N/A
B71: =Table1[[#Headers],[Especificação]] -> Especificação | C71: =D71&"_"&E71 -> PROTECTION_TYP_EMSSNS_SCR | D71: PROTECTION | E71: TYP_EMSSNS_SCR | G71: =INDEX(Table1[[Especificação]:[Total Testes]],MATCH(Sheet1!C71,Table1[CONCAT],0),MATCH(Sheet1!B71,Table1[[#Headers],[Especificação]:[Total Testes]],0)) -> #N/A | H71: =ROUND(G71/8,2) -> #N/A
B72: =Table1[[#Headers],[Especificação]] -> Especificação | C72: =D72&"_"&E72 -> PROTECTION_EPC_EMSSNS_SCR | D72: PROTECTION | E72: EPC_EMSSNS_SCR | G72: =INDEX(Table1[[Especificação]:[Total Testes]],MATCH(Sheet1!C72,Table1[CONCAT],0),MATCH(Sheet1!B72,Table1[[#Headers],[Especificação]:[Total Testes]],0)) -> #N/A | H72: =ROUND(G72/8,2) -> #N/A
B73: =Table1[[#Headers],[Especificação]] -> Especificação | C73: =D73&"_"&E73 -> PROTECTION_VHCL_EMSSNS_SCR | D73: PROTECTION | E73: VHCL_EMSSNS_SCR | G73: =INDEX(Table1[[Especificação]:[Total Testes]],MATCH(Sheet1!C73,Table1[CONCAT],0),MATCH(Sheet1!B73,Table1[[#Headers],[Especificação]:[Total Testes]],0)) -> #N/A | H73: =ROUND(G73/8,2) -> #N/A
B74: =Table1[[#Headers],[Especificação]] -> Especificação | C74: =D74&"_"&E74 -> PROTECTION_INSRNC_ID | D74: PROTECTION | E74: INSRNC_ID | G74: =INDEX(Table1[[Especificação]:[Total Testes]],MATCH(Sheet1!C74,Table1[CONCAT],0),MATCH(Sheet1!B74,Table1[[#Headers],[Especificação]:[Total Testes]],0)) -> #N/A | H74: =ROUND(G74/8,2) -> #N/A
B75: =Table1[[#Headers],[Especificação]] -> Especificação | C75: =D75&"_"&E75 -> PROTECTION_TYP_HZRDS_INSRD | D75: PROTECTION | E75: TYP_HZRDS_INSRD | G75: =INDEX(Table1[[Especificação]:[Total Testes]],MATCH(Sheet1!C75,Table1[CONCAT],0),MATCH(Sheet1!B75,Table1[[#Headers],[Especificação]:[Total Testes]],0)) -> #N/A | H75: =ROUND(G75/8,2) -> #N/A
B76: =Table1[[#Headers],[Especificação]] -> Especificação | C76: =D76&"_"&E76 -> PROTECTION_AMNT_CVRD_INSRNC | D76: PROTECTION | E76: AMNT_CVRD_INSRNC | G76: =INDEX(Table1[[Especificação]:[Total Testes]],MATCH(Sheet1!C76,Table1[CONCAT],0),MATCH(Sheet1!B76,Table1[[#Headers],[Especificação]:[Total Testes]],0)) -> #N/A | H76: =ROUND(G76/8,2) -> #N/A
B77: =Table1[[#Headers],[Especificação]] -> Especificação | C77: =D77&"_"&E77 -> PROTECTION_DT_MTRTY_INSRNC | D77: PROTECTION | E77: DT_MTRTY_INSRNC | G77: =INDEX(Table1[[Especificação]:[Total Testes]],MATCH(Sheet1!C77,Table1[CONCAT],0),MATCH(Sheet1!B77,Table1[[#Headers],[Especificação]:[Total Testes]],0)) -> #N/A | H77: =ROUND(G77/8,2) -> #N/A
B78: =Table1[[#Headers],[Especificação]] -> Especificação | C78: =D78&"_"&E78 -> PROTECTION_FLG_FRST_HM | D78: PROTECTION | E78: FLG_FRST_HM | G78: =INDEX(Table1[[Especificação]:[Total Testes]],MATCH(Sheet1!C78,Table1[CONCAT],0),MATCH(Sheet1!B78,Table1[[#Headers],[Especificação]:[Total Testes]],0)) -> #N/A | H78: =ROUND(G78/8,2) -> #N/A
... B86: =Table1[[#Headers],[Especificação]] -> Especificação | C86: =D86&"_"&E86 -> PROTECTION_RL_ESTT_CTY | D86: PROTECTION | E86: RL_ESTT_CTY | G86: =INDEX(Table1[[Especificação]:[Total Testes]],MATCH(Sheet1!C86,Table1[CONCAT],0),MATCH(Sheet1!B86,Table1[[#Headers],[Especificação]:[Total Testes]],0)) -> #N/A | H86: =ROUND(G86/8,2) -> #N/A
C87: Simulação campos (P3 + ESG Risks) | F87: =COUNTA(E88:E155) -> 68 | G87: =SUM(G88:G155) -> #N/A | H87: =ROUND(SUM(H88:H155),1) -> #N/A | I87: =SUM(J87:CQ87)-H87 -> #N/A | AK87: 1.5 | AL87: 2 | AM87: 2 | AN87: 2 | AO87: 2 | AP87: 2 | AQ87: 2 | AR87: 2 | AS87: 2 | AT87: 2 | AU87: 2 | AV87: 2 | AW87: 2 | AX87: 0.3
B88: =Table1[[#Headers],[Simulação]] -> Simulação | C88: =D88&"_"&E88 -> ENTITY_TXNMY_ELGBL_CAPEX_W | D88: ENTITY | E88: TXNMY_ELGBL_CAPEX_W | G88: =INDEX(Table1[[Especificação]:[Total Testes]],MATCH(Sheet1!C88,Table1[CONCAT],0),MATCH(Sheet1!B88,Table1[[#Headers],[Especificação]:[Total Testes]],0)) -> #N/A | H88: =ROUND(G88/8,2) -> #N/A
B89: =Table1[[#Headers],[Simulação]] -> Simulação | C89: =D89&"_"&E89 -> ENTITY_TXNMY_ELGBL_TRNVR_W | D89: ENTITY | E89: TXNMY_ELGBL_TRNVR_W | G89: =INDEX(Table1[[Especificação]:[Total Testes]],MATCH(Sheet1!C89,Table1[CONCAT],0),MATCH(Sheet1!B89,Table1[[#Headers],[Especificação]:[Total Testes]],0)) -> #N/A | H89: =ROUND(G89/8,2) -> #N/A
B90: =Table1[[#Headers],[Simulação]] -> Simulação | C90: =D90&"_"&E90 -> ENTITY_TXNMY_ELGBL_CAPEX_P | D90: ENTITY | E90: TXNMY_ELGBL_CAPEX_P | G90: =INDEX(Table1[[Especificação]:[Total Testes]],MATCH(Sheet1!C90,Table1[CONCAT],0),MATCH(Sheet1!B90,Table1[[#Headers],[Especificação]:[Total Testes]],0)) -> #N/A | H90: =ROUND(G90/8,2) -> #N/A
B91: =Table1[[#Headers],[Simulação]] -> Simulação | C91: =D91&"_"&E91 -> ENTITY_TXNMY_ELGBL_TRNVR_P | D91: ENTITY | E91: TXNMY_ELGBL_TRNVR_P | G91: =INDEX(Table1[[Especificação]:[Total Testes]],MATCH(Sheet1!C91,Table1[CONCAT],0),MATCH(Sheet1!B91,Table1[[#Headers],[Especificação]:[Total Testes]],0)) -> #N/A | H91: =ROUND(G91/8,2) -> #N/A
B92: =Table1[[#Headers],[Simulação]] -> Simulação | C92: =D92&"_"&E92 -> ENTITY_TXNMY_ELGBL_CAPEX_B | D92: ENTITY | E92: TXNMY_ELGBL_CAPEX_B | G92: =INDEX(Table1[[Especificação]:[Total Testes]],MATCH(Sheet1!C92,Table1[CONCAT],0),MATCH(Sheet1!B92,Table1[[#Headers],[Especificação]:[Total Testes]],0)) -> #N/A | H92: =ROUND(G92/8,2) -> #N/A
B93: =Table1[[#Headers],[Simulação]] -> Simulação | C93: =D93&"_"&E93 -> ENTITY_TXNMY_ELGBL_TRNVR_B | D93: ENTITY | E93: TXNMY_ELGBL_TRNVR_B | G93: =INDEX(Table1[[Especificação]:[Total Testes]],MATCH(Sheet1!C93,Table1[CONCAT],0),MATCH(Sheet1!B93,Table1[[#Headers],[Especificação]:[Total Testes]],0)) -> #N/A | H93: =ROUND(G93/8,2) -> #N/A
B94: =Table1[[#Headers],[Simulação]] -> Simulação | C94: =D94&"_"&E94 -> ENTITY_TXNMY_ELGBL_CAPEX_CE | D94: ENTITY | E94: TXNMY_ELGBL_CAPEX_CE | G94: =INDEX(Table1[[Especificação]:[Total Testes]],MATCH(Sheet1!C94,Table1[CONCAT],0),MATCH(Sheet1!B94,Table1[[#Headers],[Especificação]:[Total Testes]],0)) -> #N/A | H94: =ROUND(G94/8,2) -> #N/A
B95: =Table1[[#Headers],[Simulação]] -> Simulação | C95: =D95&"_"&E95 -> ENTITY_TXNMY_ELGBL_TRNVR_CE | D95: ENTITY | E95: TXNMY_ELGBL_TRNVR_CE | G95: =INDEX(Table1[[Especificação]:[Total Testes]],MATCH(Sheet1!C95,Table1[CONCAT],0),MATCH(Sheet1!B95,Table1[[#Headers],[Especificação]:[Total Testes]],0)) -> #N/A | H95: =ROUND(G95/8,2) -> #N/A
B96: =Table1[[#Headers],[Simulação]] -> Simulação | C96: =D96&"_"&E96 -> ENTITY_PURE_CAPEX_P | D96: ENTITY | E96: PURE_CAPEX_P | G96: =INDEX(Table1[[Especificação]:[Total Testes]],MATCH(Sheet1!C96,Table1[CONCAT],0),MATCH(Sheet1!B96,Table1[[#Headers],[Especificação]:[Total Testes]],0)) -> #N/A | H96: =ROUND(G96/8,2) -> #N/A
B97: =Table1[[#Headers],[Simulação]] -> Simulação | C97: =D97&"_"&E97 -> ENTITY_PURE_TRNVR_P | D97: ENTITY | E97: PURE_TRNVR_P | G97: =INDEX(Table1[[Especificação]:[Total Testes]],MATCH(Sheet1!C97,Table1[CONCAT],0),MATCH(Sheet1!B97,Table1[[#Headers],[Especificação]:[Total Testes]],0)) -> #N/A | H97: =ROUND(G97/8,2) -> #N/A
B98: =Table1[[#Headers],[Simulação]] -> Simulação | C98: =D98&"_"&E98 -> ENTITY_PURE_CAPEX_B | D98: ENTITY | E98: PURE_CAPEX_B | G98: =INDEX(Table1[[Especificação]:[Total Testes]],MATCH(Sheet1!C98,Table1[CONCAT],0),MATCH(Sheet1!B98,Table1[[#Headers],[Especificação]:[Total Testes]],0)) -> #N/A | H98: =ROUND(G98/8,2) -> #N/A
B99: =Table1[[#Headers],[Simulação]] -> Simulação | C99: =D99&"_"&E99 -> ENTITY_PURE_TRNVR_B | D99: ENTITY | E99: PURE_TRNVR_B | G99: =INDEX(Table1[[Especificação]:[Total Testes]],MATCH(Sheet1!C99,Table1[CONCAT],0),MATCH(Sheet1!B99,Table1[[#Headers],[Especificação]:[Total Testes]],0)) -> #N/A | H99: =ROUND(G99/8,2) -> #N/A
... B155: =Table1[[#Headers],[Simulação]] -> Simulação | C155: =D155&"_"&E155 -> PROTECTION_RL_ESTT_CTY | D155: PROTECTION | E155: RL_ESTT_CTY | G155: =INDEX(Table1[[Especificação]:[Total Testes]],MATCH(Sheet1!C155,Table1[CONCAT],0),MATCH(Sheet1!B155,Table1[[#Headers],[Especificação]:[Total Testes]],0)) -> #N/A | H155: =ROUND(G155/8,2) -> #N/A
C156: Testes Campos (P3 + ESG Risks) | F156: =COUNTA(E157:E224) -> 68 | G156: =SUM(G157:G224) -> #N/A | H156: =ROUND(SUM(H157:H224),1) -> #N/A | I156: =SUM(J156:CQ156)-H156 -> #N/A | AX156: 1.7 | AY156: 2 | AZ156: 2 | BA156: 2 | BC156: 2 | BD156: 2 | BE156: 2 | BF156: 2 | BG156: 2 | BH156: 2 | BI156: 2 | BJ156: 2 | BK156: 2 | BL156: 2 | BM156: 2 | BN156: 2 | BO156: 2 | BP156: 2 | BQ156: 0.1
B157: =Table1[[#Headers],[Total Testes]] -> Total Testes | C157: =D157&"_"&E157 -> ENTITY_TXNMY_ELGBL_CAPEX_W | D157: ENTITY | E157: TXNMY_ELGBL_CAPEX_W | G157: =INDEX(Table1[[Especificação]:[Total Testes]],MATCH(Sheet1!C157,Table1[CONCAT],0),MATCH(Sheet1!B157,Table1[[#Headers],[Especificação]:[Total Testes]],0)) -> #N/A | H157: =ROUND(G157/8,2) -> #N/A
B158: =Table1[[#Headers],[Total Testes]] -> Total Testes | C158: =D158&"_"&E158 -> ENTITY_TXNMY_ELGBL_TRNVR_W | D158: ENTITY | E158: TXNMY_ELGBL_TRNVR_W | G158: =INDEX(Table1[[Especificação]:[Total Testes]],MATCH(Sheet1!C158,Table1[CONCAT],0),MATCH(Sheet1!B158,Table1[[#Headers],[Especificação]:[Total Testes]],0)) -> #N/A | H158: =ROUND(G158/8,2) -> #N/A
B159: =Table1[[#Headers],[Total Testes]] -> Total Testes | C159: =D159&"_"&E159 -> ENTITY_TXNMY_ELGBL_CAPEX_P | D159: ENTITY | E159: TXNMY_ELGBL_CAPEX_P | G159: =INDEX(Table1[[Especificação]:[Total Testes]],MATCH(Sheet1!C159,Table1[CONCAT],0),MATCH(Sheet1!B159,Table1[[#Headers],[Especificação]:[Total Testes]],0)) -> #N/A | H159: =ROUND(G159/8,2) -> #N/A
B160: =Table1[[#Headers],[Total Testes]] -> Total Testes | C160: =D160&"_"&E160 -> ENTITY_TXNMY_ELGBL_TRNVR_P | D160: ENTITY | E160: TXNMY_ELGBL_TRNVR_P | G160: =INDEX(Table1[[Especificação]:[Total Testes]],MATCH(Sheet1!C160,Table1[CONCAT],0),MATCH(Sheet1!B160,Table1[[#Headers],[Especificação]:[Total Testes]],0)) -> #N/A | H160: =ROUND(G160/8,2) -> #N/A
B161: =Table1[[#Headers],[Total Testes]] -> Total Testes | C161: =D161&"_"&E161 -> ENTITY_TXNMY_ELGBL_CAPEX_B | D161: ENTITY | E161: TXNMY_ELGBL_CAPEX_B | G161: =INDEX(Table1[[Especificação]:[Total Testes]],MATCH(Sheet1!C161,Table1[CONCAT],0),MATCH(Sheet1!B161,Table1[[#Headers],[Especificação]:[Total Testes]],0)) -> #N/A | H161: =ROUND(G161/8,2) -> #N/A
B162: =Table1[[#Headers],[Total Testes]] -> Total Testes | C162: =D162&"_"&E162 -> ENTITY_TXNMY_ELGBL_TRNVR_B | D162: ENTITY | E162: TXNMY_ELGBL_TRNVR_B | G162: =INDEX(Table1[[Especificação]:[Total Testes]],MATCH(Sheet1!C162,Table1[CONCAT],0),MATCH(Sheet1!B162,Table1[[#Headers],[Especificação]:[Total Testes]],0)) -> #N/A | H162: =ROUND(G162/8,2) -> #N/A
B163: =Table1[[#Headers],[Total Testes]] -> Total Testes | C163: =D163&"_"&E163 -> ENTITY_TXNMY_ELGBL_CAPEX_CE | D163: ENTITY | E163: TXNMY_ELGBL_CAPEX_CE | G163: =INDEX(Table1[[Especificação]:[Total Testes]],MATCH(Sheet1!C163,Table1[CONCAT],0),MATCH(Sheet1!B163,Table1[[#Headers],[Especificação]:[Total Testes]],0)) -> #N/A | H163: =ROUND(G163/8,2) -> #N/A
B164: =Table1[[#Headers],[Total Testes]] -> Total Testes | C164: =D164&"_"&E164 -> ENTITY_TXNMY_ELGBL_TRNVR_CE | D164: ENTITY | E164: TXNMY_ELGBL_TRNVR_CE | G164: =INDEX(Table1[[Especificação]:[Total Testes]],MATCH(Sheet1!C164,Table1[CONCAT],0),MATCH(Sheet1!B164,Table1[[#Headers],[Especificação]:[Total Testes]],0)) -> #N/A | H164: =ROUND(G164/8,2) -> #N/A
B165: =Table1[[#Headers],[Total Testes]] -> Total Testes | C165: =D165&"_"&E165 -> ENTITY_PURE_CAPEX_P | D165: ENTITY | E165: PURE_CAPEX_P | G165: =INDEX(Table1[[Especificação]:[Total Testes]],MATCH(Sheet1!C165,Table1[CONCAT],0),MATCH(Sheet1!B165,Table1[[#Headers],[Especificação]:[Total Testes]],0)) -> #N/A | H165: =ROUND(G165/8,2) -> #N/A
B166: =Table1[[#Headers],[Total Testes]] -> Total Testes | C166: =D166&"_"&E166 -> ENTITY_PURE_TRNVR_P | D166: ENTITY | E166: PURE_TRNVR_P | G166: =INDEX(Table1[[Especificação]:[Total Testes]],MATCH(Sheet1!C166,Table1[CONCAT],0),MATCH(Sheet1!B166,Table1[[#Headers],[Especificação]:[Total Testes]],0)) -> #N/A | H166: =ROUND(G166/8,2) -> #N/A
B167: =Table1[[#Headers],[Total Testes]] -> Total Testes | C167: =D167&"_"&E167 -> ENTITY_PURE_CAPEX_B | D167: ENTITY | E167: PURE_CAPEX_B | G167: =INDEX(Table1[[Especificação]:[Total Testes]],MATCH(Sheet1!C167,Table1[CONCAT],0),MATCH(Sheet1!B167,Table1[[#Headers],[Especificação]:[Total Testes]],0)) -> #N/A | H167: =ROUND(G167/8,2) -> #N/A
B168: =Table1[[#Headers],[Total Testes]] -> Total Testes | C168: =D168&"_"&E168 -> ENTITY_PURE_TRNVR_B | D168: ENTITY | E168: PURE_TRNVR_B | G168: =INDEX(Table1[[Especificação]:[Total Testes]],MATCH(Sheet1!C168,Table1[CONCAT],0),MATCH(Sheet1!B168,Table1[[#Headers],[Especificação]:[Total Testes]],0)) -> #N/A | H168: =ROUND(G168/8,2) -> #N/A
... B224: =Table1[[#Headers],[Total Testes]] -> Total Testes | C224: =D224&"_"&E224 -> PROTECTION_RL_ESTT_CTY | D224: PROTECTION | E224: RL_ESTT_CTY | G224: =INDEX(Table1[[Especificação]:[Total Testes]],MATCH(Sheet1!C224,Table1[CONCAT],0),MATCH(Sheet1!B224,Table1[[#Headers],[Especificação]:[Total Testes]],0)) -> #N/A | H224: =ROUND(G224/8,2) -> #N/A
C225: Re-testes | G225: =H225*8 -> #N/A | H225: =ROUNDUP(Auxiliar!$E$12*H156,0) -> #N/A | I225: =SUM(J225:CQ225)-H225 -> #N/A | BQ225: 1.9 | BR225: 2 | BS225: 2 | BT225: 2 | BU225: 0.1
C231: Horas Total
C232: Horas Novos Requisitos

Sheet RESUMO
B2: Leverage Finance = "Y" | C2: =COUNTIFS('Lista - Âmbito Projeto GD'!$K$3:$K$71,"Y") -> 17
B4: Alteração | C4: Âmbito | D4: # Campos | E4: Observações | H4: Leveraged Finance | I4: STATUS | J4: AMBITO | K4: Status Data Lake | L4: # Campos
B5: Novo Campo | C5: ESTR (& outros) | D5: =GETPIVOTDATA("[Measures].[Count of ID Data field / Field order]",$H$4,"[Range].[STATUS]","[Range].[STATUS].&[Novo Campo]","[Range].[AMBITO]","[Range].[AMBITO].&[ESTR & GD & PILAR3]","[Range].[Status Data Lake]","[Range].[Status Data Lake].&[n/a]","[Range].[Leveraged Finance]","[Range].[Leveraged Finance].&[Y]") -> 1 | E5: n.a. | H5: N | I5: Campo eliminado | J5: PILAR3 | K5: n/a | L5: 1
C6: LF | D6: =GETPIVOTDATA("[Measures].[Count of ID Data field / Field order]",$H$4,"[Range].[STATUS]","[Range].[STATUS].&[Novo Campo]","[Range].[AMBITO]","[Range].[AMBITO].&[LF]","[Range].[Status Data Lake]","[Range].[Status Data Lake].&[n/a]","[Range].[Leveraged Finance]","[Range].[Leveraged Finance].&[Y]") -> 19 | E6: n.a. | I6: Campo eliminado - troca tabela | J6: GD & PILAR3 | K6: n/a | L6: 2
B7: Sem alterações | C7: ESTR (& outros) | D7: =SUM(L50:L72) -> 154 | E7: De notar que destes campos: - 9 provém da fonte manual de LF (lt601_lev_fin) - 39 estão sem dados/pouca qualidade com necessidades de (re)-especificações (Sindicados, Demonstrações Financeiras CIB, Re-estruturados) - 24 em testes/implementação - 15 com incidências nos controlos corporativos | J7: PILAR3 | K7: n/a | L7: 2
C8: Total | D8: =SUM(D5:D7) -> 174 | I8: Nome campo alterado | J8: PILAR3 | K8: n/a | L8: 2
I9: Nova Tabela | J9: ESTR & GD & PILAR3 | K9: n/a | L9: 1
J10: GD & PILAR3 | K10: n/a | L10: 3
B11: Leverage Finance = "N" | C11: =COUNTIFS('Lista - Âmbito Projeto GD'!$K$3:$K$71,"N") -> 51 | J11: PILAR3 | K11: n/a | L11: 3
I12: Nova Tabela - Campo existente | J12: GD & PILAR3 | K12: n/a | L12: 2
J13: PILAR3 | K13: n/a | L13: 2
B14: Alteração | C14: Âmbito | D14: # Campos | E14: Observações | I14: Novo Campo | J14: ESG_RISKS | K14: n/a | L14: 12
B15: Nova tabela | C15: ESTR (& outros) | D15: =GETPIVOTDATA("[Measures].[Count of ID Data field / Field order]",$H$4,"[Range].[STATUS]","[Range].[STATUS].&[Nova Tabela]","[Range].[AMBITO]","[Range].[AMBITO].&[ESTR & GD & PILAR3]","[Range].[Status Data Lake]","[Range].[Status Data Lake].&[n/a]","[Range].[Leveraged Finance]","[Range].[Leveraged Finance].&[N]") -> 1 | E15: Apenas 1 campo reportado na LT estrutural (questionar corporação) >>> é para ESG | J15: ESTR | K15: n/a | L15: 25
C16: GD & PILAR3 | D16: =GETPIVOTDATA("[Measures].[Count of ID Data field / Field order]",$H$4,"[Range].[STATUS]","[Range].[STATUS].&[Nova Tabela]","[Range].[AMBITO]","[Range].[AMBITO].&[GD & PILAR3]","[Range].[Status Data Lake]","[Range].[Status Data Lake].&[n/a]","[Range].[Leveraged Finance]","[Range].[Leveraged Finance].&[N]")+GETPIVOTDATA("[Measures].[Count of ID Data field / Field order]",$H$4,"[Range].[STATUS]","[Range].[STATUS].&[Nova Tabela - Campo existente]","[Range].[AMBITO]","[Range].[AMBITO].&[GD & PILAR3]","[Range].[Status Data Lake]","[Range].[Status Data Lake].&[n/a]","[Range].[Leveraged Finance]","[Range].[Leveraged Finance].&[N]") -> 5 | E16: De notar que 2 campos trocaram de tabela | J16: ESTR & GFINANCE | K16: n/a | L16: 7
C17: PILAR3 | D17: =GETPIVOTDATA("[Measures].[Count of ID Data field / Field order]",$H$4,"[Range].[STATUS]","[Range].[STATUS].&[Nova Tabela]","[Range].[AMBITO]","[Range].[AMBITO].&[PILAR3]","[Range].[Status Data Lake]","[Range].[Status Data Lake].&[n/a]","[Range].[Leveraged Finance]","[Range].[Leveraged Finance].&[N]")+GETPIVOTDATA("[Measures].[Count of ID Data field / Field order]",$H$4,"[Range].[STATUS]","[Range].[STATUS].&[Nova Tabela - Campo existente]","[Range].[AMBITO]","[Range].[AMBITO].&[PILAR3]","[Range].[Status Data Lake]","[Range].[Status Data Lake].&[n/a]","[Range].[Leveraged Finance]","[Range].[Leveraged Finance].&[N]") -> 5 | E17: De notar que 2 campos trocaram de tabela | J17: GD | K17: n/a | L17: 1
B18: Novo Campo | C18: ESTR | D18: =GETPIVOTDATA("[Measures].[Count of ID Data field / Field order]",$H$4,"[Range].[STATUS]","[Range].[STATUS].&[Novo Campo]","[Range].[AMBITO]","[Range].[AMBITO].&[ESTR]","[Range].[Status Data Lake]","[Range].[Status Data Lake].&[n/a]","[Range].[Leveraged Finance]","[Range].[Leveraged Finance].&[N]") -> 25 | E18: n.a. | J18: GD & PILAR3 | K18: n/a | L18: 1
C19: ESTR (& Green Finance) | D19: =GETPIVOTDATA("[Measures].[Count of ID Data field / Field order]",$H$4,"[Range].[STATUS]","[Range].[STATUS].&[Novo Campo]","[Range].[AMBITO]","[Range].[AMBITO].&[ESTR & GFINANCE]","[Range].[Status Data Lake]","[Range].[Status Data Lake].&[n/a]","[Range].[Leveraged Finance]","[Range].[Leveraged Finance].&[N]") -> 7 | E19: n.a. | J19: PILAR3 | K19: n/a | L19: 29
C20: GD & PILAR3 | D20: =GETPIVOTDATA("[Measures].[Count of ID Data field / Field order]",$H$4,"[Range].[STATUS]","[Range].[STATUS].&[Novo Campo]","[Range].[AMBITO]","[Range].[AMBITO].&[GD & PILAR3]","[Range].[Status Data Lake]","[Range].[Status Data Lake].&[n/a]","[Range].[Leveraged Finance]","[Range].[Leveraged Finance].&[N]") -> 1 | E20: n.a. | I20: Sem alteração | J20: ESTR | K20: 1. Especificar | L20: 9
C21: PILAR3 | D21: =GETPIVOTDATA("[Measures].[Count of ID Data field / Field order]",$H$4,"[Range].[STATUS]","[Range].[STATUS].&[Novo Campo]","[Range].[AMBITO]","[Range].[AMBITO].&[PILAR3]","[Range].[Status Data Lake]","[Range].[Status Data Lake].&[n/a]","[Range].[Leveraged Finance]","[Range].[Leveraged Finance].&[N]") -> 29 | E21: n.a. | K21: 2. Alterar especificação | L21: 15
C22: GD | D22: =GETPIVOTDATA("[Measures].[Count of ID Data field / Field order]",$H$4,"[Range].[STATUS]","[Range].[STATUS].&[Novo Campo]","[Range].[AMBITO]","[Range].[AMBITO].&[GD]","[Range].[Status Data Lake]","[Range].[Status Data Lake].&[n/a]","[Range].[Leveraged Finance]","[Range].[Leveraged Finance].&[N]") -> 1 | E22: n.a. | K22: 3. Pendente de decisão | L22: 1
C23: ESG Risks | D23: =GETPIVOTDATA("[Measures].[Count of ID Data field / Field order]",$H$4,"[Range].[STATUS]","[Range].[STATUS].&[Novo Campo]","[Range].[AMBITO]","[Range].[AMBITO].&[ESG_RISKS]","[Range].[Status Data Lake]","[Range].[Status Data Lake].&[n/a]","[Range].[Leveraged Finance]","[Range].[Leveraged Finance].&[N]") -> 12 | E23: Campos adicionados pela Corporação antes de abril e não contemplados no Data Lake. | K23: 4.1 Em implementação - Re-especificação | L23: 13
B24: Nome de campo alterado | C24: PILAR3 | D24: =GETPIVOTDATA("[Measures].[Count of ID Data field / Field order]",$H$4,"[Range].[STATUS]","[Range].[STATUS].&[Nome campo alterado]","[Range].[AMBITO]","[Range].[AMBITO].&[PILAR3]","[Range].[Status Data Lake]","[Range].[Status Data Lake].&[n/a]","[Range].[Leveraged Finance]","[Range].[Leveraged Finance].&[N]") -> 2 | E24: Sem impacto previsto a nível de re-especificação. | K24: 4.2 Em implementação - Incidência | L24: 1
B25: Sem alterações | C25: - | D25: =SUM(L20:L47) -> 269 | E25: De notar que destes campos (âmbito ESTR): - 29 estão sem dados/pouca qualidade com necessidades de (re)-especificações (Salários, Demonstrações Financeiras CIB) - 27 em testes/implementação - 42 com incidências nos controlos corporativos | K25: 5.1 Em testes - Re-especificação | L25: 7
C26: Total (excl. campos elim.) | D26: =SUM(D15:D25) -> 357 | K26: 5.2 Em testes - Incidência | L26: 2
B27: Campo eliminado | C27: GD & PILAR3 | D27: =GETPIVOTDATA("[Measures].[Count of ID Data field / Field order]",$H$4,"[Range].[STATUS]","[Range].[STATUS].&[Campo eliminado - troca tabela]","[Range].[AMBITO]","[Range].[AMBITO].&[GD & PILAR3]","[Range].[Status Data Lake]","[Range].[Status Data Lake].&[n/a]","[Range].[Leveraged Finance]","[Range].[Leveraged Finance].&[N]") -> 2 | E27: De notar que 2 campos trocaram de tabela | K27: 7. Analisar controlos e completude | L27: 36
C28: PILAR3 | D28: =GETPIVOTDATA("[Measures].[Count of ID Data field / Field order]",$H$4,"[Range].[STATUS]","[Range].[STATUS].&[Campo eliminado]","[Range].[AMBITO]","[Range].[AMBITO].&[PILAR3]","[Range].[Status Data Lake]","[Range].[Status Data Lake].&[n/a]","[Range].[Leveraged Finance]","[Range].[Leveraged Finance].&[N]")+GETPIVOTDATA("[Measures].[Count of ID Data field / Field order]",$H$4,"[Range].[STATUS]","[Range].[STATUS].&[Campo eliminado - troca tabela]","[Range].[AMBITO]","[Range].[AMBITO].&[PILAR3]","[Range].[Status Data Lake]","[Range].[Status Data Lake].&[n/a]","[Range].[Leveraged Finance]","[Range].[Leveraged Finance].&[N]") -> 3 | E28: De notar que 2 campos trocaram de tabela | K28: 8. Concluído - sem dados | L28: 6
D29: =D26+SUM(D27:D28) -> 362 | K29: 9. Concluído | L29: 73
J30: ESTR & GD | K30: 5.1 Em testes - Re-especificação | L30: 1
K31: 9. Concluído | L31: 1
J32: ESTR & GD & PILAR3 | K32: 4.1 Em implementação - Re-especificação | L32: 1
K33: 5.2 Em testes - Incidência | L33: 1
K34: 7. Analisar controlos e completude | L34: 3
K35: 9. Concluído | L35: 6
J36: ESTR & GFINANCE | K36: 9. Concluído | L36: 1
J37: ESTR & PILAR3 | K37: 1. Especificar | L37: 1
K38: 2. Alterar especificação | L38: 2
C39: Green finance + ESG Risks o que são e para que são utilizados >> 7+12 | K39: 3. Pendente de decisão | L39: 1
C40: Quem está a solicitar esta informação? >> 25 campos ESTR >> custo à unidade | K40: 4.1 Em implementação - Re-especificação | L40: 1
K41: 7. Analisar controlos e completude | L41: 3
B42: Confirmar com ficheiro enviado pela Raquel > LF | K42: 9. Concluído | L42: 6
B43: Adicionar flag de marcação | J43: GD | K43: 1. Especificar | L43: 1
B44: Ver com a Zeneida se os de CIB podem não ser preenchidos pq vêm do AQUA > corporativo | K44: n/a | L44: 25
J45: GD & PILAR3 | K45: n/a | L45: 4
J46: PILAR3 | K46: 1. Especificar | L46: 1
K47: n/a | L47: 47
H48: Y | I48: Novo Campo | J48: ESTR & GD & PILAR3 | K48: n/a | L48: 1
J49: LF | K49: n/a | L49: 19
I50: Sem alteração | J50: ESTR | K50: 1. Especificar | L50: 6
K51: 2. Alterar especificação | L51: 19
K52: 3. Pendente de decisão | L52: 6
K53: 4.1 Em implementação - Re-especificação | L53: 5
K54: 5.1 Em testes - Re-especificação | L54: 7
K55: 5.2 Em testes - Incidência | L55: 4
K56: 6. Outros Desenvolvimentos | L56: 10
K57: 7. Analisar controlos e completude | L57: 11
K58: 8. Concluído - sem dados | L58: 4
K59: 9. Concluído | L59: 45
J60: ESTR & GD | K60: 5.1 Em testes - Re-especificação | L60: 2
K61: 7. Analisar controlos e completude | L61: 1
K62: 9. Concluído | L62: 1
J63: ESTR & GD & PILAR3 | K63: 2. Alterar especificação | L63: 1
K64: 4.1 Em implementação - Re-especificação | L64: 2
K65: 5.1 Em testes - Re-especificação | L65: 1
K66: 9. Concluído | L66: 8
J67: ESTR & PILAR3 | K67: 1. Especificar | L67: 1
K68: 2. Alterar especificação | L68: 4
K69: 4.1 Em implementação - Re-especificação | L69: 1
K70: 5.2 Em testes - Incidência | L70: 2
K71: 7. Analisar controlos e completude | L71: 3
K72: 9. Concluído | L72: 10

Sheet Plano SCA
I1: =SUM(J1:BF1) -> 823.2 | J1: =J4*8 -> 16.8 | K1: =K4*8 -> 16.8 | L1: =L4*8 -> 16.8 | M1: =M4*8 -> 16.8 | N1: =N4*8 -> 16.8 | O1: =O4*8 -> 16.8 | P1: =P4*8 -> 16.8 | Q1: =Q4*8 -> 16.8 | ... BF1: =BF4*8 -> 16.8
I2: VAL | J2: =J3-J4 -> 0 | K2: =K3-K4 -> 0 | L2: =L3-L4 -> 0 | M2: =M3-M4 -> 0 | N2: =N3-N4 -> 0 | O2: =O3-O4 -> 0 | P2: =P3-P4 -> 0 | Q2: =Q3-Q4 -> 0 | ... BF2: =BF3-BF4 -> -1.575
I3: FTE REAIS | J3: =SUM(J8:J102) -> 2.1 | K3: =SUM(K8:K102) -> 2.1 | L3: =SUM(L8:L102) -> 2.1 | M3: =SUM(M8:M102) -> 2.1 | N3: =SUM(N8:N102) -> 2.1 | O3: =SUM(O8:O102) -> 2.1 | P3: =SUM(P8:P102) -> 2.1 | Q3: =SUM(Q8:Q102) -> 2.1 | ... BF3: =SUM(BF8:BF102) -> 0.525
I4: FTE ESP. | J4: 2.1 | K4: 2.1 | L4: 2.1 | M4: 2.1 | N4: 2.1 | O4: 2.1 | P4: 2.1 | Q4: 2.1 | R4: 2.1 | S4: 2.1 | T4: 2.1 | U4: 2.1 | V4: 2.1 | W4: 2.1 | X4: 2.1 | Y4: 2.1 | Z4: 2.1 | AA4: 2.1 | AB4: 2.1 | AC4: 2.1 | AD4: 2.1 | AE4: 2.1 | AF4: 2.1 | AG4: 2.1 | AH4: 2.1 | AI4: 2.1 | AJ4: 2.1 | AK4: 2.1 | AL4: 2.1 | AM4: 2.1 | AN4: 2.1 | AO4: 2.1 | AP4: 2.1 | AQ4: 2.1 | AR4: 2.1 | AS4: 2.1 | AT4: 2.1 | AU4: 2.1 | AV4: 2.1 | AW4: 2.1 | AX4: 2.1 | AY4: 2.1 | AZ4: 2.1 | BA4: 2.1 | BB4: 2.1 | BC4: 2.1 | BD4: 2.1 | BE4: 2.1 | BF4: 2.1
J5: Mês 1 | AG5: Mês 2 | BD5: Mês 3
I6: 45657 | J6: =WORKDAY(I6,1) -> 45658 | K6: =WORKDAY(J6,1) -> 45659 | L6: =WORKDAY(K6,1) -> 45660 | M6: 4 | N6: =WORKDAY(M6,1) -> 5 | O6: =WORKDAY(N6,1) -> 6 | P6: =WORKDAY(O6,1) -> 9 | Q6: =WORKDAY(P6,1) -> 10 | R6: =WORKDAY(Q6,1) -> 11 | S6: =WORKDAY(R6,1) -> 12 | T6: =WORKDAY(S6,1) -> 13 | U6: =WORKDAY(T6,1) -> 16 | ... X6: =WORKDAY(W6,1) -> 19
F7: # Campos | G7: Duração (horas) | H7: Duração (Dias) | I7: VAL | J7: 1 | K7: =J7+1 -> 2 | L7: =K7+1 -> 3 | M7: =L7+1 -> 4 | N7: =M7+1 -> 5 | O7: =N7+1 -> 6 | P7: =O7+1 -> 7 | Q7: =P7+1 -> 8 | R7: =Q7+1 -> 9 | ... BZ7: =BY7+1 -> 69
C9: Gestão Projeto | F9: n.a. | G9: =H9*8*5 -> 0 | H9: =SUM(J9:M9) -> 0
C10: 0. Gestão Projeto | F10: n.a. | G10: =H10*8 -> 51.2 | H10: =SUM(J10:BU10) -> 6.4 | I10: =SUM(J10:BU10)-H10 -> 0 | J10: 0.1 | K10: 0.1 | L10: 0.1 | M10: 0.1 | N10: 0.1 | O10: 0.1 | P10: 0.1 | Q10: 0.1 | R10: 0.1 | S10: 0.1 | T10: 0.1 | U10: 0.1 | V10: 0.1 | W10: 0.1 | X10: 0.1 | Y10: 0.1 | Z10: 0.1 | AA10: 0.1 | AB10: 0.1 | AC10: 0.1 | AD10: 0.1 | AE10: 0.1 | AF10: 0.1 | AG10: 0.1 | AH10: 0.1 | AI10: 0.1 | AJ10: 0.1 | AK10: 0.1 | AL10: 0.1 | AM10: 0.1 | AN10: 0.1 | AO10: 0.1 | AP10: 0.1 | AQ10: 0.1 | AR10: 0.1 | AS10: 0.1 | AT10: 0.1 | AU10: 0.1 | AV10: 0.1 | AW10: 0.1 | AX10: 0.1 | AY10: 0.1 | AZ10: 0.1 | BA10: 0.1 | BB10: 0.1 | BC10: 0.1 | BD10: 0.1 | BE10: 0.1 | BF10: 0.1 | BG10: 0.1 | BH10: 0.1 | BI10: 0.1 | BJ10: 0.1 | BK10: 0.1 | BL10: 0.1 | BM10: 0.1 | BN10: 0.1 | BO10: 0.1 | BP10: 0.1 | BQ10: 0.1 | BR10: 0.1 | BS10: 0.1 | BT10: 0.1 | BU10: 0.1 | BV10: 0.1 | BW10: 0.1 | BX10: 0.1 | BY10: 0.1 | BZ10: 0.1
C11: 1. Set-Up | F11: n.a. | G11: =8*4 -> 32 | H11: =G11/8 -> 4 | I11: =SUM(J11:CQ11)-H11 -> 0 | J11: 2 | K11: 2
C12: 2. Assessment ao Green Dashboard (Esp. Atual) | F12: n.a. | G12: =8*8 -> 64 | H12: =G12/8 -> 8 | I12: =SUM(J12:CQ12)-H12 -> 0 | L12: 2 | M12: 2 | N12: 2 | O12: 2
C13: 3. Re-testes aos campos concluídos do GD âmbito projeto anterior | F13: =COUNTA(D14:D36) -> 23 | G13: =SUM(G14:G36) -> 82 | H13: =G13/8 -> 10.25 | I13: =SUM(J13:CQ13)-H13 -> 0 | P13: 2 | Q13: 2 | R13: 2 | S13: 2 | T13: 2 | U13: 0.25
B14: =C14&"_"&D14 -> INSTRUMENT_COD_SOC | C14: INSTRUMENT | D14: COD_SOC | F14: =VLOOKUP(B14,'Aux DE'!B:P,15,0) -> SCA SCB1 | G14: =SUMIF('Aux DE'!B:B,'Plano SCA'!B14,'Aux DE'!I:I)+SUMIF('Aux DE'!B:B,'Plano SCA'!B14,'Aux DE'!O:O) -> 3.5 | I14: =SUM(J14:CQ14)-H14 -> 0
B15: =C15&"_"&D15 -> INSTRUMENT_SUBPORTFOLIO_ID | C15: INSTRUMENT | D15: SUBPORTFOLIO_ID | F15: =VLOOKUP(B15,'Aux DE'!B:P,15,0) -> SCA SCB1 | G15: =SUMIF('Aux DE'!B:B,'Plano SCA'!B15,'Aux DE'!I:I)+SUMIF('Aux DE'!B:B,'Plano SCA'!B15,'Aux DE'!O:O) -> 3.5 | I15: =SUM(J15:CQ15)-H15 -> 0
B16: =C16&"_"&D16 -> INSTRUMENT_DT_RFRNC | C16: INSTRUMENT | D16: DT_RFRNC | F16: =VLOOKUP(B16,'Aux DE'!B:P,15,0) -> SCA SCB1 | G16: =SUMIF('Aux DE'!B:B,'Plano SCA'!B16,'Aux DE'!I:I)+SUMIF('Aux DE'!B:B,'Plano SCA'!B16,'Aux DE'!O:O) -> 3.5 | I16: =SUM(J16:CQ16)-H16 -> 0
B17: =C17&"_"&D17 -> INSTRUMENT_DFLT_STTS_INSTRMNT | C17: INSTRUMENT | D17: DFLT_STTS_INSTRMNT | F17: =VLOOKUP(B17,'Aux DE'!B:P,15,0) -> SCA SCB1 | G17: =SUMIF('Aux DE'!B:B,'Plano SCA'!B17,'Aux DE'!I:I)+SUMIF('Aux DE'!B:B,'Plano SCA'!B17,'Aux DE'!O:O) -> 3.5 | I17: =SUM(J17:CQ17)-H17 -> 0
B18: =C18&"_"&D18 -> INSTRUMENT_IMPRMNT_STTS | C18: INSTRUMENT | D18: IMPRMNT_STTS | F18: =VLOOKUP(B18,'Aux DE'!B:P,15,0) -> SCA SCB1 | G18: =SUMIF('Aux DE'!B:B,'Plano SCA'!B18,'Aux DE'!I:I)+SUMIF('Aux DE'!B:B,'Plano SCA'!B18,'Aux DE'!O:O) -> 3.5 | I18: =SUM(J18:CQ18)-H18 -> 0
B19: =C19&"_"&D19 -> INSTRUMENT_PRFRMNG_STTS | C19: INSTRUMENT | D19: PRFRMNG_STTS | F19: =VLOOKUP(B19,'Aux DE'!B:P,15,0) -> SCA SCB1 | G19: =SUMIF('Aux DE'!B:B,'Plano SCA'!B19,'Aux DE'!I:I)+SUMIF('Aux DE'!B:B,'Plano SCA'!B19,'Aux DE'!O:O) -> 3.5 | I19: =SUM(J19:CQ19)-H19 -> 0
B20: =C20&"_"&D20 -> INSTRUMENT_TYP_INSTRMNT | C20: INSTRUMENT | D20: TYP_INSTRMNT | F20: =VLOOKUP(B20,'Aux DE'!B:P,15,0) -> SCA SCB1 | G20: =SUMIF('Aux DE'!B:B,'Plano SCA'!B20,'Aux DE'!I:I)+SUMIF('Aux DE'!B:B,'Plano SCA'!B20,'Aux DE'!O:O) -> 3.5 | I20: =SUM(J20:CQ20)-H20 -> 0
B21: =C21&"_"&D21 -> INSTRUMENT_GRSS_CRRYNG_AMNT_INSTRMNT | C21: INSTRUMENT | D21: GRSS_CRRYNG_AMNT_INSTRMNT | F21: =VLOOKUP(B21,'Aux DE'!B:P,15,0) -> SCA SCB1 | G21: =SUMIF('Aux DE'!B:B,'Plano SCA'!B21,'Aux DE'!I:I)+SUMIF('Aux DE'!B:B,'Plano SCA'!B21,'Aux DE'!O:O) -> 3.5 | I21: =SUM(J21:CQ21)-H21 -> 0
B22: =C22&"_"&D22 -> INSTRUMENT_ACCMLTD_CHNGS_FV_CR_INSTRMNT | C22: INSTRUMENT | D22: ACCMLTD_CHNGS_FV_CR_INSTRMNT | F22: =VLOOKUP(B22,'Aux DE'!B:P,15,0) -> SCA SCB1 | G22: =SUMIF('Aux DE'!B:B,'Plano SCA'!B22,'Aux DE'!I:I)+SUMIF('Aux DE'!B:B,'Plano SCA'!B22,'Aux DE'!O:O) -> 3.5 | I22: =SUM(J22:CQ22)-H22 -> 0
B23: =C23&"_"&D23 -> INSTRUMENT_ACCNTNG_CLSSFCTN | C23: INSTRUMENT | D23: ACCNTNG_CLSSFCTN | F23: =VLOOKUP(B23,'Aux DE'!B:P,15,0) -> SCA SCB1 | G23: =SUMIF('Aux DE'!B:B,'Plano SCA'!B23,'Aux DE'!I:I)+SUMIF('Aux DE'!B:B,'Plano SCA'!B23,'Aux DE'!O:O) -> 3.5 | I23: =SUM(J23:CQ23)-H23 -> 0
B24: =C24&"_"&D24 -> INSTRUMENT_OFF_BLNC_SHT_AMNT_INSTRMNT | C24: INSTRUMENT | D24: OFF_BLNC_SHT_AMNT_INSTRMNT | F24: =VLOOKUP(B24,'Aux DE'!B:P,15,0) -> SCA SCB1 | G24: =SUMIF('Aux DE'!B:B,'Plano SCA'!B24,'Aux DE'!I:I)+SUMIF('Aux DE'!B:B,'Plano SCA'!B24,'Aux DE'!O:O) -> 3.5 | I24: =SUM(J24:CQ24)-H24 -> 0
B25: =C25&"_"&D25 -> INSTRUMENT_PRVSNS_OFF_BLNC_SHT | C25: INSTRUMENT | D25: PRVSNS_OFF_BLNC_SHT | F25: =VLOOKUP(B25,'Aux DE'!B:P,15,0) -> SCA SCB1 | G25: =SUMIF('Aux DE'!B:B,'Plano SCA'!B25,'Aux DE'!I:I)+SUMIF('Aux DE'!B:B,'Plano SCA'!B25,'Aux DE'!O:O) -> 3.5 | I25: =SUM(J25:CQ25)-H25 -> 0
... B36: =C36&"_"&D36 -> INSTRUMENT_RWA_OFF_BLNC | C36: INSTRUMENT | D36: RWA_OFF_BLNC | F36: =VLOOKUP(B36,'Aux DE'!B:P,15,0) -> SCA SCB1 | G36: =SUMIF('Aux DE'!B:B,'Plano SCA'!B36,'Aux DE'!I:I)+SUMIF('Aux DE'!B:B,'Plano SCA'!B36,'Aux DE'!O:O) -> 3.5 | I36: =SUM(J36:CQ36)-H36 -> 0
C37: 4. Especificação de novos requisitos | F37: =COUNTA(D38:D51) -> 14 | G37: =SUM(G38:G51) -> 15 | H37: =G37/8 -> 1.875 | I37: =SUM(J37:CQ37)-H37 -> 0 | U37: 1.75 | V37: 0.125
B38: =C38&"_"&D38 -> INSTRUMENT_CCF | C38: INSTRUMENT | D38: CCF | F38: =VLOOKUP(B38,'Aux DE'!B:P,15,0) -> SCA SCB1 | G38: =SUMIF('Aux DE'!B:B,'Plano SCA'!B38,'Aux DE'!H:H) -> 1 | I38: =SUM(J38:CQ38)-H38 -> 0
B39: =C39&"_"&D39 -> INSTRUMENT_EAD | C39: INSTRUMENT | D39: EAD | F39: =VLOOKUP(B39,'Aux DE'!B:P,15,0) -> SCA SCB1 | G39: =SUMIF('Aux DE'!B:B,'Plano SCA'!B39,'Aux DE'!H:H) -> 1 | I39: =SUM(J39:CQ39)-H39 -> 0
B40: =C40&"_"&D40 -> INSTRUMENT_TYP_OFF_BLNC_PRDCT | C40: INSTRUMENT | D40: TYP_OFF_BLNC_PRDCT | F40: =VLOOKUP(B40,'Aux DE'!B:P,15,0) -> SCA SCB1 | G40: =SUMIF('Aux DE'!B:B,'Plano SCA'!B40,'Aux DE'!H:H) -> 1 | I40: =SUM(J40:CQ40)-H40 -> 0
B41: =C41&"_"&D41 -> INSTR_PROTECTION_COD_SOC | C41: INSTR_PROTECTION | D41: COD_SOC | F41: =VLOOKUP(B41,'Aux DE'!B:P,15,0) -> SCA SCB1 | G41: =SUMIF('Aux DE'!B:B,'Plano SCA'!B41,'Aux DE'!H:H) -> 1 | I41: =SUM(J41:CQ41)-H41 -> 0
B42: =C42&"_"&D42 -> INSTR_PROTECTION_DT_RFRNC | C42: INSTR_PROTECTION | D42: DT_RFRNC | F42: =VLOOKUP(B42,'Aux DE'!B:P,15,0) -> SCA SCB1 | G42: =SUMIF('Aux DE'!B:B,'Plano SCA'!B42,'Aux DE'!H:H) -> 1 | I42: =SUM(J42:CQ42)-H42 -> 0
B43: =C43&"_"&D43 -> INSTR_PROTECTION_INSTRMNT_ID | C43: INSTR_PROTECTION | D43: INSTRMNT_ID | F43: =VLOOKUP(B43,'Aux DE'!B:P,15,0) -> SCA SCB1 | G43: =SUMIF('Aux DE'!B:B,'Plano SCA'!B43,'Aux DE'!H:H) -> 1 | I43: =SUM(J43:CQ43)-H43 -> 0
B44: =C44&"_"&D44 -> INSTR_PROTECTION_PRTCTN_ID | C44: INSTR_PROTECTION | D44: PRTCTN_ID | F44: =VLOOKUP(B44,'Aux DE'!B:P,15,0) -> SCA SCB1 | G44: =SUMIF('Aux DE'!B:B,'Plano SCA'!B44,'Aux DE'!H:H) -> 1 | I44: =SUM(J44:CQ44)-H44 -> 0
B45: =C45&"_"&D45 -> PROTECTION_COD_SOC | C45: PROTECTION | D45: COD_SOC | F45: =VLOOKUP(B45,'Aux DE'!B:P,15,0) -> SCA SCB1 | G45: =SUMIF('Aux DE'!B:B,'Plano SCA'!B45,'Aux DE'!H:H) -> 1 | I45: =SUM(J45:CQ45)-H45 -> 0
B46: =C46&"_"&D46 -> PROTECTION_DT_RFRNC | C46: PROTECTION | D46: DT_RFRNC | F46: =VLOOKUP(B46,'Aux DE'!B:P,15,0) -> SCA SCB1 | G46: =SUMIF('Aux DE'!B:B,'Plano SCA'!B46,'Aux DE'!H:H) -> 1 | I46: =SUM(J46:CQ46)-H46 -> 0
B47: =C47&"_"&D47 -> PROTECTION_PRTCTN_ID | C47: PROTECTION | D47: PRTCTN_ID | F47: =VLOOKUP(B47,'Aux DE'!B:P,15,0) -> SCA SCB1 | G47: =SUMIF('Aux DE'!B:B,'Plano SCA'!B47,'Aux DE'!H:H) -> 1 | I47: =SUM(J47:CQ47)-H47 -> 0
B48: =C48&"_"&D48 -> PROTECTION_TYP_PRTCTN | C48: PROTECTION | D48: TYP_PRTCTN | F48: =VLOOKUP(B48,'Aux DE'!B:P,15,0) -> SCA SCB1 | G48: =SUMIF('Aux DE'!B:B,'Plano SCA'!B48,'Aux DE'!H:H) -> 1 | I48: =SUM(J48:CQ48)-H48 -> 0
B49: =C49&"_"&D49 -> PROTECTION_PRTCTN_VL | C49: PROTECTION | D49: PRTCTN_VL | F49: =VLOOKUP(B49,'Aux DE'!B:P,15,0) -> SCA SCB1 | G49: =SUMIF('Aux DE'!B:B,'Plano SCA'!B49,'Aux DE'!H:H) -> 1 | I49: =SUM(J49:CQ49)-H49 -> 0
... B51: =C51&"_"&D51 -> INSTR_ACTIVITY_PRCNTG_ACTVTY | C51: INSTR_ACTIVITY | D51: PRCNTG_ACTVTY | F51: =VLOOKUP(B51,'Aux DE'!B:P,15,0) -> SCA SCB1 | G51: =SUMIF('Aux DE'!B:B,'Plano SCA'!B51,'Aux DE'!H:H) -> 1 | I51: =SUM(J51:CQ51)-H51 -> 0
C52: 5. Testes/Re-testes | G52: =G53+G54+G100 -> 498.4 | I52: =SUM(J52:CQ52)-H52 -> 0
D53: Testes ao Universo | F53: n.a. | G53: 40 | H53: =G53/8 -> 5 | I53: =SUM(J53:CQ53)-H53 -> 0 | V53: 1.875 | W53: 2 | X53: 1.125
D54: Testes aos Campos | F54: =COUNTA(D55:D99) -> 45 | G54: =SUM(G55:G99) -> 382 | H54: =G54/8 -> 47.75 | I54: =SUM(J54:CQ54)-H54 -> 0 | X54: 0.875 | Y54: 2 | Z54: 2 | AA54: 2 | AB54: 2 | AC54: 2 | AD54: 2 | AE54: 2 | AF54: 2 | AG54: 2 | AH54: 2 | AI54: 2 | AJ54: 2 | AK54: 2 | AL54: 2 | AM54: 2 | AN54: 2 | AO54: 2 | AP54: 2 | AQ54: 2 | AR54: 2 | AS54: 2 | AT54: 2 | AU54: 2 | AV54: 0.875
B55: =C55&"_"&D55 -> INSTRUMENT_INSTRMNT_ID | C55: INSTRUMENT | D55: INSTRMNT_ID | F55: =VLOOKUP(B55,'Aux DE'!B:P,15,0) -> SCA SCB1 | G55: =SUMIF('Aux DE'!B:B,'Plano SCA'!B55,'Aux DE'!I:I)+SUMIF('Aux DE'!B:B,'Plano SCA'!B55,'Aux DE'!O:O) -> 22 | I55: =SUM(J55:CQ55)-H55 -> 0
B56: =C56&"_"&D56 -> INSTRUMENT_CCF | C56: INSTRUMENT | D56: CCF | F56: =VLOOKUP(B56,'Aux DE'!B:P,15,0) -> SCA SCB1 | G56: =SUMIF('Aux DE'!B:B,'Plano SCA'!B56,'Aux DE'!I:I)+SUMIF('Aux DE'!B:B,'Plano SCA'!B56,'Aux DE'!O:O) -> 3.5 | I56: =SUM(J56:CQ56)-H56 -> 0
B57: =C57&"_"&D57 -> INSTRUMENT_EAD | C57: INSTRUMENT | D57: EAD | F57: =VLOOKUP(B57,'Aux DE'!B:P,15,0) -> SCA SCB1 | G57: =SUMIF('Aux DE'!B:B,'Plano SCA'!B57,'Aux DE'!I:I)+SUMIF('Aux DE'!B:B,'Plano SCA'!B57,'Aux DE'!O:O) -> 3.5 | I57: =SUM(J57:CQ57)-H57 -> 0
B58: =C58&"_"&D58 -> INSTRUMENT_AVRG_BLNC | C58: INSTRUMENT | D58: AVRG_BLNC | F58: =VLOOKUP(B58,'Aux DE'!B:P,15,0) -> SCA SCB1 | G58: =SUMIF('Aux DE'!B:B,'Plano SCA'!B58,'Aux DE'!I:I)+SUMIF('Aux DE'!B:B,'Plano SCA'!B58,'Aux DE'!O:O) -> 7.5 | I58: =SUM(J58:CQ58)-H58 -> 0
B59: =C59&"_"&D59 -> INSTRUMENT_NW_BSNSS | C59: INSTRUMENT | D59: NW_BSNSS | F59: =VLOOKUP(B59,'Aux DE'!B:P,15,0) -> SCA SCB 2 | G59: =SUMIF('Aux DE'!B:B,'Plano SCA'!B59,'Aux DE'!I:I)+SUMIF('Aux DE'!B:B,'Plano SCA'!B59,'Aux DE'!O:O) -> 15 | I59: =SUM(J59:CQ59)-H59 -> 0
B60: =C60&"_"&D60 -> INSTRUMENT_GRSS_INTRST_INCM | C60: INSTRUMENT | D60: GRSS_INTRST_INCM | F60: =VLOOKUP(B60,'Aux DE'!B:P,15,0) -> SCA SCB 2 | G60: =SUMIF('Aux DE'!B:B,'Plano SCA'!B60,'Aux DE'!I:I)+SUMIF('Aux DE'!B:B,'Plano SCA'!B60,'Aux DE'!O:O) -> 18 | I60: =SUM(J60:CQ60)-H60 -> 0
B61: =C61&"_"&D61 -> INSTRUMENT_GRSS_CMMSSN_INCM | C61: INSTRUMENT | D61: GRSS_CMMSSN_INCM | F61: =VLOOKUP(B61,'Aux DE'!B:P,15,0) -> SCA SCB 2 | G61: =SUMIF('Aux DE'!B:B,'Plano SCA'!B61,'Aux DE'!I:I)+SUMIF('Aux DE'!B:B,'Plano SCA'!B61,'Aux DE'!O:O) -> 18 | I61: =SUM(J61:CQ61)-H61 -> 0
B62: =C62&"_"&D62 -> INSTRUMENT_INTRNL_TRNSFR_RT | C62: INSTRUMENT | D62: INTRNL_TRNSFR_RT | F62: =VLOOKUP(B62,'Aux DE'!B:P,15,0) -> SCA SCB1 | G62: =SUMIF('Aux DE'!B:B,'Plano SCA'!B62,'Aux DE'!I:I)+SUMIF('Aux DE'!B:B,'Plano SCA'!B62,'Aux DE'!O:O) -> 7.5 | I62: =SUM(J62:CQ62)-H62 -> 0
B63: =C63&"_"&D63 -> INSTRUMENT_NT_LN_LSS_PRVSN | C63: INSTRUMENT | D63: NT_LN_LSS_PRVSN | F63: =VLOOKUP(B63,'Aux DE'!B:P,15,0) -> SCA SCB1 | G63: =SUMIF('Aux DE'!B:B,'Plano SCA'!B63,'Aux DE'!I:I)+SUMIF('Aux DE'!B:B,'Plano SCA'!B63,'Aux DE'!O:O) -> 7.5 | I63: =SUM(J63:CQ63)-H63 -> 0
B64: =C64&"_"&D64 -> INSTRUMENT_BSNSS_AREA | C64: INSTRUMENT | D64: BSNSS_AREA | F64: =VLOOKUP(B64,'Aux DE'!B:P,15,0) -> SCA SCB1 | G64: =SUMIF('Aux DE'!B:B,'Plano SCA'!B64,'Aux DE'!I:I)+SUMIF('Aux DE'!B:B,'Plano SCA'!B64,'Aux DE'!O:O) -> 35 | I64: =SUM(J64:CQ64)-H64 -> 0
B65: =C65&"_"&D65 -> INSTRUMENT_MNGMNT_PRDCT | C65: INSTRUMENT | D65: MNGMNT_PRDCT | F65: =VLOOKUP(B65,'Aux DE'!B:P,15,0) -> SCA SCB1 | G65: =SUMIF('Aux DE'!B:B,'Plano SCA'!B65,'Aux DE'!I:I)+SUMIF('Aux DE'!B:B,'Plano SCA'!B65,'Aux DE'!O:O) -> 18 | I65: =SUM(J65:CQ65)-H65 -> 0
B66: =C66&"_"&D66 -> INSTRUMENT_GRSS_CMMSSN_EXPNS | C66: INSTRUMENT | D66: GRSS_CMMSSN_EXPNS | F66: =VLOOKUP(B66,'Aux DE'!B:P,15,0) -> SCA SCB1 | G66: =SUMIF('Aux DE'!B:B,'Plano SCA'!B66,'Aux DE'!I:I)+SUMIF('Aux DE'!B:B,'Plano SCA'!B66,'Aux DE'!O:O) -> 7.5 | I66: =SUM(J66:CQ66)-H66 -> 0
... B99: =C99&"_"&D99 -> INSTR_ACTIVITY_SSTNBL_INDCTR | C99: INSTR_ACTIVITY | D99: SSTNBL_INDCTR | F99: =VLOOKUP(B99,'Aux DE'!B:P,15,0) -> SCA SCB 2 | G99: =SUMIF('Aux DE'!B:B,'Plano SCA'!B99,'Aux DE'!I:I)+SUMIF('Aux DE'!B:B,'Plano SCA'!B99,'Aux DE'!O:O) -> 18 | I99: =SUM(J99:CQ99)-H99 -> 0
D100: Re-testes | G100: =H100*8 -> 76.4 | H100: =0.2*H54 -> 9.55 | I100: =SUM(J100:CQ100)-H100 -> 0 | AV100: 1.125 | AW100: 2 | AX100: 2 | AY100: 2 | AZ100: 2 | BA100: 0.425
C101: 5. Documentação | G101: =H101*8 -> 80 | H101: =10 -> 10 | I101: =SUM(J101:CQ101)-H101 -> 0 | BA101: 1.575 | BB101: 2 | BC101: 2 | BD101: 2 | BE101: 2 | BF101: 0.425
BF102: x
C104: Horas Total | D104: =SUM(J1:CA1) -> 823.2 | E104: SMART TOTAL
C105: Horas Novos Requisitos | E105: SMART NOVOS REQUISITOS

Sheet LISTA - Abril2024
A1: ID Data field / Field order | C1: Table | D1: Data field | E1: Field name | F1: Structural ECB Loan Tape | G1: Green Dashboard | H1: Pillar III ESG | I1: ESG Risks
A2: EN.001 | B2: =C2&"_"&D2 -> ENTITY_COD_SOC | C2: ENTITY | D2: COD_SOC | E2: Entity code of the informing society. | F2: Y | G2: N | H2: Y | I2: Y
A3: EN.002 | B3: =C3&"_"&D3 -> ENTITY_CNTRY | C3: ENTITY | D3: CNTRY | E3: Country of counterparty residence | F3: Y | G3: N | H3: Y | I3: Y
A4: EN.003 | B4: =C4&"_"&D4 -> ENTITY_DT_BRTH | C4: ENTITY | D4: DT_BRTH | E4: Birth date counterparty | F4: Y | G4: N | H4: N | I4: N
A5: EN.004 | B5: =C5&"_"&D5 -> ENTITY_DT_DFLT_STTS | C5: ENTITY | D5: DT_DFLT_STTS | E5: Date of default status | F5: Y | G5: N | H5: N | I5: N
A6: EN.005 | B6: =C6&"_"&D6 -> ENTITY_DT_FNNCL_STTMTS | C6: ENTITY | D6: DT_FNNCL_STTMTS | E6: Date of financial statements | F6: Y | G6: N | H6: N | I6: N
A7: EN.006 | B7: =C7&"_"&D7 -> ENTITY_DT_FNNCL_STTMTS_PRVS | C7: ENTITY | D7: DT_FNNCL_STTMTS_PRVS | E7: Date of previous fiscal year financial statements | F7: Y | G7: N | H7: N | I7: N
A8: EN.007 | B8: =C8&"_"&D8 -> ENTITY_DT_INTTN_LGL_PRCDNGS_LE | C8: ENTITY | D8: DT_INTTN_LGL_PRCDNGS_LE | E8: Date of initiation of legal proceedings counterparty (LE) | F8: Y | G8: N | H8: N | I8: N
A9: EN.008 | B9: =C9&"_"&D9 -> ENTITY_DT_PRFRMNG_STTS_LE | C9: ENTITY | D9: DT_PRFRMNG_STTS_LE | E9: Date of performing status | F9: Y | G9: N | H9: N | I9: N
A10: EN.009 | B10: =C10&"_"&D10 -> ENTITY_DT_RFRNC | C10: ENTITY | D10: DT_RFRNC | E10: Reference date. | F10: Y | G10: N | H10: Y | I10: N
A11: EN.010 | B11: =C11&"_"&D11 -> ENTITY_ENTTY_ID | C11: ENTITY | D11: ENTTY_ID | E11: Entity ID | F11: Y | G11: N | H11: Y | I11: Y
A12: EN.011 | B12: =C12&"_"&D12 -> ENTITY_GCC_PRNT_ID | C12: ENTITY | D12: GCC_PRNT_ID | E12: Identifier for the parent entity of a group of connected clients | F12: Y | G12: N | H12: N | I12: N
A13: EN.012 | B13: =C13&"_"&D13 -> ENTITY_GCC_PRNT_NM | C13: ENTITY | D13: GCC_PRNT_NM | E13: Name of the parent entity of a group of connected clients | F13: Y | G13: N | H13: N | I13: N
... A478: PR.066 | B478: =C478&"_"&D478 -> PROTECTION_LN_PSTN | C478: PROTECTION | D478: LN_PSTN | E478: Lien position | F478: Y | G478: N | H478: N | I478: N

Sheet LISTA - Atual
A1: ID Data field / Field order | C1: Table | D1: Data field | E1: Field name | F1: Structural ECB Loan Tape | G1: Green Dashboard | H1: Pillar III ESG | I1: ESG Risks | J1: SCIB GLOBAL FIELD | L1: Structural ECB Loan Tape | M1: val | N1: Green Dashboard | O1: val | P1: Pillar III ESG | Q1: val | R1: ESG Risks | S1: val | U1: xx
A2: EN.001 | B2: =C2&"_"&D2 -> ENTITY_COD_SOC | C2: ENTITY | D2: COD_SOC | E2: Entity code of the informing society. | F2: Y | G2: N | H2: Y | I2: Y | J2: N | L2: =IFERROR(VLOOKUP($B2,'Lista - Âmbito Projeto GD'!$B$3:$F$71,5,0),"Campo eliminado") -> Campo eliminado | M2: =IF(L2="Campo eliminado","Campo eliminado",IF(L2=F2,"Igual","Diferente")) -> Campo eliminado | N2: =IFERROR(VLOOKUP($B2,'Lista - Âmbito Projeto GD'!$B$3:$K$71,6,0),"Campo eliminado") -> Campo eliminado | O2: =IF(N2="Campo eliminado","Campo eliminado",IF(N2=G2,"Igual","Diferente")) -> Campo eliminado | P2: =IFERROR(VLOOKUP($B2,'Lista - Âmbito Projeto GD'!$B$3:$K$71,7,0),"Campo eliminado") -> Campo eliminado | Q2: =IF(P2="Campo eliminado","Campo eliminado",IF(P2=H2,"Igual","Diferente")) -> Campo eliminado | R2: =IFERROR(VLOOKUP($B2,'Lista - Âmbito Projeto GD'!$B$3:$K$71,9,0),"Campo eliminado") -> Campo eliminado | S2: =IF(R2="Campo eliminado","Campo eliminado",IF(R2=I2,"Igual","Diferente")) -> Campo eliminado | U2: =VLOOKUP(B2,DataLake!$A$4:$A$429,1,0) -> ENTITY_COD_SOC
A3: EN.002 | B3: =C3&"_"&D3 -> ENTITY_CNTRY | C3: ENTITY | D3: CNTRY | E3: Country of counterparty residence | F3: Y | G3: N | H3: Y | I3: Y | J3: N | L3: =IFERROR(VLOOKUP($B3,'Lista - Âmbito Projeto GD'!$B$3:$F$71,5,0),"Campo eliminado") -> Campo eliminado | M3: =IF(L3="Campo eliminado","Campo eliminado",IF(L3=F3,"Igual","Diferente")) -> Campo eliminado | N3: =IFERROR(VLOOKUP($B3,'Lista - Âmbito Projeto GD'!$B$3:$K$71,6,0),"Campo eliminado") -> Campo eliminado | O3: =IF(N3="Campo eliminado","Campo eliminado",IF(N3=G3,"Igual","Diferente")) -> Campo eliminado | P3: =IFERROR(VLOOKUP($B3,'Lista - Âmbito Projeto GD'!$B$3:$K$71,7,0),"Campo eliminado") -> Campo eliminado | Q3: =IF(P3="Campo eliminado","Campo eliminado",IF(P3=H3,"Igual","Diferente")) -> Campo eliminado | R3: =IFERROR(VLOOKUP($B3,'Lista - Âmbito Projeto GD'!$B$3:$K$71,9,0),"Campo eliminado") -> Campo eliminado | S3: =IF(R3="Campo eliminado","Campo eliminado",IF(R3=I3,"Igual","Diferente")) -> Campo eliminado | U3: =VLOOKUP(B3,DataLake!$A$4:$A$429,1,0) -> ENTITY_CNTRY
A4: EN.003 | B4: =C4&"_"&D4 -> ENTITY_DT_BRTH | C4: ENTITY | D4: DT_BRTH | E4: Birth date counterparty | F4: Y | G4: N | H4: N | I4: N | J4: N | L4: =IFERROR(VLOOKUP($B4,'Lista - Âmbito Projeto GD'!$B$3:$F$71,5,0),"Campo eliminado") -> Campo eliminado | M4: =IF(L4="Campo eliminado","Campo eliminado",IF(L4=F4,"Igual","Diferente")) -> Campo eliminado | N4: =IFERROR(VLOOKUP($B4,'Lista - Âmbito Projeto GD'!$B$3:$K$71,6,0),"Campo eliminado") -> Campo eliminado | O4: =IF(N4="Campo eliminado","Campo eliminado",IF(N4=G4,"Igual","Diferente")) -> Campo eliminado | P4: =IFERROR(VLOOKUP($B4,'Lista - Âmbito Projeto GD'!$B$3:$K$71,7,0),"Campo eliminado") -> Campo eliminado | Q4: =IF(P4="Campo eliminado","Campo eliminado",IF(P4=H4,"Igual","Diferente")) -> Campo eliminado | R4: =IFERROR(VLOOKUP($B4,'Lista - Âmbito Projeto GD'!$B$3:$K$71,9,0),"Campo eliminado") -> Campo eliminado | S4: =IF(R4="Campo eliminado","Campo eliminado",IF(R4=I4,"Igual","Diferente")) -> Campo eliminado | U4: =VLOOKUP(B4,DataLake!$A$4:$A$429,1,0) -> ENTITY_DT_BRTH
A5: EN.004 | B5: =C5&"_"&D5 -> ENTITY_DT_DFLT_STTS | C5: ENTITY | D5: DT_DFLT_STTS | E5: Date of default status | F5: Y | G5: N | H5: N | I5: N | J5: DT_DFLT_STTS | L5: =IFERROR(VLOOKUP($B5,'Lista - Âmbito Projeto GD'!$B$3:$F$71,5,0),"Campo eliminado") -> Campo eliminado | M5: =IF(L5="Campo eliminado","Campo eliminado",IF(L5=F5,"Igual","Diferente")) -> Campo eliminado | N5: =IFERROR(VLOOKUP($B5,'Lista - Âmbito Projeto GD'!$B$3:$K$71,6,0),"Campo eliminado") -> Campo eliminado | O5: =IF(N5="Campo eliminado","Campo eliminado",IF(N5=G5,"Igual","Diferente")) -> Campo eliminado | P5: =IFERROR(VLOOKUP($B5,'Lista - Âmbito Projeto GD'!$B$3:$K$71,7,0),"Campo eliminado") -> Campo eliminado | Q5: =IF(P5="Campo eliminado","Campo eliminado",IF(P5=H5,"Igual","Diferente")) -> Campo eliminado | R5: =IFERROR(VLOOKUP($B5,'Lista - Âmbito Projeto GD'!$B$3:$K$71,9,0),"Campo eliminado") -> Campo eliminado | S5: =IF(R5="Campo eliminado","Campo eliminado",IF(R5=I5,"Igual","Diferente")) -> Campo eliminado | U5: =VLOOKUP(B5,DataLake!$A$4:$A$429,1,0) -> ENTITY_DT_DFLT_STTS
A6: EN.005 | B6: =C6&"_"&D6 -> ENTITY_DT_FNNCL_STTMTS | C6: ENTITY | D6: DT_FNNCL_STTMTS | E6: Date of financial statements | F6: Y | G6: N | H6: N | I6: N | J6: DT_FNNCL_STTMTS | L6: =IFERROR(VLOOKUP($B6,'Lista - Âmbito Projeto GD'!$B$3:$F$71,5,0),"Campo eliminado") -> Campo eliminado | M6: =IF(L6="Campo eliminado","Campo eliminado",IF(L6=F6,"Igual","Diferente")) -> Campo eliminado | N6: =IFERROR(VLOOKUP($B6,'Lista - Âmbito Projeto GD'!$B$3:$K$71,6,0),"Campo eliminado") -> Campo eliminado | O6: =IF(N6="Campo eliminado","Campo eliminado",IF(N6=G6,"Igual","Diferente")) -> Campo eliminado | P6: =IFERROR(VLOOKUP($B6,'Lista - Âmbito Projeto GD'!$B$3:$K$71,7,0),"Campo eliminado") -> Campo eliminado | Q6: =IF(P6="Campo eliminado","Campo eliminado",IF(P6=H6,"Igual","Diferente")) -> Campo eliminado | R6: =IFERROR(VLOOKUP($B6,'Lista - Âmbito Projeto GD'!$B$3:$K$71,9,0),"Campo eliminado") -> Campo eliminado | S6: =IF(R6="Campo eliminado","Campo eliminado",IF(R6=I6,"Igual","Diferente")) -> Campo eliminado | U6: =VLOOKUP(B6,DataLake!$A$4:$A$429,1,0) -> ENTITY_DT_FNNCL_STTMTS
A7: EN.006 | B7: =C7&"_"&D7 -> ENTITY_DT_FNNCL_STTMTS_PRVS | C7: ENTITY | D7: DT_FNNCL_STTMTS_PRVS | E7: Date of previous fiscal year financial statements | F7: Y | G7: N | H7: N | I7: N | J7: DT_FNNCL_STTMTS_PRVS | L7: =IFERROR(VLOOKUP($B7,'Lista - Âmbito Projeto GD'!$B$3:$F$71,5,0),"Campo eliminado") -> Campo eliminado | M7: =IF(L7="Campo eliminado","Campo eliminado",IF(L7=F7,"Igual","Diferente")) -> Campo eliminado | N7: =IFERROR(VLOOKUP($B7,'Lista - Âmbito Projeto GD'!$B$3:$K$71,6,0),"Campo eliminado") -> Campo eliminado | O7: =IF(N7="Campo eliminado","Campo eliminado",IF(N7=G7,"Igual","Diferente")) -> Campo eliminado | P7: =IFERROR(VLOOKUP($B7,'Lista - Âmbito Projeto GD'!$B$3:$K$71,7,0),"Campo eliminado") -> Campo eliminado | Q7: =IF(P7="Campo eliminado","Campo eliminado",IF(P7=H7,"Igual","Diferente")) -> Campo eliminado | R7: =IFERROR(VLOOKUP($B7,'Lista - Âmbito Projeto GD'!$B$3:$K$71,9,0),"Campo eliminado") -> Campo eliminado | S7: =IF(R7="Campo eliminado","Campo eliminado",IF(R7=I7,"Igual","Diferente")) -> Campo eliminado | U7: =VLOOKUP(B7,DataLake!$A$4:$A$429,1,0) -> ENTITY_DT_FNNCL_STTMTS_PRVS
A8: EN.007 | B8: =C8&"_"&D8 -> ENTITY_DT_INTTN_LGL_PRCDNGS_LE | C8: ENTITY | D8: DT_INTTN_LGL_PRCDNGS_LE | E8: Date of initiation of legal proceedings counterparty (LE) | F8: Y | G8: N | H8: N | I8: N | J8: N | L8: =IFERROR(VLOOKUP($B8,'Lista - Âmbito Projeto GD'!$B$3:$F$71,5,0),"Campo eliminado") -> Campo eliminado | M8: =IF(L8="Campo eliminado","Campo eliminado",IF(L8=F8,"Igual","Diferente")) -> Campo eliminado | N8: =IFERROR(VLOOKUP($B8,'Lista - Âmbito Projeto GD'!$B$3:$K$71,6,0),"Campo eliminado") -> Campo eliminado | O8: =IF(N8="Campo eliminado","Campo eliminado",IF(N8=G8,"Igual","Diferente")) -> Campo eliminado | P8: =IFERROR(VLOOKUP($B8,'Lista - Âmbito Projeto GD'!$B$3:$K$71,7,0),"Campo eliminado") -> Campo eliminado | Q8: =IF(P8="Campo eliminado","Campo eliminado",IF(P8=H8,"Igual","Diferente")) -> Campo eliminado | R8: =IFERROR(VLOOKUP($B8,'Lista - Âmbito Projeto GD'!$B$3:$K$71,9,0),"Campo eliminado") -> Campo eliminado | S8: =IF(R8="Campo eliminado","Campo eliminado",IF(R8=I8,"Igual","Diferente")) -> Campo eliminado | U8: =VLOOKUP(B8,DataLake!$A$4:$A$429,1,0) -> ENTITY_DT_INTTN_LGL_PRCDNGS_LE
A9: EN.008 | B9: =C9&"_"&D9 -> ENTITY_DT_PRFRMNG_STTS_LE | C9: ENTITY | D9: DT_PRFRMNG_STTS_LE | E9: Date of performing status | F9: Y | G9: N | H9: N | I9: N | J9: N | L9: =IFERROR(VLOOKUP($B9,'Lista - Âmbito Projeto GD'!$B$3:$F$71,5,0),"Campo eliminado") -> Campo eliminado | M9: =IF(L9="Campo eliminado","Campo eliminado",IF(L9=F9,"Igual","Diferente")) -> Campo eliminado | N9: =IFERROR(VLOOKUP($B9,'Lista - Âmbito Projeto GD'!$B$3:$K$71,6,0),"Campo eliminado") -> Campo eliminado | O9: =IF(N9="Campo eliminado","Campo eliminado",IF(N9=G9,"Igual","Diferente")) -> Campo eliminado | P9: =IFERROR(VLOOKUP($B9,'Lista - Âmbito Projeto GD'!$B$3:$K$71,7,0),"Campo eliminado") -> Campo eliminado | Q9: =IF(P9="Campo eliminado","Campo eliminado",IF(P9=H9,"Igual","Diferente")) -> Campo eliminado | R9: =IFERROR(VLOOKUP($B9,'Lista - Âmbito Projeto GD'!$B$3:$K$71,9,0),"Campo eliminado") -> Campo eliminado | S9: =IF(R9="Campo eliminado","Campo eliminado",IF(R9=I9,"Igual","Diferente")) -> Campo eliminado | U9: =VLOOKUP(B9,DataLake!$A$4:$A$429,1,0) -> ENTITY_DT_PRFRMNG_STTS_LE
A10: EN.009 | B10: =C10&"_"&D10 -> ENTITY_DT_RFRNC | C10: ENTITY | D10: DT_RFRNC | E10: Reference date. | F10: Y | G10: N | H10: Y | I10: N | J10: N | L10: =IFERROR(VLOOKUP($B10,'Lista - Âmbito Projeto GD'!$B$3:$F$71,5,0),"Campo eliminado") -> Campo eliminado | M10: =IF(L10="Campo eliminado","Campo eliminado",IF(L10=F10,"Igual","Diferente")) -> Campo eliminado | N10: =IFERROR(VLOOKUP($B10,'Lista - Âmbito Projeto GD'!$B$3:$K$71,6,0),"Campo eliminado") -> Campo eliminado | O10: =IF(N10="Campo eliminado","Campo eliminado",IF(N10=G10,"Igual","Diferente")) -> Campo eliminado | P10: =IFERROR(VLOOKUP($B10,'Lista - Âmbito Projeto GD'!$B$3:$K$71,7,0),"Campo eliminado") -> Campo eliminado | Q10: =IF(P10="Campo eliminado","Campo eliminado",IF(P10=H10,"Igual","Diferente")) -> Campo eliminado | R10: =IFERROR(VLOOKUP($B10,'Lista - Âmbito Projeto GD'!$B$3:$K$71,9,0),"Campo eliminado") -> Campo eliminado | S10: =IF(R10="Campo eliminado","Campo eliminado",IF(R10=I10,"Igual","Diferente")) -> Campo eliminado | U10: =VLOOKUP(B10,DataLake!$A$4:$A$429,1,0) -> #N/A
A11: EN.010 | B11: =C11&"_"&D11 -> ENTITY_ENTTY_ID | C11: ENTITY | D11: ENTTY_ID | E11: Entity ID | F11: Y | G11: N | H11: Y | I11: Y | J11: N | L11: =IFERROR(VLOOKUP($B11,'Lista - Âmbito Projeto GD'!$B$3:$F$71,5,0),"Campo eliminado") -> Campo eliminado | M11: =IF(L11="Campo eliminado","Campo eliminado",IF(L11=F11,"Igual","Diferente")) -> Campo eliminado | N11: =IFERROR(VLOOKUP($B11,'Lista - Âmbito Projeto GD'!$B$3:$K$71,6,0),"Campo eliminado") -> Campo eliminado | O11: =IF(N11="Campo eliminado","Campo eliminado",IF(N11=G11,"Igual","Diferente")) -> Campo eliminado | P11: =IFERROR(VLOOKUP($B11,'Lista - Âmbito Projeto GD'!$B$3:$K$71,7,0),"Campo eliminado") -> Campo eliminado | Q11: =IF(P11="Campo eliminado","Campo eliminado",IF(P11=H11,"Igual","Diferente")) -> Campo eliminado | R11: =IFERROR(VLOOKUP($B11,'Lista - Âmbito Projeto GD'!$B$3:$K$71,9,0),"Campo eliminado") -> Campo eliminado | S11: =IF(R11="Campo eliminado","Campo eliminado",IF(R11=I11,"Igual","Diferente")) -> Campo eliminado | U11: =VLOOKUP(B11,DataLake!$A$4:$A$429,1,0) -> ENTITY_ENTTY_ID
A12: EN.011 | B12: =C12&"_"&D12 -> ENTITY_GCC_PRNT_ID | C12: ENTITY | D12: GCC_PRNT_ID | E12: Identifier for the parent entity of a group of connected clients | F12: Y | G12: N | H12: N | I12: N | J12: GCC_PRNT_ID | L12: =IFERROR(VLOOKUP($B12,'Lista - Âmbito Projeto GD'!$B$3:$F$71,5,0),"Campo eliminado") -> Campo eliminado | M12: =IF(L12="Campo eliminado","Campo eliminado",IF(L12=F12,"Igual","Diferente")) -> Campo eliminado | N12: =IFERROR(VLOOKUP($B12,'Lista - Âmbito Projeto GD'!$B$3:$K$71,6,0),"Campo eliminado") -> Campo eliminado | O12: =IF(N12="Campo eliminado","Campo eliminado",IF(N12=G12,"Igual","Diferente")) -> Campo eliminado | P12: =IFERROR(VLOOKUP($B12,'Lista - Âmbito Projeto GD'!$B$3:$K$71,7,0),"Campo eliminado") -> Campo eliminado | Q12: =IF(P12="Campo eliminado","Campo eliminado",IF(P12=H12,"Igual","Diferente")) -> Campo eliminado | R12: =IFERROR(VLOOKUP($B12,'Lista - Âmbito Projeto GD'!$B$3:$K$71,9,0),"Campo eliminado") -> Campo eliminado | S12: =IF(R12="Campo eliminado","Campo eliminado",IF(R12=I12,"Igual","Diferente")) -> Campo eliminado | U12: =VLOOKUP(B12,DataLake!$A$4:$A$429,1,0) -> ENTITY_GCC_PRNT_ID
A13: EN.012 | B13: =C13&"_"&D13 -> ENTITY_GCC_PRNT_NM | C13: ENTITY | D13: GCC_PRNT_NM | E13: Name of the parent entity of a group of connected clients | F13: Y | G13: N | H13: N | I13: N | J13: GCC_PRNT_NM | L13: =IFERROR(VLOOKUP($B13,'Lista - Âmbito Projeto GD'!$B$3:$F$71,5,0),"Campo eliminado") -> Campo eliminado | M13: =IF(L13="Campo eliminado","Campo eliminado",IF(L13=F13,"Igual","Diferente")) -> Campo eliminado | N13: =IFERROR(VLOOKUP($B13,'Lista - Âmbito Projeto GD'!$B$3:$K$71,6,0),"Campo eliminado") -> Campo eliminado | O13: =IF(N13="Campo eliminado","Campo eliminado",IF(N13=G13,"Igual","Diferente")) -> Campo eliminado | P13: =IFERROR(VLOOKUP($B13,'Lista - Âmbito Projeto GD'!$B$3:$K$71,7,0),"Campo eliminado") -> Campo eliminado | Q13: =IF(P13="Campo eliminado","Campo eliminado",IF(P13=H13,"Igual","Diferente")) -> Campo eliminado | R13: =IFERROR(VLOOKUP($B13,'Lista - Âmbito Projeto GD'!$B$3:$K$71,9,0),"Campo eliminado") -> Campo eliminado | S13: =IF(R13="Campo eliminado","Campo eliminado",IF(R13=I13,"Igual","Diferente")) -> Campo eliminado | U13: =VLOOKUP(B13,DataLake!$A$4:$A$429,1,0) -> ENTITY_GCC_PRNT_NM
... A444: PR.063 | B444: =C444&"_"&D444 -> PROTECTION_YR_CNSTRCTN | C444: PROTECTION | D444: YR_CNSTRCTN | E444: Year of construction | F444: Y | G444: N | H444: N | I444: N | J444: N | L444: =IFERROR(VLOOKUP($B444,'Lista - Âmbito Projeto GD'!$B$3:$F$71,5,0),"Campo eliminado") -> Campo eliminado | M444: =IF(L444="Campo eliminado","Campo eliminado",IF(L444=F444,"Igual","Diferente")) -> Campo eliminado | N444: =IFERROR(VLOOKUP($B444,'Lista - Âmbito Projeto GD'!$B$3:$K$71,6,0),"Campo eliminado") -> Campo eliminado | O444: =IF(N444="Campo eliminado","Campo eliminado",IF(N444=G444,"Igual","Diferente")) -> Campo eliminado | P444: =IFERROR(VLOOKUP($B444,'Lista - Âmbito Projeto GD'!$B$3:$K$71,7,0),"Campo eliminado") -> Campo eliminado | Q444: =IF(P444="Campo eliminado","Campo eliminado",IF(P444=H444,"Igual","Diferente")) -> Campo eliminado | R444: =IFERROR(VLOOKUP($B444,'Lista - Âmbito Projeto GD'!$B$3:$K$71,9,0),"Campo eliminado") -> Campo eliminado | S444: =IF(R444="Campo eliminado","Campo eliminado",IF(R444=I444,"Igual","Diferente")) -> Campo eliminado | U444: =VLOOKUP(B444,DataLake!$A$4:$A$429,1,0) -> PROTECTION_YR_CNSTRCTN

Sheet Aux DE
F3: =SUBTOTAL(9,F5:F72) -> 38.3 | H3: =SUBTOTAL(9,H5:H72) -> 2 | I3: =SUBTOTAL(9,I5:I72) -> 4 | O3: =SUBTOTAL(9,O5:O72) -> 10 | Q3: =SUBTOTAL(9,Q5:Q72) -> 38.3 | R3: =SUBTOTAL(9,R5:R72) -> 26.2 | S3: =SUBTOTAL(9,S5:S72) -> 12.1
B4: CONCAT | C4: Table | D4: Data field | E4: Est anterior | F4: Est anterior | G4: Complexidade (todos) | H4: Especificação | I4: Simulação | J4: 2. Testes comparativos | K4: Complexidade (code list) | L4: 3. Val. Code List | M4: 4. Val. Formatos | N4: 5. Val.Controlos Corp. | O4: Total Testes | P4: Cenário | Q4: Tempo SC1 | R4: Tempo SC B1 | S4: Tempo SC B2 | T4: Flg Concluído
B5: INSTRUMENT_COD_SOC | C5: INSTRUMENT | D5: COD_SOC | E5: Baixa | F5: =VLOOKUP(B5,'[1]Plano GD - SC1'!$A:$F,6,0) -> 2 | G5: M. Baixa | H5: 0 | I5: 1 | J5: 1 | K5: n.a. | L5: 0 | M5: 0.5 | N5: 1 | O5: 2.5 | P5: SCA SCB1 | Q5: =VLOOKUP(B5,'[1]Plano GD - SC1'!$A:$F,6,0) -> 2 | R5: =IFERROR(VLOOKUP(B5,'[1]Plano GD - SCB 1'!$A:$F,6,0),0) -> 2 | S5: =IFERROR(VLOOKUP(B5,'[1]Plano GD - SCB 2'!$A:$F,6,0),0) -> 0 | T5: Y
B6: INSTRUMENT_SUBPORTFOLIO_ID | C6: INSTRUMENT | D6: SUBPORTFOLIO_ID | E6: Baixa | F6: =VLOOKUP(B6,'[1]Plano GD - SC1'!$A:$F,6,0) -> 2 | G6: M. Baixa | H6: 0 | I6: 1 | J6: 1 | K6: n.a. | L6: 0 | M6: 0.5 | N6: 1 | O6: 2.5 | P6: SCA SCB1 | Q6: =VLOOKUP(B6,'[1]Plano GD - SC1'!$A:$F,6,0) -> 2 | R6: =IFERROR(VLOOKUP(B6,'[1]Plano GD - SCB 1'!$A:$F,6,0),0) -> 2 | S6: =IFERROR(VLOOKUP(B6,'[1]Plano GD - SCB 2'!$A:$F,6,0),0) -> 0 | T6: Y
B7: INSTRUMENT_DT_RFRNC | C7: INSTRUMENT | D7: DT_RFRNC | E7: Baixa | F7: =VLOOKUP(B7,'[1]Plano GD - SC1'!$A:$F,6,0) -> 2 | G7: M. Baixa | H7: 0 | I7: 1 | J7: 1 | K7: n.a. | L7: 0 | M7: 0.5 | N7: 1 | O7: 2.5 | P7: SCA SCB1 | Q7: =VLOOKUP(B7,'[1]Plano GD - SC1'!$A:$F,6,0) -> 2 | R7: =IFERROR(VLOOKUP(B7,'[1]Plano GD - SCB 1'!$A:$F,6,0),0) -> 2 | S7: =IFERROR(VLOOKUP(B7,'[1]Plano GD - SCB 2'!$A:$F,6,0),0) -> 0 | T7: Y
B8: INSTRUMENT_INSTRMNT_ID | C8: INSTRUMENT | D8: INSTRMNT_ID | E8: Alta | F8: =VLOOKUP(B8,'[1]Plano GD - SC1'!$A:$F,6,0) -> 25.2 | G8: M. Alta | H8: 0 | I8: 12 | J8: 3 | K8: n.a. | L8: 0 | M8: 1 | N8: 2 | O8: 10 | P8: SCA SCB1 | Q8: =VLOOKUP(B8,'[1]Plano GD - SC1'!$A:$F,6,0) -> 25.2 | R8: =IFERROR(VLOOKUP(B8,'[1]Plano GD - SCB 1'!$A:$F,6,0),0) -> 25.2 | S8: =IFERROR(VLOOKUP(B8,'[1]Plano GD - SCB 2'!$A:$F,6,0),0) -> 0 | T8: N
B9: INSTRUMENT_DFLT_STTS_INSTRMNT | C9: INSTRUMENT | D9: DFLT_STTS_INSTRMNT | E9: Baixa | F9: =VLOOKUP(B9,'[1]Plano GD - SC1'!$A:$F,6,0) -> 2 | G9: M. Baixa | H9: 0 | I9: 1 | J9: 1 | K9: n.a. | L9: 0 | M9: 0.5 | N9: 1 | O9: 2.5 | P9: SCA SCB1 | Q9: =VLOOKUP(B9,'[1]Plano GD - SC1'!$A:$F,6,0) -> 2 | R9: =IFERROR(VLOOKUP(B9,'[1]Plano GD - SCB 1'!$A:$F,6,0),0) -> 2 | S9: =IFERROR(VLOOKUP(B9,'[1]Plano GD - SCB 2'!$A:$F,6,0),0) -> 0 | T9: Y
B10: INSTRUMENT_IMPRMNT_STTS | C10: INSTRUMENT | D10: IMPRMNT_STTS | E10: Baixa | F10: =VLOOKUP(B10,'[1]Plano GD - SC1'!$A:$F,6,0) -> 2 | G10: M. Baixa | H10: 0 | I10: 1 | J10: 1 | K10: n.a. | L10: 0 | M10: 0.5 | N10: 1 | O10: 2.5 | P10: SCA SCB1 | Q10: =VLOOKUP(B10,'[1]Plano GD - SC1'!$A:$F,6,0) -> 2 | R10: =IFERROR(VLOOKUP(B10,'[1]Plano GD - SCB 1'!$A:$F,6,0),0) -> 2 | S10: =IFERROR(VLOOKUP(B10,'[1]Plano GD - SCB 2'!$A:$F,6,0),0) -> 0 | T10: Y
B11: INSTRUMENT_PRFRMNG_STTS | C11: INSTRUMENT | D11: PRFRMNG_STTS | E11: Baixa | F11: =VLOOKUP(B11,'[1]Plano GD - SC1'!$A:$F,6,0) -> 2 | G11: M. Baixa | H11: 0 | I11: 1 | J11: 1 | K11: n.a. | L11: 0 | M11: 0.5 | N11: 1 | O11: 2.5 | P11: SCA SCB1 | Q11: =VLOOKUP(B11,'[1]Plano GD - SC1'!$A:$F,6,0) -> 2 | R11: =IFERROR(VLOOKUP(B11,'[1]Plano GD - SCB 1'!$A:$F,6,0),0) -> 2 | S11: =IFERROR(VLOOKUP(B11,'[1]Plano GD - SCB 2'!$A:$F,6,0),0) -> 0 | T11: Y
B12: INSTRUMENT_TYP_INSTRMNT | C12: INSTRUMENT | D12: TYP_INSTRMNT | E12: Baixa | F12: =VLOOKUP(B12,'[1]Plano GD - SC1'!$A:$F,6,0) -> 2 | G12: M. Baixa | H12: 0 | I12: 1 | J12: 1 | K12: n.a. | L12: 0 | M12: 0.5 | N12: 1 | O12: 2.5 | P12: SCA SCB1 | Q12: =VLOOKUP(B12,'[1]Plano GD - SC1'!$A:$F,6,0) -> 2 | R12: =IFERROR(VLOOKUP(B12,'[1]Plano GD - SCB 1'!$A:$F,6,0),0) -> 2 | S12: =IFERROR(VLOOKUP(B12,'[1]Plano GD - SCB 2'!$A:$F,6,0),0) -> 0 | T12: Y
B13: INSTRUMENT_GRSS_CRRYNG_AMNT_INSTRMNT | C13: INSTRUMENT | D13: GRSS_CRRYNG_AMNT_INSTRMNT | E13: Baixa | F13: =VLOOKUP(B13,'[1]Plano GD - SC1'!$A:$F,6,0) -> 2 | G13: M. Baixa | H13: 0 | I13: 1 | J13: 1 | K13: n.a. | L13: 0 | M13: 0.5 | N13: 1 | O13: 2.5 | P13: SCA SCB1 | Q13: =VLOOKUP(B13,'[1]Plano GD - SC1'!$A:$F,6,0) -> 2 | R13: =IFERROR(VLOOKUP(B13,'[1]Plano GD - SCB 1'!$A:$F,6,0),0) -> 2 | S13: =IFERROR(VLOOKUP(B13,'[1]Plano GD - SCB 2'!$A:$F,6,0),0) -> 0 | T13: Y
B14: INSTRUMENT_ACCMLTD_CHNGS_FV_CR_INSTRMNT | C14: INSTRUMENT | D14: ACCMLTD_CHNGS_FV_CR_INSTRMNT | E14: Baixa | F14: =VLOOKUP(B14,'[1]Plano GD - SC1'!$A:$F,6,0) -> 2 | G14: M. Baixa | H14: 0 | I14: 1 | J14: 1 | K14: n.a. | L14: 0 | M14: 0.5 | N14: 1 | O14: 2.5 | P14: SCA SCB1 | Q14: =VLOOKUP(B14,'[1]Plano GD - SC1'!$A:$F,6,0) -> 2 | R14: =IFERROR(VLOOKUP(B14,'[1]Plano GD - SCB 1'!$A:$F,6,0),0) -> 2 | S14: =IFERROR(VLOOKUP(B14,'[1]Plano GD - SCB 2'!$A:$F,6,0),0) -> 0 | T14: Y
B15: INSTRUMENT_ACCNTNG_CLSSFCTN | C15: INSTRUMENT | D15: ACCNTNG_CLSSFCTN | E15: Baixa | F15: =VLOOKUP(B15,'[1]Plano GD - SC1'!$A:$F,6,0) -> 2 | G15: M. Baixa | H15: 0 | I15: 1 | J15: 1 | K15: n.a. | L15: 0 | M15: 0.5 | N15: 1 | O15: 2.5 | P15: SCA SCB1 | Q15: =VLOOKUP(B15,'[1]Plano GD - SC1'!$A:$F,6,0) -> 2 | R15: =IFERROR(VLOOKUP(B15,'[1]Plano GD - SCB 1'!$A:$F,6,0),0) -> 2 | S15: =IFERROR(VLOOKUP(B15,'[1]Plano GD - SCB 2'!$A:$F,6,0),0) -> 0 | T15: Y
B16: INSTRUMENT_CCF | C16: INSTRUMENT | D16: CCF | E16: Baixa | F16: =VLOOKUP(B16,'[1]Plano GD - SC1'!$A:$F,6,0) -> 2 | G16: M. Baixa | H16: 1 | I16: 1 | J16: 1 | K16: n.a. | L16: 0 | M16: 0.5 | N16: 1 | O16: 2.5 | P16: SCA SCB1 | Q16: =VLOOKUP(B16,'[1]Plano GD - SC1'!$A:$F,6,0) -> 2 | R16: =IFERROR(VLOOKUP(B16,'[1]Plano GD - SCB 1'!$A:$F,6,0),0) -> 2 | S16: =IFERROR(VLOOKUP(B16,'[1]Plano GD - SCB 2'!$A:$F,6,0),0) -> 0 | T16: N
... B72: INSTR_ACTIVITY_SSTNBL_INDCTR | C72: INSTR_ACTIVITY | D72: SSTNBL_INDCTR | E72: Alta | F72: =VLOOKUP(B72,'[1]Plano GD - SC1'!$A:$F,6,0) -> 18.1 | G72: Alta | H72: 0 | I72: 8 | J72: 1.5 | K72: Baixa | L72: 0.5 | M72: 0.5 | N72: 1 | O72: 10 | P72: SCA SCB 2 | Q72: =VLOOKUP(B72,'[1]Plano GD - SC1'!$A:$F,6,0) -> 18.1 | R72: =IFERROR(VLOOKUP(B72,'[1]Plano GD - SCB 1'!$A:$F,6,0),0) -> 0 | S72: =IFERROR(VLOOKUP(B72,'[1]Plano GD - SCB 2'!$A:$F,6,0),0) -> 18.1 | T72: N

Sheet Auxiliar
B2: Tipologia de testes
D3: Estimação Horas
B4: Categorização de Testes | C4: Descrição | D4: n.a. | E4: M. Baixa | F4: Baixa | G4: Média | H4: Alta | I4: M. Alta
B5: Especificação | C5: Levantamento de informação e especificação de requisitos | D5: 0 | E5: 1 | F5: 2 | G5: 4 | H5: 8 | I5: 10
B6: Simulação | C6: Simulação da especificação funcional. Suplementarmente, realizar reuniões de validações e esclarecimentos funcionais junto do negócio/owner. | D6: 0 | E6: 1 | F6: 1.5 | G6: 3 | H6: 6 | I6: 8
B7: 2. Testes comparativos | C7: A partir da simulação realizada, comparar resultados com a implementação de IT. | D7: 0 | E7: 1 | F7: 1.5 | G7: 3 | H7: 6 | I7: 3
B8: 3. Val. Code List | C8: A partir da simulação realizada, comparar com as parametrizações implementadas por IT (code list). | D8: 0 | E8: 0.5 | F8: 0.5 | G8: 0.5 | H8: 0.5 | I8: =H8*2 -> 1
B9: 4. Val. Formatos | C9: Validação de formato de acordo com o que é esperado pela Corporação (incluindo validação de codelists, missing e default values) Validar especificação e controlos da especificação vs o que está implementado | D9: 0 | E9: 0.5 | F9: 0.5 | G9: 0.5 | H9: 0.5 | I9: =H9*2 -> 1
B10: 5. Val.Controlos Corp. | C10: Validar controlos corporativos e se a especificação cumpre os requisitos. | D10: 0 | E10: 1 | F10: 1 | G10: 1 | H10: 1 | I10: =H10*2 -> 2
B11: 6. Testes Regressivos | C11: Testar que, com reprocessamentos, nenhum outro campo foi alterado (aplicável a toda a LT) | D11: 0 | E11: 0.1 | F11: 0.1 | G11: 0.1 | H11: 0.1 | I11: 0.1
B12: 7. Re-testes | D12: 0 | E12: 0.2 | F12: 0.2 | G12: 0.2 | H12: 0.2 | I12: 0.2
B15: Pressupostos
B18: Implementações de IT
B19: O esforço estimado de implementação de IT corresponde a metade do tempo estimado para especificação dos campos
B20: As implementações devem começar 2 semanas após o envio das definições de requisitos
B23: Testes
B24: Serão realizados testes regressivos de 3 em 3 semanas (com base em reprocessamentos sobre as várias entregas)
B25: Assume-se que 20% dos campos entregues terão incidências/re-especificações de pequenos ajustos e devem ser re-implementados
B26: Não serão realizados re-testes para as streams 4, 5 e 6 uma vez que as mesmas já pressupõe testes anteriores.

Sheet Lista - Âmbito Projeto GD
Y1: &
B2: DEZEMBRO | F2: ESTR | G2: GD | H2: PILAR3 | I2: GFINANCE | J2: ESG_RISKS | K2: LF | L2: Comparação com lista ATUAL | V2: Comparação com lista ATUAL | AC2: Estimativas
A3: ID Data field / Field order | B3: CONCAT | C3: Table | D3: Data field | E3: Field name | F3: Structural ECB Loan Tape | G3: Green Dashboard | H3: Pillar III ESG | I3: Green Finance | J3: ESG Risks | K3: Leveraged Finance | L3: ATUAL_Structural ECB Loan Tape | M3: val_ESTR | N3: ATUAL_Green Dashboard | O3: val_GD | P3: ATUAL_Pillar III ESG | Q3: val_PILAR3 | R3: ATUAL_Green Finance | S3: ATUAL_ESG Risks | T3: val_ESG_RISKS | U3: ATUAL_Leveraged Finance | V3: Fonte manual LF | W3: Status Data Lake | X3: Status Data Lake (Detalhe) | Y3: AMBITO | Z3: STATUS | AA3: Est anterior | AB3: format | AC3: Complexidade (todos) | AD3: Especificação | AE3: Simulação | AF3: 2. Testes comparativos | AG3: Complexidade (code list) | AH3: 3. Val. Code List | AI3: 4. Val. Formatos | AJ3: 5. Val.Controlos Corp. | AK3: Total Testes | AL3: Observações
A4: IN.001 | B4: =C4&"_"&D4 -> INSTRUMENT_COD_SOC | C4: INSTRUMENT | D4: COD_SOC | E4: Entity code of the informing society. | F4: Y | G4: Y | H4: Y | I4: N | J4: Y | K4: Y | L4: =IFERROR(VLOOKUP($B4,'LISTA - Atual'!$B$1:$I$444,5,0),"Novo") -> Y | M4: =IF(L4="Novo","Novo Campo",IF(L4=F4,"Igual","Diferente")) -> Igual | N4: =IFERROR(VLOOKUP($B4,'LISTA - Atual'!$B$1:$I$444,6,0),"Novo") -> Y | O4: =IF(N4="Novo","Novo Campo",IF(N4=G4,"Igual","Diferente")) -> Igual | P4: =IFERROR(VLOOKUP($B4,'LISTA - Atual'!$B$1:$I$444,7,0),"Novo") -> Y | Q4: =IF(P4="Novo","Novo Campo",IF(P4=H4,"Igual","Diferente")) -> Igual | R4: n/a | S4: =IFERROR(VLOOKUP($B4,'LISTA - Atual'!$B$1:$I$444,8,0),"Novo") -> Y | T4: =IF(S4="Novo","Novo Campo",IF(S4=J4,"Igual","Diferente")) -> Igual | U4: n/a | V4: N | W4: =IFERROR(VLOOKUP(B4,#REF!,11,0),"n/a") -> n/a | X4: =IFERROR(VLOOKUP(B4,#REF!,8,0),"n/a") -> n/a | Y4: =$F$2&$Y$1&$G$2&$Y$1&$H$2 -> ESTR & GD & PILAR3 | Z4: Sem alteração | AA4: =VLOOKUP(Table1[[#This Row],[CONCAT]],'[1]1. Tipologias Testes GD'!$F:$L,7,0) -> Baixa | AB4: VARCHAR2(5) | AC4: M. Baixa | AD4: 0 | AE4: =INDEX(Auxiliar!$D$5:$I$10,MATCH('Lista - Âmbito Projeto GD'!AE$3,Auxiliar!$B$5:$B$10,0),MATCH('Lista - Âmbito Projeto GD'!$AC4,Auxiliar!$D$4:$I$4,0)) -> 1 | AF4: =INDEX(Auxiliar!$D$5:$I$10,MATCH('Lista - Âmbito Projeto GD'!AF$3,Auxiliar!$B$5:$B$10,0),MATCH('Lista - Âmbito Projeto GD'!$AC4,Auxiliar!$D$4:$I$4,0)) -> 1 | AG4: =IF(OR(AB4="Code List",AB4="Y, N"),AC4,"n.a.") -> n.a. | AH4: =INDEX(Auxiliar!$D$5:$I$10,MATCH('Lista - Âmbito Projeto GD'!AH$3,Auxiliar!$B$5:$B$10,0),MATCH('Lista - Âmbito Projeto GD'!$AG4,Auxiliar!$D$4:$I$4,0)) -> 0 | AI4: =INDEX(Auxiliar!$D$5:$I$10,MATCH('Lista - Âmbito Projeto GD'!AI$3,Auxiliar!$B$5:$B$10,0),MATCH('Lista - Âmbito Projeto GD'!$AC4,Auxiliar!$D$4:$I$4,0)) -> 0.5 | AJ4: =INDEX(Auxiliar!$D$5:$I$10,MATCH('Lista - Âmbito Projeto GD'!AJ$3,Auxiliar!$B$5:$B$10,0),MATCH('Lista - Âmbito Projeto GD'!$AC4,Auxiliar!$D$4:$I$4,0)) -> 1 | AK4: =SUM(AF4,AH4:AJ4) -> 2.5
A5: IN.002 | B5: =C5&"_"&D5 -> INSTRUMENT_SUBPORTFOLIO_ID | C5: INSTRUMENT | D5: SUBPORTFOLIO_ID | E5: Subportfolio ID | F5: Y | G5: Y | H5: Y | I5: N | J5: Y | K5: Y | L5: =IFERROR(VLOOKUP($B5,'LISTA - Atual'!$B$1:$I$444,5,0),"Novo") -> Y | M5: =IF(L5="Novo","Novo Campo",IF(L5=F5,"Igual","Diferente")) -> Igual | N5: =IFERROR(VLOOKUP($B5,'LISTA - Atual'!$B$1:$I$444,6,0),"Novo") -> Y | O5: =IF(N5="Novo","Novo Campo",IF(N5=G5,"Igual","Diferente")) -> Igual | P5: =IFERROR(VLOOKUP($B5,'LISTA - Atual'!$B$1:$I$444,7,0),"Novo") -> Y | Q5: =IF(P5="Novo","Novo Campo",IF(P5=H5,"Igual","Diferente")) -> Igual | R5: n/a | S5: =IFERROR(VLOOKUP($B5,'LISTA - Atual'!$B$1:$I$444,8,0),"Novo") -> Y | T5: =IF(S5="Novo","Novo Campo",IF(S5=J5,"Igual","Diferente")) -> Igual | U5: n/a | V5: N | W5: =IFERROR(VLOOKUP(B5,#REF!,11,0),"n/a") -> n/a | X5: =IFERROR(VLOOKUP(B5,#REF!,8,0),"n/a") -> n/a | Y5: =$F$2&$Y$1&$G$2&$Y$1&$H$2 -> ESTR & GD & PILAR3 | Z5: Sem alteração | AA5: =VLOOKUP(Table1[[#This Row],[CONCAT]],'[1]1. Tipologias Testes GD'!$F:$L,7,0) -> Baixa | AB5: Code List | AC5: M. Baixa | AD5: 0 | AE5: =INDEX(Auxiliar!$D$5:$I$10,MATCH('Lista - Âmbito Projeto GD'!AE$3,Auxiliar!$B$5:$B$10,0),MATCH('Lista - Âmbito Projeto GD'!$AC5,Auxiliar!$D$4:$I$4,0)) -> 1 | AF5: =INDEX(Auxiliar!$D$5:$I$10,MATCH('Lista - Âmbito Projeto GD'!AF$3,Auxiliar!$B$5:$B$10,0),MATCH('Lista - Âmbito Projeto GD'!$AC5,Auxiliar!$D$4:$I$4,0)) -> 1 | AG5: n.a. | AH5: =INDEX(Auxiliar!$D$5:$I$10,MATCH('Lista - Âmbito Projeto GD'!AH$3,Auxiliar!$B$5:$B$10,0),MATCH('Lista - Âmbito Projeto GD'!$AG5,Auxiliar!$D$4:$I$4,0)) -> 0 | AI5: =INDEX(Auxiliar!$D$5:$I$10,MATCH('Lista - Âmbito Projeto GD'!AI$3,Auxiliar!$B$5:$B$10,0),MATCH('Lista - Âmbito Projeto GD'!$AC5,Auxiliar!$D$4:$I$4,0)) -> 0.5 | AJ5: =INDEX(Auxiliar!$D$5:$I$10,MATCH('Lista - Âmbito Projeto GD'!AJ$3,Auxiliar!$B$5:$B$10,0),MATCH('Lista - Âmbito Projeto GD'!$AC5,Auxiliar!$D$4:$I$4,0)) -> 1 | AK5: =SUM(AF5,AH5:AJ5) -> 2.5
A6: IN.007 | B6: =C6&"_"&D6 -> INSTRUMENT_DT_RFRNC | C6: INSTRUMENT | D6: DT_RFRNC | E6: Reference date | F6: Y | G6: Y | H6: Y | I6: N | J6: Y | K6: Y | L6: =IFERROR(VLOOKUP($B6,'LISTA - Atual'!$B$1:$I$444,5,0),"Novo") -> Y | M6: =IF(L6="Novo","Novo Campo",IF(L6=F6,"Igual","Diferente")) -> Igual | N6: =IFERROR(VLOOKUP($B6,'LISTA - Atual'!$B$1:$I$444,6,0),"Novo") -> Y | O6: =IF(N6="Novo","Novo Campo",IF(N6=G6,"Igual","Diferente")) -> Igual | P6: =IFERROR(VLOOKUP($B6,'LISTA - Atual'!$B$1:$I$444,7,0),"Novo") -> Y | Q6: =IF(P6="Novo","Novo Campo",IF(P6=H6,"Igual","Diferente")) -> Igual | R6: n/a | S6: =IFERROR(VLOOKUP($B6,'LISTA - Atual'!$B$1:$I$444,8,0),"Novo") -> Y | T6: =IF(S6="Novo","Novo Campo",IF(S6=J6,"Igual","Diferente")) -> Igual | U6: n/a | V6: N | W6: =IFERROR(VLOOKUP(B6,#REF!,11,0),"n/a") -> n/a | X6: =IFERROR(VLOOKUP(B6,#REF!,8,0),"n/a") -> n/a | Y6: =$F$2&$Y$1&$G$2&$Y$1&$H$2 -> ESTR & GD & PILAR3 | Z6: Sem alteração | AA6: =VLOOKUP(Table1[[#This Row],[CONCAT]],'[1]1. Tipologias Testes GD'!$F:$L,7,0) -> Baixa | AB6: DATE | AC6: M. Baixa | AD6: 0 | AE6: =INDEX(Auxiliar!$D$5:$I$10,MATCH('Lista - Âmbito Projeto GD'!AE$3,Auxiliar!$B$5:$B$10,0),MATCH('Lista - Âmbito Projeto GD'!$AC6,Auxiliar!$D$4:$I$4,0)) -> 1 | AF6: =INDEX(Auxiliar!$D$5:$I$10,MATCH('Lista - Âmbito Projeto GD'!AF$3,Auxiliar!$B$5:$B$10,0),MATCH('Lista - Âmbito Projeto GD'!$AC6,Auxiliar!$D$4:$I$4,0)) -> 1 | AG6: =IF(OR(AB6="Code List",AB6="Y, N"),AC6,"n.a.") -> n.a. | AH6: =INDEX(Auxiliar!$D$5:$I$10,MATCH('Lista - Âmbito Projeto GD'!AH$3,Auxiliar!$B$5:$B$10,0),MATCH('Lista - Âmbito Projeto GD'!$AG6,Auxiliar!$D$4:$I$4,0)) -> 0 | AI6: =INDEX(Auxiliar!$D$5:$I$10,MATCH('Lista - Âmbito Projeto GD'!AI$3,Auxiliar!$B$5:$B$10,0),MATCH('Lista - Âmbito Projeto GD'!$AC6,Auxiliar!$D$4:$I$4,0)) -> 0.5 | AJ6: =INDEX(Auxiliar!$D$5:$I$10,MATCH('Lista - Âmbito Projeto GD'!AJ$3,Auxiliar!$B$5:$B$10,0),MATCH('Lista - Âmbito Projeto GD'!$AC6,Auxiliar!$D$4:$I$4,0)) -> 1 | AK6: =SUM(AF6,AH6:AJ6) -> 2.5
A7: IN.008 | B7: =C7&"_"&D7 -> INSTRUMENT_INSTRMNT_ID | C7: INSTRUMENT | D7: INSTRMNT_ID | E7: Instrument ID | F7: Y | G7: Y | H7: Y | I7: N | J7: Y | K7: Y | L7: =IFERROR(VLOOKUP($B7,'LISTA - Atual'!$B$1:$I$444,5,0),"Novo") -> Y | M7: =IF(L7="Novo","Novo Campo",IF(L7=F7,"Igual","Diferente")) -> Igual | N7: =IFERROR(VLOOKUP($B7,'LISTA - Atual'!$B$1:$I$444,6,0),"Novo") -> Y | O7: =IF(N7="Novo","Novo Campo",IF(N7=G7,"Igual","Diferente")) -> Igual | P7: =IFERROR(VLOOKUP($B7,'LISTA - Atual'!$B$1:$I$444,7,0),"Novo") -> Y | Q7: =IF(P7="Novo","Novo Campo",IF(P7=H7,"Igual","Diferente")) -> Igual | R7: n/a | S7: =IFERROR(VLOOKUP($B7,'LISTA - Atual'!$B$1:$I$444,8,0),"Novo") -> Y | T7: =IF(S7="Novo","Novo Campo",IF(S7=J7,"Igual","Diferente")) -> Igual | U7: n/a | V7: N | W7: =IFERROR(VLOOKUP(B7,#REF!,11,0),"n/a") -> n/a | X7: =IFERROR(VLOOKUP(B7,#REF!,8,0),"n/a") -> n/a | Y7: =$F$2&$Y$1&$G$2&$Y$1&$H$2 -> ESTR & GD & PILAR3 | Z7: Sem alteração | AA7: =VLOOKUP(Table1[[#This Row],[CONCAT]],'[1]1. Tipologias Testes GD'!$F:$L,7,0) -> Alta | AB7: VARCHAR2(60) | AC7: M. Alta | AD7: 0 | AE7: =INDEX(Auxiliar!$D$5:$I$10,MATCH('Lista - Âmbito Projeto GD'!AE$3,Auxiliar!$B$5:$B$10,0),MATCH('Lista - Âmbito Projeto GD'!$AC7,Auxiliar!$D$4:$I$4,0)) -> 8 | AF7: =INDEX(Auxiliar!$D$5:$I$10,MATCH('Lista - Âmbito Projeto GD'!AF$3,Auxiliar!$B$5:$B$10,0),MATCH('Lista - Âmbito Projeto GD'!$AC7,Auxiliar!$D$4:$I$4,0)) -> 3 | AG7: =IF(OR(AB7="Code List",AB7="Y, N"),AC7,"n.a.") -> n.a. | AH7: =INDEX(Auxiliar!$D$5:$I$10,MATCH('Lista - Âmbito Projeto GD'!AH$3,Auxiliar!$B$5:$B$10,0),MATCH('Lista - Âmbito Projeto GD'!$AG7,Auxiliar!$D$4:$I$4,0)) -> 0 | AI7: =INDEX(Auxiliar!$D$5:$I$10,MATCH('Lista - Âmbito Projeto GD'!AI$3,Auxiliar!$B$5:$B$10,0),MATCH('Lista - Âmbito Projeto GD'!$AC7,Auxiliar!$D$4:$I$4,0)) -> 1 | AJ7: =INDEX(Auxiliar!$D$5:$I$10,MATCH('Lista - Âmbito Projeto GD'!AJ$3,Auxiliar!$B$5:$B$10,0),MATCH('Lista - Âmbito Projeto GD'!$AC7,Auxiliar!$D$4:$I$4,0)) -> 2 | AK7: =SUM(AF7,AH7:AJ7) -> 6
A8: IN.020 | B8: =C8&"_"&D8 -> INSTRUMENT_DFLT_STTS_INSTRMNT | C8: INSTRUMENT | D8: DFLT_STTS_INSTRMNT | E8: Default status of the instrument | F8: Y | G8: Y | H8: Y | I8: N | J8: N | K8: Y | L8: =IFERROR(VLOOKUP($B8,'LISTA - Atual'!$B$1:$I$444,5,0),"Novo") -> Y | M8: =IF(L8="Novo","Novo Campo",IF(L8=F8,"Igual","Diferente")) -> Igual | N8: =IFERROR(VLOOKUP($B8,'LISTA - Atual'!$B$1:$I$444,6,0),"Novo") -> Y | O8: =IF(N8="Novo","Novo Campo",IF(N8=G8,"Igual","Diferente")) -> Igual | P8: =IFERROR(VLOOKUP($B8,'LISTA - Atual'!$B$1:$I$444,7,0),"Novo") -> Y | Q8: =IF(P8="Novo","Novo Campo",IF(P8=H8,"Igual","Diferente")) -> Igual | R8: n/a | S8: =IFERROR(VLOOKUP($B8,'LISTA - Atual'!$B$1:$I$444,8,0),"Novo") -> N | T8: =IF(S8="Novo","Novo Campo",IF(S8=J8,"Igual","Diferente")) -> Igual | U8: n/a | V8: N | W8: =IFERROR(VLOOKUP(B8,#REF!,11,0),"n/a") -> n/a | X8: =IFERROR(VLOOKUP(B8,#REF!,8,0),"n/a") -> n/a | Y8: =$F$2&$Y$1&$G$2&$Y$1&$H$2 -> ESTR & GD & PILAR3 | Z8: Sem alteração | AA8: =VLOOKUP(Table1[[#This Row],[CONCAT]],'[1]1. Tipologias Testes GD'!$F:$L,7,0) -> Baixa | AB8: Code List | AC8: M. Baixa | AD8: 0 | AE8: =INDEX(Auxiliar!$D$5:$I$10,MATCH('Lista - Âmbito Projeto GD'!AE$3,Auxiliar!$B$5:$B$10,0),MATCH('Lista - Âmbito Projeto GD'!$AC8,Auxiliar!$D$4:$I$4,0)) -> 1 | AF8: =INDEX(Auxiliar!$D$5:$I$10,MATCH('Lista - Âmbito Projeto GD'!AF$3,Auxiliar!$B$5:$B$10,0),MATCH('Lista - Âmbito Projeto GD'!$AC8,Auxiliar!$D$4:$I$4,0)) -> 1 | AG8: n.a. | AH8: =INDEX(Auxiliar!$D$5:$I$10,MATCH('Lista - Âmbito Projeto GD'!AH$3,Auxiliar!$B$5:$B$10,0),MATCH('Lista - Âmbito Projeto GD'!$AG8,Auxiliar!$D$4:$I$4,0)) -> 0 | AI8: =INDEX(Auxiliar!$D$5:$I$10,MATCH('Lista - Âmbito Projeto GD'!AI$3,Auxiliar!$B$5:$B$10,0),MATCH('Lista - Âmbito Projeto GD'!$AC8,Auxiliar!$D$4:$I$4,0)) -> 0.5 | AJ8: =INDEX(Auxiliar!$D$5:$I$10,MATCH('Lista - Âmbito Projeto GD'!AJ$3,Auxiliar!$B$5:$B$10,0),MATCH('Lista - Âmbito Projeto GD'!$AC8,Auxiliar!$D$4:$I$4,0)) -> 1 | AK8: =SUM(AF8,AH8:AJ8) -> 2.5 | AL8: default
A9: IN.034 | B9: =C9&"_"&D9 -> INSTRUMENT_IMPRMNT_STTS | C9: INSTRUMENT | D9: IMPRMNT_STTS | E9: Impairment status | F9: Y | G9: Y | H9: Y | I9: N | J9: N | K9: Y | L9: =IFERROR(VLOOKUP($B9,'LISTA - Atual'!$B$1:$I$444,5,0),"Novo") -> Y | M9: =IF(L9="Novo","Novo Campo",IF(L9=F9,"Igual","Diferente")) -> Igual | N9: =IFERROR(VLOOKUP($B9,'LISTA - Atual'!$B$1:$I$444,6,0),"Novo") -> Y | O9: =IF(N9="Novo","Novo Campo",IF(N9=G9,"Igual","Diferente")) -> Igual | P9: =IFERROR(VLOOKUP($B9,'LISTA - Atual'!$B$1:$I$444,7,0),"Novo") -> Y | Q9: =IF(P9="Novo","Novo Campo",IF(P9=H9,"Igual","Diferente")) -> Igual | R9: n/a | S9: =IFERROR(VLOOKUP($B9,'LISTA - Atual'!$B$1:$I$444,8,0),"Novo") -> N | T9: =IF(S9="Novo","Novo Campo",IF(S9=J9,"Igual","Diferente")) -> Igual | U9: n/a | V9: N | W9: =IFERROR(VLOOKUP(B9,#REF!,11,0),"n/a") -> n/a | X9: =IFERROR(VLOOKUP(B9,#REF!,8,0),"n/a") -> n/a | Y9: =$F$2&$Y$1&$G$2&$Y$1&$H$2 -> ESTR & GD & PILAR3 | Z9: Sem alteração | AA9: =VLOOKUP(Table1[[#This Row],[CONCAT]],'[1]1. Tipologias Testes GD'!$F:$L,7,0) -> Baixa | AB9: Code List | AC9: M. Baixa | AD9: 0 | AE9: =INDEX(Auxiliar!$D$5:$I$10,MATCH('Lista - Âmbito Projeto GD'!AE$3,Auxiliar!$B$5:$B$10,0),MATCH('Lista - Âmbito Projeto GD'!$AC9,Auxiliar!$D$4:$I$4,0)) -> 1 | AF9: =INDEX(Auxiliar!$D$5:$I$10,MATCH('Lista - Âmbito Projeto GD'!AF$3,Auxiliar!$B$5:$B$10,0),MATCH('Lista - Âmbito Projeto GD'!$AC9,Auxiliar!$D$4:$I$4,0)) -> 1 | AG9: n.a. | AH9: =INDEX(Auxiliar!$D$5:$I$10,MATCH('Lista - Âmbito Projeto GD'!AH$3,Auxiliar!$B$5:$B$10,0),MATCH('Lista - Âmbito Projeto GD'!$AG9,Auxiliar!$D$4:$I$4,0)) -> 0 | AI9: =INDEX(Auxiliar!$D$5:$I$10,MATCH('Lista - Âmbito Projeto GD'!AI$3,Auxiliar!$B$5:$B$10,0),MATCH('Lista - Âmbito Projeto GD'!$AC9,Auxiliar!$D$4:$I$4,0)) -> 0.5 | AJ9: =INDEX(Auxiliar!$D$5:$I$10,MATCH('Lista - Âmbito Projeto GD'!AJ$3,Auxiliar!$B$5:$B$10,0),MATCH('Lista - Âmbito Projeto GD'!$AC9,Auxiliar!$D$4:$I$4,0)) -> 1 | AK9: =SUM(AF9,AH9:AJ9) -> 2.5 | AL9: mudança de fonte ifrs
A10: IN.044 | B10: =C10&"_"&D10 -> INSTRUMENT_PRFRMNG_STTS | C10: INSTRUMENT | D10: PRFRMNG_STTS | E10: Performing status | F10: Y | G10: Y | H10: Y | I10: N | J10: N | K10: Y | L10: =IFERROR(VLOOKUP($B10,'LISTA - Atual'!$B$1:$I$444,5,0),"Novo") -> Y | M10: =IF(L10="Novo","Novo Campo",IF(L10=F10,"Igual","Diferente")) -> Igual | N10: =IFERROR(VLOOKUP($B10,'LISTA - Atual'!$B$1:$I$444,6,0),"Novo") -> Y | O10: =IF(N10="Novo","Novo Campo",IF(N10=G10,"Igual","Diferente")) -> Igual | P10: =IFERROR(VLOOKUP($B10,'LISTA - Atual'!$B$1:$I$444,7,0),"Novo") -> Y | Q10: =IF(P10="Novo","Novo Campo",IF(P10=H10,"Igual","Diferente")) -> Igual | R10: n/a | S10: =IFERROR(VLOOKUP($B10,'LISTA - Atual'!$B$1:$I$444,8,0),"Novo") -> N | T10: =IF(S10="Novo","Novo Campo",IF(S10=J10,"Igual","Diferente")) -> Igual | U10: n/a | V10: N | W10: =IFERROR(VLOOKUP(B10,#REF!,11,0),"n/a") -> n/a | X10: =IFERROR(VLOOKUP(B10,#REF!,8,0),"n/a") -> n/a | Y10: =$F$2&$Y$1&$G$2&$Y$1&$H$2 -> ESTR & GD & PILAR3 | Z10: Sem alteração | AA10: =VLOOKUP(Table1[[#This Row],[CONCAT]],'[1]1. Tipologias Testes GD'!$F:$L,7,0) -> Baixa | AB10: Code List | AC10: M. Baixa | AD10: 0 | AE10: =INDEX(Auxiliar!$D$5:$I$10,MATCH('Lista - Âmbito Projeto GD'!AE$3,Auxiliar!$B$5:$B$10,0),MATCH('Lista - Âmbito Projeto GD'!$AC10,Auxiliar!$D$4:$I$4,0)) -> 1 | AF10: =INDEX(Auxiliar!$D$5:$I$10,MATCH('Lista - Âmbito Projeto GD'!AF$3,Auxiliar!$B$5:$B$10,0),MATCH('Lista - Âmbito Projeto GD'!$AC10,Auxiliar!$D$4:$I$4,0)) -> 1 | AG10: n.a. | AH10: =INDEX(Auxiliar!$D$5:$I$10,MATCH('Lista - Âmbito Projeto GD'!AH$3,Auxiliar!$B$5:$B$10,0),MATCH('Lista - Âmbito Projeto GD'!$AG10,Auxiliar!$D$4:$I$4,0)) -> 0 | AI10: =INDEX(Auxiliar!$D$5:$I$10,MATCH('Lista - Âmbito Projeto GD'!AI$3,Auxiliar!$B$5:$B$10,0),MATCH('Lista - Âmbito Projeto GD'!$AC10,Auxiliar!$D$4:$I$4,0)) -> 0.5 | AJ10: =INDEX(Auxiliar!$D$5:$I$10,MATCH('Lista - Âmbito Projeto GD'!AJ$3,Auxiliar!$B$5:$B$10,0),MATCH('Lista - Âmbito Projeto GD'!$AC10,Auxiliar!$D$4:$I$4,0)) -> 1 | AK10: =SUM(AF10,AH10:AJ10) -> 2.5 | AL10: mudança de fonte ifrs
A11: IN.055 | B11: =C11&"_"&D11 -> INSTRUMENT_TYP_INSTRMNT | C11: INSTRUMENT | D11: TYP_INSTRMNT | E11: Type of instrument | F11: Y | G11: Y | H11: Y | I11: N | J11: N | K11: Y | L11: =IFERROR(VLOOKUP($B11,'LISTA - Atual'!$B$1:$I$444,5,0),"Novo") -> Y | M11: =IF(L11="Novo","Novo Campo",IF(L11=F11,"Igual","Diferente")) -> Igual | N11: =IFERROR(VLOOKUP($B11,'LISTA - Atual'!$B$1:$I$444,6,0),"Novo") -> Y | O11: =IF(N11="Novo","Novo Campo",IF(N11=G11,"Igual","Diferente")) -> Igual | P11: =IFERROR(VLOOKUP($B11,'LISTA - Atual'!$B$1:$I$444,7,0),"Novo") -> Y | Q11: =IF(P11="Novo","Novo Campo",IF(P11=H11,"Igual","Diferente")) -> Igual | R11: n/a | S11: =IFERROR(VLOOKUP($B11,'LISTA - Atual'!$B$1:$I$444,8,0),"Novo") -> N | T11: =IF(S11="Novo","Novo Campo",IF(S11=J11,"Igual","Diferente")) -> Igual | U11: n/a | V11: N | W11: =IFERROR(VLOOKUP(B11,#REF!,11,0),"n/a") -> n/a | X11: =IFERROR(VLOOKUP(B11,#REF!,8,0),"n/a") -> n/a | Y11: =$F$2&$Y$1&$G$2&$Y$1&$H$2 -> ESTR & GD & PILAR3 | Z11: Sem alteração | AA11: =VLOOKUP(Table1[[#This Row],[CONCAT]],'[1]1. Tipologias Testes GD'!$F:$L,7,0) -> Baixa | AB11: Code List | AC11: M. Baixa | AD11: 0 | AE11: =INDEX(Auxiliar!$D$5:$I$10,MATCH('Lista - Âmbito Projeto GD'!AE$3,Auxiliar!$B$5:$B$10,0),MATCH('Lista - Âmbito Projeto GD'!$AC11,Auxiliar!$D$4:$I$4,0)) -> 1 | AF11: =INDEX(Auxiliar!$D$5:$I$10,MATCH('Lista - Âmbito Projeto GD'!AF$3,Auxiliar!$B$5:$B$10,0),MATCH('Lista - Âmbito Projeto GD'!$AC11,Auxiliar!$D$4:$I$4,0)) -> 1 | AG11: n.a. | AH11: =INDEX(Auxiliar!$D$5:$I$10,MATCH('Lista - Âmbito Projeto GD'!AH$3,Auxiliar!$B$5:$B$10,0),MATCH('Lista - Âmbito Projeto GD'!$AG11,Auxiliar!$D$4:$I$4,0)) -> 0 | AI11: =INDEX(Auxiliar!$D$5:$I$10,MATCH('Lista - Âmbito Projeto GD'!AI$3,Auxiliar!$B$5:$B$10,0),MATCH('Lista - Âmbito Projeto GD'!$AC11,Auxiliar!$D$4:$I$4,0)) -> 0.5 | AJ11: =INDEX(Auxiliar!$D$5:$I$10,MATCH('Lista - Âmbito Projeto GD'!AJ$3,Auxiliar!$B$5:$B$10,0),MATCH('Lista - Âmbito Projeto GD'!$AC11,Auxiliar!$D$4:$I$4,0)) -> 1 | AK11: =SUM(AF11,AH11:AJ11) -> 2.5
A12: IN.060 | B12: =C12&"_"&D12 -> INSTRUMENT_GRSS_CRRYNG_AMNT_INSTRMNT | C12: INSTRUMENT | D12: GRSS_CRRYNG_AMNT_INSTRMNT | E12: Gross carrying amount | F12: Y | G12: Y | H12: Y | I12: N | J12: Y | K12: Y | L12: =IFERROR(VLOOKUP($B12,'LISTA - Atual'!$B$1:$I$444,5,0),"Novo") -> Y | M12: =IF(L12="Novo","Novo Campo",IF(L12=F12,"Igual","Diferente")) -> Igual | N12: =IFERROR(VLOOKUP($B12,'LISTA - Atual'!$B$1:$I$444,6,0),"Novo") -> Y | O12: =IF(N12="Novo","Novo Campo",IF(N12=G12,"Igual","Diferente")) -> Igual | P12: =IFERROR(VLOOKUP($B12,'LISTA - Atual'!$B$1:$I$444,7,0),"Novo") -> Y | Q12: =IF(P12="Novo","Novo Campo",IF(P12=H12,"Igual","Diferente")) -> Igual | R12: n/a | S12: =IFERROR(VLOOKUP($B12,'LISTA - Atual'!$B$1:$I$444,8,0),"Novo") -> Y | T12: =IF(S12="Novo","Novo Campo",IF(S12=J12,"Igual","Diferente")) -> Igual | U12: n/a | V12: N | W12: =IFERROR(VLOOKUP(B12,#REF!,11,0),"n/a") -> n/a | X12: =IFERROR(VLOOKUP(B12,#REF!,8,0),"n/a") -> n/a | Y12: =$F$2&$Y$1&$G$2&$Y$1&$H$2 -> ESTR & GD & PILAR3 | Z12: Sem alteração | AA12: =VLOOKUP(Table1[[#This Row],[CONCAT]],'[1]1. Tipologias Testes GD'!$F:$L,7,0) -> Baixa | AB12: FLOAT 2 decimal places | AC12: M. Baixa | AD12: 0 | AE12: =INDEX(Auxiliar!$D$5:$I$10,MATCH('Lista - Âmbito Projeto GD'!AE$3,Auxiliar!$B$5:$B$10,0),MATCH('Lista - Âmbito Projeto GD'!$AC12,Auxiliar!$D$4:$I$4,0)) -> 1 | AF12: =INDEX(Auxiliar!$D$5:$I$10,MATCH('Lista - Âmbito Projeto GD'!AF$3,Auxiliar!$B$5:$B$10,0),MATCH('Lista - Âmbito Projeto GD'!$AC12,Auxiliar!$D$4:$I$4,0)) -> 1 | AG12: =IF(OR(AB12="Code List",AB12="Y, N"),AC12,"n.a.") -> n.a. | AH12: =INDEX(Auxiliar!$D$5:$I$10,MATCH('Lista - Âmbito Projeto GD'!AH$3,Auxiliar!$B$5:$B$10,0),MATCH('Lista - Âmbito Projeto GD'!$AG12,Auxiliar!$D$4:$I$4,0)) -> 0 | AI12: =INDEX(Auxiliar!$D$5:$I$10,MATCH('Lista - Âmbito Projeto GD'!AI$3,Auxiliar!$B$5:$B$10,0),MATCH('Lista - Âmbito Projeto GD'!$AC12,Auxiliar!$D$4:$I$4,0)) -> 0.5 | AJ12: =INDEX(Auxiliar!$D$5:$I$10,MATCH('Lista - Âmbito Projeto GD'!AJ$3,Auxiliar!$B$5:$B$10,0),MATCH('Lista - Âmbito Projeto GD'!$AC12,Auxiliar!$D$4:$I$4,0)) -> 1 | AK12: =SUM(AF12,AH12:AJ12) -> 2.5
A13: IN.061 | B13: =C13&"_"&D13 -> INSTRUMENT_ACCMLTD_CHNGS_FV_CR_INSTRMNT | C13: INSTRUMENT | D13: ACCMLTD_CHNGS_FV_CR_INSTRMNT | E13: Accumulated changes in fair value due to credit risk | F13: Y | G13: Y | H13: Y | I13: N | J13: N | K13: N | L13: =IFERROR(VLOOKUP($B13,'LISTA - Atual'!$B$1:$I$444,5,0),"Novo") -> Y | M13: =IF(L13="Novo","Novo Campo",IF(L13=F13,"Igual","Diferente")) -> Igual | N13: =IFERROR(VLOOKUP($B13,'LISTA - Atual'!$B$1:$I$444,6,0),"Novo") -> Y | O13: =IF(N13="Novo","Novo Campo",IF(N13=G13,"Igual","Diferente")) -> Igual | P13: =IFERROR(VLOOKUP($B13,'LISTA - Atual'!$B$1:$I$444,7,0),"Novo") -> Y | Q13: =IF(P13="Novo","Novo Campo",IF(P13=H13,"Igual","Diferente")) -> Igual | R13: n/a | S13: =IFERROR(VLOOKUP($B13,'LISTA - Atual'!$B$1:$I$444,8,0),"Novo") -> N | T13: =IF(S13="Novo","Novo Campo",IF(S13=J13,"Igual","Diferente")) -> Igual | U13: n/a | V13: N | W13: =IFERROR(VLOOKUP(B13,#REF!,11,0),"n/a") -> n/a | X13: =IFERROR(VLOOKUP(B13,#REF!,8,0),"n/a") -> n/a | Y13: =$F$2&$Y$1&$G$2&$Y$1&$H$2 -> ESTR & GD & PILAR3 | Z13: Sem alteração | AA13: =VLOOKUP(Table1[[#This Row],[CONCAT]],'[1]1. Tipologias Testes GD'!$F:$L,7,0) -> Baixa | AB13: FLOAT 2 decimal places | AC13: M. Baixa | AD13: 0 | AE13: =INDEX(Auxiliar!$D$5:$I$10,MATCH('Lista - Âmbito Projeto GD'!AE$3,Auxiliar!$B$5:$B$10,0),MATCH('Lista - Âmbito Projeto GD'!$AC13,Auxiliar!$D$4:$I$4,0)) -> 1 | AF13: =INDEX(Auxiliar!$D$5:$I$10,MATCH('Lista - Âmbito Projeto GD'!AF$3,Auxiliar!$B$5:$B$10,0),MATCH('Lista - Âmbito Projeto GD'!$AC13,Auxiliar!$D$4:$I$4,0)) -> 1 | AG13: =IF(OR(AB13="Code List",AB13="Y, N"),AC13,"n.a.") -> n.a. | AH13: =INDEX(Auxiliar!$D$5:$I$10,MATCH('Lista - Âmbito Projeto GD'!AH$3,Auxiliar!$B$5:$B$10,0),MATCH('Lista - Âmbito Projeto GD'!$AG13,Auxiliar!$D$4:$I$4,0)) -> 0 | AI13: =INDEX(Auxiliar!$D$5:$I$10,MATCH('Lista - Âmbito Projeto GD'!AI$3,Auxiliar!$B$5:$B$10,0),MATCH('Lista - Âmbito Projeto GD'!$AC13,Auxiliar!$D$4:$I$4,0)) -> 0.5 | AJ13: =INDEX(Auxiliar!$D$5:$I$10,MATCH('Lista - Âmbito Projeto GD'!AJ$3,Auxiliar!$B$5:$B$10,0),MATCH('Lista - Âmbito Projeto GD'!$AC13,Auxiliar!$D$4:$I$4,0)) -> 1 | AK13: =SUM(AF13,AH13:AJ13) -> 2.5
A14: IN.062 | B14: =C14&"_"&D14 -> INSTRUMENT_ACCNTNG_CLSSFCTN | C14: INSTRUMENT | D14: ACCNTNG_CLSSFCTN | E14: Accounting portfolio | F14: Y | G14: Y | H14: Y | I14: N | J14: N | K14: Y | L14: =IFERROR(VLOOKUP($B14,'LISTA - Atual'!$B$1:$I$444,5,0),"Novo") -> Y | M14: =IF(L14="Novo","Novo Campo",IF(L14=F14,"Igual","Diferente")) -> Igual | N14: =IFERROR(VLOOKUP($B14,'LISTA - Atual'!$B$1:$I$444,6,0),"Novo") -> Y | O14: =IF(N14="Novo","Novo Campo",IF(N14=G14,"Igual","Diferente")) -> Igual | P14: =IFERROR(VLOOKUP($B14,'LISTA - Atual'!$B$1:$I$444,7,0),"Novo") -> Y | Q14: =IF(P14="Novo","Novo Campo",IF(P14=H14,"Igual","Diferente")) -> Igual | R14: n/a | S14: =IFERROR(VLOOKUP($B14,'LISTA - Atual'!$B$1:$I$444,8,0),"Novo") -> N | T14: =IF(S14="Novo","Novo Campo",IF(S14=J14,"Igual","Diferente")) -> Igual | U14: n/a | V14: N | W14: =IFERROR(VLOOKUP(B14,#REF!,11,0),"n/a") -> n/a | X14: =IFERROR(VLOOKUP(B14,#REF!,8,0),"n/a") -> n/a | Y14: =$F$2&$Y$1&$G$2&$Y$1&$H$2 -> ESTR & GD & PILAR3 | Z14: Sem alteração | AA14: =VLOOKUP(Table1[[#This Row],[CONCAT]],'[1]1. Tipologias Testes GD'!$F:$L,7,0) -> Baixa | AB14: Code List | AC14: M. Baixa | AD14: 0 | AE14: =INDEX(Auxiliar!$D$5:$I$10,MATCH('Lista - Âmbito Projeto GD'!AE$3,Auxiliar!$B$5:$B$10,0),MATCH('Lista - Âmbito Projeto GD'!$AC14,Auxiliar!$D$4:$I$4,0)) -> 1 | AF14: =INDEX(Auxiliar!$D$5:$I$10,MATCH('Lista - Âmbito Projeto GD'!AF$3,Auxiliar!$B$5:$B$10,0),MATCH('Lista - Âmbito Projeto GD'!$AC14,Auxiliar!$D$4:$I$4,0)) -> 1 | AG14: n.a. | AH14: =INDEX(Auxiliar!$D$5:$I$10,MATCH('Lista - Âmbito Projeto GD'!AH$3,Auxiliar!$B$5:$B$10,0),MATCH('Lista - Âmbito Projeto GD'!$AG14,Auxiliar!$D$4:$I$4,0)) -> 0 | AI14: =INDEX(Auxiliar!$D$5:$I$10,MATCH('Lista - Âmbito Projeto GD'!AI$3,Auxiliar!$B$5:$B$10,0),MATCH('Lista - Âmbito Projeto GD'!$AC14,Auxiliar!$D$4:$I$4,0)) -> 0.5 | AJ14: =INDEX(Auxiliar!$D$5:$I$10,MATCH('Lista - Âmbito Projeto GD'!AJ$3,Auxiliar!$B$5:$B$10,0),MATCH('Lista - Âmbito Projeto GD'!$AC14,Auxiliar!$D$4:$I$4,0)) -> 1 | AK14: =SUM(AF14,AH14:AJ14) -> 2.5
A15: IN.065 | B15: =C15&"_"&D15 -> INSTRUMENT_CCF | C15: INSTRUMENT | D15: CCF | E15: Credit conversion factor (CCF) according to CRR | F15: Y | G15: Y | H15: N | I15: N | J15: N | K15: Y | L15: =IFERROR(VLOOKUP($B15,'LISTA - Atual'!$B$1:$I$444,5,0),"Novo") -> Y | M15: =IF(L15="Novo","Novo Campo",IF(L15=F15,"Igual","Diferente")) -> Igual | N15: =IFERROR(VLOOKUP($B15,'LISTA - Atual'!$B$1:$I$444,6,0),"Novo") -> N | O15: =IF(N15="Novo","Novo Campo",IF(N15=G15,"Igual","Diferente")) -> Diferente | P15: =IFERROR(VLOOKUP($B15,'LISTA - Atual'!$B$1:$I$444,7,0),"Novo") -> N | Q15: =IF(P15="Novo","Novo Campo",IF(P15=H15,"Igual","Diferente")) -> Igual | R15: n/a | S15: =IFERROR(VLOOKUP($B15,'LISTA - Atual'!$B$1:$I$444,8,0),"Novo") -> N | T15: =IF(S15="Novo","Novo Campo",IF(S15=J15,"Igual","Diferente")) -> Igual | U15: n/a | V15: N | W15: =IFERROR(VLOOKUP(B15,#REF!,11,0),"n/a") -> n/a | X15: =IFERROR(VLOOKUP(B15,#REF!,8,0),"n/a") -> n/a | Y15: =$F$2&$Y$1&$G$2 -> ESTR & GD | Z15: Sem alteração | AA15: =VLOOKUP(Table1[[#This Row],[CONCAT]],'[1]1. Tipologias Testes GD'!$F:$L,7,0) -> Baixa | AB15: FLOAT 6 decimal places | AC15: M. Baixa | AD15: =INDEX(Auxiliar!$D$5:$I$10,MATCH('Lista - Âmbito Projeto GD'!AD$3,Auxiliar!$B$5:$B$10,0),MATCH('Lista - Âmbito Projeto GD'!$AC15,Auxiliar!$D$4:$I$4,0)) -> 1 | AE15: =INDEX(Auxiliar!$D$5:$I$10,MATCH('Lista - Âmbito Projeto GD'!AE$3,Auxiliar!$B$5:$B$10,0),MATCH('Lista - Âmbito Projeto GD'!$AC15,Auxiliar!$D$4:$I$4,0)) -> 1 | AF15: =INDEX(Auxiliar!$D$5:$I$10,MATCH('Lista - Âmbito Projeto GD'!AF$3,Auxiliar!$B$5:$B$10,0),MATCH('Lista - Âmbito Projeto GD'!$AC15,Auxiliar!$D$4:$I$4,0)) -> 1 | AG15: =IF(OR(AB15="Code List",AB15="Y, N"),AC15,"n.a.") -> n.a. | AH15: =INDEX(Auxiliar!$D$5:$I$10,MATCH('Lista - Âmbito Projeto GD'!AH$3,Auxiliar!$B$5:$B$10,0),MATCH('Lista - Âmbito Projeto GD'!$AG15,Auxiliar!$D$4:$I$4,0)) -> 0 | AI15: =INDEX(Auxiliar!$D$5:$I$10,MATCH('Lista - Âmbito Projeto GD'!AI$3,Auxiliar!$B$5:$B$10,0),MATCH('Lista - Âmbito Projeto GD'!$AC15,Auxiliar!$D$4:$I$4,0)) -> 0.5 | AJ15: =INDEX(Auxiliar!$D$5:$I$10,MATCH('Lista - Âmbito Projeto GD'!AJ$3,Auxiliar!$B$5:$B$10,0),MATCH('Lista - Âmbito Projeto GD'!$AC15,Auxiliar!$D$4:$I$4,0)) -> 1 | AK15: =SUM(AF15,AH15:AJ15) -> 2.5
A16: IN.074 | B16: =C16&"_"&D16 -> INSTRUMENT_EAD | C16: INSTRUMENT | D16: EAD | E16: Regulatory EAD | F16: Y | G16: Y | H16: N | I16: N | J16: Y | K16: Y | L16: =IFERROR(VLOOKUP($B16,'LISTA - Atual'!$B$1:$I$444,5,0),"Novo") -> Y | M16: =IF(L16="Novo","Novo Campo",IF(L16=F16,"Igual","Diferente")) -> Igual | N16: =IFERROR(VLOOKUP($B16,'LISTA - Atual'!$B$1:$I$444,6,0),"Novo") -> N | O16: =IF(N16="Novo","Novo Campo",IF(N16=G16,"Igual","Diferente")) -> Diferente | P16: =IFERROR(VLOOKUP($B16,'LISTA - Atual'!$B$1:$I$444,7,0),"Novo") -> N | Q16: =IF(P16="Novo","Novo Campo",IF(P16=H16,"Igual","Diferente")) -> Igual | R16: n/a | S16: =IFERROR(VLOOKUP($B16,'LISTA - Atual'!$B$1:$I$444,8,0),"Novo") -> Y | T16: =IF(S16="Novo","Novo Campo",IF(S16=J16,"Igual","Diferente")) -> Igual | U16: n/a | V16: N | W16: =IFERROR(VLOOKUP(B16,#REF!,11,0),"n/a") -> n/a | X16: =IFERROR(VLOOKUP(B16,#REF!,8,0),"n/a") -> n/a | Y16: ="ESG_RISKS & "&$F$2&$Y$1&$G$2 -> ESG_RISKS & ESTR & GD | Z16: Novo Campo | AA16: =VLOOKUP(Table1[[#This Row],[CONCAT]],'[1]1. Tipologias Testes GD'!$F:$L,7,0) -> Baixa | AB16: FLOAT 2 decimal places | AC16: M. Baixa | AD16: =INDEX(Auxiliar!$D$5:$I$10,MATCH('Lista - Âmbito Projeto GD'!AD$3,Auxiliar!$B$5:$B$10,0),MATCH('Lista - Âmbito Projeto GD'!$AC16,Auxiliar!$D$4:$I$4,0)) -> 1 | AE16: =INDEX(Auxiliar!$D$5:$I$10,MATCH('Lista - Âmbito Projeto GD'!AE$3,Auxiliar!$B$5:$B$10,0),MATCH('Lista - Âmbito Projeto GD'!$AC16,Auxiliar!$D$4:$I$4,0)) -> 1 | AF16: =INDEX(Auxiliar!$D$5:$I$10,MATCH('Lista - Âmbito Projeto GD'!AF$3,Auxiliar!$B$5:$B$10,0),MATCH('Lista - Âmbito Projeto GD'!$AC16,Auxiliar!$D$4:$I$4,0)) -> 1 | AG16: =IF(OR(AB16="Code List",AB16="Y, N"),AC16,"n.a.") -> n.a. | AH16: =INDEX(Auxiliar!$D$5:$I$10,MATCH('Lista - Âmbito Projeto GD'!AH$3,Auxiliar!$B$5:$B$10,0),MATCH('Lista - Âmbito Projeto GD'!$AG16,Auxiliar!$D$4:$I$4,0)) -> 0 | AI16: =INDEX(Auxiliar!$D$5:$I$10,MATCH('Lista - Âmbito Projeto GD'!AI$3,Auxiliar!$B$5:$B$10,0),MATCH('Lista - Âmbito Projeto GD'!$AC16,Auxiliar!$D$4:$I$4,0)) -> 0.5 | AJ16: =INDEX(Auxiliar!$D$5:$I$10,MATCH('Lista - Âmbito Projeto GD'!AJ$3,Auxiliar!$B$5:$B$10,0),MATCH('Lista - Âmbito Projeto GD'!$AC16,Auxiliar!$D$4:$I$4,0)) -> 1 | AK16: =SUM(AF16,AH16:AJ16) -> 2.5 | AL16: Capital
A17: IN.078 | B17: =C17&"_"&D17 -> INSTRUMENT_OFF_BLNC_SHT_AMNT_INSTRMNT | C17: INSTRUMENT | D17: OFF_BLNC_SHT_AMNT_INSTRMNT | E17: Off-balance sheet amount | F17: Y | G17: Y | H17: N | I17: N | J17: Y | K17: Y | L17: =IFERROR(VLOOKUP($B17,'LISTA - Atual'!$B$1:$I$444,5,0),"Novo") -> Y | M17: =IF(L17="Novo","Novo Campo",IF(L17=F17,"Igual","Diferente")) -> Igual | N17: =IFERROR(VLOOKUP($B17,'LISTA - Atual'!$B$1:$I$444,6,0),"Novo") -> Y | O17: =IF(N17="Novo","Novo Campo",IF(N17=G17,"Igual","Diferente")) -> Igual | P17: =IFERROR(VLOOKUP($B17,'LISTA - Atual'!$B$1:$I$444,7,0),"Novo") -> N | Q17: =IF(P17="Novo","Novo Campo",IF(P17=H17,"Igual","Diferente")) -> Igual | R17: n/a | S17: =IFERROR(VLOOKUP($B17,'LISTA - Atual'!$B$1:$I$444,8,0),"Novo") -> Y | T17: =IF(S17="Novo","Novo Campo",IF(S17=J17,"Igual","Diferente")) -> Igual | U17: n/a | V17: N | W17: =IFERROR(VLOOKUP(B17,#REF!,11,0),"n/a") -> n/a | X17: =IFERROR(VLOOKUP(B17,#REF!,8,0),"n/a") -> n/a | Y17: ="ESG_RISKS & "&$F$2&$Y$1&$G$2 -> ESG_RISKS & ESTR & GD | Z17: Novo Campo | AA17: =VLOOKUP(Table1[[#This Row],[CONCAT]],'[1]1. Tipologias Testes GD'!$F:$L,7,0) -> Baixa | AB17: FLOAT 2 decimal places | AC17: M. Baixa | AD17: 0 | AE17: =INDEX(Auxiliar!$D$5:$I$10,MATCH('Lista - Âmbito Projeto GD'!AE$3,Auxiliar!$B$5:$B$10,0),MATCH('Lista - Âmbito Projeto GD'!$AC17,Auxiliar!$D$4:$I$4,0)) -> 1 | AF17: =INDEX(Auxiliar!$D$5:$I$10,MATCH('Lista - Âmbito Projeto GD'!AF$3,Auxiliar!$B$5:$B$10,0),MATCH('Lista - Âmbito Projeto GD'!$AC17,Auxiliar!$D$4:$I$4,0)) -> 1 | AG17: =IF(OR(AB17="Code List",AB17="Y, N"),AC17,"n.a.") -> n.a. | AH17: =INDEX(Auxiliar!$D$5:$I$10,MATCH('Lista - Âmbito Projeto GD'!AH$3,Auxiliar!$B$5:$B$10,0),MATCH('Lista - Âmbito Projeto GD'!$AG17,Auxiliar!$D$4:$I$4,0)) -> 0 | AI17: =INDEX(Auxiliar!$D$5:$I$10,MATCH('Lista - Âmbito Projeto GD'!AI$3,Auxiliar!$B$5:$B$10,0),MATCH('Lista - Âmbito Projeto GD'!$AC17,Auxiliar!$D$4:$I$4,0)) -> 0.5 | AJ17: =INDEX(Auxiliar!$D$5:$I$10,MATCH('Lista - Âmbito Projeto GD'!AJ$3,Auxiliar!$B$5:$B$10,0),MATCH('Lista - Âmbito Projeto GD'!$AC17,Auxiliar!$D$4:$I$4,0)) -> 1 | AK17: =SUM(AF17,AH17:AJ17) -> 2.5
A18: IN.082 | B18: =C18&"_"&D18 -> INSTRUMENT_PRVSNS_OFF_BLNC_SHT | C18: INSTRUMENT | D18: PRVSNS_OFF_BLNC_SHT | E18: Provisions associated with off-balance sheet exposures | F18: Y | G18: Y | H18: N | I18: N | J18: N | K18: N | L18: =IFERROR(VLOOKUP($B18,'LISTA - Atual'!$B$1:$I$444,5,0),"Novo") -> Y | M18: =IF(L18="Novo","Novo Campo",IF(L18=F18,"Igual","Diferente")) -> Igual | N18: =IFERROR(VLOOKUP($B18,'LISTA - Atual'!$B$1:$I$444,6,0),"Novo") -> Y | O18: =IF(N18="Novo","Novo Campo",IF(N18=G18,"Igual","Diferente")) -> Igual | P18: =IFERROR(VLOOKUP($B18,'LISTA - Atual'!$B$1:$I$444,7,0),"Novo") -> N | Q18: =IF(P18="Novo","Novo Campo",IF(P18=H18,"Igual","Diferente")) -> Igual | R18: n/a | S18: =IFERROR(VLOOKUP($B18,'LISTA - Atual'!$B$1:$I$444,8,0),"Novo") -> N | T18: =IF(S18="Novo","Novo Campo",IF(S18=J18,"Igual","Diferente")) -> Igual | U18: n/a | V18: N | W18: =IFERROR(VLOOKUP(B18,#REF!,11,0),"n/a") -> n/a | X18: =IFERROR(VLOOKUP(B18,#REF!,8,0),"n/a") -> n/a | Y18: =$F$2&$Y$1&$G$2 -> ESTR & GD | Z18: Sem alteração | AA18: =VLOOKUP(Table1[[#This Row],[CONCAT]],'[1]1. Tipologias Testes GD'!$F:$L,7,0) -> Baixa | AB18: FLOAT 2 decimal places | AC18: M. Baixa | AD18: 0 | AE18: =INDEX(Auxiliar!$D$5:$I$10,MATCH('Lista - Âmbito Projeto GD'!AE$3,Auxiliar!$B$5:$B$10,0),MATCH('Lista - Âmbito Projeto GD'!$AC18,Auxiliar!$D$4:$I$4,0)) -> 1 | AF18: =INDEX(Auxiliar!$D$5:$I$10,MATCH('Lista - Âmbito Projeto GD'!AF$3,Auxiliar!$B$5:$B$10,0),MATCH('Lista - Âmbito Projeto GD'!$AC18,Auxiliar!$D$4:$I$4,0)) -> 1 | AG18: =IF(OR(AB18="Code List",AB18="Y, N"),AC18,"n.a.") -> n.a. | AH18: =INDEX(Auxiliar!$D$5:$I$10,MATCH('Lista - Âmbito Projeto GD'!AH$3,Auxiliar!$B$5:$B$10,0),MATCH('Lista - Âmbito Projeto GD'!$AG18,Auxiliar!$D$4:$I$4,0)) -> 0 | AI18: =INDEX(Auxiliar!$D$5:$I$10,MATCH('Lista - Âmbito Projeto GD'!AI$3,Auxiliar!$B$5:$B$10,0),MATCH('Lista - Âmbito Projeto GD'!$AC18,Auxiliar!$D$4:$I$4,0)) -> 0.5 | AJ18: =INDEX(Auxiliar!$D$5:$I$10,MATCH('Lista - Âmbito Projeto GD'!AJ$3,Auxiliar!$B$5:$B$10,0),MATCH('Lista - Âmbito Projeto GD'!$AC18,Auxiliar!$D$4:$I$4,0)) -> 1 | AK18: =SUM(AF18,AH18:AJ18) -> 2.5
A19: IN.085 | B19: =C19&"_"&D19 -> INSTRUMENT_RWA | C19: INSTRUMENT | D19: RWA | E19: RWA | F19: Y | G19: Y | H19: N | I19: N | J19: N | K19: Y | L19: =IFERROR(VLOOKUP($B19,'LISTA - Atual'!$B$1:$I$444,5,0),"Novo") -> Y | M19: =IF(L19="Novo","Novo Campo",IF(L19=F19,"Igual","Diferente")) -> Igual | N19: =IFERROR(VLOOKUP($B19,'LISTA - Atual'!$B$1:$I$444,6,0),"Novo") -> Y | O19: =IF(N19="Novo","Novo Campo",IF(N19=G19,"Igual","Diferente")) -> Igual | P19: =IFERROR(VLOOKUP($B19,'LISTA - Atual'!$B$1:$I$444,7,0),"Novo") -> N | Q19: =IF(P19="Novo","Novo Campo",IF(P19=H19,"Igual","Diferente")) -> Igual | R19: n/a | S19: =IFERROR(VLOOKUP($B19,'LISTA - Atual'!$B$1:$I$444,8,0),"Novo") -> N | T19: =IF(S19="Novo","Novo Campo",IF(S19=J19,"Igual","Diferente")) -> Igual | U19: n/a | V19: N | W19: =IFERROR(VLOOKUP(B19,#REF!,11,0),"n/a") -> n/a | X19: =IFERROR(VLOOKUP(B19,#REF!,8,0),"n/a") -> n/a | Y19: =$F$2&$Y$1&$G$2 -> ESTR & GD | Z19: Sem alteração | AA19: =VLOOKUP(Table1[[#This Row],[CONCAT]],'[1]1. Tipologias Testes GD'!$F:$L,7,0) -> Baixa | AB19: FLOAT 2 decimal places | AC19: M. Baixa | AD19: 0 | AE19: =INDEX(Auxiliar!$D$5:$I$10,MATCH('Lista - Âmbito Projeto GD'!AE$3,Auxiliar!$B$5:$B$10,0),MATCH('Lista - Âmbito Projeto GD'!$AC19,Auxiliar!$D$4:$I$4,0)) -> 1 | AF19: =INDEX(Auxiliar!$D$5:$I$10,MATCH('Lista - Âmbito Projeto GD'!AF$3,Auxiliar!$B$5:$B$10,0),MATCH('Lista - Âmbito Projeto GD'!$AC19,Auxiliar!$D$4:$I$4,0)) -> 1 | AG19: =IF(OR(AB19="Code List",AB19="Y, N"),AC19,"n.a.") -> n.a. | AH19: =INDEX(Auxiliar!$D$5:$I$10,MATCH('Lista - Âmbito Projeto GD'!AH$3,Auxiliar!$B$5:$B$10,0),MATCH('Lista - Âmbito Projeto GD'!$AG19,Auxiliar!$D$4:$I$4,0)) -> 0 | AI19: =INDEX(Auxiliar!$D$5:$I$10,MATCH('Lista - Âmbito Projeto GD'!AI$3,Auxiliar!$B$5:$B$10,0),MATCH('Lista - Âmbito Projeto GD'!$AC19,Auxiliar!$D$4:$I$4,0)) -> 0.5 | AJ19: =INDEX(Auxiliar!$D$5:$I$10,MATCH('Lista - Âmbito Projeto GD'!AJ$3,Auxiliar!$B$5:$B$10,0),MATCH('Lista - Âmbito Projeto GD'!$AC19,Auxiliar!$D$4:$I$4,0)) -> 1 | AK19: =SUM(AF19,AH19:AJ19) -> 2.5 | AL19: Capital
A20: IN.088 | B20: =C20&"_"&D20 -> INSTRUMENT_ACCMLTD_IMPRMNT_INSTRMNT | C20: INSTRUMENT | D20: ACCMLTD_IMPRMNT_INSTRMNT | E20: Sum of LLPs and other allowances | F20: Y | G20: Y | H20: Y | I20: N | J20: N | K20: Y | L20: =IFERROR(VLOOKUP($B20,'LISTA - Atual'!$B$1:$I$444,5,0),"Novo") -> Y | M20: =IF(L20="Novo","Novo Campo",IF(L20=F20,"Igual","Diferente")) -> Igual | N20: =IFERROR(VLOOKUP($B20,'LISTA - Atual'!$B$1:$I$444,6,0),"Novo") -> Y | O20: =IF(N20="Novo","Novo Campo",IF(N20=G20,"Igual","Diferente")) -> Igual | P20: =IFERROR(VLOOKUP($B20,'LISTA - Atual'!$B$1:$I$444,7,0),"Novo") -> Y | Q20: =IF(P20="Novo","Novo Campo",IF(P20=H20,"Igual","Diferente")) -> Igual | R20: n/a | S20: =IFERROR(VLOOKUP($B20,'LISTA - Atual'!$B$1:$I$444,8,0),"Novo") -> N | T20: =IF(S20="Novo","Novo Campo",IF(S20=J20,"Igual","Diferente")) -> Igual | U20: n/a | V20: N | W20: =IFERROR(VLOOKUP(B20,#REF!,11,0),"n/a") -> n/a | X20: =IFERROR(VLOOKUP(B20,#REF!,8,0),"n/a") -> n/a | Y20: =$F$2&$Y$1&$G$2&$Y$1&$H$2 -> ESTR & GD & PILAR3 | Z20: Sem alteração | AA20: =VLOOKUP(Table1[[#This Row],[CONCAT]],'[1]1. Tipologias Testes GD'!$F:$L,7,0) -> Baixa | AB20: FLOAT 2 decimal places | AC20: M. Baixa | AD20: 0 | AE20: =INDEX(Auxiliar!$D$5:$I$10,MATCH('Lista - Âmbito Projeto GD'!AE$3,Auxiliar!$B$5:$B$10,0),MATCH('Lista - Âmbito Projeto GD'!$AC20,Auxiliar!$D$4:$I$4,0)) -> 1 | AF20: =INDEX(Auxiliar!$D$5:$I$10,MATCH('Lista - Âmbito Projeto GD'!AF$3,Auxiliar!$B$5:$B$10,0),MATCH('Lista - Âmbito Projeto GD'!$AC20,Auxiliar!$D$4:$I$4,0)) -> 1 | AG20: =IF(OR(AB20="Code List",AB20="Y, N"),AC20,"n.a.") -> n.a. | AH20: =INDEX(Auxiliar!$D$5:$I$10,MATCH('Lista - Âmbito Projeto GD'!AH$3,Auxiliar!$B$5:$B$10,0),MATCH('Lista - Âmbito Projeto GD'!$AG20,Auxiliar!$D$4:$I$4,0)) -> 0 | AI20: =INDEX(Auxiliar!$D$5:$I$10,MATCH('Lista - Âmbito Projeto GD'!AI$3,Auxiliar!$B$5:$B$10,0),MATCH('Lista - Âmbito Projeto GD'!$AC20,Auxiliar!$D$4:$I$4,0)) -> 0.5 | AJ20: =INDEX(Auxiliar!$D$5:$I$10,MATCH('Lista - Âmbito Projeto GD'!AJ$3,Auxiliar!$B$5:$B$10,0),MATCH('Lista - Âmbito Projeto GD'!$AC20,Auxiliar!$D$4:$I$4,0)) -> 1 | AK20: =SUM(AF20,AH20:AJ20) -> 2.5
A21: IN.192 | B21: =C21&"_"&D21 -> INSTRUMENT_COD_SOC_INTRGRP | C21: INSTRUMENT | D21: COD_SOC_INTRGRP | E21: Cargabal identification code of the intragroup exposure | F21: Y | G21: Y | H21: N | I21: N | J21: N | K21: N | L21: =IFERROR(VLOOKUP($B21,'LISTA - Atual'!$B$1:$I$444,5,0),"Novo") -> Y | M21: =IF(L21="Novo","Novo Campo",IF(L21=F21,"Igual","Diferente")) -> Igual | N21: =IFERROR(VLOOKUP($B21,'LISTA - Atual'!$B$1:$I$444,6,0),"Novo") -> Y | O21: =IF(N21="Novo","Novo Campo",IF(N21=G21,"Igual","Diferente")) -> Igual | P21: =IFERROR(VLOOKUP($B21,'LISTA - Atual'!$B$1:$I$444,7,0),"Novo") -> N | Q21: =IF(P21="Novo","Novo Campo",IF(P21=H21,"Igual","Diferente")) -> Igual | R21: n/a | S21: =IFERROR(VLOOKUP($B21,'LISTA - Atual'!$B$1:$I$444,8,0),"Novo") -> N | T21: =IF(S21="Novo","Novo Campo",IF(S21=J21,"Igual","Diferente")) -> Igual | U21: n/a | V21: N | W21: =IFERROR(VLOOKUP(B21,#REF!,11,0),"n/a") -> n/a | X21: =IFERROR(VLOOKUP(B21,#REF!,8,0),"n/a") -> n/a | Y21: =$F$2&$Y$1&$G$2 -> ESTR & GD | Z21: Sem alteração | AA21: =VLOOKUP(Table1[[#This Row],[CONCAT]],'[1]1. Tipologias Testes GD'!$F:$L,7,0) -> Baixa | AB21: VARCHAR2(5) | AC21: M. Baixa | AD21: 0 | AE21: =INDEX(Auxiliar!$D$5:$I$10,MATCH('Lista - Âmbito Projeto GD'!AE$3,Auxiliar!$B$5:$B$10,0),MATCH('Lista - Âmbito Projeto GD'!$AC21,Auxiliar!$D$4:$I$4,0)) -> 1 | AF21: =INDEX(Auxiliar!$D$5:$I$10,MATCH('Lista - Âmbito Projeto GD'!AF$3,Auxiliar!$B$5:$B$10,0),MATCH('Lista - Âmbito Projeto GD'!$AC21,Auxiliar!$D$4:$I$4,0)) -> 1 | AG21: =IF(OR(AB21="Code List",AB21="Y, N"),AC21,"n.a.") -> n.a. | AH21: =INDEX(Auxiliar!$D$5:$I$10,MATCH('Lista - Âmbito Projeto GD'!AH$3,Auxiliar!$B$5:$B$10,0),MATCH('Lista - Âmbito Projeto GD'!$AG21,Auxiliar!$D$4:$I$4,0)) -> 0 | AI21: =INDEX(Auxiliar!$D$5:$I$10,MATCH('Lista - Âmbito Projeto GD'!AI$3,Auxiliar!$B$5:$B$10,0),MATCH('Lista - Âmbito Projeto GD'!$AC21,Auxiliar!$D$4:$I$4,0)) -> 0.5 | AJ21: =INDEX(Auxiliar!$D$5:$I$10,MATCH('Lista - Âmbito Projeto GD'!AJ$3,Auxiliar!$B$5:$B$10,0),MATCH('Lista - Âmbito Projeto GD'!$AC21,Auxiliar!$D$4:$I$4,0)) -> 1 | AK21: =SUM(AF21,AH21:AJ21) -> 2.5
A22: IN.193 | B22: =C22&"_"&D22 -> INSTRUMENT_LCL_INSTMRNT_ID | C22: INSTRUMENT | D22: LCL_INSTMRNT_ID | E22: Local Instrument ID | F22: Y | G22: Y | H22: Y | I22: N | J22: N | K22: N | L22: =IFERROR(VLOOKUP($B22,'LISTA - Atual'!$B$1:$I$444,5,0),"Novo") -> Y | M22: =IF(L22="Novo","Novo Campo",IF(L22=F22,"Igual","Diferente")) -> Igual | N22: =IFERROR(VLOOKUP($B22,'LISTA - Atual'!$B$1:$I$444,6,0),"Novo") -> Y | O22: =IF(N22="Novo","Novo Campo",IF(N22=G22,"Igual","Diferente")) -> Igual | P22: =IFERROR(VLOOKUP($B22,'LISTA - Atual'!$B$1:$I$444,7,0),"Novo") -> Y | Q22: =IF(P22="Novo","Novo Campo",IF(P22=H22,"Igual","Diferente")) -> Igual | R22: n/a | S22: =IFERROR(VLOOKUP($B22,'LISTA - Atual'!$B$1:$I$444,8,0),"Novo") -> N | T22: =IF(S22="Novo","Novo Campo",IF(S22=J22,"Igual","Diferente")) -> Igual | U22: n/a | V22: N | W22: =IFERROR(VLOOKUP(B22,#REF!,11,0),"n/a") -> n/a | X22: =IFERROR(VLOOKUP(B22,#REF!,8,0),"n/a") -> n/a | Y22: =$F$2&$Y$1&$G$2&$Y$1&$H$2 -> ESTR & GD & PILAR3 | Z22: Sem alteração | AA22: =VLOOKUP(Table1[[#This Row],[CONCAT]],'[1]1. Tipologias Testes GD'!$F:$L,7,0) -> Baixa | AB22: VARCHAR2(60) | AC22: M. Baixa | AD22: 0 | AE22: =INDEX(Auxiliar!$D$5:$I$10,MATCH('Lista - Âmbito Projeto GD'!AE$3,Auxiliar!$B$5:$B$10,0),MATCH('Lista - Âmbito Projeto GD'!$AC22,Auxiliar!$D$4:$I$4,0)) -> 1 | AF22: =INDEX(Auxiliar!$D$5:$I$10,MATCH('Lista - Âmbito Projeto GD'!AF$3,Auxiliar!$B$5:$B$10,0),MATCH('Lista - Âmbito Projeto GD'!$AC22,Auxiliar!$D$4:$I$4,0)) -> 1 | AG22: =IF(OR(AB22="Code List",AB22="Y, N"),AC22,"n.a.") -> n.a. | AH22: =INDEX(Auxiliar!$D$5:$I$10,MATCH('Lista - Âmbito Projeto GD'!AH$3,Auxiliar!$B$5:$B$10,0),MATCH('Lista - Âmbito Projeto GD'!$AG22,Auxiliar!$D$4:$I$4,0)) -> 0 | AI22: =INDEX(Auxiliar!$D$5:$I$10,MATCH('Lista - Âmbito Projeto GD'!AI$3,Auxiliar!$B$5:$B$10,0),MATCH('Lista - Âmbito Projeto GD'!$AC22,Auxiliar!$D$4:$I$4,0)) -> 0.5 | AJ22: =INDEX(Auxiliar!$D$5:$I$10,MATCH('Lista - Âmbito Projeto GD'!AJ$3,Auxiliar!$B$5:$B$10,0),MATCH('Lista - Âmbito Projeto GD'!$AC22,Auxiliar!$D$4:$I$4,0)) -> 1 | AK22: =SUM(AF22,AH22:AJ22) -> 2.5
A23: IN.196 | B23: =C23&"_"&D23 -> INSTRUMENT_AVRG_BLNC | C23: INSTRUMENT | D23: AVRG_BLNC | E23: Average balance | F23: N | G23: Y | H23: N | I23: N | J23: N | K23: N | L23: =IFERROR(VLOOKUP($B23,'LISTA - Atual'!$B$1:$I$444,5,0),"Novo") -> N | M23: =IF(L23="Novo","Novo Campo",IF(L23=F23,"Igual","Diferente")) -> Igual | N23: =IFERROR(VLOOKUP($B23,'LISTA - Atual'!$B$1:$I$444,6,0),"Novo") -> Y | O23: =IF(N23="Novo","Novo Campo",IF(N23=G23,"Igual","Diferente")) -> Igual | P23: =IFERROR(VLOOKUP($B23,'LISTA - Atual'!$B$1:$I$444,7,0),"Novo") -> N | Q23: =IF(P23="Novo","Novo Campo",IF(P23=H23,"Igual","Diferente")) -> Igual | R23: n/a | S23: =IFERROR(VLOOKUP($B23,'LISTA - Atual'!$B$1:$I$444,8,0),"Novo") -> N | T23: =IF(S23="Novo","Novo Campo",IF(S23=J23,"Igual","Diferente")) -> Igual | U23: n/a | V23: N | W23: =IFERROR(VLOOKUP(B23,#REF!,11,0),"n/a") -> n/a | X23: =IFERROR(VLOOKUP(B23,#REF!,8,0),"n/a") -> n/a | Y23: =$G$2 -> GD | Z23: Sem alteração | AA23: =VLOOKUP(Table1[[#This Row],[CONCAT]],'[1]1. Tipologias Testes GD'!$F:$L,7,0) -> Média | AB23: FLOAT 2 decimal places | AC23: Média | AD23: 0 | AE23: =INDEX(Auxiliar!$D$5:$I$10,MATCH('Lista - Âmbito Projeto GD'!AE$3,Auxiliar!$B$5:$B$10,0),MATCH('Lista - Âmbito Projeto GD'!$AC23,Auxiliar!$D$4:$I$4,0)) -> 3 | AF23: =INDEX(Auxiliar!$D$5:$I$10,MATCH('Lista - Âmbito Projeto GD'!AF$3,Auxiliar!$B$5:$B$10,0),MATCH('Lista - Âmbito Projeto GD'!$AC23,Auxiliar!$D$4:$I$4,0)) -> 3 | AG23: =IF(OR(AB23="Code List",AB23="Y, N"),AC23,"n.a.") -> n.a. | AH23: =INDEX(Auxiliar!$D$5:$I$10,MATCH('Lista - Âmbito Projeto GD'!AH$3,Auxiliar!$B$5:$B$10,0),MATCH('Lista - Âmbito Projeto GD'!$AG23,Auxiliar!$D$4:$I$4,0)) -> 0 | AI23: =INDEX(Auxiliar!$D$5:$I$10,MATCH('Lista - Âmbito Projeto GD'!AI$3,Auxiliar!$B$5:$B$10,0),MATCH('Lista - Âmbito Projeto GD'!$AC23,Auxiliar!$D$4:$I$4,0)) -> 0.5 | AJ23: =INDEX(Auxiliar!$D$5:$I$10,MATCH('Lista - Âmbito Projeto GD'!AJ$3,Auxiliar!$B$5:$B$10,0),MATCH('Lista - Âmbito Projeto GD'!$AC23,Auxiliar!$D$4:$I$4,0)) -> 1 | AK23: =SUM(AF23,AH23:AJ23) -> 4.5
A24: IN.197 | B24: =C24&"_"&D24 -> INSTRUMENT_NW_BSNSS | C24: INSTRUMENT | D24: NW_BSNSS | E24: New Business | F24: N | G24: Y | H24: Y | I24: N | J24: N | K24: N | L24: =IFERROR(VLOOKUP($B24,'LISTA - Atual'!$B$1:$I$444,5,0),"Novo") -> N | M24: =IF(L24="Novo","Novo Campo",IF(L24=F24,"Igual","Diferente")) -> Igual | N24: =IFERROR(VLOOKUP($B24,'LISTA - Atual'!$B$1:$I$444,6,0),"Novo") -> Y | O24: =IF(N24="Novo","Novo Campo",IF(N24=G24,"Igual","Diferente")) -> Igual | P24: =IFERROR(VLOOKUP($B24,'LISTA - Atual'!$B$1:$I$444,7,0),"Novo") -> N | Q24: =IF(P24="Novo","Novo Campo",IF(P24=H24,"Igual","Diferente")) -> Diferente | R24: n/a | S24: =IFERROR(VLOOKUP($B24,'LISTA - Atual'!$B$1:$I$444,8,0),"Novo") -> N | T24: =IF(S24="Novo","Novo Campo",IF(S24=J24,"Igual","Diferente")) -> Igual | U24: n/a | V24: N | W24: =IFERROR(VLOOKUP(B24,#REF!,11,0),"n/a") -> n/a | X24: =IFERROR(VLOOKUP(B24,#REF!,8,0),"n/a") -> n/a | Y24: =$G$2&$Y$1&$H$2 -> GD & PILAR3 | Z24: Novo Campo | AA24: =VLOOKUP(Table1[[#This Row],[CONCAT]],'[1]1. Tipologias Testes GD'!$F:$L,7,0) -> Média | AB24: Y, N | AC24: M. Alta | AD24: 0 | AE24: =INDEX(Auxiliar!$D$5:$I$10,MATCH('Lista - Âmbito Projeto GD'!AE$3,Auxiliar!$B$5:$B$10,0),MATCH('Lista - Âmbito Projeto GD'!$AC24,Auxiliar!$D$4:$I$4,0)) -> 8 | AF24: =INDEX(Auxiliar!$D$5:$I$10,MATCH('Lista - Âmbito Projeto GD'!AF$3,Auxiliar!$B$5:$B$10,0),MATCH('Lista - Âmbito Projeto GD'!$AC24,Auxiliar!$D$4:$I$4,0)) -> 3 | AG24: =IF(OR(AB24="Code List",AB24="Y, N"),AC24,"n.a.") -> M. Alta | AH24: =INDEX(Auxiliar!$D$5:$I$10,MATCH('Lista - Âmbito Projeto GD'!AH$3,Auxiliar!$B$5:$B$10,0),MATCH('Lista - Âmbito Projeto GD'!$AG24,Auxiliar!$D$4:$I$4,0)) -> 1 | AI24: =INDEX(Auxiliar!$D$5:$I$10,MATCH('Lista - Âmbito Projeto GD'!AI$3,Auxiliar!$B$5:$B$10,0),MATCH('Lista - Âmbito Projeto GD'!$AC24,Auxiliar!$D$4:$I$4,0)) -> 1 | AJ24: =INDEX(Auxiliar!$D$5:$I$10,MATCH('Lista - Âmbito Projeto GD'!AJ$3,Auxiliar!$B$5:$B$10,0),MATCH('Lista - Âmbito Projeto GD'!$AC24,Auxiliar!$D$4:$I$4,0)) -> 2 | AK24: =SUM(AF24,AH24:AJ24) -> 7
A25: IN.198 | B25: =C25&"_"&D25 -> INSTRUMENT_GRSS_INTRST_INCM | C25: INSTRUMENT | D25: GRSS_INTRST_INCM | E25: Gross Interest income before distribution to SCIB under the Collabotarion Revenues distribution agreement | F25: N | G25: Y | H25: Y | I25: N | J25: N | K25: N | L25: =IFERROR(VLOOKUP($B25,'LISTA - Atual'!$B$1:$I$444,5,0),"Novo") -> N | M25: =IF(L25="Novo","Novo Campo",IF(L25=F25,"Igual","Diferente")) -> Igual | N25: =IFERROR(VLOOKUP($B25,'LISTA - Atual'!$B$1:$I$444,6,0),"Novo") -> Y | O25: =IF(N25="Novo","Novo Campo",IF(N25=G25,"Igual","Diferente")) -> Igual | P25: =IFERROR(VLOOKUP($B25,'LISTA - Atual'!$B$1:$I$444,7,0),"Novo") -> Y | Q25: =IF(P25="Novo","Novo Campo",IF(P25=H25,"Igual","Diferente")) -> Igual | R25: n/a | S25: =IFERROR(VLOOKUP($B25,'LISTA - Atual'!$B$1:$I$444,8,0),"Novo") -> N | T25: =IF(S25="Novo","Novo Campo",IF(S25=J25,"Igual","Diferente")) -> Igual | U25: n/a | V25: N | W25: =IFERROR(VLOOKUP(B25,#REF!,11,0),"n/a") -> n/a | X25: =IFERROR(VLOOKUP(B25,#REF!,8,0),"n/a") -> n/a | Y25: =$G$2&$Y$1&$H$2 -> GD & PILAR3 | Z25: Sem alteração | AA25: =VLOOKUP(Table1[[#This Row],[CONCAT]],'[1]1. Tipologias Testes GD'!$F:$L,7,0) -> Alta | AB25: FLOAT 2 decimal places | AC25: Alta | AD25: 0 | AE25: =INDEX(Auxiliar!$D$5:$I$10,MATCH('Lista - Âmbito Projeto GD'!AE$3,Auxiliar!$B$5:$B$10,0),MATCH('Lista - Âmbito Projeto GD'!$AC25,Auxiliar!$D$4:$I$4,0)) -> 6 | AF25: =INDEX(Auxiliar!$D$5:$I$10,MATCH('Lista - Âmbito Projeto GD'!AF$3,Auxiliar!$B$5:$B$10,0),MATCH('Lista - Âmbito Projeto GD'!$AC25,Auxiliar!$D$4:$I$4,0)) -> 6 | AG25: =IF(OR(AB25="Code List",AB25="Y, N"),AC25,"n.a.") -> n.a. | AH25: =INDEX(Auxiliar!$D$5:$I$10,MATCH('Lista - Âmbito Projeto GD'!AH$3,Auxiliar!$B$5:$B$10,0),MATCH('Lista - Âmbito Projeto GD'!$AG25,Auxiliar!$D$4:$I$4,0)) -> 0 | AI25: =INDEX(Auxiliar!$D$5:$I$10,MATCH('Lista - Âmbito Projeto GD'!AI$3,Auxiliar!$B$5:$B$10,0),MATCH('Lista - Âmbito Projeto GD'!$AC25,Auxiliar!$D$4:$I$4,0)) -> 0.5 | AJ25: =INDEX(Auxiliar!$D$5:$I$10,MATCH('Lista - Âmbito Projeto GD'!AJ$3,Auxiliar!$B$5:$B$10,0),MATCH('Lista - Âmbito Projeto GD'!$AC25,Auxiliar!$D$4:$I$4,0)) -> 1 | AK25: =SUM(AF25,AH25:AJ25) -> 7.5
A26: IN.199 | B26: =C26&"_"&D26 -> INSTRUMENT_GRSS_CMMSSN_INCM | C26: INSTRUMENT | D26: GRSS_CMMSSN_INCM | E26: Gross fee and commission income before distribution to SCIB under the Collabotarion Revenues distribution agreement | F26: N | G26: Y | H26: Y | I26: N | J26: N | K26: N | L26: =IFERROR(VLOOKUP($B26,'LISTA - Atual'!$B$1:$I$444,5,0),"Novo") -> N | M26: =IF(L26="Novo","Novo Campo",IF(L26=F26,"Igual","Diferente")) -> Igual | N26: =IFERROR(VLOOKUP($B26,'LISTA - Atual'!$B$1:$I$444,6,0),"Novo") -> Y | O26: =IF(N26="Novo","Novo Campo",IF(N26=G26,"Igual","Diferente")) -> Igual | P26: =IFERROR(VLOOKUP($B26,'LISTA - Atual'!$B$1:$I$444,7,0),"Novo") -> Y | Q26: =IF(P26="Novo","Novo Campo",IF(P26=H26,"Igual","Diferente")) -> Igual | R26: n/a | S26: =IFERROR(VLOOKUP($B26,'LISTA - Atual'!$B$1:$I$444,8,0),"Novo") -> N | T26: =IF(S26="Novo","Novo Campo",IF(S26=J26,"Igual","Diferente")) -> Igual | U26: n/a | V26: N | W26: =IFERROR(VLOOKUP(B26,#REF!,11,0),"n/a") -> n/a | X26: =IFERROR(VLOOKUP(B26,#REF!,8,0),"n/a") -> n/a | Y26: =$G$2&$Y$1&$H$2 -> GD & PILAR3 | Z26: Sem alteração | AA26: =VLOOKUP(Table1[[#This Row],[CONCAT]],'[1]1. Tipologias Testes GD'!$F:$L,7,0) -> Alta | AB26: FLOAT 2 decimal places | AC26: Alta | AD26: 0 | AE26: =INDEX(Auxiliar!$D$5:$I$10,MATCH('Lista - Âmbito Projeto GD'!AE$3,Auxiliar!$B$5:$B$10,0),MATCH('Lista - Âmbito Projeto GD'!$AC26,Auxiliar!$D$4:$I$4,0)) -> 6 | AF26: =INDEX(Auxiliar!$D$5:$I$10,MATCH('Lista - Âmbito Projeto GD'!AF$3,Auxiliar!$B$5:$B$10,0),MATCH('Lista - Âmbito Projeto GD'!$AC26,Auxiliar!$D$4:$I$4,0)) -> 6 | AG26: =IF(OR(AB26="Code List",AB26="Y, N"),AC26,"n.a.") -> n.a. | AH26: =INDEX(Auxiliar!$D$5:$I$10,MATCH('Lista - Âmbito Projeto GD'!AH$3,Auxiliar!$B$5:$B$10,0),MATCH('Lista - Âmbito Projeto GD'!$AG26,Auxiliar!$D$4:$I$4,0)) -> 0 | AI26: =INDEX(Auxiliar!$D$5:$I$10,MATCH('Lista - Âmbito Projeto GD'!AI$3,Auxiliar!$B$5:$B$10,0),MATCH('Lista - Âmbito Projeto GD'!$AC26,Auxiliar!$D$4:$I$4,0)) -> 0.5 | AJ26: =INDEX(Auxiliar!$D$5:$I$10,MATCH('Lista - Âmbito Projeto GD'!AJ$3,Auxiliar!$B$5:$B$10,0),MATCH('Lista - Âmbito Projeto GD'!$AC26,Auxiliar!$D$4:$I$4,0)) -> 1 | AK26: =SUM(AF26,AH26:AJ26) -> 7.5
A27: IN.200 | B27: =C27&"_"&D27 -> INSTRUMENT_INTRNL_TRNSFR_RT | C27: INSTRUMENT | D27: INTRNL_TRNSFR_RT | E27: Internal transfer rate amount | F27: N | G27: Y | H27: N | I27: N | J27: N | K27: N | L27: =IFERROR(VLOOKUP($B27,'LISTA - Atual'!$B$1:$I$444,5,0),"Novo") -> N | M27: =IF(L27="Novo","Novo Campo",IF(L27=F27,"Igual","Diferente")) -> Igual | N27: =IFERROR(VLOOKUP($B27,'LISTA - Atual'!$B$1:$I$444,6,0),"Novo") -> Y | O27: =IF(N27="Novo","Novo Campo",IF(N27=G27,"Igual","Diferente")) -> Igual | P27: =IFERROR(VLOOKUP($B27,'LISTA - Atual'!$B$1:$I$444,7,0),"Novo") -> N | Q27: =IF(P27="Novo","Novo Campo",IF(P27=H27,"Igual","Diferente")) -> Igual | R27: n/a | S27: =IFERROR(VLOOKUP($B27,'LISTA - Atual'!$B$1:$I$444,8,0),"Novo") -> N | T27: =IF(S27="Novo","Novo Campo",IF(S27=J27,"Igual","Diferente")) -> Igual | U27: n/a | V27: N | W27: =IFERROR(VLOOKUP(B27,#REF!,11,0),"n/a") -> n/a | X27: =IFERROR(VLOOKUP(B27,#REF!,8,0),"n/a") -> n/a | Y27: =$G$2 -> GD | Z27: Sem alteração | AA27: =VLOOKUP(Table1[[#This Row],[CONCAT]],'[1]1. Tipologias Testes GD'!$F:$L,7,0) -> Alta | AB27: FLOAT 2 decimal places | AC27: Média | AD27: 0 | AE27: =INDEX(Auxiliar!$D$5:$I$10,MATCH('Lista - Âmbito Projeto GD'!AE$3,Auxiliar!$B$5:$B$10,0),MATCH('Lista - Âmbito Projeto GD'!$AC27,Auxiliar!$D$4:$I$4,0)) -> 3 | AF27: =INDEX(Auxiliar!$D$5:$I$10,MATCH('Lista - Âmbito Projeto GD'!AF$3,Auxiliar!$B$5:$B$10,0),MATCH('Lista - Âmbito Projeto GD'!$AC27,Auxiliar!$D$4:$I$4,0)) -> 3 | AG27: =IF(OR(AB27="Code List",AB27="Y, N"),AC27,"n.a.") -> n.a. | AH27: =INDEX(Auxiliar!$D$5:$I$10,MATCH('Lista - Âmbito Projeto GD'!AH$3,Auxiliar!$B$5:$B$10,0),MATCH('Lista - Âmbito Projeto GD'!$AG27,Auxiliar!$D$4:$I$4,0)) -> 0 | AI27: =INDEX(Auxiliar!$D$5:$I$10,MATCH('Lista - Âmbito Projeto GD'!AI$3,Auxiliar!$B$5:$B$10,0),MATCH('Lista - Âmbito Projeto GD'!$AC27,Auxiliar!$D$4:$I$4,0)) -> 0.5 | AJ27: =INDEX(Auxiliar!$D$5:$I$10,MATCH('Lista - Âmbito Projeto GD'!AJ$3,Auxiliar!$B$5:$B$10,0),MATCH('Lista - Âmbito Projeto GD'!$AC27,Auxiliar!$D$4:$I$4,0)) -> 1 | AK27: =SUM(AF27,AH27:AJ27) -> 4.5
A28: IN.201 | B28: =C28&"_"&D28 -> INSTRUMENT_NT_LN_LSS_PRVSN | C28: INSTRUMENT | D28: NT_LN_LSS_PRVSN | E28: Net loan-loss provisions | F28: N | G28: Y | H28: N | I28: N | J28: N | K28: N | L28: =IFERROR(VLOOKUP($B28,'LISTA - Atual'!$B$1:$I$444,5,0),"Novo") -> N | M28: =IF(L28="Novo","Novo Campo",IF(L28=F28,"Igual","Diferente")) -> Igual | N28: =IFERROR(VLOOKUP($B28,'LISTA - Atual'!$B$1:$I$444,6,0),"Novo") -> Y | O28: =IF(N28="Novo","Novo Campo",IF(N28=G28,"Igual","Diferente")) -> Igual | P28: =IFERROR(VLOOKUP($B28,'LISTA - Atual'!$B$1:$I$444,7,0),"Novo") -> N | Q28: =IF(P28="Novo","Novo Campo",IF(P28=H28,"Igual","Diferente")) -> Igual | R28: n/a | S28: =IFERROR(VLOOKUP($B28,'LISTA - Atual'!$B$1:$I$444,8,0),"Novo") -> N | T28: =IF(S28="Novo","Novo Campo",IF(S28=J28,"Igual","Diferente")) -> Igual | U28: n/a | V28: N | W28: =IFERROR(VLOOKUP(B28,#REF!,11,0),"n/a") -> n/a | X28: =IFERROR(VLOOKUP(B28,#REF!,8,0),"n/a") -> n/a | Y28: =$G$2 -> GD | Z28: Sem alteração | AA28: =VLOOKUP(Table1[[#This Row],[CONCAT]],'[1]1. Tipologias Testes GD'!$F:$L,7,0) -> Média | AB28: FLOAT 2 decimal places | AC28: Média | AD28: 0 | AE28: =INDEX(Auxiliar!$D$5:$I$10,MATCH('Lista - Âmbito Projeto GD'!AE$3,Auxiliar!$B$5:$B$10,0),MATCH('Lista - Âmbito Projeto GD'!$AC28,Auxiliar!$D$4:$I$4,0)) -> 3 | AF28: =INDEX(Auxiliar!$D$5:$I$10,MATCH('Lista - Âmbito Projeto GD'!AF$3,Auxiliar!$B$5:$B$10,0),MATCH('Lista - Âmbito Projeto GD'!$AC28,Auxiliar!$D$4:$I$4,0)) -> 3 | AG28: =IF(OR(AB28="Code List",AB28="Y, N"),AC28,"n.a.") -> n.a. | AH28: =INDEX(Auxiliar!$D$5:$I$10,MATCH('Lista - Âmbito Projeto GD'!AH$3,Auxiliar!$B$5:$B$10,0),MATCH('Lista - Âmbito Projeto GD'!$AG28,Auxiliar!$D$4:$I$4,0)) -> 0 | AI28: =INDEX(Auxiliar!$D$5:$I$10,MATCH('Lista - Âmbito Projeto GD'!AI$3,Auxiliar!$B$5:$B$10,0),MATCH('Lista - Âmbito Projeto GD'!$AC28,Auxiliar!$D$4:$I$4,0)) -> 0.5 | AJ28: =INDEX(Auxiliar!$D$5:$I$10,MATCH('Lista - Âmbito Projeto GD'!AJ$3,Auxiliar!$B$5:$B$10,0),MATCH('Lista - Âmbito Projeto GD'!$AC28,Auxiliar!$D$4:$I$4,0)) -> 1 | AK28: =SUM(AF28,AH28:AJ28) -> 4.5
A29: IN.202 | B29: =C29&"_"&D29 -> INSTRUMENT_BSNSS_AREA | C29: INSTRUMENT | D29: BSNSS_AREA | E29: Business Area | F29: N | G29: Y | H29: N | I29: N | J29: N | K29: N | L29: =IFERROR(VLOOKUP($B29,'LISTA - Atual'!$B$1:$I$444,5,0),"Novo") -> N | M29: =IF(L29="Novo","Novo Campo",IF(L29=F29,"Igual","Diferente")) -> Igual | N29: =IFERROR(VLOOKUP($B29,'LISTA - Atual'!$B$1:$I$444,6,0),"Novo") -> Y | O29: =IF(N29="Novo","Novo Campo",IF(N29=G29,"Igual","Diferente")) -> Igual | P29: =IFERROR(VLOOKUP($B29,'LISTA - Atual'!$B$1:$I$444,7,0),"Novo") -> N | Q29: =IF(P29="Novo","Novo Campo",IF(P29=H29,"Igual","Diferente")) -> Igual | R29: n/a | S29: =IFERROR(VLOOKUP($B29,'LISTA - Atual'!$B$1:$I$444,8,0),"Novo") -> N | T29: =IF(S29="Novo","Novo Campo",IF(S29=J29,"Igual","Diferente")) -> Igual | U29: n/a | V29: N | W29: =IFERROR(VLOOKUP(B29,#REF!,11,0),"n/a") -> n/a | X29: =IFERROR(VLOOKUP(B29,#REF!,8,0),"n/a") -> n/a | Y29: =$G$2 -> GD | Z29: Sem alteração | AA29: =VLOOKUP(Table1[[#This Row],[CONCAT]],'[1]1. Tipologias Testes GD'!$F:$L,7,0) -> Alta | AB29: Code List | AC29: Alta | AD29: 0 | AE29: =INDEX(Auxiliar!$D$5:$I$10,MATCH('Lista - Âmbito Projeto GD'!AE$3,Auxiliar!$B$5:$B$10,0),MATCH('Lista - Âmbito Projeto GD'!$AC29,Auxiliar!$D$4:$I$4,0)) -> 6 | AF29: =INDEX(Auxiliar!$D$5:$I$10,MATCH('Lista - Âmbito Projeto GD'!AF$3,Auxiliar!$B$5:$B$10,0),MATCH('Lista - Âmbito Projeto GD'!$AC29,Auxiliar!$D$4:$I$4,0)) -> 6 | AG29: =IF(OR(AB29="Code List",AB29="Y, N"),AC29,"n.a.") -> Alta | AH29: =INDEX(Auxiliar!$D$5:$I$10,MATCH('Lista - Âmbito Projeto GD'!AH$3,Auxiliar!$B$5:$B$10,0),MATCH('Lista - Âmbito Projeto GD'!$AG29,Auxiliar!$D$4:$I$4,0)) -> 0.5 | AI29: =INDEX(Auxiliar!$D$5:$I$10,MATCH('Lista - Âmbito Projeto GD'!AI$3,Auxiliar!$B$5:$B$10,0),MATCH('Lista - Âmbito Projeto GD'!$AC29,Auxiliar!$D$4:$I$4,0)) -> 0.5 | AJ29: =INDEX(Auxiliar!$D$5:$I$10,MATCH('Lista - Âmbito Projeto GD'!AJ$3,Auxiliar!$B$5:$B$10,0),MATCH('Lista - Âmbito Projeto GD'!$AC29,Auxiliar!$D$4:$I$4,0)) -> 1 | AK29: =SUM(AF29,AH29:AJ29) -> 8
A30: IN.203 | B30: =C30&"_"&D30 -> INSTRUMENT_MNGMNT_PRDCT | C30: INSTRUMENT | D30: MNGMNT_PRDCT | E30: Management Product | F30: N | G30: Y | H30: N | I30: N | J30: N | K30: N | L30: =IFERROR(VLOOKUP($B30,'LISTA - Atual'!$B$1:$I$444,5,0),"Novo") -> N | M30: =IF(L30="Novo","Novo Campo",IF(L30=F30,"Igual","Diferente")) -> Igual | N30: =IFERROR(VLOOKUP($B30,'LISTA - Atual'!$B$1:$I$444,6,0),"Novo") -> Y | O30: =IF(N30="Novo","Novo Campo",IF(N30=G30,"Igual","Diferente")) -> Igual | P30: =IFERROR(VLOOKUP($B30,'LISTA - Atual'!$B$1:$I$444,7,0),"Novo") -> N | Q30: =IF(P30="Novo","Novo Campo",IF(P30=H30,"Igual","Diferente")) -> Igual | R30: n/a | S30: =IFERROR(VLOOKUP($B30,'LISTA - Atual'!$B$1:$I$444,8,0),"Novo") -> N | T30: =IF(S30="Novo","Novo Campo",IF(S30=J30,"Igual","Diferente")) -> Igual | U30: n/a | V30: N | W30: =IFERROR(VLOOKUP(B30,#REF!,11,0),"n/a") -> n/a | X30: =IFERROR(VLOOKUP(B30,#REF!,8,0),"n/a") -> n/a | Y30: =$G$2 -> GD | Z30: Sem alteração | AA30: =VLOOKUP(Table1[[#This Row],[CONCAT]],'[1]1. Tipologias Testes GD'!$F:$L,7,0) -> Média | AB30: Code List | AC30: Alta | AD30: 0 | AE30: =INDEX(Auxiliar!$D$5:$I$10,MATCH('Lista - Âmbito Projeto GD'!AE$3,Auxiliar!$B$5:$B$10,0),MATCH('Lista - Âmbito Projeto GD'!$AC30,Auxiliar!$D$4:$I$4,0)) -> 6 | AF30: =INDEX(Auxiliar!$D$5:$I$10,MATCH('Lista - Âmbito Projeto GD'!AF$3,Auxiliar!$B$5:$B$10,0),MATCH('Lista - Âmbito Projeto GD'!$AC30,Auxiliar!$D$4:$I$4,0)) -> 6 | AG30: =IF(OR(AB30="Code List",AB30="Y, N"),AC30,"n.a.") -> Alta | AH30: =INDEX(Auxiliar!$D$5:$I$10,MATCH('Lista - Âmbito Projeto GD'!AH$3,Auxiliar!$B$5:$B$10,0),MATCH('Lista - Âmbito Projeto GD'!$AG30,Auxiliar!$D$4:$I$4,0)) -> 0.5 | AI30: =INDEX(Auxiliar!$D$5:$I$10,MATCH('Lista - Âmbito Projeto GD'!AI$3,Auxiliar!$B$5:$B$10,0),MATCH('Lista - Âmbito Projeto GD'!$AC30,Auxiliar!$D$4:$I$4,0)) -> 0.5 | AJ30: =INDEX(Auxiliar!$D$5:$I$10,MATCH('Lista - Âmbito Projeto GD'!AJ$3,Auxiliar!$B$5:$B$10,0),MATCH('Lista - Âmbito Projeto GD'!$AC30,Auxiliar!$D$4:$I$4,0)) -> 1 | AK30: =SUM(AF30,AH30:AJ30) -> 8
A31: IN.204 | B31: =C31&"_"&D31 -> INSTRUMENT_GRSS_CMMSSN_EXPNS | C31: INSTRUMENT | D31: GRSS_CMMSSN_EXPNS | E31: Gross fee and commission expense before distribution to SCIB under the Collabotarion Revenues distribution agreement | F31: N | G31: Y | H31: N | I31: N | J31: N | K31: N | L31: =IFERROR(VLOOKUP($B31,'LISTA - Atual'!$B$1:$I$444,5,0),"Novo") -> N | M31: =IF(L31="Novo","Novo Campo",IF(L31=F31,"Igual","Diferente")) -> Igual | N31: =IFERROR(VLOOKUP($B31,'LISTA - Atual'!$B$1:$I$444,6,0),"Novo") -> Y | O31: =IF(N31="Novo","Novo Campo",IF(N31=G31,"Igual","Diferente")) -> Igual | P31: =IFERROR(VLOOKUP($B31,'LISTA - Atual'!$B$1:$I$444,7,0),"Novo") -> N | Q31: =IF(P31="Novo","Novo Campo",IF(P31=H31,"Igual","Diferente")) -> Igual | R31: n/a | S31: =IFERROR(VLOOKUP($B31,'LISTA - Atual'!$B$1:$I$444,8,0),"Novo") -> N | T31: =IF(S31="Novo","Novo Campo",IF(S31=J31,"Igual","Diferente")) -> Igual | U31: n/a | V31: N | W31: =IFERROR(VLOOKUP(B31,#REF!,11,0),"n/a") -> n/a | X31: =IFERROR(VLOOKUP(B31,#REF!,8,0),"n/a") -> n/a | Y31: =$G$2 -> GD | Z31: Sem alteração | AA31: =VLOOKUP(Table1[[#This Row],[CONCAT]],'[1]1. Tipologias Testes GD'!$F:$L,7,0) -> Alta | AB31: FLOAT 2 decimal places | AC31: Média | AD31: 0 | AE31: =INDEX(Auxiliar!$D$5:$I$10,MATCH('Lista - Âmbito Projeto GD'!AE$3,Auxiliar!$B$5:$B$10,0),MATCH('Lista - Âmbito Projeto GD'!$AC31,Auxiliar!$D$4:$I$4,0)) -> 3 | AF31: =INDEX(Auxiliar!$D$5:$I$10,MATCH('Lista - Âmbito Projeto GD'!AF$3,Auxiliar!$B$5:$B$10,0),MATCH('Lista - Âmbito Projeto GD'!$AC31,Auxiliar!$D$4:$I$4,0)) -> 3 | AG31: =IF(OR(AB31="Code List",AB31="Y, N"),AC31,"n.a.") -> n.a. | AH31: =INDEX(Auxiliar!$D$5:$I$10,MATCH('Lista - Âmbito Projeto GD'!AH$3,Auxiliar!$B$5:$B$10,0),MATCH('Lista - Âmbito Projeto GD'!$AG31,Auxiliar!$D$4:$I$4,0)) -> 0 | AI31: =INDEX(Auxiliar!$D$5:$I$10,MATCH('Lista - Âmbito Projeto GD'!AI$3,Auxiliar!$B$5:$B$10,0),MATCH('Lista - Âmbito Projeto GD'!$AC31,Auxiliar!$D$4:$I$4,0)) -> 0.5 | AJ31: =INDEX(Auxiliar!$D$5:$I$10,MATCH('Lista - Âmbito Projeto GD'!AJ$3,Auxiliar!$B$5:$B$10,0),MATCH('Lista - Âmbito Projeto GD'!$AC31,Auxiliar!$D$4:$I$4,0)) -> 1 | AK31: =SUM(AF31,AH31:AJ31) -> 4.5
A32: IN.205 | B32: =C32&"_"&D32 -> INSTRUMENT_GNS_FNNCL_TRNSCTN_EXCHNG_DFFRNCS | C32: INSTRUMENT | D32: GNS_FNNCL_TRNSCTN_EXCHNG_DFFRNCS | E32: Gains (Losses) On Financial Transaction (gft) And Exchange Differences, before distribution to SCIB under the Collabotarion Revenues distribution agreement | F32: N | G32: Y | H32: N | I32: N | J32: N | K32: N | L32: =IFERROR(VLOOKUP($B32,'LISTA - Atual'!$B$1:$I$444,5,0),"Novo") -> N | M32: =IF(L32="Novo","Novo Campo",IF(L32=F32,"Igual","Diferente")) -> Igual | N32: =IFERROR(VLOOKUP($B32,'LISTA - Atual'!$B$1:$I$444,6,0),"Novo") -> Y | O32: =IF(N32="Novo","Novo Campo",IF(N32=G32,"Igual","Diferente")) -> Igual | P32: =IFERROR(VLOOKUP($B32,'LISTA - Atual'!$B$1:$I$444,7,0),"Novo") -> N | Q32: =IF(P32="Novo","Novo Campo",IF(P32=H32,"Igual","Diferente")) -> Igual | R32: n/a | S32: =IFERROR(VLOOKUP($B32,'LISTA - Atual'!$B$1:$I$444,8,0),"Novo") -> N | T32: =IF(S32="Novo","Novo Campo",IF(S32=J32,"Igual","Diferente")) -> Igual | U32: n/a | V32: N | W32: =IFERROR(VLOOKUP(B32,#REF!,11,0),"n/a") -> n/a | X32: =IFERROR(VLOOKUP(B32,#REF!,8,0),"n/a") -> n/a | Y32: =$G$2 -> GD | Z32: Sem alteração | AA32: =VLOOKUP(Table1[[#This Row],[CONCAT]],'[1]1. Tipologias Testes GD'!$F:$L,7,0) -> Alta | AB32: FLOAT 2 decimal places | AC32: Média | AD32: 0 | AE32: =INDEX(Auxiliar!$D$5:$I$10,MATCH('Lista - Âmbito Projeto GD'!AE$3,Auxiliar!$B$5:$B$10,0),MATCH('Lista - Âmbito Projeto GD'!$AC32,Auxiliar!$D$4:$I$4,0)) -> 3 | AF32: =INDEX(Auxiliar!$D$5:$I$10,MATCH('Lista - Âmbito Projeto GD'!AF$3,Auxiliar!$B$5:$B$10,0),MATCH('Lista - Âmbito Projeto GD'!$AC32,Auxiliar!$D$4:$I$4,0)) -> 3 | AG32: =IF(OR(AB32="Code List",AB32="Y, N"),AC32,"n.a.") -> n.a. | AH32: =INDEX(Auxiliar!$D$5:$I$10,MATCH('Lista - Âmbito Projeto GD'!AH$3,Auxiliar!$B$5:$B$10,0),MATCH('Lista - Âmbito Projeto GD'!$AG32,Auxiliar!$D$4:$I$4,0)) -> 0 | AI32: =INDEX(Auxiliar!$D$5:$I$10,MATCH('Lista - Âmbito Projeto GD'!AI$3,Auxiliar!$B$5:$B$10,0),MATCH('Lista - Âmbito Projeto GD'!$AC32,Auxiliar!$D$4:$I$4,0)) -> 0.5 | AJ32: =INDEX(Auxiliar!$D$5:$I$10,MATCH('Lista - Âmbito Projeto GD'!AJ$3,Auxiliar!$B$5:$B$10,0),MATCH('Lista - Âmbito Projeto GD'!$AC32,Auxiliar!$D$4:$I$4,0)) -> 1 | AK32: =SUM(AF32,AH32:AJ32) -> 4.5
A33: IN.206 | B33: =C33&"_"&D33 -> INSTRUMENT_FLG_INTRBSNSS | C33: INSTRUMENT | D33: FLG_INTRBSNSS | E33: Flag of interbusiness | F33: N | G33: Y | H33: N | I33: N | J33: N | K33: N | L33: =IFERROR(VLOOKUP($B33,'LISTA - Atual'!$B$1:$I$444,5,0),"Novo") -> N | M33: =IF(L33="Novo","Novo Campo",IF(L33=F33,"Igual","Diferente")) -> Igual | N33: =IFERROR(VLOOKUP($B33,'LISTA - Atual'!$B$1:$I$444,6,0),"Novo") -> Y | O33: =IF(N33="Novo","Novo Campo",IF(N33=G33,"Igual","Diferente")) -> Igual | P33: =IFERROR(VLOOKUP($B33,'LISTA - Atual'!$B$1:$I$444,7,0),"Novo") -> N | Q33: =IF(P33="Novo","Novo Campo",IF(P33=H33,"Igual","Diferente")) -> Igual | R33: n/a | S33: =IFERROR(VLOOKUP($B33,'LISTA - Atual'!$B$1:$I$444,8,0),"Novo") -> N | T33: =IF(S33="Novo","Novo Campo",IF(S33=J33,"Igual","Diferente")) -> Igual | U33: n/a | V33: N | W33: =IFERROR(VLOOKUP(B33,#REF!,11,0),"n/a") -> n/a | X33: =IFERROR(VLOOKUP(B33,#REF!,8,0),"n/a") -> n/a | Y33: =$G$2 -> GD | Z33: Sem alteração | AA33: =VLOOKUP(Table1[[#This Row],[CONCAT]],'[1]1. Tipologias Testes GD'!$F:$L,7,0) -> Baixa | AB33: Y, N | AC33: M. Baixa | AD33: 0 | AE33: =INDEX(Auxiliar!$D$5:$I$10,MATCH('Lista - Âmbito Projeto GD'!AE$3,Auxiliar!$B$5:$B$10,0),MATCH('Lista - Âmbito Projeto GD'!$AC33,Auxiliar!$D$4:$I$4,0)) -> 1 | AF33: =INDEX(Auxiliar!$D$5:$I$10,MATCH('Lista - Âmbito Projeto GD'!AF$3,Auxiliar!$B$5:$B$10,0),MATCH('Lista - Âmbito Projeto GD'!$AC33,Auxiliar!$D$4:$I$4,0)) -> 1 | AG33: =IF(OR(AB33="Code List",AB33="Y, N"),AC33,"n.a.") -> M. Baixa | AH33: =INDEX(Auxiliar!$D$5:$I$10,MATCH('Lista - Âmbito Projeto GD'!AH$3,Auxiliar!$B$5:$B$10,0),MATCH('Lista - Âmbito Projeto GD'!$AG33,Auxiliar!$D$4:$I$4,0)) -> 0.5 | AI33: =INDEX(Auxiliar!$D$5:$I$10,MATCH('Lista - Âmbito Projeto GD'!AI$3,Auxiliar!$B$5:$B$10,0),MATCH('Lista - Âmbito Projeto GD'!$AC33,Auxiliar!$D$4:$I$4,0)) -> 0.5 | AJ33: =INDEX(Auxiliar!$D$5:$I$10,MATCH('Lista - Âmbito Projeto GD'!AJ$3,Auxiliar!$B$5:$B$10,0),MATCH('Lista - Âmbito Projeto GD'!$AC33,Auxiliar!$D$4:$I$4,0)) -> 1 | AK33: =SUM(AF33,AH33:AJ33) -> 3
A34: IN.207 | B34: =C34&"_"&D34 -> INSTRUMENT_INTRBSNSS_ADJ_COD | C34: INSTRUMENT | D34: INTRBSNSS_ADJ_COD | E34: Interbusiness adjustment code | F34: N | G34: Y | H34: N | I34: N | J34: N | K34: N | L34: =IFERROR(VLOOKUP($B34,'LISTA - Atual'!$B$1:$I$444,5,0),"Novo") -> N | M34: =IF(L34="Novo","Novo Campo",IF(L34=F34,"Igual","Diferente")) -> Igual | N34: =IFERROR(VLOOKUP($B34,'LISTA - Atual'!$B$1:$I$444,6,0),"Novo") -> Y | O34: =IF(N34="Novo","Novo Campo",IF(N34=G34,"Igual","Diferente")) -> Igual | P34: =IFERROR(VLOOKUP($B34,'LISTA - Atual'!$B$1:$I$444,7,0),"Novo") -> N | Q34: =IF(P34="Novo","Novo Campo",IF(P34=H34,"Igual","Diferente")) -> Igual | R34: n/a | S34: =IFERROR(VLOOKUP($B34,'LISTA - Atual'!$B$1:$I$444,8,0),"Novo") -> N | T34: =IF(S34="Novo","Novo Campo",IF(S34=J34,"Igual","Diferente")) -> Igual | U34: n/a | V34: N | W34: =IFERROR(VLOOKUP(B34,#REF!,11,0),"n/a") -> n/a | X34: =IFERROR(VLOOKUP(B34,#REF!,8,0),"n/a") -> n/a | Y34: =$G$2 -> GD | Z34: Sem alteração | AA34: =VLOOKUP(Table1[[#This Row],[CONCAT]],'[1]1. Tipologias Testes GD'!$F:$L,7,0) -> Baixa | AB34: Code List | AC34: M. Baixa | AD34: 0 | AE34: =INDEX(Auxiliar!$D$5:$I$10,MATCH('Lista - Âmbito Projeto GD'!AE$3,Auxiliar!$B$5:$B$10,0),MATCH('Lista - Âmbito Projeto GD'!$AC34,Auxiliar!$D$4:$I$4,0)) -> 1 | AF34: =INDEX(Auxiliar!$D$5:$I$10,MATCH('Lista - Âmbito Projeto GD'!AF$3,Auxiliar!$B$5:$B$10,0),MATCH('Lista - Âmbito Projeto GD'!$AC34,Auxiliar!$D$4:$I$4,0)) -> 1 | AG34: =IF(OR(AB34="Code List",AB34="Y, N"),AC34,"n.a.") -> M. Baixa | AH34: =INDEX(Auxiliar!$D$5:$I$10,MATCH('Lista - Âmbito Projeto GD'!AH$3,Auxiliar!$B$5:$B$10,0),MATCH('Lista - Âmbito Projeto GD'!$AG34,Auxiliar!$D$4:$I$4,0)) -> 0.5 | AI34: =INDEX(Auxiliar!$D$5:$I$10,MATCH('Lista - Âmbito Projeto GD'!AI$3,Auxiliar!$B$5:$B$10,0),MATCH('Lista - Âmbito Projeto GD'!$AC34,Auxiliar!$D$4:$I$4,0)) -> 0.5 | AJ34: =INDEX(Auxiliar!$D$5:$I$10,MATCH('Lista - Âmbito Projeto GD'!AJ$3,Auxiliar!$B$5:$B$10,0),MATCH('Lista - Âmbito Projeto GD'!$AC34,Auxiliar!$D$4:$I$4,0)) -> 1 | AK34: =SUM(AF34,AH34:AJ34) -> 3
A35: IN.208 | B35: =C35&"_"&D35 -> INSTRUMENT_COD_SOC_DSTNTN | C35: INSTRUMENT | D35: COD_SOC_DSTNTN | E35: Cargabal identification code of the destination entity | F35: N | G35: Y | H35: N | I35: N | J35: N | K35: N | L35: =IFERROR(VLOOKUP($B35,'LISTA - Atual'!$B$1:$I$444,5,0),"Novo") -> N | M35: =IF(L35="Novo","Novo Campo",IF(L35=F35,"Igual","Diferente")) -> Igual | N35: =IFERROR(VLOOKUP($B35,'LISTA - Atual'!$B$1:$I$444,6,0),"Novo") -> Y | O35: =IF(N35="Novo","Novo Campo",IF(N35=G35,"Igual","Diferente")) -> Igual | P35: =IFERROR(VLOOKUP($B35,'LISTA - Atual'!$B$1:$I$444,7,0),"Novo") -> N | Q35: =IF(P35="Novo","Novo Campo",IF(P35=H35,"Igual","Diferente")) -> Igual | R35: n/a | S35: =IFERROR(VLOOKUP($B35,'LISTA - Atual'!$B$1:$I$444,8,0),"Novo") -> N | T35: =IF(S35="Novo","Novo Campo",IF(S35=J35,"Igual","Diferente")) -> Igual | U35: n/a | V35: N | W35: =IFERROR(VLOOKUP(B35,#REF!,11,0),"n/a") -> n/a | X35: =IFERROR(VLOOKUP(B35,#REF!,8,0),"n/a") -> n/a | Y35: =$G$2 -> GD | Z35: Sem alteração | AA35: =VLOOKUP(Table1[[#This Row],[CONCAT]],'[1]1. Tipologias Testes GD'!$F:$L,7,0) -> Baixa | AB35: VARCHAR2(5) | AC35: M. Baixa | AD35: 0 | AE35: =INDEX(Auxiliar!$D$5:$I$10,MATCH('Lista - Âmbito Projeto GD'!AE$3,Auxiliar!$B$5:$B$10,0),MATCH('Lista - Âmbito Projeto GD'!$AC35,Auxiliar!$D$4:$I$4,0)) -> 1 | AF35: =INDEX(Auxiliar!$D$5:$I$10,MATCH('Lista - Âmbito Projeto GD'!AF$3,Auxiliar!$B$5:$B$10,0),MATCH('Lista - Âmbito Projeto GD'!$AC35,Auxiliar!$D$4:$I$4,0)) -> 1 | AG35: =IF(OR(AB35="Code List",AB35="Y, N"),AC35,"n.a.") -> n.a. | AH35: =INDEX(Auxiliar!$D$5:$I$10,MATCH('Lista - Âmbito Projeto GD'!AH$3,Auxiliar!$B$5:$B$10,0),MATCH('Lista - Âmbito Projeto GD'!$AG35,Auxiliar!$D$4:$I$4,0)) -> 0 | AI35: =INDEX(Auxiliar!$D$5:$I$10,MATCH('Lista - Âmbito Projeto GD'!AI$3,Auxiliar!$B$5:$B$10,0),MATCH('Lista - Âmbito Projeto GD'!$AC35,Auxiliar!$D$4:$I$4,0)) -> 0.5 | AJ35: =INDEX(Auxiliar!$D$5:$I$10,MATCH('Lista - Âmbito Projeto GD'!AJ$3,Auxiliar!$B$5:$B$10,0),MATCH('Lista - Âmbito Projeto GD'!$AC35,Auxiliar!$D$4:$I$4,0)) -> 1 | AK35: =SUM(AF35,AH35:AJ35) -> 2.5
A36: IN.209 | B36: =C36&"_"&D36 -> INSTRUMENT_BSNSS_AREA_DSTNTN | C36: INSTRUMENT | D36: BSNSS_AREA_DSTNTN | E36: Destination Business area | F36: N | G36: Y | H36: N | I36: N | J36: N | K36: N | L36: =IFERROR(VLOOKUP($B36,'LISTA - Atual'!$B$1:$I$444,5,0),"Novo") -> N | M36: =IF(L36="Novo","Novo Campo",IF(L36=F36,"Igual","Diferente")) -> Igual | N36: =IFERROR(VLOOKUP($B36,'LISTA - Atual'!$B$1:$I$444,6,0),"Novo") -> Y | O36: =IF(N36="Novo","Novo Campo",IF(N36=G36,"Igual","Diferente")) -> Igual | P36: =IFERROR(VLOOKUP($B36,'LISTA - Atual'!$B$1:$I$444,7,0),"Novo") -> N | Q36: =IF(P36="Novo","Novo Campo",IF(P36=H36,"Igual","Diferente")) -> Igual | R36: n/a | S36: =IFERROR(VLOOKUP($B36,'LISTA - Atual'!$B$1:$I$444,8,0),"Novo") -> N | T36: =IF(S36="Novo","Novo Campo",IF(S36=J36,"Igual","Diferente")) -> Igual | U36: n/a | V36: N | W36: =IFERROR(VLOOKUP(B36,#REF!,11,0),"n/a") -> n/a | X36: =IFERROR(VLOOKUP(B36,#REF!,8,0),"n/a") -> n/a | Y36: =$G$2 -> GD | Z36: Sem alteração | AA36: =VLOOKUP(Table1[[#This Row],[CONCAT]],'[1]1. Tipologias Testes GD'!$F:$L,7,0) -> Baixa | AB36: Code List | AC36: M. Baixa | AD36: 0 | AE36: =INDEX(Auxiliar!$D$5:$I$10,MATCH('Lista - Âmbito Projeto GD'!AE$3,Auxiliar!$B$5:$B$10,0),MATCH('Lista - Âmbito Projeto GD'!$AC36,Auxiliar!$D$4:$I$4,0)) -> 1 | AF36: =INDEX(Auxiliar!$D$5:$I$10,MATCH('Lista - Âmbito Projeto GD'!AF$3,Auxiliar!$B$5:$B$10,0),MATCH('Lista - Âmbito Projeto GD'!$AC36,Auxiliar!$D$4:$I$4,0)) -> 1 | AG36: =IF(OR(AB36="Code List",AB36="Y, N"),AC36,"n.a.") -> M. Baixa | AH36: =INDEX(Auxiliar!$D$5:$I$10,MATCH('Lista - Âmbito Projeto GD'!AH$3,Auxiliar!$B$5:$B$10,0),MATCH('Lista - Âmbito Projeto GD'!$AG36,Auxiliar!$D$4:$I$4,0)) -> 0.5 | AI36: =INDEX(Auxiliar!$D$5:$I$10,MATCH('Lista - Âmbito Projeto GD'!AI$3,Auxiliar!$B$5:$B$10,0),MATCH('Lista - Âmbito Projeto GD'!$AC36,Auxiliar!$D$4:$I$4,0)) -> 0.5 | AJ36: =INDEX(Auxiliar!$D$5:$I$10,MATCH('Lista - Âmbito Projeto GD'!AJ$3,Auxiliar!$B$5:$B$10,0),MATCH('Lista - Âmbito Projeto GD'!$AC36,Auxiliar!$D$4:$I$4,0)) -> 1 | AK36: =SUM(AF36,AH36:AJ36) -> 3
A37: IN.210 | B37: =C37&"_"&D37 -> INSTRUMENT_AVRG_BLNC_OFF_BLNC | C37: INSTRUMENT | D37: AVRG_BLNC_OFF_BLNC | E37: Average off balance | F37: N | G37: Y | H37: N | I37: N | J37: N | K37: N | L37: =IFERROR(VLOOKUP($B37,'LISTA - Atual'!$B$1:$I$444,5,0),"Novo") -> N | M37: =IF(L37="Novo","Novo Campo",IF(L37=F37,"Igual","Diferente")) -> Igual | N37: =IFERROR(VLOOKUP($B37,'LISTA - Atual'!$B$1:$I$444,6,0),"Novo") -> Y | O37: =IF(N37="Novo","Novo Campo",IF(N37=G37,"Igual","Diferente")) -> Igual | P37: =IFERROR(VLOOKUP($B37,'LISTA - Atual'!$B$1:$I$444,7,0),"Novo") -> N | Q37: =IF(P37="Novo","Novo Campo",IF(P37=H37,"Igual","Diferente")) -> Igual | R37: n/a | S37: =IFERROR(VLOOKUP($B37,'LISTA - Atual'!$B$1:$I$444,8,0),"Novo") -> N | T37: =IF(S37="Novo","Novo Campo",IF(S37=J37,"Igual","Diferente")) -> Igual | U37: n/a | V37: N | W37: =IFERROR(VLOOKUP(B37,#REF!,11,0),"n/a") -> n/a | X37: =IFERROR(VLOOKUP(B37,#REF!,8,0),"n/a") -> n/a | Y37: =$G$2 -> GD | Z37: Sem alteração | AA37: =VLOOKUP(Table1[[#This Row],[CONCAT]],'[1]1. Tipologias Testes GD'!$F:$L,7,0) -> Média | AB37: FLOAT 2 decimal places | AC37: Média | AD37: 0 | AE37: =INDEX(Auxiliar!$D$5:$I$10,MATCH('Lista - Âmbito Projeto GD'!AE$3,Auxiliar!$B$5:$B$10,0),MATCH('Lista - Âmbito Projeto GD'!$AC37,Auxiliar!$D$4:$I$4,0)) -> 3 | AF37: =INDEX(Auxiliar!$D$5:$I$10,MATCH('Lista - Âmbito Projeto GD'!AF$3,Auxiliar!$B$5:$B$10,0),MATCH('Lista - Âmbito Projeto GD'!$AC37,Auxiliar!$D$4:$I$4,0)) -> 3 | AG37: =IF(OR(AB37="Code List",AB37="Y, N"),AC37,"n.a.") -> n.a. | AH37: =INDEX(Auxiliar!$D$5:$I$10,MATCH('Lista - Âmbito Projeto GD'!AH$3,Auxiliar!$B$5:$B$10,0),MATCH('Lista - Âmbito Projeto GD'!$AG37,Auxiliar!$D$4:$I$4,0)) -> 0 | AI37: =INDEX(Auxiliar!$D$5:$I$10,MATCH('Lista - Âmbito Projeto GD'!AI$3,Auxiliar!$B$5:$B$10,0),MATCH('Lista - Âmbito Projeto GD'!$AC37,Auxiliar!$D$4:$I$4,0)) -> 0.5 | AJ37: =INDEX(Auxiliar!$D$5:$I$10,MATCH('Lista - Âmbito Projeto GD'!AJ$3,Auxiliar!$B$5:$B$10,0),MATCH('Lista - Âmbito Projeto GD'!$AC37,Auxiliar!$D$4:$I$4,0)) -> 1 | AK37: =SUM(AF37,AH37:AJ37) -> 4.5
A38: IN.211 | B38: =C38&"_"&D38 -> INSTRUMENT_INTRNL_TRNSFR_RT_OFF_BLNC | C38: INSTRUMENT | D38: INTRNL_TRNSFR_RT_OFF_BLNC | E38: Internal transfer rate due to off balance amounts | F38: N | G38: Y | H38: N | I38: N | J38: N | K38: N | L38: =IFERROR(VLOOKUP($B38,'LISTA - Atual'!$B$1:$I$444,5,0),"Novo") -> N | M38: =IF(L38="Novo","Novo Campo",IF(L38=F38,"Igual","Diferente")) -> Igual | N38: =IFERROR(VLOOKUP($B38,'LISTA - Atual'!$B$1:$I$444,6,0),"Novo") -> Y | O38: =IF(N38="Novo","Novo Campo",IF(N38=G38,"Igual","Diferente")) -> Igual | P38: =IFERROR(VLOOKUP($B38,'LISTA - Atual'!$B$1:$I$444,7,0),"Novo") -> N | Q38: =IF(P38="Novo","Novo Campo",IF(P38=H38,"Igual","Diferente")) -> Igual | R38: n/a | S38: =IFERROR(VLOOKUP($B38,'LISTA - Atual'!$B$1:$I$444,8,0),"Novo") -> N | T38: =IF(S38="Novo","Novo Campo",IF(S38=J38,"Igual","Diferente")) -> Igual | U38: n/a | V38: N | W38: =IFERROR(VLOOKUP(B38,#REF!,11,0),"n/a") -> n/a | X38: =IFERROR(VLOOKUP(B38,#REF!,8,0),"n/a") -> n/a | Y38: =$G$2 -> GD | Z38: Sem alteração | AA38: =VLOOKUP(Table1[[#This Row],[CONCAT]],'[1]1. Tipologias Testes GD'!$F:$L,7,0) -> Baixa | AB38: FLOAT 2 decimal places | AC38: M. Baixa | AD38: 0 | AE38: =INDEX(Auxiliar!$D$5:$I$10,MATCH('Lista - Âmbito Projeto GD'!AE$3,Auxiliar!$B$5:$B$10,0),MATCH('Lista - Âmbito Projeto GD'!$AC38,Auxiliar!$D$4:$I$4,0)) -> 1 | AF38: =INDEX(Auxiliar!$D$5:$I$10,MATCH('Lista - Âmbito Projeto GD'!AF$3,Auxiliar!$B$5:$B$10,0),MATCH('Lista - Âmbito Projeto GD'!$AC38,Auxiliar!$D$4:$I$4,0)) -> 1 | AG38: =IF(OR(AB38="Code List",AB38="Y, N"),AC38,"n.a.") -> n.a. | AH38: =INDEX(Auxiliar!$D$5:$I$10,MATCH('Lista - Âmbito Projeto GD'!AH$3,Auxiliar!$B$5:$B$10,0),MATCH('Lista - Âmbito Projeto GD'!$AG38,Auxiliar!$D$4:$I$4,0)) -> 0 | AI38: =INDEX(Auxiliar!$D$5:$I$10,MATCH('Lista - Âmbito Projeto GD'!AI$3,Auxiliar!$B$5:$B$10,0),MATCH('Lista - Âmbito Projeto GD'!$AC38,Auxiliar!$D$4:$I$4,0)) -> 0.5 | AJ38: =INDEX(Auxiliar!$D$5:$I$10,MATCH('Lista - Âmbito Projeto GD'!AJ$3,Auxiliar!$B$5:$B$10,0),MATCH('Lista - Âmbito Projeto GD'!$AC38,Auxiliar!$D$4:$I$4,0)) -> 1 | AK38: =SUM(AF38,AH38:AJ38) -> 2.5
A39: IN.212 | B39: =C39&"_"&D39 -> INSTRUMENT_GRSS_CMMSSN_INCM_OFF_BLNC | C39: INSTRUMENT | D39: GRSS_CMMSSN_INCM_OFF_BLNC | E39: Gross fee and commission income corresponding to off balance product before distribution to SCIB under the Collabotarion Revenues distribution agreement | F39: N | G39: Y | H39: Y | I39: N | J39: N | K39: N | L39: =IFERROR(VLOOKUP($B39,'LISTA - Atual'!$B$1:$I$444,5,0),"Novo") -> N | M39: =IF(L39="Novo","Novo Campo",IF(L39=F39,"Igual","Diferente")) -> Igual | N39: =IFERROR(VLOOKUP($B39,'LISTA - Atual'!$B$1:$I$444,6,0),"Novo") -> Y | O39: =IF(N39="Novo","Novo Campo",IF(N39=G39,"Igual","Diferente")) -> Igual | P39: =IFERROR(VLOOKUP($B39,'LISTA - Atual'!$B$1:$I$444,7,0),"Novo") -> Y | Q39: =IF(P39="Novo","Novo Campo",IF(P39=H39,"Igual","Diferente")) -> Igual | R39: n/a | S39: =IFERROR(VLOOKUP($B39,'LISTA - Atual'!$B$1:$I$444,8,0),"Novo") -> N | T39: =IF(S39="Novo","Novo Campo",IF(S39=J39,"Igual","Diferente")) -> Igual | U39: n/a | V39: N | W39: =IFERROR(VLOOKUP(B39,#REF!,11,0),"n/a") -> n/a | X39: =IFERROR(VLOOKUP(B39,#REF!,8,0),"n/a") -> n/a | Y39: =$G$2&$Y$1&$H$2 -> GD & PILAR3 | Z39: Sem alteração | AA39: =VLOOKUP(Table1[[#This Row],[CONCAT]],'[1]1. Tipologias Testes GD'!$F:$L,7,0) -> Alta | AB39: FLOAT 2 decimal places | AC39: Alta | AD39: 0 | AE39: =INDEX(Auxiliar!$D$5:$I$10,MATCH('Lista - Âmbito Projeto GD'!AE$3,Auxiliar!$B$5:$B$10,0),MATCH('Lista - Âmbito Projeto GD'!$AC39,Auxiliar!$D$4:$I$4,0)) -> 6 | AF39: =INDEX(Auxiliar!$D$5:$I$10,MATCH('Lista - Âmbito Projeto GD'!AF$3,Auxiliar!$B$5:$B$10,0),MATCH('Lista - Âmbito Projeto GD'!$AC39,Auxiliar!$D$4:$I$4,0)) -> 6 | AG39: =IF(OR(AB39="Code List",AB39="Y, N"),AC39,"n.a.") -> n.a. | AH39: =INDEX(Auxiliar!$D$5:$I$10,MATCH('Lista - Âmbito Projeto GD'!AH$3,Auxiliar!$B$5:$B$10,0),MATCH('Lista - Âmbito Projeto GD'!$AG39,Auxiliar!$D$4:$I$4,0)) -> 0 | AI39: =INDEX(Auxiliar!$D$5:$I$10,MATCH('Lista - Âmbito Projeto GD'!AI$3,Auxiliar!$B$5:$B$10,0),MATCH('Lista - Âmbito Projeto GD'!$AC39,Auxiliar!$D$4:$I$4,0)) -> 0.5 | AJ39: =INDEX(Auxiliar!$D$5:$I$10,MATCH('Lista - Âmbito Projeto GD'!AJ$3,Auxiliar!$B$5:$B$10,0),MATCH('Lista - Âmbito Projeto GD'!$AC39,Auxiliar!$D$4:$I$4,0)) -> 1 | AK39: =SUM(AF39,AH39:AJ39) -> 7.5
A40: IN.213 | B40: =C40&"_"&D40 -> INSTRUMENT_GRSS_CMMSSN_EXPNS_OFF_BLNC | C40: INSTRUMENT | D40: GRSS_CMMSSN_EXPNS_OFF_BLNC | E40: Gross fee and commission expense corresponding to off balance product before distribution to SCIB under the Collabotarion Revenues distribution agreement | F40: N | G40: Y | H40: N | I40: N | J40: N | K40: N | L40: =IFERROR(VLOOKUP($B40,'LISTA - Atual'!$B$1:$I$444,5,0),"Novo") -> N | M40: =IF(L40="Novo","Novo Campo",IF(L40=F40,"Igual","Diferente")) -> Igual | N40: =IFERROR(VLOOKUP($B40,'LISTA - Atual'!$B$1:$I$444,6,0),"Novo") -> Y | O40: =IF(N40="Novo","Novo Campo",IF(N40=G40,"Igual","Diferente")) -> Igual | P40: =IFERROR(VLOOKUP($B40,'LISTA - Atual'!$B$1:$I$444,7,0),"Novo") -> N | Q40: =IF(P40="Novo","Novo Campo",IF(P40=H40,"Igual","Diferente")) -> Igual | R40: n/a | S40: =IFERROR(VLOOKUP($B40,'LISTA - Atual'!$B$1:$I$444,8,0),"Novo") -> N | T40: =IF(S40="Novo","Novo Campo",IF(S40=J40,"Igual","Diferente")) -> Igual | U40: n/a | V40: N | W40: =IFERROR(VLOOKUP(B40,#REF!,11,0),"n/a") -> n/a | X40: =IFERROR(VLOOKUP(B40,#REF!,8,0),"n/a") -> n/a | Y40: =$G$2 -> GD | Z40: Sem alteração | AA40: =VLOOKUP(Table1[[#This Row],[CONCAT]],'[1]1. Tipologias Testes GD'!$F:$L,7,0) -> Alta | AB40: FLOAT 2 decimal places | AC40: Média | AD40: 0 | AE40: =INDEX(Auxiliar!$D$5:$I$10,MATCH('Lista - Âmbito Projeto GD'!AE$3,Auxiliar!$B$5:$B$10,0),MATCH('Lista - Âmbito Projeto GD'!$AC40,Auxiliar!$D$4:$I$4,0)) -> 3 | AF40: =INDEX(Auxiliar!$D$5:$I$10,MATCH('Lista - Âmbito Projeto GD'!AF$3,Auxiliar!$B$5:$B$10,0),MATCH('Lista - Âmbito Projeto GD'!$AC40,Auxiliar!$D$4:$I$4,0)) -> 3 | AG40: =IF(OR(AB40="Code List",AB40="Y, N"),AC40,"n.a.") -> n.a. | AH40: =INDEX(Auxiliar!$D$5:$I$10,MATCH('Lista - Âmbito Projeto GD'!AH$3,Auxiliar!$B$5:$B$10,0),MATCH('Lista - Âmbito Projeto GD'!$AG40,Auxiliar!$D$4:$I$4,0)) -> 0 | AI40: =INDEX(Auxiliar!$D$5:$I$10,MATCH('Lista - Âmbito Projeto GD'!AI$3,Auxiliar!$B$5:$B$10,0),MATCH('Lista - Âmbito Projeto GD'!$AC40,Auxiliar!$D$4:$I$4,0)) -> 0.5 | AJ40: =INDEX(Auxiliar!$D$5:$I$10,MATCH('Lista - Âmbito Projeto GD'!AJ$3,Auxiliar!$B$5:$B$10,0),MATCH('Lista - Âmbito Projeto GD'!$AC40,Auxiliar!$D$4:$I$4,0)) -> 1 | AK40: =SUM(AF40,AH40:AJ40) -> 4.5
A41: IN.214 | B41: =C41&"_"&D41 -> INSTRUMENT_RWA_OFF_BLNC | C41: INSTRUMENT | D41: RWA_OFF_BLNC | E41: RWA Off Balance | F41: N | G41: Y | H41: N | I41: N | J41: N | K41: N | L41: =IFERROR(VLOOKUP($B41,'LISTA - Atual'!$B$1:$I$444,5,0),"Novo") -> N | M41: =IF(L41="Novo","Novo Campo",IF(L41=F41,"Igual","Diferente")) -> Igual | N41: =IFERROR(VLOOKUP($B41,'LISTA - Atual'!$B$1:$I$444,6,0),"Novo") -> Y | O41: =IF(N41="Novo","Novo Campo",IF(N41=G41,"Igual","Diferente")) -> Igual | P41: =IFERROR(VLOOKUP($B41,'LISTA - Atual'!$B$1:$I$444,7,0),"Novo") -> N | Q41: =IF(P41="Novo","Novo Campo",IF(P41=H41,"Igual","Diferente")) -> Igual | R41: n/a | S41: =IFERROR(VLOOKUP($B41,'LISTA - Atual'!$B$1:$I$444,8,0),"Novo") -> N | T41: =IF(S41="Novo","Novo Campo",IF(S41=J41,"Igual","Diferente")) -> Igual | U41: n/a | V41: N | W41: =IFERROR(VLOOKUP(B41,#REF!,11,0),"n/a") -> n/a | X41: =IFERROR(VLOOKUP(B41,#REF!,8,0),"n/a") -> n/a | Y41: =$G$2 -> GD | Z41: Sem alteração | AA41: =VLOOKUP(Table1[[#This Row],[CONCAT]],'[1]1. Tipologias Testes GD'!$F:$L,7,0) -> Baixa | AB41: FLOAT 2 decimal places | AC41: M. Baixa | AD41: 0 | AE41: =INDEX(Auxiliar!$D$5:$I$10,MATCH('Lista - Âmbito Projeto GD'!AE$3,Auxiliar!$B$5:$B$10,0),MATCH('Lista - Âmbito Projeto GD'!$AC41,Auxiliar!$D$4:$I$4,0)) -> 1 | AF41: =INDEX(Auxiliar!$D$5:$I$10,MATCH('Lista - Âmbito Projeto GD'!AF$3,Auxiliar!$B$5:$B$10,0),MATCH('Lista - Âmbito Projeto GD'!$AC41,Auxiliar!$D$4:$I$4,0)) -> 1 | AG41: =IF(OR(AB41="Code List",AB41="Y, N"),AC41,"n.a.") -> n.a. | AH41: =INDEX(Auxiliar!$D$5:$I$10,MATCH('Lista - Âmbito Projeto GD'!AH$3,Auxiliar!$B$5:$B$10,0),MATCH('Lista - Âmbito Projeto GD'!$AG41,Auxiliar!$D$4:$I$4,0)) -> 0 | AI41: =INDEX(Auxiliar!$D$5:$I$10,MATCH('Lista - Âmbito Projeto GD'!AI$3,Auxiliar!$B$5:$B$10,0),MATCH('Lista - Âmbito Projeto GD'!$AC41,Auxiliar!$D$4:$I$4,0)) -> 0.5 | AJ41: =INDEX(Auxiliar!$D$5:$I$10,MATCH('Lista - Âmbito Projeto GD'!AJ$3,Auxiliar!$B$5:$B$10,0),MATCH('Lista - Âmbito Projeto GD'!$AC41,Auxiliar!$D$4:$I$4,0)) -> 1 | AK41: =SUM(AF41,AH41:AJ41) -> 2.5
A42: IN.215 | B42: =C42&"_"&D42 -> INSTRUMENT_GRSS_INTRST_EXPNS | C42: INSTRUMENT | D42: GRSS_INTRST_EXPNS | E42: Gross Interest expense before distribution to SCIB under the Collabotarion Revenues distribution agreement | F42: N | G42: Y | H42: N | I42: N | J42: N | K42: N | L42: =IFERROR(VLOOKUP($B42,'LISTA - Atual'!$B$1:$I$444,5,0),"Novo") -> N | M42: =IF(L42="Novo","Novo Campo",IF(L42=F42,"Igual","Diferente")) -> Igual | N42: =IFERROR(VLOOKUP($B42,'LISTA - Atual'!$B$1:$I$444,6,0),"Novo") -> Y | O42: =IF(N42="Novo","Novo Campo",IF(N42=G42,"Igual","Diferente")) -> Igual | P42: =IFERROR(VLOOKUP($B42,'LISTA - Atual'!$B$1:$I$444,7,0),"Novo") -> N | Q42: =IF(P42="Novo","Novo Campo",IF(P42=H42,"Igual","Diferente")) -> Igual | R42: n/a | S42: =IFERROR(VLOOKUP($B42,'LISTA - Atual'!$B$1:$I$444,8,0),"Novo") -> N | T42: =IF(S42="Novo","Novo Campo",IF(S42=J42,"Igual","Diferente")) -> Igual | U42: n/a | V42: N | W42: =IFERROR(VLOOKUP(B42,#REF!,11,0),"n/a") -> n/a | X42: =IFERROR(VLOOKUP(B42,#REF!,8,0),"n/a") -> n/a | Y42: =$G$2 -> GD | Z42: Sem alteração | AA42: =VLOOKUP(Table1[[#This Row],[CONCAT]],'[1]1. Tipologias Testes GD'!$F:$L,7,0) -> Alta | AB42: FLOAT 2 decimal places | AC42: Média | AD42: 0 | AE42: =INDEX(Auxiliar!$D$5:$I$10,MATCH('Lista - Âmbito Projeto GD'!AE$3,Auxiliar!$B$5:$B$10,0),MATCH('Lista - Âmbito Projeto GD'!$AC42,Auxiliar!$D$4:$I$4,0)) -> 3 | AF42: =INDEX(Auxiliar!$D$5:$I$10,MATCH('Lista - Âmbito Projeto GD'!AF$3,Auxiliar!$B$5:$B$10,0),MATCH('Lista - Âmbito Projeto GD'!$AC42,Auxiliar!$D$4:$I$4,0)) -> 3 | AG42: =IF(OR(AB42="Code List",AB42="Y, N"),AC42,"n.a.") -> n.a. | AH42: =INDEX(Auxiliar!$D$5:$I$10,MATCH('Lista - Âmbito Projeto GD'!AH$3,Auxiliar!$B$5:$B$10,0),MATCH('Lista - Âmbito Projeto GD'!$AG42,Auxiliar!$D$4:$I$4,0)) -> 0 | AI42: =INDEX(Auxiliar!$D$5:$I$10,MATCH('Lista - Âmbito Projeto GD'!AI$3,Auxiliar!$B$5:$B$10,0),MATCH('Lista - Âmbito Projeto GD'!$AC42,Auxiliar!$D$4:$I$4,0)) -> 0.5 | AJ42: =INDEX(Auxiliar!$D$5:$I$10,MATCH('Lista - Âmbito Projeto GD'!AJ$3,Auxiliar!$B$5:$B$10,0),MATCH('Lista - Âmbito Projeto GD'!$AC42,Auxiliar!$D$4:$I$4,0)) -> 1 | AK42: =SUM(AF42,AH42:AJ42) -> 4.5
A43: IN.216 | B43: =C43&"_"&D43 -> INSTRUMENT_NT_LN_LSS_PRVSN_OFF_BLNC | C43: INSTRUMENT | D43: NT_LN_LSS_PRVSN_OFF_BLNC | E43: Net loan-loss provisions corresponding to off balance exposures | F43: N | G43: Y | H43: N | I43: N | J43: N | K43: N | L43: =IFERROR(VLOOKUP($B43,'LISTA - Atual'!$B$1:$I$444,5,0),"Novo") -> N | M43: =IF(L43="Novo","Novo Campo",IF(L43=F43,"Igual","Diferente")) -> Igual | N43: =IFERROR(VLOOKUP($B43,'LISTA - Atual'!$B$1:$I$444,6,0),"Novo") -> Y | O43: =IF(N43="Novo","Novo Campo",IF(N43=G43,"Igual","Diferente")) -> Igual | P43: =IFERROR(VLOOKUP($B43,'LISTA - Atual'!$B$1:$I$444,7,0),"Novo") -> N | Q43: =IF(P43="Novo","Novo Campo",IF(P43=H43,"Igual","Diferente")) -> Igual | R43: n/a | S43: =IFERROR(VLOOKUP($B43,'LISTA - Atual'!$B$1:$I$444,8,0),"Novo") -> N | T43: =IF(S43="Novo","Novo Campo",IF(S43=J43,"Igual","Diferente")) -> Igual | U43: n/a | V43: N | W43: =IFERROR(VLOOKUP(B43,#REF!,11,0),"n/a") -> n/a | X43: =IFERROR(VLOOKUP(B43,#REF!,8,0),"n/a") -> n/a | Y43: =$G$2 -> GD | Z43: Sem alteração | AA43: =VLOOKUP(Table1[[#This Row],[CONCAT]],'[1]1. Tipologias Testes GD'!$F:$L,7,0) -> Média | AB43: FLOAT 2 decimal places | AC43: Média | AD43: 0 | AE43: =INDEX(Auxiliar!$D$5:$I$10,MATCH('Lista - Âmbito Projeto GD'!AE$3,Auxiliar!$B$5:$B$10,0),MATCH('Lista - Âmbito Projeto GD'!$AC43,Auxiliar!$D$4:$I$4,0)) -> 3 | AF43: =INDEX(Auxiliar!$D$5:$I$10,MATCH('Lista - Âmbito Projeto GD'!AF$3,Auxiliar!$B$5:$B$10,0),MATCH('Lista - Âmbito Projeto GD'!$AC43,Auxiliar!$D$4:$I$4,0)) -> 3 | AG43: =IF(OR(AB43="Code List",AB43="Y, N"),AC43,"n.a.") -> n.a. | AH43: =INDEX(Auxiliar!$D$5:$I$10,MATCH('Lista - Âmbito Projeto GD'!AH$3,Auxiliar!$B$5:$B$10,0),MATCH('Lista - Âmbito Projeto GD'!$AG43,Auxiliar!$D$4:$I$4,0)) -> 0 | AI43: =INDEX(Auxiliar!$D$5:$I$10,MATCH('Lista - Âmbito Projeto GD'!AI$3,Auxiliar!$B$5:$B$10,0),MATCH('Lista - Âmbito Projeto GD'!$AC43,Auxiliar!$D$4:$I$4,0)) -> 0.5 | AJ43: =INDEX(Auxiliar!$D$5:$I$10,MATCH('Lista - Âmbito Projeto GD'!AJ$3,Auxiliar!$B$5:$B$10,0),MATCH('Lista - Âmbito Projeto GD'!$AC43,Auxiliar!$D$4:$I$4,0)) -> 1 | AK43: =SUM(AF43,AH43:AJ43) -> 4.5
A44: IN.217 | B44: =C44&"_"&D44 -> INSTRUMENT_GRSS_INTRST_INCM_CCRR | C44: INSTRUMENT | D44: GRSS_INTRST_INCM_CCRR | E44: Gross Interest income distributed to SCIB under the Collabotarion Revenues distribution agreement | F44: N | G44: Y | H44: N | I44: N | J44: N | K44: N | L44: =IFERROR(VLOOKUP($B44,'LISTA - Atual'!$B$1:$I$444,5,0),"Novo") -> N | M44: =IF(L44="Novo","Novo Campo",IF(L44=F44,"Igual","Diferente")) -> Igual | N44: =IFERROR(VLOOKUP($B44,'LISTA - Atual'!$B$1:$I$444,6,0),"Novo") -> Y | O44: =IF(N44="Novo","Novo Campo",IF(N44=G44,"Igual","Diferente")) -> Igual | P44: =IFERROR(VLOOKUP($B44,'LISTA - Atual'!$B$1:$I$444,7,0),"Novo") -> N | Q44: =IF(P44="Novo","Novo Campo",IF(P44=H44,"Igual","Diferente")) -> Igual | R44: n/a | S44: =IFERROR(VLOOKUP($B44,'LISTA - Atual'!$B$1:$I$444,8,0),"Novo") -> N | T44: =IF(S44="Novo","Novo Campo",IF(S44=J44,"Igual","Diferente")) -> Igual | U44: n/a | V44: N | W44: =IFERROR(VLOOKUP(B44,#REF!,11,0),"n/a") -> n/a | X44: =IFERROR(VLOOKUP(B44,#REF!,8,0),"n/a") -> n/a | Y44: =$G$2 -> GD | Z44: Sem alteração | AA44: =VLOOKUP(Table1[[#This Row],[CONCAT]],'[1]1. Tipologias Testes GD'!$F:$L,7,0) -> Baixa | AB44: FLOAT 2 decimal places | AC44: Média | AD44: 0 | AE44: =INDEX(Auxiliar!$D$5:$I$10,MATCH('Lista - Âmbito Projeto GD'!AE$3,Auxiliar!$B$5:$B$10,0),MATCH('Lista - Âmbito Projeto GD'!$AC44,Auxiliar!$D$4:$I$4,0)) -> 3 | AF44: =INDEX(Auxiliar!$D$5:$I$10,MATCH('Lista - Âmbito Projeto GD'!AF$3,Auxiliar!$B$5:$B$10,0),MATCH('Lista - Âmbito Projeto GD'!$AC44,Auxiliar!$D$4:$I$4,0)) -> 3 | AG44: =IF(OR(AB44="Code List",AB44="Y, N"),AC44,"n.a.") -> n.a. | AH44: =INDEX(Auxiliar!$D$5:$I$10,MATCH('Lista - Âmbito Projeto GD'!AH$3,Auxiliar!$B$5:$B$10,0),MATCH('Lista - Âmbito Projeto GD'!$AG44,Auxiliar!$D$4:$I$4,0)) -> 0 | AI44: =INDEX(Auxiliar!$D$5:$I$10,MATCH('Lista - Âmbito Projeto GD'!AI$3,Auxiliar!$B$5:$B$10,0),MATCH('Lista - Âmbito Projeto GD'!$AC44,Auxiliar!$D$4:$I$4,0)) -> 0.5 | AJ44: =INDEX(Auxiliar!$D$5:$I$10,MATCH('Lista - Âmbito Projeto GD'!AJ$3,Auxiliar!$B$5:$B$10,0),MATCH('Lista - Âmbito Projeto GD'!$AC44,Auxiliar!$D$4:$I$4,0)) -> 1 | AK44: =SUM(AF44,AH44:AJ44) -> 4.5
