Workbook

Sheet FLG_ELCTRC_VHCL
B2: 1) Registos que apresentam campo combustivel a vazio para data de referência = '2024-12-31'
B4: Tabela gt013_bens_mob | D4: TAT L79
B5: combustivel | C5: tipo_eqp | D5: Descritivo | E5: # Registos
C6: 151 | D6: TRACTOR,TRACTOR BASCULANTE,DUMPERS | E6: 57
C7: 144 | D7: VEICULOS PESADOS DE MERCADORIAS | E7: 35
C8: 31 | D8: EQUIPAMENTO ESCAVACAO E TERRAPLANAGEM | E8: 284
C9: 24 | D9: MAQ. IND. PAPEL, CARTAO E ARTES GRAFICA | E9: 104
C10: 29 | D10: MAQ. IND. METALOMECANICA | E10: 205
C11: 17 | D11: MAQ. IND. ALIMENTAR (S/SEGURO) | E11: 3
C12: 143 | D12: VEICULOS PESADOS DE PASSAGEIROS | E12: 32
C13: 32 | D13: EQUIPAMENTO DE ELEVACAO E TRANSPORTE | E13: 232
C14: 52 | D14: MOBILIÁRIO | E14: 89
C15: 400 | D15: EQUIPAMENTO DIVERSO (MULTIRISCOS) | E15: 7
C16: 10 | D16: EQUIPAMENTO P/ AGRICULTURA E PESCA | E16: 198
C17: 12 | D17: COLHEITA | E17: 1
... C81: 70 | D81: EQUIPAMENTOS DIVERSOS | E81: 22
B82: # Total de registos | E82: =+SUM(E6:E81) -> 5650

Sheet análise FC
B2: tipo_eqp | C2: tayd91c0_gelemtab | D2: # Registos | E2: Equipamento/viatura? | F2: Código Corporativo
B3: 251 | C3: VEICULOS LIGEIROS DE PASSAGEIROS | D3: 6 | E3: =VLOOKUP(B3,'TAT L79'!$B$2:$F$221,3,FALSE) -> VIATURA | F3: {=INDEX('[1]2. Mapeamento a validar'!$B$6:$E$233,MATCH(C3,'[1]2. Mapeamento a validar'!$E$6:$E$233,0),1)} -> VEH01
B4: 121 | C4: EMBARCACOES | D4: 7 | E4: =VLOOKUP(B4,'TAT L79'!$B$2:$F$221,3,FALSE) -> VIATURA | F4: {=INDEX('[1]2. Mapeamento a validar'!$B$6:$E$233,MATCH(C4,'[1]2. Mapeamento a validar'!$E$6:$E$233,0),1)} -> N/A
B5: 152 | C5: EMPILHADOR | D5: 28 | E5: =VLOOKUP(B5,'TAT L79'!$B$2:$F$221,3,FALSE) -> VIATURA | F5: {=INDEX('[1]2. Mapeamento a validar'!$B$6:$E$233,MATCH(C5,'[1]2. Mapeamento a validar'!$E$6:$E$233,0),1)} -> VEH18
B6: 71 | C6: SERVIÇOS AUTO | D6: 93 | E6: =VLOOKUP(B6,'TAT L79'!$B$2:$F$221,3,FALSE) -> EQUIPAMENTO | F6: {=INDEX('[1]2. Mapeamento a validar'!$B$6:$E$233,MATCH(C6,'[1]2. Mapeamento a validar'!$E$6:$E$233,0),1)} -> N/A
B7: 30 | C7: EQUIPAMENTO PARA CONSTRUCAO CIVIL | D7: 93 | E7: =VLOOKUP(B7,'TAT L79'!$B$2:$F$221,3,FALSE) -> EQUIPAMENTO | F7: {=INDEX('[1]2. Mapeamento a validar'!$B$6:$E$233,MATCH(C7,'[1]2. Mapeamento a validar'!$E$6:$E$233,0),1)} -> N/A
B8: 360 | C8: EQUIPAMENTO PARA SERVIÇOS AUTO | D8: 35 | E8: =VLOOKUP(B8,'TAT L79'!$B$2:$F$221,3,FALSE) -> EQUIPAMENTO | F8: {=INDEX('[1]2. Mapeamento a validar'!$B$6:$E$233,MATCH(C8,'[1]2. Mapeamento a validar'!$E$6:$E$233,0),1)} -> N/A
B9: 32 | C9: EQUIPAMENTO DE ELEVACAO E TRANSPORTE | D9: 232 | E9: =VLOOKUP(B9,'TAT L79'!$B$2:$F$221,3,FALSE) -> EQUIPAMENTO | F9: {=INDEX('[1]2. Mapeamento a validar'!$B$6:$E$233,MATCH(C9,'[1]2. Mapeamento a validar'!$E$6:$E$233,0),1)} -> N/A
B10: 20 | C10: EQUIPAMENTO P/ INDUSTRIA TRANSFORMADORA | D10: 91 | E10: =VLOOKUP(B10,'TAT L79'!$B$2:$F$221,3,FALSE) -> EQUIPAMENTO | F10: {=INDEX('[1]2. Mapeamento a validar'!$B$6:$E$233,MATCH(C10,'[1]2. Mapeamento a validar'!$E$6:$E$233,0),1)} -> N/A
B11: 31 | C11: EQUIPAMENTO ESCAVACAO E TERRAPLANAGEM | D11: 284 | E11: =VLOOKUP(B11,'TAT L79'!$B$2:$F$221,3,FALSE) -> EQUIPAMENTO | F11: {=INDEX('[1]2. Mapeamento a validar'!$B$6:$E$233,MATCH(C11,'[1]2. Mapeamento a validar'!$E$6:$E$233,0),1)} -> N/A
B12: 51 | C12: INFORMÁTICA | D12: 32 | E12: =VLOOKUP(B12,'TAT L79'!$B$2:$F$221,3,FALSE) -> EQUIPAMENTO | F12: {=INDEX('[1]2. Mapeamento a validar'!$B$6:$E$233,MATCH(C12,'[1]2. Mapeamento a validar'!$E$6:$E$233,0),1)} -> N/A
B13: 130 | C13: AEREO | D13: 4 | E13: =VLOOKUP(B13,'TAT L79'!$B$2:$F$221,3,FALSE) -> VIATURA | F13: {=INDEX('[1]2. Mapeamento a validar'!$B$6:$E$233,MATCH(C13,'[1]2. Mapeamento a validar'!$E$6:$E$233,0),1)} -> N/A
B14: 60 | C14: EQUIPAMENTO SERVIÇOS DE SAUDE | D14: 605 | E14: =VLOOKUP(B14,'TAT L79'!$B$2:$F$221,3,FALSE) -> EQUIPAMENTO | F14: {=INDEX('[1]2. Mapeamento a validar'!$B$6:$E$233,MATCH(C14,'[1]2. Mapeamento a validar'!$E$6:$E$233,0),1)} -> N/A
... B78: 223 | C78: PLANTAFORMA ELEVATORIA | D78: 5 | E78: =VLOOKUP(B78,'TAT L79'!$B$2:$F$221,3,FALSE) -> VIATURA | F78: {=INDEX('[1]2. Mapeamento a validar'!$B$6:$E$233,MATCH(C78,'[1]2. Mapeamento a validar'!$E$6:$E$233,0),1)} -> VEH20
B79: Total | D79: =SUBTOTAL(9,D3:D78) -> 303

Sheet TAT L79
B2: celemtab | C2: gelemtab | D2: Nelemc01 | E2: Nelemc02 | F2: Nelemc03
B3: 10 | C3: EQUIPAMENTO P/ AGRICULTURA E PESCA | D3: EQUIPAMENTO | E3: 101
B4: 11 | C4: SEMEAR E TRATAR | D4: EQUIPAMENTO | E4: 101
B5: 12 | C5: COLHEITA | D5: EQUIPAMENTO | E5: 101
B6: 13 | C6: REGA | D6: EQUIPAMENTO | E6: 101
B7: 14 | C7: TRANSPORTE S/ MATRICULA | D7: VIATURA | E7: 204
B8: 15 | C8: EQ.AGRICOLA C/ MATRICULA | D8: VIATURA | E8: 201
B9: 17 | C9: MAQ. IND. ALIMENTAR (S/SEGURO) | D9: EQUIPAMENTO | E9: 110
B10: 18 | C10: PESCA | D10: EQUIPAMENTO | E10: 113
B11: 19 | C11: INST. HIDRAULICAS E DE TRATAMENTO AGUAS | D11: EQUIPAMENTO | E11: 105
B12: 20 | C12: EQUIPAMENTO P/ INDUSTRIA TRANSFORMADORA | D12: EQUIPAMENTO | E12: 110
B13: 21 | C13: MAQ. IND. ALIMENTAR | D13: EQUIPAMENTO | E13: 110
B14: 22 | C14: MAQ. IND. TEXTIL, COURO E CALCADO | D14: EQUIPAMENTO | E14: 110
... B221: 999 | C221: OUTROS BAPOP | D221: EQUIPAMENTO | E221: 109
