Workbook
Name asefadf: #REF!
Name bn: #REF!

Sheet 1. Status Resumo
B6: Sumário Executivo | 02/jan a 09/jan
B8: - Inicio do assessment aos campos previamente definidos pela Deloitte. - Início da atualização da documentação (word e excel) com a proposta de especificação to-be.
B13: 1. Assesment | G13: Bens Imóveis - Input | H13: Bens Imóveis - Output | I13: Modelo Verde - Input | J13: Modelo Verde - Output | K13: Pilar III
C16: Resumo | H16: Status (campos) | K16: 45665 | L16: % | N16: Highlights
H17: 0. Cancelado | K17: 3 | L17: =K17/$K$23 -> 0.078947368 | N17: Dos 38 campos em âmbito do Assessment inicial, temos: • 3 campos cancelados: - LG_INSTRMNT_CNCLLD: passou a chamar-se CNCLLD_INSTRMNT_STTS e deixou de ser um campo de sim/não e passou a ser uma code list; - SSTNBL_INDCTR: campo continua a existir mas mudou de tabela (passou da lt002_instrument para a lt007_instr_activity); - SSTNBL_CTGRY: campo continua a existir mas mudou de tabela (passou da lt002_instrument para a lt007_instr_activity) • 10 campos concluídos: especificação validada com CdG. • 6 campos em análise. • 5 campos para validação da especificação com CdG. • 14 campos por iniciar.
H18: 1. Fora de âmbito | K18: 0 | L18: =K18/$K$23 -> 0
H19: 2. Concluído | K19: 10 | L19: =K19/$K$23 -> 0.26315789
H20: 3. Em Análise | K20: 6 | L20: =K20/$K$23 -> 0.15789474
H21: 4. Validação da especificação | K21: 5 | L21: =K21/$K$23 -> 0.13157895
H22: 5. Por Iniciar | K22: 14 | L22: =K22/$K$23 -> 0.36842105
H23: Total | K23: =SUM(K17:K22) -> 38 | L23: =K23/$K$23 -> 1
C28: Detalhe por Tabela

Sheet FC
B6: MacroPlano | Testes GD
F8: Datas Estimadas | J8: Semana 1 | O8: Semana 2 | T8: Semana 3 | Y8: Semana 4 | AD8: Semana 5 | AI8: Semana 6 | AN8: Semana 7 | AS8: Semana 8 | AX8: Semana 9 | BC8: Semana 10 | BH8: Semana 11 | BM8: Semana 12 | BR8: Semana 13
B9: ID | C9: Atividades | D9: Owner | E9: Status | F9: Data Inicio | G9: Data Fim | H9: Data Fim Real | J9: 02/jan-03/jan | O9: 06/jan-10/jan | T9: 13/jan-17/jan | Y9: 20/jan-24/jan | AD9: 27/jan-31/jan | AI9: 03/fev-07/fev | AN9: 10/fev-14/fev | AS9: 17/fev-21/fev | AX9: 24/fev-28/fev | BC9: 03/mar-07/mar | BH9: 10/mar-14/mar | BM9: 17/mar-21/mar
B11: 1. | C11: Assessment Especificação Deloitte
B12: 1.1 | C12: Validação da especificação dos campos (total = 35) | E12: =
B13: 1.2 | C13: Atualização da documentação (word + excel) com a especificação to-be | E13: =
B14: 1.3 | E14: =
B15: 1.4 | E15: =
B16: 1.5 | E16: N/A
B17: 1.6 | E17: =
B18: 1.7 | E18: =
B19: 1.8 | E19: =
B21: 2.
B22: 2.1 | E22: =
B23: 2.2 | E23: =
B24: 2.3 | E24: =
B25: 2.4 | E25: =
B26: 2.5 | E26: =
B27: 2.6 | E27: =
B29: 3.
B30: 3.1 | E30: =
B31: 3.2 | E31: =
B32: 3.3 | E32: =
B33: 3.4 | E33: =
B35: 4.
B36: 4.1 | E36: = | Z36: «
B37: 4.2 | E37: = | AG37: «
B38: 4.3 | E38: = | AW38: «
B39: 4.4 | E39: = | BR39: «
B41: 5. | C41: Outros Temas
B42: 5.1 | C42: Desagregação por Business Area | E42: =
B43: 5.2 | C43: Contratos intra-mês: validação do universo
B46: Legenda:
C48: Feriados
B50: = | C50: Concluído
B51: = | C51: Em progresso
B52: = | C52: Por iniciar
B53: « | C53: Entregas

Sheet Sheet2
B3: 02/jan | C3: 03/jan | D3: 02/jan-03/jan | E3: Semana 1
B4: 06/jan | C4: 10/jan | D4: 06/jan-10/jan | E4: Semana 2
B5: =C4+3 -> 45670 | C5: =B5+4 -> 45674 | D5: 13/jan-17/jan | E5: Semana 3
B6: =C5+3 -> 45677 | C6: =B6+4 -> 45681 | D6: 20/jan-24/jan | E6: Semana 4
B7: =C6+3 -> 45684 | C7: =B7+4 -> 45688 | D7: 27/jan-31/jan | E7: Semana 5
B8: =C7+3 -> 45691 | C8: =B8+4 -> 45695 | D8: 03/fev-07/fev | E8: Semana 6
B9: =C8+3 -> 45698 | C9: =B9+4 -> 45702 | D9: 10/fev-14/fev | E9: Semana 7
B10: =C9+3 -> 45705 | C10: =B10+4 -> 45709 | D10: 17/fev-21/fev | E10: Semana 8
B11: =C10+3 -> 45712 | C11: =B11+4 -> 45716 | D11: 24/fev-28/fev | E11: Semana 9
B12: =C11+3 -> 45719 | C12: =B12+4 -> 45723 | D12: 03/mar-07/mar | E12: Semana 10
B13: =C12+3 -> 45726 | C13: =B13+4 -> 45730 | D13: 10/mar-14/mar | E13: Semana 11
B14: =C13+3 -> 45733 | C14: =B14+4 -> 45737 | D14: 17/mar-21/mar | E14: Semana 12

Sheet 2. Status Detalhe Campos
B6: Âmbito | C6: Categoria | D6: Tipo de teste | E6: Tabela | F6: Campo | G6: Status Atual | H6: Status Anterior | I6: Observações | J6: Data de Pedido correção/esclarecimento | K6: Data de correção prevista | L6: Data de correção efetiva | M6: Data Prevista de Re-especificação | N6: Data Prevista de Teste
A7: =E7&F7 -> lt002_instrumentAVRG_BLNC | B7: Green Dashboard | C7: Assessment | D7: {=INDEX(Plano_Detalhado!$B$10:$H$47,MATCH(1,(Plano_Detalhado!$E$10:$E$47=$E7)*($F7=Plano_Detalhado!$F$10:$F$47),0),3)} -> 2. Campo | E7: lt002_instrument | F7: AVRG_BLNC | G7: {=INDEX(Plano_Detalhado!$B$10:$H$47,MATCH(1,(Plano_Detalhado!$E$10:$E$47=$E7)*($F7=Plano_Detalhado!$F$10:$F$47),0),6)} -> 2. Concluído | H7: {=INDEX(Plano_Detalhado!$B$10:$H$47,MATCH(1,(Plano_Detalhado!$E$10:$E$47=$E7)*($F7=Plano_Detalhado!$F$10:$F$47),0),7)} -> 2. Concluído
A8: =E8&F8 -> lt002_instrumentNW_BSNSS | B8: Green Dashboard | C8: Assessment | D8: {=INDEX(Plano_Detalhado!$B$10:$H$47,MATCH(1,(Plano_Detalhado!$E$10:$E$47=$E8)*($F8=Plano_Detalhado!$F$10:$F$47),0),3)} -> 2. Campo | E8: lt002_instrument | F8: NW_BSNSS | G8: {=INDEX(Plano_Detalhado!$B$10:$H$47,MATCH(1,(Plano_Detalhado!$E$10:$E$47=$E8)*($F8=Plano_Detalhado!$F$10:$F$47),0),6)} -> 4. Validação da especificação | H8: {=INDEX(Plano_Detalhado!$B$10:$H$47,MATCH(1,(Plano_Detalhado!$E$10:$E$47=$E8)*($F8=Plano_Detalhado!$F$10:$F$47),0),7)} -> 8. Por Iniciar
A9: =E9&F9 -> lt002_instrumentGRSS_INTRST_INCM | B9: Green Dashboard | C9: Assessment | D9: {=INDEX(Plano_Detalhado!$B$10:$H$47,MATCH(1,(Plano_Detalhado!$E$10:$E$47=$E9)*($F9=Plano_Detalhado!$F$10:$F$47),0),3)} -> 2. Campo | E9: lt002_instrument | F9: GRSS_INTRST_INCM | G9: {=INDEX(Plano_Detalhado!$B$10:$H$47,MATCH(1,(Plano_Detalhado!$E$10:$E$47=$E9)*($F9=Plano_Detalhado!$F$10:$F$47),0),6)} -> 2. Concluído | H9: {=INDEX(Plano_Detalhado!$B$10:$H$47,MATCH(1,(Plano_Detalhado!$E$10:$E$47=$E9)*($F9=Plano_Detalhado!$F$10:$F$47),0),7)} -> 4. Validação da especificação
A10: =E10&F10 -> lt002_instrumentGRSS_CMMSSN_INCM | B10: Green Dashboard | C10: Assessment | D10: {=INDEX(Plano_Detalhado!$B$10:$H$47,MATCH(1,(Plano_Detalhado!$E$10:$E$47=$E10)*($F10=Plano_Detalhado!$F$10:$F$47),0),3)} -> 2. Campo | E10: lt002_instrument | F10: GRSS_CMMSSN_INCM | G10: {=INDEX(Plano_Detalhado!$B$10:$H$47,MATCH(1,(Plano_Detalhado!$E$10:$E$47=$E10)*($F10=Plano_Detalhado!$F$10:$F$47),0),6)} -> 2. Concluído | H10: {=INDEX(Plano_Detalhado!$B$10:$H$47,MATCH(1,(Plano_Detalhado!$E$10:$E$47=$E10)*($F10=Plano_Detalhado!$F$10:$F$47),0),7)} -> 4. Validação da especificação
A11: =E11&F11 -> lt002_instrumentINTRNL_TRNSFR_RT | B11: Green Dashboard | C11: Assessment | D11: {=INDEX(Plano_Detalhado!$B$10:$H$47,MATCH(1,(Plano_Detalhado!$E$10:$E$47=$E11)*($F11=Plano_Detalhado!$F$10:$F$47),0),3)} -> 2. Campo | E11: lt002_instrument | F11: INTRNL_TRNSFR_RT | G11: {=INDEX(Plano_Detalhado!$B$10:$H$47,MATCH(1,(Plano_Detalhado!$E$10:$E$47=$E11)*($F11=Plano_Detalhado!$F$10:$F$47),0),6)} -> 2. Concluído | H11: {=INDEX(Plano_Detalhado!$B$10:$H$47,MATCH(1,(Plano_Detalhado!$E$10:$E$47=$E11)*($F11=Plano_Detalhado!$F$10:$F$47),0),7)} -> 2. Concluído
A12: =E12&F12 -> lt002_instrumentNT_LN_LSS_PRVSN | B12: Green Dashboard | C12: Assessment | D12: {=INDEX(Plano_Detalhado!$B$10:$H$47,MATCH(1,(Plano_Detalhado!$E$10:$E$47=$E12)*($F12=Plano_Detalhado!$F$10:$F$47),0),3)} -> 2. Campo | E12: lt002_instrument | F12: NT_LN_LSS_PRVSN | G12: {=INDEX(Plano_Detalhado!$B$10:$H$47,MATCH(1,(Plano_Detalhado!$E$10:$E$47=$E12)*($F12=Plano_Detalhado!$F$10:$F$47),0),6)} -> 2. Concluído | H12: {=INDEX(Plano_Detalhado!$B$10:$H$47,MATCH(1,(Plano_Detalhado!$E$10:$E$47=$E12)*($F12=Plano_Detalhado!$F$10:$F$47),0),7)} -> 2. Concluído
A13: =E13&F13 -> lt002_instrumentBSNSS_AREA | B13: Green Dashboard | C13: Assessment | D13: {=INDEX(Plano_Detalhado!$B$10:$H$47,MATCH(1,(Plano_Detalhado!$E$10:$E$47=$E13)*($F13=Plano_Detalhado!$F$10:$F$47),0),3)} -> 2. Campo | E13: lt002_instrument | F13: BSNSS_AREA | G13: {=INDEX(Plano_Detalhado!$B$10:$H$47,MATCH(1,(Plano_Detalhado!$E$10:$E$47=$E13)*($F13=Plano_Detalhado!$F$10:$F$47),0),6)} -> 2. Concluído | H13: {=INDEX(Plano_Detalhado!$B$10:$H$47,MATCH(1,(Plano_Detalhado!$E$10:$E$47=$E13)*($F13=Plano_Detalhado!$F$10:$F$47),0),7)} -> 8. Por Iniciar
A14: =E14&F14 -> lt002_instrumentMNGMNT_PRDCT | B14: Green Dashboard | C14: Assessment | D14: {=INDEX(Plano_Detalhado!$B$10:$H$47,MATCH(1,(Plano_Detalhado!$E$10:$E$47=$E14)*($F14=Plano_Detalhado!$F$10:$F$47),0),3)} -> 2. Campo | E14: lt002_instrument | F14: MNGMNT_PRDCT | G14: {=INDEX(Plano_Detalhado!$B$10:$H$47,MATCH(1,(Plano_Detalhado!$E$10:$E$47=$E14)*($F14=Plano_Detalhado!$F$10:$F$47),0),6)} -> 2. Concluído | H14: {=INDEX(Plano_Detalhado!$B$10:$H$47,MATCH(1,(Plano_Detalhado!$E$10:$E$47=$E14)*($F14=Plano_Detalhado!$F$10:$F$47),0),7)} -> 2. Concluído
A15: =E15&F15 -> lt002_instrumentGRSS_CMMSSN_EXPNS | B15: Green Dashboard | C15: Assessment | D15: {=INDEX(Plano_Detalhado!$B$10:$H$47,MATCH(1,(Plano_Detalhado!$E$10:$E$47=$E15)*($F15=Plano_Detalhado!$F$10:$F$47),0),3)} -> 2. Campo | E15: lt002_instrument | F15: GRSS_CMMSSN_EXPNS | G15: {=INDEX(Plano_Detalhado!$B$10:$H$47,MATCH(1,(Plano_Detalhado!$E$10:$E$47=$E15)*($F15=Plano_Detalhado!$F$10:$F$47),0),6)} -> 2. Concluído | H15: {=INDEX(Plano_Detalhado!$B$10:$H$47,MATCH(1,(Plano_Detalhado!$E$10:$E$47=$E15)*($F15=Plano_Detalhado!$F$10:$F$47),0),7)} -> 2. Concluído
A16: =E16&F16 -> lt002_instrumentGNS_FNNCL_TRNSCTN_EXCHNG_DFFRNCS | B16: Green Dashboard | C16: Assessment | D16: {=INDEX(Plano_Detalhado!$B$10:$H$47,MATCH(1,(Plano_Detalhado!$E$10:$E$47=$E16)*($F16=Plano_Detalhado!$F$10:$F$47),0),3)} -> 2. Campo | E16: lt002_instrument | F16: GNS_FNNCL_TRNSCTN_EXCHNG_DFFRNCS | G16: {=INDEX(Plano_Detalhado!$B$10:$H$47,MATCH(1,(Plano_Detalhado!$E$10:$E$47=$E16)*($F16=Plano_Detalhado!$F$10:$F$47),0),6)} -> 2. Concluído | H16: {=INDEX(Plano_Detalhado!$B$10:$H$47,MATCH(1,(Plano_Detalhado!$E$10:$E$47=$E16)*($F16=Plano_Detalhado!$F$10:$F$47),0),7)} -> 2. Concluído
A17: =E17&F17 -> lt002_instrumentFLG_INTRBSNSS | B17: Green Dashboard | C17: Assessment | D17: {=INDEX(Plano_Detalhado!$B$10:$H$47,MATCH(1,(Plano_Detalhado!$E$10:$E$47=$E17)*($F17=Plano_Detalhado!$F$10:$F$47),0),3)} -> 2. Campo | E17: lt002_instrument | F17: FLG_INTRBSNSS | G17: {=INDEX(Plano_Detalhado!$B$10:$H$47,MATCH(1,(Plano_Detalhado!$E$10:$E$47=$E17)*($F17=Plano_Detalhado!$F$10:$F$47),0),6)} -> 3. Em Análise | H17: {=INDEX(Plano_Detalhado!$B$10:$H$47,MATCH(1,(Plano_Detalhado!$E$10:$E$47=$E17)*($F17=Plano_Detalhado!$F$10:$F$47),0),7)} -> 8. Por Iniciar
A18: =E18&F18 -> lt002_instrumentINTRBSNSS_ADJ_COD | B18: Green Dashboard | C18: Assessment | D18: {=INDEX(Plano_Detalhado!$B$10:$H$47,MATCH(1,(Plano_Detalhado!$E$10:$E$47=$E18)*($F18=Plano_Detalhado!$F$10:$F$47),0),3)} -> 2. Campo | E18: lt002_instrument | F18: INTRBSNSS_ADJ_COD | G18: {=INDEX(Plano_Detalhado!$B$10:$H$47,MATCH(1,(Plano_Detalhado!$E$10:$E$47=$E18)*($F18=Plano_Detalhado!$F$10:$F$47),0),6)} -> 3. Em Análise | H18: {=INDEX(Plano_Detalhado!$B$10:$H$47,MATCH(1,(Plano_Detalhado!$E$10:$E$47=$E18)*($F18=Plano_Detalhado!$F$10:$F$47),0),7)} -> 8. Por Iniciar
... A31: =E31&F31 -> lt002_instrumentGRSS_CMMSSN_EXPNS_CCRR | B31: Green Dashboard | C31: Assessment | D31: {=INDEX(Plano_Detalhado!$B$10:$H$47,MATCH(1,(Plano_Detalhado!$E$10:$E$47=$E31)*($F31=Plano_Detalhado!$F$10:$F$47),0),3)} -> 2. Campo | E31: lt002_instrument | F31: GRSS_CMMSSN_EXPNS_CCRR | G31: {=INDEX(Plano_Detalhado!$B$10:$H$47,MATCH(1,(Plano_Detalhado!$E$10:$E$47=$E31)*($F31=Plano_Detalhado!$F$10:$F$47),0),6)} -> 2. Concluído | H31: {=INDEX(Plano_Detalhado!$B$10:$H$47,MATCH(1,(Plano_Detalhado!$E$10:$E$47=$E31)*($F31=Plano_Detalhado!$F$10:$F$47),0),7)} -> 8. Por Iniciar
B32: Green Dashboard | C32: Assessment | D32: {=INDEX(Plano_Detalhado!$B$10:$H$47,MATCH(1,(Plano_Detalhado!$E$10:$E$47=$E32)*($F32=Plano_Detalhado!$F$10:$F$47),0),3)} -> 2. Campo | E32: lt002_instrument | F32: GNS_FNNCL_TRNSCTN_EXCHNG_CCRR | G32: {=INDEX(Plano_Detalhado!$B$10:$H$47,MATCH(1,(Plano_Detalhado!$E$10:$E$47=$E32)*($F32=Plano_Detalhado!$F$10:$F$47),0),6)} -> 2. Concluído | H32: {=INDEX(Plano_Detalhado!$B$10:$H$47,MATCH(1,(Plano_Detalhado!$E$10:$E$47=$E32)*($F32=Plano_Detalhado!$F$10:$F$47),0),7)} -> 8. Por Iniciar
B33: Green Dashboard | C33: Assessment | D33: {=INDEX(Plano_Detalhado!$B$10:$H$47,MATCH(1,(Plano_Detalhado!$E$10:$E$47=$E33)*($F33=Plano_Detalhado!$F$10:$F$47),0),3)} -> 2. Campo | E33: lt002_instrument | F33: BSNSS_AREA_CCRR | G33: {=INDEX(Plano_Detalhado!$B$10:$H$47,MATCH(1,(Plano_Detalhado!$E$10:$E$47=$E33)*($F33=Plano_Detalhado!$F$10:$F$47),0),6)} -> 2. Concluído | H33: {=INDEX(Plano_Detalhado!$B$10:$H$47,MATCH(1,(Plano_Detalhado!$E$10:$E$47=$E33)*($F33=Plano_Detalhado!$F$10:$F$47),0),7)} -> 8. Por Iniciar
B34: Green Dashboard | C34: Assessment | D34: {=INDEX(Plano_Detalhado!$B$10:$H$47,MATCH(1,(Plano_Detalhado!$E$10:$E$47=$E34)*($F34=Plano_Detalhado!$F$10:$F$47),0),3)} -> 2. Campo | E34: lt002_instrument | F34: GRSS_CMMSSN_INCM_OFF_BLNC_CCRR | G34: {=INDEX(Plano_Detalhado!$B$10:$H$47,MATCH(1,(Plano_Detalhado!$E$10:$E$47=$E34)*($F34=Plano_Detalhado!$F$10:$F$47),0),6)} -> 2. Concluído | H34: {=INDEX(Plano_Detalhado!$B$10:$H$47,MATCH(1,(Plano_Detalhado!$E$10:$E$47=$E34)*($F34=Plano_Detalhado!$F$10:$F$47),0),7)} -> 8. Por Iniciar
B35: Green Dashboard | C35: Assessment | D35: {=INDEX(Plano_Detalhado!$B$10:$H$47,MATCH(1,(Plano_Detalhado!$E$10:$E$47=$E35)*($F35=Plano_Detalhado!$F$10:$F$47),0),3)} -> 2. Campo | E35: lt002_instrument | F35: GRSS_CMMSSN_EXPNS_OFF_BLNC_CCRR | G35: {=INDEX(Plano_Detalhado!$B$10:$H$47,MATCH(1,(Plano_Detalhado!$E$10:$E$47=$E35)*($F35=Plano_Detalhado!$F$10:$F$47),0),6)} -> 2. Concluído | H35: {=INDEX(Plano_Detalhado!$B$10:$H$47,MATCH(1,(Plano_Detalhado!$E$10:$E$47=$E35)*($F35=Plano_Detalhado!$F$10:$F$47),0),7)} -> 8. Por Iniciar
B36: Green Dashboard | C36: Assessment | D36: {=INDEX(Plano_Detalhado!$B$10:$H$47,MATCH(1,(Plano_Detalhado!$E$10:$E$47=$E36)*($F36=Plano_Detalhado!$F$10:$F$47),0),3)} -> 2. Campo | E36: lt002_instrument | F36: FLG_INSTRMNT_CNCLLD | G36: {=INDEX(Plano_Detalhado!$B$10:$H$47,MATCH(1,(Plano_Detalhado!$E$10:$E$47=$E36)*($F36=Plano_Detalhado!$F$10:$F$47),0),6)} -> 0. Cancelado | H36: {=INDEX(Plano_Detalhado!$B$10:$H$47,MATCH(1,(Plano_Detalhado!$E$10:$E$47=$E36)*($F36=Plano_Detalhado!$F$10:$F$47),0),7)} -> 0. Cancelado
B37: Green Dashboard | C37: Assessment | D37: {=INDEX(Plano_Detalhado!$B$10:$H$47,MATCH(1,(Plano_Detalhado!$E$10:$E$47=$E37)*($F37=Plano_Detalhado!$F$10:$F$47),0),3)} -> 2. Campo | E37: lt824_assoc_kpi_gd | F37: ambito | G37: {=INDEX(Plano_Detalhado!$B$10:$H$47,MATCH(1,(Plano_Detalhado!$E$10:$E$47=$E37)*($F37=Plano_Detalhado!$F$10:$F$47),0),6)} -> 2. Concluído | H37: {=INDEX(Plano_Detalhado!$B$10:$H$47,MATCH(1,(Plano_Detalhado!$E$10:$E$47=$E37)*($F37=Plano_Detalhado!$F$10:$F$47),0),7)} -> 3. Em Análise
B38: Green Dashboard | C38: Assessment | D38: {=INDEX(Plano_Detalhado!$B$10:$H$47,MATCH(1,(Plano_Detalhado!$E$10:$E$47=$E38)*($F38=Plano_Detalhado!$F$10:$F$47),0),3)} -> 2. Campo | E38: lt824_assoc_kpi_gd | F38: tipo_conta_local | G38: {=INDEX(Plano_Detalhado!$B$10:$H$47,MATCH(1,(Plano_Detalhado!$E$10:$E$47=$E38)*($F38=Plano_Detalhado!$F$10:$F$47),0),6)} -> 2. Concluído | H38: {=INDEX(Plano_Detalhado!$B$10:$H$47,MATCH(1,(Plano_Detalhado!$E$10:$E$47=$E38)*($F38=Plano_Detalhado!$F$10:$F$47),0),7)} -> 3. Em Análise
B39: Green Dashboard | C39: Assessment | D39: {=INDEX(Plano_Detalhado!$B$10:$H$47,MATCH(1,(Plano_Detalhado!$E$10:$E$47=$E39)*($F39=Plano_Detalhado!$F$10:$F$47),0),3)} -> 2. Campo | E39: lt824_assoc_kpi_gd | F39: valor_gd | G39: {=INDEX(Plano_Detalhado!$B$10:$H$47,MATCH(1,(Plano_Detalhado!$E$10:$E$47=$E39)*($F39=Plano_Detalhado!$F$10:$F$47),0),6)} -> 2. Concluído | H39: {=INDEX(Plano_Detalhado!$B$10:$H$47,MATCH(1,(Plano_Detalhado!$E$10:$E$47=$E39)*($F39=Plano_Detalhado!$F$10:$F$47),0),7)} -> 3. Em Análise
B40: Green Dashboard | C40: Assessment | D40: {=INDEX(Plano_Detalhado!$B$10:$H$47,MATCH(1,(Plano_Detalhado!$E$10:$E$47=$E40)*($F40=Plano_Detalhado!$F$10:$F$47),0),3)} -> 2. Campo | E40: lt824_assoc_kpi_gd | F40: kpi | G40: {=INDEX(Plano_Detalhado!$B$10:$H$47,MATCH(1,(Plano_Detalhado!$E$10:$E$47=$E40)*($F40=Plano_Detalhado!$F$10:$F$47),0),6)} -> 2. Concluído | H40: {=INDEX(Plano_Detalhado!$B$10:$H$47,MATCH(1,(Plano_Detalhado!$E$10:$E$47=$E40)*($F40=Plano_Detalhado!$F$10:$F$47),0),7)} -> 3. Em Análise
B41: Green Dashboard | C41: Assessment | D41: {=INDEX(Plano_Detalhado!$B$10:$H$47,MATCH(1,(Plano_Detalhado!$E$10:$E$47=$E41)*($F41=Plano_Detalhado!$F$10:$F$47),0),3)} -> 2. Campo | E41: lt824_assoc_kpi_gd | F41: ordem | G41: {=INDEX(Plano_Detalhado!$B$10:$H$47,MATCH(1,(Plano_Detalhado!$E$10:$E$47=$E41)*($F41=Plano_Detalhado!$F$10:$F$47),0),6)} -> 2. Concluído | H41: {=INDEX(Plano_Detalhado!$B$10:$H$47,MATCH(1,(Plano_Detalhado!$E$10:$E$47=$E41)*($F41=Plano_Detalhado!$F$10:$F$47),0),7)} -> 3. Em Análise
B42: Green Dashboard | C42: Assessment | D42: {=INDEX(Plano_Detalhado!$B$10:$H$47,MATCH(1,(Plano_Detalhado!$E$10:$E$47=$E42)*($F42=Plano_Detalhado!$F$10:$F$47),0),3)} -> 2. Campo | E42: lt824_assoc_kpi_gd | F42: ref_date | G42: {=INDEX(Plano_Detalhado!$B$10:$H$47,MATCH(1,(Plano_Detalhado!$E$10:$E$47=$E42)*($F42=Plano_Detalhado!$F$10:$F$47),0),6)} -> 2. Concluído | H42: {=INDEX(Plano_Detalhado!$B$10:$H$47,MATCH(1,(Plano_Detalhado!$E$10:$E$47=$E42)*($F42=Plano_Detalhado!$F$10:$F$47),0),7)} -> 3. Em Análise
B43: Green Dashboard | C43: Assessment | D43: {=INDEX(Plano_Detalhado!$B$10:$H$47,MATCH(1,(Plano_Detalhado!$E$10:$E$47=$E43)*($F43=Plano_Detalhado!$F$10:$F$47),0),3)} -> 2. Campo | E43: lt002_instrument | F43: SSTNBL_INDCTR | G43: {=INDEX(Plano_Detalhado!$B$10:$H$47,MATCH(1,(Plano_Detalhado!$E$10:$E$47=$E43)*($F43=Plano_Detalhado!$F$10:$F$47),0),6)} -> 0. Cancelado | H43: {=INDEX(Plano_Detalhado!$B$10:$H$47,MATCH(1,(Plano_Detalhado!$E$10:$E$47=$E43)*($F43=Plano_Detalhado!$F$10:$F$47),0),7)} -> 0. Cancelado
B44: Green Dashboard | C44: Assessment | D44: {=INDEX(Plano_Detalhado!$B$10:$H$47,MATCH(1,(Plano_Detalhado!$E$10:$E$47=$E44)*($F44=Plano_Detalhado!$F$10:$F$47),0),3)} -> 2. Campo | E44: lt002_instrument | F44: SSTNBL_CTGRY | G44: {=INDEX(Plano_Detalhado!$B$10:$H$47,MATCH(1,(Plano_Detalhado!$E$10:$E$47=$E44)*($F44=Plano_Detalhado!$F$10:$F$47),0),6)} -> 0. Cancelado | H44: {=INDEX(Plano_Detalhado!$B$10:$H$47,MATCH(1,(Plano_Detalhado!$E$10:$E$47=$E44)*($F44=Plano_Detalhado!$F$10:$F$47),0),7)} -> 0. Cancelado

Sheet Plano_Detalhado
Q6: Janeiro | AM6: Fevereiro | BG6: Março
Q7: =Q8 -> 45659 | R7: =R8 -> 45660 | S7: =S8 -> 45663 | T7: =T8 -> 45664 | U7: =U8 -> 45665 | V7: =V8 -> 45666 | W7: =W8 -> 45667 | X7: =X8 -> 45670 | ... CA7: =CA8 -> 45747
B8: Âmbito | C8: Sub-âmbito | D8: Tipo de teste | E8: Tabela | F8: Campo | G8: Status Atual | H8: Status Anterior | I8: Horas previstas | J8: Dias | K8: Horas efetivas | L8: Dias efetivos | M8: Status Estimado | N8: Status Real | O8: Desvios | P8: Observações | Q8: 45659 | R8: =WORKDAY(Q8,1) -> 45660 | S8: =WORKDAY(R8,1) -> 45663 | T8: =WORKDAY(S8,1) -> 45664 | U8: =WORKDAY(T8,1) -> 45665 | V8: =WORKDAY(U8,1) -> 45666 | W8: =WORKDAY(V8,1) -> 45667 | X8: =WORKDAY(W8,1) -> 45670 | Y8: =WORKDAY(X8,1) -> 45671 | ... CA8: =WORKDAY(BZ8,1) -> 45747
B9: 1. Assessment | I9: =+Macro_Plano_2025_v1!J15 -> 64 | J9: =I9/8 -> 8 | K9: =SUM(K10:K34) -> 6.5 | L9: =SUM(L10:L34) -> 1.5625 | M9: =SUMPRODUCT(M10:M34,I10:I34)/I9 -> 0.04 | N9: =SUMPRODUCT(N10:N34,J10:J34)/J9 -> 0.04 | O9: =N9-M9 -> 0 | P9: N/A
B10: GD | C10: Exclusivo GD - Campos Deloitte | D10: 2. Campo | E10: lt002_instrument | F10: AVRG_BLNC | G10: 2. Concluído | H10: 2. Concluído | I10: =+$I$9/25 -> 2.56 | J10: =+$J$9/25 -> 0.32 | K10: =SUM(Q10:CA10) -> 0.5 | L10: =K10/8 -> 0.0625 | M10: =100% -> 1 | N10: =100% -> 1 | O10: =N10-M10 -> 0 | P10: N/A | Q10: 0.5
B11: GD | C11: Exclusivo GD - Campos Deloitte | D11: 2. Campo | E11: lt002_instrument | F11: NW_BSNSS | G11: 4. Validação da especificação | H11: 8. Por Iniciar | I11: =+$I$9/25 -> 2.56 | J11: =+$J$9/25 -> 0.32 | K11: =SUM(Q11:CA11) -> 0.5 | L11: 0.0625 | R11: 0.5
B12: GD | C12: Exclusivo GD - Campos Deloitte | D12: 2. Campo | E12: lt002_instrument | F12: GRSS_INTRST_INCM | G12: 2. Concluído | H12: 4. Validação da especificação | I12: =+$I$9/25 -> 2.56 | J12: =+$J$9/25 -> 0.32 | K12: =SUM(Q12:CA12) -> 0.5 | L12: 0.0625 | S12: 0.5
B13: GD | C13: Exclusivo GD - Campos Deloitte | D13: 2. Campo | E13: lt002_instrument | F13: GRSS_CMMSSN_INCM | G13: 2. Concluído | H13: 4. Validação da especificação | I13: =+$I$9/25 -> 2.56 | J13: =+$J$9/25 -> 0.32 | K13: =SUM(Q13:CA13) -> 0 | L13: 0.0625
B14: GD | C14: Exclusivo GD - Campos Deloitte | D14: 2. Campo | E14: lt002_instrument | F14: INTRNL_TRNSFR_RT | G14: 2. Concluído | H14: 2. Concluído | I14: =+$I$9/25 -> 2.56 | J14: =+$J$9/25 -> 0.32 | K14: =SUM(Q14:CA14) -> 1.5 | L14: 0.0625 | R14: 1.5
B15: GD | C15: Exclusivo GD - Campos Deloitte | D15: 2. Campo | E15: lt002_instrument | F15: NT_LN_LSS_PRVSN | G15: 2. Concluído | H15: 2. Concluído | I15: =+$I$9/25 -> 2.56 | J15: =+$J$9/25 -> 0.32 | K15: =SUM(Q15:CA15) -> 0.5 | L15: 0.0625 | R15: 0.5
B16: GD | C16: Exclusivo GD - Campos Deloitte | D16: 2. Campo | E16: lt002_instrument | F16: BSNSS_AREA | G16: 2. Concluído | H16: 8. Por Iniciar | I16: =+$I$9/25 -> 2.56 | J16: =+$J$9/25 -> 0.32 | K16: =SUM(Q16:CA16) -> 0 | L16: 0.0625
B17: GD | C17: Exclusivo GD - Campos Deloitte | D17: 2. Campo | E17: lt002_instrument | F17: MNGMNT_PRDCT | G17: 2. Concluído | H17: 2. Concluído | I17: =+$I$9/25 -> 2.56 | J17: =+$J$9/25 -> 0.32 | K17: =SUM(Q17:CA17) -> 0 | L17: 0.0625
B18: GD | C18: Exclusivo GD - Campos Deloitte | D18: 2. Campo | E18: lt002_instrument | F18: GRSS_CMMSSN_EXPNS | G18: 2. Concluído | H18: 2. Concluído | I18: =+$I$9/25 -> 2.56 | J18: =+$J$9/25 -> 0.32 | K18: =SUM(Q18:CA18) -> 0 | L18: 0.0625
B19: GD | C19: Exclusivo GD - Campos Deloitte | D19: 2. Campo | E19: lt002_instrument | F19: GNS_FNNCL_TRNSCTN_EXCHNG_DFFRNCS | G19: 2. Concluído | H19: 2. Concluído | I19: =+$I$9/25 -> 2.56 | J19: =+$J$9/25 -> 0.32 | K19: =SUM(Q19:CA19) -> 0 | L19: 0.0625
B20: GD | C20: Exclusivo GD - Campos Deloitte | D20: 2. Campo | E20: lt002_instrument | F20: FLG_INTRBSNSS | G20: 3. Em Análise | H20: 8. Por Iniciar | I20: =+$I$9/25 -> 2.56 | J20: =+$J$9/25 -> 0.32 | K20: =SUM(Q20:CA20) -> 0 | L20: 0.0625
B21: GD | C21: Exclusivo GD - Campos Deloitte | D21: 2. Campo | E21: lt002_instrument | F21: INTRBSNSS_ADJ_COD | G21: 3. Em Análise | H21: 8. Por Iniciar | I21: =+$I$9/25 -> 2.56 | J21: =+$J$9/25 -> 0.32 | K21: =SUM(Q21:CA21) -> 0.5 | L21: 0.0625 | R21: 0.5
B22: GD | C22: Exclusivo GD - Campos Deloitte | D22: 2. Campo | E22: lt002_instrument | F22: COD_SOC_DSTNTN | G22: 3. Em Análise | H22: 8. Por Iniciar | I22: =+$I$9/25 -> 2.56 | J22: =+$J$9/25 -> 0.32 | K22: =SUM(Q22:CA22) -> 0.5 | L22: 0.0625 | R22: 0.5
B23: GD | C23: Exclusivo GD - Campos Deloitte | D23: 2. Campo | E23: lt002_instrument | F23: BSNSS_AREA_DSTNTN | G23: 2. Concluído | H23: 8. Por Iniciar | I23: =+$I$9/25 -> 2.56 | J23: =+$J$9/25 -> 0.32 | K23: =SUM(Q23:CA23) -> 0.5 | L23: 0.0625 | R23: 0.5
B24: GD | C24: Exclusivo GD - Campos Deloitte | D24: 2. Campo | E24: lt002_instrument | F24: AVRG_BLNC_OFF_BLNC | G24: 2. Concluído | H24: 2. Concluído | I24: =+$I$9/25 -> 2.56 | J24: =+$J$9/25 -> 0.32 | K24: =SUM(Q24:CA24) -> 0.5 | L24: 0.0625 | R24: 0.5
B25: GD | C25: Exclusivo GD - Campos Deloitte | D25: 2. Campo | E25: lt002_instrument | F25: INTRNL_TRNSFR_RT_OFF_BLNC | G25: 2. Concluído | H25: 4. Validação da especificação | I25: =+$I$9/25 -> 2.56 | J25: =+$J$9/25 -> 0.32 | K25: =SUM(Q25:CA25) -> 0.5 | L25: 0.0625 | R25: 0.5
B26: GD | C26: Exclusivo GD - Campos Deloitte | D26: 2. Campo | E26: lt002_instrument | F26: GRSS_CMMSSN_INCM_OFF_BLNC | G26: 2. Concluído | H26: 4. Validação da especificação | I26: =+$I$9/25 -> 2.56 | J26: =+$J$9/25 -> 0.32 | K26: =SUM(Q26:CA26) -> 0.5 | L26: 0.0625 | R26: 0.5
B27: GD | C27: Exclusivo GD - Campos Deloitte | D27: 2. Campo | E27: lt002_instrument | F27: GRSS_CMMSSN_EXPNS_OFF_BLNC | G27: 2. Concluído | H27: 2. Concluído | I27: =+$I$9/25 -> 2.56 | J27: =+$J$9/25 -> 0.32 | K27: =SUM(Q27:CA27) -> 0 | L27: 0.0625
B28: GD | C28: Exclusivo GD - Campos Deloitte | D28: 2. Campo | E28: lt002_instrument | F28: RWA_OFF_BLNC | G28: 2. Concluído | H28: 4. Validação da especificação | I28: =+$I$9/25 -> 2.56 | J28: =+$J$9/25 -> 0.32 | K28: =SUM(Q28:CA28) -> 0 | L28: 0.0625
B29: GD | C29: Exclusivo GD - Campos Deloitte | D29: 2. Campo | E29: lt002_instrument | F29: GRSS_INTRST_EXPNS | G29: 2. Concluído | H29: 2. Concluído | I29: =+$I$9/25 -> 2.56 | J29: =+$J$9/25 -> 0.32 | K29: =SUM(Q29:CA29) -> 0 | L29: 0.0625
B30: GD | C30: Exclusivo GD - Campos Deloitte | D30: 2. Campo | E30: lt002_instrument | F30: NT_LN_LSS_PRVSN_OFF_BLNC | G30: 2. Concluído | H30: 2. Concluído | I30: =+$I$9/25 -> 2.56 | J30: =+$J$9/25 -> 0.32 | K30: =SUM(Q30:CA30) -> 0 | L30: 0.0625
B31: GD | C31: Exclusivo GD - Campos Deloitte | D31: 2. Campo | E31: lt002_instrument | F31: GRSS_INTRST_INCM_CCRR | G31: 2. Concluído | H31: 8. Por Iniciar | I31: =+$I$9/25 -> 2.56 | J31: =+$J$9/25 -> 0.32 | K31: =SUM(Q31:CA31) -> 0 | L31: 0.0625
B32: GD | C32: Exclusivo GD - Campos Deloitte | D32: 2. Campo | E32: lt002_instrument | F32: GRSS_INTRST_EXPNS_CCRR | G32: 2. Concluído | H32: 8. Por Iniciar | I32: =+$I$9/25 -> 2.56 | J32: =+$J$9/25 -> 0.32 | K32: =SUM(Q32:CA32) -> 0 | L32: 0.0625
B33: GD | C33: Exclusivo GD - Campos Deloitte | D33: 2. Campo | E33: lt002_instrument | F33: GRSS_CMMSSN_INCM_CCRR | G33: 2. Concluído | H33: 8. Por Iniciar | I33: =+$I$9/25 -> 2.56 | J33: =+$J$9/25 -> 0.32 | K33: =SUM(Q33:CA33) -> 0 | L33: 0.0625
B34: GD | C34: Exclusivo GD - Campos Deloitte | D34: 2. Campo | E34: lt002_instrument | F34: GRSS_CMMSSN_EXPNS_CCRR | G34: 2. Concluído | H34: 8. Por Iniciar | I34: =+$I$9/25 -> 2.56 | J34: =+$J$9/25 -> 0.32 | K34: =SUM(Q34:CA34) -> 0 | L34: 0.0625
B35: GD | C35: Exclusivo GD - Campos Deloitte | D35: 2. Campo | E35: lt002_instrument | F35: GNS_FNNCL_TRNSCTN_EXCHNG_CCRR | G35: 2. Concluído | H35: 8. Por Iniciar
B36: GD | C36: Exclusivo GD - Campos Deloitte | D36: 2. Campo | E36: lt002_instrument | F36: BSNSS_AREA_CCRR | G36: 2. Concluído | H36: 8. Por Iniciar
B37: GD | C37: Exclusivo GD - Campos Deloitte | D37: 2. Campo | E37: lt002_instrument | F37: GRSS_CMMSSN_INCM_OFF_BLNC_CCRR | G37: 2. Concluído | H37: 8. Por Iniciar
B38: GD | C38: Exclusivo GD - Campos Deloitte | D38: 2. Campo | E38: lt002_instrument | F38: GRSS_CMMSSN_EXPNS_OFF_BLNC_CCRR | G38: 2. Concluído | H38: 8. Por Iniciar
B39: GD | C39: Exclusivo GD - Campos Deloitte | D39: 2. Campo | E39: lt002_instrument | F39: FLG_INSTRMNT_CNCLLD | G39: 0. Cancelado | H39: 0. Cancelado
B40: GD | C40: Exclusivo GD - Campos Deloitte | D40: 2. Campo | E40: lt824_assoc_kpi_gd | F40: ambito | G40: 2. Concluído | H40: 3. Em Análise
B41: GD | C41: Exclusivo GD - Campos Deloitte | D41: 2. Campo | E41: lt824_assoc_kpi_gd | F41: tipo_conta_local | G41: 2. Concluído | H41: 3. Em Análise
B42: GD | C42: Exclusivo GD - Campos Deloitte | D42: 2. Campo | E42: lt824_assoc_kpi_gd | F42: valor_gd | G42: 2. Concluído | H42: 3. Em Análise
B43: GD | C43: Exclusivo GD - Campos Deloitte | D43: 2. Campo | E43: lt824_assoc_kpi_gd | F43: kpi | G43: 2. Concluído | H43: 3. Em Análise
B44: GD | C44: Exclusivo GD - Campos Deloitte | D44: 2. Campo | E44: lt824_assoc_kpi_gd | F44: ordem | G44: 2. Concluído | H44: 3. Em Análise
B45: GD | C45: Exclusivo GD - Campos Deloitte | D45: 2. Campo | E45: lt824_assoc_kpi_gd | F45: ref_date | G45: 2. Concluído | H45: 3. Em Análise
B46: GD | C46: Exclusivo GD - Campos Deloitte | D46: 2. Campo | E46: lt002_instrument | F46: SSTNBL_INDCTR | G46: 0. Cancelado | H46: 0. Cancelado
B47: GD | C47: Exclusivo GD - Campos Deloitte | D47: 2. Campo | E47: lt002_instrument | F47: SSTNBL_CTGRY | G47: 0. Cancelado | H47: 0. Cancelado
B49: 2. Re-especificação | I49: =SUM(I50:I52) -> 120 | J49: =SUM(J50:J52) -> 15 | K49: =N49*I49 -> 118.8 | L49: =N49*J49 -> 14.85 | M49: =SUMPRODUCT(M50:M53,I50:I53)/I49 -> #REF! | N49: =SUMPRODUCT(N50:N52,J50:J52)/J49 -> 0.99 | O49: =N49-M49 -> #REF! | P49: N/A
B50: Pilar III | C50: Bens Imóveis | G50: 7. Por iniciar | I50: =J50*8 -> 40 | J50: 5 | M50: =SUMIFS(Q50:CA50,#REF!,"S")/J50 -> #REF! | N50: =100% -> 1 | O50: =N50-M50 -> #REF! | P50: N/A | BJ50: 0.5 | BO50: 0.5 | BT50: 0.5
B51: Pilar III | C51: Modelo Verde | G51: 7. Por iniciar | I51: =J51*8 -> 40 | J51: 5 | M51: =SUMIFS(Q51:CA51,#REF!,"S")/J51 -> #REF! | N51: 1 | O51: =N51-M51 -> #REF! | P51: N/A | BJ51: 0.5 | BO51: 0.5 | BT51: 0.5
B52: Pilar III | C52: LT Pilar III | G52: 7. Por iniciar | I52: =J52*8 -> 40 | J52: 5 | M52: =SUMIFS(Q52:CA52,#REF!,"S")/J52 -> #REF! | N52: 0.97 | O52: =N52-M52 -> #REF! | P52: - Em falta a re-especificação de um campo do Pilar III dependente de reunião com o LCM | BO52: 0.5 | BT52: 0.5 | BY52: 0.5
B54: 3. Testes / Re-testes | I54: =I55+I70+I234+I401+I486 -> #REF! | J54: =J55+J70+J234+J401+J486 -> #REF! | K54: =K55+K70+K234+K401+K486 -> #REF! | L54: =L55+L70+L234+L401+L486 -> #REF! | M54: =((M55*J55)+(M70*J70)+(M234*J234)+(M401*J401)+(M486*J486))/J54 -> #REF! | N54: =((N55*L55)+(N70*L70)+(N234*L234)+(N401*L401)+(N486*L486))/L54 -> #REF! | O54: =N54-M54 -> #REF! | P54: N/A
B55: Pilar III | C55: Bens Imóveis - Input | I55: =SUM(I56:I69) -> #REF! | J55: =ROUNDUP(I55/8,0) -> #REF! | K55: =SUM(K56:K69) -> #REF! | L55: =ROUNDUP(K55/8,0) -> #REF! | M55: =SUMIFS(Q55:CA55,#REF!,"S")/J55 -> #REF! | N55: =IFERROR(L55/J55,0) -> 0 | O55: =N55-M55 -> #REF! | P55: - Pendência de desenvolvimentos de IT: Tabela da Gloval
A56: =E56&F56 -> ENERGY_CERTIFICATE_EST_INPUTn.a. | B56: Pilar III | C56: Bens Imóveis - Input | D56: 1. Universo | E56: ENERGY_CERTIFICATE_EST_INPUT | F56: n.a. | G56: =INDEX(#REF!,MATCH(Plano_Detalhado!H56,#REF!,0),1) -> #REF! | H56: =VLOOKUP(A56,#REF!,2,0) -> #REF! | I56: =SUMIFS(#REF!,#REF!,Plano_Detalhado!E56,#REF!,Plano_Detalhado!F56) -> #REF! | J56: =I56/8 -> #REF! | K56: =SUMIFS(#REF!,#REF!,Plano_Detalhado!E56,#REF!,Plano_Detalhado!F56) -> #REF! | L56: =K56/8 -> #REF! | N56: =L56/J56 -> #REF! | O56: =N56-M56 -> #REF! | P56: sem pendencia
A57: =E57&F57 -> ENERGY_CERTIFICATE_EST_INPUTPROPERTY_BANK_ID | B57: Pilar III | C57: Bens Imóveis - Input | D57: 2. Campo | E57: ENERGY_CERTIFICATE_EST_INPUT | F57: PROPERTY_BANK_ID | G57: =INDEX(#REF!,MATCH(Plano_Detalhado!H57,#REF!,0),1) -> #REF! | H57: =VLOOKUP(A57,#REF!,2,0) -> #REF! | I57: =SUMIFS(#REF!,#REF!,Plano_Detalhado!E57,#REF!,Plano_Detalhado!F57) -> #REF! | J57: =I57/8 -> #REF! | K57: =SUMIFS(#REF!,#REF!,Plano_Detalhado!E57,#REF!,Plano_Detalhado!F57) -> #REF! | L57: =K57/8 -> #REF! | N57: =L57/J57 -> #REF! | O57: =N57-M57 -> #REF! | P57: sem pendencia
A58: =E58&F58 -> ENERGY_CERTIFICATE_EST_INPUTENCRYPTED_KEY | B58: Pilar III | C58: Bens Imóveis - Input | D58: 2. Campo | E58: ENERGY_CERTIFICATE_EST_INPUT | F58: ENCRYPTED_KEY | G58: =INDEX(#REF!,MATCH(Plano_Detalhado!H58,#REF!,0),1) -> #REF! | H58: =VLOOKUP(A58,#REF!,2,0) -> #REF! | I58: =SUMIFS(#REF!,#REF!,Plano_Detalhado!E58,#REF!,Plano_Detalhado!F58) -> #REF! | J58: =I58/8 -> #REF! | K58: =SUMIFS(#REF!,#REF!,Plano_Detalhado!E58,#REF!,Plano_Detalhado!F58) -> #REF! | L58: =K58/8 -> #REF! | N58: =L58/J58 -> #REF! | O58: =N58-M58 -> #REF! | P58: sem pendencia
A59: =E59&F59 -> ENERGY_CERTIFICATE_EST_INPUTPROPERTY_BRANCH_CODE | B59: Pilar III | C59: Bens Imóveis - Input | D59: 2. Campo | E59: ENERGY_CERTIFICATE_EST_INPUT | F59: PROPERTY_BRANCH_CODE | G59: =INDEX(#REF!,MATCH(Plano_Detalhado!H59,#REF!,0),1) -> #REF! | H59: =VLOOKUP(A59,#REF!,2,0) -> #REF! | I59: =SUMIFS(#REF!,#REF!,Plano_Detalhado!E59,#REF!,Plano_Detalhado!F59) -> #REF! | J59: =I59/8 -> #REF! | K59: =SUMIFS(#REF!,#REF!,Plano_Detalhado!E59,#REF!,Plano_Detalhado!F59) -> #REF! | L59: =K59/8 -> #REF! | N59: =L59/J59 -> #REF! | O59: =N59-M59 -> #REF! | P59: sem pendencia
A60: =E60&F60 -> ENERGY_CERTIFICATE_EST_INPUTPROPERTY_CONTRACT_ID | B60: Pilar III | C60: Bens Imóveis - Input | D60: 2. Campo | E60: ENERGY_CERTIFICATE_EST_INPUT | F60: PROPERTY_CONTRACT_ID | G60: =INDEX(#REF!,MATCH(Plano_Detalhado!H60,#REF!,0),1) -> #REF! | H60: =VLOOKUP(A60,#REF!,2,0) -> #REF! | I60: =SUMIFS(#REF!,#REF!,Plano_Detalhado!E60,#REF!,Plano_Detalhado!F60) -> #REF! | J60: =I60/8 -> #REF! | K60: =SUMIFS(#REF!,#REF!,Plano_Detalhado!E60,#REF!,Plano_Detalhado!F60) -> #REF! | L60: =K60/8 -> #REF! | N60: =L60/J60 -> #REF! | O60: =N60-M60 -> #REF! | P60: sem pendencia
A61: =E61&F61 -> ENERGY_CERTIFICATE_EST_INPUTPROPERTY_REFERENCE_CODE | B61: Pilar III | C61: Bens Imóveis - Input | D61: 2. Campo | E61: ENERGY_CERTIFICATE_EST_INPUT | F61: PROPERTY_REFERENCE_CODE | G61: =INDEX(#REF!,MATCH(Plano_Detalhado!H61,#REF!,0),1) -> #REF! | H61: =VLOOKUP(A61,#REF!,2,0) -> #REF! | I61: =SUMIFS(#REF!,#REF!,Plano_Detalhado!E61,#REF!,Plano_Detalhado!F61) -> #REF! | J61: =I61/8 -> #REF! | K61: =SUMIFS(#REF!,#REF!,Plano_Detalhado!E61,#REF!,Plano_Detalhado!F61) -> #REF! | L61: =K61/8 -> #REF! | N61: =L61/J61 -> #REF! | O61: =N61-M61 -> #REF! | P61: sem pendencia
A62: =E62&F62 -> ENERGY_CERTIFICATE_EST_INPUTDATA_EXTRACTION_DATE | B62: Pilar III | C62: Bens Imóveis - Input | D62: 2. Campo | E62: ENERGY_CERTIFICATE_EST_INPUT | F62: DATA_EXTRACTION_DATE | G62: =INDEX(#REF!,MATCH(Plano_Detalhado!H62,#REF!,0),1) -> #REF! | H62: =VLOOKUP(A62,#REF!,2,0) -> #REF! | I62: =SUMIFS(#REF!,#REF!,Plano_Detalhado!E62,#REF!,Plano_Detalhado!F62) -> #REF! | J62: =I62/8 -> #REF! | K62: =SUMIFS(#REF!,#REF!,Plano_Detalhado!E62,#REF!,Plano_Detalhado!F62) -> #REF! | L62: =K62/8 -> #REF! | N62: =L62/J62 -> #REF! | O62: =N62-M62 -> #REF! | P62: sem pendencia
A63: =E63&F63 -> ENERGY_CERTIFICATE_EST_INPUTEPC | B63: Pilar III | C63: Bens Imóveis - Input | D63: 2. Campo | E63: ENERGY_CERTIFICATE_EST_INPUT | F63: EPC | G63: =INDEX(#REF!,MATCH(Plano_Detalhado!H63,#REF!,0),1) -> #REF! | H63: =VLOOKUP(A63,#REF!,2,0) -> #REF! | I63: =SUMIFS(#REF!,#REF!,Plano_Detalhado!E63,#REF!,Plano_Detalhado!F63) -> #REF! | J63: =I63/8 -> #REF! | K63: =SUMIFS(#REF!,#REF!,Plano_Detalhado!E63,#REF!,Plano_Detalhado!F63) -> #REF! | L63: =K63/8 -> #REF! | N63: =L63/J63 -> #REF! | O63: =N63-M63 -> #REF! | P63: sem pendencia
A64: =E64&F64 -> ENERGY_CERTIFICATE_EST_INPUTDATA_PROVIDER | B64: Pilar III | C64: Bens Imóveis - Input | D64: 2. Campo | E64: ENERGY_CERTIFICATE_EST_INPUT | F64: DATA_PROVIDER | G64: =INDEX(#REF!,MATCH(Plano_Detalhado!H64,#REF!,0),1) -> #REF! | H64: =VLOOKUP(A64,#REF!,2,0) -> #REF! | I64: =SUMIFS(#REF!,#REF!,Plano_Detalhado!E64,#REF!,Plano_Detalhado!F64) -> #REF! | J64: =I64/8 -> #REF! | K64: =SUMIFS(#REF!,#REF!,Plano_Detalhado!E64,#REF!,Plano_Detalhado!F64) -> #REF! | L64: =K64/8 -> #REF! | N64: =L64/J64 -> #REF! | O64: =N64-M64 -> #REF! | P64: sem pendencia
A65: =E65&F65 -> ENERGY_CERTIFICATE_EST_INPUTACTUAL_VALUE_IND | B65: Pilar III | C65: Bens Imóveis - Input | D65: 2. Campo | E65: ENERGY_CERTIFICATE_EST_INPUT | F65: ACTUAL_VALUE_IND | G65: =INDEX(#REF!,MATCH(Plano_Detalhado!H65,#REF!,0),1) -> #REF! | H65: =VLOOKUP(A65,#REF!,2,0) -> #REF! | I65: =SUMIFS(#REF!,#REF!,Plano_Detalhado!E65,#REF!,Plano_Detalhado!F65) -> #REF! | J65: =I65/8 -> #REF! | K65: =SUMIFS(#REF!,#REF!,Plano_Detalhado!E65,#REF!,Plano_Detalhado!F65) -> #REF! | L65: =K65/8 -> #REF! | N65: =L65/J65 -> #REF! | O65: =N65-M65 -> #REF! | P65: sem pendencia
A66: =E66&F66 -> ENERGY_CERTIFICATE_EST_INPUTQUALITY_SCORE | B66: Pilar III | C66: Bens Imóveis - Input | D66: 2. Campo | E66: ENERGY_CERTIFICATE_EST_INPUT | F66: QUALITY_SCORE | G66: =INDEX(#REF!,MATCH(Plano_Detalhado!H66,#REF!,0),1) -> #REF! | H66: =VLOOKUP(A66,#REF!,2,0) -> #REF! | I66: =SUMIFS(#REF!,#REF!,Plano_Detalhado!E66,#REF!,Plano_Detalhado!F66) -> #REF! | J66: =I66/8 -> #REF! | K66: =SUMIFS(#REF!,#REF!,Plano_Detalhado!E66,#REF!,Plano_Detalhado!F66) -> #REF! | L66: =K66/8 -> #REF! | N66: =L66/J66 -> #REF! | O66: =N66-M66 -> #REF! | P66: sem pendencia
A67: =E67&F67 -> ENERGY_CERTIFICATE_EST_INPUTENERGY_CONSUMPTION_VALUE_YEAR | B67: Pilar III | C67: Bens Imóveis - Input | D67: 2. Campo | E67: ENERGY_CERTIFICATE_EST_INPUT | F67: ENERGY_CONSUMPTION_VALUE_YEAR | G67: =INDEX(#REF!,MATCH(Plano_Detalhado!H67,#REF!,0),1) -> #REF! | H67: =VLOOKUP(A67,#REF!,2,0) -> #REF! | I67: =SUMIFS(#REF!,#REF!,Plano_Detalhado!E67,#REF!,Plano_Detalhado!F67) -> #REF! | J67: =I67/8 -> #REF! | K67: =SUMIFS(#REF!,#REF!,Plano_Detalhado!E67,#REF!,Plano_Detalhado!F67) -> #REF! | L67: =K67/8 -> #REF! | N67: =L67/J67 -> #REF! | O67: =N67-M67 -> #REF! | P67: sem pendencia
A68: =E68&F68 -> ENERGY_CERTIFICATE_EST_INPUTCARBON_EMISSION_VALUE_YEAR | B68: Pilar III | C68: Bens Imóveis - Input | D68: 2. Campo | E68: ENERGY_CERTIFICATE_EST_INPUT | F68: CARBON_EMISSION_VALUE_YEAR | G68: =INDEX(#REF!,MATCH(Plano_Detalhado!H68,#REF!,0),1) -> #REF! | H68: =VLOOKUP(A68,#REF!,2,0) -> #REF! | I68: =SUMIFS(#REF!,#REF!,Plano_Detalhado!E68,#REF!,Plano_Detalhado!F68) -> #REF! | J68: =I68/8 -> #REF! | K68: =SUMIFS(#REF!,#REF!,Plano_Detalhado!E68,#REF!,Plano_Detalhado!F68) -> #REF! | L68: =K68/8 -> #REF! | N68: =L68/J68 -> #REF! | O68: =N68-M68 -> #REF! | P68: sem pendencia
A69: =E69&F69 -> Re-testesn.a. | B69: Pilar III | C69: Bens Imóveis - Input | D69: 2. Campo | E69: Re-testes | F69: n.a. | G69: 7. Por iniciar | I69: =SUM(I56:I68)*#REF! -> #REF! | J69: =I69/8 -> #REF! | K69: =SUM(K56:K68)*#REF! -> #REF! | L69: =K69/8 -> #REF! | N69: =L69/J69 -> #REF! | O69: =N69-M69 -> #REF! | P69: sem pendencia
A70: =E70&F70 | B70: Pilar III | C70: Bens Imóveis - Output | I70: =SUM(I71:I233) -> #REF! | J70: =ROUNDUP(I70/8,0) -> #REF! | K70: =SUM(K71:K233) -> #REF! | L70: =ROUNDUP(K70/8,0) -> #REF! | M70: =SUMIFS(Q70:CA70,#REF!,"S")/J70 -> #REF! | N70: =IFERROR(L70/J70,0) -> 0 | O70: =N70-M70 -> #REF! | P70: - Pendência de reprocessamento de IT: Tabela de certificados energéticos. | BI70: 2 | BJ70: 0.5 | BK70: 2 | BL70: 2 | BM70: 2 | BO70: 0.5 | BP70: 2 | BQ70: 2 | BR70: 2 | BS70: 2 | BT70: 1.5 | BU70: 2 | BV70: 2 | BW70: 2 | BX70: 2 | BY70: 2 | BZ70: 2 | CA70: 2
A71: =E71&F71 -> PROCESSn.a. | B71: Pilar III | C71: Bens Imóveis - Output | D71: 1. Universo | E71: PROCESS | F71: n.a. | G71: =INDEX(#REF!,MATCH(Plano_Detalhado!H71,#REF!,0),1) -> #REF! | H71: =VLOOKUP(A71,#REF!,2,0) -> #REF! | I71: =SUMIFS(#REF!,#REF!,Plano_Detalhado!E71,#REF!,Plano_Detalhado!F71) -> #REF! | J71: =I71/8 -> #REF! | K71: =SUMIFS(#REF!,#REF!,Plano_Detalhado!E71,#REF!,Plano_Detalhado!F71) -> #REF! | L71: =K71/8 -> #REF! | N71: =L71/J71 -> #REF! | O71: =N71-M71 -> #REF! | P71: cd_imv_out_trz_cred_prc
A72: =E72&F72 -> PROCESSPROCESS_BANK_ID | B72: Pilar III | C72: Bens Imóveis - Output | D72: 2. Campo | E72: PROCESS | F72: PROCESS_BANK_ID | G72: =INDEX(#REF!,MATCH(Plano_Detalhado!H72,#REF!,0),1) -> #REF! | H72: =VLOOKUP(A72,#REF!,2,0) -> #REF! | I72: =SUMIFS(#REF!,#REF!,Plano_Detalhado!E72,#REF!,Plano_Detalhado!F72) -> #REF! | J72: =I72/8 -> #REF! | K72: =SUMIFS(#REF!,#REF!,Plano_Detalhado!E72,#REF!,Plano_Detalhado!F72) -> #REF! | L72: =K72/8 -> #REF! | N72: =L72/J72 -> #REF! | O72: =N72-M72 -> #REF! | P72: cd_imv_out_trz_cred_prc
A73: =E73&F73 -> PROCESSPROCESS_BRANCH_CODE | B73: Pilar III | C73: Bens Imóveis - Output | D73: 2. Campo | E73: PROCESS | F73: PROCESS_BRANCH_CODE | G73: =INDEX(#REF!,MATCH(Plano_Detalhado!H73,#REF!,0),1) -> #REF! | H73: =VLOOKUP(A73,#REF!,2,0) -> #REF! | I73: =SUMIFS(#REF!,#REF!,Plano_Detalhado!E73,#REF!,Plano_Detalhado!F73) -> #REF! | J73: =I73/8 -> #REF! | K73: =SUMIFS(#REF!,#REF!,Plano_Detalhado!E73,#REF!,Plano_Detalhado!F73) -> #REF! | L73: =K73/8 -> #REF! | N73: =L73/J73 -> #REF! | O73: =N73-M73 -> #REF! | P73: cd_imv_out_trz_cred_prc
A74: =E74&F74 -> PROCESSPROCESS_ACCOUNT_ID | B74: Pilar III | C74: Bens Imóveis - Output | D74: 2. Campo | E74: PROCESS | F74: PROCESS_ACCOUNT_ID | G74: =INDEX(#REF!,MATCH(Plano_Detalhado!H74,#REF!,0),1) -> #REF! | H74: =VLOOKUP(A74,#REF!,2,0) -> #REF! | I74: =SUMIFS(#REF!,#REF!,Plano_Detalhado!E74,#REF!,Plano_Detalhado!F74) -> #REF! | J74: =I74/8 -> #REF! | K74: =SUMIFS(#REF!,#REF!,Plano_Detalhado!E74,#REF!,Plano_Detalhado!F74) -> #REF! | L74: =K74/8 -> #REF! | N74: =L74/J74 -> #REF! | O74: =N74-M74 -> #REF! | P74: cd_imv_out_trz_cred_prc
A75: =E75&F75 -> PROCESScod_estd_prcs | B75: Pilar III | C75: Bens Imóveis - Output | D75: 2. Campo | E75: PROCESS | F75: cod_estd_prcs | G75: =INDEX(#REF!,MATCH(Plano_Detalhado!H75,#REF!,0),1) -> #REF! | H75: =VLOOKUP(A75,#REF!,2,0) -> #REF! | I75: 0 | J75: =I75/8 -> 0 | K75: =SUMIFS(#REF!,#REF!,Plano_Detalhado!E75,#REF!,Plano_Detalhado!F75) -> #REF! | L75: =K75/8 -> #REF! | N75: =L75/J75 -> #REF! | O75: =N75-M75 -> #REF! | P75: cd_imv_out_trz_cred_prc
A76: =E76&F76 -> PROCESSGUARANTEE_CODE | B76: Pilar III | C76: Bens Imóveis - Output | D76: 2. Campo | E76: PROCESS | F76: GUARANTEE_CODE | G76: =INDEX(#REF!,MATCH(Plano_Detalhado!H76,#REF!,0),1) -> #REF! | H76: =VLOOKUP(A76,#REF!,2,0) -> #REF! | I76: =SUMIFS(#REF!,#REF!,Plano_Detalhado!E76,#REF!,Plano_Detalhado!F76) -> #REF! | J76: =I76/8 -> #REF! | K76: =SUMIFS(#REF!,#REF!,Plano_Detalhado!E76,#REF!,Plano_Detalhado!F76) -> #REF! | L76: =K76/8 -> #REF! | N76: =L76/J76 -> #REF! | O76: =N76-M76 -> #REF! | P76: cd_imv_out_trz_cred_prc
A77: =E77&F77 -> PROCESSCURRENCY_CODE | B77: Pilar III | C77: Bens Imóveis - Output | D77: 2. Campo | E77: PROCESS | F77: CURRENCY_CODE | G77: =INDEX(#REF!,MATCH(Plano_Detalhado!H77,#REF!,0),1) -> #REF! | H77: =VLOOKUP(A77,#REF!,2,0) -> #REF! | I77: =SUMIFS(#REF!,#REF!,Plano_Detalhado!E77,#REF!,Plano_Detalhado!F77) -> #REF! | J77: =I77/8 -> #REF! | K77: =SUMIFS(#REF!,#REF!,Plano_Detalhado!E77,#REF!,Plano_Detalhado!F77) -> #REF! | L77: =K77/8 -> #REF! | N77: =L77/J77 -> #REF! | O77: =N77-M77 -> #REF! | P77: cd_imv_out_trz_cred_prc
A78: =E78&F78 -> PROCESSPROCESS_CAMPAIGN_CODE | B78: Pilar III | C78: Bens Imóveis - Output | D78: 2. Campo | E78: PROCESS | F78: PROCESS_CAMPAIGN_CODE | G78: =INDEX(#REF!,MATCH(Plano_Detalhado!H78,#REF!,0),1) -> #REF! | H78: =VLOOKUP(A78,#REF!,2,0) -> #REF! | I78: =SUMIFS(#REF!,#REF!,Plano_Detalhado!E78,#REF!,Plano_Detalhado!F78) -> #REF! | J78: =I78/8 -> #REF! | K78: =SUMIFS(#REF!,#REF!,Plano_Detalhado!E78,#REF!,Plano_Detalhado!F78) -> #REF! | L78: =K78/8 -> #REF! | N78: =L78/J78 -> #REF! | O78: =N78-M78 -> #REF! | P78: cd_imv_out_trz_cred_prc
A79: =E79&F79 -> PROCESSPROCESS_PRODUCT_ID | B79: Pilar III | C79: Bens Imóveis - Output | D79: 2. Campo | E79: PROCESS | F79: PROCESS_PRODUCT_ID | G79: =INDEX(#REF!,MATCH(Plano_Detalhado!H79,#REF!,0),1) -> #REF! | H79: =VLOOKUP(A79,#REF!,2,0) -> #REF! | I79: =SUMIFS(#REF!,#REF!,Plano_Detalhado!E79,#REF!,Plano_Detalhado!F79) -> #REF! | J79: =I79/8 -> #REF! | K79: =SUMIFS(#REF!,#REF!,Plano_Detalhado!E79,#REF!,Plano_Detalhado!F79) -> #REF! | L79: =K79/8 -> #REF! | N79: =L79/J79 -> #REF! | O79: =N79-M79 -> #REF! | P79: cd_imv_out_trz_cred_prc
A80: =E80&F80 -> PROCESSPROCESS_SUBPRODUCT_ID | B80: Pilar III | C80: Bens Imóveis - Output | D80: 2. Campo | E80: PROCESS | F80: PROCESS_SUBPRODUCT_ID | G80: =INDEX(#REF!,MATCH(Plano_Detalhado!H80,#REF!,0),1) -> #REF! | H80: =VLOOKUP(A80,#REF!,2,0) -> #REF! | I80: =SUMIFS(#REF!,#REF!,Plano_Detalhado!E80,#REF!,Plano_Detalhado!F80) -> #REF! | J80: =I80/8 -> #REF! | K80: =SUMIFS(#REF!,#REF!,Plano_Detalhado!E80,#REF!,Plano_Detalhado!F80) -> #REF! | L80: =K80/8 -> #REF! | N80: =L80/J80 -> #REF! | O80: =N80-M80 -> #REF! | P80: cd_imv_out_trz_cred_prc
A81: =E81&F81 -> PROCESSGUARANTEE_TYPE_CODE | B81: Pilar III | C81: Bens Imóveis - Output | D81: 2. Campo | E81: PROCESS | F81: GUARANTEE_TYPE_CODE | G81: =INDEX(#REF!,MATCH(Plano_Detalhado!H81,#REF!,0),1) -> #REF! | H81: =VLOOKUP(A81,#REF!,2,0) -> #REF! | I81: =SUMIFS(#REF!,#REF!,Plano_Detalhado!E81,#REF!,Plano_Detalhado!F81) -> #REF! | J81: =I81/8 -> #REF! | K81: =SUMIFS(#REF!,#REF!,Plano_Detalhado!E81,#REF!,Plano_Detalhado!F81) -> #REF! | L81: =K81/8 -> #REF! | N81: =L81/J81 -> #REF! | O81: =N81-M81 -> #REF! | P81: cd_imv_out_trz_cred_prc
A82: =E82&F82 -> PROCESSPROCESS_REFERENCE_CODE | B82: Pilar III | C82: Bens Imóveis - Output | D82: 2. Campo | E82: PROCESS | F82: PROCESS_REFERENCE_CODE | G82: =INDEX(#REF!,MATCH(Plano_Detalhado!H82,#REF!,0),1) -> #REF! | H82: =VLOOKUP(A82,#REF!,2,0) -> #REF! | I82: =SUMIFS(#REF!,#REF!,Plano_Detalhado!E82,#REF!,Plano_Detalhado!F82) -> #REF! | J82: =I82/8 -> #REF! | K82: =SUMIFS(#REF!,#REF!,Plano_Detalhado!E82,#REF!,Plano_Detalhado!F82) -> #REF! | L82: =K82/8 -> #REF! | N82: =L82/J82 -> #REF! | O82: =N82-M82 -> #REF! | P82: cd_imv_out_trz_cred_prc
A83: =E83&F83 -> PROCESSPROCESS_START_DATE | B83: Pilar III | C83: Bens Imóveis - Output | D83: 2. Campo | E83: PROCESS | F83: PROCESS_START_DATE | G83: =INDEX(#REF!,MATCH(Plano_Detalhado!H83,#REF!,0),1) -> #REF! | H83: =VLOOKUP(A83,#REF!,2,0) -> #REF! | I83: =SUMIFS(#REF!,#REF!,Plano_Detalhado!E83,#REF!,Plano_Detalhado!F83) -> #REF! | J83: =I83/8 -> #REF! | K83: =SUMIFS(#REF!,#REF!,Plano_Detalhado!E83,#REF!,Plano_Detalhado!F83) -> #REF! | L83: =K83/8 -> #REF! | N83: =L83/J83 -> #REF! | O83: =N83-M83 -> #REF! | P83: cd_imv_out_trz_cred_prc
A84: =E84&F84 -> PROCESSPROCESS_DUE_DATE | B84: Pilar III | C84: Bens Imóveis - Output | D84: 2. Campo | E84: PROCESS | F84: PROCESS_DUE_DATE | G84: =INDEX(#REF!,MATCH(Plano_Detalhado!H84,#REF!,0),1) -> #REF! | H84: =VLOOKUP(A84,#REF!,2,0) -> #REF! | I84: =SUMIFS(#REF!,#REF!,Plano_Detalhado!E84,#REF!,Plano_Detalhado!F84) -> #REF! | J84: =I84/8 -> #REF! | K84: =SUMIFS(#REF!,#REF!,Plano_Detalhado!E84,#REF!,Plano_Detalhado!F84) -> #REF! | L84: =K84/8 -> #REF! | N84: =L84/J84 -> #REF! | O84: =N84-M84 -> #REF! | P84: cd_imv_out_trz_cred_prc
A85: =E85&F85 -> PROCESSmontante_eur | B85: Pilar III | C85: Bens Imóveis - Output | D85: 2. Campo | E85: PROCESS | F85: montante_eur | G85: =INDEX(#REF!,MATCH(Plano_Detalhado!H85,#REF!,0),1) -> #REF! | H85: =VLOOKUP(A85,#REF!,2,0) -> #REF! | I85: 0 | J85: =I85/8 -> 0 | K85: =SUMIFS(#REF!,#REF!,Plano_Detalhado!E85,#REF!,Plano_Detalhado!F85) -> #REF! | L85: =K85/8 -> #REF! | N85: =L85/J85 -> #REF! | O85: =N85-M85 -> #REF! | P85: cd_imv_out_trz_cred_prc
A86: =E86&F86 -> PROCESSmontante_org | B86: Pilar III | C86: Bens Imóveis - Output | D86: 2. Campo | E86: PROCESS | F86: montante_org | G86: =INDEX(#REF!,MATCH(Plano_Detalhado!H86,#REF!,0),1) -> #REF! | H86: =VLOOKUP(A86,#REF!,2,0) -> #REF! | I86: 0 | J86: =I86/8 -> 0 | K86: =SUMIFS(#REF!,#REF!,Plano_Detalhado!E86,#REF!,Plano_Detalhado!F86) -> #REF! | L86: =K86/8 -> #REF! | N86: =L86/J86 -> #REF! | O86: =N86-M86 -> #REF! | P86: cd_imv_out_trz_cred_prc
A87: =E87&F87 -> PROCESSorigem | B87: Pilar III | C87: Bens Imóveis - Output | D87: 2. Campo | E87: PROCESS | F87: origem | G87: =INDEX(#REF!,MATCH(Plano_Detalhado!H87,#REF!,0),1) -> #REF! | H87: =VLOOKUP(A87,#REF!,2,0) -> #REF! | I87: =SUMIFS(#REF!,#REF!,Plano_Detalhado!E87,#REF!,Plano_Detalhado!F87) -> #REF! | J87: =I87/8 -> #REF! | K87: =SUMIFS(#REF!,#REF!,Plano_Detalhado!E87,#REF!,Plano_Detalhado!F87) -> #REF! | L87: =K87/8 -> #REF! | N87: =L87/J87 -> #REF! | O87: =N87-M87 -> #REF! | P87: cd_imv_out_trz_cred_prc
A88: =E88&F88 -> PROCESSDATA_DATE_PART | B88: Pilar III | C88: Bens Imóveis - Output | D88: 2. Campo | E88: PROCESS | F88: DATA_DATE_PART | G88: =INDEX(#REF!,MATCH(Plano_Detalhado!H88,#REF!,0),1) -> #REF! | H88: =VLOOKUP(A88,#REF!,2,0) -> #REF! | I88: =SUMIFS(#REF!,#REF!,Plano_Detalhado!E88,#REF!,Plano_Detalhado!F88) -> #REF! | J88: =I88/8 -> #REF! | K88: =SUMIFS(#REF!,#REF!,Plano_Detalhado!E88,#REF!,Plano_Detalhado!F88) -> #REF! | L88: =K88/8 -> #REF! | N88: =L88/J88 -> #REF! | O88: =N88-M88 -> #REF! | P88: cd_imv_out_trz_cred_prc
A89: =E89&F89 -> RESPONSIBILITY_PROCESS_RELn.a. | B89: Pilar III | C89: Bens Imóveis - Output | D89: 1. Universo | E89: RESPONSIBILITY_PROCESS_REL | F89: n.a. | G89: =INDEX(#REF!,MATCH(Plano_Detalhado!H89,#REF!,0),1) -> #REF! | H89: =VLOOKUP(A89,#REF!,2,0) -> #REF! | I89: =SUMIFS(#REF!,#REF!,Plano_Detalhado!E89,#REF!,Plano_Detalhado!F89) -> #REF! | J89: =I89/8 -> #REF! | K89: =SUMIFS(#REF!,#REF!,Plano_Detalhado!E89,#REF!,Plano_Detalhado!F89) -> #REF! | L89: =K89/8 -> #REF! | N89: =L89/J89 -> #REF! | O89: =N89-M89 -> #REF! | P89: sem pendencia
A90: =E90&F90 -> RESPONSIBILITY_PROCESS_RELPROCESS_BANK_ID | B90: Pilar III | C90: Bens Imóveis - Output | D90: 2. Campo | E90: RESPONSIBILITY_PROCESS_REL | F90: PROCESS_BANK_ID | G90: =INDEX(#REF!,MATCH(Plano_Detalhado!H90,#REF!,0),1) -> #REF! | H90: =VLOOKUP(A90,#REF!,2,0) -> #REF! | I90: =SUMIFS(#REF!,#REF!,Plano_Detalhado!E90,#REF!,Plano_Detalhado!F90) -> #REF! | J90: =I90/8 -> #REF! | K90: =SUMIFS(#REF!,#REF!,Plano_Detalhado!E90,#REF!,Plano_Detalhado!F90) -> #REF! | L90: =K90/8 -> #REF! | N90: =L90/J90 -> #REF! | O90: =N90-M90 -> #REF! | P90: sem pendencia
A91: =E91&F91 -> RESPONSIBILITY_PROCESS_RELBANK_ID | B91: Pilar III | C91: Bens Imóveis - Output | D91: 2. Campo | E91: RESPONSIBILITY_PROCESS_REL | F91: BANK_ID | G91: =INDEX(#REF!,MATCH(Plano_Detalhado!H91,#REF!,0),1) -> #REF! | H91: =VLOOKUP(A91,#REF!,2,0) -> #REF! | I91: =SUMIFS(#REF!,#REF!,Plano_Detalhado!E91,#REF!,Plano_Detalhado!F91) -> #REF! | J91: =I91/8 -> #REF! | K91: =SUMIFS(#REF!,#REF!,Plano_Detalhado!E91,#REF!,Plano_Detalhado!F91) -> #REF! | L91: =K91/8 -> #REF! | N91: =L91/J91 -> #REF! | O91: =N91-M91 -> #REF! | P91: sem pendencia
A92: =E92&F92 -> RESPONSIBILITY_PROCESS_RELPROCESS_BRANCH_CODE | B92: Pilar III | C92: Bens Imóveis - Output | D92: 2. Campo | E92: RESPONSIBILITY_PROCESS_REL | F92: PROCESS_BRANCH_CODE | G92: =INDEX(#REF!,MATCH(Plano_Detalhado!H92,#REF!,0),1) -> #REF! | H92: =VLOOKUP(A92,#REF!,2,0) -> #REF! | I92: =SUMIFS(#REF!,#REF!,Plano_Detalhado!E92,#REF!,Plano_Detalhado!F92) -> #REF! | J92: =I92/8 -> #REF! | K92: =SUMIFS(#REF!,#REF!,Plano_Detalhado!E92,#REF!,Plano_Detalhado!F92) -> #REF! | L92: =K92/8 -> #REF! | N92: =L92/J92 -> #REF! | O92: =N92-M92 -> #REF! | P92: sem pendencia
A93: =E93&F93 -> RESPONSIBILITY_PROCESS_RELBRANCH_CODE | B93: Pilar III | C93: Bens Imóveis - Output | D93: 2. Campo | E93: RESPONSIBILITY_PROCESS_REL | F93: BRANCH_CODE | G93: =INDEX(#REF!,MATCH(Plano_Detalhado!H93,#REF!,0),1) -> #REF! | H93: =VLOOKUP(A93,#REF!,2,0) -> #REF! | I93: =SUMIFS(#REF!,#REF!,Plano_Detalhado!E93,#REF!,Plano_Detalhado!F93) -> #REF! | J93: =I93/8 -> #REF! | K93: =SUMIFS(#REF!,#REF!,Plano_Detalhado!E93,#REF!,Plano_Detalhado!F93) -> #REF! | L93: =K93/8 -> #REF! | N93: =L93/J93 -> #REF! | O93: =N93-M93 -> #REF! | P93: sem pendencia
A94: =E94&F94 -> RESPONSIBILITY_PROCESS_RELCONTRACT_ID | B94: Pilar III | C94: Bens Imóveis - Output | D94: 2. Campo | E94: RESPONSIBILITY_PROCESS_REL | F94: CONTRACT_ID | G94: =INDEX(#REF!,MATCH(Plano_Detalhado!H94,#REF!,0),1) -> #REF! | H94: =VLOOKUP(A94,#REF!,2,0) -> #REF! | I94: =SUMIFS(#REF!,#REF!,Plano_Detalhado!E94,#REF!,Plano_Detalhado!F94) -> #REF! | J94: =I94/8 -> #REF! | K94: =SUMIFS(#REF!,#REF!,Plano_Detalhado!E94,#REF!,Plano_Detalhado!F94) -> #REF! | L94: =K94/8 -> #REF! | N94: =L94/J94 -> #REF! | O94: =N94-M94 -> #REF! | P94: sem pendencia
A95: =E95&F95 -> RESPONSIBILITY_PROCESS_RELPROCESS_ACCOUNT_ID | B95: Pilar III | C95: Bens Imóveis - Output | D95: 2. Campo | E95: RESPONSIBILITY_PROCESS_REL | F95: PROCESS_ACCOUNT_ID | G95: =INDEX(#REF!,MATCH(Plano_Detalhado!H95,#REF!,0),1) -> #REF! | H95: =VLOOKUP(A95,#REF!,2,0) -> #REF! | I95: =SUMIFS(#REF!,#REF!,Plano_Detalhado!E95,#REF!,Plano_Detalhado!F95) -> #REF! | J95: =I95/8 -> #REF! | K95: =SUMIFS(#REF!,#REF!,Plano_Detalhado!E95,#REF!,Plano_Detalhado!F95) -> #REF! | L95: =K95/8 -> #REF! | N95: =L95/J95 -> #REF! | O95: =N95-M95 -> #REF! | P95: sem pendencia
A96: =E96&F96 -> RESPONSIBILITY_PROCESS_RELREFERENCE_CODE | B96: Pilar III | C96: Bens Imóveis - Output | D96: 2. Campo | E96: RESPONSIBILITY_PROCESS_REL | F96: REFERENCE_CODE | G96: =INDEX(#REF!,MATCH(Plano_Detalhado!H96,#REF!,0),1) -> #REF! | H96: =VLOOKUP(A96,#REF!,2,0) -> #REF! | I96: =SUMIFS(#REF!,#REF!,Plano_Detalhado!E96,#REF!,Plano_Detalhado!F96) -> #REF! | J96: =I96/8 -> #REF! | K96: =SUMIFS(#REF!,#REF!,Plano_Detalhado!E96,#REF!,Plano_Detalhado!F96) -> #REF! | L96: =K96/8 -> #REF! | N96: =L96/J96 -> #REF! | O96: =N96-M96 -> #REF! | P96: sem pendencia
A97: =E97&F97 -> RESPONSIBILITY_PROCESS_RELPURPOSE_CODE | B97: Pilar III | C97: Bens Imóveis - Output | D97: 2. Campo | E97: RESPONSIBILITY_PROCESS_REL | F97: PURPOSE_CODE | G97: =INDEX(#REF!,MATCH(Plano_Detalhado!H97,#REF!,0),1) -> #REF! | H97: =VLOOKUP(A97,#REF!,2,0) -> #REF! | I97: =SUMIFS(#REF!,#REF!,Plano_Detalhado!E97,#REF!,Plano_Detalhado!F97) -> #REF! | J97: =I97/8 -> #REF! | K97: =SUMIFS(#REF!,#REF!,Plano_Detalhado!E97,#REF!,Plano_Detalhado!F97) -> #REF! | L97: =K97/8 -> #REF! | N97: =L97/J97 -> #REF! | O97: =N97-M97 -> #REF! | P97: sem pendencia
A98: =E98&F98 -> RESPONSIBILITY_PROCESS_RELINDIVIDUAL_OCCUPATION_CODE | B98: Pilar III | C98: Bens Imóveis - Output | D98: 2. Campo | E98: RESPONSIBILITY_PROCESS_REL | F98: INDIVIDUAL_OCCUPATION_CODE | G98: =INDEX(#REF!,MATCH(Plano_Detalhado!H98,#REF!,0),1) -> #REF! | H98: =VLOOKUP(A98,#REF!,2,0) -> #REF! | I98: =SUMIFS(#REF!,#REF!,Plano_Detalhado!E98,#REF!,Plano_Detalhado!F98) -> #REF! | J98: =I98/8 -> #REF! | K98: =SUMIFS(#REF!,#REF!,Plano_Detalhado!E98,#REF!,Plano_Detalhado!F98) -> #REF! | L98: =K98/8 -> #REF! | N98: =L98/J98 -> #REF! | O98: =N98-M98 -> #REF! | P98: sem pendencia
A99: =E99&F99 -> RESPONSIBILITY_PROCESS_RELPRODUCT_ID | B99: Pilar III | C99: Bens Imóveis - Output | D99: 2. Campo | E99: RESPONSIBILITY_PROCESS_REL | F99: PRODUCT_ID | G99: =INDEX(#REF!,MATCH(Plano_Detalhado!H99,#REF!,0),1) -> #REF! | H99: =VLOOKUP(A99,#REF!,2,0) -> #REF! | I99: =SUMIFS(#REF!,#REF!,Plano_Detalhado!E99,#REF!,Plano_Detalhado!F99) -> #REF! | J99: =I99/8 -> #REF! | K99: =SUMIFS(#REF!,#REF!,Plano_Detalhado!E99,#REF!,Plano_Detalhado!F99) -> #REF! | L99: =K99/8 -> #REF! | N99: =L99/J99 -> #REF! | O99: =N99-M99 -> #REF! | P99: sem pendencia
A100: =E100&F100 -> RESPONSIBILITY_PROCESS_RELcod_sit | B100: Pilar III | C100: Bens Imóveis - Output | D100: 2. Campo | E100: RESPONSIBILITY_PROCESS_REL | F100: cod_sit | G100: =INDEX(#REF!,MATCH(Plano_Detalhado!H100,#REF!,0),1) -> #REF! | H100: =VLOOKUP(A100,#REF!,2,0) -> #REF! | I100: 0 | J100: =I100/8 -> 0 | K100: =SUMIFS(#REF!,#REF!,Plano_Detalhado!E100,#REF!,Plano_Detalhado!F100) -> #REF! | L100: =K100/8 -> #REF! | N100: =L100/J100 -> #REF! | O100: =N100-M100 -> #REF! | P100: sem pendencia
A101: =E101&F101 -> RESPONSIBILITY_PROCESS_RELSUBPRODUCT_ID | B101: Pilar III | C101: Bens Imóveis - Output | D101: 2. Campo | E101: RESPONSIBILITY_PROCESS_REL | F101: SUBPRODUCT_ID | G101: =INDEX(#REF!,MATCH(Plano_Detalhado!H101,#REF!,0),1) -> #REF! | H101: =VLOOKUP(A101,#REF!,2,0) -> #REF! | I101: =SUMIFS(#REF!,#REF!,Plano_Detalhado!E101,#REF!,Plano_Detalhado!F101) -> #REF! | J101: =I101/8 -> #REF! | K101: =SUMIFS(#REF!,#REF!,Plano_Detalhado!E101,#REF!,Plano_Detalhado!F101) -> #REF! | L101: =K101/8 -> #REF! | N101: =L101/J101 -> #REF! | O101: =N101-M101 -> #REF! | P101: sem pendencia
A102: =E102&F102 -> RESPONSIBILITY_PROCESS_RELPROCESS_REFERENCE_CODE | B102: Pilar III | C102: Bens Imóveis - Output | D102: 2. Campo | E102: RESPONSIBILITY_PROCESS_REL | F102: PROCESS_REFERENCE_CODE | G102: =INDEX(#REF!,MATCH(Plano_Detalhado!H102,#REF!,0),1) -> #REF! | H102: =VLOOKUP(A102,#REF!,2,0) -> #REF! | I102: =SUMIFS(#REF!,#REF!,Plano_Detalhado!E102,#REF!,Plano_Detalhado!F102) -> #REF! | J102: =I102/8 -> #REF! | K102: =SUMIFS(#REF!,#REF!,Plano_Detalhado!E102,#REF!,Plano_Detalhado!F102) -> #REF! | L102: =K102/8 -> #REF! | N102: =L102/J102 -> #REF! | O102: =N102-M102 -> #REF! | P102: sem pendencia
A103: =E103&F103 -> RESPONSIBILITY_PROCESS_RELEFFECTIVE_RELATION_END_DATE | B103: Pilar III | C103: Bens Imóveis - Output | D103: 2. Campo | E103: RESPONSIBILITY_PROCESS_REL | F103: EFFECTIVE_RELATION_END_DATE | G103: =INDEX(#REF!,MATCH(Plano_Detalhado!H103,#REF!,0),1) -> #REF! | H103: =VLOOKUP(A103,#REF!,2,0) -> #REF! | I103: =SUMIFS(#REF!,#REF!,Plano_Detalhado!E103,#REF!,Plano_Detalhado!F103) -> #REF! | J103: =I103/8 -> #REF! | K103: =SUMIFS(#REF!,#REF!,Plano_Detalhado!E103,#REF!,Plano_Detalhado!F103) -> #REF! | L103: =K103/8 -> #REF! | N103: =L103/J103 -> #REF! | O103: =N103-M103 -> #REF! | P103: sem pendencia
A104: =E104&F104 -> RESPONSIBILITY_PROCESS_RELPROCESS_START_DATE | B104: Pilar III | C104: Bens Imóveis - Output | D104: 2. Campo | E104: RESPONSIBILITY_PROCESS_REL | F104: PROCESS_START_DATE | G104: =INDEX(#REF!,MATCH(Plano_Detalhado!H104,#REF!,0),1) -> #REF! | H104: =VLOOKUP(A104,#REF!,2,0) -> #REF! | I104: =SUMIFS(#REF!,#REF!,Plano_Detalhado!E104,#REF!,Plano_Detalhado!F104) -> #REF! | J104: =I104/8 -> #REF! | K104: =SUMIFS(#REF!,#REF!,Plano_Detalhado!E104,#REF!,Plano_Detalhado!F104) -> #REF! | L104: =K104/8 -> #REF! | N104: =L104/J104 -> #REF! | O104: =N104-M104 -> #REF! | P104: sem pendencia
A105: =E105&F105 -> RESPONSIBILITY_PROCESS_RELPROCESS_DUE_DATE | B105: Pilar III | C105: Bens Imóveis - Output | D105: 2. Campo | E105: RESPONSIBILITY_PROCESS_REL | F105: PROCESS_DUE_DATE | G105: =INDEX(#REF!,MATCH(Plano_Detalhado!H105,#REF!,0),1) -> #REF! | H105: =VLOOKUP(A105,#REF!,2,0) -> #REF! | I105: =SUMIFS(#REF!,#REF!,Plano_Detalhado!E105,#REF!,Plano_Detalhado!F105) -> #REF! | J105: =I105/8 -> #REF! | K105: =SUMIFS(#REF!,#REF!,Plano_Detalhado!E105,#REF!,Plano_Detalhado!F105) -> #REF! | L105: =K105/8 -> #REF! | N105: =L105/J105 -> #REF! | O105: =N105-M105 -> #REF! | P105: sem pendencia
A106: =E106&F106 -> RESPONSIBILITY_PROCESS_RELidetgar | B106: Pilar III | C106: Bens Imóveis - Output | D106: 2. Campo | E106: RESPONSIBILITY_PROCESS_REL | F106: idetgar | G106: =INDEX(#REF!,MATCH(Plano_Detalhado!H106,#REF!,0),1) -> #REF! | H106: =VLOOKUP(A106,#REF!,2,0) -> #REF! | I106: 0 | J106: =I106/8 -> 0 | K106: =SUMIFS(#REF!,#REF!,Plano_Detalhado!E106,#REF!,Plano_Detalhado!F106) -> #REF! | L106: =K106/8 -> #REF! | N106: =L106/J106 -> #REF! | O106: =N106-M106 -> #REF! | P106: sem pendencia
A107: =E107&F107 -> RESPONSIBILITY_PROCESS_RELnum_prop | B107: Pilar III | C107: Bens Imóveis - Output | D107: 2. Campo | E107: RESPONSIBILITY_PROCESS_REL | F107: num_prop | G107: =INDEX(#REF!,MATCH(Plano_Detalhado!H107,#REF!,0),1) -> #REF! | H107: =VLOOKUP(A107,#REF!,2,0) -> #REF! | I107: 0 | J107: =I107/8 -> 0 | K107: =SUMIFS(#REF!,#REF!,Plano_Detalhado!E107,#REF!,Plano_Detalhado!F107) -> #REF! | L107: =K107/8 -> #REF! | N107: =L107/J107 -> #REF! | O107: =N107-M107 -> #REF! | P107: sem pendencia
...

Sheet Macro_Plano_2025_v1
V6: 2 corresponde a 1 dia de trabalho
V7: 49 dias
N8: Janeiro | R8: Fevereiro | U8: Março
C9: ID | D9: Atividade | G9: Status | H9: # Campos | I9: Duração (semana) | J9: Duração (horas) | L9: 45660 | M9: =L9+7 -> 45667 | N9: =M9+7 -> 45674 | O9: =N9+7 -> 45681 | P9: =O9+7 -> 45688 | Q9: =P9+7 -> 45695 | R9: =Q9+7 -> 45702 | S9: =R9+7 -> 45709 | T9: =S9+7 -> 45716 | ... V9: =U9+7 -> 45730
C11: 0. | D11: Gestão Projeto | H11: n.a. | J11: =SUM(L11:V11)*8 -> 41.6 | L11: =0.1*2 -> 0.2 | M11: =0.1*5 -> 0.5 | N11: =0.1*5 -> 0.5 | O11: =0.1*5 -> 0.5 | P11: =0.1*5 -> 0.5 | Q11: =0.1*5 -> 0.5 | R11: =0.1*5 -> 0.5 | S11: =0.1*5 -> 0.5 | T11: =0.1*5 -> 0.5 | ... V11: =0.1*5 -> 0.5
C13: 1. | D13: Set-Up | H13: n.a. | J13: =SUM(L13:M13)*8 -> 32 | L13: 4
C15: 2. | D15: Assessment ao Green Dashboard (Especificação Atual) | H15: n.a. | J15: =SUM(L15:V15)*8 -> 64 | M15: 8
C17: 3. | D17: Testes regressivos aos campos concluidos do GD (âmbito projeto anterior) | H17: =COUNTA(E18:E40) -> 23 | I17: =SUM(I18:I40) -> #VALUE! | J17: =SUM(J18:J40) -> #VALUE! | M17: 2 | N17: =8.25 -> 8.25
B18: =D18&"_"&E18 -> INSTRUMENT_COD_SOC | C18: 3.1. | D18: INSTRUMENT | E18: COD_SOC | I18: =J18/8/5 -> #VALUE! | J18: =SUMIF([1]Aux!B:B,Macro_Plano_2025_v1!B18,[1]Aux!I:I)+SUMIF([1]Aux!B:B,Macro_Plano_2025_v1!B18,[1]Aux!O:O) -> #VALUE! | M18: =J18/8 -> #VALUE!
B19: =D19&"_"&E19 -> INSTRUMENT_SUBPORTFOLIO_ID | C19: 3.2. | D19: INSTRUMENT | E19: SUBPORTFOLIO_ID | I19: =J19/8/5 -> #VALUE! | J19: =SUMIF([1]Aux!B:B,Macro_Plano_2025_v1!B19,[1]Aux!I:I)+SUMIF([1]Aux!B:B,Macro_Plano_2025_v1!B19,[1]Aux!O:O) -> #VALUE! | M19: =J19/8 -> #VALUE!
B20: =D20&"_"&E20 -> INSTRUMENT_DT_RFRNC | C20: 3.3. | D20: INSTRUMENT | E20: DT_RFRNC | I20: =J20/8/5 -> #VALUE! | J20: =SUMIF([1]Aux!B:B,Macro_Plano_2025_v1!B20,[1]Aux!I:I)+SUMIF([1]Aux!B:B,Macro_Plano_2025_v1!B20,[1]Aux!O:O) -> #VALUE! | M20: =J20/8 -> #VALUE!
B21: =D21&"_"&E21 -> INSTRUMENT_DFLT_STTS_INSTRMNT | C21: 3.4. | D21: INSTRUMENT | E21: DFLT_STTS_INSTRMNT | I21: =J21/8/5 -> #VALUE! | J21: =SUMIF([1]Aux!B:B,Macro_Plano_2025_v1!B21,[1]Aux!I:I)+SUMIF([1]Aux!B:B,Macro_Plano_2025_v1!B21,[1]Aux!O:O) -> #VALUE! | M21: =J21/8 -> #VALUE!
B22: =D22&"_"&E22 -> INSTRUMENT_IMPRMNT_STTS | C22: 3.5. | D22: INSTRUMENT | E22: IMPRMNT_STTS | I22: =J22/8/5 -> #VALUE! | J22: =SUMIF([1]Aux!B:B,Macro_Plano_2025_v1!B22,[1]Aux!I:I)+SUMIF([1]Aux!B:B,Macro_Plano_2025_v1!B22,[1]Aux!O:O) -> #VALUE! | M22: =M17-SUM(M18:M21) -> #VALUE! | N22: =(J22/8)-M22 -> #VALUE!
B23: =D23&"_"&E23 -> INSTRUMENT_PRFRMNG_STTS | C23: 3.6. | D23: INSTRUMENT | E23: PRFRMNG_STTS | I23: =J23/8/5 -> #VALUE! | J23: =SUMIF([1]Aux!B:B,Macro_Plano_2025_v1!B23,[1]Aux!I:I)+SUMIF([1]Aux!B:B,Macro_Plano_2025_v1!B23,[1]Aux!O:O) -> #VALUE! | N23: =J23/8 -> #VALUE!
B24: =D24&"_"&E24 -> INSTRUMENT_TYP_INSTRMNT | C24: 3.7. | D24: INSTRUMENT | E24: TYP_INSTRMNT | I24: =J24/8/5 -> #VALUE! | J24: =SUMIF([1]Aux!B:B,Macro_Plano_2025_v1!B24,[1]Aux!I:I)+SUMIF([1]Aux!B:B,Macro_Plano_2025_v1!B24,[1]Aux!O:O) -> #VALUE! | N24: =J24/8 -> #VALUE!
B25: =D25&"_"&E25 -> INSTRUMENT_GRSS_CRRYNG_AMNT_INSTRMNT | C25: 3.8. | D25: INSTRUMENT | E25: GRSS_CRRYNG_AMNT_INSTRMNT | I25: =J25/8/5 -> #VALUE! | J25: =SUMIF([1]Aux!B:B,Macro_Plano_2025_v1!B25,[1]Aux!I:I)+SUMIF([1]Aux!B:B,Macro_Plano_2025_v1!B25,[1]Aux!O:O) -> #VALUE! | N25: =J25/8 -> #VALUE!
B26: =D26&"_"&E26 -> INSTRUMENT_ACCMLTD_CHNGS_FV_CR_INSTRMNT | C26: 3.9. | D26: INSTRUMENT | E26: ACCMLTD_CHNGS_FV_CR_INSTRMNT | I26: =J26/8/5 -> #VALUE! | J26: =SUMIF([1]Aux!B:B,Macro_Plano_2025_v1!B26,[1]Aux!I:I)+SUMIF([1]Aux!B:B,Macro_Plano_2025_v1!B26,[1]Aux!O:O) -> #VALUE! | N26: =J26/8 -> #VALUE!
B27: =D27&"_"&E27 -> INSTRUMENT_ACCNTNG_CLSSFCTN | C27: 3.10. | D27: INSTRUMENT | E27: ACCNTNG_CLSSFCTN | I27: =J27/8/5 -> #VALUE! | J27: =SUMIF([1]Aux!B:B,Macro_Plano_2025_v1!B27,[1]Aux!I:I)+SUMIF([1]Aux!B:B,Macro_Plano_2025_v1!B27,[1]Aux!O:O) -> #VALUE! | N27: =J27/8 -> #VALUE!
B28: =D28&"_"&E28 -> INSTRUMENT_OFF_BLNC_SHT_AMNT_INSTRMNT | C28: 3.11. | D28: INSTRUMENT | E28: OFF_BLNC_SHT_AMNT_INSTRMNT | I28: =J28/8/5 -> #VALUE! | J28: =SUMIF([1]Aux!B:B,Macro_Plano_2025_v1!B28,[1]Aux!I:I)+SUMIF([1]Aux!B:B,Macro_Plano_2025_v1!B28,[1]Aux!O:O) -> #VALUE! | N28: =J28/8 -> #VALUE!
B29: =D29&"_"&E29 -> INSTRUMENT_PRVSNS_OFF_BLNC_SHT | C29: 3.12. | D29: INSTRUMENT | E29: PRVSNS_OFF_BLNC_SHT | I29: =J29/8/5 -> #VALUE! | J29: =SUMIF([1]Aux!B:B,Macro_Plano_2025_v1!B29,[1]Aux!I:I)+SUMIF([1]Aux!B:B,Macro_Plano_2025_v1!B29,[1]Aux!O:O) -> #VALUE! | N29: =J29/8 -> #VALUE!
B30: =D30&"_"&E30 -> INSTRUMENT_RWA | C30: 3.13. | D30: INSTRUMENT | E30: RWA | I30: =J30/8/5 -> #VALUE! | J30: =SUMIF([1]Aux!B:B,Macro_Plano_2025_v1!B30,[1]Aux!I:I)+SUMIF([1]Aux!B:B,Macro_Plano_2025_v1!B30,[1]Aux!O:O) -> #VALUE! | N30: =J30/8 -> #VALUE!
B31: =D31&"_"&E31 -> INSTRUMENT_ACCMLTD_IMPRMNT_INSTRMNT | C31: 3.14. | D31: INSTRUMENT | E31: ACCMLTD_IMPRMNT_INSTRMNT | I31: =J31/8/5 -> #VALUE! | J31: =SUMIF([1]Aux!B:B,Macro_Plano_2025_v1!B31,[1]Aux!I:I)+SUMIF([1]Aux!B:B,Macro_Plano_2025_v1!B31,[1]Aux!O:O) -> #VALUE! | N31: =J31/8 -> #VALUE!
B32: =D32&"_"&E32 -> INSTRUMENT_COD_SOC_INTRGRP | C32: 3.15. | D32: INSTRUMENT | E32: COD_SOC_INTRGRP | I32: =J32/8/5 -> #VALUE! | J32: =SUMIF([1]Aux!B:B,Macro_Plano_2025_v1!B32,[1]Aux!I:I)+SUMIF([1]Aux!B:B,Macro_Plano_2025_v1!B32,[1]Aux!O:O) -> #VALUE! | N32: =J32/8 -> #VALUE!
B33: =D33&"_"&E33 -> INSTRUMENT_LCL_INSTMRNT_ID | C33: 3.16. | D33: INSTRUMENT | E33: LCL_INSTMRNT_ID | I33: =J33/8/5 -> #VALUE! | J33: =SUMIF([1]Aux!B:B,Macro_Plano_2025_v1!B33,[1]Aux!I:I)+SUMIF([1]Aux!B:B,Macro_Plano_2025_v1!B33,[1]Aux!O:O) -> #VALUE! | N33: =J33/8 -> #VALUE!
B34: =D34&"_"&E34 -> INSTRUMENT_FLG_INTRBSNSS | C34: 3.17. | D34: INSTRUMENT | E34: FLG_INTRBSNSS | I34: =J34/8/5 -> #VALUE! | J34: =SUMIF([1]Aux!B:B,Macro_Plano_2025_v1!B34,[1]Aux!I:I)+SUMIF([1]Aux!B:B,Macro_Plano_2025_v1!B34,[1]Aux!O:O) -> #VALUE! | N34: =J34/8 -> #VALUE!
... B40: =D40&"_"&E40 -> INSTRUMENT_RWA_OFF_BLNC | C40: 3.23. | D40: INSTRUMENT | E40: RWA_OFF_BLNC | I40: =J40/8/5 -> #VALUE! | J40: =SUMIF([1]Aux!B:B,Macro_Plano_2025_v1!B40,[1]Aux!I:I)+SUMIF([1]Aux!B:B,Macro_Plano_2025_v1!B40,[1]Aux!O:O) -> #VALUE! | N40: =J40/8 -> #VALUE!
C42: 4. | D42: Re-especificações e especificação de novos requisitos | H42: =COUNTA(E43:E56) -> 14 | I42: =+SUM(I43:I56) -> #VALUE! | J42: =SUM(J43:J56) -> #VALUE! | N42: 1.75 | O42: 0.125
B43: =D43&"_"&E43 -> INSTRUMENT_CCF | C43: 4.1. | D43: INSTRUMENT | E43: CCF | I43: =J43/8/5 -> #VALUE! | J43: =SUMIF([1]Aux!B:B,Macro_Plano_2025_v1!B43,[1]Aux!H:H) -> #VALUE! | N43: =J43/8 -> #VALUE!
B44: =D44&"_"&E44 -> INSTRUMENT_EAD | C44: 4.2. | D44: INSTRUMENT | E44: EAD | I44: =J44/8/5 -> #VALUE! | J44: =SUMIF([1]Aux!B:B,Macro_Plano_2025_v1!B44,[1]Aux!H:H) -> #VALUE! | N44: =J44/8 -> #VALUE!
B45: =D45&"_"&E45 -> INSTRUMENT_TYP_OFF_BLNC_PRDCT | C45: 4.3. | D45: INSTRUMENT | E45: TYP_OFF_BLNC_PRDCT | I45: =J45/8/5 -> #VALUE! | J45: =SUMIF([1]Aux!B:B,Macro_Plano_2025_v1!B45,[1]Aux!H:H) -> #VALUE! | N45: =J45/8 -> #VALUE!
B46: =D46&"_"&E46 -> INSTR_PROTECTION_COD_SOC | C46: 4.4. | D46: INSTR_PROTECTION | E46: COD_SOC | I46: =J46/8/5 -> #VALUE! | J46: =SUMIF([1]Aux!B:B,Macro_Plano_2025_v1!B46,[1]Aux!H:H) -> #VALUE! | N46: =J46/8 -> #VALUE!
B47: =D47&"_"&E47 -> INSTR_PROTECTION_DT_RFRNC | C47: 4.5. | D47: INSTR_PROTECTION | E47: DT_RFRNC | I47: =J47/8/5 -> #VALUE! | J47: =SUMIF([1]Aux!B:B,Macro_Plano_2025_v1!B47,[1]Aux!H:H) -> #VALUE! | N47: =J47/8 -> #VALUE!
B48: =D48&"_"&E48 -> INSTR_PROTECTION_INSTRMNT_ID | C48: 4.6. | D48: INSTR_PROTECTION | E48: INSTRMNT_ID | I48: =J48/8/5 -> #VALUE! | J48: =SUMIF([1]Aux!B:B,Macro_Plano_2025_v1!B48,[1]Aux!H:H) -> #VALUE! | N48: =J48/8 -> #VALUE!
B49: =D49&"_"&E49 -> INSTR_PROTECTION_PRTCTN_ID | C49: 4.7. | D49: INSTR_PROTECTION | E49: PRTCTN_ID | I49: =J49/8/5 -> #VALUE! | J49: =SUMIF([1]Aux!B:B,Macro_Plano_2025_v1!B49,[1]Aux!H:H) -> #VALUE! | N49: =J49/8 -> #VALUE!
B50: =D50&"_"&E50 -> PROTECTION_COD_SOC | C50: 4.8. | D50: PROTECTION | E50: COD_SOC | I50: =J50/8/5 -> #VALUE! | J50: =SUMIF([1]Aux!B:B,Macro_Plano_2025_v1!B50,[1]Aux!H:H) -> #VALUE! | N50: =J50/8 -> #VALUE!
B51: =D51&"_"&E51 -> PROTECTION_DT_RFRNC | C51: 4.9. | D51: PROTECTION | E51: DT_RFRNC | I51: =J51/8/5 -> #VALUE! | J51: =SUMIF([1]Aux!B:B,Macro_Plano_2025_v1!B51,[1]Aux!H:H) -> #VALUE! | N51: =J51/8 -> #VALUE!
B52: =D52&"_"&E52 -> PROTECTION_PRTCTN_ID | C52: 4.10 | D52: PROTECTION | E52: PRTCTN_ID | I52: =J52/8/5 -> #VALUE! | J52: =SUMIF([1]Aux!B:B,Macro_Plano_2025_v1!B52,[1]Aux!H:H) -> #VALUE! | N52: =J52/8 -> #VALUE!
B53: =D53&"_"&E53 -> PROTECTION_TYP_PRTCTN | C53: 4.11. | D53: PROTECTION | E53: TYP_PRTCTN | I53: =J53/8/5 -> #VALUE! | J53: =SUMIF([1]Aux!B:B,Macro_Plano_2025_v1!B53,[1]Aux!H:H) -> #VALUE! | N53: =J53/8 -> #VALUE!
B54: =D54&"_"&E54 -> PROTECTION_PRTCTN_VL | C54: 4.12. | D54: PROTECTION | E54: PRTCTN_VL | I54: =J54/8/5 -> #VALUE! | J54: =SUMIF([1]Aux!B:B,Macro_Plano_2025_v1!B54,[1]Aux!H:H) -> #VALUE! | N54: =J54/8 -> #VALUE!
B55: =D55&"_"&E55 -> PROTECTION_FLG_ELCTRC_VHCL | C55: 4.13. | D55: PROTECTION | E55: FLG_ELCTRC_VHCL | I55: =J55/8/5 -> #VALUE! | J55: =SUMIF([1]Aux!B:B,Macro_Plano_2025_v1!B55,[1]Aux!H:H) -> #VALUE! | N55: =J55/8 -> #VALUE!
B56: =D56&"_"&E56 -> INSTR_ACTIVITY_PRCNTG_ACTVTY | C56: 4.14. | D56: INSTR_ACTIVITY | E56: PRCNTG_ACTVTY | I56: =J56/8/5 -> #VALUE! | J56: =SUMIF([1]Aux!B:B,Macro_Plano_2025_v1!B56,[1]Aux!H:H) -> #VALUE! | O56: =J56/8 -> #VALUE!
C58: 5. | D58: Testes/Re-testes às métricas do GD | J58: =J59+J60+J106 -> #VALUE!
C59: 5.1. | E59: Testes ao Universo | H59: n.a. | J59: 40 | O59: 5
C60: 5.2. | E60: Simulação/ Testes aos Campos | H60: =COUNTA(E61:E105) -> 45 | J60: =SUM(J61:J105) -> #VALUE! | O60: 4.875 | P60: 10 | Q60: 10 | R60: 10 | S60: 10 | T60: 2.875
B61: =D61&"_"&E61 -> INSTRUMENT_INSTRMNT_ID | C61: 5.2.1 | D61: INSTRUMENT | E61: INSTRMNT_ID | J61: =SUMIF([1]Aux!B:B,Macro_Plano_2025_v1!B61,[1]Aux!I:I)+SUMIF([1]Aux!B:B,Macro_Plano_2025_v1!B61,[1]Aux!O:O) -> #VALUE! | O61: =J61/8 -> #VALUE!
B62: =D62&"_"&E62 -> INSTRUMENT_CCF | C62: 5.2.2. | D62: INSTRUMENT | E62: CCF | J62: =SUMIF([1]Aux!B:B,Macro_Plano_2025_v1!B62,[1]Aux!I:I)+SUMIF([1]Aux!B:B,Macro_Plano_2025_v1!B62,[1]Aux!O:O) -> #VALUE! | O62: =J62/8 -> #VALUE!
B63: =D63&"_"&E63 -> INSTRUMENT_EAD | C63: 5.2.3. | D63: INSTRUMENT | E63: EAD | J63: =SUMIF([1]Aux!B:B,Macro_Plano_2025_v1!B63,[1]Aux!I:I)+SUMIF([1]Aux!B:B,Macro_Plano_2025_v1!B63,[1]Aux!O:O) -> #VALUE! | O63: =J63/8 -> #VALUE!
B64: =D64&"_"&E64 -> INSTRUMENT_AVRG_BLNC | C64: 5.2.4. | D64: INSTRUMENT | E64: AVRG_BLNC | J64: =SUMIF([1]Aux!B:B,Macro_Plano_2025_v1!B64,[1]Aux!I:I)+SUMIF([1]Aux!B:B,Macro_Plano_2025_v1!B64,[1]Aux!O:O) -> #VALUE! | O64: =J64/8 -> #VALUE!
B65: =D65&"_"&E65 -> INSTRUMENT_NW_BSNSS | C65: 5.2.5. | D65: INSTRUMENT | E65: NW_BSNSS | J65: =SUMIF([1]Aux!B:B,Macro_Plano_2025_v1!B65,[1]Aux!I:I)+SUMIF([1]Aux!B:B,Macro_Plano_2025_v1!B65,[1]Aux!O:O) -> #VALUE! | O65: =O60-SUM(O61:O64) -> #VALUE! | P65: =(J65/8)-O65 -> #VALUE!
B66: =D66&"_"&E66 -> INSTRUMENT_GRSS_INTRST_INCM | C66: 5.2.6. | D66: INSTRUMENT | E66: GRSS_INTRST_INCM | J66: =SUMIF([1]Aux!B:B,Macro_Plano_2025_v1!B66,[1]Aux!I:I)+SUMIF([1]Aux!B:B,Macro_Plano_2025_v1!B66,[1]Aux!O:O) -> #VALUE! | P66: =J66/8 -> #VALUE!
B67: =D67&"_"&E67 -> INSTRUMENT_GRSS_CMMSSN_INCM | C67: 5.2.7. | D67: INSTRUMENT | E67: GRSS_CMMSSN_INCM | J67: =SUMIF([1]Aux!B:B,Macro_Plano_2025_v1!B67,[1]Aux!I:I)+SUMIF([1]Aux!B:B,Macro_Plano_2025_v1!B67,[1]Aux!O:O) -> #VALUE! | P67: =J67/8 -> #VALUE!
B68: =D68&"_"&E68 -> INSTRUMENT_INTRNL_TRNSFR_RT | C68: 5.2.8. | D68: INSTRUMENT | E68: INTRNL_TRNSFR_RT | J68: =SUMIF([1]Aux!B:B,Macro_Plano_2025_v1!B68,[1]Aux!I:I)+SUMIF([1]Aux!B:B,Macro_Plano_2025_v1!B68,[1]Aux!O:O) -> #VALUE! | P68: =J68/8 -> #VALUE!
B69: =D69&"_"&E69 -> INSTRUMENT_NT_LN_LSS_PRVSN | C69: 5.2.9. | D69: INSTRUMENT | E69: NT_LN_LSS_PRVSN | J69: =SUMIF([1]Aux!B:B,Macro_Plano_2025_v1!B69,[1]Aux!I:I)+SUMIF([1]Aux!B:B,Macro_Plano_2025_v1!B69,[1]Aux!O:O) -> #VALUE! | P69: =J69/8 -> #VALUE!
B70: =D70&"_"&E70 -> INSTRUMENT_BSNSS_AREA | C70: 5.2.10. | D70: INSTRUMENT | E70: BSNSS_AREA | J70: =SUMIF([1]Aux!B:B,Macro_Plano_2025_v1!B70,[1]Aux!I:I)+SUMIF([1]Aux!B:B,Macro_Plano_2025_v1!B70,[1]Aux!O:O) -> #VALUE! | P70: =P60-SUM(P65:P69) -> #VALUE! | Q70: =(J70/8)-P70 -> #VALUE!
B71: =D71&"_"&E71 -> INSTRUMENT_MNGMNT_PRDCT | C71: 5.2.11. | D71: INSTRUMENT | E71: MNGMNT_PRDCT | J71: =SUMIF([1]Aux!B:B,Macro_Plano_2025_v1!B71,[1]Aux!I:I)+SUMIF([1]Aux!B:B,Macro_Plano_2025_v1!B71,[1]Aux!O:O) -> #VALUE! | Q71: =J71/8 -> #VALUE!
B72: =D72&"_"&E72 -> INSTRUMENT_GRSS_CMMSSN_EXPNS | C72: 5.2.12. | D72: INSTRUMENT | E72: GRSS_CMMSSN_EXPNS | J72: =SUMIF([1]Aux!B:B,Macro_Plano_2025_v1!B72,[1]Aux!I:I)+SUMIF([1]Aux!B:B,Macro_Plano_2025_v1!B72,[1]Aux!O:O) -> #VALUE! | Q72: =J72/8 -> #VALUE!
B73: =D73&"_"&E73 -> INSTRUMENT_GNS_FNNCL_TRNSCTN_EXCHNG_DFFRNCS | C73: 5.2.13. | D73: INSTRUMENT | E73: GNS_FNNCL_TRNSCTN_EXCHNG_DFFRNCS | J73: =SUMIF([1]Aux!B:B,Macro_Plano_2025_v1!B73,[1]Aux!I:I)+SUMIF([1]Aux!B:B,Macro_Plano_2025_v1!B73,[1]Aux!O:O) -> #VALUE! | Q73: =J73/8 -> #VALUE!
B74: =D74&"_"&E74 -> INSTRUMENT_AVRG_BLNC_OFF_BLNC | C74: 5.2.14. | D74: INSTRUMENT | E74: AVRG_BLNC_OFF_BLNC | J74: =SUMIF([1]Aux!B:B,Macro_Plano_2025_v1!B74,[1]Aux!I:I)+SUMIF([1]Aux!B:B,Macro_Plano_2025_v1!B74,[1]Aux!O:O) -> #VALUE! | Q74: =J74/8 -> #VALUE!
B75: =D75&"_"&E75 -> INSTRUMENT_GRSS_CMMSSN_INCM_OFF_BLNC | C75: 5.2.15. | D75: INSTRUMENT | E75: GRSS_CMMSSN_INCM_OFF_BLNC | J75: =SUMIF([1]Aux!B:B,Macro_Plano_2025_v1!B75,[1]Aux!I:I)+SUMIF([1]Aux!B:B,Macro_Plano_2025_v1!B75,[1]Aux!O:O) -> #VALUE! | Q75: =J75/8 -> #VALUE!
B76: =D76&"_"&E76 -> INSTRUMENT_GRSS_CMMSSN_EXPNS_OFF_BLNC | C76: 5.2.16. | D76: INSTRUMENT | E76: GRSS_CMMSSN_EXPNS_OFF_BLNC | J76: =SUMIF([1]Aux!B:B,Macro_Plano_2025_v1!B76,[1]Aux!I:I)+SUMIF([1]Aux!B:B,Macro_Plano_2025_v1!B76,[1]Aux!O:O) -> #VALUE! | Q76: =Q60-SUM(Q70:Q75) -> #VALUE! | R76: =(J76/8)-Q76 -> #VALUE!
B77: =D77&"_"&E77 -> INSTRUMENT_GRSS_INTRST_EXPNS | C77: 5.2.17. | D77: INSTRUMENT | E77: GRSS_INTRST_EXPNS | J77: =SUMIF([1]Aux!B:B,Macro_Plano_2025_v1!B77,[1]Aux!I:I)+SUMIF([1]Aux!B:B,Macro_Plano_2025_v1!B77,[1]Aux!O:O) -> #VALUE! | R77: =J77/8 -> #VALUE!
B78: =D78&"_"&E78 -> INSTRUMENT_NT_LN_LSS_PRVSN_OFF_BLNC | C78: 5.2.18. | D78: INSTRUMENT | E78: NT_LN_LSS_PRVSN_OFF_BLNC | J78: =SUMIF([1]Aux!B:B,Macro_Plano_2025_v1!B78,[1]Aux!I:I)+SUMIF([1]Aux!B:B,Macro_Plano_2025_v1!B78,[1]Aux!O:O) -> #VALUE! | R78: =J78/8 -> #VALUE!
B79: =D79&"_"&E79 -> INSTRUMENT_GRSS_INTRST_INCM_CCRR | C79: 5.2.19. | D79: INSTRUMENT | E79: GRSS_INTRST_INCM_CCRR | J79: =SUMIF([1]Aux!B:B,Macro_Plano_2025_v1!B79,[1]Aux!I:I)+SUMIF([1]Aux!B:B,Macro_Plano_2025_v1!B79,[1]Aux!O:O) -> #VALUE! | R79: =J79/8 -> #VALUE!
B80: =D80&"_"&E80 -> INSTRUMENT_GRSS_INTRST_EXPNS_CCRR | C80: 5.2.20. | D80: INSTRUMENT | E80: GRSS_INTRST_EXPNS_CCRR | J80: =SUMIF([1]Aux!B:B,Macro_Plano_2025_v1!B80,[1]Aux!I:I)+SUMIF([1]Aux!B:B,Macro_Plano_2025_v1!B80,[1]Aux!O:O) -> #VALUE! | R80: =J80/8 -> #VALUE!
B81: =D81&"_"&E81 -> INSTRUMENT_GRSS_CMMSSN_INCM_CCRR | C81: 5.2.21. | D81: INSTRUMENT | E81: GRSS_CMMSSN_INCM_CCRR | J81: =SUMIF([1]Aux!B:B,Macro_Plano_2025_v1!B81,[1]Aux!I:I)+SUMIF([1]Aux!B:B,Macro_Plano_2025_v1!B81,[1]Aux!O:O) -> #VALUE! | R81: =J81/8 -> #VALUE!
B82: =D82&"_"&E82 -> INSTRUMENT_GRSS_CMMSSN_EXPNS_CCRR | C82: 5.2.22. | D82: INSTRUMENT | E82: GRSS_CMMSSN_EXPNS_CCRR | J82: =SUMIF([1]Aux!B:B,Macro_Plano_2025_v1!B82,[1]Aux!I:I)+SUMIF([1]Aux!B:B,Macro_Plano_2025_v1!B82,[1]Aux!O:O) -> #VALUE! | R82: =J82/8 -> #VALUE!
B83: =D83&"_"&E83 -> INSTRUMENT_GNS_FNNCL_TRNSCTN_EXCHNG_CCRR | C83: 5.2.23. | D83: INSTRUMENT | E83: GNS_FNNCL_TRNSCTN_EXCHNG_CCRR | J83: =SUMIF([1]Aux!B:B,Macro_Plano_2025_v1!B83,[1]Aux!I:I)+SUMIF([1]Aux!B:B,Macro_Plano_2025_v1!B83,[1]Aux!O:O) -> #VALUE! | R83: =J83/8 -> #VALUE!
B84: =D84&"_"&E84 -> INSTRUMENT_BSNSS_AREA_CCRR | C84: 5.2.24. | D84: INSTRUMENT | E84: BSNSS_AREA_CCRR | J84: =SUMIF([1]Aux!B:B,Macro_Plano_2025_v1!B84,[1]Aux!I:I)+SUMIF([1]Aux!B:B,Macro_Plano_2025_v1!B84,[1]Aux!O:O) -> #VALUE! | R84: =J84/8 -> #VALUE!
B85: =D85&"_"&E85 -> INSTRUMENT_GRSS_CMMSSN_INCM_OFF_BLNC_CCRR | C85: 5.2.25. | D85: INSTRUMENT | E85: GRSS_CMMSSN_INCM_OFF_BLNC_CCRR | J85: =SUMIF([1]Aux!B:B,Macro_Plano_2025_v1!B85,[1]Aux!I:I)+SUMIF([1]Aux!B:B,Macro_Plano_2025_v1!B85,[1]Aux!O:O) -> #VALUE! | R85: =J85/8 -> #VALUE!
B86: =D86&"_"&E86 -> INSTRUMENT_GRSS_CMMSSN_EXPNS_OFF_BLNC_CCRR | C86: 5.2.26. | D86: INSTRUMENT | E86: GRSS_CMMSSN_EXPNS_OFF_BLNC_CCRR | J86: =SUMIF([1]Aux!B:B,Macro_Plano_2025_v1!B86,[1]Aux!I:I)+SUMIF([1]Aux!B:B,Macro_Plano_2025_v1!B86,[1]Aux!O:O) -> #VALUE! | R86: =J86/8 -> #VALUE!
B87: =D87&"_"&E87 -> INSTRUMENT_CNCLLD_INSTRMNT_STTS | C87: 5.2.27. | D87: INSTRUMENT | E87: CNCLLD_INSTRMNT_STTS | J87: =SUMIF([1]Aux!B:B,Macro_Plano_2025_v1!B87,[1]Aux!I:I)+SUMIF([1]Aux!B:B,Macro_Plano_2025_v1!B87,[1]Aux!O:O) -> #VALUE! | S87: =J87/8 -> #VALUE!
B88: =D88&"_"&E88 -> INSTRUMENT_TYP_OFF_BLNC_PRDCT | C88: 5.2.28. | D88: INSTRUMENT | E88: TYP_OFF_BLNC_PRDCT | J88: =SUMIF([1]Aux!B:B,Macro_Plano_2025_v1!B88,[1]Aux!I:I)+SUMIF([1]Aux!B:B,Macro_Plano_2025_v1!B88,[1]Aux!O:O) -> #VALUE! | S88: =J88/8 -> #VALUE!
B89: =D89&"_"&E89 -> INSTR_PROTECTION_COD_SOC | C89: 5.2.29. | D89: INSTR_PROTECTION | E89: COD_SOC | J89: =SUMIF([1]Aux!B:B,Macro_Plano_2025_v1!B89,[1]Aux!I:I)+SUMIF([1]Aux!B:B,Macro_Plano_2025_v1!B89,[1]Aux!O:O) -> #VALUE! | S89: =J89/8 -> #VALUE!
B90: =D90&"_"&E90 -> INSTR_PROTECTION_DT_RFRNC | C90: 5.2.30. | D90: INSTR_PROTECTION | E90: DT_RFRNC | J90: =SUMIF([1]Aux!B:B,Macro_Plano_2025_v1!B90,[1]Aux!I:I)+SUMIF([1]Aux!B:B,Macro_Plano_2025_v1!B90,[1]Aux!O:O) -> #VALUE! | S90: =J90/8 -> #VALUE!
B91: =D91&"_"&E91 -> INSTR_PROTECTION_INSTRMNT_ID | C91: 5.2.31. | D91: INSTR_PROTECTION | E91: INSTRMNT_ID | J91: =SUMIF([1]Aux!B:B,Macro_Plano_2025_v1!B91,[1]Aux!I:I)+SUMIF([1]Aux!B:B,Macro_Plano_2025_v1!B91,[1]Aux!O:O) -> #VALUE! | S91: =J91/8 -> #VALUE!
B92: =D92&"_"&E92 -> INSTR_PROTECTION_PRTCTN_ID | C92: 5.2.32. | D92: INSTR_PROTECTION | E92: PRTCTN_ID | J92: =SUMIF([1]Aux!B:B,Macro_Plano_2025_v1!B92,[1]Aux!I:I)+SUMIF([1]Aux!B:B,Macro_Plano_2025_v1!B92,[1]Aux!O:O) -> #VALUE! | S92: =J92/8 -> #VALUE!
B93: =D93&"_"&E93 -> INSTR_PROTECTION_TYP_RLTN | C93: 5.2.33. | D93: INSTR_PROTECTION | E93: TYP_RLTN | J93: =SUMIF([1]Aux!B:B,Macro_Plano_2025_v1!B93,[1]Aux!I:I)+SUMIF([1]Aux!B:B,Macro_Plano_2025_v1!B93,[1]Aux!O:O) -> #VALUE! | S93: =J93/8 -> #VALUE!
B94: =D94&"_"&E94 -> PROTECTION_COD_SOC | C94: 5.2.34. | D94: PROTECTION | E94: COD_SOC | J94: =SUMIF([1]Aux!B:B,Macro_Plano_2025_v1!B94,[1]Aux!I:I)+SUMIF([1]Aux!B:B,Macro_Plano_2025_v1!B94,[1]Aux!O:O) -> #VALUE! | S94: =J94/8 -> #VALUE!
B95: =D95&"_"&E95 -> PROTECTION_DT_RFRNC | C95: 5.2.35. | D95: PROTECTION | E95: DT_RFRNC | J95: =SUMIF([1]Aux!B:B,Macro_Plano_2025_v1!B95,[1]Aux!I:I)+SUMIF([1]Aux!B:B,Macro_Plano_2025_v1!B95,[1]Aux!O:O) -> #VALUE! | S95: =J95/8 -> #VALUE!
B96: =D96&"_"&E96 -> PROTECTION_PRTCTN_ID | C96: 5.2.36. | D96: PROTECTION | E96: PRTCTN_ID | J96: =SUMIF([1]Aux!B:B,Macro_Plano_2025_v1!B96,[1]Aux!I:I)+SUMIF([1]Aux!B:B,Macro_Plano_2025_v1!B96,[1]Aux!O:O) -> #VALUE! | S96: =J96/8 -> #VALUE!
B97: =D97&"_"&E97 -> PROTECTION_TYP_PRTCTN | C97: 5.2.37. | D97: PROTECTION | E97: TYP_PRTCTN | J97: =SUMIF([1]Aux!B:B,Macro_Plano_2025_v1!B97,[1]Aux!I:I)+SUMIF([1]Aux!B:B,Macro_Plano_2025_v1!B97,[1]Aux!O:O) -> #VALUE! | S97: =J97/8 -> #VALUE!
B98: =D98&"_"&E98 -> PROTECTION_PRTCTN_VL | C98: 5.2.38. | D98: PROTECTION | E98: PRTCTN_VL | J98: =SUMIF([1]Aux!B:B,Macro_Plano_2025_v1!B98,[1]Aux!I:I)+SUMIF([1]Aux!B:B,Macro_Plano_2025_v1!B98,[1]Aux!O:O) -> #VALUE! | S98: =J98/8 -> #VALUE!
... B102: =D102&"_"&E102 -> INSTR_ACTIVITY_INSTRMNT_ID | C102: 5.2.42. | D102: INSTR_ACTIVITY | E102: INSTRMNT_ID | J102: =SUMIF([1]Aux!B:B,Macro_Plano_2025_v1!B102,[1]Aux!I:I)+SUMIF([1]Aux!B:B,Macro_Plano_2025_v1!B102,[1]Aux!O:O) -> #VALUE! | S102: =J102/8 -> #VALUE!
B103: =D103&"_"&E103 -> INSTR_ACTIVITY_SSTNBL_CTGRY | C103: 5.2.43. | D103: INSTR_ACTIVITY | E103: SSTNBL_CTGRY | J103: =SUMIF([1]Aux!B:B,Macro_Plano_2025_v1!B103,[1]Aux!I:I)+SUMIF([1]Aux!B:B,Macro_Plano_2025_v1!B103,[1]Aux!O:O) -> #VALUE! | S103: =S60-SUM(S87:S102) -> #VALUE! | T103: =(J103/8)-S103 -> #VALUE!
B104: =D104&"_"&E104 -> INSTR_ACTIVITY_PRCNTG_ACTVTY | C104: 5.2.44. | D104: INSTR_ACTIVITY | E104: PRCNTG_ACTVTY | J104: =SUMIF([1]Aux!B:B,Macro_Plano_2025_v1!B104,[1]Aux!I:I)+SUMIF([1]Aux!B:B,Macro_Plano_2025_v1!B104,[1]Aux!O:O) -> #VALUE! | T104: =J104/8 -> #VALUE!
B105: =D105&"_"&E105 -> INSTR_ACTIVITY_SSTNBL_INDCTR | C105: 5.2.45. | D105: INSTR_ACTIVITY | E105: SSTNBL_INDCTR | J105: =SUMIF([1]Aux!B:B,Macro_Plano_2025_v1!B105,[1]Aux!I:I)+SUMIF([1]Aux!B:B,Macro_Plano_2025_v1!B105,[1]Aux!O:O) -> #VALUE! | T105: =J105/8 -> #VALUE!
C106: 5.3 | E106: Re-testes | J106: 76.4 | T106: 7.125 | U106: 2.425
C108: 6. | D108: Documentação | J108: 80 | U108: 7.575 | V108: 2.425

Sheet Sheet1
B2: Campos Assessment (especificação DTT) | G2: Testes Regressivos (campos concluídos Neyond) | M2: Re-especificações e especificação de novos requisitos | Q2: Simulação/ Testes aos Campos
C3: =COUNTA(C6:C43) -> 38 | H3: =COUNTA(H6:H28) -> 23 | N3: =COUNTA(N6:N19) -> 14 | R3: =COUNTA(R6:R50) -> 45
B5: Tabela | C5: Campo | D5: Status | E5: Notas | G5: Tabela | H5: Campo | I5: Existe na especificação da DTT? | J5: Next Step | K5: Notas | M5: Tabela | N5: Campo | O5: Next Steps | Q5: Tabela | R5: Campo | S5: Existe DTT? | T5: Existe Neyond anterior? | U5: Existe nova especificação? | V5: Notas
B6: lt002_instrument | C6: AVRG_BLNC | D6: 2. Concluído | G6: lt002_instrument | H6: COD_SOC | I6: {=_xlfn.IFNA(IF(INDEX($B$6:$C$43,MATCH(1,(G6=$B$6:$B$43)*(H6=$C$6:$C$43),0),2)=H6,"Sim","Não"),"Não")} -> Não | J6: Validar a qualidade do campo através do teste regressivo | M6: lt002_instrument | N6: CCF | O6: Fazer a especificação do campo | Q6: lt002_instrument | R6: INSTRMNT_ID | S6: {=INDEX($B$6:$C$43,MATCH(1,(Q6=$B$6:$B$43)*(R6=$C$6:$C$43),0),2)} -> #N/A | T6: {=INDEX($G$6:$H$28,MATCH(1,(Q6=$G$6:$G$28)*(R6=$H$6:$H$28),0),2)} -> #N/A | U6: {=INDEX($M$6:$N$19,MATCH(1,(Q6=$M$6:$M$19)*(R6=$N$6:$N$19),0),2)} -> #N/A
B7: lt002_instrument | C7: NW_BSNSS | D7: 8. Por Iniciar | G7: lt002_instrument | H7: SUBPORTFOLIO_ID | I7: {=_xlfn.IFNA(IF(INDEX($B$6:$C$43,MATCH(1,(G7=$B$6:$B$43)*(H7=$C$6:$C$43),0),2)=H7,"Sim","Não"),"Não")} -> Não | J7: Validar a qualidade do campo através do teste regressivo | M7: lt002_instrument | N7: EAD | O7: Fazer a especificação do campo | Q7: lt002_instrument | R7: CCF | S7: {=INDEX($B$6:$C$43,MATCH(1,(Q7=$B$6:$B$43)*(R7=$C$6:$C$43),0),2)} -> #N/A | T7: {=INDEX($G$6:$H$28,MATCH(1,(Q7=$G$6:$G$28)*(R7=$H$6:$H$28),0),2)} -> #N/A | U7: {=INDEX($M$6:$N$19,MATCH(1,(Q7=$M$6:$M$19)*(R7=$N$6:$N$19),0),2)} -> CCF
B8: lt002_instrument | C8: GRSS_INTRST_INCM | D8: 4. Validação da especificação | G8: lt002_instrument | H8: DT_RFRNC | I8: {=_xlfn.IFNA(IF(INDEX($B$6:$C$43,MATCH(1,(G8=$B$6:$B$43)*(H8=$C$6:$C$43),0),2)=H8,"Sim","Não"),"Não")} -> Não | J8: Validar a qualidade do campo através do teste regressivo | M8: lt002_instrument | N8: TYP_OFF_BLNC_PRDCT | O8: Fazer a especificação do campo | Q8: lt002_instrument | R8: EAD | S8: {=INDEX($B$6:$C$43,MATCH(1,(Q8=$B$6:$B$43)*(R8=$C$6:$C$43),0),2)} -> #N/A | T8: {=INDEX($G$6:$H$28,MATCH(1,(Q8=$G$6:$G$28)*(R8=$H$6:$H$28),0),2)} -> #N/A | U8: {=INDEX($M$6:$N$19,MATCH(1,(Q8=$M$6:$M$19)*(R8=$N$6:$N$19),0),2)} -> EAD
B9: lt002_instrument | C9: GRSS_CMMSSN_INCM | D9: 4. Validação da especificação | G9: lt002_instrument | H9: DFLT_STTS_INSTRMNT | I9: {=_xlfn.IFNA(IF(INDEX($B$6:$C$43,MATCH(1,(G9=$B$6:$B$43)*(H9=$C$6:$C$43),0),2)=H9,"Sim","Não"),"Não")} -> Não | J9: Validar a qualidade do campo através do teste regressivo | M9: lt006_instr_protection | N9: COD_SOC | O9: Fazer a especificação do campo | Q9: lt002_instrument | R9: AVRG_BLNC | S9: {=INDEX($B$6:$C$43,MATCH(1,(Q9=$B$6:$B$43)*(R9=$C$6:$C$43),0),2)} -> AVRG_BLNC | T9: {=INDEX($G$6:$H$28,MATCH(1,(Q9=$G$6:$G$28)*(R9=$H$6:$H$28),0),2)} -> #N/A | U9: {=INDEX($M$6:$N$19,MATCH(1,(Q9=$M$6:$M$19)*(R9=$N$6:$N$19),0),2)} -> #N/A
B10: lt002_instrument | C10: INTRNL_TRNSFR_RT | D10: 2. Concluído | G10: lt002_instrument | H10: IMPRMNT_STTS | I10: {=_xlfn.IFNA(IF(INDEX($B$6:$C$43,MATCH(1,(G10=$B$6:$B$43)*(H10=$C$6:$C$43),0),2)=H10,"Sim","Não"),"Não")} -> Não | J10: Validar a qualidade do campo através do teste regressivo | M10: lt006_instr_protection | N10: DT_RFRNC | O10: Fazer a especificação do campo | Q10: lt002_instrument | R10: NW_BSNSS | S10: {=INDEX($B$6:$C$43,MATCH(1,(Q10=$B$6:$B$43)*(R10=$C$6:$C$43),0),2)} -> NW_BSNSS | T10: {=INDEX($G$6:$H$28,MATCH(1,(Q10=$G$6:$G$28)*(R10=$H$6:$H$28),0),2)} -> #N/A | U10: {=INDEX($M$6:$N$19,MATCH(1,(Q10=$M$6:$M$19)*(R10=$N$6:$N$19),0),2)} -> #N/A
B11: lt002_instrument | C11: NT_LN_LSS_PRVSN | D11: 2. Concluído | G11: lt002_instrument | H11: PRFRMNG_STTS | I11: {=_xlfn.IFNA(IF(INDEX($B$6:$C$43,MATCH(1,(G11=$B$6:$B$43)*(H11=$C$6:$C$43),0),2)=H11,"Sim","Não"),"Não")} -> Não | J11: Validar a qualidade do campo através do teste regressivo | M11: lt006_instr_protection | N11: INSTRMNT_ID | O11: Fazer a especificação do campo | Q11: lt002_instrument | R11: GRSS_INTRST_INCM | S11: {=INDEX($B$6:$C$43,MATCH(1,(Q11=$B$6:$B$43)*(R11=$C$6:$C$43),0),2)} -> GRSS_INTRST_INCM | T11: {=INDEX($G$6:$H$28,MATCH(1,(Q11=$G$6:$G$28)*(R11=$H$6:$H$28),0),2)} -> #N/A | U11: {=INDEX($M$6:$N$19,MATCH(1,(Q11=$M$6:$M$19)*(R11=$N$6:$N$19),0),2)} -> #N/A
B12: lt002_instrument | C12: BSNSS_AREA | D12: 8. Por Iniciar | G12: lt002_instrument | H12: TYP_INSTRMNT | I12: {=_xlfn.IFNA(IF(INDEX($B$6:$C$43,MATCH(1,(G12=$B$6:$B$43)*(H12=$C$6:$C$43),0),2)=H12,"Sim","Não"),"Não")} -> Não | J12: Validar a qualidade do campo através do teste regressivo | M12: lt006_instr_protection | N12: PRTCTN_ID | O12: Fazer a especificação do campo | Q12: lt002_instrument | R12: GRSS_CMMSSN_INCM | S12: {=INDEX($B$6:$C$43,MATCH(1,(Q12=$B$6:$B$43)*(R12=$C$6:$C$43),0),2)} -> GRSS_CMMSSN_INCM | T12: {=INDEX($G$6:$H$28,MATCH(1,(Q12=$G$6:$G$28)*(R12=$H$6:$H$28),0),2)} -> #N/A | U12: {=INDEX($M$6:$N$19,MATCH(1,(Q12=$M$6:$M$19)*(R12=$N$6:$N$19),0),2)} -> #N/A
B13: lt002_instrument | C13: MNGMNT_PRDCT | D13: 2. Concluído | G13: lt002_instrument | H13: GRSS_CRRYNG_AMNT_INSTRMNT | I13: {=_xlfn.IFNA(IF(INDEX($B$6:$C$43,MATCH(1,(G13=$B$6:$B$43)*(H13=$C$6:$C$43),0),2)=H13,"Sim","Não"),"Não")} -> Não | J13: Validar a qualidade do campo através do teste regressivo | M13: lt004_protection | N13: COD_SOC | O13: Fazer a especificação do campo | Q13: lt002_instrument | R13: INTRNL_TRNSFR_RT | S13: {=INDEX($B$6:$C$43,MATCH(1,(Q13=$B$6:$B$43)*(R13=$C$6:$C$43),0),2)} -> INTRNL_TRNSFR_RT | T13: {=INDEX($G$6:$H$28,MATCH(1,(Q13=$G$6:$G$28)*(R13=$H$6:$H$28),0),2)} -> #N/A | U13: {=INDEX($M$6:$N$19,MATCH(1,(Q13=$M$6:$M$19)*(R13=$N$6:$N$19),0),2)} -> #N/A
B14: lt002_instrument | C14: GRSS_CMMSSN_EXPNS | D14: 2. Concluído | G14: lt002_instrument | H14: ACCMLTD_CHNGS_FV_CR_INSTRMNT | I14: {=_xlfn.IFNA(IF(INDEX($B$6:$C$43,MATCH(1,(G14=$B$6:$B$43)*(H14=$C$6:$C$43),0),2)=H14,"Sim","Não"),"Não")} -> Não | J14: Validar a qualidade do campo através do teste regressivo | M14: lt004_protection | N14: DT_RFRNC | O14: Fazer a especificação do campo | Q14: lt002_instrument | R14: NT_LN_LSS_PRVSN | S14: {=INDEX($B$6:$C$43,MATCH(1,(Q14=$B$6:$B$43)*(R14=$C$6:$C$43),0),2)} -> NT_LN_LSS_PRVSN | T14: {=INDEX($G$6:$H$28,MATCH(1,(Q14=$G$6:$G$28)*(R14=$H$6:$H$28),0),2)} -> #N/A | U14: {=INDEX($M$6:$N$19,MATCH(1,(Q14=$M$6:$M$19)*(R14=$N$6:$N$19),0),2)} -> #N/A
B15: lt002_instrument | C15: GNS_FNNCL_TRNSCTN_EXCHNG_DFFRNCS | D15: 2. Concluído | G15: lt002_instrument | H15: ACCNTNG_CLSSFCTN | I15: {=_xlfn.IFNA(IF(INDEX($B$6:$C$43,MATCH(1,(G15=$B$6:$B$43)*(H15=$C$6:$C$43),0),2)=H15,"Sim","Não"),"Não")} -> Não | J15: Validar a qualidade do campo através do teste regressivo | M15: lt004_protection | N15: PRTCTN_ID | O15: Fazer a especificação do campo | Q15: lt002_instrument | R15: BSNSS_AREA | S15: {=INDEX($B$6:$C$43,MATCH(1,(Q15=$B$6:$B$43)*(R15=$C$6:$C$43),0),2)} -> BSNSS_AREA | T15: {=INDEX($G$6:$H$28,MATCH(1,(Q15=$G$6:$G$28)*(R15=$H$6:$H$28),0),2)} -> #N/A | U15: {=INDEX($M$6:$N$19,MATCH(1,(Q15=$M$6:$M$19)*(R15=$N$6:$N$19),0),2)} -> #N/A
B16: lt002_instrument | C16: FLG_INTRBSNSS | D16: 8. Por Iniciar | G16: lt002_instrument | H16: OFF_BLNC_SHT_AMNT_INSTRMNT | I16: {=_xlfn.IFNA(IF(INDEX($B$6:$C$43,MATCH(1,(G16=$B$6:$B$43)*(H16=$C$6:$C$43),0),2)=H16,"Sim","Não"),"Não")} -> Não | J16: Validar a qualidade do campo através do teste regressivo | M16: lt004_protection | N16: TYP_PRTCTN | O16: Fazer a especificação do campo | Q16: lt002_instrument | R16: MNGMNT_PRDCT | S16: {=INDEX($B$6:$C$43,MATCH(1,(Q16=$B$6:$B$43)*(R16=$C$6:$C$43),0),2)} -> MNGMNT_PRDCT | T16: {=INDEX($G$6:$H$28,MATCH(1,(Q16=$G$6:$G$28)*(R16=$H$6:$H$28),0),2)} -> #N/A | U16: {=INDEX($M$6:$N$19,MATCH(1,(Q16=$M$6:$M$19)*(R16=$N$6:$N$19),0),2)} -> #N/A
B17: lt002_instrument | C17: INTRBSNSS_ADJ_COD | D17: 8. Por Iniciar | G17: lt002_instrument | H17: PRVSNS_OFF_BLNC_SHT | I17: {=_xlfn.IFNA(IF(INDEX($B$6:$C$43,MATCH(1,(G17=$B$6:$B$43)*(H17=$C$6:$C$43),0),2)=H17,"Sim","Não"),"Não")} -> Não | J17: Validar a qualidade do campo através do teste regressivo | M17: lt004_protection | N17: PRTCTN_VL | O17: Fazer a especificação do campo | Q17: lt002_instrument | R17: GRSS_CMMSSN_EXPNS | S17: {=INDEX($B$6:$C$43,MATCH(1,(Q17=$B$6:$B$43)*(R17=$C$6:$C$43),0),2)} -> GRSS_CMMSSN_EXPNS | T17: {=INDEX($G$6:$H$28,MATCH(1,(Q17=$G$6:$G$28)*(R17=$H$6:$H$28),0),2)} -> #N/A | U17: {=INDEX($M$6:$N$19,MATCH(1,(Q17=$M$6:$M$19)*(R17=$N$6:$N$19),0),2)} -> #N/A
B18: lt002_instrument | C18: COD_SOC_DSTNTN | D18: 8. Por Iniciar | G18: lt002_instrument | H18: RWA | I18: {=_xlfn.IFNA(IF(INDEX($B$6:$C$43,MATCH(1,(G18=$B$6:$B$43)*(H18=$C$6:$C$43),0),2)=H18,"Sim","Não"),"Não")} -> Não | J18: Validar a qualidade do campo através do teste regressivo | L18: falar com mafalda do leasing | M18: lt004_protection | N18: FLG_ELCTRC_VHCL | O18: Fazer a especificação do campo | Q18: lt002_instrument | R18: GNS_FNNCL_TRNSCTN_EXCHNG_DFFRNCS | S18: {=INDEX($B$6:$C$43,MATCH(1,(Q18=$B$6:$B$43)*(R18=$C$6:$C$43),0),2)} -> GNS_FNNCL_TRNSCTN_EXCHNG_DFFRNCS | T18: {=INDEX($G$6:$H$28,MATCH(1,(Q18=$G$6:$G$28)*(R18=$H$6:$H$28),0),2)} -> #N/A | U18: {=INDEX($M$6:$N$19,MATCH(1,(Q18=$M$6:$M$19)*(R18=$N$6:$N$19),0),2)} -> #N/A
B19: lt002_instrument | C19: BSNSS_AREA_DSTNTN | D19: 8. Por Iniciar | G19: lt002_instrument | H19: ACCMLTD_IMPRMNT_INSTRMNT | I19: {=_xlfn.IFNA(IF(INDEX($B$6:$C$43,MATCH(1,(G19=$B$6:$B$43)*(H19=$C$6:$C$43),0),2)=H19,"Sim","Não"),"Não")} -> Não | J19: Validar a qualidade do campo através do teste regressivo | M19: lt007_instr_activity | N19: PRCNTG_ACTVTY | O19: Fazer a especificação do campo | Q19: lt002_instrument | R19: AVRG_BLNC_OFF_BLNC | S19: {=INDEX($B$6:$C$43,MATCH(1,(Q19=$B$6:$B$43)*(R19=$C$6:$C$43),0),2)} -> AVRG_BLNC_OFF_BLNC | T19: {=INDEX($G$6:$H$28,MATCH(1,(Q19=$G$6:$G$28)*(R19=$H$6:$H$28),0),2)} -> #N/A | U19: {=INDEX($M$6:$N$19,MATCH(1,(Q19=$M$6:$M$19)*(R19=$N$6:$N$19),0),2)} -> #N/A
B20: lt002_instrument | C20: AVRG_BLNC_OFF_BLNC | D20: 2. Concluído | G20: lt002_instrument | H20: COD_SOC_INTRGRP | I20: {=_xlfn.IFNA(IF(INDEX($B$6:$C$43,MATCH(1,(G20=$B$6:$B$43)*(H20=$C$6:$C$43),0),2)=H20,"Sim","Não"),"Não")} -> Não | J20: Validar a qualidade do campo através do teste regressivo | M20: lt002_instrument | N20: CNCLLD_INSTRMNT_STTS | O20: Fazer a especificação do campo | Q20: lt002_instrument | R20: GRSS_CMMSSN_INCM_OFF_BLNC | S20: {=INDEX($B$6:$C$43,MATCH(1,(Q20=$B$6:$B$43)*(R20=$C$6:$C$43),0),2)} -> GRSS_CMMSSN_INCM_OFF_BLNC | T20: {=INDEX($G$6:$H$28,MATCH(1,(Q20=$G$6:$G$28)*(R20=$H$6:$H$28),0),2)} -> #N/A | U20: {=INDEX($M$6:$N$19,MATCH(1,(Q20=$M$6:$M$19)*(R20=$N$6:$N$19),0),2)} -> #N/A
B21: lt002_instrument | C21: INTRNL_TRNSFR_RT_OFF_BLNC | D21: 4. Validação da especificação | G21: lt002_instrument | H21: LCL_INSTMRNT_ID | I21: {=_xlfn.IFNA(IF(INDEX($B$6:$C$43,MATCH(1,(G21=$B$6:$B$43)*(H21=$C$6:$C$43),0),2)=H21,"Sim","Não"),"Não")} -> Não | J21: Validar a qualidade do campo através do teste regressivo | L21: ver c/ JB e HF | M21: lt007_instr_activity | N21: SSTNBL_INDCTR | O21: Fazer a especificação do campo, capitalizar info do Pilar 3, e necessário desagregar por linhas | P21: colocar em curso a especificação | Q21: lt002_instrument | R21: GRSS_CMMSSN_EXPNS_OFF_BLNC | S21: {=INDEX($B$6:$C$43,MATCH(1,(Q21=$B$6:$B$43)*(R21=$C$6:$C$43),0),2)} -> GRSS_CMMSSN_EXPNS_OFF_BLNC | T21: {=INDEX($G$6:$H$28,MATCH(1,(Q21=$G$6:$G$28)*(R21=$H$6:$H$28),0),2)} -> #N/A | U21: {=INDEX($M$6:$N$19,MATCH(1,(Q21=$M$6:$M$19)*(R21=$N$6:$N$19),0),2)} -> #N/A
B22: lt002_instrument | C22: GRSS_CMMSSN_INCM_OFF_BLNC | D22: 4. Validação da especificação | G22: lt002_instrument | H22: FLG_INTRBSNSS | I22: {=_xlfn.IFNA(IF(INDEX($B$6:$C$43,MATCH(1,(G22=$B$6:$B$43)*(H22=$C$6:$C$43),0),2)=H22,"Sim","Não"),"Não")} -> Sim | J22: Revalidar especificação --> validar a qualidade do campo através do teste regressivo | K22: A aguardar feedback da equipa anterior da Neyond | L22: ver c/ JB e HF | M22: lt007_instr_activity | N22: SSTNBL_CTGRY | O22: Fazer a especificação do campo, capitalizar info do Pilar 3, e necessário desagregar por linhas | P22: colocar em curso a especificação | Q22: lt002_instrument | R22: GRSS_INTRST_EXPNS | S22: {=INDEX($B$6:$C$43,MATCH(1,(Q22=$B$6:$B$43)*(R22=$C$6:$C$43),0),2)} -> GRSS_INTRST_EXPNS | T22: {=INDEX($G$6:$H$28,MATCH(1,(Q22=$G$6:$G$28)*(R22=$H$6:$H$28),0),2)} -> #N/A | U22: {=INDEX($M$6:$N$19,MATCH(1,(Q22=$M$6:$M$19)*(R22=$N$6:$N$19),0),2)} -> #N/A
B23: lt002_instrument | C23: GRSS_CMMSSN_EXPNS_OFF_BLNC | D23: 2. Concluído | G23: lt002_instrument | H23: INTRBSNSS_ADJ_COD | I23: {=_xlfn.IFNA(IF(INDEX($B$6:$C$43,MATCH(1,(G23=$B$6:$B$43)*(H23=$C$6:$C$43),0),2)=H23,"Sim","Não"),"Não")} -> Sim | J23: Revalidar especificação --> validar a qualidade do campo através do teste regressivo | K23: A aguardar feedback da equipa anterior da Neyond | Q23: lt002_instrument | R23: NT_LN_LSS_PRVSN_OFF_BLNC | S23: {=INDEX($B$6:$C$43,MATCH(1,(Q23=$B$6:$B$43)*(R23=$C$6:$C$43),0),2)} -> NT_LN_LSS_PRVSN_OFF_BLNC | T23: {=INDEX($G$6:$H$28,MATCH(1,(Q23=$G$6:$G$28)*(R23=$H$6:$H$28),0),2)} -> #N/A | U23: {=INDEX($M$6:$N$19,MATCH(1,(Q23=$M$6:$M$19)*(R23=$N$6:$N$19),0),2)} -> #N/A
B24: lt002_instrument | C24: RWA_OFF_BLNC | D24: 4. Validação da especificação | G24: lt002_instrument | H24: COD_SOC_DSTNTN | I24: {=_xlfn.IFNA(IF(INDEX($B$6:$C$43,MATCH(1,(G24=$B$6:$B$43)*(H24=$C$6:$C$43),0),2)=H24,"Sim","Não"),"Não")} -> Sim | J24: Revalidar especificação --> validar a qualidade do campo através do teste regressivo | K24: A aguardar feedback da equipa anterior da Neyond | Q24: lt002_instrument | R24: GRSS_INTRST_INCM_CCRR | S24: {=INDEX($B$6:$C$43,MATCH(1,(Q24=$B$6:$B$43)*(R24=$C$6:$C$43),0),2)} -> GRSS_INTRST_INCM_CCRR | T24: {=INDEX($G$6:$H$28,MATCH(1,(Q24=$G$6:$G$28)*(R24=$H$6:$H$28),0),2)} -> #N/A | U24: {=INDEX($M$6:$N$19,MATCH(1,(Q24=$M$6:$M$19)*(R24=$N$6:$N$19),0),2)} -> #N/A
B25: lt002_instrument | C25: GRSS_INTRST_EXPNS | D25: 2. Concluído | G25: lt002_instrument | H25: BSNSS_AREA_DSTNTN | I25: {=_xlfn.IFNA(IF(INDEX($B$6:$C$43,MATCH(1,(G25=$B$6:$B$43)*(H25=$C$6:$C$43),0),2)=H25,"Sim","Não"),"Não")} -> Sim | J25: Revalidar especificação --> validar a qualidade do campo através do teste regressivo | Q25: lt002_instrument | R25: GRSS_INTRST_EXPNS_CCRR | S25: {=INDEX($B$6:$C$43,MATCH(1,(Q25=$B$6:$B$43)*(R25=$C$6:$C$43),0),2)} -> GRSS_INTRST_EXPNS_CCRR | T25: {=INDEX($G$6:$H$28,MATCH(1,(Q25=$G$6:$G$28)*(R25=$H$6:$H$28),0),2)} -> #N/A | U25: {=INDEX($M$6:$N$19,MATCH(1,(Q25=$M$6:$M$19)*(R25=$N$6:$N$19),0),2)} -> #N/A
B26: lt002_instrument | C26: NT_LN_LSS_PRVSN_OFF_BLNC | D26: 2. Concluído | G26: lt002_instrument | H26: INTRNL_TRNSFR_RT_OFF_BLNC | I26: {=_xlfn.IFNA(IF(INDEX($B$6:$C$43,MATCH(1,(G26=$B$6:$B$43)*(H26=$C$6:$C$43),0),2)=H26,"Sim","Não"),"Não")} -> Sim | J26: Revalidar especificação --> validar a qualidade do campo através do teste regressivo | K26: Especificação validada com CdG. | Q26: lt002_instrument | R26: GRSS_CMMSSN_INCM_CCRR | S26: {=INDEX($B$6:$C$43,MATCH(1,(Q26=$B$6:$B$43)*(R26=$C$6:$C$43),0),2)} -> GRSS_CMMSSN_INCM_CCRR | T26: {=INDEX($G$6:$H$28,MATCH(1,(Q26=$G$6:$G$28)*(R26=$H$6:$H$28),0),2)} -> #N/A | U26: {=INDEX($M$6:$N$19,MATCH(1,(Q26=$M$6:$M$19)*(R26=$N$6:$N$19),0),2)} -> #N/A
B27: lt002_instrument | C27: GRSS_INTRST_INCM_CCRR | D27: 8. Por Iniciar | G27: lt002_instrument | H27: IDCMB | I27: {=_xlfn.IFNA(IF(INDEX($B$6:$C$43,MATCH(1,(G27=$B$6:$B$43)*(H27=$C$6:$C$43),0),2)=H27,"Sim","Não"),"Não")} -> Não | J27: Validar a qualidade do campo através do teste regressivo | Q27: lt002_instrument | R27: GRSS_CMMSSN_EXPNS_CCRR | S27: {=INDEX($B$6:$C$43,MATCH(1,(Q27=$B$6:$B$43)*(R27=$C$6:$C$43),0),2)} -> GRSS_CMMSSN_EXPNS_CCRR | T27: {=INDEX($G$6:$H$28,MATCH(1,(Q27=$G$6:$G$28)*(R27=$H$6:$H$28),0),2)} -> #N/A | U27: {=INDEX($M$6:$N$19,MATCH(1,(Q27=$M$6:$M$19)*(R27=$N$6:$N$19),0),2)} -> #N/A
B28: lt002_instrument | C28: GRSS_INTRST_EXPNS_CCRR | D28: 8. Por Iniciar | G28: lt002_instrument | H28: RWA_OFF_BLNC | I28: {=_xlfn.IFNA(IF(INDEX($B$6:$C$43,MATCH(1,(G28=$B$6:$B$43)*(H28=$C$6:$C$43),0),2)=H28,"Sim","Não"),"Não")} -> Sim | J28: Revalidar especificação --> validar a qualidade do campo através do teste regressivo | K28: Especificação validada com CdG. | Q28: lt002_instrument | R28: GNS_FNNCL_TRNSCTN_EXCHNG_CCRR | S28: {=INDEX($B$6:$C$43,MATCH(1,(Q28=$B$6:$B$43)*(R28=$C$6:$C$43),0),2)} -> GNS_FNNCL_TRNSCTN_EXCHNG_CCRR | T28: {=INDEX($G$6:$H$28,MATCH(1,(Q28=$G$6:$G$28)*(R28=$H$6:$H$28),0),2)} -> #N/A | U28: {=INDEX($M$6:$N$19,MATCH(1,(Q28=$M$6:$M$19)*(R28=$N$6:$N$19),0),2)} -> #N/A
B29: lt002_instrument | C29: GRSS_CMMSSN_INCM_CCRR | D29: 8. Por Iniciar | Q29: lt002_instrument | R29: BSNSS_AREA_CCRR | S29: {=INDEX($B$6:$C$43,MATCH(1,(Q29=$B$6:$B$43)*(R29=$C$6:$C$43),0),2)} -> BSNSS_AREA_CCRR | T29: {=INDEX($G$6:$H$28,MATCH(1,(Q29=$G$6:$G$28)*(R29=$H$6:$H$28),0),2)} -> #N/A | U29: {=INDEX($M$6:$N$19,MATCH(1,(Q29=$M$6:$M$19)*(R29=$N$6:$N$19),0),2)} -> #N/A
B30: lt002_instrument | C30: GRSS_CMMSSN_EXPNS_CCRR | D30: 8. Por Iniciar | Q30: lt002_instrument | R30: GRSS_CMMSSN_INCM_OFF_BLNC_CCRR | S30: {=INDEX($B$6:$C$43,MATCH(1,(Q30=$B$6:$B$43)*(R30=$C$6:$C$43),0),2)} -> GRSS_CMMSSN_INCM_OFF_BLNC_CCRR | T30: {=INDEX($G$6:$H$28,MATCH(1,(Q30=$G$6:$G$28)*(R30=$H$6:$H$28),0),2)} -> #N/A | U30: {=INDEX($M$6:$N$19,MATCH(1,(Q30=$M$6:$M$19)*(R30=$N$6:$N$19),0),2)} -> #N/A
B31: lt002_instrument | C31: GNS_FNNCL_TRNSCTN_EXCHNG_CCRR | D31: 8. Por Iniciar | Q31: lt002_instrument | R31: GRSS_CMMSSN_EXPNS_OFF_BLNC_CCRR | S31: {=INDEX($B$6:$C$43,MATCH(1,(Q31=$B$6:$B$43)*(R31=$C$6:$C$43),0),2)} -> GRSS_CMMSSN_EXPNS_OFF_BLNC_CCRR | T31: {=INDEX($G$6:$H$28,MATCH(1,(Q31=$G$6:$G$28)*(R31=$H$6:$H$28),0),2)} -> #N/A | U31: {=INDEX($M$6:$N$19,MATCH(1,(Q31=$M$6:$M$19)*(R31=$N$6:$N$19),0),2)} -> #N/A
B32: lt002_instrument | C32: BSNSS_AREA_CCRR | D32: 8. Por Iniciar | Q32: lt002_instrument | R32: CNCLLD_INSTRMNT_STTS | S32: {=INDEX($B$6:$C$43,MATCH(1,(Q32=$B$6:$B$43)*(R32=$C$6:$C$43),0),2)} -> #N/A | T32: {=INDEX($G$6:$H$28,MATCH(1,(Q32=$G$6:$G$28)*(R32=$H$6:$H$28),0),2)} -> #N/A | U32: {=INDEX($M$6:$N$19,MATCH(1,(Q32=$M$6:$M$19)*(R32=$N$6:$N$19),0),2)} -> #N/A | V32: Campo que mudou de nome
B33: lt002_instrument | C33: GRSS_CMMSSN_INCM_OFF_BLNC_CCRR | D33: 8. Por Iniciar | Q33: lt002_instrument | R33: TYP_OFF_BLNC_PRDCT | S33: {=INDEX($B$6:$C$43,MATCH(1,(Q33=$B$6:$B$43)*(R33=$C$6:$C$43),0),2)} -> #N/A | T33: {=INDEX($G$6:$H$28,MATCH(1,(Q33=$G$6:$G$28)*(R33=$H$6:$H$28),0),2)} -> #N/A | U33: {=INDEX($M$6:$N$19,MATCH(1,(Q33=$M$6:$M$19)*(R33=$N$6:$N$19),0),2)} -> TYP_OFF_BLNC_PRDCT
B34: lt002_instrument | C34: GRSS_CMMSSN_EXPNS_OFF_BLNC_CCRR | D34: 8. Por Iniciar | Q34: lt006_instr_protection | R34: COD_SOC | S34: {=INDEX($B$6:$C$43,MATCH(1,(Q34=$B$6:$B$43)*(R34=$C$6:$C$43),0),2)} -> #N/A | T34: {=INDEX($G$6:$H$28,MATCH(1,(Q34=$G$6:$G$28)*(R34=$H$6:$H$28),0),2)} -> #N/A | U34: {=INDEX($M$6:$N$19,MATCH(1,(Q34=$M$6:$M$19)*(R34=$N$6:$N$19),0),2)} -> COD_SOC
B35: lt002_instrument | C35: FLG_INSTRMNT_CNCLLD | D35: 0. Cancelado | E35: Novo nome "CNCLLD_INSTRMNT_STTS", e passou de ser um campo Y/N para uma code list | Q35: lt006_instr_protection | R35: DT_RFRNC | S35: {=INDEX($B$6:$C$43,MATCH(1,(Q35=$B$6:$B$43)*(R35=$C$6:$C$43),0),2)} -> #N/A | T35: {=INDEX($G$6:$H$28,MATCH(1,(Q35=$G$6:$G$28)*(R35=$H$6:$H$28),0),2)} -> #N/A | U35: {=INDEX($M$6:$N$19,MATCH(1,(Q35=$M$6:$M$19)*(R35=$N$6:$N$19),0),2)} -> DT_RFRNC
B36: lt824_assoc_kpi_gd | C36: ambito | D36: 3. Em Análise | Q36: lt006_instr_protection | R36: INSTRMNT_ID | S36: {=INDEX($B$6:$C$43,MATCH(1,(Q36=$B$6:$B$43)*(R36=$C$6:$C$43),0),2)} -> #N/A | T36: {=INDEX($G$6:$H$28,MATCH(1,(Q36=$G$6:$G$28)*(R36=$H$6:$H$28),0),2)} -> #N/A | U36: {=INDEX($M$6:$N$19,MATCH(1,(Q36=$M$6:$M$19)*(R36=$N$6:$N$19),0),2)} -> INSTRMNT_ID
B37: lt824_assoc_kpi_gd | C37: tipo_conta_local | D37: 3. Em Análise | Q37: lt006_instr_protection | R37: PRTCTN_ID | S37: {=INDEX($B$6:$C$43,MATCH(1,(Q37=$B$6:$B$43)*(R37=$C$6:$C$43),0),2)} -> #N/A | T37: {=INDEX($G$6:$H$28,MATCH(1,(Q37=$G$6:$G$28)*(R37=$H$6:$H$28),0),2)} -> #N/A | U37: {=INDEX($M$6:$N$19,MATCH(1,(Q37=$M$6:$M$19)*(R37=$N$6:$N$19),0),2)} -> PRTCTN_ID
B38: lt824_assoc_kpi_gd | C38: valor_gd | D38: 3. Em Análise | Q38: lt006_instr_protection | R38: TYP_RLTN | S38: {=INDEX($B$6:$C$43,MATCH(1,(Q38=$B$6:$B$43)*(R38=$C$6:$C$43),0),2)} -> #N/A | T38: {=INDEX($G$6:$H$28,MATCH(1,(Q38=$G$6:$G$28)*(R38=$H$6:$H$28),0),2)} -> #N/A | U38: {=INDEX($M$6:$N$19,MATCH(1,(Q38=$M$6:$M$19)*(R38=$N$6:$N$19),0),2)} -> #N/A
B39: lt824_assoc_kpi_gd | C39: kpi | D39: 3. Em Análise | Q39: lt004_protection | R39: COD_SOC | S39: {=INDEX($B$6:$C$43,MATCH(1,(Q39=$B$6:$B$43)*(R39=$C$6:$C$43),0),2)} -> #N/A | T39: {=INDEX($G$6:$H$28,MATCH(1,(Q39=$G$6:$G$28)*(R39=$H$6:$H$28),0),2)} -> #N/A | U39: {=INDEX($M$6:$N$19,MATCH(1,(Q39=$M$6:$M$19)*(R39=$N$6:$N$19),0),2)} -> COD_SOC
B40: lt824_assoc_kpi_gd | C40: ordem | D40: 3. Em Análise | Q40: lt004_protection | R40: DT_RFRNC | S40: {=INDEX($B$6:$C$43,MATCH(1,(Q40=$B$6:$B$43)*(R40=$C$6:$C$43),0),2)} -> #N/A | T40: {=INDEX($G$6:$H$28,MATCH(1,(Q40=$G$6:$G$28)*(R40=$H$6:$H$28),0),2)} -> #N/A | U40: {=INDEX($M$6:$N$19,MATCH(1,(Q40=$M$6:$M$19)*(R40=$N$6:$N$19),0),2)} -> DT_RFRNC
B41: lt824_assoc_kpi_gd | C41: ref_date | D41: 3. Em Análise | Q41: lt004_protection | R41: PRTCTN_ID | S41: {=INDEX($B$6:$C$43,MATCH(1,(Q41=$B$6:$B$43)*(R41=$C$6:$C$43),0),2)} -> #N/A | T41: {=INDEX($G$6:$H$28,MATCH(1,(Q41=$G$6:$G$28)*(R41=$H$6:$H$28),0),2)} -> #N/A | U41: {=INDEX($M$6:$N$19,MATCH(1,(Q41=$M$6:$M$19)*(R41=$N$6:$N$19),0),2)} -> PRTCTN_ID
B42: lt002_instrument | C42: SSTNBL_INDCTR | D42: 0. Cancelado | E42: Passou para a lt007_instr_activity; capitalizar a info do projeto Pilar 3 | Q42: lt004_protection | R42: TYP_PRTCTN | S42: {=INDEX($B$6:$C$43,MATCH(1,(Q42=$B$6:$B$43)*(R42=$C$6:$C$43),0),2)} -> #N/A | T42: {=INDEX($G$6:$H$28,MATCH(1,(Q42=$G$6:$G$28)*(R42=$H$6:$H$28),0),2)} -> #N/A | U42: {=INDEX($M$6:$N$19,MATCH(1,(Q42=$M$6:$M$19)*(R42=$N$6:$N$19),0),2)} -> TYP_PRTCTN
B43: lt002_instrument | C43: SSTNBL_CTGRY | D43: 0. Cancelado | E43: Passou para a lt007_instr_activity; capitalizar a info do projeto Pilar 3 | Q43: lt004_protection | R43: PRTCTN_VL | S43: {=INDEX($B$6:$C$43,MATCH(1,(Q43=$B$6:$B$43)*(R43=$C$6:$C$43),0),2)} -> #N/A | T43: {=INDEX($G$6:$H$28,MATCH(1,(Q43=$G$6:$G$28)*(R43=$H$6:$H$28),0),2)} -> #N/A | U43: {=INDEX($M$6:$N$19,MATCH(1,(Q43=$M$6:$M$19)*(R43=$N$6:$N$19),0),2)} -> PRTCTN_VL
Q44: lt004_protection | R44: FLG_ELCTRC_VHCL | S44: {=INDEX($B$6:$C$43,MATCH(1,(Q44=$B$6:$B$43)*(R44=$C$6:$C$43),0),2)} -> #N/A | T44: {=INDEX($G$6:$H$28,MATCH(1,(Q44=$G$6:$G$28)*(R44=$H$6:$H$28),0),2)} -> #N/A | U44: {=INDEX($M$6:$N$19,MATCH(1,(Q44=$M$6:$M$19)*(R44=$N$6:$N$19),0),2)} -> FLG_ELCTRC_VHCL
Q45: lt007_instr_activity | R45: COD_SOC | S45: {=INDEX($B$6:$C$43,MATCH(1,(Q45=$B$6:$B$43)*(R45=$C$6:$C$43),0),2)} -> #N/A | T45: {=INDEX($G$6:$H$28,MATCH(1,(Q45=$G$6:$G$28)*(R45=$H$6:$H$28),0),2)} -> #N/A | U45: {=INDEX($M$6:$N$19,MATCH(1,(Q45=$M$6:$M$19)*(R45=$N$6:$N$19),0),2)} -> #N/A
Q46: lt007_instr_activity | R46: DT_RFRNC | S46: {=INDEX($B$6:$C$43,MATCH(1,(Q46=$B$6:$B$43)*(R46=$C$6:$C$43),0),2)} -> #N/A | T46: {=INDEX($G$6:$H$28,MATCH(1,(Q46=$G$6:$G$28)*(R46=$H$6:$H$28),0),2)} -> #N/A | U46: {=INDEX($M$6:$N$19,MATCH(1,(Q46=$M$6:$M$19)*(R46=$N$6:$N$19),0),2)} -> #N/A
Q47: lt007_instr_activity | R47: INSTRMNT_ID | S47: {=INDEX($B$6:$C$43,MATCH(1,(Q47=$B$6:$B$43)*(R47=$C$6:$C$43),0),2)} -> #N/A | T47: {=INDEX($G$6:$H$28,MATCH(1,(Q47=$G$6:$G$28)*(R47=$H$6:$H$28),0),2)} -> #N/A | U47: {=INDEX($M$6:$N$19,MATCH(1,(Q47=$M$6:$M$19)*(R47=$N$6:$N$19),0),2)} -> #N/A
Q48: lt007_instr_activity | R48: SSTNBL_CTGRY | S48: {=INDEX($B$6:$C$43,MATCH(1,(Q48=$B$6:$B$43)*(R48=$C$6:$C$43),0),2)} -> #N/A | T48: {=INDEX($G$6:$H$28,MATCH(1,(Q48=$G$6:$G$28)*(R48=$H$6:$H$28),0),2)} -> #N/A | U48: {=INDEX($M$6:$N$19,MATCH(1,(Q48=$M$6:$M$19)*(R48=$N$6:$N$19),0),2)} -> #N/A | V48: campo que mudou de tabela
Q49: lt007_instr_activity | R49: PRCNTG_ACTVTY | S49: {=INDEX($B$6:$C$43,MATCH(1,(Q49=$B$6:$B$43)*(R49=$C$6:$C$43),0),2)} -> #N/A | T49: {=INDEX($G$6:$H$28,MATCH(1,(Q49=$G$6:$G$28)*(R49=$H$6:$H$28),0),2)} -> #N/A | U49: {=INDEX($M$6:$N$19,MATCH(1,(Q49=$M$6:$M$19)*(R49=$N$6:$N$19),0),2)} -> PRCNTG_ACTVTY
Q50: lt007_instr_activity | R50: SSTNBL_INDCTR | S50: {=INDEX($B$6:$C$43,MATCH(1,(Q50=$B$6:$B$43)*(R50=$C$6:$C$43),0),2)} -> #N/A | T50: {=INDEX($G$6:$H$28,MATCH(1,(Q50=$G$6:$G$28)*(R50=$H$6:$H$28),0),2)} -> #N/A | U50: {=INDEX($M$6:$N$19,MATCH(1,(Q50=$M$6:$M$19)*(R50=$N$6:$N$19),0),2)} -> #N/A | V50: campo que mudou de tabela

Sheet Auxiliar_GD
B7: Tipo de Teste | C7: Descrição
B8: 1. Universo | C8: Validação do universo
B9: 2. Campo | C9: Validação à informação do campo
B11: Categoria | C11: Descrição | D11: # Campos
B12: Assessment | C12: Validação da especificação efetuada pela Deloitte | D12: 25
B13: Testes Regressivos Campos Concluídos | C13: Testes regressivos aos campos já concluídos
B14: Testes Implementação Campos Novos | C14: Testes aos novos campos de forma a garantir a correta implementação
B15: Testes Regressivos Campos Novos | C15: Testes regressivos de forma a garantir que os novos campos não impactaram outros
B17: Status para Assessment - Campos especificados anteriormente pela Deloitte
B19: Status | C19: Descrição | D19: Owner
B20: 0. Cancelado | C20: Campo cancelado | D20: N/A
B21: 1. Fora de âmbito | C21: Campo não se encontra no âmbito do projeto | D21: N/A
B22: 2. Concluído | C22: Especificação do campo validada com CdG | D22: N/A
B23: 3. Em Análise | C23: Campo em análise pela equipa Neyond | D23: Neyond
B24: 4. Validação da especificação | C24: Especificação para validação da área de negócio | D24: CdG
B25: 5. Em Re-especificação | C25: Campo em re-especificação pela equipa Neyond | D25: Neyond
B26: 6. Em Implementação | C26: Campo em implementação por IT da nova especificação | D26: IT
B27: 7. Em Testes | C27: Campo em testes pela equipa de testes | D27: Neyond
B28: 8. Por Iniciar | C28: Campo não inciado pela equipa de testes | D28: Neyond
B30: Status para Especificações/Re-especificações
B32: Status | C32: Descrição | D32: Owner
B33: 0. Cancelado | C33: Campo cancelado | D33: N/A
B34: 1. Concluído | C34: Campo concluído com sucesso | D34: N/A
B35: 2. Em Teste | C35: Campo em testes pela equipa de testes | D35: Neyond
B36: 3. Em Especificação/Re-especificação | C36: Campo em especificação/re-especificação pela equipa de testes | D36: Neyond
B37: 4. Pendente de outros desenvolvimentos/validações | C37: Campo a aguardar informação de outros intervenientes para a sua especificação | D37: Outras áreas
B38: 5. Validação da especificação | C38: Especificação para validação da área de negócio | D38: CdG
B39: 6. Em Correção | C39: Campo com incidências e em correção por IT | D39: IT
B40: 7. Em Implementação | C40: Campo em implementação por IT | D40: IT
B41: 8. Por Iniciar | C41: Campo não inciado pela equipa de testes | D41: Neyond

Sheet Pivots_GD
B2: Categoria | C2: Assessment
B4: Row Labels | C4: Count of Status Atual
B5: 0. Cancelado | C5: 3
B6: 2. Concluído | C6: 31
B7: 4. Validação da especificação | C7: 1
B8: 3. Em Análise | C8: 3
B9: Grand Total | C9: 38
B12: Count of Status Atual | C12: Column Labels
B13: Row Labels | C13: 0. Cancelado | D13: 2. Concluído | E13: 4. Validação da especificação | F13: 3. Em Análise | G13: Grand Total
B14: lt002_instrument | C14: 3 | D14: 25 | E14: 1 | F14: 3 | G14: 32
B15: lt824_assoc_kpi_gd | D15: 6 | G15: 6
B16: Grand Total | C16: 3 | D16: 31 | E16: 1 | F16: 3 | G16: 38
