Workbook
Name _Hlk71900621: 'Campos IMP vs CNT'!$C$61
Name _Toc164082157: 'Campos IMP vs CNT'!#REF!
Name _Toc164082158: 'Campos IMP vs CNT'!$C$52
Name _Toc164082286: 'Campos IMP vs CNT'!$C$62
Name _Toc164082298: 'Campos IMP vs CNT'!$C$64
Name _Toc164082299: 'Campos IMP vs CNT'!$C$65
Name _Toc164082302: 'Campos IMP vs CNT'!$C$12
Name _Toc164082303: 'Campos IMP vs CNT'!$C$13
Name _Toc164082304: 'Campos IMP vs CNT'!$C$49
Name _Toc164082314: 'Campos IMP vs CNT'!$C$5
Name _Toc164082315: 'Campos IMP vs CNT'!$C$3
Name _Toc164082316: 'Campos IMP vs CNT'!$C$4
Name _Toc164082319: 'Campos IMP vs CNT'!$C$60
Name _Toc164082330: 'Campos IMP vs CNT'!$C$48
Name _Toc164082331: 'Campos IMP vs CNT'!$C$68
Name _Toc164082332: 'Campos IMP vs CNT'!$C$22
Name _Toc164082333: 'Campos IMP vs CNT'!$C$36
Name _Toc164082334: 'Campos IMP vs CNT'!$C$37
Name _Toc164082339: 'Campos IMP vs CNT'!$C$42
Name _Toc164082348: 'Campos IMP vs CNT'!$C$51
Name _Toc164082349: 'Campos IMP vs CNT'!$C$69
Name _Toc164082351: 'Campos IMP vs CNT'!$C$57
Name _Toc164082352: 'Campos IMP vs CNT'!$C$58
Name _Toc164082353: 'Campos IMP vs CNT'!$C$59
Name _Toc164082359: 'Campos IMP vs CNT'!$C$33
Name _Toc164082360: 'Campos IMP vs CNT'!$C$34
Name _Toc164082361: 'Campos IMP vs CNT'!$C$35
Name _Toc164082362: 'Campos IMP vs CNT'!$C$38
Name _Toc164082363: 'Campos IMP vs CNT'!$C$39
Name _Toc164082366: 'Campos IMP vs CNT'!$C$43
Name _Toc164082367: 'Campos IMP vs CNT'!$C$44
Name _Toc164082368: 'Campos IMP vs CNT'!$C$7
Name _Toc164082369: 'Campos IMP vs CNT'!$C$45
Name _Toc164082370: 'Campos IMP vs CNT'!$C$8
Name _Toc164082371: 'Campos IMP vs CNT'!$C$46
Name _Toc164082372: 'Campos IMP vs CNT'!$C$9
Name _Toc164082373: 'Campos IMP vs CNT'!$C$10
Name _Toc164082374: 'Campos IMP vs CNT'!$C$11
Name _Toc164082375: 'Campos IMP vs CNT'!$C$66
Name _Toc164082381: 'Campos IMP vs CNT'!#REF!
Name _Toc164082382: 'Campos IMP vs CNT'!$C$53
Name _Toc164082383: 'Campos IMP vs CNT'!$C$54
Name _Toc164082394: 'Campos IMP vs CNT'!#REF!
Name _Toc164082395: 'Campos IMP vs CNT'!#REF!
Name _Toc164082396: 'Campos IMP vs CNT'!#REF!
Name _Toc164082397: 'Campos IMP vs CNT'!#REF!

Sheet Status
U7: Status Atual | V7: (All)
U9: Row Labels | V9: Count of Categorização
C10: Âmbito (Projeto) | D10: PM | I10: Âmbito (Projeto) | J10: PM | U10: Fora OSI | V10: 119
R11: Potencial de proposta - Campos concluídos, sem melhorias identidicadas, mas com necessidade de documentação | U11: Analisar controlos NOK | V11: 16
C12: Count of Status Atual | J12: OSI VS FORA OSI | R12: Potencial de proposta - Campos com melhorias mais complexas identificadas na OSI ou fora da mesma. | U12: Melhorias estruturais (garantir coerência entre campos) | V12: 14
C13: Status Atual | D13: Fora OSI | E13: OSI | F13: Grand Total | J13: Fora OSI | L13: OSI | N13: Total # | O13: Total % | R13: Quick-win âmbito do projeto em curso | U13: Novo campo | V13: 9
C14: 1. Especificar | D14: 9 | E14: 1 | F14: 10 | I14: Quick Win | J14: # | K14: % | L14: # | M14: % | U14: Necessidade de correção de erros | V14: 5
C15: 2. Alterar especificação | D15: 3 | E15: 14 | F15: 17 | I15: Campo Fechado | J15: 69 | K15: 0.26436782 | L15: 96 | M15: 0.36781609 | N15: 165 | O15: 0.63218391 | U15: Campo concluído, mas sem ou pouca informação na fonte | V15: 10
C16: 3. Pendente de decisão | E16: 2 | F16: 2 | I16: Não | J16: 30 | K16: 0.11494253 | L16: 40 | M16: 0.1532567 | N16: 70 | O16: 0.26819923 | U16: Campo concluido | V16: 65
C17: 4.1 Em implementação - Re-especificação | D17: 1 | F17: 1 | I17: Sim | J17: 3 | K17: 0.011494253 | L17: 23 | M17: 0.088122605 | N17: 26 | O17: 0.099616858 | U17: OSI | V17: 227
C18: 5.1 Em testes - Re-especificação | D18: 4 | E18: 18 | F18: 22 | I18: Grand Total | J18: 102 | K18: 0.3908046 | L18: 159 | M18: 0.6091954 | N18: 261 | O18: 1 | U18: Alteração de especificação por parte do BCE | V18: 8
C19: 5.2 Em testes - Incidência | E19: 3 | F19: 3 | U19: Analisar controlos NOK | V19: 41
C20: 7. Analisar controlos e completude | D20: 16 | E20: 26 | F20: 42 | U20: Melhorias estruturais (garantir coerência entre campos) | V20: 37
C21: 8. Concluído - sem dados | D21: 6 | E21: 1 | F21: 7 | U21: Novo campo | V21: 6
C22: 9. Concluído | D22: 63 | E22: 94 | F22: 157 | U22: Necessidade de correção de erros | V22: 21
C23: Grand Total | D23: 102 | E23: 159 | F23: 261 | U23: Pendente de decisão | V23: 24
U24: Campo concluído, mas sem ou pouca informação na fonte | V24: 2
U25: Campo concluido | V25: 88
U26: Grand Total | V26: 346

Sheet PDS (old)
B8: 2 | C8: Especificação | D8: 11 | E8: Especificação
C9: ORGNL_PRTCTN_VL | E9: Campos Contabilidade
C10: DT_ORGNL_PRTCTN_VL | E10: IMPRMNT_STTS
E11: PRFRMNG_STTS
E12: IMPRMNT_STTS_PRVS
E13: PRFRMNG_STTS_PRVS
E14: DPD_12M_PRFRMNG_STTS
E15: DPD_24M_PRFRMNG_STTS
E16: DPD_PRFRMNG_STTS
E17: DT_IMPRMNT_STTS
E18: DT_IMPRMNT_STTS_PRVS
E19: DT_PRFRMNG_STTS
E20: DT_PRFRMNG_STTS_PRVS
J27: 1. Especificar | K27: 2. Alterar especificação | L27: 3. Pendente de decisão | M27: 4.1 Em implementação - Re-especificação | N27: 4.2 Em implementação - Incidência | O27: 5.1 Em testes - Re-especificação | P27: 5.2 Em testes - Incidência | Q27: 6. Outros Desenvolvimentos | R27: 7. Analisar controlos e completude | S27: 8. Concluído - sem dados | T27: 9. Concluído
I28: Status Atual | J28: =COUNTIF(Detalhe!$K:$K,J27) -> 50 | K28: =COUNTIF(Detalhe!$K:$K,K27) -> 41 | L28: =COUNTIF(Detalhe!$K:$K,L27) -> 8 | M28: =COUNTIF(Detalhe!$K:$K,M27) -> 1 | N28: =COUNTIF(Detalhe!$K:$K,N27) -> 0 | O28: =COUNTIF(Detalhe!$K:$K,O27) -> 32 | P28: =COUNTIF(Detalhe!$K:$K,P27) -> 9 | Q28: =COUNTIF(Detalhe!$K:$K,Q27) -> 10 | ... T28: =COUNTIF(Detalhe!$K:$K,T27) -> 161
I29: Status Inicial (pós OSI) | J29: =COUNTIF(Detalhe!$E:$E,J27) -> 50 | K29: =COUNTIF(Detalhe!$E:$E,K27) -> 42 | L29: =COUNTIF(Detalhe!$E:$E,L27) -> 17 | M29: =COUNTIF(Detalhe!$E:$E,M27) -> 4 | N29: =COUNTIF(Detalhe!$E:$E,N27) -> 0 | O29: =COUNTIF(Detalhe!$E:$E,O27) -> 21 | P29: =COUNTIF(Detalhe!$E:$E,P27) -> 17 | Q29: =COUNTIF(Detalhe!$E:$E,Q27) -> 10 | ... T29: =COUNTIF(Detalhe!$E:$E,T27) -> 151
I30: Variação | J30: {=_xlfn.IFS(J28>J29, "↑",J28<J29, "↓",J28=J29, "=")} -> = | K30: {=_xlfn.IFS(K28>K29, "↑",K28<K29, "↓",K28=K29, "=")} -> ↓ | L30: {=_xlfn.IFS(L28>L29, "↑",L28<L29, "↓",L28=L29, "=")} -> ↓ | M30: {=_xlfn.IFS(M28>M29, "↑",M28<M29, "↓",M28=M29, "=")} -> ↓ | N30: {=_xlfn.IFS(N28>N29, "↑",N28<N29, "↓",N28=N29, "=")} -> = | O30: {=_xlfn.IFS(O28>O29, "↑",O28<O29, "↓",O28=O29, "=")} -> ↑ | P30: {=_xlfn.IFS(P28>P29, "↑",P28<P29, "↓",P28=P29, "=")} -> ↓ | Q30: {=_xlfn.IFS(Q28>Q29, "↑",Q28<Q29, "↓",Q28=Q29, "=")} -> = | ... T30: {=_xlfn.IFS(T28>T29, "↑",T28<T29, "↓",T28=T29, "=")} -> ↑
I31: Progressão | J31: =J28-J29 -> 0 | K31: =K28-K29 -> -1 | L31: =L28-L29 -> -9 | M31: =M28-M29 -> -3 | N31: =N28-N29 -> 0 | O31: =O28-O29 -> 11 | P31: =P28-P29 -> -8 | Q31: =Q28-Q29 -> 0 | ... T31: =T28-T29 -> 10
J34: 3. Pendente de decisão - Identificados temas em OSI nos campos e é necessário identificar cauisticas (pode ficar como está ou ser alterado). Quem toma as decisões são as areas de negócio, porém o Luis poderá dar a decisão final
C35: 45555
B36: Tema | D36: Questão | I36: Decisão
B37: DT_ORGNL_PRTCTN_VL | D37: O campo 'dtvalia_resp_bem' só possuI informação para datas de referências posteriores a 2024-07-31. Como devemos proceder caso seja necessário reportar dados anteriores a Jul.2024? | I37: Manter a especificação com mapeamento após jul.24
B38: ORGNL_PRTCTN_VL | D38: O campo 'mavaliai_resp_bem' só possuI informação para datas de referências posteriores a 2024-07-31. Como devemos proceder caso seja necessário reportar dados anteriores a Jul.2024? | I38: Manter a especificação com mapeamento após jul.24
B39: DT_CNSTRCTN_STTS | D39: Teremos de criar uma tabela auxiliar com o histórico dos estados de construção e mapear para a data mais antiga do estado de construção atual. Uma vez que o MUG tem uma ótica de atualização diária, para o mapeamento e criação desta tabela auxiliar devemos olhar para uma ótica ou mensal? | I39: Criar tabela auxiliar e ir buscar a ref_date. Devemos utilizar uma ótica diária. Analisar controlos por amostragem.
B40: DT_CNSTRCTN_STTS | D40: Caso o bem só tenha um estado desde sempre/ desde que foi recebido como garantia devemos reportar a DT_INCPTN? E caso tenha mais do que um instrumento associado, qual a dt_incptn que devemos utilizar? A mais antiga? | I40: Questionar Corporação: 1) Caso o bem só tenha um estado desde sempre/ desde que foi recebido como garantia qual a data que devemos reportar? 2) A DR_CNSTRCTN_STTS pode ser anterior à DT_INCPTN? Estes casos poderão acontecer caso uma garantia esteja associada a mais do que um contrato.
B41: Campos Contabilidade vs Imparidade | D41: 12 campos com informação de Imparidade, em que a Contabilidade assumiu a ownership uma vez que reporta este dado. Avançamos na re-especificação dos campos utilizando o mapeamento das tabelas de Contabilidade para datas de referência após Dez.22 e a tabela 7_8 de Imparidade para datas anteriores a Dez.22? IMPRMNT_STTS PRFRMNG_STTS IMPRMNT_STTS_PRVS POCI PRFRMNG_STTS_PRVS DPD_12M_PRFRMNG_STTS DPD_24M_PRFRMNG_STTS DPD_PRFRMNG_STTS DT_IMPRMNT_STTS DT_IMPRMNT_STTS_PRVS DT_PRFRMNG_STTS DT_PRFRMNG_STTS_PRVS | I41: Atualmente o campo de stage está a ser populado com informação de Imparidade até Dez.19 e a partir de Jan.20 com informação da FR004. Deste modo, a alteração de especificação prende-se apenas com a alteração da data para Dez.22. Solicitar a Alexandre Gonçalvez que validem os campos após implementação de IT, sem prejuizo dos testes por parte da equipa LT.
B42: Campos Imparidade - Fonte da Verdade | D42: 12 campos de Imparidade. Devemos sugerir mapeamento dos campos tendo em conta a tabela de o David Texugo indicou e enviar para validação? Enviamos um e-mail a solicitar esse mapeamento, mas sem resposta até ao momento. EIR EIR_INCPTN IFRS9_CCF IFRS9_EAD IFRS9_LGD INTRNL_SGMNT_IFRS9 PD_IFRS9_12M_INCPTN PD_IFRS9_12M_RD PD_IFRS9_12M_RD_T1 PD_IFRS9_LFTM_INCPTN PD_IFRS9_RMNNG_LFTM_INCPTN PD_IFRS9_RMNNG_LFTM_RD | I42: Fazer proposta. Segmentar por campos OK e NOK.
B43: PRTCTN_VL | D43: 40 garantias imóveis com valor de proteção a zero, cuja origem são a G39 ou G26. Analisados por Henrique e Susana: 35 casos encontram-se no nosso ficheiro de Erros dos Métodos Indiciários com falta de informação: 33 – Apenas com informação na GP26 1 – Valor de avaliação a zero 1 - % de CI não encontrado para o critério 2 casos são do cliente Vilamoura World – imóvel não identificado 3 casos são do cliente IAD da Madeira e já foram distratados
B44: PRTCTN_VL | D44: 11 Garantias Imóveis cuja origem provêm das CSs, com valor da proteção igual a zero (não são clones). Para quem devemos enviar estes casos para análise?
B45: PRTCTN_VL | D45: 121 Garantias Imóveis com contratos de Leasing associados, cujo valor da proteção é zero (não são clones). Para quem devemos enviar estes casos para análise?
B46: PRTCTN_VL | D46: 1 garantia Financeira, cujo valor da proteção é zero – Caso não está na GT018 para datas posteriores a 2024-05-31. Devíamos retirar da LT os casos com o msldreal a zero (temos 25 casos)?
B47: PRTCTN_VL | D47: 46 casos com data inválidas 0001-01-01 para análise da equipa de leasing.
J49: 4.1 respecificado
J50: 4.2 IT não implementou corretamente
J51: 6. Outros desenvolvimentos - Não podemos avançar no campo por haver necessidade de alguma alteração no campo fonte
J52: 7. Controlos corporativos NOK que necessitam de ser analizados
J53: 8. Campos que não são para mexer
J54: 9. A partir do momento que sobe a CD

Sheet Aux.
B2: Estado | C2: Status Inicial | E2: Status Atual | F2: Status Atual (%) | G2: Progressão
B3: 1. Especificar | C3: =COUNTIFS(Detalhe!E:E,B3,Detalhe!W:W,"PM") -> 10 | D3: =C3/$C$14 -> 0.038314176 | E3: =COUNTIFS(Detalhe!K:K,B3,Detalhe!W:W,"PM") -> 10 | F3: =E3/$E$14 -> 0.038314176 | G3: =E3-C3 -> 0
B4: 2. Alterar especificação | C4: =COUNTIFS(Detalhe!E:E,B4,Detalhe!W:W,"PM") -> 18 | D4: =C4/$C$14 -> 0.068965517 | E4: =COUNTIFS(Detalhe!K:K,B4,Detalhe!W:W,"PM") -> 17 | F4: =E4/$E$14 -> 0.0651341 | G4: =E4-C4 -> -1
B5: 3. Pendente de decisão | C5: =COUNTIFS(Detalhe!E:E,B5,Detalhe!W:W,"PM") -> 11 | D5: =C5/$C$14 -> 0.042145594 | E5: =COUNTIFS(Detalhe!K:K,B5,Detalhe!W:W,"PM") -> 2 | F5: =E5/$E$14 -> 0.0076628352 | G5: =E5-C5 -> -9
B6: 4.1 Em implementação - Re-especificação | C6: =COUNTIFS(Detalhe!E:E,B6,Detalhe!W:W,"PM") -> 4 | D6: =C6/$C$14 -> 0.01532567 | E6: =COUNTIFS(Detalhe!K:K,B6,Detalhe!W:W,"PM") -> 1 | F6: =E6/$E$14 -> 0.0038314176 | G6: =E6-C6 -> -3
B7: 4.2 Em implementação - Incidência | C7: =COUNTIFS(Detalhe!E:E,B7,Detalhe!W:W,"PM") -> 0 | D7: =C7/$C$14 -> 0 | E7: =COUNTIFS(Detalhe!K:K,B7,Detalhe!W:W,"PM") -> 0 | F7: =E7/$E$14 -> 0 | G7: =E7-C7 -> 0
B8: 5.1 Em testes - Re-especificação | C8: =COUNTIFS(Detalhe!E:E,B8,Detalhe!W:W,"PM") -> 11 | D8: =C8/$C$14 -> 0.042145594 | E8: =COUNTIFS(Detalhe!K:K,B8,Detalhe!W:W,"PM") -> 22 | F8: =E8/$E$14 -> 0.084291188 | G8: =E8-C8 -> 11
B9: 5.2 Em testes - Incidência | C9: =COUNTIFS(Detalhe!E:E,B9,Detalhe!W:W,"PM") -> 11 | D9: =C9/$C$14 -> 0.042145594 | E9: =COUNTIFS(Detalhe!K:K,B9,Detalhe!W:W,"PM") -> 3 | F9: =E9/$E$14 -> 0.011494253 | G9: =E9-C9 -> -8
B10: 6. Outros Desenvolvimentos | C10: =COUNTIFS(Detalhe!E:E,B10,Detalhe!W:W,"PM") -> 0 | D10: =C10/$C$14 -> 0 | E10: =COUNTIFS(Detalhe!K:K,B10,Detalhe!W:W,"PM") -> 0 | F10: =E10/$E$14 -> 0 | G10: =E10-C10 -> 0
B11: 7. Analisar controlos e completude | C11: =COUNTIFS(Detalhe!E:E,B11,Detalhe!W:W,"PM") -> 42 | D11: =C11/$C$14 -> 0.16091954 | E11: =COUNTIFS(Detalhe!K:K,B11,Detalhe!W:W,"PM") -> 42 | F11: =E11/$E$14 -> 0.16091954 | G11: =E11-C11 -> 0
B12: 8. Concluído - sem dados | C12: =COUNTIFS(Detalhe!E:E,B12,Detalhe!W:W,"PM") -> 7 | D12: =C12/$C$14 -> 0.026819923 | E12: =COUNTIFS(Detalhe!K:K,B12,Detalhe!W:W,"PM") -> 7 | F12: =E12/$E$14 -> 0.026819923 | G12: =E12-C12 -> 0
B13: 9. Concluído | C13: =COUNTIFS(Detalhe!E:E,B13,Detalhe!W:W,"PM") -> 147 | D13: =C13/$C$14 -> 0.56321839 | E13: =COUNTIFS(Detalhe!K:K,B13,Detalhe!W:W,"PM") -> 157 | F13: =E13/$E$14 -> 0.60153257 | G13: =E13-C13 -> 10
C14: =SUM(C3:C13) -> 261 | E14: =SUM(E3:E13) -> 261

Sheet PDS
B8: 2 | C8: Especificação | D8: 11 | E8: Especificação
C9: ORGNL_PRTCTN_VL | E9: Campos Contabilidade
C10: DT_ORGNL_PRTCTN_VL | E10: IMPRMNT_STTS
E11: PRFRMNG_STTS
E12: IMPRMNT_STTS_PRVS
E13: PRFRMNG_STTS_PRVS
E14: DPD_12M_PRFRMNG_STTS
E15: DPD_24M_PRFRMNG_STTS
E16: DPD_PRFRMNG_STTS
E17: DT_IMPRMNT_STTS
E18: DT_IMPRMNT_STTS_PRVS
E19: DT_PRFRMNG_STTS
E20: DT_PRFRMNG_STTS_PRVS
J27: 1. Especificar | K27: 2. Alterar especificação | L27: 3. Pendente de decisão | M27: 4.1 Em implementação - Re-especificação | N27: 4.2 Em implementação - Incidência | O27: 5.1 Em testes - Re-especificação | P27: 5.2 Em testes - Incidência | Q27: 6. Outros Desenvolvimentos | R27: 7. Analisar controlos e completude | S27: 8. Concluído - sem dados | T27: 9. Concluído
I28: Status Atual | J28: =COUNTIFS(Detalhe!$K:$K,J27,Detalhe!$W:$W,"PM") -> 10 | K28: =COUNTIFS(Detalhe!$K:$K,K27,Detalhe!$W:$W,"PM") -> 17 | L28: =COUNTIFS(Detalhe!$K:$K,L27,Detalhe!$W:$W,"PM") -> 2 | M28: =COUNTIFS(Detalhe!$K:$K,M27,Detalhe!$W:$W,"PM") -> 1 | N28: =COUNTIFS(Detalhe!$K:$K,N27,Detalhe!$W:$W,"PM") -> 0 | O28: =COUNTIFS(Detalhe!$K:$K,O27,Detalhe!$W:$W,"PM") -> 22 | P28: =COUNTIFS(Detalhe!$K:$K,P27,Detalhe!$W:$W,"PM") -> 3 | Q28: =COUNTIFS(Detalhe!$K:$K,Q27,Detalhe!$W:$W,"PM") -> 0 | ... T28: =COUNTIFS(Detalhe!$K:$K,T27,Detalhe!$W:$W,"PM") -> 157
I29: Status Inicial (pós OSI) | J29: =COUNTIFS(Detalhe!$E:$E,J27,Detalhe!$W:$W,"PM") -> 10 | K29: =COUNTIFS(Detalhe!$E:$E,K27,Detalhe!$W:$W,"PM") -> 18 | L29: =COUNTIFS(Detalhe!$E:$E,L27,Detalhe!$W:$W,"PM") -> 11 | M29: =COUNTIFS(Detalhe!$E:$E,M27,Detalhe!$W:$W,"PM") -> 4 | N29: =COUNTIFS(Detalhe!$E:$E,N27,Detalhe!$W:$W,"PM") -> 0 | O29: =COUNTIFS(Detalhe!$E:$E,O27,Detalhe!$W:$W,"PM") -> 11 | P29: =COUNTIFS(Detalhe!$E:$E,P27,Detalhe!$W:$W,"PM") -> 11 | Q29: =COUNTIFS(Detalhe!$E:$E,Q27,Detalhe!$W:$W,"PM") -> 0 | ... T29: =COUNTIFS(Detalhe!$E:$E,T27,Detalhe!$W:$W,"PM") -> 147
I30: Variação | J30: {=_xlfn.IFS(J28>J29, "↑",J28<J29, "↓",J28=J29, "=")} -> = | K30: {=_xlfn.IFS(K28>K29, "↑",K28<K29, "↓",K28=K29, "=")} -> ↓ | L30: {=_xlfn.IFS(L28>L29, "↑",L28<L29, "↓",L28=L29, "=")} -> ↓ | M30: {=_xlfn.IFS(M28>M29, "↑",M28<M29, "↓",M28=M29, "=")} -> ↓ | N30: {=_xlfn.IFS(N28>N29, "↑",N28<N29, "↓",N28=N29, "=")} -> = | O30: {=_xlfn.IFS(O28>O29, "↑",O28<O29, "↓",O28=O29, "=")} -> ↑ | P30: {=_xlfn.IFS(P28>P29, "↑",P28<P29, "↓",P28=P29, "=")} -> ↓ | Q30: {=_xlfn.IFS(Q28>Q29, "↑",Q28<Q29, "↓",Q28=Q29, "=")} -> = | ... T30: {=_xlfn.IFS(T28>T29, "↑",T28<T29, "↓",T28=T29, "=")} -> ↑
I31: Progressão | J31: =J28-J29 -> 0 | K31: =K28-K29 -> -1 | L31: =L28-L29 -> -9 | M31: =M28-M29 -> -3 | N31: =N28-N29 -> 0 | O31: =O28-O29 -> 11 | P31: =P28-P29 -> -8 | Q31: =Q28-Q29 -> 0 | ... T31: =T28-T29 -> 10
I35: Legenda
I37: 1. Especificar | J37: O campo será especificado pela primeira vez
I38: 2. Alterar especificação | J38: O campo já foi especificado, no entanto foi necessário alterar
I39: 3. Pendente de decisão | J39: Houve algum tema identificado em OSI nos campos e é necessário identificar casuísticas (podendo ficar como está ou ser alterado). Quem toma as decisões são as áreas de negócio, porém o Luis poderá dar a decisão final
I40: 4.1 Em implementação - Re-especificação | J40: O campo já foi re-especificado e está do lado de IT
I41: 4.2 Em implementação - Incidência | J41: O campo já foi re-especificado e entregue, no entanto veio com erros de implementação por parte de IT
I42: 5.1 Em testes - Re-especificação | J42: O campo foi re-especificado e implementado por IT e está em fase de testes
I43: 5.2 Em testes - Incidência | J43: O campo foi re-especificado e implementado por IT, porém foram encontradas incidências que levaram a uma nova fase de testes
I44: 6. Outros Desenvolvimentos | J44: Não podemos avançar no campo por haver necessidade de alguma alteração no campo fonte pendente da área responsável
I45: 7. Analisar controlos e completude | J45: Controlos corporativos NOK que necessitam de ser analizados
I46: 8. Concluído - sem dados | J46: Campos que não são para alterar
I47: 9. Concluído | J47: O campo já subiu a CD

Sheet Detalhe
C2: Quick-win de alta prioridade
C3: Quick-win de média prioridade
B5: TABLE_NAME | C5: COLUMN_NAME | D5: ÂMBITO | E5: Status | F5: Controlos e Completude | G5: Descrição | H5: Detalhe | I5: Quick-win | J5: Data alteração status | K5: Status Atual | L5: Controlos e Completuade atual | M5: Comentários | N5: Data envio para IT | O5: Data Implementação | P5: Categorização | Q5: Structural ECB Loan Tape | R5: Green Dashboard | S5: Pillar III ESG | T5: Green Finance | U5: ESG Risks | V5: Leveraged Finance | W5: Âmbito (Projeto) | X5: STREAM
A6: =B6&"_"&C6 -> INSTRUMENT_ACCMLTD_CHNGS_FV_CR_INSTRMNT | B6: INSTRUMENT | C6: ACCMLTD_CHNGS_FV_CR_INSTRMNT | D6: OSI | E6: 9. Concluído | F6: OK | G6: Concluido, controlos OK | I6: Campo Fechado | J6: 45450 | K6: 9. Concluído | L6: =F6 -> OK | P6: Campo concluido | Q6: Y | R6: Y | S6: Y | T6: N | U6: N | V6: N | W6: PM | X6: 0
A7: =B7&"_"&C7 -> INSTRUMENT_ACCMLTD_IMPRMNT_INSTRMNT | B7: INSTRUMENT | C7: ACCMLTD_IMPRMNT_INSTRMNT | D7: OSI | E7: 9. Concluído | F7: OK | G7: Concluido, controlos OK | I7: Campo Fechado | J7: 45450 | K7: 9. Concluído | L7: =F7 -> OK | P7: Campo concluido | Q7: Y | R7: Y | S7: Y | T7: N | U7: N | V7: Y | W7: PM | X7: 6.1. Fora âmbito | Campos concluídos - Sem necessidade de espec.
A8: =B8&"_"&C8 -> INSTRUMENT_ACCMLTD_IMPRMNT_INSTRMNT_PRVS | B8: INSTRUMENT | C8: ACCMLTD_IMPRMNT_INSTRMNT_PRVS | D8: OSI | E8: 5.2 Em testes - Incidência | F8: OK | G8: Campo com incidência. Verificar fonte LT | I8: Sim | J8: 45450 | K8: 5.2 Em testes - Incidência | L8: =F8 -> OK | P8: Necessidade de correção de erros | Q8: Y | R8: N | S8: N | T8: N | U8: N | V8: Y | W8: LF | X8: 3. Campos em testes ou c/ incidências
A9: =B9&"_"&C9 -> INSTRUMENT_ACCMLTD_WRTFFS_INSTRMNT | B9: INSTRUMENT | C9: ACCMLTD_WRTFFS_INSTRMNT | D9: OSI | E9: 9. Concluído | F9: OK | G9: Concluido, controlos OK | I9: Campo Fechado | J9: 45450 | K9: 9. Concluído | L9: =F9 -> OK | P9: Campo concluido | Q9: Y | R9: N | S9: N | T9: N | U9: N | V9: Y | W9: PM | X9: 6.1. Fora âmbito | Campos concluídos - Sem necessidade de espec.
A10: =B10&"_"&C10 -> INSTRUMENT_ACCNTNG_CLSSFCTN | B10: INSTRUMENT | C10: ACCNTNG_CLSSFCTN | D10: OSI | E10: 9. Concluído | F10: OK | G10: Concluido, controlos OK | I10: Campo Fechado | J10: 45450 | K10: 9. Concluído | L10: =F10 -> OK | P10: Campo concluido | Q10: Y | R10: Y | S10: Y | T10: N | U10: N | V10: Y | W10: PM | X10: 6.1. Fora âmbito | Campos concluídos - Sem necessidade de espec.
A11: =B11&"_"&C11 -> ENTITY_ACCNTNG_FRMWRK_SL | B11: ENTITY | C11: ACCNTNG_FRMWRK_SL | D11: OSI | E11: 2. Alterar especificação | F11: OK | G11: Em especificação (Financial Statments CIB) | H11: Campo implementação, mas com falta de informação para o segmento de clientes CIB | I11: Não | J11: 45450 | K11: 2. Alterar especificação | L11: =F11 -> OK | P11: Melhorias estruturais (garantir coerência entre campos) | Q11: Y | R11: N | S11: N | T11: N | U11: N | V11: Y | W11: PM & LF | X11: 6.4. Fora âmbito | Re-especificação de campos complexos - Dem. Fin. CIB
A12: =B12&"_"&C12 -> INSTRUMENT_TYP_MRTGG | B12: INSTRUMENT | C12: TYP_MRTGG | D12: OSI | E12: 3. Pendente de decisão | F12: NOK | G12: Alteração da Code list por parte do BCE | I12: Sim | J12: 45568 | K12: 2. Alterar especificação | L12: =F12 -> NOK | M12: Alterar especificação de acordo com codelist atual. No MUG existem apenas garantias elegiveis para cálculo de capital? Se sim, TYP_MRTGG irá assumir os valores 1, 5 e N/A. Caso contrário assumirá os valores 1, 5, 6 e N/A. | P12: Alteração de especificação por parte do BCE | Q12: Y | R12: N | S12: N | T12: N | U12: N | V12: N | W12: PM | X12: 0
A13: =B13&"_"&C13 -> INSTRUMENT_AMNT_D_AT_MTRTY | B13: INSTRUMENT | C13: AMNT_D_AT_MTRTY | D13: OSI | E13: 1. Especificar | F13: NOK | G13: Re-especificar o campo utilizando o código da OSI (código é uma proxy com base no tipo de amortização e na frequência de pagamentos) | I13: Não | J13: 45450 | K13: 1. Especificar | L13: =F13 -> NOK | M13: Re-especificar o campo utilizando o código da OSI (código é uma proxy com base no tipo de amortização e na frequência de pagamentos) | P13: Novo campo | Q13: Y | R13: N | S13: N | T13: N | U13: N | V13: Y | W13: LF | X13: 2.2 Re-especificação de campos complexos - Resto
A14: =B14&"_"&C14 -> ENTITY_ANNL_TRNVR_LE | B14: ENTITY | C14: ANNL_TRNVR_LE | D14: OSI | E14: 2. Alterar especificação | F14: OK | G14: Em especificação (Financial Statments CIB) | H14: Campo implementação, mas com falta de informação para o segmento de clientes CIB | I14: Não | J14: 45450 | K14: 2. Alterar especificação | L14: =F14 -> OK | P14: Melhorias estruturais (garantir coerência entre campos) | Q14: Y | R14: N | S14: Y | T14: N | U14: N | V14: Y | W14: PM & LF | X14: 6.4. Fora âmbito | Re-especificação de campos complexos - Dem. Fin. CIB
A15: =B15&"_"&C15 -> ENTITY_ANNL_TRNVR_LE_BDR | B15: ENTITY | C15: ANNL_TRNVR_LE_BDR | D15: Fora OSI | E15: 9. Concluído | F15: OK | G15: Concluido, controlos OK | I15: Campo Fechado | J15: 45450 | K15: 9. Concluído | L15: =F15 -> OK | P15: Campo concluido | Q15: Y | R15: N | S15: N | T15: N | U15: N | V15: N | W15: PM | X15: 0
A16: =B16&"_"&C16 -> ENTITY_ANNL_TRNVR_PRVS | B16: ENTITY | C16: ANNL_TRNVR_PRVS | D16: OSI | E16: 2. Alterar especificação | F16: OK | G16: Em especificação (Financial Statments CIB) | H16: Campo implementação, mas com falta de informação para o segmento de clientes CIB | I16: Não | J16: 45450 | K16: 2. Alterar especificação | L16: =F16 -> OK | P16: Melhorias estruturais (garantir coerência entre campos) | Q16: Y | R16: N | S16: N | T16: N | U16: N | V16: Y | W16: PM & LF | X16: 6.4. Fora âmbito | Re-especificação de campos complexos - Dem. Fin. CIB
A17: =B17&"_"&C17 -> ENTITY_ANNL_TRNVR_PRVS_BDR | B17: ENTITY | C17: ANNL_TRNVR_PRVS_BDR | D17: Fora OSI | E17: 9. Concluído | F17: OK | G17: Concluido, controlos OK | I17: Campo Fechado | J17: 45450 | K17: 9. Concluído | L17: =F17 -> OK | P17: Campo concluido | Q17: Y | R17: N | S17: N | T17: N | U17: N | V17: N | W17: PM | X17: 0
A18: =B18&"_"&C18 -> INSTRUMENT_ANNLSD_AGRD_RT | B18: INSTRUMENT | C18: ANNLSD_AGRD_RT | D18: OSI | E18: 3. Pendente de decisão | F18: OK | G18: Verificar necessidade de alteração da fonte para fins de reconciliação. Rever Fonte | H18: Rever se devemos utilizar a informação de IFRS9 ou manter a de alm | I18: Sim | J18: 45450 | K18: 3. Pendente de decisão | L18: =F18 -> OK | P18: Pendente de decisão | Q18: Y | R18: N | S18: Y | T18: N | U18: N | V18: N | W18: PM | X18: 0
A19: =B19&"_"&C19 -> PROTECTION_APPRSL_CRRNCY | B19: PROTECTION | C19: APPRSL_CRRNCY | D19: OSI | E19: 7. Analisar controlos e completude | F19: NOK | G19: Controlos NOK | I19: Não | J19: 45450 | K19: 7. Analisar controlos e completude | L19: =F19 -> NOK | P19: Analisar controlos NOK | Q19: Y | R19: N | S19: N | T19: N | U19: N | V19: N | W19: PM | X19: 0
A20: =B20&"_"&C20 -> PROTECTION_APPRSR | B20: PROTECTION | C20: APPRSR | D20: OSI | E20: 7. Analisar controlos e completude | F20: NOK | G20: Controlos NOK | I20: Não | J20: 45450 | K20: 7. Analisar controlos e completude | L20: =F20 -> NOK | P20: Analisar controlos NOK | Q20: Y | R20: N | S20: N | T20: N | U20: N | V20: N | W20: PM | X20: 0
A21: =B21&"_"&C21 -> INSTRUMENT_ARRRS_INSTRMNT | B21: INSTRUMENT | C21: ARRRS_INSTRMNT | D21: OSI | E21: 7. Analisar controlos e completude | F21: NOK | G21: Controlos NOK | I21: Não | J21: 45450 | K21: 7. Analisar controlos e completude | L21: =F21 -> NOK | P21: Analisar controlos NOK | Q21: Y | R21: N | S21: N | T21: N | U21: N | V21: Y | W21: LF | X21: 4. Campos com NOK controlos Corporativos
A22: =B22&"_"&C22 -> INSTRUMENT_ARRRS_INSTRMNT_12M | B22: INSTRUMENT | C22: ARRRS_INSTRMNT_12M | D22: OSI | E22: 7. Analisar controlos e completude | F22: NOK | G22: Controlos NOK | I22: Não | J22: 45450 | K22: 7. Analisar controlos e completude | L22: =F22 -> NOK | P22: Analisar controlos NOK | Q22: Y | R22: N | S22: N | T22: N | U22: N | V22: N | W22: PM | X22: 0
A23: =B23&"_"&C23 -> INSTRUMENT_ASST_SCRT_CLSS | B23: INSTRUMENT | C23: ASST_SCRT_CLSS | D23: Fora OSI | E23: 9. Concluído | F23: OK | G23: Concluido, controlos OK | I23: Campo Fechado | J23: 45450 | K23: 9. Concluído | L23: =F23 -> OK | P23: Campo concluido | Q23: Y | R23: N | S23: N | T23: N | U23: N | V23: N | W23: PM | X23: 0
A24: =B24&"_"&C24 -> INSTRUMENT_BRCHD_CVNNTS | B24: INSTRUMENT | C24: BRCHD_CVNNTS | D24: OSI | E24: 8. Concluído - sem dados | F24: OK | G24: Campo especificado, mas sem dados. Campo marcado com MISS ou NA | I24: Campo Fechado | J24: 45450 | K24: 8. Concluído - sem dados | L24: =F24 -> OK | P24: Campo concluído, mas sem ou pouca informação na fonte | Q24: Y | R24: N | S24: N | T24: N | U24: N | V24: Y | W24: PM | X24: 6.1. Fora âmbito | Campos concluídos - Sem necessidade de espec.
A25: =B25&"_"&C25 -> ENTITY_CAPEX | B25: ENTITY | C25: CAPEX | D25: OSI | E25: 2. Alterar especificação | F25: OK | G25: Em especificação (Financial Statments CIB) | H25: Campo implementação, mas com falta de informação para o segmento de clientes CIB | I25: Não | J25: 45450 | K25: 2. Alterar especificação | L25: =F25 -> OK | P25: Melhorias estruturais (garantir coerência entre campos) | Q25: Y | R25: N | S25: N | T25: N | U25: N | V25: N | W25: PM | X25: 0
A26: =B26&"_"&C26 -> ENTITY_CAPEX_PRVS | B26: ENTITY | C26: CAPEX_PRVS | D26: OSI | E26: 2. Alterar especificação | F26: OK | G26: Em especificação (Financial Statments CIB) | H26: Campo implementação, mas com falta de informação para o segmento de clientes CIB | I26: Não | J26: 45450 | K26: 2. Alterar especificação | L26: =F26 -> OK | P26: Melhorias estruturais (garantir coerência entre campos) | Q26: Y | R26: N | S26: N | T26: N | U26: N | V26: N | W26: PM | X26: 0
A27: =B27&"_"&C27 -> INSTRUMENT_CCF | B27: INSTRUMENT | C27: CCF | D27: OSI | E27: 9. Concluído | F27: OK | G27: Concluido, controlos OK | I27: Campo Fechado | J27: 45450 | K27: 9. Concluído | L27: =F27 -> OK | P27: Campo concluido | Q27: Y | R27: Y | S27: N | T27: N | U27: N | V27: Y | W27: PM | X27: 6.1. Fora âmbito | Campos concluídos - Sem necessidade de espec.
A28: =B28&"_"&C28 -> INSTRUMENT_CHNNL_ORGNTN | B28: INSTRUMENT | C28: CHNNL_ORGNTN | D28: Fora OSI | E28: 4.1 Em implementação - Re-especificação | F28: NOK | G28: Aguarda implementação de IT | I28: Não | J28: 45450 | K28: 4.1 Em implementação - Re-especificação | L28: =F28 -> NOK | N28: 45296 | P28: Melhorias estruturais (garantir coerência entre campos) | Q28: Y | R28: N | S28: N | T28: N | U28: N | V28: N | W28: PM | X28: 0
A29: =B29&"_"&C29 -> ENTITY_CLLCTN_MD | B29: ENTITY | C29: CLLCTN_MD | D29: Fora OSI | E29: 9. Concluído | F29: OK | G29: Concluido, controlos OK | I29: Campo Fechado | J29: 45450 | K29: 9. Concluído | L29: =F29 -> OK | P29: Campo concluido | Q29: Y | R29: N | S29: N | T29: N | U29: N | V29: N | W29: PM | X29: 0
A30: =B30&"_"&C30 -> ENTITY_TTL_INTRST_PD | B30: ENTITY | C30: TTL_INTRST_PD | D30: Fora OSI | E30: 2. Alterar especificação | F30: NOK | G30: Em especificação (Amortizações Capital/ Juros) | I30: Não | J30: 45450 | K30: 2. Alterar especificação | L30: =F30 -> NOK | P30: Melhorias estruturais (garantir coerência entre campos) | Q30: Y | R30: N | S30: N | T30: N | U30: N | V30: Y | W30: LF | X30: 2.2 Re-especificação de campos complexos - Resto
A31: =B31&"_"&C31 -> INSTRUMENT_CMMTMNT_INCPTN_INSTRMNT | B31: INSTRUMENT | C31: CMMTMNT_INCPTN_INSTRMNT | D31: OSI | E31: 7. Analisar controlos e completude | F31: NOK | G31: Analisar controlos e completude | I31: Não | J31: 45450 | K31: 7. Analisar controlos e completude | L31: =F31 -> NOK | P31: Analisar controlos NOK | Q31: Y | R31: N | S31: N | T31: N | U31: N | V31: N | W31: PM | X31: 0
A32: =B32&"_"&C32 -> PROTECTION_RL_ESTT_CLLTRL_LCTN | B32: PROTECTION | C32: RL_ESTT_CLLTRL_LCTN | D32: OSI | E32: 2. Alterar especificação | F32: NOK | G32: Alterados 3 casos. Campo está a devolver PT para todas as proteções, no entanto estas não estão localizadas em PT e alterou-se a localização para os respetivos paises. | I32: Não | J32: 45450 | K32: 2. Alterar especificação | L32: =F32 -> NOK | P32: Melhorias estruturais (garantir coerência entre campos) | Q32: Y | R32: N | S32: Y | T32: N | U32: Y | V32: N | W32: PM | X32: 0
A33: =B33&"_"&C33 -> INSTRUMENT_CMPLNT_MRTR_C19_NM | B33: INSTRUMENT | C33: CMPLNT_MRTR_C19_NM | D33: Fora OSI | E33: 9. Concluído | F33: OK | G33: Concluido, controlos OK | I33: Campo Fechado | J33: 45450 | K33: 9. Concluído | L33: =F33 -> OK | P33: Campo concluido | Q33: Y | R33: N | S33: N | T33: N | U33: N | V33: N | W33: PM | X33: 0
A34: =B34&"_"&C34 -> INSTRUMENT_CNSMPTN_FNRP18 | B34: INSTRUMENT | C34: CNSMPTN_FNRP18 | D34: Fora OSI | E34: 9. Concluído | F34: OK | G34: Concluido, controlos OK | I34: Campo Fechado | J34: 45450 | K34: 9. Concluído | L34: =F34 -> OK | P34: Campo concluido | Q34: Y | R34: N | S34: N | T34: N | U34: N | V34: N | W34: PM | X34: 0
A35: =B35&"_"&C35 -> PROTECTION_DT_APPRSL_PRVS | B35: PROTECTION | C35: DT_APPRSL_PRVS | D35: OSI | E35: 5.2 Em testes - Incidência | F35: NOK | G35: Campo com incidência e controlos NOK | H35: 1) Campo com incidência, data igual à data da protection_vl 2) Alteração de formatos MISS | I35: Campo Fechado | J35: 45670 | K35: 9. Concluído | L35: OK | M35: Alteraração da definição do campo no Guia da Corporação. Campo passou a reportar a data da avaliação completa anterior à data da última avaliação completa. | N35: 45485 | O35: 45646 | P35: Alteração de especificação por parte do BCE | Q35: Y | R35: N | S35: N | T35: N | U35: N | V35: N | W35: PM | X35: 0
A36: =B36&"_"&C36 -> INSTRUMENT_CNTRCT_ID | B36: INSTRUMENT | C36: CNTRCT_ID | D36: OSI | E36: 9. Concluído | F36: OK | G36: Concluido, controlos OK | I36: Campo Fechado | J36: 45450 | K36: 9. Concluído | L36: =F36 -> OK | P36: Campo concluido | Q36: Y | R36: N | S36: N | T36: N | U36: N | V36: N | W36: PM | X36: 0
A37: =B37&"_"&C37 -> INSTRUMENT_CNTRCT_ID_BDR | B37: INSTRUMENT | C37: CNTRCT_ID_BDR | D37: Fora OSI | E37: 9. Concluído | F37: OK | G37: Concluido, controlos OK | I37: Campo Fechado | J37: 45450 | K37: 9. Concluído | L37: =F37 -> OK | P37: Campo concluido | Q37: Y | R37: N | S37: N | T37: N | U37: N | V37: N | W37: PM | X37: 0
A38: =B38&"_"&C38 -> ENTITY_CNTRY | B38: ENTITY | C38: CNTRY | D38: OSI | E38: 9. Concluído | F38: OK | G38: Concluido, controlos OK | I38: Campo Fechado | J38: 45450 | K38: 9. Concluído | L38: =F38 -> OK | P38: Campo concluido | Q38: Y | R38: N | S38: Y | T38: N | U38: Y | V38: Y | W38: PM | X38: 6.1. Fora âmbito | Campos concluídos - Sem necessidade de espec.
A39: =B39&"_"&C39 -> ENTITY_COD_SOC | B39: ENTITY | C39: COD_SOC | D39: OSI | E39: 9. Concluído | F39: OK | G39: Concluido, controlos OK | I39: Campo Fechado | J39: 45450 | K39: 9. Concluído | L39: =F39 -> OK | P39: Campo concluido | Q39: Y | R39: N | S39: Y | T39: N | U39: Y | V39: Y | W39: PM | X39: 6.1. Fora âmbito | Campos concluídos - Sem necessidade de espec.
A40: =B40&"_"&C40 -> INSTR_ENTITY_COD_SOC | B40: INSTR_ENTITY | C40: COD_SOC | D40: OSI | E40: 9. Concluído | F40: OK | G40: Concluido, controlos OK | I40: Campo Fechado | J40: 45450 | K40: 9. Concluído | L40: =F40 -> OK | P40: Campo concluido | Q40: Y | R40: N | S40: Y | T40: N | U40: N | V40: Y | W40: PM | X40: 6.1. Fora âmbito | Campos concluídos - Sem necessidade de espec.
A41: =B41&"_"&C41 -> INSTR_PROTECTION_COD_SOC | B41: INSTR_PROTECTION | C41: COD_SOC | D41: OSI | E41: 9. Concluído | F41: OK | G41: Concluido, controlos OK | I41: Campo Fechado | J41: 45450 | K41: 9. Concluído | L41: =F41 -> OK | P41: Campo concluido | Q41: Y | R41: Y | S41: Y | T41: N | U41: N | V41: N | W41: PM | X41: 0
A42: =B42&"_"&C42 -> INSTRUMENT_COD_SOC | B42: INSTRUMENT | C42: COD_SOC | D42: OSI | E42: 9. Concluído | F42: OK | G42: Concluido, controlos OK | I42: Campo Fechado | J42: 45450 | K42: 9. Concluído | L42: =F42 -> OK | P42: Campo concluido | Q42: Y | R42: Y | S42: Y | T42: N | U42: Y | V42: Y | W42: PM | X42: 6.1. Fora âmbito | Campos concluídos - Sem necessidade de espec.
A43: =B43&"_"&C43 -> PROTECTION_COD_SOC | B43: PROTECTION | C43: COD_SOC | D43: OSI | E43: 9. Concluído | F43: OK | G43: Concluido, controlos OK | I43: Campo Fechado | J43: 45450 | K43: 9. Concluído | L43: =F43 -> OK | P43: Campo concluido | Q43: Y | R43: Y | S43: Y | T43: N | U43: Y | V43: N | W43: PM | X43: 0
A44: =B44&"_"&C44 -> INSTRUMENT_COD_SOC_INTRGRP | B44: INSTRUMENT | C44: COD_SOC_INTRGRP | D44: OSI | E44: 4.1 Em implementação - Re-especificação | F44: NOK | G44: Aguarda implementação de IT | I44: Não | J44: 45460 | K44: 5.1 Em testes - Re-especificação | L44: =F44 -> NOK | N44: 45303 | O44: 45379 | P44: Novo campo | Q44: Y | R44: Y | S44: N | T44: N | U44: N | V44: N | W44: PM | X44: 0
A45: =B45&"_"&C45 -> INSTRUMENT_CPN_CRRNCY | B45: INSTRUMENT | C45: CPN_CRRNCY | D45: Fora OSI | E45: 9. Concluído | F45: OK | G45: Concluido, controlos OK | I45: Campo Fechado | J45: 45450 | K45: 9. Concluído | L45: =F45 -> OK | P45: Campo concluido | Q45: Y | R45: N | S45: N | T45: N | U45: N | V45: N | W45: PM | X45: 0
A46: =B46&"_"&C46 -> INSTRUMENT_CPN_RT_FXD | B46: INSTRUMENT | C46: CPN_RT_FXD | D46: Fora OSI | E46: 9. Concluído | F46: OK | G46: Concluido, controlos OK | I46: Campo Fechado | J46: 45450 | K46: 9. Concluído | L46: =F46 -> OK | P46: Campo concluido | Q46: Y | R46: N | S46: N | T46: N | U46: N | V46: N | W46: PM | X46: 0
A47: =B47&"_"&C47 -> ENTITY_CR_FLG | B47: ENTITY | C47: CR_FLG | D47: Fora OSI | E47: 7. Analisar controlos e completude | F47: NOK | G47: Controlos NOK | I47: Não | J47: 45450 | K47: 7. Analisar controlos e completude | L47: =F47 -> NOK | P47: Analisar controlos NOK | Q47: Y | R47: N | S47: N | T47: N | U47: N | V47: N | W47: PM | X47: 0
A48: =B48&"_"&C48 -> INSTRUMENT_CRE_FNRP18 | B48: INSTRUMENT | C48: CRE_FNRP18 | D48: OSI | E48: 9. Concluído | F48: OK | G48: Concluido, controlos OK | I48: Campo Fechado | J48: 45450 | K48: 9. Concluído | L48: =F48 -> OK | P48: Campo concluido | Q48: Y | R48: N | S48: N | T48: N | U48: N | V48: N | W48: PM | X48: 0
A49: =B49&"_"&C49 -> PROTECTION_CRE_INCM_CRRNCY | B49: PROTECTION | C49: CRE_INCM_CRRNCY | D49: Fora OSI | E49: 8. Concluído - sem dados | F49: NOK | G49: Campo sem mapeamento, para análise da área de Riscos | I49: Campo Fechado | J49: 45450 | K49: 8. Concluído - sem dados | L49: =F49 -> NOK | P49: Campo concluído, mas sem ou pouca informação na fonte | Q49: Y | R49: N | S49: N | T49: N | U49: N | V49: N | W49: PM | X49: 0
A50: =B50&"_"&C50 -> PROTECTION_CRE_YRLY_EXPNSS | B50: PROTECTION | C50: CRE_YRLY_EXPNSS | D50: Fora OSI | E50: 8. Concluído - sem dados | F50: OK | G50: Campo sem mapeamento, para análise da área de Riscos | I50: Campo Fechado | J50: 45450 | K50: 8. Concluído - sem dados | L50: =F50 -> OK | P50: Campo concluído, mas sem ou pouca informação na fonte | Q50: Y | R50: N | S50: N | T50: N | U50: N | V50: N | W50: PM | X50: 0
A51: =B51&"_"&C51 -> PROTECTION_CRE_YRLY_INCM | B51: PROTECTION | C51: CRE_YRLY_INCM | D51: Fora OSI | E51: 8. Concluído - sem dados | F51: OK | G51: Campo sem mapeamento, para análise da área de Riscos | I51: Campo Fechado | J51: 45450 | K51: 8. Concluído - sem dados | L51: =F51 -> OK | P51: Campo concluído, mas sem ou pouca informação na fonte | Q51: Y | R51: N | S51: N | T51: N | U51: N | V51: N | W51: PM | X51: 0
A52: =B52&"_"&C52 -> INSTRUMENT_CRRLTN_CFFCNT | B52: INSTRUMENT | C52: CRRLTN_CFFCNT | D52: Fora OSI | E52: 7. Analisar controlos e completude | F52: NOK | G52: Controlos NOK | I52: Não | J52: 45450 | K52: 7. Analisar controlos e completude | L52: =F52 -> NOK | P52: Analisar controlos NOK | Q52: Y | R52: N | S52: N | T52: N | U52: N | V52: N | W52: PM | X52: 0
A53: =B53&"_"&C53 -> INSTRUMENT_CRRNCY_DNMNTN | B53: INSTRUMENT | C53: CRRNCY_DNMNTN | D53: OSI | E53: 9. Concluído | F53: OK | G53: Concluido, controlos OK | I53: Campo Fechado | J53: 45450 | K53: 9. Concluído | L53: =F53 -> OK | P53: Campo concluido | Q53: Y | R53: N | S53: N | T53: N | U53: N | V53: Y | W53: PM | X53: 6.1. Fora âmbito | Campos concluídos - Sem necessidade de espec.
A54: =B54&"_"&C54 -> INSTRUMENT_CRRYNG_AMNT_INSTRMNT | B54: INSTRUMENT | C54: CRRYNG_AMNT_INSTRMNT | D54: OSI | E54: 9. Concluído | F54: OK | G54: Concluido, controlos OK | I54: Campo Fechado | J54: 45450 | K54: 9. Concluído | L54: =F54 -> OK | P54: Campo concluido | Q54: Y | R54: N | S54: N | T54: N | U54: N | V54: Y | W54: PM | X54: 6.1. Fora âmbito | Campos concluídos - Sem necessidade de espec.
A55: =B55&"_"&C55 -> ENTITY_CSH | B55: ENTITY | C55: CSH | D55: OSI | E55: 2. Alterar especificação | F55: OK | G55: Em especificação (Financial Statments CIB) | H55: Campo implementação, mas com falta de informação para o segmento de clientes CIB | I55: Não | J55: 45450 | K55: 2. Alterar especificação | L55: =F55 -> OK | P55: Melhorias estruturais (garantir coerência entre campos) | Q55: Y | R55: N | S55: N | T55: N | U55: N | V55: N | W55: PM | X55: 0
A56: =B56&"_"&C56 -> ENTITY_CSH_PRVS | B56: ENTITY | C56: CSH_PRVS | D56: OSI | E56: 2. Alterar especificação | F56: OK | G56: Em especificação (Financial Statments CIB) | H56: Campo implementação, mas com falta de informação para o segmento de clientes CIB | I56: Não | J56: 45450 | K56: 2. Alterar especificação | L56: =F56 -> OK | P56: Melhorias estruturais (garantir coerência entre campos) | Q56: Y | R56: N | S56: N | T56: N | U56: N | V56: N | W56: PM | X56: 0
A57: =B57&"_"&C57 -> INSTRUMENT_CSH_SWP_TRP | B57: INSTRUMENT | C57: CSH_SWP_TRP | D57: OSI | E57: 9. Concluído | F57: OK | G57: Concluido, controlos OK | I57: Campo Fechado | J57: 45450 | K57: 9. Concluído | L57: =F57 -> OK | P57: Campo concluido | Q57: Y | R57: N | S57: N | T57: N | U57: N | V57: Y | W57: PM | X57: 6.1. Fora âmbito | Campos concluídos - Sem necessidade de espec.
A58: =B58&"_"&C58 -> INSTRUMENT_CVNNT_STTS | B58: INSTRUMENT | C58: CVNNT_STTS | D58: Fora OSI | E58: 8. Concluído - sem dados | F58: OK | G58: Campo especificado, mas sem dados. Campo marcado com MISS ou NA | I58: Campo Fechado | J58: 45450 | K58: 8. Concluído - sem dados | L58: =F58 -> OK | P58: Campo concluído, mas sem ou pouca informação na fonte | Q58: Y | R58: N | S58: N | T58: N | U58: N | V58: Y | W58: PM & LF | X58: 6.3. Fora âmbito | Fonte Manual LF
A59: =B59&"_"&C59 -> INSTRUMENT_CVNNT_TYP | B59: INSTRUMENT | C59: CVNNT_TYP | D59: Fora OSI | E59: 9. Concluído | F59: OK | G59: Concluido, controlos OK | I59: Campo Fechado | J59: 45450 | K59: 9. Concluído | L59: =F59 -> OK | P59: Campo concluido | Q59: Y | R59: N | S59: N | T59: N | U59: N | V59: Y | W59: PM & LF | X59: 6.3. Fora âmbito | Fonte Manual LF
A60: =B60&"_"&C60 -> ENTITY_DBT_RPYMNT_CPCTY_SNR_DBT | B60: ENTITY | C60: DBT_RPYMNT_CPCTY_SNR_DBT | D60: Fora OSI | E60: 8. Concluído - sem dados | F60: OK | G60: Campo especificado, mas sem dados. Campo marcado com MISS ou NA | I60: Campo Fechado | J60: 45450 | K60: 8. Concluído - sem dados | L60: =F60 -> OK | P60: Campo concluído, mas sem ou pouca informação na fonte | Q60: Y | R60: N | S60: N | T60: N | U60: N | V60: Y | W60: PM & LF | X60: 6.3. Fora âmbito | Fonte Manual LF
A61: =B61&"_"&C61 -> ENTITY_DBT_RPYMNT_CPCTY_TTL | B61: ENTITY | C61: DBT_RPYMNT_CPCTY_TTL | D61: Fora OSI | E61: 9. Concluído | F61: OK | G61: Concluido, controlos OK | I61: Campo Fechado | J61: 45450 | K61: 9. Concluído | L61: =F61 -> OK | P61: Campo concluido | Q61: Y | R61: N | S61: N | T61: N | U61: N | V61: Y | W61: PM | X61: 6.1. Fora âmbito | Campos concluídos - Sem necessidade de espec.
A62: =B62&"_"&C62 -> ENTITY_DBT_SRVC_RT | B62: ENTITY | C62: DBT_SRVC_RT | D62: OSI | E62: 2. Alterar especificação | F62: OK | G62: Em especificação (Financial Statments CIB) | H62: Campo implementação, mas com falta de informação para o segmento de clientes CIB | I62: Não | J62: 45450 | K62: 2. Alterar especificação | L62: =F62 -> OK | P62: Melhorias estruturais (garantir coerência entre campos) | Q62: Y | R62: N | S62: N | T62: N | U62: N | V62: N | W62: PM | X62: 0
A63: =B63&"_"&C63 -> ENTITY_DBT_SRVC_RT_12M | B63: ENTITY | C63: DBT_SRVC_RT_12M | D63: OSI | E63: 2. Alterar especificação | F63: OK | G63: Em especificação (Financial Statments CIB) | H63: Campo implementação, mas com falta de informação para o segmento de clientes CIB | I63: Não | J63: 45450 | K63: 2. Alterar especificação | L63: =F63 -> OK | P63: Melhorias estruturais (garantir coerência entre campos) | Q63: Y | R63: N | S63: N | T63: N | U63: N | V63: N | W63: PM | X63: 0
A64: =B64&"_"&C64 -> INSTRUMENT_DBT_YLD | B64: INSTRUMENT | C64: DBT_YLD | D64: Fora OSI | E64: 8. Concluído - sem dados | F64: OK | G64: Concluido, controlos OK | I64: Campo Fechado | J64: 45450 | K64: 8. Concluído - sem dados | L64: =F64 -> OK | P64: Campo concluído, mas sem ou pouca informação na fonte | Q64: Y | R64: N | S64: N | T64: N | U64: N | V64: N | W64: PM | X64: 0
A65: =B65&"_"&C65 -> ENTITY_DCSD | B65: ENTITY | C65: DCSD | D65: Fora OSI | E65: 9. Concluído | F65: OK | G65: Concluido, controlos OK | I65: Campo Fechado | J65: 45450 | K65: 9. Concluído | L65: =F65 -> OK | P65: Campo concluido | Q65: Y | R65: N | S65: N | T65: N | U65: N | V65: N | W65: PM | X65: 0
A66: =B66&"_"&C66 -> ENTITY_DFLT_STTS | B66: ENTITY | C66: DFLT_STTS | D66: OSI | E66: 3. Pendente de decisão | F66: NOK | G66: Alterar especificação caso a LT passe a reportar os 1os titulares da Contabilidade. | H66: Na OSI foram reportados os 1os titulares da Contabilidade, o que para alguns casos, são diferentes do que está na CL01. Apenas será necessário ajustar este campo caso a LT passe a reportar os 1os titulares da Contabilidade. Campo com incidência: Para os casos em que o cliente tem operações titularizadas (flag consumo capital = 0) e tem pelo menos uma não titularizada (N/A), a LT está atualmente a reporta N/A. | I66: Sim | J66: 45450 | K66: 3. Pendente de decisão | L66: =F66 -> NOK | P66: Pendente de decisão | Q66: Y | R66: N | S66: N | T66: N | U66: N | V66: Y | W66: LF | X66: 5. Campos com outras possíveis alterações - Dependente de decisões OSI
A67: =B67&"_"&C67 -> INSTRUMENT_RFNNC_PRPS | B67: INSTRUMENT | C67: RFNNC_PRPS | D67: OSI | E67: 2. Alterar especificação | F67: OK | G67: Alterar especificação. Campo depende do FRBRNC_STTS_INSTRMNT | H67: Sempre que o campo FRBRNC_STTS_INSTRMNT =3 o campo RFNNC_PRPS deve estar marcado como Y. Reespecificar, implementar e testar. | I67: Não | J67: 45450 | K67: 2. Alterar especificação | L67: =F67 -> OK | P67: Melhorias estruturais (garantir coerência entre campos) | Q67: Y | R67: N | S67: N | T67: N | U67: N | V67: N | W67: PM | X67: 0
A68: =B68&"_"&C68 -> INSTRUMENT_DPD | B68: INSTRUMENT | C68: DPD | D68: OSI | E68: 7. Analisar controlos e completude | F68: NOK | G68: Controlos NOK | I68: Não | J68: 45450 | K68: 7. Analisar controlos e completude | L68: =F68 -> NOK | P68: Analisar controlos NOK | Q68: Y | R68: N | S68: N | T68: N | U68: N | V68: Y | W68: LF | X68: 4. Campos com NOK controlos Corporativos
A69: =B69&"_"&C69 -> INSTRUMENT_DPD_12M | B69: INSTRUMENT | C69: DPD_12M | D69: OSI | E69: 7. Analisar controlos e completude | F69: NOK | G69: Controlos NOK | I69: Não | J69: 45450 | K69: 7. Analisar controlos e completude | L69: =F69 -> NOK | P69: Analisar controlos NOK | Q69: Y | R69: N | S69: N | T69: N | U69: N | V69: N | W69: PM | X69: 0
A70: =B70&"_"&C70 -> INSTRUMENT_DPD_12M_FRBRNC_STTS | B70: INSTRUMENT | C70: DPD_12M_FRBRNC_STTS | D70: OSI | E70: 5.1 Em testes - Re-especificação | F70: NOK | G70: Em testes. Campo depende do FRBRNC_STTS que está com incidência nos formatos. Não é necessário alterar a especificação do mesmo, apenas testar quando o campo FRBRNC_STTS estiver corrigido. | I70: Não | J70: 45450 | K70: 5.1 Em testes - Re-especificação | L70: =F70 -> NOK | N70: 44679 | O70: 44700 | P70: Melhorias estruturais (garantir coerência entre campos) | Q70: Y | R70: N | S70: N | T70: N | U70: N | V70: N | W70: PM | X70: 0
A71: =B71&"_"&C71 -> INSTRUMENT_DPD_12M_PRFRMNG_STTS | B71: INSTRUMENT | C71: DPD_12M_PRFRMNG_STTS | D71: OSI | E71: 5.1 Em testes - Re-especificação | F71: NOK | G71: Campo depende do histórico do PRFRMNG_STTS. Não é necessário alterar a especificação do mesmo, apenas testar se a metodologia do campo PRFRMNG_STTS for alterada. | I71: Sim | J71: 45670 | K71: 5.1 Em testes - Re-especificação | L71: OK | M71: Alteração da fonte das tabela de Imparidade Reporting para as 8_7 e alteração da data a partir da qual a fonte passa a ser as tabelas de Contabilidade ( 2019 para Dez 2022) | N71: 45562 | P71: Pendente de decisão | Q71: Y | R71: N | S71: N | T71: N | U71: N | V71: N | W71: PM | X71: 0
A72: =B72&"_"&C72 -> INSTRUMENT_DPD_24M_FRBRNC_STTS | B72: INSTRUMENT | C72: DPD_24M_FRBRNC_STTS | D72: OSI | E72: 7. Analisar controlos e completude | F72: NOK | G72: Controlos NOK | I72: Não | J72: 45450 | K72: 7. Analisar controlos e completude | L72: =F72 -> NOK | P72: Analisar controlos NOK | Q72: Y | R72: N | S72: N | T72: N | U72: N | V72: N | W72: PM | X72: 0
A73: =B73&"_"&C73 -> INSTRUMENT_DPD_24M_PRFRMNG_STTS | B73: INSTRUMENT | C73: DPD_24M_PRFRMNG_STTS | D73: OSI | E73: 5.1 Em testes - Re-especificação | F73: NOK | G73: Em testes. Campo depende do campo PRFRMNG_STTS. Não é necessário alterar a especificação do mesmo, apenas testar se o campo PRFRMNG_STTS for alterado. | I73: Sim | J73: 45670 | K73: 5.1 Em testes - Re-especificação | L73: OK | M73: Alteração da fonte das tabela de Imparidade Reporting para as 8_7 e alteração da data a partir da qual a fonte passa a ser as tabelas de Contabilidade ( 2019 para Dez 2022) | N73: 45562 | P73: Pendente de decisão | Q73: Y | R73: N | S73: N | T73: N | U73: N | V73: N | W73: PM | X73: 0
A74: =B74&"_"&C74 -> INSTRUMENT_DPD_FRBRNC_STTS | B74: INSTRUMENT | C74: DPD_FRBRNC_STTS | D74: OSI | E74: 7. Analisar controlos e completude | F74: NOK | G74: Controlos NOK | I74: Não | J74: 45450 | K74: 7. Analisar controlos e completude | L74: =F74 -> NOK | P74: Analisar controlos NOK | Q74: Y | R74: N | S74: N | T74: N | U74: N | V74: N | W74: PM | X74: 0
A75: =B75&"_"&C75 -> INSTRUMENT_DPD_PRFRMNG_STTS | B75: INSTRUMENT | C75: DPD_PRFRMNG_STTS | D75: OSI | E75: 5.1 Em testes - Re-especificação | F75: OK | G75: Em testes. Campo depende do campo PRFRMNG_STTS. Não é necessário alterar a especificação do mesmo, apenas testar se o campo PRFRMNG_STTS for alterado. | I75: Sim | J75: 45670 | K75: 5.1 Em testes - Re-especificação | L75: =F75 -> OK | M75: Alteração da fonte das tabela de Imparidade Reporting para as 8_7 e alteração da data a partir da qual a fonte passa a ser as tabelas de Contabilidade ( 2019 para Dez 2022) | N75: 45562 | P75: Pendente de decisão | Q75: Y | R75: N | S75: N | T75: N | U75: N | V75: N | W75: PM | X75: 0
A76: =B76&"_"&C76 -> INSTRUMENT_DSTI | B76: INSTRUMENT | C76: DSTI | D76: Fora OSI | E76: 1. Especificar | F76: OK | G76: Em especificação (Campos Novos) | I76: Não | J76: 45450 | K76: 1. Especificar | L76: =F76 -> OK | P76: Novo campo | Q76: Y | R76: N | S76: N | T76: N | U76: N | V76: N | W76: PM | X76: 0
A77: =B77&"_"&C77 -> PROTECTION_TYP_PRTCTN | B77: PROTECTION | C77: TYP_PRTCTN | D77: OSI | E77: 2. Alterar especificação | F77: NOK | G77: Alterar especificação (alteração da fonte para MUG) | H77: Campo depende do campo 'cgarant' do MUG | I77: Campo Fechado | J77: 45670 | K77: 9. Concluído | L77: OK | M77: Alteração de especificação com base no campo cgarant_bem e cgarant_rpt do MUG. Controlo NOK - A Corporação ajustou o controlo e estes casos passarão a estar OK | N77: 45492 | O77: 45646 | P77: Necessidade de correção de erros | Q77: Y | R77: Y | S77: Y | T77: N | U77: Y | V77: N | W77: PM | X77: 0
A78: =B78&"_"&C78 -> ENTITY_DT_BRTH | B78: ENTITY | C78: DT_BRTH | D78: Fora OSI | E78: 7. Analisar controlos e completude | F78: NOK | G78: Controlos NOK | I78: Não | J78: 45450 | K78: 7. Analisar controlos e completude | L78: =F78 -> NOK | P78: Analisar controlos NOK | Q78: Y | R78: N | S78: N | T78: N | U78: N | V78: N | W78: PM | X78: 0
A79: =B79&"_"&C79 -> INSTRUMENT_DT_CMPLNT_MRTR_STTS_C19 | B79: INSTRUMENT | C79: DT_CMPLNT_MRTR_STTS_C19 | D79: Fora OSI | E79: 9. Concluído | F79: OK | G79: Concluido, controlos OK | I79: Campo Fechado | J79: 45450 | K79: 9. Concluído | L79: =F79 -> OK | P79: Campo concluido | Q79: Y | R79: N | S79: N | T79: N | U79: N | V79: N | W79: PM | X79: 0
A80: =B80&"_"&C80 -> INSTRUMENT_DT_CMPLNT_MRTR_STTS_PRVS_C19 | B80: INSTRUMENT | C80: DT_CMPLNT_MRTR_STTS_PRVS_C19 | D80: Fora OSI | E80: 9. Concluído | F80: OK | G80: Concluido, controlos OK | I80: Campo Fechado | J80: 45450 | K80: 9. Concluído | L80: =F80 -> OK | P80: Campo concluido | Q80: Y | R80: N | S80: N | T80: N | U80: N | V80: N | W80: PM | X80: 0
A81: =B81&"_"&C81 -> PROTECTION_DT_PRTCTN_VL | B81: PROTECTION | C81: DT_PRTCTN_VL | D81: OSI | E81: 5.2 Em testes - Incidência | F81: NOK | G81: Campo com incidência e controlos NOK. | H81: Alteração formato de 0001-01-01 para 0000-00-00 | I81: Campo Fechado | J81: 45670 | K81: 9. Concluído | L81: OK | M81: Incidência corrigida. Especificação alterada para campo da GT018, de modo a estar coerente com a especificação do campo PRTCTN_VL Controlo NOK (ver caderno de testes a 03/12/2023) | N81: 45492 | O81: 45646 | P81: Necessidade de correção de erros | Q81: Y | R81: N | S81: N | T81: N | U81: N | V81: N | W81: PM | X81: 0
A82: =B82&"_"&C82 -> ENTITY_DT_DFLT_STTS | B82: ENTITY | C82: DT_DFLT_STTS | D82: OSI | E82: 3. Pendente de decisão | F82: NOK | G82: Alterar especificação caso a LT passe a reportar os 1os titulares da Contabilidade. | H82: Na OSI foram reportados os 1os titulares da Contabilidade, o que para alguns casos, são diferentes do que está na CL01. Apenas será necessário ajustar este campo caso a LT passe a reportar os 1os titulares da Contabilidade. | I82: Sim | J82: 45450 | K82: 3. Pendente de decisão | L82: =F82 -> NOK | P82: Pendente de decisão | Q82: Y | R82: N | S82: N | T82: N | U82: N | V82: Y | W82: LF | X82: 5. Campos com outras possíveis alterações - Dependente de decisões OSI
A83: =B83&"_"&C83 -> INSTRUMENT_DT_DFLT_STTS_INSTRMNT | B83: INSTRUMENT | C83: DT_DFLT_STTS_INSTRMNT | D83: OSI | E83: 5.2 Em testes - Incidência | F83: NOK | G83: Campo com incidência. É necessário adicionar a data de inception sempre que os contratos não estejam em default Campo entregue por IT durante a OSI, no entanto foi detatada a incidência identificada supra | H83: Na OSI foram reportados os 1os titulares da Contabilidade, o que para alguns casos, são diferentes do que está na CL01. Apenas será necessário ajustar este campo caso a LT passe a reportar os 1os titulares da Contabilidade. | I83: Não | J83: 45450 | K83: 5.2 Em testes - Incidência | L83: =F83 -> NOK | P83: Melhorias estruturais (garantir coerência entre campos) | Q83: Y | R83: N | S83: N | T83: N | U83: N | V83: Y | W83: LF | X83: 3. Campos em testes ou c/ incidências
A84: =B84&"_"&C84 -> INSTRUMENT_DT_END_GP_PPAL | B84: INSTRUMENT | C84: DT_END_GP_PPAL | D84: OSI | E84: 7. Analisar controlos e completude | F84: NOK | G84: Controlos NOK | I84: Não | J84: 45450 | K84: 7. Analisar controlos e completude | L84: =F84 -> NOK | P84: Analisar controlos NOK | Q84: Y | R84: N | S84: N | T84: N | U84: N | V84: N | W84: PM | X84: 0
A85: =B85&"_"&C85 -> INSTRUMENT_DT_END_GP_PPAL_C19 | B85: INSTRUMENT | C85: DT_END_GP_PPAL_C19 | D85: Fora OSI | E85: 9. Concluído | F85: OK | G85: Concluido, controlos OK | I85: Campo Fechado | J85: 45450 | K85: 9. Concluído | L85: =F85 -> OK | P85: Campo concluido | Q85: Y | R85: N | S85: N | T85: N | U85: N | V85: N | W85: PM | X85: 0
A86: =B86&"_"&C86 -> INSTRUMENT_DT_END_INTRST_ONLY | B86: INSTRUMENT | C86: DT_END_INTRST_ONLY | D86: OSI | E86: 7. Analisar controlos e completude | F86: NOK | G86: Controlos NOK | I86: Não | J86: 45450 | K86: 7. Analisar controlos e completude | L86: =F86 -> NOK | P86: Analisar controlos NOK | Q86: Y | R86: N | S86: N | T86: N | U86: N | V86: N | W86: PM | X86: 0
A87: =B87&"_"&C87 -> INSTRUMENT_DT_END_INTRST_ONLY_C19 | B87: INSTRUMENT | C87: DT_END_INTRST_ONLY_C19 | D87: Fora OSI | E87: 9. Concluído | F87: OK | G87: Concluido, controlos OK | I87: Campo Fechado | J87: 45450 | K87: 9. Concluído | L87: =F87 -> OK | P87: Campo concluido | Q87: Y | R87: N | S87: N | T87: N | U87: N | V87: N | W87: PM | X87: 0
A88: =B88&"_"&C88 -> PROTECTION_CNSTRCTN_STTS | B88: PROTECTION | C88: CNSTRCTN_STTS | D88: Fora OSI | E88: 2. Alterar especificação | F88: NOK | G88: Campo dependente do MUG | H88: Campo depende do campo 'cgarant' do MUG | I88: Campo Fechado | J88: 45670 | K88: 9. Concluído | L88: OK | N88: 45513 | O88: 45646 | P88: Necessidade de correção de erros | Q88: Y | R88: N | S88: N | T88: N | U88: N | V88: N | W88: PM | X88: 0
A89: =B89&"_"&C89 -> ENTITY_DT_FNNCL_STTMTS | B89: ENTITY | C89: DT_FNNCL_STTMTS | D89: OSI | E89: 2. Alterar especificação | F89: NOK | G89: Em especificação (Financial Statments CIB) | H89: Campo implementação, mas com falta de informação para o segmento de clientes CIB | I89: Não | J89: 45450 | K89: 2. Alterar especificação | L89: =F89 -> NOK | P89: Melhorias estruturais (garantir coerência entre campos) | Q89: Y | R89: N | S89: N | T89: N | U89: N | V89: Y | W89: PM & LF | X89: 6.4. Fora âmbito | Re-especificação de campos complexos - Dem. Fin. CIB
A90: =B90&"_"&C90 -> ENTITY_DT_FNNCL_STTMTS_PRVS | B90: ENTITY | C90: DT_FNNCL_STTMTS_PRVS | D90: OSI | E90: 2. Alterar especificação | F90: NOK | G90: Em especificação (Financial Statments CIB) | H90: Campo implementação, mas com falta de informação para o segmento de clientes CIB | I90: Não | J90: 45450 | K90: 2. Alterar especificação | L90: =F90 -> NOK | P90: Melhorias estruturais (garantir coerência entre campos) | Q90: Y | R90: N | S90: N | T90: N | U90: N | V90: Y | W90: PM & LF | X90: 6.4. Fora âmbito | Re-especificação de campos complexos - Dem. Fin. CIB
A91: =B91&"_"&C91 -> INSTRUMENT_RCVD_INTRST_24M | B91: INSTRUMENT | C91: RCVD_INTRST_24M | D91: OSI | E91: 2. Alterar especificação | F91: OK | G91: Em especificação (Amortizações Capital/ Juros). Campo com dados mas pouca qualidade | I91: Não | J91: 45450 | K91: 2. Alterar especificação | L91: =F91 -> OK | P91: Melhorias estruturais (garantir coerência entre campos) | Q91: Y | R91: N | S91: N | T91: N | U91: N | V91: Y | W91: LF | X91: 2.2 Re-especificação de campos complexos - Resto
A92: =B92&"_"&C92 -> INSTRUMENT_DT_FRBRNC_STTS_C19 | B92: INSTRUMENT | C92: DT_FRBRNC_STTS_C19 | D92: Fora OSI | E92: 9. Concluído | F92: OK | G92: Concluido, controlos OK | I92: Campo Fechado | J92: 45450 | K92: 9. Concluído | L92: =F92 -> OK | P92: Campo concluido | Q92: Y | R92: N | S92: N | T92: N | U92: N | V92: N | W92: PM | X92: 0
A93: =B93&"_"&C93 -> INSTRUMENT_RCVD_INTRST_12M | B93: INSTRUMENT | C93: RCVD_INTRST_12M | D93: OSI | E93: 2. Alterar especificação | F93: NOK | G93: Em especificação (Amortizações Capital/ Juros) | I93: Não | J93: 45450 | K93: 2. Alterar especificação | L93: =F93 -> NOK | P93: Melhorias estruturais (garantir coerência entre campos) | Q93: Y | R93: N | S93: N | T93: N | U93: N | V93: Y | W93: LF | X93: 2.2 Re-especificação de campos complexos - Resto
A94: =B94&"_"&C94 -> INSTRUMENT_DT_FRBRNC_STTS_PRVS_C19 | B94: INSTRUMENT | C94: DT_FRBRNC_STTS_PRVS_C19 | D94: Fora OSI | E94: 9. Concluído | F94: OK | G94: Concluido, controlos OK | I94: Campo Fechado | J94: 45450 | K94: 9. Concluído | L94: =F94 -> OK | P94: Campo concluido | Q94: Y | R94: N | S94: N | T94: N | U94: N | V94: N | W94: PM | X94: 0
A95: =B95&"_"&C95 -> PROTECTION_DT_FRST_USG | B95: PROTECTION | C95: DT_FRST_USG | D95: Fora OSI | E95: 7. Analisar controlos e completude | F95: NOK | G95: Controlos NOK por parte de Riscos | I95: Não | J95: 45450 | K95: 7. Analisar controlos e completude | L95: =F95 -> NOK | P95: Analisar controlos NOK | Q95: Y | R95: N | S95: N | T95: N | U95: N | V95: N | W95: PM | X95: 0
A96: =B96&"_"&C96 -> INSTRUMENT_DT_IMPRMNT_STTS | B96: INSTRUMENT | C96: DT_IMPRMNT_STTS | D96: OSI | E96: 3. Pendente de decisão | F96: NOK | G96: Verificar necessidade de alteração da fonte para fins de reconciliação. Rever Fonte | H96: Rever fonte. Confirmar com LCM que a informação deverá estar de acordo com IFRS9/Imparidade, mantendo a metodologia da OSI (ir apenas à tabela FR004 na data de referência, as restantes datas ir à tabela de IFRS9) | I96: Sim | J96: 45670 | K96: 5.1 Em testes - Re-especificação | L96: =F96 -> NOK | M96: Alteração da fonte das tabela de Imparidade Reporting para as 8_7 e alteração da data a partir da qual a fonte passa a ser as tabelas de Contabilidade | N96: 45562 | P96: Pendente de decisão | Q96: Y | R96: N | S96: N | T96: N | U96: N | V96: Y | W96: PM | X96: 6.2. Fora âmbito | Campos em testes ou c/ incidências (LT - PM)
A97: =B97&"_"&C97 -> INSTRUMENT_DT_IMPRMNT_STTS_PRVS | B97: INSTRUMENT | C97: DT_IMPRMNT_STTS_PRVS | D97: OSI | E97: 3. Pendente de decisão | F97: NOK | G97: Verificar necessidade de alteração da fonte para fins de reconciliação. Rever Fonte | H97: Rever fonte. Confirmar com LCM que a informação deverá estar de acordo com IFRS9/Imparidade, mantendo a metodologia da OSI (ir apenas à tabela FR004 na data de referência, as restantes datas ir à tabela de IFRS9) | I97: Sim | J97: 45670 | K97: 5.1 Em testes - Re-especificação | L97: =F97 -> NOK | M97: Alteração da fonte das tabela de Imparidade Reporting para as 8_7 e alteração da data a partir da qual a fonte passa a ser as tabelas de Contabilidade | N97: 45562 | P97: Pendente de decisão | Q97: Y | R97: N | S97: N | T97: N | U97: N | V97: N | W97: PM | X97: 0
A98: =B98&"_"&C98 -> INSTRUMENT_DT_INCPTN | B98: INSTRUMENT | C98: DT_INCPTN | D98: OSI | E98: 7. Analisar controlos e completude | F98: NOK | G98: Controlos NOK | I98: Não | J98: 45450 | K98: 7. Analisar controlos e completude | L98: =F98 -> NOK | P98: Analisar controlos NOK | Q98: Y | R98: N | S98: Y | T98: N | U98: N | V98: Y | W98: LF | X98: 4. Campos com NOK controlos Corporativos
A99: =B99&"_"&C99 -> ENTITY_DT_INTRNL_RTNG | B99: ENTITY | C99: DT_INTRNL_RTNG | D99: OSI | E99: 5.1 Em testes - Re-especificação | F99: NOK | G99: Em testes, campo entregue por IT durante a OSI. Incidência nos formatos. Testar e validar controlos NOK | I99: Sim | J99: 45450 | K99: 5.1 Em testes - Re-especificação | L99: =F99 -> NOK | M99: Campo entregue durante a OSI | N99: 45338 | O99: 45436 | P99: Necessidade de correção de erros | Q99: Y | R99: N | S99: N | T99: N | U99: N | V99: Y | W99: LF | X99: 3. Campos em testes ou c/ incidências
A100: =B100&"_"&C100 -> INSTRUMENT_DT_INTRNL_RTNG | B100: INSTRUMENT | C100: DT_INTRNL_RTNG | D100: OSI | E100: 5.1 Em testes - Re-especificação | F100: NOK | G100: Em testes, campo entregue por IT durante a OSI. Testar e validar controlos | I100: Sim | J100: 45450 | K100: 5.1 Em testes - Re-especificação | L100: =F100 -> NOK | M100: Campo entregue durante a OSI | N100: 45338 | O100: 45436 | P100: Necessidade de correção de erros | Q100: Y | R100: N | S100: N | T100: N | U100: N | V100: Y | W100: LF | X100: 3. Campos em testes ou c/ incidências
A101: =B101&"_"&C101 -> ENTITY_DT_INTTN_LGL_PRCDNGS_LE | B101: ENTITY | C101: DT_INTTN_LGL_PRCDNGS_LE | D101: OSI | E101: 9. Concluído | F101: OK | G101: Concluido, controlos OK | I101: Campo Fechado | J101: 45450 | K101: 9. Concluído | L101: =F101 -> OK | P101: Campo concluido | Q101: Y | R101: N | S101: N | T101: N | U101: N | V101: Y | W101: PM | X101: 6.1. Fora âmbito | Campos concluídos - Sem necessidade de espec.
A102: =B102&"_"&C102 -> PROTECTION_DVLPMNT_STTS | B102: PROTECTION | C102: DVLPMNT_STTS | D102: OSI | E102: 2. Alterar especificação | F102: NOK | G102: Alterar especificação. Campo dependente do MUG | H102: Campo depende do campo 'cgarant' do MUG | I102: Campo Fechado | J102: 45670 | K102: 9. Concluído | L102: OK | M102: Mapeamento de acordo com o CNSTRCTN_STTS | N102: 45513 | O102: 45646 | P102: Necessidade de correção de erros | Q102: Y | R102: N | S102: N | T102: N | U102: N | V102: N | W102: PM | X102: 0
...

Sheet Caderno Testes
A1: Tabela | B1: Campo | C1: Tipo de teste | D1: Descritivo | E1: Data atualização | F1: Data de referência | G1: Status | H1: Duvidas/comentários | I1: Query
A2: INSTRMNT | B2: RWA_MTHD | C2: Completude | D2: Validar se o número de MISS e N/A | E2: 45460 | F2: 45443 | G2: OK | I2: SELECT rwa_mthd, a.NUM_REGISTOS, a.NUM_REGISTOS/b.NUM_REGISTOS*100 as Perc from (SELECT rwa_mthd , COUNT(*) AS NUM_REGISTOS FROM cd_loan_tapes_bce.LT002_INSTRUMENT WHERE REF_DATE='${date}' AND NOME_PERIMETRO='Individual Corporativo' AND AMBITO = 'PM' AND SEGMENTO = 'ESTR' GROUP BY 1 ) a join ( SELECT COUNT(*) AS NUM_REGISTOS FROM cd_loan_tapes_bce.LT002_INSTRUMENT WHERE REF_DATE='${date}' AND NOME_PERIMETRO='Individual Corporativo' AND AMBITO = 'PM' AND SEGMENTO = 'ESTR' ) b where rwa_mthd in ('99999999999', '11111111111')
A3: INSTRMNT | B3: RWA_MTHD | C3: Desenvolvimento | D3: Validar alteração de formato de 11111111.00 para 11111111 | E3: 45460 | F3: 45443 | G3: OK | I3: SELECT count(*), rwa_mthd FROM cd_loan_tapes_bce.lt002_instrument WHERE 1=1 AND REF_DATE='${date}' AND NOME_PERIMETRO='Individual Corporativo' AND AMBITO = 'PM' AND SEGMENTO = 'ESTR' GROUP BY 2 ORDER BY 1
A4: INSTRMNT | B4: RWA_MTHD | C4: Desenvolvimento | D4: Validar condição de N/A sempre que não existe de consumo de capital | E4: 45460 | F4: 45443 | G4: OK | I4: SELECT DISTINCT EAD, RWA, rwa_mthd, VAL FROM (SELECT DISTINCT INSTRMNT_ID, EAD, RWA, rwa_mthd FROM cd_loan_tapes_bce.LT002_INSTRUMENT WHERE REF_DATE='${date}' AND NOME_PERIMETRO='Individual Corporativo' AND AMBITO = 'PM') LT002 LEFT JOIN (SELECT CHAVE_FR, SUM(flag_cons_cap) AS VAL FROM (SELECT CHAVE_FR, S1EMP, CONTRA1 FROM (SELECT DISTINCT CONCAT(CEMPRESA, CBALCAO,CNUMECTA, ZDEPOSIT) AS CHAVE_MASTER, CONCAT(CEMPRESA_FR, CBALCAO_FR,CNUMECTA_FR, ZDEPOSIT_FR) AS CHAVE_FR FROM cd_captools.KT_CHAVES_FINREP WHERE REF_DATE='${date}') KT_FR INNER JOIN (SELECT DISTINCT CONCAT(CEMPRESA, CBALCAO,CNUMECTA, ZDEPOSIT) AS CHAVE_MASTER, S1EMP, CONTRA1 FROM cd_captools.KT_CHAVES_BDR WHERE REF_DATE='${date}') KT_BDR ON KT_FR.CHAVE_MASTER=KT_BDR.CHAVE_MASTER ) KT LEFT JOIN (SELECT CT013.* FROM (SELECT DISTINCT REF_DATE, id_capital_perimetros, s1emp, contra1, flag_cons_cap FROM cd_captools.ct013_rwa_princ WHERE REF_DATE = '${date}' -- AND flag_cons_cap = 1 AND flag_conc_contab = 1 AND exercicio = "REAL" -- 30-03-2021: Adição de filtro AND subtipo_risco in ('1.1', '1.2', '1.3', '1.4', '1.5', '1.6', '1.7', '1.8', '1.9', '1.13')) CT013 INNER JOIN (SELECT DISTINCT ID_CAPITAL_PERIMETROS, REF_DATE FROM cd_captools.ct020_rwa_per WHERE REF_DATE = '${date}' AND NOME_PERIMETRO='Individual Corporativo') CT020 on CT013.ID_CAPITAL_PERIMETROS=CT020.ID_CAPITAL_PERIMETROS) CAP ON CAP.S1EMP=KT.S1EMP AND CAP.CONTRA1=KT.CONTRA1 GROUP BY 1 ) BASE ON INSTRMNT_ID=CHAVE_FR WHERE VAL=0
A5: INSTRMNT | B5: RWA_MTHD | C5: Controlos | D5: If "RWA" is populated other than default values, then "RWA calculation method" cannot be 'Not applicable' | E5: 45460 | F5: 45443 | G5: OK | I5: SELECT instrmnt_id, ead, rwa, rwa_mthd FROM cd_loan_tapes_bce.lt002_instrument WHERE 1=1 AND REF_DATE='${date}' AND NOME_PERIMETRO='Individual Corporativo' AND AMBITO = 'PM' AND SEGMENTO = 'ESTR' AND rwa NOT IN (99999999999.00, 11111111111.00) and rwa_mthd = 11111111111
A6: INSTRMNT | B6: RWA_MTHD | C6: Controlos | D6: If "RWA" is populated with 'Not applicable', then "RWA calculation method" must be a default value | E6: 45460 | F6: 45443 | G6: OK | I6: SELECT instrmnt_id, ead, rwa, rwa_mthd FROM cd_loan_tapes_bce.lt002_instrument WHERE 1=1 AND REF_DATE='${date}' AND NOME_PERIMETRO='Individual Corporativo' AND AMBITO = 'PM' AND SEGMENTO = 'ESTR' AND rwa = 11111111111.00 and rwa_mthd <> 11111111111
A7: INSTRMNT | B7: RWA_MTHD | C7: Controlos | D7: Validar se o campo está de acordo com a Codelist | E7: 45460 | F7: 45443 | G7: OK | I7: SELECT count(*), rwa_mthd FROM cd_loan_tapes_bce.lt002_instrument WHERE 1=1 AND REF_DATE='${date}' AND NOME_PERIMETRO='Individual Corporativo' AND AMBITO = 'PM' AND SEGMENTO = 'ESTR' GROUP BY 2 ORDER BY 1
A8: INSTRMNT | B8: RWA | C8: Completude | D8: Validar se o número de MISS e N/A | E8: 45460 | F8: 45443 | G8: OK | I8: SELECT rwa, a.NUM_REGISTOS, a.NUM_REGISTOS/b.NUM_REGISTOS*100 as Perc from (SELECT rwa , COUNT(*) AS NUM_REGISTOS FROM cd_loan_tapes_bce.LT002_INSTRUMENT WHERE REF_DATE='${date}' AND NOME_PERIMETRO='Individual Corporativo' AND AMBITO = 'PM' AND SEGMENTO = 'ESTR' GROUP BY 1 ) a join ( SELECT COUNT(*) AS NUM_REGISTOS FROM cd_loan_tapes_bce.LT002_INSTRUMENT WHERE REF_DATE='${date}' AND NOME_PERIMETRO='Individual Corporativo' AND AMBITO = 'PM' AND SEGMENTO = 'ESTR' ) b where rwa in (99999999999, 11111111111)
A9: INSTRMNT | B9: RWA | C9: Desenvolvimento | D9: Validar condição de N/A sempre que não existe de consumo de capital | E9: 45460 | F9: 45443 | G9: OK | I9: SELECT DISTINCT EAD, RWA, rwa_mthd, VAL FROM (SELECT DISTINCT INSTRMNT_ID, EAD, RWA, rwa_mthd FROM cd_loan_tapes_bce.LT002_INSTRUMENT WHERE REF_DATE='${date}' AND NOME_PERIMETRO='Individual Corporativo' AND AMBITO = 'PM') LT002 LEFT JOIN (SELECT CHAVE_FR, SUM(flag_cons_cap) AS VAL FROM (SELECT CHAVE_FR, S1EMP, CONTRA1 FROM (SELECT DISTINCT CONCAT(CEMPRESA, CBALCAO,CNUMECTA, ZDEPOSIT) AS CHAVE_MASTER, CONCAT(CEMPRESA_FR, CBALCAO_FR,CNUMECTA_FR, ZDEPOSIT_FR) AS CHAVE_FR FROM cd_captools.KT_CHAVES_FINREP WHERE REF_DATE='${date}') KT_FR INNER JOIN (SELECT DISTINCT CONCAT(CEMPRESA, CBALCAO,CNUMECTA, ZDEPOSIT) AS CHAVE_MASTER, S1EMP, CONTRA1 FROM cd_captools.KT_CHAVES_BDR WHERE REF_DATE='${date}') KT_BDR ON KT_FR.CHAVE_MASTER=KT_BDR.CHAVE_MASTER ) KT LEFT JOIN (SELECT CT013.* FROM (SELECT DISTINCT REF_DATE, id_capital_perimetros, s1emp, contra1, flag_cons_cap FROM cd_captools.ct013_rwa_princ WHERE REF_DATE = '${date}' -- AND flag_cons_cap = 1 AND flag_conc_contab = 1 AND exercicio = "REAL" -- 30-03-2021: Adição de filtro AND subtipo_risco in ('1.1', '1.2', '1.3', '1.4', '1.5', '1.6', '1.7', '1.8', '1.9', '1.13')) CT013 INNER JOIN (SELECT DISTINCT ID_CAPITAL_PERIMETROS, REF_DATE FROM cd_captools.ct020_rwa_per WHERE REF_DATE = '${date}' AND NOME_PERIMETRO='Individual Corporativo') CT020 on CT013.ID_CAPITAL_PERIMETROS=CT020.ID_CAPITAL_PERIMETROS) CAP ON CAP.S1EMP=KT.S1EMP AND CAP.CONTRA1=KT.CONTRA1 GROUP BY 1 ) BASE ON INSTRMNT_ID=CHAVE_FR WHERE VAL=0
A10: INSTRMNT | B10: RWA | C10: Controlos | D10: Validar formatos | E10: 45460 | F10: 45443 | G10: OK | I10: SELECT count(*), rwa FROM cd_loan_tapes_bce.lt002_instrument WHERE 1=1 AND REF_DATE='${date}' AND NOME_PERIMETRO='Individual Corporativo' AND AMBITO = 'PM' AND SEGMENTO = 'ESTR' GROUP BY 2 ORDER BY 1
A11: INSTRMNT | B11: RWA | C11: Controlos | D11: Validar se não existem valores negativos | E11: 45460 | F11: 45443 | G11: NOK | H11: 1 Contrato com valores negativos | I11: SELECT DISTINCT INSTRMNT_ID, EAD, RWA, rwa_mthd, VAL FROM (SELECT DISTINCT INSTRMNT_ID, EAD, RWA, rwa_mthd FROM cd_loan_tapes_bce.LT002_INSTRUMENT WHERE REF_DATE='${date}' AND NOME_PERIMETRO='Individual Corporativo' AND AMBITO = 'PM' -- AND instrmnt_id = '31000314294093096000000000000000' ) LT002 LEFT JOIN (SELECT CHAVE_FR, SUM(flag_cons_cap) AS VAL FROM (SELECT CHAVE_FR, S1EMP, CONTRA1 FROM (SELECT DISTINCT CONCAT(CEMPRESA, CBALCAO,CNUMECTA, ZDEPOSIT) AS CHAVE_MASTER, CONCAT(CEMPRESA_FR, CBALCAO_FR,CNUMECTA_FR, ZDEPOSIT_FR) AS CHAVE_FR FROM cd_captools.KT_CHAVES_FINREP WHERE REF_DATE='${date}') KT_FR INNER JOIN (SELECT DISTINCT CONCAT(CEMPRESA, CBALCAO,CNUMECTA, ZDEPOSIT) AS CHAVE_MASTER, S1EMP, CONTRA1 FROM cd_captools.KT_CHAVES_BDR WHERE REF_DATE='${date}') KT_BDR ON KT_FR.CHAVE_MASTER=KT_BDR.CHAVE_MASTER ) KT LEFT JOIN (SELECT CT013.* FROM (SELECT DISTINCT REF_DATE, id_capital_perimetros, s1emp, contra1, flag_cons_cap FROM cd_captools.ct013_rwa_princ WHERE REF_DATE = '${date}' -- AND flag_cons_cap = 1 AND flag_conc_contab = 1 AND exercicio = "REAL" -- 30-03-2021: Adição de filtro AND subtipo_risco in ('1.1', '1.2', '1.3', '1.4', '1.5', '1.6', '1.7', '1.8', '1.9', '1.13')) CT013 INNER JOIN (SELECT DISTINCT ID_CAPITAL_PERIMETROS, REF_DATE FROM cd_captools.ct020_rwa_per WHERE REF_DATE = '${date}' AND NOME_PERIMETRO='Individual Corporativo') CT020 on CT013.ID_CAPITAL_PERIMETROS=CT020.ID_CAPITAL_PERIMETROS) CAP ON CAP.S1EMP=KT.S1EMP AND CAP.CONTRA1=KT.CONTRA1 GROUP BY 1 ) BASE ON INSTRMNT_ID=CHAVE_FR WHERE RWA < 0
A12: INSTRMNT | B12: RWA | C12: Controlos | D12: Teste contra a fonte | E12: 45462 | F12: 45443 | G12: OK | H12: A fonte (CT013) tem um valor muito superior, porque existem várias chaves FR para uma chave BDR | I12: SELECT DISTINCT INSTRMNT_ID, S1EMP, CONTRA1, EAD, RWA, rwa_final, ead_final_bruta FROM (SELECT DISTINCT INSTRMNT_ID, CCF, dflt_stts_instrmnt, DPD, EAD, LGD, pd_crr_incptn, pd_crr_rd, pd_crr_rd_t1, RWA, rwa_mthd, spcltv_lndng, crrltn_cffcnt FROM cd_loan_tapes_bce.LT002_INSTRUMENT WHERE REF_DATE='${date}' AND NOME_PERIMETRO='Individual Corporativo' AND AMBITO = 'PM' -- AND instrmnt_id = '31000347000690020000000000000000' ) LT002 INNER JOIN (SELECT CHAVE_FR, KT.S1EMP, KT.CONTRA1, SUM(flag_cons_cap) AS VAL, SUM(RWA_FINAL) AS RWA_FINAL, SUM(ead_final_bruta) AS ead_final_bruta FROM (SELECT CHAVE_FR, S1EMP, CONTRA1 FROM (SELECT DISTINCT CONCAT(CEMPRESA, CBALCAO,CNUMECTA, ZDEPOSIT) AS CHAVE_MASTER, CONCAT(CEMPRESA_FR, CBALCAO_FR,CNUMECTA_FR, ZDEPOSIT_FR) AS CHAVE_FR FROM cd_captools.KT_CHAVES_FINREP WHERE REF_DATE='${date}') KT_FR INNER JOIN (SELECT DISTINCT CONCAT(CEMPRESA, CBALCAO,CNUMECTA, ZDEPOSIT) AS CHAVE_MASTER, S1EMP, CONTRA1 FROM cd_captools.KT_CHAVES_BDR WHERE REF_DATE='${date}') KT_BDR ON KT_FR.CHAVE_MASTER=KT_BDR.CHAVE_MASTER WHERE CHAVE_FR = '31005122428280011667450200000001' OR concat(S1EMP,CONTRA1) = '1814008684' ) KT INNER JOIN (SELECT CT013.* FROM (SELECT REF_DATE, id_capital_perimetros, s1emp, contra1, flag_cons_cap, rwa_final, ead_final_bruta FROM cd_captools.ct013_rwa_princ WHERE REF_DATE = '${date}' -- AND flag_cons_cap = 1 AND flag_conc_contab = 1 AND exercicio = "REAL" -- 30-03-2021: Adição de filtro AND subtipo_risco in ('1.1', '1.2', '1.3', '1.4', '1.5', '1.6', '1.7', '1.8', '1.9', '1.13')) CT013 INNER JOIN (SELECT DISTINCT ID_CAPITAL_PERIMETROS, REF_DATE FROM cd_captools.ct020_rwa_per WHERE REF_DATE = '${date}' AND NOME_PERIMETRO='Individual Corporativo') CT020 on CT013.ID_CAPITAL_PERIMETROS=CT020.ID_CAPITAL_PERIMETROS) CAP ON CAP.S1EMP=KT.S1EMP AND CAP.CONTRA1=KT.CONTRA1 GROUP BY 1,2,3 ) X on CHAVE_FR = INSTRMNT_ID
A13: INSTRMNT | B13: RWA | C13: Controlos | D13: Verificar saldo de capital | E13: 45462 | F13: 45443 | G13: OK | I13: SELECT LT002.instrmnt_id, RWA, EAD, CONCAT(LT001.cempresa,LT001.cbalcao,LT001.cnumecta,LT001.zdeposit) AS CHAVE_FR, NVL(SUM(LT001.msaldo_final),0) AS Saldo_Capital FROM (SELECT cempresa, cbalcao, cnumecta, zdeposit, ccontab_final_cargabal, msaldo_final FROM cd_loan_tapes_bce.lt001_univ_oper WHERE REF_DATE = '${date}' AND NOME_PERIMETRO='Individual Corporativo' AND AMBITO = 'PM' ) LT001 INNER JOIN (SELECT * FROM cd_loan_tapes_bce.kt_chaves_lt WHERE REF_DATE = '${date}' AND NOME_PERIMETRO='Individual Corporativo' AND AMBITO = 'PM' AND segmento = 'ESTR') KT_LT ON CONCAT(LT001.cempresa,LT001.cbalcao,LT001.cnumecta,LT001.zdeposit) = CONCAT(KT_LT.cempresa,KT_LT.cbalcao,KT_LT.cnumecta,KT_LT.zdeposit) INNER JOIN (SELECT instrmnt_id, rwa, ead FROM cd_loan_tapes_bce.lt002_instrument WHERE REF_DATE = '${date}' AND NOME_PERIMETRO='Individual Corporativo' AND AMBITO = 'PM' AND segmento ='ESTR' AND instrmnt_id in ( '310051224282800116674502P0080001', '310051224282800116674502P0070001', '310051224282800116674502P0060001', '31005122428280011667450200000001', '310051224282800116674502P0100001', '310051224282800116674502P0110001', '310051224282800116674502P0020001', '310051224282800116674502P0010001', '310051224282800116674502P0030001', '310051224282800116674502P0090001' ) ) LT002 ON KT_LT.INSTRMNT_ID = LT002.INSTRMNT_ID LEFT JOIN (SELECT * FROM cd_captools.fr802_pl_contas WHERE 1=1 AND REF_DATE = '${date}' AND cod_plano = 'CARGABAL' AND ((tipo_conta IN ('A','P') AND carteira_contabilistica not in('provisoes para compromissos e garantias concedidas', 'outras provisoes') AND composicao_valor <> 'imparidade acumulada' AND bruto_imparidade <> 'imparidade') OR (tipo_conta IN ('EA','EP','M'))) ) FR802 ON FR802.CONTA = LT001.ccontab_final_cargabal LEFT JOIN (SELECT * FROM cd_captools.ct805_matriz_cnt WHERE 1=1 AND REF_DATE = '${date}' AND DOMINIO = 'Capital' AND NOME_PERIMETRO = 'Individual Corporativo' ) CT805 ON FR802.CONTA = CT805.CONTA GROUP BY 1,2,3,4
A14: INSTRMNT | B14: EAD | C14: Completude | D14: Validar se o número de MISS e N/A | E14: 45460 | F14: 45443 | G14: OK | I14: SELECT ead, a.NUM_REGISTOS, a.NUM_REGISTOS/b.NUM_REGISTOS*100 as Perc from (SELECT ead , COUNT(*) AS NUM_REGISTOS FROM cd_loan_tapes_bce.LT002_INSTRUMENT WHERE REF_DATE='${date}' AND NOME_PERIMETRO='Individual Corporativo' AND AMBITO = 'PM' AND SEGMENTO = 'ESTR' GROUP BY 1 ) a join ( SELECT COUNT(*) AS NUM_REGISTOS FROM cd_loan_tapes_bce.LT002_INSTRUMENT WHERE REF_DATE='${date}' AND NOME_PERIMETRO='Individual Corporativo' AND AMBITO = 'PM' AND SEGMENTO = 'ESTR' ) b where ead in (99999999999, 11111111111)
A15: INSTRMNT | B15: EAD | C15: Desenvolvimento | D15: Validar condição de N/A sempre que não existe de consumo de capital | E15: 45460 | F15: 45443 | G15: OK | I15: SELECT DISTINCT EAD, RWA, rwa_mthd, VAL FROM (SELECT DISTINCT INSTRMNT_ID, EAD, RWA, rwa_mthd FROM cd_loan_tapes_bce.LT002_INSTRUMENT WHERE REF_DATE='${date}' AND NOME_PERIMETRO='Individual Corporativo' AND AMBITO = 'PM') LT002 LEFT JOIN (SELECT CHAVE_FR, SUM(flag_cons_cap) AS VAL FROM (SELECT CHAVE_FR, S1EMP, CONTRA1 FROM (SELECT DISTINCT CONCAT(CEMPRESA, CBALCAO,CNUMECTA, ZDEPOSIT) AS CHAVE_MASTER, CONCAT(CEMPRESA_FR, CBALCAO_FR,CNUMECTA_FR, ZDEPOSIT_FR) AS CHAVE_FR FROM cd_captools.KT_CHAVES_FINREP WHERE REF_DATE='${date}') KT_FR INNER JOIN (SELECT DISTINCT CONCAT(CEMPRESA, CBALCAO,CNUMECTA, ZDEPOSIT) AS CHAVE_MASTER, S1EMP, CONTRA1 FROM cd_captools.KT_CHAVES_BDR WHERE REF_DATE='${date}') KT_BDR ON KT_FR.CHAVE_MASTER=KT_BDR.CHAVE_MASTER ) KT LEFT JOIN (SELECT CT013.* FROM (SELECT DISTINCT REF_DATE, id_capital_perimetros, s1emp, contra1, flag_cons_cap FROM cd_captools.ct013_rwa_princ WHERE REF_DATE = '${date}' -- AND flag_cons_cap = 1 AND flag_conc_contab = 1 AND exercicio = "REAL" -- 30-03-2021: Adição de filtro AND subtipo_risco in ('1.1', '1.2', '1.3', '1.4', '1.5', '1.6', '1.7', '1.8', '1.9', '1.13')) CT013 INNER JOIN (SELECT DISTINCT ID_CAPITAL_PERIMETROS, REF_DATE FROM cd_captools.ct020_rwa_per WHERE REF_DATE = '${date}' AND NOME_PERIMETRO='Individual Corporativo') CT020 on CT013.ID_CAPITAL_PERIMETROS=CT020.ID_CAPITAL_PERIMETROS) CAP ON CAP.S1EMP=KT.S1EMP AND CAP.CONTRA1=KT.CONTRA1 GROUP BY 1 ) BASE ON INSTRMNT_ID=CHAVE_FR WHERE VAL=0
A16: INSTRMNT | B16: EAD | C16: Controlos | D16: Validar formatos | E16: 45460 | F16: 45443 | G16: OK | I16: SELECT count(*), rwa FROM cd_loan_tapes_bce.lt002_instrument WHERE 1=1 AND REF_DATE='${date}' AND NOME_PERIMETRO='Individual Corporativo' AND AMBITO = 'PM' AND SEGMENTO = 'ESTR' GROUP BY 2 ORDER BY 1
A17: INSTRMNT | B17: EAD | C17: Controlos | D17: Validar se não existem valores negativos | E17: 45460 | F17: 45443 | G17: NOK | H17: 1 Contrato com valores negativos | I17: SELECT DISTINCT INSTRMNT_ID, EAD, RWA, rwa_mthd, VAL FROM (SELECT DISTINCT INSTRMNT_ID, EAD, RWA, rwa_mthd FROM cd_loan_tapes_bce.LT002_INSTRUMENT WHERE REF_DATE='${date}' AND NOME_PERIMETRO='Individual Corporativo' AND AMBITO = 'PM' -- AND instrmnt_id = '31000314294093096000000000000000' ) LT002 LEFT JOIN (SELECT CHAVE_FR, SUM(flag_cons_cap) AS VAL FROM (SELECT CHAVE_FR, S1EMP, CONTRA1 FROM (SELECT DISTINCT CONCAT(CEMPRESA, CBALCAO,CNUMECTA, ZDEPOSIT) AS CHAVE_MASTER, CONCAT(CEMPRESA_FR, CBALCAO_FR,CNUMECTA_FR, ZDEPOSIT_FR) AS CHAVE_FR FROM cd_captools.KT_CHAVES_FINREP WHERE REF_DATE='${date}') KT_FR INNER JOIN (SELECT DISTINCT CONCAT(CEMPRESA, CBALCAO,CNUMECTA, ZDEPOSIT) AS CHAVE_MASTER, S1EMP, CONTRA1 FROM cd_captools.KT_CHAVES_BDR WHERE REF_DATE='${date}') KT_BDR ON KT_FR.CHAVE_MASTER=KT_BDR.CHAVE_MASTER ) KT LEFT JOIN (SELECT CT013.* FROM (SELECT DISTINCT REF_DATE, id_capital_perimetros, s1emp, contra1, flag_cons_cap FROM cd_captools.ct013_rwa_princ WHERE REF_DATE = '${date}' -- AND flag_cons_cap = 1 AND flag_conc_contab = 1 AND exercicio = "REAL" -- 30-03-2021: Adição de filtro AND subtipo_risco in ('1.1', '1.2', '1.3', '1.4', '1.5', '1.6', '1.7', '1.8', '1.9', '1.13')) CT013 INNER JOIN (SELECT DISTINCT ID_CAPITAL_PERIMETROS, REF_DATE FROM cd_captools.ct020_rwa_per WHERE REF_DATE = '${date}' AND NOME_PERIMETRO='Individual Corporativo') CT020 on CT013.ID_CAPITAL_PERIMETROS=CT020.ID_CAPITAL_PERIMETROS) CAP ON CAP.S1EMP=KT.S1EMP AND CAP.CONTRA1=KT.CONTRA1 GROUP BY 1 ) BASE ON INSTRMNT_ID=CHAVE_FR WHERE EAD < 0
A18: INSTRMNT | B18: EAD | C18: Controlos | D18: Teste contra a fonte | E18: 45462 | F18: 45443 | G18: OK | H18: A fonte (CT013) tem um valor muito superior, porque existem várias chaves FR para uma chave BDR | I18: SELECT DISTINCT INSTRMNT_ID, S1EMP, CONTRA1, EAD, RWA, rwa_final, ead_final_bruta FROM (SELECT DISTINCT INSTRMNT_ID, CCF, dflt_stts_instrmnt, DPD, EAD, LGD, pd_crr_incptn, pd_crr_rd, pd_crr_rd_t1, RWA, rwa_mthd, spcltv_lndng, crrltn_cffcnt FROM cd_loan_tapes_bce.LT002_INSTRUMENT WHERE REF_DATE='${date}' AND NOME_PERIMETRO='Individual Corporativo' AND AMBITO = 'PM' -- AND instrmnt_id = '31000347000690020000000000000000' ) LT002 INNER JOIN (SELECT CHAVE_FR, KT.S1EMP, KT.CONTRA1, SUM(flag_cons_cap) AS VAL, SUM(RWA_FINAL) AS RWA_FINAL, SUM(ead_final_bruta) AS ead_final_bruta FROM (SELECT CHAVE_FR, S1EMP, CONTRA1 FROM (SELECT DISTINCT CONCAT(CEMPRESA, CBALCAO,CNUMECTA, ZDEPOSIT) AS CHAVE_MASTER, CONCAT(CEMPRESA_FR, CBALCAO_FR,CNUMECTA_FR, ZDEPOSIT_FR) AS CHAVE_FR FROM cd_captools.KT_CHAVES_FINREP WHERE REF_DATE='${date}') KT_FR INNER JOIN (SELECT DISTINCT CONCAT(CEMPRESA, CBALCAO,CNUMECTA, ZDEPOSIT) AS CHAVE_MASTER, S1EMP, CONTRA1 FROM cd_captools.KT_CHAVES_BDR WHERE REF_DATE='${date}') KT_BDR ON KT_FR.CHAVE_MASTER=KT_BDR.CHAVE_MASTER WHERE CHAVE_FR = '31005122428280011667450200000001' OR concat(S1EMP,CONTRA1) = '1814008684' ) KT INNER JOIN (SELECT CT013.* FROM (SELECT REF_DATE, id_capital_perimetros, s1emp, contra1, flag_cons_cap, rwa_final, ead_final_bruta FROM cd_captools.ct013_rwa_princ WHERE REF_DATE = '${date}' -- AND flag_cons_cap = 1 AND flag_conc_contab = 1 AND exercicio = "REAL" -- 30-03-2021: Adição de filtro AND subtipo_risco in ('1.1', '1.2', '1.3', '1.4', '1.5', '1.6', '1.7', '1.8', '1.9', '1.13')) CT013 INNER JOIN (SELECT DISTINCT ID_CAPITAL_PERIMETROS, REF_DATE FROM cd_captools.ct020_rwa_per WHERE REF_DATE = '${date}' AND NOME_PERIMETRO='Individual Corporativo') CT020 on CT013.ID_CAPITAL_PERIMETROS=CT020.ID_CAPITAL_PERIMETROS) CAP ON CAP.S1EMP=KT.S1EMP AND CAP.CONTRA1=KT.CONTRA1 GROUP BY 1,2,3 ) X on CHAVE_FR = INSTRMNT_ID
A19: INSTRMNT | B19: EAD | C19: Controlos | D19: Verificar saldo de capital | E19: 45462 | F19: 45443 | G19: OK | I19: SELECT LT002.instrmnt_id, RWA, EAD, CONCAT(LT001.cempresa,LT001.cbalcao,LT001.cnumecta,LT001.zdeposit) AS CHAVE_FR, NVL(SUM(LT001.msaldo_final),0) AS Saldo_Capital FROM (SELECT cempresa, cbalcao, cnumecta, zdeposit, ccontab_final_cargabal, msaldo_final FROM cd_loan_tapes_bce.lt001_univ_oper WHERE REF_DATE = '${date}' AND NOME_PERIMETRO='Individual Corporativo' AND AMBITO = 'PM' ) LT001 INNER JOIN (SELECT * FROM cd_loan_tapes_bce.kt_chaves_lt WHERE REF_DATE = '${date}' AND NOME_PERIMETRO='Individual Corporativo' AND AMBITO = 'PM' AND segmento = 'ESTR') KT_LT ON CONCAT(LT001.cempresa,LT001.cbalcao,LT001.cnumecta,LT001.zdeposit) = CONCAT(KT_LT.cempresa,KT_LT.cbalcao,KT_LT.cnumecta,KT_LT.zdeposit) INNER JOIN (SELECT instrmnt_id, rwa, ead FROM cd_loan_tapes_bce.lt002_instrument WHERE REF_DATE = '${date}' AND NOME_PERIMETRO='Individual Corporativo' AND AMBITO = 'PM' AND segmento ='ESTR' AND instrmnt_id in ( '310051224282800116674502P0080001', '310051224282800116674502P0070001', '310051224282800116674502P0060001', '31005122428280011667450200000001', '310051224282800116674502P0100001', '310051224282800116674502P0110001', '310051224282800116674502P0020001', '310051224282800116674502P0010001', '310051224282800116674502P0030001', '310051224282800116674502P0090001' ) ) LT002 ON KT_LT.INSTRMNT_ID = LT002.INSTRMNT_ID LEFT JOIN (SELECT * FROM cd_captools.fr802_pl_contas WHERE 1=1 AND REF_DATE = '${date}' AND cod_plano = 'CARGABAL' AND ((tipo_conta IN ('A','P') AND carteira_contabilistica not in('provisoes para compromissos e garantias concedidas', 'outras provisoes') AND composicao_valor <> 'imparidade acumulada' AND bruto_imparidade <> 'imparidade') OR (tipo_conta IN ('EA','EP','M'))) ) FR802 ON FR802.CONTA = LT001.ccontab_final_cargabal LEFT JOIN (SELECT * FROM cd_captools.ct805_matriz_cnt WHERE 1=1 AND REF_DATE = '${date}' AND DOMINIO = 'Capital' AND NOME_PERIMETRO = 'Individual Corporativo' ) CT805 ON FR802.CONTA = CT805.CONTA GROUP BY 1,2,3,4
A20: PRTCTN | B20: PRM_LCTN | C20: Default values | D20: Validar que os MISS e NA estão de acordo com a especificação | E20: 45464 | F20: 45443 | G20: NOK | H20: 100220 Casos que deviam ser N e estão a ser reportados MISS | I20: SELECT substr(prtctn_id,1,1), valor_it, count(*) FROM (SELECT prtctn_id, valor_it, CASE WHEN substr(prtctn_id,1,1)<>'I' THEN 'N/A' WHEN cfinbem IN ('01','06','07','08') AND CL_HAB>='3.40' THEN 'Y' WHEN cfinbem IN ('01','06','07','08') AND CL_HAB<'3.40' THEN 'N' WHEN cfinbem='02' AND CL_COM>='3.40' THEN 'Y' WHEN cfinbem='02' AND CL_COM<'3.40' THEN 'N' WHEN cfinbem='03' AND CL_SERV>='3.40' THEN 'Y' WHEN cfinbem='03' AND CL_SERV<'3.40' THEN 'N' WHEN cfinbem IN ('04','05') AND CL_IND>='3.40' THEN 'Y' WHEN cfinbem IN ('04','05') AND CL_IND<'3.40' THEN 'N' else 'MISS' END AS valor_simulado, cdisconf, cfinbem, CD_REPARTICAO_FIN, CL_COM, CL_HAB, CL_IND, CL_SERV FROM (SELECT prtctn_id, prm_lctn as valor_it FROM cd_loan_tapes_bce.lt004_protection WHERE ref_date='${date}' AND nome_perimetro='Individual Corporativo' AND segmento='ESTR' AND ambito='PM') AS LT004 LEFT JOIN (SELECT ckbalbem, ckctabem, ckrefbem, trim (cfinbem) as cfinbem, cdisconf FROM cd_garantias.gt009_bens_imov WHERE ref_date='${date}') AS gt009 on prtctn_id=concat('I_', CKBALBEM, '_', CKCTABEM, '_', CKREFBEM) LEFT JOIN (SELECT tayd91c0_celemtab, tayd91c0_nelemc10 AS CD_REPARTICAO_FIN FROM cd_estruturais.tat91_tabelas WHERE tayd91c0_ctabela='J48' AND data_date_part IN (SELECT MAX(data_date_part) from cd_estruturais.tat91_tabelas where data_date_part <= '${date}' and tayd91c0_ctabela= 'J48' )) AS TAT_J48 ON gt009.cdisconf=TAT_J48.tayd91c0_celemtab LEFT JOIN (SELECT tayd91c0_celemtab, trim(SUBSTR(TAYD91C0_NELEMC11,5,4)) as CL_HAB, trim(SUBSTR(TAYD91C0_NELEMC12,5,4)) AS CL_COM, trim(SUBSTR(TAYD91C0_NELEMC13,5,4)) AS CL_IND, trim(SUBSTR(TAYD91C0_NELEMC14,5,4)) AS CL_SERV FROM cd_estruturais.tat91_tabelas WHERE tayd91c0_ctabela='162' AND data_date_part IN (SELECT MAX(data_date_part) from cd_estruturais.tat91_tabelas where data_date_part <= '${date}' and tayd91c0_ctabela= '162' )) AS TAT_162 ON TAT_J48.CD_REPARTICAO_FIN=TAT_162.tayd91c0_celemtab ) as base GROUP BY 1,2
A21: PRTCTN | B21: PRM_LCTN | C21: Desenvolvimento | D21: Validar se campo está de acordo com o especificado | E21: 45464 | F21: 45443 | G21: NOK | H21: 100220 Casos que deviam ser N e estão a ser reportados MISS | I21: SELECT count(*) FROM (SELECT prtctn_id, valor_it, CASE WHEN substr(prtctn_id,1,1)<>'I' THEN 'N/A' WHEN cfinbem IN ('','01','06','07','08') AND CL_HAB>='3.40' THEN 'Y' WHEN cfinbem IN ('','01','06','07','08') AND CL_HAB<'3.40' THEN 'N' WHEN cfinbem is NULL AND CL_HAB>='3.40' THEN 'Y' WHEN cfinbem is NULL AND CL_HAB < '3.40' THEN 'N' WHEN cfinbem='02' AND CL_COM>='3.40' THEN 'Y' WHEN cfinbem='02' AND CL_COM<'3.40' THEN 'N' WHEN cfinbem='03' AND CL_SERV>='3.40' THEN 'Y' WHEN cfinbem='03' AND CL_SERV<'3.40' THEN 'N' WHEN cfinbem IN ('04','05') THEN 'N' else 'N' END AS valor_simulado, cdisconf, cfinbem, CD_REPARTICAO_FIN, CL_COM, CL_HAB, CL_IND, CL_SERV FROM (SELECT prtctn_id, prm_lctn as valor_it FROM cd_loan_tapes_bce.lt004_protection WHERE ref_date='${date}' AND nome_perimetro='Individual Corporativo' AND segmento='ESTR' AND ambito='PM') AS LT004 LEFT JOIN (SELECT ckbalbem, ckctabem, ckrefbem, trim (cfinbem) as cfinbem, cdisconf FROM cd_garantias.gt009_bens_imov WHERE ref_date='${date}') AS gt009 on prtctn_id=concat('I_', CKBALBEM, '_', CKCTABEM, '_', CKREFBEM) LEFT JOIN (SELECT tayd91c0_celemtab, tayd91c0_nelemc10 AS CD_REPARTICAO_FIN FROM cd_estruturais.tat91_tabelas WHERE tayd91c0_ctabela='J48' AND data_date_part='2024-05-31') AS TAT_J48 ON gt009.cdisconf=TAT_J48.tayd91c0_celemtab LEFT JOIN (SELECT tayd91c0_celemtab, trim(SUBSTR(TAYD91C0_NELEMC11,5,4)) as CL_HAB, trim(SUBSTR(TAYD91C0_NELEMC12,5,4)) AS CL_COM, trim(SUBSTR(TAYD91C0_NELEMC13,5,4)) AS CL_IND, trim(SUBSTR(TAYD91C0_NELEMC14,5,4)) AS CL_SERV FROM cd_estruturais.tat91_tabelas WHERE tayd91c0_ctabela='162' AND data_date_part='2024-05-31') AS TAT_162 ON TAT_J48.CD_REPARTICAO_FIN=TAT_162.tayd91c0_celemtab ) as base WHERE 1=1 AND valor_it <> valor_simulado
A22: PRTCTN | B22: PRM_LCTN | C22: Controlos | D22: Verificar se o campo está de acordo com a Codelist | E22: 45464 | F22: 45443 | G22: OK | I22: SELECT prm_lctn, COUNT(*) FROM cd_loan_tapes_bce.lt004_protection WHERE ref_date='${date}' AND nome_perimetro='Individual Corporativo' AND segmento='ESTR' AND ambito='PM' GROUP BY prm_lctn
A23: PRTCTN | B23: PRM_LCTN | C23: Controlos | D23: If "Protection type" does not equal '8 - Residential real estate collateral' nor '9 - Offices and commercial premises' nor '10 - Commercial real estate collateral' then "Prime location according to bank-internal definition (Y/N)" must be populated with default values | E23: 45468 | F23: 45443 | G23: OK | H23: Existem 13 casos com TYP_PRTCTN a MISS. Voltar a testar quando TYP_PRTCTN estiver concluído | I23: SELECT * FROM (SELECT prtctn_id, valor_it, CASE WHEN substr(prtctn_id,1,1)<>'I' THEN 'N/A' WHEN cfinbem IN ('','01','06','07','08') AND CL_HAB>='3.40' THEN 'Y' WHEN cfinbem IN ('','01','06','07','08') AND CL_HAB<'3.40' THEN 'N' WHEN cfinbem is NULL AND CL_HAB>='3.40' THEN 'Y' WHEN cfinbem is NULL AND CL_HAB < '3.40' THEN 'N' WHEN cfinbem='02' AND CL_COM>='3.40' THEN 'Y' WHEN cfinbem='02' AND CL_COM<'3.40' THEN 'N' WHEN cfinbem='03' AND CL_SERV>='3.40' THEN 'Y' WHEN cfinbem='03' AND CL_SERV<'3.40' THEN 'N' WHEN cfinbem IN ('04','05') THEN 'N' else 'N' END AS valor_simulado, TYP_PRTCTN FROM (SELECT prtctn_id, TYP_PRTCTN, prm_lctn as valor_it FROM cd_loan_tapes_bce.lt004_protection WHERE ref_date='${date}' AND nome_perimetro='Individual Corporativo' AND segmento='ESTR' AND ambito='PM') AS LT004 LEFT JOIN (SELECT ckbalbem, ckctabem, ckrefbem, trim (cfinbem) as cfinbem, cdisconf FROM cd_garantias.gt009_bens_imov WHERE ref_date='${date}') AS gt009 on prtctn_id=concat('I_', CKBALBEM, '_', CKCTABEM, '_', CKREFBEM) LEFT JOIN (SELECT tayd91c0_celemtab, tayd91c0_nelemc10 AS CD_REPARTICAO_FIN FROM cd_estruturais.tat91_tabelas WHERE tayd91c0_ctabela='J48' AND data_date_part='2024-05-31') AS TAT_J48 ON gt009.cdisconf=TAT_J48.tayd91c0_celemtab LEFT JOIN (SELECT tayd91c0_celemtab, trim(SUBSTR(TAYD91C0_NELEMC11,5,4)) as CL_HAB, trim(SUBSTR(TAYD91C0_NELEMC12,5,4)) AS CL_COM, trim(SUBSTR(TAYD91C0_NELEMC13,5,4)) AS CL_IND, trim(SUBSTR(TAYD91C0_NELEMC14,5,4)) AS CL_SERV FROM cd_estruturais.tat91_tabelas WHERE tayd91c0_ctabela='162' AND data_date_part='2024-05-31') AS TAT_162 ON TAT_J48.CD_REPARTICAO_FIN=TAT_162.tayd91c0_celemtab ) as base WHERE 1=1 AND typ_prtctn NOT IN ('8','9','10') AND VALOR_SIMULADO <> 'N/A'
A24: PRTCTN | B24: PRM_LCTN | C24: Controlos | D24: If "Protection type" equals '8 - Residential real estate collateral' or '9 - Offices and commercial premises' or '10 - Commercial real estate collateral' then "Prime location according to bank-internal definition (Y/N)" cannot be 'Not applicable' | E24: 45468 | F24: 45443 | G24: OK | I24: SELECT * FROM (SELECT prtctn_id, valor_it, CASE WHEN substr(prtctn_id,1,1)<>'I' THEN 'N/A' WHEN cfinbem IN ('','01','06','07','08') AND CL_HAB>='3.40' THEN 'Y' WHEN cfinbem IN ('','01','06','07','08') AND CL_HAB<'3.40' THEN 'N' WHEN cfinbem is NULL AND CL_HAB>='3.40' THEN 'Y' WHEN cfinbem is NULL AND CL_HAB < '3.40' THEN 'N' WHEN cfinbem='02' AND CL_COM>='3.40' THEN 'Y' WHEN cfinbem='02' AND CL_COM<'3.40' THEN 'N' WHEN cfinbem='03' AND CL_SERV>='3.40' THEN 'Y' WHEN cfinbem='03' AND CL_SERV<'3.40' THEN 'N' WHEN cfinbem IN ('04','05') THEN 'N' else 'N' END AS valor_simulado, TYP_PRTCTN FROM (SELECT prtctn_id, TYP_PRTCTN, prm_lctn as valor_it FROM cd_loan_tapes_bce.lt004_protection WHERE ref_date='${date}' AND nome_perimetro='Individual Corporativo' AND segmento='ESTR' AND ambito='PM') AS LT004 LEFT JOIN (SELECT ckbalbem, ckctabem, ckrefbem, trim (cfinbem) as cfinbem, cdisconf FROM cd_garantias.gt009_bens_imov WHERE ref_date='${date}') AS gt009 on prtctn_id=concat('I_', CKBALBEM, '_', CKCTABEM, '_', CKREFBEM) LEFT JOIN (SELECT tayd91c0_celemtab, tayd91c0_nelemc10 AS CD_REPARTICAO_FIN FROM cd_estruturais.tat91_tabelas WHERE tayd91c0_ctabela='J48' AND data_date_part='2024-05-31') AS TAT_J48 ON gt009.cdisconf=TAT_J48.tayd91c0_celemtab LEFT JOIN (SELECT tayd91c0_celemtab, trim(SUBSTR(TAYD91C0_NELEMC11,5,4)) as CL_HAB, trim(SUBSTR(TAYD91C0_NELEMC12,5,4)) AS CL_COM, trim(SUBSTR(TAYD91C0_NELEMC13,5,4)) AS CL_IND, trim(SUBSTR(TAYD91C0_NELEMC14,5,4)) AS CL_SERV FROM cd_estruturais.tat91_tabelas WHERE tayd91c0_ctabela='162' AND data_date_part='2024-05-31') AS TAT_162 ON TAT_J48.CD_REPARTICAO_FIN=TAT_162.tayd91c0_celemtab ) as base WHERE 1=1 AND typ_prtctn IN ('8','9','10') AND VALOR_SIMULADO ='N/A'
A25: INSTRMNT | B25: OFF_BLNC_SHT_AMNT_INSTRMNT_PRVS | C25: Desenvolvimento | D25: Validar se campo está de acordo com o especificado | E25: 45463 | F25: 45443 | G25: NOK | H25: Campo com valor 0 para os restantes contratos que não estão marcados com valores default | I25: SELECT off_blnc_sht_amnt_instrmnt_prvs, count(*) FROM cd_loan_tapes_bce.lt002_instrument WHERE 1=1 AND REF_DATE='${date}' AND NOME_PERIMETRO='Individual Corporativo' AND AMBITO = 'PM' AND SEGMENTO = 'ESTR' AND off_blnc_sht_amnt_instrmnt_prvs NOT IN(11111111111.00,99999999999.00) GROUP BY 1
A26: INSTRMNT | B26: OTSTNDNG_NMNL_AMNT_INSTRMNT_PRVS | C26: Desenvolvimento | D26: Validar se campo está de acordo com o especificado | E26: 45463 | F26: 45443 | G26: NOK
A27: PRTCTN | B27: DT_LST_FLL_APPRSL | C27: Desenvolvimento | D27: Validar se campo está de acordo com o especificado | E27: 45468 | F27: 45443 | G27: NOK | H27: Campo está a reportar a data da última avaliação e não a data da última avaliação in person. Implementação não está a aplicar a metodologia de cálculo de acordo com a especificação | I27: SELECT count(*) FROM (SELECT LT004.prtctn_id, LT004.dt_lst_fll_apprsl as valor_lt, LT004.dt_orgnl_prtctn_vl, valor_simulado FROM (SELECT prtctn_id, dt_lst_fll_apprsl, dt_prtctn_vl, dt_orgnl_prtctn_vl FROM cd_loan_tapes_bce.lt004_protection WHERE ref_date='${date}' AND nome_perimetro='Individual Corporativo' AND segmento='ESTR' AND ambito='PM' AND prtctn_id LIKE 'I%') LT004 LEFT JOIN (SELECT max(davalia) as valor_simulado, CONCAT('I_', CKBALBEM, '_', CKCTABEM, '_', CKREFBEM) AS prtctn_id FROM cd_garantias.gt011_avalc_imov WHERE 1=1 AND ref_date='${date}' AND ( (CTIPREAVL IN ('A','R') AND CORAVGP = 'G39') OR CORAVGP='G26') GROUP BY 2 ) GT011 ON LT004.prtctn_id = GT011.prtctn_id ) x WHERE 1=1 AND valor_simulado <> valor_lt
A28: PRTCTN | B28: DT_LST_FLL_APPRSL | C28: Default values | D28: Validar que os MISS e NA estão de acordo com a especificação | E28: 45467 | F28: 45443 | G28: OK | I28: SELECT prtctn_id, dt_lst_fll_apprsl FROM cd_loan_tapes_bce.lt004_protection WHERE ref_date='${date}' AND nome_perimetro='Individual Corporativo' AND segmento='ESTR' AND ambito='PM' AND prtctn_id LIKE 'P%' -- AND prtctn_id LIKE 'F%' AND dt_lst_fll_apprsl <> '1111-11-11'
A29: PRTCTN | B29: DT_LST_FLL_APPRSL | C29: Controlos | D29: Date of last full appraisal must be later than 01 January 1970 | E29: 45467 | F29: 45443 | G29: OK | I29: SELECT DISTINCT dt_lst_fll_apprsl FROM cd_loan_tapes_bce.lt004_protection WHERE ref_date='${date}' AND nome_perimetro='Individual Corporativo' AND segmento='ESTR' AND ambito='PM' AND dt_lst_fll_apprsl < '1970-01-01'
A30: PRTCTN | B30: DT_LST_FLL_APPRSL | C30: Controlos | D30: Date of last full appraisal must have a Date format (yyyy-mm-dd) | E30: 45467 | F30: 45443 | G30: OK | I30: SELECT DISTINCT dt_lst_fll_apprsl FROM cd_loan_tapes_bce.lt004_protection WHERE ref_date='${date}' AND nome_perimetro='Individual Corporativo' AND segmento='ESTR' AND ambito='PM' AND length(dt_lst_fll_apprsl) <> 10
A31: PRTCTN | B31: DT_LST_FLL_APPRSL | C31: Controlos | D31: "Date of last full appraisal" cannot be later than "Reference date" | E31: 45467 | F31: 45443 | G31: OK | I31: SELECT count(*) FROM (SELECT LT004.prtctn_id, LT004.dt_lst_fll_apprsl as valor_lt, LT004.dt_orgnl_prtctn_vl, valor_simulado FROM (SELECT prtctn_id, dt_lst_fll_apprsl, dt_prtctn_vl, dt_orgnl_prtctn_vl FROM cd_loan_tapes_bce.lt004_protection WHERE ref_date='${date}' AND nome_perimetro='Individual Corporativo' AND segmento='ESTR' AND ambito='PM' AND prtctn_id LIKE 'I%') LT004 LEFT JOIN (SELECT max(davalia) as valor_simulado, CONCAT('I_', CKBALBEM, '_', CKCTABEM, '_', CKREFBEM) AS prtctn_id FROM cd_garantias.gt011_avalc_imov WHERE 1=1 AND ref_date='${date}' AND ( (CTIPREAVL IN ('A','R') AND CORAVGP = 'G39') OR CORAVGP='G26') GROUP BY 2 ) GT011 ON LT004.prtctn_id = GT011.prtctn_id ) x WHERE 1=1 -- AND valor_simulado <> valor_lt -- AND valor_simulado >= dt_orgnl_prtctn_vl AND valor_simulado > '${date}' -- GROUP BY 1,2,3,4
A32: PRTCTN | B32: DT_LST_FLL_APPRSL | C32: Controlos | D32: "Date of last full appraisal" must be greater or equal to the "Date of the appraisal previous to the most recent one available, i.e. previous to the last full appraisal (field DT_LST_FLL_APPRSL)." If DT_LST_FLL_APPRSL and DT_APPRSL_PRVS are populated other than default values, then DT_LST_FLL_APPRSL >= DT_APPRSL_PRVS | E32: 45471 | F32: 45443
A33: INSTRMNT | B33: TYP_MRTGG | C33: Desenvolvimento | D33: Simular especificação | E33: 45468 | F33: 45443 | G33: NOK | I33: SELECT CASE WHEN TYP_INSTRMNT NOT IN ('71','80','1001','1002','1004','2001') THEN '11111111111' WHEN LT06.INSTRMNT_ID IS NULL THEN '11111111111' WHEN LT06.INSTRMNT_ID IS NOT NULL AND imov>0 THEN '1' WHEN LT06.INSTRMNT_ID IS NOT NULL AND imov=0 THEN '5' END AS TYP_MRTGG_Simulado FROM (SELECT * FROM cd_loan_tapes_bce.lt002_instrument WHERE ref_date = '${date}' AND nome_perimetro = 'Individual Corporativo' AND segmento='ESTR' AND ambito='PM' ) LT02 LEFT JOIN (SELECT instrmnt_id, prtctn_id, sum(if(substr(prtctn_id,1,1) = 'I',1,0)) as imov FROM cd_loan_tapes_bce.lt006_instr_prot WHERE ref_date = '${date}' AND nome_perimetro = 'Individual Corporativo' AND segmento='ESTR' AND ambito='PM' GROUP BY 1,2 ) LT06 on LT02.instrmnt_id = LT06.instrmnt_id
A34: INSTRMNT | B34: TYP_MRTGG | C34: Controlos | D34: If "Type of instrument" is different from '71 - Trade receivables', '80- Finance leases', '1001 - Revolving credit other than overdrafts and credit card debt', '1002 - Credit lines other than revolving credit', '1004 - Loans other than overdrafts, convenience credit, extended credit, credit card credit, revolving credit other than credit card credit, reverse repurchase agreements, trade receivables and financial leases' or '2001 - Guarantees' then "Type of mortgage" has to be populated with default values | E34: 45468 | F34: 45443 | G34: NOK | H34: 1027 contratos que possuem uma garantia | I34: SELECT DISTINCT LT02.instrmnt_id, LT06.instrmnt_id, LT06.prtctn_id, CASE WHEN TYP_INSTRMNT NOT IN ('71','80','1001','1002','1004','2001') THEN '11111111111' WHEN LT06.INSTRMNT_ID IS NULL THEN '11111111111' WHEN LT06.INSTRMNT_ID IS NOT NULL AND imov>0 THEN '1' WHEN LT06.INSTRMNT_ID IS NOT NULL AND imov=0 THEN '5' END AS TYP_MRTGG_Simulado, typ_prtctn, TYP_INSTRMNT FROM (SELECT * FROM cd_loan_tapes_bce.lt002_instrument WHERE ref_date = '${date}' AND nome_perimetro = 'Individual Corporativo' AND segmento='ESTR' AND ambito='PM' ) LT02 LEFT JOIN (SELECT instrmnt_id, prtctn_id, sum(if(substr(prtctn_id,1,1) = 'I',1,0)) as imov FROM cd_loan_tapes_bce.lt006_instr_prot WHERE ref_date = '${date}' AND nome_perimetro = 'Individual Corporativo' AND segmento='ESTR' AND ambito='PM' GROUP BY 1,2 ) LT06 on LT02.instrmnt_id = LT06.instrmnt_id ---- CONTROLOS LEFT JOIN (SELECT prtctn_id, typ_prtctn FROM cd_loan_tapes_bce.lt004_protection WHERE ref_date = '${date}' AND nome_perimetro = 'Individual Corporativo' AND segmento='ESTR' AND ambito='PM' ) LT04 ON LT04.prtctn_id = LT06.prtctn_id WHERE 1=1 AND TYP_INSTRMNT NOT IN ('71','80','1001','1002','1004','2001')
A35: INSTRMNT | B35: TYP_MRTGG | C35: Controlos | D35: If "Protection type" equals '8 - Residential real estate collateral' or '9 - Offices and commercial premises' or '10 - Commercial real estate collateral', then "Type of mortgage" cannot be 'Not applicable' | E35: 45468 | F35: 45443 | G35: NOK | H35: 46 Contratos descobertos com proteções imóveis associadas | I35: SELECT DISTINCT LT02.instrmnt_id, LT06.instrmnt_id, LT06.prtctn_id, CASE WHEN TYP_INSTRMNT NOT IN ('71','80','1001','1002','1004','2001') THEN '11111111111' WHEN LT06.INSTRMNT_ID IS NULL THEN '11111111111' WHEN LT06.INSTRMNT_ID IS NOT NULL AND imov>0 THEN '1' WHEN LT06.INSTRMNT_ID IS NOT NULL AND imov=0 THEN '5' END AS TYP_MRTGG_Simulado, typ_prtctn, TYP_INSTRMNT FROM (SELECT * FROM cd_loan_tapes_bce.lt002_instrument WHERE ref_date = '${date}' AND nome_perimetro = 'Individual Corporativo' AND segmento='ESTR' AND ambito='PM' ) LT02 LEFT JOIN (SELECT instrmnt_id, prtctn_id, sum(if(substr(prtctn_id,1,1) = 'I',1,0)) as imov FROM cd_loan_tapes_bce.lt006_instr_prot WHERE ref_date = '${date}' AND nome_perimetro = 'Individual Corporativo' AND segmento='ESTR' AND ambito='PM' GROUP BY 1,2 ) LT06 on LT02.instrmnt_id = LT06.instrmnt_id ---- CONTROLOS LEFT JOIN (SELECT prtctn_id, typ_prtctn FROM cd_loan_tapes_bce.lt004_protection WHERE ref_date = '${date}' AND nome_perimetro = 'Individual Corporativo' AND segmento='ESTR' AND ambito='PM' ) LT04 ON LT04.prtctn_id = LT06.prtctn_id WHERE 1=1 AND TYP_PRTCTN IN ('8','9','10')
A36: INSTRMNT | B36: TYP_MRTGG | C36: Controlos | D36: Número de casos com incidência | E36: 45468 | F36: 45443 | G36: NOK | H36: 46 Contratos descobertos com proteções imóveis associadas | I36: SELECT count(*) FROM (SELECT DISTINCT LT02.instrmnt_id AS instrmnt_id_LT02, LT06.instrmnt_id, LT06.prtctn_id, CASE WHEN TYP_INSTRMNT NOT IN ('71','80','1001','1002','1004','2001') THEN '11111111111' WHEN LT06.INSTRMNT_ID IS NULL THEN '11111111111' WHEN LT06.INSTRMNT_ID IS NOT NULL AND imov>0 THEN '1' WHEN LT06.INSTRMNT_ID IS NOT NULL AND imov=0 THEN '5' END AS TYP_MRTGG_Simulado, typ_prtctn, TYP_INSTRMNT FROM (SELECT * FROM cd_loan_tapes_bce.lt002_instrument WHERE ref_date = '${date}' AND nome_perimetro = 'Individual Corporativo' AND segmento='ESTR' AND ambito='PM' ) LT02 LEFT JOIN (SELECT instrmnt_id, prtctn_id, sum(if(substr(prtctn_id,1,1) = 'I',1,0)) as imov FROM cd_loan_tapes_bce.lt006_instr_prot WHERE ref_date = '${date}' AND nome_perimetro = 'Individual Corporativo' AND segmento='ESTR' AND ambito='PM' GROUP BY 1,2 ) LT06 on LT02.instrmnt_id = LT06.instrmnt_id ---- CONTROLOS LEFT JOIN (SELECT prtctn_id, typ_prtctn FROM cd_loan_tapes_bce.lt004_protection WHERE ref_date = '${date}' AND nome_perimetro = 'Individual Corporativo' AND segmento='ESTR' AND ambito='PM' ) LT04 ON LT04.prtctn_id = LT06.prtctn_id WHERE 1=1 -- AND TYP_INSTRMNT NOT IN ('71','80','1001','1002','1004','2001') AND TYP_PRTCTN IN ('8','9','10') )X WHERE 1=1 AND TYP_MRTGG_Simulado = '11111111111' AND TYP_INSTRMNT = '20'
A37: INSTRMNT | B37: TYP_MRTGG | C37: Controlos | D37: Número de casos com incidência | E37: 45469 | F37: 45443 | G37: NOK | H37: 1027 contratos que possuem uma garantia | I37: SELECT count(*), count(DISTINCT instrmnt_id_LT02) FROM (SELECT DISTINCT LT02.instrmnt_id AS instrmnt_id_LT02, LT06.instrmnt_id, LT06.prtctn_id, CASE -- WHEN TYP_INSTRMNT NOT IN ('71','80','1001','1002','1004','2001') THEN '11111111111' WHEN LT06.INSTRMNT_ID IS NULL THEN '11111111111' WHEN LT06.INSTRMNT_ID IS NOT NULL AND imov>0 THEN '1' WHEN LT06.INSTRMNT_ID IS NOT NULL AND imov=0 THEN '5' END AS TYP_MRTGG_Simulado, typ_prtctn, TYP_INSTRMNT FROM (SELECT * FROM cd_loan_tapes_bce.lt002_instrument WHERE ref_date = '${date}' AND nome_perimetro = 'Individual Corporativo' AND segmento='ESTR' AND ambito='PM' ) LT02 LEFT JOIN (SELECT instrmnt_id, prtctn_id, sum(if(substr(prtctn_id,1,1) = 'I',1,0)) as imov FROM cd_loan_tapes_bce.lt006_instr_prot WHERE ref_date = '${date}' AND nome_perimetro = 'Individual Corporativo' AND segmento='ESTR' AND ambito='PM' GROUP BY 1,2 ) LT06 on LT02.instrmnt_id = LT06.instrmnt_id ---- CONTROLOS LEFT JOIN (SELECT prtctn_id, typ_prtctn FROM cd_loan_tapes_bce.lt004_protection WHERE ref_date = '${date}' AND nome_perimetro = 'Individual Corporativo' AND segmento='ESTR' AND ambito='PM' ) LT04 ON LT04.prtctn_id = LT06.prtctn_id WHERE 1=1 AND TYP_INSTRMNT not IN ('71','80','1001','1002','1004','2001') and LT06.prtctn_id is not null -- AND TYP_PRTCTN IN ('8','9','10') )X -- ORDER BY TYP_MRTGG_Simulado DESC -- WHERE 1=1 -- AND TYP_MRTGG_Simulado = '11111111111' -- AND TYP_INSTRMNT = '20'
A38: INSTRMNT | B38: SICR_ASSSSMNT_MTHD | C38: Controlos | D38: "Significant increase in credit risk assessment approach" should match the information on the Codelist | E38: 45468 | F38: 45443 | G38: OK | I38: SELECT count(*), sicr_assssmnt_mthd, imprmnt_stts FROM cd_loan_tapes_bce.lt002_instrument WHERE ref_date='2024-05-31' AND nome_perimetro='Individual Corporativo' AND segmento='ESTR' AND ambito='PM' GROUP BY 2, 3
A39: INSTRMNT | B39: SICR_ASSSSMNT_MTHD | C39: Controlos | D39: If "Impairment status" equals '23 - Stage1' or '24 - Stage 2' then "Significant increase in credit risk assessment approach" cannot be 'Not applicable' | E39: 45468 | F39: 45443 | G39: OK | I39: SELECT count(*), sicr_assssmnt_mthd, imprmnt_stts FROM cd_loan_tapes_bce.lt002_instrument WHERE ref_date='2024-05-31' AND nome_perimetro='Individual Corporativo' AND segmento='ESTR' AND ambito='PM' GROUP BY 2, 3
A40: INSTRMNT | B40: SICR_ASSSSMNT_MTHD | C40: Controlos | D40: If "Impairment status" is not equal '23 - Stage1' nor '24 - Stage 2' then "Significant increase in credit risk assessment approach" must be 'Not applicable' | E40: 45468 | F40: 45443 | G40: OK | I40: SELECT count(*), sicr_assssmnt_mthd, imprmnt_stts FROM cd_loan_tapes_bce.lt002_instrument WHERE ref_date='2024-05-31' AND nome_perimetro='Individual Corporativo' AND segmento='ESTR' AND ambito='PM' GROUP BY 2, 3
A41: PRTCTN | B41: TYP_PRTCTN | C41: Desenvolvimento | D41: Simular especificação | E41: 45461 | F41: 45443 | G41: OK | I41: SELECT prtctn_id, CASE -- GARANTIAS IMOVEIS WHEN CGARANT_BEM = '5000' THEN '10' WHEN CGARANT_BEM = '5101' THEN '8' WHEN CGARANT_BEM = '5102' THEN '8' WHEN CGARANT_BEM = '5103' THEN '8' WHEN CGARANT_BEM = '5104' THEN '8' WHEN CGARANT_BEM = '5201' THEN '10' WHEN CGARANT_BEM = '5202' THEN '10' WHEN CGARANT_BEM = '5302' THEN '10' WHEN CGARANT_BEM = '5203' THEN '9' WHEN CGARANT_BEM = '5204' THEN '9' WHEN CGARANT_BEM = '5205' THEN '10' WHEN CGARANT_BEM = '5206' THEN '10' WHEN CGARANT_BEM = '5207' THEN '10' WHEN CGARANT_BEM = '5208' THEN '10' WHEN CGARANT_BEM = '5209' THEN '10' WHEN CGARANT_BEM = '5210' THEN '10' WHEN CGARANT_BEM = '5211' THEN '10' WHEN CGARANT_BEM = '5300' THEN '10' WHEN CGARANT_BEM = '5212' THEN '10' WHEN CGARANT_BEM = '5213' THEN '10' WHEN CGARANT_BEM = '5214' THEN '10' WHEN CGARANT_BEM = '5303' THEN '10' WHEN CGARANT_BEM = '5301' THEN '10' WHEN CGARANT_BEM = '5215' THEN '10' WHEN CGARANT_BEM = '5216' THEN '10' WHEN CGARANT_BEM = '5217' THEN '10' WHEN CGARANT_BEM = '5218' THEN '10' -- GARANTIAS FINANCEIRAS WHEN CGARANT_BEM = '6101' THEN '5' WHEN CGARANT_BEM = '6102' THEN '5' WHEN CGARANT_BEM = '6201' THEN '15' WHEN CGARANT_BEM = '6202' THEN '15' WHEN CGARANT_BEM = '6300' THEN '18' WHEN CGARANT_BEM = '6401' THEN '12' WHEN CGARANT_BEM = '6402' THEN '12' WHEN CGARANT_BEM = '6403' THEN '12' WHEN CGARANT_BEM = '6404' THEN '12' WHEN CGARANT_BEM = '6405' THEN '12' WHEN CGARANT_BEM = '6406' THEN '12' WHEN CGARANT_BEM = '6407' THEN '12' WHEN CGARANT_BEM = '6408' THEN '12' WHEN CGARANT_BEM = '6501' THEN '18' WHEN CGARANT_BEM = '6502' THEN '18' WHEN CGARANT_BEM = '6503' THEN '18' WHEN CGARANT_BEM = '6504' THEN '18' -- GARABTIAS PESSOAIS WHEN CGARANT_RPT= '158' THEN '7' WHEN CGARANT_RPT= '182' THEN '7' WHEN CGARANT_RPT= '108' THEN '7' WHEN CGARANT_RPT= '107' THEN '7' WHEN CGARANT_RPT= '159' THEN '7' WHEN CGARANT_RPT= '197' THEN '7' WHEN CGARANT_RPT= '198' THEN '7' WHEN CGARANT_RPT= '106' THEN '7' WHEN CGARANT_RPT= '1B5' THEN '7' WHEN CGARANT_RPT= '164' THEN '7' WHEN CGARANT_RPT= '169' THEN '7' WHEN CGARANT_RPT= '183' THEN '7' WHEN CGARANT_RPT= '1SS' THEN '7' WHEN CGARANT_RPT= '160' THEN '7' WHEN CGARANT_RPT= '309' THEN '7' WHEN CGARANT_RPT= '321' THEN '7' WHEN CGARANT_RPT= '298' THEN '7' WHEN CGARANT_RPT= '105' THEN '7' WHEN CGARANT_RPT= '126' THEN '7' WHEN CGARANT_RPT= '125' THEN '7' WHEN CGARANT_RPT= '199' THEN '7' WHEN CGARANT_RPT= '104' THEN '7' WHEN CGARANT_RPT= '157' THEN '7' WHEN CGARANT_RPT= '1EE' THEN '7' WHEN CGARANT_RPT= '181' THEN '7' WHEN CGARANT_RPT= '120' THEN '7' WHEN CGARANT_RPT= '186' THEN '7' WHEN CGARANT_RPT= '999' THEN '7' WHEN CGARANT_RPT= '101' THEN '7' WHEN CGARANT_RPT= 'LSA' THEN '7' WHEN CGARANT_RPT= '190' THEN '7' WHEN CGARANT_RPT= '501' THEN '7' WHEN CGARANT_RPT= '001' THEN '7' WHEN CGARANT_RPT= '111' THEN '7' WHEN CGARANT_RPT= '103' THEN '7' WHEN CGARANT_RPT= '1CC' THEN '7' WHEN CGARANT_RPT= '196' THEN '7' WHEN CGARANT_RPT= '1SW' THEN '7' WHEN CGARANT_RPT= '102' THEN '7' WHEN CGARANT_RPT= '133' THEN '7' WHEN CGARANT_RPT= '345' THEN '7' ELSE '99999999999' END as TYP_PRTCTN FROM (SELECT prtctn_id, typ_prtctn_intrnl FROM cd_loan_tapes_bce.lt004_protection WHERE 1=1 AND ambito = 'PM' AND segmento = 'ESTR' AND ref_date = '${date}' AND nome_perimetro = 'Individual Corporativo' ) LT004 LEFT JOIN (SELECT ckbalbem, ckctabem, ckrefbem, cgarant_bem, cgarant_rpt, tipologia FROM cd_garantias.gt018_rateio_aval WHERE ref_date = '${date}') GT018 ON prtctn_id = CONCAT(SUBSTR(TIPOLOGIA,1,1),'_',CKBALBEM, '_', CKCTABEM, '_', CKREFBEM)
A42: PRTCTN | B42: TYP_PRTCTN | C42: Controlos | D42: "Protection type" should match the information on the Codelist | E42: 45470 | F42: 45443 | G42: OK | I42: SELECT DISTINCT CASE -- GARANTIAS IMOVEIS WHEN CGARANT_BEM = '5000' THEN '10' WHEN CGARANT_BEM = '5101' THEN '8' WHEN CGARANT_BEM = '5102' THEN '8' WHEN CGARANT_BEM = '5103' THEN '8' WHEN CGARANT_BEM = '5104' THEN '8' WHEN CGARANT_BEM = '5201' THEN '10' WHEN CGARANT_BEM = '5202' THEN '10' WHEN CGARANT_BEM = '5302' THEN '10' WHEN CGARANT_BEM = '5203' THEN '9' WHEN CGARANT_BEM = '5204' THEN '9' WHEN CGARANT_BEM = '5205' THEN '10' WHEN CGARANT_BEM = '5206' THEN '10' WHEN CGARANT_BEM = '5207' THEN '10' WHEN CGARANT_BEM = '5208' THEN '10' WHEN CGARANT_BEM = '5209' THEN '10' WHEN CGARANT_BEM = '5210' THEN '10' WHEN CGARANT_BEM = '5211' THEN '10' WHEN CGARANT_BEM = '5300' THEN '10' WHEN CGARANT_BEM = '5212' THEN '10' WHEN CGARANT_BEM = '5213' THEN '10' WHEN CGARANT_BEM = '5214' THEN '10' WHEN CGARANT_BEM = '5303' THEN '10' WHEN CGARANT_BEM = '5301' THEN '10' WHEN CGARANT_BEM = '5215' THEN '10' WHEN CGARANT_BEM = '5216' THEN '10' WHEN CGARANT_BEM = '5217' THEN '10' WHEN CGARANT_BEM = '5218' THEN '10' -- GARANTIAS FINANCEIRAS WHEN CGARANT_BEM = '6101' THEN '5' WHEN CGARANT_BEM = '6102' THEN '5' WHEN CGARANT_BEM = '6201' THEN '15' WHEN CGARANT_BEM = '6202' THEN '15' WHEN CGARANT_BEM = '6300' THEN '18' WHEN CGARANT_BEM = '6401' THEN '12' WHEN CGARANT_BEM = '6402' THEN '12' WHEN CGARANT_BEM = '6403' THEN '12' WHEN CGARANT_BEM = '6404' THEN '12' WHEN CGARANT_BEM = '6405' THEN '12' WHEN CGARANT_BEM = '6406' THEN '12' WHEN CGARANT_BEM = '6407' THEN '12' WHEN CGARANT_BEM = '6408' THEN '12' WHEN CGARANT_BEM = '6501' THEN '18' WHEN CGARANT_BEM = '6502' THEN '18' WHEN CGARANT_BEM = '6503' THEN '18' WHEN CGARANT_BEM = '6504' THEN '18' -- GARABTIAS PESSOAIS WHEN CGARANT_RPT= '158' THEN '7' WHEN CGARANT_RPT= '182' THEN '7' WHEN CGARANT_RPT= '108' THEN '7' WHEN CGARANT_RPT= '107' THEN '7' WHEN CGARANT_RPT= '159' THEN '7' WHEN CGARANT_RPT= '197' THEN '7' WHEN CGARANT_RPT= '198' THEN '7' WHEN CGARANT_RPT= '106' THEN '7' WHEN CGARANT_RPT= '1B5' THEN '7' WHEN CGARANT_RPT= '164' THEN '7' WHEN CGARANT_RPT= '169' THEN '7' WHEN CGARANT_RPT= '183' THEN '7' WHEN CGARANT_RPT= '1SS' THEN '7' WHEN CGARANT_RPT= '160' THEN '7' WHEN CGARANT_RPT= '309' THEN '7' WHEN CGARANT_RPT= '321' THEN '7' WHEN CGARANT_RPT= '298' THEN '7' WHEN CGARANT_RPT= '105' THEN '7' WHEN CGARANT_RPT= '126' THEN '7' WHEN CGARANT_RPT= '125' THEN '7' WHEN CGARANT_RPT= '199' THEN '7' WHEN CGARANT_RPT= '104' THEN '7' WHEN CGARANT_RPT= '157' THEN '7' WHEN CGARANT_RPT= '1EE' THEN '7' WHEN CGARANT_RPT= '181' THEN '7' WHEN CGARANT_RPT= '120' THEN '7' WHEN CGARANT_RPT= '186' THEN '7' WHEN CGARANT_RPT= '999' THEN '7' WHEN CGARANT_RPT= '101' THEN '7' WHEN CGARANT_RPT= 'LSA' THEN '7' WHEN CGARANT_RPT= '190' THEN '7' WHEN CGARANT_RPT= '501' THEN '7' WHEN CGARANT_RPT= '001' THEN '7' WHEN CGARANT_RPT= '111' THEN '7' WHEN CGARANT_RPT= '103' THEN '7' WHEN CGARANT_RPT= '1CC' THEN '7' WHEN CGARANT_RPT= '196' THEN '7' WHEN CGARANT_RPT= '1SW' THEN '7' WHEN CGARANT_RPT= '102' THEN '7' WHEN CGARANT_RPT= '133' THEN '7' WHEN CGARANT_RPT= '345' THEN '7' ELSE '99999999999' END as TYP_PRTCTN FROM (SELECT prtctn_id, typ_prtctn_intrnl FROM cd_loan_tapes_bce.lt004_protection WHERE 1=1 AND ambito = 'PM' AND segmento = 'ESTR' AND ref_date = '${date}' AND nome_perimetro = 'Individual Corporativo' ) LT004 LEFT JOIN (SELECT ckbalbem, ckctabem, ckrefbem, cgarant_bem, cgarant_rpt, tipologia FROM cd_garantias.gt018_rateio_aval WHERE ref_date = '${date}') GT018 ON prtctn_id = CONCAT(SUBSTR(TIPOLOGIA,1,1),'_',CKBALBEM, '_', CKCTABEM, '_', CKREFBEM)
A43: PRTCTN | B43: TYP_PRTCTN | C43: Controlos | D43: If "Type of protection received, irrespective of its eligibility for credit risk mitigation according to bank-internal classification" is informed other than default values, then "Protection type" has to be informed other than default values | E43: 45470 | F43: 45443 | G43: OK | I43: SELECT prtctn_id, typ_prtctn_intrnl, TYP_PRTCTN FROM (SELECT *, CASE -- GARANTIAS IMOVEIS WHEN CGARANT_BEM = '5000' THEN '10' WHEN CGARANT_BEM = '5101' THEN '8' WHEN CGARANT_BEM = '5102' THEN '8' WHEN CGARANT_BEM = '5103' THEN '8' WHEN CGARANT_BEM = '5104' THEN '8' WHEN CGARANT_BEM = '5201' THEN '10' WHEN CGARANT_BEM = '5202' THEN '10' WHEN CGARANT_BEM = '5302' THEN '10' WHEN CGARANT_BEM = '5203' THEN '9' WHEN CGARANT_BEM = '5204' THEN '9' WHEN CGARANT_BEM = '5205' THEN '10' WHEN CGARANT_BEM = '5206' THEN '10' WHEN CGARANT_BEM = '5207' THEN '10' WHEN CGARANT_BEM = '5208' THEN '10' WHEN CGARANT_BEM = '5209' THEN '10' WHEN CGARANT_BEM = '5210' THEN '10' WHEN CGARANT_BEM = '5211' THEN '10' WHEN CGARANT_BEM = '5300' THEN '10' WHEN CGARANT_BEM = '5212' THEN '10' WHEN CGARANT_BEM = '5213' THEN '10' WHEN CGARANT_BEM = '5214' THEN '10' WHEN CGARANT_BEM = '5303' THEN '10' WHEN CGARANT_BEM = '5301' THEN '10' WHEN CGARANT_BEM = '5215' THEN '10' WHEN CGARANT_BEM = '5216' THEN '10' WHEN CGARANT_BEM = '5217' THEN '10' WHEN CGARANT_BEM = '5218' THEN '10' -- GARANTIAS FINANCEIRAS WHEN CGARANT_BEM = '6101' THEN '5' WHEN CGARANT_BEM = '6102' THEN '5' WHEN CGARANT_BEM = '6201' THEN '15' WHEN CGARANT_BEM = '6202' THEN '15' WHEN CGARANT_BEM = '6300' THEN '18' WHEN CGARANT_BEM = '6401' THEN '12' WHEN CGARANT_BEM = '6402' THEN '12' WHEN CGARANT_BEM = '6403' THEN '12' WHEN CGARANT_BEM = '6404' THEN '12' WHEN CGARANT_BEM = '6405' THEN '12' WHEN CGARANT_BEM = '6406' THEN '12' WHEN CGARANT_BEM = '6407' THEN '12' WHEN CGARANT_BEM = '6408' THEN '12' WHEN CGARANT_BEM = '6501' THEN '18' WHEN CGARANT_BEM = '6502' THEN '18' WHEN CGARANT_BEM = '6503' THEN '18' WHEN CGARANT_BEM = '6504' THEN '18' -- GARABTIAS PESSOAIS WHEN CGARANT_RPT= '158' THEN '7' WHEN CGARANT_RPT= '182' THEN '7' WHEN CGARANT_RPT= '108' THEN '7' WHEN CGARANT_RPT= '107' THEN '7' WHEN CGARANT_RPT= '159' THEN '7' WHEN CGARANT_RPT= '197' THEN '7' WHEN CGARANT_RPT= '198' THEN '7' WHEN CGARANT_RPT= '106' THEN '7' WHEN CGARANT_RPT= '1B5' THEN '7' WHEN CGARANT_RPT= '164' THEN '7' WHEN CGARANT_RPT= '169' THEN '7' WHEN CGARANT_RPT= '183' THEN '7' WHEN CGARANT_RPT= '1SS' THEN '7' WHEN CGARANT_RPT= '160' THEN '7' WHEN CGARANT_RPT= '309' THEN '7' WHEN CGARANT_RPT= '321' THEN '7' WHEN CGARANT_RPT= '298' THEN '7' WHEN CGARANT_RPT= '105' THEN '7' WHEN CGARANT_RPT= '126' THEN '7' WHEN CGARANT_RPT= '125' THEN '7' WHEN CGARANT_RPT= '199' THEN '7' WHEN CGARANT_RPT= '104' THEN '7' WHEN CGARANT_RPT= '157' THEN '7' WHEN CGARANT_RPT= '1EE' THEN '7' WHEN CGARANT_RPT= '181' THEN '7' WHEN CGARANT_RPT= '120' THEN '7' WHEN CGARANT_RPT= '186' THEN '7' WHEN CGARANT_RPT= '999' THEN '7' WHEN CGARANT_RPT= '101' THEN '7' WHEN CGARANT_RPT= 'LSA' THEN '7' WHEN CGARANT_RPT= '190' THEN '7' WHEN CGARANT_RPT= '501' THEN '7' WHEN CGARANT_RPT= '001' THEN '7' WHEN CGARANT_RPT= '111' THEN '7' WHEN CGARANT_RPT= '103' THEN '7' WHEN CGARANT_RPT= '1CC' THEN '7' WHEN CGARANT_RPT= '196' THEN '7' WHEN CGARANT_RPT= '1SW' THEN '7' WHEN CGARANT_RPT= '102' THEN '7' WHEN CGARANT_RPT= '133' THEN '7' WHEN CGARANT_RPT= '345' THEN '7' ELSE '99999999999' END as TYP_PRTCTN FROM (SELECT prtctn_id, typ_prtctn_intrnl FROM cd_loan_tapes_bce.lt004_protection WHERE 1=1 AND ambito = 'PM' AND segmento = 'ESTR' AND ref_date = '${date}' AND nome_perimetro = 'Individual Corporativo' ) LT004 LEFT JOIN (SELECT ckbalbem, ckctabem, ckrefbem, cgarant_bem, cgarant_rpt, tipologia FROM cd_garantias.gt018_rateio_aval WHERE ref_date = '${date}') GT018 ON prtctn_id = CONCAT(SUBSTR(TIPOLOGIA,1,1),'_',CKBALBEM, '_', CKCTABEM, '_', CKREFBEM) ) A WHERE 1=1 AND typ_prtctn_intrnl <> 'N/A' AND TYP_PRTCTN = '11111111111'
A44: PRTCTN | B44: TYP_PRTCTN | C44: Controlos | D44: If "Type of protection received, irrespective of its eligibility for credit risk mitigation according to bank-internal classification" is populated with 'Not Applicable' values then "Protection type" has to be informed with default values | E44: 45470 | F44: 45443 | G44: OK | H44: Não exitem casos em que TYP_PRTCTN_INTRNL = N/A | I44: SELECT prtctn_id, typ_prtctn_intrnl, TYP_PRTCTN FROM (SELECT *, CASE -- GARANTIAS IMOVEIS WHEN CGARANT_BEM = '5000' THEN '10' WHEN CGARANT_BEM = '5101' THEN '8' WHEN CGARANT_BEM = '5102' THEN '8' WHEN CGARANT_BEM = '5103' THEN '8' WHEN CGARANT_BEM = '5104' THEN '8' WHEN CGARANT_BEM = '5201' THEN '10' WHEN CGARANT_BEM = '5202' THEN '10' WHEN CGARANT_BEM = '5302' THEN '10' WHEN CGARANT_BEM = '5203' THEN '9' WHEN CGARANT_BEM = '5204' THEN '9' WHEN CGARANT_BEM = '5205' THEN '10' WHEN CGARANT_BEM = '5206' THEN '10' WHEN CGARANT_BEM = '5207' THEN '10' WHEN CGARANT_BEM = '5208' THEN '10' WHEN CGARANT_BEM = '5209' THEN '10' WHEN CGARANT_BEM = '5210' THEN '10' WHEN CGARANT_BEM = '5211' THEN '10' WHEN CGARANT_BEM = '5300' THEN '10' WHEN CGARANT_BEM = '5212' THEN '10' WHEN CGARANT_BEM = '5213' THEN '10' WHEN CGARANT_BEM = '5214' THEN '10' WHEN CGARANT_BEM = '5303' THEN '10' WHEN CGARANT_BEM = '5301' THEN '10' WHEN CGARANT_BEM = '5215' THEN '10' WHEN CGARANT_BEM = '5216' THEN '10' WHEN CGARANT_BEM = '5217' THEN '10' WHEN CGARANT_BEM = '5218' THEN '10' -- GARANTIAS FINANCEIRAS WHEN CGARANT_BEM = '6101' THEN '5' WHEN CGARANT_BEM = '6102' THEN '5' WHEN CGARANT_BEM = '6201' THEN '15' WHEN CGARANT_BEM = '6202' THEN '15' WHEN CGARANT_BEM = '6300' THEN '18' WHEN CGARANT_BEM = '6401' THEN '12' WHEN CGARANT_BEM = '6402' THEN '12' WHEN CGARANT_BEM = '6403' THEN '12' WHEN CGARANT_BEM = '6404' THEN '12' WHEN CGARANT_BEM = '6405' THEN '12' WHEN CGARANT_BEM = '6406' THEN '12' WHEN CGARANT_BEM = '6407' THEN '12' WHEN CGARANT_BEM = '6408' THEN '12' WHEN CGARANT_BEM = '6501' THEN '18' WHEN CGARANT_BEM = '6502' THEN '18' WHEN CGARANT_BEM = '6503' THEN '18' WHEN CGARANT_BEM = '6504' THEN '18' -- GARABTIAS PESSOAIS WHEN CGARANT_RPT= '158' THEN '7' WHEN CGARANT_RPT= '182' THEN '7' WHEN CGARANT_RPT= '108' THEN '7' WHEN CGARANT_RPT= '107' THEN '7' WHEN CGARANT_RPT= '159' THEN '7' WHEN CGARANT_RPT= '197' THEN '7' WHEN CGARANT_RPT= '198' THEN '7' WHEN CGARANT_RPT= '106' THEN '7' WHEN CGARANT_RPT= '1B5' THEN '7' WHEN CGARANT_RPT= '164' THEN '7' WHEN CGARANT_RPT= '169' THEN '7' WHEN CGARANT_RPT= '183' THEN '7' WHEN CGARANT_RPT= '1SS' THEN '7' WHEN CGARANT_RPT= '160' THEN '7' WHEN CGARANT_RPT= '309' THEN '7' WHEN CGARANT_RPT= '321' THEN '7' WHEN CGARANT_RPT= '298' THEN '7' WHEN CGARANT_RPT= '105' THEN '7' WHEN CGARANT_RPT= '126' THEN '7' WHEN CGARANT_RPT= '125' THEN '7' WHEN CGARANT_RPT= '199' THEN '7' WHEN CGARANT_RPT= '104' THEN '7' WHEN CGARANT_RPT= '157' THEN '7' WHEN CGARANT_RPT= '1EE' THEN '7' WHEN CGARANT_RPT= '181' THEN '7' WHEN CGARANT_RPT= '120' THEN '7' WHEN CGARANT_RPT= '186' THEN '7' WHEN CGARANT_RPT= '999' THEN '7' WHEN CGARANT_RPT= '101' THEN '7' WHEN CGARANT_RPT= 'LSA' THEN '7' WHEN CGARANT_RPT= '190' THEN '7' WHEN CGARANT_RPT= '501' THEN '7' WHEN CGARANT_RPT= '001' THEN '7' WHEN CGARANT_RPT= '111' THEN '7' WHEN CGARANT_RPT= '103' THEN '7' WHEN CGARANT_RPT= '1CC' THEN '7' WHEN CGARANT_RPT= '196' THEN '7' WHEN CGARANT_RPT= '1SW' THEN '7' WHEN CGARANT_RPT= '102' THEN '7' WHEN CGARANT_RPT= '133' THEN '7' WHEN CGARANT_RPT= '345' THEN '7' ELSE '99999999999' END as TYP_PRTCTN FROM (SELECT prtctn_id, typ_prtctn_intrnl FROM cd_loan_tapes_bce.lt004_protection WHERE 1=1 AND ambito = 'PM' AND segmento = 'ESTR' AND ref_date = '${date}' AND nome_perimetro = 'Individual Corporativo' ) LT004 LEFT JOIN (SELECT ckbalbem, ckctabem, ckrefbem, cgarant_bem, cgarant_rpt, tipologia FROM cd_garantias.gt018_rateio_aval WHERE ref_date = '${date}') GT018 ON prtctn_id = CONCAT(SUBSTR(TIPOLOGIA,1,1),'_',CKBALBEM, '_', CKCTABEM, '_', CKREFBEM) ) A WHERE 1=1 AND typ_prtctn_intrnl = 'N/A' AND TYP_PRTCTN <> '11111111111'
A45: PRTCTN | B45: TYP_PRTCTN | C45: Controlos | D45: If "Type of protection value" is set as '1 - Fair value' then "Protection type" has to be set as '3 - Other physical collaterals', '7 - Other protection', '13 - Gold' or '18 - Equity and investment funds shares' | E45: 45470 | F45: 45443 | G45: NOK | H45: 2291 Casos | I45: SELECT count(*) FROM (SELECT *, CASE -- GARANTIAS IMOVEIS WHEN CGARANT_BEM = '5000' THEN '10' WHEN CGARANT_BEM = '5101' THEN '8' WHEN CGARANT_BEM = '5102' THEN '8' WHEN CGARANT_BEM = '5103' THEN '8' WHEN CGARANT_BEM = '5104' THEN '8' WHEN CGARANT_BEM = '5201' THEN '10' WHEN CGARANT_BEM = '5202' THEN '10' WHEN CGARANT_BEM = '5302' THEN '10' WHEN CGARANT_BEM = '5203' THEN '9' WHEN CGARANT_BEM = '5204' THEN '9' WHEN CGARANT_BEM = '5205' THEN '10' WHEN CGARANT_BEM = '5206' THEN '10' WHEN CGARANT_BEM = '5207' THEN '10' WHEN CGARANT_BEM = '5208' THEN '10' WHEN CGARANT_BEM = '5209' THEN '10' WHEN CGARANT_BEM = '5210' THEN '10' WHEN CGARANT_BEM = '5211' THEN '10' WHEN CGARANT_BEM = '5300' THEN '10' WHEN CGARANT_BEM = '5212' THEN '10' WHEN CGARANT_BEM = '5213' THEN '10' WHEN CGARANT_BEM = '5214' THEN '10' WHEN CGARANT_BEM = '5303' THEN '10' WHEN CGARANT_BEM = '5301' THEN '10' WHEN CGARANT_BEM = '5215' THEN '10' WHEN CGARANT_BEM = '5216' THEN '10' WHEN CGARANT_BEM = '5217' THEN '10' WHEN CGARANT_BEM = '5218' THEN '10' -- GARANTIAS FINANCEIRAS WHEN CGARANT_BEM = '6101' THEN '5' WHEN CGARANT_BEM = '6102' THEN '5' WHEN CGARANT_BEM = '6201' THEN '15' WHEN CGARANT_BEM = '6202' THEN '15' WHEN CGARANT_BEM = '6300' THEN '18' WHEN CGARANT_BEM = '6401' THEN '12' WHEN CGARANT_BEM = '6402' THEN '12' WHEN CGARANT_BEM = '6403' THEN '12' WHEN CGARANT_BEM = '6404' THEN '12' WHEN CGARANT_BEM = '6405' THEN '12' WHEN CGARANT_BEM = '6406' THEN '12' WHEN CGARANT_BEM = '6407' THEN '12' WHEN CGARANT_BEM = '6408' THEN '12' WHEN CGARANT_BEM = '6501' THEN '18' WHEN CGARANT_BEM = '6502' THEN '18' WHEN CGARANT_BEM = '6503' THEN '18' WHEN CGARANT_BEM = '6504' THEN '18' -- GARABTIAS PESSOAIS WHEN CGARANT_RPT= '158' THEN '7' WHEN CGARANT_RPT= '182' THEN '7' WHEN CGARANT_RPT= '108' THEN '7' WHEN CGARANT_RPT= '107' THEN '7' WHEN CGARANT_RPT= '159' THEN '7' WHEN CGARANT_RPT= '197' THEN '7' WHEN CGARANT_RPT= '198' THEN '7' WHEN CGARANT_RPT= '106' THEN '7' WHEN CGARANT_RPT= '1B5' THEN '7' WHEN CGARANT_RPT= '164' THEN '7' WHEN CGARANT_RPT= '169' THEN '7' WHEN CGARANT_RPT= '183' THEN '7' WHEN CGARANT_RPT= '1SS' THEN '7' WHEN CGARANT_RPT= '160' THEN '7' WHEN CGARANT_RPT= '309' THEN '7' WHEN CGARANT_RPT= '321' THEN '7' WHEN CGARANT_RPT= '298' THEN '7' WHEN CGARANT_RPT= '105' THEN '7' WHEN CGARANT_RPT= '126' THEN '7' WHEN CGARANT_RPT= '125' THEN '7' WHEN CGARANT_RPT= '199' THEN '7' WHEN CGARANT_RPT= '104' THEN '7' WHEN CGARANT_RPT= '157' THEN '7' WHEN CGARANT_RPT= '1EE' THEN '7' WHEN CGARANT_RPT= '181' THEN '7' WHEN CGARANT_RPT= '120' THEN '7' WHEN CGARANT_RPT= '186' THEN '7' WHEN CGARANT_RPT= '999' THEN '7' WHEN CGARANT_RPT= '101' THEN '7' WHEN CGARANT_RPT= 'LSA' THEN '7' WHEN CGARANT_RPT= '190' THEN '7' WHEN CGARANT_RPT= '501' THEN '7' WHEN CGARANT_RPT= '001' THEN '7' WHEN CGARANT_RPT= '111' THEN '7' WHEN CGARANT_RPT= '103' THEN '7' WHEN CGARANT_RPT= '1CC' THEN '7' WHEN CGARANT_RPT= '196' THEN '7' WHEN CGARANT_RPT= '1SW' THEN '7' WHEN CGARANT_RPT= '102' THEN '7' WHEN CGARANT_RPT= '133' THEN '7' WHEN CGARANT_RPT= '345' THEN '7' ELSE '99999999999' END as TYP_PRTCTN FROM (SELECT prtctn_id, typ_prtctn_intrnl, typ_prtctn_vl FROM cd_loan_tapes_bce.lt004_protection WHERE 1=1 AND ambito = 'PM' AND segmento = 'ESTR' AND ref_date = '${date}' AND nome_perimetro = 'Individual Corporativo' ) LT004 LEFT JOIN (SELECT ckbalbem, ckctabem, ckrefbem, cgarant_bem, cgarant_rpt, tipologia FROM cd_garantias.gt018_rateio_aval WHERE ref_date = '${date}') GT018 ON prtctn_id = CONCAT(SUBSTR(TIPOLOGIA,1,1),'_',CKBALBEM, '_', CKCTABEM, '_', CKREFBEM) ) A WHERE 1=1 AND typ_prtctn_vl = '1' AND TYP_PRTCTN not in ('3', '7', '13', '18')
A46: PRTCTN | B46: TYP_PRTCTN | C46: Controlos | D46: Identificar casuistica da incidência | E46: 45470 | F46: 45443 | G46: OK | H46: 2262 garantias financeiras que não são derivados de crédito, 28 securities, 1 MISS | I46: SELECT count(*), typ_prtctn_vl, TYP_PRTCTN FROM (SELECT *, CASE -- GARANTIAS IMOVEIS WHEN CGARANT_BEM = '5000' THEN '10' WHEN CGARANT_BEM = '5101' THEN '8' WHEN CGARANT_BEM = '5102' THEN '8' WHEN CGARANT_BEM = '5103' THEN '8' WHEN CGARANT_BEM = '5104' THEN '8' WHEN CGARANT_BEM = '5201' THEN '10' WHEN CGARANT_BEM = '5202' THEN '10' WHEN CGARANT_BEM = '5302' THEN '10' WHEN CGARANT_BEM = '5203' THEN '9' WHEN CGARANT_BEM = '5204' THEN '9' WHEN CGARANT_BEM = '5205' THEN '10' WHEN CGARANT_BEM = '5206' THEN '10' WHEN CGARANT_BEM = '5207' THEN '10' WHEN CGARANT_BEM = '5208' THEN '10' WHEN CGARANT_BEM = '5209' THEN '10' WHEN CGARANT_BEM = '5210' THEN '10' WHEN CGARANT_BEM = '5211' THEN '10' WHEN CGARANT_BEM = '5300' THEN '10' WHEN CGARANT_BEM = '5212' THEN '10' WHEN CGARANT_BEM = '5213' THEN '10' WHEN CGARANT_BEM = '5214' THEN '10' WHEN CGARANT_BEM = '5303' THEN '10' WHEN CGARANT_BEM = '5301' THEN '10' WHEN CGARANT_BEM = '5215' THEN '10' WHEN CGARANT_BEM = '5216' THEN '10' WHEN CGARANT_BEM = '5217' THEN '10' WHEN CGARANT_BEM = '5218' THEN '10' -- GARANTIAS FINANCEIRAS WHEN CGARANT_BEM = '6101' THEN '5' WHEN CGARANT_BEM = '6102' THEN '5' WHEN CGARANT_BEM = '6201' THEN '15' WHEN CGARANT_BEM = '6202' THEN '15' WHEN CGARANT_BEM = '6300' THEN '18' WHEN CGARANT_BEM = '6401' THEN '12' WHEN CGARANT_BEM = '6402' THEN '12' WHEN CGARANT_BEM = '6403' THEN '12' WHEN CGARANT_BEM = '6404' THEN '12' WHEN CGARANT_BEM = '6405' THEN '12' WHEN CGARANT_BEM = '6406' THEN '12' WHEN CGARANT_BEM = '6407' THEN '12' WHEN CGARANT_BEM = '6408' THEN '12' WHEN CGARANT_BEM = '6501' THEN '18' WHEN CGARANT_BEM = '6502' THEN '18' WHEN CGARANT_BEM = '6503' THEN '18' WHEN CGARANT_BEM = '6504' THEN '18' -- GARABTIAS PESSOAIS WHEN CGARANT_RPT= '158' THEN '7' WHEN CGARANT_RPT= '182' THEN '7' WHEN CGARANT_RPT= '108' THEN '7' WHEN CGARANT_RPT= '107' THEN '7' WHEN CGARANT_RPT= '159' THEN '7' WHEN CGARANT_RPT= '197' THEN '7' WHEN CGARANT_RPT= '198' THEN '7' WHEN CGARANT_RPT= '106' THEN '7' WHEN CGARANT_RPT= '1B5' THEN '7' WHEN CGARANT_RPT= '164' THEN '7' WHEN CGARANT_RPT= '169' THEN '7' WHEN CGARANT_RPT= '183' THEN '7' WHEN CGARANT_RPT= '1SS' THEN '7' WHEN CGARANT_RPT= '160' THEN '7' WHEN CGARANT_RPT= '309' THEN '7' WHEN CGARANT_RPT= '321' THEN '7' WHEN CGARANT_RPT= '298' THEN '7' WHEN CGARANT_RPT= '105' THEN '7' WHEN CGARANT_RPT= '126' THEN '7' WHEN CGARANT_RPT= '125' THEN '7' WHEN CGARANT_RPT= '199' THEN '7' WHEN CGARANT_RPT= '104' THEN '7' WHEN CGARANT_RPT= '157' THEN '7' WHEN CGARANT_RPT= '1EE' THEN '7' WHEN CGARANT_RPT= '181' THEN '7' WHEN CGARANT_RPT= '120' THEN '7' WHEN CGARANT_RPT= '186' THEN '7' WHEN CGARANT_RPT= '999' THEN '7' WHEN CGARANT_RPT= '101' THEN '7' WHEN CGARANT_RPT= 'LSA' THEN '7' WHEN CGARANT_RPT= '190' THEN '7' WHEN CGARANT_RPT= '501' THEN '7' WHEN CGARANT_RPT= '001' THEN '7' WHEN CGARANT_RPT= '111' THEN '7' WHEN CGARANT_RPT= '103' THEN '7' WHEN CGARANT_RPT= '1CC' THEN '7' WHEN CGARANT_RPT= '196' THEN '7' WHEN CGARANT_RPT= '1SW' THEN '7' WHEN CGARANT_RPT= '102' THEN '7' WHEN CGARANT_RPT= '133' THEN '7' WHEN CGARANT_RPT= '345' THEN '7' ELSE '99999999999' END as TYP_PRTCTN FROM (SELECT prtctn_id, typ_prtctn_intrnl, typ_prtctn_vl FROM cd_loan_tapes_bce.lt004_protection WHERE 1=1 AND ambito = 'PM' AND segmento = 'ESTR' AND ref_date = '${date}' AND nome_perimetro = 'Individual Corporativo' ) LT004 LEFT JOIN (SELECT ckbalbem, ckctabem, ckrefbem, cgarant_bem, cgarant_rpt, tipologia FROM cd_garantias.gt018_rateio_aval WHERE ref_date = '${date}') GT018 ON prtctn_id = CONCAT(SUBSTR(TIPOLOGIA,1,1),'_',CKBALBEM, '_', CKCTABEM, '_', CKREFBEM) ) A WHERE 1=1 AND typ_prtctn_vl = '1' AND TYP_PRTCTN not in ('3', '7', '13', '18') group by 2,3
A47: INSTRMNT | B47: SICR_ASSSSMNT_MTHD | C47: Controlos | D47: Validar se campo está de acordo com o especificado | E47: 45468 | F47: 45443 | G47: OK | I47: SELECT count(*), sicr_assssmnt_mthd, imprmnt_stts FROM cd_loan_tapes_bce.lt002_instrument WHERE ref_date='2024-05-31' AND nome_perimetro='Individual Corporativo' AND segmento='ESTR' AND ambito='PM' GROUP BY 2, 3
A48: PRTCTN | B48: TYP_PRTCTN | C48: Controlos | D48: If "Type of protection value" is set as '2 - Long-term sustainable value' or '3 - Market value' then "Protection type" has to be set as '8 - Residential real estate collateral', '9 - Offices and commercial premises' or '10 - Commercial real estate collateral' | E48: 45477 | F48: 45443 | G48: OK | I48: SELECT * FROM (SELECT *, CASE -- GARANTIAS IMOVEIS WHEN CGARANT_BEM = '5000' THEN '10' WHEN CGARANT_BEM = '5101' THEN '8' WHEN CGARANT_BEM = '5102' THEN '8' WHEN CGARANT_BEM = '5103' THEN '8' WHEN CGARANT_BEM = '5104' THEN '8' WHEN CGARANT_BEM = '5201' THEN '10' WHEN CGARANT_BEM = '5202' THEN '10' WHEN CGARANT_BEM = '5302' THEN '10' WHEN CGARANT_BEM = '5203' THEN '9' WHEN CGARANT_BEM = '5204' THEN '9' WHEN CGARANT_BEM = '5205' THEN '10' WHEN CGARANT_BEM = '5206' THEN '10' WHEN CGARANT_BEM = '5207' THEN '10' WHEN CGARANT_BEM = '5208' THEN '10' WHEN CGARANT_BEM = '5209' THEN '10' WHEN CGARANT_BEM = '5210' THEN '10' WHEN CGARANT_BEM = '5211' THEN '10' WHEN CGARANT_BEM = '5300' THEN '10' WHEN CGARANT_BEM = '5212' THEN '10' WHEN CGARANT_BEM = '5213' THEN '10' WHEN CGARANT_BEM = '5214' THEN '10' WHEN CGARANT_BEM = '5303' THEN '10' WHEN CGARANT_BEM = '5301' THEN '10' WHEN CGARANT_BEM = '5215' THEN '10' WHEN CGARANT_BEM = '5216' THEN '10' WHEN CGARANT_BEM = '5217' THEN '10' WHEN CGARANT_BEM = '5218' THEN '10' -- GARANTIAS FINANCEIRAS WHEN CGARANT_BEM = '6101' THEN '5' WHEN CGARANT_BEM = '6102' THEN '5' WHEN CGARANT_BEM = '6201' THEN '15' WHEN CGARANT_BEM = '6202' THEN '15' WHEN CGARANT_BEM = '6300' THEN '18' WHEN CGARANT_BEM = '6401' THEN '12' WHEN CGARANT_BEM = '6402' THEN '12' WHEN CGARANT_BEM = '6403' THEN '12' WHEN CGARANT_BEM = '6404' THEN '12' WHEN CGARANT_BEM = '6405' THEN '12' WHEN CGARANT_BEM = '6406' THEN '12' WHEN CGARANT_BEM = '6407' THEN '12' WHEN CGARANT_BEM = '6408' THEN '12' WHEN CGARANT_BEM = '6501' THEN '18' WHEN CGARANT_BEM = '6502' THEN '18' WHEN CGARANT_BEM = '6503' THEN '18' WHEN CGARANT_BEM = '6504' THEN '18' -- GARABTIAS PESSOAIS WHEN CGARANT_RPT= '158' THEN '7' WHEN CGARANT_RPT= '182' THEN '7' WHEN CGARANT_RPT= '108' THEN '7' WHEN CGARANT_RPT= '107' THEN '7' WHEN CGARANT_RPT= '159' THEN '7' WHEN CGARANT_RPT= '197' THEN '7' WHEN CGARANT_RPT= '198' THEN '7' WHEN CGARANT_RPT= '106' THEN '7' WHEN CGARANT_RPT= '1B5' THEN '7' WHEN CGARANT_RPT= '164' THEN '7' WHEN CGARANT_RPT= '169' THEN '7' WHEN CGARANT_RPT= '183' THEN '7' WHEN CGARANT_RPT= '1SS' THEN '7' WHEN CGARANT_RPT= '160' THEN '7' WHEN CGARANT_RPT= '309' THEN '7' WHEN CGARANT_RPT= '321' THEN '7' WHEN CGARANT_RPT= '298' THEN '7' WHEN CGARANT_RPT= '105' THEN '7' WHEN CGARANT_RPT= '126' THEN '7' WHEN CGARANT_RPT= '125' THEN '7' WHEN CGARANT_RPT= '199' THEN '7' WHEN CGARANT_RPT= '104' THEN '7' WHEN CGARANT_RPT= '157' THEN '7' WHEN CGARANT_RPT= '1EE' THEN '7' WHEN CGARANT_RPT= '181' THEN '7' WHEN CGARANT_RPT= '120' THEN '7' WHEN CGARANT_RPT= '186' THEN '7' WHEN CGARANT_RPT= '999' THEN '7' WHEN CGARANT_RPT= '101' THEN '7' WHEN CGARANT_RPT= 'LSA' THEN '7' WHEN CGARANT_RPT= '190' THEN '7' WHEN CGARANT_RPT= '501' THEN '7' WHEN CGARANT_RPT= '001' THEN '7' WHEN CGARANT_RPT= '111' THEN '7' WHEN CGARANT_RPT= '103' THEN '7' WHEN CGARANT_RPT= '1CC' THEN '7' WHEN CGARANT_RPT= '196' THEN '7' WHEN CGARANT_RPT= '1SW' THEN '7' WHEN CGARANT_RPT= '102' THEN '7' WHEN CGARANT_RPT= '133' THEN '7' WHEN CGARANT_RPT= '345' THEN '7' ELSE '99999999999' END as TYP_PRTCTN FROM (SELECT prtctn_id, typ_prtctn_intrnl, typ_prtctn_vl FROM cd_loan_tapes_bce.lt004_protection WHERE 1=1 AND ambito = 'PM' AND segmento = 'ESTR' AND ref_date = '${date}' AND nome_perimetro = 'Individual Corporativo' ) LT004 LEFT JOIN (SELECT ckbalbem, ckctabem, ckrefbem, cgarant_bem, cgarant_rpt, tipologia FROM cd_garantias.gt018_rateio_aval WHERE ref_date = '${date}') GT018 ON prtctn_id = CONCAT(SUBSTR(TIPOLOGIA,1,1),'_',CKBALBEM, '_', CKCTABEM, '_', CKREFBEM) ) A WHERE 1=1 AND typ_prtctn_vl IN ('2','3') AND TYP_PRTCTN NOT IN ('8','9','10')
A49: PRTCTN | B49: DT_APPRSL_PRVS | C49: Controlos | D49: "Previous appraisal date" must have a Date format (yyyy-mm-dd) | E49: 45478 | F49: 45443 | G49: OK | I49: SELECT * FROM (SELECT LT004.prtctn_id, dt_apprsl_prvs AS valor_lt, CASE WHEN prtctn_id NOT LIKE 'I%' THEN '1111-11-11' WHEN prtctn_id_GT011 IS NULL THEN '1111-11-11' -- garantia com apenas 1 avaliação completa WHEN prtctn_id_GT011 IS NOT NULL THEN davalia ELSE '0000-00-00' END AS valor_simulado FROM (SELECT prtctn_id, dt_apprsl_prvs, typ_prtctn FROM cd_loan_tapes_bce.lt004_protection WHERE ref_date='${date}' AND nome_perimetro='Individual Corporativo' AND segmento='ESTR' AND ambito='PM' )LT004 LEFT JOIN (SELECT * FROM (SELECT *, RANK() OVER (PARTITION BY prtctn_id_GT011 ORDER BY davalia DESC) AS ranking FROM (SELECT DISTINCT CONCAT('I_', CKBALBEM, '_', CKCTABEM, '_', CKREFBEM) AS prtctn_id_GT011, davalia FROM cd_garantias.gt011_avalc_imov WHERE 1=1 AND ref_date='${date}' AND ( (CTIPREAVL = 'A' AND CORAVGP = 'G39') OR CORAVGP='G26') ) GT011 )GT011 WHERE ranking = 2 )GT011 ON LT004.prtctn_id = GT011.prtctn_id_GT011 ) x WHERE 1=1 AND substring(valor_simulado,5,1) <> '-' or substring(valor_simulado,8,1) <> '-' -- AND valor_simulado = '9999-99-99' -- AND valor_simulado = '0001-01-01' -- AND length(valor_simulado) <> 10
A50: PRTCTN | B50: DT_APPRSL_PRVS | C50: Controlos | D50: "Previous appraisal date" must be later than 01 January 1970 | E50: 45478 | F50: 45443 | G50: NOK | H50: 2 casos com datas ambiguas (anos 1008 e 0201) | I50: SELECT * FROM (SELECT LT004.prtctn_id, dt_apprsl_prvs AS valor_lt, CASE WHEN prtctn_id NOT LIKE 'I%' THEN '1111-11-11' WHEN prtctn_id_GT011 IS NULL THEN '1111-11-11' -- garantia com apenas 1 avaliação completa WHEN prtctn_id_GT011 IS NOT NULL THEN davalia ELSE '0000-00-00' END AS valor_simulado FROM (SELECT prtctn_id, dt_apprsl_prvs, typ_prtctn FROM cd_loan_tapes_bce.lt004_protection WHERE ref_date='${date}' AND nome_perimetro='Individual Corporativo' AND segmento='ESTR' AND ambito='PM' )LT004 LEFT JOIN (SELECT * FROM (SELECT *, RANK() OVER (PARTITION BY prtctn_id_GT011 ORDER BY davalia DESC) AS ranking FROM (SELECT DISTINCT CONCAT('I_', CKBALBEM, '_', CKCTABEM, '_', CKREFBEM) AS prtctn_id_GT011, davalia FROM cd_garantias.gt011_avalc_imov WHERE 1=1 AND ref_date='${date}' AND ( (CTIPREAVL = 'A' AND CORAVGP = 'G39') OR CORAVGP='G26') ) GT011 )GT011 WHERE ranking = 2 )GT011 ON LT004.prtctn_id = GT011.prtctn_id_GT011 ) x WHERE 1=1 AND valor_simulado < '1970-01-01' AND valor_simulado NOT IN ('1111-11-11', '0000-00-00')
A51: PRTCTN | B51: DT_APPRSL_PRVS | C51: Controlos | D51: "Previous appraisal date" cannot be later than "Reference date" | E51: 45478 | F51: 45443 | G51: OK | I51: SELECT * FROM (SELECT LT004.prtctn_id, dt_apprsl_prvs AS valor_lt, CASE WHEN prtctn_id NOT LIKE 'I%' THEN '1111-11-11' WHEN prtctn_id_GT011 IS NULL THEN '1111-11-11' -- garantia com apenas 1 avaliação completa WHEN prtctn_id_GT011 IS NOT NULL THEN davalia ELSE '0000-00-00' END AS valor_simulado FROM (SELECT prtctn_id, dt_apprsl_prvs, typ_prtctn FROM cd_loan_tapes_bce.lt004_protection WHERE ref_date='${date}' AND nome_perimetro='Individual Corporativo' AND segmento='ESTR' AND ambito='PM' )LT004 LEFT JOIN (SELECT * FROM (SELECT *, RANK() OVER (PARTITION BY prtctn_id_GT011 ORDER BY davalia DESC) AS ranking FROM (SELECT DISTINCT CONCAT('I_', CKBALBEM, '_', CKCTABEM, '_', CKREFBEM) AS prtctn_id_GT011, davalia FROM cd_garantias.gt011_avalc_imov WHERE 1=1 AND ref_date='${date}' AND ( (CTIPREAVL = 'A' AND CORAVGP = 'G39') OR CORAVGP='G26') ) GT011 )GT011 WHERE ranking = 2 )GT011 ON LT004.prtctn_id = GT011.prtctn_id_GT011 ) x WHERE 1=1 AND valor_simulado > '2024-05-31'
A52: PRTCTN | B52: DT_APPRSL_PRVS | C52: Controlos | D52: "Previous appraisal date" cannot be earlier than "Date of original protection value" | E52: 45478 | F52: 45443 | G52: NOK | H52: Campo DT_ORGNL_PRTCN_VL com incidência | I52: SELECT * FROM (SELECT LT004.prtctn_id, DT_ORGNL_PRTCTN_VL, dt_apprsl_prvs AS valor_lt, CASE WHEN prtctn_id NOT LIKE 'I%' THEN '1111-11-11' WHEN prtctn_id_GT011 IS NULL THEN '1111-11-11' -- garantia com apenas 1 avaliação completa WHEN prtctn_id_GT011 IS NOT NULL THEN davalia ELSE '0000-00-00' END AS valor_simulado FROM (SELECT prtctn_id, dt_apprsl_prvs, typ_prtctn, DT_ORGNL_PRTCTN_VL FROM cd_loan_tapes_bce.lt004_protection WHERE ref_date='${date}' AND nome_perimetro='Individual Corporativo' AND segmento='ESTR' AND ambito='PM' )LT004 LEFT JOIN (SELECT * FROM (SELECT *, RANK() OVER (PARTITION BY prtctn_id_GT011 ORDER BY davalia DESC) AS ranking FROM (SELECT DISTINCT CONCAT('I_', CKBALBEM, '_', CKCTABEM, '_', CKREFBEM) AS prtctn_id_GT011, davalia FROM cd_garantias.gt011_avalc_imov WHERE 1=1 AND ref_date='${date}' AND ( (CTIPREAVL = 'A' AND CORAVGP = 'G39') OR CORAVGP='G26') ) GT011 )GT011 WHERE ranking = 2 )GT011 ON LT004.prtctn_id = GT011.prtctn_id_GT011 ) x WHERE 1=1 AND valor_simulado < DT_ORGNL_PRTCTN_VL ;
A53: PRTCTN | B53: DT_APPRSL_PRVS | C53: Controlos | D53: "Previous appraisal date" cannot be later than "Date of protection value | E53: 45478 | F53: 45443 | G53: OK | I53: SELECT * FROM (SELECT LT004.prtctn_id, DT_PRTCTN_VL, dt_apprsl_prvs AS valor_lt, CASE WHEN prtctn_id NOT LIKE 'I%' THEN '1111-11-11' WHEN prtctn_id_GT011 IS NULL THEN '1111-11-11' -- garantia com apenas 1 avaliação completa WHEN prtctn_id_GT011 IS NOT NULL THEN davalia ELSE '0000-00-00' END AS valor_simulado FROM (SELECT prtctn_id, dt_apprsl_prvs, typ_prtctn, DT_PRTCTN_VL FROM cd_loan_tapes_bce.lt004_protection WHERE ref_date='${date}' AND nome_perimetro='Individual Corporativo' AND segmento='ESTR' AND ambito='PM' )LT004 LEFT JOIN (SELECT * FROM (SELECT *, RANK() OVER (PARTITION BY prtctn_id_GT011 ORDER BY davalia DESC) AS ranking FROM (SELECT DISTINCT CONCAT('I_', CKBALBEM, '_', CKCTABEM, '_', CKREFBEM) AS prtctn_id_GT011, davalia FROM cd_garantias.gt011_avalc_imov WHERE 1=1 AND ref_date='${date}' AND ( (CTIPREAVL = 'A' AND CORAVGP = 'G39') OR CORAVGP='G26') ) GT011 )GT011 WHERE ranking = 2 )GT011 ON LT004.prtctn_id = GT011.prtctn_id_GT011 ) x WHERE 1=1 AND valor_simulado > DT_PRTCTN_VL AND valor_simulado NOT IN ('1111-11-11','0000-00-00')
A54: PRTCTN | B54: DT_APPRSL_PRVS | C54: Controlos | D54: If the protection is a "personal guarantee" then "Previous appraisal date" should be 'Not Applicable' (We consider "personal guarantee" when "Protection ID" matches the "Protection Provider ID" (Guarantor) or "Tax ID" (Protection level) is populated other than default value and the "Protection type" equals '7 - Other protection') | E54: 45478 | F54: 45443 | G54: OK | I54: SELECT * FROM (SELECT LT004.prtctn_id, DT_PRTCTN_VL, dt_apprsl_prvs AS valor_lt, CASE WHEN prtctn_id NOT LIKE 'I%' THEN '1111-11-11' WHEN prtctn_id_GT011 IS NULL THEN '1111-11-11' -- garantia com apenas 1 avaliação completa WHEN prtctn_id_GT011 IS NOT NULL THEN davalia ELSE '0000-00-00' END AS valor_simulado FROM (SELECT prtctn_id, dt_apprsl_prvs, typ_prtctn, DT_PRTCTN_VL FROM cd_loan_tapes_bce.lt004_protection WHERE ref_date='${date}' AND nome_perimetro='Individual Corporativo' AND segmento='ESTR' AND ambito='PM' )LT004 LEFT JOIN (SELECT * FROM (SELECT *, RANK() OVER (PARTITION BY prtctn_id_GT011 ORDER BY davalia DESC) AS ranking FROM (SELECT DISTINCT CONCAT('I_', CKBALBEM, '_', CKCTABEM, '_', CKREFBEM) AS prtctn_id_GT011, davalia FROM cd_garantias.gt011_avalc_imov WHERE 1=1 AND ref_date='${date}' AND ( (CTIPREAVL = 'A' AND CORAVGP = 'G39') OR CORAVGP='G26') ) GT011 )GT011 WHERE ranking = 2 )GT011 ON LT004.prtctn_id = GT011.prtctn_id_GT011 ) x WHERE 1=1 AND prtctn_id LIKE 'P%' AND valor_simulado <> '1111-11-11'
A55: INSTRMNT | B55: IMPRMNT_STTS | C55: Controlos | D55: "Impairment status" should match the information on the Codelist | E55: 45481 | F55: 45443 | G55: OK | I55: SELECT count(*), imprmnt_stts FROM cd_loan_tapes_bce.lt002_instrument WHERE ref_date='${date}' AND nome_perimetro='Individual Corporativo' AND segmento='ESTR' AND ambito='PM' GROUP BY 2
A56: INSTRMNT | B56: IMPRMNT_STTS | C56: Controlos | D56: "Impairment status" can only be '23 - Stage 1 (IFRS)' or '24 - Stage 2 (IFRS)' or '25 - Stage 3 (IFRS)' or default values(Since Santander Group is IFRS compliance and do not apply General Accounting Accepted Principles (GAAP) on a consolidated basis) | E56: 45481 | F56: 45443 | G56: OK | I56: SELECT count(*), imprmnt_stts FROM cd_loan_tapes_bce.lt002_instrument WHERE ref_date='${date}' AND nome_perimetro='Individual Corporativo' AND segmento='ESTR' AND ambito='PM' GROUP BY 2
A57: INSTRMNT | B57: IMPRMNT_STTS | C57: Controlos | D57: if "Days past due at reference date" is between 30 and 90 days and "Subportfolio ID" is not classified as 'VRPL - FV with changes in PL' then "Impairment status" must be '24 - Stage 2 (IFRS)' or '25 - Stage 3 (IFRS)' | E57: 45481 | F57: 45443 | G57: NOK | H57: 5 contratos com em stage 1 | I57: SELECT instrmnt_id, imprmnt_stts, dpd, subportfolio_id FROM cd_loan_tapes_bce.lt002_instrument WHERE ref_date='${date}' AND nome_perimetro='Individual Corporativo' AND segmento='ESTR' AND ambito='PM' AND subportfolio_id <> 'VRPL' AND DPD > 30 AND DPD < 90 AND imprmnt_stts NOT IN ('24', '25')
A58: INSTRMNT | B58: IMPRMNT_STTS | C58: Controlos | D58: if "Default status of the instrument" is set as '18 - Default because both unlikely to pay and more than 90/180 days past due', '19 - Default because unlikely to pay' or '20 - Default because more than 90/180 days past due' and "Subportfolio ID" is not classified as 'VRPL - FV with changes in PL' then "Impairment status" is set as "25 - Stage 3 (IFRS)" | E58: 45481 | F58: 45443 | G58: NOK | H58: 2561 casos em default marcados com stage 1 ou 2 | I58: SELECT count(*), imprmnt_stts, dflt_stts_instrmnt FROM cd_loan_tapes_bce.lt002_instrument WHERE ref_date='${date}' AND nome_perimetro='Individual Corporativo' AND segmento='ESTR' AND ambito='PM' AND subportfolio_id <> 'VRPL' AND dflt_stts_instrmnt IN ('18','19','20') AND imprmnt_stts <> '25' GROUP BY 2,3 ORDER BY 1 DESC
A59: INSTRMNT | B59: IMPRMNT_STTS | C59: Controlos | D59: if "Default status of the instrument" is set as '14 - Not in default' and "Subportfolio ID" is not classified as 'VRPL - FV with changes in PL' then "Impairment status" cannot be 25 - Stage 3 (IFRS)' | E59: 45481 | F59: 45443 | G59: NOK | H59: 4198 contratos que não estão em default e estaão marcados como stage 3. | I59: SELECT count(*), imprmnt_stts, dflt_stts_instrmnt FROM cd_loan_tapes_bce.lt002_instrument WHERE ref_date='${date}' AND nome_perimetro='Individual Corporativo' AND segmento='ESTR' AND ambito='PM' AND subportfolio_id <> 'VRPL' AND dflt_stts_instrmnt = '14' AND imprmnt_stts = '25' GROUP BY 2,3 ORDER BY 1 DESC
A60: INSTRMNT | B60: IMPRMNT_STTS | C60: Controlos | D60: if "Performing status" is '11 - Performing' and "Subportfolio ID" is not classified as 'VRPL - FV with changes in PL' then "Impairment status" cannot be '25 - Stage 3 (IFRS)' | E60: 45481 | F60: 45443 | G60: OK | I60: SELECT count(*), imprmnt_stts, prfrmng_stts FROM cd_loan_tapes_bce.lt002_instrument WHERE ref_date='${date}' AND nome_perimetro='Individual Corporativo' AND segmento='ESTR' AND ambito='PM' AND subportfolio_id <> 'VRPL' AND prfrmng_stts = '11' AND imprmnt_stts = '25' GROUP BY 2,3 ORDER BY 1 DESC
A61: PRTCTN | B61: TYP_PRTCTN | C61: Controlos | D61: If "Type of protection value" is set as '4 - Notional amount' then "Protection type" has to be set as '2 - Life insurance policies pledged', '4 - Credit derivatives', '5 - Financial guarantees other than credit derivatives', '12 - Securities', '15 - Currency and deposits', '16 - Loans', '17 - Trade receivables' or '7 - Other protection' | E61: 45482 | F61: 45443 | G61: OK | I61: SELECT * FROM (SELECT *, CASE -- GARANTIAS IMOVEIS WHEN CGARANT_BEM = '5000' THEN '10' WHEN CGARANT_BEM = '5101' THEN '8' WHEN CGARANT_BEM = '5102' THEN '8' WHEN CGARANT_BEM = '5103' THEN '8' WHEN CGARANT_BEM = '5104' THEN '8' WHEN CGARANT_BEM = '5201' THEN '10' WHEN CGARANT_BEM = '5202' THEN '10' WHEN CGARANT_BEM = '5302' THEN '10' WHEN CGARANT_BEM = '5203' THEN '9' WHEN CGARANT_BEM = '5204' THEN '9' WHEN CGARANT_BEM = '5205' THEN '10' WHEN CGARANT_BEM = '5206' THEN '10' WHEN CGARANT_BEM = '5207' THEN '10' WHEN CGARANT_BEM = '5208' THEN '10' WHEN CGARANT_BEM = '5209' THEN '10' WHEN CGARANT_BEM = '5210' THEN '10' WHEN CGARANT_BEM = '5211' THEN '10' WHEN CGARANT_BEM = '5300' THEN '10' WHEN CGARANT_BEM = '5212' THEN '10' WHEN CGARANT_BEM = '5213' THEN '10' WHEN CGARANT_BEM = '5214' THEN '10' WHEN CGARANT_BEM = '5303' THEN '10' WHEN CGARANT_BEM = '5301' THEN '10' WHEN CGARANT_BEM = '5215' THEN '10' WHEN CGARANT_BEM = '5216' THEN '10' WHEN CGARANT_BEM = '5217' THEN '10' WHEN CGARANT_BEM = '5218' THEN '10' -- GARANTIAS FINANCEIRAS WHEN CGARANT_BEM = '6101' THEN '5' WHEN CGARANT_BEM = '6102' THEN '5' WHEN CGARANT_BEM = '6201' THEN '15' WHEN CGARANT_BEM = '6202' THEN '15' WHEN CGARANT_BEM = '6300' THEN '18' WHEN CGARANT_BEM = '6401' THEN '12' WHEN CGARANT_BEM = '6402' THEN '12' WHEN CGARANT_BEM = '6403' THEN '12' WHEN CGARANT_BEM = '6404' THEN '12' WHEN CGARANT_BEM = '6405' THEN '12' WHEN CGARANT_BEM = '6406' THEN '12' WHEN CGARANT_BEM = '6407' THEN '12' WHEN CGARANT_BEM = '6408' THEN '12' WHEN CGARANT_BEM = '6501' THEN '18' WHEN CGARANT_BEM = '6502' THEN '18' WHEN CGARANT_BEM = '6503' THEN '18' WHEN CGARANT_BEM = '6504' THEN '18' -- GARABTIAS PESSOAIS WHEN CGARANT_RPT= '158' THEN '7' WHEN CGARANT_RPT= '182' THEN '7' WHEN CGARANT_RPT= '108' THEN '7' WHEN CGARANT_RPT= '107' THEN '7' WHEN CGARANT_RPT= '159' THEN '7' WHEN CGARANT_RPT= '197' THEN '7' WHEN CGARANT_RPT= '198' THEN '7' WHEN CGARANT_RPT= '106' THEN '7' WHEN CGARANT_RPT= '1B5' THEN '7' WHEN CGARANT_RPT= '164' THEN '7' WHEN CGARANT_RPT= '169' THEN '7' WHEN CGARANT_RPT= '183' THEN '7' WHEN CGARANT_RPT= '1SS' THEN '7' WHEN CGARANT_RPT= '160' THEN '7' WHEN CGARANT_RPT= '309' THEN '7' WHEN CGARANT_RPT= '321' THEN '7' WHEN CGARANT_RPT= '298' THEN '7' WHEN CGARANT_RPT= '105' THEN '7' WHEN CGARANT_RPT= '126' THEN '7' WHEN CGARANT_RPT= '125' THEN '7' WHEN CGARANT_RPT= '199' THEN '7' WHEN CGARANT_RPT= '104' THEN '7' WHEN CGARANT_RPT= '157' THEN '7' WHEN CGARANT_RPT= '1EE' THEN '7' WHEN CGARANT_RPT= '181' THEN '7' WHEN CGARANT_RPT= '120' THEN '7' WHEN CGARANT_RPT= '186' THEN '7' WHEN CGARANT_RPT= '999' THEN '7' WHEN CGARANT_RPT= '101' THEN '7' WHEN CGARANT_RPT= 'LSA' THEN '7' WHEN CGARANT_RPT= '190' THEN '7' WHEN CGARANT_RPT= '501' THEN '7' WHEN CGARANT_RPT= '001' THEN '7' WHEN CGARANT_RPT= '111' THEN '7' WHEN CGARANT_RPT= '103' THEN '7' WHEN CGARANT_RPT= '1CC' THEN '7' WHEN CGARANT_RPT= '196' THEN '7' WHEN CGARANT_RPT= '1SW' THEN '7' WHEN CGARANT_RPT= '102' THEN '7' WHEN CGARANT_RPT= '133' THEN '7' WHEN CGARANT_RPT= '345' THEN '7' ELSE '99999999999' END as TYP_PRTCTN FROM (SELECT prtctn_id, typ_prtctn_intrnl, typ_prtctn_vl FROM cd_loan_tapes_bce.lt004_protection WHERE 1=1 AND ambito = 'PM' AND segmento = 'ESTR' AND ref_date = '${date}' AND nome_perimetro = 'Individual Corporativo' ) LT004 LEFT JOIN (SELECT ckbalbem, ckctabem, ckrefbem, cgarant_bem, cgarant_rpt, tipologia FROM cd_garantias.gt018_rateio_aval WHERE ref_date = '${date}') GT018 ON prtctn_id = CONCAT(SUBSTR(TIPOLOGIA,1,1),'_',CKBALBEM, '_', CKCTABEM, '_', CKREFBEM) ) A WHERE 1=1 AND typ_prtctn_vl = '4' AND TYP_PRTCTN NOT IN ('2','4','5', '12','15','16','17','7')
A62: PRTCTN | B62: TYP_PRTCTN | C62: Controlos | D62: If "Type of protection value" is set as '5 - Types of protection values other than notional amount, market value, fair value or long-term sustainable value' then "Protection type" cannot be 'Not applicable' | E62: 45482 | F62: 45443 | G62: OK | H62: Não existem casos em que TYP_PRTCTN = 5 | I62: SELECT * FROM (SELECT *, CASE -- GARANTIAS IMOVEIS WHEN CGARANT_BEM = '5000' THEN '10' WHEN CGARANT_BEM = '5101' THEN '8' WHEN CGARANT_BEM = '5102' THEN '8' WHEN CGARANT_BEM = '5103' THEN '8' WHEN CGARANT_BEM = '5104' THEN '8' WHEN CGARANT_BEM = '5201' THEN '10' WHEN CGARANT_BEM = '5202' THEN '10' WHEN CGARANT_BEM = '5302' THEN '10' WHEN CGARANT_BEM = '5203' THEN '9' WHEN CGARANT_BEM = '5204' THEN '9' WHEN CGARANT_BEM = '5205' THEN '10' WHEN CGARANT_BEM = '5206' THEN '10' WHEN CGARANT_BEM = '5207' THEN '10' WHEN CGARANT_BEM = '5208' THEN '10' WHEN CGARANT_BEM = '5209' THEN '10' WHEN CGARANT_BEM = '5210' THEN '10' WHEN CGARANT_BEM = '5211' THEN '10' WHEN CGARANT_BEM = '5300' THEN '10' WHEN CGARANT_BEM = '5212' THEN '10' WHEN CGARANT_BEM = '5213' THEN '10' WHEN CGARANT_BEM = '5214' THEN '10' WHEN CGARANT_BEM = '5303' THEN '10' WHEN CGARANT_BEM = '5301' THEN '10' WHEN CGARANT_BEM = '5215' THEN '10' WHEN CGARANT_BEM = '5216' THEN '10' WHEN CGARANT_BEM = '5217' THEN '10' WHEN CGARANT_BEM = '5218' THEN '10' -- GARANTIAS FINANCEIRAS WHEN CGARANT_BEM = '6101' THEN '5' WHEN CGARANT_BEM = '6102' THEN '5' WHEN CGARANT_BEM = '6201' THEN '15' WHEN CGARANT_BEM = '6202' THEN '15' WHEN CGARANT_BEM = '6300' THEN '18' WHEN CGARANT_BEM = '6401' THEN '12' WHEN CGARANT_BEM = '6402' THEN '12' WHEN CGARANT_BEM = '6403' THEN '12' WHEN CGARANT_BEM = '6404' THEN '12' WHEN CGARANT_BEM = '6405' THEN '12' WHEN CGARANT_BEM = '6406' THEN '12' WHEN CGARANT_BEM = '6407' THEN '12' WHEN CGARANT_BEM = '6408' THEN '12' WHEN CGARANT_BEM = '6501' THEN '18' WHEN CGARANT_BEM = '6502' THEN '18' WHEN CGARANT_BEM = '6503' THEN '18' WHEN CGARANT_BEM = '6504' THEN '18' -- GARABTIAS PESSOAIS WHEN CGARANT_RPT= '158' THEN '7' WHEN CGARANT_RPT= '182' THEN '7' WHEN CGARANT_RPT= '108' THEN '7' WHEN CGARANT_RPT= '107' THEN '7' WHEN CGARANT_RPT= '159' THEN '7' WHEN CGARANT_RPT= '197' THEN '7' WHEN CGARANT_RPT= '198' THEN '7' WHEN CGARANT_RPT= '106' THEN '7' WHEN CGARANT_RPT= '1B5' THEN '7' WHEN CGARANT_RPT= '164' THEN '7' WHEN CGARANT_RPT= '169' THEN '7' WHEN CGARANT_RPT= '183' THEN '7' WHEN CGARANT_RPT= '1SS' THEN '7' WHEN CGARANT_RPT= '160' THEN '7' WHEN CGARANT_RPT= '309' THEN '7' WHEN CGARANT_RPT= '321' THEN '7' WHEN CGARANT_RPT= '298' THEN '7' WHEN CGARANT_RPT= '105' THEN '7' WHEN CGARANT_RPT= '126' THEN '7' WHEN CGARANT_RPT= '125' THEN '7' WHEN CGARANT_RPT= '199' THEN '7' WHEN CGARANT_RPT= '104' THEN '7' WHEN CGARANT_RPT= '157' THEN '7' WHEN CGARANT_RPT= '1EE' THEN '7' WHEN CGARANT_RPT= '181' THEN '7' WHEN CGARANT_RPT= '120' THEN '7' WHEN CGARANT_RPT= '186' THEN '7' WHEN CGARANT_RPT= '999' THEN '7' WHEN CGARANT_RPT= '101' THEN '7' WHEN CGARANT_RPT= 'LSA' THEN '7' WHEN CGARANT_RPT= '190' THEN '7' WHEN CGARANT_RPT= '501' THEN '7' WHEN CGARANT_RPT= '001' THEN '7' WHEN CGARANT_RPT= '111' THEN '7' WHEN CGARANT_RPT= '103' THEN '7' WHEN CGARANT_RPT= '1CC' THEN '7' WHEN CGARANT_RPT= '196' THEN '7' WHEN CGARANT_RPT= '1SW' THEN '7' WHEN CGARANT_RPT= '102' THEN '7' WHEN CGARANT_RPT= '133' THEN '7' WHEN CGARANT_RPT= '345' THEN '7' ELSE '99999999999' END as TYP_PRTCTN FROM (SELECT prtctn_id, typ_prtctn_intrnl, typ_prtctn_vl FROM cd_loan_tapes_bce.lt004_protection WHERE 1=1 AND ambito = 'PM' AND segmento = 'ESTR' AND ref_date = '${date}' AND nome_perimetro = 'Individual Corporativo' ) LT004 LEFT JOIN (SELECT ckbalbem, ckctabem, ckrefbem, cgarant_bem, cgarant_rpt, tipologia FROM cd_garantias.gt018_rateio_aval WHERE ref_date = '${date}') GT018 ON prtctn_id = CONCAT(SUBSTR(TIPOLOGIA,1,1),'_',CKBALBEM, '_', CKCTABEM, '_', CKREFBEM) ) A WHERE 1=1 AND typ_prtctn_vl = '5'
A63: PRTCTN | B63: TYP_PRTCTN | C63: Controlos | D63: If "Type of protection value" equals 'Not applicable', then "Protection type" should equal '7 - Other protection' | E63: 45482 | F63: 45443 | G63: OK | I63: SELECT * FROM (SELECT *, CASE -- GARANTIAS IMOVEIS WHEN CGARANT_BEM = '5000' THEN '10' WHEN CGARANT_BEM = '5101' THEN '8' WHEN CGARANT_BEM = '5102' THEN '8' WHEN CGARANT_BEM = '5103' THEN '8' WHEN CGARANT_BEM = '5104' THEN '8' WHEN CGARANT_BEM = '5201' THEN '10' WHEN CGARANT_BEM = '5202' THEN '10' WHEN CGARANT_BEM = '5302' THEN '10' WHEN CGARANT_BEM = '5203' THEN '9' WHEN CGARANT_BEM = '5204' THEN '9' WHEN CGARANT_BEM = '5205' THEN '10' WHEN CGARANT_BEM = '5206' THEN '10' WHEN CGARANT_BEM = '5207' THEN '10' WHEN CGARANT_BEM = '5208' THEN '10' WHEN CGARANT_BEM = '5209' THEN '10' WHEN CGARANT_BEM = '5210' THEN '10' WHEN CGARANT_BEM = '5211' THEN '10' WHEN CGARANT_BEM = '5300' THEN '10' WHEN CGARANT_BEM = '5212' THEN '10' WHEN CGARANT_BEM = '5213' THEN '10' WHEN CGARANT_BEM = '5214' THEN '10' WHEN CGARANT_BEM = '5303' THEN '10' WHEN CGARANT_BEM = '5301' THEN '10' WHEN CGARANT_BEM = '5215' THEN '10' WHEN CGARANT_BEM = '5216' THEN '10' WHEN CGARANT_BEM = '5217' THEN '10' WHEN CGARANT_BEM = '5218' THEN '10' -- GARANTIAS FINANCEIRAS WHEN CGARANT_BEM = '6101' THEN '5' WHEN CGARANT_BEM = '6102' THEN '5' WHEN CGARANT_BEM = '6201' THEN '15' WHEN CGARANT_BEM = '6202' THEN '15' WHEN CGARANT_BEM = '6300' THEN '18' WHEN CGARANT_BEM = '6401' THEN '12' WHEN CGARANT_BEM = '6402' THEN '12' WHEN CGARANT_BEM = '6403' THEN '12' WHEN CGARANT_BEM = '6404' THEN '12' WHEN CGARANT_BEM = '6405' THEN '12' WHEN CGARANT_BEM = '6406' THEN '12' WHEN CGARANT_BEM = '6407' THEN '12' WHEN CGARANT_BEM = '6408' THEN '12' WHEN CGARANT_BEM = '6501' THEN '18' WHEN CGARANT_BEM = '6502' THEN '18' WHEN CGARANT_BEM = '6503' THEN '18' WHEN CGARANT_BEM = '6504' THEN '18' -- GARABTIAS PESSOAIS WHEN CGARANT_RPT= '158' THEN '7' WHEN CGARANT_RPT= '182' THEN '7' WHEN CGARANT_RPT= '108' THEN '7' WHEN CGARANT_RPT= '107' THEN '7' WHEN CGARANT_RPT= '159' THEN '7' WHEN CGARANT_RPT= '197' THEN '7' WHEN CGARANT_RPT= '198' THEN '7' WHEN CGARANT_RPT= '106' THEN '7' WHEN CGARANT_RPT= '1B5' THEN '7' WHEN CGARANT_RPT= '164' THEN '7' WHEN CGARANT_RPT= '169' THEN '7' WHEN CGARANT_RPT= '183' THEN '7' WHEN CGARANT_RPT= '1SS' THEN '7' WHEN CGARANT_RPT= '160' THEN '7' WHEN CGARANT_RPT= '309' THEN '7' WHEN CGARANT_RPT= '321' THEN '7' WHEN CGARANT_RPT= '298' THEN '7' WHEN CGARANT_RPT= '105' THEN '7' WHEN CGARANT_RPT= '126' THEN '7' WHEN CGARANT_RPT= '125' THEN '7' WHEN CGARANT_RPT= '199' THEN '7' WHEN CGARANT_RPT= '104' THEN '7' WHEN CGARANT_RPT= '157' THEN '7' WHEN CGARANT_RPT= '1EE' THEN '7' WHEN CGARANT_RPT= '181' THEN '7' WHEN CGARANT_RPT= '120' THEN '7' WHEN CGARANT_RPT= '186' THEN '7' WHEN CGARANT_RPT= '999' THEN '7' WHEN CGARANT_RPT= '101' THEN '7' WHEN CGARANT_RPT= 'LSA' THEN '7' WHEN CGARANT_RPT= '190' THEN '7' WHEN CGARANT_RPT= '501' THEN '7' WHEN CGARANT_RPT= '001' THEN '7' WHEN CGARANT_RPT= '111' THEN '7' WHEN CGARANT_RPT= '103' THEN '7' WHEN CGARANT_RPT= '1CC' THEN '7' WHEN CGARANT_RPT= '196' THEN '7' WHEN CGARANT_RPT= '1SW' THEN '7' WHEN CGARANT_RPT= '102' THEN '7' WHEN CGARANT_RPT= '133' THEN '7' WHEN CGARANT_RPT= '345' THEN '7' ELSE '99999999999' END as TYP_PRTCTN FROM (SELECT prtctn_id, typ_prtctn_intrnl, typ_prtctn_vl FROM cd_loan_tapes_bce.lt004_protection WHERE 1=1 AND ambito = 'PM' AND segmento = 'ESTR' AND ref_date = '${date}' AND nome_perimetro = 'Individual Corporativo' ) LT004 LEFT JOIN (SELECT ckbalbem, ckctabem, ckrefbem, cgarant_bem, cgarant_rpt, tipologia FROM cd_garantias.gt018_rateio_aval WHERE ref_date = '${date}') GT018 ON prtctn_id = CONCAT(SUBSTR(TIPOLOGIA,1,1),'_',CKBALBEM, '_', CKCTABEM, '_', CKREFBEM) ) A WHERE 1=1 AND typ_prtctn_vl = '11111111111' AND TYP_PRTCTN <> '7'
A64: PRTCTN | B64: TYP_PRTCTN | C64: Controlos | D64: If "Previous appraisal date" is populated other than default values then "Protection type" has to be set as '8 - Residential real estate collateral', '9 - Offices and commercial premises' or '10 - Commercial real estate collateral' | E64: 45482 | F64: 45443 | G64: OK | I64: SELECT * FROM (SELECT *, CASE -- GARANTIAS IMOVEIS WHEN CGARANT_BEM = '5000' THEN '10' WHEN CGARANT_BEM = '5101' THEN '8' WHEN CGARANT_BEM = '5102' THEN '8' WHEN CGARANT_BEM = '5103' THEN '8' WHEN CGARANT_BEM = '5104' THEN '8' WHEN CGARANT_BEM = '5201' THEN '10' WHEN CGARANT_BEM = '5202' THEN '10' WHEN CGARANT_BEM = '5302' THEN '10' WHEN CGARANT_BEM = '5203' THEN '9' WHEN CGARANT_BEM = '5204' THEN '9' WHEN CGARANT_BEM = '5205' THEN '10' WHEN CGARANT_BEM = '5206' THEN '10' WHEN CGARANT_BEM = '5207' THEN '10' WHEN CGARANT_BEM = '5208' THEN '10' WHEN CGARANT_BEM = '5209' THEN '10' WHEN CGARANT_BEM = '5210' THEN '10' WHEN CGARANT_BEM = '5211' THEN '10' WHEN CGARANT_BEM = '5300' THEN '10' WHEN CGARANT_BEM = '5212' THEN '10' WHEN CGARANT_BEM = '5213' THEN '10' WHEN CGARANT_BEM = '5214' THEN '10' WHEN CGARANT_BEM = '5303' THEN '10' WHEN CGARANT_BEM = '5301' THEN '10' WHEN CGARANT_BEM = '5215' THEN '10' WHEN CGARANT_BEM = '5216' THEN '10' WHEN CGARANT_BEM = '5217' THEN '10' WHEN CGARANT_BEM = '5218' THEN '10' -- GARANTIAS FINANCEIRAS WHEN CGARANT_BEM = '6101' THEN '5' WHEN CGARANT_BEM = '6102' THEN '5' WHEN CGARANT_BEM = '6201' THEN '15' WHEN CGARANT_BEM = '6202' THEN '15' WHEN CGARANT_BEM = '6300' THEN '18' WHEN CGARANT_BEM = '6401' THEN '12' WHEN CGARANT_BEM = '6402' THEN '12' WHEN CGARANT_BEM = '6403' THEN '12' WHEN CGARANT_BEM = '6404' THEN '12' WHEN CGARANT_BEM = '6405' THEN '12' WHEN CGARANT_BEM = '6406' THEN '12' WHEN CGARANT_BEM = '6407' THEN '12' WHEN CGARANT_BEM = '6408' THEN '12' WHEN CGARANT_BEM = '6501' THEN '18' WHEN CGARANT_BEM = '6502' THEN '18' WHEN CGARANT_BEM = '6503' THEN '18' WHEN CGARANT_BEM = '6504' THEN '18' -- GARABTIAS PESSOAIS WHEN CGARANT_RPT= '158' THEN '7' WHEN CGARANT_RPT= '182' THEN '7' WHEN CGARANT_RPT= '108' THEN '7' WHEN CGARANT_RPT= '107' THEN '7' WHEN CGARANT_RPT= '159' THEN '7' WHEN CGARANT_RPT= '197' THEN '7' WHEN CGARANT_RPT= '198' THEN '7' WHEN CGARANT_RPT= '106' THEN '7' WHEN CGARANT_RPT= '1B5' THEN '7' WHEN CGARANT_RPT= '164' THEN '7' WHEN CGARANT_RPT= '169' THEN '7' WHEN CGARANT_RPT= '183' THEN '7' WHEN CGARANT_RPT= '1SS' THEN '7' WHEN CGARANT_RPT= '160' THEN '7' WHEN CGARANT_RPT= '309' THEN '7' WHEN CGARANT_RPT= '321' THEN '7' WHEN CGARANT_RPT= '298' THEN '7' WHEN CGARANT_RPT= '105' THEN '7' WHEN CGARANT_RPT= '126' THEN '7' WHEN CGARANT_RPT= '125' THEN '7' WHEN CGARANT_RPT= '199' THEN '7' WHEN CGARANT_RPT= '104' THEN '7' WHEN CGARANT_RPT= '157' THEN '7' WHEN CGARANT_RPT= '1EE' THEN '7' WHEN CGARANT_RPT= '181' THEN '7' WHEN CGARANT_RPT= '120' THEN '7' WHEN CGARANT_RPT= '186' THEN '7' WHEN CGARANT_RPT= '999' THEN '7' WHEN CGARANT_RPT= '101' THEN '7' WHEN CGARANT_RPT= 'LSA' THEN '7' WHEN CGARANT_RPT= '190' THEN '7' WHEN CGARANT_RPT= '501' THEN '7' WHEN CGARANT_RPT= '001' THEN '7' WHEN CGARANT_RPT= '111' THEN '7' WHEN CGARANT_RPT= '103' THEN '7' WHEN CGARANT_RPT= '1CC' THEN '7' WHEN CGARANT_RPT= '196' THEN '7' WHEN CGARANT_RPT= '1SW' THEN '7' WHEN CGARANT_RPT= '102' THEN '7' WHEN CGARANT_RPT= '133' THEN '7' WHEN CGARANT_RPT= '345' THEN '7' ELSE '99999999999' END as TYP_PRTCTN FROM (SELECT prtctn_id, typ_prtctn_intrnl, typ_prtctn_vl FROM cd_loan_tapes_bce.lt004_protection WHERE 1=1 AND ambito = 'PM' AND segmento = 'ESTR' AND ref_date = '${date}' AND nome_perimetro = 'Individual Corporativo' ) LT004 LEFT JOIN (SELECT ckbalbem, ckctabem, ckrefbem, cgarant_bem, cgarant_rpt, tipologia FROM cd_garantias.gt018_rateio_aval WHERE ref_date = '${date}') GT018 ON prtctn_id = CONCAT(SUBSTR(TIPOLOGIA,1,1),'_',CKBALBEM, '_', CKCTABEM, '_', CKREFBEM) ) A LEFT JOIN (SELECT LT004.prtctn_id, dt_apprsl_prvs AS valor_lt, CASE WHEN prtctn_id NOT LIKE 'I%' THEN '1111-11-11' WHEN prtctn_id_GT011 IS NULL THEN '1111-11-11' -- garantia com apenas 1 avaliação completa WHEN prtctn_id_GT011 IS NOT NULL THEN davalia ELSE '0000-00-00' END AS valor_simulado FROM (SELECT prtctn_id, dt_apprsl_prvs, typ_prtctn FROM cd_loan_tapes_bce.lt004_protection WHERE ref_date='${date}' AND nome_perimetro='Individual Corporativo' AND segmento='ESTR' AND ambito='PM' ) LT004 LEFT JOIN (SELECT * FROM (SELECT *, RANK() OVER (PARTITION BY prtctn_id_GT011 ORDER BY davalia DESC) AS ranking FROM (SELECT DISTINCT CONCAT('I_', CKBALBEM, '_', CKCTABEM, '_', CKREFBEM) AS prtctn_id_GT011, davalia FROM cd_garantias.gt011_avalc_imov WHERE 1=1 AND ref_date='${date}' AND ( (CTIPREAVL = 'A' AND CORAVGP = 'G39') OR CORAVGP='G26') ) GT011 )GT011 WHERE ranking = 2 )GT011 ON LT004.prtctn_id = GT011.prtctn_id_GT011 ) B ON A.prtctn_id = B.prtctn_id WHERE 1=1 AND valor_simulado <> '1111-11-11' AND TYP_PRTCTN NOT IN ('8','9','10')
A65: PRTCTN | B65: TYP_PRTCTN | C65: Controlos | D65: If "Currency of annual income and expenses" is populated other than default values then "Protection type" has to be set as '10 - Commercial real estate collateral' or '9 - Offices and commercial premises' | E65: 45482 | F65: 45443 | G65: OK | I65: SELECT * FROM (SELECT *, CASE -- GARANTIAS IMOVEIS WHEN CGARANT_BEM = '5000' THEN '10' WHEN CGARANT_BEM = '5101' THEN '8' WHEN CGARANT_BEM = '5102' THEN '8' WHEN CGARANT_BEM = '5103' THEN '8' WHEN CGARANT_BEM = '5104' THEN '8' WHEN CGARANT_BEM = '5201' THEN '10' WHEN CGARANT_BEM = '5202' THEN '10' WHEN CGARANT_BEM = '5302' THEN '10' WHEN CGARANT_BEM = '5203' THEN '9' WHEN CGARANT_BEM = '5204' THEN '9' WHEN CGARANT_BEM = '5205' THEN '10' WHEN CGARANT_BEM = '5206' THEN '10' WHEN CGARANT_BEM = '5207' THEN '10' WHEN CGARANT_BEM = '5208' THEN '10' WHEN CGARANT_BEM = '5209' THEN '10' WHEN CGARANT_BEM = '5210' THEN '10' WHEN CGARANT_BEM = '5211' THEN '10' WHEN CGARANT_BEM = '5300' THEN '10' WHEN CGARANT_BEM = '5212' THEN '10' WHEN CGARANT_BEM = '5213' THEN '10' WHEN CGARANT_BEM = '5214' THEN '10' WHEN CGARANT_BEM = '5303' THEN '10' WHEN CGARANT_BEM = '5301' THEN '10' WHEN CGARANT_BEM = '5215' THEN '10' WHEN CGARANT_BEM = '5216' THEN '10' WHEN CGARANT_BEM = '5217' THEN '10' WHEN CGARANT_BEM = '5218' THEN '10' -- GARANTIAS FINANCEIRAS WHEN CGARANT_BEM = '6101' THEN '5' WHEN CGARANT_BEM = '6102' THEN '5' WHEN CGARANT_BEM = '6201' THEN '15' WHEN CGARANT_BEM = '6202' THEN '15' WHEN CGARANT_BEM = '6300' THEN '18' WHEN CGARANT_BEM = '6401' THEN '12' WHEN CGARANT_BEM = '6402' THEN '12' WHEN CGARANT_BEM = '6403' THEN '12' WHEN CGARANT_BEM = '6404' THEN '12' WHEN CGARANT_BEM = '6405' THEN '12' WHEN CGARANT_BEM = '6406' THEN '12' WHEN CGARANT_BEM = '6407' THEN '12' WHEN CGARANT_BEM = '6408' THEN '12' WHEN CGARANT_BEM = '6501' THEN '18' WHEN CGARANT_BEM = '6502' THEN '18' WHEN CGARANT_BEM = '6503' THEN '18' WHEN CGARANT_BEM = '6504' THEN '18' -- GARABTIAS PESSOAIS WHEN CGARANT_RPT= '158' THEN '7' WHEN CGARANT_RPT= '182' THEN '7' WHEN CGARANT_RPT= '108' THEN '7' WHEN CGARANT_RPT= '107' THEN '7' WHEN CGARANT_RPT= '159' THEN '7' WHEN CGARANT_RPT= '197' THEN '7' WHEN CGARANT_RPT= '198' THEN '7' WHEN CGARANT_RPT= '106' THEN '7' WHEN CGARANT_RPT= '1B5' THEN '7' WHEN CGARANT_RPT= '164' THEN '7' WHEN CGARANT_RPT= '169' THEN '7' WHEN CGARANT_RPT= '183' THEN '7' WHEN CGARANT_RPT= '1SS' THEN '7' WHEN CGARANT_RPT= '160' THEN '7' WHEN CGARANT_RPT= '309' THEN '7' WHEN CGARANT_RPT= '321' THEN '7' WHEN CGARANT_RPT= '298' THEN '7' WHEN CGARANT_RPT= '105' THEN '7' WHEN CGARANT_RPT= '126' THEN '7' WHEN CGARANT_RPT= '125' THEN '7' WHEN CGARANT_RPT= '199' THEN '7' WHEN CGARANT_RPT= '104' THEN '7' WHEN CGARANT_RPT= '157' THEN '7' WHEN CGARANT_RPT= '1EE' THEN '7' WHEN CGARANT_RPT= '181' THEN '7' WHEN CGARANT_RPT= '120' THEN '7' WHEN CGARANT_RPT= '186' THEN '7' WHEN CGARANT_RPT= '999' THEN '7' WHEN CGARANT_RPT= '101' THEN '7' WHEN CGARANT_RPT= 'LSA' THEN '7' WHEN CGARANT_RPT= '190' THEN '7' WHEN CGARANT_RPT= '501' THEN '7' WHEN CGARANT_RPT= '001' THEN '7' WHEN CGARANT_RPT= '111' THEN '7' WHEN CGARANT_RPT= '103' THEN '7' WHEN CGARANT_RPT= '1CC' THEN '7' WHEN CGARANT_RPT= '196' THEN '7' WHEN CGARANT_RPT= '1SW' THEN '7' WHEN CGARANT_RPT= '102' THEN '7' WHEN CGARANT_RPT= '133' THEN '7' WHEN CGARANT_RPT= '345' THEN '7' ELSE '99999999999' END as TYP_PRTCTN FROM (SELECT prtctn_id, typ_prtctn_intrnl, typ_prtctn_vl, cre_incm_crrncy FROM cd_loan_tapes_bce.lt004_protection WHERE 1=1 AND ambito = 'PM' AND segmento = 'ESTR' AND ref_date = '${date}' AND nome_perimetro = 'Individual Corporativo' ) LT004 LEFT JOIN (SELECT ckbalbem, ckctabem, ckrefbem, cgarant_bem, cgarant_rpt, tipologia FROM cd_garantias.gt018_rateio_aval WHERE ref_date = '${date}') GT018 ON prtctn_id = CONCAT(SUBSTR(TIPOLOGIA,1,1),'_',CKBALBEM, '_', CKCTABEM, '_', CKREFBEM) ) A WHERE 1=1 AND CRE_INCM_CRRNCY NOT IN ('N/A', 'MISS') AND TYP_PRTCTN NOT IN ('9','10') ; SELECT * FROM (SELECT *, CASE -- GARANTIAS IMOVEIS WHEN CGARANT_BEM = '5000' THEN '10' WHEN CGARANT_BEM = '5101' THEN '8' WHEN CGARANT_BEM = '5102' THEN '8' WHEN CGARANT_BEM = '5103' THEN '8' WHEN CGARANT_BEM = '5104' THEN '8' WHEN CGARANT_BEM = '5201' THEN '10' WHEN CGARANT_BEM = '5202' THEN '10' WHEN CGARANT_BEM = '5302' THEN '10' WHEN CGARANT_BEM = '5203' THEN '9' WHEN CGARANT_BEM = '5204' THEN '9' WHEN CGARANT_BEM = '5205' THEN '10' WHEN CGARANT_BEM = '5206' THEN '10' WHEN CGARANT_BEM = '5207' THEN '10' WHEN CGARANT_BEM = '5208' THEN '10' WHEN CGARANT_BEM = '5209' THEN '10' WHEN CGARANT_BEM = '5210' THEN '10' WHEN CGARANT_BEM = '5211' THEN '10' WHEN CGARANT_BEM = '5300' THEN '10' WHEN CGARANT_BEM = '5212' THEN '10' WHEN CGARANT_BEM = '5213' THEN '10' WHEN CGARANT_BEM = '5214' THEN '10' WHEN CGARANT_BEM = '5303' THEN '10' WHEN CGARANT_BEM = '5301' THEN '10' WHEN CGARANT_BEM = '5215' THEN '10' WHEN CGARANT_BEM = '5216' THEN '10' WHEN CGARANT_BEM = '5217' THEN '10' WHEN CGARANT_BEM = '5218' THEN '10' -- GARANTIAS FINANCEIRAS WHEN CGARANT_BEM = '6101' THEN '5' WHEN CGARANT_BEM = '6102' THEN '5' WHEN CGARANT_BEM = '6201' THEN '15' WHEN CGARANT_BEM = '6202' THEN '15' WHEN CGARANT_BEM = '6300' THEN '18' WHEN CGARANT_BEM = '6401' THEN '12' WHEN CGARANT_BEM = '6402' THEN '12' WHEN CGARANT_BEM = '6403' THEN '12' WHEN CGARANT_BEM = '6404' THEN '12' WHEN CGARANT_BEM = '6405' THEN '12' WHEN CGARANT_BEM = '6406' THEN '12' WHEN CGARANT_BEM = '6407' THEN '12' WHEN CGARANT_BEM = '6408' THEN '12' WHEN CGARANT_BEM = '6501' THEN '18' WHEN CGARANT_BEM = '6502' THEN '18' WHEN CGARANT_BEM = '6503' THEN '18' WHEN CGARANT_BEM = '6504' THEN '18' -- GARABTIAS PESSOAIS WHEN CGARANT_RPT= '158' THEN '7' WHEN CGARANT_RPT= '182' THEN '7' WHEN CGARANT_RPT= '108' THEN '7' WHEN CGARANT_RPT= '107' THEN '7' WHEN CGARANT_RPT= '159' THEN '7' WHEN CGARANT_RPT= '197' THEN '7' WHEN CGARANT_RPT= '198' THEN '7' WHEN CGARANT_RPT= '106' THEN '7' WHEN CGARANT_RPT= '1B5' THEN '7' WHEN CGARANT_RPT= '164' THEN '7' WHEN CGARANT_RPT= '169' THEN '7' WHEN CGARANT_RPT= '183' THEN '7' WHEN CGARANT_RPT= '1SS' THEN '7' WHEN CGARANT_RPT= '160' THEN '7' WHEN CGARANT_RPT= '309' THEN '7' WHEN CGARANT_RPT= '321' THEN '7' WHEN CGARANT_RPT= '298' THEN '7' WHEN CGARANT_RPT= '105' THEN '7' WHEN CGARANT_RPT= '126' THEN '7' WHEN CGARANT_RPT= '125' THEN '7' WHEN CGARANT_RPT= '199' THEN '7' WHEN CGARANT_RPT= '104' THEN '7' WHEN CGARANT_RPT= '157' THEN '7' WHEN CGARANT_RPT= '1EE' THEN '7' WHEN CGARANT_RPT= '181' THEN '7' WHEN CGARANT_RPT= '120' THEN '7' WHEN CGARANT_RPT= '186' THEN '7' WHEN CGARANT_RPT= '999' THEN '7' WHEN CGARANT_RPT= '101' THEN '7' WHEN CGARANT_RPT= 'LSA' THEN '7' WHEN CGARANT_RPT= '190' THEN '7' WHEN CGARANT_RPT= '501' THEN '7' WHEN CGARANT_RPT= '001' THEN '7' WHEN CGARANT_RPT= '111' THEN '7' WHEN CGARANT_RPT= '103' THEN '7' WHEN CGARANT_RPT= '1CC' THEN '7' WHEN CGARANT_RPT= '196' THEN '7' WHEN CGARANT_RPT= '1SW' THEN '7' WHEN CGARANT_RPT= '102' THEN '7' WHEN CGARANT_RPT= '133' THEN '7' WHEN CGARANT_RPT= '345' THEN '7' ELSE '99999999999' END as TYP_PRTCTN FROM (SELECT prtctn_id, typ_prtctn_intrnl, typ_prtctn_vl, cre_incm_crrncy FROM cd_loan_tapes_bce.lt004_protection WHERE 1=1 AND ambito = 'PM' AND segmento = 'ESTR' AND ref_date = '${date}' AND nome_perimetro = 'Individual Corporativo' ) LT004 LEFT JOIN (SELECT ckbalbem, ckctabem, ckrefbem, cgarant_bem, cgarant_rpt, tipologia FROM cd_garantias.gt018_rateio_aval WHERE ref_date = '${date}') GT018 ON prtctn_id = CONCAT(SUBSTR(TIPOLOGIA,1,1),'_',CKBALBEM, '_', CKCTABEM, '_', CKREFBEM) ) A WHERE 1=1 AND CRE_INCM_CRRNCY NOT IN ('N/A', 'MISS') AND TYP_PRTCTN NOT IN ('9','10')
A66: PRTCTN | B66: TYP_PRTCTN | C66: Controlos | D66: If "Provider of latest valuation (appraiser)" is populated other than default values then "Protection type" has to be set as '8 - Residential real estate collateral', '9 - Offices and commercial premises', '10 - Commercial real estate collateral' | E66: 45482 | F66: 45443 | G66: OK | I66: SELECT * FROM (SELECT *, CASE -- GARANTIAS IMOVEIS WHEN CGARANT_BEM = '5000' THEN '10' WHEN CGARANT_BEM = '5101' THEN '8' WHEN CGARANT_BEM = '5102' THEN '8' WHEN CGARANT_BEM = '5103' THEN '8' WHEN CGARANT_BEM = '5104' THEN '8' WHEN CGARANT_BEM = '5201' THEN '10' WHEN CGARANT_BEM = '5202' THEN '10' WHEN CGARANT_BEM = '5302' THEN '10' WHEN CGARANT_BEM = '5203' THEN '9' WHEN CGARANT_BEM = '5204' THEN '9' WHEN CGARANT_BEM = '5205' THEN '10' WHEN CGARANT_BEM = '5206' THEN '10' WHEN CGARANT_BEM = '5207' THEN '10' WHEN CGARANT_BEM = '5208' THEN '10' WHEN CGARANT_BEM = '5209' THEN '10' WHEN CGARANT_BEM = '5210' THEN '10' WHEN CGARANT_BEM = '5211' THEN '10' WHEN CGARANT_BEM = '5300' THEN '10' WHEN CGARANT_BEM = '5212' THEN '10' WHEN CGARANT_BEM = '5213' THEN '10' WHEN CGARANT_BEM = '5214' THEN '10' WHEN CGARANT_BEM = '5303' THEN '10' WHEN CGARANT_BEM = '5301' THEN '10' WHEN CGARANT_BEM = '5215' THEN '10' WHEN CGARANT_BEM = '5216' THEN '10' WHEN CGARANT_BEM = '5217' THEN '10' WHEN CGARANT_BEM = '5218' THEN '10' -- GARANTIAS FINANCEIRAS WHEN CGARANT_BEM = '6101' THEN '5' WHEN CGARANT_BEM = '6102' THEN '5' WHEN CGARANT_BEM = '6201' THEN '15' WHEN CGARANT_BEM = '6202' THEN '15' WHEN CGARANT_BEM = '6300' THEN '18' WHEN CGARANT_BEM = '6401' THEN '12' WHEN CGARANT_BEM = '6402' THEN '12' WHEN CGARANT_BEM = '6403' THEN '12' WHEN CGARANT_BEM = '6404' THEN '12' WHEN CGARANT_BEM = '6405' THEN '12' WHEN CGARANT_BEM = '6406' THEN '12' WHEN CGARANT_BEM = '6407' THEN '12' WHEN CGARANT_BEM = '6408' THEN '12' WHEN CGARANT_BEM = '6501' THEN '18' WHEN CGARANT_BEM = '6502' THEN '18' WHEN CGARANT_BEM = '6503' THEN '18' WHEN CGARANT_BEM = '6504' THEN '18' -- GARABTIAS PESSOAIS WHEN CGARANT_RPT= '158' THEN '7' WHEN CGARANT_RPT= '182' THEN '7' WHEN CGARANT_RPT= '108' THEN '7' WHEN CGARANT_RPT= '107' THEN '7' WHEN CGARANT_RPT= '159' THEN '7' WHEN CGARANT_RPT= '197' THEN '7' WHEN CGARANT_RPT= '198' THEN '7' WHEN CGARANT_RPT= '106' THEN '7' WHEN CGARANT_RPT= '1B5' THEN '7' WHEN CGARANT_RPT= '164' THEN '7' WHEN CGARANT_RPT= '169' THEN '7' WHEN CGARANT_RPT= '183' THEN '7' WHEN CGARANT_RPT= '1SS' THEN '7' WHEN CGARANT_RPT= '160' THEN '7' WHEN CGARANT_RPT= '309' THEN '7' WHEN CGARANT_RPT= '321' THEN '7' WHEN CGARANT_RPT= '298' THEN '7' WHEN CGARANT_RPT= '105' THEN '7' WHEN CGARANT_RPT= '126' THEN '7' WHEN CGARANT_RPT= '125' THEN '7' WHEN CGARANT_RPT= '199' THEN '7' WHEN CGARANT_RPT= '104' THEN '7' WHEN CGARANT_RPT= '157' THEN '7' WHEN CGARANT_RPT= '1EE' THEN '7' WHEN CGARANT_RPT= '181' THEN '7' WHEN CGARANT_RPT= '120' THEN '7' WHEN CGARANT_RPT= '186' THEN '7' WHEN CGARANT_RPT= '999' THEN '7' WHEN CGARANT_RPT= '101' THEN '7' WHEN CGARANT_RPT= 'LSA' THEN '7' WHEN CGARANT_RPT= '190' THEN '7' WHEN CGARANT_RPT= '501' THEN '7' WHEN CGARANT_RPT= '001' THEN '7' WHEN CGARANT_RPT= '111' THEN '7' WHEN CGARANT_RPT= '103' THEN '7' WHEN CGARANT_RPT= '1CC' THEN '7' WHEN CGARANT_RPT= '196' THEN '7' WHEN CGARANT_RPT= '1SW' THEN '7' WHEN CGARANT_RPT= '102' THEN '7' WHEN CGARANT_RPT= '133' THEN '7' WHEN CGARANT_RPT= '345' THEN '7' ELSE '99999999999' END as TYP_PRTCTN FROM (SELECT prtctn_id, typ_prtctn_intrnl, typ_prtctn_vl, apprsr FROM cd_loan_tapes_bce.lt004_protection WHERE 1=1 AND ambito = 'PM' AND segmento = 'ESTR' AND ref_date = '${date}' AND nome_perimetro = 'Individual Corporativo' ) LT004 LEFT JOIN (SELECT ckbalbem, ckctabem, ckrefbem, cgarant_bem, cgarant_rpt, tipologia FROM cd_garantias.gt018_rateio_aval WHERE ref_date = '${date}') GT018 ON prtctn_id = CONCAT(SUBSTR(TIPOLOGIA,1,1),'_',CKBALBEM, '_', CKCTABEM, '_', CKREFBEM) ) A WHERE 1=1 AND APPRSR NOT IN ('N/A', 'MISS') AND TYP_PRTCTN NOT IN ('8','9','10')
A67: PRTCTN | B67: TYP_PRTCTN | C67: Controlos | D67: If "Date of last full appraisal" is populated other than default values then "Protection type" has to be set as '8 - Residential real estate collateral', '9 - Offices and commercial premises' or '10 - Commercial real estate collateral' | E67: 45482 | F67: 45443 | G67: OK | I67: SELECT * FROM ( --- GARANTIAS IMÓVEIS SELECT prtctn_id, typ_prtctn_vl, CASE WHEN CGARANT_BEM = '5000' THEN '10' WHEN CGARANT_BEM = '5101' THEN '8' WHEN CGARANT_BEM = '5102' THEN '8' WHEN CGARANT_BEM = '5103' THEN '8' WHEN CGARANT_BEM = '5104' THEN '8' WHEN CGARANT_BEM = '5201' THEN '10' WHEN CGARANT_BEM = '5202' THEN '10' WHEN CGARANT_BEM = '5302' THEN '10' WHEN CGARANT_BEM = '5203' THEN '9' WHEN CGARANT_BEM = '5204' THEN '9' WHEN CGARANT_BEM = '5205' THEN '10' WHEN CGARANT_BEM = '5206' THEN '10' WHEN CGARANT_BEM = '5207' THEN '10' WHEN CGARANT_BEM = '5208' THEN '10' WHEN CGARANT_BEM = '5209' THEN '10' WHEN CGARANT_BEM = '5210' THEN '10' WHEN CGARANT_BEM = '5211' THEN '10' WHEN CGARANT_BEM = '5300' THEN '10' WHEN CGARANT_BEM = '5212' THEN '10' WHEN CGARANT_BEM = '5213' THEN '10' WHEN CGARANT_BEM = '5214' THEN '10' WHEN CGARANT_BEM = '5303' THEN '10' WHEN CGARANT_BEM = '5301' THEN '10' WHEN CGARANT_BEM = '5215' THEN '10' WHEN CGARANT_BEM = '5216' THEN '10' WHEN CGARANT_BEM = '5217' THEN '10' WHEN CGARANT_BEM = '5218' THEN '10' ELSE '99999999999' END as TYP_PRTCTN FROM (SELECT prtctn_id, typ_prtctn_vl FROM cd_loan_tapes_bce.lt004_protection WHERE 1=1 AND ambito = 'PM' AND segmento = 'ESTR' AND ref_date = '${date}' AND nome_perimetro = 'Individual Corporativo' AND prtctn_id LIKE 'I%') LT004 LEFT JOIN (SELECT cgarant_bem, ckbalbem, ckctabem, ckrefbem FROM cd_garantias.gt009_bens_imov WHERE ref_date = '${date}') GT009 ON prtctn_id = concat('I_',GT009.ckbalbem,'_',GT009.ckctabem,'_',GT009.ckrefbem) UNION ALL ---- GARANTIAS FINANCEIRAS SELECT prtctn_id, typ_prtctn_vl, CASE WHEN CGARANT_BEM = '6101' THEN '5' WHEN CGARANT_BEM = '6102' THEN '5' WHEN CGARANT_BEM = '6201' THEN '15' WHEN CGARANT_BEM = '6202' THEN '15' WHEN CGARANT_BEM = '6300' THEN '18' WHEN CGARANT_BEM = '6401' THEN '12' WHEN CGARANT_BEM = '6402' THEN '12' WHEN CGARANT_BEM = '6403' THEN '12' WHEN CGARANT_BEM = '6404' THEN '12' WHEN CGARANT_BEM = '6405' THEN '12' WHEN CGARANT_BEM = '6406' THEN '12' WHEN CGARANT_BEM = '6407' THEN '12' WHEN CGARANT_BEM = '6408' THEN '12' WHEN CGARANT_BEM = '6501' THEN '18' WHEN CGARANT_BEM = '6502' THEN '18' WHEN CGARANT_BEM = '6503' THEN '18' WHEN CGARANT_BEM = '6504' THEN '18' ELSE '99999999999' END as TYP_PRTCTN FROM (SELECT prtctn_id, typ_prtctn_vl FROM cd_loan_tapes_bce.lt004_protection WHERE 1=1 AND ambito = 'PM' AND segmento = 'ESTR' AND ref_date = '${date}' AND nome_perimetro = 'Individual Corporativo' AND prtctn_id LIKE 'F%') LT004 LEFT JOIN (SELECT cgarant_bem, ckbalbem, ckctabem, ckrefbem FROM cd_garantias.gt004_bens_fin WHERE ref_date = '${date}') GT004 ON prtctn_id = concat('F_',GT004.ckbalbem,'_',GT004.ckctabem,'_',GT004.ckrefbem) UNION ALL --- GARANTIAS PESSOAIS SELECT DISTINCT prtctn_id, typ_prtctn_vl, CASE WHEN CGARANT_RPT= '158' THEN '7' WHEN CGARANT_RPT= '182' THEN '7' WHEN CGARANT_RPT= '108' THEN '7' WHEN CGARANT_RPT= '107' THEN '7' WHEN CGARANT_RPT= '159' THEN '7' WHEN CGARANT_RPT= '197' THEN '7' WHEN CGARANT_RPT= '198' THEN '7' WHEN CGARANT_RPT= '106' THEN '7' WHEN CGARANT_RPT= '1B5' THEN '7' WHEN CGARANT_RPT= '164' THEN '7' WHEN CGARANT_RPT= '169' THEN '7' WHEN CGARANT_RPT= '183' THEN '7' WHEN CGARANT_RPT= '1SS' THEN '7' WHEN CGARANT_RPT= '160' THEN '7' WHEN CGARANT_RPT= '309' THEN '7' WHEN CGARANT_RPT= '321' THEN '7' WHEN CGARANT_RPT= '298' THEN '7' WHEN CGARANT_RPT= '105' THEN '7' WHEN CGARANT_RPT= '126' THEN '7' WHEN CGARANT_RPT= '125' THEN '7' WHEN CGARANT_RPT= '199' THEN '7' WHEN CGARANT_RPT= '104' THEN '7' WHEN CGARANT_RPT= '157' THEN '7' WHEN CGARANT_RPT= '1EE' THEN '7' WHEN CGARANT_RPT= '181' THEN '7' WHEN CGARANT_RPT= '120' THEN '7' WHEN CGARANT_RPT= '186' THEN '7' WHEN CGARANT_RPT= '999' THEN '7' WHEN CGARANT_RPT= '101' THEN '7' WHEN CGARANT_RPT= 'LSA' THEN '7' WHEN CGARANT_RPT= '190' THEN '7' WHEN CGARANT_RPT= '501' THEN '7' WHEN CGARANT_RPT= '001' THEN '7' WHEN CGARANT_RPT= '111' THEN '7' WHEN CGARANT_RPT= '103' THEN '7' WHEN CGARANT_RPT= '1CC' THEN '7' WHEN CGARANT_RPT= '196' THEN '7' WHEN CGARANT_RPT= '1SW' THEN '7' WHEN CGARANT_RPT= '102' THEN '7' WHEN CGARANT_RPT= '133' THEN '7' WHEN CGARANT_RPT= '345' THEN '7' ELSE '99999999999' END as TYP_PRTCTN FROM (SELECT prtctn_id, typ_prtctn_vl FROM cd_loan_tapes_bce.lt004_protection WHERE 1=1 AND ambito = 'PM' AND segmento = 'ESTR' AND ref_date = '${date}' AND nome_perimetro = 'Individual Corporativo' AND prtctn_id LIKE 'P%') LT004 LEFT JOIN (SELECT DISTINCT cgarant_rpt, ckbalbem, ckctabem, ckrefbem FROM cd_garantias.gt007_trz_gt_pes WHERE ref_date = '${date}') GT007 ON prtctn_id = concat('P_',GT007.ckbalbem,'_',GT007.ckctabem,'_',GT007.ckrefbem) ) A SELECT * FROM (SELECT *, CASE -- GARANTIAS IMOVEIS WHEN CGARANT_BEM = '5000' THEN '10' WHEN CGARANT_BEM = '5101' THEN '8' WHEN CGARANT_BEM = '5102' THEN '8' WHEN CGARANT_BEM = '5103' THEN '8' WHEN CGARANT_BEM = '5104' THEN '8' WHEN CGARANT_BEM = '5201' THEN '10' WHEN CGARANT_BEM = '5202' THEN '10' WHEN CGARANT_BEM = '5302' THEN '10' WHEN CGARANT_BEM = '5203' THEN '9' WHEN CGARANT_BEM = '5204' THEN '9' WHEN CGARANT_BEM = '5205' THEN '10' WHEN CGARANT_BEM = '5206' THEN '10' WHEN CGARANT_BEM = '5207' THEN '10' WHEN CGARANT_BEM = '5208' THEN '10' WHEN CGARANT_BEM = '5209' THEN '10' WHEN CGARANT_BEM = '5210' THEN '10' WHEN CGARANT_BEM = '5211' THEN '10' WHEN CGARANT_BEM = '5300' THEN '10' WHEN CGARANT_BEM = '5212' THEN '10' WHEN CGARANT_BEM = '5213' THEN '10' WHEN CGARANT_BEM = '5214' THEN '10' WHEN CGARANT_BEM = '5303' THEN '10' WHEN CGARANT_BEM = '5301' THEN '10' WHEN CGARANT_BEM = '5215' THEN '10' WHEN CGARANT_BEM = '5216' THEN '10' WHEN CGARANT_BEM = '5217' THEN '10' WHEN CGARANT_BEM = '5218' THEN '10' -- GARANTIAS FINANCEIRAS WHEN CGARANT_BEM = '6101' THEN '5' WHEN CGARANT_BEM = '6102' THEN '5' WHEN CGARANT_BEM = '6201' THEN '15' WHEN CGARANT_BEM = '6202' THEN '15' WHEN CGARANT_BEM = '6300' THEN '18' WHEN CGARANT_BEM = '6401' THEN '12' WHEN CGARANT_BEM = '6402' THEN '12' WHEN CGARANT_BEM = '6403' THEN '12' WHEN CGARANT_BEM = '6404' THEN '12' WHEN CGARANT_BEM = '6405' THEN '12' WHEN CGARANT_BEM = '6406' THEN '12' WHEN CGARANT_BEM = '6407' THEN '12' WHEN CGARANT_BEM = '6408' THEN '12' WHEN CGARANT_BEM = '6501' THEN '18' WHEN CGARANT_BEM = '6502' THEN '18' WHEN CGARANT_BEM = '6503' THEN '18' WHEN CGARANT_BEM = '6504' THEN '18' -- GARABTIAS PESSOAIS WHEN CGARANT_RPT= '158' THEN '7' WHEN CGARANT_RPT= '182' THEN '7' WHEN CGARANT_RPT= '108' THEN '7' WHEN CGARANT_RPT= '107' THEN '7' WHEN CGARANT_RPT= '159' THEN '7' WHEN CGARANT_RPT= '197' THEN '7' WHEN CGARANT_RPT= '198' THEN '7' WHEN CGARANT_RPT= '106' THEN '7' WHEN CGARANT_RPT= '1B5' THEN '7' WHEN CGARANT_RPT= '164' THEN '7' WHEN CGARANT_RPT= '169' THEN '7' WHEN CGARANT_RPT= '183' THEN '7' WHEN CGARANT_RPT= '1SS' THEN '7' WHEN CGARANT_RPT= '160' THEN '7' WHEN CGARANT_RPT= '309' THEN '7' WHEN CGARANT_RPT= '321' THEN '7' WHEN CGARANT_RPT= '298' THEN '7' WHEN CGARANT_RPT= '105' THEN '7' WHEN CGARANT_RPT= '126' THEN '7' WHEN CGARANT_RPT= '125' THEN '7' WHEN CGARANT_RPT= '199' THEN '7' WHEN CGARANT_RPT= '104' THEN '7' WHEN CGARANT_RPT= '157' THEN '7' WHEN CGARANT_RPT= '1EE' THEN '7' WHEN CGARANT_RPT= '181' THEN '7' WHEN CGARANT_RPT= '120' THEN '7' WHEN CGARANT_RPT= '186' THEN '7' WHEN CGARANT_RPT= '999' THEN '7' WHEN CGARANT_RPT= '101' THEN '7' WHEN CGARANT_RPT= 'LSA' THEN '7' WHEN CGARANT_RPT= '190' THEN '7' WHEN CGARANT_RPT= '501' THEN '7' WHEN CGARANT_RPT= '001' THEN '7' WHEN CGARANT_RPT= '111' THEN '7' WHEN CGARANT_RPT= '103' THEN '7' WHEN CGARANT_RPT= '1CC' THEN '7' WHEN CGARANT_RPT= '196' THEN '7' WHEN CGARANT_RPT= '1SW' THEN '7' WHEN CGARANT_RPT= '102' THEN '7' WHEN CGARANT_RPT= '133' THEN '7' WHEN CGARANT_RPT= '345' THEN '7' ELSE '99999999999' END as TYP_PRTCTN FROM (SELECT prtctn_id, typ_prtctn_intrnl, typ_prtctn_vl, apprsr FROM cd_loan_tapes_bce.lt004_protection WHERE 1=1 AND ambito = 'PM' AND segmento = 'ESTR' AND ref_date = '${date}' AND nome_perimetro = 'Individual Corporativo' ) LT004 LEFT JOIN (SELECT ckbalbem, ckctabem, ckrefbem, cgarant_bem, cgarant_rpt, tipologia FROM cd_garantias.gt018_rateio_aval WHERE ref_date = '${date}') GT018 ON prtctn_id = CONCAT(SUBSTR(TIPOLOGIA,1,1),'_',CKBALBEM, '_', CKCTABEM, '_', CKREFBEM) ) A LEFT JOIN ( SELECT LT004.prtctn_id, LT004.dt_lst_fll_apprsl as valor_lt, LT004.dt_orgnl_prtctn_vl, valor_simulado FROM (SELECT prtctn_id, dt_lst_fll_apprsl, dt_prtctn_vl, dt_orgnl_prtctn_vl FROM cd_loan_tapes_bce.lt004_protection WHERE ref_date='${date}' AND nome_perimetro='Individual Corporativo' AND segmento='ESTR' AND ambito='PM' AND prtctn_id LIKE 'I%') LT004 LEFT JOIN (SELECT max(davalia) as valor_simulado, CONCAT('I_', CKBALBEM, '_', CKCTABEM, '_', CKREFBEM) AS prtctn_id FROM cd_garantias.gt011_avalc_imov WHERE 1=1 AND ref_date='${date}' AND ( (CTIPREAVL = 'A' AND CORAVGP = 'G39') OR CORAVGP='G26') GROUP BY 2 ) GT011 ON LT004.prtctn_id = GT011.prtctn_id ) B ON A.prtctn_id = B.prtctn_id WHERE 1=1 AND valor_simulado <> '1111-11-11' AND TYP_PRTCTN NOT IN ('8','9','10')
A68: PRTCTN | B68: TYP_PRTCTN | C68: Controlos | D68: If "Type protection value is a public guarantee scheme in response to the COVID19 situation" is equal to 'Y' then "Protection type" has to be set as '7 - Other protection' | E68: 45482 | F68: 45443 | H68: Foram eliminados os campos relacionados com Covid 19
A69: PRTCTN | B69: TYP_PRTCTN | C69: Controlos | D69: If "Flag first home" is set as 'Y - Yes' then "Protection Type" must be '8 - Residential real estate collateral', '9- Offices and commercial premises' or '10 - Commercial real estate collateral' | E69: 45482 | F69: 45443 | H69: Campo novo, ainda não especificado (FLG_FRST_HM)
A70: PRTCTN | B70: TYP_PRTCTN | C70: Controlos | D70: If "Flag Acute Physical Risk at protection level" is set as 'Y - Yes' then "Protection Type" must be '8 - Residential real estate collateral', '9- Offices and commercial premises' or '10 - Commercial real estate collateral' | E70: 45482 | F70: 45443 | H70: FLG_ACT_PHYSCL_RSK campo todo a NULL
A71: PRTCTN | B71: TYP_PRTCTN | C71: Controlos | D71: If "Loans Collateralized Classification" is set as 'FMC2 - Real Estate. Residential' then at least one PROTECTION_ID linked to INSTRUMENT_ID "Protection Type" must be '8 - Residential real estate collateral' | E71: 45482 | F71: 45443 | H71: LNS_CLLTRLZD_CLSSFCTN campo todo a NULL
A72: PRTCTN | B72: TYP_PRTCTN | C72: Controlos | D72: If "Loans Collateralized Classification" is set as 'FMC1 - Real Estate. Commercial' then at least one PROTECTION_ID linked to INSTRUMENT_ID "Protection Type" must be '9 - Offices and commercial premises' or '10 - Commercial real estate collateral' | E72: 45482 | F72: 45443 | H72: LNS_CLLTRLZD_CLSSFCTN campo todo a NULL
A73: PRTCTN | B73: TYP_PRTCTN | C73: Controlos | D73: If "Loans Collateralized Classification" is set as 'FMC3 - Other Real Collateral' then at least one PROTECTION_ID linked to INSTRUMENT_ID "Protection Type" must be populated with other than default values, '8 - Residential Real Estate Collateral', '9 - Offices and Commercial Premises', '10 - Commercial Real Estate Collateral' and cannot be a "personal guarantee" (We consider "personal guarantee" when "Protection ID" matches the "Protection Provider ID" (Guarantor) or "Tax ID" (Protection level) is populated other than default value and the "Protection type" equals '7 - Other protection') | E73: 45482 | F73: 45443 | H73: LNS_CLLTRLZD_CLSSFCTN campo todo a NULL
A74: PRTCTN | B74: DT_PRTCTN_VL | C74: Desenvolvimento | D74: Validar incidência | E74: 45482 | F74: 45443 | G74: OK | I74: Select * FROM (SELECT prtctn_id, DT_PRTCTN_VL, CASE WHEN prtctn_id LIKE 'P%' THEN '1111-11-11' ELSE max(dtrcaval) END AS DT_PRTCTN_VL_SIMULADO FROM (Select * From cd_loan_tapes_bce.lt004_protection WHERE segmento = 'ESTR' AND nome_perimetro ='Individual Corporativo' AND ref_date='${date}' AND AMBITO = 'PM') lt004 Left join (Select * From cd_garantias.gt018_rateio_aval Where ref_date='${date}') gt018 ON prtctn_id = concat(substr(TIPOLOGIA,1,1),'_',ckbalbem,'_',ckctabem,'_',ckrefbem) GROUP BY 1,2 ) A WHERE 1=1 AND DT_PRTCTN_VL_SIMULADO = '0001-01-01'
A75: PRTCTN | B75: DT_PRTCTN_VL | C75: Controlos | D75: "Date of protection value" must have a Date format (yyyy-mm-dd) | E75: 45482 | F75: 45443 | G75: OK | I75: Select * FROM (SELECT prtctn_id, DT_PRTCTN_VL, CASE WHEN prtctn_id LIKE 'P%' THEN '1111-11-11' ELSE max(dtrcaval) END AS DT_PRTCTN_VL_SIMULADO FROM (Select * From cd_loan_tapes_bce.lt004_protection WHERE segmento = 'ESTR' AND nome_perimetro ='Individual Corporativo' AND ref_date='${date}' AND AMBITO = 'PM') lt004 Left join (Select * From cd_garantias.gt018_rateio_aval Where ref_date='${date}') gt018 ON prtctn_id = concat(substr(TIPOLOGIA,1,1),'_',ckbalbem,'_',ckctabem,'_',ckrefbem) GROUP BY 1,2 ) A WHERE 1=1 AND substring(DT_PRTCTN_VL_SIMULADO,5,1) <> '-' or substring(DT_PRTCTN_VL_SIMULADO,8,1) <> '-' -- AND length(DT_PRTCTN_VL_SIMULADO) <> 10 -- AND DT_PRTCTN_VL_SIMULADO = '9999-99-99'
A76: PRTCTN | B76: DT_PRTCTN_VL | C76: Controlos | D76: "Date of protection value" must be later than 01 January 1970 | E76: 45482 | F76: 45443 | G76: OK | I76: Select * FROM (SELECT prtctn_id, DT_PRTCTN_VL, CASE WHEN prtctn_id LIKE 'P%' THEN '1111-11-11' ELSE max(dtrcaval) END AS DT_PRTCTN_VL_SIMULADO FROM (Select * From cd_loan_tapes_bce.lt004_protection WHERE segmento = 'ESTR' AND nome_perimetro ='Individual Corporativo' AND ref_date='${date}' AND AMBITO = 'PM') lt004 Left join (Select * From cd_garantias.gt018_rateio_aval Where ref_date='${date}') gt018 ON prtctn_id = concat(substr(TIPOLOGIA,1,1),'_',ckbalbem,'_',ckctabem,'_',ckrefbem) GROUP BY 1,2 ) A WHERE 1=1 AND dt_prtctn_vl < '1970-01-01' AND dt_prtctn_vl NOT IN ('1111-11-11','0000-00-00')
A77: PRTCTN | B77: DT_PRTCTN_VL | C77: Controlos | D77: In the case of protection items which are valued at their notional amount, the date of protection value is the reporting reference date. | E77: 45482 | F77: 45443 | G77: OK | H77: Com a alteração da fonte, os 2416 Casos NOK ficam OK | I77: Select * FROM (SELECT prtctn_id, TYP_PRTCTN_VL, DT_PRTCTN_VL, CASE WHEN prtctn_id LIKE 'P%' THEN '1111-11-11' ELSE max(dtrcaval) END AS DT_PRTCTN_VL_SIMULADO FROM (Select * From cd_loan_tapes_bce.lt004_protection WHERE segmento = 'ESTR' AND nome_perimetro ='Individual Corporativo' AND ref_date='${date}' AND AMBITO = 'PM') lt004 Left join (Select * From cd_garantias.gt018_rateio_aval Where ref_date='${date}') gt018 ON prtctn_id = concat(substr(TIPOLOGIA,1,1),'_',ckbalbem,'_',ckctabem,'_',ckrefbem) GROUP BY 1,2,3 ) A WHERE 1=1 AND TYP_PRTCTN_VL = '4' AND DT_PRTCTN_VL_SIMULADO <> '2024-05-31'
A78: PRTCTN | B78: DT_PRTCTN_VL | C78: Controlos | D78: "Date of protection value" cannot be later than "Reference date" | E78: 45482 | F78: 45443 | G78: OK | I78: Select * FROM (SELECT prtctn_id, DT_PRTCTN_VL, CASE WHEN prtctn_id LIKE 'P%' THEN '1111-11-11' ELSE max(dtrcaval) END AS DT_PRTCTN_VL_SIMULADO FROM (Select * From cd_loan_tapes_bce.lt004_protection WHERE segmento = 'ESTR' AND nome_perimetro ='Individual Corporativo' AND ref_date='${date}' AND AMBITO = 'PM') lt004 Left join (Select * From cd_garantias.gt018_rateio_aval Where ref_date='${date}') gt018 ON prtctn_id = concat(substr(TIPOLOGIA,1,1),'_',ckbalbem,'_',ckctabem,'_',ckrefbem) GROUP BY 1,2 ) A WHERE 1=1 AND DT_PRTCTN_VL_SIMULADO > '2024-05-31'
A79: PRTCTN | B79: DT_PRTCTN_VL | C79: Controlos | D79: "Date of protection value" must be later or equal than "Date of last full appraisal" | E79: 45482 | F79: 45443 | G79: OK | I79: Select * FROM (SELECT prtctn_id, DT_PRTCTN_VL, CASE WHEN prtctn_id LIKE 'P%' THEN '1111-11-11' ELSE max(dtrcaval) END AS DT_PRTCTN_VL_SIMULADO FROM (Select * From cd_loan_tapes_bce.lt004_protection WHERE segmento = 'ESTR' AND nome_perimetro ='Individual Corporativo' AND ref_date='${date}' AND AMBITO = 'PM') lt4 Left join (Select * From cd_garantias.gt018_rateio_aval Where ref_date='${date}') gt018 ON prtctn_id = concat(substr(TIPOLOGIA,1,1),'_',ckbalbem,'_',ckctabem,'_',ckrefbem) GROUP BY 1,2 ) A LEFT JOIN ------------- DT_LST_FLL_APPRSL ( SELECT LT004.prtctn_id, LT004.dt_lst_fll_apprsl as valor_lt, LT004.dt_orgnl_prtctn_vl, valor_simulado FROM (SELECT prtctn_id, dt_lst_fll_apprsl, dt_prtctn_vl, dt_orgnl_prtctn_vl FROM cd_loan_tapes_bce.lt004_protection WHERE ref_date='${date}' AND nome_perimetro='Individual Corporativo' AND segmento='ESTR' AND ambito='PM' AND prtctn_id LIKE 'I%') LT004 LEFT JOIN (SELECT max(davalia) as valor_simulado, CONCAT('I_', CKBALBEM, '_', CKCTABEM, '_', CKREFBEM) AS prtctn_id FROM cd_garantias.gt011_avalc_imov WHERE 1=1 AND ref_date='${date}' AND ( (CTIPREAVL = 'A' AND CORAVGP = 'G39') OR CORAVGP='G26') GROUP BY 2 ) GT011 ON LT004.prtctn_id = GT011.prtctn_id ) B ON A.prtctn_id = B.prtctn_id WHERE A.DT_PRTCTN_VL_SIMULADO < valor_simulado
A80: PRTCTN | B80: DT_PRTCTN_VL | C80: Controlos | D80: If "Previous appraisal date" is other than default values, then "Date of protection value" cannot be 'Not applicable' | E80: 45482 | F80: 45443 | G80: OK | I80: Select * FROM (SELECT prtctn_id, DT_PRTCTN_VL, CASE WHEN prtctn_id LIKE 'P%' THEN '1111-11-11' ELSE max(dtrcaval) END AS DT_PRTCTN_VL_SIMULADO FROM (Select * From cd_loan_tapes_bce.lt004_protection WHERE segmento = 'ESTR' AND nome_perimetro ='Individual Corporativo' AND ref_date='${date}' AND AMBITO = 'PM') lt4 Left join (Select * From cd_garantias.gt018_rateio_aval Where ref_date='${date}') gt018 ON prtctn_id = concat(substr(TIPOLOGIA,1,1),'_',ckbalbem,'_',ckctabem,'_',ckrefbem) GROUP BY 1,2 ) A LEFT JOIN -------------- DT_APPRSL_PRVS ----------------------- ( SELECT LT004.prtctn_id, dt_apprsl_prvs AS valor_lt, CASE WHEN prtctn_id NOT LIKE 'I%' THEN '1111-11-11' WHEN prtctn_id_GT011 IS NULL THEN '1111-11-11' -- garantia com apenas 1 avaliação completa WHEN prtctn_id_GT011 IS NOT NULL THEN davalia ELSE '0000-00-00' END AS valor_simulado FROM (SELECT prtctn_id, dt_apprsl_prvs, typ_prtctn FROM cd_loan_tapes_bce.lt004_protection WHERE ref_date='${date}' AND nome_perimetro='Individual Corporativo' AND segmento='ESTR' AND ambito='PM' ) LT004 LEFT JOIN (SELECT * FROM (SELECT *, RANK() OVER (PARTITION BY prtctn_id_GT011 ORDER BY davalia DESC) AS ranking FROM (SELECT DISTINCT CONCAT('I_', CKBALBEM, '_', CKCTABEM, '_', CKREFBEM) AS prtctn_id_GT011, davalia FROM cd_garantias.gt011_avalc_imov WHERE 1=1 AND ref_date='${date}' AND ( (CTIPREAVL = 'A' AND CORAVGP = 'G39') OR CORAVGP='G26') ) GT011 )GT011 WHERE ranking = 2 )GT011 ON LT004.prtctn_id = GT011.prtctn_id_GT011 ) B ON A.prtctn_id = B.prtctn_id WHERE 1=1 AND valor_simulado <> '1111-11-11' AND DT_PRTCTN_VL_SIMULADO = '1111-11-11'
A81: PRTCTN | B81: PRTCTN_VL | C81: Desenvolvimento | D81: Validar se campo está de acordo com o especificado | E81: 45482 | F81: 45443 | G81: OK | I81: Select * FROM (SELECT prtctn_id, sum(mavaliaa) as valor_simulado, prtctn_vl FROM (Select * From cd_loan_tapes_bce.lt004_protection WHERE segmento = 'ESTR' AND nome_perimetro ='Individual Corporativo' AND ref_date='${date}' AND AMBITO = 'PM') lt004 Left join (Select * From cd_garantias.gt018_rateio_aval Where ref_date='${date}') gt018 ON prtctn_id = concat(substr(TIPOLOGIA,1,1),'_',ckbalbem,'_',ckctabem,'_',ckrefbem) GROUP BY prtctn_id, prtctn_vl ) A Where valor_simulado <> Prtctn_vl
A82: PRTCTN | B82: PRTCTN_VL | C82: Controlos | D82: "Appraised market value" should have a Format numeric (2 decimal places) | E82: 45483 | F82: 45443 | G82: OK | I82: Select * FROM (SELECT prtctn_id, sum(mavaliaa) as valor_simulado, prtctn_vl FROM (Select * From cd_loan_tapes_bce.lt004_protection WHERE segmento = 'ESTR' AND nome_perimetro ='Individual Corporativo' AND ref_date='${date}' AND AMBITO = 'PM') lt004 Left join (Select * From cd_garantias.gt018_rateio_aval Where ref_date='${date}') gt018 ON prtctn_id = concat(substr(TIPOLOGIA,1,1),'_',ckbalbem,'_',ckctabem,'_',ckrefbem) GROUP BY prtctn_id, prtctn_vl ) A Where cast(valor_simulado as VARCHAR) NOT LIKE '%.__'
A83: PRTCTN | B83: PRTCTN_VL | C83: Controlos | D83: "Appraised market value" shall be larger or equal to 0; Negative values trigger attention | E83: 45483 | F83: 45443 | G83: OK | I83: Select * FROM (SELECT prtctn_id, sum(mavaliaa) as valor_simulado, prtctn_vl FROM (Select * From cd_loan_tapes_bce.lt004_protection WHERE segmento = 'ESTR' AND nome_perimetro ='Individual Corporativo' AND ref_date='${date}' AND AMBITO = 'PM') lt004 Left join (Select * From cd_garantias.gt018_rateio_aval Where ref_date='${date}') gt018 ON prtctn_id = concat(substr(TIPOLOGIA,1,1),'_',ckbalbem,'_',ckctabem,'_',ckrefbem) GROUP BY prtctn_id, prtctn_vl ) A Where valor_simulado < 0
A84: PRTCTN | B84: PRTCTN_VL | C84: Controlos | D84: The amount of "Appraised market value" must be greater or equal than the amount of "Protection allocated value" | E84: 45483 | F84: 45443 | G84: OK | I84: Select * FROM (SELECT prtctn_id, sum(mavaliaa) as valor_simulado, prtctn_vl FROM (Select * From cd_loan_tapes_bce.lt004_protection WHERE segmento = 'ESTR' AND nome_perimetro ='Individual Corporativo' AND ref_date='${date}' AND AMBITO = 'PM') lt004 Left join (Select * From cd_garantias.gt018_rateio_aval Where ref_date='${date}') gt018 ON prtctn_id = concat(substr(TIPOLOGIA,1,1),'_',ckbalbem,'_',ckctabem,'_',ckrefbem) GROUP BY prtctn_id, prtctn_vl ) A LEFT JOIN (Select prtctn_id, prtctn_allctd_vl From cd_loan_tapes_bce.lt006_instr_prot WHERE segmento = 'ESTR' AND nome_perimetro ='Individual Corporativo' AND ref_date='${date}' AND AMBITO = 'PM') lt006 ON A.prtctn_id=lt006.prtctn_id Where valor_simulado < prtctn_allctd_vl
A85: PRTCTN | B85: PRTCTN_VL | C85: Controlos | D85: If "Date of protection value" is other than 'Not applicable', then "Appraised market value" cannot be 'Not applicable' or zero | E85: 45483 | F85: 45443 | G85: NOK | H85: 44 garantias em DT_PRTCTN_VL não é N/A e PRTCTN_VL é zero. | I85: Select * FROM (SELECT prtctn_id, sum(mavaliaa) as valor_simulado, prtctn_vl, DT_PRTCTN_VL, CASE WHEN prtctn_id LIKE 'P%' THEN '1111-11-11' ELSE soma_dtrcaval END AS DT_PRTCTN_VL_SIMULADO FROM (Select * From cd_loan_tapes_bce.lt004_protection WHERE segmento = 'ESTR' AND nome_perimetro ='Individual Corporativo' AND ref_date='${date}' AND AMBITO = 'PM') lt004 Left join (Select ckbalbem, ckctabem, ckrefbem, mavaliaa, tipologia, max(dtrcaval) as soma_dtrcaval From cd_garantias.gt018_rateio_aval Where ref_date='${date}' GROUP BY 1,2,3,4,5 ) gt018 ON prtctn_id = concat(substr(TIPOLOGIA,1,1),'_',ckbalbem,'_',ckctabem,'_',ckrefbem) GROUP BY prtctn_id, prtctn_vl, DT_PRTCTN_VL, DT_PRTCTN_VL_SIMULADO ) A WHERE 1=1 AND DT_PRTCTN_VL_SIMULADO <> '1111-11-11' AND valor_simulado in (11111111111,0)
A86: PRTCTN | B86: PRTCTN_VL | C86: Controlos | D86: The amount of "Appraised market value" must be greater or equal than the sum of amount of "Protection allocated value" of all the instruments that share the same protection | E86: 45489 | F86: 45443 | G86: OK | I86: Select * FROM (SELECT prtctn_id, sum(mavaliaa) as valor_simulado, prtctn_vl FROM (Select * From cd_loan_tapes_bce.lt004_protection WHERE segmento = 'ESTR' AND nome_perimetro ='Individual Corporativo' AND ref_date='${date}' AND AMBITO = 'PM') lt004 Left join (Select * From cd_garantias.gt018_rateio_aval Where ref_date='${date}') gt018 ON prtctn_id = concat(substr(TIPOLOGIA,1,1),'_',ckbalbem,'_',ckctabem,'_',ckrefbem) GROUP BY prtctn_id, prtctn_vl ) A LEFT JOIN (Select prtctn_id, sum(prtctn_allctd_vl) as prtctn_allctd_vl From cd_loan_tapes_bce.lt006_instr_prot WHERE segmento = 'ESTR' AND nome_perimetro ='Individual Corporativo' AND ref_date='${date}' AND AMBITO = 'PM' GROUP BY 1 ) lt006 ON A.prtctn_id=lt006.prtctn_id Where valor_simulado < prtctn_allctd_vl
A87: PRTCTN | B87: PRTCTN_VL | C87: Controlos | D87: If the protection is a "personal guarantee" then "Appraised market value" cannot be 'Not applicable' (We consider "personal guarantee" when "Protection ID" matches the "Protection Provider ID" (Guarantor) or "Tax ID" (Protection level) is populated other than default value and the "Protection type" equals '7 - Other protection') | E87: 45483 | F87: 45443 | G87: OK | I87: Select * FROM (SELECT prtctn_id, sum(mavaliaa) as valor_simulado, prtctn_vl FROM (Select * From cd_loan_tapes_bce.lt004_protection WHERE segmento = 'ESTR' AND nome_perimetro ='Individual Corporativo' AND ref_date='${date}' AND AMBITO = 'PM') lt004 Left join (Select * From cd_garantias.gt018_rateio_aval Where ref_date='${date}') gt018 ON prtctn_id = concat(substr(TIPOLOGIA,1,1),'_',ckbalbem,'_',ckctabem,'_',ckrefbem) GROUP BY prtctn_id, prtctn_vl ) A Where prtctn_id like 'P%' And valor_simulado = 11111111111
A88: PRTCTN | B88: NTNL_ID | C88: Desenvolvimento | D88: Incidência | E88: 45484 | F88: 45443 | G88: NOK | H88: 181 casos com aspas | I88: SELECT count(*) FROM cd_loan_tapes_bce.lt004_protection WHERE 1=1 AND ambito = 'PM' AND segmento = 'ESTR' AND ref_date = '2024-05-31' AND nome_perimetro = 'Individual Corporativo' AND ntnl_id LIKE '%"%' -- AND ntnl_id LIKE '%F%'
A89: INSTRMNT | B89: IFRS9_BHVRL_MTRTY | C89: Controlos | D89: "Behavioural maturity" should have a Format numeric (0 decimal places) | E89: 45495 | F89: 45443 | G89: OK | I89: Select instrmnt_id, Case when IFRS9.contract_id IS NULL Then 11111111111 Else cast(months_to_maturity as INT) END as IFRS9_BHVRL_MTRTY_Simulado From (SELECT instrmnt_id FROM cd_loan_tapes_bce.lt002_instrument WHERE segmento = 'ESTR' AND nome_perimetro ='Individual Corporativo' AND ref_date='${date}' AND AMBITO = 'PM') LT002 LEFT JOIN (select cempresa_fr, cbalcao_fr, cnumecta_fr, zdeposit_fr, cempresa, cbalcao, cnumecta, zdeposit From cd_captools.kt_chaves_finrep Where ref_date='${date}') CHFIN ON LT002.instrmnt_id = Concat(CHFIN.cempresa_fr, CHFIN.cbalcao_fr, CHFIN.cnumecta_fr, CHFIN.zdeposit_fr) LEFT JOIN (select contract_id, cempresa, cbalcao, cnumecta, zdeposit From cd_captools.kt_chaves_ifrs9 Where ref_date='${date}') CHIFR ON Concat(CHFIN.cempresa, CHFIN.cbalcao, CHFIN.cnumecta, CHFIN.zdeposit) = Concat(CHIFR.cempresa, CHIFR.cbalcao, CHIFR.cnumecta, CHIFR.zdeposit) LEFT JOIN (select contract_id, months_to_maturity From bu_ifrs9.IFRS9_OUT_EXPECTED_LOSS_REPORTING WHERE exec_id_part IN (SELECT exec_id_part FROM cd_captools.imcatf046_flag_fecho WHERE CMES = '${CMES}') )IFRS9 ON CHIFR.contract_id=IFRS9.contract_id Having cast(IFRS9_BHVRL_MTRTY_Simulado as VARCHAR) LIKE '%.'
A90: INSTRMNT | B90: IFRS9_BHVRL_MTRTY | C90: Controlos | D90: "Behavioural maturity" shall be larger or equal to 0 and less than 960; Negative values trigger attention | E90: 45495 | F90: 45443 | G90: OK | H90: Dois casos em que a Maturidade é superior a 960 meses (1000 e 2162) | I90: Select instrmnt_id, Case when IFRS9.contract_id IS NULL Then 11111111111 Else cast(months_to_maturity as INT) END as IFRS9_BHVRL_MTRTY_Simulado From (SELECT instrmnt_id FROM cd_loan_tapes_bce.lt002_instrument WHERE segmento = 'ESTR' AND nome_perimetro ='Individual Corporativo' AND ref_date='${date}' AND AMBITO = 'PM') LT002 LEFT JOIN (select cempresa_fr, cbalcao_fr, cnumecta_fr, zdeposit_fr, cempresa, cbalcao, cnumecta, zdeposit From cd_captools.kt_chaves_finrep Where ref_date='${date}') CHFIN ON LT002.instrmnt_id = Concat(CHFIN.cempresa_fr, CHFIN.cbalcao_fr, CHFIN.cnumecta_fr, CHFIN.zdeposit_fr) LEFT JOIN (select contract_id, cempresa, cbalcao, cnumecta, zdeposit From cd_captools.kt_chaves_ifrs9 Where ref_date='${date}') CHIFR ON Concat(CHFIN.cempresa, CHFIN.cbalcao, CHFIN.cnumecta, CHFIN.zdeposit) = Concat(CHIFR.cempresa, CHIFR.cbalcao, CHIFR.cnumecta, CHIFR.zdeposit) LEFT JOIN (select contract_id, months_to_maturity From bu_ifrs9.IFRS9_OUT_EXPECTED_LOSS_REPORTING WHERE exec_id_part IN (SELECT exec_id_part FROM cd_captools.imcatf046_flag_fecho WHERE CMES = '${CMES}') )IFRS9 ON CHIFR.contract_id=IFRS9.contract_id Having (IFRS9_BHVRL_MTRTY_Simulado > 960 OR IFRS9_BHVRL_MTRTY_Simulado < 0) AND IFRS9_BHVRL_MTRTY_Simulado <> 11111111111
