Workbook

Sheet 1. Status Resumo
B6: Sumário Executivo |06 de dezembro a 13 de dezembro
B8: - Concluída a Tabela de Certificados do Modelo de Bens Imóveis - Concluídos 14 campos da Tabela de Clientes do Modelo Verde - Concluídos 10 campos da Loan Tape Pilar III
B13: 1. Visão Geral
C16: Resumo | H16: Detalhe por Tabela | P16: Status (campos) | T16: 45625 | U16: =T16+7 -> 45632 | V16: ∆ | X16: Highlights
P17: 0. Cancelado | T17: =COUNTIFS('2. Status Detalhe Campos'!$H$7:$H$574,'1. Status Resumo'!$P63,'2. Status Detalhe Campos'!$C$7:$C$574,'1. Status Resumo'!$G$59,'2. Status Detalhe Campos'!$D$7:$D$574,"2. Campo")+COUNTIFS('2. Status Detalhe Campos'!$H$7:$H$574,'1. Status Resumo'!$P63,'2. Status Detalhe Campos'!$C$7:$C$574,'1. Status Resumo'!$H$59,'2. Status Detalhe Campos'!$D$7:$D$574,"2. Campo")+COUNTIFS('2. Status Detalhe Campos'!$H$7:$H$574,'1. Status Resumo'!$P87,'2. Status Detalhe Campos'!$C$7:$C$574,'1. Status Resumo'!$G$83,'2. Status Detalhe Campos'!$D$7:$D$574,"2. Campo")+COUNTIFS('2. Status Detalhe Campos'!$H$7:$H$574,'1. Status Resumo'!$P87,'2. Status Detalhe Campos'!$C$7:$C$574,'1. Status Resumo'!$H$83,'2. Status Detalhe Campos'!$D$7:$D$574,"2. Campo")+COUNTIFS(Table4[Status Anterior],'1. Status Resumo'!$P122,Table4[Sub-âmbito],'1. Status Resumo'!$G$118,Table4[Tipo de teste],"2. Campo") -> 24 | U17: =COUNTIFS('2. Status Detalhe Campos'!$G$7:$G$574,'1. Status Resumo'!$P63,'2. Status Detalhe Campos'!$C$7:$C$574,'1. Status Resumo'!$G$59,'2. Status Detalhe Campos'!$D$7:$D$574,"2. Campo")+COUNTIFS('2. Status Detalhe Campos'!$G$7:$G$574,'1. Status Resumo'!$P63,'2. Status Detalhe Campos'!$C$7:$C$574,'1. Status Resumo'!$H$59,'2. Status Detalhe Campos'!$D$7:$D$574,"2. Campo")+COUNTIFS('2. Status Detalhe Campos'!$G$7:$G$574,'1. Status Resumo'!$P87,'2. Status Detalhe Campos'!$C$7:$C$574,'1. Status Resumo'!$G$83,'2. Status Detalhe Campos'!$D$7:$D$574,"2. Campo")+COUNTIFS('2. Status Detalhe Campos'!$G$7:$G$574,'1. Status Resumo'!$P87,'2. Status Detalhe Campos'!$C$7:$C$574,'1. Status Resumo'!$H$83,'2. Status Detalhe Campos'!$D$7:$D$574,"2. Campo")+COUNTIFS(Table4[Status Atual],'1. Status Resumo'!$P122,Table4[Sub-âmbito],'1. Status Resumo'!$G$118,Table4[Tipo de teste],"2. Campo") -> 20 | V17: =U17-T17 -> -4
P18: 1. Concluído | T18: =COUNTIFS('2. Status Detalhe Campos'!$H$7:$H$574,'1. Status Resumo'!$P64,'2. Status Detalhe Campos'!$C$7:$C$574,'1. Status Resumo'!$G$59,'2. Status Detalhe Campos'!$D$7:$D$574,"2. Campo")+COUNTIFS('2. Status Detalhe Campos'!$H$7:$H$574,'1. Status Resumo'!$P64,'2. Status Detalhe Campos'!$C$7:$C$574,'1. Status Resumo'!$H$59,'2. Status Detalhe Campos'!$D$7:$D$574,"2. Campo")+COUNTIFS('2. Status Detalhe Campos'!$H$7:$H$574,'1. Status Resumo'!$P88,'2. Status Detalhe Campos'!$C$7:$C$574,'1. Status Resumo'!$G$83,'2. Status Detalhe Campos'!$D$7:$D$574,"2. Campo")+COUNTIFS('2. Status Detalhe Campos'!$H$7:$H$574,'1. Status Resumo'!$P88,'2. Status Detalhe Campos'!$C$7:$C$574,'1. Status Resumo'!$H$83,'2. Status Detalhe Campos'!$D$7:$D$574,"2. Campo")+COUNTIFS(Table4[Status Anterior],'1. Status Resumo'!$P123,Table4[Sub-âmbito],'1. Status Resumo'!$G$118,Table4[Tipo de teste],"2. Campo") -> 401 | U18: =COUNTIFS('2. Status Detalhe Campos'!$G$7:$G$574,'1. Status Resumo'!$P64,'2. Status Detalhe Campos'!$C$7:$C$574,'1. Status Resumo'!$G$59,'2. Status Detalhe Campos'!$D$7:$D$574,"2. Campo")+COUNTIFS('2. Status Detalhe Campos'!$G$7:$G$574,'1. Status Resumo'!$P64,'2. Status Detalhe Campos'!$C$7:$C$574,'1. Status Resumo'!$H$59,'2. Status Detalhe Campos'!$D$7:$D$574,"2. Campo")+COUNTIFS('2. Status Detalhe Campos'!$G$7:$G$574,'1. Status Resumo'!$P88,'2. Status Detalhe Campos'!$C$7:$C$574,'1. Status Resumo'!$G$83,'2. Status Detalhe Campos'!$D$7:$D$574,"2. Campo")+COUNTIFS('2. Status Detalhe Campos'!$G$7:$G$574,'1. Status Resumo'!$P88,'2. Status Detalhe Campos'!$C$7:$C$574,'1. Status Resumo'!$H$83,'2. Status Detalhe Campos'!$D$7:$D$574,"2. Campo")+COUNTIFS(Table4[Status Atual],'1. Status Resumo'!$P123,Table4[Sub-âmbito],'1. Status Resumo'!$G$118,Table4[Tipo de teste],"2. Campo") -> 435 | V18: =U18-T18 -> 34
P19: 2.1 Em Teste | T19: =COUNTIFS('2. Status Detalhe Campos'!$H$7:$H$574,'1. Status Resumo'!$P65,'2. Status Detalhe Campos'!$C$7:$C$574,'1. Status Resumo'!$G$59,'2. Status Detalhe Campos'!$D$7:$D$574,"2. Campo")+COUNTIFS('2. Status Detalhe Campos'!$H$7:$H$574,'1. Status Resumo'!$P65,'2. Status Detalhe Campos'!$C$7:$C$574,'1. Status Resumo'!$H$59,'2. Status Detalhe Campos'!$D$7:$D$574,"2. Campo")+COUNTIFS('2. Status Detalhe Campos'!$H$7:$H$574,'1. Status Resumo'!$P89,'2. Status Detalhe Campos'!$C$7:$C$574,'1. Status Resumo'!$G$83,'2. Status Detalhe Campos'!$D$7:$D$574,"2. Campo")+COUNTIFS('2. Status Detalhe Campos'!$H$7:$H$574,'1. Status Resumo'!$P89,'2. Status Detalhe Campos'!$C$7:$C$574,'1. Status Resumo'!$H$83,'2. Status Detalhe Campos'!$D$7:$D$574,"2. Campo")+COUNTIFS(Table4[Status Anterior],'1. Status Resumo'!$P124,Table4[Sub-âmbito],'1. Status Resumo'!$G$118,Table4[Tipo de teste],"2. Campo") -> 58 | U19: =COUNTIFS('2. Status Detalhe Campos'!$G$7:$G$574,'1. Status Resumo'!$P65,'2. Status Detalhe Campos'!$C$7:$C$574,'1. Status Resumo'!$G$59,'2. Status Detalhe Campos'!$D$7:$D$574,"2. Campo")+COUNTIFS('2. Status Detalhe Campos'!$G$7:$G$574,'1. Status Resumo'!$P65,'2. Status Detalhe Campos'!$C$7:$C$574,'1. Status Resumo'!$H$59,'2. Status Detalhe Campos'!$D$7:$D$574,"2. Campo")+COUNTIFS('2. Status Detalhe Campos'!$G$7:$G$574,'1. Status Resumo'!$P89,'2. Status Detalhe Campos'!$C$7:$C$574,'1. Status Resumo'!$G$83,'2. Status Detalhe Campos'!$D$7:$D$574,"2. Campo")+COUNTIFS('2. Status Detalhe Campos'!$G$7:$G$574,'1. Status Resumo'!$P89,'2. Status Detalhe Campos'!$C$7:$C$574,'1. Status Resumo'!$H$83,'2. Status Detalhe Campos'!$D$7:$D$574,"2. Campo")+COUNTIFS(Table4[Status Atual],'1. Status Resumo'!$P124,Table4[Sub-âmbito],'1. Status Resumo'!$G$118,Table4[Tipo de teste],"2. Campo") -> 53 | V19: =U19-T19 -> -5
P20: 2.2 Em Re-especificação | T20: =COUNTIFS('2. Status Detalhe Campos'!$H$7:$H$574,'1. Status Resumo'!$P66,'2. Status Detalhe Campos'!$C$7:$C$574,'1. Status Resumo'!$G$59,'2. Status Detalhe Campos'!$D$7:$D$574,"2. Campo")+COUNTIFS('2. Status Detalhe Campos'!$H$7:$H$574,'1. Status Resumo'!$P66,'2. Status Detalhe Campos'!$C$7:$C$574,'1. Status Resumo'!$H$59,'2. Status Detalhe Campos'!$D$7:$D$574,"2. Campo")+COUNTIFS('2. Status Detalhe Campos'!$H$7:$H$574,'1. Status Resumo'!$P90,'2. Status Detalhe Campos'!$C$7:$C$574,'1. Status Resumo'!$G$83,'2. Status Detalhe Campos'!$D$7:$D$574,"2. Campo")+COUNTIFS('2. Status Detalhe Campos'!$H$7:$H$574,'1. Status Resumo'!$P90,'2. Status Detalhe Campos'!$C$7:$C$574,'1. Status Resumo'!$H$83,'2. Status Detalhe Campos'!$D$7:$D$574,"2. Campo")+COUNTIFS(Table4[Status Anterior],'1. Status Resumo'!$P125,Table4[Sub-âmbito],'1. Status Resumo'!$G$118,Table4[Tipo de teste],"2. Campo") -> 0 | U20: =COUNTIFS('2. Status Detalhe Campos'!$G$7:$G$574,'1. Status Resumo'!$P66,'2. Status Detalhe Campos'!$C$7:$C$574,'1. Status Resumo'!$G$59,'2. Status Detalhe Campos'!$D$7:$D$574,"2. Campo")+COUNTIFS('2. Status Detalhe Campos'!$G$7:$G$574,'1. Status Resumo'!$P66,'2. Status Detalhe Campos'!$C$7:$C$574,'1. Status Resumo'!$H$59,'2. Status Detalhe Campos'!$D$7:$D$574,"2. Campo")+COUNTIFS('2. Status Detalhe Campos'!$G$7:$G$574,'1. Status Resumo'!$P90,'2. Status Detalhe Campos'!$C$7:$C$574,'1. Status Resumo'!$G$83,'2. Status Detalhe Campos'!$D$7:$D$574,"2. Campo")+COUNTIFS('2. Status Detalhe Campos'!$G$7:$G$574,'1. Status Resumo'!$P90,'2. Status Detalhe Campos'!$C$7:$C$574,'1. Status Resumo'!$H$83,'2. Status Detalhe Campos'!$D$7:$D$574,"2. Campo")+COUNTIFS(Table4[Status Atual],'1. Status Resumo'!$P125,Table4[Sub-âmbito],'1. Status Resumo'!$G$118,Table4[Tipo de teste],"2. Campo") -> 0 | V20: =U20-T20 -> 0
P21: 3. Pendente de outros desenvolvimentos | T21: =COUNTIFS('2. Status Detalhe Campos'!$H$7:$H$574,'1. Status Resumo'!$P67,'2. Status Detalhe Campos'!$C$7:$C$574,'1. Status Resumo'!$G$59,'2. Status Detalhe Campos'!$D$7:$D$574,"2. Campo")+COUNTIFS('2. Status Detalhe Campos'!$H$7:$H$574,'1. Status Resumo'!$P67,'2. Status Detalhe Campos'!$C$7:$C$574,'1. Status Resumo'!$H$59,'2. Status Detalhe Campos'!$D$7:$D$574,"2. Campo")+COUNTIFS('2. Status Detalhe Campos'!$H$7:$H$574,'1. Status Resumo'!$P91,'2. Status Detalhe Campos'!$C$7:$C$574,'1. Status Resumo'!$G$83,'2. Status Detalhe Campos'!$D$7:$D$574,"2. Campo")+COUNTIFS('2. Status Detalhe Campos'!$H$7:$H$574,'1. Status Resumo'!$P91,'2. Status Detalhe Campos'!$C$7:$C$574,'1. Status Resumo'!$H$83,'2. Status Detalhe Campos'!$D$7:$D$574,"2. Campo")+COUNTIFS(Table4[Status Anterior],'1. Status Resumo'!$P126,Table4[Sub-âmbito],'1. Status Resumo'!$G$118,Table4[Tipo de teste],"2. Campo") -> 4 | U21: =COUNTIFS('2. Status Detalhe Campos'!$G$7:$G$574,'1. Status Resumo'!$P67,'2. Status Detalhe Campos'!$C$7:$C$574,'1. Status Resumo'!$G$59,'2. Status Detalhe Campos'!$D$7:$D$574,"2. Campo")+COUNTIFS('2. Status Detalhe Campos'!$G$7:$G$574,'1. Status Resumo'!$P67,'2. Status Detalhe Campos'!$C$7:$C$574,'1. Status Resumo'!$H$59,'2. Status Detalhe Campos'!$D$7:$D$574,"2. Campo")+COUNTIFS('2. Status Detalhe Campos'!$G$7:$G$574,'1. Status Resumo'!$P91,'2. Status Detalhe Campos'!$C$7:$C$574,'1. Status Resumo'!$G$83,'2. Status Detalhe Campos'!$D$7:$D$574,"2. Campo")+COUNTIFS('2. Status Detalhe Campos'!$G$7:$G$574,'1. Status Resumo'!$P91,'2. Status Detalhe Campos'!$C$7:$C$574,'1. Status Resumo'!$H$83,'2. Status Detalhe Campos'!$D$7:$D$574,"2. Campo")+COUNTIFS(Table4[Status Atual],'1. Status Resumo'!$P126,Table4[Sub-âmbito],'1. Status Resumo'!$G$118,Table4[Tipo de teste],"2. Campo") -> 2 | V21: =U21-T21 -> -2
P22: 4. Validação EF | T22: =COUNTIFS('2. Status Detalhe Campos'!$H$7:$H$574,'1. Status Resumo'!$P68,'2. Status Detalhe Campos'!$C$7:$C$574,'1. Status Resumo'!$G$59,'2. Status Detalhe Campos'!$D$7:$D$574,"2. Campo")+COUNTIFS('2. Status Detalhe Campos'!$H$7:$H$574,'1. Status Resumo'!$P68,'2. Status Detalhe Campos'!$C$7:$C$574,'1. Status Resumo'!$H$59,'2. Status Detalhe Campos'!$D$7:$D$574,"2. Campo")+COUNTIFS('2. Status Detalhe Campos'!$H$7:$H$574,'1. Status Resumo'!$P92,'2. Status Detalhe Campos'!$C$7:$C$574,'1. Status Resumo'!$G$83,'2. Status Detalhe Campos'!$D$7:$D$574,"2. Campo")+COUNTIFS('2. Status Detalhe Campos'!$H$7:$H$574,'1. Status Resumo'!$P92,'2. Status Detalhe Campos'!$C$7:$C$574,'1. Status Resumo'!$H$83,'2. Status Detalhe Campos'!$D$7:$D$574,"2. Campo")+COUNTIFS(Table4[Status Anterior],'1. Status Resumo'!$P127,Table4[Sub-âmbito],'1. Status Resumo'!$G$118,Table4[Tipo de teste],"2. Campo") -> 1 | U22: =COUNTIFS('2. Status Detalhe Campos'!$G$7:$G$574,'1. Status Resumo'!$P68,'2. Status Detalhe Campos'!$C$7:$C$574,'1. Status Resumo'!$G$59,'2. Status Detalhe Campos'!$D$7:$D$574,"2. Campo")+COUNTIFS('2. Status Detalhe Campos'!$G$7:$G$574,'1. Status Resumo'!$P68,'2. Status Detalhe Campos'!$C$7:$C$574,'1. Status Resumo'!$H$59,'2. Status Detalhe Campos'!$D$7:$D$574,"2. Campo")+COUNTIFS('2. Status Detalhe Campos'!$G$7:$G$574,'1. Status Resumo'!$P92,'2. Status Detalhe Campos'!$C$7:$C$574,'1. Status Resumo'!$G$83,'2. Status Detalhe Campos'!$D$7:$D$574,"2. Campo")+COUNTIFS('2. Status Detalhe Campos'!$G$7:$G$574,'1. Status Resumo'!$P92,'2. Status Detalhe Campos'!$C$7:$C$574,'1. Status Resumo'!$H$83,'2. Status Detalhe Campos'!$D$7:$D$574,"2. Campo")+COUNTIFS(Table4[Status Atual],'1. Status Resumo'!$P127,Table4[Sub-âmbito],'1. Status Resumo'!$G$118,Table4[Tipo de teste],"2. Campo") -> 2 | V22: =U22-T22 -> 1
P23: 5. Em Correção | R23: (incidências) | T23: =COUNTIFS('2. Status Detalhe Campos'!$H$7:$H$574,'1. Status Resumo'!$P69,'2. Status Detalhe Campos'!$C$7:$C$574,'1. Status Resumo'!$G$59,'2. Status Detalhe Campos'!$D$7:$D$574,"2. Campo")+COUNTIFS('2. Status Detalhe Campos'!$H$7:$H$574,'1. Status Resumo'!$P69,'2. Status Detalhe Campos'!$C$7:$C$574,'1. Status Resumo'!$H$59,'2. Status Detalhe Campos'!$D$7:$D$574,"2. Campo")+COUNTIFS('2. Status Detalhe Campos'!$H$7:$H$574,'1. Status Resumo'!$P93,'2. Status Detalhe Campos'!$C$7:$C$574,'1. Status Resumo'!$G$83,'2. Status Detalhe Campos'!$D$7:$D$574,"2. Campo")+COUNTIFS('2. Status Detalhe Campos'!$H$7:$H$574,'1. Status Resumo'!$P93,'2. Status Detalhe Campos'!$C$7:$C$574,'1. Status Resumo'!$H$83,'2. Status Detalhe Campos'!$D$7:$D$574,"2. Campo")+COUNTIFS(Table4[Status Anterior],'1. Status Resumo'!$P128,Table4[Sub-âmbito],'1. Status Resumo'!$G$118,Table4[Tipo de teste],"2. Campo") -> 19 | U23: =COUNTIFS('2. Status Detalhe Campos'!$G$7:$G$574,'1. Status Resumo'!$P69,'2. Status Detalhe Campos'!$C$7:$C$574,'1. Status Resumo'!$G$59,'2. Status Detalhe Campos'!$D$7:$D$574,"2. Campo")+COUNTIFS('2. Status Detalhe Campos'!$G$7:$G$574,'1. Status Resumo'!$P69,'2. Status Detalhe Campos'!$C$7:$C$574,'1. Status Resumo'!$H$59,'2. Status Detalhe Campos'!$D$7:$D$574,"2. Campo")+COUNTIFS('2. Status Detalhe Campos'!$G$7:$G$574,'1. Status Resumo'!$P93,'2. Status Detalhe Campos'!$C$7:$C$574,'1. Status Resumo'!$G$83,'2. Status Detalhe Campos'!$D$7:$D$574,"2. Campo")+COUNTIFS('2. Status Detalhe Campos'!$G$7:$G$574,'1. Status Resumo'!$P93,'2. Status Detalhe Campos'!$C$7:$C$574,'1. Status Resumo'!$H$83,'2. Status Detalhe Campos'!$D$7:$D$574,"2. Campo")+COUNTIFS(Table4[Status Atual],'1. Status Resumo'!$P128,Table4[Sub-âmbito],'1. Status Resumo'!$G$118,Table4[Tipo de teste],"2. Campo") -> 5 | V23: =U23-T23 -> -14
P24: 6. Em implementação (re-especificação) | T24: =COUNTIFS('2. Status Detalhe Campos'!$H$7:$H$574,'1. Status Resumo'!$P70,'2. Status Detalhe Campos'!$C$7:$C$574,'1. Status Resumo'!$G$59,'2. Status Detalhe Campos'!$D$7:$D$574,"2. Campo")+COUNTIFS('2. Status Detalhe Campos'!$H$7:$H$574,'1. Status Resumo'!$P70,'2. Status Detalhe Campos'!$C$7:$C$574,'1. Status Resumo'!$H$59,'2. Status Detalhe Campos'!$D$7:$D$574,"2. Campo")+COUNTIFS('2. Status Detalhe Campos'!$H$7:$H$574,'1. Status Resumo'!$P94,'2. Status Detalhe Campos'!$C$7:$C$574,'1. Status Resumo'!$G$83,'2. Status Detalhe Campos'!$D$7:$D$574,"2. Campo")+COUNTIFS('2. Status Detalhe Campos'!$H$7:$H$574,'1. Status Resumo'!$P94,'2. Status Detalhe Campos'!$C$7:$C$574,'1. Status Resumo'!$H$83,'2. Status Detalhe Campos'!$D$7:$D$574,"2. Campo")+COUNTIFS(Table4[Status Anterior],'1. Status Resumo'!$P129,Table4[Sub-âmbito],'1. Status Resumo'!$G$118,Table4[Tipo de teste],"2. Campo") -> 42 | U24: =COUNTIFS('2. Status Detalhe Campos'!$G$7:$G$574,'1. Status Resumo'!$P70,'2. Status Detalhe Campos'!$C$7:$C$574,'1. Status Resumo'!$G$59,'2. Status Detalhe Campos'!$D$7:$D$574,"2. Campo")+COUNTIFS('2. Status Detalhe Campos'!$G$7:$G$574,'1. Status Resumo'!$P70,'2. Status Detalhe Campos'!$C$7:$C$574,'1. Status Resumo'!$H$59,'2. Status Detalhe Campos'!$D$7:$D$574,"2. Campo")+COUNTIFS('2. Status Detalhe Campos'!$G$7:$G$574,'1. Status Resumo'!$P94,'2. Status Detalhe Campos'!$C$7:$C$574,'1. Status Resumo'!$G$83,'2. Status Detalhe Campos'!$D$7:$D$574,"2. Campo")+COUNTIFS('2. Status Detalhe Campos'!$G$7:$G$574,'1. Status Resumo'!$P94,'2. Status Detalhe Campos'!$C$7:$C$574,'1. Status Resumo'!$H$83,'2. Status Detalhe Campos'!$D$7:$D$574,"2. Campo")+COUNTIFS(Table4[Status Atual],'1. Status Resumo'!$P129,Table4[Sub-âmbito],'1. Status Resumo'!$G$118,Table4[Tipo de teste],"2. Campo") -> 4 | V24: =U24-T24 -> -38
P25: 7. Por iniciar | T25: =COUNTIFS('2. Status Detalhe Campos'!$H$7:$H$574,'1. Status Resumo'!$P71,'2. Status Detalhe Campos'!$C$7:$C$574,'1. Status Resumo'!$G$59,'2. Status Detalhe Campos'!$D$7:$D$574,"2. Campo")+COUNTIFS('2. Status Detalhe Campos'!$H$7:$H$574,'1. Status Resumo'!$P71,'2. Status Detalhe Campos'!$C$7:$C$574,'1. Status Resumo'!$H$59,'2. Status Detalhe Campos'!$D$7:$D$574,"2. Campo")+COUNTIFS('2. Status Detalhe Campos'!$H$7:$H$574,'1. Status Resumo'!$P95,'2. Status Detalhe Campos'!$C$7:$C$574,'1. Status Resumo'!$G$83,'2. Status Detalhe Campos'!$D$7:$D$574,"2. Campo")+COUNTIFS('2. Status Detalhe Campos'!$H$7:$H$574,'1. Status Resumo'!$P95,'2. Status Detalhe Campos'!$C$7:$C$574,'1. Status Resumo'!$H$83,'2. Status Detalhe Campos'!$D$7:$D$574,"2. Campo")+COUNTIFS(Table4[Status Anterior],'1. Status Resumo'!$P130,Table4[Sub-âmbito],'1. Status Resumo'!$G$118,Table4[Tipo de teste],"2. Campo") -> 0 | U25: =COUNTIFS('2. Status Detalhe Campos'!$G$7:$G$574,'1. Status Resumo'!$P71,'2. Status Detalhe Campos'!$C$7:$C$574,'1. Status Resumo'!$G$59,'2. Status Detalhe Campos'!$D$7:$D$574,"2. Campo")+COUNTIFS('2. Status Detalhe Campos'!$G$7:$G$574,'1. Status Resumo'!$P71,'2. Status Detalhe Campos'!$C$7:$C$574,'1. Status Resumo'!$H$59,'2. Status Detalhe Campos'!$D$7:$D$574,"2. Campo")+COUNTIFS('2. Status Detalhe Campos'!$G$7:$G$574,'1. Status Resumo'!$P95,'2. Status Detalhe Campos'!$C$7:$C$574,'1. Status Resumo'!$G$83,'2. Status Detalhe Campos'!$D$7:$D$574,"2. Campo")+COUNTIFS('2. Status Detalhe Campos'!$G$7:$G$574,'1. Status Resumo'!$P95,'2. Status Detalhe Campos'!$C$7:$C$574,'1. Status Resumo'!$H$83,'2. Status Detalhe Campos'!$D$7:$D$574,"2. Campo")+COUNTIFS(Table4[Status Atual],'1. Status Resumo'!$P130,Table4[Sub-âmbito],'1. Status Resumo'!$G$118,Table4[Tipo de teste],"2. Campo") -> 0 | V25: =U25-T25 -> 0
T26: =SUM(T17:T25) -> 549 | U26: =SUM(U17:U25) -> 521
B30: 1. Plano de Testes
X34: Highlights
D35: T. Campos | E35: T. Concluídos | F35: T. Cancelados | G35: Por testar | H35: 45639 | I35: 45639 | J35: 45646 | K35: 45646 | L35: 45649 | M35: 45660 | N35: 45667 | O35: 45674 | P35: 45678 | Q35: Plano | X35: Testes 13/Dez: 1. Modelo de Bens Imóveis: Foram concluídos os 22 campos previstos, permitindo fechar a tabela de Output de Certificados 2. Modelo Verde: Foram concluídos os 14 campos previstos da tabela de output de Clientes 3. Pilar III: Dos 20 campos previstos fechar no Pilar III foram concluídos 10. - 5 foram testados mas reportados com incidências - 1 está em implementação de re-especificação - 3 estão pendentes: a) da atualização da tabela de parametrização de Marcação Verde do Modelo Verde; b) Da implementação do campo 'cagarant_bem' da tabela de Bens do Modelo de Bens Imóveis - 1 está ok para o universo comum de Loan Tape Estrutural mas não foi possível concluir os testes para o universo restante Testes 20/Dez: 1. Modelo Verde: Está previsto testar 16 campos do Modelo verde - 12 campos da tabela de Output de Marcação Verde e 4 referentes aos riscos físicos da tabela de Clientes 2. Pilar III: Está previsto testar 23 campos (13 previstos do dia 20/Dez + os 10 que não foram concluídos no dia 13/Dez)
C36: MBI | D36: =T72 -> 169 | E36: =T64 -> 124 | F36: =T63 -> 10 | G36: =D36-E36-F36 -> 35 | H36: 22 | I36: 22 | J36: 0 | K36: 0 | L36: 0 | M36: 0 | N36: 13 | O36: 0 | P36: 0 | Q36: =SUM(H36,J36:N36,O36,P36) -> 35
C37: MV | D37: =T96 -> 245 | E37: =T88 -> 184 | F37: =T87 -> 14 | G37: =D37-E37-F37 -> 47 | H37: 14 | I37: 14 | J37: 16 | K37: 16 | L37: 0 | M37: 0 | N37: 0 | O37: =4+12 -> 16 | P37: tbd | Q37: =SUM(H37,JO37,P37,J37,L37:O37) -> 46
C38: Pilar III | D38: =T131 -> 135 | E38: =T123 -> 93 | F38: =T122 -> 0 | G38: =D38-E38-F38 -> 42 | H38: 20 | I38: 10 | J38: 13 | K38: =J38+(H38-I38) -> 23 | L38: 6 | M38: 0 | N38: 0 | O38: 3 | P38: 0 | Q38: =SUM(H38,J38,L38:N38,O38,P38) -> 42
C39: TOTAL | D39: =SUM(D36:D38) -> 549 | E39: =SUM(E36:E38) -> 401 | F39: =SUM(F36:F38) -> 24 | G39: =SUM(G36:G38) -> 124 | H39: =SUM(H36:H38) -> 56 | I39: =SUM(I36:I38) -> 46 | J39: 29 | K39: =SUM(K36:K38) -> 39 | L39: 6 | M39: 0 | N39: 13 | O39: =SUM(O36:O38) -> 19 | P39: 0 | Q39: =SUM(Q36:Q38) -> 123
C40: Status | E40: =E39/$D$39 -> 0.73041894 | F40: =F39/$D$39 -> 0.043715847 | G40: =G39/$D$39 -> 0.22586521
C41: Satus s/ cancelados | E41: =E39/($D$39-$F$39) -> 0.76380952 | F41: - | G41: =G39/($D$39-$F$39) -> 0.23619048
D44: T. Campos | E44: T. Concluídos | F44: T. Cancelados | G44: Por testar | H44: 45639 | I44: 45646 | J44: 45649 | K44: 45660 | L44: 45667 | M44: 45674 | N44: 45678 | O44: Plano
C45: MBI | D45: =U72 -> 169 | E45: =U64 -> 146 | F45: =U63 -> 10 | G45: =D45-E45-F45 -> 13 | H45: 22 | I45: 0 | J45: 0 | K45: 0 | L45: 13 | M45: 0 | N45: 0 | O45: =SUM(I45:N45) -> 13
C46: MV | D46: =U96 -> 245 | E46: =U88 -> 198 | F46: =U87 -> 14 | G46: =D46-E46-F46 -> 33 | H46: 14 | I46: 16 | J46: 0 | K46: 0 | L46: 0 | M46: =4+12 -> 16 | N46: tbd | O46: =SUM(I46:N46) -> 32
C47: Pilar III | D47: =U131 -> 135 | E47: =U123 -> 103 | F47: =U122 -> 0 | G47: =D47-E47-F47 -> 32 | H47: 10 | I47: 23 | J47: 6 | K47: 0 | L47: 0 | M47: 3 | N47: 0 | O47: =SUM(I47:N47) -> 32
C48: TOTAL | D48: =SUM(D45:D47) -> 549 | E48: =SUM(E45:E47) -> 447 | F48: =SUM(F45:F47) -> 24 | G48: =SUM(G45:G47) -> 78 | H48: =SUM(H45:H47) -> 46 | I48: =SUM(I45:I47) -> 39 | J48: =SUM(J45:J47) -> 6 | K48: =SUM(K45:K47) -> 0 | ... M48: =SUM(M45:M47) -> 19 | N48: 0 | O48: =SUM(O45:O47) -> 77
C49: Status | E49: =E48/$D$48 -> 0.81420765 | F49: =F48/$D$48 -> 0.043715847 | G49: =G48/$D$48 -> 0.1420765
C50: Satus s/ cancelados | E50: =E48/($D$48-F48) -> 0.85142857 | F50: - | G50: =G48/($D$48-F48) -> 0.14857143
B59: 2. Modelo de Bens Imóveis | G59: Bens Imóveis - Input | H59: Bens Imóveis - Output | I59: Modelo Verde - Input | J59: Modelo Verde - Output | K59: Pilar III
C62: Resumo | G62: Detalhe por Tabela | P62: Status (campos) | T62: 45632 | U62: =T62+7 -> 45639 | V62: ∆ | X62: Highlights
P63: 0. Cancelado | T63: =COUNTIFS('2. Status Detalhe Campos'!$H$7:$H$574,'1. Status Resumo'!$P63,'2. Status Detalhe Campos'!$C$7:$C$574,'1. Status Resumo'!$G$59,'2. Status Detalhe Campos'!$D$7:$D$574,"2. Campo")+COUNTIFS('2. Status Detalhe Campos'!$H$7:$H$574,'1. Status Resumo'!$P63,'2. Status Detalhe Campos'!$C$7:$C$574,'1. Status Resumo'!$H$59,'2. Status Detalhe Campos'!$D$7:$D$574,"2. Campo") -> 10 | U63: 10 | V63: =U63-T63 -> 0 | X63: 1. Datas de entrega de Tecnologia: - Nova especificação da tabela output de certificados (property_energy_certificate): 12/12 -> Entregue no dia 13/12 - Inclusão campo CGARANT_BEM (tabela Property): 19/12 - Habilitação de reprocessamento via front-end: 19/12 2. Testes: - Testados os 22 campos da Tabela de Output de Certificados, permitindo assim dar como concluída a mesma.
P64: 1. Concluído | T64: =COUNTIFS('2. Status Detalhe Campos'!$H$7:$H$574,'1. Status Resumo'!$P64,'2. Status Detalhe Campos'!$C$7:$C$574,'1. Status Resumo'!$G$59,'2. Status Detalhe Campos'!$D$7:$D$574,"2. Campo")+COUNTIFS('2. Status Detalhe Campos'!$H$7:$H$574,'1. Status Resumo'!$P64,'2. Status Detalhe Campos'!$C$7:$C$574,'1. Status Resumo'!$H$59,'2. Status Detalhe Campos'!$D$7:$D$574,"2. Campo") -> 124 | U64: 146 | V64: =U64-T64 -> 22
P65: 2.1 Em Teste | T65: =COUNTIFS('2. Status Detalhe Campos'!$H$7:$H$574,'1. Status Resumo'!$P65,'2. Status Detalhe Campos'!$C$7:$C$574,'1. Status Resumo'!$G$59,'2. Status Detalhe Campos'!$D$7:$D$574,"2. Campo")+COUNTIFS('2. Status Detalhe Campos'!$H$7:$H$574,'1. Status Resumo'!$P65,'2. Status Detalhe Campos'!$C$7:$C$574,'1. Status Resumo'!$H$59,'2. Status Detalhe Campos'!$D$7:$D$574,"2. Campo") -> 0 | U65: =COUNTIFS('2. Status Detalhe Campos'!$G$7:$G$574,'1. Status Resumo'!$P65,'2. Status Detalhe Campos'!$C$7:$C$574,'1. Status Resumo'!$G$59,'2. Status Detalhe Campos'!$D$7:$D$574,"2. Campo")+COUNTIFS('2. Status Detalhe Campos'!$G$7:$G$574,'1. Status Resumo'!$P65,'2. Status Detalhe Campos'!$C$7:$C$574,'1. Status Resumo'!$H$59,'2. Status Detalhe Campos'!$D$7:$D$574,"2. Campo") -> 0 | V65: =U65-T65 -> 0
D66: ="# "&U72 -> # 169 | P66: 2.2 Em Re-especificação | T66: =COUNTIFS('2. Status Detalhe Campos'!$H$7:$H$574,'1. Status Resumo'!$P66,'2. Status Detalhe Campos'!$C$7:$C$574,'1. Status Resumo'!$G$59,'2. Status Detalhe Campos'!$D$7:$D$574,"2. Campo")+COUNTIFS('2. Status Detalhe Campos'!$H$7:$H$574,'1. Status Resumo'!$P66,'2. Status Detalhe Campos'!$C$7:$C$574,'1. Status Resumo'!$H$59,'2. Status Detalhe Campos'!$D$7:$D$574,"2. Campo") -> 0 | U66: =COUNTIFS('2. Status Detalhe Campos'!$G$7:$G$574,'1. Status Resumo'!$P66,'2. Status Detalhe Campos'!$C$7:$C$574,'1. Status Resumo'!$G$59,'2. Status Detalhe Campos'!$D$7:$D$574,"2. Campo")+COUNTIFS('2. Status Detalhe Campos'!$G$7:$G$574,'1. Status Resumo'!$P66,'2. Status Detalhe Campos'!$C$7:$C$574,'1. Status Resumo'!$H$59,'2. Status Detalhe Campos'!$D$7:$D$574,"2. Campo") -> 0 | V66: =U66-T66 -> 0
P67: 3. Pendente de outros desenvolvimentos | T67: =COUNTIFS('2. Status Detalhe Campos'!$H$7:$H$574,'1. Status Resumo'!$P67,'2. Status Detalhe Campos'!$C$7:$C$574,'1. Status Resumo'!$G$59,'2. Status Detalhe Campos'!$D$7:$D$574,"2. Campo")+COUNTIFS('2. Status Detalhe Campos'!$H$7:$H$574,'1. Status Resumo'!$P67,'2. Status Detalhe Campos'!$C$7:$C$574,'1. Status Resumo'!$H$59,'2. Status Detalhe Campos'!$D$7:$D$574,"2. Campo") -> 0 | U67: =COUNTIFS('2. Status Detalhe Campos'!$G$7:$G$574,'1. Status Resumo'!$P67,'2. Status Detalhe Campos'!$C$7:$C$574,'1. Status Resumo'!$G$59,'2. Status Detalhe Campos'!$D$7:$D$574,"2. Campo")+COUNTIFS('2. Status Detalhe Campos'!$G$7:$G$574,'1. Status Resumo'!$P67,'2. Status Detalhe Campos'!$C$7:$C$574,'1. Status Resumo'!$H$59,'2. Status Detalhe Campos'!$D$7:$D$574,"2. Campo") -> 0 | V67: =U67-T67 -> 0
P68: 4. Validação EF | T68: =COUNTIFS('2. Status Detalhe Campos'!$H$7:$H$574,'1. Status Resumo'!$P68,'2. Status Detalhe Campos'!$C$7:$C$574,'1. Status Resumo'!$G$59,'2. Status Detalhe Campos'!$D$7:$D$574,"2. Campo")+COUNTIFS('2. Status Detalhe Campos'!$H$7:$H$574,'1. Status Resumo'!$P68,'2. Status Detalhe Campos'!$C$7:$C$574,'1. Status Resumo'!$H$59,'2. Status Detalhe Campos'!$D$7:$D$574,"2. Campo") -> 0 | U68: =COUNTIFS('2. Status Detalhe Campos'!$G$7:$G$574,'1. Status Resumo'!$P68,'2. Status Detalhe Campos'!$C$7:$C$574,'1. Status Resumo'!$G$59,'2. Status Detalhe Campos'!$D$7:$D$574,"2. Campo")+COUNTIFS('2. Status Detalhe Campos'!$G$7:$G$574,'1. Status Resumo'!$P68,'2. Status Detalhe Campos'!$C$7:$C$574,'1. Status Resumo'!$H$59,'2. Status Detalhe Campos'!$D$7:$D$574,"2. Campo") -> 0 | V68: =U68-T68 -> 0
P69: 5. Em Correção | R69: (incidências) | T69: =COUNTIFS('2. Status Detalhe Campos'!$H$7:$H$574,'1. Status Resumo'!$P69,'2. Status Detalhe Campos'!$C$7:$C$574,'1. Status Resumo'!$G$59,'2. Status Detalhe Campos'!$D$7:$D$574,"2. Campo")+COUNTIFS('2. Status Detalhe Campos'!$H$7:$H$574,'1. Status Resumo'!$P69,'2. Status Detalhe Campos'!$C$7:$C$574,'1. Status Resumo'!$H$59,'2. Status Detalhe Campos'!$D$7:$D$574,"2. Campo") -> 0 | U69: =COUNTIFS('2. Status Detalhe Campos'!$G$7:$G$574,'1. Status Resumo'!$P69,'2. Status Detalhe Campos'!$C$7:$C$574,'1. Status Resumo'!$G$59,'2. Status Detalhe Campos'!$D$7:$D$574,"2. Campo")+COUNTIFS('2. Status Detalhe Campos'!$G$7:$G$574,'1. Status Resumo'!$P69,'2. Status Detalhe Campos'!$C$7:$C$574,'1. Status Resumo'!$H$59,'2. Status Detalhe Campos'!$D$7:$D$574,"2. Campo") -> 0 | V69: =U69-T69 -> 0
P70: 6. Em implementação (re-especificação) | T70: =COUNTIFS('2. Status Detalhe Campos'!$H$7:$H$574,'1. Status Resumo'!$P70,'2. Status Detalhe Campos'!$C$7:$C$574,'1. Status Resumo'!$G$59,'2. Status Detalhe Campos'!$D$7:$D$574,"2. Campo")+COUNTIFS('2. Status Detalhe Campos'!$H$7:$H$574,'1. Status Resumo'!$P70,'2. Status Detalhe Campos'!$C$7:$C$574,'1. Status Resumo'!$H$59,'2. Status Detalhe Campos'!$D$7:$D$574,"2. Campo") -> 35 | U70: 13 | V70: =U70-T70 -> -22
P71: 7. Por iniciar | T71: =COUNTIFS('2. Status Detalhe Campos'!$H$7:$H$574,'1. Status Resumo'!$P71,'2. Status Detalhe Campos'!$C$7:$C$574,'1. Status Resumo'!$G$59,'2. Status Detalhe Campos'!$D$7:$D$574,"2. Campo")+COUNTIFS('2. Status Detalhe Campos'!$H$7:$H$574,'1. Status Resumo'!$P71,'2. Status Detalhe Campos'!$C$7:$C$574,'1. Status Resumo'!$H$59,'2. Status Detalhe Campos'!$D$7:$D$574,"2. Campo") -> 0 | U71: =COUNTIFS('2. Status Detalhe Campos'!$G$7:$G$574,'1. Status Resumo'!$P71,'2. Status Detalhe Campos'!$C$7:$C$574,'1. Status Resumo'!$G$59,'2. Status Detalhe Campos'!$D$7:$D$574,"2. Campo")+COUNTIFS('2. Status Detalhe Campos'!$G$7:$G$574,'1. Status Resumo'!$P71,'2. Status Detalhe Campos'!$C$7:$C$574,'1. Status Resumo'!$H$59,'2. Status Detalhe Campos'!$D$7:$D$574,"2. Campo") -> 0 | V71: =U71-T71 -> 0
T72: =SUM(T63:T71) -> 169 | U72: =SUM(U63:U71) -> 169
G73: Status (Tabelas) | P73: Status (Universos)
F74: > | G74: Tabela de Bens Imóveis | L74: 1 campo Em Implementação | O74: > | P74: Universo Bens Colateralizados (MUG) | T74: OK
F75: > | G75: Tabelas de Processos Imobiliários | L75: OK | O75: > | P75: Universo Bens Não Colateralizados (GP) | T75: OK
F76: > | G76: Tabela de Traçabilidade Processo -Bem | L76: OK | O76: > | P76: Universo Bens Adjudicados | T76: Não serão testados neste projeto
F77: > | G77: Tabela de Traçabilidade Crédito - Processo | L77: OK
F78: > | G78: Tabela input de Cerificados Energéticos (Gloval) | L78: Em Implementação
F79: > | G79: Tabela Output de Cerificados Energéticos | L79: OK
B83: 3. Modelo Verde | G83: Modelo Verde - Input | H83: Modelo Verde - Output
C86: Resumo | G86: Detalhe por Tabela | P86: Status (campos) | T86: =T62 -> 45632 | U86: =U62 -> 45639 | V86: ∆ | X86: Highlights
P87: 0. Cancelado | T87: =COUNTIFS('2. Status Detalhe Campos'!$H$7:$H$574,'1. Status Resumo'!$P87,'2. Status Detalhe Campos'!$C$7:$C$574,'1. Status Resumo'!$G$83,'2. Status Detalhe Campos'!$D$7:$D$574,"2. Campo")+COUNTIFS('2. Status Detalhe Campos'!$H$7:$H$574,'1. Status Resumo'!$P87,'2. Status Detalhe Campos'!$C$7:$C$574,'1. Status Resumo'!$H$83,'2. Status Detalhe Campos'!$D$7:$D$574,"2. Campo") -> 14 | U87: =COUNTIFS('2. Status Detalhe Campos'!$G$7:$G$574,'1. Status Resumo'!$P87,'2. Status Detalhe Campos'!$C$7:$C$574,'1. Status Resumo'!$G$83,'2. Status Detalhe Campos'!$D$7:$D$574,"2. Campo")+COUNTIFS('2. Status Detalhe Campos'!$G$7:$G$574,'1. Status Resumo'!$P87,'2. Status Detalhe Campos'!$C$7:$C$574,'1. Status Resumo'!$H$83,'2. Status Detalhe Campos'!$D$7:$D$574,"2. Campo") -> 14 | V87: =U87-T87 -> 0 | X87: 1. Datas de entrega de Tecnologia: Tabela de Clientes (modesg_out_empr_info_nfin): - Risco Físico Clientes: 12/12 (4 campos) -> Entregue no dia 13/12 2. Testes: - Tabela de Output de Clientes: concluídos os 14 campos de rácios de eligibilidade que tinham sido reportados com incidências
P88: 1. Concluído | T88: =COUNTIFS('2. Status Detalhe Campos'!$H$7:$H$574,'1. Status Resumo'!$P88,'2. Status Detalhe Campos'!$C$7:$C$574,'1. Status Resumo'!$G$83,'2. Status Detalhe Campos'!$D$7:$D$574,"2. Campo")+COUNTIFS('2. Status Detalhe Campos'!$H$7:$H$574,'1. Status Resumo'!$P88,'2. Status Detalhe Campos'!$C$7:$C$574,'1. Status Resumo'!$H$83,'2. Status Detalhe Campos'!$D$7:$D$574,"2. Campo") -> 184 | U88: =COUNTIFS('2. Status Detalhe Campos'!$G$7:$G$574,'1. Status Resumo'!$P88,'2. Status Detalhe Campos'!$C$7:$C$574,'1. Status Resumo'!$G$83,'2. Status Detalhe Campos'!$D$7:$D$574,"2. Campo")+COUNTIFS('2. Status Detalhe Campos'!$G$7:$G$574,'1. Status Resumo'!$P88,'2. Status Detalhe Campos'!$C$7:$C$574,'1. Status Resumo'!$H$83,'2. Status Detalhe Campos'!$D$7:$D$574,"2. Campo") -> 198 | V88: =U88-T88 -> 14
P89: 2.1 Em Teste | T89: =COUNTIFS('2. Status Detalhe Campos'!$H$7:$H$574,'1. Status Resumo'!$P89,'2. Status Detalhe Campos'!$C$7:$C$574,'1. Status Resumo'!$G$83,'2. Status Detalhe Campos'!$D$7:$D$574,"2. Campo")+COUNTIFS('2. Status Detalhe Campos'!$H$7:$H$574,'1. Status Resumo'!$P89,'2. Status Detalhe Campos'!$C$7:$C$574,'1. Status Resumo'!$H$83,'2. Status Detalhe Campos'!$D$7:$D$574,"2. Campo") -> 28 | U89: =COUNTIFS('2. Status Detalhe Campos'!$G$7:$G$574,'1. Status Resumo'!$P89,'2. Status Detalhe Campos'!$C$7:$C$574,'1. Status Resumo'!$G$83,'2. Status Detalhe Campos'!$D$7:$D$574,"2. Campo")+COUNTIFS('2. Status Detalhe Campos'!$G$7:$G$574,'1. Status Resumo'!$P89,'2. Status Detalhe Campos'!$C$7:$C$574,'1. Status Resumo'!$H$83,'2. Status Detalhe Campos'!$D$7:$D$574,"2. Campo") -> 32 | V89: =U89-T89 -> 4
D90: ="# "&U96 -> # 245 | P90: 2.2 Em Re-especificação | T90: =COUNTIFS('2. Status Detalhe Campos'!$H$7:$H$574,'1. Status Resumo'!$P90,'2. Status Detalhe Campos'!$C$7:$C$574,'1. Status Resumo'!$G$83,'2. Status Detalhe Campos'!$D$7:$D$574,"2. Campo")+COUNTIFS('2. Status Detalhe Campos'!$H$7:$H$574,'1. Status Resumo'!$P90,'2. Status Detalhe Campos'!$C$7:$C$574,'1. Status Resumo'!$H$83,'2. Status Detalhe Campos'!$D$7:$D$574,"2. Campo") -> 0 | U90: =COUNTIFS('2. Status Detalhe Campos'!$G$7:$G$574,'1. Status Resumo'!$P90,'2. Status Detalhe Campos'!$C$7:$C$574,'1. Status Resumo'!$G$83,'2. Status Detalhe Campos'!$D$7:$D$574,"2. Campo")+COUNTIFS('2. Status Detalhe Campos'!$G$7:$G$574,'1. Status Resumo'!$P90,'2. Status Detalhe Campos'!$C$7:$C$574,'1. Status Resumo'!$H$83,'2. Status Detalhe Campos'!$D$7:$D$574,"2. Campo") -> 0 | V90: =U90-T90 -> 0
P91: 3. Pendente de outros desenvolvimentos | T91: =COUNTIFS('2. Status Detalhe Campos'!$H$7:$H$574,'1. Status Resumo'!$P91,'2. Status Detalhe Campos'!$C$7:$C$574,'1. Status Resumo'!$G$83,'2. Status Detalhe Campos'!$D$7:$D$574,"2. Campo")+COUNTIFS('2. Status Detalhe Campos'!$H$7:$H$574,'1. Status Resumo'!$P91,'2. Status Detalhe Campos'!$C$7:$C$574,'1. Status Resumo'!$H$83,'2. Status Detalhe Campos'!$D$7:$D$574,"2. Campo") -> 0 | U91: =COUNTIFS('2. Status Detalhe Campos'!$G$7:$G$574,'1. Status Resumo'!$P91,'2. Status Detalhe Campos'!$C$7:$C$574,'1. Status Resumo'!$G$83,'2. Status Detalhe Campos'!$D$7:$D$574,"2. Campo")+COUNTIFS('2. Status Detalhe Campos'!$G$7:$G$574,'1. Status Resumo'!$P91,'2. Status Detalhe Campos'!$C$7:$C$574,'1. Status Resumo'!$H$83,'2. Status Detalhe Campos'!$D$7:$D$574,"2. Campo") -> 0 | V91: =U91-T91 -> 0
P92: 4. Validação EF | T92: =COUNTIFS('2. Status Detalhe Campos'!$H$7:$H$574,'1. Status Resumo'!$P92,'2. Status Detalhe Campos'!$C$7:$C$574,'1. Status Resumo'!$G$83,'2. Status Detalhe Campos'!$D$7:$D$574,"2. Campo")+COUNTIFS('2. Status Detalhe Campos'!$H$7:$H$574,'1. Status Resumo'!$P92,'2. Status Detalhe Campos'!$C$7:$C$574,'1. Status Resumo'!$H$83,'2. Status Detalhe Campos'!$D$7:$D$574,"2. Campo") -> 1 | U92: =COUNTIFS('2. Status Detalhe Campos'!$G$7:$G$574,'1. Status Resumo'!$P92,'2. Status Detalhe Campos'!$C$7:$C$574,'1. Status Resumo'!$G$83,'2. Status Detalhe Campos'!$D$7:$D$574,"2. Campo")+COUNTIFS('2. Status Detalhe Campos'!$G$7:$G$574,'1. Status Resumo'!$P92,'2. Status Detalhe Campos'!$C$7:$C$574,'1. Status Resumo'!$H$83,'2. Status Detalhe Campos'!$D$7:$D$574,"2. Campo") -> 1 | V92: =U92-T92 -> 0
P93: 5. Em Correção | R93: (incidências) | T93: =COUNTIFS('2. Status Detalhe Campos'!$H$7:$H$574,'1. Status Resumo'!$P93,'2. Status Detalhe Campos'!$C$7:$C$574,'1. Status Resumo'!$G$83,'2. Status Detalhe Campos'!$D$7:$D$574,"2. Campo")+COUNTIFS('2. Status Detalhe Campos'!$H$7:$H$574,'1. Status Resumo'!$P93,'2. Status Detalhe Campos'!$C$7:$C$574,'1. Status Resumo'!$H$83,'2. Status Detalhe Campos'!$D$7:$D$574,"2. Campo") -> 14 | U93: =COUNTIFS('2. Status Detalhe Campos'!$G$7:$G$574,'1. Status Resumo'!$P93,'2. Status Detalhe Campos'!$C$7:$C$574,'1. Status Resumo'!$G$83,'2. Status Detalhe Campos'!$D$7:$D$574,"2. Campo")+COUNTIFS('2. Status Detalhe Campos'!$G$7:$G$574,'1. Status Resumo'!$P93,'2. Status Detalhe Campos'!$C$7:$C$574,'1. Status Resumo'!$H$83,'2. Status Detalhe Campos'!$D$7:$D$574,"2. Campo") -> 0 | V93: =U93-T93 -> -14
P94: 6. Em implementação (re-especificação) | T94: =COUNTIFS('2. Status Detalhe Campos'!$H$7:$H$574,'1. Status Resumo'!$P94,'2. Status Detalhe Campos'!$C$7:$C$574,'1. Status Resumo'!$G$83,'2. Status Detalhe Campos'!$D$7:$D$574,"2. Campo")+COUNTIFS('2. Status Detalhe Campos'!$H$7:$H$574,'1. Status Resumo'!$P94,'2. Status Detalhe Campos'!$C$7:$C$574,'1. Status Resumo'!$H$83,'2. Status Detalhe Campos'!$D$7:$D$574,"2. Campo") -> 4 | U94: =COUNTIFS('2. Status Detalhe Campos'!$G$7:$G$574,'1. Status Resumo'!$P94,'2. Status Detalhe Campos'!$C$7:$C$574,'1. Status Resumo'!$G$83,'2. Status Detalhe Campos'!$D$7:$D$574,"2. Campo")+COUNTIFS('2. Status Detalhe Campos'!$G$7:$G$574,'1. Status Resumo'!$P94,'2. Status Detalhe Campos'!$C$7:$C$574,'1. Status Resumo'!$H$83,'2. Status Detalhe Campos'!$D$7:$D$574,"2. Campo") -> 0 | V94: =U94-T94 -> -4
P95: 7. Por iniciar | T95: =COUNTIFS('2. Status Detalhe Campos'!$H$7:$H$574,'1. Status Resumo'!$P95,'2. Status Detalhe Campos'!$C$7:$C$574,'1. Status Resumo'!$G$83,'2. Status Detalhe Campos'!$D$7:$D$574,"2. Campo")+COUNTIFS('2. Status Detalhe Campos'!$H$7:$H$574,'1. Status Resumo'!$P95,'2. Status Detalhe Campos'!$C$7:$C$574,'1. Status Resumo'!$H$83,'2. Status Detalhe Campos'!$D$7:$D$574,"2. Campo") -> 0 | U95: =COUNTIFS('2. Status Detalhe Campos'!$G$7:$G$574,'1. Status Resumo'!$P95,'2. Status Detalhe Campos'!$C$7:$C$574,'1. Status Resumo'!$G$83,'2. Status Detalhe Campos'!$D$7:$D$574,"2. Campo")+COUNTIFS('2. Status Detalhe Campos'!$G$7:$G$574,'1. Status Resumo'!$P95,'2. Status Detalhe Campos'!$C$7:$C$574,'1. Status Resumo'!$H$83,'2. Status Detalhe Campos'!$D$7:$D$574,"2. Campo") -> 0 | V95: =U95-T95 -> 0
T96: =SUM(T87:T95) -> 245 | U96: =SUM(U87:U95) -> 245
P98: Status (Universos - Inputs)
O99: > | P99: modesg_inp_risco_fisico | T99: OK
O100: > | P100: modesg_inp_nfrd_alinhamento_tax | T100: OK
O101: > | P101: modesg_inp_km_medios_emss_vcls | T101: OK
O102: > | P102: modesg_inp_emss_vcls | T102: OK
O103: > | P103: modesg_inp_emss_scib | T103: OK
O104: > | P104: modesg_inp_emss_nace | T104: OK
O105: > | P105: modesg_inp_emss_bens_imoveis | T105: OK
O106: > | P106: modesg_inp_empr_excl_paris | T106: OK
O107: > | P107: modesg_param_sfcs_taxon_europeia | T107: Validação EF
O108: > | P108: Input Munich Re | T108: Em Implementação
P110: Status (Universos - Outputs)
O111: > | P111: modesg_out_ems_vcls | T111: OK
O112: > | P112: modesg_out_bens_imoveis | T112: OK (coerente com Modelo de Bens Imóveis)
O113: > | P113: modesg_out_empr_info_nfin | T113: OK
O114: > | P114: modesg_out_sfcs_taxon_europeia | T114: Em Teste
B118: 4. Loan Tape | Pilar III | G118: Pilar III
C121: Resumo | G121: Detalhe por Tabela | P121: Status (campos) | T121: =T62 -> 45632 | U121: =U62 -> 45639 | V121: ∆ | X121: Highlights
P122: 0. Cancelado | T122: =COUNTIFS(Table4[Status Anterior],'1. Status Resumo'!$P122,Table4[Sub-âmbito],'1. Status Resumo'!$G$118,Table4[Tipo de teste],"2. Campo") -> 0 | U122: =COUNTIFS(Table4[Status Atual],'1. Status Resumo'!$P122,Table4[Sub-âmbito],'1. Status Resumo'!$G$118,Table4[Tipo de teste],"2. Campo") -> 0 | V122: =U122-T122 -> 0 | X122: 1. Testes: - 14 campos da tabela de Clientes: Concluídos 8 campos da tabela de clientes, 5 campos foram testados e reportados com incidências e 1 está em implementação de re-especificação (lt003_entity) - 5 campos da tabela de Garantias: Concluídos 2 campo da tabela de garantias, 2 campos não são possíveis testar por estarem dependentes de outros desenvolvimentos e 1 campo está ok para o universo comum da Loan Tape estrutural mas não foi possível testar para o restante universo (lt004_protection) - 1 campo da tabela de Contratos: Não foi possível testar o campo uma vez que está dependente da atualização da tabela de parametrização da marcação verde do Modelo Verde (lt002_instrument)
P123: 1. Concluído | T123: =COUNTIFS(Table4[Status Anterior],'1. Status Resumo'!$P123,Table4[Sub-âmbito],'1. Status Resumo'!$G$118,Table4[Tipo de teste],"2. Campo") -> 93 | U123: =COUNTIFS(Table4[Status Atual],'1. Status Resumo'!$P123,Table4[Sub-âmbito],'1. Status Resumo'!$G$118,Table4[Tipo de teste],"2. Campo") -> 103 | V123: =U123-T123 -> 10
P124: 2.1 Em Teste | T124: =COUNTIFS(Table4[Status Anterior],'1. Status Resumo'!$P124,Table4[Sub-âmbito],'1. Status Resumo'!$G$118,Table4[Tipo de teste],"2. Campo") -> 30 | U124: =COUNTIFS(Table4[Status Atual],'1. Status Resumo'!$P124,Table4[Sub-âmbito],'1. Status Resumo'!$G$118,Table4[Tipo de teste],"2. Campo") -> 21 | V124: =U124-T124 -> -9
D125: ="# "&U131 -> # 135 | P125: 2.2 Em Re-especificação | T125: =COUNTIFS(Table4[Status Anterior],'1. Status Resumo'!$P125,Table4[Sub-âmbito],'1. Status Resumo'!$G$118,Table4[Tipo de teste],"2. Campo") -> 0 | U125: =COUNTIFS(Table4[Status Atual],'1. Status Resumo'!$P125,Table4[Sub-âmbito],'1. Status Resumo'!$G$118,Table4[Tipo de teste],"2. Campo") -> 0 | V125: =U125-T125 -> 0
P126: 3. Pendente de outros desenvolvimentos | T126: =COUNTIFS(Table4[Status Anterior],'1. Status Resumo'!$P126,Table4[Sub-âmbito],'1. Status Resumo'!$G$118,Table4[Tipo de teste],"2. Campo") -> 4 | U126: =COUNTIFS(Table4[Status Atual],'1. Status Resumo'!$P126,Table4[Sub-âmbito],'1. Status Resumo'!$G$118,Table4[Tipo de teste],"2. Campo") -> 2 | V126: =U126-T126 -> -2
P127: 4. Validação EF | T127: =COUNTIFS(Table4[Status Anterior],'1. Status Resumo'!$P127,Table4[Sub-âmbito],'1. Status Resumo'!$G$118,Table4[Tipo de teste],"2. Campo") -> 0 | U127: =COUNTIFS(Table4[Status Atual],'1. Status Resumo'!$P127,Table4[Sub-âmbito],'1. Status Resumo'!$G$118,Table4[Tipo de teste],"2. Campo") -> 1 | V127: =U127-T127 -> 1
P128: 5. Em Correção | R128: (incidências) | T128: =COUNTIFS(Table4[Status Anterior],'1. Status Resumo'!$P128,Table4[Sub-âmbito],'1. Status Resumo'!$G$118,Table4[Tipo de teste],"2. Campo") -> 5 | U128: =COUNTIFS(Table4[Status Atual],'1. Status Resumo'!$P128,Table4[Sub-âmbito],'1. Status Resumo'!$G$118,Table4[Tipo de teste],"2. Campo") -> 5 | V128: =U128-T128 -> 0
P129: 6. Em implementação (re-especificação) | T129: =COUNTIFS(Table4[Status Anterior],'1. Status Resumo'!$P129,Table4[Sub-âmbito],'1. Status Resumo'!$G$118,Table4[Tipo de teste],"2. Campo") -> 3 | U129: =COUNTIFS(Table4[Status Atual],'1. Status Resumo'!$P129,Table4[Sub-âmbito],'1. Status Resumo'!$G$118,Table4[Tipo de teste],"2. Campo") -> 3 | V129: =U129-T129 -> 0
P130: 7. Por iniciar | T130: =COUNTIFS(Table4[Status Anterior],'1. Status Resumo'!$P130,Table4[Sub-âmbito],'1. Status Resumo'!$G$118,Table4[Tipo de teste],"2. Campo") -> 0 | U130: =COUNTIFS(Table4[Status Atual],'1. Status Resumo'!$P130,Table4[Sub-âmbito],'1. Status Resumo'!$G$118,Table4[Tipo de teste],"2. Campo") -> 0 | V130: =U130-T130 -> 0
T131: =SUM(T122:T130) -> 135 | U131: =SUM(U122:U130) -> 135
P133: Status (Tabelas)
O134: > | P134: lt002_instrument | T134: Em Curso
O135: > | P135: lt003_entity | T135: Em Curso
O136: > | P136: lt004_protection | T136: Em Curso
O137: > | P137: lt005_instr_ent | T137: OK
O138: > | P138: lt006_instr_prot | T138: OK
O139: > | P139: lt007_instr_activity | T139: Em Teste
O140: > | P140: lt827_mthd_usd_instrmnt | T140: OK
O141: > | P141: lt826_esg_sbsctr | T141: OK

Sheet 2. Status Detalhe Campos
B6: Âmbito | C6: Sub-âmbito | D6: Tipo de teste | E6: Tabela | F6: Campo | G6: Status Atual | H6: Status Anterior | I6: Observações | J6: Data de Pedido correção/esclarecimento | K6: Data de correção prevista | L6: Data de correção efetiva | M6: Data Prevista de Re-especificação | N6: Data Prevista de Teste | O6: Modelo
A7: =E7&F7 -> ENERGY_CERTIFICATE_EST_INPUTn.a. | B7: Pilar III | C7: Bens Imóveis - Input | D7: 1. Universo | E7: ENERGY_CERTIFICATE_EST_INPUT | F7: n.a. | G7: =VLOOKUP(A7,#REF!,7,0) -> #REF! | H7: 6. Em implementação (re-especificação) | I7: Apesar da data de correção ser 28/11 a data que importa é 24/10, uma vez que a última implementação não é relevanta para iniciar os testes à tabela | J7: =IF(VLOOKUP(A7,#REF!,3,0)=0, "",VLOOKUP(A7,#REF!,3,0)) -> #REF! | K7: =IF(VLOOKUP(A7,#REF!,4,0)=0, "",VLOOKUP(A7,#REF!,4,0)) -> #REF! | L7: =IF(VLOOKUP(A7,#REF!,5,0)=0, "",VLOOKUP(A7,#REF!,5,0)) -> #REF! | O7: Bens Imóveis
A8: =E8&F8 -> ENERGY_CERTIFICATE_EST_INPUTPROPERTY_BANK_ID | B8: Pilar III | C8: Bens Imóveis - Input | D8: 2. Campo | E8: ENERGY_CERTIFICATE_EST_INPUT | F8: PROPERTY_BANK_ID | G8: =VLOOKUP(A8,#REF!,7,0) -> #REF! | H8: 6. Em implementação (re-especificação) | I8: Apesar da data de correção ser 28/11 a data que importa é 24/10, uma vez que a última implementação não é relevanta para iniciar os testes à tabela | J8: =IF(VLOOKUP(A8,#REF!,3,0)=0, "",VLOOKUP(A8,#REF!,3,0)) -> #REF! | K8: =IF(VLOOKUP(A8,#REF!,4,0)=0, "",VLOOKUP(A8,#REF!,4,0)) -> #REF! | L8: =IF(VLOOKUP(A8,#REF!,5,0)=0, "",VLOOKUP(A8,#REF!,5,0)) -> #REF! | O8: Bens Imóveis
A9: =E9&F9 -> ENERGY_CERTIFICATE_EST_INPUTENCRYPTED_KEY | B9: Pilar III | C9: Bens Imóveis - Input | D9: 2. Campo | E9: ENERGY_CERTIFICATE_EST_INPUT | F9: ENCRYPTED_KEY | G9: =VLOOKUP(A9,#REF!,7,0) -> #REF! | H9: 6. Em implementação (re-especificação) | I9: Apesar da data de correção ser 28/11 a data que importa é 24/10, uma vez que a última implementação não é relevanta para iniciar os testes à tabela | J9: =IF(VLOOKUP(A9,#REF!,3,0)=0, "",VLOOKUP(A9,#REF!,3,0)) -> #REF! | K9: =IF(VLOOKUP(A9,#REF!,4,0)=0, "",VLOOKUP(A9,#REF!,4,0)) -> #REF! | L9: =IF(VLOOKUP(A9,#REF!,5,0)=0, "",VLOOKUP(A9,#REF!,5,0)) -> #REF! | O9: Bens Imóveis
A10: =E10&F10 -> ENERGY_CERTIFICATE_EST_INPUTPROPERTY_BRANCH_CODE | B10: Pilar III | C10: Bens Imóveis - Input | D10: 2. Campo | E10: ENERGY_CERTIFICATE_EST_INPUT | F10: PROPERTY_BRANCH_CODE | G10: =VLOOKUP(A10,#REF!,7,0) -> #REF! | H10: 6. Em implementação (re-especificação) | I10: Apesar da data de correção ser 28/11 a data que importa é 24/10, uma vez que a última implementação não é relevanta para iniciar os testes à tabela | J10: =IF(VLOOKUP(A10,#REF!,3,0)=0, "",VLOOKUP(A10,#REF!,3,0)) -> #REF! | K10: =IF(VLOOKUP(A10,#REF!,4,0)=0, "",VLOOKUP(A10,#REF!,4,0)) -> #REF! | L10: =IF(VLOOKUP(A10,#REF!,5,0)=0, "",VLOOKUP(A10,#REF!,5,0)) -> #REF! | O10: Bens Imóveis
A11: =E11&F11 -> ENERGY_CERTIFICATE_EST_INPUTPROPERTY_CONTRACT_ID | B11: Pilar III | C11: Bens Imóveis - Input | D11: 2. Campo | E11: ENERGY_CERTIFICATE_EST_INPUT | F11: PROPERTY_CONTRACT_ID | G11: =VLOOKUP(A11,#REF!,7,0) -> #REF! | H11: 6. Em implementação (re-especificação) | I11: Apesar da data de correção ser 28/11 a data que importa é 24/10, uma vez que a última implementação não é relevanta para iniciar os testes à tabela | J11: =IF(VLOOKUP(A11,#REF!,3,0)=0, "",VLOOKUP(A11,#REF!,3,0)) -> #REF! | K11: =IF(VLOOKUP(A11,#REF!,4,0)=0, "",VLOOKUP(A11,#REF!,4,0)) -> #REF! | L11: =IF(VLOOKUP(A11,#REF!,5,0)=0, "",VLOOKUP(A11,#REF!,5,0)) -> #REF! | O11: Bens Imóveis
A12: =E12&F12 -> ENERGY_CERTIFICATE_EST_INPUTPROPERTY_REFERENCE_CODE | B12: Pilar III | C12: Bens Imóveis - Input | D12: 2. Campo | E12: ENERGY_CERTIFICATE_EST_INPUT | F12: PROPERTY_REFERENCE_CODE | G12: =VLOOKUP(A12,#REF!,7,0) -> #REF! | H12: 6. Em implementação (re-especificação) | I12: Apesar da data de correção ser 28/11 a data que importa é 24/10, uma vez que a última implementação não é relevanta para iniciar os testes à tabela | J12: =IF(VLOOKUP(A12,#REF!,3,0)=0, "",VLOOKUP(A12,#REF!,3,0)) -> #REF! | K12: =IF(VLOOKUP(A12,#REF!,4,0)=0, "",VLOOKUP(A12,#REF!,4,0)) -> #REF! | L12: =IF(VLOOKUP(A12,#REF!,5,0)=0, "",VLOOKUP(A12,#REF!,5,0)) -> #REF! | O12: Bens Imóveis
A13: =E13&F13 -> ENERGY_CERTIFICATE_EST_INPUTDATA_EXTRACTION_DATE | B13: Pilar III | C13: Bens Imóveis - Input | D13: 2. Campo | E13: ENERGY_CERTIFICATE_EST_INPUT | F13: DATA_EXTRACTION_DATE | G13: =VLOOKUP(A13,#REF!,7,0) -> #REF! | H13: 6. Em implementação (re-especificação) | I13: Apesar da data de correção ser 28/11 a data que importa é 24/10, uma vez que a última implementação não é relevanta para iniciar os testes à tabela | J13: =IF(VLOOKUP(A13,#REF!,3,0)=0, "",VLOOKUP(A13,#REF!,3,0)) -> #REF! | K13: =IF(VLOOKUP(A13,#REF!,4,0)=0, "",VLOOKUP(A13,#REF!,4,0)) -> #REF! | L13: =IF(VLOOKUP(A13,#REF!,5,0)=0, "",VLOOKUP(A13,#REF!,5,0)) -> #REF! | O13: Bens Imóveis
A14: =E14&F14 -> ENERGY_CERTIFICATE_EST_INPUTEPC | B14: Pilar III | C14: Bens Imóveis - Input | D14: 2. Campo | E14: ENERGY_CERTIFICATE_EST_INPUT | F14: EPC | G14: =VLOOKUP(A14,#REF!,7,0) -> #REF! | H14: 6. Em implementação (re-especificação) | I14: Apesar da data de correção ser 28/11 a data que importa é 24/10, uma vez que a última implementação não é relevanta para iniciar os testes à tabela | J14: =IF(VLOOKUP(A14,#REF!,3,0)=0, "",VLOOKUP(A14,#REF!,3,0)) -> #REF! | K14: =IF(VLOOKUP(A14,#REF!,4,0)=0, "",VLOOKUP(A14,#REF!,4,0)) -> #REF! | L14: =IF(VLOOKUP(A14,#REF!,5,0)=0, "",VLOOKUP(A14,#REF!,5,0)) -> #REF! | O14: Bens Imóveis
A15: =E15&F15 -> ENERGY_CERTIFICATE_EST_INPUTDATA_PROVIDER | B15: Pilar III | C15: Bens Imóveis - Input | D15: 2. Campo | E15: ENERGY_CERTIFICATE_EST_INPUT | F15: DATA_PROVIDER | G15: =VLOOKUP(A15,#REF!,7,0) -> #REF! | H15: 6. Em implementação (re-especificação) | I15: Apesar da data de correção ser 28/11 a data que importa é 24/10, uma vez que a última implementação não é relevanta para iniciar os testes à tabela | J15: =IF(VLOOKUP(A15,#REF!,3,0)=0, "",VLOOKUP(A15,#REF!,3,0)) -> #REF! | K15: =IF(VLOOKUP(A15,#REF!,4,0)=0, "",VLOOKUP(A15,#REF!,4,0)) -> #REF! | L15: =IF(VLOOKUP(A15,#REF!,5,0)=0, "",VLOOKUP(A15,#REF!,5,0)) -> #REF! | O15: Bens Imóveis
A16: =E16&F16 -> ENERGY_CERTIFICATE_EST_INPUTACTUAL_VALUE_IND | B16: Pilar III | C16: Bens Imóveis - Input | D16: 2. Campo | E16: ENERGY_CERTIFICATE_EST_INPUT | F16: ACTUAL_VALUE_IND | G16: =VLOOKUP(A16,#REF!,7,0) -> #REF! | H16: 6. Em implementação (re-especificação) | I16: Apesar da data de correção ser 28/11 a data que importa é 24/10, uma vez que a última implementação não é relevanta para iniciar os testes à tabela | J16: =IF(VLOOKUP(A16,#REF!,3,0)=0, "",VLOOKUP(A16,#REF!,3,0)) -> #REF! | K16: =IF(VLOOKUP(A16,#REF!,4,0)=0, "",VLOOKUP(A16,#REF!,4,0)) -> #REF! | L16: =IF(VLOOKUP(A16,#REF!,5,0)=0, "",VLOOKUP(A16,#REF!,5,0)) -> #REF! | O16: Bens Imóveis
A17: =E17&F17 -> ENERGY_CERTIFICATE_EST_INPUTQUALITY_SCORE | B17: Pilar III | C17: Bens Imóveis - Input | D17: 2. Campo | E17: ENERGY_CERTIFICATE_EST_INPUT | F17: QUALITY_SCORE | G17: =VLOOKUP(A17,#REF!,7,0) -> #REF! | H17: 6. Em implementação (re-especificação) | I17: Apesar da data de correção ser 28/11 a data que importa é 24/10, uma vez que a última implementação não é relevanta para iniciar os testes à tabela | J17: =IF(VLOOKUP(A17,#REF!,3,0)=0, "",VLOOKUP(A17,#REF!,3,0)) -> #REF! | K17: =IF(VLOOKUP(A17,#REF!,4,0)=0, "",VLOOKUP(A17,#REF!,4,0)) -> #REF! | L17: =IF(VLOOKUP(A17,#REF!,5,0)=0, "",VLOOKUP(A17,#REF!,5,0)) -> #REF! | O17: Bens Imóveis
A18: =E18&F18 -> ENERGY_CERTIFICATE_EST_INPUTENERGY_CONSUMPTION_VALUE_YEAR | B18: Pilar III | C18: Bens Imóveis - Input | D18: 2. Campo | E18: ENERGY_CERTIFICATE_EST_INPUT | F18: ENERGY_CONSUMPTION_VALUE_YEAR | G18: =VLOOKUP(A18,#REF!,7,0) -> #REF! | H18: 6. Em implementação (re-especificação) | I18: Apesar da data de correção ser 28/11 a data que importa é 24/10, uma vez que a última implementação não é relevanta para iniciar os testes à tabela | J18: =IF(VLOOKUP(A18,#REF!,3,0)=0, "",VLOOKUP(A18,#REF!,3,0)) -> #REF! | K18: =IF(VLOOKUP(A18,#REF!,4,0)=0, "",VLOOKUP(A18,#REF!,4,0)) -> #REF! | L18: =IF(VLOOKUP(A18,#REF!,5,0)=0, "",VLOOKUP(A18,#REF!,5,0)) -> #REF! | O18: Bens Imóveis
A19: =E19&F19 -> ENERGY_CERTIFICATE_EST_INPUTCARBON_EMISSION_VALUE_YEAR | B19: Pilar III | C19: Bens Imóveis - Input | D19: 2. Campo | E19: ENERGY_CERTIFICATE_EST_INPUT | F19: CARBON_EMISSION_VALUE_YEAR | G19: =VLOOKUP(A19,#REF!,7,0) -> #REF! | H19: 6. Em implementação (re-especificação) | I19: Apesar da data de correção ser 28/11 a data que importa é 24/10, uma vez que a última implementação não é relevanta para iniciar os testes à tabela | J19: =IF(VLOOKUP(A19,#REF!,3,0)=0, "",VLOOKUP(A19,#REF!,3,0)) -> #REF! | K19: =IF(VLOOKUP(A19,#REF!,4,0)=0, "",VLOOKUP(A19,#REF!,4,0)) -> #REF! | L19: =IF(VLOOKUP(A19,#REF!,5,0)=0, "",VLOOKUP(A19,#REF!,5,0)) -> #REF! | O19: Bens Imóveis
A20: =E20&F20 -> PROCESSn.a. | B20: Pilar III | C20: Bens Imóveis - Output | D20: 1. Universo | E20: PROCESS | F20: n.a. | G20: =VLOOKUP(A20,#REF!,7,0) -> #REF! | H20: 1. Concluído | J20: =IF(VLOOKUP(A20,#REF!,3,0)=0, "",VLOOKUP(A20,#REF!,3,0)) -> #REF! | K20: =IF(VLOOKUP(A20,#REF!,4,0)=0, "",VLOOKUP(A20,#REF!,4,0)) -> #REF! | L20: =IF(VLOOKUP(A20,#REF!,5,0)=0, "",VLOOKUP(A20,#REF!,5,0)) -> #REF! | O20: Bens Imóveis
A21: =E21&F21 -> PROCESSPROCESS_BANK_ID | B21: Pilar III | C21: Bens Imóveis - Output | D21: 2. Campo | E21: PROCESS | F21: PROCESS_BANK_ID | G21: =VLOOKUP(A21,#REF!,7,0) -> #REF! | H21: 1. Concluído | I21: 26/07/2024: Conclusão de testes ao universo MUG e GP. Adjudicados fora de âmbito deste projeto. | J21: =IF(VLOOKUP(A21,#REF!,3,0)=0, "",VLOOKUP(A21,#REF!,3,0)) -> #REF! | K21: =IF(VLOOKUP(A21,#REF!,4,0)=0, "",VLOOKUP(A21,#REF!,4,0)) -> #REF! | L21: =IF(VLOOKUP(A21,#REF!,5,0)=0, "",VLOOKUP(A21,#REF!,5,0)) -> #REF! | O21: Bens Imóveis
A22: =E22&F22 -> PROCESSPROCESS_BRANCH_CODE | B22: Pilar III | C22: Bens Imóveis - Output | D22: 2. Campo | E22: PROCESS | F22: PROCESS_BRANCH_CODE | G22: =VLOOKUP(A22,#REF!,7,0) -> #REF! | H22: 1. Concluído | I22: 26/07/2024: Conclusão de testes ao universo MUG e GP. Adjudicados fora de âmbito deste projeto. | J22: =IF(VLOOKUP(A22,#REF!,3,0)=0, "",VLOOKUP(A22,#REF!,3,0)) -> #REF! | K22: =IF(VLOOKUP(A22,#REF!,4,0)=0, "",VLOOKUP(A22,#REF!,4,0)) -> #REF! | L22: =IF(VLOOKUP(A22,#REF!,5,0)=0, "",VLOOKUP(A22,#REF!,5,0)) -> #REF! | O22: Bens Imóveis
A23: =E23&F23 -> PROCESSPROCESS_ACCOUNT_ID | B23: Pilar III | C23: Bens Imóveis - Output | D23: 2. Campo | E23: PROCESS | F23: PROCESS_ACCOUNT_ID | G23: =VLOOKUP(A23,#REF!,7,0) -> #REF! | H23: 1. Concluído | I23: 26/07/2024: Conclusão de testes ao universo MUG e GP. Adjudicados fora de âmbito deste projeto. | J23: =IF(VLOOKUP(A23,#REF!,3,0)=0, "",VLOOKUP(A23,#REF!,3,0)) -> #REF! | K23: =IF(VLOOKUP(A23,#REF!,4,0)=0, "",VLOOKUP(A23,#REF!,4,0)) -> #REF! | L23: =IF(VLOOKUP(A23,#REF!,5,0)=0, "",VLOOKUP(A23,#REF!,5,0)) -> #REF! | O23: Bens Imóveis
A24: =E24&F24 -> PROCESScod_estd_prcs | B24: Pilar III | C24: Bens Imóveis - Output | D24: 2. Campo | E24: PROCESS | F24: cod_estd_prcs | G24: =VLOOKUP(A24,#REF!,7,0) -> #REF! | H24: 0. Cancelado | I24: 19/07/2024: Campo eliminado do Modelo para garantir coerência com MUG | J24: =IF(VLOOKUP(A24,#REF!,3,0)=0, "",VLOOKUP(A24,#REF!,3,0)) -> #REF! | K24: =IF(VLOOKUP(A24,#REF!,4,0)=0, "",VLOOKUP(A24,#REF!,4,0)) -> #REF! | L24: =IF(VLOOKUP(A24,#REF!,5,0)=0, "",VLOOKUP(A24,#REF!,5,0)) -> #REF! | O24: Bens Imóveis
A25: =E25&F25 -> PROCESSGUARANTEE_CODE | B25: Pilar III | C25: Bens Imóveis - Output | D25: 2. Campo | E25: PROCESS | F25: GUARANTEE_CODE | G25: =VLOOKUP(A25,#REF!,7,0) -> #REF! | H25: 1. Concluído | J25: =IF(VLOOKUP(A25,#REF!,3,0)=0, "",VLOOKUP(A25,#REF!,3,0)) -> #REF! | K25: =IF(VLOOKUP(A25,#REF!,4,0)=0, "",VLOOKUP(A25,#REF!,4,0)) -> #REF! | L25: =IF(VLOOKUP(A25,#REF!,5,0)=0, "",VLOOKUP(A25,#REF!,5,0)) -> #REF! | O25: Bens Imóveis
A26: =E26&F26 -> PROCESSCURRENCY_CODE | B26: Pilar III | C26: Bens Imóveis - Output | D26: 2. Campo | E26: PROCESS | F26: CURRENCY_CODE | G26: =VLOOKUP(A26,#REF!,7,0) -> #REF! | H26: 1. Concluído | J26: =IF(VLOOKUP(A26,#REF!,3,0)=0, "",VLOOKUP(A26,#REF!,3,0)) -> #REF! | K26: =IF(VLOOKUP(A26,#REF!,4,0)=0, "",VLOOKUP(A26,#REF!,4,0)) -> #REF! | L26: =IF(VLOOKUP(A26,#REF!,5,0)=0, "",VLOOKUP(A26,#REF!,5,0)) -> #REF! | O26: Bens Imóveis
A27: =E27&F27 -> PROCESSPROCESS_CAMPAIGN_CODE | B27: Pilar III | C27: Bens Imóveis - Output | D27: 2. Campo | E27: PROCESS | F27: PROCESS_CAMPAIGN_CODE | G27: =VLOOKUP(A27,#REF!,7,0) -> #REF! | H27: 1. Concluído | J27: =IF(VLOOKUP(A27,#REF!,3,0)=0, "",VLOOKUP(A27,#REF!,3,0)) -> #REF! | K27: =IF(VLOOKUP(A27,#REF!,4,0)=0, "",VLOOKUP(A27,#REF!,4,0)) -> #REF! | L27: =IF(VLOOKUP(A27,#REF!,5,0)=0, "",VLOOKUP(A27,#REF!,5,0)) -> #REF! | O27: Bens Imóveis
A28: =E28&F28 -> PROCESSPROCESS_PRODUCT_ID | B28: Pilar III | C28: Bens Imóveis - Output | D28: 2. Campo | E28: PROCESS | F28: PROCESS_PRODUCT_ID | G28: =VLOOKUP(A28,#REF!,7,0) -> #REF! | H28: 1. Concluído | J28: =IF(VLOOKUP(A28,#REF!,3,0)=0, "",VLOOKUP(A28,#REF!,3,0)) -> #REF! | K28: =IF(VLOOKUP(A28,#REF!,4,0)=0, "",VLOOKUP(A28,#REF!,4,0)) -> #REF! | L28: =IF(VLOOKUP(A28,#REF!,5,0)=0, "",VLOOKUP(A28,#REF!,5,0)) -> #REF! | O28: Bens Imóveis
A29: =E29&F29 -> PROCESSPROCESS_SUBPRODUCT_ID | B29: Pilar III | C29: Bens Imóveis - Output | D29: 2. Campo | E29: PROCESS | F29: PROCESS_SUBPRODUCT_ID | G29: =VLOOKUP(A29,#REF!,7,0) -> #REF! | H29: 1. Concluído | J29: =IF(VLOOKUP(A29,#REF!,3,0)=0, "",VLOOKUP(A29,#REF!,3,0)) -> #REF! | K29: =IF(VLOOKUP(A29,#REF!,4,0)=0, "",VLOOKUP(A29,#REF!,4,0)) -> #REF! | L29: =IF(VLOOKUP(A29,#REF!,5,0)=0, "",VLOOKUP(A29,#REF!,5,0)) -> #REF! | O29: Bens Imóveis
A30: =E30&F30 -> PROCESSGUARANTEE_TYPE_CODE | B30: Pilar III | C30: Bens Imóveis - Output | D30: 2. Campo | E30: PROCESS | F30: GUARANTEE_TYPE_CODE | G30: =VLOOKUP(A30,#REF!,7,0) -> #REF! | H30: 1. Concluído | J30: =IF(VLOOKUP(A30,#REF!,3,0)=0, "",VLOOKUP(A30,#REF!,3,0)) -> #REF! | K30: =IF(VLOOKUP(A30,#REF!,4,0)=0, "",VLOOKUP(A30,#REF!,4,0)) -> #REF! | L30: =IF(VLOOKUP(A30,#REF!,5,0)=0, "",VLOOKUP(A30,#REF!,5,0)) -> #REF! | O30: Bens Imóveis
A31: =E31&F31 -> PROCESSPROCESS_REFERENCE_CODE | B31: Pilar III | C31: Bens Imóveis - Output | D31: 2. Campo | E31: PROCESS | F31: PROCESS_REFERENCE_CODE | G31: =VLOOKUP(A31,#REF!,7,0) -> #REF! | H31: 1. Concluído | J31: =IF(VLOOKUP(A31,#REF!,3,0)=0, "",VLOOKUP(A31,#REF!,3,0)) -> #REF! | K31: =IF(VLOOKUP(A31,#REF!,4,0)=0, "",VLOOKUP(A31,#REF!,4,0)) -> #REF! | L31: =IF(VLOOKUP(A31,#REF!,5,0)=0, "",VLOOKUP(A31,#REF!,5,0)) -> #REF! | O31: Bens Imóveis
A32: =E32&F32 -> PROCESSPROCESS_START_DATE | B32: Pilar III | C32: Bens Imóveis - Output | D32: 2. Campo | E32: PROCESS | F32: PROCESS_START_DATE | G32: =VLOOKUP(A32,#REF!,7,0) -> #REF! | H32: 1. Concluído | J32: =IF(VLOOKUP(A32,#REF!,3,0)=0, "",VLOOKUP(A32,#REF!,3,0)) -> #REF! | K32: =IF(VLOOKUP(A32,#REF!,4,0)=0, "",VLOOKUP(A32,#REF!,4,0)) -> #REF! | L32: =IF(VLOOKUP(A32,#REF!,5,0)=0, "",VLOOKUP(A32,#REF!,5,0)) -> #REF! | O32: Bens Imóveis
A33: =E33&F33 -> PROCESSPROCESS_DUE_DATE | B33: Pilar III | C33: Bens Imóveis - Output | D33: 2. Campo | E33: PROCESS | F33: PROCESS_DUE_DATE | G33: =VLOOKUP(A33,#REF!,7,0) -> #REF! | H33: 1. Concluído | J33: =IF(VLOOKUP(A33,#REF!,3,0)=0, "",VLOOKUP(A33,#REF!,3,0)) -> #REF! | K33: =IF(VLOOKUP(A33,#REF!,4,0)=0, "",VLOOKUP(A33,#REF!,4,0)) -> #REF! | L33: =IF(VLOOKUP(A33,#REF!,5,0)=0, "",VLOOKUP(A33,#REF!,5,0)) -> #REF! | O33: Bens Imóveis
A34: =E34&F34 -> PROCESSmontante_eur | B34: Pilar III | C34: Bens Imóveis - Output | D34: 2. Campo | E34: PROCESS | F34: montante_eur | G34: =VLOOKUP(A34,#REF!,7,0) -> #REF! | H34: 0. Cancelado | I34: 19/07/2024: Campo eliminado do Modelo para garantir coerência com MUG | J34: =IF(VLOOKUP(A34,#REF!,3,0)=0, "",VLOOKUP(A34,#REF!,3,0)) -> #REF! | K34: =IF(VLOOKUP(A34,#REF!,4,0)=0, "",VLOOKUP(A34,#REF!,4,0)) -> #REF! | L34: =IF(VLOOKUP(A34,#REF!,5,0)=0, "",VLOOKUP(A34,#REF!,5,0)) -> #REF! | O34: Bens Imóveis
A35: =E35&F35 -> PROCESSmontante_org | B35: Pilar III | C35: Bens Imóveis - Output | D35: 2. Campo | E35: PROCESS | F35: montante_org | G35: =VLOOKUP(A35,#REF!,7,0) -> #REF! | H35: 0. Cancelado | I35: 19/07/2024: Campo eliminado do Modelo para garantir coerência com MUG | J35: =IF(VLOOKUP(A35,#REF!,3,0)=0, "",VLOOKUP(A35,#REF!,3,0)) -> #REF! | K35: =IF(VLOOKUP(A35,#REF!,4,0)=0, "",VLOOKUP(A35,#REF!,4,0)) -> #REF! | L35: =IF(VLOOKUP(A35,#REF!,5,0)=0, "",VLOOKUP(A35,#REF!,5,0)) -> #REF! | O35: Bens Imóveis
A36: =E36&F36 -> PROCESSorigem | B36: Pilar III | C36: Bens Imóveis - Output | D36: 2. Campo | E36: PROCESS | F36: origem | G36: =VLOOKUP(A36,#REF!,7,0) -> #REF! | H36: 0. Cancelado | I36: 08/08/2024: Campo eliminado de modo a garantir a coerência com o atualmente realizado no Modelo Único de Garantias. | J36: =IF(VLOOKUP(A36,#REF!,3,0)=0, "",VLOOKUP(A36,#REF!,3,0)) -> #REF! | K36: =IF(VLOOKUP(A36,#REF!,4,0)=0, "",VLOOKUP(A36,#REF!,4,0)) -> #REF! | L36: =IF(VLOOKUP(A36,#REF!,5,0)=0, "",VLOOKUP(A36,#REF!,5,0)) -> #REF! | O36: Bens Imóveis
A37: =E37&F37 -> PROCESSDATA_DATE_PART | B37: Pilar III | C37: Bens Imóveis - Output | D37: 2. Campo | E37: PROCESS | F37: DATA_DATE_PART | G37: 1. Concluído | H37: 1. Concluído | O37: Bens Imóveis
A38: =E38&F38 -> RESPONSIBILITY_PROCESS_RELn.a. | B38: Pilar III | C38: Bens Imóveis - Output | D38: 1. Universo | E38: RESPONSIBILITY_PROCESS_REL | F38: n.a. | G38: 1. Concluído | H38: 1. Concluído | O38: Bens Imóveis
A39: =E39&F39 -> RESPONSIBILITY_PROCESS_RELPROCESS_BANK_ID | B39: Pilar III | C39: Bens Imóveis - Output | D39: 2. Campo | E39: RESPONSIBILITY_PROCESS_REL | F39: PROCESS_BANK_ID | G39: 1. Concluído | H39: 1. Concluído | I39: 26/07/2024: Conclusão de testes ao universo MUG e GP. Adjudicados fora de âmbito deste projeto. | O39: Bens Imóveis
A40: =E40&F40 -> RESPONSIBILITY_PROCESS_RELBANK_ID | B40: Pilar III | C40: Bens Imóveis - Output | D40: 2. Campo | E40: RESPONSIBILITY_PROCESS_REL | F40: BANK_ID | G40: 1. Concluído | H40: 1. Concluído | I40: 26/07/2024: Conclusão de testes ao universo MUG e GP. Adjudicados fora de âmbito deste projeto. | O40: Bens Imóveis
A41: =E41&F41 -> RESPONSIBILITY_PROCESS_RELPROCESS_BRANCH_CODE | B41: Pilar III | C41: Bens Imóveis - Output | D41: 2. Campo | E41: RESPONSIBILITY_PROCESS_REL | F41: PROCESS_BRANCH_CODE | G41: 1. Concluído | H41: 1. Concluído | I41: 26/07/2024: Conclusão de testes ao universo MUG e GP. Adjudicados fora de âmbito deste projeto. | O41: Bens Imóveis
A42: =E42&F42 -> RESPONSIBILITY_PROCESS_RELBRANCH_CODE | B42: Pilar III | C42: Bens Imóveis - Output | D42: 2. Campo | E42: RESPONSIBILITY_PROCESS_REL | F42: BRANCH_CODE | G42: 1. Concluído | H42: 1. Concluído | I42: 26/07/2024: Conclusão de testes ao universo MUG e GP. Adjudicados fora de âmbito deste projeto. | O42: Bens Imóveis
A43: =E43&F43 -> RESPONSIBILITY_PROCESS_RELCONTRACT_ID | B43: Pilar III | C43: Bens Imóveis - Output | D43: 2. Campo | E43: RESPONSIBILITY_PROCESS_REL | F43: CONTRACT_ID | G43: 1. Concluído | H43: 1. Concluído | I43: 26/07/2024: Conclusão de testes ao universo MUG e GP. Adjudicados fora de âmbito deste projeto. | O43: Bens Imóveis
A44: =E44&F44 -> RESPONSIBILITY_PROCESS_RELPROCESS_ACCOUNT_ID | B44: Pilar III | C44: Bens Imóveis - Output | D44: 2. Campo | E44: RESPONSIBILITY_PROCESS_REL | F44: PROCESS_ACCOUNT_ID | G44: 1. Concluído | H44: 1. Concluído | I44: 26/07/2024: Conclusão de testes ao universo MUG e GP. Adjudicados fora de âmbito deste projeto. | O44: Bens Imóveis
A45: =E45&F45 -> RESPONSIBILITY_PROCESS_RELREFERENCE_CODE | B45: Pilar III | C45: Bens Imóveis - Output | D45: 2. Campo | E45: RESPONSIBILITY_PROCESS_REL | F45: REFERENCE_CODE | G45: 1. Concluído | H45: 1. Concluído | I45: 26/07/2024: Conclusão de testes ao universo MUG e GP. Adjudicados fora de âmbito deste projeto. | O45: Bens Imóveis
A46: =E46&F46 -> RESPONSIBILITY_PROCESS_RELPURPOSE_CODE | B46: Pilar III | C46: Bens Imóveis - Output | D46: 2. Campo | E46: RESPONSIBILITY_PROCESS_REL | F46: PURPOSE_CODE | G46: 1. Concluído | H46: 1. Concluído | O46: Bens Imóveis
A47: =E47&F47 -> RESPONSIBILITY_PROCESS_RELINDIVIDUAL_OCCUPATION_CODE | B47: Pilar III | C47: Bens Imóveis - Output | D47: 2. Campo | E47: RESPONSIBILITY_PROCESS_REL | F47: INDIVIDUAL_OCCUPATION_CODE | G47: 1. Concluído | H47: 1. Concluído | O47: Bens Imóveis
A48: =E48&F48 -> RESPONSIBILITY_PROCESS_RELPRODUCT_ID | B48: Pilar III | C48: Bens Imóveis - Output | D48: 2. Campo | E48: RESPONSIBILITY_PROCESS_REL | F48: PRODUCT_ID | G48: 1. Concluído | H48: 1. Concluído | O48: Bens Imóveis
A49: =E49&F49 -> RESPONSIBILITY_PROCESS_RELcod_sit | B49: Pilar III | C49: Bens Imóveis - Output | D49: 2. Campo | E49: RESPONSIBILITY_PROCESS_REL | F49: cod_sit | G49: 0. Cancelado | H49: 0. Cancelado | I49: 19/07/2024: Campo eliminado do Modelo para garantir coerência com MUG | O49: Bens Imóveis
A50: =E50&F50 -> RESPONSIBILITY_PROCESS_RELSUBPRODUCT_ID | B50: Pilar III | C50: Bens Imóveis - Output | D50: 2. Campo | E50: RESPONSIBILITY_PROCESS_REL | F50: SUBPRODUCT_ID | G50: 1. Concluído | H50: 1. Concluído | O50: Bens Imóveis
A51: =E51&F51 -> RESPONSIBILITY_PROCESS_RELPROCESS_REFERENCE_CODE | B51: Pilar III | C51: Bens Imóveis - Output | D51: 2. Campo | E51: RESPONSIBILITY_PROCESS_REL | F51: PROCESS_REFERENCE_CODE | G51: 1. Concluído | H51: 1. Concluído | O51: Bens Imóveis
A52: =E52&F52 -> RESPONSIBILITY_PROCESS_RELEFFECTIVE_RELATION_END_DATE | B52: Pilar III | C52: Bens Imóveis - Output | D52: 2. Campo | E52: RESPONSIBILITY_PROCESS_REL | F52: EFFECTIVE_RELATION_END_DATE | G52: 1. Concluído | H52: 1. Concluído | O52: Bens Imóveis
A53: =E53&F53 -> RESPONSIBILITY_PROCESS_RELPROCESS_START_DATE | B53: Pilar III | C53: Bens Imóveis - Output | D53: 2. Campo | E53: RESPONSIBILITY_PROCESS_REL | F53: PROCESS_START_DATE | G53: 1. Concluído | H53: 1. Concluído | O53: Bens Imóveis
A54: =E54&F54 -> RESPONSIBILITY_PROCESS_RELPROCESS_DUE_DATE | B54: Pilar III | C54: Bens Imóveis - Output | D54: 2. Campo | E54: RESPONSIBILITY_PROCESS_REL | F54: PROCESS_DUE_DATE | G54: 1. Concluído | H54: 1. Concluído | O54: Bens Imóveis
A55: =E55&F55 -> RESPONSIBILITY_PROCESS_RELidetgar | B55: Pilar III | C55: Bens Imóveis - Output | D55: 2. Campo | E55: RESPONSIBILITY_PROCESS_REL | F55: idetgar | G55: 0. Cancelado | H55: 0. Cancelado | I55: 19/07/2024: Campo eliminado do Modelo para garantir coerência com MUG | O55: Bens Imóveis
A56: =E56&F56 -> RESPONSIBILITY_PROCESS_RELnum_prop | B56: Pilar III | C56: Bens Imóveis - Output | D56: 2. Campo | E56: RESPONSIBILITY_PROCESS_REL | F56: num_prop | G56: 0. Cancelado | H56: 0. Cancelado | I56: 19/07/2024: Campo eliminado do Modelo para garantir coerência com MUG | O56: Bens Imóveis
A57: =E57&F57 -> RESPONSIBILITY_PROCESS_RELSOURCE_CODE | B57: Pilar III | C57: Bens Imóveis - Output | D57: 2. Campo | E57: RESPONSIBILITY_PROCESS_REL | F57: SOURCE_CODE | G57: 1. Concluído | H57: 1. Concluído | O57: Bens Imóveis
A58: =E58&F58 -> RESPONSIBILITY_PROCESS_RELDATA_DATE_PART | B58: Pilar III | C58: Bens Imóveis - Output | D58: 2. Campo | E58: RESPONSIBILITY_PROCESS_REL | F58: DATA_DATE_PART | G58: 1. Concluído | H58: 1. Concluído | O58: Bens Imóveis
A59: =E59&F59 -> PROCESS_PROPERTY_RELn.a. | B59: Pilar III | C59: Bens Imóveis - Output | D59: 1. Universo | E59: PROCESS_PROPERTY_REL | F59: n.a. | G59: 1. Concluído | H59: 1. Concluído | O59: Bens Imóveis
A60: =E60&F60 -> PROCESS_PROPERTY_RELPROPERTY_BANK_ID | B60: Pilar III | C60: Bens Imóveis - Output | D60: 2. Campo | E60: PROCESS_PROPERTY_REL | F60: PROPERTY_BANK_ID | G60: 1. Concluído | H60: 1. Concluído | O60: Bens Imóveis
A61: =E61&F61 -> PROCESS_PROPERTY_RELPROCESS_BANK_ID | B61: Pilar III | C61: Bens Imóveis - Output | D61: 2. Campo | E61: PROCESS_PROPERTY_REL | F61: PROCESS_BANK_ID | G61: 1. Concluído | H61: 1. Concluído | I61: 26/07/2024: Conclusão de testes ao universo MUG e GP. Adjudicados fora de âmbito deste projeto. | O61: Bens Imóveis
A62: =E62&F62 -> PROCESS_PROPERTY_RELPROPERTY_BRANCH_CODE | B62: Pilar III | C62: Bens Imóveis - Output | D62: 2. Campo | E62: PROCESS_PROPERTY_REL | F62: PROPERTY_BRANCH_CODE | G62: 1. Concluído | H62: 1. Concluído | I62: 26/07/2024: Conclusão de testes ao universo MUG e GP. Adjudicados fora de âmbito deste projeto. | O62: Bens Imóveis
A63: =E63&F63 -> PROCESS_PROPERTY_RELPROCESS_BRANCH_CODE | B63: Pilar III | C63: Bens Imóveis - Output | D63: 2. Campo | E63: PROCESS_PROPERTY_REL | F63: PROCESS_BRANCH_CODE | G63: 1. Concluído | H63: 1. Concluído | I63: 26/07/2024: Conclusão de testes ao universo MUG e GP. Adjudicados fora de âmbito deste projeto. | O63: Bens Imóveis
A64: =E64&F64 -> PROCESS_PROPERTY_RELPROPERTY_CONTRACT_ID | B64: Pilar III | C64: Bens Imóveis - Output | D64: 2. Campo | E64: PROCESS_PROPERTY_REL | F64: PROPERTY_CONTRACT_ID | G64: 1. Concluído | H64: 1. Concluído | I64: 26/07/2024: Conclusão de testes ao universo MUG e GP. Adjudicados fora de âmbito deste projeto. | O64: Bens Imóveis
A65: =E65&F65 -> PROCESS_PROPERTY_RELPROCESS_ACCOUNT_ID | B65: Pilar III | C65: Bens Imóveis - Output | D65: 2. Campo | E65: PROCESS_PROPERTY_REL | F65: PROCESS_ACCOUNT_ID | G65: 1. Concluído | H65: 1. Concluído | I65: 26/07/2024: Conclusão de testes ao universo MUG e GP. Adjudicados fora de âmbito deste projeto. | O65: Bens Imóveis
A66: =E66&F66 -> PROCESS_PROPERTY_RELPROPERTY_REFERENCE_CODE | B66: Pilar III | C66: Bens Imóveis - Output | D66: 2. Campo | E66: PROCESS_PROPERTY_REL | F66: PROPERTY_REFERENCE_CODE | G66: 1. Concluído | H66: 1. Concluído | O66: Bens Imóveis
A67: =E67&F67 -> PROCESS_PROPERTY_RELPROCESS_REFERENCE_CODE | B67: Pilar III | C67: Bens Imóveis - Output | D67: 2. Campo | E67: PROCESS_PROPERTY_REL | F67: PROCESS_REFERENCE_CODE | G67: 1. Concluído | H67: 1. Concluído | O67: Bens Imóveis
A68: =E68&F68 -> PROCESS_PROPERTY_RELdata_assc | B68: Pilar III | C68: Bens Imóveis - Output | D68: 2. Campo | E68: PROCESS_PROPERTY_REL | F68: data_assc | G68: 0. Cancelado | H68: 0. Cancelado | I68: 19/07/2024: Campo eliminado do Modelo para garantir coerência com MUG | O68: Bens Imóveis
A69: =E69&F69 -> PROCESS_PROPERTY_RELSEIZED_PROPERTY_IND | B69: Pilar III | C69: Bens Imóveis - Output | D69: 2. Campo | E69: PROCESS_PROPERTY_REL | F69: SEIZED_PROPERTY_IND | G69: 1. Concluído | H69: 1. Concluído | O69: Bens Imóveis
A70: =E70&F70 -> PROCESS_PROPERTY_RELCOLLATERAL_PROPERTY_IND | B70: Pilar III | C70: Bens Imóveis - Output | D70: 2. Campo | E70: PROCESS_PROPERTY_REL | F70: COLLATERAL_PROPERTY_IND | G70: 1. Concluído | H70: 1. Concluído | O70: Bens Imóveis
A71: =E71&F71 -> PROCESS_PROPERTY_RELFINANCED_PROPERTY_IND | B71: Pilar III | C71: Bens Imóveis - Output | D71: 2. Campo | E71: PROCESS_PROPERTY_REL | F71: FINANCED_PROPERTY_IND | G71: 1. Concluído | H71: 1. Concluído | O71: Bens Imóveis
A72: =E72&F72 -> PROCESS_PROPERTY_RELOWNED_PROPERTY_IND | B72: Pilar III | C72: Bens Imóveis - Output | D72: 2. Campo | E72: PROCESS_PROPERTY_REL | F72: OWNED_PROPERTY_IND | G72: 1. Concluído | H72: 1. Concluído | O72: Bens Imóveis
A73: =E73&F73 -> PROCESS_PROPERTY_RELSOURCE_CODE | B73: Pilar III | C73: Bens Imóveis - Output | D73: 2. Campo | E73: PROCESS_PROPERTY_REL | F73: SOURCE_CODE | G73: 1. Concluído | H73: 1. Concluído | O73: Bens Imóveis
A74: =E74&F74 -> PROCESS_PROPERTY_RELDATA_DATE_PART | B74: Pilar III | C74: Bens Imóveis - Output | D74: 2. Campo | E74: PROCESS_PROPERTY_REL | F74: DATA_DATE_PART | G74: 1. Concluído | H74: 1. Concluído | O74: Bens Imóveis
A75: =E75&F75 -> PROPERTYn.a. | B75: Pilar III | C75: Bens Imóveis - Output | D75: 1. Universo | E75: PROPERTY | F75: n.a. | G75: 1. Concluído | H75: 1. Concluído | O75: Bens Imóveis
A76: =E76&F76 -> PROPERTYCONSTRUCTION_YEAR | B76: Pilar III | C76: Bens Imóveis - Output | D76: 2. Campo | E76: PROPERTY | F76: CONSTRUCTION_YEAR | G76: 1. Concluído | H76: 1. Concluído | O76: Bens Imóveis
A77: =E77&F77 -> PROPERTYNET_FLOOR_AREA | B77: Pilar III | C77: Bens Imóveis - Output | D77: 2. Campo | E77: PROPERTY | F77: NET_FLOOR_AREA | G77: 1. Concluído | H77: 1. Concluído | O77: Bens Imóveis
A78: =E78&F78 -> PROPERTYPROPERTY_BANK_ID | B78: Pilar III | C78: Bens Imóveis - Output | D78: 2. Campo | E78: PROPERTY | F78: PROPERTY_BANK_ID | G78: 1. Concluído | H78: 1. Concluído | O78: Bens Imóveis
A79: =E79&F79 -> PROPERTYPROPERTY_BRANCH_CODE | B79: Pilar III | C79: Bens Imóveis - Output | D79: 2. Campo | E79: PROPERTY | F79: PROPERTY_BRANCH_CODE | G79: 1. Concluído | H79: 1. Concluído | O79: Bens Imóveis
A80: =E80&F80 -> PROPERTYPROPERTY_CONTRACT_ID | B80: Pilar III | C80: Bens Imóveis - Output | D80: 2. Campo | E80: PROPERTY | F80: PROPERTY_CONTRACT_ID | G80: 1. Concluído | H80: 1. Concluído | O80: Bens Imóveis
... A83: =E83&F83 -> PROPERTYAPPRAISAL_CODE | B83: Pilar III | C83: Bens Imóveis - Output | D83: 2. Campo | E83: PROPERTY | F83: APPRAISAL_CODE | G83: 1. Concluído | H83: 1. Concluído | O83: Bens Imóveis
A84: =E84&F84 -> PROPERTYcod_bem | B84: Pilar III | C84: Bens Imóveis - Output | D84: 2. Campo | E84: PROPERTY | F84: cod_bem | G84: 0. Cancelado | H84: 0. Cancelado | I84: 19/07/2024: Campo eliminado do Modelo para garantir coerência com MUG | O84: Bens Imóveis
A85: =E85&F85 -> PROPERTYDISTRICT_MUNICIP_PARISH_CODE | B85: Pilar III | C85: Bens Imóveis - Output | D85: 2. Campo | E85: PROPERTY | F85: DISTRICT_MUNICIP_PARISH_CODE | G85: 1. Concluído | H85: 1. Concluído | O85: Bens Imóveis
A86: =E86&F86 -> PROPERTYPROPERTY_PURPOSE_CODE | B86: Pilar III | C86: Bens Imóveis - Output | D86: 2. Campo | E86: PROPERTY | F86: PROPERTY_PURPOSE_CODE | G86: 1. Concluído | H86: 1. Concluído | O86: Bens Imóveis
A87: =E87&F87 -> PROPERTYPROPERTY_LIFETIME_CODE | B87: Pilar III | C87: Bens Imóveis - Output | D87: 2. Campo | E87: PROPERTY | F87: PROPERTY_LIFETIME_CODE | G87: 1. Concluído | H87: 1. Concluído | O87: Bens Imóveis
A88: =E88&F88 -> PROPERTYADDRESS_CODE | B88: Pilar III | C88: Bens Imóveis - Output | D88: 2. Campo | E88: PROPERTY | F88: ADDRESS_CODE | G88: 1. Concluído | H88: 1. Concluído | O88: Bens Imóveis
A89: =E89&F89 -> PROPERTYCOUNTRY_CODE | B89: Pilar III | C89: Bens Imóveis - Output | D89: 2. Campo | E89: PROPERTY | F89: COUNTRY_CODE | G89: 1. Concluído | H89: 1. Concluído | O89: Bens Imóveis
A90: =E90&F90 -> PROPERTYPOSTAL_CODE | B90: Pilar III | C90: Bens Imóveis - Output | D90: 2. Campo | E90: PROPERTY | F90: POSTAL_CODE | G90: 1. Concluído | H90: 1. Concluído | O90: Bens Imóveis
A91: =E91&F91 -> PROPERTYPROPERTY_TYPE_CODE | B91: Pilar III | C91: Bens Imóveis - Output | D91: 2. Campo | E91: PROPERTY | F91: PROPERTY_TYPE_CODE | G91: 1. Concluído | H91: 1. Concluído | O91: Bens Imóveis
A92: =E92&F92 -> PROPERTYLAST_APPRAISAL_DATE | B92: Pilar III | C92: Bens Imóveis - Output | D92: 2. Campo | E92: PROPERTY | F92: LAST_APPRAISAL_DATE | G92: 1. Concluído | H92: 1. Concluído | O92: Bens Imóveis
A93: =E93&F93 -> PROPERTYUSAGE_PERMIT_START_DATE | B93: Pilar III | C93: Bens Imóveis - Output | D93: 2. Campo | E93: PROPERTY | F93: USAGE_PERMIT_START_DATE | G93: 1. Concluído | H93: 1. Concluído | O93: Bens Imóveis
A94: =E94&F94 -> PROPERTYCONSERVATORY_REG_FILE_ID | B94: Pilar III | C94: Bens Imóveis - Output | D94: 2. Campo | E94: PROPERTY | F94: CONSERVATORY_REG_FILE_ID | G94: 1. Concluído | H94: 1. Concluído | O94: Bens Imóveis
A95: =E95&F95 -> PROPERTYFLOOR_NUMBER | B95: Pilar III | C95: Bens Imóveis - Output | D95: 2. Campo | E95: PROPERTY | F95: FLOOR_NUMBER | G95: 1. Concluído | H95: 1. Concluído | O95: Bens Imóveis
A96: =E96&F96 -> PROPERTYLOCALITY | B96: Pilar III | C96: Bens Imóveis - Output | D96: 2. Campo | E96: PROPERTY | F96: LOCALITY | G96: 1. Concluído | H96: 1. Concluído | O96: Bens Imóveis
... A102: =E102&F102 -> PROPERTYPROPERTY_NUMBER | B102: Pilar III | C102: Bens Imóveis - Output | D102: 2. Campo | E102: PROPERTY | F102: PROPERTY_NUMBER | G102: 1. Concluído | H102: 1. Concluído | O102: Bens Imóveis
A103: =E103&F103 -> PROPERTYOrigem | B103: Pilar III | C103: Bens Imóveis - Output | D103: 2. Campo | E103: PROPERTY | F103: Origem | G103: 0. Cancelado | H103: 0. Cancelado | I103: 08/08/2024: Campo eliminado de modo a garantir a coerência com o atualmente realizado no Modelo Único de Garantias. | O103: Bens Imóveis
A104: =E104&F104 -> PROPERTYCURRENT_CONSTRUCTION_PCT | B104: Pilar III | C104: Bens Imóveis - Output | D104: 2. Campo | E104: PROPERTY | F104: CURRENT_CONSTRUCTION_PCT | G104: 1. Concluído | H104: 1. Concluído | I104: 22/07/2024: Entrega de campo para testes | J104: 45491 | K104: 45495 | L104: 45495 | O104: Bens Imóveis
A105: =E105&F105 -> PROPERTYCONSTRUCTION_COMPLETED_PCT | B105: Pilar III | C105: Bens Imóveis - Output | D105: 2. Campo | E105: PROPERTY | F105: CONSTRUCTION_COMPLETED_PCT | G105: 1. Concluído | H105: 1. Concluído | I105: 22/07/2024: Entrega de campo para testes | J105: 45491 | K105: 45495 | L105: 45495 | O105: Bens Imóveis
A106: =E106&F106 -> PROPERTYDATA_DATE_PART | B106: Pilar III | C106: Bens Imóveis - Output | D106: 2. Campo | E106: PROPERTY | F106: DATA_DATE_PART | G106: 1. Concluído | H106: 1. Concluído | O106: Bens Imóveis
A107: =E107&F107 -> PROPERTYCGARANT_BEM | B107: Pilar III | C107: Bens Imóveis - Output | D107: 2. Campo | E107: PROPERTY | F107: CGARANT_BEM | G107: 6. Em implementação (re-especificação) | H107: 6. Em implementação (re-especificação) | O107: Bens Imóveis
A108: =E108&F108 -> PROPERTYURBANIZATION | B108: Pilar III | C108: Bens Imóveis - Output | D108: 2. Campo | E108: PROPERTY | F108: URBANIZATION | G108: 1. Concluído | H108: 1. Concluído | O108: Bens Imóveis
A109: =E109&F109 -> PROPERTY_ENERGY_CERTIFICATEn.a. | B109: Pilar III | C109: Bens Imóveis - Output | D109: 1. Universo | E109: PROPERTY_ENERGY_CERTIFICATE | F109: n.a. | G109: 1. Concluído | H109: 1. Concluído | O109: Bens Imóveis
A110: =E110&F110 -> PROPERTY_ENERGY_CERTIFICATEPROPERTY_BANK_ID | B110: Pilar III | C110: Bens Imóveis - Output | D110: 2. Campo | E110: PROPERTY_ENERGY_CERTIFICATE | F110: PROPERTY_BANK_ID | G110: 1. Concluído | H110: 1. Concluído | O110: Bens Imóveis
A111: =E111&F111 -> PROPERTY_ENERGY_CERTIFICATEPROPERTY_BRANCH_CODE | B111: Pilar III | C111: Bens Imóveis - Output | D111: 2. Campo | E111: PROPERTY_ENERGY_CERTIFICATE | F111: PROPERTY_BRANCH_CODE | G111: 1. Concluído | H111: 1. Concluído | O111: Bens Imóveis
A112: =E112&F112 -> PROPERTY_ENERGY_CERTIFICATEPROPERTY_CONTRACT_ID | B112: Pilar III | C112: Bens Imóveis - Output | D112: 2. Campo | E112: PROPERTY_ENERGY_CERTIFICATE | F112: PROPERTY_CONTRACT_ID | G112: 1. Concluído | H112: 1. Concluído | O112: Bens Imóveis
...

Sheet Plano Campos
C7: Re-especificação
C8: Entrega IT prevista
C9: Entrega IT real
C10: Testes | M10: Outubro | N10: Novembro | T10: Dezembro | AD10: Janeiro
M11: 45590 | N11: 45597 | O11: 45604 | P11: 45610 | Q11: 45611 | R11: 45618 | S11: 45625 | T11: 45632 | U11: 45639 | V11: 45646 | W11: 45649 | X11: 45650 | Y11: 45651 | Z11: 45652 | AA11: 45653 | AB11: 45656 | AC11: 45657 | AD11: =AD12 -> 45658 | AE11: 45667 | AF11: 45674 | AG11: 45678
B12: Âmbito | C12: Sub-âmbito | D12: Tabela | E12: Entrega | F12: Campo | G12: Status Atual | H12: Data Fim Testes (prevista) | I12: Status Atual (%) | J12: Status Estimado (%) | K12: Variação (%) | L12: Observações | M12: 45590 | N12: 45597 | O12: 45604 | P12: 45610 | Q12: 45611 | R12: 45618 | S12: 45625 | T12: 45632 | U12: 45639 | V12: 45646 | W12: 45649 | X12: 45650 | Y12: 45651 | Z12: 45652 | AA12: 45653 | AB12: 45656 | AC12: 45657 | AD12: =WORKDAY(AC12,1) -> 45658 | AE12: 45667 | AF12: 45674 | AG12: 45678
B13: Pilar III | C13: Pilar III | D13: lt002_instrument | E13: Entrega #1 | F13: 1 | G13: Concluído | H13: 45593 | I13: 1 | J13: 1 | K13: 0 | L13: n.a.
B14: Pilar III | C14: Modelo Verde - Output | D14: modesg_out_bens_imoveis | E14: Entrega #1 (Re-especificação) | F14: 8 | G14: Concluído | H14: 45611 | I14: 1 | J14: 1 | K14: 0 | L14: n.a. | Q14: x
B15: Pilar III | C15: Modelo Verde - Input | D15: modesg_param_sfcs_taxon_europeia | E15: Entrega #1 | F15: 15 | G15: Concluído | H15: 45611 | I15: 1 | J15: 1 | K15: 0 | L15: n.a. | Q15: x
B16: Pilar III | C16: Modelo Verde - Input | D16: modesg_param_sfcs_taxon_europeia | E16: Entrega #1 (Pendência Negócio) | F16: 1 | G16: Pendente CdG | H16: 45611 | I16: 0.25 | J16: 1 | K16: -0.75 | L16: Pendente de alteração de parametrizaçao de marcação verde com CdG (categorias SFICS) | Q16: x
B17: Pilar III | C17: Modelo Verde - Output | D17: modesg_out_emss_vcls | E17: Entrega #1 | F17: 3 | G17: Concluído | H17: 45618 | I17: 1 | J17: 1 | K17: 0 | L17: n.a. | R17: x
B18: Pilar III | C18: Pilar III | D18: lt827_mthd_usd_instrmnt | E18: Entrega #1 (Re-especificação) | F18: 10 | G18: Concluído | H18: 45625 | I18: 1 | J18: 1 | K18: 0 | L18: 29/11: Conclusão de teste aos campos | S18: x
B19: Pilar III | C19: Pilar III | D19: lt003_entity | E19: Entrega #1 | F19: 15 | G19: Concluído | H19: 45625 | I19: 1 | J19: 1 | K19: 0 | L19: 29/11: Conclusão de teste aos campos | S19: x
B20: Pilar III | C20: Pilar III | D20: lt002_instrument | E20: Entrega #2 | F20: 2 | G20: Concluído | H20: 45625 | I20: 1 | J20: 1 | K20: 0 | L20: 29/11: Conclusão de teste aos campos | S20: x
B21: Pilar III | C21: Pilar III | D21: lt004_protection | E21: Entrega #1 | F21: 2 | G21: Concluído | H21: 45632 | I21: 1 | J21: 1 | K21: 0 | L21: 06/12: Conclusão de teste aos campos | T21: x
B22: Pilar III | C22: Pilar III | D22: lt004_protection | E22: Entrega #1 (Re-especificação) | F22: 2 | G22: IT - Em implementação | H22: 45646 | I22: 0 | J22: 1 | K22: -1 | L22: Re-especificação sobre os campos ep_scr e epc_lbl -> a aguardar data de entrega. Pendente de entrega do Modelo de Bens Imóveis | T22: x | U22: x | V22: x
B23: Pilar III | C23: Pilar III | D23: lt004_protection | E23: Entrega #1 (Incidências) | F23: 1 | G23: Concluído | H23: 45639 | I23: 1 | J23: 1 | K23: 0 | L23: 13/12: Conclusão de teste ao campo | T23: x | U23: x
B24: Pilar III | C24: Pilar III | D24: lt003_entity | E24: Entrega #2 | F24: 3 | G24: Concluído | H24: 45632 | I24: 1 | J24: 1 | K24: 0 | L24: 06/12: Conclusão de teste aos campos | T24: x
B25: Pilar III | C25: Pilar III | D25: lt003_entity | E25: Entrega #2 (Incidências) | F25: 1 | G25: IT - Correção de incidências | H25: 45646 | I25: 0 | J25: 1 | K25: -1 | L25: Campo com incidência -> a aguardar data de entrega | T25: x | U25: x | V25: x
B26: Pilar III | C26: Pilar III | D26: lt003_entity | E26: Entrega #2 (Re-especificação) | F26: 1 | G26: IT - Em implementação | H26: 45646 | I26: 0 | J26: 1 | K26: -1 | L26: Re-especificação sobre o campo grp_ttl_lblty -> a aguardar data de entrega | T26: x | U26: x | V26: x
B27: Pilar III | C27: Pilar III | D27: lt003_entity | E27: Entrega #5 (Incidências) | F27: 1 | G27: Concluído | H27: 45639 | I27: 1 | J27: 1 | K27: 0 | L27: 13/12: Conclusão de teste ao campo | T27: x | U27: x
B28: Pilar III | C28: Pilar III | D28: lt004_protection | E28: Entrega #2 | F28: 3 | G28: Concluído | H28: 45632 | I28: 1 | J28: 1 | K28: 0 | L28: 06/12: Conclusão de teste aos campos | T28: x
B29: Pilar III | C29: Pilar III | D29: lt004_protection | E29: Entrega #2 | F29: 1 | G29: Concluído | H29: 45639 | I29: 1 | J29: 1 | K29: 0 | L29: 13/12: Conclusão de teste ao campo | T29: x | U29: x
B30: Pilar III | C30: Pilar III | D30: lt004_protection | E30: Entrega #2 | F30: 1 | G30: Pendente Loan Tape | H30: 45646 | I30: 0 | J30: 1 | K30: -1 | L30: Pendente da entrega do campo na Loan Tape Estrutural | T30: x | U30: x | V30: x
B31: Pilar III | C31: Modelo Verde - Output | D31: modesg_out_empr_info_nfin | E31: Entrega #1 | F31: 14 | G31: Concluído | H31: 45639 | I31: 1 | J31: 1 | K31: 0 | L31: 13/12: Conclusão de teste aos campos | T31: x | U31: x
B32: Pilar III | C32: Pilar III | D32: lt003_entity | E32: Entrega #4 | F32: 1 | G32: IT - Correção de incidências | H32: 45646 | I32: 0 | J32: 1 | K32: -1 | L32: Campo com incidência -> a aguardar data de entrega | T32: x | U32: x | V32: x
B33: Pilar III | C33: Modelo Verde - Output | D33: modesg_out_emss_vcls | E33: Entrega #1 (Incidências) | F33: 4 | G33: Concluído | H33: 45632 | I33: 1 | J33: 1 | K33: 0 | L33: 06/12: Conclusão de teste aos campos | T33: x
B34: Pilar III | C34: Pilar III | D34: lt003_entity | E34: Entrega #1 | F34: 2 | G34: Concluído | H34: 45639 | I34: 1 | J34: 1 | K34: 0 | L34: 13/12: Conclusão de teste aos campos | U34: x
B35: Pilar III | C35: Pilar III | D35: lt003_entity | E35: Entrega #1 | F35: 3 | G35: IT - Correção de incidências | H35: 45646 | I35: 0 | J35: 1 | K35: -1 | L35: Campos com incidências -> a aguardar data de entrega | U35: x | V35: x
B36: Pilar III | C36: Pilar III | D36: lt003_entity | E36: Entrega #1 (Dependências) | F36: 2 | G36: Concluído | H36: 45639 | I36: 1 | J36: 1 | K36: 0 | L36: 13/12: Conclusão de teste aos campos | U36: x
B37: Pilar III | C37: Modelo Verde - Output | D37: modesg_out_empr_info_nfin | E37: Entrega #1 | F37: 6 | G37: NYD - Em teste | H37: 45674 | I37: 0.25 | J37: 0 | K37: 0.25 | L37: n.a. | AF37: x
B38: Pilar III | C38: Pilar III | D38: lt003_entity | E38: Entrega #3 | F38: 3 | G38: Concluído | H38: 45639 | I38: 1 | J38: 1 | K38: 0 | L38: 13/12: Conclusão de teste aos campos | U38: x
B39: Pilar III | C39: Modelo Verde - Output | D39: modesg_out_empr_info_nfin | E39: Entrega #2 | F39: 6 | G39: NYD - Em teste | H39: 45674 | I39: 0.67 | J39: 0.66666667 | K39: 0.0033333333 | L39: n.a. | AF39: x
B40: Pilar III | C40: Pilar III | D40: lt002_instrument | E40: Entrega #3 | F40: 1 | G40: Pendente CdG | H40: 45646 | I40: 0.25 | J40: 1 | K40: -0.75 | L40: Pendente de alteração de parametrizaçao de marcação verde com CdG (categorias SFICS) | U40: x | V40: x
B41: Pilar III | C41: Pilar III | D41: lt007_instr_activity | E41: Entrega #1 | F41: 4 | G41: NYD - Em teste | H41: 45646 | I41: 0.25 | J41: 0 | K41: 0.25 | L41: n.a. | V41: x
B42: Pilar III | C42: Pilar III | D42: lt004_protection | E42: Entrega #3 | F42: 5 | G42: NYD - Em teste | H42: 45646 | I42: 0.25 | J42: 0 | K42: 0.25 | L42: n.a. | V42: x
B43: Pilar III | C43: Pilar III | D43: lt004_protection | E43: Entrega #4 (Re-especificação) | F43: 1 | G43: Pendente Modelo Bens Imóveis | H43: 45646 | I43: 0 | J43: 0 | K43: 0 | L43: Re-especificação com base num novo campo do MBI | V43: x
B44: Pilar III | C44: Modelo Verde - Output | D44: modesg_out_sfcs_taxon_europeia | E44: Entrega #1 | F44: 12 | G44: NYD - Em teste | H44: 45646 | I44: 0.7 | J44: 0.69565217 | K44: 0.0043478261 | L44: Nova data de entrega > de 28/11 para 02/12 | V44: x
B45: Pilar III | C45: Pilar III | D45: lt002_instrument | E45: Entrega #2 (Re-especificação2) | F45: 3 | G45: NYD - Em teste | H45: 45646 | I45: 0.25 | J45: 0 | K45: 0.25 | L45: Nova data de entrega de 15/11 para 05/12 | V45: x
B46: Pilar III | C46: Modelo Verde - Output | D46: modesg_out_empr_info_nfin | E46: Entrega #3 | F46: 4 | G46: NYD - Em teste | H46: 45646 | I46: 0.25 | J46: 0.2 | K46: 0.05 | L46: Nova data de entrega > de 28/11 para 12/12 | V46: x
B47: Pilar III | C47: Pilar III | D47: lt004_protection | E47: Entrega #1 (Re-especificação 2) | F47: 6 | G47: NYD - Em teste | H47: 45649 | I47: 0.25 | J47: 0 | K47: 0.25 | L47: Re-especificação sobre campos de scopes sobre tipo de propriedade. Nova data de entrega de 31/10 para 05/12 | W47: x
B48: Pilar III | C48: Bens Imóveis - Input | D48: ENERGY_CERTIFICATE_EST_INPUT | E48: Entrega #1 | F48: 12 | G48: IT - Em implementação | H48: 45667 | I48: 0 | J48: 0 | K48: 0 | L48: Apesar de entregue, não é possível testar por temos de usuário | AE48: x
B49: Pilar III | C49: Bens Imóveis - Output | D49: PROPERTY | E49: Entrega #1 | F49: 1 | G49: IT - Em implementação | H49: 45667 | I49: 0 | J49: 0 | K49: 0 | L49: Novo campo na tabela. Nova data de entrega de 05/12 para 19/12 | AE49: x
B50: Pilar III | C50: Bens Imóveis - Input | D50: GLOVAL - Tabela unificada/ traçabilidade | E50: Entrega #1 | F50: tbd | G50: IT - Em implementação | H50: 45667 | I50: 0 | J50: 0 | K50: 0 | L50: Nova data de entrega > de 28/11 para 04/12 | AE50: x
B51: Pilar III | C51: Modelo Verde - Output | D51: modesg_out_bens_imoveis | E51: Entrega #2 | F51: 4 | G51: NYD - Em teste | H51: 45674 | I51: 0.25 | J51: 0 | K51: 0.25 | L51: Só será possível testar com base no input de risco físico corporativo | AF51: x
A52: =D52&F52 -> lt002_instrument3 | B52: Pilar III | C52: Pilar III | D52: lt002_instrument | E52: Entrega #4 | F52: 3 | G52: NYD - Em teste | H52: 45674 | I52: 0.25 | J52: 0 | K52: 0.25 | L52: Campos comuns ao GD com incidência > a aguardar data de entrega | AF52: x
B53: Pilar III | C53: Bens Imóveis - Output | D53: PROPERTY_ENERGY_CERTIFICATE | E53: Entrega #1 (Re-especificação) | F53: 22 | G53: Concluído | H53: 45639 | I53: 1 | J53: 1 | K53: 0 | L53: 13/12: Conclusão de teste aos campos | U53: x
B54: Pilar III | C54: Bens Imóveis - Input | D54: GLOVAL - Reprocessamento via front | E54: Entrega #1 | F54: tbd | G54: IT - Em implementação | H54: 45674 | I54: 0 | J54: 0 | K54: 0 | L54: Nova data de entrega de 28/11para 04/12. Nova data de entrega de 04/12 para 19/12 | AF54: x
A55: =D55&F55 -> munichRetbd | B55: Pilar III | C55: Modelo Verde - Input | D55: munichRe | E55: Entrega #1 | F55: tbd | G55: IT - Em implementação | H55: 45678 | I55: 0 | J55: 0 | K55: 0 | L55: Entrega de IT adiada. Será testado em Janeiro na extensão do projeto | AG55: 1
B56: Pilar III | C56: Todos | D56: RE-TESTES
