Workbook

Sheet PDS
E2: Total | G2: Concluido | I2: Mapeamento com LT fechado, mas parametrização pendente | K2: Novo campo, mapeamento datalake fechado, com necessidade de criar parametrização | M2: Novo campo, mapeamento datalake fechado, sem necessidade de criar parametrização | O2: Novo campo, mapeamento datalake pendente, com necessidade de criar parametrização | Q2: Novo campo, mapeamento datalake pendente, sem necessidade de criar parametrização | S2: Por iniciar
B3: Módulo | C3: Submódulo | D3: Nome do Ficheiro | E3: abs | F3: Total (%) | G3: abs | H3: % | I3: abs | J3: % | K3: abs | L3: % | M3: abs | N3: % | O3: abs | P3: % | Q3: abs | R3: % | S3: abs | T3: %
B4: Exposures to legal persons | C4: Instruments | D4: XXXXX_YYYYMMDD_01_01_leg_instr.csv | E4: =COUNTA(LEGALP_INSTRUMENTS!A3:A27) -> 7 | F4: =SUM(H4,J4,L4,N4,P4,R4,T4) -> 1 | G4: =COUNTIF(LEGALP_INSTRUMENTS!M:M,"Concluido") -> 5 | H4: =G4/E4 -> 0.71428571 | I4: =COUNTIF(LEGALP_INSTRUMENTS!M:M,"Mapeamento com LT fechado, mas parametrização pendente") -> 1 | J4: =I4/E4 -> 0.14285714 | K4: =COUNTIF(LEGALP_INSTRUMENTS!M:M,"Novo campo, mapeamento datalake fechado, com necessidade de criar parametrização") -> 0 | L4: =K4/E4 -> 0 | M4: =COUNTIF(LEGALP_INSTRUMENTS!M:M,"Novo campo, mapeamento datalake fechado, sem necessidade de criar parametrização") -> 0 | N4: =M4/E4 -> 0 | O4: =COUNTIF(LEGALP_INSTRUMENTS!M:M,"Novo campo, mapeamento datalake pendente, com necessidade de criar parametrização") -> 1 | P4: =O4/E4 -> 0.14285714 | Q4: =COUNTIF(LEGALP_INSTRUMENTS!M:M,"Novo campo, mapeamento datalake pendente, sem necessidade de criar parametrização") -> 0 | R4: =Q4/E4 -> 0 | S4: =COUNTIF(LEGALP_INSTRUMENTS!M:M,"Por iniciar") -> 0 | T4: =S4/E4 -> 0
C5: Counterparties | D5: XXXXX_YYYYMMDD_01_02_leg_count.csv | E5: =COUNTA(LEGALP_COUNTERPARTIES!A3:A27) -> 5 | F5: =SUM(H5,J5,L5,N5,P5,R5,T5) -> 1 | G5: =COUNTIF(LEGALP_COUNTERPARTIES!M:M,"Concluido") -> 4 | H5: =G5/E5 -> 0.8 | I5: =COUNTIF(LEGALP_COUNTERPARTIES!M:M,"Mapeamento com LT fechado, mas parametrização pendente") -> 0 | J5: =I5/E5 -> 0 | K5: =COUNTIF(LEGALP_COUNTERPARTIES!M:M,"Novo campo, mapeamento datalake fechado, com necessidade de criar parametrização") -> 0 | L5: =K5/E5 -> 0 | M5: =COUNTIF(LEGALP_COUNTERPARTIES!M:M,"Novo campo, mapeamento datalake fechado, sem necessidade de criar parametrização") -> 0 | N5: =M5/E5 -> 0 | O5: =COUNTIF(LEGALP_COUNTERPARTIES!M:M,"Novo campo, mapeamento datalake pendente, com necessidade de criar parametrização") -> 0 | P5: =O5/E5 -> 0 | Q5: =COUNTIF(LEGALP_COUNTERPARTIES!M:M,"Novo campo, mapeamento datalake pendente, sem necessidade de criar parametrização") -> 0 | R5: =Q5/E5 -> 0 | S5: =COUNTIF(LEGALP_COUNTERPARTIES!M:M,"Por iniciar") -> 1 | T5: =S5/E5 -> 0.2
C6: Protections | D6: XXXXX_YYYYMMDD_01_03_leg_prot.csv | E6: =COUNTA(LEGALP_PROTECTIONS!A3:A18) -> 8 | F6: =SUM(H6,J6,L6,N6,P6,R6,T6) -> 1 | G6: =COUNTIF(LEGALP_PROTECTIONS!M:M,"Concluido") -> 3 | H6: =G6/E6 -> 0.375 | I6: =COUNTIF(LEGALP_PROTECTIONS!M:M,"Mapeamento com LT fechado, mas parametrização pendente") -> 1 | J6: =I6/E6 -> 0.125 | K6: =COUNTIF(LEGALP_PROTECTIONS!M:M,"Novo campo, mapeamento datalake fechado, com necessidade de criar parametrização") -> 0 | L6: =K6/E6 -> 0 | M6: =COUNTIF(LEGALP_PROTECTIONS!M:M,"Novo campo, mapeamento datalake fechado, sem necessidade de criar parametrização") -> 1 | N6: =M6/E6 -> 0.125 | O6: =COUNTIF(LEGALP_PROTECTIONS!M:M,"Novo campo, mapeamento datalake pendente, com necessidade de criar parametrização") -> 1 | P6: =O6/E6 -> 0.125 | Q6: =COUNTIF(LEGALP_PROTECTIONS!M:M,"Novo campo, mapeamento datalake pendente, sem necessidade de criar parametrização") -> 2 | R6: =Q6/E6 -> 0.25 | S6: =COUNTIF(LEGALP_PROTECTIONS!M:M,"Por iniciar") -> 0 | T6: =S6/E6 -> 0
C7: Instrument-Counterparty relation | D7: XXXXX_YYYYMMDD_01_04_leg_instr_count.csv | E7: =COUNTA(LEGALP_INSTRUMENT_COUNTERPARTY!A3:A7) -> 2 | F7: =SUM(H7,J7,L7,N7,P7,R7,T7) -> 1 | G7: =COUNTIF(LEGALP_INSTRUMENT_COUNTERPARTY!M:M,"Concluido") -> 2 | H7: =G7/E7 -> 1 | I7: =COUNTIF(LEGALP_INSTRUMENT_COUNTERPARTY!M:M,"Mapeamento com LT fechado, mas parametrização pendente") -> 0 | J7: =I7/E7 -> 0 | K7: =COUNTIF(LEGALP_INSTRUMENT_COUNTERPARTY!M:M,"Novo campo, mapeamento datalake fechado, com necessidade de criar parametrização") -> 0 | L7: =K7/E7 -> 0 | M7: =COUNTIF(LEGALP_INSTRUMENT_COUNTERPARTY!M:M,"Novo campo, mapeamento datalake fechado, sem necessidade de criar parametrização") -> 0 | N7: =M7/E7 -> 0 | O7: =COUNTIF(LEGALP_INSTRUMENT_COUNTERPARTY!M:M,"Novo campo, mapeamento datalake pendente, com necessidade de criar parametrização") -> 0 | P7: =O7/E7 -> 0 | Q7: =COUNTIF(LEGALP_INSTRUMENT_COUNTERPARTY!M:M,"Novo campo, mapeamento datalake pendente, sem necessidade de criar parametrização") -> 0 | R7: =Q7/E7 -> 0 | S7: =COUNTIF(LEGALP_INSTRUMENT_COUNTERPARTY!M:M,"Por iniciar") -> 0 | T7: =S7/E7 -> 0
C8: Instrument-Protection relation | D8: XXXXX_YYYYMMDD_01_05_leg_instr_prot.csv | E8: =COUNTA(LEGALP_INSTRUMENT_PROTECTION!A3:A10) -> 2 | F8: =SUM(H8,J8,L8,N8,P8,R8,T8) -> 1 | G8: =COUNTIF(LEGALP_INSTRUMENT_PROTECTION!M:M,"Concluido") -> 2 | H8: =G8/E8 -> 1 | I8: =COUNTIF(LEGALP_INSTRUMENT_PROTECTION!M:M,"Mapeamento com LT fechado, mas parametrização pendente") -> 0 | J8: =I8/E8 -> 0 | K8: =COUNTIF(LEGALP_INSTRUMENT_PROTECTION!M:M,"Novo campo, mapeamento datalake fechado, com necessidade de criar parametrização") -> 0 | L8: =K8/E8 -> 0 | M8: =COUNTIF(LEGALP_INSTRUMENT_PROTECTION!M:M,"Novo campo, mapeamento datalake fechado, sem necessidade de criar parametrização") -> 0 | N8: =M8/E8 -> 0 | O8: =COUNTIF(LEGALP_INSTRUMENT_PROTECTION!M:M,"Novo campo, mapeamento datalake pendente, com necessidade de criar parametrização") -> 0 | P8: =O8/E8 -> 0 | Q8: =COUNTIF(LEGALP_INSTRUMENT_PROTECTION!M:M,"Novo campo, mapeamento datalake pendente, sem necessidade de criar parametrização") -> 0 | R8: =Q8/E8 -> 0 | S8: =COUNTIF(LEGALP_INSTRUMENT_PROTECTION!M:M,"Por iniciar") -> 0 | T8: =S8/E8 -> 0
B9: Exposures to natural persons | C9: Instruments | D9: XXXXX_YYYYMMDD_02_01_nat_instr.csv | E9: =COUNTA(NATURALP_INSTRUMENTS!A3:A142) -> 53 | F9: =SUM(H9,J9,L9,N9,P9,R9,T9) -> 1 | G9: =COUNTIF(NATURALP_INSTRUMENTS!M:M,"Concluido") -> 32 | H9: =G9/E9 -> 0.60377358 | I9: =COUNTIF(NATURALP_INSTRUMENTS!M:M,"Mapeamento com LT fechado, mas parametrização pendente") -> 15 | J9: =I9/E9 -> 0.28301887 | K9: =COUNTIF(NATURALP_INSTRUMENTS!M:M,"Novo campo, mapeamento datalake fechado, com necessidade de criar parametrização") -> 1 | L9: =K9/E9 -> 0.018867925 | M9: =COUNTIF(NATURALP_INSTRUMENTS!M:M,"Novo campo, mapeamento datalake fechado, sem necessidade de criar parametrização") -> 0 | N9: =M9/E9 -> 0 | O9: =COUNTIF(NATURALP_INSTRUMENTS!M:M,"Novo campo, mapeamento datalake pendente, com necessidade de criar parametrização") -> 3 | P9: =O9/E9 -> 0.056603774 | Q9: =COUNTIF(NATURALP_INSTRUMENTS!M:M,"Novo campo, mapeamento datalake pendente, sem necessidade de criar parametrização") -> 2 | R9: =Q9/E9 -> 0.037735849 | S9: =COUNTIF(NATURALP_INSTRUMENTS!M:M,"Por iniciar") -> 0 | T9: =S9/E9 -> 0
C10: Counterparties | D10: XXXXX_YYYYMMDD_02_02_nat_count.csv | E10: =COUNTA(NATURALP_COUNTERPARTIES!A3:A29) -> 8 | F10: =SUM(H10,J10,L10,N10,P10,R10,T10) -> 1 | G10: =COUNTIF(NATURALP_COUNTERPARTIES!M:M,"Concluido") -> 6 | H10: =G10/E10 -> 0.75 | I10: =COUNTIF(NATURALP_COUNTERPARTIES!M:M,"Mapeamento com LT fechado, mas parametrização pendente") -> 1 | J10: =I10/E10 -> 0.125 | K10: =COUNTIF(NATURALP_COUNTERPARTIES!M:M,"Novo campo, mapeamento datalake fechado, com necessidade de criar parametrização") -> 0 | L10: =K10/E10 -> 0 | M10: =COUNTIF(NATURALP_COUNTERPARTIES!M:M,"Novo campo, mapeamento datalake fechado, sem necessidade de criar parametrização") -> 0 | N10: =M10/E10 -> 0 | O10: =COUNTIF(NATURALP_COUNTERPARTIES!M:M,"Novo campo, mapeamento datalake pendente, com necessidade de criar parametrização") -> 0 | P10: =O10/E10 -> 0 | Q10: =COUNTIF(NATURALP_COUNTERPARTIES!M:M,"Novo campo, mapeamento datalake pendente, sem necessidade de criar parametrização") -> 0 | R10: =Q10/E10 -> 0 | S10: =COUNTIF(NATURALP_COUNTERPARTIES!M:M,"Por iniciar") -> 1 | T10: =S10/E10 -> 0.125
C11: Protections | D11: XXXXX_YYYYMMDD_02_03_nat_prot.csv | E11: =COUNTA(NATURALP_PROTECTIONS!A3:A27) -> 17 | F11: =SUM(H11,J11,L11,N11,P11,R11,T11) -> 1 | G11: =COUNTIF(NATURALP_PROTECTIONS!M:M,"Concluido") -> 11 | H11: =G11/E11 -> 0.64705882 | I11: =COUNTIF(NATURALP_PROTECTIONS!M:M,"Mapeamento com LT fechado, mas parametrização pendente") -> 3 | J11: =I11/E11 -> 0.17647059 | K11: =COUNTIF(NATURALP_PROTECTIONS!M:M,"Novo campo, mapeamento datalake fechado, com necessidade de criar parametrização") -> 0 | L11: =K11/E11 -> 0 | M11: =COUNTIF(NATURALP_PROTECTIONS!M:M,"Novo campo, mapeamento datalake fechado, sem necessidade de criar parametrização") -> 1 | N11: =M11/E11 -> 0.058823529 | O11: =COUNTIF(NATURALP_PROTECTIONS!M:M,"Novo campo, mapeamento datalake pendente, com necessidade de criar parametrização") -> 0 | P11: =O11/E11 -> 0 | Q11: =COUNTIF(NATURALP_PROTECTIONS!M:M,"Novo campo, mapeamento datalake pendente, sem necessidade de criar parametrização") -> 2 | R11: =Q11/E11 -> 0.11764706 | S11: =COUNTIF(NATURALP_PROTECTIONS!M:M,"Por iniciar") -> 0 | T11: =S11/E11 -> 0
C12: Instrument-Counterparty relation | D12: XXXXX_YYYYMMDD_02_04_nat_instr_count.csv | E12: =COUNTA(NATURALP_INSTRUMENT_COUNTERPART!A3:A9) -> 4 | F12: =SUM(H12,J12,L12,N12,P12,R12,T12) -> 1 | G12: =COUNTIF(NATURALP_INSTRUMENT_COUNTERPART!M:M,"Concluido") -> 3 | H12: =G12/E12 -> 0.75 | I12: =COUNTIF(NATURALP_INSTRUMENT_COUNTERPART!M:M,"Mapeamento com LT fechado, mas parametrização pendente") -> 0 | J12: =I12/E12 -> 0 | K12: =COUNTIF(NATURALP_INSTRUMENT_COUNTERPART!M:M,"Novo campo, mapeamento datalake fechado, com necessidade de criar parametrização") -> 0 | L12: =K12/E12 -> 0 | M12: =COUNTIF(NATURALP_INSTRUMENT_COUNTERPART!M:M,"Novo campo, mapeamento datalake fechado, sem necessidade de criar parametrização") -> 0 | N12: =M12/E12 -> 0 | O12: =COUNTIF(NATURALP_INSTRUMENT_COUNTERPART!M:M,"Novo campo, mapeamento datalake pendente, com necessidade de criar parametrização") -> 1 | P12: =O12/E12 -> 0.25 | Q12: =COUNTIF(NATURALP_INSTRUMENT_COUNTERPART!M:M,"Novo campo, mapeamento datalake pendente, sem necessidade de criar parametrização") -> 0 | R12: =Q12/E12 -> 0 | S12: =COUNTIF(NATURALP_INSTRUMENT_COUNTERPART!M:M,"Por iniciar") -> 0 | T12: =S12/E12 -> 0
C13: Instrument-Protection relation | D13: XXXXX_YYYYMMDD_02_05_nat_instr_prot.csv | E13: =COUNTA(NATURALP_INSTRUMENT_PROTECTION!A3:A12) -> 4 | F13: =SUM(H13,J13,L13,N13,P13,R13,T13) -> 1 | G13: =COUNTIF(NATURALP_INSTRUMENT_PROTECTION!M:M,"Concluido") -> 4 | H13: =G13/E13 -> 1 | I13: =COUNTIF(NATURALP_INSTRUMENT_PROTECTION!M:M,"Mapeamento com LT fechado, mas parametrização pendente") -> 0 | J13: =I13/E13 -> 0 | K13: =COUNTIF(NATURALP_INSTRUMENT_PROTECTION!M:M,"Novo campo, mapeamento datalake fechado, com necessidade de criar parametrização") -> 0 | L13: =K13/E13 -> 0 | M13: =COUNTIF(NATURALP_INSTRUMENT_PROTECTION!M:M,"Novo campo, mapeamento datalake fechado, sem necessidade de criar parametrização") -> 0 | N13: =M13/E13 -> 0 | O13: =COUNTIF(NATURALP_INSTRUMENT_PROTECTION!M:M,"Novo campo, mapeamento datalake pendente, com necessidade de criar parametrização") -> 0 | P13: =O13/E13 -> 0 | Q13: =COUNTIF(NATURALP_INSTRUMENT_PROTECTION!M:M,"Novo campo, mapeamento datalake pendente, sem necessidade de criar parametrização") -> 0 | R13: =Q13/E13 -> 0 | S13: =COUNTIF(NATURALP_INSTRUMENT_PROTECTION!M:M,"Por iniciar") -> 0 | T13: =S13/E13 -> 0
B14: Off-balance sheet exposures | C14: Instruments | D14: XXXXX_YYYYMMDD_03_01_off_instr.csv | E14: =COUNTA(OFFBAL_INSTRUMENTS!A3:A67) -> 27 | F14: =SUM(H14,J14,L14,N14,P14,R14,T14) -> 1 | G14: =COUNTIF(OFFBAL_INSTRUMENTS!M:M,"Concluido") -> 18 | H14: =G14/E14 -> 0.66666667 | I14: =COUNTIF(OFFBAL_INSTRUMENTS!M:M,"Mapeamento com LT fechado, mas parametrização pendente") -> 6 | J14: =I14/E14 -> 0.22222222 | K14: =COUNTIF(OFFBAL_INSTRUMENTS!M:M,"Novo campo, mapeamento datalake fechado, com necessidade de criar parametrização") -> 0 | L14: =K14/E14 -> 0 | M14: =COUNTIF(OFFBAL_INSTRUMENTS!M:M,"Novo campo, mapeamento datalake fechado, sem necessidade de criar parametrização") -> 0 | N14: =M14/E14 -> 0 | O14: =COUNTIF(OFFBAL_INSTRUMENTS!M:M,"Novo campo, mapeamento datalake pendente, com necessidade de criar parametrização") -> 2 | P14: =O14/E14 -> 0.074074074 | Q14: =COUNTIF(OFFBAL_INSTRUMENTS!M:M,"Novo campo, mapeamento datalake pendente, sem necessidade de criar parametrização") -> 1 | R14: =Q14/E14 -> 0.037037037 | S14: =COUNTIF(OFFBAL_INSTRUMENTS!M:M,"Por iniciar") -> 0 | T14: =S14/E14 -> 0
C15: Counterparties | D15: XXXXX_YYYYMMDD_03_02_off_count.csv | E15: =COUNTA(OFFBAL_COUNTERPARTIES!A3:A59) -> 30 | F15: =SUM(H15,J15,L15,N15,P15,R15,T15) -> 1 | G15: =COUNTIF(OFFBAL_COUNTERPARTIES!M:M,"Concluido") -> 12 | H15: =G15/E15 -> 0.4 | I15: =COUNTIF(OFFBAL_COUNTERPARTIES!M:M,"Mapeamento com LT fechado, mas parametrização pendente") -> 5 | J15: =I15/E15 -> 0.16666667 | K15: =COUNTIF(OFFBAL_COUNTERPARTIES!M:M,"Novo campo, mapeamento datalake fechado, com necessidade de criar parametrização") -> 0 | L15: =K15/E15 -> 0 | M15: =COUNTIF(OFFBAL_COUNTERPARTIES!M:M,"Novo campo, mapeamento datalake fechado, sem necessidade de criar parametrização") -> 0 | N15: =M15/E15 -> 0 | O15: =COUNTIF(OFFBAL_COUNTERPARTIES!M:M,"Novo campo, mapeamento datalake pendente, com necessidade de criar parametrização") -> 2 | P15: =O15/E15 -> 0.066666667 | Q15: =COUNTIF(OFFBAL_COUNTERPARTIES!M:M,"Novo campo, mapeamento datalake pendente, sem necessidade de criar parametrização") -> 10 | R15: =Q15/E15 -> 0.33333333 | S15: =COUNTIF(OFFBAL_COUNTERPARTIES!M:M,"Por iniciar") -> 1 | T15: =S15/E15 -> 0.033333333
C16: Protections | D16: XXXXX_YYYYMMDD_03_03_off_prot.csv | E16: =COUNTA(OFFBAL_PROTECTIONS!A3:A27) -> 17 | F16: =SUM(H16,J16,L16,N16,P16,R16,T16) -> 1 | G16: =COUNTIF(OFFBAL_PROTECTIONS!M:M,"Concluido") -> 11 | H16: =G16/E16 -> 0.64705882 | I16: =COUNTIF(OFFBAL_PROTECTIONS!M:M,"Mapeamento com LT fechado, mas parametrização pendente") -> 3 | J16: =I16/E16 -> 0.17647059 | K16: =COUNTIF(OFFBAL_PROTECTIONS!M:M,"Novo campo, mapeamento datalake fechado, com necessidade de criar parametrização") -> 0 | L16: =K16/E16 -> 0 | M16: =COUNTIF(OFFBAL_PROTECTIONS!M:M,"Novo campo, mapeamento datalake fechado, sem necessidade de criar parametrização") -> 1 | N16: =M16/E16 -> 0.058823529 | O16: =COUNTIF(OFFBAL_PROTECTIONS!M:M,"Novo campo, mapeamento datalake pendente, com necessidade de criar parametrização") -> 0 | P16: =O16/E16 -> 0 | Q16: =COUNTIF(OFFBAL_PROTECTIONS!M:M,"Novo campo, mapeamento datalake pendente, sem necessidade de criar parametrização") -> 2 | R16: =Q16/E16 -> 0.11764706 | S16: =COUNTIF(OFFBAL_PROTECTIONS!M:M,"Por iniciar") -> 0 | T16: =S16/E16 -> 0
C17: Instrument-Counterparty relation | D17: XXXXX_YYYYMMDD_03_04_off_instr_count.csv | E17: =COUNTA(OFFBAL_INSTRUMENT_COUNTERPARTY!A3:A8) -> 3 | F17: =SUM(H17,J17,L17,N17,P17,R17,T17) -> 1 | G17: =COUNTIF(OFFBAL_INSTRUMENT_COUNTERPARTY!M:M,"Concluido") -> 3 | H17: =G17/E17 -> 1 | I17: =COUNTIF(OFFBAL_INSTRUMENT_COUNTERPARTY!M:M,"Mapeamento com LT fechado, mas parametrização pendente") -> 0 | J17: =I17/E17 -> 0 | K17: =COUNTIF(OFFBAL_INSTRUMENT_COUNTERPARTY!M:M,"Novo campo, mapeamento datalake fechado, com necessidade de criar parametrização") -> 0 | L17: =K17/E17 -> 0 | M17: =COUNTIF(OFFBAL_INSTRUMENT_COUNTERPARTY!M:M,"Novo campo, mapeamento datalake fechado, sem necessidade de criar parametrização") -> 0 | N17: =M17/E17 -> 0 | O17: =COUNTIF(OFFBAL_INSTRUMENT_COUNTERPARTY!M:M,"Novo campo, mapeamento datalake pendente, com necessidade de criar parametrização") -> 0 | P17: =O17/E17 -> 0 | Q17: =COUNTIF(OFFBAL_INSTRUMENT_COUNTERPARTY!M:M,"Novo campo, mapeamento datalake pendente, sem necessidade de criar parametrização") -> 0 | R17: =Q17/E17 -> 0 | S17: =COUNTIF(OFFBAL_INSTRUMENT_COUNTERPARTY!M:M,"Por iniciar") -> 0 | T17: =S17/E17 -> 0
C18: Instrument-Protection relation | D18: XXXXX_YYYYMMDD_03_05_off_instr_prot.csv | E18: =COUNTA(OFFBAL_INSTRUMENT_PROTECTION!A3:A12) -> 4 | F18: =SUM(H18,J18,L18,N18,P18,R18,T18) -> 1 | G18: =COUNTIF(OFFBAL_INSTRUMENT_PROTECTION!M:M,"Concluido") -> 4 | H18: =G18/E18 -> 1 | I18: =COUNTIF(OFFBAL_INSTRUMENT_PROTECTION!M:M,"Mapeamento com LT fechado, mas parametrização pendente") -> 0 | J18: =I18/E18 -> 0 | K18: =COUNTIF(OFFBAL_INSTRUMENT_PROTECTION!M:M,"Novo campo, mapeamento datalake fechado, com necessidade de criar parametrização") -> 0 | L18: =K18/E18 -> 0 | M18: =COUNTIF(OFFBAL_INSTRUMENT_PROTECTION!M:M,"Novo campo, mapeamento datalake fechado, sem necessidade de criar parametrização") -> 0 | N18: =M18/E18 -> 0 | O18: =COUNTIF(OFFBAL_INSTRUMENT_PROTECTION!M:M,"Novo campo, mapeamento datalake pendente, com necessidade de criar parametrização") -> 0 | P18: =O18/E18 -> 0 | Q18: =COUNTIF(OFFBAL_INSTRUMENT_PROTECTION!M:M,"Novo campo, mapeamento datalake pendente, sem necessidade de criar parametrização") -> 0 | R18: =Q18/E18 -> 0 | S18: =COUNTIF(OFFBAL_INSTRUMENT_PROTECTION!M:M,"Por iniciar") -> 0 | T18: =S18/E18 -> 0
B19: Derivatives | C19: - | D19: XXXXX_YYYYMMDD_04_01_derivatives.csv | E19: =COUNTA(DERIVATIVES!A3:A69) -> 29 | F19: =SUM(H19,J19,L19,N19,P19,R19,T19) -> 1 | G19: =COUNTIF(DERIVATIVES!M:M,"Concluido") -> 0 | H19: =G19/E19 -> 0 | I19: =COUNTIF(DERIVATIVES!M:M,"Mapeamento com LT fechado, mas parametrização pendente") -> 0 | J19: =I19/E19 -> 0 | K19: =COUNTIF(DERIVATIVES!M:M,"Novo campo, mapeamento datalake fechado, com necessidade de criar parametrização") -> 0 | L19: =K19/E19 -> 0 | M19: =COUNTIF(DERIVATIVES!M:M,"Novo campo, mapeamento datalake fechado, sem necessidade de criar parametrização") -> 0 | N19: =M19/E19 -> 0 | O19: =COUNTIF(DERIVATIVES!M:M,"Novo campo, mapeamento datalake pendente, com necessidade de criar parametrização") -> 0 | P19: =O19/E19 -> 0 | Q19: =COUNTIF(DERIVATIVES!M:M,"Novo campo, mapeamento datalake pendente, sem necessidade de criar parametrização") -> 0 | R19: =Q19/E19 -> 0 | S19: =COUNTIF(DERIVATIVES!M:M,"Por iniciar") -> 29 | T19: =S19/E19 -> 1
B20: Debt securities | C20: - | D20: XXXXX_YYYYMMDD_05_01_debtsecurities.csv | E20: =COUNTA(DEBT_SECURITIES!A3:A77) -> 40 | F20: =SUM(H20,J20,L20,N20,P20,R20,T20) -> 1 | G20: =COUNTIF(DEBT_SECURITIES!M:M,"Concluido") -> 14 | H20: =G20/E20 -> 0.35 | I20: =COUNTIF(DEBT_SECURITIES!M:M,"Mapeamento com LT fechado, mas parametrização pendente") -> 25 | J20: =I20/E20 -> 0.625 | K20: =COUNTIF(DEBT_SECURITIES!M:M,"Novo campo, mapeamento datalake fechado, com necessidade de criar parametrização") -> 0 | L20: =K20/E20 -> 0 | M20: =COUNTIF(DEBT_SECURITIES!M:M,"Novo campo, mapeamento datalake fechado, sem necessidade de criar parametrização") -> 0 | N20: =M20/E20 -> 0 | O20: =COUNTIF(DEBT_SECURITIES!M:M,"Novo campo, mapeamento datalake pendente, com necessidade de criar parametrização") -> 0 | P20: =O20/E20 -> 0 | Q20: =COUNTIF(DEBT_SECURITIES!M:M,"Novo campo, mapeamento datalake pendente, sem necessidade de criar parametrização") -> 0 | R20: =Q20/E20 -> 0 | S20: =COUNTIF(DEBT_SECURITIES!M:M,"Por iniciar") -> 1 | T20: =S20/E20 -> 0.025
B21: Equity | C21: - | D21: XXXXX_YYYYMMDD_06_01_equity.csv | E21: =COUNTA(EQUITY_INSTRUMENTS!A3:A35) -> 18 | F21: =SUM(H21,J21,L21,N21,P21,R21,T21) -> 1 | G21: =COUNTIF(EQUITY_INSTRUMENTS!M:M,"Concluido") -> 0 | H21: =G21/E21 -> 0 | I21: =COUNTIF(EQUITY_INSTRUMENTS!M:M,"Mapeamento com LT fechado, mas parametrização pendente") -> 0 | J21: =I21/E21 -> 0 | K21: =COUNTIF(EQUITY_INSTRUMENTS!M:M,"Novo campo, mapeamento datalake fechado, com necessidade de criar parametrização") -> 0 | L21: =K21/E21 -> 0 | M21: =COUNTIF(EQUITY_INSTRUMENTS!M:M,"Novo campo, mapeamento datalake fechado, sem necessidade de criar parametrização") -> 0 | N21: =M21/E21 -> 0 | O21: =COUNTIF(EQUITY_INSTRUMENTS!M:M,"Novo campo, mapeamento datalake pendente, com necessidade de criar parametrização") -> 0 | P21: =O21/E21 -> 0 | Q21: =COUNTIF(EQUITY_INSTRUMENTS!M:M,"Novo campo, mapeamento datalake pendente, sem necessidade de criar parametrização") -> 0 | R21: =Q21/E21 -> 0 | S21: =COUNTIF(EQUITY_INSTRUMENTS!M:M,"Por iniciar") -> 18 | T21: =S21/E21 -> 1
B22: DTAs/DTCs | C22: - | D22: XXXXX_YYYYMMDD_07_01_dtasdtcs.csv | E22: =COUNTA(DTA_DTC!A3:A19) -> 17 | F22: =SUM(H22,J22,L22,N22,P22,R22,T22) -> 1 | G22: =COUNTIF(DTA_DTC!M:M,"Concluido") -> 0 | H22: =G22/E22 -> 0 | I22: =COUNTIF(DTA_DTC!M:M,"Mapeamento com LT fechado, mas parametrização pendente") -> 0 | J22: =I22/E22 -> 0 | K22: =COUNTIF(DTA_DTC!M:M,"Novo campo, mapeamento datalake fechado, com necessidade de criar parametrização") -> 0 | L22: =K22/E22 -> 0 | M22: =COUNTIF(DTA_DTC!M:M,"Novo campo, mapeamento datalake fechado, sem necessidade de criar parametrização") -> 0 | N22: =M22/E22 -> 0 | O22: =COUNTIF(DTA_DTC!M:M,"Novo campo, mapeamento datalake pendente, com necessidade de criar parametrização") -> 0 | P22: =O22/E22 -> 0 | Q22: =COUNTIF(DTA_DTC!M:M,"Novo campo, mapeamento datalake pendente, sem necessidade de criar parametrização") -> 0 | R22: =Q22/E22 -> 0 | S22: =COUNTIF(DTA_DTC!M:M,"Por iniciar") -> 17 | T22: =S22/E22 -> 1
B23: Intangible assets | C23: - | D23: XXXXX_YYYYMMDD_08_01_intangible.csv | E23: =COUNTA(INTANGIBLE_ASSETS!A3:A15) -> 13 | F23: =SUM(H23,J23,L23,N23,P23,R23,T23) -> 1 | G23: =COUNTIF(INTANGIBLE_ASSETS!M:M,"Concluido") -> 0 | H23: =G23/E23 -> 0 | I23: =COUNTIF(INTANGIBLE_ASSETS!M:M,"Mapeamento com LT fechado, mas parametrização pendente") -> 0 | J23: =I23/E23 -> 0 | K23: =COUNTIF(INTANGIBLE_ASSETS!M:M,"Novo campo, mapeamento datalake fechado, com necessidade de criar parametrização") -> 0 | L23: =K23/E23 -> 0 | M23: =COUNTIF(INTANGIBLE_ASSETS!M:M,"Novo campo, mapeamento datalake fechado, sem necessidade de criar parametrização") -> 0 | N23: =M23/E23 -> 0 | O23: =COUNTIF(INTANGIBLE_ASSETS!M:M,"Novo campo, mapeamento datalake pendente, com necessidade de criar parametrização") -> 0 | P23: =O23/E23 -> 0 | Q23: =COUNTIF(INTANGIBLE_ASSETS!M:M,"Novo campo, mapeamento datalake pendente, sem necessidade de criar parametrização") -> 0 | R23: =Q23/E23 -> 0 | S23: =COUNTIF(INTANGIBLE_ASSETS!M:M,"Por iniciar") -> 13 | T23: =S23/E23 -> 1
C24: Total | E24: =SUM(E4:E23) -> 308 | F24: =SUM(H24,J24,L24,N24,P24,R24,T24) -> 1 | G24: =SUM(G4:G23) -> 134 | H24: =G24/E24 -> 0.43506494 | I24: =SUM(I4:I23) -> 60 | J24: =I24/E24 -> 0.19480519 | K24: =SUM(K4:K23) -> 1 | L24: =K24/E24 -> 0.0032467532 | M24: =SUM(M4:M23) -> 3 | N24: =M24/E24 -> 0.0097402597 | O24: =SUM(O4:O23) -> 10 | P24: =O24/E24 -> 0.032467532 | Q24: =SUM(Q4:Q23) -> 19 | R24: =Q24/E24 -> 0.061688312 | S24: =SUM(S4:S23) -> 81 | T24: =S24/E24 -> 0.26298701

Sheet UNIVERSOS
A1: O Report Valuation está dividido em vários Universos. De seguida iremos explicar como separar entre: ‣ LEGAL PERSON; ‣ NATURAL PERSON; ‣ OFF-BALANCE; ‣ DERIVATIVE; ‣ DEBT SECURITIES; ‣ EQUITY INSTRUMENTS
A10: DERIVATIVE | B10: DEBT SECURITIES | C10: EQUITY INSTRUMENTS | D10: OFF-BALANCE | E10: LEGAL PERSON | F10: NATURAL PERSON
A11: Todos os contratos da tabela cd_alm.al011_derivados | B11: Para filtrar este universo de contratos é necessário ligar a tabela cd_captools.ct610_titulos com a tabela cd_captools.ct010_dim_valor (filtrado por id_dimensao = 76) através dos campos "nome_atributo_dim"="tipo_titulo". O universo de DEBT SECURITIES trata-se dos contratos da tabela cd_captools.ct610_titulos cujo campo "cod_atributo_dim" resultante da ligação com a tabela cd_captools.ct010_dim_valor começa por "Inst_Div". | C11: Para filtrar este universo de contratos é necessário ligar a tabela cd_captools.ct610_titulos com a tabela cd_captools.ct010_dim_valor (filtrado por id_dimensao = 76) através dos campos "nome_atributo_dim"="tipo_titulo". O universo de DEBT SECURITIES trata-se dos contratos da tabela cd_captools.ct610_titulos cujo campo "cod_atributo_dim" resultante da ligação com a tabela cd_captools.ct010_dim_valor começa por "Inst_Cap". | D11: Todos os contratos da tabela cd_captools.ct001_univ_saldo cuja ligação com a tabela cd_captools.fr802_pl_contas (cod_plano = "BST_IND") resulte no campo "carteira_contabilistica" = "garantias e compromissos concedidos" e o campo "produto" entre as opções ("compromissos de credito concedidos", "garantias financeiras prestadas", "outras responsabilidades perante terceiros") NOTA: Rever criação da variável "produto_off_bal" com Pedro Mendes, penso que o filtro feito ao campo produto da tabela vds_inp_fr_pl_contas não está retornar o que devia | E11: Todos os clientes (zcliente) da tabela cd_captools.ct003_univ_cli onde o campo "itip_cli" = "J" | F11: Tudo o resto

Sheet LEGAL PERSONS DATA SETS
A1: SRB DATA SET FOR EXPOSURES TO LEGAL PERSONS The AnaCredit database provides very detailed and individual information concerning exposures to legal persons. The SRB Valuation Data Set complements the AnaCredit database and provides data fields on segments, which allows mapping individual exposures with prudential reporting segments (FINREP and COREP), and credit risk data parameters aimed at supporting valuers. The SRB Valuation Data Set also provides data fields on risk parameters provided by banks’ internal risk models, which valuers are able to rely on in order to perform valuations on an aggregated basis, where necessary. Serão produzidos cinco ficheiros de report referentes a Legal Persons: ‣ SRB Instruments Data Set for exposures to legal persons (LEGALP_INSTRUMENTS); ‣ SRB Counterparties Data Set for exposures to legal persons (LEGALP_COUNTERPARTIES); ‣ SRB Protection received Data Set for exposures to legal persons (LEGALP_PROTECTIONS); ‣ SRB Instrument/Counterparty mapping Data Set for exposures to legal persons (LEGALP_INSTRUMENT_COUNTERPARTY); ‣ SRB Instrument/Protection mapping Data Set for exposures to legal persons (LEGALP_INSTRUMENT_PROTECTION);
A2: SRB DATA SET FOR EXPOSURES TO LEGAL PERSONS A base de dados AnaCredit disponibiliza informação muito detalhada e individualizada sobre exposições a pessoas coletivas. O dataset de avaliação do SRB complementa a base de dados AnaCredit e fornece campos de dados por segmentos, o que permite mapear exposições individuais com segmentos de reporte prudencial (FINREP e COREP) e parâmetros de dados de risco de crédito destinados a apoiar os avaliadores. O dataset de avaliação do CUR também fornece campos de dados sobre parâmetros de risco fornecidos pelos modelos de risco internos dos bancos, nos quais os avaliadores podem confiar para realizar avaliações numa base agregada, sempre que necessário. Serão produzidos três ficheiros de report referentes a Legal Persons: ‣ SRB Instruments Data Set for exposures to legal persons (VDS_OUT_LEGALP_INSTRUMENTS); ‣ SRB Counterparties Data Set for exposures to legal persons (VDS_OUT_LEGALP_COUNTERPARTIES); ‣ SRB Protection received Data Set for exposures to legal persons (VDS_OUT_LEGALP_PROTECTIONS).

Sheet LEGALP_INSTRUMENTS
A1: SRB Instruments Data Set for exposures to legal persons
A2: ID | B2: Categoria | C2: Coluna | D2: Tipo de dados | E2: Descrição | F2: Descrição - Português | H2: Mapeamentos Corporação (LT) | I2: Descrição (LT) | J2: Additional Guidance (LT) | L2: Comentários | M2: Estado especificação | O2: Fontes de Informação | P2: Filtros | Q2: Campo | R2: Regras de Preenchimento | S2: Agrupações | U2: Comentários reuniões
A3: V_1 | B3: Identification information | C3: Instrument Identifier | D3: Alphanumeric | E3: An identifier applied to uniquely identify each instrument. Each instrument must have one instrument identifier | F3: Um identificador aplicado para identificar exclusivamente cada instrumento. Cada instrumento deve ter um identificador de instrumento. | H3: INSTRUMENT-INSTRMNT_ID | I3: Instrument ID | J3: An identifier applied by the reporting agent to uniquely identify each instrument under a single contract. Each instrument must have one instrument identifier. This value will not change over time and cannot be used as the instrument identifier for any other instrument under the same contract. Supervised Insitutions are asked to furnish the INSTRMNT_ID with the exact same value as it is reported to AnaCredit (or any similar central credit register). If this is not available, the value shall be reported as it is internally used. If an instrument is not reported to AnaCredit but requested for the purposes of the on-site inspection please provide the bank-internally used value. | L3: INSTRUMENT-INSTRMNT_ID | M3: Concluido | O3: cd_alm.al029_cnt_core_m | P3: ‣ ref_date = data do report | Q3: cempresa | R3: ‣ Concatenação dos campos mencionados anteriormente: cempresa + cbalcao + cnumecta + zdeposit | U3: Após reunião com LCM foi indicado que este campo deveria ser na mesma o cempresa … zeposit mas da tabela fr001/fr004 em vez da al029 isto porque tendo que conciliar com o finrep, faz sentido que tenha a mesma granularidade
Q4: cbalcao
Q5: cnumecta
Q6: zdeposit
A7: V_2 | B7: Identification information | C7: Counterparty Identifier | D7: Alphanumeric | E7: Identifier applied to uniquely identify each counterparty. | F7: Identificador aplicado para identificar exclusivamente cada contraparte | H7: Not applicable: To be reported as "N/A". This information will be availabe in "01_04_leg_instr_count" table | I7: - | J7: - | L7: Not applicable: To be reported as "N/A". This information will be availabe in "01_04_leg_instr_count" table | M7: Concluido | O7: cd_alm.al029_cnt_core_m | P7: ‣ ref_date = data do report | Q7: zcliente | R7: ‣ Direto | U7: Se se alterar o universo trazer o zcliente respetivo
A8: V_3 | B8: Exposure class | C8: CRR Exposure class | D8: String | E8: The exposures classes for the calculation of risk-weighted assets (RWAs) for credit risks are as follows (not applicable when exposures are classified in the CRR trading book as defined in Article 4(1)(86) of Regulation (EU) No 575/2013): Where a bank uses the standardised approach: ‣ Central governments or central banks (SCENGOV) ‣ Regional governments or local authorities (SREGGOV) ‣ Public sector entities (SPUBSEC) ‣ Multilateral development banks (SDEVBAN) ‣ International organisation (SINTORG) ‣ Institutions (SINSTIT) ‣ Corporates (SCORPOR) ‣ Retail (SRETAIL) ‣ Secured by mortgages and immovable property (SSECMOR) ‣ Defaulted (SDEFAUL) ‣ High risk (SHIGHRI) ‣ Covered bonds (SCOVBON) ‣ Items representing securitisation positions ‣ Institutions and corporates with a short term credit assessment (SSHOTER) ‣ Collective investment undertakings (SCOLINV) ‣ Equity (SEQUITY) ‣ Other (SOTHERI) Where a bank uses the IRB approach: ‣ Central governments and central banks (ICENGOV) ‣ Institutions (IINSTIT) ‣ Corporates (ICORPOR) ‣ Retail (IRETAIL) ‣ Equity (IEQUITY) ‣ Items representing securitisation positions ‣ Other non-credit-obligation assets (IOTHERC) | F8: As classes de posições em risco para o cálculo dos ativos ponderados pelo risco (RWA) para riscos de crédito são as seguintes (não aplicável quando as posições em risco são classificadas na carteira de negociação do CRR, conforme definido no artigo 4(1)(86), do Regulamento (UE) No 575 /2013). Informação deriva de uma lista baseada na classificação da facilidade utilizando a classe de risco, conforme descrito no artigo 112 do Regulamento (UE) No 575/2013 para bancos que utilizam a abordagem padrão) e no artigo 147 do Regulamento (UE) No 575/2013 (para bancos que utilizam abordagem baseada em classificações internas (IRB)) Quando um banco utiliza a abordagem padrão: ‣ Central governments or central banks (SCENGOV) ‣ Regional governments or local authorities (SREGGOV) ‣ Public sector entities (SPUBSEC) ‣ Multilateral development banks (SDEVBAN) ‣ International organisation (SINTORG) ‣ Institutions (SINSTIT) ‣ Corporates (SCORPOR) ‣ Retail (SRETAIL) ‣ Secured by mortgages and immovable property (SSECMOR) ‣ Defaulted (SDEFAUL) ‣ High risk (SHIGHRI) ‣ Covered bonds (SCOVBON) ‣ Items representing securitisation positions ‣ Institutions and corporates with a short term credit assessment (SSHOTER) ‣ Collective investment undertakings (SCOLINV) ‣ Equity (SEQUITY) ‣ Other (SOTHERI) Quando um banco utiliza a abordagem IRB: ‣ Central governments and central banks (ICENGOV) ‣ Institutions (IINSTIT) ‣ Corporates (ICORPOR) ‣ Retail (IRETAIL) ‣ Equity (IEQUITY) ‣ Items representing securitisation positions ‣ Other non-credit-obligation assets (IOTHERC) | H8: - | I8: - | J8: - | L8: ‣ Não encontramos no LT -> Confirmar com Nádia Ahmad e Dora Roxo; ‣ Se não existir no LT trazer o segmento_corep_final da ct013, tendo em atenção RWA_mtethod (se for IRB ou STD) ‣ Temos de explorar como ligar o universo lt ao de capital (O) ‣Email de Pedro Mendes com a resposta da Corporação (26/03/2024 17:28) ‣ No LT para calculo do LGD que vem da ct013, quando existe IRB e STD, escolhe-se IRB. Contudo, é preciso clarificar o que se envia quando existem vários segmentos IRB ou também quando existem vários segmentos STD. | M8: Novo campo, mapeamento datalake pendente, com necessidade de criar parametrização | O8: Tabela de parametrização: codemapping | P8: ‣ dd_field_id = "3" | Q8: dd_code | R8: ‣ Tradução do campo "segmento_corep_final" através de uma ligação com o campo "dd_code" para obter o campo: dd_value
Q9: dd_value
O10: cd_captools.ct013_rwa_princ | P10: ‣ ref_date = data do report ‣ flag_cons_cap = 1 ‣ exercicio = 'REAL' | Q10: segmento_corep_final
A11: V_4 | B11: Exposure class | C11: FINREP Exposure class | D11: String | E11: Classification of the facility (exposure class) as defined in ITS 680/2014 Annex V Instructions FINREP (Counterparty breakdown). Options: ‣ Central banks ‣ Central governments ‣ Credit institutions ‣ Other financial corporations ‣ Non-financial corporations ‣ Households | F11: Classificação da instalação (exposure class) conforme definido na ITS 680/2014 Anexo V Instruções FINREP (Counterparty breakdown). Opções: ‣ Central banks ‣ Central governments ‣ Credit institutions ‣ Other financial corporations ‣ Non-financial corporations ‣ Households | H11: - | I11: - | J11: - | L11: INSTRUMENT-INTRNL_SGMNT Segundo LCM cada contrato tem apenas 1 segmento FINREP | M11: Mapeamento com LT fechado, mas parametrização pendente | O11: Tabela de parametrização: codemapping | P11: ‣ dd_field_id = "4" | Q11: dd_code | R11: ‣ Inicialmente para cada combinação dos campos "cempresa", "cbalcao", "cnumecta", "zdeposit" iremos recuperar o MAX(contraparte_i): ‣ Este campo MAX(contraparte_i) será traduzido através de uma ligação com o campo "dd_code" para obter o campo: dd_value | U11: Pragosa diz que o LCM já indicou reapontar a ct081_finrep para a fr004
Q12: dd_value
O13: cd_captools.ct081_finrep | P13: ‣ ref_date = data do report | Q13: cempresa
Q14: cbalcao
Q15: cnumecta
Q16: zdeposit
Q17: contraparte_i
A18: V_5 | B18: Risk parameters | C18: Total Risk Exposure Amount | D18: Numeric (euro) | E18: The total risk exposure amount of the instrument, calculated according to Articles 92(3) and 92(4) of Regulation (EU) No 575/2013 (CRR), where applicable. | F18: O montante total das posições em risco do instrumento, calculado de acordo com o artigo 92(3) e 92(4) do Regulamento (UE) No 575/2013 (CRR), quando aplicável. | H18: INSTRUMENT-RWA | I18: RWA | J18: RWA according to Regulation (EU) No 575/2013. | L18: INSTRUMENT-RWA | M18: Concluido | O18: cd_captools.ct013_rwa_princ | P18: ‣ ref_date = data do report ‣ flag_cons_cap = 1 ‣ exercicio = 'REAL' | Q18: s1emp | R18: ‣ Para cada Instrument Identifier é somada a: ‣ Média do campo "rwa_final" para cada par de campos "s1emp", "contra1" | S18: A agrupação é feita segundo o campo "Instrument Identifier" deste mesmo documento | U18: Dependendo do instrument id indicado, este campo deverá ser a soma do rwa_final
Q19: contra1
Q20: rwa_final
A21: V_6 | B21: Risk parameters | C21: CRR Loss given default | D21: Numeric. Basis points | E21: Current level of the ‘Loss given default’ of the loan, determined in accordance with Articles 161, 164, 179 and 181 of Regulation (EU) No 575/2013. | F21: Nível atual da "Loss given default" do empréstimo, determinado em conformidade com os artigos 161, 164, 179 e 181 do Regulamento (UE) No 575/2013. | H21: INSTRUMENT-LGD | I21: Regulatory LGD | J21: If differences between regulatory and internal LGD exist, use regulatory LGD (according to Regulation (EU) No 575/2013). In particular, in IRB-F use regulatory LGD values. | L21: INSTRUMENT-LGD | M21: Concluido | O21: cd_captools.ct013_rwa_princ | P21: ‣ ref_date = data do report ‣ flag_cons_cap = 1 ‣ exercicio = 'REAL' | Q21: s1emp | R21: ‣ Para cada Instrument Identifier é calculada a: ‣ Média ponderada do campo "lgdfinal" em relação à: ‣ Média do campo "ead_final_bruta" para cada par dos campos "s1emp", "contra1" | S21: A agrupação é feita segundo o campo "Instrument Identifier" deste mesmo documento | U21: Dependendo do instrument id indicado, este campo deverá ser a média ponderada de lgd_final por ead_final_bruta
Q22: contra1
Q23: ead_final_bruta
O24: cd_captools.ct014_rwa_irb | P24: ‣ ref_date = data do report | Q24: lgdfinal
A25: V_7 | B25: Risk parameters | C25: IFRS 9 Loss given default | D25: Numeric. Basis points | E25: Current level of the ‘Loss given default’ of the loan determined for accounting purposes. | F25: Nível atual da "Loss given default" do empréstimo determinado para efeitos contabilísticos. | H25: INSTRUMENT-IFRS9_LGD | I25: IFRS 9 accounting LGD | J25: IFRS 9 accounting Loss Given Default as at reference date for defaulted and non-defaulted exposures. In case the bank models time-depended LGD variable for non-defaulted exposures then 12-month LGD as at reference date regardless the classification as Stage 1 or 2 | L25: INSTRUMENT-IFRS9_LGD | M25: Concluido | O25: cd_captools.ifrs9_out_expected_loss_8_7 | P25: ‣ Apenas são trazidos os "contract_id"s que têm "exec_id_part" correspondente na tabela cd_captools.imcatf046_flag_fecho à data ("cmes") do report | Q25: contract_id | R25: ‣ Para cada Instrument Identifier é calculada a: ‣ Média ponderada do campo "lgd_ifrs9" em relação à: ‣ Média do campo "ead" para cada "contract_id" | S25: A agrupação é feita segundo o campo "Instrument Identifier" deste mesmo documento | U25: Tal como nos anteriores explorar porque é feita a média do ead
Q26: lgd_ifrs9
Q27: ead

Sheet LEGALP_COUNTERPARTIES
A1: SRB Counterparties Data Set for exposures to legal persons
A2: ID | B2: Categoria | C2: Coluna | D2: Tipo de dados | E2: Descrição | F2: Descrição - Português | H2: Mapeamentos Corporação (LT) | I2: Descrição (LT) | J2: Additional Guidance (LT) | L2: Comentários | M2: Estado especificação | O2: Fontes de Informação | P2: Filtros | Q2: Campo | R2: Regras de Preenchimento | S2: Agrupações | T2: Comentários reuniões
A3: V_2 | B3: Identification information | C3: Counterparty Identifier | D3: Alphanumeric | E3: Identifier applied to uniquely identify each counterparty. | F3: Identificador aplicado para identificar exclusivamente cada contraparte. | H3: ENTITY-ENTTY_ID | I3: Entity ID | J3: An identifier applied by the reporting agent to uniquely identify each counterparty. Each counterparty has a unique and exclusive counterparty identifier. This means that this value will not change over time and can never be used as the counterparty identifier for any other counterparty. | L3: ENTITY-ENTTY_ID | M3: Concluido | O3: cd_alm.al029_cnt_core_m | P3: ‣ ref_date = data do report | Q3: zcliente | R3: ‣ Direto | T3: Se se alterar o universo trazer o zcliente respetivo
A4: V_8 | B4: Risk parameters | C4: Current Internal Credit Rating/Scoring | D4: Numeric / alphanumeric | E4: Internal credit rating/scoring issued to the counterparty. | F4: Classificação/pontuação de crédito interna emitida para a contraparte. | H4: ENTITY-INTRNL_RTNG | I4: Internal rating at reference date | J4: Internal rating at the reference date according to Regulation (EU) No 575/2013. Please also add in sheet "Code List" the list of values used, i.e. bank-internal masterscale. | L4: ENTITY-INTRNL_RTNG Segundo o documento "Especificação - BCE Loan Tape - Internal Ratings_v1.4", é referido: "Nível do cliente: deverá ser consultada a tabela CD_CAPTOOLS.JM_CAL_IN_CL;" ou seja, vem do input Capital. | M4: Concluido | O4: cd_loan_tapes_bce.lt003_entity | P4: ‣ ref_date = data do report | Q4: intrnl_rtng | R4: ‣ Para cada Counterparty Identifier é obtido o: MAX(intrnl_rtng) | S4: A agrupação é feita segundo o campo "Counterparty Identifier" deste mesmo documento | T4: Explorar alternativas para ir buscar este campo
A5: V_9 | B5: Risk parameters | C5: External Credit rating | D5: Alphanumeric | E5: External credit rating issued to the counterparty at cut-off date. In case several ratings are assigned, the approach described in Art. 138 of the CRR applies. | F5: Rating de crédito externo emitido para a contraparte na data de corte. Caso sejam atribuídas diversas classificações, aplica-se a abordagem descrita no Art. 138 do CRR. | H5: ENTITY-EXTRNL_RTNG | I5: External rating | J5: External rating at the reference date. | L5: ENTITY-EXTRNL_RTNG | M5: Concluido | O5: cd_loan_tapes_bce.lt003_entity | P5: ‣ ref_date = data do report | Q5: extrnl_rtng | R5: ‣ Para cada Counterparty Identifier é obtido o: MAX(extrnl_rtng) | S5: A agrupação é feita segundo o campo "Counterparty Identifier" deste mesmo documento | T5: Explorar alternativas para ir buscar este campo
A6: V_10 | B6: Risk parameters | C6: IFRS 9 Probability of default/impairment | D6: Numeric. Basis points | E6: The probability of default/impairment is calculated in accordance with the requirements specific to probability of default (PD) estimation as laid down in the accounting framework. If PDs are produced at the instrument level only, the counterparty’s PD is to be reported as the exposure-weighted average PD across the PDs of all instruments of the counterparty. If, for a given counterparty, PDs are estimated for both the counterparty and (some of) the products of the counterparty, it is the counterparty’s PD which is to be reported. | F6: A probabilidade de incumprimento/imparidade é calculada de acordo com os requisitos específicos para a estimativa da probabilidade de incumprimento (PD) definidos no quadro contabilístico. Se as PDs forem produzidas apenas ao nível do instrumento, a PD da contraparte deve ser reportada como a PD média ponderada pela exposição entre as PD de todos os instrumentos da contraparte. Se, para uma determinada contraparte, forem estimadas PDs tanto para a contraparte como para (alguns dos) produtos da contraparte, é a PD da contraparte que deve ser reportada. | H6: ENTITY-PD_IFRS9_12M_RD | I6: 12-month PD at reporting date according to IFRS 9 | J6: 12-month PD at reference date which is used by the bank for computation of stage 1 ECL or for SICR assessment if bank use 12 month proxy for staging. If the PD is calculated on instruments level please provide an EAD weighted average. | L6: No documento de "Feedback Statement in response to the consultation on the SRB valuation data set" tem a seguinte nota sobre este campo: "‘Data Point V_10’, entitled ‘IFRS 9 Probability of default’, refers to PDs used for accounting purposes, being a 12-month PD for stage 1 exposures and a lifetime PD for stage 2 and 3 exposures as per the accounting framework." Email David Texugo (01/04/2024 17:23) Para algumas das operações em Stage 1 deve-se considerar PD lifetime também. Para operações em Stage 1 para as quais não é possível avaliar o SICR via variação de PD/Rating por PD/Rating origem inválido, o cálculo de provisões é lifetime, conforme pode ser verificado no campo loss_type. Com a exceção destas casuísticas, deve-se seguir a lógica que indicas. Adicionalmente Stage 3 deveria ter sempre PD 100%. Aparentemente, faz sentido criar um novo campo ("PD misto" ) na LT002_INSTRUMENT dado que se solicita um "misto" entre a PD 12m e a PD lifetime, assim: -Se stage 1 selecionar PD12M_IFRS9 da tabela BU_IFRS9.IFRS9_OUT_EXPECTED_LOSS_REPORTING (confirmar que neste campo já está incluída a lógica de David Texugo) -Se stage 2 selecionar PD_LT_IFRS9 da tabela BU_IFRS9.IFRS9_OUT_EXPECTED_LOSS_REPORTING -Se stage 3 forçar 1 Sugere-se criar o campo na LT002_INSTRUMENT e não na LT003_ENTITY porque após consultar a a LT003_ENTITY verificámos que existia o campo PD_IFRS9_12M_RD para o qual é usada a LT005_INSTR_ENT para Identificar todos os contratos onde o cliente é o 1º Titular, de seguida para cada cliente aplica-se uma média ponderada da PD em relação ao EAD (porque cada cliente pode ter vários contratos). Assim sugerimos replicar esta lógica para o novo campo "PD misto" adicionado na LT002_INSTRUMENT de forma a poder ser criado também um novo campo "PD misto" na LT003_ENTITY. Nota: Atenção que o campo PD_IFRS9_12M_RD apenas está a ser calculado para os Primeiros Titulares (provavelmente porque em IFRS9 também só calculam para os Primeiros Titulares) | M6: Por iniciar | O6: cd_captools.ct013_rwa_princ | P6: ‣ ref_date = data do report ‣ flag_cons_cap = 1 ‣ exercicio = 'REAL' | Q6: s1emp | R6: ‣ Este campo tem de ser calculado por fases: ‣ 1º - Calculamos o campo auxiliar "ead_final_liquida_grup": ‣ Para cada combinação dos campos "cempresa", "cbalcao", "cnumecta", "zdeposit" iremos SOMAR as: Médias do campo "ead_final_liquida" para cada par dos campos "s1emp", "contra1"; ‣ 2º - Calculamos o campo auxiliar "final_stage_grup": ‣ Para cada combinação dos campos "cempresa", "cbalcao", "cnumecta", "zdeposit" iremos calcular "final_stage" máximo: MAX(final_stage); ‣ 3º - Calculamos o campo auxiliar "pd12m_ifrs9_grup": ‣ Para cada combinação dos campos "cempresa", "cbalcao", "cnumecta", "zdeposit" iremos calcular a média ponderada do campo "pd12m_ifrs9" ao campo "ead": SUM(ead * pd12m_ifrs9) / SUM(ead); ‣ 4º - Calculamos o campo auxiliar "pd_lt_ifrs9_grup": ‣ Para cada combinação dos campos "cempresa", "cbalcao", "cnumecta", "zdeposit" iremos calcular a média ponderada do campo "pd_lt_ifrs9" ao campo "ead": SUM(pd_lt_ifrs9 * ead) / SUM(ead); ‣ 5º - Calculamos o campo auxiliar "pd_ifrs9_grup": ‣ Se final_stage_grup = '1': pd12m_ifrs9_grup; ‣ Caso contrário: pd_lt_ifrs9_grup; ‣ Finalmente para cada Counterparty Identifier calculamos a média ponderada do campo auxiliar "pd_ifrs9_grup" ao campo auxiliar "ead_final_liquida_grup": SUM(pd_ifrs9_grup * ead_final_liquida_grup) / SUM(ead_final_liquida_grup) | S6: A agrupação final é feita segundo o campo "Counterparty Identifier" deste mesmo documento | T6: Esta lógica pode mudar se o Instrument Identifier for redefinido. Explorar também a média do ead_liquida
Q7: contra1
Q8: ead_final_liquida
O9: cd_alm.al029_cnt_core_m | P9: ‣ ref_date = data do report | Q9: cempresa
Q10: cbalcao
Q11: cnumecta
Q12: zdeposit
O13: ifrs9_out_expected_loss_8_7 | P13: ‣ Apenas são trazidos os "contract_id"s que têm "exec_id_part" correspondente na tabela cd_captools.imcatf046_flag_fecho à data ("cmes") do report | Q13: pd12m_ifrs9
Q14: pd_lt_ifrs9
Q15: ead
O16: ifrs9_out_staging_8_7 | P16: ‣ Apenas são trazidos os "contract_id"s que têm "exec_id_part" correspondente na tabela cd_captools.imcatf046_flag_fecho à data ("cmes") do report | Q16: final_stage
A17: V_11 | B17: Risk parameters | C17: Probability of default (others) | D17: Numeric. Basis points | E17: Applicable only to institutions not using CRR IRB models. These institutions should maintain records of probabilities of default or scores provided by scoring/rating models. In the case of PDs produced at the instrument level only, the counterparty’s PD is to be reported as the exposure-weighted average PD across the PDs of all instruments of the counterparty. If, for a given counterparty, PDs are estimated for both the counterparty and (some of) the products of the counterparty, it is the counterparty’s PD which is to be reported. | F17: Aplicável apenas a instituições que não utilizam modelos CRR IRB. Estas instituições devem manter registos das probabilidades de incumprimento ou das pontuações fornecidas pelos modelos de pontuação/rating. No caso de PDs produzidas apenas ao nível do instrumento, a PD da contraparte deve ser relatada como a PD média ponderada pela exposição entre as PDs de todos os instrumentos da contraparte. Se, para uma determinada contraparte, forem estimadas PDs tanto para a contraparte como para (alguns dos) produtos da contraparte, é a PD da contraparte que deve ser reportada. | H17: - | I17: - | J17: - | L17: Este campo é Not Applicable, reportar: 11111111111 | M17: Concluido | O17: N/A | P17: N/A | Q17: N/A | R17: N/A | S17: N/A

Sheet LEGALP_PROTECTIONS
A1: SRB Protection received Data Set for exposures to legal persons
A2: ID | B2: Categoria | C2: Coluna | D2: Tipo de dados | E2: Descrição | F2: Descrição - Português | H2: Mapeamentos Corporação (LT) | I2: Descrição (LT) | J2: Additional Guidance (LT) | L2: Comentários | M2: Estado especificação | O2: Fontes de Informação | P2: Filtros | Q2: Campo | R2: Regras de Preenchimento | S2: Agrupações | T2: Comentários reuniões
A3: V_12 | B3: Identification information | C3: Protection identifier | D3: Alphanumeric | E3: An identifier applied to uniquely identify each protection/collateral used to secure the instrument. | F3: Um identificador aplicado para identificar exclusivamente cada proteção/garantia utilizada para garantir o instrumento. | H3: PROTECTION-PRTCTN_ID | I3: Protection ID | J3: An identifier applied by the reporting agent to uniquely identify each protection used to secure the instrument. Each protection must have one protection identifier. This value will not change over time and cannot be used as the protection identifier for any other protection. | L3: PROTECTION-PRTCTN_ID | M3: Concluido | O3: cd_captools.fr003_colaterais | P3: ‣ ref_date = data do report | Q3: cempresa | R3: ‣ Concatenação dos campos mencionados anteriormente: cempresa + cbalcao_caucao + cnumecta_caucao + zcaucao | T3: Ver se não devemos ir antes às tabelas de garantias (gts)
Q4: cbalcao_caucao
Q5: cnumecta_caucao
Q6: zcaucao
A7: V_1 | B7: Identification information | C7: Instrument Identifier | D7: Alphanumeric | E7: An identifier applied to uniquely identify each instrument. Each instrument must have one instrument identifier. | F7: Um identificador aplicado para identificar exclusivamente cada instrumento. Cada instrumento deve ter um identificador de instrumento. | H7: Not applicable: To be reported as "N/A". This information will be availabe in "01_05_leg_instr_prot" table | I7: - | J7: - | L7: Not applicable: To be reported as "N/A". This information will be availabe in "01_05_leg_instr_prot" table | M7: Concluido | O7: cd_alm.kt_chaves_alm_m | P7: ‣ ref_date = data do report | Q7: cempresa | R7: ‣ Concatenação dos campos mencionados anteriormente: cempresa + cbalcao + cnumecta + zdeposit | T7: Após reunião com LCM foi indicado que este campo deveria ser na mesma o cempresa … zeposit mas da tabela fr001/fr004 em vez da al029 isto porque tendo que conciliar com o finrep, faz sentido que tenha a mesma granularidade
Q8: cbalcao
Q9: cnumecta
Q10: zdeposit
A11: V_187 | B11: Identification information | C11: Type of collateral | D11: String | E11: The AnaCredit item “type of protection” (Section 9.4.3. of the Anacredit Reporting Manual part II - Dataset and data attributes) provides a breakdown of collateral eligible in accordance with the CRR. The proposed breakdown adds several categories. Options: ‣ Gold ‣ Currency and deposits ‣ Securities ‣ Loans ‣ Equity and investment fund shares or units ‣ Credit derivatives ‣ Financial guarantees other than credit derivatives ‣ Trade receivables ‣ Life insurance policies pledged ‣ Residential real estate collateral ‣ Offices and commercial premises ‣ Commercial real estate collateral ‣ Other physical collateral ‣ Other protection ‣ Hotels & entertainment ‣ Infrastructure projects ‣ Factories – warehouses ‣ Equipment & machinery ‣ Automotive ‣ Aircraft ‣ Shipping | F11: O item "type of protection" da AnaCredit (Secção 9.4.3. do Anacredit Reporting Manual parte II - Dataset and data attributes) fornece uma discriminação das garantias elegíveis de acordo com o CRR. A repartição proposta acrescenta diversas categorias. Opções: ‣ Gold ‣ Currency and deposits ‣ Securities ‣ Loans ‣ Equity and investment fund shares or units ‣ Credit derivatives ‣ Financial guarantees other than credit derivatives ‣ Trade receivables ‣ Life insurance policies pledged ‣ Residential real estate collateral ‣ Offices and commercial premises ‣ Commercial real estate collateral ‣ Other physical collateral ‣ Other protection ‣ Hotels & entertainment ‣ Infrastructure projects ‣ Factories – warehouses ‣ Equipment & machinery ‣ Automotive ‣ Aircraft ‣ Shipping | H11: PROTECTION-TYP_PRTCTN | I11: Protection type | J11: Type of protection received, irrespective of its eligibility for credit risk mitigation. | L11: PROTECTION-TYP_PRTCTN | M11: Mapeamento com LT fechado, mas parametrização pendente | O11: Tabela de parametrização: codemapping | P11: ‣ dd_field_id = "187" | Q11: dd_code | R11: ‣ Tradução do campo "typ_prtctn" através de uma ligação com o campo "dd_code" para obter o campo: dd_value
Q12: dd_value
O13: cd_loan_tapes_bce.lt004_protection | P13: ‣ ref_date = data do report | Q13: typ_prtctn
A14: V_14 | B14: Size collateral | C14: Building Area (M2) | D14: Numeric | E14: Building area of the building in square metres. Only applicable to Residential real estate collateral, Offices and commercial premises, Commercial real estate collateral, Hotels & entertainment, Factories – warehouses. | F14: Área de construção do edifício em metros quadrados. Aplicável apenas a Garantias imobiliárias residenciais, Escritórios e instalações comerciais, Garantias imobiliárias comerciais, Hotéis e entretenimento, Fábricas – armazéns. | H14: - | I14: - | J14: - | L14: ‣ Não encontramos no LT -> Confirmar com Nádia Ahmad e Dora Roxo; ‣ Segundo Luís Capitão-Mor, estes campos deverão vir do MUG (Modelo Único de Garantias). ‣ Reunião Alexandre Dionísio Esteves (08-04-2024): 1) Estes campos ainda não existem no MUG. 2) Esta informação existe na GPT32, embora nessa tabela estes campos não sejam de preenchimento obrigatório, como tal, existem GAPs de informação. 3) Foi-nos também comentado que o universo completo de imóveis está na tabela gpt18 os quais não estão 100% mapeados na gpt32. 4) Alexandre irá analisar em detalhe e irá marcar reunião com Luís Capitão-Mor para a semana de 15/04/2024 | M14: Novo campo, mapeamento datalake pendente, sem necessidade de criar parametrização | R14: ‣ Forçado a NULL | T14: É necessário verificar onde existe esta informação (ex: cd_emprestimos.gpt32_bemimove)
A15: V_15 | B15: Size collateral | C15: Land Area (M2) | D15: Numeric | E15: Land area of the property in square metres, including any land surrounding the building(s) on the property that is part of the property. | F15: Área do terreno do imóvel em metros quadrados, incluindo qualquer terreno ao redor do(s) edifício(s) do imóvel que faz parte do imóvel. | H15: - | I15: - | J15: - | L15: ‣ Não encontramos no LT -> Confirmar com Nádia Ahmad e Dora Roxo; ‣ Segundo Luís Capitão-Mor, estes campos deverão vir do MUG (Modelo Único de Garantias). ‣ Reunião Alexandre Dionísio Esteves (08-04-2024): 1) Estes campos ainda não existem no MUG. 2) Esta informação existe na GPT32, embora nessa tabela estes campos não sejam de preenchimento obrigatório, como tal, existem GAPs de informação. 3) Foi-nos também comentado que o universo completo de imóveis está na tabela gpt18 os quais não estão 100% mapeados na gpt32. 4) Alexandre irá analisar em detalhe e irá marcar reunião com Luís Capitão-Mor para a semana de 15/04/2024 | M15: Novo campo, mapeamento datalake pendente, sem necessidade de criar parametrização | R15: ‣ Forçado a NULL
A16: V_16 | B16: Location | C16: Property postcode | D16: Numeric | E16: Postcode where the property is located. Only applicable to Residential real estate collateral, Offices and commercial premises, Commercial real estate collateral, Hotels & entertainment, Factories – warehouses. | F16: Código postal onde o imóvel está localizado. Aplicável apenas a Garantias imobiliárias residenciais, Escritórios e instalações comerciais, Garantias imobiliárias comerciais, Hotéis e entretenimento, Fábricas – armazéns. | H16: PROTECTION-RL_ESTT_PST_CD | I16: Post code / ZIP | J16: Post code / ZIP. | L16: PROTECTION-RL_ESTT_PST_CD | M16: Concluido | O16: cd_loan_tapes_bce.lt004_protection | P16: ‣ ref_date = data do report | Q16: rl_estt_pst_cd | R16: ‣ Direto
A17: V_17 | B17: Lien | C17: Lien position | D17: Numeric | E17: The highest ranking position(s) in relation to the collateral held by the counterparty to secure the facility. If the facility has several liens on one collateral, the highest claim is reported in this data field. | F17: A(s) posição(ões) mais elevada(s) em relação às garantias detidas pela contraparte para garantir a instalação. Se a instalação tiver vários ônus sobre uma garantia, a reivindicação mais alta será relatada neste campo de dados. | H17: - | I17: - | J17: - | L17: ‣ Não encontramos no LT -> Confirmar com Nádia Ahmad e Dora Roxo; [Reunião 2024-04-08] Segundo Luís Capitão-Mor, o Banco só aceita primeiras hipotecas, como tal, este campo deverá ser sempre preenchido com '1'. | M17: Novo campo, mapeamento datalake fechado, sem necessidade de criar parametrização | O17: cd_loan_tapes_bce.lt006_instr_prot | P17: ‣ ref_date = data do report | Q17: thrd_prty_prrty_clms | R17: ‣ Direto | T17: Confirmar se este é o campo correto para recuperar esta informação
A18: V_18 | B18: Collateral characteristics | C18: Detailed type of Shipping collateral | D18: String | E18: Detailed type of collateral received. Applicable only to shipping portfolios. Options: ‣ Bulker (1) ‣ Container (2) ‣ Crude Oil Tanker (3) ‣ Product Tanker (4) ‣ Chemical Tanker (5) ‣ Cruise Ship (6) ‣ Ferry (7) ‣ LPG Carrier (8) ‣ Offshore (9) ‣ Other (10) | F18: Tipo detalhado de garantia recebida. Aplicável apenas a portfólios de remessa. Opções: ‣ Bulker (1) ‣ Container (2) ‣ Crude Oil Tanker (3) ‣ Product Tanker (4) ‣ Chemical Tanker (5) ‣ Cruise Ship (6) ‣ Ferry (7) ‣ LPG Carrier (8) ‣ Offshore (9) ‣ Other (10) | H18: - | I18: - | J18: - | L18: ‣ emaill 22/04/2024 20:17 Rute Ferreira com o Histórico de conversações: - Carmo Rodrigues não conseguiu esclarecer as 3 questões endereçadas. ‣ email 23/04/2024 20:24 de Paulo Oliveira: 1) Não tenho conhecimento que existam shipping portfolios no Banco, confirmas? Pode ser que seja categorizado pelo Banco de outra forma. Asset lending não, mas não descartava que houvesse alguns barcos financiados em leasing nomeadamente para empresas do sector. Perguntava á Leasing. Não sei se não haverá como colateral algum cliente que tenha dado o seu barco de recreio (iate). 2) Se eventualmente existisse uma Empresa que quisesse dar alguma destas opções como colateral, o Banco aceitava? Sim, são activos com valor de mercado. Tal como aceitamos aviões, aceitariamos navios como colateral 3) Em caso afirmativo ao ponto 2), sabes de algum caso em concreto para que possa ir verificar e ver como fica registado no Banco? Não me lembro de nenhum Acho que deveramos ir analisar as empresas de navegação com frota. | M18: Novo campo, mapeamento datalake pendente, com necessidade de criar parametrização | O18: N/A | P18: N/A | Q18: N/A | R18: N/A | S18: N/A | T18: Não existe este genero de operativa

Sheet LEGALP_INSTRUMENT_COUNTERPARTY
A1: SRB Instrument/Counterparty mapping Data Set for exposures to legal persons
A2: ID | B2: Categoria | C2: Coluna | D2: Tipo de dados | E2: Descrição | F2: Descrição - Português | H2: Mapeamentos Corporação (LT) | I2: Descrição (LT) | J2: Additional Guidance (LT) | L2: Comentários | M2: Estado especificação | O2: Fontes de Informação | P2: Filtros | Q2: Campo | R2: Regras de Preenchimento | S2: Agrupações | T2: Comentários reuniões
A3: V_1 | B3: Identification information | C3: Instrument Identifier | D3: Alphanumeric | E3: An identifier applied to uniquely identify each instrument. Each instrument must have one instrument identifier | F3: Um identificador aplicado para identificar exclusivamente cada instrumento. Cada instrumento deve ter um identificador de instrumento. | H3: INSTR_ENTITY-INSTRMNT_ID | I3: Instrument ID | J3: An identifier applied by the reporting agent to uniquely identify each instrument under a single contract. Each instrument must have one instrument identifier. This value will not change over time and cannot be used as the instrument identifier for any other instrument under the same contract. Supervised Insitutions are asked to furnish the INSTRMNT_ID with the exact same value as it is reported to AnaCredit (or any similar central credit register). If this is not available, the value shall be reported as it is internally used. If an instrument is not reported to AnaCredit but requested for the purposes of the on-site inspection please provide the bank-internally used value. Foreign Key from INSTRUMENT table. | L3: INSTR_ENTITY-INSTRMNT_ID | M3: Concluido | O3: cd_alm.al029_cnt_core_m | P3: ‣ ref_date = data do report | Q3: cempresa | R3: ‣ Concatenação dos campos mencionados anteriormente: cempresa + cbalcao + cnumecta + zdeposit | T3: Ver se não devemos ir antes às tabelas de garantias (gts)
Q4: cbalcao
Q5: cnumecta
Q6: zdeposit
A7: V_2 | B7: Identification information | C7: Counterparty Identifier | D7: Alphanumeric | E7: Identifier applied to uniquely identify each counterparty. | F7: Identificador aplicado para identificar exclusivamente cada contraparte. | H7: INSTR_ENTITY-ENTTY_ID | I7: Entity ID | J7: An identifier applied by the reporting agent to uniquely identify each counterparty. Each counterparty has a unique and exclusive counterparty identifier. This means that this value will not change over time and can never be used as the counterparty identifier for any other counterparty. Foreign key from ENTITY table. | L7: INSTR_ENTITY-ENTTY_ID | M7: Concluido | O7: cd_alm.al029_cnt_core_m | P7: ‣ ref_date = data do report | Q7: zcliente | R7: ‣ Direto

Sheet LEGALP_INSTRUMENT_PROTECTION
A1: SRB Instrument/Protection mapping Data Set for exposures to legal persons
A2: ID | B2: Categoria | C2: Coluna | D2: Tipo de dados | E2: Descrição | F2: Descrição - Português | H2: Mapeamentos Corporação (LT) | I2: Descrição (LT) | J2: Additional Guidance (LT) | L2: Comentários | M2: Estado especificação | O2: Fontes de Informação | P2: Filtros | Q2: Campo | R2: Regras de Preenchimento | S2: Agrupações | T2: Comentários reuniões
A3: V_1 | B3: Identification information | C3: Instrument Identifier | D3: Alphanumeric | E3: An identifier applied to uniquely identify each instrument. Each instrument must have one instrument identifier | F3: Um identificador aplicado para identificar exclusivamente cada instrumento. Cada instrumento deve ter um identificador de instrumento. | H3: INSTR_PROTECTION-INSTRMNT_ID | I3: Instrument ID | J3: An identifier applied by the reporting agent to uniquely identify each instrument under a single contract. Each instrument must have one instrument identifier. This value will not change over time and cannot be used as the instrument identifier for any other instrument under the same contract. Supervised Insitutions are asked to furnish the INSTRMNT_ID with the exact same value as it is reported to AnaCredit (or any similar central credit register). If this is not available, the value shall be reported as it is internally used. If an instrument is not reported to AnaCredit but requested for the purposes of the on-site inspection please provide the bank-internally used value. Foreign Key from INSTRUMENT table. | L3: INSTR_PROTECTION-INSTRMNT_ID | M3: Concluido | O3: cd_alm.al029_cnt_core_m | P3: ‣ ref_date = data do report | Q3: cempresa | R3: ‣ Concatenação dos campos mencionados anteriormente: cempresa + cbalcao + cnumecta + zdeposit | T3: Ver se não devemos ir antes às tabelas de garantias (gts)
Q4: cbalcao
Q5: cnumecta
Q6: zdeposit
A7: V_12 | B7: Identification information | C7: Protection identifier | D7: Alphanumeric | E7: An identifier applied to uniquely identify each protection/collateral used to secure the instrument. | F7: Um identificador aplicado para identificar exclusivamente cada proteção/garantia utilizada para garantir o instrumento. | H7: INSTR_PROTECTION-PRTCTN_ID | I7: Protection ID | J7: An identifier applied by the reporting agent to uniquely identify each protection used to secure the instrument. Each protection must have one protection identifier. This value will not change over time and cannot be used as the protection identifier for any other protection. Foreign Key from PROTECTION table. | L7: INSTR_PROTECTION-PRTCTN_ID | M7: Concluido | O7: cd_captools.fr003_colaterais | P7: ‣ ref_date = data do report | Q7: cempresa | R7: ‣ Concatenação dos campos mencionados anteriormente: cempresa + cbalcao_caucao + cnumecta_caucao + zcaucao
Q8: cbalcao_caucao
Q9: cnumecta_caucao
Q10: zcaucao

Sheet NATURAL PERSONS DATA SETS
A1: SRB DATA SET FOR EXPOSURES TO NATURAL PERSONS The following data set covers exposures to natural persons, which, in many cases, represent the main type of exposures on banks’ balance sheets (e.g. retail institutions or mortgage institutions). Such exposures might comprise lending products such as mortgages, consumer loans, credit cards, etc. Valuations of retail portfolios are usually made with lesser granularity than valuations of corporate portfolios. However, in specific circumstances (e.g. high default rates in mortgage portfolios) a collective assessment might not suffice and the valuer might rely on a more granular approach for qualitatively and quantitatively assessing the level of economic impairment of exposures to natural persons that would typically be impaired on a collective basis under International Financial Reporting Standard (IFRS 9). In this case, the valuer would require a more granular data set to perform valuations. To avoid any duplication of data points or definitions, the data set for exposures to natural persons is based on the AnaCredit data points and definitions for legal persons. However, institutions can leverage on the definitions, data points and reporting thresholds of local standards or legislation, provided those definitions and data points are, in the IRT’s view, equivalent to those envisaged for AnaCredit. Serão produzidos cinco ficheiros de report referentes a Natural Persons: ‣ SRB Instruments Data Set for exposures to natural persons (NATURALP_INSTRUMENTS); ‣ SRB Counterparties Data Set for exposures to natural persons (NATURALP_COUNTERPARTIES); ‣ SRB Protection received Data Set for exposures to natural persons (NATURALP_PROTECTIONS); ‣ SRB Instrument/Counterparty mapping Data Set for exposures to natural persons (NATURALP_INSTRUMENT_COUNTERPARTY); ‣ SRB Instrument/Protection mapping Data Set for exposures to natural persons (NATURALP_INSTRUMENT_PROTECTION);
A2: SRB DATA SET FOR EXPOSURES TO NATURAL PERSONS O seguinte data set abrange exposições a pessoas singulares, que, em muitos casos, representam o principal tipo de exposições nos balanços dos bancos (por exemplo, instituições de retalho ou instituições hipotecárias). Essas exposições podem incluir produtos de empréstimo, como hipotecas, empréstimos pessoais, cartões de crédito, etc. As avaliações de carteiras de retalho são geralmente feitas com menos granularidade do que as avaliações de carteiras corporativas. No entanto, em circunstâncias específicas (por exemplo, elevadas taxas de incumprimento em carteiras hipotecárias), uma avaliação colectiva pode não ser suficiente e o avaliador pode basear-se numa abordagem mais granular para avaliar qualitativa e quantitativamente o nível de imparidade económica das exposições a pessoas singulares que normalmente seriam prejudicadas numa base colectiva ao abrigo da International Financial Reporting Standard (IFRS 9). Neste caso, o avaliador necessitaria de um conjunto de dados mais granular para realizar avaliações. Para evitar qualquer duplicação de pontos de dados ou definições, o data set para exposições a pessoas singulares baseia-se nos pontos de dados e definições da AnaCredit para pessoas coletivas. No entanto, as instituições podem aproveitar as definições, os pontos de dados e os limites de reporte das normas ou legislação local, desde que essas definições e pontos de dados sejam, na opinião do IRT, equivalentes aos previstos para o AnaCredit. Serão produzidos cinco ficheiros de report referentes a Natural Persons: ‣ SRB Instruments Data Set for exposures to natural persons (VDS_OUT_NATURALP_INSTRUMENTS); ‣ SRB Counterparties Data Set for exposures to natural persons (VDS_OUT_NATURALP_COUNTERPARTIES); ‣ SRB Protection received Data Set for exposures to natural persons (VDS_OUT_NATURALP_PROTECTIONS).

Sheet NATURALP_INSTRUMENTS
A1: SRB Instruments Data Set for exposures to natural persons
A2: ID | B2: Categoria | C2: Coluna | D2: Tipo de dados | E2: Descrição | F2: Descrição | H2: Mapeamentos Corporação (LT) | I2: Descrição (LT) | J2: Additional Guidance (LT) | L2: Comentários | M2: Estado especificação | O2: Fontes de Informação | P2: Filtros | Q2: Campo | R2: Regras de Preenchimento | S2: Agrupações | T2: Comentários reuniões
A3: V_1 | B3: Identification information | C3: Instrument Identifier | D3: Alphanumeric | E3: Identifier applied to uniquely identify each instrument. Each instrument must have one instrument identifier. | F3: Um identificador aplicado para identificar exclusivamente cada instrumento. Cada instrumento deve ter um identificador de instrumento. | H3: INSTRUMENT-INSTRMNT_ID | I3: Instrument ID | J3: An identifier applied by the reporting agent to uniquely identify each instrument under a single contract. Each instrument must have one instrument identifier. This value will not change over time and cannot be used as the instrument identifier for any other instrument under the same contract. Supervised Insitutions are asked to furnish the INSTRMNT_ID with the exact same value as it is reported to AnaCredit (or any similar central credit register). If this is not available, the value shall be reported as it is internally used. If an instrument is not reported to AnaCredit but requested for the purposes of the on-site inspection please provide the bank-internally used value. | L3: INSTRUMENT-INSTRMNT_ID | M3: Concluido | O3: cd_alm.al029_cnt_core_m | P3: ‣ ref_date = data do report | Q3: cempresa | R3: ‣ Concatenação dos campos mencionados anteriormente: cempresa + cbalcao + cnumecta + zdeposit | T3: Após reunião com LCM foi indicado que este campo deveria ser na mesma o cempresa … zeposit mas da tabela fr001/fr004 em vez da al029 isto porque tendo que conciliar com o finrep, faz sentido que tenha a mesma granularidade
Q4: cbalcao
Q5: cnumecta
Q6: zdeposit
A7: V_2 | B7: Identification information | C7: Counterparty Identifier | D7: Alphanumeric | E7: Identifier applied to uniquely identify each counterparty. | F7: Identificador aplicado para identificar exclusivamente cada contraparte. | H7: Not applicable: To be reported as "N/A". This information will be availabe in "02_04_nat_instr_count" table | I7: - | J7: - | L7: Not applicable: To be reported as "N/A". This information will be availabe in "02_04_nat_instr_count" table | M7: Concluido | O7: cd_alm.al029_cnt_core_m | P7: ‣ ref_date = data do report | Q7: zcliente | R7: ‣ Direto | T7: Se se alterar o universo trazer o zcliente respetivo
A8: V_139 | B8: Identification information | C8: Reporting data identifier | D8: Alphanumeric | E8: The counterparty identifier of the reporting agent which reports the data. | F8: O identificador da contraparte do agente inquirido que comunica os dados. | H8: INSTRUMENT-COD_SOC | I8: Entity code of the informing society. | J8: Cargabal code or internal identifier of the informing society. | L8: INSTRUMENT-COD_SOC | M8: Concluido | R8: ‣ Forçado a "549300URJH9VSI58CS32" (código lei do BANCO SANTANDER TOTTA, S.A.)
A9: V_140 | B9: Identification information | C9: Observed agent identifier | D9: Alphanumeric | E9: The counterparty identifier of the observed agent (i.e. an institutional unit of the reporting agent) whose data are reported by the reporting agent. | F9: O identificador da contraparte do agente observado (ou seja, uma unidade institucional do agente inquirido) cujos dados são comunicados pelo agente inquirido. | H9: INSTRUMENT-OBSRVD_AGNT_ID | I9: Observed agent identifier | J9: Counterparty identifier for the observed agent. If there are several observed agents to be reported please separate by comma (,). | L9: INSTRUMENT-OBSRVD_AGNT_ID | M9: Concluido | R9: ‣ Forçado a "549300URJH9VSI58CS32" (código lei do BANCO SANTANDER TOTTA, S.A.)
A10: V_141 | B10: Identification information | C10: Contract identifier | D10: Alphanumeric | E10: An identifier applied by the reporting agent to uniquely identify each contract. The contract identifier refers to the credit agreement between two or more parties under which the instrument is created. | F10: Um identificador aplicado pelo agente inquirido para identificar de forma única cada contrato. O identificador do contrato refere-se ao contrato de crédito entre duas ou mais partes ao abrigo do qual o instrumento é criado. | H10: INSTRUMENT-CNTRCT_ID | I10: Contract ID | J10: An identifier applied by the reporting agent to uniquely identify each contract. Each contract must have one contract identifier. This value will not change over time and cannot be used as the contract identifier for any other contract. | L10: INSTRUMENT-CNTRCT_ID | M10: Concluido | O10: cd_alm.al029_cnt_core_m | P10: ‣ ref_date = data do report | Q10: cempresa | R10: ‣ Concatenação dos campos mencionados anteriormente: cempresa + "_" + cbalcao + "_" + cnumecta + "_" + zdeposit | T10: Replicar o Instrument_id
Q11: cbalcao
Q12: cnumecta
Q13: zdeposit
A14: V_3 | B14: Exposure class | C14: CRR Exposure class | D14: String | E14: The exposures classes for the calculation of RWAs for credit risks are as follows (not applicable when exposures are classified in the CRR trading book as defined in Article 4(1)(86) of Regulation (EU) No 575/2013): Where a bank uses the standardised approach: ‣ Central governments or central banks (SCENGOV) ‣ Regional governments or local authorities (SREGGOV) ‣ Public sector entities (SPUBSEC) ‣ Multilateral development banks (SDEVBAN) ‣ International organisation (SINTORG) ‣ Institutions (SINSTIT) ‣ Corporates (SCORPOR) ‣ Retail (SRETAIL) ‣ Secured by mortgages and immovable property (SSECMOR) ‣ Defaulted (SDEFAUL) ‣ High risk (SHIGHRI) ‣ Covered bonds (SCOVBON) ‣ Items representing securitisation positions ‣ Institutions and corporates with a short term credit assessment (SSHOTER) ‣ Collective investment undertakings (SCOLINV) ‣ Equity (SEQUITY) ‣ Other (SOTHERI) Where a bank uses the IRB approach: ‣ Central governments and central banks (ICENGOV) ‣ Institutions (IINSTIT) ‣ Corporates (ICORPOR) ‣ Retail (IRETAIL) ‣ Equity (IEQUITY) ‣ Items representing securitisation positions ‣ Other non-credit-obligation assets (IOTHERC) | F14: As classes de posições em risco para o cálculo dos ativos ponderados pelo risco (RWA) para riscos de crédito são as seguintes (não aplicável quando as posições em risco são classificadas na carteira de negociação do CRR, conforme definido no artigo 4(1)(86), do Regulamento (UE) No 575 /2013). Informação deriva de uma lista baseada na classificação da facilidade utilizando a classe de risco, conforme descrito no artigo 112 do Regulamento (UE) No 575/2013 para bancos que utilizam a abordagem padrão) e no artigo 147 do Regulamento (UE) No 575/2013 (para bancos que utilizam abordagem baseada em classificações internas (IRB)) Quando um banco utiliza a abordagem padrão: ‣ Central governments or central banks (SCENGOV) ‣ Regional governments or local authorities (SREGGOV) ‣ Public sector entities (SPUBSEC) ‣ Multilateral development banks (SDEVBAN) ‣ International organisation (SINTORG) ‣ Institutions (SINSTIT) ‣ Corporates (SCORPOR) ‣ Retail (SRETAIL) ‣ Secured by mortgages and immovable property (SSECMOR) ‣ Defaulted (SDEFAUL) ‣ High risk (SHIGHRI) ‣ Covered bonds (SCOVBON) ‣ Items representing securitisation positions ‣ Institutions and corporates with a short term credit assessment (SSHOTER) ‣ Collective investment undertakings (SCOLINV) ‣ Equity (SEQUITY) ‣ Other (SOTHERI) Quando um banco utiliza a abordagem IRB: ‣ Central governments and central banks (ICENGOV) ‣ Institutions (IINSTIT) ‣ Corporates (ICORPOR) ‣ Retail (IRETAIL) ‣ Equity (IEQUITY) ‣ Items representing securitisation positions ‣ Other non-credit-obligation assets (IOTHERC) | H14: - | I14: - | J14: - | L14: ‣ Não encontramos no LT -> Confirmar com Nádia Ahmad e Dora Roxo; ‣ Se não existir no LT trazer o segmento_corep_final da ct013, tendo em atenção RWA_mtethod (se for IRB ou STD) ‣ Temos de explorar como ligar o universo lt ao de capital (O) ‣Email de Pedro Mendes com a resposta da Corporação (26/03/2024 17:28) ‣ No LT para calculo do LGD que vem da ct013, quando existe IRB e STD, escolhe-se IRB. Contudo, é preciso clarificar o que se envia quando existem vários segmentos IRB ou também quando existem vários segmentos STD. | M14: Novo campo, mapeamento datalake pendente, com necessidade de criar parametrização | O14: Tabela de parametrização: codemapping | P14: ‣ dd_field_id = "3" | Q14: dd_code | R14: ‣ Tradução do campo "segmento_corep_final" através de uma ligação com o campo "dd_code" para obter o campo: dd_value
Q15: dd_value
O16: cd_captools.ct013_rwa_princ | P16: ‣ ref_date = data do report ‣ flag_cons_cap = 1 ‣ exercicio = 'REAL' | Q16: segmento_corep_final
A17: V_4 | B17: Exposure class | C17: FINREP Exposure class | D17: String | E17: Classification of the facility (exposure class) as defined in ITS 680/2014 Annex V Instructions FINREP (Counterparty breakdown). Opções: ‣ Central banks ‣ Central governments ‣ Credit institutions ‣ Other financial corporations ‣ Non-financial corporations ‣ Households | F17: Classificação da instalação (exposure class) conforme definido na ITS 680/2014 Anexo V Instruções FINREP (Counterparty breakdown). Opções: ‣ Central banks ‣ Central governments ‣ Credit institutions ‣ Other financial corporations ‣ Non-financial corporations ‣ Households | H17: - | I17: - | J17: - | L17: INSTRUMENT-INTRNL_SGMNT Segundo LCM cada contrato tem apenas 1 segmento FINREP | M17: Mapeamento com LT fechado, mas parametrização pendente | O17: Tabela de parametrização: codemapping | P17: ‣ dd_field_id = "4" | Q17: dd_code | R17: ‣ Inicialmente para cada combinação dos campos "cempresa", "cbalcao", "cnumecta", "zdeposit" iremos recuperar o MAX(contraparte_i): ‣ Este campo MAX(contraparte_i) será traduzido através de uma ligação com o campo "dd_code" para obter o campo: dd_value
Q18: dd_value
O19: cd_captools.ct081_finrep | P19: ‣ ref_date = data do report | Q19: cempresa
Q20: cbalcao
Q21: cnumecta
Q22: zdeposit
Q23: contraparte_i
A24: V_5 | B24: Risk parameters | C24: Total Risk Exposure Amount | D24: Numeric (euro) | E24: The total risk exposure amount of the instrument, calculated according to Articles 92(3) and 92(4) of Regulation (EU) No 575/2013 (CRR), where applicable. | F24: O montante total das posições em risco do instrumento, calculado de acordo com o artigo 92(3) e 92(4) do Regulamento (UE) No 575/2013 (CRR), quando aplicável. | H24: INSTRUMENT-RWA | I24: RWA | J24: RWA according to Regulation (EU) No 575/2013. | L24: INSTRUMENT-RWA | M24: Concluido | O24: cd_captools.ct013_rwa_princ | P24: ‣ ref_date = data do report ‣ flag_cons_cap = 1 ‣ exercicio = 'REAL' | Q24: s1emp | R24: ‣ Para cada Instrument Identifier é somada a: ‣ Média do campo "rwa_final" para cada par de campos "s1emp", "contra1" | S24: A agrupação é feita segundo o campo "Instrument Identifier" deste mesmo documento | T24: Dependendo do instrument id indicado, este campo deverá ser a soma do rwa_final
Q25: contra1
Q26: rwa_final
A27: V_6 | B27: Risk parameters | C27: CRR Loss given default | D27: Numeric. Basis points | E27: Current level of the ‘Loss given default’ of the loan, determined in accordance with Articles 161, 164, 179 and 181 of Regulation (EU) No 575/2013. | F27: Nível atual da "Loss given default" do empréstimo, determinado em conformidade com os artigos 161, 164, 179 e 181 do Regulamento (UE) No 575/2013. | H27: INSTRUMENT-LGD | I27: Regulatory LGD | J27: If differences between regulatory and internal LGD exist, use regulatory LGD (according to Regulation (EU) No 575/2013). In particular, in IRB-F use regulatory LGD values. | L27: INSTRUMENT-LGD | M27: Concluido | O27: cd_captools.ct013_rwa_princ | P27: ‣ ref_date = data do report ‣ flag_cons_cap = 1 ‣ exercicio = 'REAL' | Q27: s1emp | R27: ‣ Para cada Instrument Identifier é calculada a: ‣ Média ponderada do campo "lgdfinal" em relação à: ‣ Média do campo "ead_final_bruta" para cada par dos campos "s1emp", "contra1" | S27: A agrupação é feita segundo o campo "Instrument Identifier" deste mesmo documento | T27: Dependendo do instrument id indicado, este campo deverá ser a média ponderada de lgd_final por ead_final_bruta
Q28: contra1
Q29: ead_final_bruta
O30: cd_captools.ct014_rwa_irb | P30: ‣ ref_date = data do report | Q30: lgdfinal
A31: V_7 | B31: Risk parameters | C31: IFRS 9 Loss given default | D31: Numeric. Basis points | E31: Current level of the ‘Loss given default’ of the loan determined for accounting purposes. | F31: Nível atual da "Loss given default" do empréstimo determinado para efeitos contabilísticos. | H31: INSTRUMENT-IFRS9_LGD | I31: IFRS 9 accounting LGD | J31: IFRS 9 accounting Loss Given Default as at reference date for defaulted and non-defaulted exposures. In case the bank models time-depended LGD variable for non-defaulted exposures then 12-month LGD as at reference date regardless the classification as Stage 1 or 2 | L31: INSTRUMENT-IFRS9_LGD | M31: Concluido | O31: cd_captools.ifrs9_out_expected_loss_8_7 | P31: ‣ Apenas são trazidos os "contract_id"s que têm "exec_id_part" correspondente na tabela cd_captools.imcatf046_flag_fecho à data ("cmes") do report | Q31: contract_id | R31: ‣ Para cada Instrument Identifier é calculada a: ‣ Média ponderada do campo "lgd_ifrs9" em relação à: ‣ Média do campo "ead" para cada "contract_id" | S31: A agrupação é feita segundo o campo "Instrument Identifier" deste mesmo documento | T31: Tal como nos anteriores explorar porque é feita a média do ead
Q32: lgd_ifrs9
Q33: ead
A34: V_35 | B34: Instruments characteristics | C34: Type of instrument | D34: String | E34: Classification of the instrument according to the type of contractual terms agreed between the parties. Opções: ‣ Overdraft ‣ Credit card debt ‣ Revolving credit other than overdrafts and credit card debt ‣ Credit lines other than revolving credit ‣ Financial lease ‣ Loan ‣ Other | F34: Classificação do instrumento de acordo com o tipo de termos contratuais acordados entre as partes. Opções: ‣ Overdraft ‣ Credit card debt ‣ Revolving credit other than overdrafts and credit card debt ‣ Credit lines other than revolving credit ‣ Financial lease ‣ Loan ‣ Other | H34: INSTRUMENT-TYP_INSTRMNT | I34: Type of instrument | J34: Classification of the instrument according to the type of contractual terms agreed between the parties. | L34: INSTRUMENT-TYP_INSTRMNT | M34: Mapeamento com LT fechado, mas parametrização pendente | O34: Tabela de parametrização: codemapping | P34: ‣ dd_field_id = "35" | Q34: dd_code | R34: ‣ Tradução do campo "typ_instrmnt" através de uma ligação com o campo "dd_code" para obter o campo: dd_value
Q35: dd_value
O36: cd_loan_tapes_bce.lt002_instrument | P36: ‣ ref_date = data do report | Q36: typ_instrmnt
A37: V_142 | B37: Instruments characteristics | C37: Amortization type | D37: String | E37: Type of amortisation of the instrument including principal and interest at the reporting reference date. Opções: ‣ French ‣ German ‣ Fixed amortisation schedule ‣ Bullet ‣ Other | F37: Tipo de amortização do instrumento incluindo capital e juros à data de referência do relato. Opções: ‣ French ‣ German ‣ Fixed amortisation schedule ‣ Bullet ‣ Other | H37: INSTRUMENT-TYP_AMRTSTN | I37: Type of amortisation | J37: Type of amortisation of the instrument including principal and interest. | L37: INSTRUMENT-TYP_AMRTSTN | M37: Mapeamento com LT fechado, mas parametrização pendente | O37: Tabela de parametrização: codemapping | P37: ‣ dd_field_id = "3" | Q37: dd_code | R37: ‣ Tradução do campo "typ_amrtstn" através de uma ligação com o campo "dd_code" para obter o campo: dd_value
Q38: dd_value
O39: cd_loan_tapes_bce.lt002_instrument | P39: ‣ ref_date = data do report | Q39: typ_amrtstn
A40: V_143 | B40: Instruments characteristics | C40: Currency | D40: String | E40: Currency denomination of instruments, in accordance with the ISO 4217 standard. | F40: Denominação monetária dos instrumentos, de acordo com a norma ISO 4217. | H40: INSTRUMENT-CRRNCY_DNMNTN | I40: Currency denomination | J40: Currency denomination of instruments, in accordance with the ISO 4217 standard. | L40: INSTRUMENT-CRRNCY_DNMNTN | M40: Mapeamento com LT fechado, mas parametrização pendente | O40: cd_alm.al029_cnt_core_m | P40: ‣ ref_date = data do report | Q40: cmoeda_act | R40: ‣ Se o contrato for ativo: cmoeda_act ‣ Se o contrato for passivo: cmoeda_pas | T40: Não trazer componente passiva, e o universo pode alterar para as fr
Q41: cmoeda_pas
A42: V_144 | B42: Instruments characteristics | C42: Inception date | D42: DD/MM/AA | E42: The date on which the contractual relationship originated, i.e. the date on which the contract agreement becomes binding for all parties. | F42: A data em que a relação contratual se originou, ou seja, a data em que o acordo contratual se torna vinculativo para todas as partes. | H42: INSTRUMENT-DT_INCPTN | I42: Date of inception | J42: The date on which the contractual relationship originated, i.e. the date on which the contract agreement becomes binding for all parties | L42: INSTRUMENT-DT_INCPTN | M42: Concluido | O42: cd_alm.al029_cnt_core_m | P42: ‣ ref_date = data do report | Q42: dinicio | R42: ‣ Direto | T42: Alterando a granularidade também deveriamos trazer esta info de outro lado
A43: V_145 | B43: Interest rate information | C43: End date of interest-only period | D43: DD/MM/AA | E43: The date on which the interest-only period ends. | F43: A data em que termina o período somente de juros. | H43: INSTRUMENT-DT_END_INTRST_ONLY | I43: End date of the interest-only period | J43: The date on which the interest-only period ends. Interest-only instruments are those for which, for a contractually set period, only the interest on the principal balance is paid, with the principal balance remaining unchanged. The scope of the field refers to any interest only period, either due to renegotiations or interest only agreements at loan inception. | L43: INSTRUMENT-DT_END_INTRST_ONLY | M43: Concluido | O43: cd_alm.al029_cnt_core_m | P43: ‣ ref_date = data do report | Q43: dfim_care | R43: ‣ Direto
A44: V_146 | B44: Interest rate information | C44: Interest rate cap | D44: Numeric. Reported in basis points with the same convention as for the attribute “interest rate spread/margin”. | E44: The maximum interest rate per annum that can be charged on the outstanding nominal amount (or parts thereof). | F44: A taxa de juros máxima anual que pode ser cobrada sobre o valor nominal em dívida (ou partes dele). | H44: - | I44: - | J44: - | L44: ‣ Não encontramos no LT -> Confirmar com Nádia Ahmad e Dora Roxo; Segundo LCM, terá de se adicionar um campo novo a constar na al029_cnt_core_m | M44: Novo campo, mapeamento datalake pendente, sem necessidade de criar parametrização | O44: Não foi implementado | P44: Não foi implementado | Q44: Não foi implementado | R44: Não foi implementado | S44: Não foi implementado | T44: Ver como são obtidos no ALM.
A45: V_147 | B45: Interest rate information | C45: Interest rate floor | D45: Numeric. Reported in basis points with the same convention as for the attribute “interest rate spread/margin”. | E45: The minimum interest rate per annum that can be charged on the outstanding nominal amount (or parts thereof). | F45: A taxa de juros mínima anual que pode ser cobrada sobre o valor nominal em dívida (ou partes dele). | H45: - | I45: - | J45: - | L45: ‣ Não encontramos no LT -> Confirmar com Nádia Ahmad e Dora Roxo; Segundo LCM, terá de se adicionar um campo novo a constar na al029_cnt_core_m | M45: Novo campo, mapeamento datalake pendente, sem necessidade de criar parametrização | O45: Não foi implementado | P45: Não foi implementado | Q45: Não foi implementado | R45: Não foi implementado | S45: Não foi implementado
A46: V_148 | B46: Interest rate information | C46: Interest rate reset frequency | D46: String | E46: Frequency at which the interest rate is reset after the initial fixed-rate period, if any. Opções: ‣ Overnight ‣ Monthly/quarterly/semiannual/ annual ‣ At creditor discretion ‣ Other frequency | F46: Frequência com que a taxa de juro é reposta após o período inicial de taxa fixa, se existir. Opções: ‣ Overnight ‣ Monthly/quarterly/semiannual/ annual ‣ At creditor discretion ‣ Other frequency | H46: INSTRUMENT-INTRST_RT_RST_FRQNCY | I46: Interest rate reset frequency | J46: Frequency at which the interest rate is reset after the initial fixed-rate period, if any. | L46: INSTRUMENT-INTRST_RT_RST_FRQNCY | M46: Mapeamento com LT fechado, mas parametrização pendente | O46: cd_alm.al029_cnt_core_m | P46: ‣ ref_date = data do report | Q46: cod_freq_taxa_act | R46: ‣ Inicialmente é obtida a varivel intermedia "cod_freq_taxa": ‣ Se o contrato for ativo: cod_freq_taxa_act ‣ Se o contrato for passivo: cod_freq_taxa_pas ‣ De seguida é obtido este campo aplicando as seguintes regras: ‣ Se cod_freq_taxa for "0": "OVERNIGHT" ‣ Se cod_freq_taxa for "2" ou "M" e se as 8 posições após o primeiro caracter retornarem "1": "MONTHLY" ‣ Se cod_freq_taxa for "2" ou "M" e se as 8 posições após o primeiro caracter retornarem "3": "QUARTERLY" ‣ Se (cod_freq_taxa for "2" ou "M" e se as 8 posições após o primeiro caracter retornarem "6") ou se (cod_freq_taxa for "R" e se as 8 posições após o primeiro caracter retornarem "2") ou se (cod_freq_taxa for "E" e se as 8 posições após o primeiro caracter retornarem "1"): "SEMI-ANNUAL" ‣ Se (cod_freq_taxa for "2" ou "M" e se as 8 posições após o primeiro caracter retornarem "12") ou se (cod_freq_taxa for "R" e se as 8 posições após o primeiro caracter retornarem "4") ou se (cod_freq_taxa for "E" e se as 8 posições após o primeiro caracter retornarem "2") ou se (cod_freq_taxa for "3" ou "N" e se as 8 posições após o primeiro caracter retornarem "1"): "ANNUAL" ‣ Caso contrário: "OTHER FREQUENCY" Nota esta regra está mal definida logo pelo facto de a mesma string não poder ser igual a um caracter "2" ou "M" por exemplo e depois ter também 8 caracteres a seguir com "1". Necessário rever este campo | T46: Alterando a granularidade também deveriamos trazer esta info de outro lado
Q47: cod_freq_taxa_pas
A48: V_149 | B48: Interest rate information | C48: Interest rate spread/margin | D48: Numeric (percentage) | E48: Margin or spread to add to the reference rate that is used for the calculation of the interest rate in basis points. This applies to interest rates charged for variable interest loans. | F48: Margem ou spread a adicionar à taxa de referência utilizada para o cálculo da taxa de juro em pontos de base. Isto aplica-se às taxas de juro cobradas pelos empréstimos com juros variáveis. | H48: - | I48: - | J48: - | L48: INSTRUMENT-SPRD | M48: Concluido | O48: cd_alm.al029_cnt_core_m | P48: ‣ ref_date = data do report | Q48: tx_spread_act_1 | R48: ‣ Se o contrato for ativo: tx_spread_act_1 ‣ Se o contrato for passivo: tx_spread_pas_1 | T48: Alterando a granularidade também deveriamos trazer esta info de outro lado
Q49: tx_spread_pas_1
A50: V_150 | B50: Interest rate information | C50: Interest rate type | D50: String | E50: Classification of credit exposures based on the base rate for establishing the interest rate for each payment period. Opções: ‣ Fixed ‣ Variable ‣ Mixed | F50: Classificação das posições em risco de crédito com base na taxa de base para determinar a taxa de juro para cada período de pagamento. Opções: ‣ Fixed ‣ Variable ‣ Mixed | H50: INSTRUMENT-TYP_INTRST_RT | I50: Type of interest rate | J50: Classification of credit exposures based on the base rate for establishing the interest rate for each payment period. | L50: INSTRUMENT-TYP_INTRST_RT | M50: Mapeamento com LT fechado, mas parametrização pendente | O50: cd_alm.al029_cnt_core_m | P50: ‣ ref_date = data do report | Q50: cod_tipo_taxa_ref_act | R50: ‣ Inicialmente é obtida a varivel intermedia "cod_tipo_taxa_ref": ‣ Se o contrato for ativo: cod_tipo_taxa_ref_act ‣ Se o contrato for passivo: cod_tipo_taxa_ref_pas ‣ De seguida é obtido este campo aplicando as seguintes regras: ‣ Se cod_tipo_taxa_ref = "V": "Variable" ‣ Se cod_tipo_taxa_ref = "F": "Fixed" ‣ Caso contrário: "Mixed" | T50: Alterando a granularidade também deveriamos trazer esta info de outro lado
Q51: cod_tipo_taxa_ref_pas
A52: V_151 | B52: Instrument characteristics | C52: Legal final maturity date | D52: DD/MM/AA | E52: The contractual maturity date of the instrument, taking into account any agreements amending initial contracts. | F52: A data de vencimento contratual do instrumento, tendo em conta quaisquer acordos que alterem contratos iniciais. | H52: INSTRUMENT-DT_LGL_FNL_MTRTY | I52: Legal final maturity date (latest repayment date) | J52: The contractual maturity date of the instrument, taking into account any agreements amending initial contracts. As for retail revolving credit facilities this attribute is to be reported "not applicable". | L52: INSTRUMENT-DT_LGL_FNL_MTRTY | M52: Concluido | O52: cd_alm.al029_cnt_core_m | P52: ‣ ref_date = data do report | Q52: dfim | R52: ‣ Direto | T52: Alterando a granularidade também deveriamos trazer esta info de outro lado
A53: V_152 | B53: Instrument characteristics | C53: Commitment amount at inception | D53: Numeric (euro) | E53: Observed agent’s maximum exposure to credit risk on the inception date of the instrument, without taking into account any protection held or other credit enhancements. | F53: Exposição máxima do agente observado ao risco de crédito na data de início do instrumento, sem ter em conta qualquer proteção detida ou outras melhorias de crédito. | H53: INSTRUMENT-CMMTMNT_INCPTN_INSTRMNT | I53: Commitment amount at inception | J53: Observed agent’s maximum exposure to credit risk on the inception date of the instrument, without taking into account any protection held or other credit enhancements. Total commitment amount on the inception date is established during the approval process and is intended to restrict an observed agent’s amount of credit risk to a given counterparty for the relevant instrument. | L53: INSTRUMENT-CMMTMNT_INCPTN_INSTRMNT | M53: Concluido | O53: cd_loan_tapes_bce.lt002_instrument | P53: ‣ ref_date = data do report | Q53: cmmtmnt_incptn_instrmnt | R53: ‣ Direto
A54: V_153 | B54: Instrument characteristics | C54: Payment frequency | D54: String | E54: Frequency of payments due, either of principal or interest, i.e. number of months between payments at the reporting reference date. Opções: ‣ Monthly/quarterly/semiannual/annual ‣ Bullet ‣ Zero coupon ‣ Other | F54: Periodicidade dos pagamentos devidos, quer de capital quer de juros, ou seja, número de meses entre pagamentos na data de referência de relato. | H54: INSTRUMENT-PYMNT_FRQNCY | I54: Payment frequency | J54: Frequency of payments due, either of principal or interest, i.e. number of months between payments. | L54: INSTRUMENT-PYMNT_FRQNCY | M54: Mapeamento com LT fechado, mas parametrização pendente | O54: cd_alm.al029_cnt_core_m | P54: ‣ ref_date = data do report | Q54: tx_contrato_act | R54: ‣ Este campo está dividido em dois outros v_153_interest_payment_freq e v_153_capital_payment_freq ‣ v_153_interest_payment_freq: ‣ Inicialmente são obtidas as variváveis intermedias "tx_contrato" e "cod_freq_liq_jur": ‣ Se o contrato for ativo: tx_contrato_act; cod_freq_liq_jur_act; ‣ Se o contrato for passivo: tx_contrato_pas; cod_freq_liq_jur_pas; ‣ De seguida é obtido este campo aplicando as seguintes regras: ‣ Se tx_contrato for 0: "Zero Coupon" ‣ Se cod_freq_liq_jur for "2" ou "M" e se as 8 posições após o primeiro caracter retornarem "1": "Monthly" ‣ Se (cod_freq_liq_jur for "2" ou "M" e se as 8 posições após o primeiro caracter retornarem "3") ou se (cod_freq_liq_jur for "R" e se as 8 posições após o primeiro caracter retornarem "1"): "Quarterly" ‣ Se (cod_freq_liq_jur for "2" ou "M" e se as 8 posições após o primeiro caracter retornarem "6") ou se (cod_freq_liq_jur for "R" e se as 8 posições após o primeiro caracter retornarem "2") ou se (cod_freq_liq_jur for "E" e se as 8 posições após o primeiro caracter retornarem "1"): "Semi-annual" ‣ Se (cod_freq_liq_jur for "2" ou "M" e se as 8 posições após o primeiro caracter retornarem "12") ou se (cod_freq_liq_jur for "R" e se as 8 posições após o primeiro caracter retornarem "4") ou se (cod_freq_liq_jur for "E" e se as 8 posições após o primeiro caracter retornarem "2") ou se (cod_freq_liq_jur for "3" ou "N" e se as 8 posições após o primeiro caracter retornarem "1"): "Annual" ‣ Caso contrário: "Other frequency" ‣ v_153_capital_payment_freq: ‣ Inicialmente é obtida a varivável intermedia "cod_freq_amort_capital": ‣ Se o contrato for ativo: cod_freq_amort_capital_act; ‣ Se o contrato for passivo: cod_freq_amort_capital_pas; ‣ De seguida é obtido este campo aplicando as seguintes regras: ‣ Se cod_tipo_amortizacao for "A" ou "U": "Bullet" ‣ Se cod_freq_amort_capital for "2" ou "M" e se as 8 posições após o primeiro caracter retornarem "1": "Monthly" ‣ Se (cod_freq_amort_capital for "2" ou "M" e se as 8 posições após o primeiro caracter retornarem "3") ou se (cod_freq_amort_capital for "R" e se as 8 posições após o primeiro caracter retornarem "1"): "Quarterly" ‣ Se (cod_freq_amort_capital for "2" ou "M" e se as 8 posições após o primeiro caracter retornarem "6") ou se (cod_freq_amort_capital for "R" e se as 8 posições após o primeiro caracter retornarem "2") ou se (cod_freq_amort_capital for "E" e se as 8 posições após o primeiro caracter retornarem "1"): "Semi-annual" ‣ Se (cod_freq_amort_capital for "2" ou "M" e se as 8 posições após o primeiro caracter retornarem "12") ou se (cod_freq_amort_capital for "R" e se as 8 posições após o primeiro caracter retornarem "4") ou se (cod_freq_amort_capital for "E" e se as 8 posições após o primeiro caracter retornarem "2") ou se (cod_freq_amort_capital for "3" ou "N" e se as 8 posições após o primeiro caracter retornarem "1"): "Annual" ‣ Caso contrário: "Other frequency"
Q55: tx_contrato_pas
Q56: cod_freq_liq_jur_act
Q57: cod_freq_liq_jur_pas
Q58: cod_tipo_amortizacao
Q59: cod_freq_amort_capital_act
Q60: cod_freq_amort_capital_pas
A61: V_154 | B61: Instrument characteristics | C61: Reference rate | D61: String | E61: Reference rate used for the calculation of the actual interest rate. The reference rate code is a combination of the reference rate value and maturity value. Opções: ‣ EURIBOR ‣ USD LIBOR ‣ GBP LIBOR ‣ EUR LIBOR ‣ JPY LIBOR ‣ CHF LIBOR ‣ MIBOR ‣ OTHER SINGLE REFERENCE RATES ‣ OTHER MULTIPLE REFERENCE RATES | F61: Taxa de referência utilizada para o cálculo da taxa de juro efetiva. O código da taxa de referência é uma combinação do valor da taxa de referência e do valor do prazo de vencimento. Opções: ‣ EURIBOR ‣ USD LIBOR ‣ GBP LIBOR ‣ EUR LIBOR ‣ JPY LIBOR ‣ CHF LIBOR ‣ MIBOR ‣ OTHER SINGLE REFERENCE RATES ‣ OTHER MULTIPLE REFERENCE RATES | H61: - | I61: - | J61: - | L61: ‣ Não encontramos no LT -> Confirmar com Nádia Ahmad e Dora Roxo; ‣ Se não existir no LT, consumir o campo "cod_tipo_taxa_ref_act" da tabela al029_cnt_core_m; ‣ Segundo Pedro Mendes LIBOR foram todas descontinuadas, é necessário definir um novo mapeamento (questionar corporação). | M61: Novo campo, mapeamento datalake fechado, com necessidade de criar parametrização | O61: cd_alm.al029_cnt_core_m | P61: ‣ ref_date = data do report | Q61: cod_tipo_taxa_ref_act | R61: ‣ Se o contrato for ativo: cod_tipo_taxa_ref_act ‣ Se o contrato for passivo: cod_tipo_taxa_ref_pas
Q62: cod_tipo_taxa_ref_pas
A63: V_155 | B63: Instrument characteristics | C63: Settlement date | D63: DD/MM/AA | E63: The date on which the conditions specified in the contract are or can be executed for the first time, i.e. the date on which financial instruments are initially exchanged or created. | F63: A data em que as condições especificadas no contrato são ou podem ser executadas pela primeira vez, ou seja, a data em que os instrumentos financeiros são inicialmente trocados ou criados. | H63: - | I63: - | J63: - | L63: INSTRUMENT-DT_INCPTN Devido ao facto do DT_INCPTN ser usado em 2 campos do CSV (Inception date e Settlement date) terá de se ver com Mónica se isto é possível. Em caso negativo terá de se alterar o processo para permitir. | M63: Concluido | O63: cd_alm.al007_prog_ppc | P63: ‣ ref_date = data do report | Q63: dbreak_clause | R63: ‣ Direto
A64: V_156 | B64: Interest rate information | C64: Interest rate | D64: Numeric (percentage with two decimals, both positive and negative values). | E64: Annualised agreed rate or narrowly defined interest rate in accordance with Part 1 of Annex I to Regulation (EU) No 1072/2013 of the European Central Bank (ECB/2013/34) | F64: Taxa acordada numa base anual ou taxa de juro estritamente definida de acordo com a parte 1 do anexo I do Regulamento (UE) No 1072/2013 do Banco Central Europeu (BCE/2013/34) | H64: INSTRUMENT-ANNLSD_AGRD_RT | I64: Interest rate at the reference date | J64: Annualised agreed rate or narrowly defined interest rate at reference date in accordance with Regulation (EU) No 1072/2013 of the European Central Bank (ECB/2013/34). | L64: INSTRUMENT-ANNLSD_AGRD_RT | M64: Concluido | O64: cd_alm.al029_cnt_core_m | P64: ‣ ref_date = data do report | Q64: tx_contrato_act | R64: ‣ Se o contrato for ativo: tx_contrato_act ‣ Se o contrato for passivo: tx_contrato_pas
Q65: tx_contrato_pas
A66: V_157 | B66: Interest rate information | C66: Next interest rate reset date | D66: DD/MM/AA | E66: The date when the next interest rate reset, as defined in Part 3 of Annex I to Regulation (EU) No 1071/2013 (ECB/2013/33), takes place. | F66: A data em que ocorre a próxima reposição da taxa de juro, tal como definida na parte 3 do anexo I do Regulamento (UE) No 1071/2013 (BCE/2013/33). | H66: INSTRUMENT-DT_NXT_INTRST_RT_RST | I66: Next interest rate reset date | J66: The date when the next interest rate reset, as defined in Part 3 of Annex I to Regulation (EU) No 1071/2013 (ECB/2013/33), takes place. | L66: INSTRUMENT-DT_NXT_INTRST_RT_RST | M66: Concluido | O66: cd_alm.al029_cnt_core_m | P66: ‣ ref_date = data do report | Q66: dt_prox_renov_taxa_act | R66: ‣ Se o contrato for ativo: dt_prox_renov_taxa_act ‣ Se o contrato for passivo: dt_prox_renov_taxa_pas
Q67: dt_prox_renov_taxa_pas
A68: V_158 | B68: Financial information | C68: Default status of the instrument | D68: String | E68: Identification of the default status of the instrument in accordance with Article 178 of Regulation (EU) No 575/2013. Opções: ‣ Not in default ‣ Default because unlikely to pay (not more than 90/180 days past due) ‣ Default because more than 90/180 days past due ‣ Default because both unlikely to pay and more than 90/180 days past due. | F68: Identificação da situação de incumprimento do instrumento em conformidade com o artigo 178 do Regulamento (UE) No 575/2013. Opções: ‣ Not in default ‣ Default because unlikely to pay (not more than 90/180 days past due) ‣ Default because more than 90/180 days past due ‣ Default because both unlikely to pay and more than 90/180 days past due. | H68: INSTRUMENT-DFLT_STTS_INSTRMNT | I68: Default status of the instrument | J68: Identification of the default status of the instrument. Categories describing the situations in which an instrument can be described as being at default in accordance with Article 178 of Regulation (EU) No 575/2013. | L68: INSTRUMENT-DFLT_STTS_INSTRMNT | M68: Mapeamento com LT fechado, mas parametrização pendente | O68: Tabela de parametrização: codemapping | P68: ‣ dd_field_id = "158" | Q68: dd_code | R68: ‣ Tradução do campo "dflt_stts_instrmnt" através de uma ligação com o campo "dd_code" para obter o campo: dd_value
Q69: dd_value
O70: cd_loan_tapes_bce.lt002_instrument | P70: ‣ ref_date = data do report | Q70: dflt_stts_instrmnt
A71: V_159 | B71: Financial information | C71: Date of the default status of the instrument | D71: DD/MM/AA | E71: The date on which the default status, as reported in the data attribute “default status of the instrument”, is considered to have occurred. | F71: A data em que o status padrão, conforme relatado no atributo de dados "Default status of the instrument", é considerado como tendo ocorrido. | H71: INSTRUMENT-DT_DFLT_STTS_INSTRMNT | I71: Date of default status | J71: The date on which the default status, as reported in the data attribute “Default status”, is considered to have arisen. If "Not in default" since inception then this attribute is to be reported equally to the inception date. If more than one Instrument is classified as defaulted then the earliest date has to be provided. The definition of default is aligned with Art 178 of Regulation (EU) No 575/2013. | L71: INSTRUMENT-DT_DFLT_STTS_INSTRMNT | M71: Concluido | O71: cd_loan_tapes_bce.lt002_instrument | P71: ‣ ref_date = data do report | Q71: dt_dflt_stts_instrmnt | R71: ‣ Direto
A72: V_160 | B72: Financial information | C72: Transferred amount | D72: Numeric (euro) | E72: Transferred amount of the economic ownership of the financial asset to third parties. This data attribute captures the part of the outstanding nominal amount that has been transferred to another creditor. | F72: Montante transferido da propriedade económica do ativo financeiro para terceiros. Este atributo de dados capta a parte do montante nominal pendente que foi transferida para outro credor. | H72: - | I72: - | J72: - | L72: Este campo é Not Applicable, reportar: 11111111111 | M72: Concluido | O72: N/A | P72: N/A | Q72: N/A | R72: N/A | S72: N/A | T72: N/A
A73: V_161 | B73: Financial information | C73: Arrears for the instrument | D73: Numeric (euro) | E73: Aggregated amount of the principal, interest and any fee payment outstanding at the reporting date, which is contractually due and has not been paid (past due). | F73: Montante agregado do capital, juros e quaisquer pagamentos de comissões pendentes à data de relato, contratualmente devidos e não pagos (vencidos). | H73: INSTRUMENT-ARRRS_INSTRMNT | I73: Total exposure in arrears | J73: Aggregated amount of the principal, interest and any fee payment outstanding at the reporting date, which is contractually due and has not been paid (past due). | L73: INSTRUMENT-ARRRS_INSTRMNT | M73: Concluido | O73: cd_loan_tapes_bce.lt002_instrument | P73: ‣ ref_date = data do report | Q73: arrrs_instrmnt | R73: ‣ Direto
A74: V_162 | B74: Financial information | C74: Date of past due for the instrument | D74: DD/MM/AA | E74: The date on which the instrument became past due in accordance with Part 2.96 of Annex V to the amended Implementing Regulation (EU) No 680/2014. | F74: Data de vencimento do ato, em conformidade com a parte 2.96 do anexo V do Regulamento de Execução (UE) No 680/2014 alterado. | H74: INSTRUMENT-DT_PST_D | I74: Date past due | J74: The date on which the instrument became past due in accordance with Part 2.96 of Annex V to the amended Implementing Regulation (EU) No 680/2014. This is the latest such date prior to the reporting reference date and it is to be reported if the instrument is past due on the reporting reference date. | L74: INSTRUMENT-DT_PST_D | M74: Concluido | O74: cd_captools.ct004_univ_cto | P74: ‣ ref_date = data do report | Q74: dincump | R74: ‣ Direto
A75: V_163 | B75: Financial information/Instrument characteristics | C75: Type of securitization | D75: String | E75: Captures the type of securitisation, if any, to which the instrument has been subject, in accordance with Article 242(10), (11), 243 and 244 of Regulation (EU) No 575/2013. Opções: ‣ Traditional securitisation ‣ Synthetic securitisation ‣ Not securitised | F75: Abrange o tipo de titularização, se for caso disso, a que o instrumento foi sujeito, em conformidade com o artigo 242(10), (11), 243 e 244 do Regulamento (UE) No 575/2013. Opções: ‣ Traditional securitisation ‣ Synthetic securitisation ‣ Not securitised | H75: - | I75: - | J75: - | L75: ‣ Não encontramos no LT -> Confirmar com Nádia Ahmad e Dora Roxo; Resposta do Email a Pedro Inacio (19:44 12-03-2024): "Essa informação pode ser obtida no campo “Tipo de Titulización” da tabela SPV da BDR (E0691_TITU_TIP), com o seguinte detalhe: 00 - 'No informado' 01 - 'Tradicional' 02 - 'Sintética' 99999 - 'No aplica' " | M75: Novo campo, mapeamento datalake pendente, com necessidade de criar parametrização | O75: cd_captools.ct013_rwa_princ | P75: ‣ ref_date = data do report ‣ flag_cons_cap = 1 ‣ exercicio = 'REAL' | Q75: cod_spv | R75: ‣ Se o campo "cod_spv" começar por "SYN": "SYNTHETIC SECURITISATION" ‣ Se o campo "cod_spv" não for "" (vazio): "TRADITIONAL SECURITISATION" ‣ Caso contrário (se o contrato não estiver na tabela ct013_rwa_princ): "NOT SECURITISED"
A76: V_164 | B76: Instrument charcteristics | C76: Outstanding nominal amount | D76: Numeric (euro) | E76: Principal amount outstanding at the end of the reporting reference date, including unpaid past due interest but excluding accrued interest, net of write-offs and write-downs as determined by the relevant accounting practices. | F76: Montante de capital em dívida no final da data de referência do relato, incluindo juros vencidos não pagos, mas excluindo juros vencidos, líquidos de anulações e amortizações, conforme determinado pelas práticas contabilísticas relevantes. | H76: INSTRUMENT-OTSTNDNG_NMNL_AMNT_INSTRMNT | I76: Outstanding gross nominal amount | J76: Principal amount outstanding at the end of the reporting reference date, including unpaid past due interest but excluding accrued interest. The outstanding nominal amount must be reported net of write-offs and write-downs as determined by the relevant accounting practices. | L76: INSTRUMENT-OTSTNDNG_NMNL_AMNT_INSTRMNT | M76: Concluido | O76: cd_loan_tapes_bce.lt002_instrument | P76: ‣ ref_date = data do report | Q76: otstndng_nmnl_amnt_instrmnt | R76: ‣ Direto
A77: V_165 | B77: Instrument charcteristics | C77: Accrued interest | D77: Numeric (euro) | E77: The amount of accrued interest on loans at the reporting reference date as defined in Regulation (EU) No 1071/2013 (ECB/2013/33). | F77: O montante dos juros vencidos sobre empréstimos na data de referência de reporte, tal como definido no Regulamento (UE) No 1071/2013 (BCE/2013/33). | H77: INSTRUMENT-ACCRD_INTRST_INSTRMNT | I77: Accrued interest balance as recognised on the balance sheet | J77: The amount of accrued interest on loans at the reporting reference date as defined in Regulation (EU) No 1071/2013 (ECB/2013/33). In accordance with the general principle of accruals accounting, interest receivable on instruments should be subject to on-balance sheet recording as it accrues (i.e. on an accruals basis) rather than when it is actually received (i.e. on a cash basis). | L77: INSTRUMENT-ACCRD_INTRST_INSTRMNT | M77: Concluido | R77: ‣ Forçado a NULL
A78: V_166 | B78: Financial information | C78: Off-balancesheet amount | D78: Numeric (euro) | E78: Total nominal amount of off-balance-sheet exposures. | F78: Montante nominal total das posições em risco extrapatrimoniais. | H78: INSTRUMENT-OFF_BLNC_SHT_AMNT_INSTRMNT | I78: Off-balance sheet amount | J78: Total nominal amount of off-balance-sheet exposures. This includes any commitment to lend before considering conversion factors and credit risk mitigation techniques. It is the amount that best represents the institution’s maximum exposure to credit risk without taking into account any protection held or other credit enhancements. To be reported in accordance with Annex V Regulation 680/2014. If no amount can be drawn by or disbursed to the debtor without contractual changes, the off-balance-sheet amount of the instrument is reported as ”not applicable”. | L78: INSTRUMENT-OFF_BLNC_SHT_AMNT_INSTRMNT | M78: Concluido | O78: cd_alm.al030_sld_core_m | P78: ‣ ref_date = data do report | Q78: mon_extrapatri | R78: ‣ Direto | S78: Ignorei a parte em que também se traz a componente passiva
A79: V_167 | B79: Financial information | C79: Joint liabilities amount | D79: Numeric (euro) | E79: Outstanding nominal amount for which each debtor is liable in relation to a single instrument where there are two or more debtors. | F79: Montante nominal pendente pelo qual cada devedor é responsável em relação a um único instrumento, caso existam dois ou mais devedores. | H79: Not applicable: To be reported as "11111111111". This information will be availabe in "02_04_nat_instr_count" table | I79: - | J79: - | L79: Not applicable: To be reported as "11111111111". This information will be availabe in "02_04_nat_instr_count" table | M79: Concluido | O79: cd_loan_tapes_bce.lt005_instr_ent | P79: ‣ ref_date = data do report | Q79: jnt_lblty_amnt | R79: ‣ Direto
A80: V_168 | B80: Informação financeira | C80: Accounting classification of instruments | D80: String | E80: Accounting portfolio where the instrument is recorded in accordance with the accounting standard – IFRS or national GAAP – under Regulation (EU) 2015/534 (ECB/2015/13) applied by the observed agent’s legal entity. Opções: | F80: Carteira contabilística em que o instrumento é registado de acordo com a norma contabilística – IFRS ou GAAP nacionais – nos termos do Regulamento (UE) 2015/534 (BCE/2015/13) aplicada pela entidade jurídica do agente observado. Opções: | H80: INSTRUMENT-ACCNTNG_CLSSFCTN | I80: Accounting portfolio | J80: Accounting portfolio where the instrument is recorded in accordance with the accounting standard – IFRS or national GAAP – under Regulation (EU) 2015/534 (ECB/2015/13) applied by the observed agent’s legal entity. | L80: INSTRUMENT-ACCNTNG_CLSSFCTN | M80: Mapeamento com LT fechado, mas parametrização pendente | O80: Tabela de parametrização: codemapping | P80: ‣ dd_field_id = "168" | Q80: dd_code | R80: ‣ Inicialmente para cada combinação dos campos "cempresa", "cbalcao", "cnumecta", "zdeposit" iremos recuperar o MAX(carteira_contabilistica): ‣ Este campo MAX(carteira_contabilistica) será traduzido através de uma ligação com o campo "dd_code" para obter o campo: dd_value
Q81: dd_value
O82: cd_captools.ct081_finrep | P82: ‣ ref_date = data do report | Q82: cempresa
Q83: cbalcao
Q84: cnumecta
Q85: zdeposit
Q86: carteira_contabilistica
A87: V_169 | B87: Informação financeira | C87: Balance sheet recognition | D87: String | E87: Balance sheet recognition of the financial asset. This data attribute classifies the reported instruments pursuant to their balance sheet recognition in accordance with Annex III and Template 15 in Annex IV to the ITS. Opções: ‣ Entirely recognised ‣ Recognised to the extent of the institution’s continuing involvement ‣ Entirely derecognised | F87: Reconhecimento de balanço do ativo financeiro. Este atributo de dados classifica os instrumentos reportados de acordo com o seu reconhecimento no balanço de acordo com o anexo III e o modelo 15 do anexo IV da ITS. Opções: ‣ Entirely recognised ‣ Recognised to the extent of the institution’s continuing involvement ‣ Entirely derecognised | H87: - | I87: - | J87: - | L87: ‣ Não encontramos no LT -> Confirmar com Nádia Ahmad e Dora Roxo Foi marcada uma reuniao com Luisa/Rafael (02-04-2024) para discutir este campo juntamente com o campo "Off-balance sheet": Questionar LCM com que entendimento ficou? Sempre 'Entirely recognised' ou sempre 'NA'. | M87: Novo campo, mapeamento datalake pendente, com necessidade de criar parametrização | O87: Não foi implementado | P87: Não foi implementado | Q87: Não foi implementado | R87: Não foi implementado | S87: Não foi implementado
A88: V_170 | B88: Financial information | C88: Accumulated write-offs | D88: Numeric (euro) | E88: Cumulative amount of principal and past due interest of any debt instrument that the institution is no longer recognising because they are considered uncollectible, independently of the portfolio in which they were included. | F88: Montante acumulado de capital e juros vencidos de qualquer instrumento de dívida que a instituição deixou de reconhecer por serem considerados incobráveis, independentemente da carteira em que estavam incluídos. | H88: INSTRUMENT-ACCMLTD_WRTFFS_INSTRMNT | I88: Accumulated write-offs | J88: Cumulative amount of principal and past due interest of any debt instrument that the institution is no longer recognising because they are considered uncollectible, independently of the portfolio in which they were included. Write-offs could be caused both by reductions in the carrying amount of financial assets recognised directly in profit or loss and by reductions in the amounts of the allowance accounts for credit losses set off against the carrying amount of financial assets. | L88: INSTRUMENT-ACCMLTD_WRTFFS_INSTRMNT | M88: Concluido | O88: Não foi implementado | P88: Não foi implementado | Q88: Não foi implementado | R88: Não foi implementado | S88: Não foi implementado
A89: V_171 | B89: Financial information | C89: Accumulated impairment amount | D89: Numeric (euro) | E89: The amount of loss allowances that are held against or are allocated to the instrument on the reporting reference date. This data attribute applies to instruments subject to impairment under the applied accounting standard. Under IFRS, the accumulated impairment relates to the following amounts: (i) loss allowance at an amount equal to 12-month expected credit losses; (ii) loss allowance at an amount equal to lifetime expected credit losses. Under GAAP, the accumulated impairment relates to the following amounts: (i) loss allowance at an amount equal to general allowances; (ii) loss allowance at an amount equal to specific allowances. | F89: A quantia de provisões para perdas detidas ou imputadas ao instrumento na data de referência do relato. Este atributo de dados aplica-se a instrumentos sujeitos a imparidade ao abrigo da norma contabilística aplicada. Em IFRS, a imparidade acumulada respeita aos seguintes montantes: (i) provisão para perdas em um valor igual às perdas de crédito esperadas para 12 meses; (ii) provisão para perdas em montante igual às perdas de crédito esperadas ao longo da vida. De acordo com os GAAP, a imparidade acumulada refere-se aos seguintes montantes: (ii.i) provisão para perdas em montante igual às provisões gerais; (ii.ii) provisão para perdas em valor igual às provisões específicas. | H89: INSTRUMENT-ACCMLTD_IMPRMNT_INSTRMNT | I89: Sum of LLPs and other allowances | J89: The amount of loss allowances that are held against or are allocated to the instrument on the reporting reference date. This data attribute applies to instruments subject to impairment under the applied accounting standard. Under IFRS, the accumulated impairment relates to the following amounts: (i) loss allowance at an amount equal to 12-month expected credit losses; (ii) loss allowance at an amount equal to lifetime expected credit losses. Under nGAAP, the accumulated impairment relates to the following amounts: (i) loss allowance at an amount equal to specific allowances; (ii) loss allowance at an amount equal to general allowances. | L89: INSTRUMENT-ACCMLTD_IMPRMNT_INSTRMNT | M89: Concluido | O89: cd_alm.al030_sld_core_m | P89: ‣ ref_date = data do report ‣ tipo_balanco = "A" | Q89: mon_imparid_patri | R89: ‣ Soma dos campos mencionados anteriormente: mon_imparid_patri + mon_imparidade_extra
Q90: mon_imparidade_extra
A91: V_172 | B91: Financial information | C91: Type of impairment | D91: String | E91: This data attribute indicates the type of impairment to which the instrument is subject. Opções: ‣ Stage 1 (IFRS) ‣ Stage 2 (IFRS) ‣ Stage 3 (IFRS) ‣ General allowances (GAAP) ‣ Specific allowances (GAAP) | F91: Este atributo de dados indica o tipo de imparidade a que o instrumento é sujeito. Opções: ‣ Stage 1 (IFRS) ‣ Stage 2 (IFRS) ‣ Stage 3 (IFRS) ‣ General allowances (GAAP) ‣ Specific allowances (GAAP) | H91: INSTRUMENT-IMPRMNT_STTS | I91: Impairment status | J91: Type of impairment. | L91: INSTRUMENT-IMPRMNT_STTS | M91: Mapeamento com LT fechado, mas parametrização pendente | O91: Tabela de parametrização: codemapping | P91: ‣ dd_field_id = "172" | Q91: dd_code | R91: ‣ Tradução do campo "stage" através de uma ligação com o campo "dd_code" para obter o campo: dd_value
Q92: dd_value
O93: cd_captools.ct004_univ_cto | P93: ‣ ref_date = data do report | Q93: stage
A94: V_173 | B94: Financial information | C94: Impairment assessment method | D94: String | E94: The method by which the impairment is assessed, if the instrument is subject to impairment in accordance with applied accounting standards. Opções: ‣ Individually assessed ‣ Collectively assessed | F94: O método pelo qual a imparidade é avaliada, se o instrumento está sujeito a imparidade de acordo com as normas aplicadas à contabilidade. Opções: ‣ Individually assessed ‣ Collectively assessed | H94: INSTRUMENT-IMPRMNT_ASSSSMNT_MTHD | I94: Impairment assessment method | J94: The method by which the impairment is assessed, if the instrument is subject to impairment in accordance with applied accounting standards. Collective and individual methods are distinguished. | L94: INSTRUMENT-IMPRMNT_ASSSSMNT_MTHD | M94: Mapeamento com LT fechado, mas parametrização pendente | O94: Tabela de parametrização: codemapping | P94: ‣ dd_field_id = "173" | Q94: dd_code | R94: ‣ Tradução do campo "tipo_analise" através de uma ligação com o campo "dd_code" para obter o campo: dd_value
Q95: dd_value
O96: cd_captools.ct004_univ_cto | P96: ‣ ref_date = data do report | Q96: tipo_analise
A97: V_174 | B97: Instrument characteristics | C97: Sources of encumbrance | D97: String | E97: Type of transaction in which the exposure is encumbered in accordance with Implementing Regulation (EU) No 680/2014. An asset will be treated as encumbered if it has been pledged or if it is subject to any form of arrangement to secure, collateralise or credit enhance any instrument from which it cannot be freely withdrawn. Opções: ‣ Central bank funding ‣ Exchange traded derivatives ‣ Over-the-counter derivatives ‣ Deposits – repurchase agreements other than to central banks ‣ Deposits other than repurchase agreements ‣ Debt securities issued – covered bonds securities ‣ Debt securities issued – assetbacked securities ‣ Debt securities issued – other than covered bonds and ABSs ‣ Other sources of encumbrance ‣ No encumbrance | F97: Tipo de operação em que o risco é onerado de acordo com o Regulamento de Execução (UE) n.o 680/2014. Um ativo será tratado como onerado se tiver sido penhorado ou se estiver sujeito a qualquer forma de acordo para garantir, caucionar ou reforçar o crédito instrumento do qual não pode ser livremente retirado. Opções: ‣ Central bank funding ‣ Exchange traded derivatives ‣ Over-the-counter derivatives ‣ Deposits – repurchase agreements other than to central banks ‣ Deposits other than repurchase agreements ‣ Debt securities issued – covered bonds securities ‣ Debt securities issued – assetbacked securities ‣ Debt securities issued – other than covered bonds and ABSs ‣ Other sources of encumbrance ‣ No encumbrance | H97: - | I97: - | J97: - | L97: INSTRUMENT-SRCS_ENCMBRNC | M97: Mapeamento com LT fechado, mas parametrização pendente | O97: Tabela de parametrização: codemapping | P97: ‣ dd_field_id = "174" | Q97: dd_code | R97: ‣ Tradução do campo "srcs_encmbrnc" através de uma ligação com o campo "dd_code" para obter o campo: dd_value
Q98: dd_value
O99: cd_loan_tapes_bce.lt002_instrument | P99: ‣ ref_date = data do report | Q99: srcs_encmbrnc
A100: V_175 | B100: Financial information | C100: Performing status of the instrument | D100: String | E100: The instrument is to be classified on the reporting reference date, in accordance with Implementing Regulation (EU) No 680/2014. Opções: ‣ Non-performing ‣ Performing | F100: O instrumento deve ser classificado na data de referência do relatório, em conformidade com o Regulamento de Execução (UE) n.o 680/2014. | H100: INSTRUMENT-PRFRMNG_STTS | I100: Performing status | J100: The instrument is to be classified on the reference date under one of the following categories: performing or non-performing, in accordance with Implementing Regulation (EU) No 680/2014. If the performing status is measured on entity level only all instruments are to be classified according to the status on entity level. | L100: INSTRUMENT-PRFRMNG_STTS | M100: Mapeamento com LT fechado, mas parametrização pendente | O100: ifrs9_out_staging_8_7 | P100: ‣ Apenas são trazidos os "contract_id"s que têm "exec_id_part" correspondente na tabela cd_captools.imcatf046_flag_fecho à data ("cmes") do report | Q100: final_stage | R100: ‣ Se o campo "final_stage" for "3": "Non-performing" ‣ Caso contrário: "Performing"
...

Sheet NATURALP_COUNTERPARTIES
A1: SRB Counterparties Data Set for exposures to natural persons
A2: ID | B2: Categoria | C2: Coluna | D2: Tipo de dados | E2: Descrição | F2: Descrição | H2: Mapeamentos Corporação (LT) | I2: Descrição (LT) | J2: Additional Guidance (LT) | L2: Comentários | M2: Estado especificação | O2: Fontes de Informação | P2: Filtros | Q2: Campo | R2: Regras de Preenchimento | S2: Agrupações
A3: V_2 | B3: Identification information | C3: Counterparty Identifier | D3: Alphanumeric | E3: Identifier applied to uniquely identify each counterparty. | F3: Identificador aplicado para identificar exclusivamente cada contraparte. | H3: ENTITY-ENTTY_ID | I3: Entity ID | J3: An identifier applied by the reporting agent to uniquely identify each counterparty. Each counterparty has a unique and exclusive counterparty identifier. This means that this value will not change over time and can never be used as the counterparty identifier for any other counterparty. | L3: ENTITY-ENTTY_ID | M3: Concluido | O3: cd_alm.al029_cnt_core_m | P3: ‣ ref_date = data do report | Q3: zcliente | R3: ‣ Direto
A4: V_139 | B4: Risk parameters | C4: Probability of default | D4: Numeric. Basis points. | E4: The counterparty’s probability of default over one year, determined in accordance with Articles 160, 163, 179 and 180 of Regulation (EU) No 575/2013. The probability of default (PD) is in accordance with the requirements specific to PD estimation as laid down in the CRR. In the case of PDs produced at the instrument level only (the so-called product PD), the counterparty PD is reported as the exposure weighted average PD of all instruments of the counterparty. If, for a given counterparty, a PD is estimated for both the counterparty and (some of) the products of the counterparty, the counterparty’s PD is to be reported. | F4: A probabilidade de incumprimento da contraparte durante um ano, determinada nos termos dos artigos 160.o, 163.o, 179.o e 180.o do Regulamento (UE) n.o 575/2013. A probabilidade de incumprimento (PD) está em conformidade com os requisitos específicos para a estimativa da PD, tal como estabelecido no CRR. No caso de PD produzidos apenas ao nível do instrumento (o chamado PD do produto), o PD da contraparte é reportado como o PD médio ponderado da posição em risco de todos os instrumentos da contraparte. Se, para uma dada contraparte, for estimado um PD tanto para a contraparte como para (alguns dos) produtos da contraparte, deve ser comunicado o PD da contraparte. | H4: ENTITY-PD_CRR_RD | I4: Probability of default according to CRR at reference date | J4: The PD over one year, determined in accordance with Articles 160, 163, 179 and 180 of Regulation (EU) No 575/2013. If the PD is calculated on obligor level then provide the obligor PD. If the PD is calculated on instruments level please provide an EAD weighted average. | L4: ENTITY-PD_CRR_RD | M4: Concluido | O4: cd_captools.ct013_rwa_princ | P4: ‣ ref_date = data do report ‣ flag_cons_cap = 1 ‣ exercicio = 'REAL' | Q4: s1emp | R4: ‣ Este campo tem de ser calculado por fases: ‣ 1º - Calculamos o campo auxiliar "ead_final_bruta_grup1": Média do campo "ead_final_bruta" para cada par dos campos "s1emp", "contra1"; ‣ 2º - Calculamos o campo auxiliar "in_pdini_grup1": ‣ Para cada par dos campos "s1emp", "contra1", calculamos a média ponderada do campo "in_pdini" em relação ao campo "ead_final_bruta": SUM(in_pdini * ead_final_bruta) / SUM(ead_final_bruta) ‣ 3º - Calculamos o campo auxiliar "ead_final_bruta_grup2": Soma do campo auxiliar "ead_final_bruta_grup1" para cada combinação dos campos "cempresa", "cbalcao", "cnumecta", "zdeposit"; ‣ 4º - Calculamos o campo auxiliar "in_pdini_grup2": ‣ Para cada combinação dos campos "cempresa", "cbalcao", "cnumecta", "zdeposit", calculamos a média ponderada do campo auxiliar "in_pdini_grup1" em relação ao campo auxiliar "ead_final_bruta_grup1": SUM(in_pdini_grup1 * ead_final_bruta_grup1) / SUM(ead_final_bruta_grup1) ‣ Finalmente para cada Counterparty Identifier calculamos a média ponderada do campo auxiliar "in_pdini_grup2" em relação ao campo auxiliar "ead_final_bruta_grup2": SUM(in_pdini_grup2 * ead_final_bruta_grup2) / SUM(ead_final_bruta_grup2) | S4: A agrupação é feita segundo o campo "Counterparty Identifier" deste mesmo documento
Q5: contra1
Q6: ead_final_bruta
O7: cd_captools.ct014_rwa_irb | P7: ‣ ref_date = data do report | Q7: in_pdini
O8: cd_alm.al029_cnt_core_m | P8: ‣ ref_date = data do report | Q8: cempresa
Q9: cbalcao
Q10: cnumecta
Q11: zdeposit
A12: V_8 | B12: Risk parameters | C12: Current Internal Credit Rating/Scoring | D12: Numeric / Alphanumeric | E12: Internal credit rating/scoring issued to the Counterparty. | F12: Notação de risco interna emitida para a Contraparte. | H12: ENTITY-INTRNL_RTNG | I12: Internal rating at reference date | J12: Internal rating at the reference date according to Regulation (EU) No 575/2013. Please also add in sheet "Code List" the list of values used, i.e. bank-internal masterscale. | L12: ENTITY-INTRNL_RTNG Segundo o documento "Especificação - BCE Loan Tape - Internal Ratings_v1.4", é referido: "Nível do cliente: deverá ser consultada a tabela CD_CAPTOOLS.JM_CAL_IN_CL;" ou seja, vem do input Capital. | M12: Concluido | O12: cd_loan_tapes_bce.lt003_entity | P12: ‣ ref_date = data do report | Q12: intrnl_rtng | R12: ‣ Para cada Counterparty Identifier é obtido o: MAX(intrnl_rtng) | S12: A agrupação é feita segundo o campo "Counterparty Identifier" deste mesmo documento
A13: V_10 | B13: Risk parameters | C13: IFRS 9 Probability of default/impairment | D13: Numeric. Basis points | E13: The probability of default/impairment is calculated in accordance with the requirements specific to PD estimation as laid down in the accounting framework. If PDs are produced at the instrument level only, the counterparty’s PD is to be reported as the exposure-weighted average PD across the PDs of all instruments of the counterparty. If, for a given counterparty, PDs are estimated for both the counterparty and (some of) the products of the counterparty, it is the counterparty’s PD which is to be reported. | F13: A probabilidade de incumprimento/imparidade é calculada de acordo com os requisitos específicos para a estimativa de PD, tal como estabelecido no quadro contabilístico. Se os PD forem produzidos apenas ao nível do instrumento, o PD da contraparte deve ser reportado como o PD médio ponderado pelas posições em risco nos PD de todos os instrumentos da contraparte. Se, para uma dada contraparte, as PD forem estimadas tanto para a contraparte como para (alguns) dos produtos da contraparte, é o PD da contraparte que deve ser comunicado. | H13: ENTITY-PD_IFRS9_12M_RD | I13: 12-month PD at reporting date according to IFRS 9 | J13: 12-month PD at reference date which is used by the bank for computation of stage 1 ECL or for SICR assessment if bank use 12 month proxy for staging. If the PD is calculated on instruments level please provide an EAD weighted average. | L13: No documento de "Feedback Statement in response to the consultation on the SRB valuation data set" tem a seguinte nota sobre este campo: "‘Data Point V_10’, entitled ‘IFRS 9 Probability of default’, refers to PDs used for accounting purposes, being a 12-month PD for stage 1 exposures and a lifetime PD for stage 2 and 3 exposures as per the accounting framework." Email David Texugo (01/04/2024 17:23) Para algumas das operações em Stage 1 deve-se considerar PD lifetime também. Para operações em Stage 1 para as quais não é possível avaliar o SICR via variação de PD/Rating por PD/Rating origem inválido, o cálculo de provisões é lifetime, conforme pode ser verificado no campo loss_type. Com a exceção destas casuísticas, deve-se seguir a lógica que indicas. Adicionalmente Stage 3 deveria ter sempre PD 100%. Aparentemente, faz sentido criar um novo campo ("PD misto" ) na LT002_INSTRUMENT dado que se solicita um "misto" entre a PD 12m e a PD lifetime, assim: -Se stage 1 selecionar PD12M_IFRS9 da tabela BU_IFRS9.IFRS9_OUT_EXPECTED_LOSS_REPORTING (confirmar que neste campo já está incluída a lógica de David Texugo) -Se stage 2 selecionar PD_LT_IFRS9 da tabela BU_IFRS9.IFRS9_OUT_EXPECTED_LOSS_REPORTING -Se stage 3 forçar 1 Sugere-se criar o campo na LT002_INSTRUMENT e não na LT003_ENTITY porque após consultar a a LT003_ENTITY verificámos que existia o campo PD_IFRS9_12M_RD para o qual é usada a LT005_INSTR_ENT para Identificar todos os contratos onde o cliente é o 1º Titular, de seguida para cada cliente aplica-se uma média ponderada da PD em relação ao EAD (porque cada cliente pode ter vários contratos). Assim sugerimos replicar esta lógica para o novo campo "PD misto" adicionado na LT002_INSTRUMENT de forma a poder ser criado também um novo campo "PD misto" na LT003_ENTITY. Nota: Atenção que o campo PD_IFRS9_12M_RD apenas está a ser calculado para os Primeiros Titulares (provavelmente porque em IFRS9 também só calculam para os Primeiros Titulares) | M13: Por iniciar | O13: cd_captools.ct013_rwa_princ | P13: ‣ ref_date = data do report ‣ flag_cons_cap = 1 ‣ exercicio = 'REAL' | Q13: s1emp | R13: ‣ Este campo tem de ser calculado por fases: ‣ 1º - Calculamos o campo auxiliar "ead_final_liquida_grup": ‣ Para cada combinação dos campos "cempresa", "cbalcao", "cnumecta", "zdeposit" iremos SOMAR as: Médias do campo "ead_final_liquida" para cada par dos campos "s1emp", "contra1"; ‣ 2º - Calculamos o campo auxiliar "final_stage_grup": ‣ Para cada combinação dos campos "cempresa", "cbalcao", "cnumecta", "zdeposit" iremos calcular "final_stage" máximo: MAX(final_stage); ‣ 3º - Calculamos o campo auxiliar "pd12m_ifrs9_grup": ‣ Para cada combinação dos campos "cempresa", "cbalcao", "cnumecta", "zdeposit" iremos calcular a média ponderada do campo "pd12m_ifrs9" ao campo "ead": SUM(ead * pd12m_ifrs9) / SUM(ead); ‣ 4º - Calculamos o campo auxiliar "pd_lt_ifrs9_grup": ‣ Para cada combinação dos campos "cempresa", "cbalcao", "cnumecta", "zdeposit" iremos calcular a média ponderada do campo "pd_lt_ifrs9" ao campo "ead": SUM(pd_lt_ifrs9 * ead) / SUM(ead); ‣ 5º - Calculamos o campo auxiliar "pd_ifrs9_grup": ‣ Se final_stage_grup = '1': pd12m_ifrs9_grup; ‣ Caso contrário: pd_lt_ifrs9_grup; ‣ Finalmente para cada Counterparty Identifier calculamos a média ponderada do campo auxiliar "pd_ifrs9_grup" ao campo auxiliar "ead_final_liquida_grup": SUM(pd_ifrs9_grup * ead_final_liquida_grup) / SUM(ead_final_liquida_grup) | S13: A agrupação final é feita segundo o campo "Counterparty Identifier" deste mesmo documento
Q14: contra1
Q15: ead_final_liquida
O16: cd_alm.al029_cnt_core_m | P16: ‣ ref_date = data do report | Q16: cempresa
Q17: cbalcao
Q18: cnumecta
Q19: zdeposit
O20: ifrs9_out_expected_loss_8_7 | P20: ‣ Apenas são trazidos os "contract_id"s que têm "exec_id_part" correspondente na tabela cd_captools.imcatf046_flag_fecho à data ("cmes") do report | Q20: pd12m_ifrs9
Q21: pd_lt_ifrs9
Q22: ead
O23: ifrs9_out_staging_8_7 | P23: ‣ Apenas são trazidos os "contract_id"s que têm "exec_id_part" correspondente na tabela cd_captools.imcatf046_flag_fecho à data ("cmes") do report | Q23: final_stage
A24: V_11 | B24: Risk parameters | C24: Probability of default (others) | D24: Numeric. Basis points | E24: Applicable only to institutions neither using models for estimating IFRS 9 impairments nor CRR IRB models. These institutions should maintain records of probabilities of default or scores provided by scoring/rating models. In the case of PDs produced at the instrument level only, the counterparty’s PD is to be reported as the exposure-weighted average PD across the PDs of all instruments of the counterparty. If, for a given counterparty, PDs are estimated for both the counterparty and (some of) the products of the counterparty, it is the counterparty’s PDs which is to be reported. | F24: Aplicável apenas às instituições que não utilizam modelos de estimativa Imparidades IFRS 9 nem modelos de IRB CRR. Estas instituições devem: manter registos das probabilidades de incumprimento ou das pontuações fornecidas por modelos de pontuação/classificação.No caso de PD produzidos apenas ao nível do instrumento, o PD da contraparte deve ser reportado como o PD médio ponderado pela posição em risco entre os PD de todos os instrumentos de a contraparte. Se, para uma dada contraparte, as PD forem estimadas tanto para a contraparte como para (alguns dos) produtos da contraparte, são as PD da contraparte que devem ser comunicadas. | H24: - | I24: - | J24: - | L24: Este campo é Not Applicable, reportar: 11111111111 | M24: Concluido | O24: N/A | P24: N/A | Q24: N/A | R24: N/A | S24: N/A
A25: V_184 | B25: Counterparty characteristics | C25: Counterparty role | D25: String | E25: The roles that counterparties assume in relation to an instrument recorded in the instrument dataset are recorded in the counterparty-instrument dataset. Opções: ‣ Creditor ‣ Debtor ‣ Servicer ‣ Originator | F25: As funções que as contrapartes assumem em relação a um instrumento registados no conjunto de dados do instrumento são registados no conjunto de dados contraparte-instrumento. Opções: ‣ Creditor ‣ Debtor ‣ Servicer ‣ Originator | H25: Not applicable: To be reported as "N/A". This information will be availabe in "02_04_nat_instr_count" table | I25: - | J25: - | L25: Not applicable: To be reported as "N/A". This information will be availabe in "02_04_nat_instr_count" table | M25: Concluido | O25: Não foi implementado | P25: Não foi implementado | Q25: Não foi implementado | R25: Não foi implementado | S25: Não foi implementado
A26: V_185 | B26: Financial information | C26: Default status of the counterparty | D26: String | E26: Identification of the default status of the counterparty. Categories describing the motives for which the counterparty can be in default in accordance with Article 178 of Regulation (EU) No 575/2013. Opções: ‣ Not in default ‣ Default because unlikely to pay ‣ Default because more than 90/180 days past due ‣ Default because both unlikely to pay and more than 90/180 days past due | F26: Identificação da situação de incumprimento da contraparte. Categorias que descrevem os motivos pelos quais a contraparte pode estar em situação de incumprimento, em conformidade com o artigo 178.o do Regulamento (UE) n.o 575/2013. Opções: ‣ Not in default ‣ Default because unlikely to pay ‣ Default because more than 90/180 days past due ‣ Default because both unlikely to pay and more than 90/180 days past due | H26: ENTITY-DFLT_STTS | I26: Default status of the entity | J26: Identification of the default status of the counterparty. Categories describing the motives for which the counterparty can be in default in accordance with Article 178 of Regulation (EU) No 575/2013. For retail only: If default classification performed on instrument level then Entity is classified as defaulted when at least one instrument is classified as defaulted. For corporate, SME, CRE and LF: if default classification performed on instrument level then entity level is "not applicable". | L26: ENTITY-DFLT_STTS | M26: Mapeamento com LT fechado, mas parametrização pendente | O26: Tabela de parametrização: codemapping | P26: ‣ dd_field_id = "35" | Q26: dd_code | R26: ‣ Este campo tem de ser calculado por fases: ‣ 1º - Para cada Counterparty Identifier calculamos o máximo do campo "dflt_stts_instrmnt": MAX(dflt_stts_instrmnt); ‣ 2º - Tradução do MAX(dflt_stts_instrmnt) através de uma ligação com o campo "dd_code" para obter o campo: dd_value. | S26: A agrupação é feita segundo o campo "Counterparty Identifier" deste mesmo documento
Q27: dd_value
O28: cd_loan_tapes_bce.lt002_instrument | P28: ‣ ref_date = data do report | Q28: dflt_stts_instrmnt
A29: V_186 | B29: Financial information | C29: Date of the default status of the counterparty | D29: DD/MM/YYYY | E29: The date on which the default status, as reported in the data attribute “Default status of the counterparty”, is considered to have arisen. | F29: A data em que se considera que surgiu o estatuto de incumprimento, tal como indicado no atributo de dados "Estado de incumprimento da contraparte". | H29: ENTITY-DT_DFLT_STTS | I29: Date of default status | J29: The date on which the default status, as reported in the data attribute “Default status”, is considered to have arisen. If "Not in default" since inception then this attribute is to be reported equally to the inception date. If default classification performed on instrument level then Entity is classified as defaulted when at least one instrument is classified as defaulted. If more than one Instrument is classified as defaulted then the earliest date has to be provided. The definition of default is aligned with Art 178 of Regulation (EU) No 575/2013. | L29: ENTITY-DT_DFLT_STTS | M29: Concluido | O29: cd_loan_tapes_bce.lt002_instrument | P29: ‣ ref_date = data do report | Q29: dt_dflt_stts_instrmnt | R29: ‣ Para cada Counterparty Identifier calculamos o minimo do campo "dt_dflt_stts_instrmnt": MIN(dt_dflt_stts_instrmnt) | S29: A agrupação é feita segundo o campo "Counterparty Identifier" deste mesmo documento

Sheet NATURALP_PROTECTIONS
A1: SRB Protection received Data Set for exposures to natural persons
A2: ID | B2: Categoria | C2: Coluna | D2: Tipo de dados | E2: Descrição | F2: Descrição | H2: Mapeamentos Corporação (LT) | I2: Descrição (LT) | J2: Additional Guidance (LT) | L2: Comentários | M2: Estado especificação | O2: Fontes de Informação | P2: Filtros | Q2: Campo | R2: Regras de Preenchimento | S2: Agrupações
A3: V_12 | B3: Identification information | C3: Protection identifier | D3: Alphanumeric | E3: An identifier applied to uniquely identify each protection/collateral used to secure the instrument. | F3: Um identificador aplicado para identificar exclusivamente cada proteção/garantia usada para proteger o instrumento. | H3: PROTECTION-PRTCTN_ID | I3: Protection ID | J3: An identifier applied by the reporting agent to uniquely identify each protection used to secure the instrument. Each protection must have one protection identifier. This value will not change over time and cannot be used as the protection identifier for any other protection. | L3: PROTECTION-PRTCTN_ID | M3: Concluido | O3: cd_captools.fr003_colaterais | P3: ‣ ref_date = data do report | Q3: cempresa | R3: ‣ Concatenação dos campos mencionados anteriormente: cempresa + "_" + cbalcao_caucao + "_" + cnumecta_caucao + "_" + zcaucao
Q4: cbalcao_caucao
Q5: cnumecta_caucao
Q6: zcaucao
A7: V_219 | B7: Identification information | C7: Protection provider identifier | D7: Alphanumeric | E7: The protection provider identifier is the counterparty identifier of the counterparty that grants protection against a contractually agreed negative credit event and that is obliged to make payments to the creditor if the debtor fails to meet the obligation to make repayments arising under the instrument secured by the protection item. | F7: O identificador do prestador de proteção é o identificador da contraparte que concede proteção contra um acontecimento de crédito negativo contratualmente acordado e que é obrigada a efetuar pagamentos ao credor se o devedor não cumprir a obrigação de efetuar reembolsos decorrentes do instrumento garantido pelo elemento de proteção. | H7: PROTECTION-PRTCTN_PRVDR_ID | I7: Protection Provider ID (Guarantor) | J7: Counterparty identifier for the protection provider. If the protection provider is not a legal entity, the protection provider identifier is not required to be reported. | L7: PROTECTION-PRTCTN_PRVDR_ID | M7: Concluido | O7: cd_captools.fr003_colaterais | P7: ‣ ref_date = data do report | Q7: garante | R7: ‣ Direto
A8: V_1 | B8: Identification information | C8: Instrument Identifier | D8: Alphanumeric | E8: An identifier applied to uniquely identify each instrument. Each instrument must have one instrument identifier. | F8: Um identificador aplicado para identificar exclusivamente cada instrumento. Cada instrumento deve ter um identificador de instrumento. | H8: Not applicable: To be reported as "N/A". This information will be availabe in "02_05_nat_instr_prot" table | I8: - | J8: - | L8: Not applicable: To be reported as "N/A". This information will be availabe in "02_05_nat_instr_prot" table | M8: Concluido | O8: cd_alm.kt_chaves_alm_m | P8: ‣ ref_date = data do report | Q8: cempresa | R8: ‣ Concatenação dos campos mencionados anteriormente: cempresa + "_" + cbalcao + "_" + cnumecta + "_" + zdeposit
Q9: cbalcao
Q10: cnumecta
Q11: zdeposit
A12: V_187 | B12: Identification information | C12: Type of collateral | D12: String | E12: The AnaCredit item “type of protection” (Section 9.4.3. of the AnaCredit Reporting Manual Part II – Datasets and data attributes) provides a breakdown of collaterals eligible in accordance with the CRR. The proposed breakdown adds several categories. Options: ‣ Gold ‣ Currency and deposits ‣ Securities ‣ Loans ‣ Equity and investment fund shares or units ‣ Credit derivatives ‣ Financial guarantees other than credit derivatives ‣ Trade receivables ‣ Life insurance policies pledged ‣ Residential real estate collateral ‣ Offices and commercial premises ‣ Commercial real estate collateral ‣ Other physical collateral ‣ Other protection ‣ Hotels & entertainment ‣ Infrastructure projects ‣ Factories – Warehouses ‣ Equipment & machinery ‣ Automotive ‣ Aircraft ‣ Shipping | F12: A rubrica "tipo de proteção" da AnaCredit (Secção 9.4.3 do Manual de Comunicação de Informação AnaCredit Parte II – Conjuntos de dados e atributos de dados) fornece uma discriminação das garantias elegíveis de acordo com o RRFP (CRR). A repartição proposta acrescenta várias categorias. Opções: ‣ Gold ‣ Currency and deposits ‣ Securities ‣ Loans ‣ Equity and investment fund shares or units ‣ Credit derivatives ‣ Financial guarantees other than credit derivatives ‣ Trade receivables ‣ Life insurance policies pledged ‣ Residential real estate collateral ‣ Offices and commercial premises ‣ Commercial real estate collateral ‣ Other physical collateral ‣ Other protection ‣ Hotels & entertainment ‣ Infrastructure projects ‣ Factories – Warehouses ‣ Equipment & machinery ‣ Automotive ‣ Aircraft ‣ Shipping | H12: PROTECTION-TYP_PRTCTN | I12: Protection type | J12: Type of protection received, irrespective of its eligibility for credit risk mitigation. | L12: PROTECTION-TYP_PRTCTN | M12: Mapeamento com LT fechado, mas parametrização pendente | O12: Tabela de parametrização: codemapping | P12: ‣ dd_field_id = "187" | Q12: dd_code | R12: ‣ Tradução do campo "typ_prtctn" através de uma ligação com o campo "dd_code" para obter o campo: dd_value
Q13: dd_value
O14: cd_loan_tapes_bce.lt004_protection | P14: ‣ ref_date = data do report | Q14: typ_prtctn
A15: V_14 | B15: Size collateral | C15: Building Area (M2) | D15: Numeric | E15: Building area of the building in square meters. Only applicable to Residential real estate collateral, Offices and commercial premises, Commercial real estate collateral, Hotels & entertainment, Factories – warehouses. | F15: Área de construção do edifício em metros quadrados. Aplicável apenas a garantias imobiliárias residenciais, escritórios e estabelecimentos comerciais, garantias imobiliárias comerciais, hotéis e entretenimento, fábricas – armazéns. | H15: - | I15: - | J15: - | L15: ‣ Não encontramos no LT -> Confirmar com Nádia Ahmad e Dora Roxo; ‣ Segundo Luís Capitão-Mor, estes campos deverão vir do MUG (Modelo Único de Garantias). ‣ Reunião Alexandre Dionísio Esteves (08-04-2024): 1) Estes campos ainda não existem no MUG. 2) Esta informação existe na GPT32, embora nessa tabela estes campos não sejam de preenchimento obrigatório, como tal, existem GAPs de informação. 3) Foi-nos também comentado que o universo completo de imóveis está na tabela gpt18 os quais não estão 100% mapeados na gpt32. 4) Alexandre irá analisar em detalhe e irá marcar reunião com Luís Capitão-Mor para a semana de 15/04/2024 | M15: Novo campo, mapeamento datalake pendente, sem necessidade de criar parametrização | O15: Não está implementado | P15: Não está implementado | Q15: Não está implementado | R15: Não está implementado | S15: Não está implementado
A16: V_15 | B16: Size collateral | C16: Land Area (M2) | D16: Numeric | E16: Land area of the property in square meters. | F16: Área do terreno da propriedade em metros quadrados. | H16: - | I16: - | J16: - | L16: ‣ Não encontramos no LT -> Confirmar com Nádia Ahmad e Dora Roxo; ‣ Segundo Luís Capitão-Mor, estes campos deverão vir do MUG (Modelo Único de Garantias). ‣ Reunião Alexandre Dionísio Esteves (08-04-2024): 1) Estes campos ainda não existem no MUG. 2) Esta informação existe na GPT32, embora nessa tabela estes campos não sejam de preenchimento obrigatório, como tal, existem GAPs de informação. 3) Foi-nos também comentado que o universo completo de imóveis está na tabela gpt18 os quais não estão 100% mapeados na gpt32. 4) Alexandre irá analisar em detalhe e irá marcar reunião com Luís Capitão-Mor para a semana de 15/04/2024 | M16: Novo campo, mapeamento datalake pendente, sem necessidade de criar parametrização | O16: Não está implementado | P16: Não está implementado | Q16: Não está implementado | R16: Não está implementado | S16: Não está implementado
A17: V_16 | B17: Location | C17: Property postcode | D17: Numeric | E17: Postcode where the property is located. Only applicable to Residential real estate collateral, Offices and commercial premises, Commercial real estate collateral, Hotels & entertainment, Factories – Warehouses. | F17: Código postal onde o imóvel está localizado. Aplicável apenas a Garantias imobiliárias residenciais, Escritórios e espaços comerciais, Garantias imobiliárias comerciais, Hotéis e entretenimento, Fábricas – Armazéns. | H17: PROTECTION-RL_ESTT_PST_CD | I17: Post code / ZIP | J17: Post code / ZIP. | L17: PROTECTION-RL_ESTT_PST_CD | M17: Concluido | O17: cd_loan_tapes_bce.lt004_protection | P17: ‣ ref_date = data do report | Q17: rl_estt_pst_cd | R17: ‣ Direto
A18: V_17 | B18: Lien | C18: Lien position | D18: Numeric | E18: The highest ranking position(s) in relation to the collateral held by the counterparty to secure the facility. In case the facility has several liens on one collateral, the highest claim is reported in this data field. | F18: A(s) posição(ões) mais elevada(s) em relação às garantias detidas pela contraparte para garantir a facilidade. No caso de a facilidade ter vários ónus sobre uma garantia, o crédito mais elevado é comunicado neste campo de dados. | H18: - | I18: - | J18: - | L18: ‣ Não encontramos no LT -> Confirmar com Nádia Ahmad e Dora Roxo; [Reunião 2024-04-08] Segundo Luís Capitão-Mor, o Banco só aceita primeiras hipotecas, como tal, este campo deverá ser sempre preenchido com '1'. | M18: Novo campo, mapeamento datalake fechado, sem necessidade de criar parametrização | O18: cd_loan_tapes_bce.lt006_instr_prot | P18: ‣ ref_date = data do report | Q18: thrd_prty_prrty_clms | R18: ‣ Direto
A19: V_188 | B19: Valuation | C19: Date of protection value | D19: DD/MM/YYYY | E19: The date on which the latest appraisal or valuation of the protection was carried out prior to the reporting reference date, i.e. the date on which the amount reported in the attribute “protection value” of the value type reported in the attribute “type of protection value” was established under the valuation method reported in the attribute protection valuation approach. | F19: A data em que a última avaliação ou avaliação da proteção foi realizada antes da data de referência do relatório, ou seja, a data em que a quantidade relatada no atributo "valor de proteção" do tipo de valor relatado no atributo "tipo de proteção valor" foi estabelecido de acordo com o método de avaliação relatado na abordagem de avaliação de proteção de atributos. | H19: PROTECTION-DT_PRTCTN_VL | I19: Date of protection value | J19: The date on which the latest appraisal or valuation of the protection was carried out prior to the reporting reference date. | L19: PROTECTION-DT_PRTCTN_VL | M19: Concluido | O19: cd_captools.fr003_colaterais | P19: ‣ ref_date = data do report | Q19: dultmod | R19: ‣ Direto
A20: V_220 | B20: Valuation | C20: Protection value | D20: Numeric (euro) | E20: The amount of the protection value is the monetary value of the protection that was established at the latest valuation date | F20: O montante do valor de proteção é o valor monetário da proteção que foi estabelecido na última data de avaliação | H20: PROTECTION-PRTCTN_VL | I20: Appraised market value | J20: The amount of the protection value as established for the relevant “Type of protection value” following the valuation approach. Market value from the appraisal without any haircut, in case a haircut is applied by the bank this should be in field HRCT_MV. In case of Guarantees, guaranteed amount. In case of Financial Assets, Market value of the asset. | L20: PROTECTION-PRTCTN_VL | M20: Concluido | O20: cd_captools.fr003_colaterais | P20: ‣ ref_date = data do report | Q20: mavaliaa | R20: ‣ Direto
A21: V_189 | B21: Protection characteristics | C21: Maturity date of the protection | D21: DD/MM/YYYY | E21: The contractual maturity date of the protection, which is the earliest date at which the protection may terminate or be terminated, taking into account any agreements amending initial contracts. | F21: A data de vencimento contratual da proteção, que é a data mais próxima em que a proteção pode cessar ou cessou, tendo em conta quaisquer acordos que alterem contratos iniciais. | H21: PROTECTION-DT_MTRTY_PRTCTN | I21: Maturity date of the protection | J21: The contractual maturity date of the protection, which is the earliest date at which the protection may terminate or be terminated, taking into account any agreements amending initial contracts. | L21: PROTECTION-DT_MTRTY_PRTCTN | M21: Concluido | O21: cd_captools.fr003_colaterais | P21: ‣ ref_date = data do report | Q21: dvencime | R21: ‣ Direto
A22: V_190 | B22: Valuation | C22: Original protection value | D22: Numeric (euro) | E22: The monetary value of the protection item that was established at the date when the protection item was originally received as a credit protection. | F22: O valor monetário do item de proteção que foi estabelecido na data em que o item de proteção foi originalmente recebido como proteção de crédito. | H22: PROTECTION-ORGNL_PRTCTN_VL | I22: Original protection value (at inception) | J22: The original protection value is the monetary value of the protection item that was established at the date when the protection item was originally received as a credit protection. | L22: PROTECTION-ORGNL_PRTCTN_VL | M22: Concluido | O22: cd_captools.fr003_colaterais | P22: ‣ ref_date = data do report | Q22: mavaliai | R22: ‣ Direto
A23: V_191 | B23: Valuation | C23: Date of original protection value | D23: DD/MM/YYYY | E23: The date on which the latest appraisal or valuation of the protection was carried out prior to its initial receipt as credit protection. | F23: O tipo do valor relatado do item de proteção conforme relatado no atributo de dados. Opção: ‣ Notional amount ‣ Fair value ‣ Market value ‣ Long-term sustainable value ‣ Other protection value | H23: PROTECTION-DT_ORGNL_PRTCTN_VL | I23: Date of original protection value | J23: The date of original protection value is the date on which the latest appraisal or valuation of the protection was carried out prior to its initial receipt as credit protection. | L23: PROTECTION-DT_ORGNL_PRTCTN_VL As regras de preenchimento deste campo encontram-se no documento de especificação (existiam colunas a hide no documento). Avaliar as regras de preenchimento deste campo, de forma a perceber se se está a recuperar a data mais antiga de uma garantia, ou a mais antiga que continua viva, ou a mais recente anterior à data de inicio do contrato onde o bem foi dado como garantia (pensamos ser este o pedido). | M23: Concluido | O23: cd_captools.fr003_colaterais | P23: ‣ ref_date = data do report | Q23: dabertur | R23: ‣ Direto
A24: V_192 | B24: Valuation | C24: Type of protection value | D24: String | E24: The type of the reported value of the protection item as reported in the data attribute “protection value”. Options: ‣ Notional amount ‣ Fair value ‣ Market value ‣ Long-term sustainable value ‣ Other protection value | F24: O tipo do valor relatado do item de proteção conforme relatado no atributo de dados. Opções: ‣ Notional amount ‣ Fair value ‣ Market value ‣ Long-term sustainable value ‣ Other protection value | H24: PROTECTION-TYP_PRTCTN_VL | I24: Type of protection value | J24: Identification of the type of value provided in the data attribute “Protection value”. | L24: PROTECTION-TYP_PRTCTN_VL | M24: Mapeamento com LT fechado, mas parametrização pendente | R24: ‣ Forçado a "Fair value"
A25: V_221 | B25: Valuation | C25: Protection valuation approach | D25: String | E25: Method used to determine the protection value. Options: ‣ Mark-to-to-market valuation ‣ Counterparty estimation ‣ Creditor valuation ‣ Third party valuation | F25: Método utilizado para determinar o valor da proteção. Opções: ‣ Mark-to-to-market valuation ‣ Counterparty estimation ‣ Creditor valuation ‣ Third party valuation | H25: PROTECTION-PRTCTN_VLTN_APPRCH | I25: Protection valuation approach | J25: Type of protection valuation; method used to determine the protection value. | L25: PROTECTION-PRTCTN_VLTN_APPRCH | M25: Mapeamento com LT fechado, mas parametrização pendente | R25: ‣ Forçado a "Mark-to-to-market valuation"
A26: V_193 | B26: Valuation | C26: Protection allocated value | D26: Numeric (euro) | E26: The maximum amount of the protection value that can be considered as credit protection for the instrument. The amount of the existing third parties or observed agent priority claims against the protection must be excluded in the protection allocated value. | F26: O montante máximo do valor de proteção que pode ser considerado como proteção de crédito para o instrumento. A quantidade das reivindicações de prioridade de terceiros existentes ou agentes observados contra a proteção devem ser excluídas no valor atribuído à proteção. | H26: Not applicable: To be reported as "11111111111". This information will be availabe in "02_05_nat_instr_prot" table | I26: - | J26: - | L26: PROTECTION-PRTCTN_VL Como o banco só aceita 1ªs hipotecas este campo é exatamente igual ao PROTECTION-PRTCTN_VL, e como tal da perspetiva de Luis Capitão-Mor deve ser reportado aqui. Desta forma terá de se confirmar com a corporação se podemos reportar o referido anteriormente, se não continua a vir "11111111111" (Not applicable). | M26: Concluido | O26: cd_loan_tapes_bce.lt006_instr_prot | P26: ‣ ref_date = data do report | Q26: prtctn_allctd_vl | R26: ‣ Direto
A27: V_194 | B27: Lien | C27: Third-party priority claims against the protection | D27: Numeric (euro) | E27: The maximum amount of any existing higher ranked liens with respect to third parties other than the observed agent against the protection. | F27: O montante máximo de quaisquer ónus de grau superior existentes em relação a terceiros que não o agente observado contra o proteção. | H27: Not applicable: To be reported as "11111111111". This information will be availabe in "02_05_nat_instr_prot" table | I27: - | J27: - | L27: Not applicable: To be reported as "11111111111". This information will be availabe in "02_05_nat_instr_prot" table Como o banco só aceita 1ªs hipotecas, este campo deverá ser reportado com 0. Desta forma terá de se confirmar com a corporação se podemos reportar o referido anteriormente, se não continua a vir "11111111111" (Not applicable). | M27: Concluido | O27: cd_loan_tapes_bce.lt006_instr_prot | P27: ‣ ref_date = data do report | Q27: thrd_prty_prrty_clms | R27: ‣ Direto

Sheet NATURALP_INSTRUMENT_COUNTERPART
A1: SRB Instrument/Counterparty mapping Data Set for exposures to natural persons
A2: ID | B2: Categoria | C2: Coluna | D2: Tipo de dados | E2: Descrição | F2: Descrição | H2: Mapeamentos Corporação (LT) | I2: Descrição (LT) | J2: Additional Guidance (LT) | L2: Comentários | M2: Estado especificação | O2: Fontes de Informação | P2: Filtros | Q2: Campo | R2: Regras de Preenchimento | S2: Agrupações | T2: Comentários reuniões
A3: V_1 | B3: Identification information | C3: Instrument Identifier | D3: Alphanumeric | E3: An identifier applied to uniquely identify each instrument. Each instrument must have one instrument identifier | F3: Um identificador aplicado para identificar exclusivamente cada instrumento. Cada instrumento deve ter um identificador de instrumento. | H3: INSTR_ENTITY-INSTRMNT_ID | I3: Instrument ID | J3: An identifier applied by the reporting agent to uniquely identify each instrument under a single contract. Each instrument must have one instrument identifier. This value will not change over time and cannot be used as the instrument identifier for any other instrument under the same contract. Supervised Insitutions are asked to furnish the INSTRMNT_ID with the exact same value as it is reported to AnaCredit (or any similar central credit register). If this is not available, the value shall be reported as it is internally used. If an instrument is not reported to AnaCredit but requested for the purposes of the on-site inspection please provide the bank-internally used value. Foreign Key from INSTRUMENT table. | L3: INSTR_ENTITY-INSTRMNT_ID | M3: Concluido | O3: cd_alm.al029_cnt_core_m | P3: ‣ ref_date = data do report | Q3: cempresa | R3: ‣ Concatenação dos campos mencionados anteriormente: cempresa + cbalcao + cnumecta + zdeposit | T3: Ver se não devemos ir antes às tabelas de garantias (gts)
Q4: cbalcao
Q5: cnumecta
Q6: zdeposit
A7: V_2 | B7: Identification information | C7: Counterparty Identifier | D7: Alphanumeric | E7: Identifier applied to uniquely identify each counterparty. | F7: Identificador aplicado para identificar exclusivamente cada contraparte. | H7: INSTR_ENTITY-ENTTY_ID | I7: Entity ID | J7: An identifier applied by the reporting agent to uniquely identify each counterparty. Each counterparty has a unique and exclusive counterparty identifier. This means that this value will not change over time and can never be used as the counterparty identifier for any other counterparty. Foreign key from ENTITY table. | L7: INSTR_ENTITY-ENTTY_ID | M7: Concluido | O7: cd_alm.al029_cnt_core_m | P7: ‣ ref_date = data do report | Q7: zcliente | R7: ‣ Direto
A8: V_167 | B8: Financial information | C8: Joint liabilities amount | D8: Numeric (euro) | E8: Outstanding nominal amount for which each debtor is liable in relation to a single instrument where there are two or more debtors. | F8: Montante nominal pendente pelo qual cada devedor é responsável em relação a um único instrumento, caso existam dois ou mais devedores. | H8: INSTR_ENTITY-JNT_LBLTY_AMNT | I8: Joint-liability amount | J8: Outstanding nominal amount for which each debtor is liable in relation to a single instrument where there are two or more debtors. In the case of instruments where there is only one debtor, please report "not applicable" using the respective fall-back parameters. | L8: INSTR_ENTITY-JNT_LBLTY_AMNT | M8: Concluido | O8: cd_loan_tapes_bce.lt005_instr_ent | P8: ‣ ref_date = data do report | Q8: jnt_lblty_amnt | R8: ‣ Direto
A9: V_184 | B9: Counterparty characteristics | C9: Counterparty role | D9: String | E9: The roles that counterparties assume in relation to an instrument recorded in the instrument dataset are recorded in the counterparty-instrument dataset. Opções: ‣ Creditor ‣ Debtor ‣ Servicer ‣ Originator | F9: As funções que as contrapartes assumem em relação a um instrumento registados no conjunto de dados do instrumento são registados no conjunto de dados contraparte-instrumento. Opções: ‣ Creditor ‣ Debtor ‣ Servicer ‣ Originator | H9: - | I9: - | J9: - | L9: Na Parametrização atual do LT só são selecionados Titulares. Como tal, aqui no Valuation se fizermos a mesma parametrização, e dado que o report é sobre o Ativo, então o valor é sempre Debtor. Contudo, é necessário validar melhor porque sera um campo novo e que noutros casos que nao o Valuation, por exemplo o Bail In sobre passivom então este campo deveria ser Creditor. Ou não se cria o campo na tabela e fica apenas na exportação? (O) | M9: Novo campo, mapeamento datalake pendente, com necessidade de criar parametrização | O9: Não foi implementado | P9: Não foi implementado | Q9: Não foi implementado | R9: Não foi implementado | S9: Não foi implementado

Sheet NATURALP_INSTRUMENT_PROTECTION
A1: SRB Instrument/Counterparty mapping Data Set for exposures to natural persons
A2: ID | B2: Categoria | C2: Coluna | D2: Tipo de dados | E2: Descrição | F2: Descrição | H2: Mapeamentos Corporação (LT) | I2: Descrição (LT) | J2: Additional Guidance (LT) | L2: Comentários | M2: Estado especificação | O2: Fontes de Informação | P2: Filtros | Q2: Campo | R2: Regras de Preenchimento | S2: Agrupações | T2: Comentários reuniões
A3: V_1 | B3: Identification information | C3: Instrument Identifier | D3: Alphanumeric | E3: An identifier applied to uniquely identify each instrument. Each instrument must have one instrument identifier | F3: Um identificador aplicado para identificar exclusivamente cada instrumento. Cada instrumento deve ter um identificador de instrumento. | H3: INSTR_PROTECTION-INSTRMNT_ID | I3: Instrument ID | J3: An identifier applied by the reporting agent to uniquely identify each instrument under a single contract. Each instrument must have one instrument identifier. This value will not change over time and cannot be used as the instrument identifier for any other instrument under the same contract. Supervised Insitutions are asked to furnish the INSTRMNT_ID with the exact same value as it is reported to AnaCredit (or any similar central credit register). If this is not available, the value shall be reported as it is internally used. If an instrument is not reported to AnaCredit but requested for the purposes of the on-site inspection please provide the bank-internally used value. Foreign Key from INSTRUMENT table. | L3: INSTR_PROTECTION-INSTRMNT_ID | M3: Concluido | O3: cd_alm.al029_cnt_core_m | P3: ‣ ref_date = data do report | Q3: cempresa | R3: ‣ Concatenação dos campos mencionados anteriormente: cempresa + cbalcao + cnumecta + zdeposit | T3: Ver se não devemos ir antes às tabelas de garantias (gts)
Q4: cbalcao
Q5: cnumecta
Q6: zdeposit
A7: V_12 | B7: Identification information | C7: Protection identifier | D7: Alphanumeric | E7: An identifier applied to uniquely identify each protection/collateral used to secure the instrument. | F7: Um identificador aplicado para identificar exclusivamente cada proteção/garantia usada para proteger o instrumento. | H7: INSTR_PROTECTION-PRTCTN_ID | I7: Protection ID | J7: An identifier applied by the reporting agent to uniquely identify each protection used to secure the instrument. Each protection must have one protection identifier. This value will not change over time and cannot be used as the protection identifier for any other protection. Foreign Key from PROTECTION table. | L7: INSTR_PROTECTION-PRTCTN_ID | M7: Concluido | O7: cd_captools.fr003_colaterais | P7: ‣ ref_date = data do report | Q7: cempresa | R7: ‣ Concatenação dos campos mencionados anteriormente: cempresa + "_" + cbalcao_caucao + "_" + cnumecta_caucao + "_" + zcaucao
Q8: cbalcao_caucao
Q9: cnumecta_caucao
Q10: zcaucao
A11: V_193 | B11: Valuation | C11: Protection allocated value | D11: Numeric (euro) | E11: The maximum amount of the protection value that can be considered as credit protection for the instrument. The amount of the existing third parties or observed agent priority claims against the protection must be excluded in the protection allocated value. | F11: O montante máximo do valor de proteção que pode ser considerado como proteção de crédito para o instrumento. A quantidade das reivindicações de prioridade de terceiros existentes ou agentes observados contra a proteção devem ser excluídas no valor atribuído à proteção. | H11: INSTR_PROTECTION-PRTCTN_ALLCTD_VL | I11: Protection allocated value | J11: The maximum amount of the protection value that can be considered as credit protection for the instrument. The amount of the existing third parties or observed agent priority claims against the protection must be excluded in the protection allocated value. | L11: INSTR_PROTECTION-PRTCTN_ALLCTD_VL | M11: Concluido | O11: cd_loan_tapes_bce.lt006_instr_prot | P11: ‣ ref_date = data do report | Q11: prtctn_allctd_vl | R11: ‣ Direto
A12: V_194 | B12: Lien | C12: Third-partypriority claims against the protection | D12: Numeric (euro) | E12: The maximum amount of any existing higher ranked liens with respect to third parties other than the observed agent against the protection. | F12: O montante máximo de quaisquer ónus de grau superior existentes em relação a terceiros que não o agente observado contra o proteção. | H12: INSTR_PROTECTION-THRD_PRTY_PRRTY_CLMS | I12: Third party priority claims against the protection | J12: The maximum amount of any existing higher ranked liens with respect to third parties other than the observed agent against the protection. | L12: INSTR_PROTECTION-THRD_PRTY_PRRTY_CLMS | M12: Concluido | O12: cd_loan_tapes_bce.lt006_instr_prot | P12: ‣ ref_date = data do report | Q12: thrd_prty_prrty_clms | R12: ‣ Direto

Sheet OFF-BALANCE DATA SETS
A1: SRB OFF-BALANCE SHEET EXPOSURES DATA SETS Off-balance sheet exposures do not fall under the scope of the AnaCredit reporting requirements. The SRB Valuation Data Sets for off-balance sheet exposures introduces adhoc data points for these exposures and combine data from difference sources: existing SRB Data Sets for exposures to legal persons and the AnaCredit database. Additionally a set of ad hoc data points covers basic features of off-balance sheet exposures. Off-balance sheet exposures shall include the off-balance sheet items as listed in Annex I of CRR. This data set does not include data on credit derivatives, which are covered by the SRB Valuation Data Set on derivatives. Serão produzidos cinco ficheiros de report referentes a Off-Balance Sheet Exposures: ‣ SRB Instruments Data Set for off-balance sheet exposures (OFFBAL_INSTRUMENTS); ‣ SRB Counterparties Data Set for off-balance sheet exposure (OFFBAL_COUNTERPARTIES); ‣ SRB Protection received Data Set for off-balance sheet exposures (OFFBAL_PROTECTIONS); ‣ SRB Instrument/Counterparty mapping Data Set for off-balance sheet exposures (OFFBAL_INSTRUMENT_COUNTERPARTY); ‣ SRB Instrument/Protection mapping Data Set for off-balance sheet exposures (OFFBAL_INSTRUMENT_PROTECTION);
A2: SRB OFF-BALANCE SHEET EXPOSURES DATA SETS Os requisitos de 'Off-balance sheet exposures', não se enquadram no âmbito do report da AnaCredit. O conjunto de dados de avaliação do CUR (SBR) para posições em risco extrapatrimoniais introduz pontos de dados para estas exposições e combinar dados de diferentes fontes: existentes Conjuntos de dados do CUR para posições em risco sobre pessoas coletivas e a base de dados AnaCredit. Além disso, um conjunto dos pontos de dados ad hoc abrange as características básicas das posições em risco extrapatrimoniais. As posições em risco extrapatrimoniais devem incluir os elementos extrapatrimoniais enumerados no anexo I do CRR. Este conjunto de dados não inclui dados sobre derivados de crédito, que são abrangidos pelo conjunto de dados de avaliação do CUR sobre derivados. Serão produzidos três ficheiros de report referentes a Natural Persons: ‣ SRB Instruments Data Set for off-balance sheet exposures (VDS_OUT_OFFBAL_INSTRUMENTS); ‣ SRB Counterparties Data Set for off-balance sheet exposure (VDS_OUT_OFFBAL_COUNTERPARTIES); ‣ SRB Protection received Data Set for off-balance sheet exposures (VDS_OUT_OFFBAL_PROTECTIONS).

Sheet OFFBAL_INSTRUMENTS
A1: SRB Instruments Data Set for off-balance sheet exposures
A2: ID | B2: Categoria | C2: Coluna | D2: Tipo de dados | E2: Descrição | F2: Descrição | H2: Mapeamentos Corporação (LT) | I2: Descrição (LT) | J2: Additional Guidance (LT) | L2: Comentários | M2: Estado especificação | O2: Fontes de Informação | P2: Filtros | Q2: Campo | R2: Regras de Preenchimento | S2: Agrupações | U2: Observações Maria
A3: V_1 | B3: Identification information | C3: Instrument Identifier | D3: Alphanumeric | E3: An identifier applied to uniquely identify each instrument. Each instrument must have one instrument identifier. | F3: Um identificador aplicado para identificar exclusivamente cada instrumento. Cada instrumento deve ter um identificador de instrumento. | H3: INSTRUMENT-INSTRMNT_ID | I3: Instrument ID | J3: An identifier applied by the reporting agent to uniquely identify each instrument under a single contract. Each instrument must have one instrument identifier. This value will not change over time and cannot be used as the instrument identifier for any other instrument under the same contract. Supervised Insitutions are asked to furnish the INSTRMNT_ID with the exact same value as it is reported to AnaCredit (or any similar central credit register). If this is not available, the value shall be reported as it is internally used. If an instrument is not reported to AnaCredit but requested for the purposes of the on-site inspection please provide the bank-internally used value. | L3: INSTRUMENT-INSTRMNT_ID | M3: Concluido | O3: cd_alm.al029_cnt_core_m | P3: ‣ ref_date = data do report | Q3: cempresa | R3: ‣ Concatenação dos campos mencionados anteriormente: cempresa + "_" + cbalcao + "_" + cnumecta + "_" + zdeposit
Q4: cbalcao
Q5: cnumecta
Q6: zdeposit
A7: V_2 | B7: Identification information | C7: Counterparty Identifier | D7: Alphanumeric | E7: Identifier applied to uniquely identify each counterparty. | F7: Identificador aplicado para identificar exclusivamente cada contraparte. | H7: Not applicable: To be reported as "N/A". This information will be availabe in "03_04_off_instr_count" table | I7: - | J7: - | L7: Not applicable: To be reported as "N/A". This information will be availabe in "03_04_off_instr_count" table | M7: Concluido | O7: cd_alm.al029_cnt_core_m | P7: ‣ ref_date = data do report | Q7: zcliente | R7: ‣ Direto
A8: V_139 | B8: Identification information | C8: Reporting data identifier | D8: Alphanumeric | E8: The reporting agent identifier is the counterparty identifier of the reporting agent which reports the data. | F8: The reporting agent identifier is the counterparty identifier of the reporting agent which reports the data. | H8: INSTRUMENT-COD_SOC | I8: Entity code of the informing society. | J8: Cargabal code or internal identifier of the informing society. | L8: INSTRUMENT-COD_SOC | M8: Concluido | R8: ‣ Forçado a "549300URJH9VSI58CS32" (código lei do BANCO SANTANDER TOTTA, S.A.)
A9: V_140 | B9: Identification information | C9: Observed agent identifier | D9: Alphanumeric | E9: The observed agent identifier is the counterparty identifier of the observed agent (i.e. an institutional unit of the reporting agent) whose data are reported by the reporting agent. | F9: O identificador do agente observado é o identificador da contraparte do agente observado (ou seja, uma unidade institucional do agente inquirido) cujos dados são comunicados pelo agente inquirido. | H9: INSTRUMENT-OBSRVD_AGNT_ID | I9: Observed agent identifier | J9: Counterparty identifier for the observed agent. If there are several observed agents to be reported please separate by comma (,). | L9: INSTRUMENT-OBSRVD_AGNT_ID | M9: Concluido | R9: ‣ Forçado a "549300URJH9VSI58CS32" (código lei do BANCO SANTANDER TOTTA, S.A.)
A10: V_141 | B10: Identification information | C10: Contract identifier | D10: Alphanumeric | E10: An identifier applied by the reporting agent to uniquely identify each contract. The contract identifier refers to the credit agreement between two or more parties under which the instrument is created. | F10: Um identificador aplicado pelo agente relator para identificar exclusivamente cada contrato. O identificador do contrato refere-se ao contrato de crédito entre duas ou mais partes ao abrigo do qual o instrumento é criado. | H10: INSTRUMENT-CNTRCT_ID | I10: Contract ID | J10: An identifier applied by the reporting agent to uniquely identify each contract. Each contract must have one contract identifier. This value will not change over time and cannot be used as the contract identifier for any other contract. | L10: INSTRUMENT-CNTRCT_ID | M10: Concluido | O10: cd_alm.al029_cnt_core_m | P10: ‣ ref_date = data do report | Q10: cempresa | R10: ‣ Concatenação dos campos mencionados anteriormente: cempresa + "_" + cbalcao + "_" + cnumecta + "_" + zdeposit
Q11: cbalcao
Q12: cnumecta
Q13: zdeposit
A14: V_222 | B14: Exposure class | C14: Type | D14: String | E14: Type of commitment or guarantee as per FINREP classification. Options: ‣ Loan commitments given ‣ Financial guarantees given ‣ Other commitments given | F14: Tipo de compromisso ou garantia de acordo com a classificação FINREP. Opções: ‣ Loan commitments given ‣ Financial guarantees given ‣ Other commitments given | H14: - | I14: - | J14: - | L14: ‣ Não encontramos no LT -> Confirmar com Nádia Ahmad e Dora Roxo 16/04/2024 08:59 Email Luísa Quendera: ‣ Este campo deve ser obtido a partir da tabela fr802_pl_contas: 1º - Ligar o universo de INSTRUMENTS à tabela fr802_pl_contas através do campo conta, filtrando a tabela pelo campo carteira_contabilistica = 'garantias e compromissos concedidos'; 2º - Nesta tabela filtrada como é referido acima, obtemos as seguintes opções para o campo produto e as respetivas correspondências para o mapeamento pedido pelo SRB: -> '' --corresponde a---> '' (não indicado pela Luísa -> Questionar) -> 'garantias financeiras prestadas' --corresponde a---> ?????'Financial guarantees given'????? (não indicado pela Luísa -> Questionar) -> 'garantias prestadas' --corresponde a---> 'Financial guarantees given' -> 'compromissos perante terceiros' --corresponde a---> 'Loan commitments given' -> 'compromissos de credito concedidos' --corresponde a---> ?????'Loan commitments given'????? (não indicado pela Luísa -> Questionar) -> 'outras responsabilidades perante terceiros' --corresponde a---> 'Other Commitments given' METEDOLOGIA DE CRUZAMENTO: 1) Cruzar LT002_INSTRUMENT com FR001_UNIV_SALDO para obter o campo contas contabílisticas: LT002_INSTRUMENT LEFT JOIN (SELECT * FROM FR001_UNIV_SALDO) ON INSTRMNT_ID = CONCAT(CEMPRESA, CBALCAO, CNUMECTA, ZDEPOSIT) 2) Cruzar o campo obtido no passo anterior com o plano de contas através da tabela FR802_PL_CONTAS: (SELECT * FROM FR802_PL_CONTAS WHERE cod_plano = '[Perimetro]') ON [CONTA] = CONTA NOTA: A variável [CONTA] proveniente da tabela FR001_UNIV_SALDO varia entre CCONTAB_FINAL_IFRS, CCONTAB_FINAL_ST_SGPS, CCONTAB_FINAL_SGPS_CONS, CCONTAB_FINAL_CARGABAL consoante o nome_perimetro calculado. Como o nosso processo é sobre o Individual Local, devemos usar o campo CCONTAB_FINAL_IFRS e no filtro da tabela FR802 indicado em cima [Perimetro] devemos colocar 'BST_IND', embora o prcesso Loan Tapes tem de estar preparado para qualquer perimetro visto que é uma wallet de campos e outros projetos podem necessitar desta informação para outro perimetro. | M14: Novo campo, mapeamento datalake pendente, com necessidade de criar parametrização | O14: Não está implementado | P14: Não está implementado | Q14: Não está implementado | R14: Não está implementado | S14: Não está implementado | U14: Não está implementado
A15: V_3 | B15: Exposure class | C15: CRR Exposure class | D15: String | E15: The exposures classes for the calculation of RWAs for credit risks are as follows (not applicable when exposures are classified in the CRR trading book as defined in Article 4(1)(86) of Regulation (EU) No 575/2013): Where a bank uses the standardised approach: ‣ Central governments or central banks (SCENGOV) ‣ Regional governments or local authorities (SREGGOV) ‣ Public sector entities (SPUBSEC) ‣ Multilateral development banks (SDEVBAN) ‣ International organisation (SINTORG) ‣ Institutions (SINSTIT) ‣ Corporates (SCORPOR) ‣ Retail (SRETAIL) ‣ Secured by mortgages and immovable property (SSECMOR) ‣ Defaulted (SDEFAUL) ‣ High risk (SHIGHRI) ‣ Covered bonds (SCOVBON) ‣ Items representing securitization positions ‣ Institutions and corporates with a short term credit assessment (SSHOTER) ‣ Collective investment undertakings (SCOLINV) ‣ Equity (SEQUITY) ‣ Other (SOTHERI) Quando um banco utiliza a abordagem IRB: ‣ Central governments and central banks (ICENGOV) ‣ Institutions (IINSTIT) ‣ Corporates (ICORPOR) ‣ Retail (IRETAIL) ‣ Equity (IEQUITY) ‣ Items representing securitization positions ‣ Other non-credit-obligation assets (IOTHERC) | F15: As classes de posições em risco para o cálculo dos ativos ponderados pelo risco de crédito são as seguintes (não aplicáveis quando as posições são classificadas na carteira de negociação do RRFP, tal como definida no artigo 4.o, n.o 1, ponto 86, do Regulamento (UE) n.o 575/2013): Caso um banco utilize o método padrão: ‣ Central governments or central banks (SCENGOV) ‣ Regional governments or local authorities (SREGGOV) ‣ Public sector entities (SPUBSEC) ‣ Multilateral development banks (SDEVBAN) ‣ International organisation (SINTORG) ‣ Institutions (SINSTIT) ‣ Corporates (SCORPOR) ‣ Retail (SRETAIL) ‣ Secured by mortgages and immovable property (SSECMOR) ‣ Defaulted (SDEFAUL) ‣ High risk (SHIGHRI) ‣ Covered bonds (SCOVBON) ‣ Items representing securitization positions ‣ Institutions and corporates with a short term credit assessment (SSHOTER) ‣ Collective investment undertakings (SCOLINV) ‣ Equity (SEQUITY) ‣ Other (SOTHERI) Quando um banco utiliza a abordagem IRB: ‣ Central governments and central banks (ICENGOV) ‣ Institutions (IINSTIT) ‣ Corporates (ICORPOR) ‣ Retail (IRETAIL) ‣ Equity (IEQUITY) ‣ Items representing securitization positions ‣ Other non-credit-obligation assets (IOTHERC) | H15: - | I15: - | J15: - | L15: ‣ Não encontramos no LT -> Confirmar com Nádia Ahmad e Dora Roxo; ‣ Se não existir no LT trazer o segmento_corep_final da ct013, tendo em atenção RWA_mtethod (se for IRB ou STD) ‣ Temos de explorar como ligar o universo lt ao de capital (O) ‣Email de Pedro Mendes com a resposta da Corporação (26/03/2024 17:28) ‣ No LT para calculo do LGD que vem da ct013, quando existe IRB e STD, escolhe-se IRB. Contudo, é preciso clarificar o que se envia quando existem vários segmentos IRB ou também quando existem vários segmentos STD. | M15: Novo campo, mapeamento datalake pendente, com necessidade de criar parametrização | O15: Tabela de parametrização: codemapping | P15: ‣ dd_field_id = "3" | Q15: dd_code | R15: ‣ Tradução do campo "segmento_corep_final" através de uma ligação com o campo "dd_code" para obter o campo: dd_value
Q16: dd_value
O17: cd_captools.ct013_rwa_princ | P17: ‣ ref_date = data do report ‣ flag_cons_cap = 1 ‣ exercicio = 'REAL | Q17: segmento_corep_final
A18: V_4 | B18: Exposure class | C18: FINREP Exposure class | D18: String | E18: Classification of the facility (exposure class) as defined in ITS 680/2014 Annex V Instructions FINREP (Counterparty breakdown). Options: ‣ Central banks ‣ Central governments ‣ Credit institutions ‣ Other financial corporations ‣ Non-financial corporations ‣ Households | F18: Classificação da facilidade (classe de exposição), tal como definida no anexo V do ITS 680/2014, Instruções FINREP (desagregação da contraparte). Opções: ‣ Central banks ‣ Central governments ‣ Credit institutions ‣ Other financial corporations ‣ Non-financial corporations ‣ Households | H18: - | I18: - | J18: - | L18: INSTRUMENT-INTRNL_SGMNT Segundo LCM cada contrato tem apenas 1 segmento FINREP | M18: Mapeamento com LT fechado, mas parametrização pendente | O18: Tabela de parametrização: codemapping | P18: ‣ dd_field_id = "4" | Q18: dd_code | R18: ‣ Inicialmente para cada combinação dos campos "cempresa", "cbalcao", "cnumecta", "zdeposit" iremos recuperar o MAX(carteira_contabilistica): ‣ Este campo MAX(contraparte_i) será traduzido através de uma ligação com o campo "dd_code" para obter o campo: dd_value
Q19: dd_value
O20: cd_captools.ct081_finrep | P20: ‣ ref_date = data do report | Q20: contraparte_i
A21: V_23 | B21: Risk parameters | C21: Credit conversion factor | D21: Numeric. Basis points | E21: Credit conversion factor as defined by the CRR. | F21: Fator de conversão de crédito, tal como definido pelo CRR. | H21: INSTRUMENT-CCF | I21: Credit conversion factor (CCF) according to CRR | J21: Credit conversion factor according to regulation (EU) No 575/2013. | L21: INSTRUMENT-CCF | M21: Concluido | O21: cd_captools.ct013_rwa_princ | P21: ‣ ref_date = data do report ‣ flag_cons_cap = 1 ‣ exercicio = 'REAL | Q21: k2 | R21: ‣ Este campo tem de ser calculado por fases: ‣ 1º - Calculamos o campo auxiliar "ead_final_bruta_grup": ‣ Para cada combinação dos campos "cempresa", "cbalcao", "cnumecta", "zdeposit" iremos SOMAR as: Médias do campo "ead_final_bruta" para cada par dos campos "s1emp", "contra1"; ‣ 2º - Calculamos o campo auxiliar "k2_final": ‣ a) Calculamos o campo auxiliar "ead_avg": Média do campo "ead_final_bruta" para cada par dos campos "s1emp", "contra1"; ‣ b) Calculamos o campo auxiliar "k2_ponderado": ‣ Para cada par dos campos "s1emp", "contra1", iremos calcular a média ponderada do campo "k2" em relação ao campo "ead_final_bruta": SUM(k2 * ead_final_bruta) / SUM(ead_final_bruta); ‣ c) Finalmente calculamos o campo auxiliar "k2_final" através de uma média ponderada do campo "k2_ponderado" em relação ao campo "ead_avg": SUM(k2_ponderado * ead_avg) / SUM(ead_avg); ‣ Finalmente para cada Counterparty Identifier calculamos a média ponderada do campo auxiliar "k2_final" em relação ao campo auxiliar "ead_final_bruta_grup": SUM(k2_final * ead_final_bruta_grup) / SUM(ead_final_bruta_grup) | S21: A agrupação final é feita segundo o campo "Counterparty Identifier" deste mesmo documento
Q22: ead_final_bruta
Q23: s1emp
Q24: contra1
O25: cd_alm.kt_chaves_alm_m | P25: ‣ ref_date = data do report | Q25: cempresa
Q26: cbalcao
Q27: cnumecta
Q28: zdeposit
A29: V_5 | B29: Risk parameters | C29: Total Risk Exposure Amount | D29: Numeric (euro) | E29: The total risk exposure amount of the instrument, calculated according to Articles 92(3) and 92(4) of Regulation (EU) No 575/2013 (CRR), where applicable. | F29: O montante total das posições em risco do instrumento, calculado em conformidade com o artigo 92.o, n.os 3 e 4, do Regulamento (UE) n.o 575/2013 (CRR), em que aplicável. | H29: INSTRUMENT-RWA | I29: RWA | J29: RWA according to Regulation (EU) No 575/2013. | L29: INSTRUMENT-RWA | M29: Concluido | O29: cd_captools.ct013_rwa_princ | P29: ‣ ref_date = data do report ‣ flag_cons_cap = 1 ‣ exercicio = 'REAL | Q29: s1emp | R29: ‣ Para cada Instrument Identifier é somada a: ‣ Média do campo "rwa_final" para cada par de campos "s1emp", "contra1" | S29: A agrupação é feita segundo o campo "Instrument Identifier" deste mesmo documento
Q30: contr1
Q31: rwa_final
A32: V_6 | B32: Risk parameters | C32: CRR Loss given default | D32: Numeric (euro) | E32: Current level of the ‘Loss given default’ of the loan, determined in accordance with Articles 161, 164, 179 and 181 of Regulation (EU) No 575/2013. | F32: Nível atual das «perdas em caso de incumprimento» do empréstimo, determinado em conformidade com os artigos 161.o, 164.o, 179.o e 181.o do Regulamento (UE) n.o 575/2013. | H32: INSTRUMENT-LGD | I32: Regulatory LGD | J32: If differences between regulatory and internal LGD exist, use regulatory LGD (according to Regulation (EU) No 575/2013). In particular, in IRB-F use regulatory LGD values. | L32: INSTRUMENT-LGD | M32: Concluido | O32: cd_captools.ct014_rwa_irb | P32: ‣ ref_date = data do report | Q32: lgdfinal | R32: ‣ Este campo tem de ser calculado por fases: ‣ 1º - Calculamos o campo auxiliar "ead_final_bruta_grup": ‣ Para cada combinação dos campos "cempresa", "cbalcao", "cnumecta", "zdeposit" iremos SOMAR as: Médias do campo "ead_final_bruta" para cada par dos campos "s1emp", "contra1"; ‣ 2º - Calculamos o campo auxiliar "lgdfinal_final": ‣ a) Calculamos o campo auxiliar "ead_avg": Média do campo "ead_final_bruta" para cada par dos campos "s1emp", "contra1"; ‣ b) Calculamos o campo auxiliar "lgdfinal_ponderado": ‣ Para cada par dos campos "s1emp", "contra1", iremos calcular a média ponderada do campo "lgdfinal" em relação ao campo "ead_final_bruta": SUM(lgdfinal * ead_final_bruta) / SUM(ead_final_bruta); ‣ c) Finalmente calculamos o campo auxiliar "lgdfinal_final" através de uma média ponderada do campo "lgdfinal_ponderado" em relação ao campo "ead_avg": SUM(lgdfinal_ponderado * ead_avg) / SUM(ead_avg); ‣ Finalmente para cada Counterparty Identifier calculamos a média ponderada do campo auxiliar "lgdfinal_final" em relação ao campo auxiliar "ead_final_bruta_grup": SUM(lgdfinal_final * ead_final_bruta_grup) / SUM(ead_final_bruta_grup) | S32: A agrupação final é feita segundo o campo "Counterparty Identifier" deste mesmo documento
O33: cd_captools.ct013_rwa_princ | P33: ‣ ref_date = data do report ‣ flag_cons_cap = 1 ‣ exercicio = 'REAL | Q33: ead_final_bruta
Q34: s1emp
Q35: contra1
O36: cd_alm.kt_chaves_alm_m | P36: ‣ ref_date = data do report | Q36: cempresa
Q37: cbalcao
Q38: cnumecta
Q39: zdeposit
A40: V_7 | B40: Risk parameters | C40: IFRS 9 Loss given default | D40: Numeric (euro) | E40: Current level of the ‘Loss given default’ of the loan determined for accounting purposes. | F40: Nível atual da «Perda em caso de incumprimento» do empréstimo determinado para efeitos contabilísticos. | H40: INSTRUMENT-IFRS9_LGD | I40: IFRS 9 accounting LGD | J40: IFRS 9 accounting Loss Given Default as at reference date for defaulted and non-defaulted exposures. In case the bank models time-depended LGD variable for non-defaulted exposures then 12-month LGD as at reference date regardless the classification as Stage 1 or 2 | L40: INSTRUMENT-IFRS9_LGD | M40: Concluido | O40: cd_captools.ifrs9_out_expected_loss_8_7 | P40: ‣ Apenas são trazidos os "contract_id"s que têm "exec_id_part" correspondente na tabela cd_captools.imcatf046_flag_fecho à data ("cmes") do report | Q40: contract_id | R40: ‣ Para cada Instrument Identifier é calculada a: ‣ Média ponderada do campo "lgd_ifrs9" em relação à: ‣ Média do campo "ead" para cada "contract_id" | S40: A agrupação é feita segundo o campo "Instrument Identifier" deste mesmo documento
Q41: ead
Q42: lgd_ifrs9
A43: V_223 | B43: Financial information | C43: Nominal amount | D43: Numeric (euro) | E43: Total nominal amount of off-balance-sheet exposure under IFRS 9. | F43: Montante nominal total da posição em risco extrapatrimonial de acordo com a IFRS 9. | H43: INSTRUMENT-OFF_BLNC_SHT_AMNT_INSTRMNT | I43: Off-balance sheet amount | J43: Total nominal amount of off-balance-sheet exposures. This includes any commitment to lend before considering conversion factors and credit risk mitigation techniques. It is the amount that best represents the institution’s maximum exposure to credit risk without taking into account any protection held or other credit enhancements. To be reported in accordance with Annex V Regulation 680/2014. If no amount can be drawn by or disbursed to the debtor without contractual changes, the off-balance-sheet amount of the instrument is reported as ”not applicable”. | L43: INSTRUMENT-OFF_BLNC_SHT_AMNT_INSTRMNT O SRB solicita o Total nominal amount of off-balance-sheet exposure de IFRS9, contudo, no LT o campo OFF_BLNC_SHT_AMNT_INSTRMNT está a ser obtido da Contabilidade (FR004/LT001), ou seja não está a ser obtido de IFRS9. Portanto, para utilizar o campo LT indicado foi necessário confirmar com IFRS9 que o valor que IFRS9 tem é o da Contabilidade: Segundo David Texugo (email 01/04/2024 17:23), "Os saldos que constam em IFRS9 são reconciliados pela Contabilidade, tratando-se de um subset de contas contabilísticas das carteiras IC que é definido pela Contabilidade." Adicionalmente, confirmou-se na query abaixo: - O campo "amount" da tabela ifrs9_input_motor_8_7 filtrada para amount_type='#903' (off balance) bate certo com o campo valor_bruto_off_a da FR004. - O campo "undrawn_balance" da tabela ifrs9_out_expected_loss_8_7 bate certo com o campo valor_bruto_off_a da FR004. PREOCUPAÇÃO: Não haverá a possibilidade de existirem contratos off balance na fr004 que não existem em IFRS9? Em caso afirmativo, significa que iríamos preencher um valor que não seria o de IFRS9 para estes casos (mas sim o da Contabilidade). SELECT contract_id, montante_ifrs9, montante_fr, montante_fr+montante_ifrs9 as dif FROM -- ( -- select contract_id, CAST(replace(amount,'#','') as DECIMAL(30,8)) as montante_ifrs9 -- from cd_captools.ifrs9_input_motor_8_7 where data_date_part='2023-10-31' and amount_type='#903' -- ) as ifrs9 ( select contract_id, CAST(undrawn_balance as DECIMAL(30,8)) as montante_ifrs9 from cd_captools.ifrs9_out_expected_loss_8_7 where data_date_part='2023-11-03' ) as ifrs9 INNER JOIN ( SELECT CONCAT(contract_id) as IFRS9_ID, CONCAT(CEMPRESA_FR, CBALCAO_FR, CNUMECTA_FR, ZDEPOSIT_FR) as FR_ID FROM (SELECT * FROM cd_captools.KT_CHAVES_FINREP where ref_date = '2023-10-31') as a INNER JOIN (SELECT * FROM cd_captools.KT_CHAVES_IFRS9 where ref_date = '2023-10-31' ) as b ON a.CEMPRESA = b.CEMPRESA AND a.CBALCAO = b.CBALCAO AND a.CNUMECTA = b.CNUMECTA AND a.ZDEPOSIT = b.ZDEPOSIT ) as tradutor on tradutor.IFRS9_ID = ifrs9.contract_id INNER JOIN ( select concat(cempresa, cbalcao, cnumecta, zdeposit) as contr_id, CAST(valor_bruto_off_a as DECIMAL(30,8)) as montante_fr from cd_captools.fr004_cto where ref_date='2023-10-31' ) as fr ON fr.contr_id = tradutor.FR_ID HAVING dif <> 0 | M43: Concluido | O43: cd_alm.al030_sld_core_m | P43: ‣ ref_date = data do report | Q43: mon_extrapatri | R43: ‣ Para cada "Counterparty Identifier" e "Instrument Identifier" é calculado a soma do campo mon_extraptri | S43: A agrupação é feita segundo o campo "Instrument Identifier" e "Counterparty Identifier" deste mesmo documento | U43: verificar a agrupação com o miguel visto que vem de tabelas difetentes
A44: V_224 | B44: Financial information | C44: Maturity / expiry date | D44: DD/MM/YY | E44: Expiry date. | F44: Data de validade. | H44: INSTRUMENT-DT_LGL_FNL_MTRTY | I44: Legal final maturity date (latest repayment date) | J44: The contractual maturity date of the instrument, taking into account any agreements amending initial contracts. As for retail revolving credit facilities this attribute is to be reported "not applicable". | L44: DT_LGL_FNL_MTRTY | M44: Concluido | O44: cd_alm.al029_cnt_core_m | P44: ‣ ref_date = data do report | Q44: dfim | R44: ‣ Direto
A45: V_225 | B45: Financial information | C45: Nominal interest rate or fee | D45: Numeric. Basis points | E45: Notional interest rate or fee as agreed and payable. | F45: Notional interest rate or fee as agreed and payable. | H45: - | I45: - | J45: - | L45: ?ANNLSD_AGRD_RT? Ana Clara/Alexandre Fel./Barata não conhecem o conceito. Questionar Corporação? | M45: Novo campo, mapeamento datalake pendente, sem necessidade de criar parametrização | O45: cd_alm.al029_cnt_core_m | P45: ‣ ref_date = data do report | Q45: tx_contrato_pas | R45: ‣ Direto
Q46: tx_contrato_act
A47: V_158 | B47: Financial information | C47: Default status of the instrument | D47: String | E47: Identification of the default status of the instrument in accordance with Article 178 of Regulation (EU) No 575/2013. Options: ‣ Not in default ‣ Default because unlikely to pay (not more than 90/180 days past due). ‣ Default because more than 90/180 days past due ‣ Default because both unlikely to pay and more than 90/180 days past due. | F47: Identificação da situação de incumprimento do instrumento em conformidade com o artigo 178.o do Regulamento (UE) n.o 575/2013. Opções: ‣ Not in default ‣ Default because unlikely to pay (not more than 90/180 days past due). ‣ Default because more than 90/180 days past due ‣ Default because both unlikely to pay and more than 90/180 days past due. | H47: INSTRUMENT-DFLT_STTS_INSTRMNT | I47: Default status of the instrument | J47: Identification of the default status of the instrument. Categories describing the situations in which an instrument can be described as being at default in accordance with Article 178 of Regulation (EU) No 575/2013. | L47: INSTRUMENT-DFLT_STTS_INSTRMNT | M47: Mapeamento com LT fechado, mas parametrização pendente | O47: Tabela de parametrização: codemapping | P47: ‣ dd_field_id = "158" | Q47: dd_code | R47: ‣ Tradução do campo "dflt_stts_instrmnt" através de uma ligação com o campo "dd_code" para obter o campo: dd_value
Q48: dd_value
O49: cd_loan_tapes_bce.lt002_instrument | P49: ‣ ref_date = data do report | Q49: dflt_stts_instrmnt
A50: V_159 | B50: Financial information | C50: Date of the default status of the instrument | D50: DD/MM/YY | E50: The date on which the default status, as reported in the data attribute “default status of the instrument”, is considered to have occurred. | F50: A data em que o status padrão, conforme relatado no atributo de dados "status padrão do instrumento", é considerado como tendo ocorrido. | H50: INSTRUMENT-DT_DFLT_STTS_INSTRMNT | I50: Date of default status | J50: The date on which the default status, as reported in the data attribute “Default status”, is considered to have arisen. If "Not in default" since inception then this attribute is to be reported equally to the inception date. If more than one Instrument is classified as defaulted then the earliest date has to be provided. The definition of default is aligned with Art 178 of Regulation (EU) No 575/2013. | L50: INSTRUMENT-DT_DFLT_STTS_INSTRMNT | M50: Concluido | O50: cd_loan_tapes_bce.lt002_instrument | P50: ‣ ref_date = data do report | Q50: dt_dflt_stts_instrmnt | R50: ‣ Direto
