Workbook

Sheet Âmbito de atuação
B6: Âmbito de atuação
C9: Modelo Relacional - Modelo Verde | V9: Modelo Relacional - Bens Imóveis
C39: Legenda:
D40: Tabelas âmbito de atuação

Sheet 1. Status Resumo
B6: Sumário Executivo |19 de julho a 25 de julho
B8: 1. Apesar dos testes ao Green Dashboard se encontrarem em Stand By, ainda foram realizadas reuniões de esclarecimentos com área de negócio sobre a desagregação dos contratos por Business Area e estão agendadas 2 reuniões de seguimento. 2. Pelas dependências de alterações aos inputs do Modelo Verde (Tecnologia) e da validação da parametrização de marcações verdes (área de negócio), a equipa de testes encontra-se focada no Modelo de Bens Imóveis. 3. Sobre os testes ao Modelo de Bens Imóveis, a validação de universo de bens colateralizados e bens provenientes das GP encontra-se concluída e na próxima semana serão realizados testes aos campos de atributos. Não foi possível testar o universo de bens adjudicados, uma vez que os dados sobre o mesmo, à data, não estão totalmente dísponiveis no DL. Será realizado um projeto onde será testado este universo.
B17: 1. Modelo de Bens Imóveis | G17: Bens Imóveis - Input | H17: Bens Imóveis - Output
C20: Resumo | G20: Detalhe por Tabela | P20: Status | T20: 45492 | U20: 45499 | V20: ∆ | X20: Highlights
P21: 0. Cancelado | T21: =COUNTIFS('2. Status Detalhe Campos'!$H$7:$H$605,'1. Status Resumo'!$P21,'2. Status Detalhe Campos'!$C$7:$C$605,'1. Status Resumo'!$G$17,'2. Status Detalhe Campos'!$D$7:$D$605,"2. Campo")+COUNTIFS('2. Status Detalhe Campos'!$H$7:$H$605,'1. Status Resumo'!$P21,'2. Status Detalhe Campos'!$C$7:$C$605,'1. Status Resumo'!$H$17,'2. Status Detalhe Campos'!$D$7:$D$605,"2. Campo") -> 8 | U21: =COUNTIFS('2. Status Detalhe Campos'!$G$7:$G$605,'1. Status Resumo'!$P21,'2. Status Detalhe Campos'!$C$7:$C$605,'1. Status Resumo'!$G$17,'2. Status Detalhe Campos'!$D$7:$D$605,"2. Campo")+COUNTIFS('2. Status Detalhe Campos'!$G$7:$G$605,'1. Status Resumo'!$P21,'2. Status Detalhe Campos'!$C$7:$C$605,'1. Status Resumo'!$H$17,'2. Status Detalhe Campos'!$D$7:$D$605,"2. Campo") -> 8 | V21: =U21-T21 -> 0 | X21: 1. A validação de universo de bens colateralizados e bens provenientes das GP encontra-se concluída com sucesso (15 campos de chave Responsabilidade, Processo e Bem). Não foram identificados bens adjudicados no modelo. 2. Foram re-especificadas as regras de cruzamento com as aplicações de GP por forma a garantir a coerência com o MUG (pouco impacto na implementação e sem impactos a nível de resultados na data da realização do teste). 3. Foram entregues 2 campos por IT para teste sobre correção de incidência no dia 22 de julho. 4. Deve ser repensado o modo de upload do Input da Gloval no front do Data Lake por forma a não "esmagar" a informação já carregada previamente ou atualizar caso necessário (afeta 65 campos).
P22: 1. Concluído | T22: =COUNTIFS('2. Status Detalhe Campos'!$H$7:$H$605,'1. Status Resumo'!$P22,'2. Status Detalhe Campos'!$C$7:$C$605,'1. Status Resumo'!$G$17,'2. Status Detalhe Campos'!$D$7:$D$605,"2. Campo")+COUNTIFS('2. Status Detalhe Campos'!$H$7:$H$605,'1. Status Resumo'!$P22,'2. Status Detalhe Campos'!$C$7:$C$605,'1. Status Resumo'!$H$17,'2. Status Detalhe Campos'!$D$7:$D$605,"2. Campo") -> 35 | U22: =COUNTIFS('2. Status Detalhe Campos'!$G$7:$G$605,'1. Status Resumo'!$P22,'2. Status Detalhe Campos'!$C$7:$C$605,'1. Status Resumo'!$G$17,'2. Status Detalhe Campos'!$D$7:$D$605,"2. Campo")+COUNTIFS('2. Status Detalhe Campos'!$G$7:$G$605,'1. Status Resumo'!$P22,'2. Status Detalhe Campos'!$C$7:$C$605,'1. Status Resumo'!$H$17,'2. Status Detalhe Campos'!$D$7:$D$605,"2. Campo") -> 50 | V22: =U22-T22 -> 15
P23: 2. Em Teste | T23: =COUNTIFS('2. Status Detalhe Campos'!$H$7:$H$605,'1. Status Resumo'!$P23,'2. Status Detalhe Campos'!$C$7:$C$605,'1. Status Resumo'!$G$17,'2. Status Detalhe Campos'!$D$7:$D$605,"2. Campo")+COUNTIFS('2. Status Detalhe Campos'!$H$7:$H$605,'1. Status Resumo'!$P23,'2. Status Detalhe Campos'!$C$7:$C$605,'1. Status Resumo'!$H$17,'2. Status Detalhe Campos'!$D$7:$D$605,"2. Campo") -> 103 | U23: =COUNTIFS('2. Status Detalhe Campos'!$G$7:$G$605,'1. Status Resumo'!$P23,'2. Status Detalhe Campos'!$C$7:$C$605,'1. Status Resumo'!$G$17,'2. Status Detalhe Campos'!$D$7:$D$605,"2. Campo")+COUNTIFS('2. Status Detalhe Campos'!$G$7:$G$605,'1. Status Resumo'!$P23,'2. Status Detalhe Campos'!$C$7:$C$605,'1. Status Resumo'!$H$17,'2. Status Detalhe Campos'!$D$7:$D$605,"2. Campo") -> 90 | V23: =U23-T23 -> -13
D24: ="# "&U29 -> # 161 | P24: 3. Pendente de outros desenvolvimentos | T24: =COUNTIFS('2. Status Detalhe Campos'!$H$7:$H$605,'1. Status Resumo'!$P24,'2. Status Detalhe Campos'!$C$7:$C$605,'1. Status Resumo'!$G$17,'2. Status Detalhe Campos'!$D$7:$D$605,"2. Campo")+COUNTIFS('2. Status Detalhe Campos'!$H$7:$H$605,'1. Status Resumo'!$P24,'2. Status Detalhe Campos'!$C$7:$C$605,'1. Status Resumo'!$H$17,'2. Status Detalhe Campos'!$D$7:$D$605,"2. Campo") -> 0 | U24: =COUNTIFS('2. Status Detalhe Campos'!$G$7:$G$605,'1. Status Resumo'!$P24,'2. Status Detalhe Campos'!$C$7:$C$605,'1. Status Resumo'!$G$17,'2. Status Detalhe Campos'!$D$7:$D$605,"2. Campo")+COUNTIFS('2. Status Detalhe Campos'!$G$7:$G$605,'1. Status Resumo'!$P24,'2. Status Detalhe Campos'!$C$7:$C$605,'1. Status Resumo'!$H$17,'2. Status Detalhe Campos'!$D$7:$D$605,"2. Campo") -> 0 | V24: =U24-T24 -> 0
P25: 4. Validação EF | T25: =COUNTIFS('2. Status Detalhe Campos'!$H$7:$H$605,'1. Status Resumo'!$P25,'2. Status Detalhe Campos'!$C$7:$C$605,'1. Status Resumo'!$G$17,'2. Status Detalhe Campos'!$D$7:$D$605,"2. Campo")+COUNTIFS('2. Status Detalhe Campos'!$H$7:$H$605,'1. Status Resumo'!$P25,'2. Status Detalhe Campos'!$C$7:$C$605,'1. Status Resumo'!$H$17,'2. Status Detalhe Campos'!$D$7:$D$605,"2. Campo") -> 13 | U25: =COUNTIFS('2. Status Detalhe Campos'!$G$7:$G$605,'1. Status Resumo'!$P25,'2. Status Detalhe Campos'!$C$7:$C$605,'1. Status Resumo'!$G$17,'2. Status Detalhe Campos'!$D$7:$D$605,"2. Campo")+COUNTIFS('2. Status Detalhe Campos'!$G$7:$G$605,'1. Status Resumo'!$P25,'2. Status Detalhe Campos'!$C$7:$C$605,'1. Status Resumo'!$H$17,'2. Status Detalhe Campos'!$D$7:$D$605,"2. Campo") -> 13 | V25: =U25-T25 -> 0
P26: 5. Em Correção | R26: (incidências) | T26: =COUNTIFS('2. Status Detalhe Campos'!$H$7:$H$605,'1. Status Resumo'!$P26,'2. Status Detalhe Campos'!$C$7:$C$605,'1. Status Resumo'!$G$17,'2. Status Detalhe Campos'!$D$7:$D$605,"2. Campo")+COUNTIFS('2. Status Detalhe Campos'!$H$7:$H$605,'1. Status Resumo'!$P26,'2. Status Detalhe Campos'!$C$7:$C$605,'1. Status Resumo'!$H$17,'2. Status Detalhe Campos'!$D$7:$D$605,"2. Campo") -> 2 | U26: =COUNTIFS('2. Status Detalhe Campos'!$G$7:$G$605,'1. Status Resumo'!$P26,'2. Status Detalhe Campos'!$C$7:$C$605,'1. Status Resumo'!$G$17,'2. Status Detalhe Campos'!$D$7:$D$605,"2. Campo")+COUNTIFS('2. Status Detalhe Campos'!$G$7:$G$605,'1. Status Resumo'!$P26,'2. Status Detalhe Campos'!$C$7:$C$605,'1. Status Resumo'!$H$17,'2. Status Detalhe Campos'!$D$7:$D$605,"2. Campo") -> 0 | V26: =U26-T26 -> -2
P27: 6. Em implementação (re-especificação) | T27: =COUNTIFS('2. Status Detalhe Campos'!$H$7:$H$605,'1. Status Resumo'!$P27,'2. Status Detalhe Campos'!$C$7:$C$605,'1. Status Resumo'!$G$17,'2. Status Detalhe Campos'!$D$7:$D$605,"2. Campo")+COUNTIFS('2. Status Detalhe Campos'!$H$7:$H$605,'1. Status Resumo'!$P27,'2. Status Detalhe Campos'!$C$7:$C$605,'1. Status Resumo'!$H$17,'2. Status Detalhe Campos'!$D$7:$D$605,"2. Campo") -> 0 | U27: =COUNTIFS('2. Status Detalhe Campos'!$G$7:$G$605,'1. Status Resumo'!$P27,'2. Status Detalhe Campos'!$C$7:$C$605,'1. Status Resumo'!$G$17,'2. Status Detalhe Campos'!$D$7:$D$605,"2. Campo")+COUNTIFS('2. Status Detalhe Campos'!$G$7:$G$605,'1. Status Resumo'!$P27,'2. Status Detalhe Campos'!$C$7:$C$605,'1. Status Resumo'!$H$17,'2. Status Detalhe Campos'!$D$7:$D$605,"2. Campo") -> 0 | V27: =U27-T27 -> 0
P28: 7. Por iniciar | T28: =COUNTIFS('2. Status Detalhe Campos'!$H$7:$H$605,'1. Status Resumo'!$P28,'2. Status Detalhe Campos'!$C$7:$C$605,'1. Status Resumo'!$G$17,'2. Status Detalhe Campos'!$D$7:$D$605,"2. Campo")+COUNTIFS('2. Status Detalhe Campos'!$H$7:$H$605,'1. Status Resumo'!$P28,'2. Status Detalhe Campos'!$C$7:$C$605,'1. Status Resumo'!$H$17,'2. Status Detalhe Campos'!$D$7:$D$605,"2. Campo") -> 0 | U28: =COUNTIFS('2. Status Detalhe Campos'!$G$7:$G$605,'1. Status Resumo'!$P28,'2. Status Detalhe Campos'!$C$7:$C$605,'1. Status Resumo'!$G$17,'2. Status Detalhe Campos'!$D$7:$D$605,"2. Campo")+COUNTIFS('2. Status Detalhe Campos'!$G$7:$G$605,'1. Status Resumo'!$P28,'2. Status Detalhe Campos'!$C$7:$C$605,'1. Status Resumo'!$H$17,'2. Status Detalhe Campos'!$D$7:$D$605,"2. Campo") -> 0 | V28: =U28-T28 -> 0
T29: =SUM(T21:T28) -> 161 | U29: =SUM(U21:U28) -> 161
O31: > | P31: Universo Bens Colateralizados (MUG) | T31: OK
O32: > | P32: Universo Bens Não Colateralizados (GP) | T32: OK
O33: > | P33: Universo Bens Adjudicados | T33: Não serão testados neste projeto
B36: 2. Modelo Verde | G36: Modelo Verde - Input | H36: Modelo Verde - Output
C39: Resumo | G39: Detalhe por Tabela | P39: Status | T39: =T20 -> 45492 | U39: =U20 -> 45499 | V39: ∆ | X39: Highlights
P40: 0. Cancelado | T40: =COUNTIFS('2. Status Detalhe Campos'!$H$7:$H$605,'1. Status Resumo'!$P40,'2. Status Detalhe Campos'!$C$7:$C$605,'1. Status Resumo'!$G$36,'2. Status Detalhe Campos'!$D$7:$D$605,"2. Campo")+COUNTIFS('2. Status Detalhe Campos'!$H$7:$H$605,'1. Status Resumo'!$P40,'2. Status Detalhe Campos'!$C$7:$C$605,'1. Status Resumo'!$H$36,'2. Status Detalhe Campos'!$D$7:$D$605,"2. Campo") -> 10 | U40: =COUNTIFS('2. Status Detalhe Campos'!$G$7:$G$605,'1. Status Resumo'!$P40,'2. Status Detalhe Campos'!$C$7:$C$605,'1. Status Resumo'!$G$36,'2. Status Detalhe Campos'!$D$7:$D$605,"2. Campo")+COUNTIFS('2. Status Detalhe Campos'!$G$7:$G$605,'1. Status Resumo'!$P40,'2. Status Detalhe Campos'!$C$7:$C$605,'1. Status Resumo'!$H$36,'2. Status Detalhe Campos'!$D$7:$D$605,"2. Campo") -> 10 | V40: =U40-T40 -> 0 | X40: 1. Continua em curso o assessment ao Modelo Verde 2. Os campos que dependem da hierarquia de ordem de aprovisionamento da tabela de clientes (LEI, ISIN, KGL) estão em correção por Tecnologia com data prevista para 31 de julho. 3. Foi realizada uma análise aos impactos sobre a eliminação/adição de campos aos inputs corporativos e já foi partilhada com a equipa de Tecnologia a proposta de solução. Está agendada uma reunião no dia 1 de agosto para discussão de proposta com Tecnologia, CDO e área de Negócio.
P41: 1. Concluído | T41: =COUNTIFS('2. Status Detalhe Campos'!$H$7:$H$605,'1. Status Resumo'!$P41,'2. Status Detalhe Campos'!$C$7:$C$605,'1. Status Resumo'!$G$36,'2. Status Detalhe Campos'!$D$7:$D$605,"2. Campo")+COUNTIFS('2. Status Detalhe Campos'!$H$7:$H$605,'1. Status Resumo'!$P41,'2. Status Detalhe Campos'!$C$7:$C$605,'1. Status Resumo'!$H$36,'2. Status Detalhe Campos'!$D$7:$D$605,"2. Campo") -> 63 | U41: =COUNTIFS('2. Status Detalhe Campos'!$G$7:$G$605,'1. Status Resumo'!$P41,'2. Status Detalhe Campos'!$C$7:$C$605,'1. Status Resumo'!$G$36,'2. Status Detalhe Campos'!$D$7:$D$605,"2. Campo")+COUNTIFS('2. Status Detalhe Campos'!$G$7:$G$605,'1. Status Resumo'!$P41,'2. Status Detalhe Campos'!$C$7:$C$605,'1. Status Resumo'!$H$36,'2. Status Detalhe Campos'!$D$7:$D$605,"2. Campo") -> 63 | V41: =U41-T41 -> 0
P42: 2. Em Teste | T42: =COUNTIFS('2. Status Detalhe Campos'!$H$7:$H$605,'1. Status Resumo'!$P42,'2. Status Detalhe Campos'!$C$7:$C$605,'1. Status Resumo'!$G$36,'2. Status Detalhe Campos'!$D$7:$D$605,"2. Campo")+COUNTIFS('2. Status Detalhe Campos'!$H$7:$H$605,'1. Status Resumo'!$P42,'2. Status Detalhe Campos'!$C$7:$C$605,'1. Status Resumo'!$H$36,'2. Status Detalhe Campos'!$D$7:$D$605,"2. Campo") -> 6 | U42: =COUNTIFS('2. Status Detalhe Campos'!$G$7:$G$605,'1. Status Resumo'!$P42,'2. Status Detalhe Campos'!$C$7:$C$605,'1. Status Resumo'!$G$36,'2. Status Detalhe Campos'!$D$7:$D$605,"2. Campo")+COUNTIFS('2. Status Detalhe Campos'!$G$7:$G$605,'1. Status Resumo'!$P42,'2. Status Detalhe Campos'!$C$7:$C$605,'1. Status Resumo'!$H$36,'2. Status Detalhe Campos'!$D$7:$D$605,"2. Campo") -> 6 | V42: =U42-T42 -> 0
D43: ="# "&U48 -> # 242 | P43: 3. Pendente de outros desenvolvimentos | T43: =COUNTIFS('2. Status Detalhe Campos'!$H$7:$H$605,'1. Status Resumo'!$P43,'2. Status Detalhe Campos'!$C$7:$C$605,'1. Status Resumo'!$G$36,'2. Status Detalhe Campos'!$D$7:$D$605,"2. Campo")+COUNTIFS('2. Status Detalhe Campos'!$H$7:$H$605,'1. Status Resumo'!$P43,'2. Status Detalhe Campos'!$C$7:$C$605,'1. Status Resumo'!$H$36,'2. Status Detalhe Campos'!$D$7:$D$605,"2. Campo") -> 45 | U43: =COUNTIFS('2. Status Detalhe Campos'!$G$7:$G$605,'1. Status Resumo'!$P43,'2. Status Detalhe Campos'!$C$7:$C$605,'1. Status Resumo'!$G$36,'2. Status Detalhe Campos'!$D$7:$D$605,"2. Campo")+COUNTIFS('2. Status Detalhe Campos'!$G$7:$G$605,'1. Status Resumo'!$P43,'2. Status Detalhe Campos'!$C$7:$C$605,'1. Status Resumo'!$H$36,'2. Status Detalhe Campos'!$D$7:$D$605,"2. Campo") -> 45 | V43: =U43-T43 -> 0
P44: 4. Validação EF | T44: =COUNTIFS('2. Status Detalhe Campos'!$H$7:$H$605,'1. Status Resumo'!$P44,'2. Status Detalhe Campos'!$C$7:$C$605,'1. Status Resumo'!$G$36,'2. Status Detalhe Campos'!$D$7:$D$605,"2. Campo")+COUNTIFS('2. Status Detalhe Campos'!$H$7:$H$605,'1. Status Resumo'!$P44,'2. Status Detalhe Campos'!$C$7:$C$605,'1. Status Resumo'!$H$36,'2. Status Detalhe Campos'!$D$7:$D$605,"2. Campo") -> 22 | U44: =COUNTIFS('2. Status Detalhe Campos'!$G$7:$G$605,'1. Status Resumo'!$P44,'2. Status Detalhe Campos'!$C$7:$C$605,'1. Status Resumo'!$G$36,'2. Status Detalhe Campos'!$D$7:$D$605,"2. Campo")+COUNTIFS('2. Status Detalhe Campos'!$G$7:$G$605,'1. Status Resumo'!$P44,'2. Status Detalhe Campos'!$C$7:$C$605,'1. Status Resumo'!$H$36,'2. Status Detalhe Campos'!$D$7:$D$605,"2. Campo") -> 22 | V44: =U44-T44 -> 0
P45: 5. Em Correção | R45: (incidências) | T45: =COUNTIFS('2. Status Detalhe Campos'!$H$7:$H$605,'1. Status Resumo'!$P45,'2. Status Detalhe Campos'!$C$7:$C$605,'1. Status Resumo'!$G$36,'2. Status Detalhe Campos'!$D$7:$D$605,"2. Campo")+COUNTIFS('2. Status Detalhe Campos'!$H$7:$H$605,'1. Status Resumo'!$P45,'2. Status Detalhe Campos'!$C$7:$C$605,'1. Status Resumo'!$H$36,'2. Status Detalhe Campos'!$D$7:$D$605,"2. Campo") -> 95 | U45: =COUNTIFS('2. Status Detalhe Campos'!$G$7:$G$605,'1. Status Resumo'!$P45,'2. Status Detalhe Campos'!$C$7:$C$605,'1. Status Resumo'!$G$36,'2. Status Detalhe Campos'!$D$7:$D$605,"2. Campo")+COUNTIFS('2. Status Detalhe Campos'!$G$7:$G$605,'1. Status Resumo'!$P45,'2. Status Detalhe Campos'!$C$7:$C$605,'1. Status Resumo'!$H$36,'2. Status Detalhe Campos'!$D$7:$D$605,"2. Campo") -> 95 | V45: =U45-T45 -> 0
P46: 6. Em implementação (re-especificação) | T46: =COUNTIFS('2. Status Detalhe Campos'!$H$7:$H$605,'1. Status Resumo'!$P46,'2. Status Detalhe Campos'!$C$7:$C$605,'1. Status Resumo'!$G$36,'2. Status Detalhe Campos'!$D$7:$D$605,"2. Campo")+COUNTIFS('2. Status Detalhe Campos'!$H$7:$H$605,'1. Status Resumo'!$P46,'2. Status Detalhe Campos'!$C$7:$C$605,'1. Status Resumo'!$H$36,'2. Status Detalhe Campos'!$D$7:$D$605,"2. Campo") -> 0 | U46: =COUNTIFS('2. Status Detalhe Campos'!$G$7:$G$605,'1. Status Resumo'!$P46,'2. Status Detalhe Campos'!$C$7:$C$605,'1. Status Resumo'!$G$36,'2. Status Detalhe Campos'!$D$7:$D$605,"2. Campo")+COUNTIFS('2. Status Detalhe Campos'!$G$7:$G$605,'1. Status Resumo'!$P46,'2. Status Detalhe Campos'!$C$7:$C$605,'1. Status Resumo'!$H$36,'2. Status Detalhe Campos'!$D$7:$D$605,"2. Campo") -> 0 | V46: =U46-T46 -> 0
P47: 7. Por iniciar | T47: =COUNTIFS('2. Status Detalhe Campos'!$H$7:$H$605,'1. Status Resumo'!$P47,'2. Status Detalhe Campos'!$C$7:$C$605,'1. Status Resumo'!$G$36,'2. Status Detalhe Campos'!$D$7:$D$605,"2. Campo")+COUNTIFS('2. Status Detalhe Campos'!$H$7:$H$605,'1. Status Resumo'!$P47,'2. Status Detalhe Campos'!$C$7:$C$605,'1. Status Resumo'!$H$36,'2. Status Detalhe Campos'!$D$7:$D$605,"2. Campo") -> 1 | U47: =COUNTIFS('2. Status Detalhe Campos'!$G$7:$G$605,'1. Status Resumo'!$P47,'2. Status Detalhe Campos'!$C$7:$C$605,'1. Status Resumo'!$G$36,'2. Status Detalhe Campos'!$D$7:$D$605,"2. Campo")+COUNTIFS('2. Status Detalhe Campos'!$G$7:$G$605,'1. Status Resumo'!$P47,'2. Status Detalhe Campos'!$C$7:$C$605,'1. Status Resumo'!$H$36,'2. Status Detalhe Campos'!$D$7:$D$605,"2. Campo") -> 1 | V47: =U47-T47 -> 0
T48: =SUM(T40:T47) -> 242 | U48: =SUM(U40:U47) -> 242
B58: 3. Loan Tape | Pilar III | G58: Pilar III
C61: Resumo | G61: Detalhe por Tabela | P61: Status | T61: =T20 -> 45492 | U61: =$U$20 -> 45499 | V61: ∆ | X61: Highlights
P62: 0. Cancelado | T62: =COUNTIFS(Table4[Status Anterior],'1. Status Resumo'!$P62,Table4[Sub-âmbito],'1. Status Resumo'!$G$58,Table4[Tipo de teste],"2. Campo") -> 0 | U62: =COUNTIFS(Table4[Status Atual],'1. Status Resumo'!$P62,Table4[Sub-âmbito],'1. Status Resumo'!$G$58,Table4[Tipo de teste],"2. Campo") -> 0 | V62: =U62-T62 -> 0 | X62: Sem desenvolvimentos sobre o ultimo PdS. Nota: 1. Universo de contratos deve corresponder ao da Loan Tape Estrutural 2. Na tabela da Protection apenas serão testadas os imóveis colateralizados.
P63: 1. Concluído | T63: =COUNTIFS(Table4[Status Anterior],'1. Status Resumo'!$P63,Table4[Sub-âmbito],'1. Status Resumo'!$G$58,Table4[Tipo de teste],"2. Campo") -> 0 | U63: =COUNTIFS(Table4[Status Atual],'1. Status Resumo'!$P63,Table4[Sub-âmbito],'1. Status Resumo'!$G$58,Table4[Tipo de teste],"2. Campo") -> 0 | V63: =U63-T63 -> 0
P64: 2. Em Teste | T64: =COUNTIFS(Table4[Status Anterior],'1. Status Resumo'!$P64,Table4[Sub-âmbito],'1. Status Resumo'!$G$58,Table4[Tipo de teste],"2. Campo") -> 0 | U64: =COUNTIFS(Table4[Status Atual],'1. Status Resumo'!$P64,Table4[Sub-âmbito],'1. Status Resumo'!$G$58,Table4[Tipo de teste],"2. Campo") -> 0 | V64: =U64-T64 -> 0
D65: ="# "&U70 -> # 126 | P65: 3. Pendente de outros desenvolvimentos | T65: =COUNTIFS(Table4[Status Anterior],'1. Status Resumo'!$P65,Table4[Sub-âmbito],'1. Status Resumo'!$G$58,Table4[Tipo de teste],"2. Campo") -> 0 | U65: =COUNTIFS(Table4[Status Atual],'1. Status Resumo'!$P65,Table4[Sub-âmbito],'1. Status Resumo'!$G$58,Table4[Tipo de teste],"2. Campo") -> 0 | V65: =U65-T65 -> 0
P66: 4. Validação EF | T66: =COUNTIFS(Table4[Status Anterior],'1. Status Resumo'!$P66,Table4[Sub-âmbito],'1. Status Resumo'!$G$58,Table4[Tipo de teste],"2. Campo") -> 0 | U66: =COUNTIFS(Table4[Status Atual],'1. Status Resumo'!$P66,Table4[Sub-âmbito],'1. Status Resumo'!$G$58,Table4[Tipo de teste],"2. Campo") -> 0 | V66: =U66-T66 -> 0
P67: 5. Em Correção | R67: (incidências) | T67: =COUNTIFS(Table4[Status Anterior],'1. Status Resumo'!$P67,Table4[Sub-âmbito],'1. Status Resumo'!$G$58,Table4[Tipo de teste],"2. Campo") -> 0 | U67: =COUNTIFS(Table4[Status Atual],'1. Status Resumo'!$P67,Table4[Sub-âmbito],'1. Status Resumo'!$G$58,Table4[Tipo de teste],"2. Campo") -> 0 | V67: =U67-T67 -> 0
P68: 6. Em implementação (re-especificação) | T68: =COUNTIFS(Table4[Status Anterior],'1. Status Resumo'!$P68,Table4[Sub-âmbito],'1. Status Resumo'!$G$58,Table4[Tipo de teste],"2. Campo") -> 0 | U68: =COUNTIFS(Table4[Status Atual],'1. Status Resumo'!$P68,Table4[Sub-âmbito],'1. Status Resumo'!$G$58,Table4[Tipo de teste],"2. Campo") -> 0 | V68: =U68-T68 -> 0
P69: 7. Por iniciar | T69: =COUNTIFS(Table4[Status Anterior],'1. Status Resumo'!$P69,Table4[Sub-âmbito],'1. Status Resumo'!$G$58,Table4[Tipo de teste],"2. Campo") -> 126 | U69: =COUNTIFS(Table4[Status Atual],'1. Status Resumo'!$P69,Table4[Sub-âmbito],'1. Status Resumo'!$G$58,Table4[Tipo de teste],"2. Campo") -> 126 | V69: =U69-T69 -> 0
T70: =SUM(T62:T69) -> 126 | U70: =SUM(U62:U69) -> 126
B74: 4. Loan Tape | Green Dashboard | G74: GD
C77: Resumo | G77: Detalhe por Tabela | P77: Status | T77: =T39 -> 45492 | U77: =$U$20 -> 45499 | V77: ∆ | X77: Highlights
P78: 0. Cancelado | T78: =COUNTIFS('2. Status Detalhe Campos'!$H$7:$H$595,'1. Status Resumo'!$P78,'2. Status Detalhe Campos'!$C$7:$C$595,'1. Status Resumo'!$G$74,'2. Status Detalhe Campos'!$D$7:$D$595,"2. Campo") -> 0 | U78: =COUNTIFS('2. Status Detalhe Campos'!$G$7:$G$595,'1. Status Resumo'!$P78,'2. Status Detalhe Campos'!$C$7:$C$595,'1. Status Resumo'!$G$74,'2. Status Detalhe Campos'!$D$7:$D$595,"2. Campo") -> 0 | V78: =U78-T78 -> 0 | X78: 1. Foi realizada uma reunião de esclarecimento/dúvida relativamente à especificação as-is e to-be dos campos e desagregação da chave do contrato com as equipas envolvidas. Não obstante, está agendada uma reunião de seguimento para decisão (1 de agosto). 2. Foram entregues 2 campos por IT para teste sobre correção de incidência no dia 8 de julho. Este bloco encontra-se em stand by pela equipa de testes.
P79: 1. Concluído | T79: =COUNTIFS('2. Status Detalhe Campos'!$H$7:$H$595,'1. Status Resumo'!$P79,'2. Status Detalhe Campos'!$C$7:$C$595,'1. Status Resumo'!$G$74,'2. Status Detalhe Campos'!$D$7:$D$595,"2. Campo") -> 23 | U79: =COUNTIFS('2. Status Detalhe Campos'!$G$7:$G$595,'1. Status Resumo'!$P79,'2. Status Detalhe Campos'!$C$7:$C$595,'1. Status Resumo'!$G$74,'2. Status Detalhe Campos'!$D$7:$D$595,"2. Campo") -> 23 | V79: =U79-T79 -> 0
P80: 2. Em Teste | T80: =COUNTIFS('2. Status Detalhe Campos'!$H$7:$H$595,'1. Status Resumo'!$P80,'2. Status Detalhe Campos'!$C$7:$C$595,'1. Status Resumo'!$G$74,'2. Status Detalhe Campos'!$D$7:$D$595,"2. Campo") -> 24 | U80: =COUNTIFS('2. Status Detalhe Campos'!$G$7:$G$595,'1. Status Resumo'!$P80,'2. Status Detalhe Campos'!$C$7:$C$595,'1. Status Resumo'!$G$74,'2. Status Detalhe Campos'!$D$7:$D$595,"2. Campo") -> 26 | V80: =U80-T80 -> 2
D81: ="# "&U86 -> # 50 | P81: 3. Pendente de outros desenvolvimentos | T81: =COUNTIFS('2. Status Detalhe Campos'!$H$7:$H$595,'1. Status Resumo'!$P81,'2. Status Detalhe Campos'!$C$7:$C$595,'1. Status Resumo'!$G$74,'2. Status Detalhe Campos'!$D$7:$D$595,"2. Campo") -> 1 | U81: =COUNTIFS('2. Status Detalhe Campos'!$G$7:$G$595,'1. Status Resumo'!$P81,'2. Status Detalhe Campos'!$C$7:$C$595,'1. Status Resumo'!$G$74,'2. Status Detalhe Campos'!$D$7:$D$595,"2. Campo") -> 1 | V81: =U81-T81 -> 0
P82: 4. Validação EF | T82: =COUNTIFS('2. Status Detalhe Campos'!$H$7:$H$595,'1. Status Resumo'!$P82,'2. Status Detalhe Campos'!$C$7:$C$595,'1. Status Resumo'!$G$74,'2. Status Detalhe Campos'!$D$7:$D$595,"2. Campo") -> 0 | U82: =COUNTIFS('2. Status Detalhe Campos'!$G$7:$G$595,'1. Status Resumo'!$P82,'2. Status Detalhe Campos'!$C$7:$C$595,'1. Status Resumo'!$G$74,'2. Status Detalhe Campos'!$D$7:$D$595,"2. Campo") -> 0 | V82: =U82-T82 -> 0
P83: 5. Em Correção | R83: (incidências) | T83: =COUNTIFS('2. Status Detalhe Campos'!$H$7:$H$595,'1. Status Resumo'!$P83,'2. Status Detalhe Campos'!$C$7:$C$595,'1. Status Resumo'!$G$74,'2. Status Detalhe Campos'!$D$7:$D$595,"2. Campo") -> 2 | U83: =COUNTIFS('2. Status Detalhe Campos'!$G$7:$G$595,'1. Status Resumo'!$P83,'2. Status Detalhe Campos'!$C$7:$C$595,'1. Status Resumo'!$G$74,'2. Status Detalhe Campos'!$D$7:$D$595,"2. Campo") -> 0 | V83: =U83-T83 -> -2
P84: 6. Em implementação (re-especificação) | T84: =COUNTIFS('2. Status Detalhe Campos'!$H$7:$H$595,'1. Status Resumo'!$P84,'2. Status Detalhe Campos'!$C$7:$C$595,'1. Status Resumo'!$G$74,'2. Status Detalhe Campos'!$D$7:$D$595,"2. Campo") -> 0 | U84: =COUNTIFS('2. Status Detalhe Campos'!$G$7:$G$595,'1. Status Resumo'!$P84,'2. Status Detalhe Campos'!$C$7:$C$595,'1. Status Resumo'!$G$74,'2. Status Detalhe Campos'!$D$7:$D$595,"2. Campo") -> 0 | V84: =U84-T84 -> 0
P85: 7. Por iniciar | T85: =COUNTIFS('2. Status Detalhe Campos'!$H$7:$H$595,'1. Status Resumo'!$P85,'2. Status Detalhe Campos'!$C$7:$C$595,'1. Status Resumo'!$G$74,'2. Status Detalhe Campos'!$D$7:$D$595,"2. Campo") -> 0 | U85: =COUNTIFS('2. Status Detalhe Campos'!$G$7:$G$595,'1. Status Resumo'!$P85,'2. Status Detalhe Campos'!$C$7:$C$595,'1. Status Resumo'!$G$74,'2. Status Detalhe Campos'!$D$7:$D$595,"2. Campo") -> 0 | V85: =U85-T85 -> 0
T86: =SUM(T78:T85) -> 50 | U86: =SUM(U78:U85) -> 50

Sheet 2. Status Detalhe Campos
B6: Âmbito | C6: Sub-âmbito | D6: Tipo de teste | E6: Tabela | F6: Campo | G6: Status Atual | H6: Status Anterior | I6: Observações | J6: Data de Pedido correção/esclarecimento | K6: Data de correção prevista | L6: Data de correção efetiva
A7: =E7&F7 -> cd_imv_inp_certif_estimativan.a. | B7: Pilar III | C7: Bens Imóveis - Input | D7: 1. Universo | E7: cd_imv_inp_certif_estimativa | F7: n.a. | G7: 4. Validação EF | H7: 4. Validação EF
A8: =E8&F8 -> cd_imv_inp_certif_estimativacempbem | B8: Pilar III | C8: Bens Imóveis - Input | D8: 2. Campo | E8: cd_imv_inp_certif_estimativa | F8: cempbem | G8: 4. Validação EF | H8: 4. Validação EF
A9: =E9&F9 -> cd_imv_inp_certif_estimativachave_encriptada | B9: Pilar III | C9: Bens Imóveis - Input | D9: 2. Campo | E9: cd_imv_inp_certif_estimativa | F9: chave_encriptada | G9: 4. Validação EF | H9: 4. Validação EF
A10: =E10&F10 -> cd_imv_inp_certif_estimativackbalbem | B10: Pilar III | C10: Bens Imóveis - Input | D10: 2. Campo | E10: cd_imv_inp_certif_estimativa | F10: ckbalbem | G10: 4. Validação EF | H10: 4. Validação EF
A11: =E11&F11 -> cd_imv_inp_certif_estimativackctabem | B11: Pilar III | C11: Bens Imóveis - Input | D11: 2. Campo | E11: cd_imv_inp_certif_estimativa | F11: ckctabem | G11: 4. Validação EF | H11: 4. Validação EF
A12: =E12&F12 -> cd_imv_inp_certif_estimativackrefbem | B12: Pilar III | C12: Bens Imóveis - Input | D12: 2. Campo | E12: cd_imv_inp_certif_estimativa | F12: ckrefbem | G12: 4. Validação EF | H12: 4. Validação EF
A13: =E13&F13 -> cd_imv_inp_certif_estimativadata_extraccao_info | B13: Pilar III | C13: Bens Imóveis - Input | D13: 2. Campo | E13: cd_imv_inp_certif_estimativa | F13: data_extraccao_info | G13: 4. Validação EF | H13: 4. Validação EF
A14: =E14&F14 -> cd_imv_inp_certif_estimativaepc | B14: Pilar III | C14: Bens Imóveis - Input | D14: 2. Campo | E14: cd_imv_inp_certif_estimativa | F14: epc | G14: 4. Validação EF | H14: 4. Validação EF
A15: =E15&F15 -> cd_imv_inp_certif_estimativafornecedor | B15: Pilar III | C15: Bens Imóveis - Input | D15: 2. Campo | E15: cd_imv_inp_certif_estimativa | F15: fornecedor | G15: 4. Validação EF | H15: 4. Validação EF
A16: =E16&F16 -> cd_imv_inp_certif_estimativametodo_info | B16: Pilar III | C16: Bens Imóveis - Input | D16: 2. Campo | E16: cd_imv_inp_certif_estimativa | F16: metodo_info | G16: 4. Validação EF | H16: 4. Validação EF
A17: =E17&F17 -> cd_imv_inp_certif_estimativascore_qualidade | B17: Pilar III | C17: Bens Imóveis - Input | D17: 2. Campo | E17: cd_imv_inp_certif_estimativa | F17: score_qualidade | G17: 4. Validação EF | H17: 4. Validação EF
A18: =E18&F18 -> cd_imv_inp_certif_estimativavlr_cnsm_ano | B18: Pilar III | C18: Bens Imóveis - Input | D18: 2. Campo | E18: cd_imv_inp_certif_estimativa | F18: vlr_cnsm_ano | G18: 4. Validação EF | H18: 4. Validação EF
... A20: =E20&F20 -> cd_imv_out_prcn.a. | B20: Pilar III | C20: Bens Imóveis - Output | D20: 1. Universo | E20: cd_imv_out_prc | F20: n.a. | G20: 2. Em Teste | H20: 2. Em Teste
A21: =E21&F21 -> cd_imv_out_prccempresa | B21: Pilar III | C21: Bens Imóveis - Output | D21: 2. Campo | E21: cd_imv_out_prc | F21: cempresa | G21: 1. Concluído | H21: 2. Em Teste | I21: 26/07/2024: Conclusão de testes ao universo MUG e GP. Adjudicados fora de âmbito deste projeto.
A22: =E22&F22 -> cd_imv_out_prcckbalcao | B22: Pilar III | C22: Bens Imóveis - Output | D22: 2. Campo | E22: cd_imv_out_prc | F22: ckbalcao | G22: 1. Concluído | H22: 2. Em Teste | I22: 26/07/2024: Conclusão de testes ao universo MUG e GP. Adjudicados fora de âmbito deste projeto.
A23: =E23&F23 -> cd_imv_out_prccknumcta | B23: Pilar III | C23: Bens Imóveis - Output | D23: 2. Campo | E23: cd_imv_out_prc | F23: cknumcta | G23: 1. Concluído | H23: 2. Em Teste | I23: 26/07/2024: Conclusão de testes ao universo MUG e GP. Adjudicados fora de âmbito deste projeto.
A24: =E24&F24 -> cd_imv_out_prccod_estd_prcs | B24: Pilar III | C24: Bens Imóveis - Output | D24: 2. Campo | E24: cd_imv_out_prc | F24: cod_estd_prcs | G24: 0. Cancelado | H24: 0. Cancelado
A25: =E25&F25 -> cd_imv_out_prccod_grt | B25: Pilar III | C25: Bens Imóveis - Output | D25: 2. Campo | E25: cd_imv_out_prc | F25: cod_grt | G25: 2. Em Teste | H25: 2. Em Teste
A26: =E26&F26 -> cd_imv_out_prccod_moeda | B26: Pilar III | C26: Bens Imóveis - Output | D26: 2. Campo | E26: cd_imv_out_prc | F26: cod_moeda | G26: 2. Em Teste | H26: 2. Em Teste
A27: =E27&F27 -> cd_imv_out_prccod_observacao | B27: Pilar III | C27: Bens Imóveis - Output | D27: 2. Campo | E27: cd_imv_out_prc | F27: cod_observacao | G27: 2. Em Teste | H27: 2. Em Teste
A28: =E28&F28 -> cd_imv_out_prccod_prd_grnt | B28: Pilar III | C28: Bens Imóveis - Output | D28: 2. Campo | E28: cd_imv_out_prc | F28: cod_prd_grnt | G28: 2. Em Teste | H28: 2. Em Teste
A29: =E29&F29 -> cd_imv_out_prccod_sprd_grnt | B29: Pilar III | C29: Bens Imóveis - Output | D29: 2. Campo | E29: cd_imv_out_prc | F29: cod_sprd_grnt | G29: 2. Em Teste | H29: 2. Em Teste
A30: =E30&F30 -> cd_imv_out_prccod_tipo | B30: Pilar III | C30: Bens Imóveis - Output | D30: 2. Campo | E30: cd_imv_out_prc | F30: cod_tipo | G30: 2. Em Teste | H30: 2. Em Teste
A31: =E31&F31 -> cd_imv_out_prccomp_id_gar | B31: Pilar III | C31: Bens Imóveis - Output | D31: 2. Campo | E31: cd_imv_out_prc | F31: comp_id_gar | G31: 2. Em Teste | H31: 2. Em Teste
A32: =E32&F32 -> cd_imv_out_prcdata_inicio | B32: Pilar III | C32: Bens Imóveis - Output | D32: 2. Campo | E32: cd_imv_out_prc | F32: data_inicio | G32: 2. Em Teste | H32: 2. Em Teste
A33: =E33&F33 -> cd_imv_out_prcdata_vcmt | B33: Pilar III | C33: Bens Imóveis - Output | D33: 2. Campo | E33: cd_imv_out_prc | F33: data_vcmt | G33: 2. Em Teste | H33: 2. Em Teste
A34: =E34&F34 -> cd_imv_out_prcmontante_eur | B34: Pilar III | C34: Bens Imóveis - Output | D34: 2. Campo | E34: cd_imv_out_prc | F34: montante_eur | G34: 0. Cancelado | H34: 0. Cancelado
A35: =E35&F35 -> cd_imv_out_prcmontante_org | B35: Pilar III | C35: Bens Imóveis - Output | D35: 2. Campo | E35: cd_imv_out_prc | F35: montante_org | G35: 0. Cancelado | H35: 0. Cancelado
... A38: =E38&F38 -> cd_imv_out_trz_cred_prcn.a. | B38: Pilar III | C38: Bens Imóveis - Output | D38: 1. Universo | E38: cd_imv_out_trz_cred_prc | F38: n.a. | G38: 2. Em Teste | H38: 2. Em Teste
A39: =E39&F39 -> cd_imv_out_trz_cred_prccempresa | B39: Pilar III | C39: Bens Imóveis - Output | D39: 2. Campo | E39: cd_imv_out_trz_cred_prc | F39: cempresa | G39: 1. Concluído | H39: 2. Em Teste | I39: 26/07/2024: Conclusão de testes ao universo MUG e GP. Adjudicados fora de âmbito deste projeto.
A40: =E40&F40 -> cd_imv_out_trz_cred_prccempresp | B40: Pilar III | C40: Bens Imóveis - Output | D40: 2. Campo | E40: cd_imv_out_trz_cred_prc | F40: cempresp | G40: 1. Concluído | H40: 2. Em Teste | I40: 26/07/2024: Conclusão de testes ao universo MUG e GP. Adjudicados fora de âmbito deste projeto.
A41: =E41&F41 -> cd_imv_out_trz_cred_prcckbalcao | B41: Pilar III | C41: Bens Imóveis - Output | D41: 2. Campo | E41: cd_imv_out_trz_cred_prc | F41: ckbalcao | G41: 1. Concluído | H41: 2. Em Teste | I41: 26/07/2024: Conclusão de testes ao universo MUG e GP. Adjudicados fora de âmbito deste projeto.
A42: =E42&F42 -> cd_imv_out_trz_cred_prcckbalres | B42: Pilar III | C42: Bens Imóveis - Output | D42: 2. Campo | E42: cd_imv_out_trz_cred_prc | F42: ckbalres | G42: 1. Concluído | H42: 2. Em Teste | I42: 26/07/2024: Conclusão de testes ao universo MUG e GP. Adjudicados fora de âmbito deste projeto.
A43: =E43&F43 -> cd_imv_out_trz_cred_prcckctares | B43: Pilar III | C43: Bens Imóveis - Output | D43: 2. Campo | E43: cd_imv_out_trz_cred_prc | F43: ckctares | G43: 1. Concluído | H43: 2. Em Teste | I43: 26/07/2024: Conclusão de testes ao universo MUG e GP. Adjudicados fora de âmbito deste projeto.
A44: =E44&F44 -> cd_imv_out_trz_cred_prccknumcta | B44: Pilar III | C44: Bens Imóveis - Output | D44: 2. Campo | E44: cd_imv_out_trz_cred_prc | F44: cknumcta | G44: 1. Concluído | H44: 2. Em Teste | I44: 26/07/2024: Conclusão de testes ao universo MUG e GP. Adjudicados fora de âmbito deste projeto.
A45: =E45&F45 -> cd_imv_out_trz_cred_prcckrefresp | B45: Pilar III | C45: Bens Imóveis - Output | D45: 2. Campo | E45: cd_imv_out_trz_cred_prc | F45: ckrefresp | G45: 1. Concluído | H45: 2. Em Teste | I45: 26/07/2024: Conclusão de testes ao universo MUG e GP. Adjudicados fora de âmbito deste projeto.
A46: =E46&F46 -> cd_imv_out_trz_cred_prccod_fnld | B46: Pilar III | C46: Bens Imóveis - Output | D46: 2. Campo | E46: cd_imv_out_trz_cred_prc | F46: cod_fnld | G46: 2. Em Teste | H46: 2. Em Teste
A47: =E47&F47 -> cd_imv_out_trz_cred_prccod_ocupacao | B47: Pilar III | C47: Bens Imóveis - Output | D47: 2. Campo | E47: cd_imv_out_trz_cred_prc | F47: cod_ocupacao | G47: 2. Em Teste | H47: 2. Em Teste
A48: =E48&F48 -> cd_imv_out_trz_cred_prccod_prd_resp | B48: Pilar III | C48: Bens Imóveis - Output | D48: 2. Campo | E48: cd_imv_out_trz_cred_prc | F48: cod_prd_resp | G48: 2. Em Teste | H48: 2. Em Teste
A49: =E49&F49 -> cd_imv_out_trz_cred_prccod_sit | B49: Pilar III | C49: Bens Imóveis - Output | D49: 2. Campo | E49: cd_imv_out_trz_cred_prc | F49: cod_sit | G49: 0. Cancelado | H49: 0. Cancelado
A50: =E50&F50 -> cd_imv_out_trz_cred_prccod_sprd_resp | B50: Pilar III | C50: Bens Imóveis - Output | D50: 2. Campo | E50: cd_imv_out_trz_cred_prc | F50: cod_sprd_resp | G50: 2. Em Teste | H50: 2. Em Teste
A51: =E51&F51 -> cd_imv_out_trz_cred_prccomp_id_gar | B51: Pilar III | C51: Bens Imóveis - Output | D51: 2. Campo | E51: cd_imv_out_trz_cred_prc | F51: comp_id_gar | G51: 2. Em Teste | H51: 2. Em Teste
A52: =E52&F52 -> cd_imv_out_trz_cred_prcdata_fim | B52: Pilar III | C52: Bens Imóveis - Output | D52: 2. Campo | E52: cd_imv_out_trz_cred_prc | F52: data_fim | G52: 2. Em Teste | H52: 2. Em Teste
A53: =E53&F53 -> cd_imv_out_trz_cred_prcdata_inicio | B53: Pilar III | C53: Bens Imóveis - Output | D53: 2. Campo | E53: cd_imv_out_trz_cred_prc | F53: data_inicio | G53: 2. Em Teste | H53: 2. Em Teste
A54: =E54&F54 -> cd_imv_out_trz_cred_prcdata_vcmt | B54: Pilar III | C54: Bens Imóveis - Output | D54: 2. Campo | E54: cd_imv_out_trz_cred_prc | F54: data_vcmt | G54: 2. Em Teste | H54: 2. Em Teste
A55: =E55&F55 -> cd_imv_out_trz_cred_prcidetgar | B55: Pilar III | C55: Bens Imóveis - Output | D55: 2. Campo | E55: cd_imv_out_trz_cred_prc | F55: idetgar | G55: 0. Cancelado | H55: 0. Cancelado
A56: =E56&F56 -> cd_imv_out_trz_cred_prcnum_prop | B56: Pilar III | C56: Bens Imóveis - Output | D56: 2. Campo | E56: cd_imv_out_trz_cred_prc | F56: num_prop | G56: 0. Cancelado | H56: 0. Cancelado
A57: =E57&F57 -> cd_imv_out_trz_cred_prcorigem | B57: Pilar III | C57: Bens Imóveis - Output | D57: 2. Campo | E57: cd_imv_out_trz_cred_prc | F57: origem | G57: 2. Em Teste | H57: 2. Em Teste
... A60: =E60&F60 -> cd_imv_out_trz_prc_bens_imvcempbem | B60: Pilar III | C60: Bens Imóveis - Output | D60: 2. Campo | E60: cd_imv_out_trz_prc_bens_imv | F60: cempbem | G60: 1. Concluído | H60: 1. Concluído
A61: =E61&F61 -> cd_imv_out_trz_prc_bens_imvcempresa | B61: Pilar III | C61: Bens Imóveis - Output | D61: 2. Campo | E61: cd_imv_out_trz_prc_bens_imv | F61: cempresa | G61: 1. Concluído | H61: 2. Em Teste | I61: 26/07/2024: Conclusão de testes ao universo MUG e GP. Adjudicados fora de âmbito deste projeto.
A62: =E62&F62 -> cd_imv_out_trz_prc_bens_imvckbalbem | B62: Pilar III | C62: Bens Imóveis - Output | D62: 2. Campo | E62: cd_imv_out_trz_prc_bens_imv | F62: ckbalbem | G62: 1. Concluído | H62: 2. Em Teste | I62: 26/07/2024: Conclusão de testes ao universo MUG e GP. Adjudicados fora de âmbito deste projeto.
A63: =E63&F63 -> cd_imv_out_trz_prc_bens_imvckbalcao | B63: Pilar III | C63: Bens Imóveis - Output | D63: 2. Campo | E63: cd_imv_out_trz_prc_bens_imv | F63: ckbalcao | G63: 1. Concluído | H63: 2. Em Teste | I63: 26/07/2024: Conclusão de testes ao universo MUG e GP. Adjudicados fora de âmbito deste projeto.
A64: =E64&F64 -> cd_imv_out_trz_prc_bens_imvckctabem | B64: Pilar III | C64: Bens Imóveis - Output | D64: 2. Campo | E64: cd_imv_out_trz_prc_bens_imv | F64: ckctabem | G64: 1. Concluído | H64: 2. Em Teste | I64: 26/07/2024: Conclusão de testes ao universo MUG e GP. Adjudicados fora de âmbito deste projeto.
A65: =E65&F65 -> cd_imv_out_trz_prc_bens_imvcknumcta | B65: Pilar III | C65: Bens Imóveis - Output | D65: 2. Campo | E65: cd_imv_out_trz_prc_bens_imv | F65: cknumcta | G65: 1. Concluído | H65: 2. Em Teste | I65: 26/07/2024: Conclusão de testes ao universo MUG e GP. Adjudicados fora de âmbito deste projeto.
A66: =E66&F66 -> cd_imv_out_trz_prc_bens_imvckrefbem | B66: Pilar III | C66: Bens Imóveis - Output | D66: 2. Campo | E66: cd_imv_out_trz_prc_bens_imv | F66: ckrefbem | G66: 1. Concluído | H66: 1. Concluído
A67: =E67&F67 -> cd_imv_out_trz_prc_bens_imvcomp_id_gar | B67: Pilar III | C67: Bens Imóveis - Output | D67: 2. Campo | E67: cd_imv_out_trz_prc_bens_imv | F67: comp_id_gar | G67: 2. Em Teste | H67: 2. Em Teste
A68: =E68&F68 -> cd_imv_out_trz_prc_bens_imvdata_assc | B68: Pilar III | C68: Bens Imóveis - Output | D68: 2. Campo | E68: cd_imv_out_trz_prc_bens_imv | F68: data_assc | G68: 0. Cancelado | H68: 0. Cancelado
A69: =E69&F69 -> cd_imv_out_trz_prc_bens_imvflg_adj | B69: Pilar III | C69: Bens Imóveis - Output | D69: 2. Campo | E69: cd_imv_out_trz_prc_bens_imv | F69: flg_adj | G69: 1. Concluído | H69: 1. Concluído
A70: =E70&F70 -> cd_imv_out_trz_prc_bens_imvflg_col | B70: Pilar III | C70: Bens Imóveis - Output | D70: 2. Campo | E70: cd_imv_out_trz_prc_bens_imv | F70: flg_col | G70: 1. Concluído | H70: 1. Concluído
A71: =E71&F71 -> cd_imv_out_trz_prc_bens_imvflg_fin | B71: Pilar III | C71: Bens Imóveis - Output | D71: 2. Campo | E71: cd_imv_out_trz_prc_bens_imv | F71: flg_fin | G71: 1. Concluído | H71: 1. Concluído
A72: =E72&F72 -> cd_imv_out_trz_prc_bens_imvflg_pro | B72: Pilar III | C72: Bens Imóveis - Output | D72: 2. Campo | E72: cd_imv_out_trz_prc_bens_imv | F72: flg_pro | G72: 1. Concluído | H72: 1. Concluído
A73: =E73&F73 -> cd_imv_out_trz_prc_bens_imvorigem | B73: Pilar III | C73: Bens Imóveis - Output | D73: 2. Campo | E73: cd_imv_out_trz_prc_bens_imv | F73: origem | G73: 1. Concluído | H73: 1. Concluído
A74: =E74&F74 -> cd_imv_out_trz_prc_bens_imvref_date | B74: Pilar III | C74: Bens Imóveis - Output | D74: 2. Campo | E74: cd_imv_out_trz_prc_bens_imv | F74: ref_date | G74: 1. Concluído | H74: 1. Concluído
A75: =E75&F75 -> cd_imv_out_bensn.a. | B75: Pilar III | C75: Bens Imóveis - Output | D75: 1. Universo | E75: cd_imv_out_bens | F75: n.a. | G75: 2. Em Teste | H75: 2. Em Teste
A76: =E76&F76 -> cd_imv_out_bensano_construcao | B76: Pilar III | C76: Bens Imóveis - Output | D76: 2. Campo | E76: cd_imv_out_bens | F76: ano_construcao | G76: 4. Validação EF | H76: 4. Validação EF
A77: =E77&F77 -> cd_imv_out_bensarea_util | B77: Pilar III | C77: Bens Imóveis - Output | D77: 2. Campo | E77: cd_imv_out_bens | F77: area_util | G77: 2. Em Teste | H77: 2. Em Teste
... A103: =E103&F103 -> cd_imv_out_bensorigem | B103: Pilar III | C103: Bens Imóveis - Output | D103: 2. Campo | E103: cd_imv_out_bens | F103: origem | G103: 1. Concluído | H103: 1. Concluído
A104: =E104&F104 -> cd_imv_out_bensperc_obra | B104: Pilar III | C104: Bens Imóveis - Output | D104: 2. Campo | E104: cd_imv_out_bens | F104: perc_obra | G104: 2. Em Teste | H104: 5. Em Correção | I104: 22/07/2024: Entrega de campo para testes | J104: 45491 | K104: 45495 | L104: 45495
A105: =E105&F105 -> cd_imv_out_bensprealcons | B105: Pilar III | C105: Bens Imóveis - Output | D105: 2. Campo | E105: cd_imv_out_bens | F105: prealcons | G105: 2. Em Teste | H105: 5. Em Correção | I105: 22/07/2024: Entrega de campo para testes | J105: 45491 | K105: 45495 | L105: 45495
A106: =E106&F106 -> cd_imv_out_bensref_date | B106: Pilar III | C106: Bens Imóveis - Output | D106: 2. Campo | E106: cd_imv_out_bens | F106: ref_date | G106: 1. Concluído | H106: 1. Concluído
A107: =E107&F107 -> cd_imv_out_bensurbaniz | B107: Pilar III | C107: Bens Imóveis - Output | D107: 2. Campo | E107: cd_imv_out_bens | F107: urbaniz | G107: 1. Concluído | H107: 1. Concluído
A108: =E108&F108 -> cd_imv_out_certifn.a. | B108: Pilar III | C108: Bens Imóveis - Output | D108: 1. Universo | E108: cd_imv_out_certif | F108: n.a. | G108: 2. Em Teste | H108: 2. Em Teste
A109: =E109&F109 -> cd_imv_out_certifcempbem | B109: Pilar III | C109: Bens Imóveis - Output | D109: 2. Campo | E109: cd_imv_out_certif | F109: cempbem | G109: 2. Em Teste | H109: 2. Em Teste
A110: =E110&F110 -> cd_imv_out_certifckbalbem | B110: Pilar III | C110: Bens Imóveis - Output | D110: 2. Campo | E110: cd_imv_out_certif | F110: ckbalbem | G110: 2. Em Teste | H110: 2. Em Teste
A111: =E111&F111 -> cd_imv_out_certifckctabem | B111: Pilar III | C111: Bens Imóveis - Output | D111: 2. Campo | E111: cd_imv_out_certif | F111: ckctabem | G111: 2. Em Teste | H111: 2. Em Teste
A112: =E112&F112 -> cd_imv_out_certifckrefbem | B112: Pilar III | C112: Bens Imóveis - Output | D112: 2. Campo | E112: cd_imv_out_certif | F112: ckrefbem | G112: 2. Em Teste | H112: 2. Em Teste
A113: =E113&F113 -> cd_imv_out_certifcod_cnsrvtr_rgst_prdl | B113: Pilar III | C113: Bens Imóveis - Output | D113: 2. Campo | E113: cd_imv_out_certif | F113: cod_cnsrvtr_rgst_prdl | G113: 2. Em Teste | H113: 2. Em Teste
A114: =E114&F114 -> cd_imv_out_certifcod_inscrc | B114: Pilar III | C114: Bens Imóveis - Output | D114: 2. Campo | E114: cd_imv_out_certif | F114: cod_inscrc | G114: 2. Em Teste | H114: 2. Em Teste
A115: =E115&F115 -> cd_imv_out_certifcod_sce | B115: Pilar III | C115: Bens Imóveis - Output | D115: 2. Campo | E115: cd_imv_out_certif | F115: cod_sce | G115: 2. Em Teste | H115: 2. Em Teste
A116: =E116&F116 -> cd_imv_out_certifdata_epc | B116: Pilar III | C116: Bens Imóveis - Output | D116: 2. Campo | E116: cd_imv_out_certif | F116: data_epc | G116: 2. Em Teste | H116: 2. Em Teste
A117: =E117&F117 -> cd_imv_out_certifdata_exprc_epc | B117: Pilar III | C117: Bens Imóveis - Output | D117: 2. Campo | E117: cd_imv_out_certif | F117: data_exprc_epc | G117: 2. Em Teste | H117: 2. Em Teste
... A190: =E190&F190 -> modesg_param_sfcs_taxon_europeiaepc | B190: Pilar III | C190: Modelo Verde - Input | D190: 2. Campo | E190: modesg_param_sfcs_taxon_europeia | F190: epc | G190: 1. Concluído | H190: 1. Concluído
A191: =E191&F191 -> modesg_param_sfcs_taxon_europeiaflag_project_finance | B191: Pilar III | C191: Modelo Verde - Input | D191: 2. Campo | E191: modesg_param_sfcs_taxon_europeia | F191: flag_project_finance | G191: 4. Validação EF | H191: 4. Validação EF | I191: Novo Campo - IT já implementou
A192: =E192&F192 -> modesg_param_sfcs_taxon_europeiacfinalidad | B192: Pilar III | C192: Modelo Verde - Input | D192: 2. Campo | E192: modesg_param_sfcs_taxon_europeia | F192: cfinalidad | G192: 4. Validação EF | H192: 4. Validação EF | I192: Novo Campo - IT já implementou
A193: =E193&F193 -> modesg_param_sfcs_taxon_europeiatipo_combust | B193: Pilar III | C193: Modelo Verde - Input | D193: 2. Campo | E193: modesg_param_sfcs_taxon_europeia | F193: tipo_combust | G193: 4. Validação EF | H193: 4. Validação EF | I193: Novo Campo
A194: =E194&F194 -> modesg_param_sfcs_taxon_europeiamontante_pndrc | B194: Pilar III | C194: Modelo Verde - Input | D194: 2. Campo | E194: modesg_param_sfcs_taxon_europeia | F194: montante_pndrc | G194: 4. Validação EF | H194: 4. Validação EF
A195: =E195&F195 -> modesg_param_sfcs_taxon_europeianome_ctgr_sfcs | B195: Pilar III | C195: Modelo Verde - Input | D195: 2. Campo | E195: modesg_param_sfcs_taxon_europeia | F195: nome_ctgr_sfcs | G195: 4. Validação EF | H195: 4. Validação EF
A196: =E196&F196 -> modesg_param_sfcs_taxon_europeianome_general_specific_purpose | B196: Pilar III | C196: Modelo Verde - Input | D196: 2. Campo | E196: modesg_param_sfcs_taxon_europeia | F196: nome_general_specific_purpose | G196: 1. Concluído | H196: 1. Concluído
A197: =E197&F197 -> modesg_param_sfcs_taxon_europeianome_purpose_esg | B197: Pilar III | C197: Modelo Verde - Input | D197: 2. Campo | E197: modesg_param_sfcs_taxon_europeia | F197: nome_purpose_esg | G197: 1. Concluído | H197: 1. Concluído
A198: =E198&F198 -> modesg_param_sfcs_taxon_europeianome_specific_eligible | B198: Pilar III | C198: Modelo Verde - Input | D198: 2. Campo | E198: modesg_param_sfcs_taxon_europeia | F198: nome_specific_eligible | G198: 1. Concluído | H198: 1. Concluído
A199: =E199&F199 -> modesg_param_sfcs_taxon_europeianome_specific_sustainable | B199: Pilar III | C199: Modelo Verde - Input | D199: 2. Campo | E199: modesg_param_sfcs_taxon_europeia | F199: nome_specific_sustainable | G199: 1. Concluído | H199: 1. Concluído
A200: =E200&F200 -> modesg_param_sfcs_taxon_europeiaref_date | B200: Pilar III | C200: Modelo Verde - Input | D200: 2. Campo | E200: modesg_param_sfcs_taxon_europeia | F200: ref_date | G200: 1. Concluído | H200: 1. Concluído
A201: =E201&F201 -> modesg_param_sfcs_taxon_europeiazcliente | B201: Pilar III | C201: Modelo Verde - Input | D201: 2. Campo | E201: modesg_param_sfcs_taxon_europeia | F201: zcliente | G201: 1. Concluído | H201: 1. Concluído
A202: =E202&F202 -> modesg_param_sfcs_taxon_europeiazdeposit | B202: Pilar III | C202: Modelo Verde - Input | D202: 2. Campo | E202: modesg_param_sfcs_taxon_europeia | F202: zdeposit | G202: 1. Concluído | H202: 1. Concluído
A203: =E203&F203 -> modesg_inp_emss_vclsn.a. | B203: Pilar III | C203: Modelo Verde - Input | D203: 1. Universo | E203: modesg_inp_emss_vcls | F203: n.a. | G203: 5. Em Correção | H203: 5. Em Correção | I203: Alteração estrutural | J203: 45471
A204: =E204&F204 -> modesg_inp_km_medios_emss_vclsn.a. | B204: Pilar III | C204: Modelo Verde - Input | D204: 1. Universo | E204: modesg_inp_km_medios_emss_vcls | F204: n.a. | G204: 5. Em Correção | H204: 5. Em Correção | I204: Alteração estrutural
A205: =E205&F205 -> modesg_inp_empr_excl_parisn.a. | B205: Pilar III | C205: Modelo Verde - Input | D205: 1. Universo | E205: modesg_inp_empr_excl_paris | F205: n.a. | G205: 1. Concluído | H205: 1. Concluído
A206: =E206&F206 -> modesg_inp_nfrd_alinhamento_taxn.a. | B206: Pilar III | C206: Modelo Verde - Input | D206: 1. Universo | E206: modesg_inp_nfrd_alinhamento_tax | F206: n.a. | G206: 5. Em Correção | H206: 5. Em Correção | I206: Alteração estrutural
A207: =E207&F207 -> modesg_inp_risco_fisicon.a. | B207: Pilar III | C207: Modelo Verde - Input | D207: 1. Universo | E207: modesg_inp_risco_fisico | F207: n.a. | G207: 1. Concluído | H207: 1. Concluído
...

Sheet Aux - Pivots2
B2: 1. Modelo Bens imóveis
B5: Âmbito | C5: Pilar III
B6: Sub-âmbito | C6: (Multiple Items)
B7: Tipo de teste | C7: 2. Campo
B9: Count of Campo | C9: Column Labels
B10: Row Labels | C10: 0. Cancelado | D10: 1. Concluído | E10: 2. Em Teste | F10: 4. Validação EF | G10: Grand Total
B11: cd_imv_out_trz_prc_bens_imv | C11: 1 | D11: 13 | E11: 1 | G11: 15
B12: cd_imv_out_trz_cred_prc | C12: 3 | D12: 7 | E12: 10 | G12: 20
B13: cd_imv_out_prc | C13: 3 | D13: 3 | E13: 11 | G13: 17
B14: cd_imv_out_certif | E14: 65 | G14: 65
B15: cd_imv_out_bens | C15: 1 | D15: 27 | E15: 3 | F15: 1 | G15: 32
B16: cd_imv_inp_certif_estimativa | F16: 12 | G16: 12
B17: Grand Total | C17: 8 | D17: 50 | E17: 90 | F17: 13 | G17: 161
B23: Âmbito | C23: Pilar III
B24: Sub-âmbito | C24: (Multiple Items)
B25: Tipo de teste | C25: 2. Campo
B27: Row Labels | C27: Count of Campo
B28: 0. Cancelado | C28: 8
B29: 1. Concluído | C29: 50
B30: 2. Em Teste | C30: 90
B31: 4. Validação EF | C31: 13
B32: Grand Total | C32: 161
B42: 2. Modelo Verde
B44: Âmbito | C44: Pilar III
B45: Sub-âmbito | C45: (Multiple Items)
B46: Tipo de teste | C46: 2. Campo
B48: Count of Campo | C48: Column Labels
B49: Row Labels | C49: 0. Cancelado | D49: 1. Concluído | E49: 2. Em Teste | F49: 3. Pendente de outros desenvolvimentos | G49: 4. Validação EF | H49: 5. Em Correção | I49: 7. Por iniciar | J49: Grand Total
B50: modesg_param_sfcs_taxon_europeia | D50: 18 | G50: 10 | J50: 28
B51: modesg_out_sfcs_taxon_europeia | D51: 1 | G51: 12 | I51: 1 | J51: 14
B52: modesg_out_emss_vcls | D52: 8 | F52: 7 | J52: 15
B53: modesg_out_empr_info_nfin | D53: 2 | F53: 30 | J53: 32
B54: modesg_out_bens_imoveis | D54: 6 | E54: 4 | F54: 8 | J54: 18
B55: modesg_inp_risco_fisico | D55: 6 | J55: 6
B56: modesg_inp_nfrd_alinhamento_tax | H56: 40 | J56: 40
B57: modesg_inp_km_medios_emss_vcls | C57: 3 | H57: 6 | J57: 9
B58: modesg_inp_emss_vcls | H58: 17 | J58: 17
B59: modesg_inp_emss_scib | D59: 15 | E59: 2 | J59: 17
B60: modesg_inp_emss_nace | C60: 7 | H60: 14 | J60: 21
B61: modesg_inp_emss_bens_imoveis | H61: 18 | J61: 18
B62: modesg_inp_empr_excl_paris | D62: 7 | J62: 7
B63: Grand Total | C63: 10 | D63: 63 | E63: 6 | F63: 45 | G63: 22 | H63: 95 | I63: 1 | J63: 242
B68: Âmbito | C68: Pilar III
B69: Sub-âmbito | C69: (Multiple Items)
B70: Tipo de teste | C70: 2. Campo
B72: Row Labels | C72: Count of Campo
B73: 0. Cancelado | C73: 10
B74: 1. Concluído | C74: 63
B75: 2. Em Teste | C75: 6
B76: 3. Pendente de outros desenvolvimentos | C76: 45
B77: 4. Validação EF | C77: 22
B78: 5. Em Correção | C78: 95
B79: 7. Por iniciar | C79: 1
B80: Grand Total | C80: 242
B87: 3. Loan Tape | Pilar III
B90: Âmbito | C90: Pilar III
B91: Sub-âmbito | C91: Pilar III
B92: Tipo de teste | C92: 2. Campo
B94: Count of Campo | C94: Column Labels
B95: Row Labels | C95: 7. Por iniciar | D95: Grand Total
B96: lt002_instrument | C96: 34 | D96: 34
B97: lt003_entity | C97: 43 | D97: 43
B98: lt004_protection | C98: 20 | D98: 20
B99: lt005_instr_ent | C99: 5 | D99: 5
B100: lt006_instr_prot | C100: 5 | D100: 5
B101: lt825_mthd_usd_instrmnt | C101: 10 | D101: 10
B102: lt826_esg_sbsctr | C102: 9 | D102: 9
B103: Grand Total | C103: 126 | D103: 126
B111: Âmbito | C111: Pilar III
B112: Sub-âmbito | C112: Pilar III
B113: Tipo de teste | C113: 2. Campo
B115: Row Labels | C115: Count of Campo
B116: 7. Por iniciar | C116: 126
B117: Grand Total | C117: 126
B129: 4. Loan Tape | Green Dashboard
B132: Âmbito | C132: GD
B133: Tipo de teste | C133: 2. Campo
B135: Count of Campo | C135: Column Labels
B136: Row Labels | C136: 1. Concluído | D136: 2. Em Teste | E136: 3. Pendente de outros desenvolvimentos | F136: Grand Total
B137: lt002_insrmnt | C137: 23 | D137: 26 | E137: 1 | F137: 50
B138: Grand Total | C138: 23 | D138: 26 | E138: 1 | F138: 50
B141: Âmbito | C141: GD
B142: Tipo de teste | C142: 2. Campo
B144: Row Labels | C144: Count of Campo
B145: 1. Concluído | C145: 23
B146: 2. Em Teste | C146: 26
B147: 3. Pendente de outros desenvolvimentos | C147: 1
B148: Grand Total | C148: 50

Sheet Auxiliar
D2: Estimação Horas
B3: Tipologia de testes | D3: Complexidade
B4: Categorização de Testes | C4: Descrição | D4: Baixa | E4: Média | F4: Alta | H4: Baixa | I4: Média | J4: Alta
B5: 1. Teste de universo | C5: 1. Validação de universo de contratos (quando comparado âmbito "CDG" e "PM", e numero de registos) 2. Controlos sobre o desdobramento de chaves nas relações FR-MIS | D5: 8 | E5: 8 | F5: 8 | H5: 1 | I5: 3 | J5: 8
B6: 2. Simulação | C6: Simulação da especificação funcional. Suplementarmente, realizar reuniões de validações e esclarecimentos funcionais junto do negócio/owner. | D6: 2 | E6: 4 | F6: 8 | H6: 1 | I6: 3 | J6: 4
B7: 3. Testes comparativos (Espec. VS Impl.) | C7: A partir da simulação realizada, comparar resultados com a implementação de IT. | D7: 2 | E7: 4 | F7: 8 | H7: 1 | I7: 1 | J7: 2
B8: 4. Validação de parametrizações | C8: A partir da simulação realizada, comparar com as parametrizações implementadas por IT. | D8: 2 | E8: 4 | F8: 8 | H8: 2 | I8: 4 | J8: 4
B9: 5. Teste comparativos com LT | C9: Garantir que a informação do campo da LT-ESTR âmbito 'PM' está espelhado no âmbito 'CDG'. | D9: 1 | E9: 1 | F9: 1
B10: 6. Validação de formatos | C10: Validação de formato de acordo com o que é esperado pela Corporação (incluindo validação de codelists, missing e default values) Validar especificação e controlos da especificação vs o que está implementado | D10: 0.1 | E10: 0.1 | F10: 0.1 | H10: 0.1 | I10: 0.5 | J10: 0.5
B11: 7. Validação de controlos corporativos | C11: Validar controlos corporativos e se a especificação cumpre os requisitos. | D11: 1 | E11: 2 | F11: 2
B12: 8. Teste de Carregamento | C12: Garantir que o carregamento do ficheiro é realizado com sucesso no Front. | D12: 0.5 | E12: 0.5 | F12: 0.5 | H12: 0.5 | I12: 0.5 | J12: 0.5
B13: 9. Teste de Integridade | C13: Garantir integridade entre o ficheiro importado pela equipa de testes e o ficheiro de tecnologia (Ex: Garantir que a informação de todos os campos está correta de acordo com os dados corporativos) | D13: 0.5 | E13: 0.5 | F13: 0.5 | H13: 0.5 | I13: 0.5 | J13: 0.5
B15: Status
B16: 1. Concluído | C16: =_xlfn.NUMBERVALUE(LEFT(B16,1)) -> 1 | D16: 1
A17: Pendente de outros campos/tabelas | B17: 3. Pendente de outros desenvolvimentos | C17: =_xlfn.NUMBERVALUE(LEFT(B17,1)) -> 3 | D17: 0.25
B18: 7. Por iniciar | C18: =_xlfn.NUMBERVALUE(LEFT(B18,1)) -> 7 | D18: 0
B19: 2. Em Teste | C19: =_xlfn.NUMBERVALUE(LEFT(B19,1)) -> 2 | D19: 0.5
A20: Validação da Susana/conceito/alterações | B20: 4. Validação EF | C20: =_xlfn.NUMBERVALUE(LEFT(B20,1)) -> 4 | D20: 0.25
A21: Por IT | B21: 5. Em Correção | C21: =_xlfn.NUMBERVALUE(LEFT(B21,1)) -> 5 | D21: 0.25
B22: 6. Em implementação (re-especificação) | C22: =_xlfn.NUMBERVALUE(LEFT(B22,1)) -> 6 | D22: 0.25
A23: Campo eliminado | B23: 0. Cancelado | C23: =_xlfn.NUMBERVALUE(LEFT(B23,1)) -> 0 | D23: 0
