Workbook
Name _b81494: #REF!
Name Impact_flag: #REF!
Name Index: #REF!
Name IndexArray: #REF!
Name IQ_CH: 110000
Name IQ_CQ: 5000
Name IQ_CY: 10000
Name IQ_DAILY: 500000
Name IQ_FH: 100000
Name IQ_FQ: 500
Name IQ_FY: 1000
Name IQ_LTM: 2000
Name IQ_MONTH: 15000
Name IQ_NTM: 6000
Name IQ_WEEK: 50000
Name IQ_YTD: 3000
Name LatestChange: #REF!
Name LatestPerson: #REF!
Name LatestVersion: #REF!
Name ModelName: #REF!
Name Quality_flag: #REF!
Name Risk_flag: #REF!
Name Status_Checking: #REF!
Name Status_Overall: #REF!
Name Status_Update: #REF!
Name Team: #REF!
Name YesNo: #REF!

Sheet SCIB
B2: BUSINESS LOANS: EMISSIONS CALCULATED FROM SCIB INFO.
E7: To be filled out by HQ
B8: GLCS Code | C8: NACE CODE | D8: Gross Carrying Amount (M€) | E8: SCOPE 1 REPORTED | F8: SCOPE 2 REPORTED | G8: SCOPE 3 REPORTED | H8: Total Debt | I8: Total Equity | J8: SCOPE 1 FINANCED EMISSIONS | K8: SCOPE 2 FINANCED EMISSIONS | L8: SCOPE 3 FINANCED EMISSIONS
B9: IBR00 | C9: 35.11 | D9: 1000 | E9: 11270639 | F9: 1893116 | G9: 55597710 | H9: 51525 | I9: 58114 | J9: 102797.72 | K9: 17266.812 | L9: 507097.93
G25: Dúvidas | H25: SCIB com DQS4 ou DQS5 entra aqui? // Se scope 1 for DQS2, mas scope 3 for DQS5 entra?
B26: *Units need to fill out the columns in red, columns in grey will be filled out by HQ | H26: SCIB pode ser cruzado com input por clei -> Estes casos, assumo o KGL do input corporativo?
G27: Assumption | H27: Não entra emissões calculadas por MVL ou RE, mesmo que o cliente seja SCIB
H28: Nace vou tirar letra e último ponto

Sheet DQS4
B2: BUSINESS LOANS: EMISSIONS ESTIMATED BY PCAF DQS4
E7: To be filled out by HQ
B8: Region | C8: NACE CODE | D8: Gross Carrying Amount (in Million €) | E8: PCAF FACTOR S1 | F8: PCAF FACTOR S2 | G8: PCAF FACTOR S3 | H8: Total Debt (in Million €) | I8: Total Equity (in Million €) | J8: Total Revenue (in Million €) | K8: SCOPE 1 FINANCED EMISSIONS | L8: SCOPE 2 FINANCED EMISSIONS | M8: SCOPE 3 FINANCED EMISSIONS
B9: European Union | C9: 06.10 | D9: 1000 | E9: 1571.88 | F9: 204.756 | G9: 786.716 | H9: 500 | I9: 1000 | J9: 600 | K9: 1.7465333 | L9: 0.22750667 | M9: 0.87412889
B26: *Units need to fill out the columns in red, columns in grey will be filled out by HQ | F26: Dúvidas | G26: DQS4 de MVL e RE entra aqui? Se entrar, puxo valor para debt, equity e revenues, ou vai a zero? | H26: Não entra

Sheet Sheet6
B2: origem_scp1_emss | C2: origem_scp2_emss | D2: origem_scp3_emss
B3: BCL_DQS1_SCIB | C3: BCL_DQS2_SCIB | D3: BCL_DQS1_SCIB
B4: BCL_DQS1_SCIB | C4: BCL_DQS1_SCIB | D4: BCL_DQS1_SCIB
B5: BCL_DQS1_SCIB | C5: BCL_DQS2_SCIB | D5: BCL_DQS4_SCIB
B6: BCL_DQS1_SCIB | C6: BCL_DQS1_SCIB | D6: BCL_DQS4_SCIB
B7: BCL_DQS2_SCIB | C7: BCL_DQS2_SCIB | D7: BCL_DQS4_SCIB
B8: BCL_DQS4_3A | C8: BCL_DQS4_3A | D8: BCL_DQS4_3A
B9: BCL_DQS4_SCIB | C9: BCL_DQS2_SCIB | D9: BCL_DQS4_SCIB
B10: BCL_DQS4_SCIB | C10: BCL_DQS1_SCIB | D10: BCL_DQS4_SCIB
B11: BCL_DQS5_3B | C11: BCL_DQS5_3B | D11: BCL_DQS5_3B
B12: MISS | C12: MISS | D12: Nao Aplicavel
B13: MISS | C13: MISS | D13: MISS
... B29: RE_DQS5_3 | C29: RE_DQS5_3 | D29: Nao Aplicavel

Sheet DQS5
B2: BUSINESS LOANS: EMISSIONS ESTIMATED BY PCAF DQS5
E7: To be filled out by HQ
B8: Region | C8: NACE CODE | D8: Gross Carrying Amount (in Million €) | E8: PCAF FACTOR S1 | F8: PCAF FACTOR S2 | G8: PCAF FACTOR S3 | H8: SCOPE 1 FINANCED EMISSIONS | I8: SCOPE 2 FINANCED EMISSIONS | J8: SCOPE 3 FINANCED EMISSIONS
B9: European Union | C9: 06.10 | D9: 1000 | E9: 1571.88 | F9: 204.756 | G9: 786.716 | H9: 1.7465333 | I9: 0.22750667 | J9: 0.87412889
B26: *Units need to fill out the columns in red, columns in grey will be filled out by HQ

Sheet Auxiliar >>

Sheet 1. Input Junho 2025
A1: ccli_kgl | B1: nome_grupo | C1: isin | D1: clei | E1: scp1_emss | F1: scp2_emss | G1: scp3_emss | H1: score_scp1 | I1: score_scp2 | J1: score_scp3 | K1: ano_info | L1: origem_scp1 | M1: origem_scp2 | N1: origem_scp3 | O1: divida_total | P1: capital_proprio
A2: 3MGRG | B2: 3M | C2: US88579Y1010 | D2: LUZQVYP4VS22CLWDAR65 | E2: 2420000 | F2: 1460000 | G2: 72852902.489811 | H2: 1 | I2: 2 | J2: 4 | K2: 2023 | L2: Reported | M2: Reported | N2: Estimated | O2: 16894.94
A3: 22A2A | B3: A2A | C3: IT0001233417 | D3: 81560076E3944316DB24 | E3: 8882175 | F3: 183507 | G3: 27077885.803923 | H3: 1 | I3: 1 | J3: 4 | K3: 2023 | L3: Reported | M3: Reported | N3: Estimated | O3: 13275
A4: ABBBG | B4: ABB | C4: CH0012221716 | D4: 5493000LKVGOO9PELI61 | E4: 156000 | F4: 305000 | G4: 99031733.625942 | H4: 1 | I4: 1 | J4: 4 | K4: 2023 | L4: Reported | M4: Reported | N4: Estimated | O4: 22259.97
A5: ABTGG | B5: ABBOTT LABORATORIES | C5: US0028241000 | D5: HQD377W2YR662HK5JX27 | E5: 530000 | F5: 476000 | G5: 11963516 | H5: 1 | I5: 1 | J5: 4 | K5: 2023 | L5: Reported | M5: Reported | N5: Estimated | O5: 60807.55
A6: ABVIE | B6: ABBVIE GROUP | C6: US00287Y1091 | D6: FR5LCKFTG8054YNNRU85 | E6: 342607 | F6: 271055 | G6: 8063583.305804 | H6: 1 | I6: 1 | J6: 4 | K6: 2023 | L6: Reported | M6: Reported | N6: Estimated | O6: 68706.87
A7: 5CUMG | B7: ACCIONA | C7: ES0125220311 | D7: 54930002KP75TLLLNO21 | E7: 159652 | F7: 139733 | G7: 15545375.935379 | H7: 1 | I7: 1 | J7: 4 | K7: 2023 | L7: Reported | M7: Reported | N7: Estimated | O7: 18968
A8: 5ACXG | B8: ACCOR | C8: FR0000120404 | D8: 969500QZC2Q0TK11NV07 | E8: 344000 | F8: 2584000 | G8: 2169583.250466 | H8: 1 | I8: 1 | J8: 4 | K8: 2023 | L8: Reported | M8: Reported | N8: Estimated | O8: 9226
A9: ACRXG | B9: ACERINOX | C9: ES0132105018 | D9: 95980020140005582721 | E9: 872253 | F9: 1581947 | G9: 3735287.887073 | H9: 1 | I9: 1 | J9: 4 | K9: 2023 | L9: Reported | M9: Reported | N9: Estimated | O9: 4976
A10: CGYNG | B10: ACS - DRAGADOS | C10: ES0167050915 | D10: 95980020140005558665 | E10: 389195 | F10: 121602 | G10: 10332395 | H10: 1 | I10: 1 | J10: 4 | K10: 2023 | L10: Reported | M10: Reported | N10: Estimated | O10: 10423.53
A11: AB7WK | B11: ADECOAGRO | C11: LU0584671464 | D11: 529900Q00UR5LFELO811 | E11: 171338 | F11: 18643 | G11: 637667.091714 | H11: 4 | I11: 2 | J11: 4 | K11: 2023 | L11: Estimated | M11: Reported | N11: Estimated | O11: 2434.85
A12: AAP5K | B12: ADVANCE AUTO PARTS INC | C12: US00751Y1064 | D12: 529900UCNQ5H9FSL0Y70 | E12: 173157 | F12: 168878 | G12: 6065722.982578 | H12: 1 | I12: 1 | J12: 4 | K12: 2023 | L12: Reported | M12: Reported | N12: Estimated | O12: 6080.94
A13: AENAK | B13: AENA | C13: ES0105046009 | D13: 959800R7QMXKF0NFMT29 | E13: 19976 | F13: 164604 | G13: 3770063.24 | H13: 1 | I13: 1 | J13: 4 | K13: 2023 | L13: Reported | M13: Reported | N13: Estimated | O13: 15527.07
A14: AERCG | B14: AERCAP, GR | C14: NL0000687663 | D14: 549300SZYINBBLJQU475 | E14: 316 | F14: 265 | G14: 52500783.709817 | H14: 2 | I14: 2 | J14: 4 | K14: 2023 | L14: Reported | M14: Reported | N14: Estimated | O14: 60205.55
A15: AEYMX | B15: AEROMEXICO | C15: MX01AE010005 | E15: 3823270 | F15: 4364 | G15: 2012140.983574 | H15: 2 | I15: 1 | J15: 4 | K15: 2023 | L15: Reported | M15: Reported | N15: Estimated | O15: 3562.17
A16: AEPAR | B16: AEROPORTS DE PARIS | C16: FR0010340141 | D16: 969500PJMBSFHYC37989 | E16: 77785 | F16: 70609 | G16: 23315053 | H16: 1 | I16: 1 | J16: 4 | K16: 2023 | L16: Reported | M16: Reported | N16: Estimated | O16: 16225
A17: 5AEBG | B17: AES | C17: US00130H1059 | D17: 2NUNNB7D43COUIRE5295 | E17: 40011490 | F17: 515129 | G17: 2450793.622109 | H17: 2 | I17: 2 | J17: 4 | K17: 2023 | L17: Reported | M17: Reported | N17: Estimated | O17: 37533.09
A18: AGIZG | B18: AGILITY. TRISTAR | C18: KW0EQ0601041 | D18: 549300C16Q6C2NMAI063 | E18: 319009 | F18: 69238 | G18: 662065.568053 | H18: 4 | I18: 2 | J18: 4 | K18: 2023 | L18: Estimated | M18: Reported | N18: Estimated | O18: 11002.93
A19: 0W20G | B19: AIR FRANCE KLM | C19: FR001400J770 | D19: 969500AQW31GYO8JZD66 | E19: 22620100 | F19: 50700 | G19: 9621365.772297 | H19: 1 | I19: 1 | J19: 4 | K19: 2023 | L19: Reported | M19: Reported | N19: Estimated | O19: 15462
A20: ARLCG | B20: AIR LEASE CORPORATION | C20: US00912X3026 | D20: 5493004NW4M4P8TMMK63 | E20: 5599 | F20: 255 | G20: 47954246.865602 | H20: 2 | I20: 2 | J20: 4 | K20: 2023 | L20: Reported | M20: Reported | N20: Estimated | O20: 26702.55
A21: AIRPG | B21: AIR PRODUCTS | C21: US0091581068 | D21: 7QEON6Y1RL5XR3R1W237 | E21: 16800000 | F21: 9700000 | G21: 22395466.965968 | H21: 1 | I21: 1 | J21: 4 | K21: 2023 | L21: Reported | M21: Reported | N21: Estimated | O21: 32457
A22: 00027 | B22: AIR TRANSPORT SERVICES GROUP, GR | C22: US00922R1059 | D22: 5493000F3MSFGIXTQE27 | E22: 1606250.46 | F22: 4653.93 | G22: 720635.723355 | H22: 4 | I22: 4 | J22: 4 | K22: 2023 | L22: Estimated | M22: Estimated | N22: Estimated | O22: 2970.91
A23: 5EEDG | B23: AIRBUS | C23: NL0000235190 | D23: MINO79WLOO247M1IL051 | E23: 554801 | F23: 301809 | G23: 439424869.893171 | H23: 1 | I23: 1 | J23: 4 | K23: 2023 | L23: Reported | M23: Reported | N23: Estimated | O23: 33975
A24: 5B50G | B24: AKZO NOBEL | C24: NL0013267909 | D24: 724500XYIJUGXAA5QD70 | E24: 60130 | F24: 195300 | G24: 14427286.40937 | H24: 1 | I24: 2 | J24: 4 | K24: 2023 | L24: Reported | M24: Reported | N24: Estimated | O24: 10184
A25: ALBEG | B25: ALBEMARLE | C25: US0126531013 | D25: HDBLS2Q6GV1LSKQPBS54 | E25: 617636 | F25: 334379 | G25: 2305424.699118 | H25: 1 | I25: 1 | J25: 4 | K25: 2023 | L25: Reported | M25: Reported | N25: Estimated | O25: 13328.83
A26: DOALG | B26: ALDO | E26: 520 | F26: 5808 | G26: 244653 | H26: 1 | I26: 1 | J26: 1 | K26: 2023 | L26: Reported | M26: Reported | N26: Reported | O26: 385827.61
A27: ALTCG | B27: ALEATICA | C27: MX01AL1C0003 | D27: 529900YI9E9NDAYEDU63 | E27: 11152 | F27: 69862 | G27: 112438.80897 | H27: 4 | I27: 2 | J27: 4 | K27: 2023 | L27: Estimated | M27: Reported | N27: Estimated | O27: 12365.31
A28: ALFAK | B28: ALFA LAVAL, GR | D28: 549300ZEHHN9SLH1F270 | E28: 16004 | F28: 62763 | G28: 31587541 | H28: 1 | I28: 1 | J28: 1 | K28: 2023 | L28: Reported | M28: Reported | N28: Reported | O28: 4875.89
A29: BNYLD | B29: ALGONQUIN POWER | C29: CA0158571053 | D29: 549300K5VIUTJXQL7X75 | E29: 2542820 | F29: 89200 | G29: 5798987.471637 | H29: 1 | I29: 1 | J29: 4 | K29: 2023 | L29: Reported | M29: Reported | N29: Estimated | O29: 12425.84
A30: ALING | B30: ALIANSCE | C30: BRALSOACNOR5 | E30: 21019 | F30: 5801 | G30: 59197 | H30: 1 | I30: 1 | J30: 4 | K30: 2023 | L30: Reported | M30: Reported | N30: Estimated | O30: 3285.49
A31: LBBRP | B31: ALIBABA GROUP? | C31: US01609W1027 | D31: 5493001NTNQJDH60PM02 | E31: 928939 | F31: 5141880 | G31: 18957231.899696 | H31: 1 | I31: 1 | J31: 4 | K31: 2023 | L31: Reported | M31: Reported | N31: Estimated | O31: 173822.81
A32: AGRLG | B32: ALLEGRO | C32: LU2237380790 | D32: 222100VRLXV3FPMG4982 | E32: 1421755 | F32: 21414 | G32: 180170.653572 | H32: 2 | I32: 2 | J32: 4 | K32: 2023 | L32: Reported | M32: Reported | N32: Estimated | O32: 3847.48
A33: LPRGT | B33: ALPARGATAS | C33: BRALPAACNPR7 | D33: 254900LU3422XPKEQJ79 | E33: 17743 | F33: 5528 | G33: 599477.57 | H33: 2 | I33: 2 | J33: 4 | K33: 2023 | L33: Reported | M33: Reported | N33: Estimated | O33: 878.99
A34: GOOGL | B34: ALPHABET INC | C34: US02079K3059 | D34: 5493006MHB84DD0ZWV18 | E34: 91200 | F34: 8045400 | G34: 14356503 | H34: 1 | I34: 1 | J34: 4 | K34: 2023 | L34: Reported | M34: Reported | N34: Estimated | O34: 339978.83
A35: ALPIK | B35: ALPIQ GROUP | D35: 5299006COKGB66PUHW42 | E35: 4722123.57 | F35: 377430.94 | G35: 9546595.544146 | H35: 4 | I35: 4 | J35: 4 | K35: 2023 | L35: Estimated | M35: Estimated | N35: Estimated | O35: 6619.96
A36: GALSG | B36: ALSEA | C36: MXP001391012 | D36: 4469000001BJLPKNUN21 | E36: 82888 | F36: 112932 | G36: 2271523.206893 | H36: 2 | I36: 2 | J36: 4 | K36: 2023 | L36: Reported | M36: Reported | N36: Estimated | O36: 2857
A37: 5AXMH | B37: ALSTOM | C37: FR0010220475 | D37: 96950032TUYMW11FB530 | E37: 93970 | F37: 133651 | G37: 44972826.283037 | H37: 1 | I37: 1 | J37: 4 | K37: 2023 | L37: Reported | M37: Reported | N37: Estimated | O37: 13433
A38: ALTRG | B38: ALTRIA GROUP | C38: US02209S1033 | D38: XSGZFLO9YTNO9VCQV219 | E38: 123892 | F38: 114625 | G38: 4476014 | H38: 1 | I38: 1 | J38: 1 | K38: 2023 | L38: Reported | M38: Reported | N38: Reported | O38: 23991.53
A39: AMNHG | B39: ALUMINUM CORP OF CHINA | C39: CNE1000001T8 | D39: 529900TKZUWQLIQN6T48 | E39: 7780179 | F39: 3721076 | G39: 33656524.357213 | H39: 4 | I39: 2 | J39: 4 | K39: 2023 | L39: Estimated | M39: Reported | N39: Estimated | O39: 23282.15
A40: ALUOG | B40: ALUPAR | C40: BRALUPCDAM15 | E40: 1975 | F40: 226 | G40: 536612.751844 | H40: 2 | I40: 2 | J40: 4 | K40: 2023 | L40: Reported | M40: Reported | N40: Estimated | O40: 3804.48
A41: 5XADG | B41: AMADEUS, GR | C41: ES0109067019 | D41: 9598004A3FTY3TEHHN09 | E41: 1600 | F41: 35257 | G41: 284078.118982 | H41: 1 | I41: 1 | J41: 4 | K41: 2023 | L41: Reported | M41: Reported | N41: Estimated | O41: 8438.1
A42: AMGGI | B42: AMAGGI | D42: 5493009U13BC8YV3EX21 | E42: 1184985 | F42: 21675 | G42: 5017606.57 | H42: 1 | I42: 1 | J42: 1 | K42: 2023 | L42: Reported | M42: Reported | N42: Reported | O42: 5128.04
A43: AMAZO | B43: AMAZON | C43: US0231351067 | D43: ZXTILKJKG63JELOEG630 | E43: 14270000 | F43: 12768034 | G43: 56871574.642786 | H43: 1 | I43: 1 | J43: 4 | K43: 2023 | L43: Reported | M43: Reported | N43: Estimated | O43: 424824.1
A44: AMCOG | B44: AMCOR PLC | C44: JE00BJ1F3079 | D44: 549300GSODGFCDQ3DI89 | E44: 520069 | F44: 1318669 | G44: 9942364.215251 | H44: 1 | I44: 1 | J44: 4 | K44: 2023 | L44: Reported | M44: Reported | N44: Estimated | O44: 10920.64
A45: ATELG | B45: AMERICA MOVIL | C45: MX01AM050019 | D45: 5493000FNR3UCEAONM59 | E45: 305501 | F45: 1786873 | G45: 2606779 | H45: 1 | I45: 1 | J45: 4 | K45: 2023 | L45: Reported | M45: Reported | N45: Estimated | O45: 56272.6
A46: ATWRK | B46: AMERICAN TOWER CORPORATION | C46: US03027X1000 | D46: 5493006ORUSIL88JOE18 | E46: 628716 | F46: 571425 | G46: 3925696.003332 | H46: 2 | I46: 2 | J46: 4 | K46: 2023 | L46: Reported | M46: Reported | N46: Estimated | O46: 51593.24
A47: AQQKG | B47: AMERISOURCEBERGEN | C47: US03073E1055 | D47: AI8GXW8LG5WK7E9UD086 | E47: 124045 | F47: 97356 | G47: 25556384 | H47: 1 | I47: 1 | J47: 4 | K47: 2023 | L47: Reported | M47: Reported | N47: Estimated | O47: 64586.04
A48: AMICG | B48: AMICA | C48: PLAMICA00010 | D48: 259400IUQZHB2GOLIV25 | E48: 9034 | F48: 15502 | G48: 1317399.596007 | H48: 2 | I48: 2 | J48: 4 | K48: 2023 | L48: Reported | M48: Reported | N48: Estimated | O48: 300.12
A49: GAAMG | B49: AMORIM | C49: PTCOR0AE0006 | D49: 213800J5M11TDEP3LQ76 | E49: 5687 | F49: 66087 | G49: 670480.065494 | H49: 1 | I49: 1 | J49: 4 | K49: 2023 | L49: Reported | M49: Reported | N49: Estimated | O49: 1030.8
A50: APFNG | B50: AMPLIFON | C50: IT0004056880 | D50: ZYXJDNVM2JI3VBM8G556 | E50: 5745 | F50: 10341 | G50: 138646.577413 | H50: 1 | I50: 1 | J50: 4 | K50: 2023 | L50: Reported | M50: Reported | N50: Estimated | O50: 2894.36
A51: AMSEG | B51: AMREST | C51: ES0105375002 | D51: 259400T6ZDQIMDBGDN42 | E51: 51583 | F51: 98752 | G51: 1451154.817988 | H51: 4 | I51: 2 | J51: 4 | K51: 2023 | L51: Estimated | M51: Reported | N51: Estimated | O51: 1975.7
A52: ANHOL | B52: ANA HOLDINGS | C52: JP3429800000 | D52: 5493008IRKIY0G3TE305 | E52: 7694587 | F52: 65855 | G52: 2818458 | H52: 1 | I52: 1 | J52: 1 | K52: 2023 | L52: Reported | M52: Reported | N52: Reported | O52: 15557.81
A53: 5AG1G | B53: ANGLO AMERICAN | C53: GB00B1XZS820 | D53: 549300S9XF92D1X8ME43 | E53: 8262027 | F53: 5002161 | G53: 104280876.350962 | H53: 1 | I53: 1 | J53: 4 | K53: 2023 | L53: Reported | M53: Reported | N53: Estimated | O53: 45598.92
A54: ANOIG | B54: ANTOLIN | E54: 24201 | F54: 171407 | G54: 2074690.528369 | H54: 2 | I54: 2 | J54: 4 | K54: 2023 | L54: Reported | M54: Reported | N54: Estimated | O54: 1596.16
A55: AGMPA | B55: APOLLO GLOBAL MANAGEMENT | C55: US03769M1062 | D55: 254900LMFT1CY9IYB476 | E55: 45668.54 | F55: 1185041.11 | G55: 393530.815456 | H55: 4 | I55: 4 | J55: 4 | K55: 2023 | L55: Estimated | M55: Estimated | N55: Estimated | O55: 363727.8
A56: APPLG | B56: APPLE | C56: US0378331005 | D56: HWUPKR0MPOU8FGXBT394 | E56: 55200 | F56: 1065405 | G56: 24109534.570886 | H56: 1 | I56: 1 | J56: 4 | K56: 2023 | L56: Reported | M56: Reported | N56: Estimated | O56: 169410.46
A57: ARAMX | B57: ARAMARK | C57: US03852U1060 | D57: 549300MR6PG2DWZUIL39 | E57: 338397 | F57: 52589 | G57: 6022619.35 | H57: 2 | I57: 2 | J57: 4 | K57: 2023 | L57: Reported | M57: Reported | N57: Estimated | O57: 8290.2
A58: EBARG | B58: ARCA CONTINENTAL | C58: MX01AC100006 | D58: 254900U2BSJCQHJCXN24 | E58: 320635 | F58: 179312 | G58: 4426644.95 | H58: 1 | I58: 1 | J58: 4 | K58: 2023 | L58: Reported | M58: Reported | N58: Estimated | O58: 10391.71
A59: ACE0G | B59: ARCELOR - MITTAL | C59: LU1598757687 | D59: 2EULGUTUI56JI9SAL165 | E59: 113434783 | F59: 6157041 | G59: 80093319.285629 | H59: 1 | I59: 1 | J59: 4 | K59: 2023 | L59: Reported | M59: Reported | N59: Estimated | O59: 60492.81
A60: AR4HD | B60: ARCHER-DANIELS-MIDLAND | C60: US0394831020 | D60: 549300LO13MQ9HYSTR83 | E60: 13500000 | F60: 2130000 | G60: 111926488.732468 | H60: 1 | I60: 1 | J60: 4 | K60: 2023 | L60: Reported | M60: Reported | N60: Estimated | O60: 32695.51
A61: SAGEX | B61: ARCOS DORADOS HOLDINGS | C61: VGG0457F1071 | D61: 54930023P2MIZN13DQ85 | E61: 175037 | F61: 110693 | G61: 2360973.797396 | H61: 4 | I61: 1 | J61: 4 | K61: 2023 | L61: Estimated | M61: Reported | N61: Estimated | O61: 2147.09
A62: ARKEG | B62: ARKEMA | C62: FR0010313833 | D62: 9695000EHMS84KKP2785 | E62: 1330000 | F62: 964300 | G62: 12146730.72485 | H62: 1 | I62: 1 | J62: 4 | K62: 2023 | L62: Reported | M62: Reported | N62: Estimated | O62: 12315
A63: AROUN | B63: AROUNDTOWN SA | C63: LU1673108939 | D63: 529900H4DWG3KWMBMQ39 | E63: 13534 | F63: 28525 | G63: 638120.781304 | H63: 4 | I63: 1 | J63: 4 | K63: 2023 | L63: Estimated | M63: Reported | N63: Estimated | O63: 29713.2
A64: AEIMK | B64: ARROW ELECTRONICS, INC. | C64: US0427351004 | D64: 549300YNNLBXT8N8R512 | E64: 11675 | F64: 28437 | G64: 14513778 | H64: 2 | I64: 2 | J64: 4 | K64: 2023 | L64: Reported | M64: Reported | N64: Estimated | O64: 8876.94
A65: DVCED | B65: ASE TECHNOLOGY HOLDING CO., LTD | C65: TW0003711008 | D65: 300300GO8QHPMV87NZ73 | E65: 90993 | F65: 2171847 | G65: 58343071.65607 | H65: 1 | I65: 1 | J65: 4 | K65: 2023 | L65: Reported | M65: Reported | N65: Estimated | O65: 16023.17
A66: AM0LG | B66: ASML | C66: NL0010273215 | D66: 724500Y6DUVHQD6OXN27 | E66: 17300 | F66: 193000 | G66: 13552704.346985 | H66: 1 | I66: 1 | J66: 4 | K66: 2023 | L66: Reported | M66: Reported | N66: Estimated | O66: 23541.3
A67: ASSGG | B67: ASSICURAZIONI GENERALI SPA GR | C67: IT0000062072 | D67: 549300X5UKJVE386ZB61 | E67: 40789 | F67: 62638 | G67: 278740.962682 | H67: 1 | I67: 1 | J67: 4 | K67: 2023 | L67: Reported | M67: Reported | N67: Estimated | O67: 538647
A68: ASB1G | B68: ASSOCIATED BRITISH FOODS | C68: GB0006731235 | D68: GBQKSY6W7G0OHCQ8OQ72 | E68: 2408430 | F68: 698978 | G68: 7940302 | H68: 1 | I68: 1 | J68: 4 | K68: 2023 | L68: Reported | M68: Reported | N68: Estimated | O68: 18033.72
A69: 7B1LK | B69: ASSURA PLC | E69: 1505 | F69: 13447 | G69: 2760636 | H69: 1 | I69: 1 | J69: 1 | K69: 2023 | L69: Reported | M69: Reported | N69: Reported | O69: 6980.32
A70: 0A30G | B70: ASTM - GAVIO | C70: IT0000084027 | D70: 8156003F2286CFA55E20 | E70: 85879 | F70: 41563 | G70: 2502482.997973 | H70: 1 | I70: 1 | J70: 4 | K70: 2023 | L70: Reported | M70: Reported | N70: Estimated | O70: 13939.81
A71: ASTZG | B71: ASTRA ZENECA, GR | C71: GB0009895292 | D71: PY6ZZQWO2IZFZC3IOL08 | E71: 245117 | F71: 195126 | G71: 6369757 | H71: 1 | I71: 1 | J71: 1 | K71: 2023 | L71: Reported | M71: Reported | N71: Reported | O71: 68656.82
A72: AT&TG | B72: AT&T | C72: US00206R1023 | D72: 549300Z40J86GGSTL398 | E72: 917036 | F72: 4962516 | G72: 12312996 | H72: 1 | I72: 1 | J72: 1 | K72: 2023 | L72: Reported | M72: Reported | N72: Reported | O72: 255430.96
A73: ATEZG | B73: ATENTO | E73: 5527.06 | F73: 20348.18 | G73: 176778.53 | H73: 2 | I73: 2 | J73: 1 | K73: 2023 | L73: Reported | M73: Reported | N73: Reported | O73: 696.23
A74: ATTAN | B74: ATLANTICA SUSTAINABLE INFRASTRUCTURE | C74: GB00BLP5YB54 | D74: 549300ITBBGKJ651R879 | E74: 1775010 | F74: 236135 | G74: 699463 | H74: 1 | I74: 1 | J74: 1 | K74: 2023 | L74: Reported | M74: Reported | N74: Reported | O74: 6427.61
A75: ATOSG | B75: ATOS | C75: FR0000051732 | D75: 5493001EZOOA66PTBR68 | E75: 20517 | F75: 130592 | G75: 1582219.911638 | H75: 4 | I75: 1 | J75: 4 | K75: 2023 | L75: Estimated | M75: Reported | N75: Estimated | O75: 3610
A76: AUREN | B76: AUREN | C76: BRAUREACNOR9 | E76: 4423 | F76: 31 | G76: 180331.906215 | H76: 1 | I76: 1 | J76: 4 | K76: 2023 | L76: Reported | M76: Reported | N76: Estimated | O76: 6487.58
A77: AUPIG | B77: AUTOSTRADE PER L ITALIA SPA | D77: 815600149448CEB9B230 | E77: 56589 | F77: 56064 | G77: 1706758 | H77: 1 | I77: 1 | J77: 4 | K77: 2023 | L77: Reported | M77: Reported | N77: Estimated | O77: 15359.13
A78: AUTZK | B78: AUTOZONE INC | C78: US0533321024 | D78: GA3JGKJ41LJKXDN23E90 | E78: 253026 | F78: 200079 | G78: 5395009.070638 | H78: 2 | I78: 2 | J78: 4 | K78: 2023 | L78: Reported | M78: Reported | N78: Estimated | O78: 12176.57
A79: AVNEG | B79: AVNET, INC. | E79: 7233 | F79: 22449 | G79: 9647314 | H79: 2 | I79: 2 | J79: 4 | K79: 2023 | L79: Reported | M79: Reported | N79: Estimated | O79: 7750.83
A80: AXPHG | B80: AXPO HOLDING | E80: 987869 | F80: 335844 | G80: 4245034.717113 | H80: 1 | I80: 1 | J80: 4 | K80: 2023 | L80: Reported | M80: Reported | N80: Estimated | O80: 19892.09
A81: 12X0G | B81: AZUL LINHAS AEREAS | C81: BRAZULACNPR4 | D81: 549300Z0MWZ57Q9RR205 | E81: 3089851 | F81: 316 | G81: 1440920.619675 | H81: 1 | I81: 1 | J81: 4 | K81: 2023 | L81: Reported | M81: Reported | N81: Estimated | O81: 5840.98
A82: BABCK | B82: BABCOCK INTERNATIONAL | C82: GB0009697037 | D82: 213800TSKOLX4EU6L377 | E82: 127167 | F82: 46114 | G82: 961622.677502 | H82: 1 | I82: 1 | J82: 4 | K82: 2023 | L82: Reported | M82: Reported | N82: Estimated | O82: 1693.04
A83: BAESS | B83: BAE SYSTEMS | C83: GB0002634946 | D83: 8SVCSVKSGDWMW2QHOH83 | E83: 113089 | F83: 281182 | G83: 76585567.157709 | H83: 1 | I83: 1 | J83: 4 | K83: 2023 | L83: Reported | M83: Reported | N83: Estimated | O83: 26639.4
A84: BAHUG | B84: BAKER HUGHES INC | C84: US05722G1004 | E84: 1340525.34 | F84: 401317.2 | G84: 3733950.684326 | H84: 4 | I84: 4 | J84: 4 | K84: 2023 | L84: Estimated | M84: Estimated | N84: Estimated | O84: 22860.58
A85: BCKVK | B85: BALL CORPORATION., GR | C85: US0584981064 | D85: 0BGI85ALH27ZJP15DY16 | E85: 449608 | F85: 803219 | G85: 15435517.547286 | H85: 1 | I85: 1 | J85: 4 | K85: 2023 | L85: Reported | M85: Reported | N85: Estimated | O85: 11499.11
A86: LATLP | B86: BANCO INTERNACIONAL DEL PERU - INTERBANK, GR (GR) | C86: PEP148001006 | D86: 5493001TRCGXJLRLHN14 | E86: 1768 | F86: 3715 | G86: 17850.467615 | H86: 4 | I86: 2 | J86: 4 | K86: 2023 | L86: Estimated | M86: Reported | N86: Estimated | O86: 5167.03
A87: BGIAK | B87: BARNES GROUP, INC | C87: US0678061096 | D87: G1MSYD2DQZX30V5DMX12 | E87: 5170 | F87: 41640 | G87: 6745301.819799 | H87: 2 | I87: 2 | J87: 4 | K87: 2023 | L87: Reported | M87: Reported | N87: Estimated | O87: 2447.92
A88: BDQ1G | B88: BARRATT DEVELOPMENTS PLC, GR | C88: GB0000811801 | D88: 2138006R85VEOF5YNK29 | E88: 23234 | F88: 4802 | G88: 3802591 | H88: 1 | I88: 1 | J88: 1 | K88: 2023 | L88: Reported | M88: Reported | N88: Reported | O88: 6851.15
A89: GOLDG | B89: BARRICK GOLD | C89: CA0679011084 | D89: 0O4KBQCJZX82UKGCBV73 | E89: 5981000 | F89: 1419000 | G89: 9148695.893907 | H89: 1 | I89: 1 | J89: 4 | K89: 2023 | L89: Reported | M89: Reported | N89: Estimated | O89: 37068.19
A90: 5BQRG | B90: BARRY CALLEBAUT | C90: CH0009002962 | D90: 213800Y5RWKLDPUTT265 | E90: 103877 | F90: 271861 | G90: 8476011.049276 | H90: 1 | I90: 1 | J90: 4 | K90: 2023 | L90: Reported | M90: Reported | N90: Estimated | O90: 8118.44
A91: BASFG | B91: BASF | C91: DE000BASF111 | D91: 529900PM64WH8AF1E917 | E91: 16555000 | F91: 3558000 | G91: 107674512.545904 | H91: 1 | I91: 1 | J91: 4 | K91: 2023 | L91: Reported | M91: Reported | N91: Estimated | O91: 60878
A92: ITBAG | B92: BASIC FIT | C92: NL0011872650 | D92: 724500HUXGTQC07CAZ61 | E92: 5318 | F92: 11371 | G92: 463576.902865 | H92: 4 | I92: 2 | J92: 4 | K92: 2023 | L92: Estimated | M92: Reported | N92: Estimated | O92: 3240.3
A93: BXTRG | B93: BAXTER INTERNATIONAL | C93: US0718131099 | D93: J5OIVXX3P24RJRW5CK77 | E93: 373000 | F93: 413000 | G93: 5915000 | H93: 1 | I93: 1 | J93: 1 | K93: 2023 | L93: Reported | M93: Reported | N93: Reported | O93: 19705.47
A94: BAYHG | B94: BAYER | C94: DE000BAY0017 | D94: 549300J4U55H3WP1XT59 | E94: 1910000 | F94: 1560000 | G94: 22379761.041394 | H94: 1 | I94: 1 | J94: 4 | K94: 2023 | L94: Reported | M94: Reported | N94: Estimated | O94: 72856
A95: BEDIG | B95: BECTON DICKINSON | C95: US0758871091 | D95: ICE2EP6D98PQUILVRZ91 | E95: 150535 | F95: 442260 | G95: 3660347.634078 | H95: 2 | I95: 2 | J95: 4 | K95: 2023 | L95: Reported | M95: Reported | N95: Estimated | O95: 45054.14
A96: BEFEG | B96: BEFESA | C96: LU1704650164 | D96: 222100VXGA8L6J4ZWG61 | E96: 882001 | F96: 155369 | G96: 244907.539646 | H96: 4 | I96: 2 | J96: 4 | K96: 2023 | L96: Estimated | M96: Reported | N96: Estimated | O96: 1567.21
A97: BEIEG | B97: BEIERSDORF | C97: DE0005200000 | D97: L47NHHI0Z9X22DV46U41 | E97: 39497 | F97: 59495 | G97: 1973480.313677 | H97: 1 | I97: 1 | J97: 4 | K97: 2023 | L97: Reported | M97: Reported | N97: Estimated | O97: 8609
A98: BE0LG | B98: BELLWAY PLC | D98: 9845008UA759C64C2F52 | E98: 16692 | F98: 4419 | G98: 2732457 | H98: 1 | I98: 1 | J98: 4 | K98: 2023 | L98: Reported | M98: Reported | N98: Estimated | O98: 4352.28
A99: BERTG | B99: BERTELSMANN | D99: 5299001BUUGXAREGE533 | E99: 191100 | F99: 171500 | G99: 1612075.725798 | H99: 1 | I99: 1 | J99: 4 | K99: 2023 | L99: Reported | M99: Reported | N99: Estimated | O99: 22607
A100: BBLOG | B100: BHP BILLITON | C100: AU000000BHP4 | D100: WZE1WSENV6JSZFK0JC28 | E100: 9200000 | F100: 4800000 | G100: 404883069.15876 | H100: 1 | I100: 1 | J100: 4 | K100: 2023 | L100: Reported | M100: Reported | N100: Estimated | O100: 68676.07
...

Sheet Sheet5
A1: flag_scib | B1: 1
A3: Row Labels | B3: Sum of total
A4: A | B4: 874.37529
A5: B | B5: 0
A6: C | B6: 480906.46
A7: D | B7: 153229.75
A8: E | B8: 15.84476
A9: F | B9: 12276.503
A10: G | B10: 306817.3
A11: H | B11: 155977.98
A12: I | B12: 309.73441
A13: J | B13: 1154.3638
A14: K | B14: 0
A15: M | B15: 492104.73
... A18: Grand Total | B18: 1606711.9

Sheet AS IS 
A1: bu_esg_work.EMI_FINAN_V3
A2: nace | B2: origem_scp1_emss | C2: origem_scp2_emss | D2: origem_scp3_emss | E2: glcs_code | F2: flag_cliente | G2: flag_scib | H2: montante | I2: total | J2: amount | K2: gesi | L2: gesii | M2: gesiii | N2: divida_tatico | O2: divida_estr | S2: Row Labels | T2: Sum of amount | U2: Sum of gesi | V2: Sum of gesii | W2: Sum of gesiii | X2: Sum of total
A3: A | B3: RE_DQS4_2B | C3: RE_DQS4_2B | D3: Nao Aplicavel | E3: NULL | F3: 0 | G3: 0 | H3: -93149827 | I3: 778636.77 | J3: 93149827 | K3: 122252.17 | L3: 656384.61 | P3: =+O3-N3 -> 0 | R3: A | S3: A | T3: 3.4864756e+08 | U3: 363755.54 | V3: 675360.74 | W3: 97706.477 | X3: 1136822.8 | Y3: =+VLOOKUP(R3,'2. Emissões Reportadas'!A:V,21,FALSE) -> 348.64756 | Z3: =+VLOOKUP(R3,'2. Emissões Reportadas'!A:V,22,FALSE) -> 1136823
A4: A | B4: Nao Aplicavel | C4: MVL_DQS3_2B | D4: Nao Aplicavel | E4: NULL | F4: 0 | G4: 0 | H4: -3076.44 | I4: 0.147255 | J4: 3076.44 | L4: 0.147255 | P4: =+O4-N4 -> 0 | R4: B | S4: B | T4: 14118758 | U4: 12988.756 | V4: 18680.406 | W4: 6071.9934 | X4: 37741.155 | Y4: =+VLOOKUP(R4,'2. Emissões Reportadas'!A:V,21,FALSE) -> 14.118758 | Z4: =+VLOOKUP(R4,'2. Emissões Reportadas'!A:V,22,FALSE) -> 37741
A5: A | B5: MISS | C5: MISS | D5: MISS | E5: NULL | F5: 0 | G5: 0 | H5: -161.91 | I5: 0 | J5: 161.91 | P5: =+O5-N5 -> 0 | R5: C | S5: C | T5: 2.3116558e+09 | U5: 324645.8 | V5: 176346.14 | W5: 1574169.2 | X5: 2075161.1 | Y5: =+VLOOKUP(R5,'2. Emissões Reportadas'!A:V,21,FALSE) -> 2311.661 | Z5: =+VLOOKUP(R5,'2. Emissões Reportadas'!A:V,22,FALSE) -> 2075162
A6: A | B6: BCL_DQS1_SCIB | C6: BCL_DQS1_SCIB | D6: BCL_DQS4_SCIB | E6: GAAMG | F6: 0 | G6: 1 | H6: -1214809.1 | I6: 874.37529 | J6: 1214809.1 | K6: 6.699286 | L6: 77.850486 | M6: 789.82552 | N6: 1030.8 | O6: 1030.8 | P6: =+O6-N6 -> 0 | R6: D | S6: D | T6: 7.3690288e+08 | U6: 206749.94 | V6: 12429.255 | W6: 159753.48 | X6: 378932.67 | Y6: =+VLOOKUP(R6,'2. Emissões Reportadas'!A:V,21,FALSE) -> 736.90288 | Z6: =+VLOOKUP(R6,'2. Emissões Reportadas'!A:V,22,FALSE) -> 378933
A7: A | B7: RE_DQS3_2A | C7: RE_DQS3_2A | D7: Nao Aplicavel | E7: NULL | F7: 0 | G7: 0 | H7: -4653076.8 | I7: 74.365354 | J7: 4653076.8 | K7: 18.832077 | L7: 55.533277 | P7: =+O7-N7 -> 0 | R7: E | S7: E | T7: 88021193 | U7: 10300.257 | V7: 1524.4562 | W7: 10807.973 | X7: 22632.687 | Y7: =+VLOOKUP(R7,'2. Emissões Reportadas'!A:V,21,FALSE) -> 88.021193 | Z7: =+VLOOKUP(R7,'2. Emissões Reportadas'!A:V,22,FALSE) -> 22633
A8: A | B8: MVL_DQS4_3A | C8: MVL_DQS4_3A | D8: Nao Aplicavel | E8: NULL | F8: 0 | G8: 0 | H8: -60827.81 | I8: 3.714809 | J8: 60827.81 | K8: 2.00862 | L8: 1.706189 | P8: =+O8-N8 -> 0 | R8: F | S8: F | T8: 1.052869e+09 | U8: 44584.01 | V8: 25180.914 | W8: 284926.72 | X8: 354691.65 | Y8: =+VLOOKUP(R8,'2. Emissões Reportadas'!A:V,21,FALSE) -> 1052.869 | Z8: =+VLOOKUP(R8,'2. Emissões Reportadas'!A:V,22,FALSE) -> 354692
A9: A | B9: MISS | C9: MISS | D9: Nao Aplicavel | E9: NULL | F9: 0 | G9: 0 | H9: -932603.12 | I9: 0 | J9: 932603.12 | P9: =+O9-N9 -> 0 | R9: G | S9: G | T9: 1.9794221e+09 | U9: 249090.97 | V9: 139306.77 | W9: 1044350.5 | X9: 1432748.3 | Y9: =+VLOOKUP(R9,'2. Emissões Reportadas'!A:V,21,FALSE) -> 1979.4221 | Z9: =+VLOOKUP(R9,'2. Emissões Reportadas'!A:V,22,FALSE) -> 1432748
A10: A | B10: RE_DQS5_3 | C10: RE_DQS5_3 | D10: Nao Aplicavel | E10: NULL | F10: 0 | G10: 0 | H10: -22779304 | I10: 539.52692 | J10: 22779304 | K10: 84.697433 | L10: 454.82949 | P10: =+O10-N10 -> 0 | R10: H | S10: H | T10: 7.8108571e+08 | U10: 322739.65 | V10: 24282.343 | W10: 607039.49 | X10: 954061.49 | Y10: =+VLOOKUP(R10,'2. Emissões Reportadas'!A:V,21,FALSE) -> 781.08571 | Z10: =+VLOOKUP(R10,'2. Emissões Reportadas'!A:V,22,FALSE) -> 954062
A11: A | B11: MVL_DQS3_2B | C11: Nao Aplicavel | D11: Nao Aplicavel | E11: NULL | F11: 0 | G11: 0 | H11: -25286.05 | I11: 1.475289 | J11: 25286.05 | K11: 1.475289 | P11: =+O11-N11 -> 0 | R11: I | S11: I | T11: 1.0632868e+09 | U11: 32368.439 | V11: 70913.038 | W11: 90094.08 | X11: 193375.56 | Y11: =+VLOOKUP(R11,'2. Emissões Reportadas'!A:V,21,FALSE) -> 1063.2868 | Z11: =+VLOOKUP(R11,'2. Emissões Reportadas'!A:V,22,FALSE) -> 193375
A12: A | B12: MVL_DQS3_2B | C12: MVL_DQS3_2B | D12: Nao Aplicavel | E12: NULL | F12: 0 | G12: 0 | H12: -65727.71 | I12: 2.69886 | J12: 65727.71 | K12: 1.278572 | L12: 1.420288 | P12: =+O12-N12 -> 0 | R12: J | S12: J | T12: 1.1295492e+08 | U12: 4628.3249 | V12: 3073.8282 | W12: 18004.536 | X12: 25706.689
A13: A | B13: BCL_DQS5_3B | C13: BCL_DQS5_3B | D13: BCL_DQS5_3B | E13: NULL | F13: 0 | G13: 0 | H13: -33133672 | I13: 60605.678 | J13: 33133672 | K13: 40931.535 | L13: 3135.495 | M13: 16538.649 | P13: =+O13-N13 -> 0 | Q13: 1 | R13: K | S13: K | T13: 3460620 | U13: 115.18347 | V13: 128.90945 | W13: 490.17356 | X13: 734.26648 | Y13: =+VLOOKUP(R13,'2. Emissões Reportadas'!A:V,21,FALSE) -> 3.46062 | Z13: =+VLOOKUP(R13,'2. Emissões Reportadas'!A:V,22,FALSE) -> 734
A14: A | B14: Nao Aplicavel | C14: Nao Aplicavel | D14: Nao Aplicavel | E14: NULL | F14: 0 | G14: 0 | H14: -203068.95 | I14: 0 | J14: 203068.95 | P14: =+O14-N14 -> 0 | R14: L | S14: L | T14: 1.1712311e+09 | U14: 19430.251 | V14: 80937.153 | W14: 14579.583 | X14: 114946.99 | Y14: =+VLOOKUP(R14,'2. Emissões Reportadas'!A:V,21,FALSE) -> 1171.2311 | Z14: =+VLOOKUP(R14,'2. Emissões Reportadas'!A:V,22,FALSE) -> 114947
A15: A | B15: BCL_DQS4_3A | C15: BCL_DQS4_3A | D15: BCL_DQS4_3A | E15: NULL | F15: 0 | G15: 0 | H15: -1.8924206e+08 | I15: 294543.89 | J15: 1.8924206e+08 | K15: 198927.34 | L15: 15238.544 | M15: 80378.003 | P15: =+O15-N15 -> 0 | R15: M | S15: M | T15: 1.97005e+09 | U15: 19976.77 | V15: 58503.304 | W15: 506257.23 | X15: 584737.3 | Z15: 2988.6102 | AA15: 814880
A16: A | B16: Nao Aplicavel | C16: MVL_DQS4_3A | D16: Nao Aplicavel | E16: NULL | F16: 0 | G16: 0 | H16: -561805.37 | I16: 10.606774 | J16: 561805.37 | L16: 10.606774 | P16: =+O16-N16 -> 0 | R16: N | S16: N | T16: 3.5380775e+08 | U16: 35735.338 | V16: 7414.2076 | W16: 50416.713 | X16: 93566.258 | Z16: =+SUM(GETPIVOTDATA("Sum of amount",$S$2,"nace","J"),T15:T23) -> 2.9886102e+09 | AA16: =+SUM(GETPIVOTDATA("Sum of total",$S$2,"nace","J"),X15:X23) -> 814880.63
A17: A | B17: MVL_DQS4_3A | C17: Nao Aplicavel | D17: Nao Aplicavel | E17: NULL | F17: 0 | G17: 0 | H17: -2622249.3 | I17: 1529.5052 | J17: 2622249.3 | K17: 1529.5052 | P17: =+O17-N17 -> 0 | R17: O | S17: O | T17: 25808809 | U17: 796.05705 | V17: 131.55992 | W17: 1440.035 | X17: 2367.6519
A18: B | B18: BCL_DQS4_3A | C18: BCL_DQS4_3A | D18: BCL_DQS4_3A | E18: NULL | F18: 0 | G18: 0 | H18: -11141015 | I18: 15627.024 | J18: 11141015 | K18: 8855.4206 | L18: 1072.3756 | M18: 5699.2273 | P18: =+O18-N18 -> 0 | R18: P | S18: P | T18: 61212833 | U18: 2524.3598 | V18: 2043.8711 | W18: 3561.7427 | X18: 8129.9735
A19: B | B19: MVL_DQS3_2B | C19: Nao Aplicavel | D19: Nao Aplicavel | E19: NULL | F19: 0 | G19: 0 | H19: -2059.5 | I19: 0.303349 | J19: 2059.5 | K19: 0.303349 | P19: =+O19-N19 -> 0 | R19: Q | S19: Q | T19: 2.3290165e+08 | U19: 13379.708 | V19: 6944.3009 | W19: 22193.314 | X19: 42517.323
A20: B | B20: MVL_DQS4_3A | C20: Nao Aplicavel | D20: Nao Aplicavel | E20: NULL | F20: 0 | G20: 0 | H20: -561375.11 | I20: 287.6099 | J20: 561375.11 | K20: 287.6099 | P20: =+O20-N20 -> 0 | R20: R | S20: R | T20: 87565945 | U20: 9507.2266 | V20: 22404.216 | W20: 8885.7629 | X20: 40797.205
A21: B | B21: MISS | C21: MISS | D21: Nao Aplicavel | E21: NULL | F21: 0 | G21: 0 | H21: -171502.45 | I21: 0 | J21: 171502.45 | P21: =+O21-N21 -> 0 | R21: S | S21: S | T21: 37304852 | U21: 2590.9152 | V21: 1280.8358 | W21: 5452.5175 | X21: 9324.2685
A22: B | B22: RE_DQS4_2B | C22: RE_DQS4_2B | D22: Nao Aplicavel | E22: NULL | F22: 0 | G22: 0 | H22: -1082136.2 | I22: 20800.538 | J22: 1082136.2 | K22: 3265.7265 | L22: 17534.811 | P22: =+O22-N22 -> 0 | R22: T | S22: T | T22: 137710.58 | U22: 5.850449 | V22: 1.036039 | W22: 10.620306 | X22: 17.506794
A23: B | B23: RE_DQS5_3 | C23: RE_DQS5_3 | D23: Nao Aplicavel | E23: NULL | F23: 0 | G23: 0 | H23: -30665.63 | I23: 1.894781 | J23: 30665.63 | K23: 0.297451 | L23: 1.59733 | P23: =+O23-N23 -> 0 | R23: U | S23: U | T23: 1.0686572e+08 | U23: 2552.108 | V23: 415.68633 | W23: 4748.663 | X23: 7716.4573
A24: B | B24: Nao Aplicavel | C24: Nao Aplicavel | D24: Nao Aplicavel | E24: NULL | F24: 0 | G24: 0 | H24: -23647.01 | I24: 0 | J24: 23647.01 | P24: =+O24-N24 -> 0 | S24: (blank) | T24: 113017.05 | X24: 0
A25: B | B25: BCL_DQS5_3B | C25: BCL_DQS5_3B | D25: BCL_DQS5_3B | E25: NULL | F25: 0 | G25: 0 | H25: -1030687.4 | I25: 1022.108 | J25: 1030687.4 | K25: 579.20166 | L25: 70.140302 | M25: 372.76605 | P25: =+O25-N25 -> 0 | Q25: 1 | S25: Grand Total | T25: 1.2539425e+10 | U25: 1678465.5 | V25: 1327303 | W25: 4510960.8 | X25: 7516729.3
A26: B | B26: Nao Aplicavel | C26: MVL_DQS4_3A | D26: Nao Aplicavel | E26: NULL | F26: 0 | G26: 0 | H26: -34713.2 | I26: 0.882598 | J26: 34713.2 | L26: 0.882598 | P26: =+O26-N26 -> 0
A27: B | B27: BCL_DQS4_SCIB | C27: BCL_DQS2_SCIB | D27: BCL_DQS4_SCIB | E27: GRSEM | F27: 0 | G27: 1 | H27: -2059.86 | I27: 0 | J27: 2059.86 | K27: 0 | L27: 0 | M27: 0 | N27: 3726.86 | O27: 3726.86 | P27: =+O27-N27 -> 0
A28: B | B28: NULL | C28: NULL | D28: NULL | E28: NULL | F28: 0 | G28: 0 | I28: 0 | P28: =+O28-N28 -> 0
A29: B | B29: RE_DQS3_2A | C29: RE_DQS3_2A | D29: Nao Aplicavel | E29: NULL | F29: 0 | G29: 0 | H29: -38897.24 | I29: 0.795289 | J29: 38897.24 | K29: 0.196588 | L29: 0.598701 | P29: =+O29-N29 -> 0
A30: C | B30: BCL_DQS1_SCIB | C30: BCL_DQS1_SCIB | D30: BCL_DQS1_SCIB | E30: GLACG | F30: 0 | G30: 1 | H30: -205480.95 | I30: 532.66561 | J30: 205480.95 | K30: 18.034452 | L30: 7.783464 | M30: 506.8477 | N30: 43710.6 | O30: 43710.6 | P30: =+O30-N30 -> 0
A31: C | B31: Nao Aplicavel | C31: MVL_DQS4_3A | D31: Nao Aplicavel | E31: NULL | F31: 0 | G31: 0 | H31: -7313055.6 | I31: 147.04918 | J31: 7313055.6 | L31: 147.04918 | P31: =+O31-N31 -> 0
A32: C | B32: BCL_DQS1_SCIB | C32: BCL_DQS1_SCIB | D32: BCL_DQS4_SCIB | E32: SIHOG | F32: 0 | G32: 1 | H32: -33735.81 | I32: 0 | J32: 33735.81 | K32: 0 | L32: 0 | M32: 0 | N32: 312450 | O32: 312450 | P32: =+O32-N32 -> 0
A33: C | B33: BCL_DQS1_SCIB | C33: BCL_DQS1_SCIB | D33: BCL_DQS4_SCIB | E33: IXLZG | F33: 0 | G33: 1 | H33: -2545673.2 | I33: 4523.1687 | J33: 2545673.2 | K33: 21.08 | L33: 84.438296 | M33: 4417.6504 | N33: 2666372 | O33: 2666372 | P33: =+O33-N33 -> 0
A34: C | B34: RE_DQS5_3 | C34: RE_DQS5_3 | D34: Nao Aplicavel | E34: NULL | F34: 0 | G34: 0 | H34: -66716161 | I34: 5907.954 | J34: 66716161 | K34: 927.458 | L34: 4980.496 | P34: =+O34-N34 -> 0
A35: C | B35: BCL_DQS1_SCIB | C35: BCL_DQS1_SCIB | D35: BCL_DQS4_SCIB | E35: SCFRG | F35: 0 | G35: 1 | H35: -13009.35 | I35: 0 | J35: 13009.35 | K35: 0 | L35: 0 | M35: 0 | N35: 222180 | O35: 222180 | P35: =+O35-N35 -> 0
A36: C | B36: BCL_DQS5_3B | C36: BCL_DQS5_3B | D36: BCL_DQS5_3B | E36: NULL | F36: 0 | G36: 0 | H36: -2.6647899e+08 | I36: 125298.09 | J36: 2.6647899e+08 | K36: 15813.03 | L36: 6784.3711 | M36: 102700.69 | P36: =+O36-N36 -> 0 | Q36: 1
A37: C | B37: BCL_DQS1_SCIB | C37: BCL_DQS1_SCIB | D37: BCL_DQS4_SCIB | E37: BIGRG | F37: 0 | G37: 1 | H37: -2833.17 | I37: 0 | J37: 2833.17 | K37: 0 | L37: 0 | M37: 0 | N37: 14618.7 | O37: 14618.7 | P37: =+O37-N37 -> 0
A38: C | B38: BCL_DQS1_SCIB | C38: BCL_DQS1_SCIB | D38: BCL_DQS1_SCIB | E38: NEHOG | F38: 0 | G38: 1 | H38: -4223095.2 | I38: 1305.4462 | J38: 4223095.2 | K38: 42.106805 | L38: 33.965425 | M38: 1229.374 | N38: 22164280 | O38: 22164280 | P38: =+O38-N38 -> 0
A39: C | B39: BCL_DQS1_SCIB | C39: BCL_DQS1_SCIB | D39: BCL_DQS4_SCIB | E39: DSSGG | F39: 0 | G39: 1 | H39: -8255893.3 | I39: 6584.1071 | J39: 8255893.3 | K39: 1380.3138 | L39: 797.68396 | M39: 4406.1094 | N39: 2525839.7 | O39: 2525839.7 | P39: =+O39-N39 -> 0
A40: C | B40: RE_DQS4_2B | C40: RE_DQS4_2B | D40: Nao Aplicavel | E40: UNHOG | F40: 0 | G40: 0 | H40: -16112063 | I40: 771.29462 | J40: 16112063 | K40: 121.08139 | L40: 650.21323 | N40: 54608 | O40: 54608 | P40: =+O40-N40 -> 0
A41: C | B41: RE_DQS3_2A | C41: RE_DQS3_2A | D41: Nao Aplicavel | E41: NULL | F41: 0 | G41: 0 | H41: -2600440 | I41: 42.239578 | J41: 2600440 | K41: 12.64163 | L41: 29.597948 | P41: =+O41-N41 -> 0
A42: C | B42: BCL_DQS4_SCIB | C42: BCL_DQS2_SCIB | D42: BCL_DQS4_SCIB | E42: GRSEM | F42: 0 | G42: 1 | H42: -29895370 | I42: 76811.28 | J42: 29895370 | K42: 45407.526 | L42: 5828.5178 | M42: 25575.237 | N42: 637293.06 | O42: 637293.06 | P42: =+O42-N42 -> 0
A43: C | B43: BCL_DQS1_SCIB | C43: BCL_DQS1_SCIB | D43: BCL_DQS4_SCIB | E43: 5EBRO | F43: 0 | G43: 1 | H43: -9878.31 | I43: 15.650292 | J43: 9878.31 | K43: 0.515055 | L43: 0.307401 | M43: 14.827836 | N43: 8639.16 | O43: 8639.16 | P43: =+O43-N43 -> 0
A44: C | B44: BCL_DQS1_SCIB | C44: BCL_DQS1_SCIB | D44: BCL_DQS1_SCIB | E44: 5YATG | F44: 0 | G44: 1 | H44: -615733.75 | I44: 0 | J44: 615733.75 | K44: 0 | L44: 0 | M44: 0 | N44: 8699782.7 | O44: 8699782.7 | P44: =+O44-N44 -> 0
A45: C | B45: MVL_DQS5_3B | C45: MVL_DQS5_3B | D45: Nao Aplicavel | E45: NULL | F45: 0 | G45: 0 | H45: -42782.09 | I45: 4.505063 | J45: 42782.09 | K45: 4.413032 | L45: 0.092031 | P45: =+O45-N45 -> 0
A46: C | B46: MVL_DQS3_2B | C46: Nao Aplicavel | D46: Nao Aplicavel | E46: NULL | F46: 0 | G46: 0 | H46: -869247.52 | I46: 83.665758 | J46: 869247.52 | K46: 83.665758 | P46: =+O46-N46 -> 0
A47: C | B47: BCL_DQS1_SCIB | C47: BCL_DQS1_SCIB | D47: BCL_DQS4_SCIB | E47: SMURG | F47: 0 | G47: 1 | H47: -35332.2 | I47: 6.895318 | J47: 35332.2 | K47: 2.540979 | L47: 0.745156 | M47: 3.609183 | N47: 184807.74 | O47: 184807.74 | P47: =+O47-N47 -> 0
A48: C | B48: BCL_DQS1_SCIB | C48: BCL_DQS1_SCIB | D48: BCL_DQS4_SCIB | E48: 6SYNT | F48: 0 | G48: 1 | H48: -109921.2 | I48: 185.63395 | J48: 109921.2 | K48: 10.89369 | L48: 10.06317 | M48: 164.6771 | N48: 7185.51 | O48: 7185.51 | P48: =+O48-N48 -> 0
A49: C | B49: BCL_DQS1_SCIB | C49: BCL_DQS1_SCIB | D49: BCL_DQS4_SCIB | E49: SIKAG | F49: 0 | G49: 1 | H49: -552014.46 | I49: 53.893101 | J49: 552014.46 | K49: 0.468288 | L49: 0.481053 | M49: 52.94376 | N49: 3237844.8 | O49: 3237844.8 | P49: =+O49-N49 -> 0
A50: C | B50: Nao Aplicavel | C50: Nao Aplicavel | D50: Nao Aplicavel | E50: UNHOG | F50: 0 | G50: 0 | H50: -574.56 | I50: 0 | J50: 574.56 | N50: 54608 | O50: 54608 | P50: =+O50-N50 -> 0
A51: C | B51: MVL_DQS4_3A | C51: MVL_DQS4_3A | D51: Nao Aplicavel | E51: NULL | F51: 0 | G51: 0 | H51: -3340899.9 | I51: 143.3072 | J51: 3340899.9 | K51: 75.954384 | L51: 67.35282 | P51: =+O51-N51 -> 0
A52: C | B52: MVL_DQS4_3A | C52: Nao Aplicavel | D52: Nao Aplicavel | E52: NULL | F52: 0 | G52: 0 | H52: -14526144 | I52: 2875.6209 | J52: 14526144 | K52: 2875.6209 | P52: =+O52-N52 -> 0
A53: C | B53: MVL_DQS3_2B | C53: MVL_DQS3_2B | D53: Nao Aplicavel | E53: NULL | F53: 0 | G53: 0 | H53: -1086047.5 | I53: 39.480111 | J53: 1086047.5 | K53: 17.46405 | L53: 22.016061 | P53: =+O53-N53 -> 0
A54: C | B54: BCL_DQS4_3A | C54: BCL_DQS4_3A | D54: BCL_DQS4_3A | E54: NULL | F54: 0 | G54: 0 | H54: -1.652683e+09 | I54: 1384243.5 | J54: 1.652683e+09 | K54: 243993.6 | L54: 92696.126 | M54: 1047553.7 | P54: =+O54-N54 -> 0
A55: C | B55: BCL_DQS1_SCIB | C55: BCL_DQS1_SCIB | D55: BCL_DQS4_SCIB | E55: GAAMG | F55: 0 | G55: 1 | H55: -19865537 | I55: 13537.972 | J55: 19865537 | K55: 103.72519 | L55: 1205.3608 | M55: 12228.886 | N55: 2855316 | O55: 2855316 | P55: =+O55-N55 -> 0
A56: C | B56: RE_DQS4_2B | C56: RE_DQS4_2B | D56: Nao Aplicavel | E56: NULL | F56: 0 | G56: 0 | H56: -82759536 | I56: 74675.595 | J56: 82759536 | K56: 12471.557 | L56: 62204.038 | P56: =+O56-N56 -> 0
A57: C | B57: BCL_DQS1_SCIB | C57: BCL_DQS1_SCIB | D57: BCL_DQS4_SCIB | E57: IDVTG | F57: 0 | G57: 1 | H57: -6737.5 | I57: 0 | J57: 6737.5 | K57: 0 | L57: 0 | M57: 0 | N57: 11262.25 | O57: 11262.25 | P57: =+O57-N57 -> 0
A58: C | B58: BCL_DQS1_SCIB | C58: BCL_DQS1_SCIB | D58: BCL_DQS4_SCIB | E58: HEIKG | F58: 0 | G58: 1 | H58: -2200.27 | I58: 0 | J58: 2200.27 | K58: 0 | L58: 0 | M58: 0 | N58: 39451 | O58: 39451 | P58: =+O58-N58 -> 0
A59: C | B59: BCL_DQS1_SCIB | C59: BCL_DQS1_SCIB | D59: BCL_DQS4_SCIB | E59: CCEUP | F59: 0 | G59: 1 | H59: -408462.9 | I59: 120.21219 | J59: 408462.9 | K59: 3.846752 | L59: 3.946761 | M59: 112.41867 | N59: 960257 | O59: 960257 | P59: =+O59-N59 -> 0
A60: C | B60: BCL_DQS1_SCIB | C60: BCL_DQS1_SCIB | D60: BCL_DQS4_SCIB | E60: 5RKTG | F60: 0 | G60: 1 | H60: -41346.37 | I60: 25.756482 | J60: 41346.37 | K60: 0.24255 | L60: 0.474942 | M60: 25.03899 | N60: 18751.16 | O60: 18751.16 | P60: =+O60-N60 -> 0
A61: C | B61: MISS | C61: MISS | D61: Nao Aplicavel | E61: NULL | F61: 0 | G61: 0 | H61: -213727.09 | I61: 0 | J61: 213727.09 | P61: =+O61-N61 -> 0
A62: C | B62: BCL_DQS1_SCIB | C62: BCL_DQS1_SCIB | D62: BCL_DQS4_SCIB | E62: ROBEG | F62: 0 | G62: 1 | H62: -4184.2 | I62: 0 | J62: 4184.2 | K62: 0 | L62: 0 | M62: 0 | N62: 255564 | O62: 255564 | P62: =+O62-N62 -> 0
A63: C | B63: Nao Aplicavel | C63: Nao Aplicavel | D63: Nao Aplicavel | E63: NULL | F63: 0 | G63: 0 | H63: -1518171.2 | I63: 0 | J63: 1518171.2 | P63: =+O63-N63 -> 0
A64: C | B64: Nao Aplicavel | C64: Nao Aplicavel | D64: Nao Aplicavel | E64: GLACG | F64: 0 | G64: 0 | H64: -25.71 | I64: 0 | J64: 25.71 | N64: 14570.2 | O64: 14570.2 | P64: =+O64-N64 -> 0
A65: C | B65: BCL_DQS1_SCIB | C65: BCL_DQS1_SCIB | D65: BCL_DQS1_SCIB | E65: SNTGG | F65: 0 | G65: 1 | H65: -2243862.9 | I65: 3315.6493 | J65: 2243862.9 | K65: 319.06039 | L65: 98.721606 | M65: 2897.8673 | N65: 5178548 | O65: 5178548 | P65: =+O65-N65 -> 0
A66: C | B66: BCL_DQS1_SCIB | C66: BCL_DQS1_SCIB | D66: BCL_DQS4_SCIB | E66: UNHOG | F66: 0 | G66: 1 | H66: -15978470 | I66: 14215.439 | J66: 15978470 | K66: 117.4108 | L66: 285.4243 | M66: 13812.604 | N66: 6662176 | O66: 6662176 | P66: =+O66-N66 -> 0
A67: C | B67: Nao Aplicavel | C67: MVL_DQS3_2B | D67: Nao Aplicavel | E67: NULL | F67: 0 | G67: 0 | H67: -1061371.7 | I67: 22.407818 | J67: 1061371.7 | L67: 22.407818 | P67: =+O67-N67 -> 0
A68: C | B68: BCL_DQS1_SCIB | C68: BCL_DQS1_SCIB | D68: BCL_DQS1_SCIB | E68: IPAGG | F68: 0 | G68: 1 | H68: -2058850 | I68: 1371.5275 | J68: 2058850 | K68: 12.49827 | L68: 28.354212 | M68: 1330.6751 | N68: 2192905 | O68: 2192905 | P68: =+O68-N68 -> 0
A69: C | B69: BCL_DQS1_SCIB | C69: BCL_DQS1_SCIB | D69: BCL_DQS4_SCIB | E69: CMTAG | F69: 0 | G69: 1 | H69: -191126.27 | I69: 96.967113 | J69: 191126.27 | K69: 3.236896 | L69: 17.311264 | M69: 76.418953 | N69: 123216.36 | O69: 123216.36 | P69: =+O69-N69 -> 0
A70: C | B70: BCL_DQS1_SCIB | C70: BCL_DQS1_SCIB | D70: BCL_DQS4_SCIB | E70: LUXOG | F70: 0 | G70: 1 | H70: -89738.23 | I70: 3.692308 | J70: 89738.23 | K70: 0.108453 | L70: 0.704804 | M70: 2.879051 | N70: 596398 | O70: 596398 | P70: =+O70-N70 -> 0
A71: C | B71: BCL_DQS1_SCIB | C71: BCL_DQS1_SCIB | D71: BCL_DQS4_SCIB | E71: 5FRQG | F71: 0 | G71: 1 | H71: -221016.19 | I71: 13.026574 | J71: 221016.19 | K71: 1.12521 | L71: 1.797038 | M71: 10.104326 | N71: 440271 | O71: 440271 | P71: =+O71-N71 -> 0
A72: C | B72: BCL_DQS1_SCIB | C72: BCL_DQS2_SCIB | D72: BCL_DQS4_SCIB | E72: VDRLG | F72: 0 | G72: 1 | H72: -106287.82 | I72: 123.12137 | J72: 106287.82 | K72: 53.586278 | L72: 8.069784 | M72: 61.465309 | N72: 11921.98 | O72: 11921.98 | P72: =+O72-N72 -> 0
A73: C | B73: BCL_DQS1_SCIB | C73: BCL_DQS1_SCIB | D73: BCL_DQS4_SCIB | E73: 04D0G | F73: 0 | G73: 1 | H73: -1775938.9 | I73: 124.78716 | J73: 1775938.9 | K73: 0.876109 | L73: 5.105958 | M73: 118.80509 | N73: 7299006 | O73: 7299006 | P73: =+O73-N73 -> 0
A74: C | B74: NULL | C74: NULL | D74: NULL | E74: NULL | F74: 0 | G74: 0 | I74: 0 | P74: =+O74-N74 -> 0
A75: C | B75: BCL_DQS1_SCIB | C75: BCL_DQS1_SCIB | D75: BCL_DQS4_SCIB | E75: 5EBRG | F75: 0 | G75: 1 | H75: -1.0325824e+08 | I75: 357713.57 | J75: 1.0325824e+08 | K75: 749.57238 | L75: 322.26981 | M75: 356641.73 | N75: 28649.35 | O75: 28649.35 | P75: =+O75-N75 -> 0
A76: C | B76: MISS | C76: MISS | D76: MISS | E76: NULL | F76: 0 | G76: 0 | H76: -1503093 | I76: 0 | J76: 1503093 | P76: =+O76-N76 -> 0
A77: C | B77: BCL_DQS1_SCIB | C77: BCL_DQS1_SCIB | D77: BCL_DQS4_SCIB | E77: WEGHG | F77: 0 | G77: 1 | H77: -50379.05 | I77: 225.99957 | J77: 50379.05 | K77: 0.54864 | L77: 0.85066 | M77: 224.60027 | N77: 21426.5 | O77: 21426.5 | P77: =+O77-N77 -> 0
A78: C | B78: BCL_DQS1_SCIB | C78: BCL_DQS1_SCIB | D78: BCL_DQS4_SCIB | E78: CELLN | F78: 0 | G78: 1 | H78: -30117.64 | I78: 0 | J78: 30117.64 | K78: 0 | L78: 0 | M78: 0 | N78: 147298.68 | O78: 147298.68 | P78: =+O78-N78 -> 0
A79: D | B79: BCL_DQS1_SCIB | C79: BCL_DQS1_SCIB | D79: BCL_DQS4_SCIB | E79: IBR00 | F79: 0 | G79: 1 | H79: -1579.15 | I79: 0 | J79: 1579.15 | K79: 0 | L79: 0 | M79: 0 | N79: 121004 | O79: 121004 | P79: =+O79-N79 -> 0
A80: D | B80: BCL_DQS5_3B | C80: BCL_DQS5_3B | D80: BCL_DQS5_3B | E80: NULL | F80: 0 | G80: 0 | H80: -1.4514241e+08 | I80: 121033.44 | J80: 1.4514241e+08 | K80: 89814.42 | L80: 3334.3623 | M80: 27884.662 | P80: =+O80-N80 -> 0 | Q80: 1
A81: D | B81: Nao Aplicavel | C81: MVL_DQS3_2B | D81: Nao Aplicavel | E81: NULL | F81: 0 | G81: 0 | H81: -40426.05 | I81: 0.827235 | J81: 40426.05 | L81: 0.827235 | P81: =+O81-N81 -> 0
A82: D | B82: Nao Aplicavel | C82: MVL_DQS4_3A | D82: Nao Aplicavel | E82: NULL | F82: 0 | G82: 0 | H82: -151009.55 | I82: 2.174276 | J82: 151009.55 | L82: 2.174276 | P82: =+O82-N82 -> 0
A83: D | B83: BCL_DQS4_3A | C83: BCL_DQS4_3A | D83: BCL_DQS4_3A | E83: NULL | F83: 0 | G83: 0 | H83: -1.7866817e+08 | I83: 56334.215 | J83: 1.7866817e+08 | K83: 41803.528 | L83: 1551.9528 | M83: 12978.734 | P83: =+O83-N83 -> 0
A84: D | B84: BCL_DQS1_SCIB | C84: BCL_DQS1_SCIB | D84: BCL_DQS4_SCIB | E84: EDP0G | F84: 0 | G84: 1 | H84: -2.0359462e+08 | I84: 102001.66 | J84: 2.0359462e+08 | K84: 47909.248 | L84: 2390.7314 | M84: 51701.677 | N84: 4936819.4 | O84: 4936819.4 | P84: =+O84-N84 -> 0
A85: D | B85: MVL_DQS4_3A | C85: Nao Aplicavel | D85: Nao Aplicavel | E85: NULL | F85: 0 | G85: 0 | H85: -34515.32 | I85: 3.969752 | J85: 34515.32 | K85: 3.969752 | P85: =+O85-N85 -> 0
A86: D | B86: PF_DQS1_1A | C86: PF_DQS5_3B | D86: PF_DQS5_3B | E86: NULL | F86: 0 | G86: 0 | H86: -1.4556169e+08 | I86: 31309.153 | J86: 1.4556169e+08 | K86: 0 | L86: 3343.9885 | M86: 27965.165 | P86: =+O86-N86 -> 0 | Q86: 1
A87: D | B87: MVL_DQS4_3A | C87: MVL_DQS4_3A | D87: Nao Aplicavel | E87: NULL | F87: 0 | G87: 0 | H87: -34923.24 | I87: 1.480984 | J87: 34923.24 | K87: 0.65041 | L87: 0.830574 | P87: =+O87-N87 -> 0
A88: D | B88: PF_DQS1_SCIB | C88: PF_DQS1_SCIB | D88: PF_DQS4_SCIB | E88: 5ESRG | F88: 0 | G88: 1 | H88: -33077228 | I88: 48710.517 | J88: 33077228 | K88: 14540.199 | L88: 1102.3727 | M88: 33067.946 | N88: 120494 | O88: 120494 | P88: =+O88-N88 -> 0
A89: D | B89: RE_DQS4_2B | C89: RE_DQS4_2B | D89: Nao Aplicavel | E89: NULL | F89: 0 | G89: 0 | H89: -741121.8 | I89: 0.030284 | J89: 741121.8 | K89: 0.004754 | L89: 0.02553 | P89: =+O89-N89 -> 0
A90: D | B90: BCL_DQS1_SCIB | C90: BCL_DQS1_SCIB | D90: BCL_DQS4_SCIB | E90: 5ESRG | F90: 0 | G90: 1 | H90: -3873.27 | I90: 0 | J90: 3873.27 | K90: 0 | L90: 0 | M90: 0 | N90: 120494 | O90: 120494 | P90: =+O90-N90 -> 0
A91: D | B91: MVL_DQS3_2B | C91: MVL_DQS3_2B | D91: Nao Aplicavel | E91: NULL | F91: 0 | G91: 0 | H91: -80742.14 | I91: 2.617042 | J91: 80742.14 | K91: 1.451398 | L91: 1.165644 | P91: =+O91-N91 -> 0
A92: D | B92: BCL_DQS1_SCIB | C92: BCL_DQS2_SCIB | D92: BCL_DQS1_SCIB | E92: RENLG | F92: 0 | G92: 1 | H92: -6725374.1 | I92: 365.06056 | J92: 6725374.1 | K92: 48.257732 | L92: 198.45871 | M92: 118.34411 | N92: 461202.56 | O92: 461202.56 | P92: =+O92-N92 -> 0
A93: D | B93: PF_DQS5_3B | C93: PF_DQS5_3B | D93: PF_DQS5_3B | E93: NULL | F93: 0 | G93: 0 | H93: -20384980 | I93: 16998.891 | J93: 20384980 | K93: 12614.245 | L93: 468.30412 | M93: 3916.3418 | P93: =+O93-N93 -> 0 | Q93: 1
A94: D | B94: Nao Aplicavel | C94: Nao Aplicavel | D94: Nao Aplicavel | E94: NULL | F94: 0 | G94: 0 | H94: -1408.7 | I94: 0 | J94: 1408.7 | P94: =+O94-N94 -> 0
A95: D | B95: PF_DQS1_1A | C95: PF_DQS1_SCIB | D95: PF_DQS4_SCIB | E95: 5CUMG | F95: 0 | G95: 1 | H95: -2591275.1 | I95: 2133.1748 | J95: 2591275.1 | K95: 0 | L95: 19.003688 | M95: 2114.1711 | N95: 18968 | O95: 18968 | P95: =+O95-N95 -> 0
A96: D | B96: BCL_DQS4_SCIB | C96: BCL_DQS2_SCIB | D96: BCL_DQS4_SCIB | E96: GRSEM | F96: 0 | G96: 1 | H96: -9539.88 | I96: 19.34062 | J96: 9539.88 | K96: 11.433344 | L96: 1.467586 | M96: 6.43969 | N96: 14907.44 | O96: 14907.44 | P96: =+O96-N96 -> 0
A97: D | B97: RE_DQS5_3 | C97: RE_DQS5_3 | D97: Nao Aplicavel | E97: NULL | F97: 0 | G97: 0 | H97: -57989.6 | I97: 16.121021 | J97: 57989.6 | K97: 2.530753 | L97: 13.590268 | P97: =+O97-N97 -> 0
A98: E | B98: MISS | C98: MISS | D98: Nao Aplicavel | E98: 5VFRG | F98: 1 | G98: 0 | H98: -1251.26 | I98: 0 | J98: 1251.26 | N98: 44588 | P98: =+O98-N98 -> -44588
A99: E | B99: RE_DQS5_3 | C99: RE_DQS5_3 | D99: Nao Aplicavel | E99: NULL | F99: 0 | G99: 0 | H99: -2135479.5 | I99: 162.83464 | J99: 2135479.5 | K99: 25.562536 | L99: 137.2721 | P99: =+O99-N99 -> 0
A100: E | B100: BCL_DQS5_3B | C100: BCL_DQS5_3B | D100: BCL_DQS5_3B | E100: NULL | F100: 0 | G100: 0 | H100: -2206355.2 | I100: 346.43951 | J100: 2206355.2 | K100: 130.48049 | L100: 21.22449 | M100: 194.73453 | P100: =+O100-N100 -> 0 | Q100: 1
...

Sheet 2. Emissões Reportadas
C2: Template 1: Banking book- Climate Change transition risk: Credit quality of exposures by sector, emissions and residual maturity
C3: Sector/subsector | D3: a | E3: b | F3: c | G3: d | H3: e | I3: f | J3: g | K3: h | L3: i | M3: j | N3: k | O3: l | P3: m | Q3: n | R3: o | S3: p
D4: Gross carrying amount (Mln EUR) | I4: Accumulated impairment, accumulated negative changes in fair value due to credit risk and provisions (Mln EUR) | L4: GHG financed emissions (scope 1, scope 2 and scope 3 emissions of the counterparty) (in tons of CO2 equivalent) | N4: GHG emissions (column i): gross carrying amount percentage of the portfolio derived from company-specific reporting | O4: <= 5 years | P4: > 5 year <= 10 years | Q4: > 10 year <= 20 years | R4: > 20 years | S4: Average weighted maturity
E5: Of which exposures towards companies excluded from EU Paris-aligned Benchmarks in accordance with points (d) to (g) of Article 12.1 and in accordance with Article 12.2 of Climate Benchmark Standards Regulation | F5: Of which environmentally sustainable (CCM) | G5: Of which stage 2 exposures | H5: Of which non-performing exposures | J5: Of which Stage 2 exposures | K5: Of which non-performing exposures | M5: Of which Scope 3 financed emissions
B6: 1 | C6: Exposures towards sectors that highly contribute to climate change* | D6: 9547.246 | E6: 36.816487 | F6: 129.12492 | G6: 853.59693 | H6: 400.68493 | I6: -321.20209 | J6: -43.288942 | K6: -260.53892 | L6: 6701116 | M6: 3889502 | N6: 0.076181585 | O6: 7294.8837 | P6: 1257.2137 | Q6: 931.49854 | R6: 63.650073 | S6: 4 | U6: =+D6 -> 9547.246 | V6: =+L6 -> 6701116
A7: A | B7: 2 | C7: A - Agriculture, forestry and fishing | D7: 348.64756 | E7: 0 | F7: 0.048106 | G7: 45.154885 | H7: 25.925782 | I7: -8.085153 | J7: -2.414584 | K7: -5.03654 | L7: 1136823 | M7: 97707 | N7: 0.0023228981 | O7: 223.55119 | P7: 65.941244 | Q7: 59.155128 | R7: 0 | S7: 5 | U7: =+D7 -> 348.64756 | V7: =+L7 -> 1136823
A8: B | B8: 3 | C8: B - Mining and quarrying | D8: 14.118758 | E8: 0 | F8: 9.2e-05 | G8: 2.018222 | H8: 1.809686 | I8: -1.203046 | J8: -0.116567 | K8: -1.057855 | L8: 37741 | M8: 6072 | N8: 4.8631756e-05 | O8: 13.19721 | P8: 0.921548 | Q8: 0 | R8: 0 | S8: 2 | U8: =+D8 -> 14.118758 | V8: =+L8 -> 37741
A9: B5 | B9: 4 | C9: B.05 - Mining of coal and lignite | D9: 0 | E9: 0 | F9: 0 | G9: 0 | H9: 0 | I9: 0 | J9: 0 | K9: 0 | L9: 0 | M9: 0 | N9: 0 | O9: 0 | P9: 0 | Q9: 0 | R9: 0 | S9: 0 | U9: =+D9 -> 0 | V9: =+L9 -> 0
A10: B6 | B10: 5 | C10: B.06 - Extraction of crude petroleum and natural gas | D10: 0 | E10: 0 | F10: 0 | G10: 0 | H10: 0 | I10: 0 | J10: 0 | K10: 0 | L10: 0 | M10: 0 | N10: 0 | O10: 0 | P10: 0 | Q10: 0 | R10: 0 | S10: 0 | U10: =+D10 -> 0 | V10: =+L10 -> 0
A11: B7 | B11: 6 | C11: B.07 - Mining of metal ores | D11: 0.101846 | E11: 0 | F11: 0 | G11: 0 | H11: 0 | I11: -3.9e-05 | J11: 0 | K11: 0 | L11: 65 | M11: 24 | N11: 0 | O11: 0.101846 | P11: 0 | Q11: 0 | R11: 0 | S11: 0 | U11: =+D11 -> 0.101846 | V11: =+L11 -> 65
A12: B8 | B12: 7 | C12: B.08 - Other mining and quarrying | D12: 13.962026 | E12: 0 | F12: 9.2e-05 | G12: 1.963875 | H12: 1.809156 | I12: -1.201902 | J12: -0.115934 | K12: -1.057384 | L12: 37641 | M12: 6035 | N12: 4.9177677e-05 | O12: 13.040478 | P12: 0.921548 | Q12: 0 | R12: 0 | S12: 2 | U12: =+D12 -> 13.962026 | V12: =+L12 -> 37641
A13: B9 | B13: 8 | C13: B.09 - Mining support service activities | D13: 0.054887 | E13: 0 | F13: 0 | G13: 0.054348 | H13: 0.00053 | I13: -0.001105 | J13: -0.000633 | K13: -0.000471 | L13: 36 | M13: 13 | N13: 0 | O13: 0.054887 | P13: 0 | Q13: 0 | R13: 0 | S13: 2 | U13: =+D13 -> 0.054887 | V13: =+L13 -> 36
A14: C | B14: 9 | C14: C - Manufacturing | D14: 2311.661 | E14: 0.209683 | F14: 10.032239 | G14: 237.21648 | H14: 84.608832 | I14: -74.90135 | J14: -10.927852 | K14: -59.252308 | L14: 2075162 | M14: 1574170 | N14: 0.052647942 | O14: 2089.3961 | P14: 174.11267 | Q14: 48.116587 | R14: 0.035578 | S14: 2 | U14: =+D14 -> 2311.661 | V14: =+L14 -> 2075162
A15: C10 | B15: 10 | C15: C.10 - Manufacture of food products | D15: 314.64138 | E15: 0 | F15: 0 | G15: 31.937245 | H15: 10.73584 | I15: -8.756349 | J15: -1.680093 | K15: -6.235924 | L15: 391597 | M15: 341601 | N15: 0.04795734 | O15: 272.6108 | P15: 25.146231 | Q15: 16.884346 | R15: 0 | S15: 2 | U15: =+D15 -> 314.64138 | V15: =+L15 -> 391597
A16: C11 | B16: 11 | C16: C.11 - Manufacture of beverages | D16: 235.60425 | E16: 0 | F16: 0 | G16: 7.27825 | H16: 0.355556 | I16: -0.963141 | J16: -0.417743 | K16: -0.276624 | L16: 137620 | M16: 104248 | N16: 0.001162014 | O16: 173.30136 | P16: 61.492993 | Q16: 0.809899 | R16: 0 | S16: 2 | U16: =+D16 -> 235.60425 | V16: =+L16 -> 137620
A17: C12 | B17: 12 | C17: C.12 - Manufacture of tobacco products | D17: 3.372252 | E17: 0 | F17: 0 | G17: 0 | H17: 0 | I17: -0.005161 | J17: 0 | K17: 0 | L17: 8560 | M17: 7523 | N17: 0.18258829 | O17: 3.372252 | P17: 0 | Q17: 0 | R17: 0 | S17: 0 | U17: =+D17 -> 3.372252 | V17: =+L17 -> 8560
A18: C13 | B18: 13 | C18: C.13 - Manufacture of textiles | D18: 101.48952 | E18: 0 | F18: 0 | G18: 15.990182 | H18: 4.615805 | I18: -4.895716 | J18: -0.9697 | K18: -3.54194 | L18: 36307 | M18: 29046 | N18: 0 | O18: 97.686888 | P18: 3.369196 | Q18: 0.433435 | R18: 0 | S18: 2 | U18: =+D18 -> 101.48952 | V18: =+L18 -> 36307
... A57: L | B57: 52 | C57: L - Real estate activities | D57: 1171.2311 | E57: 0 | F57: 0 | G57: 103.53666 | H57: 28.048686 | I57: -26.141884 | J57: -5.718605 | K57: -18.83917 | L57: 114947 | M57: 14580 | N57: 0 | O57: 685.24786 | P57: 255.32025 | Q57: 230.53181 | R57: 0.131176 | S57: 6 | U57: =+D57 -> 1171.2311 | V57: =+L57 -> 114947
B58: 53 | C58: Exposures towards sectors other than those that highly contribute to climate change* | D58: 2992.0708 | E58: 351.47054 | F58: 9.760108 | G58: 206.64534 | H58: 50.382795 | I58: -64.724279 | J58: -19.212288 | K58: -38.329482 | L58: 815614 | M58: 621461 | N58: 0.23499639 | O58: 2432.2646 | P58: 354.27076 | Q58: 204.5029 | R58: 1.032553 | S58: 3 | U58: =+D58 -> 2992.0708 | V58: =+L58 -> 815614
A59: K | B59: 54 | C59: K - Financial and insurance activities | D59: 3.46062 | E59: 0 | F59: 5.7e-05 | G59: 0.175923 | H59: 0.050877 | I59: -0.401491 | J59: -0.014942 | K59: -0.037403 | L59: 734 | M59: 490 | N59: 7.9471307e-05 | O59: 2.352348 | P59: 0.627912 | Q59: 0.14648 | R59: 0.33388 | S59: 11 | U59: =+D59 -> 3.46062 | V59: =+L59 -> 734
A60: J, M-U | B60: 55 | C60: Exposures to other sectors (NACE codes J, M - U) | D60: 2988.6102 | E60: 351.47054 | F60: 9.760051 | G60: 206.46942 | H60: 50.331918 | I60: -64.322788 | J60: -19.197346 | K60: -38.292079 | L60: 814880 | M60: 620971 | N60: 0.2352684 | O60: 2429.9122 | P60: 353.64285 | Q60: 204.35642 | R60: 0.698673 | S60: 3 | U60: =+D60 -> 2988.6102 | V60: =+L60 -> 814880
A61: TOTAL | B61: 56 | C61: TOTAL | D61: 12539.317 | E61: 388.28703 | F61: 138.88503 | G61: 1060.2423 | H61: 451.06772 | I61: -385.92637 | J61: -62.50123 | K61: -298.86841 | L61: 7516730 | M61: 4510963 | N61: 0.1140772 | O61: 9727.1483 | P61: 1611.4845 | Q61: 1136.0014 | R61: 64.682626 | S61: 3 | U61: =+D61 -> 12539.317 | V61: =+L61 -> 7516730
C62: * In accordance with the Commission delegated regulation EU) 2020/1818 supplementing regulation (EU) 2016/1011 as regards minimum standards for EU Climate Transition Benchmarks and EU Paris-aligned Benchmarks -Climate Benchmark Standards Regulation - Recital 6: Sectors listed in Sections A to H and Section L of Annex I to Regulation (EC) No 1893/2006
D63: valor bruto | E63: valor bruto | F63: 1 | G63: valor bruto | H63: valor bruto | I63: imparidade | J63: imparidade | K63: imparidade | O63: valor bruto | P63: valor bruto | Q63: valor bruto | R63: valor bruto | S63: valor bruto
E64: excluido | G64: stage 2 | H64: stage 3 | J64: stage 2 | K64: stage 3 | O64: -4 | P64: >5 | Q64: >10 | R64: >20 | S64: -1
P65: <=10 | Q65: <=20 | R65: -3 | S65: -2
R66: -2

Sheet 3. Clientes KGL diferente
B2: CLIENTES SCIB NA NFIN REPORTADA, MAS NA NA NFIN GERADA NO DIA 14/10 NÃO FORAM APANHADOS COMO SCIB
B4: zcliente | C4: ccli_grupo | D4: ccli_kgl | E4: clei | F4: cpais_residencia | G4: valor_mv | H4: ccliente_rst159 | I4: centlegal_rst159 | J4: cgrupo_rst159 | K4: zcliente_ct088 | L4: kgl5_ct071 | M4: ccli_grupo_max_clei | N4: clei_grupo_max_clei | O4: rank_max_clei | P4: zcliente_fr004 | Q4: sum_saldo_fr004 | R4: zcliente_pf | S4: zcliente_pme | T4: fatr_indv_pme | U4: zcliente_contraparte | V4: ref_date_contraparte | W4: contraparte | X4: zcliente_jquest | Y4: ccli_kgl_jquest | Z4: cpty_code_jquest | AA4: cptyparent_code_jquest | AB4: cptylastparent_code_jquest | AC4: clei_trat | AD4: flag_pf
B5: 8029317631 | C5: 0006661442 | D5: 98DF | E5: # | F5: 620 | G5: EU member states | H5: NULL | I5: NULL | J5: NULL | K5: NULL | L5: NULL | M5: NULL | N5: NULL | O5: NULL | P5: 8029317631 | Q5: 136.000000 | R5: NULL | S5: 8029317631 | T5: 20970000.000000 | U5: 8029317631 | V5: 2025-06-30 | W5: outras empresas nao financeiras | X5: 8029317631 | Y5: 98DF | Z5: 98DF | AA5: 98DFG | AB5: PRISA | AC5: # | AD5: N | AE5: =+VLOOKUP(Z5,'1. Input Junho 2025'!$A:$A,1,FALSE) -> #N/A | AF5: =+VLOOKUP(AA5,'1. Input Junho 2025'!$A:$A,1,FALSE) -> #N/A | AG5: =+VLOOKUP(AB5,'1. Input Junho 2025'!$A:$A,1,FALSE) -> PRISA | AH5: =+VLOOKUP(AC5,'1. Input Junho 2025'!$A:$A,1,FALSE) -> #N/A | AI5: =+VLOOKUP(AD5,'1. Input Junho 2025'!$A:$A,1,FALSE) -> #N/A
B6: 8000520483 | C6: 0008485994 | D6: 9SND | E6: # | F6: 620 | G6: EU member states | H6: NULL | I6: NULL | J6: NULL | K6: NULL | L6: NULL | M6: NULL | N6: NULL | O6: NULL | P6: 8000520483 | Q6: 37185.850000 | R6: NULL | S6: 8000520483 | T6: 59693583.300000 | U6: 8000520483 | V6: 2025-06-30 | W6: outras empresas nao financeiras | X6: 8000520483 | Y6: 9SND | Z6: 9SND | AA6: 9SNDG | AB6: 0S30G | AC6: # | AD6: N | AE6: =+VLOOKUP(Z6,'1. Input Junho 2025'!$A:$A,1,FALSE) -> #N/A | AF6: =+VLOOKUP(AA6,'1. Input Junho 2025'!$A:$A,1,FALSE) -> #N/A | AG6: =+VLOOKUP(AB6,'1. Input Junho 2025'!$A:$A,1,FALSE) -> 0S30G | AH6: =+VLOOKUP(AC6,'1. Input Junho 2025'!$A:$A,1,FALSE) -> #N/A | AI6: =+VLOOKUP(AD6,'1. Input Junho 2025'!$A:$A,1,FALSE) -> #N/A
B7: 8001732068 | C7: 0006504946 | D7: D82E | E7: # | F7: 620 | G7: EU member states | H7: NULL | I7: NULL | J7: NULL | K7: NULL | L7: NULL | M7: NULL | N7: NULL | O7: NULL | P7: 8001732068 | Q7: 4905803.860000 | R7: NULL | S7: 8001732068 | T7: 361893280.480000 | U7: 8001732068 | V7: 2025-06-30 | W7: outras empresas nao financeiras | X7: 8001732068 | Y7: D82E | Z7: D82E | AA7: D82EG | AB7: CGYNG | AC7: # | AD7: N | AE7: =+VLOOKUP(Z7,'1. Input Junho 2025'!$A:$A,1,FALSE) -> #N/A | AF7: =+VLOOKUP(AA7,'1. Input Junho 2025'!$A:$A,1,FALSE) -> #N/A | AG7: =+VLOOKUP(AB7,'1. Input Junho 2025'!$A:$A,1,FALSE) -> CGYNG | AH7: =+VLOOKUP(AC7,'1. Input Junho 2025'!$A:$A,1,FALSE) -> #N/A | AI7: =+VLOOKUP(AD7,'1. Input Junho 2025'!$A:$A,1,FALSE) -> #N/A
B8: 8008740708 | C8: 0006656255 | D8: IPR0 | E8: # | F8: 620 | G8: EU member states | H8: NULL | I8: NULL | J8: NULL | K8: NULL | L8: NULL | M8: NULL | N8: NULL | O8: NULL | P8: 8008740708 | Q8: 7369.850000 | R8: NULL | S8: 8008740708 | T8: 25553320.730000 | U8: 8008740708 | V8: 2025-06-30 | W8: outras empresas nao financeiras | X8: 8008740708 | Y8: IPR0 | Z8: IPR0 | AA8: IPR1G | AB8: 5VFRG | AC8: # | AD8: N | AE8: =+VLOOKUP(Z8,'1. Input Junho 2025'!$A:$A,1,FALSE) -> #N/A | AF8: =+VLOOKUP(AA8,'1. Input Junho 2025'!$A:$A,1,FALSE) -> #N/A | AG8: =+VLOOKUP(AB8,'1. Input Junho 2025'!$A:$A,1,FALSE) -> 5VFRG | AH8: =+VLOOKUP(AC8,'1. Input Junho 2025'!$A:$A,1,FALSE) -> #N/A | AI8: =+VLOOKUP(AD8,'1. Input Junho 2025'!$A:$A,1,FALSE) -> #N/A
B9: 8046459070 | C9: 0005301589 | D9: PUNN | E9: # | F9: 620 | G9: EU member states | H9: 8046459070 | I9: PPTCG | J9: PPTCK | K9: NULL | L9: NULL | M9: NULL | N9: NULL | O9: NULL | P9: 8046459070 | Q9: 13493287.050000 | R9: 8046459070 | S9: 8046459070 | T9: 97569351.320000 | U9: 8046459070 | V9: 2025-06-30 | W9: outras empresas nao financeiras | X9: 8046459070 | Y9: PUNN | Z9: PUNN | AA9: PUNNG | AB9: 1500G | AC9: # | AD9: Y | AE9: =+VLOOKUP(Z9,'1. Input Junho 2025'!$A:$A,1,FALSE) -> #N/A | AF9: =+VLOOKUP(AA9,'1. Input Junho 2025'!$A:$A,1,FALSE) -> #N/A | AG9: =+VLOOKUP(AB9,'1. Input Junho 2025'!$A:$A,1,FALSE) -> 1500G | AH9: =+VLOOKUP(AC9,'1. Input Junho 2025'!$A:$A,1,FALSE) -> #N/A | AI9: =+VLOOKUP(AD9,'1. Input Junho 2025'!$A:$A,1,FALSE) -> #N/A
X11: 8029317631 | Y11: PRISA
X12: 8000520483 | Y12: 0S30G
X13: 8001732068 | Y13: CGYNG
X14: 8008740708 | Y14: 5VFRG
X15: 8046459070 | Y15: 1500G

Sheet ANL1
A3: Row Labels | B3: Sum of gesi | C3: Sum of gesii | D3: Sum of gesiii | J3: flag_scib | K3: 1
A4: A | B4: 6.699286 | C4: 77.850486 | D4: 789.82552 | E4: 6.699286 | F4: 77.850486 | G4: 789.82552 | H4: =+SUM(E4,F4,G4) -> 874.37529
A5: C | B5: 48249.317 | C5: 8742.3777 | D5: 423914.77 | E5: 48249.317 | F5: 8742.3777 | G5: 423914.77 | H5: =+SUM(E5,F5,G5) -> 480906.46 | J5: Row Labels | K5: Sum of total
A6: D | B6: 62509.138 | C6: 3712.034 | D6: 87008.577 | E6: 62509.138 | F6: 3712.034 | G6: 87008.577 | H6: =+SUM(E6,F6,G6) -> 153229.75 | J6: A | K6: 874.37529
A7: E | B7: 0.159652 | C7: 0.139733 | D7: 15.545375 | E7: 0.159652 | F7: 0.139733 | G7: 15.545375 | H7: =+SUM(E7,F7,G7) -> 15.84476 | J7: B | K7: 0
A8: F | B8: 461.71584 | C8: 182.0752 | D8: 11632.712 | E8: 461.71584 | F8: 182.0752 | G8: 11632.712 | H8: =+SUM(E8,F8,G8) -> 12276.503 | J8: C | K8: 480906.46
A9: G | B9: 57348.027 | C9: 11987.388 | D9: 237481.88 | E9: 57348.027 | F9: 11987.388 | G9: 237481.88 | H9: =+SUM(E9,F9,G9) -> 306817.3 | J9: D | K9: 153229.75
A10: H | B10: 714.59982 | C10: 606.34077 | D10: 154657.04 | E10: 714.59982 | F10: 606.34077 | G10: 154657.04 | H10: =+SUM(E10,F10,G10) -> 155977.98 | J10: E | K10: 15.84476
A11: I | B11: 2.6 | C11: 1.216982 | D11: 305.91743 | E11: 2.6 | F11: 1.216982 | G11: 305.91743 | H11: =+SUM(E11,F11,G11) -> 309.73441 | J11: F | K11: 12276.503
A12: J | B12: 15.547202 | C12: 140.05209 | D12: 998.76455 | E12: 15.547202 | F12: 140.05209 | G12: 998.76455 | H12: =+SUM(E12,F12,G12) -> 1154.3638 | J12: G | K12: 306817.3
A13: M | B13: 5424.1724 | C13: 22991.281 | D13: 463689.27 | E13: 5424.1724 | F13: 22991.281 | G13: 463689.27 | H13: =+SUM(E13,F13,G13) -> 492104.73 | J13: H | K13: 155977.98
A14: N | B14: 983.67199 | C14: 9.097671 | D14: 1871.8726 | E14: 983.67199 | F14: 9.097671 | G14: 1871.8726 | H14: =+SUM(E14,F14,G14) -> 2864.6423 | J14: I | K14: 309.73441
A15: Q | B15: 84.645315 | C15: 4.223907 | D15: 91.345718 | E15: 84.645315 | F15: 4.223907 | G15: 91.345718 | H15: =+SUM(E15,F15,G15) -> 180.21494 | J15: J | K15: 1154.3638
A16: Grand Total | B16: 175800.29 | C16: 48454.078 | D16: 1382457.5 | E16: 175800.29 | F16: 48454.078 | G16: 1382457.5 | H16: =+SUM(E16,F16,G16) -> 1606711.9 | J16: K | K16: 0
J17: M | K17: 492104.73
J18: N | K18: 2864.6423
J19: Q | K19: 180.21494
J20: Grand Total | K20: 1606711.9
