Workbook

Sheet 1. Status Resumo
D11: Resumo de Testes | L11: Highlights
L12: Resumo semana atual: Equipa de tecnologia disponibilizou um total de 8 campos, bem como a correção de 3 incidências. 1. Certificação B02.00: Foram testados 5 campos disponibilizados pela equipa de IT - 1 da tabela de loan tape e 4 da tabela de output. Adicionalmente, foram re-testadas 3 incidências que foram corrigidas pela equipa de IT (1 da tabela de output e 2 da tabela de loan tape), tendo 2 campos ficado ok e 1 deles manteve-se com incidências. 2. Certificação B05.00: Não foram disponibilizados novos campos por IT na entrega de 16/12. 3. Certificação B90.00: Foram testados 3 campos disponibilizados pela equipa de IT - 1 da tabela de loan tape e 2 da tabela de output. Estes 3 campos mantêm-se com incidências. 4. Controlos: Foram efetuados 18 novos controlos, um deles com incidências. 5. Partilha de incidências: será partilhado formalmente durante o dia de hoje um novo ficheiro de incidências. Próxima semana: - Receção de 2 campos da equipa de IT (entrega a 22 de Dezembro); - Continuação da certificação dos campos da tabela de output para a totalidade do universo; - Continuação da preparação do ficheiro final de controlos em ODBC.
D13: Streams | F13: Semana Atual
F14: Por iniciar | G14: Em curso | H14: Concluído | I14: Com Incidências | J14: Pendente de desenvolv.
C15: A. Novos Campos | D15: B02.00
C16: B1. Re-especificação de campos de Sindicados | D16: Loan Tape | F16: =COUNTIFS('2. Status Detalhe Campos'!B:B,"B02.00",'2. Status Detalhe Campos'!C:C,"Loan Tape",'2. Status Detalhe Campos'!I:I,'1. Status Resumo'!$F$14) -> 0 | G16: =COUNTIFS('2. Status Detalhe Campos'!B:B,"B02.00",'2. Status Detalhe Campos'!C:C,"Loan Tape",'2. Status Detalhe Campos'!I:I,'1. Status Resumo'!$G$14) -> 1 | H16: =COUNTIFS('2. Status Detalhe Campos'!B:B,"B02.00",'2. Status Detalhe Campos'!C:C,"Loan Tape",'2. Status Detalhe Campos'!I:I,'1. Status Resumo'!$H$14) -> 23 | I16: =COUNTIFS('2. Status Detalhe Campos'!B:B,"B02.00",'2. Status Detalhe Campos'!C:C,"Loan Tape",'2. Status Detalhe Campos'!I:I,'1. Status Resumo'!$I$14) -> 6 | J16: =COUNTIFS('2. Status Detalhe Campos'!B:B,"B02.00",'2. Status Detalhe Campos'!C:C,"Loan Tape",'2. Status Detalhe Campos'!I:I,'1. Status Resumo'!$J$14) -> 0 | K16: =SUM(F16:J16) -> 30
C17: B2. Re-especificação de outros campos | D17: Tabela Output | F17: =COUNTIFS('2. Status Detalhe Campos'!B:B,"B02.00",'2. Status Detalhe Campos'!C:C,"Tabela Output",'2. Status Detalhe Campos'!I:I,'1. Status Resumo'!F14) -> 0 | G17: =COUNTIFS('2. Status Detalhe Campos'!B:B,"B02.00",'2. Status Detalhe Campos'!C:C,"Tabela Output",'2. Status Detalhe Campos'!I:I,'1. Status Resumo'!G14) -> 0 | H17: =COUNTIFS('2. Status Detalhe Campos'!B:B,"B02.00",'2. Status Detalhe Campos'!C:C,"Tabela Output",'2. Status Detalhe Campos'!I:I,'1. Status Resumo'!H14) -> 75 | I17: =COUNTIFS('2. Status Detalhe Campos'!B:B,"B02.00",'2. Status Detalhe Campos'!C:C,"Tabela Output",'2. Status Detalhe Campos'!I:I,'1. Status Resumo'!I14) -> 6 | J17: =COUNTIFS('2. Status Detalhe Campos'!B:B,"B02.00",'2. Status Detalhe Campos'!C:C,"Tabela Output",'2. Status Detalhe Campos'!I:I,'1. Status Resumo'!J14) -> 0 | K17: =SUM(F17:J17) -> 81
C18: F4. Fora âmbito | Re-especificação de campos complexos - Dem. Fin. CIB | D18: Total | F18: =SUM(F16:F17) -> 0 | G18: =SUM(G16:G17) -> 1 | H18: =SUM(H16:H17) -> 98 | I18: =SUM(I16:I17) -> 12 | J18: =SUM(J16:J17) -> 0 | K18: =SUM(F18:J18) -> 111
C19: C. Campos em testes ou c/ incidências | D19: B05.00
C20: D. Campos com NOK controlos Corporativos | D20: Loan Tape | F20: =COUNTIFS('2. Status Detalhe Campos'!B:B,"B05.00",'2. Status Detalhe Campos'!C:C,"Loan Tape",'2. Status Detalhe Campos'!I:I,'1. Status Resumo'!F14) -> 0 | G20: =COUNTIFS('2. Status Detalhe Campos'!B:B,"B05.00",'2. Status Detalhe Campos'!C:C,"Loan Tape",'2. Status Detalhe Campos'!I:I,'1. Status Resumo'!G14) -> 0 | H20: =COUNTIFS('2. Status Detalhe Campos'!B:B,"B05.00",'2. Status Detalhe Campos'!C:C,"Loan Tape",'2. Status Detalhe Campos'!I:I,'1. Status Resumo'!H14) -> 4 | I20: =COUNTIFS('2. Status Detalhe Campos'!B:B,"B05.00",'2. Status Detalhe Campos'!C:C,"Loan Tape",'2. Status Detalhe Campos'!I:I,'1. Status Resumo'!I14) -> 0 | J20: =COUNTIFS('2. Status Detalhe Campos'!B:B,"B05.00",'2. Status Detalhe Campos'!C:C,"Loan Tape",'2. Status Detalhe Campos'!I:I,'1. Status Resumo'!J14) -> 1 | K20: =SUM(F20:J20) -> 5
C21: E. Campos com outras possíveis alterações - Dependente de decisões OSI | D21: Tabela Output | F21: =COUNTIFS('2. Status Detalhe Campos'!B:B,"B05.00",'2. Status Detalhe Campos'!C:C,"Tabela Output",'2. Status Detalhe Campos'!I:I,'1. Status Resumo'!F14) -> 0 | G21: =COUNTIFS('2. Status Detalhe Campos'!B:B,"B05.00",'2. Status Detalhe Campos'!C:C,"Tabela Output",'2. Status Detalhe Campos'!I:I,'1. Status Resumo'!G14) -> 0 | H21: =COUNTIFS('2. Status Detalhe Campos'!B:B,"B05.00",'2. Status Detalhe Campos'!C:C,"Tabela Output",'2. Status Detalhe Campos'!I:I,'1. Status Resumo'!H14) -> 14 | I21: =COUNTIFS('2. Status Detalhe Campos'!B:B,"B05.00",'2. Status Detalhe Campos'!C:C,"Tabela Output",'2. Status Detalhe Campos'!I:I,'1. Status Resumo'!I14) -> 0 | J21: =COUNTIFS('2. Status Detalhe Campos'!B:B,"B05.00",'2. Status Detalhe Campos'!C:C,"Tabela Output",'2. Status Detalhe Campos'!I:I,'1. Status Resumo'!J14) -> 1 | K21: =SUM(F21:J21) -> 15
C22: F4. Fora âmbito | Re-especificação de campos complexos - Dem. Fin. CIB | D22: Total | F22: =SUM(F20:F21) -> 0 | G22: =SUM(G20:G21) -> 0 | H22: =SUM(H20:H21) -> 18 | I22: =SUM(I20:I21) -> 0 | J22: =SUM(J20:J21) -> 2 | K22: =SUM(F22:J22) -> 20
C23: F1. Fora âmbito | Campos concluídos - Sem necessidade de espec. | D23: B90.00
C24: F2. Fora âmbito | Campos em testes ou c/ incidências (LT - PM) | D24: Loan Tape | F24: =COUNTIFS('2. Status Detalhe Campos'!B:B,"B90.00",'2. Status Detalhe Campos'!C:C,"Loan Tape",'2. Status Detalhe Campos'!I:I,'1. Status Resumo'!$F$14) -> 0 | G24: =COUNTIFS('2. Status Detalhe Campos'!B:B,"B90.00",'2. Status Detalhe Campos'!C:C,"Loan Tape",'2. Status Detalhe Campos'!I:I,'1. Status Resumo'!$G$14) -> 0 | H24: =COUNTIFS('2. Status Detalhe Campos'!B:B,"B90.00",'2. Status Detalhe Campos'!C:C,"Loan Tape",'2. Status Detalhe Campos'!I:I,'1. Status Resumo'!$H$14) -> 7 | I24: =COUNTIFS('2. Status Detalhe Campos'!B:B,"B90.00",'2. Status Detalhe Campos'!C:C,"Loan Tape",'2. Status Detalhe Campos'!I:I,'1. Status Resumo'!$I$14) -> 4 | J24: =COUNTIFS('2. Status Detalhe Campos'!B:B,"B90.00",'2. Status Detalhe Campos'!C:C,"Loan Tape",'2. Status Detalhe Campos'!I:I,'1. Status Resumo'!$J$14) -> 0 | K24: =SUM(F24:J24) -> 11
C25: F3. Fora âmbito | Fonte manual LF | D25: Tabela Output | F25: =COUNTIFS('2. Status Detalhe Campos'!B:B,"B90.00",'2. Status Detalhe Campos'!C:C,"Tabela Output",'2. Status Detalhe Campos'!I:I,'1. Status Resumo'!$F$14) -> 0 | G25: =COUNTIFS('2. Status Detalhe Campos'!B:B,"B90.00",'2. Status Detalhe Campos'!C:C,"Tabela Output",'2. Status Detalhe Campos'!I:I,'1. Status Resumo'!$G$14) -> 0 | H25: =COUNTIFS('2. Status Detalhe Campos'!B:B,"B90.00",'2. Status Detalhe Campos'!C:C,"Tabela Output",'2. Status Detalhe Campos'!I:I,'1. Status Resumo'!$H$14) -> 7 | I25: =COUNTIFS('2. Status Detalhe Campos'!B:B,"B90.00",'2. Status Detalhe Campos'!C:C,"Tabela Output",'2. Status Detalhe Campos'!I:I,'1. Status Resumo'!$I$14) -> 4 | J25: =COUNTIFS('2. Status Detalhe Campos'!B:B,"B90.00",'2. Status Detalhe Campos'!C:C,"Tabela Output",'2. Status Detalhe Campos'!I:I,'1. Status Resumo'!$J$14) -> 0 | K25: =SUM(F25:J25) -> 11
C26: F4. Fora âmbito | Re-especificação de campos complexos - Dem. Fin. CIB | D26: Total | F26: =SUM(F24:F25) -> 0 | G26: =SUM(G24:G25) -> 0 | H26: =SUM(H24:H25) -> 14 | I26: =SUM(I24:I25) -> 8 | J26: =SUM(J24:J25) -> 0 | K26: =SUM(F26:J26) -> 22
D28: Resumo de Controlos
D30: Streams | F30: Semana Atual
F31: Por iniciar | G31: Em curso | H31: Concluído | I31: Com Incidências | J31: Pendente de desenvolv.
D32: B02.00 | F32: =COUNTIFS('2. Status Detalhe Campos'!$B:$B,$D$32,'2. Status Detalhe Campos'!$C:$C,"Controlos",'2. Status Detalhe Campos'!$I:$I,F$31) -> 0 | G32: =COUNTIFS('2. Status Detalhe Campos'!$B:$B,$D$32,'2. Status Detalhe Campos'!$C:$C,"Controlos",'2. Status Detalhe Campos'!$I:$I,G$31) -> 5 | H32: =COUNTIFS('2. Status Detalhe Campos'!$B:$B,$D$32,'2. Status Detalhe Campos'!$C:$C,"Controlos",'2. Status Detalhe Campos'!$I:$I,H$31) -> 142 | I32: =COUNTIFS('2. Status Detalhe Campos'!$B:$B,$D$32,'2. Status Detalhe Campos'!$C:$C,"Controlos",'2. Status Detalhe Campos'!$I:$I,I$31) -> 9 | J32: =COUNTIFS('2. Status Detalhe Campos'!$B:$B,$D$32,'2. Status Detalhe Campos'!$C:$C,"Controlos",'2. Status Detalhe Campos'!$I:$I,J$31) -> 0 | K32: =SUM(F32:J32) -> 156
D33: B05.00 | F33: =COUNTIFS('2. Status Detalhe Campos'!$B:$B,$D$33,'2. Status Detalhe Campos'!$C:$C,"Controlos",'2. Status Detalhe Campos'!$I:$I,F$31) -> 0 | G33: =COUNTIFS('2. Status Detalhe Campos'!$B:$B,$D$33,'2. Status Detalhe Campos'!$C:$C,"Controlos",'2. Status Detalhe Campos'!$I:$I,G$31) -> 0 | H33: =COUNTIFS('2. Status Detalhe Campos'!$B:$B,$D$33,'2. Status Detalhe Campos'!$C:$C,"Controlos",'2. Status Detalhe Campos'!$I:$I,H$31) -> 15 | I33: =COUNTIFS('2. Status Detalhe Campos'!$B:$B,$D$33,'2. Status Detalhe Campos'!$C:$C,"Controlos",'2. Status Detalhe Campos'!$I:$I,I$31) -> 2 | J33: =COUNTIFS('2. Status Detalhe Campos'!$B:$B,$D$33,'2. Status Detalhe Campos'!$C:$C,"Controlos",'2. Status Detalhe Campos'!$I:$I,J$31) -> 2 | K33: =SUM(F33:J33) -> 19
D34: B90.00 | F34: =COUNTIFS('2. Status Detalhe Campos'!$B:$B,$D$34,'2. Status Detalhe Campos'!$C:$C,"Controlos",'2. Status Detalhe Campos'!$I:$I,F$31) -> 0 | G34: =COUNTIFS('2. Status Detalhe Campos'!$B:$B,$D$34,'2. Status Detalhe Campos'!$C:$C,"Controlos",'2. Status Detalhe Campos'!$I:$I,G$31) -> 0 | H34: =COUNTIFS('2. Status Detalhe Campos'!$B:$B,$D$34,'2. Status Detalhe Campos'!$C:$C,"Controlos",'2. Status Detalhe Campos'!$I:$I,H$31) -> 12 | I34: =COUNTIFS('2. Status Detalhe Campos'!$B:$B,$D$34,'2. Status Detalhe Campos'!$C:$C,"Controlos",'2. Status Detalhe Campos'!$I:$I,I$31) -> 3 | J34: =COUNTIFS('2. Status Detalhe Campos'!$B:$B,$D$34,'2. Status Detalhe Campos'!$C:$C,"Controlos",'2. Status Detalhe Campos'!$I:$I,J$31) -> 0 | K34: =SUM(F34:J34) -> 15
D35: Total | F35: =SUM(F32:F34) -> 0 | G35: =SUM(G32:G34) -> 5 | H35: =SUM(H32:H34) -> 169 | I35: =SUM(I32:I34) -> 14 | J35: =SUM(J32:J34) -> 2 | K35: =SUM(F35:J35) -> 190
D42: B02.00
P45: Highlights
C46: A. Novos Campos | P46: Resumo semana atual: Foram testados 5 campos - 1 da tabela de loan tape e 4 da tabela de output; Tabela de Loan Tape (lt005_instr_ent): - 1 campo com incidências (prtn_amnt_rprtng_entty). Tabela de Output (out_B0200_main_liabilities): Foram testados 4 campos: -2 campos com incidências (0120_otstndng_amnt, 0130_rlvnt_amnt_wdc) -2 campos sem incidências (0090_prtn_amnt_rprtng_entty, 0391_nmbr_scrts_rprtng_entty) Adicionalmente, foram re-testadas 3 incidências que foram corrigidas pela equipa de IT (1 da tabela de output e 2 da tabela de loan tape). 2 destas incidências ficaram corrigidas (ID009 - typ_instrmnt e ID010 - 0140_ntr_lblty) e 1 mantém-se em aberto (ID028- otstndng_prncpl_amnt)
C47: B1. Re-especificação de campos de Sindicados
C48: B2. Re-especificação de outros campos
C50: F4. Fora âmbito | Re-especificação de campos complexos - Dem. Fin. CIB
D59: Status (campos) | E59: 46003 | F59: 46010 | G59: ∆ | J59: Status (campos) | K59: 46003 | L59: 46010 | M59: ∆
D60: Por iniciar | E60: =COUNTIFS('2. Status Detalhe Campos'!B:B,"B02.00",'2. Status Detalhe Campos'!C:C,"Loan Tape",'2. Status Detalhe Campos'!J:J,"Por iniciar") -> 0 | F60: =COUNTIFS('2. Status Detalhe Campos'!B:B,"B02.00",'2. Status Detalhe Campos'!C:C,"Loan Tape",'2. Status Detalhe Campos'!I:I,"Por iniciar") -> 0 | G60: =+F60-E60 -> 0 | H60: =+IF(F60=0,NA(),F60) -> #N/A | J60: Por iniciar | K60: =COUNTIFS('2. Status Detalhe Campos'!B:B,"B02.00",'2. Status Detalhe Campos'!C:C,"Tabela Output",'2. Status Detalhe Campos'!J:J,"Por iniciar") -> 0 | L60: =COUNTIFS('2. Status Detalhe Campos'!B:B,"B02.00",'2. Status Detalhe Campos'!C:C,"Tabela Output",'2. Status Detalhe Campos'!I:I,"Por iniciar") -> 0 | M60: =+L60-K60 -> 0 | N60: =+IF(L60=0,NA(),L60) -> #N/A
D61: Em curso | E61: =COUNTIFS('2. Status Detalhe Campos'!B:B,"B02.00",'2. Status Detalhe Campos'!C:C,"Loan Tape",'2. Status Detalhe Campos'!J:J,"Em curso") -> 2 | F61: =COUNTIFS('2. Status Detalhe Campos'!B:B,"B02.00",'2. Status Detalhe Campos'!C:C,"Loan Tape",'2. Status Detalhe Campos'!I:I,"Em curso") -> 1 | G61: =+F61-E61 -> -1 | H61: =+IF(F61=0,NA(),F61) -> 1 | J61: Em curso | K61: =COUNTIFS('2. Status Detalhe Campos'!B:B,"B02.00",'2. Status Detalhe Campos'!C:C,"Tabela Output",'2. Status Detalhe Campos'!J:J,"Em curso") -> 1 | L61: =COUNTIFS('2. Status Detalhe Campos'!B:B,"B02.00",'2. Status Detalhe Campos'!C:C,"Tabela Output",'2. Status Detalhe Campos'!I:I,"Em curso") -> 0 | M61: =+L61-K61 -> -1 | N61: =+IF(L61=0,NA(),L61) -> #N/A
D62: Concluídos | E62: =COUNTIFS('2. Status Detalhe Campos'!B:B,"B02.00",'2. Status Detalhe Campos'!C:C,"Loan Tape",'2. Status Detalhe Campos'!J:J,"Concluído") -> 21 | F62: =COUNTIFS('2. Status Detalhe Campos'!B:B,"B02.00",'2. Status Detalhe Campos'!C:C,"Loan Tape",'2. Status Detalhe Campos'!I:I,"Concluído") -> 23 | G62: =+F62-E62 -> 2 | H62: =+IF(F62=0,NA(),F62) -> 23 | J62: Concluídos | K62: =COUNTIFS('2. Status Detalhe Campos'!B:B,"B02.00",'2. Status Detalhe Campos'!C:C,"Tabela Output",'2. Status Detalhe Campos'!J:J,"Concluído") -> 72 | L62: =COUNTIFS('2. Status Detalhe Campos'!B:B,"B02.00",'2. Status Detalhe Campos'!C:C,"Tabela Output",'2. Status Detalhe Campos'!I:I,"Concluído") -> 75 | M62: =+L62-K62 -> 3 | N62: =+IF(L62=0,NA(),L62) -> 75
D63: Pendente de desenvolv. | E63: =COUNTIFS('2. Status Detalhe Campos'!B:B,"B02.00",'2. Status Detalhe Campos'!C:C,"Loan Tape",'2. Status Detalhe Campos'!J:J,"Pendente de desenvolv.") -> 1 | F63: =COUNTIFS('2. Status Detalhe Campos'!B:B,"B02.00",'2. Status Detalhe Campos'!C:C,"Loan Tape",'2. Status Detalhe Campos'!I:I,"Pendente de desenvolv.") -> 0 | G63: =+F63-E63 -> -1 | H63: =+IF(F63=0,NA(),F63) -> #N/A | J63: Pendente de desenvolv. | K63: =COUNTIFS('2. Status Detalhe Campos'!B:B,"B02.00",'2. Status Detalhe Campos'!C:C,"Tabela Output",'2. Status Detalhe Campos'!J:J,"Pendente de desenvolv.") -> 4 | L63: =COUNTIFS('2. Status Detalhe Campos'!B:B,"B02.00",'2. Status Detalhe Campos'!C:C,"Tabela Output",'2. Status Detalhe Campos'!I:I,"Pendente de desenvolv.") -> 0 | M63: =+L63-K63 -> -4 | N63: =+IF(L63=0,NA(),L63) -> #N/A
D64: Com Incidências. | E64: =COUNTIFS('2. Status Detalhe Campos'!B:B,"B02.00",'2. Status Detalhe Campos'!C:C,"Loan Tape",'2. Status Detalhe Campos'!J:J,"Com incidências") -> 6 | F64: =COUNTIFS('2. Status Detalhe Campos'!B:B,"B02.00",'2. Status Detalhe Campos'!C:C,"Loan Tape",'2. Status Detalhe Campos'!I:I,"Com incidências") -> 6 | G64: =+F64-E64 -> 0 | H64: =+IF(F64=0,NA(),F64) -> 6 | J64: Com Incidências. | K64: =COUNTIFS('2. Status Detalhe Campos'!B:B,"B02.00",'2. Status Detalhe Campos'!C:C,"Tabela Output",'2. Status Detalhe Campos'!J:J,"Com incidências") -> 4 | L64: =COUNTIFS('2. Status Detalhe Campos'!B:B,"B02.00",'2. Status Detalhe Campos'!C:C,"Tabela Output",'2. Status Detalhe Campos'!I:I,"Com incidências") -> 6 | M64: =+L64-K64 -> 2 | N64: =+IF(L64=0,NA(),L64) -> 6
D65: Total | E65: =SUM(E60:E64) -> 30 | F65: =SUM(F60:F64) -> 30 | G65: =+F65-E65 -> 0 | J65: Total | K65: =SUM(K60:K64) -> 81 | L65: =SUM(L60:L64) -> 81 | M65: =+L65-K65 -> 0
D68: B05.00
P71: Highlights
C72: A. Novos Campos | P72: Resumo semana atual: Sem alterações face à semana anterior, uma vez que não foram disponibilizados novos campos para teste.
C73: B1. Re-especificação de campos de Sindicados
C74: B2. Re-especificação de outros campos
C76: F4. Fora âmbito | Re-especificação de campos complexos - Dem. Fin. CIB
D85: Status (campos) | E85: 46003 | F85: 46010 | G85: ∆ | J85: Status (campos) | K85: 46003 | L85: 46010 | M85: ∆
D86: Por iniciar | E86: =COUNTIFS('2. Status Detalhe Campos'!B:B,"B05.00",'2. Status Detalhe Campos'!C:C,"Loan Tape",'2. Status Detalhe Campos'!J:J,"Por iniciar") -> 0 | F86: =COUNTIFS('2. Status Detalhe Campos'!B:B,"B05.00",'2. Status Detalhe Campos'!C:C,"Loan Tape",'2. Status Detalhe Campos'!I:I,"Por iniciar") -> 0 | G86: =+F86-E86 -> 0 | H86: =+IF(F86=0,NA(),F86) -> #N/A | J86: Por iniciar | K86: =COUNTIFS('2. Status Detalhe Campos'!B:B,"B05.00",'2. Status Detalhe Campos'!C:C,"Tabela Output",'2. Status Detalhe Campos'!J:J,"Por iniciar") -> 0 | L86: =COUNTIFS('2. Status Detalhe Campos'!B:B,"B05.00",'2. Status Detalhe Campos'!C:C,"Tabela Output",'2. Status Detalhe Campos'!I:I,"Por iniciar") -> 0 | M86: =+L86-K86 -> 0 | N86: =+IF(L86=0,NA(),L86) -> #N/A
D87: Em curso | E87: =COUNTIFS('2. Status Detalhe Campos'!B:B,"B05.00",'2. Status Detalhe Campos'!C:C,"Loan Tape",'2. Status Detalhe Campos'!J:J,"Em curso") -> 0 | F87: =COUNTIFS('2. Status Detalhe Campos'!B:B,"B05.00",'2. Status Detalhe Campos'!C:C,"Loan Tape",'2. Status Detalhe Campos'!I:I,"Em curso") -> 0 | G87: =+F87-E87 -> 0 | H87: =+IF(F87=0,NA(),F87) -> #N/A | J87: Em curso | K87: =COUNTIFS('2. Status Detalhe Campos'!B:B,"B05.00",'2. Status Detalhe Campos'!C:C,"Tabela Output",'2. Status Detalhe Campos'!J:J,"Em curso") -> 0 | L87: =COUNTIFS('2. Status Detalhe Campos'!B:B,"B05.00",'2. Status Detalhe Campos'!C:C,"Tabela Output",'2. Status Detalhe Campos'!I:I,"Em curso") -> 0 | M87: =+L87-K87 -> 0 | N87: =+IF(L87=0,NA(),L87) -> #N/A
D88: Concluídos | E88: =COUNTIFS('2. Status Detalhe Campos'!B:B,"B05.00",'2. Status Detalhe Campos'!C:C,"Loan Tape",'2. Status Detalhe Campos'!J:J,"Concluído") -> 4 | F88: =COUNTIFS('2. Status Detalhe Campos'!B:B,"B05.00",'2. Status Detalhe Campos'!C:C,"Loan Tape",'2. Status Detalhe Campos'!I:I,"Concluído") -> 4 | G88: =+F88-E88 -> 0 | H88: =+IF(F88=0,NA(),F88) -> 4 | J88: Concluídos | K88: =COUNTIFS('2. Status Detalhe Campos'!B:B,"B05.00",'2. Status Detalhe Campos'!C:C,"Tabela Output",'2. Status Detalhe Campos'!J:J,"Concluído") -> 14 | L88: =COUNTIFS('2. Status Detalhe Campos'!B:B,"B05.00",'2. Status Detalhe Campos'!C:C,"Tabela Output",'2. Status Detalhe Campos'!I:I,"Concluído") -> 14 | M88: =+L88-K88 -> 0 | N88: =+IF(L88=0,NA(),L88) -> 14
D89: Pendente de desenvolv. | E89: =COUNTIFS('2. Status Detalhe Campos'!B:B,"B05.00",'2. Status Detalhe Campos'!C:C,"Loan Tape",'2. Status Detalhe Campos'!J:J,"Pendente de desenvolv.") -> 1 | F89: =COUNTIFS('2. Status Detalhe Campos'!B:B,"B05.00",'2. Status Detalhe Campos'!C:C,"Loan Tape",'2. Status Detalhe Campos'!I:I,"Pendente de desenvolv.") -> 1 | G89: =+F89-E89 -> 0 | H89: =+IF(F89=0,NA(),F89) -> 1 | J89: Pendente de desenvolv. | K89: =COUNTIFS('2. Status Detalhe Campos'!B:B,"B05.00",'2. Status Detalhe Campos'!C:C,"Tabela Output",'2. Status Detalhe Campos'!J:J,"Pendente de desenvolv.") -> 1 | L89: =COUNTIFS('2. Status Detalhe Campos'!B:B,"B05.00",'2. Status Detalhe Campos'!C:C,"Tabela Output",'2. Status Detalhe Campos'!I:I,"Pendente de desenvolv.") -> 1 | M89: =+L89-K89 -> 0 | N89: =+IF(L89=0,NA(),L89) -> 1
D90: Com Incidências. | E90: =COUNTIFS('2. Status Detalhe Campos'!B:B,"B05.00",'2. Status Detalhe Campos'!C:C,"Loan Tape",'2. Status Detalhe Campos'!J:J,"Com incidências") -> 0 | F90: =COUNTIFS('2. Status Detalhe Campos'!B:B,"B05.00",'2. Status Detalhe Campos'!C:C,"Loan Tape",'2. Status Detalhe Campos'!I:I,"Com incidências") -> 0 | G90: =+F90-E90 -> 0 | H90: =+IF(F90=0,NA(),F90) -> #N/A | J90: Com Incidências. | K90: =COUNTIFS('2. Status Detalhe Campos'!B:B,"B05.00",'2. Status Detalhe Campos'!C:C,"Tabela Output",'2. Status Detalhe Campos'!J:J,"Com incidências") -> 0 | L90: =COUNTIFS('2. Status Detalhe Campos'!B:B,"B05.00",'2. Status Detalhe Campos'!C:C,"Tabela Output",'2. Status Detalhe Campos'!I:I,"Com incidências") -> 0 | M90: =+L90-K90 -> 0 | N90: =+IF(L90=0,NA(),L90) -> #N/A
D91: Total | E91: =SUM(E86:E90) -> 5 | F91: =SUM(F86:F90) -> 5 | G91: =SUM(G86:G90) -> 0 | J91: Total | K91: =SUM(K86:K90) -> 15 | L91: =SUM(L86:L90) -> 15 | M91: =SUM(M86:M90) -> 0
D93: B90.00
P96: Highlights
C97: A. Novos Campos | P97: Resumo semana atual: Foram testados 3 campos - 1 da tabela de loan tape e 2 da tabela de output; Tabelas de Loan Tape (lt003_entity): - 1 campos testado e com incidências (cntrprty_rsltn_grp). Tabela de Output (out_B9000_counterparties): - 2 campos testados, que se encontram com incidências (0030_cntrprty_rsltn_grp, 0100_rlvnt_amnt_wdc)
C98: B1. Re-especificação de campos de Sindicados
C99: B2. Re-especificação de outros campos
C101: F4. Fora âmbito | Re-especificação de campos complexos - Dem. Fin. CIB
D110: Status (campos) | E110: 46003 | F110: 46010 | G110: ∆ | J110: Status (campos) | K110: 46003 | L110: 46010 | M110: ∆
D111: Por iniciar | E111: =COUNTIFS('2. Status Detalhe Campos'!B:B,"B90.00",'2. Status Detalhe Campos'!C:C,"Loan Tape",'2. Status Detalhe Campos'!J:J,"Por iniciar") -> 0 | F111: =COUNTIFS('2. Status Detalhe Campos'!B:B,"B90.00",'2. Status Detalhe Campos'!C:C,"Loan Tape",'2. Status Detalhe Campos'!I:I,"Por iniciar") -> 0 | G111: =+F111-E111 -> 0 | H111: =+IF(F111=0,NA(),F111) -> #N/A | J111: Por iniciar | K111: =COUNTIFS('2. Status Detalhe Campos'!B:B,"B90.00",'2. Status Detalhe Campos'!C:C,"Tabela Output",'2. Status Detalhe Campos'!J:J,"Por iniciar") -> 0 | L111: =COUNTIFS('2. Status Detalhe Campos'!B:B,"B90.00",'2. Status Detalhe Campos'!C:C,"Tabela Output",'2. Status Detalhe Campos'!I:I,"Por iniciar") -> 0 | M111: =+L111-K111 -> 0 | N111: =+IF(L111=0,NA(),L111) -> #N/A
D112: Em curso | E112: =COUNTIFS('2. Status Detalhe Campos'!B:B,"B90.00",'2. Status Detalhe Campos'!C:C,"Loan Tape",'2. Status Detalhe Campos'!J:J,"Em curso") -> 0 | F112: =COUNTIFS('2. Status Detalhe Campos'!B:B,"B90.00",'2. Status Detalhe Campos'!C:C,"Loan Tape",'2. Status Detalhe Campos'!I:I,"Em curso") -> 0 | G112: =+F112-E112 -> 0 | H112: =+IF(F112=0,NA(),F112) -> #N/A | J112: Em curso | K112: =COUNTIFS('2. Status Detalhe Campos'!B:B,"B90.00",'2. Status Detalhe Campos'!C:C,"Tabela Output",'2. Status Detalhe Campos'!J:J,"Em curso") -> 0 | L112: =COUNTIFS('2. Status Detalhe Campos'!B:B,"B90.00",'2. Status Detalhe Campos'!C:C,"Tabela Output",'2. Status Detalhe Campos'!I:I,"Em curso") -> 0 | M112: =+L112-K112 -> 0 | N112: =+IF(L112=0,NA(),L112) -> #N/A
D113: Concluídos | E113: =COUNTIFS('2. Status Detalhe Campos'!B:B,"B90.00",'2. Status Detalhe Campos'!C:C,"Loan Tape",'2. Status Detalhe Campos'!J:J,"Concluído") -> 7 | F113: =COUNTIFS('2. Status Detalhe Campos'!B:B,"B90.00",'2. Status Detalhe Campos'!C:C,"Loan Tape",'2. Status Detalhe Campos'!I:I,"Concluído") -> 7 | G113: =+F113-E113 -> 0 | H113: =+IF(F113=0,NA(),F113) -> 7 | J113: Concluídos | K113: =COUNTIFS('2. Status Detalhe Campos'!B:B,"B90.00",'2. Status Detalhe Campos'!C:C,"Tabela Output",'2. Status Detalhe Campos'!J:J,"Concluído") -> 8 | L113: =COUNTIFS('2. Status Detalhe Campos'!B:B,"B90.00",'2. Status Detalhe Campos'!C:C,"Tabela Output",'2. Status Detalhe Campos'!I:I,"Concluído") -> 7 | M113: =+L113-K113 -> -1 | N113: =+IF(L113=0,NA(),L113) -> 7
D114: Pendente de desenvolv. | E114: =COUNTIFS('2. Status Detalhe Campos'!B:B,"B90.00",'2. Status Detalhe Campos'!C:C,"Loan Tape",'2. Status Detalhe Campos'!J:J,"Pendente de desenvolv.") -> 1 | F114: =COUNTIFS('2. Status Detalhe Campos'!B:B,"B90.00",'2. Status Detalhe Campos'!C:C,"Loan Tape",'2. Status Detalhe Campos'!I:I,"Pendente de desenvolv.") -> 0 | G114: =+F114-E114 -> -1 | H114: =+IF(F114=0,NA(),F114) -> #N/A | J114: Pendente de desenvolv. | K114: =COUNTIFS('2. Status Detalhe Campos'!B:B,"B90.00",'2. Status Detalhe Campos'!C:C,"Tabela Output",'2. Status Detalhe Campos'!J:J,"Pendente de desenvolv.") -> 2 | L114: =COUNTIFS('2. Status Detalhe Campos'!B:B,"B90.00",'2. Status Detalhe Campos'!C:C,"Tabela Output",'2. Status Detalhe Campos'!I:I,"Pendente de desenvolv.") -> 0 | M114: =+L114-K114 -> -2 | N114: =+IF(L114=0,NA(),L114) -> #N/A
D115: Com Incidências. | E115: =COUNTIFS('2. Status Detalhe Campos'!B:B,"B90.00",'2. Status Detalhe Campos'!C:C,"Loan Tape",'2. Status Detalhe Campos'!J:J,"Com incidências") -> 3 | F115: =COUNTIFS('2. Status Detalhe Campos'!B:B,"B90.00",'2. Status Detalhe Campos'!C:C,"Loan Tape",'2. Status Detalhe Campos'!I:I,"Com incidências") -> 4 | G115: =+F115-E115 -> 1 | H115: =+IF(F115=0,NA(),F115) -> 4 | J115: Com Incidências. | K115: =COUNTIFS('2. Status Detalhe Campos'!B:B,"B90.00",'2. Status Detalhe Campos'!C:C,"Tabela Output",'2. Status Detalhe Campos'!J:J,"Com incidências") -> 1 | L115: =COUNTIFS('2. Status Detalhe Campos'!B:B,"B90.00",'2. Status Detalhe Campos'!C:C,"Tabela Output",'2. Status Detalhe Campos'!I:I,"Com incidências") -> 4 | M115: =+L115-K115 -> 3 | N115: =+IF(L115=0,NA(),L115) -> 4
D116: Total | E116: =SUM(E111:E115) -> 11 | F116: =SUM(F111:F115) -> 11 | G116: =SUM(G111:G115) -> 0 | J116: Total | K116: =SUM(K111:K115) -> 11 | L116: =SUM(L111:L115) -> 11 | M116: =SUM(M111:M115) -> 0
D124: Status dos Controlos | P124: Highlights
P125: Resumo semana atual: Dos 18 controlos efetuados aos campos disponibilizados durante a presente semana, apenas 1 deles se econtra com incidências.
D126: Tipo de Controlo | F126: #Controlos Totais | G126: #Controlos Por Iniciar (Pendente IT) | H126: #Controlos Em Curso | I126: #Controlos OK | J126: #Controlos NOK | L126: Observações
J127: #Controlos por justificar | K127: #Controlos justificados
D128: B02.00 | F128: =+SUM(F129,F132,F135) -> 156 | G128: =+SUM(G129,G132,G135)/$F$128 -> 0 | H128: =+SUM(H129,H132,H135)/$F$128 -> 0.032051282 | I128: =+SUM(I129,I132,I135)/$F$128 -> 0.91025641 | J128: =+SUM(J129,J132,J135)/$F$128 -> 0.019230769 | K128: =+SUM(K129,K132,K135)/$F$128 -> 0.038461538
D129: Nível I | F129: =+SUM(F130:F131) -> 39 | G129: =+F129-SUM(H129:K129) -> 0 | H129: =+SUM(H130:H131) -> 2 | I129: =+SUM(I130:I131) -> 37 | J129: =+SUM(J130:J131) -> 0 | K129: =+SUM(K130:K131) -> 0
D130: High Severity | F130: =+COUNTIFS(Controlos!F:F,'1. Status Resumo'!$D$128,Controlos!D:D,"lvl1",Controlos!E:E,"h") -> 30 | G130: =+F130-SUM(H130:K130) -> 0 | H130: =+COUNTIFS(Controlos!F:F,'1. Status Resumo'!$D$128,Controlos!D:D,"lvl1",Controlos!E:E,"h",Controlos!J:J,"Em curso") -> 2 | I130: =+COUNTIFS(Controlos!F:F,'1. Status Resumo'!$D$128,Controlos!D:D,"lvl1",Controlos!E:E,"h",Controlos!J:J,"Concluído") -> 28 | J130: =+COUNTIFS(Controlos!F:F,'1. Status Resumo'!$D$128,Controlos!D:D,"lvl1",Controlos!E:E,"h",Controlos!J:J,"Com Incidências",Controlos!K:K,"") -> 0 | K130: =+COUNTIFS(Controlos!F:F,'1. Status Resumo'!$D$128,Controlos!D:D,"lvl1",Controlos!E:E,"h",Controlos!J:J,"Com Incidências",Controlos!K:K,"<>") -> 0 | L130: 2 em curso - dependem do B99.00
D131: Warning | F131: =+COUNTIFS(Controlos!F:F,'1. Status Resumo'!$D$128,Controlos!D:D,"lvl1",Controlos!E:E,"w") -> 9 | G131: =+F131-SUM(H131:K131) -> 0 | H131: =+COUNTIFS(Controlos!F:F,'1. Status Resumo'!$D$128,Controlos!D:D,"lvl1",Controlos!E:E,"w",Controlos!J:J,"Em curso") -> 0 | I131: =+COUNTIFS(Controlos!F:F,'1. Status Resumo'!$D$128,Controlos!D:D,"lvl1",Controlos!E:E,"w",Controlos!J:J,"Concluído") -> 9 | J131: =+COUNTIFS(Controlos!F:F,'1. Status Resumo'!$D$128,Controlos!D:D,"lvl1",Controlos!E:E,"w",Controlos!J:J,"Com Incidências",Controlos!K:K,"") -> 0 | K131: =+COUNTIFS(Controlos!F:F,'1. Status Resumo'!$D$128,Controlos!D:D,"lvl1",Controlos!E:E,"w",Controlos!J:J,"Com Incidências",Controlos!K:K,"<>") -> 0
D132: Nível II | F132: =+SUM(F133:F134) -> 36 | G132: =+F132-SUM(H132:K132) -> 0 | H132: =+SUM(H133:H134) -> 3 | I132: =+SUM(I133:I134) -> 31 | J132: =+SUM(J133:J134) -> 2 | K132: =+SUM(K133:K134) -> 0
D133: High Severity | F133: =+COUNTIFS(Controlos!F:F,'1. Status Resumo'!$D$128,Controlos!D:D,"lvl2",Controlos!E:E,"h") -> 33 | G133: =+F133-SUM(H133:K133) -> 0 | H133: =+COUNTIFS(Controlos!F:F,'1. Status Resumo'!$D$128,Controlos!D:D,"lvl2",Controlos!E:E,"h",Controlos!J:J,"Em curso") -> 3 | I133: =+COUNTIFS(Controlos!F:F,'1. Status Resumo'!$D$128,Controlos!D:D,"lvl2",Controlos!E:E,"h",Controlos!J:J,"Concluído") -> 28 | J133: =+COUNTIFS(Controlos!F:F,'1. Status Resumo'!$D$128,Controlos!D:D,"lvl2",Controlos!E:E,"h",Controlos!J:J,"Com Incidências",Controlos!K:K,"") -> 2 | K133: =+COUNTIFS(Controlos!F:F,'1. Status Resumo'!$D$128,Controlos!D:D,"lvl2",Controlos!E:E,"h",Controlos!J:J,"Com Incidências",Controlos!K:K,"<>") -> 0 | L133: 3 em curso - dependem do B99.00
D134: Warning | F134: =+COUNTIFS(Controlos!F:F,'1. Status Resumo'!$D$128,Controlos!D:D,"lvl2",Controlos!E:E,"w") -> 3 | G134: =+F134-SUM(H134:K134) -> 0 | H134: =+COUNTIFS(Controlos!F:F,'1. Status Resumo'!$D$128,Controlos!D:D,"lvl2",Controlos!E:E,"w",Controlos!J:J,"Em curso") -> 0 | I134: =+COUNTIFS(Controlos!F:F,'1. Status Resumo'!$D$128,Controlos!D:D,"lvl2",Controlos!E:E,"w",Controlos!J:J,"Concluído") -> 3 | J134: =+COUNTIFS(Controlos!F:F,'1. Status Resumo'!$D$128,Controlos!D:D,"lvl2",Controlos!E:E,"w",Controlos!J:J,"Com Incidências",Controlos!K:K,"") -> 0 | K134: =+COUNTIFS(Controlos!F:F,'1. Status Resumo'!$D$128,Controlos!D:D,"lvl2",Controlos!E:E,"w",Controlos!J:J,"Com Incidências",Controlos!K:K,"<>") -> 0
D135: Formatos | F135: =+COUNTIFS(Controlos!F:F,$D$128,Controlos!D:D,"frmt") -> 81 | G135: =+F135-SUM(H135:K135) -> 0 | H135: =+COUNTIFS(Controlos!F:F,'1. Status Resumo'!$D$128,Controlos!D:D,"frmt",Controlos!J:J,"Em curso") -> 0 | I135: =+COUNTIFS(Controlos!F:F,'1. Status Resumo'!$D$128,Controlos!D:D,"frmt",Controlos!J:J,"Concluído") -> 74 | J135: =+COUNTIFS(Controlos!F:F,'1. Status Resumo'!$D$128,Controlos!D:D,"frmt",Controlos!J:J,"Com Incidências",Controlos!K:K,"") -> 1 | K135: =+COUNTIFS(Controlos!F:F,'1. Status Resumo'!$D$128,Controlos!D:D,"frmt",Controlos!E:E,"f",Controlos!J:J,"Com Incidências",Controlos!K:K,"<>") -> 6 | L135: Valor 'Not applicable' justificados
D136: B05.00 | F136: =+SUM(F137,F140,F143) -> 19 | G136: =+SUM(G137,G140,G143)/$F$136 -> 0.10526316 | H136: =+SUM(H137,H140,H143)/$F$136 -> 0 | I136: =+SUM(I137,I140,I143)/$F$136 -> 0.78947368 | J136: =+SUM(J137,J140,J143)/$F$136 -> 0 | K136: =+SUM(K137,K140,K143)/$F$136 -> 0.10526316
D137: Nível I | F137: =+SUM(F138:F139) -> 0 | G137: =+F137-SUM(H137:K137) -> 0 | H137: =+SUM(H138:H139) -> 0 | I137: =+SUM(I138:I139) -> 0 | J137: =+SUM(J138:J139) -> 0 | K137: =+SUM(K138:K139) -> 0
D138: High Severity | F138: =+COUNTIFS(Controlos!F:F,$D$136,Controlos!D:D,"lvl1",Controlos!E:E,"h") -> 0 | G138: =+F138-SUM(H138:K138) -> 0 | H138: =+COUNTIFS(Controlos!F:F,$D$136,Controlos!D:D,"lvl1",Controlos!E:E,"h",Controlos!J:J,"Em curso") -> 0 | I138: =+COUNTIFS(Controlos!F:F,$D$136,Controlos!D:D,"lvl1",Controlos!E:E,"h",Controlos!J:J,"Concluído") -> 0 | J138: =+COUNTIFS(Controlos!F:F,'1. Status Resumo'!$D$136,Controlos!D:D,"lvl1",Controlos!E:E,"h",Controlos!J:J,"Com Incidências",Controlos!K:K,"") -> 0 | K138: =+COUNTIFS(Controlos!F:F,'1. Status Resumo'!$D$136,Controlos!D:D,"lvl1",Controlos!E:E,"h",Controlos!J:J,"Com Incidências",Controlos!K:K,"<>") -> 0
D139: Warning | F139: =+COUNTIFS(Controlos!F:F,$D$136,Controlos!D:D,"lvl1",Controlos!E:E,"w") -> 0 | G139: =+F139-SUM(H139:K139) -> 0 | H139: =+COUNTIFS(Controlos!F:F,$D$136,Controlos!D:D,"lvl1",Controlos!E:E,"w",Controlos!J:J,"Em curso") -> 0 | I139: =+COUNTIFS(Controlos!F:F,$D$136,Controlos!D:D,"lvl1",Controlos!E:E,"w",Controlos!J:J,"Concluído") -> 0 | J139: =+COUNTIFS(Controlos!F:F,'1. Status Resumo'!$D$136,Controlos!D:D,"lvl1",Controlos!E:E,"w",Controlos!J:J,"Com Incidências",Controlos!K:K,"") -> 0 | K139: =+COUNTIFS(Controlos!F:F,'1. Status Resumo'!$D$136,Controlos!D:D,"lvl1",Controlos!E:E,"w",Controlos!J:J,"Com Incidências",Controlos!K:K,"<>") -> 0
D140: Nível II | F140: =+SUM(F141:F142) -> 5 | G140: =+F140-SUM(H140:K140) -> 1 | H140: =+SUM(H141:H142) -> 0 | I140: =+SUM(I141:I142) -> 4 | J140: =+SUM(J141:J142) -> 0 | K140: =+SUM(K141:K142) -> 0
D141: High Severity | F141: =+COUNTIFS(Controlos!F:F,$D$136,Controlos!D:D,"lvl2",Controlos!E:E,"h") -> 5 | G141: =+F141-SUM(H141:K141) -> 1 | H141: =+COUNTIFS(Controlos!F:F,$D$136,Controlos!D:D,"lvl2",Controlos!E:E,"h",Controlos!J:J,"Em curso") -> 0 | I141: =+COUNTIFS(Controlos!F:F,$D$136,Controlos!D:D,"lvl2",Controlos!E:E,"h",Controlos!J:J,"Concluído") -> 4 | J141: =+COUNTIFS(Controlos!F:F,'1. Status Resumo'!$D$136,Controlos!D:D,"lvl2",Controlos!E:E,"h",Controlos!J:J,"Com Incidências",Controlos!K:K,"") -> 0 | K141: =+COUNTIFS(Controlos!F:F,'1. Status Resumo'!$D$136,Controlos!D:D,"lvl2",Controlos!E:E,"h",Controlos!J:J,"Com Incidências",Controlos!K:K,"<>") -> 0
D142: Warning | F142: =+COUNTIFS(Controlos!F:F,$D$136,Controlos!D:D,"lvl2",Controlos!E:E,"w") -> 0 | G142: =+F142-SUM(H142:K142) -> 0 | H142: =+COUNTIFS(Controlos!F:F,$D$136,Controlos!D:D,"lvl2",Controlos!E:E,"w",Controlos!J:J,"Em curso") -> 0 | I142: =+COUNTIFS(Controlos!F:F,$D$136,Controlos!D:D,"lvl2",Controlos!E:E,"w",Controlos!J:J,"Concluído") -> 0 | J142: =+COUNTIFS(Controlos!F:F,'1. Status Resumo'!$D$136,Controlos!D:D,"lvl2",Controlos!E:E,"w",Controlos!J:J,"Com Incidências",Controlos!K:K,"") -> 0 | K142: =+COUNTIFS(Controlos!F:F,'1. Status Resumo'!$D$136,Controlos!D:D,"lvl2",Controlos!E:E,"w",Controlos!J:J,"Com Incidências",Controlos!K:K,"<>") -> 0
D143: Formatos | F143: =+COUNTIFS(Controlos!F:F,$D$136,Controlos!D:D,"frmt") -> 14 | G143: =+F143-SUM(H143:K143) -> 1 | H143: =+COUNTIFS(Controlos!F:F,$D$136,Controlos!D:D,"frmt",Controlos!J:J,"Em curso") -> 0 | I143: =+COUNTIFS(Controlos!F:F,$D$136,Controlos!D:D,"frmt",Controlos!J:J,"Concluído") -> 11 | J143: =+COUNTIFS(Controlos!F:F,'1. Status Resumo'!$D$136,Controlos!D:D,"frmt",Controlos!J:J,"Com Incidências",Controlos!K:K,"") -> 0 | K143: =+COUNTIFS(Controlos!F:F,'1. Status Resumo'!$D$136,Controlos!D:D,"frmt",Controlos!J:J,"Com Incidências",Controlos!K:K,"<>") -> 2 | L143: Valor 'Not applicable' justificados
D144: B90.00 | F144: =+SUM(F145,F148,F151) -> 15 | G144: =+SUM(G145,G148,G151)/$F$144 -> 0 | H144: =+SUM(H145,H148,H151)/$F$144 -> 0 | I144: =+SUM(I145,I148,I151)/$F$144 -> 0.8 | J144: =+SUM(J145,J148,J151)/$F$144 -> 0.066666667 | K144: =+SUM(K145,K148,K151)/$F$144 -> 0.13333333
D145: Nível I | F145: =+SUM(F146:F147) -> 1 | G145: =+F145-SUM(H145:K145) -> 0 | H145: =+SUM(H146:H147) -> 0 | I145: =+SUM(I146:I147) -> 1 | J145: =+SUM(J146:J147) -> 0 | K145: =+SUM(K146:K147) -> 0
D146: High Severity | F146: =+COUNTIFS(Controlos!F:F,$D$144,Controlos!D:D,"lvl1",Controlos!E:E,"h") -> 1 | G146: =+F146-SUM(H146:K146) -> 0 | H146: =+COUNTIFS(Controlos!F:F,$D$144,Controlos!D:D,"lvl1",Controlos!E:E,"h",Controlos!J:J,"Em curso") -> 0 | I146: =+COUNTIFS(Controlos!F:F,$D$144,Controlos!D:D,"lvl1",Controlos!E:E,"h",Controlos!J:J,"Concluído") -> 1 | J146: =+COUNTIFS(Controlos!F:F,$D$144,Controlos!D:D,"lvl1",Controlos!E:E,"h",Controlos!J:J,"Com Incidências",Controlos!K:K,"") -> 0 | K146: =+COUNTIFS(Controlos!F:F,$D$144,Controlos!D:D,"lvl1",Controlos!E:E,"h",Controlos!J:J,"Com Incidências",Controlos!K:K,"<>") -> 0
D147: Warning | F147: =+COUNTIFS(Controlos!F:F,$D$144,Controlos!D:D,"lvl1",Controlos!E:E,"w") -> 0 | G147: =+F147-SUM(H147:K147) -> 0 | H147: =+COUNTIFS(Controlos!F:F,$D$144,Controlos!D:D,"lvl1",Controlos!E:E,"w",Controlos!J:J,"Em curso") -> 0 | I147: =+COUNTIFS(Controlos!F:F,$D$144,Controlos!D:D,"lvl1",Controlos!E:E,"w",Controlos!J:J,"Concluído") -> 0 | J147: =+COUNTIFS(Controlos!F:F,$D$144,Controlos!D:D,"lvl1",Controlos!E:E,"w",Controlos!J:J,"Com Incidências",Controlos!K:K,"") -> 0 | K147: =+COUNTIFS(Controlos!F:F,$D$144,Controlos!D:D,"lvl1",Controlos!E:E,"w",Controlos!J:J,"Com Incidências",Controlos!K:K,"<>") -> 0
D148: Nível II | F148: =+SUM(F149:F150) -> 3 | G148: =+F148-SUM(H148:K148) -> 0 | H148: =+SUM(H149:H150) -> 0 | I148: =+SUM(I149:I150) -> 2 | J148: =+SUM(J149:J150) -> 0 | K148: =+SUM(K149:K150) -> 1 | L148: Valor 'Not applicable' justificados
D149: High Severity | F149: =+COUNTIFS(Controlos!F:F,$D$144,Controlos!D:D,"lvl2",Controlos!E:E,"h") -> 3 | G149: =+F149-SUM(H149:K149) -> 0 | H149: =+COUNTIFS(Controlos!F:F,$D$144,Controlos!D:D,"lvl2",Controlos!E:E,"h",Controlos!J:J,"Em curso") -> 0 | I149: =+COUNTIFS(Controlos!F:F,$D$144,Controlos!D:D,"lvl2",Controlos!E:E,"h",Controlos!J:J,"Concluído") -> 2 | J149: =+COUNTIFS(Controlos!F:F,$D$144,Controlos!D:D,"lvl2",Controlos!E:E,"h",Controlos!J:J,"Com Incidências",Controlos!K:K,"") -> 0 | K149: =+COUNTIFS(Controlos!F:F,$D$144,Controlos!D:D,"lvl2",Controlos!E:E,"h",Controlos!J:J,"Com Incidências",Controlos!K:K,"<>") -> 1
D150: Warning | F150: =+COUNTIFS(Controlos!F:F,$D$144,Controlos!D:D,"lvl2",Controlos!E:E,"2") -> 0 | G150: =+F150-SUM(H150:K150) -> 0 | H150: =+COUNTIFS(Controlos!F:F,$D$144,Controlos!D:D,"lvl2",Controlos!E:E,"w",Controlos!J:J,"Em curso") -> 0 | I150: =+COUNTIFS(Controlos!F:F,$D$144,Controlos!D:D,"lvl2",Controlos!E:E,"w",Controlos!J:J,"Concluído") -> 0 | J150: =+COUNTIFS(Controlos!F:F,$D$144,Controlos!D:D,"lvl2",Controlos!E:E,"w",Controlos!J:J,"Com Incidências",Controlos!K:K,"") -> 0 | K150: =+COUNTIFS(Controlos!F:F,$D$144,Controlos!D:D,"lvl2",Controlos!E:E,"w",Controlos!J:J,"Com Incidências",Controlos!K:K,"<>") -> 0
D151: Formatos | F151: =+COUNTIFS(Controlos!F:F,$D$144,Controlos!D:D,"frmt") -> 11 | G151: =+F151-SUM(H151:K151) -> 0 | H151: =+COUNTIFS(Controlos!F:F,$D$144,Controlos!D:D,"frmt",Controlos!J:J,"Em curso") -> 0 | I151: =+COUNTIFS(Controlos!F:F,$D$144,Controlos!D:D,"frmt",Controlos!J:J,"Concluído") -> 9 | J151: =+COUNTIFS(Controlos!F:F,$D$144,Controlos!D:D,"frmt",Controlos!J:J,"Com Incidências",Controlos!K:K,"") -> 1 | K151: =+COUNTIFS(Controlos!F:F,$D$144,Controlos!D:D,"frmt",Controlos!J:J,"Com Incidências",Controlos!K:K,"<>") -> 1 | L151: Valor 'Not applicable' justificados
D152: Total | F152: =+SUM(F129,F132,F135,F137,F140,F143,F145,F148,F151) -> 190 | G152: =+SUM(G129,G132,G135,G137,G140,G143,G145,G148,G151) -> 2 | H152: =+SUM(H129,H132,H135,H137,H140,H143,H145,H148,H151) -> 5 | I152: =+SUM(I129,I132,I135,I137,I140,I143,I145,I148,I151) -> 169 | J152: =+SUM(J129,J132,J135,J137,J140,J143,J145,J148,J151) -> 4 | K152: =+SUM(K129,K132,K135,K137,K140,K143,K145,K148,K151) -> 10
D156: Status (Controlos) | E156: 45996 | F156: 46003 | G156: ∆
D157: Por iniciar (Pendente IT) | E157: =+E162-SUM(E158:E161) -> 20 | F157: =+$G$152 -> 2 | G157: =+F157-E157 -> -18 | H157: =+IF(F157=0,NA(),F157) -> 2
D158: Em curso | E158: =+COUNTIFS(Controlos!L:L,"Em curso") -> 5 | F158: =+$H$152 -> 5 | G158: =+F158-E158 -> 0 | H158: =+IF(F158=0,NA(),F158) -> 5
D159: OK | E159: =+COUNTIFS(Controlos!L:L,"Concluído") -> 145 | F159: =+I152 -> 169 | G159: =+F159-E159 -> 24 | H159: =+IF(F159=0,NA(),F159) -> 169
D160: NOK - Por justificar | E160: =+COUNTIFS(Controlos!L:L,"Com Incidências",Controlos!M:M,"") -> 10 | F160: =+J152 -> 4 | G160: =+F160-E160 -> -6 | H160: =+IF(F160=0,NA(),F160) -> 4
D161: NOK - Justificados | E161: =+COUNTIFS(Controlos!L:L,"Com Incidências",Controlos!M:M,"<>") -> 10 | F161: =+K152 -> 10 | G161: =+F161-E161 -> 0 | H161: =+IF(F161=0,NA(),F161) -> 10
D162: Total | E162: =+COUNTIFS(Controlos!L:L,"<>")-1 -> 190 | F162: =SUM(F157:F161) -> 190 | G162: =SUM(G157:G161) -> 0

Sheet 2. Status Detalhe Campos
A7: XXX | B7: Stream | C7: Sub-stream | D7: Loan Tape/Output Table | E7: Data field | F7: Field Status | G7: Status Especificação | H7: Status Desenvolvimento | I7: Status Atual | J7: Status Anterior | K7: Data entrega IT (real) | L7: Data conclusão | M7: Observações
A8: =+IF(C8="Loan Tape",LEFT(D8,5),B8) -> lt001 | B8: B02.00 | C8: Loan Tape | D8: lt001_univ_oper | E8: FLAG_GAR_INTRG_SAN | F8: Campo já existente no LT | G8: Concluído | H8: =+IF(C8="Controlos","Não aplicável", IFERROR(VLOOKUP(A8&"_"&E8,Testes!A:Z,25,FALSE),"Não aplicável")) -> Concluído | I8: =+IF(C8="Controlos", IFERROR(VLOOKUP(E8,Controlos!B:J,9,FALSE),"Não aplicável"), IFERROR(VLOOKUP(A8&"_"&E8,Testes!A:Z,26,FALSE),"Não aplicável")) -> Em curso | J8: Concluído | N8: =+IF(I8=J8,0,1) -> 1
A9: =+IF(C9="Loan Tape",LEFT(D9,5),B9) -> lt001 | B9: B02.00 | C9: Loan Tape | D9: lt001_univ_oper | E9: FLAG_INST_CAP | F9: Campo já existente no LT | G9: Concluído | H9: =+IF(C9="Controlos","Não aplicável", IFERROR(VLOOKUP(A9&"_"&E9,Testes!A:Z,25,FALSE),"Não aplicável")) -> Concluído | I9: =+IF(C9="Controlos", IFERROR(VLOOKUP(E9,Controlos!B:J,9,FALSE),"Não aplicável"), IFERROR(VLOOKUP(A9&"_"&E9,Testes!A:Z,26,FALSE),"Não aplicável")) -> Concluído | J9: Concluído | N9: =+IF(I9=J9,0,1) -> 0
A10: =+IF(C10="Loan Tape",LEFT(D10,5),B10) -> lt001 | B10: B02.00 | C10: Loan Tape | D10: lt001_univ_oper | E10: FLAG_INST_DIV | F10: Campo já existente no LT | G10: Concluído | H10: =+IF(C10="Controlos","Não aplicável", IFERROR(VLOOKUP(A10&"_"&E10,Testes!A:Z,25,FALSE),"Não aplicável")) -> Concluído | I10: =+IF(C10="Controlos", IFERROR(VLOOKUP(E10,Controlos!B:J,9,FALSE),"Não aplicável"), IFERROR(VLOOKUP(A10&"_"&E10,Testes!A:Z,26,FALSE),"Não aplicável")) -> Concluído | J10: Concluído | N10: =+IF(I10=J10,0,1) -> 0
A11: =+IF(C11="Loan Tape",LEFT(D11,5),B11) -> lt001 | B11: B02.00 | C11: Loan Tape | D11: lt001_univ_oper | E11: FLAG_INST_TITULOS | F11: Campo já existente no LT | G11: Concluído | H11: =+IF(C11="Controlos","Não aplicável", IFERROR(VLOOKUP(A11&"_"&E11,Testes!A:Z,25,FALSE),"Não aplicável")) -> Concluído | I11: =+IF(C11="Controlos", IFERROR(VLOOKUP(E11,Controlos!B:J,9,FALSE),"Não aplicável"), IFERROR(VLOOKUP(A11&"_"&E11,Testes!A:Z,26,FALSE),"Não aplicável")) -> Concluído | J11: Concluído | N11: =+IF(I11=J11,0,1) -> 0
A12: =+IF(C12="Loan Tape",LEFT(D12,5),B12) -> lt002 | B12: B02.00 | C12: Loan Tape | D12: lt002_instrument | E12: accntng_clssfctn | F12: Campo já existente no LT | G12: Concluído | H12: =+IF(C12="Controlos","Não aplicável", IFERROR(VLOOKUP(A12&"_"&E12,Testes!A:Z,25,FALSE),"Não aplicável")) -> Concluído | I12: =+IF(C12="Controlos", IFERROR(VLOOKUP(E12,Controlos!B:J,9,FALSE),"Não aplicável"), IFERROR(VLOOKUP(A12&"_"&E12,Testes!A:Z,26,FALSE),"Não aplicável")) -> Concluído | J12: Concluído | K12: x | N12: =+IF(I12=J12,0,1) -> 0
A13: =+IF(C13="Loan Tape",LEFT(D13,5),B13) -> lt002 | B13: B02.00 | C13: Loan Tape | D13: lt002_instrument | E13: accrd_intrst_instrmnt | F13: Campo já existente no LT - Nova Especificação | G13: Concluído | H13: =+IF(C13="Controlos","Não aplicável", IFERROR(VLOOKUP(A13&"_"&E13,Testes!A:Z,25,FALSE),"Não aplicável")) -> Concluído | I13: =+IF(C13="Controlos", IFERROR(VLOOKUP(E13,Controlos!B:J,9,FALSE),"Não aplicável"), IFERROR(VLOOKUP(A13&"_"&E13,Testes!A:Z,26,FALSE),"Não aplicável")) -> Com incidências | J13: Com incidências | N13: =+IF(I13=J13,0,1) -> 0
A14: =+IF(C14="Loan Tape",LEFT(D14,5),B14) -> lt002 | B14: B02.00 | C14: Loan Tape | D14: lt002_instrument | E14: amnt_scrty_eur | F14: Campo novo no LT | G14: Concluído | H14: =+IF(C14="Controlos","Não aplicável", IFERROR(VLOOKUP(A14&"_"&E14,Testes!A:Z,25,FALSE),"Não aplicável")) -> Concluído | I14: =+IF(C14="Controlos", IFERROR(VLOOKUP(E14,Controlos!B:J,9,FALSE),"Não aplicável"), IFERROR(VLOOKUP(A14&"_"&E14,Testes!A:Z,26,FALSE),"Não aplicável")) -> Concluído | J14: Concluído | N14: =+IF(I14=J14,0,1) -> 0
A15: =+IF(C15="Loan Tape",LEFT(D15,5),B15) -> lt002 | B15: B02.00 | C15: Loan Tape | D15: lt002_instrument | E15: amnt_scrty_fx | F15: Campo novo no LT | G15: Concluído | H15: =+IF(C15="Controlos","Não aplicável", IFERROR(VLOOKUP(A15&"_"&E15,Testes!A:Z,25,FALSE),"Não aplicável")) -> Concluído | I15: =+IF(C15="Controlos", IFERROR(VLOOKUP(E15,Controlos!B:J,9,FALSE),"Não aplicável"), IFERROR(VLOOKUP(A15&"_"&E15,Testes!A:Z,26,FALSE),"Não aplicável")) -> Concluído | J15: Concluído | N15: =+IF(I15=J15,0,1) -> 0
A16: =+IF(C16="Loan Tape",LEFT(D16,5),B16) -> lt002 | B16: B02.00 | C16: Loan Tape | D16: lt002_instrument | E16: crrncy_dnmntn | F16: Campo já existente no LT | G16: Concluído | H16: =+IF(C16="Controlos","Não aplicável", IFERROR(VLOOKUP(A16&"_"&E16,Testes!A:Z,25,FALSE),"Não aplicável")) -> Concluído | I16: =+IF(C16="Controlos", IFERROR(VLOOKUP(E16,Controlos!B:J,9,FALSE),"Não aplicável"), IFERROR(VLOOKUP(A16&"_"&E16,Testes!A:Z,26,FALSE),"Não aplicável")) -> Concluído | J16: Concluído | N16: =+IF(I16=J16,0,1) -> 0
A17: =+IF(C17="Loan Tape",LEFT(D17,5),B17) -> lt002 | B17: B02.00 | C17: Loan Tape | D17: lt002_instrument | E17: crryng_amnt_instrmnt | F17: Campo já existente no LT | G17: Concluído | H17: =+IF(C17="Controlos","Não aplicável", IFERROR(VLOOKUP(A17&"_"&E17,Testes!A:Z,25,FALSE),"Não aplicável")) -> Concluído | I17: =+IF(C17="Controlos", IFERROR(VLOOKUP(E17,Controlos!B:J,9,FALSE),"Não aplicável"), IFERROR(VLOOKUP(A17&"_"&E17,Testes!A:Z,26,FALSE),"Não aplicável")) -> Concluído | J17: Concluído | N17: =+IF(I17=J17,0,1) -> 0
A18: =+IF(C18="Loan Tape",LEFT(D18,5),B18) -> lt002 | B18: B02.00 | C18: Loan Tape | D18: lt002_instrument | E18: csd | F18: Campo novo no LT | G18: Concluído | H18: =+IF(C18="Controlos","Não aplicável", IFERROR(VLOOKUP(A18&"_"&E18,Testes!A:Z,25,FALSE),"Não aplicável")) -> Concluído | I18: =+IF(C18="Controlos", IFERROR(VLOOKUP(E18,Controlos!B:J,9,FALSE),"Não aplicável"), IFERROR(VLOOKUP(A18&"_"&E18,Testes!A:Z,26,FALSE),"Não aplicável")) -> Concluído | J18: Concluído | N18: =+IF(I18=J18,0,1) -> 0
A19: =+IF(C19="Loan Tape",LEFT(D19,5),B19) -> lt002 | B19: B02.00 | C19: Loan Tape | D19: lt002_instrument | E19: csd_lei | F19: Campo novo no LT | G19: Concluído | H19: =+IF(C19="Controlos","Não aplicável", IFERROR(VLOOKUP(A19&"_"&E19,Testes!A:Z,25,FALSE),"Não aplicável")) -> Concluído | I19: =+IF(C19="Controlos", IFERROR(VLOOKUP(E19,Controlos!B:J,9,FALSE),"Não aplicável"), IFERROR(VLOOKUP(A19&"_"&E19,Testes!A:Z,26,FALSE),"Não aplicável")) -> Concluído | J19: Concluído | N19: =+IF(I19=J19,0,1) -> 0
A20: =+IF(C20="Loan Tape",LEFT(D20,5),B20) -> lt002 | B20: B02.00 | C20: Loan Tape | D20: lt002_instrument | E20: dt_incptn | F20: Campo já existente no LT | G20: Concluído | H20: =+IF(C20="Controlos","Não aplicável", IFERROR(VLOOKUP(A20&"_"&E20,Testes!A:Z,25,FALSE),"Não aplicável")) -> Concluído | I20: =+IF(C20="Controlos", IFERROR(VLOOKUP(E20,Controlos!B:J,9,FALSE),"Não aplicável"), IFERROR(VLOOKUP(A20&"_"&E20,Testes!A:Z,26,FALSE),"Não aplicável")) -> Concluído | J20: Concluído | N20: =+IF(I20=J20,0,1) -> 0
A21: =+IF(C21="Loan Tape",LEFT(D21,5),B21) -> lt002 | B21: B02.00 | C21: Loan Tape | D21: lt002_instrument | E21: dt_lgl_fnl_mtrty | F21: Campo já existente no LT | G21: Concluído | H21: =+IF(C21="Controlos","Não aplicável", IFERROR(VLOOKUP(A21&"_"&E21,Testes!A:Z,25,FALSE),"Não aplicável")) -> Concluído | I21: =+IF(C21="Controlos", IFERROR(VLOOKUP(E21,Controlos!B:J,9,FALSE),"Não aplicável"), IFERROR(VLOOKUP(A21&"_"&E21,Testes!A:Z,26,FALSE),"Não aplicável")) -> Com incidências | J21: Com incidências | N21: =+IF(I21=J21,0,1) -> 0
A22: =+IF(C22="Loan Tape",LEFT(D22,5),B22) -> lt002 | B22: B02.00 | C22: Loan Tape | D22: lt002_instrument | E22: dt_nxt_intrst_pymnt | F22: Campo novo no LT | G22: Concluído | H22: =+IF(C22="Controlos","Não aplicável", IFERROR(VLOOKUP(A22&"_"&E22,Testes!A:Z,25,FALSE),"Não aplicável")) -> Concluído | I22: =+IF(C22="Controlos", IFERROR(VLOOKUP(E22,Controlos!B:J,9,FALSE),"Não aplicável"), IFERROR(VLOOKUP(A22&"_"&E22,Testes!A:Z,26,FALSE),"Não aplicável")) -> Com incidências | J22: Com incidências | N22: =+IF(I22=J22,0,1) -> 0
A23: =+IF(C23="Loan Tape",LEFT(D23,5),B23) -> lt002 | B23: B02.00 | C23: Loan Tape | D23: lt002_instrument | E23: elgbl_amnt_own_fnds_indvdl_lvl | F23: Campo novo no LT | G23: Concluído | H23: =+IF(C23="Controlos","Não aplicável", IFERROR(VLOOKUP(A23&"_"&E23,Testes!A:Z,25,FALSE),"Não aplicável")) -> Concluído | I23: =+IF(C23="Controlos", IFERROR(VLOOKUP(E23,Controlos!B:J,9,FALSE),"Não aplicável"), IFERROR(VLOOKUP(A23&"_"&E23,Testes!A:Z,26,FALSE),"Não aplicável")) -> Concluído | J23: Concluído | N23: =+IF(I23=J23,0,1) -> 0
A24: =+IF(C24="Loan Tape",LEFT(D24,5),B24) -> lt002 | B24: B02.00 | C24: Loan Tape | D24: lt002_instrument | E24: governing_law | F24: Campo já existente no LT | G24: Concluído | H24: =+IF(C24="Controlos","Não aplicável", IFERROR(VLOOKUP(A24&"_"&E24,Testes!A:Z,25,FALSE),"Não aplicável")) -> Concluído | I24: =+IF(C24="Controlos", IFERROR(VLOOKUP(E24,Controlos!B:J,9,FALSE),"Não aplicável"), IFERROR(VLOOKUP(A24&"_"&E24,Testes!A:Z,26,FALSE),"Não aplicável")) -> Concluído | J24: Em curso | N24: =+IF(I24=J24,0,1) -> 1
... A30: =+IF(C30="Loan Tape",LEFT(D30,5),B30) -> lt002 | B30: B02.00 | C30: Loan Tape | D30: lt002_instrument | E30: pyng_agnt_lei | F30: Campo novo no LT | G30: Concluído | H30: =+IF(C30="Controlos","Não aplicável", IFERROR(VLOOKUP(A30&"_"&E30,Testes!A:Z,25,FALSE),"Não aplicável")) -> Concluído | I30: =+IF(C30="Controlos", IFERROR(VLOOKUP(E30,Controlos!B:J,9,FALSE),"Não aplicável"), IFERROR(VLOOKUP(A30&"_"&E30,Testes!A:Z,26,FALSE),"Não aplicável")) -> Concluído | J30: Concluído | N30: =+IF(I30=J30,0,1) -> 0
A31: =+IF(C31="Loan Tape",LEFT(D31,5),B31) -> lt002 | B31: B02.00 | C31: Loan Tape | D31: lt002_instrument | E31: rank_insolv | F31: Campo novo no LT | G31: Concluído | H31: =+IF(C31="Controlos","Não aplicável", IFERROR(VLOOKUP(A31&"_"&E31,Testes!A:Z,25,FALSE),"Não aplicável")) -> Concluído | I31: =+IF(C31="Controlos", IFERROR(VLOOKUP(E31,Controlos!B:J,9,FALSE),"Não aplicável"), IFERROR(VLOOKUP(A31&"_"&E31,Testes!A:Z,26,FALSE),"Não aplicável")) -> Concluído | J31: Concluído | K31: x | N31: =+IF(I31=J31,0,1) -> 0
A32: =+IF(C32="Loan Tape",LEFT(D32,5),B32) -> lt002 | B32: B02.00 | C32: Loan Tape | D32: lt002_instrument | E32: trdng_mthd | F32: Em curso | G32: Em curso | H32: =+IF(C32="Controlos","Não aplicável", IFERROR(VLOOKUP(A32&"_"&E32,Testes!A:Z,25,FALSE),"Não aplicável")) -> Concluído | I32: =+IF(C32="Controlos", IFERROR(VLOOKUP(E32,Controlos!B:J,9,FALSE),"Não aplicável"), IFERROR(VLOOKUP(A32&"_"&E32,Testes!A:Z,26,FALSE),"Não aplicável")) -> Concluído | J32: Concluído | N32: =+IF(I32=J32,0,1) -> 0
A33: =+IF(C33="Loan Tape",LEFT(D33,5),B33) -> lt002 | B33: B02.00 | C33: Loan Tape | D33: lt002_instrument | E33: typ_instrmnt | F33: Campo já existente no LT | G33: Concluído | H33: =+IF(C33="Controlos","Não aplicável", IFERROR(VLOOKUP(A33&"_"&E33,Testes!A:Z,25,FALSE),"Não aplicável")) -> Concluído | I33: =+IF(C33="Controlos", IFERROR(VLOOKUP(E33,Controlos!B:J,9,FALSE),"Não aplicável"), IFERROR(VLOOKUP(A33&"_"&E33,Testes!A:Z,26,FALSE),"Não aplicável")) -> Concluído | J33: Com incidências | N33: =+IF(I33=J33,0,1) -> 1
A34: =+IF(C34="Loan Tape",LEFT(D34,5),B34) -> lt002 | B34: B02.00 | C34: Loan Tape | D34: lt002_instrument | E34: typ_own_fnds_indvdl_lvl | F34: Campo novo no LT | G34: Concluído | H34: =+IF(C34="Controlos","Não aplicável", IFERROR(VLOOKUP(A34&"_"&E34,Testes!A:Z,25,FALSE),"Não aplicável")) -> Concluído | I34: =+IF(C34="Controlos", IFERROR(VLOOKUP(E34,Controlos!B:J,9,FALSE),"Não aplicável"), IFERROR(VLOOKUP(A34&"_"&E34,Testes!A:Z,26,FALSE),"Não aplicável")) -> Concluído | J34: Concluído | N34: =+IF(I34=J34,0,1) -> 0
A35: =+IF(C35="Loan Tape",LEFT(D35,5),B35) -> lt003 | B35: B90.00 | C35: Loan Tape | D35: lt003_entity | E35: cntrprty_rsltn_grp | F35: Campo novo no LT | G35: Concluído | H35: =+IF(C35="Controlos","Não aplicável", IFERROR(VLOOKUP(A35&"_"&E35,Testes!A:Z,25,FALSE),"Não aplicável")) -> Concluído | I35: =+IF(C35="Controlos", IFERROR(VLOOKUP(E35,Controlos!B:J,9,FALSE),"Não aplicável"), IFERROR(VLOOKUP(A35&"_"&E35,Testes!A:Z,26,FALSE),"Não aplicável")) -> Com incidências | J35: Pendente de desenvolv. | N35: =+IF(I35=J35,0,1) -> 1
A36: =+IF(C36="Loan Tape",LEFT(D36,5),B36) -> lt003 | B36: B90.00 | C36: Loan Tape | D36: lt003_entity | E36: cntrprty_typ | F36: Por iniciar | G36: Não Concluído | H36: =+IF(C36="Controlos","Não aplicável", IFERROR(VLOOKUP(A36&"_"&E36,Testes!A:Z,25,FALSE),"Não aplicável")) -> Concluído | I36: =+IF(C36="Controlos", IFERROR(VLOOKUP(E36,Controlos!B:J,9,FALSE),"Não aplicável"), IFERROR(VLOOKUP(A36&"_"&E36,Testes!A:Z,26,FALSE),"Não aplicável")) -> Concluído | J36: Concluído | N36: =+IF(I36=J36,0,1) -> 0
A37: =+IF(C37="Loan Tape",LEFT(D37,5),B37) -> lt003 | B37: B90.00 | C37: Loan Tape | D37: lt003_entity | E37: cntry | F37: Em curso | G37: Não Concluído | H37: =+IF(C37="Controlos","Não aplicável", IFERROR(VLOOKUP(A37&"_"&E37,Testes!A:Z,25,FALSE),"Não aplicável")) -> Concluído | I37: =+IF(C37="Controlos", IFERROR(VLOOKUP(E37,Controlos!B:J,9,FALSE),"Não aplicável"), IFERROR(VLOOKUP(A37&"_"&E37,Testes!A:Z,26,FALSE),"Não aplicável")) -> Com incidências | J37: Com incidências | N37: =+IF(I37=J37,0,1) -> 0
A38: =+IF(C38="Loan Tape",LEFT(D38,5),B38) -> lt003 | B38: B90.00 | C38: Loan Tape | D38: lt003_entity | E38: entty_id | F38: Campo já existente no LT | G38: Concluído | H38: =+IF(C38="Controlos","Não aplicável", IFERROR(VLOOKUP(A38&"_"&E38,Testes!A:Z,25,FALSE),"Não aplicável")) -> Concluído | I38: =+IF(C38="Controlos", IFERROR(VLOOKUP(E38,Controlos!B:J,9,FALSE),"Não aplicável"), IFERROR(VLOOKUP(A38&"_"&E38,Testes!A:Z,26,FALSE),"Não aplicável")) -> Concluído | J38: Concluído | N38: =+IF(I38=J38,0,1) -> 0
A39: =+IF(C39="Loan Tape",LEFT(D39,5),B39) -> lt003 | B39: B90.00 | C39: Loan Tape | D39: lt003_entity | E39: entty_nm | F39: Campo já existente no LT | G39: Concluído | H39: =+IF(C39="Controlos","Não aplicável", IFERROR(VLOOKUP(A39&"_"&E39,Testes!A:Z,25,FALSE),"Não aplicável")) -> Concluído | I39: =+IF(C39="Controlos", IFERROR(VLOOKUP(E39,Controlos!B:J,9,FALSE),"Não aplicável"), IFERROR(VLOOKUP(A39&"_"&E39,Testes!A:Z,26,FALSE),"Não aplicável")) -> Com incidências | J39: Com incidências | N39: =+IF(I39=J39,0,1) -> 0
A40: =+IF(C40="Loan Tape",LEFT(D40,5),B40) -> lt003 | B40: B90.00 | C40: Loan Tape | D40: lt003_entity | E40: lei | F40: Campo já existente no LT | G40: Concluído | H40: =+IF(C40="Controlos","Não aplicável", IFERROR(VLOOKUP(A40&"_"&E40,Testes!A:Z,25,FALSE),"Não aplicável")) -> Concluído | I40: =+IF(C40="Controlos", IFERROR(VLOOKUP(E40,Controlos!B:J,9,FALSE),"Não aplicável"), IFERROR(VLOOKUP(A40&"_"&E40,Testes!A:Z,26,FALSE),"Não aplicável")) -> Concluído | J40: Concluído | N40: =+IF(I40=J40,0,1) -> 0
A41: =+IF(C41="Loan Tape",LEFT(D41,5),B41) -> lt003 | B41: B90.00 | C41: Loan Tape | D41: lt003_entity | E41: prsn_typ | F41: Em curso | G41: Não Concluído | H41: =+IF(C41="Controlos","Não aplicável", IFERROR(VLOOKUP(A41&"_"&E41,Testes!A:Z,25,FALSE),"Não aplicável")) -> Concluído | I41: =+IF(C41="Controlos", IFERROR(VLOOKUP(E41,Controlos!B:J,9,FALSE),"Não aplicável"), IFERROR(VLOOKUP(A41&"_"&E41,Testes!A:Z,26,FALSE),"Não aplicável")) -> Com incidências | J41: Com incidências | N41: =+IF(I41=J41,0,1) -> 0
A42: =+IF(C42="Loan Tape",LEFT(D42,5),B42) -> lt004 | B42: B05.00 | C42: Loan Tape | D42: lt004_protection | E42: dt_mtrty_prtctn | F42: Em curso | G42: Não Concluído | H42: =+IF(C42="Controlos","Não aplicável", IFERROR(VLOOKUP(A42&"_"&E42,Testes!A:Z,25,FALSE),"Não aplicável")) -> Concluído | I42: =+IF(C42="Controlos", IFERROR(VLOOKUP(E42,Controlos!B:J,9,FALSE),"Não aplicável"), IFERROR(VLOOKUP(A42&"_"&E42,Testes!A:Z,26,FALSE),"Não aplicável")) -> Concluído | J42: Concluído | N42: =+IF(I42=J42,0,1) -> 0
A43: =+IF(C43="Loan Tape",LEFT(D43,5),B43) -> lt004 | B43: B05.00 | C43: Loan Tape | D43: lt004_protection | E43: flg_scrd | F43: Campo novo no LT | G43: Concluído | H43: =+IF(C43="Controlos","Não aplicável", IFERROR(VLOOKUP(A43&"_"&E43,Testes!A:Z,25,FALSE),"Não aplicável")) -> Não Concluído | I43: =+IF(C43="Controlos", IFERROR(VLOOKUP(E43,Controlos!B:J,9,FALSE),"Não aplicável"), IFERROR(VLOOKUP(A43&"_"&E43,Testes!A:Z,26,FALSE),"Não aplicável")) -> Pendente de desenvolv. | J43: Pendente de desenvolv. | N43: =+IF(I43=J43,0,1) -> 0
... A129: =+IF(C129="Loan Tape",LEFT(D129,5),B129) -> B02.00 | B129: B02.00 | C129: Tabela Output | D129: out_b0200_main_liabilities | E129: 0610_crryng_amnt_ifrs | F129: Campo já existente no LT | G129: Concluído | H129: =+IF(C129="Controlos","Não aplicável", IFERROR(VLOOKUP(A129&"_"&E129,Testes!A:Z,25,FALSE),"Não aplicável")) -> Concluído | I129: =+IF(C129="Controlos", IFERROR(VLOOKUP(E129,Controlos!B:J,9,FALSE),"Não aplicável"), IFERROR(VLOOKUP(A129&"_"&E129,Testes!A:Z,26,FALSE),"Não aplicável")) -> Concluído | J129: Concluído | N129: =+IF(I129=J129,0,1) -> 0
A130: =+IF(C130="Loan Tape",LEFT(D130,5),B130) -> B02.00 | B130: B02.00 | C130: Tabela Output | D130: out_b0200_main_liabilities | E130: 0620_blnc_sht_ifrs | F130: Campo já existente no LT | G130: Concluído | H130: =+IF(C130="Controlos","Não aplicável", IFERROR(VLOOKUP(A130&"_"&E130,Testes!A:Z,25,FALSE),"Não aplicável")) -> Concluído | I130: =+IF(C130="Controlos", IFERROR(VLOOKUP(E130,Controlos!B:J,9,FALSE),"Não aplicável"), IFERROR(VLOOKUP(A130&"_"&E130,Testes!A:Z,26,FALSE),"Não aplicável")) -> Concluído | J130: Concluído | K130: x | N130: =+IF(I130=J130,0,1) -> 0
A131: =+IF(C131="Loan Tape",LEFT(D131,5),B131) -> B02.00 | B131: B02.00 | C131: Tabela Output | D131: out_b0200_main_liabilities | E131: 0630_crrying_amnt_ngaap | F131: Campo não LT (apenas tabela Output) | G131: Concluído | H131: =+IF(C131="Controlos","Não aplicável", IFERROR(VLOOKUP(A131&"_"&E131,Testes!A:Z,25,FALSE),"Não aplicável")) -> Concluído | I131: =+IF(C131="Controlos", IFERROR(VLOOKUP(E131,Controlos!B:J,9,FALSE),"Não aplicável"), IFERROR(VLOOKUP(A131&"_"&E131,Testes!A:Z,26,FALSE),"Não aplicável")) -> Concluído | J131: Concluído | N131: =+IF(I131=J131,0,1) -> 0
A132: =+IF(C132="Loan Tape",LEFT(D132,5),B132) -> B02.00 | B132: B02.00 | C132: Tabela Output | D132: out_b0200_main_liabilities | E132: 0640_blnc_sht_ngaap | F132: Campo não LT (apenas tabela Output) | G132: Concluído | H132: =+IF(C132="Controlos","Não aplicável", IFERROR(VLOOKUP(A132&"_"&E132,Testes!A:Z,25,FALSE),"Não aplicável")) -> Concluído | I132: =+IF(C132="Controlos", IFERROR(VLOOKUP(E132,Controlos!B:J,9,FALSE),"Não aplicável"), IFERROR(VLOOKUP(A132&"_"&E132,Testes!A:Z,26,FALSE),"Não aplicável")) -> Concluído | J132: Concluído | N132: =+IF(I132=J132,0,1) -> 0
A133: =+IF(C133="Loan Tape",LEFT(D133,5),B133) -> B02.00 | B133: B02.00 | C133: Tabela Output | D133: out_b0200_main_liabilities | E133: 5000_flg_shrhldr_not_rsltn_grp | F133: Campo não LT (apenas tabela Output) | G133: Concluído | H133: =+IF(C133="Controlos","Não aplicável", IFERROR(VLOOKUP(A133&"_"&E133,Testes!A:Z,25,FALSE),"Não aplicável")) -> Concluído | I133: =+IF(C133="Controlos", IFERROR(VLOOKUP(E133,Controlos!B:J,9,FALSE),"Não aplicável"), IFERROR(VLOOKUP(A133&"_"&E133,Testes!A:Z,26,FALSE),"Não aplicável")) -> Concluído | J133: Concluído | N133: =+IF(I133=J133,0,1) -> 0
A134: =+IF(C134="Loan Tape",LEFT(D134,5),B134) -> B02.00 | B134: B02.00 | C134: Tabela Output | D134: out_b0200_main_liabilities | E134: 5010_flg_art21_7a_srmr | F134: Campo não LT (apenas tabela Output) | G134: Concluído | H134: =+IF(C134="Controlos","Não aplicável", IFERROR(VLOOKUP(A134&"_"&E134,Testes!A:Z,25,FALSE),"Não aplicável")) -> Concluído | I134: =+IF(C134="Controlos", IFERROR(VLOOKUP(E134,Controlos!B:J,9,FALSE),"Não aplicável"), IFERROR(VLOOKUP(A134&"_"&E134,Testes!A:Z,26,FALSE),"Não aplicável")) -> Concluído | J134: Concluído | N134: =+IF(I134=J134,0,1) -> 0
A135: =+IF(C135="Loan Tape",LEFT(D135,5),B135) -> B02.00 | B135: B02.00 | C135: Controlos | D135: out_b0200_main_liabilities | E135: b0200_frmt_0010_row_nmbr | F135: Não aplicável | G135: Não aplicável | H135: =+IF(C135="Controlos","Não aplicável", IFERROR(VLOOKUP(A135&"_"&E135,Testes!A:Z,25,FALSE),"Não aplicável")) -> Não aplicável | I135: =+IF(C135="Controlos", IFERROR(VLOOKUP(E135,Controlos!B:J,9,FALSE),"Não aplicável"), IFERROR(VLOOKUP(A135&"_"&E135,Testes!A:Z,26,FALSE),"Não aplicável")) -> Concluído | J135: Concluído | N135: =+IF(I135=J135,0,1) -> 0
A136: =+IF(C136="Loan Tape",LEFT(D136,5),B136) -> B02.00 | B136: B02.00 | C136: Controlos | D136: out_b0200_main_liabilities | E136: b0200_frmt_0020_uniq_id | F136: Não aplicável | G136: Não aplicável | H136: =+IF(C136="Controlos","Não aplicável", IFERROR(VLOOKUP(A136&"_"&E136,Testes!A:Z,25,FALSE),"Não aplicável")) -> Não aplicável | I136: =+IF(C136="Controlos", IFERROR(VLOOKUP(E136,Controlos!B:J,9,FALSE),"Não aplicável"), IFERROR(VLOOKUP(A136&"_"&E136,Testes!A:Z,26,FALSE),"Não aplicável")) -> Concluído | J136: Concluído | N136: =+IF(I136=J136,0,1) -> 0
A137: =+IF(C137="Loan Tape",LEFT(D137,5),B137) -> B02.00 | B137: B02.00 | C137: Controlos | D137: out_b0200_main_liabilities | E137: b0200_frmt_0030_uniq_id_knwn_cntrprty | F137: Não aplicável | G137: Não aplicável | H137: =+IF(C137="Controlos","Não aplicável", IFERROR(VLOOKUP(A137&"_"&E137,Testes!A:Z,25,FALSE),"Não aplicável")) -> Não aplicável | I137: =+IF(C137="Controlos", IFERROR(VLOOKUP(E137,Controlos!B:J,9,FALSE),"Não aplicável"), IFERROR(VLOOKUP(A137&"_"&E137,Testes!A:Z,26,FALSE),"Não aplicável")) -> Concluído | J137: Concluído | N137: =+IF(I137=J137,0,1) -> 0
A138: =+IF(C138="Loan Tape",LEFT(D138,5),B138) -> B02.00 | B138: B02.00 | C138: Controlos | D138: out_b0200_main_liabilities | E138: b0200_frmt_0040_typ_uniq_id_knwn_cntrprty | F138: Não aplicável | G138: Não aplicável | H138: =+IF(C138="Controlos","Não aplicável", IFERROR(VLOOKUP(A138&"_"&E138,Testes!A:Z,25,FALSE),"Não aplicável")) -> Não aplicável | I138: =+IF(C138="Controlos", IFERROR(VLOOKUP(E138,Controlos!B:J,9,FALSE),"Não aplicável"), IFERROR(VLOOKUP(A138&"_"&E138,Testes!A:Z,26,FALSE),"Não aplicável")) -> Concluído | J138: Concluído | N138: =+IF(I138=J138,0,1) -> 0
A139: =+IF(C139="Loan Tape",LEFT(D139,5),B139) -> B02.00 | B139: B02.00 | C139: Controlos | D139: out_b0200_main_liabilities | E139: b0200_frmt_0050_orgnl_amnt_eur | F139: Não aplicável | G139: Não aplicável | H139: =+IF(C139="Controlos","Não aplicável", IFERROR(VLOOKUP(A139&"_"&E139,Testes!A:Z,25,FALSE),"Não aplicável")) -> Não aplicável | I139: =+IF(C139="Controlos", IFERROR(VLOOKUP(E139,Controlos!B:J,9,FALSE),"Não aplicável"), IFERROR(VLOOKUP(A139&"_"&E139,Testes!A:Z,26,FALSE),"Não aplicável")) -> Concluído | J139: Concluído | N139: =+IF(I139=J139,0,1) -> 0
A140: =+IF(C140="Loan Tape",LEFT(D140,5),B140) -> B02.00 | B140: B02.00 | C140: Controlos | D140: out_b0200_main_liabilities | E140: b0200_frmt_0060_orgnl_amnt_fx | F140: Não aplicável | G140: Não aplicável | H140: =+IF(C140="Controlos","Não aplicável", IFERROR(VLOOKUP(A140&"_"&E140,Testes!A:Z,25,FALSE),"Não aplicável")) -> Não aplicável | I140: =+IF(C140="Controlos", IFERROR(VLOOKUP(E140,Controlos!B:J,9,FALSE),"Não aplicável"), IFERROR(VLOOKUP(A140&"_"&E140,Testes!A:Z,26,FALSE),"Não aplicável")) -> Concluído | J140: Concluído | N140: =+IF(I140=J140,0,1) -> 0
A141: =+IF(C141="Loan Tape",LEFT(D141,5),B141) -> B02.00 | B141: B02.00 | C141: Controlos | D141: out_b0200_main_liabilities | E141: b0200_frmt_0070_cntrct_crrncy | F141: Não aplicável | G141: Não aplicável | H141: =+IF(C141="Controlos","Não aplicável", IFERROR(VLOOKUP(A141&"_"&E141,Testes!A:Z,25,FALSE),"Não aplicável")) -> Não aplicável | I141: =+IF(C141="Controlos", IFERROR(VLOOKUP(E141,Controlos!B:J,9,FALSE),"Não aplicável"), IFERROR(VLOOKUP(A141&"_"&E141,Testes!A:Z,26,FALSE),"Não aplicável")) -> Concluído | J141: Concluído | N141: =+IF(I141=J141,0,1) -> 0
A142: =+IF(C142="Loan Tape",LEFT(D142,5),B142) -> B02.00 | B142: B02.00 | C142: Controlos | D142: out_b0200_main_liabilities | E142: b0200_frmt_0080_otstndng_prncpl_amnt | F142: Não aplicável | G142: Não aplicável | H142: =+IF(C142="Controlos","Não aplicável", IFERROR(VLOOKUP(A142&"_"&E142,Testes!A:Z,25,FALSE),"Não aplicável")) -> Não aplicável | I142: =+IF(C142="Controlos", IFERROR(VLOOKUP(E142,Controlos!B:J,9,FALSE),"Não aplicável"), IFERROR(VLOOKUP(A142&"_"&E142,Testes!A:Z,26,FALSE),"Não aplicável")) -> Concluído | J142: Com Incidências | N142: =+IF(I142=J142,0,1) -> 1
... A350: =+IF(C350="Loan Tape",LEFT(D350,5),B350) -> B90.00 | B350: B90.00 | C350: Controlos | D350: out_b9000_counterparties | E350: b9000_lvl2_h_0090_cntry_cntrprty | F350: Não aplicável | G350: Não aplicável | H350: =+IF(C350="Controlos","Não aplicável", IFERROR(VLOOKUP(A350&"_"&E350,Testes!A:Z,25,FALSE),"Não aplicável")) -> Não aplicável | I350: =+IF(C350="Controlos", IFERROR(VLOOKUP(E350,Controlos!B:J,9,FALSE),"Não aplicável"), IFERROR(VLOOKUP(A350&"_"&E350,Testes!A:Z,26,FALSE),"Não aplicável")) -> Com Incidências | J350: Com Incidências | N350: =+IF(I350=J350,0,1) -> 0

Sheet Aux
B7: Field Status
B9: Campo já existente no LT
B10: Campo já existente no LT - Nova Especificação
B11: Campo novo no LT
B12: Campo via Holístico
B13: Campo não LT (apenas tabela Output)
B14: Não aplicável
B15: Em curso
B17: Status Especificação/Desenvolvimento
B18: Em curso
B19: Concluído
B20: Não aplicável
... B29: Pendente de desenvolv.

Sheet Detalhe Especificação -->

Sheet B02.00
A1: B02.00 - Main Liabilities: the tab includes the data points requested at resolution entity (point of entry) level for the implementation of the bail-in tool, or at non resolution entity level (up to the Senior Non-Preferred layer)11 for monitoring and implementing the loss transfer and recapitalisation mechanisms. Generally, the data points in this tab are requested at individual level12. However, some specific data points may be requested at consolidated level on an adhoc basis by the IRT
A2: SRB Instructions | I2: Especificação IT
I3: Fase 1 - Granular (Loan Tape) | N3: Fase 2 - Agregada (Não Loan Tape) | P3: Comentários/Histórico EF
A4: Data Point | B4: ID | C4: Data type | D4: Constrain | E4: Description | F4: Treatment of "Not applicable" (if cell is grey out, input is not expected) | G4: Treatment of "Not available" (if cell is grey out, input is not expected) | I4: Novo campo? | J4: Nome campo | K4: Missing Value (LT804) | L4: Not Applicable Value (LT804) | M4: Regra campo | N4: Nome campo | O4: Regra campo | Q4: Estado Especificação | R4: Estado Desenvolvimento | S4: Necessita de ajuste? (2025-10-31 vs 2025-11-14)
A5: Row number | B5: 0010 | C5: Numeric | D5: Integer | E5: The unique number / primary key to identify the row items (the number must be an integer). | I5: Não | N5: out_b0200_main_liabilities.0010_row_nmbr | O5: Sequenciador a implementar na tabela de output out_b0200_main_liabilities Nota: A cada execução não deverão ser gerados Row numbers diferentes pelo que provisoriamente deverá ser feito um order by instrmnt_id | P5: Reunião 2025-06-16 Luís Capitão-Mor, Pedro Mendes, Luísa Sousa | Q5: Campo não LT (apenas tabela Output) | R5: Concluído | S5: NÃO | T5: =IF(SEARCH(B5,N5,4),"ok","nok") -> ok
A6: Unique internal identification number | B6: 0020 | C6: String | D6: Free text | E6: The unique internal identifier of the instrument/liability. For deposits reported on an aggregate level, please indicate: ▪ ‘NCNP’ for the aggregated not covered not preferential deposits (field c0280 = TRUE); and ▪ ‘NCBP’ for the aggregated not covered but preferential deposits (field c0290 = TRUE). | I6: Não | J6: lt002_instrument.instrmnt_id | L6: {=_xlfn.SWITCH(C6,"Numeric","999999999999999","String","Not applicable","Date","0001-01-01")} -> Not applicable | N6: out_b0200_main_liabilities.0020_uniq_id | O6: lt002_instrument.instrmnt_id | P6: Reunião 2025-06-16 Luís Capitão-Mor, Pedro Mendes, Luísa Sousa | Q6: Campo já existente no LT | R6: Concluído | S6: NÃO | T6: =IF(SEARCH(B6,N6,4),"ok","nok") -> ok
A7: Unique identification number (known to the counterparty) | B7: 0030 | C7: String | D7: Free text | E7: The unique identifier of the instrument/liability that would allow the counterparty to conclude that it will be affected by the potential resolution action, without external third parties being able to identify the creditor. For securities, the ISIN code must be indicated where available (other identifiers need only be provided in the absence of an ISIN). For deposits and other liabilities, the account/contract number should be reported. In the event of multiple tranches (multiple counterparties) of one promissory-note loan (e.g. Schuldscheindarlehen) or a syndicated loan, a unique ID must be allocated to each tranche. For deposits reported on an aggregate level, please indicate: ▪ ‘NCNP’ for the aggregated not covered not preferential deposits (field c0280 = TRUE); and ▪ ‘NCBP’ for the aggregated not covered but preferential deposits (field c0290 = TRUE). | I7: Não | J7: lt002_instrument.isin | L7: {=_xlfn.SWITCH(C7,"Numeric","999999999999999","String","Not applicable","Date","0001-01-01")} -> Not applicable | N7: out_b0200_main_liabilities.0030_uniq_id_knwn_cntrprty | O7: lt002_instrument.isin | P7: Reunião 2025-06-16 Luís Capitão-Mor, Pedro Mendes, Luísa Sousa | Q7: Campo já existente no LT | R7: Concluído | S7: NÃO | T7: =IF(SEARCH(B7,N7,4),"ok","nok") -> ok
A8: Type of the unique identifier (known to the counterparty) | B8: 0040 | C8: String | D8: Free text, but fixed values for specific items | E8: Free text, to indicate what type of identifier has been used in data point c0020, e.g. if the identifier is an ISIN, please input ‘ISIN’; if the identifier is an account number, please input ‘Account number’; if the identifier is a contract number, please input ‘Contract number’. For deposits reported on an aggregate level, please indicate ‘Aggregated’. | I8: Não | N8: out_b0200_main_liabilities.0040_typ_uniq_id_knwn_cntrprty | O8: Valor fixo 'ISIN' | P8: Reunião 2025-06-16 Luís Capitão-Mor, Pedro Mendes, Luísa Sousa: Neste caso não faz sentido criar o campo no Loan Tape quando ele já existe, portanto será criado apenas na tabela output out_b0200_main_liabilities. Caso contrário haveria um princípio de colisão, pois estar-se-ia a repetir conceitos de campos. | Q8: Campo não LT (apenas tabela Output) | R8: Concluído | S8: NÃO | T8: =IF(SEARCH(B8,N8,4),"ok","nok") -> ok
A9: Original amount issued in EUR | B9: 50 | C9: Numeric | D9: 2 decimals | E9: The EUR (counter)value of the total issue size of the instrument, irrespective of the effective issuance dates, i.e. the total nominal amount / face value of a specific liability. For shares, it should reflect the face value / carrying amount of the shares. If a nominal value does not exist, this field is not applicable. This data point is not applicable for cash accounts / saving accounts and deposits reported in aggregated form (Submission A). If a value is reported in a foreign currency (c0060), the amount must additionally be converted into euros and reported in the corresponding EUR field (c0050), using the euro reference exchange rate published by the ECB on the date for which the information is reported40. In the case of foreign currencies for which no euro reference exchange rate is available, a customary market reference rate must be used. If such other customary reference exchange rates are used, a uniform source must be used wherever possible. | F9: Input 999999999999999 | I9: Sim | J9: lt002_instrument.orgnl_amnt_eur | L9: {=_xlfn.SWITCH(C9,"Numeric","999999999999999","String","Not applicable","Date","0001-01-01")} -> 999999999999999 | M9: Se flag_inst_titulos = '1': Obter campo nom_tot_inic da ct610_titulos. Adicionalmente, efetuar conversão via tabela cambios, seguindo a lógica definida nos restantes processos, dado que o campo nom_tot_inic está expresso na moeda original (campo cmoeda). Exemplo de query que utiliza a tabela cambios para converter moeda original em moeda eur (quando é eur a tcmbme é 1 pelo que o valor é igual): SELECT DISTINCT concat(cempresa,cbalcao, cnumecta, zdeposit), (ct610.nom_tot_inic / cambios.tcmbme) AS orgnl_amnt_eur FROM (SELECT cempresa,cbalcao, cnumecta, zdeposit, nom_tot_inic, cmoeda FROM cd_captools.ct610_titulos WHERE ref_date='${ref_date}' and concat(cempresa,cbalcao, cnumecta, zdeposit) IN ( '31641600000000000PTSTOGOM0003000', '31641600005800007PTBSRDOM0037000', '31641600005800007PTSTOCOM0007000', '31641600005800007PTCPP0AM0007000', '31641600000000000PTSTOEOM0021000', '31641600000000000PTSTOHOM0002000', '31641600000000000PTBSREOM0028000', '31641600000000000PTSTOFOM0004000')) ct610 LEFT JOIN (SELECT cmoeda, tcmbme FROM cd_captools.cambios WHERE data_date_part = '${ref_date}' AND dcambio = '${ref_date}' AND zseqcamb = 99 AND ctbcamb = 'F' AND cmarca = 'BT') cambios ON cambios.cmoeda = ct610.cmoeda; Se flag_inst_titulos = '0': Not applicable. O respetivo valor default de Not applicable deverá ser parametrizado na lt804_conf_dflt. | N9: out_b0200_main_liabilities.0050_orgnl_amnt_eur | O9: lt002_instrument.orgnl_amnt_eur | P9: Reunião 2025-08-04 Luís Capitão-Mor, Pedro Mendes, Luísa Sousa | Q9: Campo novo no LT | R9: Concluído | S9: NÃO | T9: =IF(SEARCH(B9,N9,4),"ok","nok") -> ok
A10: Original amount issued in foreign currency | B10: 0060 | C10: Numeric | D10: 2 decimals | E10: Same as c0050 above, but in the foreign currency (where relevant). Please also report the EUR-converted amount in the corresponding EUR field (c0050). This data point is not applicable for cash accounts / savings accounts and deposits reported in aggregated form (Submission A). | F10: Input 999999999999999 | I10: Sim | J10: lt002_instrument.orgnl_amnt_fx | L10: {=_xlfn.SWITCH(C10,"Numeric","999999999999999","String","Not applicable","Date","0001-01-01")} -> 999999999999999 | M10: Se flag_inst_titulos = '1' e se campo cmoeda da ct610_titulos = '978' (eur): Not applicable. O respetivo valor default de Not applicable deverá ser parametrizado na lt804_conf_dflt. Se flag_inst_titulos = '1' e se campo cmoeda da ct610_titulos <> '978' (eur): Obter campo nom_tot_inic da ct610_titulos Se flag_inst_titulos = '0': Not applicable. O respetivo valor default de Not applicable deverá ser parametrizado na lt804_conf_dflt. | N10: out_b0200_main_liabilities.0060_orgnl_amnt_fx | O10: lt002_instrument.orgnl_amnt_fx | P10: Reunião 2025-08-04 Luís Capitão-Mor, Pedro Mendes, Luísa Sousa | Q10: Campo novo no LT | R10: Concluído | S10: NÃO | T10: =IF(SEARCH(B10,N10,4),"ok","nok") -> ok
A11: Contract currency | B11: 0070 | C11: String | D11: 3-letters ISO 4217 | E11: The currency in which the instrument/liability is issued. The currency must be reported with its 3-letter ISO 4217 code. For deposits reported on an aggregate level, please indicate ‘XXX’. | F11: Input "XXX" | I11: Não | J11: lt002_instrument.crrncy_dnmntn | L11: XXX | N11: out_b0200_main_liabilities.0070_cntrct_crrncy | O11: lt002_instrument.crrncy_dnmntn | P11: Reunião 2025-06-16 Luís Capitão-Mor, Pedro Mendes, Luísa Sousa | Q11: Campo já existente no LT | R11: Concluído | S11: NÃO | T11: =IF(SEARCH(B11,N11,4),"ok","nok") -> ok
A12: Outstanding principal amount | B12: 80 | C12: Numeric | D12: 2 decimals | E12: The EUR (counter)value of the outstanding principal amount of the instrument/liability. The difference between the original amount issued and the outstanding principal amount may be due to partial buybacks of the instrument, amortising instruments, etc. The portion of eligible liabilities subscribed by intragroup entities and excluded under Article 27(3)(h) SRMR must be included in the outstanding principal amount. Only claims against other parties must be reported (i.e. excluding the portion held by the entity itself, which must be reported in field c0090). For zero coupon bonds issued at discount (i.e. c0240 = ZCB issued at discount) the final redemption amount should be reported. | I12: Sim | J12: lt005_instr_ent.otstndng_prncpl_amnt | L12: {=_xlfn.SWITCH(C12,"Numeric","999999999999999","String","Not applicable","Date","0001-01-01")} -> 999999999999999 | M12: Se flag_inst_titulos = '1': Passo 1: Verificar para cada "entty_id" (de um determinado "instrmnt_id") da lt005_instr_ent se o mesmo consta no vetor "zcliente_investidor" da ct610_titulos (desse "instrmnt_id"). Se constar, identificar em que posição consta e em seguida obter do vetor "nom_tot_ini_investe" da ct610_titulos o montante que consta nessa posição; Passo 2: Verificar se a soma dos vários "nom_tot_ini_investe" é igual ao "nom_tot_inic", da ct610_titulos -> Se for igual: Não é necessária ação adicional -> Se for diferente: Somar essa diferença no "entty_id" 0000000000 Passo 3: Dado que o "outstanding principal amount" que se pretende é o atual e não o inicial, então terá de se multiplicar os vários "nom_tot_ini_investe" pelo rácio "nom_tot_atual"/"nom_tot_inic", da ct610_titulos. Nota: O Universo do MBDT terá sempre este rácio=1 e portanto o valor inicial será igual ao valor atual, contudo, se existissem titularizações (onde se aplica o conceito de pool factor), o valor inicial seria diferente do valor atual (porque o "pool_factor" seria diferente de 1). Passo 4: Converter o montante obtido para eur pela tabela de cambios (ver query de conversão já definida no campo Original amount issued in EUR (0050)) Se flag_inst_titulos = '0': Not applicable. O respetivo valor default de Not applicable deverá ser parametrizado na lt804_conf_dflt. Na sheet "Aux Campos Montante" consta um exemplo com a aplicação desta lógica. | N12: out_b0200_main_liabilities.0080_otstndng_prncpl_amnt | O12: Soma "otstndng_prncpl_amnt" - Soma "portion_amnt_rprtng_entty", por cada instrmnt_id da lt005_instr_ent Na sheet "Aux Campos Montante" consta um exemplo com a aplicação desta lógica. | P12: Reunião 2025-10-09 Luís Capitão-Mor, Pedro Mendes Reunião 2025-09-22 e 2025-09-18 Luís Capitão-Mor, Pedro Mendes: Segundo Luís Capitão-Mor não se pode utilizar o campo OTSTNDNG_NMNL_AMNT_INSTRMNT da lt002_instrument dado que esse campo é contabilístico (a pedido do guia do BCE) e o SRB não pede contabilístico. Adicionalmente, interpretou-se da definição dada pelo SRB que se pretende retirar as recompras do BST e deve-se incluir o que está no Santander S.A (ou seja não deve se retirar o que está no Santander S.A.). Exemplo 1: Emissão de 1000M eur em que: 100M eur estão recomprados pelo BST 900M eur estão no mercado (e destes 900M eur, 500M eur estão no Santander S.A.) Ou seja, neste exemplo o Outstanding principal amount deverá ser 900M eur. Exemplo 2: Emissão 1000M eur a 95% (abaixo do par), portanto 950M eur. Na contabilidade na data inicial consta Outstanding principal amount=950M eur mas na ct610_titulos constam 1000M eur. Ou seja, o valor contabilístico nem sempre é igual ao não contabilístico. | Q12: Campo novo no LT | R12: Não Concluído | S12: NÃO | T12: =IF(SEARCH(B12,N12,4),"ok","nok") -> ok
A13: Portion of instrument or liability held by the reporting entity | B13: 0090 | C13: Numeric | D13: 2 decimals | E13: The EUR amount related to the portion of the liability held by the reporting entity itself. The amount can either be defined as the principal amount plus accrued interest and fees and charges, or as the relevant portion of fair value held by the reporting entity itself, in the event that field c0250 applies. This data point is only relevant for securities. | F13: Input 999999999999999 | I13: Sim | J13: lt005_instr_ent.prtn_amnt_rprtng_entty | L13: {=_xlfn.SWITCH(C13,"Numeric","999999999999999","String","Not applicable","Date","0001-01-01")} -> 999999999999999 | M13: Se flag_inst_titulos = '1': Verificar para cada "entty_id" (de um determinado "instrmnt_id") da lt005_instr_ent se o mesmo corresponde ao "zcliente_emitente" da ct610_titulos (desse "instrmnt_id"). Se não corresponder: Reportar 0 Se corresponder: Verificar se esse "entty_id" consta no vetor "zcliente_investidor" da ct610_titulos. Se constar: Passo 1: Identificar em que posição consta no vetor "zcliente_investidor" e em seguida obter do vetor "nom_tot_ini_investe" da ct610_titulos o montante que consta nessa posição; Passo 2: Dado que o "Portion of instrument or liability held by the reporting entity" que se pretende é o atual e não o inicial, então terá de se multiplicar o montante obtido no passo anterior pelo rácio "nom_tot_atual"/"nom_tot_inic", da ct610_titulos; Passo 3: Converter para eur pela tabela de cambios (ver query de conversão já definida no campo Original amount issued in EUR (0050)). Se não constar: Reportar 0 Se flag_inst_titulos = '0': Not applicable. O respetivo valor default de Not applicable deverá ser parametrizado na lt804_conf_dflt. Na sheet "Aux Campos Montante" consta um exemplo com a aplicação desta lógica. | N13: out_b0200_main_liabilities.0090_prtn_amnt_rprtng_entty | O13: Soma "prtn_amnt_rprtng_entty", por cada instrmnt_id da lt005_instr_ent Na sheet "Aux Campos Montante" consta um exemplo com a aplicação desta lógica. | P13: Reunião 2025-10-09 Luís Capitão-Mor, Pedro Mendes Reunião 2025-09-22 e 2025-09-18 Luís Capitão-Mor, Pedro Mendes | Q13: Campo novo no LT | R13: Não Concluído | S13: NÃO | T13: =IF(SEARCH(B13,N13,4),"ok","nok") -> ok
A14: Accrued interest | B14: 100 | C14: Numeric | D14: 2 decimals | E14: The EUR (counter)value of the outstanding accrued interest on the instrument. In jurisdictions where accrued interests do not rank pari passu to the principal liability amount, the relevant NRAs have the option to request the reporting of interest accruals on separate line items (41). Only claims against third parties must be reported (i.e. excluding the proportion held by the entity itself, which must be reported in field c0090). In case the field is not applicable (e.g. shares, zero coupon bonds issued at discount), please refer to the specific instructions in the Technical Annex. (41) - In such cases, please refer to the specific reporting example in Annex II, paragraph 3.7. | F14: Input 999999999999999 | G14: Leave blank | I14: Sim | J14: lt002_instrument.accrd_intrst_instrmnt (campo já existente a alterar) lt005_instr_ent.accrd_intrst_instrmnt (campo novo a criar) | L14: {=_xlfn.SWITCH(C14,"Numeric","999999999999999","String","Not applicable","Date","0001-01-01")} -> 999999999999999 | M14: lt002_instrument.accrd_intrst_instrmnt (campo já existente a alterar): O campo accrd_intrst_instrmnt (da lt002_instrument) está atualmente a sair com valor 0 para estes registos de Títulos Passivos (o que não é suposto dado que existem registos que deveriam ter valor). O campo accrd_intrst_instrmnt (da lt002_instrument) alimenta-se do campo juros_corridos (da lt001_univ_oper) e é calculado atualmente da seguinte forma (segundo "Especificação - BCE Loan Tape_20250915 LF + ESTR"): NVL ( SUM(-1*juros_corridos) ,0 ) O campo juros_corridos (da lt001_univ_oper) será calculado da seguinte forma (segundo re-especificação solicitada por Gonçalo Filipe, email 5 de agosto de 2025 12:58): SUM(MSALDO_FINAL) WHERE COD_PLANO = 'BST_IND' AND CCONTAB_FINAL_PCSB NOT LIKE '28%' AND COMPOSICAO_VALOR = 'juros/rendimentos a receber' AND TIPO_CONTA = 'A' AND CARTEIRA_CONTABILISTICA IN ('ativos financeiros ao custo amortizado','ativos financeiros ao justo valor atraves de outro rendimento integral','ativos financeiros ao justo valor atraves de resultados') Constata-se portanto que o campo juros_corridos (da lt001_univ_oper) não contempla atualmente o Passivo (razão pela qual o campo sai com valor 0), pelo que deverá ser adicionada a condição do "OR" abaixo: SUM(MSALDO_FINAL) WHERE ( COD_PLANO = 'BST_IND' AND CCONTAB_FINAL_PCSB NOT LIKE '28%' AND COMPOSICAO_VALOR = 'juros/rendimentos a receber' AND TIPO_CONTA = 'A' AND CARTEIRA_CONTABILISTICA IN ('ativos financeiros ao custo amortizado','ativos financeiros ao justo valor atraves de outro rendimento integral','ativos financeiros ao justo valor atraves de resultados') ) OR ( COD_PLANO = 'BST_IND' AND COMPOSICAO_VALOR = 'juros/encargos a pagar' AND TIPO_CONTA = 'P' AND CARTEIRA_CONTABILISTICA IN ('passivos financeiros ao custo amortizado') ) - Luís Capitão-Mor, Luísa Sousa, Gonçalo Filipe e Dora Roxo não identificaram impacto nesta alteração. lt005_instr_ent.accrd_intrst_instrmnt (campo novo a criar): 'Se flag_inst_titulos = '1': Efetuar exatamente a mesma especificação da lt002_instrument.accrd_intrst_instrmnt mas obtendo o valor por cada "entty_id" (na lt001_univ_oper). Ex: Para o contrato 'A' (cempresa, cbalcao, cnumecta, zdeposit) temos 3 linhas com a seguinte distribuição de juros_corridos na lt001_univ_oper: cempresa+cbalcao+cnumecta+zdeposit= 'A' | zcliente='1' | juros_corridos = 10 cempresa+cbalcao+cnumecta+zdeposit= 'A' | zcliente='2' | juros_corridos = 20 cempresa+cbalcao+cnumecta+zdeposit= 'A' | zcliente='3' | juros_corridos = 30 Atualmente o campo accrd_intrst_instrmnt da lt002_instrument calcula simplesmente a soma dos vários montantes de juros_corridos por contrato, ou seja, na lt002_instrument é apresentado uma única linha: instrmnt_id= 'A' | accrd_intrst_instrmnt = 60 O que se pretende no novo campo accrd_intrst_instrmnt a criar na lt005_instr_ent: instrmnt_id= 'A' | entty_id=1 | accrd_intrst_instrmnt = 10 instrmnt_id= 'A' | entty_id=2 | accrd_intrst_instrmnt = 20 instrmnt_id= 'A' | entty_id=3 | accrd_intrst_instrmnt = 30 Se flag_inst_titulos = '0': Not applicable. O respetivo valor default de Not applicable deverá ser parametrizado na lt804_conf_dflt. | N14: out_b0200_main_liabilities.0100_accrd_intrst_instrmnt | O14: (-1) * Soma "accrd_intrst_instrmnt ", por cada instrmnt_id da lt005_instr_ent Nota: Esta multiplicação por -1, deve-se ao facto de no Loan Tape o campo accrd_intrst_instrmnt apresentar valores negativos (para o caso destes registos de Títulos Passivos) e neste report pretenderem-se valores positivos (segundo Pedro Mendes). Ex: O contrato 31 6416 00000000000 PTBSREOM0028000 (para 2025-06-30) tem saldo de juros +418465.480000 na fr001_univ_saldo e terá +418465.480000 na lt001_univ_oper (após a nova re-especificação do Gonçalo Filipe, atualmente tem -418465.480000) e terá -418465.480000 na lt002_instrument (dada a fórmula NVL ( SUM(-1*juros_corridos) ,0 )). É portanto necessária a multiplicação por -1, ficando assim +418465.480000. Deverá ser feita a multiplicação por -1 e não o valor absoluto (abs), dado que poderá vir a existir algum contrato contra natura. | P14: Reunião 2025-10-09 Luís Capitão-Mor, Pedro Mendes Reunião 2025-09-16 Luís Capitão-Mor, Pedro Mendes, Luísa Sousa | Q14: Campo já existente no LT - Nova Especificação | R14: Concluído | S14: SIM | T14: =IF(SEARCH(B14,N14,4),"ok","nok") -> ok
A15: Applicable fees and charges | B15: 110 | C15: Numeric | D15: 2 decimals | E15: Total EUR amount of applicable fees and charges (e.g. contractual fees for late payments) linked to the instrument, if the fee or charge is payable and due, but not yet settled with the counterparty as of the request date. This is to the extent that the fee or charge is not covered within the outstanding principal amount, the accrued interest or a separate liability. Fees and charges do not include agios or fees in conjunction with the listing of an instrument. Only claims against third parties must be reported (i.e. excluding the proportion held by the entity itself, which must be reported in field c0090). In case the field is not applicable (e.g. shares), please refer to the specific instructions in the Technical Annex. | F15: Input 999999999999999 | G15: Leave blank | I15: Não | N15: out_b0200_main_liabilities.0110_applcbl_fees_charges | O15: Valor fixo 0 | P15: Reunião 2025-09-22 Luís Capitão-Mor, Pedro Mendes, Luísa Sousa Solução 1: Dado que o BST não tem comissões que ainda não tenham sido pagas/liquidadas (not yet settled) neste Universo de Títulos, reportar neste campo valor fixo 0 na tabela final (out_b0200_main_liabilities). Segundo Pedro Mendes, nem sequer existem comissões iniciais neste Universo de Títulos dado que é tudo feito internamente ou com o Banco Santander S.A.. Solução 2: Trazer as comissões periodificadas da Contabilidade, contudo, essas comissões periodificadas podem ter sido pagas ou não, pelo que não é exatamente o que o SRB pede, dado que o SRB refere que quer as não pagas. Esta solução implicaria criar um campo novo no Loan Tape e trazer um conceito que não é o que o SRB solicita. Adicionalmente o resultado deste campo seria um conjunto vazio para este Universo de Títulos. Solução 3: Criar um campo novo na ct610_titulos. Contudo, este campo seria dinâmico pelo que também não seria uma boa solução. Dadas as soluções apresentadas, optou-se pela solução 1. OLD: Reunião 31/10/2024 Luís Capitão-Mor, Pedro Mendes: Segundo Luís Capitão-Mor, Pedro Mendes, este campo aplica-se aos custos periodificados do banco (ainda não pagos, que estão pendentes de pagar) nas emissões que o Banco faz de covered bonds, seniores,... (estão no Passivo do Banco), tem de se pagar aos Advogados, etc. Naturalmente, este campo não se aplica a Depósitos. Ações solicitadas por Luís Capitão-Mor: - Agendar reunião com Rafael Pessoa/Carlos Fernandes para ver onde constam estes custos na fr802 (devem ter uma conta contabilistica), levando para a reunião 2 exemplos de covered bonds: 1) Identificar esses 2 exemplos para uma data mais recente; 2) Verificar na ct001 quais as contas PCSB (uma conta 50%) e IFRS associadas; 3) Verificar se para essas contas consta na composicao_valor ou noutro campo da fr802 a indicação de comissão ou despesa 4) Verificar se esta comissão ficou ou não incluida no gross carrying amount (provavelmente foi incluido). 5) Verificar na fr004 se já existe lá este conceito de comissão (só seria para adicionar na fr004 caso fosse um conceito que faça sentido para a contabilidade) 6) Tabela de conceitos ct872 (tem os conceitos com base em campos da fr802): criar nesta tabela o conceito caso ele não exista. | Q15: Campo não LT (apenas tabela Output) | R15: Concluído | S15: NÃO | T15: =IF(SEARCH(B15,N15,4),"ok","nok") -> ok
A16: Outstanding amount | B16: 0120 | C16: Numeric | D16: 2 decimals | E16: Total EUR value of the outstanding amount of the instrument/deposit held by the counterparty, calculated as the sum of the amounts reported in data points c0080, c0100 and c0110 (where applicable). The amount is in fact the aggregate of the outstanding principal amount plus, if applicable, interest accrued up to the reference date, and fees and charges, irrespective of whether and to what extent the relevant principal, interest or fee-and-charge liability was already due as at the reference date and whether it is required to be recognised as a liability item in the relevant entity’s balance sheet drawn up in accordance with the applicable accounting principles. In jurisdictions where accrued interest may not rank pari passu to the liability amount, the relevant NRA may request the reporting of interest accruals on separate line items. | F16: Input 999999999999999 | I16: Não | N16: out_b0200_main_liabilities.0120_otstndng_amnt | O16: Soma dos 3 campos acima (0080, 0100 e 0110 ): Outstanding principal amount + Accrued interest + Applicable fees and charges | P16: Reunião 2025-10-09 Luís Capitão-Mor, Pedro Mendes Reunião 2025-09-22 Luís Capitão-Mor, Pedro Mendes, Luísa Sousa: Tem de se ter presente que neste campo vamos somar o "Outstanding principal amount" (que não é contabilístico, vem da ct610_titulos) com o "Accrued interest" (que é contabilístico) e com o "Applicable fees and charges" (que é contabilístico). Ou seja, 2 campos vão-se buscar à Contabilidade mas 1 campo não se vai buscar à Contabilidade, o que não é totalmente coerente. Contudo, não se vê tema dado que o SRB não refere que este campo tem de "bater" com a Contabilidade. | Q16: Campo não LT (apenas tabela Output) | R16: Não Concluído | S16: SIM | T16: =IF(SEARCH(B16,N16,4),"ok","nok") -> ok
A17: Relevant amount for Bail-in/WDC | B17: 0130 | C17: Numeric | D17: 2 decimals | E17: Total EUR value of the amount eligible for write-down / conversion. Pursuant to Article 48(1) BRRD, resolution authorities shall exercise the write-down and conversion powers in accordance with the cascade set out in letters (a) to (e) of Article 48(1) BRRD. Article 48(2) BRRD further provides that "when applying the write down or conversion powers, resolution authorities shall allocate the losses [...] by reducing the principal amount of, or outstanding amount payable in respect of, those shares or other instruments of ownership and bail-inable liabilities to the same extent pro rata to their value (42) […]". The portion of eligible liabilities subscribed by intragroup entities and excluded under Article 27(3)(h) SRMR must not be reported as part of the relevant amount for bail-in / WDC. When determining the relevant amount for bail-in, entities shall take into account national laws that transpose the BRRD. If those provisions do not provide complete and clear guidance for determining the relevant amount for bail-in, careful consideration should in general be given to how the item in question is dealt with under applicable insolvency legislation43. Furthermore, the contractual terms governing each liability might provide additional insight when performing this assessment. For debt instruments with embedded derivatives, the following list of items shall be considered: ▪ Any contractually defined floor or cap to the final redemption amount. ▪ Any contractually defined early termination amount, if such amount is deemed to represent the investor’s claim in insolvency/resolution. ▪ The performance of the underlying, whenever it impacts the repayment of the principal amount. ▪ The contractual provisions ruling the payment of interests, to assess whether the accrued component can be properly determined and is relevant for bail-in purposes. ▪ The inclusion of an Article 12c(2)(b) SRMR clause. ▪ Any element relevant to Article 12c(2)(a) SRMR. ▪ Any settlement/close out costs. ▪ Any other term, condition, rule, mechanism or element affecting the making, timing and amount of any kind of payment owed to the holders of the debt instruments with embedded derivatives (please specify). Without prejudice to the considerations above, in principle: • the relevant amount for bail-in is defined as the outstanding amount (including accrued interest and fees, when applicable) less any existing components subject to exemptions according to Article 27(3) SRMR (e.g. covered share for bail-inable deposits indicated in data point c0300), or other factors affecting the conversion amount (e.g. safeguards under Articles 76 to 80 BRRD, as applicable); • for zero coupon bonds issued at discount (i.e. c0240 = ZCB issued at discount), the amount to be reported is the amortised face value (i.e. initially paid up amount plus accrued component of the discount) plus any applicable fees and charges (c0110); and • for structured instruments, the amount reported in field c0270 minus the value of the collateral (if given) should in principle be considered the relevant amount. In case of products where the derivative component is only affecting the coupon payment (i.e. c0250 = Only structured coupon), please refer to the points above.applicable insolvency legislation43. Furthermore, the contractual terms governing each liability might provide additional insight when performing this assessment. For debt instruments with embedded derivatives, the following list of items shall be considered: ▪ Any contractually defined floor or cap to the final redemption amount. ▪ Any contractually defined early termination amount, if such amount is deemed to represent the investor’s claim in insolvency/resolution. ▪ The performance of the underlying, whenever it impacts the repayment of the principal amount. ▪ The contractual provisions ruling the payment of interests, to assess whether the accrued component can be properly determined and is relevant for bail-in purposes. ▪ The inclusion of an Article 12c(2)(b) SRMR clause. ▪ Any element relevant to Article 12c(2)(a) SRMR. ▪ Any settlement/close out costs. ▪ Any other term, condition, rule, mechanism or element affecting the making, timing and amount of any kind of payment owed to the holders of the debt instruments with embedded derivatives (please specify). Without prejudice to the considerations above, in principle: • the relevant amount for bail-in is defined as the outstanding amount (including accrued interest and fees, when applicable) less any existing components subject to exemptions according to Article 27(3) SRMR (e.g. covered share for bail-inable deposits indicated in data point c0300), or other factors affecting the conversion amount (e.g. safeguards under Articles 76 to 80 BRRD, as applicable); • for zero coupon bonds issued at discount (i.e. c0240 = ZCB issued at discount), the amount to be reported is the amortised face value (i.e. initially paid up amount plus accrued component of the discount) plus any applicable fees and charges (c0110); and • for structured instruments, the amount reported in field c0270 minus the value of the collateral (if given) should in principle be considered the relevant amount. In case of products where the derivative component is only affecting the coupon payment (i.e. c0250 = Only structured coupon), please refer to the points above. In jurisdictions where accrued interest may not rank pari passu to the liability amount, the relevant NRA may request the reporting of interest accruals on separate line items. Own holdings (identified in field c0090) should be deducted. (42) - For the definition of ‘value’, please refer to EBA Q&A 2017_3629 (https://www.eba.europa.eu/single-rule-book-qa/- /qna/view/publicId/2017_3629). | I17: Não | N17: out_b0200_main_liabilities.0130_rlvnt_amnt_wdc | O17: Reportar Outstanding amount (0120) | P17: Reunião 2025-09-24 Luís Capitão-Mor, Pedro Mendes: Segundo Pedro Mendes, neste campo deve reportar-se o mesmo que é reportado no Outstanding amount (0120). O Outstanding amount (0120) é a Soma de 3 campos: Outstanding principal amount (0080) + Accrued interest (0100) + Applicable fees and charges (0110). Não se deve reportar o Outstanding principal amount (0040) dado que não contém juros, e segundo Pedro Mendes em caso de resolução os juros devem ser considerados (apesar de na definição não ser referido pelo SRB que se pretende juros), como tal, deve apontar-se para o Outstanding amount (0120), que contém juros. O Outstanding amount (0120) também contém Applicable fees and charges (0110), mas esse campo conterá valor fixo 0. | Q17: Campo não LT (apenas tabela Output) | R17: Não Concluído | S17: SIM | T17: =IF(SEARCH(B17,N17,4),"ok","nok") -> ok
A18: Nature of the liability | B18: 0140 | C18: String | D18: Drop-down | E18: The corresponding category of the instrument/liability. Value to be chosen from the following drop-down list: • Registered Bond • Bearer Bond • Borrower Note Loan • Certificate of Deposit / Commercial paper • Title of ownership44 • Cash account/saving account45 • Term deposit46 • Loan • Bill of exchange • Other For deposits reported on an aggregated level (Submission A), please indicate ‘Other’. | I18: Não | J18: lt002_instrument.typ_instrmnt | L18: {=_xlfn.SWITCH(C18,"Numeric","999999999999999","String","Not applicable","Date","0001-01-01")} -> Not applicable | M18: Necessário criar novas parametrizações nas tabelas lt829_regras_conversao e lt830_conversoes, podendo as mesmas ser consultadas neste documento nas sheets: LT829 - filtrando por campo_conceito = 'TYP_INSTRMNT' e regra_conversao = '2'; LT830 - filtrando por segmento = 'ESTR' e campo_conceito = 'TYP_INSTRMNT'. | N18: out_b0200_main_liabilities.0140_ntr_lblty | O18: lt002_instrument.typ_instrmnt | P18: Parametrizações da lt829_regras_conversao e da lt830_conversoes validadas com Luísa Sousa em 2025-08-13. Adicionalmente, acrescentou-se na lt831_param_conceitos uma nova linha com instrmnt_fncr='titulos de divida emitidos' a mapear para o valor_destino='1005' dado que estes registos estavam a ser preenchidos com typ_instrmnt= '2020' (ou seja, 'Other'). Reunião 2025-07-25 Luís Capitão-Mor, Luísa Sousa | Q18: Campo já existente no LT | R18: Concluído | S18: NÃO | T18: =IF(SEARCH(B18,N18,4),"ok","nok") -> ok
A19: Nature of the liability (if other) | B19: 0141 | C19: String | D19: Free text | E19: Free text. If ‘Other’ is selected in field c0140, include a meaningful description of the nature of the liability. | I19: Não | N19: out_b0200_main_liabilities.0141_ntr_lblty_othr | O19: Valor fixo 'Not applicable' | P19: Reunião 2025-07-25 Luís Capitão-Mor, Luísa Sousa: | Q19: Campo não LT (apenas tabela Output) | R19: Concluído | S19: NÃO | T19: =IF(SEARCH(B19,N19,4),"ok","nok") -> ok
A20: Structurally subordinated | B20: 0150 | C20: String | D20: TRUE / FALSE boolean | E20: Indicate whether the instrument is considered structurally subordinated (i.e. groups with a HoldCo/OpCo structure). The value to be reported is a TRUE/FALSE Boolean. | I20: Não | N20: out_b0200_main_liabilities.0150_flg_strctrlly_sbrdntd | O20: Valor fixo 'Not applicable' | P20: Reunião 2025-06-23 Luís Capitão-Mor, Pedro Mendes, Luísa Sousa: Segundo o anexo III, este campo deve, em princípio, ser considerado não aplicável para non-resolution entities. Pedro Mendes enviou email dia 24-06 confirmando que este campo é não aplicável. "Sim, confirmo que todos os campos são não aplicáveis." | Q20: Campo não LT (apenas tabela Output) | R20: Concluído | S20: NÃO | T20: =IF(SEARCH(B20,N20,4),"ok","nok") -> ok
A21: Insolvency ranking | B21: 0160 | C21: Numeric | D21: Integer | E21: The corresponding insolvency ranking of the instrument. Numeric value (e.g. integer of 1 or more). | I21: Sim | J21: lt002_instrument.rank_insolv | L21: {=_xlfn.SWITCH(C21,"Numeric","999999999999999","String","Not applicable","Date","0001-01-01")} -> 999999999999999 | M21: Se flag_inst_titulos = '1': Obter rank_insolv da ct610_titulos; Se flag_inst_titulos = '0': Não preencher | N21: out_b0200_main_liabilities.0160_rank_insolv | O21: lt002_instrument.rank_insolv | P21: Reunião 2025-06-20 Luís Capitão-Mor, Pedro Mendes, Luísa Sousa | Q21: Campo novo no LT | R21: Concluído | S21: NÃO | T21: =IF(SEARCH(B21,N21,4),"ok","nok") -> ok
A22: Contractual subordination | B22: 0161 | C22: Numeric | D22: 2 decimals | E22: Numeric sequence to indicate whether an instrument/liability is subordinated within the same insolvency rank as a result of its own contractual terms. The inclusion of these contractual terms should duly consider paragraph 141 of the EBA report on the monitoring of Additional Tier 1 (AT1) instruments of European Union (EU) institutions47, as well as any country-specific provision in this regard. The value of the field must be indicated using the corresponding insolvency ranking to which the instrument pertains and the numeric sequence of its contractual subordination, separated by a dot (e.g. two instruments in insolvency rank 2 subordinated to each other will have this field set to 2.01 and 2.02). Please refer to the specific reporting example (Annex II, paragraph 3.6). | F22: Input 999999999999999 | I22: Não | N22: out_b0200_main_liabilities.0161_cntrctl_sbrdntn | O22: Valor fixo 999999999999999 | P22: Reunião 2025-07-31 Luís Capitão-Mor, Pedro Mendes: Segundo Pedro Mendes, este campo é not applicable porque na nossa operativa as emissões têm sempre o mesmo grau de subordinação dentro do mesmo ranking. Ou seja, por exemplo no caso do ranking 4 não teremos 4.01, 4.02, 4.03 dado que é tudo ranking 4. | Q22: Campo não LT (apenas tabela Output) | R22: Concluído | S22: NÃO | T22: =IF(SEARCH(B22,N22,4),"ok","nok") -> ok
A23: Bail-in cascade | B23: 162 | C23: String | D23: Fixed values | E23: (Alpha)numeric sequence to indicate the order of write-down and conversion pursuant to Article 48 BRRD. If the priority order of this cascade differs from the one stemming from the insolvency ranking reported in field c0160, please refer to the relevant Country Annex or to the specific instructions provided by the relevant NRA/IRT. When allowed under the applicable national law, institutions must reflect in this sequence the order provided by the applicable contractual subordination. Please refer to the specific reporting example (Annex II, paragraph 3.6). The bail-in cascade assigned to secured liabilities shall always be the one applicable to the (potentially) unsecured part of the liability based on the current internal valuation of the collateral by the bank. | I23: Não | J23: lt002_instrument.rank_insolv | L23: {=_xlfn.SWITCH(C23,"Numeric","999999999999999","String","Not applicable","Date","0001-01-01")} -> Not applicable | N23: out_b0200_main_liabilities.0162_bail_in_cascade | O23: lt002_instrument.rank_insolv | P23: Reunião 2025-07-30 Luís Capitão-Mor, Pedro Mendes, Luísa Sousa: No caso de Portugal o bail-in cascade é igual ao ranking de insolvência. | Q23: Campo não LT (apenas tabela Output) | R23: Concluído | S23: NÃO | T23: =IF(SEARCH(B23,N23,4),"ok","nok") -> ok
A24: Date of issuance | B24: 0170 | C24: Date | D24: yyyy-mm-dd | E24: Date of the original issuance of the liability. Format required: yyyy-mm-dd. This field is not applicable for liabilities of the type ‘Cash account/saving account’ (c0140) and deposits reported in aggregated form (Submission A). For securities issued as part of a tap issue, i.e. an issuance of additional securities under an ISIN that already exists, there should only be one row including all securities under that ISIN. The date of issuance should be the issuance date of the first issue under that ISIN. | I24: Não | J24: lt002_instrument.dt_incptn | L24: {=_xlfn.SWITCH(C24,"Numeric","999999999999999","String","Not applicable","Date","0001-01-01")} -> 0001-01-01 | N24: out_b0200_main_liabilities.0170_dt_incptn | O24: lt002_instrument.dt_incptn | P24: Reunião 2025-06-23 Luís Capitão-Mor, Pedro Mendes, Luísa Sousa | Q24: Campo já existente no LT | R24: Concluído | S24: NÃO | T24: =IF(SEARCH(B24,N24,4),"ok","nok") -> ok
A25: Date of the next interest payment | B25: 0180 | C25: Date | D25: yyyy-mm-dd | E25: The payment date from which the income distribution is made available for payment by the reporting entity. Format required: yyyy-mm-dd. If not applicable (e.g. shares), the bank should report ‘0001-01-01’. This field is not applicable for deposits reported in aggregated form (Submission A). | F25: Input "0001-01-01" | G25: Leave blank | I25: Sim | J25: lt002_instrument.dt_nxt_intrst_pymnt | L25: {=_xlfn.SWITCH(C25,"Numeric","999999999999999","String","Not applicable","Date","0001-01-01")} -> 0001-01-01 | M25: ‣ Para o universo aplicável, obter campos "dt_prox_liq_juros_act" e "dt_prox_liq_juros_pas" da cd_alm.al029_cnt_core_m. Para cada contrato, mapear com o campo que estiver preenchido. Ou seja, se num determinado contrato estiver preenchido o "dt_prox_liq_juros_act" então mapear este campo, se estiver preenchido o "dt_prox_liq_juros_pas" então mapear este campo (se nenhum dos 2 campos estiver preenchido então é um "MISS") ‣ Para o universo não aplicável (dt_nxt_intrst_pymnt ='1111-11-11' -> valor de Not Applicable para data), necessário criar nova parametrização na tabela lt831_param_conceitos, podendo a mesma ser consultada neste documento na sheet 'LT831' filtrando por tabela_conceito = 'LT002_INSTRUMENT' e campo_conceito = 'DT_NXT_INTRST_PYMNT'. Nota: Deverá seguir-se a mesma lógica de obtenção de campos de ALM que atualmente existe no Loan Tape | N25: out_b0200_main_liabilities.0180_dt_nxt_intrst_pymnt | O25: lt002_instrument.dt_nxt_intrst_pymnt | P25: Reunião 2025-08-08 Luís Capitão-Mor, Pedro Mendes, Luísa Sousa: Segundo Luís Capitão-Mor, o universo Not Applicable deste campo é o mesmo do campo PYMNT_FRQNCY. O PYMNT_FRQNCY tem definidos os typ_instrumnt not applicable na lt803_codigos_lt (procurar na lt803_codigos_lt por campo_lt= 'PYMNT_FRQNCY_NA'). Dado que este campo é um campo novo então deverá efetuar-se essa parametrização mas na lt831_param_conceitos (e não na lt803_codigos_lt). Reunião 2025-08-06 Luís Capitão-Mor, Pedro Mendes, Luísa Sousa Reunião 2025-06-23 Luís Capitão-Mor, Pedro Mendes, Luísa Sousa | Q25: Campo novo no LT | R25: Concluído | S25: NÃO | T25: =IF(SEARCH(B25,N25,4),"ok","nok") -> ok
A26: Date of the next (partial) redemption payment | B26: 0190 | C26: Date | D26: yyyy-mm-dd | E26: The payment date or the date on which the (partial) redemption payment is due for payment (e.g. cases in which a portion of the liabilities is reimbursed before the final legal maturity). If not applicable, please report the final legal maturity (c0210). This field is not applicable for liabilities of the type ‘Cash account/saving account’ (c0140) and for deposits reported in aggregated form (Submission A). | F26: Input the final legal maturity of the liability (c0210) | I26: Não | N26: out_b0200_main_liabilities.0190_dt_nxt_rdmptn_pymnt | O26: lt002_instrument.dt_lgl_fnl_mtrty | P26: Reunião 2025-09-16 Luís Capitão-Mor, Pedro Mendes: O conceito de date of the next redemption payment é aplicável aos Títulos, no limite, pode ser a data de maturidade. Identificaram-se 2 Soluções possíveis: Solução 1: Criar um campo novo no Loan Tape (caso não exista): ‣ Para o universo aplicável, obter campos "dt_prox_amort_capital_act" e "dt_prox_amort_capital_pas" da cd_alm.al029_cnt_core_m. Para cada contrato, mapear com o campo que estiver preenchido. Ou seja, se num determinado contrato estiver preenchido o "dt_prox_amort_capital_act" então mapear este campo, se estiver preenchido o "dt_prox_amort_capital_pas" então mapear este campo (se nenhum dos 2 campos estiver preenchido então é um "MISS") ‣ Para o universo não aplicável, necessário criar nova parametrização na tabela lt831_param_conceitos Solução 2: Não criar o campo no Loan Tape, e na tabela de output final (out_b0200_main_liabilities) apontar este campo para o campo lt002_instrument.dt_lgl_fnl_mtrty, dado que nos registos deste Universo de Títulos este campo corresponde sempre à data de maturidade e não se prevê que esta situação se altere no futuro. Dado que a Solução 1 é mais dispendiosa (apesar de ser mais resiliente), nesta fase optou-se pela Solução 2. Adicionalmente, confirmou-se que não existe valor nos campos "dt_prox_amort_capital_act" e "dt_prox_amort_capital_pas" na cd_alm.al029_cnt_core_m para os registos deste Universo de Títulos. Query: select distinct concat(cempresa,cbalcao,cnumecta,zdeposit) as contrato, trim(dt_prox_amort_capital_act) , trim(dt_prox_amort_capital_pas) from cd_alm.al029_cnt_core_m where ref_date = '2025-06-30' and concat(cempresa,cbalcao,cnumecta,zdeposit) in ( '31641600000000000PTSTOGOM0003000', '31641600005800007PTBSRDOM0037000', '31641600005800007PTSTOCOM0007000', '31641600005800007PTCPP0AM0007000', '31641600000000000PTSTOEOM0021000', '31641600000000000PTSTOHOM0002000', '31641600000000000PTBSREOM0028000', '31641600000000000PTSTOFOM0004000') order by 1; | Q26: Campo não LT (apenas tabela Output) | R26: Concluído | S26: NÃO | T26: =IF(SEARCH(B26,N26,4),"ok","nok") -> ok
A27: Earliest redemption date | B27: 0200 | C27: Date | D27: yyyy-mm-dd | E27: If an option exists for holders of the instrument to request early reimbursement, or conditions for early reimbursement are contractually provided, the earliest occurrence date should be reported. Format required: yyyy-mm-dd. If that date corresponds to the legal maturity (c0210), please report the latter. If not applicable, the bank should report ‘0001-01-01’. This field is not applicable for liabilities of the type ‘Cash account/saving account’ (c0140) and for deposits reported in aggregated form (Submission A). | F27: Input "0001-01-01" | I27: Não | N27: out_b0200_main_liabilities.0200_dt_erlst_rdmptn | O27: Valor fixo ‘0001-01-01’. | P27: Reunião 2025-09-10 Luís Capitão-Mor, Pedro Mendes, Luísa Sousa: Segundo Pedro Mendes, este campo é na visão do Investidor. Ou seja, para o âmbito em questão é não aplicável, só o Banco tem a opção de terminar a emissão mais cedo em datas pré-definidas. Portanto, decidiu-se que este campo será reportado com o valor fixo ‘0001-01-01’ (Not applicable). | Q27: Campo não LT (apenas tabela Output) | R27: Concluído | S27: NÃO | T27: Campo a visitar na próxima reunião
A28: Legal maturity | B28: 0210 | C28: Date | D28: yyyy-mm-dd | E28: Date of the legal, final maturity of the instrument or liability (including term deposits). Format required: yyyy-mm-dd. For perpetual instruments, the bank should report ‘2099-01-31’. If not applicable, the bank should report ‘0001-01-01’. This field is not applicable for liabilities of the type ‘Cash account/saving account’ (c0140) and for deposits reported in aggregated form (Submission A). | F28: Input "0001-01-01" | I28: Não | J28: lt002_instrument.dt_lgl_fnl_mtrty | L28: {=_xlfn.SWITCH(C28,"Numeric","999999999999999","String","Not applicable","Date","0001-01-01")} -> 0001-01-01 | M28: ‣ Necessário criar novas parametrizaçôes nas tabelas lt829_regras_conversao e lt830_conversoes, podendo as mesmas ser consultadas neste documento nas sheets: LT829 - filtrando por campo_conceito = 'DT_LGL_FNL_MTRTY' e regra_conversao = '1'; LT830 - filtrando por segmento = 'ESTR' e campo_conceito = 'DT_LGL_FNL_MTRTY'. | N28: out_b0200_main_liabilities.0210_dt_lgl_fnl_mtrty | O28: lt002_instrument.dt_lgl_fnl_mtrty | P28: Reunião 2025-08-06 Luís Capitão-Mor, Pedro Mendes, Luísa Sousa Reunião 2025-06-23 Luís Capitão-Mor, Pedro Mendes, Luísa Sousa Nota: Mariana Romão comentou que não é necessário colocar na parametrização da lt829 a linha de quando é not in ('9999-12-31', '1111-11-11') a mapear para o dt_lgl_fnl_mtrty, dado que o código já está a fazer isso, ou seja, o código aplica as parametrizações que estão na lt029 e o que não estiver traz o que vem no campo (neste caso o dt_lgl_fnl_mtrty). | Q28: Campo já existente no LT | R28: Concluído | S28: NÃO | T28: =IF(SEARCH(B28,N28,4),"ok","nok") -> ok
A29: Governing law | B29: 0220 | C29: String | D29: ISO 3166-1 alpha 2 / ISO 3166-2 | E29: The ISO 3166-1 alpha-2 code of the country whose law governs the instrument (please use the ISO 3166-2 code when the law of an administrative subdivision is relevant, e.g. ‘US-NY’). If the contract is governed by the law of more than one country, the country whose law has the highest relevance for the recognition of write-down and conversion powers must be reported. For deposits reported on an aggregate level, please indicate ‘XX’. | F29: Input "XX" | I29: Não | J29: lt002_instrument.governing_law | L29: XX | N29: out_b0200_main_liabilities.0220_governing_law | O29: lt002_instrument.governing_law | P29: Reunião 2025-06-23 Luís Capitão-Mor, Pedro Mendes, Luísa Sousa | Q29: Campo já existente no LT | R29: Concluído | S29: NÃO | T29: =IF(SEARCH(B29,N29,4),"ok","nok") -> ok
A30: Bail-in recognition clause | B30: 0230 | C30: String | D30: Drop-down | E30: Indicate one of the following: • Yes, supported by Legal Opinion = the liability includes a bail-in recognition clause in line with Article 55 BRRD that is supported by a legal opinion; • Yes, not supported by Legal Opinion = the liability includes a bail-in recognition clause in line with Article 55 BRRD that is currently not supported by a legal opinion; • No = the liability does not include a bail-in recognition clause; • Not applicable = the bail-in clause is not applicable (e.g. the governing law is not that of a third country, or a recognition clause is not requested as the third-country jurisdiction recognises the powers of the resolution authority). • Aggregated = deposits reported on an aggregated level. | F30: Input "Not applicable" | I30: Não | N30: out_b0200_main_liabilities.0230_bail_in_rcgntn_cls | O30: Valor fixo 'Yes, supported by Legal Opinion' | P30: Reunião 2025-07-30 Luís Capitão-Mor, Pedro Mendes, Luísa Sousa | Q30: Campo não LT (apenas tabela Output) | R30: Concluído | S30: NÃO | T30: =IF(SEARCH(B30,N30,4),"ok","nok") -> ok
A31: Zero-Coupon | B31: 0240 | C31: String | D31: Drop-down | E31: Indicate whether the instrument/liability is: • ZCB issued at discount = liabilities issued at discount where the principal / face value of 100% will be repaid at maturity; • ZCB not issued at discount = liabilities issued at a face value of 100%, where there is one payment at maturity that consists of the face value and the accrued interest; • No ZCB = the liability is not a zero coupon bond; • Aggregated = deposits reported on an aggregated level. | I31: Não | N31: out_b0200_main_liabilities.0240_zero_coupon | O31: Valor fixo 'No ZCB' | P31: Reunião 2025-07-30 Luís Capitão-Mor, Pedro Mendes, Luísa Sousa | Q31: Campo não LT (apenas tabela Output) | R31: Concluído | S31: NÃO | T31: =IF(SEARCH(B31,N31,4),"ok","nok") -> ok
A32: Structured product | B32: 0250 | C32: String | D32: Drop-down | E32: Indicate whether the instrument/liability is to be considered structured or contains specific non-standard terms, using one of the following values: • Non-structured/Vanilla; • Structured; • Other non-standard terms = “Non-standardised terms” refers to terms and conditions that may influence, among others, the nature and maturity of the contract. Examples of such non-standardised terms are material-adverse-change clauses, termination options with rising interest rates etc; • Only structured coupon = “Only structured coupon” refers to structured product where the derivative component only affects the coupon payment, namely is fully capital guaranteed with no possibility to reimburse at maturity an amount (excluding the coupon) that differs from the nominal amount. In addition, it is applicable only in case the accrued interest can be computed; • Aggregated = deposits reported on an aggregated level. A structured instrument is defined as a debt obligation with an embedded derivative component and whose returns are determined by an underlying, e.g. an underlying security or index (public or special index, e.g. based on shares or bonds, fixed-income investments or loan, foreign exchange, commodities, etc.). Structured debt instruments do not cover debt instruments with an underlying only call or put options, i.e. the value of the instrument is not determined by an embedded derivative. | I32: Não | N32: out_b0200_main_liabilities.0250_strctrd_prdct | O32: Valor fixo 'Non-structured/Vanilla' | P32: Reunião 2025-09-23 Pedro Mendes: Segundo Pedro Mendes, este campo deverá assumir valor fixo 'Non-structured/Vanilla'. Reunião 2025-06-23 Luís Capitão-Mor, Pedro Mendes, Luísa Sousa: Segundo o anexo III, este campo deve, em princípio, ser considerado não aplicável para non-resolution entities. Pedro Mendes enviou email dia 24-06 confirmando que este campo é não aplicável. "Sim, confirmo que todos os campos são não aplicáveis." | Q32: Campo não LT (apenas tabela Output) | R32: Concluído | S32: NÃO | T32: =IF(SEARCH(B32,N32,4),"ok","nok") -> ok
A33: Guaranteed minimum repayment amount of the structured product | B33: 0260 | C33: Numeric | D33: 2 decimals | E33: Guaranteed minimum principal amount, which is not dependent on contingent liabilities. Relevant only for structured liabilities. Only claims against other parties are to be reported (i.e. excluding the portion held by the entity itself, which must be reported in field c0090). | I33: Não | N33: out_b0200_main_liabilities.0260_grntd_min_amnt_strctrd_prdct | O33: Valor fixo 999999999999999 | P33: Reunião 2025-06-23 Luís Capitão-Mor, Pedro Mendes, Luísa Sousa: Segundo o anexo III, este campo deve, em princípio, ser considerado não aplicável para non-resolution entities. Pedro Mendes enviou email dia 24-06 confirmando que este campo é não aplicável. "Sim, confirmo que todos os campos são não aplicáveis." | Q33: Campo não LT (apenas tabela Output) | R33: Concluído | S33: NÃO | T33: =IF(SEARCH(B33,N33,4),"ok","nok") -> ok
A34: Fair value of the structured product | B34: 0270 | C34: Numeric | D34: 2 decimals | E34: Total EUR amount of the fair value of the structured product to estimate the outstanding amount due in resolution (including fees, if applicable). Relevant only for structured liabilities. The impact of the relevant entity’s own credit-risk component shall not be included when determining the value. Only claims against other parties are to be reported (i.e. excluding the portion held by the entity itself, which must be reported in field c0090). | I34: Não | N34: out_b0200_main_liabilities.0270_fv_amnt_strctrd_prdct | O34: Valor fixo 999999999999999 | P34: Reunião 2025-06-23 Luís Capitão-Mor, Pedro Mendes, Luísa Sousa: Segundo o anexo III, este campo deve, em princípio, ser considerado não aplicável para non-resolution entities. Pedro Mendes enviou email dia 24-06 confirmando que este campo é não aplicável. "Sim, confirmo que todos os campos são não aplicáveis." | Q34: Campo não LT (apenas tabela Output) | R34: Concluído | S34: NÃO | T34: =IF(SEARCH(B34,N34,4),"ok","nok") -> ok
A35: Not covered and not preferential deposit | B35: 0280 | C35: String | D35: TRUE / FALSE boolean | E35: Identification if the deposit does not qualify for exclusion from bail-in or preferential treatment in accordance with Article 27(3)(a) SRMR or Article 108 BRRD. The value to be reported is a TRUE/FALSE Boolean, where ‘TRUE’ identifies an NCNP deposit and ‘FALSE’ identifies otherwise. This field should be reported only for deposits (48). (48) - Deposits are deposits according to Directive 2014/49/EU and its national transpositions. | I35: Não | N35: out_b0200_main_liabilities.0280_flg_ncnp_dpsts | O35: Valor fixo 'FALSE' | P35: Reunião 2025-09-23 Pedro Mendes: Segundo Pedro Mendes, este campo deverá assumir valor fixo 'FALSE'. Reunião 2025-06-23 Luís Capitão-Mor, Pedro Mendes, Luísa Sousa: Tomou-se a decisão de não colocar estes campos not applicable no Loan Tape uma vez que eles não teriam lógica associada. Se a futuro for necessário desenvolver estes campos, então aí sim deverão ser colocados e desenvolvidos no Loan Tape. | Q35: Campo não LT (apenas tabela Output) | R35: Concluído | S35: NÃO | T35: =IF(SEARCH(B35,N35,4),"ok","nok") -> ok
A36: Not covered but preferential deposit | B36: 0290 | C36: String | D36: TRUE / FALSE boolean | E36: Identification if the deposit does not qualify for exclusion from bail-in (Article 27(3)(a) SRMR), yet to which preferential treatment is provided by Article 108 BRRD. The value to be reported is a TRUE/FALSE Boolean, where ‘TRUE’ identifies an NCBP deposit and ‘FALSE’ identifies otherwise. This field should be reported only for deposits (49). (49) - Deposits are those defined as such by Directive 2014/49/EU and its national transpositions | I36: Não | N36: out_b0200_main_liabilities.0290_flg_ncbp_dpsts | O36: Valor fixo 'FALSE' | P36: Reunião 2025-09-23 Pedro Mendes: Segundo Pedro Mendes, este campo deverá assumir valor fixo 'FALSE'. Reunião 2025-06-23 Luís Capitão-Mor, Pedro Mendes, Luísa Sousa: Tomou-se a decisão de não colocar estes campos not applicable no Loan Tape uma vez que eles não teriam lógica associada. Se a futuro for necessário desenvolver estes campos, então aí sim deverão ser colocados e desenvolvidos no Loan Tape. | Q36: Campo não LT (apenas tabela Output) | R36: Concluído | S36: NÃO | T36: =IF(SEARCH(B36,N36,4),"ok","nok") -> ok
A37: Covered portion of eligible deposits | B37: 0300 | C37: Numeric | D37: 2 decimals | E37: Total EUR amount of the covered portion of eligible deposits as per Article 27(3)a SRMR. As the amount of covered deposits is calculated per depositor (50), in the case of depositors with multiple accounts, this amount shall in principle be calculated pro rata for the different accounts reported at a granular level (on an account by account basis), unless specific provisions resulting from the transposition of Directive 2014/49/EU into national law are applicable (51). This field should be reported only for deposits (52). Fully covered deposits must not be reported. (50) - Article 6 of Directive 2014/49/EU. (51) - Please refer to the specific reporting example in Annex II, paragraph 3.9. (52) - Deposits are those defined as such by Directive 2014/49/EU and its national transpositions. | I37: Não | N37: out_b0200_main_liabilities.0300_amnt_cvrd_elgbl_dpsts | O37: Valor fixo 999999999999999 | P37: Reunião 2025-06-23 Luís Capitão-Mor, Pedro Mendes, Luísa Sousa: Tomou-se a decisão de não colocar estes campos not applicable no Loan Tape uma vez que eles não teriam lógica associada. Se a futuro for necessário desenvolver estes campos, então aí sim deverão ser colocados e desenvolvidos no Loan Tape. | Q37: Campo não LT (apenas tabela Output) | R37: Concluído | S37: NÃO | T37: =IF(SEARCH(B37,N37,4),"ok","nok") -> ok
A38: Secured/Unsecured | B38: 0310 | C38: String | D38: Drop-down | E38: Indicate whether the instrument is subject to collateral agreements or not, from a predefined list: • Secured; • Unsecured. When reporting secured liabilities, please refer to the related reporting example in the Technical Annex. | I38: Não | N38: out_b0200_main_liabilities.0310_flg_clltrl_agrmnts | O38: Valor fixo 'Unsecured' | P38: Reunião 2025-09-23 Pedro Mendes: Segundo Pedro Mendes, este campo deverá assumir valor fixo 'Unsecured'. Reunião 2025-06-23 Luís Capitão-Mor, Pedro Mendes, Luísa Sousa: Segundo o anexo III, este campo deve, em princípio, ser considerado não aplicável para non-resolution entities. Pedro Mendes enviou email dia 24-06 confirmando que este campo é não aplicável. "Sim, confirmo que todos os campos são não aplicáveis." | Q38: Campo não LT (apenas tabela Output) | R38: Concluído | S38: NÃO | T38: =IF(SEARCH(B38,N38,4),"ok","nok") -> ok
A39: Amount of pledge, lien or collateral | B39: 0320 | C39: Numeric | D39: 2 decimals | E39: Total EUR amount (market value) of the pledge, lien or collateral if the liability is secured, based on the current internal valuation. For unsecured liabilities, this field is not applicable. If the entity retains a portion of the secured liability (i.e. own holdings), the collateral value should only refer to the portion of the liability against other parties and not held by the reporting entity.(53) This amount determines the secured portion of each secured liability(54). For collateral pools securing multiple row items, the overall coverage ratio should be determined and applied pro rata to all row items covered by this pool. For subordinated collaterals, the outstanding amount of the senior secured liability must be deducted. (53)=(54)=Please refer to the dedicated reporting example in Annex II, paragraph 3.5. | I39: Não | N39: out_b0200_main_liabilities.0320_amnt_clltrl | O39: Valor fixo 999999999999999 | P39: Reunião 2025-06-23 Luís Capitão-Mor, Pedro Mendes, Luísa Sousa: Segundo o anexo III, este campo deve, em princípio, ser considerado não aplicável para non-resolution entities. Pedro Mendes enviou email dia 24-06 confirmando que este campo é não aplicável. "Sim, confirmo que todos os campos são não aplicáveis." | Q39: Campo não LT (apenas tabela Output) | R39: Concluído | S39: NÃO | T39: =IF(SEARCH(B39,N39,4),"ok","nok") -> ok
A40: Amount of the uncollateralized part | B40: 0330 | C40: Numeric | D40: 2 decimals | E40: The positive difference between the outstanding amount (or fair value, when applicable) of the secured liability (or the liability for which collateral has been pledged) as reported in field c0120 (or c0270, when applicable) and the market value of the pledge, lien or collateral (c0320). For collateral pools securing multiple row items, the overall coverage ratio should be determined and applied pro rata to all row items covered by this pool. | G40: Leave blank | I40: Não | N40: out_b0200_main_liabilities.0330_amnt_unclltrlzd | O40: Valor fixo 999999999999999 | P40: Reunião 2025-06-23 Luís Capitão-Mor, Pedro Mendes, Luísa Sousa: Segundo o anexo III, este campo deve, em princípio, ser considerado não aplicável para non-resolution entities. Pedro Mendes enviou email dia 24-06 confirmando que este campo é não aplicável. "Sim, confirmo que todos os campos são não aplicáveis." | Q40: Campo não LT (apenas tabela Output) | R40: Concluído | S40: NÃO | T40: =IF(SEARCH(B40,N40,4),"ok","nok") -> ok
A41: Internal identification number of the pledge, lien or collateral/collateral pool | B41: 0340 | C41: String | D41: Free text | E41: Indicate the internal identifier of the pledge, lien or collateral / collateral pool (where applicable). In the event of several relevant IDs, all IDs should be reported and separated by a vertical bar. | I41: Não | N41: out_b0200_main_liabilities.0340_id_clltrl | O41: Valor fixo 'Not applicable' | P41: Reunião 2025-06-23 Luís Capitão-Mor, Pedro Mendes, Luísa Sousa: Segundo o anexo III, este campo deve, em princípio, ser considerado não aplicável para non-resolution entities. Pedro Mendes enviou email dia 24-06 confirmando que este campo é não aplicável. "Sim, confirmo que todos os campos são não aplicáveis." | Q41: Campo não LT (apenas tabela Output) | R41: Concluído | S41: NÃO | T41: =IF(SEARCH(B41,N41,4),"ok","nok") -> ok
A42: Type of the collateral | B42: 0350 | C42: String | D42: Drop-down | E42: Identify the type of collateral used for the collateralisation: • Real estate; • Ships; • Aircraft; • Financial; • Other; • Not applicable | F42: Input "Not applicable" | G42: Leave blank | I42: Não | N42: out_b0200_main_liabilities.0350_typ_clltrl | O42: Valor fixo 'Not applicable' | P42: Reunião 2025-06-23 Luís Capitão-Mor, Pedro Mendes, Luísa Sousa: Segundo o anexo III, este campo deve, em princípio, ser considerado não aplicável para non-resolution entities. Pedro Mendes enviou email dia 24-06 confirmando que este campo é não aplicável. "Sim, confirmo que todos os campos são não aplicáveis." | Q42: Campo não LT (apenas tabela Output) | R42: Concluído | S42: NÃO | T42: =IF(SEARCH(B42,N42,4),"ok","nok") -> ok
A43: Type of the collateral (if other) | B43: 0351 | C43: String | D43: Free text | E43: Specify the type of collateral if ‘Other’ is selected in field c0350. | I43: Não | N43: out_b0200_main_liabilities.0351_typ_clltrl_othr | O43: Valor fixo 'Not applicable' | P43: Reunião 2025-06-23 Luís Capitão-Mor, Pedro Mendes, Luísa Sousa: Segundo o anexo III, este campo deve, em princípio, ser considerado não aplicável para non-resolution entities. Pedro Mendes enviou email dia 24-06 confirmando que este campo é não aplicável. "Sim, confirmo que todos os campos são não aplicáveis." | Q43: Campo não LT (apenas tabela Output) | R43: Concluído | S43: NÃO | T43: =IF(SEARCH(B43,N43,4),"ok","nok") -> ok
A44: Trading method | B44: 0360 | C44: String | D44: Drop-down | E44: Indicate whether the security is traded (55), either in nominal form or in units (56), as specified in the corresponding final issuance documentation, by selecting one of the following: • Nominal; • Unit; • Not applicable. Please refer to the reporting example in Annex II, paragraph 3.8. (55) - In this context, ‘traded’ means all securities for which there is a CSD of issuance, as indicated in data point c0460 (Central securities depository). (56) - As a general indication, please refer to the definitions provided in the International Securities Operational Market Practice Book published by Euroclear Bank and Clearstream Banking, in particular Annex 9 (‘Units and Nominal recommendation’). Data points c0360 to c0521 might be relevant only in cases of externally issued liabilities or for intragroup liabilities issued in CSDs/iCSDs. | I44: Sim | J44: lt002_instrument.trdng_mthd | L44: {=_xlfn.SWITCH(C44,"Numeric","999999999999999","String","Not applicable","Date","0001-01-01")} -> Not applicable | M44: Necessário criar nova parametrização na tabela lt831_param_conceitos podendo a mesma ser consultada neste documento na sheet 'LT831' filtrando por tabela_conceito = 'LT002_INSTRUMENT' e campo_conceito = 'TRDNG_MTHD'. A parametrização irá basear-se nos campos 'TIPO_TITULO' (proveniente da ct610_titulos), 'FLAG_INST_TITULOS' (proveniente da lt001_univ_oper) e 'PRDCT' (proveniente da lt002_instrument). | N44: out_b0200_main_liabilities.0360_trdng_mthd | O44: lt002_instrument.trdng_mthd | P44: Reunião 2025-10-30/2025-10-28 Luís Capitão-Mor, Pedro Mendes, Luísa Sousa Reunião 2025-10-22 Luís Capitão-Mor, Pedro Mendes, Carlos Daniel: Tipicamente o que é renda fixa (ex: Obrigações) é em Valor Nominal e o que é renda variável (ex: Ações) é em Unidades/Quantidade. Nota: O Papel Comercial (produto 113) também deverá ser considerado 'Nominal' | Q44: Campo novo no LT | R44: Não Concluído | S44: NÃO | T44: =IF(SEARCH(B44,N44,4),"ok","nok") -> ok
A45: Denomination / Nominal value per security in EUR | B45: 370 | C45: Numeric | D45: 2 decimals | E45: The smallest amount of the security that can be transferred, in EUR currency (if the original currency is not EUR, please also report the EUR-converted amount in this field). If a denomination exists, it represents the higher integral multiple amount. For unit-traded securities (when indicated in data point c0360), this field should be reported only if a nominal value exists. Please refer to the reporting example in Annex II, paragraph 3.8. Data points c0360 to c0521 might be relevant only in cases of externally issued liabilities or for intragroup liabilities issued in CSDs/iCSDs. | I45: Sim | J45: lt002_instrument.amnt_scrty_eur | L45: {=_xlfn.SWITCH(C45,"Numeric","999999999999999","String","Not applicable","Date","0001-01-01")} -> 999999999999999 | M45: Se flag_inst_titulos = '1': Obter campo nom_unit_atual da ct610_titulos. Adicionalmente, efetuar conversão via tabela cambios (ver query de conversão já definida no campo Original amount issued in EUR (0050)) Se flag_inst_titulos = '0': Not applicable. O respetivo valor default de Not applicable deverá ser parametrizado na lt804_conf_dflt. | N45: out_b0200_main_liabilities.0370_amnt_scrty_eur | O45: lt002_instrument.amnt_scrty_eur | P45: Reunião 2025-09-22 Luís Capitão-Mor, Pedro Mendes, Luísa Sousa: Interpreta-se que o SRB solicita o valor nominal de cada título | Q45: Campo novo no LT | R45: Concluído | S45: NÃO | T45: =IF(SEARCH(B45,N45,4),"ok","nok") -> ok
A46: Denomination / Nominal value per security in original currency | B46: 0380 | C46: Numeric | D46: 2 decimals | E46: The smallest amount of the security that can be transferred, in the original currency. If a denomination exists, it represents the higher integral multiple amount. For unit-traded securities (when indicated in data point c0360), this field should be reported only if a nominal value exists. Please refer to the reporting example in Annex II, paragraph 3.8. Data points c0360 to c0521 might be relevant only in cases of externally issued liabilities or for intragroup liabilities issued in CSDs/iCSDs. | I46: Sim | J46: lt002_instrument.amnt_scrty_fx | L46: {=_xlfn.SWITCH(C46,"Numeric","999999999999999","String","Not applicable","Date","0001-01-01")} -> 999999999999999 | M46: Se flag_inst_titulos = '1': Obter campo nom_unit_atual da ct610_titulos. Se flag_inst_titulos = '0': Not applicable. O respetivo valor default de Not applicable deverá ser parametrizado na lt804_conf_dflt. | N46: out_b0200_main_liabilities.0380_amnt_scrty_fx | O46: lt002_instrument.amnt_scrty_fx | P46: Reunião 2025-09-22 Luís Capitão-Mor, Pedro Mendes, Luísa Sousa: Campo igual ao "Denomination / Nominal value per security in EUR" (0370) mas sem efetuar a conversão para Eur (dado que o SRB solicita o montante na moeda original) | Q46: Campo novo no LT | R46: Concluído | S46: NÃO | T46: =IF(SEARCH(B46,N46,4),"ok","nok") -> ok
A47: Number of securities outstanding not held by the reporting entity | B47: 390 | C47: Numeric | D47: Integer | E47: Number of outstanding securities issued per ISIN (or other code), not held by the reporting entity itself. Data points c0360 to c0521 might be relevant only in cases of externally issued liabilities or for intragroup liabilities issued in CSDs/iCSDs. | I47: Não | N47: out_b0200_main_liabilities.0390_nmbr_scrts_not_rprtng_entty | O47: Number of securities outstanding not held by the reporting entity= 0080 / 0370 0080 -> Outstanding principal amount 0370 -> Denomination / Nominal value per security in EUR | P47: Reunião 2025-10-30 Luís Capitão-Mor, Pedro Mendes, Luísa Sousa: Dividir Outstanding principal amount (0080) pelo Denomination / Nominal value per security in EUR (0370) Reunião 2025-08-04 Luís Capitão-Mor, Pedro Mendes, Luísa Sousa: Segundo Pedro Mendes, aqui pede-se a quantidade. Segundo Luís Capitão-Mor, verificar se nos campos acima de montante existe algum que só tenha o nominal atual excluindo as recompras próprias, mas com tudo o resto. Exemplo: Emissão inicial de uma Titularização de 1000 Milhões de Eur Atualmente, temos 900 Milhões de Eur (devido ao pool factor de 0,9). Desses 900 Milhões de Eur: - 50 Milhões de Eur foram recomprados pelo próprio BST - 100 Milhões de Eur estão no Banco Santander SA - 750 Milhões de Eur estão no Mercado Ou seja, tem de se identificar se nos campos existentes se existe algum que tenha os 850 Milhões de Eur. O cálculo do campo "Number of securities outstanding not held by the reporting entity" deverá ser feito dividindo esse campo acima pelo valor nominal... | Q47: Campo não LT (apenas tabela Output) | R47: Não Concluído | S47: NÃO | T47: =IF(SEARCH(B47,N47,4),"ok","nok") -> ok
A48: Number of securities outstanding held by the reporting entity | B48: 0391 | C48: Numeric | D48: Integer | E48: Number of outstanding securities issued per ISIN (or other code), held by the reporting entity itself. This field must be reported consistently with data point c0090. Data points c0360 to c0521 might be relevant only in cases of externally issued liabilities or for intragroup liabilities issued in CSDs/iCSDs. | I48: Não | N48: out_b0200_main_liabilities.0391_nmbr_scrts_rprtng_entty | O48: Number of securities outstanding held by the reporting entity= 0090 / 0370 0090 -> Portion of instrument or liability held by the reporting entity 0370 -> Denomination / Nominal value per security in EUR | P48: Reunião 2025-10-30 Luís Capitão-Mor, Pedro Mendes, Luísa Sousa: Dividir Portion of instrument or liability held by the reporting entity (0090) pelo Denomination / Nominal value per security in EUR (0370) | Q48: Campo não LT (apenas tabela Output) | R48: Não Concluído | S48: NÃO | T48: =IF(SEARCH(B48,N48,4),"ok","nok") -> ok
A49: Accrued interest per security | B49: 0400 | C49: Numeric | D49: 4 decimals | E49: Total EUR amount of the accrued interest per security issued per ISIN (or other code). In jurisdictions where accrued interests do not rank pari passu to the principal liability amount, the relevant NRAs may request reporting of interest accruals as on separate line items. Data points c0360 to c0521 might be relevant only in cases of externally issued liabilities or for intragroup liabilities issued in CSDs/iCSDs. | I49: Não | N49: out_b0200_main_liabilities.0400_accrd_intrst_scrty | O49: Accrued interest per security= 0100 / 0390 0100 -> Accrued interest 0390 -> Number of securities outstanding not held by the reporting entity | P49: Reunião 2025-10-30 Luís Capitão-Mor, Pedro Mendes, Luísa Sousa: A contabilidade não tem juros corridos sobre o que está recomprado. Por exemplo, no caso de uma Emissão de 1000 Milhões eur, em que 100 Milhões eur estão recomprados pelo BST e 900 Milhões eur estão no Mercado, os juros corridos que estão registados na Contabilidade são apenas sobre os 900 Milhões eur, os 100 Milhões eur não têm juros corridos. No limite, se dos 1000 Milhões eur emitidos estivessem 1000 Milhões eur recomprados, não haveria juros corridos. Carlos Fernandes confirmou este entendimento (email Carlos Fernandes 05/11/2025 11:28) Portanto, a fórmula deste campo deverá ser o Accrued interest a dividir pela quantidade excluindo as recompras, ou seja, neste exemplo a quantidade deverá ser sobre os 900 Milhões eur e não sobre os 1000 Milhões eur. Em suma, a fórmula deverá ser: Accrued interest (0100) / Number of securities outstanding not held by the reporting entity (0390) old: Reunião 2025-09-22 Luís Capitão-Mor, Pedro Mendes, Luísa Sousa: 1) Ver se na bloomberg (ou algum site que a Financeira usa) constam estes títulos e ver o accrued interest que lá está. Ou com a Cláudia no Asset Control. -> Segundo Pedro Mendes, na Financeira o que existe atualmente é apenas o excel da Contabilidade com as Emissões. -> Segundo Cláudia Correia, "não existe. O Asset Control só tem preços puros de mercado" | Q49: Campo não LT (apenas tabela Output) | R49: Não Concluído | S49: SIM | T49: =IF(SEARCH(B49,N49,4),"ok","nok") -> ok
A50: Fees and charges per security | B50: 0410 | C50: Numeric | D50: 4 decimals | E50: Total EUR amount of the fees and charges per security issued per ISIN (or other code). Applicable fees and charges (e.g. contractual fees for late payments) linked to the instrument, if the fee or charge is payable and due but not yet settled with the counterparty as of the request date, to the extent that the fee or charge is not covered within the outstanding principal amount, the accrued interest or a separate liability. Fees and charges do not include agios or fees in conjunction with the listing of a security. Data points c0360 to c0521 might be relevant only in cases of externally issued liabilities or for intragroup liabilities issued in CSDs/iCSDs. | I50: Não | N50: out_b0200_main_liabilities.0410_fees_charges_scrty | O50: Valor fixo 0 | P50: Reunião 2025-09-24 Luís Capitão-Mor, Pedro Mendes: Tendo em conta que no campo "Applicable fees and charges" (0110) se vai reportar valor fixo 0, e que este campo trata do mesmo conceito (apresenta a mesma definição) mas por título (per security), então também se deve reportar valor fixo 0. | Q50: Campo não LT (apenas tabela Output) | R50: Concluído | S50: NÃO | T50: =IF(SEARCH(B50,N50,4),"ok","nok") -> ok
A51: Fair value per security | B51: 0420 | C51: Numeric | D51: 4 decimals | E51: Total EUR amount of the fair value (as reported in field c0270) per security issued per ISIN (or other code). Data points c0360 to c0521 might be relevant only in cases of externally issued liabilities or for intragroup liabilities issued in CSDs/iCSDs. | I51: Não | N51: out_b0200_main_liabilities.0420_fv_amnt_scrty | O51: Valor fixo 999999999999999 | P51: Reunião 2025-09-24 Luís Capitão-Mor, Pedro Mendes: Tendo em conta que no campo "Fair value of the structured product" (0270) se vai reportar valor fixo 999999999999999, e que este campo trata do mesmo conceito (apresenta a mesma definição) mas por título (per security), então também se deve reportar valor fixo 999999999999999. | Q51: Campo não LT (apenas tabela Output) | R51: Concluído | S51: NÃO | T51: =IF(SEARCH(B51,N51,4),"ok","nok") -> ok
A52: Principal amount of the global note in EUR | B52: 0430 | C52: Numeric | D52: 2 decimals | E52: The outstanding aggregate principal amount of the global note per ISIN or other code, in EUR (including own holdings when applicable). If the value is reported in a foreign currency in field c0431, the amount must be converted into EUR and reported in this field using the EUR reference exchange rate. For foreign currencies for which no EUR reference exchange rate is available, a customary market reference rate must be used. If such other customary reference exchange rates are used, a uniform source must be used wherever possible. This field is not applicable if the trading method selected in field c0360 is ‘Unit’. Data points c0360 to c0521 might be relevant only in cases of externally issued liabilities or for intragroup liabilities issued in CSDs/iCSDs. | F52: Input 999999999999999 | I52: Não | N52: out_b0200_main_liabilities.0430_prncpl_amnt_glbl_nt_eur | O52: Valor fixo 999999999999999 | P52: Reunião 2025-08-13 Luís Capitão-Mor, Pedro Mendes, Luísa Sousa | Q52: Campo não LT (apenas tabela Output) | R52: Concluído | S52: NÃO | T52: =IF(SEARCH(B52,N52,4),"ok","nok") -> ok
A53: Principal amount of the global note in original currency | B53: 0431 | C53: Numeric | D53: 2 decimals | E53: The outstanding aggregate principal amount of the global note per ISIN or other code in the original currency (including own holdings when applicable). Please also report the EUR-converted amount in the corresponding EUR field (c0430). This field is not applicable if trading method selected in field c0360 is ‘Unit’. Data points c0360 to c0521 might be relevant only in cases of externally issued liabilities or for intragroup liabilities issued in CSDs/iCSDs. | F53: Input 999999999999999 | I53: Não | N53: out_b0200_main_liabilities.0431_prncpl_amnt_glbl_nt_fx | O53: Valor fixo 999999999999999 | P53: Reunião 2025-08-13 Luís Capitão-Mor, Pedro Mendes, Luísa Sousa | Q53: Campo não LT (apenas tabela Output) | R53: Concluído | S53: NÃO | T53: =IF(SEARCH(B53,N53,4),"ok","nok") -> ok
A54: Nature of the global note | B54: 0440 | C54: String | D54: Drop-down | E54: Indicate whether the liability is a Classical Global Note (CGN) or a New Global Note (NGN): • CGN = a form of global certificate that requires physical annotation on the attached schedule to reflect changes in the issue outstanding amount; • NGN = a form of global certificate that refers to the records of the ICSDs to determine the issue outstanding amount. • Not applicable = if it is not applicable (the liability has not been issued in an ICSD, or has another nature). Data points c0360 to c0521 might be relevant only in cases of externally issued liabilities or for intragroup liabilities issued in CSDs/iCSDs. | F54: Input "Not applicable" | I54: Não | N54: out_b0200_main_liabilities.0440_ntr_glbl_nt | O54: Valor fixo 'Not applicable' | P54: Reunião 2025-07-31 Luís Capitão-Mor, Pedro Mendes: Não aplicável ao universo de títulos em causa, contudo, aplica-se a outros títulos. | Q54: Campo não LT (apenas tabela Output) | R54: Concluído | S54: NÃO | T54: =IF(SEARCH(B54,N54,4),"ok","nok") -> ok
A55: Current pool factor | B55: 0450 | C55: Numeric | D55: Values between 0 and 1, with 9 decimals | E55: If applicable, the factor used to calculate the value of the outstanding principal of the financial instrument applicable until the next redemption (factor) date, or after the redemption (factor) date. Can also be defined as: ratio of outstanding principal to original face value. Please refer to the SRB publication ‘Reflecting bail-in in the books of the International Central Securities Depositories (ICSDs) (57). (57) - https://www.srb.europa.eu/system/files/media/document/bail-in_in_books_of_icsds_enn_final_web.pdf (Annex III, letter G) Data points c0360 to c0521 might be relevant only in cases of externally issued liabilities or for intragroup liabilities issued in CSDs/iCSDs. | F55: Input -9999.999999999 | I55: Não | N55: out_b0200_main_liabilities.0450_crrnt_pool_fctr | O55: Valor Fixo -9999.999999999 | P55: Reunião 2025-07-24 Luís Capitão-Mor, Flávia Pinho, Luísa Sousa: Por definição, o conceito de Pool Factor aplica-se apenas a titularizações (instrumentos financeiros que têm fundos) e não se aplica aos restantes Produtos. Portanto, sabendo que o universo deste report não contempla Titularizações, então não será criado o campo no Loan Tape e será criado apenas na tabela de output out_b0200_main_liabilities com o valor de not applicable. | Q55: Campo não LT (apenas tabela Output) | R55: Concluído | S55: NÃO | T55: =IF(SEARCH(B55,N55,4),"ok","nok") -> ok
A56: Central securities depository | B56: 0460 | C56: String | D56: Fixed values | E56: Indicate the CSD of issue for the security. When applicable, please use the values from the predefined list provided below. In the event of multiple entries, please separate them with a vertical bar and indicate the CSD of issue as the first entry on the list. For securities deposited by international central securities depositories (ICSDs), both CSDs must be reported. • ATHEX CSD_EL • BOGS_EL • CBF_DE • CBL_LU • CDCP SR_SK • CDCP_CZ • Central Depository & Clearing Company_HR • Central Depository of Securities Prague_CZ • Central Depository_BG • Cyprus CDCR_CY • Depozitarul Central_RO • DTC_US • Euroclear Bank_BE • Euroclear Belgium_BE • Euroclear Finland_FI • Euroclear France_FR • Euroclear Netherlands_NL • Euroclear Sweden_SE • Euroclear UK & Ireland_UK • Government Securities Depository (GSD)_BG • Iberclear_ES • INTERBOLSA_PT • KDD_SI • KDPW_PL • KELER_HU • LUX CSD_LU • Malta Stock Exchange CSD_MT • Euronext Securities Milan_IT • Nasdaq CSD_EE • Nasdaq CSD_LT • Nasdaq CSD_LV • NBB SSS_BE • nCDCP_SK • OeKB CSD_AT • SAFIR_RO • SIX SIS_CH • SKARBNET4_PL • SKD_CZ • VP Securities_DK • VPS_NO • Other • Not applicable Data points c0360 to c0521 might be relevant only in cases of externally issued liabilities or for intragroup liabilities issued in CSDs/iCSDs. | I56: Sim | J56: lt002_instrument.csd | L56: {=_xlfn.SWITCH(C56,"Numeric","999999999999999","String","Not applicable","Date","0001-01-01")} -> Not applicable | M56: Se flag_inst_titulos = '1': Obter campo central_valores da ct610_titulos (que contém o código lei) e cruzá-lo com o campo clei da ct003_univ_cli, de forma a obter o campo gcliente da ct003_univ_cli. Caso o cruzamento resulte em mais do que 1 gcliente, terá de se trazer apenas 1 gcliente. Para tal, selecionar o zcliente maior (max (zcliente)) que tenha gcliente preenchido. Se flag_inst_titulos = '0': Not applicable. O respetivo valor default de Not applicable deverá ser parametrizado na lt804_conf_dflt. Necessário criar novas parametrizaçôes nas tabelas lt829_regras_conversao e lt830_conversoes, podendo as mesmas ser consultadas neste documento nas sheets: LT829 - filtrando por campo_conceito = 'CSD' e regra_conversao = '1'; LT830 - filtrando por segmento = 'ESTR' e campo_conceito = 'CSD'. | N56: out_b0200_main_liabilities.0460_csd | O56: lt002_instrument.csd | P56: Reunião 2025-07-30 Luís Capitão-Mor, Pedro Mendes, Luísa Sousa Reunião 2025-07-28 Luís Capitão-Mor, Pedro Mendes Reunião 2025-07-17 Luís Capitão-Mor, Flávia Pinho, Luísa Sousa | Q56: Campo novo no LT | R56: Concluído | S56: NÃO | T56: =IF(SEARCH(B56,N56,4),"ok","nok") -> ok
A57: Central securities depository (LEI) | B57: 0461 | C57: String | D57: Free text | E57: When applicable, please indicate the LEI (or another ID) of the CSD. In case of multiple entries, please separate them with a vertical bar and indicate the CSD of issue as the first entry on the list | I57: Sim | J57: lt002_instrument.csd_lei | L57: {=_xlfn.SWITCH(C57,"Numeric","999999999999999","String","Not applicable","Date","0001-01-01")} -> Not applicable | M57: Se flag_inst_titulos = '1': Obter campo central_valores da ct610_titulos. Se flag_inst_titulos = '0': Not applicable. O respetivo valor default de Not applicable deverá ser parametrizado na lt804_conf_dflt. | N57: out_b0200_main_liabilities.0461_csd_lei | O57: lt002_instrument.csd_lei | P57: Reunião 2025-07-30 Luís Capitão-Mor, Pedro Mendes, Luísa Sousa Reunião 2025-07-28 Luís Capitão-Mor, Pedro Mendes Reunião 2025-07-17 Luís Capitão-Mor, Flávia Pinho, Luísa Sousa | Q57: Campo novo no LT | R57: Concluído | S57: NÃO | T57: =IF(SEARCH(B57,N57,4),"ok","nok") -> ok
A58: Central securities depository name (if other) | B58: 0462 | C58: String | D58: Free text | E58: Indicate the name of the central securities depository if ‘Other’ is selected in field c0460. Data points c0360 to c0521 might be relevant only in cases of externally issued liabilities or for intragroup liabilities issued in CSDs/iCSDs. | I58: Não | N58: out_b0200_main_liabilities.0462_csd_othr | O58: Valor fixo 'Not applicable' | P58: Reunião 2025-07-17 Luís Capitão-Mor, Flávia Pinho, Luísa Sousa Reunião 2025-07-17 Luís Capitão-Mor, Flávia Pinho, Luísa Sousa | Q58: Campo não LT (apenas tabela Output) | R58: Concluído | S58: NÃO | T58: =IF(SEARCH(B58,N58,4),"ok","nok") -> ok
A59: (Mandated) paying agent | B59: 0470 | C59: String | D59: Free text | E59: Indicate the name of the paying agent, i.e. the entity (or part of an entity) that is processing the cash payments related to the liability’s lifecycle events (e.g. dividend, coupon or redemption) to the holders of that liability. For stocks, a paying agent distributes dividends to stockholders. For bonds, it distributes coupon payments and reimbursements of principal to bondholders. For deposits reported on an aggregated level, input ‘Not applicable’. Data points c0360 to c0521 might be relevant only in cases of externally issued liabilities or for intragroup liabilities issued in CSDs/iCSDs. | F59: Input "Not applicable" | I59: Sim | J59: lt002_instrument.pyng_agnt | L59: {=_xlfn.SWITCH(C59,"Numeric","999999999999999","String","Not applicable","Date","0001-01-01")} -> Not applicable | M59: Se flag_inst_titulos = '1': Obter campo agente_pagador da ct610_titulos (que contém o código lei) e cruzá-lo com o campo clei da ct003_univ_cli, de forma a obter o campo gcliente da ct003_univ_cli. Caso o cruzamento resulte em mais do que 1 gcliente, terá de se trazer apenas 1 gcliente. Para tal, selecionar o zcliente maior (max (zcliente)) que tenha gcliente preenchido. Se flag_inst_titulos = '0': Not applicable. O respetivo valor default de Not applicable deverá ser parametrizado na lt804_conf_dflt. | N59: out_b0200_main_liabilities.0470_pyng_agnt | O59: lt002_instrument.pyng_agnt | P59: Reunião 2025-07-30 Luís Capitão-Mor, Pedro Mendes, Luísa Sousa Reunião 2025-07-28 Luís Capitão-Mor, Pedro Mendes Reunião 2025-07-17 Luís Capitão-Mor, Flávia Pinho, Luísa Sousa | Q59: Campo novo no LT | R59: Concluído | S59: NÃO | T59: =IF(SEARCH(B59,N59,4),"ok","nok") -> ok
A60: (Mandated) paying agent (LEI) | B60: 0471 | C60: String | D60: Free text | E60: When applicable, please indicate the LEI (or another ID) of the paying agent. For deposits reported on an aggregated level, input ‘Not applicable’. Data points c0360 to c0521 might be relevant only in cases of externally issued liabilities or for intragroup liabilities issued in CSDs/iCSDs. | F60: Input "Not applicable" | I60: Sim | J60: lt002_instrument.pyng_agnt_lei | L60: {=_xlfn.SWITCH(C60,"Numeric","999999999999999","String","Not applicable","Date","0001-01-01")} -> Not applicable | M60: Se flag_inst_titulos = '1': Obter agente_pagador da ct610_titulos. Se flag_inst_titulos = '0': Not applicable. O respetivo valor default de Not applicable deverá ser parametrizado na lt804_conf_dflt. | N60: out_b0200_main_liabilities.0471_pyng_agnt_lei | O60: lt002_instrument.pyng_agnt_lei | P60: Reunião 2025-07-30 Luís Capitão-Mor, Pedro Mendes, Luísa Sousa Reunião 2025-07-28 Luís Capitão-Mor, Pedro Mendes Reunião 2025-07-17 Luís Capitão-Mor, Flávia Pinho, Luísa Sousa | Q60: Campo novo no LT | R60: Concluído | S60: NÃO | T60: =IF(SEARCH(B60,N60,4),"ok","nok") -> ok
A61: Trading venue | B61: 0480 | C61: String | D61: Free text | E61: A trading venue is either a regulated market (a stock exchange), a multilateral trading facility (MTF, i.e. a multilateral trading system operated by an investment firm or market operator) or an organised trading facility (OTF, i.e. a multilateral system that is not a regulated market or an MTF). Indicate the name of the trading venue where the liability is admitted to trading. This also includes MTFs and OTFs, where known. In the event of multiple entries, please separate each with a vertical bar. Regulated trading venues must be reported in this field, while unregulated trading venues can be reported on a best-effort basis. When the security is not listed on a trading venue, the attribute ‘Not listed’ must be entered. In case of private placements, the attribute ‘Private placement’ must be entered. For deposits reported on an aggregated level, input ‘Not applicable’. Data points c0360 to c0521 might be relevant only in cases of externally issued liabilities or for intragroup liabilities issued in CSDs/iCSDs. | F61: Input "Not applicable" | I61: Não | N61: out_b0200_main_liabilities.0480_trdng_vn | O61: Valor fixo 'Not applicable' | P61: Reunião 2025-07-30 Luís Capitão-Mor, Pedro Mendes, Luísa Sousa: Email 2025-07-29 11:06 de Pedro Mendes: Segundo Pedro Mendes, este campo é não aplicável para o universo em causa. Reunião 2025-07-28 Luís Capitão-Mor, Pedro Mendes Reunião 2025-07-17 Luís Capitão-Mor, Flávia Pinho, Luísa Sousa | Q61: Campo não LT (apenas tabela Output) | R61: Concluído | S61: NÃO | T61: =IF(SEARCH(B61,N61,4),"ok","nok") -> ok
A62: Trading venue (LEI) | B62: 0481 | C62: String | D62: Free text | E62: When applicable, please indicate the LEI (or another ID) of the trading venue where the liability is admitted to trading. In the event of multiple entries, please separate each with a vertical bar. For deposits reported on an aggregated level, input ‘Not applicable’. Data points c0360 to c0521 might be relevant only in cases of externally issued liabilities or for intragroup liabilities issued in CSDs/iCSDs. | F62: Input "Not applicable" | I62: Não | N62: out_b0200_main_liabilities.0481_trdng_vn_lei | O62: Valor fixo 'Not applicable' | P62: Reunião 2025-07-30 Luís Capitão-Mor, Pedro Mendes, Luísa Sousa: Email 2025-07-29 11:06 de Pedro Mendes: Segundo Pedro Mendes, este campo é não aplicável para o universo em causa. Reunião 2025-07-28 Luís Capitão-Mor, Pedro Mendes Reunião 2025-07-17 Luís Capitão-Mor, Flávia Pinho, Luísa Sousa | Q62: Campo não LT (apenas tabela Output) | R62: Concluído | S62: NÃO | T62: =IF(SEARCH(B62,N62,4),"ok","nok") -> ok
A63: Registrar for information about creditors/holders | B63: 0490 | C63: String | D63: Free text | E63: Indicate the name of the registrar (responsible for holding the records of these liabilities’ owners). The registrar or register holder is usually the issuer itself, a CSD or another entity. For deposits reported on an aggregated level, input ‘Not applicable’. Data points c0360 to c0521 might be relevant only in cases of externally issued liabilities or for intragroup liabilities issued in CSDs/iCSDs. | F63: Input "Not applicable" | I63: Não | J63: lt002_instrument.csd | L63: {=_xlfn.SWITCH(C63,"Numeric","999999999999999","String","Not applicable","Date","0001-01-01")} -> Not applicable | N63: out_b0200_main_liabilities.0490_rgstrr | O63: lt002_instrument.csd | P63: Reunião 2025-07-30 Luís Capitão-Mor, Pedro Mendes, Luísa Sousa Reunião 2025-07-28 Luís Capitão-Mor, Pedro Mendes: Decidiu-se apontar para o campo csd que será criado na lt002_instrument. Reunião 2025-07-17 Luís Capitão-Mor, Flávia Pinho, Luísa Sousa old: Se flag_inst_titulos = '1': Obter campo agente_pagador da ct610_titulos (que contém o código lei) e cruzá-lo com o campo clei da ct003_univ_cli, de forma a obter o campo gcliente da ct003_univ_cli. O cruzamento não poderá resultar em mais do que 1 gnome, como tal, trazer o gcliente com maior zcliente. Caso o cruzamento resulte em mais do que 1 gcliente, terá de se trazer apenas 1 gcliente. Para tal, selecionar o zcliente maior: max(zcliente). Se flag_inst_titulos = '0': ? Aguarda-se resposta ao email enviado a Flávia Pinho (21/07/2025 11:03) | Q63: Campo não LT (apenas tabela Output) | R63: Concluído | S63: NÃO | T63: =IF(SEARCH(B63,N63,4),"ok","nok") -> ok
A64: Registrar for information about creditors/holders (LEI) | B64: 0491 | C64: String | D64: Free text | E64: When applicable, please indicate the LEI (or another ID) of the registrar. For deposits reported on an aggregated level, input ‘Not applicable’. Data points c0360 to c0521 might be relevant only in cases of externally issued liabilities or for intragroup liabilities issued in CSDs/iCSDs. | F64: Input "Not applicable" | I64: Não | J64: lt002_instrument.csd_lei | L64: {=_xlfn.SWITCH(C64,"Numeric","999999999999999","String","Not applicable","Date","0001-01-01")} -> Not applicable | N64: out_b0200_main_liabilities.0491_rgstrr_lei | O64: lt002_instrument.csd_lei | P64: Reunião 2025-07-30 Luís Capitão-Mor, Pedro Mendes, Luísa Sousa Reunião 2025-07-28 Luís Capitão-Mor, Pedro Mendes: Decidiu-se apontar para o campo csd_lei que será criado na lt002_instrument. Reunião 2025-07-17 Luís Capitão-Mor, Flávia Pinho, Luísa Sousa | Q64: Campo não LT (apenas tabela Output) | R64: Concluído | S64: NÃO | T64: =IF(SEARCH(B64,N64,4),"ok","nok") -> ok
A65: National Numbering Agency | B65: 0500 | C65: String | D65: Free text | E65: Indicate the name of the organisation responsible for issuing International Securities Identification Numbers (ISINs) as described by ISO 6166, and the Classification of Financial Instruments code as described by ISO 10962. The role of NNA is typically assigned to the national stock exchange, CSD, central bank or financial regulator. When applicable, for securities deposited by the international central securities depositories (ICSDs), both CSDs shall be reported. For deposits reported on an aggregated level, input ‘Not applicable’. Data points c0360 to c0521 might be relevant only in cases of externally issued liabilities or for intragroup liabilities issued in CSDs/iCSDs. | F65: Input "Not applicable" | I65: Não | J65: lt002_instrument.csd | L65: {=_xlfn.SWITCH(C65,"Numeric","999999999999999","String","Not applicable","Date","0001-01-01")} -> Not applicable | N65: out_b0200_main_liabilities.0500_nna | O65: lt002_instrument.csd | P65: Reunião 2025-07-30 Luís Capitão-Mor, Pedro Mendes, Luísa Sousa Reunião 2025-07-28 Luís Capitão-Mor, Pedro Mendes: Decidiu-se apontar para o campo csd que será criado na lt002_instrument. Reunião 2025-07-17 Luís Capitão-Mor, Flávia Pinho, Luísa Sousa | Q65: Campo não LT (apenas tabela Output) | R65: Concluído | S65: NÃO | T65: =IF(SEARCH(B65,N65,4),"ok","nok") -> ok
A66: National Numbering Agency (LEI) | B66: 0501 | C66: String | D66: Free text | E66: When applicable, please indicate the LEI code (or another ID) of the national numbering agency. For deposits reported on an aggregated level, input ‘Not applicable’. Data points c0360 to c0521 might be relevant only in cases of externally issued liabilities or for intragroup liabilities issued in CSDs/iCSDs. | F66: Input "Not applicable" | I66: Não | J66: lt002_instrument.csd_lei | L66: {=_xlfn.SWITCH(C66,"Numeric","999999999999999","String","Not applicable","Date","0001-01-01")} -> Not applicable | N66: out_b0200_main_liabilities.0501_nna_lei | O66: lt002_instrument.csd_lei | P66: Reunião 2025-07-30 Luís Capitão-Mor, Pedro Mendes, Luísa Sousa Reunião 2025-07-28 Luís Capitão-Mor, Pedro Mendes: Decidiu-se apontar para o campo CSD já existente. Reunião 2025-07-17 Luís Capitão-Mor, Flávia Pinho, Luísa Sousa | Q66: Campo não LT (apenas tabela Output) | R66: Concluído | S66: NÃO | T66: =IF(SEARCH(B66,N66,4),"ok","nok") -> ok
A67: Common Depository | B67: 0510 | C67: String | D67: Free text | E67: Indicate the name of the common depository, when applicable (i.e. if issued in one of the ICSDs and in CGN form). A common depository is an entity appointed by the ICSDs (Euroclear Bank and Clearstream Banking Luxembourg) to provide safekeeping and asset servicing for securities in Classical Global Note form. For deposits reported on an aggregated level, input ‘Not applicable’. Data points c0360 to c0521 might be relevant only in cases of externally issued liabilities or for intragroup liabilities issued in CSDs/iCSDs. | F67: Input "Not applicable" | I67: Não | N67: out_b0200_main_liabilities.0510_cmmn_dpstry | O67: Valor fixo 'Not applicable' | P67: Reunião 2025-07-30 Luís Capitão-Mor, Pedro Mendes, Luísa Sousa Email 2025-07-29 11:06 de Pedro Mendes: Segundo Pedro Mendes, este campo é não aplicável para o universo em causa. Reunião 2025-07-28 Luís Capitão-Mor, Pedro Mendes Reunião 2025-07-17 Luís Capitão-Mor, Flávia Pinho, Luísa Sousa | Q67: Campo não LT (apenas tabela Output) | R67: Concluído | S67: NÃO | T67: =IF(SEARCH(B67,N67,4),"ok","nok") -> ok
A68: Common Depository (LEI) | B68: 0511 | C68: String | D68: Free text | E68: When applicable, please indicate the LEI code (or another ID) of the common depository. For deposits reported on an aggregated level, input ‘Not applicable’. Data points c0360 to c0521 might be relevant only in cases of externally issued liabilities or for intragroup liabilities issued in CSDs/iCSDs. | F68: Input "Not applicable" | I68: Não | N68: out_b0200_main_liabilities.0511_cmmn_dpstry_lei | O68: Valor fixo 'Not applicable' | P68: Reunião 2025-07-30 Luís Capitão-Mor, Pedro Mendes, Luísa Sousa Email 2025-07-29 11:06 de Pedro Mendes: Segundo Pedro Mendes, este campo é não aplicável para o universo em causa. Reunião 2025-07-28 Luís Capitão-Mor, Pedro Mendes Reunião 2025-07-17 Luís Capitão-Mor, Flávia Pinho, Luísa Sousa | Q68: Campo não LT (apenas tabela Output) | R68: Concluído | S68: NÃO | T68: =IF(SEARCH(B68,N68,4),"ok","nok") -> ok
A69: Common Service Provider | B69: 0520 | C69: String | D69: Free text | E69: Indicate the name of the common service provider, when applicable (i.e. if issued in one of the ICSDs and in NGN form). A common service provider is an entity appointed by the ICSDs to provide asset servicing for New Global Notes. For deposits reported on an aggregated level, input ‘Not applicable’. Data points c0360 to c0521 might be relevant only in cases of externally issued liabilities or for intragroup liabilities issued in CSDs/iCSDs. | F69: Input "Not applicable" | I69: Não | N69: out_b0200_main_liabilities.0520_cmmn_srvc_prvdr | O69: Valor fixo 'Not applicable' | P69: Reunião 2025-07-30 Luís Capitão-Mor, Pedro Mendes, Luísa Sousa Email 2025-07-29 11:06 de Pedro Mendes: Segundo Pedro Mendes, este campo é não aplicável para o universo em causa. Reunião 2025-07-28 Luís Capitão-Mor, Pedro Mendes Reunião 2025-07-17 Luís Capitão-Mor, Flávia Pinho, Luísa Sousa | Q69: Campo não LT (apenas tabela Output) | R69: Concluído | S69: NÃO | T69: =IF(SEARCH(B69,N69,4),"ok","nok") -> ok
A70: Common Service Provider (LEI) | B70: 0521 | C70: String | D70: Free text | E70: When applicable, please indicate the LEI code (or another ID) of the common service provider. For deposits reported on an aggregated level, input ‘Not applicable’. Data points c0360 to c0521 might be relevant only in cases of externally issued liabilities or for intragroup liabilities issued in CSDs/iCSDs. | F70: Input "Not applicable" | I70: Não | N70: out_b0200_main_liabilities.0521_cmmn_srvc_prvdr_lei | O70: Valor fixo 'Not applicable' | P70: Reunião 2025-07-30 Luís Capitão-Mor, Pedro Mendes, Luísa Sousa Email 2025-07-29 11:06 de Pedro Mendes: Segundo Pedro Mendes, este campo é não aplicável para o universo em causa. Reunião 2025-07-28 Luís Capitão-Mor, Pedro Mendes Reunião 2025-07-17 Luís Capitão-Mor, Flávia Pinho, Luísa Sousa | Q70: Campo não LT (apenas tabela Output) | R70: Concluído | S70: NÃO | T70: =IF(SEARCH(B70,N70,4),"ok","nok") -> ok
A71: Type of own funds at individual level | B71: 0530 | C71: String | D71: Drop-down | E71: Indicate the type of own funds, as classified at individual level: • T2 in phase-out; • Grandfathered T2; • Fully Compliant T2; • Partially (A)T1 and T2; • Grandfathered AT1; • Fully Compliant AT1; • CET1; • No. In the list of options, the term ‘phase-out’ refers to the period of 5 years before maturity of any given T2 instrument, during which there is only proportionate recognition based on the time remaining until maturity. ‘Grandfathered’ should be understood as any transitional measure applicable to a T2 instrument, not including the ‘phase-out’. During this ‘grandfathering’, recognition may be full or partial. If the instrument is not classified as own funds, please indicate ‘No’. | F71: Input "Not applicable" | I71: Sim | J71: lt002_instrument.typ_own_fnds_indvdl_lvl | L71: {=_xlfn.SWITCH(C71,"Numeric","999999999999999","String","Not applicable","Date","0001-01-01")} -> Not applicable | M71: Se flag_inst_titulos = '1': Obter eleg_fund_prop da ct610_titulos. Se flag_inst_titulos = '0': Not applicable. O respetivo valor default de Not applicable deverá ser parametrizado na lt804_conf_dflt. | N71: out_b0200_main_liabilities.0530_typ_own_fnds_ind_lvl | O71: lt002_instrument.typ_own_fnds_indvdl_lvl | P71: Reunião 2025-07-30 Luís Capitão-Mor, Pedro Mendes, Luísa Sousa Reunião 2025-07-24 Luís Capitão-Mor, Flávia Pinho, Luísa Sousa | Q71: Campo novo no LT | R71: Concluído | S71: NÃO | T71: =IF(SEARCH(B71,N71,4),"ok","nok") -> ok
A72: Eligible amount for own funds at individual level | B72: 0540 | C72: Numeric | D72: 2 decimals | E72: The actual amount in EUR of the instrument qualifying as own funds at individual level. | F72: Input 999999999999999 | I72: Sim | J72: lt002_instrument.elgbl_amnt_own_fnds_indvdl_lvl | L72: {=_xlfn.SWITCH(C72,"Numeric","999999999999999","String","Not applicable","Date","0001-01-01")} -> 999999999999999 | M72: Se flag_inst_titulos = '1': Obter mon_fund_prop da ct610_titulos. Se flag_inst_titulos = '0': Not applicable. O respetivo valor default de Not applicable deverá ser parametrizado na lt804_conf_dflt. | N72: out_b0200_main_liabilities.0540_elgbl_amnt_own_fnds_ind_lvl | O72: lt002_instrument.elgbl_amnt_own_fnds_indvdl_lvl | P72: Reunião 2025-07-30 Luís Capitão-Mor, Pedro Mendes, Luísa Sousa Reunião 2025-07-24 Luís Capitão-Mor, Flávia Pinho, Luísa Sousa | Q72: Campo novo no LT | R72: Concluído | S72: SIM | T72: =IF(SEARCH(B72,N72,4),"ok","nok") -> ok
A73: Type of own funds at consolidated level | B73: 0550 | C73: String | D73: Drop-down | E73: Indicate the type of own funds, as classified at consolidated level: • T2 in phase-out; • Grandfathered T2; • Fully Compliant T2; • Partially (A)T1 and T2; • Grandfathered AT1; • Fully Compliant AT1; • CET1; • No. In the list of options, the term ‘phase-out’ refers to the period of 5 years before maturity of any given T2 instrument, during which there is only proportionate recognition based on the time remaining until maturity. ‘Grandfathered’ should be understood as any transitional measure applicable to a T2 instrument, not including the ‘phase-out’. During this ‘grandfathering’, recognition may be full or partial. If the instrument is not classified as own funds, please indicate ‘No’. For data points c0550 (Type of own funds at consolidated level) and c0560 (Eligible amount of own funds at consolidated level), non-resolution entities should report the type and amount of the liability that is eligible towards the consolidated own funds68, if any. The consolidated own funds should be understood as the ones computed by the corresponding Point of Entry for its consolidated (resolution group) perimeter. When the reporting Non-Resolution Entity is required to consolidate on a sub-consolidated basis, the data point c0550 should be interpreted as “Type of own funds at sub-consolidated level” and c0560 as “Eligible amount of own funds at subconsolidated level”. | F73: Input "Not applicable" | I73: Não | J73: lt002_instrument.typ_own_fnds_indvdl_lvl | L73: {=_xlfn.SWITCH(C73,"Numeric","999999999999999","String","Not applicable","Date","0001-01-01")} -> Not applicable | N73: out_b0200_main_liabilities.0550_typ_own_fnds_cnsldtd_lvl | O73: lt002_instrument.typ_own_fnds_indvdl_lvl | P73: Reunião 2025-09-10 Luís Capitão-Mor, Pedro Mendes, Luísa Sousa Segundo Pedro Mendes: "A minha interpretação é que eles terão os mesmos valores dos data points 0530 e 0540 respetivamente. Isto porque diz na guia: "When the reporting Non-Resolution Entity is required to consolidate on a sub-consolidated basis, the data point c0550 should be interpreted as “Type of own funds at sub-consolidated level” and c0560 as “Eligible amount of own funds at subconsolidated level”." Ou seja o BST individual consolida num BST consolidado que é um sub-consolidado. Quer no BST individual, quer no BST consolidado os instrumentos e respetivos montantes de fundos próprios são os mesmos". Adicionalmente, Pedro Mendes comentou que confirmou com Espanha este entendimento. Reunião 2025-07-30 Luís Capitão-Mor, Pedro Mendes, Luísa Sousa Reunião 2025-07-24 Luís Capitão-Mor, Flávia Pinho, Luísa Sousa | Q73: Campo não LT (apenas tabela Output) | R73: Concluído | S73: NÃO | T73: =IF(SEARCH(B73,N73,4),"ok","nok") -> ok
A74: Eligible amount for own funds at consolidated level | B74: 0560 | C74: Numeric | D74: 2 decimals | E74: The actual amount in EUR of the instrument qualifying as own funds at consolidated level. For data points c0550 (Type of own funds at consolidated level) and c0560 (Eligible amount of own funds at consolidated level), non-resolution entities should report the type and amount of the liability that is eligible towards the consolidated own funds68, if any. The consolidated own funds should be understood as the ones computed by the corresponding Point of Entry for its consolidated (resolution group) perimeter. When the reporting Non-Resolution Entity is required to consolidate on a sub-consolidated basis, the data point c0550 should be interpreted as “Type of own funds at sub-consolidated level” and c0560 as “Eligible amount of own funds at subconsolidated level”. | F74: Input 999999999999999 | I74: Não | J74: lt002_instrument.elgbl_amnt_own_fnds_indvdl_lvl | L74: {=_xlfn.SWITCH(C74,"Numeric","999999999999999","String","Not applicable","Date","0001-01-01")} -> 999999999999999 | N74: out_b0200_main_liabilities.0560_elgbl_amnt_own_fnds_cnsldtd_lvl | O74: lt002_instrument.elgbl_amnt_own_fnds_indvdl_lvl | P74: Reunião 2025-09-10 Luís Capitão-Mor, Pedro Mendes, Luísa Sousa Segundo Pedro Mendes: "A minha interpretação é que eles terão os mesmos valores dos data points 0530 e 0540 respetivamente. Isto porque diz na guia "When the reporting Non-Resolution Entity is required to consolidate on a sub-consolidated basis, the data point c0550 should be interpreted as “Type of own funds at sub-consolidated level” and c0560 as “Eligible amount of own funds at subconsolidated level”." Ou seja o BST individual consolida num BST consolidado que é um sub-consolidado. Quer no BST individual, quer no BST consolidado os instrumentos e respetivos montantes de fundos proprios são os mesmos". Adicionalmente, Pedro Mendes comentou que confirmou com Espanha este entendimento. Reunião 2025-07-30 Luís Capitão-Mor, Pedro Mendes, Luísa Sousa Reunião 2025-07-24 Luís Capitão-Mor, Flávia Pinho, Luísa Sousa | Q74: Campo não LT (apenas tabela Output) | R74: Concluído | S74: SIM | T74: =IF(SEARCH(B74,N74,4),"ok","nok") -> ok
A75: Amount of the security interest provided | B75: 0570 | C75: Numeric | D75: 2 decimals | E75: EUR amount of the security interest provided by a third party. | I75: Não | N75: out_b0200_main_liabilities.0570_amnt_scrty_intrst_prvdd | O75: Valor fixo 0 | P75: Reunião 2025-08-08 Luís Capitão-Mor, Pedro Mendes, Luísa Sousa: Dado que no caso do BST não existe uma third party, tomou-se a decisão de mapear o valor 0. | Q75: Campo não LT (apenas tabela Output) | R75: Concluído | S75: NÃO | T75: =IF(SEARCH(B75,N75,4),"ok","nok") -> ok
A76: Security interest provider (Name) | B76: 0580 | C76: String | D76: Free text | E76: Name of the entity providing the security interest. For deposits reported on an aggregated level, input ‘Not applicable’. | F76: Input "Not applicable" | I76: Não | N76: out_b0200_main_liabilities.0580_scrty_intrst_prvdr | O76: Valor fixo 'Not applicable' | P76: Reunião 2025-08-08 Luís Capitão-Mor, Pedro Mendes, Luísa Sousa: Dado que no caso do BST não existe uma third party, tomou-se a decisão de mapear 'Not applicable'. | Q76: Campo não LT (apenas tabela Output) | R76: Concluído | S76: NÃO | T76: =IF(SEARCH(B76,N76,4),"ok","nok") -> ok
A77: Security interest provider (LEI) | B77: 0581 | C77: String | D77: Free text | E77: LEI code of the entity providing the security interest. For deposits reported on an aggregated level, input ‘Not applicable’. | F77: Input "Not applicable" | I77: Não | N77: out_b0200_main_liabilities.0581_scrty_intrst_prvdr_lei | O77: Valor fixo 'Not applicable' | P77: Reunião 2025-08-08 Luís Capitão-Mor, Pedro Mendes, Luísa Sousa: Dado que no caso do BST não existe uma third party, tomou-se a decisão de mapear 'Not applicable'. | Q77: Campo não LT (apenas tabela Output) | R77: Concluído | S77: NÃO | T77: =IF(SEARCH(B77,N77,4),"ok","nok") -> ok
A78: Type of security interest provided by a third party | B78: 0590 | C78: String | D78: Drop-down | E78: Interest linked to guarantees and sureties. Please select the entry from the following drop-down list: • Lien • Guarantee • Surety • Guarantee obligation • Other • Not applicable In the list of options, "Guarantee obligation" refers to a special type of guarantee agreement that used to be extended to publicly owned banks by their owners where the owners would guarantee liabilities of the respective bank. An example would be the former "Gewährträgerhaftung" applicable to German Landesbanken. For deposits reported on an aggregated level, input ‘Aggregated’. | F78: Input "Not applicable" | I78: Não | N78: out_b0200_main_liabilities.0590_typ_scrty_intrst_prvdd | O78: Valor fixo 'Not applicable' | P78: Reunião 2025-08-08 Luís Capitão-Mor, Pedro Mendes, Luísa Sousa: Dado que no caso do BST não existe uma third party, tomou-se a decisão de mapear 'Not applicable'. | Q78: Campo não LT (apenas tabela Output) | R78: Concluído | S78: NÃO | T78: =IF(SEARCH(B78,N78,4),"ok","nok") -> ok
A79: Collateral for an asset position | B79: 0600 | C79: String | D79: TRUE / FALSE boolean | E79: Indicate whether the liability is used as collateral for an asset position. The value to be reported is a TRUE/FALSE Boolean (where ‘TRUE’ = used as collateral, and ‘FALSE’ = not used as collateral). For deposits reported on an aggregate level, this data point is not applicable. | F79: Input "Not applicable" | I79: Não | N79: out_b0200_main_liabilities.0600_flg_clltrl_asst_pstn | O79: Valor fixo 'FALSE' | P79: Reunião 2025-08-13 Luís Capitão-Mor, Pedro Mendes, Luísa Sousa: Dado que este universo de títulos contém risco, então dificilmente serão usados como Colateral. Como tal, tomou-se a decisão de mapear 'FALSE'. | Q79: Campo não LT (apenas tabela Output) | R79: Concluído | S79: NÃO | T79: =IF(SEARCH(B79,N79,4),"ok","nok") -> ok
A80: Carrying amount IFRS | B80: 0610 | C80: Numeric | D80: 2 decimals | E80: To the extent relevant for the bank, the carrying amount under IFRS (58). (58) - When precise values are not available, estimates can be used to fill this data point. | I80: Não | J80: lt002_instrument.crryng_amnt_instrmnt | L80: {=_xlfn.SWITCH(C80,"Numeric","999999999999999","String","Not applicable","Date","0001-01-01")} -> 999999999999999 | N80: out_b0200_main_liabilities.0610_crryng_amnt_ifrs | O80: (-1) * lt002_instrument.crryng_amnt_instrmnt Nota: Esta multiplicação por -1, deve-se ao facto de no Loan Tape o campo crryng_amnt_instrmnt apresentar valores negativos (para o caso destes registos de Títulos Passivos) e neste report pretenderem-se valores positivos (segundo Pedro Mendes). | P80: Reunião 2025-08-13 Luís Capitão-Mor, Pedro Mendes, Luísa Sousa | Q80: Campo já existente no LT | R80: Concluído | S80: SIM | T80: =IF(SEARCH(B80,N80,4),"ok","nok") -> ok | U80: Dado que inclui Juros
A81: Balance sheet item according to IFRS | B81: 0620 | C81: String | D81: Drop-down | E81: One of the following items to be selected as attribute in accordance with the classification in FINREP (according to Annex IV of Regulation (EU) 2015/534 of the ECB): • 010 Financial liabilities held for trading; • 070 Financial liabilities at fair value through profit or loss; • 110 Financial liabilities at amortized cost; • 280 Other liabilities; • 300 Total equity. For deposits reported on an aggregated level, please indicate the most prevalent balance sheet item category. | I81: Não | J81: lt002_instrument. accntng_clssfctn | L81: {=_xlfn.SWITCH(C81,"Numeric","999999999999999","String","Not applicable","Date","0001-01-01")} -> Not applicable | M81: Necessário criar novas parametrizaçôes nas tabelas lt829_regras_conversao e lt830_conversoes, podendo as mesmas ser consultadas neste documento nas sheets: LT829 - filtrando por campo_conceito = 'ACCNTNG_CLSSFCTN' e regra_conversao = '3'; LT830 - filtrando por segmento = 'ESTR' e campo_conceito = 'ACCNTNG_CLSSFCTN'. | N81: out_b0200_main_liabilities.0620_blnc_sht_ifrs | O81: lt002_instrument. accntng_clssfctn | P81: Reunião 2025-08-06 Luísa Sousa Em 2025-08-11 Luísa Sousa adicionou na tabela lt803_codigos_lt novas parametrizações, que podem ser consultadas na sheet LT803 - filtrando por campo_lt = 'ACCNTNG_CLSSFCTN'; Parametrizações da lt803_codigos_lt/lt829_regras_conversao/lt830_conversoes confirmadas com Luísa Sousa. Reunião 2025-07-31 Luís Capitão-Mor, Pedro Mendes | Q81: Campo já existente no LT | R81: Concluído | S81: NÃO | T81: =IF(SEARCH(B81,N81,4),"ok","nok") -> ok
A82: Carrying amount national GAAP | B82: 0630 | C82: Numeric | D82: 2 decimals | E82: Carrying amount under national GAAP (where applicable) (59). (59) - When precise values are not available, estimates can be used to fill this data point. | I82: Não | N82: out_b0200_main_liabilities.0630_crrying_amnt_ngaap | O82: Valor fixo 999999999999999 | P82: Reunião 2025-08-13 Luís Capitão-Mor, Pedro Mendes, Luísa Sousa: O BST usa IFRS, não usa national GAAP, como tal, este campo é Not Applicable. | Q82: Campo não LT (apenas tabela Output) | R82: Concluído | S82: NÃO | T82: =IF(SEARCH(B82,N82,4),"ok","nok") -> ok
A83: Balance sheet item at Resolution entity level according to national GAAP | B83: 0640 | C83: String | D83: Free text | E83: Classification in accordance with national GAAP (where applicable). For deposits reported on an aggregated level, please indicate the most prevalent balance sheet item category. | I83: Não | N83: out_b0200_main_liabilities.0640_blnc_sht_ngaap | O83: Valor fixo 'Not applicable' | P83: Reunião 2025-07-31 Luís Capitão-Mor, Pedro Mendes: Segundo Pedro Mendes este campo é not applicable por duas razões: - Porque o BST é uma non-resolution entity; - Porque no caso de Portugal, usa-se o IFRS e não o national GAAP. | Q83: Campo não LT (apenas tabela Output) | R83: Concluído | S83: NÃO | T83: =IF(SEARCH(B83,N83,4),"ok","nok") -> ok
A84: Instrument/liability is issued to or bought by an existing shareholder that is not part of the same resolution group | B84: 5000 | C84: String | D84: TRUE / FALSE boolean | E84: Flag to identify whether a liability is issued to or bought by an existing shareholder that is not part of the same resolution group according to Article 12g(2)(a)(i) SRMR. The value to be reported is a TRUE/FALSE Boolean. | I84: Não | N84: out_b0200_main_liabilities.5000_flg_shrhldr_not_rsltn_grp | O84: Valor fixo 'FALSE' | P84: Reunião 2025-07-31 Luís Capitão-Mor, Pedro Mendes: Campo com o valor fixo 'False'. Não existe previsão de que a futuro existam alterações na estrutura dos grupos de resolução, como tal, assumiu-se este valor como fixo. | Q84: Campo não LT (apenas tabela Output) | R84: Concluído | S84: NÃO | T84: =IF(SEARCH(B84,N84,4),"ok","nok") -> ok
A85: Instrument/liability meets the requirements of Art. 21(7a) SRMR | B85: 5010 | C85: String | D85: TRUE / FALSE boolean | E85: Flag to identify whether a liability fulfils the criteria laid down in Article 21(7a) SRMR (conditions referred to in point Article 12g(2)(a) SRMR, except the condition relating to the remaining maturity of liabilities as set out in Article 72c(1) CRR). The value to be reported is a TRUE/FALSE Boolean. This data point is especially relevant if the scope of collection is expanded, as mentioned in the first paragraph of this annex. | I85: Não | N85: out_b0200_main_liabilities.5010_flg_art21_7a_srmr | O85: Valor fixo 'TRUE' | P85: Reunião 2025-07-31 Luís Capitão-Mor, Pedro Mendes: Segundo Pedro Mendes este campo terá valor fixo 'True', pois para o universo em causa do bail-in (títulos) todos os registos contam para MREL. | Q85: Campo não LT (apenas tabela Output) | R85: Concluído | S85: NÃO | T85: =IF(SEARCH(B85,N85,4),"ok","nok") -> ok
I86: =COUNTIF(I5:I85,"Não") -> 65

Sheet B05.00
A1: B05.00 - Guarantees provided to the Non-Resolution Entity: this tab includes the relevant data points on guarantees for monitoring and implementing the loss transfer and recapitalisation mechanisms at non-resolution entity level;
A2: SRB Instructions | I2: Especificação IT | S2: lt833_agreg_campos
I3: Fase 1 - Granular (Loan Tape) | N3: Fase 2 - Agregada (Não Loan Tape) | P3: Comentários/Histórico EF
A4: Data Point | B4: ID | C4: Data type | D4: Constrain | E4: Description | F4: Treatment of "Not applicable" (if cell is grey out, input is not expected) | G4: Treatment of "Not available" (if cell is grey out, input is not expected) | I4: Novo campo? | J4: Nome campo | K4: Missing Value (LT804) | L4: Not Applicable Value (LT804) | M4: Regra campo | N4: Nome campo | O4: Regra campo | Q4: Estado Especificação | R4: Estado Desenvolvimento | S4: tabela_condicao | T4: campo_condicao | U4: valor_condicao | V4: tabela_origem | W4: campo_origem | X4: campo_destino | Y4: campo_exp | Z4: acao | AA4: ckutulmo | AB4: htimest | AC4: ambito | AD4: segmento | AE4: segmento_agregado | AF4: ref_date | AG4: cod_visao | AH4: Tipo de Garantia | AI4: Necessita de ajuste? (2025-10-31 vs 2025-11-14)
A5: Row number | B5: 0010 | C5: Numeric | D5: Integer | E5: The unique number / primary key to identify the row items (the number must be an integer). | I5: Não | N5: out_b0500_guarantees.0010_row_nmbr | O5: Sequenciador a implementar na tabela de output out_b0500_guarantees Nota: A cada execução não deverão ser gerados Row numbers diferentes pelo que provisoriamente deverá ser feito um order by 0020_uniq_id_guarantee | P5: Reunião 2025-06-02 Luís Capitão-Mor, Pedro Mendes, Luísa Sousa | Q5: Campo não LT (apenas tabela Output) | R5: Concluído | X5: 1 | Y5: 0010 | Z5: SEQUENCIA | AC5: SRB | AE5: B0500 | AG5: 1 | AH5: Geral | AI5: NÃO
A6: Unique (internal) identifier of the guarantee provided to the Non-Resolution Entity | B6: 0020 | C6: String | D6: Free text | E6: Internal identifier of the guarantee and of the financial support arrangement, if applicable. | I6: Não | J6: lt006_instr_prot.instrmnt_id.instrmnt_id lt006_instr_prot.prtctn_id | L6: {=_xlfn.SWITCH(C6,"Numeric","999999999999999","String","Not applicable","Date","0001-01-01")} -> Not applicable | N6: out_b0500_guarantees.0020_uniq_id_guarantee | O6: concat(lt006_instr_prot.instrmnt_id, lt006_instr_prot.prtctn_id) | P6: Reunião 2025-10-13 Luís Capitão-Mor, Pedro Mendes, Luísa Sousa: concat(lt006_instr_prot.instrmnt_id, lt006_instr_prot.prtctn_id) Reunião 2025-06-02 Luís Capitão-Mor, Pedro Mendes, Luísa Sousa: lt004_protection.prtctn_id | Q6: Campo já existente no LT | R6: Concluído | S6: lt002_instrument | T6: ind_univ | U6: B0500 | V6: lt004_protection | W6: prtctn_id | X6: 2 | Y6: 0020 | Z6: AGRUPAR | AC6: SRB | AE6: B0500 | AG6: 1 | AH6: Geral | AI6: NÃO
A7: Governing law | B7: 0030 | C7: String | D7: ISO 3166-1 alpha 2 / ISO 3166-2 | E7: The ISO 3166-1 alpha-2 code of the country whose law governs the instrument (please use the ISO 3166-2 code when the law of an administrative subdivision is relevant, e.g. ‘US-NY’). If the contract is governed by the law of more than one country, indicate the country whose law has the highest relevance for the recognition of write-down and conversion powers. | I7: Não | N7: out_b0500_guarantees.0030_governing_law | O7: Valor fixo 'PT' | P7: Reunião 2025-09-08 Luís Capitão-Mor, Pedro Mendes: No âmbito do campo Governing law da sheet B05.00, verificou-se que os registos deste Universo têm maioritarimente Governing law= 'PT', contudo, existe pelo menos 1 registo, "ELECGAS (TEJO II) 557MM 04/03/08 CLOII" cujo Governing law é 'GB'. Para este registo, consta "English Law" no documento LMA Trade Confirmation Risk Participation (Email recebido 26/06/2025 18:40 de Luís Capitão-Mor com os vários documentos). Será portanto, necessário efectuar um desenvolvimento estrutural que permita alterar o valor reportado em cada campo de cada uma das quatro tabelas de output (out_b0100_aggregate_view, out_b0200_main_liabilities, out_b0500_guarantees, out_b9000_counterparties). Este novo desenvolvimento deverá consistir num processo igual ao holístico já existente no Loan Tape. Exemplo: O campo acima (Governing law) terá o valor fixo ‘PT’ para todos os registos da sheet B05.00. Com este novo desenvolvimento, o Utilizador terá a possibilidade de alterar o valor do registo acima ("ELECGAS (TEJO II) 557MM 04/03/08 CLOII") de 'PT' para 'GB'. Email Pedro Mendes 17/06/2025 08:53: Neste campo pretende-se a governing law ao nível da garantia (recebida). | Q7: Campo não LT (apenas tabela Output) | R7: Concluído | S7: lt002_instrument | T7: ind_univ | U7: B0500 | V7: lt002_instrument | W7: governing_law Campo já existente na lt002_instrument (e não na lt004_protection) | X7: 3 | Y7: 0030 | Z7: AGRUPAR | AC7: SRB | AE7: B0500 | AG7: 1 | AH7: Geral | AI7: NÃO
A8: Guarantee fulfils the requirements pursuant to Art. 12g (3) SRMR | B8: 0040 | C8: String | D8: TRUE / FALSE boolean | E8: Indicate whether the guarantee fulfils the requirements pursuant to Article 12g(3) SRMR. The value to be reported is a TRUE/FALSE Boolean. ‘TRUE’ should be selected only if the SRB has officially recognised that all necessary requirements have been fulfilled. | I8: Não | N8: out_b0500_guarantees.0040_flg_art12g_3_srmr | O8: Valor fixo 'FALSE' | P8: Reunião 2025-08-13 Luís Capitão-Mor, Pedro Mendes, Luísa Sousa ‣ Acordou-se que o campo será criado apenas na tabela final out_b0500_guarantees e não será criado no Loan Tape, à semelhança dos restantes campos de valor fixo. Reunião 2025-06-04 Luís Capitão-Mor, Pedro Mendes, Luísa Sousa ‣ Segundo Pedro Mendes este campo é sempre 'FALSE'. Email Pedro Mendes 17/06/2025 08:53: O BST não tem e não está previsto que venha a ter este tipo de garantias. | Q8: Campo não LT (apenas tabela Output) | R8: Concluído | S8: lt002_instrument | T8: ind_univ | U8: B0500 | V8: lt004_protection | W8: flg_art12g3_srmr Campo novo | X8: 4 | Y8: 0040 | Z8: AGRUPAR | AC8: SRB | AE8: B0500 | AG8: 1 | AH8: Geral | AI8: NÃO
A9: Type of guarantee | B9: 0050 | C9: String | D9: Drop down | E9: Indicate the type of guarantee using one of the values from the Liability Data Report, namely: • Issuance = for guarantees on specific instruments/liabilities that have been issued; • Counterparty = for guarantees granted to a specific counterparty of the institution; • Unlimited = for general guarantees not limited to a fixed amount; • Other types of guarantee than issuance guarantees, counterparty guarantees and unlimited guarantees. | I9: Não | N9: out_b0500_guarantees.0050_typ_guarantee | O9: Valor fixo 'Counterparty' | P9: Reunião 2025-08-13 Luís Capitão-Mor, Pedro Mendes, Luísa Sousa ‣ Acordou-se que o campo será criado apenas na tabela final out_b0500_guarantees e não será criado no Loan Tape, à semelhança dos restantes campos de valor fixo. Reunião 2025-06-04 Luís Capitão-Mor, Pedro Mendes, Luísa Sousa ‣ Segundo Pedro Mendes este campo é sempre 'Counterparty'. ‣ Comentários Luís Capitão-Mor: - O BST não tem nada a garantir uma emissão específíca (portanto não há "Issuance"); - O BST não tem "Unlimited". | Q9: Campo não LT (apenas tabela Output) | R9: Concluído | S9: lt002_instrument | T9: ind_univ | U9: B0500 | V9: lt004_protection | W9: Existem dois campos na lt004_protection: typ_prtctn e typ_prtctn_intrnl. Usar o typ_prtctn ou será um campo novo? | X9: 5 | Y9: 0050 | Z9: AGRUPAR | AC9: SRB | AE9: B0500 | AG9: 1 | AH9: Geral | AI9: NÃO
A10: Maximum amount of the guarantee | B10: 0060 | C10: Numeric | D10: 2 decimals | E10: The EUR (counter)value of the maximum amount (if any) covered by the guarantee / financial support arrangement. | I10: Não | J10: lt006_instr_prot.prtctn_allctd_vl | L10: {=_xlfn.SWITCH(C10,"Numeric","999999999999999","String","Not applicable","Date","0001-01-01")} -> 999999999999999 | N10: out_b0500_guarantees.0060_max_amnt_guarantee | O10: lt006_instr_prot.prtctn_allctd_vl | P10: Reunião 2025-09-10 Luís Capitão-Mor, Pedro Mendes, Luísa Sousa: lt006_instr_prot.prtctn_allctd_vl Reunião 2025-06-04 Luís Capitão-Mor, Pedro Mendes, Luísa Sousa: lt004_protection.prtctn_vl Comentários Luís Capitão-Mor: Se tivermos o Banco Santander S.A. a garantir 4 responsabilidades diferentes ao BST: Garantia 1: 1.000.000 eur Garantia 2: 2.000.000 eur Garantia 3: 3.000.000 eur Garantia 4: 4.000.000 eur Na lt004_protection temos um zcliente único, e portanto, um prtctn_id único dado que no caso das garantias pessoais o protection_id contém o zcliente, logo o prtctn_vl conterá a soma das 4 garantias, ou seja, 10.000.000 eur. Na lt006_instr_prot temos 4 linhas com os 4 prtctn_allctd_vl (1.000.000 eur, 2.000.000 eur, 3.000.000 eur, 4.000.000 eur). Neste caso, queremos reportar 10.000.000 eur que corresponde ao campo prtctn_vl da lt004_protection. A alternativa seria "vetorizar" este campo (1.000.000 | 2.000.000 | 3.000.000 | 4.000.000), mas depois não ficaria com valores somáveis. | Q10: Campo já existente no LT | R10: Concluído | S10: lt002_instrument | T10: ind_univ | U10: B0500 | V10: lt004_protection | W10: max_amnt_prtctn Campo novo nota: já existe o ma | X10: 6 | Y10: 0060 | Z10: SOMAR | AC10: SRB | AE10: B0500 | AG10: 1 | AH10: Geral
A11: Guarantee is secured | B11: 0070 | C11: String | D11: Drop down | E11: Indicate whether the guarantee is: • Secured; • Unsecured. | I11: Sim | J11: lt004_protection.flg_scrd | L11: {=_xlfn.SWITCH(C11,"Numeric","999999999999999","String","Not applicable","Date","0001-01-01")} -> Not applicable | M11: Passo 1: Usar tradutor chaves finrep para converter chave finrep para chave ICs, dado que a gt018_rateio_aval está em chave ICs. Passo 2: Com a chave ICs obtida no Passo 1, aceder à gt018_rateio_aval e obter campo tipologia. Passo 3 Converter campo tipologia obtido no Passo 2 em 'Secured' ou 'Unsecured'. Para tal, será necessário criar nova parametrização na tabela lt831_param_conceitos, podendo a mesma ser consultada neste documento na sheet 'LT831' filtrando por tabela_conceito = 'LT004_PROTECTION' e campo_conceito = 'FLG_SCRD'. | N11: out_b0500_guarantees.0070_flg_scrd | O11: lt004_protection.flg_scrd | P11: Reunião 2025-06-06 Luís Capitão-Mor, Pedro Mendes, Luísa Sousa Comentário Pedro Mendes: - Secured (quando a garantia é real) e Unsecured (quando a garantia não é real). Portanto, como as garantias pessoais não são reais, então são Unsecured. Comentário Luís Capitão-Mor: - Este campo terá de estar sempre preenchido ('Secured' ou 'Unsecured'), não é expectável existirem MISS ou N/A; | Q11: Campo novo no LT | R11: Não Concluído | S11: lt002_instrument | T11: ind_univ | U11: B0500 | V11: lt004_protection | W11: flg_scrd_prtctn Campo novo | X11: 7 | Y11: 0070 | Z11: AGRUPAR | AC11: SRB | AE11: B0500 | AG11: 1 | AH11: Geral | AI11: NÃO
A12: Current value of the collateral | B12: 0080 | C12: Numeric | D12: 2 decimals | E12: If collateralised (field c0070 = ‘Secured’), indicate the amount of collateral provided, net of valuation adjustments and haircuts. | I12: Não | N12: out_b0500_guarantees.0080_amnt_clltrl | O12: Valor fixo 999999999999999 (valor default N/A para numérico definido pelo SRB) | P12: Reunião 2025-06-26 Luís Capitão-Mor, Pedro Mendes, Luísa Sousa: Luis Capitão-Mor indicou que este campo não será criado no Loan Tape mas sim, apenas na tabela de output out_b0500_guarantees, com valor fixo de não aplicável. Isto porque o campo é referente a informação de Colateral, e no caso do BST só existem garantias pessoais recebidas de clientes intragrupo Santander (ou seja, não existem garantias reais, onde se aplica o conceito de colateral). Adicionalmente, Pedro Mendes concordou com esta abordagem (email 03/07/2025 10:18). Reunião 2025-06-05 Luís Capitão-Mor, Pedro Mendes, Luísa Sousa Comentário Luís Capitão-Mor: Existe o campo de haircuts no Loan Tape (HRCT_MV), contudo, o mesmo é referente a IFRS9 (segundo o guia do Loan Tape Estrutural da Corporação). Portanto, como o SRB não refere nada relativamente a IFRS9 então não vamos considerar haircuts. old: Se typ_scrd (campo ID 0070) = 'Secured' reportar lt004_protection.prtctn_vl Se typ_scrd (campo ID 0070) = 'Unsecured' reportar 999999999999999 (valor default N/A para numérico definido pelo SRB) Nota: terá de ser sempre um campo novo pois o campo prtctn_vl já foi solicitado noutro campo deste report. | Q12: Campo não LT (apenas tabela Output) | R12: Concluído | S12: lt002_instrument | T12: ind_univ | U12: B0500 | V12: lt004_protection | W12: crrnt_value_prtctn Campo novo (se bem que existe o prtctn_vl) | X12: 8 | Y12: 0080 | Z12: SOMAR | AC12: SRB | AE12: B0500 | AG12: 1 | AH12: Collateral | AI12: NÃO
A13: Guarantee trigger | B13: 0090 | C13: String | D13: Fixed values | E13: Provide the type(s) of event(s) triggering the activation of the guarantee / financial support, i.e. the event(s) enabling the right for the counterparty to execute the guarantee, choosing from: • Default; • Solvency-related; • Liquidity-related; • Other than default, solvency-related or liquidity-related. In case of multiple entries, please separate them with a vertical bar. | I13: Não | N13: out_b0500_guarantees.0090_guarantee_trggr | O13: Valor fixo 'Default' | P13: Reunião 2025-09-08 Luís Capitão-Mor, Pedro Mendes: - Sugere-se reportar valor fixo 'Default' para este campo. No entanto, se a futuro se identificar a necessidade de se alterar este valor para algum registo, deverá recorrer-se ao novo desenvolvimento estrutural anteriormente mencionado no campo Governing law e no documento funcional MBDT Estrutura v1.0, que permitirá alterar de 'Default' para um dos seguintes valores possíveis (code-list SRB): 'Solvency-related', 'Liquidity-related', 'Other than default, solvency-related or liquidity-related' - Identificaram-se as seguintes referências a Default/Insolvency no documento LMA Trade Confirmation Risk Participation (exemplo Auto-Estradas XXI): -"2.1 Notice of Default (a) If any amont which falls due from an Obligor at any time during the relevant Risk Period and which is referred to in Clause 2.2 (Included Amounts) is not received and applied by the Grantor in full when due, the Grantor may notify the Participant accordingly." -"15. Termination (c) If an Insolvency Event occurs in respect of the Grantor, the Participant may at any time after the occurrence of that Insolvency Event deliver a termination notice to the Grantor and the Risk Participation shall be terminated on and with effect from the date specified in such termination notice." | Q13: Campo não LT (apenas tabela Output) | R13: Concluído | S13: lt002_instrument | T13: ind_univ | U13: B0500 | V13: lt004_protection | W13: trigger_prtctn Campo novo | X13: 9 | Y13: 0090 | Z13: AGRUPAR | AC13: SRB | AE13: B0500 | AG13: 1 | AH13: Geral | AI13: NÃO
