Workbook

Sheet T 01.00 a
A1: T 01.00.b - Liability structure - carrying amount
D4: Columns
D5: Households | E5: Micro & SME | F5: Corporates | G5: Institutions | H5: Other financial corporations | J5: Government, central banks & supranationals | K5: Instruments listed on exchange platforms | L5: Others/non-identified | M5: Total
D6: Carrying amount | E6: Carrying amount | F6: Carrying amount | G6: Carrying amount | H6: Carrying amount | I6: Of which Insurance firms & pension funds | J6: Carrying amount | K6: Carrying amount | L6: Carrying amount | M6: Carrying amount | N6: Of which: intragroup | O6: Of which: issuances under non-EU MS jurisdiction/law, excluding intragroup
I7: Carrying amount | N7: Carrying amount | O7: Carrying amount
D8: 0011 | E8: 0021 | F8: 0031 | G8: 0041 | H8: 0051 | I8: 0061 | J8: 0081 | K8: 0091 | L8: 0101 | M8: 0121 | N8: 0131 | O8: 0141
A9: Rows | B9: Liabilities excluded from bail-in | C9: 0100 | D9: =D10+D11+D12+D13+D14+D15+D16+D17+D18+D19+D20 -> 1.9384943e+10 | E9: =E10+E11+E12+E13+E14+E15+E16+E17+E18+E19+E20 -> 2.3350551e+09 | F9: =F10+F11+F12+F13+F14+F15+F16+F17+F18+F19+F20 -> 3.8825771e+08 | G9: =G10+G11+G12+G13+G14+G15+G16+G17+G18+G19+G20 -> 2.1391569e+09 | H9: =H10+H11+H12+H13+H14+H15+H16+H17+H18+H19+H20 -> 3.9249404e+09 | I9: =I10+I11+I12+I13+I14+I15+I16+I17+I18+I19+I20 -> 3.0305582e+08 | J9: =J10+J11+J12+J13+J14+J15+J16+J17+J18+J19+J20 -> 7.7635511e+09 | K9: =K10+K11+K12+K13+K14+K15+K16+K17+K18+K19+K20 -> 0 | L9: =L10+L11+L12+L13+L14+L15+L16+L17+L18+L19+L20 -> 0 | M9: =SUM(D9:L9)-I9 -> 3.5935904e+10 | N9: =N10+N11+N12+N13+N14+N15+N16+N17+N18+N19+N20 -> 9.0358516e+08 | O9: 0
B10: Covered deposits (BRRD art. 44/2/a) | C10: 0110 | D10: =+SUMIFS('T 05.01'!$M:$M,'T 05.01'!$E:$E,"r0110 - Covered deposits (BRRD art. 44/2/a)",'T 05.01'!$F:$F,"c001x - Households")+SUMIFS('T 03.01'!P:P,'T 03.01'!E:E,"r0110 - Covered deposits (BRRD art. 44/2/a)",'T 03.01'!$F:$F,"c001x - Households") -> 1.914788e+10 | E10: =+SUMIFS('T 05.01'!$M:$M,'T 05.01'!$E:$E,"r0110 - Covered deposits (BRRD art. 44/2/a)",'T 05.01'!$F:$F,"c002x - Micro & SME")+SUMIFS('T 03.01'!P:P,'T 03.01'!E:E,"r0110 - Covered deposits (BRRD art. 44/2/a)",'T 03.01'!$F:$F,"c002x - Micro & SME") -> 2.3350551e+09 | F10: =+SUMIFS('T 05.01'!$M:$M,'T 05.01'!$E:$E,"r0110 - Covered deposits (BRRD art. 44/2/a)",'T 05.01'!$F:$F,"c003x - Corporates")+SUMIFS('T 03.01'!P:P,'T 03.01'!E:E,"r0110 - Covered deposits (BRRD art. 44/2/a)",'T 03.01'!$F:$F,"c003x - Corporates") -> 3.8825771e+08 | G10: =+SUMIFS('T 05.01'!$M:$M,'T 05.01'!$E:$E,"r0110 - Covered deposits (BRRD art. 44/2/a)",'T 05.01'!$F:$F,"c004x - Institutions")+SUMIFS('T 03.01'!P:P,'T 03.01'!E:E,"r0110 - Covered deposits (BRRD art. 44/2/a)",'T 03.01'!$F:$F,"c004x - Institutions") -> 0 | H10: =+SUMIFS('T 05.01'!$M:$M,'T 05.01'!$E:$E,"r0110 - Covered deposits (BRRD art. 44/2/a)",'T 05.01'!$F:$F,"c005x - Other financial corporations")+I10+SUMIFS('T 03.01'!P:P,'T 03.01'!E:E,"r0110 - Covered deposits (BRRD art. 44/2/a)",'T 03.01'!$F:$F,"c005x - Other financial corporations") -> 0 | I10: =+SUMIFS('T 05.01'!$M:$M,'T 05.01'!$E:$E,"r0110 - Covered deposits (BRRD art. 44/2/a)",'T 05.01'!$F:$F,"c006x - Insurance firms & pension funds")+SUMIFS('T 03.01'!P:P,'T 03.01'!E:E,"r0110 - Covered deposits (BRRD art. 44/2/a)",'T 03.01'!$F:$F,"c006x - Insurance firms & pension funds") -> 0 | J10: =+SUMIFS('T 05.01'!$M:$M,'T 05.01'!$E:$E,"r0110 - Covered deposits (BRRD art. 44/2/a)",'T 05.01'!$F:$F,"c008x - Government, central banks & supranationals")+SUMIFS('T 03.01'!P:P,'T 03.01'!E:E,"r0110 - Covered deposits (BRRD art. 44/2/a)",'T 03.01'!$F:$F,"c008x - Government, central banks & supranationals") -> 0 | K10: 0 | L10: =+SUMIFS('T 05.01'!$M:$M,'T 05.01'!$E:$E,"r0110 - Covered deposits (BRRD art. 44/2/a)",'T 05.01'!$F:$F,"")+SUMIFS('T 03.01'!P:P,'T 03.01'!E:E,"r0110 - Covered deposits (BRRD art. 44/2/a)",'T 03.01'!$F:$F,"") -> 0 | M10: =SUM(D10:L10)-I10 -> 2.1871193e+10 | N10: =+SUMIF('T 03.01'!E:E,"r0110 - Covered deposits (BRRD art. 44/2/a)",'T 03.01'!P:P) -> 732268.55 | O10: 0 | V10: =+N10+N22+M27 -> 6.6805752e+09
B11: Secured liabilities - collateralized part (BRRD art. 44/2/b) | C11: 0120 | D11: =SUMIF('T 08.00'!$E:$E,"c001x - Households",'T 08.00'!$O:$O)+SUMIFS('T 03.01'!P:P,'T 03.01'!E:E,"r0120 - Secured liabilities - collateralized part (BRRD art. 44/2/b)",'T 03.01'!$F:$F,"c001x - Households")+SUMIFS('T 04.00'!N:N,'T 04.00'!F:F,"c001x - Households",'T 04.00'!E:E,"r0120 - Secured liabilities - collateralized part (BRRD art. 44/2/b)") -> 0 | E11: =SUMIF('T 08.00'!$E:$E,"c002x - Micro & SME",'T 08.00'!$O:$O)+SUMIFS('T 03.01'!P:P,'T 03.01'!E:E,"r0120 - Secured liabilities - collateralized part (BRRD art. 44/2/b)",'T 03.01'!$F:$F,"c002x - Micro & SME")+SUMIFS('T 04.00'!N:N,'T 04.00'!F:F,"c002x - Micro & SME",'T 04.00'!E:E,"r0120 - Secured liabilities - collateralized part (BRRD art. 44/2/b)") -> 0 | F11: =SUMIF('T 08.00'!$E:$E,"c003x - Corporates",'T 08.00'!$O:$O)+SUMIFS('T 03.01'!P:P,'T 03.01'!E:E,"r0120 - Secured liabilities - collateralized part (BRRD art. 44/2/b)",'T 03.01'!$F:$F,"c003x - Corporates")+SUMIFS('T 04.00'!N:N,'T 04.00'!F:F,"c003x - Corporates",'T 04.00'!E:E,"r0120 - Secured liabilities - collateralized part (BRRD art. 44/2/b)") -> 0 | G11: =SUMIF('T 08.00'!$E:$E,"c004x - Institutions",'T 08.00'!$O:$O)+SUMIFS('T 03.01'!P:P,'T 03.01'!E:E,"r0120 - Secured liabilities - collateralized part (BRRD art. 44/2/b)",'T 03.01'!$F:$F,"c004x - Institutions")+SUMIFS('T 04.00'!N:N,'T 04.00'!F:F,"c004x - Institutions",'T 04.00'!E:E,"r0120 - Secured liabilities - collateralized part (BRRD art. 44/2/b)") -> 1.9851326e+09 | H11: =SUMIF('T 08.00'!$E:$E,"c005x - Other financial corporations",'T 08.00'!$O:$O)+I11+SUMIFS('T 03.01'!P:P,'T 03.01'!E:E,"r0120 - Secured liabilities - collateralized part (BRRD art. 44/2/b)",'T 03.01'!$F:$F,"c005x - Other financial corporations")+SUMIFS('T 04.00'!N:N,'T 04.00'!F:F,"c005x - Other financial corporations",'T 04.00'!E:E,"r0120 - Secured liabilities - collateralized part (BRRD art. 44/2/b)") -> 3.0229429e+09 | I11: =SUMIF('T 08.00'!$E:$E,"c006x - Insurance firms & pension funds",'T 08.00'!$O:$O)+SUMIFS('T 03.01'!P:P,'T 03.01'!E:E,"r0120 - Secured liabilities - collateralized part (BRRD art. 44/2/b)",'T 03.01'!$F:$F,"c006x - Insurance firms & pension funds")+SUMIFS('T 04.00'!N:N,'T 04.00'!F:F,"c006x - Insurance firms & pension funds",'T 04.00'!E:E,"r0120 - Secured liabilities - collateralized part (BRRD art. 44/2/b)") -> 0 | J11: =SUMIF('T 08.00'!$E:$E,"c008x - Government, central banks & supranationals",'T 08.00'!$O:$O)+SUMIFS('T 03.01'!P:P,'T 03.01'!E:E,"r0120 - Secured liabilities - collateralized part (BRRD art. 44/2/b)",'T 03.01'!$F:$F,"c008x - Government, central banks & supranationals")+SUMIFS('T 04.00'!N:N,'T 04.00'!F:F,"c008x - Government, central banks & supranationals",'T 04.00'!E:E,"r0120 - Secured liabilities - collateralized part (BRRD art. 44/2/b)") -> 7.410242e+09 | K11: 0 | L11: =SUMIF('T 08.00'!$E:$E,"",'T 08.00'!$O:$O)+SUMIFS('T 03.01'!P:P,'T 03.01'!E:E,"r0120 - Secured liabilities - collateralized part (BRRD art. 44/2/b)",'T 03.01'!$F:$F,"")+SUMIFS('T 04.00'!N:N,'T 04.00'!F:F,"",'T 04.00'!E:E,"r0120 - Secured liabilities - collateralized part (BRRD art. 44/2/b)") -> 0 | M11: =SUM(D11:L11)-I11 -> 1.2418317e+10 | N11: =+SUMIF('T 03.01'!E:E,"r0150 - Institution liabilities < 7 days (BRRD art. 44/2/e)",'T 03.01'!P:P) -> 0 | O11: 0
B12: Client liabilities, if protected in insolvency (BRRD art. 44/2/c) | C12: 0130 | D12: 0 | E12: 0 | F12: 0 | G12: 0 | H12: 0 | I12: 0 | J12: 0 | K12: 0 | L12: 0 | M12: =SUM(D12:L12)-I12 -> 0 | N12: 0 | O12: 0
B13: Fiduciary liabilities, if protected in insolvency (BRRD art. 44/2/d) | C13: 0140 | D13: 0 | E13: 0 | F13: 0 | G13: 0 | H13: 0 | I13: 0 | J13: 0 | K13: 0 | L13: 0 | M13: =SUM(D13:L13)-I13 -> 0 | N13: 0 | O13: 0
B14: Institution liabilities < 7 days (BRRD art. 44/2/e) | C14: 0150 | D14: =+SUMIFS('T 06.01'!$O:$O,'T 06.01'!$E:$E,"r0150 - Institution liabilities < 7 days (BRRD art. 44/2/e)",'T 06.01'!$F:$F,"c001x - Households")+SUMIFS('T 03.01'!P:P,'T 03.01'!E:E,"r0150 - Institution liabilities < 7 days (BRRD art. 44/2/e)",'T 03.01'!$F:$F,"c001x - Households") -> 0 | E14: =+SUMIFS('T 06.01'!$O:$O,'T 06.01'!$E:$E,"r0150 - Institution liabilities < 7 days (BRRD art. 44/2/e)",'T 06.01'!$F:$F,"c002x - Micro & SME")+SUMIFS('T 03.01'!P:P,'T 03.01'!E:E,"r0150 - Institution liabilities < 7 days (BRRD art. 44/2/e)",'T 03.01'!$F:$F,"c002x - Micro & SME") -> 0 | F14: =+SUMIFS('T 06.01'!$O:$O,'T 06.01'!$E:$E,"r0150 - Institution liabilities < 7 days (BRRD art. 44/2/e)",'T 06.01'!$F:$F,"c003x - Corporates")+SUMIFS('T 03.01'!P:P,'T 03.01'!E:E,"r0150 - Institution liabilities < 7 days (BRRD art. 44/2/e)",'T 03.01'!$F:$F,"c003x - Corporates") -> 0 | G14: =+SUMIFS('T 06.01'!$O:$O,'T 06.01'!$E:$E,"r0150 - Institution liabilities < 7 days (BRRD art. 44/2/e)",'T 06.01'!$F:$F,"c004x - Institutions")+SUMIFS('T 03.01'!P:P,'T 03.01'!E:E,"r0150 - Institution liabilities < 7 days (BRRD art. 44/2/e)",'T 03.01'!$F:$F,"c004x - Institutions") -> 1.5312813e+08 | H14: =+SUMIFS('T 06.01'!$O:$O,'T 06.01'!$E:$E,"r0150 - Institution liabilities < 7 days (BRRD art. 44/2/e)",'T 06.01'!$F:$F,"c005x - Other financial corporations")+I14+SUMIFS('T 03.01'!P:P,'T 03.01'!E:E,"r0150 - Institution liabilities < 7 days (BRRD art. 44/2/e)",'T 03.01'!$F:$F,"c005x - Other financial corporations") -> 0 | I14: =+SUMIFS('T 06.01'!$O:$O,'T 06.01'!$E:$E,"r0150 - Institution liabilities < 7 days (BRRD art. 44/2/e)",'T 06.01'!$F:$F,"c006x - Insurance firms & pension funds")+SUMIFS('T 03.01'!P:P,'T 03.01'!E:E,"r0150 - Institution liabilities < 7 days (BRRD art. 44/2/e)",'T 03.01'!$F:$F,"c006x - Insurance firms & pension funds") -> 0 | J14: =+SUMIFS('T 06.01'!$O:$O,'T 06.01'!$E:$E,"r0150 - Institution liabilities < 7 days (BRRD art. 44/2/e)",'T 06.01'!$F:$F,"c008x - Government, central banks & supranationals")+SUMIFS('T 03.01'!P:P,'T 03.01'!E:E,"r0150 - Institution liabilities < 7 days (BRRD art. 44/2/e)",'T 03.01'!$F:$F,"c008x - Government, central banks & supranationals") -> 0 | K14: 0 | L14: =+SUMIFS('T 06.01'!$O:$O,'T 06.01'!$E:$E,"r0150 - Institution liabilities < 7 days (BRRD art. 44/2/e)",'T 06.01'!$F:$F,"")+SUMIFS('T 03.01'!P:P,'T 03.01'!E:E,"r0150 - Institution liabilities < 7 days (BRRD art. 44/2/e)",'T 03.01'!$F:$F,"") -> 0 | M14: =SUM(D14:L14)-I14 -> 1.5312813e+08 | N14: =+SUMIF('T 03.01'!E:E,"r0150 - Institution liabilities < 7 days (BRRD art. 44/2/e)",'T 03.01'!P:P) -> 0 | O14: 0
B15: System (operator) and CCP liabilities < 7 days (BRRD art. 44/2/f) | C15: 0161 | D15: =+SUMIFS('T 06.01'!$O:$O,'T 06.01'!$E:$E,"r0161 - System (operator) and CCP liabilities < 7 days (BRRD art. 44/2/f)",'T 06.01'!$F:$F,"c001x - Households")+SUMIFS('T 03.01'!P:P,'T 03.01'!E:E,"r0161 - System (operator) and CCP liabilities < 7 days (BRRD art. 44/2/f)",'T 03.01'!$F:$F,"c001x - Households") -> 0 | E15: =+SUMIFS('T 06.01'!$O:$O,'T 06.01'!$E:$E,"r0161 - System (operator) and CCP liabilities < 7 days (BRRD art. 44/2/f)",'T 06.01'!$F:$F,"c002x - Micro & SME")+SUMIFS('T 03.01'!P:P,'T 03.01'!E:E,"r0161 - System (operator) and CCP liabilities < 7 days (BRRD art. 44/2/f)",'T 03.01'!$F:$F,"c002x - Micro & SME") -> 0 | F15: =+SUMIFS('T 06.01'!$O:$O,'T 06.01'!$E:$E,"r0161 - System (operator) and CCP liabilities < 7 days (BRRD art. 44/2/f)",'T 06.01'!$F:$F,"c003x - Corporates")+SUMIFS('T 03.01'!P:P,'T 03.01'!E:E,"r0161 - System (operator) and CCP liabilities < 7 days (BRRD art. 44/2/f)",'T 03.01'!$F:$F,"c003x - Corporates") -> 0 | G15: =+SUMIFS('T 06.01'!$O:$O,'T 06.01'!$E:$E,"r0161 - System (operator) and CCP liabilities < 7 days (BRRD art. 44/2/f)",'T 06.01'!$F:$F,"c004x - Institutions")+SUMIFS('T 03.01'!P:P,'T 03.01'!E:E,"r0161 - System (operator) and CCP liabilities < 7 days (BRRD art. 44/2/f)",'T 03.01'!$F:$F,"c004x - Institutions") -> 40810.25 | H15: =+SUMIFS('T 06.01'!$O:$O,'T 06.01'!$E:$E,"r0161 - System (operator) and CCP liabilities < 7 days (BRRD art. 44/2/f)",'T 06.01'!$F:$F,"c005x - Other financial corporations")+I15+SUMIFS('T 03.01'!P:P,'T 03.01'!E:E,"r0161 - System (operator) and CCP liabilities < 7 days (BRRD art. 44/2/f)",'T 03.01'!$F:$F,"c005x - Other financial corporations") -> 0 | I15: =+SUMIFS('T 06.01'!$O:$O,'T 06.01'!$E:$E,"r0161 - System (operator) and CCP liabilities < 7 days (BRRD art. 44/2/f)",'T 06.01'!$F:$F,"c006x - Insurance firms & pension funds")+SUMIFS('T 03.01'!P:P,'T 03.01'!E:E,"r0161 - System (operator) and CCP liabilities < 7 days (BRRD art. 44/2/f)",'T 03.01'!$F:$F,"c006x - Insurance firms & pension funds") -> 0 | J15: =+SUMIFS('T 06.01'!$O:$O,'T 06.01'!$E:$E,"r0161 - System (operator) and CCP liabilities < 7 days (BRRD art. 44/2/f)",'T 06.01'!$F:$F,"c008x - Government, central banks & supranationals")+SUMIFS('T 03.01'!P:P,'T 03.01'!E:E,"r0161 - System (operator) and CCP liabilities < 7 days (BRRD art. 44/2/f)",'T 03.01'!$F:$F,"c008x - Government, central banks & supranationals") -> 0 | K15: 0 | L15: =+SUMIFS('T 06.01'!$O:$O,'T 06.01'!$E:$E,"r0161 - System (operator) and CCP liabilities < 7 days (BRRD art. 44/2/f)",'T 06.01'!$F:$F,"")+SUMIFS('T 03.01'!P:P,'T 03.01'!E:E,"r0161 - System (operator) and CCP liabilities < 7 days (BRRD art. 44/2/f)",'T 03.01'!$F:$F,"") -> 0 | M15: =SUM(D15:L15)-I15 -> 40810.25 | N15: =+SUMIF('T 03.01'!E:E,"r0161 - System (operator) and CCP liabilities < 7 days (BRRD art. 44/2/f)",'T 03.01'!P:P) -> 0 | O15: 0
B16: Employee liabilities (BRRD art. 44/2/g/i) | C16: 0170 | D16: =+SUMIFS('T 09.00'!$M:$M,'T 09.00'!$E:$E,"r0170 - Employee liabilities (BRRD art. 44/2/g/i)",'T 09.00'!$F:$F,"c001x - Households")+SUMIFS('T 03.01'!P:P,'T 03.01'!E:E,"r0170 - Employee liabilities (BRRD art. 44/2/g/i)",'T 03.01'!$F:$F,"c001x - Households") -> 2.3292511e+08 | E16: =+SUMIFS('T 09.00'!$M:$M,'T 09.00'!$E:$E,"r0170 - Employee liabilities (BRRD art. 44/2/g/i)",'T 09.00'!$F:$F,"c002x - Micro & SME")+SUMIFS('T 03.01'!P:P,'T 03.01'!E:E,"r0170 - Employee liabilities (BRRD art. 44/2/g/i)",'T 03.01'!$F:$F,"c002x - Micro & SME") -> 0 | F16: =+SUMIFS('T 09.00'!$M:$M,'T 09.00'!$E:$E,"r0170 - Employee liabilities (BRRD art. 44/2/g/i)",'T 09.00'!$F:$F,"c003x - Corporates")+SUMIFS('T 03.01'!P:P,'T 03.01'!E:E,"r0170 - Employee liabilities (BRRD art. 44/2/g/i)",'T 03.01'!$F:$F,"c003x - Corporates") -> 0 | G16: =+SUMIFS('T 09.00'!$M:$M,'T 09.00'!$E:$E,"r0170 - Employee liabilities (BRRD art. 44/2/g/i)",'T 09.00'!$F:$F,"c004x - Institutions")+SUMIFS('T 03.01'!P:P,'T 03.01'!E:E,"r0170 - Employee liabilities (BRRD art. 44/2/g/i)",'T 03.01'!$F:$F,"c004x - Institutions") -> 0 | H16: =+SUMIFS('T 09.00'!$M:$M,'T 09.00'!$E:$E,"r0170 - Employee liabilities (BRRD art. 44/2/g/i)",'T 09.00'!$F:$F,"c005x - Other financial corporations")+I16+SUMIFS('T 03.01'!P:P,'T 03.01'!E:E,"r0170 - Employee liabilities (BRRD art. 44/2/g/i)",'T 03.01'!$F:$F,"c005x - Other financial corporations") -> 0 | I16: =+SUMIFS('T 09.00'!$M:$M,'T 09.00'!$E:$E,"r0170 - Employee liabilities (BRRD art. 44/2/g/i)",'T 09.00'!$F:$F,"c006x - Insurance firms & pension funds")+SUMIFS('T 03.01'!P:P,'T 03.01'!E:E,"r0170 - Employee liabilities (BRRD art. 44/2/g/i)",'T 03.01'!$F:$F,"c006x - Insurance firms & pension funds") -> 0 | J16: =+SUMIFS('T 09.00'!$M:$M,'T 09.00'!$E:$E,"r0170 - Employee liabilities (BRRD art. 44/2/g/i)",'T 09.00'!$F:$F,"c008x - Government, central banks & supranationals")+SUMIFS('T 03.01'!P:P,'T 03.01'!E:E,"r0170 - Employee liabilities (BRRD art. 44/2/g/i)",'T 03.01'!$F:$F,"c008x - Government, central banks & supranationals") -> 0 | K16: 0 | L16: =+SUMIFS('T 09.00'!$M:$M,'T 09.00'!$E:$E,"r0170 - Employee liabilities (BRRD art. 44/2/g/i)",'T 09.00'!$F:$F,"c010x - Non-identified, not listed on an exchange platform")+SUMIFS('T 03.01'!P:P,'T 03.01'!E:E,"r0170 - Employee liabilities (BRRD art. 44/2/g/i)",'T 03.01'!$F:$F,"") -> 0 | M16: =SUM(D16:L16)-I16 -> 2.3292511e+08 | N16: =+SUMIF('T 03.01'!E:E,"r0170 - Employee liabilities (BRRD art. 44/2/g/i)",'T 03.01'!P:P) -> 0 | O16: 0
B17: Critical service liabilities (BRRD art. 44/2/g/ii) | C17: 0180 | D17: =+SUMIFS('T 06.01'!$O:$O,'T 06.01'!$E:$E,"r0180 - Critical service liabilities (BRRD art. 44/2/g/ii)",'T 06.01'!$F:$F,"c001x - Households")+SUMIFS('T 03.01'!P:P,'T 03.01'!E:E,"r0180 - Critical service liabilities (BRRD art. 44/2/g/ii)",'T 03.01'!$F:$F,"c001x - Households") -> 4137337.4 | E17: =+SUMIFS('T 06.01'!$O:$O,'T 06.01'!$E:$E,"r0180 - Critical service liabilities (BRRD art. 44/2/g/ii)",'T 06.01'!$F:$F,"c002x - Micro & SME")+SUMIFS('T 03.01'!P:P,'T 03.01'!E:E,"r0180 - Critical service liabilities (BRRD art. 44/2/g/ii)",'T 03.01'!$F:$F,"c002x - Micro & SME") -> 0 | F17: =+SUMIFS('T 06.01'!$O:$O,'T 06.01'!$E:$E,"r0180 - Critical service liabilities (BRRD art. 44/2/g/ii)",'T 06.01'!$F:$F,"c003x - Corporates")+SUMIFS('T 03.01'!P:P,'T 03.01'!E:E,"r0180 - Critical service liabilities (BRRD art. 44/2/g/ii)",'T 03.01'!$F:$F,"c003x - Corporates") -> 0 | G17: =+SUMIFS('T 06.01'!$O:$O,'T 06.01'!$E:$E,"r0180 - Critical service liabilities (BRRD art. 44/2/g/ii)",'T 06.01'!$F:$F,"c004x - Institutions")+SUMIFS('T 03.01'!P:P,'T 03.01'!E:E,"r0180 - Critical service liabilities (BRRD art. 44/2/g/ii)",'T 03.01'!$F:$F,"c004x - Institutions") -> 0 | H17: =+SUMIFS('T 06.01'!$O:$O,'T 06.01'!$E:$E,"r0180 - Critical service liabilities (BRRD art. 44/2/g/ii)",'T 06.01'!$F:$F,"c005x - Other financial corporations")+I17+SUMIFS('T 03.01'!P:P,'T 03.01'!E:E,"r0180 - Critical service liabilities (BRRD art. 44/2/g/ii)",'T 03.01'!$F:$F,"c005x - Other financial corporations") -> 0 | I17: =+SUMIFS('T 06.01'!$O:$O,'T 06.01'!$E:$E,"r0180 - Critical service liabilities (BRRD art. 44/2/g/ii)",'T 06.01'!$F:$F,"c006x - Insurance firms & pension funds")+SUMIFS('T 03.01'!P:P,'T 03.01'!E:E,"r0180 - Critical service liabilities (BRRD art. 44/2/g/ii)",'T 03.01'!$F:$F,"c006x - Insurance firms & pension funds") -> 0 | J17: =+SUMIFS('T 06.01'!$O:$O,'T 06.01'!$E:$E,"r0180 - Critical service liabilities (BRRD art. 44/2/g/ii)",'T 06.01'!$F:$F,"c008x - Government, central banks & supranationals")+SUMIFS('T 03.01'!P:P,'T 03.01'!E:E,"r0180 - Critical service liabilities (BRRD art. 44/2/g/ii)",'T 03.01'!$F:$F,"c008x - Government, central banks & supranationals") -> 0 | K17: 0 | L17: =+SUMIFS('T 06.01'!$O:$O,'T 06.01'!$E:$E,"r0180 - Critical service liabilities (BRRD art. 44/2/g/ii)",'T 06.01'!$F:$F,"")+SUMIFS('T 03.01'!P:P,'T 03.01'!E:E,"r0180 - Critical service liabilities (BRRD art. 44/2/g/ii)",'T 03.01'!$F:$F,"") -> 0 | M17: =SUM(D17:L17)-I17 -> 4137337.4 | N17: =+SUMIF('T 03.01'!E:E,"r0180 - Critical service liabilities (BRRD art. 44/2/g/ii)",'T 03.01'!P:P) -> 0 | O17: 0
B18: Tax and social security authorities liabilities, if preferred (BRRD art. 44/2/g/iii) | C18: 0190 | D18: =+SUMIFS('T 06.01'!$O:$O,'T 06.01'!$E:$E,"r0190 - Tax and social security authorities liabilities, if preferred (BRRD art. 44/2/g/iii)",'T 06.01'!$F:$F,"c001x - Households")+SUMIFS('T 03.01'!P:P,'T 03.01'!E:E,"r0190 - Tax and social security authorities liabilities, if preferred (BRRD art. 44/2/g/iii)",'T 03.01'!$F:$F,"c001x - Households") -> 0 | E18: =+SUMIFS('T 06.01'!$O:$O,'T 06.01'!$E:$E,"r0190 - Tax and social security authorities liabilities, if preferred (BRRD art. 44/2/g/iii)",'T 06.01'!$F:$F,"c002x - Micro & SME")+SUMIFS('T 03.01'!P:P,'T 03.01'!E:E,"r0190 - Tax and social security authorities liabilities, if preferred (BRRD art. 44/2/g/iii)",'T 03.01'!$F:$F,"c002x - Micro & SME") -> 0 | F18: =+SUMIFS('T 06.01'!$O:$O,'T 06.01'!$E:$E,"r0190 - Tax and social security authorities liabilities, if preferred (BRRD art. 44/2/g/iii)",'T 06.01'!$F:$F,"c003x - Corporates")+SUMIFS('T 03.01'!P:P,'T 03.01'!E:E,"r0190 - Tax and social security authorities liabilities, if preferred (BRRD art. 44/2/g/iii)",'T 03.01'!$F:$F,"c003x - Corporates") -> 0 | G18: =+SUMIFS('T 06.01'!$O:$O,'T 06.01'!$E:$E,"r0190 - Tax and social security authorities liabilities, if preferred (BRRD art. 44/2/g/iii)",'T 06.01'!$F:$F,"c004x - Institutions")+SUMIFS('T 03.01'!P:P,'T 03.01'!E:E,"r0190 - Tax and social security authorities liabilities, if preferred (BRRD art. 44/2/g/iii)",'T 03.01'!$F:$F,"c004x - Institutions") -> 0 | H18: =+SUMIFS('T 06.01'!$O:$O,'T 06.01'!$E:$E,"r0190 - Tax and social security authorities liabilities, if preferred (BRRD art. 44/2/g/iii)",'T 06.01'!$F:$F,"c005x - Other financial corporations")+I18+SUMIFS('T 03.01'!P:P,'T 03.01'!E:E,"r0190 - Tax and social security authorities liabilities, if preferred (BRRD art. 44/2/g/iii)",'T 03.01'!$F:$F,"c005x - Other financial corporations") -> 0 | I18: =+SUMIFS('T 06.01'!$O:$O,'T 06.01'!$E:$E,"r0190 - Tax and social security authorities liabilities, if preferred (BRRD art. 44/2/g/iii)",'T 06.01'!$F:$F,"c006x - Insurance firms & pension funds")+SUMIFS('T 03.01'!P:P,'T 03.01'!E:E,"r0190 - Tax and social security authorities liabilities, if preferred (BRRD art. 44/2/g/iii)",'T 03.01'!$F:$F,"c006x - Insurance firms & pension funds") -> 0 | J18: =+SUMIFS('T 06.01'!$O:$O,'T 06.01'!$E:$E,"r0190 - Tax and social security authorities liabilities, if preferred (BRRD art. 44/2/g/iii)",'T 06.01'!$F:$F,"c008x - Government, central banks & supranationals")+SUMIFS('T 03.01'!P:P,'T 03.01'!E:E,"r0190 - Tax and social security authorities liabilities, if preferred (BRRD art. 44/2/g/iii)",'T 03.01'!$F:$F,"c008x - Government, central banks & supranationals") -> 3.5330907e+08 | K18: 0 | L18: =+SUMIFS('T 06.01'!$O:$O,'T 06.01'!$E:$E,"r0190 - Tax and social security authorities liabilities, if preferred (BRRD art. 44/2/g/iii)",'T 06.01'!$F:$F,"")+SUMIFS('T 03.01'!P:P,'T 03.01'!E:E,"r0190 - Tax and social security authorities liabilities, if preferred (BRRD art. 44/2/g/iii)",'T 03.01'!$F:$F,"") -> 0 | M18: =SUM(D18:L18)-I18 -> 3.5330907e+08 | N18: =+SUMIF('T 03.01'!E:E,"r0190 - Tax and social security authorities liabilities, if preferred (BRRD art. 44/2/g/iii)",'T 03.01'!P:P) -> 0 | O18: 0
B19: DGS liabilities (BRRD art. 44/2/g/iv) | C19: 0200 | D19: 0 | E19: 0 | F19: 0 | G19: 0 | H19: 0 | I19: 0 | J19: 0 | K19: 0 | L19: 0 | M19: =SUM(D19:L19)-I19 -> 0 | N19: 0 | O19: 0
B20: Liabilities towards other entities of the resolution group (BRRD art. 44/2/h) | C20: 0210 | D20: 0 | E20: 0 | F20: 0 | G20: =SUMIFS('T 03.01'!P:P,'T 03.01'!E:E,"r0210 - Liabilities towards other entities of the resolution group (BRRD art. 44/2/h)",'T 03.01'!$F:$F,"c004x - Institutions") -> 855362.17 | H20: =I20+SUMIFS('T 03.01'!P:P,'T 03.01'!E:E,"r0210 - Liabilities towards other entities of the resolution group (BRRD art. 44/2/h)",'T 03.01'!$F:$F,"c005x - Other financial corporations") -> 9.0199753e+08 | I20: =SUMIFS('T 03.01'!P:P,'T 03.01'!E:E,"r0210 - Liabilities towards other entities of the resolution group (BRRD art. 44/2/h)",'T 03.01'!$F:$F,"c006x - Insurance firms & pension funds") -> 3.0305582e+08 | J20: 0 | K20: 0 | L20: 0 | M20: =SUM(D20:L20)-I20 -> 9.0285289e+08 | N20: =+SUMIF('T 03.01'!E:E,"r0210 - Liabilities towards other entities of the resolution group (BRRD art. 44/2/h)",'T 03.01'!P:P) -> 9.0285289e+08 | O20: 0
B21: Liabilities not excluded from bail-in | C21: 0300 | D21: =+D22+D27+D32+D37+D42+D47+D57+D62+D65+D66 -> 5.3969556e+09 | E21: =+E22+E27+E32+E37+E42+E47+E57+E62+E65+E66 -> 4.8401961e+09 | F21: =+F22+F27+F32+F37+F42+F47+F57+F62+F65+F66 -> 4.3864769e+09 | G21: =+G22+G27+G32+G37+G42+G47+G57+G62+G65+G66 -> 1.0528835e+09 | H21: =+H22+H27+H32+H37+H42+H47+H57+H62+H65+H66 -> 1.5737242e+09 | I21: =+I22+I27+I32+I37+I42+I47+I57+I62+I65+I66 -> 1.1153964e+09 | J21: =+J22+J27+J32+J37+J42+J47+J57+J62+J65+J66 -> 9.0433897e+08 | K21: =+K22+K27+K32+K37+K42+K47+K57+K62+K65+K66 -> 0 | L21: =+L22+L27+L32+L37+L42+L47+L57+L62+L65+L66 -> 3.1330474e+08 | M21: =SUM(D21:L21)-I21 -> 1.846788e+10 | N21: =+N22+N27+N32+N37+N42+N47+N57+N62+N65+N66 -> 8.8703414e+08 | O21: 0
B22: Deposits, not covered but preferential (BRRD art. 108) | C22: 0310 | D22: =SUM(D23:D26) -> 5.3324587e+09 | E22: =SUM(E23:E26) -> 4.8008204e+09 | F22: =SUM(F23:F26) -> 0 | G22: =SUM(G23:G26) -> 0 | H22: =SUM(H23:H26) -> 0 | I22: =SUM(I23:I26) -> 0 | J22: =SUM(J23:J26) -> 0 | K22: =SUM(K23:K26) -> 0 | L22: =SUM(L23:L26) -> 0 | M22: =SUM(D22:L22)-I23 -> 1.0133279e+10 | N22: =SUM(N23:N26) -> 0 | O22: 0
B23: o/w residual maturity <= 1 month | C23: 0311 | D23: =+SUMIFS('T 05.01'!$M:$M,'T 05.01'!$E:$E,"r0310 - Deposits, not covered but preferential (BRRD art. 108)",'T 05.01'!$F:$F,"c001x - Households")+SUMIFS('T 03.01'!P:P,'T 03.01'!E:E,"r0310 - Deposits, not covered but preferential (BRRD art. 108)",'T 03.01'!$F:$F,"c001x - Households") -> 5.3324587e+09 | E23: =+SUMIFS('T 05.01'!$M:$M,'T 05.01'!$E:$E,"r0310 - Deposits, not covered but preferential (BRRD art. 108)",'T 05.01'!$F:$F,"c002x - Micro & SME")+SUMIFS('T 03.01'!P:P,'T 03.01'!E:E,"r0310 - Deposits, not covered but preferential (BRRD art. 108)",'T 03.01'!$F:$F,"c002x - Micro & SME") -> 4.8008204e+09 | F23: =+SUMIFS('T 05.01'!$M:$M,'T 05.01'!$E:$E,"r0310 - Deposits, not covered but preferential (BRRD art. 108)",'T 05.01'!$F:$F,"c003x - Corporates")+SUMIFS('T 03.01'!P:P,'T 03.01'!E:E,"r0310 - Deposits, not covered but preferential (BRRD art. 108)",'T 03.01'!$F:$F,"c003x - Corporates") -> 0 | G23: =+SUMIFS('T 05.01'!$M:$M,'T 05.01'!$E:$E,"r0310 - Deposits, not covered but preferential (BRRD art. 108)",'T 05.01'!$F:$F,"c004x - Institutions")+SUMIFS('T 03.01'!P:P,'T 03.01'!E:E,"r0310 - Deposits, not covered but preferential (BRRD art. 108)",'T 03.01'!$F:$F,"c004x - Institutions") -> 0 | H23: =+SUMIFS('T 05.01'!$M:$M,'T 05.01'!$E:$E,"r0310 - Deposits, not covered but preferential (BRRD art. 108)",'T 05.01'!$F:$F,"c005x - Other financial corporations")+I23+SUMIFS('T 03.01'!P:P,'T 03.01'!E:E,"r0310 - Deposits, not covered but preferential (BRRD art. 108)",'T 03.01'!$F:$F,"c005x - Other financial corporations") -> 0 | I23: =+SUMIFS('T 05.01'!$M:$M,'T 05.01'!$E:$E,"r0310 - Deposits, not covered but preferential (BRRD art. 108)",'T 05.01'!$F:$F,"c006x - Insurance firms & pension funds")+SUMIFS('T 03.01'!P:P,'T 03.01'!E:E,"r0310 - Deposits, not covered but preferential (BRRD art. 108)",'T 03.01'!$F:$F,"c006x - Insurance firms & pension funds") -> 0 | J23: =+SUMIFS('T 05.01'!$M:$M,'T 05.01'!$E:$E,"r0310 - Deposits, not covered but preferential (BRRD art. 108)",'T 05.01'!$F:$F,"c008x - Government, central banks & supranationals")+SUMIFS('T 03.01'!P:P,'T 03.01'!E:E,"r0310 - Deposits, not covered but preferential (BRRD art. 108)",'T 03.01'!$F:$F,"c008x - Government, central banks & supranationals") -> 0 | K23: 0 | L23: =+SUMIFS('T 05.01'!$M:$M,'T 05.01'!$E:$E,"r0310 - Deposits, not covered but preferential (BRRD art. 108)",'T 05.01'!$F:$F,"")+SUMIFS('T 03.01'!P:P,'T 03.01'!E:E,"r0310 - Deposits, not covered but preferential (BRRD art. 108)",'T 03.01'!$F:$F,"") -> 0 | M23: =SUM(D23:L23)-I24 -> 1.0133279e+10 | N23: =+SUMIF('T 03.01'!E:E,"r0310 - Deposits, not covered but preferential (BRRD art. 108)",'T 03.01'!P:P) -> 0 | O23: 0
B24: o/w residual maturity > 1 month < 1 year | C24: 0312 | D24: 0 | E24: 0 | F24: 0 | G24: 0 | H24: 0 | I24: 0 | J24: 0 | K24: 0 | L24: 0 | M24: =SUM(D24:L24)-I24 -> 0 | N24: 0 | O24: 0
B25: o/w residual maturity >= 1 year and < 2 years | C25: 0313 | D25: 0 | E25: 0 | F25: 0 | G25: 0 | H25: 0 | I25: 0 | J25: 0 | K25: 0 | L25: 0 | M25: =SUM(D25:L25)-I25 -> 0 | N25: 0 | O25: 0
B26: o/w residual maturity >= 2 years | C26: 0314 | D26: 0 | E26: 0 | F26: 0 | G26: 0 | H26: 0 | I26: 0 | J26: 0 | K26: 0 | L26: 0 | M26: =SUM(D26:L26)-I26 -> 0 | N26: 0 | O26: 0
B27: Deposits, not covered and not preferential | C27: 0320 | D27: =SUM(D28:D31) -> 0 | E27: =SUM(E28:E31) -> 1834.98 | F27: =SUM(F28:F31) -> 4.3159708e+09 | G27: =SUM(G28:G31) -> 2.3697488e+08 | H27: =SUM(H28:H31) -> 1.2438125e+09 | I27: =SUM(I28:I31) -> 1.1108616e+09 | J27: =SUM(J28:J31) -> 8.8308299e+08 | K27: =SUM(K28:K31) -> 0 | L27: =SUM(L28:L31) -> 0 | M27: =SUM(D27:L27)-I27 -> 6.6798429e+09 | N27: =+SUMIF('T 03.01'!E:E,"r0320 - Deposits, not covered and not preferential",'T 03.01'!P:P)+SUMIF('T 03.01'!E:E,"r0320 - Deposits, not covered and not preferential",'T 03.01'!Q:Q) -> 1.8819345e+08 | O27: 0
B28: o/w residual maturity <= 1 month | C28: 0321 | D28: =+SUMIFS('T 05.01'!$M:$M,'T 05.01'!$E:$E,"r0320 - Deposits, not covered and not preferential",'T 05.01'!$F:$F,"c001x - Households")+SUMIFS('T 03.01'!P:P,'T 03.01'!E:E,"r0320 - Deposits, not covered and not preferential",'T 03.01'!$F:$F,"c001x - Households") -> 0 | E28: =+SUMIFS('T 05.01'!$M:$M,'T 05.01'!$E:$E,"r0320 - Deposits, not covered and not preferential",'T 05.01'!$F:$F,"c002x - Micro & SME")+SUMIFS('T 03.01'!P:P,'T 03.01'!E:E,"r0320 - Deposits, not covered and not preferential",'T 03.01'!$F:$F,"c002x - Micro & SME") -> 1834.98 | F28: =+SUMIFS('T 05.01'!$M:$M,'T 05.01'!$E:$E,"r0320 - Deposits, not covered and not preferential",'T 05.01'!$F:$F,"c003x - Corporates")+SUMIFS('T 03.01'!P:P,'T 03.01'!E:E,"r0320 - Deposits, not covered and not preferential",'T 03.01'!$F:$F,"c003x - Corporates") -> 4.3159708e+09 | G28: =+SUMIFS('T 05.01'!$M:$M,'T 05.01'!$E:$E,"r0320 - Deposits, not covered and not preferential",'T 05.01'!$F:$F,"c004x - Institutions")+SUMIFS('T 03.01'!P:P,'T 03.01'!E:E,"r0320 - Deposits, not covered and not preferential",'T 03.01'!$F:$F,"c004x - Institutions") -> 2.3697488e+08 | H28: =+SUMIFS('T 05.01'!$M:$M,'T 05.01'!$E:$E,"r0320 - Deposits, not covered and not preferential",'T 05.01'!$F:$F,"c005x - Other financial corporations")+I28+SUMIFS('T 03.01'!P:P,'T 03.01'!E:E,"r0320 - Deposits, not covered and not preferential",'T 03.01'!$F:$F,"c005x - Other financial corporations") -> 1.2438125e+09 | I28: =+SUMIFS('T 05.01'!$M:$M,'T 05.01'!$E:$E,"r0320 - Deposits, not covered and not preferential",'T 05.01'!$F:$F,"c006x - Insurance firms & pension funds")+SUMIFS('T 03.01'!P:P,'T 03.01'!E:E,"r0320 - Deposits, not covered and not preferential",'T 03.01'!$F:$F,"c006x - Insurance firms & pension funds") -> 1.1108616e+09 | J28: =+SUMIFS('T 05.01'!$M:$M,'T 05.01'!$E:$E,"r0320 - Deposits, not covered and not preferential",'T 05.01'!$F:$F,"c008x - Government, central banks & supranationals")+SUMIFS('T 03.01'!P:P,'T 03.01'!E:E,"r0320 - Deposits, not covered and not preferential",'T 03.01'!$F:$F,"c008x - Government, central banks & supranationals") -> 8.8308299e+08 | K28: 0 | L28: =+SUMIFS('T 05.01'!$M:$M,'T 05.01'!$E:$E,"r0320 - Deposits, not covered and not preferential",'T 05.01'!$F:$F,"")+SUMIFS('T 03.01'!P:P,'T 03.01'!E:E,"r0320 - Deposits, not covered and not preferential",'T 03.01'!$F:$F,"") -> 0 | M28: =SUM(D28:L28)-I28 -> 6.6798429e+09 | N28: =+SUMIF('T 03.01'!E:E,"r0320 - Deposits, not covered and not preferential",'T 03.01'!P:P) -> 1.9482184e+08 | O28: 0
B29: o/w residual maturity > 1 month < 1 year | C29: 0322 | D29: 0 | E29: 0 | F29: 0 | G29: 0 | H29: 0 | I29: 0 | J29: 0 | K29: 0 | L29: 0 | M29: =SUM(D29:L29)-I29 -> 0 | N29: 0 | O29: 0
B30: o/w residual maturity >= 1 year and < 2 years | C30: 0323 | D30: 0 | E30: 0 | F30: 0 | G30: 0 | H30: 0 | I30: 0 | J30: 0 | K30: 0 | L30: 0 | M30: =SUM(D30:L30)-I30 -> 0 | N30: 0 | O30: 0
B31: o/w residual maturity >= 2 years | C31: 0324 | D31: 0 | E31: 0 | F31: 0 | G31: 0 | H31: 0 | I31: 0 | J31: 0 | K31: 0 | L31: 0 | M31: =SUM(D31:L31)-I31 -> 0 | N31: 0 | O31: 0
B32: Balance sheet liabilities arising from derivatives | C32: 0330 | D32: =SUMIF('T 07.00'!$E:$E,"c001x - Households",'T 07.00'!$R:$R) -> 0 | E32: =SUMIF('T 07.00'!$E:$E,"c002x - Micro & SME",'T 07.00'!$R:$R) -> 146937.32 | F32: =SUMIF('T 07.00'!$E:$E,"c003x - Corporates",'T 07.00'!$R:$R) -> 5065106.2 | G32: =SUMIF('T 07.00'!$E:$E,"c004x - Institutions",'T 07.00'!$R:$R) -> 6.1245005e+08 | H32: =SUMIF('T 07.00'!$E:$E,"c005x - Other financial corporations",'T 07.00'!$R:$R)+I32 -> 2.8177616e+08 | I32: =SUMIF('T 07.00'!$E:$E,"c006x - Insurance firms & pension funds",'T 07.00'!$R:$R) -> 0 | J32: =SUMIF('T 07.00'!$E:$E,"c008x - Government, central banks & supranationals",'T 07.00'!$R:$R) -> 0 | K32: 0 | L32: =SUMIF('T 07.00'!$E:$E,"",'T 07.00'!$R:$R) -> 0 | M32: =SUM(D32:L32)-I32 -> 8.9943825e+08 | N32: =SUMIF('T 07.00'!$O:$O,"TRUE",'T 07.00'!$R:$R) -> 6.406435e+08 | O32: 0
B33: Sum of net liability positions taking into account contractual netting sets, after mark-to-market adjustments, prior to collateral offset | C33: 0331 | D33: =SUMIF('T 07.00'!$E:$E,"c001x - Households",'T 07.00'!$R:$R) -> 0 | E33: =SUMIF('T 07.00'!$E:$E,"c002x - Micro & SME",'T 07.00'!$R:$R) -> 146937.32 | F33: =SUMIF('T 07.00'!$E:$E,"c003x - Corporates",'T 07.00'!$R:$R) -> 5065106.2 | G33: =SUMIF('T 07.00'!$E:$E,"c004x - Institutions",'T 07.00'!$R:$R) -> 6.1245005e+08 | H33: =SUMIF('T 07.00'!$E:$E,"c005x - Other financial corporations",'T 07.00'!$R:$R)+I33 -> 2.8177616e+08 | I33: =SUMIF('T 07.00'!$E:$E,"c006x - Insurance firms & pension funds",'T 07.00'!$R:$R) -> 0 | J33: =SUMIF('T 07.00'!$E:$E,"c008x - Government, central banks & supranationals",'T 07.00'!$R:$R) -> 0 | K33: 0 | L33: =SUMIF('T 07.00'!$E:$E,"",'T 07.00'!$R:$R) -> 0 | M33: =SUM(D33:L33)-I33 -> 8.9943825e+08 | N33: =SUMIF('T 07.00'!O:O,"TRUE",'T 07.00'!$R:$R) -> 6.406435e+08 | O33: 0
B34: Sum of net liability positions taking into account contractual netting sets, after mark-to-market adjustments, post collateral offset | C34: 0332 | D34: =SUMIF('T 07.00'!$E:$E,"c001x - Households",'T 07.00'!$R:$R) -> 0 | E34: =SUMIF('T 07.00'!$E:$E,"c002x - Micro & SME",'T 07.00'!$R:$R) -> 146937.32 | F34: =SUMIF('T 07.00'!$E:$E,"c003x - Corporates",'T 07.00'!$R:$R) -> 5065106.2 | G34: =SUMIF('T 07.00'!$E:$E,"c004x - Institutions",'T 07.00'!$R:$R) -> 6.1245005e+08 | H34: =SUMIF('T 07.00'!$E:$E,"c005x - Other financial corporations",'T 07.00'!$R:$R)+I34 -> 2.8177616e+08 | I34: =SUMIF('T 07.00'!$E:$E,"c006x - Insurance firms & pension funds",'T 07.00'!$R:$R) -> 0 | J34: =SUMIF('T 07.00'!$E:$E,"c008x - Government, central banks & supranationals",'T 07.00'!$R:$R) -> 0 | K34: 0 | L34: =SUMIF('T 07.00'!$E:$E,"",'T 07.00'!$R:$R) -> 0 | M34: =SUM(D34:L34)-I34 -> 8.9943825e+08 | N34: =SUMIF('T 07.00'!O:O,"TRUE",'T 07.00'!$R:$R) -> 6.406435e+08 | O34: 0
B35: Sum of net liability positions taking into account contractual netting sets, after mark-to-market adjustments, post collateral offset, incorporating estimated close-out amounts | C35: 0333 | D35: =SUMIF('T 07.00'!$E:$E,"c001x - Households",'T 07.00'!$R:$R) -> 0 | E35: =SUMIF('T 07.00'!$E:$E,"c002x - Micro & SME",'T 07.00'!$R:$R) -> 146937.32 | F35: =SUMIF('T 07.00'!$E:$E,"c003x - Corporates",'T 07.00'!$R:$R) -> 5065106.2 | G35: =SUMIF('T 07.00'!$E:$E,"c004x - Institutions",'T 07.00'!$R:$R) -> 6.1245005e+08 | H35: =SUMIF('T 07.00'!$E:$E,"c005x - Other financial corporations",'T 07.00'!$R:$R)+I35 -> 2.8177616e+08 | I35: =SUMIF('T 07.00'!$E:$E,"c006x - Insurance firms & pension funds",'T 07.00'!$R:$R) -> 0 | J35: =SUMIF('T 07.00'!$E:$E,"c008x - Government, central banks & supranationals",'T 07.00'!$R:$R) -> 0 | K35: 0 | L35: =SUMIF('T 07.00'!$E:$E,"",'T 07.00'!$R:$R) -> 0 | M35: =SUM(D35:L35)-I35 -> 8.9943825e+08 | N35: =SUMIF('T 07.00'!O:O,"TRUE",'T 07.00'!$R:$R) -> 6.406435e+08 | O35: 0
B36: Sum of net liability positions taking into account prudential netting rules | C36: 0334 | D36: =SUMIF('T 07.00'!$E:$E,"c001x - Households",'T 07.00'!$U:$U) -> 0 | E36: =SUMIF('T 07.00'!$E:$E,"c002x - Micro & SME",'T 07.00'!$U:$U) -> 146937.32 | F36: =SUMIF('T 07.00'!$E:$E,"c003x - Corporates",'T 07.00'!$U:$U) -> 5065106.3 | G36: =SUMIF('T 07.00'!$E:$E,"c004x - Institutions",'T 07.00'!$U:$U) -> 1.7284551e+08 | H36: =SUMIF('T 07.00'!$E:$E,"c005x - Other financial corporations",'T 07.00'!$U:$U)+I36 -> 36658488 | I36: =SUMIF('T 07.00'!$E:$E,"c006x - Insurance firms & pension funds",'T 07.00'!$U:$U) -> 0 | J36: =SUMIF('T 07.00'!$E:$E,"c008x - Government, central banks & supranationals",'T 07.00'!$U:$U) -> 0 | K36: 0 | L36: =SUMIF('T 07.00'!$E:$E,"",'T 07.00'!$U:$U) -> 0 | M36: =SUM(D36:L36)-I36 -> 2.1471605e+08 | N36: =SUMIF('T 07.00'!O:O,"TRUE",'T 07.00'!$U:$U) -> 2.0161074e+08 | O36: 0
B37: Uncollateralized secured liabilities | C37: 0340 | D37: 0 | E37: 0 | F37: 0 | G37: 0 | H37: 0 | I37: 0 | J37: 0 | K37: 0 | L37: 0 | M37: =SUM(D37:L37)-I37 -> 0 | N37: 0 | O37: 0
B38: o/w residual maturity <= 1 month | C38: 0341 | D38: 0 | E38: 0 | F38: 0 | G38: 0 | H38: 0 | I38: 0 | J38: 0 | K38: 0 | L38: 0 | M38: =SUM(D38:L38)-I38 -> 0 | N38: 0 | O38: 0
B39: o/w residual maturity > 1 month < 1 year | C39: 0342 | D39: 0 | E39: 0 | F39: 0 | G39: 0 | H39: 0 | I39: 0 | J39: 0 | K39: 0 | L39: 0 | M39: =SUM(D39:L39)-I39 -> 0 | N39: 0 | O39: 0
B40: o/w residual maturity >= 1 year and < 2 years | C40: 0343 | D40: 0 | E40: 0 | F40: 0 | G40: 0 | H40: 0 | I40: 0 | J40: 0 | K40: 0 | L40: 0 | M40: =SUM(D40:L40)-I40 -> 0 | N40: 0 | O40: 0
B41: o/w residual maturity >= 2 years | C41: 0344 | D41: 0 | E41: 0 | F41: 0 | G41: 0 | H41: 0 | I41: 0 | J41: 0 | K41: 0 | L41: 0 | M41: =SUM(D41:L41)-I41 -> 0 | N41: 0 | O41: 0
B42: Structured notes | C42: 0350 | D42: =SUM(D43:D46) -> 0 | E42: =SUM(E43:E46) -> 0 | F42: =SUM(F43:F46) -> 0 | G42: =SUM(G43:G46) -> 182884000 | H42: =SUM(H43:H46) -> 0 | I42: =SUM(I43:I46) -> 0 | J42: =SUM(J43:J46) -> 0 | K42: =SUM(K43:K46) -> 0 | L42: =SUM(L43:L46) -> 0 | M42: =SUM(D42:L42)-I42 -> 182884000 | N42: =SUM(N43:N46) -> 8209741.6 | O42: =SUM(O43:O46) -> 0
B43: o/w residual maturity <= 1 month | C43: 0351 | D43: =+SUMIFS('T 04.00'!$N:$N,'T 04.00'!$F:$F,"c001x - Households",'T 04.00'!$E:$E,"r0350 - Structured notes",'T 04.00'!AL:AL,1) -> 0 | E43: =+SUMIFS('T 04.00'!$N:$N,'T 04.00'!$F:$F,"c002x - Micro & SME",'T 04.00'!$E:$E,"r0350 - Structured notes",'T 04.00'!AL:AL,1) -> 0 | F43: =+SUMIFS('T 04.00'!$N:$N,'T 04.00'!$F:$F,"c003x - Corporates",'T 04.00'!$E:$E,"r0350 - Structured notes",'T 04.00'!AL:AL,1) -> 0 | G43: =+SUMIFS('T 04.00'!$N:$N,'T 04.00'!$F:$F,"c004x - Institutions",'T 04.00'!$E:$E,"r0350 - Structured notes",'T 04.00'!AL:AL,1) -> 0 | H43: =+SUMIFS('T 04.00'!$N:$N,'T 04.00'!$F:$F,"c005x - Other financial corporations",'T 04.00'!$E:$E,"r0350 - Structured notes",'T 04.00'!AL:AL,1) -> 0 | I43: =+SUMIFS('T 04.00'!$N:$N,'T 04.00'!$F:$F,"c006x - Insurance firms & pension funds",'T 04.00'!$E:$E,"r0350 - Structured notes",'T 04.00'!AL:AL,1) -> 0 | J43: =+SUMIFS('T 04.00'!$N:$N,'T 04.00'!$F:$F,"c008x - Government, central banks & supranationals",'T 04.00'!$E:$E,"r0350 - Structured notes",'T 04.00'!AL:AL,1) -> 0 | K43: 0 | L43: =+SUMIFS('T 04.00'!$N:$N,'T 04.00'!$F:$F,"",'T 04.00'!$E:$E,"r0350 - Structured notes",'T 04.00'!AL:AL,1) -> 0 | M43: =SUM(D43:L43)-I43 -> 0 | N43: =SUMIFS('T 03.01'!$P:$P,'T 03.01'!$E:$E,"r0350 - Structured notes",'T 03.01'!AC:AC,1) -> 0 | O43: 0
B44: o/w residual maturity > 1 month < 1 year | C44: 0352 | D44: =+SUMIFS('T 04.00'!$N:$N,'T 04.00'!$F:$F,"c001x - Households",'T 04.00'!$E:$E,"r0350 - Structured notes",'T 04.00'!AL:AL,2) -> 0 | E44: =+SUMIFS('T 04.00'!$N:$N,'T 04.00'!$F:$F,"c002x - Micro & SME",'T 04.00'!$E:$E,"r0350 - Structured notes",'T 04.00'!AL:AL,2) -> 0 | F44: =+SUMIFS('T 04.00'!$N:$N,'T 04.00'!$F:$F,"c003x - Corporates",'T 04.00'!$E:$E,"r0350 - Structured notes",'T 04.00'!AL:AL,2) -> 0 | G44: =+SUMIFS('T 04.00'!$N:$N,'T 04.00'!$F:$F,"c004x - Institutions",'T 04.00'!$E:$E,"r0350 - Structured notes",'T 04.00'!AL:AL,2) -> 0 | H44: =+SUMIFS('T 04.00'!$N:$N,'T 04.00'!$F:$F,"c005x - Other financial corporations",'T 04.00'!$E:$E,"r0350 - Structured notes",'T 04.00'!AL:AL,2) -> 0 | I44: =+SUMIFS('T 04.00'!$N:$N,'T 04.00'!$F:$F,"c006x - Insurance firms & pension funds",'T 04.00'!$E:$E,"r0350 - Structured notes",'T 04.00'!AL:AL,2) -> 0 | J44: =+SUMIFS('T 04.00'!$N:$N,'T 04.00'!$F:$F,"c008x - Government, central banks & supranationals",'T 04.00'!$E:$E,"r0350 - Structured notes",'T 04.00'!AL:AL,2) -> 0 | K44: 0 | L44: =+SUMIFS('T 04.00'!$N:$N,'T 04.00'!$F:$F,"",'T 04.00'!$E:$E,"r0350 - Structured notes",'T 04.00'!AL:AL,2) -> 0 | M44: =SUM(D44:L44)-I44 -> 0 | N44: =SUMIFS('T 03.01'!$P:$P,'T 03.01'!$E:$E,"r0350 - Structured notes",'T 03.01'!AC:AC,2) -> 0 | O44: 0
B45: o/w residual maturity >= 1 year and < 2 years | C45: 0353 | D45: =+SUMIFS('T 04.00'!$N:$N,'T 04.00'!$F:$F,"c001x - Households",'T 04.00'!$E:$E,"r0350 - Structured notes",'T 04.00'!AL:AL,3) -> 0 | E45: =+SUMIFS('T 04.00'!$N:$N,'T 04.00'!$F:$F,"c002x - Micro & SME",'T 04.00'!$E:$E,"r0350 - Structured notes",'T 04.00'!AL:AL,3) -> 0 | F45: =+SUMIFS('T 04.00'!$N:$N,'T 04.00'!$F:$F,"c003x - Corporates",'T 04.00'!$E:$E,"r0350 - Structured notes",'T 04.00'!AL:AL,3) -> 0 | G45: =+SUMIFS('T 04.00'!$N:$N,'T 04.00'!$F:$F,"c004x - Institutions",'T 04.00'!$E:$E,"r0350 - Structured notes",'T 04.00'!AL:AL,3) -> 0 | H45: =+SUMIFS('T 04.00'!$N:$N,'T 04.00'!$F:$F,"c005x - Other financial corporations",'T 04.00'!$E:$E,"r0350 - Structured notes",'T 04.00'!AL:AL,3) -> 0 | I45: =+SUMIFS('T 04.00'!$N:$N,'T 04.00'!$F:$F,"c006x - Insurance firms & pension funds",'T 04.00'!$E:$E,"r0350 - Structured notes",'T 04.00'!AL:AL,3) -> 0 | J45: =+SUMIFS('T 04.00'!$N:$N,'T 04.00'!$F:$F,"c008x - Government, central banks & supranationals",'T 04.00'!$E:$E,"r0350 - Structured notes",'T 04.00'!AL:AL,3) -> 0 | K45: 0 | L45: =+SUMIFS('T 04.00'!$N:$N,'T 04.00'!$F:$F,"",'T 04.00'!$E:$E,"r0350 - Structured notes",'T 04.00'!AL:AL,3) -> 0 | M45: =SUM(D45:L45)-I45 -> 0 | N45: =SUMIFS('T 03.01'!$P:$P,'T 03.01'!$E:$E,"r0350 - Structured notes",'T 03.01'!AC:AC,3) -> 0 | O45: 0
B46: o/w residual maturity >= 2 years | C46: 0354 | D46: =+SUMIFS('T 04.00'!$N:$N,'T 04.00'!$F:$F,"c001x - Households",'T 04.00'!$E:$E,"r0350 - Structured notes",'T 04.00'!AL:AL,4) -> 0 | E46: =+SUMIFS('T 04.00'!$N:$N,'T 04.00'!$F:$F,"c002x - Micro & SME",'T 04.00'!$E:$E,"r0350 - Structured notes",'T 04.00'!AL:AL,4) -> 0 | F46: =+SUMIFS('T 04.00'!$N:$N,'T 04.00'!$F:$F,"c003x - Corporates",'T 04.00'!$E:$E,"r0350 - Structured notes",'T 04.00'!AL:AL,4) -> 0 | G46: =+SUMIFS('T 04.00'!$N:$N,'T 04.00'!$F:$F,"c004x - Institutions",'T 04.00'!$E:$E,"r0350 - Structured notes",'T 04.00'!AL:AL,4) -> 182884000 | H46: =+SUMIFS('T 04.00'!$N:$N,'T 04.00'!$F:$F,"c005x - Other financial corporations",'T 04.00'!$E:$E,"r0350 - Structured notes",'T 04.00'!AL:AL,4) -> 0 | I46: =+SUMIFS('T 04.00'!$N:$N,'T 04.00'!$F:$F,"c006x - Insurance firms & pension funds",'T 04.00'!$E:$E,"r0350 - Structured notes",'T 04.00'!AL:AL,4) -> 0 | J46: =+SUMIFS('T 04.00'!$N:$N,'T 04.00'!$F:$F,"c008x - Government, central banks & supranationals",'T 04.00'!$E:$E,"r0350 - Structured notes",'T 04.00'!AL:AL,4) -> 0 | K46: 0 | L46: =+SUMIFS('T 04.00'!$N:$N,'T 04.00'!$F:$F,"",'T 04.00'!$E:$E,"r0350 - Structured notes",'T 04.00'!AL:AL,4) -> 0 | M46: =SUM(D46:L46)-I46 -> 182884000 | N46: =SUMIFS('T 03.01'!$P:$P,'T 03.01'!$E:$E,"r0350 - Structured notes",'T 03.01'!AC:AC,4) -> 8209741.6 | O46: 0
B47: Senior unsecured liabilities | C47: 0360 | D47: =+SUM(D48:D51) -> 0 | E47: 0 | F47: 0 | G47: 0 | H47: 0 | I47: 0 | J47: 0 | K47: 0 | L47: 0 | M47: =SUM(D47:L47)-I47 -> 0 | N47: =+SUM(N48:N51) -> 0 | O47: 0
B48: o/w residual maturity <= 1 month | C48: 0361 | D48: 0 | E48: 0 | F48: 0 | G48: 0 | H48: 0 | I48: 0 | J48: 0 | K48: 0 | L48: 0 | M48: =SUM(D48:L48)-I48 -> 0 | N48: 0 | O48: 0
B49: o/w residual maturity > 1 month < 1 year | C49: 0362 | D49: 0 | E49: 0 | F49: 0 | G49: 0 | H49: 0 | I49: 0 | J49: 0 | K49: 0 | L49: 0 | M49: =SUM(D49:L49)-I49 -> 0 | N49: 0 | O49: 0
B50: o/w residual maturity >= 1 year and < 2 years | C50: 0363 | D50: 0 | E50: 0 | F50: 0 | G50: 0 | H50: 0 | I50: 0 | J50: 0 | K50: 0 | L50: 0 | M50: =SUM(D50:L50)-I50 -> 0 | N50: 0 | O50: 0
B51: o/w residual maturity >= 2 years | C51: 0364 | D51: 0 | E51: 0 | F51: 0 | G51: 0 | H51: 0 | I51: 0 | J51: 0 | K51: 0 | L51: 0 | M51: =SUM(D51:L51)-I51 -> 0 | N51: 0 | O51: 0
B52: Senior non-preferred liabilities | C52: 0365 | D52: =+SUM(D53:D56) -> 0 | E52: 0 | F52: 0 | G52: 0 | H52: 0 | I52: 0 | J52: 0 | K52: 0 | L52: 0 | M52: =SUM(D52:L52)-I52 -> 0 | N52: 0 | O52: 0
B53: Of which: residual maturity <= 1 month | C53: 0366 | D53: 0 | E53: 0 | F53: 0 | G53: 0 | H53: 0 | I53: 0 | J53: 0 | K53: 0 | L53: 0 | M53: =SUM(D53:L53)-I53 -> 0 | N53: 0 | O53: 0
B54: Of which: residual maturity > 1 month < 1 year | C54: 0367 | D54: 0 | E54: 0 | F54: 0 | G54: 0 | H54: 0 | I54: 0 | J54: 0 | K54: 0 | L54: 0 | M54: =SUM(D54:L54)-I54 -> 0 | N54: 0 | O54: 0
B55: Of which: residual maturity >= 1 year and < 2 years | C55: 0368 | D55: 0 | E55: 0 | F55: 0 | G55: 0 | H55: 0 | I55: 0 | J55: 0 | K55: 0 | L55: 0 | M55: =SUM(D55:L55)-I55 -> 0 | N55: 0 | O55: 0
B56: Of which: residual maturity >= 2 years | C56: 0369 | D56: 0 | E56: 0 | F56: 0 | G56: 0 | H56: 0 | I56: 0 | J56: 0 | K56: 0 | L56: 0 | M56: =SUM(D56:L56)-I56 -> 0 | N56: 0 | O56: 0
B57: Subordinated liabilities (not recognised as own funds) | C57: 0370 | D57: =+SUM(D58:D61) -> 0 | E57: =+SUM(E58:E61) -> 0 | F57: =+SUM(F58:F61) -> 0 | G57: =+SUM(G58:G61) -> 0 | H57: =+SUM(H58:H61) -> 0 | I57: =+SUM(I58:I61) -> 0 | J57: =+SUM(J58:J61) -> 0 | K57: =+SUM(K58:K61) -> 0 | L57: =+SUM(L58:L61) -> 0 | M57: =SUM(D57:L57)-I57 -> 0 | N57: =+SUM(N58:N61) -> 0 | O57: 0
B58: o/w residual maturity <= 1 month | C58: 0371 | D58: =SUMIFS('T 03.01'!$P:$P,'T 03.01'!$F:$F,"c001x - Households",'T 03.01'!$E:$E,"r0370 - Subordinated liabilities (not recognised as own funds)",'T 03.01'!$AC:$AC,1) -> 0 | E58: =SUMIFS('T 03.01'!$P:$P,'T 03.01'!$F:$F,"c002x - Micro & SME",'T 03.01'!$E:$E,"r0370 - Subordinated liabilities (not recognised as own funds)",'T 03.01'!AC:AC,1) -> 0 | F58: =SUMIFS('T 03.01'!$P:$P,'T 03.01'!$F:$F,"c003x - Corporates",'T 03.01'!$E:$E,"r0370 - Subordinated liabilities (not recognised as own funds)",'T 03.01'!AC:AC,1) -> 0 | G58: =SUMIFS('T 03.01'!$P:$P,'T 03.01'!$F:$F,"c004x - Institutions",'T 03.01'!$E:$E,"r0370 - Subordinated liabilities (not recognised as own funds)",'T 03.01'!AC:AC,1) -> 0 | H58: =SUMIFS('T 03.01'!$P:$P,'T 03.01'!$F:$F,"c005x - Other financial corporations",'T 03.01'!$E:$E,"r0370 - Subordinated liabilities (not recognised as own funds)",'T 03.01'!AC:AC,1) -> 0 | I58: =SUMIFS('T 03.01'!$P:$P,'T 03.01'!$F:$F,"c006x - Insurance firms & pension funds",'T 03.01'!$E:$E,"r0370 - Subordinated liabilities (not recognised as own funds)",'T 03.01'!AC:AC,1) -> 0 | J58: =SUMIFS('T 03.01'!$P:$P,'T 03.01'!$F:$F,"c008x - Government, central banks & supranationals",'T 03.01'!$E:$E,"r0370 - Subordinated liabilities (not recognised as own funds)",'T 03.01'!AC:AC,1) -> 0 | K58: 0 | L58: =SUMIFS('T 03.01'!$P:$P,'T 03.01'!$F:$F,"",'T 03.01'!$E:$E,"r0370 - Subordinated liabilities (not recognised as own funds)",'T 03.01'!AC:AC,1) -> 0 | M58: =SUM(D58:L58)-I58 -> 0 | N58: =SUMIFS('T 03.01'!$P:$P,'T 03.01'!$E:$E,"r0370 - Subordinated liabilities (not recognised as own funds)",'T 03.01'!AC:AC,1) -> 0 | O58: 0
B59: o/w residual maturity > 1 month < 1 year | C59: 0372 | D59: =SUMIFS('T 03.01'!$P:$P,'T 03.01'!$F:$F,"c001x - Households",'T 03.01'!$E:$E,"r0370 - Subordinated liabilities (not recognised as own funds)",'T 03.01'!$AC:$AC,2) -> 0 | E59: =SUMIFS('T 03.01'!$P:$P,'T 03.01'!$F:$F,"c002x - Micro & SME",'T 03.01'!$E:$E,"r0370 - Subordinated liabilities (not recognised as own funds)",'T 03.01'!AC:AC,2) -> 0 | F59: =SUMIFS('T 03.01'!$P:$P,'T 03.01'!$F:$F,"c003x - Corporates",'T 03.01'!$E:$E,"r0370 - Subordinated liabilities (not recognised as own funds)",'T 03.01'!AC:AC,2) -> 0 | G59: =SUMIFS('T 03.01'!$P:$P,'T 03.01'!$F:$F,"c004x - Institutions",'T 03.01'!$E:$E,"r0370 - Subordinated liabilities (not recognised as own funds)",'T 03.01'!AC:AC,2) -> 0 | H59: =SUMIFS('T 03.01'!$P:$P,'T 03.01'!$F:$F,"c005x - Other financial corporations",'T 03.01'!$E:$E,"r0370 - Subordinated liabilities (not recognised as own funds)",'T 03.01'!AC:AC,2) -> 0 | I59: =SUMIFS('T 03.01'!$P:$P,'T 03.01'!$F:$F,"c006x - Insurance firms & pension funds",'T 03.01'!$E:$E,"r0370 - Subordinated liabilities (not recognised as own funds)",'T 03.01'!AC:AC,2) -> 0 | J59: =SUMIFS('T 03.01'!$P:$P,'T 03.01'!$F:$F,"c008x - Government, central banks & supranationals",'T 03.01'!$E:$E,"r0370 - Subordinated liabilities (not recognised as own funds)",'T 03.01'!AC:AC,2) -> 0 | K59: 0 | L59: =SUMIFS('T 03.01'!$P:$P,'T 03.01'!$F:$F,"",'T 03.01'!$E:$E,"r0370 - Subordinated liabilities (not recognised as own funds)",'T 03.01'!AC:AC,2) -> 0 | M59: =SUM(D59:L59)-I59 -> 0 | N59: =SUMIFS('T 03.01'!$P:$P,'T 03.01'!$E:$E,"r0370 - Subordinated liabilities (not recognised as own funds)",'T 03.01'!AC:AC,2) -> 0 | O59: 0
B60: o/w residual maturity >= 1 year and < 2 years | C60: 0373 | D60: =SUMIFS('T 03.01'!$P:$P,'T 03.01'!$F:$F,"c001x - Households",'T 03.01'!$E:$E,"r0370 - Subordinated liabilities (not recognised as own funds)",'T 03.01'!$AC:$AC,3) -> 0 | E60: =SUMIFS('T 03.01'!$P:$P,'T 03.01'!$F:$F,"c002x - Micro & SME",'T 03.01'!$E:$E,"r0370 - Subordinated liabilities (not recognised as own funds)",'T 03.01'!AC:AC,3) -> 0 | F60: =SUMIFS('T 03.01'!$P:$P,'T 03.01'!$F:$F,"c003x - Corporates",'T 03.01'!$E:$E,"r0370 - Subordinated liabilities (not recognised as own funds)",'T 03.01'!AC:AC,3) -> 0 | G60: =SUMIFS('T 03.01'!$P:$P,'T 03.01'!$F:$F,"c004x - Institutions",'T 03.01'!$E:$E,"r0370 - Subordinated liabilities (not recognised as own funds)",'T 03.01'!AC:AC,3) -> 0 | H60: =SUMIFS('T 03.01'!$P:$P,'T 03.01'!$F:$F,"c005x - Other financial corporations",'T 03.01'!$E:$E,"r0370 - Subordinated liabilities (not recognised as own funds)",'T 03.01'!AC:AC,3) -> 0 | I60: =SUMIFS('T 03.01'!$P:$P,'T 03.01'!$F:$F,"c006x - Insurance firms & pension funds",'T 03.01'!$E:$E,"r0370 - Subordinated liabilities (not recognised as own funds)",'T 03.01'!AC:AC,3) -> 0 | J60: =SUMIFS('T 03.01'!$P:$P,'T 03.01'!$F:$F,"c008x - Government, central banks & supranationals",'T 03.01'!$E:$E,"r0370 - Subordinated liabilities (not recognised as own funds)",'T 03.01'!AC:AC,3) -> 0 | K60: 0 | L60: =SUMIFS('T 03.01'!$P:$P,'T 03.01'!$F:$F,"",'T 03.01'!$E:$E,"r0370 - Subordinated liabilities (not recognised as own funds)",'T 03.01'!AC:AC,3) -> 0 | M60: =SUM(D60:L60)-I60 -> 0 | N60: =SUMIFS('T 03.01'!$P:$P,'T 03.01'!$E:$E,"r0370 - Subordinated liabilities (not recognised as own funds)",'T 03.01'!AC:AC,3) -> 0 | O60: 0
B61: o/w residual maturity >= 2 years | C61: 0374 | D61: =SUMIFS('T 03.01'!$P:$P,'T 03.01'!$F:$F,"c001x - Households",'T 03.01'!$E:$E,"r0370 - Subordinated liabilities (not recognised as own funds)",'T 03.01'!$AC:$AC,4) -> 0 | E61: =SUMIFS('T 03.01'!$P:$P,'T 03.01'!$F:$F,"c002x - Micro & SME",'T 03.01'!$E:$E,"r0370 - Subordinated liabilities (not recognised as own funds)",'T 03.01'!AC:AC,4) -> 0 | F61: =SUMIFS('T 03.01'!$P:$P,'T 03.01'!$F:$F,"c003x - Corporates",'T 03.01'!$E:$E,"r0370 - Subordinated liabilities (not recognised as own funds)",'T 03.01'!AC:AC,4) -> 0 | G61: =SUMIFS('T 03.01'!$P:$P,'T 03.01'!$F:$F,"c004x - Institutions",'T 03.01'!$E:$E,"r0370 - Subordinated liabilities (not recognised as own funds)",'T 03.01'!AC:AC,4) -> 0 | H61: =SUMIFS('T 03.01'!$P:$P,'T 03.01'!$F:$F,"c005x - Other financial corporations",'T 03.01'!$E:$E,"r0370 - Subordinated liabilities (not recognised as own funds)",'T 03.01'!AC:AC,4) -> 0 | I61: =SUMIFS('T 03.01'!$P:$P,'T 03.01'!$F:$F,"c006x - Insurance firms & pension funds",'T 03.01'!$E:$E,"r0370 - Subordinated liabilities (not recognised as own funds)",'T 03.01'!AC:AC,4) -> 0 | J61: =SUMIFS('T 03.01'!$P:$P,'T 03.01'!$F:$F,"c008x - Government, central banks & supranationals",'T 03.01'!$E:$E,"r0370 - Subordinated liabilities (not recognised as own funds)",'T 03.01'!AC:AC,4) -> 0 | K61: 0 | L61: =SUMIFS('T 03.01'!$P:$P,'T 03.01'!$F:$F,"",'T 03.01'!$E:$E,"r0370 - Subordinated liabilities (not recognised as own funds)",'T 03.01'!AC:AC,4) -> 0 | M61: =SUM(D61:L61)-I61 -> 0 | N61: =SUMIFS('T 03.01'!$P:$P,'T 03.01'!$E:$E,"r0370 - Subordinated liabilities (not recognised as own funds)",'T 03.01'!AC:AC,4) -> 0 | O61: 0
B62: Other MREL eligible liabilities | C62: 0380 | D62: 0 | E62: 0 | F62: 0 | G62: 0 | H62: 0 | I62: 0 | J62: 0 | K62: 0 | L62: 0 | M62: =SUM(D62:L62)-I62 -> 0 | N62: 0 | O62: 0
B63: o/w residual maturity >= 1 year and < 2 years | C63: 0381 | D63: 0 | E63: 0 | F63: 0 | G63: 0 | H63: 0 | I63: 0 | J63: 0 | K63: 0 | L63: 0 | M63: =SUM(D63:L63)-I63 -> 0 | N63: 0 | O63: 0
B64: o/w residual maturity >= 2 years | C64: 0382 | D64: 0 | E64: 0 | F64: 0 | G64: 0 | H64: 0 | I64: 0 | J64: 0 | K64: 0 | L64: 0 | M64: =SUM(D64:L64)-I64 -> 0 | N64: 0 | O64: 0
B65: Non-financial liabilities | C65: 0390 | D65: =+SUMIFS('T 09.00'!$M:$M,'T 09.00'!$E:$E,"r0390 - Non-financial liabilities",'T 09.00'!$F:$F,"c001x - Households")+SUMIFS('T 03.01'!P:P,'T 03.01'!E:E,"r0390 - Non-financial liabilities",'T 03.01'!$F:$F,"c001x - Households") -> 64496913 | E65: =+SUMIFS('T 09.00'!$M:$M,'T 09.00'!$E:$E,"r0390 - Non-financial liabilities",'T 09.00'!$F:$F,"c002x - Micro & SME")+SUMIFS('T 03.01'!P:P,'T 03.01'!E:E,"r0390 - Non-financial liabilities",'T 03.01'!$F:$F,"c002x - Micro & SME") -> 39226891 | F65: =+SUMIFS('T 09.00'!$M:$M,'T 09.00'!$E:$E,"r0390 - Non-financial liabilities",'T 09.00'!$F:$F,"c003x - Corporates")+SUMIFS('T 03.01'!P:P,'T 03.01'!E:E,"r0390 - Non-financial liabilities",'T 03.01'!$F:$F,"c003x - Corporates") -> 65441064 | G65: =+SUMIFS('T 09.00'!$M:$M,'T 09.00'!$E:$E,"r0390 - Non-financial liabilities",'T 09.00'!$F:$F,"c004x - Institutions")+SUMIFS('T 03.01'!P:P,'T 03.01'!E:E,"r0390 - Non-financial liabilities",'T 03.01'!$F:$F,"c004x - Institutions") -> 20574581 | H65: =+SUMIFS('T 09.00'!$M:$M,'T 09.00'!$E:$E,"r0390 - Non-financial liabilities",'T 09.00'!$F:$F,"c005x - Other financial corporations")+I65+SUMIFS('T 03.01'!P:P,'T 03.01'!E:E,"r0390 - Non-financial liabilities",'T 03.01'!$F:$F,"c005x - Other financial corporations") -> 48135527 | I65: =+SUMIFS('T 09.00'!$M:$M,'T 09.00'!$E:$E,"r0390 - Non-financial liabilities",'T 09.00'!$F:$F,"c006x - Insurance firms & pension funds")+SUMIFS('T 03.01'!P:P,'T 03.01'!E:E,"r0390 - Non-financial liabilities",'T 03.01'!$F:$F,"c006x - Insurance firms & pension funds") -> 4534786.2 | J65: =+SUMIFS('T 09.00'!$M:$M,'T 09.00'!$E:$E,"r0390 - Non-financial liabilities",'T 09.00'!$F:$F,"c008x - Government, central banks & supranationals")+SUMIFS('T 03.01'!P:P,'T 03.01'!E:E,"r0390 - Non-financial liabilities",'T 03.01'!$F:$F,"c008x - Government, central banks & supranationals") -> 21255982 | K65: 0 | L65: =+SUMIFS('T 09.00'!$M:$M,'T 09.00'!$E:$E,"r0390 - Non-financial liabilities",'T 09.00'!$F:$F,"c010x - Non-identified, not listed on an exchange platform")+SUMIFS('T 03.01'!P:P,'T 03.01'!E:E,"r0390 - Non-financial liabilities",'T 03.01'!$F:$F,"") -> 3.1330474e+08 | M65: =SUM(D65:L65)-I65 -> 5.7243569e+08 | N65: =+SUMIF('T 03.01'!E:E,"r0390 - Non-financial liabilities",'T 03.01'!P:P) -> 49987448 | O65: 0
B66: Residual liabilities | C66: 0400 | D66: 0 | E66: 0 | F66: 0 | G66: 0 | H66: 0 | I66: 0 | J66: 0 | K66: 0 | L66: 0 | M66: =SUM(D66:L66)-I66 -> 0 | N66: 0 | O66: 0
B67: 0500 Own funds
B68: 0510 Common Equity Tier 1 Capital
B69: o/w capital instruments/share capital | C69: 0511 | D69: =SUMIFS('T 03.01'!P:P,'T 03.01'!E:E,"r0511 - o/w capital instruments/share capital",'T 03.01'!$F:$F,"c001x - Households") -> 0 | E69: =SUMIFS('T 03.01'!P:P,'T 03.01'!E:E,"r0511 - o/w capital instruments/share capital",'T 03.01'!$F:$F,"c002x - Micro & SME") -> 0 | F69: =SUMIFS('T 03.01'!P:P,'T 03.01'!E:E,"r0511 - o/w capital instruments/share capital",'T 03.01'!$F:$F,"c003x - Corporates") -> 14593315 | G69: =SUMIFS('T 03.01'!P:P,'T 03.01'!E:E,"r0511 - o/w capital instruments/share capital",'T 03.01'!$F:$F,"c004x - Institutions") -> 0 | H69: =I69+SUMIFS('T 03.01'!P:P,'T 03.01'!E:E,"r0511 - o/w capital instruments/share capital",'T 03.01'!$F:$F,"c005x - Other financial corporations") -> 1.4333118e+09 | I69: =SUMIFS('T 03.01'!P:P,'T 03.01'!E:E,"r0511 - o/w capital instruments/share capital",'T 03.01'!$F:$F,"c006x - Insurance firms & pension funds") -> 0 | J69: =SUMIFS('T 03.01'!P:P,'T 03.01'!E:E,"r0511 - o/w capital instruments/share capital",'T 03.01'!$F:$F,"c008x - Government, central banks & supranationals") -> 0 | K69: 0 | L69: =SUMIFS('T 03.01'!P:P,'T 03.01'!E:E,"r0511 - o/w capital instruments/share capital",'T 03.01'!$F:$F,"") -> 0 | M69: =SUM(D69:L69)-I69 -> 1.4479051e+09 | N69: =+SUMIF('T 03.01'!E:E,"r0511 - o/w capital instruments/share capital",'T 03.01'!P:P) -> 1.4479051e+09 | O69: 0
B70: o/w instruments ranking pari passu with ordinary shares | C70: 0512 | D70: =SUMIFS('T 03.01'!P:P,'T 03.01'!E:E,"r0512 - o/w instruments ranking pari passu with ordinary shares",'T 03.01'!$F:$F,"c001x - Households") -> 0 | E70: =SUMIFS('T 03.01'!P:P,'T 03.01'!E:E,"r0512 - o/w instruments ranking pari passu with ordinary shares",'T 03.01'!$F:$F,"c002x - Micro & SME") -> 0 | F70: =SUMIFS('T 03.01'!P:P,'T 03.01'!E:E,"r0512 - o/w instruments ranking pari passu with ordinary shares",'T 03.01'!$F:$F,"c003x - Corporates") -> 0 | G70: =SUMIFS('T 03.01'!P:P,'T 03.01'!E:E,"r0512 - o/w instruments ranking pari passu with ordinary shares",'T 03.01'!$F:$F,"c004x - Institutions") -> 0 | H70: =I70+SUMIFS('T 03.01'!P:P,'T 03.01'!E:E,"r0512 - o/w instruments ranking pari passu with ordinary shares",'T 03.01'!$F:$F,"c005x - Other financial corporations") -> 135000000 | I70: =SUMIFS('T 03.01'!P:P,'T 03.01'!E:E,"r0512 - o/w instruments ranking pari passu with ordinary shares",'T 03.01'!$F:$F,"c006x - Insurance firms & pension funds") -> 0 | J70: =SUMIFS('T 03.01'!P:P,'T 03.01'!E:E,"r0512 - o/w instruments ranking pari passu with ordinary shares",'T 03.01'!$F:$F,"c008x - Government, central banks & supranationals") -> 0 | K70: 0 | L70: =SUMIFS('T 03.01'!P:P,'T 03.01'!E:E,"r0512 - o/w instruments ranking pari passu with ordinary shares",'T 03.01'!$F:$F,"") -> 0 | M70: =SUM(D70:L70)-I70 -> 135000000 | N70: =+SUMIF('T 03.01'!E:E,"r0512 - o/w instruments ranking pari passu with ordinary shares",'T 03.01'!P:P) -> 135000000 | O70: 0
B71: 0520 Additional Tier 1 capital
B72: o/w (part of) subordinated liabilities recognised as own funds | C72: 0521 | D72: =SUMIFS('T 03.01'!P:P,'T 03.01'!E:E,"r0521 -o/w (part of) subordinated liabilities recognised as own funds",'T 03.01'!$F:$F,"c001x - Households") -> 0 | E72: =SUMIFS('T 03.01'!P:P,'T 03.01'!E:E,"r0521 -o/w (part of) subordinated liabilities recognised as own funds",'T 03.01'!$F:$F,"c002x - Micro & SME") -> 0 | F72: =SUMIFS('T 03.01'!P:P,'T 03.01'!E:E,"r0521 -o/w (part of) subordinated liabilities recognised as own funds",'T 03.01'!$F:$F,"c003x - Corporates") -> 0 | G72: =SUMIFS('T 03.01'!P:P,'T 03.01'!E:E,"r0521 -o/w (part of) subordinated liabilities recognised as own funds",'T 03.01'!$F:$F,"c004x - Institutions") -> 0 | H72: =I72+SUMIFS('T 03.01'!P:P,'T 03.01'!E:E,"r0521 -o/w (part of) subordinated liabilities recognised as own funds",'T 03.01'!$F:$F,"c005x - Other financial corporations") -> 0 | I72: =SUMIFS('T 03.01'!P:P,'T 03.01'!E:E,"r0521 -o/w (part of) subordinated liabilities recognised as own funds",'T 03.01'!$F:$F,"c006x - Insurance firms & pension funds") -> 0 | J72: =SUMIFS('T 03.01'!P:P,'T 03.01'!E:E,"r0521 -o/w (part of) subordinated liabilities recognised as own funds",'T 03.01'!$F:$F,"c008x - Government, central banks & supranationals") -> 0 | K72: 0 | L72: =SUMIFS('T 03.01'!P:P,'T 03.01'!E:E,"r0521 -o/w (part of) subordinated liabilities recognised as own funds",'T 03.01'!$F:$F,"") -> 0 | M72: =SUM(D72:L72)-I72 -> 0 | N72: =+SUMIF('T 03.01'!E:E,"r0521 -o/w (part of) subordinated liabilities recognised as own funds",'T 03.01'!P:P) -> 0 | O72: 0
B73: 0530 Tier 2 Capital
B74: o/w (part of) subordinated liabilities recognised as own funds | C74: 0531 | D74: =SUMIFS('T 03.01'!P:P,'T 03.01'!E:E,"r0531 - o/w (part of) subordinated liabilities recognised as own funds",'T 03.01'!$F:$F,"c001x - Households")+SUMIFS('T 04.00'!$N:$N,'T 04.00'!$E:$E,"r0531 - o/w (part of) subordinated liabilities recognised as own funds",'T 04.00'!$F:$F,"c001x - Households") -> 7599000 | E74: =SUMIFS('T 03.01'!P:P,'T 03.01'!E:E,"r0531 - o/w (part of) subordinated liabilities recognised as own funds",'T 03.01'!$F:$F,"c002x - Micro & SME")+SUMIFS('T 04.00'!$N:$N,'T 04.00'!$E:$E,"r0531 - o/w (part of) subordinated liabilities recognised as own funds",'T 04.00'!$F:$F,"c002x - Micro & SME") -> 0 | F74: =SUMIFS('T 03.01'!P:P,'T 03.01'!E:E,"r0531 - o/w (part of) subordinated liabilities recognised as own funds",'T 03.01'!$F:$F,"c003x - Corporates")+SUMIFS('T 04.00'!$N:$N,'T 04.00'!$E:$E,"r0531 - o/w (part of) subordinated liabilities recognised as own funds",'T 04.00'!$F:$F,"c003x - Corporates") -> 0 | G74: =SUMIFS('T 03.01'!P:P,'T 03.01'!E:E,"r0531 - o/w (part of) subordinated liabilities recognised as own funds",'T 03.01'!$F:$F,"c004x - Institutions")+SUMIFS('T 04.00'!$N:$N,'T 04.00'!$E:$E,"r0531 - o/w (part of) subordinated liabilities recognised as own funds",'T 04.00'!$F:$F,"c004x - Institutions") -> 0 | H74: =I74+SUMIFS('T 03.01'!P:P,'T 03.01'!E:E,"r0531 - o/w (part of) subordinated liabilities recognised as own funds",'T 03.01'!$F:$F,"c005x - Other financial corporations")+SUMIFS('T 04.00'!$N:$N,'T 04.00'!$E:$E,"r0531 - o/w (part of) subordinated liabilities recognised as own funds",'T 04.00'!$F:$F,"c005x - Other financial corporations") -> 320000000 | I74: =SUMIFS('T 03.01'!P:P,'T 03.01'!E:E,"r0531 - o/w (part of) subordinated liabilities recognised as own funds",'T 03.01'!$F:$F,"c006x - Insurance firms & pension funds")+SUMIFS('T 04.00'!$N:$N,'T 04.00'!$E:$E,"r0531 - o/w (part of) subordinated liabilities recognised as own funds",'T 04.00'!$F:$F,"c006x - Insurance firms & pension funds") -> 0 | J74: =SUMIFS('T 03.01'!P:P,'T 03.01'!E:E,"r0531 - o/w (part of) subordinated liabilities recognised as own funds",'T 03.01'!$F:$F,"c008x - Government, central banks & supranationals")+SUMIFS('T 04.00'!$N:$N,'T 04.00'!$E:$E,"r0531 - o/w (part of) subordinated liabilities recognised as own funds",'T 04.00'!$F:$F,"c008x - Government, central banks & supranationals") -> 0 | K74: 0 | L74: =SUMIFS('T 03.01'!P:P,'T 03.01'!E:E,"r0531 - o/w (part of) subordinated liabilities recognised as own funds",'T 03.01'!$F:$F,"")+SUMIFS('T 04.00'!$N:$N,'T 04.00'!$E:$E,"r0531 - o/w (part of) subordinated liabilities recognised as own funds",'T 04.00'!$F:$F,"") -> 0 | M74: =SUM(D74:L74)-I74 -> 327599000 | N74: =+SUMIF('T 03.01'!E:E,"r0531 - o/w (part of) subordinated liabilities recognised as own funds",'T 03.01'!P:P)+SUMIF('T 03.01'!E:E,"r0531 - o/w (part of) subordinated liabilities recognised as own funds",'T 03.01'!Q:Q) -> 3.2001387e+08 | O74: 0
B75: Total liabilities & own funds including derivative liabilities | C75: 0600
B76: Leverage exposure | C76: 1000

Sheet T 01.00 b
A1: T 01.00.b - Liability structure - carrying amount
D4: Columns
D5: Households | E5: Micro & SME | F5: Corporates | G5: Institutions | H5: Other financial corporations | J5: Government, central banks & supranationals | K5: Instruments listed on exchange platforms | L5: Others/non-identified | M5: Total
D6: Carrying amount | E6: Carrying amount | F6: Carrying amount | G6: Carrying amount | H6: Carrying amount | I6: Of which Insurance firms & pension funds | J6: Carrying amount | K6: Carrying amount | L6: Carrying amount | M6: Carrying amount | N6: Of which: intragroup | O6: Of which: issuances under non-EU MS jurisdiction/law, excluding intragroup
I7: Carrying amount | N7: Carrying amount | O7: Carrying amount
D8: 0011 | E8: 0021 | F8: 0031 | G8: 0041 | H8: 0051 | I8: 0061 | J8: 0081 | K8: 0091 | L8: 0101 | M8: 0121 | N8: 0131 | O8: 0141
A9: Rows | B9: Liabilities excluded from bail-in | C9: 0100 | D9: =D10+D11+D12+D13+D14+D15+D16+D17+D18+D19+D20 -> 1.9384943e+10 | E9: =E10+E11+E12+E13+E14+E15+E16+E17+E18+E19+E20 -> 2.3350551e+09 | F9: =F10+F11+F12+F13+F14+F15+F16+F17+F18+F19+F20 -> 3.8825771e+08 | G9: =G10+G11+G12+G13+G14+G15+G16+G17+G18+G19+G20 -> 2.1365971e+09 | H9: =H10+H11+H12+H13+H14+H15+H16+H17+H18+H19+H20 -> 3.9267518e+09 | I9: =I10+I11+I12+I13+I14+I15+I16+I17+I18+I19+I20 -> 3.0369526e+08 | J9: =J10+J11+J12+J13+J14+J15+J16+J17+J18+J19+J20 -> 7.7635511e+09 | K9: =K10+K11+K12+K13+K14+K15+K16+K17+K18+K19+K20 -> 0 | L9: =L10+L11+L12+L13+L14+L15+L16+L17+L18+L19+L20 -> 0 | M9: =SUM(D9:L9)-I9 -> 3.5935156e+10 | N9: =N10+N11+N12+N13+N14+N15+N16+N17+N18+N19+N20 -> 3.9283394e+09 | O9: 0
B10: Covered deposits (BRRD art. 44/2/a) | C10: 0110 | D10: =+SUMIFS('T 05.01'!$M:$M,'T 05.01'!$E:$E,"r0110 - Covered deposits (BRRD art. 44/2/a)",'T 05.01'!$F:$F,"c001x - Households")+SUMIFS('T 05.01'!$N:$N,'T 05.01'!$E:$E,"r0110 - Covered deposits (BRRD art. 44/2/a)",'T 05.01'!$F:$F,"c001x - Households")+SUMIFS('T 03.01'!P:P,'T 03.01'!E:E,"r0110 - Covered deposits (BRRD art. 44/2/a)",'T 03.01'!$F:$F,"c001x - Households")+SUMIFS('T 03.01'!Q:Q,'T 03.01'!E:E,"r0110 - Covered deposits (BRRD art. 44/2/a)",'T 03.01'!$F:$F,"c001x - Households") -> 1.914788e+10 | E10: =+SUMIFS('T 05.01'!$M:$M,'T 05.01'!$E:$E,"r0110 - Covered deposits (BRRD art. 44/2/a)",'T 05.01'!$F:$F,"c002x - Micro & SME")+SUMIFS('T 05.01'!$N:$N,'T 05.01'!$E:$E,"r0110 - Covered deposits (BRRD art. 44/2/a)",'T 05.01'!$F:$F,"c002x - Micro & SME")+SUMIFS('T 03.01'!P:P,'T 03.01'!E:E,"r0110 - Covered deposits (BRRD art. 44/2/a)",'T 03.01'!$F:$F,"c002x - Micro & SME")+SUMIFS('T 03.01'!Q:Q,'T 03.01'!E:E,"r0110 - Covered deposits (BRRD art. 44/2/a)",'T 03.01'!$F:$F,"c002x - Micro & SME") -> 2.3350551e+09 | F10: =+SUMIFS('T 05.01'!$M:$M,'T 05.01'!$E:$E,"r0110 - Covered deposits (BRRD art. 44/2/a)",'T 05.01'!$F:$F,"c003x - Corporates")+SUMIFS('T 05.01'!$N:$N,'T 05.01'!$E:$E,"r0110 - Covered deposits (BRRD art. 44/2/a)",'T 05.01'!$F:$F,"c003x - Corporates")+SUMIFS('T 03.01'!P:P,'T 03.01'!E:E,"r0110 - Covered deposits (BRRD art. 44/2/a)",'T 03.01'!$F:$F,"c003x - Corporates")+SUMIFS('T 03.01'!Q:Q,'T 03.01'!E:E,"r0110 - Covered deposits (BRRD art. 44/2/a)",'T 03.01'!$F:$F,"c003x - Corporates") -> 3.8825771e+08 | G10: =+SUMIFS('T 05.01'!$M:$M,'T 05.01'!$E:$E,"r0110 - Covered deposits (BRRD art. 44/2/a)",'T 05.01'!$F:$F,"c004x - Institutions")+SUMIFS('T 05.01'!$N:$N,'T 05.01'!$E:$E,"r0110 - Covered deposits (BRRD art. 44/2/a)",'T 05.01'!$F:$F,"c004x - Institutions")+SUMIFS('T 03.01'!P:P,'T 03.01'!E:E,"r0110 - Covered deposits (BRRD art. 44/2/a)",'T 03.01'!$F:$F,"c004x - Institutions")+SUMIFS('T 03.01'!Q:Q,'T 03.01'!E:E,"r0110 - Covered deposits (BRRD art. 44/2/a)",'T 03.01'!$F:$F,"c004x - Institutions") -> 0 | H10: =+SUMIFS('T 05.01'!$M:$M,'T 05.01'!$E:$E,"r0110 - Covered deposits (BRRD art. 44/2/a)",'T 05.01'!$F:$F,"c005x - Other financial corporations")+SUMIFS('T 05.01'!$N:$N,'T 05.01'!$E:$E,"r0110 - Covered deposits (BRRD art. 44/2/a)",'T 05.01'!$F:$F,"c005x - Other financial corporations")+I10+SUMIFS('T 03.01'!P:P,'T 03.01'!E:E,"r0110 - Covered deposits (BRRD art. 44/2/a)",'T 03.01'!$F:$F,"c005x - Other financial corporations")+SUMIFS('T 03.01'!Q:Q,'T 03.01'!E:E,"r0110 - Covered deposits (BRRD art. 44/2/a)",'T 03.01'!$F:$F,"c005x - Other financial corporations") -> 0 | I10: =+SUMIFS('T 05.01'!$M:$M,'T 05.01'!$E:$E,"r0110 - Covered deposits (BRRD art. 44/2/a)",'T 05.01'!$F:$F,"c006x - Insurance firms & pension funds")+SUMIFS('T 05.01'!$N:$N,'T 05.01'!$E:$E,"r0110 - Covered deposits (BRRD art. 44/2/a)",'T 05.01'!$F:$F,"c006x - Insurance firms & pension funds")+SUMIFS('T 03.01'!P:P,'T 03.01'!E:E,"r0110 - Covered deposits (BRRD art. 44/2/a)",'T 03.01'!$F:$F,"c006x - Insurance firms & pension funds")+SUMIFS('T 03.01'!Q:Q,'T 03.01'!E:E,"r0110 - Covered deposits (BRRD art. 44/2/a)",'T 03.01'!$F:$F,"c006x - Insurance firms & pension funds") -> 0 | J10: =+SUMIFS('T 05.01'!$M:$M,'T 05.01'!$E:$E,"r0110 - Covered deposits (BRRD art. 44/2/a)",'T 05.01'!$F:$F,"c008x - Government, central banks & supranationals")+SUMIFS('T 05.01'!$N:$N,'T 05.01'!$E:$E,"r0110 - Covered deposits (BRRD art. 44/2/a)",'T 05.01'!$F:$F,"c008x - Government, central banks & supranationals")+SUMIFS('T 03.01'!P:P,'T 03.01'!E:E,"r0110 - Covered deposits (BRRD art. 44/2/a)",'T 03.01'!$F:$F,"c008x - Government, central banks & supranationals")+SUMIFS('T 03.01'!Q:Q,'T 03.01'!E:E,"r0110 - Covered deposits (BRRD art. 44/2/a)",'T 03.01'!$F:$F,"c008x - Government, central banks & supranationals") -> 0 | K10: 0 | L10: =+SUMIFS('T 05.01'!$M:$M,'T 05.01'!$E:$E,"r0110 - Covered deposits (BRRD art. 44/2/a)",'T 05.01'!$F:$F,"")+SUMIFS('T 05.01'!$N:$N,'T 05.01'!$E:$E,"r0110 - Covered deposits (BRRD art. 44/2/a)",'T 05.01'!$F:$F,"")+SUMIFS('T 03.01'!P:P,'T 03.01'!E:E,"r0110 - Covered deposits (BRRD art. 44/2/a)",'T 03.01'!$F:$F,"")+SUMIFS('T 03.01'!Q:Q,'T 03.01'!E:E,"r0110 - Covered deposits (BRRD art. 44/2/a)",'T 03.01'!$F:$F,"") -> 0 | M10: =SUM(D10:L10)-I10 -> 2.1871193e+10 | N10: =+SUMIF('T 03.01'!E:E,"r0110 - Covered deposits (BRRD art. 44/2/a)",'T 03.01'!P:P)+SUMIF('T 03.01'!E:E,"r0110 - Covered deposits (BRRD art. 44/2/a)",'T 03.01'!Q:Q) -> 732268.55 | O10: 0 | V10: =+N10+N22+M27 -> 6.6741117e+09
B11: Secured liabilities - collateralized part (BRRD art. 44/2/b) | C11: 0120 | D11: =SUMIF('T 08.00'!$E:$E,"c001x - Households",'T 08.00'!$O:$O)+SUMIFS('T 03.01'!P:P,'T 03.01'!E:E,"r0120 - Secured liabilities - collateralized part (BRRD art. 44/2/b)",'T 03.01'!$F:$F,"c001x - Households")+SUMIFS('T 03.01'!Q:Q,'T 03.01'!E:E,"r0120 - Secured liabilities - collateralized part (BRRD art. 44/2/b)",'T 03.01'!$F:$F,"c001x - Households")+SUMIFS('T 04.00'!M:M,'T 04.00'!F:F,"c001x - Households",'T 04.00'!E:E,"r0120 - Secured liabilities - collateralized part (BRRD art. 44/2/b)")+SUMIFS('T 04.00'!O:O,'T 04.00'!F:F,"c001x - Households",'T 04.00'!E:E,"r0120 - Secured liabilities - collateralized part (BRRD art. 44/2/b)") -> 0 | E11: =SUMIF('T 08.00'!$E:$E,"c002x - Micro & SME",'T 08.00'!$O:$O)+SUMIFS('T 03.01'!P:P,'T 03.01'!E:E,"r0120 - Secured liabilities - collateralized part (BRRD art. 44/2/b)",'T 03.01'!$F:$F,"c002x - Micro & SME")+SUMIFS('T 03.01'!Q:Q,'T 03.01'!E:E,"r0120 - Secured liabilities - collateralized part (BRRD art. 44/2/b)",'T 03.01'!$F:$F,"c002x - Micro & SME")+SUMIFS('T 04.00'!M:M,'T 04.00'!F:F,"c002x - Micro & SME",'T 04.00'!E:E,"r0120 - Secured liabilities - collateralized part (BRRD art. 44/2/b)")+SUMIFS('T 04.00'!O:O,'T 04.00'!F:F,"c002x - Micro & SME",'T 04.00'!E:E,"r0120 - Secured liabilities - collateralized part (BRRD art. 44/2/b)") -> 0 | F11: =SUMIF('T 08.00'!$E:$E,"c003x - Corporates",'T 08.00'!$O:$O)+SUMIFS('T 03.01'!P:P,'T 03.01'!E:E,"r0120 - Secured liabilities - collateralized part (BRRD art. 44/2/b)",'T 03.01'!$F:$F,"c003x - Corporates")+SUMIFS('T 03.01'!Q:Q,'T 03.01'!E:E,"r0120 - Secured liabilities - collateralized part (BRRD art. 44/2/b)",'T 03.01'!$F:$F,"c003x - Corporates")+SUMIFS('T 04.00'!M:M,'T 04.00'!F:F,"c003x - Corporates",'T 04.00'!E:E,"r0120 - Secured liabilities - collateralized part (BRRD art. 44/2/b)")+SUMIFS('T 04.00'!O:O,'T 04.00'!F:F,"c003x - Corporates",'T 04.00'!E:E,"r0120 - Secured liabilities - collateralized part (BRRD art. 44/2/b)") -> 0 | G11: =SUMIF('T 08.00'!$E:$E,"c004x - Institutions",'T 08.00'!$O:$O)+SUMIFS('T 03.01'!P:P,'T 03.01'!E:E,"r0120 - Secured liabilities - collateralized part (BRRD art. 44/2/b)",'T 03.01'!$F:$F,"c004x - Institutions")+SUMIFS('T 03.01'!Q:Q,'T 03.01'!E:E,"r0120 - Secured liabilities - collateralized part (BRRD art. 44/2/b)",'T 03.01'!$F:$F,"c004x - Institutions")+SUMIFS('T 04.00'!N:N,'T 04.00'!F:F,"c004x - Institutions",'T 04.00'!E:E,"r0120 - Secured liabilities - collateralized part (BRRD art. 44/2/b)")+SUMIFS('T 04.00'!O:O,'T 04.00'!F:F,"c004x - Institutions",'T 04.00'!E:E,"r0120 - Secured liabilities - collateralized part (BRRD art. 44/2/b)") -> 1.9824519e+09 | H11: =SUMIF('T 08.00'!$E:$E,"c005x - Other financial corporations",'T 08.00'!$O:$O)+I11+SUMIFS('T 03.01'!P:P,'T 03.01'!E:E,"r0120 - Secured liabilities - collateralized part (BRRD art. 44/2/b)",'T 03.01'!$F:$F,"c005x - Other financial corporations")+SUMIFS('T 03.01'!Q:Q,'T 03.01'!E:E,"r0120 - Secured liabilities - collateralized part (BRRD art. 44/2/b)",'T 03.01'!$F:$F,"c005x - Other financial corporations")+SUMIFS('T 04.00'!N:N,'T 04.00'!F:F,"c005x - Other financial corporations",'T 04.00'!E:E,"r0120 - Secured liabilities - collateralized part (BRRD art. 44/2/b)")+SUMIFS('T 04.00'!O:O,'T 04.00'!F:F,"c005x - Other financial corporations",'T 04.00'!E:E,"r0120 - Secured liabilities - collateralized part (BRRD art. 44/2/b)") -> 3.0241148e+09 | I11: =SUMIF('T 08.00'!$E:$E,"c006x - Insurance firms & pension funds",'T 08.00'!$O:$O)+SUMIFS('T 03.01'!P:P,'T 03.01'!E:E,"r0120 - Secured liabilities - collateralized part (BRRD art. 44/2/b)",'T 03.01'!$F:$F,"c006x - Insurance firms & pension funds")+SUMIFS('T 03.01'!Q:Q,'T 03.01'!E:E,"r0120 - Secured liabilities - collateralized part (BRRD art. 44/2/b)",'T 03.01'!$F:$F,"c006x - Insurance firms & pension funds")+SUMIFS('T 04.00'!N:N,'T 04.00'!F:F,"c006x - Insurance firms & pension funds",'T 04.00'!E:E,"r0120 - Secured liabilities - collateralized part (BRRD art. 44/2/b)")+SUMIFS('T 04.00'!O:O,'T 04.00'!F:F,"c006x - Insurance firms & pension funds",'T 04.00'!E:E,"r0120 - Secured liabilities - collateralized part (BRRD art. 44/2/b)") -> 0 | J11: =SUMIF('T 08.00'!$E:$E,"c008x - Government, central banks & supranationals",'T 08.00'!$O:$O)+SUMIFS('T 03.01'!P:P,'T 03.01'!E:E,"r0120 - Secured liabilities - collateralized part (BRRD art. 44/2/b)",'T 03.01'!$F:$F,"c008x - Government, central banks & supranationals")+SUMIFS('T 03.01'!Q:Q,'T 03.01'!E:E,"r0120 - Secured liabilities - collateralized part (BRRD art. 44/2/b)",'T 03.01'!$F:$F,"c008x - Government, central banks & supranationals")+SUMIFS('T 04.00'!N:N,'T 04.00'!F:F,"c008x - Government, central banks & supranationals",'T 04.00'!E:E,"r0120 - Secured liabilities - collateralized part (BRRD art. 44/2/b)")+SUMIFS('T 04.00'!O:O,'T 04.00'!F:F,"c008x - Government, central banks & supranationals",'T 04.00'!E:E,"r0120 - Secured liabilities - collateralized part (BRRD art. 44/2/b)") -> 7.410242e+09 | K11: 0 | L11: =SUMIF('T 08.00'!$E:$E,"",'T 08.00'!$O:$O)+SUMIFS('T 03.01'!P:P,'T 03.01'!E:E,"r0120 - Secured liabilities - collateralized part (BRRD art. 44/2/b)",'T 03.01'!$F:$F,"")+SUMIFS('T 03.01'!Q:Q,'T 03.01'!E:E,"r0120 - Secured liabilities - collateralized part (BRRD art. 44/2/b)",'T 03.01'!$F:$F,"")+SUMIFS('T 04.00'!O:O,'T 04.00'!F:F,"",'T 04.00'!E:E,"r0120 - Secured liabilities - collateralized part (BRRD art. 44/2/b)") -> 0 | M11: =SUM(D11:L11)-I11 -> 1.2416809e+10 | N11: =+SUMIF('T 03.01'!E:E,"r0120 - Secured liabilities - collateralized part (BRRD art. 44/2/b)",'T 03.01'!P:P)+SUMIF('T 03.01'!E:E,"r0120 - Secured liabilities - collateralized part (BRRD art. 44/2/b)",'T 03.01'!Q:Q) -> 3.0241148e+09 | O11: 0
B12: Client liabilities, if protected in insolvency (BRRD art. 44/2/c) | C12: 0130 | D12: 0 | E12: 0 | F12: 0 | G12: 0 | H12: 0 | I12: 0 | J12: 0 | K12: 0 | L12: 0 | M12: =SUM(D12:L12)-I12 -> 0 | N12: 0 | O12: 0
B13: Fiduciary liabilities, if protected in insolvency (BRRD art. 44/2/d) | C13: 0140 | D13: 0 | E13: 0 | F13: 0 | G13: 0 | H13: 0 | I13: 0 | J13: 0 | K13: 0 | L13: 0 | M13: =SUM(D13:L13)-I13 -> 0 | N13: 0 | O13: 0
B14: Institution liabilities < 7 days (BRRD art. 44/2/e) | C14: 0150 | D14: =+SUMIFS('T 06.01'!$O:$O,'T 06.01'!$E:$E,"r0150 - Institution liabilities < 7 days (BRRD art. 44/2/e)",'T 06.01'!$F:$F,"c001x - Households")+SUMIFS('T 06.01'!$P:$P,'T 06.01'!$E:$E,"r0150 - Institution liabilities < 7 days (BRRD art. 44/2/e)",'T 06.01'!$F:$F,"c001x - Households")+SUMIFS('T 03.01'!P:P,'T 03.01'!E:E,"r0150 - Institution liabilities < 7 days (BRRD art. 44/2/e)",'T 03.01'!$F:$F,"c001x - Households")+SUMIFS('T 03.01'!Q:Q,'T 03.01'!E:E,"r0150 - Institution liabilities < 7 days (BRRD art. 44/2/e)",'T 03.01'!$F:$F,"c001x - Households") -> 0 | E14: =+SUMIFS('T 06.01'!$O:$O,'T 06.01'!$E:$E,"r0150 - Institution liabilities < 7 days (BRRD art. 44/2/e)",'T 06.01'!$F:$F,"c002x - Micro & SME")+SUMIFS('T 06.01'!$P:$P,'T 06.01'!$E:$E,"r0150 - Institution liabilities < 7 days (BRRD art. 44/2/e)",'T 06.01'!$F:$F,"c002x - Micro & SME")+SUMIFS('T 03.01'!P:P,'T 03.01'!E:E,"r0150 - Institution liabilities < 7 days (BRRD art. 44/2/e)",'T 03.01'!$F:$F,"c002x - Micro & SME")+SUMIFS('T 03.01'!Q:Q,'T 03.01'!E:E,"r0150 - Institution liabilities < 7 days (BRRD art. 44/2/e)",'T 03.01'!$F:$F,"c002x - Micro & SME") -> 0 | F14: =+SUMIFS('T 06.01'!$O:$O,'T 06.01'!$E:$E,"r0150 - Institution liabilities < 7 days (BRRD art. 44/2/e)",'T 06.01'!$F:$F,"c003x - Corporates")+SUMIFS('T 06.01'!$P:$P,'T 06.01'!$E:$E,"r0150 - Institution liabilities < 7 days (BRRD art. 44/2/e)",'T 06.01'!$F:$F,"c003x - Corporates")+SUMIFS('T 03.01'!P:P,'T 03.01'!E:E,"r0150 - Institution liabilities < 7 days (BRRD art. 44/2/e)",'T 03.01'!$F:$F,"c003x - Corporates")+SUMIFS('T 03.01'!Q:Q,'T 03.01'!E:E,"r0150 - Institution liabilities < 7 days (BRRD art. 44/2/e)",'T 03.01'!$F:$F,"c003x - Corporates") -> 0 | G14: =+SUMIFS('T 06.01'!$O:$O,'T 06.01'!$E:$E,"r0150 - Institution liabilities < 7 days (BRRD art. 44/2/e)",'T 06.01'!$F:$F,"c004x - Institutions")+SUMIFS('T 06.01'!$P:$P,'T 06.01'!$E:$E,"r0150 - Institution liabilities < 7 days (BRRD art. 44/2/e)",'T 06.01'!$F:$F,"c004x - Institutions")+SUMIFS('T 03.01'!P:P,'T 03.01'!E:E,"r0150 - Institution liabilities < 7 days (BRRD art. 44/2/e)",'T 03.01'!$F:$F,"c004x - Institutions")+SUMIFS('T 03.01'!Q:Q,'T 03.01'!E:E,"r0150 - Institution liabilities < 7 days (BRRD art. 44/2/e)",'T 03.01'!$F:$F,"c004x - Institutions") -> 1.5324904e+08 | H14: =+SUMIFS('T 06.01'!$O:$O,'T 06.01'!$E:$E,"r0150 - Institution liabilities < 7 days (BRRD art. 44/2/e)",'T 06.01'!$F:$F,"c005x - Other financial corporations")+SUMIFS('T 06.01'!$P:$P,'T 06.01'!$E:$E,"r0150 - Institution liabilities < 7 days (BRRD art. 44/2/e)",'T 06.01'!$F:$F,"c005x - Other financial corporations")+I14+SUMIFS('T 03.01'!P:P,'T 03.01'!E:E,"r0150 - Institution liabilities < 7 days (BRRD art. 44/2/e)",'T 03.01'!$F:$F,"c005x - Other financial corporations")+SUMIFS('T 03.01'!Q:Q,'T 03.01'!E:E,"r0150 - Institution liabilities < 7 days (BRRD art. 44/2/e)",'T 03.01'!$F:$F,"c005x - Other financial corporations") -> 0 | I14: =+SUMIFS('T 06.01'!$O:$O,'T 06.01'!$E:$E,"r0150 - Institution liabilities < 7 days (BRRD art. 44/2/e)",'T 06.01'!$F:$F,"c006x - Insurance firms & pension funds")+SUMIFS('T 06.01'!$P:$P,'T 06.01'!$E:$E,"r0150 - Institution liabilities < 7 days (BRRD art. 44/2/e)",'T 06.01'!$F:$F,"c006x - Insurance firms & pension funds")+SUMIFS('T 03.01'!P:P,'T 03.01'!E:E,"r0150 - Institution liabilities < 7 days (BRRD art. 44/2/e)",'T 03.01'!$F:$F,"c006x - Insurance firms & pension funds")+SUMIFS('T 03.01'!Q:Q,'T 03.01'!E:E,"r0150 - Institution liabilities < 7 days (BRRD art. 44/2/e)",'T 03.01'!$F:$F,"c006x - Insurance firms & pension funds") -> 0 | J14: =+SUMIFS('T 06.01'!$O:$O,'T 06.01'!$E:$E,"r0150 - Institution liabilities < 7 days (BRRD art. 44/2/e)",'T 06.01'!$F:$F,"c008x - Government, central banks & supranationals")+SUMIFS('T 06.01'!$P:$P,'T 06.01'!$E:$E,"r0150 - Institution liabilities < 7 days (BRRD art. 44/2/e)",'T 06.01'!$F:$F,"c008x - Government, central banks & supranationals")+SUMIFS('T 03.01'!P:P,'T 03.01'!E:E,"r0150 - Institution liabilities < 7 days (BRRD art. 44/2/e)",'T 03.01'!$F:$F,"c008x - Government, central banks & supranationals")+SUMIFS('T 03.01'!Q:Q,'T 03.01'!E:E,"r0150 - Institution liabilities < 7 days (BRRD art. 44/2/e)",'T 03.01'!$F:$F,"c008x - Government, central banks & supranationals") -> 0 | K14: 0 | L14: =+SUMIFS('T 06.01'!$O:$O,'T 06.01'!$E:$E,"r0150 - Institution liabilities < 7 days (BRRD art. 44/2/e)",'T 06.01'!$F:$F,"")+SUMIFS('T 06.01'!$P:$P,'T 06.01'!$E:$E,"r0150 - Institution liabilities < 7 days (BRRD art. 44/2/e)",'T 06.01'!$F:$F,"")+SUMIFS('T 03.01'!P:P,'T 03.01'!E:E,"r0150 - Institution liabilities < 7 days (BRRD art. 44/2/e)",'T 03.01'!$F:$F,"")+SUMIFS('T 03.01'!Q:Q,'T 03.01'!E:E,"r0150 - Institution liabilities < 7 days (BRRD art. 44/2/e)",'T 03.01'!$F:$F,"") -> 0 | M14: =SUM(D14:L14)-I14 -> 1.5324904e+08 | N14: =+SUMIF('T 03.01'!E:E,"r0150 - Institution liabilities < 7 days (BRRD art. 44/2/e)",'T 03.01'!P:P)+SUMIF('T 03.01'!E:E,"r0150 - Institution liabilities < 7 days (BRRD art. 44/2/e)",'T 03.01'!Q:Q) -> 0 | O14: 0
B15: System (operator) and CCP liabilities < 7 days (BRRD art. 44/2/f) | C15: 0161 | D15: =+SUMIFS('T 06.01'!$O:$O,'T 06.01'!$E:$E,"r0161 - System (operator) and CCP liabilities < 7 days (BRRD art. 44/2/f)",'T 06.01'!$F:$F,"c001x - Households")+SUMIFS('T 06.01'!$P:$P,'T 06.01'!$E:$E,"r0161 - System (operator) and CCP liabilities < 7 days (BRRD art. 44/2/f)",'T 06.01'!$F:$F,"c001x - Households")+SUMIFS('T 03.01'!P:P,'T 03.01'!E:E,"r0161 - System (operator) and CCP liabilities < 7 days (BRRD art. 44/2/f)",'T 03.01'!$F:$F,"c001x - Households")+SUMIFS('T 03.01'!Q:Q,'T 03.01'!E:E,"r0161 - System (operator) and CCP liabilities < 7 days (BRRD art. 44/2/f)",'T 03.01'!$F:$F,"c001x - Households") -> 0 | E15: =+SUMIFS('T 06.01'!$O:$O,'T 06.01'!$E:$E,"r0161 - System (operator) and CCP liabilities < 7 days (BRRD art. 44/2/f)",'T 06.01'!$F:$F,"c002x - Micro & SME")+SUMIFS('T 06.01'!$P:$P,'T 06.01'!$E:$E,"r0161 - System (operator) and CCP liabilities < 7 days (BRRD art. 44/2/f)",'T 06.01'!$F:$F,"c002x - Micro & SME")+SUMIFS('T 03.01'!P:P,'T 03.01'!E:E,"r0161 - System (operator) and CCP liabilities < 7 days (BRRD art. 44/2/f)",'T 03.01'!$F:$F,"c002x - Micro & SME")+SUMIFS('T 03.01'!Q:Q,'T 03.01'!E:E,"r0161 - System (operator) and CCP liabilities < 7 days (BRRD art. 44/2/f)",'T 03.01'!$F:$F,"c002x - Micro & SME") -> 0 | F15: =+SUMIFS('T 06.01'!$O:$O,'T 06.01'!$E:$E,"r0161 - System (operator) and CCP liabilities < 7 days (BRRD art. 44/2/f)",'T 06.01'!$F:$F,"c003x - Corporates")+SUMIFS('T 06.01'!$P:$P,'T 06.01'!$E:$E,"r0161 - System (operator) and CCP liabilities < 7 days (BRRD art. 44/2/f)",'T 06.01'!$F:$F,"c003x - Corporates")+SUMIFS('T 03.01'!P:P,'T 03.01'!E:E,"r0161 - System (operator) and CCP liabilities < 7 days (BRRD art. 44/2/f)",'T 03.01'!$F:$F,"c003x - Corporates")+SUMIFS('T 03.01'!Q:Q,'T 03.01'!E:E,"r0161 - System (operator) and CCP liabilities < 7 days (BRRD art. 44/2/f)",'T 03.01'!$F:$F,"c003x - Corporates") -> 0 | G15: =+SUMIFS('T 06.01'!$O:$O,'T 06.01'!$E:$E,"r0161 - System (operator) and CCP liabilities < 7 days (BRRD art. 44/2/f)",'T 06.01'!$F:$F,"c004x - Institutions")+SUMIFS('T 06.01'!$P:$P,'T 06.01'!$E:$E,"r0161 - System (operator) and CCP liabilities < 7 days (BRRD art. 44/2/f)",'T 06.01'!$F:$F,"c004x - Institutions")+SUMIFS('T 03.01'!P:P,'T 03.01'!E:E,"r0161 - System (operator) and CCP liabilities < 7 days (BRRD art. 44/2/f)",'T 03.01'!$F:$F,"c004x - Institutions")+SUMIFS('T 03.01'!Q:Q,'T 03.01'!E:E,"r0161 - System (operator) and CCP liabilities < 7 days (BRRD art. 44/2/f)",'T 03.01'!$F:$F,"c004x - Institutions") -> 40810.25 | H15: =+SUMIFS('T 06.01'!$O:$O,'T 06.01'!$E:$E,"r0161 - System (operator) and CCP liabilities < 7 days (BRRD art. 44/2/f)",'T 06.01'!$F:$F,"c005x - Other financial corporations")+SUMIFS('T 06.01'!$P:$P,'T 06.01'!$E:$E,"r0161 - System (operator) and CCP liabilities < 7 days (BRRD art. 44/2/f)",'T 06.01'!$F:$F,"c005x - Other financial corporations")+I15+SUMIFS('T 03.01'!P:P,'T 03.01'!E:E,"r0161 - System (operator) and CCP liabilities < 7 days (BRRD art. 44/2/f)",'T 03.01'!$F:$F,"c005x - Other financial corporations")+SUMIFS('T 03.01'!Q:Q,'T 03.01'!E:E,"r0161 - System (operator) and CCP liabilities < 7 days (BRRD art. 44/2/f)",'T 03.01'!$F:$F,"c005x - Other financial corporations") -> 0 | I15: =+SUMIFS('T 06.01'!$O:$O,'T 06.01'!$E:$E,"r0161 - System (operator) and CCP liabilities < 7 days (BRRD art. 44/2/f)",'T 06.01'!$F:$F,"c006x - Insurance firms & pension funds")+SUMIFS('T 06.01'!$P:$P,'T 06.01'!$E:$E,"r0161 - System (operator) and CCP liabilities < 7 days (BRRD art. 44/2/f)",'T 06.01'!$F:$F,"c006x - Insurance firms & pension funds")+SUMIFS('T 03.01'!P:P,'T 03.01'!E:E,"r0161 - System (operator) and CCP liabilities < 7 days (BRRD art. 44/2/f)",'T 03.01'!$F:$F,"c006x - Insurance firms & pension funds")+SUMIFS('T 03.01'!Q:Q,'T 03.01'!E:E,"r0161 - System (operator) and CCP liabilities < 7 days (BRRD art. 44/2/f)",'T 03.01'!$F:$F,"c006x - Insurance firms & pension funds") -> 0 | J15: =+SUMIFS('T 06.01'!$O:$O,'T 06.01'!$E:$E,"r0161 - System (operator) and CCP liabilities < 7 days (BRRD art. 44/2/f)",'T 06.01'!$F:$F,"c008x - Government, central banks & supranationals")+SUMIFS('T 06.01'!$P:$P,'T 06.01'!$E:$E,"r0161 - System (operator) and CCP liabilities < 7 days (BRRD art. 44/2/f)",'T 06.01'!$F:$F,"c008x - Government, central banks & supranationals")+SUMIFS('T 03.01'!P:P,'T 03.01'!E:E,"r0161 - System (operator) and CCP liabilities < 7 days (BRRD art. 44/2/f)",'T 03.01'!$F:$F,"c008x - Government, central banks & supranationals")+SUMIFS('T 03.01'!Q:Q,'T 03.01'!E:E,"r0161 - System (operator) and CCP liabilities < 7 days (BRRD art. 44/2/f)",'T 03.01'!$F:$F,"c008x - Government, central banks & supranationals") -> 0 | K15: 0 | L15: =+SUMIFS('T 06.01'!$O:$O,'T 06.01'!$E:$E,"r0161 - System (operator) and CCP liabilities < 7 days (BRRD art. 44/2/f)",'T 06.01'!$F:$F,"")+SUMIFS('T 06.01'!$P:$P,'T 06.01'!$E:$E,"r0161 - System (operator) and CCP liabilities < 7 days (BRRD art. 44/2/f)",'T 06.01'!$F:$F,"")+SUMIFS('T 03.01'!P:P,'T 03.01'!E:E,"r0161 - System (operator) and CCP liabilities < 7 days (BRRD art. 44/2/f)",'T 03.01'!$F:$F,"")+SUMIFS('T 03.01'!Q:Q,'T 03.01'!E:E,"r0161 - System (operator) and CCP liabilities < 7 days (BRRD art. 44/2/f)",'T 03.01'!$F:$F,"") -> 0 | M15: =SUM(D15:L15)-I15 -> 40810.25 | N15: =+SUMIF('T 03.01'!E:E,"r0161 - System (operator) and CCP liabilities < 7 days (BRRD art. 44/2/f)",'T 03.01'!P:P)+SUMIF('T 03.01'!E:E,"r0161 - System (operator) and CCP liabilities < 7 days (BRRD art. 44/2/f)",'T 03.01'!Q:Q) -> 0 | O15: 0
B16: Employee liabilities (BRRD art. 44/2/g/i) | C16: 0170 | D16: =+SUMIFS('T 09.00'!$M:$M,'T 09.00'!$E:$E,"r0170 - Employee liabilities (BRRD art. 44/2/g/i)",'T 09.00'!$F:$F,"c001x - Households")+SUMIFS('T 03.01'!P:P,'T 03.01'!E:E,"r0170 - Employee liabilities (BRRD art. 44/2/g/i)",'T 03.01'!$F:$F,"c001x - Households")+SUMIFS('T 03.01'!Q:Q,'T 03.01'!E:E,"r0170 - Employee liabilities (BRRD art. 44/2/g/i)",'T 03.01'!$F:$F,"c001x - Households") -> 2.3292511e+08 | E16: =+SUMIFS('T 09.00'!$M:$M,'T 09.00'!$E:$E,"r0170 - Employee liabilities (BRRD art. 44/2/g/i)",'T 09.00'!$F:$F,"c002x - Micro & SME")+SUMIFS('T 03.01'!P:P,'T 03.01'!E:E,"r0170 - Employee liabilities (BRRD art. 44/2/g/i)",'T 03.01'!$F:$F,"c002x - Micro & SME")+SUMIFS('T 03.01'!Q:Q,'T 03.01'!E:E,"r0170 - Employee liabilities (BRRD art. 44/2/g/i)",'T 03.01'!$F:$F,"c002x - Micro & SME") -> 0 | F16: =+SUMIFS('T 09.00'!$M:$M,'T 09.00'!$E:$E,"r0170 - Employee liabilities (BRRD art. 44/2/g/i)",'T 09.00'!$F:$F,"c003x - Corporates")+SUMIFS('T 03.01'!P:P,'T 03.01'!E:E,"r0170 - Employee liabilities (BRRD art. 44/2/g/i)",'T 03.01'!$F:$F,"c003x - Corporates")+SUMIFS('T 03.01'!Q:Q,'T 03.01'!E:E,"r0170 - Employee liabilities (BRRD art. 44/2/g/i)",'T 03.01'!$F:$F,"c003x - Corporates") -> 0 | G16: =+SUMIFS('T 09.00'!$M:$M,'T 09.00'!$E:$E,"r0170 - Employee liabilities (BRRD art. 44/2/g/i)",'T 09.00'!$F:$F,"c004x - Institutions")+SUMIFS('T 03.01'!P:P,'T 03.01'!E:E,"r0170 - Employee liabilities (BRRD art. 44/2/g/i)",'T 03.01'!$F:$F,"c004x - Institutions")+SUMIFS('T 03.01'!Q:Q,'T 03.01'!E:E,"r0170 - Employee liabilities (BRRD art. 44/2/g/i)",'T 03.01'!$F:$F,"c004x - Institutions") -> 0 | H16: =+SUMIFS('T 09.00'!$M:$M,'T 09.00'!$E:$E,"r0170 - Employee liabilities (BRRD art. 44/2/g/i)",'T 09.00'!$F:$F,"c005x - Other financial corporations")+I16+SUMIFS('T 03.01'!P:P,'T 03.01'!E:E,"r0170 - Employee liabilities (BRRD art. 44/2/g/i)",'T 03.01'!$F:$F,"c005x - Other financial corporations")+SUMIFS('T 03.01'!Q:Q,'T 03.01'!E:E,"r0170 - Employee liabilities (BRRD art. 44/2/g/i)",'T 03.01'!$F:$F,"c005x - Other financial corporations") -> 0 | I16: =+SUMIFS('T 09.00'!$M:$M,'T 09.00'!$E:$E,"r0170 - Employee liabilities (BRRD art. 44/2/g/i)",'T 09.00'!$F:$F,"c006x - Insurance firms & pension funds")+SUMIFS('T 03.01'!P:P,'T 03.01'!E:E,"r0170 - Employee liabilities (BRRD art. 44/2/g/i)",'T 03.01'!$F:$F,"c006x - Insurance firms & pension funds")+SUMIFS('T 03.01'!Q:Q,'T 03.01'!E:E,"r0170 - Employee liabilities (BRRD art. 44/2/g/i)",'T 03.01'!$F:$F,"c006x - Insurance firms & pension funds") -> 0 | J16: =+SUMIFS('T 09.00'!$M:$M,'T 09.00'!$E:$E,"r0170 - Employee liabilities (BRRD art. 44/2/g/i)",'T 09.00'!$F:$F,"c008x - Government, central banks & supranationals")+SUMIFS('T 03.01'!P:P,'T 03.01'!E:E,"r0170 - Employee liabilities (BRRD art. 44/2/g/i)",'T 03.01'!$F:$F,"c008x - Government, central banks & supranationals")+SUMIFS('T 03.01'!Q:Q,'T 03.01'!E:E,"r0170 - Employee liabilities (BRRD art. 44/2/g/i)",'T 03.01'!$F:$F,"c008x - Government, central banks & supranationals") -> 0 | K16: 0 | L16: =+SUMIFS('T 09.00'!$M:$M,'T 09.00'!$E:$E,"r0170 - Employee liabilities (BRRD art. 44/2/g/i)",'T 09.00'!$F:$F,"c010x - Non-identified, not listed on an exchange platform")+SUMIFS('T 03.01'!P:P,'T 03.01'!E:E,"r0170 - Employee liabilities (BRRD art. 44/2/g/i)",'T 03.01'!$F:$F,"")+SUMIFS('T 03.01'!Q:Q,'T 03.01'!E:E,"r0170 - Employee liabilities (BRRD art. 44/2/g/i)",'T 03.01'!$F:$F,"") -> 0 | M16: =SUM(D16:L16)-I16 -> 2.3292511e+08 | N16: =+SUMIF('T 03.01'!E:E,"r0170 - Employee liabilities (BRRD art. 44/2/g/i)",'T 03.01'!P:P)+SUMIF('T 03.01'!E:E,"r0170 - Employee liabilities (BRRD art. 44/2/g/i)",'T 03.01'!Q:Q) -> 0 | O16: 0
B17: Critical service liabilities (BRRD art. 44/2/g/ii) | C17: 0180 | D17: =+SUMIFS('T 06.01'!$O:$O,'T 06.01'!$E:$E,"r0180 - Critical service liabilities (BRRD art. 44/2/g/ii)",'T 06.01'!$F:$F,"c001x - Households")+SUMIFS('T 06.01'!$P:$P,'T 06.01'!$E:$E,"r0180 - Critical service liabilities (BRRD art. 44/2/g/ii)",'T 06.01'!$F:$F,"c001x - Households")+SUMIFS('T 03.01'!P:P,'T 03.01'!E:E,"r0180 - Critical service liabilities (BRRD art. 44/2/g/ii)",'T 03.01'!$F:$F,"c001x - Households")+SUMIFS('T 03.01'!Q:Q,'T 03.01'!E:E,"r0180 - Critical service liabilities (BRRD art. 44/2/g/ii)",'T 03.01'!$F:$F,"c001x - Households") -> 4137337.4 | E17: =+SUMIFS('T 06.01'!$O:$O,'T 06.01'!$E:$E,"r0180 - Critical service liabilities (BRRD art. 44/2/g/ii)",'T 06.01'!$F:$F,"c002x - Micro & SME")+SUMIFS('T 06.01'!$P:$P,'T 06.01'!$E:$E,"r0180 - Critical service liabilities (BRRD art. 44/2/g/ii)",'T 06.01'!$F:$F,"c002x - Micro & SME")+SUMIFS('T 03.01'!P:P,'T 03.01'!E:E,"r0180 - Critical service liabilities (BRRD art. 44/2/g/ii)",'T 03.01'!$F:$F,"c002x - Micro & SME")+SUMIFS('T 03.01'!Q:Q,'T 03.01'!E:E,"r0180 - Critical service liabilities (BRRD art. 44/2/g/ii)",'T 03.01'!$F:$F,"c002x - Micro & SME") -> 0 | F17: =+SUMIFS('T 06.01'!$O:$O,'T 06.01'!$E:$E,"r0180 - Critical service liabilities (BRRD art. 44/2/g/ii)",'T 06.01'!$F:$F,"c003x - Corporates")+SUMIFS('T 06.01'!$P:$P,'T 06.01'!$E:$E,"r0180 - Critical service liabilities (BRRD art. 44/2/g/ii)",'T 06.01'!$F:$F,"c003x - Corporates")+SUMIFS('T 03.01'!P:P,'T 03.01'!E:E,"r0180 - Critical service liabilities (BRRD art. 44/2/g/ii)",'T 03.01'!$F:$F,"c003x - Corporates")+SUMIFS('T 03.01'!Q:Q,'T 03.01'!E:E,"r0180 - Critical service liabilities (BRRD art. 44/2/g/ii)",'T 03.01'!$F:$F,"c003x - Corporates") -> 0 | G17: =+SUMIFS('T 06.01'!$O:$O,'T 06.01'!$E:$E,"r0180 - Critical service liabilities (BRRD art. 44/2/g/ii)",'T 06.01'!$F:$F,"c004x - Institutions")+SUMIFS('T 06.01'!$P:$P,'T 06.01'!$E:$E,"r0180 - Critical service liabilities (BRRD art. 44/2/g/ii)",'T 06.01'!$F:$F,"c004x - Institutions")+SUMIFS('T 03.01'!P:P,'T 03.01'!E:E,"r0180 - Critical service liabilities (BRRD art. 44/2/g/ii)",'T 03.01'!$F:$F,"c004x - Institutions")+SUMIFS('T 03.01'!Q:Q,'T 03.01'!E:E,"r0180 - Critical service liabilities (BRRD art. 44/2/g/ii)",'T 03.01'!$F:$F,"c004x - Institutions") -> 0 | H17: =+SUMIFS('T 06.01'!$O:$O,'T 06.01'!$E:$E,"r0180 - Critical service liabilities (BRRD art. 44/2/g/ii)",'T 06.01'!$F:$F,"c005x - Other financial corporations")+SUMIFS('T 06.01'!$P:$P,'T 06.01'!$E:$E,"r0180 - Critical service liabilities (BRRD art. 44/2/g/ii)",'T 06.01'!$F:$F,"c005x - Other financial corporations")+I17+SUMIFS('T 03.01'!P:P,'T 03.01'!E:E,"r0180 - Critical service liabilities (BRRD art. 44/2/g/ii)",'T 03.01'!$F:$F,"c005x - Other financial corporations")+SUMIFS('T 03.01'!Q:Q,'T 03.01'!E:E,"r0180 - Critical service liabilities (BRRD art. 44/2/g/ii)",'T 03.01'!$F:$F,"c005x - Other financial corporations") -> 0 | I17: =+SUMIFS('T 06.01'!$O:$O,'T 06.01'!$E:$E,"r0180 - Critical service liabilities (BRRD art. 44/2/g/ii)",'T 06.01'!$F:$F,"c006x - Insurance firms & pension funds")+SUMIFS('T 06.01'!$P:$P,'T 06.01'!$E:$E,"r0180 - Critical service liabilities (BRRD art. 44/2/g/ii)",'T 06.01'!$F:$F,"c006x - Insurance firms & pension funds")+SUMIFS('T 03.01'!P:P,'T 03.01'!E:E,"r0180 - Critical service liabilities (BRRD art. 44/2/g/ii)",'T 03.01'!$F:$F,"c006x - Insurance firms & pension funds")+SUMIFS('T 03.01'!Q:Q,'T 03.01'!E:E,"r0180 - Critical service liabilities (BRRD art. 44/2/g/ii)",'T 03.01'!$F:$F,"c006x - Insurance firms & pension funds") -> 0 | J17: =+SUMIFS('T 06.01'!$O:$O,'T 06.01'!$E:$E,"r0180 - Critical service liabilities (BRRD art. 44/2/g/ii)",'T 06.01'!$F:$F,"c008x - Government, central banks & supranationals")+SUMIFS('T 06.01'!$P:$P,'T 06.01'!$E:$E,"r0180 - Critical service liabilities (BRRD art. 44/2/g/ii)",'T 06.01'!$F:$F,"c008x - Government, central banks & supranationals")+SUMIFS('T 03.01'!P:P,'T 03.01'!E:E,"r0180 - Critical service liabilities (BRRD art. 44/2/g/ii)",'T 03.01'!$F:$F,"c008x - Government, central banks & supranationals")+SUMIFS('T 03.01'!Q:Q,'T 03.01'!E:E,"r0180 - Critical service liabilities (BRRD art. 44/2/g/ii)",'T 03.01'!$F:$F,"c008x - Government, central banks & supranationals") -> 0 | K17: 0 | L17: =+SUMIFS('T 06.01'!$O:$O,'T 06.01'!$E:$E,"r0180 - Critical service liabilities (BRRD art. 44/2/g/ii)",'T 06.01'!$F:$F,"")+SUMIFS('T 06.01'!$P:$P,'T 06.01'!$E:$E,"r0180 - Critical service liabilities (BRRD art. 44/2/g/ii)",'T 06.01'!$F:$F,"")+SUMIFS('T 03.01'!P:P,'T 03.01'!E:E,"r0180 - Critical service liabilities (BRRD art. 44/2/g/ii)",'T 03.01'!$F:$F,"")+SUMIFS('T 03.01'!Q:Q,'T 03.01'!E:E,"r0180 - Critical service liabilities (BRRD art. 44/2/g/ii)",'T 03.01'!$F:$F,"") -> 0 | M17: =SUM(D17:L17)-I17 -> 4137337.4 | N17: =+SUMIF('T 03.01'!E:E,"r0180 - Critical service liabilities (BRRD art. 44/2/g/ii)",'T 03.01'!P:P)+SUMIF('T 03.01'!E:E,"r0180 - Critical service liabilities (BRRD art. 44/2/g/ii)",'T 03.01'!Q:Q) -> 0 | O17: 0
B18: Tax and social security authorities liabilities, if preferred (BRRD art. 44/2/g/iii) | C18: 0190 | D18: =+SUMIFS('T 06.01'!$O:$O,'T 06.01'!$E:$E,"r0190 - Tax and social security authorities liabilities, if preferred (BRRD art. 44/2/g/iii)",'T 06.01'!$F:$F,"c001x - Households")+SUMIFS('T 06.01'!$P:$P,'T 06.01'!$E:$E,"r0190 - Tax and social security authorities liabilities, if preferred (BRRD art. 44/2/g/iii)",'T 06.01'!$F:$F,"c001x - Households")+SUMIFS('T 03.01'!P:P,'T 03.01'!E:E,"r0190 - Tax and social security authorities liabilities, if preferred (BRRD art. 44/2/g/iii)",'T 03.01'!$F:$F,"c001x - Households")+SUMIFS('T 03.01'!Q:Q,'T 03.01'!E:E,"r0190 - Tax and social security authorities liabilities, if preferred (BRRD art. 44/2/g/iii)",'T 03.01'!$F:$F,"c001x - Households") -> 0 | E18: =+SUMIFS('T 06.01'!$O:$O,'T 06.01'!$E:$E,"r0190 - Tax and social security authorities liabilities, if preferred (BRRD art. 44/2/g/iii)",'T 06.01'!$F:$F,"c002x - Micro & SME")+SUMIFS('T 06.01'!$P:$P,'T 06.01'!$E:$E,"r0190 - Tax and social security authorities liabilities, if preferred (BRRD art. 44/2/g/iii)",'T 06.01'!$F:$F,"c002x - Micro & SME")+SUMIFS('T 03.01'!P:P,'T 03.01'!E:E,"r0190 - Tax and social security authorities liabilities, if preferred (BRRD art. 44/2/g/iii)",'T 03.01'!$F:$F,"c002x - Micro & SME")+SUMIFS('T 03.01'!Q:Q,'T 03.01'!E:E,"r0190 - Tax and social security authorities liabilities, if preferred (BRRD art. 44/2/g/iii)",'T 03.01'!$F:$F,"c002x - Micro & SME") -> 0 | F18: =+SUMIFS('T 06.01'!$O:$O,'T 06.01'!$E:$E,"r0190 - Tax and social security authorities liabilities, if preferred (BRRD art. 44/2/g/iii)",'T 06.01'!$F:$F,"c003x - Corporates")+SUMIFS('T 06.01'!$P:$P,'T 06.01'!$E:$E,"r0190 - Tax and social security authorities liabilities, if preferred (BRRD art. 44/2/g/iii)",'T 06.01'!$F:$F,"c003x - Corporates")+SUMIFS('T 03.01'!P:P,'T 03.01'!E:E,"r0190 - Tax and social security authorities liabilities, if preferred (BRRD art. 44/2/g/iii)",'T 03.01'!$F:$F,"c003x - Corporates")+SUMIFS('T 03.01'!Q:Q,'T 03.01'!E:E,"r0190 - Tax and social security authorities liabilities, if preferred (BRRD art. 44/2/g/iii)",'T 03.01'!$F:$F,"c003x - Corporates") -> 0 | G18: =+SUMIFS('T 06.01'!$O:$O,'T 06.01'!$E:$E,"r0190 - Tax and social security authorities liabilities, if preferred (BRRD art. 44/2/g/iii)",'T 06.01'!$F:$F,"c004x - Institutions")+SUMIFS('T 06.01'!$P:$P,'T 06.01'!$E:$E,"r0190 - Tax and social security authorities liabilities, if preferred (BRRD art. 44/2/g/iii)",'T 06.01'!$F:$F,"c004x - Institutions")+SUMIFS('T 03.01'!P:P,'T 03.01'!E:E,"r0190 - Tax and social security authorities liabilities, if preferred (BRRD art. 44/2/g/iii)",'T 03.01'!$F:$F,"c004x - Institutions")+SUMIFS('T 03.01'!Q:Q,'T 03.01'!E:E,"r0190 - Tax and social security authorities liabilities, if preferred (BRRD art. 44/2/g/iii)",'T 03.01'!$F:$F,"c004x - Institutions") -> 0 | H18: =+SUMIFS('T 06.01'!$O:$O,'T 06.01'!$E:$E,"r0190 - Tax and social security authorities liabilities, if preferred (BRRD art. 44/2/g/iii)",'T 06.01'!$F:$F,"c005x - Other financial corporations")+SUMIFS('T 06.01'!$P:$P,'T 06.01'!$E:$E,"r0190 - Tax and social security authorities liabilities, if preferred (BRRD art. 44/2/g/iii)",'T 06.01'!$F:$F,"c005x - Other financial corporations")+I18+SUMIFS('T 03.01'!P:P,'T 03.01'!E:E,"r0190 - Tax and social security authorities liabilities, if preferred (BRRD art. 44/2/g/iii)",'T 03.01'!$F:$F,"c005x - Other financial corporations")+SUMIFS('T 03.01'!Q:Q,'T 03.01'!E:E,"r0190 - Tax and social security authorities liabilities, if preferred (BRRD art. 44/2/g/iii)",'T 03.01'!$F:$F,"c005x - Other financial corporations") -> 0 | I18: =+SUMIFS('T 06.01'!$O:$O,'T 06.01'!$E:$E,"r0190 - Tax and social security authorities liabilities, if preferred (BRRD art. 44/2/g/iii)",'T 06.01'!$F:$F,"c006x - Insurance firms & pension funds")+SUMIFS('T 06.01'!$P:$P,'T 06.01'!$E:$E,"r0190 - Tax and social security authorities liabilities, if preferred (BRRD art. 44/2/g/iii)",'T 06.01'!$F:$F,"c006x - Insurance firms & pension funds")+SUMIFS('T 03.01'!P:P,'T 03.01'!E:E,"r0190 - Tax and social security authorities liabilities, if preferred (BRRD art. 44/2/g/iii)",'T 03.01'!$F:$F,"c006x - Insurance firms & pension funds")+SUMIFS('T 03.01'!Q:Q,'T 03.01'!E:E,"r0190 - Tax and social security authorities liabilities, if preferred (BRRD art. 44/2/g/iii)",'T 03.01'!$F:$F,"c006x - Insurance firms & pension funds") -> 0 | J18: =+SUMIFS('T 06.01'!$O:$O,'T 06.01'!$E:$E,"r0190 - Tax and social security authorities liabilities, if preferred (BRRD art. 44/2/g/iii)",'T 06.01'!$F:$F,"c008x - Government, central banks & supranationals")+SUMIFS('T 06.01'!$P:$P,'T 06.01'!$E:$E,"r0190 - Tax and social security authorities liabilities, if preferred (BRRD art. 44/2/g/iii)",'T 06.01'!$F:$F,"c008x - Government, central banks & supranationals")+SUMIFS('T 03.01'!P:P,'T 03.01'!E:E,"r0190 - Tax and social security authorities liabilities, if preferred (BRRD art. 44/2/g/iii)",'T 03.01'!$F:$F,"c008x - Government, central banks & supranationals")+SUMIFS('T 03.01'!Q:Q,'T 03.01'!E:E,"r0190 - Tax and social security authorities liabilities, if preferred (BRRD art. 44/2/g/iii)",'T 03.01'!$F:$F,"c008x - Government, central banks & supranationals") -> 3.5330907e+08 | K18: 0 | L18: =+SUMIFS('T 06.01'!$O:$O,'T 06.01'!$E:$E,"r0190 - Tax and social security authorities liabilities, if preferred (BRRD art. 44/2/g/iii)",'T 06.01'!$F:$F,"")+SUMIFS('T 06.01'!$P:$P,'T 06.01'!$E:$E,"r0190 - Tax and social security authorities liabilities, if preferred (BRRD art. 44/2/g/iii)",'T 06.01'!$F:$F,"")+SUMIFS('T 03.01'!P:P,'T 03.01'!E:E,"r0190 - Tax and social security authorities liabilities, if preferred (BRRD art. 44/2/g/iii)",'T 03.01'!$F:$F,"")+SUMIFS('T 03.01'!Q:Q,'T 03.01'!E:E,"r0190 - Tax and social security authorities liabilities, if preferred (BRRD art. 44/2/g/iii)",'T 03.01'!$F:$F,"") -> 0 | M18: =SUM(D18:L18)-I18 -> 3.5330907e+08 | N18: =+SUMIF('T 03.01'!E:E,"r0190 - Tax and social security authorities liabilities, if preferred (BRRD art. 44/2/g/iii)",'T 03.01'!P:P)+SUMIF('T 03.01'!E:E,"r0190 - Tax and social security authorities liabilities, if preferred (BRRD art. 44/2/g/iii)",'T 03.01'!Q:Q) -> 0 | O18: 0
B19: DGS liabilities (BRRD art. 44/2/g/iv) | C19: 0200 | D19: 0 | E19: 0 | F19: 0 | G19: 0 | H19: 0 | I19: 0 | J19: 0 | K19: 0 | L19: 0 | M19: =SUM(D19:L19)-I19 -> 0 | N19: 0 | O19: 0
B20: Liabilities towards other entities of the resolution group (BRRD art. 44/2/h) | C20: 0210 | D20: 0 | E20: 0 | F20: 0 | G20: =SUMIFS('T 03.01'!P:P,'T 03.01'!E:E,"r0210 - Liabilities towards other entities of the resolution group (BRRD art. 44/2/h)",'T 03.01'!$F:$F,"c004x - Institutions")+SUMIFS('T 03.01'!Q:Q,'T 03.01'!E:E,"r0210 - Liabilities towards other entities of the resolution group (BRRD art. 44/2/h)",'T 03.01'!$F:$F,"c004x - Institutions") -> 855362.17 | H20: =I20+SUMIFS('T 03.01'!P:P,'T 03.01'!E:E,"r0210 - Liabilities towards other entities of the resolution group (BRRD art. 44/2/h)",'T 03.01'!$F:$F,"c005x - Other financial corporations")+SUMIFS('T 03.01'!Q:Q,'T 03.01'!E:E,"r0210 - Liabilities towards other entities of the resolution group (BRRD art. 44/2/h)",'T 03.01'!$F:$F,"c005x - Other financial corporations") -> 9.0263696e+08 | I20: =SUMIFS('T 03.01'!P:P,'T 03.01'!E:E,"r0210 - Liabilities towards other entities of the resolution group (BRRD art. 44/2/h)",'T 03.01'!$F:$F,"c006x - Insurance firms & pension funds")+SUMIFS('T 03.01'!Q:Q,'T 03.01'!E:E,"r0210 - Liabilities towards other entities of the resolution group (BRRD art. 44/2/h)",'T 03.01'!$F:$F,"c006x - Insurance firms & pension funds") -> 3.0369526e+08 | J20: 0 | K20: 0 | L20: 0 | M20: =SUM(D20:L20)-I20 -> 9.0349232e+08 | N20: =+SUMIF('T 03.01'!E:E,"r0210 - Liabilities towards other entities of the resolution group (BRRD art. 44/2/h)",'T 03.01'!P:P)+SUMIF('T 03.01'!E:E,"r0210 - Liabilities towards other entities of the resolution group (BRRD art. 44/2/h)",'T 03.01'!Q:Q) -> 9.0349232e+08 | O20: 0
B21: Liabilities not excluded from bail-in | C21: 0300 | D21: =+D22+D27+D32+D33+D38+D43+D53+D58+D61+D62 -> 5.4009898e+09 | E21: =+E22+E27+E32+E33+E38+E43+E53+E58+E61+E62 -> 4.8403554e+09 | F21: =+F22+F27+F32+F33+F38+F43+F53+F58+F61+F62 -> 4.3865153e+09 | G21: =+G22+G27+G32+G33+G38+G43+G53+G58+G61+G62 -> 1.0555008e+09 | H21: =+H22+H27+H32+H33+H38+H43+H53+H58+H61+H62 -> 1.57559e+09 | I21: =+I22+I27+I32+I33+I38+I43+I53+I58+I61+I62 -> 1.1238906e+09 | J21: =+J22+J27+J32+J33+J38+J43+J53+J58+J61+J62 -> 9.0435696e+08 | K21: =+K22+K27+K32+K33+K38+K43+K53+K58+K61+K62 -> 0 | L21: =+L22+L27+L32+L33+L38+L43+L53+L58+L61+L62 -> 3.1330474e+08 | M21: =SUM(D21:L21)-I21 -> 1.8476613e+10 | N21: =+N22+N27+N32+N33+N38+N43+N53+N58+N61+N62 -> 8.8721959e+08 | O21: 0
B22: Deposits, not covered but preferential (BRRD art. 108) | C22: 0310 | D22: =SUM(D23:D26) -> 5.3364929e+09 | E22: =SUM(E23:E26) -> 4.8009797e+09 | F22: =SUM(F23:F26) -> 0 | G22: =SUM(G23:G26) -> 0 | H22: =SUM(H23:H26) -> 0 | I22: =SUM(I23:I26) -> 0 | J22: =SUM(J23:J26) -> 0 | K22: =SUM(K23:K26) -> 0 | L22: =SUM(L23:L26) -> 0 | M22: =SUM(D22:L22)-I23 -> 1.0137473e+10 | N22: =+SUMIF('T 03.01'!E:E,"r0310 - Deposits, not covered but preferential (BRRD art. 108)",'T 03.01'!P:P)+SUMIF('T 03.01'!E:E,"r0310 - Deposits, not covered but preferential (BRRD art. 108)",'T 03.01'!Q:Q) -> 0 | O22: 0
B23: o/w residual maturity <= 1 month | C23: 0311 | D23: =+SUMIFS('T 05.01'!$M:$M,'T 05.01'!$E:$E,"r0310 - Deposits, not covered but preferential (BRRD art. 108)",'T 05.01'!$F:$F,"c001x - Households")+SUMIFS('T 05.01'!$N:$N,'T 05.01'!$E:$E,"r0310 - Deposits, not covered but preferential (BRRD art. 108)",'T 05.01'!$F:$F,"c001x - Households")+SUMIFS('T 03.01'!P:P,'T 03.01'!E:E,"r0310 - Deposits, not covered but preferential (BRRD art. 108)",'T 03.01'!$F:$F,"c001x - Households")+SUMIFS('T 03.01'!Q:Q,'T 03.01'!E:E,"r0310 - Deposits, not covered but preferential (BRRD art. 108)",'T 03.01'!$F:$F,"c001x - Households") -> 5.3364929e+09 | E23: =+SUMIFS('T 05.01'!$M:$M,'T 05.01'!$E:$E,"r0310 - Deposits, not covered but preferential (BRRD art. 108)",'T 05.01'!$F:$F,"c002x - Micro & SME")+SUMIFS('T 05.01'!$N:$N,'T 05.01'!$E:$E,"r0310 - Deposits, not covered but preferential (BRRD art. 108)",'T 05.01'!$F:$F,"c002x - Micro & SME")+SUMIFS('T 03.01'!P:P,'T 03.01'!E:E,"r0310 - Deposits, not covered but preferential (BRRD art. 108)",'T 03.01'!$F:$F,"c002x - Micro & SME")+SUMIFS('T 03.01'!Q:Q,'T 03.01'!E:E,"r0310 - Deposits, not covered but preferential (BRRD art. 108)",'T 03.01'!$F:$F,"c002x - Micro & SME") -> 4.8009797e+09 | F23: =+SUMIFS('T 05.01'!$M:$M,'T 05.01'!$E:$E,"r0310 - Deposits, not covered but preferential (BRRD art. 108)",'T 05.01'!$F:$F,"c003x - Corporates")+SUMIFS('T 05.01'!$N:$N,'T 05.01'!$E:$E,"r0310 - Deposits, not covered but preferential (BRRD art. 108)",'T 05.01'!$F:$F,"c003x - Corporates")+SUMIFS('T 03.01'!P:P,'T 03.01'!E:E,"r0310 - Deposits, not covered but preferential (BRRD art. 108)",'T 03.01'!$F:$F,"c003x - Corporates")+SUMIFS('T 03.01'!Q:Q,'T 03.01'!E:E,"r0310 - Deposits, not covered but preferential (BRRD art. 108)",'T 03.01'!$F:$F,"c003x - Corporates") -> 0 | G23: =+SUMIFS('T 05.01'!$M:$M,'T 05.01'!$E:$E,"r0310 - Deposits, not covered but preferential (BRRD art. 108)",'T 05.01'!$F:$F,"c004x - Institutions")+SUMIFS('T 05.01'!$N:$N,'T 05.01'!$E:$E,"r0310 - Deposits, not covered but preferential (BRRD art. 108)",'T 05.01'!$F:$F,"c004x - Institutions")+SUMIFS('T 03.01'!P:P,'T 03.01'!E:E,"r0310 - Deposits, not covered but preferential (BRRD art. 108)",'T 03.01'!$F:$F,"c004x - Institutions")+SUMIFS('T 03.01'!Q:Q,'T 03.01'!E:E,"r0310 - Deposits, not covered but preferential (BRRD art. 108)",'T 03.01'!$F:$F,"c004x - Institutions") -> 0 | H23: =+SUMIFS('T 05.01'!$M:$M,'T 05.01'!$E:$E,"r0310 - Deposits, not covered but preferential (BRRD art. 108)",'T 05.01'!$F:$F,"c005x - Other financial corporations")+SUMIFS('T 05.01'!$N:$N,'T 05.01'!$E:$E,"r0310 - Deposits, not covered but preferential (BRRD art. 108)",'T 05.01'!$F:$F,"c005x - Other financial corporations")+I23+SUMIFS('T 03.01'!P:P,'T 03.01'!E:E,"r0310 - Deposits, not covered but preferential (BRRD art. 108)",'T 03.01'!$F:$F,"c005x - Other financial corporations")+SUMIFS('T 03.01'!Q:Q,'T 03.01'!E:E,"r0310 - Deposits, not covered but preferential (BRRD art. 108)",'T 03.01'!$F:$F,"c005x - Other financial corporations") -> 0 | I23: =+SUMIFS('T 05.01'!$M:$M,'T 05.01'!$E:$E,"r0310 - Deposits, not covered but preferential (BRRD art. 108)",'T 05.01'!$F:$F,"c006x - Insurance firms & pension funds")+SUMIFS('T 05.01'!$N:$N,'T 05.01'!$E:$E,"r0310 - Deposits, not covered but preferential (BRRD art. 108)",'T 05.01'!$F:$F,"c006x - Insurance firms & pension funds")+SUMIFS('T 03.01'!P:P,'T 03.01'!E:E,"r0310 - Deposits, not covered but preferential (BRRD art. 108)",'T 03.01'!$F:$F,"c006x - Insurance firms & pension funds")+SUMIFS('T 03.01'!Q:Q,'T 03.01'!E:E,"r0310 - Deposits, not covered but preferential (BRRD art. 108)",'T 03.01'!$F:$F,"c006x - Insurance firms & pension funds") -> 0 | J23: =+SUMIFS('T 05.01'!$M:$M,'T 05.01'!$E:$E,"r0310 - Deposits, not covered but preferential (BRRD art. 108)",'T 05.01'!$F:$F,"c008x - Government, central banks & supranationals")+SUMIFS('T 05.01'!$N:$N,'T 05.01'!$E:$E,"r0310 - Deposits, not covered but preferential (BRRD art. 108)",'T 05.01'!$F:$F,"c008x - Government, central banks & supranationals")+SUMIFS('T 03.01'!P:P,'T 03.01'!E:E,"r0310 - Deposits, not covered but preferential (BRRD art. 108)",'T 03.01'!$F:$F,"c008x - Government, central banks & supranationals")+SUMIFS('T 03.01'!Q:Q,'T 03.01'!E:E,"r0310 - Deposits, not covered but preferential (BRRD art. 108)",'T 03.01'!$F:$F,"c008x - Government, central banks & supranationals") -> 0 | K23: 0 | L23: =+SUMIFS('T 05.01'!$M:$M,'T 05.01'!$E:$E,"r0310 - Deposits, not covered but preferential (BRRD art. 108)",'T 05.01'!$F:$F,"")+SUMIFS('T 05.01'!$N:$N,'T 05.01'!$E:$E,"r0310 - Deposits, not covered but preferential (BRRD art. 108)",'T 05.01'!$F:$F,"")+SUMIFS('T 03.01'!P:P,'T 03.01'!E:E,"r0310 - Deposits, not covered but preferential (BRRD art. 108)",'T 03.01'!$F:$F,"")+SUMIFS('T 03.01'!Q:Q,'T 03.01'!E:E,"r0310 - Deposits, not covered but preferential (BRRD art. 108)",'T 03.01'!$F:$F,"") -> 0 | M23: =SUM(D23:L23)-I24 -> 1.0137473e+10 | N23: =+SUMIF('T 03.01'!E:E,"r0310 - Deposits, not covered but preferential (BRRD art. 108)",'T 03.01'!P:P)+SUMIF('T 03.01'!E:E,"r0310 - Deposits, not covered but preferential (BRRD art. 108)",'T 03.01'!Q:Q) -> 0 | O23: 0
B24: o/w residual maturity > 1 month < 1 year | C24: 0312 | D24: 0 | E24: 0 | F24: 0 | G24: 0 | H24: 0 | I24: 0 | J24: 0 | K24: 0 | L24: 0 | M24: =SUM(D24:L24)-I24 -> 0 | N24: 0 | O24: 0
B25: o/w residual maturity >= 1 year and < 2 years | C25: 0313 | D25: 0 | E25: 0 | F25: 0 | G25: 0 | H25: 0 | I25: 0 | J25: 0 | K25: 0 | L25: 0 | M25: =SUM(D25:L25)-I25 -> 0 | N25: 0 | O25: 0
B26: o/w residual maturity >= 2 years | C26: 0314 | D26: 0 | E26: 0 | F26: 0 | G26: 0 | H26: 0 | I26: 0 | J26: 0 | K26: 0 | L26: 0 | M26: =SUM(D26:L26)-I26 -> 0 | N26: 0 | O26: 0
B27: Deposits, not covered and not preferential | C27: 0320 | D27: =SUM(D28:D31) -> 0 | E27: =SUM(E28:E31) -> 1834.98 | F27: =SUM(F28:F31) -> 4.3160092e+09 | G27: =SUM(G28:G31) -> 2.369844e+08 | H27: =SUM(H28:H31) -> 1.2372831e+09 | I27: =SUM(I28:I31) -> 1.1109606e+09 | J27: =SUM(J28:J31) -> 8.8310098e+08 | K27: =SUM(K28:K31) -> 0 | L27: =SUM(L28:L31) -> 0 | M27: =SUM(D27:L27)-I27 -> 6.6733795e+09 | N27: =+SUMIF('T 03.01'!E:E,"r0320 - Deposits, not covered and not preferential",'T 03.01'!P:P)+SUMIF('T 03.01'!E:E,"r0320 - Deposits, not covered and not preferential",'T 03.01'!Q:Q) -> 1.8819345e+08 | O27: 0
B28: o/w residual maturity <= 1 month | C28: 0321 | D28: =+SUMIFS('T 05.01'!$M:$M,'T 05.01'!$E:$E,"r0320 - Deposits, not covered and not preferential",'T 05.01'!$F:$F,"c001x - Households")+SUMIFS('T 05.01'!$N:$N,'T 05.01'!$E:$E,"r0320 - Deposits, not covered and not preferential",'T 05.01'!$F:$F,"c001x - Households")+SUMIFS('T 03.01'!P:P,'T 03.01'!E:E,"r0320 - Deposits, not covered and not preferential",'T 03.01'!$F:$F,"c001x - Households")+SUMIFS('T 03.01'!Q:Q,'T 03.01'!E:E,"r0320 - Deposits, not covered and not preferential",'T 03.01'!$F:$F,"c001x - Households") -> 0 | E28: =+SUMIFS('T 05.01'!$M:$M,'T 05.01'!$E:$E,"r0320 - Deposits, not covered and not preferential",'T 05.01'!$F:$F,"c002x - Micro & SME")+SUMIFS('T 05.01'!$N:$N,'T 05.01'!$E:$E,"r0320 - Deposits, not covered and not preferential",'T 05.01'!$F:$F,"c002x - Micro & SME")+SUMIFS('T 03.01'!P:P,'T 03.01'!E:E,"r0320 - Deposits, not covered and not preferential",'T 03.01'!$F:$F,"c002x - Micro & SME")+SUMIFS('T 03.01'!Q:Q,'T 03.01'!E:E,"r0320 - Deposits, not covered and not preferential",'T 03.01'!$F:$F,"c002x - Micro & SME") -> 1834.98 | F28: =+SUMIFS('T 05.01'!$M:$M,'T 05.01'!$E:$E,"r0320 - Deposits, not covered and not preferential",'T 05.01'!$F:$F,"c003x - Corporates")+SUMIFS('T 05.01'!$N:$N,'T 05.01'!$E:$E,"r0320 - Deposits, not covered and not preferential",'T 05.01'!$F:$F,"c003x - Corporates")+SUMIFS('T 03.01'!P:P,'T 03.01'!E:E,"r0320 - Deposits, not covered and not preferential",'T 03.01'!$F:$F,"c003x - Corporates")+SUMIFS('T 03.01'!Q:Q,'T 03.01'!E:E,"r0320 - Deposits, not covered and not preferential",'T 03.01'!$F:$F,"c003x - Corporates") -> 4.3160092e+09 | G28: =+SUMIFS('T 05.01'!$M:$M,'T 05.01'!$E:$E,"r0320 - Deposits, not covered and not preferential",'T 05.01'!$F:$F,"c004x - Institutions")+SUMIFS('T 05.01'!$N:$N,'T 05.01'!$E:$E,"r0320 - Deposits, not covered and not preferential",'T 05.01'!$F:$F,"c004x - Institutions")+SUMIFS('T 03.01'!P:P,'T 03.01'!E:E,"r0320 - Deposits, not covered and not preferential",'T 03.01'!$F:$F,"c004x - Institutions")+SUMIFS('T 03.01'!Q:Q,'T 03.01'!E:E,"r0320 - Deposits, not covered and not preferential",'T 03.01'!$F:$F,"c004x - Institutions") -> 2.369844e+08 | H28: =+SUMIFS('T 05.01'!$M:$M,'T 05.01'!$E:$E,"r0320 - Deposits, not covered and not preferential",'T 05.01'!$F:$F,"c005x - Other financial corporations")+SUMIFS('T 05.01'!$N:$N,'T 05.01'!$E:$E,"r0320 - Deposits, not covered and not preferential",'T 05.01'!$F:$F,"c005x - Other financial corporations")+I28+SUMIFS('T 03.01'!P:P,'T 03.01'!E:E,"r0320 - Deposits, not covered and not preferential",'T 03.01'!$F:$F,"c005x - Other financial corporations")+SUMIFS('T 03.01'!Q:Q,'T 03.01'!E:E,"r0320 - Deposits, not covered and not preferential",'T 03.01'!$F:$F,"c005x - Other financial corporations") -> 1.2372831e+09 | I28: =+SUMIFS('T 05.01'!$M:$M,'T 05.01'!$E:$E,"r0320 - Deposits, not covered and not preferential",'T 05.01'!$F:$F,"c006x - Insurance firms & pension funds")+SUMIFS('T 05.01'!$N:$N,'T 05.01'!$E:$E,"r0320 - Deposits, not covered and not preferential",'T 05.01'!$F:$F,"c006x - Insurance firms & pension funds")+SUMIFS('T 03.01'!P:P,'T 03.01'!E:E,"r0320 - Deposits, not covered and not preferential",'T 03.01'!$F:$F,"c006x - Insurance firms & pension funds")+SUMIFS('T 03.01'!Q:Q,'T 03.01'!E:E,"r0320 - Deposits, not covered and not preferential",'T 03.01'!$F:$F,"c006x - Insurance firms & pension funds") -> 1.1109606e+09 | J28: =+SUMIFS('T 05.01'!$M:$M,'T 05.01'!$E:$E,"r0320 - Deposits, not covered and not preferential",'T 05.01'!$F:$F,"c008x - Government, central banks & supranationals")+SUMIFS('T 05.01'!$N:$N,'T 05.01'!$E:$E,"r0320 - Deposits, not covered and not preferential",'T 05.01'!$F:$F,"c008x - Government, central banks & supranationals")+SUMIFS('T 03.01'!P:P,'T 03.01'!E:E,"r0320 - Deposits, not covered and not preferential",'T 03.01'!$F:$F,"c008x - Government, central banks & supranationals")+SUMIFS('T 03.01'!Q:Q,'T 03.01'!E:E,"r0320 - Deposits, not covered and not preferential",'T 03.01'!$F:$F,"c008x - Government, central banks & supranationals") -> 8.8310098e+08 | K28: 0 | L28: =+SUMIFS('T 05.01'!$M:$M,'T 05.01'!$E:$E,"r0320 - Deposits, not covered and not preferential",'T 05.01'!$F:$F,"")+SUMIFS('T 05.01'!$N:$N,'T 05.01'!$E:$E,"r0320 - Deposits, not covered and not preferential",'T 05.01'!$F:$F,"")+SUMIFS('T 03.01'!P:P,'T 03.01'!E:E,"r0320 - Deposits, not covered and not preferential",'T 03.01'!$F:$F,"")+SUMIFS('T 03.01'!Q:Q,'T 03.01'!E:E,"r0320 - Deposits, not covered and not preferential",'T 03.01'!$F:$F,"") -> 0 | M28: =SUM(D28:L28)-I28 -> 6.6733795e+09 | N28: =+SUMIF('T 03.01'!E:E,"r0320 - Deposits, not covered and not preferential",'T 03.01'!P:P)+SUMIF('T 03.01'!E:E,"r0320 - Deposits, not covered and not preferential",'T 03.01'!Q:Q) -> 1.8819345e+08 | O28: 0
B29: o/w residual maturity > 1 month < 1 year | C29: 0322 | D29: 0 | E29: 0 | F29: 0 | G29: 0 | H29: 0 | I29: 0 | J29: 0 | K29: 0 | L29: 0 | M29: =SUM(D29:L29)-I29 -> 0 | N29: 0 | O29: 0
B30: o/w residual maturity >= 1 year and < 2 years | C30: 0323 | D30: 0 | E30: 0 | F30: 0 | G30: 0 | H30: 0 | I30: 0 | J30: 0 | K30: 0 | L30: 0 | M30: =SUM(D30:L30)-I30 -> 0 | N30: 0 | O30: 0
B31: o/w residual maturity >= 2 years | C31: 0324 | D31: 0 | E31: 0 | F31: 0 | G31: 0 | H31: 0 | I31: 0 | J31: 0 | K31: 0 | L31: 0 | M31: =SUM(D31:L31)-I31 -> 0 | N31: 0 | O31: 0
B32: Balance sheet liabilities arising from derivatives | C32: 0330 | D32: =SUMIF('T 07.00'!$E:$E,"c001x - Households",'T 07.00'!$R:$R) -> 0 | E32: =SUMIF('T 07.00'!$E:$E,"c002x - Micro & SME",'T 07.00'!$R:$R) -> 146937.32 | F32: =SUMIF('T 07.00'!$E:$E,"c003x - Corporates",'T 07.00'!$R:$R) -> 5065106.2 | G32: =SUMIF('T 07.00'!$E:$E,"c004x - Institutions",'T 07.00'!$R:$R) -> 6.1245005e+08 | H32: =SUMIF('T 07.00'!$E:$E,"c005x - Other financial corporations",'T 07.00'!$R:$R)+I32 -> 2.8177616e+08 | I32: =SUMIF('T 07.00'!$E:$E,"c006x - Insurance firms & pension funds",'T 07.00'!$R:$R) -> 0 | J32: =SUMIF('T 07.00'!$E:$E,"c008x - Government, central banks & supranationals",'T 07.00'!$R:$R) -> 0 | K32: 0 | L32: =SUMIF('T 07.00'!$E:$E,"",'T 07.00'!$R:$R) -> 0 | M32: =SUM(D32:L32)-I32 -> 8.9943825e+08 | N32: =SUMIF('T 07.00'!O:O,"TRUE",'T 07.00'!R:R) -> 6.406435e+08 | O32: 0
B33: Uncollateralized secured liabilities | C33: 0340 | D33: 0 | E33: 0 | F33: 0 | G33: 0 | H33: 0 | I33: 0 | J33: 0 | K33: 0 | L33: 0 | M33: =SUM(D33:L33)-I33 -> 0 | N33: 0 | O33: 0
B34: o/w residual maturity <= 1 month | C34: 0341 | D34: 0 | E34: 0 | F34: 0 | G34: 0 | H34: 0 | I34: 0 | J34: 0 | K34: 0 | L34: 0 | M34: =SUM(D34:L34)-I34 -> 0 | N34: 0 | O34: 0
B35: o/w residual maturity > 1 month < 1 year | C35: 0342 | D35: 0 | E35: 0 | F35: 0 | G35: 0 | H35: 0 | I35: 0 | J35: 0 | K35: 0 | L35: 0 | M35: =SUM(D35:L35)-I35 -> 0 | N35: 0 | O35: 0
B36: o/w residual maturity >= 1 year and < 2 years | C36: 0343 | D36: 0 | E36: 0 | F36: 0 | G36: 0 | H36: 0 | I36: 0 | J36: 0 | K36: 0 | L36: 0 | M36: =SUM(D36:L36)-I36 -> 0 | N36: 0 | O36: 0
B37: o/w residual maturity >= 2 years | C37: 0344 | D37: 0 | E37: 0 | F37: 0 | G37: 0 | H37: 0 | I37: 0 | J37: 0 | K37: 0 | L37: 0 | M37: =SUM(D37:L37)-I37 -> 0 | N37: 0 | O37: 0
B38: Structured notes | C38: 0350 | D38: =SUM(D39:D42) -> 0 | E38: =SUM(E39:E42) -> 0 | F38: =SUM(F39:F42) -> 0 | G38: =SUM(G39:G42) -> 185491750 | H38: =SUM(H39:H42) -> 8395194.5 | I38: =SUM(I39:I42) -> 8395194.5 | J38: =SUM(J39:J42) -> 0 | K38: =SUM(K39:K42) -> 0 | L38: =SUM(L39:L42) -> 0 | M38: =SUM(D38:L38)-I38 -> 1.9388694e+08 | N38: =SUM(N39:N42) -> 8395194.5 | O38: =SUM(O39:O42) -> 0
B39: o/w residual maturity <= 1 month | C39: 0351 | D39: =+SUMIFS('T 04.00'!$N:$N,'T 04.00'!$F:$F,"c001x - Households",'T 04.00'!$E:$E,"r0350 - Structured notes",'T 04.00'!AL:AL,1)+SUMIFS('T 04.00'!$O:$O,'T 04.00'!$F:$F,"c001x - Households",'T 04.00'!$E:$E,"r0350 - Structured notes",'T 04.00'!AL:AL,1)+SUMIFS('T 03.01'!$P:$P,'T 03.01'!$F:$F,"c001x - Households",'T 03.01'!$E:$E,"r0350 - Structured notes",'T 03.01'!$AC:$AC,1)+SUMIFS('T 03.01'!$Q:$Q,'T 03.01'!$F:$F,"c001x - Households",'T 03.01'!$E:$E,"r0350 - Structured notes",'T 03.01'!$AC:$AC,1) -> 0 | E39: =+SUMIFS('T 04.00'!$N:$N,'T 04.00'!$F:$F,"c002x - Micro & SME",'T 04.00'!$E:$E,"r0350 - Structured notes",'T 04.00'!AL:AL,1)+SUMIFS('T 04.00'!$O:$O,'T 04.00'!$F:$F,"c002x - Micro & SME",'T 04.00'!$E:$E,"r0350 - Structured notes",'T 04.00'!AL:AL,1)+SUMIFS('T 03.01'!$P:$P,'T 03.01'!$F:$F,"c002x - Micro & SME",'T 03.01'!$E:$E,"r0350 - Structured notes",'T 03.01'!$AC:$AC,1)+SUMIFS('T 03.01'!$Q:$Q,'T 03.01'!$F:$F,"c002x - Micro & SME",'T 03.01'!$E:$E,"r0350 - Structured notes",'T 03.01'!$AC:$AC,1) -> 0 | F39: =+SUMIFS('T 04.00'!$N:$N,'T 04.00'!$F:$F,"c003x - Corporates",'T 04.00'!$E:$E,"r0350 - Structured notes",'T 04.00'!AL:AL,1)+SUMIFS('T 04.00'!$O:$O,'T 04.00'!$F:$F,"c003x - Corporates",'T 04.00'!$E:$E,"r0350 - Structured notes",'T 04.00'!AL:AL,1)+SUMIFS('T 03.01'!$P:$P,'T 03.01'!$F:$F,"c003x - Corporates",'T 03.01'!$E:$E,"r0350 - Structured notes",'T 03.01'!$AC:$AC,1)+SUMIFS('T 03.01'!$Q:$Q,'T 03.01'!$F:$F,"c003x - Corporates",'T 03.01'!$E:$E,"r0350 - Structured notes",'T 03.01'!$AC:$AC,1) -> 0 | G39: =+SUMIFS('T 04.00'!$N:$N,'T 04.00'!$F:$F,"c004x - Institutions",'T 04.00'!$E:$E,"r0350 - Structured notes",'T 04.00'!AL:AL,1)+SUMIFS('T 04.00'!$O:$O,'T 04.00'!$F:$F,"c004x - Institutions",'T 04.00'!$E:$E,"r0350 - Structured notes",'T 04.00'!AL:AL,1)+SUMIFS('T 03.01'!$P:$P,'T 03.01'!$F:$F,"c004x - Institutions",'T 03.01'!$E:$E,"r0350 - Structured notes",'T 03.01'!$AC:$AC,1)+SUMIFS('T 03.01'!$Q:$Q,'T 03.01'!$F:$F,"c004x - Institutions",'T 03.01'!$E:$E,"r0350 - Structured notes",'T 03.01'!$AC:$AC,1) -> 0 | H39: =+SUMIFS('T 04.00'!$N:$N,'T 04.00'!$F:$F,"c005x - Other financial corporations",'T 04.00'!$E:$E,"r0350 - Structured notes",'T 04.00'!AL:AL,1)+SUMIFS('T 04.00'!$O:$O,'T 04.00'!$F:$F,"c005x - Other financial corporations",'T 04.00'!$E:$E,"r0350 - Structured notes",'T 04.00'!AL:AL,1)+SUMIFS('T 03.01'!$P:$P,'T 03.01'!$F:$F,"c005x - Other financial corporations",'T 03.01'!$E:$E,"r0350 - Structured notes",'T 03.01'!$AC:$AC,1)+SUMIFS('T 03.01'!$Q:$Q,'T 03.01'!$F:$F,"c005x - Other financial corporations",'T 03.01'!$E:$E,"r0350 - Structured notes",'T 03.01'!$AC:$AC,1)+I39 -> 0 | I39: =+SUMIFS('T 04.00'!$N:$N,'T 04.00'!$F:$F,"c006x - Insurance firms & pension funds",'T 04.00'!$E:$E,"r0350 - Structured notes",'T 04.00'!AL:AL,1)+SUMIFS('T 04.00'!$O:$O,'T 04.00'!$F:$F,"c006x - Insurance firms & pension funds",'T 04.00'!$E:$E,"r0350 - Structured notes",'T 04.00'!AL:AL,1)+SUMIFS('T 03.01'!$P:$P,'T 03.01'!$F:$F,"c006x - Insurance firms & pension funds",'T 03.01'!$E:$E,"r0350 - Structured notes",'T 03.01'!$AC:$AC,1)+SUMIFS('T 03.01'!$Q:$Q,'T 03.01'!$F:$F,"c006x - Insurance firms & pension funds",'T 03.01'!$E:$E,"r0350 - Structured notes",'T 03.01'!$AC:$AC,1) -> 0 | J39: =+SUMIFS('T 04.00'!$N:$N,'T 04.00'!$F:$F,"c008x - Government, central banks & supranationals",'T 04.00'!$E:$E,"r0350 - Structured notes",'T 04.00'!AL:AL,1)+SUMIFS('T 04.00'!$O:$O,'T 04.00'!$F:$F,"c008x - Government, central banks & supranationals",'T 04.00'!$E:$E,"r0350 - Structured notes",'T 04.00'!AL:AL,1)+SUMIFS('T 03.01'!$P:$P,'T 03.01'!$F:$F,"c008x - Government, central banks & supranationals",'T 03.01'!$E:$E,"r0350 - Structured notes",'T 03.01'!$AC:$AC,1)+SUMIFS('T 03.01'!$Q:$Q,'T 03.01'!$F:$F,"c008x - Government, central banks & supranationals",'T 03.01'!$E:$E,"r0350 - Structured notes",'T 03.01'!$AC:$AC,1) -> 0 | K39: 0 | L39: =+SUMIFS('T 04.00'!$N:$N,'T 04.00'!$F:$F,"",'T 04.00'!$E:$E,"r0350 - Structured notes",'T 04.00'!AL:AL,1)+SUMIFS('T 04.00'!$O:$O,'T 04.00'!$F:$F,"",'T 04.00'!$E:$E,"r0350 - Structured notes",'T 04.00'!AL:AL,1)+SUMIFS('T 03.01'!$P:$P,'T 03.01'!$F:$F,"",'T 03.01'!$E:$E,"r0350 - Structured notes",'T 03.01'!$AC:$AC,1)+SUMIFS('T 03.01'!$Q:$Q,'T 03.01'!$F:$F,"",'T 03.01'!$E:$E,"r0350 - Structured notes",'T 03.01'!$AC:$AC,1) -> 0 | M39: =SUM(D39:L39)-I39 -> 0 | N39: =SUMIFS('T 03.01'!$P:$P,'T 03.01'!$E:$E,"r0350 - Structured notes",'T 03.01'!AC:AC,1)+SUMIFS('T 03.01'!$Q:$Q,'T 03.01'!$E:$E,"r0350 - Structured notes",'T 03.01'!AC:AC,1) -> 0 | O39: 0
B40: o/w residual maturity > 1 month < 1 year | C40: 0352 | D40: =+SUMIFS('T 04.00'!$N:$N,'T 04.00'!$F:$F,"c001x - Households",'T 04.00'!$E:$E,"r0350 - Structured notes",'T 04.00'!AL:AL,2)+SUMIFS('T 04.00'!$O:$O,'T 04.00'!$F:$F,"c001x - Households",'T 04.00'!$E:$E,"r0350 - Structured notes",'T 04.00'!AL:AL,2)+SUMIFS('T 03.01'!$P:$P,'T 03.01'!$F:$F,"c001x - Households",'T 03.01'!$E:$E,"r0350 - Structured notes",'T 03.01'!$AC:$AC,2)+SUMIFS('T 03.01'!$Q:$Q,'T 03.01'!$F:$F,"c001x - Households",'T 03.01'!$E:$E,"r0350 - Structured notes",'T 03.01'!$AC:$AC,2) -> 0 | E40: =+SUMIFS('T 04.00'!$N:$N,'T 04.00'!$F:$F,"c002x - Micro & SME",'T 04.00'!$E:$E,"r0350 - Structured notes",'T 04.00'!AL:AL,2)+SUMIFS('T 04.00'!$O:$O,'T 04.00'!$F:$F,"c002x - Micro & SME",'T 04.00'!$E:$E,"r0350 - Structured notes",'T 04.00'!AL:AL,2)+SUMIFS('T 03.01'!$P:$P,'T 03.01'!$F:$F,"c002x - Micro & SME",'T 03.01'!$E:$E,"r0350 - Structured notes",'T 03.01'!$AC:$AC,2)+SUMIFS('T 03.01'!$Q:$Q,'T 03.01'!$F:$F,"c002x - Micro & SME",'T 03.01'!$E:$E,"r0350 - Structured notes",'T 03.01'!$AC:$AC,2) -> 0 | F40: =+SUMIFS('T 04.00'!$N:$N,'T 04.00'!$F:$F,"c003x - Corporates",'T 04.00'!$E:$E,"r0350 - Structured notes",'T 04.00'!AL:AL,2)+SUMIFS('T 04.00'!$O:$O,'T 04.00'!$F:$F,"c003x - Corporates",'T 04.00'!$E:$E,"r0350 - Structured notes",'T 04.00'!AL:AL,2)+SUMIFS('T 03.01'!$P:$P,'T 03.01'!$F:$F,"c003x - Corporates",'T 03.01'!$E:$E,"r0350 - Structured notes",'T 03.01'!$AC:$AC,2)+SUMIFS('T 03.01'!$Q:$Q,'T 03.01'!$F:$F,"c003x - Corporates",'T 03.01'!$E:$E,"r0350 - Structured notes",'T 03.01'!$AC:$AC,2) -> 0 | G40: =+SUMIFS('T 04.00'!$N:$N,'T 04.00'!$F:$F,"c004x - Institutions",'T 04.00'!$E:$E,"r0350 - Structured notes",'T 04.00'!AL:AL,2)+SUMIFS('T 04.00'!$O:$O,'T 04.00'!$F:$F,"c004x - Institutions",'T 04.00'!$E:$E,"r0350 - Structured notes",'T 04.00'!AL:AL,2)+SUMIFS('T 03.01'!$P:$P,'T 03.01'!$F:$F,"c004x - Institutions",'T 03.01'!$E:$E,"r0350 - Structured notes",'T 03.01'!$AC:$AC,2)+SUMIFS('T 03.01'!$Q:$Q,'T 03.01'!$F:$F,"c004x - Institutions",'T 03.01'!$E:$E,"r0350 - Structured notes",'T 03.01'!$AC:$AC,2) -> 0 | H40: =+SUMIFS('T 04.00'!$N:$N,'T 04.00'!$F:$F,"c005x - Other financial corporations",'T 04.00'!$E:$E,"r0350 - Structured notes",'T 04.00'!AL:AL,2)+SUMIFS('T 04.00'!$O:$O,'T 04.00'!$F:$F,"c005x - Other financial corporations",'T 04.00'!$E:$E,"r0350 - Structured notes",'T 04.00'!AL:AL,2)+SUMIFS('T 03.01'!$P:$P,'T 03.01'!$F:$F,"c005x - Other financial corporations",'T 03.01'!$E:$E,"r0350 - Structured notes",'T 03.01'!$AC:$AC,2)+SUMIFS('T 03.01'!$Q:$Q,'T 03.01'!$F:$F,"c005x - Other financial corporations",'T 03.01'!$E:$E,"r0350 - Structured notes",'T 03.01'!$AC:$AC,2)+I40 -> 0 | I40: =+SUMIFS('T 04.00'!$N:$N,'T 04.00'!$F:$F,"c006x - Insurance firms & pension funds",'T 04.00'!$E:$E,"r0350 - Structured notes",'T 04.00'!AL:AL,2)+SUMIFS('T 04.00'!$O:$O,'T 04.00'!$F:$F,"c006x - Insurance firms & pension funds",'T 04.00'!$E:$E,"r0350 - Structured notes",'T 04.00'!AL:AL,2)+SUMIFS('T 03.01'!$P:$P,'T 03.01'!$F:$F,"c006x - Insurance firms & pension funds",'T 03.01'!$E:$E,"r0350 - Structured notes",'T 03.01'!$AC:$AC,2)+SUMIFS('T 03.01'!$Q:$Q,'T 03.01'!$F:$F,"c006x - Insurance firms & pension funds",'T 03.01'!$E:$E,"r0350 - Structured notes",'T 03.01'!$AC:$AC,2) -> 0 | J40: =+SUMIFS('T 04.00'!$N:$N,'T 04.00'!$F:$F,"c008x - Government, central banks & supranationals",'T 04.00'!$E:$E,"r0350 - Structured notes",'T 04.00'!AL:AL,2)+SUMIFS('T 04.00'!$O:$O,'T 04.00'!$F:$F,"c008x - Government, central banks & supranationals",'T 04.00'!$E:$E,"r0350 - Structured notes",'T 04.00'!AL:AL,2)+SUMIFS('T 03.01'!$P:$P,'T 03.01'!$F:$F,"c008x - Government, central banks & supranationals",'T 03.01'!$E:$E,"r0350 - Structured notes",'T 03.01'!$AC:$AC,2)+SUMIFS('T 03.01'!$Q:$Q,'T 03.01'!$F:$F,"c008x - Government, central banks & supranationals",'T 03.01'!$E:$E,"r0350 - Structured notes",'T 03.01'!$AC:$AC,2) -> 0 | K40: 0 | L40: =+SUMIFS('T 04.00'!$N:$N,'T 04.00'!$F:$F,"",'T 04.00'!$E:$E,"r0350 - Structured notes",'T 04.00'!AL:AL,2)+SUMIFS('T 04.00'!$O:$O,'T 04.00'!$F:$F,"",'T 04.00'!$E:$E,"r0350 - Structured notes",'T 04.00'!AL:AL,2)+SUMIFS('T 03.01'!$P:$P,'T 03.01'!$F:$F,"",'T 03.01'!$E:$E,"r0350 - Structured notes",'T 03.01'!$AC:$AC,2)+SUMIFS('T 03.01'!$Q:$Q,'T 03.01'!$F:$F,"",'T 03.01'!$E:$E,"r0350 - Structured notes",'T 03.01'!$AC:$AC,2) -> 0 | M40: =SUM(D40:L40)-I40 -> 0 | N40: =SUMIFS('T 03.01'!$P:$P,'T 03.01'!$E:$E,"r0350 - Structured notes",'T 03.01'!AC:AC,2)+SUMIFS('T 03.01'!$Q:$Q,'T 03.01'!$E:$E,"r0350 - Structured notes",'T 03.01'!AC:AC,2) -> 0 | O40: 0
B41: o/w residual maturity >= 1 year and < 2 years | C41: 0353 | D41: =+SUMIFS('T 04.00'!$N:$N,'T 04.00'!$F:$F,"c001x - Households",'T 04.00'!$E:$E,"r0350 - Structured notes",'T 04.00'!AL:AL,3)+SUMIFS('T 04.00'!$O:$O,'T 04.00'!$F:$F,"c001x - Households",'T 04.00'!$E:$E,"r0350 - Structured notes",'T 04.00'!AL:AL,3)+SUMIFS('T 03.01'!$P:$P,'T 03.01'!$F:$F,"c001x - Households",'T 03.01'!$E:$E,"r0350 - Structured notes",'T 03.01'!$AC:$AC,3)+SUMIFS('T 03.01'!$Q:$Q,'T 03.01'!$F:$F,"c001x - Households",'T 03.01'!$E:$E,"r0350 - Structured notes",'T 03.01'!$AC:$AC,3) -> 0 | E41: =+SUMIFS('T 04.00'!$N:$N,'T 04.00'!$F:$F,"c002x - Micro & SME",'T 04.00'!$E:$E,"r0350 - Structured notes",'T 04.00'!AL:AL,3)+SUMIFS('T 04.00'!$O:$O,'T 04.00'!$F:$F,"c002x - Micro & SME",'T 04.00'!$E:$E,"r0350 - Structured notes",'T 04.00'!AL:AL,3)+SUMIFS('T 03.01'!$P:$P,'T 03.01'!$F:$F,"c002x - Micro & SME",'T 03.01'!$E:$E,"r0350 - Structured notes",'T 03.01'!$AC:$AC,3)+SUMIFS('T 03.01'!$Q:$Q,'T 03.01'!$F:$F,"c002x - Micro & SME",'T 03.01'!$E:$E,"r0350 - Structured notes",'T 03.01'!$AC:$AC,3) -> 0 | F41: =+SUMIFS('T 04.00'!$N:$N,'T 04.00'!$F:$F,"c003x - Corporates",'T 04.00'!$E:$E,"r0350 - Structured notes",'T 04.00'!AL:AL,3)+SUMIFS('T 04.00'!$O:$O,'T 04.00'!$F:$F,"c003x - Corporates",'T 04.00'!$E:$E,"r0350 - Structured notes",'T 04.00'!AL:AL,3)+SUMIFS('T 03.01'!$P:$P,'T 03.01'!$F:$F,"c003x - Corporates",'T 03.01'!$E:$E,"r0350 - Structured notes",'T 03.01'!$AC:$AC,3)+SUMIFS('T 03.01'!$Q:$Q,'T 03.01'!$F:$F,"c003x - Corporates",'T 03.01'!$E:$E,"r0350 - Structured notes",'T 03.01'!$AC:$AC,3) -> 0 | G41: =+SUMIFS('T 04.00'!$N:$N,'T 04.00'!$F:$F,"c004x - Institutions",'T 04.00'!$E:$E,"r0350 - Structured notes",'T 04.00'!AL:AL,3)+SUMIFS('T 04.00'!$O:$O,'T 04.00'!$F:$F,"c004x - Institutions",'T 04.00'!$E:$E,"r0350 - Structured notes",'T 04.00'!AL:AL,3)+SUMIFS('T 03.01'!$P:$P,'T 03.01'!$F:$F,"c004x - Institutions",'T 03.01'!$E:$E,"r0350 - Structured notes",'T 03.01'!$AC:$AC,3)+SUMIFS('T 03.01'!$Q:$Q,'T 03.01'!$F:$F,"c004x - Institutions",'T 03.01'!$E:$E,"r0350 - Structured notes",'T 03.01'!$AC:$AC,3) -> 0 | H41: =+SUMIFS('T 04.00'!$N:$N,'T 04.00'!$F:$F,"c005x - Other financial corporations",'T 04.00'!$E:$E,"r0350 - Structured notes",'T 04.00'!AL:AL,3)+SUMIFS('T 04.00'!$O:$O,'T 04.00'!$F:$F,"c005x - Other financial corporations",'T 04.00'!$E:$E,"r0350 - Structured notes",'T 04.00'!AL:AL,3)+SUMIFS('T 03.01'!$P:$P,'T 03.01'!$F:$F,"c005x - Other financial corporations",'T 03.01'!$E:$E,"r0350 - Structured notes",'T 03.01'!$AC:$AC,3)+SUMIFS('T 03.01'!$Q:$Q,'T 03.01'!$F:$F,"c005x - Other financial corporations",'T 03.01'!$E:$E,"r0350 - Structured notes",'T 03.01'!$AC:$AC,3)+I41 -> 0 | I41: =+SUMIFS('T 04.00'!$N:$N,'T 04.00'!$F:$F,"c006x - Insurance firms & pension funds",'T 04.00'!$E:$E,"r0350 - Structured notes",'T 04.00'!AL:AL,3)+SUMIFS('T 04.00'!$O:$O,'T 04.00'!$F:$F,"c006x - Insurance firms & pension funds",'T 04.00'!$E:$E,"r0350 - Structured notes",'T 04.00'!AL:AL,3)+SUMIFS('T 03.01'!$P:$P,'T 03.01'!$F:$F,"c006x - Insurance firms & pension funds",'T 03.01'!$E:$E,"r0350 - Structured notes",'T 03.01'!$AC:$AC,3)+SUMIFS('T 03.01'!$Q:$Q,'T 03.01'!$F:$F,"c006x - Insurance firms & pension funds",'T 03.01'!$E:$E,"r0350 - Structured notes",'T 03.01'!$AC:$AC,3) -> 0 | J41: =+SUMIFS('T 04.00'!$N:$N,'T 04.00'!$F:$F,"c008x - Government, central banks & supranationals",'T 04.00'!$E:$E,"r0350 - Structured notes",'T 04.00'!AL:AL,3)+SUMIFS('T 04.00'!$O:$O,'T 04.00'!$F:$F,"c008x - Government, central banks & supranationals",'T 04.00'!$E:$E,"r0350 - Structured notes",'T 04.00'!AL:AL,3)+SUMIFS('T 03.01'!$P:$P,'T 03.01'!$F:$F,"c008x - Government, central banks & supranationals",'T 03.01'!$E:$E,"r0350 - Structured notes",'T 03.01'!$AC:$AC,3)+SUMIFS('T 03.01'!$Q:$Q,'T 03.01'!$F:$F,"c008x - Government, central banks & supranationals",'T 03.01'!$E:$E,"r0350 - Structured notes",'T 03.01'!$AC:$AC,3) -> 0 | K41: 0 | L41: =+SUMIFS('T 04.00'!$N:$N,'T 04.00'!$F:$F,"",'T 04.00'!$E:$E,"r0350 - Structured notes",'T 04.00'!AL:AL,3)+SUMIFS('T 04.00'!$O:$O,'T 04.00'!$F:$F,"",'T 04.00'!$E:$E,"r0350 - Structured notes",'T 04.00'!AL:AL,3)+SUMIFS('T 03.01'!$P:$P,'T 03.01'!$F:$F,"",'T 03.01'!$E:$E,"r0350 - Structured notes",'T 03.01'!$AC:$AC,3)+SUMIFS('T 03.01'!$Q:$Q,'T 03.01'!$F:$F,"",'T 03.01'!$E:$E,"r0350 - Structured notes",'T 03.01'!$AC:$AC,3) -> 0 | M41: =SUM(D41:L41)-I41 -> 0 | N41: =SUMIFS('T 03.01'!$P:$P,'T 03.01'!$E:$E,"r0350 - Structured notes",'T 03.01'!AC:AC,3)+SUMIFS('T 03.01'!$Q:$Q,'T 03.01'!$E:$E,"r0350 - Structured notes",'T 03.01'!AC:AC,3) -> 0 | O41: 0
B42: o/w residual maturity >= 2 years | C42: 0354 | D42: =+SUMIFS('T 04.00'!$N:$N,'T 04.00'!$F:$F,"c001x - Households",'T 04.00'!$E:$E,"r0350 - Structured notes",'T 04.00'!AL:AL,4)+SUMIFS('T 04.00'!$O:$O,'T 04.00'!$F:$F,"c001x - Households",'T 04.00'!$E:$E,"r0350 - Structured notes",'T 04.00'!AL:AL,4)+SUMIFS('T 03.01'!$P:$P,'T 03.01'!$F:$F,"c001x - Households",'T 03.01'!$E:$E,"r0350 - Structured notes",'T 03.01'!$AC:$AC,4)+SUMIFS('T 03.01'!$Q:$Q,'T 03.01'!$F:$F,"c001x - Households",'T 03.01'!$E:$E,"r0350 - Structured notes",'T 03.01'!$AC:$AC,4) -> 0 | E42: =+SUMIFS('T 04.00'!$N:$N,'T 04.00'!$F:$F,"c002x - Micro & SME",'T 04.00'!$E:$E,"r0350 - Structured notes",'T 04.00'!AL:AL,4)+SUMIFS('T 04.00'!$O:$O,'T 04.00'!$F:$F,"c002x - Micro & SME",'T 04.00'!$E:$E,"r0350 - Structured notes",'T 04.00'!AL:AL,4)+SUMIFS('T 03.01'!$P:$P,'T 03.01'!$F:$F,"c002x - Micro & SME",'T 03.01'!$E:$E,"r0350 - Structured notes",'T 03.01'!$AC:$AC,4)+SUMIFS('T 03.01'!$Q:$Q,'T 03.01'!$F:$F,"c002x - Micro & SME",'T 03.01'!$E:$E,"r0350 - Structured notes",'T 03.01'!$AC:$AC,4) -> 0 | F42: =+SUMIFS('T 04.00'!$N:$N,'T 04.00'!$F:$F,"c003x - Corporates",'T 04.00'!$E:$E,"r0350 - Structured notes",'T 04.00'!AL:AL,4)+SUMIFS('T 04.00'!$O:$O,'T 04.00'!$F:$F,"c003x - Corporates",'T 04.00'!$E:$E,"r0350 - Structured notes",'T 04.00'!AL:AL,4)+SUMIFS('T 03.01'!$P:$P,'T 03.01'!$F:$F,"c003x - Corporates",'T 03.01'!$E:$E,"r0350 - Structured notes",'T 03.01'!$AC:$AC,4)+SUMIFS('T 03.01'!$Q:$Q,'T 03.01'!$F:$F,"c003x - Corporates",'T 03.01'!$E:$E,"r0350 - Structured notes",'T 03.01'!$AC:$AC,4) -> 0 | G42: =+SUMIFS('T 04.00'!$N:$N,'T 04.00'!$F:$F,"c004x - Institutions",'T 04.00'!$E:$E,"r0350 - Structured notes",'T 04.00'!AL:AL,4)+SUMIFS('T 04.00'!$O:$O,'T 04.00'!$F:$F,"c004x - Institutions",'T 04.00'!$E:$E,"r0350 - Structured notes",'T 04.00'!AL:AL,4)+SUMIFS('T 03.01'!$P:$P,'T 03.01'!$F:$F,"c004x - Institutions",'T 03.01'!$E:$E,"r0350 - Structured notes",'T 03.01'!$AC:$AC,4)+SUMIFS('T 03.01'!$Q:$Q,'T 03.01'!$F:$F,"c004x - Institutions",'T 03.01'!$E:$E,"r0350 - Structured notes",'T 03.01'!$AC:$AC,4) -> 185491750 | H42: =+SUMIFS('T 04.00'!$N:$N,'T 04.00'!$F:$F,"c005x - Other financial corporations",'T 04.00'!$E:$E,"r0350 - Structured notes",'T 04.00'!AL:AL,4)+SUMIFS('T 04.00'!$O:$O,'T 04.00'!$F:$F,"c005x - Other financial corporations",'T 04.00'!$E:$E,"r0350 - Structured notes",'T 04.00'!AL:AL,4)+SUMIFS('T 03.01'!$P:$P,'T 03.01'!$F:$F,"c005x - Other financial corporations",'T 03.01'!$E:$E,"r0350 - Structured notes",'T 03.01'!$AC:$AC,4)+SUMIFS('T 03.01'!$Q:$Q,'T 03.01'!$F:$F,"c005x - Other financial corporations",'T 03.01'!$E:$E,"r0350 - Structured notes",'T 03.01'!$AC:$AC,4)+I42 -> 8395194.5 | I42: =+SUMIFS('T 04.00'!$N:$N,'T 04.00'!$F:$F,"c006x - Insurance firms & pension funds",'T 04.00'!$E:$E,"r0350 - Structured notes",'T 04.00'!AL:AL,4)+SUMIFS('T 04.00'!$O:$O,'T 04.00'!$F:$F,"c006x - Insurance firms & pension funds",'T 04.00'!$E:$E,"r0350 - Structured notes",'T 04.00'!AL:AL,4)+SUMIFS('T 03.01'!$P:$P,'T 03.01'!$F:$F,"c006x - Insurance firms & pension funds",'T 03.01'!$E:$E,"r0350 - Structured notes",'T 03.01'!$AC:$AC,4)+SUMIFS('T 03.01'!$Q:$Q,'T 03.01'!$F:$F,"c006x - Insurance firms & pension funds",'T 03.01'!$E:$E,"r0350 - Structured notes",'T 03.01'!$AC:$AC,4) -> 8395194.5 | J42: =+SUMIFS('T 04.00'!$N:$N,'T 04.00'!$F:$F,"c008x - Government, central banks & supranationals",'T 04.00'!$E:$E,"r0350 - Structured notes",'T 04.00'!AL:AL,4)+SUMIFS('T 04.00'!$O:$O,'T 04.00'!$F:$F,"c008x - Government, central banks & supranationals",'T 04.00'!$E:$E,"r0350 - Structured notes",'T 04.00'!AL:AL,4)+SUMIFS('T 03.01'!$P:$P,'T 03.01'!$F:$F,"c008x - Government, central banks & supranationals",'T 03.01'!$E:$E,"r0350 - Structured notes",'T 03.01'!$AC:$AC,4)+SUMIFS('T 03.01'!$Q:$Q,'T 03.01'!$F:$F,"c008x - Government, central banks & supranationals",'T 03.01'!$E:$E,"r0350 - Structured notes",'T 03.01'!$AC:$AC,4) -> 0 | K42: 0 | L42: =+SUMIFS('T 04.00'!$N:$N,'T 04.00'!$F:$F,"",'T 04.00'!$E:$E,"r0350 - Structured notes",'T 04.00'!AL:AL,4)+SUMIFS('T 04.00'!$O:$O,'T 04.00'!$F:$F,"",'T 04.00'!$E:$E,"r0350 - Structured notes",'T 04.00'!AL:AL,4)+SUMIFS('T 03.01'!$P:$P,'T 03.01'!$F:$F,"",'T 03.01'!$E:$E,"r0350 - Structured notes",'T 03.01'!$AC:$AC,4)+SUMIFS('T 03.01'!$Q:$Q,'T 03.01'!$F:$F,"",'T 03.01'!$E:$E,"r0350 - Structured notes",'T 03.01'!$AC:$AC,4) -> 0 | M42: =SUM(D42:L42)-I42 -> 1.9388694e+08 | N42: =SUMIFS('T 03.01'!$P:$P,'T 03.01'!$E:$E,"r0350 - Structured notes",'T 03.01'!AC:AC,4)+SUMIFS('T 03.01'!$Q:$Q,'T 03.01'!$E:$E,"r0350 - Structured notes",'T 03.01'!AC:AC,4) -> 8395194.5 | O42: 0
B43: Senior unsecured liabilities | C43: 0360 | D43: =+SUM(D44:D47) -> 0 | E43: 0 | F43: 0 | G43: 0 | H43: 0 | I43: 0 | J43: 0 | K43: 0 | L43: 0 | M43: =SUM(D43:L43)-I43 -> 0 | N43: =+SUM(N44:N47) -> 0 | O43: 0
B44: o/w residual maturity <= 1 month | C44: 0361 | D44: 0 | E44: 0 | F44: 0 | G44: 0 | H44: 0 | I44: 0 | J44: 0 | K44: 0 | L44: 0 | M44: =SUM(D44:L44)-I44 -> 0 | N44: 0 | O44: 0
B45: o/w residual maturity > 1 month < 1 year | C45: 0362 | D45: 0 | E45: 0 | F45: 0 | G45: 0 | H45: 0 | I45: 0 | J45: 0 | K45: 0 | L45: 0 | M45: =SUM(D45:L45)-I45 -> 0 | N45: 0 | O45: 0
B46: o/w residual maturity >= 1 year and < 2 years | C46: 0363 | D46: 0 | E46: 0 | F46: 0 | G46: 0 | H46: 0 | I46: 0 | J46: 0 | K46: 0 | L46: 0 | M46: =SUM(D46:L46)-I46 -> 0 | N46: 0 | O46: 0
B47: o/w residual maturity >= 2 years | C47: 0364 | D47: 0 | E47: 0 | F47: 0 | G47: 0 | H47: 0 | I47: 0 | J47: 0 | K47: 0 | L47: 0 | M47: =SUM(D47:L47)-I47 -> 0 | N47: 0 | O47: 0
B48: Senior non-preferred liabilities | C48: 0365 | D48: =+SUM(D49:D52) -> 0 | E48: 0 | F48: 0 | G48: 0 | H48: 0 | I48: 0 | J48: 0 | K48: 0 | L48: 0 | M48: =SUM(D48:L48)-I48 -> 0 | N48: 0 | O48: 0
B49: Of which: residual maturity <= 1 month | C49: 0366 | D49: 0 | E49: 0 | F49: 0 | G49: 0 | H49: 0 | I49: 0 | J49: 0 | K49: 0 | L49: 0 | M49: =SUM(D49:L49)-I49 -> 0 | N49: 0 | O49: 0
B50: Of which: residual maturity > 1 month < 1 year | C50: 0367 | D50: 0 | E50: 0 | F50: 0 | G50: 0 | H50: 0 | I50: 0 | J50: 0 | K50: 0 | L50: 0 | M50: =SUM(D50:L50)-I50 -> 0 | N50: 0 | O50: 0
B51: Of which: residual maturity >= 1 year and < 2 years | C51: 0368 | D51: 0 | E51: 0 | F51: 0 | G51: 0 | H51: 0 | I51: 0 | J51: 0 | K51: 0 | L51: 0 | M51: =SUM(D51:L51)-I51 -> 0 | N51: 0 | O51: 0
B52: Of which: residual maturity >= 2 years | C52: 0369 | D52: 0 | E52: 0 | F52: 0 | G52: 0 | H52: 0 | I52: 0 | J52: 0 | K52: 0 | L52: 0 | M52: =SUM(D52:L52)-I52 -> 0 | N52: 0 | O52: 0
B53: Subordinated liabilities (not recognised as own funds) | C53: 0370 | D53: =+SUM(D54:D57) -> 0 | E53: =+SUM(E54:E57) -> 0 | F53: =+SUM(F54:F57) -> 0 | G53: =+SUM(G54:G57) -> 0 | H53: =+SUM(H54:H57) -> 0 | I53: =+SUM(I54:I57) -> 0 | J53: =+SUM(J54:J57) -> 0 | K53: =+SUM(K54:K57) -> 0 | L53: =+SUM(L54:L57) -> 0 | M53: =SUM(D53:L53)-I53 -> 0 | N53: =+SUM(N54:N57) -> 0 | O53: 0
B54: o/w residual maturity <= 1 month | C54: 0371 | D54: =SUMIFS('T 03.01'!$P:$P,'T 03.01'!$F:$F,"c001x - Households",'T 03.01'!$E:$E,"r0370 - Subordinated liabilities (not recognised as own funds)",'T 03.01'!$AC:$AC,1)+SUMIFS('T 03.01'!$Q:$Q,'T 03.01'!$F:$F,"c001x - Households",'T 03.01'!$E:$E,"r0370 - Subordinated liabilities (not recognised as own funds)",'T 03.01'!$AC:$AC,1) -> 0 | E54: =SUMIFS('T 03.01'!$P:$P,'T 03.01'!$F:$F,"c002x - Micro & SME",'T 03.01'!$E:$E,"r0370 - Subordinated liabilities (not recognised as own funds)",'T 03.01'!AC:AC,1)+SUMIFS('T 03.01'!$Q:$Q,'T 03.01'!$F:$F,"c002x - Micro & SME",'T 03.01'!$E:$E,"r0370 - Subordinated liabilities (not recognised as own funds)",'T 03.01'!AC:AC,1) -> 0 | F54: =SUMIFS('T 03.01'!$P:$P,'T 03.01'!$F:$F,"c003x - Corporates",'T 03.01'!$E:$E,"r0370 - Subordinated liabilities (not recognised as own funds)",'T 03.01'!AC:AC,1)+SUMIFS('T 03.01'!$Q:$Q,'T 03.01'!$F:$F,"c003x - Corporates",'T 03.01'!$E:$E,"r0370 - Subordinated liabilities (not recognised as own funds)",'T 03.01'!AC:AC,1) -> 0 | G54: =SUMIFS('T 03.01'!$P:$P,'T 03.01'!$F:$F,"c004x - Institutions",'T 03.01'!$E:$E,"r0370 - Subordinated liabilities (not recognised as own funds)",'T 03.01'!AC:AC,1)+SUMIFS('T 03.01'!$Q:$Q,'T 03.01'!$F:$F,"c004x - Institutions",'T 03.01'!$E:$E,"r0370 - Subordinated liabilities (not recognised as own funds)",'T 03.01'!AC:AC,1) -> 0 | H54: =SUMIFS('T 03.01'!$P:$P,'T 03.01'!$F:$F,"c005x - Other financial corporations",'T 03.01'!$E:$E,"r0370 - Subordinated liabilities (not recognised as own funds)",'T 03.01'!AC:AC,1)+SUMIFS('T 03.01'!$Q:$Q,'T 03.01'!$F:$F,"c005x - Other financial corporations",'T 03.01'!$E:$E,"r0370 - Subordinated liabilities (not recognised as own funds)",'T 03.01'!AC:AC,1) -> 0 | I54: =SUMIFS('T 03.01'!$P:$P,'T 03.01'!$F:$F,"c006x - Insurance firms & pension funds",'T 03.01'!$E:$E,"r0370 - Subordinated liabilities (not recognised as own funds)",'T 03.01'!AC:AC,1)+SUMIFS('T 03.01'!$Q:$Q,'T 03.01'!$F:$F,"c006x - Insurance firms & pension funds",'T 03.01'!$E:$E,"r0370 - Subordinated liabilities (not recognised as own funds)",'T 03.01'!AC:AC,1) -> 0 | J54: =SUMIFS('T 03.01'!$P:$P,'T 03.01'!$F:$F,"c008x - Government, central banks & supranationals",'T 03.01'!$E:$E,"r0370 - Subordinated liabilities (not recognised as own funds)",'T 03.01'!AC:AC,1)+SUMIFS('T 03.01'!$Q:$Q,'T 03.01'!$F:$F,"c008x - Government, central banks & supranationals",'T 03.01'!$E:$E,"r0370 - Subordinated liabilities (not recognised as own funds)",'T 03.01'!AC:AC,1) -> 0 | K54: 0 | L54: =SUMIFS('T 03.01'!$P:$P,'T 03.01'!$F:$F,"",'T 03.01'!$E:$E,"r0370 - Subordinated liabilities (not recognised as own funds)",'T 03.01'!AC:AC,1)+SUMIFS('T 03.01'!$Q:$Q,'T 03.01'!$F:$F,"",'T 03.01'!$E:$E,"r0370 - Subordinated liabilities (not recognised as own funds)",'T 03.01'!AC:AC,1) -> 0 | M54: =SUM(D54:L54)-I54 -> 0 | N54: =SUMIFS('T 03.01'!$P:$P,'T 03.01'!$E:$E,"r0370 - Subordinated liabilities (not recognised as own funds)",'T 03.01'!AC:AC,1)+SUMIFS('T 03.01'!$Q:$Q,'T 03.01'!$E:$E,"r0370 - Subordinated liabilities (not recognised as own funds)",'T 03.01'!AC:AC,1) -> 0 | O54: 0
B55: o/w residual maturity > 1 month < 1 year | C55: 0372 | D55: =SUMIFS('T 03.01'!$P:$P,'T 03.01'!$F:$F,"c001x - Households",'T 03.01'!$E:$E,"r0370 - Subordinated liabilities (not recognised as own funds)",'T 03.01'!$AC:$AC,2)+SUMIFS('T 03.01'!$Q:$Q,'T 03.01'!$F:$F,"c001x - Households",'T 03.01'!$E:$E,"r0370 - Subordinated liabilities (not recognised as own funds)",'T 03.01'!$AC:$AC,2) -> 0 | E55: =SUMIFS('T 03.01'!$P:$P,'T 03.01'!$F:$F,"c002x - Micro & SME",'T 03.01'!$E:$E,"r0370 - Subordinated liabilities (not recognised as own funds)",'T 03.01'!AC:AC,2)+SUMIFS('T 03.01'!$Q:$Q,'T 03.01'!$F:$F,"c002x - Micro & SME",'T 03.01'!$E:$E,"r0370 - Subordinated liabilities (not recognised as own funds)",'T 03.01'!AC:AC,2) -> 0 | F55: =SUMIFS('T 03.01'!$P:$P,'T 03.01'!$F:$F,"c003x - Corporates",'T 03.01'!$E:$E,"r0370 - Subordinated liabilities (not recognised as own funds)",'T 03.01'!AC:AC,2)+SUMIFS('T 03.01'!$Q:$Q,'T 03.01'!$F:$F,"c003x - Corporates",'T 03.01'!$E:$E,"r0370 - Subordinated liabilities (not recognised as own funds)",'T 03.01'!AC:AC,2) -> 0 | G55: =SUMIFS('T 03.01'!$P:$P,'T 03.01'!$F:$F,"c004x - Institutions",'T 03.01'!$E:$E,"r0370 - Subordinated liabilities (not recognised as own funds)",'T 03.01'!AC:AC,2)+SUMIFS('T 03.01'!$Q:$Q,'T 03.01'!$F:$F,"c004x - Institutions",'T 03.01'!$E:$E,"r0370 - Subordinated liabilities (not recognised as own funds)",'T 03.01'!AC:AC,2) -> 0 | H55: =SUMIFS('T 03.01'!$P:$P,'T 03.01'!$F:$F,"c005x - Other financial corporations",'T 03.01'!$E:$E,"r0370 - Subordinated liabilities (not recognised as own funds)",'T 03.01'!AC:AC,2)+SUMIFS('T 03.01'!$Q:$Q,'T 03.01'!$F:$F,"c005x - Other financial corporations",'T 03.01'!$E:$E,"r0370 - Subordinated liabilities (not recognised as own funds)",'T 03.01'!AC:AC,2) -> 0 | I55: =SUMIFS('T 03.01'!$P:$P,'T 03.01'!$F:$F,"c006x - Insurance firms & pension funds",'T 03.01'!$E:$E,"r0370 - Subordinated liabilities (not recognised as own funds)",'T 03.01'!AC:AC,2)+SUMIFS('T 03.01'!$Q:$Q,'T 03.01'!$F:$F,"c006x - Insurance firms & pension funds",'T 03.01'!$E:$E,"r0370 - Subordinated liabilities (not recognised as own funds)",'T 03.01'!AC:AC,2) -> 0 | J55: =SUMIFS('T 03.01'!$P:$P,'T 03.01'!$F:$F,"c008x - Government, central banks & supranationals",'T 03.01'!$E:$E,"r0370 - Subordinated liabilities (not recognised as own funds)",'T 03.01'!AC:AC,2)+SUMIFS('T 03.01'!$Q:$Q,'T 03.01'!$F:$F,"c008x - Government, central banks & supranationals",'T 03.01'!$E:$E,"r0370 - Subordinated liabilities (not recognised as own funds)",'T 03.01'!AC:AC,2) -> 0 | K55: 0 | L55: =SUMIFS('T 03.01'!$P:$P,'T 03.01'!$F:$F,"",'T 03.01'!$E:$E,"r0370 - Subordinated liabilities (not recognised as own funds)",'T 03.01'!AC:AC,2)+SUMIFS('T 03.01'!$Q:$Q,'T 03.01'!$F:$F,"",'T 03.01'!$E:$E,"r0370 - Subordinated liabilities (not recognised as own funds)",'T 03.01'!AC:AC,2) -> 0 | M55: =SUM(D55:L55)-I55 -> 0 | N55: =SUMIFS('T 03.01'!$P:$P,'T 03.01'!$E:$E,"r0370 - Subordinated liabilities (not recognised as own funds)",'T 03.01'!AC:AC,2)+SUMIFS('T 03.01'!$Q:$Q,'T 03.01'!$E:$E,"r0370 - Subordinated liabilities (not recognised as own funds)",'T 03.01'!AC:AC,2) -> 0 | O55: 0
B56: o/w residual maturity >= 1 year and < 2 years | C56: 0373 | D56: =SUMIFS('T 03.01'!$P:$P,'T 03.01'!$F:$F,"c001x - Households",'T 03.01'!$E:$E,"r0370 - Subordinated liabilities (not recognised as own funds)",'T 03.01'!$AC:$AC,3)+SUMIFS('T 03.01'!$Q:$Q,'T 03.01'!$F:$F,"c001x - Households",'T 03.01'!$E:$E,"r0370 - Subordinated liabilities (not recognised as own funds)",'T 03.01'!$AC:$AC,3) -> 0 | E56: =SUMIFS('T 03.01'!$P:$P,'T 03.01'!$F:$F,"c002x - Micro & SME",'T 03.01'!$E:$E,"r0370 - Subordinated liabilities (not recognised as own funds)",'T 03.01'!AC:AC,3)+SUMIFS('T 03.01'!$Q:$Q,'T 03.01'!$F:$F,"c002x - Micro & SME",'T 03.01'!$E:$E,"r0370 - Subordinated liabilities (not recognised as own funds)",'T 03.01'!AC:AC,3) -> 0 | F56: =SUMIFS('T 03.01'!$P:$P,'T 03.01'!$F:$F,"c003x - Corporates",'T 03.01'!$E:$E,"r0370 - Subordinated liabilities (not recognised as own funds)",'T 03.01'!AC:AC,3)+SUMIFS('T 03.01'!$Q:$Q,'T 03.01'!$F:$F,"c003x - Corporates",'T 03.01'!$E:$E,"r0370 - Subordinated liabilities (not recognised as own funds)",'T 03.01'!AC:AC,3) -> 0 | G56: =SUMIFS('T 03.01'!$P:$P,'T 03.01'!$F:$F,"c004x - Institutions",'T 03.01'!$E:$E,"r0370 - Subordinated liabilities (not recognised as own funds)",'T 03.01'!AC:AC,3)+SUMIFS('T 03.01'!$Q:$Q,'T 03.01'!$F:$F,"c004x - Institutions",'T 03.01'!$E:$E,"r0370 - Subordinated liabilities (not recognised as own funds)",'T 03.01'!AC:AC,3) -> 0 | H56: =SUMIFS('T 03.01'!$P:$P,'T 03.01'!$F:$F,"c005x - Other financial corporations",'T 03.01'!$E:$E,"r0370 - Subordinated liabilities (not recognised as own funds)",'T 03.01'!AC:AC,3)+SUMIFS('T 03.01'!$Q:$Q,'T 03.01'!$F:$F,"c005x - Other financial corporations",'T 03.01'!$E:$E,"r0370 - Subordinated liabilities (not recognised as own funds)",'T 03.01'!AC:AC,3) -> 0 | I56: =SUMIFS('T 03.01'!$P:$P,'T 03.01'!$F:$F,"c006x - Insurance firms & pension funds",'T 03.01'!$E:$E,"r0370 - Subordinated liabilities (not recognised as own funds)",'T 03.01'!AC:AC,3)+SUMIFS('T 03.01'!$Q:$Q,'T 03.01'!$F:$F,"c006x - Insurance firms & pension funds",'T 03.01'!$E:$E,"r0370 - Subordinated liabilities (not recognised as own funds)",'T 03.01'!AC:AC,3) -> 0 | J56: =SUMIFS('T 03.01'!$P:$P,'T 03.01'!$F:$F,"c008x - Government, central banks & supranationals",'T 03.01'!$E:$E,"r0370 - Subordinated liabilities (not recognised as own funds)",'T 03.01'!AC:AC,3)+SUMIFS('T 03.01'!$Q:$Q,'T 03.01'!$F:$F,"c008x - Government, central banks & supranationals",'T 03.01'!$E:$E,"r0370 - Subordinated liabilities (not recognised as own funds)",'T 03.01'!AC:AC,3) -> 0 | K56: 0 | L56: =SUMIFS('T 03.01'!$P:$P,'T 03.01'!$F:$F,"",'T 03.01'!$E:$E,"r0370 - Subordinated liabilities (not recognised as own funds)",'T 03.01'!AC:AC,3)+SUMIFS('T 03.01'!$Q:$Q,'T 03.01'!$F:$F,"",'T 03.01'!$E:$E,"r0370 - Subordinated liabilities (not recognised as own funds)",'T 03.01'!AC:AC,3) -> 0 | M56: =SUM(D56:L56)-I56 -> 0 | N56: =SUMIFS('T 03.01'!$P:$P,'T 03.01'!$E:$E,"r0370 - Subordinated liabilities (not recognised as own funds)",'T 03.01'!AC:AC,3)+SUMIFS('T 03.01'!$Q:$Q,'T 03.01'!$E:$E,"r0370 - Subordinated liabilities (not recognised as own funds)",'T 03.01'!AC:AC,3) -> 0 | O56: 0
B57: o/w residual maturity >= 2 years | C57: 0374 | D57: =SUMIFS('T 03.01'!$P:$P,'T 03.01'!$F:$F,"c001x - Households",'T 03.01'!$E:$E,"r0370 - Subordinated liabilities (not recognised as own funds)",'T 03.01'!$AC:$AC,4)+SUMIFS('T 03.01'!$Q:$Q,'T 03.01'!$F:$F,"c001x - Households",'T 03.01'!$E:$E,"r0370 - Subordinated liabilities (not recognised as own funds)",'T 03.01'!$AC:$AC,4) -> 0 | E57: =SUMIFS('T 03.01'!$P:$P,'T 03.01'!$F:$F,"c002x - Micro & SME",'T 03.01'!$E:$E,"r0370 - Subordinated liabilities (not recognised as own funds)",'T 03.01'!AC:AC,4)+SUMIFS('T 03.01'!$Q:$Q,'T 03.01'!$F:$F,"c002x - Micro & SME",'T 03.01'!$E:$E,"r0370 - Subordinated liabilities (not recognised as own funds)",'T 03.01'!AC:AC,4) -> 0 | F57: =SUMIFS('T 03.01'!$P:$P,'T 03.01'!$F:$F,"c003x - Corporates",'T 03.01'!$E:$E,"r0370 - Subordinated liabilities (not recognised as own funds)",'T 03.01'!AC:AC,4)+SUMIFS('T 03.01'!$Q:$Q,'T 03.01'!$F:$F,"c003x - Corporates",'T 03.01'!$E:$E,"r0370 - Subordinated liabilities (not recognised as own funds)",'T 03.01'!AC:AC,4) -> 0 | G57: =SUMIFS('T 03.01'!$P:$P,'T 03.01'!$F:$F,"c004x - Institutions",'T 03.01'!$E:$E,"r0370 - Subordinated liabilities (not recognised as own funds)",'T 03.01'!AC:AC,4)+SUMIFS('T 03.01'!$Q:$Q,'T 03.01'!$F:$F,"c004x - Institutions",'T 03.01'!$E:$E,"r0370 - Subordinated liabilities (not recognised as own funds)",'T 03.01'!AC:AC,4) -> 0 | H57: =SUMIFS('T 03.01'!$P:$P,'T 03.01'!$F:$F,"c005x - Other financial corporations",'T 03.01'!$E:$E,"r0370 - Subordinated liabilities (not recognised as own funds)",'T 03.01'!AC:AC,4)+SUMIFS('T 03.01'!$Q:$Q,'T 03.01'!$F:$F,"c005x - Other financial corporations",'T 03.01'!$E:$E,"r0370 - Subordinated liabilities (not recognised as own funds)",'T 03.01'!AC:AC,4) -> 0 | I57: =SUMIFS('T 03.01'!$P:$P,'T 03.01'!$F:$F,"c006x - Insurance firms & pension funds",'T 03.01'!$E:$E,"r0370 - Subordinated liabilities (not recognised as own funds)",'T 03.01'!AC:AC,4)+SUMIFS('T 03.01'!$Q:$Q,'T 03.01'!$F:$F,"c006x - Insurance firms & pension funds",'T 03.01'!$E:$E,"r0370 - Subordinated liabilities (not recognised as own funds)",'T 03.01'!AC:AC,4) -> 0 | J57: =SUMIFS('T 03.01'!$P:$P,'T 03.01'!$F:$F,"c008x - Government, central banks & supranationals",'T 03.01'!$E:$E,"r0370 - Subordinated liabilities (not recognised as own funds)",'T 03.01'!AC:AC,4)+SUMIFS('T 03.01'!$Q:$Q,'T 03.01'!$F:$F,"c008x - Government, central banks & supranationals",'T 03.01'!$E:$E,"r0370 - Subordinated liabilities (not recognised as own funds)",'T 03.01'!AC:AC,4) -> 0 | K57: 0 | L57: =SUMIFS('T 03.01'!$P:$P,'T 03.01'!$F:$F,"",'T 03.01'!$E:$E,"r0370 - Subordinated liabilities (not recognised as own funds)",'T 03.01'!AC:AC,4)+SUMIFS('T 03.01'!$Q:$Q,'T 03.01'!$F:$F,"",'T 03.01'!$E:$E,"r0370 - Subordinated liabilities (not recognised as own funds)",'T 03.01'!AC:AC,4) -> 0 | M57: =SUM(D57:L57)-I57 -> 0 | N57: =SUMIFS('T 03.01'!$P:$P,'T 03.01'!$E:$E,"r0370 - Subordinated liabilities (not recognised as own funds)",'T 03.01'!AC:AC,4)+SUMIFS('T 03.01'!$Q:$Q,'T 03.01'!$E:$E,"r0370 - Subordinated liabilities (not recognised as own funds)",'T 03.01'!AC:AC,4) -> 0 | O57: 0
B58: Other MREL eligible liabilities | C58: 0380 | D58: 0 | E58: 0 | F58: 0 | G58: 0 | H58: 0 | I58: 0 | J58: 0 | K58: 0 | L58: 0 | M58: =SUM(D58:L58)-I58 -> 0 | N58: 0 | O58: 0
B59: o/w residual maturity >= 1 year and < 2 years | C59: 0381 | D59: 0 | E59: 0 | F59: 0 | G59: 0 | H59: 0 | I59: 0 | J59: 0 | K59: 0 | L59: 0 | M59: =SUM(D59:L59)-I59 -> 0 | N59: 0 | O59: 0
B60: o/w residual maturity >= 2 years | C60: 0382 | D60: 0 | E60: 0 | F60: 0 | G60: 0 | H60: 0 | I60: 0 | J60: 0 | K60: 0 | L60: 0 | M60: =SUM(D60:L60)-I60 -> 0 | N60: 0 | O60: 0
B61: Non-financial liabilities | C61: 0390 | D61: =+SUMIFS('T 09.00'!$M:$M,'T 09.00'!$E:$E,"r0390 - Non-financial liabilities",'T 09.00'!$F:$F,"c001x - Households")+SUMIFS('T 03.01'!P:P,'T 03.01'!E:E,"r0390 - Non-financial liabilities",'T 03.01'!$F:$F,"c001x - Households")+SUMIFS('T 03.01'!Q:Q,'T 03.01'!E:E,"r0390 - Non-financial liabilities",'T 03.01'!$F:$F,"c001x - Households") -> 64496913 | E61: =+SUMIFS('T 09.00'!$M:$M,'T 09.00'!$E:$E,"r0390 - Non-financial liabilities",'T 09.00'!$F:$F,"c002x - Micro & SME")+SUMIFS('T 03.01'!P:P,'T 03.01'!E:E,"r0390 - Non-financial liabilities",'T 03.01'!$F:$F,"c002x - Micro & SME")+SUMIFS('T 03.01'!Q:Q,'T 03.01'!E:E,"r0390 - Non-financial liabilities",'T 03.01'!$F:$F,"c002x - Micro & SME") -> 39226891 | F61: =+SUMIFS('T 09.00'!$M:$M,'T 09.00'!$E:$E,"r0390 - Non-financial liabilities",'T 09.00'!$F:$F,"c003x - Corporates")+SUMIFS('T 03.01'!P:P,'T 03.01'!E:E,"r0390 - Non-financial liabilities",'T 03.01'!$F:$F,"c003x - Corporates")+SUMIFS('T 03.01'!Q:Q,'T 03.01'!E:E,"r0390 - Non-financial liabilities",'T 03.01'!$F:$F,"c003x - Corporates") -> 65441064 | G61: =+SUMIFS('T 09.00'!$M:$M,'T 09.00'!$E:$E,"r0390 - Non-financial liabilities",'T 09.00'!$F:$F,"c004x - Institutions")+SUMIFS('T 03.01'!P:P,'T 03.01'!E:E,"r0390 - Non-financial liabilities",'T 03.01'!$F:$F,"c004x - Institutions")+SUMIFS('T 03.01'!Q:Q,'T 03.01'!E:E,"r0390 - Non-financial liabilities",'T 03.01'!$F:$F,"c004x - Institutions") -> 20574581 | H61: =+SUMIFS('T 09.00'!$M:$M,'T 09.00'!$E:$E,"r0390 - Non-financial liabilities",'T 09.00'!$F:$F,"c005x - Other financial corporations")+I61+SUMIFS('T 03.01'!P:P,'T 03.01'!E:E,"r0390 - Non-financial liabilities",'T 03.01'!$F:$F,"c005x - Other financial corporations")+SUMIFS('T 03.01'!Q:Q,'T 03.01'!E:E,"r0390 - Non-financial liabilities",'T 03.01'!$F:$F,"c005x - Other financial corporations") -> 48135527 | I61: =+SUMIFS('T 09.00'!$M:$M,'T 09.00'!$E:$E,"r0390 - Non-financial liabilities",'T 09.00'!$F:$F,"c006x - Insurance firms & pension funds")+SUMIFS('T 03.01'!P:P,'T 03.01'!E:E,"r0390 - Non-financial liabilities",'T 03.01'!$F:$F,"c006x - Insurance firms & pension funds")+SUMIFS('T 03.01'!Q:Q,'T 03.01'!E:E,"r0390 - Non-financial liabilities",'T 03.01'!$F:$F,"c006x - Insurance firms & pension funds") -> 4534786.2 | J61: =+SUMIFS('T 09.00'!$M:$M,'T 09.00'!$E:$E,"r0390 - Non-financial liabilities",'T 09.00'!$F:$F,"c008x - Government, central banks & supranationals")+SUMIFS('T 03.01'!P:P,'T 03.01'!E:E,"r0390 - Non-financial liabilities",'T 03.01'!$F:$F,"c008x - Government, central banks & supranationals")+SUMIFS('T 03.01'!Q:Q,'T 03.01'!E:E,"r0390 - Non-financial liabilities",'T 03.01'!$F:$F,"c008x - Government, central banks & supranationals") -> 21255982 | K61: 0 | L61: =+SUMIFS('T 09.00'!$M:$M,'T 09.00'!$E:$E,"r0390 - Non-financial liabilities",'T 09.00'!$F:$F,"c010x - Non-identified, not listed on an exchange platform")+SUMIFS('T 03.01'!P:P,'T 03.01'!E:E,"r0390 - Non-financial liabilities",'T 03.01'!$F:$F,"")+SUMIFS('T 03.01'!Q:Q,'T 03.01'!E:E,"r0390 - Non-financial liabilities",'T 03.01'!$F:$F,"") -> 3.1330474e+08 | M61: =SUM(D61:L61)-I61 -> 5.7243569e+08 | N61: =+SUMIF('T 03.01'!E:E,"r0390 - Non-financial liabilities",'T 03.01'!P:P)+SUMIF('T 03.01'!E:E,"r0390 - Non-financial liabilities",'T 03.01'!Q:Q) -> 49987448 | O61: 0
B62: Residual liabilities | C62: 0400 | D62: 0 | E62: 0 | F62: 0 | G62: 0 | H62: 0 | I62: 0 | J62: 0 | K62: 0 | L62: 0 | M62: =SUM(D62:L62)-I62 -> 0 | N62: 0 | O62: 0
B63: 0500 Own funds
B64: 0510 Common Equity Tier 1 Capital
B65: o/w capital instruments/share capital | C65: 0511 | D65: =SUMIFS('T 03.01'!P:P,'T 03.01'!E:E,"r0511 - o/w capital instruments/share capital",'T 03.01'!$F:$F,"c001x - Households")+SUMIFS('T 03.01'!Q:Q,'T 03.01'!E:E,"r0511 - o/w capital instruments/share capital",'T 03.01'!$F:$F,"c001x - Households") -> 0 | E65: =SUMIFS('T 03.01'!P:P,'T 03.01'!E:E,"r0511 - o/w capital instruments/share capital",'T 03.01'!$F:$F,"c002x - Micro & SME")+SUMIFS('T 03.01'!Q:Q,'T 03.01'!E:E,"r0511 - o/w capital instruments/share capital",'T 03.01'!$F:$F,"c002x - Micro & SME") -> 0 | F65: =SUMIFS('T 03.01'!P:P,'T 03.01'!E:E,"r0511 - o/w capital instruments/share capital",'T 03.01'!$F:$F,"c003x - Corporates")+SUMIFS('T 03.01'!Q:Q,'T 03.01'!E:E,"r0511 - o/w capital instruments/share capital",'T 03.01'!$F:$F,"c003x - Corporates") -> 14593315 | G65: =SUMIFS('T 03.01'!P:P,'T 03.01'!E:E,"r0511 - o/w capital instruments/share capital",'T 03.01'!$F:$F,"c004x - Institutions")+SUMIFS('T 03.01'!Q:Q,'T 03.01'!E:E,"r0511 - o/w capital instruments/share capital",'T 03.01'!$F:$F,"c004x - Institutions") -> 0 | H65: =I65+SUMIFS('T 03.01'!P:P,'T 03.01'!E:E,"r0511 - o/w capital instruments/share capital",'T 03.01'!$F:$F,"c005x - Other financial corporations")+SUMIFS('T 03.01'!Q:Q,'T 03.01'!E:E,"r0511 - o/w capital instruments/share capital",'T 03.01'!$F:$F,"c005x - Other financial corporations") -> 1.4333118e+09 | I65: =SUMIFS('T 03.01'!P:P,'T 03.01'!E:E,"r0511 - o/w capital instruments/share capital",'T 03.01'!$F:$F,"c006x - Insurance firms & pension funds")+SUMIFS('T 03.01'!Q:Q,'T 03.01'!E:E,"r0511 - o/w capital instruments/share capital",'T 03.01'!$F:$F,"c006x - Insurance firms & pension funds") -> 0 | J65: =SUMIFS('T 03.01'!P:P,'T 03.01'!E:E,"r0511 - o/w capital instruments/share capital",'T 03.01'!$F:$F,"c008x - Government, central banks & supranationals")+SUMIFS('T 03.01'!Q:Q,'T 03.01'!E:E,"r0511 - o/w capital instruments/share capital",'T 03.01'!$F:$F,"c008x - Government, central banks & supranationals") -> 0 | K65: 0 | L65: =SUMIFS('T 03.01'!P:P,'T 03.01'!E:E,"r0511 - o/w capital instruments/share capital",'T 03.01'!$F:$F,"")+SUMIFS('T 03.01'!Q:Q,'T 03.01'!E:E,"r0511 - o/w capital instruments/share capital",'T 03.01'!$F:$F,"") -> 0 | M65: =SUM(D65:L65)-I65 -> 1.4479051e+09 | N65: =+SUMIF('T 03.01'!E:E,"r0511 - o/w capital instruments/share capital",'T 03.01'!P:P)+SUMIF('T 03.01'!E:E,"r0511 - o/w capital instruments/share capital",'T 03.01'!Q:Q) -> 1.4479051e+09 | O65: 0
B66: o/w instruments ranking pari passu with ordinary shares | C66: 0512 | D66: =SUMIFS('T 03.01'!P:P,'T 03.01'!E:E,"r0512 - o/w instruments ranking pari passu with ordinary shares",'T 03.01'!$F:$F,"c001x - Households")+SUMIFS('T 03.01'!Q:Q,'T 03.01'!E:E,"r0512 - o/w instruments ranking pari passu with ordinary shares",'T 03.01'!$F:$F,"c001x - Households") -> 0 | E66: =SUMIFS('T 03.01'!P:P,'T 03.01'!E:E,"r0512 - o/w instruments ranking pari passu with ordinary shares",'T 03.01'!$F:$F,"c002x - Micro & SME")+SUMIFS('T 03.01'!Q:Q,'T 03.01'!E:E,"r0512 - o/w instruments ranking pari passu with ordinary shares",'T 03.01'!$F:$F,"c002x - Micro & SME") -> 0 | F66: =SUMIFS('T 03.01'!P:P,'T 03.01'!E:E,"r0512 - o/w instruments ranking pari passu with ordinary shares",'T 03.01'!$F:$F,"c003x - Corporates")+SUMIFS('T 03.01'!Q:Q,'T 03.01'!E:E,"r0512 - o/w instruments ranking pari passu with ordinary shares",'T 03.01'!$F:$F,"c003x - Corporates") -> 0 | G66: =SUMIFS('T 03.01'!P:P,'T 03.01'!E:E,"r0512 - o/w instruments ranking pari passu with ordinary shares",'T 03.01'!$F:$F,"c004x - Institutions")+SUMIFS('T 03.01'!Q:Q,'T 03.01'!E:E,"r0512 - o/w instruments ranking pari passu with ordinary shares",'T 03.01'!$F:$F,"c004x - Institutions") -> 0 | H66: =I66+SUMIFS('T 03.01'!P:P,'T 03.01'!E:E,"r0512 - o/w instruments ranking pari passu with ordinary shares",'T 03.01'!$F:$F,"c005x - Other financial corporations")+SUMIFS('T 03.01'!Q:Q,'T 03.01'!E:E,"r0512 - o/w instruments ranking pari passu with ordinary shares",'T 03.01'!$F:$F,"c005x - Other financial corporations") -> 135000000 | I66: =SUMIFS('T 03.01'!P:P,'T 03.01'!E:E,"r0512 - o/w instruments ranking pari passu with ordinary shares",'T 03.01'!$F:$F,"c006x - Insurance firms & pension funds")+SUMIFS('T 03.01'!Q:Q,'T 03.01'!E:E,"r0512 - o/w instruments ranking pari passu with ordinary shares",'T 03.01'!$F:$F,"c006x - Insurance firms & pension funds") -> 0 | J66: =SUMIFS('T 03.01'!P:P,'T 03.01'!E:E,"r0512 - o/w instruments ranking pari passu with ordinary shares",'T 03.01'!$F:$F,"c008x - Government, central banks & supranationals")+SUMIFS('T 03.01'!Q:Q,'T 03.01'!E:E,"r0512 - o/w instruments ranking pari passu with ordinary shares",'T 03.01'!$F:$F,"c008x - Government, central banks & supranationals") -> 0 | K66: 0 | L66: =SUMIFS('T 03.01'!P:P,'T 03.01'!E:E,"r0512 - o/w instruments ranking pari passu with ordinary shares",'T 03.01'!$F:$F,"")+SUMIFS('T 03.01'!Q:Q,'T 03.01'!E:E,"r0512 - o/w instruments ranking pari passu with ordinary shares",'T 03.01'!$F:$F,"") -> 0 | M66: =SUM(D66:L66)-I66 -> 135000000 | N66: =+SUMIF('T 03.01'!E:E,"r0512 - o/w instruments ranking pari passu with ordinary shares",'T 03.01'!P:P)+SUMIF('T 03.01'!E:E,"r0512 - o/w instruments ranking pari passu with ordinary shares",'T 03.01'!Q:Q) -> 135000000 | O66: 0
B67: 0520 Additional Tier 1 capital
B68: o/w (part of) subordinated liabilities recognised as own funds | C68: 0521 | D68: =SUMIFS('T 03.01'!P:P,'T 03.01'!E:E,"r0521 -o/w (part of) subordinated liabilities recognised as own funds",'T 03.01'!$F:$F,"c001x - Households")+SUMIFS('T 03.01'!Q:Q,'T 03.01'!E:E,"r0521 -o/w (part of) subordinated liabilities recognised as own funds",'T 03.01'!$F:$F,"c001x - Households") -> 0 | E68: =SUMIFS('T 03.01'!P:P,'T 03.01'!E:E,"r0521 -o/w (part of) subordinated liabilities recognised as own funds",'T 03.01'!$F:$F,"c002x - Micro & SME")+SUMIFS('T 03.01'!Q:Q,'T 03.01'!E:E,"r0521 -o/w (part of) subordinated liabilities recognised as own funds",'T 03.01'!$F:$F,"c002x - Micro & SME") -> 0 | F68: =SUMIFS('T 03.01'!P:P,'T 03.01'!E:E,"r0521 -o/w (part of) subordinated liabilities recognised as own funds",'T 03.01'!$F:$F,"c003x - Corporates")+SUMIFS('T 03.01'!Q:Q,'T 03.01'!E:E,"r0521 -o/w (part of) subordinated liabilities recognised as own funds",'T 03.01'!$F:$F,"c003x - Corporates") -> 0 | G68: =SUMIFS('T 03.01'!P:P,'T 03.01'!E:E,"r0521 -o/w (part of) subordinated liabilities recognised as own funds",'T 03.01'!$F:$F,"c004x - Institutions")+SUMIFS('T 03.01'!Q:Q,'T 03.01'!E:E,"r0521 -o/w (part of) subordinated liabilities recognised as own funds",'T 03.01'!$F:$F,"c004x - Institutions") -> 0 | H68: =I68+SUMIFS('T 03.01'!P:P,'T 03.01'!E:E,"r0521 -o/w (part of) subordinated liabilities recognised as own funds",'T 03.01'!$F:$F,"c005x - Other financial corporations")+SUMIFS('T 03.01'!Q:Q,'T 03.01'!E:E,"r0521 -o/w (part of) subordinated liabilities recognised as own funds",'T 03.01'!$F:$F,"c005x - Other financial corporations") -> 0 | I68: =SUMIFS('T 03.01'!P:P,'T 03.01'!E:E,"r0521 -o/w (part of) subordinated liabilities recognised as own funds",'T 03.01'!$F:$F,"c006x - Insurance firms & pension funds")+SUMIFS('T 03.01'!Q:Q,'T 03.01'!E:E,"r0521 -o/w (part of) subordinated liabilities recognised as own funds",'T 03.01'!$F:$F,"c006x - Insurance firms & pension funds") -> 0 | J68: =SUMIFS('T 03.01'!P:P,'T 03.01'!E:E,"r0521 -o/w (part of) subordinated liabilities recognised as own funds",'T 03.01'!$F:$F,"c008x - Government, central banks & supranationals")+SUMIFS('T 03.01'!Q:Q,'T 03.01'!E:E,"r0521 -o/w (part of) subordinated liabilities recognised as own funds",'T 03.01'!$F:$F,"c008x - Government, central banks & supranationals") -> 0 | K68: 0 | L68: =SUMIFS('T 03.01'!P:P,'T 03.01'!E:E,"r0521 -o/w (part of) subordinated liabilities recognised as own funds",'T 03.01'!$F:$F,"")+SUMIFS('T 03.01'!Q:Q,'T 03.01'!E:E,"r0521 -o/w (part of) subordinated liabilities recognised as own funds",'T 03.01'!$F:$F,"") -> 0 | M68: =SUM(D68:L68)-I68 -> 0 | N68: =+SUMIF('T 03.01'!E:E,"r0521 -o/w (part of) subordinated liabilities recognised as own funds",'T 03.01'!P:P)+SUMIF('T 03.01'!E:E,"r0521 -o/w (part of) subordinated liabilities recognised as own funds",'T 03.01'!Q:Q) -> 0 | O68: 0
B69: 0530 Tier 2 Capital
B70: o/w (part of) subordinated liabilities recognised as own funds | C70: 0531 | D70: =SUMIFS('T 03.01'!P:P,'T 03.01'!E:E,"r0531 - o/w (part of) subordinated liabilities recognised as own funds",'T 03.01'!$F:$F,"c001x - Households")+SUMIFS('T 03.01'!Q:Q,'T 03.01'!E:E,"r0531 - o/w (part of) subordinated liabilities recognised as own funds",'T 03.01'!$F:$F,"c001x - Households")+SUMIFS('T 04.00'!$N:$N,'T 04.00'!$E:$E,"r0531 - o/w (part of) subordinated liabilities recognised as own funds",'T 04.00'!$F:$F,"c001x - Households")+SUMIFS('T 04.00'!O:O,'T 04.00'!E:E,"r0531 - o/w (part of) subordinated liabilities recognised as own funds",'T 04.00'!$F:$F,"c001x - Households") -> 7734845.1 | E70: =SUMIFS('T 03.01'!P:P,'T 03.01'!E:E,"r0531 - o/w (part of) subordinated liabilities recognised as own funds",'T 03.01'!$F:$F,"c002x - Micro & SME")+SUMIFS('T 03.01'!Q:Q,'T 03.01'!E:E,"r0531 - o/w (part of) subordinated liabilities recognised as own funds",'T 03.01'!$F:$F,"c002x - Micro & SME")+SUMIFS('T 04.00'!$N:$N,'T 04.00'!$E:$E,"r0531 - o/w (part of) subordinated liabilities recognised as own funds",'T 04.00'!$F:$F,"c002x - Micro & SME")+SUMIFS('T 04.00'!O:O,'T 04.00'!E:E,"r0531 - o/w (part of) subordinated liabilities recognised as own funds",'T 04.00'!$F:$F,"c002x - Micro & SME") -> 0 | F70: =SUMIFS('T 03.01'!P:P,'T 03.01'!E:E,"r0531 - o/w (part of) subordinated liabilities recognised as own funds",'T 03.01'!$F:$F,"c003x - Corporates")+SUMIFS('T 03.01'!Q:Q,'T 03.01'!E:E,"r0531 - o/w (part of) subordinated liabilities recognised as own funds",'T 03.01'!$F:$F,"c003x - Corporates")+SUMIFS('T 04.00'!$N:$N,'T 04.00'!$E:$E,"r0531 - o/w (part of) subordinated liabilities recognised as own funds",'T 04.00'!$F:$F,"c003x - Corporates")+SUMIFS('T 04.00'!O:O,'T 04.00'!E:E,"r0531 - o/w (part of) subordinated liabilities recognised as own funds",'T 04.00'!$F:$F,"c003x - Corporates") -> 0 | G70: =SUMIFS('T 03.01'!P:P,'T 03.01'!E:E,"r0531 - o/w (part of) subordinated liabilities recognised as own funds",'T 03.01'!$F:$F,"c004x - Institutions")+SUMIFS('T 03.01'!Q:Q,'T 03.01'!E:E,"r0531 - o/w (part of) subordinated liabilities recognised as own funds",'T 03.01'!$F:$F,"c004x - Institutions")+SUMIFS('T 04.00'!$N:$N,'T 04.00'!$E:$E,"r0531 - o/w (part of) subordinated liabilities recognised as own funds",'T 04.00'!$F:$F,"c004x - Institutions")+SUMIFS('T 04.00'!O:O,'T 04.00'!E:E,"r0531 - o/w (part of) subordinated liabilities recognised as own funds",'T 04.00'!$F:$F,"c004x - Institutions") -> 0 | H70: =I70+SUMIFS('T 03.01'!P:P,'T 03.01'!E:E,"r0531 - o/w (part of) subordinated liabilities recognised as own funds",'T 03.01'!$F:$F,"c005x - Other financial corporations")+SUMIFS('T 03.01'!Q:Q,'T 03.01'!E:E,"r0531 - o/w (part of) subordinated liabilities recognised as own funds",'T 03.01'!$F:$F,"c005x - Other financial corporations")+SUMIFS('T 04.00'!$N:$N,'T 04.00'!$E:$E,"r0531 - o/w (part of) subordinated liabilities recognised as own funds",'T 04.00'!$F:$F,"c005x - Other financial corporations")+SUMIFS('T 04.00'!O:O,'T 04.00'!E:E,"r0531 - o/w (part of) subordinated liabilities recognised as own funds",'T 04.00'!$F:$F,"c005x - Other financial corporations") -> 3.2001387e+08 | I70: =SUMIFS('T 03.01'!P:P,'T 03.01'!E:E,"r0531 - o/w (part of) subordinated liabilities recognised as own funds",'T 03.01'!$F:$F,"c006x - Insurance firms & pension funds")+SUMIFS('T 03.01'!Q:Q,'T 03.01'!E:E,"r0531 - o/w (part of) subordinated liabilities recognised as own funds",'T 03.01'!$F:$F,"c006x - Insurance firms & pension funds")+SUMIFS('T 04.00'!$N:$N,'T 04.00'!$E:$E,"r0531 - o/w (part of) subordinated liabilities recognised as own funds",'T 04.00'!$F:$F,"c006x - Insurance firms & pension funds")+SUMIFS('T 04.00'!O:O,'T 04.00'!E:E,"r0531 - o/w (part of) subordinated liabilities recognised as own funds",'T 04.00'!$F:$F,"c006x - Insurance firms & pension funds") -> 0 | J70: =SUMIFS('T 03.01'!P:P,'T 03.01'!E:E,"r0531 - o/w (part of) subordinated liabilities recognised as own funds",'T 03.01'!$F:$F,"c008x - Government, central banks & supranationals")+SUMIFS('T 03.01'!Q:Q,'T 03.01'!E:E,"r0531 - o/w (part of) subordinated liabilities recognised as own funds",'T 03.01'!$F:$F,"c008x - Government, central banks & supranationals")+SUMIFS('T 04.00'!$N:$N,'T 04.00'!$E:$E,"r0531 - o/w (part of) subordinated liabilities recognised as own funds",'T 04.00'!$F:$F,"c008x - Government, central banks & supranationals")+SUMIFS('T 04.00'!O:O,'T 04.00'!E:E,"r0531 - o/w (part of) subordinated liabilities recognised as own funds",'T 04.00'!$F:$F,"c008x - Government, central banks & supranationals") -> 0 | K70: 0 | L70: =SUMIFS('T 03.01'!P:P,'T 03.01'!E:E,"r0531 - o/w (part of) subordinated liabilities recognised as own funds",'T 03.01'!$F:$F,"")+SUMIFS('T 03.01'!Q:Q,'T 03.01'!E:E,"r0531 - o/w (part of) subordinated liabilities recognised as own funds",'T 03.01'!$F:$F,"")+SUMIFS('T 04.00'!$N:$N,'T 04.00'!$E:$E,"r0531 - o/w (part of) subordinated liabilities recognised as own funds",'T 04.00'!$F:$F,"")+SUMIFS('T 04.00'!O:O,'T 04.00'!E:E,"r0531 - o/w (part of) subordinated liabilities recognised as own funds",'T 04.00'!$F:$F,"") -> 0 | M70: =SUM(D70:L70)-I70 -> 3.2774871e+08 | N70: =+SUMIF('T 03.01'!E:E,"r0531 - o/w (part of) subordinated liabilities recognised as own funds",'T 03.01'!P:P)+SUMIF('T 03.01'!E:E,"r0531 - o/w (part of) subordinated liabilities recognised as own funds",'T 03.01'!Q:Q) -> 3.2001387e+08 | O70: 0
B71: Off-balance sheet exposures | C71: 0700 | D71: =-'Off-balance '!A19-'Off-balance '!A20-'Off-balance '!A21 -> 1.9161112e+09 | E71: =-'Off-balance '!A11 -> 1.1831104e+09 | F71: =-'Off-balance '!A8-'Off-balance '!A9-'Off-balance '!A10 -> 4.8202258e+09 | G71: =-'Off-balance '!A4-'Off-balance '!A5-'Off-balance '!A6-'Off-balance '!A7 -> 4.641698e+08 | H71: =-'Off-balance '!A12-'Off-balance '!A13-'Off-balance '!A15-'Off-balance '!A17-'Off-balance '!A14-'Off-balance '!A16-'Off-balance '!A18 -> 8.716818e+08 | I71: =-'Off-balance '!A14-'Off-balance '!A16-'Off-balance '!A18 -> 17574512 | J71: =-'Off-balance '!A22-'Off-balance '!A23-'Off-balance '!A24-'Off-balance '!A2-'Off-balance '!A3 -> 3.1007107e+08 | K71: 0 | L71: 0 | M71: =+SUM(D71:L71)-I71 -> 9.5653701e+09 | N71: =-'Off-balance '!A6-'Off-balance '!A10-'Off-balance '!A15-'Off-balance '!A16 -> 1.2359714e+09 | O71: 0
B72: Loan commitments received | C72: 0750 | D72: 0 | E72: 0 | F72: =-'Loan commitments received'!A4 -> 3758123 | G72: 0 | H72: =-'Loan commitments received'!A5 -> 2.7446645e+08 | I72: 0 | J72: =-'Loan commitments received'!A3 -> 140000000 | K72: 0 | L72: 0 | M72: =+SUM(D72:L72)-I72 -> 4.1822457e+08 | N72: 0 | O72: 0
B73: Financial guarantees received | C73: 0760 | O73: 0
B74: Other commitments received | C74: 0770 | D74: 0 | E74: 0 | F74: 0 | G74: 0 | H74: 0 | I74: 0 | J74: 0 | K74: 0 | L74: 0 | M74: 0 | N74: 0 | O74: 0
B75: Derivatives | C75: 0780 | D75: =-Derivados!A8 -> 0 | E75: =-Derivados!A5 -> 65181579 | F75: =-Derivados!A4 -> 3.289276e+08 | G75: =-Derivados!A2-Derivados!A3 -> 1.6225041e+10 | H75: =-Derivados!A6-Derivados!A7 -> 4012176240 | I75: =-Derivados!A7 -> 212176240 | M75: =+SUM(D75:H75) -> 2.0631326e+10 | N75: =-Derivados!A7-Derivados!A3 -> 1.5064134e+10 | O75: 0
B76: Total equity | C76: 0800
B77: Total assets | C77: 0900

Sheet Loan commitments received
A1: SUM_of_SUM_of_msaldo_final | B1: contraparte_i_desc | C1: flag_pme | D1: Intragrupo | E1: csector_inst
A2: 0 | B2: bancos centrais
A3: -140000000 | B3: bancos centrais | C3: 0
A4: -3758123 | B4: outras empresas nao financeiras
A5: -2.7446645e+08 | B5: outras instituicoes financeiras

Sheet Off-balance 
A1: SUM_of_SUM_of_msaldo_final | B1: contraparte_i_desc | C1: flag_pme | D1: Intragrupo | E1: csector_inst
A2: 0 | B2: bancos centrais
A3: -65055.68 | B3: bancos centrais | C3: 0
A4: 0.01 | B4: instituicoes de credito
A5: -57988990 | B5: instituicoes de credito | C5: 0
A6: -4.0517081e+08 | B6: instituicoes de credito | C6: 0 | D6: 1
A7: -1010000 | B7: instituicoes de credito | C7: 1
A8: 2790003.6 | B8: outras empresas nao financeiras
A9: -4.7761718e+09 | B9: outras empresas nao financeiras | C9: 0
A10: -46844038 | B10: outras empresas nao financeiras | C10: 0 | D10: 1
A11: -1.1831104e+09 | B11: outras empresas nao financeiras | C11: 1
A12: 0 | B12: outras instituicoes financeiras
A13: -76879637 | B13: outras instituicoes financeiras | C13: 0
A14: -6854388.3 | B14: outras instituicoes financeiras | C14: 0 | E14: S128
A15: -7.7344738e+08 | B15: outras instituicoes financeiras | C15: 0 | D15: 1
A16: -10509146 | B16: outras instituicoes financeiras | C16: 0 | D16: 1 | E16: S128
A17: -3780272.6 | B17: outras instituicoes financeiras | C17: 1
A18: -210976.75 | B18: outras instituicoes financeiras | C18: 1 | E18: S128
A19: 358214.29 | B19: particulares
A20: -1.8261427e+09 | B20: particulares | C20: 0
A21: -90326732 | B21: particulares | C21: 1
A22: 0 | B22: setor publico
A23: -2.3076783e+08 | B23: setor publico | C23: 0
A24: -79238178 | B24: setor publico | C24: 1

Sheet Derivados
A1: SUM_of_msaldo_final | B1: contraparte_i_desc | C1: flag_pme | D1: Calculation | E1: Intragrupo
A2: -1.3730829e+09 | B2: instituicoes de credito | C2: 0
A3: -1.4851958e+10 | B3: instituicoes de credito | C3: 0 | E3: 1
A4: -3.289276e+08 | B4: outras empresas nao financeiras | C4: 0
A5: -65181579 | B5: outras empresas nao financeiras | C5: 1
A6: -3800000000 | B6: outras instituicoes financeiras | C6: 0
A7: -212176240 | B7: outras instituicoes financeiras | C7: 0 | D7: S128 | E7: 1

Sheet T 03.01
A1: T 03.01 - Intragroup liabilities
D4: Columns
D5: Number | E5: Reconciliation with aggregated data | G5: Intragroup liabilities
E6: Line | F6: Column | G6: Insolvency ranking | H6: Contract identifier | I6: Entity name of lending entity | J6: Identifier of Lending Entity (preferably LEI) | K6: Type of identifier | L6: Relationship of lending entity with issuing entity | M6: Is lending entity included in the resolution group of reporting entity? | N6: Governing law | O6: If third country, contractual recognition | P6: Outstanding principal amount | Q6: Accrued interest | R6: Currency | S6: Issuance date | T6: Earliest redemption date | U6: Legal maturity | V6: Secured/unsecured | W6: Amount of pledge, lien or collateral | X6: Guarantor if applicable | Y6: Structured or other Non-Standard Terms | Z6: Amount meeting the conditions for Internal MREL eligibility | AA6: Qualifying as own funds | AB6: Amount Included in own funds, taking into account phase-out as applicable
D7: 0010 | E7: 0020 | F7: 0021 | G7: 0030 | H7: 0040 | I7: 0045 | J7: 0050 | K7: 0053 | L7: 0055 | M7: 0057 | N7: 0060 | O7: 0070 | P7: 0080 | Q7: 0090 | R7: 0100 | S7: 0110 | T7: 0120 | U7: 0130 | V7: 0140 | W7: 0150 | X7: 0160 | Y7: 0170 | Z7: 0175 | AA7: 0180 | AB7: 0190 | AC7: Apoio às datas
A8: Rows | B8: Row ID (Intragroup liability) | C8: 999 | D8: 1 | E8: r0320 - Deposits, not covered and not preferential | F8: c003x - Corporates | G8: Rank 12 - Ranking in insolvency (master scale) | H8: 000000000000000 | I8: GESBAN SERVICIOS A. GLOBALES SA - SUC PORTUGAL | J8: 7400760971 | K8: Type of identifier, other than LEI or MFI code | L8: Sister | M8: false | N8: Portugal | O8: Not applicable (Contractual recognition of bail-in powers) | P8: 671676.95 | Q8: 0 | R8: Euro | S8: 2021-12-31 | T8: 44564 | U8: 44564 | V8: Unsecured | W8: 0 | X8: N/A | Y8: Non-structured/Vanilla | AA8: No | AB8: 0 | AC8: =IFERROR(IF(DATEDIF(#REF!,U8,"m")<=1,1,IF(AND(DATEDIF(#REF!,U8,"m")>1,DATEDIF(#REF!,U8,"m")<12),2,IF(AND(DATEDIF(#REF!,U8,"m")>=12,DATEDIF(#REF!,U8,"m")<24),3,IF(DATEDIF(#REF!,U8,"m")>=24,4,"")))),IF(E8="r0320 - Deposits, not covered and not preferential",1,4)) -> 1
C9: 999 | D9: 2 | E9: r0320 - Deposits, not covered and not preferential | F9: c003x - Corporates | G9: Rank 12 - Ranking in insolvency (master scale) | H9: 000000000000000 | I9: Portal Universia | J9: 8046273535 | K9: Type of identifier, other than LEI or MFI code | L9: Sister | M9: false | N9: Portugal | O9: Not applicable (Contractual recognition of bail-in powers) | P9: 54615.88 | Q9: 0 | R9: Euro | S9: 2021-12-31 | T9: 44564 | U9: 44564 | V9: Unsecured | W9: 0 | X9: N/A | Y9: Non-structured/Vanilla | AA9: No | AB9: 0 | AC9: =IFERROR(IF(DATEDIF(#REF!,U9,"m")<=1,1,IF(AND(DATEDIF(#REF!,U9,"m")>1,DATEDIF(#REF!,U9,"m")<12),2,IF(AND(DATEDIF(#REF!,U9,"m")>=12,DATEDIF(#REF!,U9,"m")<24),3,IF(DATEDIF(#REF!,U9,"m")>=24,4,"")))),IF(E9="r0320 - Deposits, not covered and not preferential",1,4)) -> 1
C10: 999 | D10: 3 | E10: r0320 - Deposits, not covered and not preferential | F10: c003x - Corporates | G10: Rank 12 - Ranking in insolvency (master scale) | H10: 000000000000000 | I10: GEOBAN SA SUCURSAL EM PORTUGAL | J10: 7400315551 | K10: Type of identifier, other than LEI or MFI code | L10: Sister | M10: false | N10: Portugal | O10: Not applicable (Contractual recognition of bail-in powers) | P10: 1534356.4 | Q10: 0 | R10: Euro | S10: 2021-12-31 | T10: 44564 | U10: 44564 | V10: Unsecured | W10: 0 | X10: N/A | Y10: Non-structured/Vanilla | AA10: No | AB10: 0 | AC10: =IFERROR(IF(DATEDIF(#REF!,U10,"m")<=1,1,IF(AND(DATEDIF(#REF!,U10,"m")>1,DATEDIF(#REF!,U10,"m")<12),2,IF(AND(DATEDIF(#REF!,U10,"m")>=12,DATEDIF(#REF!,U10,"m")<24),3,IF(DATEDIF(#REF!,U10,"m")>=24,4,"")))),IF(E10="r0320 - Deposits, not covered and not preferential",1,4)) -> 1
C11: 999 | D11: 4 | E11: r0320 - Deposits, not covered and not preferential | F11: c003x - Corporates | G11: Rank 12 - Ranking in insolvency (master scale) | H11: 000000000000000 | I11: ISBAN - SUC PORTUGAL | J11: 7400456469 | K11: Type of identifier, other than LEI or MFI code | L11: Sister | M11: false | N11: Portugal | O11: Not applicable (Contractual recognition of bail-in powers) | P11: 6857006.7 | Q11: 0 | R11: Euro | S11: 2021-12-31 | T11: 44564 | U11: 44564 | V11: Unsecured | W11: 0 | X11: N/A | Y11: Non-structured/Vanilla | AA11: No | AB11: 0 | AC11: =IFERROR(IF(DATEDIF(#REF!,U11,"m")<=1,1,IF(AND(DATEDIF(#REF!,U11,"m")>1,DATEDIF(#REF!,U11,"m")<12),2,IF(AND(DATEDIF(#REF!,U11,"m")>=12,DATEDIF(#REF!,U11,"m")<24),3,IF(DATEDIF(#REF!,U11,"m")>=24,4,"")))),IF(E11="r0320 - Deposits, not covered and not preferential",1,4)) -> 1
C12: 999 | D12: 5 | E12: r0320 - Deposits, not covered and not preferential | F12: c003x - Corporates | G12: Rank 12 - Ranking in insolvency (master scale) | H12: 000000000000000 | I12: TottaUrbe | J12: 8000391312 | K12: Type of identifier, other than LEI or MFI code | L12: Sister | M12: true | N12: Portugal | O12: Not applicable (Contractual recognition of bail-in powers) | P12: 37572080 | Q12: 0 | R12: Euro | S12: 2021-12-31 | T12: 44564 | U12: 44564 | V12: Unsecured | W12: 0 | X12: N/A | Y12: Non-structured/Vanilla | AA12: No | AB12: 0 | AC12: =IFERROR(IF(DATEDIF(#REF!,U12,"m")<=1,1,IF(AND(DATEDIF(#REF!,U12,"m")>1,DATEDIF(#REF!,U12,"m")<12),2,IF(AND(DATEDIF(#REF!,U12,"m")>=12,DATEDIF(#REF!,U12,"m")<24),3,IF(DATEDIF(#REF!,U12,"m")>=24,4,"")))),IF(E12="r0320 - Deposits, not covered and not preferential",1,4)) -> 1
C13: 999 | D13: 6 | E13: r0320 - Deposits, not covered and not preferential | F13: c003x - Corporates | G13: Rank 12 - Ranking in insolvency (master scale) | H13: 000000000000000 | I13: CONSULTEAM-CONSULTORES GESTAO,SA | J13: 5100262318 | K13: Type of identifier, other than LEI or MFI code | L13: Sister | M13: false | N13: Portugal | O13: Not applicable (Contractual recognition of bail-in powers) | P13: 983570.28 | Q13: 0 | R13: Euro | S13: 2021-12-31 | T13: 44564 | U13: 44564 | V13: Unsecured | W13: 0 | X13: N/A | Y13: Non-structured/Vanilla | AA13: No | AB13: 0 | AC13: =IFERROR(IF(DATEDIF(#REF!,U13,"m")<=1,1,IF(AND(DATEDIF(#REF!,U13,"m")>1,DATEDIF(#REF!,U13,"m")<12),2,IF(AND(DATEDIF(#REF!,U13,"m")>=12,DATEDIF(#REF!,U13,"m")<24),3,IF(DATEDIF(#REF!,U13,"m")>=24,4,"")))),IF(E13="r0320 - Deposits, not covered and not preferential",1,4)) -> 1
C14: 999 | D14: 7 | E14: r0320 - Deposits, not covered and not preferential | F14: c003x - Corporates | G14: Rank 12 - Ranking in insolvency (master scale) | H14: 000000000000000 | I14: Taxageste | J14: 8044901277 | K14: Type of identifier, other than LEI or MFI code | L14: Sister | M14: true | N14: Portugal | O14: Not applicable (Contractual recognition of bail-in powers) | P14: 13753407 | Q14: 0 | R14: Euro | S14: 2021-12-31 | T14: 44564 | U14: 44564 | V14: Unsecured | W14: 0 | X14: N/A | Y14: Non-structured/Vanilla | AA14: No | AB14: 0 | AC14: =IFERROR(IF(DATEDIF(#REF!,U14,"m")<=1,1,IF(AND(DATEDIF(#REF!,U14,"m")>1,DATEDIF(#REF!,U14,"m")<12),2,IF(AND(DATEDIF(#REF!,U14,"m")>=12,DATEDIF(#REF!,U14,"m")<24),3,IF(DATEDIF(#REF!,U14,"m")>=24,4,"")))),IF(E14="r0320 - Deposits, not covered and not preferential",1,4)) -> 1
C15: 999 | D15: 8 | E15: r0320 - Deposits, not covered and not preferential | F15: c003x - Corporates | G15: Rank 12 - Ranking in insolvency (master scale) | H15: 000000000000000 | I15: IBERICA DE COMPRAS CORPORATIVAS - SUC EM PORTUGAL | J15: 7400939384 | K15: Type of identifier, other than LEI or MFI code | L15: Sister | M15: false | N15: Portugal | O15: Not applicable (Contractual recognition of bail-in powers) | P15: 1012164.6 | Q15: 0 | R15: Euro | S15: 2021-12-31 | T15: 44564 | U15: 44564 | V15: Unsecured | W15: 0 | X15: N/A | Y15: Non-structured/Vanilla | AA15: No | AB15: 0 | AC15: =IFERROR(IF(DATEDIF(#REF!,U15,"m")<=1,1,IF(AND(DATEDIF(#REF!,U15,"m")>1,DATEDIF(#REF!,U15,"m")<12),2,IF(AND(DATEDIF(#REF!,U15,"m")>=12,DATEDIF(#REF!,U15,"m")<24),3,IF(DATEDIF(#REF!,U15,"m")>=24,4,"")))),IF(E15="r0320 - Deposits, not covered and not preferential",1,4)) -> 1
C16: 999 | D16: 9 | E16: r0320 - Deposits, not covered and not preferential | F16: c003x - Corporates | G16: Rank 12 - Ranking in insolvency (master scale) | H16: 000000000000000 | I16: RETAMA REAL ESTATE | J16: 7400886823 | K16: Type of identifier, other than LEI or MFI code | L16: Sister | M16: false | N16: Portugal | O16: Not applicable (Contractual recognition of bail-in powers) | P16: 0 | Q16: 0 | R16: Euro | S16: 2021-12-31 | T16: 44564 | U16: 44564 | V16: Unsecured | W16: 0 | X16: N/A | Y16: Non-structured/Vanilla | AA16: No | AB16: 0 | AC16: =IFERROR(IF(DATEDIF(#REF!,U16,"m")<=1,1,IF(AND(DATEDIF(#REF!,U16,"m")>1,DATEDIF(#REF!,U16,"m")<12),2,IF(AND(DATEDIF(#REF!,U16,"m")>=12,DATEDIF(#REF!,U16,"m")<24),3,IF(DATEDIF(#REF!,U16,"m")>=24,4,"")))),IF(E16="r0320 - Deposits, not covered and not preferential",1,4)) -> 1
C17: 999 | D17: 10 | E17: r0320 - Deposits, not covered and not preferential | F17: c002x - Micro & SME | G17: Rank 12 - Ranking in insolvency (master scale) | H17: 000000000000000 | I17: CCPT - COMPRARCASA REDE SERVICOS IMOBILIARIOS, S.A | J17: 1700210720 | K17: Type of identifier, other than LEI or MFI code | L17: Sister | M17: false | N17: Portugal | O17: Not applicable (Contractual recognition of bail-in powers) | P17: 1834.98 | Q17: 0 | R17: Euro | S17: 2021-12-31 | T17: 44564 | U17: 44564 | V17: Unsecured | W17: 0 | X17: N/A | Y17: Non-structured/Vanilla | AA17: No | AB17: 0 | AC17: =IFERROR(IF(DATEDIF(#REF!,U17,"m")<=1,1,IF(AND(DATEDIF(#REF!,U17,"m")>1,DATEDIF(#REF!,U17,"m")<12),2,IF(AND(DATEDIF(#REF!,U17,"m")>=12,DATEDIF(#REF!,U17,"m")<24),3,IF(DATEDIF(#REF!,U17,"m")>=24,4,"")))),IF(E17="r0320 - Deposits, not covered and not preferential",1,4)) -> 1
C18: 999 | D18: 11 | E18: r0210 - Liabilities towards other entities of the resolution group (BRRD art. 44/2/h) | F18: c006x - Insurance firms & pension funds | H18: 000000000000000 | I18: POPULAR SEGUROS - COMPANHIA DE SEGUROS, SA | J18: 213800DS888O1NMGEJ90 | K18: LEI code | L18: Sister | M18: true | N18: Portugal | O18: Not applicable (Contractual recognition of bail-in powers) | P18: 10885798 | Q18: 0 | R18: Euro | S18: 2021-12-31 | T18: 2021-12-31 | U18: 2021-12-31 | V18: Unsecured | W18: 0 | X18: N/A | Y18: Structured | AA18: No | AB18: 0 | AC18: =IFERROR(IF(DATEDIF(#REF!,U18,"m")<=1,1,IF(AND(DATEDIF(#REF!,U18,"m")>1,DATEDIF(#REF!,U18,"m")<12),2,IF(AND(DATEDIF(#REF!,U18,"m")>=12,DATEDIF(#REF!,U18,"m")<24),3,IF(DATEDIF(#REF!,U18,"m")>=24,4,"")))),IF(E18="r0320 - Deposits, not covered and not preferential",1,4)) -> 4
C19: 999 | D19: 12 | E19: r0210 - Liabilities towards other entities of the resolution group (BRRD art. 44/2/h) | F19: c005x - Other financial corporations | H19: 000000000000000 | I19: GAMMA SOC TITULARIZACAO CREDITOS, SA | J19: 2101355138 | K19: Type of identifier, other than LEI or MFI code | L19: Sister | M19: true | N19: Portugal | O19: Not applicable (Contractual recognition of bail-in powers) | P19: 1.869448e+08 | Q19: 0 | R19: Euro | S19: 2021-12-31 | T19: 2021-12-31 | U19: 2021-12-31 | V19: Unsecured | W19: 0 | X19: N/A | Y19: Structured | AA19: No | AB19: 0 | AC19: =IFERROR(IF(DATEDIF(#REF!,U19,"m")<=1,1,IF(AND(DATEDIF(#REF!,U19,"m")>1,DATEDIF(#REF!,U19,"m")<12),2,IF(AND(DATEDIF(#REF!,U19,"m")>=12,DATEDIF(#REF!,U19,"m")<24),3,IF(DATEDIF(#REF!,U19,"m")>=24,4,"")))),IF(E19="r0320 - Deposits, not covered and not preferential",1,4)) -> 4
C20: 999 | D20: 13 | E20: r0210 - Liabilities towards other entities of the resolution group (BRRD art. 44/2/h) | F20: c005x - Other financial corporations | H20: 000000000000000 | I20: Totta Ireland, PLC | J20: 8041492238 | K20: Type of identifier, other than LEI or MFI code | L20: Sister | M20: true | N20: Portugal | O20: Not applicable (Contractual recognition of bail-in powers) | P20: 5293541 | Q20: 0 | R20: Euro | S20: 2021-12-31 | T20: 2021-12-31 | U20: 2021-12-31 | V20: Unsecured | W20: 0 | X20: N/A | Y20: Structured | AA20: No | AB20: 0 | AC20: =IFERROR(IF(DATEDIF(#REF!,U20,"m")<=1,1,IF(AND(DATEDIF(#REF!,U20,"m")>1,DATEDIF(#REF!,U20,"m")<12),2,IF(AND(DATEDIF(#REF!,U20,"m")>=12,DATEDIF(#REF!,U20,"m")<24),3,IF(DATEDIF(#REF!,U20,"m")>=24,4,"")))),IF(E20="r0320 - Deposits, not covered and not preferential",1,4)) -> 4
C21: 999 | D21: 14 | E21: r0210 - Liabilities towards other entities of the resolution group (BRRD art. 44/2/h) | F21: c004x - Institutions | H21: 000000000000000 | I21: BANCO SANTANDER TOTTA SA | J21: 549300URJH9VSI58CS32 | K21: LEI code | L21: Parent | M21: false | N21: Portugal | O21: Not applicable (Contractual recognition of bail-in powers) | P21: 11361.96 | Q21: 0 | R21: Euro | S21: 2021-12-31 | T21: 2021-12-31 | U21: 2021-12-31 | V21: Unsecured | W21: 0 | X21: N/A | Y21: Structured | AA21: No | AB21: 0 | AC21: =IFERROR(IF(DATEDIF(#REF!,U21,"m")<=1,1,IF(AND(DATEDIF(#REF!,U21,"m")>1,DATEDIF(#REF!,U21,"m")<12),2,IF(AND(DATEDIF(#REF!,U21,"m")>=12,DATEDIF(#REF!,U21,"m")<24),3,IF(DATEDIF(#REF!,U21,"m")>=24,4,"")))),IF(E21="r0320 - Deposits, not covered and not preferential",1,4)) -> 4
C22: 999 | D22: 15 | E22: r0210 - Liabilities towards other entities of the resolution group (BRRD art. 44/2/h) | F22: c006x - Insurance firms & pension funds | H22: 000000000000000 | I22: Totta Seguros - Comp. Seg. Vida, SA. | J22: 54930006K2IUPA083C07 | K22: LEI code | L22: Sister | M22: true | N22: Portugal | O22: Not applicable (Contractual recognition of bail-in powers) | P22: 2.4837045e+08 | Q22: 677.16 | R22: Euro | S22: 2021-12-31 | T22: 2021-12-31 | U22: 2021-12-31 | V22: Unsecured | W22: 0 | X22: N/A | Y22: Structured | AA22: No | AB22: 0 | AC22: =IFERROR(IF(DATEDIF(#REF!,U22,"m")<=1,1,IF(AND(DATEDIF(#REF!,U22,"m")>1,DATEDIF(#REF!,U22,"m")<12),2,IF(AND(DATEDIF(#REF!,U22,"m")>=12,DATEDIF(#REF!,U22,"m")<24),3,IF(DATEDIF(#REF!,U22,"m")>=24,4,"")))),IF(E22="r0320 - Deposits, not covered and not preferential",1,4)) -> 4
C23: 999 | D23: 16 | E23: r0210 - Liabilities towards other entities of the resolution group (BRRD art. 44/2/h) | F23: c006x - Insurance firms & pension funds | H23: 000000000000000 | I23: AEGON SANTANDER NAO VIDA PORTUGAL | J23: 9598001GSAW026UNLE02 | K23: LEI code | L23: Sister | M23: true | N23: Portugal | O23: Not applicable (Contractual recognition of bail-in powers) | P23: 5303802.1 | Q23: 0 | R23: Euro | S23: 2021-12-31 | T23: 2021-12-31 | U23: 2021-12-31 | V23: Unsecured | W23: 0 | X23: N/A | Y23: Structured | AA23: No | AB23: 0 | AC23: =IFERROR(IF(DATEDIF(#REF!,U23,"m")<=1,1,IF(AND(DATEDIF(#REF!,U23,"m")>1,DATEDIF(#REF!,U23,"m")<12),2,IF(AND(DATEDIF(#REF!,U23,"m")>=12,DATEDIF(#REF!,U23,"m")<24),3,IF(DATEDIF(#REF!,U23,"m")>=24,4,"")))),IF(E23="r0320 - Deposits, not covered and not preferential",1,4)) -> 4
C24: 999 | D24: 17 | E24: r0210 - Liabilities towards other entities of the resolution group (BRRD art. 44/2/h) | F24: c006x - Insurance firms & pension funds | H24: 000000000000000 | I24: AEGON SANTANDER VIDA PORTUGAL | J24: 959800S4Y2DCN7EVAG59 | K24: LEI code | L24: Sister | M24: true | N24: Portugal | O24: Not applicable (Contractual recognition of bail-in powers) | P24: 8439317.9 | Q24: 0 | R24: Euro | S24: 2021-12-31 | T24: 2021-12-31 | U24: 2021-12-31 | V24: Unsecured | W24: 0 | X24: N/A | Y24: Structured | AA24: No | AB24: 0 | AC24: =IFERROR(IF(DATEDIF(#REF!,U24,"m")<=1,1,IF(AND(DATEDIF(#REF!,U24,"m")>1,DATEDIF(#REF!,U24,"m")<12),2,IF(AND(DATEDIF(#REF!,U24,"m")>=12,DATEDIF(#REF!,U24,"m")<24),3,IF(DATEDIF(#REF!,U24,"m")>=24,4,"")))),IF(E24="r0320 - Deposits, not covered and not preferential",1,4)) -> 4
C25: 999 | D25: 18 | E25: r0210 - Liabilities towards other entities of the resolution group (BRRD art. 44/2/h) | F25: c006x - Insurance firms & pension funds | H25: 000002000000000 | I25: Totta Seguros - Comp. Seg. Vida, SA. | J25: 54930006K2IUPA083C07 | K25: LEI code | L25: Sister | M25: true | N25: Portugal | O25: Not applicable (Contractual recognition of bail-in powers) | P25: 2760000 | Q25: 5812.51 | R25: Euro | S25: 2021-12-31 | T25: 2021-12-31 | U25: 2021-12-31 | V25: Unsecured | W25: 0 | X25: N/A | Y25: Structured | AA25: No | AB25: 0 | AC25: =IFERROR(IF(DATEDIF(#REF!,U25,"m")<=1,1,IF(AND(DATEDIF(#REF!,U25,"m")>1,DATEDIF(#REF!,U25,"m")<12),2,IF(AND(DATEDIF(#REF!,U25,"m")>=12,DATEDIF(#REF!,U25,"m")<24),3,IF(DATEDIF(#REF!,U25,"m")>=24,4,"")))),IF(E25="r0320 - Deposits, not covered and not preferential",1,4)) -> 4
C26: 999 | D26: 19 | E26: r0210 - Liabilities towards other entities of the resolution group (BRRD art. 44/2/h) | F26: c005x - Other financial corporations | H26: 000000000000000 | I26: GAMMA - SOCIEDADE DE TITULIZACAO DE CREDITOS | J26: 7401393942 | K26: Type of identifier, other than LEI or MFI code | L26: Sister | M26: true | N26: Portugal | O26: Not applicable (Contractual recognition of bail-in powers) | P26: 93903231 | Q26: 0 | R26: Euro | S26: 2021-12-31 | T26: 2021-12-31 | U26: 2021-12-31 | V26: Unsecured | W26: 0 | X26: N/A | Y26: Structured | AA26: No | AB26: 0 | AC26: =IFERROR(IF(DATEDIF(#REF!,U26,"m")<=1,1,IF(AND(DATEDIF(#REF!,U26,"m")>1,DATEDIF(#REF!,U26,"m")<12),2,IF(AND(DATEDIF(#REF!,U26,"m")>=12,DATEDIF(#REF!,U26,"m")<24),3,IF(DATEDIF(#REF!,U26,"m")>=24,4,"")))),IF(E26="r0320 - Deposits, not covered and not preferential",1,4)) -> 4
C27: 999 | D27: 20 | E27: r0210 - Liabilities towards other entities of the resolution group (BRRD art. 44/2/h) | F27: c004x - Institutions | H27: 000000000000000 | I27: BANCO SANTANDER TOTTA | J27: 549300URJH9VSI58CS32 | K27: LEI code | L27: Sister | M27: false | N27: Portugal | O27: Not applicable (Contractual recognition of bail-in powers) | P27: 27137.78 | Q27: 0 | R27: Euro | S27: 2021-12-31 | T27: 2021-12-31 | U27: 2021-12-31 | V27: Unsecured | W27: 0 | X27: N/A | Y27: Structured | AA27: No | AB27: 0 | AC27: =IFERROR(IF(DATEDIF(#REF!,U27,"m")<=1,1,IF(AND(DATEDIF(#REF!,U27,"m")>1,DATEDIF(#REF!,U27,"m")<12),2,IF(AND(DATEDIF(#REF!,U27,"m")>=12,DATEDIF(#REF!,U27,"m")<24),3,IF(DATEDIF(#REF!,U27,"m")>=24,4,"")))),IF(E27="r0320 - Deposits, not covered and not preferential",1,4)) -> 4
C28: 999 | D28: 21 | E28: r0390 - Non-financial liabilities | F28: c004x - Institutions | G28: Rank 9 - Ranking in insolvency (master scale) | H28: 962304870356080 | I28: BSCH-Banco Santander Central Hispano | J28: 5493006QMFDDMYWIAM13 | K28: LEI code | L28: Sister | M28: false | N28: Portugal | O28: Not applicable (Contractual recognition of bail-in powers) | P28: 9.15 | Q28: 0 | R28: Euro | S28: -- | T28: -- | U28: -- | V28: Unsecured | W28: 0 | X28: N/A | Y28: Structured | AA28: No | AB28: 0 | AC28: =IFERROR(IF(DATEDIF(#REF!,U28,"m")<=1,1,IF(AND(DATEDIF(#REF!,U28,"m")>1,DATEDIF(#REF!,U28,"m")<12),2,IF(AND(DATEDIF(#REF!,U28,"m")>=12,DATEDIF(#REF!,U28,"m")<24),3,IF(DATEDIF(#REF!,U28,"m")>=24,4,"")))),IF(E28="r0320 - Deposits, not covered and not preferential",1,4)) -> 4
C29: 999 | D29: 22 | E29: r0390 - Non-financial liabilities | F29: c004x - Institutions | G29: Rank 9 - Ranking in insolvency (master scale) | H29: 599904832822330 | I29: BANCO SANTANDER TOTTA SA | J29: 549300URJH9VSI58CS32 | K29: LEI code | L29: Parent | M29: false | N29: Portugal | O29: Not applicable (Contractual recognition of bail-in powers) | P29: 0.1 | Q29: 0 | R29: Euro | S29: -- | T29: -- | U29: -- | V29: Unsecured | W29: 0 | X29: N/A | Y29: Structured | AA29: No | AB29: 0 | AC29: =IFERROR(IF(DATEDIF(#REF!,U29,"m")<=1,1,IF(AND(DATEDIF(#REF!,U29,"m")>1,DATEDIF(#REF!,U29,"m")<12),2,IF(AND(DATEDIF(#REF!,U29,"m")>=12,DATEDIF(#REF!,U29,"m")<24),3,IF(DATEDIF(#REF!,U29,"m")>=24,4,"")))),IF(E29="r0320 - Deposits, not covered and not preferential",1,4)) -> 4
C30: 999 | D30: 23 | E30: r0120 - Secured liabilities - collateralized part (BRRD art. 44/2/b) | F30: c005x - Other financial corporations | G30: Rank 20 - Ranking in insolvency (master scale) | H30: 333000000000000 | I30: HIPOTOTTA 5 PLC | J30: 7400987939 | K30: Type of identifier, other than LEI or MFI code | L30: Sister | M30: true | N30: Portugal | O30: Not applicable (Contractual recognition of bail-in powers) | P30: 86101.18 | Q30: 11.01 | R30: Euro | S30: -- | U30: -- | V30: Secured | W30: 0 | X30: N/A | Y30: Non-structured/Vanilla | AA30: No | AB30: 0 | AC30: =IFERROR(IF(DATEDIF(#REF!,U30,"m")<=1,1,IF(AND(DATEDIF(#REF!,U30,"m")>1,DATEDIF(#REF!,U30,"m")<12),2,IF(AND(DATEDIF(#REF!,U30,"m")>=12,DATEDIF(#REF!,U30,"m")<24),3,IF(DATEDIF(#REF!,U30,"m")>=24,4,"")))),IF(E30="r0320 - Deposits, not covered and not preferential",1,4)) -> 4
C31: 999 | D31: 24 | E31: r0120 - Secured liabilities - collateralized part (BRRD art. 44/2/b) | F31: c005x - Other financial corporations | G31: Rank 20 - Ranking in insolvency (master scale) | H31: 365700000000000 | I31: HIPOTOTTA Nº 4 PLC | J31: 7400615058 | K31: Type of identifier, other than LEI or MFI code | L31: Sister | M31: true | N31: Portugal | O31: Not applicable (Contractual recognition of bail-in powers) | P31: 146906.53 | Q31: 96.35 | R31: Euro | S31: -- | U31: -- | V31: Secured | W31: 0 | X31: N/A | Y31: Non-structured/Vanilla | AA31: No | AB31: 0 | AC31: =IFERROR(IF(DATEDIF(#REF!,U31,"m")<=1,1,IF(AND(DATEDIF(#REF!,U31,"m")>1,DATEDIF(#REF!,U31,"m")<12),2,IF(AND(DATEDIF(#REF!,U31,"m")>=12,DATEDIF(#REF!,U31,"m")<24),3,IF(DATEDIF(#REF!,U31,"m")>=24,4,"")))),IF(E31="r0320 - Deposits, not covered and not preferential",1,4)) -> 4
C32: 999 | D32: 25 | E32: r0390 - Non-financial liabilities | F32: c004x - Institutions | G32: Rank 9 - Ranking in insolvency (master scale) | H32: 599904816311470 | I32: BST | J32: 549300URJH9VSI58CS32 | K32: LEI code | L32: Sister | M32: false | N32: Portugal | O32: Not applicable (Contractual recognition of bail-in powers) | P32: 0.01 | Q32: 0 | R32: Euro | S32: -- | T32: -- | U32: -- | V32: Unsecured | W32: 0 | X32: N/A | Y32: Structured | AA32: No | AB32: 0 | AC32: =IFERROR(IF(DATEDIF(#REF!,U32,"m")<=1,1,IF(AND(DATEDIF(#REF!,U32,"m")>1,DATEDIF(#REF!,U32,"m")<12),2,IF(AND(DATEDIF(#REF!,U32,"m")>=12,DATEDIF(#REF!,U32,"m")<24),3,IF(DATEDIF(#REF!,U32,"m")>=24,4,"")))),IF(E32="r0320 - Deposits, not covered and not preferential",1,4)) -> 4
C33: 999 | D33: 26 | E33: r0390 - Non-financial liabilities | F33: c004x - Institutions | G33: Rank 9 - Ranking in insolvency (master scale) | H33: 262304840024000 | I33: BANCO SANTANDER TOTTA | J33: 549300URJH9VSI58CS32 | K33: LEI code | L33: Sister | M33: false | N33: Portugal | O33: Not applicable (Contractual recognition of bail-in powers) | P33: 0.3 | Q33: 0 | R33: Euro | S33: -- | T33: -- | U33: -- | V33: Unsecured | W33: 0 | X33: N/A | Y33: Structured | AA33: No | AB33: 0 | AC33: =IFERROR(IF(DATEDIF(#REF!,U33,"m")<=1,1,IF(AND(DATEDIF(#REF!,U33,"m")>1,DATEDIF(#REF!,U33,"m")<12),2,IF(AND(DATEDIF(#REF!,U33,"m")>=12,DATEDIF(#REF!,U33,"m")<24),3,IF(DATEDIF(#REF!,U33,"m")>=24,4,"")))),IF(E33="r0320 - Deposits, not covered and not preferential",1,4)) -> 4
C34: 999 | D34: 27 | E34: r0390 - Non-financial liabilities | F34: c004x - Institutions | G34: Rank 9 - Ranking in insolvency (master scale) | H34: 962304820354640 | I34: BANCO SANTANDER PARIS | J34: 7400416227 | K34: Type of identifier, other than LEI or MFI code | L34: Sister | M34: false | N34: Portugal | O34: Not applicable (Contractual recognition of bail-in powers) | P34: 3.87 | Q34: 0 | R34: Euro | S34: -- | T34: -- | U34: -- | V34: Unsecured | W34: 0 | X34: N/A | Y34: Structured | AA34: No | AB34: 0 | AC34: =IFERROR(IF(DATEDIF(#REF!,U34,"m")<=1,1,IF(AND(DATEDIF(#REF!,U34,"m")>1,DATEDIF(#REF!,U34,"m")<12),2,IF(AND(DATEDIF(#REF!,U34,"m")>=12,DATEDIF(#REF!,U34,"m")<24),3,IF(DATEDIF(#REF!,U34,"m")>=24,4,"")))),IF(E34="r0320 - Deposits, not covered and not preferential",1,4)) -> 4
C35: 999 | D35: 28 | E35: r0120 - Secured liabilities - collateralized part (BRRD art. 44/2/b) | F35: c005x - Other financial corporations | G35: Rank 20 - Ranking in insolvency (master scale) | H35: 336500000000000 | I35: HIPOTOTTA Nº 4 PLC | J35: 7400615058 | K35: Type of identifier, other than LEI or MFI code | L35: Sister | M35: true | N35: Portugal | O35: Not applicable (Contractual recognition of bail-in powers) | P35: 57011.18 | Q35: 73.68 | R35: Euro | S35: -- | U35: -- | V35: Secured | W35: 0 | X35: N/A | Y35: Non-structured/Vanilla | AA35: No | AB35: 0 | AC35: =IFERROR(IF(DATEDIF(#REF!,U35,"m")<=1,1,IF(AND(DATEDIF(#REF!,U35,"m")>1,DATEDIF(#REF!,U35,"m")<12),2,IF(AND(DATEDIF(#REF!,U35,"m")>=12,DATEDIF(#REF!,U35,"m")<24),3,IF(DATEDIF(#REF!,U35,"m")>=24,4,"")))),IF(E35="r0320 - Deposits, not covered and not preferential",1,4)) -> 4
C36: 999 | D36: 29 | E36: r0390 - Non-financial liabilities | F36: c004x - Institutions | G36: Rank 9 - Ranking in insolvency (master scale) | H36: 862304880011980 | I36: BANCO SANTANDER TOTTA | J36: 549300URJH9VSI58CS32 | K36: LEI code | L36: Sister | M36: false | N36: Portugal | O36: Not applicable (Contractual recognition of bail-in powers) | P36: 1.33 | Q36: 0 | R36: Euro | S36: -- | T36: -- | U36: -- | V36: Unsecured | W36: 0 | X36: N/A | Y36: Structured | AA36: No | AB36: 0 | AC36: =IFERROR(IF(DATEDIF(#REF!,U36,"m")<=1,1,IF(AND(DATEDIF(#REF!,U36,"m")>1,DATEDIF(#REF!,U36,"m")<12),2,IF(AND(DATEDIF(#REF!,U36,"m")>=12,DATEDIF(#REF!,U36,"m")<24),3,IF(DATEDIF(#REF!,U36,"m")>=24,4,"")))),IF(E36="r0320 - Deposits, not covered and not preferential",1,4)) -> 4
C37: 999 | D37: 30 | E37: r0120 - Secured liabilities - collateralized part (BRRD art. 44/2/b) | F37: c005x - Other financial corporations | G37: Rank 20 - Ranking in insolvency (master scale) | H37: 368200000000000 | I37: HIPOTOTTA Nº 4 PLC | J37: 7400615058 | K37: Type of identifier, other than LEI or MFI code | L37: Sister | M37: true | N37: Portugal | O37: Not applicable (Contractual recognition of bail-in powers) | P37: 46427.45 | Q37: 84.54 | R37: Euro | S37: -- | U37: -- | V37: Secured | W37: 0 | X37: N/A | Y37: Non-structured/Vanilla | AA37: No | AB37: 0 | AC37: =IFERROR(IF(DATEDIF(#REF!,U37,"m")<=1,1,IF(AND(DATEDIF(#REF!,U37,"m")>1,DATEDIF(#REF!,U37,"m")<12),2,IF(AND(DATEDIF(#REF!,U37,"m")>=12,DATEDIF(#REF!,U37,"m")<24),3,IF(DATEDIF(#REF!,U37,"m")>=24,4,"")))),IF(E37="r0320 - Deposits, not covered and not preferential",1,4)) -> 4
C38: 999 | D38: 31 | E38: r0390 - Non-financial liabilities | F38: c004x - Institutions | G38: Rank 9 - Ranking in insolvency (master scale) | H38: 262304820021230 | I38: BANCO SANTANDER TOTTA | J38: 549300URJH9VSI58CS32 | K38: LEI code | L38: Sister | M38: false | N38: Portugal | O38: Not applicable (Contractual recognition of bail-in powers) | P38: 0.67 | Q38: 0 | R38: Euro | S38: -- | T38: -- | U38: -- | V38: Unsecured | W38: 0 | X38: N/A | Y38: Structured | AA38: No | AB38: 0 | AC38: =IFERROR(IF(DATEDIF(#REF!,U38,"m")<=1,1,IF(AND(DATEDIF(#REF!,U38,"m")>1,DATEDIF(#REF!,U38,"m")<12),2,IF(AND(DATEDIF(#REF!,U38,"m")>=12,DATEDIF(#REF!,U38,"m")<24),3,IF(DATEDIF(#REF!,U38,"m")>=24,4,"")))),IF(E38="r0320 - Deposits, not covered and not preferential",1,4)) -> 4
C39: 999 | D39: 32 | E39: r0390 - Non-financial liabilities | F39: c004x - Institutions | G39: Rank 9 - Ranking in insolvency (master scale) | H39: 599904815741130 | I39: BST | J39: 549300URJH9VSI58CS32 | K39: LEI code | L39: Sister | M39: false | N39: Portugal | O39: Not applicable (Contractual recognition of bail-in powers) | P39: 0.01 | Q39: 0 | R39: Euro | S39: -- | T39: -- | U39: -- | V39: Unsecured | W39: 0 | X39: N/A | Y39: Structured | AA39: No | AB39: 0 | AC39: =IFERROR(IF(DATEDIF(#REF!,U39,"m")<=1,1,IF(AND(DATEDIF(#REF!,U39,"m")>1,DATEDIF(#REF!,U39,"m")<12),2,IF(AND(DATEDIF(#REF!,U39,"m")>=12,DATEDIF(#REF!,U39,"m")<24),3,IF(DATEDIF(#REF!,U39,"m")>=24,4,"")))),IF(E39="r0320 - Deposits, not covered and not preferential",1,4)) -> 4
