Workbook
Name asefadf: #REF!
Name asefadf: #REF!
Name asefadf: #REF!
Name bn: '[2]Code List'!#REF!
Name bn: '[3]Code List'!#REF!
Name bn: '[2]Code List'!#REF!
Name Estados: Table7[Estados]
Name Pendências: Table6[Pendências]

Sheet Capa
B4: BCE Loan Tape
B8: Lisboa, | C8: =TODAY() -> 46128

Sheet 1. Metodologia
B5: Metodologia de aplicação de especificação
B7: 1. Enquadramento | G7: O presente documento de especificação é realizado no âmbito do projeto da Loan Tape para o BCE. A metodologia de cálculo prevista neste documento deve considerar, adicionalmente, níveis de aplicação de "Default values" (Not applicable ou Nullable), como explicado no esquema infra.
B9: 2. Níveis de aplicação de "Default Values"
G10: Nível 1. Aplicar os valores Not Applicable aos campos que não são reportados, via regra de report por segmento;
G11: Nível 2. Aplicar os valores Not Applicable aos campos que verificam as regras de negócio identificadas pela corporação;
G12: Nível 3. Aplicar os valores Nullable aos campos que após a aplicação das regras 1 e 2 persistam sem valor ou com valores default provenientes das respetivas origens.
K14: Nível 1 | N14: Nível 2 | Q14: Nível 3
G21: * Regras definidas na coluna "Metodologia de Cálculo (NOT APLICABLE)" nas sheets Entity, Instrument, Instr_Entity, Protection e Instr_Protection do presente documento
G23: Legenda:
H25: Regras a definir no presente documento
H27: Regras a definir no documento "Definição Requisitos Loan Tape", produzido pela área do CDO
G30: Qualquer referência no presente documento aos níveis 1 e 3 deste processo, deve-se consultar o documento "Definição Requisitos Loan Tape"
B33: Notas adicionais | Metodologia de cálculo | G33: Todos os campos devem ser calculados sobre a data de referência em análise/processamento, exceto quando mencionado o contrário. Exemplo: se DT_RFRNC = '2021-12-31' então data de referência na fonte deverá ser DATA_DATE_PART = DT_RFRNC ou REF_DATE = DT_RFRNC
B35: Notas adicionais | Nível 3 - NULLABLE | G35: O valor de default de NULLABLE deve considerar todos os blanks, nulls e campos só com espaços na fonte ou quando determinadas chaves de contratato/cliente/garantia não cruzam com a fonte, exceto quando mencionado o contrário. Exemplos: TRIM(CAMPO_X) = '' então valor da coluna NULLABLE CAMPO_X is NULL então valor da coluna NULLABLE INSTRMNT_ID não existe na fonte (e não está mencionado nada na metodologia de NOT APPLICABLE) então valor da coluna NULLABLE

Sheet LT002_INSTRUMENT
B5: INPUT BCE | S5: INPUT CORPORAÇÃO | AB5: ESPECIFICAÇÃO
B6: TABLE_NAME | C6: COLUMN_NAME | D6: DATA_TYPE | E6: ANACREDIT | F6: CRP | G6: CRE | H6: LF | I6: RRE | J6: Retail SME | K6: Retail Other | L6: DESCRIPTION | M6: Field Definition / Additional Guidance | N6: Field Definition / Additional Guidance (new) | O6: Validação | P6: NULLABLE | Q6: NOT APPLICABLE | R6: Column5 | S6: ORDER | T6: Cash balances and other deposits | U6: General governments | V6: Credit institutions | W6: Other financial corporations | X6: Non financial corporations | Y6: Households | Z6: DEBT SECURITIES | AA6: Column3 | AB6: Schema DL | AC6: Tabela | AD6: Campo | AE6: Metodologia de Cálculo | AF6: Metodologia de Cálculo (NOT APPLICABLE) | AG6: Metodologia de cruzamento | AH6: Column2 | AI6: DT Atualização - Especificação | AJ6: Histórico EF | AK6: Observações Metodologia / Conceito | AL6: CRC/ Anacredit | AM6: Guia Corporativo | AN6: Melhoria | AO6: Revisto | AP6: Temática | AQ6: Área | AR6: Responável área | AS6: Notas Reuniões | AT6: Reunião com LCM | AU6: Alteração EF
A7: =_xlfn.CONCAT(Table2[[#This Row],[TABLE_NAME]],Table2[[#This Row],[COLUMN_NAME]]) -> INSTRUMENTACCMLTD_CHNGS_FV_CR_INSTRMNT | B7: INSTRUMENT | C7: ACCMLTD_CHNGS_FV_CR_INSTRMNT | D7: FLOAT 2 decimal places | E7: Y | F7: Y | G7: N | H7: N | I7: N | J7: N | K7: N | L7: Accumulated changes in fair value due to credit risk | M7: Accumulated changes in fair value due to credit risk in accordance with Part 2.46 of Annex V to Implementing Regulation (EU) No 680/2014. | N7: Accumulated changes in fair value due to credit risk in accordance with Part 2.46 of Annex V to Implementing Regulation (EU) No 680/2014. | O7: TRUE | P7: 99999999999 | Q7: 11111111111 | S7: IN.061 | T7: N | U7: Y | V7: Y | W7: Y | X7: Y | Y7: N | Z7: Y | AB7: FIXO | AC7: FIXO | AD7: FIXO | AE7: 0 | AF7: - Se PRFRMNG_STTS <> '1' - Se ACCNTNG_CLSSFCTN not in ('4','41') | AG7: - | AI7: 45065 | AJ7: 08/11/21: A metodologia de Not Applicable mantém-se igual à versão original (não foi aplicada a metodologia de default values proposta pela corporação). 29/05/2023: Atualização de metodologia de Not Applicable e cálculo. | AK7: Metodologia / Conceito: 1) No mapa F18 o campo está a ser reportado a vazio. Para os instrumentos a "fair value through profit or loss" o GRSS_CRRYNG_AMNT_INSTRMNT = CRRYNG_AMNT_INSTRMNT + ACCMLTD_CHNGS_FV_CR_INSTRMNT 2) Aplicar metodologia de N/A definida pela Corporação; 3) Caso o contrato não cumpra as condições de N/A, deve ser reportado 0, à semelhança do FINREP/NOPER; 4) Não está planeado o FINREP passar a reportar esta informação. Especificado/ Revisto por: Contabilidade (Luisa de Sousa) Guia de conceitos da Corporação: De acordo com o pretendido no Guia. | AL7: Campo: varAcumRC De acordo com o reportado na AnaCredit | AM7: OK | AN7: N | AO7: Y | AP7: Contabilidade | AQ7: CONTABILIDADE | AR7: Rafael Pessoa | AS7: Configuração por subproduto (TAT91 Ctabela 927 e pedir para criar view sobre ela caso não exista) | AU7: 1
A8: =_xlfn.CONCAT(Table2[[#This Row],[TABLE_NAME]],Table2[[#This Row],[COLUMN_NAME]]) -> INSTRUMENTACCMLTD_IMPRMNT_INSTRMNT | B8: INSTRUMENT | C8: ACCMLTD_IMPRMNT_INSTRMNT | D8: FLOAT 2 decimal places | E8: Y | F8: Y | G8: Y | H8: Y | I8: Y | J8: Y | K8: Y | L8: Sum of LLPs and other allowances | M8: The amount of loss allowances that are held against or are allocated to the instrument on the reporting reference date. This data attribute applies to instruments subject to impairment under the applied accounting standard. Under IFRS, the accumulated impairment relates to the following amounts: (i) loss allowance at an amount equal to 12-month expected credit losses; (ii) loss allowance at an amount equal to lifetime expected credit losses. Under nGAAP, the accumulated impairment relates to the following amounts: (i) loss allowance at an amount equal to specific allowances; (ii) loss allowance at an amount equal to general allowances. | N8: The amount of loss allowances that are held against or are allocated to the instrument on the reporting reference date. This data attribute applies to instruments subject to impairment under the applied accounting standard. Under IFRS, the accumulated impairment relates to the following amounts: (i) loss allowance at an amount equal to 12-month expected credit losses; (ii) loss allowance at an amount equal to lifetime expected credit losses. Under nGAAP, the accumulated impairment relates to the following amounts: (i) loss allowance at an amount equal to specific allowances; (ii) loss allowance at an amount equal to general allowances. | O8: TRUE | P8: 99999999999 | Q8: 11111111111 | S8: IN.088 | T8: Y | U8: Y | V8: Y | W8: Y | X8: Y | Y8: Y | Z8: Y | AB8: CD_LOAN_TAPES_BCE | AC8: LT001_UNIV_OPER | AD8: PROVISAO_ON CARTEIRA_CONTABILISTICA | AE8: NVL ( SUM(PROVISAO_ON) ; 0 ) | AF8: Se ACCNTNG_CLSSFCTN IN ('2','4','41') | AG8: 1) Cruzar LT002_INSTRUMENT com LT001_UNIV_OPER para obter o campo PROVISAO_ON: LT002_INSTRUMENT LEFT JOIN (SELECT * FROM LT001_UNIV_OPER GROUP BY CEMPRESA, CBALCAO, CNUMECTA, ZDEPOSIT) ON INSTRMNT_ID = CONCAT(CEMPRESA, CBALCAO, CNUMECTA, ZDEPOSIT) | AI8: 46010 | AJ8: 08/11/21: A metodologia de Not Applicable mantém-se igual à versão original (não foi aplicada a metodologia de default values proposta pela corporação). 30/03/22: Atualização da metodologia de cálculo para prever os novos campos da LT001. 19/12/2025: Atualização da metodologia de NOT APPLICABLE quando ACCNTNG_CLSSFCTN IN ('2','4','41') | AK8: Metodologia / Conceito: 1) Somatório de provisões dentro de balanço que constam no mapa FINREP18/ NOPER. 2) De forma a coniliar com o FINREP, os campos de saldos têm como fonte o universo da LT (Tabela LT001 com as operações por conta contabilistica) que por sua vez tem como fonte a tabela de universo do FINREP (FR001). Especificado/ Revisto por: CDO (Luis Capitão-Mor) Guia de conceitos da Corporação: De acordo com o pretendido no Guia.
A9: =_xlfn.CONCAT(Table2[[#This Row],[TABLE_NAME]],Table2[[#This Row],[COLUMN_NAME]]) -> INSTRUMENTACCMLTD_IMPRMNT_INSTRMNT_PRVS | B9: INSTRUMENT | C9: ACCMLTD_IMPRMNT_INSTRMNT_PRVS | D9: FLOAT 2 decimal places | E9: N | F9: Y | G9: Y | H9: Y | I9: Y | J9: Y | K9: Y | L9: Previous sum of LLPs and other allowances | M9: The amount of loss allowances that are held against or are allocated to the instrument on the date one year before the reporting reference date. This data attribute applies to instruments subject to impairment under the applied accounting standard. Under IFRS, the accumulated impairment relates to the following amounts: (i) loss allowance at an amount equal to 12-month expected credit losses; (ii) loss allowance at an amount equal to lifetime expected credit losses. Under nGAAP, the accumulated impairment relates to the following amounts: (i) loss allowance at an amount equal to specific allowances; (ii) loss allowance at an amount equal to general allowances. | N9: The amount of loss allowances that are held against or are allocated to the instrument on the date one year before the loan tape reporting reference date. This data attribute applies to instruments subject to impairment under the applied accounting standard. Under IFRS, the accumulated impairment relates to the following amounts: (i) loss allowance at an amount equal to 12-month expected credit losses; (ii) loss allowance at an amount equal to lifetime expected credit losses. Under nGAAP, the accumulated impairment relates to the following amounts: (i) loss allowance at an amount equal to specific allowances; (ii) loss allowance at an amount equal to general allowances. | O9: FALSE | P9: 99999999999 | Q9: 11111111111 | S9: IN.089 | T9: Y | U9: Y | V9: Y | W9: Y | X9: Y | Y9: Y | Z9: Y | AB9: CD_LOAN_TAPES_BCE | AC9: LT001_UNIV_OPER | AD9: PROVISAO_ON_PRVS | AE9: NVL ( SUM(PROVISAO_ON_PRVS) ; 0 ) | AF9: - Se a DT_INCPTN > REF_DATE - 1 ANO - Se ACCNTNG_CLSSFCTN IN ('2','4','41') | AG9: 1) Cruzar LT002_INSTRUMENT com LT001_UNIV_OPER para obter o campo PROVISAO_ON_PRVS: LT002_INSTRUMENT LEFT JOIN (SELECT * FROM LT001_UNIV_OPER GROUP BY CEMPRESA, CBALCAO, CNUMECTA, ZDEPOSIT) ON INSTRMNT_ID = CONCAT(CEMPRESA, CBALCAO, CNUMECTA, ZDEPOSIT) | AI9: 46010 | AJ9: 08/11/21: Foram eliminadas da metodologia de Not Applicable as regras" - Se o campo ACCNTNG_CLSSFCTN assumir os valores: '2','4','41'; - Se todas as linhas do contrato na FR802, o campo PRODUTO assumir os valores: 'garantias prestadas','compromissos perante terceiros', 'outras responsabilidades perante terceiros','garantias financeiras prestadas';" 30/03/22: Atualização da metodologia de cálculo para prever os novos campos da LT001 19/12/2025: Foi atualizada a metodologia de cálculo para que o campo apresente o valor da coluna de nullable, até 2022-12-31 15/07/22: Foi anulada a última alteração (apagada a frase "* Reportar valor da coluna NULLABLE até 2022-12-31") 13/01/22: Alteração da metodologia de cálculo e Not Applicable para prever casos em que a REF_DATE de há 1 ano seja menor que a DT_INCPTN 26/06/2025: Criação do campo PROVISAO_ON_PRVS na LT001 e alteração da metodologia de cálculo para prever estes mesmos campos como fonte. O campo é calculado diretamente a partir dos campos do Universo. 02/12/2025: Atualização da metodologia de NOT APPLICABLE quando ACCNTNG_CLSSFCTN IN ('2','4','41') | AK9: Metodologia / Conceito: 1) Somatório de provisões dentro de balanço que constam no mapa FINREP18/ NOPER 1 ano antes da data de referência. 2) De forma a coniliar com o FINREP, os campos de saldos têm como fonte o universo da LT (Tabela LT001 com as operações por conta contabilistica) que por sua vez tem como fonte a tabela de universo do FINREP (FR001). 3) A condição de N/A foi definida de modo a estar de acordo com os controlos corporativos. Independentemente de essa condição não constar no guia corporativo. Especificado/ Revisto por: CDO (Luis Capitão-Mor) Guia de conceitos da Corporação: De acordo com o pretendido no Guia, exceto o reporte da informação à data de inception quando o contrato nasceu entre o ano anterior e a data de reporte. | AL9: N/A | AM9: OK | AN9: N | AO9: Y | AP9: Contabilidade | AQ9: CONTABILIDADE | AR9: Rafael Pessoa | AS9: Em reunião com Luis Capitão Mor e Luísa Reparamos que atual um determinado contrato não existir no ano passado então o valor PRVS deve ser marcado como N/A. No entanto, fomos rever o Granular Tool onde encontramos a seguinte condição: "If the operation was granted between the last reporting and the current one, in this case, it should be reported the amount at the inception date of the transaction." No entanto, nos controlos corporativos temos um controlo que diz caso o contrato não exista no ano anterior o valor a marcar é o de N/A. O Luis sugeriu manter a marcação como N/A, ignorando a condição do GT para que deste modo haja coerência com o controlo e evitemos de criar campos de saldos à data de INCPTN de cada um dos contratos. | AU9: 1
A10: =_xlfn.CONCAT(Table2[[#This Row],[TABLE_NAME]],Table2[[#This Row],[COLUMN_NAME]]) -> INSTRUMENTACCMLTD_WRTFFS_INSTRMNT | B10: INSTRUMENT | C10: ACCMLTD_WRTFFS_INSTRMNT | D10: FLOAT 2 decimal places | E10: Y | F10: Y | G10: Y | H10: Y | I10: Y | J10: Y | K10: Y | L10: Accumulated write-offs | M10: Cumulative amount of principal and past due interest of any debt instrument that the institution is no longer recognising because they are considered uncollectible, independently of the portfolio in which they were included. Write-offs could be caused both by reductions in the carrying amount of financial assets recognised directly in profit or loss and by reductions in the amounts of the allowance accounts for credit losses set off against the carrying amount of financial assets. | N10: Cumulative amount of principal and past due interest of any debt instrument that the institution is no longer recognising because they are considered uncollectible, independently of the portfolio in which they were included. Write-offs could be caused both by reductions in the carrying amount of financial assets recognised directly in profit or loss and by reductions in the amounts of the allowance accounts for credit losses set off against the carrying amount of financial assets. | O10: TRUE | P10: 99999999999 | Q10: 11111111111 | S10: IN.090 | T10: N | U10: Y | V10: Y | W10: Y | X10: Y | Y10: Y | Z10: Y | AB10: CD_CAPTOOLS | AC10: FR001_UNIV_SALDO | AD10: MSALDO_FINAL | AE10: NVL (SUM((-1)*MSALDO_FINAL) ,0 ) WHERE FR001_UNIV_SALDO.[CONTA] = FR802_PL_CONTAS.CONTA AND COD_PLANO = [COD_PLANO] AND COMPOSICAO_VALOR = 'capital abatido' Notas: 1) A variável [CONTA] proveniente da tabela FR001_UNIV_SALDO varia entre CCONTAB_FINAL_IFRS, CCONTAB_FINAL_ST_SGPS, CCONTAB_FINAL_SGPS_CONS, CCONTAB_FINAL_CARGABAL consoante o nome_perimetro calculado. 2) A variável [COD_PLANO] proveniente da tabela FR802_PL_CONTAS varia entre BST_IND, ST_SGPS, SGPS_CONSOLIDADO, CARGABAL consoante o nome_perimetro calculado. | AF10: - | AG10: 1) Cruzar LT002_INSTRUMENT com FR001_UNIV_SALDO para obter os campos MSALDO_FINAL e contas contabílisticas: LT002_INSTRUMENT LEFT JOIN (SELECT * FROM FR001_UNIV_SALDO) ON INSTRMNT_ID = CONCAT(CEMPRESA, CBALCAO, CNUMECTA, ZDEPOSIT) 2) Cruzar os campos obtidos no passo anterior com o plano de contas através da tabela FR802_PL_CONTAS: (SELECT * FROM FR802_PL_CONTAS) ON [CONTA] = CONTA A variável [CONTA] proveniente da tabela FR001_UNIV_SALDO varia entre CCONTAB_FINAL_IFRS, CCONTAB_FINAL_ST_SGPS, CCONTAB_FINAL_SGPS_CONS, CCONTAB_FINAL_CARGABAL consoante o nome_perimetro calculado. | AI10: 44518 | AJ10: 08/11/2021: Metodologia de cálculo em revisão 10/11/2021: Atualização da especificação da metodologia de cálculo. 18/11/2021: Atualização da especificação da metodologia de cálculo (após implementação da parametrização) | AK10: Metodologia / Conceito: 1) Campo deve ser reportado segundo o saldo (FR001_UNIV_SALDO) das contas contabilisticas referentes a capital abatido (presente no campo COMPOSICAO_VALOR da FR802_PL_CONTAS). 2) As contas contabilisticas e COD_PLANO devem ser filtrados de acordo com o perimetro em análise. 3) O valor 'capital abatido' no campo COMPOSICAO_VALOR só entrou em produção em outubro de 2021. Especificado/ Revisto por: Contabilidade (Luisa de Sousa) Guia de conceitos da Corporação: De acordo com o pretendido no Guia. | AL10: Campo: montAbAtv Não está de acordo com o reportado na AnaCredit: A CRC utiliza como fonte de dados as ICs (sem ajustes), não sendo possível conciliar com o reportado pela área da contabilidade. | AM10: OK | AN10: N | AO10: Y | AP10: Contabilidade | AQ10: CONTABILIDADE | AR10: Rafael Pessoa | AS10: 09/11/2021 Reunião LCM: A FR07_ABATIDOS tem os movimentos e não os acumulados. Para o FinRep os Write-offs estão a ir por conta contabilistica, o que poderá causar entropia com os diferentes perimetros (Individual/consolidado). Luisa e Rafael: incluir um atributo para os write-offs na FR802 (plano de contas) enviar email : composição valor - "abatidos" | AU10: 1
A11: =_xlfn.CONCAT(Table2[[#This Row],[TABLE_NAME]],Table2[[#This Row],[COLUMN_NAME]]) -> INSTRUMENTACCNTNG_CLSSFCTN | B11: INSTRUMENT | C11: ACCNTNG_CLSSFCTN | D11: Code List | E11: Y | F11: Y | G11: Y | H11: Y | I11: Y | J11: Y | K11: Y | L11: Accounting portfolio | M11: Accounting portfolio where the instrument is recorded in accordance with the accounting standard – IFRS or national GAAP – under Regulation (EU) 2015/534 (ECB/2015/13) applied by the observed agent’s legal entity. | N11: Accounting portfolio where the instrument is recorded in accordance with the accounting standard – IFRS or national GAAP – under Regulation (EU) 2015/534 (ECB/2015/13) applied by the observed agent’s legal entity. | O11: TRUE | P11: 99999999999 | Q11: 11111111111 | S11: IN.062 | T11: Y | U11: Y | V11: Y | W11: Y | X11: Y | Y11: Y | Z11: Y | AB11: CD_CAPTOOLS CD_LOAN_TAPES_BCE | AC11: LT001_UNIV_OPER LT803_CODIGOS_LT | AD11: CARTEIRA_CONTABILISTICA VALOR_LT | AE11: VALOR_LT WHERE CAMPO_LT = 'ACCNTNG_CLSSFCTN' AND CARTEIRA_CONTABILISTICA = VALOR_ORIGEM Em caso de duplicação de valores por contrato deve ser seguida a sequinte prioritização*: 1) carteira contabilística atribuída às contas dentro do balanço em detrimento das contas fora do balanço (1ºValor_bruto_on, 2ºProvisao_on, 3ºValor_bruto_off, 4ºProvisao_off) 2) carteira contabilística com saldo absoluto superior * O campo deve estar alinhado com o SUBPORTFOLIO_ID | AF11: - | AG11: 1) Cruzar LT002_INSTRUMENT com LT001_UNIV_OPER para obter a carteira contabilistica do contrato: LT002_INSTRUMENT LEFT JOIN (SELECT * FROM LT001_UNIV_OPER) ON INSTRMNT_ID = CONCAT(CEMPRESA, CBALCAO, CNUMECTA, ZDEPOSIT) 2) Cruzar campo obtido no passo anterior com a tabela de parametrização LT803_CODIGOS_LT de modo a obter os códigos permitidos na code list: LEFT JOIN (SELECT * FROM LT803_CODIGOS_LT) ON VALOR_ORIGEM = CARTEIRA_CONTABILISTICA | AI11: 44679 | AJ11: 08/11/21: A metodologia de Not Applicable mantém-se igual à versão original (não foi aplicada a metodologia de default values proposta pela corporação). 29/11/2021: Atualização de nomenclatura da tabela de parametrização - em vez de TABELA_PARAMETRIZACAO, LT803_CODIGOS_LT. Sem impactos a nível de implementação. 28/04/2022: Atualização da metodologia de cálculo (Condição de prioridade das contas dentro do balanço). 15/09/2023: Adição de condições na tabela de parametrização LT803_CODIGOS_LT. Sem impactos a nível de implementação. | AK11: Metodologia / Conceito: 1) Campo deve ser reportado segundo a carteira contabilistica de cada contrato (presente no campo CARTEIRA_CONTABILISTICA da LT001_UNIV_OPER) e parametrizado através da tabela de parametrização LT803_CODIGOS_LT. 2) Denote-se que caso um contrato tenha uma exposição patrimonial e extrapatrimonial, é dada prioridade á patrimonial (metodologia aplicada no campo implementado da tabela LT001_UNIV_OPER). Especificado/ Revisto por: Contabilidade (Rafael Pessoa) Guia de conceitos da Corporação: De acordo com o pretendido no Guia exceto para exposições 100% off-balance, onde não foi especificada nenhuma condição de not aplicable. | AL11: Campo: classContbInst Não está de acordo com o reportado na AnaCredit: Caso um contrato tiver uma exposição patrimonial e extrapatrimonial, a CRC considera um código correspondente a "Não aplicável". Na Loan Tape é dada prioridade à exposição patrimonial. | AM11: NOK - Not aplicable não foi especificada | AN11: N | AO11: Y | AP11: Contabilidade | AQ11: CONTABILIDADE | AR11: Rafael Pessoa | AU11: 1
A12: =_xlfn.CONCAT(Table2[[#This Row],[TABLE_NAME]],Table2[[#This Row],[COLUMN_NAME]]) -> INSTRUMENTACCRD_INTRST_INSTRMNT | B12: INSTRUMENT | C12: ACCRD_INTRST_INSTRMNT | D12: FLOAT 2 decimal places | E12: Y | F12: Y | G12: N | H12: Y | I12: Y | J12: Y | K12: Y | L12: Accrued interest balance as recognised on the balance sheet | M12: The amount of accrued interest on loans at the reporting reference date as defined in Regulation (EU) No 1071/2013 (ECB/2013/33). In accordance with the general principle of accruals accounting, interest receivable on instruments should be subject to on-balance sheet recording as it accrues (i.e. on an accruals basis) rather than when it is actually received (i.e. on a cash basis). | N12: The amount of accrued interest on loans at the reporting reference date as defined in Regulation (EU) No 1071/2013 (ECB/2013/33). In accordance with the general principle of accruals accounting, interest receivable on instruments should be subject to on-balance sheet recording as it accrues (i.e. on an accruals basis) rather than when it is actually received (i.e. on a cash basis). | O12: TRUE | P12: 99999999999 | Q12: 11111111111 | S12: IN.063 | T12: N | U12: Y | V12: Y | W12: Y | X12: Y | Y12: Y | Z12: Y | AB12: CD_LOAN_TAPES_BCE | AC12: LT001_UNIV_OPER KT_CHAVES_LT | AD12: ACCRD_INTRST_INSTRMNT | AE12: NVL ( SUM(-1*JUROS_CORRIDOS) ,0 ) | AF12: - | AG12: 1. CRUZAR LT002_INSTRUMENT COM O TRADUTOR DE CHAVES LOAN TAPE: LT002_INSTRUMENT INNER JOIN KT_CHAVES_LT ON CONCAT(CEMPRESA,CBALCAO,CNUMECTA,ZDEPOSIT)=INSTRMNT_ID 2. CRUZAR COM LT001_UNIV_OPER PARA OBTER O CAMPO ACCRD_INTRST_INSTRMNT: LEFT JOIN (SELECT * FROM LT001_UNIV_OPER GROUP BY CEMPRESA,CBALCAO,CNUMECTA,ZDEPOSIT) ON CONCAT(CEMPRESA,CBALCAO,CNUMECTA,ZDEPOSIT) = CONCAT(CEMPRESA,CBALCAO,CNUMECTA,ZDEPOSIT) | AI12: 45873 | AJ12: 08/11/21: A metodologia de Not Applicable mantém-se igual à versão original (não foi aplicada a metodologia de default values proposta pela corporação). 07/04/2025: Campo passa a ser aprovisionado através da LT001. 04/08/2025: Alterada metodologia de calculo para NVL (SUM(-1*JUROS_CORRIDOS) ,0 ) para manter coerência com restantes campos de saldos | AK12: Metodologia / Conceito: 1) Campo deve ser reportado segundo o saldo (FR001_UNIV_SALDO) das contas contabilisticas referentes a juros/rendimentos a receber (presente no campo COMPOSICAO_VALOR da FR802_PL_CONTAS). 2) Esta tipologia de valor apenas é possível averiguar no plano de contas PCSB. Especificado/ Revisto por: Contabilidade (Luisa de Sousa) Guia de conceitos da Corporação: De acordo com o pretendido no Guia. | AL12: Campo: jurCorr Não está de acordo com o reportado na AnaCredit: A CRC utiliza como fonte de dados as Ics (sem ajustes), não sendo possível conciliar com o reportado pela área da contabilidade. | AM12: OK | AN12: N | AO12: Y | AP12: Contabilidade | AQ12: CONTABILIDADE | AR12: Rafael Pessoa | AS12: Validar esposição dos moyr1060, moyr1061, validar com rafa e tania Usar a CT004 os dias de incumprimento (preciso deste indicador para ir ao moyr?) | AU12: 1
A13: =_xlfn.CONCAT(Table2[[#This Row],[TABLE_NAME]],Table2[[#This Row],[COLUMN_NAME]]) -> INSTRUMENTAMNT_D_AT_MTRTY | B13: INSTRUMENT | C13: AMNT_D_AT_MTRTY | D13: FLOAT 2 decimal places | E13: N | F13: Y | G13: Y | H13: Y | I13: Y | J13: Y | K13: Y | L13: Amount due at the legal final maturity date | M13: Total amount of principal repayment to be paid at the final legal maturity date (i.e. DT_LGL_FNL_MTRTY), i.e. amount of last instalment at maturity date. | N13: Total amount of principal repayment to be paid at the final legal maturity date (i.e. DT_LGL_FNL_MTRTY), i.e. amount of last instalment at maturity date. | O13: TRUE | P13: 99999999999 | Q13: 11111111111 | S13: IN.064 | T13: N | U13: Y | V13: Y | W13: Y | X13: Y | Y13: Y | Z13: N | AB13: CD_LOAN_TAPES_BCE | AC13: LT002_INSTRUMENT | AD13: PYMNT_FRQNCY OTSTNDNG_NMNL_AMNT_INSTRMNT DT_LGL_FNL_MTRTY | AE13: CASE WHEN PYMNT_FRQNCY= '8' THEN OTSTNDNG_NMNL_AMNT_INSTRMNT/(CASE WHEN ROUND(DATEDIFF(DT_LGL_FNL_MTRTY,REF_DATE)/30,0) <= 0 THEN 1 ELSE ROUND(DATEDIFF(DT_LGL_FNL_MTRTY,REF_DATE)/30,0) END) WHEN PYMNT_FRQNCY= '1' THEN OTSTNDNG_NMNL_AMNT_INSTRMNT/(CASE WHEN ROUND(DATEDIFF(DT_LGL_FNL_MTRTY,REF_DATE)/365,0) <= 0 THEN 1 ELSE ROUND(DATEDIFF(DT_LGL_FNL_MTRTY,REF_DATE)/365,0) END) WHEN PYMNT_FRQNCY= '18' THEN OTSTNDNG_NMNL_AMNT_INSTRMNT/(CASE WHEN ROUND(DATEDIFF(DT_LGL_FNL_MTRTY,REF_DATE)/90,0) <= 0 THEN 1 ELSE ROUND(DATEDIFF(DT_LGL_FNL_MTRTY,REF_DATE)/90,0) END) WHEN PYMNT_FRQNCY= '19' THEN OTSTNDNG_NMNL_AMNT_INSTRMNT/(CASE WHEN ROUND(DATEDIFF(DT_LGL_FNL_MTRTY,REF_DATE)/180,0) <= 0 THEN 1 ELSE ROUND(DATEDIFF(DT_LGL_FNL_MTRTY,REF_DATE)/180,0) END) WHEN PYMNT_FRQNCY IN ('4','22') THEN OTSTNDNG_NMNL_AMNT_INSTRMNT END SE PELO MENOS UM DOS CAMPOS FONTE TIVER INFORMADO COM O VALOR DA COLUNA NULLABLE, ENTÃO VALOR DA COLUNA NULLABLE | AF13: SE PELO MENOS UM DOS CAMPOS FONTE TIVER O VALOR DE NOT APPLICABLE | AG13: UTILIZAR OS CAMPOS PYMNT_FRQNCY, OTSTNDNG_NMNL_AMNT_INSTRMNT E DT_LGL_FNL_MTRTY PARA O CÁLCULO | AI13: 45754 | AJ13: 05/07/2023: Adição de condição de metodologia de NOT APPLICABLE 07/04/2025: Utilizou-se uma proxy para o cálculo do campo utilizado a frequência de pagamento - proxy definida com Luis CapitãoMor | AK13: Metodologia / Conceito: 1) Com base nos dados existentes em sistema, apenas é possível calcular a ultima prestação do crédito, i.e. na data de maturidade do contrato, quando os mesmos têm uma amortização do tipo "bullet" (TYP_AMRTSTN = '4'); 2) Para a restante carteira de crédito, assumir o valor da coluna "NULLABLE" 3) Esta informação deve ser aprovisionada apenas para os produtos de Empréstimos, Leasing, Linhas de crédito e Garantias (definidos através do campo TYP_INSTRMNT) - Indicado pela Corporação por e-mail no dia 03/07/2023. Especificado/ Revisto por: CDO (Luis Capitão-Mor) Guia de conceitos da Corporação: De acordo com o pretendido no Guia apenas para contratos com tipo de amortização bullet. | AL13: N/A | AM13: WIP | AN13: Y | AO13: N | AP13: Portfolio Instrumentos | AQ13: PORTFOLIO MANAGER | AR13: Marino Peres | AU13: 1
A14: =_xlfn.CONCAT(Table2[[#This Row],[TABLE_NAME]],Table2[[#This Row],[COLUMN_NAME]]) -> INSTRUMENTANNLSD_AGRD_RT | B14: INSTRUMENT | C14: ANNLSD_AGRD_RT | D14: FLOAT 6 decimal places | E14: Y | F14: Y | G14: Y | H14: N | I14: Y | J14: Y | K14: Y | L14: Interest rate at the reference date | M14: Annualised agreed rate or narrowly defined interest rate at reference date in accordance with Regulation (EU) No 1072/2013 of the European Central Bank (ECB/2013/34). | N14: Annualised agreed rate or narrowly defined interest rate at reference date in accordance with Regulation (EU) No 1072/2013 of the European Central Bank (ECB/2013/34). | O14: TRUE | P14: 99999999999 | Q14: 11111111111 | S14: IN.125 | T14: Y | U14: Y | V14: Y | W14: Y | X14: Y | Y14: Y | Z14: Y | AB14: CD_ALM | AC14: AL029_CNT_CORE_M | AD14: TX_CONTRATO_ACT | AE14: TX_CONTRATO_ACT/100 Se duplicações de chave do universo com chave ALM então: 1. Escolher o registo de ALM que tenha origem <> "MANUAL" 2. Escolher o registo de ALM com mais campos preenchidos 3. Escolher o registo de ALM com maior saldo: (-(MON_CAP_ST1_C0 + MON_CAP_ST1_C1 + MON_CAP_ST1_CO + MON_CAP_ST1_VIVO + MON_CAP_ST2_C0 + MON_CAP_ST2_C1 + MON_CAP_ST2_CO + MON_CAP_ST2_VIVO + MON_CAP_ST3_C0 + MON_CAP_ST3_C1 + MON_CAP_ST3_CO + MON_CAP_ST3_VIVO + MON_JUR_ST1 + MON_JUR_ST1_C0 + MON_JUR_ST1_C1 + MON_JUR_ST1_CO + MON_JUR_ST2 + MON_JUR_ST2_C0 + MON_JUR_ST2_C1 + MON_JUR_ST2_CO + MON_JUR_ST3 + MON_JUR_ST3_C0 + MON_JUR_ST3_C1 + MON_JUR_ST3_CO + MON_COMISSOES + MON_DESPESAS + MON_IMPARID_PATRI + MON_IMPARIDADE_EXTRA + MON_EXTRAPATRI)) | AF14: - | AG14: 1) Replicar passo 1) do campo INTRST_RT_RST_FRQNCY 2) Replicar passo 2) do campo INTRST_RT_RST_FRQNCY 3) Replicar passo 4) do campo INTRST_RT_RST_FRQNCY | AI14: 44672 | AJ14: 04/11/21: A metodologia de Not Applicbale mantém-se igual à versão original (não foi aplicada a metodologia de default values proposta pela corporação). 28/04/2022: Alteração da metodologia de cáclulo para dividir o campo por 100 por forma obter a taxa entre 0 e 1 e adição de campos no cálculo do saldo ALM para eliminar duplicados na duplicação de chaves. | AK14: Metodologia / Conceito: 1) Conceito previsto nas tabelas de ALM 2) Metodologia a aplicar para duplicação de chaves (após cruzamento com tradutores): 2.1. Escolher o registo de ALM que tenha origem <> "MANUAL" 2.2. Escolher o registo de ALM com mais campos preenchidos 2.3. Escolher o registo de ALM com maior saldo Especificado/ Revisto por: Risco de Mercado (Cláudia Correia) Guia de conceitos da Corporação: Análise não realizada. | AL14: Campo: TAA? Não está de acordo com o reportado na AnaCredit: CRC utiliza fonte distinta da ALM. | AM14: Análise não realizada | AN14: N | AO14: Y | AP14: Portfolio Instrumentos | AQ14: RISCO DE MERCADO / ALM | AR14: Cláudia Correia | AS14: [Reunião LCM 07-06]: O Rafael Pessoa indicou-nos que esta informação está a ir a vazio no FinRep pelo que para o Loan Tape também irá a vazio | AU14: 1
A15: =_xlfn.CONCAT(Table2[[#This Row],[TABLE_NAME]],Table2[[#This Row],[COLUMN_NAME]]) -> INSTRUMENTARRRS_INSTRMNT | B15: INSTRUMENT | C15: ARRRS_INSTRMNT | D15: FLOAT 2 decimal places | E15: Y | F15: Y | G15: Y | H15: Y | I15: Y | J15: Y | K15: Y | L15: Total exposure in arrears | M15: Aggregated amount of the principal, interest and any fee payment outstanding at the reporting date, which is contractually due and has not been paid (past due). | N15: Aggregated amount of the principal, interest and any fee payment outstanding at the reporting date, which is contractually due and has not been paid (past due). | O15: TRUE | P15: 99999999999 | Q15: 11111111111 | S15: IN.091 | T15: N | U15: Y | V15: Y | W15: Y | X15: Y | Y15: Y | Z15: Y | AB15: CD_LOAN_TAPES_BCE | AC15: TMP_BCE_LT_MOYR | AD15: ARRRS_INSTRMNT | AE15: NVL(SUM(ARRRS_INSTRMNT),0) | AG15: CONSULTAR DOCUMENTO BS_TABELAS_TEMPORÁRIAS_LOAN_TAPE.XLSX (TMP_BCE_LT_MOYR) UNIVERSO INSTR LEFT JOIN (SELECT * FROM CD_CAPTOOLS.KT_CHAVES_FINREP ON CEMPRESA_FR, CBALCAO_FR, CNUMECTA_FR, ZDEPOSIT_FR) LEFT JOIN (SELECT * FROM TMP_BCE_LT_MOYR WHERE DATA_DATE_PART = REF_DATE) ON CEMPRESA, CBALCAO, CNUMECTA, ZDEPOSIT GROUP BY CEMPRESA_FR, CBALCAO_FR, CNUMECTA_FR, ZDEPOSIT_FR | AI15: 45779 | AJ15: 30/04/2025: Sem necessidade de re-especificação (controlos Corporativos justificados) Reunião Luísa Sousa e Rui Sarroeira: verifica-se que a Contabilidade e CRC reporta apenas contratos vencidos > 30 dias; no entanto, na Loan Tape e FINREP, é considerado default a partir do momento 0 | AK15: Metodologia / Conceito: A informação de reporte de cálculo de contabilidade é apresentada com uma granularidade distinta do universo esperado na Loan Tape para o BCE. Deste modo, são necessários tratamentos ao nível da chave de contabilidade anteriores ao mapeamento com o universo da Loan Tape: Step 1) TMP_BCE_LT_MOYR60: Tratamento da informação de histórico de capital vencido na moeda local - Com o objetivo de manter a coerência com a restante informação reportada, o universo de contratos na tabela MOYR1060 deve resultar dos contratos comuns entre (1) A tabela filtrada pelas seguintes características: csubcart <> 'A' ; csubprod <> 'MOR'; cgrupoic not in ('31','91'), (2) A tabela filtrada pelo máximo das data_date_part, agrupadas pelo último dia do mês; - Com o objetivo de manter a coerência com a restante informação reportada, o universo de contratos na tabela CAMBIOS deve resultar dos contratos comuns entre (1) A tabela filtrada pelas seguintes características: zseqcamb = 99; ctbcamb = 'F' ; camarca = 'BT' ; cdivisa = '0', (2) A tabela filtrada pelo máximo das data_date_part, agrupadas pelo último dia do mês; - Finalmente, de forma a obter o montante de capital em incumprimento, são somadas, por cada chave, as várias relações entre os valores obtidos nos campos MOYR1N60_MSLDIRR e TCMBME das tabelas MOYR1060 e CAMBIOS, respetivamente. Step 2) TMP_BCE_LT_MOYR61: Tratamento da informação de histórico de juros vencidos na moeda local - Com o objetivo de manter a coerência com a restante informação reportada, o universo de contratos na tabela MOYR1061 deve resultar dos contratos comuns entre (1) A tabela filtrada pelas seguintes características: csubcart <> 'A' ; csubprod <> 'MOR'; cgrupoic not in ('31','91'); and not (cnaturic = 'I' and (csubprod <> 'MOR'; clasrisc not in ('0','1'); codprov in ('090','***','111',''))); and not (cnaturic in ('D','M','S'); MOYR1N60_CLASRISC NOT IN ('0','1')), (2) A tabela filtrada pelo máximo das data_date_part, agrupadas pelo último dia do mês; - Com o objetivo de manter a coerência com a restante informação reportada, o universo de contratos na tabela CAMBIOS deve resultar dos contratos comuns entre (1) A tabela filtrada pelas seguintes características: zseqcamb = 99; ctbcamb = 'F' ; camarca = 'BT' ; cdivisa = '0', (2) A tabela filtrada pelo máximo das data_date_part, agrupadas pelo último dia do mês; - Finalmente, de forma a obter o montante de capital em incumprimento, são somadas, por cada chave, as várias relações entre os valores obtidos nos campos MOYR1N61_MSLDIRR e TCMBME das tabelas MOYR1060 e CAMBIOS, respetivamente. Step 3) TMP_BCE_LT_MOYR_IFIC: Tratamento da informação de histórico de capital e juros vencidos na moeda local à data de referência para IFIC - Com o objetivo de manter a coerência com a restante informação reportada, o universo de contratos na tabela CT622_MOYR_IFIC deve resultar dos contratos comuns entre (1) A tabela sem qualquer filtro, (2) A tabela filtrada pelo máximo das ref_date, agrupadas pelo último dia do mês; - Finalmente, de forma a obter o montante de capital e juros em incumprimento, são somadas, por cada chave, os valores obtidos no campo VENCIDO_CTRVLR. Step 4) TMP_BCE_LT_MOYR: Informação de histórico de capital e juros vencidos na moeda local - Universo de contratos a considerar para a informação histórica de capital e juros vencidos com base nas tabelas anteriormente criadas; - Finalmente, de forma a obter o montante de capital e juros em incumprimento, são somadas, por cada chave, os valores que resultem do campo criado nas tabelas anteriores. Especificado/ Revisto por: Contabilidade Guia de conceitos da Corporação: De acordo com o pretendido no Guia. | AL15: 0 | AM15: WIP | AN15: N | AO15: N | AP15: NPE | AQ15: CONTABILIDADE | AR15: Rafael Pessoa | AU15: 1
A16: =_xlfn.CONCAT(Table2[[#This Row],[TABLE_NAME]],Table2[[#This Row],[COLUMN_NAME]]) -> INSTRUMENTARRRS_INSTRMNT_12M | B16: INSTRUMENT | C16: ARRRS_INSTRMNT_12M | D16: FLOAT 2 decimal places | E16: N | F16: Y | G16: N | H16: N | I16: Y | J16: Y | K16: Y | L16: Highest total exposure in arrears in the last 12 months before the reference date | M16: Highest aggregated amount of the principal, interest and any fee payment outstanding at a period of 12 months before the reference date, which is contractually due and has not been paid (past due). | N16: Highest aggregated amount of the principal, interest and any fee payment outstanding at a period of 12 months before the reference date, which is contractually due and has not been paid (past due). | O16: TRUE | P16: 99999999999 | Q16: 11111111111 | S16: IN.092 | T16: N | U16: Y | V16: Y | W16: Y | X16: Y | Y16: Y | Z16: Y | AB16: CD_LOAN_TAPES_BCE | AC16: TMP_BCE_LT_MOYR | AD16: ARRRS_INSTRMNT | AE16: NVL(SUM(ARRRS_INSTRMNT),0) | AF16: - | AG16: Consultar documento BS_Tabelas_Temporárias_Loan_Tape.xlsx (TMP_BCE_LT_MOYR) UNIVERSO INSTR LEFT JOIN (SELECT * FROM CD_CAPTOOLS.KT_CHAVES_FINREP ON CEMPRESA_FR, CBALCAO_FR, CNUMECTA_FR, ZDEPOSIT_FR) LEFT JOIN (SELECT * FROM TMP_BCE_LT_MOYR WHERE DATA_DATE_PART = REF_DATE) ON CEMPRESA, CBALCAO, CNUMECTA, ZDEPOSIT GROUP BY CEMPRESA_FR, CBALCAO_FR, CNUMECTA_FR, ZDEPOSIT_FR | AI16: 44404 | AK16: No caso de não estarem reunidas as condições para apurar o histórico nos últimos 12 meses (Consultar documento BS_Tabelas_Temporárias_Loan_Tape.xlsx), considera-se o valor da coluna "NULLABLE" | AL16: N/A | AM16: WIP | AN16: N | AO16: N | AP16: NPE | AQ16: CONTABILIDADE | AR16: Rafael Pessoa | AS16: ver rsv133 sa1 e sa2 | AU16: 1
A17: =_xlfn.CONCAT(Table2[[#This Row],[TABLE_NAME]],Table2[[#This Row],[COLUMN_NAME]]) -> INSTRUMENTASST_SCRT_CLSS | B17: INSTRUMENT | C17: ASST_SCRT_CLSS | D17: Code List | E17: Y | L17: Asset securitisation class | M17: To be reported if the instrument is a securitisation or covered bond. | N17: To be reported if the instrument is a securitisation or covered bond. | O17: TRUE | P17: 99999999999 | Q17: 11111111111 | S17: IN.155 | T17: N | U17: N | V17: N | W17: N | X17: N | Y17: N | Z17: Y | AB17: CD_LOAN_TAPES_BCE | AC17: TMP_BCE_LT_MOYR | AD17: ARRRS_INSTRMNT | AE17: NVL ( MAX(ARRRS_INSTRMNT), 0) | AF17: - | AG17: Consultar documento BS_Tabelas_Temporárias_Loan_Tape.xlsx (TMP_BCE_LT_MOYR) UNIVERSO INSTR LEFT JOIN (SELECT * FROM CD_CAPTOOLS.KT_CHAVES_FINREP ON CEMPRESA_FR, CBALCAO_FR, CNUMECTA_FR, ZDEPOSIT_FR) LEFT JOIN (SELECT * FROM TMP_BCE_LT_MOYR WHERE DATA_DATE_PART BETWEEN REF_DATE-12MESES AND REF_DATE GROUP BY CEMPRESA, CBALCAO, CNUMECTA, ZDEPOSIT) ON CEMPRESA, CBALCAO, CNUMECTA, ZDEPOSIT GROUP BY CEMPRESA_FR, CBALCAO_FR, CNUMECTA_FR, ZDEPOSIT_FR | AI17: 44602 | AJ17: 04/11/21: A metodologia de Not Applicbale mantém-se igual à versão original (não foi aplicada a metodologia de default values proposta pela corporação). 10/02/2022: Foi adicionado um NVL à metodologia de cálculo. | AK17: Metodologia / Conceito: 1) Campo previsto apenas para títulos. Atualmente não existe no banco os diferentes tipos de titularização previstos pela codelist. Foram apenas mapeadas as tipologias que existem atualmente. Especificado/ Revisto por: CDO (Luís Capitão-Mor) Guia de conceitos da Corporação: Conceito não existente no Guia. | AL17: Atualmente a CRC não reporta informação de debt securities. | AM17: Conceito não existente no Guia | AN17: N | AO17: Y | AP17: Debt Securities | AQ17: RISCO DE MERCADO / ALM | AR17: Cláudia Correia | AU17: 1
A18: =_xlfn.CONCAT(Table2[[#This Row],[TABLE_NAME]],Table2[[#This Row],[COLUMN_NAME]]) -> INSTRUMENTBRCHD_CVNNTS | B18: INSTRUMENT | C18: BRCHD_CVNNTS | D18: VARCHAR2(255) | E18: N | F18: Y | G18: Y | H18: Y | I18: N | J18: N | K18: N | L18: Breached covenants | M18: Breached covenants separated by comma (,). | N18: Breached covenants separated by comma (,). | O18: TRUE | P18: MISS | Q18: N/A | S18: IN.015 | T18: N | U18: Y | V18: Y | W18: Y | X18: Y | Y18: N | Z18: N | AB18: CD_LOAN_TAPES_BCE | AC18: LT604_HOLIS_MAN | AD18: VALOR | AE18: NOTA: PARA TODO O UNIVERSO O CAMPO DEVE SER REPORTADO COM 'N/A' | AF18: - | AG18: - | AI18: 45849 | AJ18: 11/07/25: Alteração da metodologia de cálculo do campo('N/A' ao invés de 'MISS'), de modo a garantir consistência com guidlines Corporativas. Adicionalmente, este campo passa a ser populado através da tabela holística. | AK18: Metodologia / Conceito: 1) Relativamente a papel comercial, os responsáveis por monitorizar o incumprimento das cláusulas dos contratos são os Gestores. Esta monitorização não é realizada através de qualquer sistema de informação. (Daniel Xarepe) 2) Para a restante carteira de crédito, também não existe informação nas bases de dados do Banco. (Luis Bastos) 3) Campo deve ser reportado como "sem informação", i.e., com o valor da coluna NULLABLE. Especificado/ Revisto por: Risco de Crédito + Controlo CIB (Luis Bastos + Daniel Xarepe) Guia de conceitos da Corporação: Análise não realizada. | AL18: N/A | AM18: Análise não realizada | AN18: N | AO18: Y | AP18: Portfolio Instrumentos | AQ18: INFORMAÇÃO DE RISCOS | AR18: Marino Peres | AU18: 1
A19: =_xlfn.CONCAT(Table2[[#This Row],[TABLE_NAME]],Table2[[#This Row],[COLUMN_NAME]]) -> INSTRUMENTCCF | B19: INSTRUMENT | C19: CCF | D19: FLOAT 6 decimal places | E19: N | F19: Y | G19: Y | H19: Y | I19: Y | J19: Y | K19: Y | L19: Credit conversion factor (CCF) according to CRR | M19: Credit conversion factor according to regulation (EU) No 575/2013. | N19: Credit conversion factor according to regulation (EU) No 575/2013. | O19: TRUE | P19: 99999999999 | Q19: 11111111111 | S19: IN.065 | T19: N | U19: Y | V19: Y | W19: Y | X19: Y | Y19: Y | Z19: N | AB19: CD_LOAN_TAPES_BCE | AC19: BCE_LT_INSTR_CAP | AD19: CCF | AE19: CCF | AF19: - Se o campo auxiliar FLG_CONS_CAP=0 (utilizado na definição do universo de capital) | AG19: 1) Cruzar LT002_INSTRUMENT com tabela temporária BCE_LT_INSTR_CAP para o perimetro em análise: LT002_INSTRUMENT LEFT JOIN (SELECT * FROM BCE_LT_INSTR_CAP) ON INSTRMNT_ID = CHAVE_FR Consultar documento BS_Tabelas_Temporárias_Loan_Tape.xlsx (BCE_LT_INSTR_CAP) | AI19: 45915 | AJ19: 27/10/2021 Reunião LCM: Eliminação da regra "'- Se a entidade não pertencer ao universo de Capital (BCE_LT_INSTR_CAP)" na Metodologia de NOT APPLICABLE. 21/12/2023 Reunião LCM: Adição de condições de NOT APPLICABLE na sequência da análise dos controlos da Corporação e completude. 15/09/2025 Reunião LCM: Para o perímetro Individual IDComb na CT020, deve ser filtrada pelo perímetro Individual Corporativo quando a data de referência (REF_DATE) for anterior a 30 de abril de 2025. A partir dessa data (inclusive), deve ser filtrada pelo perímetro Individual IDComb. | AK19: Metodologia / Conceito: A informação de reporte de cálculo de capital é apresentada com uma granularidade distinta do universo esperado na Loan Tape para o BCE. Deste modo, são necessários tratamentos ao nível da chave de capital anteriores ao mapeamento com o universo da Loan Tape: Step 1) TMP_BCE_LT_INSTR_CAP: Tratamento da informação por chave de capital (id_capital_perimetros, s1emp, contra1) - Com o objetivo de fazer face às orientações do BCE relativamente à informação reportada, o universo de contratos da ct013_rwa_princ deve ser filtrado pelas seguintes características: (1) Universo com método de cálculo de capital Standard e IRB - subtipo_risco in (1.1; 1.2; 1.3; 1.4; 1.5; 1.6; 1.7; 1.8; 1.9; 1.13), (2) Universo reportado pelas regulações específicas da área de Capital (ex. COREP) - flag_cons_cap = 1, (3) Universo que concilia contabilisticamente - flag_conc_contab = 1 e (4) exercicio = “REAL”; - De seguida, e uma vez que o mesmo contrato de capital pode ter múltiplos registos e ser calculado em 2 métodos distintos, foram realizadas transformações para os diferentes campos de modo a obter um registo único por chave de capital (nota i); - Finalmente, para cada chave de capital, foram filtrados os id_capital_perimetros que pertencem ao perímetro em análise (através da tabela ct020_rwa_per); Step 2) BCE_LT_INSTR_CAP: Tratamento da informação por chave FINREP (chave_fr = instrmnt_id) - Foi realizado o cruzamento com os tradutores de modo a mapear a chave do Universo da Loan Tape (chave FINREP) com a de capital (obtida no Step 1); - Uma vez que uma chave FINREP pode estar relacionada com múltiplas de capital e vice-versa, foram realizadas transformações para os diferentes campos de modo a obter um registo único por chave FINREP; - Para os campos de atributos, caso um contrato de com chave de finrep esteja relacionado com múltiplas de capital deve ser escolhido o registo de acordo com as seguintes ordens de prioridade: 1º Se a chave FINREP contiver chaves de capital com FLG_IDCTOORI for 1 e 0 escolher registo onde FLG_IDCTOORI = 0; 2º Se a chave FINREP contiver chaves de capital com produtos de estruturas e diferente de estruturas (id_prod = 47) então escolher registo onde id_prod <> 47 (diferente de estruturas) 3º Se a chave FINREP contiver chaves de capital com 2 RWA_MTHD escolher registo onde RWA_MTHD = '1' (IRB) 4º (nota ii) Especificamente sobre o campo CCF (referente à exposição extrapatrimonial): Nota i: Foi calculado o CCF máximo dentro do mesmo método e escolhido o referente ao que foi utilizado em cálculo IRB; Nota ii: Foi calculada a média ponderada pela EAD. Especificado/ Revisto por: Capital + CDO (Susana Arrochinho + Luis Capitão-Mor) Guia de conceitos da Corporação: Não está de acordo com o pretendido no Guia, uma vez que 1) porque a granularidade é diferente entre a BDR e a Loan Tape, os resultados esperados podem diferir (exemplo: para contratos em IRB e STD considera-se o CCF de IRB). Para contratos da Loan Tape que mapeiam para 2 de IRB/STD calcula-se a média ponderada. Adicionalmente, 2), no guia considera-se o valor de not applicable para contratos com exposição 100% patrimonial. | AL19: N/A | AM19: OK | AN19: N | AO19: N - rever se mantemos em tabela temporária ou no DDR (processo) | AP19: Capital | AQ19: CAPITAL | AR19: Helder Gomes | AS19: 1. Enviar e-mail a Jesus a confirmar se existe informação de data na BDR ---> E9952_FECCALI | AU19: 1
A20: =_xlfn.CONCAT(Table2[[#This Row],[TABLE_NAME]],Table2[[#This Row],[COLUMN_NAME]]) -> INSTRUMENTCHNNL_ORGNTN | B20: INSTRUMENT | C20: CHNNL_ORGNTN | D20: Code List | E20: N | F20: N | G20: N | H20: N | I20: Y | J20: Y | K20: Y | L20: Channel of origination | M20: Description of the loan origination channel. | N20: Description of the loan origination channel. | O20: TRUE | P20: 99999999999 | Q20: 11111111111 | S20: IN.016 | T20: N | U20: Y | V20: Y | W20: Y | X20: Y | Y20: Y | Z20: N | AB20: Universo 1 - CD_LOGS Universo 2 - por aplicação de produto de crédito - Consultar documentos word ("Metodologia_Cálculo_CHNLL_ORGNTN" e "Metodologia_Cruzamento_CHNLL_ORGNTN" de Cálculo na pasta 04 - Especificação | AC20: Universo 1 - LOG_OPERATION Universo 2 - por aplicação de produto de crédito - Consultar documentos word ("Metodologia_Cálculo_CHNLL_ORGNTN" e "Metodologia_Cruzamento_CHNLL_ORGNTN" de Cálculo na pasta 04 - Especificação | AD20: - | AE20: Universo 1. Operações CrediSimples CASE WHEN CODIGOINTERACAO = 'CEM08' AND DADO13 = 'Contratado' AND DADO20 = 'NBE' THEN 2 ELSE Valor da coluna Nullable WHERE DATA_DATE_PART<= DT_RFRNC Universo 2. Por aplicação de produto de crédito: Consultar documento word "Metodologia_Cálculo_CHNLL_ORGNTN" Universo 3. Contas DO Consultar documento word "Metodologia_Cálculo_CHNLL_ORGNTN" NOTA: O processo de aprovisionamento deverá corresponder a um NVL (Universo 1, Universo 2, Universo 3) | AF20: - | AG20: NOTA: A tabela LOG_OPERATION deve ser filtrada por todas as DATA_DATE_PART inferiores à data de referência 1) Cruzar LT002_INSTRUMENT com tradutor de chaves FINREP LT002_INSTRUMENT LEFT JOIN (SELECT * FROM KT_CHAVES_FINREP) ON INSTRMNT_ID = CONCAT(CEMPRESA_FR, CBALCAO_FR, CNUMECTA_FR, ZDEPOSIT_FR) 2) Cruzar chave MASTER obtida no passo anterior com tabela LOG_OPERATION para obter campos CODIGOINTERACAO e as colunas necessárias para cada tipo de produto: LEFT JOIN (SELECT * FROM LOG_OPERATION) ON CONCAT(CBALCAO, CNUMECTA, ZDEPOSIT) = CONCAT(DADO15, '000000000000000') Universo 2. Por aplicação de produto de crédito: Consultar documento word "Metodologia_Cálculo_CHNLL_ORGNTN" Universo 3. Contas DO Consultar documento word "Metodologia_Cálculo_CHNLL_ORGNTN" na pasta "04 - Especificação" | AI20: 45303 | AJ20: 12/05/2022: Foi atualizada a especificação 24/06/2022: Foi atualizada a especificação para contemplar as paremetrizações anteriormente realizadas por tabela de parametrização (Sem impactos na implementação). 01/07/2022: Atualização da metodologia de cálculo para inclui condição da data_date_part <= dt_rfrnc 05/01/2023: Especificação para o universo de contratos cujo canal de contratação será definido pelas aplicações de produto de crédito 12/01/2024: Especificação para o universo de contratos não foi preenchido pelos processos anteriores e corresponde a uma DO. | AK20: Metodologia / Conceito: 1) WIP Especificado/ Revisto por: CDO (Luis Capitão-Mor) Guia de conceitos da Corporação: De acordo com o pretendido no Guia. | AL20: N/A | AM20: WIP | AN20: Y | AO20: N | AP20: Portfolio Instrumentos | AQ20: CANAIS | AR20: Ângelo Sarmento | AS20: Notas: Não existe informação centralmente na aplicação de empréstimos. O que podemos fazer? Ir por produto? Qual é a tabela que marca quando se contrata um emprestimo/ deposit/ etc... Pedro Vicente - Área de Canais Angelo Miguel Loureiro Sarmento - Área de Canais Luis Barata ou Cladia Correia - em ALM poderá existir Pedro Vicente/ Angelo Miguel - Todos os contratos de canais empresas são contratados (e cruzar com a informação é complicado porque depende do produto - ex. credito simples é por proposta, mas os restantes teria-se de ver) Romeu Viegas ou Rita Brito Grito Oliveira (Eles dizem que todos os dias enviam a info em Batch e que isto está no DL e tem todos os prdoutos contartados) - Em que tabelas está no DL É necessário ter acesso às schemma e rever os campos com o Ângelo Miguel | AT20: Raquel Ferreira - Existem tabelas na DW que já tratam a informação dos logs | AU20: 1
A21: =_xlfn.CONCAT(Table2[[#This Row],[TABLE_NAME]],Table2[[#This Row],[COLUMN_NAME]]) -> INSTRUMENTCMLTV_RCVRS_SNC_DFLT_INSTRMNT | B21: INSTRUMENT | C21: CMLTV_RCVRS_SNC_DFLT_INSTRMNT | D21: FLOAT 2 decimal places | E21: Y | F21: Y | G21: Y | H21: N | I21: Y | J21: Y | K21: Y | L21: Cumulative recoveries since default | M21: The total amount recovered since the date of default. | N21: The total amount recovered since the date of default. | O21: TRUE | P21: 99999999999 | Q21: 11111111111 | S21: IN.093 | T21: N | U21: Y | V21: Y | W21: Y | X21: Y | Y21: Y | Z21: Y | AB21: FIXO | AC21: FIXO | AD21: FIXO | AE21: Valor da coluna "NULLABLE" | AF21: - Se contrato não está em default (DFLT_STTS_INSTRMNT = '14'). | AG21: - | AI21: 44601 | AJ21: 09/02/2021: Atualização da especificação da metodologia de cálculo. 04/05/2023: Pedido de ingesta JM_ACUMTO_BDI e carregamento de histórico. | AK21: Metodologia / Conceito: 1) Informação de todas as recuperações sobre o contrato desde a entrada em default (apenas aplicável a contratos que estão em default - DFLT_STTS_INSTRMNT <> 14). Esta informação não está disponivel de forma direta em sistema (inclusivamente na área de recuperações). 2) Campo deve ser reportado como "sem informação", i.e., com o valor da coluna NULLABLE; 3) A futuro, devem ser considerados os COPERACS/ OBBs utilizados pela área de contabilidade para descriminar as tipologias de movimentos por contrato: capital, juros, pagamento de seguros, etc. 4) Adicionalmente, deve ser averiguada a possibilidade de utilizar a BDI para reporte desta informação (registo de perdas e recuperações). Especificado/ Revisto por: CDO (Luis Capitão-Mor) Guia de conceitos da Corporação: Não está de acordo com o pretendido no guia. ("All recoveries since the date of default are taken into account, irrespective of their source; for example, this data attribute takes into account any voluntary cash repayments, any proceeds from liquidating collateral, amounts received as a result of calling guarantees, proceeds from selling the instrument, etc., provided that they were received during the period of default”) | AL21: Campo: recAcumIncump Não está de acordo com o reportado na AnaCredit: CRC reporta de acordo com movimentos contabilisticos - somatório do valor dos movimentos vezes (-1) do campo VMOV_PROV da DWT1080_HIST_PROVISOES para os seguintes ‘Tipos de movimento de recuperação com o campo CTIPMOV (CMOT_PROV) = 2,6,7,9,D,E,F; quando o campo IUTILPRV (CUTIL_PROV) = '2 - recuperação'; na tabela TCT63-MMOVIM que na DW está na DWT1080_HIST_PROVISOES. | AM21: WIP | AN21: Y | AO21: N | AP21: Amortizações | AQ21: RECUPERAÇÕES | AR21: Rui Querido | AT21: Notas: OSI: José Duarte: Valor de write-offs (que na prática não são recuperações) Catarina Caroço / Rui querido: Não têm essa informação. Ricardo Lopes da Costa Jorge: Sem resposta | AU21: 1
A22: =_xlfn.CONCAT(Table2[[#This Row],[TABLE_NAME]],Table2[[#This Row],[COLUMN_NAME]]) -> INSTRUMENTCMMTMNT_INCPTN_INSTRMNT | B22: INSTRUMENT | C22: CMMTMNT_INCPTN_INSTRMNT | D22: FLOAT 2 decimal places | E22: Y | F22: Y | G22: Y | H22: N | I22: Y | J22: Y | K22: Y | L22: Commitment amount at inception | M22: Observed agent’s maximum exposure to credit risk on the inception date of the instrument, without taking into account any protection held or other credit enhancements. Total commitment amount on the inception date is established during the approval process and is intended to restrict an observed agent’s amount of credit risk to a given counterparty for the relevant instrument. | N22: Observed agent’s maximum exposure to credit risk on the inception date of the instrument, without taking into account any protection held or other credit enhancements. Total commitment amount on the inception date is established during the approval process and is intended to restrict an observed agent’s amount of credit risk to a given counterparty for the relevant instrument. | O22: TRUE | P22: 99999999999 | Q22: 11111111111 | S22: IN.066 | T22: N | U22: Y | V22: Y | W22: Y | X22: Y | Y22: Y | Z22: N | AB22: CD_LOAN_TAPES_BCE | AC22: BCE_LT_INSTR_MIS | AD22: VTOT_CREDITO_CONTRATADO | AE22: VTOT_CREDITO_CONTRATADO WHERE NOME_PERIMETRO = Perímetro em análise | AF22: - | AG22: 1) Cruzar LT002_INSTRUMENT com tabela temporária BCE_LT_INSTR_MIS para o perimetro em análise: LT002_INSTRUMENT LEFT JOIN (SELECT * FROM BCE_LT_INSTR_MIS) ON INSTRMNT_ID = CHAVE_FR Consultar documento BS_Tabelas_Temporárias_Loan_Tape.xlsx (BCE_LT_INSTR_MIS) | AI22: 44799 | AJ22: 09/02/2022: Atualização da metodologia de cálculo 07/04/2022: Atualização da metodologia de cálculo utilizada para a ponderação do campo decorrente da análise dos controlos do BCE. 26/06/2022: Metodologia idêntica à anterior, mas apontado para uma tabela diferente (CRV004XA1) | AK22: Metodologia / Conceito: 1) Montante em dívida do contrato na data de origem encontra-se disponível na tabela de risco RSTF101_DET_CNT_RSC. (Marino Peres) 2) Uma vez que a chave do contrato nessa tabela é a chave MIS, foi necessária a utilização de um tradutor de chaves (KT_CHAVES_MIS). 3) Adicionalmente, como é possível existirem relações de chaves MIS para FINREP diferentes de 1 para 1 e de modo a não reportar informação duplicada, foi criada uma tabela temporária com o tratamento deste campo (BCE_LT_INSTR_MIS): ponderação do montante proveniente da fonte através dos saldos dos contratos que contém contas contabilísticas do domínio de capital. Este procedimento deve ser realizado para o perímetro em análise. (Luis Capitão-Mor). Especificado/ Revisto por: Portfolio Manager + CDO (Marino Peres + Luis Capitão-Mor) Guia de conceitos da Corporação: Análise não realizada. | AL22: Campo: montIni | AM22: WIP | AN22: Y | AO22: N | AP22: Portfolio Instrumentos | AQ22: INFORMAÇÃO DE RISCOS | AR22: Marino Peres | AU22: 1
A23: =_xlfn.CONCAT(Table2[[#This Row],[TABLE_NAME]],Table2[[#This Row],[COLUMN_NAME]]) -> INSTRUMENTCMMTMNT_INSTRMNT | B23: INSTRUMENT | C23: CMMTMNT_INSTRMNT | D23: FLOAT 2 decimal places | E23: N | F23: Y | G23: Y | H23: N | I23: Y | J23: Y | K23: Y | L23: Commitment amount at reference date | M23: Observed agent’s maximum exposure to credit risk on the reference date of the instrument, without taking into account any protection held or other credit enhancements. Total commitment amount on the reference date is established during the life cycle of the loan and is intended to restrict an observed agent’s amount of credit risk to a given counterparty for the relevant instrument. | N23: Observed agent’s maximum exposure to credit risk on the reference date of the instrument, without taking into account any protection held or other credit enhancements. Total commitment amount on the reference date is established during the life cycle of the loan and is intended to restrict an observed agent’s amount of credit risk to a given counterparty for the relevant instrument. | O23: TRUE | P23: 99999999999 | Q23: 11111111111 | S23: IN.067 | T23: N | U23: Y | V23: Y | W23: Y | X23: Y | Y23: Y | Z23: N | AB23: CD_LOAN_TAPES_BCE | AC23: BCE_LT_INSTR_MIS | AD23: VINICIAL_EMPRESTIMO | AE23: VINICIAL_EMPRESTIMO WHERE NOME_PERIMETRO = Perímetro em análise | AF23: - | AG23: 1) Cruzar LT002_INSTRUMENT com tabela temporária BCE_LT_INSTR_MIS para o perimetro em análise: LT002_INSTRUMENT LEFT JOIN (SELECT * FROM BCE_LT_INSTR_MIS) ON INSTRMNT_ID = CHAVE_FR Consultar documento BS_Tabelas_Temporárias_Loan_Tape.xlsx (BCE_LT_INSTR_MIS) | AI23: 44799 | AJ23: 09/02/2022: Atualização da metodologia de cálculo. 07/04/2022: Atualização da metodologia de cálculo utilizada para a ponderação do campo decorrente da análise dos controlos do BCE. 26/08/2022: Alteração da especificação para reportar o campo VINICIAL_EMPRESTIMO ao invés do campo VRESPONSABILIDADE (especificação anterior do campo CMMTMNT_INCPTN_INSTRMNT) | AK23: Metodologia / Conceito: 1) Montante em dívida do contrato na data de referência encontra-se disponível na tabela de risco RSTF101_DET_CNT_RSC. (Marino Peres) 2) Uma vez que a chave do contrato nessa tabela é a chave MIS, foi necessária a utilização de um tradutor de chaves (KT_CHAVES_MIS). 3) Adicionalmente, como é possível existirem relações de chaves MIS para FINREP diferentes de 1 para 1 e de modo a não reportar informação duplicada, foi criada uma tabela temporária com o tratamento deste campo (BCE_LT_INSTR_MIS): ponderação do montante proveniente da fonte através dos saldos dos contratos que contém contas contabilísticas do domínio de capital. Este procedimento deve ser realizado para o perímetro em análise. (Luis Capitão-Mor). Especificado/ Revisto por: Portfolio Manager + CDO (Marino Peres + Luis Capitão-Mor) Guia de conceitos da Corporação: Análise não realizada. | AL23: N/A | AM23: WIP | AN23: Y | AO23: N | AP23: Portfolio Instrumentos | AQ23: INFORMAÇÃO DE RISCOS | AR23: Marino Peres | AU23: 1
A24: =_xlfn.CONCAT(Table2[[#This Row],[TABLE_NAME]],Table2[[#This Row],[COLUMN_NAME]]) -> INSTRUMENTCMPLNT_MRTR_C19_NM | B24: INSTRUMENT | C24: CMPLNT_MRTR_C19_NM | D24: VARCHAR2(255) | E24: N | F24: Y | G24: Y | H24: Y | I24: Y | J24: Y | K24: Y | L24: Internal name of EBA compliant moratoria as registered by the bank | M24: The name of the EBA compliant moratoria. EBA/GL/2020/07 Guidelines on reporting and disclosure of exposures subject to measures applied in response to the COVID-19 crisis. Data attribute shall be reported if not waived by the competent authority according to points (a), (c), (d) or (e) of Article 19 of EBA/GL/2020/07 Guidelines on reporting and disclosure of exposures subject to measures applied in response to the COVID-19 crisis. | N24: The name of the EBA compliant moratoria. EBA/GL/2020/07 Guidelines on reporting and disclosure of exposures subject to measures applied in response to the COVID-19 crisis. Data attribute shall be reported if not waived by the competent authority according to points (a), (c), (d) or (e) of Article 19 of EBA/GL/2020/07 Guidelines on reporting and disclosure of exposures subject to measures applied in response to the COVID-19 crisis. | O24: TRUE | P24: MISS | Q24: N/A | S24: IN.145 | T24: N | U24: Y | V24: Y | W24: Y | X24: Y | Y24: Y | Z24: N | AB24: FIXO | AC24: FIXO | AD24: FIXO | AE24: "Compliant Moratoriums" | AF24: - Se o contrato não pertencer ao universo COVID-19 Moratórias* *Universo COVID-19 Moratórias EBA a ser considerado: CT902_EBA_REPORT_CONTAB WHERE F_NEW_MONEY ='0' | AG24: 1) Replicar passos do campo DT_CMPLNT_MRTR_STTS_C19 (para aprovisionamento da metodologia de NOT APPLICABLE) | AI24: 44547 | AJ24: 17/12/2021: Foi reestruturado o texto da metodologia de Not Applicable, por forma a tornar mais claro o pretendido (sem impacto na implementação) | AK24: Metodologia / Conceito: 1) Metodologia aplicada segundo o guia corporitivo: valor fixo "Compliant Moratoriums" 2) A partir de 31 de dezembro 2022, os campos relacionados com COVID-19 devem ser reportados com o valor da coluna de NOT APLICABLE. Guia de conceitos da Corporação: De acordo com o pretendido no Guia. | AL24: N/A | AM24: OK | AN24: N | AO24: Y | AP24: COVID19 | AQ24: CONTABILIDADE | AR24: Rafael Pessoa | AU24: 1
A25: =_xlfn.CONCAT(Table2[[#This Row],[TABLE_NAME]],Table2[[#This Row],[COLUMN_NAME]]) -> INSTRUMENTCNSMPTN_FNRP18 | B25: INSTRUMENT | C25: CNSMPTN_FNRP18 | D25: Y, N | E25: - | L25: Flag of Credit for consumption | M25: Loans granted to Consumer Credit (reported in FinRep 18 rows No 170, 913, 933: “of which: credit for consumption”). | N25: Loans granted to Consumer Credit (reported in FinRep 18 rows No 170, 913, 933: “of which: credit for consumption”). | O25: TRUE | P25: Default value not allowed | Q25: Default value not allowed | S25: IN.006 | T25: N | U25: N | V25: N | W25: N | X25: N | Y25: Y | Z25: N | AB25: Consultar documento de especificação de cálculo de Universo | AC25: Consultar documento de especificação de cálculo de Universo | AD25: Consultar documento de especificação de cálculo de Universo | AE25: Consultar documento de especificação de cálculo de Universo | AF25: Consultar documento de especificação de cálculo de Universo | AG25: Consultar documento de especificação de cálculo de Universo | AI25: - | AK25: Metodologia / Conceito: 1) Flag dummy para identificar se uma determinada exposição se classificada como crédito ao consumo segundo o Mapa FINREP 18/ NOPER. 2) Consultar documento de especificação de cálculo de Universo para mais informações sobre o cálculo do campo. Especificado / revisto por: CDO (Luis Capitão-Mor) Guia de conceitos da Corporação: De acordo com o pretendido no Guia. | AL25: N/A | AM25: OK | AN25: N | AO25: Y | AP25: Portfolio Instrumentos | AQ25: PORTFOLIO MANAGER / CONTABILIDADE | AR25: Marino Peres / Rafael Pessoa | AU25: 0
A26: =_xlfn.CONCAT(Table2[[#This Row],[TABLE_NAME]],Table2[[#This Row],[COLUMN_NAME]]) -> INSTRUMENTCNTRCT_ID | B26: INSTRUMENT | C26: CNTRCT_ID | D26: VARCHAR2(60) | E26: Y | F26: Y | G26: Y | H26: N | I26: Y | J26: Y | K26: Y | L26: Contract ID | M26: An identifier applied by the reporting agent to uniquely identify each contract. Each contract must have one contract identifier. This value will not change over time and cannot be used as the contract identifier for any other contract. | N26: An identifier applied by the reporting agent to uniquely identify each contract. Each contract must have one contract identifier. This value will not change over time and cannot be used as the contract identifier for any other contract. | O26: TRUE | P26: Default value not allowed | Q26: Default value not allowed | S26: IN.009 | T26: Y | U26: Y | V26: Y | W26: Y | X26: Y | Y26: Y | Z26: Y | AB26: CD_CAPTOOLS | AC26: LT001_UNIV_OPER | AD26: CBALCAO CNUMECTA | AE26: CONCAT(CBALCAO, CNUMECTA) | AF26: - | AG26: - | AI26: 44313 | AK26: Metodologia / Conceito: 1) Foi adotada a metodologia de reporte da CRC: cbalcao + cnumecta. Especificado/ Revisto por: Portfolio Manager + CRC (Marino Peres + José Duarte) Guia de conceitos da Corporação: De acordo com o pretendido no Guia. | AL26: Campo: idCont De acordo com o reportado no AnaCredit. | AM26: OK | AN26: N | AO26: Y | AP26: Portfolio Instrumentos | AQ26: PORTFOLIO MANAGER | AR26: Marino Peres | AU26: 1
A27: =_xlfn.CONCAT(Table2[[#This Row],[TABLE_NAME]],Table2[[#This Row],[COLUMN_NAME]]) -> INSTRUMENTCNTRCT_ID_BDR | B27: INSTRUMENT | C27: CNTRCT_ID_BDR | D27: VARCHAR2(60) | E27: N | L27: BDR Contract ID | M27: BDR internal contract identifier (CONTRA1). Each contract must have one contract identifier. This value will not change over time and cannot be used as the contract identifier for any other contract. | N27: BDR internal contract identifier (CONTRA1). Each contract must have one contract identifier. This value will not change over time and cannot be used as the contract identifier for any other contract. | O27: TRUE | P27: MISS | Q27: N/A | S27: IN.191 | T27: Y | U27: Y | V27: Y | W27: Y | X27: Y | Y27: Y | Z27: Y | AB27: CD_CAPTOOLS | AC27: CT013_RWA_PRINC | AD27: S1EMP CONTRA1 | AE27: DISTINCT(GROUP_CONCAT(CONCAT(S1EMP, CONTRA1))) Consultar exemplo do campo INTRNL_SGMNT_CAT_MSTA. Aplicar os filtros realizados na tabela temporária TMP_BCE_LT_INSTR_CAP através dos campos: subtipo_risco, flag_cons_cap, flag_conc_contab, exercicio e nome_perimetro. | AF27: - | AG27: 1) Cruzar LT002_INSTRUMENT com tradutor de chaves FINREP e BDR: LT002_INSTRUMENT LEFT JOIN (SELECT * FROM KT_CHAVES_FINREP INNER JOIN SELECT * FROM KT_CHAVES_BDR ON CEMPRESA, CBALCAO, CNUMECTA, ZDEPOSIT = CEMPRESA, CBALCAO, CNUMECTA, ZDEPOSIT ) ON INSTRMNT_ID = CONCAT(CEMPRESA_FR, CBALCAO_FR, CNUMECTA_FR, ZDEPOSIT_FR) 2) Cruzar chave BDR obtida no passo anterior com a tabela CT013_RWA_PRINC para obter o campo ID_CAPITAL_PERIMETROS e outros campos necessários aos filtros da informação: LEFT JOIN (SELECT * FROM CT013_RWA_PRINC) ON S1EMP = S1MP AND CONTRA1 = CONTRA1 3) Cruzar chave BDR obtida no passo anterior com tabela de perimetros CT020_RWA_PER de modo a obter informação sobre o perimetro de cada contrato em âmbito de capital: INNER JOIN (SELECT * FROM CT020_RWA_PER) ON ID_CAPITAL_PERIMETROS = ID_CAPITAL_PERIMETROS | AI27: 45062 | AJ27: 09/09/2022: Especificação do campo 03/03/2022: Alteração da metodologia de cálculo 16/05/2023: Alteração da metodologia de cálculo (DISTINCT) de forma a eliminar linhas duplicadas | AK27: Metodologia / Conceito: A informação de reporte de cálculo de capital é apresentada com uma granularidade distinta do universo esperado na Loan Tape para o BCE. Deste modo, são necessários tratamentos ao nível da chave de capital anteriores ao mapeamento com o universo da Loan Tape: Step 1) TMP_BCE_LT_INSTR_CAP: Tratamento da informação por chave de capital (id_capital_perimetros, s1emp, contra1) - Com o objetivo de fazer face às orientações do BCE relativamente à informação reportada, o universo de contratos da ct013_rwa_princ deve ser filtrado pelas seguintes características: (1) Universo com método de cálculo de capital Standard e IRB - subtipo_risco in (1.1; 1.2; 1.3; 1.4; 1.5; 1.6; 1.7; 1.8; 1.9; 1.13), (2) Universo reportado pelas regulações específicas da área de Capital (ex. COREP) - flag_cons_cap = 1, (3) Universo que concilia contabilisticamente - flag_conc_contab = 1 e (4) exercicio = “REAL”; - Finalmente, para cada chave de capital, foram filtrados os id_capital_perimetros que pertencem ao perímetro em análise (através da tabela ct020_rwa_per); Step 2) CT013_RWA_PRINC: Tratamento da informação por chave FINREP (instrmnt_id) - Foi realizado o cruzamento com os tradutores de modo a mapear a chave do Universo da Loan Tape (chave FINREP) com a de capital (obtida no Step 1); - Uma vez que uma chave FINREP pode estar relacionada com múltiplas de capital e vice-versa, foram realizadas transformações para os diferentes campos de modo a obter um registo único por chave FINREP: group_concat (formula utilizada para juntar todas as chaves de capital/BDR por chave FINREP separada por virgulas). Especificado/ Revisto por: CDO (Luis Capitão-Mor) Guia de conceitos da Corporação: De acordo com o pretendido no Guia. | AL27: N/A | AM27: OK | AN27: N | AO27: Y | AP27: Capital | AQ27: CAPITAL | AR27: Helder Gomes | AU27: 1
A28: =_xlfn.CONCAT(Table2[[#This Row],[TABLE_NAME]],Table2[[#This Row],[COLUMN_NAME]]) -> INSTRUMENTCOD_SOC | B28: INSTRUMENT | C28: COD_SOC | D28: VARCHAR2(5) | E28: - | L28: Entity code of the informing society. | M28: Cargabal code or internal identifier of the informing society. | N28: Cargabal code or internal identifier of the informing society. | O28: TRUE | P28: Default value not allowed | Q28: Default value not allowed | S28: IN.001 | T28: Y | U28: Y | V28: Y | W28: Y | X28: Y | Y28: Y | Z28: Y | AB28: CD_LOAN_TAPES_BCE | AC28: LT001_UNIV_OPER | AD28: COD_SOC | AE28: COD_SOC | AG28: 1) Cruzar LT002_INSTRUMENT com LT001_UNIV_OPER para obter o campo COD_SOC: LT002_INSTRUMENT LEFT JOIN (SELECT * FROM LT001_UNIV_OPER GROUP BY CEMPRESA, CBALCAO, CNUMECTA, ZDEPOSIT) ON INSTRMNT_ID = CONCAT(CEMPRESA, CBALCAO, CNUMECTA, ZDEPOSIT) | AI28: 46010 | AJ28: 02/12/2025: Atualização da metodologia de cálculo para prever os novos campos da LT001. | AK28: Metodologia / Conceito: 1) Código da sociedade contraparte - Código espanha. 2) Consultar documento de especificação de cálculo de Universo para mais informações sobre o cálculo do campo. Especificado / revisto por: CDO (Luis Capitão-Mor) Guia de conceitos da Corporação: De acordo com o pretendido no Guia. | AL28: N/A | AM28: OK | AN28: N | AO28: Y | AP28: Pocessamento | AQ28: PORTFOLIO MANAGER | AR28: Marino Peres | AU28: 0
A29: =_xlfn.CONCAT(Table2[[#This Row],[TABLE_NAME]],Table2[[#This Row],[COLUMN_NAME]]) -> INSTRUMENTCOD_SOC_INTRGRP | B29: INSTRUMENT | C29: COD_SOC_INTRGRP | D29: VARCHAR2(5) | E29: N | L29: Cargabal identification code of the intragroup exposure | N29: Cargabal identification code or internal identifier of the intragroup exposure | O29: FALSE | P29: Default value not allowed | Q29: 00000 | S29: IN.192 | T29: Y | U29: Y | V29: Y | W29: Y | X29: Y | Y29: Y | Z29: Y | AB29: CD_LOAN_TAPES_BCE | AC29: LT001_UNIV_OPER | AD29: COD_SOC_INTRGRP | AE29: COD_SOC_INTRGRP | AG29: 1) Cruzar LT002_INSTRUMENT com LT001_UNIV_OPER para obter o campo COD_SOC_INTRGRP: LT002_INSTRUMENT LEFT JOIN (SELECT * FROM LT001_UNIV_OPER GROUP BY CEMPRESA, CBALCAO, CNUMECTA, ZDEPOSIT) ON INSTRMNT_ID = CONCAT(CEMPRESA, CBALCAO, CNUMECTA, ZDEPOSIT) | AI29: 46010 | AJ29: 12/01/22024: Novo campo adicionado pela Corpração. Atualização da especificação da metodologia de cálculo. 15/09/2025: Alteração do campo fonte do campo CONSOLES da tabela CLIENTES_CONTRAPARTE para o campo SOCIEDADE_CONTRAPARTE da tabela FR012 19/12/2025: Atualização da metodologia de cálculo para prever os novos campos da LT001. | AK29: Metodologia / Conceito: 1) Código da sociedade intragrupo; 2) Conceito previsto no campo CONSOLES da tabela CLIENTES_INTRAGRUPO; 3) Caso o 1º titular não exista na tabela supra, então considera-se o valor de NOT APPLICABLE. Especificado/ Revisto por: CDO (Luís Capitão-Mor) Guia de conceitos da Corporação: Conceito adicionado na versão de dez/23. De acordo com o Guia. | AU29: 1
A30: =_xlfn.CONCAT(Table2[[#This Row],[TABLE_NAME]],Table2[[#This Row],[COLUMN_NAME]]) -> INSTRUMENTCPN_CRRNCY | B30: INSTRUMENT | C30: CPN_CRRNCY | D30: Code List | E30: N | L30: Coupon currency | M30: Currency in which the coupon is paid. | N30: Currency in which the coupon is paid. | O30: TRUE | P30: MISS | Q30: N/A | S30: IN.156 | T30: N | U30: N | V30: N | W30: N | X30: N | Y30: N | Z30: Y | AB30: CD_ALM CD_ESTRUTURAIS | AC30: AL029_CNT_CORE_M TAT91_TABELAS | AD30: CMOEDA_ACT TAYD91C0_CELEMTAB | AE30: TAYD91C0_NELEMC01 WHERE AL029_CNT_CORE_M.TIPO_BALANCO = 'A' AND TAT91_TABELAS.TAYD91C0_CTABELA = '206' AND TAYD91C0_CELEMTAB = CMOEDA_ACT | AF30: - Se flag_inst_div = 0 (LT001_UNIV_OPER) | AG30: 1) Cruzar LT002_INSTRUMENT com tradutor de chaves FINREP e ALM: LT002_INSTRUMENT LEFT JOIN (SELECT * FROM KT_CHAVES_FINREP INNER JOIN SELECT * FROM KT_CHAVES_ALM_M ON CONCAT(CEMPRESA, CBALCAO, CNUMECTA, ZDEPOSIT) = CONCAT(CEMPRESA_MASTER, CBALCAO_MASTER, CNUMECTA_MASTER, ZDEPOSIT_MASTER)) ON INSTRMNT_ID = CONCAT(CEMPRESA_FR, CBALCAO_FR, CNUMECTA_FR, ZDEPOSIT_FR) 2) Cruzar com a informação de ALM para obter o CMOEDA_ACT LEFT JOIN (SELECT * FROM AL029_CNT_CORE_M) ON CONCAT(CEMPRESA, CBALCAO, CNUMECTA, ZDEPOSIT) = CONCAT(CEMPRESA, CBALCAO, CNUMECTA, ZDEPOSIT) 3) Cruzar com a tabela de parametrização para obter o código LEFT JOIN (SELECT * FROM TAT91_TABELAS) ON TAYD91C0_CELEMTAB = CMOEDA_ACT | AI30: 44585 | AJ30: 22/11/2021: Atualização da especificação da metodologia de Cruzamnto e de Not Applicable para passar a influir "Flag_instr_div" 29/11/2021: Atualização de nomenclatura da tabela de parametrização - em vez de TABELA_PARAMETRIZACAO, LT803_CODIGOS_LT. Sem impactos a nível de implementação. 09/12/2021: Atulização da metodologia de cálculo para passar a prever o que foi implementado. Foi alterdo o left join para o inner join com a tabela de perimetros, e acrescentado a condição do nome_perimetro. 24/01/2022: Atualização da metodologia de cálculo e de cruzamento para recorrer à TAT em vez da tabela est_moedas (feedback de Luis Capitão-Mor). 25/01/2022: Alteração da fonte, ao invés de ir pela tabela CT610, ir à tabela AL029 | AK30: Metodologia / Conceito: 1) Moeda na qual o cupão foi pago. 2) Foi utilizado o campo de moeda identificado nas tabelas de ALM Especificado/ Revisto por: CDO (Luís Capitão-Mor) Guia de conceitos da Corporação: Conceito não existente no Guia. | AL30: N/A | AM30: Conceito não existente no Guia | AN30: N | AO30: Y | AP30: Debt Securities | AQ30: RISCO DE MERCADO / ALM | AR30: Cláudia Correia | AS30: Utilizar o CMOEDA da CT610. | AU30: 1
A31: =_xlfn.CONCAT(Table2[[#This Row],[TABLE_NAME]],Table2[[#This Row],[COLUMN_NAME]]) -> INSTRUMENTCPN_RT | B31: INSTRUMENT | C31: CPN_RT | D31: FLOAT 6 decimal places | E31: N | L31: Coupon rate | M31: Coupon rate (if fixed). | N31: Coupon rate (if fixed). | O31: TRUE | P31: 99999999999 | Q31: 11111111111 | S31: IN.157 | T31: N | U31: N | V31: N | W31: N | X31: N | Y31: N | Z31: Y | AB31: CD_ALM | AC31: AL029_CNT_CORE_M | AD31: TX_CONTRATO_ACT | AE31: TX_CONTRATO_ACT/100 WHERE AL029_CNT_CORE_M.TIPO_BALANCO = 'A' AND COD_TIPO_TAXA_ACT = 'F' | AF31: - Se flag_inst_div = 0 (LT001_UNIV_OPER) - Se o campo COD_TIPO_TAXA_ACT assumir um valor diferente de "F" | AG31: 1) Cruzar LT002_INSTRUMENT com tradutor de chaves FINREP e ALM: LT002_INSTRUMENT LEFT JOIN (SELECT * FROM KT_CHAVES_FINREP INNER JOIN SELECT * FROM KT_CHAVES_ALM_M ON CONCAT(CEMPRESA, CBALCAO, CNUMECTA, ZDEPOSIT) = CONCAT(CEMPRESA_MASTER, CBALCAO_MASTER, CNUMECTA_MASTER, ZDEPOSIT_MASTER)) ON INSTRMNT_ID = CONCAT(CEMPRESA_FR, CBALCAO_FR, CNUMECTA_FR, ZDEPOSIT_FR) 2) Cruzar com a informação de ALM para obter o COD_TIPO_TAXA_ACT e TX_CONTRATO_ACT LEFT JOIN (SELECT * FROM AL029_CNT_CORE_M) ON CONCAT(CEMPRESA, CBALCAO, CNUMECTA, ZDEPOSIT) = CONCAT(CEMPRESA, CBALCAO, CNUMECTA, ZDEPOSIT) | AI31: 44672 | AJ31: 22/11/2021: Atualização da especificação da metodologia de Cruzamnto e de Not Applicable para passar a influir "Flag_instr_div" 25/01/2021: Foi retirada a condição de Not Applicable da metodologia de cálculo e a mesma foi adicionada na metodologia de Not Applicable. Foi atualizada a metodologia de cruzamento para facilitar a compreensão. Sem impactos na implementação 20/04/2022: Alteração da metodologia de cáclulo para dividir o campo por 100 por forma obte a taxa enter 0 e 1 | AK31: Metodologia / Conceito: 1) Utilizar conceito previsto nas tabelas de ALM Especificado/ Revisto por: CDO e Risco de Mercado (Luís Capitão-Mor e Cláudia Correia) Guia de conceitos da Corporação: Conceito não existente no Guia. | AL31: N/A | AM31: Conceito não existente no Guia | AN31: N | AO31: N | AP31: Debt Securities | AQ31: RISCO DE MERCADO / ALM | AR31: Cláudia Correia | AS31: Reunião LCM 23-09-2021 (Nova abordagem): Ver AL029 (tipo_balanco = A). (Antiga Abordagem) Ir buscar a taxa associativa quando tipo_taxa = 'fixa'. - Criar uma inteligência de forma a identificar o período em que nos encontramos e identificar a taxa em função desse período. - Validar em função da data de referência a taxa que se aplica. | AU31: 1
A32: =_xlfn.CONCAT(Table2[[#This Row],[TABLE_NAME]],Table2[[#This Row],[COLUMN_NAME]]) -> INSTRUMENTCRE_FNRP18 | B32: INSTRUMENT | C32: CRE_FNRP18 | D32: Y, N | E32: - | L32: Flag of CREs | M32: Loans granted to Commercial Real Estate (reported in FinRep 18 rows 140, 903, 923: “of which: loans collateralized by commercial immovable property”). | N32: Loans granted to Commercial Real Estate (reported in FinRep 18 rows 140, 903, 923: “of which: loans collateralized by commercial immovable property”). | O32: TRUE | P32: Default value not allowed | Q32: Default value not allowed | S32: IN.003 | T32: N | U32: N | V32: N | W32: N | X32: Y | Y32: N | Z32: Y | AB32: Consultar documento de especificação de cálculo de Universo | AC32: Consultar documento de especificação de cálculo de Universo | AD32: Consultar documento de especificação de cálculo de Universo | AE32: Consultar documento de especificação de cálculo de Universo | AF32: Consultar documento de especificação de cálculo de Universo | AG32: Consultar documento de especificação de cálculo de Universo | AI32: - | AK32: Metodologia / Conceito: 1) Flag dummy para identificar se uma determinada exposição se classificada como commercial real estate segundo o Mapa FINREP 18/ NOPER. 2) Consultar documento de especificação de cálculo de Universo para mais informações sobre o cálculo do campo. Especificado / revisto por: CDO (Luis Capitão-Mor) Guia de conceitos da Corporação: De acordo com o pretendido no Guia. | AL32: N/A | AM32: OK | AN32: N | AO32: Y | AP32: Portfolio Instrumentos | AQ32: PORTFOLIO MANAGER / CONTABILIDADE | AR32: Marino Peres / Rafael Pessoa | AU32: 0
A33: =_xlfn.CONCAT(Table2[[#This Row],[TABLE_NAME]],Table2[[#This Row],[COLUMN_NAME]]) -> INSTRUMENTCRRLTN_CFFCNT | B33: INSTRUMENT | C33: CRRLTN_CFFCNT | D33: FLOAT 6 decimal places | E33: N | L33: Coefficient of correlation (R) | M33: The coeefficient of correlation pursuant to Art. 154 Regulation (EU) No 575/2013. | N33: The coeefficient of correlation pursuant to Art. 154 Regulation (EU) No 575/2013. | O33: TRUE | P33: 99999999999 | Q33: 11111111111 | S33: IN.189 | T33: Y | U33: Y | V33: Y | W33: Y | X33: Y | Y33: Y | Z33: N | AB33: CD_LOAN_TAPES_BCE | AC33: BCE_LT_INSTR_CAP | AD33: CRRLTN_CFFCNT | AE33: CRRLTN_CFFCNT | AF33: - Se o campo RWA_MTHD assumir o valor: '2' - Se o campo DFLT_STTS_INSTRMNT = '14' - Se o campo PRJCT_FNNC_LN = '2' - Se o campo auxiliar FLG_CONS_CAP=0 (utilizado na definição do universo de capital) | AG33: 1) Cruzar LT002_INSTRUMENT com tabela temporária BCE_LT_INSTR_CAP para o perimetro em análise: LT002_INSTRUMENT LEFT JOIN (SELECT * FROM BCE_LT_INSTR_CAP) ON INSTRMNT_ID = CHAVE_FR Consultar documento BS_Tabelas_Temporárias_Loan_Tape.xlsx (BCE_LT_INSTR_CAP) | AI33: 45915 | AJ33: 02/09/2022: Atualização da especificação (Campo disponível na BDR apenas apartir de novembro) 21/04/2023: Alteração da fonte do campo CRRLTN_CFFCNT da tabela TMP_BCE_LT_INSTR_CAP para incluir apenas os registos reportados em IRB no COREP. 04/05/2023: Adição de condição na metodologia de cálculo. 16/06/2023: Alteração do cruzamento do campo CRRLTN_CFFCNT da tabela TMP_BCE_LT_INSTR_CAP para incluir a chave primária completa. Adicionalmente, foi alterada a metodologia de cálculo de um DISTINCT para uma média ponderada. Sem impactos na implementação. 21/12/2023: Adição de condições de NOT APPLICABLE na sequência da análise dos controlos da Corporação e completude. 15/09/2025 Reunião LCM: Para o perímetro Individual IDComb na CT020, deve ser filtrada pelo perímetro Individual Corporativo quando a data de referência (REF_DATE) for anterior a 30 de abril de 2025. A partir dessa data (inclusive), deve ser filtrada pelo perímetro Individual IDComb. | AK33: Metodologia / Conceito: A informação de reporte de cálculo de capital é apresentada com uma granularidade distinta do universo esperado na Loan Tape para o BCE. Deste modo, são necessários tratamentos ao nível da chave de capital anteriores ao mapeamento com o universo da Loan Tape: Step 1) TMP_BCE_LT_INSTR_CAP: Tratamento da informação por chave de capital (id_capital_perimetros, s1emp, contra1) - Com o objetivo de fazer face às orientações do BCE relativamente à informação reportada, o universo de contratos da ct013_rwa_princ deve ser filtrado pelas seguintes características: (1) Universo com método de cálculo de capital Standard e IRB - subtipo_risco in (1.1; 1.2; 1.3; 1.4; 1.5; 1.6; 1.7; 1.8; 1.9; 1.13), (2) Universo reportado pelas regulações específicas da área de Capital (ex. COREP) - flag_cons_cap = 1, (3) Universo que concilia contabilisticamente - flag_conc_contab = 1 e (4) exercicio = “REAL”; - De seguida, e uma vez que o mesmo contrato de capital pode ter múltiplos registos e ser calculado em 2 métodos distintos, foram realizadas transformações para os diferentes campos de modo a obter um registo único por chave de capital (nota i); - Finalmente, para cada chave de capital, foram filtrados os id_capital_perimetros que pertencem ao perímetro em análise (através da tabela ct020_rwa_per); Step 2) BCE_LT_INSTR_CAP: Tratamento da informação por chave FINREP (chave_fr = instrmnt_id) - Foi realizado o cruzamento com os tradutores de modo a mapear a chave do Universo da Loan Tape (chave FINREP) com a de capital (obtida no Step 1); - Uma vez que uma chave FINREP pode estar relacionada com múltiplas de capital e vice-versa, foram realizadas transformações para os diferentes campos de modo a obter um registo único por chave FINREP; - Para os campos de atributos, caso um contrato de com chave de finrep esteja relacionado com múltiplas de capital deve ser escolhido o registo de acordo com as seguintes ordens de prioridade: 1º Se a chave FINREP contiver chaves de capital com FLG_IDCTOORI for 1 e 0 escolher registo onde FLG_IDCTOORI = 0; 2º Se a chave FINREP contiver chaves de capital com produtos de estruturas e diferente de estruturas (id_prod = 47) então escolher registo onde id_prod <> 47 (diferente de estruturas) 3º Se a chave FINREP contiver chaves de capital com 2 RWA_MTHD escolher registo onde RWA_MTHD = '1' (IRB) 4º (nota ii) Especificamente sobre o campo CRRLTN_CFFCNT (referente ao coeficiente de correlação de acrdo com o artigo Art. 154 do CRR - No 575/2013): Nota i: Sem tratamento adicional; Nota ii: Foi calculada a média ponderada pela EAD. Notas adicionais: 1) O campo apenas não será aplicável a: a) Contratos calculados em método Standard; b) Contratos que não consomem capital (flg_cons_cap=0) - [Definido em reunião com LCM a 21/12/2023] c) Contratos para contratos em IRB que (i) estão em default ou (ii) são project finance loans. [definido em âmbito de análise aos controlos - e-mail de confirmação de João Tiago Reis a 20/12/2023] Especificado/ Revisto por: CDO (Luis Capitão-Mor) Guia de conceitos da Corporação: De acordo com o pretendido no Guia. | AL33: N/A | AM33: OK | AN33: N | AO33: N - rever se mantemos em tabela temporária ou no DDR (processo) | AP33: Capital | AQ33: CAPITAL | AR33: Helder Gomes | AU33: 1
A34: =_xlfn.CONCAT(Table2[[#This Row],[TABLE_NAME]],Table2[[#This Row],[COLUMN_NAME]]) -> INSTRUMENTCRRNCY_DNMNTN | B34: INSTRUMENT | C34: CRRNCY_DNMNTN | D34: Code List | E34: Y | F34: Y | G34: Y | H34: Y | I34: Y | J34: Y | K34: Y | L34: Currency denomination | M34: Currency denomination of instruments, in accordance with the ISO 4217 standard. | N34: Currency denomination of instruments, in accordance with the ISO 4217 standard. | O34: TRUE | P34: MISS | Q34: Default value not allowed | S34: IN.010 | T34: Y | U34: Y | V34: Y | W34: Y | X34: Y | Y34: Y | Z34: Y | AB34: CD_CAPTOOLS CD_ESTRUTURAIS | AC34: FR004_CTO TAT91_TABELAS | AD34: CMOEDA1 TAYD91C0_NELEMC01 | AE34: TAYD91C0_NELEMC01 WHERE TAYD91C0_CTABELA = '206' AND TRIM(TAYD91C0_CELEMTAB) = CMOEDA1 | AF34: - | AG34: 1) Cruzar LT002_INSTRUMENT com FR004_CTO para obter o campo CMOEDA1: LT002_INSTRUMENT LEFT JOIN (SELECT * FROM FR004_CTO) ON INSTRMNT_ID = CONCAT(CEMPRESA, CBALCAO, CNUMECTA, ZDEPOSIT) 2) Cruzar o campo obtido no passo anterior com a tabela de parametrização TAT91_TABELAS de modo a obter os códigos permitidos na code list: (SELECT * FROM CD_ESTRUTURAIS.TAT91_TABELAS) ON TAYD91C0_CELEMTAB = CMOEDA1 | AI34: 44575 | AJ34: 29/11/2021: Atualização de nomenclatura da tabela de parametrização - em vez de TABELA_PARAMETRIZACAO, LT803_CODIGOS_LT. Sem impactos a nível de implementação. 14/01/2022: Atualização da metodologia de cálculo e de cruzamento para recorrer à TAT em vez da tabela est_moedas (feedback de Luis Capitão-Mor). 28/07/2023: Atualização de parametrização de NOT APLLICABLE para contratos de ajustes. | AK34: Metodologia / Conceito: 1) Campo deve ser reportado segundo os códigos de moedas presentes no campo CMOEDA1 da FR004_CTO e parametrizado através da TAT91 (ctabela = '206') de modo a obter os códigos permitidos pela Code List. Especificado/ Revisto por: Contabilidade + CDO (Rafael Pessoa + Luis Capitão-Mor) Guia de conceitos da Corporação: De acordo com o pretendido no Guia. | AL34: Campo: moeda Não está de acordo com o reportado na AnaCredit: Alguns dos contratos não deverão conciliar com a CRC quando esta reporta 'USD', o que corresponde ao valor '840' identificado no campo CMOEDA2 da tabela CT004_UNIV_CTO, ao invés de reportar 'EUR' que corresponde ao valor de '978' identificado no campo CMOEDA1 da mesma tabela. A fonte para esta variável é o campo CMOEDA da tabela DWT846_Carteiras_IC, o campo ‘CMOEDA’ da tabela SAT1202_FA_SALDOS_FS para (Ficheiro 22 – Factoring) e o campo ‘CMOEDA’ da tabela SAT1206_LG_SALDOS_FS para (Ficheiro 22 – Leasing) e o campo CMOEDA-ORIG do ficheiro BIYR0103 de Londres. | AM34: OK | AN34: N | AO34: Y | AP34: Portfolio Instrumentos | AQ34: CONTABILIDADE | AR34: Rafael Pessoa | AU34: 1
A35: =_xlfn.CONCAT(Table2[[#This Row],[TABLE_NAME]],Table2[[#This Row],[COLUMN_NAME]]) -> INSTRUMENTCRRYNG_AMNT_INSTRMNT | B35: INSTRUMENT | C35: CRRYNG_AMNT_INSTRMNT | D35: FLOAT 2 decimal places | E35: Y | F35: Y | G35: Y | H35: Y | I35: Y | J35: Y | K35: Y | L35: Carrying amount | M35: Net carrying amount including accrued interest as laid down in Annex 5 Regulation 680/2014. | N35: Net carrying amount including accrued interest as laid down in Annex 5 Regulation 680/2014. | O35: TRUE | P35: 99999999999 | Q35: 11111111111 | S35: IN.068 | T35: Y | U35: Y | V35: Y | W35: Y | X35: Y | Y35: Y | Z35: Y | AB35: CD_LOAN_TAPES_BCE | AC35: LT002_INSTRUMENT | AD35: GRSS_CRRYNG_AMNT_INSTRMNT ACCMLTD_IMPRMNT_INSTRMNT | AE35: GRSS_CRRYNG_AMNT_INSTRMNT - ACCMLTD_IMPRMNT_INSTRMNT | AF35: - | AG35: 1) Usar os campos GRSS_CRRYNG_AMNT_INSTRMNT e ACCMLTD_IMPRMNT_INSTRMNT a aprovisionar na tabela LT002_INSTRUMENT. | AI35: 44650 | AJ35: 08/11/21: A metodologia de Not Applicable mantém-se igual à versão original (não foi aplicada a metodologia de default values proposta pela corporação). 18/02/22: Atualização da metodologia de cálculo para prever os novos campos da FR004 30/03/22: Atualização da metodologia de cálculo para prever os campos da LT002 | AK35: Metodologia / Conceito: 1) Campo deve ser reportado segundo o saldo da exposição liquida dentro de balanço, isto é, valor bruto deduzido de provisões. 2) Uma vez que ambos os campos, são calculados na Loan Tape, este é calculado com base na subtração de GRSS_CRRYNG_AMNT_INSTRMNT com ACCMLTD_IMPRMNT_INSTRMNT Nota: É suposto e normal existirem valores negativos. No mapa F18 do FINREP, os valores negativos são, também, considerados. Especificado/ Revisto por: Contabilidade (Rafael Pessoa e Luisa de Sousa) Guia de conceitos da Corporação: De acordo com o pretendido no Guia. | AM35: OK | AN35: N | AO35: Y | AP35: Contabilidade | AQ35: CONTABILIDADE | AR35: Rafael Pessoa | AU35: 1
A36: =_xlfn.CONCAT(Table2[[#This Row],[TABLE_NAME]],Table2[[#This Row],[COLUMN_NAME]]) -> INSTRUMENTCSH_SWP_TRP | B36: INSTRUMENT | C36: CSH_SWP_TRP | D36: Y, N | E36: N | F36: Y | G36: Y | H36: Y | I36: N | J36: N | K36: N | L36: Cash sweep or cash trap covenants agreed (Y/N) | M36: Report "Y" if the agreement with the debtor includes cash sweep or cash trap covenants. | N36: Report "Y" if the agreement with the debtor includes cash sweep or cash trap covenants. | O36: TRUE | P36: MISS | Q36: N/A | S36: IN.017 | T36: Y | U36: Y | V36: Y | W36: Y | X36: Y | Y36: N | Z36: N | AB36: FIXO | AC36: FIXO | AD36: FIXO | AE36: 'N' | AF36: - | AG36: - | AI36: 44370 | AK36: Metodologia / Conceito: 1) O tipo de mecanismo presente neste campo não existe para a carteira de Crédito do Banco, sendo mais usual em projects. Deste modo, assumiu-se o valor "N" (não) para toda a carteira de crédito. Especificado/ Revisto por: Risco de Crédito (Luis Bastos) Guia de conceitos da Corporação: Análise não realizada. | AL36: N/A | AM36: Análise não realizada | AN36: N | AO36: Y | AP36: Portfolio Instrumentos | AQ36: INFORMAÇÃO DE RISCOS | AR36: Marino Peres | AU36: 1
A37: =_xlfn.CONCAT(Table2[[#This Row],[TABLE_NAME]],Table2[[#This Row],[COLUMN_NAME]]) -> INSTRUMENTCVNNT_STTS | B37: INSTRUMENT | C37: CVNNT_STTS | D37: Code List | E37: N | F37: N | G37: N | H37: Y | I37: N | J37: N | K37: N | L37: Covenant status | M37: In accordance with "ECB Guidance on leveraged transactions". The term "material covenant" should be defined according to bank-internal nomenclature. | N37: In accordance with "ECB Guidance on leveraged transactions". The term "material covenant" should be defined according to bank-internal nomenclature. | O37: TRUE | P37: 99999999999 | Q37: 11111111111 | S37: IN.018 | T37: N | U37: N | V37: N | W37: N | X37: Y | Y37: N | Z37: N | AB37: CD_LOAN_TAPES_BCE | AC37: LT601_LEV_FIN LT803_CODIGOS_LT | AD37: ESTADO_ACORDO VALOR_LT | AE37: VALOR_LT | AF37: - Se o contrato não pertencer ao universo de Leverage Finance (LT601_LEV_FIN) | AG37: UNIVERSO INSTR LEFT JOIN SELECT * FROM KT_CHAVES_FINREP ON INSTRMNT_ID = CONCAT(CEMPRESA, CBALCAO, CNUMECTA, ZDEPOSIT) LEFT JOIN SELECT * FROM LT601_LEV_FIN ON CONCAT(CEMPRESA, CBALCAO, CNUMECTA, ZDEPOSIT) LEFT JOIN SELECT * FROM LT803_CODIGOS_LT WHERE CAMPO_LT = 'CVNNT_STTS' ON VALOR_ORIGEM = ESTADO_ACORDO | AI37: 44665 | AJ37: 08/11/21: A metodologia de Not Applicable mantém-se igual à versão original (não foi aplicada a metodologia de default values proposta pela corporação). 29/11/2021: Atualização de nomenclatura da tabela de parametrização - em vez de TABELA_PARAMETRIZACAO, LT803_CODIGOS_LT. Sem impactos a nível de implementação. 14/04/22: Inclusão de uma cláusula de not applicable | AK37: 1. A informação de leverage finance só é reportada trimestralmente, pelo que a informação é igual durante o trimestre (exemplo: Janeiro 2021 e Fevereiro 2021 são iguais a Dezembro 2020) 2. A informação está a null na tabela original (LVF) Guia de conceitos da Corporação: De acordo com o Guia da Corporação. | AL37: N/A | AM37: WIP | AN37: ? | AO37: N | AP37: Leverage Finance | AQ37: INFORMAÇÃO DE RISCOS | AR37: Marino Peres | AS37: Reunião Alexandre Duarte 05/07/2021: 1. Informação reportada trimestralmente. 2. Teresa Romão não tem como preencher este campo. 3. Alex ficou de corfirmar com o LCM o aprovisionamento deste campo, | AU37: 1
A38: =_xlfn.CONCAT(Table2[[#This Row],[TABLE_NAME]],Table2[[#This Row],[COLUMN_NAME]]) -> INSTRUMENTCVNNT_TYP | B38: INSTRUMENT | C38: CVNNT_TYP | D38: Code List | E38: N | F38: N | G38: N | H38: Y | I38: N | J38: N | K38: N | L38: Covenant Type | M38: Type of covenant according to "ECB Guidance on leveraged transactions". | N38: Type of covenant according to "ECB Guidance on leveraged transactions". | O38: TRUE | P38: 99999999999 | Q38: 11111111111 | S38: IN.019 | T38: N | U38: N | V38: N | W38: N | X38: Y | Y38: N | Z38: N | AB38: CD_LOAN_TAPES_BCE | AC38: LT601_LEV_FIN LT803_CODIGOS_LT | AD38: TIPO_ACORDO VALOR_LT | AE38: VALOR_LT | AF38: - Se o contrato não pertencer ao universo de Leverage Finance (LT601_LEV_FIN) | AG38: UNIVERSO INSTR LEFT JOIN SELECT * FROM KT_CHAVES_FINREP ON INSTRMNT_ID = CONCAT(CEMPRESA, CBALCAO, CNUMECTA, ZDEPOSIT) LEFT JOIN SELECT * FROM LT601_LEV_FIN ON CONCAT(CEMPRESA, CBALCAO, CNUMECTA, ZDEPOSIT) LEFT JOIN SELECT * FROM LT803_CODIGOS_LT WHERE CAMPO_LT = 'CVNNT_TYP' ON VALOR_ORIGEM = TIPO_ACORDO | AI38: 44665 | AJ38: 08/11/21: A metodologia de Not Applicable mantém-se igual à versão original (não foi aplicada a metodologia de default values proposta pela corporação). 29/11/2021: Atualização de nomenclatura da tabela de parametrização - em vez de TABELA_PARAMETRIZACAO, LT803_CODIGOS_LT. Sem impactos a nível de implementação. 14/04/22: Inclusão de uma cláusula de not applicable | AK38: 1. A informação de leverage finance só é reportada trimestralmente, pelo que a informação é igual durante o trimestre (exemplo: Janeiro 2021 e Fevereiro 2021 são iguais a Dezembro 2020). Guia de conceitos da Corporação: De acordo com o Guia da Corporação. | AL38: N/A | AM38: WIP | AN38: ? | AO38: N | AP38: Leverage Finance | AQ38: INFORMAÇÃO DE RISCOS | AR38: Marino Peres | AS38: Reunião Alexandre Duarte 05/07/2021: 1. Informação reportada trimestralmente. 2. Alexandre ficou de enviar mapeamento das descrições com as do BCE 3. Nome do campo TIPO_ACORDO pode mudar de nome Reunião Marino 1. Falar com Teresa/ sonia/erik sobre Pari Passu | AU38: 1
A39: =_xlfn.CONCAT(Table2[[#This Row],[TABLE_NAME]],Table2[[#This Row],[COLUMN_NAME]]) -> INSTRUMENTDBT_YLD | B39: INSTRUMENT | C39: DBT_YLD | D39: FLOAT 6 decimal places | E39: N | F39: N | G39: Y | H39: N | I39: N | J39: N | K39: N | L39: Debt yield | M39: Ratio of net annual rental income divided by the total gross carrying amount which is secured by the CRE property - (see ESRB/2016/14 for details regarding the calculation of net annual rental income). | N39: Ratio of net annual rental income divided by the total gross carrying amount which is secured by the CRE property - (see ESRB/2016/14 for details regarding the calculation of net annual rental income). | O39: TRUE | P39: 99999999999 | Q39: 11111111111 | S39: IN.069 | T39: N | U39: N | V39: N | W39: N | X39: Y | Y39: N | Z39: N | AB39: FIXO | AC39: FIXO | AD39: FIXO | AE39: Valor da coluna "NULLABLE" | AF39: - | AG39: - | AI39: 44550 | AK39: Metodologia / Conceito: 1) Deve ser calculado o rácio entre os rendimentos liquidos do CRE de rendimento e a exposição bruta do contrato na origem do contrato. 2) A informação de rendimentos e despesas de CRE de rendimento não está disponível em sistema, deste modo, o campo deve ser reportado como "sem informação", i.e., com o valor da coluna NULLABLE. Especificado/ Revisto por: Portfolio Manager (Marino Peres) Guia de conceitos da Corporação: Não está de acordo com o Guia porque será reportado com o valor da coluna NULLABLE. | AL39: N/A | AM39: OK | AN39: N | AO39: Y | AP39: Crédito Hipotecário | AQ39: PORTFOLIO MANAGER | AR39: Marino Peres | AU39: 1
A40: =_xlfn.CONCAT(Table2[[#This Row],[TABLE_NAME]],Table2[[#This Row],[COLUMN_NAME]]) -> INSTRUMENTDFLT_STTS_INSTRMNT | B40: INSTRUMENT | C40: DFLT_STTS_INSTRMNT | D40: Code List | E40: Y | F40: Y | G40: Y | H40: Y | I40: Y | J40: Y | K40: Y | L40: Default status of the instrument | M40: Identification of the default status of the instrument. Categories describing the situations in which an instrument can be described as being at default in accordance with Article 178 of Regulation (EU) No 575/2013. | N40: Identification of the default status of the instrument. Categories describing the situations in which an instrument can be described as being at default in accordance with Article 178 of Regulation (EU) No 575/2013. | O40: TRUE | P40: 99999999999 | Q40: Default value not allowed | S40: IN.020 | T40: Y | U40: Y | V40: Y | W40: Y | X40: Y | Y40: Y | Z40: N | AB40: CD_LOAN_TAPES_BCE | AC40: BCE_LT_INSTR_CAP | AD40: DFLT_STTS_INSTRMNT | AE40: NVL(DFLT_STTS_INSTRMNT,99999999999) | AF40: - | AG40: 1. CRUZAR LT002_INSTRUMENT COM O TRADUTOR DE CHAVES LT LT002 LEFT JOIN (SELECT * FROM KT_CHAVES_LT) 2. CRUZAR COM TABELA TEMPORÁRIA BCE_LT_INSTR_CAP, PARA O PERÍMETRO EM ANÁLISE: LEFT JOIN (SELECT * FROM BCE_LT_INSTR_CAP) ON INSTRMNT_ID = CHAVE_FR CONSULTAR DOCUMENTO BS_TABELAS_TEMPORÁRIAS_LOAN_TAPE.XLSX (BCE_LT_INSTR_CAP) | AI40: 45915 | AJ40: 27/10/2021 Reunião LCM: Eliminação da regra "'- Se a entidade não pertencer ao universo de Capital (BCE_LT_INSTR_CAP)" na Metodologia de NOT APPLICABLE. 04/02/2022: Alteração de tabela de parametrização (adição de campo de ordem). 21/12/2023 Reunião LCM: Adição de condições de NOT APPLICABLE na sequência da análise dos controlos da Corporação e completude. 22/04/2025: Reunião LCM e Maria Leonor: Eliminação de condições NOT APPLICABLE, na sequência de guidelines e controlos da Corporação Alteração da metodologia de cálculo, incluindo NVL Alteração dos filtros de ataque à ct013 na tabela temporária bce_lt_instr_cap flag_cons_cap IN (1,2) OR flag_conc_contab IN (1,2) ao invés de (flag_cons_cap IN (1,2) AND flag_conc_contab IN (1,2) Alteração da tabela de parametrização (a lt802 deverá ser desconsiderada, passando a utilizar-se a lt831) 11/07/2025: Adição na metodologia de cruzamento do KT_CHAVES_BDR, de modo a ter valor de dafult para os ajustes 15/09/2025 Reunião LCM: Para o perímetro Individual IDComb na CT020, deve ser filtrada pelo perímetro Individual Corporativo quando a data de referência (REF_DATE) for anterior a 30 de abril de 2025. A partir dessa data (inclusive), deve ser filtrada pelo perímetro Individual IDComb. | AK40: Metodologia / Conceito: A informação de reporte de cálculo de capital é apresentada com uma granularidade distinta do universo esperado na Loan Tape para o BCE. Deste modo, são necessários tratamentos ao nível da chave de capital anteriores ao mapeamento com o universo da Loan Tape: Step 1) TMP_BCE_LT_INSTR_CAP: Tratamento da informação por chave de capital (id_capital_perimetros, s1emp, contra1) - Com o objetivo de fazer face às orientações do BCE relativamente à informação reportada, o universo de contratos da ct013_rwa_princ deve ser filtrado pelas seguintes características: (1) Universo com método de cálculo de capital Standard e IRB - subtipo_risco in (1.1; 1.2; 1.3; 1.4; 1.5; 1.6; 1.7; 1.8; 1.9; 1.13), (2) Universo reportado pelas regulações específicas da área de Capital (ex. COREP) - flag_cons_cap = 1, (3) Universo que concilia contabilisticamente - flag_conc_contab = 1 e (4) exercicio = “REAL”; - De seguida, e uma vez que o mesmo contrato de capital pode ter múltiplos registos e ser calculado em 2 métodos distintos, foram realizadas transformações para os diferentes campos de modo a obter um registo único por chave de capital (nota i); - Finalmente, para cada chave de capital, foram filtrados os id_capital_perimetros que pertencem ao perímetro em análise (através da tabela ct020_rwa_per); Step 2) BCE_LT_INSTR_CAP: Tratamento da informação por chave FINREP (chave_fr = instrmnt_id) - Foi realizado o cruzamento com os tradutores de modo a mapear a chave do Universo da Loan Tape (chave FINREP) com a de capital (obtida no Step 1); - Uma vez que uma chave FINREP pode estar relacionada com múltiplas de capital e vice-versa, foram realizadas transformações para os diferentes campos de modo a obter um registo único por chave FINREP; - Para os campos de atributos, caso um contrato de com chave de finrep esteja relacionado com múltiplas de capital deve ser escolhido o registo de acordo com as seguintes ordens de prioridade: 1º Se a chave FINREP contiver chaves de capital com FLG_IDCTOORI for 1 e 0 escolher registo onde FLG_IDCTOORI = 0; 2º Se a chave FINREP contiver chaves de capital com produtos de estruturas e diferente de estruturas (id_prod = 47) então escolher registo onde id_prod <> 47 (diferente de estruturas) 3º Se a chave FINREP contiver chaves de capital com 2 RWA_MTHD escolher registo onde RWA_MTHD = '1' (IRB) 4º (nota ii) Especificamente sobre o campo DFLT_STTS_INSTRMNT (referente ao estado de default inicial): Nota i: 1) Uma vez que é permitido um conjunto limitado de opções de default face às disponíveis no motor de cálculo de new default, ficaram definidas as seguintes regras (consultar tabela de parametrização LT802_DFLT_STTS): - 14 (not in default): flag de default inicial = 0 - 18 (Default because both unlikely to pay and more than 90/180 days past due): flag de default inicial = 1 e com um indicador de UTP e 91 dias ou mais em atraso * , ou com um indicador de período probatório ou de efeito de pulling. Estes últimos foram inseridos nesta categoria por não ser clara a razão destes indicadores (se por dias de atraso ou UTP). - 19 (Default because unlikely to pay): flag de default inicial = 1 e com um indicador de UTP (garantindo que não existem dias de atraso) - 20 (Default because more than 90/180 days past due): flag de default inicial = 1 e com 91 dias ou mais de atraso (garantindo que não tem um indicador de UTP) *denote-se que o motor não afere quando está em ambas as situações ao mesmo tempo, mas sim sobre a primeira. A tabela de parametrização deve contemplar todos os campos que contribuem para essa classificação. Por exemplo, se no motor está indicado que o cliente entrou em default por dias de incumprimento, é necessário validar os campos GEST_SIT e UTP_CLI para validar se também está com um indicador de UTP. Estas regras devem ser validadas regularmente para garantir que o reportado na LT é similar às regras do motor. Nota ii: Caso permaneça mais do que um DFLT_STTS_INSTRMNT distinto por chave FINREP, deve ser escolhido o 18 (exceto nos seguintes casos: se um contrato com chave FINREP tiver um estado de default (19 ou 20) e um not default (14), então escolher o de default (19 ou 20). Caso contrário, atribuir o status associado. Notas adicionais: 1) Em âmbito do projeto do Loan Tape os campos de New Deafult provenientes do motor de cálculo da BDR foram adicionados à tabela CT013_RWA_PRINC no Datalake. Especificado/ Revisto por: Capital + CDO (Susana Arrochinho e José Carlos Epifânio + Luis Capitão-Mor). Guia de conceitos da Corporação: Não está de acordo com o pretendido no Guia, uma vez que 1) porque a granularidade é diferente entre a BDR e a Loan Tape, os resultados esperados podem diferir. Adicionalmente, 2), os indicadores de pulling effect estão a ser considerados como código 19 e a LT considera como 18, uma vez que não é possível aferir qual o efeito que está a ser contagiado, se por dias de atraso ou UTP. | AL40: Campo: estIncInst Análise não realizada após atualização do campo reportado na AnaCredit. (atualização realizada no dia 02/02/2022) | AM40: OK | AN40: N | AO40: N - rever se mantemos em tabela temporária ou no DDR (processo) | AP40: New Default | AQ40: CAPITAL | AR40: Helder Gomes | AS40: 1. INMORA inicial = 1 2 3 5 6 7 -- novos codigos de ND- Gonçalo Marques ou jose carlos 3. INMORIN (do titular) --- Sim 4. Qual o mapeamento dos códigos deles da BDR 5. Ver feedback da Corporação (ID4 - mapeamento está a ser realizado | Indicador de mora pré mitigação) 2. Feedback de Jesus sobre mapeamento (reunião 10/03) a) Caso a flag seja DPD, então analisar tabela de situação de gestão e ver se o contrato está marcado com códigos de UTP i. To-dos: Ver modelo físico o mapeamento de códigos e confirmar com José Carlos Epifanio -- ok b. Caso a flag seja UTP, então analisar campo de Days Past Due. Se DPD > 90 dias, então tem os dois critérios, senão só UTP prioriza o 1º portanto vou ver a situação de gestão e se sim - está nos 2 c. Para os casos em que as flags são "Probation Period", então andar para trás até encontrar uma flag de UTP ou DPD. Replicar cases a) e b) para esse rácio Reunião 16-03-2021: 1. Validar com Corporação metodologia a adotar: Iremos ter 6 casos --- Corporação concordou a) Não está em default (14) b) Só em UTP (por IND_DEF ou Situação de Gestão ou Flag UTP na Client_BII) (19) c) So em DPD (por IND_DEF ou DIAS_ATR >92) (20) d) Em UTP e DPD (junção da alinea b e c) (18) e) Em PP (assumir que pode estar assim por UTP ou DPD) (18) - Para estes casos propor ao BCE a criação de um novo código f) Em Pulling (18) | AU40: 1
A41: =_xlfn.CONCAT(Table2[[#This Row],[TABLE_NAME]],Table2[[#This Row],[COLUMN_NAME]]) -> INSTRUMENTDPD | B41: INSTRUMENT | C41: DPD | D41: INTEGER | E41: N | F41: Y | G41: Y | H41: Y | I41: Y | J41: Y | K41: Y | L41: Days past due at reference date | M41: Days past due at reference date in accordance with Art 178 of Regulation (EU) No 575/2013. | N41: Days past due at reference date in accordance with Art 178 of Regulation (EU) No 575/2013. | O41: TRUE | P41: 99999999999 | Q41: 11111111111 | S41: IN.094 | T41: N | U41: Y | V41: Y | W41: Y | X41: Y | Y41: Y | Z41: N | AB41: CD_LOAN_TAPES_BCE | AC41: BCE_LT_INSTR_CAP | AD41: DPD | AE41: DPD | AF41: - Se o campo RWA_MTHD assumir o valor: '2'. - Se o campo auxiliar FLG_CONS_CAP=0 (utilizado na definição do universo de capital) | AG41: 1) Cruzar LT002_INSTRUMENT com tabela temporária BCE_LT_INSTR_CAP para o perimetro em análise: LT002_INSTRUMENT LEFT JOIN (SELECT * FROM BCE_LT_INSTR_CAP) ON INSTRMNT_ID = CHAVE_FR Consultar documento BS_Tabelas_Temporárias_Loan_Tape.xlsx (BCE_LT_INSTR_CAP) | AI41: 45915 | AJ41: 27/10/2021 Reunião LCM: Eliminação da regra "'- Se a entidade não pertencer ao universo de Capital (BCE_LT_INSTR_CAP)" na Metodologia de NOT APPLICABLE. 24/04/2025: Alteração dos filtros de ataque à ct013 na tabela temporária bce_lt_instr_cap flag_cons_cap IN (1,2) OR flag_conc_contab IN (1,2) ao invés de (flag_cons_cap IN (1,2) AND flag_conc_contab IN (1,2) 15/09/2025 Reunião LCM: Para o perímetro Individual IDComb na CT020, deve ser filtrada pelo perímetro Individual Corporativo quando a data de referência (REF_DATE) for anterior a 30 de abril de 2025. A partir dessa data (inclusive), deve ser filtrada pelo perímetro Individual IDComb. | AK41: Metodologia / Conceito: A informação de reporte de cálculo de capital é apresentada com uma granularidade distinta do universo esperado na Loan Tape para o BCE. Deste modo, são necessários tratamentos ao nível da chave de capital anteriores ao mapeamento com o universo da Loan Tape: Step 1) TMP_BCE_LT_INSTR_CAP: Tratamento da informação por chave de capital (id_capital_perimetros, s1emp, contra1) - Com o objetivo de fazer face às orientações do BCE relativamente à informação reportada, o universo de contratos da ct013_rwa_princ deve ser filtrado pelas seguintes características: (1) Universo com método de cálculo de capital Standard e IRB - subtipo_risco in (1.1; 1.2; 1.3; 1.4; 1.5; 1.6; 1.7; 1.8; 1.9; 1.13), (2) Universo reportado pelas regulações específicas da área de Capital (ex. COREP) - flag_cons_cap = 1, (3) Universo que concilia contabilisticamente - flag_conc_contab = 1 e (4) exercicio = “REAL”; - De seguida, e uma vez que o mesmo contrato de capital pode ter múltiplos registos e ser calculado em 2 métodos distintos, foram realizadas transformações para os diferentes campos de modo a obter um registo único por chave de capital (nota i); - Finalmente, para cada chave de capital, foram filtrados os id_capital_perimetros que pertencem ao perímetro em análise (através da tabela ct020_rwa_per); Step 2) BCE_LT_INSTR_CAP: Tratamento da informação por chave FINREP (chave_fr = instrmnt_id) - Foi realizado o cruzamento com os tradutores de modo a mapear a chave do Universo da Loan Tape (chave FINREP) com a de capital (obtida no Step 1); - Uma vez que uma chave FINREP pode estar relacionada com múltiplas de capital e vice-versa, foram realizadas transformações para os diferentes campos de modo a obter um registo único por chave FINREP; - Para os campos de atributos, caso um contrato de com chave de finrep esteja relacionado com múltiplas de capital deve ser escolhido o registo de acordo com as seguintes ordens de prioridade: 1º Se a chave FINREP contiver chaves de capital com FLG_IDCTOORI for 1 e 0 escolher registo onde FLG_IDCTOORI = 0; 2º Se a chave FINREP contiver chaves de capital com produtos de estruturas e diferente de estruturas (id_prod = 47) então escolher registo onde id_prod <> 47 (diferente de estruturas) 3º Se a chave FINREP contiver chaves de capital com 2 RWA_MTHD escolher registo onde RWA_MTHD = '1' (IRB) 4º (nota ii) Especificamente sobre o campo DPD (referente ao calculo de dias de atraso segundo a normativa de New Default): Nota i: Sem tratamento adicional Nota ii: Caso sejam identificados mais do que 1 indicação de dias de atraso para uma chave FINREP, considerou-se o máximo. Notas adicionais: 1) O campo DPD, ao contrário dos restantes campos DPD_*, segue a normativa de New Default utilizada pela área de capital e os restantes seguirem a metodologia da área da contabilidade (através do MOYR e área de Imparidade). A futuro todos os campos devem ser revistos por forma a validar se a metodologia se mantém. 2) Em âmbito do projeto do Loan Tape os campos de New Default provenientes do motor de cálculo da BDR foram adicionados à tabela CT013_RWA_PRINC no Datalake. Especificado/ Revisto por: Capital + CDO (Susana Arrochinho e José Carlos Epifânio + Luis Capitão-Mor). Guia de conceitos da Corporação: De acordo com o pretendido no Guia, uma vez que a metodologia de cálculo já está incorporada no próprio motor da BDR | AL41: N/A | AM41: OK | AN41: N | AO41: N - rever se mantemos em tabela temporária ou no DDR (processo) | AP41: New Default | AQ41: CAPITAL | AR41: Helder Gomes | AS41: 1. Validar nas tabelas CT014 ou CT022 se é possivel obter este campo da BDR. 2. Atenção este campo pode conter informação de Rating (0 a 99 - definidos pelo analista) e de Scoring (0 a 500) e conceptualmente o campo pede apenas Ratings -- Validar com Jesus. (ver se há outro campo para ajudar a diferenciar o rating do scoring) -- Tipmodel 3. Validar de o rating que é considerado em capital está em codigo local ou nativo (preferncial) --- Validar com Jesus 4. Validar com Pedro Almeida se são valores nativos ou de bdr 5. Validar valores possiveis -- lista de baremos 6. Validar se o output do LT tem que ser atualizado e em que formato? 7. Criar uma tabela de parametrização (identificar numero de dimensões que vamos exportar - através das ct009, ct010, ct011) 8. Adicionar nos requisitos que o mapa do LT deverá também exportar algumas dimensões e num formato particular 9. Se apenas o devedor for classificado, então aplicar esse rating a todos os seus contratos. 10. Reunião 10/03 a. Em principio só existem ratings a nivel de cliente i. To-dos: 1) Ver todos os ratings que estão a sair (por TIPO e TIPMODEL) 2) Ver com Fernando Jara os resultados (ver email com resposta) b. Campo de ratings é sempre preenchido independentemente do método de cálculo de RWA (STD ou IRB) c. O mapeamento entre Ratings e PD é realizado via online. i. To-dos: 1) Ver com Jaime como seria possivel extrair a tabela de parametrização via SAS (ou modelica?) d) Uma vez que a Code List é efetuada localmente, o mapeamento de códigos de ratings e PD deverá ser inserida diretamente na pestana de code list do excel | AU41: 1
A42: =_xlfn.CONCAT(Table2[[#This Row],[TABLE_NAME]],Table2[[#This Row],[COLUMN_NAME]]) -> INSTRUMENTDPD_12M | B42: INSTRUMENT | C42: DPD_12M | D42: INTEGER | E42: N | F42: Y | G42: Y | H42: N | I42: Y | J42: Y | K42: Y | L42: Highest number of days past due in the last 12 months | M42: Highest number of days past due within a period of 12 months prior to the reference date. | N42: Highest number of days past due within a period of 12 months prior to the reference date. | O42: TRUE | P42: 99999999999 | Q42: 11111111111 | S42: IN.095 | T42: N | U42: Y | V42: Y | W42: Y | X42: Y | Y42: Y | Z42: N | AB42: CD_LOAN_TAPES_BCE | AC42: TMP_BCE_LT_MOYR | AD42: DIAS_INCUMP | AE42: NVL( MAX(DIAS_INCUMP) ; 0 ) | AF42: - | AG42: Consultar documento BS_Tabelas_Temporárias_Loan_Tape.xlsx (TMP_BCE_LT_MOYR) UNIVERSO INSTR LEFT JOIN (SELECT * FROM CD_CAPTOOLS.KT_CHAVES_FINREP GROUP BY EMPRESA, CBALCAO, CNUMECTA, ZDEPOSIT) ON CEMPRESA, CBALCAO, CNUMECTA, ZDEPOSIT LEFT JOIN (SELECT * FROM TMP_BCE_LT_MOYR WHERE DATA_DATE_PART ['${REFDATE}' -12 MESES] AND '${REFDATE}' GROUP BY CEMPRESA, CBALCAO, CNUMECTA, ZDEPOSIT) ON CEMPRESA, CBALCAO, CNUMECTA, ZDEPOSIT | AI42: 44236 | AJ42: 04/02/2022: Foi adicionado um NVL à metodologia de cálculo. | AK42: Simulação realizada com histórico de 3 meses (dez20, jan21, fev21) | AL42: N/A | AM42: WIP | AN42: N | AO42: N | AP42: NPE | AQ42: CONTABILIDADE | AR42: Rafael Pessoa | AU42: 1
A43: =_xlfn.CONCAT(Table2[[#This Row],[TABLE_NAME]],Table2[[#This Row],[COLUMN_NAME]]) -> INSTRUMENTDPD_12M_FRBRNC_STTS | B43: INSTRUMENT | C43: DPD_12M_FRBRNC_STTS | D43: INTEGER | E43: N | F43: Y | G43: N | H43: N | I43: Y | J43: Y | K43: Y | L43: Highest number of days past due in the 12 months prior to the most recent change of the forbearance status | M43: Highest number of days past due within a period of 12 months prior to the most recent change of the forbearance status. As regards forbearance status please refer to Part 18 of Annex V to Implementing Regulation (EU) No 680/2014. The data attribute is only to be populated for instances where a status change occured during an observation period of maximum 24month preceding the reference date. | N43: Highest number of days past due within a period of 12 months prior to the most recent change of the forbearance status. As regards forbearance status please refer to Part 18 of Annex V to Implementing Regulation (EU) No 680/2014. The data attribute is only to be populated for instances where a status change occured during an observation period of maximum 24month preceding the reference date. | O43: TRUE | P43: 99999999999 | Q43: 11111111111 | S43: IN.096 | T43: N | U43: Y | V43: Y | W43: Y | X43: Y | Y43: Y | Z43: N | AB43: CD_LOAN_TAPES_BCE | AC43: TMP_BCE_LT_MOYR | AD43: DIAS_INCUMP | AE43: 1. Obtenção de campos auxiliares ao cálculo: a) DT_12M: [LT002_INSTRUMENT.DT_FRBRNC_STTS - 12 meses] 2. Obtenção do campo DPD_12M_FRBRNC_STTS - NVL ( MAX(DIAS_INCUMP) ; 0) WHERE SUBSTR(DT_12M,1,7) < SUBSTR(BCE_LT_MOYR.DATA_DATE_PART, 1,7) AND SUBSTR(LT002_INSTRUMENT.DT_FRBRNC_STTS,1,7) > = SUBSTR(BCE_LT_MOYR.DATA_DATE_PART, 1,7) | AF43: - Se o campo FRBRNC_STTS_INSTRMNT assumir o valor "8" e o campo DT_FRBRNC_STTS = DT_INCPTN - Se o campo DT_FRBRNC_STTS < [ref_date - 24 meses] | AG43: 1) Cruzar LT002_INSTRUMENT com tradutor de chaves FINREP para obter os campos necessários: LT002_INSTRUMENT LEFT JOIN (SELECT * FROM KT_CHAVES_FINREP) ON INSTRMNT_ID = CONCAT(CEMPRESA_FR, CBALCAO_FR, CNUMECTA_FR, ZDEPOSIT_FR) 2) Cruzar com a tabela TMP_BCE_LT_MOYR pela chave master, de forma a obter um período histórico de 12 meses: INNER JOIN (SELECT * FROM TMP_BCE_LT_MOYR) ON CEMPRESA = CEMPRESA AND CBALCAO = CBALCAO AND CNUMECTA = CNUMECTA AND ZDEPOSIT = ZDEPOSIT AND SUBSTR(DT_12M,1,7) < SUBSTR(DATA_DATE_PART,1,7) AND SUBSTR(DT_FRBRNC_STTS,1,7) > = SUBSTR(DATA_DATE_PART,1,7) Consultar documento BS_Tabelas_Temporárias_Loan_Tape.xlsx (TMP_BCE_LT_MOYR) | AI43: 44679 | AJ43: 23/12/2021: Substituição da tabela fonte RSV133SA1_DEST_SOL_CRED pela RNT05_SOLDST e atualização do nome dos campos 04/02/2022: Foi adicionada uma condição à metodologia de Not Applicable e adicionado um NVL à metodologia de cálculo 09/02/2022: Foi adicionada uma condição à metodologia de Not Applicable 18/03/2022: Atualização da metodologia de cálculo e de cruzamento para passar a depender de outro campo (DT_FRBRNC_STTS). Foi alterada a condição à metodologia de Not Applicable 28/04/2022: Atualização da metodologia de cálculo e cruzamento de forma a que o período de 12 meses em análise inclua o fecho de mês da DT_FRBRNC_STTS. Exemplo: DT_FRBRNC_STTS = 07/10/2021 então período em análise [31/10/2021 - 31/10/2020[ . | AK43: Conceito / Metodologia: 1) Informação sobre os dias de atraso deve ser consultada nos MOYRs à data de fim de mês, uma vez que as tabelas podem não ser processadas diariamente; 2) Período em análise deve considerar o período de 12 meses que antecedem a data de entrada no estado de forbearance (incluindo a data de final de mês da data do forbearance status). Exemplo: DT_FRBRNC_STTS = 07/10/2021 então período em análise [31/10/2021 - 31/10/2020[ . Notas de Espanha: FINREP ou Capital? Efectivamente deberían seguir la definición de Non Performing y Forbereance de FINREP, ya que van relacionados con el Anexo V de las ITS que es la base para el propio FINREP. En cuanto a la frecuencia de generación, la plan de trabajo definido consiste en la generación trimestral de estos Loan Tapes, ya que el ECB nos ha confirmado que en futuras inspecciones se podrá requerir información de cierres trimestrales. | AL43: N/A | AM43: WIP | AN43: N | AO43: N | AP43: NPE | AQ43: CONTABILIDADE | AR43: Rafael Pessoa | AU43: 1
A44: =_xlfn.CONCAT(Table2[[#This Row],[TABLE_NAME]],Table2[[#This Row],[COLUMN_NAME]]) -> INSTRUMENTDPD_12M_PRFRMNG_STTS | B44: INSTRUMENT | C44: DPD_12M_PRFRMNG_STTS | D44: INTEGER | E44: N | F44: Y | G44: N | H44: N | I44: Y | J44: Y | K44: Y | L44: Highest number of days past due in the 12 months prior to the most recent change of performing status | M44: Highest number of days past due within a period of 12 months prior to the change of the performing status. As regards performing status please refer to Part 17 of Annex V to Implementing Regulation (EU) No 680/2014. The data attribute is only to be populated for instances where a status change occured during an observation period of maximum 24month preceding the reference date. | N44: Highest number of days past due within a period of 12 months prior to the change of the performing status. As regards performing status please refer to Part 17 of Annex V to Implementing Regulation (EU) No 680/2014. The data attribute is only to be populated for instances where a status change occured during an observation period of maximum 24month preceding the reference date. | O44: TRUE | P44: 99999999999 | Q44: 11111111111 | S44: IN.097 | T44: N | U44: Y | V44: Y | W44: Y | X44: Y | Y44: Y | Z44: N | AB44: CD_CAPTOOLS | AC44: TMP_BCE_LT_MOYR | AD44: DIAS_INCUMP | AE44: NVL ( MAX(DIAS_INCUMP); 0 ) | AF44: - Se o DT_PRFRMNG_STTS assumir o valor da DT_INCPTN - Se o campo DT_PRFRMNG_STTS < [ref_date - 24 meses] | AG44: Consultar documento BS_Tabelas_Temporárias_Loan_Tape.xlsx (TMP_BCE_LT_MOYR) UNIVERSO INSTR LEFT JOIN (SELECT * FROM CD_CAPTOOLS.KT_CHAVES_FINREP GROUP BY EMPRESA, CBALCAO, CNUMECTA, ZDEPOSIT) ON CEMPRESA, CBALCAO, CNUMECTA, ZDEPOSIT LEFT JOIN ( (SELECT * FROM TMP_BCE_LT_MOYR) A INNER JOIN (SELECT MAX(REF_DATE) AS DT_ULT_ALT, (MAX(REF_DATE) - 12MESES) AS DT_12M FROM BU_CAPTOOLS.BCE_LT_SPRT_PRFM GROUP BY CONTRACT) B ON (A.DATA_DATE_PART > B.DT_12M AND A.DATA_DATE_PART < A.DT_ULT_ALT) GROUP BY CEMPRESA, CBALCAO, CNUMECTA, ZDEPOSIT ) ON CEMPRESA, CBALCAO, CNUMECTA, ZDEPOSIT | AI44: 45880 | AJ44: 04/02/2022: Foi adicionada uma condição à metodologia de Not Applicable e adicionado um NVL à metodologia de cálculo. 16/09/22: Campo influênciado pela alteração da tabela temporária BU_CAPTOOLS.BCE_LT_SPRT_PRFM (nova especificação enviada a 09/09/22). 27/09/2024: Alteração na tabela de suporte temporária de forma a prever as alterações de stage/performing nas tabelas de IFRS9 (até Nov.22 fonte IFRS9, após Dez.22 inclusive fonte FR) 27/05/2025: Alteração da metodologia de NOT APPLICABLE onde foi eliminada a condição do PRFRMNG_STTS_PRVS = 11111111111 e adicionada a condição em que o DT_PRFRMNG_STTS_PRVS assumir o valor da DT_INCPTN (Atualização do Guia Corporativo) 11/08/2025: Alteração da metodologia de NOT APPLICABLE onde foi alterada a condição em que o DT_PRFRMNG_STTS assumir o valor da DT_INCPTN | AK44: 1. Validar informação de dias de incumpriemento nos 12 meses anteriores à ultima classificação como performing | AL44: N/A | AM44: WIP | AN44: N | AO44: N | AP44: NPE | AQ44: IMPARIDADE / CONTABILIDADE | AR44: Alexandre Gonçalves / Rafael Pessoa | AS44: Duplicados | AU44: 1
A45: =_xlfn.CONCAT(Table2[[#This Row],[TABLE_NAME]],Table2[[#This Row],[COLUMN_NAME]]) -> INSTRUMENTDPD_24M_FRBRNC_STTS | B45: INSTRUMENT | C45: DPD_24M_FRBRNC_STTS | D45: INTEGER | E45: N | F45: Y | G45: N | H45: N | I45: Y | J45: Y | K45: Y | L45: Highest number of days past due in the 24 months prior to the most recent change of the forbearance status | M45: Highest number of days past due within a period of 24 months prior to the change of the forbearance status. As regards forbearance status please refer to Part 18 of Annex V to Implementing Regulation (EU) No 680/2014. The data attribute is only to be populated for instances where a status change occured during an observation period of maximum 24month preceding the reference date. | N45: Highest number of days past due within a period of 24 months prior to the change of the forbearance status. As regards forbearance status please refer to Part 18 of Annex V to Implementing Regulation (EU) No 680/2014. The data attribute is only to be populated for instances where a status change occured during an observation period of maximum 24month preceding the reference date. | O45: TRUE | P45: 99999999999 | Q45: 11111111111 | S45: IN.098 | T45: N | U45: Y | V45: Y | W45: Y | X45: Y | Y45: Y | Z45: N | AB45: CD_CAPTOOLS | AC45: TMP_BCE_LT_MOYR | AD45: DIAS_INCUMP | AE45: 1. Obtenção de campos auxiliares ao cálculo: a) DT_24M: [LT002_INSTRUMENT.DT_FRBRNC_STTS - 24 meses] 2. Obtenção do campo DPD_24M_FRBRNC_STTS - NVL ( MAX(DIAS_INCUMP) ; 0) WHERE SUBSTR(DT_24M,1,7) < SUBSTR(BCE_LT_MOYR.DATA_DATE_PART, 1,7) AND SUBSTR(LT002_INSTRUMENT.DT_FRBRNC_STTS,1,7) > = SUBSTR(BCE_LT_MOYR.DATA_DATE_PART, 1,7) | AF45: - Se o campo FRBRNC_STTS_INSTRMNT assumir o valor "8" e o campo DT_FRBRNC_STTS = DT_INCPTN - Se o campo DT_FRBRNC_STTS < [ref_date - 24 meses] | AG45: 1) Cruzar LT002_INSTRUMENT com tradutor de chaves FINREP para obter os campos necessários: LT002_INSTRUMENT LEFT JOIN (SELECT * FROM KT_CHAVES_FINREP) ON INSTRMNT_ID = CONCAT(CEMPRESA_FR, CBALCAO_FR, CNUMECTA_FR, ZDEPOSIT_FR) 2) Cruzar com a tabela TMP_BCE_LT_MOYR pela chave master, de forma a obter um período histórico de 24 meses: INNER JOIN (SELECT * FROM TMP_BCE_LT_MOYR) ON CEMPRESA = CEMPRESA AND CBALCAO = CBALCAO AND CNUMECTA = CNUMECTA AND ZDEPOSIT = ZDEPOSIT AND SUBSTR(DT_24M,1,7) < SUBSTR(DATA_DATE_PART,1,7) AND SUBSTR(DT_FRBRNC_STTS1,7) > =SUBSTR(DATA_DATE_PART,1,7) Consultar documento BS_Tabelas_Temporárias_Loan_Tape.xlsx (TMP_BCE_LT_MOYR) | AI45: 44679 | AJ45: 23/12/2021: Substituição da tabela fonte RSV133SA1_DEST_SOL_CRED pela RNT05_SOLDST e atualização do nome dos campos 04/02/2022: Foi adicionada uma condição à metodologia de Not Applicable e adicionado um NVL à metodologia de cálculo 09/02/2022: Foi adicionada uma condição à metodologia de Not Applicable 18/03/2022: Atualização da metodologia de cálculo e de cruzamento para passar a depender de outro campo (DT_FRBRNC_STTS). Foi alterada a condição à metodologia de Not Applicable 28/04/2022: Atualização da metodologia de cálculo e cruzamento de forma a que o período de 24 meses em análise inclua o fecho de mês da DT_FRBRNC_STTS. Exemplo: DT_FRBRNC_STTS = 07/10/2021 então período em análise [31/10/2021 - 31/10/2019[ . | AK45: Conceito / Metodologia: 1) Informação sobre os dias de atraso deve ser consultada nos MOYRs à data de fim de mês, uma vez que as tabelas podem não ser processadas diariamente; 2) Período em análise deve considerar o período de 24 meses que antecedem a data de entrada no estado de forbearance (incluindo a data de final de mês da data do forbearance status). Exemplo: DT_FRBRNC_STTS = 07/10/2021 então período em análise [31/10/2021 - 31/10/2019[ . | AL45: N/A | AM45: WIP | AN45: N | AO45: N | AP45: NPE | AQ45: CONTABILIDADE | AR45: Rafael Pessoa | AS45: Validar se existe nas tabelas de risco (rstf_99) / IFR001 & 802 | AU45: 1
A46: =_xlfn.CONCAT(Table2[[#This Row],[TABLE_NAME]],Table2[[#This Row],[COLUMN_NAME]]) -> INSTRUMENTDPD_24M_PRFRMNG_STTS | B46: INSTRUMENT | C46: DPD_24M_PRFRMNG_STTS | D46: INTEGER | E46: N | F46: Y | G46: N | H46: N | I46: Y | J46: Y | K46: Y | L46: Highest number of days past due in the 24 months before most recent change of performing status | M46: Highest number of days past due within a period of 24 months prior to the change of the performing status. As regards performing status please refer to Part 17 of Annex V to Implementing Regulation (EU) No 680/2014. | N46: Highest number of days past due within a period of 24 months prior to the change of the performing status. As regards performing status please refer to Part 17 of Annex V to Implementing Regulation (EU) No 680/2014. | O46: TRUE | P46: 99999999999 | Q46: 11111111111 | S46: IN.099 | T46: N | U46: Y | V46: Y | W46: Y | X46: Y | Y46: Y | Z46: N | AB46: CD_CAPTOOLS | AC46: TMP_BCE_LT_MOYR | AD46: DIAS_INCUMP | AE46: NVL ( MAX(DIAS_INCUMP); 0 ) | AF46: - Se o DT_PRFRMNG_STTS assumir o valor da DT_INCPTN - Se o campo DT_PRFRMNG_STTS < [ref_date - 24 meses] | AG46: Consultar documento BS_Tabelas_Temporárias_Loan_Tape.xlsx (TMP_BCE_LT_MOYR) UNIVERSO INSTR LEFT JOIN (SELECT * FROM CD_CAPTOOLS.KT_CHAVES_FINREP GROUP BY EMPRESA, CBALCAO, CNUMECTA, ZDEPOSIT) ON CEMPRESA, CBALCAO, CNUMECTA, ZDEPOSIT LEFT JOIN ( (SELECT * FROM TMP_BCE_LT_MOYR) A INNER JOIN (SELECT MAX(REF_DATE) AS DT_ULT_ALT, (MAX(REF_DATE) - 24MESES) AS DT_24M FROM BU_CAPTOOLS.BCE_LT_SPRT_PRFM GROUP BY CONTRACT) B ON (A.DATA_DATE_PART > B.DT_24M AND A.DATA_DATE_PART < A.DT_ULT_ALT) GROUP BY CEMPRESA, CBALCAO, CNUMECTA, ZDEPOSIT ) ON CEMPRESA, CBALCAO, CNUMECTA, ZDEPOSIT | AI46: 45880 | AJ46: 04/02/2022: Foi adicionada uma condição à metodologia de Not Applicable e adicionado um NVL à metodologia de cálculo. 16/09/22: Campo influênciado pela alteração da tabela temporária BU_CAPTOOLS.BCE_LT_SPRT_PRFM (nova especificação enviada a 09/09/22). 27/09/2024: Alteração na tabela de suporte temporária de forma a prever as alterações de stage/performing nas tabelas de IFRS9 (até Nov.22 fonte IFRS9, após Dez.22 inclusive fonte FR) 27/05/2025: Alteração da metodologia de NOT APPLICABLE onde foi eliminada a condição do PRFRMNG_STTS_PRVS = 11111111111 e adicionada a condição em que o DT_PRFRMNG_STTS_PRVS assumir o valor da DT_INCPTN (Atualização do Guia Corporativo) 11/08/2025: Alteração da metodologia de NOT APPLICABLE onde foi alterada a condição em que o DT_PRFRMNG_STTS assumir o valor da DT_INCPTN | AK46: 1. Validar informação de dias de incumpriemento nos 24 meses anteriores à ultima classificação como performing | AL46: N/A | AM46: WIP | AN46: N | AO46: N | AP46: NPE | AQ46: IMPARIDADE / CONTABILIDADE | AR46: Alexandre Gonçalves / Rafael Pessoa | AU46: 1
A47: =_xlfn.CONCAT(Table2[[#This Row],[TABLE_NAME]],Table2[[#This Row],[COLUMN_NAME]]) -> INSTRUMENTDPD_FRBRNC_STTS | B47: INSTRUMENT | C47: DPD_FRBRNC_STTS | D47: INTEGER | E47: N | F47: Y | G47: Y | H47: N | I47: Y | J47: Y | K47: Y | L47: Days past due at the date of the most recent change of the forbearance status | M47: Days past due at the date of the most recent change of the forbearance status. Data attribute reported only for those instruments where any change in its classification occured during a maximum observation period of 24 month preceding the reference date. As regards forbearance status please refer to Part 18 of Annex V to Implementing Regulation (EU) No 680/2014. | N47: Days past due at the date of the most recent change of the forbearance status. Data attribute reported only for those instruments where any change in its classification occured during a maximum observation period of 24 month preceding the reference date. As regards forbearance status please refer to Part 18 of Annex V to Implementing Regulation (EU) No 680/2014. | O47: TRUE | P47: 99999999999 | Q47: 11111111111 | S47: IN.100 | T47: N | U47: Y | V47: Y | W47: Y | X47: Y | Y47: Y | Z47: N | AB47: CD_CAPTOOLS | AC47: TMP_BCE_LT_MOYR | AD47: DIAS_INCUMP | AE47: NVL ( DIAS_INCUMP ; 0 ) | AF47: - Se o campo FRBRNC_STTS_INSTRMNT assumir o valor "8" e o campo DT_FRBRNC_STTS = DT_INCPTN - Se o campo DT_FRBRNC_STTS < [ref_date - 24 meses] | AG47: 1) Cruzar LT002_INSTRUMENT com tradutor de chaves FINREP para obter os campos necessários: LT002_INSTRUMENT LEFT JOIN (SELECT * FROM KT_CHAVES_FINREP) ON INSTRMNT_ID = CONCAT(CEMPRESA_FR, CBALCAO_FR, CNUMECTA_FR, ZDEPOSIT_FR) 2) Cruzar com a tabela TMP_BCE_LT_MOYR pela chave master, à data de fim de mês de frorbearance status (definida no campo DT_FRBRNC_STTS): INNER JOIN (SELECT * FROM TMP_BCE_LT_MOYR) ON CEMPRESA = CEMPRESA AND CBALCAO = CBALCAO AND CNUMECTA = CNUMECTA AND ZDEPOSIT = ZDEPOSIT AND SUBSTR(DT_FRBRNC_STTS, 1 ,7) =SUBSTR(DATA_DATE _PART,1,7) Consultar documento BS_Tabelas_Temporárias_Loan_Tape.xlsx (TMP_BCE_LT_MOYR) | AI47: 44679 | AJ47: 23/12/2021: Substituição da tabela fonte RSV133SA1_DEST_SOL_CRED pela RNT05_SOLDST e atualização do nome dos campos 04/02/2022: Foi adicionada um conndição à metodologia de Not Applicable e adicionado um NVL à metodologia de cálculo 09/02/2022: Foi adicionada uma condição à metodologia de Not Applicable 18/03/2022: Atualização da metodologia de cálculo e de cruzamento para passar a depender de outro campo (DT_FRBRNC_STTS). Foi alterada a condição à metodologia de Not Applicable 28/04/2022: Atualização da metodologia de cálculo e cruzamento: Por forma a tornar o campo coerente com os campos DPD_12M_FRBRNC_STTS e DPD_24M_FRBRNC_STTS. Exemplo: DT_FRBRNC_STTS = 07/10/2021 então a data de análise nos MOYRS: 31/10/2021 | AK47: Conceito / Metodologia: 1) Informação sobre os dias de atraso deve ser consultada nos MOYRs à data de fim de mês, uma vez que as tabelas podem não ser processadas diariamente; 2) Por forma a tornar o campo coerente com os campos DPD_12M_FRBRNC_STTS e DPD_24M_FRBRNC_STTS, se um contrato tem uma data de forbearnce a meio do mês, deve-se considerar os dias em atraso no fim do mesmo mê. Exemplo: DT_FRBRNC_STTS = 07/10/2021 data de análise 31/10/2021 | AL47: N/A | AM47: WIP | AN47: N | AO47: N | AP47: NPE | AQ47: CONTABILIDADE | AR47: Rafael Pessoa | AS47: Validar com IT | AU47: 1
A48: =_xlfn.CONCAT(Table2[[#This Row],[TABLE_NAME]],Table2[[#This Row],[COLUMN_NAME]]) -> INSTRUMENTDPD_PRFRMNG_STTS | B48: INSTRUMENT | C48: DPD_PRFRMNG_STTS | D48: INTEGER | E48: N | F48: Y | G48: Y | H48: N | I48: Y | J48: Y | K48: Y | L48: Days past due at the time of the most recent change of the performing status | M48: Days past due at the time of the most recent change of the performing status. As regards performing status please refer to Part 17 of Annex V to Implementing Regulation (EU) No 680/2014. | N48: Days past due at the time of the most recent change of the performing status. As regards performing status please refer to Part 17 of Annex V to Implementing Regulation (EU) No 680/2014. | O48: TRUE | P48: 99999999999 | Q48: 11111111111 | S48: IN.101 | T48: N | U48: Y | V48: Y | W48: Y | X48: Y | Y48: Y | Z48: N | AB48: CD_CAPTOOLS | AC48: TMP_BCE_LT_MOYR | AD48: DIAS_INCUMP | AE48: NVL ( DIAS_INCUMP ; 0 ) | AF48: - Se o DT_PRFRMNG_STTS assumir o valor da DT_INCPTN - Se o campo DT_PRFRMNG_STTS < [ref_date - 24 meses] | AG48: Consultar documento BS_Tabelas_Temporárias_Loan_Tape.xlsx (TMP_BCE_LT_MOYR) UNIVERSO INSTR LEFT JOIN (SELECT * FROM CD_CAPTOOLS.KT_CHAVES_FINREP GROUP BY EMPRESA, CBALCAO, CNUMECTA, ZDEPOSIT) ON CEMPRESA, CBALCAO, CNUMECTA, ZDEPOSIT LEFT JOIN ( (SELECT * FROM TMP_BCE_LT_MOYR) A INNER JOIN (SELECT MAX(REF_DATE) AS DT_ULT_ALT FROM BU_CAPTOOLS.BCE_LT_SPRT_PRFM GROUP BY CONTRACT) B ON (A.DATA_DATE_PART = DT_ULT_ALT) GROUP BY CEMPRESA, CBALCAO, CNUMECTA, ZDEPOSIT ) ON CEMPRESA, CBALCAO, CNUMECTA, ZDEPOSIT | AI48: 45880 | AJ48: 04/02/2022: Foi adicionada uma condição à metodologia de Not Applicable e adicionado um NVL à metodologia de cálculo. 16/09/22: Campo influênciado pela alteração da tabela temporária BU_CAPTOOLS.BCE_LT_SPRT_PRFM (nova especificação enviada a 09/09/22) 27/09/2024: Alteração na tabela de suporte temporária de forma a prever as alterações de stage/performing nas tabelas de IFRS9 (até Nov.22 fonte IFRS9, após Dez.22 inclusive fonte FR) 27/05/2025: Alteração da metodologia de NOT APPLICABLE onde foi eliminada a condição do PRFRMNG_STTS_PRVS = 11111111111 e adicionada a condição em que o DT_PRFRMNG_STTS_PRVS assumir o valor da DT_INCPTN (Atualização do Guia Corporativo) 11/08/2025: Alteração da metodologia de NOT APPLICABLE onde foi alterada a condição em que o DT_PRFRMNG_STTS assumir o valor da DT_INCPTN | AK48: XXXXX - + conservadora Guia de conceitos da Corporação: De acordo com o pretendido no Guia. | AL48: N/A | AM48: WIP | AN48: N | AO48: N | AP48: NPE | AQ48: IMPARIDADE / CONTABILIDADE | AR48: Alexandre Gonçalves / Rafael Pessoa | AS48: (ver com IT historico > 12 meses) | AU48: 1
A49: =_xlfn.CONCAT(Table2[[#This Row],[TABLE_NAME]],Table2[[#This Row],[COLUMN_NAME]]) -> INSTRUMENTDSTI | B49: INSTRUMENT | C49: DSTI | D49: FLOAT 6 decimal places | E49: N | L49: DSTI at reference date | N49: Debt Service to Income (DSTI) as defined in Recommendation ESRB/2016/14 as amended by Recommendation ESRB/2019/3, Annex IV, i.e. ‘disposable income’ of the borrower at numerator. The income should include to the extent possible the following items: Disposable income = employee income + self-employment income (e.g. profits) + income from public pensions + income from private and occupational pensions + income from unemployment benefits + income from social transfers other than unemployment benefits + regular private transfers (such as alimonies) + gross rental income from real estate property + income from financial investments + income from private business or partnership + regular income from other sources + loan subsidies – taxes – health care/social security/medical insurance premiums + tax rebates. Debt Services is the annual debt servicing costs of the total debt of the borrower, whether or not this debt is secured by real estate, including all outstanding financial loans, granted by the bank itself or by other lenders. Income and debt information should be reported at the latest available date. If only income information at origination is available, then income at origination should be reported. | O49: FALSE | P49: 99999999999 | Q49: 11111111111 | S49: IN.237 | T49: N | U49: N | V49: N | W49: N | X49: N | Y49: Y | Z49: N | AI49: - | AU49: 0
A50: =_xlfn.CONCAT(Table2[[#This Row],[TABLE_NAME]],Table2[[#This Row],[COLUMN_NAME]]) -> INSTRUMENTDT_CMPLNT_MRTR_STTS_C19 | B50: INSTRUMENT | C50: DT_CMPLNT_MRTR_STTS_C19 | D50: DATE | E50: N | F50: Y | G50: Y | H50: Y | I50: Y | J50: Y | K50: Y | L50: Date of EBA compliant moratoria status | M50: The latest date on which the EBA moratoria status as reported in “EBA compliant moratoria status” is considered to have been established or changed. Exposures that are subject to both EBA-compliant moratoria and other COVID-19-related forbearance measures should be reported only once as EBA-compliant moratoria. Data attribute shall be reported if not waived by the competent authority according to points (a), (c), (d) or (e) of Article 19 of EBA/GL/2020/07 Guidelines on reporting and disclosure of exposures subject to measures applied in response to the COVID-19 crisis. | N50: The latest date on which the EBA moratoria status as reported in “EBA compliant moratoria status” is considered to have been established or changed. Exposures that are subject to both EBA-compliant moratoria and other COVID-19-related forbearance measures should be reported only once as EBA-compliant moratoria. Data attribute shall be reported if not waived by the competent authority according to points (a), (c), (d) or (e) of Article 19 of EBA/GL/2020/07 Guidelines on reporting and disclosure of exposures subject to measures applied in response to the COVID-19 crisis. | O50: TRUE | P50: 0000-00-00 | Q50: 1111-11-11 | S50: IN.140 | T50: N | U50: N | V50: N | W50: N | X50: Y | Y50: Y | Z50: N | AB50: CD_CAPTOOLS | AC50: CT902_EBA_REPORT_CONTAB | AD50: DTESTADO DINIPED | AE50: CASE WHEN DTESTADO = '9999-12-31' THEN DINIPED ELSE DTESTADO WHERE F_NEW_MONEY = '0' | AF50: - Se o contrato não pertencer ao universo COVID-19 Moratórias* *Universo COVID-19 Moratórias EBA a ser considerado: CT902_EBA_REPORT_CONTAB WHERE F_NEW_MONEY ='0' | AG50: 1) Cruzar LT002_INSTRUMENT com LT001_UNIV_OPER para obter as várias componentes da chave do contrato: LT002_INSTRUMENT LEFT JOIN (SELECT * FROM LT001_UNIV_OPER) ON INSTRMNT_ID = CONCAT(CEMPRESA, CBALCAO, CNUMECTA, ZDEPOSIT) 2) Cruzar chave obtida no passo anterior com informação de moratórias COVID-19: LEFT JOIN (SELECT * FROM CT902_EBA_REPORT_CONTAB) ON CONCAT(CBALCAO, CNUMECTA, ZDEPOSIT) = CONCAT(CBALCAO, CNUMECTA, ZDEPOSIT) | AI50: 44679 | AJ50: 08/11/21: Foi eliminada da metdologia de Not Applicable "Se ACCNTNG_CLSSFCTN = 2" 17/12/2021: Foi reestruturado o texto da metodologia de Not Applicable, por forma a tornar mais claro o pretendido (sem impacto na implementação) 28/04/22: Foi alterada a metodologia de cáclulo de modo a garantir que o campo DT_CMPLNT_MRTR_STTS_C19 não é reportardo com '9999-12-31' | AL50: N/A | AP50: COVID19 | AQ50: CONTABILIDADE | AR50: Rafael Pessoa | AU50: 1
A51: =_xlfn.CONCAT(Table2[[#This Row],[TABLE_NAME]],Table2[[#This Row],[COLUMN_NAME]]) -> INSTRUMENTDT_CMPLNT_MRTR_STTS_PRVS_C19 | B51: INSTRUMENT | C51: DT_CMPLNT_MRTR_STTS_PRVS_C19 | D51: DATE | E51: N | F51: Y | G51: Y | H51: Y | I51: Y | J51: Y | K51: Y | L51: Initial date of first EBA compliant moratoria status | M51: The date on which the previous EBA moratoria status as reported in “EBA compliant moratoria status” is considered to have been established or changed. Exposures that are subject to both EBA-compliant moratoria and other COVID-19-related forbearance measures should be reported only once as EBA-compliant moratoria. EBA/GL/2020/07 Guidelines on reporting and disclosure of exposures subject to measures applied in response to the COVID-19 crisis. Data attribute shall be reported if not waived by the competent authority according to points (a), (c), (d) or (e) of Article 19 of EBA/GL/2020/07 Guidelines on reporting and disclosure of exposures subject to measures applied in response to the COVID-19 crisis. | N51: The date on which the previous EBA moratoria status as reported in “EBA compliant moratoria status” is considered to have been established or changed. Exposures that are subject to both EBA-compliant moratoria and other COVID-19-related forbearance measures should be reported only once as EBA-compliant moratoria. EBA/GL/2020/07 Guidelines on reporting and disclosure of exposures subject to measures applied in response to the COVID-19 crisis. Data attribute shall be reported if not waived by the competent authority according to points (a), (c), (d) or (e) of Article 19 of EBA/GL/2020/07 Guidelines on reporting and disclosure of exposures subject to measures applied in response to the COVID-19 crisis. | O51: TRUE | P51: 0000-00-00 | Q51: 1111-11-11 | S51: IN.141 | T51: N | U51: N | V51: N | W51: N | X51: Y | Y51: Y | Z51: N | AB51: CD_CAPTOOLS | AC51: CT902_EBA_REPORT_CONTAB | AD51: DTESTADO DINIPED | AE51: CASE WHEN DTESTADO = '9999-12-31' THEN VALOR DA COLUNA NOT APPLICABALE WHEN DTESTADO <> '9999-12-31' AND DINIPED <> '9999-12-31' THEN DINIPED | AF51: - Se o contrato não pertencer ao universo COVID-19 Moratórias* *Universo COVID-19 Moratórias EBA a ser considerado: CT902_EBA_REPORT_CONTAB WHERE F_NEW_MONEY ='0' | AG51: UNIVERSO INSTR LEFT JOIN SELECT * FROM CT902_EBA_REPORT_CONTAB WHERE F_NEW_MONEY = '0' ON CBALCAO AND CNUMECTA AND ZDEPOSIT | AI51: 44693 | AJ51: 04/11/21: A metodologia de Not Applicbale mantém-se igual à versão original (não foi aplicada a metodologia de default values proposta pela corporação). 17/12/2021: Foi reestruturado o texto da metodologia de Not Applicable, por forma a tornar mais claro o pretendido (sem impacto na implementação) 28/04/22: Foi alterada a metodologia de cáclulo de modo a garantir que o campo DT_CMPLNT_MRTR_STTS_C19 não é reportardo com '9999-12-31' 12/05/22: Foi alterada a metodologia de cáclulo de modo a garantir que o campo DT_CMPLNT_MRTR_STTS_PRVS_C19 não é reportardo com '9999-12-31' | AL51: N/A | AP51: COVID19 | AQ51: CONTABILIDADE | AR51: Rafael Pessoa | AS51: Validar se o Luis Barata consegue apoiar na identificação da informação | AU51: 1
A52: =_xlfn.CONCAT(Table2[[#This Row],[TABLE_NAME]],Table2[[#This Row],[COLUMN_NAME]]) -> INSTRUMENTDT_DFLT_STTS_INSTRMNT | B52: INSTRUMENT | C52: DT_DFLT_STTS_INSTRMNT | D52: DATE | E52: Y | F52: Y | G52: Y | H52: Y | I52: Y | J52: Y | K52: Y | L52: Date of default status | M52: The date on which the default status, as reported in the data attribute “Default status”, is considered to have arisen. If "Not in default" since inception then this attribute is to be reported equally to the inception date. If more than one Instrument is classified as defaulted then the earliest date has to be provided. The definition of default is aligned with Art 178 of Regulation (EU) No 575/2013. | N52: The date on which the default status, as reported in the data attribute “Default status”, is considered to have arisen. If "Not in default" since inception then this attribute is to be reported equally to the inception date. If more than one Instrument is classified as defaulted then the earliest date has to be provided. The definition of default is aligned with Art 178 of Regulation (EU) No 575/2013. | O52: TRUE | P52: 0000-00-00 | Q52: Default value not allowed | S52: IN.021 | T52: Y | U52: Y | V52: Y | W52: Y | X52: Y | Y52: Y | Z52: N | AB52: CD_LOAN_TAPES_BCE | AC52: BCE_LT_SPRT_DFLT | AD52: DT_DFLT_STTS_INSTRMNT | AE52: 1. SE DFLT_STTS_INSTRMNT = 14 E MAX(NR) = 1, ENTÃO ASSUMIR O VALOR DO CAMPO "DT_INCPTN" 2. SE DFLT_STTS_INSTRMNT IN (18,19,20) E MAX(NR)=1 ENTÃO ASSUMIR O VALOR DO CAMPO "FEC_DEF" 2. CASO CONTRÁRIO REF_DATE, ONDE NR = MAX(NR) | AG52: CONSULTAR DOCUMENTO BS_TABELAS_SUPORTE_PROCESSO.XLSX (BCE_LT_SPRT_DFLT) 1. CRUZAR LT002_INSTRUMENT COM A TABELA TEMPORÁRIA: UNIVERSO INSTR LEFT JOIN SELECT * FROM BCE_LT_SPRT_DFLT ON INSTRMNT_ID=INSTRMNT_ID 2. CRUZAR COM OS TRADUTORES DE CHAVES PARA IR BUSCAR O CONTRA1: LEFT JOIN ( SELECT * FROM KT_CHAVES_FINREP INNER JOIN SELECT * FROM KT_CHAVES_BDR ON CONCAT(CEMPRESA,CBALCAO,CNUMECTA,ZDEPOSIT)=CONCAT(CEMPRESA,CBALCAO,CNUMECTA,ZDEPOSIT) ) 3. CRUZAR A CHAVE OBTIDA COM A TABELA CT013_RWA_PRINC PARA OBTER O CAMPO FEC_DEF, FILTRADO POR DATA: LEFT JOIN SELECT * FROM CT013_RWA_PRINC ON CONTRA1=CONTRA1 AND S1EMP=S1EMP | AI52: 45849 | AJ52: 27/10/2021: Reunião LCM: Eliminação da regra "Se a entidade não pertencer ao universo de Capital (BCE_LT_INSTR_CAP)" na metodologia de NOT APPLICABLE: 09/11/2021: Correção de metodologia de cálculo e de cruzamento. Esta correção tem como adicional a criação da tabela de suporte BCE_LT_SPRT_DFLT (Consultar documento BS_Tabelas_Suporte_Processo.xlsx); Adicionalmente, e como consequência de uma Reunião com LCM, foi adicionada a condição: "1) Se DFLT_STTS_INSTRMNT = valor da respetiva coluna de NULLABLE, então valor da coluna NULLABLE;" de modo a prever os contratos que não estão calculados pela nova definição de default; 07/04/2022: Alteração da especificação de metodologia de cálculo do campo DT_DFLT_STTS_INSTRMNT da tabela de suporte BCE_LT_SPRT_DFLT (Consultar documento BS_Tabelas_Temporárias_v4.0.xlsx); 28/04/2022: Alteração da especificação de metodologia de cálculo do campo DT_DFLT_STTS_INSTRMNT da tabela de suporte BCE_LT_SPRT_DFLT (Consultar documento BS_Tabelas_Temporárias_v4.0.xlsx) 24/04/2025: Foi eliminada a condição: "1) Se DFLT_STTS_INSTRMNT = valor da respetiva coluna de NULLABLE, então valor da coluna NULLABLE", uma vez que o campo tem default value not allowed 11/07/2025: Após reunião com a Maria Leonor, ficou definido que este campo iria reportar a data de referência de alteração do status de default. Para os casos em que não houve alteração do status e que nunca estiveram em default reporta-se a data de inception e para os casos em que não houve alteração do status e que no histórico da ct013 estiveram sempre em default devemos reportar a data do campo fec_def. | AK52: Metodologia / Conceito: A informação de reporte de cálculo de capital é apresentada com uma granularidade distinta do universo esperado na Loan Tape para o BCE. Deste modo, são necessários tratamentos ao nível da chave de capital anteriores ao mapeamento com o universo da Loan Tape: Step 1) TMP_BCE_LT_INSTR_CAP: Tratamento da informação por chave de capital (id_capital_perimetros, s1emp, contra1) - Com o objetivo de fazer face às orientações do BCE relativamente à informação reportada, o universo de contratos da ct013_rwa_princ deve ser filtrado pelas seguintes características: (1) Universo com método de cálculo de capital Standard e IRB - subtipo_risco in (1.1; 1.2; 1.3; 1.4; 1.5; 1.6; 1.7; 1.8; 1.9; 1.13), (2) Universo reportado pelas regulações específicas da área de Capital (ex. COREP) - flag_cons_cap = 1, (3) Universo que concilia contabilisticamente - flag_conc_contab = 1 e (4) exercicio = “REAL”; - De seguida, e uma vez que o mesmo contrato de capital pode ter múltiplos registos e ser calculado em 2 métodos distintos, foram realizadas transformações para os diferentes campos de modo a obter um registo único por chave de capital (nota i); - Finalmente, para cada chave de capital, foram filtrados os id_capital_perimetros que pertencem ao perímetro em análise (através da tabela ct020_rwa_per); Step 2) BCE_LT_INSTR_CAP: Tratamento da informação por chave FINREP (chave_fr = instrmnt_id) - Foi realizado o cruzamento com os tradutores de modo a mapear a chave do Universo da Loan Tape (chave FINREP) com a de capital (obtida no Step 1); - Uma vez que uma chave FINREP pode estar relacionada com múltiplas de capital e vice-versa, foram realizadas transformações para os diferentes campos de modo a obter um registo único por chave FINREP; - Para os campos de atributos, caso um contrato de com chave de finrep esteja relacionado com múltiplas de capital deve ser escolhido o registo de acordo com as seguintes ordens de prioridade: 1º Se a chave FINREP contiver chaves de capital com FLG_IDCTOORI for 1 e 0 escolher registo onde FLG_IDCTOORI = 0; 2º Se a chave FINREP contiver chaves de capital com produtos de estruturas e diferente de estruturas (id_prod = 47) então escolher registo onde id_prod <> 47 (diferente de estruturas) 3º Se a chave FINREP contiver chaves de capital com 2 RWA_MTHD escolher registo onde RWA_MTHD = '1' (IRB) 4º (nota ii) Especificamente sobre o campo DT_DFLT_STTS_INSTRMNT (referente à data correspondente ao status de default segundo a normativa de New Default): Nota i: Sem tratamento adicional Nota ii: Caso sejam identificados mais do que 1 data de default status deve ser considerada a mais antiga. Step 3) Adicionlmente aos passos anteriores, deve ser guardada a informação das dos status de default e respetivas datas de inicio (tabela BCE_LT_SPRT_DFLT). O objetivo da criação desta tabela tem que ver com alterações aos parametros utilizados no calculo do status. Por exemplo, caso um determinado contrato tem status 18 em várias datas de referência seguidas mas com datas de entrada em default diferentes na fonte (campo FEC_DEF da tabela CT013_RWA_PRINC), deve ser mantida a 1ª data em que o mesmo entrou no status 18. (consultar sheet 9.BCE_LT_SPRT_DFLT do ficheiro BS_Tabelas_Temporárias_Loan_Tape.xlsx para mais detalhe) Notas adicionais: 1) Em âmbito do projeto do Loan Tape os campos de New Default provenientes do motor de cálculo da BDR foram adicionados à tabela CT013_RWA_PRINC no Datalake. 2) Caso o DFLT_STTS_INSTRMNT nunca tenha estado em default (14) então assumir o valor a data de origem do contrato. 3) Caso o DFLT_STTS_INSTRMNT já tenha sido default e depois voltado para "Nor in Default", então assumir a data do rácio dessa mesma alteração. Especificado/ Revisto por: Capital + CDO (Susana Arrochinho e José Carlos Epifânio + Luis Capitão-Mor). Guia de conceitos da Corporação: De acordo com o pretendido no Guia. | AL52: Campo: estIncInst Análise não realizada após atualização do campo reportado na AnaCredit. (atualização realizada no dia 02/02/2022) | AM52: OK | AN52: N | AO52: N - rever se mantemos em tabela temporária ou no DDR (processo) | AP52: New Default | AQ52: CAPITAL | AR52: Helder Gomes | AU52: 1
A53: =_xlfn.CONCAT(Table2[[#This Row],[TABLE_NAME]],Table2[[#This Row],[COLUMN_NAME]]) -> INSTRUMENTDT_END_GP_PPAL | B53: INSTRUMENT | C53: DT_END_GP_PPAL | D53: DATE | E53: N | F53: Y | G53: N | H53: N | I53: Y | J53: Y | K53: Y | L53: End date of principal grace period | M53: The latest date on which the principal payment postponement ends according to the instrument agreement. | N53: The latest date on which the principal payment postponement ends according to the instrument agreement. The scope of the field refers to any interest only period, either due to renegotiations or interest only agreements at loan inception. | O53: FALSE | P53: 0000-00-00 | Q53: 1111-11-11 | S53: IN.022 | T53: N | U53: Y | V53: Y | W53: Y | X53: Y | Y53: Y | Z53: N | AB53: CD_EMPRESTIMOS CD_ALM | AC53: EPT01_CONTAS DADOS_GERAIS_EMP | AD53: DFIMCARE EPYR8510_DFIMCARE | AE53: Emprestimos Cintra: DFIMCARE WHERE DFIMCARE IS NOT NULL AND TRIM(DFIMCARE) <> '0001-01-01' AND TRIM(DFIMCARE) <> '' Emprestimos Partenon: EPYR8510_DFIMCARE WHERE EPYR8510_DFIMCARE > EPRY8510_DFORMALI | AF53: - Se o campo DFIMCARE assumir o valor '0001-01-01' ou TRIM(DFIMCARE) = ' ' - Se o campo TYP_AMRTSTN assumir o valor 4 (bullet). - Se o contrato pertencer aos produtos identificados na tabela de parametrização: Tabela de parametrização LT803_CODIGOS_LT se VALOR_LT = 1 Onde TYP_INSTRMNT = VALOR_ORIGEM e CAMPO_LT = 'GRACE_PERIOD' | AG53: 1) Replicar passo 1) do campo DT_END_INTRST_ONLY 2) Replicar passo 2) do campo DT_END_INTRST_ONLY 3) Replicar passo 3) do campo DT_END_INTRST_ONLY 4) Replicar passo 4) do campo DT_END_INTRST_ONLY | AI53: 44806 | AJ53: 10/11/2021: Atualização da especificação da metodologia de cálculo. 16/03/2021: Atualização da especificação da metodologia de cálculo e de cruzamento para prever a informação recebida no email do dia 08/03/2022 (PRDX.LG_D90.FAM90D53.LGCONTRA apenas contem informação de moratórias de cortesia). 21/03/2021: Atualização da especificação da metodologia de cruzamento. Sem impactos a nível de implementação. 04/04/2022: Atualização da especificação da metodologia de cálculo (NOT APPLICABLE). 13/04/2022: Atualização da especificação da metodologia de cruzamento. Sem impactos a nível de implementação. 03/06/2022: Atualização da metodologia de NOT APPLICABLE (com base na indicação da Corporação). 26/08/2022: Inclusão do universo de empréstimos Partenon 02/09/2022: Atualização da metodologia de NOT APPLICABLE (inclusão de regras com base na tabela de parametrização LT803 - Inclusão de novo campo_lt) 05/07/2023: Uniformização da escrita da metodologia de NOT APPLICABLE. Sem impactos a nível de implementação. | AK53: Metodologia / Conceito: 1) Data de fim do período de carência de capital. 2) Esta informação deve ser aprovisionada apenas para os produtos de Empréstimos, Leasing e Linhas de crédito (definidos através do campo TYP_INSTRMNT) - Indicado pela Corporação por e-mail no dia 14/06/2023. 3) Está disponível em sistema apenas para as carteiras de Empréstimos. Na carteira de Leasing a informação de datas de carência é referente a moratórias e não serão utilizadas para este efeito. Especificado/ Revisto por: Empréstimos + Leasing (João Almeida + Luis Fontão + Cláudia Gomes) Guia de conceitos da Corporação: De acordo com o pretendido no Guia, a diferença entre a data de fim do período de carência e a data de fim de pagamento de apenas de juros diferem apenas para contratos com tipo de amortização bullet. | AL53: N/A | AM53: OK | AN53: N | AO53: Y | AP53: Portfolio Instrumentos | AQ53: CONTABILIDADE | AR53: Pedro Cadete | AU53: 1
A54: =_xlfn.CONCAT(Table2[[#This Row],[TABLE_NAME]],Table2[[#This Row],[COLUMN_NAME]]) -> INSTRUMENTDT_END_GP_PPAL_C19 | B54: INSTRUMENT | C54: DT_END_GP_PPAL_C19 | D54: DATE | E54: N | F54: Y | G54: Y | H54: Y | I54: Y | J54: Y | K54: Y | L54: End date of principal grace period for COVID19 related measures | M54: The date on which the principal payment postponement ends according to the instrument agreement. EBA/GL/2020/07 Guidelines on reporting and disclosure of exposures subject to measures applied in response to the COVID-19 crisis. Data attribute shall be reported if not waived by the competent authority according to points (a), (c), (d) or (e) of Article 19 of EBA/GL/2020/07 Guidelines on reporting and disclosure of exposures subject to measures applied in response to the COVID-19 crisis. | N54: The date on which the principal payment postponement ends according to the instrument agreement. EBA/GL/2020/07 Guidelines on reporting and disclosure of exposures subject to measures applied in response to the COVID-19 crisis. Data attribute shall be reported if not waived by the competent authority according to points (a), (c), (d) or (e) of Article 19 of EBA/GL/2020/07 Guidelines on reporting and disclosure of exposures subject to measures applied in response to the COVID-19 crisis. | O54: TRUE | P54: 0000-00-00 | Q54: 1111-11-11 | S54: IN.150 | T54: N | U54: N | V54: N | W54: N | X54: Y | Y54: Y | Z54: N | AB54: CD_CAPTOOLS | AC54: CT902_EBA_REPORT_CONTAB | AD54: DFIMCAR | AE54: CASE WHEN CTIPCAR = 'CAP' THEN DFIMCAR ELSE valor da coluna NOT APPLICABLE WHERE F_NEW_MONEY = '0' | AF54: - Se o contrato não pertencer ao universo COVID-19 Moratórias* *Universo COVID-19 Moratórias EBA a ser considerado: CT902_EBA_REPORT_CONTAB WHERE F_NEW_MONEY ='0' | AG54: 1) Replicar passos do campo DT_CMPLNT_MRTR_STTS_C19 | AI54: 44547 | AJ54: 04/11/21: A metodologia de cálculo mantém-se igual à versão original (não foi aplicada a metodologia proposta pela corporação). 17/12/2021: Foi reestruturado o texto da metodologia de Not Applicable, por forma a tornar mais claro o pretendido (sem impacto na implementação) 17/12/2021: Na metodologia de cruzamento foi substituido "NULL" por "valor da coluna NOT APPLICBLE" | AK54: A metodologia é a mesma entre o campo DT_END_GP_PPAL_C19 e DT_END_INTRST_ONLY_C19, uma vez que a data de fim do periodo de carência de capital é a mesma que a data de pagamento "interst only" | AL54: N/A | AP54: COVID19 | AQ54: CONTABILIDADE | AR54: Rafael Pessoa | AU54: 1
A55: =_xlfn.CONCAT(Table2[[#This Row],[TABLE_NAME]],Table2[[#This Row],[COLUMN_NAME]]) -> INSTRUMENTDT_END_INTRST_ONLY | B55: INSTRUMENT | C55: DT_END_INTRST_ONLY | D55: DATE | E55: Y | F55: Y | G55: N | H55: N | I55: Y | J55: Y | K55: Y | L55: End date of the interest-only period | M55: The date on which the interest-only period ends. Interest-only instruments are those for which, for a contractually set period, only the interest on the principal balance is paid, with the principal balance remaining unchanged. The scope of the field refers to any interest only period, either due to renegotiations or interest only agreements at loan inception. | N55: The date on which the interest-only period ends. Interest-only instruments are those for which, for a contractually set period, only the interest on the principal balance is paid, with the principal balance remaining unchanged. The scope of the field refers to any interest only period, either due to renegotiations or interest only agreements at loan inception. | O55: TRUE | P55: 0000-00-00 | Q55: 1111-11-11 | S55: IN.023 | T55: N | U55: Y | V55: Y | W55: Y | X55: Y | Y55: Y | Z55: N | AB55: CD_EMPRESTIMOS CD_ALM | AC55: EPT01_CONTAS DADOS_GERAIS_EMP | AD55: DFIMCARE EPYR8510_DFIMCARE | AE55: Emprestimos Cintra: DFIMCARE WHERE DFIMCARE IS NOT NULL AND TRIM(DFIMCARE) <> '0001-01-01' AND TRIM(DFIMCARE) <> '' Emprestimos Partenon: EPYR8510_DFIMCARE WHERE EPYR8510_DFIMCARE > EPRY8510_DFORMALI | AF55: - Se o campo DFIMCARE assumir o valor '0001-01-01' ou TRIM(DFIMCARE) = ' ' - Se o contrato pertencer aos produtos identificados na tabela de parametrização: Tabela de parametrização LT803_CODIGOS_LT se VALOR_LT = 1 Onde TYP_INSTRMNT = VALOR_ORIGEM e CAMPO_LT = 'GRACE_PERIOD' | AG55: 1) Cruzar com tradutor de chaves FINREP: LT002_INSTRUMENT LEFT JOIN (SELECT * FROM KT_CHAVES_FINREP) ON INSTRMNT_ID = CONCAT(CEMPRESA_FR, CBALCAO_FR, CNUMECTA_FR, ZDEPOSIT_FR) 2) Cruzar chave MASTER obtida no passo anterior com tabela EPT01_CONTAS para obter os campos necessários da carteira de empréstimos cintra: LEFT JOIN (SELECT * FROM EPT01_CONTAS) ON CONCAT(CBALCAO, CNUMECTA, ZDEPOSIT) = CONCAT(CKBALCAO, CKNUMCTA, '000000000000000') 3) Cruzar chave MASTER obtida no passo 1) com tabela DADOS_GERAIS_EMP para obter os campos necessários da carteira de empréstimos partenon: LEFT JOIN (SELECT * FROM DADOS_GERAIS_EMP) ON CONCAT(CBALCAO, CNUMECTA, ZDEPOSIT) = CONCAT(EPYR8510_CKBALCAO, EPYR8510_CKNUMCTA, '000000000000000') 4) Metodologia de cálculo (NOT APPLICABLE) Cruzar LT002_INSTRUMENT com tabela de paramatrização LT803_CODIGOS_LT: LEFT JOIN (SELECT * FROM LT803_CODIGOS_LT) ON TYP_INSTRMNT = VALOR_ORIGEM | AI55: 44806 | AJ55: 10/11/2021: Atualização da especificação da metodologia de cálculo. 16/03/2021: Atualização da especificação da metodologia de cálculo e de cruzamento para prever a informação recebida no email do dia 08/03/2022 (PRDX.LG_D90.FAM90D53.LGCONTRA apenas contem informação de moratórias de cortesia). 21/03/2021: Atualização da especificação da metodologia de cruzamento. Sem impactos a nível de implementação. 07/04/2022: Atualização da especificação da metodologia de cálculo (NOT APPLICABLE). 13/04/2022: Atualização da especificação da metodologia de cruzamento. Sem impactos a nível de implementação. 03/06/2022: Atualização da metodologia de NOT APPLICABLE (com base na indicação da Corporação). 01/07/2022: Atualização da metodologia de NOT APPLICABLE (inclusão de regras anteriores sobre valores nas fontes) 26/08/2022: Inclusão do universo de empréstimos Partenon 02/09/2022: Atualização da metodologia de NOT APPLICABLE (inclusão de regras com base na tabela de parametrização LT803 - Inclusão de novo campo_lt) 07/07/2023: Uniformização da escrita da metodologia de NOT APPLICABLE. Sem impactos a nível de implementação. | AK55: Metodologia / Conceito: 1) Data de fim do período de carência de capital. 2) Esta informação deve ser aprovisionada apenas para os produtos de Empréstimos, Leasing e Linhas de crédito (definidos através do campo TYP_INSTRMNT) - Indicado pela Corporação por e-mail no dia 13/06/2023. 3) Está disponível em sistema apenas para as carteiras de Empréstimos. Na carteira de Leasing a informação de datas de carência é referente a moratórias e não serão utilizadas para este efeito. Especificado/ Revisto por: Empréstimos + Leasing (João Almeida + Luis Fontão + Cláudia Gomes) Guia de conceitos da Corporação: De acordo com o pretendido no Guia, a diferença entre a data de fim do período de carência e a data de fim de pagamento de apenas de juros diferem apenas para contratos com tipo de amortização bullet. | AL55: Campo: dtFimCarJur Não está de acordo com o reportado na AnaCredit. No DDR está indicado que esta variável não será preenchida porque não existem no BST contratos com carência de juros ativos. | AM55: OK | AN55: N | AO55: Y | AP55: Portfolio Instrumentos | AQ55: CONTABILIDADE | AR55: Pedro Cadete | AU55: 1
A56: =_xlfn.CONCAT(Table2[[#This Row],[TABLE_NAME]],Table2[[#This Row],[COLUMN_NAME]]) -> INSTRUMENTDT_END_INTRST_ONLY_C19 | B56: INSTRUMENT | C56: DT_END_INTRST_ONLY_C19 | D56: DATE | E56: N | F56: Y | G56: Y | H56: Y | I56: Y | J56: Y | K56: Y | L56: End date of the interest-only period for COVID19 related measures | M56: The date on which the interest-only period ends. Interest-only instruments are those for which, for a contractually set period, only the interest on the principal balance is paid, with the principal balance remaining unchanged. EBA/GL/2020/07 Guidelines on reporting and disclosure of exposures subject to measures applied in response to the COVID-19 crisis. Data attribute shall be reported if not waived by the competent authority according to points (a), (c), (d) or (e) of Article 19 of EBA/GL/2020/07 Guidelines on reporting and disclosure of exposures subject to measures applied in response to the COVID-19 crisis. | N56: The date on which the interest-only period ends. Interest-only instruments are those for which, for a contractually set period, only the interest on the principal balance is paid, with the principal balance remaining unchanged. EBA/GL/2020/07 Guidelines on reporting and disclosure of exposures subject to measures applied in response to the COVID-19 crisis. Data attribute shall be reported if not waived by the competent authority according to points (a), (c), (d) or (e) of Article 19 of EBA/GL/2020/07 Guidelines on reporting and disclosure of exposures subject to measures applied in response to the COVID-19 crisis. | O56: TRUE | P56: 0000-00-00 | Q56: 1111-11-11 | S56: IN.151 | T56: N | U56: N | V56: N | W56: N | X56: Y | Y56: Y | Z56: N | AB56: CD_CAPTOOLS | AC56: CT902_EBA_REPORT_CONTAB | AD56: DFIMCAR | AE56: CASE WHEN CTIPCAR = 'CAP' THEN DFIMCAR ELSE valor da coluna NOT APPLICABLE WHERE F_NEW_MONEY = '0' | AF56: - Se o contrato não pertencer ao universo COVID-19 Moratórias* *Universo COVID-19 Moratórias EBA a ser considerado: CT902_EBA_REPORT_CONTAB WHERE F_NEW_MONEY ='0' | AG56: 1) Replicar passos do campo DT_CMPLNT_MRTR_STTS_C19 | AI56: 44547 | AJ56: 04/11/21: A metodologia de cálculo mantém-se igual à versão original (não foi aplicada a metodologia proposta pela corporação). 17/12/2021: Foi reestruturado o texto da metodologia de Not Applicable, por forma a tornar mais claro o pretendido (sem impacto na implementação) 17/12/2021: Na metodologia de cruzamento foi substituido "NULL" por "valor da coluna NOT APPLICBLE" | AK56: A metodologia é a mesma entre o campo DT_END_GP_PPAL_C19 e DT_END_INTRST_ONLY_C19, uma vez que a data de fim do periodo de carência de capital é a mesma que a data de pagamento "interst only" | AL56: N/A | AP56: COVID19 | AQ56: CONTABILIDADE | AR56: Rafael Pessoa | AS56: Falar com Alexandre Gonçalves (ver o que está no input_ifrs) - Interest only - Periodo de carencia do contrato - Grace period capital - Periodo que o Banco da ao devedor para ele poder postecipar (al029 - dfim_care - Luis Barata tem que tirar os 0001-01-01 - não faz sentido conceptualmente) | AU56: 1
A57: =_xlfn.CONCAT(Table2[[#This Row],[TABLE_NAME]],Table2[[#This Row],[COLUMN_NAME]]) -> INSTRUMENTDT_FRBRNC_STTS | B57: INSTRUMENT | C57: DT_FRBRNC_STTS | D57: DATE | E57: Y | F57: Y | G57: Y | H57: Y | I57: Y | J57: Y | K57: Y | L57: Date of forbearance status | M57: Date of forbearance status. If the instrument has never been subject to forbearance measure then this date would be equal to the inception date. | N57: Date of forbearance status. If the instrument has never been subject to forbearance measure then this date would be equal to the inception date. | O57: TRUE | P57: 0000-00-00 | Q57: Default value not allowed | S57: IN.024 | T57: Y | U57: Y | V57: Y | W57: Y | X57: Y | Y57: Y | Z57: N | AB57: CD_LOAN_TAPES_BCE | AC57: LT002_INSTRMNT FR004_CTO | AD57: DATA_INICIO DT_INCPTN | AE57: CASE WHEN DATA_INICIO IS NULL THEN DT_INCPTN ELSE DATA_INICIO | AG57: 1. CRUZAT A LT002_INSTRUMENT COM O KT_CHAVES_LT LT002_INSTRUMENT LEFT JOIN (SELECT * FROM KT_CHAVES_LT) ON INSTRMNT_ID=INSTRMNT_ID 2.CRUZAR A CHAVE OBTIDA COM A TABELA FR004_CTO DE MODO A OBTER O CAMPO DATA_INICIO: LT002_INSTRUMENT LEFT JOIN (SELECT * FROM FR004) ON INSTRMNT_ID = CONCAT(CEMPRESA, CBALCAO, CNUMECTA, ZDEPOSIT) | AI57: 45793 | AJ57: 04/11/2021: Foi acrescentada à metodologia de Cálculo "Se o campo FRBRNC_STTS_INSTRMNT = '8', assumir o valor do campo "DT_INCPTN""; 23/12/2021: Substituição da tabela fonte RSV133SA1_DEST_SOL_CRED pela RNT05_SOLDST e atualização do nome dos campos; 10/02/2022: Correção na metodologia de cruzamento ao nível do cruzamento de tabelas sem impacto ao nível da implementação; 21/03/2022: Atualização da especificação da metodologia de cálculo; 27/06/2022: Actualização da especificação da metodologia de cálculo (adição de NVL); 13/01/2023: Atualização da especificação da metodologia de cálculo. A tabela fonte deve ser revista aquando da ingesta 28/03/2025: Alteração da metodologia de cruzamento de forma a que o universo da LT passe a ir buscar informação diretamente à tabela FR004_CTO. 16/05/2025: Adição do cruzamento com o tradutor de chaves LT na metodologia de cruzamento. | AM57: WIP | AN57: Y | AO57: N | AP57: Reestruturados | AQ57: INFORMAÇÃO DE RISCOS | AR57: Marino Peres | AS57: (ver com IT historico > 12 meses) | AU57: 1
A58: =_xlfn.CONCAT(Table2[[#This Row],[TABLE_NAME]],Table2[[#This Row],[COLUMN_NAME]]) -> INSTRUMENTDT_FRBRNC_STTS_C19 | B58: INSTRUMENT | C58: DT_FRBRNC_STTS_C19 | D58: DATE | E58: N | F58: Y | G58: Y | H58: Y | I58: Y | J58: Y | K58: Y | L58: Date of COVID-19 related forbearance measure status | M58: The date on which the forborne status as reported in “COVID-19 related forbearance measure status” is considered to have been established or changed. EBA/GL/2020/07 Guidelines on reporting and disclosure of exposures subject to measures applied in response to the COVID-19 crisis. Data attribute shall be reported if not waived by the competent authority according to points (a), (c), (d) or (e) of Article 19 of EBA/GL/2020/07 Guidelines on reporting and disclosure of exposures subject to measures applied in response to the COVID-19 crisis | N58: The date on which the forborne status as reported in “COVID-19 related forbearance measure status” is considered to have been established or changed. EBA/GL/2020/07 Guidelines on reporting and disclosure of exposures subject to measures applied in response to the COVID-19 crisis. Data attribute shall be reported if not waived by the competent authority according to points (a), (c), (d) or (e) of Article 19 of EBA/GL/2020/07 Guidelines on reporting and disclosure of exposures subject to measures applied in response to the COVID-19 crisis | O58: TRUE | P58: 0000-00-00 | Q58: 1111-11-11 | S58: IN.147 | T58: N | U58: N | V58: N | W58: N | X58: Y | Y58: Y | Z58: N | AB58: CD_LOAN_TAPES_BCE CD_CAPTOOLS | AC58: LT002_INSTRUMENT RNT05_SOLDST | AD58: FRBRNC_STTS_C19 DFIMREC DINIREC | AE58: CASE WHEN FRBRNC_STTS_C19* = '4' THEN DFIMREC CASE WHEN FRBRNC_STTS_C19* = '2' THEN DINIREC END WHERE RNT01.CTIPSOL = '94' AND RNT05.DINIREC > '0001-01-01' AND RNT05.DANULREC = '0001-01-01' AND RNT30.CODRISCO = 'MBS' Caso sejam identificados registos duplicados na tabela RNT05, então escolher por: 1º Valor máximo de DINIREC 2º Valor máximo de ZSOLCRE *Dependente do campo FRBRNC_STTS_C19 a aprovisionar na tabela final | AF58: - Se o contrato não pertencer ao universo dos reestruturados COVID-19 (moratórias de cortesia)* *Universo dos reestruturados COVID-19 (moratórias de cortesia) a ser considerado: RNT30_MORMARCA WHERE CODRISCO ='MBS' AND RNT01_SOLCRED WHERE CTIPSOL = '94' | AG58: 1) Usar o campo FRBRNC_STTS_C19 a aprovisionar na tabela LT002_INSTRUMENT. 2) Replicar passos do campo FRBRNC_STTS_C19 | AI58: 44693 | AJ58: 02/12/2021: Atualização da especificação da metodologia de cálculo, cruzamento e not applicable. 09/12/2021: Substituição da tabela fonte RSV133SA1_DEST_SOL_CRED pela RNT05_SOLDST e atualização do nome dos campos 17/12/2021: Foi reestruturado o texto da metodologia de Not Applicable, por forma a tornar mais claro o pretendido (sem impacto na implementação) 30/03/2022: Foi alterada a metodologia de cruzamento, de forma a adicionar os tradutores de chave FINREP e MIS (com impactos na implementação) 12/05/2022: Foi adicionada uma condição na metodologia de not applicable de forma a restringir o universo de moratórias. | AK58: A tabela RNT30_MORMARCA só passou para a CD em Janeiro. No campo DT_FRBRNC_STTS_C19 está a ser reportada a data de reestruturação atual. | AL58: N/A | AP58: COVID19 | AQ58: INFORMAÇÃO DE RISCOS | AR58: Marino Peres | AS58: Reestruturados c19 Expired = Data fim Granted = Data de inicio (dinireestr) | AU58: 1
A59: =_xlfn.CONCAT(Table2[[#This Row],[TABLE_NAME]],Table2[[#This Row],[COLUMN_NAME]]) -> INSTRUMENTDT_FRBRNC_STTS_PRVS | B59: INSTRUMENT | C59: DT_FRBRNC_STTS_PRVS | D59: DATE | E59: N | F59: Y | G59: Y | H59: N | I59: Y | J59: Y | K59: Y | L59: Date of previous forbearance status | M59: This field should contain the previous value of "DT_FRBRNC_STTS" (date of the change in FRBRNC_STTS previous to the current one), i.e.: DT_FRBRNC_STTS_PRVS reflects the date of the forbearance measure preceding the one as at reference date. If only one forbearance measure was undertaken since loan origination the field should be the same as DT_FRBRNC_STTS. If the instrument has never been subject to forbearance measure then this date would be equal to the inception date. | N59: This field should contain the previous value of "DT_FRBRNC_STTS" (date of the change in FRBRNC_STTS previous to the current one), i.e.: DT_FRBRNC_STTS_PRVS reflects the date of the forbearance measure preceding the one as at reference date. If only one forbearance measure was undertaken since loan origination the field should be the same as DT_FRBRNC_STTS. If the instrument has never been subject to forbearance measure then this date would be equal to the inception date. | O59: TRUE | P59: 0000-00-00 | Q59: Default value not allowed | S59: IN.025 | T59: Y | U59: Y | V59: Y | W59: Y | X59: Y | Y59: Y | Z59: N | AB59: CD_LOAN_TAPES_BCE | AC59: BCE_LT_SPRT_FRBRNC LT002_INSTRMNT | AD59: DT_INICIO REF_DATE DT_INCPTN NMBR_FRBRNC_MSRS | AE59: CASE WHEN NMBR_FRBRNC_MSRS = 1 AND MAX (NR) = 1 THEN DT_INCPTN WHEN NMBR_FRBRNC_MSRS > 1 AND MAX (NR) = 1 THEN Valor da coluna NULLABLE ELSE NVL (CASE WHEN MAX(NR) > 2 THEN MAX (REF_DATE) ELSE MIN(DATA_INICIO), DT_INCPTN) END GROUP BY CONTRACT_ID WHERE NR-1, DT_INCPTN) | AF59: - | AG59: 1) Cruzar LT002_INSTRUMENT com tabela de suporte BCE_LT_SPRT_FRBRNC: LT002_INSTRUMENT LEFT JOIN (SELECT * FROM (SELECT MAX(NR)-1 FROM BCE_LT_SPRT_FRBRNC GROUP BY CONTRCT_ID INNER JOIN SELECT * FROM BCE_LT_SPRT_FRBRNC ON CONTRCT_ID, NR)) ON CONTRCT_ID = INSTRMNT_ID Consultar documento BS_Tabelas_Temporárias_Loan_Tape.xlsx (BCE_LT_SPRT_FRBRNC) Nota: A tabela não deve ser filtrada. | AI59: 44939 | AJ59: 23/12/2021: Substituição da tabela fonte RSV133SA1_DEST_SOL_CRED pela RNT05_SOLDST e atualização do nome dos campos 21/03/2022: Atualização da especificação da metodologia de cálculo. 27/06/2022: Actualização da especificação da metodologia de cálculo (adição de NVL) 13/01/2023: Atualização da especificação da metodologia de cálculo. A tabela fonte deve ser revista aquando da ingesta. | AL59: N/A | AM59: WIP | AN59: Y | AO59: N | AP59: Reestruturados | AQ59: INFORMAÇÃO DE RISCOS | AR59: Marino Peres | AS59: (ver com IT historico > 12 meses) | AU59: 1
A60: =_xlfn.CONCAT(Table2[[#This Row],[TABLE_NAME]],Table2[[#This Row],[COLUMN_NAME]]) -> INSTRUMENTDT_FRBRNC_STTS_PRVS_C19 | B60: INSTRUMENT | C60: DT_FRBRNC_STTS_PRVS_C19 | D60: DATE | E60: N | F60: Y | G60: Y | H60: Y | I60: Y | J60: Y | K60: Y | L60: Initial date of first COVID-19 related forbearance measure status | M60: The date on which the intial forboreance status as reported in “COVID-19 related forbearance measure status” is considered to have been established or changed. EBA/GL/2020/07 Guidelines on reporting and disclosure of exposures subject to measures applied in response to the COVID-19 crisis. Data attribute shall be reported if not waived by the competent authority according to points (a), (c), (d) or (e) of Article 19 of EBA/GL/2020/07 Guidelines on reporting and disclosure of exposures subject to measures applied in response to the COVID-19 crisis. | N60: The date on which the intial forboreance status as reported in “COVID-19 related forbearance measure status” is considered to have been established or changed. EBA/GL/2020/07 Guidelines on reporting and disclosure of exposures subject to measures applied in response to the COVID-19 crisis. Data attribute shall be reported if not waived by the competent authority according to points (a), (c), (d) or (e) of Article 19 of EBA/GL/2020/07 Guidelines on reporting and disclosure of exposures subject to measures applied in response to the COVID-19 crisis. | O60: TRUE | P60: 0000-00-00 | Q60: 1111-11-11 | S60: IN.148 | T60: N | U60: N | V60: N | W60: N | X60: Y | Y60: Y | Z60: N | AB60: CD_LOAN_TAPES_BCE CD_CAPTOOLS | AC60: LT002_INSTRUMENT RNT05_SOLDST | AD60: FRBRNC_STTS_C19 DINIREC | AE60: CASE WHEN FRBRNC_STTS_C19* = '4' THEN DINIREC CASE WHEN FRBRNC_STTS_C19* = '2' THEN valor da coluna "NULLABLE" END WHERE RNT01.CTIPSOL = '94' AND RNT05.DINIREC > '0001-01-01' AND RNT05.DANULREC = '0001-01-01' AND RNT30.CODRISCO = 'MBS' Caso sejam identificados registos duplicados na tabela RNT05, então escolher por: 1º Valor máximo de DINIREC 2º Valor máximo de ZSOLCRE *Dependente do campo FRBRNC_STTS_C19 a aprovisionar na tabela final | AF60: - Se o contrato não pertencer ao universo dos reestruturados COVID-19 (moratórias de cortesia)* *Universo dos reestruturados COVID-19 (moratórias de cortesia) a ser considerado: RNT30_MORMARCA WHERE CODRISCO ='MBS' AND RNT01_SOLCRED WHERE CTIPSOL = '94' | AG60: 1) Usar o campo FRBRNC_STTS_C19 a aprovisionar na tabela LT002_INSTRUMENT. 2) Replicar passos do campo FRBRNC_STTS_C19 | AI60: 44693 | AJ60: 02/12/2021: Atualização da especificação da metodologia de cálculo, cruzamento e not applicable. 09/12/2021: Substituição da tabela fonte RSV133SA1_DEST_SOL_CRED pela RNT05_SOLDST e atualização do nome dos campos 17/12/2021: Foi reestruturado o texto da metodologia de Not Applicable, por forma a tornar mais claro o pretendido (sem impacto na implementação) 30/03/2022: Foi alterada a metodologia de cruzamento, de forma a adicionar os tradutores de chave FINREP e MIS (com impactos na implementação) 12/05/2022: Foi adicionada uma condição na metodologia de not applicable de forma a restringir o universo de moratórias. | AK60: A tabela RNT30_MORMARCA só passou para a CD em Janeiro. | AL60: N/A | AP60: COVID19 | AQ60: INFORMAÇÃO DE RISCOS | AR60: Marino Peres | AS60: Reestruturados c19 Expired ((neste momento) = Data de inicio (dinireestr) (granted) Granted = Data do pedido (DWT1482 (contrato)- dinipedido) | AU60: 1
A61: =_xlfn.CONCAT(Table2[[#This Row],[TABLE_NAME]],Table2[[#This Row],[COLUMN_NAME]]) -> INSTRUMENTDT_IMPRMNT_STTS | B61: INSTRUMENT | C61: DT_IMPRMNT_STTS | D61: DATE | E61: Y | F61: Y | G61: Y | H61: Y | I61: Y | J61: Y | K61: Y | L61: Date of impairment status | M61: Date of entering the current impairment status. For instruments which did not change the stage classification since initial recognition, this date should be equal to inception date. Data attribute aligned with IFRS9. N-GAAP accounting banks should distinguish the status change between the recognition of General allowances (GAAP) and Specific allowances (GAAP). | N61: Date of entering the current impairment status. For instruments which did not change the stage classification since initial recognition, this date should be equal to inception date. Data attribute aligned with IFRS9. N-GAAP accounting banks should distinguish the status change between the recognition of General allowances (GAAP) and Specific allowances (GAAP). | O61: TRUE | P61: 0000-00-00 | Q61: 1111-11-11 | S61: IN.102 | T61: Y | U61: Y | V61: Y | W61: Y | X61: Y | Y61: Y | Z61: Y | AB61: CD_LOAN_TAPES_BCE | AC61: BCE_LT_SPRT_STAGE | AD61: REF_DATE | AE61: MAX (REF_DATE) Se o stage não se alterou desde a data de inception, assumir o valor do campo "DT_INCPTN" Se o "DT_IMPRMNT_STTS" for inferior à "DT_INCPTN", assumir o valor da "DT_INCPTN" | AF61: - | AG61: UNIVERSO INSTR LEFT JOIN SELECT * FROM BCE_LT_SPRT_STAGE GROUP BY CONTRACT_ID ON CONCAT(CBALCAO, CNUMECTA, ZDEPOSIT) = CONTRACT_ID | AI61: 45832 | AJ61: 08/11/21: A metodologia de Not Applicable mantém-se igual à versão original (não foi aplicada a metodologia de default values proposta pela corporação). 09/11/21: Foi corrigido o nome da tabela na metodologia de cruzamento para "BCE_LT_SPRT_STAGE" 09/09/22: Alteração na tabela de suporte temporária de forma a prever as alterações de stage/performing nas tabelas de IFRS9 (para os anos 2018 e 2019). 27/09/2024: Alteração na tabela de suporte temporária de forma a prever as alterações de stage/performing nas tabelas de IFRS9 (até Nov.22 fonte IFRS9, após Dez.22 inclusive fonte FR) 28/02/2025: Adicionada a regra de quando o DT_IMPRMNT_STTS for inferior à DT_INCPTN então o valor a assumir é o do DT_INCPTN 24/06/2025: Adição de tratamento nas tabelas de IFRS9 onde caso o STAGE esteja marcado como NULL então deve ser reportado como STAGE 3 | AK61: Metodologia / Conceito: 1) Data de entrada do STAGE atual 2) No processo da marcação do STAGE foi incluído um tratamento onde sempre que nas tabelas de imparidade apresentam STAGE a NULL então para essa data o STAGE deve ser marcado como 3. Este processo foi adicionado para acautelar contratos abatidos que nas tabelas 8_7 apresentavam registos a NULL para determinadas datas (validado em reunião com Alexandre Gonçalves) 3) Contabilidade utiliza o ficheiro IMP_CONTAB que passa os stage a null de imparidade para stage 3 Especificado/ Revisto por: Luis Capitão Mor/ Luísa Sousa Guia de conceitos da Corporação: De acordo com o pretendido no Guia. | AP61: IFRS9 | AQ61: IMPARIDADE | AR61: Alexandre Gonçalves | AT61: Foram identificados contratos com o campo Stage a NULL durante alguns periodos. Após avaliação conjunta com Alexandre Gonçalves, foi indicado que esses contratos haviam sido abatidos e posteriormente reintegrados na carteira do banco. Esses casos geravam problemas no processo de marcação de Stage, pois o sistema interpretava os registros a NULL como uma alteração de Stage. Para resolver essa situação, ficou definido na reunião de 17/06/2025 que, nas tabelas de IFRS9, sempre que existirem registos a NULL, estes devem ser considerados como Stage 3, garantindo coerência com o reportado em contabilidade. (Alteração feita por Gonçalo Filipe) | AU61: 1
A62: =_xlfn.CONCAT(Table2[[#This Row],[TABLE_NAME]],Table2[[#This Row],[COLUMN_NAME]]) -> INSTRUMENTDT_IMPRMNT_STTS_PRVS | B62: INSTRUMENT | C62: DT_IMPRMNT_STTS_PRVS | D62: DATE | E62: N | F62: Y | G62: Y | H62: N | I62: Y | J62: Y | K62: Y | L62: Date of previous impairment status | M62: Date of impairment status previous to the one at reference date. For instruments which did not change the stage classification since initial recognition, this date should be equal to inception date. Data attribute aligned with IFRS9. N-GAAP accounting banks should distinguish the status change between the recognition of General allowances (GAAP) and Specific allowances (GAAP). | N62: Date of impairment status previous to the one at reference date. For instruments which did not change the stage classification since initial recognition, this date should be equal to inception date. Data attribute aligned with IFRS9. N-GAAP accounting banks should distinguish the status change between the recognition of General allowances (GAAP) and Specific allowances (GAAP). | O62: TRUE | P62: 0000-00-00 | Q62: 1111-11-11 | S62: IN.103 | T62: Y | U62: Y | V62: Y | W62: Y | X62: Y | Y62: Y | Z62: Y | AB62: CD_LOAN_TAPES_BCE | AC62: BCE_LT_SPRT_STAGE | AD62: REF_DATE | AE62: REF_DATE Se o stage não se alterou ou teve apenas uma alteração de stage desde a data de inception, assumir o valor do campo "DT_INCPTN" Se o "DT_IMPRMNT_STTS_PRVS" for inferior à "DT_INCPTN", assumir o valor da "DT_INCPTN" | AF62: - | AG62: UNIVERSO INSTR LEFT JOIN (SELECT MAX(NR)-1 FROM BCE_LT_SPRT_STAGE GROUP BY CONTRACT_ID INNER JOIN SELECT * BCE_LT_SPRT_STAGE ON CONTRACT_ID, NR) ON CONCAT( CBALCAO, CNUMECTA, ZDEPOSIT) = CONTRACT_ID | AI62: 45832 | AJ62: 08/11/21: A metodologia de Not Applicable mantém-se igual à versão original (não foi aplicada a metodologia de default values proposta pela corporação). 09/09/22: Alteração na tabela de suporte temporária de forma a prever as alterações de stage/performing nas tabelas de IFRS9 (para os anos 2018 e 2019) 27/09/2024: Alteração na tabela de suporte temporária de forma a prever as alterações de stage/performing nas tabelas de IFRS9 (até Nov.22 fonte IFRS9, após Dez.22 inclusive fonte FR) 08/01/2025: Alteração da metodologia de cálculo para assumir o valor do campo DT_INCPTN quando o STAGE não altera ou altera apenas uma vez desde a data de inception 28/02/2025: Adicionada a regra de quando o DT_IMPRMNT_STTS_PRVS for inferior à DT_INCPTN então o valor a assumir é o do DT_INCPTN 24/06/2025: Adição de tratamento nas tabelas de IFRS9 onde caso o STAGE esteja marcado como NULL então deve ser reportado como STAGE 3 | AK62: Metodologia / Conceito: 1) Data de entrada do STAGE anterior 2) No processo da marcação do STAGE foi incluído um tratamento onde sempre que nas tabelas de imparidade apresentam STAGE a NULL então para essa data o STAGE deve ser marcado como 3. Este processo foi adicionado para acautelar contratos abatidos que nas tabelas 8_7 apresentavam registos a NULL para determinadas datas (validado em reunião com Alexandre Gonçalves) 3) Contabilidade utiliza o ficheiro IMP_CONTAB que passa os stage a null de imparidade para stage 3 Especificado/ Revisto por: Luis Capitão Mor/ Luísa Sousa Guia de conceitos da Corporação: De acordo com o pretendido no Guia. | AL62: N/A | AP62: IFRS9 | AQ62: IMPARIDADE | AR62: Alexandre Gonçalves | AT62: Foram identificados contratos com o campo Stage a NULL durante alguns periodos. Após avaliação conjunta com Alexandre Gonçalves, foi indicado que esses contratos haviam sido abatidos e posteriormente reintegrados na carteira do banco. Esses casos geravam problemas no processo de marcação de Stage, pois o sistema interpretava os registros a NULL como uma alteração de Stage. Para resolver essa situação, ficou definido na reunião de 17/06/2025 que, nas tabelas de IFRS9, sempre que existirem registos a NULL, estes devem ser considerados como Stage 3, garantindo coerência com o reportado em contabilidade. (Alteração feita por Gonçalo Filipe) | AU62: 1
A63: =_xlfn.CONCAT(Table2[[#This Row],[TABLE_NAME]],Table2[[#This Row],[COLUMN_NAME]]) -> INSTRUMENTDT_INCPTN | B63: INSTRUMENT | C63: DT_INCPTN | D63: DATE | E63: Y | F63: Y | G63: Y | H63: Y | I63: Y | J63: Y | K63: Y | L63: Date of inception | M63: The date on which the contractual relationship originated, i.e. the date on which the contract agreement becomes binding for all parties | N63: The date on which the contractual relationship originated, i.e. the date on which the contract agreement becomes binding for all parties | O63: TRUE | P63: 0000-00-00 | Q63: Default value not allowed | S63: IN.011 | T63: Y | U63: Y | V63: Y | W63: Y | X63: Y | Y63: Y | Z63: Y | AB63: CD_CAPTOOLS | AC63: FR004_CTO | AD63: DATA_ABERTURA | AE63: DATA_ABERTURA SE DATA_ABERTURA = 0001-01-01 ENTÃO VALOR DA COLUNA NULLABLE | AF63: - | AG63: 1) CRUZAR LT002_INSTRUMENT COM FR004_CTO, DE MODO A OBTER OS CAMPOS NECESSÁRIOS: LT002_INSTRUMENT LEFT JOIN (SELECT * FROM FR004_CTO) ON INSTRMNT_ID = CONCAT(CEMPRESA, CBALCAO, CNUMECTA, ZDEPOSIT) | AI63: 45771 | AJ63: 04/11/2021: A metodologia de cálculo mantém-se igual à versão original (não foi aplicada a metodologia proposta pela Corporação); 23/03/2022: Foi adicionada uma condição de Nullable para colmatar uma incidência dos controlos da Corporação 24/04/2025: Sem necessidade de re-especificação (controlos Corporativos justificados com Luís Capitão) | AK63: Metodologia / Conceito: 1) Campo deve ser reportado segundo as datas de abertura presentes no campo DATA_ABERTURA da FR004_CTO. Especificado/ Revisto por: CDO (Luis Capitão-Mor) Guia de conceitos da Corporação: Não está de acordo com o pretendido no Guia, uma vez que a data pedida no guia é relativa ao contrato e não ao instrumento. Exemplo: conta cartão vs cartão. | AP63: Portfolio Instrumentos | AQ63: PORTFOLIO MANAGER | AR63: Marino Peres | AU63: 1
A64: =_xlfn.CONCAT(Table2[[#This Row],[TABLE_NAME]],Table2[[#This Row],[COLUMN_NAME]]) -> INSTRUMENTDT_INTRNL_RTNG | B64: INSTRUMENT | C64: DT_INTRNL_RTNG | D64: DATE | E64: N | F64: Y | G64: Y | H64: Y | I64: Y | J64: Y | K64: Y | L64: Date of internal rating | M64: Date of the most recent internal rating according to Regulation (EU) No 575/2013, i.e. applicable rating as at the reference date. If the rating is assigned on entity level then provide the entity rating for all instruments. | N64: Date of the most recent internal rating according to Regulation (EU) No 575/2013, i.e. applicable rating as at the reference date. If the rating is assigned on entity level then provide the entity rating for all instruments. | O64: TRUE | P64: 0000-00-00 | Q64: 1111-11-11 | S64: IN.026 | T64: Y | U64: Y | V64: Y | W64: Y | X64: Y | Y64: Y | Z64: Y | AB64: CD_LOAN_TAPES_BCE | AC64: BCE_LT_INTRNL_RTNGS | AD64: DT_INTRNL_RTNG | AE64: CONSULTAR DOCUMENTO DE ESPECIFICAÇÃO DE INTERNAL RATINGS - CAPÍTULO LT002_INSTRUMENT: CAMPOS INTRNL_RTNG, DT_INTRNL_RTNG, RTNG_MTHD | AF64: SE O CONTRATO ESTIVER EM DEFAULT (DFLT_STTS_INSTRMNT IN (18,19,20)) | AG64: 1. CRUZAR LT002_INSTRUMENT COM TABELA TEMPORÁRIA BCE_LT_INTRNL_RTNGS, PARA O PERÍMETRO EM ANÁLISE: LT002_INSTRUMENT LEFT JOIN (SELECT * FROM BCE_LT_INTRNL_RTNGS) ON INSTRMNT_ID = INSTRMNT_ID CONSULTAR DOCUMENTO ESPECIFICAÇÃO - BCE LOAN TAPE - INTERNAL RATINGS V1.6 | AI64: 45877 | AJ64: 04/11/2021: A metodologia de cálculo mantém-se igual à versão original (não foi aplicada a metodologia proposta pela Corporação) Foi adicionada à metodologia de NOT APPLICABLE: "Se o instrumento não tem maturidade contratualizada (DATA_VENCIMENTO = 9999-31-12)"; 04/03/2022: Foi adicionada à metodologia de cálculo "Se DATA_VENCIMENTO = 0001-01-01", então valor da coluna NULLABLE 11/04/2025: Foi adicionada à metodologia de cuzamento, a metodologia de cálculo (NOT APPLICABLE) 12/05/2025: Alteração no ficheiro Especificação - BCE Loan Tape - Internal Ratings ao tratamento feito à tabela LT005_INSTR_ENT, para passar a identificar o 1º titular através do campo mn_entty_id. Para além disso, substituir a tabela LT822_INTRNL_RTNG pela tabela LT82025_INTRNL_RTNG. 16/05/2025: Adição de novas condições nas prioridades da LT002_INSTRUMENT e LT003_ENTITY, de forma a refletir os casos em que o método de apuramento de risco não é IRB, mas que a informação provém de tabelas da BDR. 08/08/2025: Adição de condição de not applicable, caso o contrato esteja em default, o campo deverá ser marcado com o respetivo valor de not applicable. | AK64: Metodologia / Conceito: A informação de reporte de cálculo de capital é apresentada com uma granularidade distinta do universo esperado na Loan Tape para o BCE. Deste modo, são necessários tratamentos ao nível da chave de capital anteriores ao mapeamento com o universo da Loan Tape: Step 1) TMP_BCE_LT_INSTR_CAP: Tratamento da informação por chave de capital (id_capital_perimetros, s1emp, contra1) - Com o objetivo de fazer face às orientações do BCE relativamente à informação reportada, o universo de contratos da ct013_rwa_princ deve ser filtrado pelas seguintes características: (1) Universo com método de cálculo de capital Standard e IRB - subtipo_risco in (1.1; 1.2; 1.3; 1.4; 1.5; 1.6; 1.7; 1.8; 1.9; 1.13), (2) Universo reportado pelas regulações específicas da área de Capital (ex. COREP) - flag_cons_cap = 1, (3) Universo que concilia contabilisticamente - flag_conc_contab = 1 e (4) exercicio = “REAL”; - De seguida, e uma vez que o mesmo contrato de capital pode ter múltiplos registos e ser calculado em 2 métodos distintos, foram realizadas transformações para os diferentes campos de modo a obter um registo único por chave de capital (nota i); - Finalmente, para cada chave de capital, foram filtrados os id_capital_perimetros que pertencem ao perímetro em análise (através da tabela ct020_rwa_per); Step 2) BCE_LT_INSTR_CAP: Tratamento da informação por chave FINREP (chave_fr = instrmnt_id) - Foi realizado o cruzamento com os tradutores de modo a mapear a chave do Universo da Loan Tape (chave FINREP) com a de capital (obtida no Step 1); - Uma vez que uma chave FINREP pode estar relacionada com múltiplas de capital e vice-versa, foram realizadas transformações para os diferentes campos de modo a obter um registo único por chave FINREP; - Para os campos de atributos, caso um contrato de com chave de finrep esteja relacionado com múltiplas de capital deve ser escolhido o registo de acordo com as seguintes ordens de prioridade: 1º Se a chave FINREP contiver chaves de capital com FLG_IDCTOORI for 1 e 0 escolher registo onde FLG_IDCTOORI = 0; 2º Se a chave FINREP contiver chaves de capital com produtos de estruturas e diferente de estruturas (id_prod = 47) então escolher registo onde id_prod <> 47 (diferente de estruturas) 3º Se a chave FINREP contiver chaves de capital com 2 RWA_MTHD escolher registo onde RWA_MTHD = '1' (IRB) 4º (nota ii) Especificamente sobre o campo DT_INTRNL_RTNG (referente data de reporte do rating interno do cliente – não estão incluídos scorings): Nota i: uma vez que o rating é calculado a nível do cliente (S1EMP e IDNUMCLI) e para excluir os scorings desta classificação, foi aplicada uma tabela de parametrização sobre o campo TIPMODEL (tabela CT021_RWA_CLI). Após filtrados os ratings, o campo FECCALI foi mapeado para cada IDNUMCLI da tabela CT013_RWA_PRINC. Nota ii: Foi calculada data do IDPUNSCO escolhido. Notas adicionais: 1) Sheet EF - Code List está mapeada a especificação da Code List interna Especificado/ Revisto por: Capital + Metodologia e Sistemas de crédito + CDO (Susana Arrochinho + Fernando Jara + Luis Capitão-Mor) Guia de conceitos da Corporação: Não está de acordo com o pretendido no Guia, uma vez que, segundo o guia, a corporação irá preencher este campo. | AL64: N/A | AN64: Y | AP64: Rating | AQ64: CAPITAL | AR64: Helder Gomes | AS64: 1. média ponderada dos LGD pela EAD ou pelo produto --- perguntar ao Elias >> Guia de conceitos explica que deve ser so pela EAD | AU64: 1
A65: =_xlfn.CONCAT(Table2[[#This Row],[TABLE_NAME]],Table2[[#This Row],[COLUMN_NAME]]) -> INSTRUMENTDT_LGL_FNL_MTRTY | B65: INSTRUMENT | C65: DT_LGL_FNL_MTRTY | D65: DATE | E65: Y | F65: Y | G65: Y | H65: Y | I65: Y | J65: Y | K65: Y | L65: Legal final maturity date (latest repayment date) | M65: The contractual maturity date of the instrument, taking into account any agreements amending initial contracts. As for retail revolving credit facilities this attribute is to be reported "not applicable". | N65: The contractual maturity date of the instrument, taking into account any agreements amending initial contracts. As for retail revolving credit facilities this attribute is to be reported "not applicable". | O65: TRUE | P65: 0000-00-00 | Q65: 1111-11-11 | S65: IN.070 | T65: Y | U65: Y | V65: Y | W65: Y | X65: Y | Y65: Y | Z65: Y | AB65: CD_LOAN_TAPES_BCE | AC65: FR004_CTO | AD65: DATA_VENCIMENTO | AE65: CAMPO APROVISIONADO DIRETAMENTE NOTA: SE DATA_VENCIMENTO = 0001-01-01, ENTÃO VALOR DA COLUNA NULLABLE | AF65: - SE O INSTRUMENTO NÃO TEM MATURIDADE CONTRATUALIZADA (DATA_VENCIMENTO = "9999-12-%") '- SE O CONTRATO PERTENCER AOS PRODUTOS DESCOBERTOS E CARTÕES: TABELA DE PARAMETRIZAÇÃO LT831_PARAM_CONCEITOS, SE VALOR_DESTINO = 'CONCEPT NOT APPLICABLE' ONDE VALOR_ORIGEM_1 = 'TYP_INSTRMNT' E CAMPO_CONCEITO = 'FINAL_MATURITY_DATE' | AG65: 1. CRUZAR LT002_INSTRUMENT COM FR004_CTO, DE MODO A OBTER O CAMPO DATA_VENCIMENTO: LT002_INSTRUMENT LEFT JOIN (SELECT * FROM FR004_CTO) ON INSTRMNT_ID = CONCAT(CEMPRESA,CBALCAO,CNUMECTA,ZDEPOSIT) 2. CRUZAR COM A TABELA LT831_PARAM_CONCEITOS PARA DEFINIR A METODOLOGIA DE CÁLCULO (NOT APPLICABLE): LEFT JOIN (SELECT * FROM LT831_PARAM_CONCEITOS) ON TYP_INSTRMNT = VALOR_ORIGEM_1 | AI65: 45758 | AJ65: 04/11/2021: A metodologia de cálculo mantém-se igual à versão original (não foi aplicada a metodologia proposta pela Corporação) Foi adicionada à metodologia de NOT APPLICABLE: "Se o instrumento não tem maturidade contratualizada (DATA_VENCIMENTO = 9999-31-12)"; 04/03/2022: Foi adicionada à metodologia de cálculo "Se DATA_VENCIMENTO = 0001-01-01", então valor da coluna NULLABLE 11/04/2025: Foi adicionada à metodologia de cuzamento, a metodologia de cálculo (NOT APPLICABLE) | AK65: Metodologia / Conceito: 1) Campo deve ser reportado segundo as datas de vencimento presentes no campo DATA_VENCIMENTO da FR004_CTO. 2) Caso o instrumento não tenha maturidade contratualizada (DATA_VENCIMENTO = 9999-31-12), então assumir valor da coluna de "NOT APPLICABLE". Especificado/ Revisto por: CDO (Luis Capitão-Mor) Guia de conceitos da Corporação: Análise não realizada. | AP65: Portfolio Instrumentos | AQ65: PORTFOLIO MANAGER | AR65: Marino Peres | AS65: Reunião com LCM 09-06-2021: Metodologia para duplicação de contratos. Escolhe-se o que tem mais variáveis preenchidas Escolher o que tem maior saldo em ALM | AU65: 1
A66: =_xlfn.CONCAT(Table2[[#This Row],[TABLE_NAME]],Table2[[#This Row],[COLUMN_NAME]]) -> INSTRUMENTDT_NXT_INTRST_RT_RST | B66: INSTRUMENT | C66: DT_NXT_INTRST_RT_RST | D66: DATE | E66: Y | F66: Y | G66: N | H66: N | I66: Y | J66: Y | K66: Y | L66: Next interest rate reset date | M66: The date when the next interest rate reset, as defined in Part 3 of Annex I to Regulation (EU) No 1071/2013 (ECB/2013/33), takes place. | N66: The date when the next interest rate reset, as defined in Part 3 of Annex I to Regulation (EU) No 1071/2013 (ECB/2013/33), takes place. | O66: TRUE | P66: 0000-00-00 | Q66: 1111-11-11 | S66: IN.071 | T66: Y | U66: Y | V66: Y | W66: Y | X66: Y | Y66: Y | Z66: Y | AB66: CD_ALM | AC66: AL029_CNT_CORE_M | AD66: DT_PROX_RENOV_TAXA_ACT | AE66: TRIM(DT_PROX_RENOV_TAXA_ACT) Se duplicações de chave do universo com chave ALM então: 1. Escolher o registo de ALM que tenha origem <> "MANUAL" 2. Escolher o registo de ALM com mais campos preenchidos 3. Escolher o registo de ALM com maior saldo: (-(MON_CAP_ST1_C0 + MON_CAP_ST1_C1 + MON_CAP_ST1_CO + MON_CAP_ST1_VIVO + MON_CAP_ST2_C0 + MON_CAP_ST2_C1 + MON_CAP_ST2_CO + MON_CAP_ST2_VIVO + MON_CAP_ST3_C0 + MON_CAP_ST3_C1 + MON_CAP_ST3_CO + MON_CAP_ST3_VIVO + MON_JUR_ST1 + MON_JUR_ST1_C0 + MON_JUR_ST1_C1 + MON_JUR_ST1_CO + MON_JUR_ST2 + MON_JUR_ST2_C0 + MON_JUR_ST2_C1 + MON_JUR_ST2_CO + MON_JUR_ST3 + MON_JUR_ST3_C0 + MON_JUR_ST3_C1 + MON_JUR_ST3_CO + MON_COMISSOES + MON_DESPESAS + MON_IMPARID_PATRI + MON_IMPARIDADE_EXTRA + MON_EXTRAPATRI)) | AF66: - Se o instrumento não tem uma data de reset da taxa de juro (DT_PROX_RENOV_TAXA_ACT = 9999-31-12) - Se o contrato pertencer aos produtos identificados na tabela de parametrização: Tabela de parametrização LT803_CODIGOS_LT se VALOR_LT = 1 Onde TYP_INSTRMNT = VALOR_ORIGEM e CAMPO_LT = 'INTRST_RT_RST_NA' | AG66: 1) Replicar passo 1) do campo INTRST_RT_RST_FRQNCY 2) Replicar passo 2) do campo INTRST_RT_RST_FRQNCY 3) Replicar passo 4) do campo INTRST_RT_RST_FRQNCY 4) Replicar passo 5) do campo INTRST_RT_RST_FRQNCY | AI66: 45135 | AJ66: 04/11/21: A metodologia de Not Applicbale mantém-se igual à versão original (não foi aplicada a metodologia de default values proposta pela corporação). 03/01/2022: Atualização da metodologia de default value para Not Aplicable. 23/03/2022: Atualização da metodologia de cálculo (Adição de TRIM) 07/07/2023: Atualização da metodologia de NOT APPLICABLE. 28/07/2023: Atualização da metodologia de NOT APPLICABLE. | AK66: Metodologia / Conceito: 1) Conceito previsto nas tabelas de ALM 2) Esta informação deve ser aprovisionada apenas para os produtos de Empréstimos, Leasing, Linhas de crédito e Debt Securities (definidos através do campo TYP_INSTRMNT) - Indicado pela Corporação por e-mail no dia 05/07/2023. 3) Metodologia a aplicar para duplicação de chaves (após cruzamento com tradutores): 3.1. Escolher o registo de ALM que tenha origem <> "MANUAL" 3.2. Escolher o registo de ALM com mais campos preenchidos 3.3. Escolher o registo de ALM com maior saldo Especificado/ Revisto por: Risco de Mercado (Cláudia Correia) Guia de conceitos da Corporação: Análise não realizada. | AP66: Portfolio Instrumentos | AQ66: RISCO DE MERCADO / ALM | AR66: Cláudia Correia | AS66: Reunião Recuperações 18/05/2021: 1. Falar com Ricardo Jorge (área Collections and recoveries) para averiguar se este campo já é apurado pela área. 2. Caso não seja, em alternativa, averiguar se é possível realizar a comparação de montantes de responsabilidades entre os 2 períodos (entrada em default e data de referência). A desvantagem na utilização desta metodologia é tal que na comparação entre períodos não são excluídos do cálculo novos incrementos de divida. | AU66: 1
