Workbook

Sheet Mapeamento
B6: 1. Mapeamento das Business Areas com as respetivas ckareas
B8: Guia Corporativo | D8: Área de Negócio | F8: Observações
B9: Code | C9: Description | D9: Código | E9: Descrição
B10: BA1 | C10: Private Banking | D10: BP | E10: =+VLOOKUP(D10,Auxiliar!$A$2:$B$88,2,FALSE) -> Private Banking
B11: BA2 | C11: Individuals | D11: BC1015 | E11: =+VLOOKUP(D11,Auxiliar!$A$2:$B$88,2,FALSE) -> Individuals
B12: BA3 | C12: Companies | D12: AN01020210 | E12: =+VLOOKUP(D12,Auxiliar!$A$2:$B$88,2,FALSE) -> Companies
B13: BA4 | C13: SMEs | D13: BC1014 | E13: =+VLOOKUP(D13,Auxiliar!$A$2:$B$88,2,FALSE) -> SMEs
B14: BA5 | C14: Institutions | D14: AN01040220 | E14: =+VLOOKUP(D14,Auxiliar!$A$2:$B$88,2,FALSE) -> Institutions
B15: BA6 | C15: Consumer | D15: FC | E15: =+VLOOKUP(D15,Auxiliar!$A$2:$B$88,2,FALSE) -> DCB
B16: BA7 | C16: M & A - Mergers and Acquisitions | D16: AN02050600 | E16: =+VLOOKUP(D16,Auxiliar!$A$2:$B$88,2,FALSE) -> M & A - Mergers and Acquisitions
B17: BA8 | C17: ECM - Equity Capital Markets | D17: GB0510 | E17: =+VLOOKUP(D17,Auxiliar!$A$2:$B$88,2,FALSE) -> ECM - Equity Capital Markets & Others | F17: A BA8 tambem poderá ser mapeeada a partir do código ckarea = AN02050500 que corresponde a ECM - Equity Capital Markets.
B18: BA9 | C18: Corporate Equity Derivatives | D18: AN02050800 | E18: =+VLOOKUP(D18,Auxiliar!$A$2:$B$88,2,FALSE) -> Corporate Equity Derivatives
B19: BA10 | C19: Project and Acquisition Finance | D19: AN02030300 | E19: =+VLOOKUP(D19,Auxiliar!$A$2:$B$88,2,FALSE) -> Project and Acquisition Finance.
B20: BA11 | C20: Syndicated loans | D20: AN02030400 | E20: =+VLOOKUP(D20,Auxiliar!$A$2:$B$88,2,FALSE) -> Syndicated Loans
B21: BA12 | C21: Debt Capital Markets - DCM | D21: AN02030200 | E21: =+VLOOKUP(D21,Auxiliar!$A$2:$B$88,2,FALSE) -> DCM
B22: BA13 | C22: ABF - Asset based finance | D22: AN02010200 | E22: =+VLOOKUP(D22,Auxiliar!$A$2:$B$88,2,FALSE) -> ABF
B23: BA14 | C23: Leveraged Finance | D23: AN02030600 | E23: =+VLOOKUP(D23,Auxiliar!$A$2:$B$88,2,FALSE) -> Leveraged Finance
B24: BA15 | C24: Cash Management | D24: AN02020100 | E24: =+VLOOKUP(D24,Auxiliar!$A$2:$B$88,2,FALSE) -> Cash Management
B25: BA16 | C25: Core Funding/ Basic financing | D25: AN02020300 | E25: =+VLOOKUP(D25,Auxiliar!$A$2:$B$88,2,FALSE) -> Financiación Básica
B26: BA17 | C26: Trade & WCS (Working Capital Solutions) | D26: AN02020200 | E26: =+VLOOKUP(D26,Auxiliar!$A$2:$B$88,2,FALSE) -> Trade & WCS
B27: BA18 | C27: Export & Agency Finance | D27: AN02020400 | E27: =+VLOOKUP(D27,Auxiliar!$A$2:$B$88,2,FALSE) -> Export & Agency Finance
B28: BA20 | C28: ACPM | D28: AN02030045 | E28: =+VLOOKUP(D28,Auxiliar!$A$2:$B$88,2,FALSE) -> ACPM
B29: BA21 | C29: Financial Management | D29: AC05 | E29: =+VLOOKUP(D29,Auxiliar!$A$2:$B$88,2,FALSE) -> Financial Management
... B39: BA31 | C39: XVA - X-Value Adjustment | D39: AN02030900 | E39: =+VLOOKUP(D39,Auxiliar!$A$2:$B$88,2,FALSE) -> XVA
C41: Deixar nota relativamente ao BA19 estar rasurado

Sheet Auxiliar
A1: Código | B1: English Description
A2: AN | B2: Total Business Area
A3: WM | B3: Wealth Management and Insurance
A4: BP | B4: Private Banking
A5: AN01010100 | B5: Private Wealth
A6: AN01050000 | B6: Private Banking Rest
A7: GA | B7: Asset Management
A8: AN03010000 | B8: Investment Funds
A9: AN03020000 | B9: Pension Funds
A10: SE | B10: Insurance
A11: AN03030000 | B11: Insurance.
A12: PIW | B12: Investment Platforms Wealth
... A88: EL | B88: Intra-Group Reassignment

Sheet Mapeamento ckarea filhos FC
B2: Guia Corporativo | D2: Área de Negócio
B3: Code | C3: Description | D3: Código | E3: Descrição | K3: Código | L3: English Description
B4: BA1 | C4: Private Banking | D4: BP | E4: =+VLOOKUP(D4,Auxiliar!$A$2:$B$88,2,FALSE) -> Private Banking | F4: AN01010100 | G4: AN01050000 | K4: AN | L4: Total Business Area | M4: =VLOOKUP(K4,$D:$D,1,FALSE) -> #N/A
B5: BA2 | C5: Individuals | D5: BC1015 | E5: =+VLOOKUP(D5,Auxiliar!$A$2:$B$88,2,FALSE) -> Individuals | K5: WM | L5: Wealth Management and Insurance | M5: =VLOOKUP(K5,$D:$D,1,FALSE) -> #N/A
B6: BA3 | C6: Companies | D6: AN01020210 | E6: =+VLOOKUP(D6,Auxiliar!$A$2:$B$88,2,FALSE) -> Companies | K6: BP | L6: Private Banking | M6: =VLOOKUP(K6,$D:$D,1,FALSE) -> BP
B7: BA4 | C7: SMEs | D7: BC1014 | E7: =+VLOOKUP(D7,Auxiliar!$A$2:$B$88,2,FALSE) -> SMEs | K7: AN01010100 | L7: Private Wealth | M7: =VLOOKUP(K7,$D:$D,1,FALSE) -> #N/A
B8: BA5 | C8: Institutions | D8: AN01040220 | E8: =+VLOOKUP(D8,Auxiliar!$A$2:$B$88,2,FALSE) -> Institutions | K8: AN01050000 | L8: Private Banking Rest | M8: =VLOOKUP(K8,$D:$D,1,FALSE) -> #N/A
B9: BA6 | C9: Consumer | D9: FC | E9: =+VLOOKUP(D9,Auxiliar!$A$2:$B$88,2,FALSE) -> DCB | K9: GA | L9: Asset Management | M9: =VLOOKUP(K9,$D:$D,1,FALSE) -> #N/A
B10: BA7 | C10: M & A - Mergers and Acquisitions | D10: AN02050600 | E10: =+VLOOKUP(D10,Auxiliar!$A$2:$B$88,2,FALSE) -> M & A - Mergers and Acquisitions | K10: AN03010000 | L10: Investment Funds | M10: =VLOOKUP(K10,$D:$D,1,FALSE) -> #N/A
B11: BA8 | C11: ECM - Equity Capital Markets | D11: GB0510 | E11: =+VLOOKUP(D11,Auxiliar!$A$2:$B$88,2,FALSE) -> ECM - Equity Capital Markets & Others | K11: AN03020000 | L11: Pension Funds | M11: =VLOOKUP(K11,$D:$D,1,FALSE) -> #N/A
B12: BA9 | C12: Corporate Equity Derivatives | D12: AN02050800 | E12: =+VLOOKUP(D12,Auxiliar!$A$2:$B$88,2,FALSE) -> Corporate Equity Derivatives | K12: SE | L12: Insurance | M12: =VLOOKUP(K12,$D:$D,1,FALSE) -> #N/A
B13: BA10 | C13: Project and Acquisition Finance | D13: AN02030300 | E13: =+VLOOKUP(D13,Auxiliar!$A$2:$B$88,2,FALSE) -> Project and Acquisition Finance. | K13: AN03030000 | L13: Insurance. | M13: =VLOOKUP(K13,$D:$D,1,FALSE) -> #N/A
B14: BA11 | C14: Syndicated loans | D14: AN02030400 | E14: =+VLOOKUP(D14,Auxiliar!$A$2:$B$88,2,FALSE) -> Syndicated Loans | K14: PIW | L14: Investment Platforms Wealth | M14: =VLOOKUP(K14,$D:$D,1,FALSE) -> #N/A
B15: BA12 | C15: Debt Capital Markets - DCM | D15: AN02030200 | E15: =+VLOOKUP(D15,Auxiliar!$A$2:$B$88,2,FALSE) -> DCM | K15: AN03040000 | L15: IPUS | M15: =VLOOKUP(K15,$D:$D,1,FALSE) -> #N/A
B16: BA13 | C16: ABF - Asset based finance | D16: AN02010200 | E16: =+VLOOKUP(D16,Auxiliar!$A$2:$B$88,2,FALSE) -> ABF | K16: AN03050000 | L16: Legacy | M16: =VLOOKUP(K16,$D:$D,1,FALSE) -> #N/A
... B33: BA31 | C33: XVA - X-Value Adjustment | D33: AN02030900 | E33: =+VLOOKUP(D33,Auxiliar!$A$2:$B$88,2,FALSE) -> XVA | K33: PYM | L33: Payments | M33: =VLOOKUP(K33,$D:$D,1,FALSE) -> #N/A
K34: CA | L34: Cards | M34: =VLOOKUP(K34,$D:$D,1,FALSE) -> #N/A
K35: CA00 | L35: Cards sum cero | M35: =VLOOKUP(K35,$D:$D,1,FALSE) -> #N/A
K36: AN07020000 | L36: Cards Load | M36: =VLOOKUP(K36,$D:$D,1,FALSE) -> #N/A
K37: AN07030000 | L37: Cards Cancel R&C | M37: =VLOOKUP(K37,$D:$D,1,FALSE) -> #N/A
K38: AN07040000 | L38: Cards Cancel DCB | M38: =VLOOKUP(K38,$D:$D,1,FALSE) -> #N/A
K39: AN07050000 | L39: Platform Cards | M39: =VLOOKUP(K39,$D:$D,1,FALSE) -> #N/A
K40: GT | L40: PagoNxt | M40: =VLOOKUP(K40,$D:$D,1,FALSE) -> #N/A
K41: AN08010000 | L41: Business Other PagoNxt | M41: =VLOOKUP(K41,$D:$D,1,FALSE) -> #N/A
K42: AN08020000 | L42: Business PagoNxt Ebury | M42: =VLOOKUP(K42,$D:$D,1,FALSE) -> #N/A
K43: AN08030000 | L43: Business PagoNxt Payment | M43: =VLOOKUP(K43,$D:$D,1,FALSE) -> #N/A
K44: AN08040000 | L44: Business PagoNxt Merchant | M44: =VLOOKUP(K44,$D:$D,1,FALSE) -> #N/A
K45: GB | L45: CIB | M45: =VLOOKUP(K45,$D:$D,1,FALSE) -> #N/A
... K90: EL | L90: Intra-Group Reassignment | M90: =VLOOKUP(K90,$D:$D,1,FALSE) -> #N/A
