Workbook

Sheet CT875
B2: campo | C2: valor_campo | D2: cnmetanseg | E2: ccentro_gestor | F2: ckmetamis | G2: cmetacom | H2: ckarea | I2: ordem | J2: ckutulmo | K2: htimest | L2: ref_date | M2: cod_visao
B3: BSNSS_AREA | C3: BA1 | D3: NULL | E3: NULL | F3: NULL | G3: NULL | H3: BP | I3: 1 | M3: 1 | N3: =VLOOKUP(H3,'CT010 & CT011'!$B:$C,2,FALSE) -> Banca Privada
B4: BSNSS_AREA | C4: BA2 | D4: NULL | E4: NULL | F4: NULL | G4: NULL | H4: BC1015 | I4: 1 | M4: 1 | N4: =VLOOKUP(H4,'CT010 & CT011'!$B:$C,2,FALSE) -> Particulares
B5: BSNSS_AREA | C5: BA3 | D5: NULL | E5: NULL | F5: NULL | G5: NULL | H5: AN01020210 | I5: 1 | M5: 1 | N5: =VLOOKUP(H5,'CT010 & CT011'!$B:$C,2,FALSE) -> Empresas
B6: BSNSS_AREA | C6: BA4 | D6: NULL | E6: NULL | F6: NULL | G6: NULL | H6: BC1014 | I6: 1 | M6: 1 | N6: =VLOOKUP(H6,'CT010 & CT011'!$B:$C,2,FALSE) -> Pymes
B7: BSNSS_AREA | C7: BA5 | D7: NULL | E7: NULL | F7: NULL | G7: NULL | H7: AN01040220 | I7: 1 | M7: 1 | N7: =VLOOKUP(H7,'CT010 & CT011'!$B:$C,2,FALSE) -> Instituciones
B8: BSNSS_AREA | C8: BA6 | D8: NULL | E8: NULL | F8: NULL | G8: NULL | H8: FC | I8: 1 | M8: 1 | N8: =VLOOKUP(H8,'CT010 & CT011'!$B:$C,2,FALSE) -> DCB
B9: BSNSS_AREA | C9: BA7 | D9: NULL | E9: NULL | F9: NULL | G9: NULL | H9: AN02050600 | I9: 2 | M9: 1 | N9: =VLOOKUP(H9,'CT010 & CT011'!$B:$C,2,FALSE) -> M & A - Mergers and Acquisitions
B10: BSNSS_AREA | C10: BA8 | D10: NULL | E10: NULL | F10: NULL | G10: NULL | H10: GB0510 | I10: 3 | M10: 1 | N10: =VLOOKUP(H10,'CT010 & CT011'!$B:$C,2,FALSE) -> ECM - Equity Capital Markets & Others
B11: BSNSS_AREA | C11: BA9 | D11: NULL | E11: NULL | F11: NULL | G11: NULL | H11: AN02050800 | I11: 4 | M11: 1 | N11: =VLOOKUP(H11,'CT010 & CT011'!$B:$C,2,FALSE) -> Corporate Equity Derivatives
B12: BSNSS_AREA | C12: BA10 | D12: NULL | E12: NULL | F12: NULL | G12: NULL | H12: AN02030300 | I12: 5 | M12: 1 | N12: =VLOOKUP(H12,'CT010 & CT011'!$B:$C,2,FALSE) -> Project and Acquisition Finance.
B13: BSNSS_AREA | C13: BA11 | D13: NULL | E13: NULL | F13: NULL | G13: NULL | H13: AN02030400 | I13: 6 | M13: 1 | N13: =VLOOKUP(H13,'CT010 & CT011'!$B:$C,2,FALSE) -> Syndicated Loans
B14: BSNSS_AREA | C14: BA12 | D14: NULL | E14: NULL | F14: NULL | G14: NULL | H14: AN02030200 | I14: 7 | M14: 1 | N14: =VLOOKUP(H14,'CT010 & CT011'!$B:$C,2,FALSE) -> DCM
... B32: BSNSS_AREA | C32: BA31 | D32: NULL | E32: NULL | F32: NULL | G32: NULL | H32: AN02030900 | I32: 25 | M32: 1 | N32: =VLOOKUP(H32,'CT010 & CT011'!$B:$C,2,FALSE) -> XVA

Sheet CT010 & CT011
B2: Informação com as novas ckareas (dados de janeiro 2025)
B4: cod_atributo_dim | C4: nome_atributo_dim | D4: desc_atributo_dim | E4: nivel_0 | F4: nivel_1 | G4: nivel_2 | H4: nivel_3 | I4: nivel_4 | J4: nivel_5 | K4: nivel_6 | L4: nivel_7 | M4: nivel_8 | N4: nivel_9 | O4: nivel_10 | P4: nivel_11 | Q4: nivel_12 | R4: ref_date | S4: id_dimensao
B5: AN | C5: Total Área de Negocio | D5: Total Business Area | E5: AN | F5: AN | G5: AN | H5: AN | I5: AN | J5: AN | K5: AN | L5: AN | M5: AN | N5: AN | O5: AN | P5: AN | Q5: AN | R5: 2025-01-31 | S5: 6
B6: AC | C6: Actividades Corporativas | D6: Corporate Activities | E6: AN | F6: AC | G6: AC | H6: AC | I6: AC | J6: AC | K6: AC | L6: AC | M6: AC | N6: AC | O6: AC | P6: AC | Q6: AC | R6: 2025-01-31 | S6: 6
B7: AC05 | C7: Gestión Financiera | D7: Financial Management | E7: AN | F7: AC | G7: AC05 | H7: AC05 | I7: AC05 | J7: AC05 | K7: AC05 | L7: AC05 | M7: AC05 | N7: AC05 | O7: AC05 | P7: AC05 | Q7: AC05 | R7: 2025-01-31 | S7: 6
B8: AN04010500 | C8: Financiación | D8: Funding | E8: AN | F8: AC | G8: AC05 | H8: AN04010500 | I8: AN04010500 | J8: AN04010500 | K8: AN04010500 | L8: AN04010500 | M8: AN04010500 | N8: AN04010500 | O8: AN04010500 | P8: AN04010500 | Q8: AN04010500 | R8: 2025-01-31 | S8: 6
B9: AN04010600 | C9: Coberturas estratégicas | D9: Strategic Hedge | E9: AN | F9: AC | G9: AC05 | H9: AN04010600 | I9: AN04010600 | J9: AN04010600 | K9: AN04010600 | L9: AN04010600 | M9: AN04010600 | N9: AN04010600 | O9: AN04010600 | P9: AN04010600 | Q9: AN04010600 | R9: 2025-01-31 | S9: 6
B10: AN04010100 | C10: ALCO | D10: ALCO | E10: AN | F10: AC | G10: AC05 | H10: AN04010100 | I10: AN04010100 | J10: AN04010100 | K10: AN04010100 | L10: AN04010100 | M10: AN04010100 | N10: AN04010100 | O10: AN04010100 | P10: AN04010100 | Q10: AN04010100 | R10: 2025-01-31 | S10: 6
B11: AN04010400 | C11: Coberturas de balance | D11: Balance Hedge | E11: AN | F11: AC | G11: AC05 | H11: AN04010400 | I11: AN04010400 | J11: AN04010400 | K11: AN04010400 | L11: AN04010400 | M11: AN04010400 | N11: AN04010400 | O11: AN04010400 | P11: AN04010400 | Q11: AN04010400 | R11: 2025-01-31 | S11: 6
B12: AN04010700 | C12: Financiación intragrupo | D12: Intragroup Funding | E12: AN | F12: AC | G12: AC05 | H12: AN04010700 | I12: AN04010700 | J12: AN04010700 | K12: AN04010700 | L12: AN04010700 | M12: AN04010700 | N12: AN04010700 | O12: AN04010700 | P12: AN04010700 | Q12: AN04010700 | R12: 2025-01-31 | S12: 6
B13: AC10 | C13: Resto | D13: Other | E13: AN | F13: AC | G13: AC10 | H13: AC10 | I13: AC10 | J13: AC10 | K13: AC10 | L13: AC10 | M13: AC10 | N13: AC10 | O13: AC10 | P13: AC10 | Q13: AC10 | R13: 2025-01-31 | S13: 6
B14: AC1010 | C14: Otros | D14: Other | E14: AN | F14: AC | G14: AC10 | H14: AC1010 | I14: AC1010 | J14: AC1010 | K14: AC1010 | L14: AC1010 | M14: AC1010 | N14: AC1010 | O14: AC1010 | P14: AC1010 | Q14: AC1010 | R14: 2025-01-31 | S14: 6
B15: AN04030000 | C15: Resto Actividades Corporativas | D15: Other Corporate Activities (Holding) | E15: AN | F15: AC | G15: AC10 | H15: AC1010 | I15: AN04030000 | J15: AN04030000 | K15: AN04030000 | L15: AN04030000 | M15: AN04030000 | N15: AN04030000 | O15: AN04030000 | P15: AN04030000 | Q15: AN04030000 | R15: 2025-01-31 | S15: 6
B16: AN04020000 | C16: Pool de Fondos | D16: Pool of Funds | E16: AN | F16: AC | G16: AC10 | H16: AN04020000 | I16: AN04020000 | J16: AN04020000 | K16: AN04020000 | L16: AN04020000 | M16: AN04020000 | N16: AN04020000 | O16: AN04020000 | P16: AN04020000 | Q16: AN04020000 | R16: 2025-01-31 | S16: 6
... B91: AN03040000 | C91: IPUS | D91: IPUS | E91: AN | F91: WM | G91: PIW | H91: AN03040000 | I91: AN03040000 | J91: AN03040000 | K91: AN03040000 | L91: AN03040000 | M91: AN03040000 | N91: AN03040000 | O91: AN03040000 | P91: AN03040000 | Q91: AN03040000 | R91: 2025-01-31 | S91: 6

Sheet Mapeamento CKAREA-BA
B2: Mapeamento BA - ckarea com a desagregação por filho
B4: BUSINESS AREA | C4: CKAREA
B5: BA1 | C5: BP | D5: AN01010100 | E5: AN01050000 | I5: =_xlfn.CONCAT("'",C5,"'",",","'",D5,"'",",","'",E5,"'") -> 'BP','AN01010100','AN01050000' | J5: =_xlfn.CONCAT("WHEN CKAREA IN (",I5,") THEN ","'",B5,"'") -> WHEN CKAREA IN ('BP','AN01010100','AN01050000') THEN 'BA1'
B6: BA2 | C6: BC1015 | D6: AN01010201 | E6: AN01010500 | I6: =_xlfn.CONCAT("'",C6,"'",",","'",D6,"'",",","'",E6,"'") -> 'BC1015','AN01010201','AN01010500' | J6: =_xlfn.CONCAT("WHEN CKAREA IN (",I6,") THEN ","'",B6,"'") -> WHEN CKAREA IN ('BC1015','AN01010201','AN01010500') THEN 'BA2'
B7: BA3 | C7: AN01020210 | I7: =_xlfn.CONCAT("'",C7,"'") -> 'AN01020210' | J7: =_xlfn.CONCAT("WHEN CKAREA IN (",I7,") THEN ","'",B7,"'") -> WHEN CKAREA IN ('AN01020210') THEN 'BA3'
B8: BA4 | C8: BC1014 | D8: AN01020410 | E8: AN01020200 | I8: =_xlfn.CONCAT("'",C8,"'",",","'",D8,"'",",","'",E8,"'") -> 'BC1014','AN01020410','AN01020200' | J8: =_xlfn.CONCAT("WHEN CKAREA IN (",I8,") THEN ","'",B8,"'") -> WHEN CKAREA IN ('BC1014','AN01020410','AN01020200') THEN 'BA4'
B9: BA5 | C9: AN01040220 | I9: =_xlfn.CONCAT("'",C9,"'") -> 'AN01040220' | J9: =_xlfn.CONCAT("WHEN CKAREA IN (",I9,") THEN ","'",B9,"'") -> WHEN CKAREA IN ('AN01040220') THEN 'BA5'
B10: BA6 | C10: FC | D10: AN06010000 | E10: AN06020000 | F10: AN06030000 | I10: =_xlfn.CONCAT("'",C10,"'",",","'",D10,"'",",","'",E10,"'",",","'",F10,"'") -> 'FC','AN06010000','AN06020000','AN06030000' | J10: =_xlfn.CONCAT("WHEN CKAREA IN (",I10,") THEN ","'",B10,"'") -> WHEN CKAREA IN ('FC','AN06010000','AN06020000','AN06030000') THEN 'BA6'
B11: BA7 | C11: AN02050600 | I11: =_xlfn.CONCAT("'",C11,"'") -> 'AN02050600' | J11: =_xlfn.CONCAT("WHEN CKAREA IN (",I11,") THEN ","'",B11,"'") -> WHEN CKAREA IN ('AN02050600') THEN 'BA7'
B12: BA8 | C12: GB0510 | D12: AN02050500 | E12: AN02050900 | I12: =_xlfn.CONCAT("'",C12,"'",",","'",D12,"'",",","'",E12,"'") -> 'GB0510','AN02050500','AN02050900' | J12: =_xlfn.CONCAT("WHEN CKAREA IN (",I12,") THEN ","'",B12,"'") -> WHEN CKAREA IN ('GB0510','AN02050500','AN02050900') THEN 'BA8'
B13: BA9 | C13: AN02050800 | I13: =_xlfn.CONCAT("'",C13,"'") -> 'AN02050800' | J13: =_xlfn.CONCAT("WHEN CKAREA IN (",I13,") THEN ","'",B13,"'") -> WHEN CKAREA IN ('AN02050800') THEN 'BA9'
B14: BA10 | C14: AN02030300 | I14: =_xlfn.CONCAT("'",C14,"'") -> 'AN02030300' | J14: =_xlfn.CONCAT("WHEN CKAREA IN (",I14,") THEN ","'",B14,"'") -> WHEN CKAREA IN ('AN02030300') THEN 'BA10'
B15: BA11 | C15: AN02030400 | I15: =_xlfn.CONCAT("'",C15,"'") -> 'AN02030400' | J15: =_xlfn.CONCAT("WHEN CKAREA IN (",I15,") THEN ","'",B15,"'") -> WHEN CKAREA IN ('AN02030400') THEN 'BA11'
B16: BA12 | C16: AN02030200 | I16: =_xlfn.CONCAT("'",C16,"'") -> 'AN02030200' | J16: =_xlfn.CONCAT("WHEN CKAREA IN (",I16,") THEN ","'",B16,"'") -> WHEN CKAREA IN ('AN02030200') THEN 'BA12'
B17: BA13 | C17: AN02010200 | I17: =_xlfn.CONCAT("'",C17,"'") -> 'AN02010200' | J17: =_xlfn.CONCAT("WHEN CKAREA IN (",I17,") THEN ","'",B17,"'") -> WHEN CKAREA IN ('AN02010200') THEN 'BA13'
B18: BA14 | C18: AN02030600 | I18: =_xlfn.CONCAT("'",C18,"'") -> 'AN02030600' | J18: =_xlfn.CONCAT("WHEN CKAREA IN (",I18,") THEN ","'",B18,"'") -> WHEN CKAREA IN ('AN02030600') THEN 'BA14'
B19: BA15 | C19: AN02020100 | I19: =_xlfn.CONCAT("'",C19,"'") -> 'AN02020100' | J19: =_xlfn.CONCAT("WHEN CKAREA IN (",I19,") THEN ","'",B19,"'") -> WHEN CKAREA IN ('AN02020100') THEN 'BA15'
B20: BA16 | C20: AN02020300 | I20: =_xlfn.CONCAT("'",C20,"'") -> 'AN02020300' | J20: =_xlfn.CONCAT("WHEN CKAREA IN (",I20,") THEN ","'",B20,"'") -> WHEN CKAREA IN ('AN02020300') THEN 'BA16'
B21: BA17 | C21: AN02020200 | I21: =_xlfn.CONCAT("'",C21,"'") -> 'AN02020200' | J21: =_xlfn.CONCAT("WHEN CKAREA IN (",I21,") THEN ","'",B21,"'") -> WHEN CKAREA IN ('AN02020200') THEN 'BA17'
B22: BA18 | C22: AN02020400 | I22: =_xlfn.CONCAT("'",C22,"'") -> 'AN02020400' | J22: =_xlfn.CONCAT("WHEN CKAREA IN (",I22,") THEN ","'",B22,"'") -> WHEN CKAREA IN ('AN02020400') THEN 'BA18'
B23: BA20 | C23: AN02030045 | I23: =_xlfn.CONCAT("'",C23,"'") -> 'AN02030045' | J23: =_xlfn.CONCAT("WHEN CKAREA IN (",I23,") THEN ","'",B23,"'") -> WHEN CKAREA IN ('AN02030045') THEN 'BA20'
B24: BA21 | C24: AC05 | D24: AN04010500 | E24: AN04010600 | F24: AN04010100 | G24: AN04010400 | H24: AN04010700 | I24: =_xlfn.CONCAT("'",C24,"'",",","'",D24,"'",",","'",E24,"'",",","'",F24,"'",",","'",G24,"'",",","'",H24,"'") -> 'AC05','AN04010500','AN04010600','AN04010100','AN04010400','AN04010700' | J24: =_xlfn.CONCAT("WHEN CKAREA IN (",I24,") THEN ","'",B24,"'") -> WHEN CKAREA IN ('AC05','AN04010500','AN04010600','AN04010100','AN04010400','AN04010700') THEN 'BA21'
B25: BA22 | C25: AN04030000 | I25: =_xlfn.CONCAT("'",C25,"'") -> 'AN04030000' | J25: =_xlfn.CONCAT("WHEN CKAREA IN (",I25,") THEN ","'",B25,"'") -> WHEN CKAREA IN ('AN04030000') THEN 'BA22'
B26: BA23 | C26: AN02040100 | I26: =_xlfn.CONCAT("'",C26,"'") -> 'AN02040100' | J26: =_xlfn.CONCAT("WHEN CKAREA IN (",I26,") THEN ","'",B26,"'") -> WHEN CKAREA IN ('AN02040100') THEN 'BA23'
B27: BA24 | C27: AN02040200 | I27: =_xlfn.CONCAT("'",C27,"'") -> 'AN02040200' | J27: =_xlfn.CONCAT("WHEN CKAREA IN (",I27,") THEN ","'",B27,"'") -> WHEN CKAREA IN ('AN02040200') THEN 'BA24'
B28: BA25 | C28: AN02040300 | I28: =_xlfn.CONCAT("'",C28,"'") -> 'AN02040300' | J28: =_xlfn.CONCAT("WHEN CKAREA IN (",I28,") THEN ","'",B28,"'") -> WHEN CKAREA IN ('AN02040300') THEN 'BA25'
B29: BA26 | C29: AN02040400 | I29: =_xlfn.CONCAT("'",C29,"'") -> 'AN02040400' | J29: =_xlfn.CONCAT("WHEN CKAREA IN (",I29,") THEN ","'",B29,"'") -> WHEN CKAREA IN ('AN02040400') THEN 'BA26'
B30: BA27 | C30: AN02040600 | I30: =_xlfn.CONCAT("'",C30,"'") -> 'AN02040600' | J30: =_xlfn.CONCAT("WHEN CKAREA IN (",I30,") THEN ","'",B30,"'") -> WHEN CKAREA IN ('AN02040600') THEN 'BA27'
B31: BA28 | C31: AN02050100 | I31: =_xlfn.CONCAT("'",C31,"'") -> 'AN02050100' | J31: =_xlfn.CONCAT("WHEN CKAREA IN (",I31,") THEN ","'",B31,"'") -> WHEN CKAREA IN ('AN02050100') THEN 'BA28'
B32: BA29 | C32: AN02040700 | I32: =_xlfn.CONCAT("'",C32,"'") -> 'AN02040700' | J32: =_xlfn.CONCAT("WHEN CKAREA IN (",I32,") THEN ","'",B32,"'") -> WHEN CKAREA IN ('AN02040700') THEN 'BA29'
B33: BA30 | C33: AN02050400 | I33: =_xlfn.CONCAT("'",C33,"'") -> 'AN02050400' | J33: =_xlfn.CONCAT("WHEN CKAREA IN (",I33,") THEN ","'",B33,"'") -> WHEN CKAREA IN ('AN02050400') THEN 'BA30'
B34: BA31 | C34: AN02030900 | I34: =_xlfn.CONCAT("'",C34,"'") -> 'AN02030900' | J34: =_xlfn.CONCAT("WHEN CKAREA IN (",I34,") THEN ","'",B34,"'") -> WHEN CKAREA IN ('AN02030900') THEN 'BA31'

Sheet Código
B2: SELECT
B3: CT010.COD_ATRIBUTO_DIM,
B4: CT010.NOME_ATRIBUTO_DIM,
B5: CT010.DESC_ATRIBUTO_DIM,
B6: CT011.NIVEL_0,
B7: CT011.NIVEL_1,
B8: CT011.NIVEL_2,
B9: CT011.NIVEL_3,
B10: CT011.NIVEL_4,
B11: CT011.NIVEL_5,
B12: CT011.NIVEL_6,
B13: CT011.NIVEL_7,
... B42: ;
