Workbook
Name _ftnref1_50: '[1]Table 39_'!#REF!
Name _ftnref1_51: '[1]Table 39_'!#REF!
Name _ftref1_50: '[1]Table 39_'!#REF!
Name Carlos: #REF!
Name DataPointIDs: #REF!
Name DataPointTooltips: #REF!
Name DBName: #REF!
Name dsa: #REF!
Name F20.04: #REF!
Name F20.04ES: #REF!
Name F20.06: #REF!
Name F20.061: #REF!
Name F20.062: #REF!
Name fdsg: '[1]Table 39_'!#REF!
Name ho: #REF!
Name JedenRadekPodSestavou: #REF!
Name JedenRadekPodSestavou_11: #REF!
Name JedenRadekPodSestavou_2: #REF!
Name JedenRadekPodSestavou_28: #REF!
Name JedenRadekVedleSestavy: #REF!
Name JedenRadekVedleSestavy_11: #REF!
Name JedenRadekVedleSestavy_2: #REF!
Name JedenRadekVedleSestavy_28: #REF!
Name MaxOblastTabulky: #REF!
Name MaxOblastTabulky_11: #REF!
Name MaxOblastTabulky_2: #REF!
Name MaxOblastTabulky_28: #REF!
Name myData: OFFSET(#REF!,0,0,MATCH("*",#REF!,-1),6)
Name myFilterSelection: #REF!
Name myPivotTable: #REF!
Name myPivotTableStart: #REF!
Name OblastDat2: #REF!
Name OblastDat2_11: #REF!
Name OblastDat2_2: #REF!
Name OblastDat2_28: #REF!
Name OblastNadpisuRadku: #REF!
Name OblastNadpisuRadku_11: #REF!
Name OblastNadpisuRadku_2: #REF!
Name OblastNadpisuRadku_28: #REF!
Name OblastNadpisuSloupcu: #REF!
Name OblastNadpisuSloupcu_11: #REF!
Name OblastNadpisuSloupcu_2: #REF!
Name OblastNadpisuSloupcu_28: #REF!
Name OLE_LINK11: 'BA_BST individual (ifrs9)'!#REF!
Name Print_Area_MI: #REF!
Name Print_Area_MI_11: #REF!
Name Print_Area_MI_2: #REF!
Name Print_Area_MI_28: #REF!
Name Print_Titles_MI: #REF!
Name Print_Titles_MI_11: #REF!
Name Print_Titles_MI_2: #REF!
Name Print_Titles_MI_28: #REF!
Name rfgf: '[1]Table 39_'!#REF!
Name Templates: #REF!

Sheet BA_BST individual (ifrs9)
AS5: BANCO SANTANDER TOTTA, S.A.
AS7: BALANÇO INDIVIDUAL EM 31 DE AGOSTO DE 2025
AS9: (Montantes expressos em Euros)
AW13: 31-08-2025 | BA13: 45535
AU14: Valor antes de
AU15: imparidade e | AW15: Imparidade | AY15: Valor | BA15: Valor | BB15: Comparação | BD15: Comparação | BF15: Comparação | BM15: Comparação
AS16: ATIVO | AU16: amortizações | AW16: e amortizações | AY16: líquido | BA16: líquido | BB16: com NCA | BD16: com NCA | BF16: com NCA | BH16: PASSIVO E CAPITAL PRÓPRIO | BJ16: 31-08-2025 | BL16: 45535 | BM16: com NCA
AQ18: 1 | AR18: 1A | AS18: Caixa e disponibilidades em bancos centrais | AU18: 2390252510 | AW18: 0 | AY18: 2390252510 | BA18: 4769740374 | BB18: 2390252510 | BD18: 0 | BF18: 2390252510
AQ19: 2 | AR19: 2A | AS19: Disponibilidades em outras instituições de crédito | AU19: 145948864 | AW19: 0 | AY19: 145948864 | BA19: 121759491 | BB19: 145948864 | BD19: 0 | BF19: 145948864 | BG19: #11311 ok igual á Luisa - Nat juridicas | BH19: Passivos financeiros detidos para negociação | BJ19: 1032943916 | BL19: 1769856402 | BM19: 1032943916 | BN19: 18
AQ20: 3 | AR20: 3A | AS20: Ativos financeiros detidos para negociação | AU20: 1025183417 | AW20: 0 | AY20: 1025183417 | BA20: 1752471502 | BB20: 1025183417 | BD20: 0 | BF20: 1025183417 | BG20: ok igual á Luisa - Nat juridicas | BH20: Passivos financeiros obrigatóriamente ao justo valor através de resultados | BJ20: 0 | BL20: 0 | BM20: 0 | BN20: 18B
AQ21: 4 | AR21: 4A | AS21: Outros ativos financeiros obrigatoriamente ao justo valor através de resultados | AU21: 1351822724 | AW21: 0 | AY21: 1351822724 | BA21: 974195873 | BB21: 1351822724 | BD21: 0 | BF21: 1351822724 | BH21: Passivos financeiros ao custo amortizado
AQ22: 4.1 | AR22: 4.1A | AS22: Ativos financeiros contabilizados pelo justo valor através dos resultados | AU22: 0 | AW22: 0 | AY22: 0 | BA22: 0 | BB22: 0 | BD22: 0 | BF22: 0 | BH22: Recursos de bancos centrais | BJ22: 0 | BL22: 0 | BM22: 0 | BN22: 19
AS23: Outros ativos financeiros ao justo valor através de outro rendimento integral | BH23: Recursos de outras instituições de crédito | BJ23: 4460030364 | BL23: 4969377880 | BM23: 4460030364 | BN23: 20
AQ24: 5 | AR24: 5A | AS24: Aplicações em instituições de crédito | AU24: 0 | AW24: 0 | AY24: 0 | BA24: 0 | BB24: 0 | BD24: 0 | BF24: 0 | BH24: Recursos de clientes e outros empréstimos | BJ24: 39318871565 | BL24: 38836200910 | BM24: 39318871565 | BN24: 21
AQ25: 5.1 | AR25: 5.1A | AS25: Instrumentos de capital | AU25: 169698614 | AW25: 0 | AY25: 169698614 | BA25: 173452663 | BB25: 169698614 | BD25: 0 | BF25: 169698614 | BH25: Responsabilidades representadas por títulos | BJ25: 6840218617 | BL25: 5201077047 | BM25: 6840218617 | BN25: 22
AQ26: 5.2 | AR26: 5.2A | AS26: Títulos de dívida | AU26: 1222852426 | AW26: 0 | AY26: 1222852426 | BA26: 1224622352 | BB26: 1222852426 | BD26: 0 | BF26: 1222852426 | BH26: Passivos financeiros associados a ativos transferidos | BJ26: 3633062456 | BL26: 2141339429 | BM26: 3633062456 | BN26: 23A
AQ27: 5.3 | AR27: 5.3A | AS27: Crédito concedido | AU27: 2364589478 | AW27: 0 | AY27: 2364589478 | BA27: 2386481110 | BB27: 2364589478 | BD27: 0 | BF27: 2364589478 | BH27: Outros passivos financeiros | BJ27: 312671155 | BL27: 234890036 | BM27: 312671155 | BN27: 23B
AQ28: 5.4 | AR28: 5.4A | AS28: Outros saldos a receber | AU28: 0 | AW28: 0 | AY28: 0 | BA28: 0 | BB28: 0 | BD28: 0 | BF28: 0 | BH28: Derivados de cobertura | BJ28: 37571213 | BL28: 16653614 | BM28: 37571213 | BN28: 24
AS29: Ativos financeiros ao custo amortizado | BH29: Correções de valor em passivos inseridos em operações de cobertura | BJ29: 0 | BL29: 0 | BM29: 0 | BN29: 25
AQ30: 6 | AR30: 6A | AS30: Aplicações em instituições de crédito | AU30: 59394085 | AW30: 145567 | AY30: 59248518 | BA30: 2895979 | BB30: 59394085 | BD30: 145567 | BF30: 59248518 | BG30: #11311 ok igual á Luisa - Nat juridicas | BH30: Provisões | BJ30: 120776624 | BL30: 114830529 | BM30: 120776624 | BN30: 26
AQ31: 6.1 | AR31: 6.1A | AS31: Títulos de dívida | AU31: 13461888846 | AW31: 4782964 | AY31: 13457105882 | BA31: 10070811828 | BB31: 13461888846 | BD31: 4782964 | BF31: 13457105882 | BH31: Passivos por impostos | BJ31: 212779714 | BL31: 419576132 | BM31: 212779714 | BN31: 27
AQ32: 7 | AR32: 7A | AS32: Crédito concedido | AU32: 37345717909 | AW32: 717087457 | AY32: 36628630452 | BA32: 34677756016 | BB32: 37345717909 | BD32: 717087457 | BF32: 36628630452 | BG32: ok igual á Luisa - Nat juridicas | BH32: Instrumentos representativos de capital reembolsáveis | BJ32: 0 | BL32: 0 | BM32: 0 | BN32: 28
AQ33: 7.1 | AR33: 7.1A | AS33: Outros saldos a receber | AU33: 482504824 | AW33: 6400170 | AY33: 476104654 | BA33: 523444450 | BB33: 482504824 | BD33: 6400170 | BF33: 476104654 | BH33: Outros passivos | BJ33: 468042601 | BL33: 539829673 | BM33: 468042601 | BN33: 29
AQ34: 8 | AR34: 8A | AS34: Investimentos detidos até à maturidade | AU34: 0 | AW34: 0 | AY34: 0 | BA34: 0 | BB34: 0 | BD34: 0 | BF34: 0 | BH34: Total do Passivo | BJ34: 56436968225 | BL34: 54243631652 | BM34: 56436968225
AQ35: 9 | AR35: 9A | AS35: Derivados de cobertura | AU35: 99620948 | AW35: 0 | AY35: 99620948 | BA35: 161633777 | BB35: 99620948 | BD35: 0 | BF35: 99620948
AQ36: 10 | AR36: 10A | AS36: Correções de valor em ativos inseridos em operações de cobertura | AU36: 0 | AW36: 0 | AY36: 0 | BA36: 0 | BB36: 0 | BD36: 0 | BF36: 0 | BH36: Capital Próprio
AQ37: 11 | AR37: 11A | AS37: Investimentos em associadas | AU37: 558558076 | AW37: 11000000 | AY37: 547558076 | BA37: 548607576 | BB37: 558558076 | BD37: 11000000 | BF37: 547558076 | BH37: Capital | BJ37: 1391779674 | BL37: 1391779674 | BM37: 1391779674 | BN37: 30
AQ38: 12 | AR38: 12A | AS38: Propriedades de investimento | AU38: 0 | AW38: 0 | AY38: 0 | BA38: 0 | BB38: 0 | BD38: 0 | BF38: 0 | BH38: Prémios de emissão | BJ38: 193389954 | BL38: 193389954 | BM38: 193389954 | BN38: 31
AQ39: 13 | AR39: 13A | AS39: Outros ativos tangíveis | AU39: 493216147 | AW39: 240466323 | AY39: 252749824 | BA39: 255604388 | BB39: 493216147 | BD39: 240466323 | BF39: 252749824 | BH39: Outros instrumentos de capital | BJ39: 1200000000 | BL39: 400000000 | BM39: 1200000000 | BN39: 32
AQ40: 14 | AR40: 14A | AS40: Ativos intangíveis | AU40: 142757281 | AW40: 103221776 | AY40: 39535505 | BA40: 31998127 | BB40: 142757281 | BD40: 103221776 | BF40: 39535505 | BH40: Reservas por rendimento integral acumulado | BJ40: -292128382 | BL40: -211938705 | BM40: -292128382 | BN40: 33
AQ41: 15 | AR41: 15A | AS41: Ativos por impostos | AU41: 110932357 | AW41: 0 | AY41: 110932357 | BA41: 131526792 | BB41: 110932357 | BD41: 0 | BF41: 110932357 | BH41: Outras reservas e resultados transitados | BJ41: 1127394251 | BL41: 1346162051 | BM41: 1127394251 | BN41: 34
AQ42: 16 | AR42: 16A | AS42: Outros ativos | AU42: 346781254 | AW42: 24567538 | AY42: 322213716 | BA42: 243676529 | BB42: 346781254 | BD42: 24567538 | BF42: 322213716 | BH42: (Ações próprias) | BJ42: -19146966 | BL42: -2239096 | BM42: -19146966 | BN42: 35
AQ43: 17 | AR43: 17A | AS43: Ativos não correntes detidos para venda | AU43: 24217238 | AW43: 9664038 | AY43: 14553200 | BA43: 30584109 | BB43: 24217238 | BD43: 9664038 | BF43: 14553200 | BH43: Resultado Individual do periodo | BJ43: 640344409 | BL43: 720477406 | BM43: 640344409
BH44: Dividendos antecipados | BJ44: 0 | BL44: 0 | BM44: 4241632940
BH45: Total Capital Próprio | BJ45: 4241632940 | BL45: 3837631284
AS46: Total do Ativo | AU46: 61795936998 | AW46: 1117335833 | AY46: 60678601165 | BA46: 58081262936 | BB46: 61795936998 | BD46: 1117335833 | BF46: 60678601165 | BH46: Total Passivo + Capital Próprio | BJ46: 60678601165 | BL46: 58081262936 | BM46: 60678601165

Sheet EMISSÕES
C1: EMISSÕES PRÓPRIAS - BST
C2: 45900
A4: EMP | B4: Conta IFRS | C4: Estrutura | D4: Conta IFRS | E4: ISIN | F4: Cód.Titulo | G4: Titulos | H4: Moeda | I4: Montante Emissão (EUR) | J4: Valor Nominal | K4: Quantidade | M4: Data Inicio Emissão | N4: Data Reembolso | O4: Taxa F/V | P4: Spread | Q4: Minimo Garantido Operação Periodo | R4: Dias total cupão | S4: Data Inicio Cupão | T4: Data Fim Cupão | U4: Taxa Cupão | V4: Dias Corridos | W4: Conta IFRS | X4: Juros Mensualizados | Y4: Acumulado Mês Anterior | Z4: Mês | AA4: Base Cálculo | AB4: Compra Carteira Propria | AC4: 45900 | AF4: 45919 | AI4: Ranking Insolvencia | AK4: Unique internal identification number | AL4: Unique identification number (known to the counterparty)
A6: 31 | B6: 251019900 | D6: 9994 | E6: PTCPP0AM0007 | G6: Acao Ordinaria Banco Santander Totta, S.A. | H6: EUR | I6: =+'BA_BST individual (ifrs9)'!BJ37+'BA_BST individual (ifrs9)'!BJ38 -> 1585169628 | J6: 1000 | K6: =+I6/J6 -> 1585169.6 | M6: 1992-01-05 | N6: 72716 | T6: 0001-01-01 | AI6: 1 | AK6: =+VLOOKUP(E6,[2]Sheet!$E:$F,2,0) -> PTCPP0AM0007000 | AL6: =+E6 -> PTCPP0AM0007 | AM6: =+AG6+I6 -> 1585169628
A7: 31 | B7: 251019900 | D7: 9994 | E7: PTBSREOM0028 | F7: 9220004322 | G7: OB.BANCO SANTANDER TOTTA SA 7.5% 06/10/2026 | H7: EUR | I7: 7599000 | J7: 1000 | K7: 7599 | M7: 42649 | N7: 46301 | O7: F | P7: 0 | Q7: 0.075 | R7: 365 | S7: 45571 | T7: 45936 | U7: 0.075 | V7: 330 | W7: 251019901 | X7: 515274.66 | Y7: 466870.07 | Z7: 48404.589 | AA7: Actual/365 | AC7: =+$AC$4-S7+1 -> 330 | AD7: =+I7*Q7*AC7/365 -> 515274.66 | AE7: =+AD7-X7 -> 0 | AF7: =+$AF$4-S7+1 -> 349 | AG7: =+I7*Q7*AF7/365 -> 544941.99 | AI7: 3 | AK7: =+VLOOKUP(E7,[2]Sheet!$E:$F,2,0) -> PTBSREOM0028000 | AL7: =+E7 -> PTBSREOM0028 | AM7: =+AG7+I7 -> 8143942
A8: 31 | B8: 251019900 | D8: 9994 | E8: PTSTOFOM0004 | F8: 9220014986 | G8: OB.OB.SANTANDER TOTTA SGPS 4.714% 2032/06/09 | H8: EUR | I8: 200000000 | J8: 100000 | K8: 2000 | M8: 44721 | N8: 48374 | O8: F | P8: 0 | Q8: 0.04714 | R8: 365 | S8: 45817 | T8: 46182 | U8: 0.04714 | V8: 84 | W8: 251019901 | X8: 2169731.5 | Y8: 1368997.3 | Z8: 800734.25 | AA8: Actual/365 | AC8: =+$AC$4-S8+1 -> 84 | AD8: =+I8*Q8*AC8/365 -> 2169731.5 | AE8: =+AD8-X8 -> 0 | AF8: =+$AF$4-S8+1 -> 103 | AG8: =+I8*Q8*AF8/365 -> 2660504.1 | AI8: 3 | AK8: =+VLOOKUP(E8,[2]Sheet!$E:$F,2,0) -> PTSTOFOM0004000 | AL8: =+E8 -> PTSTOFOM0004 | AM8: =+AG8+I8 -> 2.026605e+08
A9: 31 | B9: 251019910 | D9: 9991 | E9: PTSTOEOM0021 | F9: 9220014975 | G9: OB.SANT TOTTA SGPS 3,078% 2028/06/03 | H9: EUR | I9: 600000000 | J9: 100000 | K9: 6000 | M9: 44715 | N9: 46907 | O9: F | P9: 0 | Q9: 0.03078 | R9: 365 | S9: 45811 | T9: 46176 | U9: 0.03078 | V9: 90 | W9: 251019911 | X9: 4553753.4 | Y9: 2985238.4 | Z9: 1568515.1 | AA9: Actual/Ãctual | AC9: =+$AC$4-S9+1 -> 90 | AD9: =+I9*Q9*AC9/365 -> 4553753.4 | AE9: =+AD9-X9 -> 0 | AF9: =+$AF$4-S9+1 -> 109 | AG9: =+I9*Q9*AF9/365 -> 5515101.4 | AI9: 8 | AK9: =+VLOOKUP(E9,[2]Sheet!$E:$F,2,0) -> PTSTOEOM0021000 | AL9: =+E9 -> PTSTOEOM0021 | AM9: =+AG9+I9 -> 6.055151e+08
A10: 31 | B10: 251019910 | D10: 9991 | E10: PTSTOHOM0002 | F10: 9220017520 | G10: OB.SANTANDER TOTTA SGPS 4.063% 30/07/2030 | H10: EUR | I10: 500000000 | J10: 100000 | K10: 5000 | M10: 45503 | N10: 47694 | O10: F | P10: 0 | Q10: 0.04063 | R10: 365 | S10: 45868 | T10: 46233 | U10: 0.04063 | V10: 33 | W10: 251019911 | X10: 1836698.6 | Y10: 111315.07 | Z10: 1725383.6 | AA10: Actual/Ãctual | AC10: =+$AC$4-S10+1 -> 33 | AD10: =+I10*Q10*AC10/365 -> 1836698.6 | AE10: =+AD10-X10 -> 0 | AF10: =+$AF$4-S10+1 -> 52 | AG10: =+I10*Q10*AF10/365 -> 2894191.8 | AI10: 8 | AK10: =+VLOOKUP(E10,[2]Sheet!$E:$F,2,0) -> PTSTOHOM0002000 | AL10: =+E10 -> PTSTOHOM0002 | AM10: =+AG10+I10 -> 5.0289419e+08
A11: 31 | B11: 6205 | E11: PTSTOCOM0007 | F11: 9220014350 | G11: OB.SANTANDER TOTTA SGPS SA TIER 1 PERPETUAL | H11: EUR | I11: 400000000 | J11: 100000 | K11: 4000 | M11: 44210 | N11: 72716 | O11: V | P11: 0 | R11: 0 | T11: 0001-01-01 | U11: 0 | V11: 45901 | X11: 0 | Y11: 0 | Z11: 0 | AI11: 2 | AK11: =+VLOOKUP(E11,[2]Sheet!$E:$F,2,0) -> PTSTOCOM0007000 | AL11: =+E11 -> PTSTOCOM0007 | AM11: =+AG11+I11 -> 400000000
A12: 31 | B12: 6205 | E12: PTSTOGOM0003 | F12: 9220015021 | G12: OB.SANTANDER TOTTA SGPS SA ADIC TIER 1 PERPET | H12: EUR | I12: 300000000 | J12: 100000 | K12: 3000 | M12: 45344 | N12: 72716 | O12: V | P12: 0 | R12: 0 | T12: 0001-01-01 | U12: 0 | V12: 45901 | X12: 0 | Y12: 0 | Z12: 0 | AI12: 2 | AK12: =+VLOOKUP(E12,[2]Sheet!$E:$F,2,0) -> PTSTOGOM0003000 | AL12: =+E12 -> PTSTOGOM0003 | AM12: =+AG12+I12 -> 300000000
A13: 31 | B13: 6205 | E13: PTBSRDOM0037 | F13: 9220018358 | G13: OB.SANTANDER TOTTA/2025-EUR500M FIX RATE PERP | H13: EUR | I13: 500000000 | J13: 100000 | K13: 5000 | M13: 45806 | N13: 72716 | O13: V | P13: 0 | R13: 365 | T13: 0001-01-01 | U13: 0 | V13: 95 | X13: 0 | Y13: 0 | Z13: 0 | AI13: 2 | AK13: =+VLOOKUP(E13,[2]Sheet!$E:$F,2,0) -> PTBSRDOM0037000 | AL13: =+E13 -> PTBSRDOM0037 | AM13: =+AG13+I13 -> 500000000
AD20: =+I8+AD8 -> 2.0216973e+08
AD21: 2.038392e+08
AD22: =+AD21-AD20 -> 1669469.5

Sheet MBDT ----->
C3: MBDT ----->

Sheet B9900
A1: Name of Legal Entity | B1: LEI of Legal Entity | C1: Country of incorporation | D1: Name of the ultimate parent entity | E1: LEI of the ultimate parent entity | F1: Name of the Resolution Entity | G1: LEI of the Resolution Entity | H1: Reporting entity type | I1: Reference date | J1: Reported currency | K1: EUR exchange rate
A2: 0010 | B2: 0020 | C2: 0030 | D2: 0040 | E2: 0041 | F2: 0050 | G2: 0051 | H2: 0060 | I2: 0070 | J2: 0080 | K2: 0090
A3: Banco Santander Totta, SA | B3: 549300URJH9VSI58CS32 | C3: PT | D3: Banco Santander, S.A. | E3: 5493006QMFDDMYWIAM13 | F3: Banco Santander, S.A. | G3: 5493006QMFDDMYWIAM13 | H3: Non-Resolution Entity | I3: 45920 | J3: EUR | K3: 1
A8: String | B8: String | C8: String | D8: String | E8: String | F8: String | G8: String | H8: String | I8: Date | J8: String | K8: Numeric | M8: Data type
A9: Free text | B9: Free text | C9: ISO 3166-1 | D9: Free text | E9: Free text | F9: Free text | G9: Free text | H9: Drop-down | I9: yyyy-mm-dd hh:mm:ss | J9: 3-letters ISO 4217 | K9: 4 decimals | M9: Constrain
A11: Banco Santander Totta, SA | B11: 549300URJH9VSI58CS32 | C11: PT | D11: Banco Santander, S.A. | E11: 5493006QMFDDMYWIAM13 | F11: Banco Santander, S.A. | G11: 5493006QMFDDMYWIAM13 | H11: Non-Resolution Entity | I11: 45920 | J11: EUR | K11: 1

Sheet VALIDATIONS ----->
C3: VALIDATIONS ----->

Sheet Lists
A1: Reporting entity type | B1: Boolean | C1: Category | D1: Instrument or liability within the resolution group | E1: Nature of the liability | F1: Bail-in recognition clause | G1: Zero coupon bond | H1: Structured product | I1: Secured/Unsecured | J1: Type of the collateral | K1: Trading method | L1: Nature of the global note | M1: Counterparty Type | N1: Type of own funds | O1: Type of security interest provided by a third party | P1: Balance sheet item according to IFRS | Q1: ISDA Protocol Resolution Stay – reporting entity | R1: Recognition Resolution Stay of the counterparty | S1: Type of guarantee | T1: Type of protection value | U1: Protection valuation approach | V1: MBDT tab
A2: Resolution Entity | B2: TRUE | C2: Covered deposits (BRRD art. 44/2/a) | D2: Intragroup and intra-resolution group | E2: Registered Bond | F2: Yes, supported by Legal Opinion | G2: ZCB issued at discount | H2: Non-structured/Vanilla | I2: Secured | J2: Real estate | K2: Nominal | L2: NGN | M2: Households | N2: T2 in phase-out | O2: Lien | P2: 010 Financial liabilities held for trading | Q2: Yes - ISDA Universal Protocol | R2: Yes - ISDA Universal Protocol | S2: Issuance | T2: Notional amount | U2: Mark-to-market valuation | V2: B0200
A3: Non-Resolution Entity | B3: FALSE | C3: Secured liabilities - collateralized part (BRRD art. 44/2/b) | D3: Intragroup but not intra-resolution group | E3: Bearer Bond | F3: Yes, not supported by Legal Opinion | G3: ZCB not issued at discount | H3: Structured | I3: Unsecured | J3: Ships | K3: Unit | L3: CGN | M3: Micro & SME | N3: Grandfathered T2 | O3: Guarantee | P3: 070 Financial liabilities at fair value through profit or loss | Q3: Yes - ISDA JMP Module | R3: Yes - ISDA JMP Module | S3: Counterparty | T3: Fair value | U3: Counterparty estimation | V3: B0300
C4: Client liabilities, if protected in insolvency (BRRD art. 44/2/c) | D4: No | E4: Borrower Note Loan | F4: No | G4: No ZCB | H4: Other non-standard terms | J4: Aircraft | K4: Not applicable | L4: Not applicable | M4: Corporates | N4: Fully Compliant T2 | O4: Surety | P4: 110 Financial liabilities at amortized cost | Q4: Yes - Other | R4: Yes - Other Agreement for resolution stay recognition | S4: Unlimited | T4: Market value | U4: Creditor valuation | V4: B0400
C5: Fiduciary liabilities, if protected in insolvency (BRRD art. 44/2/d) | E5: Certificate of Deposit / Commercial paper | F5: Not applicable | G5: Aggregated | H5: Only structured coupon | J5: Financial | M5: Institutions | N5: Partially (A)T1 and T2 | O5: Guarantee obligation | P5: 280 Other liabilities | Q5: Not applicable | R5: Not applicable | S5: Other types of guarantee than issuance guarantees, counterparty guarantees and unlimited guarantees | T5: Long-term sustainable value | U5: Third party valuation | V5: B0500
C6: Institution liabilities < 7 days (BRRD art. 44/2/e) | E6: Title of ownership | F6: Aggregated | H6: Aggregated | J6: Other | M6: Other financial corporations | N6: Grandfathered AT1 | O6: Other | P6: 300 Total equity | Q6: No resolution stay recognition | R6: No resolution stay recognition | T6: Other protection value
C7: System (operator) and CCP liabilities < 7 days (BRRD art. 44/2/f) | E7: Cash account/saving account | J7: Not applicable | M7: Insurance firms & pension funds | N7: Fully Compliant AT1 | O7: Not applicable
C8: Employee liabilities (BRRD art. 44/2/g/i) | E8: Term deposit | M8: Government, central banks & supranationals | N8: CET1 | O8: Aggregated
C9: Critical service liabilities (BRRD art. 44/2/g/ii) | E9: Loan | M9: Non identified, listed on an exchange platform | N9: No
C10: Tax and social security authorities liabilities, if preferred (BRRD art. 44/2/g/iii) | E10: Bill of exchange | M10: Non identified, not listed on an exchange platform
C11: DGS liabilities (BRRD art. 44/2/g/iv) | E11: Other
C12: Liabilities towards other entities of the resolution group (BRRD art. 44/2/h)
C13: Liabilities eligible for bail-in
C14: Other equity items
C15: Title of ownership

Sheet Sheet13

Sheet B0200
A1: Row number | B1: Unique internal identification number | C1: Unique identification number (known to the counterparty) | D1: Type of the unique identifier (known to the counterparty) | E1: Original amount issued in EUR | F1: Original amount issued in foreign currency | G1: Contract currency | H1: Outstanding principal amount | I1: Portion of instrument or liability held by the reporting entity | J1: Accrued interest | K1: Applicable fees and charges | L1: Outstanding amount | N1: Relevant amount for Bail-in/WDC | O1: Nature of the liability | P1: Nature of the liability (if other) | Q1: Structurally subordinated | R1: Insolvency ranking | S1: Contractual subordination | T1: Bail-in cascade | U1: Date of issuance | V1: Date of the next interest payment | W1: Date of the next (partial) redemption payment | X1: Earliest redemption date | Y1: Legal maturity | Z1: Governing law | AA1: Bail-in recognition clause | AB1: Zero-Coupon | AC1: Structured product | AD1: Guaranteed minimum repayment amount of the structured product | AE1: Fair value of the structured product | AF1: Not covered and not preferential deposit | AG1: Not covered but preferential deposit | AH1: Covered portion of eligible deposits | AI1: Secured/Unsecured | AJ1: Amount of pledge, lien or collateral | AK1: Amount of the uncollateralized part | AL1: Internal identification number of the pledge, lien or collateral/collateral pool | AM1: Type of the collateral | AN1: Type of the collateral (if other) | AO1: Trading method | AP1: Denomination / Nominal value per security in EUR | AQ1: Denomination / Nominal value per security in original currency | AR1: Number of securities outstanding not held by the reporting entity | AS1: Number of securities outstanding held by the reporting entity | AT1: Accrued interest per security | AU1: Fees and charges per security | AV1: Fair value per security | AW1: Principal amount of the global note in EUR | AX1: Principal amount of the global note in original currency | AY1: Nature of the global note | AZ1: Current pool factor | BA1: Central securities depository | BB1: Central securities depository (LEI) | BC1: Central securities depository name (if other) | BD1: (Mandated) paying agent | BE1: (Mandated) paying agent (LEI) | BF1: Trading venue | BG1: Trading venue (LEI) | BH1: Registrar for information about creditors/holders | BI1: Registrar for information about creditors/holders (LEI) | BJ1: National Numbering Agency | BK1: National Numbering Agency (LEI) | BL1: Common Depository | BM1: Common Depository (LEI) | BN1: Common Service Provider | BO1: Common Service Provider (LEI) | BP1: Type of own funds at individual level | BQ1: Eligible amount for own funds at individual level | BR1: Type of own funds at consolidated level | BS1: Eligible amount for own funds at consolidated level | BT1: Amount of the security interest provided | BU1: Security interest provider (Name) | BV1: Security interest provider (LEI) | BW1: Type of security interest provided by a third party | BX1: Collateral for an asset position | BY1: Carrying amount IFRS | BZ1: Balance sheet item according to IFRS | CA1: Carrying amount national GAAP | CB1: Balance sheet item at Resolution entity level according to national GAAP | CC1: Instrument/liability is issued to or bought by an existing shareholder that is not part of the same resolution group | CD1: Instrument/liability meets the requirements of Art. 21(7a) SRMR
A2: 0010 | B2: 0020 | C2: 0030 | D2: 0040 | E2: 0050 | F2: 0060 | G2: 0070 | H2: 0080 | I2: 0090 | J2: 0100 | K2: 0110 | L2: 0120 | M2: 0121 | N2: 0130 | O2: 0140 | P2: 0141 | Q2: 0150 | R2: 0160 | S2: 0161 | T2: 0162 | U2: 0170 | V2: 0180 | W2: 0190 | X2: 0200 | Y2: 0210 | Z2: 0220 | AA2: 0230 | AB2: 0240 | AC2: 0250 | AD2: 0260 | AE2: 0270 | AF2: 0280 | AG2: 0290 | AH2: 0300 | AI2: 0310 | AJ2: 0320 | AK2: 0330 | AL2: 0340 | AM2: 0350 | AN2: 0351 | AO2: 0360 | AP2: 0370 | AQ2: 0380 | AR2: 0390 | AS2: 0391 | AT2: 0400 | AU2: 0410 | AV2: 0420 | AW2: 0430 | AX2: 0431 | AY2: 0440 | AZ2: 0450 | BA2: 0460 | BB2: 0461 | BC2: 0462 | BD2: 0470 | BE2: 0471 | BF2: 0480 | BG2: 0481 | BH2: 0490 | BI2: 0491 | BJ2: 0500 | BK2: 0501 | BL2: 0510 | BM2: 0511 | BN2: 0520 | BO2: 0521 | BP2: 0530 | BQ2: 0540 | BR2: 0550 | BS2: 0560 | BT2: 0570 | BU2: 0580 | BV2: 0581 | BW2: 0590 | BX2: 0600 | BY2: 0610 | BZ2: 0620 | CA2: 0630 | CB2: 0640 | CC2: 5000 | CD2: 5010
A5: Numeric | B5: String | C5: String | D5: String | E5: Numeric | F5: Numeric | G5: String | H5: Numeric | I5: Numeric | J5: Numeric | K5: Numeric | L5: Numeric | N5: Numeric | O5: String | P5: String | Q5: String | R5: Numeric | S5: Numeric | T5: String | U5: Date | V5: Date | W5: Date | X5: Date | Y5: Date | Z5: String | AA5: String | AB5: String | AC5: String | AD5: Numeric | AE5: Numeric | AF5: String | AG5: String | AH5: Numeric | AI5: String | AJ5: Numeric | AK5: Numeric | AL5: String | AM5: String | AN5: String | AO5: String | AP5: Numeric | AQ5: Numeric | AR5: Numeric | AS5: Numeric | AT5: Numeric | AU5: Numeric | AV5: Numeric | AW5: Numeric | AX5: Numeric | AY5: String | AZ5: Numeric | BA5: String | BB5: String | BC5: String | BD5: String | BE5: String | BF5: String | BG5: String | BH5: String | BI5: String | BJ5: String | BK5: String | BL5: String | BM5: String | BN5: String | BO5: String | BP5: String | BQ5: Numeric | BR5: String | BS5: Numeric | BT5: Numeric | BU5: String | BV5: String | BW5: String | BX5: String | BY5: Numeric | BZ5: String | CA5: Numeric | CB5: String | CC5: String | CD5: String
A6: Integer | B6: Free text | C6: Free text | D6: Free text, but fixed values for specific items | E6: 2 decimals | F6: 2 decimals | G6: 3-letters ISO 4217 | H6: 2 decimals | I6: 2 decimals | J6: 2 decimals | K6: 2 decimals | L6: 2 decimals | N6: 2 decimals | O6: Drop-down | P6: Free text | Q6: TRUE / FALSE boolean | R6: Integer | S6: 2 decimals | T6: Fixed values | U6: yyyy-mm-dd | V6: yyyy-mm-dd | W6: yyyy-mm-dd | X6: yyyy-mm-dd | Y6: yyyy-mm-dd | Z6: ISO 3166-1 alpha 2 / ISO 3166-2 | AA6: Drop-down | AB6: Drop-down | AC6: Drop-down | AD6: 2 decimals | AE6: 2 decimals | AF6: TRUE / FALSE boolean | AG6: TRUE / FALSE boolean | AH6: 2 decimals | AI6: Drop-down | AJ6: 2 decimals | AK6: 2 decimals | AL6: Free text | AM6: Drop-down | AN6: Free text | AO6: Drop-down | AP6: 2 decimals | AQ6: 2 decimals | AR6: Integer | AS6: Integer | AT6: 4 decimals | AU6: 4 decimals | AV6: 4 decimals | AW6: 2 decimals | AX6: 2 decimals | AY6: Drop-down | AZ6: Values between 0 and 1, with 9 decimals | BA6: Fixed values | BB6: Free text | BC6: Free text | BD6: Free text | BE6: Free text | BF6: Free text | BG6: Free text | BH6: Free text | BI6: Free text | BJ6: Free text | BK6: Free text | BL6: Free text | BM6: Free text | BN6: Free text | BO6: Free text | BP6: Drop-down | BQ6: 2 decimals | BR6: Drop-down | BS6: 2 decimals | BT6: 2 decimals | BU6: Free text | BV6: Free text | BW6: Drop-down | BX6: TRUE / FALSE boolean | BY6: 2 decimals | BZ6: Drop-down | CA6: 2 decimals | CB6: Free text | CC6: TRUE / FALSE boolean | CD6: TRUE / FALSE boolean
A8: =+A7+1 -> 1 | B8: =+EMISSÕES!AK13 -> PTBSRDOM0037000 | C8: =+EMISSÕES!AL13 -> PTBSRDOM0037 | D8: ISIN | E8: =+EMISSÕES!I13 -> 500000000 | F8: 0 | G8: EUR | H8: =+ROUND(EMISSÕES!AM13,2) -> 500000000 | I8: 0 | J8: =+ROUND(EMISSÕES!AG13,2) -> 0 | K8: 0 | L8: =+E8 -> 500000000 | M8: =H8+J8+K8 -> 500000000 | N8: =+H8 -> 500000000 | O8: Registered Bond | P8: Not applicable | Q8: =+P8 -> Not applicable | R8: =+EMISSÕES!AI13 -> 2 | S8: 999999999999999 | T8: =+R8 -> 2 | U8: =+TEXT(EMISSÕES!M13,"AAAA-MM-DD") -> 2025-05-29 | V8: =+TEXT(EMISSÕES!T13,"AAAA-MM-DD") -> 0001-01-01 | W8: =+Y8 -> 2099-01-31 | X8: =+X7 -> 0 | Y8: =+TEXT(EMISSÕES!N13,"AAAA-MM-DD") -> 2099-01-31 | Z8: PT | AA8: Yes, supported by Legal Opinion | AB8: No ZCB | AC8: Non-structured/Vanilla | AD8: 999999999999999 | AE8: 999999999999999 | AF8: FALSE | AG8: FALSE | AH8: 999999999999999 | AI8: Unsecured | AJ8: 999999999999999 | AK8: 999999999999999 | AL8: Not applicable | AM8: Not applicable | AN8: Not applicable | AO8: Nominal | AP8: =+EMISSÕES!I13 -> 500000000 | AQ8: =+EMISSÕES!I13/EMISSÕES!J13 -> 5000 | AR8: =+ROUND(EMISSÕES!J13,0) -> 100000 | AS8: =+AR8 -> 100000 | AT8: =+ROUND(EMISSÕES!AG13,4) -> 0 | AU8: 0 | AV8: 999999999999999 | AW8: 999999999999999 | AX8: 999999999999999 | AY8: Not applicable | AZ8: -9999.999999999 | BA8: INTERBOLSA_PT | BB8: 529900LG70TCAGWCXT47 | BC8: Not applicable | BD8: Not applicable | BE8: Not applicable | BF8: Not applicable | BG8: Not applicable | BH8: Not applicable | BI8: Not applicable | BJ8: =+BA8 -> INTERBOLSA_PT | BK8: =+BB8 -> 529900LG70TCAGWCXT47 | BL8: Not applicable | BM8: Not applicable | BN8: Not applicable | BO8: Not applicable | BP8: Fully Compliant AT1 | BQ8: =+E8+J8 -> 500000000 | BR8: Not applicable | BS8: 999999999999999 | BT8: =+ROUND(0,2) -> 0 | BU8: Not applicable | BV8: Not applicable | BW8: Not applicable | BX8: Not applicable | BY8: =+H8-I8 -> 500000000 | BZ8: 110 Financial liabilities at amortized cost | CA8: =+BY8 -> 500000000 | CB8: 110 Financial liabilities at amortized cost | CC8: FALSE | CD8: TRUE
A9: =+A8+1 -> 2 | B9: =+EMISSÕES!AK7 -> PTBSREOM0028000 | C9: =+EMISSÕES!AL7 -> PTBSREOM0028 | D9: ISIN | E9: =+EMISSÕES!I7 -> 7599000 | F9: 0 | G9: EUR | H9: =+ROUND(EMISSÕES!AM7,2) -> 8143942 | I9: 0 | J9: =+ROUND(EMISSÕES!AG7,2) -> 544941.99 | K9: 0 | L9: =+E9 -> 7599000 | M9: =H9+J9+K9 -> 8688884 | N9: =+H9 -> 8143942 | O9: Registered Bond | P9: Not applicable | Q9: =+P9 -> Not applicable | R9: =+EMISSÕES!AI7 -> 3 | S9: 999999999999999 | T9: =+R9 -> 3 | U9: =+TEXT(EMISSÕES!M7,"AAAA-MM-DD") -> 2016-10-06 | V9: =+TEXT(EMISSÕES!T7,"AAAA-MM-DD") -> 2025-10-06 | W9: =+Y9 -> 2026-10-06 | X9: =+X8 -> 0 | Y9: =+TEXT(EMISSÕES!N7,"AAAA-MM-DD") -> 2026-10-06 | Z9: PT | AA9: Yes, supported by Legal Opinion | AB9: No ZCB | AC9: Non-structured/Vanilla | AD9: 999999999999999 | AE9: 999999999999999 | AF9: FALSE | AG9: FALSE | AH9: 999999999999999 | AI9: Unsecured | AJ9: 999999999999999 | AK9: 999999999999999 | AL9: Not applicable | AM9: Not applicable | AN9: Not applicable | AO9: Nominal | AP9: =+EMISSÕES!I7 -> 7599000 | AQ9: =+EMISSÕES!I7/EMISSÕES!J7 -> 7599 | AR9: =+ROUND(EMISSÕES!J7,0) -> 1000 | AS9: =+AR9 -> 1000 | AT9: =+ROUND(EMISSÕES!AG7,4) -> 544941.99 | AU9: 0 | AV9: 999999999999999 | AW9: 999999999999999 | AX9: 999999999999999 | AY9: Not applicable | AZ9: -9999.999999999 | BA9: INTERBOLSA_PT | BB9: 529900LG70TCAGWCXT47 | BC9: Not applicable | BD9: Not applicable | BE9: Not applicable | BF9: Not applicable | BG9: Not applicable | BH9: Not applicable | BI9: Not applicable | BJ9: =+BA9 -> INTERBOLSA_PT | BK9: =+BB9 -> 529900LG70TCAGWCXT47 | BL9: Not applicable | BM9: Not applicable | BN9: Not applicable | BO9: Not applicable | BP9: T2 in phase-out | BQ9: 1669469.5 | BR9: Not applicable | BS9: 999999999999999 | BT9: =+ROUND(0,2) -> 0 | BU9: Not applicable | BV9: Not applicable | BW9: Not applicable | BX9: Not applicable | BY9: =+H9-I9 -> 8143942 | BZ9: 110 Financial liabilities at amortized cost | CA9: =+BY9 -> 8143942 | CB9: 110 Financial liabilities at amortized cost | CC9: FALSE | CD9: TRUE
A10: 1 | B10: =+EMISSÕES!AK6 -> PTCPP0AM0007000 | C10: =+EMISSÕES!AL6 -> PTCPP0AM0007 | D10: ISIN | E10: =+EMISSÕES!I6 -> 1585169628 | F10: 0 | G10: EUR | H10: =+ROUND(EMISSÕES!AM6,2) -> 1585169628 | I10: =-'BA_BST individual (ifrs9)'!BJ42 -> 19146966 | J10: =+ROUND(EMISSÕES!AG6,2) -> 0 | K10: 0 | L10: =+E10 -> 1585169628 | M10: =H10+J10+K10 -> 1585169628 | N10: =+H10 -> 1585169628 | O10: Title of ownership | P10: Not applicable | Q10: =+P10 -> Not applicable | R10: =+EMISSÕES!AI6 -> 1 | S10: 999999999999999 | T10: =+R10 -> 1 | U10: =+TEXT(EMISSÕES!M6,"AAAA-MM-DD") -> 1992-01-05 | V10: =+TEXT(EMISSÕES!T6,"AAAA-MM-DD") -> 0001-01-01 | W10: =+Y10 -> 2099-01-31 | X10: =+V10 -> 0001-01-01 | Y10: =+TEXT(EMISSÕES!N6,"AAAA-MM-DD") -> 2099-01-31 | Z10: PT | AA10: Yes, supported by Legal Opinion | AB10: No ZCB | AC10: Non-structured/Vanilla | AD10: 999999999999999 | AE10: 999999999999999 | AF10: FALSE | AG10: FALSE | AH10: 999999999999999 | AI10: Unsecured | AJ10: 999999999999999 | AK10: 999999999999999 | AL10: Not applicable | AM10: Not applicable | AN10: Not applicable | AO10: Nominal | AP10: =+EMISSÕES!I6 -> 1585169628 | AQ10: =+EMISSÕES!I6/EMISSÕES!J6 -> 1585169.6 | AR10: =+ROUND(EMISSÕES!J6,0) -> 1000 | AS10: =+AR10 -> 1000 | AT10: =+ROUND(EMISSÕES!AG6,4) -> 0 | AU10: 0 | AV10: 999999999999999 | AW10: 999999999999999 | AX10: 999999999999999 | AY10: Not applicable | AZ10: -9999.999999999 | BA10: INTERBOLSA_PT | BB10: 529900LG70TCAGWCXT47 | BC10: Not applicable | BD10: Not applicable | BE10: Not applicable | BF10: Not applicable | BG10: Not applicable | BH10: Not applicable | BI10: Not applicable | BJ10: =+BA10 -> INTERBOLSA_PT | BK10: =+BB10 -> 529900LG70TCAGWCXT47 | BL10: Not applicable | BM10: Not applicable | BN10: Not applicable | BO10: Not applicable | BP10: CET1 | BQ10: =+E10-I10 -> 1566022662 | BR10: Not applicable | BS10: 999999999999999 | BT10: =+ROUND(0,2) -> 0 | BU10: Not applicable | BV10: Not applicable | BW10: Not applicable | BX10: Not applicable | BY10: =+H10-I10 -> 1566022662 | BZ10: 300 Total equity | CA10: =+BY10 -> 1566022662 | CB10: 300 Total equity | CC10: FALSE | CD10: TRUE
A11: =+A10+1 -> 2 | B11: =+EMISSÕES!AK11 -> PTSTOCOM0007000 | C11: =+EMISSÕES!AL11 -> PTSTOCOM0007 | D11: ISIN | E11: =+EMISSÕES!I11 -> 400000000 | F11: 0 | G11: EUR | H11: =+ROUND(EMISSÕES!AM11,2) -> 400000000 | I11: 0 | J11: =+ROUND(EMISSÕES!AG11,2) -> 0 | K11: 0 | L11: =+E11 -> 400000000 | M11: =H11+J11+K11 -> 400000000 | N11: =+H11 -> 400000000 | O11: Registered Bond | P11: Not applicable | Q11: =+P11 -> Not applicable | R11: =+EMISSÕES!AI11 -> 2 | S11: 999999999999999 | T11: =+R11 -> 2 | U11: =+TEXT(EMISSÕES!M11,"AAAA-MM-DD") -> 2021-01-14 | V11: =+TEXT(EMISSÕES!T11,"AAAA-MM-DD") -> 0001-01-01 | W11: =+Y11 -> 2099-01-31 | X11: =+X10 -> 0001-01-01 | Y11: =+TEXT(EMISSÕES!N11,"AAAA-MM-DD") -> 2099-01-31 | Z11: PT | AA11: Yes, supported by Legal Opinion | AB11: No ZCB | AC11: Non-structured/Vanilla | AD11: 999999999999999 | AE11: 999999999999999 | AF11: FALSE | AG11: FALSE | AH11: 999999999999999 | AI11: Unsecured | AJ11: 999999999999999 | AK11: 999999999999999 | AL11: Not applicable | AM11: Not applicable | AN11: Not applicable | AO11: Nominal | AP11: =+EMISSÕES!I11 -> 400000000 | AQ11: =+EMISSÕES!I11/EMISSÕES!J11 -> 4000 | AR11: =+ROUND(EMISSÕES!J11,0) -> 100000 | AS11: =+AR11 -> 100000 | AT11: =+ROUND(EMISSÕES!AG11,4) -> 0 | AU11: 0 | AV11: 999999999999999 | AW11: 999999999999999 | AX11: 999999999999999 | AY11: Not applicable | AZ11: -9999.999999999 | BA11: INTERBOLSA_PT | BB11: 529900LG70TCAGWCXT47 | BC11: Not applicable | BD11: Not applicable | BE11: Not applicable | BF11: Not applicable | BG11: Not applicable | BH11: Not applicable | BI11: Not applicable | BJ11: =+BA11 -> INTERBOLSA_PT | BK11: =+BB11 -> 529900LG70TCAGWCXT47 | BL11: Not applicable | BM11: Not applicable | BN11: Not applicable | BO11: Not applicable | BP11: Fully Compliant AT1 | BQ11: =+E11+J11 -> 400000000 | BR11: Not applicable | BS11: 999999999999999 | BT11: =+ROUND(0,2) -> 0 | BU11: Not applicable | BV11: Not applicable | BW11: Not applicable | BX11: Not applicable | BY11: =+H11-I11 -> 400000000 | BZ11: 110 Financial liabilities at amortized cost | CA11: =+BY11 -> 400000000 | CB11: 110 Financial liabilities at amortized cost | CC11: FALSE | CD11: TRUE
A12: =+A11+1 -> 3 | B12: =+EMISSÕES!AK9 -> PTSTOEOM0021000 | C12: =+EMISSÕES!AL9 -> PTSTOEOM0021 | D12: ISIN | E12: =+EMISSÕES!I9 -> 600000000 | F12: 0 | G12: EUR | H12: =+ROUND(EMISSÕES!AM9,2) -> 6.055151e+08 | I12: 0 | J12: =+ROUND(EMISSÕES!AG9,2) -> 5515101.4 | K12: 0 | L12: =+E12 -> 600000000 | M12: =H12+J12+K12 -> 6.110302e+08 | N12: =+H12 -> 6.055151e+08 | O12: Registered Bond | P12: Not applicable | Q12: =+P12 -> Not applicable | R12: =+EMISSÕES!AI9 -> 8 | S12: 999999999999999 | T12: =+R12 -> 8 | U12: =+TEXT(EMISSÕES!M9,"AAAA-MM-DD") -> 2022-06-03 | V12: =+TEXT(EMISSÕES!T9,"AAAA-MM-DD") -> 2026-06-03 | W12: =+Y12 -> 2028-06-03 | X12: =+X11 -> 0001-01-01 | Y12: =+TEXT(EMISSÕES!N9,"AAAA-MM-DD") -> 2028-06-03 | Z12: PT | AA12: Yes, supported by Legal Opinion | AB12: No ZCB | AC12: Non-structured/Vanilla | AD12: 999999999999999 | AE12: 999999999999999 | AF12: FALSE | AG12: FALSE | AH12: 999999999999999 | AI12: Unsecured | AJ12: 999999999999999 | AK12: 999999999999999 | AL12: Not applicable | AM12: Not applicable | AN12: Not applicable | AO12: Nominal | AP12: =+EMISSÕES!I9 -> 600000000 | AQ12: =+EMISSÕES!I9/EMISSÕES!J9 -> 6000 | AR12: =+ROUND(EMISSÕES!J9,0) -> 100000 | AS12: =+AR12 -> 100000 | AT12: =+ROUND(EMISSÕES!AG9,4) -> 5515101.4 | AU12: 0 | AV12: 999999999999999 | AW12: 999999999999999 | AX12: 999999999999999 | AY12: Not applicable | AZ12: -9999.999999999 | BA12: INTERBOLSA_PT | BB12: 529900LG70TCAGWCXT47 | BC12: Not applicable | BD12: Not applicable | BE12: Not applicable | BF12: Not applicable | BG12: Not applicable | BH12: Not applicable | BI12: Not applicable | BJ12: =+BA12 -> INTERBOLSA_PT | BK12: =+BB12 -> 529900LG70TCAGWCXT47 | BL12: Not applicable | BM12: Not applicable | BN12: Not applicable | BO12: Not applicable | BP12: No | BQ12: =+E12+J12 -> 6.055151e+08 | BR12: Not applicable | BS12: 999999999999999 | BT12: =+ROUND(0,2) -> 0 | BU12: Not applicable | BV12: Not applicable | BW12: Not applicable | BX12: Not applicable | BY12: =+H12-I12 -> 6.055151e+08 | BZ12: 110 Financial liabilities at amortized cost | CA12: =+BY12 -> 6.055151e+08 | CB12: 110 Financial liabilities at amortized cost | CC12: FALSE | CD12: TRUE
A13: =+A12+1 -> 4 | B13: =+EMISSÕES!AK8 -> PTSTOFOM0004000 | C13: =+EMISSÕES!AL8 -> PTSTOFOM0004 | D13: ISIN | E13: =+EMISSÕES!I8 -> 200000000 | F13: 0 | G13: EUR | H13: =+ROUND(EMISSÕES!AM8,2) -> 2.026605e+08 | I13: 0 | J13: =+ROUND(EMISSÕES!AG8,2) -> 2660504.1 | K13: 0 | L13: =+E13 -> 200000000 | M13: =H13+J13+K13 -> 2.0532101e+08 | N13: =+H13 -> 2.026605e+08 | O13: Registered Bond | P13: Not applicable | Q13: =+P13 -> Not applicable | R13: =+EMISSÕES!AI8 -> 3 | S13: 999999999999999 | T13: =+R13 -> 3 | U13: =+TEXT(EMISSÕES!M8,"AAAA-MM-DD") -> 2022-06-09 | V13: =+TEXT(EMISSÕES!T8,"AAAA-MM-DD") -> 2026-06-09 | W13: =+Y13 -> 2032-06-09 | X13: =+X12 -> 0001-01-01 | Y13: =+TEXT(EMISSÕES!N8,"AAAA-MM-DD") -> 2032-06-09 | Z13: PT | AA13: Yes, supported by Legal Opinion | AB13: No ZCB | AC13: Non-structured/Vanilla | AD13: 999999999999999 | AE13: 999999999999999 | AF13: FALSE | AG13: FALSE | AH13: 999999999999999 | AI13: Unsecured | AJ13: 999999999999999 | AK13: 999999999999999 | AL13: Not applicable | AM13: Not applicable | AN13: Not applicable | AO13: Nominal | AP13: =+EMISSÕES!I8 -> 200000000 | AQ13: =+EMISSÕES!I8/EMISSÕES!J8 -> 2000 | AR13: =+ROUND(EMISSÕES!J8,0) -> 100000 | AS13: =+AR13 -> 100000 | AT13: =+ROUND(EMISSÕES!AG8,4) -> 2660504.1 | AU13: 0 | AV13: 999999999999999 | AW13: 999999999999999 | AX13: 999999999999999 | AY13: Not applicable | AZ13: -9999.999999999 | BA13: INTERBOLSA_PT | BB13: 529900LG70TCAGWCXT47 | BC13: Not applicable | BD13: Not applicable | BE13: Not applicable | BF13: Not applicable | BG13: Not applicable | BH13: Not applicable | BI13: Not applicable | BJ13: =+BA13 -> INTERBOLSA_PT | BK13: =+BB13 -> 529900LG70TCAGWCXT47 | BL13: Not applicable | BM13: Not applicable | BN13: Not applicable | BO13: Not applicable | BP13: Fully Compliant T2 | BQ13: =+E13+J13 -> 2.026605e+08 | BR13: Not applicable | BS13: 999999999999999 | BT13: =+ROUND(0,2) -> 0 | BU13: Not applicable | BV13: Not applicable | BW13: Not applicable | BX13: Not applicable | BY13: =+H13-I13 -> 2.026605e+08 | BZ13: 110 Financial liabilities at amortized cost | CA13: =+BY13 -> 2.026605e+08 | CB13: 110 Financial liabilities at amortized cost | CC13: FALSE | CD13: TRUE
A14: =+A13+1 -> 5 | B14: =+EMISSÕES!AK12 -> PTSTOGOM0003000 | C14: =+EMISSÕES!AL12 -> PTSTOGOM0003 | D14: ISIN | E14: =+EMISSÕES!I12 -> 300000000 | F14: 0 | G14: EUR | H14: =+ROUND(EMISSÕES!AM12,2) -> 300000000 | I14: 0 | J14: =+ROUND(EMISSÕES!AG12,2) -> 0 | K14: 0 | L14: =+E14 -> 300000000 | M14: =H14+J14+K14 -> 300000000 | N14: =+H14 -> 300000000 | O14: Registered Bond | P14: Not applicable | Q14: =+P14 -> Not applicable | R14: =+EMISSÕES!AI12 -> 2 | S14: 999999999999999 | T14: =+R14 -> 2 | U14: =+TEXT(EMISSÕES!M12,"AAAA-MM-DD") -> 2024-02-22 | V14: =+TEXT(EMISSÕES!T12,"AAAA-MM-DD") -> 0001-01-01 | W14: =+Y14 -> 2099-01-31 | X14: =+X13 -> 0001-01-01 | Y14: =+TEXT(EMISSÕES!N12,"AAAA-MM-DD") -> 2099-01-31 | Z14: PT | AA14: Yes, supported by Legal Opinion | AB14: No ZCB | AC14: Non-structured/Vanilla | AD14: 999999999999999 | AE14: 999999999999999 | AF14: FALSE | AG14: FALSE | AH14: 999999999999999 | AI14: Unsecured | AJ14: 999999999999999 | AK14: 999999999999999 | AL14: Not applicable | AM14: Not applicable | AN14: Not applicable | AO14: Nominal | AP14: =+EMISSÕES!I12 -> 300000000 | AQ14: =+EMISSÕES!I12/EMISSÕES!J12 -> 3000 | AR14: =+ROUND(EMISSÕES!J12,0) -> 100000 | AS14: =+AR14 -> 100000 | AT14: =+ROUND(EMISSÕES!AG12,4) -> 0 | AU14: 0 | AV14: 999999999999999 | AW14: 999999999999999 | AX14: 999999999999999 | AY14: Not applicable | AZ14: -9999.999999999 | BA14: INTERBOLSA_PT | BB14: 529900LG70TCAGWCXT47 | BC14: Not applicable | BD14: Not applicable | BE14: Not applicable | BF14: Not applicable | BG14: Not applicable | BH14: Not applicable | BI14: Not applicable | BJ14: =+BA14 -> INTERBOLSA_PT | BK14: =+BB14 -> 529900LG70TCAGWCXT47 | BL14: Not applicable | BM14: Not applicable | BN14: Not applicable | BO14: Not applicable | BP14: Fully Compliant AT1 | BQ14: =+E14+J14 -> 300000000 | BR14: Not applicable | BS14: 999999999999999 | BT14: =+ROUND(0,2) -> 0 | BU14: Not applicable | BV14: Not applicable | BW14: Not applicable | BX14: Not applicable | BY14: =+H14-I14 -> 300000000 | BZ14: 110 Financial liabilities at amortized cost | CA14: =+BY14 -> 300000000 | CB14: 110 Financial liabilities at amortized cost | CC14: FALSE | CD14: TRUE
A15: =+A14+1 -> 6 | B15: =+EMISSÕES!AK10 -> PTSTOHOM0002000 | C15: =+EMISSÕES!AL10 -> PTSTOHOM0002 | D15: ISIN | E15: =+EMISSÕES!I10 -> 500000000 | F15: 0 | G15: EUR | H15: =+ROUND(EMISSÕES!AM10,2) -> 5.0289419e+08 | I15: 0 | J15: =+ROUND(EMISSÕES!AG10,2) -> 2894191.8 | K15: 0 | L15: =+E15 -> 500000000 | M15: =H15+J15+K15 -> 5.0578838e+08 | N15: =+H15 -> 5.0289419e+08 | O15: Registered Bond | P15: Not applicable | Q15: =+P15 -> Not applicable | R15: =+EMISSÕES!AI10 -> 8 | S15: 999999999999999 | T15: =+R15 -> 8 | U15: =+TEXT(EMISSÕES!M10,"AAAA-MM-DD") -> 2024-07-30 | V15: =+TEXT(EMISSÕES!T10,"AAAA-MM-DD") -> 2026-07-30 | W15: =+Y15 -> 2030-07-30 | X15: =+X14 -> 0001-01-01 | Y15: =+TEXT(EMISSÕES!N10,"AAAA-MM-DD") -> 2030-07-30 | Z15: PT | AA15: Yes, supported by Legal Opinion | AB15: No ZCB | AC15: Non-structured/Vanilla | AD15: 999999999999999 | AE15: 999999999999999 | AF15: FALSE | AG15: FALSE | AH15: 999999999999999 | AI15: Unsecured | AJ15: 999999999999999 | AK15: 999999999999999 | AL15: Not applicable | AM15: Not applicable | AN15: Not applicable | AO15: Nominal | AP15: =+EMISSÕES!I10 -> 500000000 | AQ15: =+EMISSÕES!I10/EMISSÕES!J10 -> 5000 | AR15: =+ROUND(EMISSÕES!J10,0) -> 100000 | AS15: =+AR15 -> 100000 | AT15: =+ROUND(EMISSÕES!AG10,4) -> 2894191.8 | AU15: 0 | AV15: 999999999999999 | AW15: 999999999999999 | AX15: 999999999999999 | AY15: Not applicable | AZ15: -9999.999999999 | BA15: INTERBOLSA_PT | BB15: 529900LG70TCAGWCXT47 | BC15: Not applicable | BD15: Not applicable | BE15: Not applicable | BF15: Not applicable | BG15: Not applicable | BH15: Not applicable | BI15: Not applicable | BJ15: =+BA15 -> INTERBOLSA_PT | BK15: =+BB15 -> 529900LG70TCAGWCXT47 | BL15: Not applicable | BM15: Not applicable | BN15: Not applicable | BO15: Not applicable | BP15: No | BQ15: =+E15+J15 -> 5.0289419e+08 | BR15: Not applicable | BS15: 999999999999999 | BT15: =+ROUND(0,2) -> 0 | BU15: Not applicable | BV15: Not applicable | BW15: Not applicable | BX15: Not applicable | BY15: =+H15-I15 -> 5.0289419e+08 | BZ15: 110 Financial liabilities at amortized cost | CA15: =+BY15 -> 5.0289419e+08 | CB15: 110 Financial liabilities at amortized cost | CC15: FALSE | CD15: TRUE
A16: sequência incorreta | B16: Deveria ser cempresa+cbalcao+cnumecta+zdeposit | E16: Registo a vermelho não bate certo com o nom_tot_inic da ct610 (1391779674.000000) | F16: Não Deveria ser 999999999999999? | H16: nom_tot_atual - nom_tot_ini_investe (atenção à posiçao do emitente/investidro) | I16: Registo a vermelho não bate certo com o nom_tot_ini_investe do zcliente_investidor 5100011001 (6326736.000000) | L16: Os registos a vermelho não correspondem à soma dos campos 0080, 0100 e 0110

Sheet B9000
A1: Row number | B1: Tab of origin | C1: Unique identification number (known to the counterparty) | D1: Counterparty within the resolution group | E1: Counterparty name | F1: Counterparty identifier (preferably LEI) | G1: Type of counterparty identifier | H1: Internal identifier of the counterparty | I1: Counterparty type | J1: Country of the counterparty | K1: Relevant amount for Bail-in/WDC
A2: 0010 | B2: 0011 | C2: 0020 | D2: 0030 | E2: 0040 | F2: 0050 | G2: 0060 | H2: 0070 | I2: 0080 | J2: 0090 | K2: 0100
A5: Numeric | B5: String | C5: String | D5: String | E5: String | F5: String | G5: String | H5: String | I5: String | J5: String | K5: Numeric
A6: Integer | B6: Drop-down | C6: Free text | D6: Drop-down | E6: Free text | F6: Free text | G6: Free text, but fixed values for specific items | H6: Free text | I6: Drop-down | J6: ISO 3166-1 | K6: 2 decimals
A8: 1 | B8: B0200 | C8: =+'B0200'!C8 -> PTBSRDOM0037 | D8: Intragroup and intra-resolution group | E8: {=+B99.00[0040]} -> Banco Santander, S.A. | F8: {=+B99.00[0041]} -> 5493006QMFDDMYWIAM13 | G8: LEI | H8: 399904810324780 | I8: Other financial corporations | J8: ES | K8: =+ROUND('B0200'!N8,2) -> 500000000
A9: =+A8+1 -> 2 | B9: B0200 | C9: =+'B0200'!C9 -> PTBSREOM0028 | D9: Intragroup and intra-resolution group | E9: {=+B99.00[0040]} -> Banco Santander, S.A. | F9: {=+B99.00[0041]} -> 5493006QMFDDMYWIAM13 | G9: LEI | H9: 399904810324780 | I9: Other financial corporations | J9: ES | K9: =+ROUND('B0200'!N9,2) -> 8143942
A10: =+A9+1 -> 3 | B10: B0200 | C10: =+'B0200'!C10 -> PTCPP0AM0007 | D10: Intragroup and intra-resolution group | E10: {=+B99.00[0040]} -> Banco Santander, S.A. | F10: {=+B99.00[0041]} -> 5493006QMFDDMYWIAM13 | G10: LEI | H10: 399904810324780 | I10: Other financial corporations | J10: ES | K10: =+ROUND('B0200'!N10,2) -> 1585169628
A11: =+A10+1 -> 4 | B11: B0200 | C11: =+'B0200'!C11 -> PTSTOCOM0007 | D11: Intragroup and intra-resolution group | E11: {=+B99.00[0040]} -> Banco Santander, S.A. | F11: {=+B99.00[0041]} -> 5493006QMFDDMYWIAM13 | G11: LEI | H11: 399904810324780 | I11: Other financial corporations | J11: ES | K11: =+ROUND('B0200'!N11,2) -> 400000000
A12: =+A11+1 -> 5 | B12: B0200 | C12: =+'B0200'!C12 -> PTSTOEOM0021 | D12: Intragroup and intra-resolution group | E12: {=+B99.00[0040]} -> Banco Santander, S.A. | F12: {=+B99.00[0041]} -> 5493006QMFDDMYWIAM13 | G12: LEI | H12: 399904810324780 | I12: Other financial corporations | J12: ES | K12: =+ROUND('B0200'!N12,2) -> 6.055151e+08
A13: =+A12+1 -> 6 | B13: B0200 | C13: =+'B0200'!C13 -> PTSTOFOM0004 | D13: Intragroup and intra-resolution group | E13: {=+B99.00[0040]} -> Banco Santander, S.A. | F13: {=+B99.00[0041]} -> 5493006QMFDDMYWIAM13 | G13: LEI | H13: 399904810324780 | I13: Other financial corporations | J13: ES | K13: =+ROUND('B0200'!N13,2) -> 2.026605e+08
A14: =+A13+1 -> 7 | B14: B0200 | C14: =+'B0200'!C14 -> PTSTOGOM0003 | D14: Intragroup and intra-resolution group | E14: {=+B99.00[0040]} -> Banco Santander, S.A. | F14: {=+B99.00[0041]} -> 5493006QMFDDMYWIAM13 | G14: LEI | H14: 399904810324780 | I14: Other financial corporations | J14: ES | K14: =+ROUND('B0200'!N14,2) -> 300000000
A15: =+A14+1 -> 8 | B15: B0200 | C15: =+'B0200'!C15 -> PTSTOHOM0002 | D15: Intragroup and intra-resolution group | E15: {=+B99.00[0040]} -> Banco Santander, S.A. | F15: {=+B99.00[0041]} -> 5493006QMFDDMYWIAM13 | G15: LEI | H15: 399904810324780 | I15: Other financial corporations | J15: ES | K15: =+ROUND('B0200'!N15,2) -> 5.0289419e+08

Sheet VALIDATIONS
A1: Tab | B1: B02.00 | C1: B02.00 | D1: B02.00 | E1: B02.00 | F1: B02.00 | G1: B02.00 | H1: B02.00 | I1: B02.00 | J1: B02.00 | K1: B02.00 | L1: B02.00 | M1: B02.00 | N1: B02.00 | O1: B02.00 | P1: B02.00 | Q1: B02.00 | R1: B02.00 | S1: B02.00 | T1: B02.00 | U1: B02.00 | V1: B02.00 | W1: B02.00 | X1: B02.00 | Y1: B02.00 | Z1: B02.00 | AA1: B02.00 | AB1: B02.00 | AC1: B02.00 | AD1: B02.00 | AE1: B02.00 | AF1: B02.00 | AG1: B02.00 | AH1: B02.00 | AI1: B02.00 | AJ1: B02.00 | AK1: B02.00 | AL1: B02.00 | AM1: B02.00 | AN1: B02.00 | AO1: B90.00
A2: Rule # | B2: v_1_0001 | C2: v_1_0002 | D2: v_1_0003 | E2: v_1_0004 | F2: v_1_0005 | G2: v_1_0006 | H2: v_1_0007 | I2: v_1_0008 | J2: v_1_0009 | K2: v_1_0010 | L2: v_1_0011 | M2: v_1_0012 | N2: v_1_0013 | O2: v_1_0014 | P2: v_1_0015 | Q2: v_1_0016 | R2: v_1_0017 | S2: v_1_0018 | T2: v_1_0019 | U2: v_1_0020 | V2: v_1_0021 | W2: v_1_0022 | X2: v_1_0023 | Y2: v_1_0024 | Z2: v_1_0025 | AA2: v_1_0026 | AB2: v_1_0027 | AC2: v_1_0028 | AD2: v_1_0029 | AE2: v_1_0030 | AF2: v_1_0031 | AG2: v_1_0032 | AH2: v_1_0033 | AI2: v_1_0034 | AJ2: v_1_0035 | AK2: v_1_0036 | AL2: v_1_0037 | AM2: v_1_0038 | AN2: v_1_0039 | AO2: v_1_0056
B3: =+VLOOKUP(B2,'Level 1 Guidance'!$B$2:$D$42,3,0) -> 0010 | C3: =+VLOOKUP(C2,'Level 1 Guidance'!$B$2:$D$42,3,0) -> 0030 | D3: =+VLOOKUP(D2,'Level 1 Guidance'!$B$2:$D$42,3,0) -> 0040 | E3: =+VLOOKUP(E2,'Level 1 Guidance'!$B$2:$D$42,3,0) -> 0070 | F3: =+VLOOKUP(F2,'Level 1 Guidance'!$B$2:$D$42,3,0) -> 0080 | G3: =+VLOOKUP(G2,'Level 1 Guidance'!$B$2:$D$42,3,0) -> 0080 | H3: =+VLOOKUP(H2,'Level 1 Guidance'!$B$2:$D$42,3,0) -> 0090 | I3: =+VLOOKUP(I2,'Level 1 Guidance'!$B$2:$D$42,3,0) -> 0100 | ... AO3: =+VLOOKUP(AO2,'Level 1 Guidance'!$B$2:$D$42,3,0) -> 0030
A4: =+'B0200'!A8 -> 1 | B4: =+IF(ISBLANK('B0200'!A8),"ERROR","OK") -> OK | C4: =+IF(ISBLANK('B0200'!C8),"ERROR","OK") -> OK | D4: =+IF(ISBLANK('B0200'!D8),"ERROR","OK") -> OK | E4: =+IF(ISBLANK('B0200'!G8),"ERROR","OK") -> OK | F4: =+IF(ISBLANK('B0200'!H8),"ERROR","OK") -> OK | G4: =+IF('B0200'!D8="ISIN",IF(ISBLANK('B0200'!H8),"ERROR","OK"),"OK") -> OK | H4: =+IF(ISBLANK('B0200'!I8),"ERROR","OK") -> OK | I4: =+IF(ISBLANK('B0200'!J8),"ERROR","OK") -> OK | J4: =+IF(ISBLANK('B0200'!J8),"ERROR","OK") -> OK | K4: =+IF(ISBLANK('B0200'!L8),"ERROR","OK") -> OK | L4: =+IF(ISBLANK('B0200'!L8),"ERROR","OK") -> OK | M4: =+IF(ISBLANK('B0200'!N8),"ERROR","OK") -> OK | N4: =+IF(VLOOKUP('B0200'!O8,'Aux Validations'!$A$3:$B$13,2,0)=1,"OK","ERROR") -> OK | O4: =+IF('B0200'!O8="Other","ERROR","OK") -> OK | P4: =+IF(ISBLANK('B0200'!R8),"ERROR","OK") -> OK | Q4: =+IF(ISBLANK('B0200'!T8),"ERROR","OK") -> OK | R4: =+IF(ISBLANK('B0200'!V8),"ERROR","OK") -> OK | S4: =+IF(ISBLANK('B0200'!V8),"ERROR","OK") -> OK | T4: =+IF(ISBLANK('B0200'!X8),"ERROR","OK") -> OK | U4: =+IF(ISBLANK('B0200'!Y8),"ERROR","OK") -> OK | V4: =+IF(ISBLANK('B0200'!Z8),"ERROR","OK") -> OK | W4: =+IF(VLOOKUP('B0200'!AC8,'Aux Validations'!$D$3:$E$8,2,0)=1,"OK","ERROR") -> OK | X4: =+IF(OR('B0200'!AC8='Aux Validations'!$D$5,'B0200'!AC8='Aux Validations'!$D$7),ISBLANK('B0200'!AD8),"OK") -> OK | Y4: =+IF(OR('B0200'!AC8='Aux Validations'!$D$5,'B0200'!AC8='Aux Validations'!$D$7),ISBLANK('B0200'!AE8),"OK") -> OK | Z4: =+IF('B0200'!AF8="TRUE",IF(ISBLANK('B0200'!AH8),"ERRO","OK"),"OK") -> OK | AA4: =+IF(ISBLANK('B0200'!AI8),"ERROR","OK") -> OK | AB4: =+IF('B0200'!AI8=Lists!$I$2,IF(ISBLANK('B0200'!AJ8),"ERRO","OK"),"OK") -> OK | AC4: =+IF('B0200'!AI8=Lists!$I$2,IF(ISBLANK('B0200'!AK8),"ERRO","OK"),"OK") -> OK | AD4: =+IF('B0200'!AI8=Lists!$I$2,IF(ISBLANK('B0200'!AM8),"ERRO","OK"),"OK") -> OK | AE4: =+IF('B0200'!AM8="Other",IF(ISBLANK('B0200'!AN8),"ERRO","OK"),"OK") -> OK | AF4: =+IF(AND('B0200'!D8="ISIN",'B0200'!AO8="Nominal"),IF(ISBLANK('B0200'!AP8),"ERRO","OK"),"OK") -> OK | AG4: =+IF(AND('B0200'!D8="ISIN",'B0200'!AO8="Unit"),IF(ISBLANK('B0200'!AP8),"ERRO","OK"),"OK") -> OK | AH4: =+IF('B0200'!D8="ISIN",IF(ISBLANK('B0200'!AR8),"ERROR","OK"),"OK") -> OK | AI4: =+IF('B0200'!D8="ISIN",IF(ISBLANK('B0200'!AS8),"ERROR","OK"),"OK") -> OK | AJ4: =+IF('B0200'!AB8="ZCB issued at discount",IF(ISBLANK('B0200'!AT8),"ERROR","OK"),"OK") -> OK | AL4: =+IF(ISBLANK('B0200'!BY8),"ERROR","OK") -> OK | AM4: =+IF('B9900'!$H$11=Lists!$A$3,IF(ISBLANK('B0200'!CC8),"ERRO","OK")) -> OK | AN4: =+IF('B9900'!$H$11=Lists!$A$3,IF(ISBLANK('B0200'!CD8),"ERRO","OK")) -> OK | AO4: =+IF(ISBLANK('B9000'!D8),"ERRO","OK") -> OK
A5: =+'B0200'!A9 -> 2 | B5: =+IF(ISBLANK('B0200'!A9),"ERROR","OK") -> OK | C5: =+IF(ISBLANK('B0200'!C9),"ERROR","OK") -> OK | D5: =+IF(ISBLANK('B0200'!D9),"ERROR","OK") -> OK | E5: =+IF(ISBLANK('B0200'!G9),"ERROR","OK") -> OK | F5: =+IF(ISBLANK('B0200'!H9),"ERROR","OK") -> OK | G5: =+IF('B0200'!D9="ISIN",IF(ISBLANK('B0200'!H9),"ERROR","OK"),"OK") -> OK | H5: =+IF(ISBLANK('B0200'!I9),"ERROR","OK") -> OK | I5: =+IF(ISBLANK('B0200'!J9),"ERROR","OK") -> OK | J5: =+IF(ISBLANK('B0200'!J9),"ERROR","OK") -> OK | K5: =+IF(ISBLANK('B0200'!L9),"ERROR","OK") -> OK | L5: =+IF(ISBLANK('B0200'!L9),"ERROR","OK") -> OK | M5: =+IF(ISBLANK('B0200'!N9),"ERROR","OK") -> OK | N5: =+IF(VLOOKUP('B0200'!O9,'Aux Validations'!$A$3:$B$13,2,0)=1,"OK","ERROR") -> OK | O5: =+IF('B0200'!O9="Other","ERROR","OK") -> OK | P5: =+IF(ISBLANK('B0200'!R9),"ERROR","OK") -> OK | Q5: =+IF(ISBLANK('B0200'!T9),"ERROR","OK") -> OK | R5: =+IF(ISBLANK('B0200'!V9),"ERROR","OK") -> OK | S5: =+IF(ISBLANK('B0200'!V9),"ERROR","OK") -> OK | T5: =+IF(ISBLANK('B0200'!X9),"ERROR","OK") -> OK | U5: =+IF(ISBLANK('B0200'!Y9),"ERROR","OK") -> OK | V5: =+IF(ISBLANK('B0200'!Z9),"ERROR","OK") -> OK | W5: =+IF(VLOOKUP('B0200'!AC9,'Aux Validations'!$D$3:$E$8,2,0)=1,"OK","ERROR") -> OK | X5: =+IF(OR('B0200'!AC9='Aux Validations'!$D$5,'B0200'!AC9='Aux Validations'!$D$7),"ERRO","OK") -> OK | Y5: =+IF(OR('B0200'!AC9='Aux Validations'!$D$5,'B0200'!AC9='Aux Validations'!$D$7),ISBLANK('B0200'!AE9),"OK") -> OK | Z5: =+IF('B0200'!AF9="TRUE",IF(ISBLANK('B0200'!AH9),"ERRO","OK"),"OK") -> OK | AA5: =+IF(ISBLANK('B0200'!AI9),"ERROR","OK") -> OK | AB5: =+IF('B0200'!AI9=Lists!$I$2,IF(ISBLANK('B0200'!AJ9),"ERRO","OK"),"OK") -> OK | AC5: =+IF('B0200'!AI9=Lists!$I$2,IF(ISBLANK('B0200'!AK9),"ERRO","OK"),"OK") -> OK | AD5: =+IF('B0200'!AI9=Lists!$I$2,IF(ISBLANK('B0200'!AM9),"ERRO","OK"),"OK") -> OK | AE5: =+IF('B0200'!AM9="Other",IF(ISBLANK('B0200'!AN9),"ERRO","OK"),"OK") -> OK | AF5: =+IF(AND('B0200'!D9="ISIN",'B0200'!AO9="Nominal"),IF(ISBLANK('B0200'!AP9),"ERRO","OK"),"OK") -> OK | AG5: =+IF(AND('B0200'!D9="ISIN",'B0200'!AO9="Unit"),IF(ISBLANK('B0200'!AP9),"ERRO","OK"),"OK") -> OK | AH5: =+IF('B0200'!D9="ISIN",IF(ISBLANK('B0200'!AR9),"ERROR","OK"),"OK") -> OK | AI5: =+IF('B0200'!D9="ISIN",IF(ISBLANK('B0200'!AS9),"ERROR","OK"),"OK") -> OK | AJ5: =+IF('B0200'!AB9="ZCB issued at discount",IF(ISBLANK('B0200'!AT9),"ERROR","OK"),"OK") -> OK | AL5: =+IF(ISBLANK('B0200'!BY9),"ERROR","OK") -> OK | AM5: =+IF('B9900'!$H$11=Lists!$A$3,IF(ISBLANK('B0200'!CC9),"ERRO","OK")) -> OK | AN5: =+IF('B9900'!$H$11=Lists!$A$3,IF(ISBLANK('B0200'!CD9),"ERRO","OK")) -> OK | AO5: =+IF(ISBLANK('B9000'!D9),"ERRO","OK") -> OK
A6: =+'B0200'!A10 -> 1 | B6: =+IF(ISBLANK('B0200'!A10),"ERROR","OK") -> OK | C6: =+IF(ISBLANK('B0200'!C10),"ERROR","OK") -> OK | D6: =+IF(ISBLANK('B0200'!D10),"ERROR","OK") -> OK | E6: =+IF(ISBLANK('B0200'!G10),"ERROR","OK") -> OK | F6: =+IF(ISBLANK('B0200'!H10),"ERROR","OK") -> OK | G6: =+IF('B0200'!D10="ISIN",IF(ISBLANK('B0200'!H10),"ERROR","OK"),"OK") -> OK | H6: =+IF(ISBLANK('B0200'!I10),"ERROR","OK") -> OK | I6: =+IF(ISBLANK('B0200'!J10),"ERROR","OK") -> OK | J6: =+IF(ISBLANK('B0200'!J10),"ERROR","OK") -> OK | K6: =+IF(ISBLANK('B0200'!L10),"ERROR","OK") -> OK | L6: =+IF(ISBLANK('B0200'!L10),"ERROR","OK") -> OK | M6: =+IF(ISBLANK('B0200'!N10),"ERROR","OK") -> OK | N6: =+IF(VLOOKUP('B0200'!O10,'Aux Validations'!$A$3:$B$13,2,0)=1,"OK","ERROR") -> OK | O6: =+IF('B0200'!O10="Other","ERROR","OK") -> OK | P6: =+IF(ISBLANK('B0200'!R10),"ERROR","OK") -> OK | Q6: =+IF(ISBLANK('B0200'!T10),"ERROR","OK") -> OK | R6: =+IF(ISBLANK('B0200'!V10),"ERROR","OK") -> OK | S6: =+IF(ISBLANK('B0200'!V10),"ERROR","OK") -> OK | T6: =+IF(ISBLANK('B0200'!X10),"ERROR","OK") -> OK | U6: =+IF(ISBLANK('B0200'!Y10),"ERROR","OK") -> OK | V6: =+IF(ISBLANK('B0200'!Z10),"ERROR","OK") -> OK | W6: =+IF(VLOOKUP('B0200'!AC10,'Aux Validations'!$D$3:$E$8,2,0)=1,"OK","ERROR") -> OK | X6: =+IF(OR('B0200'!AC10='Aux Validations'!$D$5,'B0200'!AC10='Aux Validations'!$D$7),"ERRO","OK") -> OK | Y6: =+IF(OR('B0200'!AC10='Aux Validations'!$D$5,'B0200'!AC10='Aux Validations'!$D$7),ISBLANK('B0200'!AE10),"OK") -> OK | Z6: =+IF('B0200'!AF10="TRUE",IF(ISBLANK('B0200'!AH10),"ERRO","OK"),"OK") -> OK | AA6: =+IF(ISBLANK('B0200'!AI10),"ERROR","OK") -> OK | AB6: =+IF('B0200'!AI10=Lists!$I$2,IF(ISBLANK('B0200'!AJ10),"ERRO","OK"),"OK") -> OK | AC6: =+IF('B0200'!AI10=Lists!$I$2,IF(ISBLANK('B0200'!AK10),"ERRO","OK"),"OK") -> OK | AD6: =+IF('B0200'!AI10=Lists!$I$2,IF(ISBLANK('B0200'!AM10),"ERRO","OK"),"OK") -> OK | AE6: =+IF('B0200'!AM10="Other",IF(ISBLANK('B0200'!AN10),"ERRO","OK"),"OK") -> OK | AF6: =+IF(AND('B0200'!D10="ISIN",'B0200'!AO10="Nominal"),IF(ISBLANK('B0200'!AP10),"ERRO","OK"),"OK") -> OK | AG6: =+IF(AND('B0200'!D10="ISIN",'B0200'!AO10="Unit"),IF(ISBLANK('B0200'!AP10),"ERRO","OK"),"OK") -> OK | AH6: =+IF('B0200'!D10="ISIN",IF(ISBLANK('B0200'!AR10),"ERROR","OK"),"OK") -> OK | AI6: =+IF('B0200'!D10="ISIN",IF(ISBLANK('B0200'!AS10),"ERROR","OK"),"OK") -> OK | AJ6: =+IF('B0200'!AB10="ZCB issued at discount",IF(ISBLANK('B0200'!AT10),"ERROR","OK"),"OK") -> OK | AL6: =+IF(ISBLANK('B0200'!BY10),"ERROR","OK") -> OK | AM6: =+IF('B9900'!$H$11=Lists!$A$3,IF(ISBLANK('B0200'!CC10),"ERRO","OK")) -> OK | AN6: =+IF('B9900'!$H$11=Lists!$A$3,IF(ISBLANK('B0200'!CD10),"ERRO","OK")) -> OK | AO6: =+IF(ISBLANK('B9000'!D10),"ERRO","OK") -> OK
A7: =+'B0200'!A11 -> 2 | B7: =+IF(ISBLANK('B0200'!A11),"ERROR","OK") -> OK | C7: =+IF(ISBLANK('B0200'!C11),"ERROR","OK") -> OK | D7: =+IF(ISBLANK('B0200'!D11),"ERROR","OK") -> OK | E7: =+IF(ISBLANK('B0200'!G11),"ERROR","OK") -> OK | F7: =+IF(ISBLANK('B0200'!H11),"ERROR","OK") -> OK | G7: =+IF('B0200'!D11="ISIN",IF(ISBLANK('B0200'!H11),"ERROR","OK"),"OK") -> OK | H7: =+IF(ISBLANK('B0200'!I11),"ERROR","OK") -> OK | I7: =+IF(ISBLANK('B0200'!J11),"ERROR","OK") -> OK | J7: =+IF(ISBLANK('B0200'!J11),"ERROR","OK") -> OK | K7: =+IF(ISBLANK('B0200'!L11),"ERROR","OK") -> OK | L7: =+IF(ISBLANK('B0200'!L11),"ERROR","OK") -> OK | M7: =+IF(ISBLANK('B0200'!N11),"ERROR","OK") -> OK | N7: =+IF(VLOOKUP('B0200'!O11,'Aux Validations'!$A$3:$B$13,2,0)=1,"OK","ERROR") -> OK | O7: =+IF('B0200'!O11="Other","ERROR","OK") -> OK | P7: =+IF(ISBLANK('B0200'!R11),"ERROR","OK") -> OK | Q7: =+IF(ISBLANK('B0200'!T11),"ERROR","OK") -> OK | R7: =+IF(ISBLANK('B0200'!V11),"ERROR","OK") -> OK | S7: =+IF(ISBLANK('B0200'!V11),"ERROR","OK") -> OK | T7: =+IF(ISBLANK('B0200'!X11),"ERROR","OK") -> OK | U7: =+IF(ISBLANK('B0200'!Y11),"ERROR","OK") -> OK | V7: =+IF(ISBLANK('B0200'!Z11),"ERROR","OK") -> OK | W7: =+IF(VLOOKUP('B0200'!AC11,'Aux Validations'!$D$3:$E$8,2,0)=1,"OK","ERROR") -> OK | X7: =+IF(OR('B0200'!AC11='Aux Validations'!$D$5,'B0200'!AC11='Aux Validations'!$D$7),"ERRO","OK") -> OK | Y7: =+IF(OR('B0200'!AC11='Aux Validations'!$D$5,'B0200'!AC11='Aux Validations'!$D$7),ISBLANK('B0200'!AE11),"OK") -> OK | Z7: =+IF('B0200'!AF11="TRUE",IF(ISBLANK('B0200'!AH11),"ERRO","OK"),"OK") -> OK | AA7: =+IF(ISBLANK('B0200'!AI11),"ERROR","OK") -> OK | AB7: =+IF('B0200'!AI11=Lists!$I$2,IF(ISBLANK('B0200'!AJ11),"ERRO","OK"),"OK") -> OK | AC7: =+IF('B0200'!AI11=Lists!$I$2,IF(ISBLANK('B0200'!AK11),"ERRO","OK"),"OK") -> OK | AD7: =+IF('B0200'!AI11=Lists!$I$2,IF(ISBLANK('B0200'!AM11),"ERRO","OK"),"OK") -> OK | AE7: =+IF('B0200'!AM11="Other",IF(ISBLANK('B0200'!AN11),"ERRO","OK"),"OK") -> OK | AF7: =+IF(AND('B0200'!D11="ISIN",'B0200'!AO11="Nominal"),IF(ISBLANK('B0200'!AP11),"ERRO","OK"),"OK") -> OK | AG7: =+IF(AND('B0200'!D11="ISIN",'B0200'!AO11="Unit"),IF(ISBLANK('B0200'!AP11),"ERRO","OK"),"OK") -> OK | AH7: =+IF('B0200'!D11="ISIN",IF(ISBLANK('B0200'!AR11),"ERROR","OK"),"OK") -> OK | AI7: =+IF('B0200'!D11="ISIN",IF(ISBLANK('B0200'!AS11),"ERROR","OK"),"OK") -> OK | AJ7: =+IF('B0200'!AB11="ZCB issued at discount",IF(ISBLANK('B0200'!AT11),"ERROR","OK"),"OK") -> OK | AL7: =+IF(ISBLANK('B0200'!BY11),"ERROR","OK") -> OK | AM7: =+IF('B9900'!$H$11=Lists!$A$3,IF(ISBLANK('B0200'!CC11),"ERRO","OK")) -> OK | AN7: =+IF('B9900'!$H$11=Lists!$A$3,IF(ISBLANK('B0200'!CD11),"ERRO","OK")) -> OK | AO7: =+IF(ISBLANK('B9000'!D11),"ERRO","OK") -> OK
A8: =+'B0200'!A12 -> 3 | B8: =+IF(ISBLANK('B0200'!A12),"ERROR","OK") -> OK | C8: =+IF(ISBLANK('B0200'!C12),"ERROR","OK") -> OK | D8: =+IF(ISBLANK('B0200'!D12),"ERROR","OK") -> OK | E8: =+IF(ISBLANK('B0200'!G12),"ERROR","OK") -> OK | F8: =+IF(ISBLANK('B0200'!H12),"ERROR","OK") -> OK | G8: =+IF('B0200'!D12="ISIN",IF(ISBLANK('B0200'!H12),"ERROR","OK"),"OK") -> OK | H8: =+IF(ISBLANK('B0200'!I12),"ERROR","OK") -> OK | I8: =+IF(ISBLANK('B0200'!J12),"ERROR","OK") -> OK | J8: =+IF(ISBLANK('B0200'!J12),"ERROR","OK") -> OK | K8: =+IF(ISBLANK('B0200'!L12),"ERROR","OK") -> OK | L8: =+IF(ISBLANK('B0200'!L12),"ERROR","OK") -> OK | M8: =+IF(ISBLANK('B0200'!N12),"ERROR","OK") -> OK | N8: =+IF(VLOOKUP('B0200'!O12,'Aux Validations'!$A$3:$B$13,2,0)=1,"OK","ERROR") -> OK | O8: =+IF('B0200'!O12="Other","ERROR","OK") -> OK | P8: =+IF(ISBLANK('B0200'!R12),"ERROR","OK") -> OK | Q8: =+IF(ISBLANK('B0200'!T12),"ERROR","OK") -> OK | R8: =+IF(ISBLANK('B0200'!V12),"ERROR","OK") -> OK | S8: =+IF(ISBLANK('B0200'!V12),"ERROR","OK") -> OK | T8: =+IF(ISBLANK('B0200'!X12),"ERROR","OK") -> OK | U8: =+IF(ISBLANK('B0200'!Y12),"ERROR","OK") -> OK | V8: =+IF(ISBLANK('B0200'!Z12),"ERROR","OK") -> OK | W8: =+IF(VLOOKUP('B0200'!AC12,'Aux Validations'!$D$3:$E$8,2,0)=1,"OK","ERROR") -> OK | X8: =+IF(OR('B0200'!AC12='Aux Validations'!$D$5,'B0200'!AC12='Aux Validations'!$D$7),"ERRO","OK") -> OK | Y8: =+IF(OR('B0200'!AC12='Aux Validations'!$D$5,'B0200'!AC12='Aux Validations'!$D$7),ISBLANK('B0200'!AE12),"OK") -> OK | Z8: =+IF('B0200'!AF12="TRUE",IF(ISBLANK('B0200'!AH12),"ERRO","OK"),"OK") -> OK | AA8: =+IF(ISBLANK('B0200'!AI12),"ERROR","OK") -> OK | AB8: =+IF('B0200'!AI12=Lists!$I$2,IF(ISBLANK('B0200'!AJ12),"ERRO","OK"),"OK") -> OK | AC8: =+IF('B0200'!AI12=Lists!$I$2,IF(ISBLANK('B0200'!AK12),"ERRO","OK"),"OK") -> OK | AD8: =+IF('B0200'!AI12=Lists!$I$2,IF(ISBLANK('B0200'!AM12),"ERRO","OK"),"OK") -> OK | AE8: =+IF('B0200'!AM12="Other",IF(ISBLANK('B0200'!AN12),"ERRO","OK"),"OK") -> OK | AF8: =+IF(AND('B0200'!D12="ISIN",'B0200'!AO12="Nominal"),IF(ISBLANK('B0200'!AP12),"ERRO","OK"),"OK") -> OK | AG8: =+IF(AND('B0200'!D12="ISIN",'B0200'!AO12="Unit"),IF(ISBLANK('B0200'!AP12),"ERRO","OK"),"OK") -> OK | AH8: =+IF('B0200'!D12="ISIN",IF(ISBLANK('B0200'!AR12),"ERROR","OK"),"OK") -> OK | AI8: =+IF('B0200'!D12="ISIN",IF(ISBLANK('B0200'!AS12),"ERROR","OK"),"OK") -> OK | AJ8: =+IF('B0200'!AB12="ZCB issued at discount",IF(ISBLANK('B0200'!AT12),"ERROR","OK"),"OK") -> OK | AL8: =+IF(ISBLANK('B0200'!BY12),"ERROR","OK") -> OK | AM8: =+IF('B9900'!$H$11=Lists!$A$3,IF(ISBLANK('B0200'!CC12),"ERRO","OK")) -> OK | AN8: =+IF('B9900'!$H$11=Lists!$A$3,IF(ISBLANK('B0200'!CD12),"ERRO","OK")) -> OK | AO8: =+IF(ISBLANK('B9000'!D12),"ERRO","OK") -> OK
A9: =+'B0200'!A13 -> 4 | B9: =+IF(ISBLANK('B0200'!A13),"ERROR","OK") -> OK | C9: =+IF(ISBLANK('B0200'!C13),"ERROR","OK") -> OK | D9: =+IF(ISBLANK('B0200'!D13),"ERROR","OK") -> OK | E9: =+IF(ISBLANK('B0200'!G13),"ERROR","OK") -> OK | F9: =+IF(ISBLANK('B0200'!H13),"ERROR","OK") -> OK | G9: =+IF('B0200'!D13="ISIN",IF(ISBLANK('B0200'!H13),"ERROR","OK"),"OK") -> OK | H9: =+IF(ISBLANK('B0200'!I13),"ERROR","OK") -> OK | I9: =+IF(ISBLANK('B0200'!J13),"ERROR","OK") -> OK | J9: =+IF(ISBLANK('B0200'!J13),"ERROR","OK") -> OK | K9: =+IF(ISBLANK('B0200'!L13),"ERROR","OK") -> OK | L9: =+IF(ISBLANK('B0200'!L13),"ERROR","OK") -> OK | M9: =+IF(ISBLANK('B0200'!N13),"ERROR","OK") -> OK | N9: =+IF(VLOOKUP('B0200'!O13,'Aux Validations'!$A$3:$B$13,2,0)=1,"OK","ERROR") -> OK | O9: =+IF('B0200'!O13="Other","ERROR","OK") -> OK | P9: =+IF(ISBLANK('B0200'!R13),"ERROR","OK") -> OK | Q9: =+IF(ISBLANK('B0200'!T13),"ERROR","OK") -> OK | R9: =+IF(ISBLANK('B0200'!V13),"ERROR","OK") -> OK | S9: =+IF(ISBLANK('B0200'!V13),"ERROR","OK") -> OK | T9: =+IF(ISBLANK('B0200'!X13),"ERROR","OK") -> OK | U9: =+IF(ISBLANK('B0200'!Y13),"ERROR","OK") -> OK | V9: =+IF(ISBLANK('B0200'!Z13),"ERROR","OK") -> OK | W9: =+IF(VLOOKUP('B0200'!AC13,'Aux Validations'!$D$3:$E$8,2,0)=1,"OK","ERROR") -> OK | X9: =+IF(OR('B0200'!AC13='Aux Validations'!$D$5,'B0200'!AC13='Aux Validations'!$D$7),"ERRO","OK") -> OK | Y9: =+IF(OR('B0200'!AC13='Aux Validations'!$D$5,'B0200'!AC13='Aux Validations'!$D$7),ISBLANK('B0200'!AE13),"OK") -> OK | Z9: =+IF('B0200'!AF13="TRUE",IF(ISBLANK('B0200'!AH13),"ERRO","OK"),"OK") -> OK | AA9: =+IF(ISBLANK('B0200'!AI13),"ERROR","OK") -> OK | AB9: =+IF('B0200'!AI13=Lists!$I$2,IF(ISBLANK('B0200'!AJ13),"ERRO","OK"),"OK") -> OK | AC9: =+IF('B0200'!AI13=Lists!$I$2,IF(ISBLANK('B0200'!AK13),"ERRO","OK"),"OK") -> OK | AD9: =+IF('B0200'!AI13=Lists!$I$2,IF(ISBLANK('B0200'!AM13),"ERRO","OK"),"OK") -> OK | AE9: =+IF('B0200'!AM13="Other",IF(ISBLANK('B0200'!AN13),"ERRO","OK"),"OK") -> OK | AF9: =+IF(AND('B0200'!D13="ISIN",'B0200'!AO13="Nominal"),IF(ISBLANK('B0200'!AP13),"ERRO","OK"),"OK") -> OK | AG9: =+IF(AND('B0200'!D13="ISIN",'B0200'!AO13="Unit"),IF(ISBLANK('B0200'!AP13),"ERRO","OK"),"OK") -> OK | AH9: =+IF('B0200'!D13="ISIN",IF(ISBLANK('B0200'!AR13),"ERROR","OK"),"OK") -> OK | AI9: =+IF('B0200'!D13="ISIN",IF(ISBLANK('B0200'!AS13),"ERROR","OK"),"OK") -> OK | AJ9: =+IF('B0200'!AB13="ZCB issued at discount",IF(ISBLANK('B0200'!AT13),"ERROR","OK"),"OK") -> OK | AL9: =+IF(ISBLANK('B0200'!BY13),"ERROR","OK") -> OK | AM9: =+IF('B9900'!$H$11=Lists!$A$3,IF(ISBLANK('B0200'!CC13),"ERRO","OK")) -> OK | AN9: =+IF('B9900'!$H$11=Lists!$A$3,IF(ISBLANK('B0200'!CD13),"ERRO","OK")) -> OK | AO9: =+IF(ISBLANK('B9000'!D13),"ERRO","OK") -> OK
A10: =+'B0200'!A14 -> 5 | B10: =+IF(ISBLANK('B0200'!A14),"ERROR","OK") -> OK | C10: =+IF(ISBLANK('B0200'!C14),"ERROR","OK") -> OK | D10: =+IF(ISBLANK('B0200'!D14),"ERROR","OK") -> OK | E10: =+IF(ISBLANK('B0200'!G14),"ERROR","OK") -> OK | F10: =+IF(ISBLANK('B0200'!H14),"ERROR","OK") -> OK | G10: =+IF('B0200'!D14="ISIN",IF(ISBLANK('B0200'!H14),"ERROR","OK"),"OK") -> OK | H10: =+IF(ISBLANK('B0200'!I14),"ERROR","OK") -> OK | I10: =+IF(ISBLANK('B0200'!J14),"ERROR","OK") -> OK | J10: =+IF(ISBLANK('B0200'!J14),"ERROR","OK") -> OK | K10: =+IF(ISBLANK('B0200'!L14),"ERROR","OK") -> OK | L10: =+IF(ISBLANK('B0200'!L14),"ERROR","OK") -> OK | M10: =+IF(ISBLANK('B0200'!N14),"ERROR","OK") -> OK | N10: =+IF(VLOOKUP('B0200'!O14,'Aux Validations'!$A$3:$B$13,2,0)=1,"OK","ERROR") -> OK | O10: =+IF('B0200'!O14="Other","ERROR","OK") -> OK | P10: =+IF(ISBLANK('B0200'!R14),"ERROR","OK") -> OK | Q10: =+IF(ISBLANK('B0200'!T14),"ERROR","OK") -> OK | R10: =+IF(ISBLANK('B0200'!V14),"ERROR","OK") -> OK | S10: =+IF(ISBLANK('B0200'!V14),"ERROR","OK") -> OK | T10: =+IF(ISBLANK('B0200'!X14),"ERROR","OK") -> OK | U10: =+IF(ISBLANK('B0200'!Y14),"ERROR","OK") -> OK | V10: =+IF(ISBLANK('B0200'!Z14),"ERROR","OK") -> OK | W10: =+IF(VLOOKUP('B0200'!AC14,'Aux Validations'!$D$3:$E$8,2,0)=1,"OK","ERROR") -> OK | X10: =+IF(OR('B0200'!AC14='Aux Validations'!$D$5,'B0200'!AC14='Aux Validations'!$D$7),"ERRO","OK") -> OK | Y10: =+IF(OR('B0200'!AC14='Aux Validations'!$D$5,'B0200'!AC14='Aux Validations'!$D$7),ISBLANK('B0200'!AE14),"OK") -> OK | Z10: =+IF('B0200'!AF14="TRUE",IF(ISBLANK('B0200'!AH14),"ERRO","OK"),"OK") -> OK | AA10: =+IF(ISBLANK('B0200'!AI14),"ERROR","OK") -> OK | AB10: =+IF('B0200'!AI14=Lists!$I$2,IF(ISBLANK('B0200'!AJ14),"ERRO","OK"),"OK") -> OK | AC10: =+IF('B0200'!AI14=Lists!$I$2,IF(ISBLANK('B0200'!AK14),"ERRO","OK"),"OK") -> OK | AD10: =+IF('B0200'!AI14=Lists!$I$2,IF(ISBLANK('B0200'!AM14),"ERRO","OK"),"OK") -> OK | AE10: =+IF('B0200'!AM14="Other",IF(ISBLANK('B0200'!AN14),"ERRO","OK"),"OK") -> OK | AF10: =+IF(AND('B0200'!D14="ISIN",'B0200'!AO14="Nominal"),IF(ISBLANK('B0200'!AP14),"ERRO","OK"),"OK") -> OK | AG10: =+IF(AND('B0200'!D14="ISIN",'B0200'!AO14="Unit"),IF(ISBLANK('B0200'!AP14),"ERRO","OK"),"OK") -> OK | AH10: =+IF('B0200'!D14="ISIN",IF(ISBLANK('B0200'!AR14),"ERROR","OK"),"OK") -> OK | AI10: =+IF('B0200'!D14="ISIN",IF(ISBLANK('B0200'!AS14),"ERROR","OK"),"OK") -> OK | AJ10: =+IF('B0200'!AB14="ZCB issued at discount",IF(ISBLANK('B0200'!AT14),"ERROR","OK"),"OK") -> OK | AL10: =+IF(ISBLANK('B0200'!BY14),"ERROR","OK") -> OK | AM10: =+IF('B9900'!$H$11=Lists!$A$3,IF(ISBLANK('B0200'!CC14),"ERRO","OK")) -> OK | AN10: =+IF('B9900'!$H$11=Lists!$A$3,IF(ISBLANK('B0200'!CD14),"ERRO","OK")) -> OK | AO10: =+IF(ISBLANK('B9000'!D14),"ERRO","OK") -> OK
A11: =+'B0200'!A15 -> 6 | B11: =+IF(ISBLANK('B0200'!A15),"ERROR","OK") -> OK | C11: =+IF(ISBLANK('B0200'!C15),"ERROR","OK") -> OK | D11: =+IF(ISBLANK('B0200'!D15),"ERROR","OK") -> OK | E11: =+IF(ISBLANK('B0200'!G15),"ERROR","OK") -> OK | F11: =+IF(ISBLANK('B0200'!H15),"ERROR","OK") -> OK | G11: =+IF('B0200'!D15="ISIN",IF(ISBLANK('B0200'!H15),"ERROR","OK"),"OK") -> OK | H11: =+IF(ISBLANK('B0200'!I15),"ERROR","OK") -> OK | I11: =+IF(ISBLANK('B0200'!J15),"ERROR","OK") -> OK | J11: =+IF(ISBLANK('B0200'!J15),"ERROR","OK") -> OK | K11: =+IF(ISBLANK('B0200'!L15),"ERROR","OK") -> OK | L11: =+IF(ISBLANK('B0200'!L15),"ERROR","OK") -> OK | M11: =+IF(ISBLANK('B0200'!N15),"ERROR","OK") -> OK | N11: =+IF(VLOOKUP('B0200'!O15,'Aux Validations'!$A$3:$B$13,2,0)=1,"OK","ERROR") -> OK | O11: =+IF('B0200'!O15="Other","ERROR","OK") -> OK | P11: =+IF(ISBLANK('B0200'!R15),"ERROR","OK") -> OK | Q11: =+IF(ISBLANK('B0200'!T15),"ERROR","OK") -> OK | R11: =+IF(ISBLANK('B0200'!V15),"ERROR","OK") -> OK | S11: =+IF(ISBLANK('B0200'!V15),"ERROR","OK") -> OK | T11: =+IF(ISBLANK('B0200'!X15),"ERROR","OK") -> OK | U11: =+IF(ISBLANK('B0200'!Y15),"ERROR","OK") -> OK | V11: =+IF(ISBLANK('B0200'!Z15),"ERROR","OK") -> OK | W11: =+IF(VLOOKUP('B0200'!AC15,'Aux Validations'!$D$3:$E$8,2,0)=1,"OK","ERROR") -> OK | X11: =+IF(OR('B0200'!AC15='Aux Validations'!$D$5,'B0200'!AC15='Aux Validations'!$D$7),"ERRO","OK") -> OK | Y11: =+IF(OR('B0200'!AC15='Aux Validations'!$D$5,'B0200'!AC15='Aux Validations'!$D$7),ISBLANK('B0200'!AE15),"OK") -> OK | Z11: =+IF('B0200'!AF15="TRUE",IF(ISBLANK('B0200'!AH15),"ERRO","OK"),"OK") -> OK | AA11: =+IF(ISBLANK('B0200'!AI15),"ERROR","OK") -> OK | AB11: =+IF('B0200'!AI15=Lists!$I$2,IF(ISBLANK('B0200'!AJ15),"ERRO","OK"),"OK") -> OK | AC11: =+IF('B0200'!AI15=Lists!$I$2,IF(ISBLANK('B0200'!AK15),"ERRO","OK"),"OK") -> OK | AD11: =+IF('B0200'!AI15=Lists!$I$2,IF(ISBLANK('B0200'!AM15),"ERRO","OK"),"OK") -> OK | AE11: =+IF('B0200'!AM15="Other",IF(ISBLANK('B0200'!AN15),"ERRO","OK"),"OK") -> OK | AF11: =+IF(AND('B0200'!D15="ISIN",'B0200'!AO15="Nominal"),IF(ISBLANK('B0200'!AP15),"ERRO","OK"),"OK") -> OK | AG11: =+IF(AND('B0200'!D15="ISIN",'B0200'!AO15="Unit"),IF(ISBLANK('B0200'!AP15),"ERRO","OK"),"OK") -> OK | AH11: =+IF('B0200'!D15="ISIN",IF(ISBLANK('B0200'!AR15),"ERROR","OK"),"OK") -> OK | AI11: =+IF('B0200'!D15="ISIN",IF(ISBLANK('B0200'!AS15),"ERROR","OK"),"OK") -> OK | AJ11: =+IF('B0200'!AB15="ZCB issued at discount",IF(ISBLANK('B0200'!AT15),"ERROR","OK"),"OK") -> OK | AL11: =+IF(ISBLANK('B0200'!BY15),"ERROR","OK") -> OK | AM11: =+IF('B9900'!$H$11=Lists!$A$3,IF(ISBLANK('B0200'!CC15),"ERRO","OK")) -> OK | AN11: =+IF('B9900'!$H$11=Lists!$A$3,IF(ISBLANK('B0200'!CD15),"ERRO","OK")) -> OK | AO11: =+IF(ISBLANK('B9000'!D15),"ERRO","OK") -> OK

Sheet Level 1 Guidance
B1: MBDT - Level 1 Validation Rules: completeness checks.
B2: Check ID | C2: Tab | D2: Data point (Row/Column) | E2: Data point (Label) | F2: Data point type | G2: High severity (i.e the validation rule should in general not be breached) | H2: Warning only (i.e. the validation rule can be breached in certain cases) | I2: Type of test (missing values means "not applicable" or "not available") | J2: Prerequisite / Dependency | K2: Explanation
A3: 0001 | B3: =CONCATENATE("v_1_",A3) -> v_1_0001 | C3: B02.00 | D3: =VLOOKUP(CONCATENATE(C3,"_",E3),'Data types'!A:E,4,FALSE) -> 0010 | E3: Row number | F3: =VLOOKUP(CONCATENATE(C3,"_",E3),'Data types'!A:F,6,FALSE) -> Numeric: Integer | G3: X | I3: Test for missing values. | K3: Missing value. The field must be reported.
A4: 0002 | B4: =CONCATENATE("v_1_",A4) -> v_1_0002 | C4: B02.00 | D4: =VLOOKUP(CONCATENATE(C4,"_",E4),'Data types'!A:E,4,FALSE) -> 0030 | E4: Unique identification number (known to the counterparty) | F4: =VLOOKUP(CONCATENATE(C4,"_",E4),'Data types'!A:F,6,FALSE) -> String: Free text | G4: X | I4: Test for missing values. | K4: Missing value. The field must be reported.
A5: 0003 | B5: =CONCATENATE("v_1_",A5) -> v_1_0003 | C5: B02.00 | D5: =VLOOKUP(CONCATENATE(C5,"_",E5),'Data types'!A:E,4,FALSE) -> 0040 | E5: Type of the unique identifier (known to the counterparty) | F5: =VLOOKUP(CONCATENATE(C5,"_",E5),'Data types'!A:F,6,FALSE) -> String: Free text, but fixed values for specific items | G5: X | I5: Test for missing values. | K5: Missing value. The field must be reported.
A6: 0004 | B6: =CONCATENATE("v_1_",A6) -> v_1_0004 | C6: B02.00 | D6: =VLOOKUP(CONCATENATE(C6,"_",E6),'Data types'!A:E,4,FALSE) -> 0070 | E6: Contract Currency | F6: =VLOOKUP(CONCATENATE(C6,"_",E6),'Data types'!A:F,6,FALSE) -> String: 3-letters ISO 4217 | G6: X | I6: Test for missing values. | K6: Missing value. The field must be reported.
A7: 0005 | B7: =CONCATENATE("v_1_",A7) -> v_1_0005 | C7: B02.00 | D7: =VLOOKUP(CONCATENATE(C7,"_",E7),'Data types'!A:E,4,FALSE) -> 0080 | E7: Outstanding principal amount | F7: =VLOOKUP(CONCATENATE(C7,"_",E7),'Data types'!A:F,6,FALSE) -> Numeric: 2 decimals | G7: X | I7: Test for missing values. | J7: Rule applicable if c0250 = ("Non-Structured/Vanilla" OR "Other non-standard terms") | K7: Missing value. The field must be reported for non-structured liabilities.
A8: 0006 | B8: =CONCATENATE("v_1_",A8) -> v_1_0006 | C8: B02.00 | D8: =VLOOKUP(CONCATENATE(C8,"_",E8),'Data types'!A:E,4,FALSE) -> 0080 | E8: Outstanding principal amount | F8: =VLOOKUP(CONCATENATE(C8,"_",E8),'Data types'!A:F,6,FALSE) -> Numeric: 2 decimals | H8: X | I8: Test for missing values. | J8: Rule applicable if c0250 = ("Structured" OR "Only structured coupon") | K8: Missing value (warning only). For structured liabilities, the field has to be reported if the information exists.
A9: 0007 | B9: =CONCATENATE("v_1_",A9) -> v_1_0007 | C9: B02.00 | D9: =VLOOKUP(CONCATENATE(C9,"_",E9),'Data types'!A:E,4,FALSE) -> 0090 | E9: Portion of instrument or liability held by the reporting entity | F9: =VLOOKUP(CONCATENATE(C9,"_",E9),'Data types'!A:F,6,FALSE) -> Numeric: 2 decimals | G9: X | I9: Test for missing values. | J9: Rule applicable only if c0040 = "ISIN" | K9: Missing value. The field must be reported for securities.
A10: 0008 | B10: =CONCATENATE("v_1_",A10) -> v_1_0008 | C10: B02.00 | D10: =VLOOKUP(CONCATENATE(C10,"_",E10),'Data types'!A:E,4,FALSE) -> 0100 | E10: Accrued interest | F10: =VLOOKUP(CONCATENATE(C10,"_",E10),'Data types'!A:F,6,FALSE) -> Numeric: 2 decimals | G10: X | I10: Test for missing values. | J10: Rule applicable if c0250 = ("Non-Structured" OR "Other non-standard terms") AND c0240 != "ZCB issued at discount" | K10: Missing value. For non-structured liabilities that are not zero coupon bonds issued at discount, this field must be reported.
A11: 0009 | B11: =CONCATENATE("v_1_",A11) -> v_1_0009 | C11: B02.00 | D11: =VLOOKUP(CONCATENATE(C11,"_",E11),'Data types'!A:E,4,FALSE) -> 0100 | E11: Accrued interest | F11: =VLOOKUP(CONCATENATE(C11,"_",E11),'Data types'!A:F,6,FALSE) -> Numeric: 2 decimals | H11: X | I11: Test for missing values. | J11: Rule applicable only if c0250 != ("Structured" OR "Only structured coupon") | K11: Missing value (warning only). For structured liabilities, the field has to be reported if the information exists.
A12: 0010 | B12: =CONCATENATE("v_1_",A12) -> v_1_0010 | C12: B02.00 | D12: =VLOOKUP(CONCATENATE(C12,"_",E12),'Data types'!A:E,4,FALSE) -> 0120 | E12: Outstanding amount | F12: =VLOOKUP(CONCATENATE(C12,"_",E12),'Data types'!A:F,6,FALSE) -> Numeric: 2 decimals | G12: X | I12: Test for missing values. | J12: Rule applicable if c0250 = ("Non-Structured/Vanilla" OR "Other non-standard terms") | K12: Missing value. For non-structured liabilities, this field must be reported.
A13: 0011 | B13: =CONCATENATE("v_1_",A13) -> v_1_0011 | C13: B02.00 | D13: =VLOOKUP(CONCATENATE(C13,"_",E13),'Data types'!A:E,4,FALSE) -> 0120 | E13: Outstanding amount | F13: =VLOOKUP(CONCATENATE(C13,"_",E13),'Data types'!A:F,6,FALSE) -> Numeric: 2 decimals | H13: X | I13: Test for missing values. | J13: Rule applicable only if c0250 != ("Structured" OR "Only structured coupon") | K13: Missing value (warning only). For structured liabilities, the field has to be reported if the information exists.
A14: 0012 | B14: =CONCATENATE("v_1_",A14) -> v_1_0012 | C14: B02.00 | D14: =VLOOKUP(CONCATENATE(C14,"_",E14),'Data types'!A:E,4,FALSE) -> 0130 | E14: Relevant amount for Bail-in/WDC | F14: =VLOOKUP(CONCATENATE(C14,"_",E14),'Data types'!A:F,6,FALSE) -> Numeric: 2 decimals | G14: X | I14: Test for missing values. | K14: Missing value. The field must be reported.
A15: 0013 | B15: =CONCATENATE("v_1_",A15) -> v_1_0013 | C15: B02.00 | D15: =VLOOKUP(CONCATENATE(C15,"_",E15),'Data types'!A:E,4,FALSE) -> 0140 | E15: Nature of the liability | F15: =VLOOKUP(CONCATENATE(C15,"_",E15),'Data types'!A:F,6,FALSE) -> String: Drop-down | G15: X | I15: Test for missing values. | K15: Missing value. The field must be reported.
A16: 0014 | B16: =CONCATENATE("v_1_",A16) -> v_1_0014 | C16: B02.00 | D16: =VLOOKUP(CONCATENATE(C16,"_",E16),'Data types'!A:E,4,FALSE) -> 0141 | E16: Nature of the liability (if other) | F16: =VLOOKUP(CONCATENATE(C16,"_",E16),'Data types'!A:F,6,FALSE) -> String: Free text | G16: X | I16: Test for missing values. | J16: Rule applicable only if c0140 = "Other". | K16: Missing value. The field must be reported if option "Other" has been selected in c0140.
A17: 0015 | B17: =CONCATENATE("v_1_",A17) -> v_1_0015 | C17: B02.00 | D17: =VLOOKUP(CONCATENATE(C17,"_",E17),'Data types'!A:E,4,FALSE) -> 0160 | E17: Insolvency ranking | F17: =VLOOKUP(CONCATENATE(C17,"_",E17),'Data types'!A:F,6,FALSE) -> Numeric: Integer | G17: X | I17: Test for missing values. | K17: Missing value. The field must be reported.
A18: 0016 | B18: =CONCATENATE("v_1_",A18) -> v_1_0016 | C18: B02.00 | D18: =VLOOKUP(CONCATENATE(C18,"_",E18),'Data types'!A:E,4,FALSE) -> 0162 | E18: Bail-in cascade | F18: =VLOOKUP(CONCATENATE(C18,"_",E18),'Data types'!A:F,6,FALSE) -> String: Fixed values | G18: X | I18: Test for missing values. | K18: Missing value. The field must be reported.
A19: 0017 | B19: =CONCATENATE("v_1_",A19) -> v_1_0017 | C19: B02.00 | D19: =VLOOKUP(CONCATENATE(C19,"_",E19),'Data types'!A:E,4,FALSE) -> 0180 | E19: Date of the next interest payment | F19: =VLOOKUP(CONCATENATE(C19,"_",E19),'Data types'!A:F,6,FALSE) -> Date: yyyy-mm-dd | G19: X | I19: Test for missing values. | J19: Rule applicable if c0250 = ("Non-Structured/Vanilla" OR "Other non-standard terms") AND c0240 != "ZCB issued at discount" | K19: Missing value. For non-structured liabilities that are not zero coupon bonds issued at discount, this field is must be reported.
A20: 0018 | B20: =CONCATENATE("v_1_",A20) -> v_1_0018 | C20: B02.00 | D20: =VLOOKUP(CONCATENATE(C20,"_",E20),'Data types'!A:E,4,FALSE) -> 0180 | E20: Date of the next interest payment | F20: =VLOOKUP(CONCATENATE(C20,"_",E20),'Data types'!A:F,6,FALSE) -> Date: yyyy-mm-dd | H20: X | I20: Test for missing values. | J20: Rule applicable only if c0250 != ("Structured" OR "Only structured coupon") | K20: Missing value (warning only). For structured liabilities, this field should be reported only if the information exists..
A21: 0019 | B21: =CONCATENATE("v_1_",A21) -> v_1_0019 | C21: B02.00 | D21: =VLOOKUP(CONCATENATE(C21,"_",E21),'Data types'!A:E,4,FALSE) -> 0200 | E21: Earliest redemption date | F21: =VLOOKUP(CONCATENATE(C21,"_",E21),'Data types'!A:F,6,FALSE) -> Date: yyyy-mm-dd | H21: X | I21: Test for missing values. | K21: Missing value (warning only). This field needs to be reported if the information exists.
A22: 0020 | B22: =CONCATENATE("v_1_",A22) -> v_1_0020 | C22: B02.00 | D22: =VLOOKUP(CONCATENATE(C22,"_",E22),'Data types'!A:E,4,FALSE) -> 0210 | E22: Legal maturity | F22: =VLOOKUP(CONCATENATE(C22,"_",E22),'Data types'!A:F,6,FALSE) -> Date: yyyy-mm-dd | G22: X | I22: Test for missing values. | J22: Rule applicable if c0140 != "Cash account/saving account". | K22: Missing value.For liabilities other than of the type "Cash account/savings account, the field must be reported.
A23: 0021 | B23: =CONCATENATE("v_1_",A23) -> v_1_0021 | C23: B02.00 | D23: =VLOOKUP(CONCATENATE(C23,"_",E23),'Data types'!A:E,4,FALSE) -> 0220 | E23: Governing law | F23: =VLOOKUP(CONCATENATE(C23,"_",E23),'Data types'!A:F,6,FALSE) -> String: ISO 3166-1 alpha 2 / ISO 3166-2 | G23: X | I23: Test for missing values. | K23: Missing value. The field must be reported.
A24: 0022 | B24: =CONCATENATE("v_1_",A24) -> v_1_0022 | C24: B02.00 | D24: =VLOOKUP(CONCATENATE(C24,"_",E24),'Data types'!A:E,4,FALSE) -> 0250 | E24: Structured product | F24: =VLOOKUP(CONCATENATE(C24,"_",E24),'Data types'!A:F,6,FALSE) -> String: Drop-down | G24: X | I24: Test for missing values. | K24: Missing value. The field must be reported.
A25: 0023 | B25: =CONCATENATE("v_1_",A25) -> v_1_0023 | C25: B02.00 | D25: =VLOOKUP(CONCATENATE(C25,"_",E25),'Data types'!A:E,4,FALSE) -> 0260 | E25: Guaranteed minimum repayment amount of the structured product | F25: =VLOOKUP(CONCATENATE(C25,"_",E25),'Data types'!A:F,6,FALSE) -> Numeric: 2 decimals | H25: X | I25: Test for missing values. | J25: Rule applicable only if c0250 = ("Structured" OR "Structured coupon only") | K25: Missing value (warning only). For structured liabilities, this field should be reported if the information exists..
A26: 0024 | B26: =CONCATENATE("v_1_",A26) -> v_1_0024 | C26: B02.00 | D26: =VLOOKUP(CONCATENATE(C26,"_",E26),'Data types'!A:E,4,FALSE) -> 0270 | E26: Fair value of the structured product | F26: =VLOOKUP(CONCATENATE(C26,"_",E26),'Data types'!A:F,6,FALSE) -> Numeric: 2 decimals | G26: X | I26: Test for missing values. | J26: Rule applicable only if c0250 = ("Structured" OR "Structured coupon only") | K26: Missing value. The field must be reported for structured products.
A27: 0025 | B27: =CONCATENATE("v_1_",A27) -> v_1_0025 | C27: B02.00 | D27: =VLOOKUP(CONCATENATE(C27,"_",E27),'Data types'!A:E,4,FALSE) -> 0300 | E27: Covered portion of eligible deposits | F27: =VLOOKUP(CONCATENATE(C27,"_",E27),'Data types'!A:F,6,FALSE) -> Numeric: 2 decimals | G27: X | I27: Test for missing values. | J27: Rule applicable only if c0280 = "TRUE" or c0290 = "TRUE". | K27: Missing value. The field must be reported for eligible deposits. If the value is zero, "0" should be entered.
A28: 0026 | B28: =CONCATENATE("v_1_",A28) -> v_1_0026 | C28: B02.00 | D28: =VLOOKUP(CONCATENATE(C28,"_",E28),'Data types'!A:E,4,FALSE) -> 0310 | E28: Secured/Unsecured | F28: =VLOOKUP(CONCATENATE(C28,"_",E28),'Data types'!A:F,6,FALSE) -> String: Drop-down | G28: X | I28: Test for missing values. | K28: Missing value. The field must be reported.
A29: 0027 | B29: =CONCATENATE("v_1_",A29) -> v_1_0027 | C29: B02.00 | D29: =VLOOKUP(CONCATENATE(C29,"_",E29),'Data types'!A:E,4,FALSE) -> 0320 | E29: Amount of pledge, lien or collateral based on the current internal valuation | F29: =VLOOKUP(CONCATENATE(C29,"_",E29),'Data types'!A:F,6,FALSE) -> Numeric: 2 decimals | G29: X | I29: Test for missing values. | J29: Rule applicable only if c0310 = "Secured" | K29: Missing value. The field must be reported for secured products. If the value is zero, "0" should be entered.
A30: 0028 | B30: =CONCATENATE("v_1_",A30) -> v_1_0028 | C30: B02.00 | D30: =VLOOKUP(CONCATENATE(C30,"_",E30),'Data types'!A:E,4,FALSE) -> 0330 | E30: Amount of the uncollateralized part | F30: =VLOOKUP(CONCATENATE(C30,"_",E30),'Data types'!A:F,6,FALSE) -> Numeric: 2 decimals | G30: X | I30: Test for missing values. | J30: Rule applicable only if c0310 = "Secured" | K30: Missing value. The field must be reported for secured products.
A31: 0029 | B31: =CONCATENATE("v_1_",A31) -> v_1_0029 | C31: B02.00 | D31: =VLOOKUP(CONCATENATE(C31,"_",E31),'Data types'!A:E,4,FALSE) -> 0350 | E31: Type of the collateral | F31: =VLOOKUP(CONCATENATE(C31,"_",E31),'Data types'!A:F,6,FALSE) -> String: Drop-down | G31: X | I31: Test for missing values. | J31: Rule applicable only if c0310 = "Secured" | K31: Missing value. The field must be reported for secured products.
A32: 0030 | B32: =CONCATENATE("v_1_",A32) -> v_1_0030 | C32: B02.00 | D32: =VLOOKUP(CONCATENATE(C32,"_",E32),'Data types'!A:E,4,FALSE) -> 0351 | E32: Type of the collateral (if other) | F32: =VLOOKUP(CONCATENATE(C32,"_",E32),'Data types'!A:F,6,FALSE) -> String: Free text | G32: X | I32: Test for missing values. | J32: Rule applicable only if c0350 = "Other" | K32: Missing value (warning). The field should be reported if c0350 = "Other".
A33: 0031 | B33: =CONCATENATE("v_1_",A33) -> v_1_0031 | C33: B02.00 | D33: =VLOOKUP(CONCATENATE(C33,"_",E33),'Data types'!A:E,4,FALSE) -> 0370 | E33: Denomination / Nominal value per security in EUR | F33: =VLOOKUP(CONCATENATE(C33,"_",E33),'Data types'!A:F,6,FALSE) -> Numeric: 2 decimals | G33: X | I33: Test for missing values. | J33: Rule applicable only if c0040 = "ISIN" and c0360 = "Nominal" | K33: Missing value. The field must be reported for securities with trading-method = "Nominal".
A34: 0032 | B34: =CONCATENATE("v_1_",A34) -> v_1_0032 | C34: B02.00 | D34: =VLOOKUP(CONCATENATE(C34,"_",E34),'Data types'!A:E,4,FALSE) -> 0370 | E34: Denomination / Nominal value per security in EUR | F34: =VLOOKUP(CONCATENATE(C34,"_",E34),'Data types'!A:F,6,FALSE) -> Numeric: 2 decimals | H34: X | J34: Rule applicable only if c0040 = "ISIN" and c0360 = "Unit" | K34: Missing value (warning only). The field should be reported for securities with trading-method = "Unit" if the information exists.
A35: 0033 | B35: =CONCATENATE("v_1_",A35) -> v_1_0033 | C35: B02.00 | D35: =VLOOKUP(CONCATENATE(C35,"_",E35),'Data types'!A:E,4,FALSE) -> 0390 | E35: Number of securities outstanding not held by the reporting entity | F35: =VLOOKUP(CONCATENATE(C35,"_",E35),'Data types'!A:F,6,FALSE) -> Numeric: Integer | G35: X | I35: Test for missing values. | J35: Rule applicable only if c0040 = "ISIN". | K35: Missing value. The field must be reported when c0040 = "ISIN". If the value is zero, "0" must be entered.
A36: 0034 | B36: =CONCATENATE("v_1_",A36) -> v_1_0034 | C36: B02.00 | D36: =VLOOKUP(CONCATENATE(C36,"_",E36),'Data types'!A:E,4,FALSE) -> 0391 | E36: Number of securities outstanding held by the reporting entity | F36: =VLOOKUP(CONCATENATE(C36,"_",E36),'Data types'!A:F,6,FALSE) -> Numeric: Integer | G36: X | I36: Test for missing values. | J36: Rule applicable only if c0040 = "ISIN". | K36: Missing value. The field must be reported for securities. If the value is zero, "0" must be entered.
A37: 0035 | B37: =CONCATENATE("v_1_",A37) -> v_1_0035 | C37: B02.00 | D37: =VLOOKUP(CONCATENATE(C37,"_",E37),'Data types'!A:E,4,FALSE) -> 0400 | E37: Accrued interest per security | F37: =VLOOKUP(CONCATENATE(C37,"_",E37),'Data types'!A:F,6,FALSE) -> Numeric: 4 decimals | G37: X | I37: Test for missing values. | J37: Rule applicable if c0040 = "ISIN", c0250 = ("Non-Structured/Vanilla" OR "Other non-standard terms) AND c0240 != "ZCB issued at discount" | K37: Missing value. The field must be reported for non-structured securities that are not zero coupon bonds issued at discount.
A38: 0036 | B38: =CONCATENATE("v_1_",A38) -> v_1_0036 | C38: B02.00 | D38: =VLOOKUP(CONCATENATE(C38,"_",E38),'Data types'!A:E,4,FALSE) -> 0400 | E38: Accrued interest per security | F38: =VLOOKUP(CONCATENATE(C38,"_",E38),'Data types'!A:F,6,FALSE) -> Numeric: 4 decimals | H38: X | I38: Test for missing values. | J38: Rule applicable if c0040 = "ISIN", c0250 != ("Structured" OR "Only structured coupon") | K38: Missing value (warning only). This field must be reported for structured securities if the information exists.
A39: 0037 | B39: =CONCATENATE("v_1_",A39) -> v_1_0037 | C39: B02.00 | D39: =VLOOKUP(CONCATENATE(C39,"_",E39),'Data types'!A:E,4,FALSE) -> 0610 | E39: Carrying amount IFRS | F39: =VLOOKUP(CONCATENATE(C39,"_",E39),'Data types'!A:F,6,FALSE) -> Numeric: 2 decimals | H39: X | I39: Test for missing values. | K39: Missing value (warning only). The field must be reported if the information exists, i.e. the entity reports in IFRS.
A40: 0038 | B40: =CONCATENATE("v_1_",A40) -> v_1_0038 | C40: B02.00 | D40: =VLOOKUP(CONCATENATE(C40,"_",E40),'Data types'!A:E,4,FALSE) -> 5000 | E40: Instrument/liability is issued to or bought by an existing shareholder that is not part of the same resolution group | F40: =VLOOKUP(CONCATENATE(C40,"_",E40),'Data types'!A:F,6,FALSE) -> String: TRUE / FALSE boolean | G40: X | I40: Test for missing values. | J40: if {B99.00;c0060} = "Non-Resolution Entity" | K40: Missing value. The field must be reported for Non-Resolution Entities.
A41: 0039 | B41: =CONCATENATE("v_1_",A41) -> v_1_0039 | C41: B02.00 | D41: =VLOOKUP(CONCATENATE(C41,"_",E41),'Data types'!A:E,4,FALSE) -> 5010 | E41: Instrument/liability meets the requirements of Art. 21(7a) SRMR | F41: =VLOOKUP(CONCATENATE(C41,"_",E41),'Data types'!A:F,6,FALSE) -> String: TRUE / FALSE boolean | G41: X | I41: Test for missing values. | J41: if {B99.00;c0060} = "Non-Resolution Entity" | K41: Missing value. The field must be reported for Non-Resolution Entities.
A42: 0056 | B42: =CONCATENATE("v_1_",A42) -> v_1_0056 | C42: B90.00 | D42: =VLOOKUP(CONCATENATE(C42,"_",E42),'Data types'!A:E,4,FALSE) -> 0030 | E42: Counterparty within the resolution group | F42: =VLOOKUP(CONCATENATE(C42,"_",E42),'Data types'!A:F,6,FALSE) -> String: Drop-down | G42: X | I42: Test for missing values. | K42: Missing value. The field must be reported.

Sheet Aux Validations
A1: v_1_0013 | D1: v_1_0022
A3: Nature of the liability | D3: Structured product
A4: Registered Bond | B4: 1 | D4: Non-structured/Vanilla | E4: 1
A5: Bearer Bond | B5: 1 | D5: Structured | E5: 1
A6: Borrower Note Loan | B6: 1 | D6: Other non-standard terms | E6: 1
A7: Certificate of Deposit / Commercial paper | B7: 1 | D7: Only structured coupon | E7: 1
A8: Title of ownership | B8: 1 | D8: Aggregated | E8: 1
A9: Cash account/saving account | B9: 1
A10: Term deposit | B10: 1
A11: Loan | B11: 1
A12: Bill of exchange | B12: 1
A13: Other | B13: 1

Sheet Level 2 Guidance
B1: Level 2 Validation Rules: internal consistency checks.
B2: Check ID | C2: Tab | D2: Data point (Row/Column) | E2: Data point (Label) | F2: Data point type | G2: High severity (i.e the validation rule should in general not be breached) | H2: Warning only (i.e. the validation rule can be breached in certain cases) | I2: Type of test | J2: Prerequisites | K2: Explanation
A3: 0001 | B3: =CONCATENATE("v_2_",A3) -> v_2_0001 | C3: B02.00 | D3: =VLOOKUP(CONCATENATE(C3,"_",E3),'Data types'!A:E,4,FALSE) -> 0030 | E3: Unique identification number (known to the counterparty) | F3: =VLOOKUP(CONCATENATE(C3,"_",E3),'Data types'!A:F,6,FALSE) -> String: Free text | G3: X | I3: The field must have the characteristics of an ISIN, e.g., max. 12 characters and start with 2 letters signifying the ISO country code. | J3: c0040 = "ISIN" | K3: If the ID is an ISIN (c0030 = "ISIN"), then the ID reported in c0020 must have the characteristics of an ISIN, e.g. 12 characters and start with 2 letters signifying the ISO country code.
A4: 0003 | B4: =CONCATENATE("v_2_",A4) -> v_2_0003 | C4: B02.00 | D4: =VLOOKUP(CONCATENATE(C4,"_",E4),'Data types'!A:E,4,FALSE) -> 0070 | E4: Contract Currency | F4: =VLOOKUP(CONCATENATE(C4,"_",E4),'Data types'!A:F,6,FALSE) -> String: 3-letters ISO 4217 | G4: X | I4: Check if the reported field respect the 3-letters ISO 4217 code. | J4: c0020 ≠ (NCNP OR NCBP) | K4: Currencies must be reported using the 3-letters ISO 4217 code.
A5: 0004 | B5: =CONCATENATE("v_2_",A5) -> v_2_0004 | C5: B02.00 | D5: =VLOOKUP(CONCATENATE(C5,"_",E5),'Data types'!A:E,4,FALSE) -> 0080 | E5: Outstanding principal amount | F5: =VLOOKUP(CONCATENATE(C5,"_",E5),'Data types'!A:F,6,FALSE) -> Numeric: 2 decimals | H5: X | I5: Check if the reported field is higher than 0. | K5: The reported amount must in general be positive.
A6: 0005 | B6: =CONCATENATE("v_2_",A6) -> v_2_0005 | C6: B02.00 | D6: =VLOOKUP(CONCATENATE(C6,"_",E6),'Data types'!A:E,4,FALSE) -> 0090 | E6: Portion of instrument or liability held by the reporting entity | F6: =VLOOKUP(CONCATENATE(C6,"_",E6),'Data types'!A:F,6,FALSE) -> Numeric: 2 decimals | G6: X | I6: Check if the reported field is higher than or equal 0. | J6: c0040 = "ISIN" | K6: The reported amount must be positive or zero.
A7: 0006 | B7: =CONCATENATE("v_2_",A7) -> v_2_0006 | C7: B02.00 | D7: =VLOOKUP(CONCATENATE(C7,"_",E7),'Data types'!A:E,4,FALSE) -> 0100 | E7: Accrued interest | F7: =VLOOKUP(CONCATENATE(C7,"_",E7),'Data types'!A:F,6,FALSE) -> Numeric: 2 decimals | H7: X | I7: Check if the reported field is higher than or equal 0. | K7: The reported amount should be positive or zero. However, negative accrued interests are in principle allowed, if duly justified by the reporting entity.
A8: 0007 | B8: =CONCATENATE("v_2_",A8) -> v_2_0007 | C8: B02.00 | D8: =VLOOKUP(CONCATENATE(C8,"_",E8),'Data types'!A:E,4,FALSE) -> 0110 | E8: Applicable fees and charges | F8: =VLOOKUP(CONCATENATE(C8,"_",E8),'Data types'!A:F,6,FALSE) -> Numeric: 2 decimals | H8: X | I8: Check if the reported field is higher than or equal 0. | K8: The reported amount should be in general positive or zero.
A9: 0008 | B9: =CONCATENATE("v_2_",A9) -> v_2_0008 | C9: B02.00 | D9: =VLOOKUP(CONCATENATE(C9,"_",E9),'Data types'!A:E,4,FALSE) -> 0120 | E9: Outstanding amount | F9: =VLOOKUP(CONCATENATE(C9,"_",E9),'Data types'!A:F,6,FALSE) -> Numeric: 2 decimals | G9: X | I9: Check if the reported field is higher than 0. | K9: The reported amount should be positive.
A10: 0009 | B10: =CONCATENATE("v_2_",A10) -> v_2_0009 | C10: B02.00 | D10: =VLOOKUP(CONCATENATE(C10,"_",E10),'Data types'!A:E,4,FALSE) -> 0120 | E10: Outstanding amount | F10: =VLOOKUP(CONCATENATE(C10,"_",E10),'Data types'!A:F,6,FALSE) -> Numeric: 2 decimals | G10: X | I10: Check if the reported field is equal to c0080 + c0100 + c0110. | K10: The reported amount should be equal to: c0080 + c0100 + c0110.
A11: 0011 | B11: =CONCATENATE("v_2_",A11) -> v_2_0011 | C11: B02.00 | D11: =VLOOKUP(CONCATENATE(C11,"_",E11),'Data types'!A:E,4,FALSE) -> 0130 | E11: Relevant amount for Bail-in/WDC | F11: =VLOOKUP(CONCATENATE(C11,"_",E11),'Data types'!A:F,6,FALSE) -> Numeric: 2 decimals | G11: X | I11: Check if the reported field is equal to of: max{0, c0120 - c0300 - c0320}. | J11: c0250 = ("Non-structured/Vanilla" OR "Other non-standard terms") & c0240 != "ZCB issued at discount" | K11: The reported amount should be equal to: c0120 - c0300 - c0320, besides for Zero Coupon Bonds for which specific provisions may apply.
A12: 0012 | B12: =CONCATENATE("v_2_",A12) -> v_2_0012 | C12: B02.00 | D12: =VLOOKUP(CONCATENATE(C12,"_",E12),'Data types'!A:E,4,FALSE) -> 0130 | E12: Relevant amount for Bail-in/WDC | F12: =VLOOKUP(CONCATENATE(C12,"_",E12),'Data types'!A:F,6,FALSE) -> Numeric: 2 decimals | G12: X | I12: Check if the reported field is either equal to max(0, c0270 - c0300 - c0320) OR equal to max(0, c0120 - c0300 - c0320) | J12: c0250 = ( "Structured" OR "Structured coupon only") | K12: For structured products, the reported amount should be equal to: (c0270 - c0300 - c0320) if the fair value is used to support the determination of the relevant amount for bail-in, OR (c0120 - c0300 - c0320) if not.
A13: 0013 | B13: =CONCATENATE("v_2_",A13) -> v_2_0013 | C13: B02.00 | D13: =VLOOKUP(CONCATENATE(C13,"_",E13),'Data types'!A:E,4,FALSE) -> 0140 | E13: Nature of the liability | F13: =VLOOKUP(CONCATENATE(C13,"_",E13),'Data types'!A:F,6,FALSE) -> String: Drop-down | G13: X | I13: Drop down values must be respected. | K13: The drop down values must be respected.
A14: 0014 | B14: =CONCATENATE("v_2_",A14) -> v_2_0014 | C14: B02.00 | D14: =VLOOKUP(CONCATENATE(C14,"_",E14),'Data types'!A:E,4,FALSE) -> 0160 | E14: Insolvency ranking | F14: =VLOOKUP(CONCATENATE(C14,"_",E14),'Data types'!A:F,6,FALSE) -> Numeric: Integer | G14: X | I14: Numeric integer values from 1 onwards must be reported. | K14: Numeric values from 1 onwards must be reported.
A15: 0015 | B15: =CONCATENATE("v_2_",A15) -> v_2_0015 | C15: B02.00 | D15: =VLOOKUP(CONCATENATE(C15,"_",E15),'Data types'!A:E,4,FALSE) -> 0170 | E15: Date of issuance | F15: =VLOOKUP(CONCATENATE(C15,"_",E15),'Data types'!A:F,6,FALSE) -> Date: yyyy-mm-dd | G15: X | I15: The reported value must be a date (yyyy-mm-gg). | J15: (c0020 ≠ "NCNP" OR "NCBP") | K15: The reported value must be a date (yyyy-mm-gg).
A16: 0016 | B16: =CONCATENATE("v_2_",A16) -> v_2_0016 | C16: B02.00 | D16: =VLOOKUP(CONCATENATE(C16,"_",E16),'Data types'!A:E,4,FALSE) -> 0170 | E16: Date of issuance | F16: =VLOOKUP(CONCATENATE(C16,"_",E16),'Data types'!A:F,6,FALSE) -> Date: yyyy-mm-dd | G16: X | I16: The reported value must be before the Date of the next (partial) redemption payment (c0190) and the earliest redemption date (c0200). | J16: (c0190 or c0200) are reported & (c0020 ≠ "NCNP" OR "NCBP") | K16: The reported value must be before the Date of the next (partial) redemption payment (c0190) and the earliest redemption date (c0200).
A17: 0017 | B17: =CONCATENATE("v_2_",A17) -> v_2_0017 | C17: B02.00 | D17: =VLOOKUP(CONCATENATE(C17,"_",E17),'Data types'!A:E,4,FALSE) -> 0180 | E17: Date of the next interest payment | F17: =VLOOKUP(CONCATENATE(C17,"_",E17),'Data types'!A:F,6,FALSE) -> Date: yyyy-mm-dd | G17: X | I17: The reported value must be a date (yyyy-mm-gg). | J17: (c0020 ≠ "NCNP" OR "NCBP") | K17: The reported value must be a date (yyyy-mm-gg).
A18: 0018 | B18: =CONCATENATE("v_2_",A18) -> v_2_0018 | C18: B02.00 | D18: =VLOOKUP(CONCATENATE(C18,"_",E18),'Data types'!A:E,4,FALSE) -> 0180 | E18: Date of the next interest payment | F18: =VLOOKUP(CONCATENATE(C18,"_",E18),'Data types'!A:F,6,FALSE) -> Date: yyyy-mm-dd | G18: X | I18: The reported value must be after the reference date reported in B99.00 (c0070). | J18: {B99.00;c0070} is reported & (c0020 ≠ "NCNP" OR "NCBP") | K18: The reported value must be after the reference date reported in B99.00 (c0070).
A19: 0019 | B19: =CONCATENATE("v_2_",A19) -> v_2_0019 | C19: B02.00 | D19: =VLOOKUP(CONCATENATE(C19,"_",E19),'Data types'!A:E,4,FALSE) -> 0200 | E19: Earliest redemption date | F19: =VLOOKUP(CONCATENATE(C19,"_",E19),'Data types'!A:F,6,FALSE) -> Date: yyyy-mm-dd | G19: X | I19: The reported value must be a date (yyyy-mm-gg). | J19: (c0020 ≠ "NCNP" OR "NCBP") | K19: The reported value must be a date (yyyy-mm-gg).
A20: 0020 | B20: =CONCATENATE("v_2_",A20) -> v_2_0020 | C20: B02.00 | D20: =VLOOKUP(CONCATENATE(C20,"_",E20),'Data types'!A:E,4,FALSE) -> 0200 | E20: Earliest redemption date | F20: =VLOOKUP(CONCATENATE(C20,"_",E20),'Data types'!A:F,6,FALSE) -> Date: yyyy-mm-dd | G20: X | I20: The reported value must be after the reference date reported in B99.00 (c0070). | J20: {B99.00;c0070} is reported & (c0020 ≠ "NCNP" OR "NCBP") | K20: The reported value must be after the reference date reported in B99.00 (c0070).
A21: 0021 | B21: =CONCATENATE("v_2_",A21) -> v_2_0021 | C21: B02.00 | D21: =VLOOKUP(CONCATENATE(C21,"_",E21),'Data types'!A:E,4,FALSE) -> 0210 | E21: Legal maturity | F21: =VLOOKUP(CONCATENATE(C21,"_",E21),'Data types'!A:F,6,FALSE) -> Date: yyyy-mm-dd | G21: X | I21: The reported value must be a date (yyyy-mm-gg). | J21: (c0020 ≠ "NCNP" OR "NCBP") | K21: The reported value must be a date (yyyy-mm-gg).
A22: 0022 | B22: =CONCATENATE("v_2_",A22) -> v_2_0022 | C22: B02.00 | D22: =VLOOKUP(CONCATENATE(C22,"_",E22),'Data types'!A:E,4,FALSE) -> 0210 | E22: Legal maturity | F22: =VLOOKUP(CONCATENATE(C22,"_",E22),'Data types'!A:F,6,FALSE) -> Date: yyyy-mm-dd | G22: X | I22: The reported value must be after the reference date reported in B99.00 (c0070). | J22: {B99.00;c0070} is reported & (c0020 ≠ "NCNP" OR "NCBP") | K22: The reported value must be after the reference date reported in B99.00 (c0070).
A23: 0023 | B23: =CONCATENATE("v_2_",A23) -> v_2_0023 | C23: B02.00 | D23: =VLOOKUP(CONCATENATE(C23,"_",E23),'Data types'!A:E,4,FALSE) -> 0220 | E23: Governing law | F23: =VLOOKUP(CONCATENATE(C23,"_",E23),'Data types'!A:F,6,FALSE) -> String: ISO 3166-1 alpha 2 / ISO 3166-2 | G23: X | I23: Check if the reported field respects the ISO 3166-1 alpha-2 code or 3166-2 | J23: (c0020 ≠ "NCNP" OR "NCBP") | K23: Governing law must be reported using the ISO 3166-1 alpha-2 code.
A24: 0024 | B24: =CONCATENATE("v_2_",A24) -> v_2_0024 | C24: B02.00 | D24: =VLOOKUP(CONCATENATE(C24,"_",E24),'Data types'!A:E,4,FALSE) -> 0230 | E24: Bail-in recognition clause | F24: =VLOOKUP(CONCATENATE(C24,"_",E24),'Data types'!A:F,6,FALSE) -> String: Drop-down | G24: X | I24: Drop down values must be respected. | J24: (c0020 ≠ "NCNP" OR "NCBP") | K24: The drop down values must be respected.
A25: 0025 | B25: =CONCATENATE("v_2_",A25) -> v_2_0025 | C25: B02.00 | D25: =VLOOKUP(CONCATENATE(C25,"_",E25),'Data types'!A:E,4,FALSE) -> 0250 | E25: Structured product | F25: =VLOOKUP(CONCATENATE(C25,"_",E25),'Data types'!A:F,6,FALSE) -> String: Drop-down | G25: X | I25: Drop down values must be respected. | K25: The drop down values must be respected.
A26: 0026 | B26: =CONCATENATE("v_2_",A26) -> v_2_0026 | C26: B02.00 | D26: =VLOOKUP(CONCATENATE(C26,"_",E26),'Data types'!A:E,4,FALSE) -> 0310 | E26: Secured/Unsecured | F26: =VLOOKUP(CONCATENATE(C26,"_",E26),'Data types'!A:F,6,FALSE) -> String: Drop-down | G26: X | I26: Drop down values must be respected. | K26: The drop down values must be respected.
A27: 0027 | B27: =CONCATENATE("v_2_",A27) -> v_2_0027 | C27: B02.00 | D27: =VLOOKUP(CONCATENATE(C27,"_",E27),'Data types'!A:E,4,FALSE) -> 0330 | E27: Amount of the uncollateralized part | F27: =VLOOKUP(CONCATENATE(C27,"_",E27),'Data types'!A:F,6,FALSE) -> Numeric: 2 decimals | G27: X | I27: Check if the reported field is equal to: max(0,c0120 - c0320.) | J27: c0310 = "Secured" & c0250 = ( "Non-structured/Vanilla"OR "Other non-standard terms") AND c0240 !="ZCB issued at discount" | K27: The reported field should be equal to: c0120 - c0320.
A28: 0028 | B28: =CONCATENATE("v_2_",A28) -> v_2_0028 | C28: B02.00 | D28: =VLOOKUP(CONCATENATE(C28,"_",E28),'Data types'!A:E,4,FALSE) -> 0330 | E28: Amount of the uncollateralized part | F28: =VLOOKUP(CONCATENATE(C28,"_",E28),'Data types'!A:F,6,FALSE) -> Numeric: 2 decimals | G28: X | I28: Check if the reported field is either max(0, c0270 - c0320) or max (0, c0120 - c0320) | J28: c0310 = "Secured" & c0250 = ("Structured" OR "Only structured coupon") | K28: The reported field should be equal to (c0270 - c0320) if the fair value is used, or equal to (c0120 - c0320) otherwise
A29: 0029 | B29: =CONCATENATE("v_2_",A29) -> v_2_0029 | C29: B02.00 | D29: =VLOOKUP(CONCATENATE(C29,"_",E29),'Data types'!A:E,4,FALSE) -> 0350 | E29: Type of the collateral | F29: =VLOOKUP(CONCATENATE(C29,"_",E29),'Data types'!A:F,6,FALSE) -> String: Drop-down | G29: X | I29: Drop down values must be respected. | K29: The drop down values must be respected.
A30: 0030 | B30: =CONCATENATE("v_2_",A30) -> v_2_0030 | C30: B02.00 | D30: =VLOOKUP(CONCATENATE(C30,"_",E30),'Data types'!A:E,4,FALSE) -> 0350 | E30: Type of the collateral | F30: =VLOOKUP(CONCATENATE(C30,"_",E30),'Data types'!A:F,6,FALSE) -> String: Drop-down | G30: X | I30: "Not applicable" must be reported. | J30: c0310 = "Unsecured" | K30: The field must be "Not applicable" if c0310 is unsecured.
A31: 0031 | B31: =CONCATENATE("v_2_",A31) -> v_2_0031 | C31: B02.00 | D31: =VLOOKUP(CONCATENATE(C31,"_",E31),'Data types'!A:E,4,FALSE) -> 0440 | E31: Nature of the global note | F31: =VLOOKUP(CONCATENATE(C31,"_",E31),'Data types'!A:F,6,FALSE) -> String: Drop-down | G31: X | I31: Drop down values must be respected. | K31: The drop down values must be respected.
A32: 0032 | B32: =CONCATENATE("v_2_",A32) -> v_2_0032 | C32: B02.00 | D32: =VLOOKUP(CONCATENATE(C32,"_",E32),'Data types'!A:E,4,FALSE) -> 0530 | E32: Type of own funds at individual level | F32: =VLOOKUP(CONCATENATE(C32,"_",E32),'Data types'!A:F,6,FALSE) -> String: Drop-down | G32: X | I32: Drop down values must be respected. | K32: The drop down values must be respected.
A33: 0033 | B33: =CONCATENATE("v_2_",A33) -> v_2_0033 | C33: B02.00 | D33: =VLOOKUP(CONCATENATE(C33,"_",E33),'Data types'!A:E,4,FALSE) -> 0540 | E33: Eligible amount for own funds at individual level | F33: =VLOOKUP(CONCATENATE(C33,"_",E33),'Data types'!A:F,6,FALSE) -> Numeric: 2 decimals | G33: X | I33: Check if the reported field is higher than or equal 0. | K33: The reported amount should be positive or zero.
A34: 0034 | B34: =CONCATENATE("v_2_",A34) -> v_2_0034 | C34: B02.00 | D34: =VLOOKUP(CONCATENATE(C34,"_",E34),'Data types'!A:E,4,FALSE) -> 0550 | E34: Type of own funds at consolidated level | F34: =VLOOKUP(CONCATENATE(C34,"_",E34),'Data types'!A:F,6,FALSE) -> String: Drop-down | G34: X | I34: Drop down values must be respected. | K34: The drop down values must be respected.
A35: 0035 | B35: =CONCATENATE("v_2_",A35) -> v_2_0035 | C35: B02.00 | D35: =VLOOKUP(CONCATENATE(C35,"_",E35),'Data types'!A:E,4,FALSE) -> 0560 | E35: Eligible amount for own funds at consolidated level | F35: =VLOOKUP(CONCATENATE(C35,"_",E35),'Data types'!A:F,6,FALSE) -> Numeric: 2 decimals | G35: X | I35: Check if the reported field is higher than or equal 0. | K35: The reported amount should be positive or zero.
A36: 0036 | B36: =CONCATENATE("v_2_",A36) -> v_2_0036 | C36: B02.00 | D36: =VLOOKUP(CONCATENATE(C36,"_",E36),'Data types'!A:E,4,FALSE) -> 0590 | E36: Type of security interest provided by a third party | F36: =VLOOKUP(CONCATENATE(C36,"_",E36),'Data types'!A:F,6,FALSE) -> String: Drop-down | G36: X | I36: Drop down values must be respected. | K36: The drop down values must be respected.
A37: 0037 | B37: =CONCATENATE("v_2_",A37) -> v_2_0037 | C37: B02.00 | D37: =VLOOKUP(CONCATENATE(C37,"_",E37),'Data types'!A:E,4,FALSE) -> 0610 | E37: Carrying amount IFRS | F37: =VLOOKUP(CONCATENATE(C37,"_",E37),'Data types'!A:F,6,FALSE) -> Numeric: 2 decimals | G37: X | I37: Check if the reported field is higher than or equal 0. | K37: The reported amount should be positive or zero.
A38: 0038 | B38: =CONCATENATE("v_2_",A38) -> v_2_0038 | C38: B02.00 | D38: =VLOOKUP(CONCATENATE(C38,"_",E38),'Data types'!A:E,4,FALSE) -> 0620 | E38: Balance sheet item according to IFRS | F38: =VLOOKUP(CONCATENATE(C38,"_",E38),'Data types'!A:F,6,FALSE) -> String: Drop-down | G38: x | I38: Drop down values must be respected. | K38: The drop down values must be respected.
A39: 0058 | B39: =CONCATENATE("v_2_",A39) -> v_2_0058 | C39: B90.00 | D39: =VLOOKUP(CONCATENATE(C39,"_",E39),'Data types'!A:E,4,FALSE) -> 0030 | E39: Counterparty within the resolution group | F39: =VLOOKUP(CONCATENATE(C39,"_",E39),'Data types'!A:F,6,FALSE) -> String: Drop-down | G39: X | I39: Drop down values must be respected. | K39: The drop down values must be respected.
A40: 0059 | B40: =CONCATENATE("v_2_",A40) -> v_2_0059 | C40: B90.00 | D40: =VLOOKUP(CONCATENATE(C40,"_",E40),'Data types'!A:E,4,FALSE) -> 0080 | E40: Counterparty Type | F40: =VLOOKUP(CONCATENATE(C40,"_",E40),'Data types'!A:F,6,FALSE) -> String: Drop-down | G40: X | I40: Drop down values must be respected. | K40: The drop down values must be respected.
A41: 0060 | B41: =CONCATENATE("v_2_",A41) -> v_2_0060 | C41: B90.00 | D41: =VLOOKUP(CONCATENATE(C41,"_",E41),'Data types'!A:E,4,FALSE) -> 0090 | E41: Country of the counterparty | F41: =VLOOKUP(CONCATENATE(C41,"_",E41),'Data types'!A:F,6,FALSE) -> String: ISO 3166-1 | G41: X | I41: Check if the reported field respects the ISO 3166-1 alpha-2 code. | J41: c0080 ≠ "XX" OR "99" | K41: The field must be reported using the ISO 3166-1 alpha-2 code.
A42: 0061 | B42: =CONCATENATE("v_2_",A42) -> v_2_0061 | C42: B90.00 | D42: =VLOOKUP(CONCATENATE(C42,"_",E42),'Data types'!A:E,4,FALSE) -> 0100 | E42: Relevant amount for Bail-in/WDC | F42: =VLOOKUP(CONCATENATE(C42,"_",E42),'Data types'!A:F,6,FALSE) -> Numeric: 2 decimals | H42: X | I42: Check if the reported field is equal 0. | J42: c0030 ≠ "No" | K42: Positive values are allowed in case intragroup liabilities do not meet the conditions set forth in article 44(2)h BRRD and should be duly justified by the reporting entity

Sheet Data types
A1: Tech | B1: Tab | C1: DP | D1: Column | E1: Label | F1: Data type label | G1: Data type | H1: Type of constrain | I1: Treatment of "Not applicable" (if cell is grey out, input is not expected) | J1: Treatment of "Not available" (if cell is grey out, input is not expected)
A2: =CONCATENATE(B2,"_",E2) -> B99.00_Name of Legal Entity | B2: B99.00 | C2: =CONCATENATE(B2,";c",D2) -> B99.00;c0010 | D2: 0010 | E2: Name of Legal Entity | F2: =CONCATENATE(G2,": ",H2) -> String: Free text | G2: String | H2: Free text
A3: =CONCATENATE(B3,"_",E3) -> B99.00_LEI of Legal Entity | B3: B99.00 | C3: =CONCATENATE(B3,";c",D3) -> B99.00;c0020 | D3: 0020 | E3: LEI of Legal Entity | F3: =CONCATENATE(G3,": ",H3) -> String: Free text | G3: String | H3: Free text
A4: =CONCATENATE(B4,"_",E4) -> B99.00_Country of incorporation | B4: B99.00 | C4: =CONCATENATE(B4,";c",D4) -> B99.00;c0030 | D4: 0030 | E4: Country of incorporation | F4: =CONCATENATE(G4,": ",H4) -> String: ISO 3166-1 | G4: String | H4: ISO 3166-1
A5: =CONCATENATE(B5,"_",E5) -> B99.00_Name of the ultimate parent entity | B5: B99.00 | C5: =CONCATENATE(B5,";c",D5) -> B99.00;c0040 | D5: 0040 | E5: Name of the ultimate parent entity | F5: =CONCATENATE(G5,": ",H5) -> String: Free text | G5: String | H5: Free text
A6: =CONCATENATE(B6,"_",E6) -> B99.00_LEI of the ultimate parent entity | B6: B99.00 | C6: =CONCATENATE(B6,";c",D6) -> B99.00;c0041 | D6: 0041 | E6: LEI of the ultimate parent entity | F6: =CONCATENATE(G6,": ",H6) -> String: Free text | G6: String | H6: Free text
A7: =CONCATENATE(B7,"_",E7) -> B99.00_Name of the Resolution Entity | B7: B99.00 | C7: =CONCATENATE(B7,";c",D7) -> B99.00;c0050 | D7: 0050 | E7: Name of the Resolution Entity | F7: =CONCATENATE(G7,": ",H7) -> String: Free text | G7: String | H7: Free text
A8: =CONCATENATE(B8,"_",E8) -> B99.00_LEI of the Resolution Entity | B8: B99.00 | C8: =CONCATENATE(B8,";c",D8) -> B99.00;c0051 | D8: 0051 | E8: LEI of the Resolution Entity | F8: =CONCATENATE(G8,": ",H8) -> String: Free text | G8: String | H8: Free text
A9: =CONCATENATE(B9,"_",E9) -> B99.00_Reporting entity type | B9: B99.00 | C9: =CONCATENATE(B9,";c",D9) -> B99.00;c0060 | D9: 0060 | E9: Reporting entity type | F9: =CONCATENATE(G9,": ",H9) -> String: Drop-down | G9: String | H9: Drop-down
A10: =CONCATENATE(B10,"_",E10) -> B99.00_Reference date | B10: B99.00 | C10: =CONCATENATE(B10,";c",D10) -> B99.00;c0070 | D10: 0070 | E10: Reference date | F10: =CONCATENATE(G10,": ",H10) -> Date: yyyy-mm-dd hh:mm:ss | G10: Date | H10: yyyy-mm-dd hh:mm:ss
A11: =CONCATENATE(B11,"_",E11) -> B99.00_Reported currency | B11: B99.00 | C11: =CONCATENATE(B11,";c",D11) -> B99.00;c0080 | D11: 0080 | E11: Reported currency | F11: =CONCATENATE(G11,": ",H11) -> String: 3-letters ISO 4217 | G11: String | H11: 3-letters ISO 4217
A12: =CONCATENATE(B12,"_",E12) -> B99.00_EUR exchange rate | B12: B99.00 | C12: =CONCATENATE(B12,";c",D12) -> B99.00;c0090 | D12: 0090 | E12: EUR exchange rate | F12: =CONCATENATE(G12,": ",H12) -> Numeric: 4 decimals | G12: Numeric | H12: 4 decimals
A13: =CONCATENATE(B13,"_",E13) -> B01.00_Row number | B13: B01.00 | C13: =CONCATENATE(B13,";c",D13) -> B01.00;c0010 | D13: 0010 | E13: Row number | F13: =CONCATENATE(G13,": ",H13) -> Numeric: Integer | G13: Numeric | H13: Integer
... A16: =CONCATENATE(B16,"_",E16) -> B01.00_Counterparty type | B16: B01.00 | C16: =CONCATENATE(B16,";c",D16) -> B01.00;c0040 | D16: 0040 | E16: Counterparty type | F16: =CONCATENATE(G16,": ",H16) -> String: Drop-down | G16: String | H16: Drop-down
A17: =CONCATENATE(B17,"_",E17) -> B01.00_Relevant amount for Bail-in/WDC | B17: B01.00 | C17: =CONCATENATE(B17,";c",D17) -> B01.00;c0050 | D17: 0050 | E17: Relevant amount for Bail-in/WDC | F17: =CONCATENATE(G17,": ",H17) -> Numeric: 2 decimals | G17: Numeric | H17: 2 decimals | I17: Input "Not applicable"
A18: =CONCATENATE(B18,"_",E18) -> B01.00_Amount excluded from Bail-in/WDC | B18: B01.00 | C18: =CONCATENATE(B18,";c",D18) -> B01.00;c0060 | D18: 0060 | E18: Amount excluded from Bail-in/WDC | F18: =CONCATENATE(G18,": ",H18) -> Numeric: 2 decimals | G18: Numeric | H18: 2 decimals
A19: =CONCATENATE(B19,"_",E19) -> B02.00_Row number | B19: B02.00 | C19: =CONCATENATE(B19,";c",D19) -> B02.00;c0010 | D19: 0010 | E19: Row number | F19: =CONCATENATE(G19,": ",H19) -> Numeric: Integer | G19: Numeric | H19: Integer
A20: =CONCATENATE(B20,"_",E20) -> B02.00_Unique internal identification number | B20: B02.00 | C20: =CONCATENATE(B20,";c",D20) -> B02.00;c0020 | D20: 0020 | E20: Unique internal identification number | F20: =CONCATENATE(G20,": ",H20) -> String: Free text | G20: String | H20: Free text
A21: =CONCATENATE(B21,"_",E21) -> B02.00_Unique identification number (known to the counterparty) | B21: B02.00 | C21: =CONCATENATE(B21,";c",D21) -> B02.00;c0030 | D21: 0030 | E21: Unique identification number (known to the counterparty) | F21: =CONCATENATE(G21,": ",H21) -> String: Free text | G21: String | H21: Free text
A22: =CONCATENATE(B22,"_",E22) -> B02.00_Type of the unique identifier (known to the counterparty) | B22: B02.00 | C22: =CONCATENATE(B22,";c",D22) -> B02.00;c0040 | D22: 0040 | E22: Type of the unique identifier (known to the counterparty) | F22: =CONCATENATE(G22,": ",H22) -> String: Free text, but fixed values for specific items | G22: String | H22: Free text, but fixed values for specific items
A23: =CONCATENATE(B23,"_",E23) -> B02.00_Original amount issued in EUR | B23: B02.00 | C23: =CONCATENATE(B23,";c",D23) -> B02.00;c0050 | D23: 0050 | E23: Original amount issued in EUR | F23: =CONCATENATE(G23,": ",H23) -> Numeric: 2 decimals | G23: Numeric | H23: 2 decimals | I23: Input 999999999999999
A24: =CONCATENATE(B24,"_",E24) -> B02.00_Original amount issued in original currency | B24: B02.00 | C24: =CONCATENATE(B24,";c",D24) -> B02.00;c0060 | D24: 0060 | E24: Original amount issued in original currency | F24: =CONCATENATE(G24,": ",H24) -> Numeric: 2 decimals | G24: Numeric | H24: 2 decimals | I24: Input 999999999999999
A25: =CONCATENATE(B25,"_",E25) -> B02.00_Contract currency | B25: B02.00 | C25: =CONCATENATE(B25,";c",D25) -> B02.00;c0070 | D25: 0070 | E25: Contract currency | F25: =CONCATENATE(G25,": ",H25) -> String: 3-letters ISO 4217 | G25: String | H25: 3-letters ISO 4217 | I25: Input "XXX"
A26: =CONCATENATE(B26,"_",E26) -> B02.00_Outstanding principal amount | B26: B02.00 | C26: =CONCATENATE(B26,";c",D26) -> B02.00;c0080 | D26: 0080 | E26: Outstanding principal amount | F26: =CONCATENATE(G26,": ",H26) -> Numeric: 2 decimals | G26: Numeric | H26: 2 decimals
A27: =CONCATENATE(B27,"_",E27) -> B02.00_Portion of instrument or liability held by the reporting entity | B27: B02.00 | C27: =CONCATENATE(B27,";c",D27) -> B02.00;c0090 | D27: 0090 | E27: Portion of instrument or liability held by the reporting entity | F27: =CONCATENATE(G27,": ",H27) -> Numeric: 2 decimals | G27: Numeric | H27: 2 decimals | I27: Input 999999999999999
A28: =CONCATENATE(B28,"_",E28) -> B02.00_Accrued interest | B28: B02.00 | C28: =CONCATENATE(B28,";c",D28) -> B02.00;c0100 | D28: 0100 | E28: Accrued interest | F28: =CONCATENATE(G28,": ",H28) -> Numeric: 2 decimals | G28: Numeric | H28: 2 decimals | I28: Input 999999999999999 | J28: Leave blank
A29: =CONCATENATE(B29,"_",E29) -> B02.00_Applicable fees and charges | B29: B02.00 | C29: =CONCATENATE(B29,";c",D29) -> B02.00;c0110 | D29: 0110 | E29: Applicable fees and charges | F29: =CONCATENATE(G29,": ",H29) -> Numeric: 2 decimals | G29: Numeric | H29: 2 decimals | I29: Input 999999999999999 | J29: Leave blank
A30: =CONCATENATE(B30,"_",E30) -> B02.00_Outstanding amount | B30: B02.00 | C30: =CONCATENATE(B30,";c",D30) -> B02.00;c0120 | D30: 0120 | E30: Outstanding amount | F30: =CONCATENATE(G30,": ",H30) -> Numeric: 2 decimals | G30: Numeric | H30: 2 decimals | I30: Input 999999999999999
A31: =CONCATENATE(B31,"_",E31) -> B02.00_Relevant amount for Bail-in/WDC | B31: B02.00 | C31: =CONCATENATE(B31,";c",D31) -> B02.00;c0130 | D31: 0130 | E31: Relevant amount for Bail-in/WDC | F31: =CONCATENATE(G31,": ",H31) -> Numeric: 2 decimals | G31: Numeric | H31: 2 decimals
A32: =CONCATENATE(B32,"_",E32) -> B02.00_Nature of the liability | B32: B02.00 | C32: =CONCATENATE(B32,";c",D32) -> B02.00;c0140 | D32: 0140 | E32: Nature of the liability | F32: =CONCATENATE(G32,": ",H32) -> String: Drop-down | G32: String | H32: Drop-down
A33: =CONCATENATE(B33,"_",E33) -> B02.00_Nature of the liability (if other) | B33: B02.00 | C33: =CONCATENATE(B33,";c",D33) -> B02.00;c0141 | D33: 0141 | E33: Nature of the liability (if other) | F33: =CONCATENATE(G33,": ",H33) -> String: Free text | G33: String | H33: Free text
A34: =CONCATENATE(B34,"_",E34) -> B02.00_Structurally subordinated | B34: B02.00 | C34: =CONCATENATE(B34,";c",D34) -> B02.00;c0150 | D34: 0150 | E34: Structurally subordinated | F34: =CONCATENATE(G34,": ",H34) -> String: Drop-down | G34: String | H34: Drop-down
A35: =CONCATENATE(B35,"_",E35) -> B02.00_Insolvency ranking | B35: B02.00 | C35: =CONCATENATE(B35,";c",D35) -> B02.00;c0160 | D35: 0160 | E35: Insolvency ranking | F35: =CONCATENATE(G35,": ",H35) -> Numeric: Integer | G35: Numeric | H35: Integer
A36: =CONCATENATE(B36,"_",E36) -> B02.00_Contractual subordination | B36: B02.00 | C36: =CONCATENATE(B36,";c",D36) -> B02.00;c0161 | D36: 0161 | E36: Contractual subordination | F36: =CONCATENATE(G36,": ",H36) -> Numeric: 2 decimals | G36: Numeric | H36: 2 decimals | I36: Input 999999999999999
A37: =CONCATENATE(B37,"_",E37) -> B02.00_Bail-in cascade | B37: B02.00 | C37: =CONCATENATE(B37,";c",D37) -> B02.00;c0162 | D37: 0162 | E37: Bail-in cascade | F37: =CONCATENATE(G37,": ",H37) -> String: Fixed values | G37: String | H37: Fixed values
A38: =CONCATENATE(B38,"_",E38) -> B02.00_Date of issuance | B38: B02.00 | C38: =CONCATENATE(B38,";c",D38) -> B02.00;c0170 | D38: 0170 | E38: Date of issuance | F38: =CONCATENATE(G38,": ",H38) -> Date: yyyy-mm-dd | G38: Date | H38: yyyy-mm-dd
A39: =CONCATENATE(B39,"_",E39) -> B02.00_Date of the next interest payment | B39: B02.00 | C39: =CONCATENATE(B39,";c",D39) -> B02.00;c0180 | D39: 0180 | E39: Date of the next interest payment | F39: =CONCATENATE(G39,": ",H39) -> Date: yyyy-mm-dd | G39: Date | H39: yyyy-mm-dd | I39: Input "0001-01-01" | J39: Leave blank
A40: =CONCATENATE(B40,"_",E40) -> B02.00_Date of the next (partial) redemption payment | B40: B02.00 | C40: =CONCATENATE(B40,";c",D40) -> B02.00;c0190 | D40: 0190 | E40: Date of the next (partial) redemption payment | F40: =CONCATENATE(G40,": ",H40) -> Date: yyyy-mm-dd | G40: Date | H40: yyyy-mm-dd | I40: Input the final legal maturity of the liability (c0210)
A41: =CONCATENATE(B41,"_",E41) -> B02.00_Earliest redemption date | B41: B02.00 | C41: =CONCATENATE(B41,";c",D41) -> B02.00;c0200 | D41: 0200 | E41: Earliest redemption date | F41: =CONCATENATE(G41,": ",H41) -> Date: yyyy-mm-dd | G41: Date | H41: yyyy-mm-dd | I41: Input "0001-01-01"
A42: =CONCATENATE(B42,"_",E42) -> B02.00_Legal maturity | B42: B02.00 | C42: =CONCATENATE(B42,";c",D42) -> B02.00;c0210 | D42: 0210 | E42: Legal maturity | F42: =CONCATENATE(G42,": ",H42) -> Date: yyyy-mm-dd | G42: Date | H42: yyyy-mm-dd | I42: Input "0001-01-01"
A43: =CONCATENATE(B43,"_",E43) -> B02.00_Governing law | B43: B02.00 | C43: =CONCATENATE(B43,";c",D43) -> B02.00;c0220 | D43: 0220 | E43: Governing law | F43: =CONCATENATE(G43,": ",H43) -> String: ISO 3166-1 alpha 2 / ISO 3166-2 | G43: String | H43: ISO 3166-1 alpha 2 / ISO 3166-2 | I43: Input "XX"
A44: =CONCATENATE(B44,"_",E44) -> B02.00_Bail-in recognition clause | B44: B02.00 | C44: =CONCATENATE(B44,";c",D44) -> B02.00;c0230 | D44: 0230 | E44: Bail-in recognition clause | F44: =CONCATENATE(G44,": ",H44) -> String: Drop-down | G44: String | H44: Drop-down | I44: Input "Not applicable"
A45: =CONCATENATE(B45,"_",E45) -> B02.00_Zero-Coupon | B45: B02.00 | C45: =CONCATENATE(B45,";c",D45) -> B02.00;c0240 | D45: 0240 | E45: Zero-Coupon | F45: =CONCATENATE(G45,": ",H45) -> String: Drop-down | G45: String | H45: Drop-down
A46: =CONCATENATE(B46,"_",E46) -> B02.00_Structured product | B46: B02.00 | C46: =CONCATENATE(B46,";c",D46) -> B02.00;c0250 | D46: 0250 | E46: Structured product | F46: =CONCATENATE(G46,": ",H46) -> String: Drop-down | G46: String | H46: Drop-down
A47: =CONCATENATE(B47,"_",E47) -> B02.00_Guaranteed minimum repayment amount of the structured product | B47: B02.00 | C47: =CONCATENATE(B47,";c",D47) -> B02.00;c0260 | D47: 0260 | E47: Guaranteed minimum repayment amount of the structured product | F47: =CONCATENATE(G47,": ",H47) -> Numeric: 2 decimals | G47: Numeric | H47: 2 decimals
A48: =CONCATENATE(B48,"_",E48) -> B02.00_Fair value of the structured product | B48: B02.00 | C48: =CONCATENATE(B48,";c",D48) -> B02.00;c0270 | D48: 0270 | E48: Fair value of the structured product | F48: =CONCATENATE(G48,": ",H48) -> Numeric: 2 decimals | G48: Numeric | H48: 2 decimals
A49: =CONCATENATE(B49,"_",E49) -> B02.00_Not covered and not preferential deposit | B49: B02.00 | C49: =CONCATENATE(B49,";c",D49) -> B02.00;c0280 | D49: 0280 | E49: Not covered and not preferential deposit | F49: =CONCATENATE(G49,": ",H49) -> String: TRUE / FALSE boolean | G49: String | H49: TRUE / FALSE boolean
A50: =CONCATENATE(B50,"_",E50) -> B02.00_Not covered but preferential deposit | B50: B02.00 | C50: =CONCATENATE(B50,";c",D50) -> B02.00;c0290 | D50: 0290 | E50: Not covered but preferential deposit | F50: =CONCATENATE(G50,": ",H50) -> String: TRUE / FALSE boolean | G50: String | H50: TRUE / FALSE boolean
A51: =CONCATENATE(B51,"_",E51) -> B02.00_Covered portion of eligible deposits | B51: B02.00 | C51: =CONCATENATE(B51,";c",D51) -> B02.00;c0300 | D51: 0300 | E51: Covered portion of eligible deposits | F51: =CONCATENATE(G51,": ",H51) -> Numeric: 2 decimals | G51: Numeric | H51: 2 decimals
A52: =CONCATENATE(B52,"_",E52) -> B02.00_Secured/Unsecured | B52: B02.00 | C52: =CONCATENATE(B52,";c",D52) -> B02.00;c0310 | D52: 0310 | E52: Secured/Unsecured | F52: =CONCATENATE(G52,": ",H52) -> String: Drop-down | G52: String | H52: Drop-down
A53: =CONCATENATE(B53,"_",E53) -> B02.00_Amount of pledge, lien or collateral based on the current internal valuation | B53: B02.00 | C53: =CONCATENATE(B53,";c",D53) -> B02.00;c0320 | D53: 0320 | E53: Amount of pledge, lien or collateral based on the current internal valuation | F53: =CONCATENATE(G53,": ",H53) -> Numeric: 2 decimals | G53: Numeric | H53: 2 decimals
A54: =CONCATENATE(B54,"_",E54) -> B02.00_Amount of the uncollateralized part | B54: B02.00 | C54: =CONCATENATE(B54,";c",D54) -> B02.00;c0330 | D54: 0330 | E54: Amount of the uncollateralized part | F54: =CONCATENATE(G54,": ",H54) -> Numeric: 2 decimals | G54: Numeric | H54: 2 decimals | J54: Leave blank
A55: =CONCATENATE(B55,"_",E55) -> B02.00_Internal identification number of the pledge, lien or collateral/collateral pool | B55: B02.00 | C55: =CONCATENATE(B55,";c",D55) -> B02.00;c0340 | D55: 0340 | E55: Internal identification number of the pledge, lien or collateral/collateral pool | F55: =CONCATENATE(G55,": ",H55) -> String: Free text | G55: String | H55: Free text
A56: =CONCATENATE(B56,"_",E56) -> B02.00_Type of the collateral | B56: B02.00 | C56: =CONCATENATE(B56,";c",D56) -> B02.00;c0350 | D56: 0350 | E56: Type of the collateral | F56: =CONCATENATE(G56,": ",H56) -> String: Drop-down | G56: String | H56: Drop-down | I56: Input "Not applicable" | J56: Leave blank
A57: =CONCATENATE(B57,"_",E57) -> B02.00_Type of the collateral (if other) | B57: B02.00 | C57: =CONCATENATE(B57,";c",D57) -> B02.00;c0351 | D57: 0351 | E57: Type of the collateral (if other) | F57: =CONCATENATE(G57,": ",H57) -> String: Free text | G57: String | H57: Free text
A58: =CONCATENATE(B58,"_",E58) -> B02.00_Trading method | B58: B02.00 | C58: =CONCATENATE(B58,";c",D58) -> B02.00;c0360 | D58: 0360 | E58: Trading method | F58: =CONCATENATE(G58,": ",H58) -> String: Drop-down | G58: String | H58: Drop-down
A59: =CONCATENATE(B59,"_",E59) -> B02.00_Denomination / Nominal value per security in EUR | B59: B02.00 | C59: =CONCATENATE(B59,";c",D59) -> B02.00;c0370 | D59: 0370 | E59: Denomination / Nominal value per security in EUR | F59: =CONCATENATE(G59,": ",H59) -> Numeric: 2 decimals | G59: Numeric | H59: 2 decimals
A60: =CONCATENATE(B60,"_",E60) -> B02.00_Denomination / Nominal value per security in original currency | B60: B02.00 | C60: =CONCATENATE(B60,";c",D60) -> B02.00;c0380 | D60: 0380 | E60: Denomination / Nominal value per security in original currency | F60: =CONCATENATE(G60,": ",H60) -> Numeric: 2 decimals | G60: Numeric | H60: 2 decimals
A61: =CONCATENATE(B61,"_",E61) -> B02.00_Number of securities outstanding not held by the reporting entity | B61: B02.00 | C61: =CONCATENATE(B61,";c",D61) -> B02.00;c0390 | D61: 0390 | E61: Number of securities outstanding not held by the reporting entity | F61: =CONCATENATE(G61,": ",H61) -> Numeric: Integer | G61: Numeric | H61: Integer
A62: =CONCATENATE(B62,"_",E62) -> B02.00_Number of securities outstanding held by the reporting entity | B62: B02.00 | C62: =CONCATENATE(B62,";c",D62) -> B02.00;c0391 | D62: 0391 | E62: Number of securities outstanding held by the reporting entity | F62: =CONCATENATE(G62,": ",H62) -> Numeric: Integer | G62: Numeric | H62: Integer
A63: =CONCATENATE(B63,"_",E63) -> B02.00_Accrued interest per security | B63: B02.00 | C63: =CONCATENATE(B63,";c",D63) -> B02.00;c0400 | D63: 0400 | E63: Accrued interest per security | F63: =CONCATENATE(G63,": ",H63) -> Numeric: 4 decimals | G63: Numeric | H63: 4 decimals
A64: =CONCATENATE(B64,"_",E64) -> B02.00_Fees and charges per security | B64: B02.00 | C64: =CONCATENATE(B64,";c",D64) -> B02.00;c0410 | D64: 0410 | E64: Fees and charges per security | F64: =CONCATENATE(G64,": ",H64) -> Numeric: 4 decimals | G64: Numeric | H64: 4 decimals
A65: =CONCATENATE(B65,"_",E65) -> B02.00_Fair value per security | B65: B02.00 | C65: =CONCATENATE(B65,";c",D65) -> B02.00;c0420 | D65: 0420 | E65: Fair value per security | F65: =CONCATENATE(G65,": ",H65) -> Numeric: 4 decimals | G65: Numeric | H65: 4 decimals
A66: =CONCATENATE(B66,"_",E66) -> B02.00_Principal amount of the global note in EUR | B66: B02.00 | C66: =CONCATENATE(B66,";c",D66) -> B02.00;c0430 | D66: 0430 | E66: Principal amount of the global note in EUR | F66: =CONCATENATE(G66,": ",H66) -> Numeric: 2 decimals | G66: Numeric | H66: 2 decimals | I66: Input 999999999999999
A67: =CONCATENATE(B67,"_",E67) -> B02.00_Principal amount of the global note in original currency | B67: B02.00 | C67: =CONCATENATE(B67,";c",D67) -> B02.00;c0431 | D67: 0431 | E67: Principal amount of the global note in original currency | F67: =CONCATENATE(G67,": ",H67) -> Numeric: 2 decimals | G67: Numeric | H67: 2 decimals | I67: Input 999999999999999
A68: =CONCATENATE(B68,"_",E68) -> B02.00_Nature of the global note | B68: B02.00 | C68: =CONCATENATE(B68,";c",D68) -> B02.00;c0440 | D68: 0440 | E68: Nature of the global note | F68: =CONCATENATE(G68,": ",H68) -> String: Drop-down | G68: String | H68: Drop-down | I68: Input "Not applicable"
A69: =CONCATENATE(B69,"_",E69) -> B02.00_Current pool factor | B69: B02.00 | C69: =CONCATENATE(B69,";c",D69) -> B02.00;c0450 | D69: 0450 | E69: Current pool factor | F69: =CONCATENATE(G69,": ",H69) -> Numeric: Values between 0 and 1, with 9 decimals | G69: Numeric | H69: Values between 0 and 1, with 9 decimals | I69: Input -9999.999999999
A70: =CONCATENATE(B70,"_",E70) -> B02.00_Central securities depository | B70: B02.00 | C70: =CONCATENATE(B70,";c",D70) -> B02.00;c0460 | D70: 0460 | E70: Central securities depository | F70: =CONCATENATE(G70,": ",H70) -> String: Fixed values | G70: String | H70: Fixed values
A71: =CONCATENATE(B71,"_",E71) -> B02.00_Central securities depository (LEI) | B71: B02.00 | C71: =CONCATENATE(B71,";c",D71) -> B02.00;c0461 | D71: 0461 | E71: Central securities depository (LEI) | F71: =CONCATENATE(G71,": ",H71) -> String: Free text | G71: String | H71: Free text
A72: =CONCATENATE(B72,"_",E72) -> B02.00_Central securities depository name (if other) | B72: B02.00 | C72: =CONCATENATE(B72,";c",D72) -> B02.00;c0462 | D72: 0462 | E72: Central securities depository name (if other) | F72: =CONCATENATE(G72,": ",H72) -> String: Free text | G72: String | H72: Free text
A73: =CONCATENATE(B73,"_",E73) -> B02.00_(Mandated) paying agent | B73: B02.00 | C73: =CONCATENATE(B73,";c",D73) -> B02.00;c0470 | D73: 0470 | E73: (Mandated) paying agent | F73: =CONCATENATE(G73,": ",H73) -> String: Free text | G73: String | H73: Free text | I73: Input "Not applicable"
A74: =CONCATENATE(B74,"_",E74) -> B02.00_(Mandated) paying agent (LEI) | B74: B02.00 | C74: =CONCATENATE(B74,";c",D74) -> B02.00;c0471 | D74: 0471 | E74: (Mandated) paying agent (LEI) | F74: =CONCATENATE(G74,": ",H74) -> String: Free text | G74: String | H74: Free text | I74: Input "Not applicable"
A75: =CONCATENATE(B75,"_",E75) -> B02.00_Trading venue | B75: B02.00 | C75: =CONCATENATE(B75,";c",D75) -> B02.00;c0480 | D75: 0480 | E75: Trading venue | F75: =CONCATENATE(G75,": ",H75) -> String: Free text | G75: String | H75: Free text | I75: Input "Not applicable"
A76: =CONCATENATE(B76,"_",E76) -> B02.00_Trading venue (LEI) | B76: B02.00 | C76: =CONCATENATE(B76,";c",D76) -> B02.00;c0481 | D76: 0481 | E76: Trading venue (LEI) | F76: =CONCATENATE(G76,": ",H76) -> String: Free text | G76: String | H76: Free text | I76: Input "Not applicable"
A77: =CONCATENATE(B77,"_",E77) -> B02.00_Registrar for information about creditors/holders | B77: B02.00 | C77: =CONCATENATE(B77,";c",D77) -> B02.00;c0490 | D77: 0490 | E77: Registrar for information about creditors/holders | F77: =CONCATENATE(G77,": ",H77) -> String: Free text | G77: String | H77: Free text | I77: Input "Not applicable"
A78: =CONCATENATE(B78,"_",E78) -> B02.00_Registrar for information about creditors/holders (LEI) | B78: B02.00 | C78: =CONCATENATE(B78,";c",D78) -> B02.00;c0491 | D78: 0491 | E78: Registrar for information about creditors/holders (LEI) | F78: =CONCATENATE(G78,": ",H78) -> String: Free text | G78: String | H78: Free text | I78: Input "Not applicable"
A79: =CONCATENATE(B79,"_",E79) -> B02.00_National Numbering Agency | B79: B02.00 | C79: =CONCATENATE(B79,";c",D79) -> B02.00;c0500 | D79: 0500 | E79: National Numbering Agency | F79: =CONCATENATE(G79,": ",H79) -> String: Free text | G79: String | H79: Free text | I79: Input "Not applicable"
A80: =CONCATENATE(B80,"_",E80) -> B02.00_National Numbering Agency (LEI) | B80: B02.00 | C80: =CONCATENATE(B80,";c",D80) -> B02.00;c0501 | D80: 0501 | E80: National Numbering Agency (LEI) | F80: =CONCATENATE(G80,": ",H80) -> String: Free text | G80: String | H80: Free text | I80: Input "Not applicable"
A81: =CONCATENATE(B81,"_",E81) -> B02.00_Common Depository | B81: B02.00 | C81: =CONCATENATE(B81,";c",D81) -> B02.00;c0510 | D81: 0510 | E81: Common Depository | F81: =CONCATENATE(G81,": ",H81) -> String: Free text | G81: String | H81: Free text | I81: Input "Not applicable"
A82: =CONCATENATE(B82,"_",E82) -> B02.00_Common Depository (LEI) | B82: B02.00 | C82: =CONCATENATE(B82,";c",D82) -> B02.00;c0511 | D82: 0511 | E82: Common Depository (LEI) | F82: =CONCATENATE(G82,": ",H82) -> String: Free text | G82: String | H82: Free text | I82: Input "Not applicable"
A83: =CONCATENATE(B83,"_",E83) -> B02.00_Common Service Provider | B83: B02.00 | C83: =CONCATENATE(B83,";c",D83) -> B02.00;c0520 | D83: 0520 | E83: Common Service Provider | F83: =CONCATENATE(G83,": ",H83) -> String: Free text | G83: String | H83: Free text | I83: Input "Not applicable"
A84: =CONCATENATE(B84,"_",E84) -> B02.00_Common Service Provider (LEI) | B84: B02.00 | C84: =CONCATENATE(B84,";c",D84) -> B02.00;c0521 | D84: 0521 | E84: Common Service Provider (LEI) | F84: =CONCATENATE(G84,": ",H84) -> String: Free text | G84: String | H84: Free text | I84: Input "Not applicable"
... A88: =CONCATENATE(B88,"_",E88) -> B02.00_Eligible amount for own funds at consolidated level | B88: B02.00 | C88: =CONCATENATE(B88,";c",D88) -> B02.00;c0560 | D88: 0560 | E88: Eligible amount for own funds at consolidated level | F88: =CONCATENATE(G88,": ",H88) -> Numeric: 2 decimals | G88: Numeric | H88: 2 decimals | I88: Input 999999999999999
A89: =CONCATENATE(B89,"_",E89) -> B02.00_Amount of the security interest provided | B89: B02.00 | C89: =CONCATENATE(B89,";c",D89) -> B02.00;c0570 | D89: 0570 | E89: Amount of the security interest provided | F89: =CONCATENATE(G89,": ",H89) -> Numeric: 2 decimals | G89: Numeric | H89: 2 decimals
A90: =CONCATENATE(B90,"_",E90) -> B02.00_Security interest provider (Name) | B90: B02.00 | C90: =CONCATENATE(B90,";c",D90) -> B02.00;c0580 | D90: 0580 | E90: Security interest provider (Name) | F90: =CONCATENATE(G90,": ",H90) -> String: Free text | G90: String | H90: Free text | I90: Input "Not applicable"
A91: =CONCATENATE(B91,"_",E91) -> B02.00_Security interest provider (LEI) | B91: B02.00 | C91: =CONCATENATE(B91,";c",D91) -> B02.00;c0581 | D91: 0581 | E91: Security interest provider (LEI) | F91: =CONCATENATE(G91,": ",H91) -> String: Free text | G91: String | H91: Free text | I91: Input "Not applicable"
A92: =CONCATENATE(B92,"_",E92) -> B02.00_Type of security interest provided by a third party | B92: B02.00 | C92: =CONCATENATE(B92,";c",D92) -> B02.00;c0590 | D92: 0590 | E92: Type of security interest provided by a third party | F92: =CONCATENATE(G92,": ",H92) -> String: Drop-down | G92: String | H92: Drop-down | I92: Input "Not applicable"
A93: =CONCATENATE(B93,"_",E93) -> B02.00_Collateral for an asset position | B93: B02.00 | C93: =CONCATENATE(B93,";c",D93) -> B02.00;c0600 | D93: 0600 | E93: Collateral for an asset position | F93: =CONCATENATE(G93,": ",H93) -> String: TRUE / FALSE boolean | G93: String | H93: TRUE / FALSE boolean | I93: Input "Not applicable"
A94: =CONCATENATE(B94,"_",E94) -> B02.00_Carrying amount IFRS | B94: B02.00 | C94: =CONCATENATE(B94,";c",D94) -> B02.00;c0610 | D94: 0610 | E94: Carrying amount IFRS | F94: =CONCATENATE(G94,": ",H94) -> Numeric: 2 decimals | G94: Numeric | H94: 2 decimals
A95: =CONCATENATE(B95,"_",E95) -> B02.00_Balance sheet item according to IFRS | B95: B02.00 | C95: =CONCATENATE(B95,";c",D95) -> B02.00;c0620 | D95: 0620 | E95: Balance sheet item according to IFRS | F95: =CONCATENATE(G95,": ",H95) -> String: Drop-down | G95: String | H95: Drop-down
A96: =CONCATENATE(B96,"_",E96) -> B02.00_Carrying amount national GAAP | B96: B02.00 | C96: =CONCATENATE(B96,";c",D96) -> B02.00;c0630 | D96: 0630 | E96: Carrying amount national GAAP | F96: =CONCATENATE(G96,": ",H96) -> Numeric: 2 decimals | G96: Numeric | H96: 2 decimals
A97: =CONCATENATE(B97,"_",E97) -> B02.00_Balance sheet item according to national GAAP | B97: B02.00 | C97: =CONCATENATE(B97,";c",D97) -> B02.00;c0640 | D97: 0640 | E97: Balance sheet item according to national GAAP | F97: =CONCATENATE(G97,": ",H97) -> String: Free text | G97: String | H97: Free text
A98: =CONCATENATE(B98,"_",E98) -> B02.00_Instrument/liability is issued to or bought by an existing shareholder that is not part of the same resolution group | B98: B02.00 | C98: =CONCATENATE(B98,";c",D98) -> B02.00;c5000 | D98: 5000 | E98: Instrument/liability is issued to or bought by an existing shareholder that is not part of the same resolution group | F98: =CONCATENATE(G98,": ",H98) -> String: TRUE / FALSE boolean | G98: String | H98: TRUE / FALSE boolean
A99: =CONCATENATE(B99,"_",E99) -> B02.00_Instrument/liability meets the requirements of Art. 21(7a) SRMR | B99: B02.00 | C99: =CONCATENATE(B99,";c",D99) -> B02.00;c5010 | D99: 5010 | E99: Instrument/liability meets the requirements of Art. 21(7a) SRMR | F99: =CONCATENATE(G99,": ",H99) -> String: TRUE / FALSE boolean | G99: String | H99: TRUE / FALSE boolean
A100: =CONCATENATE(B100,"_",E100) -> B03.00_Row number | B100: B03.00 | C100: =CONCATENATE(B100,";c",D100) -> B03.00;c0010 | D100: 0010 | E100: Row number | F100: =CONCATENATE(G100,": ",H100) -> Numeric: Integer | G100: Numeric | H100: Integer
A101: =CONCATENATE(B101,"_",E101) -> B03.00_Unique identification number of the netting set known to the counterparty | B101: B03.00 | C101: =CONCATENATE(B101,";c",D101) -> B03.00;c0020 | D101: 0020 | E101: Unique identification number of the netting set known to the counterparty | F101: =CONCATENATE(G101,": ",H101) -> String: Free text | G101: String | H101: Free text
A102: =CONCATENATE(B102,"_",E102) -> B03.00_Insolvency ranking | B102: B03.00 | C102: =CONCATENATE(B102,";c",D102) -> B03.00;c0030 | D102: 0030 | E102: Insolvency ranking | F102: =CONCATENATE(G102,": ",H102) -> Numeric: Integer | G102: Numeric | H102: Integer
A103: =CONCATENATE(B103,"_",E103) -> B03.00_Bail-in cascade | B103: B03.00 | C103: =CONCATENATE(B103,";c",D103) -> B03.00;c0031 | D103: 0031 | E103: Bail-in cascade | F103: =CONCATENATE(G103,": ",H103) -> String: Free text | G103: String | H103: Free text
A104: =CONCATENATE(B104,"_",E104) -> B03.00_ISDA Protocol Resolution Stay of the reporting entity | B104: B03.00 | C104: =CONCATENATE(B104,";c",D104) -> B03.00;c0040 | D104: 0040 | E104: ISDA Protocol Resolution Stay of the reporting entity | F104: =CONCATENATE(G104,": ",H104) -> String: Drop down | G104: String | H104: Drop down
A105: =CONCATENATE(B105,"_",E105) -> B03.00_Recognition Resolution Stay of counterparty | B105: B03.00 | C105: =CONCATENATE(B105,";c",D105) -> B03.00;c0050 | D105: 0050 | E105: Recognition Resolution Stay of counterparty | F105: =CONCATENATE(G105,": ",H105) -> String: Drop down | G105: String | H105: Drop down
...
