Workbook
Name _ftn1: '1a_PnL and OCI impacts'!#REF!
Name _ftn2: '1a_PnL and OCI impacts'!#REF!
Name all_data: #REF!
Name all_data: #REF!
Name all_data: #REF!
Name base_krzystof: #REF!
Name base_krzystof: #REF!
Name base_krzystof: #REF!
Name DataPointIDs: #REF!
Name DataPointIDs: #REF!
Name DataPointIDs: #REF!
Name DataPointTooltips: #REF!
Name DataPointTooltips: #REF!
Name DataPointTooltips: #REF!
Name DBName: #REF!
Name DBName: #REF!
Name DBName: #REF!
Name IQ_CH: 110000
Name IQ_CQ: 5000
Name IQ_CY: 10000
Name IQ_DAILY: 500000
Name IQ_FH: 100000
Name IQ_FQ: 500
Name IQ_FY: 1000
Name IQ_LTM: 2000
Name IQ_MONTH: 15000
Name IQ_NTM: 6000
Name IQ_WEEK: 50000
Name IQ_YTD: 3000
Name myData: OFFSET(#REF!,0,0,MATCH("*",#REF!,-1),6)
Name myData: OFFSET(#REF!,0,0,MATCH("*",#REF!,-1),6)
Name myData: OFFSET(#REF!,0,0,MATCH("*",#REF!,-1),6)
Name myFilterSelection: #REF!
Name myFilterSelection: #REF!
Name myFilterSelection: #REF!
Name myPivotTable: #REF!
Name myPivotTable: #REF!
Name myPivotTable: #REF!
Name myPivotTableStart: #REF!
Name myPivotTableStart: #REF!
Name myPivotTableStart: #REF!
Name suba: #REF!
Name suba: #REF!
Name suba: #REF!
Name tbl_1_Overall_impacts: '1_Overall impacts'!$B$7:$J$17
Name tbl_1a_PnL_OCI_impacts: '1a_PnL and OCI impacts'!$G$6:$K$33
Name tbl_1b_PRR_Impacts: '1b_PRR impacts'!$F$6:$I$39
Name tbl_2_VaR_ES: '2_VaR'!$C$6:$H$10
Name tbl_2_VaR_ES: #REF!
Name tbl_2_VaR_overshooring: '2_VaR'!$B$14:$E$20
Name tbl_2_VaR_overshooring: #REF!
Name tbl_2_VaR_Qualitative_questions: '2_VaR'!#REF!
Name tbl_2_VaR_Qualitative_questions: #REF!
Name tbl_3_EQRBB: '3_EQRBB'!$E$7:$I$20
Name tbl_4_SFX: '4_SFX'!$D$6:$N$28
Name tbl_5_FVadj: '5_FVadj'!$C$6:$G$8
Name tbl_6_PRR_levelling: '6_PRR levelling'!$D$7:$AC$19
Name Templates: #REF!
Name Templates: #REF!
Name Templates: #REF!

Sheet 0_ReadMe
B2: MARKET RISK
B4: GENERAL INSTRUCTIONS
B6: Sheets "1_Overall impacts", "1a_PnL and OCI impacts" and "1b_PRR impacts"
B7: For the instructions of sheets "1_Overall impacts", "1a_PnL and OCI impacts" and "1b_PRR impacts", please refer to the EBA reporting instructions of the EBA stress-test exercise:
B8: https://www.eba.europa.eu/eba-launches-2023-eu-wide-stress-test-0
B9: Sheets "1_Overall impacts", "1a_PnL and OCI impacts" and "1b_PRR impacts" are based on the related EBA reporting templates, but reduced to capture only the relevant market risk scope.
B10: This template contains the inputs and results for the full revaluation of positions under partial or full fair value measurement that should be subject to the market risk scenario as defined under section 3.3 of the Methodological Note of EBA Stress Test.
B12: Sheet "2_VaR"
B13: This template gathers information about the value at risk (VaR), the expected shortfall and related limits/breaches, as well as the standard deviation of the daily P&L of the prudential trading book and equities in the banking book
B15: Sheet "3_EQRBB"
B16: This template gathers detailed information for the calculation of own funds requirements for Equity risk in the Banking Book (EQRBB) on the basis of the sensitivities-based method defined in article 325e of Regulation(EU) No 575/2013.
B18: Sheet "4_SFX"
... B45: The text box should be used for reporting information regarding: (a) material positions outside the scope of the STE for SREP data collection; (b) quality assurance; (c) empty cells; (d) other information.

Sheet 0_Identification
B2: Template 0_Identification
B4: General information
B6: Country: (two-letter ISO code)
B8: Bank code: (RIAD MFI code)
B10: Bank LEI code:
B12: Bank: (name)
B14: Reference date: T (dd/mm/yyyy format)
B16: Level of consolidation:
B18: Materiality checks | E18: Does the template need to be reported?
B20: Template "1_Overall Impacts", "1a_PnL and OCI Impacts" and "1b_PRR Impacts"
B21: Please specify which approach you follow: Comprehensive Approach (CA) or Trading Exemption (TE)? | E21: =IF(C21="CA","Reported via CA",IF(C21="TE","Reported via TE","Please answer the question")) -> Please answer the question
B23: Template "2_VaR"
B24: 1. Does the institution compute the VaR for internal risk management purposes, or does the institution calculate the VaR for prudential purposes and uses in parallel a different VaR for internal risk management purposes? | E24: =IF(C24="yes","Please report the VaR for internal purposes and the standard deviation",IF(AND(C24="no",C25="no",C26="no"),"No reporting needed",IF(AND(C24="no",C25="yes"),"Please report the VaR for prudential purposes and standard deviation",IF(AND(C24="no",C25="no",C26="yes"),"Report the standard deviation of daily P&L on the FV portfolio","Please answer all the questions")))) -> Please answer all the questions
B25: 2. If no to question 1., does the institution only calculate the VaR for prudential purposes?
B26: 3. If no to question 2., does the institution meet one or more of the conditions set out in paragraph 1 of Article 325a CRR?
B28: Template "3_EQRBB"
B29: Does this ratio exceed the specified threshold? [(F_0101_r0142_c0010 + F_0101_r0176_c0010)] / C_0200_r0010_c0010 > 0.3% | E29: =IF(C29="yes", "Needs to be reported", IF(C29 = "no", "No reporting needed", "Please calculate the ratio and compare with the set threshold")) -> Please calculate the ratio and compare with the set threshold
B31: Template "4_SFX"
B32: 1. Does the institution have a structural FX waiver? | E32: =IF(OR(C32="yes",C34="yes"), "Needs to be reported", IF(AND(C32="no",C34="no"), "No reporting needed", "Please answer all the question")) -> Please answer all the question
B33: 1a. If the institution has a waiver, when was it obtained? (dd/mm/yyyy format)
B34: 2. Does this ratio exceed the specified threshold? [Size of the net open Structural FX position suitable for the exemption, expressed in Euro] / [Total RWAs] > 1%
B36: Template "5_FVadj"
B37: Does the institution use a simplified approach to calculate the AVAs? | E37: =IF(C37="yes", "Needs to be reported", IF(C37= "no", "No reporting needed", "Please answer the question")) -> Please answer the question
B39: Template "6_PRR levelling"
B40: Does the institution use the core approach to calculate the AVAs? | E40: =IF(C40="yes", "Needs to be reported",IF(C40="no", "No reporting needed", "Please answer the question")) -> Please answer the question
B43: Additional comments: The text box should be used for reporting information regarding: (a) scope issues; (b) clarifications on processes; (c) applicable but not reported data; (d) other required or additional information.

Sheet 1_Overall impacts
B2: Template 1: Overall impacts
G4: ='0_Identification'!C21 -> 0 | I4: Adverse Scenario
G5: Sum of fair value of asset (positive) and liabilities (positive) | H5: Fair value | I5: PnL | J5: OCI
F6: (thousands EUR)
B7: Items under stress | G7: 0010 | H7: 0020 | I7: 0030 | J7: 0040
B8: Balance sheet | C8: Assets | D8: FVOCI | E8: (i) Holding or selling equity position | F8: 0010 | H8: ='1a_PnL and OCI impacts'!I9 -> 0 | J8: ='1a_PnL and OCI impacts'!K9 -> 0
C9: Net asset and liabilities | D9: FVPL | E9: Held with a trading intent and their related economic hedges | F9: 0020 | H9: ='1a_PnL and OCI impacts'!I26 -> 0 | I9: =IF('0_Identification'!C21="CA",$G$17*MIN('1a_PnL and OCI impacts'!J26,-0.2%*G9),-0.2%*G9) -> 0
E10: Economic hedges excluding hedges of items held with a trading intent | F10: 0030 | H10: ='1a_PnL and OCI impacts'!I33 -> 0 | I10: ='1a_PnL and OCI impacts'!J33 -> 0
E11: Mandatory or optional at FVPL | F11: 0040 | H11: ='1a_PnL and OCI impacts'!I13 -> 0 | I11: ='1a_PnL and OCI impacts'!J13 -> 0
B12: Reserves - Stress impact under the adverse scenario | E12: CVA net of eligible CVA hedges | F12: 0050 | I12: =('1b_PRR impacts'!H24-'1b_PRR impacts'!G24)-'1b_PRR impacts'!I24 -> 0
E13: Accounting Liquidity and modelling uncertainty reserves - FVPL | F13: 0060 | I13: ='1b_PRR impacts'!H24-'1b_PRR impacts'!H29-'1b_PRR impacts'!G29 -> 0
E14: Accounting Liquidity and modelling uncertainty reserves - FVOCI | F14: 0070 | J14: ='1b_PRR impacts'!H34-'1b_PRR impacts'!G34 -> 0
B15: Daily VaR at reference date | F15: 0080
B16: 75th percentile of daily VaR over the last 250 business days | F16: 0090
B17: Scaling factor | F17: 0100 | G17: =IFERROR(MAX(1,G16/G15),0) -> 0

Sheet 1a_PnL and OCI impacts
B2: Template 1a: PnL and OCI impacts
H4: ='0_Identification'!C21 -> 0 | J4: Adverse scenario
H5: Notional exposure | I5: Fair value | J5: Gains (+) / losses (-) from full revaluation
H6: Total | I6: Total | J6: Total
B7: Balance sheet | C7: IFRS 9 measurement type | D7: Hedging instruments / hedged item / other use | E7: FINREP (breakdown of FINREP 16.4 applied to categories with derivatives and FINREP 4.4 for amortised cost items) | F7: Linear or Optional for derivative products | G7: (thousands EUR) | J7: PnL impact | K7: OCI impact
H8: 0010 | I8: 0020 | J8: 0030 | K8: 0040
B9: Asset | C9: FVOCI | D9: (i) Holding or selling equity position | E9: Equity instruments | F9: Total | G9: 0010
B10: Net asset and liabilities | C10: FVPL | D10: Mandatory or optional at FVPL | E10: Equity instruments | F10: Total | G10: 0020
B11: Net asset and liabilities | C11: FVPL | D11: Mandatory or optional at FVPL | E11: Debt instruments | F11: Total | G11: 0030
B12: Net asset and liabilities | C12: FVPL | D12: Mandatory or optional at FVPL | E12: Other | F12: Total | G12: 0040
B13: Net asset and liabilities | C13: FVPL | D13: Mandatory or optional at FVPL | E13: Total | F13: Total | G13: 0050 | H13: =SUM(H10:H12) -> 0 | I13: =SUM(I10:I12) -> 0 | J13: =SUM(J10:J12) -> 0
B14: Net asset and liabilities | C14: FVPL (HFT) | D14: Held with a trading intent and their related economic hedges | E14: Credit risk instruments and related derivatives | F14: Linear | G14: 0060
B15: Net asset and liabilities | C15: FVPL (HFT) | D15: Held with a trading intent and their related economic hedges | E15: Credit risk instruments and related derivatives | F15: Optional derivatives | G15: 0070
B16: Net asset and liabilities | C16: FVPL (HFT) | D16: Held with a trading intent and their related economic hedges | E16: Derivatives related with commodities | F16: Linear | G16: 0080
B17: Net asset and liabilities | C17: FVPL (HFT) | D17: Held with a trading intent and their related economic hedges | E17: Derivatives related with commodities | F17: Optional derivatives | G17: 0090
B18: Net asset and liabilities | C18: FVPL (HFT) | D18: Held with a trading intent and their related economic hedges | E18: Equity instruments and related derivatives | F18: Linear | G18: 0100
B19: Net asset and liabilities | C19: FVPL (HFT) | D19: Held with a trading intent and their related economic hedges | E19: Equity instruments and related derivatives | F19: Optional derivatives | G19: 0110
B20: Net asset and liabilities | C20: FVPL (HFT) | D20: Held with a trading intent and their related economic hedges | E20: Foreign exchange trading and derivatives related with foreign exchange and gold | F20: Linear | G20: 0120
B21: Net asset and liabilities | C21: FVPL (HFT) | D21: Held with a trading intent and their related economic hedges | E21: Foreign exchange trading and derivatives related with foreign exchange and gold | F21: Optional derivatives | G21: 0130
B22: Net asset and liabilities | C22: FVPL (HFT) | D22: Held with a trading intent and their related economic hedges | E22: Interest rate instruments and related derivatives | F22: Linear | G22: 0140
B23: Net asset and liabilities | C23: FVPL (HFT) | D23: Held with a trading intent and their related economic hedges | E23: Interest rate instruments and related derivatives | F23: Optional derivatives | G23: 0150
B24: Net asset and liabilities | C24: FVPL (HFT) | D24: Held with a trading intent and their related economic hedges | E24: Other | F24: Linear | G24: 0160
B25: Net asset and liabilities | C25: FVPL (HFT) | D25: Held with a trading intent and their related economic hedges | E25: Other | F25: Optional derivatives | G25: 0170
B26: Net asset and liabilities | C26: FVPL (HFT) | D26: Held with a trading intent and their related economic hedges | E26: Total | F26: Total | G26: 0180 | H26: =SUM(H14:H25) -> 0 | I26: =SUM(I14:I25) -> 0 | J26: =SUM(J14:J25) -> 0
B27: Net asset and liabilities | C27: FVPL (HFT) | D27: Economic hedges excluding hedges of items held with a trading intent | E27: Credit risk instruments and related derivatives | F27: Total | G27: 0190
B28: Net asset and liabilities | C28: FVPL (HFT) | D28: Economic hedges excluding hedges of items held with a trading intent | E28: Derivatives related with commodities | F28: Total | G28: 0200
B29: Net asset and liabilities | C29: FVPL (HFT) | D29: Economic hedges excluding hedges of items held with a trading intent | E29: Equity instruments and related derivatives | F29: Total | G29: 0210
B30: Net asset and liabilities | C30: FVPL (HFT) | D30: Economic hedges excluding hedges of items held with a trading intent | E30: Foreign exchange trading and derivatives related with foreign exchange and gold | F30: Total | G30: 0220
B31: Net asset and liabilities | C31: FVPL (HFT) | D31: Economic hedges excluding hedges of items held with a trading intent | E31: Interest rate instruments and related derivatives | F31: Total | G31: 0230
B32: Net asset and liabilities | C32: FVPL (HFT) | D32: Economic hedges excluding hedges of items held with a trading intent | E32: Other | F32: Total | G32: 0240
B33: Net asset and liabilities | C33: FVPL (HFT) | D33: Economic hedges excluding hedges of items held with a trading intent | E33: Total | F33: Total | G33: 0250 | H33: =SUM(H27:H32) -> 0 | I33: =SUM(I27:I32) -> 0 | J33: =SUM(J27:J32) -> 0

Sheet 1b_PRR impacts
B2: Template 1b: PRR impacts
G4: Actual | H4: Adverse scenario
C5: Counterparty | E5: Credit or L1/L2/L3 category | G5: Accounting reserves (CVA or Liquidity&Modelling Uncertainty) | I5: Impact of eligible CVA hedges according to Art. 386 CRR
F6: (thousands EUR) | G6: 0010 | H6: 0020 | I6: 0030
B7: CVA reserve | C7: Financial Institutions (Banks, Funds, Asset Managers, etc.) | E7: IG | F7: 0010
E8: Sub-IG | F8: 0020
E9: Total | F9: 0030 | G9: =SUM(G7:G8) -> 0 | H9: =SUM(H7:H8) -> 0
C10: Insurers | E10: IG | F10: 0040
E11: Sub-IG | F11: 0050
E12: Total | F12: 0060 | G12: =SUM(G10:G11) -> 0 | H12: =SUM(H10:H11) -> 0
C13: Corporates | E13: IG | F13: 0070
E14: Sub-IG | F14: 0080
E15: Total | F15: 0090 | G15: =SUM(G13:G14) -> 0 | H15: =SUM(H13:H14) -> 0
C16: Sovereigns, supranationals, local authorities, etc. | E16: IG | F16: 0100
E17: Sub-IG | F17: 0110
E18: Total | F18: 0120 | G18: =SUM(G16:G17) -> 0 | H18: =SUM(H16:H17) -> 0
C19: Others | E19: IG | F19: 0130
E20: Sub-IG | F20: 0140
E21: Total | F21: 0150 | G21: =SUM(G19:G20) -> 0 | H21: =SUM(H19:H20) -> 0
C22: Total | E22: IG | F22: 0160 | G22: =SUM(G7,G10,G13,G16,G19) -> 0 | H22: =SUM(H7,H10,H13,H16,H19) -> 0
E23: Sub-IG | F23: 0170 | G23: =SUM(G8,G11,G14,G17,G20) -> 0 | H23: =SUM(H8,H11,H14,H17,H20) -> 0
E24: Total | F24: 0180 | G24: =SUM(G9,G12,G15,G18,G21) -> 0 | H24: =SUM(H9,H12,H15,H18,H21) -> 0 | I24: =SUM(I9,I12,I15,I18,I21) -> 0
B25: Market liquidity and model uncertainty reserve* | C25: Assets and liabilities | D25: FVPL | E25: Level 1 | F25: 0190
E26: Cleared Level 2 | F26: 0200
E27: Other Level 2 | F27: 0210
E28: Level 3 | F28: 0220
E29: Total | F29: 0230 | G29: =SUM(G25:G28) -> 0 | H29: =SUM(H25:H28) -> 0
C30: Assets | D30: FVOCI | E30: Level 1 | F30: 0240
E31: Cleared Level 2 | F31: 0250
E32: Other Level 2 | F32: 0260
E33: Level 3 | F33: 0270
E34: Total | F34: 0280 | G34: =SUM(G30:G33) -> 0 | H34: =SUM(H30:H33) -> 0
C35: Total | E35: Total | F35: 0290 | G35: =G29+G34 -> 0 | H35: =H29+H34 -> 0
B36: Memo item - Other reserves | C36: Assets and liabilities | D36: FVPL | E36: Total | F36: 0300
C37: Assets | D37: FVOCI | E37: Total | F37: 0310
C38: Total | E38: Total | F38: 0320 | G38: =SUM(G36:G37) -> 0
B39: Day one profit and loss related reserves | C39: Assets and liabilities | D39: FVPL&FVOCI | E39: Total | F39: 0330
B41: * Reserves do not include hedge accounting.

Sheet 2_VaR
B2: Template 2: VaR
D4: Reporting perimeter | F4: Managerial perimeter | K4: Please describe the VaR/ ES methodology
D5: Standard deviation | E5: Level of VaR | F5: Average of VaR/ES (Last quarter) | G5: Limit of VaR/ES (Last quarter) | H5: # limit breach (Last quarter) | I5: Level at which limit is set | J5: # Overshootings (Last 250 days)
C6: (thousands EUR) | D6: 0010 | E6: 0020 | F6: 0030 | G6: 0040 | H6: 0050 | I6: 0060 | J6: 0065 | K6: 0070
B7: Total Trading Book + Equities in the Banking book | C7: 0010 | K7: (free text)
B8: Trading Book | C8: 0020
B9: Equities in the Banking book | C9: 0030
B10: Expected shortfall (optional) | C10: 0040 | K10: (free text)
B11: Coverage (%) | C11: 0050
B12: Additional information on perimeter | C12: 0060 | D12: (free text)
B14: Top overshootings in the last 250 days (ranked down in terms of difference between the overshooting and the VaR on the day in which the overshooting was observed) | D14: Managerial 1d-VaR | E14: Managerial P&L | F14: Date (dd/mm/yyyy) | G14: Comments and explanations
D15: 0080 | E15: 0090 | F15: 0100 | G15: 0110
B16: 1 | C16: 0070
B17: 2 | C17: 0071
B18: 3 | C18: 0072
B19: 4 | C19: 0073
B20: 5 | C20: 0074

Sheet 3_EQRBB
B2: Template 3: EQRBB
B4: Bucket | F4: Carrying amount | H4: Weighted sensitivities
H5: Spot prices
F6: FVPL | G6: FVOCI | H6: Delta risk factors | I6: Vega risk factors
E7: (thousands EUR) | F7: 0010 | G7: 0020 | H7: 0030 | I7: 0040
B8: Large | C8: Emerging market economy | D8: Consumer goods and services, transportation and storage, administrative and support service activities, healthcare, utilities | E8: 0010
D9: Telecommunications, industrials | E9: 0020
D10: Basic materials, energy, agriculture, manufacturing, mining and quarrying | E10: 0030
D11: Financials including government-backed financials, real estate activities, technology | E11: 0040
C12: Advanced economy | D12: Consumer goods and services, transportation and storage, administrative and support service activities, healthcare, utilities | E12: 0050
D13: Telecommunications, industrials | E13: 0060
D14: Basic materials, energy, agriculture, manufacturing, mining and quarrying | E14: 0070
D15: Financials including government-backed financials, real estate activities, technology | E15: 0080
B16: Small | C16: Emerging market economy | D16: All sectors described under row numbers 0010, 0020, 0030 and 0040 | E16: 0090
C17: Advanced economy | D17: All sectors described under row numbers 0050, 0060, 0070 and 0080 | E17: 0100
B18: Other sector | E18: 0110
B19: Large market capitalisation, advanced economy indices | E19: 0120
B20: Other indices | E20: 0130

Sheet 4_SFX
B2: Template 4: SFX
B4: # Total list of currencies | C4: #
B6: Currencies | D6: (thousands EUR) | E6: Net open position in the currency previous to any exemption | F6: Positions that are not structural | G6: Positions suitable for the exemption | H6: Positions not suitable for the exemption | I6: Max open position | J6: Excluded open position | K6: Sensitivity - prescribed formula | L6: Sensitivity - internal methodogies | M6: Structural positions included in the sensitivity | N6: Credit risk RWA in the foreign CCY over total RWA (%)
B8: Number | C8: Identifier (e.g. USD) | E8: 0010 | F8: 0020 | G8: 0030 | H8: 0040 | I8: 0050 | J8: 0060 | K8: 0070 | L8: 0080 | M8: 0090 | N8: 0100
B9: 1 | D9: 0010
B10: 2 | D10: 0020
B11: 3 | D11: 0030
B12: 4 | D12: 0040
B13: 5 | D13: 0050
B14: 6 | D14: 0060
B15: 7 | D15: 0070
B16: 8 | D16: 0080
B17: 9 | D17: 0090
B18: 10 | D18: 0100
B19: 11 | D19: 0110
B20: 12 | D20: 0120
... B28: 20 | D28: 0200

Sheet 5_FVadj
B2: Template 5: FVadj
D4: Day 1 P&L | E4: IPV difference | F4: Fair value adjustments
F5: Total | G5: o/w Unearned credit spreads
C6: (thousands EUR) | D6: 0010 | E6: 0020 | F6: 0030 | G6: 0040
B7: Total | C7: 0010
B8: Of which: trading book | C8: 0020

Sheet 6_PRR levelling
B2: Template 6: PRR levelling
E4: Fair-valued assets and liabilities (Gross) | G4: Day1 P&L | I4: IPV difference | K4: Fair value adjustments (Fvadj) | Y4: Category level AVA
K5: Market price uncertainty | M5: Close-out costs | O5: Model risk | Q5: Concentrated positions | S5: Unearned credit spreads | U5: Investing and funding costs | W5: Other Fvadj
E6: Total | F6: o/w Level 3 | G6: Total | H6: o/w Level 3 | I6: Total | J6: o/w Level 3 | K6: Total | L6: o/w Level 3 | M6: Total | N6: o/w Level 3 | O6: Total | P6: o/w Level 3 | Q6: Total | R6: o/w Level 3 | S6: Total | T6: o/w Level 3 | U6: Total | V6: o/w Level 3 | W6: Total | X6: o/w Level 3 | Y6: Market price uncertainty | Z6: Close-out costs | AA6: Model risk | AB6: Concentrated positions | AC6: Other AVA (Future administrative costs, Early termination, Operational risk)
D7: (thousands EUR) | E7: 0010 | F7: 0020 | G7: 0030 | H7: 0040 | I7: 0050 | J7: 0060 | K7: 0070 | L7: 0080 | M7: 0090 | N7: 0100 | O7: 0110 | P7: 0120 | Q7: 0130 | R7: 0140 | S7: 0150 | T7: 0160 | U7: 0170 | V7: 0180 | W7: 0190 | X7: 0200 | Y7: 0210 | Z7: 0220 | AA7: 0230 | AB7: 0240 | AC7: 0250
B8: FVPL | C8: Derivatives | D8: 0010
C9: Interest rates | D9: 0020
C10: Foreign exchange | D10: 0030
C11: Credit | D11: 0040
C12: Equities | D12: 0050
C13: Commodities | D13: 0060
C14: Equity instruments | D14: 0070
C15: Debt securities | D15: 0080
C16: Others | D16: 0090
B17: FVOCI | C17: Equity instruments | D17: 0100
C18: Debt securities | D18: 0110
C19: Others | D19: 0120

Sheet Currencies
A1: Country/Currency | B1: Abbreviation
A2: Australia Dollar | B2: AUD
A3: Great Britain Pound | B3: GBP
A4: Euro | B4: EUR
A5: Japan Yen | B5: JPY
A6: Switzerland Franc | B6: CHF
A7: USA Dollar | B7: USD
A8: Afghanistan Afghani | B8: AFN
A9: Albania Lek | B9: ALL
A10: Algeria Dinar | B10: DZD
A11: Angola Kwanza | B11: AOA
A12: Argentina Peso | B12: ARS
... A161: Other currencies | B161: Other
