Workbook

Sheet PDS
G1: Estado especificação | U1: Estado desenvolvimento
E2: Total | G2: Concluído | I2: Mapeamento com LT fechado, mas parametrização pendente | K2: Novo campo, mapeamento datalake fechado, com necessidade de criar parametrização | M2: Novo campo, mapeamento datalake fechado, sem necessidade de criar parametrização | O2: Novo campo, mapeamento datalake pendente, com necessidade de criar parametrização | Q2: Novo campo, mapeamento datalake pendente, sem necessidade de criar parametrização | S2: Por iniciar | U2: Concluído | W2: Em desenvolvimento | Y2: Aguarda desenvolvimento de outras equipas | AA2: Por especificar
B3: Módulo | C3: Submódulo | D3: Nome do Ficheiro | E3: abs | F3: % | G3: abs | H3: % | I3: abs | J3: % | K3: abs | L3: % | M3: abs | N3: % | O3: abs | P3: % | Q3: abs | R3: % | S3: abs | T3: % | U3: abs | V3: % | W3: abs | X3: % | Y3: abs | Z3: % | AA3: abs | AB3: %
B4: Exposures to legal persons | C4: Instruments | D4: XXXXX_YYYYMMDD_01_01_leg_instr.csv | E4: =COUNTA(LEGALP_INSTRUMENTS!A3:A27) -> 7 | F4: =SUM(H4,J4,L4,N4,P4,R4,T4) -> 1 | G4: =COUNTIF(LEGALP_INSTRUMENTS!O:O,"Concluído") -> 7 | H4: =G4/E4 -> 1 | I4: =COUNTIF(LEGALP_INSTRUMENTS!O:O,"Mapeamento com LT fechado, mas parametrização pendente") -> 0 | J4: =I4/E4 -> 0 | K4: =COUNTIF(LEGALP_INSTRUMENTS!O:O,"Novo campo, mapeamento datalake fechado, com necessidade de criar parametrização") -> 0 | L4: =K4/E4 -> 0 | M4: =COUNTIF(LEGALP_INSTRUMENTS!O:O,"Novo campo, mapeamento datalake fechado, sem necessidade de criar parametrização") -> 0 | N4: =M4/E4 -> 0 | O4: =COUNTIF(LEGALP_INSTRUMENTS!O:O,"Novo campo, mapeamento datalake pendente, com necessidade de criar parametrização") -> 0 | P4: =O4/E4 -> 0 | Q4: =COUNTIF(LEGALP_INSTRUMENTS!O:O,"Novo campo, mapeamento datalake pendente, sem necessidade de criar parametrização") -> 0 | R4: =Q4/E4 -> 0 | S4: =COUNTIF(LEGALP_INSTRUMENTS!O:O,"Por iniciar") -> 0 | T4: =S4/E4 -> 0 | U4: =COUNTIF(LEGALP_INSTRUMENTS!P:P,"Concluído") -> 7 | V4: =U4/E4 -> 1 | W4: =COUNTIF(LEGALP_INSTRUMENTS!P:P,"Em desenvolvimento") -> 0 | X4: =W4/E4 -> 0 | Y4: =COUNTIF(LEGALP_INSTRUMENTS!P:P,"Aguarda desenvolvimento de outras equipas") -> 0 | Z4: =Y4/E4 -> 0 | AA4: =COUNTIF(LEGALP_INSTRUMENTS!P:P,"Por especificar") -> 0 | AB4: =AA4/E4 -> 0
C5: Counterparties | D5: XXXXX_YYYYMMDD_01_02_leg_count.csv | E5: =COUNTA(LEGALP_COUNTERPARTIES!A3:A27) -> 5 | F5: =SUM(H5,J5,L5,N5,P5,R5,T5) -> 1 | G5: =COUNTIF(LEGALP_COUNTERPARTIES!O:O,"Concluído") -> 5 | H5: =G5/E5 -> 1 | I5: =COUNTIF(LEGALP_COUNTERPARTIES!O:O,"Mapeamento com LT fechado, mas parametrização pendente") -> 0 | J5: =I5/E5 -> 0 | K5: =COUNTIF(LEGALP_COUNTERPARTIES!O:O,"Novo campo, mapeamento datalake fechado, com necessidade de criar parametrização") -> 0 | L5: =K5/E5 -> 0 | M5: =COUNTIF(LEGALP_COUNTERPARTIES!O:O,"Novo campo, mapeamento datalake fechado, sem necessidade de criar parametrização") -> 0 | N5: =M5/E5 -> 0 | O5: =COUNTIF(LEGALP_COUNTERPARTIES!O:O,"Novo campo, mapeamento datalake pendente, com necessidade de criar parametrização") -> 0 | P5: =O5/E5 -> 0 | Q5: =COUNTIF(LEGALP_COUNTERPARTIES!O:O,"Novo campo, mapeamento datalake pendente, sem necessidade de criar parametrização") -> 0 | R5: =Q5/E5 -> 0 | S5: =COUNTIF(LEGALP_COUNTERPARTIES!O:O,"Por iniciar") -> 0 | T5: =S5/E5 -> 0 | U5: =COUNTIF(LEGALP_COUNTERPARTIES!P:P,"Concluído") -> 5 | V5: =U5/E5 -> 1 | W5: =COUNTIF(LEGALP_COUNTERPARTIES!P:P,"Em desenvolvimento") -> 0 | X5: =W5/E5 -> 0 | Y5: =COUNTIF(LEGALP_COUNTERPARTIES!P:P,"Aguarda desenvolvimento de outras equipas") -> 0 | Z5: =Y5/E5 -> 0 | AA5: =COUNTIF(LEGALP_COUNTERPARTIES!P:P,"Por especificar") -> 0 | AB5: =AA5/E5 -> 0
C6: Protections | D6: XXXXX_YYYYMMDD_01_03_leg_prot.csv | E6: =COUNTA(LEGALP_PROTECTIONS!A3:A18) -> 8 | F6: =SUM(H6,J6,L6,N6,P6,R6,T6) -> 1 | G6: =COUNTIF(LEGALP_PROTECTIONS!O:O,"Concluído") -> 8 | H6: =G6/E6 -> 1 | I6: =COUNTIF(LEGALP_PROTECTIONS!O:O,"Mapeamento com LT fechado, mas parametrização pendente") -> 0 | J6: =I6/E6 -> 0 | K6: =COUNTIF(LEGALP_PROTECTIONS!O:O,"Novo campo, mapeamento datalake fechado, com necessidade de criar parametrização") -> 0 | L6: =K6/E6 -> 0 | M6: =COUNTIF(LEGALP_PROTECTIONS!O:O,"Novo campo, mapeamento datalake fechado, sem necessidade de criar parametrização") -> 0 | N6: =M6/E6 -> 0 | O6: =COUNTIF(LEGALP_PROTECTIONS!O:O,"Novo campo, mapeamento datalake pendente, com necessidade de criar parametrização") -> 0 | P6: =O6/E6 -> 0 | Q6: =COUNTIF(LEGALP_PROTECTIONS!O:O,"Novo campo, mapeamento datalake pendente, sem necessidade de criar parametrização") -> 0 | R6: =Q6/E6 -> 0 | S6: =COUNTIF(LEGALP_PROTECTIONS!O:O,"Por iniciar") -> 0 | T6: =S6/E6 -> 0 | U6: =COUNTIF(LEGALP_PROTECTIONS!P:P,"Concluído") -> 8 | V6: =U6/E6 -> 1 | W6: =COUNTIF(LEGALP_PROTECTIONS!P:P,"Em desenvolvimento") -> 0 | X6: =W6/E6 -> 0 | Y6: =COUNTIF(LEGALP_PROTECTIONS!P:P,"Aguarda desenvolvimento de outras equipas") -> 0 | Z6: =Y6/E6 -> 0 | AA6: =COUNTIF(LEGALP_PROTECTIONS!P:P,"Por especificar") -> 0 | AB6: =AA6/E6 -> 0
C7: Instrument-Counterparty relation | D7: XXXXX_YYYYMMDD_01_04_leg_instr_count.csv | E7: =COUNTA(LEGALP_INSTRUMENT_COUNTERPARTY!A3:A7) -> 2 | F7: =SUM(H7,J7,L7,N7,P7,R7,T7) -> 1 | G7: =COUNTIF(LEGALP_INSTRUMENT_COUNTERPARTY!O:O,"Concluído") -> 2 | H7: =G7/E7 -> 1 | I7: =COUNTIF(LEGALP_INSTRUMENT_COUNTERPARTY!O:O,"Mapeamento com LT fechado, mas parametrização pendente") -> 0 | J7: =I7/E7 -> 0 | K7: =COUNTIF(LEGALP_INSTRUMENT_COUNTERPARTY!O:O,"Novo campo, mapeamento datalake fechado, com necessidade de criar parametrização") -> 0 | L7: =K7/E7 -> 0 | M7: =COUNTIF(LEGALP_INSTRUMENT_COUNTERPARTY!O:O,"Novo campo, mapeamento datalake fechado, sem necessidade de criar parametrização") -> 0 | N7: =M7/E7 -> 0 | O7: =COUNTIF(LEGALP_INSTRUMENT_COUNTERPARTY!O:O,"Novo campo, mapeamento datalake pendente, com necessidade de criar parametrização") -> 0 | P7: =O7/E7 -> 0 | Q7: =COUNTIF(LEGALP_INSTRUMENT_COUNTERPARTY!O:O,"Novo campo, mapeamento datalake pendente, sem necessidade de criar parametrização") -> 0 | R7: =Q7/E7 -> 0 | S7: =COUNTIF(LEGALP_INSTRUMENT_COUNTERPARTY!O:O,"Por iniciar") -> 0 | T7: =S7/E7 -> 0 | U7: =COUNTIF(LEGALP_INSTRUMENT_COUNTERPARTY!P:P,"Concluído") -> 2 | V7: =U7/E7 -> 1 | W7: =COUNTIF(LEGALP_INSTRUMENT_COUNTERPARTY!P:P,"Em desenvolvimento") -> 0 | X7: =W7/E7 -> 0 | Y7: =COUNTIF(LEGALP_INSTRUMENT_COUNTERPARTY!P:P,"Aguarda desenvolvimento de outras equipas") -> 0 | Z7: =Y7/E7 -> 0 | AA7: =COUNTIF(LEGALP_INSTRUMENT_COUNTERPARTY!P:P,"Por especificar") -> 0 | AB7: =AA7/E7 -> 0
C8: Instrument-Protection relation | D8: XXXXX_YYYYMMDD_01_05_leg_instr_prot.csv | E8: =COUNTA(LEGALP_INSTRUMENT_PROTECTION!A3:A10) -> 2 | F8: =SUM(H8,J8,L8,N8,P8,R8,T8) -> 1 | G8: =COUNTIF(LEGALP_INSTRUMENT_PROTECTION!O:O,"Concluído") -> 2 | H8: =G8/E8 -> 1 | I8: =COUNTIF(LEGALP_INSTRUMENT_PROTECTION!O:O,"Mapeamento com LT fechado, mas parametrização pendente") -> 0 | J8: =I8/E8 -> 0 | K8: =COUNTIF(LEGALP_INSTRUMENT_PROTECTION!O:O,"Novo campo, mapeamento datalake fechado, com necessidade de criar parametrização") -> 0 | L8: =K8/E8 -> 0 | M8: =COUNTIF(LEGALP_INSTRUMENT_PROTECTION!O:O,"Novo campo, mapeamento datalake fechado, sem necessidade de criar parametrização") -> 0 | N8: =M8/E8 -> 0 | O8: =COUNTIF(LEGALP_INSTRUMENT_PROTECTION!O:O,"Novo campo, mapeamento datalake pendente, com necessidade de criar parametrização") -> 0 | P8: =O8/E8 -> 0 | Q8: =COUNTIF(LEGALP_INSTRUMENT_PROTECTION!O:O,"Novo campo, mapeamento datalake pendente, sem necessidade de criar parametrização") -> 0 | R8: =Q8/E8 -> 0 | S8: =COUNTIF(LEGALP_INSTRUMENT_PROTECTION!O:O,"Por iniciar") -> 0 | T8: =S8/E8 -> 0 | U8: =COUNTIF(LEGALP_INSTRUMENT_PROTECTION!P:P,"Concluído") -> 2 | V8: =U8/E8 -> 1 | W8: =COUNTIF(LEGALP_INSTRUMENT_PROTECTION!P:P,"Em desenvolvimento") -> 0 | X8: =W8/E8 -> 0 | Y8: =COUNTIF(LEGALP_INSTRUMENT_PROTECTION!P:P,"Aguarda desenvolvimento de outras equipas") -> 0 | Z8: =Y8/E8 -> 0 | AA8: =COUNTIF(LEGALP_INSTRUMENT_PROTECTION!P:P,"Por especificar") -> 0 | AB8: =AA8/E8 -> 0
B9: Exposures to natural persons | C9: Instruments | D9: XXXXX_YYYYMMDD_02_01_nat_instr.csv | E9: =COUNTA(NATURALP_INSTRUMENTS!A3:A142) -> 53 | F9: =SUM(H9,J9,L9,N9,P9,R9,T9) -> 1 | G9: =COUNTIF(NATURALP_INSTRUMENTS!P:P,"Concluído") -> 53 | H9: =G9/E9 -> 1 | I9: =COUNTIF(NATURALP_INSTRUMENTS!P:P,"Mapeamento com LT fechado, mas parametrização pendente") -> 0 | J9: =I9/E9 -> 0 | K9: =COUNTIF(NATURALP_INSTRUMENTS!P:P,"Novo campo, mapeamento datalake fechado, com necessidade de criar parametrização") -> 0 | L9: =K9/E9 -> 0 | M9: =COUNTIF(NATURALP_INSTRUMENTS!P:P,"Novo campo, mapeamento datalake fechado, sem necessidade de criar parametrização") -> 0 | N9: =M9/E9 -> 0 | O9: =COUNTIF(NATURALP_INSTRUMENTS!P:P,"Novo campo, mapeamento datalake pendente, com necessidade de criar parametrização") -> 0 | P9: =O9/E9 -> 0 | Q9: =COUNTIF(NATURALP_INSTRUMENTS!P:P,"Novo campo, mapeamento datalake pendente, sem necessidade de criar parametrização") -> 0 | R9: =Q9/E9 -> 0 | S9: =COUNTIF(NATURALP_INSTRUMENTS!P:P,"Por iniciar") -> 0 | T9: =S9/E9 -> 0 | U9: =COUNTIF(NATURALP_INSTRUMENTS!Q:Q,"Concluído") -> 53 | V9: =U9/E9 -> 1 | W9: =COUNTIF(NATURALP_INSTRUMENTS!Q:Q,"Em desenvolvimento") -> 0 | X9: =W9/E9 -> 0 | Y9: =COUNTIF(NATURALP_INSTRUMENTS!Q:Q,"Aguarda desenvolvimento de outras equipas") -> 0 | Z9: =Y9/E9 -> 0 | AA9: =COUNTIF(NATURALP_INSTRUMENTS!Q:Q,"Por especificar") -> 0 | AB9: =AA9/E9 -> 0
C10: Counterparties | D10: XXXXX_YYYYMMDD_02_02_nat_count.csv | E10: =COUNTA(NATURALP_COUNTERPARTIES!A3:A29) -> 8 | F10: =SUM(H10,J10,L10,N10,P10,R10,T10) -> 1 | G10: =COUNTIF(NATURALP_COUNTERPARTIES!O:O,"Concluído") -> 8 | H10: =G10/E10 -> 1 | I10: =COUNTIF(NATURALP_COUNTERPARTIES!O:O,"Mapeamento com LT fechado, mas parametrização pendente") -> 0 | J10: =I10/E10 -> 0 | K10: =COUNTIF(NATURALP_COUNTERPARTIES!O:O,"Novo campo, mapeamento datalake fechado, com necessidade de criar parametrização") -> 0 | L10: =K10/E10 -> 0 | M10: =COUNTIF(NATURALP_COUNTERPARTIES!O:O,"Novo campo, mapeamento datalake fechado, sem necessidade de criar parametrização") -> 0 | N10: =M10/E10 -> 0 | O10: =COUNTIF(NATURALP_COUNTERPARTIES!O:O,"Novo campo, mapeamento datalake pendente, com necessidade de criar parametrização") -> 0 | P10: =O10/E10 -> 0 | Q10: =COUNTIF(NATURALP_COUNTERPARTIES!O:O,"Novo campo, mapeamento datalake pendente, sem necessidade de criar parametrização") -> 0 | R10: =Q10/E10 -> 0 | S10: =COUNTIF(NATURALP_COUNTERPARTIES!O:O,"Por iniciar") -> 0 | T10: =S10/E10 -> 0 | U10: =COUNTIF(NATURALP_COUNTERPARTIES!P:P,"Concluído") -> 8 | V10: =U10/E10 -> 1 | W10: =COUNTIF(NATURALP_COUNTERPARTIES!P:P,"Em desenvolvimento") -> 0 | X10: =W10/E10 -> 0 | Y10: =COUNTIF(NATURALP_COUNTERPARTIES!P:P,"Aguarda desenvolvimento de outras equipas") -> 0 | Z10: =Y10/E10 -> 0 | AA10: =COUNTIF(NATURALP_COUNTERPARTIES!P:P,"Por especificar") -> 0 | AB10: =AA10/E10 -> 0
C11: Protections | D11: XXXXX_YYYYMMDD_02_03_nat_prot.csv | E11: =COUNTA(NATURALP_PROTECTIONS!A3:A27) -> 17 | F11: =SUM(H11,J11,L11,N11,P11,R11,T11) -> 1 | G11: =COUNTIF(NATURALP_PROTECTIONS!O:O,"Concluído") -> 17 | H11: =G11/E11 -> 1 | I11: =COUNTIF(NATURALP_PROTECTIONS!O:O,"Mapeamento com LT fechado, mas parametrização pendente") -> 0 | J11: =I11/E11 -> 0 | K11: =COUNTIF(NATURALP_PROTECTIONS!O:O,"Novo campo, mapeamento datalake fechado, com necessidade de criar parametrização") -> 0 | L11: =K11/E11 -> 0 | M11: =COUNTIF(NATURALP_PROTECTIONS!O:O,"Novo campo, mapeamento datalake fechado, sem necessidade de criar parametrização") -> 0 | N11: =M11/E11 -> 0 | O11: =COUNTIF(NATURALP_PROTECTIONS!O:O,"Novo campo, mapeamento datalake pendente, com necessidade de criar parametrização") -> 0 | P11: =O11/E11 -> 0 | Q11: =COUNTIF(NATURALP_PROTECTIONS!O:O,"Novo campo, mapeamento datalake pendente, sem necessidade de criar parametrização") -> 0 | R11: =Q11/E11 -> 0 | S11: =COUNTIF(NATURALP_PROTECTIONS!O:O,"Por iniciar") -> 0 | T11: =S11/E11 -> 0 | U11: =COUNTIF(NATURALP_PROTECTIONS!P:P,"Concluído") -> 17 | V11: =U11/E11 -> 1 | W11: =COUNTIF(NATURALP_PROTECTIONS!P:P,"Em desenvolvimento") -> 0 | X11: =W11/E11 -> 0 | Y11: =COUNTIF(NATURALP_PROTECTIONS!P:P,"Aguarda desenvolvimento de outras equipas") -> 0 | Z11: =Y11/E11 -> 0 | AA11: =COUNTIF(NATURALP_PROTECTIONS!P:P,"Por especificar") -> 0 | AB11: =AA11/E11 -> 0
C12: Instrument-Counterparty relation | D12: XXXXX_YYYYMMDD_02_04_nat_instr_count.csv | E12: =COUNTA(NATURALP_INSTRUMENT_COUNTERPART!A3:A9) -> 4 | F12: =SUM(H12,J12,L12,N12,P12,R12,T12) -> 1 | G12: =COUNTIF(NATURALP_INSTRUMENT_COUNTERPART!P:P,"Concluído") -> 4 | H12: =G12/E12 -> 1 | I12: =COUNTIF(NATURALP_INSTRUMENT_COUNTERPART!P:P,"Mapeamento com LT fechado, mas parametrização pendente") -> 0 | J12: =I12/E12 -> 0 | K12: =COUNTIF(NATURALP_INSTRUMENT_COUNTERPART!P:P,"Novo campo, mapeamento datalake fechado, com necessidade de criar parametrização") -> 0 | L12: =K12/E12 -> 0 | M12: =COUNTIF(NATURALP_INSTRUMENT_COUNTERPART!P:P,"Novo campo, mapeamento datalake fechado, sem necessidade de criar parametrização") -> 0 | N12: =M12/E12 -> 0 | O12: =COUNTIF(NATURALP_INSTRUMENT_COUNTERPART!P:P,"Novo campo, mapeamento datalake pendente, com necessidade de criar parametrização") -> 0 | P12: =O12/E12 -> 0 | Q12: =COUNTIF(NATURALP_INSTRUMENT_COUNTERPART!P:P,"Novo campo, mapeamento datalake pendente, sem necessidade de criar parametrização") -> 0 | R12: =Q12/E12 -> 0 | S12: =COUNTIF(NATURALP_INSTRUMENT_COUNTERPART!P:P,"Por iniciar") -> 0 | T12: =S12/E12 -> 0 | U12: =COUNTIF(NATURALP_INSTRUMENT_COUNTERPART!Q:Q,"Concluído") -> 4 | V12: =U12/E12 -> 1 | W12: =COUNTIF(NATURALP_INSTRUMENT_COUNTERPART!Q:Q,"Em desenvolvimento") -> 0 | X12: =W12/E12 -> 0 | Y12: =COUNTIF(NATURALP_INSTRUMENT_COUNTERPART!Q:Q,"Aguarda desenvolvimento de outras equipas") -> 0 | Z12: =Y12/E12 -> 0 | AA12: =COUNTIF(NATURALP_INSTRUMENT_COUNTERPART!Q:Q,"Por especificar") -> 0 | AB12: =AA12/E12 -> 0
C13: Instrument-Protection relation | D13: XXXXX_YYYYMMDD_02_05_nat_instr_prot.csv | E13: =COUNTA(NATURALP_INSTRUMENT_PROTECTION!A3:A12) -> 4 | F13: =SUM(H13,J13,L13,N13,P13,R13,T13) -> 1 | G13: =COUNTIF(NATURALP_INSTRUMENT_PROTECTION!O:O,"Concluído") -> 4 | H13: =G13/E13 -> 1 | I13: =COUNTIF(NATURALP_INSTRUMENT_PROTECTION!O:O,"Mapeamento com LT fechado, mas parametrização pendente") -> 0 | J13: =I13/E13 -> 0 | K13: =COUNTIF(NATURALP_INSTRUMENT_PROTECTION!O:O,"Novo campo, mapeamento datalake fechado, com necessidade de criar parametrização") -> 0 | L13: =K13/E13 -> 0 | M13: =COUNTIF(NATURALP_INSTRUMENT_PROTECTION!O:O,"Novo campo, mapeamento datalake fechado, sem necessidade de criar parametrização") -> 0 | N13: =M13/E13 -> 0 | O13: =COUNTIF(NATURALP_INSTRUMENT_PROTECTION!O:O,"Novo campo, mapeamento datalake pendente, com necessidade de criar parametrização") -> 0 | P13: =O13/E13 -> 0 | Q13: =COUNTIF(NATURALP_INSTRUMENT_PROTECTION!O:O,"Novo campo, mapeamento datalake pendente, sem necessidade de criar parametrização") -> 0 | R13: =Q13/E13 -> 0 | S13: =COUNTIF(NATURALP_INSTRUMENT_PROTECTION!O:O,"Por iniciar") -> 0 | T13: =S13/E13 -> 0 | U13: =COUNTIF(NATURALP_INSTRUMENT_PROTECTION!P:P,"Concluído") -> 4 | V13: =U13/E13 -> 1 | W13: =COUNTIF(NATURALP_INSTRUMENT_PROTECTION!P:P,"Em desenvolvimento") -> 0 | X13: =W13/E13 -> 0 | Y13: =COUNTIF(NATURALP_INSTRUMENT_PROTECTION!P:P,"Aguarda desenvolvimento de outras equipas") -> 0 | Z13: =Y13/E13 -> 0 | AA13: =COUNTIF(NATURALP_INSTRUMENT_PROTECTION!P:P,"Por especificar") -> 0 | AB13: =AA13/E13 -> 0
B14: Off-balance sheet exposures | C14: Instruments | D14: XXXXX_YYYYMMDD_03_01_off_instr.csv | E14: =COUNTA(OFFBAL_INSTRUMENTS!A3:A67) -> 27 | F14: =SUM(H14,J14,L14,N14,P14,R14,T14) -> 1 | G14: =COUNTIF(OFFBAL_INSTRUMENTS!O:O,"Concluído") -> 27 | H14: =G14/E14 -> 1 | I14: =COUNTIF(OFFBAL_INSTRUMENTS!O:O,"Mapeamento com LT fechado, mas parametrização pendente") -> 0 | J14: =I14/E14 -> 0 | K14: =COUNTIF(OFFBAL_INSTRUMENTS!O:O,"Novo campo, mapeamento datalake fechado, com necessidade de criar parametrização") -> 0 | L14: =K14/E14 -> 0 | M14: =COUNTIF(OFFBAL_INSTRUMENTS!O:O,"Novo campo, mapeamento datalake fechado, sem necessidade de criar parametrização") -> 0 | N14: =M14/E14 -> 0 | O14: =COUNTIF(OFFBAL_INSTRUMENTS!O:O,"Novo campo, mapeamento datalake pendente, com necessidade de criar parametrização") -> 0 | P14: =O14/E14 -> 0 | Q14: =COUNTIF(OFFBAL_INSTRUMENTS!O:O,"Novo campo, mapeamento datalake pendente, sem necessidade de criar parametrização") -> 0 | R14: =Q14/E14 -> 0 | S14: =COUNTIF(OFFBAL_INSTRUMENTS!O:O,"Por iniciar") -> 0 | T14: =S14/E14 -> 0 | U14: =COUNTIF(OFFBAL_INSTRUMENTS!P:P,"Concluído") -> 27 | V14: =U14/E14 -> 1 | W14: =COUNTIF(OFFBAL_INSTRUMENTS!P:P,"Em desenvolvimento") -> 0 | X14: =W14/E14 -> 0 | Y14: =COUNTIF(OFFBAL_INSTRUMENTS!P:P,"Aguarda desenvolvimento de outras equipas") -> 0 | Z14: =Y14/E14 -> 0 | AA14: =COUNTIF(OFFBAL_INSTRUMENTS!P:P,"Por especificar") -> 0 | AB14: =AA14/E14 -> 0
C15: Counterparties | D15: XXXXX_YYYYMMDD_03_02_off_count.csv | E15: =COUNTA(OFFBAL_COUNTERPARTIES!A3:A59) -> 30 | F15: =SUM(H15,J15,L15,N15,P15,R15,T15) -> 1 | G15: =COUNTIF(OFFBAL_COUNTERPARTIES!O:O,"Concluído") -> 30 | H15: =G15/E15 -> 1 | I15: =COUNTIF(OFFBAL_COUNTERPARTIES!O:O,"Mapeamento com LT fechado, mas parametrização pendente") -> 0 | J15: =I15/E15 -> 0 | K15: =COUNTIF(OFFBAL_COUNTERPARTIES!O:O,"Novo campo, mapeamento datalake fechado, com necessidade de criar parametrização") -> 0 | L15: =K15/E15 -> 0 | M15: =COUNTIF(OFFBAL_COUNTERPARTIES!O:O,"Novo campo, mapeamento datalake fechado, sem necessidade de criar parametrização") -> 0 | N15: =M15/E15 -> 0 | O15: =COUNTIF(OFFBAL_COUNTERPARTIES!O:O,"Novo campo, mapeamento datalake pendente, com necessidade de criar parametrização") -> 0 | P15: =O15/E15 -> 0 | Q15: =COUNTIF(OFFBAL_COUNTERPARTIES!O:O,"Novo campo, mapeamento datalake pendente, sem necessidade de criar parametrização") -> 0 | R15: =Q15/E15 -> 0 | S15: =COUNTIF(OFFBAL_COUNTERPARTIES!O:O,"Por iniciar") -> 0 | T15: =S15/E15 -> 0 | U15: =COUNTIF(OFFBAL_COUNTERPARTIES!P:P,"Concluído") -> 30 | V15: =U15/E15 -> 1 | W15: =COUNTIF(OFFBAL_COUNTERPARTIES!P:P,"Em desenvolvimento") -> 0 | X15: =W15/E15 -> 0 | Y15: =COUNTIF(OFFBAL_COUNTERPARTIES!P:P,"Aguarda desenvolvimento de outras equipas") -> 0 | Z15: =Y15/E15 -> 0 | AA15: =COUNTIF(OFFBAL_COUNTERPARTIES!P:P,"Por especificar") -> 0 | AB15: =AA15/E15 -> 0
C16: Protections | D16: XXXXX_YYYYMMDD_03_03_off_prot.csv | E16: =COUNTA(OFFBAL_PROTECTIONS!A3:A27) -> 17 | F16: =SUM(H16,J16,L16,N16,P16,R16,T16) -> 1 | G16: =COUNTIF(OFFBAL_PROTECTIONS!O:O,"Concluído") -> 17 | H16: =G16/E16 -> 1 | I16: =COUNTIF(OFFBAL_PROTECTIONS!O:O,"Mapeamento com LT fechado, mas parametrização pendente") -> 0 | J16: =I16/E16 -> 0 | K16: =COUNTIF(OFFBAL_PROTECTIONS!O:O,"Novo campo, mapeamento datalake fechado, com necessidade de criar parametrização") -> 0 | L16: =K16/E16 -> 0 | M16: =COUNTIF(OFFBAL_PROTECTIONS!O:O,"Novo campo, mapeamento datalake fechado, sem necessidade de criar parametrização") -> 0 | N16: =M16/E16 -> 0 | O16: =COUNTIF(OFFBAL_PROTECTIONS!O:O,"Novo campo, mapeamento datalake pendente, com necessidade de criar parametrização") -> 0 | P16: =O16/E16 -> 0 | Q16: =COUNTIF(OFFBAL_PROTECTIONS!O:O,"Novo campo, mapeamento datalake pendente, sem necessidade de criar parametrização") -> 0 | R16: =Q16/E16 -> 0 | S16: =COUNTIF(OFFBAL_PROTECTIONS!O:O,"Por iniciar") -> 0 | T16: =S16/E16 -> 0 | U16: =COUNTIF(OFFBAL_PROTECTIONS!P:P,"Concluído") -> 17 | V16: =U16/E16 -> 1 | W16: =COUNTIF(OFFBAL_PROTECTIONS!P:P,"Em desenvolvimento") -> 0 | X16: =W16/E16 -> 0 | Y16: =COUNTIF(OFFBAL_PROTECTIONS!P:P,"Aguarda desenvolvimento de outras equipas") -> 0 | Z16: =Y16/E16 -> 0 | AA16: =COUNTIF(OFFBAL_PROTECTIONS!P:P,"Por especificar") -> 0 | AB16: =AA16/E16 -> 0
C17: Instrument-Counterparty relation | D17: XXXXX_YYYYMMDD_03_04_off_instr_count.csv | E17: =COUNTA(OFFBAL_INSTRUMENT_COUNTERPARTY!A3:A8) -> 3 | F17: =SUM(H17,J17,L17,N17,P17,R17,T17) -> 1 | G17: =COUNTIF(OFFBAL_INSTRUMENT_COUNTERPARTY!O:O,"Concluído") -> 3 | H17: =G17/E17 -> 1 | I17: =COUNTIF(OFFBAL_INSTRUMENT_COUNTERPARTY!O:O,"Mapeamento com LT fechado, mas parametrização pendente") -> 0 | J17: =I17/E17 -> 0 | K17: =COUNTIF(OFFBAL_INSTRUMENT_COUNTERPARTY!O:O,"Novo campo, mapeamento datalake fechado, com necessidade de criar parametrização") -> 0 | L17: =K17/E17 -> 0 | M17: =COUNTIF(OFFBAL_INSTRUMENT_COUNTERPARTY!O:O,"Novo campo, mapeamento datalake fechado, sem necessidade de criar parametrização") -> 0 | N17: =M17/E17 -> 0 | O17: =COUNTIF(OFFBAL_INSTRUMENT_COUNTERPARTY!O:O,"Novo campo, mapeamento datalake pendente, com necessidade de criar parametrização") -> 0 | P17: =O17/E17 -> 0 | Q17: =COUNTIF(OFFBAL_INSTRUMENT_COUNTERPARTY!O:O,"Novo campo, mapeamento datalake pendente, sem necessidade de criar parametrização") -> 0 | R17: =Q17/E17 -> 0 | S17: =COUNTIF(OFFBAL_INSTRUMENT_COUNTERPARTY!O:O,"Por iniciar") -> 0 | T17: =S17/E17 -> 0 | U17: =COUNTIF(OFFBAL_INSTRUMENT_COUNTERPARTY!P:P,"Concluído") -> 3 | V17: =U17/E17 -> 1 | W17: =COUNTIF(OFFBAL_INSTRUMENT_COUNTERPARTY!P:P,"Em desenvolvimento") -> 0 | X17: =W17/E17 -> 0 | Y17: =COUNTIF(OFFBAL_INSTRUMENT_COUNTERPARTY!P:P,"Aguarda desenvolvimento de outras equipas") -> 0 | Z17: =Y17/E17 -> 0 | AA17: =COUNTIF(OFFBAL_INSTRUMENT_COUNTERPARTY!P:P,"Por especificar") -> 0 | AB17: =AA17/E17 -> 0
C18: Instrument-Protection relation | D18: XXXXX_YYYYMMDD_03_05_off_instr_prot.csv | E18: =COUNTA(OFFBAL_INSTRUMENT_PROTECTION!A3:A12) -> 4 | F18: =SUM(H18,J18,L18,N18,P18,R18,T18) -> 1 | G18: =COUNTIF(OFFBAL_INSTRUMENT_PROTECTION!O:O,"Concluído") -> 4 | H18: =G18/E18 -> 1 | I18: =COUNTIF(OFFBAL_INSTRUMENT_PROTECTION!O:O,"Mapeamento com LT fechado, mas parametrização pendente") -> 0 | J18: =I18/E18 -> 0 | K18: =COUNTIF(OFFBAL_INSTRUMENT_PROTECTION!O:O,"Novo campo, mapeamento datalake fechado, com necessidade de criar parametrização") -> 0 | L18: =K18/E18 -> 0 | M18: =COUNTIF(OFFBAL_INSTRUMENT_PROTECTION!O:O,"Novo campo, mapeamento datalake fechado, sem necessidade de criar parametrização") -> 0 | N18: =M18/E18 -> 0 | O18: =COUNTIF(OFFBAL_INSTRUMENT_PROTECTION!O:O,"Novo campo, mapeamento datalake pendente, com necessidade de criar parametrização") -> 0 | P18: =O18/E18 -> 0 | Q18: =COUNTIF(OFFBAL_INSTRUMENT_PROTECTION!O:O,"Novo campo, mapeamento datalake pendente, sem necessidade de criar parametrização") -> 0 | R18: =Q18/E18 -> 0 | S18: =COUNTIF(OFFBAL_INSTRUMENT_PROTECTION!O:O,"Por iniciar") -> 0 | T18: =S18/E18 -> 0 | U18: =COUNTIF(OFFBAL_INSTRUMENT_PROTECTION!P:P,"Concluído") -> 4 | V18: =U18/E18 -> 1 | W18: =COUNTIF(OFFBAL_INSTRUMENT_PROTECTION!P:P,"Em desenvolvimento") -> 0 | X18: =W18/E18 -> 0 | Y18: =COUNTIF(OFFBAL_INSTRUMENT_PROTECTION!P:P,"Aguarda desenvolvimento de outras equipas") -> 0 | Z18: =Y18/E18 -> 0 | AA18: =COUNTIF(OFFBAL_INSTRUMENT_PROTECTION!P:P,"Por especificar") -> 0 | AB18: =AA18/E18 -> 0
B19: Derivatives | C19: Instruments | D19: XXXXX_YYYYMMDD_04_01_derivatives.csv | E19: =COUNTA(DERIVATIVES!A3:A69) -> 29 | F19: =SUM(H19,J19,L19,N19,P19,R19,T19) -> 1 | G19: =COUNTIF(DERIVATIVES!O:O,"Concluído") -> 29 | H19: =G19/E19 -> 1 | I19: =COUNTIF(DERIVATIVES!O:O,"Mapeamento com LT fechado, mas parametrização pendente") -> 0 | J19: =I19/E19 -> 0 | K19: =COUNTIF(DERIVATIVES!O:O,"Novo campo, mapeamento datalake fechado, com necessidade de criar parametrização") -> 0 | L19: =K19/E19 -> 0 | M19: =COUNTIF(DERIVATIVES!O:O,"Novo campo, mapeamento datalake fechado, sem necessidade de criar parametrização") -> 0 | N19: =M19/E19 -> 0 | O19: =COUNTIF(DERIVATIVES!O:O,"Novo campo, mapeamento datalake pendente, com necessidade de criar parametrização") -> 0 | P19: =O19/E19 -> 0 | Q19: =COUNTIF(DERIVATIVES!O:O,"Novo campo, mapeamento datalake pendente, sem necessidade de criar parametrização") -> 0 | R19: =Q19/E19 -> 0 | S19: =COUNTIF(DERIVATIVES!O:O,"Por iniciar") -> 0 | T19: =S19/E19 -> 0 | U19: =COUNTIF(DERIVATIVES!P:P,"Concluído") -> 29 | V19: =U19/E19 -> 1 | W19: =COUNTIF(DERIVATIVES!P:P,"Em desenvolvimento") -> 0 | X19: =W19/E19 -> 0 | Y19: =COUNTIF(DERIVATIVES!P:P,"Aguarda desenvolvimento de outras equipas") -> 0 | Z19: =Y19/E19 -> 0 | AA19: =COUNTIF(DERIVATIVES!P:P,"Por especificar") -> 0 | AB19: =AA19/E19 -> 0
B20: Debt securities | C20: Instruments | D20: XXXXX_YYYYMMDD_05_01_debtsecurities.csv | E20: =COUNTA(DEBT_SECURITIES!A3:A77) -> 40 | F20: =SUM(H20,J20,L20,N20,P20,R20,T20) -> 1 | G20: =COUNTIF(DEBT_SECURITIES!O:O,"Concluído") -> 40 | H20: =G20/E20 -> 1 | I20: =COUNTIF(DEBT_SECURITIES!O:O,"Mapeamento com LT fechado, mas parametrização pendente") -> 0 | J20: =I20/E20 -> 0 | K20: =COUNTIF(DEBT_SECURITIES!O:O,"Novo campo, mapeamento datalake fechado, com necessidade de criar parametrização") -> 0 | L20: =K20/E20 -> 0 | M20: =COUNTIF(DEBT_SECURITIES!O:O,"Novo campo, mapeamento datalake fechado, sem necessidade de criar parametrização") -> 0 | N20: =M20/E20 -> 0 | O20: =COUNTIF(DEBT_SECURITIES!O:O,"Novo campo, mapeamento datalake pendente, com necessidade de criar parametrização") -> 0 | P20: =O20/E20 -> 0 | Q20: =COUNTIF(DEBT_SECURITIES!O:O,"Novo campo, mapeamento datalake pendente, sem necessidade de criar parametrização") -> 0 | R20: =Q20/E20 -> 0 | S20: =COUNTIF(DEBT_SECURITIES!O:O,"Por iniciar") -> 0 | T20: =S20/E20 -> 0 | U20: =COUNTIF(DEBT_SECURITIES!P:P,"Concluído") -> 40 | V20: =U20/E20 -> 1 | W20: =COUNTIF(DEBT_SECURITIES!P:P,"Em desenvolvimento") -> 0 | X20: =W20/E20 -> 0 | Y20: =COUNTIF(DEBT_SECURITIES!P:P,"Aguarda desenvolvimento de outras equipas") -> 0 | Z20: =Y20/E20 -> 0 | AA20: =COUNTIF(DEBT_SECURITIES!P:P,"Por especificar") -> 0 | AB20: =AA20/E20 -> 0
B21: Equity | C21: Instruments | D21: XXXXX_YYYYMMDD_06_01_equity.csv | E21: =COUNTA(EQUITY_INSTRUMENTS!A3:A35) -> 18 | F21: =SUM(H21,J21,L21,N21,P21,R21,T21) -> 1 | G21: =COUNTIF(EQUITY_INSTRUMENTS!O:O,"Concluído") -> 18 | H21: =G21/E21 -> 1 | I21: =COUNTIF(EQUITY_INSTRUMENTS!O:O,"Mapeamento com LT fechado, mas parametrização pendente") -> 0 | J21: =I21/E21 -> 0 | K21: =COUNTIF(EQUITY_INSTRUMENTS!O:O,"Novo campo, mapeamento datalake fechado, com necessidade de criar parametrização") -> 0 | L21: =K21/E21 -> 0 | M21: =COUNTIF(EQUITY_INSTRUMENTS!O:O,"Novo campo, mapeamento datalake fechado, sem necessidade de criar parametrização") -> 0 | N21: =M21/E21 -> 0 | O21: =COUNTIF(EQUITY_INSTRUMENTS!O:O,"Novo campo, mapeamento datalake pendente, com necessidade de criar parametrização") -> 0 | P21: =O21/E21 -> 0 | Q21: =COUNTIF(EQUITY_INSTRUMENTS!O:O,"Novo campo, mapeamento datalake pendente, sem necessidade de criar parametrização") -> 0 | R21: =Q21/E21 -> 0 | S21: =COUNTIF(EQUITY_INSTRUMENTS!O:O,"Por iniciar") -> 0 | T21: =S21/E21 -> 0 | U21: =COUNTIF(EQUITY_INSTRUMENTS!P:P,"Concluído") -> 18 | V21: =U21/E21 -> 1 | W21: =COUNTIF(EQUITY_INSTRUMENTS!P:P,"Em desenvolvimento") -> 0 | X21: =W21/E21 -> 0 | Y21: =COUNTIF(EQUITY_INSTRUMENTS!P:P,"Aguarda desenvolvimento de outras equipas") -> 0 | Z21: =Y21/E21 -> 0 | AA21: =COUNTIF(EQUITY_INSTRUMENTS!P:P,"Por especificar") -> 0 | AB21: =AA21/E21 -> 0
B22: DTAs/DTCs | C22: - | D22: XXXXX_YYYYMMDD_07_01_dtasdtcs.csv | E22: =COUNTA(DTA_DTC!A3:A19) -> 17 | F22: =SUM(H22,J22,L22,N22,P22,R22,T22) -> 1 | G22: =COUNTIF(DTA_DTC!M:M,"Concluído") -> 17 | H22: =G22/E22 -> 1 | I22: =COUNTIF(DTA_DTC!M:M,"Mapeamento com LT fechado, mas parametrização pendente") -> 0 | J22: =I22/E22 -> 0 | K22: =COUNTIF(DTA_DTC!M:M,"Novo campo, mapeamento datalake fechado, com necessidade de criar parametrização") -> 0 | L22: =K22/E22 -> 0 | M22: =COUNTIF(DTA_DTC!M:M,"Novo campo, mapeamento datalake fechado, sem necessidade de criar parametrização") -> 0 | N22: =M22/E22 -> 0 | O22: =COUNTIF(DTA_DTC!M:M,"Novo campo, mapeamento datalake pendente, com necessidade de criar parametrização") -> 0 | P22: =O22/E22 -> 0 | Q22: =COUNTIF(DTA_DTC!M:M,"Novo campo, mapeamento datalake pendente, sem necessidade de criar parametrização") -> 0 | R22: =Q22/E22 -> 0 | S22: =COUNTIF(DTA_DTC!M:M,"Por iniciar") -> 0 | T22: =S22/E22 -> 0 | U22: =COUNTIF(DTA_DTC!N:N,"Concluído") -> 17 | V22: =U22/E22 -> 1 | W22: =COUNTIF(DTA_DTC!N:N,"Mapeamento com LT fechado, mas parametrização pendente") -> 0 | X22: =W22/E22 -> 0 | Y22: =COUNTIF(DTA_DTC!N:N,"Novo campo, mapeamento datalake fechado, com necessidade de criar parametrização") -> 0 | Z22: =Y22/E22 -> 0 | AA22: =COUNTIF(DTA_DTC!N:N,"Novo campo, mapeamento datalake fechado, sem necessidade de criar parametrização") -> 0 | AB22: =AA22/E22 -> 0 | AC22: Produzido manualmente pela Contabilidade
B23: Intangible assets | C23: - | D23: XXXXX_YYYYMMDD_08_01_intangible.csv | E23: =COUNTA(INTANGIBLE_ASSETS!A3:A15) -> 13 | F23: =SUM(H23,J23,L23,N23,P23,R23,T23) -> 1 | G23: =COUNTIF(INTANGIBLE_ASSETS!M:M,"Concluído") -> 13 | H23: =G23/E23 -> 1 | I23: =COUNTIF(INTANGIBLE_ASSETS!M:M,"Mapeamento com LT fechado, mas parametrização pendente") -> 0 | J23: =I23/E23 -> 0 | K23: =COUNTIF(INTANGIBLE_ASSETS!M:M,"Novo campo, mapeamento datalake fechado, com necessidade de criar parametrização") -> 0 | L23: =K23/E23 -> 0 | M23: =COUNTIF(INTANGIBLE_ASSETS!M:M,"Novo campo, mapeamento datalake fechado, sem necessidade de criar parametrização") -> 0 | N23: =M23/E23 -> 0 | O23: =COUNTIF(INTANGIBLE_ASSETS!M:M,"Novo campo, mapeamento datalake pendente, com necessidade de criar parametrização") -> 0 | P23: =O23/E23 -> 0 | Q23: =COUNTIF(INTANGIBLE_ASSETS!M:M,"Novo campo, mapeamento datalake pendente, sem necessidade de criar parametrização") -> 0 | R23: =Q23/E23 -> 0 | S23: =COUNTIF(INTANGIBLE_ASSETS!M:M,"Por iniciar") -> 0 | T23: =S23/E23 -> 0 | U23: =COUNTIF(INTANGIBLE_ASSETS!N:N,"Concluído") -> 13 | V23: =U23/E23 -> 1 | W23: =COUNTIF(INTANGIBLE_ASSETS!N:N,"Mapeamento com LT fechado, mas parametrização pendente") -> 0 | X23: =W23/E23 -> 0 | Y23: =COUNTIF(INTANGIBLE_ASSETS!N:N,"Novo campo, mapeamento datalake fechado, com necessidade de criar parametrização") -> 0 | Z23: =Y23/E23 -> 0 | AA23: =COUNTIF(INTANGIBLE_ASSETS!N:N,"Novo campo, mapeamento datalake fechado, sem necessidade de criar parametrização") -> 0 | AB23: =AA23/E23 -> 0 | AC23: Produzido manualmente pela Contabilidade
C24: Total | E24: =SUM(E4:E23) -> 308 | F24: =SUM(H24,J24,L24,N24,P24,R24,T24) -> 1 | G24: =SUM(G4:G23) -> 308 | H24: =G24/E24 -> 1 | I24: =SUM(I4:I23) -> 0 | J24: =I24/E24 -> 0 | K24: =SUM(K4:K23) -> 0 | L24: =K24/E24 -> 0 | M24: =SUM(M4:M23) -> 0 | N24: =M24/E24 -> 0 | O24: =SUM(O4:O23) -> 0 | P24: =O24/E24 -> 0 | Q24: =SUM(Q4:Q23) -> 0 | R24: =Q24/E24 -> 0 | S24: =SUM(S4:S23) -> 0 | T24: =S24/E24 -> 0 | U24: =SUM(U4:U23) -> 308 | V24: =U24/SUM(E4:E23) -> 1 | W24: =SUM(W4:W23) -> 0 | X24: =W24/SUM(E4:E23) -> 0 | Y24: =SUM(Y4:Y23) -> 0 | Z24: =Y24/SUM(E4:E23) -> 0 | AA24: =SUM(AA4:AA23) -> 0 | AB24: =AA24/SUM(E4:E23) -> 0

Sheet PDS - Desenvolvimento
B2: Table | C2: Table | D2: Exclusivo Report Valuation | E2: Exposures to legal persons | F2: Exposures to natural persons | G2: Off-balance sheet exposures | H2: Derivatives | I2: Debt securities | J2: Equity | K2: Estado Dev
B3: INSTRUMENT | C3: INSTRMNT_ID | E3: x | F3: x | G3: x | I3: x | J3: x | K3: Concluído
B4: INSTRUMENT | C4: CNTRCT_ID | F4: x | G4: x | K4: Concluído
B5: INSTRUMENT | C5: CRRNCY_DNMNTN | F5: x | I5: x | K5: Concluído
B6: INSTRUMENT | C6: DT_INCPTN | F6: x | I6: x | K6: Concluído
B7: INSTRUMENT | C7: OBSRVD_AGNT_ID | F7: x | G7: x | K7: Concluído
B8: INSTRUMENT | C8: OTSTNDNG_NMNL_AMNT_INSTRMNT | E8: carteira | F8: x | K8: Concluído
B9: INSTRUMENT | C9: PRDCT | H9: x | K9: Concluído
B10: INSTRUMENT | C10: DFLT_STTS_INSTRMNT | F10: x | G10: x | K10: Concluído
B11: INSTRUMENT | C11: CPN_CRRNCY | I11: x | K11: Concluído
B12: INSTRUMENT | C12: DT_DFLT_STTS_INSTRMNT | F12: x | G12: x | K12: Concluído
B13: INSTRUMENT | C13: DT_END_INTRST_ONLY | F13: x | K13: Concluído
B14: INSTRUMENT | C14: DT_FRBRNC_STTS | F14: x | G14: x | K14: Concluído
B15: INSTRUMENT | C15: DT_PRFRMNG_STTS | F15: x | G15: x | K15: Concluído
B16: INSTRUMENT | C16: FRBRNC_STTS_INSTRMNT | F16: x | G16: x | K16: Concluído
B17: INSTRUMENT | C17: IMPRMNT_STTS | F17: x | G17: x | K17: Concluído
B18: INSTRUMENT | C18: INTRNL_RTNG | K18: Concluído
B19: INSTRUMENT | C19: INTRNL_SGMNT | E19: x | F19: x | G19: x | K19: Concluído
B20: INSTRUMENT | C20: PRFRMNG_STTS | F20: x | G20: x | I20: x | K20: Concluído
B21: INSTRUMENT | C21: TYP_AMRTSTN | F21: x | K21: Concluído
B22: INSTRUMENT | C22: TYP_INSTRMNT | F22: x | K22: Concluído
B23: INSTRUMENT | C23: TYP_INTRST_RT | F23: x | I23: x | K23: Concluído
B24: INSTRUMENT | C24: GRSS_CRRYNG_AMNT_INSTRMNT | H24: x | K24: Concluído
B25: INSTRUMENT | C25: ACCMLTD_CHNGS_FV_CR_INSTRMNT | F25: x | K25: Concluído
B26: INSTRUMENT | C26: ACCNTNG_CLSSFCTN | F26: x | H26: x | I26: x | J26: x | K26: Concluído
B27: INSTRUMENT | C27: ACCRD_INTRST_INSTRMNT | F27: x | K27: Concluído
B28: INSTRUMENT | C28: CCF | G28: x | K28: Concluído
B29: INSTRUMENT | C29: CMMTMNT_INCPTN_INSTRMNT | F29: x | K29: Concluído
B30: INSTRUMENT | C30: CRRYNG_AMNT_INSTRMNT | F30: x | K30: Concluído
B31: INSTRUMENT | C31: DT_LGL_FNL_MTRTY | F31: x | G31: x | I31: x | K31: Concluído
B32: INSTRUMENT | C32: DT_NXT_INTRST_RT_RST | F32: x | K32: Concluído
B33: INSTRUMENT | C33: OFF_BLNC_SHT_AMNT_INSTRMNT | F33: x | G33: x | K33: Concluído
B34: INSTRUMENT | C34: PRVSNS_OFF_BLNC_SHT | F34: x | K34: Concluído
B35: INSTRUMENT | C35: PYMNT_FRQNCY | F35: x | I35: x | K35: Concluído
B36: INSTRUMENT | C36: RWA | E36: x | F36: x | G36: x | H36: x | I36: x | J36: x | K36: Concluído
B37: INSTRUMENT | C37: ACCMLTD_IMPRMNT_INSTRMNT | F37: x | G37: x | K37: Concluído
B38: INSTRUMENT | C38: ACCMLTD_WRTFFS_INSTRMNT | F38: x | K38: Concluído
B39: INSTRUMENT | C39: ARRRS_INSTRMNT | F39: x | G39: x | K39: Concluído
B40: INSTRUMENT | C40: CMLTV_RCVRS_SNC_DFLT_INSTRMNT | F40: x | K40: Concluído
B41: INSTRUMENT | C41: DT_PST_D | F41: x | G41: x | K41: Concluído
B42: INSTRUMENT | C42: IMPRMNT_ASSSSMNT_MTHD | F42: x | G42: x | K42: Concluído
B43: INSTRUMENT | C43: IFRS9_LGD | E43: x | F43: x | G43: x | K43: Concluído
B44: INSTRUMENT | C44: LGD | E44: x | F44: x | G44: x | K44: Concluído
B45: INSTRUMENT | C45: ANNLSD_AGRD_RT | F45: x | K45: Concluído
B46: INSTRUMENT | C46: INTRST_RT_RST_FRQNCY | F46: x | K46: Concluído
B47: INSTRUMENT | C47: ASST_SCRT_CLSS | I47: x | K47: Concluído
B48: INSTRUMENT | C48: CPN_RT | I48: x | K48: Concluído
B49: INSTRUMENT | C49: DT_VLTN | I49: x | J49: x | K49: Concluído
B50: INSTRUMENT | C50: ELGBLTY_ECB | I50: x | K50: Concluído
B51: INSTRUMENT | C51: GRNTR_ID | I51: x | K51: Concluído
B52: INSTRUMENT | C52: GRNTR_ID_TYP | I52: x | K52: Concluído
B53: INSTRUMENT | C53: HEDGE_ID | H53: x | I53: x | K53: Concluído
B54: INSTRUMENT | C54: INSTR_SNRTY_CLSS | I54: x | K54: Concluído
B55: INSTRUMENT | C55: INSTRMNT_CLSS | I55: x | K55: Concluído
B56: INSTRUMENT | C56: ISIN | I56: x | J56: x | K56: Concluído
B57: INSTRUMENT | C57: ISSR_CNTRY | I57: x | J57: x | K57: Concluído
B58: INSTRUMENT | C58: ISSR_ESA_2010 | I58: x | J58: x | K58: Concluído
B59: INSTRUMENT | C59: ISSR_ID | I59: x | J59: x | K59: Concluído
B60: INSTRUMENT | C60: ISSR_ID_TYP | I60: x | J60: x | K60: Concluído
B61: INSTRUMENT | C61: ISSR_NACE_SCTR | I61: x | J61: x | K61: Concluído
B62: INSTRUMENT | C62: ISSR_RTNG | I62: x | J62: x | K62: Concluído
B63: INSTRUMENT | C63: ISSR_RTNG_SRC | I63: x | J63: x | K63: Concluído
B64: INSTRUMENT | C64: ISSR_TYP | I64: x | J64: x | K64: Concluído
B65: INSTRUMENT | C65: LCR_BFFR_CTGRY | I65: x | K65: Concluído
B66: INSTRUMENT | C66: PRCH_UNDR_RSL_AGR | I66: x | K66: Concluído
B67: INSTRUMENT | C67: PRDNTL_PRTFL | F67: x | H67: x | I67: x | J67: x | K67: Concluído
B68: INSTRUMENT | C68: PRMRY_ASST_CLSSF | I68: x | K68: Concluído
B69: INSTRUMENT | C69: PRT_LCR_BFFR | I69: x | J69: x | K69: Concluído
B70: INSTRUMENT | C70: RFRNC_RT | I70: x | K70: Concluído
B71: INSTRUMENT | C71: SPRD | F71: x | I71: x | K71: Concluído
B72: INSTRUMENT | C72: SRCS_ENCMBRNC | F72: x | I72: x | K72: Concluído
B73: INSTRUMENT | C73: TYPE_OF_PLCMNT | I73: x | K73: Concluído
B74: INSTRUMENT | C74: VLTN_CRRNCY | I74: x | J74: x | K74: Concluído
B75: INSTRUMENT | C75: VLTN_TYP | I75: x | J75: x | K75: Concluído
B76: INSTRUMENT | C76: COD_SOC | F76: x | G76: x | K76: Concluído
B77: INSTRUMENT | C77: COUNTERPARTY_ID | D77: x | E77: x | F77: x | G77: x | H77: x | K77: Concluído
B78: INSTRUMENT | C78: COUNTERPARTY_TYPE_ID | D78: x | H78: x | K78: Concluído
B79: INSTRUMENT | C79: COUNTERPARTY_COUNTRY | D79: x | H79: x | K79: Concluído
B80: INSTRUMENT | C80: DIVIDEND_YIELD | D80: x | J80: x | K80: Concluído
B81: INSTRUMENT | C81: CRR_EXPOSURE_CLASS | D81: x | E81: x | F81: x | G81: x | K81: Concluído
B82: INSTRUMENT | C82: INTEREST_RATE_CAP | D82: x | F82: x | K82: Concluído
B83: INSTRUMENT | C83: INTEREST_RATE_FLOOR | D83: x | F83: x | K83: Concluído
B84: INSTRUMENT | C84: INTRST_INDXNG | D84: x | F84: x | K84: Concluído
B85: INSTRUMENT | C85: SETTLEMENT_DATE | D85: x | F85: x | K85: Concluído
B86: INSTRUMENT | C86: TRANSFERRED_AMOUNT | D86: x | F86: x | K86: Concluído
B87: INSTRUMENT | C87: TYPE_SECURITIZATION | D87: x | F87: x | K87: Concluído
B88: INSTRUMENT | C88: JOINT_LIABILITIES_AMOUNT | D88: x | F88: x | G88: x | K88: Concluído
B89: INSTRUMENT | C89: BALANCE_SHEET_RECOGN | D89: x | F89: x | K89: Concluído
B90: INSTRUMENT | C90: TYPE | D90: x | G90: x | K90: Concluído
B91: INSTRUMENT | C91: NOMINAL_INTEREST_RATE_FEE | D91: x | G91: x | K91: Concluído
B92: INSTRUMENT | C92: UNIQUE_TRADE_ID | D92: x | H92: x | K92: Concluído
B93: INSTRUMENT | C93: BASE_PRODUCT | D93: x | H93: x | K93: Concluído
B94: INSTRUMENT | C94: GOVERNING_LAW | D94: x | H94: x | K94: Concluído
B95: INSTRUMENT | C95: CONTRACT_RECOGN_WRITE_DOWN | D95: x | H95: x | K95: Concluído
B96: INSTRUMENT | C96: CONTRACT_RECOGN_SUSPENSION | D96: x | H96: x | K96: Concluído
B97: INSTRUMENT | C97: CONTRACT_RECOGN_RESOLUTION | D97: x | H97: x | K97: Concluído
B98: INSTRUMENT | C98: COLLATERAL_PORTFOLIO | D98: x | H98: x | K98: Concluído
B99: INSTRUMENT | C99: COLLATERAL_POSTED | D99: x | H99: x | K99: Concluído
B100: INSTRUMENT | C100: COLLATERAL_POSTED_CURRENCY | D100: x | H100: x | K100: Concluído
B101: INSTRUMENT | C101: COLLATERAL_RECEIVED | D101: x | H101: x | K101: Concluído
...

Sheet Filtros dos Segmentos
A1: • Exposures to legal persons: tipo_conta='A' e instrumento_financeiro='credito concedido e outros ativos financeiros' e contraparte <> ‘particulares’ e contraparte_i <> ‘particulares’ e carteira_contabilistica <> 'ativos nao correntes detidos para venda' • Exposures to natural persons: tipo_conta='A' e instrumento_financeiro='credito concedido e outros ativos financeiros' e contraparte = ‘particulares’ e contraparte_i = ‘particulares’ e carteira_contabilistica <> 'ativos nao correntes detidos para venda' • Off-balance sheet exposures: tipo_conta='EA' • Derivatives: instrumento_financeiro='derivados’ e tipo_conta in ('A', 'P') • Debt securities: tipo_conta='A' e instrumento_financeiro='instrumentos de divida' • Equity: tipo_conta='A' e instrumento_financeiro='instrumentos de capital' e carteira_contabilistica <> 'ativos nao correntes detidos para venda' Nota: Após a definição inicial com Pedro Mendes e Contabilidade, no processo de validações foi identificado que teriam de ser aplicados mais filtros do que os previstos inicialmente (email Francisco de Mesquita Gouveia 15/01/2025 19:06). Os filtros apresentados acima já refletem essas alterações

Sheet LEGAL PERSONS DATA SETS
A1: SRB DATA SET FOR EXPOSURES TO LEGAL PERSONS The AnaCredit database provides very detailed and individual information concerning exposures to legal persons. The SRB Valuation Data Set complements the AnaCredit database and provides data fields on segments, which allows mapping individual exposures with prudential reporting segments (FINREP and COREP), and credit risk data parameters aimed at supporting valuers. The SRB Valuation Data Set also provides data fields on risk parameters provided by banks’ internal risk models, which valuers are able to rely on in order to perform valuations on an aggregated basis, where necessary. Serão produzidos cinco ficheiros de report referentes a Legal Persons: ‣ SRB Instruments Data Set for exposures to legal persons (LEGALP_INSTRUMENTS); ‣ SRB Counterparties Data Set for exposures to legal persons (LEGALP_COUNTERPARTIES); ‣ SRB Protection received Data Set for exposures to legal persons (LEGALP_PROTECTIONS); ‣ SRB Instrument/Counterparty mapping Data Set for exposures to legal persons (LEGALP_INSTRUMENT_COUNTERPARTY); ‣ SRB Instrument/Protection mapping Data Set for exposures to legal persons (LEGALP_INSTRUMENT_PROTECTION);
A2: SRB DATA SET FOR EXPOSURES TO LEGAL PERSONS A base de dados AnaCredit disponibiliza informação muito detalhada e individualizada sobre exposições a pessoas coletivas. O dataset de avaliação do SRB complementa a base de dados AnaCredit e fornece campos de dados por segmentos, o que permite mapear exposições individuais com segmentos de reporte prudencial (FINREP e COREP) e parâmetros de dados de risco de crédito destinados a apoiar os avaliadores. O dataset de avaliação do CUR também fornece campos de dados sobre parâmetros de risco fornecidos pelos modelos de risco internos dos bancos, nos quais os avaliadores podem confiar para realizar avaliações numa base agregada, sempre que necessário. Serão produzidos três ficheiros de report referentes a Legal Persons: ‣ SRB Instruments Data Set for exposures to legal persons (VDS_OUT_LEGALP_INSTRUMENTS); ‣ SRB Counterparties Data Set for exposures to legal persons (VDS_OUT_LEGALP_COUNTERPARTIES); ‣ SRB Protection received Data Set for exposures to legal persons (VDS_OUT_LEGALP_PROTECTIONS).

Sheet LEGALP_INSTRUMENTS
A1: Instruções SRB | H1: Mapeamento efetuado pela Corporação e respetiva Descrição Loan Tape (LT) | L1: Análise IT | T1: Implementação Deloitte (OLD)
A2: ID | B2: Categoria | C2: Coluna | D2: Tipo de dados | E2: Descrição | F2: Descrição - Português | H2: Mapeamentos Corporação (LT) | I2: Descrição (LT) | J2: Additional Guidance (LT) | L2: Novo campo na tabela LT002? | M2: Nome do campo no ficheiro | N2: Mapeamento LT / Comentários IT | O2: Estado especificação | P2: Estado desenvolvimento | Q2: Data da última alteração do Estado desenvolvimento | R2: Tipo de Tarefa para a estimativa | T2: Fontes de Informação | U2: Filtros | V2: Campo | W2: Regras de Preenchimento | X2: Agrupações | Z2: Comentários reuniões
A3: V_1 | B3: Identification information | C3: Instrument Identifier | D3: Alphanumeric | E3: An identifier applied to uniquely identify each instrument. Each instrument must have one instrument identifier | F3: Um identificador aplicado para identificar exclusivamente cada instrumento. Cada instrumento deve ter um identificador de instrumento. | H3: INSTRUMENT-INSTRMNT_ID | I3: Instrument ID | J3: An identifier applied by the reporting agent to uniquely identify each instrument under a single contract. Each instrument must have one instrument identifier. This value will not change over time and cannot be used as the instrument identifier for any other instrument under the same contract. Supervised Insitutions are asked to furnish the INSTRMNT_ID with the exact same value as it is reported to AnaCredit (or any similar central credit register). If this is not available, the value shall be reported as it is internally used. If an instrument is not reported to AnaCredit but requested for the purposes of the on-site inspection please provide the bank-internally used value. | L3: NÃO | M3: instrument_id | N3: LT002_INSTRUMENT.INSTRMNT_ID | O3: Concluído | P3: ='PDS - Desenvolvimento'!$K$3 -> Concluído | Q3: 45608 | R3: Concluído | T3: cd_alm.al029_cnt_core_m | U3: ‣ ref_date = data do report | V3: cempresa | W3: ‣ Concatenação dos campos mencionados anteriormente: cempresa + cbalcao + cnumecta + zdeposit | Z3: Após reunião com LCM foi indicado que este campo deveria ser na mesma o cempresa … zeposit mas da tabela fr001/fr004 em vez da al029 isto porque tendo que conciliar com o finrep, faz sentido que tenha a mesma granularidade
V4: cbalcao
V5: cnumecta
V6: zdeposit
A7: V_2 | B7: Identification information | C7: Counterparty Identifier | D7: Alphanumeric | E7: Identifier applied to uniquely identify each counterparty. | F7: Identificador aplicado para identificar exclusivamente cada contraparte | H7: Not applicable: To be reported as "N/A". This information will be availabe in "01_04_leg_instr_count" table | I7: - | J7: - | L7: SIM | M7: counterparty_id | N7: Mapeamento LT: Not Applicable: Reportar 'N/A' Comentários IT: Este campo constará no ficheiro "01_04_leg_instr_count" | O7: Concluído | P7: ='PDS - Desenvolvimento'!$K$77 -> Concluído | Q7: 45608 | R7: Alterações ao Motor LT - Novos Campos: Definição Fechada / Dados existem no Datalake | T7: cd_alm.al029_cnt_core_m | U7: ‣ ref_date = data do report | V7: zcliente | W7: ‣ Direto | Z7: Se se alterar o universo trazer o zcliente respetivo
A8: V_3 | B8: Exposure class | C8: CRR Exposure class | D8: String | E8: The exposures classes for the calculation of risk-weighted assets (RWAs) for credit risks are as follows (not applicable when exposures are classified in the CRR trading book as defined in Article 4(1)(86) of Regulation (EU) No 575/2013): Where a bank uses the standardised approach: ‣ Central governments or central banks (SCENGOV) ‣ Regional governments or local authorities (SREGGOV) ‣ Public sector entities (SPUBSEC) ‣ Multilateral development banks (SDEVBAN) ‣ International organisation (SINTORG) ‣ Institutions (SINSTIT) ‣ Corporates (SCORPOR) ‣ Retail (SRETAIL) ‣ Secured by mortgages and immovable property (SSECMOR) ‣ Defaulted (SDEFAUL) ‣ High risk (SHIGHRI) ‣ Covered bonds (SCOVBON) ‣ Items representing securitisation positions ‣ Institutions and corporates with a short term credit assessment (SSHOTER) ‣ Collective investment undertakings (SCOLINV) ‣ Equity (SEQUITY) ‣ Other (SOTHERI) Where a bank uses the IRB approach: ‣ Central governments and central banks (ICENGOV) ‣ Institutions (IINSTIT) ‣ Corporates (ICORPOR) ‣ Retail (IRETAIL) ‣ Equity (IEQUITY) ‣ Items representing securitisation positions ‣ Other non-credit-obligation assets (IOTHERC) | F8: As classes de posições em risco para o cálculo dos ativos ponderados pelo risco (RWA) para riscos de crédito são as seguintes (não aplicável quando as posições em risco são classificadas na carteira de negociação do CRR, conforme definido no artigo 4(1)(86), do Regulamento (UE) No 575 /2013). Informação deriva de uma lista baseada na classificação da facilidade utilizando a classe de risco, conforme descrito no artigo 112 do Regulamento (UE) No 575/2013 para bancos que utilizam a abordagem padrão) e no artigo 147 do Regulamento (UE) No 575/2013 (para bancos que utilizam abordagem baseada em classificações internas (IRB)) Quando um banco utiliza a abordagem padrão: ‣ Central governments or central banks (SCENGOV) ‣ Regional governments or local authorities (SREGGOV) ‣ Public sector entities (SPUBSEC) ‣ Multilateral development banks (SDEVBAN) ‣ International organisation (SINTORG) ‣ Institutions (SINSTIT) ‣ Corporates (SCORPOR) ‣ Retail (SRETAIL) ‣ Secured by mortgages and immovable property (SSECMOR) ‣ Defaulted (SDEFAUL) ‣ High risk (SHIGHRI) ‣ Covered bonds (SCOVBON) ‣ Items representing securitisation positions ‣ Institutions and corporates with a short term credit assessment (SSHOTER) ‣ Collective investment undertakings (SCOLINV) ‣ Equity (SEQUITY) ‣ Other (SOTHERI) Quando um banco utiliza a abordagem IRB: ‣ Central governments and central banks (ICENGOV) ‣ Institutions (IINSTIT) ‣ Corporates (ICORPOR) ‣ Retail (IRETAIL) ‣ Equity (IEQUITY) ‣ Items representing securitisation positions ‣ Other non-credit-obligation assets (IOTHERC) | H8: - | I8: - | J8: - | L8: SIM | M8: crr_exposure_class | N8: Mapeamento LT: ‣ Utilizar o campo "segmento_corep_final" da tabela ct013_rwa_princ; Nota: Os códigos "segmento_corep_final" seguem sempre a mesma estrutura, começam com um caracter que identifica se é IRB (I_...) ou Standard (S_...) e de seguida um numérico (ex. I_3.1, I_5.1, S_1.0). ‣ Para o mesmo contrato este campo pode retornar vários códigos "segmento_corep_final" distintos, de seguida estão os passos que permitem resolver esta ambiguidade: 1. Deve seguir a lógica do campo RWA_MTHD, de momento a lógica é, se existir IRB e Standard então trazer informação relativa a IRB; 2. Se mesmo aplicando o passo 1 ainda existirem vários códigos "segmento_corep_final" distintos (vários códigos IRB ou vários códigos Standard) então: recuperar o código "segmento_corep_final" com o menor numérico associado. Exemplo: O contrato A tem associados os seguintes códigos "segmento_corep_final" distintos: I_3.1, I_5.1, S_1.0: 1. Remover o Standard: I_3.1, I_5.1; 2. Ficar com o menor numérico: I_3.1. ‣ Necessário criar nova parametrização na tabela lt831_param_conceitos, podendo a mesma ser consultada neste documento na sheet 'LT831' filtrando por tabela_conceito = 'LT002_INSTRUMENT' e campo_conceito = 'CRR_EXPOSURE_CLASS' ‣ Reportar ‘N/A’ se campo flag_cons_cap=0 da tabela cd_captools.ct013_rwa_princ Comentários IT: '‣ Proposta: Consumir o campo "segmento_corep_final" da tabela ct013_rwa_princ, tendo em atenção que se tem de manter a lógica aplicada no campo LT "RWA_MTHD" (se for IRB ou Standard), para resolver os casos em que para o mesmo contrato temos mais do que segmento corep (IRB e Standard). Nota existem contratos que têm mais do que um segmento corep IRB ou Standard ou seja tem de haver uma lógica de selecionar o mais significativo pois só podemos reportar um valor neste campo). ‣ No Loan Tape para cálculo do LGD que vem da ct013_rwa_princ, quando existe IRB e STD, escolhe-se IRB. ‣ Segundo Email de Pedro Mendes com a resposta da Corporação (26/03/2024 17:28), no caso de existir mais do que 1 CRR Exposure class para o mesmo contrato, é permitido reportar o mais significativo dos dois por valor ou os dois separados por “,” colocando o mais significativo primeiro. ‣ Analisar documento 'BS_Tabelas_Temporárias_Loan_Tape.xlsx' para consultar as regras de seleção aplicadas no campo RWA_MTHD. ‣ Reunião Pedro Mendes, Luís Capitão-Mor 05-11-2024: Foi definida a regra para este campo, como dito anteriormente: - Deve seguir a lógica do campo RWA_MTHD, de momento a lógica é, se existir IRB e Standard então trazer informação relativa a IRB; - Para os casos em que temos mais do que um "segmento_corep_final" IRB ou Standard, foram propostas duas soluções, uma seria utilizar o campo "EAD_FINAL_BRUTA" também da tabela ct013_rwa_pric como fator de peso, recuperando o "segmento_corep_final" associado ao maior "EAD_FINAL_BRUTA" (mais significativo). A segunda solução, mais simples, seria simplesmente recuperar o código "segmento_corep_final" com a numeração mais baixa, por exemplo se um contrato tiver os códigos "segmento_corep_final" I_3.1, I_5.1 ficamos apenas com o I_3.1. Optou-se pela segunda solução. ‣ Query que demonstra que para um contrato FINREP pode haver mais do que um 'segmento_corep_final' tanto para a approach 'IRB' como para a 'Standard': SELECT contract_id_fr, --ct013.s1emp,ct013.contra1, GROUP_CONCAT(DISTINCT ct013.segmento_corep_final) as segmento_corep_final_conc, --GROUP_CONCAT(ct013.segmento_corep_final) as segmento_corep_final_conc, --GROUP_CONCAT(CAST(ct013.ead_final_bruta AS STRING)) as ead_final_bruta_conc, COUNT(*) as cnt, COUNT(DISTINCT ct013.segmento_corep_final) as cnt_dist FROM ( SELECT fr004.contract_id_fr, s1emp, contra1 FROM ( SELECT DISTINCT CONCAT(cempresa,cbalcao,cnumecta,zdeposit) as contract_id_fr FROM cd_captools.fr004_cto WHERE ref_date = '2024-08-31' ) as fr004 --6211142 LEFT JOIN ( SELECT CONCAT(cempresa_fr,cbalcao_fr,cnumecta_fr,zdeposit_fr) as contract_id_fr, CONCAT(cempresa,cbalcao,cnumecta,zdeposit) as contract_id_ct FROM cd_captools.kt_chaves_finrep WHERE ref_date = '2024-08-31' ) as chaves_finrep ON chaves_finrep.contract_id_fr = fr004.contract_id_fr --6211142 LEFT JOIN ( SELECT s1emp, contra1, CONCAT(cempresa,cbalcao,cnumecta,zdeposit) as contract_id_ct FROM cd_captools.kt_chaves_bdr WHERE ref_date = '2024-08-31' ) as chaves_bdr ON chaves_bdr.contract_id_ct = chaves_finrep.contract_id_ct --2046835 WHERE chaves_bdr.contract_id_ct IS NOT NULL GROUP BY contract_id_fr, s1emp, contra1 ) as core --2046835 DIST fr --2047298 nº total LEFT JOIN ( SELECT s1emp, contra1, segmento_corep_final, ead_final_bruta FROM cd_captools.ct013_rwa_princ WHERE ref_date = '2024-08-31' ) as ct013 ON core.s1emp = ct013.s1emp AND core.contra1 = ct013.contra1 WHERE ct013.s1emp IS NOT NULL GROUP BY contract_id_fr --GROUP BY ct013.s1emp, ct013.contra1 ORDER BY cnt_dist DESC | O8: Concluído | P8: ='PDS - Desenvolvimento'!$K$81 -> Concluído | Q8: 45674 | R8: Alterações ao Motor LT - Novos Campos: Definição Incompleta / Dados existem no Datalake | T8: Tabela de parametrização: codemapping | U8: ‣ dd_field_id = "3" | V8: dd_code | W8: ‣ Tradução do campo "segmento_corep_final" através de uma ligação com o campo "dd_code" para obter o campo: dd_value
V9: dd_value
T10: cd_captools.ct013_rwa_princ | U10: ‣ ref_date = data do report ‣ flag_cons_cap = 1 ‣ exercicio = 'REAL' | V10: segmento_corep_final
A11: V_4 | B11: Exposure class | C11: FINREP Exposure class | D11: String | E11: Classification of the facility (exposure class) as defined in ITS 680/2014 Annex V Instructions FINREP (Counterparty breakdown). Options: ‣ Central banks ‣ Central governments ‣ Credit institutions ‣ Other financial corporations ‣ Non-financial corporations ‣ Households | F11: Classificação da instalação (exposure class) conforme definido na ITS 680/2014 Anexo V Instruções FINREP (Counterparty breakdown). Opções: ‣ Central banks ‣ Central governments ‣ Credit institutions ‣ Other financial corporations ‣ Non-financial corporations ‣ Households | H11: - | I11: - | J11: - | L11: NÃO | M11: finrep_exposure_class | N11: LT002_INSTRUMENT.INTRNL_SGMNT ‣ Necessário criar novas parametrizaçôes nas tabelas lt829_regras_conversao e lt830_conversoes, podendo as mesmas ser consultadas neste documento nas sheets: ‣ LT829 - filtrando por campo_conceito = 'INTRNL_SGMNT' e regra_conversao = '1'; ‣ LT830 - filtrando por segmento = 'Exposures to legal persons' e campo_conceito = 'INTRNL_SGMNT'. | O11: Concluído | P11: ='PDS - Desenvolvimento'!$K$19 -> Concluído | Q11: 45665 | R11: Concluído | T11: Tabela de parametrização: codemapping | U11: ‣ dd_field_id = "4" | V11: dd_code | W11: ‣ Inicialmente para cada combinação dos campos "cempresa", "cbalcao", "cnumecta", "zdeposit" iremos recuperar o MAX(contraparte_i): ‣ Este campo MAX(contraparte_i) será traduzido através de uma ligação com o campo "dd_code" para obter o campo: dd_value | Z11: Pragosa diz que o LCM já indicou reapontar a ct081_finrep para a fr004
V12: dd_value
T13: cd_captools.ct081_finrep | U13: ‣ ref_date = data do report | V13: cempresa
V14: cbalcao
V15: cnumecta
V16: zdeposit
V17: contraparte_i
A18: V_5 | B18: Risk parameters | C18: Total Risk Exposure Amount | D18: Numeric (euro) | E18: The total risk exposure amount of the instrument, calculated according to Articles 92(3) and 92(4) of Regulation (EU) No 575/2013 (CRR), where applicable. | F18: O montante total das posições em risco do instrumento, calculado de acordo com o artigo 92(3) e 92(4) do Regulamento (UE) No 575/2013 (CRR), quando aplicável. | H18: INSTRUMENT-RWA | I18: RWA | J18: RWA according to Regulation (EU) No 575/2013. | L18: NÃO | M18: total_risk_exposure_amount | N18: LT002_INSTRUMENT.RWA | O18: Concluído | P18: ='PDS - Desenvolvimento'!$K$36 -> Concluído | Q18: 45608 | R18: Concluído | T18: cd_captools.ct013_rwa_princ | U18: ‣ ref_date = data do report ‣ flag_cons_cap = 1 ‣ exercicio = 'REAL' | V18: s1emp | W18: ‣ Para cada Instrument Identifier é somada a: ‣ Média do campo "rwa_final" para cada par de campos "s1emp", "contra1" | X18: A agrupação é feita segundo o campo "Instrument Identifier" deste mesmo documento | Z18: Dependendo do instrument id indicado, este campo deverá ser a soma do rwa_final
V19: contra1
V20: rwa_final
A21: V_6 | B21: Risk parameters | C21: CRR Loss given default | D21: Numeric. Basis points | E21: Current level of the ‘Loss given default’ of the loan, determined in accordance with Articles 161, 164, 179 and 181 of Regulation (EU) No 575/2013. | F21: Nível atual da "Loss given default" do empréstimo, determinado em conformidade com os artigos 161, 164, 179 e 181 do Regulamento (UE) No 575/2013. | H21: INSTRUMENT-LGD | I21: Regulatory LGD | J21: If differences between regulatory and internal LGD exist, use regulatory LGD (according to Regulation (EU) No 575/2013). In particular, in IRB-F use regulatory LGD values. | L21: NÃO | M21: crr_loss_given_default | N21: LT002_INSTRUMENT.LGD | O21: Concluído | P21: ='PDS - Desenvolvimento'!$K$44 -> Concluído | Q21: 45608 | R21: Concluído | T21: cd_captools.ct013_rwa_princ | U21: ‣ ref_date = data do report ‣ flag_cons_cap = 1 ‣ exercicio = 'REAL' | V21: s1emp | W21: ‣ Para cada Instrument Identifier é calculada a: ‣ Média ponderada do campo "lgdfinal" em relação à: ‣ Média do campo "ead_final_bruta" para cada par dos campos "s1emp", "contra1" | X21: A agrupação é feita segundo o campo "Instrument Identifier" deste mesmo documento | Z21: Dependendo do instrument id indicado, este campo deverá ser a média ponderada de lgd_final por ead_final_bruta
V22: contra1
V23: ead_final_bruta
T24: cd_captools.ct014_rwa_irb | U24: ‣ ref_date = data do report | V24: lgdfinal
A25: V_7 | B25: Risk parameters | C25: IFRS 9 Loss given default | D25: Numeric. Basis points | E25: Current level of the ‘Loss given default’ of the loan determined for accounting purposes. | F25: Nível atual da "Loss given default" do empréstimo determinado para efeitos contabilísticos. | H25: INSTRUMENT-IFRS9_LGD | I25: IFRS 9 accounting LGD | J25: IFRS 9 accounting Loss Given Default as at reference date for defaulted and non-defaulted exposures. In case the bank models time-depended LGD variable for non-defaulted exposures then 12-month LGD as at reference date regardless the classification as Stage 1 or 2 | L25: NÃO | M25: ifrs9_loss_given_default | N25: LT002_INSTRUMENT.IFRS9_LGD | O25: Concluído | P25: ='PDS - Desenvolvimento'!$K$43 -> Concluído | Q25: 45608 | R25: Concluído | T25: cd_captools.ifrs9_out_expected_loss_8_7 | U25: ‣ Apenas são trazidos os "contract_id"s que têm "exec_id_part" correspondente na tabela cd_captools.imcatf046_flag_fecho à data ("cmes") do report | V25: contract_id | W25: ‣ Para cada Instrument Identifier é calculada a: ‣ Média ponderada do campo "lgd_ifrs9" em relação à: ‣ Média do campo "ead" para cada "contract_id" | X25: A agrupação é feita segundo o campo "Instrument Identifier" deste mesmo documento | Z25: Tal como nos anteriores explorar porque é feita a média do ead
V26: lgd_ifrs9
V27: ead

Sheet LEGALP_COUNTERPARTIES
A1: Instruções SRB | H1: Mapeamento efetuado pela Corporação e respetiva Descrição Loan Tape (LT) | L1: Análise IT | T1: Implementação Deloitte (OLD)
A2: ID | B2: Categoria | C2: Coluna | D2: Tipo de dados | E2: Descrição | F2: Descrição - Português | H2: Mapeamentos Corporação (LT) | I2: Descrição (LT) | J2: Additional Guidance (LT) | L2: Novo campo na tabela LT003? | M2: Nome do campo no ficheiro | N2: Mapeamento LT / Comentários IT | O2: Estado especificação | P2: Estado desenvolvimento | Q2: Data da última alteração do Estado desenvolvimento | R2: Tipo de Tarefa para a estimativa | T2: Fontes de Informação | U2: Filtros | V2: Campo | W2: Regras de Preenchimento | X2: Agrupações | Y2: Comentários reuniões
A3: V_2 | B3: Identification information | C3: Counterparty Identifier | D3: Alphanumeric | E3: Identifier applied to uniquely identify each counterparty. | F3: Identificador aplicado para identificar exclusivamente cada contraparte. | H3: ENTITY-ENTTY_ID | I3: Entity ID | J3: An identifier applied by the reporting agent to uniquely identify each counterparty. Each counterparty has a unique and exclusive counterparty identifier. This means that this value will not change over time and can never be used as the counterparty identifier for any other counterparty. | L3: NÃO | M3: counterparty_id | N3: LT003_ENTITY.ENTTY_ID | O3: Concluído | P3: ='PDS - Desenvolvimento'!$K$113 -> Concluído | Q3: 45608 | R3: Concluído | T3: cd_alm.al029_cnt_core_m | U3: ‣ ref_date = data do report | V3: zcliente | W3: ‣ Direto | Y3: Se se alterar o universo trazer o zcliente respetivo
A4: V_8 | B4: Risk parameters | C4: Current Internal Credit Rating/Scoring | D4: Numeric / alphanumeric | E4: Internal credit rating/scoring issued to the counterparty. | F4: Classificação/pontuação de crédito interna emitida para a contraparte. | H4: ENTITY-INTRNL_RTNG | I4: Internal rating at reference date | J4: Internal rating at the reference date according to Regulation (EU) No 575/2013. Please also add in sheet "Code List" the list of values used, i.e. bank-internal masterscale. | L4: NÃO | M4: internal_credit_rating | N4: LT003_ENTITY.INTRNL_RTNG ‣ Luís Capitão-Mor solicitou que se confirme que este campo no Loan Tape tem origem no input de Capital. Segundo o documento "Especificação - BCE Loan Tape - Internal Ratings_v1.4", é referido: "Nível do cliente: deverá ser consultada a tabela CD_CAPTOOLS.JM_CAL_IN_CL;" ou seja, confirma-se que tem origem no input de Capital. | O4: Concluído | P4: ='PDS - Desenvolvimento'!$K$124 -> Concluído | Q4: 45608 | R4: Concluído | T4: cd_loan_tapes_bce.lt003_entity | U4: ‣ ref_date = data do report | V4: intrnl_rtng | W4: ‣ Para cada Counterparty Identifier é obtido o: MAX(intrnl_rtng) | X4: A agrupação é feita segundo o campo "Counterparty Identifier" deste mesmo documento | Y4: Explorar alternativas para ir buscar este campo
A5: V_9 | B5: Risk parameters | C5: External Credit rating | D5: Alphanumeric | E5: External credit rating issued to the counterparty at cut-off date. In case several ratings are assigned, the approach described in Art. 138 of the CRR applies. | F5: Rating de crédito externo emitido para a contraparte na data de corte. Caso sejam atribuídas diversas classificações, aplica-se a abordagem descrita no Art. 138 do CRR. | H5: ENTITY-EXTRNL_RTNG | I5: External rating | J5: External rating at the reference date. | L5: NÃO | M5: external_credit_rating | N5: LT003_ENTITY.EXTRNL_RTNG | O5: Concluído | P5: ='PDS - Desenvolvimento'!$K$123 -> Concluído | Q5: 45608 | R5: Concluído | T5: cd_loan_tapes_bce.lt003_entity | U5: ‣ ref_date = data do report | V5: extrnl_rtng | W5: ‣ Para cada Counterparty Identifier é obtido o: MAX(extrnl_rtng) | X5: A agrupação é feita segundo o campo "Counterparty Identifier" deste mesmo documento | Y5: Explorar alternativas para ir buscar este campo
A6: V_10 | B6: Risk parameters | C6: IFRS 9 Probability of default/impairment | D6: Numeric. Basis points | E6: The probability of default/impairment is calculated in accordance with the requirements specific to probability of default (PD) estimation as laid down in the accounting framework. If PDs are produced at the instrument level only, the counterparty’s PD is to be reported as the exposure-weighted average PD across the PDs of all instruments of the counterparty. If, for a given counterparty, PDs are estimated for both the counterparty and (some of) the products of the counterparty, it is the counterparty’s PD which is to be reported. No documento "Feedback Statement in response to the consultation on the SRB valuation data set" é referida a seguinte nota sobre este campo: "‘Data Point V_10’, entitled ‘IFRS 9 Probability of default’, refers to PDs used for accounting purposes, being a 12-month PD for stage 1 exposures and a lifetime PD for stage 2 and 3 exposures as per the accounting framework." | F6: A probabilidade de incumprimento/imparidade é calculada de acordo com os requisitos específicos para a estimativa da probabilidade de incumprimento (PD) definidos no quadro contabilístico. Se as PDs forem produzidas apenas ao nível do instrumento, a PD da contraparte deve ser reportada como a PD média ponderada pela exposição entre as PD de todos os instrumentos da contraparte. Se, para uma determinada contraparte, forem estimadas PDs tanto para a contraparte como para (alguns dos) produtos da contraparte, é a PD da contraparte que deve ser reportada. | H6: Definição apresentada pela Corporação no documento "VDS_CommonConsiderations_v2.5.xlsx": INSTRUMENT-PD_IFRS9_12M_RD and INSTRUMENT-PD_IFRS9_RMNNG_LFTM_RD Exposure-weighted average PD by counterparty taking PD as: -Stage 1: INSTRUMENT-PD_IFRS9_12M_RD -Stage 2: INSTRUMENT-PD_IFRS9_RMNNG_LFTM_RD -Stage 3: INSTRUMENT-PD_IFRS9_RMNNG_LFTM_RD Example in Tab V_10 | L6: SIM pd_ifrs9_12m_lftm_rd | M6: ifrs9_prob_default_impairment | N6: Mapeamento LT: ‣ Necessário criar um novo campo Probability of Default "Mista" (PD_IFRS9_12M_LFTM_RD) na tabela de Clientes do Loan Tape (LT003_ENTITY). ‣ Regra de construção definida no email enviado por Luís Pragosa a David Texugo/Alexandre Gonçalves 20/03/2025 14:04. ‣ Metodologia de cruzamento: 1) Cruzar LT003_ENTITY com LT005_INSTR_ENT: LT003_ENTITY LEFT JOIN (SELECT * FROM LT005_INSTR_ENT) ON ENTTY_ID = ENTTY_ID 2) Cruzar contratos obtidos no passo anterior com a tabela LT002_INSTRUMENT para obter os campos EAD, PD_IFRS9_12M_RD, PD_IFRS9_RMNNG_LFTM_RD e IMPRMNT_STTS: LEFT JOIN (SELECT * FROM LT002_INSTRUMENT) ON INSTRMNT_ID = INSTRMNT_ID ‣ Metodologia de Cálculo (NOT APPLICABLE) - Definida à semelhança do campo PD_IFRS9_12M_RD existente na LT003_ENTITY: - Se o campo IFRS9_EAD da Instrument (LT002_INSTRUMENT) asumir valor da coluna Not Applicable para todos os contratos do cliente. - Se a entidade não for 1º titular (csequencia_rel <> '00001') ‣ Metodologia de Cálculo: 1) Identificar os Contratos onde o Cliente é o 1º Titular: LT005_INSTR_ENT WHERE CRELACAO_CL_CNT = '1' AND CSEQUENCIA_REL = '00001' 2) Para cada par Contrato/Cliente obtido no passo anterior, determinar a PD relevante da tabela LT002_INSTRUMENT (PD_IFRS9_12M_RD ou PD_IFRS9_RMNNG_LFTM_RD) consoante o Stage (IMPRMNT_STTS -> '23' - Stage 1; '24' - Stage 2; '25' - Stage 3): CASE WHEN IMPRMNT_STTS = ‘23’ THEN PD_IFRS9_12M_RD ELSE PD_IFRS9_RMNNG_LFTM_RD END as PD_AUX 3) Aplicar o seguinte cálculo por Cliente: CASE WHEN SUM(IFRS9_EAD)<> 0 THEN SUM(PD_AUX * IFRS9_EAD) / SUM(IFRS9_EAD) ELSE AVG(PD_AUX) END as PD_IFRS9_SRB Comentários IT: Email David Texugo (01/04/2024 17:23) "Para algumas das operações em Stage 1 deve-se considerar PD lifetime também. Para operações em Stage 1 para as quais não é possível avaliar o SICR via variação de PD/Rating por PD/Rating origem inválido, o cálculo de provisões é lifetime, conforme pode ser verificado no campo loss_type. Com a exceção destas casuísticas, deve-se seguir a lógica que indicas. Adicionalmente Stage 3 deveria ter sempre PD 100%." Aparentemente faz sentido criar um novo campo ("PD misto" ) na LT002_INSTRUMENT dado que se solicita um "misto" entre a PD 12m e a PD lifetime. Como tal, deverá confirmar-se com Luís Capitão-Mor a lógica de preenchimento deste novo campo: -Se stage 1: Se loss_type LIKE 'Lifetime expected credit losses%' selecionar PD_LT_IFRS9 da tabela BU_IFRS9.IFRS9_OUT_EXPECTED_LOSS_REPORTING, caso contrário selecionar PD12M_IFRS9 da tabela BU_IFRS9.IFRS9_OUT_EXPECTED_LOSS_REPORTING -Se stage 2: selecionar PD_LT_IFRS9 da tabela BU_IFRS9.IFRS9_OUT_EXPECTED_LOSS_REPORTING -Se stage 3: forçar 1 Sugere-se criar o campo na LT002_INSTRUMENT e não na LT003_ENTITY porque após consultar a a LT003_ENTITY verificou-se que existia o campo PD_IFRS9_12M_RD para o qual é usada a LT005_INSTR_ENT para identificar todos os contratos onde o cliente é o 1º Titular, de seguida para cada cliente aplica-se uma média ponderada da PD em relação ao EAD (porque cada cliente pode ter vários contratos). Assim sugere-se replicar esta lógica para o novo campo "PD misto" adicionado na LT002_INSTRUMENT de forma a poder ser criado também um novo campo "PD misto" na LT003_ENTITY. Nota: Atenção que o campo PD_IFRS9_12M_RD apenas está a ser calculado para os Primeiros Titulares (provavelmente porque em IFRS9 também só calculam para os Primeiros Titulares?) Reunião com Luís Capitão-Mor 8 /11/2024 14:30: Foi pedido que fosse marcada uma reunião com David Texugo e Alexandre Gonçalves para revisitar os conceitos de PD pedidos pelo BCE e comparar com o pedido no report Valuation, o objetivo será perceber se é necessário criar um campo novo no Loan Tapes ou se é necessário alterar a lógica de algum dos campos PD do Loan Tapes para refletir a lógica pedida pelo SRB. Foi também comentado que houve uma OSI em Maio/Junho e que se deveria questionar a David Texugo e Alexandre Gonçalves se esta informação de PDs foi pedida e se houve alterações nos conceitos pedidos. Lógica proposta para a criação do novo campo na LT002: CASE WHEN IMPRMNT_STTS_INSTRMNT = '23' --(Stage 1) THEN IF( loss_type LIKE 'Lifetime expected credit losses%', PD_LT_IFRS9, PD12M_IFRS9) WHEN IMPRMNT_STTS_INSTRMNT = '24' --(Stage 2) THEN PD_LT_IFRS9 WHEN IMPRMNT_STTS_INSTRMNT = '25' --(Stage 3) THEN 1 ELSE ??????N/A or MISS????? --(O que fazer nos casos em que o stage 'IMPRMNT_STTS_INSTRMNT ' não está preenchido?) END as PD_IFRS9_12M_LFTM_RD --(Confirmar o nome que este novo campo deve tomar) WHERE IMCATF046_FLAG_FECHO.CMES = REF_DATE Lógica proposta para a criação do novo campo na LT003: 1) Identificar contratos onde o cliente é o 1º Titular: LT005_INSTR_ENT WHERE CRELACAO_CL_CNT = '1' AND CSEQUENCIA_REL = '00001' 2) Aplicar o seguinte cáclulo por entidade: CASE WHEN SUM(IFRS9_EAD)<> 0 THEN SUM(PD_IFRS9_12M_LFTM_RD * IFRS9_EAD) / SUM(IFRS9_EAD) ELSE AVG(PD_IFRS9_12M_LFTM_RD) END as ifrs9_prob_default_impairment Análise: QUERY que permite perceber a realção entre o stage e o loss_type: SELECT --core.contract_id_fr, core.stage_atual, ifrs9_os_8_7.loss_type, IF(tradutor.contract_id_fr IS NOT NULL, '1', '0') as flag, COUNT(*) --SELECT COUNT(DISTINCT ifrs9_oel_8_7.contract_id_ifrs9) --SELECT COUNT(DISTINCT core.contract_id_fr) --SELECT COUNT(*) FROM ( SELECT fr004.contract_id as contract_id_fr, stage_atual FROM ( SELECT CONCAT(cempresa, cbalcao, cnumecta, zdeposit) as contract_id, stage_atual FROM cd_captools.fr004_cto WHERE ref_date = '2024-09-30' --AND contraparte <> 'particulares' ) as fr004 LEFT JOIN ( SELECT CONCAT(cempresa, cbalcao, cnumecta, zdeposit) as contract_id, ccontab_final_ifrs FROM cd_captools.fr001_univ_saldo WHERE ref_date = '2024-09-30' ) as fr001 ON fr001.contract_id = fr004.contract_id INNER JOIN ( SELECT conta, tipo_conta FROM cd_captools.fr802_pl_contas WHERE ref_date = '2024-09-30' AND cod_plano = 'BST_IND' AND ((TRIM(tipo_conta) ='A' AND instrumento_financeiro='credito concedido e outros ativos financeiros') OR TRIM(tipo_conta) = 'EA') --AND NVL(contraparte_i, '') <> 'particulares' ) as fr802 ON fr802.conta = fr001.ccontab_final_ifrs ) as core LEFT JOIN ( SELECT trad_fr.contract_id_fr, trad_ifrs9.contract_id_ifrs9 FROM ( SELECT CONCAT(cempresa_fr, cbalcao_fr, cnumecta_fr, zdeposit_fr) as contract_id_fr, CONCAT(cempresa, cbalcao, cnumecta, zdeposit) as contract_id_ct FROM cd_captools.kt_chaves_finrep WHERE ref_date = '2024-09-30' ) as trad_fr INNER JOIN ( SELECT contract_id as contract_id_ifrs9, CONCAT(cempresa, cbalcao, cnumecta, zdeposit) as contract_id_ct FROM cd_captools.kt_chaves_ifrs9 WHERE ref_date = '2024-09-30' ) as trad_ifrs9 ON trad_ifrs9.contract_id_ct = trad_fr.contract_id_ct ) as tradutor ON tradutor.contract_id_fr = core.contract_id_fr --WHERE tradutor.contract_id_fr IS NULL -- Temos 1447 contratos LEGALP, NATP e OFFBAL de um total de 2054616 contratos que existem no universo FINREP mas não estão no universo IFRS9 LEFT JOIN ( SELECT contract_id as contract_id_ifrs9, loss_type FROM cd_captools.ifrs9_out_staging_8_7 WHERE data_date_part = (SELECT MIN(data_date_part) FROM cd_captools.ifrs9_out_staging_8_7 WHERE data_date_part >= '2024-09-30') GROUP BY contract_id_ifrs9, loss_type ) as ifrs9_os_8_7 ON ifrs9_os_8_7.contract_id_ifrs9 = tradutor.contract_id_ifrs9 GROUP BY core.stage_atual, ifrs9_os_8_7.loss_type, flag | O6: Concluído | P6: ='PDS - Desenvolvimento'!$K$130 -> Concluído | R6: Alterações ao Motor LT - Novos Campos: Definição por Iniciar | T6: cd_captools.ct013_rwa_princ | U6: ‣ ref_date = data do report ‣ flag_cons_cap = 1 ‣ exercicio = 'REAL' | V6: s1emp | W6: ‣ Este campo tem de ser calculado por fases: ‣ 1º - Calculamos o campo auxiliar "ead_final_liquida_grup": ‣ Para cada combinação dos campos "cempresa", "cbalcao", "cnumecta", "zdeposit" iremos SOMAR as: Médias do campo "ead_final_liquida" para cada par dos campos "s1emp", "contra1"; ‣ 2º - Calculamos o campo auxiliar "final_stage_grup": ‣ Para cada combinação dos campos "cempresa", "cbalcao", "cnumecta", "zdeposit" iremos calcular "final_stage" máximo: MAX(final_stage); ‣ 3º - Calculamos o campo auxiliar "pd12m_ifrs9_grup": ‣ Para cada combinação dos campos "cempresa", "cbalcao", "cnumecta", "zdeposit" iremos calcular a média ponderada do campo "pd12m_ifrs9" ao campo "ead": SUM(ead * pd12m_ifrs9) / SUM(ead); ‣ 4º - Calculamos o campo auxiliar "pd_lt_ifrs9_grup": ‣ Para cada combinação dos campos "cempresa", "cbalcao", "cnumecta", "zdeposit" iremos calcular a média ponderada do campo "pd_lt_ifrs9" ao campo "ead": SUM(pd_lt_ifrs9 * ead) / SUM(ead); ‣ 5º - Calculamos o campo auxiliar "pd_ifrs9_grup": ‣ Se final_stage_grup = '1': pd12m_ifrs9_grup; ‣ Caso contrário: pd_lt_ifrs9_grup; ‣ Finalmente para cada Counterparty Identifier calculamos a média ponderada do campo auxiliar "pd_ifrs9_grup" ao campo auxiliar "ead_final_liquida_grup": SUM(pd_ifrs9_grup * ead_final_liquida_grup) / SUM(ead_final_liquida_grup) | X6: A agrupação final é feita segundo o campo "Counterparty Identifier" deste mesmo documento | Y6: Esta lógica pode mudar se o Instrument Identifier for redefinido. Explorar também a média do ead_liquida
V7: contra1
V8: ead_final_liquida
T9: cd_alm.al029_cnt_core_m | U9: ‣ ref_date = data do report | V9: cempresa
V10: cbalcao
V11: cnumecta
V12: zdeposit
T13: ifrs9_out_expected_loss_8_7 | U13: ‣ Apenas são trazidos os "contract_id"s que têm "exec_id_part" correspondente na tabela cd_captools.imcatf046_flag_fecho à data ("cmes") do report | V13: pd12m_ifrs9
V14: pd_lt_ifrs9
V15: ead
T16: ifrs9_out_staging_8_7 | U16: ‣ Apenas são trazidos os "contract_id"s que têm "exec_id_part" correspondente na tabela cd_captools.imcatf046_flag_fecho à data ("cmes") do report | V16: final_stage
A17: V_11 | B17: Risk parameters | C17: Probability of default (others) | D17: Numeric. Basis points | E17: Applicable only to institutions not using CRR IRB models. These institutions should maintain records of probabilities of default or scores provided by scoring/rating models. In the case of PDs produced at the instrument level only, the counterparty’s PD is to be reported as the exposure-weighted average PD across the PDs of all instruments of the counterparty. If, for a given counterparty, PDs are estimated for both the counterparty and (some of) the products of the counterparty, it is the counterparty’s PD which is to be reported. | F17: Aplicável apenas a instituições que não utilizam modelos CRR IRB. Estas instituições devem manter registos das probabilidades de incumprimento ou das pontuações fornecidas pelos modelos de pontuação/rating. No caso de PDs produzidas apenas ao nível do instrumento, a PD da contraparte deve ser relatada como a PD média ponderada pela exposição entre as PDs de todos os instrumentos da contraparte. Se, para uma determinada contraparte, forem estimadas PDs tanto para a contraparte como para (alguns dos) produtos da contraparte, é a PD da contraparte que deve ser reportada. | H17: - | I17: - | J17: - | L17: SIM | M17: probability_default_others | N17: Mapeamento LT: Este campo é Not Applicable, reportar 11111111111 | O17: Concluído | P17: ='PDS - Desenvolvimento'!$K$131 -> Concluído | Q17: 45608 | R17: Alterações ao Motor LT - Novos Campos: Definição Fechada / Dados existem no Datalake | T17: N/A | U17: N/A | V17: N/A | W17: N/A | X17: N/A

Sheet LEGALP_PROTECTIONS
A1: Instruções SRB | H1: Mapeamento efetuado pela Corporação e respetiva Descrição Loan Tape (LT) | L1: Análise IT | T1: Implementação Deloitte (OLD)
A2: ID | B2: Categoria | C2: Coluna | D2: Tipo de dados | E2: Descrição | F2: Descrição - Português | H2: Mapeamentos Corporação (LT) | I2: Descrição (LT) | J2: Additional Guidance (LT) | L2: Novo campo na tabela LT004? | M2: Nome do campo no ficheiro | N2: Mapeamento LT / Comentários IT | O2: Estado especificação | P2: Estado desenvolvimento | Q2: Data da última alteração do Estado desenvolvimento | R2: Tipo de Tarefa para a estimativa | T2: Fontes de Informação | U2: Filtros | V2: Campo | W2: Regras de Preenchimento | X2: Agrupações | Y2: Comentários reuniões
A3: V_12 | B3: Identification information | C3: Protection identifier | D3: Alphanumeric | E3: An identifier applied to uniquely identify each protection/collateral used to secure the instrument. | F3: Um identificador aplicado para identificar exclusivamente cada proteção/garantia utilizada para garantir o instrumento. | H3: PROTECTION-PRTCTN_ID | I3: Protection ID | J3: An identifier applied by the reporting agent to uniquely identify each protection used to secure the instrument. Each protection must have one protection identifier. This value will not change over time and cannot be used as the protection identifier for any other protection. | L3: NÃO | M3: protection_id | N3: LT004_PROTECTION.PRTCTN_ID | O3: Concluído | P3: ='PDS - Desenvolvimento'!$K$148 -> Concluído | Q3: 45608 | R3: Concluído | T3: cd_captools.fr003_colaterais | U3: ‣ ref_date = data do report | V3: cempresa | W3: ‣ Concatenação dos campos mencionados anteriormente: cempresa + cbalcao_caucao + cnumecta_caucao + zcaucao | Y3: Ver se não devemos ir antes às tabelas de garantias (gts)
V4: cbalcao_caucao
V5: cnumecta_caucao
V6: zcaucao
A7: V_1 | B7: Identification information | C7: Instrument Identifier | D7: Alphanumeric | E7: An identifier applied to uniquely identify each instrument. Each instrument must have one instrument identifier. | F7: Um identificador aplicado para identificar exclusivamente cada instrumento. Cada instrumento deve ter um identificador de instrumento. | H7: Not applicable: To be reported as "N/A". This information will be availabe in "01_05_leg_instr_prot" table | I7: - | J7: - | L7: SIM | M7: instrument_id | N7: Mapeamento LT: Not Applicable: Reportar 'N/A' Comentários IT: Este campo constará no ficheiro "01_05_leg_instr_prot" | O7: Concluído | P7: ='PDS - Desenvolvimento'!$K$163 -> Concluído | Q7: 45608 | R7: Alterações ao Motor LT - Novos Campos: Definição Fechada / Dados existem no Datalake | T7: cd_alm.kt_chaves_alm_m | U7: ‣ ref_date = data do report | V7: cempresa | W7: ‣ Concatenação dos campos mencionados anteriormente: cempresa + cbalcao + cnumecta + zdeposit | Y7: Após reunião com LCM foi indicado que este campo deveria ser na mesma o cempresa … zeposit mas da tabela fr001/fr004 em vez da al029 isto porque tendo que conciliar com o finrep, faz sentido que tenha a mesma granularidade
V8: cbalcao
V9: cnumecta
V10: zdeposit
A11: V_187 | B11: Identification information | C11: Type of collateral | D11: String | E11: The AnaCredit item “type of protection” (Section 9.4.3. of the Anacredit Reporting Manual part II - Dataset and data attributes) provides a breakdown of collateral eligible in accordance with the CRR. The proposed breakdown adds several categories. Options: ‣ Gold ‣ Currency and deposits ‣ Securities ‣ Loans ‣ Equity and investment fund shares or units ‣ Credit derivatives ‣ Financial guarantees other than credit derivatives ‣ Trade receivables ‣ Life insurance policies pledged ‣ Residential real estate collateral ‣ Offices and commercial premises ‣ Commercial real estate collateral ‣ Other physical collateral ‣ Other protection ‣ Hotels & entertainment ‣ Infrastructure projects ‣ Factories – warehouses ‣ Equipment & machinery ‣ Automotive ‣ Aircraft ‣ Shipping | F11: O item "type of protection" da AnaCredit (Secção 9.4.3. do Anacredit Reporting Manual parte II - Dataset and data attributes) fornece uma discriminação das garantias elegíveis de acordo com o CRR. A repartição proposta acrescenta diversas categorias. Opções: ‣ Gold ‣ Currency and deposits ‣ Securities ‣ Loans ‣ Equity and investment fund shares or units ‣ Credit derivatives ‣ Financial guarantees other than credit derivatives ‣ Trade receivables ‣ Life insurance policies pledged ‣ Residential real estate collateral ‣ Offices and commercial premises ‣ Commercial real estate collateral ‣ Other physical collateral ‣ Other protection ‣ Hotels & entertainment ‣ Infrastructure projects ‣ Factories – warehouses ‣ Equipment & machinery ‣ Automotive ‣ Aircraft ‣ Shipping | H11: PROTECTION-TYP_PRTCTN | I11: Protection type | J11: Type of protection received, irrespective of its eligibility for credit risk mitigation. | L11: NÃO | M11: type_collateral | N11: LT004_PROTECTION.TYP_PRTCTN ‣ Necessário criar novas parametrizaçôes nas tabelas lt829_regras_conversao e lt830_conversoes, podendo as mesmas ser consultadas neste documento nas sheets: ‣ LT829 - filtrando por campo_conceito = 'TYP_PRTCTN' e regra_conversao = '1'; ‣ LT830 - filtrando por segmento = 'Exposures to legal persons' e campo_conceito = 'TYP_PRTCTN'. | O11: Concluído | P11: ='PDS - Desenvolvimento'!$K$152 -> Concluído | Q11: 45665 | R11: Concluído | T11: Tabela de parametrização: codemapping | U11: ‣ dd_field_id = "187" | V11: dd_code | W11: ‣ Tradução do campo "typ_prtctn" através de uma ligação com o campo "dd_code" para obter o campo: dd_value
V12: dd_value
T13: cd_loan_tapes_bce.lt004_protection | U13: ‣ ref_date = data do report | V13: typ_prtctn
A14: V_14 | B14: Size collateral | C14: Building Area (M2) | D14: Numeric | E14: Building area of the building in square metres. Only applicable to Residential real estate collateral, Offices and commercial premises, Commercial real estate collateral, Hotels & entertainment, Factories – warehouses. | F14: Área de construção do edifício em metros quadrados. Aplicável apenas a Garantias imobiliárias residenciais, Escritórios e instalações comerciais, Garantias imobiliárias comerciais, Hotéis e entretenimento, Fábricas – armazéns. | H14: - | I14: - | J14: - | L14: SIM gross_area | M14: building_area_m2 | N14: Mapeamento LT: Campo "narbrut" da tabela cd_garantias.gt009_bens_imov Comentários IT: ‣ Segundo Luís Capitão-Mor, este novo campo deverá ser alimentado pelo MUG (Modelo Único de Garantias). Como tal, agendou-se reunião com Alexandre Dionísio Esteves (08-04-2024), na qual se comentou: 1) Este campo ainda não existe no MUG (deveria ser adicionado à cd_garantias.gt009_bens_imov); 2) Esta informação existe na gpt32, embora nessa tabela este campo não seja de preenchimento obrigatório, como tal, existem GAPs de informação; 3) O universo completo de imóveis está na tabela gpt18 os quais não estão 100% mapeados na gpt32; 4) Luís Capitão-Mor solicitou a Alexandre Dionísio Esteves o agendamento de uma reunião com Susana Fernandes/Ricardo. Nessa reunião terá de se questionar: 1) O que significam cada uma das áreas apresentadas pelo Alexandre Dionísio Esteves (área de implantação, área do terreno, área bruta, área útil, área coberta, ...) 2) Para cada tipo de imóvel (apartamento, vivenda, armazém, ...) perceber quais das áreas se aplicam e o seu significado. 5) Luís Capitão-Mor comentou que se deveria questionar a Corporação sobre o que representa a building area nos vários tipos de imóveis, dando exemplos das nossas dúvidas. ex: - No caso de um apartamento é a área do apartamento ou do edifício onde se encontra? Faria sentido ser a do apartamento, contudo, a descrição do SRB pede a do edifício (of the building). - Esta área inclui paredes? - No caso de uma vivenda que tem 3 andares, a área seria a da implantação (100m2) ou a dos 3 andares (300m2) Reunião 08/08/2024 com Alexandre Esteves, Susana Fernandes: -Building Area: Usar a área bruta da GPT32. Se não existir, usar a área útil da GPT32. - Land Area: Usar a área do terreno da GPT32. Se for um terreno/lote terreno e se a area do terreno da GPT32 não existir, usar a área bruta da GPT32. - Em princípio, traziam-se 3 campos da GPT32 para o MUG: area bruta, area util, area terreno. Depois seria no Loan Tape que se aplicariam as regras mencionadas acima. - Alexandre Esteves ficou de verificar para cada um dos tipos de imoveis se as regras mencionadas acima funcionariam. Reunião 14/08/2024 com Luís Capitão-Mor, Alexandre Esteves, Pedro Mendes: - Luís Capitão-Mor solicitou que se questionasse a Corporação relativamente a estes 2 campos -> ver email Luís Pragosa 14/08/2024 16:40 para Pedro Mendes - Deverá questionar-se o José Rio para se perceber se nos Certificados Energéticos existem campos de áreas. Caso existam, o MUG deverá considerar quer a GPT32 quer os Certificados Energéticos. Reunião 09/09/2024 com José Rio: José Rio referiu que já existe na Cloud a tabela Buildingenergycertificate (campo builtupareaquantity) e existirá On-Prem na BD curated_internal_gestaoimoveis previsivelmente em PRO: 16/Set. Reunião 09/09/2024 com Alexandre Esteves: Alexandre Esteves irá agendar reunião com LCM. Terão de se trazer 3 campos para o MUG: area terreno (origem GPT32), area bruta (origem GPT32) e area util (origem GPT32 e buildingenergycertificate).Em princípio, a area util deverá ser area com data mais recente entre as 2 tabelas (GPT32 e buildingenergycertificate). No caso de terem a mesma data, dar prioridade ao Certificados Energéticos (buildingenergycertificate). Email Pedro Mendes 11/09/2024 11:07 com resposta da Corporação: 2. No te puedo responder con tanto detalle porque, en ausencia de una definición por parte del SRB más aterrizada, lo único que hacemos nosotros es reportar los campos recogidos en las bases de datos utilizadas para el reporte de AnaCredit, cuya definición recojo a continuación: • Land area: Número de metros cuadrados que tiene el suelo en garantía • Building area: Aprovechamiento sobre rasante en metros cuadrados útiles del ámbito, parcela o sector en que se ubica el terreno valorado, independientemente de la superficie de este. Se sumarán todos los usos lucrativos, independientemente de la tipología. que se reporta en Anacredit (al que hace referencia el SRB de forma continua en su documentación). 19/09/2024 Dora Roxo e Nádia Ahmad, não têm conhecimento de campos referentes a áreas. Reunião Final 26/09/2024 Luís Capitão-Mor, Alexandre Esteves: Terão de ser adicionados 3 campos no MUG (tabela cd_garantias.gt009_bens_imov): campo "narterr" (campo "narterr" proveniente da tabela GPT32 que representa a área do terreno ), campo "narbrut " (campo "narbrut " proveniente da tabela GPT32 que representa a área bruta), campo "narutil " (campo "narutil " proveniente da tabela GPT32 que representa a área útil). Na tabela lt004_protection serão adicionados 2 novos campos que virão do MUG: campo "land_area" (campo "narterr" proveniente da tabela cd_garantias.gt009_bens_imov) e campo "gross_area" (campo "narbrut" proveniente da tabela cd_garantias.gt009_bens_imov) | O14: Concluído | P14: ='PDS - Desenvolvimento'!$K$159 -> Concluído | Q14: 45611 | R14: Alterações ao Motor LT - Novos Campos: Definição Incompleta / Dados não existem no Datalake | W14: ‣ Forçado a NULL | Y14: É necessário verificar onde existe esta informação (ex: cd_emprestimos.gpt32_bemimove)
A15: V_15 | B15: Size collateral | C15: Land Area (M2) | D15: Numeric | E15: Land area of the property in square metres, including any land surrounding the building(s) on the property that is part of the property. | F15: Área do terreno do imóvel em metros quadrados, incluindo qualquer terreno ao redor do(s) edifício(s) do imóvel que faz parte do imóvel. | H15: - | I15: - | J15: - | L15: SIM land_area | M15: land_area_m2 | N15: Mapeamento LT: Campo "narterr" da tabela cd_garantias.gt009_bens_imov Comentários IT: ‣Aplicam-se os mesmos comentários do campo acima (Building Area (M2)) dado que estes 2 campos foram analisados em conjunto. | O15: Concluído | P15: ='PDS - Desenvolvimento'!$K$160 -> Concluído | Q15: 45611 | R15: Alterações ao Motor LT - Novos Campos: Definição Incompleta / Dados não existem no Datalake | W15: ‣ Forçado a NULL
A16: V_16 | B16: Location | C16: Property postcode | D16: Numeric | E16: Postcode where the property is located. Only applicable to Residential real estate collateral, Offices and commercial premises, Commercial real estate collateral, Hotels & entertainment, Factories – warehouses. | F16: Código postal onde o imóvel está localizado. Aplicável apenas a Garantias imobiliárias residenciais, Escritórios e instalações comerciais, Garantias imobiliárias comerciais, Hotéis e entretenimento, Fábricas – armazéns. | H16: PROTECTION-RL_ESTT_PST_CD | I16: Post code / ZIP | J16: Post code / ZIP. | L16: NÃO | M16: property_postcode | N16: LT004_PROTECTION.RL_ESTT_PST_CD | O16: Concluído | P16: ='PDS - Desenvolvimento'!$K$151 -> Concluído | Q16: 45608 | R16: Concluído | T16: cd_loan_tapes_bce.lt004_protection | U16: ‣ ref_date = data do report | V16: rl_estt_pst_cd | W16: ‣ Direto
A17: V_17 | B17: Lien | C17: Lien position | D17: Numeric | E17: The highest ranking position(s) in relation to the collateral held by the counterparty to secure the facility. If the facility has several liens on one collateral, the highest claim is reported in this data field. | F17: A(s) posição(ões) mais elevada(s) em relação às garantias detidas pela contraparte para garantir a instalação. Se a instalação tiver vários ônus sobre uma garantia, a reivindicação mais alta será relatada neste campo de dados. | H17: - | I17: - | J17: - | L17: SIM | M17: lien_position | N17: Mapeamento LT: Reportar sempre 1 Comentários IT: ‣ Reunião 2024-04-08: Segundo Luís Capitão-Mor, o Banco só aceita primeiras hipotecas, como tal, este campo deverá ser sempre preenchido com 1. | O17: Concluído | P17: ='PDS - Desenvolvimento'!$K$161 -> Concluído | Q17: 45608 | R17: Alterações ao Motor LT - Novos Campos: Definição Fechada / Dados existem no Datalake | T17: cd_loan_tapes_bce.lt006_instr_prot | U17: ‣ ref_date = data do report | V17: thrd_prty_prrty_clms | W17: ‣ Direto | Y17: Confirmar se este é o campo correto para recuperar esta informação
A18: V_18 | B18: Collateral characteristics | C18: Detailed type of Shipping collateral | D18: String | E18: Detailed type of collateral received. Applicable only to shipping portfolios. Options: ‣ Bulker (1) ‣ Container (2) ‣ Crude Oil Tanker (3) ‣ Product Tanker (4) ‣ Chemical Tanker (5) ‣ Cruise Ship (6) ‣ Ferry (7) ‣ LPG Carrier (8) ‣ Offshore (9) ‣ Other (10) | F18: Tipo detalhado de garantia recebida. Aplicável apenas a portfólios de remessa. Opções: ‣ Bulker (1) ‣ Container (2) ‣ Crude Oil Tanker (3) ‣ Product Tanker (4) ‣ Chemical Tanker (5) ‣ Cruise Ship (6) ‣ Ferry (7) ‣ LPG Carrier (8) ‣ Offshore (9) ‣ Other (10) | H18: - | I18: - | J18: - | L18: SIM | M18: det_type_ship_collateral | N18: Mapeamento LT: Not Applicable: Reportar 'N/A' Comentários IT: ‣ Reunião 2025-04-14 Luís Capitão-Mor, Pedro Mendes: Trata-se de uma operativa que o Banco não promove, pelo que se sugere N/A. ‣ Email Paulo Oliveira 23/04/2024 20:24: "1) Não tenho conhecimento que existam shipping portfolios no Banco, confirmas? Pode ser que seja categorizado pelo Banco de outra forma. Asset lending não, mas não descartava que houvesse alguns barcos financiados em leasing nomeadamente para empresas do sector. Perguntava á Leasing. Não sei se não haverá como colateral algum cliente que tenha dado o seu barco de recreio (iate). 2) Se eventualmente existisse uma Empresa que quisesse dar alguma destas opções como colateral, o Banco aceitava? Sim, são activos com valor de mercado. Tal como aceitamos aviões, aceitariamos navios como colateral 3) Em caso afirmativo ao ponto 2), sabes de algum caso em concreto para que possa ir verificar e ver como fica registado no Banco? Não me lembro de nenhum Acho que deveramos ir analisar as empresas de navegação com frota." ‣ Email Rute Ferreira 22/04/2024 20:17 com o Histórico de conversações (ver pasta Emails: "RE IR RH Report Valuation - Campo Detailed type of Shipping collateral") | O18: Concluído | P18: ='PDS - Desenvolvimento'!$K$162 -> Concluído | R18: Alterações ao Motor LT - Novos Campos: Definição por Iniciar | T18: N/A | U18: N/A | V18: N/A | W18: N/A | X18: N/A | Y18: Não existe este genero de operativa

Sheet LEGALP_INSTRUMENT_COUNTERPARTY
A1: Instruções SRB | H1: Mapeamento efetuado pela Corporação e respetiva Descrição Loan Tape (LT) | L1: Análise IT | T1: Implementação Deloitte (OLD)
A2: ID | B2: Categoria | C2: Coluna | D2: Tipo de dados | E2: Descrição | F2: Descrição - Português | H2: Mapeamentos Corporação (LT) | I2: Descrição (LT) | J2: Additional Guidance (LT) | L2: Novo campo na tabela LT005? | M2: Nome do campo no ficheiro | N2: Mapeamento LT / Comentários IT | O2: Estado especificação | P2: Estado desenvolvimento | Q2: Data da última alteração do Estado desenvolvimento | R2: Tipo de Tarefa para a estimativa | T2: Fontes de Informação | U2: Filtros | V2: Campo | W2: Regras de Preenchimento | X2: Agrupações | Y2: Comentários reuniões
A3: V_1 | B3: Identification information | C3: Instrument Identifier | D3: Alphanumeric | E3: An identifier applied to uniquely identify each instrument. Each instrument must have one instrument identifier | F3: Um identificador aplicado para identificar exclusivamente cada instrumento. Cada instrumento deve ter um identificador de instrumento. | H3: INSTR_ENTITY-INSTRMNT_ID | I3: Instrument ID | J3: An identifier applied by the reporting agent to uniquely identify each instrument under a single contract. Each instrument must have one instrument identifier. This value will not change over time and cannot be used as the instrument identifier for any other instrument under the same contract. Supervised Insitutions are asked to furnish the INSTRMNT_ID with the exact same value as it is reported to AnaCredit (or any similar central credit register). If this is not available, the value shall be reported as it is internally used. If an instrument is not reported to AnaCredit but requested for the purposes of the on-site inspection please provide the bank-internally used value. Foreign Key from INSTRUMENT table. | L3: NÃO | M3: instrument_id | N3: LT005_INSTR_ENT.INSTRMNT_ID | O3: Concluído | P3: ='PDS - Desenvolvimento'!$K$144 -> Concluído | Q3: 45608 | R3: Concluído | T3: cd_alm.al029_cnt_core_m | U3: ‣ ref_date = data do report | V3: cempresa | W3: ‣ Concatenação dos campos mencionados anteriormente: cempresa + cbalcao + cnumecta + zdeposit | Y3: Ver se não devemos ir antes às tabelas de garantias (gts)
V4: cbalcao
V5: cnumecta
V6: zdeposit
A7: V_2 | B7: Identification information | C7: Counterparty Identifier | D7: Alphanumeric | E7: Identifier applied to uniquely identify each counterparty. | F7: Identificador aplicado para identificar exclusivamente cada contraparte. | H7: INSTR_ENTITY-ENTTY_ID | I7: Entity ID | J7: An identifier applied by the reporting agent to uniquely identify each counterparty. Each counterparty has a unique and exclusive counterparty identifier. This means that this value will not change over time and can never be used as the counterparty identifier for any other counterparty. Foreign key from ENTITY table. | L7: NÃO | M7: counterparty_id | N7: LT005_INSTR_ENT.ENTTY_ID | O7: Concluído | P7: ='PDS - Desenvolvimento'!$K$145 -> Concluído | Q7: 45608 | R7: Concluído | T7: cd_alm.al029_cnt_core_m | U7: ‣ ref_date = data do report | V7: zcliente | W7: ‣ Direto

Sheet LEGALP_INSTRUMENT_PROTECTION
A1: Instruções SRB | H1: Mapeamento efetuado pela Corporação e respetiva Descrição Loan Tape (LT) | L1: Análise IT | T1: Implementação Deloitte (OLD)
A2: ID | B2: Categoria | C2: Coluna | D2: Tipo de dados | E2: Descrição | F2: Descrição - Português | H2: Mapeamentos Corporação (LT) | I2: Descrição (LT) | J2: Additional Guidance (LT) | L2: Novo campo na tabela LT006? | M2: Nome do campo no ficheiro | N2: Mapeamento LT / Comentários IT | O2: Estado especificação | P2: Estado desenvolvimento | Q2: Data da última alteração do Estado desenvolvimento | R2: Tipo de Tarefa para a estimativa | T2: Fontes de Informação | U2: Filtros | V2: Campo | W2: Regras de Preenchimento | X2: Agrupações | Y2: Comentários reuniões
A3: V_1 | B3: Identification information | C3: Instrument Identifier | D3: Alphanumeric | E3: An identifier applied to uniquely identify each instrument. Each instrument must have one instrument identifier | F3: Um identificador aplicado para identificar exclusivamente cada instrumento. Cada instrumento deve ter um identificador de instrumento. | H3: INSTR_PROTECTION-INSTRMNT_ID | I3: Instrument ID | J3: An identifier applied by the reporting agent to uniquely identify each instrument under a single contract. Each instrument must have one instrument identifier. This value will not change over time and cannot be used as the instrument identifier for any other instrument under the same contract. Supervised Insitutions are asked to furnish the INSTRMNT_ID with the exact same value as it is reported to AnaCredit (or any similar central credit register). If this is not available, the value shall be reported as it is internally used. If an instrument is not reported to AnaCredit but requested for the purposes of the on-site inspection please provide the bank-internally used value. Foreign Key from INSTRUMENT table. | L3: NÃO | M3: instrument_id | N3: LT006_INSTR_PROT.INSTRMNT_ID | O3: Concluído | P3: ='PDS - Desenvolvimento'!$K$166 -> Concluído | Q3: 45608 | R3: Concluído | T3: cd_alm.al029_cnt_core_m | U3: ‣ ref_date = data do report | V3: cempresa | W3: ‣ Concatenação dos campos mencionados anteriormente: cempresa + cbalcao + cnumecta + zdeposit | Y3: Ver se não devemos ir antes às tabelas de garantias (gts)
V4: cbalcao
V5: cnumecta
V6: zdeposit
A7: V_12 | B7: Identification information | C7: Protection identifier | D7: Alphanumeric | E7: An identifier applied to uniquely identify each protection/collateral used to secure the instrument. | F7: Um identificador aplicado para identificar exclusivamente cada proteção/garantia utilizada para garantir o instrumento. | H7: INSTR_PROTECTION-PRTCTN_ID | I7: Protection ID | J7: An identifier applied by the reporting agent to uniquely identify each protection used to secure the instrument. Each protection must have one protection identifier. This value will not change over time and cannot be used as the protection identifier for any other protection. Foreign Key from PROTECTION table. | L7: NÃO | M7: protection_id | N7: LT006_INSTR_PROT.PRTCTN_ID | O7: Concluído | P7: ='PDS - Desenvolvimento'!$K$167 -> Concluído | Q7: 45608 | R7: Concluído | T7: cd_captools.fr003_colaterais | U7: ‣ ref_date = data do report | V7: cempresa | W7: ‣ Concatenação dos campos mencionados anteriormente: cempresa + cbalcao_caucao + cnumecta_caucao + zcaucao
V8: cbalcao_caucao
V9: cnumecta_caucao
V10: zcaucao

Sheet NATURAL PERSONS DATA SETS
A1: SRB DATA SET FOR EXPOSURES TO NATURAL PERSONS The following data set covers exposures to natural persons, which, in many cases, represent the main type of exposures on banks’ balance sheets (e.g. retail institutions or mortgage institutions). Such exposures might comprise lending products such as mortgages, consumer loans, credit cards, etc. Valuations of retail portfolios are usually made with lesser granularity than valuations of corporate portfolios. However, in specific circumstances (e.g. high default rates in mortgage portfolios) a collective assessment might not suffice and the valuer might rely on a more granular approach for qualitatively and quantitatively assessing the level of economic impairment of exposures to natural persons that would typically be impaired on a collective basis under International Financial Reporting Standard (IFRS 9). In this case, the valuer would require a more granular data set to perform valuations. To avoid any duplication of data points or definitions, the data set for exposures to natural persons is based on the AnaCredit data points and definitions for legal persons. However, institutions can leverage on the definitions, data points and reporting thresholds of local standards or legislation, provided those definitions and data points are, in the IRT’s view, equivalent to those envisaged for AnaCredit. Serão produzidos cinco ficheiros de report referentes a Natural Persons: ‣ SRB Instruments Data Set for exposures to natural persons (NATURALP_INSTRUMENTS); ‣ SRB Counterparties Data Set for exposures to natural persons (NATURALP_COUNTERPARTIES); ‣ SRB Protection received Data Set for exposures to natural persons (NATURALP_PROTECTIONS); ‣ SRB Instrument/Counterparty mapping Data Set for exposures to natural persons (NATURALP_INSTRUMENT_COUNTERPARTY); ‣ SRB Instrument/Protection mapping Data Set for exposures to natural persons (NATURALP_INSTRUMENT_PROTECTION);
A2: SRB DATA SET FOR EXPOSURES TO NATURAL PERSONS O seguinte data set abrange exposições a pessoas singulares, que, em muitos casos, representam o principal tipo de exposições nos balanços dos bancos (por exemplo, instituições de retalho ou instituições hipotecárias). Essas exposições podem incluir produtos de empréstimo, como hipotecas, empréstimos pessoais, cartões de crédito, etc. As avaliações de carteiras de retalho são geralmente feitas com menos granularidade do que as avaliações de carteiras corporativas. No entanto, em circunstâncias específicas (por exemplo, elevadas taxas de incumprimento em carteiras hipotecárias), uma avaliação colectiva pode não ser suficiente e o avaliador pode basear-se numa abordagem mais granular para avaliar qualitativa e quantitativamente o nível de imparidade económica das exposições a pessoas singulares que normalmente seriam prejudicadas numa base colectiva ao abrigo da International Financial Reporting Standard (IFRS 9). Neste caso, o avaliador necessitaria de um conjunto de dados mais granular para realizar avaliações. Para evitar qualquer duplicação de pontos de dados ou definições, o data set para exposições a pessoas singulares baseia-se nos pontos de dados e definições da AnaCredit para pessoas coletivas. No entanto, as instituições podem aproveitar as definições, os pontos de dados e os limites de reporte das normas ou legislação local, desde que essas definições e pontos de dados sejam, na opinião do IRT, equivalentes aos previstos para o AnaCredit. Serão produzidos cinco ficheiros de report referentes a Natural Persons: ‣ SRB Instruments Data Set for exposures to natural persons (VDS_OUT_NATURALP_INSTRUMENTS); ‣ SRB Counterparties Data Set for exposures to natural persons (VDS_OUT_NATURALP_COUNTERPARTIES); ‣ SRB Protection received Data Set for exposures to natural persons (VDS_OUT_NATURALP_PROTECTIONS).

Sheet NATURALP_INSTRUMENTS
A1: Instruções SRB | H1: Mapeamento efetuado pela Corporação e respetiva Descrição Loan Tape (LT) | M1: Análise IT | U1: Implementação Deloitte (OLD)
A2: ID | B2: Categoria | C2: Coluna | D2: Tipo de dados | E2: Descrição | F2: Descrição | H2: Mapeamentos Corporação (LT) | I2: Descrição (LT) | J2: Additional Guidance (LT) | M2: Novo campo na tabela LT002? | N2: Nome do campo no ficheiro | O2: Mapeamento LT / Comentários IT | P2: Estado especificação | Q2: Estado desenvolvimento | R2: Data da última alteração do Estado desenvolvimento | S2: Tipo de Tarefa para a estimativa | U2: Fontes de Informação | V2: Filtros | W2: Campo | X2: Regras de Preenchimento | Y2: Agrupações | Z2: Comentários reuniões
A3: V_1 | B3: Identification information | C3: Instrument Identifier | D3: Alphanumeric | E3: Identifier applied to uniquely identify each instrument. Each instrument must have one instrument identifier. | F3: Um identificador aplicado para identificar exclusivamente cada instrumento. Cada instrumento deve ter um identificador de instrumento. | H3: INSTRUMENT-INSTRMNT_ID | I3: Instrument ID | J3: An identifier applied by the reporting agent to uniquely identify each instrument under a single contract. Each instrument must have one instrument identifier. This value will not change over time and cannot be used as the instrument identifier for any other instrument under the same contract. Supervised Insitutions are asked to furnish the INSTRMNT_ID with the exact same value as it is reported to AnaCredit (or any similar central credit register). If this is not available, the value shall be reported as it is internally used. If an instrument is not reported to AnaCredit but requested for the purposes of the on-site inspection please provide the bank-internally used value. | M3: NÃO | N3: instrument_id | O3: LT002_INSTRUMENT.INSTRMNT_ID | P3: Concluído | Q3: ='PDS - Desenvolvimento'!$K$3 -> Concluído | R3: 45608 | S3: Concluído | U3: cd_alm.al029_cnt_core_m | V3: ‣ ref_date = data do report | W3: cempresa | X3: ‣ Concatenação dos campos mencionados anteriormente: cempresa + cbalcao + cnumecta + zdeposit | Z3: Após reunião com LCM foi indicado que este campo deveria ser na mesma o cempresa … zeposit mas da tabela fr001/fr004 em vez da al029 isto porque tendo que conciliar com o finrep, faz sentido que tenha a mesma granularidade
W4: cbalcao
W5: cnumecta
W6: zdeposit
A7: V_2 | B7: Identification information | C7: Counterparty Identifier | D7: Alphanumeric | E7: Identifier applied to uniquely identify each counterparty. | F7: Identificador aplicado para identificar exclusivamente cada contraparte. | H7: Not applicable: To be reported as "N/A". This information will be availabe in "02_04_nat_instr_count" table | I7: - | J7: - | M7: SIM | N7: counterparty_id | O7: Mapeamento LT: Not Applicable: Reportar 'N/A' Comentários IT: Este campo constará no ficheiro "02_04_nat_instr_count" | P7: Concluído | Q7: ='PDS - Desenvolvimento'!$K$77 -> Concluído | R7: 45608 | S7: Alterações ao Motor LT - Novos Campos: Definição Fechada / Dados existem no Datalake | U7: cd_alm.al029_cnt_core_m | V7: ‣ ref_date = data do report | W7: zcliente | X7: ‣ Direto | Z7: Se se alterar o universo trazer o zcliente respetivo
A8: V_139 | B8: Identification information | C8: Reporting data identifier | D8: Alphanumeric | E8: The counterparty identifier of the reporting agent which reports the data. | F8: O identificador da contraparte do agente inquirido que comunica os dados. | H8: INSTRUMENT-COD_SOC | I8: Entity code of the informing society. | J8: Cargabal code or internal identifier of the informing society. | M8: NÃO | N8: reporting_data_id | O8: LT002_INSTRUMENT.COD_SOC | P8: Concluído | Q8: ='PDS - Desenvolvimento'!$K$76 -> Concluído | R8: 45608 | S8: Concluído | X8: ‣ Forçado a "549300URJH9VSI58CS32" (código lei do BANCO SANTANDER TOTTA, S.A.)
A9: V_140 | B9: Identification information | C9: Observed agent identifier | D9: Alphanumeric | E9: The counterparty identifier of the observed agent (i.e. an institutional unit of the reporting agent) whose data are reported by the reporting agent. | F9: O identificador da contraparte do agente observado (ou seja, uma unidade institucional do agente inquirido) cujos dados são comunicados pelo agente inquirido. | H9: INSTRUMENT-OBSRVD_AGNT_ID | I9: Observed agent identifier | J9: Counterparty identifier for the observed agent. If there are several observed agents to be reported please separate by comma (,). | M9: NÃO | N9: observed_agent_id | O9: LT002_INSTRUMENT.OBSRVD_AGNT_ID | P9: Concluído | Q9: ='PDS - Desenvolvimento'!$K$7 -> Concluído | R9: 45608 | S9: Concluído | X9: ‣ Forçado a "549300URJH9VSI58CS32" (código lei do BANCO SANTANDER TOTTA, S.A.)
A10: V_141 | B10: Identification information | C10: Contract identifier | D10: Alphanumeric | E10: An identifier applied by the reporting agent to uniquely identify each contract. The contract identifier refers to the credit agreement between two or more parties under which the instrument is created. | F10: Um identificador aplicado pelo agente inquirido para identificar de forma única cada contrato. O identificador do contrato refere-se ao contrato de crédito entre duas ou mais partes ao abrigo do qual o instrumento é criado. | H10: INSTRUMENT-CNTRCT_ID | I10: Contract ID | J10: An identifier applied by the reporting agent to uniquely identify each contract. Each contract must have one contract identifier. This value will not change over time and cannot be used as the contract identifier for any other contract. | M10: NÃO | N10: contract_id | O10: LT002_INSTRUMENT.CNTRCT_ID | P10: Concluído | Q10: ='PDS - Desenvolvimento'!$K$4 -> Concluído | R10: 45608 | S10: Concluído | U10: cd_alm.al029_cnt_core_m | V10: ‣ ref_date = data do report | W10: cempresa | X10: ‣ Concatenação dos campos mencionados anteriormente: cempresa + "_" + cbalcao + "_" + cnumecta + "_" + zdeposit | Z10: Replicar o Instrument_id
W11: cbalcao
W12: cnumecta
W13: zdeposit
A14: V_3 | B14: Exposure class | C14: CRR Exposure class | D14: String | E14: The exposures classes for the calculation of RWAs for credit risks are as follows (not applicable when exposures are classified in the CRR trading book as defined in Article 4(1)(86) of Regulation (EU) No 575/2013): Where a bank uses the standardised approach: ‣ Central governments or central banks (SCENGOV) ‣ Regional governments or local authorities (SREGGOV) ‣ Public sector entities (SPUBSEC) ‣ Multilateral development banks (SDEVBAN) ‣ International organisation (SINTORG) ‣ Institutions (SINSTIT) ‣ Corporates (SCORPOR) ‣ Retail (SRETAIL) ‣ Secured by mortgages and immovable property (SSECMOR) ‣ Defaulted (SDEFAUL) ‣ High risk (SHIGHRI) ‣ Covered bonds (SCOVBON) ‣ Items representing securitisation positions ‣ Institutions and corporates with a short term credit assessment (SSHOTER) ‣ Collective investment undertakings (SCOLINV) ‣ Equity (SEQUITY) ‣ Other (SOTHERI) Where a bank uses the IRB approach: ‣ Central governments and central banks (ICENGOV) ‣ Institutions (IINSTIT) ‣ Corporates (ICORPOR) ‣ Retail (IRETAIL) ‣ Equity (IEQUITY) ‣ Items representing securitisation positions ‣ Other non-credit-obligation assets (IOTHERC) | F14: As classes de posições em risco para o cálculo dos ativos ponderados pelo risco (RWA) para riscos de crédito são as seguintes (não aplicável quando as posições em risco são classificadas na carteira de negociação do CRR, conforme definido no artigo 4(1)(86), do Regulamento (UE) No 575 /2013). Informação deriva de uma lista baseada na classificação da facilidade utilizando a classe de risco, conforme descrito no artigo 112 do Regulamento (UE) No 575/2013 para bancos que utilizam a abordagem padrão) e no artigo 147 do Regulamento (UE) No 575/2013 (para bancos que utilizam abordagem baseada em classificações internas (IRB)) Quando um banco utiliza a abordagem padrão: ‣ Central governments or central banks (SCENGOV) ‣ Regional governments or local authorities (SREGGOV) ‣ Public sector entities (SPUBSEC) ‣ Multilateral development banks (SDEVBAN) ‣ International organisation (SINTORG) ‣ Institutions (SINSTIT) ‣ Corporates (SCORPOR) ‣ Retail (SRETAIL) ‣ Secured by mortgages and immovable property (SSECMOR) ‣ Defaulted (SDEFAUL) ‣ High risk (SHIGHRI) ‣ Covered bonds (SCOVBON) ‣ Items representing securitisation positions ‣ Institutions and corporates with a short term credit assessment (SSHOTER) ‣ Collective investment undertakings (SCOLINV) ‣ Equity (SEQUITY) ‣ Other (SOTHERI) Quando um banco utiliza a abordagem IRB: ‣ Central governments and central banks (ICENGOV) ‣ Institutions (IINSTIT) ‣ Corporates (ICORPOR) ‣ Retail (IRETAIL) ‣ Equity (IEQUITY) ‣ Items representing securitisation positions ‣ Other non-credit-obligation assets (IOTHERC) | H14: - | I14: - | J14: - | M14: SIM | N14: crr_exposure_class | O14: Mapeamento LT: ‣ Utilizar o campo "segmento_corep_final" da tabela ct013_rwa_princ; Nota: Os códigos "segmento_corep_final" seguem sempre a mesma estrutura, começam com um caracter que identifica se é IRB (I_...) ou Standard (S_...) e de seguida um numérico (ex. I_3.1, I_5.1, S_1.0). ‣ Para o mesmo contrato este campo pode retornar vários códigos "segmento_corep_final" distintos, de seguida estão os passos que permitem resolver esta ambiguidade: 1. Deve seguir a lógica do campo RWA_MTHD, de momento a lógica é, se existir IRB e Standard então trazer informação relativa a IRB; 2. Se mesmo aplicando o passo 1 ainda existirem vários códigos "segmento_corep_final" distintos (vários códigos IRB ou vários códigos Standard) então: recuperar o código "segmento_corep_final" com o menor numérico associado. Exemplo: O contrato A tem associados os seguintes códigos "segmento_corep_final" distintos: I_3.1, I_5.1, S_1.0: 1. Remover o Standard: I_3.1, I_5.1; 2. Ficar com o menor numérico: I_3.1. ‣ Necessário criar nova parametrização na tabela lt831_param_conceitos, podendo a mesma ser consultada neste documento na sheet 'LT831' filtrando por tabela_conceito = 'LT002_INSTRUMENT' e campo_conceito = 'CRR_EXPOSURE_CLASS' ‣ Reportar ‘N/A’ se campo flag_cons_cap=0 da tabela cd_captools.ct013_rwa_princ Comentários IT: '‣ Proposta: Consumir o campo "segmento_corep_final" da tabela ct013_rwa_princ, tendo em atenção que se tem de manter a lógica aplicada no campo LT "RWA_MTHD" (se for IRB ou Standard), para resolver os casos em que para o mesmo contrato temos mais do que segmento corep (IRB e Standard). Nota existem contratos que têm mais do que um segmento corep IRB ou Standard ou seja tem de haver uma lógica de selecionar o mais significativo pois só podemos reportar um valor neste campo). ‣ No Loan Tape para cálculo do LGD que vem da ct013_rwa_princ, quando existe IRB e STD, escolhe-se IRB. ‣ Segundo Email de Pedro Mendes com a resposta da Corporação (26/03/2024 17:28), no caso de existir mais do que 1 CRR Exposure class para o mesmo contrato, é permitido reportar o mais significativo dos dois por valor ou os dois separados por “,” colocando o mais significativo primeiro. ‣ Analisar documento 'BS_Tabelas_Temporárias_Loan_Tape.xlsx' para consultar as regras de seleção aplicadas no campo RWA_MTHD. ‣ Reunião Pedro Mendes, Luís Capitão-Mor 05-11-2024: Foi definida a regra para este campo, como dito anteriormente: - Deve seguir a lógica do campo RWA_MTHD, de momento a lógica é, se existir IRB e Standard então trazer informação relativa a IRB; - Para os casos em que temos mais do que um "segmento_corep_final" IRB ou Standard, foram propostas duas soluções, uma seria utilizar o campo "EAD_FINAL_BRUTA" também da tabela ct013_rwa_pric como fator de peso, recuperando o "segmento_corep_final" associado ao maior "EAD_FINAL_BRUTA" (mais significativo). A segunda solução, mais simples, seria simplesmente recuperar o código "segmento_corep_final" com a numeração mais baixa, por exemplo se um contrato tiver os códigos "segmento_corep_final" I_3.1, I_5.1 ficamos apenas com o I_3.1. Optou-se pela segunda solução. ‣ Query que demonstra que para um contrato FINREP pode haver mais do que um 'segmento_corep_final' tanto para a approach 'IRB' como para a 'Standard': SELECT contract_id_fr, --ct013.s1emp,ct013.contra1, GROUP_CONCAT(DISTINCT ct013.segmento_corep_final) as segmento_corep_final_conc, --GROUP_CONCAT(ct013.segmento_corep_final) as segmento_corep_final_conc, --GROUP_CONCAT(CAST(ct013.ead_final_bruta AS STRING)) as ead_final_bruta_conc, COUNT(*) as cnt, COUNT(DISTINCT ct013.segmento_corep_final) as cnt_dist FROM ( SELECT fr004.contract_id_fr, s1emp, contra1 FROM ( SELECT DISTINCT CONCAT(cempresa,cbalcao,cnumecta,zdeposit) as contract_id_fr FROM cd_captools.fr004_cto WHERE ref_date = '2024-08-31' ) as fr004 --6211142 LEFT JOIN ( SELECT CONCAT(cempresa_fr,cbalcao_fr,cnumecta_fr,zdeposit_fr) as contract_id_fr, CONCAT(cempresa,cbalcao,cnumecta,zdeposit) as contract_id_ct FROM cd_captools.kt_chaves_finrep WHERE ref_date = '2024-08-31' ) as chaves_finrep ON chaves_finrep.contract_id_fr = fr004.contract_id_fr --6211142 LEFT JOIN ( SELECT s1emp, contra1, CONCAT(cempresa,cbalcao,cnumecta,zdeposit) as contract_id_ct FROM cd_captools.kt_chaves_bdr WHERE ref_date = '2024-08-31' ) as chaves_bdr ON chaves_bdr.contract_id_ct = chaves_finrep.contract_id_ct --2046835 WHERE chaves_bdr.contract_id_ct IS NOT NULL GROUP BY contract_id_fr, s1emp, contra1 ) as core --2046835 DIST fr --2047298 nº total LEFT JOIN ( SELECT s1emp, contra1, segmento_corep_final, ead_final_bruta FROM cd_captools.ct013_rwa_princ WHERE ref_date = '2024-08-31' ) as ct013 ON core.s1emp = ct013.s1emp AND core.contra1 = ct013.contra1 WHERE ct013.s1emp IS NOT NULL GROUP BY contract_id_fr --GROUP BY ct013.s1emp, ct013.contra1 ORDER BY cnt_dist DESC | P14: Concluído | Q14: ='PDS - Desenvolvimento'!$K$81 -> Concluído | R14: 17/01/2025 | S14: Alterações ao Motor LT - Novos Campos: Definição Incompleta / Dados existem no Datalake | U14: Tabela de parametrização: codemapping | V14: ‣ dd_field_id = "3" | W14: dd_code | X14: ‣ Tradução do campo "segmento_corep_final" através de uma ligação com o campo "dd_code" para obter o campo: dd_value
W15: dd_value
U16: cd_captools.ct013_rwa_princ | V16: ‣ ref_date = data do report ‣ flag_cons_cap = 1 ‣ exercicio = 'REAL' | W16: segmento_corep_final
A17: V_4 | B17: Exposure class | C17: FINREP Exposure class | D17: String | E17: Classification of the facility (exposure class) as defined in ITS 680/2014 Annex V Instructions FINREP (Counterparty breakdown). Opções: ‣ Central banks ‣ Central governments ‣ Credit institutions ‣ Other financial corporations ‣ Non-financial corporations ‣ Households | F17: Classificação da instalação (exposure class) conforme definido na ITS 680/2014 Anexo V Instruções FINREP (Counterparty breakdown). Opções: ‣ Central banks ‣ Central governments ‣ Credit institutions ‣ Other financial corporations ‣ Non-financial corporations ‣ Households | H17: - | I17: - | J17: - | M17: NÃO | N17: finrep_exposure_class | O17: LT002_INSTRUMENT.INTRNL_SGMNT ‣ Necessário criar novas parametrizaçôes nas tabelas lt829_regras_conversao e lt830_conversoes, podendo as mesmas ser consultadas neste documento nas sheets: ‣ LT829 - filtrando por campo_conceito = 'INTRNL_SGMNT' e regra_conversao = '1'; ‣ LT830 - filtrando por segmento = 'Exposures to natural persons' e campo_conceito = 'INTRNL_SGMNT'. | P17: Concluído | Q17: ='PDS - Desenvolvimento'!$K$19 -> Concluído | S17: Concluído | U17: Tabela de parametrização: codemapping | V17: ‣ dd_field_id = "4" | W17: dd_code | X17: ‣ Inicialmente para cada combinação dos campos "cempresa", "cbalcao", "cnumecta", "zdeposit" iremos recuperar o MAX(contraparte_i): ‣ Este campo MAX(contraparte_i) será traduzido através de uma ligação com o campo "dd_code" para obter o campo: dd_value
W18: dd_value
U19: cd_captools.ct081_finrep | V19: ‣ ref_date = data do report | W19: cempresa
W20: cbalcao
W21: cnumecta
W22: zdeposit
W23: contraparte_i
A24: V_5 | B24: Risk parameters | C24: Total Risk Exposure Amount | D24: Numeric (euro) | E24: The total risk exposure amount of the instrument, calculated according to Articles 92(3) and 92(4) of Regulation (EU) No 575/2013 (CRR), where applicable. | F24: O montante total das posições em risco do instrumento, calculado de acordo com o artigo 92(3) e 92(4) do Regulamento (UE) No 575/2013 (CRR), quando aplicável. | H24: INSTRUMENT-RWA | I24: RWA | J24: RWA according to Regulation (EU) No 575/2013. | M24: NÃO | N24: total_risk_exposure_amount | O24: LT002_INSTRUMENT.RWA | P24: Concluído | Q24: ='PDS - Desenvolvimento'!$K$36 -> Concluído | R24: 45608 | S24: Concluído | U24: cd_captools.ct013_rwa_princ | V24: ‣ ref_date = data do report ‣ flag_cons_cap = 1 ‣ exercicio = 'REAL' | W24: s1emp | X24: ‣ Para cada Instrument Identifier é somada a: ‣ Média do campo "rwa_final" para cada par de campos "s1emp", "contra1" | Y24: A agrupação é feita segundo o campo "Instrument Identifier" deste mesmo documento | Z24: Dependendo do instrument id indicado, este campo deverá ser a soma do rwa_final
W25: contra1
W26: rwa_final
A27: V_6 | B27: Risk parameters | C27: CRR Loss given default | D27: Numeric. Basis points | E27: Current level of the ‘Loss given default’ of the loan, determined in accordance with Articles 161, 164, 179 and 181 of Regulation (EU) No 575/2013. | F27: Nível atual da "Loss given default" do empréstimo, determinado em conformidade com os artigos 161, 164, 179 e 181 do Regulamento (UE) No 575/2013. | H27: INSTRUMENT-LGD | I27: Regulatory LGD | J27: If differences between regulatory and internal LGD exist, use regulatory LGD (according to Regulation (EU) No 575/2013). In particular, in IRB-F use regulatory LGD values. | M27: NÃO | N27: crr_loss_given_default | O27: LT002_INSTRUMENT.LGD | P27: Concluído | Q27: ='PDS - Desenvolvimento'!$K$44 -> Concluído | R27: 45608 | S27: Concluído | U27: cd_captools.ct013_rwa_princ | V27: ‣ ref_date = data do report ‣ flag_cons_cap = 1 ‣ exercicio = 'REAL' | W27: s1emp | X27: ‣ Para cada Instrument Identifier é calculada a: ‣ Média ponderada do campo "lgdfinal" em relação à: ‣ Média do campo "ead_final_bruta" para cada par dos campos "s1emp", "contra1" | Y27: A agrupação é feita segundo o campo "Instrument Identifier" deste mesmo documento | Z27: Dependendo do instrument id indicado, este campo deverá ser a média ponderada de lgd_final por ead_final_bruta
W28: contra1
W29: ead_final_bruta
U30: cd_captools.ct014_rwa_irb | V30: ‣ ref_date = data do report | W30: lgdfinal
A31: V_7 | B31: Risk parameters | C31: IFRS 9 Loss given default | D31: Numeric. Basis points | E31: Current level of the ‘Loss given default’ of the loan determined for accounting purposes. | F31: Nível atual da "Loss given default" do empréstimo determinado para efeitos contabilísticos. | H31: INSTRUMENT-IFRS9_LGD | I31: IFRS 9 accounting LGD | J31: IFRS 9 accounting Loss Given Default as at reference date for defaulted and non-defaulted exposures. In case the bank models time-depended LGD variable for non-defaulted exposures then 12-month LGD as at reference date regardless the classification as Stage 1 or 2 | M31: NÃO | N31: ifrs9_loss_given_default | O31: LT002_INSTRUMENT.IFRS9_LGD | P31: Concluído | Q31: ='PDS - Desenvolvimento'!$K$43 -> Concluído | R31: 45608 | S31: Concluído | U31: cd_captools.ifrs9_out_expected_loss_8_7 | V31: ‣ Apenas são trazidos os "contract_id"s que têm "exec_id_part" correspondente na tabela cd_captools.imcatf046_flag_fecho à data ("cmes") do report | W31: contract_id | X31: ‣ Para cada Instrument Identifier é calculada a: ‣ Média ponderada do campo "lgd_ifrs9" em relação à: ‣ Média do campo "ead" para cada "contract_id" | Y31: A agrupação é feita segundo o campo "Instrument Identifier" deste mesmo documento | Z31: Tal como nos anteriores explorar porque é feita a média do ead
W32: lgd_ifrs9
W33: ead
A34: V_35 | B34: Instruments characteristics | C34: Type of instrument | D34: String | E34: Classification of the instrument according to the type of contractual terms agreed between the parties. Opções: ‣ Overdraft ‣ Credit card debt ‣ Revolving credit other than overdrafts and credit card debt ‣ Credit lines other than revolving credit ‣ Financial lease ‣ Loan ‣ Other | F34: Classificação do instrumento de acordo com o tipo de termos contratuais acordados entre as partes. Opções: ‣ Overdraft ‣ Credit card debt ‣ Revolving credit other than overdrafts and credit card debt ‣ Credit lines other than revolving credit ‣ Financial lease ‣ Loan ‣ Other | H34: INSTRUMENT-TYP_INSTRMNT | I34: Type of instrument | J34: Classification of the instrument according to the type of contractual terms agreed between the parties. | M34: NÃO | N34: type_instrument | O34: LT002_INSTRUMENT.TYP_INSTRMNT ‣ Necessário criar novas parametrizaçôes nas tabelas lt829_regras_conversao e lt830_conversoes, podendo as mesmas ser consultadas neste documento nas sheets: ‣ LT829 - filtrando por campo_conceito = 'TYP_INSTRMNT' e regra_conversao = '1'; ‣ LT830 - filtrando por segmento = 'Exposures to natural persons' e campo_conceito = 'TYP_INSTRMNT'. | P34: Concluído | Q34: ='PDS - Desenvolvimento'!$K$22 -> Concluído | R34: 45665 | S34: Concluído | U34: Tabela de parametrização: codemapping | V34: ‣ dd_field_id = "35" | W34: dd_code | X34: ‣ Tradução do campo "typ_instrmnt" através de uma ligação com o campo "dd_code" para obter o campo: dd_value
W35: dd_value
U36: cd_loan_tapes_bce.lt002_instrument | V36: ‣ ref_date = data do report | W36: typ_instrmnt
A37: V_142 | B37: Instruments characteristics | C37: Amortization type | D37: String | E37: Type of amortisation of the instrument including principal and interest at the reporting reference date. Opções: ‣ French ‣ German ‣ Fixed amortisation schedule ‣ Bullet ‣ Other | F37: Tipo de amortização do instrumento incluindo capital e juros à data de referência do relato. Opções: ‣ French ‣ German ‣ Fixed amortisation schedule ‣ Bullet ‣ Other | H37: INSTRUMENT-TYP_AMRTSTN | I37: Type of amortisation | J37: Type of amortisation of the instrument including principal and interest. | M37: NÃO | N37: amortization_type | O37: LT002_INSTRUMENT.TYP_AMRTSTN ‣ Necessário criar novas parametrizaçôes nas tabelas lt829_regras_conversao e lt830_conversoes, podendo as mesmas ser consultadas neste documento nas sheets: ‣ LT829 - filtrando por campo_conceito = 'TYP_AMRTSTN' e regra_conversao = '1'; ‣ LT830 - filtrando por segmento = 'Exposures to natural persons' e campo_conceito = 'TYP_AMRTSTN'. | P37: Concluído | Q37: ='PDS - Desenvolvimento'!$K$21 -> Concluído | S37: Concluído | U37: Tabela de parametrização: codemapping | V37: ‣ dd_field_id = "3" | W37: dd_code | X37: ‣ Tradução do campo "typ_amrtstn" através de uma ligação com o campo "dd_code" para obter o campo: dd_value
W38: dd_value
U39: cd_loan_tapes_bce.lt002_instrument | V39: ‣ ref_date = data do report | W39: typ_amrtstn
A40: V_143 | B40: Instruments characteristics | C40: Currency | D40: String | E40: Currency denomination of instruments, in accordance with the ISO 4217 standard. | F40: Denominação monetária dos instrumentos, de acordo com a norma ISO 4217. | H40: INSTRUMENT-CRRNCY_DNMNTN | I40: Currency denomination | J40: Currency denomination of instruments, in accordance with the ISO 4217 standard. | M40: NÃO | N40: currency | O40: LT002_INSTRUMENT.CRRNCY_DNMNTN | P40: Concluído | Q40: ='PDS - Desenvolvimento'!$K$5 -> Concluído | R40: 45608 | S40: Concluído | U40: cd_alm.al029_cnt_core_m | V40: ‣ ref_date = data do report | W40: cmoeda_act | X40: ‣ Se o contrato for ativo: cmoeda_act ‣ Se o contrato for passivo: cmoeda_pas | Z40: Não trazer componente passiva, e o universo pode alterar para as fr
W41: cmoeda_pas
A42: V_144 | B42: Instruments characteristics | C42: Inception date | D42: DD/MM/AA | E42: The date on which the contractual relationship originated, i.e. the date on which the contract agreement becomes binding for all parties. | F42: A data em que a relação contratual se originou, ou seja, a data em que o acordo contratual se torna vinculativo para todas as partes. | H42: INSTRUMENT-DT_INCPTN | I42: Date of inception | J42: The date on which the contractual relationship originated, i.e. the date on which the contract agreement becomes binding for all parties | M42: NÃO | N42: inception_date | O42: LT002_INSTRUMENT.DT_INCPTN | P42: Concluído | Q42: ='PDS - Desenvolvimento'!$K$6 -> Concluído | R42: 45608 | S42: Concluído | U42: cd_alm.al029_cnt_core_m | V42: ‣ ref_date = data do report | W42: dinicio | X42: ‣ Direto | Z42: Alterando a granularidade também deveriamos trazer esta info de outro lado
A43: V_145 | B43: Interest rate information | C43: End date of interest-only period | D43: DD/MM/AA | E43: The date on which the interest-only period ends. | F43: A data em que termina o período somente de juros. | H43: INSTRUMENT-DT_END_INTRST_ONLY | I43: End date of the interest-only period | J43: The date on which the interest-only period ends. Interest-only instruments are those for which, for a contractually set period, only the interest on the principal balance is paid, with the principal balance remaining unchanged. The scope of the field refers to any interest only period, either due to renegotiations or interest only agreements at loan inception. | M43: NÃO | N43: end_date_interest_only_period | O43: LT002_INSTRUMENT.DT_END_INTRST_ONLY | P43: Concluído | Q43: ='PDS - Desenvolvimento'!$K$13 -> Concluído | R43: 45608 | S43: Concluído | U43: cd_alm.al029_cnt_core_m | V43: ‣ ref_date = data do report | W43: dfim_care | X43: ‣ Direto
A44: V_146 | B44: Interest rate information | C44: Interest rate cap | D44: Numeric. Reported in basis points with the same convention as for the attribute “interest rate spread/margin”. | E44: The maximum interest rate per annum that can be charged on the outstanding nominal amount (or parts thereof). | F44: A taxa de juros máxima anual que pode ser cobrada sobre o valor nominal em dívida (ou partes dele). | H44: - | I44: - | J44: - | M44: SIM | N44: interest_rate_cap | O44: Mapeamento LT: Regra (com base na tabela ct610_titulos): • Se tx_max <> NULL então interest_rate_cap= tx_max • Se tx_max = NULL e indx_tx_max <> NULL então interest_rate_cap= indx_tx_max + sprd_tx_var Tratamentos ao campo sprd_tx_var: o Se sprd_tx_var = NULL então sprd_tx_var = 0 o Se sprd_tx_var <> NULL e tiver apenas um valor então sprd_tx_var = esse valor o Se sprd_tx_var <> NULL e tiver mais do que um valor (vetor) é necessário "desvetorizar". Para tal, será necessário verificar o período em que se está (dt_fim_sprd_tx_var). Se não se estiver em nenhum período, sprd_tx_var= 0 Exemplo: Contrato 31.6416.00005800007.PTMCABOE0009000 tem sprd_tx_var= '1.75; 2.5' e tem dt_fim_sprd_tx_var='31-12-2008;31-12-9999'. Considerando que a data de referência é 2024-12-31 então estamos no 2º valor/período da dt_fim_sprd_tx_var (31-12-9999) e portanto sprd_tx_var=2.5 Reportar interest_rate_cap=11111111111.000000 (valor default Not Applicable para numérico) nas seguintes situações: • Se tx_max/indx_tx_max = NULL • Para todos os instrumentos que não estejam na ct610_titulos • Para Derivados, ou seja, quando flag_inst_deriv = 1 Notas: - Não é expectável saírem valores MISS neste campo; - No caso do segmento Natural Persons do Valuation, é expectável reportar 111111111111111111111.000000 (Not Applicable). Comentários IT: ‣ Reunião 2025-06-26: Definiu-se que este campo é Not Applicable para Derivados ‣ Email recebido de Luís Capitão-Mor 17/04/2025 12:33 com confirmação da regra a aplicar ‣ Segundo Luís Capitão-Mor, este novo campo deveria ser alimentado por um novo campo a adicionar à al029_cnt_core_m ‣ Email recebido de Luís Capitão-Mor (03/10/2024 15:21) sobre a implementação deste campo na al029/al001: "Boa tarde, não vejo inconveniente. Isto implica do lado dele tocar não somente al029, mas também input manual al600, e também al001 (diária). Adicionalmente, no modulo recente que automatizou inputs manuais. E naturalmente, não estás a referir o enriquecimento das ingestas / fontes (nomeadamente do que vem do Sigom, ct610 (e resto ?)), e logo o apontar dos novos campos na al029/al001 para essas fontes. Atenção que o nome do campo deve ser perceptivel/entendível de forma intuitiva; deve manter a logica com sufixo _act ou _pas; deve estar na ordem correta na tabela (isto é depois dos campos de indexante e spread tx variabel), e naturalmente na parte de taxa de juro variavel. Antes de passar a PRO, isto implica ajustes no fiche" ‣ Reunião Luís Capitão-Mor/Alexandre Feliciano/Pedro Mendes 15/10/2024: Luís Capitão-Mor definiu que terão de ser adicionados 8 campos à al029: cap do indexante passivo, cap do all-in passivo (indexante+spread), floor do indexante passivo, floor do all-in passivo (indexante+spread), cap do indexante ativo, cap do all-in ativo(indexante+spread), floor do indexante ativo, floor do all-in ativo(indexante+spread) | P44: Concluído | Q44: ='PDS - Desenvolvimento'!$K$82 -> Concluído | S44: Alterações ao Motor LT - Novos Campos: Definição Incompleta / Dados existem no Datalake -> Dev Datalake (tabelas intermédias) | U44: Não foi implementado | V44: Não foi implementado | W44: Não foi implementado | X44: Não foi implementado | Y44: Não foi implementado | Z44: Ver como são obtidos no ALM.
A45: V_147 | B45: Interest rate information | C45: Interest rate floor | D45: Numeric. Reported in basis points with the same convention as for the attribute “interest rate spread/margin”. | E45: The minimum interest rate per annum that can be charged on the outstanding nominal amount (or parts thereof). | F45: A taxa de juros mínima anual que pode ser cobrada sobre o valor nominal em dívida (ou partes dele). | H45: - | I45: - | J45: - | M45: SIM | N45: interest_rate_floor | O45: Mapeamento LT: ‣ Necessário criar nova parametrização na tabela lt831_param_conceitos, podendo a mesma ser consultada neste documento na sheet 'LT831' filtrando por tabela_conceito = 'LT002_INSTRUMENT' e campo_conceito = 'INTEREST_RATE_FLOOR'. Esta parametrização será construída com base nos seguintes campos: - cproduto da al029_cnt_core_m; - intrst_indxng da lt002_instrument; - typ_intrst_rt da lt002_instrument. ‣ Reportar 11111111111.000000 (valor default Not Applicable para numérico) para Derivados, ou seja, quando flag_inst_deriv = 1 ‣ Step extra a aplicar depois da parametrização na lt831_param_conceitos: - Se valor_destino = 'CALCULA_SPREAD' então ir buscar campo sprd da lt002_instrument - Se valor_destino <> 'CALCULA_SPREAD' reportar valor_destino Nota: Este step extra é necessário dado que a lt831_param_conceitos não está preparada atualmente para reportar no valor_destino o campo sprd da lt002_instrument Comentários IT: ‣ Alexandre Feliciano partilhou a parametrização da LT831 a aplicar a este campo via Teams a 2025-06-17 ‣ Reunião 2025-05-23 e 2025-06-26 Luís Capitão-Mor/Luísa Sousa/Pedro Mendes: - Segundo Luís Capitão-Mor: 1) Este campo deverá ser preenchido com Not Applicable para Derivados (ou seja, se é um numérico reportar 11111111111.000000). Este campo para Derivados teria que se abrir em 2 campos (leg1 e leg2). 2) Este campo deverá ser preenchido com Not Applicable se não for taxa variável. ‣ Reunião 2025-05-20 Luís Capitão-Mor/Luísa Sousa/Pedro Mendes: Segundo Luís Capitão-Mor a lt831 deveria permitir 3 opções: - Discreto (é o que temos atualmente na maioria dos casos, por exemplo, atributo_origem= X valor_origem igual= Y então no valor destino= Z) - Contínuo -Misto Contudo, atualmente a lt831 só possibilita a opção Discreto dado que as restantes não foram desenvolvidas. ‣ Reunião 2025-05-19 Alexandre Feliciano/Luís Capitão-Mor/Luísa Sousa: Alexandre Feliciano apresentou a proposta de campos (e valores) que permitiriam via lt831 mapear este campo em3 opções: Spread; 0, Vazio. Adicionalmente, Luís Capitão-Mor solicitou que se questione Rafael Pessoa sobre o campo "produto" que consta na tabela fr802_pl_contas, concretamente, se esse campo é construído só com base no critério produto/subproduto ou têm mais algum critério? ‣ Segundo Luís Capitão-Mor, este novo campo deverá ser alimentado por um novo campo a adicionar à al029_cnt_core_m ‣ Email recebido de Luís Capitão-Mor (03/10/2024 15:21) sobre a implementação deste campo na al029/al001: "Boa tarde, não vejo inconveniente. Isto implica do lado dele tocar não somente al029, mas também input manual al600, e também al001 (diária). Adicionalmente, no modulo recente que automatizou inputs manuais. E naturalmente, não estás a referir o enriquecimento das ingestas / fontes (nomeadamente do que vem do Sigom, ct610 (e resto ?)), e logo o apontar dos novos campos na al029/al001 para essas fontes. Atenção que o nome do campo deve ser perceptivel/entendível de forma intuitiva; deve manter a logica com sufixo _act ou _pas; deve estar na ordem correta na tabela (isto é depois dos campos de indexante e spread tx variabel), e naturalmente na parte de taxa de juro variavel. Antes de passar a PRO, isto implica ajustes no fiche" ‣ Reunião Luís Capitão-Mor/Alexandre Feliciano/Pedro Mendes 15/10/2024: Luís Capitão-Mor definiu que terão de ser adicionados 8 campos à al029: cap do indexante passivo, cap do all-in passivo (indexante+spread), floor do indexante passivo, floor do all-in passivo (indexante+spread), cap do indexante ativo, cap do all-in ativo(indexante+spread), floor do indexante ativo, floor do all-in ativo(indexante+spread) | P45: Concluído | Q45: ='PDS - Desenvolvimento'!$K$83 -> Concluído | S45: Alterações ao Motor LT - Novos Campos: Definição Incompleta / Dados existem no Datalake -> Dev Datalake (tabelas intermédias) | U45: Não foi implementado | V45: Não foi implementado | W45: Não foi implementado | X45: Não foi implementado | Y45: Não foi implementado
A46: V_148 | B46: Interest rate information | C46: Interest rate reset frequency | D46: String | E46: Frequency at which the interest rate is reset after the initial fixed-rate period, if any. Opções: ‣ Overnight ‣ Monthly/quarterly/semiannual/annual ‣ At creditor discretion ‣ Other frequency | F46: Frequência com que a taxa de juro é reposta após o período inicial de taxa fixa, se existir. Opções: ‣ Overnight ‣ Monthly/quarterly/semiannual/ annual ‣ At creditor discretion ‣ Other frequency | H46: INSTRUMENT-INTRST_RT_RST_FRQNCY | I46: Interest rate reset frequency | J46: Frequency at which the interest rate is reset after the initial fixed-rate period, if any. | M46: NÃO | N46: interest_rate_reset_freq | O46: LT002_INSTRUMENT.INTRST_RT_RST_FRQNCY ‣ Necessário criar novas parametrizaçôes nas tabelas lt829_regras_conversao e lt830_conversoes, podendo as mesmas ser consultadas neste documento nas sheets: ‣ LT829 - filtrando por campo_conceito = 'INTRST_RT_RST_FRQNCY' e regra_conversao = '1'; ‣ LT830 - filtrando por segmento = 'Exposures to natural persons' e campo_conceito = 'INTRST_RT_RST_FRQNCY'. | P46: Concluído | Q46: ='PDS - Desenvolvimento'!$K$46 -> Concluído | S46: Concluído | U46: cd_alm.al029_cnt_core_m | V46: ‣ ref_date = data do report | W46: cod_freq_taxa_act | X46: ‣ Inicialmente é obtida a varivel intermedia "cod_freq_taxa": ‣ Se o contrato for ativo: cod_freq_taxa_act ‣ Se o contrato for passivo: cod_freq_taxa_pas ‣ De seguida é obtido este campo aplicando as seguintes regras: ‣ Se cod_freq_taxa for "0": "OVERNIGHT" ‣ Se cod_freq_taxa for "2" ou "M" e se as 8 posições após o primeiro caracter retornarem "1": "MONTHLY" ‣ Se cod_freq_taxa for "2" ou "M" e se as 8 posições após o primeiro caracter retornarem "3": "QUARTERLY" ‣ Se (cod_freq_taxa for "2" ou "M" e se as 8 posições após o primeiro caracter retornarem "6") ou se (cod_freq_taxa for "R" e se as 8 posições após o primeiro caracter retornarem "2") ou se (cod_freq_taxa for "E" e se as 8 posições após o primeiro caracter retornarem "1"): "SEMI-ANNUAL" ‣ Se (cod_freq_taxa for "2" ou "M" e se as 8 posições após o primeiro caracter retornarem "12") ou se (cod_freq_taxa for "R" e se as 8 posições após o primeiro caracter retornarem "4") ou se (cod_freq_taxa for "E" e se as 8 posições após o primeiro caracter retornarem "2") ou se (cod_freq_taxa for "3" ou "N" e se as 8 posições após o primeiro caracter retornarem "1"): "ANNUAL" ‣ Caso contrário: "OTHER FREQUENCY" Nota esta regra está mal definida logo pelo facto de a mesma string não poder ser igual a um caracter "2" ou "M" por exemplo e depois ter também 8 caracteres a seguir com "1". Necessário rever este campo | Z46: Alterando a granularidade também deveriamos trazer esta info de outro lado
W47: cod_freq_taxa_pas
A48: V_149 | B48: Interest rate information | C48: Interest rate spread/margin | D48: Numeric (percentage) | E48: Margin or spread to add to the reference rate that is used for the calculation of the interest rate in basis points. This applies to interest rates charged for variable interest loans. | F48: Margem ou spread a adicionar à taxa de referência utilizada para o cálculo da taxa de juro em pontos de base. Isto aplica-se às taxas de juro cobradas pelos empréstimos com juros variáveis. | H48: - | I48: - | J48: - | M48: NÃO | N48: interest_rate_spread_margin | O48: LT002_INSTRUMENT.SPRD | P48: Concluído | Q48: ='PDS - Desenvolvimento'!$K$71 -> Concluído | R48: 45608 | S48: Concluído | U48: cd_alm.al029_cnt_core_m | V48: ‣ ref_date = data do report | W48: tx_spread_act_1 | X48: ‣ Se o contrato for ativo: tx_spread_act_1 ‣ Se o contrato for passivo: tx_spread_pas_1 | Z48: Alterando a granularidade também deveriamos trazer esta info de outro lado
W49: tx_spread_pas_1
A50: V_150 | B50: Interest rate information | C50: Interest rate type | D50: String | E50: Classification of credit exposures based on the base rate for establishing the interest rate for each payment period. Opções: ‣ Fixed ‣ Variable ‣ Mixed | F50: Classificação das posições em risco de crédito com base na taxa de base para determinar a taxa de juro para cada período de pagamento. Opções: ‣ Fixed ‣ Variable ‣ Mixed | H50: INSTRUMENT-TYP_INTRST_RT | I50: Type of interest rate | J50: Classification of credit exposures based on the base rate for establishing the interest rate for each payment period. | M50: NÃO | N50: interest_rate_type | O50: ILT002_INSTRUMENT.TYP_INTRST_RT ‣ Necessário criar novas parametrizaçôes nas tabelas lt829_regras_conversao e lt830_conversoes, podendo as mesmas ser consultadas neste documento nas sheets: ‣ LT829 - filtrando por campo_conceito = 'TYP_INTRST_RT' e regra_conversao = '1'; ‣ LT830 - filtrando por segmento = 'Exposures to natural persons' e campo_conceito = 'TYP_INTRST_RT'. | P50: Concluído | Q50: ='PDS - Desenvolvimento'!$K$23 -> Concluído | S50: Concluído | U50: cd_alm.al029_cnt_core_m | V50: ‣ ref_date = data do report | W50: cod_tipo_taxa_ref_act | X50: ‣ Inicialmente é obtida a varivel intermedia "cod_tipo_taxa_ref": ‣ Se o contrato for ativo: cod_tipo_taxa_ref_act ‣ Se o contrato for passivo: cod_tipo_taxa_ref_pas ‣ De seguida é obtido este campo aplicando as seguintes regras: ‣ Se cod_tipo_taxa_ref = "V": "Variable" ‣ Se cod_tipo_taxa_ref = "F": "Fixed" ‣ Caso contrário: "Mixed" | Z50: Alterando a granularidade também deveriamos trazer esta info de outro lado
W51: cod_tipo_taxa_ref_pas
A52: V_151 | B52: Instrument characteristics | C52: Legal final maturity date | D52: DD/MM/AA | E52: The contractual maturity date of the instrument, taking into account any agreements amending initial contracts. | F52: A data de vencimento contratual do instrumento, tendo em conta quaisquer acordos que alterem contratos iniciais. | H52: INSTRUMENT-DT_LGL_FNL_MTRTY | I52: Legal final maturity date (latest repayment date) | J52: The contractual maturity date of the instrument, taking into account any agreements amending initial contracts. As for retail revolving credit facilities this attribute is to be reported "not applicable". | M52: NÃO | N52: maturity_date | O52: LT002_INSTRUMENT.DT_LGL_FNL_MTRTY | P52: Concluído | Q52: ='PDS - Desenvolvimento'!$K$31 -> Concluído | R52: 45608 | S52: Concluído | U52: cd_alm.al029_cnt_core_m | V52: ‣ ref_date = data do report | W52: dfim | X52: ‣ Direto | Z52: Alterando a granularidade também deveriamos trazer esta info de outro lado
A53: V_152 | B53: Instrument characteristics | C53: Commitment amount at inception | D53: Numeric (euro) | E53: Observed agent’s maximum exposure to credit risk on the inception date of the instrument, without taking into account any protection held or other credit enhancements. | F53: Exposição máxima do agente observado ao risco de crédito na data de início do instrumento, sem ter em conta qualquer proteção detida ou outras melhorias de crédito. | H53: INSTRUMENT-CMMTMNT_INCPTN_INSTRMNT | I53: Commitment amount at inception | J53: Observed agent’s maximum exposure to credit risk on the inception date of the instrument, without taking into account any protection held or other credit enhancements. Total commitment amount on the inception date is established during the approval process and is intended to restrict an observed agent’s amount of credit risk to a given counterparty for the relevant instrument. | M53: NÃO | N53: commitment_amount_inception | O53: LT002_INSTRUMENT.CMMTMNT_INCPTN_INSTRMNT | P53: Concluído | Q53: ='PDS - Desenvolvimento'!$K$29 -> Concluído | R53: 45608 | S53: Concluído | U53: cd_loan_tapes_bce.lt002_instrument | V53: ‣ ref_date = data do report | W53: cmmtmnt_incptn_instrmnt | X53: ‣ Direto
A54: V_153 | B54: Instrument characteristics | C54: Payment frequency | D54: String | E54: Frequency of payments due, either of principal or interest, i.e. number of months between payments at the reporting reference date. Opções: ‣ Monthly/quarterly/semiannual/annual ‣ Bullet ‣ Zero coupon ‣ Other | F54: Periodicidade dos pagamentos devidos, quer de capital quer de juros, ou seja, número de meses entre pagamentos na data de referência de relato. | H54: INSTRUMENT-PYMNT_FRQNCY | I54: Payment frequency | J54: Frequency of payments due, either of principal or interest, i.e. number of months between payments. | M54: NÃO | N54: payment_freq | O54: LT002_INSTRUMENT.PYMNT_FRQNCY ‣ Necessário criar novas parametrizaçôes nas tabelas lt829_regras_conversao e lt830_conversoes, podendo as mesmas ser consultadas neste documento nas sheets: ‣ LT829 - filtrando por campo_conceito = 'PYMNT_FRQNCY' e regra_conversao = '1'; ‣ LT830 - filtrando por segmento = 'Exposures to natural persons' e campo_conceito = 'PYMNT_FRQNCY'. | P54: Concluído | Q54: ='PDS - Desenvolvimento'!$K$35 -> Concluído | S54: Concluído | U54: cd_alm.al029_cnt_core_m | V54: ‣ ref_date = data do report | W54: tx_contrato_act | X54: ‣ Este campo está dividido em dois outros v_153_interest_payment_freq e v_153_capital_payment_freq ‣ v_153_interest_payment_freq: ‣ Inicialmente são obtidas as variváveis intermedias "tx_contrato" e "cod_freq_liq_jur": ‣ Se o contrato for ativo: tx_contrato_act; cod_freq_liq_jur_act; ‣ Se o contrato for passivo: tx_contrato_pas; cod_freq_liq_jur_pas; ‣ De seguida é obtido este campo aplicando as seguintes regras: ‣ Se tx_contrato for 0: "Zero Coupon" ‣ Se cod_freq_liq_jur for "2" ou "M" e se as 8 posições após o primeiro caracter retornarem "1": "Monthly" ‣ Se (cod_freq_liq_jur for "2" ou "M" e se as 8 posições após o primeiro caracter retornarem "3") ou se (cod_freq_liq_jur for "R" e se as 8 posições após o primeiro caracter retornarem "1"): "Quarterly" ‣ Se (cod_freq_liq_jur for "2" ou "M" e se as 8 posições após o primeiro caracter retornarem "6") ou se (cod_freq_liq_jur for "R" e se as 8 posições após o primeiro caracter retornarem "2") ou se (cod_freq_liq_jur for "E" e se as 8 posições após o primeiro caracter retornarem "1"): "Semi-annual" ‣ Se (cod_freq_liq_jur for "2" ou "M" e se as 8 posições após o primeiro caracter retornarem "12") ou se (cod_freq_liq_jur for "R" e se as 8 posições após o primeiro caracter retornarem "4") ou se (cod_freq_liq_jur for "E" e se as 8 posições após o primeiro caracter retornarem "2") ou se (cod_freq_liq_jur for "3" ou "N" e se as 8 posições após o primeiro caracter retornarem "1"): "Annual" ‣ Caso contrário: "Other frequency" ‣ v_153_capital_payment_freq: ‣ Inicialmente é obtida a varivável intermedia "cod_freq_amort_capital": ‣ Se o contrato for ativo: cod_freq_amort_capital_act; ‣ Se o contrato for passivo: cod_freq_amort_capital_pas; ‣ De seguida é obtido este campo aplicando as seguintes regras: ‣ Se cod_tipo_amortizacao for "A" ou "U": "Bullet" ‣ Se cod_freq_amort_capital for "2" ou "M" e se as 8 posições após o primeiro caracter retornarem "1": "Monthly" ‣ Se (cod_freq_amort_capital for "2" ou "M" e se as 8 posições após o primeiro caracter retornarem "3") ou se (cod_freq_amort_capital for "R" e se as 8 posições após o primeiro caracter retornarem "1"): "Quarterly" ‣ Se (cod_freq_amort_capital for "2" ou "M" e se as 8 posições após o primeiro caracter retornarem "6") ou se (cod_freq_amort_capital for "R" e se as 8 posições após o primeiro caracter retornarem "2") ou se (cod_freq_amort_capital for "E" e se as 8 posições após o primeiro caracter retornarem "1"): "Semi-annual" ‣ Se (cod_freq_amort_capital for "2" ou "M" e se as 8 posições após o primeiro caracter retornarem "12") ou se (cod_freq_amort_capital for "R" e se as 8 posições após o primeiro caracter retornarem "4") ou se (cod_freq_amort_capital for "E" e se as 8 posições após o primeiro caracter retornarem "2") ou se (cod_freq_amort_capital for "3" ou "N" e se as 8 posições após o primeiro caracter retornarem "1"): "Annual" ‣ Caso contrário: "Other frequency"
W55: tx_contrato_pas
W56: cod_freq_liq_jur_act
W57: cod_freq_liq_jur_pas
W58: cod_tipo_amortizacao
W59: cod_freq_amort_capital_act
W60: cod_freq_amort_capital_pas
A61: V_154 | B61: Instrument characteristics | C61: Reference rate | D61: String | E61: Reference rate used for the calculation of the actual interest rate. The reference rate code is a combination of the reference rate value and maturity value. Opções: ‣ EURIBOR ‣ USD LIBOR ‣ GBP LIBOR ‣ EUR LIBOR ‣ JPY LIBOR ‣ CHF LIBOR ‣ MIBOR ‣ OTHER SINGLE REFERENCE RATES ‣ OTHER MULTIPLE REFERENCE RATES | F61: Taxa de referência utilizada para o cálculo da taxa de juro efetiva. O código da taxa de referência é uma combinação do valor da taxa de referência e do valor do prazo de vencimento. Opções: ‣ EURIBOR ‣ USD LIBOR ‣ GBP LIBOR ‣ EUR LIBOR ‣ JPY LIBOR ‣ CHF LIBOR ‣ MIBOR ‣ OTHER SINGLE REFERENCE RATES ‣ OTHER MULTIPLE REFERENCE RATES | H61: - | I61: - | J61: - | M61: SIM intrst_indxng | N61: reference_rate | O61: Mapeamento LT: SELECT CASE WHEN tipo_balanco = 'A' AND cod_tipo_taxa_act = 'V' THEN IF(TRIM(NVL(cod_tipo_taxa_ref_act,'')) = '', 'MISS', cod_tipo_taxa_ref_act) WHEN tipo_balanco = 'P' AND cod_tipo_taxa_pas = 'V' THEN IF(TRIM(NVL(cod_tipo_taxa_ref_pas,'')) = '', 'MISS', cod_tipo_taxa_ref_pas) ELSE 'N/A' END as INTRST_INDXNG FROM cd_alm.al029_cnt_core_m WHERE ref_date = 'Data de referência' ‣ Necessário criar novas parametrizaçôes nas tabelas lt829_regras_conversao e lt830_conversoes, podendo as mesmas ser consultadas neste documento nas sheets: ‣ LT829 - filtrando por campo_conceito = 'INTRST_INDXNG' e regra_conversao = '1'; ‣ LT830 - filtrando por segmento = 'Exposures to natural persons' e campo_conceito = 'INTRST_INDXNG'. Comentários IT: ‣Pedro Mendes enviou mapeamento com base no codelist sugerido pelo SRB (Teams 2024-10-03).Contudo, dado que a maioria das LIBOR foram descontinuadas Pedro Mendes questionou a Corporação (2024-10-03)). Se não houver um novo codelist, muitos dos valores teriam de ser mapeados em "OTHER SINGLE REFERENCE RATES". A corporação respondeu: 'Nada... no hay ninguna actualizacion. Habría que dejar el generico que indicas de other single reference rates' | P61: Concluído | Q61: ='PDS - Desenvolvimento'!$K$84 -> Concluído | S61: Alterações ao Motor LT - Novos Campos: Definição Fechada / Dados existem no Datalake | U61: cd_alm.al029_cnt_core_m | V61: ‣ ref_date = data do report | W61: cod_tipo_taxa_ref_act | X61: ‣ Se o contrato for ativo: cod_tipo_taxa_ref_act ‣ Se o contrato for passivo: cod_tipo_taxa_ref_pas
W62: cod_tipo_taxa_ref_pas
A63: V_155 | B63: Instrument characteristics | C63: Settlement date | D63: DD/MM/AA | E63: The date on which the conditions specified in the contract are or can be executed for the first time, i.e. the date on which financial instruments are initially exchanged or created. | F63: A data em que as condições especificadas no contrato são ou podem ser executadas pela primeira vez, ou seja, a data em que os instrumentos financeiros são inicialmente trocados ou criados. | H63: - | I63: - | J63: - | M63: SIM | N63: settlement_date | O63: Mapeamento LT: Deverá ser criado um novo campo SETTLEMNT_DATE na tabela LT002_INSTRUMENT que será um campo cópia do campo DT_INCPTN da mesma tabela Comentários IT: ‣ Segundo Luís Capitão-Mor, este campo é o DT_INCPTN. ‣ Deverá confirmar-se com Mónica Guerreiro se é possível um campo do Loan Tape (LT002_INSTRUMENT.DT_INCPTN) ser mapeado para 2 campos distintos no ficheiro CSV (DT_INCPTN e Settlement date). Caso não seja possível, é necessário criar um novo campo no Loan Tape: - Este tema já foi confirmado, e não é possivel, sendo necessário criar um novo campo (cópia) no Loan Tape (Validado com Mariana Romão) | P63: Concluído | Q63: ='PDS - Desenvolvimento'!$K$85 -> Concluído | S63: Concluído | U63: cd_alm.al007_prog_ppc | V63: ‣ ref_date = data do report | W63: dbreak_clause | X63: ‣ Direto
A64: V_156 | B64: Interest rate information | C64: Interest rate | D64: Numeric (percentage with two decimals, both positive and negative values). | E64: Annualised agreed rate or narrowly defined interest rate in accordance with Part 1 of Annex I to Regulation (EU) No 1072/2013 of the European Central Bank (ECB/2013/34) | F64: Taxa acordada numa base anual ou taxa de juro estritamente definida de acordo com a parte 1 do anexo I do Regulamento (UE) No 1072/2013 do Banco Central Europeu (BCE/2013/34) | H64: INSTRUMENT-ANNLSD_AGRD_RT | I64: Interest rate at the reference date | J64: Annualised agreed rate or narrowly defined interest rate at reference date in accordance with Regulation (EU) No 1072/2013 of the European Central Bank (ECB/2013/34). | M64: NÃO | N64: interest_rate | O64: LT002_INSTRUMENT.ANNLSD_AGRD_RT | P64: Concluído | Q64: ='PDS - Desenvolvimento'!$K$45 -> Concluído | R64: 45608 | S64: Concluído | U64: cd_alm.al029_cnt_core_m | V64: ‣ ref_date = data do report | W64: tx_contrato_act | X64: ‣ Se o contrato for ativo: tx_contrato_act ‣ Se o contrato for passivo: tx_contrato_pas
W65: tx_contrato_pas
A66: V_157 | B66: Interest rate information | C66: Next interest rate reset date | D66: DD/MM/AA | E66: The date when the next interest rate reset, as defined in Part 3 of Annex I to Regulation (EU) No 1071/2013 (ECB/2013/33), takes place. | F66: A data em que ocorre a próxima reposição da taxa de juro, tal como definida na parte 3 do anexo I do Regulamento (UE) No 1071/2013 (BCE/2013/33). | H66: INSTRUMENT-DT_NXT_INTRST_RT_RST | I66: Next interest rate reset date | J66: The date when the next interest rate reset, as defined in Part 3 of Annex I to Regulation (EU) No 1071/2013 (ECB/2013/33), takes place. | M66: NÃO | N66: next_interest_rate_reset_date | O66: LT002_INSTRUMENT.DT_NXT_INTRST_RT_RST | P66: Concluído | Q66: ='PDS - Desenvolvimento'!$K$32 -> Concluído | R66: 45608 | S66: Concluído | U66: cd_alm.al029_cnt_core_m | V66: ‣ ref_date = data do report | W66: dt_prox_renov_taxa_act | X66: ‣ Se o contrato for ativo: dt_prox_renov_taxa_act ‣ Se o contrato for passivo: dt_prox_renov_taxa_pas
W67: dt_prox_renov_taxa_pas
A68: V_158 | B68: Financial information | C68: Default status of the instrument | D68: String | E68: Identification of the default status of the instrument in accordance with Article 178 of Regulation (EU) No 575/2013. Opções: ‣ Not in default ‣ Default because unlikely to pay (not more than 90/180 days past due) ‣ Default because more than 90/180 days past due ‣ Default because both unlikely to pay and more than 90/180 days past due. | F68: Identificação da situação de incumprimento do instrumento em conformidade com o artigo 178 do Regulamento (UE) No 575/2013. Opções: ‣ Not in default ‣ Default because unlikely to pay (not more than 90/180 days past due) ‣ Default because more than 90/180 days past due ‣ Default because both unlikely to pay and more than 90/180 days past due. | H68: INSTRUMENT-DFLT_STTS_INSTRMNT | I68: Default status of the instrument | J68: Identification of the default status of the instrument. Categories describing the situations in which an instrument can be described as being at default in accordance with Article 178 of Regulation (EU) No 575/2013. | M68: NÃO | N68: default_status_instrument | O68: LT002_INSTRUMENT.DFLT_STTS_INSTRMNT ‣ Necessário criar novas parametrizaçôes nas tabelas lt829_regras_conversao e lt830_conversoes, podendo as mesmas ser consultadas neste documento nas sheets: ‣ LT829 - filtrando por campo_conceito = 'DFLT_STTS_INSTRMNT' e regra_conversao = '1'; ‣ LT830 - filtrando por segmento = 'Exposures to natural persons', campo_conceito = 'DFLT_STTS_INSTRMNT'. | P68: Concluído | Q68: ='PDS - Desenvolvimento'!$K$10 -> Concluído | S68: Concluído | U68: Tabela de parametrização: codemapping | V68: ‣ dd_field_id = "158" | W68: dd_code | X68: ‣ Tradução do campo "dflt_stts_instrmnt" através de uma ligação com o campo "dd_code" para obter o campo: dd_value
W69: dd_value
U70: cd_loan_tapes_bce.lt002_instrument | V70: ‣ ref_date = data do report | W70: dflt_stts_instrmnt
A71: V_159 | B71: Financial information | C71: Date of the default status of the instrument | D71: DD/MM/AA | E71: The date on which the default status, as reported in the data attribute “default status of the instrument”, is considered to have occurred. | F71: A data em que o status padrão, conforme relatado no atributo de dados "Default status of the instrument", é considerado como tendo ocorrido. | H71: INSTRUMENT-DT_DFLT_STTS_INSTRMNT | I71: Date of default status | J71: The date on which the default status, as reported in the data attribute “Default status”, is considered to have arisen. If "Not in default" since inception then this attribute is to be reported equally to the inception date. If more than one Instrument is classified as defaulted then the earliest date has to be provided. The definition of default is aligned with Art 178 of Regulation (EU) No 575/2013. | M71: NÃO | N71: date_default_status_instrument | O71: LT002_INSTRUMENT.DT_DFLT_STTS_INSTRMNT | P71: Concluído | Q71: ='PDS - Desenvolvimento'!$K$12 -> Concluído | R71: 45608 | S71: Concluído | U71: cd_loan_tapes_bce.lt002_instrument | V71: ‣ ref_date = data do report | W71: dt_dflt_stts_instrmnt | X71: ‣ Direto
A72: V_160 | B72: Financial information | C72: Transferred amount | D72: Numeric (euro) | E72: Transferred amount of the economic ownership of the financial asset to third parties. This data attribute captures the part of the outstanding nominal amount that has been transferred to another creditor. | F72: Montante transferido da propriedade económica do ativo financeiro para terceiros. Este atributo de dados capta a parte do montante nominal pendente que foi transferida para outro credor. | H72: - | I72: - | J72: - | M72: SIM | N72: transferred_amount | O72: Mapeamento LT: Este campo é Not Applicable, reportar 11111111111 | P72: Concluído | Q72: ='PDS - Desenvolvimento'!$K$86 -> Concluído | R72: 45608 | S72: Alterações ao Motor LT - Novos Campos: Definição Fechada / Dados existem no Datalake | U72: N/A | V72: N/A | W72: N/A | X72: N/A | Y72: N/A | Z72: N/A
A73: V_161 | B73: Financial information | C73: Arrears for the instrument | D73: Numeric (euro) | E73: Aggregated amount of the principal, interest and any fee payment outstanding at the reporting date, which is contractually due and has not been paid (past due). | F73: Montante agregado do capital, juros e quaisquer pagamentos de comissões pendentes à data de relato, contratualmente devidos e não pagos (vencidos). | H73: INSTRUMENT-ARRRS_INSTRMNT | I73: Total exposure in arrears | J73: Aggregated amount of the principal, interest and any fee payment outstanding at the reporting date, which is contractually due and has not been paid (past due). | M73: NÃO | N73: arrears_instrument | O73: LT002_INSTRUMENT.ARRRS_INSTRMNT | P73: Concluído | Q73: ='PDS - Desenvolvimento'!$K$39 -> Concluído | R73: 45608 | S73: Concluído | U73: cd_loan_tapes_bce.lt002_instrument | V73: ‣ ref_date = data do report | W73: arrrs_instrmnt | X73: ‣ Direto
A74: V_162 | B74: Financial information | C74: Date of past due for the instrument | D74: DD/MM/AA | E74: The date on which the instrument became past due in accordance with Part 2.96 of Annex V to the amended Implementing Regulation (EU) No 680/2014. | F74: Data de vencimento do ato, em conformidade com a parte 2.96 do anexo V do Regulamento de Execução (UE) No 680/2014 alterado. | H74: INSTRUMENT-DT_PST_D | I74: Date past due | J74: The date on which the instrument became past due in accordance with Part 2.96 of Annex V to the amended Implementing Regulation (EU) No 680/2014. This is the latest such date prior to the reporting reference date and it is to be reported if the instrument is past due on the reporting reference date. | M74: NÃO | N74: date_past_due_instrument | O74: LT002_INSTRUMENT.DT_PST_D | P74: Concluído | Q74: ='PDS - Desenvolvimento'!$K$41 -> Concluído | R74: 45608 | S74: Concluído | U74: cd_captools.ct004_univ_cto | V74: ‣ ref_date = data do report | W74: dincump | X74: ‣ Direto
A75: V_163 | B75: Financial information/Instrument characteristics | C75: Type of securitization | D75: String | E75: Captures the type of securitisation, if any, to which the instrument has been subject, in accordance with Article 242(10), (11), 243 and 244 of Regulation (EU) No 575/2013. Opções: ‣ Traditional securitisation ‣ Synthetic securitisation ‣ Not securitised | F75: Abrange o tipo de titularização, se for caso disso, a que o instrumento foi sujeito, em conformidade com o artigo 242(10), (11), 243 e 244 do Regulamento (UE) No 575/2013. Opções: ‣ Traditional securitisation ‣ Synthetic securitisation ‣ Not securitised | H75: - | I75: - | J75: - | M75: SIM | N75: type_securitization | O75: Mapeamento LT: ‣ Neste campo o objetivo é reportar o campo TITU_TIP da tabela cd_captools.ct036_securitis_cap que tem como chaves os campos S1EMP, COD_SPV. Desta forma será necessário ligar o universo de contratos INSTRMNT_ID à tabela cd_captools.ct013_rwa_princ de forma a obter a chave da tabela cd_captools.ct036_securitis_cap (S1EMP, COD_SPV), no entanto para o mesmo contrato podem existir vários pares (S1EMP, COD_SPV) distintos e como tal podemos obter mais do que um TITU_TIP para o mesmo contrato FINREP. Abaixo está a lógica que deverá ser aplicada para resolver esta âmbiguidade: 1º Passo - Obter para cada contrato (INSTRMNT_ID) o par (S1EMP, COD_SPV) mais 'significativo'. Por vezes o campo COD_SPV pode vir a vazio, estes casos devem ser ignorados de forma que quando for feito o ataque à tabela cd_captools.ct013_rwa_princ se deve aplicar o filtro ( WHERE TRIM(COD_SPV)<>'' ): 1. Seguir a lógica do campo RWA_MTHD, de momento a lógica é: se existir IRB e Standard então trazer informação relativa a IRB; 2. Se mesmo assim ainda existirem vários pares (S1EMP, COD_SPV) distintos então: recuperar o par (S1EMP, COD_SPV) com o maior valor atribuido no campo EAD_FINAL_BRUTA; 3. Ficamos então com uma tabela intermédia (TITU_TIP_INTR) com uma relação unica entre cada contrato FINREP (INSTRMNT_ID) e os campos (S1EMP, COD_SPV). 2ª Passo - Ligar os pares (S1EMP, COD_SPV) obtidos no passo anterior com a tabela cd_captools.ct036_securitis_cap de forma a obter o campo TITU_TIP: TITU_TIP_INTR LEFT JOIN (SELECT S1EMP, COD_SPV, TITU_TIP FROM cd_captools.ct036_securitis_cap ) as SECUR_CAP ON TITU_TIP_INTR.S1EMP = SECUR_CAP.S1EMP AND TITU_TIP_INTR.COD_SPV = SECUR_CAP.COD_SPV 3º Passo - Ligar o campo TITU_TIP obtido no passo anterior com a tabela cd_loan_tapes_bce.lt831_param_conceitos filtrada pelos campos tabela_conceito = 'LT002_INSTRUMENT' e campo_conceito = 'TYPE_SECURITIZATION', de forma a converter os seu valores nos códigos pedidos pelo SRB. ‣ Necessário criar nova parametrização na tabela lt831_param_conceitos, podendo a mesma ser consultada neste documento na sheet 'LT831' filtrando por tabela_conceito = 'LT002_INSTRUMENT' e campo_conceito = 'TYPE_SECURITIZATION' Comentários IT: '‣ Luís Capitão-Mor solicitou que se perguntasse a Pedro Inácio qual o campo/tabela da BDR que contém esta informação. Email Pedro Inacio (19:44 12-03-2024): "Essa informação pode ser obtida no campo “Tipo de Titulización” da tabela SPV da BDR (E0691_TITU_TIP), com o seguinte detalhe: 00 - 'No informado' 01 - 'Tradicional' 02 - 'Sintética' 99999 - 'No aplica' " '‣ Mensagem Pedro Mendes Teams (21/01/2025 10:41) sobre como parametrizar as opções '00' e '99999' do campo TITU_TIP: "Pedro Mendes: Olá Miguel Duarte Cardoso Rodrigues, parce-me bem mapear o miss e o 99999 para not securitised. Miguel Rodrigues: Devemos então mapear tanto o '00' como o '99999' com o "Not securitised", certo? Pedro Mendes: isso mesmo" ‣ Reunião 21/10/2024 com Luís Capitão-Mor/Pedro Mendes: - Luís Capitão-Mor referiu que terá de ser ingestada a tabela da BDR "JM_SPV" (será bdr_jm_spv na curated_internal_bdr); - Deverá ser criada uma nova tabela CT% (por ex: CT_SECURITIS_CAP) que terá os seguintes campos: S1EMP, COD_SPV, TITU_TIP, CKUTULMO, HTIMEST , REF_DATE. (Confirmar se não há outros da tabela JM_SPV que faça sentido trazer também) -> Esta tabela deverá ser atualizada mensalmente juntamente com as tabelas de Capital (ct013, ct014,...), geradas pelo motor RWA. Para tal é necessário atacar a ingesta bdr_jm_spv filtrando os campos "DATA_DATE_PART" = 'data mais recente à data de execução' e "E0691_FECHASTA" like '%9999' e trazer os campos mencionados acima (mesmo nome sem 'E0691_'). Quanto ao campo "REF_DATE" deve ser atribuida a data de fim de mês referente ao mês para o qual se está a obter esta informação. -> Seguindo esta lógica surgem casos em que um contrato tem dois tipos de securitização distintos, Pedro Mendes confirmou com Joana Guerreiro que estes casos são normais de acontecer (não se trata de um erro de dados). -> Para contornar o problema acima, deverá implementar-se uma lógica que trará apenas o tipo de securitização associado ao montante mais significativo. -> O campo da tabela ct013_rwa_princ que deve ser usado como fator de peso para selecionar o tipo de securitização mais significativo é o EAD_FINAL_BRUTA confirmado com Helder Gomes e João Reis (reunião Teams 04/02/2025 17:00 - 17:30) e este entendimento foi validado com Luis Capitão-Mor no email de 04/02/2025 19:51. ‣ Pedido de estimativa para ingesta da tabela JM_SPV (REQ014321568/RITM014348547); ‣ Enviar email a pedir autorização para a tabela CT_SECURITIS_CAP. ‣ Query de análise à lógica pensada para este campo: - Existem contratos fr com ambos os métodos IRB e Standard; - Existem contratos fr que dentro do método IRB têm vários cod_spvs; - Os unicos exemplos verificados em um contrato fr tem dois type_securituization diferente são para contratos apenas com método IRB que têm simultâneamente um cod_spv = 'FORTALEZA' e outro cod_spv = 'H13-201801GMMBSTNXXN0100' (aka. HIPOTOTTA 13). SELECT contract_id_fr, cod_spv_conc, method_conc, type_securitization_conc, cnt FROM ( SELECT contract_id_fr, -- s1emp, -- cod_spv, CONCAT('|',group_concat(cod_spv,'|'),'|') as cod_spv_conc, CONCAT('|',group_concat(method,'|'),'|') as method_conc, CONCAT('|',group_concat(type_securitization,'|'),'|') as type_securitization_conc, COUNT(*) as cnt FROM ( SELECT contract_id_fr, -- ct013.s1emp, ct013.cod_spv, ct013.method, CASE WHEN TRIM(ct013.s1emp) = '18' AND TRIM(ct013.cod_spv) IN ('CONSUMER1','H13-201801GMMBSTNXXN0100','H4-720007852','H5-720009022') THEN '1' WHEN TRIM(ct013.s1emp) = '18' AND TRIM(ct013.cod_spv) IN ('FORTALEZA','SYNTOTTA2','SYNTOTTA3','SYNTOTTA4','SYNTOTTA5') THEN '2' WHEN TRIM(ct013.s1emp) = '22008' AND TRIM(ct013.cod_spv) IN ('MORTAGE2-200802GMMBNFNXXN0025','MORTAGE3-200810GMMBNFNXXN0028','MORTAGE4-200902GMMBNFS0033') THEN '1' WHEN TRIM(ct013.s1emp) = '22005' AND TRIM(ct013.cod_spv) IN ('SYNTOTTA2','SYNTOTTA3','SYNTOTTA4','SYNTOTTA5') THEN '2' ELSE '' END AS type_securitization FROM ( SELECT fr004.contract_id_fr, s1emp, contra1 FROM ( SELECT DISTINCT CONCAT(cempresa,cbalcao,cnumecta,zdeposit) as contract_id_fr FROM cd_captools.fr004_cto WHERE ref_date = '2024-08-31' ) as fr004 --6211142 LEFT JOIN ( SELECT CONCAT(cempresa_fr,cbalcao_fr,cnumecta_fr,zdeposit_fr) as contract_id_fr, CONCAT(cempresa,cbalcao,cnumecta,zdeposit) as contract_id_ct FROM cd_captools.kt_chaves_finrep WHERE ref_date = '2024-08-31' ) as chaves_finrep ON chaves_finrep.contract_id_fr = fr004.contract_id_fr --6211142 LEFT JOIN ( SELECT s1emp, contra1, CONCAT(cempresa,cbalcao,cnumecta,zdeposit) as contract_id_ct FROM cd_captools.kt_chaves_bdr WHERE ref_date = '2024-08-31' ) as chaves_bdr ON chaves_bdr.contract_id_ct = chaves_finrep.contract_id_ct --2046835 WHERE chaves_bdr.contract_id_ct IS NOT NULL GROUP BY contract_id_fr, s1emp, contra1 ) as core --2046835 DIST fr --2047298 nº total LEFT JOIN ( SELECT s1emp, contra1, cod_spv, IF(segmento_corep_final LIKE 'I%', 'IRB', IF(segmento_corep_final LIKE 'S%', 'Standard', '')) as method FROM cd_captools.ct013_rwa_princ WHERE ref_date = '2024-08-31' GROUP BY segmento_corep_final, s1emp, contra1, cod_spv ) as ct013 ON core.s1emp = ct013.s1emp AND core.contra1 = ct013.contra1 WHERE ct013.cod_spv IS NOT NULL AND TRIM(ct013.cod_spv) != '' -- ATENÇÃO, não sei se deveria estar a fazer isto GROUP BY contract_id_fr, type_securitization, ct013.method, ct013.cod_spv ) as a GROUP BY contract_id_fr ) as b --WHERE method_conc = '|Standard|' --WHERE type_securitization_conc like '%1%2%' --OR type_securitization_conc like '%2%1%' ORDER BY cnt DESC | P75: Concluído | Q75: ='PDS - Desenvolvimento'!$K$87 -> Concluído | R75: 45721 | S75: Alterações ao Motor LT - Novos Campos: Definição Incompleta / Dados não existem no Datalake | U75: cd_captools.ct013_rwa_princ | V75: ‣ ref_date = data do report ‣ flag_cons_cap = 1 ‣ exercicio = 'REAL' | W75: cod_spv | X75: ‣ Se o campo "cod_spv" começar por "SYN": "SYNTHETIC SECURITISATION" ‣ Se o campo "cod_spv" não for "" (vazio): "TRADITIONAL SECURITISATION" ‣ Caso contrário (se o contrato não estiver na tabela ct013_rwa_princ): "NOT SECURITISED"
A76: V_164 | B76: Instrument charcteristics | C76: Outstanding nominal amount | D76: Numeric (euro) | E76: Principal amount outstanding at the end of the reporting reference date, including unpaid past due interest but excluding accrued interest, net of write-offs and write-downs as determined by the relevant accounting practices. | F76: Montante de capital em dívida no final da data de referência do relato, incluindo juros vencidos não pagos, mas excluindo juros vencidos, líquidos de anulações e amortizações, conforme determinado pelas práticas contabilísticas relevantes. | H76: INSTRUMENT-OTSTNDNG_NMNL_AMNT_INSTRMNT | I76: Outstanding gross nominal amount | J76: Principal amount outstanding at the end of the reporting reference date, including unpaid past due interest but excluding accrued interest. The outstanding nominal amount must be reported net of write-offs and write-downs as determined by the relevant accounting practices. | M76: NÃO | N76: outstanding_nominal_amount | O76: LT002_INSTRUMENT.OTSTNDNG_NMNL_AMNT_INSTRMNT | P76: Concluído | Q76: ='PDS - Desenvolvimento'!$K$8 -> Concluído | R76: 45608 | S76: Concluído | U76: cd_loan_tapes_bce.lt002_instrument | V76: ‣ ref_date = data do report | W76: otstndng_nmnl_amnt_instrmnt | X76: ‣ Direto
A77: V_165 | B77: Instrument charcteristics | C77: Accrued interest | D77: Numeric (euro) | E77: The amount of accrued interest on loans at the reporting reference date as defined in Regulation (EU) No 1071/2013 (ECB/2013/33). | F77: O montante dos juros vencidos sobre empréstimos na data de referência de reporte, tal como definido no Regulamento (UE) No 1071/2013 (BCE/2013/33). | H77: INSTRUMENT-ACCRD_INTRST_INSTRMNT | I77: Accrued interest balance as recognised on the balance sheet | J77: The amount of accrued interest on loans at the reporting reference date as defined in Regulation (EU) No 1071/2013 (ECB/2013/33). In accordance with the general principle of accruals accounting, interest receivable on instruments should be subject to on-balance sheet recording as it accrues (i.e. on an accruals basis) rather than when it is actually received (i.e. on a cash basis). | M77: NÃO | N77: accrued_interest | O77: LT002_INSTRUMENT.ACCRD_INTRST_INSTRMNT | P77: Concluído | Q77: ='PDS - Desenvolvimento'!$K$27 -> Concluído | R77: 45608 | S77: Concluído | X77: ‣ Forçado a NULL
A78: V_166 | B78: Financial information | C78: Off-balancesheet amount | D78: Numeric (euro) | E78: Total nominal amount of off-balance-sheet exposures. | F78: Montante nominal total das posições em risco extrapatrimoniais. | H78: INSTRUMENT-OFF_BLNC_SHT_AMNT_INSTRMNT | I78: Off-balance sheet amount | J78: Total nominal amount of off-balance-sheet exposures. This includes any commitment to lend before considering conversion factors and credit risk mitigation techniques. It is the amount that best represents the institution’s maximum exposure to credit risk without taking into account any protection held or other credit enhancements. To be reported in accordance with Annex V Regulation 680/2014. If no amount can be drawn by or disbursed to the debtor without contractual changes, the off-balance-sheet amount of the instrument is reported as ”not applicable”. | M78: NÃO | N78: off_balance_sheet_amount | O78: LT002_INSTRUMENT.OFF_BLNC_SHT_AMNT_INSTRMNT | P78: Concluído | Q78: ='PDS - Desenvolvimento'!$K$33 -> Concluído | R78: 45608 | S78: Concluído | U78: cd_alm.al030_sld_core_m | V78: ‣ ref_date = data do report | W78: mon_extrapatri | X78: ‣ Direto | Y78: Ignorei a parte em que também se traz a componente passiva
A79: V_167 | B79: Financial information | C79: Joint liabilities amount | D79: Numeric (euro) | E79: Outstanding nominal amount for which each debtor is liable in relation to a single instrument where there are two or more debtors. | F79: Montante nominal pendente pelo qual cada devedor é responsável em relação a um único instrumento, caso existam dois ou mais devedores. | H79: Not applicable: To be reported as "11111111111". This information will be availabe in "02_04_nat_instr_count" table | I79: - | J79: - | M79: SIM | N79: joint_liabilities_amount | O79: Mapeamento LT: Not Applicable: Reportar 11111111111 Comentários IT: Este campo constará no ficheiro "02_04_nat_instr_count" | P79: Concluído | Q79: ='PDS - Desenvolvimento'!$K$88 -> Concluído | R79: 45608 | S79: Alterações ao Motor LT - Novos Campos: Definição Fechada / Dados existem no Datalake | U79: cd_loan_tapes_bce.lt005_instr_ent | V79: ‣ ref_date = data do report | W79: jnt_lblty_amnt | X79: ‣ Direto
A80: V_168 | B80: Informação financeira | C80: Accounting classification of instruments | D80: String | E80: Accounting portfolio where the instrument is recorded in accordance with the accounting standard – IFRS or national GAAP – under Regulation (EU) 2015/534 (ECB/2015/13) applied by the observed agent’s legal entity. Opções: | F80: Carteira contabilística em que o instrumento é registado de acordo com a norma contabilística – IFRS ou GAAP nacionais – nos termos do Regulamento (UE) 2015/534 (BCE/2015/13) aplicada pela entidade jurídica do agente observado. Opções: | H80: INSTRUMENT-ACCNTNG_CLSSFCTN | I80: Accounting portfolio | J80: Accounting portfolio where the instrument is recorded in accordance with the accounting standard – IFRS or national GAAP – under Regulation (EU) 2015/534 (ECB/2015/13) applied by the observed agent’s legal entity. | M80: NÃO | N80: accounting_classification | O80: LT002_INSTRUMENT.ACCNTNG_CLSSFCTN ‣ Necessário criar novas parametrizaçôes nas tabelas lt829_regras_conversao e lt830_conversoes, podendo as mesmas ser consultadas neste documento nas sheets: ‣ LT829 - filtrando por campo_conceito = 'ACCNTNG_CLSSFCTN' e regra_conversao = '1'; ‣ LT830 - filtrando por segmento = 'Exposures to natural persons', campo_conceito = 'ACCNTNG_CLSSFCTN'. | P80: Concluído | Q80: ='PDS - Desenvolvimento'!$K$26 -> Concluído | R80: 45684 | S80: Concluído | U80: Tabela de parametrização: codemapping | V80: ‣ dd_field_id = "168" | W80: dd_code | X80: ‣ Inicialmente para cada combinação dos campos "cempresa", "cbalcao", "cnumecta", "zdeposit" iremos recuperar o MAX(carteira_contabilistica): ‣ Este campo MAX(carteira_contabilistica) será traduzido através de uma ligação com o campo "dd_code" para obter o campo: dd_value
W81: dd_value
U82: cd_captools.ct081_finrep | V82: ‣ ref_date = data do report | W82: cempresa
W83: cbalcao
W84: cnumecta
W85: zdeposit
W86: carteira_contabilistica
A87: V_169 | B87: Informação financeira | C87: Balance sheet recognition | D87: String | E87: Balance sheet recognition of the financial asset. This data attribute classifies the reported instruments pursuant to their balance sheet recognition in accordance with Annex III and Template 15 in Annex IV to the ITS. Opções: ‣ Entirely recognised ‣ Recognised to the extent of the institution’s continuing involvement ‣ Entirely derecognised | F87: Reconhecimento de balanço do ativo financeiro. Este atributo de dados classifica os instrumentos reportados de acordo com o seu reconhecimento no balanço de acordo com o anexo III e o modelo 15 do anexo IV da ITS. Opções: ‣ Entirely recognised ‣ Recognised to the extent of the institution’s continuing involvement ‣ Entirely derecognised | H87: - | I87: - | J87: - | M87: SIM | N87: balance_sheet_recogn | O87: Mapeamento LT: Preenchido sempre com o valor 'Entirely recognised' Comentários IT: ‣ Reunião com Luisa Quendera/Rafael Pessoa/Luís Capitão-Mor/Pedro Mendes (02/04/2024): Preenchido sempre com o valor 'Entirely recognised' ‣ Pedro Mendes a 07/10/2024 questionou Nuno Pinheiro (via Teams): Preenchido sempre com o valor 'Entirely recognised' | P87: Concluído | Q87: ='PDS - Desenvolvimento'!$K$89 -> Concluído | R87: 45608 | S87: Alterações ao Motor LT - Novos Campos: Definição Incompleta / Dados existem no Datalake | U87: Não foi implementado | V87: Não foi implementado | W87: Não foi implementado | X87: Não foi implementado | Y87: Não foi implementado
A88: V_170 | B88: Financial information | C88: Accumulated write-offs | D88: Numeric (euro) | E88: Cumulative amount of principal and past due interest of any debt instrument that the institution is no longer recognising because they are considered uncollectible, independently of the portfolio in which they were included. | F88: Montante acumulado de capital e juros vencidos de qualquer instrumento de dívida que a instituição deixou de reconhecer por serem considerados incobráveis, independentemente da carteira em que estavam incluídos. | H88: INSTRUMENT-ACCMLTD_WRTFFS_INSTRMNT | I88: Accumulated write-offs | J88: Cumulative amount of principal and past due interest of any debt instrument that the institution is no longer recognising because they are considered uncollectible, independently of the portfolio in which they were included. Write-offs could be caused both by reductions in the carrying amount of financial assets recognised directly in profit or loss and by reductions in the amounts of the allowance accounts for credit losses set off against the carrying amount of financial assets. | M88: NÃO | N88: accum_write_offs | O88: LT002_INSTRUMENT.ACCMLTD_WRTFFS_INSTRMNT | P88: Concluído | Q88: ='PDS - Desenvolvimento'!$K$38 -> Concluído | R88: 45608 | S88: Concluído | U88: Não foi implementado | V88: Não foi implementado | W88: Não foi implementado | X88: Não foi implementado | Y88: Não foi implementado
A89: V_171 | B89: Financial information | C89: Accumulated impairment amount | D89: Numeric (euro) | E89: The amount of loss allowances that are held against or are allocated to the instrument on the reporting reference date. This data attribute applies to instruments subject to impairment under the applied accounting standard. Under IFRS, the accumulated impairment relates to the following amounts: (i) loss allowance at an amount equal to 12-month expected credit losses; (ii) loss allowance at an amount equal to lifetime expected credit losses. Under GAAP, the accumulated impairment relates to the following amounts: (i) loss allowance at an amount equal to general allowances; (ii) loss allowance at an amount equal to specific allowances. | F89: A quantia de provisões para perdas detidas ou imputadas ao instrumento na data de referência do relato. Este atributo de dados aplica-se a instrumentos sujeitos a imparidade ao abrigo da norma contabilística aplicada. Em IFRS, a imparidade acumulada respeita aos seguintes montantes: (i) provisão para perdas em um valor igual às perdas de crédito esperadas para 12 meses; (ii) provisão para perdas em montante igual às perdas de crédito esperadas ao longo da vida. De acordo com os GAAP, a imparidade acumulada refere-se aos seguintes montantes: (ii.i) provisão para perdas em montante igual às provisões gerais; (ii.ii) provisão para perdas em valor igual às provisões específicas. | H89: INSTRUMENT-ACCMLTD_IMPRMNT_INSTRMNT | I89: Sum of LLPs and other allowances | J89: The amount of loss allowances that are held against or are allocated to the instrument on the reporting reference date. This data attribute applies to instruments subject to impairment under the applied accounting standard. Under IFRS, the accumulated impairment relates to the following amounts: (i) loss allowance at an amount equal to 12-month expected credit losses; (ii) loss allowance at an amount equal to lifetime expected credit losses. Under nGAAP, the accumulated impairment relates to the following amounts: (i) loss allowance at an amount equal to specific allowances; (ii) loss allowance at an amount equal to general allowances. | M89: NÃO | N89: accum_impairment_amount | O89: LT002_INSTRUMENT.ACCMLTD_IMPRMNT_INSTRMNT | P89: Concluído | Q89: ='PDS - Desenvolvimento'!$K$37 -> Concluído | R89: 45608 | S89: Concluído | U89: cd_alm.al030_sld_core_m | V89: ‣ ref_date = data do report ‣ tipo_balanco = "A" | W89: mon_imparid_patri | X89: ‣ Soma dos campos mencionados anteriormente: mon_imparid_patri + mon_imparidade_extra
W90: mon_imparidade_extra
A91: V_172 | B91: Financial information | C91: Type of impairment | D91: String | E91: This data attribute indicates the type of impairment to which the instrument is subject. Opções: ‣ Stage 1 (IFRS) ‣ Stage 2 (IFRS) ‣ Stage 3 (IFRS) ‣ General allowances (GAAP) ‣ Specific allowances (GAAP) | F91: Este atributo de dados indica o tipo de imparidade a que o instrumento é sujeito. Opções: ‣ Stage 1 (IFRS) ‣ Stage 2 (IFRS) ‣ Stage 3 (IFRS) ‣ General allowances (GAAP) ‣ Specific allowances (GAAP) | H91: INSTRUMENT-IMPRMNT_STTS | I91: Impairment status | J91: Type of impairment. | M91: NÃO | N91: type_impairment | O91: LT002_INSTRUMENT.IMPRMNT_STTS ‣ Necessário criar novas parametrizaçôes nas tabelas lt829_regras_conversao e lt830_conversoes, podendo as mesmas ser consultadas neste documento nas sheets: ‣ LT829 - filtrando por campo_conceito = 'IMPRMNT_STTS' e regra_conversao = '1'; ‣ LT830 - filtrando por segmento = 'Exposures to natural persons' e campo_conceito = 'IMPRMNT_STTS'. | P91: Concluído | Q91: ='PDS - Desenvolvimento'!$K$17 -> Concluído | S91: Concluído | U91: Tabela de parametrização: codemapping | V91: ‣ dd_field_id = "172" | W91: dd_code | X91: ‣ Tradução do campo "stage" através de uma ligação com o campo "dd_code" para obter o campo: dd_value
W92: dd_value
U93: cd_captools.ct004_univ_cto | V93: ‣ ref_date = data do report | W93: stage
A94: V_173 | B94: Financial information | C94: Impairment assessment method | D94: String | E94: The method by which the impairment is assessed, if the instrument is subject to impairment in accordance with applied accounting standards. Opções: ‣ Individually assessed ‣ Collectively assessed | F94: O método pelo qual a imparidade é avaliada, se o instrumento está sujeito a imparidade de acordo com as normas aplicadas à contabilidade. Opções: ‣ Individually assessed ‣ Collectively assessed | H94: INSTRUMENT-IMPRMNT_ASSSSMNT_MTHD | I94: Impairment assessment method | J94: The method by which the impairment is assessed, if the instrument is subject to impairment in accordance with applied accounting standards. Collective and individual methods are distinguished. | M94: NÃO | N94: impairment_assessment_method | O94: LT002_INSTRUMENT.IMPRMNT_ASSSSMNT_MTHD ‣ Necessário criar novas parametrizaçôes nas tabelas lt829_regras_conversao e lt830_conversoes, podendo as mesmas ser consultadas neste documento nas sheets: ‣ LT829 - filtrando por campo_conceito = 'IMPRMNT_ASSSSMNT_MTHD' e regra_conversao = '1'; ‣ LT830 - filtrando por segmento = 'Exposures to natural persons' e campo_conceito = 'IMPRMNT_ASSSSMNT_MTHD'. | P94: Concluído | Q94: ='PDS - Desenvolvimento'!$K$42 -> Concluído | S94: Concluído | U94: Tabela de parametrização: codemapping | V94: ‣ dd_field_id = "173" | W94: dd_code | X94: ‣ Tradução do campo "tipo_analise" através de uma ligação com o campo "dd_code" para obter o campo: dd_value
W95: dd_value
U96: cd_captools.ct004_univ_cto | V96: ‣ ref_date = data do report | W96: tipo_analise
A97: V_174 | B97: Instrument characteristics | C97: Sources of encumbrance | D97: String | E97: Type of transaction in which the exposure is encumbered in accordance with Implementing Regulation (EU) No 680/2014. An asset will be treated as encumbered if it has been pledged or if it is subject to any form of arrangement to secure, collateralise or credit enhance any instrument from which it cannot be freely withdrawn. Opções: ‣ Central bank funding ‣ Exchange traded derivatives ‣ Over-the-counter derivatives ‣ Deposits – repurchase agreements other than to central banks ‣ Deposits other than repurchase agreements ‣ Debt securities issued – covered bonds securities ‣ Debt securities issued – assetbacked securities ‣ Debt securities issued – other than covered bonds and ABSs ‣ Other sources of encumbrance ‣ No encumbrance | F97: Tipo de operação em que o risco é onerado de acordo com o Regulamento de Execução (UE) n.o 680/2014. Um ativo será tratado como onerado se tiver sido penhorado ou se estiver sujeito a qualquer forma de acordo para garantir, caucionar ou reforçar o crédito instrumento do qual não pode ser livremente retirado. Opções: ‣ Central bank funding ‣ Exchange traded derivatives ‣ Over-the-counter derivatives ‣ Deposits – repurchase agreements other than to central banks ‣ Deposits other than repurchase agreements ‣ Debt securities issued – covered bonds securities ‣ Debt securities issued – assetbacked securities ‣ Debt securities issued – other than covered bonds and ABSs ‣ Other sources of encumbrance ‣ No encumbrance | H97: - | I97: - | J97: - | M97: NÃO | N97: source_encumbrance | O97: Mapeamento LT: Neste campo é necessário obter para cada INSTRMNT_ID um vetor separado por ',' com todas as suas sources of encumbrance, caso o INSTRMNT_ID tenha mais do que uma source of encumbrance então o vetor não deve conter o código relativo a unencumbered. ‣ Metodologia de definição de universo Not Applicable: - Se o INSTRMNT_ID está na al015_act_fin é aplicável, Se não está na al015_act_fin é 'N/A' - Caso num determinado âmbito seja necessário restringir o Universo aplicável, deverá adicionar-se o filtro no campo reporta_valor da lt805_conf_exp. No âmbito 'PM' o campo reporta_valor deverá ser preenchido com flag_inst_div=1 de forma a reportar este campo apenas para os contratos de Debt Securities. No âmbito Valuation não se deverá preeencher nada no campo reporta_valor da lt805_conf_exp. ‣ Metodologia de cálculo: 1 - Cruzar LT002_INSTRUMENT com tradutor de chaves FINREP e ALM: LT002_INSTRUMENT LEFT JOIN ( SELECT CONCAT(CEMPRESA_FR, CBALCAO_FR, CNUMECTA_FR, ZDEPOSIT_FR) as INSTRMNT_ID CONCAT(CEMPRESA, CBALCAO, CNUMECTA, ZDEPOSIT) as INSTRMNT_ID_CT FROM cd_captools.KT_CHAVES_FINREP WHERE REF_DATE = {data de referência} ) as chaves_fr ON chaves_fr.INSTRMNT_ID = LT002_INSTRUMENT.INSTRMNT_ID LEFT JOIN ( SELECT CONCAT(CEMPRESA, CBALCAO, CNUMECTA, ZDEPOSIT) as INSTRMNT_ID_AL CONCAT(CEMPRESA_MASTER, CBALCAO_MASTER, CNUMECTA_MASTER, ZDEPOSIT_MASTER) as INSTRMNT_ID_CT FROM cd_captools.KT_CHAVES_ALM_M WHERE REF_DATE = {data de referência} ) as chaves_al ON chaves_al.INSTRMNT_ID_CT = chaves_fr.INSTRMNT_ID_CT 2 - Cruzar com a tabela AL015_ACT_FIN para obter os campos COD_PROP, SUB_COD_PROP e NOM_UTIL_LCR: LEFT JOIN ( SELECT CONCAT(CEMPRESA, CBALCAO, CNUMECTA, ZDEPOSIT) as INSTRMNT_ID_AL, COD_PROP, SUB_COD_PROP, NOM_UTIL_LCR FROM cd_alm.AL015_ACT_FIN WHERE REF_DATE = {data de referência} AND NOME_PERIMETRO = {perimetro} AND ENTIDADE = {entidade} ) as al015 ON al015.INSTRMNT_ID_AL = chaves_al.INSTRMNT_ID_AL Nota: Esta ligação pode resultar num desdobramento dos contratos ALM pelos vários contratos com os quais eles têm uma relação na tabela AL015_ACT_FIN. Exemplo: Para '2024-12-31' o contrato FINREP (INSTRMNT_ID = '31000313878326096000000000000000') quando ligado à tabela al015_act_fin resulta num desdobramento em 88 linhas com os seguintes valores distintos de COD_PROP: "REPOS", "EMISSAO EM MERCADO", "BEI", "EUROSSISTEMA". 3 - Cruzar os campos COD_PROP, SUB_COD_PROP e NOM_UTIL_LCR obtidos no passo 2 com a tabela de parametrização LT831_PARAM_CONCEITOS filtrada por tabela_conceito = ‘LT002_INSTRUMENT’ e campo_conceito = ‘SRCS_ENCMBRNC’ (sheet LT831). Esta parametrização foi elaborada com Cláudia Correia/Luís Capitão-Mor e a mesma é similar a aplicar o seguinte CASE: CASE WHEN nom_util_lcr IS NULL THEN ‘1’ WHEN nom_util_lcr= 0 THEN ‘1’ WHEN nom_util_lcr<> 0 AND cod_prop='EUROSISTEMA' THEN ‘5’ WHEN nom_util_lcr<> 0 AND cod_prop='IM DERIVADOS' THEN ‘7’ WHEN nom_util_lcr<> 0 AND cod_prop='VM DERIVADOS' THEN ‘7’ WHEN nom_util_lcr<> 0 AND cod_prop='VM REPOS' THEN ‘8’ WHEN nom_util_lcr<> 0 AND cod_prop='REPOS' THEN ‘8’ WHEN nom_util_lcr<> 0 AND cod_prop='EMISSAO EM MERCADO' AND sub_cod_prop='L' THEN ‘10’ WHEN nom_util_lcr<> 0 AND cod_prop='EMISSAO EM MERCADO' AND sub_cod_prop<> 'L' THEN ‘11’ WHEN nom_util_lcr<> 0 AND cod_prop='BEI' THEN ‘13’ WHEN nom_util_lcr<> 0 AND cod_prop='FGD' THEN ‘13’ WHEN nom_util_lcr<> 0 AND cod_prop='SII' THEN ‘13’ END as SRCS_ENCMBRNC_DESDOB Nota: Devido ao desdobramento que ocorre na ligação à tabela AL015_ACT_FIN este passo pode resultar em mais do que um SRCS_ENCMBRNC_DESDOB para cada contrato. Exemplo: Para '2024-12-31' o contrato FINREP (INSTRMNT_ID = '31000313878326096000000000000000') quando ligado à tabela al015_act_fin resulta num desdobramento em 88 linhas com os seguintes valores distintos de SRCS_ENCMBRNC_DESDOB: 1,8,10,13 4 - Assumindo que a tabela auxiliar criada no passo 3 se chama ENCMB, será necessário criar uma tabela auxiliar (REMOV_UNCMB) para identificar se um INSTRMNT_ID tem mais do que um código e se o código de Unemcumbred ('1') consta nesse grupo de códigos de forma a remover esse registo. Exemplo: O contrato FINREP (INSTRMNT_ID = '31000313878326096000000000000000') dado acima como exemplo que tem os seguintes valores distintos de SRCS_ENCMBRNC_DESDOB (1,8,10,13) deveria terminar com o campo SRCS_ENCMBRNC = '8,10,13' A lógica de criação da tabela auxiliar REMOV_UNCMB será: SELECT INSTRMNT_ID, COUNT(DISTINCT SRCS_ENCMBRNC_DESDOB) AS CNT, SUM( IF(SRCS_ENCMBRNC_DESDOB='1',1,0) ) AS FLAG_CONTAINS_UNCMB FROM ENCMB GROUP BY INSTRMNT_ID HAVING CNT > 1 AND FLAG_CONTAINS_UNCMB >0 5 - Utilizar a tabela REMOV_UNCMB para remover os registos da tabela ENCMB relativos a Unencumbered (1) em INSTRMNT_IDs com mais do que uma source of encumbrance: SELECT * FROM ENCMB LEFT JOIN REMOV_UNCMB ON ENCMB.INSTRMNT_ID = REMOV_UNCMB.INSTRMNT_ID WHERE REMOV_UNCMB.INSTRMNT_ID IS NULL OR ( REMOV_UNCMB.INSTRMNT_ID IS NOT NULL AND ENCMB.SRCS_ENCMBRNC_DESDOB <> '1') 6 - Antes de vetorizar a informação obtida no passo 5, dependendo do segmento que se está a correr pode haver a necessidade de aplicar uma parametrização supletiva, de forma a converter os códigos numéricos em códigos diferentes, por exemplo no report Valuation para o universo de Debt Securities é pedido um code-list numérico como o implementado na LT831, no entanto para o universo de Natural Persons é pedido um code-list de descritivos STRING. Desta forma, caso exista algum acesso nas tabelas LT829 /LT830 com campo_conceito = 'SRCS_ENCMBRNC' para o segmento em questão, deve ser aplicado neste passo, antes de agrupar a informação num vetor. 7 – Obter um vetor ordenado com todos os SRCS_ENCMBRNC_DESDOB obtidos para cada contrato FINREP, aplicando um GROUP BY INSTRMNT_ID e calculando o campo: CONCAT_WS(',' , SORT_ARRAY(COLLECT_SET(CAST(SRCS_ENCMBRNC_DESDOB AS STRING))) ) as SRCS_ENCMBRNC ‣ Necessário criar nova parametrização na tabela lt831_param_conceitos, podendo a mesma ser consultada neste documento na sheet 'LT831' filtrando por tabela_conceito = 'LT002_INSTRUMENT' e campo_conceito = 'SRCS_ENCMBRNC' ‣ Necessário criar nova parametrização nas tabelas lt829_regras_conversao e lt830_conversoes, podendo as mesmas ser consultadas neste documento nas sheets: ‣ LT829 - filtrando por campo_conceito = 'SRCS_ENCMBRNC' e regra_conversao = '1'; ‣ LT830 - filtrando por segmento = 'Exposures to natural persons' e campo_conceito = 'SRCS_ENCMBRNC'. Comentários IT: Reunião de 2025-05-13 Luís Capitão-Mor, Pedro Mendes, definiu-se uma nova Metodologia de definição de universo Not Applicable: - Se está na al015 é aplicável, Se não está na al015 é 'N/A' - Caso num determinado âmbito seja necessário restringir o Universo aplicável, deverá adicionar-se o filtro no campo reporta_valor da lt805_conf_exp. No âmbito 'PM' o campo reporta_valor deverá ser preenchido com flag_inst_div=1 de forma a reportar este campo apenas para os contratos de Debt Securities. No âmbito Valuation não se deverá preeencher nada no campo reporta_valor da lt805_conf_exp. Em Reunião de 2025-04-11 Luís Capitão-Mor, Pedro Mendes, definiu-se: 1) Criar uma nova linha de parametrização na lt801_param_segm que representará todo o Ativo aplicável a asset encumbrance. Para definir esta linha de parametrização é necessário realizar uma 1ª reunião com Luísa Quendera/Luís Capitão-Mor, e em seguida, realizar uma 2ªreunião com Rafael Pessoa/Nuno Pinheiro/ Luísa Quendera/Cláudia Correia para apresentação da parametrização definida na 1ª reunião 2) Criar o novo campo flag_srcs_encmbrnc na lt001_univ_oper para substituir a regra de Not Applicable existente atualmente 3) O campo reporta_valor da lt805_conf_exp, no âmbito 'PM' deverá ser preenchido com flag_inst_div=0 para identificar os registos Not Applicable. No âmbito Valuation não se deverá preeencher nada. ‣ No Loan Tape já existe um campo com esta informação (SRCS_ENCMBRNC), no entanto em análise com a Cláudia Correia chegou-se à conclusão de que a regra deste campo deveria ser atualizada. ‣ De forma a aclarar algumas duvidas sobre o que era pretendido neste campo, realizou-se uma sessão com a Corporação da qual saíram as seguintes notas: - Em casos em que um contrato tenha mais do que um tipo de encumbrance, a corporação reporta um vetor; - Todos os contratos que tenham pelo menos uma parte encumbered são reportados como estando totalmente encumbered. ‣ Juntamente com o Luís Capitão-Mor, Cláudia Correia e Pedro Mendes e tomando em conta o feedback da Corporação, foi definida uma nova regra de produção deste campo, que deverá substituir a atualmente implementada. : | P97: Concluído | Q97: ='PDS - Desenvolvimento'!$K$72 -> Concluído | S97: Concluído | U97: Tabela de parametrização: codemapping | V97: ‣ dd_field_id = "174" | W97: dd_code | X97: ‣ Tradução do campo "srcs_encmbrnc" através de uma ligação com o campo "dd_code" para obter o campo: dd_value
W98: dd_value
U99: cd_loan_tapes_bce.lt002_instrument | V99: ‣ ref_date = data do report | W99: srcs_encmbrnc
A100: V_175 | B100: Financial information | C100: Performing status of the instrument | D100: String | E100: The instrument is to be classified on the reporting reference date, in accordance with Implementing Regulation (EU) No 680/2014. Opções: ‣ Non-performing ‣ Performing | F100: O instrumento deve ser classificado na data de referência do relatório, em conformidade com o Regulamento de Execução (UE) n.o 680/2014. | H100: INSTRUMENT-PRFRMNG_STTS | I100: Performing status | J100: The instrument is to be classified on the reference date under one of the following categories: performing or non-performing, in accordance with Implementing Regulation (EU) No 680/2014. If the performing status is measured on entity level only all instruments are to be classified according to the status on entity level. | M100: NÃO | N100: perform_status_instrument | O100: LT002_INSTRUMENT.PRFRMNG_STTS ‣ Necessário criar novas parametrizaçôes nas tabelas lt829_regras_conversao e lt830_conversoes, podendo as mesmas ser consultadas neste documento nas sheets: ‣ LT829 - filtrando por campo_conceito = 'PRFRMNG_STTS' e regra_conversao = '1'; ‣ LT830 - filtrando por segmento = 'Exposures to natural persons' e campo_conceito = 'PRFRMNG_STTS'. | P100: Concluído | Q100: ='PDS - Desenvolvimento'!$K$20 -> Concluído | S100: Concluído | U100: ifrs9_out_staging_8_7 | V100: ‣ Apenas são trazidos os "contract_id"s que têm "exec_id_part" correspondente na tabela cd_captools.imcatf046_flag_fecho à data ("cmes") do report | W100: final_stage | X100: ‣ Se o campo "final_stage" for "3": "Non-performing" ‣ Caso contrário: "Performing"
...

Sheet NATURALP_COUNTERPARTIES
A1: Instruções SRB | H1: Mapeamento efetuado pela Corporação e respetiva Descrição Loan Tape (LT) | L1: Análise IT | T1: Implementação Deloitte (OLD)
A2: ID | B2: Categoria | C2: Coluna | D2: Tipo de dados | E2: Descrição | F2: Descrição | H2: Mapeamentos Corporação (LT) | I2: Descrição (LT) | J2: Additional Guidance (LT) | L2: Novo campo na tabela LT003? | M2: Nome do campo no ficheiro | N2: Mapeamento LT / Comentários IT | O2: Estado especificação | P2: Estado desenvolvimento | Q2: Data da última alteração do Estado desenvolvimento | R2: Tipo de Tarefa para a estimativa | T2: Fontes de Informação | U2: Filtros | V2: Campo | W2: Regras de Preenchimento | X2: Agrupações
A3: V_2 | B3: Identification information | C3: Counterparty Identifier | D3: Alphanumeric | E3: Identifier applied to uniquely identify each counterparty. | F3: Identificador aplicado para identificar exclusivamente cada contraparte. | H3: ENTITY-ENTTY_ID | I3: Entity ID | J3: An identifier applied by the reporting agent to uniquely identify each counterparty. Each counterparty has a unique and exclusive counterparty identifier. This means that this value will not change over time and can never be used as the counterparty identifier for any other counterparty. | L3: NÃO | M3: counterparty_id | N3: LT003_ENTITY.ENTTY_ID | O3: Concluído | P3: ='PDS - Desenvolvimento'!$K$113 -> Concluído | Q3: 45608 | R3: Concluído | T3: cd_alm.al029_cnt_core_m | U3: ‣ ref_date = data do report | V3: zcliente | W3: ‣ Direto
