Workbook
Name acumulad: [1]Portada!$C$22
Name ECms: [2]ECms!$C$3:$AA$1154
Name ECmsAcum: [2]ECms!$AC$3:$AZ$1154
Name EManuais: [3]EManuais!$C$3:$AA$61
Name EManuaisAcum: [3]EManuais!$AC$3:$AZ$61
Name ENeg: [2]ENeg!$C$3:$AA$777
Name ENegAcum: [2]ENeg!$AC$3:$AZ$777
Name ERnd: [3]ERnd!$C$3:$AA$622
Name ERndAcum: [3]ERnd!$AC$3:$AZ$622
Name ERsc: [3]ERsc!$C$3:$AA$31
Name ERscAcum: [3]ERsc!$AC$3:$AZ$31
Name EssLatest: "112002"
Name EssOptions: "A1100000000120000000001100020_010010"
Name EVE: [3]EVE!$C$3:$AA$7
Name MES_ACTUAL: [4]Portada!$C$22
Name OCms: [2]OCms!$C$3:$AA$1154
Name OCmsAcum: [2]OCms!$AC$3:$AZ$1154
Name OManuais: [3]OManuais!$C$3:$AA$61
Name OManuaisAcum: [3]OManuais!$AC$3:$AZ$61
Name ONeg: [2]ONeg!$C$3:$AA$777
Name ONegAcum: [2]ONeg!$AC$3:$AZ$777
Name ORnd: [3]ORnd!$C$3:$AA$622
Name ORndAcum: [3]ORnd!$AC$3:$AZ$622
Name ORsc: [3]ORsc!$C$3:$AA$31
Name ORscAcum: [3]ORsc!$AC$3:$AZ$31
Name OVE: [3]OVE!$C$3:$AA$7
Name RRPPMM_ML: [5]AVANCEPAIS!$A$15:$D$30
Name RRPPMMUS: [5]AVANCEPAIS!$C$5:$C$9
Name ver: [1]Portada!$C$22

Sheet QUERY_FOR_TRNSTRANSPOSED_0008
F1: =SUBTOTAL(9,F5:F1234) -> 4.9752306e+08 | G1: =SUBTOTAL(9,G5:G1234) -> 4.7685326e+08 | H1: =SUBTOTAL(9,H5:H1234) -> 20669750 | I1: =SUBTOTAL(9,I5:I1234) -> 20669795 | L1: =I1-H1 -> 45 | M1: =SUBTOTAL(9,M5:M1234) -> 1.5552561e+08
I2: =F1245+F1248+F1251 -> 20343268 | L2: =I1-I2 -> 326526.57
A4: METACOM | C4: COPERAC | D4: CONTA | E4: CONTA IFRS | F4: TOTAL_MIS 2024 Ajustado | G4: TOTAL_CONTABILIDADE 2024 | H4: MIS_vs_CONTABILIDADE | J4: Análise | L4: Produtos Fora da Contabilidade | M4: Valor | O4: Classificação Financeiras / Não Financeiras | P4: Classe Contas Contabilisticas | Q4: OREX | R4: GG | S4: RO | T4: Reclassificadas Margem
A5: AA1000 | B5: =VLOOKUP(A5,'[6]Fin vs NFin'!$A$4:$B$568,2,FALSE) -> !Manutenção Empresa | C5: 046 | D5: 825942 | E5: =VLOOKUP(D5,[6]Arvore!$N$8:$Q$6855,4,FALSE) -> 51950 | F5: 4418012.9 | G5: 4418052.6 | H5: -39.658411 | I5: -39.658411 | O5: =VLOOKUP(QUERY_FOR_TRNSTRANSPOSED_0008!A5,'[6]Fin vs NFin'!$A$4:$F$568,6,FALSE) -> Não Financeiras | P5: =LEFT(D5,2) -> 82
A6: AA1100 | B6: =VLOOKUP(A6,'[6]Fin vs NFin'!$A$4:$B$568,2,FALSE) -> !Manutenção Particulares | C6: 24L | D6: 825942 | E6: =VLOOKUP(D6,[6]Arvore!$N$8:$Q$6855,4,FALSE) -> 51950 | F6: 343483.76 | G6: 342992.18 | H6: 491.58 | I6: =SUM(H6:H7) -> 4.08 | O6: =VLOOKUP(QUERY_FOR_TRNSTRANSPOSED_0008!A6,'[6]Fin vs NFin'!$A$4:$F$568,6,FALSE) -> Não Financeiras | P6: =LEFT(D6,2) -> 82
A7: AA1100 | B7: =VLOOKUP(A7,'[6]Fin vs NFin'!$A$4:$B$568,2,FALSE) -> !Manutenção Particulares | C7: 41H | D7: 825942 | E7: =VLOOKUP(D7,[6]Arvore!$N$8:$Q$6855,4,FALSE) -> 51950 | F7: 175672.28 | G7: 176159.78 | H7: -487.5 | O7: =VLOOKUP(QUERY_FOR_TRNSTRANSPOSED_0008!A7,'[6]Fin vs NFin'!$A$4:$F$568,6,FALSE) -> Não Financeiras | P7: =LEFT(D7,2) -> 82
A8: AA1150 | B8: =VLOOKUP(A8,'[6]Fin vs NFin'!$A$4:$B$568,2,FALSE) -> !Manut.Client.Nat.Financ. | C8: CTM | D8: 825942 | E8: =VLOOKUP(D8,[6]Arvore!$N$8:$Q$6855,4,FALSE) -> 51950 | F8: -12680.77 | G8: -12680.77 | H8: 1.8189894e-12 | I8: 1.8189894e-12 | O8: =VLOOKUP(QUERY_FOR_TRNSTRANSPOSED_0008!A8,'[6]Fin vs NFin'!$A$4:$F$568,6,FALSE) -> Não Financeiras | P8: =LEFT(D8,2) -> 82
A9: AA1190 | B9: =VLOOKUP(A9,'[6]Fin vs NFin'!$A$4:$B$568,2,FALSE) -> !Manutenção Outras | C9: 2AE | D9: 825933 | E9: =VLOOKUP(D9,[6]Arvore!$N$8:$Q$6855,4,FALSE) -> 512010 | F9: 88299.76 | G9: 66554.64 | H9: 21745.12 | I9: -7.2759576e-12 | O9: =VLOOKUP(QUERY_FOR_TRNSTRANSPOSED_0008!A9,'[6]Fin vs NFin'!$A$4:$F$568,6,FALSE) -> Não Financeiras | P9: =LEFT(D9,2) -> 82
A10: AA1190 | B10: =VLOOKUP(A10,'[6]Fin vs NFin'!$A$4:$B$568,2,FALSE) -> !Manutenção Outras | C10: 2AG | D10: 825933 | E10: =VLOOKUP(D10,[6]Arvore!$N$8:$Q$6855,4,FALSE) -> 512010 | F10: 16984 | G10: 38729.12 | H10: -21745.12 | O10: =VLOOKUP(QUERY_FOR_TRNSTRANSPOSED_0008!A10,'[6]Fin vs NFin'!$A$4:$F$568,6,FALSE) -> Não Financeiras | P10: =LEFT(D10,2) -> 82
A11: AA1190 | B11: =VLOOKUP(A11,'[6]Fin vs NFin'!$A$4:$B$568,2,FALSE) -> !Manutenção Outras | C11: 8NY | D11: 825942 | E11: =VLOOKUP(D11,[6]Arvore!$N$8:$Q$6855,4,FALSE) -> 51950 | F11: -24 | G11: -24 | H11: 0 | O11: =VLOOKUP(QUERY_FOR_TRNSTRANSPOSED_0008!A11,'[6]Fin vs NFin'!$A$4:$F$568,6,FALSE) -> Não Financeiras | P11: =LEFT(D11,2) -> 82
A12: AA1190 | B12: =VLOOKUP(A12,'[6]Fin vs NFin'!$A$4:$B$568,2,FALSE) -> !Manutenção Outras | C12: VFF | D12: 825942 | E12: =VLOOKUP(D12,[6]Arvore!$N$8:$Q$6855,4,FALSE) -> 51950 | F12: -2.2 | G12: -2.2 | H12: 0 | O12: =VLOOKUP(QUERY_FOR_TRNSTRANSPOSED_0008!A12,'[6]Fin vs NFin'!$A$4:$F$568,6,FALSE) -> Não Financeiras | P12: =LEFT(D12,2) -> 82
A13: AA1200 | B13: =VLOOKUP(A13,'[6]Fin vs NFin'!$A$4:$B$568,2,FALSE) -> !Extractos | C13: !NY | D13: 89223 | E13: =VLOOKUP(D13,[6]Arvore!$N$8:$Q$6855,4,FALSE) -> 55083 | F13: 19485.59 | G13: 19560.91 | H13: -75.32 | I13: -2.1884716e-12 | O13: =VLOOKUP(QUERY_FOR_TRNSTRANSPOSED_0008!A13,'[6]Fin vs NFin'!$A$4:$F$568,6,FALSE) -> Não Financeiras | P13: =LEFT(D13,2) -> 89 | Q13: =VLOOKUP(D13,[6]Mapeamento!$A$38:$C$497,3,FALSE) -> OREX
A14: AA1200 | B14: =VLOOKUP(A14,'[6]Fin vs NFin'!$A$4:$B$568,2,FALSE) -> !Extractos | C14: 3EX | D14: 89223 | E14: =VLOOKUP(D14,[6]Arvore!$N$8:$Q$6855,4,FALSE) -> 55083 | F14: 68.08 | G14: 40.92 | H14: 27.16 | O14: =VLOOKUP(QUERY_FOR_TRNSTRANSPOSED_0008!A14,'[6]Fin vs NFin'!$A$4:$F$568,6,FALSE) -> Não Financeiras | P14: =LEFT(D14,2) -> 89 | Q14: =VLOOKUP(D14,[6]Mapeamento!$A$38:$C$497,3,FALSE) -> OREX
A15: AA1200 | B15: =VLOOKUP(A15,'[6]Fin vs NFin'!$A$4:$B$568,2,FALSE) -> !Extractos | C15: 8NW | D15: 89223 | E15: =VLOOKUP(D15,[6]Arvore!$N$8:$Q$6855,4,FALSE) -> 55083 | F15: -11.16 | G15: -111.6 | H15: 100.44 | O15: =VLOOKUP(QUERY_FOR_TRNSTRANSPOSED_0008!A15,'[6]Fin vs NFin'!$A$4:$F$568,6,FALSE) -> Não Financeiras | P15: =LEFT(D15,2) -> 89 | Q15: =VLOOKUP(D15,[6]Mapeamento!$A$38:$C$497,3,FALSE) -> OREX
A16: AA1200 | B16: =VLOOKUP(A16,'[6]Fin vs NFin'!$A$4:$B$568,2,FALSE) -> !Extractos | C16: 8P2 | D16: 89223 | E16: =VLOOKUP(D16,[6]Arvore!$N$8:$Q$6855,4,FALSE) -> 55083 | F16: 109.6 | G16: 109.6 | H16: 0 | O16: =VLOOKUP(QUERY_FOR_TRNSTRANSPOSED_0008!A16,'[6]Fin vs NFin'!$A$4:$F$568,6,FALSE) -> Não Financeiras | P16: =LEFT(D16,2) -> 89 | Q16: =VLOOKUP(D16,[6]Mapeamento!$A$38:$C$497,3,FALSE) -> OREX
A17: AA1200 | B17: =VLOOKUP(A17,'[6]Fin vs NFin'!$A$4:$B$568,2,FALSE) -> !Extractos | C17: EX1 | D17: 89223 | E17: =VLOOKUP(D17,[6]Arvore!$N$8:$Q$6855,4,FALSE) -> 55083 | F17: 23301.72 | G17: 23354 | H17: -52.28 | O17: =VLOOKUP(QUERY_FOR_TRNSTRANSPOSED_0008!A17,'[6]Fin vs NFin'!$A$4:$F$568,6,FALSE) -> Não Financeiras | P17: =LEFT(D17,2) -> 89 | Q17: =VLOOKUP(D17,[6]Mapeamento!$A$38:$C$497,3,FALSE) -> OREX
A18: AA1300 | B18: =VLOOKUP(A18,'[6]Fin vs NFin'!$A$4:$B$568,2,FALSE) -> !Levantamento Balcão | C18: !OX | D18: 825979 | E18: =VLOOKUP(D18,[6]Arvore!$N$8:$Q$6855,4,FALSE) -> 5194 | F18: 754692 | G18: 760932 | H18: -6240 | I18: 0 | O18: =VLOOKUP(QUERY_FOR_TRNSTRANSPOSED_0008!A18,'[6]Fin vs NFin'!$A$4:$F$568,6,FALSE) -> Não Financeiras | P18: =LEFT(D18,2) -> 82
A19: AA1300 | B19: =VLOOKUP(A19,'[6]Fin vs NFin'!$A$4:$B$568,2,FALSE) -> !Levantamento Balcão | C19: 8NP | D19: 825979 | E19: =VLOOKUP(D19,[6]Arvore!$N$8:$Q$6855,4,FALSE) -> 5194 | F19: -36 | G19: -318 | H19: 282 | O19: =VLOOKUP(QUERY_FOR_TRNSTRANSPOSED_0008!A19,'[6]Fin vs NFin'!$A$4:$F$568,6,FALSE) -> Não Financeiras | P19: =LEFT(D19,2) -> 82
A20: AA1300 | B20: =VLOOKUP(A20,'[6]Fin vs NFin'!$A$4:$B$568,2,FALSE) -> !Levantamento Balcão | C20: AVB | D20: 825979 | E20: =VLOOKUP(D20,[6]Arvore!$N$8:$Q$6855,4,FALSE) -> 5194 | F20: -783.3 | G20: -6741.3 | H20: 5958 | O20: =VLOOKUP(QUERY_FOR_TRNSTRANSPOSED_0008!A20,'[6]Fin vs NFin'!$A$4:$F$568,6,FALSE) -> Não Financeiras | P20: =LEFT(D20,2) -> 82
A21: AA1310 | B21: =VLOOKUP(A21,'[6]Fin vs NFin'!$A$4:$B$568,2,FALSE) -> !Depósitos ao Balcão | C21: 3MM | D21: 825949 | E21: =VLOOKUP(D21,[6]Arvore!$N$8:$Q$6855,4,FALSE) -> 51959 | F21: 54189.8 | G21: 13584.66 | H21: 40605.14 | I21: -4.5474735e-13 | O21: =VLOOKUP(QUERY_FOR_TRNSTRANSPOSED_0008!A21,'[6]Fin vs NFin'!$A$4:$F$568,6,FALSE) -> Não Financeiras | P21: =LEFT(D21,2) -> 82
A22: AA1310 | B22: =VLOOKUP(A22,'[6]Fin vs NFin'!$A$4:$B$568,2,FALSE) -> !Depósitos ao Balcão | C22: 3MN | D22: 825949 | E22: =VLOOKUP(D22,[6]Arvore!$N$8:$Q$6855,4,FALSE) -> 51959 | F22: 20294.25 | G22: 60052.25 | H22: -39758 | O22: =VLOOKUP(QUERY_FOR_TRNSTRANSPOSED_0008!A22,'[6]Fin vs NFin'!$A$4:$F$568,6,FALSE) -> Não Financeiras | P22: =LEFT(D22,2) -> 82
A23: AA1310 | B23: =VLOOKUP(A23,'[6]Fin vs NFin'!$A$4:$B$568,2,FALSE) -> !Depósitos ao Balcão | C23: 3MO | D23: 825949 | E23: =VLOOKUP(D23,[6]Arvore!$N$8:$Q$6855,4,FALSE) -> 51959 | F23: 1755.36 | G23: 2602.5 | H23: -847.14 | O23: =VLOOKUP(QUERY_FOR_TRNSTRANSPOSED_0008!A23,'[6]Fin vs NFin'!$A$4:$F$568,6,FALSE) -> Não Financeiras | P23: =LEFT(D23,2) -> 82
A24: AA1410 | B24: =VLOOKUP(A24,'[6]Fin vs NFin'!$A$4:$B$568,2,FALSE) -> !Cms Gestão Contas Part. | C24: 23L | D24: 825946 | E24: =VLOOKUP(D24,[6]Arvore!$N$8:$Q$6855,4,FALSE) -> 51959 | F24: 51940781 | G24: 52749148 | H24: -808367.67 | I24: =SUM(H24:H26) -> -310.20794 | O24: =VLOOKUP(QUERY_FOR_TRNSTRANSPOSED_0008!A24,'[6]Fin vs NFin'!$A$4:$F$568,6,FALSE) -> Não Financeiras | P24: =LEFT(D24,2) -> 82
A25: AA1410 | B25: =VLOOKUP(A25,'[6]Fin vs NFin'!$A$4:$B$568,2,FALSE) -> !Cms Gestão Contas Part. | C25: 23O | D25: 825946 | E25: =VLOOKUP(D25,[6]Arvore!$N$8:$Q$6855,4,FALSE) -> 51959 | F25: 944096.42 | G25: 934724 | H25: 9372.42 | O25: =VLOOKUP(QUERY_FOR_TRNSTRANSPOSED_0008!A25,'[6]Fin vs NFin'!$A$4:$F$568,6,FALSE) -> Não Financeiras | P25: =LEFT(D25,2) -> 82
A26: AA1410 | B26: =VLOOKUP(A26,'[6]Fin vs NFin'!$A$4:$B$568,2,FALSE) -> !Cms Gestão Contas Part. | C26: CTP | D26: 825946 | E26: =VLOOKUP(D26,[6]Arvore!$N$8:$Q$6855,4,FALSE) -> 51959 | F26: 29055771 | G26: 28257086 | H26: 798685.04 | O26: =VLOOKUP(QUERY_FOR_TRNSTRANSPOSED_0008!A26,'[6]Fin vs NFin'!$A$4:$F$568,6,FALSE) -> Não Financeiras | P26: =LEFT(D26,2) -> 82
A27: AA1420 | B27: =VLOOKUP(A27,'[6]Fin vs NFin'!$A$4:$B$568,2,FALSE) -> !Cms Gestão Contas Neg. | C27: !PE | D27: 825943 | E27: =VLOOKUP(D27,[6]Arvore!$N$8:$Q$6855,4,FALSE) -> 51950 | F27: 20166320 | G27: 20274230 | H27: -107910.26 | I27: =SUM(H27:H30) -> 0.3833667 | O27: =VLOOKUP(QUERY_FOR_TRNSTRANSPOSED_0008!A27,'[6]Fin vs NFin'!$A$4:$F$568,6,FALSE) -> Não Financeiras | P27: =LEFT(D27,2) -> 82
A28: AA1420 | B28: =VLOOKUP(A28,'[6]Fin vs NFin'!$A$4:$B$568,2,FALSE) -> !Cms Gestão Contas Neg. | C28: 23K | D28: 825943 | E28: =VLOOKUP(D28,[6]Arvore!$N$8:$Q$6855,4,FALSE) -> 51950 | F28: 763 | G28: -98741.66 | H28: 99504.66 | O28: =VLOOKUP(QUERY_FOR_TRNSTRANSPOSED_0008!A28,'[6]Fin vs NFin'!$A$4:$F$568,6,FALSE) -> Não Financeiras | P28: =LEFT(D28,2) -> 82
A29: AA1420 | B29: =VLOOKUP(A29,'[6]Fin vs NFin'!$A$4:$B$568,2,FALSE) -> !Cms Gestão Contas Neg. | C29: 23R | D29: 825943 | E29: =VLOOKUP(D29,[6]Arvore!$N$8:$Q$6855,4,FALSE) -> 51950 | F29: 1625 | G29: 1625 | H29: 0 | O29: =VLOOKUP(QUERY_FOR_TRNSTRANSPOSED_0008!A29,'[6]Fin vs NFin'!$A$4:$F$568,6,FALSE) -> Não Financeiras | P29: =LEFT(D29,2) -> 82
A30: AA1420 | B30: =VLOOKUP(A30,'[6]Fin vs NFin'!$A$4:$B$568,2,FALSE) -> !Cms Gestão Contas Neg. | C30: EGE | D30: 825943 | E30: =VLOOKUP(D30,[6]Arvore!$N$8:$Q$6855,4,FALSE) -> 51950 | F30: -786.51 | G30: -9192.4934 | H30: 8405.9834 | O30: =VLOOKUP(QUERY_FOR_TRNSTRANSPOSED_0008!A30,'[6]Fin vs NFin'!$A$4:$F$568,6,FALSE) -> Não Financeiras | P30: =LEFT(D30,2) -> 82
A31: AA1431 | B31: =VLOOKUP(A31,'[6]Fin vs NFin'!$A$4:$B$568,2,FALSE) -> !Domiciliações/Cash Back | C31: BBE | D31: 71904011 | E31: =VLOOKUP(D31,[6]Arvore!$N$8:$Q$6855,4,FALSE) -> 4161599 | F31: -5908506.9 | G31: -5908506.9 | H31: 9.3132257e-10 | I31: 9.3132257e-10 | O31: =VLOOKUP(QUERY_FOR_TRNSTRANSPOSED_0008!A31,'[6]Fin vs NFin'!$A$4:$F$568,6,FALSE) -> Não Financeiras | P31: =LEFT(D31,2) -> 71
A32: AA1432 | B32: =VLOOKUP(A32,'[6]Fin vs NFin'!$A$4:$B$568,2,FALSE) -> !Gasolina/Cash Back | C32: BBB | D32: 71904010 | E32: =VLOOKUP(D32,[6]Arvore!$N$8:$Q$6855,4,FALSE) -> 4161599 | F32: -872953.72 | G32: -872302.87 | H32: -650.85 | I32: =SUM(H32:H36) -> -2.0941116e-10 | O32: =VLOOKUP(QUERY_FOR_TRNSTRANSPOSED_0008!A32,'[6]Fin vs NFin'!$A$4:$F$568,6,FALSE) -> Não Financeiras | P32: =LEFT(D32,2) -> 71
A33: AA1432 | B33: =VLOOKUP(A33,'[6]Fin vs NFin'!$A$4:$B$568,2,FALSE) -> !Gasolina/Cash Back | C33: BBC | D33: 71904013 | E33: =VLOOKUP(D33,[6]Arvore!$N$8:$Q$6855,4,FALSE) -> 4161599 | F33: -869701.57 | G33: -869701.57 | H33: -1.1641532e-10 | O33: =VLOOKUP(QUERY_FOR_TRNSTRANSPOSED_0008!A33,'[6]Fin vs NFin'!$A$4:$F$568,6,FALSE) -> Não Financeiras | P33: =LEFT(D33,2) -> 71
A34: AA1432 | B34: =VLOOKUP(A34,'[6]Fin vs NFin'!$A$4:$B$568,2,FALSE) -> !Gasolina/Cash Back | C34: BBX | D34: 71904013 | E34: =VLOOKUP(D34,[6]Arvore!$N$8:$Q$6855,4,FALSE) -> 4161599 | F34: -1419.15 | G34: -2070 | H34: 650.85 | O34: =VLOOKUP(QUERY_FOR_TRNSTRANSPOSED_0008!A34,'[6]Fin vs NFin'!$A$4:$F$568,6,FALSE) -> Não Financeiras | P34: =LEFT(D34,2) -> 71
A35: AA1432 | B35: =VLOOKUP(A35,'[6]Fin vs NFin'!$A$4:$B$568,2,FALSE) -> !Gasolina/Cash Back | C35: ONL | D35: 71904010 | E35: =VLOOKUP(D35,[6]Arvore!$N$8:$Q$6855,4,FALSE) -> 4161599 | F35: 257305.22 | G35: 257305.22 | H35: 0 | O35: =VLOOKUP(QUERY_FOR_TRNSTRANSPOSED_0008!A35,'[6]Fin vs NFin'!$A$4:$F$568,6,FALSE) -> Não Financeiras | P35: =LEFT(D35,2) -> 71
A36: AA1432 | B36: =VLOOKUP(A36,'[6]Fin vs NFin'!$A$4:$B$568,2,FALSE) -> !Gasolina/Cash Back | C36: ONL | D36: 71904013 | E36: =VLOOKUP(D36,[6]Arvore!$N$8:$Q$6855,4,FALSE) -> 4161599 | F36: 602249.57 | G36: 602249.57 | H36: 0 | O36: =VLOOKUP(QUERY_FOR_TRNSTRANSPOSED_0008!A36,'[6]Fin vs NFin'!$A$4:$F$568,6,FALSE) -> Não Financeiras | P36: =LEFT(D36,2) -> 71
A37: AA1433 | B37: =VLOOKUP(A37,'[6]Fin vs NFin'!$A$4:$B$568,2,FALSE) -> !Cross Segment/Cash Back | C37: S9K | D37: 71904015 | E37: =VLOOKUP(D37,[6]Arvore!$N$8:$Q$6855,4,FALSE) -> 4198 | F37: -10862.54 | G37: -10862.54 | H37: 0 | I37: 0 | O37: =VLOOKUP(QUERY_FOR_TRNSTRANSPOSED_0008!A37,'[6]Fin vs NFin'!$A$4:$F$568,6,FALSE) -> Não Financeiras | P37: =LEFT(D37,2) -> 71
A38: AA1434 | B38: =VLOOKUP(A38,'[6]Fin vs NFin'!$A$4:$B$568,2,FALSE) -> !IMI/Cash Back | C38: BBI | D38: 71904018 | E38: =VLOOKUP(D38,[6]Arvore!$N$8:$Q$6855,4,FALSE) -> 4161599 | F38: -1239134.9 | G38: -1239134.9 | H38: -2.3283064e-10 | I38: 0 | O38: =VLOOKUP(QUERY_FOR_TRNSTRANSPOSED_0008!A38,'[6]Fin vs NFin'!$A$4:$F$568,6,FALSE) -> Não Financeiras | P38: =LEFT(D38,2) -> 71
A39: AA1480 | B39: =VLOOKUP(A39,'[6]Fin vs NFin'!$A$4:$B$568,2,FALSE) -> !Tramitação Manual | C39: LD6 | D39: 8251212 | E39: =VLOOKUP(D39,[6]Arvore!$N$8:$Q$6855,4,FALSE) -> 5151212 | F39: 2333970.4 | G39: 2333970.4 | H39: 0 | I39: 0 | O39: =VLOOKUP(QUERY_FOR_TRNSTRANSPOSED_0008!A39,'[6]Fin vs NFin'!$A$4:$F$568,6,FALSE) -> Não Financeiras | P39: =LEFT(D39,2) -> 82
A40: AA1490 | B40: =VLOOKUP(A40,'[6]Fin vs NFin'!$A$4:$B$568,2,FALSE) -> !Outras DO | C40: !67 | D40: 825945 | E40: =VLOOKUP(D40,[6]Arvore!$N$8:$Q$6855,4,FALSE) -> 51959 | F40: 32704.88 | G40: 32742.32 | H40: -37.44 | I40: 342371.99 | O40: =VLOOKUP(QUERY_FOR_TRNSTRANSPOSED_0008!A40,'[6]Fin vs NFin'!$A$4:$F$568,6,FALSE) -> Não Financeiras | P40: =LEFT(D40,2) -> 82
A41: AA1490 | B41: =VLOOKUP(A41,'[6]Fin vs NFin'!$A$4:$B$568,2,FALSE) -> !Outras DO | C41: 38A | D41: 71904081 | E41: =VLOOKUP(D41,[6]Arvore!$N$8:$Q$6855,4,FALSE) -> 4198 | F41: 2011.68 | G41: 2011.68 | H41: 2.2737368e-13 | O41: =VLOOKUP(QUERY_FOR_TRNSTRANSPOSED_0008!A41,'[6]Fin vs NFin'!$A$4:$F$568,6,FALSE) -> Não Financeiras | P41: =LEFT(D41,2) -> 71
A42: AA1490 | B42: =VLOOKUP(A42,'[6]Fin vs NFin'!$A$4:$B$568,2,FALSE) -> !Outras DO | C42: L01 | D42: 71904070 | E42: =VLOOKUP(D42,[6]Arvore!$N$8:$Q$6855,4,FALSE) -> 4198 | G42: 5250 | H42: -5250 | O42: =VLOOKUP(QUERY_FOR_TRNSTRANSPOSED_0008!A42,'[6]Fin vs NFin'!$A$4:$F$568,6,FALSE) -> Não Financeiras | P42: =LEFT(D42,2) -> 71
A43: AA1490 | B43: =VLOOKUP(A43,'[6]Fin vs NFin'!$A$4:$B$568,2,FALSE) -> !Outras DO | C43: L01 | D43: 71904080 | E43: =VLOOKUP(D43,[6]Arvore!$N$8:$Q$6855,4,FALSE) -> 4198 | G43: 551.11 | H43: -551.11 | O43: =VLOOKUP(QUERY_FOR_TRNSTRANSPOSED_0008!A43,'[6]Fin vs NFin'!$A$4:$F$568,6,FALSE) -> Não Financeiras | P43: =LEFT(D43,2) -> 71
A44: AA1490 | B44: =VLOOKUP(A44,'[6]Fin vs NFin'!$A$4:$B$568,2,FALSE) -> !Outras DO | C44: L01 | D44: 71909 | E44: =VLOOKUP(D44,[6]Arvore!$N$8:$Q$6855,4,FALSE) -> 4912000 | G44: -342371.99 | H44: 342371.99 | O44: =VLOOKUP(QUERY_FOR_TRNSTRANSPOSED_0008!A44,'[6]Fin vs NFin'!$A$4:$F$568,6,FALSE) -> Não Financeiras | P44: =LEFT(D44,2) -> 71
A45: AA1490 | B45: =VLOOKUP(A45,'[6]Fin vs NFin'!$A$4:$B$568,2,FALSE) -> !Outras DO | C45: NRJ | D45: 825945 | E45: =VLOOKUP(D45,[6]Arvore!$N$8:$Q$6855,4,FALSE) -> 51959 | F45: 1978.88 | G45: 1941.44 | H45: 37.44 | O45: =VLOOKUP(QUERY_FOR_TRNSTRANSPOSED_0008!A45,'[6]Fin vs NFin'!$A$4:$F$568,6,FALSE) -> Não Financeiras | P45: =LEFT(D45,2) -> 82
A46: AA1490 | B46: =VLOOKUP(A46,'[6]Fin vs NFin'!$A$4:$B$568,2,FALSE) -> !Outras DO | C46: OF9 | D46: 71904082 | E46: =VLOOKUP(D46,[6]Arvore!$N$8:$Q$6855,4,FALSE) -> 4198 | F46: -20760 | G46: -20760 | H46: 0 | O46: =VLOOKUP(QUERY_FOR_TRNSTRANSPOSED_0008!A46,'[6]Fin vs NFin'!$A$4:$F$568,6,FALSE) -> Não Financeiras | P46: =LEFT(D46,2) -> 71
A47: AA1490 | B47: =VLOOKUP(A47,'[6]Fin vs NFin'!$A$4:$B$568,2,FALSE) -> !Outras DO | C47: ONL | D47: 71904080 | E47: =VLOOKUP(D47,[6]Arvore!$N$8:$Q$6855,4,FALSE) -> 4198 | F47: -558008.78 | G47: -460772.48 | H47: -97236.3 | O47: =VLOOKUP(QUERY_FOR_TRNSTRANSPOSED_0008!A47,'[6]Fin vs NFin'!$A$4:$F$568,6,FALSE) -> Não Financeiras | P47: =LEFT(D47,2) -> 71
A48: AA1490 | B48: =VLOOKUP(A48,'[6]Fin vs NFin'!$A$4:$B$568,2,FALSE) -> !Outras DO | C48: ONL | D48: 71904081 | E48: =VLOOKUP(D48,[6]Arvore!$N$8:$Q$6855,4,FALSE) -> 4198 | F48: -609940.67 | G48: -477125.59 | H48: -132815.08 | O48: =VLOOKUP(QUERY_FOR_TRNSTRANSPOSED_0008!A48,'[6]Fin vs NFin'!$A$4:$F$568,6,FALSE) -> Não Financeiras | P48: =LEFT(D48,2) -> 71
A49: AA1490 | B49: =VLOOKUP(A49,'[6]Fin vs NFin'!$A$4:$B$568,2,FALSE) -> !Outras DO | C49: ONL | D49: 71904082 | E49: =VLOOKUP(D49,[6]Arvore!$N$8:$Q$6855,4,FALSE) -> 4198 | F49: 124576.19 | G49: -14040 | H49: 138616.19 | O49: =VLOOKUP(QUERY_FOR_TRNSTRANSPOSED_0008!A49,'[6]Fin vs NFin'!$A$4:$F$568,6,FALSE) -> Não Financeiras | P49: =LEFT(D49,2) -> 71
A50: AA1490 | B50: =VLOOKUP(A50,'[6]Fin vs NFin'!$A$4:$B$568,2,FALSE) -> !Outras DO | C50: ONL | D50: 71909 | E50: =VLOOKUP(D50,[6]Arvore!$N$8:$Q$6855,4,FALSE) -> 4912000 | G50: -97236.3 | H50: 97236.3 | O50: =VLOOKUP(QUERY_FOR_TRNSTRANSPOSED_0008!A50,'[6]Fin vs NFin'!$A$4:$F$568,6,FALSE) -> Não Financeiras | P50: =LEFT(D50,2) -> 71
A51: AA2000 | B51: =VLOOKUP(A51,'[6]Fin vs NFin'!$A$4:$B$568,2,FALSE) -> !Cadernetas | C51: 42A | D51: 825970 | E51: =VLOOKUP(D51,[6]Arvore!$N$8:$Q$6855,4,FALSE) -> 5194 | F51: 102460.78 | G51: 98346.98 | H51: 4113.8 | I51: =SUM(H51:H53) -> 0 | O51: =VLOOKUP(QUERY_FOR_TRNSTRANSPOSED_0008!A51,'[6]Fin vs NFin'!$A$4:$F$568,6,FALSE) -> Não Financeiras | P51: =LEFT(D51,2) -> 82
A52: AA2000 | B52: =VLOOKUP(A52,'[6]Fin vs NFin'!$A$4:$B$568,2,FALSE) -> !Cadernetas | C52: 4LD | D52: 825970 | E52: =VLOOKUP(D52,[6]Arvore!$N$8:$Q$6855,4,FALSE) -> 5194 | F52: 1033494.5 | G52: 1037999.5 | H52: -4505 | O52: =VLOOKUP(QUERY_FOR_TRNSTRANSPOSED_0008!A52,'[6]Fin vs NFin'!$A$4:$F$568,6,FALSE) -> Não Financeiras | P52: =LEFT(D52,2) -> 82
A53: AA2000 | B53: =VLOOKUP(A53,'[6]Fin vs NFin'!$A$4:$B$568,2,FALSE) -> !Cadernetas | C53: EAD | D53: 825970 | E53: =VLOOKUP(D53,[6]Arvore!$N$8:$Q$6855,4,FALSE) -> 5194 | F53: -152.2 | G53: -543.4 | H53: 391.2 | O53: =VLOOKUP(QUERY_FOR_TRNSTRANSPOSED_0008!A53,'[6]Fin vs NFin'!$A$4:$F$568,6,FALSE) -> Não Financeiras | P53: =LEFT(D53,2) -> 82
A54: AA2100 | B54: =VLOOKUP(A54,'[6]Fin vs NFin'!$A$4:$B$568,2,FALSE) -> !Visados/Bancários | C54: !91 | D54: 825972 | E54: =VLOOKUP(D54,[6]Arvore!$N$8:$Q$6855,4,FALSE) -> 5194 | F54: 15687.5 | G54: 8512.5 | H54: 7175 | I54: 0 | O54: =VLOOKUP(QUERY_FOR_TRNSTRANSPOSED_0008!A54,'[6]Fin vs NFin'!$A$4:$F$568,6,FALSE) -> Não Financeiras | P54: =LEFT(D54,2) -> 82
A55: AA2100 | B55: =VLOOKUP(A55,'[6]Fin vs NFin'!$A$4:$B$568,2,FALSE) -> !Visados/Bancários | C55: !91 | D55: 825976 | E55: =VLOOKUP(D55,[6]Arvore!$N$8:$Q$6855,4,FALSE) -> 5194 | F55: 843773.25 | G55: 855338.25 | H55: -11565 | O55: =VLOOKUP(QUERY_FOR_TRNSTRANSPOSED_0008!A55,'[6]Fin vs NFin'!$A$4:$F$568,6,FALSE) -> Não Financeiras | P55: =LEFT(D55,2) -> 82
A56: AA2100 | B56: =VLOOKUP(A56,'[6]Fin vs NFin'!$A$4:$B$568,2,FALSE) -> !Visados/Bancários | C56: 8NQ | D56: 825976 | E56: =VLOOKUP(D56,[6]Arvore!$N$8:$Q$6855,4,FALSE) -> 5194 | F56: -250 | G56: -3690 | H56: 3440 | O56: =VLOOKUP(QUERY_FOR_TRNSTRANSPOSED_0008!A56,'[6]Fin vs NFin'!$A$4:$F$568,6,FALSE) -> Não Financeiras | P56: =LEFT(D56,2) -> 82
A57: AA2100 | B57: =VLOOKUP(A57,'[6]Fin vs NFin'!$A$4:$B$568,2,FALSE) -> !Visados/Bancários | C57: 8NR | D57: 825976 | E57: =VLOOKUP(D57,[6]Arvore!$N$8:$Q$6855,4,FALSE) -> 5194 | G57: -375 | H57: 375 | O57: =VLOOKUP(QUERY_FOR_TRNSTRANSPOSED_0008!A57,'[6]Fin vs NFin'!$A$4:$F$568,6,FALSE) -> Não Financeiras | P57: =LEFT(D57,2) -> 82
A58: AA2100 | B58: =VLOOKUP(A58,'[6]Fin vs NFin'!$A$4:$B$568,2,FALSE) -> !Visados/Bancários | C58: 8NV | D58: 825972 | E58: =VLOOKUP(D58,[6]Arvore!$N$8:$Q$6855,4,FALSE) -> 5194 | G58: -125 | H58: 125 | O58: =VLOOKUP(QUERY_FOR_TRNSTRANSPOSED_0008!A58,'[6]Fin vs NFin'!$A$4:$F$568,6,FALSE) -> Não Financeiras | P58: =LEFT(D58,2) -> 82
A59: AA2100 | B59: =VLOOKUP(A59,'[6]Fin vs NFin'!$A$4:$B$568,2,FALSE) -> !Visados/Bancários | C59: D8C | D59: 825976 | E59: =VLOOKUP(D59,[6]Arvore!$N$8:$Q$6855,4,FALSE) -> 5194 | F59: -80 | G59: -530 | H59: 450 | O59: =VLOOKUP(QUERY_FOR_TRNSTRANSPOSED_0008!A59,'[6]Fin vs NFin'!$A$4:$F$568,6,FALSE) -> Não Financeiras | P59: =LEFT(D59,2) -> 82
A60: AA2200 | B60: =VLOOKUP(A60,'[6]Fin vs NFin'!$A$4:$B$568,2,FALSE) -> !Devolução de Cheques | C60: !YM | D60: 825975 | E60: =VLOOKUP(D60,[6]Arvore!$N$8:$Q$6855,4,FALSE) -> 5194 | F60: 401370 | G60: 407155 | H60: -5785 | I60: =SUM(H60:H61) -> 0 | O60: =VLOOKUP(QUERY_FOR_TRNSTRANSPOSED_0008!A60,'[6]Fin vs NFin'!$A$4:$F$568,6,FALSE) -> Não Financeiras | P60: =LEFT(D60,2) -> 82
A61: AA2200 | B61: =VLOOKUP(A61,'[6]Fin vs NFin'!$A$4:$B$568,2,FALSE) -> !Devolução de Cheques | C61: 8NU | D61: 825975 | E61: =VLOOKUP(D61,[6]Arvore!$N$8:$Q$6855,4,FALSE) -> 5194 | F61: -910 | G61: -6695 | H61: 5785 | O61: =VLOOKUP(QUERY_FOR_TRNSTRANSPOSED_0008!A61,'[6]Fin vs NFin'!$A$4:$F$568,6,FALSE) -> Não Financeiras | P61: =LEFT(D61,2) -> 82
A62: AA2290 | B62: =VLOOKUP(A62,'[6]Fin vs NFin'!$A$4:$B$568,2,FALSE) -> !Cheques sem Provisão | C62: !NC | D62: 8259412 | E62: =VLOOKUP(D62,[6]Arvore!$N$8:$Q$6855,4,FALSE) -> 51931 | F62: 253925 | G62: 255500 | H62: -1575 | I62: 0 | O62: =VLOOKUP(QUERY_FOR_TRNSTRANSPOSED_0008!A62,'[6]Fin vs NFin'!$A$4:$F$568,6,FALSE) -> Não Financeiras | P62: =LEFT(D62,2) -> 82
A63: AA2290 | B63: =VLOOKUP(A63,'[6]Fin vs NFin'!$A$4:$B$568,2,FALSE) -> !Cheques sem Provisão | C63: 8NX | D63: 8259412 | E63: =VLOOKUP(D63,[6]Arvore!$N$8:$Q$6855,4,FALSE) -> 51931 | F63: -150 | G63: -1725 | H63: 1575 | O63: =VLOOKUP(QUERY_FOR_TRNSTRANSPOSED_0008!A63,'[6]Fin vs NFin'!$A$4:$F$568,6,FALSE) -> Não Financeiras | P63: =LEFT(D63,2) -> 82
A64: AA2290 | B64: =VLOOKUP(A64,'[6]Fin vs NFin'!$A$4:$B$568,2,FALSE) -> !Cheques sem Provisão | C64: EEE | D64: 8259412 | E64: =VLOOKUP(D64,[6]Arvore!$N$8:$Q$6855,4,FALSE) -> 51931 | F64: -80 | G64: -80 | H64: 0 | O64: =VLOOKUP(QUERY_FOR_TRNSTRANSPOSED_0008!A64,'[6]Fin vs NFin'!$A$4:$F$568,6,FALSE) -> Não Financeiras | P64: =LEFT(D64,2) -> 82
A65: AA2300 | B65: =VLOOKUP(A65,'[6]Fin vs NFin'!$A$4:$B$568,2,FALSE) -> !Cheques Outras | C65: 257 | D65: 77961 | E65: =VLOOKUP(D65,[6]Arvore!$N$8:$Q$6855,4,FALSE) -> 41499 | F65: -1800 | G65: -1800 | H65: 0 | I65: =SUM(H65:H71) -> 0 | O65: =VLOOKUP(QUERY_FOR_TRNSTRANSPOSED_0008!A65,'[6]Fin vs NFin'!$A$4:$F$568,6,FALSE) -> Não Financeiras | P65: =LEFT(D65,2) -> 77
A66: AA2300 | B66: =VLOOKUP(A66,'[6]Fin vs NFin'!$A$4:$B$568,2,FALSE) -> !Cheques Outras | C66: 491 | D66: 825974 | E66: =VLOOKUP(D66,[6]Arvore!$N$8:$Q$6855,4,FALSE) -> 5194 | F66: 29022.5 | G66: 28782.5 | H66: 240 | O66: =VLOOKUP(QUERY_FOR_TRNSTRANSPOSED_0008!A66,'[6]Fin vs NFin'!$A$4:$F$568,6,FALSE) -> Não Financeiras | P66: =LEFT(D66,2) -> 82
A67: AA2300 | B67: =VLOOKUP(A67,'[6]Fin vs NFin'!$A$4:$B$568,2,FALSE) -> !Cheques Outras | C67: ALH | D67: 89341 | E67: =VLOOKUP(D67,[6]Arvore!$N$8:$Q$6855,4,FALSE) -> 431110 | F67: 3725 | G67: 3725 | H67: 0 | O67: =VLOOKUP(QUERY_FOR_TRNSTRANSPOSED_0008!A67,'[6]Fin vs NFin'!$A$4:$F$568,6,FALSE) -> Não Financeiras | P67: =LEFT(D67,2) -> 89 | R67: =VLOOKUP(D67,[6]Mapeamento!$A$38:$C$497,3,FALSE) -> GG
A68: AA2300 | B68: =VLOOKUP(A68,'[6]Fin vs NFin'!$A$4:$B$568,2,FALSE) -> !Cheques Outras | C68: CCD | D68: 8995 | E68: =VLOOKUP(D68,[6]Arvore!$N$8:$Q$6855,4,FALSE) -> 5194 | F68: -10 | G68: -10 | H68: 0 | O68: =VLOOKUP(QUERY_FOR_TRNSTRANSPOSED_0008!A68,'[6]Fin vs NFin'!$A$4:$F$568,6,FALSE) -> Não Financeiras | P68: =LEFT(D68,2) -> 89
A69: AA2300 | B69: =VLOOKUP(A69,'[6]Fin vs NFin'!$A$4:$B$568,2,FALSE) -> !Cheques Outras | C69: JNC | D69: 825978 | E69: =VLOOKUP(D69,[6]Arvore!$N$8:$Q$6855,4,FALSE) -> 5194 | F69: 77360 | G69: 77600 | H69: -240 | O69: =VLOOKUP(QUERY_FOR_TRNSTRANSPOSED_0008!A69,'[6]Fin vs NFin'!$A$4:$F$568,6,FALSE) -> Não Financeiras | P69: =LEFT(D69,2) -> 82
A70: AA2300 | B70: =VLOOKUP(A70,'[6]Fin vs NFin'!$A$4:$B$568,2,FALSE) -> !Cheques Outras | C70: L01 | D70: 71615 | E70: =VLOOKUP(D70,[6]Arvore!$N$8:$Q$6855,4,FALSE) -> 416190 | F70: -389678.36 | G70: -650867.42 | H70: 261189.06 | O70: =VLOOKUP(QUERY_FOR_TRNSTRANSPOSED_0008!A70,'[6]Fin vs NFin'!$A$4:$F$568,6,FALSE) -> Não Financeiras | P70: =LEFT(D70,2) -> 71
A71: AA2300 | B71: =VLOOKUP(A71,'[6]Fin vs NFin'!$A$4:$B$568,2,FALSE) -> !Cheques Outras | C71: ONL | D71: 71615 | E71: =VLOOKUP(D71,[6]Arvore!$N$8:$Q$6855,4,FALSE) -> 416190 | F71: -261189.06 | G71: 6.3664629e-12 | H71: -261189.06 | O71: =VLOOKUP(QUERY_FOR_TRNSTRANSPOSED_0008!A71,'[6]Fin vs NFin'!$A$4:$F$568,6,FALSE) -> Não Financeiras | P71: =LEFT(D71,2) -> 71
A72: AA3000 | B72: =VLOOKUP(A72,'[6]Fin vs NFin'!$A$4:$B$568,2,FALSE) -> !Desc.Autorizados | C72: !MN | D72: 518510 | E72: =VLOOKUP(D72,[6]Arvore!$N$8:$Q$6855,4,FALSE) -> 1992199 | F72: 1126.12 | G72: 0 | H72: 1126.12 | I72: -4.5474735e-13 | O72: =VLOOKUP(QUERY_FOR_TRNSTRANSPOSED_0008!A72,'[6]Fin vs NFin'!$A$4:$F$568,6,FALSE) -> Não Financeiras | P72: =LEFT(D72,2) -> 51
A73: AA3000 | B73: =VLOOKUP(A73,'[6]Fin vs NFin'!$A$4:$B$568,2,FALSE) -> !Desc.Autorizados | C73: !NB | D73: 8259411 | E73: =VLOOKUP(D73,[6]Arvore!$N$8:$Q$6855,4,FALSE) -> 51931 | F73: 1679.89 | G73: 2890.01 | H73: -1210.12 | O73: =VLOOKUP(QUERY_FOR_TRNSTRANSPOSED_0008!A73,'[6]Fin vs NFin'!$A$4:$F$568,6,FALSE) -> Não Financeiras | P73: =LEFT(D73,2) -> 82
A74: AA3000 | B74: =VLOOKUP(A74,'[6]Fin vs NFin'!$A$4:$B$568,2,FALSE) -> !Desc.Autorizados | C74: 23S | D74: 8259411 | E74: =VLOOKUP(D74,[6]Arvore!$N$8:$Q$6855,4,FALSE) -> 51931 | F74: 18750 | G74: 18666 | H74: 84 | O74: =VLOOKUP(QUERY_FOR_TRNSTRANSPOSED_0008!A74,'[6]Fin vs NFin'!$A$4:$F$568,6,FALSE) -> Não Financeiras | P74: =LEFT(D74,2) -> 82
A75: AA3001 | B75: =VLOOKUP(A75,'[6]Fin vs NFin'!$A$4:$B$568,2,FALSE) -> !Desc.Autorizados-Vercon | C75: VE4 | D75: 8259411 | E75: =VLOOKUP(D75,[6]Arvore!$N$8:$Q$6855,4,FALSE) -> 51931 | F75: 5.6 | G75: 5.6 | H75: 0 | I75: 0 | O75: =VLOOKUP(QUERY_FOR_TRNSTRANSPOSED_0008!A75,'[6]Fin vs NFin'!$A$4:$F$568,6,FALSE) -> Não Financeiras | P75: =LEFT(D75,2) -> 82
A76: AA3001 | B76: =VLOOKUP(A76,'[6]Fin vs NFin'!$A$4:$B$568,2,FALSE) -> !Desc.Autorizados-Vercon | C76: VEJ | D76: 8259411 | E76: =VLOOKUP(D76,[6]Arvore!$N$8:$Q$6855,4,FALSE) -> 51931 | F76: -24 | G76: -24 | H76: 0 | O76: =VLOOKUP(QUERY_FOR_TRNSTRANSPOSED_0008!A76,'[6]Fin vs NFin'!$A$4:$F$568,6,FALSE) -> Não Financeiras | P76: =LEFT(D76,2) -> 82
A77: AA3002 | B77: =VLOOKUP(A77,'[6]Fin vs NFin'!$A$4:$B$568,2,FALSE) -> !Desc.Autor.-Imobilização | C77: !75 | D77: 825944 | E77: =VLOOKUP(D77,[6]Arvore!$N$8:$Q$6855,4,FALSE) -> 512018 | F77: 479638.19 | G77: 479638.19 | H77: 0 | I77: 0 | O77: =VLOOKUP(QUERY_FOR_TRNSTRANSPOSED_0008!A77,'[6]Fin vs NFin'!$A$4:$F$568,6,FALSE) -> Não Financeiras | P77: =LEFT(D77,2) -> 82
A78: AA3100 | B78: =VLOOKUP(A78,'[6]Fin vs NFin'!$A$4:$B$568,2,FALSE) -> !Desc.Não Autorizados | C78: !71 | D78: 8259411 | E78: =VLOOKUP(D78,[6]Arvore!$N$8:$Q$6855,4,FALSE) -> 51931 | F78: 2239678.3 | G78: 4836572.8 | H78: -2596894.5 | I78: 0.067794433 | O78: =VLOOKUP(QUERY_FOR_TRNSTRANSPOSED_0008!A78,'[6]Fin vs NFin'!$A$4:$F$568,6,FALSE) -> Não Financeiras | P78: =LEFT(D78,2) -> 82
A79: AA3100 | B79: =VLOOKUP(A79,'[6]Fin vs NFin'!$A$4:$B$568,2,FALSE) -> !Desc.Não Autorizados | C79: !CY | D79: 579910324 | E79: =VLOOKUP(D79,[6]Arvore!$N$8:$Q$6855,4,FALSE) -> 1999 | F79: 2544574.7 | G79: 0 | H79: 2544574.7 | O79: =VLOOKUP(QUERY_FOR_TRNSTRANSPOSED_0008!A79,'[6]Fin vs NFin'!$A$4:$F$568,6,FALSE) -> Não Financeiras | P79: =LEFT(D79,2) -> 57
A80: AA3100 | B80: =VLOOKUP(A80,'[6]Fin vs NFin'!$A$4:$B$568,2,FALSE) -> !Desc.Não Autorizados | C80: 244 | D80: 8259411 | E80: =VLOOKUP(D80,[6]Arvore!$N$8:$Q$6855,4,FALSE) -> 51931 | F80: -1498.2 | G80: -51323.65 | H80: 49825.45 | O80: =VLOOKUP(QUERY_FOR_TRNSTRANSPOSED_0008!A80,'[6]Fin vs NFin'!$A$4:$F$568,6,FALSE) -> Não Financeiras | P80: =LEFT(D80,2) -> 82
A81: AA3100 | B81: =VLOOKUP(A81,'[6]Fin vs NFin'!$A$4:$B$568,2,FALSE) -> !Desc.Não Autorizados | C81: JUE | D81: 8259411 | E81: =VLOOKUP(D81,[6]Arvore!$N$8:$Q$6855,4,FALSE) -> 51931 | F81: -6509.72 | G81: -9004.1678 | H81: 2494.4478 | O81: =VLOOKUP(QUERY_FOR_TRNSTRANSPOSED_0008!A81,'[6]Fin vs NFin'!$A$4:$F$568,6,FALSE) -> Não Financeiras | P81: =LEFT(D81,2) -> 82
A82: AA3100 | B82: =VLOOKUP(A82,'[6]Fin vs NFin'!$A$4:$B$568,2,FALSE) -> !Desc.Não Autorizados | C82: ONL | D82: 8259411 | E82: =VLOOKUP(D82,[6]Arvore!$N$8:$Q$6855,4,FALSE) -> 51931 | F82: 79.9 | G82: 79.9 | H82: 0 | O82: =VLOOKUP(QUERY_FOR_TRNSTRANSPOSED_0008!A82,'[6]Fin vs NFin'!$A$4:$F$568,6,FALSE) -> Não Financeiras | P82: =LEFT(D82,2) -> 82
A83: AA3101 | B83: =VLOOKUP(A83,'[6]Fin vs NFin'!$A$4:$B$568,2,FALSE) -> !Desc.Não Autoriz-Vercon | C83: VEF | D83: 8259411 | E83: =VLOOKUP(D83,[6]Arvore!$N$8:$Q$6855,4,FALSE) -> 51931 | F83: -131211.79 | G83: -131211.79 | H83: 0 | I83: -2.2737368e-13 | O83: =VLOOKUP(QUERY_FOR_TRNSTRANSPOSED_0008!A83,'[6]Fin vs NFin'!$A$4:$F$568,6,FALSE) -> Não Financeiras | P83: =LEFT(D83,2) -> 82
A84: AA3101 | B84: =VLOOKUP(A84,'[6]Fin vs NFin'!$A$4:$B$568,2,FALSE) -> !Desc.Não Autoriz-Vercon | C84: VEK | D84: 8259411 | E84: =VLOOKUP(D84,[6]Arvore!$N$8:$Q$6855,4,FALSE) -> 51931 | F84: 944.72 | G84: 944.72 | H84: -2.2737368e-13 | O84: =VLOOKUP(QUERY_FOR_TRNSTRANSPOSED_0008!A84,'[6]Fin vs NFin'!$A$4:$F$568,6,FALSE) -> Não Financeiras | P84: =LEFT(D84,2) -> 82
A85: CC1010 | B85: =VLOOKUP(A85,'[6]Fin vs NFin'!$A$4:$B$568,2,FALSE) -> !Cash Advance | C85: S7S | D85: 82590020 | E85: =VLOOKUP(D85,[6]Arvore!$N$8:$Q$6855,4,FALSE) -> 5151512 | F85: 2247912.3 | G85: 2349001.4 | H85: -101089.13 | I85: =SUM(H85:H89) -> 0 | O85: =VLOOKUP(QUERY_FOR_TRNSTRANSPOSED_0008!A85,'[6]Fin vs NFin'!$A$4:$F$568,6,FALSE) -> Não Financeiras | P85: =LEFT(D85,2) -> 82
A86: CC1010 | B86: =VLOOKUP(A86,'[6]Fin vs NFin'!$A$4:$B$568,2,FALSE) -> !Cash Advance | C86: SQ1 | D86: 82590020 | E86: =VLOOKUP(D86,[6]Arvore!$N$8:$Q$6855,4,FALSE) -> 5151512 | F86: 148548.95 | G86: 45906.99 | H86: 102641.96 | O86: =VLOOKUP(QUERY_FOR_TRNSTRANSPOSED_0008!A86,'[6]Fin vs NFin'!$A$4:$F$568,6,FALSE) -> Não Financeiras | P86: =LEFT(D86,2) -> 82
A87: CC1010 | B87: =VLOOKUP(A87,'[6]Fin vs NFin'!$A$4:$B$568,2,FALSE) -> !Cash Advance | C87: SQG | D87: 82590020 | E87: =VLOOKUP(D87,[6]Arvore!$N$8:$Q$6855,4,FALSE) -> 5151512 | F87: -209.93 | G87: -209.93 | H87: 0 | O87: =VLOOKUP(QUERY_FOR_TRNSTRANSPOSED_0008!A87,'[6]Fin vs NFin'!$A$4:$F$568,6,FALSE) -> Não Financeiras | P87: =LEFT(D87,2) -> 82
A88: CC1010 | B88: =VLOOKUP(A88,'[6]Fin vs NFin'!$A$4:$B$568,2,FALSE) -> !Cash Advance | C88: YAB | D88: 82590020 | E88: =VLOOKUP(D88,[6]Arvore!$N$8:$Q$6855,4,FALSE) -> 5151512 | F88: 61490.8 | G88: 49129.22 | H88: 12361.58 | O88: =VLOOKUP(QUERY_FOR_TRNSTRANSPOSED_0008!A88,'[6]Fin vs NFin'!$A$4:$F$568,6,FALSE) -> Não Financeiras | P88: =LEFT(D88,2) -> 82
A89: CC1010 | B89: =VLOOKUP(A89,'[6]Fin vs NFin'!$A$4:$B$568,2,FALSE) -> !Cash Advance | C89: YEW | D89: 82590020 | E89: =VLOOKUP(D89,[6]Arvore!$N$8:$Q$6855,4,FALSE) -> 5151512 | F89: 70498.12 | G89: 84412.53 | H89: -13914.41 | O89: =VLOOKUP(QUERY_FOR_TRNSTRANSPOSED_0008!A89,'[6]Fin vs NFin'!$A$4:$F$568,6,FALSE) -> Não Financeiras | P89: =LEFT(D89,2) -> 82
A90: CC1020 | B90: =VLOOKUP(A90,'[6]Fin vs NFin'!$A$4:$B$568,2,FALSE) -> !Compras Cartões | C90: 111 | D90: 82590020 | E90: =VLOOKUP(D90,[6]Arvore!$N$8:$Q$6855,4,FALSE) -> 5151512 | F90: -15.49 | G90: -15.49 | H90: 0 | I90: -12489821 | J90: =I90+I115+I120 -> 0 | O90: =VLOOKUP(QUERY_FOR_TRNSTRANSPOSED_0008!A90,'[6]Fin vs NFin'!$A$4:$F$568,6,FALSE) -> Não Financeiras | P90: =LEFT(D90,2) -> 82
A91: CC1020 | B91: =VLOOKUP(A91,'[6]Fin vs NFin'!$A$4:$B$568,2,FALSE) -> !Compras Cartões | C91: MV1 | D91: 82590021 | E91: =VLOOKUP(D91,[6]Arvore!$N$8:$Q$6855,4,FALSE) -> 5151511 | F91: 0 | G91: 6346418.3 | H91: -6346418.3 | O91: =VLOOKUP(QUERY_FOR_TRNSTRANSPOSED_0008!A91,'[6]Fin vs NFin'!$A$4:$F$568,6,FALSE) -> Não Financeiras | P91: =LEFT(D91,2) -> 82
A92: CC1020 | B92: =VLOOKUP(A92,'[6]Fin vs NFin'!$A$4:$B$568,2,FALSE) -> !Compras Cartões | C92: ONL | D92: 8255 | E92: =VLOOKUP(D92,[6]Arvore!$N$8:$Q$6855,4,FALSE) -> 5151511 | F92: 336362.62 | G92: 336362.62 | H92: 0 | O92: =VLOOKUP(QUERY_FOR_TRNSTRANSPOSED_0008!A92,'[6]Fin vs NFin'!$A$4:$F$568,6,FALSE) -> Não Financeiras | P92: =LEFT(D92,2) -> 82
A93: CC1020 | B93: =VLOOKUP(A93,'[6]Fin vs NFin'!$A$4:$B$568,2,FALSE) -> !Compras Cartões | C93: S72 | D93: 7169002 | E93: =VLOOKUP(D93,[6]Arvore!$N$8:$Q$6855,4,FALSE) -> 5151511 | F93: 60117.03 | G93: -36380.8 | H93: 96497.83 | O93: =VLOOKUP(QUERY_FOR_TRNSTRANSPOSED_0008!A93,'[6]Fin vs NFin'!$A$4:$F$568,6,FALSE) -> Não Financeiras | P93: =LEFT(D93,2) -> 71
A94: CC1020 | B94: =VLOOKUP(A94,'[6]Fin vs NFin'!$A$4:$B$568,2,FALSE) -> !Compras Cartões | C94: S7L | D94: 82590020 | E94: =VLOOKUP(D94,[6]Arvore!$N$8:$Q$6855,4,FALSE) -> 5151512 | F94: 1014751.4 | G94: 1585093.9 | H94: -570342.46 | O94: =VLOOKUP(QUERY_FOR_TRNSTRANSPOSED_0008!A94,'[6]Fin vs NFin'!$A$4:$F$568,6,FALSE) -> Não Financeiras | P94: =LEFT(D94,2) -> 82
A95: CC1020 | B95: =VLOOKUP(A95,'[6]Fin vs NFin'!$A$4:$B$568,2,FALSE) -> !Compras Cartões | C95: SH6 | D95: 82590020 | E95: =VLOOKUP(D95,[6]Arvore!$N$8:$Q$6855,4,FALSE) -> 5151512 | F95: 1801475.6 | G95: 860816.46 | H95: 940659.18 | O95: =VLOOKUP(QUERY_FOR_TRNSTRANSPOSED_0008!A95,'[6]Fin vs NFin'!$A$4:$F$568,6,FALSE) -> Não Financeiras | P95: =LEFT(D95,2) -> 82
A96: CC1020 | B96: =VLOOKUP(A96,'[6]Fin vs NFin'!$A$4:$B$568,2,FALSE) -> !Compras Cartões | C96: Y82 | D96: 8255 | E96: =VLOOKUP(D96,[6]Arvore!$N$8:$Q$6855,4,FALSE) -> 5151511 | F96: 0 | G96: 6143402.7 | H96: -6143402.7 | O96: =VLOOKUP(QUERY_FOR_TRNSTRANSPOSED_0008!A96,'[6]Fin vs NFin'!$A$4:$F$568,6,FALSE) -> Não Financeiras | P96: =LEFT(D96,2) -> 82
A97: CC1020 | B97: =VLOOKUP(A97,'[6]Fin vs NFin'!$A$4:$B$568,2,FALSE) -> !Compras Cartões | C97: YAF | D97: 82590020 | E97: =VLOOKUP(D97,[6]Arvore!$N$8:$Q$6855,4,FALSE) -> 5151512 | F97: 481359.85 | G97: 808223.21 | H97: -326863.36 | O97: =VLOOKUP(QUERY_FOR_TRNSTRANSPOSED_0008!A97,'[6]Fin vs NFin'!$A$4:$F$568,6,FALSE) -> Não Financeiras | P97: =LEFT(D97,2) -> 82
A98: CC1020 | B98: =VLOOKUP(A98,'[6]Fin vs NFin'!$A$4:$B$568,2,FALSE) -> !Compras Cartões | C98: YDJ | D98: 8255 | E98: =VLOOKUP(D98,[6]Arvore!$N$8:$Q$6855,4,FALSE) -> 5151511 | F98: 14749472 | G98: 6873390 | H98: 7876081.9 | O98: =VLOOKUP(QUERY_FOR_TRNSTRANSPOSED_0008!A98,'[6]Fin vs NFin'!$A$4:$F$568,6,FALSE) -> Não Financeiras | P98: =LEFT(D98,2) -> 82
A99: CC1020 | B99: =VLOOKUP(A99,'[6]Fin vs NFin'!$A$4:$B$568,2,FALSE) -> !Compras Cartões | C99: YDK | D99: 8255 | E99: =VLOOKUP(D99,[6]Arvore!$N$8:$Q$6855,4,FALSE) -> 5151511 | F99: 51.02 | G99: -33988.24 | H99: 34039.26 | O99: =VLOOKUP(QUERY_FOR_TRNSTRANSPOSED_0008!A99,'[6]Fin vs NFin'!$A$4:$F$568,6,FALSE) -> Não Financeiras | P99: =LEFT(D99,2) -> 82
A100: CC1020 | B100: =VLOOKUP(A100,'[6]Fin vs NFin'!$A$4:$B$568,2,FALSE) -> !Compras Cartões | C100: YDN | D100: 8255 | E100: =VLOOKUP(D100,[6]Arvore!$N$8:$Q$6855,4,FALSE) -> 5151511 | F100: 4093539.1 | G100: 12941108 | H100: -8847569.2 | O100: =VLOOKUP(QUERY_FOR_TRNSTRANSPOSED_0008!A100,'[6]Fin vs NFin'!$A$4:$F$568,6,FALSE) -> Não Financeiras | P100: =LEFT(D100,2) -> 82
A101: CC1020 | B101: =VLOOKUP(A101,'[6]Fin vs NFin'!$A$4:$B$568,2,FALSE) -> !Compras Cartões | C101: YDO | D101: 8255 | E101: =VLOOKUP(D101,[6]Arvore!$N$8:$Q$6855,4,FALSE) -> 5151511 | F101: 52.98 | G101: -36453.97 | H101: 36506.95 | O101: =VLOOKUP(QUERY_FOR_TRNSTRANSPOSED_0008!A101,'[6]Fin vs NFin'!$A$4:$F$568,6,FALSE) -> Não Financeiras | P101: =LEFT(D101,2) -> 82
...
