Workbook

Sheet TOC
A1: Table of Contents

Sheet T 30.00
A1: T 30.00 - FMI services - Providers and users
D4: Columns
D5: ID representing combination of user, FMI, system type and intermediary | E5: User | G5: Provider | AB5: Communication
E6: Entity name | F6: Entity code | G6: FMI | L6: Intermediary | N6: Main services and governing law | W6: Service providers | AB6: Point of contact(s) at FMI/ intermediary for matters related to resolution of the entity
G7: System type | H7: FMI name (included in predefined list) | I7: FMI name (not included in predefined list) | J7: FMI code | K7: Participation mode | L7: Intermediary name | M7: Intermediary code | N7: Governing law | O7: Currencies relevant for reporting entity | U7: Services provided by FMI / representative institution | V7: Services provided to FMI / representative institution | W7: Comunication service providers | Z7: Other service providers enabling access to FMI
O8: EUR | P8: GBP | Q8: USD | R8: CHF | S8: JPY | T8: Other currencies | W8: FMI proprietary | X8: SWIFT | Y8: Other communication service providers (name) | Z8: Other service providers (name) | AA8: Services necessary to reporting entity
D9: 0010 | E9: 0020 | F9: 0030 | G9: 0040 | H9: 0050 | I9: 0060 | J9: 0070 | K9: 0080 | L9: 0090 | M9: 0100 | N9: 0110 | O9: 0120 | P9: 0130 | Q9: 0140 | R9: 0150 | S9: 0160 | T9: 0170 | U9: 0180 | V9: 0190 | W9: 0200 | X9: 0210 | Y9: 0220 | Z9: 0230 | AA9: 0240 | AB9: 0250
A10: Rows | B10: Users, FMIs, Intermediaries and System Types | C10: 999 | D10: 1 | E10: Banco Santander Totta SA | F10: 549300URJH9VSI58CS32 | G10: CCP-Derivatives | H10: LCH SA | I10: 0 | J10: R1IO4YJ0O79SMWVCHB58 | K10: Indirect | L10: Banco Santander, S.A. | M10: 0 | N10: SPAIN | O10: TRUE | P10: FALSE | Q10: FALSE | R10: FALSE | S10: FALSE | T10: FALSE | U10: Execution & Clearing; Securities Settlement | V10: liquidity provider; custody | W10: TRUE | X10: FALSE | Y10: FALSE | Z10: 0 | AA10: 0 | AB10: Mónica Braga;Technician;00351226158495;monica.braga@lchclearnet.com
C11: 999 | D11: 2 | E11: Banco Santander Totta SA | F11: 549300URJH9VSI58CS32 | G11: (I)CSD | H11: INTERBOLSA | I11: 0 | J11: 529900LG70TCAGWCXT47 | K11: Direct | L11: 0 | M11: 0 | N11: PORTUGAL | O11: TRUE | P11: FALSE | Q11: FALSE | R11: FALSE | S11: FALSE | T11: FALSE | U11: Execution & Clearing; Securities Settlement | V11: custody | W11: TRUE | X11: FALSE | Y11: FALSE | Z11: 0 | AA11: 0 | AB11: Amélia Peralta;Senior Account Manager;00351226158400;amelia.peralta@interbolsa.pt
C12: 999 | D12: 3 | E12: Banco Santander Totta SA | F12: 549300URJH9VSI58CS32 | G12: (I)CSD | H12: Euroclear Bank | I12: 0 | J12: 549300OZ46BRLZ8Y6F65 | K12: Direct | L12: 0 | M12: 0 | N12: BELGIUM | O12: TRUE | P12: FALSE | Q12: FALSE | R12: FALSE | S12: FALSE | T12: FALSE | U12: Execution & Clearing; Securities Settlement | V12: liquidity provider | W12: TRUE | X12: FALSE | Y12: FALSE | Z12: 0 | AA12: 0 | AB12: Bénédicte Brunet;Account Manager;003223262812;comercial.europe@euroclear.com
C13: 999 | D13: 4 | E13: Banco Santander Totta SA | F13: 549300URJH9VSI58CS32 | G13: PS | H13: EURO 1 | I13: 0 | J13: 2549000PZQFZ0TEPB750 | K13: Direct | L13: 0 | M13: 0 | N13: FRANCE | O13: TRUE | P13: FALSE | Q13: FALSE | R13: FALSE | S13: FALSE | T13: FALSE | U13: Payment Services | V13: liquidity provider | W13: TRUE | X13: FALSE | Y13: FALSE | Z13: 0 | AA13: 0 | AB13: Valentina Liva;Account Manager;003226432785
C14: 999 | D14: 5 | E14: Banco Santander Totta SA | F14: 549300URJH9VSI58CS32 | G14: PS | H14: SICOI | I14: 0 | J14: 54930037NWG1CCVQHF93 | K14: Direct | L14: 0 | M14: 0 | N14: PORTUGAL | O14: TRUE | P14: FALSE | Q14: FALSE | R14: FALSE | S14: FALSE | T14: FALSE | U14: Payment Services | V14: liquidity provider; liquidity provider; other (communication) | W14: TRUE | X14: FALSE | Y14: FALSE | Z14: 0 | AA14: 0 | AB14: Cristina de Oliveira Martins;Senior Account Manager;00351217813 050;cristina.martins@sibs.pt
C15: 999 | D15: 6 | E15: Banco Santander Totta SA | F15: 549300URJH9VSI58CS32 | G15: PS | H15: STEP 2 | I15: 0 | J15: 2549000PZQFZ0TEPB751 | K15: Direct | L15: 0 | M15: 0 | N15: FRANCE | O15: TRUE | P15: FALSE | Q15: FALSE | R15: FALSE | S15: FALSE | T15: FALSE | U15: Payment Services | V15: liquidity provider | W15: TRUE | X15: FALSE | Y15: FALSE | Z15: 0 | AA15: 0 | AB15: Valentina Liva;Account Manager;003226432785
C16: 999 | D16: 7 | E16: Banco Santander Totta SA | F16: 549300URJH9VSI58CS32 | G16: PS | H16: STEP 1 | I16: 0 | J16: 2549000PZQFZ0TEPB752 | K16: Direct | L16: 0 | M16: 0 | N16: FRANCE | O16: TRUE | P16: FALSE | Q16: FALSE | R16: FALSE | S16: FALSE | T16: FALSE | U16: Payment Services | V16: liquidity provider | W16: TRUE | X16: FALSE | Y16: FALSE | Z16: 0 | AA16: 0 | AB16: Valentina Liva;Account Manager;003226432785
C17: 999 | D17: 8 | E17: Banco Santander Totta SA | F17: 549300URJH9VSI58CS32 | G17: PS | H17: TARGET2 | I17: 0 | J17: 2549000PZQFZ0TEPB753 | K17: Direct | L17: 0 | M17: 0 | N17: PORTUGAL | O17: TRUE | P17: FALSE | Q17: FALSE | R17: FALSE | S17: FALSE | T17: FALSE | U17: Payment Services | V17: liquidity provider | W17: TRUE | X17: FALSE | Y17: FALSE | Z17: 0 | AA17: 0 | AB17: Lara Fernandes;Head of Divison;lmfernandes@bportugal.pt;00351213130052
C18: 999 | D18: 9 | E18: Banco Santander Totta SA | F18: 549300URJH9VSI58CS32 | G18: PS | H18: TARGET2 | I18: 0 | J18: 969500JXZA2VJ64UCM28 | K18: Indirect | L18: Banco Santander, S.A. | M18: 0 | N18: SPAIN | O18: FALSE | P18: TRUE | Q18: TRUE | R18: FALSE | S18: FALSE | T18: FALSE | U18: Payment Services | V18: liquidity provider | W18: FALSE | X18: TRUE | Y18: FALSE | Z18: 0 | AA18: 0 | AB18: Carmen Maria Rey Poza;Data Manager Director;cmrey@gruposantander.com;0034625597940

Sheet T 31.00
A1: T 31.00 - FMI services - Mapping to critical functions
D4: Columns
D5: ID representing combination of user, system type, FMI and intermediary | E5: Critical functions | G5: Link (true)
E6: Country | F6: Critical function ID
D7: 0010 | E7: 0020 | F7: 0030 | G7: 0040
A8: Rows | B8: Users, FMIs and intermediaries - critical functions | C8: 999 | D8: 1 | E8: PORTUGAL | F8: 4.1 - Capital Markets: Derivatives held for trading - OTC | G8: TRUE
C9: 999 | D9: 2 | E9: PORTUGAL | F9: 3.6 - Payment, Cash, Settlement, Clearing, Custody: Custody services | G9: TRUE
C10: 999 | D10: 3 | E10: PORTUGAL | F10: 3.6 - Payment, Cash, Settlement, Clearing, Custody: Custody services | G10: TRUE
C11: 999 | D11: 4 | E11: PORTUGAL | F11: 3.1 - Payment, Cash, Settlement, Clearing, Custody: Payment services to MFIs | G11: TRUE
C12: 999 | D12: 5 | E12: PORTUGAL | F12: 3.1 - Payment, Cash, Settlement, Clearing, Custody: Payment services to MFIs | G12: TRUE
C13: 999 | D13: 6 | E13: PORTUGAL | F13: 3.1 - Payment, Cash, Settlement, Clearing, Custody: Payment services to MFIs | G13: TRUE
C14: 999 | D14: 7 | E14: PORTUGAL | F14: 3.1 - Payment, Cash, Settlement, Clearing, Custody: Payment services to MFIs | G14: TRUE
C15: 999 | D15: 8 | E15: PORTUGAL | F15: 3.1 - Payment, Cash, Settlement, Clearing, Custody: Payment services to MFIs | G15: TRUE
C16: 999 | D16: 9 | E16: PORTUGAL | F16: 3.1 - Payment, Cash, Settlement, Clearing, Custody: Payment services to MFIs | G16: TRUE
C17: 999 | D17: 4 | E17: PORTUGAL | F17: 3.1 - Payment, Cash, Settlement, Clearing, Custody: Payment services to MFIs | G17: TRUE
C18: 999 | D18: 5 | E18: PORTUGAL | F18: 3.1 - Payment, Cash, Settlement, Clearing, Custody: Payment services to MFIs | G18: TRUE
C19: 999 | D19: 6 | E19: PORTUGAL | F19: 3.1 - Payment, Cash, Settlement, Clearing, Custody: Payment services to MFIs | G19: TRUE
C20: 999 | D20: 7 | E20: PORTUGAL | F20: 3.1 - Payment, Cash, Settlement, Clearing, Custody: Payment services to MFIs | G20: TRUE
... C34: 999 | D34: 9 | E34: PORTUGAL | F34: 3.2 - Payment, Cash, Settlement, Clearing, Custody: Payment services to non-MFIs | G34: TRUE

Sheet T 32.00
A1: T 32.00 - FMI services - Mapping to core business lines
D4: Columns
D5: ID representing combination of user, system type, FMI and intermediary | E5: Core business line | F5: Core business line ID | G5: Link (true)
D6: 0010 | E6: 0020 | F6: 0030 | G6: 0040
A7: Rows | B7: Users, FMIs and intermediaries - core business lines | C7: 999 | D7: 1 | E7: Corporate Investment Banking (CIB) | F7: BL04CIB | G7: TRUE
C8: 999 | D8: 2 | E8: Commercial banking - Retail;Commercial banking - SMEs;Commercial banking - Corporate;Corporate Investment Banking (CIB) | F8: BL01RET;BL02SME;BL03CORP;BL04CIB | G8: TRUE
C9: 999 | D9: 3 | E9: Corporate Investment Banking (CIB) | F9: BL04CIB | G9: TRUE
C10: 999 | D10: 4 | E10: Commercial banking - Retail;Commercial banking - SMEs;Commercial banking - Corporate;Corporate Investment Banking (CIB) | F10: BL01RET;BL02SME;BL03CORP;BL04CIB | G10: TRUE
C11: 999 | D11: 5 | E11: Commercial banking - Retail;Commercial banking - SMEs;Commercial banking - Corporate;Corporate Investment Banking (CIB) | F11: BL01RET;BL02SME;BL03CORP;BL04CIB | G11: TRUE
C12: 999 | D12: 6 | E12: Commercial banking - Retail;Commercial banking - SMEs;Commercial banking - Corporate;Corporate Investment Banking (CIB) | F12: BL01RET;BL02SME;BL03CORP;BL04CIB | G12: TRUE
C13: 999 | D13: 7 | E13: Commercial banking - Retail;Commercial banking - SMEs;Commercial banking - Corporate;Corporate Investment Banking (CIB) | F13: BL01RET;BL02SME;BL03CORP;BL04CIB | G13: TRUE
C14: 999 | D14: 8 | E14: Commercial banking - Retail;Commercial banking - SMEs;Commercial banking - Corporate;Corporate Investment Banking (CIB) | F14: BL01RET;BL02SME;BL03CORP;BL04CIB | G14: TRUE
C15: 999 | D15: 9 | E15: Commercial banking - Retail;Commercial banking - SMEs;Commercial banking - Corporate;Corporate Investment Banking (CIB) | F15: BL01RET;BL02SME;BL03CORP;BL04CIB | G15: TRUE

Sheet T 33.00
A1: T 33.00 - FMI services - Key metrics
D4: Columns
D5: ID representing combination of user, system type, FMI and intermediary | E5: Segment (only for CCPs) | F5: Key metrics | Q5: Reference period for averages (if different from instructions)
F6: Contribution to default fund | G6: Value of positions on proprietary accounts | H6: Value of positions on client omnibus accounts | I6: Value of positions on client segregated accounts | J6: Number of clients covered by omnibus accounts | K6: Number of clients covered by segregated accounts | L6: Value of transactions on proprietary accounts | M6: Value of transactions on client accounts | N6: Credit line | O6: Peak of (intraday) liquidity or collateral requirements | P6: Estimated additional liquidity or collateral requirements in a stress situation | Q6: First day | R6: Last day
D7: 0010 | E7: 0020 | F7: 0030 | G7: 0040 | H7: 0050 | I7: 0060 | J7: 0070 | K7: 0080 | L7: 0090 | M7: 0100 | N7: 0110 | O7: 0120 | P7: 0130 | Q7: 0140 | R7: 0150
A8: Rows | B8: Users, FMIs and intermediaries - Key metrics | C8: 999 | D8: =+'[1]T 33.00'!D8 -> 1 | E8: =+'[1]T 33.00'!E8 -> Derivatives | F8: =+'[1]T 33.00'!F8 -> 0 | G8: 0 | H8: 0 | I8: 0 | J8: 0 | K8: 0 | L8: 1.6493655e+10 | M8: 6.9331139e+08 | N8: 0 | O8: 0 | P8: 2.3088965e+08 | Q8: 2022-01-01 | R8: 2022-12-31 | S8: =+'T 30.00'!H10 -> LCH SA | T8: 0.02 | U8: =+M8*T8 -> 13866228 | V8: =+U8+U10 -> 40185307
C9: 999 | D9: =+'[1]T 33.00'!D9 -> 2 | E9: =+'[1]T 33.00'!E9 -> NA | F9: =+'[1]T 33.00'!F9 -> 0 | G9: 3.6551878e+09 | H9: 0 | I9: 2.7354714e+11 | J9: 0 | K9: 0 | L9: 1.4290048e+10 | M9: 5.6274262e+08 | N9: 0 | O9: 0 | P9: 0 | Q9: 2022-01-01 | R9: 2022-12-31 | S9: =+'T 30.00'!H11 -> INTERBOLSA | T9: 0.07 | U9: =+M9*T9 -> 39391983
C10: 999 | D10: =+'[1]T 33.00'!D10 -> 3 | E10: =+'[1]T 33.00'!E10 -> NA | F10: =+'[1]T 33.00'!F10 -> 0 | G10: 1.6473004e+10 | H10: 0 | I10: 4.2957581e+09 | J10: 0 | K10: 0 | L10: 2.8270244e+09 | M10: 1.7546053e+09 | N10: 0 | O10: 0 | P10: 12152087 | Q10: 2022-01-01 | R10: 2022-12-31 | S10: =+'T 30.00'!H12 -> Euroclear Bank | T10: 0.015 | U10: =+M10*T10 -> 26319080
C11: 999 | D11: =+'[1]T 33.00'!D11 -> 4 | E11: =+'[1]T 33.00'!E11 -> NA | F11: =+'[1]T 33.00'!F11 -> 0 | G11: 0 | H11: 0 | I11: 0 | J11: 0 | K11: 0 | L11: 34602834 | M11: 2.5306953e+08 | N11: 130000000 | O11: 0 | P11: 0 | Q11: 2022-01-01 | R11: 2022-12-31 | S11: =+'T 30.00'!H13 -> EURO 1
C12: 999 | D12: =+'[1]T 33.00'!D12 -> 5 | E12: =+'[1]T 33.00'!E12 -> NA | F12: =+'[1]T 33.00'!F12 -> 0 | G12: 0 | H12: 0 | I12: 0 | J12: 0 | K12: 0 | L12: 0 | M12: 7.4095622e+10 | N12: 130000000 | O12: 0 | P12: 0 | Q12: 2022-01-01 | R12: 2022-12-31 | S12: =+'T 30.00'!H14 -> SICOI
C13: 999 | D13: =+'[1]T 33.00'!D13 -> 6 | E13: =+'[1]T 33.00'!E13 -> NA | F13: =+'[1]T 33.00'!F13 -> 0 | G13: 0 | H13: 0 | I13: 0 | J13: 0 | K13: 0 | L13: 0 | M13: 2.8808586e+10 | N13: 130000000 | O13: 0 | P13: 0 | Q13: 2022-01-01 | R13: 2022-12-31 | S13: =+'T 30.00'!H15 -> STEP 2
C14: 999 | D14: =+'[1]T 33.00'!D14 -> 7 | E14: =+'[1]T 33.00'!E14 -> NA | F14: =+'[1]T 33.00'!F14 -> 0 | G14: 0 | H14: 0 | I14: 0 | J14: 0 | K14: 0 | L14: 7298708.2 | M14: 6.1349793e+08 | N14: 130000000 | O14: 0 | P14: 0 | Q14: 2022-01-01 | R14: 2022-12-31 | S14: =+'T 30.00'!H16 -> STEP 1
C15: 999 | D15: =+'[1]T 33.00'!D15 -> 8 | E15: =+'[1]T 33.00'!E15 -> NA | F15: =+'[1]T 33.00'!F15 -> 0 | G15: 0 | H15: 0 | I15: 0 | J15: 0 | K15: 0 | L15: 2.4021762e+10 | M15: 5.4392215e+10 | N15: 130000000 | O15: 0 | P15: 0 | Q15: 2022-01-01 | R15: 2022-12-31 | S15: =+'T 30.00'!H17 -> TARGET2
C16: 999 | D16: =+'[1]T 33.00'!D16 -> 9 | E16: =+'[1]T 33.00'!E16 -> NA | F16: =+'[1]T 33.00'!F16 -> 0 | G16: 0 | H16: 0 | I16: 0 | J16: 0 | K16: 0 | L16: 0 | M16: 5708516.1 | N16: 0 | O16: 0 | P16: 0 | Q16: 2022-01-01 | R16: 2022-12-31 | S16: =+'T 30.00'!H18 -> TARGET2
