Workbook
Name RefDateCell: '1. Dashboard'!$D$12

Sheet Instruções
B6: Instruções
C8: 1.
C9: 2.
C10: 3.

Sheet Param_RefDate
A1: Param_RefDate
A2: 2025-10-31

Sheet 1. Dashboard
B6: 1 Dashboard
B9: Controlos Reporte Bail-in
C12: Data de referência | D12: 2025-10-31
D15: MENU 1 | G15: MENU 2 | J15: NAVEGADOR
D18: TABELAS OUTPUT | G18: Processo (HUE vs CSV) | J18: Processo (HUE vs CSV)
D20: 1. Gerar Controlos | E20: [BOTÃO] | G20: 1. Gerar Controlos | H20: [BOTÃO] | J20: 1. Detalhe controlos às tabelas output | L20: [LINK]
J22: 2. Detalhe controlos ao processo (CSV) | L22: [LINK]
H29: DASHBOARD
C32: 1. Reconciliação
C59: 2. Tabelas Output
G61: NOK
C62: Mapa | D62: Total (#) | E62: OK (#) | F62: OK (%) | G62: Justificados(#) | H62: Justificados (%) | I62: Não Justificados(#) | J62: Não Justificados (%)
C63: B02.00 | D63: =+SUM(D64,D68) -> 233 | E63: =+SUM(E64,E68) -> 203 | F63: =IFERROR(E63/D63,0) -> 0.87124464 | G63: =+SUM(G64,G68) -> 6 | H63: =IFERROR(G63/D63,0) -> 0.025751073 | I63: =+SUM(I64,I68) -> 24 | J63: =IFERROR(I63/D63,0) -> 0.10300429
C64: Regulamentares (SRB) | D64: =+SUM(D65:D67) -> 151 | E64: =+SUM(E65:E67) -> 128 | F64: =IFERROR(E64/D64,0) -> 0.84768212 | G64: =+SUM(G65:G67) -> 6 | H64: =IFERROR(G64/D64,0) -> 0.039735099 | I64: =+SUM(I65:I67) -> 17 | J64: =IFERROR(I64/D64,0) -> 0.11258278
C65: High severity | D65: =+COUNTIFS('2.1. Controlos'!J:J,"BU_LOANTAPE_WORK.OUT_B0200_MAIN_LIABILITIES",'2.1. Controlos'!C:C,"H") -> 58 | E65: =+COUNTIFS('2.1. Controlos'!J:J,"BU_LOANTAPE_WORK.OUT_B0200_MAIN_LIABILITIES",'2.1. Controlos'!C:C,"H",'2.1. Controlos'!M:M,0) -> 52 | F65: =IFERROR(E65/D65,0) -> 0.89655172 | G65: =+COUNTIFS('2.1. Controlos'!J:J,"BU_LOANTAPE_WORK.OUT_B0200_MAIN_LIABILITIES",'2.1. Controlos'!C:C,"H",'2.1. Controlos'!M:M,">0",'2.1. Controlos'!P:P,"<>") -> 0 | H65: =IFERROR(G65/D65,0) -> 0 | I65: =+COUNTIFS('2.1. Controlos'!J:J,"BU_LOANTAPE_WORK.OUT_B0200_MAIN_LIABILITIES",'2.1. Controlos'!C:C,"H",'2.1. Controlos'!M:M,">0",'2.1. Controlos'!P:P,"") -> 6 | J65: =IFERROR(I65/D65,0) -> 0.10344828
C66: Warnings | D66: =+COUNTIFS('2.1. Controlos'!J:J,"BU_LOANTAPE_WORK.OUT_B0200_MAIN_LIABILITIES",'2.1. Controlos'!C:C,"W") -> 12 | E66: =+COUNTIFS('2.1. Controlos'!J:J,"BU_LOANTAPE_WORK.OUT_B0200_MAIN_LIABILITIES",'2.1. Controlos'!C:C,"W",'2.1. Controlos'!M:M,0) -> 10 | F66: =IFERROR(E66/D66,0) -> 0.83333333 | G66: =+COUNTIFS('2.1. Controlos'!J:J,"BU_LOANTAPE_WORK.OUT_B0200_MAIN_LIABILITIES",'2.1. Controlos'!C:C,"W",'2.1. Controlos'!M:M,">0",'2.1. Controlos'!P:P,"<>") -> 0 | H66: =IFERROR(G66/D66,0) -> 0 | I66: =+COUNTIFS('2.1. Controlos'!J:J,"BU_LOANTAPE_WORK.OUT_B0200_MAIN_LIABILITIES",'2.1. Controlos'!C:C,"W",'2.1. Controlos'!M:M,">0",'2.1. Controlos'!P:P,"") -> 2 | J66: =IFERROR(I66/D66,0) -> 0.16666667
C67: Formatos | D67: =+COUNTIFS('2.1. Controlos'!J:J,"BU_LOANTAPE_WORK.OUT_B0200_MAIN_LIABILITIES",'2.1. Controlos'!C:C,"F") -> 81 | E67: =+COUNTIFS('2.1. Controlos'!J:J,"BU_LOANTAPE_WORK.OUT_B0200_MAIN_LIABILITIES",'2.1. Controlos'!C:C,"F",'2.1. Controlos'!M:M,0) -> 66 | F67: =IFERROR(E67/D67,0) -> 0.81481481 | G67: =+COUNTIFS('2.1. Controlos'!J:J,"BU_LOANTAPE_WORK.OUT_B0200_MAIN_LIABILITIES",'2.1. Controlos'!C:C,"F",'2.1. Controlos'!M:M,">0",'2.1. Controlos'!P:P,"<>") -> 6 | H67: =IFERROR(G67/D67,0) -> 0.074074074 | I67: =+COUNTIFS('2.1. Controlos'!J:J,"BU_LOANTAPE_WORK.OUT_B0200_MAIN_LIABILITIES",'2.1. Controlos'!C:C,"F",'2.1. Controlos'!M:M,">0",'2.1. Controlos'!P:P,"") -> 9 | J67: =IFERROR(I67/D67,0) -> 0.11111111
C68: Outros | D68: =+SUM(D69:D72) -> 82 | E68: =+SUM(E69:E72) -> 75 | F68: =IFERROR(E68/D68,0) -> 0.91463415 | G68: =+SUM(G69:G72) -> 0 | H68: =IFERROR(G68/D68,0) -> 0 | I68: =+SUM(I69:I72) -> 7 | J68: =IFERROR(I68/D68,0) -> 0.085365854
C69: Validade (Missings/NULLS) | D69: =+COUNTIFS('2.1. Controlos'!J:J,"BU_LOANTAPE_WORK.OUT_B0200_MAIN_LIABILITIES",'2.1. Controlos'!H:H,"MISSINGS") -> 81 | E69: =+COUNTIFS('2.1. Controlos'!J:J,"BU_LOANTAPE_WORK.OUT_B0200_MAIN_LIABILITIES",'2.1. Controlos'!H:H,"MISSINGS",'2.1. Controlos'!M:M,0) -> 74 | F69: =IFERROR(E69/D69,0) -> 0.91358025 | G69: =+COUNTIFS('2.1. Controlos'!J:J,"BU_LOANTAPE_WORK.OUT_B0200_MAIN_LIABILITIES",'2.1. Controlos'!H:H,"MISSINGS",'2.1. Controlos'!M:M,">0",'2.1. Controlos'!P:P,"<>") -> 0 | H69: =IFERROR(G69/D69,0) -> 0 | I69: =+COUNTIFS('2.1. Controlos'!J:J,"BU_LOANTAPE_WORK.OUT_B0200_MAIN_LIABILITIES",'2.1. Controlos'!H:H,"MISSINGS",'2.1. Controlos'!M:M,">0",'2.1. Controlos'!P:P,"") -> 7 | J69: =IFERROR(I69/D69,0) -> 0.086419753
C70: Not applicables | F70: =IFERROR(E70/D70,0) -> 0 | H70: =IFERROR(G70/D70,0) -> 0 | J70: =IFERROR(I70/D70,0) -> 0
C71: Duplicados | D71: =+COUNTIFS('2.1. Controlos'!J:J,"BU_LOANTAPE_WORK.OUT_B0200_MAIN_LIABILITIES",'2.1. Controlos'!H:H,"DUPLICADOS") -> 1 | E71: =+COUNTIFS('2.1. Controlos'!J:J,"BU_LOANTAPE_WORK.OUT_B0200_MAIN_LIABILITIES",'2.1. Controlos'!H:H,"DUPLICADOS",'2.1. Controlos'!M:M,0) -> 1 | F71: =IFERROR(E71/D71,0) -> 1 | G71: =+COUNTIFS('2.1. Controlos'!J:J,"BU_LOANTAPE_WORK.OUT_B0200_MAIN_LIABILITIES",'2.1. Controlos'!H:H,"DUPLICADOS",'2.1. Controlos'!M:M,">0",'2.1. Controlos'!P:P,"<>") -> 0 | H71: =IFERROR(G71/D71,0) -> 0 | I71: =+COUNTIFS('2.1. Controlos'!J:J,"BU_LOANTAPE_WORK.OUT_B0200_MAIN_LIABILITIES",'2.1. Controlos'!H:H,"DUPLICADOS",'2.1. Controlos'!M:M,">0",'2.1. Controlos'!P:P,"") -> 0 | J71: =IFERROR(I71/D71,0) -> 0
C72: Integridade entre tabelas | F72: =IFERROR(E72/D72,0) -> 0 | H72: =IFERROR(G72/D72,0) -> 0 | J72: =IFERROR(I72/D72,0) -> 0
C73: B05.00 | D73: =+SUM(D74,D78) -> 36 | E73: =+SUM(E74,E78) -> 32 | F73: =IFERROR(E73/D73,0) -> 0.88888889 | G73: =+SUM(G74,G78) -> 2 | H73: =IFERROR(G73/D73,0) -> 0.055555556 | I73: =+SUM(I74,I78) -> 2 | J73: =IFERROR(I73/D73,0) -> 0.055555556
C74: Regulamentares (SRB) | D74: =+SUM(D75:D77) -> 20 | E74: =+SUM(E75:E77) -> 17 | F74: =IFERROR(E74/D74,0) -> 0.85 | G74: =+SUM(G75:G77) -> 2 | H74: =IFERROR(G74/D74,0) -> 0.1 | I74: =+SUM(I75:I77) -> 1 | J74: =IFERROR(I74/D74,0) -> 0.05
C75: High severity | D75: =+COUNTIFS('2.1. Controlos'!J:J,"BU_LOANTAPE_WORK.OUT_B0500_GUARANTEES",'2.1. Controlos'!C:C,"H") -> 5 | E75: =+COUNTIFS('2.1. Controlos'!J:J,"BU_LOANTAPE_WORK.OUT_B0500_GUARANTEES",'2.1. Controlos'!C:C,"H",'2.1. Controlos'!M:M,0) -> 4 | F75: =IFERROR(E75/D75,0) -> 0.8 | G75: =+COUNTIFS('2.1. Controlos'!J:J,"BU_LOANTAPE_WORK.OUT_B0500_GUARANTEES",'2.1. Controlos'!C:C,"H",'2.1. Controlos'!M:M,">0",'2.1. Controlos'!P:P,"<>") -> 0 | H75: =IFERROR(G75/D75,0) -> 0 | I75: =+COUNTIFS('2.1. Controlos'!J:J,"BU_LOANTAPE_WORK.OUT_B0500_GUARANTEES",'2.1. Controlos'!C:C,"H",'2.1. Controlos'!M:M,">0",'2.1. Controlos'!P:P,"") -> 1 | J75: =IFERROR(I75/D75,0) -> 0.2
C76: Warnings | D76: =+COUNTIFS('2.1. Controlos'!J:J,"BU_LOANTAPE_WORK.OUT_B0500_GUARANTEES",'2.1. Controlos'!C:C,"W") -> 0 | E76: =+COUNTIFS('2.1. Controlos'!J:J,"BU_LOANTAPE_WORK.OUT_B0500_GUARANTEES",'2.1. Controlos'!C:C,"W",'2.1. Controlos'!M:M,0) -> 0 | F76: =IFERROR(E76/D76,0) -> 0 | G76: =+COUNTIFS('2.1. Controlos'!J:J,"BU_LOANTAPE_WORK.OUT_B0500_GUARANTEES",'2.1. Controlos'!C:C,"W",'2.1. Controlos'!M:M,">0",'2.1. Controlos'!P:P,"<>") -> 0 | H76: =IFERROR(G76/D76,0) -> 0 | I76: =+COUNTIFS('2.1. Controlos'!J:J,"BU_LOANTAPE_WORK.OUT_B0500_GUARANTEES",'2.1. Controlos'!C:C,"W",'2.1. Controlos'!M:M,">0",'2.1. Controlos'!P:P,"") -> 0 | J76: =IFERROR(I76/D76,0) -> 0
C77: Formatos | D77: =+COUNTIFS('2.1. Controlos'!J:J,"BU_LOANTAPE_WORK.OUT_B0500_GUARANTEES",'2.1. Controlos'!C:C,"F") -> 15 | E77: =+COUNTIFS('2.1. Controlos'!J:J,"BU_LOANTAPE_WORK.OUT_B0500_GUARANTEES",'2.1. Controlos'!C:C,"F",'2.1. Controlos'!M:M,0) -> 13 | F77: =IFERROR(E77/D77,0) -> 0.86666667 | G77: =+COUNTIFS('2.1. Controlos'!J:J,"BU_LOANTAPE_WORK.OUT_B0500_GUARANTEES",'2.1. Controlos'!C:C,"F",'2.1. Controlos'!M:M,">0",'2.1. Controlos'!P:P,"<>") -> 2 | H77: =IFERROR(G77/D77,0) -> 0.13333333 | I77: =+COUNTIFS('2.1. Controlos'!J:J,"BU_LOANTAPE_WORK.OUT_B0500_GUARANTEES",'2.1. Controlos'!C:C,"F",'2.1. Controlos'!M:M,">0",'2.1. Controlos'!P:P,"") -> 0 | J77: =IFERROR(I77/D77,0) -> 0
C78: Outros | D78: =+SUM(D79:D82) -> 16 | E78: =+SUM(E79:E82) -> 15 | F78: =IFERROR(E78/D78,0) -> 0.9375 | G78: =+SUM(G79:G82) -> 0 | H78: =IFERROR(G78/D78,0) -> 0 | I78: =+SUM(I79:I82) -> 1 | J78: =IFERROR(I78/D78,0) -> 0.0625
C79: Validade (Missings/NULLS) | D79: =+COUNTIFS('2.1. Controlos'!J:J,"BU_LOANTAPE_WORK.OUT_B0500_GUARANTEES",'2.1. Controlos'!H:H,"MISSINGS") -> 15 | E79: =+COUNTIFS('2.1. Controlos'!J:J,"BU_LOANTAPE_WORK.OUT_B0500_GUARANTEES",'2.1. Controlos'!H:H,"MISSINGS",'2.1. Controlos'!M:M,0) -> 14 | F79: =IFERROR(E79/D79,0) -> 0.93333333 | G79: =+COUNTIFS('2.1. Controlos'!J:J,"BU_LOANTAPE_WORK.OUT_B0500_GUARANTEES",'2.1. Controlos'!H:H,"MISSINGS",'2.1. Controlos'!M:M,">0",'2.1. Controlos'!P:P,"<>") -> 0 | H79: =IFERROR(G79/D79,0) -> 0 | I79: =+COUNTIFS('2.1. Controlos'!J:J,"BU_LOANTAPE_WORK.OUT_B0500_GUARANTEES",'2.1. Controlos'!H:H,"MISSINGS",'2.1. Controlos'!M:M,">0",'2.1. Controlos'!P:P,"") -> 1 | J79: =IFERROR(I79/D79,0) -> 0.066666667
C80: Not applicables | F80: =IFERROR(E80/D80,0) -> 0 | H80: =IFERROR(G80/D80,0) -> 0 | J80: =IFERROR(I80/D80,0) -> 0
C81: Duplicados | D81: =+COUNTIFS('2.1. Controlos'!J:J,"BU_LOANTAPE_WORK.OUT_B0500_GUARANTEES",'2.1. Controlos'!H:H,"DUPLICADOS") -> 1 | E81: =+COUNTIFS('2.1. Controlos'!J:J,"BU_LOANTAPE_WORK.OUT_B0500_GUARANTEES",'2.1. Controlos'!H:H,"DUPLICADOS",'2.1. Controlos'!M:M,0) -> 1 | F81: =IFERROR(E81/D81,0) -> 1 | G81: =+COUNTIFS('2.1. Controlos'!J:J,"BU_LOANTAPE_WORK.OUT_B0500_GUARANTEES",'2.1. Controlos'!H:H,"DUPLICADOS",'2.1. Controlos'!M:M,">0",'2.1. Controlos'!P:P,"<>") -> 0 | H81: =IFERROR(G81/D81,0) -> 0 | I81: =+COUNTIFS('2.1. Controlos'!J:J,"BU_LOANTAPE_WORK.OUT_B0500_GUARANTEES",'2.1. Controlos'!H:H,"DUPLICADOS",'2.1. Controlos'!M:M,">0",'2.1. Controlos'!P:P,"") -> 0 | J81: =IFERROR(I81/D81,0) -> 0
C82: Integridade entre tabelas | F82: =IFERROR(E82/D82,0) -> 0 | H82: =IFERROR(G82/D82,0) -> 0 | J82: =IFERROR(I82/D82,0) -> 0
C83: B90.00 | D83: =+SUM(D84,D88) -> 27 | E83: =+SUM(E84,E88) -> 20 | F83: =IFERROR(E83/D83,0) -> 0.74074074 | G83: =+SUM(G84,G88) -> 2 | H83: =IFERROR(G83/D83,0) -> 0.074074074 | I83: =+SUM(I84,I88) -> 5 | J83: =IFERROR(I83/D83,0) -> 0.18518519
C84: Regulamentares (SRB) | D84: =+SUM(D85:D87) -> 15 | E84: =+SUM(E85:E87) -> 11 | F84: =IFERROR(E84/D84,0) -> 0.73333333 | G84: =+SUM(G85:G87) -> 2 | H84: =IFERROR(G84/D84,0) -> 0.13333333 | I84: =+SUM(I85:I87) -> 2 | J84: =IFERROR(I84/D84,0) -> 0.13333333
C85: High severity | D85: =+COUNTIFS('2.1. Controlos'!J:J,"BU_LOANTAPE_WORK.OUT_B9000_COUNTERPARTIES",'2.1. Controlos'!C:C,"H") -> 4 | E85: =+COUNTIFS('2.1. Controlos'!J:J,"BU_LOANTAPE_WORK.OUT_B9000_COUNTERPARTIES",'2.1. Controlos'!C:C,"H",'2.1. Controlos'!M:M,0) -> 2 | F85: =IFERROR(E85/D85,0) -> 0.5 | G85: =+COUNTIFS('2.1. Controlos'!J:J,"BU_LOANTAPE_WORK.OUT_B9000_COUNTERPARTIES",'2.1. Controlos'!C:C,"H",'2.1. Controlos'!M:M,">0",'2.1. Controlos'!P:P,"<>") -> 1 | H85: =IFERROR(G85/D85,0) -> 0.25 | I85: =+COUNTIFS('2.1. Controlos'!J:J,"BU_LOANTAPE_WORK.OUT_B9000_COUNTERPARTIES",'2.1. Controlos'!C:C,"H",'2.1. Controlos'!M:M,">0",'2.1. Controlos'!P:P,"") -> 1 | J85: =IFERROR(I85/D85,0) -> 0.25
C86: Warnings | D86: =+COUNTIFS('2.1. Controlos'!J:J,"BU_LOANTAPE_WORK.OUT_B9000_COUNTERPARTIES",'2.1. Controlos'!C:C,"W") -> 0 | E86: =+COUNTIFS('2.1. Controlos'!J:J,"BU_LOANTAPE_WORK.OUT_B9000_COUNTERPARTIES",'2.1. Controlos'!C:C,"W",'2.1. Controlos'!M:M,0) -> 0 | F86: =IFERROR(E86/D86,0) -> 0 | G86: =+COUNTIFS('2.1. Controlos'!J:J,"BU_LOANTAPE_WORK.OUT_B9000_COUNTERPARTIES",'2.1. Controlos'!C:C,"W",'2.1. Controlos'!M:M,">0",'2.1. Controlos'!P:P,"<>") -> 0 | H86: =IFERROR(G86/D86,0) -> 0 | I86: =+COUNTIFS('2.1. Controlos'!J:J,"BU_LOANTAPE_WORK.OUT_B9000_COUNTERPARTIES",'2.1. Controlos'!C:C,"W",'2.1. Controlos'!M:M,">0",'2.1. Controlos'!P:P,"") -> 0 | J86: =IFERROR(I86/D86,0) -> 0
C87: Formatos | D87: =+COUNTIFS('2.1. Controlos'!J:J,"BU_LOANTAPE_WORK.OUT_B9000_COUNTERPARTIES",'2.1. Controlos'!C:C,"F") -> 11 | E87: =+COUNTIFS('2.1. Controlos'!J:J,"BU_LOANTAPE_WORK.OUT_B9000_COUNTERPARTIES",'2.1. Controlos'!C:C,"F",'2.1. Controlos'!M:M,0) -> 9 | F87: =IFERROR(E87/D87,0) -> 0.81818182 | G87: =+COUNTIFS('2.1. Controlos'!J:J,"BU_LOANTAPE_WORK.OUT_B9000_COUNTERPARTIES",'2.1. Controlos'!C:C,"F",'2.1. Controlos'!M:M,">0",'2.1. Controlos'!P:P,"<>") -> 1 | H87: =IFERROR(G87/D87,0) -> 0.090909091 | I87: =+COUNTIFS('2.1. Controlos'!J:J,"BU_LOANTAPE_WORK.OUT_B9000_COUNTERPARTIES",'2.1. Controlos'!C:C,"F",'2.1. Controlos'!M:M,">0",'2.1. Controlos'!P:P,"") -> 1 | J87: =IFERROR(I87/D87,0) -> 0.090909091
C88: Outros | D88: =+SUM(D89:D92) -> 12 | E88: =+SUM(E89:E92) -> 9 | F88: =IFERROR(E88/D88,0) -> 0.75 | G88: =+SUM(G89:G92) -> 0 | H88: =IFERROR(G88/D88,0) -> 0 | I88: =+SUM(I89:I92) -> 3 | J88: =IFERROR(I88/D88,0) -> 0.25
C89: Validade (Missings/NULLS) | D89: =+COUNTIFS('2.1. Controlos'!J:J,"BU_LOANTAPE_WORK.OUT_B9000_COUNTERPARTIES",'2.1. Controlos'!H:H,"MISSINGS") -> 11 | E89: =+COUNTIFS('2.1. Controlos'!J:J,"BU_LOANTAPE_WORK.OUT_B9000_COUNTERPARTIES",'2.1. Controlos'!H:H,"MISSINGS",'2.1. Controlos'!M:M,0) -> 8 | F89: =IFERROR(E89/D89,0) -> 0.72727273 | G89: =+COUNTIFS('2.1. Controlos'!J:J,"BU_LOANTAPE_WORK.OUT_B9000_COUNTERPARTIES",'2.1. Controlos'!H:H,"MISSINGS",'2.1. Controlos'!M:M,">0",'2.1. Controlos'!P:P,"<>") -> 0 | H89: =IFERROR(G89/D89,0) -> 0 | I89: =+COUNTIFS('2.1. Controlos'!J:J,"BU_LOANTAPE_WORK.OUT_B9000_COUNTERPARTIES",'2.1. Controlos'!H:H,"MISSINGS",'2.1. Controlos'!M:M,">0",'2.1. Controlos'!P:P,"") -> 3 | J89: =IFERROR(I89/D89,0) -> 0.27272727
C90: Not applicables | F90: =IFERROR(E90/D90,0) -> 0 | H90: =IFERROR(G90/D90,0) -> 0 | J90: =IFERROR(I90/D90,0) -> 0
C91: Duplicados | D91: =+COUNTIFS('2.1. Controlos'!J:J,"BU_LOANTAPE_WORK.OUT_B9000_COUNTERPARTIES",'2.1. Controlos'!H:H,"DUPLICADOS") -> 1 | E91: =+COUNTIFS('2.1. Controlos'!J:J,"BU_LOANTAPE_WORK.OUT_B9000_COUNTERPARTIES",'2.1. Controlos'!H:H,"DUPLICADOS",'2.1. Controlos'!M:M,0) -> 1 | F91: =IFERROR(E91/D91,0) -> 1 | G91: =+COUNTIFS('2.1. Controlos'!J:J,"BU_LOANTAPE_WORK.OUT_B9000_COUNTERPARTIES",'2.1. Controlos'!H:H,"DUPLICADOS",'2.1. Controlos'!M:M,">0",'2.1. Controlos'!P:P,"<>") -> 0 | H91: =IFERROR(G91/D91,0) -> 0 | I91: =+COUNTIFS('2.1. Controlos'!J:J,"BU_LOANTAPE_WORK.OUT_B9000_COUNTERPARTIES",'2.1. Controlos'!H:H,"DUPLICADOS",'2.1. Controlos'!M:M,">0",'2.1. Controlos'!P:P,"") -> 0 | J91: =IFERROR(I91/D91,0) -> 0
C92: Integridade entre tabelas | F92: =IFERROR(E92/D92,0) -> 0 | H92: =IFERROR(G92/D92,0) -> 0 | J92: =IFERROR(I92/D92,0) -> 0
C93: Total | D93: =SUM(D83,D73,D63) -> 296 | E93: =SUM(E83,E73,E63) -> 255 | F93: =IFERROR(E93/D93,0) -> 0.86148649 | G93: =SUM(G83,G73,G63) -> 10 | H93: =IFERROR(G93/D93,0) -> 0.033783784 | I93: =SUM(I83,I73,I63) -> 31 | J93: =IFERROR(I93/D93,0) -> 0.10472973
C96: 3. Processo (HUE vs CSV)
C98: Mapa | D98: Total (#) | E98: OK (#) | F98: OK (%) | G98: NOK Justificados(#) | H98: NOK Justificados (%) | I98: NOK (#) | J98: NOK (%)
C99: B02.00 | D99: =+D100 -> 20 | E99: =+E100 -> 16 | F99: =+E99/$D99 -> 0.8 | G99: =+G100 -> 3 | H99: =+G99/$D99 -> 0.15 | I99: =+I100 -> 1 | J99: =+I99/$D99 -> 0.05
C100: Coerência(Mapa vs. CSV) | D100: 20 | E100: 16 | F100: =+E100/$D100 -> 0.8 | G100: 3 | H100: =+G100/$D100 -> 0.15 | I100: 1 | J100: =+I100/$D100 -> 0.05
C101: B05.00 | D101: =+D102 -> 15 | E101: =+E102 -> 10 | F101: =+E101/$D101 -> 0.66666667 | G101: =+G102 -> 2 | H101: =+G101/$D101 -> 0.13333333 | I101: =+I102 -> 3 | J101: =+I101/$D101 -> 0.2
C102: Coerência(Mapa vs. CSV) | D102: 15 | E102: 10 | F102: =+E102/$D102 -> 0.66666667 | G102: 2 | H102: =+G102/$D102 -> 0.13333333 | I102: 3 | J102: =+I102/$D102 -> 0.2
C103: B90.00 | D103: =+D104 -> 20 | E103: =+E104 -> 12 | F103: =+E103/$D103 -> 0.6 | G103: =+G104 -> 4 | H103: =+G103/$D103 -> 0.2 | I103: =+I104 -> 4 | J103: =+I103/$D103 -> 0.2
C104: Coerência(Mapa vs. CSV) | D104: 20 | E104: 12 | F104: =+E104/$D104 -> 0.6 | G104: 4 | H104: =+G104/$D104 -> 0.2 | I104: 4 | J104: =+I104/$D104 -> 0.2

Sheet 2. Inputs -->

Sheet 2.1. Controlos
F6: 2.1. Controlos
B8: AUX_TAB | C8: AUX_SEVERITY | F8: ref_date | G8: cod_kpi | H8: tipologia_teste | I8: descrição | J8: tabela | K8: campo | L8: num_reg | M8: num_reg_dif | N8: detalhe | P8: Justificação
B9: =+IF(LEFT(MID(Controlos[[#This Row],[tabela]],22,5),1)="B",MID(Controlos[[#This Row],[tabela]],22,5),MID(Controlos[[#This Row],[tabela]],18,5)) -> B0200 | C9: =+IF(Controlos[[#This Row],[tipologia_teste]]="REGULAMENTAR",IF(LEFT(Controlos[[#This Row],[cod_kpi]],1)="v",IF(LEFT(Controlos[[#This Row],[descrição]],6)="Alerta","W","H"),"F"),0) -> 0 | F9: 2025-10-31 | G9: MIS_B0200_C0010 | H9: MISSINGS | I9: Validar que não existem registos por preencher (Missings) | J9: BU_LOANTAPE_WORK.OUT_B0200_MAIN_LIABILITIES | K9: 0010_ROW_NMBR | L9: 8 | M9: 0
B10: =+IF(LEFT(MID(Controlos[[#This Row],[tabela]],22,5),1)="B",MID(Controlos[[#This Row],[tabela]],22,5),MID(Controlos[[#This Row],[tabela]],18,5)) -> B0200 | C10: =+IF(Controlos[[#This Row],[tipologia_teste]]="REGULAMENTAR",IF(LEFT(Controlos[[#This Row],[cod_kpi]],1)="v",IF(LEFT(Controlos[[#This Row],[descrição]],6)="Alerta","W","H"),"F"),0) -> 0 | F10: 2025-10-31 | G10: MIS_B0200_C0020 | H10: MISSINGS | I10: Validar que não existem registos por preencher (Missings) | J10: BU_LOANTAPE_WORK.OUT_B0200_MAIN_LIABILITIES | K10: 0020_UNIQ_ID | L10: 8 | M10: 0
B11: =+IF(LEFT(MID(Controlos[[#This Row],[tabela]],22,5),1)="B",MID(Controlos[[#This Row],[tabela]],22,5),MID(Controlos[[#This Row],[tabela]],18,5)) -> B0200 | C11: =+IF(Controlos[[#This Row],[tipologia_teste]]="REGULAMENTAR",IF(LEFT(Controlos[[#This Row],[cod_kpi]],1)="v",IF(LEFT(Controlos[[#This Row],[descrição]],6)="Alerta","W","H"),"F"),0) -> 0 | F11: 2025-10-31 | G11: MIS_B0200_C0030 | H11: MISSINGS | I11: Validar que não existem registos por preencher (Missings) | J11: BU_LOANTAPE_WORK.OUT_B0200_MAIN_LIABILITIES | K11: 0030_UNIQ_ID_KNWN_CNTRPRTY | L11: 8 | M11: 0
B12: =+IF(LEFT(MID(Controlos[[#This Row],[tabela]],22,5),1)="B",MID(Controlos[[#This Row],[tabela]],22,5),MID(Controlos[[#This Row],[tabela]],18,5)) -> B0200 | C12: =+IF(Controlos[[#This Row],[tipologia_teste]]="REGULAMENTAR",IF(LEFT(Controlos[[#This Row],[cod_kpi]],1)="v",IF(LEFT(Controlos[[#This Row],[descrição]],6)="Alerta","W","H"),"F"),0) -> 0 | F12: 2025-10-31 | G12: MIS_B0200_C0040 | H12: MISSINGS | I12: Validar que não existem registos por preencher (Missings) | J12: BU_LOANTAPE_WORK.OUT_B0200_MAIN_LIABILITIES | K12: 0040_TYP_UNIQ_ID_KNWN_CNTRPRTY | L12: 8 | M12: 0
B13: =+IF(LEFT(MID(Controlos[[#This Row],[tabela]],22,5),1)="B",MID(Controlos[[#This Row],[tabela]],22,5),MID(Controlos[[#This Row],[tabela]],18,5)) -> B0200 | C13: =+IF(Controlos[[#This Row],[tipologia_teste]]="REGULAMENTAR",IF(LEFT(Controlos[[#This Row],[cod_kpi]],1)="v",IF(LEFT(Controlos[[#This Row],[descrição]],6)="Alerta","W","H"),"F"),0) -> 0 | F13: 2025-10-31 | G13: MIS_B0200_C0050 | H13: MISSINGS | I13: Validar que não existem registos por preencher (Missings) | J13: BU_LOANTAPE_WORK.OUT_B0200_MAIN_LIABILITIES | K13: 0050_ORGNL_AMNT_EUR | L13: 8 | M13: 0
B14: =+IF(LEFT(MID(Controlos[[#This Row],[tabela]],22,5),1)="B",MID(Controlos[[#This Row],[tabela]],22,5),MID(Controlos[[#This Row],[tabela]],18,5)) -> B0200 | C14: =+IF(Controlos[[#This Row],[tipologia_teste]]="REGULAMENTAR",IF(LEFT(Controlos[[#This Row],[cod_kpi]],1)="v",IF(LEFT(Controlos[[#This Row],[descrição]],6)="Alerta","W","H"),"F"),0) -> 0 | F14: 2025-10-31 | G14: MIS_B0200_C0060 | H14: MISSINGS | I14: Validar que não existem registos por preencher (Missings) | J14: BU_LOANTAPE_WORK.OUT_B0200_MAIN_LIABILITIES | K14: 0060_ORGNL_AMNT_FX | L14: 8 | M14: 0
B15: =+IF(LEFT(MID(Controlos[[#This Row],[tabela]],22,5),1)="B",MID(Controlos[[#This Row],[tabela]],22,5),MID(Controlos[[#This Row],[tabela]],18,5)) -> B0200 | C15: =+IF(Controlos[[#This Row],[tipologia_teste]]="REGULAMENTAR",IF(LEFT(Controlos[[#This Row],[cod_kpi]],1)="v",IF(LEFT(Controlos[[#This Row],[descrição]],6)="Alerta","W","H"),"F"),0) -> 0 | F15: 2025-10-31 | G15: MIS_B0200_C0070 | H15: MISSINGS | I15: Validar que não existem registos por preencher (Missings) | J15: BU_LOANTAPE_WORK.OUT_B0200_MAIN_LIABILITIES | K15: 0070_CNTRCT_CRRNCY | L15: 8 | M15: 0
B16: =+IF(LEFT(MID(Controlos[[#This Row],[tabela]],22,5),1)="B",MID(Controlos[[#This Row],[tabela]],22,5),MID(Controlos[[#This Row],[tabela]],18,5)) -> B0200 | C16: =+IF(Controlos[[#This Row],[tipologia_teste]]="REGULAMENTAR",IF(LEFT(Controlos[[#This Row],[cod_kpi]],1)="v",IF(LEFT(Controlos[[#This Row],[descrição]],6)="Alerta","W","H"),"F"),0) -> 0 | F16: 2025-10-31 | G16: MIS_B0200_C0080 | H16: MISSINGS | I16: Validar que não existem registos por preencher (Missings) | J16: BU_LOANTAPE_WORK.OUT_B0200_MAIN_LIABILITIES | K16: 0080_OTSTNDNG_PRNCPL_AMNT | L16: 8 | M16: 8 | N16: 31641600000000000PTBSREOM0028000; 31641600000000000PTSTOEOM0021000; 31641600000000000PTSTOFOM0004000; 31641600000000000PTSTOGOM0003000; 31641600000000000PTSTOHOM0002000; 31641600005800007PTBSRDOM0037000; 31641600005800007PTCPP0AM0007000; 31641600005800007PTSTOCOM0007000
B17: =+IF(LEFT(MID(Controlos[[#This Row],[tabela]],22,5),1)="B",MID(Controlos[[#This Row],[tabela]],22,5),MID(Controlos[[#This Row],[tabela]],18,5)) -> B0200 | C17: =+IF(Controlos[[#This Row],[tipologia_teste]]="REGULAMENTAR",IF(LEFT(Controlos[[#This Row],[cod_kpi]],1)="v",IF(LEFT(Controlos[[#This Row],[descrição]],6)="Alerta","W","H"),"F"),0) -> 0 | F17: 2025-10-31 | G17: MIS_B0200_C0090 | H17: MISSINGS | I17: Validar que não existem registos por preencher (Missings) | J17: BU_LOANTAPE_WORK.OUT_B0200_MAIN_LIABILITIES | K17: 0090_PRTN_AMNT_RPRTNG_ENTTY | L17: 8 | M17: 8 | N17: 31641600000000000PTBSREOM0028000; 31641600000000000PTSTOEOM0021000; 31641600000000000PTSTOFOM0004000; 31641600000000000PTSTOGOM0003000; 31641600000000000PTSTOHOM0002000; 31641600005800007PTBSRDOM0037000; 31641600005800007PTCPP0AM0007000; 31641600005800007PTSTOCOM0007000
B18: =+IF(LEFT(MID(Controlos[[#This Row],[tabela]],22,5),1)="B",MID(Controlos[[#This Row],[tabela]],22,5),MID(Controlos[[#This Row],[tabela]],18,5)) -> B0200 | C18: =+IF(Controlos[[#This Row],[tipologia_teste]]="REGULAMENTAR",IF(LEFT(Controlos[[#This Row],[cod_kpi]],1)="v",IF(LEFT(Controlos[[#This Row],[descrição]],6)="Alerta","W","H"),"F"),0) -> 0 | F18: 2025-10-31 | G18: MIS_B0200_C0100 | H18: MISSINGS | I18: Validar que não existem registos por preencher (Missings) | J18: BU_LOANTAPE_WORK.OUT_B0200_MAIN_LIABILITIES | K18: 0100_ACCRD_INTRST_INSTRMNT | L18: 8 | M18: 0
B19: =+IF(LEFT(MID(Controlos[[#This Row],[tabela]],22,5),1)="B",MID(Controlos[[#This Row],[tabela]],22,5),MID(Controlos[[#This Row],[tabela]],18,5)) -> B0200 | C19: =+IF(Controlos[[#This Row],[tipologia_teste]]="REGULAMENTAR",IF(LEFT(Controlos[[#This Row],[cod_kpi]],1)="v",IF(LEFT(Controlos[[#This Row],[descrição]],6)="Alerta","W","H"),"F"),0) -> 0 | F19: 2025-10-31 | G19: MIS_B0200_C0110 | H19: MISSINGS | I19: Validar que não existem registos por preencher (Missings) | J19: BU_LOANTAPE_WORK.OUT_B0200_MAIN_LIABILITIES | K19: 0110_APPLCBL_FEES_CHARGES | L19: 8 | M19: 0
B20: =+IF(LEFT(MID(Controlos[[#This Row],[tabela]],22,5),1)="B",MID(Controlos[[#This Row],[tabela]],22,5),MID(Controlos[[#This Row],[tabela]],18,5)) -> B0200 | C20: =+IF(Controlos[[#This Row],[tipologia_teste]]="REGULAMENTAR",IF(LEFT(Controlos[[#This Row],[cod_kpi]],1)="v",IF(LEFT(Controlos[[#This Row],[descrição]],6)="Alerta","W","H"),"F"),0) -> 0 | F20: 2025-10-31 | G20: MIS_B0200_C0120 | H20: MISSINGS | I20: Validar que não existem registos por preencher (Missings) | J20: BU_LOANTAPE_WORK.OUT_B0200_MAIN_LIABILITIES | K20: 0120_OTSTNDNG_AMNT | L20: 8 | M20: 8 | N20: 31641600000000000PTBSREOM0028000; 31641600000000000PTSTOEOM0021000; 31641600000000000PTSTOFOM0004000; 31641600000000000PTSTOGOM0003000; 31641600000000000PTSTOHOM0002000; 31641600005800007PTBSRDOM0037000; 31641600005800007PTCPP0AM0007000; 31641600005800007PTSTOCOM0007000
B21: =+IF(LEFT(MID(Controlos[[#This Row],[tabela]],22,5),1)="B",MID(Controlos[[#This Row],[tabela]],22,5),MID(Controlos[[#This Row],[tabela]],18,5)) -> B0200 | C21: =+IF(Controlos[[#This Row],[tipologia_teste]]="REGULAMENTAR",IF(LEFT(Controlos[[#This Row],[cod_kpi]],1)="v",IF(LEFT(Controlos[[#This Row],[descrição]],6)="Alerta","W","H"),"F"),0) -> 0 | F21: 2025-10-31 | G21: MIS_B0200_C0130 | H21: MISSINGS | I21: Validar que não existem registos por preencher (Missings) | J21: BU_LOANTAPE_WORK.OUT_B0200_MAIN_LIABILITIES | K21: 0130_RLVNT_AMNT_WDC | L21: 8 | M21: 8 | N21: 31641600000000000PTBSREOM0028000; 31641600000000000PTSTOEOM0021000; 31641600000000000PTSTOFOM0004000; 31641600000000000PTSTOGOM0003000; 31641600000000000PTSTOHOM0002000; 31641600005800007PTBSRDOM0037000; 31641600005800007PTCPP0AM0007000; 31641600005800007PTSTOCOM0007000
B22: =+IF(LEFT(MID(Controlos[[#This Row],[tabela]],22,5),1)="B",MID(Controlos[[#This Row],[tabela]],22,5),MID(Controlos[[#This Row],[tabela]],18,5)) -> B0200 | C22: =+IF(Controlos[[#This Row],[tipologia_teste]]="REGULAMENTAR",IF(LEFT(Controlos[[#This Row],[cod_kpi]],1)="v",IF(LEFT(Controlos[[#This Row],[descrição]],6)="Alerta","W","H"),"F"),0) -> 0 | F22: 2025-10-31 | G22: MIS_B0200_C0140 | H22: MISSINGS | I22: Validar que não existem registos por preencher (Missings) | J22: BU_LOANTAPE_WORK.OUT_B0200_MAIN_LIABILITIES | K22: 0140_NTR_LBLTY | L22: 8 | M22: 0
B23: =+IF(LEFT(MID(Controlos[[#This Row],[tabela]],22,5),1)="B",MID(Controlos[[#This Row],[tabela]],22,5),MID(Controlos[[#This Row],[tabela]],18,5)) -> B0200 | C23: =+IF(Controlos[[#This Row],[tipologia_teste]]="REGULAMENTAR",IF(LEFT(Controlos[[#This Row],[cod_kpi]],1)="v",IF(LEFT(Controlos[[#This Row],[descrição]],6)="Alerta","W","H"),"F"),0) -> 0 | F23: 2025-10-31 | G23: MIS_B0200_C0141 | H23: MISSINGS | I23: Validar que não existem registos por preencher (Missings) | J23: BU_LOANTAPE_WORK.OUT_B0200_MAIN_LIABILITIES | K23: 0141_NTR_LBLTY_OTHR | L23: 8 | M23: 0
B24: =+IF(LEFT(MID(Controlos[[#This Row],[tabela]],22,5),1)="B",MID(Controlos[[#This Row],[tabela]],22,5),MID(Controlos[[#This Row],[tabela]],18,5)) -> B0200 | C24: =+IF(Controlos[[#This Row],[tipologia_teste]]="REGULAMENTAR",IF(LEFT(Controlos[[#This Row],[cod_kpi]],1)="v",IF(LEFT(Controlos[[#This Row],[descrição]],6)="Alerta","W","H"),"F"),0) -> 0 | F24: 2025-10-31 | G24: MIS_B0200_C0150 | H24: MISSINGS | I24: Validar que não existem registos por preencher (Missings) | J24: BU_LOANTAPE_WORK.OUT_B0200_MAIN_LIABILITIES | K24: 0150_FLG_STRCTRLLY_SBRDNTD | L24: 8 | M24: 0
B25: =+IF(LEFT(MID(Controlos[[#This Row],[tabela]],22,5),1)="B",MID(Controlos[[#This Row],[tabela]],22,5),MID(Controlos[[#This Row],[tabela]],18,5)) -> B0200 | C25: =+IF(Controlos[[#This Row],[tipologia_teste]]="REGULAMENTAR",IF(LEFT(Controlos[[#This Row],[cod_kpi]],1)="v",IF(LEFT(Controlos[[#This Row],[descrição]],6)="Alerta","W","H"),"F"),0) -> 0 | F25: 2025-10-31 | G25: MIS_B0200_C0160 | H25: MISSINGS | I25: Validar que não existem registos por preencher (Missings) | J25: BU_LOANTAPE_WORK.OUT_B0200_MAIN_LIABILITIES | K25: 0160_RANK_INSOLV | L25: 8 | M25: 0
B26: =+IF(LEFT(MID(Controlos[[#This Row],[tabela]],22,5),1)="B",MID(Controlos[[#This Row],[tabela]],22,5),MID(Controlos[[#This Row],[tabela]],18,5)) -> B0200 | C26: =+IF(Controlos[[#This Row],[tipologia_teste]]="REGULAMENTAR",IF(LEFT(Controlos[[#This Row],[cod_kpi]],1)="v",IF(LEFT(Controlos[[#This Row],[descrição]],6)="Alerta","W","H"),"F"),0) -> 0 | F26: 2025-10-31 | G26: MIS_B0200_C0161 | H26: MISSINGS | I26: Validar que não existem registos por preencher (Missings) | J26: BU_LOANTAPE_WORK.OUT_B0200_MAIN_LIABILITIES | K26: 0161_CNTRCTL_SBRDNTN | L26: 8 | M26: 0
B27: =+IF(LEFT(MID(Controlos[[#This Row],[tabela]],22,5),1)="B",MID(Controlos[[#This Row],[tabela]],22,5),MID(Controlos[[#This Row],[tabela]],18,5)) -> B0200 | C27: =+IF(Controlos[[#This Row],[tipologia_teste]]="REGULAMENTAR",IF(LEFT(Controlos[[#This Row],[cod_kpi]],1)="v",IF(LEFT(Controlos[[#This Row],[descrição]],6)="Alerta","W","H"),"F"),0) -> 0 | F27: 2025-10-31 | G27: MIS_B0200_C0162 | H27: MISSINGS | I27: Validar que não existem registos por preencher (Missings) | J27: BU_LOANTAPE_WORK.OUT_B0200_MAIN_LIABILITIES | K27: 0162_BAIL_IN_CASCADE | L27: 8 | M27: 0
B28: =+IF(LEFT(MID(Controlos[[#This Row],[tabela]],22,5),1)="B",MID(Controlos[[#This Row],[tabela]],22,5),MID(Controlos[[#This Row],[tabela]],18,5)) -> B0200 | C28: =+IF(Controlos[[#This Row],[tipologia_teste]]="REGULAMENTAR",IF(LEFT(Controlos[[#This Row],[cod_kpi]],1)="v",IF(LEFT(Controlos[[#This Row],[descrição]],6)="Alerta","W","H"),"F"),0) -> 0 | F28: 2025-10-31 | G28: MIS_B0200_C0170 | H28: MISSINGS | I28: Validar que não existem registos por preencher (Missings) | J28: BU_LOANTAPE_WORK.OUT_B0200_MAIN_LIABILITIES | K28: 0170_DT_INCPTN | L28: 8 | M28: 0
B29: =+IF(LEFT(MID(Controlos[[#This Row],[tabela]],22,5),1)="B",MID(Controlos[[#This Row],[tabela]],22,5),MID(Controlos[[#This Row],[tabela]],18,5)) -> B0200 | C29: =+IF(Controlos[[#This Row],[tipologia_teste]]="REGULAMENTAR",IF(LEFT(Controlos[[#This Row],[cod_kpi]],1)="v",IF(LEFT(Controlos[[#This Row],[descrição]],6)="Alerta","W","H"),"F"),0) -> 0 | F29: 2025-10-31 | G29: MIS_B0200_C0180 | H29: MISSINGS | I29: Validar que não existem registos por preencher (Missings) | J29: BU_LOANTAPE_WORK.OUT_B0200_MAIN_LIABILITIES | K29: 0180_DT_NXT_INTRST_PYMNT | L29: 8 | M29: 0
B30: =+IF(LEFT(MID(Controlos[[#This Row],[tabela]],22,5),1)="B",MID(Controlos[[#This Row],[tabela]],22,5),MID(Controlos[[#This Row],[tabela]],18,5)) -> B0200 | C30: =+IF(Controlos[[#This Row],[tipologia_teste]]="REGULAMENTAR",IF(LEFT(Controlos[[#This Row],[cod_kpi]],1)="v",IF(LEFT(Controlos[[#This Row],[descrição]],6)="Alerta","W","H"),"F"),0) -> 0 | F30: 2025-10-31 | G30: MIS_B0200_C0190 | H30: MISSINGS | I30: Validar que não existem registos por preencher (Missings) | J30: BU_LOANTAPE_WORK.OUT_B0200_MAIN_LIABILITIES | K30: 0190_DT_NXT_RDMPTN_PYMNT | L30: 8 | M30: 0
B31: =+IF(LEFT(MID(Controlos[[#This Row],[tabela]],22,5),1)="B",MID(Controlos[[#This Row],[tabela]],22,5),MID(Controlos[[#This Row],[tabela]],18,5)) -> B0200 | C31: =+IF(Controlos[[#This Row],[tipologia_teste]]="REGULAMENTAR",IF(LEFT(Controlos[[#This Row],[cod_kpi]],1)="v",IF(LEFT(Controlos[[#This Row],[descrição]],6)="Alerta","W","H"),"F"),0) -> 0 | F31: 2025-10-31 | G31: MIS_B0200_C0200 | H31: MISSINGS | I31: Validar que não existem registos por preencher (Missings) | J31: BU_LOANTAPE_WORK.OUT_B0200_MAIN_LIABILITIES | K31: 0200_DT_ERLST_RDMPTN | L31: 8 | M31: 0
B32: =+IF(LEFT(MID(Controlos[[#This Row],[tabela]],22,5),1)="B",MID(Controlos[[#This Row],[tabela]],22,5),MID(Controlos[[#This Row],[tabela]],18,5)) -> B0200 | C32: =+IF(Controlos[[#This Row],[tipologia_teste]]="REGULAMENTAR",IF(LEFT(Controlos[[#This Row],[cod_kpi]],1)="v",IF(LEFT(Controlos[[#This Row],[descrição]],6)="Alerta","W","H"),"F"),0) -> 0 | F32: 2025-10-31 | G32: MIS_B0200_C0210 | H32: MISSINGS | I32: Validar que não existem registos por preencher (Missings) | J32: BU_LOANTAPE_WORK.OUT_B0200_MAIN_LIABILITIES | K32: 0210_DT_LGL_FNL_MTRTY | L32: 8 | M32: 0
B33: =+IF(LEFT(MID(Controlos[[#This Row],[tabela]],22,5),1)="B",MID(Controlos[[#This Row],[tabela]],22,5),MID(Controlos[[#This Row],[tabela]],18,5)) -> B0200 | C33: =+IF(Controlos[[#This Row],[tipologia_teste]]="REGULAMENTAR",IF(LEFT(Controlos[[#This Row],[cod_kpi]],1)="v",IF(LEFT(Controlos[[#This Row],[descrição]],6)="Alerta","W","H"),"F"),0) -> 0 | F33: 2025-10-31 | G33: MIS_B0200_C0220 | H33: MISSINGS | I33: Validar que não existem registos por preencher (Missings) | J33: BU_LOANTAPE_WORK.OUT_B0200_MAIN_LIABILITIES | K33: 0220_GOVERNING_LAW | L33: 8 | M33: 0
... B50: =+IF(LEFT(MID(Controlos[[#This Row],[tabela]],22,5),1)="B",MID(Controlos[[#This Row],[tabela]],22,5),MID(Controlos[[#This Row],[tabela]],18,5)) -> B0200 | C50: =+IF(Controlos[[#This Row],[tipologia_teste]]="REGULAMENTAR",IF(LEFT(Controlos[[#This Row],[cod_kpi]],1)="v",IF(LEFT(Controlos[[#This Row],[descrição]],6)="Alerta","W","H"),"F"),0) -> 0 | F50: 2025-10-31 | G50: MIS_B0200_C0380 | H50: MISSINGS | I50: Validar que não existem registos por preencher (Missings) | J50: BU_LOANTAPE_WORK.OUT_B0200_MAIN_LIABILITIES | K50: 0380_AMNT_SCRTY_FX | L50: 8 | M50: 0
B51: =+IF(LEFT(MID(Controlos[[#This Row],[tabela]],22,5),1)="B",MID(Controlos[[#This Row],[tabela]],22,5),MID(Controlos[[#This Row],[tabela]],18,5)) -> B0200 | C51: =+IF(Controlos[[#This Row],[tipologia_teste]]="REGULAMENTAR",IF(LEFT(Controlos[[#This Row],[cod_kpi]],1)="v",IF(LEFT(Controlos[[#This Row],[descrição]],6)="Alerta","W","H"),"F"),0) -> 0 | F51: 2025-10-31 | G51: MIS_B0200_C0390 | H51: MISSINGS | I51: Validar que não existem registos por preencher (Missings) | J51: BU_LOANTAPE_WORK.OUT_B0200_MAIN_LIABILITIES | K51: 0390_NMBR_SCRTS_NOT_RPRTNG_ENTTY | L51: 8 | M51: 8 | N51: 31641600000000000PTBSREOM0028000; 31641600000000000PTSTOEOM0021000; 31641600000000000PTSTOFOM0004000; 31641600000000000PTSTOGOM0003000; 31641600000000000PTSTOHOM0002000; 31641600005800007PTBSRDOM0037000; 31641600005800007PTCPP0AM0007000; 31641600005800007PTSTOCOM0007000
B52: =+IF(LEFT(MID(Controlos[[#This Row],[tabela]],22,5),1)="B",MID(Controlos[[#This Row],[tabela]],22,5),MID(Controlos[[#This Row],[tabela]],18,5)) -> B0200 | C52: =+IF(Controlos[[#This Row],[tipologia_teste]]="REGULAMENTAR",IF(LEFT(Controlos[[#This Row],[cod_kpi]],1)="v",IF(LEFT(Controlos[[#This Row],[descrição]],6)="Alerta","W","H"),"F"),0) -> 0 | F52: 2025-10-31 | G52: MIS_B0200_C0391 | H52: MISSINGS | I52: Validar que não existem registos por preencher (Missings) | J52: BU_LOANTAPE_WORK.OUT_B0200_MAIN_LIABILITIES | K52: 0391_NMBR_SCRTS_RPRTNG_ENTTY | L52: 8 | M52: 8 | N52: 31641600000000000PTBSREOM0028000; 31641600000000000PTSTOEOM0021000; 31641600000000000PTSTOFOM0004000; 31641600000000000PTSTOGOM0003000; 31641600000000000PTSTOHOM0002000; 31641600005800007PTBSRDOM0037000; 31641600005800007PTCPP0AM0007000; 31641600005800007PTSTOCOM0007000
B53: =+IF(LEFT(MID(Controlos[[#This Row],[tabela]],22,5),1)="B",MID(Controlos[[#This Row],[tabela]],22,5),MID(Controlos[[#This Row],[tabela]],18,5)) -> B0200 | C53: =+IF(Controlos[[#This Row],[tipologia_teste]]="REGULAMENTAR",IF(LEFT(Controlos[[#This Row],[cod_kpi]],1)="v",IF(LEFT(Controlos[[#This Row],[descrição]],6)="Alerta","W","H"),"F"),0) -> 0 | F53: 2025-10-31 | G53: MIS_B0200_C0400 | H53: MISSINGS | I53: Validar que não existem registos por preencher (Missings) | J53: BU_LOANTAPE_WORK.OUT_B0200_MAIN_LIABILITIES | K53: 0400_ACCRD_INTRST_SCRTY | L53: 8 | M53: 8 | N53: 31641600000000000PTBSREOM0028000; 31641600000000000PTSTOEOM0021000; 31641600000000000PTSTOFOM0004000; 31641600000000000PTSTOGOM0003000; 31641600000000000PTSTOHOM0002000; 31641600005800007PTBSRDOM0037000; 31641600005800007PTCPP0AM0007000; 31641600005800007PTSTOCOM0007000
B54: =+IF(LEFT(MID(Controlos[[#This Row],[tabela]],22,5),1)="B",MID(Controlos[[#This Row],[tabela]],22,5),MID(Controlos[[#This Row],[tabela]],18,5)) -> B0200 | C54: =+IF(Controlos[[#This Row],[tipologia_teste]]="REGULAMENTAR",IF(LEFT(Controlos[[#This Row],[cod_kpi]],1)="v",IF(LEFT(Controlos[[#This Row],[descrição]],6)="Alerta","W","H"),"F"),0) -> 0 | F54: 2025-10-31 | G54: MIS_B0200_C0410 | H54: MISSINGS | I54: Validar que não existem registos por preencher (Missings) | J54: BU_LOANTAPE_WORK.OUT_B0200_MAIN_LIABILITIES | K54: 0410_FEES_CHARGES_SCRTY | L54: 8 | M54: 0
B55: =+IF(LEFT(MID(Controlos[[#This Row],[tabela]],22,5),1)="B",MID(Controlos[[#This Row],[tabela]],22,5),MID(Controlos[[#This Row],[tabela]],18,5)) -> B0200 | C55: =+IF(Controlos[[#This Row],[tipologia_teste]]="REGULAMENTAR",IF(LEFT(Controlos[[#This Row],[cod_kpi]],1)="v",IF(LEFT(Controlos[[#This Row],[descrição]],6)="Alerta","W","H"),"F"),0) -> 0 | F55: 2025-10-31 | G55: MIS_B0200_C0420 | H55: MISSINGS | I55: Validar que não existem registos por preencher (Missings) | J55: BU_LOANTAPE_WORK.OUT_B0200_MAIN_LIABILITIES | K55: 0420_FV_AMNT_SCRTY | L55: 8 | M55: 0
B56: =+IF(LEFT(MID(Controlos[[#This Row],[tabela]],22,5),1)="B",MID(Controlos[[#This Row],[tabela]],22,5),MID(Controlos[[#This Row],[tabela]],18,5)) -> B0200 | C56: =+IF(Controlos[[#This Row],[tipologia_teste]]="REGULAMENTAR",IF(LEFT(Controlos[[#This Row],[cod_kpi]],1)="v",IF(LEFT(Controlos[[#This Row],[descrição]],6)="Alerta","W","H"),"F"),0) -> 0 | F56: 2025-10-31 | G56: MIS_B0200_C0430 | H56: MISSINGS | I56: Validar que não existem registos por preencher (Missings) | J56: BU_LOANTAPE_WORK.OUT_B0200_MAIN_LIABILITIES | K56: 0430_PRNCPL_AMNT_GLBL_NT_EUR | L56: 8 | M56: 0
B57: =+IF(LEFT(MID(Controlos[[#This Row],[tabela]],22,5),1)="B",MID(Controlos[[#This Row],[tabela]],22,5),MID(Controlos[[#This Row],[tabela]],18,5)) -> B0200 | C57: =+IF(Controlos[[#This Row],[tipologia_teste]]="REGULAMENTAR",IF(LEFT(Controlos[[#This Row],[cod_kpi]],1)="v",IF(LEFT(Controlos[[#This Row],[descrição]],6)="Alerta","W","H"),"F"),0) -> 0 | F57: 2025-10-31 | G57: MIS_B0200_C0431 | H57: MISSINGS | I57: Validar que não existem registos por preencher (Missings) | J57: BU_LOANTAPE_WORK.OUT_B0200_MAIN_LIABILITIES | K57: 0431_PRNCPL_AMNT_GLBL_NT_FX | L57: 8 | M57: 0
B58: =+IF(LEFT(MID(Controlos[[#This Row],[tabela]],22,5),1)="B",MID(Controlos[[#This Row],[tabela]],22,5),MID(Controlos[[#This Row],[tabela]],18,5)) -> B0200 | C58: =+IF(Controlos[[#This Row],[tipologia_teste]]="REGULAMENTAR",IF(LEFT(Controlos[[#This Row],[cod_kpi]],1)="v",IF(LEFT(Controlos[[#This Row],[descrição]],6)="Alerta","W","H"),"F"),0) -> 0 | F58: 2025-10-31 | G58: MIS_B0200_C0440 | H58: MISSINGS | I58: Validar que não existem registos por preencher (Missings) | J58: BU_LOANTAPE_WORK.OUT_B0200_MAIN_LIABILITIES | K58: 0440_NTR_GLBL_NT | L58: 8 | M58: 0
B59: =+IF(LEFT(MID(Controlos[[#This Row],[tabela]],22,5),1)="B",MID(Controlos[[#This Row],[tabela]],22,5),MID(Controlos[[#This Row],[tabela]],18,5)) -> B0200 | C59: =+IF(Controlos[[#This Row],[tipologia_teste]]="REGULAMENTAR",IF(LEFT(Controlos[[#This Row],[cod_kpi]],1)="v",IF(LEFT(Controlos[[#This Row],[descrição]],6)="Alerta","W","H"),"F"),0) -> 0 | F59: 2025-10-31 | G59: MIS_B0200_C0450 | H59: MISSINGS | I59: Validar que não existem registos por preencher (Missings) | J59: BU_LOANTAPE_WORK.OUT_B0200_MAIN_LIABILITIES | K59: 0450_CRRNT_POOL_FCTR | L59: 8 | M59: 0
B60: =+IF(LEFT(MID(Controlos[[#This Row],[tabela]],22,5),1)="B",MID(Controlos[[#This Row],[tabela]],22,5),MID(Controlos[[#This Row],[tabela]],18,5)) -> B0200 | C60: =+IF(Controlos[[#This Row],[tipologia_teste]]="REGULAMENTAR",IF(LEFT(Controlos[[#This Row],[cod_kpi]],1)="v",IF(LEFT(Controlos[[#This Row],[descrição]],6)="Alerta","W","H"),"F"),0) -> 0 | F60: 2025-10-31 | G60: MIS_B0200_C0460 | H60: MISSINGS | I60: Validar que não existem registos por preencher (Missings) | J60: BU_LOANTAPE_WORK.OUT_B0200_MAIN_LIABILITIES | K60: 0460_CSD | L60: 8 | M60: 0
B61: =+IF(LEFT(MID(Controlos[[#This Row],[tabela]],22,5),1)="B",MID(Controlos[[#This Row],[tabela]],22,5),MID(Controlos[[#This Row],[tabela]],18,5)) -> B0200 | C61: =+IF(Controlos[[#This Row],[tipologia_teste]]="REGULAMENTAR",IF(LEFT(Controlos[[#This Row],[cod_kpi]],1)="v",IF(LEFT(Controlos[[#This Row],[descrição]],6)="Alerta","W","H"),"F"),0) -> 0 | F61: 2025-10-31 | G61: MIS_B0200_C0461 | H61: MISSINGS | I61: Validar que não existem registos por preencher (Missings) | J61: BU_LOANTAPE_WORK.OUT_B0200_MAIN_LIABILITIES | K61: 0461_CSD_LEI | L61: 8 | M61: 0
B62: =+IF(LEFT(MID(Controlos[[#This Row],[tabela]],22,5),1)="B",MID(Controlos[[#This Row],[tabela]],22,5),MID(Controlos[[#This Row],[tabela]],18,5)) -> B0200 | C62: =+IF(Controlos[[#This Row],[tipologia_teste]]="REGULAMENTAR",IF(LEFT(Controlos[[#This Row],[cod_kpi]],1)="v",IF(LEFT(Controlos[[#This Row],[descrição]],6)="Alerta","W","H"),"F"),0) -> 0 | F62: 2025-10-31 | G62: MIS_B0200_C0462 | H62: MISSINGS | I62: Validar que não existem registos por preencher (Missings) | J62: BU_LOANTAPE_WORK.OUT_B0200_MAIN_LIABILITIES | K62: 0462_CSD_OTHR | L62: 8 | M62: 0
B63: =+IF(LEFT(MID(Controlos[[#This Row],[tabela]],22,5),1)="B",MID(Controlos[[#This Row],[tabela]],22,5),MID(Controlos[[#This Row],[tabela]],18,5)) -> B0200 | C63: =+IF(Controlos[[#This Row],[tipologia_teste]]="REGULAMENTAR",IF(LEFT(Controlos[[#This Row],[cod_kpi]],1)="v",IF(LEFT(Controlos[[#This Row],[descrição]],6)="Alerta","W","H"),"F"),0) -> 0 | F63: 2025-10-31 | G63: MIS_B0200_C0470 | H63: MISSINGS | I63: Validar que não existem registos por preencher (Missings) | J63: BU_LOANTAPE_WORK.OUT_B0200_MAIN_LIABILITIES | K63: 0470_PYNG_AGNT | L63: 8 | M63: 0
B64: =+IF(LEFT(MID(Controlos[[#This Row],[tabela]],22,5),1)="B",MID(Controlos[[#This Row],[tabela]],22,5),MID(Controlos[[#This Row],[tabela]],18,5)) -> B0200 | C64: =+IF(Controlos[[#This Row],[tipologia_teste]]="REGULAMENTAR",IF(LEFT(Controlos[[#This Row],[cod_kpi]],1)="v",IF(LEFT(Controlos[[#This Row],[descrição]],6)="Alerta","W","H"),"F"),0) -> 0 | F64: 2025-10-31 | G64: MIS_B0200_C0471 | H64: MISSINGS | I64: Validar que não existem registos por preencher (Missings) | J64: BU_LOANTAPE_WORK.OUT_B0200_MAIN_LIABILITIES | K64: 0471_PYNG_AGNT_LEI | L64: 8 | M64: 0
B65: =+IF(LEFT(MID(Controlos[[#This Row],[tabela]],22,5),1)="B",MID(Controlos[[#This Row],[tabela]],22,5),MID(Controlos[[#This Row],[tabela]],18,5)) -> B0200 | C65: =+IF(Controlos[[#This Row],[tipologia_teste]]="REGULAMENTAR",IF(LEFT(Controlos[[#This Row],[cod_kpi]],1)="v",IF(LEFT(Controlos[[#This Row],[descrição]],6)="Alerta","W","H"),"F"),0) -> 0 | F65: 2025-10-31 | G65: MIS_B0200_C0480 | H65: MISSINGS | I65: Validar que não existem registos por preencher (Missings) | J65: BU_LOANTAPE_WORK.OUT_B0200_MAIN_LIABILITIES | K65: 0480_TRDNG_VN | L65: 8 | M65: 0
... B95: =+IF(LEFT(MID(Controlos[[#This Row],[tabela]],22,5),1)="B",MID(Controlos[[#This Row],[tabela]],22,5),MID(Controlos[[#This Row],[tabela]],18,5)) -> B0500 | C95: =+IF(Controlos[[#This Row],[tipologia_teste]]="REGULAMENTAR",IF(LEFT(Controlos[[#This Row],[cod_kpi]],1)="v",IF(LEFT(Controlos[[#This Row],[descrição]],6)="Alerta","W","H"),"F"),0) -> 0 | F95: 2025-10-31 | G95: MIS_B0500_C0060 | H95: MISSINGS | I95: Validar que não existem registos por preencher (Missings) | J95: BU_LOANTAPE_WORK.OUT_B0500_GUARANTEES | K95: 0060_MAX_AMNT_GUARANTEE | L95: 4730 | M95: 0
B96: =+IF(LEFT(MID(Controlos[[#This Row],[tabela]],22,5),1)="B",MID(Controlos[[#This Row],[tabela]],22,5),MID(Controlos[[#This Row],[tabela]],18,5)) -> B0500 | C96: =+IF(Controlos[[#This Row],[tipologia_teste]]="REGULAMENTAR",IF(LEFT(Controlos[[#This Row],[cod_kpi]],1)="v",IF(LEFT(Controlos[[#This Row],[descrição]],6)="Alerta","W","H"),"F"),0) -> 0 | F96: 2025-10-31 | G96: MIS_B0500_C0070 | H96: MISSINGS | I96: Validar que não existem registos por preencher (Missings) | J96: BU_LOANTAPE_WORK.OUT_B0500_GUARANTEES | K96: 0070_FLG_SCRD | L96: 4730 | M96: 4730 | N96: 31000000000000000962304890482490P_0000_00000000000_000006511000505; 31000304140330096000000000000000P_0000_00000000000_000000000003686; 31000307044893096000000000000000P_0000_00000000000_000000000003686; 31000307530917096000000000000000P_0000_00000000000_000000000003686; 31000311450813096000000000000000P_0000_00000000000_000000000003686; 31000311847794096000000000000000P_0000_00000000000_000000000003686; 31000313517171096000000000000000P_0000_00000000000_000000000003686; 31000315970006096000000000000000P_0000_00000000000_000000000003686; 31000315970121096000000000000000P_0000_00000000000_000000000003686; 31000315970139096000000000000000P_0000_00000000000_000000000003686; 31000315970188096000000000000000P_0000_00000000000_000000000003686; 31000315970212096000000000000000P_0000_00000000000_000000000003686; 31000315970238096000000000000000P_0000_00000000000_000000000003686; 31000315970261096000000000000000P_0000_00000000000_000000000003686; 31000315970279096000000000000000P_0000_00000000000_000000000003686; 31000315970311096000000000000000P_0000_00000000000_000000000003686; 31000315970329096000000000000000P_0000_00000000000_000000000003686; 31000315970345096000000000000000P_0000_00000000000_000000000003686; 31000315970402096000000000000000P_0000_00000000000_000000000003686; 31000315970428096000000000000000P_0000_00000000000_000000000003686; 31000315970469096000000000000000P_0000_00000000000_000000000003686; 31000315979890096000000000000000P_0000_00000000000_000006511000505; 31000318293090097000000000000000P_0000_00000000000_000008000176024; 31000318542009097000000000000000P_0000_00000000000_000006511000505; 31000318628196097000000000000000P_0000_00000000000_000006511000505; 31000318628592097000000000000000P_0000_00000000000_000008000176024; 31000318629012097000000000000000P_0000_00000000000_000008000176024; 31000318636603097000000000000000P_0000_00000000000_000008000176024; 31000318637213097000000000000000P_0000_00000000000_000008000176024; 31000322311418096000000000000000P_0000_00000000000_000000000003686; 89000020240000766001520240649818P_0000_00000000000_000003461004226; 89000020240000766001520240649824P_0000_00000000000_000003461004226; 89000020240000766001520240649825P_0000_00000000000_000003461004226; 89000020240000766001520240649826P_0000_00000000000_000003461004226; 89000020240000766001520240649827P_0000_00000000000_000003461004226; 89000020240000766001520240649838P_0000_00000000000_000003461004226; 89000020240000766001520240649839P_0000_00000000000_000003461004226; 89000020240000766001520240649873P_0000_00000000000_000003461004226; 89000020240000766001520240649874P_0000_00000000000_000003461004226; 89000020240000766001520240649875P_0000_00000000000_000003461004226; 89000020240000766001520240649894P_0000_00000000000_000003461004226; 89000020240000766001520240649898P_0000_00000000000_000003461004226; 89000020240000766001520240649899P_0000_00000000000_000003461004226; 89000020240000766001520240649900P_0000_00000000000_000003461004226; 89000020240000766001520240649901P_0000_00000000000_000003461004226; 89000020240000766001520240649909P_0000_00000000000_000003461004226; 89000020240000766001520240649910P_0000_00000000000_000003461004226; 89000020240000766001520240649911P_0000_00000000000_000003461004226; 89000020240000766001520240649912P_0000_00000000000_000003461004226; 89000020240000766001520240649913P_0000_00000000000_000003461004226; 89000020240000766001520240649914P_0000_00000000000_000003461004226; 89000020240000766001520240649915P_0000_00000000000_000003461004226; 89000020240000766001520240649916P_0000_00000000000_000003461004226; 89000020240000766001520240649917P_0000_00000000000_000003461004226; 89000020240000766001520240649918P_0000_00000000000_000003461004226; 89000020240000766001520240649919P_0000_00000000000_000003461004226; 89000020240000766001520240649920P_0000_00000000000_000003461004226; 89000020240000766001520240649921P_0000_00000000000_000003461004226; 89000020240000766001520240649942P_0000_00000000000_000003461004226; 89000020240000766001520240649943P_0000_00000000000_000003461004226; 89000020240000766001520240649944P_0000_00000000000_000003461004226; 89000020240000766001520240649945P_0000_00000000000_000003461004226; 89000020240000766001520240649946P_0000_00000000000_000003461004226; 89000020240000766001520240650004P_0000_00000000000_000003461004226; 89000020240000766001520240650005P_0000_00000000000_000003461004226; 89000020240000766001520240650006P_0000_00000000000_000003461004226; 89000020240000766001520240650007P_0000_00000000000_000003461004226; 89000020240000766001520240650008P_0000_00000000000_000003461004226; 89000020240000766001520240650009P_0000_00000000000_000003461004226; 89000020240000766001520240650010P_0000_00000000000_000003461004226; 89000020240000766001520240650011P_0000_00000000000_000003461004226; 89000020240000766001520240650116P_0000_00000000000_000003461004226; 89000020240000766001520240650192P_0000_00000000000_000003461004226; 89000020240000766001520240650202P_0000_00000000000_000003461004226; 89000020240000766001520240650203P_0000_00000000000_000003461004226; 89000020240000766001520240650204P_0000_00000000000_000003461004226; 89000020240000766001520240650205P_0000_00000000000_000003461004226; 89000020240000766001520240650206P_0000_00000000000_000003461004226; 89000020240000766001520240650207P_0000_00000000000_000003461004226; 89000020240000766001520240650208P_0000_00000000000_000003461004226; 89000020240000766001520240650349P_0000_00000000000_000003461004226; 89000020240000766001520240650350P_0000_00000000000_000003461004226; 89000020240000766001520240650351P_0000_00000000000_000003461004226; 89000020240000766001520240650352P_0000_00000000000_000003461004226; 89000020240000766001520240650353P_0000_00000000000_000003461004226; 89000020240000766001520240650354P_0000_00000000000_000003461004226; 89000020240000766001520240650355P_0000_00000000000_000003461004226; 89000020240000766001520240650356P_0000_00000000000_000003461004226; 89000020240000766001520240650357P_0000_00000000000_000003461004226; 89000020240000766001520240650358P_0000_00000000000_000003461004226; 89000020240000766001520240650359P_0000_00000000000_000003461004226; 89000020240000766001520240650360P_0000_00000000000_000003461004226; 89000020240000766001520240650361P_0000_00000000000_000003461004226; 89000020240000766001520240650362P_0000_00000000000_000003461004226; 89000020240000766001520240650363P_0000_00000000000_000003461004226; 89000020240000766001520240650364P_0000_00000000000_000003461004226; 89000020240000766001520240650365P_0000_00000000000_000003461004226; 89000020240000766001520240650366P_0000_00000000000_000003461004226; 89000020240000766001520240650367P_0000_00000000000_000003461004226; 89000020240000766001520240650368P_0000_00000000000_000003461004226; 89000020240000766001520240650369P_0000_00000000000_000003461004226; 89000020240000766001520240650370P_0000_00000000000_000003461004226; 89000020240000766001520240650371P_0000_00000000000_000003461004226; 89000020240000766001520240650372P_0000_00000000000_000003461004226; 89000020240000766001520240650373P_0000_00000000000_000003461004226; 89000020240000766001520240650374P_0000_00000000000_000003461004226; 89000020240000766001520240650375P_0000_00000000000_000003461004226; 89000020240000766001520240650376P_0000_00000000000_000003461004226; 89000020240000766001520240650377P_0000_00000000000_000003461004226; 89000020240000766001520240650378P_0000_00000000000_000003461004226; 89000020240000766001520240650379P_0000_00000000000_000003461004226; 89000020240000766001520240650380P_0000_00000000000_000003461004226; 89000020240000766001520240650381P_0000_00000000000_000003461004226; 89000020240000766001520240650382P_0000_00000000000_000003461004226; 89000020240000766001520240650383P_0000_00000000000_000003461004226; 89000020240000766001520240650384P_0000_00000000000_000003461004226; 89000020240000766001520240650385P_0000_00000000000_000003461004226; 89000020240000766001520240650386P_0000_00000000000_000003461004226; 89000020240000766001520240650387P_0000_00000000000_000003461004226; 89000020240000766001520240650388P_0000_00000000000_000003461004226; 89000020240000766001520240650389P_0000_00000000000_000003461004226; 89000020240000766001520240650390P_0000_00000000000_000003461004226; 89000020240000766001520240650391P_0000_00000000000_000003461004226; 89000020240000766001520240650392P_0000_00000000000_000003461004226; 89000020240000766001520240650393P_0000_00000000000_000003461004226; 89000020240000766001520240650394P_0000_00000000000_000003461004226; 89000020240000766001520240650396P_0000_00000000000_000003461004226; 89000020240000766001520240650397P_0000_00000000000_000003461004226; 89000020240000766001520240650398P_0000_00000000000_000003461004226; 89000020240000766001520240650399P_0000_00000000000_000003461004226; 89000020240000766001520240650400P_0000_00000000000_000003461004226; 89000020240000766001520240650401P_0000_00000000000_000003461004226; 89000020240000766001520240650402P_0000_00000000000_000003461004226; 89000020240000766001520240650403P_0000_00000000000_000003461004226; 89000020240000766001520240650404P_0000_00000000000_000003461004226; 89000020240000766001520240650405P_0000_00000000000_000003461004226; 89000020240000766001520240650406P_0000_00000000000_000003461004226; 89000020240000766001520240650407P_0000_00000000000_000003461004226; 89000020240000766001520240650408P_0000_00000000000_000003461004226; 89000020240000766001520240650409P_0000_00000000000_000003461004226; 89000020240000766001520240650410P_0000_00000000000_000003461004226; 89000020240000766001520240650411P_0000_00000000000_000003461004226; 89000020240000766001520240650412P_0000_00000000000_000003461004226; 89000020240000766001520240650413P_0000_00000000000_000003461004226; 89000020240000766001520240650414P_0000_00000000000_000003461004226; 89000020240000766001520240650415P_0000_00000000000_000003461004226; 89000020240000766001520240650416P_0000_00000000000_000003461004226; 89000020240000766001520240650417P_0000_00000000000_000003461004226; 89000020240000766001520240650418P_0000_00000000000_000003461004226; 89000020240000766001520240650419P_0000_00000000000_000003461004226; 89000020240000766001520240650420P_0000_00000000000_000003461004226; 89000020240000766001520240650421P_0000_00000000000_000003461004226; 89000020240000766001520240650422P_0000_00000000000_000003461004226; 89000020240000766001520240650423P_0000_00000000000_000003461004226; 89000020240000766001520240650424P_0000_00000000000_000003461004226; 89000020240000766001520240650425P_0000_00000000000_000003461004226; 89000020240000766001520240650426P_0000_00000000000_000003461004226; 89000020240000766001520240650427P_0000_00000000000_000003461004226; 89000020240000766001520240650428P_0000_00000000000_000003461004226; 89000020240000766001520240650429P_0000_00000000000_000003461004226; 89000020240000766001520240650431P_0000_00000000000_000003461004226; 89000020240000766001520240650432P_0000_00000000000_000003461004226; 89000020240000766001520240650433P_0000_00000000000_000003461004226; 89000020240000766001520240650434P_0000_00000000000_000003461004226; 89000020240000766001520240650435P_0000_00000000000_000003461004226; 89000020240000766001520240650436P_0000_00000000000_000003461004226; 89000020240000766001520240650476P_0000_00000000000_000003461004226; 89000020240000766001520240650477P_0000_00000000000_000003461004226; 89000020240000766001520240650478P_0000_00000000000_000003461004226; 89000020240000766001520240650479P_0000_00000000000_000003461004226; 89000020240000766001520240650480P_0000_00000000000_000003461004226; 89000020240000766001520240650481P_0000_00000000000_000003461004226; 89000020240000766001520240650482P_0000_00000000000_000003461004226; 89000020240000766001520240650483P_0000_00000000000_000003461004226; 89000020240000766001520240650484P_0000_00000000000_000003461004226; 89000020240000766001520240650485P_0000_00000000000_000003461004226; 89000020240000766001520240650486P_0000_00000000000_000003461004226; 89000020240000766001520240650487P_0000_00000000000_000003461004226; 89000020240000766001520240650488P_0000_00000000000_000003461004226; 89000020240000766001520240650489P_0000_00000000000_000003461004226; 89000020240000766001520240650490P_0000_00000000000_000003461004226; 89000020240000766001520240650491P_0000_00000000000_000003461004226; 89000020240000766001520240650492P_0000_00000000000_000003461004226; 89000020240000766001520240650493P_0000_00000000000_000003461004226; 89000020240000766001520240650494P_0000_00000000000_000003461004226; 89000020240000766001520240650495P_0000_00000000000_000003461004226; 89000020240000766001520240650496P_0000_00000000000_000003461004226; 89000020240000766001520240650497P_0000_00000000000_000003461004226; 89000020240000766001520240650498P_0000_00000000000_000003461004226; 89000020240000766001520240650499P_0000_00000000000_000003461004226; 89000020240000766001520240650500P_0000_00000000000_000003461004226; 89000020240000766001520240650501P_0000_00000000000_000003461004226; 89000020240000766001520240650502P_0000_00000000000_000003461004226; 89000020240000766001520240650503P_0000_00000000000_000003461004226; 89000020240000766001520240650504P_0000_00000000000_000003461004226; 89000020240000766001520240650505P_0000_00000000000_000003461004226; 89000020240000766001520240650506P_0000_00000000000_000003461004226; 89000020240000766001520240650507P_0000_00000000000_000003461004226; 89000020240000766001520240650508P_0000_00000000000_000003461004226; 89000020240000766001520240650509P_0000_00000000000_000003461004226; 89000020240000766001520240650510P_0000_00000000000_000003461004226; 89000020240000766001520240650511P_0000_00000000000_000003461004226; 89000020240000766001520240650512P_0000_00000000000_000003461004226; 89000020240000766001520240650513P_0000_00000000000_000003461004226; 89000020240000766001520240650514P_0000_00000000000_000003461004226; 89000020240000766001520240650515P_0000_00000000000_000003461004226; 89000020240000766001520240650516P_0000_00000000000_000003461004226; 89000020240000766001520240650517P_0000_00000000000_000003461004226; 89000020240000766001520240650518P_0000_00000000000_000003461004226; 89000020240000766001520240650519P_0000_00000000000_000003461004226; 89000020240000766001520240650520P_0000_00000000000_000003461004226; 89000020240000766001520240650521P_0000_00000000000_000003461004226; 89000020240000766001520240650522P_0000_00000000000_000003461004226; 89000020240000766001520240650523P_0000_00000000000_000003461004226; 89000020240000766001520240650524P_0000_00000000000_000003461004226; 89000020240000766001520240650525P_0000_00000000000_000003461004226; 89000020240000766001520240650526P_0000_00000000000_000003461004226; 89000020240000766001520240650527P_0000_00000000000_000003461004226; 89000020240000766001520240650528P_0000_00000000000_000003461004226; 89000020240000766001520240650529P_0000_00000000000_000003461004226; 89000020240000766001520240650530P_0000_00000000000_000003461004226; 89000020240000766001520240650531P_0000_00000000000_000003461004226; 89000020240000766001520240650532P_0000_00000000000_000003461004226; 89000020240000766001520240650533P_0000_00000000000_000003461004226; 89000020240000766001520240650534P_0000_00000000000_000003461004226; 89000020240000766001520240650535P_0000_00000000000_000003461004226; 89000020240000766001520240650536P_0000_00000000000_000003461004226; 89000020240000766001520240650537P_0000_00000000000_000003461004226; 89000020240000766001520240650538P_0000_00000000000_000003461004226; 89000020240000766001520240650539P_0000_00000000000_000003461004226; 89000020240000766001520240650540P_0000_00000000000_000003461004226; 89000020240000766001520240650541P_0000_00000000000_000003461004226; 89000020240000766001520240650542P_0000_00000000000_000003461004226; 89000020240000766001520240650543P_0000_00000000000_000003461004226; 89000020240000766001520240650544P_0000_00000000000_000003461004226; 89000020240000766001520240650545P_0000_00000000000_000003461004226; 89000020240000766001520240650546P_0000_00000000000_000003461004226; 89000020240000766001520240650547P_0000_00000000000_000003461004226; 89000020240000766001520240650548P_0000_00000000000_000003461004226; 89000020240000766001520240650549P_0000_00000000000_000003461004226; 89000020240000766001520240650550P_0000_00000000000_000003461004226; 89000020240000766001520240650551P_0000_00000000000_000003461004226; 89000020240000766001520240650552P_0000_00000000000_000003461004226; 89000020240000766001520240650553P_0000_00000000000_000003461004226; 89000020240000766001520240650554P_0000_00000000000_000003461004226; 89000020240000766001520240650555P_0000_00000000000_000003461004226; 89000020240000766001520240650556P_0000_00000000000_000003461004226; 89000020240000766001520240650557P_0000_00000000000_000003461004226; 89000020240000766001520240650558P_0000_00000000000_000003461004226; 89000020240000766001520240650559P_0000_00000000000_000003461004226; 89000020240000766001520240650560P_0000_00000000000_000003461004226; 89000020240000766001520240650561P_0000_00000000000_000003461004226; 89000020240000766001520240650562P_0000_00000000000_000003461004226; 89000020240000766001520240650563P_0000_00000000000_000003461004226; 89000020240000766001520240650564P_0000_00000000000_000003461004226; 89000020240000766001520240650565P_0000_00000000000_000003461004226; 89000020240000766001520240650566P_0000_00000000000_000003461004226; 89000020240000766001520240650567P_0000_00000000000_000003461004226; 89000020240000766001520240650568P_0000_00000000000_000003461004226; 89000020240000766001520240650569P_0000_00000000000_000003461004226; 89000020240000766001520240650783P_0000_00000000000_000003461004226; 89000020240000766001520240650784P_0000_00000000000_000003461004226; 89000020240000766001520240650785P_0000_00000000000_000003461004226; 89000020240000766001520240650786P_0000_00000000000_000003461004226; 89000020240000766001520240650787P_0000_00000000000_000003461004226; 89000020240000766001520240650788P_0000_00000000000_000003461004226; 89000020240000766001520240650851P_0000_00000000000_000003461004226; 89000020240000766001520240650853P_0000_00000000000_000003461004226; 89000020240000766001520240650865P_0000_00000000000_000003461004226; 89000020240000766001520240650868P_0000_00000000000_000003461004226; 89000020240000766001520240650869P_0000_00000000000_000003461004226; 89000020240000766001520240650873P_0000_00000000000_000003461004226; 89000020240000766001520240650875P_0000_00000000000_000003461004226; 89000020240000766001520240650930P_0000_00000000000_000003461004226; 89000020240000766001520240650947P_0000_00000000000_000003461004226; 89000020240000766001520240650948P_0000_00000000000_000003461004226; 89000020240000766001520240650949P_0000_00000000000_000003461004226; 89000020240000766001520240650950P_0000_00000000000_000003461004226; 89000020240000766001520240650951P_0000_00000000000_000003461004226; 89000020240000766001520240650952P_0000_00000000000_000003461004226; 89000020240000766001520240650953P_0000_00000000000_000003461004226; 89000020240000766001520240650954P_0000_00000000000_000003461004226; 89000020240000766001520240650955P_0000_00000000000_000003461004226; 89000020240000766001520240650956P_0000_00000000000_000003461004226; 89000020240000766001520240650957P_0000_00000000000_000003461004226; 89000020240000766001520240650958P_0000_00000000000_000003461004226; 89000020240000766001520240650959P_0000_00000000000_000003461004226; 89000020240000766001520240650960P_0000_00000000000_000003461004226; 89000020240000766001520240650961P_0000_00000000000_000003461004226; 89000020240000766001520240650962P_0000_00000000000_000003461004226; 89000020240000766001520240650968P_0000_00000000000_000003461004226; 89000020240000766001520240650969P_0000_00000000000_000003461004226; 89000020240000766001520240650970P_0000_00000000000_000003461004226; 89000020240000766001520240650971P_0000_00000000000_000003461004226; 89000020240000766001520240650972P_0000_00000000000_000003461004226; 89000020240000766001520240650973P_0000_00000000000_000003461004226; 89000020240000766001520240650974P_0000_00000000000_000003461004226; 89000020240000766001520240650975P_0000_00000000000_000003461004226; 89000020240000766001520240650976P_0000_00000000000_000003461004226; 89000020240000766001520240650978P_0000_00000000000_000003461004226; 89000020240000766001520240650979P_0000_00000000000_000003461004226; 89000020240000766001520240650980P_0000_00000000000_000003461004226; 89000020240000766001520240650981P_0000_00000000000_000003461004226; 89000020240000766001520240650982P_0000_00000000000_000003461004226; 89000020240000766001520240650983P_0000_00000000000_000003461004226; 89000020240000766001520240650984P_0000_00000000000_000003461004226; 89000020240000766001520240650985P_0000_00000000000_000003461004226; 89000020240000766001520240650986P_0000_00000000000_000003461004226; 89000020240000766001520240650987P_0000_00000000000_000003461004226; 89000020240000766001520240650988P_0000_00000000000_000003461004226; 89000020240000766001520240650989P_0000_00000000000_000003461004226; 89000020240000766001520240650990P_0000_00000000000_000003461004226; 89000020240000766001520240650991P_0000_00000000000_000003461004226; 89000020240000766001520240650992P_0000_00000000000_000003461004226; 89000020240000766001520240650993P_0000_00000000000_000003461004226; 89000020240000766001520240650994P_0000_00000000000_000003461004226; 89000020240000766001520240650995P_0000_00000000000_000003461004226; 89000020240000766001520240650996P_0000_00000000000_000003461004226; 89000020240000766001520240650997P_0000_00000000000_000003461004226; 89000020240000766001520240650998P_0000_00000000000_000003461004226; 89000020240000766001520240650999P_0000_00000000000_000003461004226; 89000020240000766001520240651000P_0000_00000000000_000003461004226; 89000020240000766001520240651001P_0000_00000000000_000003461004226; 89000020240000766001520240651002P_0000_00000000000_000003461004226; 89000020240000766001520240651003P_0000_00000000000_000003461004226; 89000020240000766001520240651004P_0000_00000000000_000003461004226; 89000020240000766001520240651005P_0000_00000000000_000003461004226; 89000020240000766001520240651006P_0000_00000000000_000003461004226; 89000020240000766001520240651020P_0000_00000000000_000003461004226; 89000020240000766001520240651095P_0000_00000000000_000003461004226; 89000020240000766001520240651174P_0000_00000000000_000003461004226; 89000020240000766001520240651175P_0000_00000000000_000003461004226; 89000020240000766001520240651177P_0000_00000000000_000003461004226; 89000020240000766001520240651179P_0000_00000000000_000003461004226; 89000020240000766001520240651180P_0000_00000000000_000003461004226; 89000020240000766001520240651187P_0000_00000000000_000003461004226; 89000020240000766001520240651188P_0000_00000000000_000003461004226; 89000020240000766001520240651189P_0000_00000000000_000003461004226; 89000020240000766001520240651190P_0000_00000000000_000003461004226; 89000020240000766001520240651192P_0000_00000000000_000003461004226; 89000020240000766001520240651193P_0000_00000000000_000003461004226; 89000020240000766001520240651194P_0000_00000000000_000003461004226; 89000020240000766001520240651195P_0000_00000000000_000003461004226; 89000020240000766001520240651196P_0000_00000000000_000003461004226; 89000020240000766001520240651197P_0000_00000000000_000003461004226; 89000020240000766001520240651198P_0000_00000000000_000003461004226; 89000020240000766001520240651199P_0000_00000000000_000003461004226; 89000020240000766001520240651200P_0000_00000000000_000003461004226; 89000020240000766001520240651201P_0000_00000000000_000003461004226; 89000020240000766001520240651202P_0000_00000000000_000003461004226; 89000020240000766001520240651203P_0000_00000000000_000003461004226; 89000020240000766001520240651204P_0000_00000000000_000003461004226; 89000020240000766001520240651307P_0000_00000000000_000003461004226; 89000020240000766001520240651409P_0000_00000000000_000003461004226; 89000020240000766001520240651410P_0000_00000000000_000003461004226; 89000020240000766001520240651411P_0000_00000000000_000003461004226; 89000020240000766001520240651412P_0000_00000000000_000003461004226; 89000020240000766001520240651444P_0000_00000000000_000003461004226; 89000020240000766001520240651449P_0000_00000000000_000003461004226; 89000020240000766001520240651453P_0000_00000000000_000003461004226; 89000020240000766001520240651454P_0000_00000000000_000003461004226; 89000020240000766001520240651455P_0000_00000000000_000003461004226; 89000020240000766001520240651456P_0000_00000000000_000003461004226; 89000020240000766001520240651464P_0000_00000000000_000003461004226; 89000020240000766001520240651468P_0000_00000000000_000003461004226; 89000020240000766001520240651470P_0000_00000000000_000003461004226; 89000020240000766001520240651471P_0000_00000000000_000003461004226; 89000020240000766001520240651473P_0000_00000000000_000003461004226; 89000020240000766001520240651474P_0000_00000000000_000003461004226; 89000020240000766001520240651475P_0000_00000000000_000003461004226; 89000020240000766001520240651476P_0000_00000000000_000003461004226; 89000020240000766001520240651477P_0000_00000000000_000003461004226; 89000020240000766001520240651643P_0000_00000000000_000003461004226; 89000020240000766001520240651644P_0000_00000000000_000003461004226; 89000020240000766001520240651645P_0000_00000000000_000003461004226; 89000020240000766001520240651684P_0000_00000000000_000003461004226; 89000020240000766001520240651693P_0000_00000000000_000003461004226; 89000020240000766001520240651694P_0000_00000000000_000003461004226; 89000020240000766001520240651695P_0000_00000000000_000003461004226; 89000020240000766001520240651696P_0000_00000000000_000003461004226; 89000020240000766001520240651697P_0000_00000000000_000003461004226; 89000020240000766001520240651698P_0000_00000000000_000003461004226; 89000020240000766001520240651699P_0000_00000000000_000003461004226; 89000020240000766001520240651700P_0000_00000000000_000003461004226; 89000020240000766001520240651701P_0000_00000000000_000003461004226; 89000020240000766001520240651702P_0000_00000000000_000003461004226; 89000020240000766001520240651706P_0000_00000000000_000003461004226; 89000020240000766001520240651707P_0000_00000000000_000003461004226; 89000020240000766001520240651708P_0000_00000000000_000003461004226; 89000020240000766001520240651709P_0000_00000000000_000003461004226; 89000020240000766001520240651710P_0000_00000000000_000003461004226; 89000020240000766001520240651711P_0000_00000000000_000003461004226; 89000020240000766001520240651712P_0000_00000000000_000003461004226; 89000020240000766001520240651713P_0000_00000000000_000003461004226; 89000020240000766001520240651714P_0000_00000000000_000003461004226; 89000020240000766001520240651715P_0000_00000000000_000003461004226; 89000020240000766001520240651716P_0000_00000000000_000003461004226; 89000020240000766001520240651717P_0000_00000000000_000003461004226; 89000020240000766001520240651718P_0000_00000000000_000003461004226; 89000020240000766001520240651719P_0000_00000000000_000003461004226; 89000020240000766001520240651720P_0000_00000000000_000003461004226; 89000020240000766001520240651721P_0000_00000000000_000003461004226; 89000020240000766001520240651722P_0000_00000000000_000003461004226; 89000020240000766001520240651723P_0000_00000000000_000003461004226; 89000020240000766001520240651727P_0000_00000000000_000003461004226; 89000020240000766001520240651728P_0000_00000000000_000003461004226; 89000020240000766001520240651729P_0000_00000000000_000003461004226; 89000020240000766001520240651730P_0000_00000000000_000003461004226; 89000020240000766001520240651731P_0000_00000000000_000003461004226; 89000020240000766001520240651732P_0000_00000000000_000003461004226; 89000020240000766001520240651733P_0000_00000000000_000003461004226; 89000020240000766001520240651849P_0000_00000000000_000003461004226; 89000020240000766001520240651857P_0000_00000000000_000003461004226; 89000020240000766001520240651867P_0000_00000000000_000003461004226; 89000020240000766001520240651870P_0000_00000000000_000003461004226; 89000020240000766001520240651874P_0000_00000000000_000003461004226; 89000020240000766001520240651875P_0000_00000000000_000003461004226; 89000020240000766001520240651877P_0000_00000000000_000003461004226; 89000020240000766001520240651881P_0000_00000000000_000003461004226; 89000020240000766001520240651883P_0000_00000000000_000003461004226; 89000020240000766001520240651918P_0000_00000000000_000003461004226; 89000020240000766001520240652005P_0000_00000000000_000003461004226; 89000020240000766001520240652043P_0000_00000000000_000003461004226; 89000020240000766001520240652066P_0000_00000000000_000003461004226; 89000020240000766001520240652067P_0000_00000000000_000003461004226; 89000020240000766001520240652070P_0000_00000000000_000003461004226; 89000020240000766001520240652072P_0000_00000000000_000003461004226; 89000020240000766001520240652073P_0000_00000000000_000003461004226; 89000020240000766001520240652165P_0000_00000000000_000003461004226; 89000020240000766001520240652311P_0000_00000000000_000003461004226; 89000020240000766001520240652312P_0000_00000000000_000003461004226; 89000020240000766001520240652313P_0000_00000000000_000003461004226; 89000020240000766001520240652314P_0000_00000000000_000003461004226; 89000020240000766001520240652315P_0000_00000000000_000003461004226; 89000020240000766001520240652316P_0000_00000000000_000003461004226; 89000020240000766001520240652317P_0000_00000000000_000003461004226; 89000020240000766001520240652318P_0000_00000000000_000003461004226; 89000020240000766001520240652319P_0000_00000000000_000003461004226; 89000020240000766001520240652320P_0000_00000000000_000003461004226; 89000020240000766001520240652321P_0000_00000000000_000003461004226; 89000020240000766001520240652322P_0000_00000000000_000003461004226; 89000020240000766001520240652323P_0000_00000000000_000003461004226; 89000020240000766001520240652342P_0000_00000000000_000003461004226; 89000020240000766001520240652343P_0000_00000000000_000003461004226; 89000020240000766001520240652344P_0000_00000000000_000003461004226; 89000020240000766001520240652345P_0000_00000000000_000003461004226; 89000020240000766001520240652347P_0000_00000000000_000003461004226; 89000020240000766001520240652348P_0000_00000000000_000003461004226; 89000020240000766001520240652349P_0000_00000000000_000003461004226; 89000020240000766001520240652352P_0000_00000000000_000003461004226; 89000020240000766001520240652353P_0000_00000000000_000003461004226; 89000020240000766001520240652354P_0000_00000000000_000003461004226; 89000020240000766001520240652365P_0000_00000000000_000003461004226; 89000020240000766001520240652370P_0000_00000000000_000003461004226; 89000020240000766001520240652371P_0000_00000000000_000003461004226; 89000020240000766001520240652372P_0000_00000000000_000003461004226; 89000020240000766001520240652373P_0000_00000000000_000003461004226; 89000020240000766001520240652374P_0000_00000000000_000003461004226; 89000020240000766001520240652375P_0000_00000000000_000003461004226; 89000020240000766001520240652376P_0000_00000000000_000003461004226; 89000020240000766001520240652377P_0000_00000000000_000003461004226; 89000020240000766001520240652379P_0000_00000000000_000003461004226; 89000020240000766001520240652387P_0000_00000000000_000003461004226; 89000020240000766001520240652388P_0000_00000000000_000003461004226; 89000020240000766001520240652389P_0000_00000000000_000003461004226; 89000020240000766001520240652390P_0000_00000000000_000003461004226; 89000020240000766001520240652391P_0000_00000000000_000003461004226; 89000020240000766001520240652392P_0000_00000000000_000003461004226; 89000020240000766001520240652393P_0000_00000000000_000003461004226; 89000020240000766001520240652394P_0000_00000000000_000003461004226; 89000020240000766001520240652439P_0000_00000000000_000003461004226; 89000020240000766001520240652440P_0000_00000000000_000003461004226; 89000020240000766001520240652441P_0000_00000000000_000003461004226; 89000020240000766001520240652442P_0000_00000000000_000003461004226; 89000020240000766001520240652443P_0000_00000000000_000003461004226; 89000020240000766001520240652444P_0000_00000000000_000003461004226; 89000020240000766001520240652445P_0000_00000000000_000003461004226; 89000020240000766001520240652446P_0000_00000000000_000003461004226; 89000020240000766001520240652447P_0000_00000000000_000003461004226; 89000020240000766001520240652448P_0000_00000000000_000003461004226; 89000020240000766001520240652449P_0000_00000000000_000003461004226; 89000020240000766001520240652450P_0000_00000000000_000003
B97: =+IF(LEFT(MID(Controlos[[#This Row],[tabela]],22,5),1)="B",MID(Controlos[[#This Row],[tabela]],22,5),MID(Controlos[[#This Row],[tabela]],18,5)) -> B0500 | C97: =+IF(Controlos[[#This Row],[tipologia_teste]]="REGULAMENTAR",IF(LEFT(Controlos[[#This Row],[cod_kpi]],1)="v",IF(LEFT(Controlos[[#This Row],[descrição]],6)="Alerta","W","H"),"F"),0) -> 0 | F97: 2025-10-31 | G97: MIS_B0500_C0080 | H97: MISSINGS | I97: Validar que não existem registos por preencher (Missings) | J97: BU_LOANTAPE_WORK.OUT_B0500_GUARANTEES | K97: 0080_AMNT_CLLTRL | L97: 4730 | M97: 0
B98: =+IF(LEFT(MID(Controlos[[#This Row],[tabela]],22,5),1)="B",MID(Controlos[[#This Row],[tabela]],22,5),MID(Controlos[[#This Row],[tabela]],18,5)) -> B0500 | C98: =+IF(Controlos[[#This Row],[tipologia_teste]]="REGULAMENTAR",IF(LEFT(Controlos[[#This Row],[cod_kpi]],1)="v",IF(LEFT(Controlos[[#This Row],[descrição]],6)="Alerta","W","H"),"F"),0) -> 0 | F98: 2025-10-31 | G98: MIS_B0500_C0090 | H98: MISSINGS | I98: Validar que não existem registos por preencher (Missings) | J98: BU_LOANTAPE_WORK.OUT_B0500_GUARANTEES | K98: 0090_GUARANTEE_TRGGR | L98: 4730 | M98: 0
B99: =+IF(LEFT(MID(Controlos[[#This Row],[tabela]],22,5),1)="B",MID(Controlos[[#This Row],[tabela]],22,5),MID(Controlos[[#This Row],[tabela]],18,5)) -> B0500 | C99: =+IF(Controlos[[#This Row],[tipologia_teste]]="REGULAMENTAR",IF(LEFT(Controlos[[#This Row],[cod_kpi]],1)="v",IF(LEFT(Controlos[[#This Row],[descrição]],6)="Alerta","W","H"),"F"),0) -> 0 | F99: 2025-10-31 | G99: MIS_B0500_C0100 | H99: MISSINGS | I99: Validar que não existem registos por preencher (Missings) | J99: BU_LOANTAPE_WORK.OUT_B0500_GUARANTEES | K99: 0100_DT_MTRTY_CLLTRL | L99: 4730 | M99: 0
B100: =+IF(LEFT(MID(Controlos[[#This Row],[tabela]],22,5),1)="B",MID(Controlos[[#This Row],[tabela]],22,5),MID(Controlos[[#This Row],[tabela]],18,5)) -> B0500 | C100: =+IF(Controlos[[#This Row],[tipologia_teste]]="REGULAMENTAR",IF(LEFT(Controlos[[#This Row],[cod_kpi]],1)="v",IF(LEFT(Controlos[[#This Row],[descrição]],6)="Alerta","W","H"),"F"),0) -> 0 | F100: 2025-10-31 | G100: MIS_B0500_C0110 | H100: MISSINGS | I100: Validar que não existem registos por preencher (Missings) | J100: BU_LOANTAPE_WORK.OUT_B0500_GUARANTEES | K100: 0110_SCRTS_CLLTRL_ID | L100: 4730 | M100: 0
B101: =+IF(LEFT(MID(Controlos[[#This Row],[tabela]],22,5),1)="B",MID(Controlos[[#This Row],[tabela]],22,5),MID(Controlos[[#This Row],[tabela]],18,5)) -> B0500 | C101: =+IF(Controlos[[#This Row],[tipologia_teste]]="REGULAMENTAR",IF(LEFT(Controlos[[#This Row],[cod_kpi]],1)="v",IF(LEFT(Controlos[[#This Row],[descrição]],6)="Alerta","W","H"),"F"),0) -> 0 | F101: 2025-10-31 | G101: MIS_B0500_C0120 | H101: MISSINGS | I101: Validar que não existem registos por preencher (Missings) | J101: BU_LOANTAPE_WORK.OUT_B0500_GUARANTEES | K101: 0120_TYP_CLLTRLZTN | L101: 4730 | M101: 0
B102: =+IF(LEFT(MID(Controlos[[#This Row],[tabela]],22,5),1)="B",MID(Controlos[[#This Row],[tabela]],22,5),MID(Controlos[[#This Row],[tabela]],18,5)) -> B0500 | C102: =+IF(Controlos[[#This Row],[tipologia_teste]]="REGULAMENTAR",IF(LEFT(Controlos[[#This Row],[cod_kpi]],1)="v",IF(LEFT(Controlos[[#This Row],[descrição]],6)="Alerta","W","H"),"F"),0) -> 0 | F102: 2025-10-31 | G102: MIS_B0500_C0130 | H102: MISSINGS | I102: Validar que não existem registos por preencher (Missings) | J102: BU_LOANTAPE_WORK.OUT_B0500_GUARANTEES | K102: 0130_TYP_PRTCTN_VL | L102: 4730 | M102: 0
B103: =+IF(LEFT(MID(Controlos[[#This Row],[tabela]],22,5),1)="B",MID(Controlos[[#This Row],[tabela]],22,5),MID(Controlos[[#This Row],[tabela]],18,5)) -> B0500 | C103: =+IF(Controlos[[#This Row],[tipologia_teste]]="REGULAMENTAR",IF(LEFT(Controlos[[#This Row],[cod_kpi]],1)="v",IF(LEFT(Controlos[[#This Row],[descrição]],6)="Alerta","W","H"),"F"),0) -> 0 | F103: 2025-10-31 | G103: MIS_B0500_C0140 | H103: MISSINGS | I103: Validar que não existem registos por preencher (Missings) | J103: BU_LOANTAPE_WORK.OUT_B0500_GUARANTEES | K103: 0140_DT_VLTN_SCRTY | L103: 4730 | M103: 0
B104: =+IF(LEFT(MID(Controlos[[#This Row],[tabela]],22,5),1)="B",MID(Controlos[[#This Row],[tabela]],22,5),MID(Controlos[[#This Row],[tabela]],18,5)) -> B0500 | C104: =+IF(Controlos[[#This Row],[tipologia_teste]]="REGULAMENTAR",IF(LEFT(Controlos[[#This Row],[cod_kpi]],1)="v",IF(LEFT(Controlos[[#This Row],[descrição]],6)="Alerta","W","H"),"F"),0) -> 0 | F104: 2025-10-31 | G104: MIS_B0500_C0150 | H104: MISSINGS | I104: Validar que não existem registos por preencher (Missings) | J104: BU_LOANTAPE_WORK.OUT_B0500_GUARANTEES | K104: 0150_PRTCTN_VLTN_APPRCH | L104: 4730 | M104: 0
B105: =+IF(LEFT(MID(Controlos[[#This Row],[tabela]],22,5),1)="B",MID(Controlos[[#This Row],[tabela]],22,5),MID(Controlos[[#This Row],[tabela]],18,5)) -> B9000 | C105: =+IF(Controlos[[#This Row],[tipologia_teste]]="REGULAMENTAR",IF(LEFT(Controlos[[#This Row],[cod_kpi]],1)="v",IF(LEFT(Controlos[[#This Row],[descrição]],6)="Alerta","W","H"),"F"),0) -> 0 | F105: 2025-10-31 | G105: MIS_B9000_C0010 | H105: MISSINGS | I105: Validar que não existem registos por preencher (Missings) | J105: BU_LOANTAPE_WORK.OUT_B9000_COUNTERPARTIES | K105: 0010_ROW_NMBR | L105: 4740 | M105: 0
B106: =+IF(LEFT(MID(Controlos[[#This Row],[tabela]],22,5),1)="B",MID(Controlos[[#This Row],[tabela]],22,5),MID(Controlos[[#This Row],[tabela]],18,5)) -> B9000 | C106: =+IF(Controlos[[#This Row],[tipologia_teste]]="REGULAMENTAR",IF(LEFT(Controlos[[#This Row],[cod_kpi]],1)="v",IF(LEFT(Controlos[[#This Row],[descrição]],6)="Alerta","W","H"),"F"),0) -> 0 | F106: 2025-10-31 | G106: MIS_B9000_C0011 | H106: MISSINGS | I106: Validar que não existem registos por preencher (Missings) | J106: BU_LOANTAPE_WORK.OUT_B9000_COUNTERPARTIES | K106: 0011_TAB_ORIGIN | L106: 4740 | M106: 0
B107: =+IF(LEFT(MID(Controlos[[#This Row],[tabela]],22,5),1)="B",MID(Controlos[[#This Row],[tabela]],22,5),MID(Controlos[[#This Row],[tabela]],18,5)) -> B9000 | C107: =+IF(Controlos[[#This Row],[tipologia_teste]]="REGULAMENTAR",IF(LEFT(Controlos[[#This Row],[cod_kpi]],1)="v",IF(LEFT(Controlos[[#This Row],[descrição]],6)="Alerta","W","H"),"F"),0) -> 0 | F107: 2025-10-31 | G107: MIS_B9000_C0020 | H107: MISSINGS | I107: Validar que não existem registos por preencher (Missings) | J107: BU_LOANTAPE_WORK.OUT_B9000_COUNTERPARTIES | K107: 0020_UNIQ_ID_KNWN_CNTRPRTY | L107: 4740 | M107: 0
B108: =+IF(LEFT(MID(Controlos[[#This Row],[tabela]],22,5),1)="B",MID(Controlos[[#This Row],[tabela]],22,5),MID(Controlos[[#This Row],[tabela]],18,5)) -> B9000 | C108: =+IF(Controlos[[#This Row],[tipologia_teste]]="REGULAMENTAR",IF(LEFT(Controlos[[#This Row],[cod_kpi]],1)="v",IF(LEFT(Controlos[[#This Row],[descrição]],6)="Alerta","W","H"),"F"),0) -> 0 | F108: 2025-10-31 | G108: MIS_B9000_C0030 | H108: MISSINGS | I108: Validar que não existem registos por preencher (Missings) | J108: BU_LOANTAPE_WORK.OUT_B9000_COUNTERPARTIES | K108: 0030_CNTRPRTY_RSLTN_GRP | L108: 4740 | M108: 4740 | N108: PTBSRDOM0037, 0000003686; PTBSREOM0028, Not applicable; PTCPP0AM0007, Not applicable; PTCPP0AM0007, 0000003686; PTCPP0AM0007, 5100011001; PTSTOCOM0007, 0000003686; PTSTOEOM0021, 0000003686; PTSTOFOM0004, 0000003686; PTSTOGOM0003, 0000003686; PTSTOHOM0002, 0000003686; 31000000000000000962304890482490P_0000_00000000000_000006511000505, 6511000505; 31000304140330096000000000000000P_0000_00000000000_000000000003686, 0000003686; 31000307044893096000000000000000P_0000_00000000000_000000000003686, 0000003686; 31000307530917096000000000000000P_0000_00000000000_000000000003686, 0000003686; 31000311450813096000000000000000P_0000_00000000000_000000000003686, 0000003686; 31000311847794096000000000000000P_0000_00000000000_000000000003686, 0000003686; 31000313517171096000000000000000P_0000_00000000000_000000000003686, 0000003686; 31000315970006096000000000000000P_0000_00000000000_000000000003686, 0000003686; 31000315970121096000000000000000P_0000_00000000000_000000000003686, 0000003686; 31000315970139096000000000000000P_0000_00000000000_000000000003686, 0000003686; 31000315970188096000000000000000P_0000_00000000000_000000000003686, 0000003686; 31000315970212096000000000000000P_0000_00000000000_000000000003686, 0000003686; 31000315970238096000000000000000P_0000_00000000000_000000000003686, 0000003686; 31000315970261096000000000000000P_0000_00000000000_000000000003686, 0000003686; 31000315970279096000000000000000P_0000_00000000000_000000000003686, 0000003686; 31000315970311096000000000000000P_0000_00000000000_000000000003686, 0000003686; 31000315970329096000000000000000P_0000_00000000000_000000000003686, 0000003686; 31000315970345096000000000000000P_0000_00000000000_000000000003686, 0000003686; 31000315970402096000000000000000P_0000_00000000000_000000000003686, 0000003686; 31000315970428096000000000000000P_0000_00000000000_000000000003686, 0000003686; 31000315970469096000000000000000P_0000_00000000000_000000000003686, 0000003686; 31000315979890096000000000000000P_0000_00000000000_000006511000505, 6511000505; 31000318293090097000000000000000P_0000_00000000000_000008000176024, 8000176024; 31000318542009097000000000000000P_0000_00000000000_000006511000505, 6511000505; 31000318628196097000000000000000P_0000_00000000000_000006511000505, 6511000505; 31000318628592097000000000000000P_0000_00000000000_000008000176024, 8000176024; 31000318629012097000000000000000P_0000_00000000000_000008000176024, 8000176024; 31000318636603097000000000000000P_0000_00000000000_000008000176024, 8000176024; 31000318637213097000000000000000P_0000_00000000000_000008000176024, 8000176024; 31000322311418096000000000000000P_0000_00000000000_000000000003686, 0000003686; 89000020240000766001520240649818P_0000_00000000000_000003461004226, 3461004226; 89000020240000766001520240649824P_0000_00000000000_000003461004226, 3461004226; 89000020240000766001520240649825P_0000_00000000000_000003461004226, 3461004226; 89000020240000766001520240649826P_0000_00000000000_000003461004226, 3461004226; 89000020240000766001520240649827P_0000_00000000000_000003461004226, 3461004226; 89000020240000766001520240649838P_0000_00000000000_000003461004226, 3461004226; 89000020240000766001520240649839P_0000_00000000000_000003461004226, 3461004226; 89000020240000766001520240649873P_0000_00000000000_000003461004226, 3461004226; 89000020240000766001520240649874P_0000_00000000000_000003461004226, 3461004226; 89000020240000766001520240649875P_0000_00000000000_000003461004226, 3461004226; 89000020240000766001520240649894P_0000_00000000000_000003461004226, 3461004226; 89000020240000766001520240649898P_0000_00000000000_000003461004226, 3461004226; 89000020240000766001520240649899P_0000_00000000000_000003461004226, 3461004226; 89000020240000766001520240649900P_0000_00000000000_000003461004226, 3461004226; 89000020240000766001520240649901P_0000_00000000000_000003461004226, 3461004226; 89000020240000766001520240649909P_0000_00000000000_000003461004226, 3461004226; 89000020240000766001520240649910P_0000_00000000000_000003461004226, 3461004226; 89000020240000766001520240649911P_0000_00000000000_000003461004226, 3461004226; 89000020240000766001520240649912P_0000_00000000000_000003461004226, 3461004226; 89000020240000766001520240649913P_0000_00000000000_000003461004226, 3461004226; 89000020240000766001520240649914P_0000_00000000000_000003461004226, 3461004226; 89000020240000766001520240649915P_0000_00000000000_000003461004226, 3461004226; 89000020240000766001520240649916P_0000_00000000000_000003461004226, 3461004226; 89000020240000766001520240649917P_0000_00000000000_000003461004226, 3461004226; 89000020240000766001520240649918P_0000_00000000000_000003461004226, 3461004226; 89000020240000766001520240649919P_0000_00000000000_000003461004226, 3461004226; 89000020240000766001520240649920P_0000_00000000000_000003461004226, 3461004226; 89000020240000766001520240649921P_0000_00000000000_000003461004226, 3461004226; 89000020240000766001520240649942P_0000_00000000000_000003461004226, 3461004226; 89000020240000766001520240649943P_0000_00000000000_000003461004226, 3461004226; 89000020240000766001520240649944P_0000_00000000000_000003461004226, 3461004226; 89000020240000766001520240649945P_0000_00000000000_000003461004226, 3461004226; 89000020240000766001520240649946P_0000_00000000000_000003461004226, 3461004226; 89000020240000766001520240650004P_0000_00000000000_000003461004226, 3461004226; 89000020240000766001520240650005P_0000_00000000000_000003461004226, 3461004226; 89000020240000766001520240650006P_0000_00000000000_000003461004226, 3461004226; 89000020240000766001520240650007P_0000_00000000000_000003461004226, 3461004226; 89000020240000766001520240650008P_0000_00000000000_000003461004226, 3461004226; 89000020240000766001520240650009P_0000_00000000000_000003461004226, 3461004226; 89000020240000766001520240650010P_0000_00000000000_000003461004226, 3461004226; 89000020240000766001520240650011P_0000_00000000000_000003461004226, 3461004226; 89000020240000766001520240650116P_0000_00000000000_000003461004226, 3461004226; 89000020240000766001520240650192P_0000_00000000000_000003461004226, 3461004226; 89000020240000766001520240650202P_0000_00000000000_000003461004226, 3461004226; 89000020240000766001520240650203P_0000_00000000000_000003461004226, 3461004226; 89000020240000766001520240650204P_0000_00000000000_000003461004226, 3461004226; 89000020240000766001520240650205P_0000_00000000000_000003461004226, 3461004226; 89000020240000766001520240650206P_0000_00000000000_000003461004226, 3461004226; 89000020240000766001520240650207P_0000_00000000000_000003461004226, 3461004226; 89000020240000766001520240650208P_0000_00000000000_000003461004226, 3461004226; 89000020240000766001520240650349P_0000_00000000000_000003461004226, 3461004226; 89000020240000766001520240650350P_0000_00000000000_000003461004226, 3461004226; 89000020240000766001520240650351P_0000_00000000000_000003461004226, 3461004226; 89000020240000766001520240650352P_0000_00000000000_000003461004226, 3461004226; 89000020240000766001520240650353P_0000_00000000000_000003461004226, 3461004226; 89000020240000766001520240650354P_0000_00000000000_000003461004226, 3461004226; 89000020240000766001520240650355P_0000_00000000000_000003461004226, 3461004226; 89000020240000766001520240650356P_0000_00000000000_000003461004226, 3461004226; 89000020240000766001520240650357P_0000_00000000000_000003461004226, 3461004226; 89000020240000766001520240650358P_0000_00000000000_000003461004226, 3461004226; 89000020240000766001520240650359P_0000_00000000000_000003461004226, 3461004226; 89000020240000766001520240650360P_0000_00000000000_000003461004226, 3461004226; 89000020240000766001520240650361P_0000_00000000000_000003461004226, 3461004226; 89000020240000766001520240650362P_0000_00000000000_000003461004226, 3461004226; 89000020240000766001520240650363P_0000_00000000000_000003461004226, 3461004226; 89000020240000766001520240650364P_0000_00000000000_000003461004226, 3461004226; 89000020240000766001520240650365P_0000_00000000000_000003461004226, 3461004226; 89000020240000766001520240650366P_0000_00000000000_000003461004226, 3461004226; 89000020240000766001520240650367P_0000_00000000000_000003461004226, 3461004226; 89000020240000766001520240650368P_0000_00000000000_000003461004226, 3461004226; 89000020240000766001520240650369P_0000_00000000000_000003461004226, 3461004226; 89000020240000766001520240650370P_0000_00000000000_000003461004226, 3461004226; 89000020240000766001520240650371P_0000_00000000000_000003461004226, 3461004226; 89000020240000766001520240650372P_0000_00000000000_000003461004226, 3461004226; 89000020240000766001520240650373P_0000_00000000000_000003461004226, 3461004226; 89000020240000766001520240650374P_0000_00000000000_000003461004226, 3461004226; 89000020240000766001520240650375P_0000_00000000000_000003461004226, 3461004226; 89000020240000766001520240650376P_0000_00000000000_000003461004226, 3461004226; 89000020240000766001520240650377P_0000_00000000000_000003461004226, 3461004226; 89000020240000766001520240650378P_0000_00000000000_000003461004226, 3461004226; 89000020240000766001520240650379P_0000_00000000000_000003461004226, 3461004226; 89000020240000766001520240650380P_0000_00000000000_000003461004226, 3461004226; 89000020240000766001520240650381P_0000_00000000000_000003461004226, 3461004226; 89000020240000766001520240650382P_0000_00000000000_000003461004226, 3461004226; 89000020240000766001520240650383P_0000_00000000000_000003461004226, 3461004226; 89000020240000766001520240650384P_0000_00000000000_000003461004226, 3461004226; 89000020240000766001520240650385P_0000_00000000000_000003461004226, 3461004226; 89000020240000766001520240650386P_0000_00000000000_000003461004226, 3461004226; 89000020240000766001520240650387P_0000_00000000000_000003461004226, 3461004226; 89000020240000766001520240650388P_0000_00000000000_000003461004226, 3461004226; 89000020240000766001520240650389P_0000_00000000000_000003461004226, 3461004226; 89000020240000766001520240650390P_0000_00000000000_000003461004226, 3461004226; 89000020240000766001520240650391P_0000_00000000000_000003461004226, 3461004226; 89000020240000766001520240650392P_0000_00000000000_000003461004226, 3461004226; 89000020240000766001520240650393P_0000_00000000000_000003461004226, 3461004226; 89000020240000766001520240650394P_0000_00000000000_000003461004226, 3461004226; 89000020240000766001520240650396P_0000_00000000000_000003461004226, 3461004226; 89000020240000766001520240650397P_0000_00000000000_000003461004226, 3461004226; 89000020240000766001520240650398P_0000_00000000000_000003461004226, 3461004226; 89000020240000766001520240650399P_0000_00000000000_000003461004226, 3461004226; 89000020240000766001520240650400P_0000_00000000000_000003461004226, 3461004226; 89000020240000766001520240650401P_0000_00000000000_000003461004226, 3461004226; 89000020240000766001520240650402P_0000_00000000000_000003461004226, 3461004226; 89000020240000766001520240650403P_0000_00000000000_000003461004226, 3461004226; 89000020240000766001520240650404P_0000_00000000000_000003461004226, 3461004226; 89000020240000766001520240650405P_0000_00000000000_000003461004226, 3461004226; 89000020240000766001520240650406P_0000_00000000000_000003461004226, 3461004226; 89000020240000766001520240650407P_0000_00000000000_000003461004226, 3461004226; 89000020240000766001520240650408P_0000_00000000000_000003461004226, 3461004226; 89000020240000766001520240650409P_0000_00000000000_000003461004226, 3461004226; 89000020240000766001520240650410P_0000_00000000000_000003461004226, 3461004226; 89000020240000766001520240650411P_0000_00000000000_000003461004226, 3461004226; 89000020240000766001520240650412P_0000_00000000000_000003461004226, 3461004226; 89000020240000766001520240650413P_0000_00000000000_000003461004226, 3461004226; 89000020240000766001520240650414P_0000_00000000000_000003461004226, 3461004226; 89000020240000766001520240650415P_0000_00000000000_000003461004226, 3461004226; 89000020240000766001520240650416P_0000_00000000000_000003461004226, 3461004226; 89000020240000766001520240650417P_0000_00000000000_000003461004226, 3461004226; 89000020240000766001520240650418P_0000_00000000000_000003461004226, 3461004226; 89000020240000766001520240650419P_0000_00000000000_000003461004226, 3461004226; 89000020240000766001520240650420P_0000_00000000000_000003461004226, 3461004226; 89000020240000766001520240650421P_0000_00000000000_000003461004226, 3461004226; 89000020240000766001520240650422P_0000_00000000000_000003461004226, 3461004226; 89000020240000766001520240650423P_0000_00000000000_000003461004226, 3461004226; 89000020240000766001520240650424P_0000_00000000000_000003461004226, 3461004226; 89000020240000766001520240650425P_0000_00000000000_000003461004226, 3461004226; 89000020240000766001520240650426P_0000_00000000000_000003461004226, 3461004226; 89000020240000766001520240650427P_0000_00000000000_000003461004226, 3461004226; 89000020240000766001520240650428P_0000_00000000000_000003461004226, 3461004226; 89000020240000766001520240650429P_0000_00000000000_000003461004226, 3461004226; 89000020240000766001520240650431P_0000_00000000000_000003461004226, 3461004226; 89000020240000766001520240650432P_0000_00000000000_000003461004226, 3461004226; 89000020240000766001520240650433P_0000_00000000000_000003461004226, 3461004226; 89000020240000766001520240650434P_0000_00000000000_000003461004226, 3461004226; 89000020240000766001520240650435P_0000_00000000000_000003461004226, 3461004226; 89000020240000766001520240650436P_0000_00000000000_000003461004226, 3461004226; 89000020240000766001520240650476P_0000_00000000000_000003461004226, 3461004226; 89000020240000766001520240650477P_0000_00000000000_000003461004226, 3461004226; 89000020240000766001520240650478P_0000_00000000000_000003461004226, 3461004226; 89000020240000766001520240650479P_0000_00000000000_000003461004226, 3461004226; 89000020240000766001520240650480P_0000_00000000000_000003461004226, 3461004226; 89000020240000766001520240650481P_0000_00000000000_000003461004226, 3461004226; 89000020240000766001520240650482P_0000_00000000000_000003461004226, 3461004226; 89000020240000766001520240650483P_0000_00000000000_000003461004226, 3461004226; 89000020240000766001520240650484P_0000_00000000000_000003461004226, 3461004226; 89000020240000766001520240650485P_0000_00000000000_000003461004226, 3461004226; 89000020240000766001520240650486P_0000_00000000000_000003461004226, 3461004226; 89000020240000766001520240650487P_0000_00000000000_000003461004226, 3461004226; 89000020240000766001520240650488P_0000_00000000000_000003461004226, 3461004226; 89000020240000766001520240650489P_0000_00000000000_000003461004226, 3461004226; 89000020240000766001520240650490P_0000_00000000000_000003461004226, 3461004226; 89000020240000766001520240650491P_0000_00000000000_000003461004226, 3461004226; 89000020240000766001520240650492P_0000_00000000000_000003461004226, 3461004226; 89000020240000766001520240650493P_0000_00000000000_000003461004226, 3461004226; 89000020240000766001520240650494P_0000_00000000000_000003461004226, 3461004226; 89000020240000766001520240650495P_0000_00000000000_000003461004226, 3461004226; 89000020240000766001520240650496P_0000_00000000000_000003461004226, 3461004226; 89000020240000766001520240650497P_0000_00000000000_000003461004226, 3461004226; 89000020240000766001520240650498P_0000_00000000000_000003461004226, 3461004226; 89000020240000766001520240650499P_0000_00000000000_000003461004226, 3461004226; 89000020240000766001520240650500P_0000_00000000000_000003461004226, 3461004226; 89000020240000766001520240650501P_0000_00000000000_000003461004226, 3461004226; 89000020240000766001520240650502P_0000_00000000000_000003461004226, 3461004226; 89000020240000766001520240650503P_0000_00000000000_000003461004226, 3461004226; 89000020240000766001520240650504P_0000_00000000000_000003461004226, 3461004226; 89000020240000766001520240650505P_0000_00000000000_000003461004226, 3461004226; 89000020240000766001520240650506P_0000_00000000000_000003461004226, 3461004226; 89000020240000766001520240650507P_0000_00000000000_000003461004226, 3461004226; 89000020240000766001520240650508P_0000_00000000000_000003461004226, 3461004226; 89000020240000766001520240650509P_0000_00000000000_000003461004226, 3461004226; 89000020240000766001520240650510P_0000_00000000000_000003461004226, 3461004226; 89000020240000766001520240650511P_0000_00000000000_000003461004226, 3461004226; 89000020240000766001520240650512P_0000_00000000000_000003461004226, 3461004226; 89000020240000766001520240650513P_0000_00000000000_000003461004226, 3461004226; 89000020240000766001520240650514P_0000_00000000000_000003461004226, 3461004226; 89000020240000766001520240650515P_0000_00000000000_000003461004226, 3461004226; 89000020240000766001520240650516P_0000_00000000000_000003461004226, 3461004226; 89000020240000766001520240650517P_0000_00000000000_000003461004226, 3461004226; 89000020240000766001520240650518P_0000_00000000000_000003461004226, 3461004226; 89000020240000766001520240650519P_0000_00000000000_000003461004226, 3461004226; 89000020240000766001520240650520P_0000_00000000000_000003461004226, 3461004226; 89000020240000766001520240650521P_0000_00000000000_000003461004226, 3461004226; 89000020240000766001520240650522P_0000_00000000000_000003461004226, 3461004226; 89000020240000766001520240650523P_0000_00000000000_000003461004226, 3461004226; 89000020240000766001520240650524P_0000_00000000000_000003461004226, 3461004226; 89000020240000766001520240650525P_0000_00000000000_000003461004226, 3461004226; 89000020240000766001520240650526P_0000_00000000000_000003461004226, 3461004226; 89000020240000766001520240650527P_0000_00000000000_000003461004226, 3461004226; 89000020240000766001520240650528P_0000_00000000000_000003461004226, 3461004226; 89000020240000766001520240650529P_0000_00000000000_000003461004226, 3461004226; 89000020240000766001520240650530P_0000_00000000000_000003461004226, 3461004226; 89000020240000766001520240650531P_0000_00000000000_000003461004226, 3461004226; 89000020240000766001520240650532P_0000_00000000000_000003461004226, 3461004226; 89000020240000766001520240650533P_0000_00000000000_000003461004226, 3461004226; 89000020240000766001520240650534P_0000_00000000000_000003461004226, 3461004226; 89000020240000766001520240650535P_0000_00000000000_000003461004226, 3461004226; 89000020240000766001520240650536P_0000_00000000000_000003461004226, 3461004226; 89000020240000766001520240650537P_0000_00000000000_000003461004226, 3461004226; 89000020240000766001520240650538P_0000_00000000000_000003461004226, 3461004226; 89000020240000766001520240650539P_0000_00000000000_000003461004226, 3461004226; 89000020240000766001520240650540P_0000_00000000000_000003461004226, 3461004226; 89000020240000766001520240650541P_0000_00000000000_000003461004226, 3461004226; 89000020240000766001520240650542P_0000_00000000000_000003461004226, 3461004226; 89000020240000766001520240650543P_0000_00000000000_000003461004226, 3461004226; 89000020240000766001520240650544P_0000_00000000000_000003461004226, 3461004226; 89000020240000766001520240650545P_0000_00000000000_000003461004226, 3461004226; 89000020240000766001520240650546P_0000_00000000000_000003461004226, 3461004226; 89000020240000766001520240650547P_0000_00000000000_000003461004226, 3461004226; 89000020240000766001520240650548P_0000_00000000000_000003461004226, 3461004226; 89000020240000766001520240650549P_0000_00000000000_000003461004226, 3461004226; 89000020240000766001520240650550P_0000_00000000000_000003461004226, 3461004226; 89000020240000766001520240650551P_0000_00000000000_000003461004226, 3461004226; 89000020240000766001520240650552P_0000_00000000000_000003461004226, 3461004226; 89000020240000766001520240650553P_0000_00000000000_000003461004226, 3461004226; 89000020240000766001520240650554P_0000_00000000000_000003461004226, 3461004226; 89000020240000766001520240650555P_0000_00000000000_000003461004226, 3461004226; 89000020240000766001520240650556P_0000_00000000000_000003461004226, 3461004226; 89000020240000766001520240650557P_0000_00000000000_000003461004226, 3461004226; 89000020240000766001520240650558P_0000_00000000000_000003461004226, 3461004226; 89000020240000766001520240650559P_0000_00000000000_000003461004226, 3461004226; 89000020240000766001520240650560P_0000_00000000000_000003461004226, 3461004226; 89000020240000766001520240650561P_0000_00000000000_000003461004226, 3461004226; 89000020240000766001520240650562P_0000_00000000000_000003461004226, 3461004226; 89000020240000766001520240650563P_0000_00000000000_000003461004226, 3461004226; 89000020240000766001520240650564P_0000_00000000000_000003461004226, 3461004226; 89000020240000766001520240650565P_0000_00000000000_000003461004226, 3461004226; 89000020240000766001520240650566P_0000_00000000000_000003461004226, 3461004226; 89000020240000766001520240650567P_0000_00000000000_000003461004226, 3461004226; 89000020240000766001520240650568P_0000_00000000000_000003461004226, 3461004226; 89000020240000766001520240650569P_0000_00000000000_000003461004226, 3461004226; 89000020240000766001520240650783P_0000_00000000000_000003461004226, 3461004226; 89000020240000766001520240650784P_0000_00000000000_000003461004226, 3461004226; 89000020240000766001520240650785P_0000_00000000000_000003461004226, 3461004226; 89000020240000766001520240650786P_0000_00000000000_000003461004226, 3461004226; 89000020240000766001520240650787P_0000_00000000000_000003461004226, 3461004226; 89000020240000766001520240650788P_0000_00000000000_000003461004226, 3461004226; 89000020240000766001520240650851P_0000_00000000000_000003461004226, 3461004226; 89000020240000766001520240650853P_0000_00000000000_000003461004226, 3461004226; 89000020240000766001520240650865P_0000_00000000000_000003461004226, 3461004226; 89000020240000766001520240650868P_0000_00000000000_000003461004226, 3461004226; 89000020240000766001520240650869P_0000_00000000000_000003461004226, 3461004226; 89000020240000766001520240650873P_0000_00000000000_000003461004226, 3461004226; 89000020240000766001520240650875P_0000_00000000000_000003461004226, 3461004226; 89000020240000766001520240650930P_0000_00000000000_000003461004226, 3461004226; 89000020240000766001520240650947P_0000_00000000000_000003461004226, 3461004226; 89000020240000766001520240650948P_0000_00000000000_000003461004226, 3461004226; 89000020240000766001520240650949P_0000_00000000000_000003461004226, 3461004226; 89000020240000766001520240650950P_0000_00000000000_000003461004226, 3461004226; 89000020240000766001520240650951P_0000_00000000000_000003461004226, 3461004226; 89000020240000766001520240650952P_0000_00000000000_000003461004226, 3461004226; 89000020240000766001520240650953P_0000_00000000000_000003461004226, 3461004226; 89000020240000766001520240650954P_0000_00000000000_000003461004226, 3461004226; 89000020240000766001520240650955P_0000_00000000000_000003461004226, 3461004226; 89000020240000766001520240650956P_0000_00000000000_000003461004226, 3461004226; 89000020240000766001520240650957P_0000_00000000000_000003461004226, 3461004226; 89000020240000766001520240650958P_0000_00000000000_000003461004226, 3461004226; 89000020240000766001520240650959P_0000_00000000000_000003461004226, 3461004226; 89000020240000766001520240650960P_0000_00000000000_000003461004226, 3461004226; 89000020240000766001520240650961P_0000_00000000000_000003461004226, 3461004226; 89000020240000766001520240650962P_0000_00000000000_000003461004226, 3461004226; 89000020240000766001520240650968P_0000_00000000000_000003461004226, 3461004226; 89000020240000766001520240650969P_0000_00000000000_000003461004226, 3461004226; 89000020240000766001520240650970P_0000_00000000000_000003461004226, 3461004226; 89000020240000766001520240650971P_0000_00000000000_000003461004226, 3461004226; 89000020240000766001520240650972P_0000_00000000000_000003461004226, 3461004226; 89000020240000766001520240650973P_0000_00000000000_000003461004226, 3461004226; 89000020240000766001520240650974P_0000_00000000000_000003461004226, 3461004226; 89000020240000766001520240650975P_0000_00000000000_000003461004226, 3461004226; 89000020240000766001520240650976P_0000_00000000000_000003461004226, 3461004226; 89000020240000766001520240650978P_0000_00000000000_000003461004226, 3461004226; 89000020240000766001520240650979P_0000_00000000000_000003461004226, 3461004226; 89000020240000766001520240650980P_0000_00000000000_000003461004226, 3461004226; 89000020240000766001520240650981P_0000_00000000000_000003461004226, 3461004226; 89000020240000766001520240650982P_0000_00000000000_000003461004226, 3461004226; 89000020240000766001520240650983P_0000_00000000000_000003461004226, 3461004226; 89000020240000766001520240650984P_0000_00000000000_000003461004226, 3461004226; 89000020240000766001520240650985P_0000_00000000000_000003461004226, 3461004226; 89000020240000766001520240650986P_0000_00000000000_000003461004226, 3461004226; 89000020240000766001520240650987P_0000_00000000000_000003461004226, 3461004226; 89000020240000766001520240650988P_0000_00000000000_000003461004226, 3461004226; 89000020240000766001520240650989P_0000_00000000000_000003461004226, 3461004226; 89000020240000766001520240650990P_0000_00000000000_000003461004226, 3461004226; 89000020240000766001520240650991P_0000_00000000000_000003461004226, 3461004226; 89000020240000766001520240650992P_0000_00000000000_000003461004226, 3461004226; 89000020240000766001520240650993P_0000_00000000000_000003461004226, 3461004226; 89000020240000766001520240650994P_0000_00000000000_000003461004226, 3461004226; 89000020240000766001520240650995P_0000_00000000000_000003461004226, 3461004226; 89000020240000766001520240650996P_0000_00000000000_000003461004226, 3461004226; 89000020240000766001520240650997P_0000_00000000000_000003461004226, 3461004226; 89000020240000766001520240650998P_0000_00000000000_000003461004226, 3461004226; 89000020240000766001520240650999P_0000_00000000000_000003461004226, 3461004226; 89000020240000766001520240651000P_0000_00000000000_000003461004226, 3461004226; 89000020240000766001520240651001P_0000_00000000000_000003461004226, 3461004226; 89000020240000766001520240651002P_0000_00000000000_000003461004226, 3461004226; 89000020240000766001520240651003P_0000_00000000000_000003461004226, 3461004226; 89000020240000766001520240651004P_0000_00000000000_000003461004226, 3461004226; 89000020240000766001520240651005P_0000_00000000000_000003461004226, 3461004226; 89000020240000766001520240651006P_0000_00000000000_000003461004226, 3461004226; 89000020240000766001520240651020P_0000_00000000000_000003461004226, 3461004226; 89000020240000766001520240651095P_0000_00000000000_000003461004226, 3461004226; 89000020240000766001520240651174P_0000_00000000000_000003461004226, 3461004226; 89000020240000766001520240651175P_0000_00000000000_000003461004226, 3461004226; 89000020240000766001520240651177P_0000_00000000000_000003461004226, 3461004226; 89000020240000766001520240651179P_0000_00000000000_000003461004226, 3461004226; 89000020240000766001520240651180P_0000_00000000000_000003461004226, 3461004226; 89000020240000766001520240651187P_0000_00000000000_000003461004226, 3461004226; 89000020240000766001520240651188P_0000_00000000000_000003461004226, 3461004226; 89000020240000766001520240651189P_0000_00000000000_000003461004226, 3461004226; 89000020240000766001520240651190P_0000_00000000000_000003461004226, 3461004226; 89000020240000766001520240651192P_0000_00000000000_000003461004226, 3461004226; 89000020240000766001520240651193P_0000_00000000000_000003461004226, 3461004226; 89000020240000766001520240651194P_0000_00000000000_000003461004226, 3461004226; 89000020240000766001520240651195P_0000_00000000000_000003461004226, 3461004226; 89000020240000766001520240651196P_0000_00000000000_000003461004226, 3461004226; 89000020240000766001520240651197P_0000_00000000000_000003461004226, 3461004226; 89000020240000766001520240651198P_0000_00000000000_000003461004226, 3461004226; 89000020240000766001520240651199P_0000_00000000000_000003461004226, 3461004226; 89000020240000766001520240651200P_0000_00000000000_000003461004226, 3461004226; 89000020240000766001520240651201P_0000_00000000000_000003461004226, 3461004226; 89000020240000766001520240651202P_0000_00000000000_000003461004226, 3461004226; 89000020240000766001520240651203P_0000_00000000000_000003461004226, 3461004226; 89000020240000766001520240651204P_0000_00000000000_000003461004226, 3461004226; 89000020240000766001520240651307P_0000_00000000000_000003461004226, 3461004226; 89000020240000766001520240651409P_0000_00000000000_000003461004226, 3461004226; 89000020240000766001520240651410P_0000_00000000000_000003461004226, 3461004226; 89000020240000766001520240651411P_0000_00000000000_000003461004226, 3461004226; 89000020240000766001520240651412P_0000_00000000000_000003461004226, 3461004226; 89000020240000766001520240651444P_0000_00000000000_000003461004226, 3461004226; 89000020240000766001520240651449P_0000_00000000000_000003461004226, 3461004226; 89000020240000766001520240651453P_0000_00000000000_000003461004226, 3461004226; 89000020240000766001520240651454P_0000_00000000000_000003461004226, 3461004226; 89000020240000766001520240651455P_0000_00000000000_000003461004226, 3461004226; 89000020240000766001520240651456P_0000_00000000000_000003461004226, 3461004226; 89000020240000766001520240651464P_0000_00000000000_000003461004226, 3461004226; 89000020240000766001520240651468P_0000_00000000000_000003461004226, 3461004226; 89000020240000766001520240651470P_0000_00000000000_000003461004226, 3461004226; 89000020240000766001520240651471P_0000_00000000000_000003461004226, 3461004226; 89000020240000766001520240651473P_0000_00000000000_000003461004226, 3461004226; 89000020240000766001520240651474P_0000_00000000000_000003461004226, 3461004226; 89000020240000766001520240651475P_0000_00000000000_000003461004226, 3461004226; 89000020240000766001520240651476P_0000_00000000000_000003461004226, 3461004226; 89000020240000766001520240651477P_0000_00000000000_000003461004226, 3461004226; 89000020240000766001520240651643P_0000_00000000000_000003461004226, 3461004226; 89000020240000766001520240651644P_0000_00000000000_000003461004226, 3461004226; 89000020240000766001520240651645P_0000_00000000000_000003461004226, 3461004226; 89000020240000766001520240651684P_0000_00000000000_000003461004226, 3461004226; 89000020240000766001520240651693P_0000_00000000000_000003461004226, 3461004226; 89000020240000766001520240651694P_0000_00000000000_000003461004226, 3461004226; 89000020240000766001520240651695P_0000_00000000000_000003461004226, 3461004226; 89000020240000766001520240651696P_0000_00000000000_000003461004226, 3461004226; 89000020240000766001520240651697P_0000_00000000000_000003461004226, 3461004226; 89000020240000766001520240651698P_0000_00000000000_000003461004226, 3461004226; 89000020240000766001520240651699P_0000_00000000000_000003461004226, 3461004226; 89000020240000766001520240651700P_0000_00000000000_000003461004226, 3461004226; 89000020240000766001520240651701P_0000_00000000000_000003461004226, 3461004226; 89000020240000766001520240651702P_0000_00000000000_000003461004226, 3461004226; 89000020240000766001520240651706P_0000_00000000000_000003461004226, 3461004226; 89000020240000766001520240651707P_0000_00000000000_000003461004226, 3461004226; 89000020240000766001520240651708P_0000_00000000000_000003461004226, 3461004226; 89000020240000766001520240651709P_0000_00000000000_000003461004226, 3461004226; 89000020240000766001520240651710P_0000_00000000000_000003461004226, 3461004226; 89000020240000766001520240651711P_0000_00000000000_000003461004226, 3461004226; 89000020240000766001520240651712P_0000_00000000000_000003461004226, 3461004226; 89000020240000766001520240651713P_0000_00000000000_000003461004226, 3461004226; 89000020240000766001520240651714P_0000_00000000000_000003461004226, 3461004226; 89000020240000766001520240651715P_0000_00000000000_000003461004226, 3461004226; 89000020240000766001520240651716P_0000_00000000000_000003461004226, 3461004226; 89000020240000766001520240651717P_0000_00000000000_000003461004226, 3461004226; 89000020240000766001520240651718P_0000_00000000000_000003461004226, 3461004226; 89000020240000766001520240651719P_0000_00000000000_000003461004226, 3461004226; 89000020240000766001520240651720P_0000_00000000000_000003461004226, 3461004226; 89000020240000766001520240651721P_0000_00000000000_000003461004226, 3461004226; 89000020240000766001520240651722P_0000_00000000000_000003461004226, 3461004226; 89000020240000766001520240651723P_0000_00000000000_000003461004226, 3461004226; 89000020240000766001520240651727P_0000_00000000000_000003461004226, 3461004226; 89000020240000766001520240651728P_0000_00000000000_000003461004226, 3461004226; 89000020240000766
B109: =+IF(LEFT(MID(Controlos[[#This Row],[tabela]],22,5),1)="B",MID(Controlos[[#This Row],[tabela]],22,5),MID(Controlos[[#This Row],[tabela]],18,5)) -> B9000 | C109: =+IF(Controlos[[#This Row],[tipologia_teste]]="REGULAMENTAR",IF(LEFT(Controlos[[#This Row],[cod_kpi]],1)="v",IF(LEFT(Controlos[[#This Row],[descrição]],6)="Alerta","W","H"),"F"),0) -> 0 | F109: 2025-10-31 | G109: MIS_B9000_C0040 | H109: MISSINGS | I109: Validar que não existem registos por preencher (Missings) | J109: BU_LOANTAPE_WORK.OUT_B9000_COUNTERPARTIES | K109: 0040_CNTRPRTY_NM | L109: 4740 | M109: 2 | N109: PTBSREOM0028, Not applicable; PTCPP0AM0007, Not applicable
B110: =+IF(LEFT(MID(Controlos[[#This Row],[tabela]],22,5),1)="B",MID(Controlos[[#This Row],[tabela]],22,5),MID(Controlos[[#This Row],[tabela]],18,5)) -> B9000 | C110: =+IF(Controlos[[#This Row],[tipologia_teste]]="REGULAMENTAR",IF(LEFT(Controlos[[#This Row],[cod_kpi]],1)="v",IF(LEFT(Controlos[[#This Row],[descrição]],6)="Alerta","W","H"),"F"),0) -> 0 | F110: 2025-10-31 | G110: MIS_B9000_C0050 | H110: MISSINGS | I110: Validar que não existem registos por preencher (Missings) | J110: BU_LOANTAPE_WORK.OUT_B9000_COUNTERPARTIES | K110: 0050_CNTRPRTY_LEI | L110: 4740 | M110: 0
B111: =+IF(LEFT(MID(Controlos[[#This Row],[tabela]],22,5),1)="B",MID(Controlos[[#This Row],[tabela]],22,5),MID(Controlos[[#This Row],[tabela]],18,5)) -> B9000 | C111: =+IF(Controlos[[#This Row],[tipologia_teste]]="REGULAMENTAR",IF(LEFT(Controlos[[#This Row],[cod_kpi]],1)="v",IF(LEFT(Controlos[[#This Row],[descrição]],6)="Alerta","W","H"),"F"),0) -> 0 | F111: 2025-10-31 | G111: MIS_B9000_C0060 | H111: MISSINGS | I111: Validar que não existem registos por preencher (Missings) | J111: BU_LOANTAPE_WORK.OUT_B9000_COUNTERPARTIES | K111: 0060_TYP_CNTRPRTY_ID | L111: 4740 | M111: 0
B112: =+IF(LEFT(MID(Controlos[[#This Row],[tabela]],22,5),1)="B",MID(Controlos[[#This Row],[tabela]],22,5),MID(Controlos[[#This Row],[tabela]],18,5)) -> B9000 | C112: =+IF(Controlos[[#This Row],[tipologia_teste]]="REGULAMENTAR",IF(LEFT(Controlos[[#This Row],[cod_kpi]],1)="v",IF(LEFT(Controlos[[#This Row],[descrição]],6)="Alerta","W","H"),"F"),0) -> 0 | F112: 2025-10-31 | G112: MIS_B9000_C0070 | H112: MISSINGS | I112: Validar que não existem registos por preencher (Missings) | J112: BU_LOANTAPE_WORK.OUT_B9000_COUNTERPARTIES | K112: 0070_CNTRPRTY_ID | L112: 4740 | M112: 0
B113: =+IF(LEFT(MID(Controlos[[#This Row],[tabela]],22,5),1)="B",MID(Controlos[[#This Row],[tabela]],22,5),MID(Controlos[[#This Row],[tabela]],18,5)) -> B9000 | C113: =+IF(Controlos[[#This Row],[tipologia_teste]]="REGULAMENTAR",IF(LEFT(Controlos[[#This Row],[cod_kpi]],1)="v",IF(LEFT(Controlos[[#This Row],[descrição]],6)="Alerta","W","H"),"F"),0) -> 0 | F113: 2025-10-31 | G113: MIS_B9000_C0080 | H113: MISSINGS | I113: Validar que não existem registos por preencher (Missings) | J113: BU_LOANTAPE_WORK.OUT_B9000_COUNTERPARTIES | K113: 0080_CNTRPRTY_TYP | L113: 4740 | M113: 0
B114: =+IF(LEFT(MID(Controlos[[#This Row],[tabela]],22,5),1)="B",MID(Controlos[[#This Row],[tabela]],22,5),MID(Controlos[[#This Row],[tabela]],18,5)) -> B9000 | C114: =+IF(Controlos[[#This Row],[tipologia_teste]]="REGULAMENTAR",IF(LEFT(Controlos[[#This Row],[cod_kpi]],1)="v",IF(LEFT(Controlos[[#This Row],[descrição]],6)="Alerta","W","H"),"F"),0) -> 0 | F114: 2025-10-31 | G114: MIS_B9000_C0090 | H114: MISSINGS | I114: Validar que não existem registos por preencher (Missings) | J114: BU_LOANTAPE_WORK.OUT_B9000_COUNTERPARTIES | K114: 0090_CNTRY_CNTRPRTY | L114: 4740 | M114: 0
B115: =+IF(LEFT(MID(Controlos[[#This Row],[tabela]],22,5),1)="B",MID(Controlos[[#This Row],[tabela]],22,5),MID(Controlos[[#This Row],[tabela]],18,5)) -> B9000 | C115: =+IF(Controlos[[#This Row],[tipologia_teste]]="REGULAMENTAR",IF(LEFT(Controlos[[#This Row],[cod_kpi]],1)="v",IF(LEFT(Controlos[[#This Row],[descrição]],6)="Alerta","W","H"),"F"),0) -> 0 | F115: 2025-10-31 | G115: MIS_B9000_C0100 | H115: MISSINGS | I115: Validar que não existem registos por preencher (Missings) | J115: BU_LOANTAPE_WORK.OUT_B9000_COUNTERPARTIES | K115: 0100_RLVNT_AMNT_WDC | L115: 4740 | M115: 4740 | N115: PTBSRDOM0037, 0000003686; PTBSREOM0028, Not applicable; PTCPP0AM0007, Not applicable; PTCPP0AM0007, 0000003686; PTCPP0AM0007, 5100011001; PTSTOCOM0007, 0000003686; PTSTOEOM0021, 0000003686; PTSTOFOM0004, 0000003686; PTSTOGOM0003, 0000003686; PTSTOHOM0002, 0000003686; 31000000000000000962304890482490P_0000_00000000000_000006511000505, 6511000505; 31000304140330096000000000000000P_0000_00000000000_000000000003686, 0000003686; 31000307044893096000000000000000P_0000_00000000000_000000000003686, 0000003686; 31000307530917096000000000000000P_0000_00000000000_000000000003686, 0000003686; 31000311450813096000000000000000P_0000_00000000000_000000000003686, 0000003686; 31000311847794096000000000000000P_0000_00000000000_000000000003686, 0000003686; 31000313517171096000000000000000P_0000_00000000000_000000000003686, 0000003686; 31000315970006096000000000000000P_0000_00000000000_000000000003686, 0000003686; 31000315970121096000000000000000P_0000_00000000000_000000000003686, 0000003686; 31000315970139096000000000000000P_0000_00000000000_000000000003686, 0000003686; 31000315970188096000000000000000P_0000_00000000000_000000000003686, 0000003686; 31000315970212096000000000000000P_0000_00000000000_000000000003686, 0000003686; 31000315970238096000000000000000P_0000_00000000000_000000000003686, 0000003686; 31000315970261096000000000000000P_0000_00000000000_000000000003686, 0000003686; 31000315970279096000000000000000P_0000_00000000000_000000000003686, 0000003686; 31000315970311096000000000000000P_0000_00000000000_000000000003686, 0000003686; 31000315970329096000000000000000P_0000_00000000000_000000000003686, 0000003686; 31000315970345096000000000000000P_0000_00000000000_000000000003686, 0000003686; 31000315970402096000000000000000P_0000_00000000000_000000000003686, 0000003686; 31000315970428096000000000000000P_0000_00000000000_000000000003686, 0000003686; 31000315970469096000000000000000P_0000_00000000000_000000000003686, 0000003686; 31000315979890096000000000000000P_0000_00000000000_000006511000505, 6511000505; 31000318293090097000000000000000P_0000_00000000000_000008000176024, 8000176024; 31000318542009097000000000000000P_0000_00000000000_000006511000505, 6511000505; 31000318628196097000000000000000P_0000_00000000000_000006511000505, 6511000505; 31000318628592097000000000000000P_0000_00000000000_000008000176024, 8000176024; 31000318629012097000000000000000P_0000_00000000000_000008000176024, 8000176024; 31000318636603097000000000000000P_0000_00000000000_000008000176024, 8000176024; 31000318637213097000000000000000P_0000_00000000000_000008000176024, 8000176024; 31000322311418096000000000000000P_0000_00000000000_000000000003686, 0000003686; 89000020240000766001520240649818P_0000_00000000000_000003461004226, 3461004226; 89000020240000766001520240649824P_0000_00000000000_000003461004226, 3461004226; 89000020240000766001520240649825P_0000_00000000000_000003461004226, 3461004226; 89000020240000766001520240649826P_0000_00000000000_000003461004226, 3461004226; 89000020240000766001520240649827P_0000_00000000000_000003461004226, 3461004226; 89000020240000766001520240649838P_0000_00000000000_000003461004226, 3461004226; 89000020240000766001520240649839P_0000_00000000000_000003461004226, 3461004226; 89000020240000766001520240649873P_0000_00000000000_000003461004226, 3461004226; 89000020240000766001520240649874P_0000_00000000000_000003461004226, 3461004226; 89000020240000766001520240649875P_0000_00000000000_000003461004226, 3461004226; 89000020240000766001520240649894P_0000_00000000000_000003461004226, 3461004226; 89000020240000766001520240649898P_0000_00000000000_000003461004226, 3461004226; 89000020240000766001520240649899P_0000_00000000000_000003461004226, 3461004226; 89000020240000766001520240649900P_0000_00000000000_000003461004226, 3461004226; 89000020240000766001520240649901P_0000_00000000000_000003461004226, 3461004226; 89000020240000766001520240649909P_0000_00000000000_000003461004226, 3461004226; 89000020240000766001520240649910P_0000_00000000000_000003461004226, 3461004226; 89000020240000766001520240649911P_0000_00000000000_000003461004226, 3461004226; 89000020240000766001520240649912P_0000_00000000000_000003461004226, 3461004226; 89000020240000766001520240649913P_0000_00000000000_000003461004226, 3461004226; 89000020240000766001520240649914P_0000_00000000000_000003461004226, 3461004226; 89000020240000766001520240649915P_0000_00000000000_000003461004226, 3461004226; 89000020240000766001520240649916P_0000_00000000000_000003461004226, 3461004226; 89000020240000766001520240649917P_0000_00000000000_000003461004226, 3461004226; 89000020240000766001520240649918P_0000_00000000000_000003461004226, 3461004226; 89000020240000766001520240649919P_0000_00000000000_000003461004226, 3461004226; 89000020240000766001520240649920P_0000_00000000000_000003461004226, 3461004226; 89000020240000766001520240649921P_0000_00000000000_000003461004226, 3461004226; 89000020240000766001520240649942P_0000_00000000000_000003461004226, 3461004226; 89000020240000766001520240649943P_0000_00000000000_000003461004226, 3461004226; 89000020240000766001520240649944P_0000_00000000000_000003461004226, 3461004226; 89000020240000766001520240649945P_0000_00000000000_000003461004226, 3461004226; 89000020240000766001520240649946P_0000_00000000000_000003461004226, 3461004226; 89000020240000766001520240650004P_0000_00000000000_000003461004226, 3461004226; 89000020240000766001520240650005P_0000_00000000000_000003461004226, 3461004226; 89000020240000766001520240650006P_0000_00000000000_000003461004226, 3461004226; 89000020240000766001520240650007P_0000_00000000000_000003461004226, 3461004226; 89000020240000766001520240650008P_0000_00000000000_000003461004226, 3461004226; 89000020240000766001520240650009P_0000_00000000000_000003461004226, 3461004226; 89000020240000766001520240650010P_0000_00000000000_000003461004226, 3461004226; 89000020240000766001520240650011P_0000_00000000000_000003461004226, 3461004226; 89000020240000766001520240650116P_0000_00000000000_000003461004226, 3461004226; 89000020240000766001520240650192P_0000_00000000000_000003461004226, 3461004226; 89000020240000766001520240650202P_0000_00000000000_000003461004226, 3461004226; 89000020240000766001520240650203P_0000_00000000000_000003461004226, 3461004226; 89000020240000766001520240650204P_0000_00000000000_000003461004226, 3461004226; 89000020240000766001520240650205P_0000_00000000000_000003461004226, 3461004226; 89000020240000766001520240650206P_0000_00000000000_000003461004226, 3461004226; 89000020240000766001520240650207P_0000_00000000000_000003461004226, 3461004226; 89000020240000766001520240650208P_0000_00000000000_000003461004226, 3461004226; 89000020240000766001520240650349P_0000_00000000000_000003461004226, 3461004226; 89000020240000766001520240650350P_0000_00000000000_000003461004226, 3461004226; 89000020240000766001520240650351P_0000_00000000000_000003461004226, 3461004226; 89000020240000766001520240650352P_0000_00000000000_000003461004226, 3461004226; 89000020240000766001520240650353P_0000_00000000000_000003461004226, 3461004226; 89000020240000766001520240650354P_0000_00000000000_000003461004226, 3461004226; 89000020240000766001520240650355P_0000_00000000000_000003461004226, 3461004226; 89000020240000766001520240650356P_0000_00000000000_000003461004226, 3461004226; 89000020240000766001520240650357P_0000_00000000000_000003461004226, 3461004226; 89000020240000766001520240650358P_0000_00000000000_000003461004226, 3461004226; 89000020240000766001520240650359P_0000_00000000000_000003461004226, 3461004226; 89000020240000766001520240650360P_0000_00000000000_000003461004226, 3461004226; 89000020240000766001520240650361P_0000_00000000000_000003461004226, 3461004226; 89000020240000766001520240650362P_0000_00000000000_000003461004226, 3461004226; 89000020240000766001520240650363P_0000_00000000000_000003461004226, 3461004226; 89000020240000766001520240650364P_0000_00000000000_000003461004226, 3461004226; 89000020240000766001520240650365P_0000_00000000000_000003461004226, 3461004226; 89000020240000766001520240650366P_0000_00000000000_000003461004226, 3461004226; 89000020240000766001520240650367P_0000_00000000000_000003461004226, 3461004226; 89000020240000766001520240650368P_0000_00000000000_000003461004226, 3461004226; 89000020240000766001520240650369P_0000_00000000000_000003461004226, 3461004226; 89000020240000766001520240650370P_0000_00000000000_000003461004226, 3461004226; 89000020240000766001520240650371P_0000_00000000000_000003461004226, 3461004226; 89000020240000766001520240650372P_0000_00000000000_000003461004226, 3461004226; 89000020240000766001520240650373P_0000_00000000000_000003461004226, 3461004226; 89000020240000766001520240650374P_0000_00000000000_000003461004226, 3461004226; 89000020240000766001520240650375P_0000_00000000000_000003461004226, 3461004226; 89000020240000766001520240650376P_0000_00000000000_000003461004226, 3461004226; 89000020240000766001520240650377P_0000_00000000000_000003461004226, 3461004226; 89000020240000766001520240650378P_0000_00000000000_000003461004226, 3461004226; 89000020240000766001520240650379P_0000_00000000000_000003461004226, 3461004226; 89000020240000766001520240650380P_0000_00000000000_000003461004226, 3461004226; 89000020240000766001520240650381P_0000_00000000000_000003461004226, 3461004226; 89000020240000766001520240650382P_0000_00000000000_000003461004226, 3461004226; 89000020240000766001520240650383P_0000_00000000000_000003461004226, 3461004226; 89000020240000766001520240650384P_0000_00000000000_000003461004226, 3461004226; 89000020240000766001520240650385P_0000_00000000000_000003461004226, 3461004226; 89000020240000766001520240650386P_0000_00000000000_000003461004226, 3461004226; 89000020240000766001520240650387P_0000_00000000000_000003461004226, 3461004226; 89000020240000766001520240650388P_0000_00000000000_000003461004226, 3461004226; 89000020240000766001520240650389P_0000_00000000000_000003461004226, 3461004226; 89000020240000766001520240650390P_0000_00000000000_000003461004226, 3461004226; 89000020240000766001520240650391P_0000_00000000000_000003461004226, 3461004226; 89000020240000766001520240650392P_0000_00000000000_000003461004226, 3461004226; 89000020240000766001520240650393P_0000_00000000000_000003461004226, 3461004226; 89000020240000766001520240650394P_0000_00000000000_000003461004226, 3461004226; 89000020240000766001520240650396P_0000_00000000000_000003461004226, 3461004226; 89000020240000766001520240650397P_0000_00000000000_000003461004226, 3461004226; 89000020240000766001520240650398P_0000_00000000000_000003461004226, 3461004226; 89000020240000766001520240650399P_0000_00000000000_000003461004226, 3461004226; 89000020240000766001520240650400P_0000_00000000000_000003461004226, 3461004226; 89000020240000766001520240650401P_0000_00000000000_000003461004226, 3461004226; 89000020240000766001520240650402P_0000_00000000000_000003461004226, 3461004226; 89000020240000766001520240650403P_0000_00000000000_000003461004226, 3461004226; 89000020240000766001520240650404P_0000_00000000000_000003461004226, 3461004226; 89000020240000766001520240650405P_0000_00000000000_000003461004226, 3461004226; 89000020240000766001520240650406P_0000_00000000000_000003461004226, 3461004226; 89000020240000766001520240650407P_0000_00000000000_000003461004226, 3461004226; 89000020240000766001520240650408P_0000_00000000000_000003461004226, 3461004226; 89000020240000766001520240650409P_0000_00000000000_000003461004226, 3461004226; 89000020240000766001520240650410P_0000_00000000000_000003461004226, 3461004226; 89000020240000766001520240650411P_0000_00000000000_000003461004226, 3461004226; 89000020240000766001520240650412P_0000_00000000000_000003461004226, 3461004226; 89000020240000766001520240650413P_0000_00000000000_000003461004226, 3461004226; 89000020240000766001520240650414P_0000_00000000000_000003461004226, 3461004226; 89000020240000766001520240650415P_0000_00000000000_000003461004226, 3461004226; 89000020240000766001520240650416P_0000_00000000000_000003461004226, 3461004226; 89000020240000766001520240650417P_0000_00000000000_000003461004226, 3461004226; 89000020240000766001520240650418P_0000_00000000000_000003461004226, 3461004226; 89000020240000766001520240650419P_0000_00000000000_000003461004226, 3461004226; 89000020240000766001520240650420P_0000_00000000000_000003461004226, 3461004226; 89000020240000766001520240650421P_0000_00000000000_000003461004226, 3461004226; 89000020240000766001520240650422P_0000_00000000000_000003461004226, 3461004226; 89000020240000766001520240650423P_0000_00000000000_000003461004226, 3461004226; 89000020240000766001520240650424P_0000_00000000000_000003461004226, 3461004226; 89000020240000766001520240650425P_0000_00000000000_000003461004226, 3461004226; 89000020240000766001520240650426P_0000_00000000000_000003461004226, 3461004226; 89000020240000766001520240650427P_0000_00000000000_000003461004226, 3461004226; 89000020240000766001520240650428P_0000_00000000000_000003461004226, 3461004226; 89000020240000766001520240650429P_0000_00000000000_000003461004226, 3461004226; 89000020240000766001520240650431P_0000_00000000000_000003461004226, 3461004226; 89000020240000766001520240650432P_0000_00000000000_000003461004226, 3461004226; 89000020240000766001520240650433P_0000_00000000000_000003461004226, 3461004226; 89000020240000766001520240650434P_0000_00000000000_000003461004226, 3461004226; 89000020240000766001520240650435P_0000_00000000000_000003461004226, 3461004226; 89000020240000766001520240650436P_0000_00000000000_000003461004226, 3461004226; 89000020240000766001520240650476P_0000_00000000000_000003461004226, 3461004226; 89000020240000766001520240650477P_0000_00000000000_000003461004226, 3461004226; 89000020240000766001520240650478P_0000_00000000000_000003461004226, 3461004226; 89000020240000766001520240650479P_0000_00000000000_000003461004226, 3461004226; 89000020240000766001520240650480P_0000_00000000000_000003461004226, 3461004226; 89000020240000766001520240650481P_0000_00000000000_000003461004226, 3461004226; 89000020240000766001520240650482P_0000_00000000000_000003461004226, 3461004226; 89000020240000766001520240650483P_0000_00000000000_000003461004226, 3461004226; 89000020240000766001520240650484P_0000_00000000000_000003461004226, 3461004226; 89000020240000766001520240650485P_0000_00000000000_000003461004226, 3461004226; 89000020240000766001520240650486P_0000_00000000000_000003461004226, 3461004226; 89000020240000766001520240650487P_0000_00000000000_000003461004226, 3461004226; 89000020240000766001520240650488P_0000_00000000000_000003461004226, 3461004226; 89000020240000766001520240650489P_0000_00000000000_000003461004226, 3461004226; 89000020240000766001520240650490P_0000_00000000000_000003461004226, 3461004226; 89000020240000766001520240650491P_0000_00000000000_000003461004226, 3461004226; 89000020240000766001520240650492P_0000_00000000000_000003461004226, 3461004226; 89000020240000766001520240650493P_0000_00000000000_000003461004226, 3461004226; 89000020240000766001520240650494P_0000_00000000000_000003461004226, 3461004226; 89000020240000766001520240650495P_0000_00000000000_000003461004226, 3461004226; 89000020240000766001520240650496P_0000_00000000000_000003461004226, 3461004226; 89000020240000766001520240650497P_0000_00000000000_000003461004226, 3461004226; 89000020240000766001520240650498P_0000_00000000000_000003461004226, 3461004226; 89000020240000766001520240650499P_0000_00000000000_000003461004226, 3461004226; 89000020240000766001520240650500P_0000_00000000000_000003461004226, 3461004226; 89000020240000766001520240650501P_0000_00000000000_000003461004226, 3461004226; 89000020240000766001520240650502P_0000_00000000000_000003461004226, 3461004226; 89000020240000766001520240650503P_0000_00000000000_000003461004226, 3461004226; 89000020240000766001520240650504P_0000_00000000000_000003461004226, 3461004226; 89000020240000766001520240650505P_0000_00000000000_000003461004226, 3461004226; 89000020240000766001520240650506P_0000_00000000000_000003461004226, 3461004226; 89000020240000766001520240650507P_0000_00000000000_000003461004226, 3461004226; 89000020240000766001520240650508P_0000_00000000000_000003461004226, 3461004226; 89000020240000766001520240650509P_0000_00000000000_000003461004226, 3461004226; 89000020240000766001520240650510P_0000_00000000000_000003461004226, 3461004226; 89000020240000766001520240650511P_0000_00000000000_000003461004226, 3461004226; 89000020240000766001520240650512P_0000_00000000000_000003461004226, 3461004226; 89000020240000766001520240650513P_0000_00000000000_000003461004226, 3461004226; 89000020240000766001520240650514P_0000_00000000000_000003461004226, 3461004226; 89000020240000766001520240650515P_0000_00000000000_000003461004226, 3461004226; 89000020240000766001520240650516P_0000_00000000000_000003461004226, 3461004226; 89000020240000766001520240650517P_0000_00000000000_000003461004226, 3461004226; 89000020240000766001520240650518P_0000_00000000000_000003461004226, 3461004226; 89000020240000766001520240650519P_0000_00000000000_000003461004226, 3461004226; 89000020240000766001520240650520P_0000_00000000000_000003461004226, 3461004226; 89000020240000766001520240650521P_0000_00000000000_000003461004226, 3461004226; 89000020240000766001520240650522P_0000_00000000000_000003461004226, 3461004226; 89000020240000766001520240650523P_0000_00000000000_000003461004226, 3461004226; 89000020240000766001520240650524P_0000_00000000000_000003461004226, 3461004226; 89000020240000766001520240650525P_0000_00000000000_000003461004226, 3461004226; 89000020240000766001520240650526P_0000_00000000000_000003461004226, 3461004226; 89000020240000766001520240650527P_0000_00000000000_000003461004226, 3461004226; 89000020240000766001520240650528P_0000_00000000000_000003461004226, 3461004226; 89000020240000766001520240650529P_0000_00000000000_000003461004226, 3461004226; 89000020240000766001520240650530P_0000_00000000000_000003461004226, 3461004226; 89000020240000766001520240650531P_0000_00000000000_000003461004226, 3461004226; 89000020240000766001520240650532P_0000_00000000000_000003461004226, 3461004226; 89000020240000766001520240650533P_0000_00000000000_000003461004226, 3461004226; 89000020240000766001520240650534P_0000_00000000000_000003461004226, 3461004226; 89000020240000766001520240650535P_0000_00000000000_000003461004226, 3461004226; 89000020240000766001520240650536P_0000_00000000000_000003461004226, 3461004226; 89000020240000766001520240650537P_0000_00000000000_000003461004226, 3461004226; 89000020240000766001520240650538P_0000_00000000000_000003461004226, 3461004226; 89000020240000766001520240650539P_0000_00000000000_000003461004226, 3461004226; 89000020240000766001520240650540P_0000_00000000000_000003461004226, 3461004226; 89000020240000766001520240650541P_0000_00000000000_000003461004226, 3461004226; 89000020240000766001520240650542P_0000_00000000000_000003461004226, 3461004226; 89000020240000766001520240650543P_0000_00000000000_000003461004226, 3461004226; 89000020240000766001520240650544P_0000_00000000000_000003461004226, 3461004226; 89000020240000766001520240650545P_0000_00000000000_000003461004226, 3461004226; 89000020240000766001520240650546P_0000_00000000000_000003461004226, 3461004226; 89000020240000766001520240650547P_0000_00000000000_000003461004226, 3461004226; 89000020240000766001520240650548P_0000_00000000000_000003461004226, 3461004226; 89000020240000766001520240650549P_0000_00000000000_000003461004226, 3461004226; 89000020240000766001520240650550P_0000_00000000000_000003461004226, 3461004226; 89000020240000766001520240650551P_0000_00000000000_000003461004226, 3461004226; 89000020240000766001520240650552P_0000_00000000000_000003461004226, 3461004226; 89000020240000766001520240650553P_0000_00000000000_000003461004226, 3461004226; 89000020240000766001520240650554P_0000_00000000000_000003461004226, 3461004226; 89000020240000766001520240650555P_0000_00000000000_000003461004226, 3461004226; 89000020240000766001520240650556P_0000_00000000000_000003461004226, 3461004226; 89000020240000766001520240650557P_0000_00000000000_000003461004226, 3461004226; 89000020240000766001520240650558P_0000_00000000000_000003461004226, 3461004226; 89000020240000766001520240650559P_0000_00000000000_000003461004226, 3461004226; 89000020240000766001520240650560P_0000_00000000000_000003461004226, 3461004226; 89000020240000766001520240650561P_0000_00000000000_000003461004226, 3461004226; 89000020240000766001520240650562P_0000_00000000000_000003461004226, 3461004226; 89000020240000766001520240650563P_0000_00000000000_000003461004226, 3461004226; 89000020240000766001520240650564P_0000_00000000000_000003461004226, 3461004226; 89000020240000766001520240650565P_0000_00000000000_000003461004226, 3461004226; 89000020240000766001520240650566P_0000_00000000000_000003461004226, 3461004226; 89000020240000766001520240650567P_0000_00000000000_000003461004226, 3461004226; 89000020240000766001520240650568P_0000_00000000000_000003461004226, 3461004226; 89000020240000766001520240650569P_0000_00000000000_000003461004226, 3461004226; 89000020240000766001520240650783P_0000_00000000000_000003461004226, 3461004226; 89000020240000766001520240650784P_0000_00000000000_000003461004226, 3461004226; 89000020240000766001520240650785P_0000_00000000000_000003461004226, 3461004226; 89000020240000766001520240650786P_0000_00000000000_000003461004226, 3461004226; 89000020240000766001520240650787P_0000_00000000000_000003461004226, 3461004226; 89000020240000766001520240650788P_0000_00000000000_000003461004226, 3461004226; 89000020240000766001520240650851P_0000_00000000000_000003461004226, 3461004226; 89000020240000766001520240650853P_0000_00000000000_000003461004226, 3461004226; 89000020240000766001520240650865P_0000_00000000000_000003461004226, 3461004226; 89000020240000766001520240650868P_0000_00000000000_000003461004226, 3461004226; 89000020240000766001520240650869P_0000_00000000000_000003461004226, 3461004226; 89000020240000766001520240650873P_0000_00000000000_000003461004226, 3461004226; 89000020240000766001520240650875P_0000_00000000000_000003461004226, 3461004226; 89000020240000766001520240650930P_0000_00000000000_000003461004226, 3461004226; 89000020240000766001520240650947P_0000_00000000000_000003461004226, 3461004226; 89000020240000766001520240650948P_0000_00000000000_000003461004226, 3461004226; 89000020240000766001520240650949P_0000_00000000000_000003461004226, 3461004226; 89000020240000766001520240650950P_0000_00000000000_000003461004226, 3461004226; 89000020240000766001520240650951P_0000_00000000000_000003461004226, 3461004226; 89000020240000766001520240650952P_0000_00000000000_000003461004226, 3461004226; 89000020240000766001520240650953P_0000_00000000000_000003461004226, 3461004226; 89000020240000766001520240650954P_0000_00000000000_000003461004226, 3461004226; 89000020240000766001520240650955P_0000_00000000000_000003461004226, 3461004226; 89000020240000766001520240650956P_0000_00000000000_000003461004226, 3461004226; 89000020240000766001520240650957P_0000_00000000000_000003461004226, 3461004226; 89000020240000766001520240650958P_0000_00000000000_000003461004226, 3461004226; 89000020240000766001520240650959P_0000_00000000000_000003461004226, 3461004226; 89000020240000766001520240650960P_0000_00000000000_000003461004226, 3461004226; 89000020240000766001520240650961P_0000_00000000000_000003461004226, 3461004226; 89000020240000766001520240650962P_0000_00000000000_000003461004226, 3461004226; 89000020240000766001520240650968P_0000_00000000000_000003461004226, 3461004226; 89000020240000766001520240650969P_0000_00000000000_000003461004226, 3461004226; 89000020240000766001520240650970P_0000_00000000000_000003461004226, 3461004226; 89000020240000766001520240650971P_0000_00000000000_000003461004226, 3461004226; 89000020240000766001520240650972P_0000_00000000000_000003461004226, 3461004226; 89000020240000766001520240650973P_0000_00000000000_000003461004226, 3461004226; 89000020240000766001520240650974P_0000_00000000000_000003461004226, 3461004226; 89000020240000766001520240650975P_0000_00000000000_000003461004226, 3461004226; 89000020240000766001520240650976P_0000_00000000000_000003461004226, 3461004226; 89000020240000766001520240650978P_0000_00000000000_000003461004226, 3461004226; 89000020240000766001520240650979P_0000_00000000000_000003461004226, 3461004226; 89000020240000766001520240650980P_0000_00000000000_000003461004226, 3461004226; 89000020240000766001520240650981P_0000_00000000000_000003461004226, 3461004226; 89000020240000766001520240650982P_0000_00000000000_000003461004226, 3461004226; 89000020240000766001520240650983P_0000_00000000000_000003461004226, 3461004226; 89000020240000766001520240650984P_0000_00000000000_000003461004226, 3461004226; 89000020240000766001520240650985P_0000_00000000000_000003461004226, 3461004226; 89000020240000766001520240650986P_0000_00000000000_000003461004226, 3461004226; 89000020240000766001520240650987P_0000_00000000000_000003461004226, 3461004226; 89000020240000766001520240650988P_0000_00000000000_000003461004226, 3461004226; 89000020240000766001520240650989P_0000_00000000000_000003461004226, 3461004226; 89000020240000766001520240650990P_0000_00000000000_000003461004226, 3461004226; 89000020240000766001520240650991P_0000_00000000000_000003461004226, 3461004226; 89000020240000766001520240650992P_0000_00000000000_000003461004226, 3461004226; 89000020240000766001520240650993P_0000_00000000000_000003461004226, 3461004226; 89000020240000766001520240650994P_0000_00000000000_000003461004226, 3461004226; 89000020240000766001520240650995P_0000_00000000000_000003461004226, 3461004226; 89000020240000766001520240650996P_0000_00000000000_000003461004226, 3461004226; 89000020240000766001520240650997P_0000_00000000000_000003461004226, 3461004226; 89000020240000766001520240650998P_0000_00000000000_000003461004226, 3461004226; 89000020240000766001520240650999P_0000_00000000000_000003461004226, 3461004226; 89000020240000766001520240651000P_0000_00000000000_000003461004226, 3461004226; 89000020240000766001520240651001P_0000_00000000000_000003461004226, 3461004226; 89000020240000766001520240651002P_0000_00000000000_000003461004226, 3461004226; 89000020240000766001520240651003P_0000_00000000000_000003461004226, 3461004226; 89000020240000766001520240651004P_0000_00000000000_000003461004226, 3461004226; 89000020240000766001520240651005P_0000_00000000000_000003461004226, 3461004226; 89000020240000766001520240651006P_0000_00000000000_000003461004226, 3461004226; 89000020240000766001520240651020P_0000_00000000000_000003461004226, 3461004226; 89000020240000766001520240651095P_0000_00000000000_000003461004226, 3461004226; 89000020240000766001520240651174P_0000_00000000000_000003461004226, 3461004226; 89000020240000766001520240651175P_0000_00000000000_000003461004226, 3461004226; 89000020240000766001520240651177P_0000_00000000000_000003461004226, 3461004226; 89000020240000766001520240651179P_0000_00000000000_000003461004226, 3461004226; 89000020240000766001520240651180P_0000_00000000000_000003461004226, 3461004226; 89000020240000766001520240651187P_0000_00000000000_000003461004226, 3461004226; 89000020240000766001520240651188P_0000_00000000000_000003461004226, 3461004226; 89000020240000766001520240651189P_0000_00000000000_000003461004226, 3461004226; 89000020240000766001520240651190P_0000_00000000000_000003461004226, 3461004226; 89000020240000766001520240651192P_0000_00000000000_000003461004226, 3461004226; 89000020240000766001520240651193P_0000_00000000000_000003461004226, 3461004226; 89000020240000766001520240651194P_0000_00000000000_000003461004226, 3461004226; 89000020240000766001520240651195P_0000_00000000000_000003461004226, 3461004226; 89000020240000766001520240651196P_0000_00000000000_000003461004226, 3461004226; 89000020240000766001520240651197P_0000_00000000000_000003461004226, 3461004226; 89000020240000766001520240651198P_0000_00000000000_000003461004226, 3461004226; 89000020240000766001520240651199P_0000_00000000000_000003461004226, 3461004226; 89000020240000766001520240651200P_0000_00000000000_000003461004226, 3461004226; 89000020240000766001520240651201P_0000_00000000000_000003461004226, 3461004226; 89000020240000766001520240651202P_0000_00000000000_000003461004226, 3461004226; 89000020240000766001520240651203P_0000_00000000000_000003461004226, 3461004226; 89000020240000766001520240651204P_0000_00000000000_000003461004226, 3461004226; 89000020240000766001520240651307P_0000_00000000000_000003461004226, 3461004226; 89000020240000766001520240651409P_0000_00000000000_000003461004226, 3461004226; 89000020240000766001520240651410P_0000_00000000000_000003461004226, 3461004226; 89000020240000766001520240651411P_0000_00000000000_000003461004226, 3461004226; 89000020240000766001520240651412P_0000_00000000000_000003461004226, 3461004226; 89000020240000766001520240651444P_0000_00000000000_000003461004226, 3461004226; 89000020240000766001520240651449P_0000_00000000000_000003461004226, 3461004226; 89000020240000766001520240651453P_0000_00000000000_000003461004226, 3461004226; 89000020240000766001520240651454P_0000_00000000000_000003461004226, 3461004226; 89000020240000766001520240651455P_0000_00000000000_000003461004226, 3461004226; 89000020240000766001520240651456P_0000_00000000000_000003461004226, 3461004226; 89000020240000766001520240651464P_0000_00000000000_000003461004226, 3461004226; 89000020240000766001520240651468P_0000_00000000000_000003461004226, 3461004226; 89000020240000766001520240651470P_0000_00000000000_000003461004226, 3461004226; 89000020240000766001520240651471P_0000_00000000000_000003461004226, 3461004226; 89000020240000766001520240651473P_0000_00000000000_000003461004226, 3461004226; 89000020240000766001520240651474P_0000_00000000000_000003461004226, 3461004226; 89000020240000766001520240651475P_0000_00000000000_000003461004226, 3461004226; 89000020240000766001520240651476P_0000_00000000000_000003461004226, 3461004226; 89000020240000766001520240651477P_0000_00000000000_000003461004226, 3461004226; 89000020240000766001520240651643P_0000_00000000000_000003461004226, 3461004226; 89000020240000766001520240651644P_0000_00000000000_000003461004226, 3461004226; 89000020240000766001520240651645P_0000_00000000000_000003461004226, 3461004226; 89000020240000766001520240651684P_0000_00000000000_000003461004226, 3461004226; 89000020240000766001520240651693P_0000_00000000000_000003461004226, 3461004226; 89000020240000766001520240651694P_0000_00000000000_000003461004226, 3461004226; 89000020240000766001520240651695P_0000_00000000000_000003461004226, 3461004226; 89000020240000766001520240651696P_0000_00000000000_000003461004226, 3461004226; 89000020240000766001520240651697P_0000_00000000000_000003461004226, 3461004226; 89000020240000766001520240651698P_0000_00000000000_000003461004226, 3461004226; 89000020240000766001520240651699P_0000_00000000000_000003461004226, 3461004226; 89000020240000766001520240651700P_0000_00000000000_000003461004226, 3461004226; 89000020240000766001520240651701P_0000_00000000000_000003461004226, 3461004226; 89000020240000766001520240651702P_0000_00000000000_000003461004226, 3461004226; 89000020240000766001520240651706P_0000_00000000000_000003461004226, 3461004226; 89000020240000766001520240651707P_0000_00000000000_000003461004226, 3461004226; 89000020240000766001520240651708P_0000_00000000000_000003461004226, 3461004226; 89000020240000766001520240651709P_0000_00000000000_000003461004226, 3461004226; 89000020240000766001520240651710P_0000_00000000000_000003461004226, 3461004226; 89000020240000766001520240651711P_0000_00000000000_000003461004226, 3461004226; 89000020240000766001520240651712P_0000_00000000000_000003461004226, 3461004226; 89000020240000766001520240651713P_0000_00000000000_000003461004226, 3461004226; 89000020240000766001520240651714P_0000_00000000000_000003461004226, 3461004226; 89000020240000766001520240651715P_0000_00000000000_000003461004226, 3461004226; 89000020240000766001520240651716P_0000_00000000000_000003461004226, 3461004226; 89000020240000766001520240651717P_0000_00000000000_000003461004226, 3461004226; 89000020240000766001520240651718P_0000_00000000000_000003461004226, 3461004226; 89000020240000766001520240651719P_0000_00000000000_000003461004226, 3461004226; 89000020240000766001520240651720P_0000_00000000000_000003461004226, 3461004226; 89000020240000766001520240651721P_0000_00000000000_000003461004226, 3461004226; 89000020240000766001520240651722P_0000_00000000000_000003461004226, 3461004226; 89000020240000766001520240651723P_0000_00000000000_000003461004226, 3461004226; 89000020240000766001520240651727P_0000_00000000000_000003461004226, 3461004226; 89000020240000766001520240651728P_0000_00000000000_000003461004226, 3461004226; 89000020240000766
B116: =+IF(LEFT(MID(Controlos[[#This Row],[tabela]],22,5),1)="B",MID(Controlos[[#This Row],[tabela]],22,5),MID(Controlos[[#This Row],[tabela]],18,5)) -> LT001 | C116: =+IF(Controlos[[#This Row],[tipologia_teste]]="REGULAMENTAR",IF(LEFT(Controlos[[#This Row],[cod_kpi]],1)="v",IF(LEFT(Controlos[[#This Row],[descrição]],6)="Alerta","W","H"),"F"),0) -> 0 | F116: 2025-10-31 | G116: MIS_LT001_FLAG_GAR_INTRG_SAN | H116: MISSINGS | I116: Validar que não existem registos por preencher (Missings) | J116: BU_LOANTAPE_WORK.LT001_UNIV_OPER | K116: FLAG_GAR_INTRG_SAN | L116: 14293 | M116: 69 | N116: 31000307530917096000000000000000153114739853147326403031521, NULL; 31000315970428096000000000000000153114739853147326403031521, NULL; 31000315970121096000000000000000153114739853147326403031521, NULL; 3100031597989009600000000000000015320433022114122210, NULL; 31000315970188096000000000000000153114739853147326403031521, NULL; 31000311450813096000000000000000153304730221141403152, NULL; 3100031829309009700000000000000015321403985324032640403001, NULL; 3100031854200909700000000000000015311403985314032640303001, NULL; 3100031597031109600000000000000015310473251221141222159, NULL; 31000315970212096000000000000000153104730221141222159, NULL; 31000315970329096000000000000000153104730221141222159, NULL; 31000315970402096000000000000000153114739853147326403031521, NULL; 3100030704489309600000000000000015310473251221141222159, NULL; 31000315970469096000000000000000153114739853147326403031521, NULL; 31000315970121096000000000000000153104730221141222159, NULL; 3100031597027909600000000000000015310473251221141222159, NULL; 31000307044893096000000000000000153104730221141222159, NULL; 310003159798900960000000000000001532043325122114122210, NULL; 31000313517171096000000000000000153114739853147326403031521, NULL; 3100031829309009700000000000000015320403022035122200, NULL; 31000304140330096000000000000000153114719853147126403031201, NULL; 3100031597042809600000000000000015310473251221141222159, NULL; 3100031597046909600000000000000015310473251221141222159, NULL; 3100031597989009600000000000000015321433985324332640403101, NULL; 31000315970188096000000000000000153104730221141222159, NULL; 3100031597032909600000000000000015310473251221141222159, NULL; 3100031597012109600000000000000015310473251221141222159, NULL; 31000311847794096000000000000000153104730221141222159, NULL; 3100031597034509600000000000000015310473251221141222159, NULL; 31000315970238096000000000000000153114739853147326403031521, NULL; 3100031597000609600000000000000015310473251221141222159, NULL; 3100031145081309600000000000000015331047398533047326400031520, NULL; 31000315970469096000000000000000153104730221141222159, NULL; 3100031829309009700000000000000015320403251220304122200, NULL; 31000315970261096000000000000000153114739853147326403031521, NULL; 31000307044893096000000000000000153114739853147326403031521, NULL; 3100031351717109600000000000000015310473251221141222159, NULL; 31000315970238096000000000000000153104730221141222159, NULL; 3100030753091709600000000000000015310473251221141222159, NULL; 3100031597026109600000000000000015310473251221141222159, NULL; 3100031597018809600000000000000015310473251221141222159, NULL; 31000315970329096000000000000000153114739853147326403031521, NULL; 31000315970279096000000000000000153114739853147326403031521, NULL; 31000315970311096000000000000000153104730221141222159, NULL; 3100031854200909700000000000000015310403022035122200, NULL; 31000315970212096000000000000000153114739853147326403031521, NULL; 3100031597023809600000000000000015310473251221141222159, NULL; 3100031597040209600000000000000015310473251221141222159, NULL; 31000315970139096000000000000000153114739853147326403031521, NULL; 31000315970006096000000000000000153104730221141222159, NULL; 31000311847794096000000000000000153114739853147326403031521, NULL; 31000304140330096000000000000000153104710221141222120, NULL; 31000315970311096000000000000000153114739853147326403031521, NULL; 3100031854200909700000000000000015310403251220304122200, NULL; 31000315970279096000000000000000153104730221141222159, NULL; 3100030414033009600000000000000015310471251221141222120, NULL; 3100031597013909600000000000000015310473251221141222159, NULL; 3100031184779409600000000000000015310473251221141222159, NULL; 31000315970345096000000000000000153114739853147326403031521, NULL; 31000315970139096000000000000000153104730221141222159, NULL; 31000311450813096000000000000000153304730282030501403152, NULL; 31000315970428096000000000000000153104730221141222159, NULL; 31000315970402096000000000000000153104730221141222159, NULL; 31000307530917096000000000000000153104730221141222159, NULL; 31000315970261096000000000000000153104730221141222159, NULL; 31000315970006096000000000000000153114739853147326403031521, NULL; 31000313517171096000000000000000153104730221141222159, NULL; 3100031597021209600000000000000015310473251221141222159, NULL; 31000315970345096000000000000000153104730221141222159, NULL
B117: =+IF(LEFT(MID(Controlos[[#This Row],[tabela]],22,5),1)="B",MID(Controlos[[#This Row],[tabela]],22,5),MID(Controlos[[#This Row],[tabela]],18,5)) -> LT001 | C117: =+IF(Controlos[[#This Row],[tipologia_teste]]="REGULAMENTAR",IF(LEFT(Controlos[[#This Row],[cod_kpi]],1)="v",IF(LEFT(Controlos[[#This Row],[descrição]],6)="Alerta","W","H"),"F"),0) -> 0 | F117: 2025-10-31 | G117: MIS_LT001_FLAG_INST_CAP | H117: MISSINGS | I117: Validar que não existem registos por preencher (Missings) | J117: BU_LOANTAPE_WORK.LT001_UNIV_OPER | K117: FLAG_INST_CAP | L117: 14293 | M117: 0
B118: =+IF(LEFT(MID(Controlos[[#This Row],[tabela]],22,5),1)="B",MID(Controlos[[#This Row],[tabela]],22,5),MID(Controlos[[#This Row],[tabela]],18,5)) -> LT001 | C118: =+IF(Controlos[[#This Row],[tipologia_teste]]="REGULAMENTAR",IF(LEFT(Controlos[[#This Row],[cod_kpi]],1)="v",IF(LEFT(Controlos[[#This Row],[descrição]],6)="Alerta","W","H"),"F"),0) -> 0 | F118: 2025-10-31 | G118: MIS_LT001_FLAG_INST_DIV | H118: MISSINGS | I118: Validar que não existem registos por preencher (Missings) | J118: BU_LOANTAPE_WORK.LT001_UNIV_OPER | K118: FLAG_INST_DIV | L118: 14293 | M118: 0
B119: =+IF(LEFT(MID(Controlos[[#This Row],[tabela]],22,5),1)="B",MID(Controlos[[#This Row],[tabela]],22,5),MID(Controlos[[#This Row],[tabela]],18,5)) -> LT001 | C119: =+IF(Controlos[[#This Row],[tipologia_teste]]="REGULAMENTAR",IF(LEFT(Controlos[[#This Row],[cod_kpi]],1)="v",IF(LEFT(Controlos[[#This Row],[descrição]],6)="Alerta","W","H"),"F"),0) -> 0 | F119: 2025-10-31 | G119: MIS_LT001_FLAG_INST_TITULOS | H119: MISSINGS | I119: Validar que não existem registos por preencher (Missings) | J119: BU_LOANTAPE_WORK.LT001_UNIV_OPER | K119: FLAG_INST_TITULOS | L119: 14293 | M119: 0
B120: =+IF(LEFT(MID(Controlos[[#This Row],[tabela]],22,5),1)="B",MID(Controlos[[#This Row],[tabela]],22,5),MID(Controlos[[#This Row],[tabela]],18,5)) -> LT002 | C120: =+IF(Controlos[[#This Row],[tipologia_teste]]="REGULAMENTAR",IF(LEFT(Controlos[[#This Row],[cod_kpi]],1)="v",IF(LEFT(Controlos[[#This Row],[descrição]],6)="Alerta","W","H"),"F"),0) -> 0 | F120: 2025-10-31 | G120: MIS_LT002_INSTRMNT_ID | H120: MISSINGS | I120: Validar que não existem registos por preencher (Missings) | J120: BU_LOANTAPE_WORK.LT002_INSTRUMENT | K120: INSTRMNT_ID | L120: 4742 | M120: 0
B121: =+IF(LEFT(MID(Controlos[[#This Row],[tabela]],22,5),1)="B",MID(Controlos[[#This Row],[tabela]],22,5),MID(Controlos[[#This Row],[tabela]],18,5)) -> LT002 | C121: =+IF(Controlos[[#This Row],[tipologia_teste]]="REGULAMENTAR",IF(LEFT(Controlos[[#This Row],[cod_kpi]],1)="v",IF(LEFT(Controlos[[#This Row],[descrição]],6)="Alerta","W","H"),"F"),0) -> 0 | F121: 2025-10-31 | G121: MIS_LT002_ISIN | H121: MISSINGS | I121: Validar que não existem registos por preencher (Missings) | J121: BU_LOANTAPE_WORK.LT002_INSTRUMENT | K121: ISIN | L121: 4742 | M121: 0
B122: =+IF(LEFT(MID(Controlos[[#This Row],[tabela]],22,5),1)="B",MID(Controlos[[#This Row],[tabela]],22,5),MID(Controlos[[#This Row],[tabela]],18,5)) -> LT002 | C122: =+IF(Controlos[[#This Row],[tipologia_teste]]="REGULAMENTAR",IF(LEFT(Controlos[[#This Row],[cod_kpi]],1)="v",IF(LEFT(Controlos[[#This Row],[descrição]],6)="Alerta","W","H"),"F"),0) -> 0 | F122: 2025-10-31 | G122: MIS_LT002_ORGNL_AMNT_EUR | H122: MISSINGS | I122: Validar que não existem registos por preencher (Missings) | J122: BU_LOANTAPE_WORK.LT002_INSTRUMENT | K122: ORGNL_AMNT_EUR | L122: 4742 | M122: 0
B123: =+IF(LEFT(MID(Controlos[[#This Row],[tabela]],22,5),1)="B",MID(Controlos[[#This Row],[tabela]],22,5),MID(Controlos[[#This Row],[tabela]],18,5)) -> LT002 | C123: =+IF(Controlos[[#This Row],[tipologia_teste]]="REGULAMENTAR",IF(LEFT(Controlos[[#This Row],[cod_kpi]],1)="v",IF(LEFT(Controlos[[#This Row],[descrição]],6)="Alerta","W","H"),"F"),0) -> 0 | F123: 2025-10-31 | G123: MIS_LT002_ORGNL_AMNT_FX | H123: MISSINGS | I123: Validar que não existem registos por preencher (Missings) | J123: BU_LOANTAPE_WORK.LT002_INSTRUMENT | K123: ORGNL_AMNT_FX | L123: 4742 | M123: 0
B124: =+IF(LEFT(MID(Controlos[[#This Row],[tabela]],22,5),1)="B",MID(Controlos[[#This Row],[tabela]],22,5),MID(Controlos[[#This Row],[tabela]],18,5)) -> LT002 | C124: =+IF(Controlos[[#This Row],[tipologia_teste]]="REGULAMENTAR",IF(LEFT(Controlos[[#This Row],[cod_kpi]],1)="v",IF(LEFT(Controlos[[#This Row],[descrição]],6)="Alerta","W","H"),"F"),0) -> 0 | F124: 2025-10-31 | G124: MIS_LT002_CRRNCY_DNMNTN | H124: MISSINGS | I124: Validar que não existem registos por preencher (Missings) | J124: BU_LOANTAPE_WORK.LT002_INSTRUMENT | K124: CRRNCY_DNMNTN | L124: 4742 | M124: 0
B125: =+IF(LEFT(MID(Controlos[[#This Row],[tabela]],22,5),1)="B",MID(Controlos[[#This Row],[tabela]],22,5),MID(Controlos[[#This Row],[tabela]],18,5)) -> LT002 | C125: =+IF(Controlos[[#This Row],[tipologia_teste]]="REGULAMENTAR",IF(LEFT(Controlos[[#This Row],[cod_kpi]],1)="v",IF(LEFT(Controlos[[#This Row],[descrição]],6)="Alerta","W","H"),"F"),0) -> 0 | F125: 2025-10-31 | G125: MIS_LT002_ACCRD_INTRST_INSTRMNT | H125: MISSINGS | I125: Validar que não existem registos por preencher (Missings) | J125: BU_LOANTAPE_WORK.LT002_INSTRUMENT | K125: ACCRD_INTRST_INSTRMNT | L125: 4742 | M125: 0
B126: =+IF(LEFT(MID(Controlos[[#This Row],[tabela]],22,5),1)="B",MID(Controlos[[#This Row],[tabela]],22,5),MID(Controlos[[#This Row],[tabela]],18,5)) -> LT002 | C126: =+IF(Controlos[[#This Row],[tipologia_teste]]="REGULAMENTAR",IF(LEFT(Controlos[[#This Row],[cod_kpi]],1)="v",IF(LEFT(Controlos[[#This Row],[descrição]],6)="Alerta","W","H"),"F"),0) -> 0 | F126: 2025-10-31 | G126: MIS_LT002_TYP_INSTRMNT | H126: MISSINGS | I126: Validar que não existem registos por preencher (Missings) | J126: BU_LOANTAPE_WORK.LT002_INSTRUMENT | K126: TYP_INSTRMNT | L126: 4742 | M126: 0
B127: =+IF(LEFT(MID(Controlos[[#This Row],[tabela]],22,5),1)="B",MID(Controlos[[#This Row],[tabela]],22,5),MID(Controlos[[#This Row],[tabela]],18,5)) -> LT002 | C127: =+IF(Controlos[[#This Row],[tipologia_teste]]="REGULAMENTAR",IF(LEFT(Controlos[[#This Row],[cod_kpi]],1)="v",IF(LEFT(Controlos[[#This Row],[descrição]],6)="Alerta","W","H"),"F"),0) -> 0 | F127: 2025-10-31 | G127: MIS_LT002_RANK_INSOLV | H127: MISSINGS | I127: Validar que não existem registos por preencher (Missings) | J127: BU_LOANTAPE_WORK.LT002_INSTRUMENT | K127: RANK_INSOLV | L127: 4742 | M127: 4734 | N127: 89000020240000766001520240650562; 89000020240000766001520250082914; 89000020240000766001520250143532; 89000020240000766001520250143644; 89000020240000766001520250210976; 89000020240000766001520250259746; 89000020240000766001520250259811; 89000020240000766001520250259890; 89000020240000766001520250327158; 89000020240000766001520250327222; 89000020240000766001520250327942; 89000020240000766001520250451335; 89000020240000766001520250451645; 89000020240000766001520250451676; 89000020240000766001520250451827; 89000020240000766001520250507859; 89000020240000766001520250507978; 89000020240000766001520250508131; 89000020240000766001520250508425; 89000020240000766001520240650005; 89000020240000766001520240651200; 89000020240000766001520240654080; 89000020240000766001520250143640; 89000020240000766001520250143880; 89000020240000766001520250208824; 89000020240000766001520250210944; 89000020240000766001520250211055; 89000020240000766001520250259748; 89000020240000766001520250259978; 89000020240000766001520250260074; 89000020240000766001520250327177; 89000020240000766001520250327534; 89000020240000766001520250400630; 89000020240000766001520250400660; 89000020240000766001520250400693; 89000020240000766001520250400752; 89000020240000766001520250451735; 89000020240000766001520250451899; 89000020240000766001520250508145; 89000020240000766001520250508160; 89000020240000766001520250508210; 89000020240000766001520250508502; 89000020240000766001520250508532; 89000020240000766001520250508539; 89000020240000766001520240654651; 89000020240000766001520250143661; 89000020240000766001520250208726; 89000020240000766001520250208938; 89000020240000766001520250260102; 89000020240000766001520250260218; 89000020240000766001520250327391; 89000020240000766001520250327572; 89000020240000766001520250327601; 89000020240000766001520250327704; 89000020240000766001520250327735; 89000020240000766001520250327889; 89000020240000766001520250400615; 89000020240000766001520250400881; 89000020240000766001520250451490; 89000020240000766001520250451512; 89000020240000766001520250451777; 89000020240000766001520250508033; 89000020240000766001520250508137; 89000020240000766001520250508289; 89000020240000766001520240650517; 89000020240000766001520240654436; 89000020240000766001520250143791; 89000020240000766001520250143809; 89000020240000766001520250143819; 89000020240000766001520250143843; 89000020240000766001520250143913; 89000020240000766001520250208742; 89000020240000766001520250208792; 89000020240000766001520250208864; 89000020240000766001520250208998; 89000020240000766001520250260092; 89000020240000766001520250327834; 89000020240000766001520250400584; 89000020240000766001520250400672; 89000020240000766001520250507902; 89000020240000766001520250507964; 89000020240000766001520250508263; 89000020240000766001520250508399; 89000020240000766001520250508509; 89000020240000766001520250508536; 89000020240000766001520240650481; 89000020240000766001520240650541; 89000020240000766001520250143471; 89000020240000766001520250143525; 89000020240000766001520250143731; 89000020240000766001520250143781; 89000020240000766001520250143854; 89000020240000766001520250143864; 89000020240000766001520250208698; 89000020240000766001520250208783; 89000020240000766001520250208939; 89000020240000766001520250259875; 89000020240000766001520250260042; 89000020240000766001520250260119; 89000020240000766001520250327125; 89000020240000766001520250327256; 89000020240000766001520250327651; 89000020240000766001520250327738; 89000020240000766001520250327812; 89000020240000766001520250327971; 89000020240000766001520250451361; 89000020240000766001520250451403; 89000020240000766001520250451413; 89000020240000766001520250451425; 89000020240000766001520250507967; 89000020240000766001520250508035; 89000020240000766001520250508446; 89000020240000766001520250508501; 89000020240000766001520240650516; 89000020240000766001520250082912; 89000020240000766001520250082937; 89000020240000766001520250210942; 89000020240000766001520250259935; 89000020240000766001520250259939; 89000020240000766001520250260188; 89000020240000766001520250327205; 89000020240000766001520250327312; 89000020240000766001520250327420; 89000020240000766001520250327483; 89000020240000766001520250327484; 89000020240000766001520250327899; 89000020240000766001520250400585; 89000020240000766001520250400677; 89000020240000766001520250400729; 89000020240000766001520250400750; 89000020240000766001520250400764; 89000020240000766001520250508028; 89000020240000766001520250508092; 89000020240000766001520250508102; 89000020240000766001520250508343; 89000020240000766001520250508396; 89000020240000766001520250508510; 31000307044893096000000000000000; 89000020240000766001520240650433; 89000020240000766001520240651700; 89000020240000766001520250082922; 89000020240000766001520250082939; 89000020240000766001520250143508; 89000020240000766001520250143513; 89000020240000766001520250143801; 89000020240000766001520250208756; 89000020240000766001520250208956; 89000020240000766001520250211025; 89000020240000766001520250259973; 89000020240000766001520250260034; 89000020240000766001520250260035; 89000020240000766001520250260166; 89000020240000766001520250327169; 89000020240000766001520250327265; 89000020240000766001520250327481; 89000020240000766001520250327721; 89000020240000766001520250327776; 89000020240000766001520250327863; 89000020240000766001520250400680; 89000020240000766001520250400727; 89000020240000766001520250451656; 89000020240000766001520250451726; 89000020240000766001520250508409; 89000020240000766001520250508508; 89000020240000766001520250508526; 89000020240000766001520240650006; 89000020240000766001520240650436; 89000020240000766001520240650506; 89000020240000766001520240650873; 89000020240000766001520240651180; 89000020240000766001520250082932; 89000020240000766001520250143451; 89000020240000766001520250143612; 89000020240000766001520250143806; 89000020240000766001520250259904; 89000020240000766001520250260045; 89000020240000766001520250327185; 89000020240000766001520250327187; 89000020240000766001520250327537; 89000020240000766001520250327843; 89000020240000766001520250400633; 89000020240000766001520250400815; 89000020240000766001520250451344; 89000020240000766001520250451530; 89000020240000766001520250451585; 89000020240000766001520250451586; 89000020240000766001520250451697; 89000020240000766001520250451741; 89000020240000766001520250451792; 89000020240000766001520250451931; 89000020240000766001520250451957; 89000020240000766001520250507945; 89000020240000766001520240650564; 89000020240000766001520250143488; 89000020240000766001520250143533; 89000020240000766001520250143580; 89000020240000766001520250143711; 89000020240000766001520250143789; 89000020240000766001520250143907; 89000020240000766001520250211059; 89000020240000766001520250211071; 89000020240000766001520250260096; 89000020240000766001520250327210; 89000020240000766001520250327438; 89000020240000766001520250327460; 89000020240000766001520250327676; 89000020240000766001520250327809; 89000020240000766001520250451498; 89000020240000766001520250451936; 89000020240000766001520250508157; 89000020240000766001520250508251; 89000020240000766001520250508542; 89000020240000766001520240650363; 89000020240000766001520240650990; 89000020240000766001520250143448; 89000020240000766001520250143570; 89000020240000766001520250143942; 89000020240000766001520250208813; 89000020240000766001520250210997; 89000020240000766001520250211083; 89000020240000766001520250259744; 89000020240000766001520250260043; 89000020240000766001520250327135; 89000020240000766001520250400709; 89000020240000766001520250451345; 89000020240000766001520250451348; 89000020240000766001520250451671; 89000020240000766001520250451763; 89000020240000766001520250451823; 89000020240000766001520250451941; 89000020240000766001520250507930; 89000020240000766001520250508095; 89000020240000766001520250508202; 89000020240000766001520250508250; 89000020240000766001520240650568; 89000020240000766001520240651713; 89000020240000766001520240654666; 89000020240000766001520250143547; 89000020240000766001520250143931; 89000020240000766001520250259756; 89000020240000766001520250259757; 89000020240000766001520250259985; 89000020240000766001520250259988; 89000020240000766001520250327399; 89000020240000766001520250327421; 89000020240000766001520250400595; 89000020240000766001520250400627; 89000020240000766001520250451343; 89000020240000766001520250451442; 89000020240000766001520250451731; 89000020240000766001520250451873; 89000020240000766001520250451910; 89000020240000766001520250451946; 89000020240000766001520250507985; 89000020240000766001520250508296; 89000020240000766001520250508406; 89000020240000766001520240650409; 89000020240000766001520240651307; 89000020240000766001520240652439; 89000020240000766001520240652441; 89000020240000766001520240652452; 89000020240000766001520250082928; 89000020240000766001520250143524; 89000020240000766001520250259734; 89000020240000766001520250260090; 89000020240000766001520250260104; 89000020240000766001520250400779; 89000020240000766001520250400855; 89000020240000766001520250451360; 89000020240000766001520250451624; 89000020240000766001520250507854; 89000020240000766001520250507888; 89000020240000766001520250507986; 89000020240000766001520250508066; 89000020240000766001520250508447; 89000020240000766001520240650203; 89000020240000766001520240650360; 89000020240000766001520240651473; 89000020240000766001520250082938; 89000020240000766001520250143449; 89000020240000766001520250143552; 89000020240000766001520250208727; 89000020240000766001520250259778; 89000020240000766001520250327156; 89000020240000766001520250327285; 89000020240000766001520250327493; 89000020240000766001520250327941; 89000020240000766001520250451370; 89000020240000766001520250451923; 89000020240000766001520250507943; 89000020240000766001520250508044; 89000020240000766001520250508319; 89000020240000766001520250508395; 89000020240000766001520240651698; 89000020240000766001520250143523; 89000020240000766001520250143768; 89000020240000766001520250210969; 89000020240000766001520250211039; 89000020240000766001520250259771; 89000020240000766001520250259782; 89000020240000766001520250259898; 89000020240000766001520250327302; 89000020240000766001520250327411; 89000020240000766001520250327454; 89000020240000766001520250327471; 89000020240000766001520250327485; 89000020240000766001520250327699; 89000020240000766001520250327855; 89000020240000766001520250327954; 89000020240000766001520250451405; 89000020240000766001520250451909; 89000020240000766001520250451966; 89000020240000766001520250508105; 89000020240000766001520250508438; 89000020240000766001520250508441; 89000020240000766001520240652388; 89000020240000766001520250082901; 89000020240000766001520250143484; 89000020240000766001520250143812; 89000020240000766001520250143821; 89000020240000766001520250143948; 89000020240000766001520250208763; 89000020240000766001520250208825; 89000020240000766001520250208964; 89000020240000766001520250211079; 89000020240000766001520250259792; 89000020240000766001520250259999; 89000020240000766001520250260212; 89000020240000766001520250327465; 89000020240000766001520250327748; 89000020240000766001520250327815; 89000020240000766001520250327891; 89000020240000766001520250400758; 89000020240000766001520250451581; 89000020240000766001520250451613; 89000020240000766001520250451693; 89000020240000766001520250451766; 89000020240000766001520250451786; 89000020240000766001520250451864; 89000020240000766001520250451924; 89000020240000766001520250507957; 89000020240000766001520250507972; 89000020240000766001520250508161; 89000020240000766001520250508247; 89000020240000766001520240649875; 89000020240000766001520240650783; 89000020240000766001520240651723; 89000020240000766001520240654455; 89000020240000766001520250082925; 89000020240000766001520250208786; 89000020240000766001520250259773; 89000020240000766001520250260069; 89000020240000766001520250327260; 89000020240000766001520250327366; 89000020240000766001520250327389; 89000020240000766001520250327418; 89000020240000766001520250327473; 89000020240000766001520250327564; 89000020240000766001520250451290; 89000020240000766001520250451314; 89000020240000766001520250451472; 89000020240000766001520250451474; 89000020240000766001520250451541; 89000020240000766001520250451859; 89000020240000766001520250451868; 89000020240000766001520250451944; 89000020240000766001520250508113; 89000020240000766001520250508334; 89000020240000766001520250508495; 89000020240000766001520240650387; 89000020240000766001520240650786; 89000020240000766001520250143440; 89000020240000766001520250143511; 89000020240000766001520250143626; 89000020240000766001520250143945; 89000020240000766001520250208703; 89000020240000766001520250208731; 89000020240000766001520250208855; 89000020240000766001520250208947; 89000020240000766001520250260222; 89000020240000766001520250327267; 89000020240000766001520250327344; 89000020240000766001520250327663; 89000020240000766001520250327682; 89000020240000766001520250400601; 89000020240000766001520250400663; 89000020240000766001520250400791; 89000020240000766001520250451305; 89000020240000766001520250451794; 89000020240000766001520250451885; 89000020240000766001520250451925; 89000020240000766001520250451950; 89000020240000766001520250507838; 89000020240000766001520250508061; 89000020240000766001520250508119; 89000020240000766001520250508479; 89000020240000766001520240650853; 89000020240000766001520240652323; 89000020240000766001520250143512; 89000020240000766001520250143818; 89000020240000766001520250208771; 89000020240000766001520250208860; 89000020240000766001520250259952; 89000020240000766001520250260027; 89000020240000766001520250260211; 89000020240000766001520250260245; 89000020240000766001520250327226; 89000020240000766001520250327425; 89000020240000766001520250327672; 89000020240000766001520250327900; 89000020240000766001520250451598; 89000020240000766001520250508100; 89000020240000766001520250508323; 89000020240000766001520240650947; 89000020240000766001520240651474; 89000020240000766001520240654084; 89000020240000766001520250143433; 89000020240000766001520250143850; 89000020240000766001520250208680; 89000020240000766001520250208758; 89000020240000766001520250208807; 89000020240000766001520250208853; 89000020240000766001520250208981; 89000020240000766001520250210967; 89000020240000766001520250260199; 89000020240000766001520250327434; 89000020240000766001520250327970; 89000020240000766001520250400737; 89000020240000766001520250400753; 89000020240000766001520250400838; 89000020240000766001520250451446; 89000020240000766001520250451620; 89000020240000766001520250508286; 89000020240000766001520250508351; 89000020240000766001520240650010; 89000020240000766001520240650355; 89000020240000766001520240651197; 89000020240000766001520240651684; 89000020240000766001520240654433; 89000020240000766001520250143730; 89000020240000766001520250143885; 89000020240000766001520250143900; 89000020240000766001520250208750; 89000020240000766001520250208885; 89000020240000766001520250259983; 89000020240000766001520250260136; 89000020240000766001520250260276; 89000020240000766001520250327112; 89000020240000766001520250327504; 89000020240000766001520250327549; 89000020240000766001520250327605; 89000020240000766001520250327833; 89000020240000766001520250327904; 89000020240000766001520250327988; 89000020240000766001520250400586; 89000020240000766001520250400674; 89000020240000766001520250400882; 89000020240000766001520250451285; 89000020240000766001520250451412; 89000020240000766001520250451654; 89000020240000766001520250507923; 89000020240000766001520250508321; 89000020240000766001520240650370; 89000020240000766001520240650514; 89000020240000766001520250143539; 89000020240000766001520250143748; 89000020240000766001520250143946; 89000020240000766001520250210984; 89000020240000766001520250259739; 89000020240000766001520250259787; 89000020240000766001520250260064; 89000020240000766001520250260095; 89000020240000766001520250327140; 89000020240000766001520250327164; 89000020240000766001520250327199; 89000020240000766001520250327349; 89000020240000766001520250400652; 89000020240000766001520250400806; 89000020240000766001520250451374; 89000020240000766001520250451379; 89000020240000766001520250451891; 89000020240000766001520250508002; 89000020240000766001520250508005; 89000020240000766001520250508204; 89000020240000766001520250508313; 89000020240000766001520240650425; 89000020240000766001520240650527; 89000020240000766001520240652066; 89000020240000766001520250143734; 89000020240000766001520250208738; 89000020240000766001520250208744; 89000020240000766001520250327332; 89000020240000766001520250327401; 89000020240000766001520250327402; 89000020240000766001520250327517; 89000020240000766001520250327540; 89000020240000766001520250327548; 89000020240000766001520250327710; 89000020240000766001520250327947; 89000020240000766001520250400802; 89000020240000766001520250400807; 89000020240000766001520250451315; 89000020240000766001520250451528; 89000020240000766001520250451638; 89000020240000766001520250451689; 89000020240000766001520250451799; 89000020240000766001520250507921; 89000020240000766001520250508011; 89000020240000766001520240650407; 89000020240000766001520240650992; 89000020240000766001520240651201; 89000020240000766001520240651476; 89000020240000766001520240652365; 89000020240000766001520250143616; 89000020240000766001520250143635; 89000020240000766001520250210939; 89000020240000766001520250260149; 89000020240000766001520250260171; 89000020240000766001520250260243; 89000020240000766001520250327147; 89000020240000766001520250327272; 89000020240000766001520250327410; 89000020240000766001520250327539; 89000020240000766001520250327670; 89000020240000766001520250327822; 89000020240000766001520250400629; 89000020240000766001520250451847; 89000020240000766001520250507891; 89000020240000766001520250507935; 89000020240000766001520250508197; 89000020240000766001520250508317; 89000020240000766001520250508354; 89000020240000766001520240650980; 89000020240000766001520240654070; 89000020240000766001520240654653; 89000020240000766001520250143827; 89000020240000766001520250208888; 89000020240000766001520250208937; 89000020240000766001520250259938; 89000020240000766001520250259944; 89000020240000766001520250260206; 89000020240000766001520250327284; 89000020240000766001520250400832; 89000020240000766001520250451710; 89000020240000766001520250451796; 89000020240000766001520250451828; 89000020240000766001520250451866; 89000020240000766001520250451955; 89000020240000766001520250507955; 89000020240000766001520250508147; 31000311847794096000000000000000; 89000020240000766001520240650393; 89000020240000766001520240650476; 89000020240000766001520240650520; 89000020240000766001520240654441; 89000020240000766001520250143683; 89000020240000766001520250208803; 89000020240000766001520250208808; 89000020240000766001520250259932; 89000020240000766001520250260028; 89000020240000766001520250327294; 89000020240000766001520250327512; 89000020240000766001520250327667; 89000020240000766001520250327673; 89000020240000766001520250327677; 89000020240000766001520250327698; 89000020240000766001520250327716; 89000020240000766001520250327740; 89000020240000766001520250327841; 89000020240000766001520250327890; 89000020240000766001520250327986; 89000020240000766001520250400592; 89000020240000766001520250400845; 89000020240000766001520250451481; 89000020240000766001520250507844; 89000020240000766001520250507971; 89000020240000766001520250508544; 31000315970345096000000000000000; 89000020240000766001520240650542; 89000020240000766001520240652461; 89000020240000766001520250082920; 89000020240000766001520250143509; 89000020240000766001520250143579; 89000020240000766001520250143744; 89000020240000766001520250208734; 89000020240000766001520250211033; 89000020240000766001520250260051; 89000020240000766001520250260175; 89000020240000766001520250327424; 89000020240000766001520250327662; 89000020240000766001520250327842; 89000020240000766001520250327958; 89000020240000766001520250400705; 89000020240000766001520250400843; 89000020240000766001520250508216; 89000020240000766001520240649873; 89000020240000766001520240650401; 89000020240000766001520240650501; 89000020240000766001520240653179; 89000020240000766001520240654429; 89000020240000766001520250143630; 89000020240000766001520250143652; 89000020240000766001520250143755; 89000020240000766001520250143894; 89000020240000766001520250208776; 89000020240000766001520250260120; 89000020240000766001520250260213; 89000020240000766001520250260233; 89000020240000766001520250327244; 89000020240000766001520250327350; 89000020240000766001520250327581; 89000020240000766001520250327848; 89000020240000766001520250327960; 89000020240000766001520250451589; 89000020240000766001520250451658; 89000020240000766001520250451849; 89000020240000766001520250507956; 89000020240000766001520250508154; 31000315970329096000000000000000; 89000020240000766001520240650372; 89000020240000766001520240654656; 89000020240000766001520250143527; 89000020240000766001520250143648; 89000020240000766001520250143840; 89000020240000766001520250208878; 89000020240000766001520250208992; 89000020240000766001520250208995; 89000020240000766001520250259822; 89000020240000766001520250260037; 89000020240000766001520250327351; 89000020240000766001520250327353; 89000020240000766001520250327362; 89000020240000766001520250327518; 89000020240000766001520250327617; 89000020240000766001520250327690; 89000020240000766001520250400805; 89000020240000766001520250451329; 89000020240000766001520250451761; 89000020240000766001520250451911; 89000020240000766001520250508322; 89000020240000766001520250508327; 89000020240000766001520250508518; 31000315970402096000000000000000; 89000020240000766001520240650349; 89000020240000766001520240650521; 89000020240000766001520240652375; 89000020240000766001520240654090; 89000020240000766001520250082891; 89000020240000766001520250211092; 89000020240000766001520250259853; 89000020240000766001520250327602; 89000020240000766001520250400719; 89000020240000766001520250400741; 89000020240000766001520250451362; 89000020240000766001520250451637; 89000020240000766001520250507889; 89000020240000766001520250508265; 89000020240000766001520250508315; 89000020240000766001520250508445; 89000020240000766001520250508452; 89000020240000766001520240650208; 89000020240000766001520240650551; 89000020240000766001520240650569; 89000020240000766001520240654074; 89000020240000766001520250082935; 89000020240000766001520250143799; 89000020240000766001520250143950; 89000020240000766001520250208895; 89000020240000766001520250208925; 89000020240000766001520250208943; 89000020240000766001520250210986; 89000020240000766001520250327224; 89000020240000766001520250327440; 89000020240000766001520250327838; 89000020240000766001520250327980; 89000020240000766001520250400669; 89000020240000766001520250400782; 89000020240000766001520250400799; 89000020240000766001520250451299; 89000020240000766001520250451387; 89000020240000766001520250451587; 89000020240000766001520250451756; 89000020240000766001520250508125; 89000020240000766001520250508468; 89000020240000766001520240650526; 89000020240000766001520240650543; 89000020240000766001520240653788; 89000020240000766001520250082915; 89000020240000766001520250143549; 89000020240000766001520250143664; 89000020240000766001520250143817; 89000020240000766001520250208780; 89000020240000766001520250208868; 89000020240000766001520250208989; 89000020240000766001520250259857; 89000020240000766001520250327189; 89000020240000766001520250327203; 89000020240000766001520250327488; 89000020240000766001520250400768; 89000020240000766001520250451573; 89000020240000766001520250451698; 89000020240000766001520250451810; 89000020240000766001520250508378; 31000318628196097000000000000000; 89000020240000766001520240650380; 89000020240000766001520240654075; 89000020240000766001520240654457; 89000020240000766001520250143422; 89000020240000766001520250143617; 89000020240000766001520250143898; 89000020240000766001520250143951; 89000020240000766001520250208787; 89000020240000766001520250259877; 89000020240000766001520250259961; 89000020240000766001520250327108; 89000020240000766001520250327257; 89000020240000766001520250327259; 89000020240000766001520250327378; 89000020240000766001520250327665; 89000020240000766001520250327844; 89000020240000766001520250400817; 89000020240000766001520250400875; 89000020240000766001520250451331; 89000020240000766001520250451617; 89000020240000766001520250451719; 89000020240000766001520250451837; 89000020240000766001520250507880; 89000020240000766001520250507949; 89000020240000766001520250508511; 89000020240000766001520240650494; 89000020240000766001520240651095; 89000020240000766001520240652320; 89000020240000766001520250143428; 89000020240000766001520250143651; 89000020240000766001520250143662; 89000020240000766001520250208741; 89000020240000766001520250208869; 89000020240000766001520250259777; 89000020240000766001520250260036; 89000020240000766001520250260093; 89000020240000766001520250260247; 89000020240000766001520250327194; 89000020240000766001520250327215; 89000020240000766001520250327231; 89000020240000766001520250327387; 89000020240000766001520250400681; 89000020240000766001520250400702; 89000020240000766001520250400755; 89000020240000766001520250451646; 89000020240000766001520250451694; 89000020240000766001520250451791; 89000020240000766001520250508304; 89000020240000766001520250508480; 89000020240000766001520240649946; 89000020240000766001520240650402; 89000020240000766001520240650948; 89000020240000766001520240651449; 89000020240000766001520240651706; 89000020240000766001520240654636; 89000020240000766001520250208767; 89000020240000766001520250260046; 89000020240000766001520250327253; 89000020240000766001520250327987; 89000020240000766001520250400720; 89000020240000766001520250451284; 89000020240000766001520250451491; 89000020240000766001520250451533; 89000020240000766001520250451665; 89000020240000766001520250451960; 89000020240000766001520250451973; 89000020240000766001520250507849; 89000020240000766001520250507992; 89000020240000766001520250508294; 89000020240000766001520250508381; 89000020240000766001520250508393; 31000318293090097000000000000000; 89000020240000766001520240650505; 89000020240000766001520240650553; 89000020240000766001520240653164; 89000020240000766001520250143531; 89000020240000766001520250143726; 89000020240000766001520250208711; 89000020240000766001520250208818; 89000020240000766001520250208822; 89000020240000766001520250211021; 89000020240000766001520250211091; 89000020240000766001520250327123; 89000020240000766001520250327166; 89000020240000766001520250327201; 89000020240000766001520250400714; 89000020240000766001520250400867; 89000020240000766001520250451367; 89000020240000766001520250451496; 89000020240000766001520250508027; 89000020240000766001520250508079; 89000020240000766001520250508082; 89000020240000766001520250508333; 89000020240000766001520250508454; 89000020240000766001520240650376; 89000020240000766001520240650523; 89000020240000766001520240654440; 89000020240000766001520250208743; 89000020240000766001520250208843; 89000020240000766001520250208913; 89000020240000766001520250208953; 89000020240000766001520250208990; 89000020240000766001520250260239; 89000020240000766001520250327310; 89000020240000766001520250327520; 89000020240000766001520250327631; 89000020240000766001520250327846; 89000020240000766001520250327948; 89000020240000766001520250327995; 89000020240000766001520250400634; 89000020240000766001520250400698; 89000020240000766001520250400725; 89000020240000766001520250400730; 89000020240000766001520250400772; 89000020240000766001520250451846; 89000020240000766001520250451906; 89000020240000766001520250508117; 89000020240000766001520250508298; 89000020240000766001520250508533; 89000020240000766001520240650420; 89000020240000766001520240650529; 89000020240000766001520240654446; 89000020240000766001520240654456; 89000020240000766001520250143692; 89000020240000766001520250143865; 89000020240000766001520250210965; 89000020240000766001520250211065; 89000020240000766001520250259795; 89000020240000766001520250259971; 89000020240000766001520250259997; 89000020240000766001520250260000; 89000020240000766001520250260087; 89000020240000766001520250260204; 89000020240000766001520250327192; 89000020240000766001520250327307; 89000020240000766001520250327372; 89000020240000766001520250327574; 89000020240000766001520250327877; 89000020240000766001520250400622; 89000020240000766001520250451394; 89000020240000766001520250451686; 89000020240000766001520250451797; 89000020240000766001520250507873; 89000020240000766001520250507946; 89000020240000766001520250508069; 89000020240000766001520250508097; 89000020240000766001520250508462; 89000020240000766001520250508494; 89000020240000766001520240650383; 89000020240000766001520240650486; 89000020240000766001520240652067; 89000020240000766001520240652312; 89000020240000766001520250082892; 89000020240000766001520250082897; 89000020240000766001520250143786; 89000020240000766001520250208684; 89000020240000766001520250210962; 89000020240000766001520250259914; 89000020240000766001520250260109; 89000020240000766001520250260277; 89000020240000766001520250327462; 89000020240000766001520250327645; 89000020240000766001520250400682; 89000020240000766001520250400873; 89000020240000766001520250451499; 89000020240000766001520250451543; 89000020240000766001520250451722; 89000020240000766001520250507872; 89000020240000766001520250508024; 89000020240000766001520250508151; 89000020240000766001520250508505; 89000020240000766001520250508537; 89000020240000766001520240650381; 89000020240000766001520250143637; 89000020240000766001520250208976; 89000020240000766001520250211050; 89000020240000766001520250260024; 89000020240000766001520250260062; 89000020240000766001520250327159; 89000020240000766001520250327197; 89000020240000766001520250327280; 89000020240000766001520250327407; 89000020240000766001520250327820; 89000020240000766001520250400654; 89000020240000766001520250400700; 89000020240000766001520250451436; 89000020240000766001520250451696; 89000020240000766001520250451772; 89000020240000766001520250451865; 89000020240000766001520250507908; 89000020240000766001520250508089; 89000020240000766001520250508110; 89000020240000766001520250508111; 89000020240000766001520250508332; 89000020240000766001520250508346; 31000313517171096000000000000000; 89000020240000766001520240651187; 89000020240000766001520240651471; 89000020240000766001520240653178; 89000020240000766001520250082909; 89000020240000766001520250143607; 89000020240000766001520250143703; 89000020240000766001520250143826; 89000020240000766001520250143875; 89000020240000766001520250208665; 89000020240000766001520250260054; 89000020240000766001520250260123; 89000020240000766001520250260185; 89000020240000766001520250260238; 89000020240000766001520250260251; 89000020240000766001520250327157; 89000020240000766001520250327409; 89000020240000766001520250327417; 89000020240000766001520250327439; 89000020240000766001520250327832; 89000020240000766001520250327873; 89000020240000766001520250400707; 89000020240000766001520250451384; 89000020240000766001520250451406; 89000020240000766001520250451554; 89000020240000766001520250451633; 89000020240000766001520250451939; 89000020240000766001520250508275; 89000020240000766001520250508388; 89000020240000766001520250508397; 31000318636603097000000000000000; 89000020240000766001520240650400; 89000020240000766001520240650555; 89000020240000766001520240650960; 89000020240000766001520240651719; 89000020240000766001520240652043; 89000020240000766001520240654072; 89000020240000766001520250143884; 89000020240000766001520250208889; 89000020240000766001520250211066; 89000020240000766001520250259740; 89000020240000766001520250259841; 89000020240000766001520250259896; 89000020240000766001520250327339; 89000020240000766001520250327403; 89000020240000766001520250327554; 89000020240000766001520250327636; 89000020240000766001520250327713; 89000020240000766001520250327734; 89000020240000766001520250451346; 89000020240000766001520250451381; 89000020240000766001520250451759; 89000020240000766001520250451933; 89000020240000766001520250508541; 89000020240000766001520240650530; 89000020240000766001520240653167; 89000020240000766001520250143923; 89000020240000766001520250260057; 89000020240000766001520250260228; 89000020240000766001520250327248; 89000020240000766001520250327859; 89000020240000766001520250400761; 89000020240000766001520250451801; 89000020240000766001520250451841; 89000020240000766001520
B128: =+IF(LEFT(MID(Controlos[[#This Row],[tabela]],22,5),1)="B",MID(Controlos[[#This Row],[tabela]],22,5),MID(Controlos[[#This Row],[tabela]],18,5)) -> LT002 | C128: =+IF(Controlos[[#This Row],[tipologia_teste]]="REGULAMENTAR",IF(LEFT(Controlos[[#This Row],[cod_kpi]],1)="v",IF(LEFT(Controlos[[#This Row],[descrição]],6)="Alerta","W","H"),"F"),0) -> 0 | F128: 2025-10-31 | G128: MIS_LT002_DT_INCPTN | H128: MISSINGS | I128: Validar que não existem registos por preencher (Missings) | J128: BU_LOANTAPE_WORK.LT002_INSTRUMENT | K128: DT_INCPTN | L128: 4742 | M128: 0
B129: =+IF(LEFT(MID(Controlos[[#This Row],[tabela]],22,5),1)="B",MID(Controlos[[#This Row],[tabela]],22,5),MID(Controlos[[#This Row],[tabela]],18,5)) -> LT002 | C129: =+IF(Controlos[[#This Row],[tipologia_teste]]="REGULAMENTAR",IF(LEFT(Controlos[[#This Row],[cod_kpi]],1)="v",IF(LEFT(Controlos[[#This Row],[descrição]],6)="Alerta","W","H"),"F"),0) -> 0 | F129: 2025-10-31 | G129: MIS_LT002_DT_NXT_INTRST_PYMNT | H129: MISSINGS | I129: Validar que não existem registos por preencher (Missings) | J129: BU_LOANTAPE_WORK.LT002_INSTRUMENT | K129: DT_NXT_INTRST_PYMNT | L129: 4742 | M129: 23 | N129: 31000315970006096000000000000000; 31000315970345096000000000000000; 31000315970329096000000000000000; 31000315970402096000000000000000; 31000313517171096000000000000000; 31000311847794096000000000000000; 31641600005800007PTCPP0AM0007000; 31000307044893096000000000000000; 31000315970188096000000000000000; 31000315970238096000000000000000; 31000315970428096000000000000000; 31000315970139096000000000000000; 31000315979890096000000000000000; 31000315970469096000000000000000; 31000307530917096000000000000000; 31000315970121096000000000000000; 31000000000000000962304890482490; 31000315970212096000000000000000; 31000315970279096000000000000000; 31000315970261096000000000000000; 31000304140330096000000000000000; 31000315970311096000000000000000; 31000311450813096000000000000000
B130: =+IF(LEFT(MID(Controlos[[#This Row],[tabela]],22,5),1)="B",MID(Controlos[[#This Row],[tabela]],22,5),MID(Controlos[[#This Row],[tabela]],18,5)) -> LT002 | C130: =+IF(Controlos[[#This Row],[tipologia_teste]]="REGULAMENTAR",IF(LEFT(Controlos[[#This Row],[cod_kpi]],1)="v",IF(LEFT(Controlos[[#This Row],[descrição]],6)="Alerta","W","H"),"F"),0) -> 0 | F130: 2025-10-31 | G130: MIS_LT002_DT_LGL_FNL_MTRTY | H130: MISSINGS | I130: Validar que não existem registos por preencher (Missings) | J130: BU_LOANTAPE_WORK.LT002_INSTRUMENT | K130: DT_LGL_FNL_MTRTY | L130: 4742 | M130: 0
