Workbook
Name RefDateCell: '1. Dashboard'!$D$12

Sheet Instruções
B6: Instruções
C8: 1.
C9: 2.
C10: 3.

Sheet Param_RefDate
A1: Param_RefDate
A2: 2025-10-31

Sheet 1. Dashboard
B6: 1 Dashboard
B9: Controlos Reporte Bail-in
C12: Data de referência | D12: 2025-10-31
D15: MENU 1 | G15: MENU 2 | J15: NAVEGADOR
D18: TABELAS OUTPUT | G18: Processo (HUE vs CSV) | J18: Processo (HUE vs CSV)
D20: 1. Gerar Controlos | E20: [BOTÃO] | G20: 1. Gerar Controlos | H20: [BOTÃO] | J20: 1. Detalhe controlos às tabelas output | L20: [LINK]
J22: 2. Detalhe controlos ao processo (CSV) | L22: [LINK]
H29: DASHBOARD
C32: 1. Tabelas Output
C34: Mapa | D34: Total (#) | E34: OK (#) | F34: OK (%) | G34: NOK Justificados(#) | H34: NOK Justificados (%) | I34: NOK (#) | J34: NOK (%)
C35: B02.00 | D35: =+SUM(D36,D40) -> 304 | E35: =+SUM(E36,E40) -> 258 | F35: =IFERROR(E35/D35,0) -> 0.84868421 | G35: =+SUM(G36,G40) -> 8 | H35: =IFERROR(G35/D35,0) -> 0.026315789 | I35: =+SUM(I36,I40) -> 33 | J35: =IFERROR(I35/D35,0) -> 0.10855263
C36: Regulamentares (SRB) | D36: =+SUM(D37:D39) -> 156 | E36: =+SUM(E37:E39) -> 134 | F36: =IFERROR(E36/D36,0) -> 0.85897436 | G36: =+SUM(G37:G39) -> 6 | H36: =IFERROR(G36/D36,0) -> 0.038461538 | I36: =+SUM(I37:I39) -> 11 | J36: =IFERROR(I36/D36,0) -> 0.070512821
C37: High severity | D37: =+COUNTIFS('2.1. Regulamentares'!G:G,'1. Dashboard'!$C$35,'2.1. Regulamentares'!F:F,"h") -> 63 | E37: =+COUNTIFS('2.1. Regulamentares'!G:G,'1. Dashboard'!$C$35,'2.1. Regulamentares'!F:F,"h",'2.1. Regulamentares'!C:C,"=0") -> 53 | F37: =IFERROR(E37/D37,0) -> 0.84126984 | G37: =+COUNTIFS('2.1. Regulamentares'!G:G,'1. Dashboard'!$C$35,'2.1. Regulamentares'!F:F,"h",'2.1. Regulamentares'!C:C,">0",'2.1. Regulamentares'!I:I,"<>") -> 0 | H37: =IFERROR(G37/D37,0) -> 0 | I37: =+COUNTIFS('2.1. Regulamentares'!G:G,'1. Dashboard'!$C$35,'2.1. Regulamentares'!F:F,"h",'2.1. Regulamentares'!C:C,">0",'2.1. Regulamentares'!I:I,"") -> 5 | J37: =IFERROR(I37/D37,0) -> 0.079365079
C38: Warnings | D38: =+COUNTIFS('2.1. Regulamentares'!G:G,'1. Dashboard'!$C$35,'2.1. Regulamentares'!F:F,"w") -> 12 | E38: =+COUNTIFS('2.1. Regulamentares'!G:G,'1. Dashboard'!$C$35,'2.1. Regulamentares'!F:F,"w",'2.1. Regulamentares'!C:C,"=0") -> 11 | F38: =IFERROR(E38/D38,0) -> 0.91666667 | G38: =+COUNTIFS('2.1. Regulamentares'!G:G,'1. Dashboard'!$C$35,'2.1. Regulamentares'!F:F,"w",'2.1. Regulamentares'!C:C,">0",'2.1. Regulamentares'!I:I,"<>") -> 0 | H38: =IFERROR(G38/D38,0) -> 0 | I38: =+COUNTIFS('2.1. Regulamentares'!G:G,'1. Dashboard'!$C$35,'2.1. Regulamentares'!F:F,"w",'2.1. Regulamentares'!C:C,">0",'2.1. Regulamentares'!I:I,"") -> 1 | J38: =IFERROR(I38/D38,0) -> 0.083333333
C39: Formatos | D39: =+COUNTIFS('2.1. Regulamentares'!G:G,'1. Dashboard'!$C$35,'2.1. Regulamentares'!F:F,"f") -> 81 | E39: =+COUNTIFS('2.1. Regulamentares'!G:G,'1. Dashboard'!$C$35,'2.1. Regulamentares'!F:F,"f",'2.1. Regulamentares'!C:C,"=0") -> 70 | F39: =IFERROR(E39/D39,0) -> 0.86419753 | G39: =+COUNTIFS('2.1. Regulamentares'!G:G,'1. Dashboard'!$C$35,'2.1. Regulamentares'!F:F,"f",'2.1. Regulamentares'!C:C,">0",'2.1. Regulamentares'!I:I,"<>") -> 6 | H39: =IFERROR(G39/D39,0) -> 0.074074074 | I39: =+COUNTIFS('2.1. Regulamentares'!G:G,'1. Dashboard'!$C$35,'2.1. Regulamentares'!F:F,"f",'2.1. Regulamentares'!C:C,">0",'2.1. Regulamentares'!I:I,"") -> 5 | J39: =IFERROR(I39/D39,0) -> 0.061728395
C40: Outros | D40: =+SUM(D41:D44) -> 148 | E40: =+SUM(E41:E44) -> 124 | F40: =IFERROR(E40/D40,0) -> 0.83783784 | G40: =+SUM(G41:G44) -> 2 | H40: =IFERROR(G40/D40,0) -> 0.013513514 | I40: =+SUM(I41:I44) -> 22 | J40: =IFERROR(I40/D40,0) -> 0.14864865
C41: Validade (Missings/NULLS) | D41: =+COUNTIFS('2.2. Outros'!H:H,'1. Dashboard'!$C$35,'2.2. Outros'!D:D,"Validade") -> 73 | E41: =+COUNTIFS('2.2. Outros'!H:H,'1. Dashboard'!$C$35,'2.2. Outros'!D:D,"Validade",'2.2. Outros'!F:F,"0") -> 70 | F41: =IFERROR(E41/D41,0) -> 0.95890411 | G41: =+COUNTIFS('2.2. Outros'!H:H,'1. Dashboard'!$C$35,'2.2. Outros'!D:D,"Validade",'2.2. Outros'!F:F,"<>0",'2.2. Outros'!I:I,"<>") -> 1 | H41: =IFERROR(G41/D41,0) -> 0.01369863 | I41: =+COUNTIFS('2.2. Outros'!H:H,'1. Dashboard'!$C$35,'2.2. Outros'!D:D,"Validade",'2.2. Outros'!F:F,"<>0",'2.2. Outros'!I:I,"") -> 2 | J41: =IFERROR(I41/D41,0) -> 0.02739726
C42: Not applicables | D42: =+COUNTIFS('2.2. Outros'!H:H,'1. Dashboard'!$C$35,'2.2. Outros'!D:D,"Not applicable") -> 73 | E42: =+COUNTIFS('2.2. Outros'!H:H,'1. Dashboard'!$C$35,'2.2. Outros'!D:D,"Not applicable",'2.2. Outros'!F:F,"0") -> 52 | F42: =IFERROR(E42/D42,0) -> 0.71232877 | G42: =+COUNTIFS('2.2. Outros'!H:H,'1. Dashboard'!$C$35,'2.2. Outros'!D:D,"Not applicable",'2.2. Outros'!F:F,"<>0",'2.2. Outros'!I:I,"<>") -> 1 | H42: =IFERROR(G42/D42,0) -> 0.01369863 | I42: =+COUNTIFS('2.2. Outros'!H:H,'1. Dashboard'!$C$35,'2.2. Outros'!D:D,"Not applicable",'2.2. Outros'!F:F,"<>0",'2.2. Outros'!I:I,"") -> 20 | J42: =IFERROR(I42/D42,0) -> 0.2739726
C43: Duplicados | D43: =+COUNTIFS('2.2. Outros'!H:H,'1. Dashboard'!$C$35,'2.2. Outros'!D:D,"Duplicados") -> 1 | E43: =+COUNTIFS('2.2. Outros'!H:H,'1. Dashboard'!$C$35,'2.2. Outros'!D:D,"Duplicados",'2.2. Outros'!F:F,"0") -> 1 | F43: =IFERROR(E43/D43,0) -> 1 | G43: =+COUNTIFS('2.2. Outros'!H:H,'1. Dashboard'!$C$35,'2.2. Outros'!D:D,"Duplicados",'2.2. Outros'!F:F,"<>0",'2.2. Outros'!I:I,"<>") -> 0 | H43: =IFERROR(G43/D43,0) -> 0 | I43: =+COUNTIFS('2.2. Outros'!H:H,'1. Dashboard'!$C$35,'2.2. Outros'!D:D,"Duplicados",'2.2. Outros'!F:F,"<>0",'2.2. Outros'!I:I,"") -> 0 | J43: =IFERROR(I43/D43,0) -> 0
C44: Integridade entre tabelas | D44: =+COUNTIFS('2.2. Outros'!H:H,'1. Dashboard'!$C$35,'2.2. Outros'!D:D,"Integridade") -> 1 | E44: =+COUNTIFS('2.2. Outros'!H:H,'1. Dashboard'!$C$35,'2.2. Outros'!D:D,"Integridade",'2.2. Outros'!F:F,"0") -> 1 | F44: =IFERROR(E44/D44,0) -> 1 | G44: =+COUNTIFS('2.2. Outros'!H:H,'1. Dashboard'!$C$35,'2.2. Outros'!D:D,"Integridade",'2.2. Outros'!F:F,"<>0",'2.2. Outros'!I:I,"<>") -> 0 | H44: =IFERROR(G44/D44,0) -> 0 | I44: =+COUNTIFS('2.2. Outros'!H:H,'1. Dashboard'!$C$35,'2.2. Outros'!D:D,"Integridade",'2.2. Outros'!F:F,"<>0",'2.2. Outros'!I:I,"") -> 0 | J44: =IFERROR(I44/D44,0) -> 0
C45: B05.00 | D45: =+SUM(D46,D50) -> 20 | E45: =+SUM(E46,E50) -> 17 | F45: =IFERROR(E45/D45,0) -> 0.85 | G45: =+SUM(G46,G50) -> 2 | H45: =IFERROR(G45/D45,0) -> 0.1 | I45: =+SUM(I46,I50) -> 1 | J45: =IFERROR(I45/D45,0) -> 0.05
C46: Regulamentares (SRB) | D46: =+SUM(D47:D49) -> 19 | E46: =+SUM(E47:E49) -> 16 | F46: =IFERROR(E46/D46,0) -> 0.84210526 | G46: =+SUM(G47:G49) -> 2 | H46: =IFERROR(G46/D46,0) -> 0.10526316 | I46: =+SUM(I47:I49) -> 1 | J46: =IFERROR(I46/D46,0) -> 0.052631579
C47: High severity | D47: =+COUNTIFS('2.1. Regulamentares'!G:G,$C$45,'2.1. Regulamentares'!F:F,"h") -> 5 | E47: =+COUNTIFS('2.1. Regulamentares'!G:G,$C$45,'2.1. Regulamentares'!F:F,"h",'2.1. Regulamentares'!C:C,"=0") -> 4 | F47: =IFERROR(E47/D47,0) -> 0.8 | G47: =+COUNTIFS('2.1. Regulamentares'!G:G,$C$45,'2.1. Regulamentares'!F:F,"h",'2.1. Regulamentares'!C:C,">0",'2.1. Regulamentares'!I:I,"<>") -> 0 | H47: =IFERROR(G47/D47,0) -> 0 | I47: =+COUNTIFS('2.1. Regulamentares'!G:G,$C$45,'2.1. Regulamentares'!F:F,"h",'2.1. Regulamentares'!C:C,">0",'2.1. Regulamentares'!I:I,"") -> 1 | J47: =IFERROR(I47/D47,0) -> 0.2
C48: Warnings | D48: =+COUNTIFS('2.1. Regulamentares'!G:G,$C$45,'2.1. Regulamentares'!F:F,"w") -> 0 | E48: =+COUNTIFS('2.1. Regulamentares'!G:G,$C$45,'2.1. Regulamentares'!F:F,"w",'2.1. Regulamentares'!C:C,"=0") -> 0 | F48: =IFERROR(E48/D48,0) -> 0 | G48: =+COUNTIFS('2.1. Regulamentares'!G:G,$C$45,'2.1. Regulamentares'!F:F,"w",'2.1. Regulamentares'!C:C,">0",'2.1. Regulamentares'!I:I,"<>") -> 0 | H48: =IFERROR(G48/D48,0) -> 0 | I48: =+COUNTIFS('2.1. Regulamentares'!G:G,$C$45,'2.1. Regulamentares'!F:F,"w",'2.1. Regulamentares'!C:C,">0",'2.1. Regulamentares'!I:I,"") -> 0 | J48: =IFERROR(I48/D48,0) -> 0
C49: Formatos | D49: =+COUNTIFS('2.1. Regulamentares'!G:G,$C$45,'2.1. Regulamentares'!F:F,"f") -> 14 | E49: =+COUNTIFS('2.1. Regulamentares'!G:G,$C$45,'2.1. Regulamentares'!F:F,"f",'2.1. Regulamentares'!C:C,"=0") -> 12 | F49: =IFERROR(E49/D49,0) -> 0.85714286 | G49: =+COUNTIFS('2.1. Regulamentares'!G:G,$C$45,'2.1. Regulamentares'!F:F,"f",'2.1. Regulamentares'!C:C,">0",'2.1. Regulamentares'!I:I,"<>") -> 2 | H49: =IFERROR(G49/D49,0) -> 0.14285714 | I49: =+COUNTIFS('2.1. Regulamentares'!G:G,$C$45,'2.1. Regulamentares'!F:F,"f",'2.1. Regulamentares'!C:C,">0",'2.1. Regulamentares'!I:I,"") -> 0 | J49: =IFERROR(I49/D49,0) -> 0
C50: Outros | D50: =+SUM(D51:D54) -> 1 | E50: =+SUM(E51:E54) -> 1 | F50: =IFERROR(E50/D50,0) -> 1 | G50: =+SUM(G51:G54) -> 0 | H50: =IFERROR(G50/D50,0) -> 0 | I50: =+SUM(I51:I54) -> 0 | J50: =IFERROR(I50/D50,0) -> 0
C51: Validade (Missings/NULLS) | D51: =+COUNTIFS('2.2. Outros'!H:H,$C$45,'2.2. Outros'!D:D,"Validade") -> 0 | E51: =+COUNTIFS('2.2. Outros'!H:H,$C$45,'2.2. Outros'!D:D,"Validade",'2.2. Outros'!F:F,"0") -> 0 | F51: =IFERROR(E51/D51,0) -> 0 | G51: =+COUNTIFS('2.2. Outros'!H:H,$C$45,'2.2. Outros'!D:D,"Validade",'2.2. Outros'!F:F,"<>0",'2.2. Outros'!I:I,"<>") -> 0 | H51: =IFERROR(G51/D51,0) -> 0 | I51: =+COUNTIFS('2.2. Outros'!H:H,$C$45,'2.2. Outros'!D:D,"Validade",'2.2. Outros'!F:F,"<>0",'2.2. Outros'!I:I,"") -> 0 | J51: =IFERROR(I51/D51,0) -> 0
C52: Not applicables | D52: =+COUNTIFS('2.2. Outros'!H:H,$C$45,'2.2. Outros'!D:D,"Not applicable") -> 0 | E52: =+COUNTIFS('2.2. Outros'!H:H,$C$45,'2.2. Outros'!D:D,"Not applicable",'2.2. Outros'!F:F,"0") -> 0 | F52: =IFERROR(E52/D52,0) -> 0 | G52: =+COUNTIFS('2.2. Outros'!H:H,$C$45,'2.2. Outros'!D:D,"Not applicable",'2.2. Outros'!F:F,"<>0",'2.2. Outros'!I:I,"<>") -> 0 | H52: =IFERROR(G52/D52,0) -> 0 | I52: =+COUNTIFS('2.2. Outros'!H:H,$C$45,'2.2. Outros'!D:D,"Not applicable",'2.2. Outros'!F:F,"<>0",'2.2. Outros'!I:I,"") -> 0 | J52: =IFERROR(I52/D52,0) -> 0
C53: Duplicados | D53: =+COUNTIFS('2.2. Outros'!H:H,$C$45,'2.2. Outros'!D:D,"Duplicados") -> 0 | E53: =+COUNTIFS('2.2. Outros'!H:H,$C$45,'2.2. Outros'!D:D,"Duplicados",'2.2. Outros'!F:F,"0") -> 0 | F53: =IFERROR(E53/D53,0) -> 0 | G53: =+COUNTIFS('2.2. Outros'!H:H,$C$45,'2.2. Outros'!D:D,"Duplicados",'2.2. Outros'!F:F,"<>0",'2.2. Outros'!I:I,"<>") -> 0 | H53: =IFERROR(G53/D53,0) -> 0 | I53: =+COUNTIFS('2.2. Outros'!H:H,$C$45,'2.2. Outros'!D:D,"Duplicados",'2.2. Outros'!F:F,"<>0",'2.2. Outros'!I:I,"") -> 0 | J53: =IFERROR(I53/D53,0) -> 0
C54: Integridade entre tabelas | D54: =+COUNTIFS('2.2. Outros'!H:H,$C$45,'2.2. Outros'!D:D,"Integridade") -> 1 | E54: =+COUNTIFS('2.2. Outros'!H:H,$C$45,'2.2. Outros'!D:D,"Integridade",'2.2. Outros'!F:F,"0") -> 1 | F54: =IFERROR(E54/D54,0) -> 1 | G54: =+COUNTIFS('2.2. Outros'!H:H,$C$45,'2.2. Outros'!D:D,"Integridade",'2.2. Outros'!F:F,"<>0",'2.2. Outros'!I:I,"<>") -> 0 | H54: =IFERROR(G54/D54,0) -> 0 | I54: =+COUNTIFS('2.2. Outros'!H:H,$C$45,'2.2. Outros'!D:D,"Integridade",'2.2. Outros'!F:F,"<>0",'2.2. Outros'!I:I,"") -> 0 | J54: =IFERROR(I54/D54,0) -> 0
C55: B90.00 | D55: =+SUM(D56,D60) -> 16 | E55: =+SUM(E56,E60) -> 13 | F55: =IFERROR(E55/D55,0) -> 0.8125 | G55: =+SUM(G56,G60) -> 2 | H55: =IFERROR(G55/D55,0) -> 0.125 | I55: =+SUM(I56,I60) -> 1 | J55: =IFERROR(I55/D55,0) -> 0.0625
C56: Regulamentares (SRB) | D56: =+SUM(D57:D59) -> 15 | E56: =+SUM(E57:E59) -> 12 | F56: =IFERROR(E56/D56,0) -> 0.8 | G56: =+SUM(G57:G59) -> 2 | H56: =IFERROR(G56/D56,0) -> 0.13333333 | I56: =+SUM(I57:I59) -> 1 | J56: =IFERROR(I56/D56,0) -> 0.066666667
C57: High severity | D57: =+COUNTIFS('2.1. Regulamentares'!G:G,$C$55,'2.1. Regulamentares'!F:F,"h") -> 4 | E57: =+COUNTIFS('2.1. Regulamentares'!G:G,$C$55,'2.1. Regulamentares'!F:F,"h",'2.1. Regulamentares'!C:C,"=0") -> 2 | F57: =IFERROR(E57/D57,0) -> 0.5 | G57: =+COUNTIFS('2.1. Regulamentares'!G:G,$C$55,'2.1. Regulamentares'!F:F,"h",'2.1. Regulamentares'!C:C,">0",'2.1. Regulamentares'!I:I,"<>") -> 1 | H57: =IFERROR(G57/D57,0) -> 0.25 | I57: =+COUNTIFS('2.1. Regulamentares'!G:G,$C$55,'2.1. Regulamentares'!F:F,"h",'2.1. Regulamentares'!C:C,">0",'2.1. Regulamentares'!I:I,"") -> 1 | J57: =IFERROR(I57/D57,0) -> 0.25
C58: Warnings | D58: =+COUNTIFS('2.1. Regulamentares'!G:G,$C$55,'2.1. Regulamentares'!F:F,"w") -> 0 | E58: =+COUNTIFS('2.1. Regulamentares'!G:G,$C$55,'2.1. Regulamentares'!F:F,"w",'2.1. Regulamentares'!C:C,"=0") -> 0 | F58: =IFERROR(E58/D58,0) -> 0 | G58: =+COUNTIFS('2.1. Regulamentares'!G:G,$C$55,'2.1. Regulamentares'!F:F,"w",'2.1. Regulamentares'!C:C,">0",'2.1. Regulamentares'!I:I,"<>") -> 0 | H58: =IFERROR(G58/D58,0) -> 0 | I58: =+COUNTIFS('2.1. Regulamentares'!G:G,$C$55,'2.1. Regulamentares'!F:F,"w",'2.1. Regulamentares'!C:C,">0",'2.1. Regulamentares'!I:I,"") -> 0 | J58: =IFERROR(I58/D58,0) -> 0
C59: Formatos | D59: =+COUNTIFS('2.1. Regulamentares'!G:G,$C$55,'2.1. Regulamentares'!F:F,"f") -> 11 | E59: =+COUNTIFS('2.1. Regulamentares'!G:G,$C$55,'2.1. Regulamentares'!F:F,"f",'2.1. Regulamentares'!C:C,"=0") -> 10 | F59: =IFERROR(E59/D59,0) -> 0.90909091 | G59: =+COUNTIFS('2.1. Regulamentares'!G:G,$C$55,'2.1. Regulamentares'!F:F,"f",'2.1. Regulamentares'!C:C,">0",'2.1. Regulamentares'!I:I,"<>") -> 1 | H59: =IFERROR(G59/D59,0) -> 0.090909091 | I59: =+COUNTIFS('2.1. Regulamentares'!G:G,$C$55,'2.1. Regulamentares'!F:F,"f",'2.1. Regulamentares'!C:C,">0",'2.1. Regulamentares'!I:I,"") -> 0 | J59: =IFERROR(I59/D59,0) -> 0
C60: Outros | D60: =+SUM(D61:D64) -> 1 | E60: =+SUM(E61:E64) -> 1 | F60: =IFERROR(E60/D60,0) -> 1 | G60: =+SUM(G61:G64) -> 0 | H60: =IFERROR(G60/D60,0) -> 0 | I60: =+SUM(I61:I64) -> 0 | J60: =IFERROR(I60/D60,0) -> 0
C61: Validade (Missings/NULLS) | D61: =+COUNTIFS('2.2. Outros'!H:H,$C$55,'2.2. Outros'!D:D,"Validade") -> 0 | E61: =+COUNTIFS('2.2. Outros'!H:H,$C$55,'2.2. Outros'!D:D,"Validade",'2.2. Outros'!F:F,"0") -> 0 | F61: =IFERROR(E61/D61,0) -> 0 | G61: =+COUNTIFS('2.2. Outros'!H:H,$C$55,'2.2. Outros'!D:D,"Validade",'2.2. Outros'!F:F,"<>0",'2.2. Outros'!I:I,"<>") -> 0 | H61: =IFERROR(G61/D61,0) -> 0 | I61: =+COUNTIFS('2.2. Outros'!H:H,$C$55,'2.2. Outros'!D:D,"Validade",'2.2. Outros'!F:F,"<>0",'2.2. Outros'!I:I,"") -> 0 | J61: =IFERROR(I61/D61,0) -> 0
C62: Not applicables | D62: =+COUNTIFS('2.2. Outros'!H:H,$C$55,'2.2. Outros'!D:D,"Not applicable") -> 0 | E62: =+COUNTIFS('2.2. Outros'!H:H,$C$55,'2.2. Outros'!D:D,"Not applicable",'2.2. Outros'!F:F,"0") -> 0 | F62: =IFERROR(E62/D62,0) -> 0 | G62: =+COUNTIFS('2.2. Outros'!H:H,$C$55,'2.2. Outros'!D:D,"Not applicable",'2.2. Outros'!F:F,"<>0",'2.2. Outros'!I:I,"<>") -> 0 | H62: =IFERROR(G62/D62,0) -> 0 | I62: =+COUNTIFS('2.2. Outros'!H:H,$C$55,'2.2. Outros'!D:D,"Not applicable",'2.2. Outros'!F:F,"<>0",'2.2. Outros'!I:I,"") -> 0 | J62: =IFERROR(I62/D62,0) -> 0
C63: Duplicados | D63: =+COUNTIFS('2.2. Outros'!H:H,$C$55,'2.2. Outros'!D:D,"Duplicados") -> 0 | E63: =+COUNTIFS('2.2. Outros'!H:H,$C$55,'2.2. Outros'!D:D,"Duplicados",'2.2. Outros'!F:F,"0") -> 0 | F63: =IFERROR(E63/D63,0) -> 0 | G63: =+COUNTIFS('2.2. Outros'!H:H,$C$55,'2.2. Outros'!D:D,"Duplicados",'2.2. Outros'!F:F,"<>0",'2.2. Outros'!I:I,"<>") -> 0 | H63: =IFERROR(G63/D63,0) -> 0 | I63: =+COUNTIFS('2.2. Outros'!H:H,$C$55,'2.2. Outros'!D:D,"Duplicados",'2.2. Outros'!F:F,"<>0",'2.2. Outros'!I:I,"") -> 0 | J63: =IFERROR(I63/D63,0) -> 0
C64: Integridade entre tabelas | D64: =+COUNTIFS('2.2. Outros'!H:H,$C$55,'2.2. Outros'!D:D,"Integridade") -> 1 | E64: =+COUNTIFS('2.2. Outros'!H:H,$C$55,'2.2. Outros'!D:D,"Integridade",'2.2. Outros'!F:F,"0") -> 1 | F64: =IFERROR(E64/D64,0) -> 1 | G64: =+COUNTIFS('2.2. Outros'!H:H,$C$55,'2.2. Outros'!D:D,"Integridade",'2.2. Outros'!F:F,"<>0",'2.2. Outros'!I:I,"<>") -> 0 | H64: =IFERROR(G64/D64,0) -> 0 | I64: =+COUNTIFS('2.2. Outros'!H:H,$C$55,'2.2. Outros'!D:D,"Integridade",'2.2. Outros'!F:F,"<>0",'2.2. Outros'!I:I,"") -> 0 | J64: =IFERROR(I64/D64,0) -> 0
C65: Total | D65: =SUM(D55,D45,D35) -> 340 | E65: =SUM(E55,E45,E35) -> 288 | F65: =IFERROR(E65/D65,0) -> 0.84705882 | G65: =SUM(G55,G45,G35) -> 12 | H65: =IFERROR(G65/D65,0) -> 0.035294118 | I65: =SUM(I55,I45,I35) -> 35 | J65: =IFERROR(I65/D65,0) -> 0.10294118
C68: 2. Processo (HUE vs CSV)
C70: Mapa | D70: Total (#) | E70: OK (#) | F70: OK (%) | G70: NOK Justificados(#) | H70: NOK Justificados (%) | I70: NOK (#) | J70: NOK (%)
C71: B02.00 | D71: =+D72 -> 20 | E71: =+E72 -> 16 | F71: =+E71/$D71 -> 0.8 | G71: =+G72 -> 3 | H71: =+G71/$D71 -> 0.15 | I71: =+I72 -> 1 | J71: =+I71/$D71 -> 0.05
C72: Coerência(Mapa vs. CSV) | D72: 20 | E72: 16 | F72: =+E72/$D72 -> 0.8 | G72: 3 | H72: =+G72/$D72 -> 0.15 | I72: 1 | J72: =+I72/$D72 -> 0.05
C73: B05.00 | D73: =+D74 -> 15 | E73: =+E74 -> 10 | F73: =+E73/$D73 -> 0.66666667 | G73: =+G74 -> 2 | H73: =+G73/$D73 -> 0.13333333 | I73: =+I74 -> 3 | J73: =+I73/$D73 -> 0.2
C74: Coerência(Mapa vs. CSV) | D74: 15 | E74: 10 | F74: =+E74/$D74 -> 0.66666667 | G74: 2 | H74: =+G74/$D74 -> 0.13333333 | I74: 3 | J74: =+I74/$D74 -> 0.2
C75: B90.00 | D75: =+D76 -> 20 | E75: =+E76 -> 12 | F75: =+E75/$D75 -> 0.6 | G75: =+G76 -> 4 | H75: =+G75/$D75 -> 0.2 | I75: =+I76 -> 4 | J75: =+I75/$D75 -> 0.2
C76: Coerência(Mapa vs. CSV) | D76: 20 | E76: 12 | F76: =+E76/$D76 -> 0.6 | G76: 4 | H76: =+G76/$D76 -> 0.2 | I76: 4 | J76: =+I76/$D76 -> 0.2

Sheet 2. Inputs -->

Sheet 2.1. Regulamentares
B6: 2.1. Controlos Regulamentares
B8: Controlo | C8: Issues | D8: Detalhe | E8: Tipo | F8: High Severity (H)/ Warning (W) | G8: Table | H8: Field | I8: Justificação
B9: b0200_lvl1_h_0010_row_nmbr | C9: 0 | E9: =+MID(B9,7,4) -> lvl1 | F9: =IF(LEFT(E9,3)="lvl",MID(B9,12,1),"f") -> h | G9: =+LEFT(B9,3)&"."&MID(B9,4,2) -> b02.00 | H9: =IF(LEFT(E9,3)="lvl",IF(OR(RIGHT(B9,2)="_1",RIGHT(B9,2)="_2"),MID(B9,14,LEN(B9)-15), MID(B9,14,LEN(B9))),MID(B9,12,LEN(B9))) -> 0010_row_nmbr
B10: b0200_lvl1_h_0030_uniq_id_knwn_cntrprty | C10: 0 | E10: =+MID(B10,7,4) -> lvl1 | F10: =IF(LEFT(E10,3)="lvl",MID(B10,12,1),"f") -> h | G10: =+LEFT(B10,3)&"."&MID(B10,4,2) -> b02.00 | H10: =IF(LEFT(E10,3)="lvl",IF(OR(RIGHT(B10,2)="_1",RIGHT(B10,2)="_2"),MID(B10,14,LEN(B10)-15), MID(B10,14,LEN(B10))),MID(B10,12,LEN(B10))) -> 0030_uniq_id_knwn_cntrprty
B11: b0200_lvl1_h_0040_typ_uniq_id_knwn_cntrprty | C11: 0 | E11: =+MID(B11,7,4) -> lvl1 | F11: =IF(LEFT(E11,3)="lvl",MID(B11,12,1),"f") -> h | G11: =+LEFT(B11,3)&"."&MID(B11,4,2) -> b02.00 | H11: =IF(LEFT(E11,3)="lvl",IF(OR(RIGHT(B11,2)="_1",RIGHT(B11,2)="_2"),MID(B11,14,LEN(B11)-15), MID(B11,14,LEN(B11))),MID(B11,12,LEN(B11))) -> 0040_typ_uniq_id_knwn_cntrprty
B12: b0200_lvl1_h_0070_cntrct_crrncy | C12: 0 | E12: =+MID(B12,7,4) -> lvl1 | F12: =IF(LEFT(E12,3)="lvl",MID(B12,12,1),"f") -> h | G12: =+LEFT(B12,3)&"."&MID(B12,4,2) -> b02.00 | H12: =IF(LEFT(E12,3)="lvl",IF(OR(RIGHT(B12,2)="_1",RIGHT(B12,2)="_2"),MID(B12,14,LEN(B12)-15), MID(B12,14,LEN(B12))),MID(B12,12,LEN(B12))) -> 0070_cntrct_crrncy
B13: b0200_lvl1_h_0080_otstndng_prncpl_amnt | C13: 0 | E13: =+MID(B13,7,4) -> lvl1 | F13: =IF(LEFT(E13,3)="lvl",MID(B13,12,1),"f") -> h | G13: =+LEFT(B13,3)&"."&MID(B13,4,2) -> b02.00 | H13: =IF(LEFT(E13,3)="lvl",IF(OR(RIGHT(B13,2)="_1",RIGHT(B13,2)="_2"),MID(B13,14,LEN(B13)-15), MID(B13,14,LEN(B13))),MID(B13,12,LEN(B13))) -> 0080_otstndng_prncpl_amnt
B14: b0200_lvl1_w_0080_otstndng_prncpl_amnt | C14: 0 | E14: =+MID(B14,7,4) -> lvl1 | F14: =IF(LEFT(E14,3)="lvl",MID(B14,12,1),"f") -> w | G14: =+LEFT(B14,3)&"."&MID(B14,4,2) -> b02.00 | H14: =IF(LEFT(E14,3)="lvl",IF(OR(RIGHT(B14,2)="_1",RIGHT(B14,2)="_2"),MID(B14,14,LEN(B14)-15), MID(B14,14,LEN(B14))),MID(B14,12,LEN(B14))) -> 0080_otstndng_prncpl_amnt
B15: b0200_lvl1_h_0090_prtn_amnt_rprtng_entty | C15: 0 | E15: =+MID(B15,7,4) -> lvl1 | F15: =IF(LEFT(E15,3)="lvl",MID(B15,12,1),"f") -> h | G15: =+LEFT(B15,3)&"."&MID(B15,4,2) -> b02.00 | H15: =IF(LEFT(E15,3)="lvl",IF(OR(RIGHT(B15,2)="_1",RIGHT(B15,2)="_2"),MID(B15,14,LEN(B15)-15), MID(B15,14,LEN(B15))),MID(B15,12,LEN(B15))) -> 0090_prtn_amnt_rprtng_entty
B16: b0200_lvl1_h_0100_accrd_intrst_instrmnt | C16: 0 | E16: =+MID(B16,7,4) -> lvl1 | F16: =IF(LEFT(E16,3)="lvl",MID(B16,12,1),"f") -> h | G16: =+LEFT(B16,3)&"."&MID(B16,4,2) -> b02.00 | H16: =IF(LEFT(E16,3)="lvl",IF(OR(RIGHT(B16,2)="_1",RIGHT(B16,2)="_2"),MID(B16,14,LEN(B16)-15), MID(B16,14,LEN(B16))),MID(B16,12,LEN(B16))) -> 0100_accrd_intrst_instrmnt
B17: b0200_lvl1_w_0100_accrd_intrst_instrmnt | C17: 0 | E17: =+MID(B17,7,4) -> lvl1 | F17: =IF(LEFT(E17,3)="lvl",MID(B17,12,1),"f") -> w | G17: =+LEFT(B17,3)&"."&MID(B17,4,2) -> b02.00 | H17: =IF(LEFT(E17,3)="lvl",IF(OR(RIGHT(B17,2)="_1",RIGHT(B17,2)="_2"),MID(B17,14,LEN(B17)-15), MID(B17,14,LEN(B17))),MID(B17,12,LEN(B17))) -> 0100_accrd_intrst_instrmnt
B18: b0200_lvl1_h_0120_otstndng_amnt | C18: 0 | E18: =+MID(B18,7,4) -> lvl1 | F18: =IF(LEFT(E18,3)="lvl",MID(B18,12,1),"f") -> h | G18: =+LEFT(B18,3)&"."&MID(B18,4,2) -> b02.00 | H18: =IF(LEFT(E18,3)="lvl",IF(OR(RIGHT(B18,2)="_1",RIGHT(B18,2)="_2"),MID(B18,14,LEN(B18)-15), MID(B18,14,LEN(B18))),MID(B18,12,LEN(B18))) -> 0120_otstndng_amnt
B19: b0200_lvl1_w_0120_otstndng_amnt | C19: 8 | E19: =+MID(B19,7,4) -> lvl1 | F19: =IF(LEFT(E19,3)="lvl",MID(B19,12,1),"f") -> w | G19: =+LEFT(B19,3)&"."&MID(B19,4,2) -> b02.00 | H19: =IF(LEFT(E19,3)="lvl",IF(OR(RIGHT(B19,2)="_1",RIGHT(B19,2)="_2"),MID(B19,14,LEN(B19)-15), MID(B19,14,LEN(B19))),MID(B19,12,LEN(B19))) -> 0120_otstndng_amnt
B20: b0200_lvl1_h_0130_rlvnt_amnt_wdc | C20: 8 | E20: =+MID(B20,7,4) -> lvl1 | F20: =IF(LEFT(E20,3)="lvl",MID(B20,12,1),"f") -> h | G20: =+LEFT(B20,3)&"."&MID(B20,4,2) -> b02.00 | H20: =IF(LEFT(E20,3)="lvl",IF(OR(RIGHT(B20,2)="_1",RIGHT(B20,2)="_2"),MID(B20,14,LEN(B20)-15), MID(B20,14,LEN(B20))),MID(B20,12,LEN(B20))) -> 0130_rlvnt_amnt_wdc
... B97: b0200_frmt_0140_ntr_lblty | C97: 4 | E97: =+MID(B97,7,4) -> frmt | F97: =IF(LEFT(E97,3)="lvl",MID(B97,12,1),"f") -> f | G97: =+LEFT(B97,3)&"."&MID(B97,4,2) -> b02.00 | H97: =IF(LEFT(E97,3)="lvl",IF(OR(RIGHT(B97,2)="_1",RIGHT(B97,2)="_2"),MID(B97,14,LEN(B97)-15), MID(B97,14,LEN(B97))),MID(B97,12,LEN(B97))) -> 0140_ntr_lblty
B98: b0200_frmt_0141_ntr_lblty_othr | C98: 8 | E98: =+MID(B98,7,4) -> frmt | F98: =IF(LEFT(E98,3)="lvl",MID(B98,12,1),"f") -> f | G98: =+LEFT(B98,3)&"."&MID(B98,4,2) -> b02.00 | H98: =IF(LEFT(E98,3)="lvl",IF(OR(RIGHT(B98,2)="_1",RIGHT(B98,2)="_2"),MID(B98,14,LEN(B98)-15), MID(B98,14,LEN(B98))),MID(B98,12,LEN(B98))) -> 0141_ntr_lblty_othr | I98: Valor fixo 'Not applicable' no campo Nature of the liability (if other), uma vez que todos os registos são considerados no campo Nature of the liability como "Title of ownership" ou "Registered Bond", não existinto "other".
B99: b0200_frmt_0150_flg_strctrlly_sbrdntd | C99: 8 | E99: =+MID(B99,7,4) -> frmt | F99: =IF(LEFT(E99,3)="lvl",MID(B99,12,1),"f") -> f | G99: =+LEFT(B99,3)&"."&MID(B99,4,2) -> b02.00 | H99: =IF(LEFT(E99,3)="lvl",IF(OR(RIGHT(B99,2)="_1",RIGHT(B99,2)="_2"),MID(B99,14,LEN(B99)-15), MID(B99,14,LEN(B99))),MID(B99,12,LEN(B99))) -> 0150_flg_strctrlly_sbrdntd | I99: Valor fixo 'Not applicable' de acordo com o Anexo III - considerado não aplicável para non-resolution entities.
B100: b0200_frmt_0160_rank_insolv | C100: 0 | E100: =+MID(B100,7,4) -> frmt | F100: =IF(LEFT(E100,3)="lvl",MID(B100,12,1),"f") -> f | G100: =+LEFT(B100,3)&"."&MID(B100,4,2) -> b02.00 | H100: =IF(LEFT(E100,3)="lvl",IF(OR(RIGHT(B100,2)="_1",RIGHT(B100,2)="_2"),MID(B100,14,LEN(B100)-15), MID(B100,14,LEN(B100))),MID(B100,12,LEN(B100))) -> 0160_rank_insolv
B101: b0200_frmt_0161_cntrctl_sbrdntn | C101: 0 | E101: =+MID(B101,7,4) -> frmt | F101: =IF(LEFT(E101,3)="lvl",MID(B101,12,1),"f") -> f | G101: =+LEFT(B101,3)&"."&MID(B101,4,2) -> b02.00 | H101: =IF(LEFT(E101,3)="lvl",IF(OR(RIGHT(B101,2)="_1",RIGHT(B101,2)="_2"),MID(B101,14,LEN(B101)-15), MID(B101,14,LEN(B101))),MID(B101,12,LEN(B101))) -> 0161_cntrctl_sbrdntn
B102: b0200_frmt_0162_bail_in_cascade | C102: 0 | E102: =+MID(B102,7,4) -> frmt | F102: =IF(LEFT(E102,3)="lvl",MID(B102,12,1),"f") -> f | G102: =+LEFT(B102,3)&"."&MID(B102,4,2) -> b02.00 | H102: =IF(LEFT(E102,3)="lvl",IF(OR(RIGHT(B102,2)="_1",RIGHT(B102,2)="_2"),MID(B102,14,LEN(B102)-15), MID(B102,14,LEN(B102))),MID(B102,12,LEN(B102))) -> 0162_bail_in_cascade
B103: b0200_frmt_0170_dt_incptn | C103: 0 | E103: =+MID(B103,7,4) -> frmt | F103: =IF(LEFT(E103,3)="lvl",MID(B103,12,1),"f") -> f | G103: =+LEFT(B103,3)&"."&MID(B103,4,2) -> b02.00 | H103: =IF(LEFT(E103,3)="lvl",IF(OR(RIGHT(B103,2)="_1",RIGHT(B103,2)="_2"),MID(B103,14,LEN(B103)-15), MID(B103,14,LEN(B103))),MID(B103,12,LEN(B103))) -> 0170_dt_incptn
B104: b0200_frmt_0180_dt_nxt_intrst_pymnt | C104: 8 | E104: =+MID(B104,7,4) -> frmt | F104: =IF(LEFT(E104,3)="lvl",MID(B104,12,1),"f") -> f | G104: =+LEFT(B104,3)&"."&MID(B104,4,2) -> b02.00 | H104: =IF(LEFT(E104,3)="lvl",IF(OR(RIGHT(B104,2)="_1",RIGHT(B104,2)="_2"),MID(B104,14,LEN(B104)-15), MID(B104,14,LEN(B104))),MID(B104,12,LEN(B104))) -> 0180_dt_nxt_intrst_pymnt
B105: b0200_frmt_0190_dt_nxt_rdmptn_pymnt | C105: 0 | E105: =+MID(B105,7,4) -> frmt | F105: =IF(LEFT(E105,3)="lvl",MID(B105,12,1),"f") -> f | G105: =+LEFT(B105,3)&"."&MID(B105,4,2) -> b02.00 | H105: =IF(LEFT(E105,3)="lvl",IF(OR(RIGHT(B105,2)="_1",RIGHT(B105,2)="_2"),MID(B105,14,LEN(B105)-15), MID(B105,14,LEN(B105))),MID(B105,12,LEN(B105))) -> 0190_dt_nxt_rdmptn_pymnt
B106: b0200_frmt_0200_dt_erlst_rdmptn | C106: 0 | E106: =+MID(B106,7,4) -> frmt | F106: =IF(LEFT(E106,3)="lvl",MID(B106,12,1),"f") -> f | G106: =+LEFT(B106,3)&"."&MID(B106,4,2) -> b02.00 | H106: =IF(LEFT(E106,3)="lvl",IF(OR(RIGHT(B106,2)="_1",RIGHT(B106,2)="_2"),MID(B106,14,LEN(B106)-15), MID(B106,14,LEN(B106))),MID(B106,12,LEN(B106))) -> 0200_dt_erlst_rdmptn
B107: b0200_frmt_0210_dt_lgl_fnl_mtrty | C107: 0 | E107: =+MID(B107,7,4) -> frmt | F107: =IF(LEFT(E107,3)="lvl",MID(B107,12,1),"f") -> f | G107: =+LEFT(B107,3)&"."&MID(B107,4,2) -> b02.00 | H107: =IF(LEFT(E107,3)="lvl",IF(OR(RIGHT(B107,2)="_1",RIGHT(B107,2)="_2"),MID(B107,14,LEN(B107)-15), MID(B107,14,LEN(B107))),MID(B107,12,LEN(B107))) -> 0210_dt_lgl_fnl_mtrty
B108: b0200_frmt_0220_governing_law | C108: 0 | E108: =+MID(B108,7,4) -> frmt | F108: =IF(LEFT(E108,3)="lvl",MID(B108,12,1),"f") -> f | G108: =+LEFT(B108,3)&"."&MID(B108,4,2) -> b02.00 | H108: =IF(LEFT(E108,3)="lvl",IF(OR(RIGHT(B108,2)="_1",RIGHT(B108,2)="_2"),MID(B108,14,LEN(B108)-15), MID(B108,14,LEN(B108))),MID(B108,12,LEN(B108))) -> 0220_governing_law
B109: b0200_frmt_0230_bail_in_rcgntn_cls | C109: 0 | E109: =+MID(B109,7,4) -> frmt | F109: =IF(LEFT(E109,3)="lvl",MID(B109,12,1),"f") -> f | G109: =+LEFT(B109,3)&"."&MID(B109,4,2) -> b02.00 | H109: =IF(LEFT(E109,3)="lvl",IF(OR(RIGHT(B109,2)="_1",RIGHT(B109,2)="_2"),MID(B109,14,LEN(B109)-15), MID(B109,14,LEN(B109))),MID(B109,12,LEN(B109))) -> 0230_bail_in_rcgntn_cls
B110: b0200_frmt_0240_zero_coupon | C110: 0 | E110: =+MID(B110,7,4) -> frmt | F110: =IF(LEFT(E110,3)="lvl",MID(B110,12,1),"f") -> f | G110: =+LEFT(B110,3)&"."&MID(B110,4,2) -> b02.00 | H110: =IF(LEFT(E110,3)="lvl",IF(OR(RIGHT(B110,2)="_1",RIGHT(B110,2)="_2"),MID(B110,14,LEN(B110)-15), MID(B110,14,LEN(B110))),MID(B110,12,LEN(B110))) -> 0240_zero_coupon
B111: b0200_frmt_0250_strctrd_prdct | C111: 0 | E111: =+MID(B111,7,4) -> frmt | F111: =IF(LEFT(E111,3)="lvl",MID(B111,12,1),"f") -> f | G111: =+LEFT(B111,3)&"."&MID(B111,4,2) -> b02.00 | H111: =IF(LEFT(E111,3)="lvl",IF(OR(RIGHT(B111,2)="_1",RIGHT(B111,2)="_2"),MID(B111,14,LEN(B111)-15), MID(B111,14,LEN(B111))),MID(B111,12,LEN(B111))) -> 0250_strctrd_prdct
... B119: b0200_frmt_0330_amnt_unclltrlzd | C119: 0 | E119: =+MID(B119,7,4) -> frmt | F119: =IF(LEFT(E119,3)="lvl",MID(B119,12,1),"f") -> f | G119: =+LEFT(B119,3)&"."&MID(B119,4,2) -> b02.00 | H119: =IF(LEFT(E119,3)="lvl",IF(OR(RIGHT(B119,2)="_1",RIGHT(B119,2)="_2"),MID(B119,14,LEN(B119)-15), MID(B119,14,LEN(B119))),MID(B119,12,LEN(B119))) -> 0330_amnt_unclltrlzd
B120: b0200_frmt_0340_id_clltrl | C120: 8 | E120: =+MID(B120,7,4) -> frmt | F120: =IF(LEFT(E120,3)="lvl",MID(B120,12,1),"f") -> f | G120: =+LEFT(B120,3)&"."&MID(B120,4,2) -> b02.00 | H120: =IF(LEFT(E120,3)="lvl",IF(OR(RIGHT(B120,2)="_1",RIGHT(B120,2)="_2"),MID(B120,14,LEN(B120)-15), MID(B120,14,LEN(B120))),MID(B120,12,LEN(B120))) -> 0340_id_clltrl | I120: Valor fixo 'Not applicable' de acordo com o Anexo III - considerado não aplicável para non-resolution entities.
B121: b0200_frmt_0350_typ_clltrl | C121: 0 | E121: =+MID(B121,7,4) -> frmt | F121: =IF(LEFT(E121,3)="lvl",MID(B121,12,1),"f") -> f | G121: =+LEFT(B121,3)&"."&MID(B121,4,2) -> b02.00 | H121: =IF(LEFT(E121,3)="lvl",IF(OR(RIGHT(B121,2)="_1",RIGHT(B121,2)="_2"),MID(B121,14,LEN(B121)-15), MID(B121,14,LEN(B121))),MID(B121,12,LEN(B121))) -> 0350_typ_clltrl
B122: b0200_frmt_0351_typ_clltrl_othr | C122: 8 | E122: =+MID(B122,7,4) -> frmt | F122: =IF(LEFT(E122,3)="lvl",MID(B122,12,1),"f") -> f | G122: =+LEFT(B122,3)&"."&MID(B122,4,2) -> b02.00 | H122: =IF(LEFT(E122,3)="lvl",IF(OR(RIGHT(B122,2)="_1",RIGHT(B122,2)="_2"),MID(B122,14,LEN(B122)-15), MID(B122,14,LEN(B122))),MID(B122,12,LEN(B122))) -> 0351_typ_clltrl_othr | I122: Valor fixo 'Not applicable' de acordo com o Anexo III - considerado não aplicável para non-resolution entities.
B123: b0200_frmt_0360_trdng_mthd | C123: 0 | E123: =+MID(B123,7,4) -> frmt | F123: =IF(LEFT(E123,3)="lvl",MID(B123,12,1),"f") -> f | G123: =+LEFT(B123,3)&"."&MID(B123,4,2) -> b02.00 | H123: =IF(LEFT(E123,3)="lvl",IF(OR(RIGHT(B123,2)="_1",RIGHT(B123,2)="_2"),MID(B123,14,LEN(B123)-15), MID(B123,14,LEN(B123))),MID(B123,12,LEN(B123))) -> 0360_trdng_mthd
B124: b0200_frmt_0370_amnt_scrty_eur | C124: 0 | E124: =+MID(B124,7,4) -> frmt | F124: =IF(LEFT(E124,3)="lvl",MID(B124,12,1),"f") -> f | G124: =+LEFT(B124,3)&"."&MID(B124,4,2) -> b02.00 | H124: =IF(LEFT(E124,3)="lvl",IF(OR(RIGHT(B124,2)="_1",RIGHT(B124,2)="_2"),MID(B124,14,LEN(B124)-15), MID(B124,14,LEN(B124))),MID(B124,12,LEN(B124))) -> 0370_amnt_scrty_eur
B125: b0200_frmt_0380_amnt_scrty_fx | C125: 0 | E125: =+MID(B125,7,4) -> frmt | F125: =IF(LEFT(E125,3)="lvl",MID(B125,12,1),"f") -> f | G125: =+LEFT(B125,3)&"."&MID(B125,4,2) -> b02.00 | H125: =IF(LEFT(E125,3)="lvl",IF(OR(RIGHT(B125,2)="_1",RIGHT(B125,2)="_2"),MID(B125,14,LEN(B125)-15), MID(B125,14,LEN(B125))),MID(B125,12,LEN(B125))) -> 0380_amnt_scrty_fx
B126: b0200_frmt_0390_nmbr_scrts_not_rprtng_entty | C126: 0 | E126: =+MID(B126,7,4) -> frmt | F126: =IF(LEFT(E126,3)="lvl",MID(B126,12,1),"f") -> f | G126: =+LEFT(B126,3)&"."&MID(B126,4,2) -> b02.00 | H126: =IF(LEFT(E126,3)="lvl",IF(OR(RIGHT(B126,2)="_1",RIGHT(B126,2)="_2"),MID(B126,14,LEN(B126)-15), MID(B126,14,LEN(B126))),MID(B126,12,LEN(B126))) -> 0390_nmbr_scrts_not_rprtng_entty
B127: b0200_frmt_0391_nmbr_scrts_rprtng_entty | C127: 8 | E127: =+MID(B127,7,4) -> frmt | F127: =IF(LEFT(E127,3)="lvl",MID(B127,12,1),"f") -> f | G127: =+LEFT(B127,3)&"."&MID(B127,4,2) -> b02.00 | H127: =IF(LEFT(E127,3)="lvl",IF(OR(RIGHT(B127,2)="_1",RIGHT(B127,2)="_2"),MID(B127,14,LEN(B127)-15), MID(B127,14,LEN(B127))),MID(B127,12,LEN(B127))) -> 0391_nmbr_scrts_rprtng_entty
B128: b0200_frmt_0400_accrd_intrst_scrty | C128: 0 | E128: =+MID(B128,7,4) -> frmt | F128: =IF(LEFT(E128,3)="lvl",MID(B128,12,1),"f") -> f | G128: =+LEFT(B128,3)&"."&MID(B128,4,2) -> b02.00 | H128: =IF(LEFT(E128,3)="lvl",IF(OR(RIGHT(B128,2)="_1",RIGHT(B128,2)="_2"),MID(B128,14,LEN(B128)-15), MID(B128,14,LEN(B128))),MID(B128,12,LEN(B128))) -> 0400_accrd_intrst_scrty
B129: b0200_frmt_0410_fees_charges_scrty | C129: 0 | E129: =+MID(B129,7,4) -> frmt | F129: =IF(LEFT(E129,3)="lvl",MID(B129,12,1),"f") -> f | G129: =+LEFT(B129,3)&"."&MID(B129,4,2) -> b02.00 | H129: =IF(LEFT(E129,3)="lvl",IF(OR(RIGHT(B129,2)="_1",RIGHT(B129,2)="_2"),MID(B129,14,LEN(B129)-15), MID(B129,14,LEN(B129))),MID(B129,12,LEN(B129))) -> 0410_fees_charges_scrty
B130: b0200_frmt_0420_fv_amnt_scrty | C130: 0 | E130: =+MID(B130,7,4) -> frmt | F130: =IF(LEFT(E130,3)="lvl",MID(B130,12,1),"f") -> f | G130: =+LEFT(B130,3)&"."&MID(B130,4,2) -> b02.00 | H130: =IF(LEFT(E130,3)="lvl",IF(OR(RIGHT(B130,2)="_1",RIGHT(B130,2)="_2"),MID(B130,14,LEN(B130)-15), MID(B130,14,LEN(B130))),MID(B130,12,LEN(B130))) -> 0420_fv_amnt_scrty
B131: b0200_frmt_0430_prncpl_amnt_glbl_nt_eur | C131: 0 | E131: =+MID(B131,7,4) -> frmt | F131: =IF(LEFT(E131,3)="lvl",MID(B131,12,1),"f") -> f | G131: =+LEFT(B131,3)&"."&MID(B131,4,2) -> b02.00 | H131: =IF(LEFT(E131,3)="lvl",IF(OR(RIGHT(B131,2)="_1",RIGHT(B131,2)="_2"),MID(B131,14,LEN(B131)-15), MID(B131,14,LEN(B131))),MID(B131,12,LEN(B131))) -> 0430_prncpl_amnt_glbl_nt_eur
B132: b0200_frmt_0431_prncpl_amnt_glbl_nt_fx | C132: 0 | E132: =+MID(B132,7,4) -> frmt | F132: =IF(LEFT(E132,3)="lvl",MID(B132,12,1),"f") -> f | G132: =+LEFT(B132,3)&"."&MID(B132,4,2) -> b02.00 | H132: =IF(LEFT(E132,3)="lvl",IF(OR(RIGHT(B132,2)="_1",RIGHT(B132,2)="_2"),MID(B132,14,LEN(B132)-15), MID(B132,14,LEN(B132))),MID(B132,12,LEN(B132))) -> 0431_prncpl_amnt_glbl_nt_fx
B133: b0200_frmt_0440_ntr_glbl_nt | C133: 0 | E133: =+MID(B133,7,4) -> frmt | F133: =IF(LEFT(E133,3)="lvl",MID(B133,12,1),"f") -> f | G133: =+LEFT(B133,3)&"."&MID(B133,4,2) -> b02.00 | H133: =IF(LEFT(E133,3)="lvl",IF(OR(RIGHT(B133,2)="_1",RIGHT(B133,2)="_2"),MID(B133,14,LEN(B133)-15), MID(B133,14,LEN(B133))),MID(B133,12,LEN(B133))) -> 0440_ntr_glbl_nt
B134: b0200_frmt_0450_crrnt_pool_fctr | C134: 0 | E134: =+MID(B134,7,4) -> frmt | F134: =IF(LEFT(E134,3)="lvl",MID(B134,12,1),"f") -> f | G134: =+LEFT(B134,3)&"."&MID(B134,4,2) -> b02.00 | H134: =IF(LEFT(E134,3)="lvl",IF(OR(RIGHT(B134,2)="_1",RIGHT(B134,2)="_2"),MID(B134,14,LEN(B134)-15), MID(B134,14,LEN(B134))),MID(B134,12,LEN(B134))) -> 0450_crrnt_pool_fctr
... B136: b0200_frmt_0461_csd_lei | C136: 0 | E136: =+MID(B136,7,4) -> frmt | F136: =IF(LEFT(E136,3)="lvl",MID(B136,12,1),"f") -> f | G136: =+LEFT(B136,3)&"."&MID(B136,4,2) -> b02.00 | H136: =IF(LEFT(E136,3)="lvl",IF(OR(RIGHT(B136,2)="_1",RIGHT(B136,2)="_2"),MID(B136,14,LEN(B136)-15), MID(B136,14,LEN(B136))),MID(B136,12,LEN(B136))) -> 0461_csd_lei
B137: b0200_frmt_0462_csd_othr | C137: 8 | E137: =+MID(B137,7,4) -> frmt | F137: =IF(LEFT(E137,3)="lvl",MID(B137,12,1),"f") -> f | G137: =+LEFT(B137,3)&"."&MID(B137,4,2) -> b02.00 | H137: =IF(LEFT(E137,3)="lvl",IF(OR(RIGHT(B137,2)="_1",RIGHT(B137,2)="_2"),MID(B137,14,LEN(B137)-15), MID(B137,14,LEN(B137))),MID(B137,12,LEN(B137))) -> 0462_csd_othr | I137: Valor fixo 'Not applicable' no campo Central securities depository name (if other), uma vez que todos os registos são considerados no campo Central securities depository name como "INTERBOLSA_PT", não existinto "other".
B138: b0200_frmt_0470_pyng_agnt | C138: 0 | E138: =+MID(B138,7,4) -> frmt | F138: =IF(LEFT(E138,3)="lvl",MID(B138,12,1),"f") -> f | G138: =+LEFT(B138,3)&"."&MID(B138,4,2) -> b02.00 | H138: =IF(LEFT(E138,3)="lvl",IF(OR(RIGHT(B138,2)="_1",RIGHT(B138,2)="_2"),MID(B138,14,LEN(B138)-15), MID(B138,14,LEN(B138))),MID(B138,12,LEN(B138))) -> 0470_pyng_agnt
B139: b0200_frmt_0471_pyng_agnt_lei | C139: 0 | E139: =+MID(B139,7,4) -> frmt | F139: =IF(LEFT(E139,3)="lvl",MID(B139,12,1),"f") -> f | G139: =+LEFT(B139,3)&"."&MID(B139,4,2) -> b02.00 | H139: =IF(LEFT(E139,3)="lvl",IF(OR(RIGHT(B139,2)="_1",RIGHT(B139,2)="_2"),MID(B139,14,LEN(B139)-15), MID(B139,14,LEN(B139))),MID(B139,12,LEN(B139))) -> 0471_pyng_agnt_lei
B140: b0200_frmt_0480_trdng_vn | C140: 0 | E140: =+MID(B140,7,4) -> frmt | F140: =IF(LEFT(E140,3)="lvl",MID(B140,12,1),"f") -> f | G140: =+LEFT(B140,3)&"."&MID(B140,4,2) -> b02.00 | H140: =IF(LEFT(E140,3)="lvl",IF(OR(RIGHT(B140,2)="_1",RIGHT(B140,2)="_2"),MID(B140,14,LEN(B140)-15), MID(B140,14,LEN(B140))),MID(B140,12,LEN(B140))) -> 0480_trdng_vn
B141: b0200_frmt_0481_trdng_vn_lei | C141: 0 | E141: =+MID(B141,7,4) -> frmt | F141: =IF(LEFT(E141,3)="lvl",MID(B141,12,1),"f") -> f | G141: =+LEFT(B141,3)&"."&MID(B141,4,2) -> b02.00 | H141: =IF(LEFT(E141,3)="lvl",IF(OR(RIGHT(B141,2)="_1",RIGHT(B141,2)="_2"),MID(B141,14,LEN(B141)-15), MID(B141,14,LEN(B141))),MID(B141,12,LEN(B141))) -> 0481_trdng_vn_lei
B142: b0200_frmt_0490_rgstrr | C142: 0 | E142: =+MID(B142,7,4) -> frmt | F142: =IF(LEFT(E142,3)="lvl",MID(B142,12,1),"f") -> f | G142: =+LEFT(B142,3)&"."&MID(B142,4,2) -> b02.00 | H142: =IF(LEFT(E142,3)="lvl",IF(OR(RIGHT(B142,2)="_1",RIGHT(B142,2)="_2"),MID(B142,14,LEN(B142)-15), MID(B142,14,LEN(B142))),MID(B142,12,LEN(B142))) -> 0490_rgstrr
B143: b0200_frmt_0491_rgstrr_lei | C143: 0 | E143: =+MID(B143,7,4) -> frmt | F143: =IF(LEFT(E143,3)="lvl",MID(B143,12,1),"f") -> f | G143: =+LEFT(B143,3)&"."&MID(B143,4,2) -> b02.00 | H143: =IF(LEFT(E143,3)="lvl",IF(OR(RIGHT(B143,2)="_1",RIGHT(B143,2)="_2"),MID(B143,14,LEN(B143)-15), MID(B143,14,LEN(B143))),MID(B143,12,LEN(B143))) -> 0491_rgstrr_lei
B144: b0200_frmt_0500_nna | C144: 0 | E144: =+MID(B144,7,4) -> frmt | F144: =IF(LEFT(E144,3)="lvl",MID(B144,12,1),"f") -> f | G144: =+LEFT(B144,3)&"."&MID(B144,4,2) -> b02.00 | H144: =IF(LEFT(E144,3)="lvl",IF(OR(RIGHT(B144,2)="_1",RIGHT(B144,2)="_2"),MID(B144,14,LEN(B144)-15), MID(B144,14,LEN(B144))),MID(B144,12,LEN(B144))) -> 0500_nna
B145: b0200_frmt_0501_nna_lei | C145: 0 | E145: =+MID(B145,7,4) -> frmt | F145: =IF(LEFT(E145,3)="lvl",MID(B145,12,1),"f") -> f | G145: =+LEFT(B145,3)&"."&MID(B145,4,2) -> b02.00 | H145: =IF(LEFT(E145,3)="lvl",IF(OR(RIGHT(B145,2)="_1",RIGHT(B145,2)="_2"),MID(B145,14,LEN(B145)-15), MID(B145,14,LEN(B145))),MID(B145,12,LEN(B145))) -> 0501_nna_lei
B146: b0200_frmt_0510_cmmn_dpstry | C146: 0 | E146: =+MID(B146,7,4) -> frmt | F146: =IF(LEFT(E146,3)="lvl",MID(B146,12,1),"f") -> f | G146: =+LEFT(B146,3)&"."&MID(B146,4,2) -> b02.00 | H146: =IF(LEFT(E146,3)="lvl",IF(OR(RIGHT(B146,2)="_1",RIGHT(B146,2)="_2"),MID(B146,14,LEN(B146)-15), MID(B146,14,LEN(B146))),MID(B146,12,LEN(B146))) -> 0510_cmmn_dpstry
B147: b0200_frmt_0511_cmmn_dpstry_lei | C147: 0 | E147: =+MID(B147,7,4) -> frmt | F147: =IF(LEFT(E147,3)="lvl",MID(B147,12,1),"f") -> f | G147: =+LEFT(B147,3)&"."&MID(B147,4,2) -> b02.00 | H147: =IF(LEFT(E147,3)="lvl",IF(OR(RIGHT(B147,2)="_1",RIGHT(B147,2)="_2"),MID(B147,14,LEN(B147)-15), MID(B147,14,LEN(B147))),MID(B147,12,LEN(B147))) -> 0511_cmmn_dpstry_lei
B148: b0200_frmt_0520_cmmn_srvc_prvdr | C148: 0 | E148: =+MID(B148,7,4) -> frmt | F148: =IF(LEFT(E148,3)="lvl",MID(B148,12,1),"f") -> f | G148: =+LEFT(B148,3)&"."&MID(B148,4,2) -> b02.00 | H148: =IF(LEFT(E148,3)="lvl",IF(OR(RIGHT(B148,2)="_1",RIGHT(B148,2)="_2"),MID(B148,14,LEN(B148)-15), MID(B148,14,LEN(B148))),MID(B148,12,LEN(B148))) -> 0520_cmmn_srvc_prvdr
B149: b0200_frmt_0521_cmmn_srvc_prvdr_lei | C149: 0 | E149: =+MID(B149,7,4) -> frmt | F149: =IF(LEFT(E149,3)="lvl",MID(B149,12,1),"f") -> f | G149: =+LEFT(B149,3)&"."&MID(B149,4,2) -> b02.00 | H149: =IF(LEFT(E149,3)="lvl",IF(OR(RIGHT(B149,2)="_1",RIGHT(B149,2)="_2"),MID(B149,14,LEN(B149)-15), MID(B149,14,LEN(B149))),MID(B149,12,LEN(B149))) -> 0521_cmmn_srvc_prvdr_lei
... B161: b0200_frmt_0630_crrying_amnt_ngaap | C161: 0 | E161: =+MID(B161,7,4) -> frmt | F161: =IF(LEFT(E161,3)="lvl",MID(B161,12,1),"f") -> f | G161: =+LEFT(B161,3)&"."&MID(B161,4,2) -> b02.00 | H161: =IF(LEFT(E161,3)="lvl",IF(OR(RIGHT(B161,2)="_1",RIGHT(B161,2)="_2"),MID(B161,14,LEN(B161)-15), MID(B161,14,LEN(B161))),MID(B161,12,LEN(B161))) -> 0630_crrying_amnt_ngaap
B162: b0200_frmt_0640_blnc_sht_ngaap | C162: 8 | E162: =+MID(B162,7,4) -> frmt | F162: =IF(LEFT(E162,3)="lvl",MID(B162,12,1),"f") -> f | G162: =+LEFT(B162,3)&"."&MID(B162,4,2) -> b02.00 | H162: =IF(LEFT(E162,3)="lvl",IF(OR(RIGHT(B162,2)="_1",RIGHT(B162,2)="_2"),MID(B162,14,LEN(B162)-15), MID(B162,14,LEN(B162))),MID(B162,12,LEN(B162))) -> 0640_blnc_sht_ngaap | I162: Valor fixo 'Not applicable' no campo Balance sheet item at Resolution entity level according to national GAAP, uma vez que o BST é uma non-resolution entity e no caso de Portugal, usa-se o IFRS e não o national GAAP.
B163: b0200_frmt_5000_flg_shrhldr_not_rsltn_grp | C163: 0 | E163: =+MID(B163,7,4) -> frmt | F163: =IF(LEFT(E163,3)="lvl",MID(B163,12,1),"f") -> f | G163: =+LEFT(B163,3)&"."&MID(B163,4,2) -> b02.00 | H163: =IF(LEFT(E163,3)="lvl",IF(OR(RIGHT(B163,2)="_1",RIGHT(B163,2)="_2"),MID(B163,14,LEN(B163)-15), MID(B163,14,LEN(B163))),MID(B163,12,LEN(B163))) -> 5000_flg_shrhldr_not_rsltn_grp
B164: b0200_frmt_5010_flg_art21_7a_srmr | C164: 0 | E164: =+MID(B164,7,4) -> frmt | F164: =IF(LEFT(E164,3)="lvl",MID(B164,12,1),"f") -> f | G164: =+LEFT(B164,3)&"."&MID(B164,4,2) -> b02.00 | H164: =IF(LEFT(E164,3)="lvl",IF(OR(RIGHT(B164,2)="_1",RIGHT(B164,2)="_2"),MID(B164,14,LEN(B164)-15), MID(B164,14,LEN(B164))),MID(B164,12,LEN(B164))) -> 5010_flg_art21_7a_srmr
B165: b0500_lvl2_h_0030_governing_law | C165: 0 | E165: =+MID(B165,7,4) -> lvl2 | F165: =IF(LEFT(E165,3)="lvl",MID(B165,12,1),"f") -> h | G165: =+LEFT(B165,3)&"."&MID(B165,4,2) -> b05.00 | H165: =IF(LEFT(E165,3)="lvl",IF(OR(RIGHT(B165,2)="_1",RIGHT(B165,2)="_2"),MID(B165,14,LEN(B165)-15), MID(B165,14,LEN(B165))),MID(B165,12,LEN(B165))) -> 0030_governing_law
B166: b0500_lvl2_h_0050_typ_guarantee | C166: 0 | E166: =+MID(B166,7,4) -> lvl2 | F166: =IF(LEFT(E166,3)="lvl",MID(B166,12,1),"f") -> h | G166: =+LEFT(B166,3)&"."&MID(B166,4,2) -> b05.00 | H166: =IF(LEFT(E166,3)="lvl",IF(OR(RIGHT(B166,2)="_1",RIGHT(B166,2)="_2"),MID(B166,14,LEN(B166)-15), MID(B166,14,LEN(B166))),MID(B166,12,LEN(B166))) -> 0050_typ_guarantee
B167: b0500_lvl2_h_0060_max_amnt_guarantee | C167: 0 | E167: =+MID(B167,7,4) -> lvl2 | F167: =IF(LEFT(E167,3)="lvl",MID(B167,12,1),"f") -> h | G167: =+LEFT(B167,3)&"."&MID(B167,4,2) -> b05.00 | H167: =IF(LEFT(E167,3)="lvl",IF(OR(RIGHT(B167,2)="_1",RIGHT(B167,2)="_2"),MID(B167,14,LEN(B167)-15), MID(B167,14,LEN(B167))),MID(B167,12,LEN(B167))) -> 0060_max_amnt_guarantee
B168: b0500_lvl2_h_0070_flg_scrd | C168: 4730 | E168: =+MID(B168,7,4) -> lvl2 | F168: =IF(LEFT(E168,3)="lvl",MID(B168,12,1),"f") -> h | G168: =+LEFT(B168,3)&"."&MID(B168,4,2) -> b05.00 | H168: =IF(LEFT(E168,3)="lvl",IF(OR(RIGHT(B168,2)="_1",RIGHT(B168,2)="_2"),MID(B168,14,LEN(B168)-15), MID(B168,14,LEN(B168))),MID(B168,12,LEN(B168))) -> 0070_flg_scrd
B169: b0500_lvl2_h_0080_amnt_clltrl | C169: 0 | E169: =+MID(B169,7,4) -> lvl2 | F169: =IF(LEFT(E169,3)="lvl",MID(B169,12,1),"f") -> h | G169: =+LEFT(B169,3)&"."&MID(B169,4,2) -> b05.00 | H169: =IF(LEFT(E169,3)="lvl",IF(OR(RIGHT(B169,2)="_1",RIGHT(B169,2)="_2"),MID(B169,14,LEN(B169)-15), MID(B169,14,LEN(B169))),MID(B169,12,LEN(B169))) -> 0080_amnt_clltrl
B170: b0500_frmt_0010_row_nmbr | C170: 0 | E170: =+MID(B170,7,4) -> frmt | F170: =IF(LEFT(E170,3)="lvl",MID(B170,12,1),"f") -> f | G170: =+LEFT(B170,3)&"."&MID(B170,4,2) -> b05.00 | H170: =IF(LEFT(E170,3)="lvl",IF(OR(RIGHT(B170,2)="_1",RIGHT(B170,2)="_2"),MID(B170,14,LEN(B170)-15), MID(B170,14,LEN(B170))),MID(B170,12,LEN(B170))) -> 0010_row_nmbr
B171: b0500_frmt_0020_uniq_id_guarantee | C171: 0 | E171: =+MID(B171,7,4) -> frmt | F171: =IF(LEFT(E171,3)="lvl",MID(B171,12,1),"f") -> f | G171: =+LEFT(B171,3)&"."&MID(B171,4,2) -> b05.00 | H171: =IF(LEFT(E171,3)="lvl",IF(OR(RIGHT(B171,2)="_1",RIGHT(B171,2)="_2"),MID(B171,14,LEN(B171)-15), MID(B171,14,LEN(B171))),MID(B171,12,LEN(B171))) -> 0020_uniq_id_guarantee
B172: b0500_frmt_0030_governing_law | C172: 0 | E172: =+MID(B172,7,4) -> frmt | F172: =IF(LEFT(E172,3)="lvl",MID(B172,12,1),"f") -> f | G172: =+LEFT(B172,3)&"."&MID(B172,4,2) -> b05.00 | H172: =IF(LEFT(E172,3)="lvl",IF(OR(RIGHT(B172,2)="_1",RIGHT(B172,2)="_2"),MID(B172,14,LEN(B172)-15), MID(B172,14,LEN(B172))),MID(B172,12,LEN(B172))) -> 0030_governing_law
B173: b0500_frmt_0040_flg_art12g_3_srmr | C173: 0 | E173: =+MID(B173,7,4) -> frmt | F173: =IF(LEFT(E173,3)="lvl",MID(B173,12,1),"f") -> f | G173: =+LEFT(B173,3)&"."&MID(B173,4,2) -> b05.00 | H173: =IF(LEFT(E173,3)="lvl",IF(OR(RIGHT(B173,2)="_1",RIGHT(B173,2)="_2"),MID(B173,14,LEN(B173)-15), MID(B173,14,LEN(B173))),MID(B173,12,LEN(B173))) -> 0040_flg_art12g_3_srmr
B174: b0500_frmt_0050_typ_guarantee | C174: 0 | E174: =+MID(B174,7,4) -> frmt | F174: =IF(LEFT(E174,3)="lvl",MID(B174,12,1),"f") -> f | G174: =+LEFT(B174,3)&"."&MID(B174,4,2) -> b05.00 | H174: =IF(LEFT(E174,3)="lvl",IF(OR(RIGHT(B174,2)="_1",RIGHT(B174,2)="_2"),MID(B174,14,LEN(B174)-15), MID(B174,14,LEN(B174))),MID(B174,12,LEN(B174))) -> 0050_typ_guarantee
... B181: b0500_frmt_0120_typ_clltrlztn | C181: 0 | E181: =+MID(B181,7,4) -> frmt | F181: =IF(LEFT(E181,3)="lvl",MID(B181,12,1),"f") -> f | G181: =+LEFT(B181,3)&"."&MID(B181,4,2) -> b05.00 | H181: =IF(LEFT(E181,3)="lvl",IF(OR(RIGHT(B181,2)="_1",RIGHT(B181,2)="_2"),MID(B181,14,LEN(B181)-15), MID(B181,14,LEN(B181))),MID(B181,12,LEN(B181))) -> 0120_typ_clltrlztn
B182: b0500_frmt_0130_typ_prtctn_vl | C182: 4730 | E182: =+MID(B182,7,4) -> frmt | F182: =IF(LEFT(E182,3)="lvl",MID(B182,12,1),"f") -> f | G182: =+LEFT(B182,3)&"."&MID(B182,4,2) -> b05.00 | H182: =IF(LEFT(E182,3)="lvl",IF(OR(RIGHT(B182,2)="_1",RIGHT(B182,2)="_2"),MID(B182,14,LEN(B182)-15), MID(B182,14,LEN(B182))),MID(B182,12,LEN(B182))) -> 0130_typ_prtctn_vl | I182: Valor fixo 'Not applicable' no campo Type of protection value, uma vez que para o BST só existem garantias pessoais recebidas de clientes intragrupo Santander,ou seja, não existem garantias reais, onde se aplica o conceito de colateral.
B183: b0500_frmt_0150_prtctn_vltn_apprch | C183: 4730 | E183: =+MID(B183,7,4) -> frmt | F183: =IF(LEFT(E183,3)="lvl",MID(B183,12,1),"f") -> f | G183: =+LEFT(B183,3)&"."&MID(B183,4,2) -> b05.00 | H183: =IF(LEFT(E183,3)="lvl",IF(OR(RIGHT(B183,2)="_1",RIGHT(B183,2)="_2"),MID(B183,14,LEN(B183)-15), MID(B183,14,LEN(B183))),MID(B183,12,LEN(B183))) -> 0150_prtctn_vltn_apprch | I183: Valor fixo 'Not applicable' no campo Type of protection value, uma vez que para o BST só existem garantias pessoais recebidas de clientes intragrupo Santander,ou seja, não existem garantias reais, onde se aplica o conceito de colateral.
B184: b9000_lvl1_h_0030_cntrprty_rsltn_grp | C184: 4740 | E184: =+MID(B184,7,4) -> lvl1 | F184: =IF(LEFT(E184,3)="lvl",MID(B184,12,1),"f") -> h | G184: =+LEFT(B184,3)&"."&MID(B184,4,2) -> b90.00 | H184: =IF(LEFT(E184,3)="lvl",IF(OR(RIGHT(B184,2)="_1",RIGHT(B184,2)="_2"),MID(B184,14,LEN(B184)-15), MID(B184,14,LEN(B184))),MID(B184,12,LEN(B184))) -> 0030_cntrprty_rsltn_grp
B185: b9000_lvl2_h_0030_cntrprty_rsltn_grp | C185: 0 | E185: =+MID(B185,7,4) -> lvl2 | F185: =IF(LEFT(E185,3)="lvl",MID(B185,12,1),"f") -> h | G185: =+LEFT(B185,3)&"."&MID(B185,4,2) -> b90.00 | H185: =IF(LEFT(E185,3)="lvl",IF(OR(RIGHT(B185,2)="_1",RIGHT(B185,2)="_2"),MID(B185,14,LEN(B185)-15), MID(B185,14,LEN(B185))),MID(B185,12,LEN(B185))) -> 0030_cntrprty_rsltn_grp
B186: b9000_lvl2_h_0080_cntrprty_typ | C186: 0 | E186: =+MID(B186,7,4) -> lvl2 | F186: =IF(LEFT(E186,3)="lvl",MID(B186,12,1),"f") -> h | G186: =+LEFT(B186,3)&"."&MID(B186,4,2) -> b90.00 | H186: =IF(LEFT(E186,3)="lvl",IF(OR(RIGHT(B186,2)="_1",RIGHT(B186,2)="_2"),MID(B186,14,LEN(B186)-15), MID(B186,14,LEN(B186))),MID(B186,12,LEN(B186))) -> 0080_cntrprty_typ
B187: b9000_lvl2_h_0090_cntry_cntrprty | C187: 2 | E187: =+MID(B187,7,4) -> lvl2 | F187: =IF(LEFT(E187,3)="lvl",MID(B187,12,1),"f") -> h | G187: =+LEFT(B187,3)&"."&MID(B187,4,2) -> b90.00 | H187: =IF(LEFT(E187,3)="lvl",IF(OR(RIGHT(B187,2)="_1",RIGHT(B187,2)="_2"),MID(B187,14,LEN(B187)-15), MID(B187,14,LEN(B187))),MID(B187,12,LEN(B187))) -> 0090_cntry_cntrprty | I187: Valor '99' de não aplicável no campo Country of the counterparty, segundo email da Corporação (email Pedro Mendes 2025-05-14), no caso do zcliente = '0000000000', reportar valor fixo '99'.
B188: b9000_frmt_0010_row_nmbr | C188: 0 | E188: =+MID(B188,7,4) -> frmt | F188: =IF(LEFT(E188,3)="lvl",MID(B188,12,1),"f") -> f | G188: =+LEFT(B188,3)&"."&MID(B188,4,2) -> b90.00 | H188: =IF(LEFT(E188,3)="lvl",IF(OR(RIGHT(B188,2)="_1",RIGHT(B188,2)="_2"),MID(B188,14,LEN(B188)-15), MID(B188,14,LEN(B188))),MID(B188,12,LEN(B188))) -> 0010_row_nmbr
B189: b9000_frmt_0011_tab_origin | C189: 0 | E189: =+MID(B189,7,4) -> frmt | F189: =IF(LEFT(E189,3)="lvl",MID(B189,12,1),"f") -> f | G189: =+LEFT(B189,3)&"."&MID(B189,4,2) -> b90.00 | H189: =IF(LEFT(E189,3)="lvl",IF(OR(RIGHT(B189,2)="_1",RIGHT(B189,2)="_2"),MID(B189,14,LEN(B189)-15), MID(B189,14,LEN(B189))),MID(B189,12,LEN(B189))) -> 0011_tab_origin
B190: b9000_frmt_0020_uniq_id_knwn_cntrprty | C190: 0 | E190: =+MID(B190,7,4) -> frmt | F190: =IF(LEFT(E190,3)="lvl",MID(B190,12,1),"f") -> f | G190: =+LEFT(B190,3)&"."&MID(B190,4,2) -> b90.00 | H190: =IF(LEFT(E190,3)="lvl",IF(OR(RIGHT(B190,2)="_1",RIGHT(B190,2)="_2"),MID(B190,14,LEN(B190)-15), MID(B190,14,LEN(B190))),MID(B190,12,LEN(B190))) -> 0020_uniq_id_knwn_cntrprty
B191: b9000_frmt_0030_cntrprty_rsltn_grp | C191: 0 | E191: =+MID(B191,7,4) -> frmt | F191: =IF(LEFT(E191,3)="lvl",MID(B191,12,1),"f") -> f | G191: =+LEFT(B191,3)&"."&MID(B191,4,2) -> b90.00 | H191: =IF(LEFT(E191,3)="lvl",IF(OR(RIGHT(B191,2)="_1",RIGHT(B191,2)="_2"),MID(B191,14,LEN(B191)-15), MID(B191,14,LEN(B191))),MID(B191,12,LEN(B191))) -> 0030_cntrprty_rsltn_grp
B192: b9000_frmt_0040_cntrprty_nm | C192: 0 | E192: =+MID(B192,7,4) -> frmt | F192: =IF(LEFT(E192,3)="lvl",MID(B192,12,1),"f") -> f | G192: =+LEFT(B192,3)&"."&MID(B192,4,2) -> b90.00 | H192: =IF(LEFT(E192,3)="lvl",IF(OR(RIGHT(B192,2)="_1",RIGHT(B192,2)="_2"),MID(B192,14,LEN(B192)-15), MID(B192,14,LEN(B192))),MID(B192,12,LEN(B192))) -> 0040_cntrprty_nm
B193: b9000_frmt_0050_cntrprty_lei | C193: 0 | E193: =+MID(B193,7,4) -> frmt | F193: =IF(LEFT(E193,3)="lvl",MID(B193,12,1),"f") -> f | G193: =+LEFT(B193,3)&"."&MID(B193,4,2) -> b90.00 | H193: =IF(LEFT(E193,3)="lvl",IF(OR(RIGHT(B193,2)="_1",RIGHT(B193,2)="_2"),MID(B193,14,LEN(B193)-15), MID(B193,14,LEN(B193))),MID(B193,12,LEN(B193))) -> 0050_cntrprty_lei
B194: b9000_frmt_0060_typ_cntrprty_id | C194: 0 | E194: =+MID(B194,7,4) -> frmt | F194: =IF(LEFT(E194,3)="lvl",MID(B194,12,1),"f") -> f | G194: =+LEFT(B194,3)&"."&MID(B194,4,2) -> b90.00 | H194: =IF(LEFT(E194,3)="lvl",IF(OR(RIGHT(B194,2)="_1",RIGHT(B194,2)="_2"),MID(B194,14,LEN(B194)-15), MID(B194,14,LEN(B194))),MID(B194,12,LEN(B194))) -> 0060_typ_cntrprty_id
B195: b9000_frmt_0070_cntrprty_id | C195: 0 | E195: =+MID(B195,7,4) -> frmt | F195: =IF(LEFT(E195,3)="lvl",MID(B195,12,1),"f") -> f | G195: =+LEFT(B195,3)&"."&MID(B195,4,2) -> b90.00 | H195: =IF(LEFT(E195,3)="lvl",IF(OR(RIGHT(B195,2)="_1",RIGHT(B195,2)="_2"),MID(B195,14,LEN(B195)-15), MID(B195,14,LEN(B195))),MID(B195,12,LEN(B195))) -> 0070_cntrprty_id
B196: b9000_frmt_0080_cntrprty_typ | C196: 0 | E196: =+MID(B196,7,4) -> frmt | F196: =IF(LEFT(E196,3)="lvl",MID(B196,12,1),"f") -> f | G196: =+LEFT(B196,3)&"."&MID(B196,4,2) -> b90.00 | H196: =IF(LEFT(E196,3)="lvl",IF(OR(RIGHT(B196,2)="_1",RIGHT(B196,2)="_2"),MID(B196,14,LEN(B196)-15), MID(B196,14,LEN(B196))),MID(B196,12,LEN(B196))) -> 0080_cntrprty_typ
B197: b9000_frmt_0090_cntry_cntrprty | C197: 2 | E197: =+MID(B197,7,4) -> frmt | F197: =IF(LEFT(E197,3)="lvl",MID(B197,12,1),"f") -> f | G197: =+LEFT(B197,3)&"."&MID(B197,4,2) -> b90.00 | H197: =IF(LEFT(E197,3)="lvl",IF(OR(RIGHT(B197,2)="_1",RIGHT(B197,2)="_2"),MID(B197,14,LEN(B197)-15), MID(B197,14,LEN(B197))),MID(B197,12,LEN(B197))) -> 0090_cntry_cntrprty | I197: Valor '99' de não aplicável no campo Country of the counterparty, segundo email da Corporação (email Pedro Mendes 2025-05-14), no caso do zcliente = '0000000000', reportar valor fixo '99'.
B198: b9000_frmt_0100_rlvnt_amnt_wdc | C198: 0 | E198: =+MID(B198,7,4) -> frmt | F198: =IF(LEFT(E198,3)="lvl",MID(B198,12,1),"f") -> f | G198: =+LEFT(B198,3)&"."&MID(B198,4,2) -> b90.00 | H198: =IF(LEFT(E198,3)="lvl",IF(OR(RIGHT(B198,2)="_1",RIGHT(B198,2)="_2"),MID(B198,14,LEN(B198)-15), MID(B198,14,LEN(B198))),MID(B198,12,LEN(B198))) -> 0100_rlvnt_amnt_wdc

Sheet 2.2. Outros
B6: 2.2. Outros Controlos
B8: TABELA | C8: CAMPO | D8: TIPOLOGIA_TESTE | E8: NUM_REG | F8: NUM_REG_DIF | G8: DETALHE | H8: Table | I8: Justificação
B9: BU_LOANTAPE_WORK.OUT_B0200_MAIN_LIABILITIES | C9: 0010_ROW_NMBR | D9: VALIDADE | E9: 8 | F9: 0 | H9: =MID(B9,22,3)&"."&MID(B9,25,2) -> B02.00
B10: BU_LOANTAPE_WORK.OUT_B0200_MAIN_LIABILITIES | C10: 0010_ROW_NMBR | D10: NOT APPLICABLE | E10: 8 | F10: 0 | H10: =MID(B10,22,3)&"."&MID(B10,25,2) -> B02.00
B11: BU_LOANTAPE_WORK.OUT_B0200_MAIN_LIABILITIES | C11: 0020_UNIQ_ID | D11: VALIDADE | E11: 8 | F11: 0 | H11: =MID(B11,22,3)&"."&MID(B11,25,2) -> B02.00
B12: BU_LOANTAPE_WORK.OUT_B0200_MAIN_LIABILITIES | C12: 0020_UNIQ_ID | D12: NOT APPLICABLE | E12: 8 | F12: 0 | H12: =MID(B12,22,3)&"."&MID(B12,25,2) -> B02.00
B13: BU_LOANTAPE_WORK.OUT_B0200_MAIN_LIABILITIES | C13: 0030_UNIQ_ID_KNWN_CNTRPRTY | D13: VALIDADE | E13: 8 | F13: 0 | H13: =MID(B13,22,3)&"."&MID(B13,25,2) -> B02.00
B14: BU_LOANTAPE_WORK.OUT_B0200_MAIN_LIABILITIES | C14: 0030_UNIQ_ID_KNWN_CNTRPRTY | D14: NOT APPLICABLE | E14: 8 | F14: 0 | H14: =MID(B14,22,3)&"."&MID(B14,25,2) -> B02.00
B15: BU_LOANTAPE_WORK.OUT_B0200_MAIN_LIABILITIES | C15: 0040_TYP_UNIQ_ID_KNWN_CNTRPRTY | D15: VALIDADE | E15: 8 | F15: 0 | H15: =MID(B15,22,3)&"."&MID(B15,25,2) -> B02.00
B16: BU_LOANTAPE_WORK.OUT_B0200_MAIN_LIABILITIES | C16: 0040_TYP_UNIQ_ID_KNWN_CNTRPRTY | D16: NOT APPLICABLE | E16: 8 | F16: 0 | H16: =MID(B16,22,3)&"."&MID(B16,25,2) -> B02.00
B17: BU_LOANTAPE_WORK.OUT_B0200_MAIN_LIABILITIES | C17: 0050_ORGNL_AMNT_EUR | D17: VALIDADE | E17: 8 | F17: 0 | H17: =MID(B17,22,3)&"."&MID(B17,25,2) -> B02.00
B18: BU_LOANTAPE_WORK.OUT_B0200_MAIN_LIABILITIES | C18: 0050_ORGNL_AMNT_EUR | D18: NOT APPLICABLE | E18: 8 | F18: 0 | H18: =MID(B18,22,3)&"."&MID(B18,25,2) -> B02.00
B19: BU_LOANTAPE_WORK.OUT_B0200_MAIN_LIABILITIES | C19: 0060_ORGNL_AMNT_FX | D19: VALIDADE | E19: 8 | F19: 0 | H19: =MID(B19,22,3)&"."&MID(B19,25,2) -> B02.00 | I19: TESTE
B20: BU_LOANTAPE_WORK.OUT_B0200_MAIN_LIABILITIES | C20: 0060_ORGNL_AMNT_FX | D20: NOT APPLICABLE | E20: 8 | F20: 0 | H20: =MID(B20,22,3)&"."&MID(B20,25,2) -> B02.00
B21: BU_LOANTAPE_WORK.OUT_B0200_MAIN_LIABILITIES | C21: 0070_CNTRCT_CRRNCY | D21: VALIDADE | E21: 8 | F21: 0 | H21: =MID(B21,22,3)&"."&MID(B21,25,2) -> B02.00
B22: BU_LOANTAPE_WORK.OUT_B0200_MAIN_LIABILITIES | C22: 0070_CNTRCT_CRRNCY | D22: NOT APPLICABLE | E22: 8 | F22: 0 | H22: =MID(B22,22,3)&"."&MID(B22,25,2) -> B02.00
B23: BU_LOANTAPE_WORK.OUT_B0200_MAIN_LIABILITIES | C23: 0100_ACCRD_INTRST_INSTRMNT | D23: VALIDADE | E23: 8 | F23: 0 | H23: =MID(B23,22,3)&"."&MID(B23,25,2) -> B02.00
B24: BU_LOANTAPE_WORK.OUT_B0200_MAIN_LIABILITIES | C24: 0100_ACCRD_INTRST_INSTRMNT | D24: NOT APPLICABLE | E24: 8 | F24: 0 | H24: =MID(B24,22,3)&"."&MID(B24,25,2) -> B02.00
B25: BU_LOANTAPE_WORK.OUT_B0200_MAIN_LIABILITIES | C25: 0110_APPLCBL_FEES_CHARGES | D25: VALIDADE | E25: 8 | F25: 0 | H25: =MID(B25,22,3)&"."&MID(B25,25,2) -> B02.00
B26: BU_LOANTAPE_WORK.OUT_B0200_MAIN_LIABILITIES | C26: 0110_APPLCBL_FEES_CHARGES | D26: NOT APPLICABLE | E26: 8 | F26: 0 | H26: =MID(B26,22,3)&"."&MID(B26,25,2) -> B02.00
B27: BU_LOANTAPE_WORK.OUT_B0200_MAIN_LIABILITIES | C27: 0140_NTR_LBLTY | D27: VALIDADE | E27: 8 | F27: 0 | H27: =MID(B27,22,3)&"."&MID(B27,25,2) -> B02.00
B28: BU_LOANTAPE_WORK.OUT_B0200_MAIN_LIABILITIES | C28: 0140_NTR_LBLTY | D28: NOT APPLICABLE | E28: 8 | F28: 0 | H28: =MID(B28,22,3)&"."&MID(B28,25,2) -> B02.00
B29: BU_LOANTAPE_WORK.OUT_B0200_MAIN_LIABILITIES | C29: 0141_NTR_LBLTY_OTHR | D29: VALIDADE | E29: 8 | F29: 0 | H29: =MID(B29,22,3)&"."&MID(B29,25,2) -> B02.00
B30: BU_LOANTAPE_WORK.OUT_B0200_MAIN_LIABILITIES | C30: 0141_NTR_LBLTY_OTHR | D30: NOT APPLICABLE | E30: 8 | F30: 8 | H30: =MID(B30,22,3)&"."&MID(B30,25,2) -> B02.00
B31: BU_LOANTAPE_WORK.OUT_B0200_MAIN_LIABILITIES | C31: 0150_FLG_STRCTRLLY_SBRDNTD | D31: VALIDADE | E31: 8 | F31: 0 | H31: =MID(B31,22,3)&"."&MID(B31,25,2) -> B02.00
... B33: BU_LOANTAPE_WORK.OUT_B0200_MAIN_LIABILITIES | C33: 0160_RANK_INSOLV | D33: VALIDADE | E33: 8 | F33: 0 | H33: =MID(B33,22,3)&"."&MID(B33,25,2) -> B02.00
B34: BU_LOANTAPE_WORK.OUT_B0200_MAIN_LIABILITIES | C34: 0160_RANK_INSOLV | D34: NOT APPLICABLE | E34: 8 | F34: 0 | H34: =MID(B34,22,3)&"."&MID(B34,25,2) -> B02.00 | I34: TESTE
B35: BU_LOANTAPE_WORK.OUT_B0200_MAIN_LIABILITIES | C35: 0161_CNTRCTL_SBRDNTN | D35: VALIDADE | E35: 8 | F35: 0 | H35: =MID(B35,22,3)&"."&MID(B35,25,2) -> B02.00
B36: BU_LOANTAPE_WORK.OUT_B0200_MAIN_LIABILITIES | C36: 0161_CNTRCTL_SBRDNTN | D36: NOT APPLICABLE | E36: 8 | F36: 0 | H36: =MID(B36,22,3)&"."&MID(B36,25,2) -> B02.00
B37: BU_LOANTAPE_WORK.OUT_B0200_MAIN_LIABILITIES | C37: 0162_BAIL_IN_CASCADE | D37: VALIDADE | E37: 8 | F37: 0 | H37: =MID(B37,22,3)&"."&MID(B37,25,2) -> B02.00
B38: BU_LOANTAPE_WORK.OUT_B0200_MAIN_LIABILITIES | C38: 0162_BAIL_IN_CASCADE | D38: NOT APPLICABLE | E38: 8 | F38: 0 | H38: =MID(B38,22,3)&"."&MID(B38,25,2) -> B02.00
B39: BU_LOANTAPE_WORK.OUT_B0200_MAIN_LIABILITIES | C39: 0170_DT_INCPTN | D39: VALIDADE | E39: 8 | F39: 0 | H39: =MID(B39,22,3)&"."&MID(B39,25,2) -> B02.00
B40: BU_LOANTAPE_WORK.OUT_B0200_MAIN_LIABILITIES | C40: 0170_DT_INCPTN | D40: NOT APPLICABLE | E40: 8 | F40: 0 | H40: =MID(B40,22,3)&"."&MID(B40,25,2) -> B02.00
B41: BU_LOANTAPE_WORK.OUT_B0200_MAIN_LIABILITIES | C41: 0180_DT_NXT_INTRST_PYMNT | D41: VALIDADE | E41: 8 | F41: 8 | H41: =MID(B41,22,3)&"."&MID(B41,25,2) -> B02.00
B42: BU_LOANTAPE_WORK.OUT_B0200_MAIN_LIABILITIES | C42: 0180_DT_NXT_INTRST_PYMNT | D42: NOT APPLICABLE | E42: 8 | F42: 0 | H42: =MID(B42,22,3)&"."&MID(B42,25,2) -> B02.00
B43: BU_LOANTAPE_WORK.OUT_B0200_MAIN_LIABILITIES | C43: 0190_DT_NXT_RDMPTN_PYMNT | D43: VALIDADE | E43: 8 | F43: 0 | H43: =MID(B43,22,3)&"."&MID(B43,25,2) -> B02.00
B44: BU_LOANTAPE_WORK.OUT_B0200_MAIN_LIABILITIES | C44: 0190_DT_NXT_RDMPTN_PYMNT | D44: NOT APPLICABLE | E44: 8 | F44: 3 | H44: =MID(B44,22,3)&"."&MID(B44,25,2) -> B02.00
B45: BU_LOANTAPE_WORK.OUT_B0200_MAIN_LIABILITIES | C45: 0200_DT_ERLST_RDMPTN | D45: VALIDADE | E45: 8 | F45: 0 | H45: =MID(B45,22,3)&"."&MID(B45,25,2) -> B02.00
B46: BU_LOANTAPE_WORK.OUT_B0200_MAIN_LIABILITIES | C46: 0200_DT_ERLST_RDMPTN | D46: NOT APPLICABLE | E46: 8 | F46: 8 | H46: =MID(B46,22,3)&"."&MID(B46,25,2) -> B02.00
... B127: BU_LOANTAPE_WORK.OUT_B0200_MAIN_LIABILITIES | C127: 0540_ELGBL_AMNT_OWN_FNDS_IND_LVL | D127: VALIDADE | E127: 8 | F127: 0 | H127: =MID(B127,22,3)&"."&MID(B127,25,2) -> B02.00
B128: BU_LOANTAPE_WORK.OUT_B0200_MAIN_LIABILITIES | C128: 0540_ELGBL_AMNT_OWN_FNDS_IND_LVL | D128: NOT APPLICABLE | E128: 8 | F128: 0 | H128: =MID(B128,22,3)&"."&MID(B128,25,2) -> B02.00 | I128: TESTE
B129: BU_LOANTAPE_WORK.OUT_B0200_MAIN_LIABILITIES | C129: 0550_TYP_OWN_FNDS_CNSLDTD_LVL | D129: VALIDADE | E129: 8 | F129: 2 | H129: =MID(B129,22,3)&"."&MID(B129,25,2) -> B02.00 | I129: TESTE
B130: BU_LOANTAPE_WORK.OUT_B0200_MAIN_LIABILITIES | C130: 0550_TYP_OWN_FNDS_CNSLDTD_LVL | D130: NOT APPLICABLE | E130: 8 | F130: 0 | H130: =MID(B130,22,3)&"."&MID(B130,25,2) -> B02.00 | I130: TESTE
B131: BU_LOANTAPE_WORK.OUT_B0200_MAIN_LIABILITIES | C131: 0560_ELGBL_AMNT_OWN_FNDS_CNSLDTD_LVL | D131: VALIDADE | E131: 8 | F131: 0 | H131: =MID(B131,22,3)&"."&MID(B131,25,2) -> B02.00
B132: BU_LOANTAPE_WORK.OUT_B0200_MAIN_LIABILITIES | C132: 0560_ELGBL_AMNT_OWN_FNDS_CNSLDTD_LVL | D132: NOT APPLICABLE | E132: 8 | F132: 0 | H132: =MID(B132,22,3)&"."&MID(B132,25,2) -> B02.00
B133: BU_LOANTAPE_WORK.OUT_B0200_MAIN_LIABILITIES | C133: 0570_AMNT_SCRTY_INTRST_PRVDD | D133: VALIDADE | E133: 8 | F133: 0 | H133: =MID(B133,22,3)&"."&MID(B133,25,2) -> B02.00
B134: BU_LOANTAPE_WORK.OUT_B0200_MAIN_LIABILITIES | C134: 0570_AMNT_SCRTY_INTRST_PRVDD | D134: NOT APPLICABLE | E134: 8 | F134: 0 | H134: =MID(B134,22,3)&"."&MID(B134,25,2) -> B02.00
B135: BU_LOANTAPE_WORK.OUT_B0200_MAIN_LIABILITIES | C135: 0580_SCRTY_INTRST_PRVDR | D135: VALIDADE | E135: 8 | F135: 0 | H135: =MID(B135,22,3)&"."&MID(B135,25,2) -> B02.00
B136: BU_LOANTAPE_WORK.OUT_B0200_MAIN_LIABILITIES | C136: 0580_SCRTY_INTRST_PRVDR | D136: NOT APPLICABLE | E136: 8 | F136: 8 | H136: =MID(B136,22,3)&"."&MID(B136,25,2) -> B02.00
B137: BU_LOANTAPE_WORK.OUT_B0200_MAIN_LIABILITIES | C137: 0581_SCRTY_INTRST_PRVDR_LEI | D137: VALIDADE | E137: 8 | F137: 0 | H137: =MID(B137,22,3)&"."&MID(B137,25,2) -> B02.00
B138: BU_LOANTAPE_WORK.OUT_B0200_MAIN_LIABILITIES | C138: 0581_SCRTY_INTRST_PRVDR_LEI | D138: NOT APPLICABLE | E138: 8 | F138: 8 | H138: =MID(B138,22,3)&"."&MID(B138,25,2) -> B02.00
B139: BU_LOANTAPE_WORK.OUT_B0200_MAIN_LIABILITIES | C139: 0590_TYP_SCRTY_INTRST_PRVDD | D139: VALIDADE | E139: 8 | F139: 0 | H139: =MID(B139,22,3)&"."&MID(B139,25,2) -> B02.00
B140: BU_LOANTAPE_WORK.OUT_B0200_MAIN_LIABILITIES | C140: 0590_TYP_SCRTY_INTRST_PRVDD | D140: NOT APPLICABLE | E140: 8 | F140: 8 | H140: =MID(B140,22,3)&"."&MID(B140,25,2) -> B02.00
B141: BU_LOANTAPE_WORK.OUT_B0200_MAIN_LIABILITIES | C141: 0600_FLG_CLLTRL_ASST_PSTN | D141: VALIDADE | E141: 8 | F141: 0 | H141: =MID(B141,22,3)&"."&MID(B141,25,2) -> B02.00
B142: BU_LOANTAPE_WORK.OUT_B0200_MAIN_LIABILITIES | C142: 0600_FLG_CLLTRL_ASST_PSTN | D142: NOT APPLICABLE | E142: 8 | F142: 0 | H142: =MID(B142,22,3)&"."&MID(B142,25,2) -> B02.00
... B145: BU_LOANTAPE_WORK.OUT_B0200_MAIN_LIABILITIES | C145: 0620_BLNC_SHT_IFRS | D145: VALIDADE | E145: 8 | F145: 0 | H145: =MID(B145,22,3)&"."&MID(B145,25,2) -> B02.00
B146: BU_LOANTAPE_WORK.OUT_B0200_MAIN_LIABILITIES | C146: 0620_BLNC_SHT_IFRS | D146: NOT APPLICABLE | E146: 8 | F146: 0 | H146: =MID(B146,22,3)&"."&MID(B146,25,2) -> B02.00 | I146: TESTE
B147: BU_LOANTAPE_WORK.OUT_B0200_MAIN_LIABILITIES | C147: 0630_CRRYING_AMNT_NGAAP | D147: VALIDADE | E147: 8 | F147: 0 | H147: =MID(B147,22,3)&"."&MID(B147,25,2) -> B02.00 | I147: TESTE
B148: BU_LOANTAPE_WORK.OUT_B0200_MAIN_LIABILITIES | C148: 0630_CRRYING_AMNT_NGAAP | D148: NOT APPLICABLE | E148: 8 | F148: 0 | H148: =MID(B148,22,3)&"."&MID(B148,25,2) -> B02.00 | I148: TESTE
B149: BU_LOANTAPE_WORK.OUT_B0200_MAIN_LIABILITIES | C149: 0640_BLNC_SHT_NGAAP | D149: VALIDADE | E149: 8 | F149: 0 | H149: =MID(B149,22,3)&"."&MID(B149,25,2) -> B02.00 | I149: TESTE
B150: BU_LOANTAPE_WORK.OUT_B0200_MAIN_LIABILITIES | C150: 0640_BLNC_SHT_NGAAP | D150: NOT APPLICABLE | E150: 8 | F150: 8 | H150: =MID(B150,22,3)&"."&MID(B150,25,2) -> B02.00 | I150: TESTE
B151: BU_LOANTAPE_WORK.OUT_B0200_MAIN_LIABILITIES | C151: 5000_FLG_SHRHLDR_NOT_RSLTN_GRP | D151: VALIDADE | E151: 8 | F151: 0 | H151: =MID(B151,22,3)&"."&MID(B151,25,2) -> B02.00
B152: BU_LOANTAPE_WORK.OUT_B0200_MAIN_LIABILITIES | C152: 5000_FLG_SHRHLDR_NOT_RSLTN_GRP | D152: NOT APPLICABLE | E152: 8 | F152: 0 | H152: =MID(B152,22,3)&"."&MID(B152,25,2) -> B02.00
B153: BU_LOANTAPE_WORK.OUT_B0200_MAIN_LIABILITIES | C153: 5010_FLG_ART21_7A_SRMR | D153: VALIDADE | E153: 8 | F153: 0 | H153: =MID(B153,22,3)&"."&MID(B153,25,2) -> B02.00
B154: BU_LOANTAPE_WORK.OUT_B0200_MAIN_LIABILITIES | C154: 5010_FLG_ART21_7A_SRMR | D154: NOT APPLICABLE | E154: 8 | F154: 0 | H154: =MID(B154,22,3)&"."&MID(B154,25,2) -> B02.00
B155: BU_LOANTAPE_WORK.OUT_B0500_GUARANTEES | C155: 0020_UNIQ_ID_GUARANTEE | D155: INTEGRIDADE | E155: 9460 | F155: 0 | G155: NULL | H155: =MID(B155,22,3)&"."&MID(B155,25,2) -> B05.00
B156: BU_LOANTAPE_WORK.OUT_B9000_COUNTERPARTIES | C156: 0020_UNIQ_ID_KNWN_CNTRPRTY | D156: INTEGRIDADE | E156: 4740 | F156: 0 | G156: NULL | H156: =MID(B156,22,3)&"."&MID(B156,25,2) -> B90.00
B157: BU_LOANTAPE_WORK.OUT_B0200_MAIN_LIABILITIES | C157: 0020_UNIQ_ID | D157: INTEGRIDADE | E157: 8 | F157: 0 | G157: NULL | H157: =MID(B157,22,3)&"."&MID(B157,25,2) -> B02.00
B158: BU_LOANTAPE_WORK.OUT_B0200_MAIN_LIABILITIES | C158: 0020_UNIQ_ID | D158: DUPLICADOS | E158: 8 | F158: 0 | G158: NULL | H158: =MID(B158,22,3)&"."&MID(B158,25,2) -> B02.00

Sheet Query1
A2: ref_date | B2: cod_kpi | C2: tipologia_teste | D2: descrição | E2: tabela | F2: campo | G2: num_reg | H2: num_reg_dif | I2: detalhe
A3: 2025-10-31 | B3: MIS_B0200_C0010 | C3: MISSINGS | D3: Validar que não existem registos por preencher (Missings) | E3: BU_LOANTAPE_WORK.OUT_B0200_MAIN_LIABILITIES | F3: 0010_ROW_NMBR | G3: 8 | H3: 0
A4: 2025-10-31 | B4: MIS_B0200_C0020 | C4: MISSINGS | D4: Validar que não existem registos por preencher (Missings) | E4: BU_LOANTAPE_WORK.OUT_B0200_MAIN_LIABILITIES | F4: 0020_UNIQ_ID | G4: 8 | H4: 0
A5: 2025-10-31 | B5: MIS_B0200_C0030 | C5: MISSINGS | D5: Validar que não existem registos por preencher (Missings) | E5: BU_LOANTAPE_WORK.OUT_B0200_MAIN_LIABILITIES | F5: 0030_UNIQ_ID_KNWN_CNTRPRTY | G5: 8 | H5: 0
A6: 2025-10-31 | B6: MIS_B0200_C0040 | C6: MISSINGS | D6: Validar que não existem registos por preencher (Missings) | E6: BU_LOANTAPE_WORK.OUT_B0200_MAIN_LIABILITIES | F6: 0040_TYP_UNIQ_ID_KNWN_CNTRPRTY | G6: 8 | H6: 0
A7: 2025-10-31 | B7: MIS_B0200_C0050 | C7: MISSINGS | D7: Validar que não existem registos por preencher (Missings) | E7: BU_LOANTAPE_WORK.OUT_B0200_MAIN_LIABILITIES | F7: 0050_ORGNL_AMNT_EUR | G7: 8 | H7: 0
A8: 2025-10-31 | B8: MIS_B0200_C0060 | C8: MISSINGS | D8: Validar que não existem registos por preencher (Missings) | E8: BU_LOANTAPE_WORK.OUT_B0200_MAIN_LIABILITIES | F8: 0060_ORGNL_AMNT_FX | G8: 8 | H8: 0
A9: 2025-10-31 | B9: MIS_B0200_C0070 | C9: MISSINGS | D9: Validar que não existem registos por preencher (Missings) | E9: BU_LOANTAPE_WORK.OUT_B0200_MAIN_LIABILITIES | F9: 0070_CNTRCT_CRRNCY | G9: 8 | H9: 0
A10: 2025-10-31 | B10: MIS_B0200_C0080 | C10: MISSINGS | D10: Validar que não existem registos por preencher (Missings) | E10: BU_LOANTAPE_WORK.OUT_B0200_MAIN_LIABILITIES | F10: 0080_OTSTNDNG_PRNCPL_AMNT | G10: 8 | H10: 8 | I10: 31641600000000000PTBSREOM0028000; 31641600000000000PTSTOEOM0021000; 31641600000000000PTSTOFOM0004000; 31641600000000000PTSTOGOM0003000; 31641600000000000PTSTOHOM0002000; 31641600005800007PTBSRDOM0037000; 31641600005800007PTCPP0AM0007000; 31641600005800007PTSTOCOM0007000
A11: 2025-10-31 | B11: MIS_B0200_C0090 | C11: MISSINGS | D11: Validar que não existem registos por preencher (Missings) | E11: BU_LOANTAPE_WORK.OUT_B0200_MAIN_LIABILITIES | F11: 0090_PRTN_AMNT_RPRTNG_ENTTY | G11: 8 | H11: 8 | I11: 31641600000000000PTBSREOM0028000; 31641600000000000PTSTOEOM0021000; 31641600000000000PTSTOFOM0004000; 31641600000000000PTSTOGOM0003000; 31641600000000000PTSTOHOM0002000; 31641600005800007PTBSRDOM0037000; 31641600005800007PTCPP0AM0007000; 31641600005800007PTSTOCOM0007000
A12: 2025-10-31 | B12: MIS_B0200_C0100 | C12: MISSINGS | D12: Validar que não existem registos por preencher (Missings) | E12: BU_LOANTAPE_WORK.OUT_B0200_MAIN_LIABILITIES | F12: 0100_ACCRD_INTRST_INSTRMNT | G12: 8 | H12: 0
A13: 2025-10-31 | B13: MIS_B0200_C0110 | C13: MISSINGS | D13: Validar que não existem registos por preencher (Missings) | E13: BU_LOANTAPE_WORK.OUT_B0200_MAIN_LIABILITIES | F13: 0110_APPLCBL_FEES_CHARGES | G13: 8 | H13: 0
A14: 2025-10-31 | B14: MIS_B0200_C0120 | C14: MISSINGS | D14: Validar que não existem registos por preencher (Missings) | E14: BU_LOANTAPE_WORK.OUT_B0200_MAIN_LIABILITIES | F14: 0120_OTSTNDNG_AMNT | G14: 8 | H14: 8 | I14: 31641600000000000PTBSREOM0028000; 31641600000000000PTSTOEOM0021000; 31641600000000000PTSTOFOM0004000; 31641600000000000PTSTOGOM0003000; 31641600000000000PTSTOHOM0002000; 31641600005800007PTBSRDOM0037000; 31641600005800007PTCPP0AM0007000; 31641600005800007PTSTOCOM0007000
A15: 2025-10-31 | B15: MIS_B0200_C0130 | C15: MISSINGS | D15: Validar que não existem registos por preencher (Missings) | E15: BU_LOANTAPE_WORK.OUT_B0200_MAIN_LIABILITIES | F15: 0130_RLVNT_AMNT_WDC | G15: 8 | H15: 8 | I15: 31641600000000000PTBSREOM0028000; 31641600000000000PTSTOEOM0021000; 31641600000000000PTSTOFOM0004000; 31641600000000000PTSTOGOM0003000; 31641600000000000PTSTOHOM0002000; 31641600005800007PTBSRDOM0037000; 31641600005800007PTCPP0AM0007000; 31641600005800007PTSTOCOM0007000
A16: 2025-10-31 | B16: MIS_B0200_C0140 | C16: MISSINGS | D16: Validar que não existem registos por preencher (Missings) | E16: BU_LOANTAPE_WORK.OUT_B0200_MAIN_LIABILITIES | F16: 0140_NTR_LBLTY | G16: 8 | H16: 0
A17: 2025-10-31 | B17: MIS_B0200_C0141 | C17: MISSINGS | D17: Validar que não existem registos por preencher (Missings) | E17: BU_LOANTAPE_WORK.OUT_B0200_MAIN_LIABILITIES | F17: 0141_NTR_LBLTY_OTHR | G17: 8 | H17: 0
A18: 2025-10-31 | B18: MIS_B0200_C0150 | C18: MISSINGS | D18: Validar que não existem registos por preencher (Missings) | E18: BU_LOANTAPE_WORK.OUT_B0200_MAIN_LIABILITIES | F18: 0150_FLG_STRCTRLLY_SBRDNTD | G18: 8 | H18: 0
A19: 2025-10-31 | B19: MIS_B0200_C0160 | C19: MISSINGS | D19: Validar que não existem registos por preencher (Missings) | E19: BU_LOANTAPE_WORK.OUT_B0200_MAIN_LIABILITIES | F19: 0160_RANK_INSOLV | G19: 8 | H19: 0
A20: 2025-10-31 | B20: MIS_B0200_C0161 | C20: MISSINGS | D20: Validar que não existem registos por preencher (Missings) | E20: BU_LOANTAPE_WORK.OUT_B0200_MAIN_LIABILITIES | F20: 0161_CNTRCTL_SBRDNTN | G20: 8 | H20: 0
A21: 2025-10-31 | B21: MIS_B0200_C0162 | C21: MISSINGS | D21: Validar que não existem registos por preencher (Missings) | E21: BU_LOANTAPE_WORK.OUT_B0200_MAIN_LIABILITIES | F21: 0162_BAIL_IN_CASCADE | G21: 8 | H21: 0
A22: 2025-10-31 | B22: MIS_B0200_C0170 | C22: MISSINGS | D22: Validar que não existem registos por preencher (Missings) | E22: BU_LOANTAPE_WORK.OUT_B0200_MAIN_LIABILITIES | F22: 0170_DT_INCPTN | G22: 8 | H22: 0
A23: 2025-10-31 | B23: MIS_B0200_C0180 | C23: MISSINGS | D23: Validar que não existem registos por preencher (Missings) | E23: BU_LOANTAPE_WORK.OUT_B0200_MAIN_LIABILITIES | F23: 0180_DT_NXT_INTRST_PYMNT | G23: 8 | H23: 0
A24: 2025-10-31 | B24: MIS_B0200_C0190 | C24: MISSINGS | D24: Validar que não existem registos por preencher (Missings) | E24: BU_LOANTAPE_WORK.OUT_B0200_MAIN_LIABILITIES | F24: 0190_DT_NXT_RDMPTN_PYMNT | G24: 8 | H24: 0
A25: 2025-10-31 | B25: MIS_B0200_C0200 | C25: MISSINGS | D25: Validar que não existem registos por preencher (Missings) | E25: BU_LOANTAPE_WORK.OUT_B0200_MAIN_LIABILITIES | F25: 0200_DT_ERLST_RDMPTN | G25: 8 | H25: 0
A26: 2025-10-31 | B26: MIS_B0200_C0210 | C26: MISSINGS | D26: Validar que não existem registos por preencher (Missings) | E26: BU_LOANTAPE_WORK.OUT_B0200_MAIN_LIABILITIES | F26: 0210_DT_LGL_FNL_MTRTY | G26: 8 | H26: 0
A27: 2025-10-31 | B27: MIS_B0200_C0220 | C27: MISSINGS | D27: Validar que não existem registos por preencher (Missings) | E27: BU_LOANTAPE_WORK.OUT_B0200_MAIN_LIABILITIES | F27: 0220_GOVERNING_LAW | G27: 8 | H27: 0
... A44: 2025-10-31 | B44: MIS_B0200_C0380 | C44: MISSINGS | D44: Validar que não existem registos por preencher (Missings) | E44: BU_LOANTAPE_WORK.OUT_B0200_MAIN_LIABILITIES | F44: 0380_AMNT_SCRTY_FX | G44: 8 | H44: 0
A45: 2025-10-31 | B45: MIS_B0200_C0390 | C45: MISSINGS | D45: Validar que não existem registos por preencher (Missings) | E45: BU_LOANTAPE_WORK.OUT_B0200_MAIN_LIABILITIES | F45: 0390_NMBR_SCRTS_NOT_RPRTNG_ENTTY | G45: 8 | H45: 8 | I45: 31641600000000000PTBSREOM0028000; 31641600000000000PTSTOEOM0021000; 31641600000000000PTSTOFOM0004000; 31641600000000000PTSTOGOM0003000; 31641600000000000PTSTOHOM0002000; 31641600005800007PTBSRDOM0037000; 31641600005800007PTCPP0AM0007000; 31641600005800007PTSTOCOM0007000
A46: 2025-10-31 | B46: MIS_B0200_C0391 | C46: MISSINGS | D46: Validar que não existem registos por preencher (Missings) | E46: BU_LOANTAPE_WORK.OUT_B0200_MAIN_LIABILITIES | F46: 0391_NMBR_SCRTS_RPRTNG_ENTTY | G46: 8 | H46: 8 | I46: 31641600000000000PTBSREOM0028000; 31641600000000000PTSTOEOM0021000; 31641600000000000PTSTOFOM0004000; 31641600000000000PTSTOGOM0003000; 31641600000000000PTSTOHOM0002000; 31641600005800007PTBSRDOM0037000; 31641600005800007PTCPP0AM0007000; 31641600005800007PTSTOCOM0007000
A47: 2025-10-31 | B47: MIS_B0200_C0400 | C47: MISSINGS | D47: Validar que não existem registos por preencher (Missings) | E47: BU_LOANTAPE_WORK.OUT_B0200_MAIN_LIABILITIES | F47: 0400_ACCRD_INTRST_SCRTY | G47: 8 | H47: 8 | I47: 31641600000000000PTBSREOM0028000; 31641600000000000PTSTOEOM0021000; 31641600000000000PTSTOFOM0004000; 31641600000000000PTSTOGOM0003000; 31641600000000000PTSTOHOM0002000; 31641600005800007PTBSRDOM0037000; 31641600005800007PTCPP0AM0007000; 31641600005800007PTSTOCOM0007000
A48: 2025-10-31 | B48: MIS_B0200_C0410 | C48: MISSINGS | D48: Validar que não existem registos por preencher (Missings) | E48: BU_LOANTAPE_WORK.OUT_B0200_MAIN_LIABILITIES | F48: 0410_FEES_CHARGES_SCRTY | G48: 8 | H48: 0
A49: 2025-10-31 | B49: MIS_B0200_C0420 | C49: MISSINGS | D49: Validar que não existem registos por preencher (Missings) | E49: BU_LOANTAPE_WORK.OUT_B0200_MAIN_LIABILITIES | F49: 0420_FV_AMNT_SCRTY | G49: 8 | H49: 0
A50: 2025-10-31 | B50: MIS_B0200_C0430 | C50: MISSINGS | D50: Validar que não existem registos por preencher (Missings) | E50: BU_LOANTAPE_WORK.OUT_B0200_MAIN_LIABILITIES | F50: 0430_PRNCPL_AMNT_GLBL_NT_EUR | G50: 8 | H50: 0
A51: 2025-10-31 | B51: MIS_B0200_C0431 | C51: MISSINGS | D51: Validar que não existem registos por preencher (Missings) | E51: BU_LOANTAPE_WORK.OUT_B0200_MAIN_LIABILITIES | F51: 0431_PRNCPL_AMNT_GLBL_NT_FX | G51: 8 | H51: 0
A52: 2025-10-31 | B52: MIS_B0200_C0440 | C52: MISSINGS | D52: Validar que não existem registos por preencher (Missings) | E52: BU_LOANTAPE_WORK.OUT_B0200_MAIN_LIABILITIES | F52: 0440_NTR_GLBL_NT | G52: 8 | H52: 0
A53: 2025-10-31 | B53: MIS_B0200_C0450 | C53: MISSINGS | D53: Validar que não existem registos por preencher (Missings) | E53: BU_LOANTAPE_WORK.OUT_B0200_MAIN_LIABILITIES | F53: 0450_CRRNT_POOL_FCTR | G53: 8 | H53: 0
A54: 2025-10-31 | B54: MIS_B0200_C0460 | C54: MISSINGS | D54: Validar que não existem registos por preencher (Missings) | E54: BU_LOANTAPE_WORK.OUT_B0200_MAIN_LIABILITIES | F54: 0460_CSD | G54: 8 | H54: 0
A55: 2025-10-31 | B55: MIS_B0200_C0461 | C55: MISSINGS | D55: Validar que não existem registos por preencher (Missings) | E55: BU_LOANTAPE_WORK.OUT_B0200_MAIN_LIABILITIES | F55: 0461_CSD_LEI | G55: 8 | H55: 0
A56: 2025-10-31 | B56: MIS_B0200_C0462 | C56: MISSINGS | D56: Validar que não existem registos por preencher (Missings) | E56: BU_LOANTAPE_WORK.OUT_B0200_MAIN_LIABILITIES | F56: 0462_CSD_OTHR | G56: 8 | H56: 0
A57: 2025-10-31 | B57: MIS_B0200_C0470 | C57: MISSINGS | D57: Validar que não existem registos por preencher (Missings) | E57: BU_LOANTAPE_WORK.OUT_B0200_MAIN_LIABILITIES | F57: 0470_PYNG_AGNT | G57: 8 | H57: 0
A58: 2025-10-31 | B58: MIS_B0200_C0471 | C58: MISSINGS | D58: Validar que não existem registos por preencher (Missings) | E58: BU_LOANTAPE_WORK.OUT_B0200_MAIN_LIABILITIES | F58: 0471_PYNG_AGNT_LEI | G58: 8 | H58: 0
A59: 2025-10-31 | B59: MIS_B0200_C0480 | C59: MISSINGS | D59: Validar que não existem registos por preencher (Missings) | E59: BU_LOANTAPE_WORK.OUT_B0200_MAIN_LIABILITIES | F59: 0480_TRDNG_VN | G59: 8 | H59: 0
... A89: 2025-10-31 | B89: MIS_B0500_C0060 | C89: MISSINGS | D89: Validar que não existem registos por preencher (Missings) | E89: BU_LOANTAPE_WORK.OUT_B0500_GUARANTEES | F89: 0060_MAX_AMNT_GUARANTEE | G89: 4730 | H89: 0
A90: 2025-10-31 | B90: MIS_B0500_C0070 | C90: MISSINGS | D90: Validar que não existem registos por preencher (Missings) | E90: BU_LOANTAPE_WORK.OUT_B0500_GUARANTEES | F90: 0070_FLG_SCRD | G90: 4730 | H90: 4730 | I90: 31000000000000000962304890482490P_0000_00000000000_000006511000505; 31000304140330096000000000000000P_0000_00000000000_000000000003686; 31000307044893096000000000000000P_0000_00000000000_000000000003686; 31000307530917096000000000000000P_0000_00000000000_000000000003686; 31000311450813096000000000000000P_0000_00000000000_000000000003686; 31000311847794096000000000000000P_0000_00000000000_000000000003686; 31000313517171096000000000000000P_0000_00000000000_000000000003686; 31000315970006096000000000000000P_0000_00000000000_000000000003686; 31000315970121096000000000000000P_0000_00000000000_000000000003686; 31000315970139096000000000000000P_0000_00000000000_000000000003686; 31000315970188096000000000000000P_0000_00000000000_000000000003686; 31000315970212096000000000000000P_0000_00000000000_000000000003686; 31000315970238096000000000000000P_0000_00000000000_000000000003686; 31000315970261096000000000000000P_0000_00000000000_000000000003686; 31000315970279096000000000000000P_0000_00000000000_000000000003686; 31000315970311096000000000000000P_0000_00000000000_000000000003686; 31000315970329096000000000000000P_0000_00000000000_000000000003686; 31000315970345096000000000000000P_0000_00000000000_000000000003686; 31000315970402096000000000000000P_0000_00000000000_000000000003686; 31000315970428096000000000000000P_0000_00000000000_000000000003686; 31000315970469096000000000000000P_0000_00000000000_000000000003686; 31000315979890096000000000000000P_0000_00000000000_000006511000505; 31000318293090097000000000000000P_0000_00000000000_000008000176024; 31000318542009097000000000000000P_0000_00000000000_000006511000505; 31000318628196097000000000000000P_0000_00000000000_000006511000505; 31000318628592097000000000000000P_0000_00000000000_000008000176024; 31000318629012097000000000000000P_0000_00000000000_000008000176024; 31000318636603097000000000000000P_0000_00000000000_000008000176024; 31000318637213097000000000000000P_0000_00000000000_000008000176024; 31000322311418096000000000000000P_0000_00000000000_000000000003686; 89000020240000766001520240649818P_0000_00000000000_000003461004226; 89000020240000766001520240649824P_0000_00000000000_000003461004226; 89000020240000766001520240649825P_0000_00000000000_000003461004226; 89000020240000766001520240649826P_0000_00000000000_000003461004226; 89000020240000766001520240649827P_0000_00000000000_000003461004226; 89000020240000766001520240649838P_0000_00000000000_000003461004226; 89000020240000766001520240649839P_0000_00000000000_000003461004226; 89000020240000766001520240649873P_0000_00000000000_000003461004226; 89000020240000766001520240649874P_0000_00000000000_000003461004226; 89000020240000766001520240649875P_0000_00000000000_000003461004226; 89000020240000766001520240649894P_0000_00000000000_000003461004226; 89000020240000766001520240649898P_0000_00000000000_000003461004226; 89000020240000766001520240649899P_0000_00000000000_000003461004226; 89000020240000766001520240649900P_0000_00000000000_000003461004226; 89000020240000766001520240649901P_0000_00000000000_000003461004226; 89000020240000766001520240649909P_0000_00000000000_000003461004226; 89000020240000766001520240649910P_0000_00000000000_000003461004226; 89000020240000766001520240649911P_0000_00000000000_000003461004226; 89000020240000766001520240649912P_0000_00000000000_000003461004226; 89000020240000766001520240649913P_0000_00000000000_000003461004226; 89000020240000766001520240649914P_0000_00000000000_000003461004226; 89000020240000766001520240649915P_0000_00000000000_000003461004226; 89000020240000766001520240649916P_0000_00000000000_000003461004226; 89000020240000766001520240649917P_0000_00000000000_000003461004226; 89000020240000766001520240649918P_0000_00000000000_000003461004226; 89000020240000766001520240649919P_0000_00000000000_000003461004226; 89000020240000766001520240649920P_0000_00000000000_000003461004226; 89000020240000766001520240649921P_0000_00000000000_000003461004226; 89000020240000766001520240649942P_0000_00000000000_000003461004226; 89000020240000766001520240649943P_0000_00000000000_000003461004226; 89000020240000766001520240649944P_0000_00000000000_000003461004226; 89000020240000766001520240649945P_0000_00000000000_000003461004226; 89000020240000766001520240649946P_0000_00000000000_000003461004226; 89000020240000766001520240650004P_0000_00000000000_000003461004226; 89000020240000766001520240650005P_0000_00000000000_000003461004226; 89000020240000766001520240650006P_0000_00000000000_000003461004226; 89000020240000766001520240650007P_0000_00000000000_000003461004226; 89000020240000766001520240650008P_0000_00000000000_000003461004226; 89000020240000766001520240650009P_0000_00000000000_000003461004226; 89000020240000766001520240650010P_0000_00000000000_000003461004226; 89000020240000766001520240650011P_0000_00000000000_000003461004226; 89000020240000766001520240650116P_0000_00000000000_000003461004226; 89000020240000766001520240650192P_0000_00000000000_000003461004226; 89000020240000766001520240650202P_0000_00000000000_000003461004226; 89000020240000766001520240650203P_0000_00000000000_000003461004226; 89000020240000766001520240650204P_0000_00000000000_000003461004226; 89000020240000766001520240650205P_0000_00000000000_000003461004226; 89000020240000766001520240650206P_0000_00000000000_000003461004226; 89000020240000766001520240650207P_0000_00000000000_000003461004226; 89000020240000766001520240650208P_0000_00000000000_000003461004226; 89000020240000766001520240650349P_0000_00000000000_000003461004226; 89000020240000766001520240650350P_0000_00000000000_000003461004226; 89000020240000766001520240650351P_0000_00000000000_000003461004226; 89000020240000766001520240650352P_0000_00000000000_000003461004226; 89000020240000766001520240650353P_0000_00000000000_000003461004226; 89000020240000766001520240650354P_0000_00000000000_000003461004226; 89000020240000766001520240650355P_0000_00000000000_000003461004226; 89000020240000766001520240650356P_0000_00000000000_000003461004226; 89000020240000766001520240650357P_0000_00000000000_000003461004226; 89000020240000766001520240650358P_0000_00000000000_000003461004226; 89000020240000766001520240650359P_0000_00000000000_000003461004226; 89000020240000766001520240650360P_0000_00000000000_000003461004226; 89000020240000766001520240650361P_0000_00000000000_000003461004226; 89000020240000766001520240650362P_0000_00000000000_000003461004226; 89000020240000766001520240650363P_0000_00000000000_000003461004226; 89000020240000766001520240650364P_0000_00000000000_000003461004226; 89000020240000766001520240650365P_0000_00000000000_000003461004226; 89000020240000766001520240650366P_0000_00000000000_000003461004226; 89000020240000766001520240650367P_0000_00000000000_000003461004226; 89000020240000766001520240650368P_0000_00000000000_000003461004226; 89000020240000766001520240650369P_0000_00000000000_000003461004226; 89000020240000766001520240650370P_0000_00000000000_000003461004226; 89000020240000766001520240650371P_0000_00000000000_000003461004226; 89000020240000766001520240650372P_0000_00000000000_000003461004226; 89000020240000766001520240650373P_0000_00000000000_000003461004226; 89000020240000766001520240650374P_0000_00000000000_000003461004226; 89000020240000766001520240650375P_0000_00000000000_000003461004226; 89000020240000766001520240650376P_0000_00000000000_000003461004226; 89000020240000766001520240650377P_0000_00000000000_000003461004226; 89000020240000766001520240650378P_0000_00000000000_000003461004226; 89000020240000766001520240650379P_0000_00000000000_000003461004226; 89000020240000766001520240650380P_0000_00000000000_000003461004226; 89000020240000766001520240650381P_0000_00000000000_000003461004226; 89000020240000766001520240650382P_0000_00000000000_000003461004226; 89000020240000766001520240650383P_0000_00000000000_000003461004226; 89000020240000766001520240650384P_0000_00000000000_000003461004226; 89000020240000766001520240650385P_0000_00000000000_000003461004226; 89000020240000766001520240650386P_0000_00000000000_000003461004226; 89000020240000766001520240650387P_0000_00000000000_000003461004226; 89000020240000766001520240650388P_0000_00000000000_000003461004226; 89000020240000766001520240650389P_0000_00000000000_000003461004226; 89000020240000766001520240650390P_0000_00000000000_000003461004226; 89000020240000766001520240650391P_0000_00000000000_000003461004226; 89000020240000766001520240650392P_0000_00000000000_000003461004226; 89000020240000766001520240650393P_0000_00000000000_000003461004226; 89000020240000766001520240650394P_0000_00000000000_000003461004226; 89000020240000766001520240650396P_0000_00000000000_000003461004226; 89000020240000766001520240650397P_0000_00000000000_000003461004226; 89000020240000766001520240650398P_0000_00000000000_000003461004226; 89000020240000766001520240650399P_0000_00000000000_000003461004226; 89000020240000766001520240650400P_0000_00000000000_000003461004226; 89000020240000766001520240650401P_0000_00000000000_000003461004226; 89000020240000766001520240650402P_0000_00000000000_000003461004226; 89000020240000766001520240650403P_0000_00000000000_000003461004226; 89000020240000766001520240650404P_0000_00000000000_000003461004226; 89000020240000766001520240650405P_0000_00000000000_000003461004226; 89000020240000766001520240650406P_0000_00000000000_000003461004226; 89000020240000766001520240650407P_0000_00000000000_000003461004226; 89000020240000766001520240650408P_0000_00000000000_000003461004226; 89000020240000766001520240650409P_0000_00000000000_000003461004226; 89000020240000766001520240650410P_0000_00000000000_000003461004226; 89000020240000766001520240650411P_0000_00000000000_000003461004226; 89000020240000766001520240650412P_0000_00000000000_000003461004226; 89000020240000766001520240650413P_0000_00000000000_000003461004226; 89000020240000766001520240650414P_0000_00000000000_000003461004226; 89000020240000766001520240650415P_0000_00000000000_000003461004226; 89000020240000766001520240650416P_0000_00000000000_000003461004226; 89000020240000766001520240650417P_0000_00000000000_000003461004226; 89000020240000766001520240650418P_0000_00000000000_000003461004226; 89000020240000766001520240650419P_0000_00000000000_000003461004226; 89000020240000766001520240650420P_0000_00000000000_000003461004226; 89000020240000766001520240650421P_0000_00000000000_000003461004226; 89000020240000766001520240650422P_0000_00000000000_000003461004226; 89000020240000766001520240650423P_0000_00000000000_000003461004226; 89000020240000766001520240650424P_0000_00000000000_000003461004226; 89000020240000766001520240650425P_0000_00000000000_000003461004226; 89000020240000766001520240650426P_0000_00000000000_000003461004226; 89000020240000766001520240650427P_0000_00000000000_000003461004226; 89000020240000766001520240650428P_0000_00000000000_000003461004226; 89000020240000766001520240650429P_0000_00000000000_000003461004226; 89000020240000766001520240650431P_0000_00000000000_000003461004226; 89000020240000766001520240650432P_0000_00000000000_000003461004226; 89000020240000766001520240650433P_0000_00000000000_000003461004226; 89000020240000766001520240650434P_0000_00000000000_000003461004226; 89000020240000766001520240650435P_0000_00000000000_000003461004226; 89000020240000766001520240650436P_0000_00000000000_000003461004226; 89000020240000766001520240650476P_0000_00000000000_000003461004226; 89000020240000766001520240650477P_0000_00000000000_000003461004226; 89000020240000766001520240650478P_0000_00000000000_000003461004226; 89000020240000766001520240650479P_0000_00000000000_000003461004226; 89000020240000766001520240650480P_0000_00000000000_000003461004226; 89000020240000766001520240650481P_0000_00000000000_000003461004226; 89000020240000766001520240650482P_0000_00000000000_000003461004226; 89000020240000766001520240650483P_0000_00000000000_000003461004226; 89000020240000766001520240650484P_0000_00000000000_000003461004226; 89000020240000766001520240650485P_0000_00000000000_000003461004226; 89000020240000766001520240650486P_0000_00000000000_000003461004226; 89000020240000766001520240650487P_0000_00000000000_000003461004226; 89000020240000766001520240650488P_0000_00000000000_000003461004226; 89000020240000766001520240650489P_0000_00000000000_000003461004226; 89000020240000766001520240650490P_0000_00000000000_000003461004226; 89000020240000766001520240650491P_0000_00000000000_000003461004226; 89000020240000766001520240650492P_0000_00000000000_000003461004226; 89000020240000766001520240650493P_0000_00000000000_000003461004226; 89000020240000766001520240650494P_0000_00000000000_000003461004226; 89000020240000766001520240650495P_0000_00000000000_000003461004226; 89000020240000766001520240650496P_0000_00000000000_000003461004226; 89000020240000766001520240650497P_0000_00000000000_000003461004226; 89000020240000766001520240650498P_0000_00000000000_000003461004226; 89000020240000766001520240650499P_0000_00000000000_000003461004226; 89000020240000766001520240650500P_0000_00000000000_000003461004226; 89000020240000766001520240650501P_0000_00000000000_000003461004226; 89000020240000766001520240650502P_0000_00000000000_000003461004226; 89000020240000766001520240650503P_0000_00000000000_000003461004226; 89000020240000766001520240650504P_0000_00000000000_000003461004226; 89000020240000766001520240650505P_0000_00000000000_000003461004226; 89000020240000766001520240650506P_0000_00000000000_000003461004226; 89000020240000766001520240650507P_0000_00000000000_000003461004226; 89000020240000766001520240650508P_0000_00000000000_000003461004226; 89000020240000766001520240650509P_0000_00000000000_000003461004226; 89000020240000766001520240650510P_0000_00000000000_000003461004226; 89000020240000766001520240650511P_0000_00000000000_000003461004226; 89000020240000766001520240650512P_0000_00000000000_000003461004226; 89000020240000766001520240650513P_0000_00000000000_000003461004226; 89000020240000766001520240650514P_0000_00000000000_000003461004226; 89000020240000766001520240650515P_0000_00000000000_000003461004226; 89000020240000766001520240650516P_0000_00000000000_000003461004226; 89000020240000766001520240650517P_0000_00000000000_000003461004226; 89000020240000766001520240650518P_0000_00000000000_000003461004226; 89000020240000766001520240650519P_0000_00000000000_000003461004226; 89000020240000766001520240650520P_0000_00000000000_000003461004226; 89000020240000766001520240650521P_0000_00000000000_000003461004226; 89000020240000766001520240650522P_0000_00000000000_000003461004226; 89000020240000766001520240650523P_0000_00000000000_000003461004226; 89000020240000766001520240650524P_0000_00000000000_000003461004226; 89000020240000766001520240650525P_0000_00000000000_000003461004226; 89000020240000766001520240650526P_0000_00000000000_000003461004226; 89000020240000766001520240650527P_0000_00000000000_000003461004226; 89000020240000766001520240650528P_0000_00000000000_000003461004226; 89000020240000766001520240650529P_0000_00000000000_000003461004226; 89000020240000766001520240650530P_0000_00000000000_000003461004226; 89000020240000766001520240650531P_0000_00000000000_000003461004226; 89000020240000766001520240650532P_0000_00000000000_000003461004226; 89000020240000766001520240650533P_0000_00000000000_000003461004226; 89000020240000766001520240650534P_0000_00000000000_000003461004226; 89000020240000766001520240650535P_0000_00000000000_000003461004226; 89000020240000766001520240650536P_0000_00000000000_000003461004226; 89000020240000766001520240650537P_0000_00000000000_000003461004226; 89000020240000766001520240650538P_0000_00000000000_000003461004226; 89000020240000766001520240650539P_0000_00000000000_000003461004226; 89000020240000766001520240650540P_0000_00000000000_000003461004226; 89000020240000766001520240650541P_0000_00000000000_000003461004226; 89000020240000766001520240650542P_0000_00000000000_000003461004226; 89000020240000766001520240650543P_0000_00000000000_000003461004226; 89000020240000766001520240650544P_0000_00000000000_000003461004226; 89000020240000766001520240650545P_0000_00000000000_000003461004226; 89000020240000766001520240650546P_0000_00000000000_000003461004226; 89000020240000766001520240650547P_0000_00000000000_000003461004226; 89000020240000766001520240650548P_0000_00000000000_000003461004226; 89000020240000766001520240650549P_0000_00000000000_000003461004226; 89000020240000766001520240650550P_0000_00000000000_000003461004226; 89000020240000766001520240650551P_0000_00000000000_000003461004226; 89000020240000766001520240650552P_0000_00000000000_000003461004226; 89000020240000766001520240650553P_0000_00000000000_000003461004226; 89000020240000766001520240650554P_0000_00000000000_000003461004226; 89000020240000766001520240650555P_0000_00000000000_000003461004226; 89000020240000766001520240650556P_0000_00000000000_000003461004226; 89000020240000766001520240650557P_0000_00000000000_000003461004226; 89000020240000766001520240650558P_0000_00000000000_000003461004226; 89000020240000766001520240650559P_0000_00000000000_000003461004226; 89000020240000766001520240650560P_0000_00000000000_000003461004226; 89000020240000766001520240650561P_0000_00000000000_000003461004226; 89000020240000766001520240650562P_0000_00000000000_000003461004226; 89000020240000766001520240650563P_0000_00000000000_000003461004226; 89000020240000766001520240650564P_0000_00000000000_000003461004226; 89000020240000766001520240650565P_0000_00000000000_000003461004226; 89000020240000766001520240650566P_0000_00000000000_000003461004226; 89000020240000766001520240650567P_0000_00000000000_000003461004226; 89000020240000766001520240650568P_0000_00000000000_000003461004226; 89000020240000766001520240650569P_0000_00000000000_000003461004226; 89000020240000766001520240650783P_0000_00000000000_000003461004226; 89000020240000766001520240650784P_0000_00000000000_000003461004226; 89000020240000766001520240650785P_0000_00000000000_000003461004226; 89000020240000766001520240650786P_0000_00000000000_000003461004226; 89000020240000766001520240650787P_0000_00000000000_000003461004226; 89000020240000766001520240650788P_0000_00000000000_000003461004226; 89000020240000766001520240650851P_0000_00000000000_000003461004226; 89000020240000766001520240650853P_0000_00000000000_000003461004226; 89000020240000766001520240650865P_0000_00000000000_000003461004226; 89000020240000766001520240650868P_0000_00000000000_000003461004226; 89000020240000766001520240650869P_0000_00000000000_000003461004226; 89000020240000766001520240650873P_0000_00000000000_000003461004226; 89000020240000766001520240650875P_0000_00000000000_000003461004226; 89000020240000766001520240650930P_0000_00000000000_000003461004226; 89000020240000766001520240650947P_0000_00000000000_000003461004226; 89000020240000766001520240650948P_0000_00000000000_000003461004226; 89000020240000766001520240650949P_0000_00000000000_000003461004226; 89000020240000766001520240650950P_0000_00000000000_000003461004226; 89000020240000766001520240650951P_0000_00000000000_000003461004226; 89000020240000766001520240650952P_0000_00000000000_000003461004226; 89000020240000766001520240650953P_0000_00000000000_000003461004226; 89000020240000766001520240650954P_0000_00000000000_000003461004226; 89000020240000766001520240650955P_0000_00000000000_000003461004226; 89000020240000766001520240650956P_0000_00000000000_000003461004226; 89000020240000766001520240650957P_0000_00000000000_000003461004226; 89000020240000766001520240650958P_0000_00000000000_000003461004226; 89000020240000766001520240650959P_0000_00000000000_000003461004226; 89000020240000766001520240650960P_0000_00000000000_000003461004226; 89000020240000766001520240650961P_0000_00000000000_000003461004226; 89000020240000766001520240650962P_0000_00000000000_000003461004226; 89000020240000766001520240650968P_0000_00000000000_000003461004226; 89000020240000766001520240650969P_0000_00000000000_000003461004226; 89000020240000766001520240650970P_0000_00000000000_000003461004226; 89000020240000766001520240650971P_0000_00000000000_000003461004226; 89000020240000766001520240650972P_0000_00000000000_000003461004226; 89000020240000766001520240650973P_0000_00000000000_000003461004226; 89000020240000766001520240650974P_0000_00000000000_000003461004226; 89000020240000766001520240650975P_0000_00000000000_000003461004226; 89000020240000766001520240650976P_0000_00000000000_000003461004226; 89000020240000766001520240650978P_0000_00000000000_000003461004226; 89000020240000766001520240650979P_0000_00000000000_000003461004226; 89000020240000766001520240650980P_0000_00000000000_000003461004226; 89000020240000766001520240650981P_0000_00000000000_000003461004226; 89000020240000766001520240650982P_0000_00000000000_000003461004226; 89000020240000766001520240650983P_0000_00000000000_000003461004226; 89000020240000766001520240650984P_0000_00000000000_000003461004226; 89000020240000766001520240650985P_0000_00000000000_000003461004226; 89000020240000766001520240650986P_0000_00000000000_000003461004226; 89000020240000766001520240650987P_0000_00000000000_000003461004226; 89000020240000766001520240650988P_0000_00000000000_000003461004226; 89000020240000766001520240650989P_0000_00000000000_000003461004226; 89000020240000766001520240650990P_0000_00000000000_000003461004226; 89000020240000766001520240650991P_0000_00000000000_000003461004226; 89000020240000766001520240650992P_0000_00000000000_000003461004226; 89000020240000766001520240650993P_0000_00000000000_000003461004226; 89000020240000766001520240650994P_0000_00000000000_000003461004226; 89000020240000766001520240650995P_0000_00000000000_000003461004226; 89000020240000766001520240650996P_0000_00000000000_000003461004226; 89000020240000766001520240650997P_0000_00000000000_000003461004226; 89000020240000766001520240650998P_0000_00000000000_000003461004226; 89000020240000766001520240650999P_0000_00000000000_000003461004226; 89000020240000766001520240651000P_0000_00000000000_000003461004226; 89000020240000766001520240651001P_0000_00000000000_000003461004226; 89000020240000766001520240651002P_0000_00000000000_000003461004226; 89000020240000766001520240651003P_0000_00000000000_000003461004226; 89000020240000766001520240651004P_0000_00000000000_000003461004226; 89000020240000766001520240651005P_0000_00000000000_000003461004226; 89000020240000766001520240651006P_0000_00000000000_000003461004226; 89000020240000766001520240651020P_0000_00000000000_000003461004226; 89000020240000766001520240651095P_0000_00000000000_000003461004226; 89000020240000766001520240651174P_0000_00000000000_000003461004226; 89000020240000766001520240651175P_0000_00000000000_000003461004226; 89000020240000766001520240651177P_0000_00000000000_000003461004226; 89000020240000766001520240651179P_0000_00000000000_000003461004226; 89000020240000766001520240651180P_0000_00000000000_000003461004226; 89000020240000766001520240651187P_0000_00000000000_000003461004226; 89000020240000766001520240651188P_0000_00000000000_000003461004226; 89000020240000766001520240651189P_0000_00000000000_000003461004226; 89000020240000766001520240651190P_0000_00000000000_000003461004226; 89000020240000766001520240651192P_0000_00000000000_000003461004226; 89000020240000766001520240651193P_0000_00000000000_000003461004226; 89000020240000766001520240651194P_0000_00000000000_000003461004226; 89000020240000766001520240651195P_0000_00000000000_000003461004226; 89000020240000766001520240651196P_0000_00000000000_000003461004226; 89000020240000766001520240651197P_0000_00000000000_000003461004226; 89000020240000766001520240651198P_0000_00000000000_000003461004226; 89000020240000766001520240651199P_0000_00000000000_000003461004226; 89000020240000766001520240651200P_0000_00000000000_000003461004226; 89000020240000766001520240651201P_0000_00000000000_000003461004226; 89000020240000766001520240651202P_0000_00000000000_000003461004226; 89000020240000766001520240651203P_0000_00000000000_000003461004226; 89000020240000766001520240651204P_0000_00000000000_000003461004226; 89000020240000766001520240651307P_0000_00000000000_000003461004226; 89000020240000766001520240651409P_0000_00000000000_000003461004226; 89000020240000766001520240651410P_0000_00000000000_000003461004226; 89000020240000766001520240651411P_0000_00000000000_000003461004226; 89000020240000766001520240651412P_0000_00000000000_000003461004226; 89000020240000766001520240651444P_0000_00000000000_000003461004226; 89000020240000766001520240651449P_0000_00000000000_000003461004226; 89000020240000766001520240651453P_0000_00000000000_000003461004226; 89000020240000766001520240651454P_0000_00000000000_000003461004226; 89000020240000766001520240651455P_0000_00000000000_000003461004226; 89000020240000766001520240651456P_0000_00000000000_000003461004226; 89000020240000766001520240651464P_0000_00000000000_000003461004226; 89000020240000766001520240651468P_0000_00000000000_000003461004226; 89000020240000766001520240651470P_0000_00000000000_000003461004226; 89000020240000766001520240651471P_0000_00000000000_000003461004226; 89000020240000766001520240651473P_0000_00000000000_000003461004226; 89000020240000766001520240651474P_0000_00000000000_000003461004226; 89000020240000766001520240651475P_0000_00000000000_000003461004226; 89000020240000766001520240651476P_0000_00000000000_000003461004226; 89000020240000766001520240651477P_0000_00000000000_000003461004226; 89000020240000766001520240651643P_0000_00000000000_000003461004226; 89000020240000766001520240651644P_0000_00000000000_000003461004226; 89000020240000766001520240651645P_0000_00000000000_000003461004226; 89000020240000766001520240651684P_0000_00000000000_000003461004226; 89000020240000766001520240651693P_0000_00000000000_000003461004226; 89000020240000766001520240651694P_0000_00000000000_000003461004226; 89000020240000766001520240651695P_0000_00000000000_000003461004226; 89000020240000766001520240651696P_0000_00000000000_000003461004226; 89000020240000766001520240651697P_0000_00000000000_000003461004226; 89000020240000766001520240651698P_0000_00000000000_000003461004226; 89000020240000766001520240651699P_0000_00000000000_000003461004226; 89000020240000766001520240651700P_0000_00000000000_000003461004226; 89000020240000766001520240651701P_0000_00000000000_000003461004226; 89000020240000766001520240651702P_0000_00000000000_000003461004226; 89000020240000766001520240651706P_0000_00000000000_000003461004226; 89000020240000766001520240651707P_0000_00000000000_000003461004226; 89000020240000766001520240651708P_0000_00000000000_000003461004226; 89000020240000766001520240651709P_0000_00000000000_000003461004226; 89000020240000766001520240651710P_0000_00000000000_000003461004226; 89000020240000766001520240651711P_0000_00000000000_000003461004226; 89000020240000766001520240651712P_0000_00000000000_000003461004226; 89000020240000766001520240651713P_0000_00000000000_000003461004226; 89000020240000766001520240651714P_0000_00000000000_000003461004226; 89000020240000766001520240651715P_0000_00000000000_000003461004226; 89000020240000766001520240651716P_0000_00000000000_000003461004226; 89000020240000766001520240651717P_0000_00000000000_000003461004226; 89000020240000766001520240651718P_0000_00000000000_000003461004226; 89000020240000766001520240651719P_0000_00000000000_000003461004226; 89000020240000766001520240651720P_0000_00000000000_000003461004226; 89000020240000766001520240651721P_0000_00000000000_000003461004226; 89000020240000766001520240651722P_0000_00000000000_000003461004226; 89000020240000766001520240651723P_0000_00000000000_000003461004226; 89000020240000766001520240651727P_0000_00000000000_000003461004226; 89000020240000766001520240651728P_0000_00000000000_000003461004226; 89000020240000766001520240651729P_0000_00000000000_000003461004226; 89000020240000766001520240651730P_0000_00000000000_000003461004226; 89000020240000766001520240651731P_0000_00000000000_000003461004226; 89000020240000766001520240651732P_0000_00000000000_000003461004226; 89000020240000766001520240651733P_0000_00000000000_000003461004226; 89000020240000766001520240651849P_0000_00000000000_000003461004226; 89000020240000766001520240651857P_0000_00000000000_000003461004226; 89000020240000766001520240651867P_0000_00000000000_000003461004226; 89000020240000766001520240651870P_0000_00000000000_000003461004226; 89000020240000766001520240651874P_0000_00000000000_000003461004226; 89000020240000766001520240651875P_0000_00000000000_000003461004226; 89000020240000766001520240651877P_0000_00000000000_000003461004226; 89000020240000766001520240651881P_0000_00000000000_000003461004226; 89000020240000766001520240651883P_0000_00000000000_000003461004226; 89000020240000766001520240651918P_0000_00000000000_000003461004226; 89000020240000766001520240652005P_0000_00000000000_000003461004226; 89000020240000766001520240652043P_0000_00000000000_000003461004226; 89000020240000766001520240652066P_0000_00000000000_000003461004226; 89000020240000766001520240652067P_0000_00000000000_000003461004226; 89000020240000766001520240652070P_0000_00000000000_000003461004226; 89000020240000766001520240652072P_0000_00000000000_000003461004226; 89000020240000766001520240652073P_0000_00000000000_000003461004226; 89000020240000766001520240652165P_0000_00000000000_000003461004226; 89000020240000766001520240652311P_0000_00000000000_000003461004226; 89000020240000766001520240652312P_0000_00000000000_000003461004226; 89000020240000766001520240652313P_0000_00000000000_000003461004226; 89000020240000766001520240652314P_0000_00000000000_000003461004226; 89000020240000766001520240652315P_0000_00000000000_000003461004226; 89000020240000766001520240652316P_0000_00000000000_000003461004226; 89000020240000766001520240652317P_0000_00000000000_000003461004226; 89000020240000766001520240652318P_0000_00000000000_000003461004226; 89000020240000766001520240652319P_0000_00000000000_000003461004226; 89000020240000766001520240652320P_0000_00000000000_000003461004226; 89000020240000766001520240652321P_0000_00000000000_000003461004226; 89000020240000766001520240652322P_0000_00000000000_000003461004226; 89000020240000766001520240652323P_0000_00000000000_000003461004226; 89000020240000766001520240652342P_0000_00000000000_000003461004226; 89000020240000766001520240652343P_0000_00000000000_000003461004226; 89000020240000766001520240652344P_0000_00000000000_000003461004226; 89000020240000766001520240652345P_0000_00000000000_000003461004226; 89000020240000766001520240652347P_0000_00000000000_000003461004226; 89000020240000766001520240652348P_0000_00000000000_000003461004226; 89000020240000766001520240652349P_0000_00000000000_000003461004226; 89000020240000766001520240652352P_0000_00000000000_000003461004226; 89000020240000766001520240652353P_0000_00000000000_000003461004226; 89000020240000766001520240652354P_0000_00000000000_000003461004226; 89000020240000766001520240652365P_0000_00000000000_000003461004226; 89000020240000766001520240652370P_0000_00000000000_000003461004226; 89000020240000766001520240652371P_0000_00000000000_000003461004226; 89000020240000766001520240652372P_0000_00000000000_000003461004226; 89000020240000766001520240652373P_0000_00000000000_000003461004226; 89000020240000766001520240652374P_0000_00000000000_000003461004226; 89000020240000766001520240652375P_0000_00000000000_000003461004226; 89000020240000766001520240652376P_0000_00000000000_000003461004226; 89000020240000766001520240652377P_0000_00000000000_000003461004226; 89000020240000766001520240652379P_0000_00000000000_000003461004226; 89000020240000766001520240652387P_0000_00000000000_000003461004226; 89000020240000766001520240652388P_0000_00000000000_000003461004226; 89000020240000766001520240652389P_0000_00000000000_000003461004226; 89000020240000766001520240652390P_0000_00000000000_000003461004226; 89000020240000766001520240652391P_0000_00000000000_000003461004226; 89000020240000766001520240652392P_0000_00000000000_000003461004226; 89000020240000766001520240652393P_0000_00000000000_000003461004226; 89000020240000766001520240652394P_0000_00000000000_000003461004226; 89000020240000766001520240652439P_0000_00000000000_000003461004226; 89000020240000766001520240652440P_0000_00000000000_000003461004226; 89000020240000766001520240652441P_0000_00000000000_000003461004226; 89000020240000766001520240652442P_0000_00000000000_000003461004226; 89000020240000766001520240652443P_0000_00000000000_000003461004226; 89000020240000766001520240652444P_0000_00000000000_000003461004226; 89000020240000766001520240652445P_0000_00000000000_000003461004226; 89000020240000766001520240652446P_0000_00000000000_000003461004226; 89000020240000766001520240652447P_0000_00000000000_000003461004226; 89000020240000766001520240652448P_0000_00000000000_000003461004226; 89000020240000766001520240652449P_0000_00000000000_000003461004226; 89000020240000766001520240652450P_0000_00000000000_000003
A91: 2025-10-31 | B91: MIS_B0500_C0080 | C91: MISSINGS | D91: Validar que não existem registos por preencher (Missings) | E91: BU_LOANTAPE_WORK.OUT_B0500_GUARANTEES | F91: 0080_AMNT_CLLTRL | G91: 4730 | H91: 0
A92: 2025-10-31 | B92: MIS_B0500_C0090 | C92: MISSINGS | D92: Validar que não existem registos por preencher (Missings) | E92: BU_LOANTAPE_WORK.OUT_B0500_GUARANTEES | F92: 0090_GUARANTEE_TRGGR | G92: 4730 | H92: 0
A93: 2025-10-31 | B93: MIS_B0500_C0100 | C93: MISSINGS | D93: Validar que não existem registos por preencher (Missings) | E93: BU_LOANTAPE_WORK.OUT_B0500_GUARANTEES | F93: 0100_DT_MTRTY_CLLTRL | G93: 4730 | H93: 0
A94: 2025-10-31 | B94: MIS_B0500_C0110 | C94: MISSINGS | D94: Validar que não existem registos por preencher (Missings) | E94: BU_LOANTAPE_WORK.OUT_B0500_GUARANTEES | F94: 0110_SCRTS_CLLTRL_ID | G94: 4730 | H94: 0
A95: 2025-10-31 | B95: MIS_B0500_C0120 | C95: MISSINGS | D95: Validar que não existem registos por preencher (Missings) | E95: BU_LOANTAPE_WORK.OUT_B0500_GUARANTEES | F95: 0120_TYP_CLLTRLZTN | G95: 4730 | H95: 0
A96: 2025-10-31 | B96: MIS_B0500_C0130 | C96: MISSINGS | D96: Validar que não existem registos por preencher (Missings) | E96: BU_LOANTAPE_WORK.OUT_B0500_GUARANTEES | F96: 0130_TYP_PRTCTN_VL | G96: 4730 | H96: 0
A97: 2025-10-31 | B97: MIS_B0500_C0140 | C97: MISSINGS | D97: Validar que não existem registos por preencher (Missings) | E97: BU_LOANTAPE_WORK.OUT_B0500_GUARANTEES | F97: 0140_DT_VLTN_SCRTY | G97: 4730 | H97: 0
A98: 2025-10-31 | B98: MIS_B0500_C0150 | C98: MISSINGS | D98: Validar que não existem registos por preencher (Missings) | E98: BU_LOANTAPE_WORK.OUT_B0500_GUARANTEES | F98: 0150_PRTCTN_VLTN_APPRCH | G98: 4730 | H98: 0
A99: 2025-10-31 | B99: MIS_B9000_C0010 | C99: MISSINGS | D99: Validar que não existem registos por preencher (Missings) | E99: BU_LOANTAPE_WORK.OUT_B9000_COUNTERPARTIES | F99: 0010_ROW_NMBR | G99: 4740 | H99: 0
A100: 2025-10-31 | B100: MIS_B9000_C0011 | C100: MISSINGS | D100: Validar que não existem registos por preencher (Missings) | E100: BU_LOANTAPE_WORK.OUT_B9000_COUNTERPARTIES | F100: 0011_TAB_ORIGIN | G100: 4740 | H100: 0
A101: 2025-10-31 | B101: MIS_B9000_C0020 | C101: MISSINGS | D101: Validar que não existem registos por preencher (Missings) | E101: BU_LOANTAPE_WORK.OUT_B9000_COUNTERPARTIES | F101: 0020_UNIQ_ID_KNWN_CNTRPRTY | G101: 4740 | H101: 0
A102: 2025-10-31 | B102: MIS_B9000_C0030 | C102: MISSINGS | D102: Validar que não existem registos por preencher (Missings) | E102: BU_LOANTAPE_WORK.OUT_B9000_COUNTERPARTIES | F102: 0030_CNTRPRTY_RSLTN_GRP | G102: 4740 | H102: 4740 | I102: PTBSRDOM0037, 0000003686; PTBSREOM0028, Not applicable; PTCPP0AM0007, Not applicable; PTCPP0AM0007, 0000003686; PTCPP0AM0007, 5100011001; PTSTOCOM0007, 0000003686; PTSTOEOM0021, 0000003686; PTSTOFOM0004, 0000003686; PTSTOGOM0003, 0000003686; PTSTOHOM0002, 0000003686; 31000000000000000962304890482490P_0000_00000000000_000006511000505, 6511000505; 31000304140330096000000000000000P_0000_00000000000_000000000003686, 0000003686; 31000307044893096000000000000000P_0000_00000000000_000000000003686, 0000003686; 31000307530917096000000000000000P_0000_00000000000_000000000003686, 0000003686; 31000311450813096000000000000000P_0000_00000000000_000000000003686, 0000003686; 31000311847794096000000000000000P_0000_00000000000_000000000003686, 0000003686; 31000313517171096000000000000000P_0000_00000000000_000000000003686, 0000003686; 31000315970006096000000000000000P_0000_00000000000_000000000003686, 0000003686; 31000315970121096000000000000000P_0000_00000000000_000000000003686, 0000003686; 31000315970139096000000000000000P_0000_00000000000_000000000003686, 0000003686; 31000315970188096000000000000000P_0000_00000000000_000000000003686, 0000003686; 31000315970212096000000000000000P_0000_00000000000_000000000003686, 0000003686; 31000315970238096000000000000000P_0000_00000000000_000000000003686, 0000003686; 31000315970261096000000000000000P_0000_00000000000_000000000003686, 0000003686; 31000315970279096000000000000000P_0000_00000000000_000000000003686, 0000003686; 31000315970311096000000000000000P_0000_00000000000_000000000003686, 0000003686; 31000315970329096000000000000000P_0000_00000000000_000000000003686, 0000003686; 31000315970345096000000000000000P_0000_00000000000_000000000003686, 0000003686; 31000315970402096000000000000000P_0000_00000000000_000000000003686, 0000003686; 31000315970428096000000000000000P_0000_00000000000_000000000003686, 0000003686; 31000315970469096000000000000000P_0000_00000000000_000000000003686, 0000003686; 31000315979890096000000000000000P_0000_00000000000_000006511000505, 6511000505; 31000318293090097000000000000000P_0000_00000000000_000008000176024, 8000176024; 31000318542009097000000000000000P_0000_00000000000_000006511000505, 6511000505; 31000318628196097000000000000000P_0000_00000000000_000006511000505, 6511000505; 31000318628592097000000000000000P_0000_00000000000_000008000176024, 8000176024; 31000318629012097000000000000000P_0000_00000000000_000008000176024, 8000176024; 31000318636603097000000000000000P_0000_00000000000_000008000176024, 8000176024; 31000318637213097000000000000000P_0000_00000000000_000008000176024, 8000176024; 31000322311418096000000000000000P_0000_00000000000_000000000003686, 0000003686; 89000020240000766001520240649818P_0000_00000000000_000003461004226, 3461004226; 89000020240000766001520240649824P_0000_00000000000_000003461004226, 3461004226; 89000020240000766001520240649825P_0000_00000000000_000003461004226, 3461004226; 89000020240000766001520240649826P_0000_00000000000_000003461004226, 3461004226; 89000020240000766001520240649827P_0000_00000000000_000003461004226, 3461004226; 89000020240000766001520240649838P_0000_00000000000_000003461004226, 3461004226; 89000020240000766001520240649839P_0000_00000000000_000003461004226, 3461004226; 89000020240000766001520240649873P_0000_00000000000_000003461004226, 3461004226; 89000020240000766001520240649874P_0000_00000000000_000003461004226, 3461004226; 89000020240000766001520240649875P_0000_00000000000_000003461004226, 3461004226; 89000020240000766001520240649894P_0000_00000000000_000003461004226, 3461004226; 89000020240000766001520240649898P_0000_00000000000_000003461004226, 3461004226; 89000020240000766001520240649899P_0000_00000000000_000003461004226, 3461004226; 89000020240000766001520240649900P_0000_00000000000_000003461004226, 3461004226; 89000020240000766001520240649901P_0000_00000000000_000003461004226, 3461004226; 89000020240000766001520240649909P_0000_00000000000_000003461004226, 3461004226; 89000020240000766001520240649910P_0000_00000000000_000003461004226, 3461004226; 89000020240000766001520240649911P_0000_00000000000_000003461004226, 3461004226; 89000020240000766001520240649912P_0000_00000000000_000003461004226, 3461004226; 89000020240000766001520240649913P_0000_00000000000_000003461004226, 3461004226; 89000020240000766001520240649914P_0000_00000000000_000003461004226, 3461004226; 89000020240000766001520240649915P_0000_00000000000_000003461004226, 3461004226; 89000020240000766001520240649916P_0000_00000000000_000003461004226, 3461004226; 89000020240000766001520240649917P_0000_00000000000_000003461004226, 3461004226; 89000020240000766001520240649918P_0000_00000000000_000003461004226, 3461004226; 89000020240000766001520240649919P_0000_00000000000_000003461004226, 3461004226; 89000020240000766001520240649920P_0000_00000000000_000003461004226, 3461004226; 89000020240000766001520240649921P_0000_00000000000_000003461004226, 3461004226; 89000020240000766001520240649942P_0000_00000000000_000003461004226, 3461004226; 89000020240000766001520240649943P_0000_00000000000_000003461004226, 3461004226; 89000020240000766001520240649944P_0000_00000000000_000003461004226, 3461004226; 89000020240000766001520240649945P_0000_00000000000_000003461004226, 3461004226; 89000020240000766001520240649946P_0000_00000000000_000003461004226, 3461004226; 89000020240000766001520240650004P_0000_00000000000_000003461004226, 3461004226; 89000020240000766001520240650005P_0000_00000000000_000003461004226, 3461004226; 89000020240000766001520240650006P_0000_00000000000_000003461004226, 3461004226; 89000020240000766001520240650007P_0000_00000000000_000003461004226, 3461004226; 89000020240000766001520240650008P_0000_00000000000_000003461004226, 3461004226; 89000020240000766001520240650009P_0000_00000000000_000003461004226, 3461004226; 89000020240000766001520240650010P_0000_00000000000_000003461004226, 3461004226; 89000020240000766001520240650011P_0000_00000000000_000003461004226, 3461004226; 89000020240000766001520240650116P_0000_00000000000_000003461004226, 3461004226; 89000020240000766001520240650192P_0000_00000000000_000003461004226, 3461004226; 89000020240000766001520240650202P_0000_00000000000_000003461004226, 3461004226; 89000020240000766001520240650203P_0000_00000000000_000003461004226, 3461004226; 89000020240000766001520240650204P_0000_00000000000_000003461004226, 3461004226; 89000020240000766001520240650205P_0000_00000000000_000003461004226, 3461004226; 89000020240000766001520240650206P_0000_00000000000_000003461004226, 3461004226; 89000020240000766001520240650207P_0000_00000000000_000003461004226, 3461004226; 89000020240000766001520240650208P_0000_00000000000_000003461004226, 3461004226; 89000020240000766001520240650349P_0000_00000000000_000003461004226, 3461004226; 89000020240000766001520240650350P_0000_00000000000_000003461004226, 3461004226; 89000020240000766001520240650351P_0000_00000000000_000003461004226, 3461004226; 89000020240000766001520240650352P_0000_00000000000_000003461004226, 3461004226; 89000020240000766001520240650353P_0000_00000000000_000003461004226, 3461004226; 89000020240000766001520240650354P_0000_00000000000_000003461004226, 3461004226; 89000020240000766001520240650355P_0000_00000000000_000003461004226, 3461004226; 89000020240000766001520240650356P_0000_00000000000_000003461004226, 3461004226; 89000020240000766001520240650357P_0000_00000000000_000003461004226, 3461004226; 89000020240000766001520240650358P_0000_00000000000_000003461004226, 3461004226; 89000020240000766001520240650359P_0000_00000000000_000003461004226, 3461004226; 89000020240000766001520240650360P_0000_00000000000_000003461004226, 3461004226; 89000020240000766001520240650361P_0000_00000000000_000003461004226, 3461004226; 89000020240000766001520240650362P_0000_00000000000_000003461004226, 3461004226; 89000020240000766001520240650363P_0000_00000000000_000003461004226, 3461004226; 89000020240000766001520240650364P_0000_00000000000_000003461004226, 3461004226; 89000020240000766001520240650365P_0000_00000000000_000003461004226, 3461004226; 89000020240000766001520240650366P_0000_00000000000_000003461004226, 3461004226; 89000020240000766001520240650367P_0000_00000000000_000003461004226, 3461004226; 89000020240000766001520240650368P_0000_00000000000_000003461004226, 3461004226; 89000020240000766001520240650369P_0000_00000000000_000003461004226, 3461004226; 89000020240000766001520240650370P_0000_00000000000_000003461004226, 3461004226; 89000020240000766001520240650371P_0000_00000000000_000003461004226, 3461004226; 89000020240000766001520240650372P_0000_00000000000_000003461004226, 3461004226; 89000020240000766001520240650373P_0000_00000000000_000003461004226, 3461004226; 89000020240000766001520240650374P_0000_00000000000_000003461004226, 3461004226; 89000020240000766001520240650375P_0000_00000000000_000003461004226, 3461004226; 89000020240000766001520240650376P_0000_00000000000_000003461004226, 3461004226; 89000020240000766001520240650377P_0000_00000000000_000003461004226, 3461004226; 89000020240000766001520240650378P_0000_00000000000_000003461004226, 3461004226; 89000020240000766001520240650379P_0000_00000000000_000003461004226, 3461004226; 89000020240000766001520240650380P_0000_00000000000_000003461004226, 3461004226; 89000020240000766001520240650381P_0000_00000000000_000003461004226, 3461004226; 89000020240000766001520240650382P_0000_00000000000_000003461004226, 3461004226; 89000020240000766001520240650383P_0000_00000000000_000003461004226, 3461004226; 89000020240000766001520240650384P_0000_00000000000_000003461004226, 3461004226; 89000020240000766001520240650385P_0000_00000000000_000003461004226, 3461004226; 89000020240000766001520240650386P_0000_00000000000_000003461004226, 3461004226; 89000020240000766001520240650387P_0000_00000000000_000003461004226, 3461004226; 89000020240000766001520240650388P_0000_00000000000_000003461004226, 3461004226; 89000020240000766001520240650389P_0000_00000000000_000003461004226, 3461004226; 89000020240000766001520240650390P_0000_00000000000_000003461004226, 3461004226; 89000020240000766001520240650391P_0000_00000000000_000003461004226, 3461004226; 89000020240000766001520240650392P_0000_00000000000_000003461004226, 3461004226; 89000020240000766001520240650393P_0000_00000000000_000003461004226, 3461004226; 89000020240000766001520240650394P_0000_00000000000_000003461004226, 3461004226; 89000020240000766001520240650396P_0000_00000000000_000003461004226, 3461004226; 89000020240000766001520240650397P_0000_00000000000_000003461004226, 3461004226; 89000020240000766001520240650398P_0000_00000000000_000003461004226, 3461004226; 89000020240000766001520240650399P_0000_00000000000_000003461004226, 3461004226; 89000020240000766001520240650400P_0000_00000000000_000003461004226, 3461004226; 89000020240000766001520240650401P_0000_00000000000_000003461004226, 3461004226; 89000020240000766001520240650402P_0000_00000000000_000003461004226, 3461004226; 89000020240000766001520240650403P_0000_00000000000_000003461004226, 3461004226; 89000020240000766001520240650404P_0000_00000000000_000003461004226, 3461004226; 89000020240000766001520240650405P_0000_00000000000_000003461004226, 3461004226; 89000020240000766001520240650406P_0000_00000000000_000003461004226, 3461004226; 89000020240000766001520240650407P_0000_00000000000_000003461004226, 3461004226; 89000020240000766001520240650408P_0000_00000000000_000003461004226, 3461004226; 89000020240000766001520240650409P_0000_00000000000_000003461004226, 3461004226; 89000020240000766001520240650410P_0000_00000000000_000003461004226, 3461004226; 89000020240000766001520240650411P_0000_00000000000_000003461004226, 3461004226; 89000020240000766001520240650412P_0000_00000000000_000003461004226, 3461004226; 89000020240000766001520240650413P_0000_00000000000_000003461004226, 3461004226; 89000020240000766001520240650414P_0000_00000000000_000003461004226, 3461004226; 89000020240000766001520240650415P_0000_00000000000_000003461004226, 3461004226; 89000020240000766001520240650416P_0000_00000000000_000003461004226, 3461004226; 89000020240000766001520240650417P_0000_00000000000_000003461004226, 3461004226; 89000020240000766001520240650418P_0000_00000000000_000003461004226, 3461004226; 89000020240000766001520240650419P_0000_00000000000_000003461004226, 3461004226; 89000020240000766001520240650420P_0000_00000000000_000003461004226, 3461004226; 89000020240000766001520240650421P_0000_00000000000_000003461004226, 3461004226; 89000020240000766001520240650422P_0000_00000000000_000003461004226, 3461004226; 89000020240000766001520240650423P_0000_00000000000_000003461004226, 3461004226; 89000020240000766001520240650424P_0000_00000000000_000003461004226, 3461004226; 89000020240000766001520240650425P_0000_00000000000_000003461004226, 3461004226; 89000020240000766001520240650426P_0000_00000000000_000003461004226, 3461004226; 89000020240000766001520240650427P_0000_00000000000_000003461004226, 3461004226; 89000020240000766001520240650428P_0000_00000000000_000003461004226, 3461004226; 89000020240000766001520240650429P_0000_00000000000_000003461004226, 3461004226; 89000020240000766001520240650431P_0000_00000000000_000003461004226, 3461004226; 89000020240000766001520240650432P_0000_00000000000_000003461004226, 3461004226; 89000020240000766001520240650433P_0000_00000000000_000003461004226, 3461004226; 89000020240000766001520240650434P_0000_00000000000_000003461004226, 3461004226; 89000020240000766001520240650435P_0000_00000000000_000003461004226, 3461004226; 89000020240000766001520240650436P_0000_00000000000_000003461004226, 3461004226; 89000020240000766001520240650476P_0000_00000000000_000003461004226, 3461004226; 89000020240000766001520240650477P_0000_00000000000_000003461004226, 3461004226; 89000020240000766001520240650478P_0000_00000000000_000003461004226, 3461004226; 89000020240000766001520240650479P_0000_00000000000_000003461004226, 3461004226; 89000020240000766001520240650480P_0000_00000000000_000003461004226, 3461004226; 89000020240000766001520240650481P_0000_00000000000_000003461004226, 3461004226; 89000020240000766001520240650482P_0000_00000000000_000003461004226, 3461004226; 89000020240000766001520240650483P_0000_00000000000_000003461004226, 3461004226; 89000020240000766001520240650484P_0000_00000000000_000003461004226, 3461004226; 89000020240000766001520240650485P_0000_00000000000_000003461004226, 3461004226; 89000020240000766001520240650486P_0000_00000000000_000003461004226, 3461004226; 89000020240000766001520240650487P_0000_00000000000_000003461004226, 3461004226; 89000020240000766001520240650488P_0000_00000000000_000003461004226, 3461004226; 89000020240000766001520240650489P_0000_00000000000_000003461004226, 3461004226; 89000020240000766001520240650490P_0000_00000000000_000003461004226, 3461004226; 89000020240000766001520240650491P_0000_00000000000_000003461004226, 3461004226; 89000020240000766001520240650492P_0000_00000000000_000003461004226, 3461004226; 89000020240000766001520240650493P_0000_00000000000_000003461004226, 3461004226; 89000020240000766001520240650494P_0000_00000000000_000003461004226, 3461004226; 89000020240000766001520240650495P_0000_00000000000_000003461004226, 3461004226; 89000020240000766001520240650496P_0000_00000000000_000003461004226, 3461004226; 89000020240000766001520240650497P_0000_00000000000_000003461004226, 3461004226; 89000020240000766001520240650498P_0000_00000000000_000003461004226, 3461004226; 89000020240000766001520240650499P_0000_00000000000_000003461004226, 3461004226; 89000020240000766001520240650500P_0000_00000000000_000003461004226, 3461004226; 89000020240000766001520240650501P_0000_00000000000_000003461004226, 3461004226; 89000020240000766001520240650502P_0000_00000000000_000003461004226, 3461004226; 89000020240000766001520240650503P_0000_00000000000_000003461004226, 3461004226; 89000020240000766001520240650504P_0000_00000000000_000003461004226, 3461004226; 89000020240000766001520240650505P_0000_00000000000_000003461004226, 3461004226; 89000020240000766001520240650506P_0000_00000000000_000003461004226, 3461004226; 89000020240000766001520240650507P_0000_00000000000_000003461004226, 3461004226; 89000020240000766001520240650508P_0000_00000000000_000003461004226, 3461004226; 89000020240000766001520240650509P_0000_00000000000_000003461004226, 3461004226; 89000020240000766001520240650510P_0000_00000000000_000003461004226, 3461004226; 89000020240000766001520240650511P_0000_00000000000_000003461004226, 3461004226; 89000020240000766001520240650512P_0000_00000000000_000003461004226, 3461004226; 89000020240000766001520240650513P_0000_00000000000_000003461004226, 3461004226; 89000020240000766001520240650514P_0000_00000000000_000003461004226, 3461004226; 89000020240000766001520240650515P_0000_00000000000_000003461004226, 3461004226; 89000020240000766001520240650516P_0000_00000000000_000003461004226, 3461004226; 89000020240000766001520240650517P_0000_00000000000_000003461004226, 3461004226; 89000020240000766001520240650518P_0000_00000000000_000003461004226, 3461004226; 89000020240000766001520240650519P_0000_00000000000_000003461004226, 3461004226; 89000020240000766001520240650520P_0000_00000000000_000003461004226, 3461004226; 89000020240000766001520240650521P_0000_00000000000_000003461004226, 3461004226; 89000020240000766001520240650522P_0000_00000000000_000003461004226, 3461004226; 89000020240000766001520240650523P_0000_00000000000_000003461004226, 3461004226; 89000020240000766001520240650524P_0000_00000000000_000003461004226, 3461004226; 89000020240000766001520240650525P_0000_00000000000_000003461004226, 3461004226; 89000020240000766001520240650526P_0000_00000000000_000003461004226, 3461004226; 89000020240000766001520240650527P_0000_00000000000_000003461004226, 3461004226; 89000020240000766001520240650528P_0000_00000000000_000003461004226, 3461004226; 89000020240000766001520240650529P_0000_00000000000_000003461004226, 3461004226; 89000020240000766001520240650530P_0000_00000000000_000003461004226, 3461004226; 89000020240000766001520240650531P_0000_00000000000_000003461004226, 3461004226; 89000020240000766001520240650532P_0000_00000000000_000003461004226, 3461004226; 89000020240000766001520240650533P_0000_00000000000_000003461004226, 3461004226; 89000020240000766001520240650534P_0000_00000000000_000003461004226, 3461004226; 89000020240000766001520240650535P_0000_00000000000_000003461004226, 3461004226; 89000020240000766001520240650536P_0000_00000000000_000003461004226, 3461004226; 89000020240000766001520240650537P_0000_00000000000_000003461004226, 3461004226; 89000020240000766001520240650538P_0000_00000000000_000003461004226, 3461004226; 89000020240000766001520240650539P_0000_00000000000_000003461004226, 3461004226; 89000020240000766001520240650540P_0000_00000000000_000003461004226, 3461004226; 89000020240000766001520240650541P_0000_00000000000_000003461004226, 3461004226; 89000020240000766001520240650542P_0000_00000000000_000003461004226, 3461004226; 89000020240000766001520240650543P_0000_00000000000_000003461004226, 3461004226; 89000020240000766001520240650544P_0000_00000000000_000003461004226, 3461004226; 89000020240000766001520240650545P_0000_00000000000_000003461004226, 3461004226; 89000020240000766001520240650546P_0000_00000000000_000003461004226, 3461004226; 89000020240000766001520240650547P_0000_00000000000_000003461004226, 3461004226; 89000020240000766001520240650548P_0000_00000000000_000003461004226, 3461004226; 89000020240000766001520240650549P_0000_00000000000_000003461004226, 3461004226; 89000020240000766001520240650550P_0000_00000000000_000003461004226, 3461004226; 89000020240000766001520240650551P_0000_00000000000_000003461004226, 3461004226; 89000020240000766001520240650552P_0000_00000000000_000003461004226, 3461004226; 89000020240000766001520240650553P_0000_00000000000_000003461004226, 3461004226; 89000020240000766001520240650554P_0000_00000000000_000003461004226, 3461004226; 89000020240000766001520240650555P_0000_00000000000_000003461004226, 3461004226; 89000020240000766001520240650556P_0000_00000000000_000003461004226, 3461004226; 89000020240000766001520240650557P_0000_00000000000_000003461004226, 3461004226; 89000020240000766001520240650558P_0000_00000000000_000003461004226, 3461004226; 89000020240000766001520240650559P_0000_00000000000_000003461004226, 3461004226; 89000020240000766001520240650560P_0000_00000000000_000003461004226, 3461004226; 89000020240000766001520240650561P_0000_00000000000_000003461004226, 3461004226; 89000020240000766001520240650562P_0000_00000000000_000003461004226, 3461004226; 89000020240000766001520240650563P_0000_00000000000_000003461004226, 3461004226; 89000020240000766001520240650564P_0000_00000000000_000003461004226, 3461004226; 89000020240000766001520240650565P_0000_00000000000_000003461004226, 3461004226; 89000020240000766001520240650566P_0000_00000000000_000003461004226, 3461004226; 89000020240000766001520240650567P_0000_00000000000_000003461004226, 3461004226; 89000020240000766001520240650568P_0000_00000000000_000003461004226, 3461004226; 89000020240000766001520240650569P_0000_00000000000_000003461004226, 3461004226; 89000020240000766001520240650783P_0000_00000000000_000003461004226, 3461004226; 89000020240000766001520240650784P_0000_00000000000_000003461004226, 3461004226; 89000020240000766001520240650785P_0000_00000000000_000003461004226, 3461004226; 89000020240000766001520240650786P_0000_00000000000_000003461004226, 3461004226; 89000020240000766001520240650787P_0000_00000000000_000003461004226, 3461004226; 89000020240000766001520240650788P_0000_00000000000_000003461004226, 3461004226; 89000020240000766001520240650851P_0000_00000000000_000003461004226, 3461004226; 89000020240000766001520240650853P_0000_00000000000_000003461004226, 3461004226; 89000020240000766001520240650865P_0000_00000000000_000003461004226, 3461004226; 89000020240000766001520240650868P_0000_00000000000_000003461004226, 3461004226; 89000020240000766001520240650869P_0000_00000000000_000003461004226, 3461004226; 89000020240000766001520240650873P_0000_00000000000_000003461004226, 3461004226; 89000020240000766001520240650875P_0000_00000000000_000003461004226, 3461004226; 89000020240000766001520240650930P_0000_00000000000_000003461004226, 3461004226; 89000020240000766001520240650947P_0000_00000000000_000003461004226, 3461004226; 89000020240000766001520240650948P_0000_00000000000_000003461004226, 3461004226; 89000020240000766001520240650949P_0000_00000000000_000003461004226, 3461004226; 89000020240000766001520240650950P_0000_00000000000_000003461004226, 3461004226; 89000020240000766001520240650951P_0000_00000000000_000003461004226, 3461004226; 89000020240000766001520240650952P_0000_00000000000_000003461004226, 3461004226; 89000020240000766001520240650953P_0000_00000000000_000003461004226, 3461004226; 89000020240000766001520240650954P_0000_00000000000_000003461004226, 3461004226; 89000020240000766001520240650955P_0000_00000000000_000003461004226, 3461004226; 89000020240000766001520240650956P_0000_00000000000_000003461004226, 3461004226; 89000020240000766001520240650957P_0000_00000000000_000003461004226, 3461004226; 89000020240000766001520240650958P_0000_00000000000_000003461004226, 3461004226; 89000020240000766001520240650959P_0000_00000000000_000003461004226, 3461004226; 89000020240000766001520240650960P_0000_00000000000_000003461004226, 3461004226; 89000020240000766001520240650961P_0000_00000000000_000003461004226, 3461004226; 89000020240000766001520240650962P_0000_00000000000_000003461004226, 3461004226; 89000020240000766001520240650968P_0000_00000000000_000003461004226, 3461004226; 89000020240000766001520240650969P_0000_00000000000_000003461004226, 3461004226; 89000020240000766001520240650970P_0000_00000000000_000003461004226, 3461004226; 89000020240000766001520240650971P_0000_00000000000_000003461004226, 3461004226; 89000020240000766001520240650972P_0000_00000000000_000003461004226, 3461004226; 89000020240000766001520240650973P_0000_00000000000_000003461004226, 3461004226; 89000020240000766001520240650974P_0000_00000000000_000003461004226, 3461004226; 89000020240000766001520240650975P_0000_00000000000_000003461004226, 3461004226; 89000020240000766001520240650976P_0000_00000000000_000003461004226, 3461004226; 89000020240000766001520240650978P_0000_00000000000_000003461004226, 3461004226; 89000020240000766001520240650979P_0000_00000000000_000003461004226, 3461004226; 89000020240000766001520240650980P_0000_00000000000_000003461004226, 3461004226; 89000020240000766001520240650981P_0000_00000000000_000003461004226, 3461004226; 89000020240000766001520240650982P_0000_00000000000_000003461004226, 3461004226; 89000020240000766001520240650983P_0000_00000000000_000003461004226, 3461004226; 89000020240000766001520240650984P_0000_00000000000_000003461004226, 3461004226; 89000020240000766001520240650985P_0000_00000000000_000003461004226, 3461004226; 89000020240000766001520240650986P_0000_00000000000_000003461004226, 3461004226; 89000020240000766001520240650987P_0000_00000000000_000003461004226, 3461004226; 89000020240000766001520240650988P_0000_00000000000_000003461004226, 3461004226; 89000020240000766001520240650989P_0000_00000000000_000003461004226, 3461004226; 89000020240000766001520240650990P_0000_00000000000_000003461004226, 3461004226; 89000020240000766001520240650991P_0000_00000000000_000003461004226, 3461004226; 89000020240000766001520240650992P_0000_00000000000_000003461004226, 3461004226; 89000020240000766001520240650993P_0000_00000000000_000003461004226, 3461004226; 89000020240000766001520240650994P_0000_00000000000_000003461004226, 3461004226; 89000020240000766001520240650995P_0000_00000000000_000003461004226, 3461004226; 89000020240000766001520240650996P_0000_00000000000_000003461004226, 3461004226; 89000020240000766001520240650997P_0000_00000000000_000003461004226, 3461004226; 89000020240000766001520240650998P_0000_00000000000_000003461004226, 3461004226; 89000020240000766001520240650999P_0000_00000000000_000003461004226, 3461004226; 89000020240000766001520240651000P_0000_00000000000_000003461004226, 3461004226; 89000020240000766001520240651001P_0000_00000000000_000003461004226, 3461004226; 89000020240000766001520240651002P_0000_00000000000_000003461004226, 3461004226; 89000020240000766001520240651003P_0000_00000000000_000003461004226, 3461004226; 89000020240000766001520240651004P_0000_00000000000_000003461004226, 3461004226; 89000020240000766001520240651005P_0000_00000000000_000003461004226, 3461004226; 89000020240000766001520240651006P_0000_00000000000_000003461004226, 3461004226; 89000020240000766001520240651020P_0000_00000000000_000003461004226, 3461004226; 89000020240000766001520240651095P_0000_00000000000_000003461004226, 3461004226; 89000020240000766001520240651174P_0000_00000000000_000003461004226, 3461004226; 89000020240000766001520240651175P_0000_00000000000_000003461004226, 3461004226; 89000020240000766001520240651177P_0000_00000000000_000003461004226, 3461004226; 89000020240000766001520240651179P_0000_00000000000_000003461004226, 3461004226; 89000020240000766001520240651180P_0000_00000000000_000003461004226, 3461004226; 89000020240000766001520240651187P_0000_00000000000_000003461004226, 3461004226; 89000020240000766001520240651188P_0000_00000000000_000003461004226, 3461004226; 89000020240000766001520240651189P_0000_00000000000_000003461004226, 3461004226; 89000020240000766001520240651190P_0000_00000000000_000003461004226, 3461004226; 89000020240000766001520240651192P_0000_00000000000_000003461004226, 3461004226; 89000020240000766001520240651193P_0000_00000000000_000003461004226, 3461004226; 89000020240000766001520240651194P_0000_00000000000_000003461004226, 3461004226; 89000020240000766001520240651195P_0000_00000000000_000003461004226, 3461004226; 89000020240000766001520240651196P_0000_00000000000_000003461004226, 3461004226; 89000020240000766001520240651197P_0000_00000000000_000003461004226, 3461004226; 89000020240000766001520240651198P_0000_00000000000_000003461004226, 3461004226; 89000020240000766001520240651199P_0000_00000000000_000003461004226, 3461004226; 89000020240000766001520240651200P_0000_00000000000_000003461004226, 3461004226; 89000020240000766001520240651201P_0000_00000000000_000003461004226, 3461004226; 89000020240000766001520240651202P_0000_00000000000_000003461004226, 3461004226; 89000020240000766001520240651203P_0000_00000000000_000003461004226, 3461004226; 89000020240000766001520240651204P_0000_00000000000_000003461004226, 3461004226; 89000020240000766001520240651307P_0000_00000000000_000003461004226, 3461004226; 89000020240000766001520240651409P_0000_00000000000_000003461004226, 3461004226; 89000020240000766001520240651410P_0000_00000000000_000003461004226, 3461004226; 89000020240000766001520240651411P_0000_00000000000_000003461004226, 3461004226; 89000020240000766001520240651412P_0000_00000000000_000003461004226, 3461004226; 89000020240000766001520240651444P_0000_00000000000_000003461004226, 3461004226; 89000020240000766001520240651449P_0000_00000000000_000003461004226, 3461004226; 89000020240000766001520240651453P_0000_00000000000_000003461004226, 3461004226; 89000020240000766001520240651454P_0000_00000000000_000003461004226, 3461004226; 89000020240000766001520240651455P_0000_00000000000_000003461004226, 3461004226; 89000020240000766001520240651456P_0000_00000000000_000003461004226, 3461004226; 89000020240000766001520240651464P_0000_00000000000_000003461004226, 3461004226; 89000020240000766001520240651468P_0000_00000000000_000003461004226, 3461004226; 89000020240000766001520240651470P_0000_00000000000_000003461004226, 3461004226; 89000020240000766001520240651471P_0000_00000000000_000003461004226, 3461004226; 89000020240000766001520240651473P_0000_00000000000_000003461004226, 3461004226; 89000020240000766001520240651474P_0000_00000000000_000003461004226, 3461004226; 89000020240000766001520240651475P_0000_00000000000_000003461004226, 3461004226; 89000020240000766001520240651476P_0000_00000000000_000003461004226, 3461004226; 89000020240000766001520240651477P_0000_00000000000_000003461004226, 3461004226; 89000020240000766001520240651643P_0000_00000000000_000003461004226, 3461004226; 89000020240000766001520240651644P_0000_00000000000_000003461004226, 3461004226; 89000020240000766001520240651645P_0000_00000000000_000003461004226, 3461004226; 89000020240000766001520240651684P_0000_00000000000_000003461004226, 3461004226; 89000020240000766001520240651693P_0000_00000000000_000003461004226, 3461004226; 89000020240000766001520240651694P_0000_00000000000_000003461004226, 3461004226; 89000020240000766001520240651695P_0000_00000000000_000003461004226, 3461004226; 89000020240000766001520240651696P_0000_00000000000_000003461004226, 3461004226; 89000020240000766001520240651697P_0000_00000000000_000003461004226, 3461004226; 89000020240000766001520240651698P_0000_00000000000_000003461004226, 3461004226; 89000020240000766001520240651699P_0000_00000000000_000003461004226, 3461004226; 89000020240000766001520240651700P_0000_00000000000_000003461004226, 3461004226; 89000020240000766001520240651701P_0000_00000000000_000003461004226, 3461004226; 89000020240000766001520240651702P_0000_00000000000_000003461004226, 3461004226; 89000020240000766001520240651706P_0000_00000000000_000003461004226, 3461004226; 89000020240000766001520240651707P_0000_00000000000_000003461004226, 3461004226; 89000020240000766001520240651708P_0000_00000000000_000003461004226, 3461004226; 89000020240000766001520240651709P_0000_00000000000_000003461004226, 3461004226; 89000020240000766001520240651710P_0000_00000000000_000003461004226, 3461004226; 89000020240000766001520240651711P_0000_00000000000_000003461004226, 3461004226; 89000020240000766001520240651712P_0000_00000000000_000003461004226, 3461004226; 89000020240000766001520240651713P_0000_00000000000_000003461004226, 3461004226; 89000020240000766001520240651714P_0000_00000000000_000003461004226, 3461004226; 89000020240000766001520240651715P_0000_00000000000_000003461004226, 3461004226; 89000020240000766001520240651716P_0000_00000000000_000003461004226, 3461004226; 89000020240000766001520240651717P_0000_00000000000_000003461004226, 3461004226; 89000020240000766001520240651718P_0000_00000000000_000003461004226, 3461004226; 89000020240000766001520240651719P_0000_00000000000_000003461004226, 3461004226; 89000020240000766001520240651720P_0000_00000000000_000003461004226, 3461004226; 89000020240000766001520240651721P_0000_00000000000_000003461004226, 3461004226; 89000020240000766001520240651722P_0000_00000000000_000003461004226, 3461004226; 89000020240000766001520240651723P_0000_00000000000_000003461004226, 3461004226; 89000020240000766001520240651727P_0000_00000000000_000003461004226, 3461004226; 89000020240000766001520240651728P_0000_00000000000_000003461004226, 3461004226; 89000020240000766
A103: 2025-10-31 | B103: MIS_B9000_C0040 | C103: MISSINGS | D103: Validar que não existem registos por preencher (Missings) | E103: BU_LOANTAPE_WORK.OUT_B9000_COUNTERPARTIES | F103: 0040_CNTRPRTY_NM | G103: 4740 | H103: 2 | I103: PTBSREOM0028, Not applicable; PTCPP0AM0007, Not applicable
A104: 2025-10-31 | B104: MIS_B9000_C0050 | C104: MISSINGS | D104: Validar que não existem registos por preencher (Missings) | E104: BU_LOANTAPE_WORK.OUT_B9000_COUNTERPARTIES | F104: 0050_CNTRPRTY_LEI | G104: 4740 | H104: 0
A105: 2025-10-31 | B105: MIS_B9000_C0060 | C105: MISSINGS | D105: Validar que não existem registos por preencher (Missings) | E105: BU_LOANTAPE_WORK.OUT_B9000_COUNTERPARTIES | F105: 0060_TYP_CNTRPRTY_ID | G105: 4740 | H105: 0
A106: 2025-10-31 | B106: MIS_B9000_C0070 | C106: MISSINGS | D106: Validar que não existem registos por preencher (Missings) | E106: BU_LOANTAPE_WORK.OUT_B9000_COUNTERPARTIES | F106: 0070_CNTRPRTY_ID | G106: 4740 | H106: 0
A107: 2025-10-31 | B107: MIS_B9000_C0080 | C107: MISSINGS | D107: Validar que não existem registos por preencher (Missings) | E107: BU_LOANTAPE_WORK.OUT_B9000_COUNTERPARTIES | F107: 0080_CNTRPRTY_TYP | G107: 4740 | H107: 0
A108: 2025-10-31 | B108: MIS_B9000_C0090 | C108: MISSINGS | D108: Validar que não existem registos por preencher (Missings) | E108: BU_LOANTAPE_WORK.OUT_B9000_COUNTERPARTIES | F108: 0090_CNTRY_CNTRPRTY | G108: 4740 | H108: 0
A109: 2025-10-31 | B109: MIS_B9000_C0100 | C109: MISSINGS | D109: Validar que não existem registos por preencher (Missings) | E109: BU_LOANTAPE_WORK.OUT_B9000_COUNTERPARTIES | F109: 0100_RLVNT_AMNT_WDC | G109: 4740 | H109: 4740 | I109: PTBSRDOM0037, 0000003686; PTBSREOM0028, Not applicable; PTCPP0AM0007, Not applicable; PTCPP0AM0007, 0000003686; PTCPP0AM0007, 5100011001; PTSTOCOM0007, 0000003686; PTSTOEOM0021, 0000003686; PTSTOFOM0004, 0000003686; PTSTOGOM0003, 0000003686; PTSTOHOM0002, 0000003686; 31000000000000000962304890482490P_0000_00000000000_000006511000505, 6511000505; 31000304140330096000000000000000P_0000_00000000000_000000000003686, 0000003686; 31000307044893096000000000000000P_0000_00000000000_000000000003686, 0000003686; 31000307530917096000000000000000P_0000_00000000000_000000000003686, 0000003686; 31000311450813096000000000000000P_0000_00000000000_000000000003686, 0000003686; 31000311847794096000000000000000P_0000_00000000000_000000000003686, 0000003686; 31000313517171096000000000000000P_0000_00000000000_000000000003686, 0000003686; 31000315970006096000000000000000P_0000_00000000000_000000000003686, 0000003686; 31000315970121096000000000000000P_0000_00000000000_000000000003686, 0000003686; 31000315970139096000000000000000P_0000_00000000000_000000000003686, 0000003686; 31000315970188096000000000000000P_0000_00000000000_000000000003686, 0000003686; 31000315970212096000000000000000P_0000_00000000000_000000000003686, 0000003686; 31000315970238096000000000000000P_0000_00000000000_000000000003686, 0000003686; 31000315970261096000000000000000P_0000_00000000000_000000000003686, 0000003686; 31000315970279096000000000000000P_0000_00000000000_000000000003686, 0000003686; 31000315970311096000000000000000P_0000_00000000000_000000000003686, 0000003686; 31000315970329096000000000000000P_0000_00000000000_000000000003686, 0000003686; 31000315970345096000000000000000P_0000_00000000000_000000000003686, 0000003686; 31000315970402096000000000000000P_0000_00000000000_000000000003686, 0000003686; 31000315970428096000000000000000P_0000_00000000000_000000000003686, 0000003686; 31000315970469096000000000000000P_0000_00000000000_000000000003686, 0000003686; 31000315979890096000000000000000P_0000_00000000000_000006511000505, 6511000505; 31000318293090097000000000000000P_0000_00000000000_000008000176024, 8000176024; 31000318542009097000000000000000P_0000_00000000000_000006511000505, 6511000505; 31000318628196097000000000000000P_0000_00000000000_000006511000505, 6511000505; 31000318628592097000000000000000P_0000_00000000000_000008000176024, 8000176024; 31000318629012097000000000000000P_0000_00000000000_000008000176024, 8000176024; 31000318636603097000000000000000P_0000_00000000000_000008000176024, 8000176024; 31000318637213097000000000000000P_0000_00000000000_000008000176024, 8000176024; 31000322311418096000000000000000P_0000_00000000000_000000000003686, 0000003686; 89000020240000766001520240649818P_0000_00000000000_000003461004226, 3461004226; 89000020240000766001520240649824P_0000_00000000000_000003461004226, 3461004226; 89000020240000766001520240649825P_0000_00000000000_000003461004226, 3461004226; 89000020240000766001520240649826P_0000_00000000000_000003461004226, 3461004226; 89000020240000766001520240649827P_0000_00000000000_000003461004226, 3461004226; 89000020240000766001520240649838P_0000_00000000000_000003461004226, 3461004226; 89000020240000766001520240649839P_0000_00000000000_000003461004226, 3461004226; 89000020240000766001520240649873P_0000_00000000000_000003461004226, 3461004226; 89000020240000766001520240649874P_0000_00000000000_000003461004226, 3461004226; 89000020240000766001520240649875P_0000_00000000000_000003461004226, 3461004226; 89000020240000766001520240649894P_0000_00000000000_000003461004226, 3461004226; 89000020240000766001520240649898P_0000_00000000000_000003461004226, 3461004226; 89000020240000766001520240649899P_0000_00000000000_000003461004226, 3461004226; 89000020240000766001520240649900P_0000_00000000000_000003461004226, 3461004226; 89000020240000766001520240649901P_0000_00000000000_000003461004226, 3461004226; 89000020240000766001520240649909P_0000_00000000000_000003461004226, 3461004226; 89000020240000766001520240649910P_0000_00000000000_000003461004226, 3461004226; 89000020240000766001520240649911P_0000_00000000000_000003461004226, 3461004226; 89000020240000766001520240649912P_0000_00000000000_000003461004226, 3461004226; 89000020240000766001520240649913P_0000_00000000000_000003461004226, 3461004226; 89000020240000766001520240649914P_0000_00000000000_000003461004226, 3461004226; 89000020240000766001520240649915P_0000_00000000000_000003461004226, 3461004226; 89000020240000766001520240649916P_0000_00000000000_000003461004226, 3461004226; 89000020240000766001520240649917P_0000_00000000000_000003461004226, 3461004226; 89000020240000766001520240649918P_0000_00000000000_000003461004226, 3461004226; 89000020240000766001520240649919P_0000_00000000000_000003461004226, 3461004226; 89000020240000766001520240649920P_0000_00000000000_000003461004226, 3461004226; 89000020240000766001520240649921P_0000_00000000000_000003461004226, 3461004226; 89000020240000766001520240649942P_0000_00000000000_000003461004226, 3461004226; 89000020240000766001520240649943P_0000_00000000000_000003461004226, 3461004226; 89000020240000766001520240649944P_0000_00000000000_000003461004226, 3461004226; 89000020240000766001520240649945P_0000_00000000000_000003461004226, 3461004226; 89000020240000766001520240649946P_0000_00000000000_000003461004226, 3461004226; 89000020240000766001520240650004P_0000_00000000000_000003461004226, 3461004226; 89000020240000766001520240650005P_0000_00000000000_000003461004226, 3461004226; 89000020240000766001520240650006P_0000_00000000000_000003461004226, 3461004226; 89000020240000766001520240650007P_0000_00000000000_000003461004226, 3461004226; 89000020240000766001520240650008P_0000_00000000000_000003461004226, 3461004226; 89000020240000766001520240650009P_0000_00000000000_000003461004226, 3461004226; 89000020240000766001520240650010P_0000_00000000000_000003461004226, 3461004226; 89000020240000766001520240650011P_0000_00000000000_000003461004226, 3461004226; 89000020240000766001520240650116P_0000_00000000000_000003461004226, 3461004226; 89000020240000766001520240650192P_0000_00000000000_000003461004226, 3461004226; 89000020240000766001520240650202P_0000_00000000000_000003461004226, 3461004226; 89000020240000766001520240650203P_0000_00000000000_000003461004226, 3461004226; 89000020240000766001520240650204P_0000_00000000000_000003461004226, 3461004226; 89000020240000766001520240650205P_0000_00000000000_000003461004226, 3461004226; 89000020240000766001520240650206P_0000_00000000000_000003461004226, 3461004226; 89000020240000766001520240650207P_0000_00000000000_000003461004226, 3461004226; 89000020240000766001520240650208P_0000_00000000000_000003461004226, 3461004226; 89000020240000766001520240650349P_0000_00000000000_000003461004226, 3461004226; 89000020240000766001520240650350P_0000_00000000000_000003461004226, 3461004226; 89000020240000766001520240650351P_0000_00000000000_000003461004226, 3461004226; 89000020240000766001520240650352P_0000_00000000000_000003461004226, 3461004226; 89000020240000766001520240650353P_0000_00000000000_000003461004226, 3461004226; 89000020240000766001520240650354P_0000_00000000000_000003461004226, 3461004226; 89000020240000766001520240650355P_0000_00000000000_000003461004226, 3461004226; 89000020240000766001520240650356P_0000_00000000000_000003461004226, 3461004226; 89000020240000766001520240650357P_0000_00000000000_000003461004226, 3461004226; 89000020240000766001520240650358P_0000_00000000000_000003461004226, 3461004226; 89000020240000766001520240650359P_0000_00000000000_000003461004226, 3461004226; 89000020240000766001520240650360P_0000_00000000000_000003461004226, 3461004226; 89000020240000766001520240650361P_0000_00000000000_000003461004226, 3461004226; 89000020240000766001520240650362P_0000_00000000000_000003461004226, 3461004226; 89000020240000766001520240650363P_0000_00000000000_000003461004226, 3461004226; 89000020240000766001520240650364P_0000_00000000000_000003461004226, 3461004226; 89000020240000766001520240650365P_0000_00000000000_000003461004226, 3461004226; 89000020240000766001520240650366P_0000_00000000000_000003461004226, 3461004226; 89000020240000766001520240650367P_0000_00000000000_000003461004226, 3461004226; 89000020240000766001520240650368P_0000_00000000000_000003461004226, 3461004226; 89000020240000766001520240650369P_0000_00000000000_000003461004226, 3461004226; 89000020240000766001520240650370P_0000_00000000000_000003461004226, 3461004226; 89000020240000766001520240650371P_0000_00000000000_000003461004226, 3461004226; 89000020240000766001520240650372P_0000_00000000000_000003461004226, 3461004226; 89000020240000766001520240650373P_0000_00000000000_000003461004226, 3461004226; 89000020240000766001520240650374P_0000_00000000000_000003461004226, 3461004226; 89000020240000766001520240650375P_0000_00000000000_000003461004226, 3461004226; 89000020240000766001520240650376P_0000_00000000000_000003461004226, 3461004226; 89000020240000766001520240650377P_0000_00000000000_000003461004226, 3461004226; 89000020240000766001520240650378P_0000_00000000000_000003461004226, 3461004226; 89000020240000766001520240650379P_0000_00000000000_000003461004226, 3461004226; 89000020240000766001520240650380P_0000_00000000000_000003461004226, 3461004226; 89000020240000766001520240650381P_0000_00000000000_000003461004226, 3461004226; 89000020240000766001520240650382P_0000_00000000000_000003461004226, 3461004226; 89000020240000766001520240650383P_0000_00000000000_000003461004226, 3461004226; 89000020240000766001520240650384P_0000_00000000000_000003461004226, 3461004226; 89000020240000766001520240650385P_0000_00000000000_000003461004226, 3461004226; 89000020240000766001520240650386P_0000_00000000000_000003461004226, 3461004226; 89000020240000766001520240650387P_0000_00000000000_000003461004226, 3461004226; 89000020240000766001520240650388P_0000_00000000000_000003461004226, 3461004226; 89000020240000766001520240650389P_0000_00000000000_000003461004226, 3461004226; 89000020240000766001520240650390P_0000_00000000000_000003461004226, 3461004226; 89000020240000766001520240650391P_0000_00000000000_000003461004226, 3461004226; 89000020240000766001520240650392P_0000_00000000000_000003461004226, 3461004226; 89000020240000766001520240650393P_0000_00000000000_000003461004226, 3461004226; 89000020240000766001520240650394P_0000_00000000000_000003461004226, 3461004226; 89000020240000766001520240650396P_0000_00000000000_000003461004226, 3461004226; 89000020240000766001520240650397P_0000_00000000000_000003461004226, 3461004226; 89000020240000766001520240650398P_0000_00000000000_000003461004226, 3461004226; 89000020240000766001520240650399P_0000_00000000000_000003461004226, 3461004226; 89000020240000766001520240650400P_0000_00000000000_000003461004226, 3461004226; 89000020240000766001520240650401P_0000_00000000000_000003461004226, 3461004226; 89000020240000766001520240650402P_0000_00000000000_000003461004226, 3461004226; 89000020240000766001520240650403P_0000_00000000000_000003461004226, 3461004226; 89000020240000766001520240650404P_0000_00000000000_000003461004226, 3461004226; 89000020240000766001520240650405P_0000_00000000000_000003461004226, 3461004226; 89000020240000766001520240650406P_0000_00000000000_000003461004226, 3461004226; 89000020240000766001520240650407P_0000_00000000000_000003461004226, 3461004226; 89000020240000766001520240650408P_0000_00000000000_000003461004226, 3461004226; 89000020240000766001520240650409P_0000_00000000000_000003461004226, 3461004226; 89000020240000766001520240650410P_0000_00000000000_000003461004226, 3461004226; 89000020240000766001520240650411P_0000_00000000000_000003461004226, 3461004226; 89000020240000766001520240650412P_0000_00000000000_000003461004226, 3461004226; 89000020240000766001520240650413P_0000_00000000000_000003461004226, 3461004226; 89000020240000766001520240650414P_0000_00000000000_000003461004226, 3461004226; 89000020240000766001520240650415P_0000_00000000000_000003461004226, 3461004226; 89000020240000766001520240650416P_0000_00000000000_000003461004226, 3461004226; 89000020240000766001520240650417P_0000_00000000000_000003461004226, 3461004226; 89000020240000766001520240650418P_0000_00000000000_000003461004226, 3461004226; 89000020240000766001520240650419P_0000_00000000000_000003461004226, 3461004226; 89000020240000766001520240650420P_0000_00000000000_000003461004226, 3461004226; 89000020240000766001520240650421P_0000_00000000000_000003461004226, 3461004226; 89000020240000766001520240650422P_0000_00000000000_000003461004226, 3461004226; 89000020240000766001520240650423P_0000_00000000000_000003461004226, 3461004226; 89000020240000766001520240650424P_0000_00000000000_000003461004226, 3461004226; 89000020240000766001520240650425P_0000_00000000000_000003461004226, 3461004226; 89000020240000766001520240650426P_0000_00000000000_000003461004226, 3461004226; 89000020240000766001520240650427P_0000_00000000000_000003461004226, 3461004226; 89000020240000766001520240650428P_0000_00000000000_000003461004226, 3461004226; 89000020240000766001520240650429P_0000_00000000000_000003461004226, 3461004226; 89000020240000766001520240650431P_0000_00000000000_000003461004226, 3461004226; 89000020240000766001520240650432P_0000_00000000000_000003461004226, 3461004226; 89000020240000766001520240650433P_0000_00000000000_000003461004226, 3461004226; 89000020240000766001520240650434P_0000_00000000000_000003461004226, 3461004226; 89000020240000766001520240650435P_0000_00000000000_000003461004226, 3461004226; 89000020240000766001520240650436P_0000_00000000000_000003461004226, 3461004226; 89000020240000766001520240650476P_0000_00000000000_000003461004226, 3461004226; 89000020240000766001520240650477P_0000_00000000000_000003461004226, 3461004226; 89000020240000766001520240650478P_0000_00000000000_000003461004226, 3461004226; 89000020240000766001520240650479P_0000_00000000000_000003461004226, 3461004226; 89000020240000766001520240650480P_0000_00000000000_000003461004226, 3461004226; 89000020240000766001520240650481P_0000_00000000000_000003461004226, 3461004226; 89000020240000766001520240650482P_0000_00000000000_000003461004226, 3461004226; 89000020240000766001520240650483P_0000_00000000000_000003461004226, 3461004226; 89000020240000766001520240650484P_0000_00000000000_000003461004226, 3461004226; 89000020240000766001520240650485P_0000_00000000000_000003461004226, 3461004226; 89000020240000766001520240650486P_0000_00000000000_000003461004226, 3461004226; 89000020240000766001520240650487P_0000_00000000000_000003461004226, 3461004226; 89000020240000766001520240650488P_0000_00000000000_000003461004226, 3461004226; 89000020240000766001520240650489P_0000_00000000000_000003461004226, 3461004226; 89000020240000766001520240650490P_0000_00000000000_000003461004226, 3461004226; 89000020240000766001520240650491P_0000_00000000000_000003461004226, 3461004226; 89000020240000766001520240650492P_0000_00000000000_000003461004226, 3461004226; 89000020240000766001520240650493P_0000_00000000000_000003461004226, 3461004226; 89000020240000766001520240650494P_0000_00000000000_000003461004226, 3461004226; 89000020240000766001520240650495P_0000_00000000000_000003461004226, 3461004226; 89000020240000766001520240650496P_0000_00000000000_000003461004226, 3461004226; 89000020240000766001520240650497P_0000_00000000000_000003461004226, 3461004226; 89000020240000766001520240650498P_0000_00000000000_000003461004226, 3461004226; 89000020240000766001520240650499P_0000_00000000000_000003461004226, 3461004226; 89000020240000766001520240650500P_0000_00000000000_000003461004226, 3461004226; 89000020240000766001520240650501P_0000_00000000000_000003461004226, 3461004226; 89000020240000766001520240650502P_0000_00000000000_000003461004226, 3461004226; 89000020240000766001520240650503P_0000_00000000000_000003461004226, 3461004226; 89000020240000766001520240650504P_0000_00000000000_000003461004226, 3461004226; 89000020240000766001520240650505P_0000_00000000000_000003461004226, 3461004226; 89000020240000766001520240650506P_0000_00000000000_000003461004226, 3461004226; 89000020240000766001520240650507P_0000_00000000000_000003461004226, 3461004226; 89000020240000766001520240650508P_0000_00000000000_000003461004226, 3461004226; 89000020240000766001520240650509P_0000_00000000000_000003461004226, 3461004226; 89000020240000766001520240650510P_0000_00000000000_000003461004226, 3461004226; 89000020240000766001520240650511P_0000_00000000000_000003461004226, 3461004226; 89000020240000766001520240650512P_0000_00000000000_000003461004226, 3461004226; 89000020240000766001520240650513P_0000_00000000000_000003461004226, 3461004226; 89000020240000766001520240650514P_0000_00000000000_000003461004226, 3461004226; 89000020240000766001520240650515P_0000_00000000000_000003461004226, 3461004226; 89000020240000766001520240650516P_0000_00000000000_000003461004226, 3461004226; 89000020240000766001520240650517P_0000_00000000000_000003461004226, 3461004226; 89000020240000766001520240650518P_0000_00000000000_000003461004226, 3461004226; 89000020240000766001520240650519P_0000_00000000000_000003461004226, 3461004226; 89000020240000766001520240650520P_0000_00000000000_000003461004226, 3461004226; 89000020240000766001520240650521P_0000_00000000000_000003461004226, 3461004226; 89000020240000766001520240650522P_0000_00000000000_000003461004226, 3461004226; 89000020240000766001520240650523P_0000_00000000000_000003461004226, 3461004226; 89000020240000766001520240650524P_0000_00000000000_000003461004226, 3461004226; 89000020240000766001520240650525P_0000_00000000000_000003461004226, 3461004226; 89000020240000766001520240650526P_0000_00000000000_000003461004226, 3461004226; 89000020240000766001520240650527P_0000_00000000000_000003461004226, 3461004226; 89000020240000766001520240650528P_0000_00000000000_000003461004226, 3461004226; 89000020240000766001520240650529P_0000_00000000000_000003461004226, 3461004226; 89000020240000766001520240650530P_0000_00000000000_000003461004226, 3461004226; 89000020240000766001520240650531P_0000_00000000000_000003461004226, 3461004226; 89000020240000766001520240650532P_0000_00000000000_000003461004226, 3461004226; 89000020240000766001520240650533P_0000_00000000000_000003461004226, 3461004226; 89000020240000766001520240650534P_0000_00000000000_000003461004226, 3461004226; 89000020240000766001520240650535P_0000_00000000000_000003461004226, 3461004226; 89000020240000766001520240650536P_0000_00000000000_000003461004226, 3461004226; 89000020240000766001520240650537P_0000_00000000000_000003461004226, 3461004226; 89000020240000766001520240650538P_0000_00000000000_000003461004226, 3461004226; 89000020240000766001520240650539P_0000_00000000000_000003461004226, 3461004226; 89000020240000766001520240650540P_0000_00000000000_000003461004226, 3461004226; 89000020240000766001520240650541P_0000_00000000000_000003461004226, 3461004226; 89000020240000766001520240650542P_0000_00000000000_000003461004226, 3461004226; 89000020240000766001520240650543P_0000_00000000000_000003461004226, 3461004226; 89000020240000766001520240650544P_0000_00000000000_000003461004226, 3461004226; 89000020240000766001520240650545P_0000_00000000000_000003461004226, 3461004226; 89000020240000766001520240650546P_0000_00000000000_000003461004226, 3461004226; 89000020240000766001520240650547P_0000_00000000000_000003461004226, 3461004226; 89000020240000766001520240650548P_0000_00000000000_000003461004226, 3461004226; 89000020240000766001520240650549P_0000_00000000000_000003461004226, 3461004226; 89000020240000766001520240650550P_0000_00000000000_000003461004226, 3461004226; 89000020240000766001520240650551P_0000_00000000000_000003461004226, 3461004226; 89000020240000766001520240650552P_0000_00000000000_000003461004226, 3461004226; 89000020240000766001520240650553P_0000_00000000000_000003461004226, 3461004226; 89000020240000766001520240650554P_0000_00000000000_000003461004226, 3461004226; 89000020240000766001520240650555P_0000_00000000000_000003461004226, 3461004226; 89000020240000766001520240650556P_0000_00000000000_000003461004226, 3461004226; 89000020240000766001520240650557P_0000_00000000000_000003461004226, 3461004226; 89000020240000766001520240650558P_0000_00000000000_000003461004226, 3461004226; 89000020240000766001520240650559P_0000_00000000000_000003461004226, 3461004226; 89000020240000766001520240650560P_0000_00000000000_000003461004226, 3461004226; 89000020240000766001520240650561P_0000_00000000000_000003461004226, 3461004226; 89000020240000766001520240650562P_0000_00000000000_000003461004226, 3461004226; 89000020240000766001520240650563P_0000_00000000000_000003461004226, 3461004226; 89000020240000766001520240650564P_0000_00000000000_000003461004226, 3461004226; 89000020240000766001520240650565P_0000_00000000000_000003461004226, 3461004226; 89000020240000766001520240650566P_0000_00000000000_000003461004226, 3461004226; 89000020240000766001520240650567P_0000_00000000000_000003461004226, 3461004226; 89000020240000766001520240650568P_0000_00000000000_000003461004226, 3461004226; 89000020240000766001520240650569P_0000_00000000000_000003461004226, 3461004226; 89000020240000766001520240650783P_0000_00000000000_000003461004226, 3461004226; 89000020240000766001520240650784P_0000_00000000000_000003461004226, 3461004226; 89000020240000766001520240650785P_0000_00000000000_000003461004226, 3461004226; 89000020240000766001520240650786P_0000_00000000000_000003461004226, 3461004226; 89000020240000766001520240650787P_0000_00000000000_000003461004226, 3461004226; 89000020240000766001520240650788P_0000_00000000000_000003461004226, 3461004226; 89000020240000766001520240650851P_0000_00000000000_000003461004226, 3461004226; 89000020240000766001520240650853P_0000_00000000000_000003461004226, 3461004226; 89000020240000766001520240650865P_0000_00000000000_000003461004226, 3461004226; 89000020240000766001520240650868P_0000_00000000000_000003461004226, 3461004226; 89000020240000766001520240650869P_0000_00000000000_000003461004226, 3461004226; 89000020240000766001520240650873P_0000_00000000000_000003461004226, 3461004226; 89000020240000766001520240650875P_0000_00000000000_000003461004226, 3461004226; 89000020240000766001520240650930P_0000_00000000000_000003461004226, 3461004226; 89000020240000766001520240650947P_0000_00000000000_000003461004226, 3461004226; 89000020240000766001520240650948P_0000_00000000000_000003461004226, 3461004226; 89000020240000766001520240650949P_0000_00000000000_000003461004226, 3461004226; 89000020240000766001520240650950P_0000_00000000000_000003461004226, 3461004226; 89000020240000766001520240650951P_0000_00000000000_000003461004226, 3461004226; 89000020240000766001520240650952P_0000_00000000000_000003461004226, 3461004226; 89000020240000766001520240650953P_0000_00000000000_000003461004226, 3461004226; 89000020240000766001520240650954P_0000_00000000000_000003461004226, 3461004226; 89000020240000766001520240650955P_0000_00000000000_000003461004226, 3461004226; 89000020240000766001520240650956P_0000_00000000000_000003461004226, 3461004226; 89000020240000766001520240650957P_0000_00000000000_000003461004226, 3461004226; 89000020240000766001520240650958P_0000_00000000000_000003461004226, 3461004226; 89000020240000766001520240650959P_0000_00000000000_000003461004226, 3461004226; 89000020240000766001520240650960P_0000_00000000000_000003461004226, 3461004226; 89000020240000766001520240650961P_0000_00000000000_000003461004226, 3461004226; 89000020240000766001520240650962P_0000_00000000000_000003461004226, 3461004226; 89000020240000766001520240650968P_0000_00000000000_000003461004226, 3461004226; 89000020240000766001520240650969P_0000_00000000000_000003461004226, 3461004226; 89000020240000766001520240650970P_0000_00000000000_000003461004226, 3461004226; 89000020240000766001520240650971P_0000_00000000000_000003461004226, 3461004226; 89000020240000766001520240650972P_0000_00000000000_000003461004226, 3461004226; 89000020240000766001520240650973P_0000_00000000000_000003461004226, 3461004226; 89000020240000766001520240650974P_0000_00000000000_000003461004226, 3461004226; 89000020240000766001520240650975P_0000_00000000000_000003461004226, 3461004226; 89000020240000766001520240650976P_0000_00000000000_000003461004226, 3461004226; 89000020240000766001520240650978P_0000_00000000000_000003461004226, 3461004226; 89000020240000766001520240650979P_0000_00000000000_000003461004226, 3461004226; 89000020240000766001520240650980P_0000_00000000000_000003461004226, 3461004226; 89000020240000766001520240650981P_0000_00000000000_000003461004226, 3461004226; 89000020240000766001520240650982P_0000_00000000000_000003461004226, 3461004226; 89000020240000766001520240650983P_0000_00000000000_000003461004226, 3461004226; 89000020240000766001520240650984P_0000_00000000000_000003461004226, 3461004226; 89000020240000766001520240650985P_0000_00000000000_000003461004226, 3461004226; 89000020240000766001520240650986P_0000_00000000000_000003461004226, 3461004226; 89000020240000766001520240650987P_0000_00000000000_000003461004226, 3461004226; 89000020240000766001520240650988P_0000_00000000000_000003461004226, 3461004226; 89000020240000766001520240650989P_0000_00000000000_000003461004226, 3461004226; 89000020240000766001520240650990P_0000_00000000000_000003461004226, 3461004226; 89000020240000766001520240650991P_0000_00000000000_000003461004226, 3461004226; 89000020240000766001520240650992P_0000_00000000000_000003461004226, 3461004226; 89000020240000766001520240650993P_0000_00000000000_000003461004226, 3461004226; 89000020240000766001520240650994P_0000_00000000000_000003461004226, 3461004226; 89000020240000766001520240650995P_0000_00000000000_000003461004226, 3461004226; 89000020240000766001520240650996P_0000_00000000000_000003461004226, 3461004226; 89000020240000766001520240650997P_0000_00000000000_000003461004226, 3461004226; 89000020240000766001520240650998P_0000_00000000000_000003461004226, 3461004226; 89000020240000766001520240650999P_0000_00000000000_000003461004226, 3461004226; 89000020240000766001520240651000P_0000_00000000000_000003461004226, 3461004226; 89000020240000766001520240651001P_0000_00000000000_000003461004226, 3461004226; 89000020240000766001520240651002P_0000_00000000000_000003461004226, 3461004226; 89000020240000766001520240651003P_0000_00000000000_000003461004226, 3461004226; 89000020240000766001520240651004P_0000_00000000000_000003461004226, 3461004226; 89000020240000766001520240651005P_0000_00000000000_000003461004226, 3461004226; 89000020240000766001520240651006P_0000_00000000000_000003461004226, 3461004226; 89000020240000766001520240651020P_0000_00000000000_000003461004226, 3461004226; 89000020240000766001520240651095P_0000_00000000000_000003461004226, 3461004226; 89000020240000766001520240651174P_0000_00000000000_000003461004226, 3461004226; 89000020240000766001520240651175P_0000_00000000000_000003461004226, 3461004226; 89000020240000766001520240651177P_0000_00000000000_000003461004226, 3461004226; 89000020240000766001520240651179P_0000_00000000000_000003461004226, 3461004226; 89000020240000766001520240651180P_0000_00000000000_000003461004226, 3461004226; 89000020240000766001520240651187P_0000_00000000000_000003461004226, 3461004226; 89000020240000766001520240651188P_0000_00000000000_000003461004226, 3461004226; 89000020240000766001520240651189P_0000_00000000000_000003461004226, 3461004226; 89000020240000766001520240651190P_0000_00000000000_000003461004226, 3461004226; 89000020240000766001520240651192P_0000_00000000000_000003461004226, 3461004226; 89000020240000766001520240651193P_0000_00000000000_000003461004226, 3461004226; 89000020240000766001520240651194P_0000_00000000000_000003461004226, 3461004226; 89000020240000766001520240651195P_0000_00000000000_000003461004226, 3461004226; 89000020240000766001520240651196P_0000_00000000000_000003461004226, 3461004226; 89000020240000766001520240651197P_0000_00000000000_000003461004226, 3461004226; 89000020240000766001520240651198P_0000_00000000000_000003461004226, 3461004226; 89000020240000766001520240651199P_0000_00000000000_000003461004226, 3461004226; 89000020240000766001520240651200P_0000_00000000000_000003461004226, 3461004226; 89000020240000766001520240651201P_0000_00000000000_000003461004226, 3461004226; 89000020240000766001520240651202P_0000_00000000000_000003461004226, 3461004226; 89000020240000766001520240651203P_0000_00000000000_000003461004226, 3461004226; 89000020240000766001520240651204P_0000_00000000000_000003461004226, 3461004226; 89000020240000766001520240651307P_0000_00000000000_000003461004226, 3461004226; 89000020240000766001520240651409P_0000_00000000000_000003461004226, 3461004226; 89000020240000766001520240651410P_0000_00000000000_000003461004226, 3461004226; 89000020240000766001520240651411P_0000_00000000000_000003461004226, 3461004226; 89000020240000766001520240651412P_0000_00000000000_000003461004226, 3461004226; 89000020240000766001520240651444P_0000_00000000000_000003461004226, 3461004226; 89000020240000766001520240651449P_0000_00000000000_000003461004226, 3461004226; 89000020240000766001520240651453P_0000_00000000000_000003461004226, 3461004226; 89000020240000766001520240651454P_0000_00000000000_000003461004226, 3461004226; 89000020240000766001520240651455P_0000_00000000000_000003461004226, 3461004226; 89000020240000766001520240651456P_0000_00000000000_000003461004226, 3461004226; 89000020240000766001520240651464P_0000_00000000000_000003461004226, 3461004226; 89000020240000766001520240651468P_0000_00000000000_000003461004226, 3461004226; 89000020240000766001520240651470P_0000_00000000000_000003461004226, 3461004226; 89000020240000766001520240651471P_0000_00000000000_000003461004226, 3461004226; 89000020240000766001520240651473P_0000_00000000000_000003461004226, 3461004226; 89000020240000766001520240651474P_0000_00000000000_000003461004226, 3461004226; 89000020240000766001520240651475P_0000_00000000000_000003461004226, 3461004226; 89000020240000766001520240651476P_0000_00000000000_000003461004226, 3461004226; 89000020240000766001520240651477P_0000_00000000000_000003461004226, 3461004226; 89000020240000766001520240651643P_0000_00000000000_000003461004226, 3461004226; 89000020240000766001520240651644P_0000_00000000000_000003461004226, 3461004226; 89000020240000766001520240651645P_0000_00000000000_000003461004226, 3461004226; 89000020240000766001520240651684P_0000_00000000000_000003461004226, 3461004226; 89000020240000766001520240651693P_0000_00000000000_000003461004226, 3461004226; 89000020240000766001520240651694P_0000_00000000000_000003461004226, 3461004226; 89000020240000766001520240651695P_0000_00000000000_000003461004226, 3461004226; 89000020240000766001520240651696P_0000_00000000000_000003461004226, 3461004226; 89000020240000766001520240651697P_0000_00000000000_000003461004226, 3461004226; 89000020240000766001520240651698P_0000_00000000000_000003461004226, 3461004226; 89000020240000766001520240651699P_0000_00000000000_000003461004226, 3461004226; 89000020240000766001520240651700P_0000_00000000000_000003461004226, 3461004226; 89000020240000766001520240651701P_0000_00000000000_000003461004226, 3461004226; 89000020240000766001520240651702P_0000_00000000000_000003461004226, 3461004226; 89000020240000766001520240651706P_0000_00000000000_000003461004226, 3461004226; 89000020240000766001520240651707P_0000_00000000000_000003461004226, 3461004226; 89000020240000766001520240651708P_0000_00000000000_000003461004226, 3461004226; 89000020240000766001520240651709P_0000_00000000000_000003461004226, 3461004226; 89000020240000766001520240651710P_0000_00000000000_000003461004226, 3461004226; 89000020240000766001520240651711P_0000_00000000000_000003461004226, 3461004226; 89000020240000766001520240651712P_0000_00000000000_000003461004226, 3461004226; 89000020240000766001520240651713P_0000_00000000000_000003461004226, 3461004226; 89000020240000766001520240651714P_0000_00000000000_000003461004226, 3461004226; 89000020240000766001520240651715P_0000_00000000000_000003461004226, 3461004226; 89000020240000766001520240651716P_0000_00000000000_000003461004226, 3461004226; 89000020240000766001520240651717P_0000_00000000000_000003461004226, 3461004226; 89000020240000766001520240651718P_0000_00000000000_000003461004226, 3461004226; 89000020240000766001520240651719P_0000_00000000000_000003461004226, 3461004226; 89000020240000766001520240651720P_0000_00000000000_000003461004226, 3461004226; 89000020240000766001520240651721P_0000_00000000000_000003461004226, 3461004226; 89000020240000766001520240651722P_0000_00000000000_000003461004226, 3461004226; 89000020240000766001520240651723P_0000_00000000000_000003461004226, 3461004226; 89000020240000766001520240651727P_0000_00000000000_000003461004226, 3461004226; 89000020240000766001520240651728P_0000_00000000000_000003461004226, 3461004226; 89000020240000766
A110: 2025-10-31 | B110: MIS_LT001_FLAG_GAR_INTRG_SAN | C110: MISSINGS | D110: Validar que não existem registos por preencher (Missings) | E110: BU_LOANTAPE_WORK.LT001_UNIV_OPER | F110: FLAG_GAR_INTRG_SAN | G110: 14293 | H110: 69 | I110: 3100031597018809600000000000000015310473251221141222159, NULL; 3100031597040209600000000000000015310473251221141222159, NULL; 31000315970139096000000000000000153114739853147326403031521, NULL; 31000315970006096000000000000000153104730221141222159, NULL; 3100031854200909700000000000000015310403022035122200, NULL; 31000311847794096000000000000000153114739853147326403031521, NULL; 31000315970311096000000000000000153104730221141222159, NULL; 31000315970212096000000000000000153114739853147326403031521, NULL; 3100031597023809600000000000000015310473251221141222159, NULL; 31000304140330096000000000000000153104710221141222120, NULL; 31000315970329096000000000000000153114739853147326403031521, NULL; 31000315970279096000000000000000153114739853147326403031521, NULL; 31000315970311096000000000000000153114739853147326403031521, NULL; 3100031854200909700000000000000015310403251220304122200, NULL; 31000315970402096000000000000000153104730221141222159, NULL; 3100031184779409600000000000000015310473251221141222159, NULL; 31000315970279096000000000000000153104730221141222159, NULL; 3100030414033009600000000000000015310471251221141222120, NULL; 3100031597013909600000000000000015310473251221141222159, NULL; 31000315970345096000000000000000153114739853147326403031521, NULL; 31000315970428096000000000000000153104730221141222159, NULL; 31000311450813096000000000000000153304730282030501403152, NULL; 31000315970139096000000000000000153104730221141222159, NULL; 31000307044893096000000000000000153104730221141222159, NULL; 310003159798900960000000000000001532043325122114122210, NULL; 31000304140330096000000000000000153114719853147126403031201, NULL; 31000313517171096000000000000000153114739853147326403031521, NULL; 3100031829309009700000000000000015320403022035122200, NULL; 3100031597042809600000000000000015310473251221141222159, NULL; 3100031597046909600000000000000015310473251221141222159, NULL; 3100031597989009600000000000000015321433985324332640403101, NULL; 3100030704489309600000000000000015310473251221141222159, NULL; 31000315970402096000000000000000153114739853147326403031521, NULL; 31000315970329096000000000000000153104730221141222159, NULL; 31000315970469096000000000000000153114739853147326403031521, NULL; 31000315970121096000000000000000153104730221141222159, NULL; 3100031597027909600000000000000015310473251221141222159, NULL; 3100030753091709600000000000000015310473251221141222159, NULL; 3100031145081309600000000000000015331047398533047326400031520, NULL; 31000315970469096000000000000000153104730221141222159, NULL; 31000315970238096000000000000000153104730221141222159, NULL; 3100031597026109600000000000000015310473251221141222159, NULL; 31000307044893096000000000000000153114739853147326403031521, NULL; 3100031351717109600000000000000015310473251221141222159, NULL; 3100031829309009700000000000000015320403251220304122200, NULL; 31000315970261096000000000000000153114739853147326403031521, NULL; 3100031597032909600000000000000015310473251221141222159, NULL; 3100031597012109600000000000000015310473251221141222159, NULL; 31000311847794096000000000000000153104730221141222159, NULL; 31000315970238096000000000000000153114739853147326403031521, NULL; 31000315970188096000000000000000153104730221141222159, NULL; 3100031597034509600000000000000015310473251221141222159, NULL; 3100031597000609600000000000000015310473251221141222159, NULL; 3100031854200909700000000000000015311403985314032640303001, NULL; 31000311450813096000000000000000153304730221141403152, NULL; 3100031829309009700000000000000015321403985324032640403001, NULL; 31000315970188096000000000000000153114739853147326403031521, NULL; 3100031597031109600000000000000015310473251221141222159, NULL; 31000315970212096000000000000000153104730221141222159, NULL; 31000313517171096000000000000000153104730221141222159, NULL; 3100031597021209600000000000000015310473251221141222159, NULL; 31000315970345096000000000000000153104730221141222159, NULL; 31000315970261096000000000000000153104730221141222159, NULL; 31000315970006096000000000000000153114739853147326403031521, NULL; 31000307530917096000000000000000153104730221141222159, NULL; 31000307530917096000000000000000153114739853147326403031521, NULL; 3100031597989009600000000000000015320433022114122210, NULL; 31000315970121096000000000000000153114739853147326403031521, NULL; 31000315970428096000000000000000153114739853147326403031521, NULL
A111: 2025-10-31 | B111: MIS_LT001_FLAG_INST_CAP | C111: MISSINGS | D111: Validar que não existem registos por preencher (Missings) | E111: BU_LOANTAPE_WORK.LT001_UNIV_OPER | F111: FLAG_INST_CAP | G111: 14293 | H111: 0
A112: 2025-10-31 | B112: MIS_LT001_FLAG_INST_DIV | C112: MISSINGS | D112: Validar que não existem registos por preencher (Missings) | E112: BU_LOANTAPE_WORK.LT001_UNIV_OPER | F112: FLAG_INST_DIV | G112: 14293 | H112: 0
A113: 2025-10-31 | B113: MIS_LT001_FLAG_INST_TITULOS | C113: MISSINGS | D113: Validar que não existem registos por preencher (Missings) | E113: BU_LOANTAPE_WORK.LT001_UNIV_OPER | F113: FLAG_INST_TITULOS | G113: 14293 | H113: 0
A114: 2025-10-31 | B114: MIS_LT002_INSTRMNT_ID | C114: MISSINGS | D114: Validar que não existem registos por preencher (Missings) | E114: BU_LOANTAPE_WORK.LT002_INSTRUMENT | F114: INSTRMNT_ID | G114: 4742 | H114: 0
A115: 2025-10-31 | B115: MIS_LT002_ISIN | C115: MISSINGS | D115: Validar que não existem registos por preencher (Missings) | E115: BU_LOANTAPE_WORK.LT002_INSTRUMENT | F115: ISIN | G115: 4742 | H115: 0
A116: 2025-10-31 | B116: MIS_LT002_ORGNL_AMNT_EUR | C116: MISSINGS | D116: Validar que não existem registos por preencher (Missings) | E116: BU_LOANTAPE_WORK.LT002_INSTRUMENT | F116: ORGNL_AMNT_EUR | G116: 4742 | H116: 0
A117: 2025-10-31 | B117: MIS_LT002_ORGNL_AMNT_FX | C117: MISSINGS | D117: Validar que não existem registos por preencher (Missings) | E117: BU_LOANTAPE_WORK.LT002_INSTRUMENT | F117: ORGNL_AMNT_FX | G117: 4742 | H117: 0
A118: 2025-10-31 | B118: MIS_LT002_CRRNCY_DNMNTN | C118: MISSINGS | D118: Validar que não existem registos por preencher (Missings) | E118: BU_LOANTAPE_WORK.LT002_INSTRUMENT | F118: CRRNCY_DNMNTN | G118: 4742 | H118: 0
A119: 2025-10-31 | B119: MIS_LT002_ACCRD_INTRST_INSTRMNT | C119: MISSINGS | D119: Validar que não existem registos por preencher (Missings) | E119: BU_LOANTAPE_WORK.LT002_INSTRUMENT | F119: ACCRD_INTRST_INSTRMNT | G119: 4742 | H119: 0
A120: 2025-10-31 | B120: MIS_LT002_TYP_INSTRMNT | C120: MISSINGS | D120: Validar que não existem registos por preencher (Missings) | E120: BU_LOANTAPE_WORK.LT002_INSTRUMENT | F120: TYP_INSTRMNT | G120: 4742 | H120: 0
