Workbook
Name _Toc51154475: 'B01.00'!#REF!
Name _Toc51154476: 'B01.00'!#REF!
Name _Toc51154477: 'B01.00'!#REF!
Name _Toc51154478: 'B01.00'!#REF!
Name _Toc51154479: 'B01.00'!#REF!
Name _Toc51154480: 'B01.00'!#REF!
Name _Toc51154482: 'B01.00'!#REF!
Name _Toc51154483: 'B01.00'!#REF!
Name _Toc51154484: 'B01.00'!#REF!
Name _Toc51154485: 'B01.00'!#REF!

Sheet B99.00 - Identification of the 
A1: B01.00 - Aggregate view: this tab includes information on an aggregate level for capital and liability items, including liabilities mandatorily excluded from the bail-in that are necessary to inform a preliminary NCWO assessment and the computation of conversion rates in accordance with Article 50 BRRD and EBA/GL/2017/03.
A2: Instruções SRB | I2: Análise IT
A3: Data Point | B3: ID | C3: Data type | D3: Type of constrain | E3: Description | F3: Treatment of "Not applicable" (if cell is grey out, input is not expected) | G3: Treatment of "Not available" (if cell is grey out, input is not expected) | I3: Desdodrável? | J3: Novo campo na tabela LT002? | K3: Mapeamento | L3: Description LT | M3: Field Definition LT | N3: Estado especificação
A4: Name of Legal Entity | B4: 0010 | C4: String | D4: Free text | E4: Free-form text identification of the incorporation name of the entity for which the table is reported. Please state the official name as listed in corporate registry, including the indication of the company form.
A5: LEI of Legal Entity | B5: 0020 | C5: String | D5: Free text | E5: The unique LEI code for the entity, in line with the requirements of EMIR or the Dodd-Frank Act, for which the report is submitted. In the absence of an LEI, the ECB Monetary Financial Institutions unique Identifier (MFIID) of the entity for use in RIAD (Register of Institutions and Affiliates Database) should be used. In the absence of both such identifiers, a local identifier must be used.
A6: Country of incorporation_x000D_ | B6: 0030 | C6: String | D6: ISO 3166-1 | E6: The ISO 3166-1 alpha-2 code of the country of incorporation of the entity._x000D_
A7: Name of the ultimate parent entity | B7: 0040 | C7: String | D7: Free text | E7: Free-form text identification of the incorporation name of the ultimate parent entity of the reporting entity, considered globally as the highest level of consolidation of the group. Please state the official name as listed in corporate registry, including the indication of the incorporation form.
A8: LEI of the ultimate parent entity | B8: 0041 | C8: String | D8: Free text | E8: The unique LEI code for the ultimate parent entity, in line with the requirements of EMIR or the Dodd-Frank Act, for which the report is submitted. In the absence of an LEI, the ECB Monetary Financial Institutions unique Identifier (MFI ID) of the entity for use in RIAD should be used. In the absence of both such identifiers, a local identifier must be used.
A9: Name of the Resolution Entity | B9: 0050 | C9: String | D9: Free text | E9: Free-form text identification of the incorporation name of the resolution entity (POE) of the reporting entity. Please state the official name as listed in corporate registry, including the indication of the incorporation form. If data point c0060 is ‘Resolution Entity’, the entry in this field must be the same as in data point c0010.
A10: LEI of the Resolution Entity | B10: 0051 | C10: String | D10: Free text | E10: The unique LEI code for the entity, in line with the requirements of EMIR or the Dodd-Frank Act, for which the report is submitted. In the absence of an LEI, the ECB Monetary Financial Institutions unique Identifier (MFIID) of the entity for use in RIAD should be used. In the absence of both such identifiers, a local identifier must be used. If data point c0060 is ‘Resolution Entity’, the entry in this field must the same as in data point c0020.
A11: Reporting entity type | B11: 0060 | C11: String | D11: Drop-down | E11: Status of the entity as indicated in the resolution plan. Please indicate either ‘Resolution Entity’ or ‘NonResolution Entity’.
A12: Reference date | B12: 0070 | C12: Date | D12: yyyy-mm-dd hh:mm:ss | E12: Reference date of the reported data in format: yyyy-mm-dd hh:mm:ss._x000D_
A13: Reported currency | B13: 0080 | C13: String | D13: 3-letters ISO 4217 | E13: The currency in which the report is submitted. The currency must be reported with its 3-letter ISO 4217 code. If the currency is not EUR, all the references to EUR throughout the Guidance and the template34 must be interpreted as being requested in local currency.
A14: EUR exchange rate_x000D_ | B14: 0090 | C14: Numeric | D14: 4 decimals | E14: The euro exchange rate used if a non-EUR currency is reported in data point r0080.

Sheet PDS
B1: PDS Especificação | N1: PDS Desenvolvimento
D2: Concluídos | J2: Não Concluídos | N2: Concluídos | O2: Não Concluídos
B3: Ficheiro | C3: Count | D3: Campo já existente no LT | E3: Campo já existente no LT - Nova Especificação | F3: Campo novo no LT | G3: Campo via Holístico | H3: Campo não LT (apenas tabela Output) | I3: Count | J3: Em curso | K3: Por iniciar | L3: Count | N3: Count | O3: Count
B4: B01.00-Aggregate view | C4: =COUNTA('B01.00'!A5:A10) -> 6 | D4: =COUNTIF('B01.00'!Q5:Q10,"Campo já existente no LT") -> 0 | E4: =COUNTIF('B01.00'!Q5:Q10,"Campo já existente no LT - Nova Especificação") -> 0 | F4: =COUNTIF('B01.00'!Q5:Q10,"Campo novo no LT") -> 0 | G4: =COUNTIF('B01.00'!Q5:Q10,"Campo via Holístico") -> 0 | H4: =COUNTIF('B01.00'!Q:Q,"Campo não LT (apenas tabela Output)") -> 0 | I4: =SUM(D4:H4) -> 0 | J4: =COUNTIF('B01.00'!Q5:Q10,"Em curso") -> 0 | K4: =COUNTIF('B01.00'!Q5:Q10,"Por iniciar") -> 6 | L4: =SUM(J4:K4) -> 6 | N4: =COUNTIF('B01.00'!R5:R10,"Concluído") -> 0 | O4: =COUNTIF('B01.00'!R5:R10,"Não Concluído") -> 6
B5: B02.00-Main Liabilities | C5: =COUNTA('B02.00'!A5:A85) -> 81 | D5: =COUNTIF('B02.00'!Q5:Q85,"Campo já existente no LT") -> 9 | E5: =COUNTIF('B02.00'!Q5:Q85,"Campo já existente no LT - Nova Especificação") -> 1 | F5: =COUNTIF('B02.00'!Q5:Q85,"Campo novo no LT") -> 15 | G5: =COUNTIF('B02.00'!Q5:Q85,"Campo via Holístico") -> 0 | H5: =COUNTIF('B02.00'!Q:Q,"Campo não LT (apenas tabela Output)") -> 56 | I5: =SUM(D5:H5) -> 81 | J5: =COUNTIF('B02.00'!Q5:Q85,"Em curso") -> 0 | K5: =COUNTIF('B02.00'!Q5:Q85,"Por iniciar") -> 0 | L5: =SUM(J5:K5) -> 0 | N5: =COUNTIF('B02.00'!R:R,"Concluído") -> 81 | O5: =COUNTIF('B02.00'!R:R,"Não Concluído") -> 0
B6: B05.00-Guarantees | C6: =COUNTA('B05.00'!A5:A19) -> 15 | D6: =COUNTIF('B05.00'!Q5:Q19,"Campo já existente no LT") -> 3 | E6: =COUNTIF('B05.00'!Q5:Q19,"Campo já existente no LT - Nova Especificação") -> 0 | F6: =COUNTIF('B05.00'!Q5:Q19,"Campo novo no LT") -> 1 | G6: =COUNTIF('B05.00'!Q5:Q19,"Campo via Holístico") -> 0 | H6: =COUNTIF('B05.00'!Q:Q,"Campo não LT (apenas tabela Output)") -> 11 | I6: =SUM(D6:H6) -> 15 | J6: =COUNTIF('B05.00'!Q5:Q19,"Em curso") -> 0 | K6: =COUNTIF('B05.00'!Q5:Q19,"Por iniciar") -> 0 | L6: =SUM(J6:K6) -> 0 | N6: =COUNTIF('B05.00'!R:R,"Concluído") -> 15 | O6: =COUNTIF('B05.00'!R:R,"Não Concluído") -> 0
B7: B90.00-Counterparties | C7: =COUNTA('B90.00'!A5:A15) -> 11 | D7: =COUNTIF('B90.00'!Q5:Q15,"Campo já existente no LT") -> 4 | E7: =COUNTIF('B90.00'!Q5:Q15,"Campo já existente no LT - Nova Especificação") -> 0 | F7: =COUNTIF('B90.00'!Q5:Q15,"Campo novo no LT") -> 2 | G7: =COUNTIF('B90.00'!Q5:Q15,"Campo via Holístico") -> 0 | H7: =COUNTIF('B90.00'!Q5:Q15,"Campo não LT (apenas tabela Output)") -> 5 | I7: =SUM(D7:H7) -> 11 | J7: =COUNTIF('B90.00'!Q5:Q15,"Em curso") -> 0 | K7: =COUNTIF('B90.00'!Q5:Q15,"Por iniciar") -> 0 | L7: =SUM(J7:K7) -> 0 | N7: =COUNTIF('B90.00'!R5:R15,"Concluído") -> 11 | O7: =COUNTIF('B90.00'!R5:R15,"Não Concluído") -> 0
B8: Total | C8: =SUM(C4:C7) -> 113 | D8: =SUM(D4:D7) -> 16 | E8: =SUM(E4:E7) -> 1 | F8: =SUM(F4:F7) -> 18 | G8: =SUM(G4:G7) -> 0 | H8: =SUM(H4:H7) -> 72 | I8: =SUM(D8:H8) -> 107 | J8: =SUM(J4:J7) -> 0 | K8: =SUM(K4:K7) -> 6 | L8: =SUM(J8:K8) -> 6 | N8: =SUM(N4:N7) -> 107 | O8: =SUM(O4:O7) -> 6
I9: =(I8/C8) -> 0.94690265 | L9: =L8/C8 -> 0.053097345 | N9: =N8/C8 -> 0.94690265 | O9: =O8/C8 -> 0.053097345

Sheet Notas LT002
A1: O Bail-in constará na Tabela LT002 em que:
A2: - Os campos desdobráveis (os que têm mais do que 1 valor para o mesmo contrato) terão os valores separados por ;? O separador de campos num CSV já é ; pelo que se deveria selecionar outro separador.
A3: - Terão de se identificar os campos desdobráveis
A4: - Existem campos que não estão preparados para desdobrar (Gross carrying amount)
A5: Se em algum momento a Corporação/SRB exigirem o desdobramento, terá depois se efetuar um desenvolvimento que pega no vetor e faz o desdobramento
A7: Temos 3 tipos de campos:
A8: - Os que já existem atualmente no LT e que vão que ter que ser desdobrados -> vamos ter de alterar estes campos para poderem desdobrar (G) dado que não se quer criar campos novos iguais mas que desdobrem
A9: - Os que vão manter o valor (ou seja o valor repete-se) e que não são vetores -> não tem de se fazer nada
A10: - Os que são desdobráveis
A13: LT002 As Is
A14: contrato | B14: GCA
A15: 32023234234234300 | B15: 30000
A17: LT002 Intermédia
A18: contrato | B18: zcliente | C18: segmento_xpto | D18: GCA
A19: 32023234234234300 | B19: 123 | C19: A | D19: 30000
A20: 32023234234234300 | B20: 123 | C20: B | D20: 30000
A21: 32023234234234300 | B21: 1234 | C21: C | D21: 30000
A23: LT002 To Be
A24: contrato | B24: zcliente | C24: segmento_xpto | D24: GCA
A25: 32023234234234300 | B25: 123;123;1234 | C25: A;B;C | D25: 30000
A27: Se for preciso abrir no futuro:
A28: contrato | B28: zcliente | C28: segmento_xpto | D28: GCA
A29: 32023234234234300 | B29: 123 | C29: A | D29: 10000
A30: 32023234234234300 | B30: 123 | C30: B | D30: 10000
A31: 32023234234234300 | B31: 1234 | C31: C | D31: 10000

Sheet Notas Financeira
A1: # | B1: Comentário | C1: Data set
A2: 1 | B2: Terá de atacar as tabelas fazendo o filtro para passivo com exceção do Data point 5 que tem uma parte de extrapatrimonial | C2: TODOS
A3: =+A2+1 -> 2 | B3: Os depósitos de clientes terá de ser feito um cruzamento com a tabela do FGD (FG001_FGD no cap tools). Os depósitos depois são divididos entre cobertos e não cobertos sendo que têm tratamento diferente consoante o caso. | C3: TODOS
A4: =+A3+1 -> 3 | B4: Para a parte das emissões de títulos, a ligação entre a AL029/AL030 e a CT610 deverá ser feita por ISIN/ZDEPOSIT | C4: 1. DATA POINTS FOR IDENTIFICATION

Sheet Diagrama_Estrutura_Accionista
A3: FALSE

Sheet B01.00
A1: B01.00 - Aggregate view: this tab includes information on an aggregate level for capital and liability items, including liabilities mandatorily excluded from the bail-in that are necessary to inform a preliminary NCWO assessment and the computation of conversion rates in accordance with Article 50 BRRD and EBA/GL/2017/03.
A2: SRB Instructions | I2: Especificação IT | S2: lt833_agreg_campos
I3: Fase 1 - Granular (Loan Tape) | N3: Fase 2 - Agregada (Não Loan Tape) | P3: Comentários/Histórico EF | Q3: Estado Especificação | R3: Estado Desenvolvimento
A4: Data Point | B4: ID | C4: Data type | D4: Constrain | E4: Description | F4: Treatment of "Not applicable" (if cell is grey out, input is not expected) | G4: Treatment of "Not available" (if cell is grey out, input is not expected) | I4: Novo campo? | J4: Nome campo | K4: Missing Value (LT804) | L4: Not Applicable Value (LT804) | M4: Regra campo | N4: Nome campo | O4: Regra campo | S4: tabela_condicao | T4: campo_condicao | U4: valor_condicao | V4: tabela_origem | W4: campo_origem | X4: campo_destino | Y4: campo_exp | Z4: acao | AA4: ckutulmo | AB4: htimest | AC4: ambito | AD4: segmento | AE4: segmento_agregado | AF4: ref_date | AG4: cod_visao | AH4: Estado preenchimento
A5: Row number | B5: 0010 | C5: Numeric | D5: Integer | E5: The unique number / primary key to identify the row items (the number must be an integer). | I5: Não | N5: out_b0100_aggregate_view.0010_row_nmbr | O5: Sequenciador a implementar na tabela de output out_b0100_aggregate_view Nota: A cada execução não deverão ser gerados Row numbers diferentes pelo que provisoriamente deverá ser feito um order by Insolvency ranking desc (alinhado com o exemplo apresentado no documento 2024-11-05_Annex-II_Facilitating-Instructions_0.pdf - páginas 30 e 31) | Q5: Por iniciar | R5: Não Concluído | X5: 1 | Y5: 0010 | Z5: SEQUENCIA | AC5: SRB | AE5: B0100 | AG5: 1 | AH5: Concluido
A6: Insolvency ranking | B6: 0020 | C6: String | D6: Free text | E6: The corresponding insolvency ranking of the instrument. Numeric value (e.g. integer of 1 or more). | I6: Não | N6: out_b0100_aggregate_view.0020_rank_insolv | O6: out_b0200_main_liabilities.0160_rank_insolv | Q6: Por iniciar | R6: Não Concluído | S6: lt002_instrument | T6: ind_univ | U6: B0200 | V6: lt002_instrument | W6: inslvncy_rnkng | X6: 2 | Y6: 0020 | Z6: AGRUPAR | AC6: SRB | AE6: B0100 | AG6: 1 | AH6: Concluido
A7: Category | B7: 0030 | C7: String | D7: Drop-down | E7: Please indicate the liability category only for the following items: title of ownership, reserves, liabilities eligible for bail-in, and liabilities that must be excluded from the bail-in in accordance with Article 44(2) of the BRRD, as per the following drop-down values: • Covered deposits (BRRD art. 44/2/a) • Secured liabilities - collateralized part (BRRD art. 44/2/b) • Client liabilities, if protected in insolvency (BRRD art. 44/2/c) • Fiduciary liabilities, if protected in insolvency (BRRD art. 44/2/d) • Institution liabilities < 7 days (BRRD art. 44/2/e) • System (operator) and CCP liabilities < 7 days (BRRD art. 44/2/f) • Employee liabilities (BRRD art. 44/2/g/i) • Critical service liabilities (BRRD art. 44/2/g/ii) • Tax and social security authorities liabilities, if preferred (BRRD art. 44/2/g/iii) • DGS liabilities (BRRD art. 44/2/g/iv) • Liabilities towards other entities of the resolution group (BRRD art. 44/2/h) • Liabilities eligible for bail-in • Other equity items • Title of ownership | I7: Não | N7: out_b0100_aggregate_view.0030_lblty_ctgry | O7: Na out_b0200_main_liabilities existe o campo 0140_ntr_lblty (que se alimenta do campo lt002_instrument.typ_instrmnt passando por uma parametrização na LT829). Este campo foi parametrizado para possibilitar 2 valores: 1005 (Debt Securities) -> Registered Bond 2006 (Equity) -> Title of ownership Possíveis Soluções: 1) Criar novo campo lt002_instrument.lblty_ctgry que se alimentaria de uma parametrização a criar na lt831_param_conceitos com base no campo lt002_instrument.typ_instrmnt (e depois a tabela final out_b0100_aggregate_view alimentaria-se deste campo): 1005 (Debt Securities) -> Liabilities eligible for bail-in?? 2006 (Equity) -> Title of ownership ver sheet "LT831" 2) Não criar novo campo lt002_instrument.lblty_ctgry, criar apenas o conceito na lt831_param_conceitos com base no 0140_ntr_lblty da out_b0200_main_liabilities (e depois a tabela final out_b0100_aggregate_view alimentaria-se deste conceito) Registered Bond -> Liabilities eligible for bail-in?? Title of ownership -> Title of ownership ver sheet "LT831" Nota: Preenchia-se 'AUX' no campo 'tabela_conceito' da LT831, dado que não é possível efetuar o upload naLT831 sem preencher o campo 'tabela_conceito' (é apresentado erro). Isto para evitar que o campo fique Hard-coded na tabela final out_b0100_aggregate_view: CASE WHEN 0140_ntr_lblty='Title of ownership' THEN 'Title of ownership' WHEN 0140_ntr_lblty='Registered Bond' THEN 'Liabilities eligible for bail-in' ELSE '' END AS 0030_lblty_ctgry | Q7: Por iniciar | R7: Não Concluído | S7: lt002_instrument | T7: ind_univ | U7: B0200 | V7: lt002_instrument | W7: ctgry | X7: 3 | Y7: 0030 | Z7: AGRUPAR | AC7: SRB | AE7: B0100 | AG7: 1 | AH7: Concluido
A8: Counterparty type | B8: 0040 | C8: String | D8: Drop-down | E8: Please refer to data point {B90.00;c0070}. This data point is relevant only for liabilities that must be excluded from bail-in in accordance with Article 27(3) SRMR. Hence, it should not be reported for: • Liabilities eligible for bail-in • Other equity items • Title of ownership | I8: Não | N8: out_b0100_aggregate_view.0040_cntrprty_typ | O8: É referido que este campo não deve ser reportado para: • Liabilities eligible for bail-in • Other equity items • Title of ownership Dado que o universo de contratos do MBDT do BST "encaixam" precisamente nestes 3 valores (a confirmar com Pedro Mendes), então não deveremos reportar este campo, certo? Em caso afirmativo, reportar Valor fixo 'Not applicable' de acordo com o exemplo apresentado no documento 2024-11-05_Annex-II_Facilitating-Instructions_0.pdf - páginas 30 (campo preenchido a vazio) e 31 (campo preenchido com 'Not applicable'). Caso o entendimento anterior esteja incorreto, ou seja se o campo for para reportar, é referido Please refer to data point {B90.00;c0070}. Contudo, esta info está errada dado que o Counterparty type é o campo c0080 (e não o c0070) da B90.00. Adicionalmente verifica-se no documento Annex I - Minimum Bail-in Data Template (MBDT) tables a presença da combo box com o valores possíveis do campo c0080 | Q8: Por iniciar | R8: Não Concluído | S8: lt002_instrument | T8: ind_univ | U8: B0200 | V8: lt002_instrument | W8: intrnl_sgmnt | X8: 4 | Y8: 0040 | Z8: AGRUPAR | AC8: SRB | AE8: B0100 | AG8: 1 | AH8: Concluido
A9: Relevant amount for Bail-in/WDC | B9: 0050 | C9: Numeric | D9: 2 decimals | E9: Please refer to data field {B02.00;c0130}. For derivatives, please refer to data field {B03.00;c0110}. For SFTs, please refer to data field {B04.00;c0080}. Liabilities mandatorily excluded from bail-in in accordance with Article 44(2)(h) BRRD shall be reported in the corresponding row item (i.e. not as “liabilities eligible for bail-in”). | F9: Input "Not applicable" | I9: Não | N9: out_b0100_aggregate_view.0050_rlvnt_amnt_wdc | O9: out_b0200_main_liabilities.0130_rlvnt_amnt_wdc | Q9: Por iniciar | R9: Não Concluído | S9: lt002_instrument | T9: ind_univ | U9: B0200 | V9: lt005_instr_ent | W9: grss_crryng_amnt_instrmnt | X9: 5 | Y9: 0050 | Z9: SOMAR | AC9: SRB | AE9: B0100 | AG9: 1 | AH9: Concluido
A10: Amount excluded from Bail-in/WDC | B10: 0060 | C10: Numeric | D10: 2 decimals | E10: Indicate the outstanding amount mandatorily excluded from bail-in in accordance with Article 27(3) SRMR. | I10: Não | N10: out_b0100_aggregate_view.0060_amnt_excldd_wdc | O10: Valor fixo 0? | Q10: Por iniciar | R10: Não Concluído | S10: lt002_instrument | T10: ind_univ | U10: B0200 | V10: lt005_instr_ent | W10: otstndng_amnt_excldd | X10: 6 | Y10: 0060 | Z10: SOMAR | AC10: SRB | AE10: B0100 | AG10: 1 | AH10: Concluido

Sheet lt834_agreg_segmento
A1: lt834_agreg_segmento
A2: ind_univ | B2: ckutulmo | C2: htimest | D2: ambito | E2: segmento | F2: segmento_agregado | G2: ref_date | H2: cod_visao
A3: B0200 | D3: SRB | F3: B0100 | H3: 1
A4: B0200 | D4: SRB | F4: B0200 | H4: 1
A5: B0500 | D5: SRB | F5: B0500 | H5: 1
D6: SRB | F6: B9000 | H6: 1
A8: Notas:
A9: Não se preenche o ind_unvi da última linha pois aplica-se a todos os registos. Dado que queremos todas as Contrapartes, quer as do Passivo (Títulos) quer do Ativo (Garantias).
A10: O ind_univ vai ser traduzido na lt829/lt830 para responder ao campo "Tab of origin" (Se ind_univ=Passivo reportar B0200; Se ind_univ=Ativo reportar B0500). Como tal, nesta tabela têm de constar o valor já traduzido (que é o valor final que vai aparecer na LT002)
A11: Luís Capitão-Mor referiu que a tabela tem de estar preparada também para receber IN ('X',''Y,'Z') apesar de não ser preciso no âmbito do Bail-in

Sheet B02.00
A1: B02.00 - Main Liabilities: the tab includes the data points requested at resolution entity (point of entry) level for the implementation of the bail-in tool, or at non resolution entity level (up to the Senior Non-Preferred layer)11 for monitoring and implementing the loss transfer and recapitalisation mechanisms. Generally, the data points in this tab are requested at individual level12. However, some specific data points may be requested at consolidated level on an adhoc basis by the IRT
A2: SRB Instructions | I2: Especificação IT
I3: Fase 1 - Granular (Loan Tape) | N3: Fase 2 - Agregada (Não Loan Tape) | P3: Comentários/Histórico EF
A4: Data Point | B4: ID | C4: Data type | D4: Constrain | E4: Description | F4: Treatment of "Not applicable" (if cell is grey out, input is not expected) | G4: Treatment of "Not available" (if cell is grey out, input is not expected) | I4: Novo campo? | J4: Nome campo | K4: Missing Value (LT804) | L4: Not Applicable Value (LT804) | M4: Regra campo | N4: Nome campo | O4: Regra campo | Q4: Estado Especificação | R4: Estado Desenvolvimento | S4: Necessita de ajuste? (2025-10-31 vs 2025-11-14)
A5: Row number | B5: 0010 | C5: Numeric | D5: Integer | E5: The unique number / primary key to identify the row items (the number must be an integer). | I5: Não | N5: out_b0200_main_liabilities.0010_row_nmbr | O5: Sequenciador a implementar na tabela de output out_b0200_main_liabilities Nota: A cada execução não deverão ser gerados Row numbers diferentes pelo que provisoriamente deverá ser feito um order by instrmnt_id | P5: Reunião 2025-06-16 Luís Capitão-Mor, Pedro Mendes, Luísa Sousa | Q5: Campo não LT (apenas tabela Output) | R5: Concluído | S5: NÃO | T5: =IF(SEARCH(B5,N5,4),"ok","nok") -> ok
A6: Unique internal identification number | B6: 0020 | C6: String | D6: Free text | E6: The unique internal identifier of the instrument/liability. For deposits reported on an aggregate level, please indicate: ▪ ‘NCNP’ for the aggregated not covered not preferential deposits (field c0280 = TRUE); and ▪ ‘NCBP’ for the aggregated not covered but preferential deposits (field c0290 = TRUE). | I6: Não | J6: lt002_instrument.instrmnt_id | L6: {=_xlfn.SWITCH(C6,"Numeric","999999999999999","String","Not applicable","Date","0001-01-01")} -> Not applicable | N6: out_b0200_main_liabilities.0020_uniq_id | O6: lt002_instrument.instrmnt_id | P6: Reunião 2025-06-16 Luís Capitão-Mor, Pedro Mendes, Luísa Sousa | Q6: Campo já existente no LT | R6: Concluído | S6: NÃO | T6: =IF(SEARCH(B6,N6,4),"ok","nok") -> ok
A7: Unique identification number (known to the counterparty) | B7: 0030 | C7: String | D7: Free text | E7: The unique identifier of the instrument/liability that would allow the counterparty to conclude that it will be affected by the potential resolution action, without external third parties being able to identify the creditor. For securities, the ISIN code must be indicated where available (other identifiers need only be provided in the absence of an ISIN). For deposits and other liabilities, the account/contract number should be reported. In the event of multiple tranches (multiple counterparties) of one promissory-note loan (e.g. Schuldscheindarlehen) or a syndicated loan, a unique ID must be allocated to each tranche. For deposits reported on an aggregate level, please indicate: ▪ ‘NCNP’ for the aggregated not covered not preferential deposits (field c0280 = TRUE); and ▪ ‘NCBP’ for the aggregated not covered but preferential deposits (field c0290 = TRUE). | I7: Não | J7: lt002_instrument.isin | L7: {=_xlfn.SWITCH(C7,"Numeric","999999999999999","String","Not applicable","Date","0001-01-01")} -> Not applicable | N7: out_b0200_main_liabilities.0030_uniq_id_knwn_cntrprty | O7: lt002_instrument.isin | P7: Reunião 2025-06-16 Luís Capitão-Mor, Pedro Mendes, Luísa Sousa | Q7: Campo já existente no LT | R7: Concluído | S7: NÃO | T7: =IF(SEARCH(B7,N7,4),"ok","nok") -> ok
A8: Type of the unique identifier (known to the counterparty) | B8: 0040 | C8: String | D8: Free text, but fixed values for specific items | E8: Free text, to indicate what type of identifier has been used in data point c0020, e.g. if the identifier is an ISIN, please input ‘ISIN’; if the identifier is an account number, please input ‘Account number’; if the identifier is a contract number, please input ‘Contract number’. For deposits reported on an aggregate level, please indicate ‘Aggregated’. | I8: Não | N8: out_b0200_main_liabilities.0040_typ_uniq_id_knwn_cntrprty | O8: Valor fixo 'ISIN' | P8: Reunião 2025-06-16 Luís Capitão-Mor, Pedro Mendes, Luísa Sousa: Neste caso não faz sentido criar o campo no Loan Tape quando ele já existe, portanto será criado apenas na tabela output out_b0200_main_liabilities. Caso contrário haveria um princípio de colisão, pois estar-se-ia a repetir conceitos de campos. | Q8: Campo não LT (apenas tabela Output) | R8: Concluído | S8: NÃO | T8: =IF(SEARCH(B8,N8,4),"ok","nok") -> ok
A9: Original amount issued in EUR | B9: 50 | C9: Numeric | D9: 2 decimals | E9: The EUR (counter)value of the total issue size of the instrument, irrespective of the effective issuance dates, i.e. the total nominal amount / face value of a specific liability. For shares, it should reflect the face value / carrying amount of the shares. If a nominal value does not exist, this field is not applicable. This data point is not applicable for cash accounts / saving accounts and deposits reported in aggregated form (Submission A). If a value is reported in a foreign currency (c0060), the amount must additionally be converted into euros and reported in the corresponding EUR field (c0050), using the euro reference exchange rate published by the ECB on the date for which the information is reported40. In the case of foreign currencies for which no euro reference exchange rate is available, a customary market reference rate must be used. If such other customary reference exchange rates are used, a uniform source must be used wherever possible. | F9: Input 999999999999999 | I9: Sim | J9: lt002_instrument.orgnl_amnt_eur | L9: {=_xlfn.SWITCH(C9,"Numeric","999999999999999","String","Not applicable","Date","0001-01-01")} -> 999999999999999 | M9: Se flag_inst_titulos = '1': Obter campo nom_tot_inic da ct610_titulos. Adicionalmente, efetuar conversão via tabela cambios, seguindo a lógica definida nos restantes processos, dado que o campo nom_tot_inic está expresso na moeda original (campo cmoeda). Exemplo de query que utiliza a tabela cambios para converter moeda original em moeda eur (quando é eur a tcmbme é 1 pelo que o valor é igual): SELECT DISTINCT concat(cempresa,cbalcao, cnumecta, zdeposit), (ct610.nom_tot_inic / cambios.tcmbme) AS orgnl_amnt_eur FROM (SELECT cempresa,cbalcao, cnumecta, zdeposit, nom_tot_inic, cmoeda FROM cd_captools.ct610_titulos WHERE ref_date='${ref_date}' and concat(cempresa,cbalcao, cnumecta, zdeposit) IN ( '31641600000000000PTSTOGOM0003000', '31641600005800007PTBSRDOM0037000', '31641600005800007PTSTOCOM0007000', '31641600005800007PTCPP0AM0007000', '31641600000000000PTSTOEOM0021000', '31641600000000000PTSTOHOM0002000', '31641600000000000PTBSREOM0028000', '31641600000000000PTSTOFOM0004000')) ct610 LEFT JOIN (SELECT cmoeda, tcmbme FROM cd_captools.cambios WHERE data_date_part = '${ref_date}' AND dcambio = '${ref_date}' AND zseqcamb = 99 AND ctbcamb = 'F' AND cmarca = 'BT') cambios ON cambios.cmoeda = ct610.cmoeda; Se flag_inst_titulos = '0': Not applicable. O respetivo valor default de Not applicable deverá ser parametrizado na lt804_conf_dflt. | N9: out_b0200_main_liabilities.0050_orgnl_amnt_eur | O9: lt002_instrument.orgnl_amnt_eur | P9: Reunião 2025-08-04 Luís Capitão-Mor, Pedro Mendes, Luísa Sousa | Q9: Campo novo no LT | R9: Concluído | S9: NÃO | T9: =IF(SEARCH(B9,N9,4),"ok","nok") -> ok
A10: Original amount issued in foreign currency | B10: 0060 | C10: Numeric | D10: 2 decimals | E10: Same as c0050 above, but in the foreign currency (where relevant). Please also report the EUR-converted amount in the corresponding EUR field (c0050). This data point is not applicable for cash accounts / savings accounts and deposits reported in aggregated form (Submission A). | F10: Input 999999999999999 | I10: Sim | J10: lt002_instrument.orgnl_amnt_fx | L10: {=_xlfn.SWITCH(C10,"Numeric","999999999999999","String","Not applicable","Date","0001-01-01")} -> 999999999999999 | M10: Se flag_inst_titulos = '1' e se campo cmoeda da ct610_titulos = '978' (eur): Not applicable. O respetivo valor default de Not applicable deverá ser parametrizado na lt804_conf_dflt. Se flag_inst_titulos = '1' e se campo cmoeda da ct610_titulos <> '978' (eur): Obter campo nom_tot_inic da ct610_titulos Se flag_inst_titulos = '0': Not applicable. O respetivo valor default de Not applicable deverá ser parametrizado na lt804_conf_dflt. | N10: out_b0200_main_liabilities.0060_orgnl_amnt_fx | O10: lt002_instrument.orgnl_amnt_fx | P10: Reunião 2025-08-04 Luís Capitão-Mor, Pedro Mendes, Luísa Sousa | Q10: Campo novo no LT | R10: Concluído | S10: NÃO | T10: =IF(SEARCH(B10,N10,4),"ok","nok") -> ok
A11: Contract currency | B11: 0070 | C11: String | D11: 3-letters ISO 4217 | E11: The currency in which the instrument/liability is issued. The currency must be reported with its 3-letter ISO 4217 code. For deposits reported on an aggregate level, please indicate ‘XXX’. | F11: Input "XXX" | I11: Não | J11: lt002_instrument.crrncy_dnmntn | L11: XXX | N11: out_b0200_main_liabilities.0070_cntrct_crrncy | O11: lt002_instrument.crrncy_dnmntn | P11: Reunião 2025-06-16 Luís Capitão-Mor, Pedro Mendes, Luísa Sousa | Q11: Campo já existente no LT | R11: Concluído | S11: NÃO | T11: =IF(SEARCH(B11,N11,4),"ok","nok") -> ok
A12: Outstanding principal amount | B12: 80 | C12: Numeric | D12: 2 decimals | E12: The EUR (counter)value of the outstanding principal amount of the instrument/liability. The difference between the original amount issued and the outstanding principal amount may be due to partial buybacks of the instrument, amortising instruments, etc. The portion of eligible liabilities subscribed by intragroup entities and excluded under Article 27(3)(h) SRMR must be included in the outstanding principal amount. Only claims against other parties must be reported (i.e. excluding the portion held by the entity itself, which must be reported in field c0090). For zero coupon bonds issued at discount (i.e. c0240 = ZCB issued at discount) the final redemption amount should be reported. | I12: Sim | J12: lt005_instr_ent.otstndng_prncpl_amnt | L12: {=_xlfn.SWITCH(C12,"Numeric","999999999999999","String","Not applicable","Date","0001-01-01")} -> 999999999999999 | M12: Se flag_inst_titulos = '1': Passo 1: Verificar para cada "entty_id" (de um determinado "instrmnt_id") da lt005_instr_ent se o mesmo consta no vetor "zcliente_investidor" da ct610_titulos (desse "instrmnt_id"). Se constar, identificar em que posição consta e em seguida obter do vetor "nom_tot_ini_investe" da ct610_titulos o montante que consta nessa posição; Passo 2: Verificar se a soma dos vários "nom_tot_ini_investe" é igual ao "nom_tot_inic", da ct610_titulos -> Se for igual: Não é necessária ação adicional -> Se for diferente: Somar essa diferença no "entty_id" 0000000000 Passo 3: Dado que o "outstanding principal amount" que se pretende é o atual e não o inicial, então terá de se multiplicar os vários "nom_tot_ini_investe" pelo rácio "nom_tot_atual"/"nom_tot_inic", da ct610_titulos. Nota: O Universo do MBDT terá sempre este rácio=1 e portanto o valor inicial será igual ao valor atual, contudo, se existissem titularizações (onde se aplica o conceito de pool factor), o valor inicial seria diferente do valor atual (porque o "pool_factor" seria diferente de 1). Passo 4: Converter o montante obtido para eur pela tabela de cambios (ver query de conversão já definida no campo Original amount issued in EUR (0050)) Se flag_inst_titulos = '0': Not applicable. O respetivo valor default de Not applicable deverá ser parametrizado na lt804_conf_dflt. Na sheet "Aux Campos Montante" consta um exemplo com a aplicação desta lógica. | N12: out_b0200_main_liabilities.0080_otstndng_prncpl_amnt | O12: Soma "otstndng_prncpl_amnt" - Soma "portion_amnt_rprtng_entty", por cada instrmnt_id da lt005_instr_ent Na sheet "Aux Campos Montante" consta um exemplo com a aplicação desta lógica. | P12: Reunião 2025-10-09 Luís Capitão-Mor, Pedro Mendes Reunião 2025-09-22 e 2025-09-18 Luís Capitão-Mor, Pedro Mendes: Segundo Luís Capitão-Mor não se pode utilizar o campo OTSTNDNG_NMNL_AMNT_INSTRMNT da lt002_instrument dado que esse campo é contabilístico (a pedido do guia do BCE) e o SRB não pede contabilístico. Adicionalmente, interpretou-se da definição dada pelo SRB que se pretende retirar as recompras do BST e deve-se incluir o que está no Santander S.A (ou seja não deve se retirar o que está no Santander S.A.). Exemplo 1: Emissão de 1000M eur em que: 100M eur estão recomprados pelo BST 900M eur estão no mercado (e destes 900M eur, 500M eur estão no Santander S.A.) Ou seja, neste exemplo o Outstanding principal amount deverá ser 900M eur. Exemplo 2: Emissão 1000M eur a 95% (abaixo do par), portanto 950M eur. Na contabilidade na data inicial consta Outstanding principal amount=950M eur mas na ct610_titulos constam 1000M eur. Ou seja, o valor contabilístico nem sempre é igual ao não contabilístico. | Q12: Campo novo no LT | R12: Concluído | S12: NÃO | T12: =IF(SEARCH(B12,N12,4),"ok","nok") -> ok
A13: Portion of instrument or liability held by the reporting entity | B13: 0090 | C13: Numeric | D13: 2 decimals | E13: The EUR amount related to the portion of the liability held by the reporting entity itself. The amount can either be defined as the principal amount plus accrued interest and fees and charges, or as the relevant portion of fair value held by the reporting entity itself, in the event that field c0250 applies. This data point is only relevant for securities. | F13: Input 999999999999999 | I13: Sim | J13: lt005_instr_ent.prtn_amnt_rprtng_entty | L13: {=_xlfn.SWITCH(C13,"Numeric","999999999999999","String","Not applicable","Date","0001-01-01")} -> 999999999999999 | M13: Se flag_inst_titulos = '1': Verificar para cada "entty_id" (de um determinado "instrmnt_id") da lt005_instr_ent se o mesmo corresponde ao "zcliente_emitente" da ct610_titulos (desse "instrmnt_id"). Se não corresponder: Reportar 0 Se corresponder: Verificar se esse "entty_id" consta no vetor "zcliente_investidor" da ct610_titulos. Se constar: Passo 1: Identificar em que posição consta no vetor "zcliente_investidor" e em seguida obter do vetor "nom_tot_ini_investe" da ct610_titulos o montante que consta nessa posição; Passo 2: Dado que o "Portion of instrument or liability held by the reporting entity" que se pretende é o atual e não o inicial, então terá de se multiplicar o montante obtido no passo anterior pelo rácio "nom_tot_atual"/"nom_tot_inic", da ct610_titulos; Passo 3: Converter para eur pela tabela de cambios (ver query de conversão já definida no campo Original amount issued in EUR (0050)). Se não constar: Reportar 0 Se flag_inst_titulos = '0': Not applicable. O respetivo valor default de Not applicable deverá ser parametrizado na lt804_conf_dflt. Na sheet "Aux Campos Montante" consta um exemplo com a aplicação desta lógica. | N13: out_b0200_main_liabilities.0090_prtn_amnt_rprtng_entty | O13: Soma "prtn_amnt_rprtng_entty", por cada instrmnt_id da lt005_instr_ent Na sheet "Aux Campos Montante" consta um exemplo com a aplicação desta lógica. | P13: Reunião 2025-10-09 Luís Capitão-Mor, Pedro Mendes Reunião 2025-09-22 e 2025-09-18 Luís Capitão-Mor, Pedro Mendes | Q13: Campo novo no LT | R13: Concluído | S13: NÃO | T13: =IF(SEARCH(B13,N13,4),"ok","nok") -> ok
A14: Accrued interest | B14: 100 | C14: Numeric | D14: 2 decimals | E14: The EUR (counter)value of the outstanding accrued interest on the instrument. In jurisdictions where accrued interests do not rank pari passu to the principal liability amount, the relevant NRAs have the option to request the reporting of interest accruals on separate line items (41). Only claims against third parties must be reported (i.e. excluding the proportion held by the entity itself, which must be reported in field c0090). In case the field is not applicable (e.g. shares, zero coupon bonds issued at discount), please refer to the specific instructions in the Technical Annex. (41) - In such cases, please refer to the specific reporting example in Annex II, paragraph 3.7. | F14: Input 999999999999999 | G14: Leave blank | I14: Sim | J14: lt002_instrument.accrd_intrst_instrmnt (campo já existente a alterar) lt005_instr_ent.accrd_intrst_instrmnt (campo novo a criar) | L14: {=_xlfn.SWITCH(C14,"Numeric","999999999999999","String","Not applicable","Date","0001-01-01")} -> 999999999999999 | M14: lt002_instrument.accrd_intrst_instrmnt (campo já existente a alterar): O campo accrd_intrst_instrmnt (da lt002_instrument) está atualmente a sair com valor 0 para estes registos de Títulos Passivos (o que não é suposto dado que existem registos que deveriam ter valor). O campo accrd_intrst_instrmnt (da lt002_instrument) alimenta-se do campo juros_corridos (da lt001_univ_oper) e é calculado atualmente da seguinte forma (segundo "Especificação - BCE Loan Tape_20250915 LF + ESTR"): NVL ( SUM(-1*juros_corridos) ,0 ) O campo juros_corridos (da lt001_univ_oper) será calculado da seguinte forma (segundo re-especificação solicitada por Gonçalo Filipe, email 5 de agosto de 2025 12:58): SUM(MSALDO_FINAL) WHERE COD_PLANO = 'BST_IND' AND CCONTAB_FINAL_PCSB NOT LIKE '28%' AND COMPOSICAO_VALOR = 'juros/rendimentos a receber' AND TIPO_CONTA = 'A' AND CARTEIRA_CONTABILISTICA IN ('ativos financeiros ao custo amortizado','ativos financeiros ao justo valor atraves de outro rendimento integral','ativos financeiros ao justo valor atraves de resultados') Constata-se portanto que o campo juros_corridos (da lt001_univ_oper) não contempla atualmente o Passivo (razão pela qual o campo sai com valor 0), pelo que deverá ser adicionada a condição do "OR" abaixo: SUM(MSALDO_FINAL) WHERE ( COD_PLANO = 'BST_IND' AND CCONTAB_FINAL_PCSB NOT LIKE '28%' AND COMPOSICAO_VALOR = 'juros/rendimentos a receber' AND TIPO_CONTA = 'A' AND CARTEIRA_CONTABILISTICA IN ('ativos financeiros ao custo amortizado','ativos financeiros ao justo valor atraves de outro rendimento integral','ativos financeiros ao justo valor atraves de resultados') ) OR ( COD_PLANO = 'BST_IND' AND COMPOSICAO_VALOR = 'juros/encargos a pagar' AND TIPO_CONTA = 'P' AND CARTEIRA_CONTABILISTICA IN ('passivos financeiros ao custo amortizado') ) - Luís Capitão-Mor, Luísa Sousa, Gonçalo Filipe e Dora Roxo não identificaram impacto nesta alteração. lt005_instr_ent.accrd_intrst_instrmnt (campo novo a criar): 'Se flag_inst_titulos = '1': Efetuar exatamente a mesma especificação da lt002_instrument.accrd_intrst_instrmnt mas obtendo o valor por cada "entty_id" (na lt001_univ_oper). Ex: Para o contrato 'A' (cempresa, cbalcao, cnumecta, zdeposit) temos 3 linhas com a seguinte distribuição de juros_corridos na lt001_univ_oper: cempresa+cbalcao+cnumecta+zdeposit= 'A' | zcliente='1' | juros_corridos = 10 cempresa+cbalcao+cnumecta+zdeposit= 'A' | zcliente='2' | juros_corridos = 20 cempresa+cbalcao+cnumecta+zdeposit= 'A' | zcliente='3' | juros_corridos = 30 Atualmente o campo accrd_intrst_instrmnt da lt002_instrument calcula simplesmente a soma dos vários montantes de juros_corridos por contrato, ou seja, na lt002_instrument é apresentado uma única linha: instrmnt_id= 'A' | accrd_intrst_instrmnt = 60 O que se pretende no novo campo accrd_intrst_instrmnt a criar na lt005_instr_ent: instrmnt_id= 'A' | entty_id=1 | accrd_intrst_instrmnt = 10 instrmnt_id= 'A' | entty_id=2 | accrd_intrst_instrmnt = 20 instrmnt_id= 'A' | entty_id=3 | accrd_intrst_instrmnt = 30 Se flag_inst_titulos = '0': Not applicable. O respetivo valor default de Not applicable deverá ser parametrizado na lt804_conf_dflt. | N14: out_b0200_main_liabilities.0100_accrd_intrst_instrmnt | O14: (-1) * Soma "accrd_intrst_instrmnt ", por cada instrmnt_id da lt005_instr_ent Nota: Esta multiplicação por -1, deve-se ao facto de no Loan Tape o campo accrd_intrst_instrmnt apresentar valores negativos (para o caso destes registos de Títulos Passivos) e neste report pretenderem-se valores positivos (segundo Pedro Mendes). Ex: O contrato 31 6416 00000000000 PTBSREOM0028000 (para 2025-06-30) tem saldo de juros +418465.480000 na fr001_univ_saldo e terá +418465.480000 na lt001_univ_oper (após a nova re-especificação do Gonçalo Filipe, atualmente tem -418465.480000) e terá -418465.480000 na lt002_instrument (dada a fórmula NVL ( SUM(-1*juros_corridos) ,0 )). É portanto necessária a multiplicação por -1, ficando assim +418465.480000. Deverá ser feita a multiplicação por -1 e não o valor absoluto (abs), dado que poderá vir a existir algum contrato contra natura. | P14: Reunião 2025-10-09 Luís Capitão-Mor, Pedro Mendes Reunião 2025-09-16 Luís Capitão-Mor, Pedro Mendes, Luísa Sousa | Q14: Campo já existente no LT - Nova Especificação | R14: Concluído | S14: SIM | T14: =IF(SEARCH(B14,N14,4),"ok","nok") -> ok
A15: Applicable fees and charges | B15: 110 | C15: Numeric | D15: 2 decimals | E15: Total EUR amount of applicable fees and charges (e.g. contractual fees for late payments) linked to the instrument, if the fee or charge is payable and due, but not yet settled with the counterparty as of the request date. This is to the extent that the fee or charge is not covered within the outstanding principal amount, the accrued interest or a separate liability. Fees and charges do not include agios or fees in conjunction with the listing of an instrument. Only claims against third parties must be reported (i.e. excluding the proportion held by the entity itself, which must be reported in field c0090). In case the field is not applicable (e.g. shares), please refer to the specific instructions in the Technical Annex. | F15: Input 999999999999999 | G15: Leave blank | I15: Não | N15: out_b0200_main_liabilities.0110_applcbl_fees_charges | O15: Valor fixo 0 | P15: Reunião 2025-09-22 Luís Capitão-Mor, Pedro Mendes, Luísa Sousa Solução 1: Dado que o BST não tem comissões que ainda não tenham sido pagas/liquidadas (not yet settled) neste Universo de Títulos, reportar neste campo valor fixo 0 na tabela final (out_b0200_main_liabilities). Segundo Pedro Mendes, nem sequer existem comissões iniciais neste Universo de Títulos dado que é tudo feito internamente ou com o Banco Santander S.A.. Solução 2: Trazer as comissões periodificadas da Contabilidade, contudo, essas comissões periodificadas podem ter sido pagas ou não, pelo que não é exatamente o que o SRB pede, dado que o SRB refere que quer as não pagas. Esta solução implicaria criar um campo novo no Loan Tape e trazer um conceito que não é o que o SRB solicita. Adicionalmente o resultado deste campo seria um conjunto vazio para este Universo de Títulos. Solução 3: Criar um campo novo na ct610_titulos. Contudo, este campo seria dinâmico pelo que também não seria uma boa solução. Dadas as soluções apresentadas, optou-se pela solução 1. OLD: Reunião 31/10/2024 Luís Capitão-Mor, Pedro Mendes: Segundo Luís Capitão-Mor, Pedro Mendes, este campo aplica-se aos custos periodificados do banco (ainda não pagos, que estão pendentes de pagar) nas emissões que o Banco faz de covered bonds, seniores,... (estão no Passivo do Banco), tem de se pagar aos Advogados, etc. Naturalmente, este campo não se aplica a Depósitos. Ações solicitadas por Luís Capitão-Mor: - Agendar reunião com Rafael Pessoa/Carlos Fernandes para ver onde constam estes custos na fr802 (devem ter uma conta contabilistica), levando para a reunião 2 exemplos de covered bonds: 1) Identificar esses 2 exemplos para uma data mais recente; 2) Verificar na ct001 quais as contas PCSB (uma conta 50%) e IFRS associadas; 3) Verificar se para essas contas consta na composicao_valor ou noutro campo da fr802 a indicação de comissão ou despesa 4) Verificar se esta comissão ficou ou não incluida no gross carrying amount (provavelmente foi incluido). 5) Verificar na fr004 se já existe lá este conceito de comissão (só seria para adicionar na fr004 caso fosse um conceito que faça sentido para a contabilidade) 6) Tabela de conceitos ct872 (tem os conceitos com base em campos da fr802): criar nesta tabela o conceito caso ele não exista. | Q15: Campo não LT (apenas tabela Output) | R15: Concluído | S15: NÃO | T15: =IF(SEARCH(B15,N15,4),"ok","nok") -> ok
A16: Outstanding amount | B16: 0120 | C16: Numeric | D16: 2 decimals | E16: Total EUR value of the outstanding amount of the instrument/deposit held by the counterparty, calculated as the sum of the amounts reported in data points c0080, c0100 and c0110 (where applicable). The amount is in fact the aggregate of the outstanding principal amount plus, if applicable, interest accrued up to the reference date, and fees and charges, irrespective of whether and to what extent the relevant principal, interest or fee-and-charge liability was already due as at the reference date and whether it is required to be recognised as a liability item in the relevant entity’s balance sheet drawn up in accordance with the applicable accounting principles. In jurisdictions where accrued interest may not rank pari passu to the liability amount, the relevant NRA may request the reporting of interest accruals on separate line items. | F16: Input 999999999999999 | I16: Não | N16: out_b0200_main_liabilities.0120_otstndng_amnt | O16: Soma dos 3 campos acima (0080, 0100 e 0110 ): Outstanding principal amount + Accrued interest + Applicable fees and charges | P16: Reunião 2025-10-09 Luís Capitão-Mor, Pedro Mendes Reunião 2025-09-22 Luís Capitão-Mor, Pedro Mendes, Luísa Sousa: Tem de se ter presente que neste campo vamos somar o "Outstanding principal amount" (que não é contabilístico, vem da ct610_titulos) com o "Accrued interest" (que é contabilístico) e com o "Applicable fees and charges" (que é contabilístico). Ou seja, 2 campos vão-se buscar à Contabilidade mas 1 campo não se vai buscar à Contabilidade, o que não é totalmente coerente. Contudo, não se vê tema dado que o SRB não refere que este campo tem de "bater" com a Contabilidade. | Q16: Campo não LT (apenas tabela Output) | R16: Concluído | S16: SIM | T16: =IF(SEARCH(B16,N16,4),"ok","nok") -> ok
A17: Relevant amount for Bail-in/WDC | B17: 0130 | C17: Numeric | D17: 2 decimals | E17: Total EUR value of the amount eligible for write-down / conversion. Pursuant to Article 48(1) BRRD, resolution authorities shall exercise the write-down and conversion powers in accordance with the cascade set out in letters (a) to (e) of Article 48(1) BRRD. Article 48(2) BRRD further provides that "when applying the write down or conversion powers, resolution authorities shall allocate the losses [...] by reducing the principal amount of, or outstanding amount payable in respect of, those shares or other instruments of ownership and bail-inable liabilities to the same extent pro rata to their value (42) […]". The portion of eligible liabilities subscribed by intragroup entities and excluded under Article 27(3)(h) SRMR must not be reported as part of the relevant amount for bail-in / WDC. When determining the relevant amount for bail-in, entities shall take into account national laws that transpose the BRRD. If those provisions do not provide complete and clear guidance for determining the relevant amount for bail-in, careful consideration should in general be given to how the item in question is dealt with under applicable insolvency legislation43. Furthermore, the contractual terms governing each liability might provide additional insight when performing this assessment. For debt instruments with embedded derivatives, the following list of items shall be considered: ▪ Any contractually defined floor or cap to the final redemption amount. ▪ Any contractually defined early termination amount, if such amount is deemed to represent the investor’s claim in insolvency/resolution. ▪ The performance of the underlying, whenever it impacts the repayment of the principal amount. ▪ The contractual provisions ruling the payment of interests, to assess whether the accrued component can be properly determined and is relevant for bail-in purposes. ▪ The inclusion of an Article 12c(2)(b) SRMR clause. ▪ Any element relevant to Article 12c(2)(a) SRMR. ▪ Any settlement/close out costs. ▪ Any other term, condition, rule, mechanism or element affecting the making, timing and amount of any kind of payment owed to the holders of the debt instruments with embedded derivatives (please specify). Without prejudice to the considerations above, in principle: • the relevant amount for bail-in is defined as the outstanding amount (including accrued interest and fees, when applicable) less any existing components subject to exemptions according to Article 27(3) SRMR (e.g. covered share for bail-inable deposits indicated in data point c0300), or other factors affecting the conversion amount (e.g. safeguards under Articles 76 to 80 BRRD, as applicable); • for zero coupon bonds issued at discount (i.e. c0240 = ZCB issued at discount), the amount to be reported is the amortised face value (i.e. initially paid up amount plus accrued component of the discount) plus any applicable fees and charges (c0110); and • for structured instruments, the amount reported in field c0270 minus the value of the collateral (if given) should in principle be considered the relevant amount. In case of products where the derivative component is only affecting the coupon payment (i.e. c0250 = Only structured coupon), please refer to the points above.applicable insolvency legislation43. Furthermore, the contractual terms governing each liability might provide additional insight when performing this assessment. For debt instruments with embedded derivatives, the following list of items shall be considered: ▪ Any contractually defined floor or cap to the final redemption amount. ▪ Any contractually defined early termination amount, if such amount is deemed to represent the investor’s claim in insolvency/resolution. ▪ The performance of the underlying, whenever it impacts the repayment of the principal amount. ▪ The contractual provisions ruling the payment of interests, to assess whether the accrued component can be properly determined and is relevant for bail-in purposes. ▪ The inclusion of an Article 12c(2)(b) SRMR clause. ▪ Any element relevant to Article 12c(2)(a) SRMR. ▪ Any settlement/close out costs. ▪ Any other term, condition, rule, mechanism or element affecting the making, timing and amount of any kind of payment owed to the holders of the debt instruments with embedded derivatives (please specify). Without prejudice to the considerations above, in principle: • the relevant amount for bail-in is defined as the outstanding amount (including accrued interest and fees, when applicable) less any existing components subject to exemptions according to Article 27(3) SRMR (e.g. covered share for bail-inable deposits indicated in data point c0300), or other factors affecting the conversion amount (e.g. safeguards under Articles 76 to 80 BRRD, as applicable); • for zero coupon bonds issued at discount (i.e. c0240 = ZCB issued at discount), the amount to be reported is the amortised face value (i.e. initially paid up amount plus accrued component of the discount) plus any applicable fees and charges (c0110); and • for structured instruments, the amount reported in field c0270 minus the value of the collateral (if given) should in principle be considered the relevant amount. In case of products where the derivative component is only affecting the coupon payment (i.e. c0250 = Only structured coupon), please refer to the points above. In jurisdictions where accrued interest may not rank pari passu to the liability amount, the relevant NRA may request the reporting of interest accruals on separate line items. Own holdings (identified in field c0090) should be deducted. (42) - For the definition of ‘value’, please refer to EBA Q&A 2017_3629 (https://www.eba.europa.eu/single-rule-book-qa/- /qna/view/publicId/2017_3629). | I17: Não | N17: out_b0200_main_liabilities.0130_rlvnt_amnt_wdc | O17: Reportar Outstanding amount (0120) | P17: Reunião 2025-09-24 Luís Capitão-Mor, Pedro Mendes: Segundo Pedro Mendes, neste campo deve reportar-se o mesmo que é reportado no Outstanding amount (0120). O Outstanding amount (0120) é a Soma de 3 campos: Outstanding principal amount (0080) + Accrued interest (0100) + Applicable fees and charges (0110). Não se deve reportar o Outstanding principal amount (0040) dado que não contém juros, e segundo Pedro Mendes em caso de resolução os juros devem ser considerados (apesar de na definição não ser referido pelo SRB que se pretende juros), como tal, deve apontar-se para o Outstanding amount (0120), que contém juros. O Outstanding amount (0120) também contém Applicable fees and charges (0110), mas esse campo conterá valor fixo 0. | Q17: Campo não LT (apenas tabela Output) | R17: Concluído | S17: SIM | T17: =IF(SEARCH(B17,N17,4),"ok","nok") -> ok
A18: Nature of the liability | B18: 0140 | C18: String | D18: Drop-down | E18: The corresponding category of the instrument/liability. Value to be chosen from the following drop-down list: • Registered Bond • Bearer Bond • Borrower Note Loan • Certificate of Deposit / Commercial paper • Title of ownership44 • Cash account/saving account45 • Term deposit46 • Loan • Bill of exchange • Other For deposits reported on an aggregated level (Submission A), please indicate ‘Other’. | I18: Não | J18: lt002_instrument.typ_instrmnt | L18: {=_xlfn.SWITCH(C18,"Numeric","999999999999999","String","Not applicable","Date","0001-01-01")} -> Not applicable | M18: Necessário criar novas parametrizações nas tabelas lt829_regras_conversao e lt830_conversoes, podendo as mesmas ser consultadas neste documento nas sheets: LT829 - filtrando por campo_conceito = 'TYP_INSTRMNT' e regra_conversao = '2'; LT830 - filtrando por segmento = 'ESTR' e campo_conceito = 'TYP_INSTRMNT'. | N18: out_b0200_main_liabilities.0140_ntr_lblty | O18: lt002_instrument.typ_instrmnt | P18: Parametrizações da lt829_regras_conversao e da lt830_conversoes validadas com Luísa Sousa em 2025-08-13. Adicionalmente, acrescentou-se na lt831_param_conceitos uma nova linha com instrmnt_fncr='titulos de divida emitidos' a mapear para o valor_destino='1005' dado que estes registos estavam a ser preenchidos com typ_instrmnt= '2020' (ou seja, 'Other'). Reunião 2025-07-25 Luís Capitão-Mor, Luísa Sousa | Q18: Campo já existente no LT | R18: Concluído | S18: NÃO | T18: =IF(SEARCH(B18,N18,4),"ok","nok") -> ok
A19: Nature of the liability (if other) | B19: 0141 | C19: String | D19: Free text | E19: Free text. If ‘Other’ is selected in field c0140, include a meaningful description of the nature of the liability. | I19: Não | N19: out_b0200_main_liabilities.0141_ntr_lblty_othr | O19: Valor fixo 'Not applicable' | P19: Email Pedro Mendes 12/01/2026 17:20: Considerou-se que o campo "Nature of the liability" (c0140) terá sempre um valor diferente de 'Other' e por conseguinte o campo "Nature of the liability (if other)" nunca terá valor. Como tal, sugere-se o preenchimento deste campo com valor fixo 'Not applicable'. Reunião 2025-07-25 Luís Capitão-Mor, Luísa Sousa | Q19: Campo não LT (apenas tabela Output) | R19: Concluído | S19: NÃO | T19: =IF(SEARCH(B19,N19,4),"ok","nok") -> ok
A20: Structurally subordinated | B20: 0150 | C20: String | D20: TRUE / FALSE boolean | E20: Indicate whether the instrument is considered structurally subordinated (i.e. groups with a HoldCo/OpCo structure). The value to be reported is a TRUE/FALSE Boolean. | I20: Não | N20: out_b0200_main_liabilities.0150_flg_strctrlly_sbrdntd | O20: Valor fixo 'Not applicable' | P20: Reunião 2025-06-23 Luís Capitão-Mor, Pedro Mendes, Luísa Sousa: Segundo o anexo III, este campo deve, em princípio, ser considerado não aplicável para non-resolution entities. Pedro Mendes enviou email dia 24-06 confirmando que este campo é não aplicável. "Sim, confirmo que todos os campos são não aplicáveis." | Q20: Campo não LT (apenas tabela Output) | R20: Concluído | S20: NÃO | T20: =IF(SEARCH(B20,N20,4),"ok","nok") -> ok
A21: Insolvency ranking | B21: 0160 | C21: Numeric | D21: Integer | E21: The corresponding insolvency ranking of the instrument. Numeric value (e.g. integer of 1 or more). | I21: Sim | J21: lt002_instrument.rank_insolv | L21: {=_xlfn.SWITCH(C21,"Numeric","999999999999999","String","Not applicable","Date","0001-01-01")} -> 999999999999999 | M21: Se flag_inst_titulos = '1': Obter rank_insolv da ct610_titulos; Se flag_inst_titulos = '0': Não preencher | N21: out_b0200_main_liabilities.0160_rank_insolv | O21: lt002_instrument.rank_insolv | P21: Reunião 2025-06-20 Luís Capitão-Mor, Pedro Mendes, Luísa Sousa | Q21: Campo novo no LT | R21: Concluído | S21: NÃO | T21: =IF(SEARCH(B21,N21,4),"ok","nok") -> ok
A22: Contractual subordination | B22: 0161 | C22: Numeric | D22: 2 decimals | E22: Numeric sequence to indicate whether an instrument/liability is subordinated within the same insolvency rank as a result of its own contractual terms. The inclusion of these contractual terms should duly consider paragraph 141 of the EBA report on the monitoring of Additional Tier 1 (AT1) instruments of European Union (EU) institutions47, as well as any country-specific provision in this regard. The value of the field must be indicated using the corresponding insolvency ranking to which the instrument pertains and the numeric sequence of its contractual subordination, separated by a dot (e.g. two instruments in insolvency rank 2 subordinated to each other will have this field set to 2.01 and 2.02). Please refer to the specific reporting example (Annex II, paragraph 3.6). | F22: Input 999999999999999 | I22: Não | N22: out_b0200_main_liabilities.0161_cntrctl_sbrdntn | O22: Valor fixo 999999999999999 | P22: Reunião 2025-07-31 Luís Capitão-Mor, Pedro Mendes: Segundo Pedro Mendes, este campo é not applicable porque na nossa operativa as emissões têm sempre o mesmo grau de subordinação dentro do mesmo ranking. Ou seja, por exemplo no caso do ranking 4 não teremos 4.01, 4.02, 4.03 dado que é tudo ranking 4. | Q22: Campo não LT (apenas tabela Output) | R22: Concluído | S22: NÃO | T22: =IF(SEARCH(B22,N22,4),"ok","nok") -> ok
A23: Bail-in cascade | B23: 162 | C23: String | D23: Fixed values | E23: (Alpha)numeric sequence to indicate the order of write-down and conversion pursuant to Article 48 BRRD. If the priority order of this cascade differs from the one stemming from the insolvency ranking reported in field c0160, please refer to the relevant Country Annex or to the specific instructions provided by the relevant NRA/IRT. When allowed under the applicable national law, institutions must reflect in this sequence the order provided by the applicable contractual subordination. Please refer to the specific reporting example (Annex II, paragraph 3.6). The bail-in cascade assigned to secured liabilities shall always be the one applicable to the (potentially) unsecured part of the liability based on the current internal valuation of the collateral by the bank. | I23: Não | J23: lt002_instrument.rank_insolv | L23: {=_xlfn.SWITCH(C23,"Numeric","999999999999999","String","Not applicable","Date","0001-01-01")} -> Not applicable | N23: out_b0200_main_liabilities.0162_bail_in_cascade | O23: lt002_instrument.rank_insolv | P23: Reunião 2025-07-30 Luís Capitão-Mor, Pedro Mendes, Luísa Sousa: No caso de Portugal o bail-in cascade é igual ao ranking de insolvência. | Q23: Campo não LT (apenas tabela Output) | R23: Concluído | S23: NÃO | T23: =IF(SEARCH(B23,N23,4),"ok","nok") -> ok
A24: Date of issuance | B24: 0170 | C24: Date | D24: yyyy-mm-dd | E24: Date of the original issuance of the liability. Format required: yyyy-mm-dd. This field is not applicable for liabilities of the type ‘Cash account/saving account’ (c0140) and deposits reported in aggregated form (Submission A). For securities issued as part of a tap issue, i.e. an issuance of additional securities under an ISIN that already exists, there should only be one row including all securities under that ISIN. The date of issuance should be the issuance date of the first issue under that ISIN. | I24: Não | J24: lt002_instrument.dt_incptn | L24: {=_xlfn.SWITCH(C24,"Numeric","999999999999999","String","Not applicable","Date","0001-01-01")} -> 0001-01-01 | N24: out_b0200_main_liabilities.0170_dt_incptn | O24: lt002_instrument.dt_incptn | P24: Reunião 2025-06-23 Luís Capitão-Mor, Pedro Mendes, Luísa Sousa | Q24: Campo já existente no LT | R24: Concluído | S24: NÃO | T24: =IF(SEARCH(B24,N24,4),"ok","nok") -> ok
A25: Date of the next interest payment | B25: 0180 | C25: Date | D25: yyyy-mm-dd | E25: The payment date from which the income distribution is made available for payment by the reporting entity. Format required: yyyy-mm-dd. If not applicable (e.g. shares), the bank should report ‘0001-01-01’. This field is not applicable for deposits reported in aggregated form (Submission A). | F25: Input "0001-01-01" | G25: Leave blank | I25: Sim | J25: lt002_instrument.dt_nxt_intrst_pymnt | L25: {=_xlfn.SWITCH(C25,"Numeric","999999999999999","String","Not applicable","Date","0001-01-01")} -> 0001-01-01 | M25: ‣ Para o universo aplicável, obter campos "dt_prox_liq_juros_act" e "dt_prox_liq_juros_pas" da cd_alm.al029_cnt_core_m. Para cada contrato, mapear com o campo que estiver preenchido. Ou seja, se num determinado contrato estiver preenchido o "dt_prox_liq_juros_act" então mapear este campo, se estiver preenchido o "dt_prox_liq_juros_pas" então mapear este campo (se nenhum dos 2 campos estiver preenchido então é um "MISS") ‣ Para o universo não aplicável (dt_nxt_intrst_pymnt ='1111-11-11' -> valor de Not Applicable para data), necessário criar nova parametrização na tabela lt831_param_conceitos, podendo a mesma ser consultada neste documento na sheet 'LT831' filtrando por tabela_conceito = 'LT002_INSTRUMENT' e campo_conceito = 'DT_NXT_INTRST_PYMNT'. Nota: Deverá seguir-se a mesma lógica de obtenção de campos de ALM que atualmente existe no Loan Tape | N25: out_b0200_main_liabilities.0180_dt_nxt_intrst_pymnt | O25: lt002_instrument.dt_nxt_intrst_pymnt | P25: Reunião 2025-08-08 Luís Capitão-Mor, Pedro Mendes, Luísa Sousa: Segundo Luís Capitão-Mor, o universo Not Applicable deste campo é o mesmo do campo PYMNT_FRQNCY. O PYMNT_FRQNCY tem definidos os typ_instrumnt not applicable na lt803_codigos_lt (procurar na lt803_codigos_lt por campo_lt= 'PYMNT_FRQNCY_NA'). Dado que este campo é um campo novo então deverá efetuar-se essa parametrização mas na lt831_param_conceitos (e não na lt803_codigos_lt). Reunião 2025-08-06 Luís Capitão-Mor, Pedro Mendes, Luísa Sousa Reunião 2025-06-23 Luís Capitão-Mor, Pedro Mendes, Luísa Sousa | Q25: Campo novo no LT | R25: Concluído | S25: NÃO | T25: =IF(SEARCH(B25,N25,4),"ok","nok") -> ok
A26: Date of the next (partial) redemption payment | B26: 0190 | C26: Date | D26: yyyy-mm-dd | E26: The payment date or the date on which the (partial) redemption payment is due for payment (e.g. cases in which a portion of the liabilities is reimbursed before the final legal maturity). If not applicable, please report the final legal maturity (c0210). This field is not applicable for liabilities of the type ‘Cash account/saving account’ (c0140) and for deposits reported in aggregated form (Submission A). | F26: Input the final legal maturity of the liability (c0210) | I26: Não | J26: lt002_instrument.dt_lgl_fnl_mtrty | L26: 1111-11-11 | N26: out_b0200_main_liabilities.0190_dt_nxt_rdmptn_pymnt | O26: lt002_instrument.dt_lgl_fnl_mtrty | P26: Reunião 2025-09-16 Luís Capitão-Mor, Pedro Mendes: O conceito de date of the next redemption payment é aplicável aos Títulos, no limite, pode ser a data de maturidade. Identificaram-se 2 Soluções possíveis: Solução 1: Criar um campo novo no Loan Tape (caso não exista): ‣ Para o universo aplicável, obter campos "dt_prox_amort_capital_act" e "dt_prox_amort_capital_pas" da cd_alm.al029_cnt_core_m. Para cada contrato, mapear com o campo que estiver preenchido. Ou seja, se num determinado contrato estiver preenchido o "dt_prox_amort_capital_act" então mapear este campo, se estiver preenchido o "dt_prox_amort_capital_pas" então mapear este campo (se nenhum dos 2 campos estiver preenchido então é um "MISS") ‣ Para o universo não aplicável, necessário criar nova parametrização na tabela lt831_param_conceitos Solução 2: Não criar o campo no Loan Tape, e na tabela de output final (out_b0200_main_liabilities) apontar este campo para o campo lt002_instrument.dt_lgl_fnl_mtrty, dado que nos registos deste Universo de Títulos este campo corresponde sempre à data de maturidade e não se prevê que esta situação se altere no futuro. Dado que a Solução 1 é mais dispendiosa (apesar de ser mais resiliente), nesta fase optou-se pela Solução 2. Adicionalmente, confirmou-se que não existe valor nos campos "dt_prox_amort_capital_act" e "dt_prox_amort_capital_pas" na cd_alm.al029_cnt_core_m para os registos deste Universo de Títulos. Query: select distinct concat(cempresa,cbalcao,cnumecta,zdeposit) as contrato, trim(dt_prox_amort_capital_act) , trim(dt_prox_amort_capital_pas) from cd_alm.al029_cnt_core_m where ref_date = '2025-06-30' and concat(cempresa,cbalcao,cnumecta,zdeposit) in ( '31641600000000000PTSTOGOM0003000', '31641600005800007PTBSRDOM0037000', '31641600005800007PTSTOCOM0007000', '31641600005800007PTCPP0AM0007000', '31641600000000000PTSTOEOM0021000', '31641600000000000PTSTOHOM0002000', '31641600000000000PTBSREOM0028000', '31641600000000000PTSTOFOM0004000') order by 1; | Q26: Campo não LT (apenas tabela Output) | R26: Concluído | S26: NÃO | T26: =IF(SEARCH(B26,N26,4),"ok","nok") -> ok
A27: Earliest redemption date | B27: 0200 | C27: Date | D27: yyyy-mm-dd | E27: If an option exists for holders of the instrument to request early reimbursement, or conditions for early reimbursement are contractually provided, the earliest occurrence date should be reported. Format required: yyyy-mm-dd. If that date corresponds to the legal maturity (c0210), please report the latter. If not applicable, the bank should report ‘0001-01-01’. This field is not applicable for liabilities of the type ‘Cash account/saving account’ (c0140) and for deposits reported in aggregated form (Submission A). | F27: Input "0001-01-01" | I27: Não | N27: out_b0200_main_liabilities.0200_dt_erlst_rdmptn | O27: Valor fixo ‘0001-01-01’. | P27: Reunião 2025-09-10 Luís Capitão-Mor, Pedro Mendes, Luísa Sousa: Segundo Pedro Mendes, este campo é na visão do Investidor. Ou seja, para o âmbito em questão é não aplicável, só o Banco tem a opção de terminar a emissão mais cedo em datas pré-definidas. Portanto, decidiu-se que este campo será reportado com o valor fixo ‘0001-01-01’ (Not applicable). | Q27: Campo não LT (apenas tabela Output) | R27: Concluído | S27: NÃO | T27: Campo a visitar na próxima reunião
A28: Legal maturity | B28: 0210 | C28: Date | D28: yyyy-mm-dd | E28: Date of the legal, final maturity of the instrument or liability (including term deposits). Format required: yyyy-mm-dd. For perpetual instruments, the bank should report ‘2099-01-31’. If not applicable, the bank should report ‘0001-01-01’. This field is not applicable for liabilities of the type ‘Cash account/saving account’ (c0140) and for deposits reported in aggregated form (Submission A). | F28: Input "0001-01-01" | I28: Não | J28: lt002_instrument.dt_lgl_fnl_mtrty | L28: 1111-11-11 | M28: ‣ Necessário criar novas parametrizações nas tabelas lt829_regras_conversao e lt830_conversoes, podendo as mesmas ser consultadas neste documento nas sheets: LT829 - filtrando por campo_conceito = 'DT_LGL_FNL_MTRTY' e regra_conversao = '1'; LT830 - filtrando por segmento = 'ESTR' e campo_conceito = 'DT_LGL_FNL_MTRTY'. | N28: out_b0200_main_liabilities.0210_dt_lgl_fnl_mtrty | O28: lt002_instrument.dt_lgl_fnl_mtrty | P28: Reunião 2025-08-06 Luís Capitão-Mor, Pedro Mendes, Luísa Sousa Reunião 2025-06-23 Luís Capitão-Mor, Pedro Mendes, Luísa Sousa Nota: Mariana Romão comentou que não é necessário colocar na parametrização da lt829 a linha de quando é not in ('9999-12-31', '1111-11-11') a mapear para o dt_lgl_fnl_mtrty, dado que o código já está a fazer isso, ou seja, o código aplica as parametrizações que estão na lt029 e o que não estiver traz o que vem no campo (neste caso o dt_lgl_fnl_mtrty). | Q28: Campo já existente no LT | R28: Concluído | S28: NÃO | T28: =IF(SEARCH(B28,N28,4),"ok","nok") -> ok
A29: Governing law | B29: 0220 | C29: String | D29: ISO 3166-1 alpha 2 / ISO 3166-2 | E29: The ISO 3166-1 alpha-2 code of the country whose law governs the instrument (please use the ISO 3166-2 code when the law of an administrative subdivision is relevant, e.g. ‘US-NY’). If the contract is governed by the law of more than one country, the country whose law has the highest relevance for the recognition of write-down and conversion powers must be reported. For deposits reported on an aggregate level, please indicate ‘XX’. | F29: Input "XX" | I29: Não | J29: lt002_instrument.governing_law | L29: XX | N29: out_b0200_main_liabilities.0220_governing_law | O29: lt002_instrument.governing_law | P29: Reunião 2025-06-23 Luís Capitão-Mor, Pedro Mendes, Luísa Sousa | Q29: Campo já existente no LT | R29: Concluído | S29: NÃO | T29: =IF(SEARCH(B29,N29,4),"ok","nok") -> ok
A30: Bail-in recognition clause | B30: 0230 | C30: String | D30: Drop-down | E30: Indicate one of the following: • Yes, supported by Legal Opinion = the liability includes a bail-in recognition clause in line with Article 55 BRRD that is supported by a legal opinion; • Yes, not supported by Legal Opinion = the liability includes a bail-in recognition clause in line with Article 55 BRRD that is currently not supported by a legal opinion; • No = the liability does not include a bail-in recognition clause; • Not applicable = the bail-in clause is not applicable (e.g. the governing law is not that of a third country, or a recognition clause is not requested as the third-country jurisdiction recognises the powers of the resolution authority). • Aggregated = deposits reported on an aggregated level. | F30: Input "Not applicable" | I30: Não | N30: out_b0200_main_liabilities.0230_bail_in_rcgntn_cls | O30: Valor fixo 'Yes, supported by Legal Opinion' | P30: Email Pedro Mendes 12/01/2026 17:20: Todas as emissões que fazem parte do perímetro do MBDT contêm clausulas contratuais que reconhecem o Bail-in. Estas emissões são feitas com o apoio de um escritórios de advogados externo ao Banco e são feitas com o propósito de poderem ser utilizadas no caso de um bail-in. Desta forma, todas as emissões têm uma opinião legal com o reconhecimento do bail-in Reunião 2025-07-30 Luís Capitão-Mor, Pedro Mendes, Luísa Sousa | Q30: Campo não LT (apenas tabela Output) | R30: Concluído | S30: NÃO | T30: =IF(SEARCH(B30,N30,4),"ok","nok") -> ok
A31: Zero-Coupon | B31: 0240 | C31: String | D31: Drop-down | E31: Indicate whether the instrument/liability is: • ZCB issued at discount = liabilities issued at discount where the principal / face value of 100% will be repaid at maturity; • ZCB not issued at discount = liabilities issued at a face value of 100%, where there is one payment at maturity that consists of the face value and the accrued interest; • No ZCB = the liability is not a zero coupon bond; • Aggregated = deposits reported on an aggregated level. | I31: Não | N31: out_b0200_main_liabilities.0240_zero_coupon | O31: Valor fixo 'No ZCB' | P31: Email Pedro Mendes 12/01/2026 17:20: O BST não tem ZCBs (Zero Coupon Bonds) e não se prevê que venha a ter, como tal, sugere-se o preenchimento deste campo com valor fixo 'No ZCB'. Reunião 2025-07-30 Luís Capitão-Mor, Pedro Mendes, Luísa Sousa | Q31: Campo não LT (apenas tabela Output) | R31: Concluído | S31: NÃO | T31: =IF(SEARCH(B31,N31,4),"ok","nok") -> ok
A32: Structured product | B32: 0250 | C32: String | D32: Drop-down | E32: Indicate whether the instrument/liability is to be considered structured or contains specific non-standard terms, using one of the following values: • Non-structured/Vanilla; • Structured; • Other non-standard terms = “Non-standardised terms” refers to terms and conditions that may influence, among others, the nature and maturity of the contract. Examples of such non-standardised terms are material-adverse-change clauses, termination options with rising interest rates etc; • Only structured coupon = “Only structured coupon” refers to structured product where the derivative component only affects the coupon payment, namely is fully capital guaranteed with no possibility to reimburse at maturity an amount (excluding the coupon) that differs from the nominal amount. In addition, it is applicable only in case the accrued interest can be computed; • Aggregated = deposits reported on an aggregated level. A structured instrument is defined as a debt obligation with an embedded derivative component and whose returns are determined by an underlying, e.g. an underlying security or index (public or special index, e.g. based on shares or bonds, fixed-income investments or loan, foreign exchange, commodities, etc.). Structured debt instruments do not cover debt instruments with an underlying only call or put options, i.e. the value of the instrument is not determined by an embedded derivative. | I32: Não | N32: out_b0200_main_liabilities.0250_strctrd_prdct | O32: Valor fixo 'Non-structured/Vanilla' | P32: Email Pedro Mendes 12/01/2026 17:20: Os títulos do BST são não estruturados e no futuro não se prevê que venham a existir títulos estruturados, como tal, sugere-se o preenchimento deste campo com valor fixo 'Non-structured/Vanilla'. Reunião 2025-09-23 Pedro Mendes: Segundo Pedro Mendes, este campo deverá assumir valor fixo 'Non-structured/Vanilla'. Reunião 2025-06-23 Luís Capitão-Mor, Pedro Mendes, Luísa Sousa: Segundo o anexo III, este campo deve, em princípio, ser considerado não aplicável para non-resolution entities. Pedro Mendes enviou email dia 24-06 confirmando que este campo é não aplicável. "Sim, confirmo que todos os campos são não aplicáveis." | Q32: Campo não LT (apenas tabela Output) | R32: Concluído | S32: NÃO | T32: =IF(SEARCH(B32,N32,4),"ok","nok") -> ok
A33: Guaranteed minimum repayment amount of the structured product | B33: 0260 | C33: Numeric | D33: 2 decimals | E33: Guaranteed minimum principal amount, which is not dependent on contingent liabilities. Relevant only for structured liabilities. Only claims against other parties are to be reported (i.e. excluding the portion held by the entity itself, which must be reported in field c0090). | I33: Não | N33: out_b0200_main_liabilities.0260_grntd_min_amnt_strctrd_prdct | O33: Valor fixo 999999999999999 | P33: Reunião 2025-06-23 Luís Capitão-Mor, Pedro Mendes, Luísa Sousa: Segundo o anexo III, este campo deve, em princípio, ser considerado não aplicável para non-resolution entities. Pedro Mendes enviou email dia 24-06 confirmando que este campo é não aplicável. "Sim, confirmo que todos os campos são não aplicáveis." | Q33: Campo não LT (apenas tabela Output) | R33: Concluído | S33: NÃO | T33: =IF(SEARCH(B33,N33,4),"ok","nok") -> ok
A34: Fair value of the structured product | B34: 0270 | C34: Numeric | D34: 2 decimals | E34: Total EUR amount of the fair value of the structured product to estimate the outstanding amount due in resolution (including fees, if applicable). Relevant only for structured liabilities. The impact of the relevant entity’s own credit-risk component shall not be included when determining the value. Only claims against other parties are to be reported (i.e. excluding the portion held by the entity itself, which must be reported in field c0090). | I34: Não | N34: out_b0200_main_liabilities.0270_fv_amnt_strctrd_prdct | O34: Valor fixo 999999999999999 | P34: Reunião 2025-06-23 Luís Capitão-Mor, Pedro Mendes, Luísa Sousa: Segundo o anexo III, este campo deve, em princípio, ser considerado não aplicável para non-resolution entities. Pedro Mendes enviou email dia 24-06 confirmando que este campo é não aplicável. "Sim, confirmo que todos os campos são não aplicáveis." | Q34: Campo não LT (apenas tabela Output) | R34: Concluído | S34: NÃO | T34: =IF(SEARCH(B34,N34,4),"ok","nok") -> ok
A35: Not covered and not preferential deposit | B35: 0280 | C35: String | D35: TRUE / FALSE boolean | E35: Identification if the deposit does not qualify for exclusion from bail-in or preferential treatment in accordance with Article 27(3)(a) SRMR or Article 108 BRRD. The value to be reported is a TRUE/FALSE Boolean, where ‘TRUE’ identifies an NCNP deposit and ‘FALSE’ identifies otherwise. This field should be reported only for deposits (48). (48) - Deposits are deposits according to Directive 2014/49/EU and its national transpositions. | I35: Não | N35: out_b0200_main_liabilities.0280_flg_ncnp_dpsts | O35: Valor fixo 'FALSE' | P35: Email Pedro Mendes 12/01/2026 17:20: Alinhou-se com a Corporação que o âmbito deste report no caso do BST (Non-resolution entity) não contempla Depósitos. Como tal, dado que este campo é referente a Depósitos sugere-se o preenchimento deste campo com valor fixo 'FALSE'. Reunião 2025-09-23 Pedro Mendes: Segundo Pedro Mendes, este campo deverá assumir valor fixo 'FALSE'. Reunião 2025-06-23 Luís Capitão-Mor, Pedro Mendes, Luísa Sousa: Tomou-se a decisão de não colocar estes campos not applicable no Loan Tape uma vez que eles não teriam lógica associada. Se a futuro for necessário desenvolver estes campos, então aí sim deverão ser colocados e desenvolvidos no Loan Tape. | Q35: Campo não LT (apenas tabela Output) | R35: Concluído | S35: NÃO | T35: =IF(SEARCH(B35,N35,4),"ok","nok") -> ok
A36: Not covered but preferential deposit | B36: 0290 | C36: String | D36: TRUE / FALSE boolean | E36: Identification if the deposit does not qualify for exclusion from bail-in (Article 27(3)(a) SRMR), yet to which preferential treatment is provided by Article 108 BRRD. The value to be reported is a TRUE/FALSE Boolean, where ‘TRUE’ identifies an NCBP deposit and ‘FALSE’ identifies otherwise. This field should be reported only for deposits (49). (49) - Deposits are those defined as such by Directive 2014/49/EU and its national transpositions | I36: Não | N36: out_b0200_main_liabilities.0290_flg_ncbp_dpsts | O36: Valor fixo 'FALSE' | P36: Email Pedro Mendes 12/01/2026 17:20: Alinhou-se com a Corporação que o âmbito deste report no caso do BST (Non-resolution entity) não contempla Depósitos. Como tal, dado que este campo é referente a Depósitos sugere-se o preenchimento deste campo com valor fixo 'FALSE'. Reunião 2025-09-23 Pedro Mendes: Segundo Pedro Mendes, este campo deverá assumir valor fixo 'FALSE'. Reunião 2025-06-23 Luís Capitão-Mor, Pedro Mendes, Luísa Sousa: Tomou-se a decisão de não colocar estes campos not applicable no Loan Tape uma vez que eles não teriam lógica associada. Se a futuro for necessário desenvolver estes campos, então aí sim deverão ser colocados e desenvolvidos no Loan Tape. | Q36: Campo não LT (apenas tabela Output) | R36: Concluído | S36: NÃO | T36: =IF(SEARCH(B36,N36,4),"ok","nok") -> ok
A37: Covered portion of eligible deposits | B37: 0300 | C37: Numeric | D37: 2 decimals | E37: Total EUR amount of the covered portion of eligible deposits as per Article 27(3)a SRMR. As the amount of covered deposits is calculated per depositor (50), in the case of depositors with multiple accounts, this amount shall in principle be calculated pro rata for the different accounts reported at a granular level (on an account by account basis), unless specific provisions resulting from the transposition of Directive 2014/49/EU into national law are applicable (51). This field should be reported only for deposits (52). Fully covered deposits must not be reported. (50) - Article 6 of Directive 2014/49/EU. (51) - Please refer to the specific reporting example in Annex II, paragraph 3.9. (52) - Deposits are those defined as such by Directive 2014/49/EU and its national transpositions. | I37: Não | N37: out_b0200_main_liabilities.0300_amnt_cvrd_elgbl_dpsts | O37: Valor fixo 999999999999999 | P37: Email Pedro Mendes 12/01/2026 17:20: Alinhou-se com a Corporação que o âmbito deste report no caso do BST (Non-resolution entity) não contempla Depósitos. Como tal, dado que este campo é referente a Depósitos sugere-se o preenchimento deste campo com valor fixo 999999999999999. Reunião 2025-06-23 Luís Capitão-Mor, Pedro Mendes, Luísa Sousa: Tomou-se a decisão de não colocar estes campos not applicable no Loan Tape uma vez que eles não teriam lógica associada. Se a futuro for necessário desenvolver estes campos, então aí sim deverão ser colocados e desenvolvidos no Loan Tape. | Q37: Campo não LT (apenas tabela Output) | R37: Concluído | S37: NÃO | T37: =IF(SEARCH(B37,N37,4),"ok","nok") -> ok
A38: Secured/Unsecured | B38: 0310 | C38: String | D38: Drop-down | E38: Indicate whether the instrument is subject to collateral agreements or not, from a predefined list: • Secured; • Unsecured. When reporting secured liabilities, please refer to the related reporting example in the Technical Annex. | I38: Não | N38: out_b0200_main_liabilities.0310_flg_clltrl_agrmnts | O38: Valor fixo 'Unsecured' | P38: Email Pedro Mendes 12/01/2026 17:20: Todas as emissões que fazem parte do perímetro do MBDT são unsecured. São por propria definição dos instrumentos utilizados. Reunião 2025-09-23 Pedro Mendes: Segundo Pedro Mendes, este campo deverá assumir valor fixo 'Unsecured'. Reunião 2025-06-23 Luís Capitão-Mor, Pedro Mendes, Luísa Sousa: Segundo o anexo III, este campo deve, em princípio, ser considerado não aplicável para non-resolution entities. Pedro Mendes enviou email dia 24-06 confirmando que este campo é não aplicável. "Sim, confirmo que todos os campos são não aplicáveis." | Q38: Campo não LT (apenas tabela Output) | R38: Concluído | S38: NÃO | T38: =IF(SEARCH(B38,N38,4),"ok","nok") -> ok
A39: Amount of pledge, lien or collateral | B39: 0320 | C39: Numeric | D39: 2 decimals | E39: Total EUR amount (market value) of the pledge, lien or collateral if the liability is secured, based on the current internal valuation. For unsecured liabilities, this field is not applicable. If the entity retains a portion of the secured liability (i.e. own holdings), the collateral value should only refer to the portion of the liability against other parties and not held by the reporting entity.(53) This amount determines the secured portion of each secured liability(54). For collateral pools securing multiple row items, the overall coverage ratio should be determined and applied pro rata to all row items covered by this pool. For subordinated collaterals, the outstanding amount of the senior secured liability must be deducted. (53)=(54)=Please refer to the dedicated reporting example in Annex II, paragraph 3.5. | I39: Não | N39: out_b0200_main_liabilities.0320_amnt_clltrl | O39: Valor fixo 999999999999999 | P39: Reunião 2025-06-23 Luís Capitão-Mor, Pedro Mendes, Luísa Sousa: Segundo o anexo III, este campo deve, em princípio, ser considerado não aplicável para non-resolution entities. Pedro Mendes enviou email dia 24-06 confirmando que este campo é não aplicável. "Sim, confirmo que todos os campos são não aplicáveis." | Q39: Campo não LT (apenas tabela Output) | R39: Concluído | S39: NÃO | T39: =IF(SEARCH(B39,N39,4),"ok","nok") -> ok
A40: Amount of the uncollateralized part | B40: 0330 | C40: Numeric | D40: 2 decimals | E40: The positive difference between the outstanding amount (or fair value, when applicable) of the secured liability (or the liability for which collateral has been pledged) as reported in field c0120 (or c0270, when applicable) and the market value of the pledge, lien or collateral (c0320). For collateral pools securing multiple row items, the overall coverage ratio should be determined and applied pro rata to all row items covered by this pool. | G40: Leave blank | I40: Não | N40: out_b0200_main_liabilities.0330_amnt_unclltrlzd | O40: Valor fixo 999999999999999 | P40: Reunião 2025-06-23 Luís Capitão-Mor, Pedro Mendes, Luísa Sousa: Segundo o anexo III, este campo deve, em princípio, ser considerado não aplicável para non-resolution entities. Pedro Mendes enviou email dia 24-06 confirmando que este campo é não aplicável. "Sim, confirmo que todos os campos são não aplicáveis." | Q40: Campo não LT (apenas tabela Output) | R40: Concluído | S40: NÃO | T40: =IF(SEARCH(B40,N40,4),"ok","nok") -> ok
A41: Internal identification number of the pledge, lien or collateral/collateral pool | B41: 0340 | C41: String | D41: Free text | E41: Indicate the internal identifier of the pledge, lien or collateral / collateral pool (where applicable). In the event of several relevant IDs, all IDs should be reported and separated by a vertical bar. | I41: Não | N41: out_b0200_main_liabilities.0340_id_clltrl | O41: Valor fixo 'Not applicable' | P41: Reunião 2025-06-23 Luís Capitão-Mor, Pedro Mendes, Luísa Sousa: Segundo o anexo III, este campo deve, em princípio, ser considerado não aplicável para non-resolution entities. Pedro Mendes enviou email dia 24-06 confirmando que este campo é não aplicável. "Sim, confirmo que todos os campos são não aplicáveis." | Q41: Campo não LT (apenas tabela Output) | R41: Concluído | S41: NÃO | T41: =IF(SEARCH(B41,N41,4),"ok","nok") -> ok
A42: Type of the collateral | B42: 0350 | C42: String | D42: Drop-down | E42: Identify the type of collateral used for the collateralisation: • Real estate; • Ships; • Aircraft; • Financial; • Other; • Not applicable | F42: Input "Not applicable" | G42: Leave blank | I42: Não | N42: out_b0200_main_liabilities.0350_typ_clltrl | O42: Valor fixo 'Not applicable' | P42: Reunião 2025-06-23 Luís Capitão-Mor, Pedro Mendes, Luísa Sousa: Segundo o anexo III, este campo deve, em princípio, ser considerado não aplicável para non-resolution entities. Pedro Mendes enviou email dia 24-06 confirmando que este campo é não aplicável. "Sim, confirmo que todos os campos são não aplicáveis." | Q42: Campo não LT (apenas tabela Output) | R42: Concluído | S42: NÃO | T42: =IF(SEARCH(B42,N42,4),"ok","nok") -> ok
A43: Type of the collateral (if other) | B43: 0351 | C43: String | D43: Free text | E43: Specify the type of collateral if ‘Other’ is selected in field c0350. | I43: Não | N43: out_b0200_main_liabilities.0351_typ_clltrl_othr | O43: Valor fixo 'Not applicable' | P43: Reunião 2025-06-23 Luís Capitão-Mor, Pedro Mendes, Luísa Sousa: Segundo o anexo III, este campo deve, em princípio, ser considerado não aplicável para non-resolution entities. Pedro Mendes enviou email dia 24-06 confirmando que este campo é não aplicável. "Sim, confirmo que todos os campos são não aplicáveis." | Q43: Campo não LT (apenas tabela Output) | R43: Concluído | S43: NÃO | T43: =IF(SEARCH(B43,N43,4),"ok","nok") -> ok
A44: Trading method | B44: 0360 | C44: String | D44: Drop-down | E44: Indicate whether the security is traded (55), either in nominal form or in units (56), as specified in the corresponding final issuance documentation, by selecting one of the following: • Nominal; • Unit; • Not applicable. Please refer to the reporting example in Annex II, paragraph 3.8. (55) - In this context, ‘traded’ means all securities for which there is a CSD of issuance, as indicated in data point c0460 (Central securities depository). (56) - As a general indication, please refer to the definitions provided in the International Securities Operational Market Practice Book published by Euroclear Bank and Clearstream Banking, in particular Annex 9 (‘Units and Nominal recommendation’). Data points c0360 to c0521 might be relevant only in cases of externally issued liabilities or for intragroup liabilities issued in CSDs/iCSDs. | I44: Sim | J44: lt002_instrument.trdng_mthd | L44: {=_xlfn.SWITCH(C44,"Numeric","999999999999999","String","Not applicable","Date","0001-01-01")} -> Not applicable | M44: Necessário criar nova parametrização na tabela lt831_param_conceitos podendo a mesma ser consultada neste documento na sheet 'LT831' filtrando por tabela_conceito = 'LT002_INSTRUMENT' e campo_conceito = 'TRDNG_MTHD'. A parametrização irá basear-se nos campos 'TIPO_TITULO' (proveniente da ct610_titulos), 'FLAG_INST_TITULOS' (proveniente da lt001_univ_oper) e 'PRDCT' (proveniente da lt002_instrument). | N44: out_b0200_main_liabilities.0360_trdng_mthd | O44: lt002_instrument.trdng_mthd | P44: Reunião 2025-10-30/2025-10-28 Luís Capitão-Mor, Pedro Mendes, Luísa Sousa Reunião 2025-10-22 Luís Capitão-Mor, Pedro Mendes, Carlos Daniel: Tipicamente o que é renda fixa (ex: Obrigações) é em Valor Nominal e o que é renda variável (ex: Ações) é em Unidades/Quantidade. Nota: O Papel Comercial (produto 113) também deverá ser considerado 'Nominal' | Q44: Campo novo no LT | R44: Concluído | S44: NÃO | T44: =IF(SEARCH(B44,N44,4),"ok","nok") -> ok
A45: Denomination / Nominal value per security in EUR | B45: 370 | C45: Numeric | D45: 2 decimals | E45: The smallest amount of the security that can be transferred, in EUR currency (if the original currency is not EUR, please also report the EUR-converted amount in this field). If a denomination exists, it represents the higher integral multiple amount. For unit-traded securities (when indicated in data point c0360), this field should be reported only if a nominal value exists. Please refer to the reporting example in Annex II, paragraph 3.8. Data points c0360 to c0521 might be relevant only in cases of externally issued liabilities or for intragroup liabilities issued in CSDs/iCSDs. | I45: Sim | J45: lt002_instrument.amnt_scrty_eur | L45: {=_xlfn.SWITCH(C45,"Numeric","999999999999999","String","Not applicable","Date","0001-01-01")} -> 999999999999999 | M45: Se flag_inst_titulos = '1': Obter campo nom_unit_atual da ct610_titulos. Adicionalmente, efetuar conversão via tabela cambios (ver query de conversão já definida no campo Original amount issued in EUR (0050)) Se flag_inst_titulos = '0': Not applicable. O respetivo valor default de Not applicable deverá ser parametrizado na lt804_conf_dflt. | N45: out_b0200_main_liabilities.0370_amnt_scrty_eur | O45: lt002_instrument.amnt_scrty_eur | P45: Reunião 2025-09-22 Luís Capitão-Mor, Pedro Mendes, Luísa Sousa: Interpreta-se que o SRB solicita o valor nominal de cada título | Q45: Campo novo no LT | R45: Concluído | S45: NÃO | T45: =IF(SEARCH(B45,N45,4),"ok","nok") -> ok
A46: Denomination / Nominal value per security in original currency | B46: 0380 | C46: Numeric | D46: 2 decimals | E46: The smallest amount of the security that can be transferred, in the original currency. If a denomination exists, it represents the higher integral multiple amount. For unit-traded securities (when indicated in data point c0360), this field should be reported only if a nominal value exists. Please refer to the reporting example in Annex II, paragraph 3.8. Data points c0360 to c0521 might be relevant only in cases of externally issued liabilities or for intragroup liabilities issued in CSDs/iCSDs. | I46: Sim | J46: lt002_instrument.amnt_scrty_fx | L46: {=_xlfn.SWITCH(C46,"Numeric","999999999999999","String","Not applicable","Date","0001-01-01")} -> 999999999999999 | M46: Se flag_inst_titulos = '1': Obter campo nom_unit_atual da ct610_titulos. Se flag_inst_titulos = '0': Not applicable. O respetivo valor default de Not applicable deverá ser parametrizado na lt804_conf_dflt. | N46: out_b0200_main_liabilities.0380_amnt_scrty_fx | O46: lt002_instrument.amnt_scrty_fx | P46: Reunião 2025-09-22 Luís Capitão-Mor, Pedro Mendes, Luísa Sousa: Campo igual ao "Denomination / Nominal value per security in EUR" (0370) mas sem efetuar a conversão para Eur (dado que o SRB solicita o montante na moeda original) | Q46: Campo novo no LT | R46: Concluído | S46: NÃO | T46: =IF(SEARCH(B46,N46,4),"ok","nok") -> ok
A47: Number of securities outstanding not held by the reporting entity | B47: 390 | C47: Numeric | D47: Integer | E47: Number of outstanding securities issued per ISIN (or other code), not held by the reporting entity itself. Data points c0360 to c0521 might be relevant only in cases of externally issued liabilities or for intragroup liabilities issued in CSDs/iCSDs. | I47: Não | N47: out_b0200_main_liabilities.0390_nmbr_scrts_not_rprtng_entty | O47: Number of securities outstanding not held by the reporting entity= 0080 / 0370 0080 -> Outstanding principal amount 0370 -> Denomination / Nominal value per security in EUR | P47: Reunião 2025-10-30 Luís Capitão-Mor, Pedro Mendes, Luísa Sousa: Dividir Outstanding principal amount (0080) pelo Denomination / Nominal value per security in EUR (0370) Reunião 2025-08-04 Luís Capitão-Mor, Pedro Mendes, Luísa Sousa: Segundo Pedro Mendes, aqui pede-se a quantidade. Segundo Luís Capitão-Mor, verificar se nos campos acima de montante existe algum que só tenha o nominal atual excluindo as recompras próprias, mas com tudo o resto. Exemplo: Emissão inicial de uma Titularização de 1000 Milhões de Eur Atualmente, temos 900 Milhões de Eur (devido ao pool factor de 0,9). Desses 900 Milhões de Eur: - 50 Milhões de Eur foram recomprados pelo próprio BST - 100 Milhões de Eur estão no Banco Santander SA - 750 Milhões de Eur estão no Mercado Ou seja, tem de se identificar se nos campos existentes se existe algum que tenha os 850 Milhões de Eur. O cálculo do campo "Number of securities outstanding not held by the reporting entity" deverá ser feito dividindo esse campo acima pelo valor nominal... | Q47: Campo não LT (apenas tabela Output) | R47: Concluído | S47: NÃO | T47: =IF(SEARCH(B47,N47,4),"ok","nok") -> ok
A48: Number of securities outstanding held by the reporting entity | B48: 0391 | C48: Numeric | D48: Integer | E48: Number of outstanding securities issued per ISIN (or other code), held by the reporting entity itself. This field must be reported consistently with data point c0090. Data points c0360 to c0521 might be relevant only in cases of externally issued liabilities or for intragroup liabilities issued in CSDs/iCSDs. | I48: Não | N48: out_b0200_main_liabilities.0391_nmbr_scrts_rprtng_entty | O48: Number of securities outstanding held by the reporting entity= 0090 / 0370 0090 -> Portion of instrument or liability held by the reporting entity 0370 -> Denomination / Nominal value per security in EUR | P48: Reunião 2025-10-30 Luís Capitão-Mor, Pedro Mendes, Luísa Sousa: Dividir Portion of instrument or liability held by the reporting entity (0090) pelo Denomination / Nominal value per security in EUR (0370) | Q48: Campo não LT (apenas tabela Output) | R48: Concluído | S48: NÃO | T48: =IF(SEARCH(B48,N48,4),"ok","nok") -> ok
A49: Accrued interest per security | B49: 0400 | C49: Numeric | D49: 4 decimals | E49: Total EUR amount of the accrued interest per security issued per ISIN (or other code). In jurisdictions where accrued interests do not rank pari passu to the principal liability amount, the relevant NRAs may request reporting of interest accruals as on separate line items. Data points c0360 to c0521 might be relevant only in cases of externally issued liabilities or for intragroup liabilities issued in CSDs/iCSDs. | I49: Não | N49: out_b0200_main_liabilities.0400_accrd_intrst_scrty | O49: Accrued interest per security= 0100 / 0390 0100 -> Accrued interest 0390 -> Number of securities outstanding not held by the reporting entity | P49: Reunião 2025-10-30 Luís Capitão-Mor, Pedro Mendes, Luísa Sousa: A contabilidade não tem juros corridos sobre o que está recomprado. Por exemplo, no caso de uma Emissão de 1000 Milhões eur, em que 100 Milhões eur estão recomprados pelo BST e 900 Milhões eur estão no Mercado, os juros corridos que estão registados na Contabilidade são apenas sobre os 900 Milhões eur, os 100 Milhões eur não têm juros corridos. No limite, se dos 1000 Milhões eur emitidos estivessem 1000 Milhões eur recomprados, não haveria juros corridos. Carlos Fernandes confirmou este entendimento (email Carlos Fernandes 05/11/2025 11:28) Portanto, a fórmula deste campo deverá ser o Accrued interest a dividir pela quantidade excluindo as recompras, ou seja, neste exemplo a quantidade deverá ser sobre os 900 Milhões eur e não sobre os 1000 Milhões eur. Em suma, a fórmula deverá ser: Accrued interest (0100) / Number of securities outstanding not held by the reporting entity (0390) old: Reunião 2025-09-22 Luís Capitão-Mor, Pedro Mendes, Luísa Sousa: 1) Ver se na bloomberg (ou algum site que a Financeira usa) constam estes títulos e ver o accrued interest que lá está. Ou com a Cláudia no Asset Control. -> Segundo Pedro Mendes, na Financeira o que existe atualmente é apenas o excel da Contabilidade com as Emissões. -> Segundo Cláudia Correia, "não existe. O Asset Control só tem preços puros de mercado" | Q49: Campo não LT (apenas tabela Output) | R49: Concluído | S49: SIM | T49: =IF(SEARCH(B49,N49,4),"ok","nok") -> ok
A50: Fees and charges per security | B50: 0410 | C50: Numeric | D50: 4 decimals | E50: Total EUR amount of the fees and charges per security issued per ISIN (or other code). Applicable fees and charges (e.g. contractual fees for late payments) linked to the instrument, if the fee or charge is payable and due but not yet settled with the counterparty as of the request date, to the extent that the fee or charge is not covered within the outstanding principal amount, the accrued interest or a separate liability. Fees and charges do not include agios or fees in conjunction with the listing of a security. Data points c0360 to c0521 might be relevant only in cases of externally issued liabilities or for intragroup liabilities issued in CSDs/iCSDs. | I50: Não | N50: out_b0200_main_liabilities.0410_fees_charges_scrty | O50: Valor fixo 0 | P50: Reunião 2025-09-24 Luís Capitão-Mor, Pedro Mendes: Tendo em conta que no campo "Applicable fees and charges" (0110) se vai reportar valor fixo 0, e que este campo trata do mesmo conceito (apresenta a mesma definição) mas por título (per security), então também se deve reportar valor fixo 0. | Q50: Campo não LT (apenas tabela Output) | R50: Concluído | S50: NÃO | T50: =IF(SEARCH(B50,N50,4),"ok","nok") -> ok
A51: Fair value per security | B51: 0420 | C51: Numeric | D51: 4 decimals | E51: Total EUR amount of the fair value (as reported in field c0270) per security issued per ISIN (or other code). Data points c0360 to c0521 might be relevant only in cases of externally issued liabilities or for intragroup liabilities issued in CSDs/iCSDs. | I51: Não | N51: out_b0200_main_liabilities.0420_fv_amnt_scrty | O51: Valor fixo 999999999999999 | P51: Reunião 2025-09-24 Luís Capitão-Mor, Pedro Mendes: Tendo em conta que no campo "Fair value of the structured product" (0270) se vai reportar valor fixo 999999999999999, e que este campo trata do mesmo conceito (apresenta a mesma definição) mas por título (per security), então também se deve reportar valor fixo 999999999999999. | Q51: Campo não LT (apenas tabela Output) | R51: Concluído | S51: NÃO | T51: =IF(SEARCH(B51,N51,4),"ok","nok") -> ok
A52: Principal amount of the global note in EUR | B52: 0430 | C52: Numeric | D52: 2 decimals | E52: The outstanding aggregate principal amount of the global note per ISIN or other code, in EUR (including own holdings when applicable). If the value is reported in a foreign currency in field c0431, the amount must be converted into EUR and reported in this field using the EUR reference exchange rate. For foreign currencies for which no EUR reference exchange rate is available, a customary market reference rate must be used. If such other customary reference exchange rates are used, a uniform source must be used wherever possible. This field is not applicable if the trading method selected in field c0360 is ‘Unit’. Data points c0360 to c0521 might be relevant only in cases of externally issued liabilities or for intragroup liabilities issued in CSDs/iCSDs. | F52: Input 999999999999999 | I52: Não | N52: out_b0200_main_liabilities.0430_prncpl_amnt_glbl_nt_eur | O52: Valor fixo 999999999999999 | P52: Email Pedro Mendes 12/01/2026 17:20: O BST não tem Global Notes e não se prevê que venha a ter, como tal, sugere-se o preenchimento deste campo com valor fixo 999999999999999. Reunião 2025-08-13 Luís Capitão-Mor, Pedro Mendes, Luísa Sousa | Q52: Campo não LT (apenas tabela Output) | R52: Concluído | S52: NÃO | T52: =IF(SEARCH(B52,N52,4),"ok","nok") -> ok
A53: Principal amount of the global note in original currency | B53: 0431 | C53: Numeric | D53: 2 decimals | E53: The outstanding aggregate principal amount of the global note per ISIN or other code in the original currency (including own holdings when applicable). Please also report the EUR-converted amount in the corresponding EUR field (c0430). This field is not applicable if trading method selected in field c0360 is ‘Unit’. Data points c0360 to c0521 might be relevant only in cases of externally issued liabilities or for intragroup liabilities issued in CSDs/iCSDs. | F53: Input 999999999999999 | I53: Não | N53: out_b0200_main_liabilities.0431_prncpl_amnt_glbl_nt_fx | O53: Valor fixo 999999999999999 | P53: Email Pedro Mendes 12/01/2026 17:20: O BST não tem Global Notes e não se prevê que venha a ter, como tal, sugere-se o preenchimento deste campo com valor fixo 999999999999999. Reunião 2025-08-13 Luís Capitão-Mor, Pedro Mendes, Luísa Sousa | Q53: Campo não LT (apenas tabela Output) | R53: Concluído | S53: NÃO | T53: =IF(SEARCH(B53,N53,4),"ok","nok") -> ok
A54: Nature of the global note | B54: 440 | C54: String | D54: Drop-down | E54: Indicate whether the liability is a Classical Global Note (CGN) or a New Global Note (NGN): • CGN = a form of global certificate that requires physical annotation on the attached schedule to reflect changes in the issue outstanding amount; • NGN = a form of global certificate that refers to the records of the ICSDs to determine the issue outstanding amount. • Not applicable = if it is not applicable (the liability has not been issued in an ICSD, or has another nature). Data points c0360 to c0521 might be relevant only in cases of externally issued liabilities or for intragroup liabilities issued in CSDs/iCSDs. | F54: Input "Not applicable" | I54: Não | N54: out_b0200_main_liabilities.0440_ntr_glbl_nt | O54: Valor fixo 'Not applicable' | P54: Email Pedro Mendes 12/01/2026 17:20: O BST não tem Global Notes e não se prevê que venha a ter, como tal, sugere-se o preenchimento deste campo com valor fixo 'Not applicable'. Reunião 2025-07-31 Luís Capitão-Mor, Pedro Mendes: Não aplicável ao universo de títulos em causa, contudo, aplica-se a outros títulos. | Q54: Campo não LT (apenas tabela Output) | R54: Concluído | S54: NÃO | T54: =IF(SEARCH(B54,N54,4),"ok","nok") -> ok
A55: Current pool factor | B55: 0450 | C55: Numeric | D55: Values between 0 and 1, with 9 decimals | E55: If applicable, the factor used to calculate the value of the outstanding principal of the financial instrument applicable until the next redemption (factor) date, or after the redemption (factor) date. Can also be defined as: ratio of outstanding principal to original face value. Please refer to the SRB publication ‘Reflecting bail-in in the books of the International Central Securities Depositories (ICSDs) (57). (57) - https://www.srb.europa.eu/system/files/media/document/bail-in_in_books_of_icsds_enn_final_web.pdf (Annex III, letter G) Data points c0360 to c0521 might be relevant only in cases of externally issued liabilities or for intragroup liabilities issued in CSDs/iCSDs. | F55: Input -9999.999999999 | I55: Não | N55: out_b0200_main_liabilities.0450_crrnt_pool_fctr | O55: Valor Fixo -9999.999999999 | P55: Reunião 2025-07-24 Luís Capitão-Mor, Flávia Pinho, Luísa Sousa: Por definição, o conceito de Pool Factor aplica-se apenas a titularizações (instrumentos financeiros que têm fundos) e não se aplica aos restantes Produtos. Portanto, sabendo que o universo deste report não contempla Titularizações, então não será criado o campo no Loan Tape e será criado apenas na tabela de output out_b0200_main_liabilities com o valor de not applicable. | Q55: Campo não LT (apenas tabela Output) | R55: Concluído | S55: NÃO | T55: =IF(SEARCH(B55,N55,4),"ok","nok") -> ok
A56: Central securities depository | B56: 0460 | C56: String | D56: Fixed values | E56: Indicate the CSD of issue for the security. When applicable, please use the values from the predefined list provided below. In the event of multiple entries, please separate them with a vertical bar and indicate the CSD of issue as the first entry on the list. For securities deposited by international central securities depositories (ICSDs), both CSDs must be reported. • ATHEX CSD_EL • BOGS_EL • CBF_DE • CBL_LU • CDCP SR_SK • CDCP_CZ • Central Depository & Clearing Company_HR • Central Depository of Securities Prague_CZ • Central Depository_BG • Cyprus CDCR_CY • Depozitarul Central_RO • DTC_US • Euroclear Bank_BE • Euroclear Belgium_BE • Euroclear Finland_FI • Euroclear France_FR • Euroclear Netherlands_NL • Euroclear Sweden_SE • Euroclear UK & Ireland_UK • Government Securities Depository (GSD)_BG • Iberclear_ES • INTERBOLSA_PT • KDD_SI • KDPW_PL • KELER_HU • LUX CSD_LU • Malta Stock Exchange CSD_MT • Euronext Securities Milan_IT • Nasdaq CSD_EE • Nasdaq CSD_LT • Nasdaq CSD_LV • NBB SSS_BE • nCDCP_SK • OeKB CSD_AT • SAFIR_RO • SIX SIS_CH • SKARBNET4_PL • SKD_CZ • VP Securities_DK • VPS_NO • Other • Not applicable Data points c0360 to c0521 might be relevant only in cases of externally issued liabilities or for intragroup liabilities issued in CSDs/iCSDs. | I56: Sim | J56: lt002_instrument.csd | L56: {=_xlfn.SWITCH(C56,"Numeric","999999999999999","String","Not applicable","Date","0001-01-01")} -> Not applicable | M56: Se flag_inst_titulos = '1': Obter campo central_valores da ct610_titulos (que contém o código lei) e cruzá-lo com o campo clei da ct003_univ_cli, de forma a obter o campo gcliente da ct003_univ_cli. Caso o cruzamento resulte em mais do que 1 gcliente, terá de se trazer apenas 1 gcliente. Para tal, selecionar o zcliente maior (max (zcliente)) que tenha gcliente preenchido. Se flag_inst_titulos = '0': Not applicable. O respetivo valor default de Not applicable deverá ser parametrizado na lt804_conf_dflt. Necessário criar novas parametrizaçôes nas tabelas lt829_regras_conversao e lt830_conversoes, podendo as mesmas ser consultadas neste documento nas sheets: LT829 - filtrando por campo_conceito = 'CSD' e regra_conversao = '1'; LT830 - filtrando por segmento = 'ESTR' e campo_conceito = 'CSD'. | N56: out_b0200_main_liabilities.0460_csd | O56: lt002_instrument.csd | P56: Reunião 2025-07-30 Luís Capitão-Mor, Pedro Mendes, Luísa Sousa Reunião 2025-07-28 Luís Capitão-Mor, Pedro Mendes Reunião 2025-07-17 Luís Capitão-Mor, Flávia Pinho, Luísa Sousa | Q56: Campo novo no LT | R56: Concluído | S56: NÃO | T56: =IF(SEARCH(B56,N56,4),"ok","nok") -> ok
A57: Central securities depository (LEI) | B57: 0461 | C57: String | D57: Free text | E57: When applicable, please indicate the LEI (or another ID) of the CSD. In case of multiple entries, please separate them with a vertical bar and indicate the CSD of issue as the first entry on the list | I57: Sim | J57: lt002_instrument.csd_lei | L57: {=_xlfn.SWITCH(C57,"Numeric","999999999999999","String","Not applicable","Date","0001-01-01")} -> Not applicable | M57: Se flag_inst_titulos = '1': Obter campo central_valores da ct610_titulos. Se flag_inst_titulos = '0': Not applicable. O respetivo valor default de Not applicable deverá ser parametrizado na lt804_conf_dflt. | N57: out_b0200_main_liabilities.0461_csd_lei | O57: lt002_instrument.csd_lei | P57: Reunião 2025-07-30 Luís Capitão-Mor, Pedro Mendes, Luísa Sousa Reunião 2025-07-28 Luís Capitão-Mor, Pedro Mendes Reunião 2025-07-17 Luís Capitão-Mor, Flávia Pinho, Luísa Sousa | Q57: Campo novo no LT | R57: Concluído | S57: NÃO | T57: =IF(SEARCH(B57,N57,4),"ok","nok") -> ok
A58: Central securities depository name (if other) | B58: 0462 | C58: String | D58: Free text | E58: Indicate the name of the central securities depository if ‘Other’ is selected in field c0460. Data points c0360 to c0521 might be relevant only in cases of externally issued liabilities or for intragroup liabilities issued in CSDs/iCSDs. | I58: Não | N58: out_b0200_main_liabilities.0462_csd_othr | O58: Valor fixo 'Not applicable' | P58: Email Pedro Mendes 12/01/2026 17:20: Considerou-se que o campo "Central securities depository" (c0460) terá sempre um valor diferente de 'Other', e por conseguinte o campo "Central securities depository name (if other)" nunca terá valor. Como tal, sugere-se o preenchimento deste campo com valor fixo 'Not applicable'. Reunião 2025-07-17 Luís Capitão-Mor, Flávia Pinho, Luísa Sousa Reunião 2025-07-17 Luís Capitão-Mor, Flávia Pinho, Luísa Sousa | Q58: Campo não LT (apenas tabela Output) | R58: Concluído | S58: NÃO | T58: =IF(SEARCH(B58,N58,4),"ok","nok") -> ok
A59: (Mandated) paying agent | B59: 0470 | C59: String | D59: Free text | E59: Indicate the name of the paying agent, i.e. the entity (or part of an entity) that is processing the cash payments related to the liability’s lifecycle events (e.g. dividend, coupon or redemption) to the holders of that liability. For stocks, a paying agent distributes dividends to stockholders. For bonds, it distributes coupon payments and reimbursements of principal to bondholders. For deposits reported on an aggregated level, input ‘Not applicable’. Data points c0360 to c0521 might be relevant only in cases of externally issued liabilities or for intragroup liabilities issued in CSDs/iCSDs. | F59: Input "Not applicable" | I59: Sim | J59: lt002_instrument.pyng_agnt | L59: {=_xlfn.SWITCH(C59,"Numeric","999999999999999","String","Not applicable","Date","0001-01-01")} -> Not applicable | M59: Se flag_inst_titulos = '1': Obter campo agente_pagador da ct610_titulos (que contém o código lei) e cruzá-lo com o campo clei da ct003_univ_cli, de forma a obter o campo gcliente da ct003_univ_cli. Caso o cruzamento resulte em mais do que 1 gcliente, terá de se trazer apenas 1 gcliente. Para tal, selecionar o zcliente maior (max (zcliente)) que tenha gcliente preenchido. Se flag_inst_titulos = '0': Not applicable. O respetivo valor default de Not applicable deverá ser parametrizado na lt804_conf_dflt. | N59: out_b0200_main_liabilities.0470_pyng_agnt | O59: lt002_instrument.pyng_agnt | P59: Reunião 2025-07-30 Luís Capitão-Mor, Pedro Mendes, Luísa Sousa Reunião 2025-07-28 Luís Capitão-Mor, Pedro Mendes Reunião 2025-07-17 Luís Capitão-Mor, Flávia Pinho, Luísa Sousa | Q59: Campo novo no LT | R59: Concluído | S59: NÃO | T59: =IF(SEARCH(B59,N59,4),"ok","nok") -> ok
A60: (Mandated) paying agent (LEI) | B60: 0471 | C60: String | D60: Free text | E60: When applicable, please indicate the LEI (or another ID) of the paying agent. For deposits reported on an aggregated level, input ‘Not applicable’. Data points c0360 to c0521 might be relevant only in cases of externally issued liabilities or for intragroup liabilities issued in CSDs/iCSDs. | F60: Input "Not applicable" | I60: Sim | J60: lt002_instrument.pyng_agnt_lei | L60: {=_xlfn.SWITCH(C60,"Numeric","999999999999999","String","Not applicable","Date","0001-01-01")} -> Not applicable | M60: Se flag_inst_titulos = '1': Obter agente_pagador da ct610_titulos. Se flag_inst_titulos = '0': Not applicable. O respetivo valor default de Not applicable deverá ser parametrizado na lt804_conf_dflt. | N60: out_b0200_main_liabilities.0471_pyng_agnt_lei | O60: lt002_instrument.pyng_agnt_lei | P60: Reunião 2025-07-30 Luís Capitão-Mor, Pedro Mendes, Luísa Sousa Reunião 2025-07-28 Luís Capitão-Mor, Pedro Mendes Reunião 2025-07-17 Luís Capitão-Mor, Flávia Pinho, Luísa Sousa | Q60: Campo novo no LT | R60: Concluído | S60: NÃO | T60: =IF(SEARCH(B60,N60,4),"ok","nok") -> ok
A61: Trading venue | B61: 0480 | C61: String | D61: Free text | E61: A trading venue is either a regulated market (a stock exchange), a multilateral trading facility (MTF, i.e. a multilateral trading system operated by an investment firm or market operator) or an organised trading facility (OTF, i.e. a multilateral system that is not a regulated market or an MTF). Indicate the name of the trading venue where the liability is admitted to trading. This also includes MTFs and OTFs, where known. In the event of multiple entries, please separate each with a vertical bar. Regulated trading venues must be reported in this field, while unregulated trading venues can be reported on a best-effort basis. When the security is not listed on a trading venue, the attribute ‘Not listed’ must be entered. In case of private placements, the attribute ‘Private placement’ must be entered. For deposits reported on an aggregated level, input ‘Not applicable’. Data points c0360 to c0521 might be relevant only in cases of externally issued liabilities or for intragroup liabilities issued in CSDs/iCSDs. | F61: Input "Not applicable" | I61: Não | N61: out_b0200_main_liabilities.0480_trdng_vn | O61: Valor fixo 'Not applicable' | P61: Email Pedro Mendes 12/01/2026 17:20: Todas as emissões que fazem parte do perímetro do MBDT não estão, nem se espera que venham a estar, admitidas num trading venue. Por isso é sempre "Not Applicable". Reunião 2025-07-30 Luís Capitão-Mor, Pedro Mendes, Luísa Sousa Email 2025-07-29 11:06 de Pedro Mendes: Segundo Pedro Mendes, este campo é não aplicável para o universo em causa. Reunião 2025-07-28 Luís Capitão-Mor, Pedro Mendes Reunião 2025-07-17 Luís Capitão-Mor, Flávia Pinho, Luísa Sousa | Q61: Campo não LT (apenas tabela Output) | R61: Concluído | S61: NÃO | T61: =IF(SEARCH(B61,N61,4),"ok","nok") -> ok
A62: Trading venue (LEI) | B62: 0481 | C62: String | D62: Free text | E62: When applicable, please indicate the LEI (or another ID) of the trading venue where the liability is admitted to trading. In the event of multiple entries, please separate each with a vertical bar. For deposits reported on an aggregated level, input ‘Not applicable’. Data points c0360 to c0521 might be relevant only in cases of externally issued liabilities or for intragroup liabilities issued in CSDs/iCSDs. | F62: Input "Not applicable" | I62: Não | N62: out_b0200_main_liabilities.0481_trdng_vn_lei | O62: Valor fixo 'Not applicable' | P62: Email Pedro Mendes 12/01/2026 17:20: Se o campo acima é sempre "Not applicable", este campo que é o código LEI do trading venue também será sempre "Not applicable". Reunião 2025-07-30 Luís Capitão-Mor, Pedro Mendes, Luísa Sousa Email 2025-07-29 11:06 de Pedro Mendes: Segundo Pedro Mendes, este campo é não aplicável para o universo em causa. Reunião 2025-07-28 Luís Capitão-Mor, Pedro Mendes Reunião 2025-07-17 Luís Capitão-Mor, Flávia Pinho, Luísa Sousa | Q62: Campo não LT (apenas tabela Output) | R62: Concluído | S62: NÃO | T62: =IF(SEARCH(B62,N62,4),"ok","nok") -> ok
A63: Registrar for information about creditors/holders | B63: 0490 | C63: String | D63: Free text | E63: Indicate the name of the registrar (responsible for holding the records of these liabilities’ owners). The registrar or register holder is usually the issuer itself, a CSD or another entity. For deposits reported on an aggregated level, input ‘Not applicable’. Data points c0360 to c0521 might be relevant only in cases of externally issued liabilities or for intragroup liabilities issued in CSDs/iCSDs. | F63: Input "Not applicable" | I63: Não | J63: lt002_instrument.csd | L63: {=_xlfn.SWITCH(C63,"Numeric","999999999999999","String","Not applicable","Date","0001-01-01")} -> Not applicable | N63: out_b0200_main_liabilities.0490_rgstrr | O63: lt002_instrument.csd | P63: Reunião 2025-07-30 Luís Capitão-Mor, Pedro Mendes, Luísa Sousa Reunião 2025-07-28 Luís Capitão-Mor, Pedro Mendes: Decidiu-se apontar para o campo csd que será criado na lt002_instrument. Reunião 2025-07-17 Luís Capitão-Mor, Flávia Pinho, Luísa Sousa old: Se flag_inst_titulos = '1': Obter campo agente_pagador da ct610_titulos (que contém o código lei) e cruzá-lo com o campo clei da ct003_univ_cli, de forma a obter o campo gcliente da ct003_univ_cli. O cruzamento não poderá resultar em mais do que 1 gnome, como tal, trazer o gcliente com maior zcliente. Caso o cruzamento resulte em mais do que 1 gcliente, terá de se trazer apenas 1 gcliente. Para tal, selecionar o zcliente maior: max(zcliente). Se flag_inst_titulos = '0': ? Aguarda-se resposta ao email enviado a Flávia Pinho (21/07/2025 11:03) | Q63: Campo não LT (apenas tabela Output) | R63: Concluído | S63: NÃO | T63: =IF(SEARCH(B63,N63,4),"ok","nok") -> ok
A64: Registrar for information about creditors/holders (LEI) | B64: 0491 | C64: String | D64: Free text | E64: When applicable, please indicate the LEI (or another ID) of the registrar. For deposits reported on an aggregated level, input ‘Not applicable’. Data points c0360 to c0521 might be relevant only in cases of externally issued liabilities or for intragroup liabilities issued in CSDs/iCSDs. | F64: Input "Not applicable" | I64: Não | J64: lt002_instrument.csd_lei | L64: {=_xlfn.SWITCH(C64,"Numeric","999999999999999","String","Not applicable","Date","0001-01-01")} -> Not applicable | N64: out_b0200_main_liabilities.0491_rgstrr_lei | O64: lt002_instrument.csd_lei | P64: Reunião 2025-07-30 Luís Capitão-Mor, Pedro Mendes, Luísa Sousa Reunião 2025-07-28 Luís Capitão-Mor, Pedro Mendes: Decidiu-se apontar para o campo csd_lei que será criado na lt002_instrument. Reunião 2025-07-17 Luís Capitão-Mor, Flávia Pinho, Luísa Sousa | Q64: Campo não LT (apenas tabela Output) | R64: Concluído | S64: NÃO | T64: =IF(SEARCH(B64,N64,4),"ok","nok") -> ok
A65: National Numbering Agency | B65: 0500 | C65: String | D65: Free text | E65: Indicate the name of the organisation responsible for issuing International Securities Identification Numbers (ISINs) as described by ISO 6166, and the Classification of Financial Instruments code as described by ISO 10962. The role of NNA is typically assigned to the national stock exchange, CSD, central bank or financial regulator. When applicable, for securities deposited by the international central securities depositories (ICSDs), both CSDs shall be reported. For deposits reported on an aggregated level, input ‘Not applicable’. Data points c0360 to c0521 might be relevant only in cases of externally issued liabilities or for intragroup liabilities issued in CSDs/iCSDs. | F65: Input "Not applicable" | I65: Não | J65: lt002_instrument.csd | L65: {=_xlfn.SWITCH(C65,"Numeric","999999999999999","String","Not applicable","Date","0001-01-01")} -> Not applicable | N65: out_b0200_main_liabilities.0500_nna | O65: lt002_instrument.csd | P65: Reunião 2025-07-30 Luís Capitão-Mor, Pedro Mendes, Luísa Sousa Reunião 2025-07-28 Luís Capitão-Mor, Pedro Mendes: Decidiu-se apontar para o campo csd que será criado na lt002_instrument. Reunião 2025-07-17 Luís Capitão-Mor, Flávia Pinho, Luísa Sousa | Q65: Campo não LT (apenas tabela Output) | R65: Concluído | S65: NÃO | T65: =IF(SEARCH(B65,N65,4),"ok","nok") -> ok
A66: National Numbering Agency (LEI) | B66: 0501 | C66: String | D66: Free text | E66: When applicable, please indicate the LEI code (or another ID) of the national numbering agency. For deposits reported on an aggregated level, input ‘Not applicable’. Data points c0360 to c0521 might be relevant only in cases of externally issued liabilities or for intragroup liabilities issued in CSDs/iCSDs. | F66: Input "Not applicable" | I66: Não | J66: lt002_instrument.csd_lei | L66: {=_xlfn.SWITCH(C66,"Numeric","999999999999999","String","Not applicable","Date","0001-01-01")} -> Not applicable | N66: out_b0200_main_liabilities.0501_nna_lei | O66: lt002_instrument.csd_lei | P66: Reunião 2025-07-30 Luís Capitão-Mor, Pedro Mendes, Luísa Sousa Reunião 2025-07-28 Luís Capitão-Mor, Pedro Mendes: Decidiu-se apontar para o campo CSD já existente. Reunião 2025-07-17 Luís Capitão-Mor, Flávia Pinho, Luísa Sousa | Q66: Campo não LT (apenas tabela Output) | R66: Concluído | S66: NÃO | T66: =IF(SEARCH(B66,N66,4),"ok","nok") -> ok
A67: Common Depository | B67: 0510 | C67: String | D67: Free text | E67: Indicate the name of the common depository, when applicable (i.e. if issued in one of the ICSDs and in CGN form). A common depository is an entity appointed by the ICSDs (Euroclear Bank and Clearstream Banking Luxembourg) to provide safekeeping and asset servicing for securities in Classical Global Note form. For deposits reported on an aggregated level, input ‘Not applicable’. Data points c0360 to c0521 might be relevant only in cases of externally issued liabilities or for intragroup liabilities issued in CSDs/iCSDs. | F67: Input "Not applicable" | I67: Não | N67: out_b0200_main_liabilities.0510_cmmn_dpstry | O67: Valor fixo 'Not applicable' | P67: Email Pedro Mendes 12/01/2026 17:20: Todas as emissões que fazem parte do perímetro do MBDT estão, e não é expectável que esta situação se altere, registadas na Interbolsa Por isso é sempre "Not Applicable". Reunião 2025-07-30 Luís Capitão-Mor, Pedro Mendes, Luísa Sousa Email 2025-07-29 11:06 de Pedro Mendes: Segundo Pedro Mendes, este campo é não aplicável para o universo em causa. Reunião 2025-07-28 Luís Capitão-Mor, Pedro Mendes Reunião 2025-07-17 Luís Capitão-Mor, Flávia Pinho, Luísa Sousa | Q67: Campo não LT (apenas tabela Output) | R67: Concluído | S67: NÃO | T67: =IF(SEARCH(B67,N67,4),"ok","nok") -> ok
A68: Common Depository (LEI) | B68: 0511 | C68: String | D68: Free text | E68: When applicable, please indicate the LEI code (or another ID) of the common depository. For deposits reported on an aggregated level, input ‘Not applicable’. Data points c0360 to c0521 might be relevant only in cases of externally issued liabilities or for intragroup liabilities issued in CSDs/iCSDs. | F68: Input "Not applicable" | I68: Não | N68: out_b0200_main_liabilities.0511_cmmn_dpstry_lei | O68: Valor fixo 'Not applicable' | P68: Email Pedro Mendes 12/01/2026 17:20: Se o campo acima é sempre "Not applicable", este campo que é o código LEI do common depository também será sempre "Not applicable". Reunião 2025-07-30 Luís Capitão-Mor, Pedro Mendes, Luísa Sousa Email 2025-07-29 11:06 de Pedro Mendes: Segundo Pedro Mendes, este campo é não aplicável para o universo em causa. Reunião 2025-07-28 Luís Capitão-Mor, Pedro Mendes Reunião 2025-07-17 Luís Capitão-Mor, Flávia Pinho, Luísa Sousa | Q68: Campo não LT (apenas tabela Output) | R68: Concluído | S68: NÃO | T68: =IF(SEARCH(B68,N68,4),"ok","nok") -> ok
A69: Common Service Provider | B69: 0520 | C69: String | D69: Free text | E69: Indicate the name of the common service provider, when applicable (i.e. if issued in one of the ICSDs and in NGN form). A common service provider is an entity appointed by the ICSDs to provide asset servicing for New Global Notes. For deposits reported on an aggregated level, input ‘Not applicable’. Data points c0360 to c0521 might be relevant only in cases of externally issued liabilities or for intragroup liabilities issued in CSDs/iCSDs. | F69: Input "Not applicable" | I69: Não | N69: out_b0200_main_liabilities.0520_cmmn_srvc_prvdr | O69: Valor fixo 'Not applicable' | P69: Email Pedro Mendes 12/01/2026 17:20: Todas as emissões que fazem parte do perímetro do MBDT estão, e não é expectável que esta situação se altere, registadas na Interbolsa Por isso é sempre "Not Applicable". Reunião 2025-07-30 Luís Capitão-Mor, Pedro Mendes, Luísa Sousa Email 2025-07-29 11:06 de Pedro Mendes: Segundo Pedro Mendes, este campo é não aplicável para o universo em causa. Reunião 2025-07-28 Luís Capitão-Mor, Pedro Mendes Reunião 2025-07-17 Luís Capitão-Mor, Flávia Pinho, Luísa Sousa | Q69: Campo não LT (apenas tabela Output) | R69: Concluído | S69: NÃO | T69: =IF(SEARCH(B69,N69,4),"ok","nok") -> ok
A70: Common Service Provider (LEI) | B70: 0521 | C70: String | D70: Free text | E70: When applicable, please indicate the LEI code (or another ID) of the common service provider. For deposits reported on an aggregated level, input ‘Not applicable’. Data points c0360 to c0521 might be relevant only in cases of externally issued liabilities or for intragroup liabilities issued in CSDs/iCSDs. | F70: Input "Not applicable" | I70: Não | N70: out_b0200_main_liabilities.0521_cmmn_srvc_prvdr_lei | O70: Valor fixo 'Not applicable' | P70: Email Pedro Mendes 12/01/2026 17:20: Se o campo acima é sempre "Not applicable", este campo que é o código LEI do Common Service Provide também será sempre "Not applicable". Reunião 2025-07-30 Luís Capitão-Mor, Pedro Mendes, Luísa Sousa Email 2025-07-29 11:06 de Pedro Mendes: Segundo Pedro Mendes, este campo é não aplicável para o universo em causa. Reunião 2025-07-28 Luís Capitão-Mor, Pedro Mendes Reunião 2025-07-17 Luís Capitão-Mor, Flávia Pinho, Luísa Sousa | Q70: Campo não LT (apenas tabela Output) | R70: Concluído | S70: NÃO | T70: =IF(SEARCH(B70,N70,4),"ok","nok") -> ok
A71: Type of own funds at individual level | B71: 0530 | C71: String | D71: Drop-down | E71: Indicate the type of own funds, as classified at individual level: • T2 in phase-out; • Grandfathered T2; • Fully Compliant T2; • Partially (A)T1 and T2; • Grandfathered AT1; • Fully Compliant AT1; • CET1; • No. In the list of options, the term ‘phase-out’ refers to the period of 5 years before maturity of any given T2 instrument, during which there is only proportionate recognition based on the time remaining until maturity. ‘Grandfathered’ should be understood as any transitional measure applicable to a T2 instrument, not including the ‘phase-out’. During this ‘grandfathering’, recognition may be full or partial. If the instrument is not classified as own funds, please indicate ‘No’. | F71: Input "Not applicable" | I71: Sim | J71: lt002_instrument.typ_own_fnds_indvdl_lvl | L71: {=_xlfn.SWITCH(C71,"Numeric","999999999999999","String","Not applicable","Date","0001-01-01")} -> Not applicable | M71: Se flag_inst_titulos = '1': Obter eleg_fund_prop da ct610_titulos. Se flag_inst_titulos = '0': Not applicable. O respetivo valor default de Not applicable deverá ser parametrizado na lt804_conf_dflt. | N71: out_b0200_main_liabilities.0530_typ_own_fnds_ind_lvl | O71: lt002_instrument.typ_own_fnds_indvdl_lvl | P71: Reunião 2025-07-30 Luís Capitão-Mor, Pedro Mendes, Luísa Sousa Reunião 2025-07-24 Luís Capitão-Mor, Flávia Pinho, Luísa Sousa | Q71: Campo novo no LT | R71: Concluído | S71: NÃO | T71: =IF(SEARCH(B71,N71,4),"ok","nok") -> ok
A72: Eligible amount for own funds at individual level | B72: 0540 | C72: Numeric | D72: 2 decimals | E72: The actual amount in EUR of the instrument qualifying as own funds at individual level. | F72: Input 999999999999999 | I72: Sim | J72: lt002_instrument.elgbl_amnt_own_fnds_indvdl_lvl | L72: {=_xlfn.SWITCH(C72,"Numeric","999999999999999","String","Not applicable","Date","0001-01-01")} -> 999999999999999 | M72: Se flag_inst_titulos = '1': Obter mon_fund_prop da ct610_titulos. Se flag_inst_titulos = '0': Not applicable. O respetivo valor default de Not applicable deverá ser parametrizado na lt804_conf_dflt. | N72: out_b0200_main_liabilities.0540_elgbl_amnt_own_fnds_ind_lvl | O72: lt002_instrument.elgbl_amnt_own_fnds_indvdl_lvl | P72: Reunião 2025-07-30 Luís Capitão-Mor, Pedro Mendes, Luísa Sousa Reunião 2025-07-24 Luís Capitão-Mor, Flávia Pinho, Luísa Sousa | Q72: Campo novo no LT | R72: Concluído | S72: SIM | T72: =IF(SEARCH(B72,N72,4),"ok","nok") -> ok
A73: Type of own funds at consolidated level | B73: 0550 | C73: String | D73: Drop-down | E73: Indicate the type of own funds, as classified at consolidated level: • T2 in phase-out; • Grandfathered T2; • Fully Compliant T2; • Partially (A)T1 and T2; • Grandfathered AT1; • Fully Compliant AT1; • CET1; • No. In the list of options, the term ‘phase-out’ refers to the period of 5 years before maturity of any given T2 instrument, during which there is only proportionate recognition based on the time remaining until maturity. ‘Grandfathered’ should be understood as any transitional measure applicable to a T2 instrument, not including the ‘phase-out’. During this ‘grandfathering’, recognition may be full or partial. If the instrument is not classified as own funds, please indicate ‘No’. For data points c0550 (Type of own funds at consolidated level) and c0560 (Eligible amount of own funds at consolidated level), non-resolution entities should report the type and amount of the liability that is eligible towards the consolidated own funds68, if any. The consolidated own funds should be understood as the ones computed by the corresponding Point of Entry for its consolidated (resolution group) perimeter. When the reporting Non-Resolution Entity is required to consolidate on a sub-consolidated basis, the data point c0550 should be interpreted as “Type of own funds at sub-consolidated level” and c0560 as “Eligible amount of own funds at subconsolidated level”. | F73: Input "Not applicable" | I73: Não | J73: lt002_instrument.typ_own_fnds_indvdl_lvl | L73: {=_xlfn.SWITCH(C73,"Numeric","999999999999999","String","Not applicable","Date","0001-01-01")} -> Not applicable | N73: out_b0200_main_liabilities.0550_typ_own_fnds_cnsldtd_lvl | O73: lt002_instrument.typ_own_fnds_indvdl_lvl | P73: Reunião 2025-09-10 Luís Capitão-Mor, Pedro Mendes, Luísa Sousa Segundo Pedro Mendes: "A minha interpretação é que eles terão os mesmos valores dos data points 0530 e 0540 respetivamente. Isto porque diz na guia: "When the reporting Non-Resolution Entity is required to consolidate on a sub-consolidated basis, the data point c0550 should be interpreted as “Type of own funds at sub-consolidated level” and c0560 as “Eligible amount of own funds at subconsolidated level”." Ou seja o BST individual consolida num BST consolidado que é um sub-consolidado. Quer no BST individual, quer no BST consolidado os instrumentos e respetivos montantes de fundos próprios são os mesmos". Adicionalmente, Pedro Mendes comentou que confirmou com Espanha este entendimento. Reunião 2025-07-30 Luís Capitão-Mor, Pedro Mendes, Luísa Sousa Reunião 2025-07-24 Luís Capitão-Mor, Flávia Pinho, Luísa Sousa | Q73: Campo não LT (apenas tabela Output) | R73: Concluído | S73: NÃO | T73: =IF(SEARCH(B73,N73,4),"ok","nok") -> ok
A74: Eligible amount for own funds at consolidated level | B74: 0560 | C74: Numeric | D74: 2 decimals | E74: The actual amount in EUR of the instrument qualifying as own funds at consolidated level. For data points c0550 (Type of own funds at consolidated level) and c0560 (Eligible amount of own funds at consolidated level), non-resolution entities should report the type and amount of the liability that is eligible towards the consolidated own funds68, if any. The consolidated own funds should be understood as the ones computed by the corresponding Point of Entry for its consolidated (resolution group) perimeter. When the reporting Non-Resolution Entity is required to consolidate on a sub-consolidated basis, the data point c0550 should be interpreted as “Type of own funds at sub-consolidated level” and c0560 as “Eligible amount of own funds at subconsolidated level”. | F74: Input 999999999999999 | I74: Não | J74: lt002_instrument.elgbl_amnt_own_fnds_indvdl_lvl | L74: {=_xlfn.SWITCH(C74,"Numeric","999999999999999","String","Not applicable","Date","0001-01-01")} -> 999999999999999 | N74: out_b0200_main_liabilities.0560_elgbl_amnt_own_fnds_cnsldtd_lvl | O74: lt002_instrument.elgbl_amnt_own_fnds_indvdl_lvl | P74: Reunião 2025-09-10 Luís Capitão-Mor, Pedro Mendes, Luísa Sousa Segundo Pedro Mendes: "A minha interpretação é que eles terão os mesmos valores dos data points 0530 e 0540 respetivamente. Isto porque diz na guia "When the reporting Non-Resolution Entity is required to consolidate on a sub-consolidated basis, the data point c0550 should be interpreted as “Type of own funds at sub-consolidated level” and c0560 as “Eligible amount of own funds at subconsolidated level”." Ou seja o BST individual consolida num BST consolidado que é um sub-consolidado. Quer no BST individual, quer no BST consolidado os instrumentos e respetivos montantes de fundos proprios são os mesmos". Adicionalmente, Pedro Mendes comentou que confirmou com Espanha este entendimento. Reunião 2025-07-30 Luís Capitão-Mor, Pedro Mendes, Luísa Sousa Reunião 2025-07-24 Luís Capitão-Mor, Flávia Pinho, Luísa Sousa | Q74: Campo não LT (apenas tabela Output) | R74: Concluído | S74: SIM | T74: =IF(SEARCH(B74,N74,4),"ok","nok") -> ok
A75: Amount of the security interest provided | B75: 0570 | C75: Numeric | D75: 2 decimals | E75: EUR amount of the security interest provided by a third party. | I75: Não | N75: out_b0200_main_liabilities.0570_amnt_scrty_intrst_prvdd | O75: Valor fixo 0 | P75: Reunião 2025-08-08 Luís Capitão-Mor, Pedro Mendes, Luísa Sousa: Dado que no caso do BST não existe uma third party, tomou-se a decisão de mapear o valor 0. | Q75: Campo não LT (apenas tabela Output) | R75: Concluído | S75: NÃO | T75: =IF(SEARCH(B75,N75,4),"ok","nok") -> ok
A76: Security interest provider (Name) | B76: 0580 | C76: String | D76: Free text | E76: Name of the entity providing the security interest. For deposits reported on an aggregated level, input ‘Not applicable’. | F76: Input "Not applicable" | I76: Não | N76: out_b0200_main_liabilities.0580_scrty_intrst_prvdr | O76: Valor fixo 'Not applicable' | P76: Reunião 2025-08-08 Luís Capitão-Mor, Pedro Mendes, Luísa Sousa: Dado que no caso do BST não existe uma third party, tomou-se a decisão de mapear 'Not applicable'. | Q76: Campo não LT (apenas tabela Output) | R76: Concluído | S76: NÃO | T76: =IF(SEARCH(B76,N76,4),"ok","nok") -> ok
A77: Security interest provider (LEI) | B77: 0581 | C77: String | D77: Free text | E77: LEI code of the entity providing the security interest. For deposits reported on an aggregated level, input ‘Not applicable’. | F77: Input "Not applicable" | I77: Não | N77: out_b0200_main_liabilities.0581_scrty_intrst_prvdr_lei | O77: Valor fixo 'Not applicable' | P77: Reunião 2025-08-08 Luís Capitão-Mor, Pedro Mendes, Luísa Sousa: Dado que no caso do BST não existe uma third party, tomou-se a decisão de mapear 'Not applicable'. | Q77: Campo não LT (apenas tabela Output) | R77: Concluído | S77: NÃO | T77: =IF(SEARCH(B77,N77,4),"ok","nok") -> ok
A78: Type of security interest provided by a third party | B78: 0590 | C78: String | D78: Drop-down | E78: Interest linked to guarantees and sureties. Please select the entry from the following drop-down list: • Lien • Guarantee • Surety • Guarantee obligation • Other • Not applicable In the list of options, "Guarantee obligation" refers to a special type of guarantee agreement that used to be extended to publicly owned banks by their owners where the owners would guarantee liabilities of the respective bank. An example would be the former "Gewährträgerhaftung" applicable to German Landesbanken. For deposits reported on an aggregated level, input ‘Aggregated’. | F78: Input "Not applicable" | I78: Não | N78: out_b0200_main_liabilities.0590_typ_scrty_intrst_prvdd | O78: Valor fixo 'Not applicable' | P78: Reunião 2025-08-08 Luís Capitão-Mor, Pedro Mendes, Luísa Sousa: Dado que no caso do BST não existe uma third party, tomou-se a decisão de mapear 'Not applicable'. | Q78: Campo não LT (apenas tabela Output) | R78: Concluído | S78: NÃO | T78: =IF(SEARCH(B78,N78,4),"ok","nok") -> ok
A79: Collateral for an asset position | B79: 0600 | C79: String | D79: TRUE / FALSE boolean | E79: Indicate whether the liability is used as collateral for an asset position. The value to be reported is a TRUE/FALSE Boolean (where ‘TRUE’ = used as collateral, and ‘FALSE’ = not used as collateral). For deposits reported on an aggregate level, this data point is not applicable. | F79: Input "Not applicable" | I79: Não | N79: out_b0200_main_liabilities.0600_flg_clltrl_asst_pstn | O79: Valor fixo 'FALSE' | P79: Reunião 2025-08-13 Luís Capitão-Mor, Pedro Mendes, Luísa Sousa: Dado que este universo de títulos contém risco, então dificilmente serão usados como Colateral. Como tal, tomou-se a decisão de mapear 'FALSE'. | Q79: Campo não LT (apenas tabela Output) | R79: Concluído | S79: NÃO | T79: =IF(SEARCH(B79,N79,4),"ok","nok") -> ok
A80: Carrying amount IFRS | B80: 0610 | C80: Numeric | D80: 2 decimals | E80: To the extent relevant for the bank, the carrying amount under IFRS (58). (58) - When precise values are not available, estimates can be used to fill this data point. | I80: Não | J80: lt002_instrument.crryng_amnt_instrmnt | L80: {=_xlfn.SWITCH(C80,"Numeric","999999999999999","String","Not applicable","Date","0001-01-01")} -> 999999999999999 | N80: out_b0200_main_liabilities.0610_crryng_amnt_ifrs | O80: (-1) * lt002_instrument.crryng_amnt_instrmnt Nota: Esta multiplicação por -1, deve-se ao facto de no Loan Tape o campo crryng_amnt_instrmnt apresentar valores negativos (para o caso destes registos de Títulos Passivos) e neste report pretenderem-se valores positivos (segundo Pedro Mendes). | P80: Reunião 2025-08-13 Luís Capitão-Mor, Pedro Mendes, Luísa Sousa | Q80: Campo já existente no LT | R80: Concluído | S80: SIM | T80: =IF(SEARCH(B80,N80,4),"ok","nok") -> ok
A81: Balance sheet item according to IFRS | B81: 0620 | C81: String | D81: Drop-down | E81: One of the following items to be selected as attribute in accordance with the classification in FINREP (according to Annex IV of Regulation (EU) 2015/534 of the ECB): • 010 Financial liabilities held for trading; • 070 Financial liabilities at fair value through profit or loss; • 110 Financial liabilities at amortized cost; • 280 Other liabilities; • 300 Total equity. For deposits reported on an aggregated level, please indicate the most prevalent balance sheet item category. | I81: Não | J81: lt002_instrument. accntng_clssfctn | L81: {=_xlfn.SWITCH(C81,"Numeric","999999999999999","String","Not applicable","Date","0001-01-01")} -> Not applicable | M81: Necessário criar novas parametrizaçôes nas tabelas lt829_regras_conversao e lt830_conversoes, podendo as mesmas ser consultadas neste documento nas sheets: LT829 - filtrando por campo_conceito = 'ACCNTNG_CLSSFCTN' e regra_conversao = '3'; LT830 - filtrando por segmento = 'ESTR' e campo_conceito = 'ACCNTNG_CLSSFCTN'. | N81: out_b0200_main_liabilities.0620_blnc_sht_ifrs | O81: lt002_instrument. accntng_clssfctn | P81: Reunião 2025-08-06 Luísa Sousa Em 2025-08-11 Luísa Sousa adicionou na tabela lt803_codigos_lt novas parametrizações, que podem ser consultadas na sheet LT803 - filtrando por campo_lt = 'ACCNTNG_CLSSFCTN'; Parametrizações da lt803_codigos_lt/lt829_regras_conversao/lt830_conversoes confirmadas com Luísa Sousa. Reunião 2025-07-31 Luís Capitão-Mor, Pedro Mendes | Q81: Campo já existente no LT | R81: Concluído | S81: NÃO | T81: =IF(SEARCH(B81,N81,4),"ok","nok") -> ok
A82: Carrying amount national GAAP | B82: 0630 | C82: Numeric | D82: 2 decimals | E82: Carrying amount under national GAAP (where applicable) (59). (59) - When precise values are not available, estimates can be used to fill this data point. | I82: Não | N82: out_b0200_main_liabilities.0630_crrying_amnt_ngaap | O82: Valor fixo 999999999999999 | P82: Reunião 2025-08-13 Luís Capitão-Mor, Pedro Mendes, Luísa Sousa: O BST usa IFRS, não usa national GAAP, como tal, este campo é Not Applicable. | Q82: Campo não LT (apenas tabela Output) | R82: Concluído | S82: NÃO | T82: =IF(SEARCH(B82,N82,4),"ok","nok") -> ok
A83: Balance sheet item at Resolution entity level according to national GAAP | B83: 0640 | C83: String | D83: Free text | E83: Classification in accordance with national GAAP (where applicable). For deposits reported on an aggregated level, please indicate the most prevalent balance sheet item category. | I83: Não | N83: out_b0200_main_liabilities.0640_blnc_sht_ngaap | O83: Valor fixo 'Not applicable' | P83: Reunião 2025-07-31 Luís Capitão-Mor, Pedro Mendes: Segundo Pedro Mendes este campo é not applicable por duas razões: - Porque o BST é uma non-resolution entity; - Porque no caso de Portugal, usa-se o IFRS e não o national GAAP. | Q83: Campo não LT (apenas tabela Output) | R83: Concluído | S83: NÃO | T83: =IF(SEARCH(B83,N83,4),"ok","nok") -> ok
A84: Instrument/liability is issued to or bought by an existing shareholder that is not part of the same resolution group | B84: 5000 | C84: String | D84: TRUE / FALSE boolean | E84: Flag to identify whether a liability is issued to or bought by an existing shareholder that is not part of the same resolution group according to Article 12g(2)(a)(i) SRMR. The value to be reported is a TRUE/FALSE Boolean. | I84: Não | N84: out_b0200_main_liabilities.5000_flg_shrhldr_not_rsltn_grp | O84: Valor fixo 'FALSE' | P84: Reunião 2025-07-31 Luís Capitão-Mor, Pedro Mendes: Campo com o valor fixo 'False'. Não existe previsão de que a futuro existam alterações na estrutura dos grupos de resolução, como tal, assumiu-se este valor como fixo. | Q84: Campo não LT (apenas tabela Output) | R84: Concluído | S84: NÃO | T84: =IF(SEARCH(B84,N84,4),"ok","nok") -> ok
A85: Instrument/liability meets the requirements of Art. 21(7a) SRMR | B85: 5010 | C85: String | D85: TRUE / FALSE boolean | E85: Flag to identify whether a liability fulfils the criteria laid down in Article 21(7a) SRMR (conditions referred to in point Article 12g(2)(a) SRMR, except the condition relating to the remaining maturity of liabilities as set out in Article 72c(1) CRR). The value to be reported is a TRUE/FALSE Boolean. This data point is especially relevant if the scope of collection is expanded, as mentioned in the first paragraph of this annex. | I85: Não | N85: out_b0200_main_liabilities.5010_flg_art21_7a_srmr | O85: Valor fixo 'TRUE' | P85: Reunião 2025-07-31 Luís Capitão-Mor, Pedro Mendes: Segundo Pedro Mendes este campo terá valor fixo 'True', pois para o universo em causa do bail-in (títulos) todos os registos contam para MREL. | Q85: Campo não LT (apenas tabela Output) | R85: Concluído | S85: NÃO | T85: =IF(SEARCH(B85,N85,4),"ok","nok") -> ok
I86: =COUNTIF(I5:I85,"Não") -> 65

Sheet B05.00
A1: B05.00 - Guarantees provided to the Non-Resolution Entity: this tab includes the relevant data points on guarantees for monitoring and implementing the loss transfer and recapitalisation mechanisms at non-resolution entity level;
A2: SRB Instructions | I2: Especificação IT | S2: lt833_agreg_campos
I3: Fase 1 - Granular (Loan Tape) | N3: Fase 2 - Agregada (Não Loan Tape) | P3: Comentários/Histórico EF
A4: Data Point | B4: ID | C4: Data type | D4: Constrain | E4: Description | F4: Treatment of "Not applicable" (if cell is grey out, input is not expected) | G4: Treatment of "Not available" (if cell is grey out, input is not expected) | I4: Novo campo? | J4: Nome campo | K4: Missing Value (LT804) | L4: Not Applicable Value (LT804) | M4: Regra campo | N4: Nome campo | O4: Regra campo | Q4: Estado Especificação | R4: Estado Desenvolvimento | S4: tabela_condicao | T4: campo_condicao | U4: valor_condicao | V4: tabela_origem | W4: campo_origem | X4: campo_destino | Y4: campo_exp | Z4: acao | AA4: ckutulmo | AB4: htimest | AC4: ambito | AD4: segmento | AE4: segmento_agregado | AF4: ref_date | AG4: cod_visao | AH4: Tipo de Garantia | AI4: Necessita de ajuste? (2025-10-31 vs 2025-11-14)
A5: Row number | B5: 0010 | C5: Numeric | D5: Integer | E5: The unique number / primary key to identify the row items (the number must be an integer). | I5: Não | N5: out_b0500_guarantees.0010_row_nmbr | O5: Sequenciador a implementar na tabela de output out_b0500_guarantees Nota: A cada execução não deverão ser gerados Row numbers diferentes pelo que provisoriamente deverá ser feito um order by 0020_uniq_id_guarantee | P5: Reunião 2025-06-02 Luís Capitão-Mor, Pedro Mendes, Luísa Sousa | Q5: Campo não LT (apenas tabela Output) | R5: Concluído | X5: 1 | Y5: 0010 | Z5: SEQUENCIA | AC5: SRB | AE5: B0500 | AG5: 1 | AH5: Geral | AI5: NÃO
A6: Unique (internal) identifier of the guarantee provided to the Non-Resolution Entity | B6: 0020 | C6: String | D6: Free text | E6: Internal identifier of the guarantee and of the financial support arrangement, if applicable. | I6: Não | J6: lt006_instr_prot.instrmnt_id.instrmnt_id lt006_instr_prot.prtctn_id | L6: {=_xlfn.SWITCH(C6,"Numeric","999999999999999","String","Not applicable","Date","0001-01-01")} -> Not applicable | N6: out_b0500_guarantees.0020_uniq_id_guarantee | O6: concat(lt006_instr_prot.instrmnt_id, lt006_instr_prot.prtctn_id) | P6: Reunião 2025-10-13 Luís Capitão-Mor, Pedro Mendes, Luísa Sousa: concat(lt006_instr_prot.instrmnt_id, lt006_instr_prot.prtctn_id) Reunião 2025-06-02 Luís Capitão-Mor, Pedro Mendes, Luísa Sousa: lt004_protection.prtctn_id | Q6: Campo já existente no LT | R6: Concluído | S6: lt002_instrument | T6: ind_univ | U6: B0500 | V6: lt004_protection | W6: prtctn_id | X6: 2 | Y6: 0020 | Z6: AGRUPAR | AC6: SRB | AE6: B0500 | AG6: 1 | AH6: Geral | AI6: NÃO
A7: Governing law | B7: 0030 | C7: String | D7: ISO 3166-1 alpha 2 / ISO 3166-2 | E7: The ISO 3166-1 alpha-2 code of the country whose law governs the instrument (please use the ISO 3166-2 code when the law of an administrative subdivision is relevant, e.g. ‘US-NY’). If the contract is governed by the law of more than one country, indicate the country whose law has the highest relevance for the recognition of write-down and conversion powers. | I7: Não | N7: out_b0500_guarantees.0030_governing_law | O7: Valor fixo 'PT' | P7: Reunião 2025-09-08 Luís Capitão-Mor, Pedro Mendes: No âmbito do campo Governing law da sheet B05.00, verificou-se que os registos deste Universo têm maioritarimente Governing law= 'PT', contudo, existe pelo menos 1 registo, "ELECGAS (TEJO II) 557MM 04/03/08 CLOII" cujo Governing law é 'GB'. Para este registo, consta "English Law" no documento LMA Trade Confirmation Risk Participation (Email recebido 26/06/2025 18:40 de Luís Capitão-Mor com os vários documentos). Será portanto, necessário efectuar um desenvolvimento estrutural que permita alterar o valor reportado em cada campo de cada uma das quatro tabelas de output (out_b0100_aggregate_view, out_b0200_main_liabilities, out_b0500_guarantees, out_b9000_counterparties). Este novo desenvolvimento deverá consistir num processo igual ao holístico já existente no Loan Tape. Exemplo: O campo acima (Governing law) terá o valor fixo ‘PT’ para todos os registos da sheet B05.00. Com este novo desenvolvimento, o Utilizador terá a possibilidade de alterar o valor do registo acima ("ELECGAS (TEJO II) 557MM 04/03/08 CLOII") de 'PT' para 'GB'. Email Pedro Mendes 17/06/2025 08:53: Neste campo pretende-se a governing law ao nível da garantia (recebida). | Q7: Campo não LT (apenas tabela Output) | R7: Concluído | S7: lt002_instrument | T7: ind_univ | U7: B0500 | V7: lt002_instrument | W7: governing_law Campo já existente na lt002_instrument (e não na lt004_protection) | X7: 3 | Y7: 0030 | Z7: AGRUPAR | AC7: SRB | AE7: B0500 | AG7: 1 | AH7: Geral | AI7: NÃO
A8: Guarantee fulfils the requirements pursuant to Art. 12g (3) SRMR | B8: 0040 | C8: String | D8: TRUE / FALSE boolean | E8: Indicate whether the guarantee fulfils the requirements pursuant to Article 12g(3) SRMR. The value to be reported is a TRUE/FALSE Boolean. ‘TRUE’ should be selected only if the SRB has officially recognised that all necessary requirements have been fulfilled. | I8: Não | N8: out_b0500_guarantees.0040_flg_art12g_3_srmr | O8: Valor fixo 'FALSE' | P8: Reunião 2025-08-13 Luís Capitão-Mor, Pedro Mendes, Luísa Sousa ‣ Acordou-se que o campo será criado apenas na tabela final out_b0500_guarantees e não será criado no Loan Tape, à semelhança dos restantes campos de valor fixo. Reunião 2025-06-04 Luís Capitão-Mor, Pedro Mendes, Luísa Sousa ‣ Segundo Pedro Mendes este campo é sempre 'FALSE'. Email Pedro Mendes 17/06/2025 08:53: O BST não tem e não está previsto que venha a ter este tipo de garantias. | Q8: Campo não LT (apenas tabela Output) | R8: Concluído | S8: lt002_instrument | T8: ind_univ | U8: B0500 | V8: lt004_protection | W8: flg_art12g3_srmr Campo novo | X8: 4 | Y8: 0040 | Z8: AGRUPAR | AC8: SRB | AE8: B0500 | AG8: 1 | AH8: Geral | AI8: NÃO
A9: Type of guarantee | B9: 0050 | C9: String | D9: Drop down | E9: Indicate the type of guarantee using one of the values from the Liability Data Report, namely: • Issuance = for guarantees on specific instruments/liabilities that have been issued; • Counterparty = for guarantees granted to a specific counterparty of the institution; • Unlimited = for general guarantees not limited to a fixed amount; • Other types of guarantee than issuance guarantees, counterparty guarantees and unlimited guarantees. | I9: Não | N9: out_b0500_guarantees.0050_typ_guarantee | O9: Valor fixo 'Counterparty' | P9: Reunião 2025-08-13 Luís Capitão-Mor, Pedro Mendes, Luísa Sousa ‣ Acordou-se que o campo será criado apenas na tabela final out_b0500_guarantees e não será criado no Loan Tape, à semelhança dos restantes campos de valor fixo. Reunião 2025-06-04 Luís Capitão-Mor, Pedro Mendes, Luísa Sousa ‣ Segundo Pedro Mendes este campo é sempre 'Counterparty'. ‣ Comentários Luís Capitão-Mor: - O BST não tem nada a garantir uma emissão específíca (portanto não há "Issuance"); - O BST não tem "Unlimited". | Q9: Campo não LT (apenas tabela Output) | R9: Concluído | S9: lt002_instrument | T9: ind_univ | U9: B0500 | V9: lt004_protection | W9: Existem dois campos na lt004_protection: typ_prtctn e typ_prtctn_intrnl. Usar o typ_prtctn ou será um campo novo? | X9: 5 | Y9: 0050 | Z9: AGRUPAR | AC9: SRB | AE9: B0500 | AG9: 1 | AH9: Geral | AI9: NÃO
A10: Maximum amount of the guarantee | B10: 0060 | C10: Numeric | D10: 2 decimals | E10: The EUR (counter)value of the maximum amount (if any) covered by the guarantee / financial support arrangement. | I10: Não | J10: lt006_instr_prot.prtctn_allctd_vl | L10: {=_xlfn.SWITCH(C10,"Numeric","999999999999999","String","Not applicable","Date","0001-01-01")} -> 999999999999999 | N10: out_b0500_guarantees.0060_max_amnt_guarantee | O10: lt006_instr_prot.prtctn_allctd_vl | P10: Reunião 2025-09-10 Luís Capitão-Mor, Pedro Mendes, Luísa Sousa: lt006_instr_prot.prtctn_allctd_vl Reunião 2025-06-04 Luís Capitão-Mor, Pedro Mendes, Luísa Sousa: lt004_protection.prtctn_vl Comentários Luís Capitão-Mor: Se tivermos o Banco Santander S.A. a garantir 4 responsabilidades diferentes ao BST: Garantia 1: 1.000.000 eur Garantia 2: 2.000.000 eur Garantia 3: 3.000.000 eur Garantia 4: 4.000.000 eur Na lt004_protection temos um zcliente único, e portanto, um prtctn_id único dado que no caso das garantias pessoais o protection_id contém o zcliente, logo o prtctn_vl conterá a soma das 4 garantias, ou seja, 10.000.000 eur. Na lt006_instr_prot temos 4 linhas com os 4 prtctn_allctd_vl (1.000.000 eur, 2.000.000 eur, 3.000.000 eur, 4.000.000 eur). Neste caso, queremos reportar 10.000.000 eur que corresponde ao campo prtctn_vl da lt004_protection. A alternativa seria "vetorizar" este campo (1.000.000 | 2.000.000 | 3.000.000 | 4.000.000), mas depois não ficaria com valores somáveis. | Q10: Campo já existente no LT | R10: Concluído | S10: lt002_instrument | T10: ind_univ | U10: B0500 | V10: lt004_protection | W10: max_amnt_prtctn Campo novo nota: já existe o ma | X10: 6 | Y10: 0060 | Z10: SOMAR | AC10: SRB | AE10: B0500 | AG10: 1 | AH10: Geral
A11: Guarantee is secured | B11: 0070 | C11: String | D11: Drop down | E11: Indicate whether the guarantee is: • Secured; • Unsecured. | I11: Sim | J11: lt004_protection.flg_scrd | L11: {=_xlfn.SWITCH(C11,"Numeric","999999999999999","String","Not applicable","Date","0001-01-01")} -> Not applicable | M11: Passo 1: Usar tradutor chaves finrep para converter chave finrep para chave ICs, dado que a gt018_rateio_aval está em chave ICs. Passo 2: Com a chave ICs obtida no Passo 1, aceder à gt018_rateio_aval e obter campo tipologia. Passo 3: Converter campo tipologia obtido no Passo 2 em 'Secured' ou 'Unsecured'. Para tal, será necessário criar nova parametrização na tabela lt831_param_conceitos, podendo a mesma ser consultada neste documento na sheet 'LT831' filtrando por tabela_conceito = 'LT004_PROTECTION' e campo_conceito = 'FLG_SCRD'. | N11: out_b0500_guarantees.0070_flg_scrd | O11: lt004_protection.flg_scrd | P11: Reunião 2025-06-06 Luís Capitão-Mor, Pedro Mendes, Luísa Sousa Comentário Pedro Mendes: - Secured (quando a garantia é real) e Unsecured (quando a garantia não é real). Portanto, como as garantias pessoais não são reais, então são Unsecured. Comentário Luís Capitão-Mor: - Este campo terá de estar sempre preenchido ('Secured' ou 'Unsecured'), não é expectável existirem MISS ou N/A; | Q11: Campo novo no LT | R11: Concluído | S11: lt002_instrument | T11: ind_univ | U11: B0500 | V11: lt004_protection | W11: flg_scrd_prtctn Campo novo | X11: 7 | Y11: 0070 | Z11: AGRUPAR | AC11: SRB | AE11: B0500 | AG11: 1 | AH11: Geral | AI11: NÃO
A12: Current value of the collateral | B12: 0080 | C12: Numeric | D12: 2 decimals | E12: yp | I12: Não | N12: out_b0500_guarantees.0080_amnt_clltrl | O12: Valor fixo 999999999999999 (valor default N/A para numérico definido pelo SRB) | P12: Reunião 2025-06-26 Luís Capitão-Mor, Pedro Mendes, Luísa Sousa: Luis Capitão-Mor indicou que este campo não será criado no Loan Tape mas sim, apenas na tabela de output out_b0500_guarantees, com valor fixo de não aplicável. Isto porque o campo é referente a informação de Colateral, e no caso do BST só existem garantias pessoais recebidas de clientes intragrupo Santander (ou seja, não existem garantias reais, onde se aplica o conceito de colateral). Adicionalmente, Pedro Mendes concordou com esta abordagem (email 03/07/2025 10:18). Reunião 2025-06-05 Luís Capitão-Mor, Pedro Mendes, Luísa Sousa Comentário Luís Capitão-Mor: Existe o campo de haircuts no Loan Tape (HRCT_MV), contudo, o mesmo é referente a IFRS9 (segundo o guia do Loan Tape Estrutural da Corporação). Portanto, como o SRB não refere nada relativamente a IFRS9 então não vamos considerar haircuts. old: Se typ_scrd (campo ID 0070) = 'Secured' reportar lt004_protection.prtctn_vl Se typ_scrd (campo ID 0070) = 'Unsecured' reportar 999999999999999 (valor default N/A para numérico definido pelo SRB) Nota: terá de ser sempre um campo novo pois o campo prtctn_vl já foi solicitado noutro campo deste report. | Q12: Campo não LT (apenas tabela Output) | R12: Concluído | S12: lt002_instrument | T12: ind_univ | U12: B0500 | V12: lt004_protection | W12: crrnt_value_prtctn Campo novo (se bem que existe o prtctn_vl) | X12: 8 | Y12: 0080 | Z12: SOMAR | AC12: SRB | AE12: B0500 | AG12: 1 | AH12: Collateral | AI12: NÃO
A13: Guarantee trigger | B13: 0090 | C13: String | D13: Fixed values | E13: Provide the type(s) of event(s) triggering the activation of the guarantee / financial support, i.e. the event(s) enabling the right for the counterparty to execute the guarantee, choosing from: • Default; • Solvency-related; • Liquidity-related; • Other than default, solvency-related or liquidity-related. In case of multiple entries, please separate them with a vertical bar. | I13: Não | N13: out_b0500_guarantees.0090_guarantee_trggr | O13: Valor fixo 'Default' | P13: Reunião 2025-09-08 Luís Capitão-Mor, Pedro Mendes: - Sugere-se reportar valor fixo 'Default' para este campo. No entanto, se a futuro se identificar a necessidade de se alterar este valor para algum registo, deverá recorrer-se ao novo desenvolvimento estrutural anteriormente mencionado no campo Governing law e no documento funcional MBDT Estrutura v1.0, que permitirá alterar de 'Default' para um dos seguintes valores possíveis (code-list SRB): 'Solvency-related', 'Liquidity-related', 'Other than default, solvency-related or liquidity-related' - Identificaram-se as seguintes referências a Default/Insolvency no documento LMA Trade Confirmation Risk Participation (exemplo Auto-Estradas XXI): -"2.1 Notice of Default (a) If any amont which falls due from an Obligor at any time during the relevant Risk Period and which is referred to in Clause 2.2 (Included Amounts) is not received and applied by the Grantor in full when due, the Grantor may notify the Participant accordingly." -"15. Termination (c) If an Insolvency Event occurs in respect of the Grantor, the Participant may at any time after the occurrence of that Insolvency Event deliver a termination notice to the Grantor and the Risk Participation shall be terminated on and with effect from the date specified in such termination notice." | Q13: Campo não LT (apenas tabela Output) | R13: Concluído | S13: lt002_instrument | T13: ind_univ | U13: B0500 | V13: lt004_protection | W13: trigger_prtctn Campo novo | X13: 9 | Y13: 0090 | Z13: AGRUPAR | AC13: SRB | AE13: B0500 | AG13: 1 | AH13: Geral | AI13: NÃO
A14: Legal maturity date of the collateral | B14: 0100 | C14: Date | D14: yyyy-mm-dd | E14: Date of the legal, final maturity of the collateral. | I14: Não | J14: lt004_protection.dt_mtrty_prtctn | L14: {=_xlfn.SWITCH(C14,"Numeric","999999999999999","String","Not applicable","Date","0001-01-01")} -> 0001-01-01 | N14: out_b0500_guarantees.0100_dt_mtrty_clltrl | O14: lt004_protection.dt_mtrty_prtctn | P14: Reunião 2025-11-04 Luís Capitão-Mor: O SRB está a solicitar a data de vencimento do Colateral e não a data de vencimento da Garantia (referem "collateral" e não "guarantee"). Colateral (ex: uma casa, um título, ...) tipicamente é Real, não se fala de Colateral para se referir a uma Garantia Pessoal, as Garantias Pessoais não são Reais. No caso do BST só existem atualmente Garantias Pessoais recebidas de clientes intragrupo Santander (não existem Garantias Reais, onde se aplica o conceito de Colateral), portanto, no caso das Garantias Pessoais é esperado reportar '0001-01-01' (Not applicable). Sendo assim, deve apontar-se para o campo lt004_protection.dt_mtrty_prtctn, que atualmente já sai a '0001-01-01' (Not applicable) no caso das Garantias Pessoais (a pedido da Corporação no âmbito do LT Estrutural) e se no futuro entrarem Garantias Reais (ex: um bem imóvel) o campo vem naturalmente preenchido. Outra hipótese seria preencher este campo com valor fixo '0001-01-01' (Not applicable) diretamente na tabela final (out_b0500_guarantees), contudo, não ficaria preparado para a situação futura de entrarem Garantias Reais pelo que não se optou por esta hipótese. OLD: Reunião 2025-10-09 Luís Capitão-Mor, Pedro Mendes: -Caminho 1: Contactar Equipa do LT da Corporação e perguntar se o campo DT_MTRTY_PRTCTN poderia passar a ser preenchido para Garantias Pessoais. Atualmente está a ser preenchido com 1111-11-11 (N/A) para Garantias Pessoais, conforme solicitado no Guia da Corporação: "This field does not apply for personal guarantees, please report “1111-11-11". -> Segundo Luísa Sousa 2025-11-04, "a resposta da corporação é que não, não faz sentido colocar data" -Caminho 2 (Se caminho 1 não for possível): Colocar este campo igual à data de vencimento da responsabilidade (ou seja a data de maturidade que consta na lt002) -> vamos assumir que é igual Reunião 2025-06-11 Luís Capitão-Mor, Pedro Mendes: Vamos considerar a data de maturidade da garantia (dt_mtrty_prtctn) apesar da descrição referir a data do colateral (estas 2 datas podem ser distintas). Ex: Empréstimo a 5 anos que tem como colateral (penhor) um DP que vence a 3 anos. Nesse caso, a data de maturidade do colateral não é 5 anos mas sim os 3 anos. | Q14: Campo já existente no LT | R14: Concluído | S14: lt002_instrument | T14: ind_univ | U14: B0500 | V14: lt004_protection | W14: dt_mtrty_prtctn Campo já existente na lt004_protection | X14: 10 | Y14: 0100 | Z14: AGRUPAR | AC14: SRB | AE14: B0500 | AG14: 1 | AH14: Geral | AI14: NÃO
A15: Identifier of the securities used as a collateral for the guarantee | B15: 0110 | C15: String | D15: Free text | E15: Identification number of the securities used as collateral for the guarantee. In the event of multiple entries, please separate them with a vertical bar. | I15: Não | N15: out_b0500_guarantees.0110_scrts_clltrl_id | O15: Valor fixo 'Not applicable' | P15: Reunião 2025-06-26 Luís Capitão-Mor, Pedro Mendes, Luísa Sousa: Luis Capitão-Mor indicou que este campo não será criado no Loan Tape mas sim, apenas na tabela de output out_b0500_guarantees, com valor fixo de não aplicável. Isto porque o campo é referente a informação de Colateral, e no caso do BST só existem garantias pessoais recebidas de clientes intragrupo Santander (ou seja, não existem garantias reais, onde se aplica o conceito de colateral). Adicionalmente, Pedro Mendes concordou com esta abordagem (email 03/07/2025 10:18). Reunião 2025-06-05 Luís Capitão-Mor, Pedro Mendes, Luísa Sousa Como o ISIN não consta na lt004_protection, e dado que no descritivo do campo não referem explicitamente que querem o ISIN (dado que falam apenas em "Identification number") então optou-se por mapear com o prtctn_id que é também composto pelo ISIN. old: Se lt004_protection.typ_prtctn ='12' (Securities) reportar lt004_protection.prtctn_id Se lt004_protection.typ_prtctn <>'12' reportar 'Not applicable' | Q15: Campo não LT (apenas tabela Output) | R15: Concluído | S15: lt002_instrument | T15: ind_univ | U15: B0500 | V15: lt004_protection | W15: id_security_clltrl Campo novo | X15: 11 | Y15: 0110 | Z15: AGRUPAR | AC15: SRB | AE15: B0500 | AG15: 1 | AH15: Securities | AI15: NÃO
A16: Type of collateralization | B16: 0120 | C16: String | D16: Free text | E16: Specify the type of collateral as defined in Article 12g(3)(f) SRMR and Article 197 CRR. | I16: Não | N16: out_b0500_guarantees.0120_typ_clltrlztn | O16: Valor fixo 'Not applicable' | P16: Reunião 2025-06-26 Luís Capitão-Mor, Pedro Mendes, Luísa Sousa: Luis Capitão-Mor indicou que este campo não será criado no Loan Tape mas sim, apenas na tabela de output out_b0500_guarantees, com valor fixo de não aplicável. Isto porque o campo é referente a informação de Colateral, e no caso do BST só existem garantias pessoais recebidas de clientes intragrupo Santander (ou seja, não existem garantias reais, onde se aplica o conceito de colateral). Adicionalmente, Pedro Mendes concordou com esta abordagem (email 03/07/2025 10:18). Nota: Este campo não será criado no Loan Tape mas sim, apenas na tabela de output out_b0500_guarantees, com valor fixo de não aplicável. Isto porque o campo é referente a informação de Colateral, e no caso do BST só existem garantias pessoais recebidas de clientes intragrupo Santander (ou seja, não existem garantias reais, onde se aplica o conceito de colateral). | Q16: Campo não LT (apenas tabela Output) | R16: Concluído | S16: lt002_instrument | T16: ind_univ | U16: B0500 | V16: lt004_protection | W16: typ_collateral_12g3_srmr Campo novo | X16: 11 | Y16: 0120 | Z16: AGRUPAR | AC16: SRB | AE16: B0500 | AG16: 1 | AH16: Collateral | AI16: NÃO
A17: Type of protection value | B17: 0130 | C17: String | D17: Drop down | E17: Indicate the type of value, choosing from the list below. • Notional amount • Fair value • Market value • Long-term sustainable value • Other protection value | I17: Não | N17: out_b0500_guarantees.0130_typ_prtctn_vl | O17: Valor fixo 'Not applicable' | P17: Reunião 2025-06-26 Luís Capitão-Mor, Pedro Mendes, Luísa Sousa: Luis Capitão-Mor indicou que este campo não será criado no Loan Tape mas sim, apenas na tabela de output out_b0500_guarantees, com valor fixo de não aplicável. Isto porque o campo é referente a informação de Colateral, e no caso do BST só existem garantias pessoais recebidas de clientes intragrupo Santander (ou seja, não existem garantias reais, onde se aplica o conceito de colateral). Adicionalmente, Pedro Mendes concordou com esta abordagem (email 03/07/2025 10:18). Reunião 2025-06-05 Luís Capitão-Mor, Pedro Mendes, Luísa Sousa - Atualmente existe uma regra de conversão na lt829_regras_conversao que converte o código que sai no ambito 'PM' ('1', '2,' '3',...) nos respetivos descritivos que são solicitados no ambito 'SRB_VALUATION' ('Fair value', 'Long-term sustainable value', 'Market value', ...), contudo, nessa parametrização é também realizada a conversão de 11111111111 para 'N/A' e de 99999999999 para 'MISS'. Já no ambito SRB_MBDT terá de ser convertido de 11111111111 para 'Not applicable' e de 99999999999 para '' (valores default para N/A e MISS segundo o guia do SRB), e portanto terá de ser criada uma regra nova na lt829_regras_conversao (regra_conversao=2) e não se poderá aproveitar a regra já existente para o ambito 'SRB_VALUATION'. old: Se typ_scrd (campo ID 0070) = 'Secured' reportar typ_prtctn_vl; Se typ_scrd (campo ID 0070) = 'Unsecured' reportar 'Not applicable' (valor default N/A para string definido pelo SRB) ‣ Necessário criar novas parametrizações nas tabelas lt829_regras_conversao e lt830_conversoes, podendo as mesmas ser consultadas neste documento nas sheets: LT829 - filtrando por campo_conceito = 'TYP_PRTCTN_VL_MBDT' e regra_conversao = '1'; LT830 - filtrando por segmento = 'ESTR' e campo_conceito = 'TYP_PRTCTN_VL_MBDT'. | Q17: Campo não LT (apenas tabela Output) | R17: Concluído | S17: lt002_instrument | T17: ind_univ | U17: B0500 | V17: lt004_protection | W17: typ_prtctn_value Campo já existente na lt004_protection | X17: 11 | Y17: 0130 | Z17: AGRUPAR | AC17: SRB | AE17: B0500 | AG17: 1 | AH17: Collateral | AI17: NÃO
A18: Date of the valuation of the security | B18: 0140 | C18: Date | D18: yyyy-mm-dd | E18: The date on which the collateral was most recently estimated or valued before the reporting reference date. | I18: Não | N18: out_b0500_guarantees.0140_dt_vltn_scrty | O18: Valor fixo '0001-01-01' | P18: Reunião 2025-06-26 Luís Capitão-Mor, Pedro Mendes, Luísa Sousa: Luis Capitão-Mor indicou que este campo não será criado no Loan Tape mas sim, apenas na tabela de output out_b0500_guarantees, com valor fixo de não aplicável. Isto porque o campo é referente a informação de Colateral, e no caso do BST só existem garantias pessoais recebidas de clientes intragrupo Santander (ou seja, não existem garantias reais, onde se aplica o conceito de colateral). Adicionalmente, Pedro Mendes concordou com esta abordagem (email 03/07/2025 10:18). Reunião 2025-06-06 Luís Capitão-Mor, Pedro Mendes, Luísa Sousa O data point refere "Date of the valuation of the security", contudo, como na description refere "...which the collateral...", decidiu-se que vamos interpretar este campo com base em colateral (e não em security). old: Se typ_scrd (campo ID 0070) = 'Secured' reportar dt_prtctn_vl; Se typ_scrd (campo ID 0070) = 'Unsecured' reportar '0001-01-01' (valor default N/A para data definido pelo SRB) Aguarda-se resposta ao Email enviado a Pedro Mendes 2025-06-16 16:15: Pedro Mendes deverá questionar Corporação relativamente à regra de Not applicable referida acima. Contudo, segundo o SRB este campo não prevê Not applicable (coluna F). | Q18: Campo não LT (apenas tabela Output) | R18: Concluído | S18: lt002_instrument | T18: ind_univ | U18: B0500 | V18: lt004_protection | W18: dt_prtctn_vl Campo já existente na lt004_protection | X18: 11 | Y18: 0140 | Z18: AGRUPAR | AC18: SRB | AE18: B0500 | AG18: 1 | AH18: Collateral | AI18: NÃO
A19: Protection valuation approach | B19: 0150 | C19: String | D19: Drop down | E19: The type of collateral assessment to determine the value, choosing from the the list below. • Mark-to-market valuation • Counterparty estimation • Creditor valuation • Third party valuation | I19: Não | N19: out_b0500_guarantees.0150_prtctn_vltn_apprch | O19: Valor fixo 'Not applicable' | P19: Reunião 2025-06-26 Luís Capitão-Mor, Pedro Mendes, Luísa Sousa: Luis Capitão-Mor indicou que este campo não será criado no Loan Tape mas sim, apenas na tabela de output out_b0500_guarantees, com valor fixo de não aplicável. Isto porque o campo é referente a informação de Colateral, e no caso do BST só existem garantias pessoais recebidas de clientes intragrupo Santander (ou seja, não existem garantias reais, onde se aplica o conceito de colateral). Adicionalmente, Pedro Mendes concordou com esta abordagem (email 03/07/2025 10:18). Reunião 2025-06-11 Luís Capitão-Mor - Nos ambitos 'PM' e 'SRB_VALUATION' este campo (prtctn_vltn_apprch ) tem também o valor '4' que corresponde a 'Other type of valuation'. Contudo, o SRB não deu esse valor como opção, mas por indicação de Luís Capitão-Mor vai considerar-se na mesma este valor dado que provavelmente tratou-se de um erro do SRB. - Atualmente existe uma regra de conversão na lt829_regras_conversao que converte o código que sai no ambito 'PM' ('1', '2,' '3',...) nos respetivos descritivos que são solicitados no ambito 'SRB_VALUATION' ('Counterparty estimation', 'Creditor valuation', 'Mark-to-market valuation', ...), contudo, nessa parametrização é também realizada a conversão de 11111111111 para 'N/A' e de 99999999999 para 'MISS'. Já no ambito SRB_MBDT terá de ser convertido de 11111111111 para 'Not applicable' e de 99999999999 para '' (valores default para N/A e MISS segundo o guia do SRB), e portanto terá de ser criada uma regra nova na lt829_regras_conversao (regra_conversao=2) e não se poderá aproveitar a regra já existente para o ambito 'SRB_VALUATION'. Old: Se typ_scrd (campo ID 0070) = 'Secured' reportar prtctn_vltn_apprch; Se typ_scrd (campo ID 0070) = 'Unsecured' reportar 'Not applicable' (valor default N/A para string definido pelo SRB). ‣ Necessário criar novas parametrizaçôes nas tabelas lt829_regras_conversao e lt830_conversoes, podendo as mesmas ser consultadas neste documento nas sheets: LT829 - filtrando por campo_conceito = 'PRTCTN_VLTN_APPRCH_MBDT' e regra_conversao = '1'; LT830 - filtrando por segmento = 'ESTR' e campo_conceito = 'PRTCTN_VLTN_APPRCH_MBDT'. | Q19: Campo não LT (apenas tabela Output) | R19: Concluído | S19: lt002_instrument | T19: ind_univ | U19: B0500 | V19: lt004_protection | W19: PRTCTN_VLTN_APPRCH Campo já existente na lt004_protection | X19: 11 | Y19: 0150 | Z19: AGRUPAR | AC19: SRB | AE19: B0500 | AG19: 1 | AH19: Collateral | AI19: NÃO

Sheet B90.00
A1: B90.00 - Counterparties: this tab includes data points related to counterparties of liabilities reported in B02.00, B03.00 and B04.00
A2: SRB Instructions | I2: Especificação IT | T2: lt833_agreg_campos
I3: Fase 1 - Granular (Loan Tape) | N3: Fase 2 - Agregada (Não Loan Tape) | P3: Comentários/Histórico EF
A4: Data Point | B4: ID | C4: Data type | D4: Constrain | E4: Description | F4: Treatment of "Not applicable" (if cell is grey out, input is not expected) | G4: Treatment of "Not available" (if cell is grey out, input is not expected) | I4: Novo campo? | J4: Nome campo | K4: Missing Value (LT804) | L4: Not Applicable Value (LT804) | M4: Regra campo | N4: Nome campo | O4: Regra campo | Q4: Estado Especificação | R4: Estado Desenvolvimento | S4: Necessita de ajuste? (2025-10-31 vs 2025-11-14) | T4: tabela_condicao | U4: campo_condicao | V4: valor_condicao | W4: tabela_origem | X4: campo_origem | Y4: campo_destino | Z4: campo_exp | AA4: acao | AB4: ckutulmo | AC4: htimest | AD4: ambito | AE4: segmento | AF4: segmento_agregado | AG4: ref_date | AH4: cod_visao | AI4: Estado preenchimento
A5: Row number | B5: 0010 | C5: Numeric | D5: Integer | E5: The unique number / primary key to identify the row items (the number must be an integer)._x000D_ | I5: Não | N5: out_b9000_counterparties.0010_row_nmbr | O5: Sequenciador a implementar na tabela de output out_b9000_counterparties. Nota: A cada execução não deverão ser gerados Row numbers diferentes pelo que deverá ser feito um order by 0011_tab_origin, 0020_uniq_id_knwn_cntrprty, 0070_cntrprty_id | P5: Reunião 2025-10-15 Luís Capitão-Mor, Pedro Mendes | Q5: Campo não LT (apenas tabela Output) | R5: Concluído | S5: NÃO | Y5: 1 | Z5: 0010 | AA5: SEQUENCIA | AD5: SRB | AF5: B9000 | AH5: 1 | AI5: Concluido
A6: Tab of origin | B6: 0011 | C6: String | D6: Drop-down | E6: Indicate, from the list of values, in which tab the liability to which the counterparty refers to is reported: ▪ B0200 ▪ B0300 ▪ B0400 ▪ B0500 | I6: Não | N6: out_b9000_counterparties.0011_tab_origin | O6: - Se registo do universo B0200: Reportar 'B0200' - Se registo do universo B0500: Reportar 'B0500' Nota: O processo que alimenta a tabela out_b9000_counterparties, será composto por duas sub-queries: - Uma com universo B0200, em que se colocará valor fixo 'B0200' para todos os registos desta sub-query; - Uma com universo B0500, em que se colocará valor fixo 'B0500' para todos os registos desta sub-query. | P6: Reunião 2025-10-15 Luís Capitão-Mor, Pedro Mendes | Q6: Campo não LT (apenas tabela Output) | R6: Concluído | S6: NÃO | W6: lt002_instrument | X6: ind_univ | Y6: 2 | Z6: 0011 | AA6: AGRUPAR | AD6: SRB | AF6: B9000 | AH6: 1 | AI6: Concluido
A7: Unique identification number (known to the counterparty) | B7: 0020 | C7: String | D7: Free text | E7: The unique identifier of the instrument/liability that would allow the counterparty to conclude that it will be affected by the potential resolution action, without external third parties being able to identify the creditor. For securities, the ISIN code must be indicated where available (other identifiers need only be provided in the absence of an ISIN). For deposits and other liabilities, the account/contract number should be reported. In the event of multiple tranches (multiple counterparties) of one promissory-note loan (e.g. Schuldscheindarlehen) or a syndicated loan, a unique ID must be allocated to each tranche. Reporting entities must ensure that for the instruments / liabilities reported in B02.00, B03.00, B04.00 and B05.00, a correspondence is guaranteed between this field and the identifiers reported in: ▪ B02.00 - c0030 (Unique identification number (known to the counterparty)); ▪ B03.00 - c0010 (Unique identification number of the netting set known to the counterparty); ▪ B04.00 - c0010 (Unique identification number of the netting set known to the counterparty); ▪ B05.00 - c0020 (Unique (internal) identifier of the guarantee provided to the Non-Resolution Entity). | I7: Não | N7: out_b9000_counterparties.0020_uniq_id_knwn_cntrprty | O7: - Se registo do universo B0200: Reportar out_b0200_main_liabilities.0030_uniq_id_knwn_cntrprty - Se registo do universo B0500: Reportar out_b0500_guarantees.0020_uniq_id_guarantee Nota: O processo que alimenta a tabela out_b9000_counterparties, será composto por duas sub-queries: - Uma com universo B0200, em que se reportará out_b0200_main_liabilities.0030_uniq_id_knwn_cntrprty para os registos desta sub-query; - Uma com universo B0500, em que se reportará out_b0500_guarantees.0020_uniq_id_guarantee para os registos desta sub-query. | P7: Reunião 2025-10-15 Luís Capitão-Mor, Pedro Mendes | Q7: Campo não LT (apenas tabela Output) | R7: Concluído | S7: NÃO | T7: lt002_instrument | U7: ind_univ | V7: B0200 | W7: lt002_instrument | X7: isin | Y7: 3 | Z7: 0020 | AA7: AGRUPAR | AD7: SRB | AF7: B9000 | AH7: 1 | AI7: Concluido
A8: Counterparty within the resolution group | B8: 0030 | C8: String | D8: Drop-down | E8: Indicate whether the counterparty of the (portion of) instrument/liability is: • ‘Intragroup and intra-resolution group’ = to be used for counterparties that are both intragroup and part of the same resolution group (64); • ‘Intragroup but not intra-resolution group’ = to be used for counterparties that are intragroup but not part of the same resolution group; • ‘No’ = to be used for counterparties which are external to the group. (64) - Resolution Group within the meaning of Article 2(1)(83b) BRRD | I8: Sim | J8: lt003_entity.cntrprty_rsltn_grp | L8: {=_xlfn.SWITCH(C8,"Numeric","999999999999999","String","Not applicable","Date","0001-01-01")} -> Not applicable | M8: O novo campo 'cntrprty_rsltn_grp' a criar na lt003_entity será populado a partir da parametrização a criar para este campo na tabela lt831_param_conceitos, podendo a mesma ser consultada neste documento na sheet 'LT831' filtrando por tabela_conceito = 'LT003_ENTITY' e campo_conceito = 'CNTRPRTY_RSLTN_GRP'. Esta parametrização irá basear-se em 2 campos: Campo 1 - 'flg_intrgrp' (para a classificação 'Intragroup'): Apesar do report MBDT ser para o Perímetro Individual Local (que não tem intragrupos por definição), neste campo do MBDT o conceito de "Intragroup" é na óptica do perímetro Santander IFRS. Para tal, deverá criar-se um campo nativo 'flg_intrgrp' para poder ser utilizado na lt831_param_conceitos. A lógica de preenchimento do campo deverá ser: flg_intrgrp= '1' no caso dos seguintes zclientes: select zcliente from (SELECT * FROM cd_captools.clientes_intragrupo WHERE data_date_part = '${date}') intragrupo INNER JOIN (SELECT * FROM cd_captools.perimetro WHERE data_date_part = '${date}' AND espanha_ifrs IN ('x', 'B')) perimetro ON intragrupo.consoles = perimetro.cod_espana flg_intrgrp= '0' no caso de outros zclientes Nota: Este campo 'flg_intrgrp' não deverá ser criado na lt003_entity dado que não se identificou necessidade de utilização futura Campo 2 - 'flg_intr_rsltn_grp' (para a classificação 'Intra-resolution group’): Deverá parametrizar-se um campo intermédio 'flg_intr_rsltn_grp' na lt831_param_conceitos, podendo o mesmo ser consultado neste documento na sheet 'LT831' filtrando por campo_conceito = 'FLG_INTR_RSLTN_GRP'. Notas: - Preencheu-se 'AUX' no campo 'tabela_conceito' da lt831_param_conceitos, dado que não é possível efetuar o upload na lt831_param_conceitos sem preencher o campo 'tabela_conceito' (é apresentado erro). - Não se justifica definir este campo para todos os zclientes dos 7 Grupos de Resolução, optou-se por definir apenas para os zclientes do Grupo de Resolução do BST. | N8: out_b9000_counterparties.0030_cntrprty_rsltn_grp | O8: lt003_entity.cntrprty_rsltn_grp | P8: Reunião 2025-10-24 Luís Capitão-Mor, Pedro Mendes Reunião 2025-10-15 Luís Capitão-Mor, Pedro Mendes Segundo email da Corporação (email Pedro Mendes 2025-05-14), no caso do zcliente = '0000000000', reportar valor fixo 'No'. | Q8: Campo novo no LT | R8: Concluído | S8: NÃO | W8: lt003_entity | X8: cntrprty_resol_group | Y8: 4 | Z8: 0030 | AA8: AGRUPAR | AD8: SRB | AF8: B9000 | AH8: 1 | AI8: Concluido
A9: Counterparty name | B9: 0040 | C9: String | D9: Free text | E9: When available, indicate the name of the counterparty/investor/creditor. When deemed relevant to ensure compliance with GDPR requirements, in case of natural persons the name of the counterparty shall be anonymised by the reporting entity. For deposits reported on an aggregate level, please indicate ‘Aggregated’. | F9: Input "Not applicable" | I9: Não | J9: lt003_entity.entty_nm | K9: MISS | L9: {=_xlfn.SWITCH(C9,"Numeric","999999999999999","String","Not applicable","Date","0001-01-01")} -> Not applicable | N9: out_b9000_counterparties.0040_cntrprty_nm | O9: Se lt003_entity.entty_id <> '0000000000' and lt003_entity.prsn_typ <> 'N': Reportar lt003_entity.entty_nm Caso Contrário: Reportar 'Not applicable'. | P9: Email Nuno Ferreira 23/12/2025 15:02: "No âmbito da certificação Bail-in, e na sequência da análise aos campos prsn_typ , cntry e entty_nm da tabela LT003_entity, identificámos algumas incidências para correção. Uma vez que estes campos já existem na LT e não são novos do âmbito 'SRB_MBDT', devem ser preenchidos com o valor 'MISS'em vez de NULL, conforme indicado na tabela cd_loan_tapes_bce.lt804_conf_dflt" Reunião 2025-12-19 Luís Pragosa: Alterada a regra para "and" em vez de "or". Antes: Se lt003_entity.entty_id <> '0000000000' or lt003_entity.prsn_typ <> 'N': Reportar lt003_entity.entty_nm Agora: Se lt003_entity.entty_id <> '0000000000' or lt003_entity.prsn_typ <> 'N': Reportar lt003_entity.entty_nm Reunião 2025-10-16 Luís Capitão-Mor, Pedro Mendes: É referido pelo SRB que no caso de Natural Persons deve-se mascarar o nome do Cliente, como tal optou-se por colocar 'Not applicable' nestes Clientes (bem como no zcliente '0000000000'). Segundo email da Corporação (email Pedro Mendes 2025-05-14), no caso do zcliente = '0000000000', reportar valor fixo 'Not applicable'. | Q9: Campo já existente no LT | R9: Concluído | S9: NÃO | W9: lt003_entity | X9: entty_nm | Y9: 5 | Z9: 0040 | AA9: AGRUPAR | AD9: SRB | AF9: B9000 | AH9: 1 | AI9: Concluido
A10: Counterparty identifier (preferably LEI) | B10: 0050 | C10: String | D10: Free text | E10: Please report the creditor’s LEI code (when available), issued by the Global Legal Entity Identifier Foundation and recommended by the FSB (65). In the absence of an LEI, for banks, the ECB Monetary Financial Institutions identifier (MFI ID) used in RIAD should be reported. For the deposits reported on an aggregate level, this data point is not applicable. When deemed relevant to ensure compliance with GDPR requirements, in case of natural persons the identifier of the counterparty shall be anonymised by the reporting entity. For deposits reported on an aggregate level, please indicate ‘Aggregated’. (65) - See also ESRB/2020/12 Recommendation B. When using the LEI as an identified counterparty, please ensure that the same LEI for the same counterparty is consistently used throughout the template | F10: Input "Not applicable" | I10: Não | J10: lt003_entity.lei lt003_entity.entty_id | L10: {=_xlfn.SWITCH(C10,"Numeric","999999999999999","String","Not applicable","Date","0001-01-01")} -> Not applicable | N10: out_b9000_counterparties.0050_cntrprty_lei | O10: - Se trim(lt003_entity.lei) <> '' ou trim(lt003_entity.lei) <> 'N/A', (lei preenchido): lt003_entity.lei - Se trim(lt003_entity.lei) = '' ou trim(lt003_entity.lei) = 'N/A', (lei não preenchido): lt003_entity.entty_id - Se lt003_entity.entty_id = '0000000000': 'Not applicable'. Nota: Atualmente quando o campo clei da ct003_univ_cli está com '#' é colocado 'N/A' no campo lei da lt003_entity. Deverá constar na lt804_conf_dflt: campo not_applic_val='N/A', quando campo_lt='LEI', tabela_lt='LT003_ENTITY', ambito='SRB_MBDT' e segmento='ESTR'. | P10: Reunião 2025-10-16 Luís Capitão-Mor, Pedro Mendes: No campo abaixo "Type of counterparty identifier" é referido "if other identifiers are reported, please provide a short description", como tal, depreende-se que quando não existe LEI nem MFI IF pode-se reportar outro identificador. Dado que não se tem o MFI ID, então optou-se por colocar o entty_id quando não se tem o código LEI. Segundo email da Corporação (email Pedro Mendes 2025-05-14), no caso do zcliente = '0000000000', reportar valor fixo 'Not applicable'. | Q10: Campo já existente no LT | R10: Concluído | S10: NÃO | W10: lt003_entity | X10: lei se não tiver preenchido entty_id | Y10: 6 | Z10: 0050 | AA10: AGRUPAR | AD10: SRB | AF10: B9000 | AH10: 1 | AI10: Concluido
A11: Type of counterparty identifier | B11: 0060 | C11: String | D11: Free text, but fixed values for specific items | E11: Free text, to indicate what type of identifier has been used in data point c0050. E.g. if the identifier is an LEI, please input ‘LEI’; if the identifier is an MFI, please input ‘MFI’; if other identifiers are reported, please provide a short description. For deposits reported on an aggregate level, please indicate ‘Aggregated’ | F11: Input "Not applicable" | I11: Não | J11: lt003_entity.lei lt003_entity.entty_id | L11: {=_xlfn.SWITCH(C11,"Numeric","999999999999999","String","Not applicable","Date","0001-01-01")} -> Not applicable | N11: out_b9000_counterparties.0060_typ_cntrprty_id | O11: - Se trim(lt003_entity.lei) <> '' ou trim(lt003_entity.lei) <> 'N/A', (lei preenchido): 'LEI' - Se trim(lt003_entity.lei) = '' ou trim(lt003_entity.lei) = 'N/A', (lei não preenchido): 'Internal identifier' - Se lt003_entity.entty_id = '0000000000': 'Not applicable'. | P11: Reunião 2025-10-16 Luís Capitão-Mor, Pedro Mendes Segundo email da Corporação (email Pedro Mendes 2025-05-14), no caso do zcliente = '0000000000', reportar valor fixo 'Not applicable'. | Q11: Campo não LT (apenas tabela Output) | R11: Concluído | S11: NÃO | W11: lt003_entity | X11: typ_instrmnt_id_knwn_cntrprty lei ou o intern ident | Y11: 7 | Z11: 0060 | AA11: AGRUPAR | AD11: SRB | AF11: B9000 | AH11: 1 | AI11: Concluido
A12: Internal identifier of the counterparty | B12: 0070 | C12: String | D12: Free text | E12: The unique internal identifier of the counterparty. For deposits reported on an aggregate level, please indicate ‘Aggregated’. | F12: Input "Not applicable" | I12: Não | J12: lt003_entity.entty_id lt004_protection.prtctn_prvdr_id | N12: out_b9000_counterparties.0070_cntrprty_id | O12: - Se registo do universo B0200: Reportar lt003_entity.entty_id - Se registo do universo B0500: Reportar lt004_protection.prtctn_prvdr_id Se lt003_entity.entty_id = '0000000000': 'Not applicable'. Nota: O processo que alimenta a tabela out_b9000_counterparties, será composto por duas sub-queries: - Uma com universo B0200, em que se reportará lt003_entity.entty_id para os registos desta sub-query; - Uma com universo B0500, em que se reportará lt004_protection.prtctn_prvdr_id para os registos desta sub-query. | P12: Reunião 2025-10-16 Luís Capitão-Mor, Pedro Mendes Segundo email da Corporação (email Pedro Mendes 2025-05-14), no caso do zcliente = '0000000000', reportar valor fixo 'Not applicable'. | Q12: Campo já existente no LT | R12: Concluído | S12: NÃO | W12: lt003_entity | X12: entty_id | Y12: 8 | Z12: 0070 | AA12: AGRUPAR | AD12: SRB | AF12: B9000 | AH12: 1 | AI12: Concluido
A13: Counterparty type | B13: 0080 | C13: String | D13: Drop-down | E13: Indicate the type of counterparty, as per the categories listed below: • Households; • Micro & SME; • Corporates; • Institutions; • Other financial corporations; • Insurance firms & pension funds; • Government, central banks & supranationals; • Non identified, listed on an exchange platform; • Non identified, not listed on an exchange platform. | F13: Input "Not applicable" | I13: Sim | J13: lt003_entity.cntrprty_typ | K13: Non identified, not listed on an exchange platform | L13: Not applicable | M13: Necessário criar nova parametrização na tabela lt831_param_conceitos podendo a mesma ser consultada neste documento na sheet 'LT831' filtrando por tabela_conceito = 'LT003_ENTITY' e campo_conceito = 'CNTRPRTY_TYP'. A parametrização irá basear-se nos campos INTRNL_SGMNT (proveniente da lt003_entity), INSTITUTIONAL_SECTOR (proveniente da lt003_entity) e ENTRPRS_SZ_LE (proveniente da lt003_entity). | N13: out_b9000_counterparties.0080_cntrprty_typ | O13: lt003_entity.cntrprty_typ | P13: Reunião 2025-10-31 Luís Capitão-Mor, Pedro Mendes, Luísa Sousa: Definida a parametrização a constar na lt831_param_conceitos. Em princípio, ficará tudo mapeado, portanto, não se adicionou à parametrização o valor "Non identified, listed on an exchange platform". No limite, se houver algum registo que não fique mapeado, entrará no valor "Non identified, not listed on an exchange platform" que foi o valor que se definiu para missing value na lt804_conf_dflt. Assim, garante-se também o requisito de reportar o valor "Non identified, not listed on an exchange platform" no caso do do zcliente = '0000000000'. Segundo email da Corporação (email Pedro Mendes 2025-05-14), no caso do zcliente = '0000000000', reportar valor fixo "Non identified, not listed on an exchange platform". | Q13: Campo novo no LT | R13: Concluído | S13: NÃO | W13: lt002_instrument | X13: Criar novo campo e criar a respetiva parametrização na lt831 com os seguintes atributos: - intrnl_smg - sme_fnrp18 -institutional_sector • Insurance firms & pension funds deveriam ser ordem 1 . sme_fnrp18= Y then Micro & SME ordem 2: ; ntrnl_smg: outras empresas nao financeiras ordem 3 ntrnl_smg=particulares ordem 4 ntrnl_smg=instituicoes de credito ordem 5 outras empresas nao financeiras ordem 6 setor publico e bancos centrais ordem 7 o que falta ordem 8 | Y13: 9 | Z13: 0080 | AA13: AGRUPAR | AD13: SRB | AF13: B9000 | AH13: 1 | AI13: Concluido
A14: Country of the counterparty | B14: 0090 | C14: String | D14: ISO 3166-1 | E14: Indicate the ISO 3166-1 alpha-2 code of the home state of the counterparty. If unavailable, it may be replaced by the tax residence of the counterparty. If the liability is held by an international/supranational organisation, such as the European Union or the European Central Bank, please enter ‘XX’. For deposits reported on an aggregate level, please indicate ‘XX’. | F14: Input "99" | I14: Não | J14: lt003_entity.cntry | K14: MISS | L14: 99 | N14: out_b9000_counterparties.0090_cntry_cntrprty | O14: lt003_entity.cntry Se lt003_entity.entty_id = '0000000000', reportar '99'. | P14: Email Nuno Ferreira 23/12/2025 15:02: "No âmbito da certificação Bail-in, e na sequência da análise aos campos prsn_typ , cntry e entty_nm da tabela LT003_entity, identificámos algumas incidências para correção. Uma vez que estes campos já existem na LT e não são novos do âmbito 'SRB_MBDT', devem ser preenchidos com o valor 'MISS'em vez de NULL, conforme indicado na tabela cd_loan_tapes_bce.lt804_conf_dflt" Reunião 2025-10-16 Luís Capitão-Mor, Pedro Mendes Segundo email da Corporação (email Pedro Mendes 2025-05-14), no caso do zcliente = '0000000000', reportar valor fixo '99'. | Q14: Campo já existente no LT | R14: Concluído | S14: NÃO | W14: lt003_entity | X14: cntry | Y14: 10 | Z14: 0090 | AA14: AGRUPAR | AD14: SRB | AF14: B9000 | AH14: 1 | AI14: Concluido
A15: Relevant amount for Bail-in/WDC | B15: 0100 | C15: Numeric | D15: 2 decimals | E15: For counterparties holding liabilities reported in tab B02.00, please indicate the amount held as portion of the amount reported in field c0130 of tab B02.00 (Relevant amount for Bail-in/WDC). For counterparties holding liabilities reported in tab B03.00, please indicate the amount held as portion of the amount reported in field c0110 of tab B03.00 (Estimated early termination amount). For counterparties holding liabilities reported in tab B04.00, please indicate the amount held as portion of the amount reported in field c0080 of tab B04.00 (Estimated early termination amount). For counterparties of guarantees reported in tab B05.00, please indicate the amount held as portion of the amount reported in field c0060 of tab B05.00 (Maximum amount of the guarantee). | I15: Não | J15: lt005_instr_ent.otstndng_prncpl_amnt lt005_instr_ent.prtn_amnt_rprtng_entty lt005_instr_ent.accrd_intrst_instrmnt lt006_instr_prot.prtctn_allctd_vl | N15: out_b9000_counterparties.0100_rlvnt_amnt_wdc | O15: - Se registo do universo B0200: Reportar o seguinte cálculo: lt005_instr_ent.otstndng_prncpl_amnt - lt005_instr_ent.prtn_amnt_rprtng_entty + lt005_instr_ent.accrd_intrst_instrmnt - Se registo do universo B0500: Reportar lt006_instr_prot.prtctn_allctd_vl | P15: Reunião 2025-10-28 Luís Capitão-Mor, Pedro Mendes, Luísa Sousa | Q15: Campo não LT (apenas tabela Output) | R15: Concluído | S15: SIM | T15: lt002_instrument | U15: ind_univ | V15: B0200 | W15: lt005_instr_ent | X15: grss_crryng_amnt_instrmnt | Y15: 11 | Z15: 0100 | AA15: SOMAR | AD15: SRB | AF15: B9000 | AH15: 1 | AI15: Por iniciar

Sheet LT803
A1: campo_lt | B1: valor_origem | C1: valor_lt | D1: descritivo_lt | E1: ckutulmo | F1: htimest | G1: ref_date | H1: cod_visao
A2: ACCNTNG_CLSSFCTN | B2: passivos financeiros detidos para negociacao | C2: 1002 | D2: IFRS: Financial liabilities held for trading | H2: 1
A3: ACCNTNG_CLSSFCTN | B3: passivos financeiros ao custo amortizado | C3: 1006 | D3: IFRS: Financial liabilities measured at amortised cost | H3: 1
A4: ACCNTNG_CLSSFCTN | B4: capital | C4: 1100 | D4: IFRS: Capital | H4: 1
A5: ACCNTNG_CLSSFCTN | B5: outros instrumentos de capital | C5: 1200 | D5: IFRS: Other equity | H5: 1
A6: ACCNTNG_CLSSFCTN | B6: acoes proprias | C6: 1300 | D6: IFRS: Treasury shares | H6: 1

Sheet LT829
A1: tabela | B1: campo_conceito | C1: regra_conversao | D1: valor_conceito | E1: valor_destino | F1: descritivo_valor_destino | G1: ckutulmo | H1: htimest | I1: ref_date | J1: cod_visao
A2: LT002_INSTRUMENT | B2: DT_LGL_FNL_MTRTY | C2: 1 | D2: 1111-11-11 | E2: 2099-01-31 | F2: For perpetual instruments, the bank should report 2099-01-31 | J2: 1
A3: LT002_INSTRUMENT | B3: CSD | C3: 1 | D3: INTERBOLSA - SOCIEDADE GESTORA DE SISTEMAS DE LIQUIDACAO E DE SISTEMAS | E3: INTERBOLSA_PT | F3: INTERBOLSA_PT | J3: 1
A4: LT002_INSTRUMENT | B4: CSD | C4: 1 | D4: INTERBOLSA SOC GEST SISTEMAS LIQUIDACAO E SISTEMAS CENTR VAL MOBILI SA | E4: INTERBOLSA_PT | F4: INTERBOLSA_PT | J4: 1
A5: LT002_INSTRUMENT | B5: CSD | C5: 1 | D5: INTERBOLSA SOCIEDADE GESTORA DE SISTEMAS DE LIQUIDACAO E DE SISTEMAS C | E5: INTERBOLSA_PT | F5: INTERBOLSA_PT | J5: 1
A6: LT002_INSTRUMENT | B6: CSD | C6: 1 | D6: INTERBOLSA-SOC.GESTORA SISTEMAS LIQ.SIST.CENTRAL.VAL.MOBILIARIOS, SA | E6: INTERBOLSA_PT | F6: INTERBOLSA_PT | J6: 1
A7: LT002_INSTRUMENT | B7: TYP_INSTRMNT | C7: 2 | D7: 1005 | E7: Registered Bond | F7: Registered Bond | J7: 1
A8: LT002_INSTRUMENT | B8: TYP_INSTRMNT | C8: 2 | D8: 2006 | E8: Title of ownership | F8: Title of ownership | J8: 1
A9: LT002_INSTRUMENT | B9: ACCNTNG_CLSSFCTN | C9: 3 | D9: 1002 | E9: 010 Financial liabilities held for trading | F9: 010 Financial liabilities held for trading | J9: 1
A10: LT002_INSTRUMENT | B10: ACCNTNG_CLSSFCTN | C10: 3 | D10: 1006 | E10: 110 Financial liabilities at amortized cost | F10: 110 Financial liabilities at amortized cost | J10: 1
A11: LT002_INSTRUMENT | B11: ACCNTNG_CLSSFCTN | C11: 3 | D11: 1100 | E11: 300 Total equity | F11: 300 Total equity | J11: 1
A12: LT002_INSTRUMENT | B12: ACCNTNG_CLSSFCTN | C12: 3 | D12: 1200 | E12: 300 Total equity | F12: 300 Total equity | J12: 1
A13: LT002_INSTRUMENT | B13: ACCNTNG_CLSSFCTN | C13: 3 | D13: 1300 | E13: 300 Total equity | F13: 300 Total equity | J13: 1

Sheet LT830
A1: segmento | B1: tabela | C1: campo_conceito | D1: regra_conversao | E1: ckutulmo | F1: htimest | G1: ambito | H1: ref_date | I1: cod_visao
A2: ESTR | B2: LT002_INSTRUMENT | C2: DT_LGL_FNL_MTRTY | D2: 1 | G2: SRB_MBDT | I2: 1
A3: ESTR | B3: LT002_INSTRUMENT | C3: TYP_INSTRMNT | D3: 2 | G3: SRB_MBDT | I3: 1
A4: ESTR | B4: LT002_INSTRUMENT | C4: CSD | D4: 1 | G4: SRB_MBDT | I4: 1
A5: ESTR | B5: LT002_INSTRUMENT | C5: ACCNTNG_CLSSFCTN | D5: 3 | G5: SRB_MBDT | I5: 1

Sheet LT831
A1: tabela_conceito | B1: campo_conceito | C1: valor_destino | D1: atributo_origem_1 | E1: valor_origem_1 | F1: atributo_origem_2 | G1: valor_origem_2 | H1: atributo_origem_3 | I1: valor_origem_3 | J1: atributo_origem_4 | K1: valor_origem_4 | L1: atributo_origem_5 | M1: valor_origem_5 | N1: atributo_origem_6 | O1: valor_origem_6 | P1: atributo_origem_7 | Q1: valor_origem_7 | R1: atributo_origem_8 | S1: valor_origem_8 | T1: atributo_origem_9 | U1: valor_origem_9 | V1: atributo_origem_10 | W1: valor_origem_10 | X1: ordem | Y1: ckutulmo | Z1: htimest | AA1: ref_date | AB1: cod_visao
A2: OUT_B0200_MAIN_LIABILITIES | B2: 0140_NTR_LBLTY | C2: Registered Bond | D2: FLAG_INST_TITULOS | E2: 1 | F2: TIPO_TITULO | G2: in ('Obrigacao Subordinada', 'Obrigacao Senior', 'Instrumento Fundos Proprios Adicionais Nivel 1 (AT1)')
A3: OUT_B0200_MAIN_LIABILITIES | B3: 0140_NTR_LBLTY | C3: Title of ownership | D3: FLAG_INST_TITULOS | E3: 1 | F3: TIPO_TITULO | G3: Acao Ordinaria
A4: OUT_B0200_MAIN_LIABILITIES | B4: 0140_NTR_LBLTY | C4: Not applicable | D4: FLAG_INST_TITULOS | E4: 0
A9: LT002_INSTRUMENT | B9: LBLTY_CTGRY | C9: Liabilities eligible for bail-in | D9: TYP_INSTRMNT | E9: 1005
A10: LT002_INSTRUMENT | B10: LBLTY_CTGRY | C10: Title of ownership | D10: TYP_INSTRMNT | E10: 2006
A12: AUX | B12: 0030_LBLTY_CTGRY | C12: Liabilities eligible for bail-in | D12: 0140_NTR_LBLTY | E12: Registered Bond
A13: AUX | B13: 0030_LBLTY_CTGRY | C13: Title of ownership | D13: 0140_NTR_LBLTY | E13: Title of ownership
A17: LT003_ENTITY | B17: CNTRPRTY_TYP | C17: Insurance firms & pension funds | D17: INTRNL_SGMNT | E17: outras instituicoes financeiras | F17: INSTITUTIONAL_SECTOR | G17: in ('Insurance corporations', 'Pension funds') | X17: 1
A18: LT003_ENTITY | B18: CNTRPRTY_TYP | C18: Other financial corporations | D18: INTRNL_SGMNT | E18: outras instituicoes financeiras | X18: 2
A19: LT003_ENTITY | B19: CNTRPRTY_TYP | C19: Micro & SME | D19: INTRNL_SGMNT | E19: outras empresas nao financeiras | F19: ENTRPRS_SZ_LE | G19: in ('2', '3', '4') | X19: 3
A20: LT003_ENTITY | B20: CNTRPRTY_TYP | C20: Corporates | D20: INTRNL_SGMNT | E20: outras empresas nao financeiras | F20: ENTRPRS_SZ_LE | G20: 1 | X20: 4
A21: LT003_ENTITY | B21: CNTRPRTY_TYP | C21: Corporates | D21: INTRNL_SGMNT | E21: outras empresas nao financeiras | X21: 5
A22: LT003_ENTITY | B22: CNTRPRTY_TYP | C22: Households | D22: INTRNL_SGMNT | E22: particulares | X22: 6
A23: LT003_ENTITY | B23: CNTRPRTY_TYP | C23: Institutions | D23: INTRNL_SGMNT | E23: instituicoes de credito | X23: 7
A24: LT003_ENTITY | B24: CNTRPRTY_TYP | C24: Government, central banks & supranationals | D24: INTRNL_SGMNT | E24: in ('setor publico', 'bancos centrais') | X24: 8
A25: LT002_INSTRUMENT | B25: TRDNG_MTHD | C25: Nominal | D25: FLAG_INST_TITULOS | E25: 1 | F25: TIPO_TITULO | G25: in ('Obrigacao Hipotecaria', 'Obrigacao Senior', 'Obrigacao Subordinada', 'Titularizacao', 'Instrumento Fundos Proprios Adicionais Nivel 1 (AT1)', 'Instrumento de Dívida', 'Bilhetes de Tesouro') | X25: 1
A26: LT002_INSTRUMENT | B26: TRDNG_MTHD | C26: Nominal | D26: FLAG_INST_TITULOS | E26: 1 | F26: substr(PRDCT, 1, 3) | G26: 113 | X26: 2
A27: LT002_INSTRUMENT | B27: TRDNG_MTHD | C27: Unit | D27: FLAG_INST_TITULOS | E27: 1 | X27: 3
A28: LT002_INSTRUMENT | B28: TRDNG_MTHD | C28: Not applicable | D28: FLAG_INST_TITULOS | E28: 0 | X28: 4
A29: LT004_PROTECTION | B29: FLG_SCRD | C29: Unsecured | D29: TIPOLOGIA | E29: PES | X29: 1
A30: LT004_PROTECTION | B30: FLG_SCRD | C30: Secured | D30: TIPOLOGIA | E30: not in ('PES') | X30: 1
A31: LT002_INSTRUMENT | B31: DT_NXT_INTRST_PYMNT | C31: 1111-11-11 | D31: TYP_INSTRMNT | E31: 71 | X31: 1
A32: LT002_INSTRUMENT | B32: DT_NXT_INTRST_PYMNT | C32: 1111-11-11 | D32: TYP_INSTRMNT | E32: 51 | X32: 1
A33: LT002_INSTRUMENT | B33: DT_NXT_INTRST_PYMNT | C33: 1111-11-11 | D33: TYP_INSTRMNT | E33: 2020 | X33: 1
A34: LT002_INSTRUMENT | B34: DT_NXT_INTRST_PYMNT | C34: 1111-11-11 | D34: TYP_INSTRMNT | E34: 2019 | X34: 1
A35: LT002_INSTRUMENT | B35: DT_NXT_INTRST_PYMNT | C35: 1111-11-11 | D35: TYP_INSTRMNT | E35: 2018 | X35: 1
A36: LT002_INSTRUMENT | B36: DT_NXT_INTRST_PYMNT | C36: 1111-11-11 | D36: TYP_INSTRMNT | E36: 2017 | X36: 1
A37: LT002_INSTRUMENT | B37: DT_NXT_INTRST_PYMNT | C37: 1111-11-11 | D37: TYP_INSTRMNT | E37: 2016 | X37: 1
A38: LT002_INSTRUMENT | B38: DT_NXT_INTRST_PYMNT | C38: 1111-11-11 | D38: TYP_INSTRMNT | E38: 2015 | X38: 1
A39: LT002_INSTRUMENT | B39: DT_NXT_INTRST_PYMNT | C39: 1111-11-11 | D39: TYP_INSTRMNT | E39: 2014 | X39: 1
A40: LT002_INSTRUMENT | B40: DT_NXT_INTRST_PYMNT | C40: 1111-11-11 | D40: TYP_INSTRMNT | E40: 2013 | X40: 1
A41: LT002_INSTRUMENT | B41: DT_NXT_INTRST_PYMNT | C41: 1111-11-11 | D41: TYP_INSTRMNT | E41: 2012 | X41: 1
A42: LT002_INSTRUMENT | B42: DT_NXT_INTRST_PYMNT | C42: 1111-11-11 | D42: TYP_INSTRMNT | E42: 2011 | X42: 1
A43: LT002_INSTRUMENT | B43: DT_NXT_INTRST_PYMNT | C43: 1111-11-11 | D43: TYP_INSTRMNT | E43: 2010 | X43: 1
... A56: LT002_INSTRUMENT | B56: DT_NXT_INTRST_PYMNT | C56: 1111-11-11 | D56: TYP_INSTRMNT | E56: 1000 | X56: 1
A57: LT003_ENTITY | B57: CNTRPRTY_RSLTN_GRP | C57: Intragroup and intra-resolution group | D57: FLG_INTGRP | E57: 1 | F57: FLG_INTR_RSLTN_GRP | G57: 1 | X57: 1
A58: LT003_ENTITY | B58: CNTRPRTY_RSLTN_GRP | C58: Intragroup but not intra-resolution group | D58: FLG_INTGRP | E58: 1 | F58: FLG_INTR_RSLTN_GRP | G58: 0 | X58: 1
A59: LT003_ENTITY | B59: CNTRPRTY_RSLTN_GRP | C59: No | D59: FLG_INTGRP | E59: 0 | X59: 1
A60: AUX | B60: FLG_INTR_RSLTN_GRP | C60: 1 | D60: zcliente | E60: 7401276246 | X60: 1
A61: AUX | B61: FLG_INTR_RSLTN_GRP | C61: 1 | D61: zcliente | E61: 2101832415 | X61: 1
A62: AUX | B62: FLG_INTR_RSLTN_GRP | C62: 1 | D62: zcliente | E62: 7401276238 | X62: 1
A63: AUX | B63: FLG_INTR_RSLTN_GRP | C63: 1 | D63: zcliente | E63: 5100615216 | X63: 1
A64: AUX | B64: FLG_INTR_RSLTN_GRP | C64: 1 | D64: zcliente | E64: 5100699767 | X64: 1
A65: AUX | B65: FLG_INTR_RSLTN_GRP | C65: 1 | D65: zcliente | E65: 5100717593 | X65: 1
A66: AUX | B66: FLG_INTR_RSLTN_GRP | C66: 1 | D66: zcliente | E66: 5100684455 | X66: 1
A67: AUX | B67: FLG_INTR_RSLTN_GRP | C67: 1 | D67: zcliente | E67: 2100182850 | X67: 1
