Workbook

Sheet 1. Status Resumo
B6: Sumário Executivo |11 de outubro a 18 de outubro
B8: 1. Implementação em ambiente de Produção das tabelas já testadas e certificadas. A partir de dia 24 já será possível testar a tabela de input da Gloval. 2. Não existiram desenvolvimentos no âmito do Modelo Verde. 3. Foram concluídos 9 campos, permitindo fechar a 3ª tabela da Loan Tape Pilar III. Adicionalmente, foram fechadas as re-especificações de 12 campos.
B22: 1. Modelo de Bens Imóveis | G22: Bens Imóveis - Input | H22: Bens Imóveis - Output
C25: Resumo | G25: Detalhe por Tabela | P25: Status (campos) | T25: 45576 | U25: =T25+7 -> 45583 | V25: ∆ | X25: Highlights
P26: 0. Cancelado | T26: =COUNTIFS('2. Status Detalhe Campos'!$H$7:$H$615,'1. Status Resumo'!$P26,'2. Status Detalhe Campos'!$C$7:$C$615,'1. Status Resumo'!$G$22,'2. Status Detalhe Campos'!$D$7:$D$615,"2. Campo")+COUNTIFS('2. Status Detalhe Campos'!$H$7:$H$615,'1. Status Resumo'!$P26,'2. Status Detalhe Campos'!$C$7:$C$615,'1. Status Resumo'!$H$22,'2. Status Detalhe Campos'!$D$7:$D$615,"2. Campo") -> 10 | U26: =COUNTIFS('2. Status Detalhe Campos'!$G$7:$G$615,'1. Status Resumo'!$P26,'2. Status Detalhe Campos'!$C$7:$C$615,'1. Status Resumo'!$G$22,'2. Status Detalhe Campos'!$D$7:$D$615,"2. Campo")+COUNTIFS('2. Status Detalhe Campos'!$G$7:$G$615,'1. Status Resumo'!$P26,'2. Status Detalhe Campos'!$C$7:$C$615,'1. Status Resumo'!$H$22,'2. Status Detalhe Campos'!$D$7:$D$615,"2. Campo") -> 10 | V26: =U26-T26 -> 0 | X26: 1. Partilha de ajustes à especificação do campo EPC da tabela de Certificados. 2. Datas de entrega de Tecnologia: - Entrada em produção (das 4 tabelas certificadas): 17/10/2024 - Disponibilização do carrgamento de input da Gloval (via front de Upload de Ficheiros): 24/10/2024 - Disponibilização da tabela de output de Certificados Energéticos (com as 4 fontes de informação): 11/11/2024 - Disponibilização de funcionalidades de Pedido de informação para a Gloval: 28/11/2024
P27: 1. Concluído | T27: =COUNTIFS('2. Status Detalhe Campos'!$H$7:$H$615,'1. Status Resumo'!$P27,'2. Status Detalhe Campos'!$C$7:$C$615,'1. Status Resumo'!$G$22,'2. Status Detalhe Campos'!$D$7:$D$615,"2. Campo")+COUNTIFS('2. Status Detalhe Campos'!$H$7:$H$615,'1. Status Resumo'!$P27,'2. Status Detalhe Campos'!$C$7:$C$615,'1. Status Resumo'!$H$22,'2. Status Detalhe Campos'!$D$7:$D$615,"2. Campo") -> 124 | U27: =COUNTIFS('2. Status Detalhe Campos'!$G$7:$G$615,'1. Status Resumo'!$P27,'2. Status Detalhe Campos'!$C$7:$C$615,'1. Status Resumo'!$G$22,'2. Status Detalhe Campos'!$D$7:$D$615,"2. Campo")+COUNTIFS('2. Status Detalhe Campos'!$G$7:$G$615,'1. Status Resumo'!$P27,'2. Status Detalhe Campos'!$C$7:$C$615,'1. Status Resumo'!$H$22,'2. Status Detalhe Campos'!$D$7:$D$615,"2. Campo") -> 124 | V27: =U27-T27 -> 0
P28: 2.1 Em Teste | T28: =COUNTIFS('2. Status Detalhe Campos'!$H$7:$H$615,'1. Status Resumo'!$P28,'2. Status Detalhe Campos'!$C$7:$C$615,'1. Status Resumo'!$G$22,'2. Status Detalhe Campos'!$D$7:$D$615,"2. Campo")+COUNTIFS('2. Status Detalhe Campos'!$H$7:$H$615,'1. Status Resumo'!$P28,'2. Status Detalhe Campos'!$C$7:$C$615,'1. Status Resumo'!$H$22,'2. Status Detalhe Campos'!$D$7:$D$615,"2. Campo") -> 0 | U28: =COUNTIFS('2. Status Detalhe Campos'!$G$7:$G$615,'1. Status Resumo'!$P28,'2. Status Detalhe Campos'!$C$7:$C$615,'1. Status Resumo'!$G$22,'2. Status Detalhe Campos'!$D$7:$D$615,"2. Campo")+COUNTIFS('2. Status Detalhe Campos'!$G$7:$G$615,'1. Status Resumo'!$P28,'2. Status Detalhe Campos'!$C$7:$C$615,'1. Status Resumo'!$H$22,'2. Status Detalhe Campos'!$D$7:$D$615,"2. Campo") -> 0 | V28: =U28-T28 -> 0
D29: ="# "&U35 -> # 168 | P29: 2.2 Em Re-especificação | T29: =COUNTIFS('2. Status Detalhe Campos'!$H$7:$H$615,'1. Status Resumo'!$P29,'2. Status Detalhe Campos'!$C$7:$C$615,'1. Status Resumo'!$G$22,'2. Status Detalhe Campos'!$D$7:$D$615,"2. Campo")+COUNTIFS('2. Status Detalhe Campos'!$H$7:$H$615,'1. Status Resumo'!$P29,'2. Status Detalhe Campos'!$C$7:$C$615,'1. Status Resumo'!$H$22,'2. Status Detalhe Campos'!$D$7:$D$615,"2. Campo") -> 0 | U29: =COUNTIFS('2. Status Detalhe Campos'!$G$7:$G$615,'1. Status Resumo'!$P29,'2. Status Detalhe Campos'!$C$7:$C$615,'1. Status Resumo'!$G$22,'2. Status Detalhe Campos'!$D$7:$D$615,"2. Campo")+COUNTIFS('2. Status Detalhe Campos'!$G$7:$G$615,'1. Status Resumo'!$P29,'2. Status Detalhe Campos'!$C$7:$C$615,'1. Status Resumo'!$H$22,'2. Status Detalhe Campos'!$D$7:$D$615,"2. Campo") -> 0 | V29: =U29-T29 -> 0
P30: 3. Pendente de outros desenvolvimentos | T30: =COUNTIFS('2. Status Detalhe Campos'!$H$7:$H$615,'1. Status Resumo'!$P30,'2. Status Detalhe Campos'!$C$7:$C$615,'1. Status Resumo'!$G$22,'2. Status Detalhe Campos'!$D$7:$D$615,"2. Campo")+COUNTIFS('2. Status Detalhe Campos'!$H$7:$H$615,'1. Status Resumo'!$P30,'2. Status Detalhe Campos'!$C$7:$C$615,'1. Status Resumo'!$H$22,'2. Status Detalhe Campos'!$D$7:$D$615,"2. Campo") -> 0 | U30: =COUNTIFS('2. Status Detalhe Campos'!$G$7:$G$615,'1. Status Resumo'!$P30,'2. Status Detalhe Campos'!$C$7:$C$615,'1. Status Resumo'!$G$22,'2. Status Detalhe Campos'!$D$7:$D$615,"2. Campo")+COUNTIFS('2. Status Detalhe Campos'!$G$7:$G$615,'1. Status Resumo'!$P30,'2. Status Detalhe Campos'!$C$7:$C$615,'1. Status Resumo'!$H$22,'2. Status Detalhe Campos'!$D$7:$D$615,"2. Campo") -> 0 | V30: =U30-T30 -> 0
P31: 4. Validação EF | T31: =COUNTIFS('2. Status Detalhe Campos'!$H$7:$H$615,'1. Status Resumo'!$P31,'2. Status Detalhe Campos'!$C$7:$C$615,'1. Status Resumo'!$G$22,'2. Status Detalhe Campos'!$D$7:$D$615,"2. Campo")+COUNTIFS('2. Status Detalhe Campos'!$H$7:$H$615,'1. Status Resumo'!$P31,'2. Status Detalhe Campos'!$C$7:$C$615,'1. Status Resumo'!$H$22,'2. Status Detalhe Campos'!$D$7:$D$615,"2. Campo") -> 0 | U31: =COUNTIFS('2. Status Detalhe Campos'!$G$7:$G$615,'1. Status Resumo'!$P31,'2. Status Detalhe Campos'!$C$7:$C$615,'1. Status Resumo'!$G$22,'2. Status Detalhe Campos'!$D$7:$D$615,"2. Campo")+COUNTIFS('2. Status Detalhe Campos'!$G$7:$G$615,'1. Status Resumo'!$P31,'2. Status Detalhe Campos'!$C$7:$C$615,'1. Status Resumo'!$H$22,'2. Status Detalhe Campos'!$D$7:$D$615,"2. Campo") -> 0 | V31: =U31-T31 -> 0
P32: 5. Em Correção | R32: (incidências) | T32: =COUNTIFS('2. Status Detalhe Campos'!$H$7:$H$615,'1. Status Resumo'!$P32,'2. Status Detalhe Campos'!$C$7:$C$615,'1. Status Resumo'!$G$22,'2. Status Detalhe Campos'!$D$7:$D$615,"2. Campo")+COUNTIFS('2. Status Detalhe Campos'!$H$7:$H$615,'1. Status Resumo'!$P32,'2. Status Detalhe Campos'!$C$7:$C$615,'1. Status Resumo'!$H$22,'2. Status Detalhe Campos'!$D$7:$D$615,"2. Campo") -> 0 | U32: =COUNTIFS('2. Status Detalhe Campos'!$G$7:$G$615,'1. Status Resumo'!$P32,'2. Status Detalhe Campos'!$C$7:$C$615,'1. Status Resumo'!$G$22,'2. Status Detalhe Campos'!$D$7:$D$615,"2. Campo")+COUNTIFS('2. Status Detalhe Campos'!$G$7:$G$615,'1. Status Resumo'!$P32,'2. Status Detalhe Campos'!$C$7:$C$615,'1. Status Resumo'!$H$22,'2. Status Detalhe Campos'!$D$7:$D$615,"2. Campo") -> 0 | V32: =U32-T32 -> 0
P33: 6. Em implementação (re-especificação) | T33: =COUNTIFS('2. Status Detalhe Campos'!$H$7:$H$615,'1. Status Resumo'!$P33,'2. Status Detalhe Campos'!$C$7:$C$615,'1. Status Resumo'!$G$22,'2. Status Detalhe Campos'!$D$7:$D$615,"2. Campo")+COUNTIFS('2. Status Detalhe Campos'!$H$7:$H$615,'1. Status Resumo'!$P33,'2. Status Detalhe Campos'!$C$7:$C$615,'1. Status Resumo'!$H$22,'2. Status Detalhe Campos'!$D$7:$D$615,"2. Campo") -> 34 | U33: =COUNTIFS('2. Status Detalhe Campos'!$G$7:$G$615,'1. Status Resumo'!$P33,'2. Status Detalhe Campos'!$C$7:$C$615,'1. Status Resumo'!$G$22,'2. Status Detalhe Campos'!$D$7:$D$615,"2. Campo")+COUNTIFS('2. Status Detalhe Campos'!$G$7:$G$615,'1. Status Resumo'!$P33,'2. Status Detalhe Campos'!$C$7:$C$615,'1. Status Resumo'!$H$22,'2. Status Detalhe Campos'!$D$7:$D$615,"2. Campo") -> 34 | V33: =U33-T33 -> 0
P34: 7. Por iniciar | T34: =COUNTIFS('2. Status Detalhe Campos'!$H$7:$H$615,'1. Status Resumo'!$P34,'2. Status Detalhe Campos'!$C$7:$C$615,'1. Status Resumo'!$G$22,'2. Status Detalhe Campos'!$D$7:$D$615,"2. Campo")+COUNTIFS('2. Status Detalhe Campos'!$H$7:$H$615,'1. Status Resumo'!$P34,'2. Status Detalhe Campos'!$C$7:$C$615,'1. Status Resumo'!$H$22,'2. Status Detalhe Campos'!$D$7:$D$615,"2. Campo") -> 0 | U34: =COUNTIFS('2. Status Detalhe Campos'!$G$7:$G$615,'1. Status Resumo'!$P34,'2. Status Detalhe Campos'!$C$7:$C$615,'1. Status Resumo'!$G$22,'2. Status Detalhe Campos'!$D$7:$D$615,"2. Campo")+COUNTIFS('2. Status Detalhe Campos'!$G$7:$G$615,'1. Status Resumo'!$P34,'2. Status Detalhe Campos'!$C$7:$C$615,'1. Status Resumo'!$H$22,'2. Status Detalhe Campos'!$D$7:$D$615,"2. Campo") -> 0 | V34: =U34-T34 -> 0
T35: =SUM(T26:T34) -> 168 | U35: =SUM(U26:U34) -> 168
G36: Status (Tabelas) | P36: Status (Universos)
F37: > | G37: Tabela de Bens Imóveis | L37: OK | O37: > | P37: Universo Bens Colateralizados (MUG) | T37: OK
F38: > | G38: Tabelas de Processos Imobiliários | L38: OK | O38: > | P38: Universo Bens Não Colateralizados (GP) | T38: OK
F39: > | G39: Tabela de Traçabilidade Processo -Bem | L39: OK | O39: > | P39: Universo Bens Adjudicados | T39: Não serão testados neste projeto
F40: > | G40: Tabela de Traçabilidade Crédito - Processo | L40: OK
F41: > | G41: Tabela input de Cerificados Energéticos (Gloval) | L41: Em Implementação
F42: > | G42: Tabela Output de Cerificados Energéticos | L42: Em Implementação
B48: 2. Modelo Verde | G48: Modelo Verde - Input | H48: Modelo Verde - Output
C51: Resumo | G51: Detalhe por Tabela | P51: Status (campos) | T51: =T25 -> 45576 | U51: =$U$25 -> 45583 | V51: ∆ | X51: Highlights
P52: 0. Cancelado | T52: =COUNTIFS('2. Status Detalhe Campos'!$H$7:$H$615,'1. Status Resumo'!$P52,'2. Status Detalhe Campos'!$C$7:$C$615,'1. Status Resumo'!$G$48,'2. Status Detalhe Campos'!$D$7:$D$615,"2. Campo")+COUNTIFS('2. Status Detalhe Campos'!$H$7:$H$615,'1. Status Resumo'!$P52,'2. Status Detalhe Campos'!$C$7:$C$615,'1. Status Resumo'!$H$48,'2. Status Detalhe Campos'!$D$7:$D$615,"2. Campo") -> 14 | U52: =COUNTIFS('2. Status Detalhe Campos'!$G$7:$G$615,'1. Status Resumo'!$P52,'2. Status Detalhe Campos'!$C$7:$C$615,'1. Status Resumo'!$G$48,'2. Status Detalhe Campos'!$D$7:$D$615,"2. Campo")+COUNTIFS('2. Status Detalhe Campos'!$G$7:$G$615,'1. Status Resumo'!$P52,'2. Status Detalhe Campos'!$C$7:$C$615,'1. Status Resumo'!$H$48,'2. Status Detalhe Campos'!$D$7:$D$615,"2. Campo") -> 14 | V52: =U52-T52 -> 0 | X52: 1. Campos Em Implementação (re-especificão) ou Em Correção.
P53: 1. Concluído | T53: =COUNTIFS('2. Status Detalhe Campos'!$H$7:$H$615,'1. Status Resumo'!$P53,'2. Status Detalhe Campos'!$C$7:$C$615,'1. Status Resumo'!$G$48,'2. Status Detalhe Campos'!$D$7:$D$615,"2. Campo")+COUNTIFS('2. Status Detalhe Campos'!$H$7:$H$615,'1. Status Resumo'!$P53,'2. Status Detalhe Campos'!$C$7:$C$615,'1. Status Resumo'!$H$48,'2. Status Detalhe Campos'!$D$7:$D$615,"2. Campo") -> 154 | U53: =COUNTIFS('2. Status Detalhe Campos'!$G$7:$G$615,'1. Status Resumo'!$P53,'2. Status Detalhe Campos'!$C$7:$C$615,'1. Status Resumo'!$G$48,'2. Status Detalhe Campos'!$D$7:$D$615,"2. Campo")+COUNTIFS('2. Status Detalhe Campos'!$G$7:$G$615,'1. Status Resumo'!$P53,'2. Status Detalhe Campos'!$C$7:$C$615,'1. Status Resumo'!$H$48,'2. Status Detalhe Campos'!$D$7:$D$615,"2. Campo") -> 154 | V53: =U53-T53 -> 0
P54: 2.1 Em Teste | T54: =COUNTIFS('2. Status Detalhe Campos'!$H$7:$H$615,'1. Status Resumo'!$P54,'2. Status Detalhe Campos'!$C$7:$C$615,'1. Status Resumo'!$G$48,'2. Status Detalhe Campos'!$D$7:$D$615,"2. Campo")+COUNTIFS('2. Status Detalhe Campos'!$H$7:$H$615,'1. Status Resumo'!$P54,'2. Status Detalhe Campos'!$C$7:$C$615,'1. Status Resumo'!$H$48,'2. Status Detalhe Campos'!$D$7:$D$615,"2. Campo") -> 0 | U54: =COUNTIFS('2. Status Detalhe Campos'!$G$7:$G$615,'1. Status Resumo'!$P54,'2. Status Detalhe Campos'!$C$7:$C$615,'1. Status Resumo'!$G$48,'2. Status Detalhe Campos'!$D$7:$D$615,"2. Campo")+COUNTIFS('2. Status Detalhe Campos'!$G$7:$G$615,'1. Status Resumo'!$P54,'2. Status Detalhe Campos'!$C$7:$C$615,'1. Status Resumo'!$H$48,'2. Status Detalhe Campos'!$D$7:$D$615,"2. Campo") -> 0 | V54: =U54-T54 -> 0
D55: ="# "&U61 -> # 245 | P55: 2.2 Em Re-especificação | T55: =COUNTIFS('2. Status Detalhe Campos'!$H$7:$H$615,'1. Status Resumo'!$P55,'2. Status Detalhe Campos'!$C$7:$C$615,'1. Status Resumo'!$G$48,'2. Status Detalhe Campos'!$D$7:$D$615,"2. Campo")+COUNTIFS('2. Status Detalhe Campos'!$H$7:$H$615,'1. Status Resumo'!$P55,'2. Status Detalhe Campos'!$C$7:$C$615,'1. Status Resumo'!$H$48,'2. Status Detalhe Campos'!$D$7:$D$615,"2. Campo") -> 0 | U55: =COUNTIFS('2. Status Detalhe Campos'!$G$7:$G$615,'1. Status Resumo'!$P55,'2. Status Detalhe Campos'!$C$7:$C$615,'1. Status Resumo'!$G$48,'2. Status Detalhe Campos'!$D$7:$D$615,"2. Campo")+COUNTIFS('2. Status Detalhe Campos'!$G$7:$G$615,'1. Status Resumo'!$P55,'2. Status Detalhe Campos'!$C$7:$C$615,'1. Status Resumo'!$H$48,'2. Status Detalhe Campos'!$D$7:$D$615,"2. Campo") -> 0 | V55: =U55-T55 -> 0
P56: 3. Pendente de outros desenvolvimentos | T56: =COUNTIFS('2. Status Detalhe Campos'!$H$7:$H$615,'1. Status Resumo'!$P56,'2. Status Detalhe Campos'!$C$7:$C$615,'1. Status Resumo'!$G$48,'2. Status Detalhe Campos'!$D$7:$D$615,"2. Campo")+COUNTIFS('2. Status Detalhe Campos'!$H$7:$H$615,'1. Status Resumo'!$P56,'2. Status Detalhe Campos'!$C$7:$C$615,'1. Status Resumo'!$H$48,'2. Status Detalhe Campos'!$D$7:$D$615,"2. Campo") -> 0 | U56: =COUNTIFS('2. Status Detalhe Campos'!$G$7:$G$615,'1. Status Resumo'!$P56,'2. Status Detalhe Campos'!$C$7:$C$615,'1. Status Resumo'!$G$48,'2. Status Detalhe Campos'!$D$7:$D$615,"2. Campo")+COUNTIFS('2. Status Detalhe Campos'!$G$7:$G$615,'1. Status Resumo'!$P56,'2. Status Detalhe Campos'!$C$7:$C$615,'1. Status Resumo'!$H$48,'2. Status Detalhe Campos'!$D$7:$D$615,"2. Campo") -> 0 | V56: =U56-T56 -> 0
P57: 4. Validação EF | T57: =COUNTIFS('2. Status Detalhe Campos'!$H$7:$H$615,'1. Status Resumo'!$P57,'2. Status Detalhe Campos'!$C$7:$C$615,'1. Status Resumo'!$G$48,'2. Status Detalhe Campos'!$D$7:$D$615,"2. Campo")+COUNTIFS('2. Status Detalhe Campos'!$H$7:$H$615,'1. Status Resumo'!$P57,'2. Status Detalhe Campos'!$C$7:$C$615,'1. Status Resumo'!$H$48,'2. Status Detalhe Campos'!$D$7:$D$615,"2. Campo") -> 0 | U57: =COUNTIFS('2. Status Detalhe Campos'!$G$7:$G$615,'1. Status Resumo'!$P57,'2. Status Detalhe Campos'!$C$7:$C$615,'1. Status Resumo'!$G$48,'2. Status Detalhe Campos'!$D$7:$D$615,"2. Campo")+COUNTIFS('2. Status Detalhe Campos'!$G$7:$G$615,'1. Status Resumo'!$P57,'2. Status Detalhe Campos'!$C$7:$C$615,'1. Status Resumo'!$H$48,'2. Status Detalhe Campos'!$D$7:$D$615,"2. Campo") -> 0 | V57: =U57-T57 -> 0
P58: 5. Em Correção | R58: (incidências) | T58: =COUNTIFS('2. Status Detalhe Campos'!$H$7:$H$615,'1. Status Resumo'!$P58,'2. Status Detalhe Campos'!$C$7:$C$615,'1. Status Resumo'!$G$48,'2. Status Detalhe Campos'!$D$7:$D$615,"2. Campo")+COUNTIFS('2. Status Detalhe Campos'!$H$7:$H$615,'1. Status Resumo'!$P58,'2. Status Detalhe Campos'!$C$7:$C$615,'1. Status Resumo'!$H$48,'2. Status Detalhe Campos'!$D$7:$D$615,"2. Campo") -> 2 | U58: =COUNTIFS('2. Status Detalhe Campos'!$G$7:$G$615,'1. Status Resumo'!$P58,'2. Status Detalhe Campos'!$C$7:$C$615,'1. Status Resumo'!$G$48,'2. Status Detalhe Campos'!$D$7:$D$615,"2. Campo")+COUNTIFS('2. Status Detalhe Campos'!$G$7:$G$615,'1. Status Resumo'!$P58,'2. Status Detalhe Campos'!$C$7:$C$615,'1. Status Resumo'!$H$48,'2. Status Detalhe Campos'!$D$7:$D$615,"2. Campo") -> 2 | V58: =U58-T58 -> 0
P59: 6. Em implementação (re-especificação) | T59: =COUNTIFS('2. Status Detalhe Campos'!$H$7:$H$615,'1. Status Resumo'!$P59,'2. Status Detalhe Campos'!$C$7:$C$615,'1. Status Resumo'!$G$48,'2. Status Detalhe Campos'!$D$7:$D$615,"2. Campo")+COUNTIFS('2. Status Detalhe Campos'!$H$7:$H$615,'1. Status Resumo'!$P59,'2. Status Detalhe Campos'!$C$7:$C$615,'1. Status Resumo'!$H$48,'2. Status Detalhe Campos'!$D$7:$D$615,"2. Campo") -> 75 | U59: =COUNTIFS('2. Status Detalhe Campos'!$G$7:$G$615,'1. Status Resumo'!$P59,'2. Status Detalhe Campos'!$C$7:$C$615,'1. Status Resumo'!$G$48,'2. Status Detalhe Campos'!$D$7:$D$615,"2. Campo")+COUNTIFS('2. Status Detalhe Campos'!$G$7:$G$615,'1. Status Resumo'!$P59,'2. Status Detalhe Campos'!$C$7:$C$615,'1. Status Resumo'!$H$48,'2. Status Detalhe Campos'!$D$7:$D$615,"2. Campo") -> 75 | V59: =U59-T59 -> 0
P60: 7. Por iniciar | T60: =COUNTIFS('2. Status Detalhe Campos'!$H$7:$H$615,'1. Status Resumo'!$P60,'2. Status Detalhe Campos'!$C$7:$C$615,'1. Status Resumo'!$G$48,'2. Status Detalhe Campos'!$D$7:$D$615,"2. Campo")+COUNTIFS('2. Status Detalhe Campos'!$H$7:$H$615,'1. Status Resumo'!$P60,'2. Status Detalhe Campos'!$C$7:$C$615,'1. Status Resumo'!$H$48,'2. Status Detalhe Campos'!$D$7:$D$615,"2. Campo") -> 0 | U60: =COUNTIFS('2. Status Detalhe Campos'!$G$7:$G$615,'1. Status Resumo'!$P60,'2. Status Detalhe Campos'!$C$7:$C$615,'1. Status Resumo'!$G$48,'2. Status Detalhe Campos'!$D$7:$D$615,"2. Campo")+COUNTIFS('2. Status Detalhe Campos'!$G$7:$G$615,'1. Status Resumo'!$P60,'2. Status Detalhe Campos'!$C$7:$C$615,'1. Status Resumo'!$H$48,'2. Status Detalhe Campos'!$D$7:$D$615,"2. Campo") -> 0 | V60: =U60-T60 -> 0
T61: =SUM(T52:T60) -> 245 | U61: =SUM(U52:U60) -> 245
P63: Status (Universos - Inputs)
O64: > | P64: modesg_inp_risco_fisico | T64: OK
O65: > | P65: modesg_inp_nfrd_alinhamento_tax | T65: OK
O66: > | P66: modesg_inp_km_medios_emss_vcls | T66: OK
O67: > | P67: modesg_inp_emss_vcls | T67: OK
O68: > | P68: modesg_inp_emss_scib | T68: OK
O69: > | P69: modesg_inp_emss_nace | T69: OK
O70: > | P70: modesg_inp_emss_bens_imoveis | T70: OK
O71: > | P71: modesg_inp_empr_excl_paris | T71: OK
O72: > | P72: modesg_param_sfcs_taxon_europeia | T72: Em Implementação (re-especificação)
O73: > | P73: Input Munich Re | T73: Em Implementação
P75: Status (Universos - Outputs)
O76: > | P76: modesg_out_ems_vcls | T76: Em Implementação (re-especificação)
O77: > | P77: modesg_out_bens_imoveis | T77: OK (coerente com Modelo de Bens Imóveis)
O78: > | P78: modesg_out_empr_info_nfin | T78: OK
O79: > | P79: modesg_out_sfcs_taxon_europeia | T79: Em Implementação (re-especificação)
B83: 3. Loan Tape | Pilar III | G83: Pilar III
C86: Resumo | G86: Detalhe por Tabela | P86: Status (campos) | T86: =T25 -> 45576 | U86: =$U$25 -> 45583 | V86: ∆ | X86: Highlights
P87: 0. Cancelado | T87: =COUNTIFS(Table4[Status Anterior],'1. Status Resumo'!$P87,Table4[Sub-âmbito],'1. Status Resumo'!$G$83,Table4[Tipo de teste],"2. Campo") -> 0 | U87: =COUNTIFS(Table4[Status Atual],'1. Status Resumo'!$P87,Table4[Sub-âmbito],'1. Status Resumo'!$G$83,Table4[Tipo de teste],"2. Campo") -> 0 | V87: =U87-T87 -> 0 | X87: 1. Continuação do assessment à Loan Tape - Pilar III. 2. Início da simulação das Tabelas instrument e entity. 3. Foram concluídos 9 campos, fechando a tabela lt826_esg_sbsctr. 4. Detalhe dos campos em Re-especificação (14): - Emissões de Scopes ao Nível do Grupo - Universo tabela Protection e respetivos atributos da Loan Tape Estrutural 5. Detalhe dos campos em Validação EF (Dependências): - Resposta da Corporação (13 campos): Metodologia de Aprovisionamento de Emissões de Scopes - Reunião com CDO e Zeneida (4 campos): Criação de Nova tabela - Validação da Susana (1 campo): Mapeamento Categoria SFICS
P88: 1. Concluído | T88: =COUNTIFS(Table4[Status Anterior],'1. Status Resumo'!$P88,Table4[Sub-âmbito],'1. Status Resumo'!$G$83,Table4[Tipo de teste],"2. Campo") -> 42 | U88: =COUNTIFS(Table4[Status Atual],'1. Status Resumo'!$P88,Table4[Sub-âmbito],'1. Status Resumo'!$G$83,Table4[Tipo de teste],"2. Campo") -> 51 | V88: =U88-T88 -> 9
P89: 2.1 Em Teste | T89: =COUNTIFS(Table4[Status Anterior],'1. Status Resumo'!$P89,Table4[Sub-âmbito],'1. Status Resumo'!$G$83,Table4[Tipo de teste],"2. Campo") -> 12 | U89: =COUNTIFS(Table4[Status Atual],'1. Status Resumo'!$P89,Table4[Sub-âmbito],'1. Status Resumo'!$G$83,Table4[Tipo de teste],"2. Campo") -> 2 | V89: =U89-T89 -> -10
D90: ="# "&U96 -> # 126 | P90: 2.2 Em Re-especificação | T90: =COUNTIFS(Table4[Status Anterior],'1. Status Resumo'!$P90,Table4[Sub-âmbito],'1. Status Resumo'!$G$83,Table4[Tipo de teste],"2. Campo") -> 23 | U90: =COUNTIFS(Table4[Status Atual],'1. Status Resumo'!$P90,Table4[Sub-âmbito],'1. Status Resumo'!$G$83,Table4[Tipo de teste],"2. Campo") -> 14 | V90: =U90-T90 -> -9
P91: 3. Pendente de outros desenvolvimentos | T91: =COUNTIFS(Table4[Status Anterior],'1. Status Resumo'!$P91,Table4[Sub-âmbito],'1. Status Resumo'!$G$83,Table4[Tipo de teste],"2. Campo") -> 20 | U91: =COUNTIFS(Table4[Status Atual],'1. Status Resumo'!$P91,Table4[Sub-âmbito],'1. Status Resumo'!$G$83,Table4[Tipo de teste],"2. Campo") -> 22 | V91: =U91-T91 -> 2
P92: 4. Validação EF | T92: =COUNTIFS(Table4[Status Anterior],'1. Status Resumo'!$P92,Table4[Sub-âmbito],'1. Status Resumo'!$G$83,Table4[Tipo de teste],"2. Campo") -> 24 | U92: =COUNTIFS(Table4[Status Atual],'1. Status Resumo'!$P92,Table4[Sub-âmbito],'1. Status Resumo'!$G$83,Table4[Tipo de teste],"2. Campo") -> 18 | V92: =U92-T92 -> -6
P93: 5. Em Correção | R93: (incidências) | T93: =COUNTIFS(Table4[Status Anterior],'1. Status Resumo'!$P93,Table4[Sub-âmbito],'1. Status Resumo'!$G$83,Table4[Tipo de teste],"2. Campo") -> 0 | U93: =COUNTIFS(Table4[Status Atual],'1. Status Resumo'!$P93,Table4[Sub-âmbito],'1. Status Resumo'!$G$83,Table4[Tipo de teste],"2. Campo") -> 1 | V93: =U93-T93 -> 1
P94: 6. Em implementação (re-especificação) | T94: =COUNTIFS(Table4[Status Anterior],'1. Status Resumo'!$P94,Table4[Sub-âmbito],'1. Status Resumo'!$G$83,Table4[Tipo de teste],"2. Campo") -> 0 | U94: =COUNTIFS(Table4[Status Atual],'1. Status Resumo'!$P94,Table4[Sub-âmbito],'1. Status Resumo'!$G$83,Table4[Tipo de teste],"2. Campo") -> 13 | V94: =U94-T94 -> 13
P95: 7. Por iniciar | T95: =COUNTIFS(Table4[Status Anterior],'1. Status Resumo'!$P95,Table4[Sub-âmbito],'1. Status Resumo'!$G$83,Table4[Tipo de teste],"2. Campo") -> 5 | U95: =COUNTIFS(Table4[Status Atual],'1. Status Resumo'!$P95,Table4[Sub-âmbito],'1. Status Resumo'!$G$83,Table4[Tipo de teste],"2. Campo") -> 5 | V95: =U95-T95 -> 0
T96: =SUM(T87:T95) -> 126 | U96: =SUM(U87:U95) -> 126
P98: Status (Tabelas)
O99: > | P99: lt002_instrument | T99: Em Curso
O100: > | P100: lt003_entity | T100: Em Curso
O101: > | P101: lt004_protection | T101: Em Curso
O102: > | P102: lt005_instr_ent | T102: OK
O103: > | P103: lt006_instr_prot | T103: OK
O104: > | P104: lt825_mthd_usd_instrmnt | T104: Validação EF
O105: > | P105: lt826_esg_sbsctr | T105: OK

Sheet 2. Status Detalhe Campos
B6: Âmbito | C6: Sub-âmbito | D6: Tipo de teste | E6: Tabela | F6: Campo | G6: Status Atual | H6: Status Anterior | I6: Observações | J6: Data de Pedido correção/esclarecimento | K6: Data de correção prevista | L6: Data de correção efetiva | M6: Data Reunião
A7: =E7&F7 -> ENERGY_CERTIFICATE_EST_INPUTn.a. | B7: Pilar III | C7: Bens Imóveis - Input | D7: 1. Universo | E7: ENERGY_CERTIFICATE_EST_INPUT | F7: n.a. | G7: 6. Em implementação (re-especificação) | H7: 6. Em implementação (re-especificação) | I7: Apesar da data de correção ser 28/11 a data que importa é 24/10, uma vez que a última implementação não é relevanta para iniciar os testes à tabela | J7: 45510 | K7: 45624
A8: =E8&F8 -> ENERGY_CERTIFICATE_EST_INPUTPROPERTY_BANK_ID | B8: Pilar III | C8: Bens Imóveis - Input | D8: 2. Campo | E8: ENERGY_CERTIFICATE_EST_INPUT | F8: PROPERTY_BANK_ID | G8: 6. Em implementação (re-especificação) | H8: 6. Em implementação (re-especificação) | I8: Apesar da data de correção ser 28/11 a data que importa é 24/10, uma vez que a última implementação não é relevanta para iniciar os testes à tabela | J8: 45510 | K8: 45624
A9: =E9&F9 -> ENERGY_CERTIFICATE_EST_INPUTENCRYPTED_KEY | B9: Pilar III | C9: Bens Imóveis - Input | D9: 2. Campo | E9: ENERGY_CERTIFICATE_EST_INPUT | F9: ENCRYPTED_KEY | G9: 6. Em implementação (re-especificação) | H9: 6. Em implementação (re-especificação) | I9: Apesar da data de correção ser 28/11 a data que importa é 24/10, uma vez que a última implementação não é relevanta para iniciar os testes à tabela | J9: 45510 | K9: 45624
A10: =E10&F10 -> ENERGY_CERTIFICATE_EST_INPUTPROPERTY_BRANCH_CODE | B10: Pilar III | C10: Bens Imóveis - Input | D10: 2. Campo | E10: ENERGY_CERTIFICATE_EST_INPUT | F10: PROPERTY_BRANCH_CODE | G10: 6. Em implementação (re-especificação) | H10: 6. Em implementação (re-especificação) | I10: Apesar da data de correção ser 28/11 a data que importa é 24/10, uma vez que a última implementação não é relevanta para iniciar os testes à tabela | J10: 45510 | K10: 45624
A11: =E11&F11 -> ENERGY_CERTIFICATE_EST_INPUTPROPERTY_CONTRACT_ID | B11: Pilar III | C11: Bens Imóveis - Input | D11: 2. Campo | E11: ENERGY_CERTIFICATE_EST_INPUT | F11: PROPERTY_CONTRACT_ID | G11: 6. Em implementação (re-especificação) | H11: 6. Em implementação (re-especificação) | I11: Apesar da data de correção ser 28/11 a data que importa é 24/10, uma vez que a última implementação não é relevanta para iniciar os testes à tabela | J11: 45510 | K11: 45624
A12: =E12&F12 -> ENERGY_CERTIFICATE_EST_INPUTPROPERTY_REFERENCE_CODE | B12: Pilar III | C12: Bens Imóveis - Input | D12: 2. Campo | E12: ENERGY_CERTIFICATE_EST_INPUT | F12: PROPERTY_REFERENCE_CODE | G12: 6. Em implementação (re-especificação) | H12: 6. Em implementação (re-especificação) | I12: Apesar da data de correção ser 28/11 a data que importa é 24/10, uma vez que a última implementação não é relevanta para iniciar os testes à tabela | J12: 45510 | K12: 45624
A13: =E13&F13 -> ENERGY_CERTIFICATE_EST_INPUTDATA_EXTRACTION_DATE | B13: Pilar III | C13: Bens Imóveis - Input | D13: 2. Campo | E13: ENERGY_CERTIFICATE_EST_INPUT | F13: DATA_EXTRACTION_DATE | G13: 6. Em implementação (re-especificação) | H13: 6. Em implementação (re-especificação) | I13: Apesar da data de correção ser 28/11 a data que importa é 24/10, uma vez que a última implementação não é relevanta para iniciar os testes à tabela | J13: 45510 | K13: 45624
A14: =E14&F14 -> ENERGY_CERTIFICATE_EST_INPUTEPC | B14: Pilar III | C14: Bens Imóveis - Input | D14: 2. Campo | E14: ENERGY_CERTIFICATE_EST_INPUT | F14: EPC | G14: 6. Em implementação (re-especificação) | H14: 6. Em implementação (re-especificação) | I14: Apesar da data de correção ser 28/11 a data que importa é 24/10, uma vez que a última implementação não é relevanta para iniciar os testes à tabela | J14: 45510 | K14: 45624
A15: =E15&F15 -> ENERGY_CERTIFICATE_EST_INPUTDATA_PROVIDER | B15: Pilar III | C15: Bens Imóveis - Input | D15: 2. Campo | E15: ENERGY_CERTIFICATE_EST_INPUT | F15: DATA_PROVIDER | G15: 6. Em implementação (re-especificação) | H15: 6. Em implementação (re-especificação) | I15: Apesar da data de correção ser 28/11 a data que importa é 24/10, uma vez que a última implementação não é relevanta para iniciar os testes à tabela | J15: 45510 | K15: 45624
A16: =E16&F16 -> ENERGY_CERTIFICATE_EST_INPUTACTUAL_VALUE_IND | B16: Pilar III | C16: Bens Imóveis - Input | D16: 2. Campo | E16: ENERGY_CERTIFICATE_EST_INPUT | F16: ACTUAL_VALUE_IND | G16: 6. Em implementação (re-especificação) | H16: 6. Em implementação (re-especificação) | I16: Apesar da data de correção ser 28/11 a data que importa é 24/10, uma vez que a última implementação não é relevanta para iniciar os testes à tabela | J16: 45510 | K16: 45624
A17: =E17&F17 -> ENERGY_CERTIFICATE_EST_INPUTQUALITY_SCORE | B17: Pilar III | C17: Bens Imóveis - Input | D17: 2. Campo | E17: ENERGY_CERTIFICATE_EST_INPUT | F17: QUALITY_SCORE | G17: 6. Em implementação (re-especificação) | H17: 6. Em implementação (re-especificação) | I17: Apesar da data de correção ser 28/11 a data que importa é 24/10, uma vez que a última implementação não é relevanta para iniciar os testes à tabela | J17: 45510 | K17: 45624
A18: =E18&F18 -> ENERGY_CERTIFICATE_EST_INPUTENERGY_CONSUMPTION_VALUE_YEAR | B18: Pilar III | C18: Bens Imóveis - Input | D18: 2. Campo | E18: ENERGY_CERTIFICATE_EST_INPUT | F18: ENERGY_CONSUMPTION_VALUE_YEAR | G18: 6. Em implementação (re-especificação) | H18: 6. Em implementação (re-especificação) | I18: Apesar da data de correção ser 28/11 a data que importa é 24/10, uma vez que a última implementação não é relevanta para iniciar os testes à tabela | J18: 45510 | K18: 45624
A19: =E19&F19 -> ENERGY_CERTIFICATE_EST_INPUTCARBON_EMISSION_VALUE_YEAR | B19: Pilar III | C19: Bens Imóveis - Input | D19: 2. Campo | E19: ENERGY_CERTIFICATE_EST_INPUT | F19: CARBON_EMISSION_VALUE_YEAR | G19: 6. Em implementação (re-especificação) | H19: 6. Em implementação (re-especificação) | I19: Apesar da data de correção ser 28/11 a data que importa é 24/10, uma vez que a última implementação não é relevanta para iniciar os testes à tabela | J19: 45510 | K19: 45624
A20: =E20&F20 -> PROCESSn.a. | B20: Pilar III | C20: Bens Imóveis - Output | D20: 1. Universo | E20: PROCESS | F20: n.a. | G20: 1. Concluído | H20: 1. Concluído
A21: =E21&F21 -> PROCESSPROCESS_BANK_ID | B21: Pilar III | C21: Bens Imóveis - Output | D21: 2. Campo | E21: PROCESS | F21: PROCESS_BANK_ID | G21: 1. Concluído | H21: 1. Concluído | I21: 26/07/2024: Conclusão de testes ao universo MUG e GP. Adjudicados fora de âmbito deste projeto.
A22: =E22&F22 -> PROCESSPROCESS_BRANCH_CODE | B22: Pilar III | C22: Bens Imóveis - Output | D22: 2. Campo | E22: PROCESS | F22: PROCESS_BRANCH_CODE | G22: 1. Concluído | H22: 1. Concluído | I22: 26/07/2024: Conclusão de testes ao universo MUG e GP. Adjudicados fora de âmbito deste projeto.
A23: =E23&F23 -> PROCESSPROCESS_ACCOUNT_ID | B23: Pilar III | C23: Bens Imóveis - Output | D23: 2. Campo | E23: PROCESS | F23: PROCESS_ACCOUNT_ID | G23: 1. Concluído | H23: 1. Concluído | I23: 26/07/2024: Conclusão de testes ao universo MUG e GP. Adjudicados fora de âmbito deste projeto.
A24: =E24&F24 -> PROCESScod_estd_prcs | B24: Pilar III | C24: Bens Imóveis - Output | D24: 2. Campo | E24: PROCESS | F24: cod_estd_prcs | G24: 0. Cancelado | H24: 0. Cancelado | I24: 19/07/2024: Campo eliminado do Modelo para garantir coerência com MUG
A25: =E25&F25 -> PROCESSGUARANTEE_CODE | B25: Pilar III | C25: Bens Imóveis - Output | D25: 2. Campo | E25: PROCESS | F25: GUARANTEE_CODE | G25: 1. Concluído | H25: 1. Concluído
A26: =E26&F26 -> PROCESSCURRENCY_CODE | B26: Pilar III | C26: Bens Imóveis - Output | D26: 2. Campo | E26: PROCESS | F26: CURRENCY_CODE | G26: 1. Concluído | H26: 1. Concluído | J26: 45512 | K26: 45526
A27: =E27&F27 -> PROCESSPROCESS_CAMPAIGN_CODE | B27: Pilar III | C27: Bens Imóveis - Output | D27: 2. Campo | E27: PROCESS | F27: PROCESS_CAMPAIGN_CODE | G27: 1. Concluído | H27: 1. Concluído
A28: =E28&F28 -> PROCESSPROCESS_PRODUCT_ID | B28: Pilar III | C28: Bens Imóveis - Output | D28: 2. Campo | E28: PROCESS | F28: PROCESS_PRODUCT_ID | G28: 1. Concluído | H28: 1. Concluído
A29: =E29&F29 -> PROCESSPROCESS_SUBPRODUCT_ID | B29: Pilar III | C29: Bens Imóveis - Output | D29: 2. Campo | E29: PROCESS | F29: PROCESS_SUBPRODUCT_ID | G29: 1. Concluído | H29: 1. Concluído
A30: =E30&F30 -> PROCESSGUARANTEE_TYPE_CODE | B30: Pilar III | C30: Bens Imóveis - Output | D30: 2. Campo | E30: PROCESS | F30: GUARANTEE_TYPE_CODE | G30: 1. Concluído | H30: 1. Concluído
A31: =E31&F31 -> PROCESSPROCESS_REFERENCE_CODE | B31: Pilar III | C31: Bens Imóveis - Output | D31: 2. Campo | E31: PROCESS | F31: PROCESS_REFERENCE_CODE | G31: 1. Concluído | H31: 1. Concluído
A32: =E32&F32 -> PROCESSPROCESS_START_DATE | B32: Pilar III | C32: Bens Imóveis - Output | D32: 2. Campo | E32: PROCESS | F32: PROCESS_START_DATE | G32: 1. Concluído | H32: 1. Concluído
A33: =E33&F33 -> PROCESSPROCESS_DUE_DATE | B33: Pilar III | C33: Bens Imóveis - Output | D33: 2. Campo | E33: PROCESS | F33: PROCESS_DUE_DATE | G33: 1. Concluído | H33: 1. Concluído
A34: =E34&F34 -> PROCESSmontante_eur | B34: Pilar III | C34: Bens Imóveis - Output | D34: 2. Campo | E34: PROCESS | F34: montante_eur | G34: 0. Cancelado | H34: 0. Cancelado | I34: 19/07/2024: Campo eliminado do Modelo para garantir coerência com MUG
A35: =E35&F35 -> PROCESSmontante_org | B35: Pilar III | C35: Bens Imóveis - Output | D35: 2. Campo | E35: PROCESS | F35: montante_org | G35: 0. Cancelado | H35: 0. Cancelado | I35: 19/07/2024: Campo eliminado do Modelo para garantir coerência com MUG
A36: =E36&F36 -> PROCESSorigem | B36: Pilar III | C36: Bens Imóveis - Output | D36: 2. Campo | E36: PROCESS | F36: origem | G36: 0. Cancelado | H36: 0. Cancelado | I36: 08/08/2024: Campo eliminado de modo a garantir a coerência com o atualmente realizado no Modelo Único de Garantias.
A37: =E37&F37 -> PROCESSDATA_DATE_PART | B37: Pilar III | C37: Bens Imóveis - Output | D37: 2. Campo | E37: PROCESS | F37: DATA_DATE_PART | G37: 1. Concluído | H37: 1. Concluído
A38: =E38&F38 -> RESPONSIBILITY_PROCESS_RELn.a. | B38: Pilar III | C38: Bens Imóveis - Output | D38: 1. Universo | E38: RESPONSIBILITY_PROCESS_REL | F38: n.a. | G38: 1. Concluído | H38: 1. Concluído
A39: =E39&F39 -> RESPONSIBILITY_PROCESS_RELPROCESS_BANK_ID | B39: Pilar III | C39: Bens Imóveis - Output | D39: 2. Campo | E39: RESPONSIBILITY_PROCESS_REL | F39: PROCESS_BANK_ID | G39: 1. Concluído | H39: 1. Concluído | I39: 26/07/2024: Conclusão de testes ao universo MUG e GP. Adjudicados fora de âmbito deste projeto.
A40: =E40&F40 -> RESPONSIBILITY_PROCESS_RELBANK_ID | B40: Pilar III | C40: Bens Imóveis - Output | D40: 2. Campo | E40: RESPONSIBILITY_PROCESS_REL | F40: BANK_ID | G40: 1. Concluído | H40: 1. Concluído | I40: 26/07/2024: Conclusão de testes ao universo MUG e GP. Adjudicados fora de âmbito deste projeto.
A41: =E41&F41 -> RESPONSIBILITY_PROCESS_RELPROCESS_BRANCH_CODE | B41: Pilar III | C41: Bens Imóveis - Output | D41: 2. Campo | E41: RESPONSIBILITY_PROCESS_REL | F41: PROCESS_BRANCH_CODE | G41: 1. Concluído | H41: 1. Concluído | I41: 26/07/2024: Conclusão de testes ao universo MUG e GP. Adjudicados fora de âmbito deste projeto.
A42: =E42&F42 -> RESPONSIBILITY_PROCESS_RELBRANCH_CODE | B42: Pilar III | C42: Bens Imóveis - Output | D42: 2. Campo | E42: RESPONSIBILITY_PROCESS_REL | F42: BRANCH_CODE | G42: 1. Concluído | H42: 1. Concluído | I42: 26/07/2024: Conclusão de testes ao universo MUG e GP. Adjudicados fora de âmbito deste projeto.
A43: =E43&F43 -> RESPONSIBILITY_PROCESS_RELCONTRACT_ID | B43: Pilar III | C43: Bens Imóveis - Output | D43: 2. Campo | E43: RESPONSIBILITY_PROCESS_REL | F43: CONTRACT_ID | G43: 1. Concluído | H43: 1. Concluído | I43: 26/07/2024: Conclusão de testes ao universo MUG e GP. Adjudicados fora de âmbito deste projeto.
A44: =E44&F44 -> RESPONSIBILITY_PROCESS_RELPROCESS_ACCOUNT_ID | B44: Pilar III | C44: Bens Imóveis - Output | D44: 2. Campo | E44: RESPONSIBILITY_PROCESS_REL | F44: PROCESS_ACCOUNT_ID | G44: 1. Concluído | H44: 1. Concluído | I44: 26/07/2024: Conclusão de testes ao universo MUG e GP. Adjudicados fora de âmbito deste projeto.
A45: =E45&F45 -> RESPONSIBILITY_PROCESS_RELREFERENCE_CODE | B45: Pilar III | C45: Bens Imóveis - Output | D45: 2. Campo | E45: RESPONSIBILITY_PROCESS_REL | F45: REFERENCE_CODE | G45: 1. Concluído | H45: 1. Concluído | I45: 26/07/2024: Conclusão de testes ao universo MUG e GP. Adjudicados fora de âmbito deste projeto.
A46: =E46&F46 -> RESPONSIBILITY_PROCESS_RELPURPOSE_CODE | B46: Pilar III | C46: Bens Imóveis - Output | D46: 2. Campo | E46: RESPONSIBILITY_PROCESS_REL | F46: PURPOSE_CODE | G46: 1. Concluído | H46: 1. Concluído
A47: =E47&F47 -> RESPONSIBILITY_PROCESS_RELINDIVIDUAL_OCCUPATION_CODE | B47: Pilar III | C47: Bens Imóveis - Output | D47: 2. Campo | E47: RESPONSIBILITY_PROCESS_REL | F47: INDIVIDUAL_OCCUPATION_CODE | G47: 1. Concluído | H47: 1. Concluído
A48: =E48&F48 -> RESPONSIBILITY_PROCESS_RELPRODUCT_ID | B48: Pilar III | C48: Bens Imóveis - Output | D48: 2. Campo | E48: RESPONSIBILITY_PROCESS_REL | F48: PRODUCT_ID | G48: 1. Concluído | H48: 1. Concluído
A49: =E49&F49 -> RESPONSIBILITY_PROCESS_RELcod_sit | B49: Pilar III | C49: Bens Imóveis - Output | D49: 2. Campo | E49: RESPONSIBILITY_PROCESS_REL | F49: cod_sit | G49: 0. Cancelado | H49: 0. Cancelado | I49: 19/07/2024: Campo eliminado do Modelo para garantir coerência com MUG
A50: =E50&F50 -> RESPONSIBILITY_PROCESS_RELSUBPRODUCT_ID | B50: Pilar III | C50: Bens Imóveis - Output | D50: 2. Campo | E50: RESPONSIBILITY_PROCESS_REL | F50: SUBPRODUCT_ID | G50: 1. Concluído | H50: 1. Concluído
A51: =E51&F51 -> RESPONSIBILITY_PROCESS_RELPROCESS_REFERENCE_CODE | B51: Pilar III | C51: Bens Imóveis - Output | D51: 2. Campo | E51: RESPONSIBILITY_PROCESS_REL | F51: PROCESS_REFERENCE_CODE | G51: 1. Concluído | H51: 1. Concluído
A52: =E52&F52 -> RESPONSIBILITY_PROCESS_RELEFFECTIVE_RELATION_END_DATE | B52: Pilar III | C52: Bens Imóveis - Output | D52: 2. Campo | E52: RESPONSIBILITY_PROCESS_REL | F52: EFFECTIVE_RELATION_END_DATE | G52: 1. Concluído | H52: 1. Concluído
A53: =E53&F53 -> RESPONSIBILITY_PROCESS_RELPROCESS_START_DATE | B53: Pilar III | C53: Bens Imóveis - Output | D53: 2. Campo | E53: RESPONSIBILITY_PROCESS_REL | F53: PROCESS_START_DATE | G53: 1. Concluído | H53: 1. Concluído
A54: =E54&F54 -> RESPONSIBILITY_PROCESS_RELPROCESS_DUE_DATE | B54: Pilar III | C54: Bens Imóveis - Output | D54: 2. Campo | E54: RESPONSIBILITY_PROCESS_REL | F54: PROCESS_DUE_DATE | G54: 1. Concluído | H54: 1. Concluído
A55: =E55&F55 -> RESPONSIBILITY_PROCESS_RELidetgar | B55: Pilar III | C55: Bens Imóveis - Output | D55: 2. Campo | E55: RESPONSIBILITY_PROCESS_REL | F55: idetgar | G55: 0. Cancelado | H55: 0. Cancelado | I55: 19/07/2024: Campo eliminado do Modelo para garantir coerência com MUG
A56: =E56&F56 -> RESPONSIBILITY_PROCESS_RELnum_prop | B56: Pilar III | C56: Bens Imóveis - Output | D56: 2. Campo | E56: RESPONSIBILITY_PROCESS_REL | F56: num_prop | G56: 0. Cancelado | H56: 0. Cancelado | I56: 19/07/2024: Campo eliminado do Modelo para garantir coerência com MUG
A57: =E57&F57 -> RESPONSIBILITY_PROCESS_RELSOURCE_CODE | B57: Pilar III | C57: Bens Imóveis - Output | D57: 2. Campo | E57: RESPONSIBILITY_PROCESS_REL | F57: SOURCE_CODE | G57: 1. Concluído | H57: 1. Concluído
A58: =E58&F58 -> RESPONSIBILITY_PROCESS_RELDATA_DATE_PART | B58: Pilar III | C58: Bens Imóveis - Output | D58: 2. Campo | E58: RESPONSIBILITY_PROCESS_REL | F58: DATA_DATE_PART | G58: 1. Concluído | H58: 1. Concluído
A59: =E59&F59 -> PROCESS_PROPERTY_RELn.a. | B59: Pilar III | C59: Bens Imóveis - Output | D59: 1. Universo | E59: PROCESS_PROPERTY_REL | F59: n.a. | G59: 1. Concluído | H59: 1. Concluído
A60: =E60&F60 -> PROCESS_PROPERTY_RELPROPERTY_BANK_ID | B60: Pilar III | C60: Bens Imóveis - Output | D60: 2. Campo | E60: PROCESS_PROPERTY_REL | F60: PROPERTY_BANK_ID | G60: 1. Concluído | H60: 1. Concluído
A61: =E61&F61 -> PROCESS_PROPERTY_RELPROCESS_BANK_ID | B61: Pilar III | C61: Bens Imóveis - Output | D61: 2. Campo | E61: PROCESS_PROPERTY_REL | F61: PROCESS_BANK_ID | G61: 1. Concluído | H61: 1. Concluído | I61: 26/07/2024: Conclusão de testes ao universo MUG e GP. Adjudicados fora de âmbito deste projeto.
A62: =E62&F62 -> PROCESS_PROPERTY_RELPROPERTY_BRANCH_CODE | B62: Pilar III | C62: Bens Imóveis - Output | D62: 2. Campo | E62: PROCESS_PROPERTY_REL | F62: PROPERTY_BRANCH_CODE | G62: 1. Concluído | H62: 1. Concluído | I62: 26/07/2024: Conclusão de testes ao universo MUG e GP. Adjudicados fora de âmbito deste projeto.
A63: =E63&F63 -> PROCESS_PROPERTY_RELPROCESS_BRANCH_CODE | B63: Pilar III | C63: Bens Imóveis - Output | D63: 2. Campo | E63: PROCESS_PROPERTY_REL | F63: PROCESS_BRANCH_CODE | G63: 1. Concluído | H63: 1. Concluído | I63: 26/07/2024: Conclusão de testes ao universo MUG e GP. Adjudicados fora de âmbito deste projeto.
A64: =E64&F64 -> PROCESS_PROPERTY_RELPROPERTY_CONTRACT_ID | B64: Pilar III | C64: Bens Imóveis - Output | D64: 2. Campo | E64: PROCESS_PROPERTY_REL | F64: PROPERTY_CONTRACT_ID | G64: 1. Concluído | H64: 1. Concluído | I64: 26/07/2024: Conclusão de testes ao universo MUG e GP. Adjudicados fora de âmbito deste projeto.
A65: =E65&F65 -> PROCESS_PROPERTY_RELPROCESS_ACCOUNT_ID | B65: Pilar III | C65: Bens Imóveis - Output | D65: 2. Campo | E65: PROCESS_PROPERTY_REL | F65: PROCESS_ACCOUNT_ID | G65: 1. Concluído | H65: 1. Concluído | I65: 26/07/2024: Conclusão de testes ao universo MUG e GP. Adjudicados fora de âmbito deste projeto.
A66: =E66&F66 -> PROCESS_PROPERTY_RELPROPERTY_REFERENCE_CODE | B66: Pilar III | C66: Bens Imóveis - Output | D66: 2. Campo | E66: PROCESS_PROPERTY_REL | F66: PROPERTY_REFERENCE_CODE | G66: 1. Concluído | H66: 1. Concluído
A67: =E67&F67 -> PROCESS_PROPERTY_RELPROCESS_REFERENCE_CODE | B67: Pilar III | C67: Bens Imóveis - Output | D67: 2. Campo | E67: PROCESS_PROPERTY_REL | F67: PROCESS_REFERENCE_CODE | G67: 1. Concluído | H67: 1. Concluído
A68: =E68&F68 -> PROCESS_PROPERTY_RELdata_assc | B68: Pilar III | C68: Bens Imóveis - Output | D68: 2. Campo | E68: PROCESS_PROPERTY_REL | F68: data_assc | G68: 0. Cancelado | H68: 0. Cancelado | I68: 19/07/2024: Campo eliminado do Modelo para garantir coerência com MUG
A69: =E69&F69 -> PROCESS_PROPERTY_RELSEIZED_PROPERTY_IND | B69: Pilar III | C69: Bens Imóveis - Output | D69: 2. Campo | E69: PROCESS_PROPERTY_REL | F69: SEIZED_PROPERTY_IND | G69: 1. Concluído | H69: 1. Concluído
A70: =E70&F70 -> PROCESS_PROPERTY_RELCOLLATERAL_PROPERTY_IND | B70: Pilar III | C70: Bens Imóveis - Output | D70: 2. Campo | E70: PROCESS_PROPERTY_REL | F70: COLLATERAL_PROPERTY_IND | G70: 1. Concluído | H70: 1. Concluído
A71: =E71&F71 -> PROCESS_PROPERTY_RELFINANCED_PROPERTY_IND | B71: Pilar III | C71: Bens Imóveis - Output | D71: 2. Campo | E71: PROCESS_PROPERTY_REL | F71: FINANCED_PROPERTY_IND | G71: 1. Concluído | H71: 1. Concluído
A72: =E72&F72 -> PROCESS_PROPERTY_RELOWNED_PROPERTY_IND | B72: Pilar III | C72: Bens Imóveis - Output | D72: 2. Campo | E72: PROCESS_PROPERTY_REL | F72: OWNED_PROPERTY_IND | G72: 1. Concluído | H72: 1. Concluído
A73: =E73&F73 -> PROCESS_PROPERTY_RELSOURCE_CODE | B73: Pilar III | C73: Bens Imóveis - Output | D73: 2. Campo | E73: PROCESS_PROPERTY_REL | F73: SOURCE_CODE | G73: 1. Concluído | H73: 1. Concluído
A74: =E74&F74 -> PROCESS_PROPERTY_RELDATA_DATE_PART | B74: Pilar III | C74: Bens Imóveis - Output | D74: 2. Campo | E74: PROCESS_PROPERTY_REL | F74: DATA_DATE_PART | G74: 1. Concluído | H74: 1. Concluído
A75: =E75&F75 -> PROPERTYn.a. | B75: Pilar III | C75: Bens Imóveis - Output | D75: 1. Universo | E75: PROPERTY | F75: n.a. | G75: 1. Concluído | H75: 1. Concluído
A76: =E76&F76 -> PROPERTYCONSTRUCTION_YEAR | B76: Pilar III | C76: Bens Imóveis - Output | D76: 2. Campo | E76: PROPERTY | F76: CONSTRUCTION_YEAR | G76: 1. Concluído | H76: 1. Concluído
A77: =E77&F77 -> PROPERTYNET_FLOOR_AREA | B77: Pilar III | C77: Bens Imóveis - Output | D77: 2. Campo | E77: PROPERTY | F77: NET_FLOOR_AREA | G77: 1. Concluído | H77: 1. Concluído
A78: =E78&F78 -> PROPERTYPROPERTY_BANK_ID | B78: Pilar III | C78: Bens Imóveis - Output | D78: 2. Campo | E78: PROPERTY | F78: PROPERTY_BANK_ID | G78: 1. Concluído | H78: 1. Concluído
A79: =E79&F79 -> PROPERTYPROPERTY_BRANCH_CODE | B79: Pilar III | C79: Bens Imóveis - Output | D79: 2. Campo | E79: PROPERTY | F79: PROPERTY_BRANCH_CODE | G79: 1. Concluído | H79: 1. Concluído
A80: =E80&F80 -> PROPERTYPROPERTY_CONTRACT_ID | B80: Pilar III | C80: Bens Imóveis - Output | D80: 2. Campo | E80: PROPERTY | F80: PROPERTY_CONTRACT_ID | G80: 1. Concluído | H80: 1. Concluído
... A83: =E83&F83 -> PROPERTYAPPRAISAL_CODE | B83: Pilar III | C83: Bens Imóveis - Output | D83: 2. Campo | E83: PROPERTY | F83: APPRAISAL_CODE | G83: 1. Concluído | H83: 1. Concluído
A84: =E84&F84 -> PROPERTYcod_bem | B84: Pilar III | C84: Bens Imóveis - Output | D84: 2. Campo | E84: PROPERTY | F84: cod_bem | G84: 0. Cancelado | H84: 0. Cancelado | I84: 19/07/2024: Campo eliminado do Modelo para garantir coerência com MUG
A85: =E85&F85 -> PROPERTYDISTRICT_MUNICIP_PARISH_CODE | B85: Pilar III | C85: Bens Imóveis - Output | D85: 2. Campo | E85: PROPERTY | F85: DISTRICT_MUNICIP_PARISH_CODE | G85: 1. Concluído | H85: 1. Concluído
A86: =E86&F86 -> PROPERTYPROPERTY_PURPOSE_CODE | B86: Pilar III | C86: Bens Imóveis - Output | D86: 2. Campo | E86: PROPERTY | F86: PROPERTY_PURPOSE_CODE | G86: 1. Concluído | H86: 1. Concluído
A87: =E87&F87 -> PROPERTYPROPERTY_LIFETIME_CODE | B87: Pilar III | C87: Bens Imóveis - Output | D87: 2. Campo | E87: PROPERTY | F87: PROPERTY_LIFETIME_CODE | G87: 1. Concluído | H87: 1. Concluído
A88: =E88&F88 -> PROPERTYADDRESS_CODE | B88: Pilar III | C88: Bens Imóveis - Output | D88: 2. Campo | E88: PROPERTY | F88: ADDRESS_CODE | G88: 1. Concluído | H88: 1. Concluído
A89: =E89&F89 -> PROPERTYCOUNTRY_CODE | B89: Pilar III | C89: Bens Imóveis - Output | D89: 2. Campo | E89: PROPERTY | F89: COUNTRY_CODE | G89: 1. Concluído | H89: 1. Concluído
A90: =E90&F90 -> PROPERTYPOSTAL_CODE | B90: Pilar III | C90: Bens Imóveis - Output | D90: 2. Campo | E90: PROPERTY | F90: POSTAL_CODE | G90: 1. Concluído | H90: 1. Concluído
A91: =E91&F91 -> PROPERTYPROPERTY_TYPE_CODE | B91: Pilar III | C91: Bens Imóveis - Output | D91: 2. Campo | E91: PROPERTY | F91: PROPERTY_TYPE_CODE | G91: 1. Concluído | H91: 1. Concluído
A92: =E92&F92 -> PROPERTYLAST_APPRAISAL_DATE | B92: Pilar III | C92: Bens Imóveis - Output | D92: 2. Campo | E92: PROPERTY | F92: LAST_APPRAISAL_DATE | G92: 1. Concluído | H92: 1. Concluído
A93: =E93&F93 -> PROPERTYUSAGE_PERMIT_START_DATE | B93: Pilar III | C93: Bens Imóveis - Output | D93: 2. Campo | E93: PROPERTY | F93: USAGE_PERMIT_START_DATE | G93: 1. Concluído | H93: 1. Concluído
A94: =E94&F94 -> PROPERTYCONSERVATORY_REG_FILE_ID | B94: Pilar III | C94: Bens Imóveis - Output | D94: 2. Campo | E94: PROPERTY | F94: CONSERVATORY_REG_FILE_ID | G94: 1. Concluído | H94: 1. Concluído
A95: =E95&F95 -> PROPERTYFLOOR_NUMBER | B95: Pilar III | C95: Bens Imóveis - Output | D95: 2. Campo | E95: PROPERTY | F95: FLOOR_NUMBER | G95: 1. Concluído | H95: 1. Concluído
A96: =E96&F96 -> PROPERTYLOCALITY | B96: Pilar III | C96: Bens Imóveis - Output | D96: 2. Campo | E96: PROPERTY | F96: LOCALITY | G96: 1. Concluído | H96: 1. Concluído
... A102: =E102&F102 -> PROPERTYPROPERTY_NUMBER | B102: Pilar III | C102: Bens Imóveis - Output | D102: 2. Campo | E102: PROPERTY | F102: PROPERTY_NUMBER | G102: 1. Concluído | H102: 1. Concluído
A103: =E103&F103 -> PROPERTYOrigem | B103: Pilar III | C103: Bens Imóveis - Output | D103: 2. Campo | E103: PROPERTY | F103: Origem | G103: 0. Cancelado | H103: 0. Cancelado | I103: 08/08/2024: Campo eliminado de modo a garantir a coerência com o atualmente realizado no Modelo Único de Garantias.
A104: =E104&F104 -> PROPERTYCURRENT_CONSTRUCTION_PCT | B104: Pilar III | C104: Bens Imóveis - Output | D104: 2. Campo | E104: PROPERTY | F104: CURRENT_CONSTRUCTION_PCT | G104: 1. Concluído | H104: 1. Concluído | I104: 22/07/2024: Entrega de campo para testes | J104: 45491 | K104: 45495 | L104: 45495
A105: =E105&F105 -> PROPERTYCONSTRUCTION_COMPLETED_PCT | B105: Pilar III | C105: Bens Imóveis - Output | D105: 2. Campo | E105: PROPERTY | F105: CONSTRUCTION_COMPLETED_PCT | G105: 1. Concluído | H105: 1. Concluído | I105: 22/07/2024: Entrega de campo para testes | J105: 45491 | K105: 45495 | L105: 45495
A106: =E106&F106 -> PROPERTYDATA_DATE_PART | B106: Pilar III | C106: Bens Imóveis - Output | D106: 2. Campo | E106: PROPERTY | F106: DATA_DATE_PART | G106: 1. Concluído | H106: 1. Concluído
A107: =E107&F107 -> PROPERTYURBANIZATION | B107: Pilar III | C107: Bens Imóveis - Output | D107: 2. Campo | E107: PROPERTY | F107: URBANIZATION | G107: 1. Concluído | H107: 1. Concluído
A108: =E108&F108 -> PROPERTY_ENERGY_CERTIFICATEn.a. | B108: Pilar III | C108: Bens Imóveis - Output | D108: 1. Universo | E108: PROPERTY_ENERGY_CERTIFICATE | F108: n.a. | G108: 1. Concluído | H108: 1. Concluído
A109: =E109&F109 -> PROPERTY_ENERGY_CERTIFICATEPROPERTY_BANK_ID | B109: Pilar III | C109: Bens Imóveis - Output | D109: 2. Campo | E109: PROPERTY_ENERGY_CERTIFICATE | F109: PROPERTY_BANK_ID | G109: 1. Concluído | H109: 1. Concluído
A110: =E110&F110 -> PROPERTY_ENERGY_CERTIFICATEPROPERTY_BRANCH_CODE | B110: Pilar III | C110: Bens Imóveis - Output | D110: 2. Campo | E110: PROPERTY_ENERGY_CERTIFICATE | F110: PROPERTY_BRANCH_CODE | G110: 1. Concluído | H110: 1. Concluído
A111: =E111&F111 -> PROPERTY_ENERGY_CERTIFICATEPROPERTY_CONTRACT_ID | B111: Pilar III | C111: Bens Imóveis - Output | D111: 2. Campo | E111: PROPERTY_ENERGY_CERTIFICATE | F111: PROPERTY_CONTRACT_ID | G111: 1. Concluído | H111: 1. Concluído
A112: =E112&F112 -> PROPERTY_ENERGY_CERTIFICATEPROPERTY_REFERENCE_CODE | B112: Pilar III | C112: Bens Imóveis - Output | D112: 2. Campo | E112: PROPERTY_ENERGY_CERTIFICATE | F112: PROPERTY_REFERENCE_CODE | G112: 1. Concluído | H112: 1. Concluído
...

Sheet Plano
Q6: Julho | AN6: Agosto | BJ6: Setembro | CE6: Outubro | DB6: Novembro | DW6: Dezembro
Q7: =Q8 -> 45474 | R7: =R8 -> 45475 | S7: =S8 -> 45476 | T7: =T8 -> 45477 | U7: =U8 -> 45478 | V7: =V8 -> 45481 | W7: =W8 -> 45482 | X7: =X8 -> 45483 | ... ER7: =ER8 -> 45657
B8: Âmbito | C8: Sub-âmbito | D8: Tipo de teste | E8: Tabela | F8: Campo | G8: Status | H8: Status2 | I8: Horas previstas | J8: Dias | K8: Horas efetivas | L8: Dias efetivos | M8: Status Estimado | N8: Status Real | O8: Desvios | P8: Observações | Q8: 45474 | R8: =WORKDAY(Q8,1) -> 45475 | S8: =WORKDAY(R8,1) -> 45476 | T8: =WORKDAY(S8,1) -> 45477 | U8: =WORKDAY(T8,1) -> 45478 | V8: =WORKDAY(U8,1) -> 45481 | W8: =WORKDAY(V8,1) -> 45482 | X8: =WORKDAY(W8,1) -> 45483 | Y8: =WORKDAY(X8,1) -> 45484 | ... ER8: =WORKDAY(EQ8,1) -> 45657
B9: 1. Assessment | I9: 160 | J9: 20 | K9: 160 | L9: 20 | M9: 1 | N9: 1 | O9: 0 | P9: N/A
B10: Pilar III | C10: Bens Imóveis | G10: 7. Por iniciar | I10: 40 | J10: 5 | M10: 1 | N10: 1 | O10: 0 | P10: N/A | AA10: 1 | AB10: 1 | AC10: 1 | AD10: 1 | AE10: 1
B11: Pilar III | C11: Modelo Verde | G11: 7. Por iniciar | I11: 80 | J11: 10 | M11: 1 | N11: 1 | O11: 0 | P11: N/A | V11: 2 | W11: 2 | X11: 2 | Y11: 2 | Z11: 2
B12: Pilar III | C12: LT Pilar III | G12: 7. Por iniciar | I12: 40 | J12: 5 | M12: 1 | N12: 1 | O12: 0 | P12: N/A | AF12: 1 | AG12: 1 | AH12: 1 | AI12: 1 | AJ12: 0.5 | AK12: 0.5
B14: 2. Re-especificação | I14: 120 | J14: 15 | K14: 105.6 | L14: 13.2 | M14: 0.86666667 | N14: 0.88 | O14: 0.013333333 | P14: N/A
B15: Pilar III | C15: Bens Imóveis | G15: 7. Por iniciar | I15: 40 | J15: 5 | M15: 1 | N15: 1 | O15: 0 | P15: N/A | AA15: 0.5 | AF15: 0.5 | AK15: 0.5 | AP15: 0.5 | AU15: 0.5 | AZ15: 0.5 | BE15: 0.5 | BJ15: 0.5 | BO15: 0.5 | BT15: 0.5
B16: Pilar III | C16: Modelo Verde | G16: 7. Por iniciar | I16: 40 | J16: 5 | M16: 1 | N16: 0.95 | O16: -0.05 | P16: - Pendência de atualização da tabela de parametrização (CdG) | AA16: 0.5 | AF16: 0.5 | AK16: 0.5 | AP16: 0.5 | AU16: 0.5 | AZ16: 0.5 | BE16: 0.5 | BJ16: 0.5 | BO16: 0.5 | BT16: 0.5
B17: Pilar III | C17: LT Pilar III | G17: 7. Por iniciar | I17: 40 | J17: 5 | M17: 0.6 | N17: 0.69 | O17: 0.09 | P17: Encontra-se em curso as re-especificações do Pilar III | BO17: 0.5 | BT17: 0.5 | BY17: 0.5 | CD17: 0.5 | CI17: 0.5 | CN17: 0.5 | CS17: 0.5 | CX17: 0.5 | DC17: 0.5
B19: 3. Testes / Re-testes | I19: #REF! | J19: #REF! | K19: #REF! | L19: #REF! | M19: 0.5 | N19: 0.58 | O19: 0.09 | P19: N/A
B20: Pilar III | C20: Bens Imóveis - Input | I20: #REF! | J20: #REF! | K20: #REF! | L20: #REF! | M20: 1 | N20: 0.33 | O20: -0.67 | P20: - Pendência de desenvolvimentos de IT: Tabela da Gloval | AB20: 0.5 | AC20: 0.5 | AG20: 0.5 | AN20: 0.5 | AO20: 0.5 | AP20: 0.5
A21: =E21&F21 | B21: Pilar III | C21: Bens Imóveis - Output | I21: #REF! | J21: #REF! | K21: #REF! | L21: #REF! | M21: 0.85 | N21: 0.71 | O21: -0.14 | P21: - Pendência de desenvolvimentos de IT: Tabela de certificados energéticos. | AK21: 1 | AL21: 1 | AM21: 1 | AN21: 1 | AQ21: 1 | AR21: 1 | AS21: 1 | AT21: 1 | AV21: 1 | AW21: 2 | AY21: 1 | BB21: 1 | BC21: 1 | BD21: 1 | BE21: 1 | BF21: 2 | BG21: 2 | BH21: 2 | BI21: 2 | BJ21: 0.5 | BK21: 2 | BL21: 2 | BM21: 2 | BN21: 2 | BO21: 0.5 | BP21: 2 | BQ21: 2 | BR21: 2 | BS21: 2 | BT21: 1.5 | BU21: 2 | BV21: 2 | BW21: 2 | BX21: 2 | BY21: 2 | BZ21: 2 | CA21: 2 | CB21: 2 | CC21: 2 | CD21: 2 | CE21: 2 | CF21: 2 | CG21: 2 | CH21: 2 | CI21: 2 | CJ21: 2 | CK21: 2 | CL21: 2 | CM21: 2 | CN21: 2 | CO21: 2 | CP21: 2 | CQ21: 2 | CR21: 2 | CS21: 2 | CT21: 2 | CU21: 2 | CV21: 2 | CW21: 1.5
A22: =E22&F22 | B22: Pilar III | C22: Modelo Verde - Input | I22: #REF! | J22: #REF! | K22: #REF! | L22: #REF! | M22: 1 | N22: 0.83 | O22: -0.17 | P22: - Pendência de desenvolvimentos de IT do input da MunichRe e dos desenvolvimentos das alterações na parametrização da marcação verde; - Pendente de envio de nova versão da tabela de parametrização com alteração da estrutura e mapeamento das categorias SFCIS. | AB22: 0.5 | AC22: 0.5 | AD22: 1 | AE22: 1 | AG22: 0.5 | AJ22: 0.5 | AK22: 0.5 | AL22: 2 | AM22: 2 | AN22: 1.5 | AO22: 1.5 | AP22: 1.5 | AQ22: 2 | AR22: 2 | AS22: 2 | AT22: 2 | AU22: 1 | AV22: 1
A23: =E23&F23 | B23: Pilar III | C23: Modelo Verde - Output | I23: #REF! | J23: #REF! | K23: #REF! | L23: #REF! | M23: 0.21 | N23: 0.19 | O23: -0.02 | P23: - Pendente de desenvolvimentos de IT | BU23: 1 | BV23: 1 | BW23: 1 | BX23: 1 | BY23: 0.5 | BZ23: 1 | CA23: 1 | CB23: 1 | CC23: 1 | CD23: 0.5 | CE23: 1 | CF23: 1 | CG23: 1 | CH23: 1 | CI23: 0.5 | CJ23: 1 | CK23: 1 | CL23: 1 | CM23: 1 | CN23: 0.5 | CO23: 1 | CP23: 1 | CQ23: 1 | CR23: 1 | CS23: 0.5 | CT23: 1 | CU23: 1 | CV23: 1 | CW23: 1 | CX23: 2 | CY23: 2 | CZ23: 2 | DA23: 2 | DB23: 2 | DC23: 2 | DD23: 2 | DE23: 2 | DF23: 2 | DG23: 2 | DH23: 2 | DI23: 2 | DJ23: 2 | DK23: 2 | DL23: 2 | DM23: 2 | DN23: 2 | DO23: 2 | DP23: 2 | DQ23: 2 | DR23: 2 | DS23: 2 | DT23: 2 | DU23: 2 | DV23: 2 | DW23: 2 | DX23: 2 | DY23: 2 | DZ23: 2 | EA23: 2 | EB23: 2 | EC23: 2 | ED23: 2 | EE23: 2 | EF23: 2 | EG23: 2 | EH23: 1.5
A24: =E24&F24 | B24: Pilar III | C24: LT Pilar III | I24: #REF! | J24: #REF! | K24: #REF! | L24: #REF! | M24: 0 | N24: 0.37 | O24: 0.37 | P24: - Já foram testados campos da LT Estrutural e uma tabela de parametrização. | CW24: 0.5 | CX24: 0.5 | CY24: 1 | CZ24: 1 | DA24: 1 | DB24: 1 | DC24: 0.5 | DD24: 1 | DE24: 1 | DF24: 1 | DG24: 1 | DH24: 1 | DI24: 1 | DJ24: 1 | DK24: 1 | DL24: 1 | DM24: 1 | DN24: 1 | DO24: 1 | DP24: 1 | DQ24: 1 | DS24: 1 | DT24: 1 | DU24: 1 | DV24: 1 | DW24: 1 | DX24: 1 | DY24: 1 | DZ24: 1 | EA24: 1 | EB24: 1 | EC24: 1 | ED24: 1 | EE24: 1 | EF24: 1 | EG24: 1 | EH24: 1.5 | EI24: 3 | EJ24: 3 | EK24: 3 | EL24: 3
AX25: x
B26: 4. Status Global | J26: #REF! | L26: #REF! | M26: 0.55 | N26: 0.64 | O26: 0.1 | P26: N/A
