Workbook

Sheet 0. Instruções
B6: 0. Instruções
B8: Projeto | D8: Testes MBDT
B9: Âmbito | D9: Análise dos campos da Loan Tape para o âmbito PM entre cd_loan_tapes_bce e bu_loantape_work.
B11: Para a validação dos campos da Loan Tape é necessário percorrer os seguintes steps:
B14: 1. Atualizar o script de simulação com o campo em análise.
B15: 1.1. Verificar a especificação do campo em análise. Se aplicável, verificar se é necessário reportar valor para ajustes.
B16: 1.2. Montar a simulação do campo tendo atenção aos seguintes pormenores:
B17: a) Não vamos fazer JOIN com a tabela de parametrização (LT803). Em alternativa, montamos um CASE WHEN ou importamos a parametrização.
B18: b) Para operações de ajustes verificar se o campo deve reportar valor.
B19: c) Se for necessário aplicar algum filtro (ou tratamento) que não está na especificação deixar um comentário no código.
B20: d) Garantir que não existem duplicados e deixar no código o número de registos de cada LEFT JOIN.
B21: 2. Executar no HUE (em HIVE) o CREATE TABLE do script de simulação.
B22: 3. Executar no HUE o script de controlo de universo.
B23: a) O número de registos em comum tem de ser igual ao número de registos do teste de coerência. Caso tenhamos registos que não são comuns é necessário ver exemplos para ver o que está a acontecer.
B24: 4. Verificar com IT o nome da tabela a testar e filtros. Caso seja necessário, atualizar as tabelas infra:
C26: Nome da Tabela | D26: Tabela Loan Tape PM | E26: Tabela Simulada | F26: Chave 1 | G26: Chave 2
C27: Univ_Oper | D27: lt001_univ_oper | E27: lt001_univ_oper | F27: concat(cempresa, cbalcao, cnumecta, zdeposit, ccontab_final_ifrs, ccontab_final_pcsb, ccontab_final_cargabal, ccontab_final) | G27: zcliente
C28: Entity | D28: lt003_entity | E28: lt003_entity | F28: entty_id
C29: Instrument | D29: lt002_instrument | E29: lt002_instrument | F29: instrmnt_id
C30: Protection | D30: lt004_protection | E30: lt004_protection | F30: prtctn_id
C31: INSTR_ENT | D31: lt005_instr_ent | E31: lt005_instr_ent | F31: instrmnt_id | G31: entty_id
C32: INSTR_PROT | D32: lt006_instr_prot | E32: lt006_instr_prot | F32: instrmnt_id | G32: prtctn_id
C34: Filtros
C35: Schema Loan Tape PM | D35: cd_loan_tapes_bce
C36: Schema Simulada | D36: bu_loantape_work
C37: nome_perimetro | D37: Individual Local
C38: segmento | D38: ESTR
C39: ambito Loan Tape | D39: PM
C40: ambito Simulação | D40: PM
C41: entidade | D41: 00100
C42: Filtro Loan Tape | D42: =+"ref_date='${ref_date}'"&" AND "&C37&"='"&D37&"' AND "&C38&"='"&D38&"' AND ambito='"&D40&"'"&" AND "&C41&"='"&D41&"'" -> ref_date='${ref_date}' AND nome_perimetro='Individual Local' AND segmento='ESTR' AND ambito='PM' AND entidade='00100'
C43: Filtro Simulação | D43: =+"ref_date='${ref_date}'"&" AND "&C37&"='"&D37&"' AND "&C38&"='"&D38&"' AND ambito='"&D39&"'"&" AND "&C41&"='"&D41&"'" -> ref_date='${ref_date}' AND nome_perimetro='Individual Local' AND segmento='ESTR' AND ambito='PM' AND entidade='00100'

Sheet 1. Status
H6: 1. Status dos Testes
H8: REF_DATE | I8: 45991
B9: Auxiliar
B10: Coerência | C10: Validade | D10: Caracteres Especiais | E10: Missings | F10: Not applicable | H10: Tabela | I10: Campo | J10: Testes Corridos (#) | K10: Número de Registos ID1. (#) | L10: ID Exec. 1. | M10: 1. Erros de Coerência (#) | N10: Comentário | O10: Status
A11: =+H11&I11&$I$8 -> UNIV_OPERmsaldo_final45991 | B11: {=+MAX(IF('3. Resultados'!A:A='1. Status'!A11&'1. Status'!$B$10,'3. Resultados'!K:K))} -> 0 | C11: {=+MAX(IF('3. Resultados'!A:A='1. Status'!A11&'1. Status'!$C$10,'3. Resultados'!K:K))} -> 0 | D11: {=+MAX(IF('3. Resultados'!A:A='1. Status'!A11&'1. Status'!$D$10,'3. Resultados'!K:K))} -> 0 | E11: {=+MAX(IF('3. Resultados'!A:A='1. Status'!A11&'1. Status'!$E$10,'3. Resultados'!K:K))} -> 0 | F11: {=+MAX(IF('3. Resultados'!A:A='1. Status'!A11&'1. Status'!$F$10,'3. Resultados'!K:K))} -> 0 | H11: UNIV_OPER | I11: msaldo_final | J11: =+COUNTIFS('3. Resultados'!C:C,'1. Status'!H11,'3. Resultados'!G:G,'1. Status'!I11) -> 1 | K11: =+IFERROR(VLOOKUP(CONCATENATE(A11,$B$10,B11),'3. Resultados'!B:J,8,FALSE),"-") -> - | L11: =+IFERROR(VLOOKUP(B11,'3. Resultados'!K:L,2,FALSE),"-") -> - | M11: =+IFERROR(VLOOKUP(CONCATENATE(A11,$B$10,B11),'3. Resultados'!B:J,9,FALSE),"-") -> - | O11: =+IF(J11=0,"Por iniciar",IF(OR(K11="-",M11="-"),"Em testes",IF(M11=0,"OK","NOK"))) -> Em testes
A12: =+H12&I12&$I$8 -> UNIV_OPERcarteira_contabilistica45991 | B12: {=+MAX(IF('3. Resultados'!A:A='1. Status'!A12&'1. Status'!$B$10,'3. Resultados'!K:K))} -> 0 | C12: {=+MAX(IF('3. Resultados'!A:A='1. Status'!A12&'1. Status'!$C$10,'3. Resultados'!K:K))} -> 0 | D12: {=+MAX(IF('3. Resultados'!A:A='1. Status'!A12&'1. Status'!$D$10,'3. Resultados'!K:K))} -> 0 | E12: {=+MAX(IF('3. Resultados'!A:A='1. Status'!A12&'1. Status'!$E$10,'3. Resultados'!K:K))} -> 0 | F12: {=+MAX(IF('3. Resultados'!A:A='1. Status'!A12&'1. Status'!$F$10,'3. Resultados'!K:K))} -> 0 | H12: UNIV_OPER | I12: carteira_contabilistica | J12: =+COUNTIFS('3. Resultados'!C:C,'1. Status'!H12,'3. Resultados'!G:G,'1. Status'!I12) -> 1 | K12: =+IFERROR(VLOOKUP(CONCATENATE(A12,$B$10,B12),'3. Resultados'!B:J,8,FALSE),"-") -> - | L12: =+IFERROR(VLOOKUP(B12,'3. Resultados'!K:L,2,FALSE),"-") -> - | M12: =+IFERROR(VLOOKUP(CONCATENATE(A12,$B$10,B12),'3. Resultados'!B:J,9,FALSE),"-") -> - | O12: =+IF(J12=0,"Por iniciar",IF(OR(K12="-",M12="-"),"Em testes",IF(M12=0,"OK","NOK"))) -> Em testes
A13: =+H13&I13&$I$8 -> UNIV_OPERinstrumento_financeiro45991 | B13: {=+MAX(IF('3. Resultados'!A:A='1. Status'!A13&'1. Status'!$B$10,'3. Resultados'!K:K))} -> 0 | C13: {=+MAX(IF('3. Resultados'!A:A='1. Status'!A13&'1. Status'!$C$10,'3. Resultados'!K:K))} -> 0 | D13: {=+MAX(IF('3. Resultados'!A:A='1. Status'!A13&'1. Status'!$D$10,'3. Resultados'!K:K))} -> 0 | E13: {=+MAX(IF('3. Resultados'!A:A='1. Status'!A13&'1. Status'!$E$10,'3. Resultados'!K:K))} -> 0 | F13: {=+MAX(IF('3. Resultados'!A:A='1. Status'!A13&'1. Status'!$F$10,'3. Resultados'!K:K))} -> 0 | H13: UNIV_OPER | I13: instrumento_financeiro | J13: =+COUNTIFS('3. Resultados'!C:C,'1. Status'!H13,'3. Resultados'!G:G,'1. Status'!I13) -> 1 | K13: =+IFERROR(VLOOKUP(CONCATENATE(A13,$B$10,B13),'3. Resultados'!B:J,8,FALSE),"-") -> - | L13: =+IFERROR(VLOOKUP(B13,'3. Resultados'!K:L,2,FALSE),"-") -> - | M13: =+IFERROR(VLOOKUP(CONCATENATE(A13,$B$10,B13),'3. Resultados'!B:J,9,FALSE),"-") -> - | O13: =+IF(J13=0,"Por iniciar",IF(OR(K13="-",M13="-"),"Em testes",IF(M13=0,"OK","NOK"))) -> Em testes
A14: =+H14&I14&$I$8 -> UNIV_OPERcontraparte45991 | B14: {=+MAX(IF('3. Resultados'!A:A='1. Status'!A14&'1. Status'!$B$10,'3. Resultados'!K:K))} -> 0 | C14: {=+MAX(IF('3. Resultados'!A:A='1. Status'!A14&'1. Status'!$C$10,'3. Resultados'!K:K))} -> 0 | D14: {=+MAX(IF('3. Resultados'!A:A='1. Status'!A14&'1. Status'!$D$10,'3. Resultados'!K:K))} -> 0 | E14: {=+MAX(IF('3. Resultados'!A:A='1. Status'!A14&'1. Status'!$E$10,'3. Resultados'!K:K))} -> 0 | F14: {=+MAX(IF('3. Resultados'!A:A='1. Status'!A14&'1. Status'!$F$10,'3. Resultados'!K:K))} -> 0 | H14: UNIV_OPER | I14: contraparte | J14: =+COUNTIFS('3. Resultados'!C:C,'1. Status'!H14,'3. Resultados'!G:G,'1. Status'!I14) -> 1 | K14: =+IFERROR(VLOOKUP(CONCATENATE(A14,$B$10,B14),'3. Resultados'!B:J,8,FALSE),"-") -> - | L14: =+IFERROR(VLOOKUP(B14,'3. Resultados'!K:L,2,FALSE),"-") -> - | M14: =+IFERROR(VLOOKUP(CONCATENATE(A14,$B$10,B14),'3. Resultados'!B:J,9,FALSE),"-") -> - | O14: =+IF(J14=0,"Por iniciar",IF(OR(K14="-",M14="-"),"Em testes",IF(M14=0,"OK","NOK"))) -> Em testes
A15: =+H15&I15&$I$8 -> UNIV_OPERcontraparte_i45991 | B15: {=+MAX(IF('3. Resultados'!A:A='1. Status'!A15&'1. Status'!$B$10,'3. Resultados'!K:K))} -> 0 | C15: {=+MAX(IF('3. Resultados'!A:A='1. Status'!A15&'1. Status'!$C$10,'3. Resultados'!K:K))} -> 0 | D15: {=+MAX(IF('3. Resultados'!A:A='1. Status'!A15&'1. Status'!$D$10,'3. Resultados'!K:K))} -> 0 | E15: {=+MAX(IF('3. Resultados'!A:A='1. Status'!A15&'1. Status'!$E$10,'3. Resultados'!K:K))} -> 0 | F15: {=+MAX(IF('3. Resultados'!A:A='1. Status'!A15&'1. Status'!$F$10,'3. Resultados'!K:K))} -> 0 | H15: UNIV_OPER | I15: contraparte_i | J15: =+COUNTIFS('3. Resultados'!C:C,'1. Status'!H15,'3. Resultados'!G:G,'1. Status'!I15) -> 1 | K15: =+IFERROR(VLOOKUP(CONCATENATE(A15,$B$10,B15),'3. Resultados'!B:J,8,FALSE),"-") -> - | L15: =+IFERROR(VLOOKUP(B15,'3. Resultados'!K:L,2,FALSE),"-") -> - | M15: =+IFERROR(VLOOKUP(CONCATENATE(A15,$B$10,B15),'3. Resultados'!B:J,9,FALSE),"-") -> - | O15: =+IF(J15=0,"Por iniciar",IF(OR(K15="-",M15="-"),"Em testes",IF(M15=0,"OK","NOK"))) -> Em testes
A16: =+H16&I16&$I$8 -> UNIV_OPERproduto45991 | B16: {=+MAX(IF('3. Resultados'!A:A='1. Status'!A16&'1. Status'!$B$10,'3. Resultados'!K:K))} -> 0 | C16: {=+MAX(IF('3. Resultados'!A:A='1. Status'!A16&'1. Status'!$C$10,'3. Resultados'!K:K))} -> 0 | D16: {=+MAX(IF('3. Resultados'!A:A='1. Status'!A16&'1. Status'!$D$10,'3. Resultados'!K:K))} -> 0 | E16: {=+MAX(IF('3. Resultados'!A:A='1. Status'!A16&'1. Status'!$E$10,'3. Resultados'!K:K))} -> 0 | F16: {=+MAX(IF('3. Resultados'!A:A='1. Status'!A16&'1. Status'!$F$10,'3. Resultados'!K:K))} -> 0 | H16: UNIV_OPER | I16: produto | J16: =+COUNTIFS('3. Resultados'!C:C,'1. Status'!H16,'3. Resultados'!G:G,'1. Status'!I16) -> 1 | K16: =+IFERROR(VLOOKUP(CONCATENATE(A16,$B$10,B16),'3. Resultados'!B:J,8,FALSE),"-") -> - | L16: =+IFERROR(VLOOKUP(B16,'3. Resultados'!K:L,2,FALSE),"-") -> - | M16: =+IFERROR(VLOOKUP(CONCATENATE(A16,$B$10,B16),'3. Resultados'!B:J,9,FALSE),"-") -> - | O16: =+IF(J16=0,"Por iniciar",IF(OR(K16="-",M16="-"),"Em testes",IF(M16=0,"OK","NOK"))) -> Em testes
A17: =+H17&I17&$I$8 -> UNIV_OPERtipo_conta45991 | B17: {=+MAX(IF('3. Resultados'!A:A='1. Status'!A17&'1. Status'!$B$10,'3. Resultados'!K:K))} -> 0 | C17: {=+MAX(IF('3. Resultados'!A:A='1. Status'!A17&'1. Status'!$C$10,'3. Resultados'!K:K))} -> 0 | D17: {=+MAX(IF('3. Resultados'!A:A='1. Status'!A17&'1. Status'!$D$10,'3. Resultados'!K:K))} -> 0 | E17: {=+MAX(IF('3. Resultados'!A:A='1. Status'!A17&'1. Status'!$E$10,'3. Resultados'!K:K))} -> 0 | F17: {=+MAX(IF('3. Resultados'!A:A='1. Status'!A17&'1. Status'!$F$10,'3. Resultados'!K:K))} -> 0 | H17: UNIV_OPER | I17: tipo_conta | J17: =+COUNTIFS('3. Resultados'!C:C,'1. Status'!H17,'3. Resultados'!G:G,'1. Status'!I17) -> 1 | K17: =+IFERROR(VLOOKUP(CONCATENATE(A17,$B$10,B17),'3. Resultados'!B:J,8,FALSE),"-") -> - | L17: =+IFERROR(VLOOKUP(B17,'3. Resultados'!K:L,2,FALSE),"-") -> - | M17: =+IFERROR(VLOOKUP(CONCATENATE(A17,$B$10,B17),'3. Resultados'!B:J,9,FALSE),"-") -> - | O17: =+IF(J17=0,"Por iniciar",IF(OR(K17="-",M17="-"),"Em testes",IF(M17=0,"OK","NOK"))) -> Em testes
A18: =+H18&I18&$I$8 -> UNIV_OPERbruto_imparidade45991 | B18: {=+MAX(IF('3. Resultados'!A:A='1. Status'!A18&'1. Status'!$B$10,'3. Resultados'!K:K))} -> 0 | C18: {=+MAX(IF('3. Resultados'!A:A='1. Status'!A18&'1. Status'!$C$10,'3. Resultados'!K:K))} -> 0 | D18: {=+MAX(IF('3. Resultados'!A:A='1. Status'!A18&'1. Status'!$D$10,'3. Resultados'!K:K))} -> 0 | E18: {=+MAX(IF('3. Resultados'!A:A='1. Status'!A18&'1. Status'!$E$10,'3. Resultados'!K:K))} -> 0 | F18: {=+MAX(IF('3. Resultados'!A:A='1. Status'!A18&'1. Status'!$F$10,'3. Resultados'!K:K))} -> 0 | H18: UNIV_OPER | I18: bruto_imparidade | J18: =+COUNTIFS('3. Resultados'!C:C,'1. Status'!H18,'3. Resultados'!G:G,'1. Status'!I18) -> 1 | K18: =+IFERROR(VLOOKUP(CONCATENATE(A18,$B$10,B18),'3. Resultados'!B:J,8,FALSE),"-") -> - | L18: =+IFERROR(VLOOKUP(B18,'3. Resultados'!K:L,2,FALSE),"-") -> - | M18: =+IFERROR(VLOOKUP(CONCATENATE(A18,$B$10,B18),'3. Resultados'!B:J,9,FALSE),"-") -> - | O18: =+IF(J18=0,"Por iniciar",IF(OR(K18="-",M18="-"),"Em testes",IF(M18=0,"OK","NOK"))) -> Em testes
A19: =+H19&I19&$I$8 -> UNIV_OPERcomposicao_valor45991 | B19: {=+MAX(IF('3. Resultados'!A:A='1. Status'!A19&'1. Status'!$B$10,'3. Resultados'!K:K))} -> 0 | C19: {=+MAX(IF('3. Resultados'!A:A='1. Status'!A19&'1. Status'!$C$10,'3. Resultados'!K:K))} -> 0 | D19: {=+MAX(IF('3. Resultados'!A:A='1. Status'!A19&'1. Status'!$D$10,'3. Resultados'!K:K))} -> 0 | E19: {=+MAX(IF('3. Resultados'!A:A='1. Status'!A19&'1. Status'!$E$10,'3. Resultados'!K:K))} -> 0 | F19: {=+MAX(IF('3. Resultados'!A:A='1. Status'!A19&'1. Status'!$F$10,'3. Resultados'!K:K))} -> 0 | H19: UNIV_OPER | I19: composicao_valor | J19: =+COUNTIFS('3. Resultados'!C:C,'1. Status'!H19,'3. Resultados'!G:G,'1. Status'!I19) -> 1 | K19: =+IFERROR(VLOOKUP(CONCATENATE(A19,$B$10,B19),'3. Resultados'!B:J,8,FALSE),"-") -> - | L19: =+IFERROR(VLOOKUP(B19,'3. Resultados'!K:L,2,FALSE),"-") -> - | M19: =+IFERROR(VLOOKUP(CONCATENATE(A19,$B$10,B19),'3. Resultados'!B:J,9,FALSE),"-") -> - | O19: =+IF(J19=0,"Por iniciar",IF(OR(K19="-",M19="-"),"Em testes",IF(M19=0,"OK","NOK"))) -> Em testes
A20: =+H20&I20&$I$8 -> UNIV_OPERcolateral45991 | B20: {=+MAX(IF('3. Resultados'!A:A='1. Status'!A20&'1. Status'!$B$10,'3. Resultados'!K:K))} -> 0 | C20: {=+MAX(IF('3. Resultados'!A:A='1. Status'!A20&'1. Status'!$C$10,'3. Resultados'!K:K))} -> 0 | D20: {=+MAX(IF('3. Resultados'!A:A='1. Status'!A20&'1. Status'!$D$10,'3. Resultados'!K:K))} -> 0 | E20: {=+MAX(IF('3. Resultados'!A:A='1. Status'!A20&'1. Status'!$E$10,'3. Resultados'!K:K))} -> 0 | F20: {=+MAX(IF('3. Resultados'!A:A='1. Status'!A20&'1. Status'!$F$10,'3. Resultados'!K:K))} -> 0 | H20: UNIV_OPER | I20: colateral | J20: =+COUNTIFS('3. Resultados'!C:C,'1. Status'!H20,'3. Resultados'!G:G,'1. Status'!I20) -> 1 | K20: =+IFERROR(VLOOKUP(CONCATENATE(A20,$B$10,B20),'3. Resultados'!B:J,8,FALSE),"-") -> - | L20: =+IFERROR(VLOOKUP(B20,'3. Resultados'!K:L,2,FALSE),"-") -> - | M20: =+IFERROR(VLOOKUP(CONCATENATE(A20,$B$10,B20),'3. Resultados'!B:J,9,FALSE),"-") -> - | O20: =+IF(J20=0,"Por iniciar",IF(OR(K20="-",M20="-"),"Em testes",IF(M20=0,"OK","NOK"))) -> Em testes
A21: =+H21&I21&$I$8 -> UNIV_OPERflag_poci45991 | B21: {=+MAX(IF('3. Resultados'!A:A='1. Status'!A21&'1. Status'!$B$10,'3. Resultados'!K:K))} -> 0 | C21: {=+MAX(IF('3. Resultados'!A:A='1. Status'!A21&'1. Status'!$C$10,'3. Resultados'!K:K))} -> 0 | D21: {=+MAX(IF('3. Resultados'!A:A='1. Status'!A21&'1. Status'!$D$10,'3. Resultados'!K:K))} -> 0 | E21: {=+MAX(IF('3. Resultados'!A:A='1. Status'!A21&'1. Status'!$E$10,'3. Resultados'!K:K))} -> 0 | F21: {=+MAX(IF('3. Resultados'!A:A='1. Status'!A21&'1. Status'!$F$10,'3. Resultados'!K:K))} -> 0 | H21: UNIV_OPER | I21: flag_poci | J21: =+COUNTIFS('3. Resultados'!C:C,'1. Status'!H21,'3. Resultados'!G:G,'1. Status'!I21) -> 1 | K21: =+IFERROR(VLOOKUP(CONCATENATE(A21,$B$10,B21),'3. Resultados'!B:J,8,FALSE),"-") -> - | L21: =+IFERROR(VLOOKUP(B21,'3. Resultados'!K:L,2,FALSE),"-") -> - | M21: =+IFERROR(VLOOKUP(CONCATENATE(A21,$B$10,B21),'3. Resultados'!B:J,9,FALSE),"-") -> - | O21: =+IF(J21=0,"Por iniciar",IF(OR(K21="-",M21="-"),"Em testes",IF(M21=0,"OK","NOK"))) -> Em testes
A22: =+H22&I22&$I$8 -> UNIV_OPERpurpose_code45991 | B22: {=+MAX(IF('3. Resultados'!A:A='1. Status'!A22&'1. Status'!$B$10,'3. Resultados'!K:K))} -> 0 | C22: {=+MAX(IF('3. Resultados'!A:A='1. Status'!A22&'1. Status'!$C$10,'3. Resultados'!K:K))} -> 0 | D22: {=+MAX(IF('3. Resultados'!A:A='1. Status'!A22&'1. Status'!$D$10,'3. Resultados'!K:K))} -> 0 | E22: {=+MAX(IF('3. Resultados'!A:A='1. Status'!A22&'1. Status'!$E$10,'3. Resultados'!K:K))} -> 0 | F22: {=+MAX(IF('3. Resultados'!A:A='1. Status'!A22&'1. Status'!$F$10,'3. Resultados'!K:K))} -> 0 | H22: UNIV_OPER | I22: purpose_code | J22: =+COUNTIFS('3. Resultados'!C:C,'1. Status'!H22,'3. Resultados'!G:G,'1. Status'!I22) -> 1 | K22: =+IFERROR(VLOOKUP(CONCATENATE(A22,$B$10,B22),'3. Resultados'!B:J,8,FALSE),"-") -> - | L22: =+IFERROR(VLOOKUP(B22,'3. Resultados'!K:L,2,FALSE),"-") -> - | M22: =+IFERROR(VLOOKUP(CONCATENATE(A22,$B$10,B22),'3. Resultados'!B:J,9,FALSE),"-") -> - | O22: =+IF(J22=0,"Por iniciar",IF(OR(K22="-",M22="-"),"Em testes",IF(M22=0,"OK","NOK"))) -> Em testes
... A63: =+H63&I63&$I$8 -> Instrumentchnnl_orgntn45991 | B63: {=+MAX(IF('3. Resultados'!A:A='1. Status'!A63&'1. Status'!$B$10,'3. Resultados'!K:K))} -> 0 | C63: {=+MAX(IF('3. Resultados'!A:A='1. Status'!A63&'1. Status'!$C$10,'3. Resultados'!K:K))} -> 0 | D63: {=+MAX(IF('3. Resultados'!A:A='1. Status'!A63&'1. Status'!$D$10,'3. Resultados'!K:K))} -> 0 | E63: {=+MAX(IF('3. Resultados'!A:A='1. Status'!A63&'1. Status'!$E$10,'3. Resultados'!K:K))} -> 0 | F63: {=+MAX(IF('3. Resultados'!A:A='1. Status'!A63&'1. Status'!$F$10,'3. Resultados'!K:K))} -> 0 | H63: Instrument | I63: chnnl_orgntn | J63: =+COUNTIFS('3. Resultados'!C:C,'1. Status'!H63,'3. Resultados'!G:G,'1. Status'!I63) -> 0 | K63: =+IFERROR(VLOOKUP(CONCATENATE(A63,$B$10,B63),'3. Resultados'!B:J,8,FALSE),"-") -> - | L63: =+IFERROR(VLOOKUP(B63,'3. Resultados'!K:L,2,FALSE),"-") -> - | M63: =+IFERROR(VLOOKUP(CONCATENATE(A63,$B$10,B63),'3. Resultados'!B:J,9,FALSE),"-") -> - | O63: =+IF(J63=0,"Por iniciar",IF(OR(K63="-",M63="-"),"Em testes",IF(M63=0,"OK","NOK"))) -> Por iniciar
H64: Instrument | I64: csh_swp_trp | J64: =+COUNTIFS('3. Resultados'!C:C,'1. Status'!H64,'3. Resultados'!G:G,'1. Status'!I64) -> 0 | K64: =+IFERROR(VLOOKUP(CONCATENATE(A64,$B$10,B64),'3. Resultados'!B:J,8,FALSE),"-") -> - | L64: =+IFERROR(VLOOKUP(B64,'3. Resultados'!K:L,2,FALSE),"-") -> - | M64: =+IFERROR(VLOOKUP(CONCATENATE(A64,$B$10,B64),'3. Resultados'!B:J,9,FALSE),"-") -> - | O64: =+IF(J64=0,"Por iniciar",IF(OR(K64="-",M64="-"),"Em testes",IF(M64=0,"OK","NOK"))) -> Por iniciar
H65: Instrument | I65: cvnnt_stts | J65: =+COUNTIFS('3. Resultados'!C:C,'1. Status'!H65,'3. Resultados'!G:G,'1. Status'!I65) -> 0 | K65: =+IFERROR(VLOOKUP(CONCATENATE(A65,$B$10,B65),'3. Resultados'!B:J,8,FALSE),"-") -> - | L65: =+IFERROR(VLOOKUP(B65,'3. Resultados'!K:L,2,FALSE),"-") -> - | M65: =+IFERROR(VLOOKUP(CONCATENATE(A65,$B$10,B65),'3. Resultados'!B:J,9,FALSE),"-") -> - | O65: =+IF(J65=0,"Por iniciar",IF(OR(K65="-",M65="-"),"Em testes",IF(M65=0,"OK","NOK"))) -> Por iniciar
H66: Instrument | I66: cvnnt_typ | J66: =+COUNTIFS('3. Resultados'!C:C,'1. Status'!H66,'3. Resultados'!G:G,'1. Status'!I66) -> 0 | K66: =+IFERROR(VLOOKUP(CONCATENATE(A66,$B$10,B66),'3. Resultados'!B:J,8,FALSE),"-") -> - | L66: =+IFERROR(VLOOKUP(B66,'3. Resultados'!K:L,2,FALSE),"-") -> - | M66: =+IFERROR(VLOOKUP(CONCATENATE(A66,$B$10,B66),'3. Resultados'!B:J,9,FALSE),"-") -> - | O66: =+IF(J66=0,"Por iniciar",IF(OR(K66="-",M66="-"),"Em testes",IF(M66=0,"OK","NOK"))) -> Por iniciar
H67: Instrument | I67: dflt_stts_instrmnt | J67: =+COUNTIFS('3. Resultados'!C:C,'1. Status'!H67,'3. Resultados'!G:G,'1. Status'!I67) -> 0 | K67: =+IFERROR(VLOOKUP(CONCATENATE(A67,$B$10,B67),'3. Resultados'!B:J,8,FALSE),"-") -> - | L67: =+IFERROR(VLOOKUP(B67,'3. Resultados'!K:L,2,FALSE),"-") -> - | M67: =+IFERROR(VLOOKUP(CONCATENATE(A67,$B$10,B67),'3. Resultados'!B:J,9,FALSE),"-") -> - | O67: =+IF(J67=0,"Por iniciar",IF(OR(K67="-",M67="-"),"Em testes",IF(M67=0,"OK","NOK"))) -> Por iniciar
H68: Instrument | I68: dt_dflt_stts_instrmnt | J68: =+COUNTIFS('3. Resultados'!C:C,'1. Status'!H68,'3. Resultados'!G:G,'1. Status'!I68) -> 0 | K68: =+IFERROR(VLOOKUP(CONCATENATE(A68,$B$10,B68),'3. Resultados'!B:J,8,FALSE),"-") -> - | L68: =+IFERROR(VLOOKUP(B68,'3. Resultados'!K:L,2,FALSE),"-") -> - | M68: =+IFERROR(VLOOKUP(CONCATENATE(A68,$B$10,B68),'3. Resultados'!B:J,9,FALSE),"-") -> - | O68: =+IF(J68=0,"Por iniciar",IF(OR(K68="-",M68="-"),"Em testes",IF(M68=0,"OK","NOK"))) -> Por iniciar
H69: Instrument | I69: dt_end_gp_ppal | J69: =+COUNTIFS('3. Resultados'!C:C,'1. Status'!H69,'3. Resultados'!G:G,'1. Status'!I69) -> 0 | K69: =+IFERROR(VLOOKUP(CONCATENATE(A69,$B$10,B69),'3. Resultados'!B:J,8,FALSE),"-") -> - | L69: =+IFERROR(VLOOKUP(B69,'3. Resultados'!K:L,2,FALSE),"-") -> - | M69: =+IFERROR(VLOOKUP(CONCATENATE(A69,$B$10,B69),'3. Resultados'!B:J,9,FALSE),"-") -> - | O69: =+IF(J69=0,"Por iniciar",IF(OR(K69="-",M69="-"),"Em testes",IF(M69=0,"OK","NOK"))) -> Por iniciar
H70: Instrument | I70: dt_end_intrst_only | J70: =+COUNTIFS('3. Resultados'!C:C,'1. Status'!H70,'3. Resultados'!G:G,'1. Status'!I70) -> 0 | K70: =+IFERROR(VLOOKUP(CONCATENATE(A70,$B$10,B70),'3. Resultados'!B:J,8,FALSE),"-") -> - | L70: =+IFERROR(VLOOKUP(B70,'3. Resultados'!K:L,2,FALSE),"-") -> - | M70: =+IFERROR(VLOOKUP(CONCATENATE(A70,$B$10,B70),'3. Resultados'!B:J,9,FALSE),"-") -> - | O70: =+IF(J70=0,"Por iniciar",IF(OR(K70="-",M70="-"),"Em testes",IF(M70=0,"OK","NOK"))) -> Por iniciar
H71: Instrument | I71: dt_frbrnc_stts | J71: =+COUNTIFS('3. Resultados'!C:C,'1. Status'!H71,'3. Resultados'!G:G,'1. Status'!I71) -> 0 | K71: =+IFERROR(VLOOKUP(CONCATENATE(A71,$B$10,B71),'3. Resultados'!B:J,8,FALSE),"-") -> - | L71: =+IFERROR(VLOOKUP(B71,'3. Resultados'!K:L,2,FALSE),"-") -> - | M71: =+IFERROR(VLOOKUP(CONCATENATE(A71,$B$10,B71),'3. Resultados'!B:J,9,FALSE),"-") -> - | O71: =+IF(J71=0,"Por iniciar",IF(OR(K71="-",M71="-"),"Em testes",IF(M71=0,"OK","NOK"))) -> Por iniciar
H72: Instrument | I72: dt_frbrnc_stts_prvs | J72: =+COUNTIFS('3. Resultados'!C:C,'1. Status'!H72,'3. Resultados'!G:G,'1. Status'!I72) -> 0 | K72: =+IFERROR(VLOOKUP(CONCATENATE(A72,$B$10,B72),'3. Resultados'!B:J,8,FALSE),"-") -> - | L72: =+IFERROR(VLOOKUP(B72,'3. Resultados'!K:L,2,FALSE),"-") -> - | M72: =+IFERROR(VLOOKUP(CONCATENATE(A72,$B$10,B72),'3. Resultados'!B:J,9,FALSE),"-") -> - | O72: =+IF(J72=0,"Por iniciar",IF(OR(K72="-",M72="-"),"Em testes",IF(M72=0,"OK","NOK"))) -> Por iniciar
H73: Instrument | I73: dt_intrnl_rtng | J73: =+COUNTIFS('3. Resultados'!C:C,'1. Status'!H73,'3. Resultados'!G:G,'1. Status'!I73) -> 0 | K73: =+IFERROR(VLOOKUP(CONCATENATE(A73,$B$10,B73),'3. Resultados'!B:J,8,FALSE),"-") -> - | L73: =+IFERROR(VLOOKUP(B73,'3. Resultados'!K:L,2,FALSE),"-") -> - | M73: =+IFERROR(VLOOKUP(CONCATENATE(A73,$B$10,B73),'3. Resultados'!B:J,9,FALSE),"-") -> - | O73: =+IF(J73=0,"Por iniciar",IF(OR(K73="-",M73="-"),"Em testes",IF(M73=0,"OK","NOK"))) -> Por iniciar
H74: Instrument | I74: dt_prfrmng_stts | J74: =+COUNTIFS('3. Resultados'!C:C,'1. Status'!H74,'3. Resultados'!G:G,'1. Status'!I74) -> 0 | K74: =+IFERROR(VLOOKUP(CONCATENATE(A74,$B$10,B74),'3. Resultados'!B:J,8,FALSE),"-") -> - | L74: =+IFERROR(VLOOKUP(B74,'3. Resultados'!K:L,2,FALSE),"-") -> - | M74: =+IFERROR(VLOOKUP(CONCATENATE(A74,$B$10,B74),'3. Resultados'!B:J,9,FALSE),"-") -> - | O74: =+IF(J74=0,"Por iniciar",IF(OR(K74="-",M74="-"),"Em testes",IF(M74=0,"OK","NOK"))) -> Por iniciar
H75: Instrument | I75: dt_prfrmng_stts_prvs | J75: =+COUNTIFS('3. Resultados'!C:C,'1. Status'!H75,'3. Resultados'!G:G,'1. Status'!I75) -> 0 | K75: =+IFERROR(VLOOKUP(CONCATENATE(A75,$B$10,B75),'3. Resultados'!B:J,8,FALSE),"-") -> - | L75: =+IFERROR(VLOOKUP(B75,'3. Resultados'!K:L,2,FALSE),"-") -> - | M75: =+IFERROR(VLOOKUP(CONCATENATE(A75,$B$10,B75),'3. Resultados'!B:J,9,FALSE),"-") -> - | O75: =+IF(J75=0,"Por iniciar",IF(OR(K75="-",M75="-"),"Em testes",IF(M75=0,"OK","NOK"))) -> Por iniciar
... H667: INSTR_PROT | I667: cod_soc | J667: =+COUNTIFS('3. Resultados'!C:C,'1. Status'!H667,'3. Resultados'!G:G,'1. Status'!I667) -> 0 | K667: =+IFERROR(VLOOKUP(CONCATENATE(A667,$B$10,B667),'3. Resultados'!B:J,8,FALSE),"-") -> - | L667: =+IFERROR(VLOOKUP(B667,'3. Resultados'!K:L,2,FALSE),"-") -> - | M667: =+IFERROR(VLOOKUP(CONCATENATE(A667,$B$10,B667),'3. Resultados'!B:J,9,FALSE),"-") -> - | O667: =+IF(J667=0,"Por iniciar",IF(OR(K667="-",M667="-"),"Em testes",IF(M667=0,"OK","NOK"))) -> Por iniciar

Sheet 2. Script 
B6: 2. Script de Controlos
B8: TABELA | C8: CAMPO | D8: TIPOLOGIA_TESTE | E8: TABELA_LT | F8: TABELA_SIMUL | H8: FORMATO CAMPO | I8: VALORES CODE LIST | J8: UNIVERSO_PM | K8: UNIVERSO_SIMUL | L8: CRUZAMENTO | M8: QUERY 1 | N8: UNION ALL
A9: =+B9&C9 -> UNIV_OPERmsaldo_final | B9: UNIV_OPER | C9: msaldo_final | D9: Coerência | E9: =+UPPER('0. Instruções'!$D$35&"."&VLOOKUP(B9,'0. Instruções'!$C$27:$D$32,2,FALSE)) -> CD_LOAN_TAPES_BCE.LT001_UNIV_OPER | F9: =+UPPER('0. Instruções'!$D$36&"."&VLOOKUP(B9,'0. Instruções'!$C$27:$E$32,3,FALSE)) -> BU_LOANTAPE_WORK.LT001_UNIV_OPER | J9: =IF(VLOOKUP(B9,'0. Instruções'!$C$27:$G$32,5,FALSE)=0, "(SELECT "&VLOOKUP(B9,'0. Instruções'!$C$27:$G$32,4,FALSE)&" AS CHAVE_IT, "&C9&" AS CAMPO_IT FROM "&E9&" WHERE "&'0. Instruções'!$D$43&")X", "(SELECT "&VLOOKUP(B9,'0. Instruções'!$C$27:$G$32,4,FALSE)&" AS CHAVE_IT1, "&VLOOKUP(B9,'0. Instruções'!$C$27:$G$32,5,FALSE)&" AS CHAVE_IT2, "&C9&" AS CAMPO_IT FROM "&E9&" WHERE "&'0. Instruções'!$D$43&")X") -> (SELECT concat(cempresa, cbalcao, cnumecta, zdeposit, ccontab_final_ifrs, ccontab_final_pcsb, ccontab_final_cargabal, ccontab_final) AS CHAVE_IT1, zcliente AS CHAVE_IT2, msaldo_final AS CAMPO_IT FROM CD_LOAN_TAPES_BCE.LT001_UNIV_OPER WHERE ref_date='${ref_date}' AND nome_perimetro='Individual Local' AND segmento='ESTR' AND ambito='PM' AND entidade='00100')X | K9: =IF(VLOOKUP(B9,'0. Instruções'!$C$27:$G$32,5,FALSE)=0, "(SELECT "&VLOOKUP(B9,'0. Instruções'!$C$27:$G$32,4,FALSE)&" AS CHAVE_SIMUL, "&C9&" AS CAMPO_SIMUL FROM "&F9&" WHERE "&'0. Instruções'!$D$42&")Y", "(SELECT "&VLOOKUP(B9,'0. Instruções'!$C$27:$G$32,4,FALSE)&" AS CHAVE_SIMUL1, "&VLOOKUP(B9,'0. Instruções'!$C$27:$G$32,5,FALSE)&" AS CHAVE_SIMUL2, "&C9&" AS CAMPO_SIMUL FROM "&F9&" WHERE "&'0. Instruções'!$D$42&")Y") -> (SELECT concat(cempresa, cbalcao, cnumecta, zdeposit, ccontab_final_ifrs, ccontab_final_pcsb, ccontab_final_cargabal, ccontab_final) AS CHAVE_SIMUL1, zcliente AS CHAVE_SIMUL2, msaldo_final AS CAMPO_SIMUL FROM BU_LOANTAPE_WORK.LT001_UNIV_OPER WHERE ref_date='${ref_date}' AND nome_perimetro='Individual Local' AND segmento='ESTR' AND ambito='PM' AND entidade='00100')Y | L9: =IF(VLOOKUP(B9,'0. Instruções'!$C$27:$G$32,5,FALSE)=0, "ON X.CHAVE_IT=Y.CHAVE_SIMUL", "ON X.CHAVE_IT1=Y.CHAVE_SIMUL1 AND X.CHAVE_IT2=Y.CHAVE_SIMUL2") -> ON X.CHAVE_IT1=Y.CHAVE_SIMUL1 AND X.CHAVE_IT2=Y.CHAVE_SIMUL2 | M9: =+IF(D9="Coerência",+IF(LEFT(H9,5)="FLOAT","SELECT '"&UPPER(B9)&"' AS TABELA, '"&UPPER(D9)&"' AS TIPOLOGIA_TESTE,'"&E9&"' AS TABELA_LT,'"&F9&"' AS TABELA_SIMUL,'"&C9&"' AS CAMPO, "&_xlfn._LONGTEXT("'${ref_date}' AS REF_DATE, COUNT(*) AS NUM_REG, SUM(IF((ABS(COALESCE(CAST(X.CAMPO_IT AS DECIMAL(18,6)),0)-COALESCE(CAST(Y.CAMPO_SIMUL AS DECIMAL(18,6)),0))>0.000001) OR (X.CAMPO_IT IS NULL AND Y.CAMPO_SIMUL IS NOT NULL ) OR (X.CAMPO_IT IS NOT NULL AND Y.C","AMPO_SIMUL IS NULL),1,0)) AS NUM_REG_DIF,'")&MAX('3. Resultados'!K:K)+1&"' AS ID_EXEC, CURRENT_TIMESTAMP() AS TIME_EXEC FROM "&J9&" INNER JOIN "&K9&" "&L9,"SELECT '"&UPPER(B9)&"' AS TABELA, '"&UPPER(D9)&"' AS TIPOLOGIA_TESTE,'"&E9&"' AS TABELA_LT,'"&F9&"' AS TABELA_SIMUL,'"&C9&"' AS CAMPO, "&_xlfn._LONGTEXT("'${ref_date}' AS REF_DATE, COUNT(*) AS NUM_REG, SUM(IF(COALESCE(CAST(X.CAMPO_IT AS STRING),'')<>COALESCE(CAST(Y.CAMPO_SIMUL AS STRING),'') OR (X.CAMPO_IT IS NULL AND Y.CAMPO_SIMUL IS NOT NULL ) OR (X.CAMPO_IT IS NOT NULL AND Y.CAMPO_SIMUL IS NULL),1,0)) A","S NUM_REG_DIF,'")&MAX('3. Resultados'!L:L)+1&"' AS ID_EXEC, CURRENT_TIMESTAMP() AS TIME_EXEC FROM "&J9&" INNER JOIN "&K9&" "&L9)) -> SELECT 'UNIV_OPER' AS TABELA, 'COERÊNCIA' AS TIPOLOGIA_TESTE,'CD_LOAN_TAPES_BCE.LT001_UNIV_OPER' AS TABELA_LT,'BU_LOANTAPE_WORK.LT001_UNIV_OPER' AS TABELA_SIMUL,'msaldo_final' AS CAMPO, '${ref_date}' AS REF_DATE, COUNT(*) AS NUM_REG, SUM(IF(COALESCE(CAST(X.CAMPO_IT AS STRING),'')<>COALESCE(CAST(Y.CAMPO_SIMUL AS STRING),'') OR (X.CAMPO_IT IS NULL AND Y.CAMPO_SIMUL IS NOT NULL ) OR (X.CAMPO_IT IS NOT NULL AND Y.CAMPO_SIMUL IS NULL),1,0)) AS NUM_REG_DIF,'1' AS ID_EXEC, CURRENT_TIMESTAMP() AS TIME_EXEC FROM (SELECT concat(cempresa, cbalcao, cnumecta, zdeposit, ccontab_final_ifrs, ccontab_final_pcsb, ccontab_final_cargabal, ccontab_final) AS CHAVE_IT1, zcliente AS CHAVE_IT2, msaldo_final AS CAMPO_IT FROM CD_LOAN_TAPES_BCE.LT001_UNIV_OPER WHERE ref_date='${ref_date}' AND nome_perimetro='Individual Local' AND segmento='ESTR' AND ambito='PM' AND entidade='00100')X INNER JOIN (SELECT concat(cempresa, cbalcao, cnumecta, zdeposit, ccontab_final_ifrs, ccontab_final_pcsb, ccontab_final_cargabal, ccontab_final) AS CHAVE_SIMUL1, zcliente AS CHAVE_SIMUL2, msaldo_final AS CAMPO_SIMUL FROM BU_LOANTAPE_WORK.LT001_UNIV_OPER WHERE ref_date='${ref_date}' AND nome_perimetro='Individual Local' AND segmento='ESTR' AND ambito='PM' AND entidade='00100')Y ON X.CHAVE_IT1=Y.CHAVE_SIMUL1 AND X.CHAVE_IT2=Y.CHAVE_SIMUL2 | N9: =+"UNION ALL "&M9 -> UNION ALL SELECT 'UNIV_OPER' AS TABELA, 'COERÊNCIA' AS TIPOLOGIA_TESTE,'CD_LOAN_TAPES_BCE.LT001_UNIV_OPER' AS TABELA_LT,'BU_LOANTAPE_WORK.LT001_UNIV_OPER' AS TABELA_SIMUL,'msaldo_final' AS CAMPO, '${ref_date}' AS REF_DATE, COUNT(*) AS NUM_REG, SUM(IF(COALESCE(CAST(X.CAMPO_IT AS STRING),'')<>COALESCE(CAST(Y.CAMPO_SIMUL AS STRING),'') OR (X.CAMPO_IT IS NULL AND Y.CAMPO_SIMUL IS NOT NULL ) OR (X.CAMPO_IT IS NOT NULL AND Y.CAMPO_SIMUL IS NULL),1,0)) AS NUM_REG_DIF,'1' AS ID_EXEC, CURRENT_TIMESTAMP() AS TIME_EXEC FROM (SELECT concat(cempresa, cbalcao, cnumecta, zdeposit, ccontab_final_ifrs, ccontab_final_pcsb, ccontab_final_cargabal, ccontab_final) AS CHAVE_IT1, zcliente AS CHAVE_IT2, msaldo_final AS CAMPO_IT FROM CD_LOAN_TAPES_BCE.LT001_UNIV_OPER WHERE ref_date='${ref_date}' AND nome_perimetro='Individual Local' AND segmento='ESTR' AND ambito='PM' AND entidade='00100')X INNER JOIN (SELECT concat(cempresa, cbalcao, cnumecta, zdeposit, ccontab_final_ifrs, ccontab_final_pcsb, ccontab_final_cargabal, ccontab_final) AS CHAVE_SIMUL1, zcliente AS CHAVE_SIMUL2, msaldo_final AS CAMPO_SIMUL FROM BU_LOANTAPE_WORK.LT001_UNIV_OPER WHERE ref_date='${ref_date}' AND nome_perimetro='Individual Local' AND segmento='ESTR' AND ambito='PM' AND entidade='00100')Y ON X.CHAVE_IT1=Y.CHAVE_SIMUL1 AND X.CHAVE_IT2=Y.CHAVE_SIMUL2
A10: =+B10&C10 -> UNIV_OPERcarteira_contabilistica | B10: UNIV_OPER | C10: carteira_contabilistica | D10: Coerência | E10: =+UPPER('0. Instruções'!$D$35&"."&VLOOKUP(B10,'0. Instruções'!$C$27:$D$32,2,FALSE)) -> CD_LOAN_TAPES_BCE.LT001_UNIV_OPER | F10: =+UPPER('0. Instruções'!$D$36&"."&VLOOKUP(B10,'0. Instruções'!$C$27:$E$32,3,FALSE)) -> BU_LOANTAPE_WORK.LT001_UNIV_OPER | J10: =IF(VLOOKUP(B10,'0. Instruções'!$C$27:$G$32,5,FALSE)=0, "(SELECT "&VLOOKUP(B10,'0. Instruções'!$C$27:$G$32,4,FALSE)&" AS CHAVE_IT, "&C10&" AS CAMPO_IT FROM "&E10&" WHERE "&'0. Instruções'!$D$43&")X", "(SELECT "&VLOOKUP(B10,'0. Instruções'!$C$27:$G$32,4,FALSE)&" AS CHAVE_IT1, "&VLOOKUP(B10,'0. Instruções'!$C$27:$G$32,5,FALSE)&" AS CHAVE_IT2, "&C10&" AS CAMPO_IT FROM "&E10&" WHERE "&'0. Instruções'!$D$43&")X") -> (SELECT concat(cempresa, cbalcao, cnumecta, zdeposit, ccontab_final_ifrs, ccontab_final_pcsb, ccontab_final_cargabal, ccontab_final) AS CHAVE_IT1, zcliente AS CHAVE_IT2, carteira_contabilistica AS CAMPO_IT FROM CD_LOAN_TAPES_BCE.LT001_UNIV_OPER WHERE ref_date='${ref_date}' AND nome_perimetro='Individual Local' AND segmento='ESTR' AND ambito='PM' AND entidade='00100')X | K10: =IF(VLOOKUP(B10,'0. Instruções'!$C$27:$G$32,5,FALSE)=0, "(SELECT "&VLOOKUP(B10,'0. Instruções'!$C$27:$G$32,4,FALSE)&" AS CHAVE_SIMUL, "&C10&" AS CAMPO_SIMUL FROM "&F10&" WHERE "&'0. Instruções'!$D$42&")Y", "(SELECT "&VLOOKUP(B10,'0. Instruções'!$C$27:$G$32,4,FALSE)&" AS CHAVE_SIMUL1, "&VLOOKUP(B10,'0. Instruções'!$C$27:$G$32,5,FALSE)&" AS CHAVE_SIMUL2, "&C10&" AS CAMPO_SIMUL FROM "&F10&" WHERE "&'0. Instruções'!$D$42&")Y") -> (SELECT concat(cempresa, cbalcao, cnumecta, zdeposit, ccontab_final_ifrs, ccontab_final_pcsb, ccontab_final_cargabal, ccontab_final) AS CHAVE_SIMUL1, zcliente AS CHAVE_SIMUL2, carteira_contabilistica AS CAMPO_SIMUL FROM BU_LOANTAPE_WORK.LT001_UNIV_OPER WHERE ref_date='${ref_date}' AND nome_perimetro='Individual Local' AND segmento='ESTR' AND ambito='PM' AND entidade='00100')Y | L10: =IF(VLOOKUP(B10,'0. Instruções'!$C$27:$G$32,5,FALSE)=0, "ON X.CHAVE_IT=Y.CHAVE_SIMUL", "ON X.CHAVE_IT1=Y.CHAVE_SIMUL1 AND X.CHAVE_IT2=Y.CHAVE_SIMUL2") -> ON X.CHAVE_IT1=Y.CHAVE_SIMUL1 AND X.CHAVE_IT2=Y.CHAVE_SIMUL2 | M10: =+IF(D10="Coerência",+IF(LEFT(H10,5)="FLOAT","SELECT '"&UPPER(B10)&"' AS TABELA, '"&UPPER(D10)&"' AS TIPOLOGIA_TESTE,'"&E10&"' AS TABELA_LT,'"&F10&"' AS TABELA_SIMUL,'"&C10&"' AS CAMPO, "&_xlfn._LONGTEXT("'${ref_date}' AS REF_DATE, COUNT(*) AS NUM_REG, SUM(IF((ABS(COALESCE(CAST(X.CAMPO_IT AS DECIMAL(18,6)),0)-COALESCE(CAST(Y.CAMPO_SIMUL AS DECIMAL(18,6)),0))>0.000001) OR (X.CAMPO_IT IS NULL AND Y.CAMPO_SIMUL IS NOT NULL ) OR (X.CAMPO_IT IS NOT NULL AND Y.C","AMPO_SIMUL IS NULL),1,0)) AS NUM_REG_DIF,'")&MAX('3. Resultados'!K:K)+1&"' AS ID_EXEC, CURRENT_TIMESTAMP() AS TIME_EXEC FROM "&J10&" INNER JOIN "&K10&" "&L10,"SELECT '"&UPPER(B10)&"' AS TABELA, '"&UPPER(D10)&"' AS TIPOLOGIA_TESTE,'"&E10&"' AS TABELA_LT,'"&F10&"' AS TABELA_SIMUL,'"&C10&"' AS CAMPO, "&_xlfn._LONGTEXT("'${ref_date}' AS REF_DATE, COUNT(*) AS NUM_REG, SUM(IF(COALESCE(CAST(X.CAMPO_IT AS STRING),'')<>COALESCE(CAST(Y.CAMPO_SIMUL AS STRING),'') OR (X.CAMPO_IT IS NULL AND Y.CAMPO_SIMUL IS NOT NULL ) OR (X.CAMPO_IT IS NOT NULL AND Y.CAMPO_SIMUL IS NULL),1,0)) A","S NUM_REG_DIF,'")&MAX('3. Resultados'!L:L)+1&"' AS ID_EXEC, CURRENT_TIMESTAMP() AS TIME_EXEC FROM "&J10&" INNER JOIN "&K10&" "&L10)) -> SELECT 'UNIV_OPER' AS TABELA, 'COERÊNCIA' AS TIPOLOGIA_TESTE,'CD_LOAN_TAPES_BCE.LT001_UNIV_OPER' AS TABELA_LT,'BU_LOANTAPE_WORK.LT001_UNIV_OPER' AS TABELA_SIMUL,'carteira_contabilistica' AS CAMPO, '${ref_date}' AS REF_DATE, COUNT(*) AS NUM_REG, SUM(IF(COALESCE(CAST(X.CAMPO_IT AS STRING),'')<>COALESCE(CAST(Y.CAMPO_SIMUL AS STRING),'') OR (X.CAMPO_IT IS NULL AND Y.CAMPO_SIMUL IS NOT NULL ) OR (X.CAMPO_IT IS NOT NULL AND Y.CAMPO_SIMUL IS NULL),1,0)) AS NUM_REG_DIF,'1' AS ID_EXEC, CURRENT_TIMESTAMP() AS TIME_EXEC FROM (SELECT concat(cempresa, cbalcao, cnumecta, zdeposit, ccontab_final_ifrs, ccontab_final_pcsb, ccontab_final_cargabal, ccontab_final) AS CHAVE_IT1, zcliente AS CHAVE_IT2, carteira_contabilistica AS CAMPO_IT FROM CD_LOAN_TAPES_BCE.LT001_UNIV_OPER WHERE ref_date='${ref_date}' AND nome_perimetro='Individual Local' AND segmento='ESTR' AND ambito='PM' AND entidade='00100')X INNER JOIN (SELECT concat(cempresa, cbalcao, cnumecta, zdeposit, ccontab_final_ifrs, ccontab_final_pcsb, ccontab_final_cargabal, ccontab_final) AS CHAVE_SIMUL1, zcliente AS CHAVE_SIMUL2, carteira_contabilistica AS CAMPO_SIMUL FROM BU_LOANTAPE_WORK.LT001_UNIV_OPER WHERE ref_date='${ref_date}' AND nome_perimetro='Individual Local' AND segmento='ESTR' AND ambito='PM' AND entidade='00100')Y ON X.CHAVE_IT1=Y.CHAVE_SIMUL1 AND X.CHAVE_IT2=Y.CHAVE_SIMUL2 | N10: =+"UNION ALL "&M10 -> UNION ALL SELECT 'UNIV_OPER' AS TABELA, 'COERÊNCIA' AS TIPOLOGIA_TESTE,'CD_LOAN_TAPES_BCE.LT001_UNIV_OPER' AS TABELA_LT,'BU_LOANTAPE_WORK.LT001_UNIV_OPER' AS TABELA_SIMUL,'carteira_contabilistica' AS CAMPO, '${ref_date}' AS REF_DATE, COUNT(*) AS NUM_REG, SUM(IF(COALESCE(CAST(X.CAMPO_IT AS STRING),'')<>COALESCE(CAST(Y.CAMPO_SIMUL AS STRING),'') OR (X.CAMPO_IT IS NULL AND Y.CAMPO_SIMUL IS NOT NULL ) OR (X.CAMPO_IT IS NOT NULL AND Y.CAMPO_SIMUL IS NULL),1,0)) AS NUM_REG_DIF,'1' AS ID_EXEC, CURRENT_TIMESTAMP() AS TIME_EXEC FROM (SELECT concat(cempresa, cbalcao, cnumecta, zdeposit, ccontab_final_ifrs, ccontab_final_pcsb, ccontab_final_cargabal, ccontab_final) AS CHAVE_IT1, zcliente AS CHAVE_IT2, carteira_contabilistica AS CAMPO_IT FROM CD_LOAN_TAPES_BCE.LT001_UNIV_OPER WHERE ref_date='${ref_date}' AND nome_perimetro='Individual Local' AND segmento='ESTR' AND ambito='PM' AND entidade='00100')X INNER JOIN (SELECT concat(cempresa, cbalcao, cnumecta, zdeposit, ccontab_final_ifrs, ccontab_final_pcsb, ccontab_final_cargabal, ccontab_final) AS CHAVE_SIMUL1, zcliente AS CHAVE_SIMUL2, carteira_contabilistica AS CAMPO_SIMUL FROM BU_LOANTAPE_WORK.LT001_UNIV_OPER WHERE ref_date='${ref_date}' AND nome_perimetro='Individual Local' AND segmento='ESTR' AND ambito='PM' AND entidade='00100')Y ON X.CHAVE_IT1=Y.CHAVE_SIMUL1 AND X.CHAVE_IT2=Y.CHAVE_SIMUL2
A11: =+B11&C11 -> UNIV_OPERinstrumento_financeiro | B11: UNIV_OPER | C11: instrumento_financeiro | D11: Coerência | E11: =+UPPER('0. Instruções'!$D$35&"."&VLOOKUP(B11,'0. Instruções'!$C$27:$D$32,2,FALSE)) -> CD_LOAN_TAPES_BCE.LT001_UNIV_OPER | F11: =+UPPER('0. Instruções'!$D$36&"."&VLOOKUP(B11,'0. Instruções'!$C$27:$E$32,3,FALSE)) -> BU_LOANTAPE_WORK.LT001_UNIV_OPER | J11: =IF(VLOOKUP(B11,'0. Instruções'!$C$27:$G$32,5,FALSE)=0, "(SELECT "&VLOOKUP(B11,'0. Instruções'!$C$27:$G$32,4,FALSE)&" AS CHAVE_IT, "&C11&" AS CAMPO_IT FROM "&E11&" WHERE "&'0. Instruções'!$D$43&")X", "(SELECT "&VLOOKUP(B11,'0. Instruções'!$C$27:$G$32,4,FALSE)&" AS CHAVE_IT1, "&VLOOKUP(B11,'0. Instruções'!$C$27:$G$32,5,FALSE)&" AS CHAVE_IT2, "&C11&" AS CAMPO_IT FROM "&E11&" WHERE "&'0. Instruções'!$D$43&")X") -> (SELECT concat(cempresa, cbalcao, cnumecta, zdeposit, ccontab_final_ifrs, ccontab_final_pcsb, ccontab_final_cargabal, ccontab_final) AS CHAVE_IT1, zcliente AS CHAVE_IT2, instrumento_financeiro AS CAMPO_IT FROM CD_LOAN_TAPES_BCE.LT001_UNIV_OPER WHERE ref_date='${ref_date}' AND nome_perimetro='Individual Local' AND segmento='ESTR' AND ambito='PM' AND entidade='00100')X | K11: =IF(VLOOKUP(B11,'0. Instruções'!$C$27:$G$32,5,FALSE)=0, "(SELECT "&VLOOKUP(B11,'0. Instruções'!$C$27:$G$32,4,FALSE)&" AS CHAVE_SIMUL, "&C11&" AS CAMPO_SIMUL FROM "&F11&" WHERE "&'0. Instruções'!$D$42&")Y", "(SELECT "&VLOOKUP(B11,'0. Instruções'!$C$27:$G$32,4,FALSE)&" AS CHAVE_SIMUL1, "&VLOOKUP(B11,'0. Instruções'!$C$27:$G$32,5,FALSE)&" AS CHAVE_SIMUL2, "&C11&" AS CAMPO_SIMUL FROM "&F11&" WHERE "&'0. Instruções'!$D$42&")Y") -> (SELECT concat(cempresa, cbalcao, cnumecta, zdeposit, ccontab_final_ifrs, ccontab_final_pcsb, ccontab_final_cargabal, ccontab_final) AS CHAVE_SIMUL1, zcliente AS CHAVE_SIMUL2, instrumento_financeiro AS CAMPO_SIMUL FROM BU_LOANTAPE_WORK.LT001_UNIV_OPER WHERE ref_date='${ref_date}' AND nome_perimetro='Individual Local' AND segmento='ESTR' AND ambito='PM' AND entidade='00100')Y | L11: =IF(VLOOKUP(B11,'0. Instruções'!$C$27:$G$32,5,FALSE)=0, "ON X.CHAVE_IT=Y.CHAVE_SIMUL", "ON X.CHAVE_IT1=Y.CHAVE_SIMUL1 AND X.CHAVE_IT2=Y.CHAVE_SIMUL2") -> ON X.CHAVE_IT1=Y.CHAVE_SIMUL1 AND X.CHAVE_IT2=Y.CHAVE_SIMUL2 | M11: =+IF(D11="Coerência",+IF(LEFT(H11,5)="FLOAT","SELECT '"&UPPER(B11)&"' AS TABELA, '"&UPPER(D11)&"' AS TIPOLOGIA_TESTE,'"&E11&"' AS TABELA_LT,'"&F11&"' AS TABELA_SIMUL,'"&C11&"' AS CAMPO, "&_xlfn._LONGTEXT("'${ref_date}' AS REF_DATE, COUNT(*) AS NUM_REG, SUM(IF((ABS(COALESCE(CAST(X.CAMPO_IT AS DECIMAL(18,6)),0)-COALESCE(CAST(Y.CAMPO_SIMUL AS DECIMAL(18,6)),0))>0.000001) OR (X.CAMPO_IT IS NULL AND Y.CAMPO_SIMUL IS NOT NULL ) OR (X.CAMPO_IT IS NOT NULL AND Y.C","AMPO_SIMUL IS NULL),1,0)) AS NUM_REG_DIF,'")&MAX('3. Resultados'!K:K)+1&"' AS ID_EXEC, CURRENT_TIMESTAMP() AS TIME_EXEC FROM "&J11&" INNER JOIN "&K11&" "&L11,"SELECT '"&UPPER(B11)&"' AS TABELA, '"&UPPER(D11)&"' AS TIPOLOGIA_TESTE,'"&E11&"' AS TABELA_LT,'"&F11&"' AS TABELA_SIMUL,'"&C11&"' AS CAMPO, "&_xlfn._LONGTEXT("'${ref_date}' AS REF_DATE, COUNT(*) AS NUM_REG, SUM(IF(COALESCE(CAST(X.CAMPO_IT AS STRING),'')<>COALESCE(CAST(Y.CAMPO_SIMUL AS STRING),'') OR (X.CAMPO_IT IS NULL AND Y.CAMPO_SIMUL IS NOT NULL ) OR (X.CAMPO_IT IS NOT NULL AND Y.CAMPO_SIMUL IS NULL),1,0)) A","S NUM_REG_DIF,'")&MAX('3. Resultados'!L:L)+1&"' AS ID_EXEC, CURRENT_TIMESTAMP() AS TIME_EXEC FROM "&J11&" INNER JOIN "&K11&" "&L11)) -> SELECT 'UNIV_OPER' AS TABELA, 'COERÊNCIA' AS TIPOLOGIA_TESTE,'CD_LOAN_TAPES_BCE.LT001_UNIV_OPER' AS TABELA_LT,'BU_LOANTAPE_WORK.LT001_UNIV_OPER' AS TABELA_SIMUL,'instrumento_financeiro' AS CAMPO, '${ref_date}' AS REF_DATE, COUNT(*) AS NUM_REG, SUM(IF(COALESCE(CAST(X.CAMPO_IT AS STRING),'')<>COALESCE(CAST(Y.CAMPO_SIMUL AS STRING),'') OR (X.CAMPO_IT IS NULL AND Y.CAMPO_SIMUL IS NOT NULL ) OR (X.CAMPO_IT IS NOT NULL AND Y.CAMPO_SIMUL IS NULL),1,0)) AS NUM_REG_DIF,'1' AS ID_EXEC, CURRENT_TIMESTAMP() AS TIME_EXEC FROM (SELECT concat(cempresa, cbalcao, cnumecta, zdeposit, ccontab_final_ifrs, ccontab_final_pcsb, ccontab_final_cargabal, ccontab_final) AS CHAVE_IT1, zcliente AS CHAVE_IT2, instrumento_financeiro AS CAMPO_IT FROM CD_LOAN_TAPES_BCE.LT001_UNIV_OPER WHERE ref_date='${ref_date}' AND nome_perimetro='Individual Local' AND segmento='ESTR' AND ambito='PM' AND entidade='00100')X INNER JOIN (SELECT concat(cempresa, cbalcao, cnumecta, zdeposit, ccontab_final_ifrs, ccontab_final_pcsb, ccontab_final_cargabal, ccontab_final) AS CHAVE_SIMUL1, zcliente AS CHAVE_SIMUL2, instrumento_financeiro AS CAMPO_SIMUL FROM BU_LOANTAPE_WORK.LT001_UNIV_OPER WHERE ref_date='${ref_date}' AND nome_perimetro='Individual Local' AND segmento='ESTR' AND ambito='PM' AND entidade='00100')Y ON X.CHAVE_IT1=Y.CHAVE_SIMUL1 AND X.CHAVE_IT2=Y.CHAVE_SIMUL2 | N11: =+"UNION ALL "&M11 -> UNION ALL SELECT 'UNIV_OPER' AS TABELA, 'COERÊNCIA' AS TIPOLOGIA_TESTE,'CD_LOAN_TAPES_BCE.LT001_UNIV_OPER' AS TABELA_LT,'BU_LOANTAPE_WORK.LT001_UNIV_OPER' AS TABELA_SIMUL,'instrumento_financeiro' AS CAMPO, '${ref_date}' AS REF_DATE, COUNT(*) AS NUM_REG, SUM(IF(COALESCE(CAST(X.CAMPO_IT AS STRING),'')<>COALESCE(CAST(Y.CAMPO_SIMUL AS STRING),'') OR (X.CAMPO_IT IS NULL AND Y.CAMPO_SIMUL IS NOT NULL ) OR (X.CAMPO_IT IS NOT NULL AND Y.CAMPO_SIMUL IS NULL),1,0)) AS NUM_REG_DIF,'1' AS ID_EXEC, CURRENT_TIMESTAMP() AS TIME_EXEC FROM (SELECT concat(cempresa, cbalcao, cnumecta, zdeposit, ccontab_final_ifrs, ccontab_final_pcsb, ccontab_final_cargabal, ccontab_final) AS CHAVE_IT1, zcliente AS CHAVE_IT2, instrumento_financeiro AS CAMPO_IT FROM CD_LOAN_TAPES_BCE.LT001_UNIV_OPER WHERE ref_date='${ref_date}' AND nome_perimetro='Individual Local' AND segmento='ESTR' AND ambito='PM' AND entidade='00100')X INNER JOIN (SELECT concat(cempresa, cbalcao, cnumecta, zdeposit, ccontab_final_ifrs, ccontab_final_pcsb, ccontab_final_cargabal, ccontab_final) AS CHAVE_SIMUL1, zcliente AS CHAVE_SIMUL2, instrumento_financeiro AS CAMPO_SIMUL FROM BU_LOANTAPE_WORK.LT001_UNIV_OPER WHERE ref_date='${ref_date}' AND nome_perimetro='Individual Local' AND segmento='ESTR' AND ambito='PM' AND entidade='00100')Y ON X.CHAVE_IT1=Y.CHAVE_SIMUL1 AND X.CHAVE_IT2=Y.CHAVE_SIMUL2
A12: =+B12&C12 -> UNIV_OPERcontraparte | B12: UNIV_OPER | C12: contraparte | D12: Coerência | E12: =+UPPER('0. Instruções'!$D$35&"."&VLOOKUP(B12,'0. Instruções'!$C$27:$D$32,2,FALSE)) -> CD_LOAN_TAPES_BCE.LT001_UNIV_OPER | F12: =+UPPER('0. Instruções'!$D$36&"."&VLOOKUP(B12,'0. Instruções'!$C$27:$E$32,3,FALSE)) -> BU_LOANTAPE_WORK.LT001_UNIV_OPER | J12: =IF(VLOOKUP(B12,'0. Instruções'!$C$27:$G$32,5,FALSE)=0, "(SELECT "&VLOOKUP(B12,'0. Instruções'!$C$27:$G$32,4,FALSE)&" AS CHAVE_IT, "&C12&" AS CAMPO_IT FROM "&E12&" WHERE "&'0. Instruções'!$D$43&")X", "(SELECT "&VLOOKUP(B12,'0. Instruções'!$C$27:$G$32,4,FALSE)&" AS CHAVE_IT1, "&VLOOKUP(B12,'0. Instruções'!$C$27:$G$32,5,FALSE)&" AS CHAVE_IT2, "&C12&" AS CAMPO_IT FROM "&E12&" WHERE "&'0. Instruções'!$D$43&")X") -> (SELECT concat(cempresa, cbalcao, cnumecta, zdeposit, ccontab_final_ifrs, ccontab_final_pcsb, ccontab_final_cargabal, ccontab_final) AS CHAVE_IT1, zcliente AS CHAVE_IT2, contraparte AS CAMPO_IT FROM CD_LOAN_TAPES_BCE.LT001_UNIV_OPER WHERE ref_date='${ref_date}' AND nome_perimetro='Individual Local' AND segmento='ESTR' AND ambito='PM' AND entidade='00100')X | K12: =IF(VLOOKUP(B12,'0. Instruções'!$C$27:$G$32,5,FALSE)=0, "(SELECT "&VLOOKUP(B12,'0. Instruções'!$C$27:$G$32,4,FALSE)&" AS CHAVE_SIMUL, "&C12&" AS CAMPO_SIMUL FROM "&F12&" WHERE "&'0. Instruções'!$D$42&")Y", "(SELECT "&VLOOKUP(B12,'0. Instruções'!$C$27:$G$32,4,FALSE)&" AS CHAVE_SIMUL1, "&VLOOKUP(B12,'0. Instruções'!$C$27:$G$32,5,FALSE)&" AS CHAVE_SIMUL2, "&C12&" AS CAMPO_SIMUL FROM "&F12&" WHERE "&'0. Instruções'!$D$42&")Y") -> (SELECT concat(cempresa, cbalcao, cnumecta, zdeposit, ccontab_final_ifrs, ccontab_final_pcsb, ccontab_final_cargabal, ccontab_final) AS CHAVE_SIMUL1, zcliente AS CHAVE_SIMUL2, contraparte AS CAMPO_SIMUL FROM BU_LOANTAPE_WORK.LT001_UNIV_OPER WHERE ref_date='${ref_date}' AND nome_perimetro='Individual Local' AND segmento='ESTR' AND ambito='PM' AND entidade='00100')Y | L12: =IF(VLOOKUP(B12,'0. Instruções'!$C$27:$G$32,5,FALSE)=0, "ON X.CHAVE_IT=Y.CHAVE_SIMUL", "ON X.CHAVE_IT1=Y.CHAVE_SIMUL1 AND X.CHAVE_IT2=Y.CHAVE_SIMUL2") -> ON X.CHAVE_IT1=Y.CHAVE_SIMUL1 AND X.CHAVE_IT2=Y.CHAVE_SIMUL2 | M12: =+IF(D12="Coerência",+IF(LEFT(H12,5)="FLOAT","SELECT '"&UPPER(B12)&"' AS TABELA, '"&UPPER(D12)&"' AS TIPOLOGIA_TESTE,'"&E12&"' AS TABELA_LT,'"&F12&"' AS TABELA_SIMUL,'"&C12&"' AS CAMPO, "&_xlfn._LONGTEXT("'${ref_date}' AS REF_DATE, COUNT(*) AS NUM_REG, SUM(IF((ABS(COALESCE(CAST(X.CAMPO_IT AS DECIMAL(18,6)),0)-COALESCE(CAST(Y.CAMPO_SIMUL AS DECIMAL(18,6)),0))>0.000001) OR (X.CAMPO_IT IS NULL AND Y.CAMPO_SIMUL IS NOT NULL ) OR (X.CAMPO_IT IS NOT NULL AND Y.C","AMPO_SIMUL IS NULL),1,0)) AS NUM_REG_DIF,'")&MAX('3. Resultados'!K:K)+1&"' AS ID_EXEC, CURRENT_TIMESTAMP() AS TIME_EXEC FROM "&J12&" INNER JOIN "&K12&" "&L12,"SELECT '"&UPPER(B12)&"' AS TABELA, '"&UPPER(D12)&"' AS TIPOLOGIA_TESTE,'"&E12&"' AS TABELA_LT,'"&F12&"' AS TABELA_SIMUL,'"&C12&"' AS CAMPO, "&_xlfn._LONGTEXT("'${ref_date}' AS REF_DATE, COUNT(*) AS NUM_REG, SUM(IF(COALESCE(CAST(X.CAMPO_IT AS STRING),'')<>COALESCE(CAST(Y.CAMPO_SIMUL AS STRING),'') OR (X.CAMPO_IT IS NULL AND Y.CAMPO_SIMUL IS NOT NULL ) OR (X.CAMPO_IT IS NOT NULL AND Y.CAMPO_SIMUL IS NULL),1,0)) A","S NUM_REG_DIF,'")&MAX('3. Resultados'!L:L)+1&"' AS ID_EXEC, CURRENT_TIMESTAMP() AS TIME_EXEC FROM "&J12&" INNER JOIN "&K12&" "&L12)) -> SELECT 'UNIV_OPER' AS TABELA, 'COERÊNCIA' AS TIPOLOGIA_TESTE,'CD_LOAN_TAPES_BCE.LT001_UNIV_OPER' AS TABELA_LT,'BU_LOANTAPE_WORK.LT001_UNIV_OPER' AS TABELA_SIMUL,'contraparte' AS CAMPO, '${ref_date}' AS REF_DATE, COUNT(*) AS NUM_REG, SUM(IF(COALESCE(CAST(X.CAMPO_IT AS STRING),'')<>COALESCE(CAST(Y.CAMPO_SIMUL AS STRING),'') OR (X.CAMPO_IT IS NULL AND Y.CAMPO_SIMUL IS NOT NULL ) OR (X.CAMPO_IT IS NOT NULL AND Y.CAMPO_SIMUL IS NULL),1,0)) AS NUM_REG_DIF,'1' AS ID_EXEC, CURRENT_TIMESTAMP() AS TIME_EXEC FROM (SELECT concat(cempresa, cbalcao, cnumecta, zdeposit, ccontab_final_ifrs, ccontab_final_pcsb, ccontab_final_cargabal, ccontab_final) AS CHAVE_IT1, zcliente AS CHAVE_IT2, contraparte AS CAMPO_IT FROM CD_LOAN_TAPES_BCE.LT001_UNIV_OPER WHERE ref_date='${ref_date}' AND nome_perimetro='Individual Local' AND segmento='ESTR' AND ambito='PM' AND entidade='00100')X INNER JOIN (SELECT concat(cempresa, cbalcao, cnumecta, zdeposit, ccontab_final_ifrs, ccontab_final_pcsb, ccontab_final_cargabal, ccontab_final) AS CHAVE_SIMUL1, zcliente AS CHAVE_SIMUL2, contraparte AS CAMPO_SIMUL FROM BU_LOANTAPE_WORK.LT001_UNIV_OPER WHERE ref_date='${ref_date}' AND nome_perimetro='Individual Local' AND segmento='ESTR' AND ambito='PM' AND entidade='00100')Y ON X.CHAVE_IT1=Y.CHAVE_SIMUL1 AND X.CHAVE_IT2=Y.CHAVE_SIMUL2 | N12: =+"UNION ALL "&M12 -> UNION ALL SELECT 'UNIV_OPER' AS TABELA, 'COERÊNCIA' AS TIPOLOGIA_TESTE,'CD_LOAN_TAPES_BCE.LT001_UNIV_OPER' AS TABELA_LT,'BU_LOANTAPE_WORK.LT001_UNIV_OPER' AS TABELA_SIMUL,'contraparte' AS CAMPO, '${ref_date}' AS REF_DATE, COUNT(*) AS NUM_REG, SUM(IF(COALESCE(CAST(X.CAMPO_IT AS STRING),'')<>COALESCE(CAST(Y.CAMPO_SIMUL AS STRING),'') OR (X.CAMPO_IT IS NULL AND Y.CAMPO_SIMUL IS NOT NULL ) OR (X.CAMPO_IT IS NOT NULL AND Y.CAMPO_SIMUL IS NULL),1,0)) AS NUM_REG_DIF,'1' AS ID_EXEC, CURRENT_TIMESTAMP() AS TIME_EXEC FROM (SELECT concat(cempresa, cbalcao, cnumecta, zdeposit, ccontab_final_ifrs, ccontab_final_pcsb, ccontab_final_cargabal, ccontab_final) AS CHAVE_IT1, zcliente AS CHAVE_IT2, contraparte AS CAMPO_IT FROM CD_LOAN_TAPES_BCE.LT001_UNIV_OPER WHERE ref_date='${ref_date}' AND nome_perimetro='Individual Local' AND segmento='ESTR' AND ambito='PM' AND entidade='00100')X INNER JOIN (SELECT concat(cempresa, cbalcao, cnumecta, zdeposit, ccontab_final_ifrs, ccontab_final_pcsb, ccontab_final_cargabal, ccontab_final) AS CHAVE_SIMUL1, zcliente AS CHAVE_SIMUL2, contraparte AS CAMPO_SIMUL FROM BU_LOANTAPE_WORK.LT001_UNIV_OPER WHERE ref_date='${ref_date}' AND nome_perimetro='Individual Local' AND segmento='ESTR' AND ambito='PM' AND entidade='00100')Y ON X.CHAVE_IT1=Y.CHAVE_SIMUL1 AND X.CHAVE_IT2=Y.CHAVE_SIMUL2
A13: =+B13&C13 -> UNIV_OPERcontraparte_i | B13: UNIV_OPER | C13: contraparte_i | D13: Coerência | E13: =+UPPER('0. Instruções'!$D$35&"."&VLOOKUP(B13,'0. Instruções'!$C$27:$D$32,2,FALSE)) -> CD_LOAN_TAPES_BCE.LT001_UNIV_OPER | F13: =+UPPER('0. Instruções'!$D$36&"."&VLOOKUP(B13,'0. Instruções'!$C$27:$E$32,3,FALSE)) -> BU_LOANTAPE_WORK.LT001_UNIV_OPER | J13: =IF(VLOOKUP(B13,'0. Instruções'!$C$27:$G$32,5,FALSE)=0, "(SELECT "&VLOOKUP(B13,'0. Instruções'!$C$27:$G$32,4,FALSE)&" AS CHAVE_IT, "&C13&" AS CAMPO_IT FROM "&E13&" WHERE "&'0. Instruções'!$D$43&")X", "(SELECT "&VLOOKUP(B13,'0. Instruções'!$C$27:$G$32,4,FALSE)&" AS CHAVE_IT1, "&VLOOKUP(B13,'0. Instruções'!$C$27:$G$32,5,FALSE)&" AS CHAVE_IT2, "&C13&" AS CAMPO_IT FROM "&E13&" WHERE "&'0. Instruções'!$D$43&")X") -> (SELECT concat(cempresa, cbalcao, cnumecta, zdeposit, ccontab_final_ifrs, ccontab_final_pcsb, ccontab_final_cargabal, ccontab_final) AS CHAVE_IT1, zcliente AS CHAVE_IT2, contraparte_i AS CAMPO_IT FROM CD_LOAN_TAPES_BCE.LT001_UNIV_OPER WHERE ref_date='${ref_date}' AND nome_perimetro='Individual Local' AND segmento='ESTR' AND ambito='PM' AND entidade='00100')X | K13: =IF(VLOOKUP(B13,'0. Instruções'!$C$27:$G$32,5,FALSE)=0, "(SELECT "&VLOOKUP(B13,'0. Instruções'!$C$27:$G$32,4,FALSE)&" AS CHAVE_SIMUL, "&C13&" AS CAMPO_SIMUL FROM "&F13&" WHERE "&'0. Instruções'!$D$42&")Y", "(SELECT "&VLOOKUP(B13,'0. Instruções'!$C$27:$G$32,4,FALSE)&" AS CHAVE_SIMUL1, "&VLOOKUP(B13,'0. Instruções'!$C$27:$G$32,5,FALSE)&" AS CHAVE_SIMUL2, "&C13&" AS CAMPO_SIMUL FROM "&F13&" WHERE "&'0. Instruções'!$D$42&")Y") -> (SELECT concat(cempresa, cbalcao, cnumecta, zdeposit, ccontab_final_ifrs, ccontab_final_pcsb, ccontab_final_cargabal, ccontab_final) AS CHAVE_SIMUL1, zcliente AS CHAVE_SIMUL2, contraparte_i AS CAMPO_SIMUL FROM BU_LOANTAPE_WORK.LT001_UNIV_OPER WHERE ref_date='${ref_date}' AND nome_perimetro='Individual Local' AND segmento='ESTR' AND ambito='PM' AND entidade='00100')Y | L13: =IF(VLOOKUP(B13,'0. Instruções'!$C$27:$G$32,5,FALSE)=0, "ON X.CHAVE_IT=Y.CHAVE_SIMUL", "ON X.CHAVE_IT1=Y.CHAVE_SIMUL1 AND X.CHAVE_IT2=Y.CHAVE_SIMUL2") -> ON X.CHAVE_IT1=Y.CHAVE_SIMUL1 AND X.CHAVE_IT2=Y.CHAVE_SIMUL2 | M13: =+IF(D13="Coerência",+IF(LEFT(H13,5)="FLOAT","SELECT '"&UPPER(B13)&"' AS TABELA, '"&UPPER(D13)&"' AS TIPOLOGIA_TESTE,'"&E13&"' AS TABELA_LT,'"&F13&"' AS TABELA_SIMUL,'"&C13&"' AS CAMPO, "&_xlfn._LONGTEXT("'${ref_date}' AS REF_DATE, COUNT(*) AS NUM_REG, SUM(IF((ABS(COALESCE(CAST(X.CAMPO_IT AS DECIMAL(18,6)),0)-COALESCE(CAST(Y.CAMPO_SIMUL AS DECIMAL(18,6)),0))>0.000001) OR (X.CAMPO_IT IS NULL AND Y.CAMPO_SIMUL IS NOT NULL ) OR (X.CAMPO_IT IS NOT NULL AND Y.C","AMPO_SIMUL IS NULL),1,0)) AS NUM_REG_DIF,'")&MAX('3. Resultados'!K:K)+1&"' AS ID_EXEC, CURRENT_TIMESTAMP() AS TIME_EXEC FROM "&J13&" INNER JOIN "&K13&" "&L13,"SELECT '"&UPPER(B13)&"' AS TABELA, '"&UPPER(D13)&"' AS TIPOLOGIA_TESTE,'"&E13&"' AS TABELA_LT,'"&F13&"' AS TABELA_SIMUL,'"&C13&"' AS CAMPO, "&_xlfn._LONGTEXT("'${ref_date}' AS REF_DATE, COUNT(*) AS NUM_REG, SUM(IF(COALESCE(CAST(X.CAMPO_IT AS STRING),'')<>COALESCE(CAST(Y.CAMPO_SIMUL AS STRING),'') OR (X.CAMPO_IT IS NULL AND Y.CAMPO_SIMUL IS NOT NULL ) OR (X.CAMPO_IT IS NOT NULL AND Y.CAMPO_SIMUL IS NULL),1,0)) A","S NUM_REG_DIF,'")&MAX('3. Resultados'!L:L)+1&"' AS ID_EXEC, CURRENT_TIMESTAMP() AS TIME_EXEC FROM "&J13&" INNER JOIN "&K13&" "&L13)) -> SELECT 'UNIV_OPER' AS TABELA, 'COERÊNCIA' AS TIPOLOGIA_TESTE,'CD_LOAN_TAPES_BCE.LT001_UNIV_OPER' AS TABELA_LT,'BU_LOANTAPE_WORK.LT001_UNIV_OPER' AS TABELA_SIMUL,'contraparte_i' AS CAMPO, '${ref_date}' AS REF_DATE, COUNT(*) AS NUM_REG, SUM(IF(COALESCE(CAST(X.CAMPO_IT AS STRING),'')<>COALESCE(CAST(Y.CAMPO_SIMUL AS STRING),'') OR (X.CAMPO_IT IS NULL AND Y.CAMPO_SIMUL IS NOT NULL ) OR (X.CAMPO_IT IS NOT NULL AND Y.CAMPO_SIMUL IS NULL),1,0)) AS NUM_REG_DIF,'1' AS ID_EXEC, CURRENT_TIMESTAMP() AS TIME_EXEC FROM (SELECT concat(cempresa, cbalcao, cnumecta, zdeposit, ccontab_final_ifrs, ccontab_final_pcsb, ccontab_final_cargabal, ccontab_final) AS CHAVE_IT1, zcliente AS CHAVE_IT2, contraparte_i AS CAMPO_IT FROM CD_LOAN_TAPES_BCE.LT001_UNIV_OPER WHERE ref_date='${ref_date}' AND nome_perimetro='Individual Local' AND segmento='ESTR' AND ambito='PM' AND entidade='00100')X INNER JOIN (SELECT concat(cempresa, cbalcao, cnumecta, zdeposit, ccontab_final_ifrs, ccontab_final_pcsb, ccontab_final_cargabal, ccontab_final) AS CHAVE_SIMUL1, zcliente AS CHAVE_SIMUL2, contraparte_i AS CAMPO_SIMUL FROM BU_LOANTAPE_WORK.LT001_UNIV_OPER WHERE ref_date='${ref_date}' AND nome_perimetro='Individual Local' AND segmento='ESTR' AND ambito='PM' AND entidade='00100')Y ON X.CHAVE_IT1=Y.CHAVE_SIMUL1 AND X.CHAVE_IT2=Y.CHAVE_SIMUL2 | N13: =+"UNION ALL "&M13 -> UNION ALL SELECT 'UNIV_OPER' AS TABELA, 'COERÊNCIA' AS TIPOLOGIA_TESTE,'CD_LOAN_TAPES_BCE.LT001_UNIV_OPER' AS TABELA_LT,'BU_LOANTAPE_WORK.LT001_UNIV_OPER' AS TABELA_SIMUL,'contraparte_i' AS CAMPO, '${ref_date}' AS REF_DATE, COUNT(*) AS NUM_REG, SUM(IF(COALESCE(CAST(X.CAMPO_IT AS STRING),'')<>COALESCE(CAST(Y.CAMPO_SIMUL AS STRING),'') OR (X.CAMPO_IT IS NULL AND Y.CAMPO_SIMUL IS NOT NULL ) OR (X.CAMPO_IT IS NOT NULL AND Y.CAMPO_SIMUL IS NULL),1,0)) AS NUM_REG_DIF,'1' AS ID_EXEC, CURRENT_TIMESTAMP() AS TIME_EXEC FROM (SELECT concat(cempresa, cbalcao, cnumecta, zdeposit, ccontab_final_ifrs, ccontab_final_pcsb, ccontab_final_cargabal, ccontab_final) AS CHAVE_IT1, zcliente AS CHAVE_IT2, contraparte_i AS CAMPO_IT FROM CD_LOAN_TAPES_BCE.LT001_UNIV_OPER WHERE ref_date='${ref_date}' AND nome_perimetro='Individual Local' AND segmento='ESTR' AND ambito='PM' AND entidade='00100')X INNER JOIN (SELECT concat(cempresa, cbalcao, cnumecta, zdeposit, ccontab_final_ifrs, ccontab_final_pcsb, ccontab_final_cargabal, ccontab_final) AS CHAVE_SIMUL1, zcliente AS CHAVE_SIMUL2, contraparte_i AS CAMPO_SIMUL FROM BU_LOANTAPE_WORK.LT001_UNIV_OPER WHERE ref_date='${ref_date}' AND nome_perimetro='Individual Local' AND segmento='ESTR' AND ambito='PM' AND entidade='00100')Y ON X.CHAVE_IT1=Y.CHAVE_SIMUL1 AND X.CHAVE_IT2=Y.CHAVE_SIMUL2
A14: =+B14&C14 -> UNIV_OPERproduto | B14: UNIV_OPER | C14: produto | D14: Coerência | E14: =+UPPER('0. Instruções'!$D$35&"."&VLOOKUP(B14,'0. Instruções'!$C$27:$D$32,2,FALSE)) -> CD_LOAN_TAPES_BCE.LT001_UNIV_OPER | F14: =+UPPER('0. Instruções'!$D$36&"."&VLOOKUP(B14,'0. Instruções'!$C$27:$E$32,3,FALSE)) -> BU_LOANTAPE_WORK.LT001_UNIV_OPER | J14: =IF(VLOOKUP(B14,'0. Instruções'!$C$27:$G$32,5,FALSE)=0, "(SELECT "&VLOOKUP(B14,'0. Instruções'!$C$27:$G$32,4,FALSE)&" AS CHAVE_IT, "&C14&" AS CAMPO_IT FROM "&E14&" WHERE "&'0. Instruções'!$D$43&")X", "(SELECT "&VLOOKUP(B14,'0. Instruções'!$C$27:$G$32,4,FALSE)&" AS CHAVE_IT1, "&VLOOKUP(B14,'0. Instruções'!$C$27:$G$32,5,FALSE)&" AS CHAVE_IT2, "&C14&" AS CAMPO_IT FROM "&E14&" WHERE "&'0. Instruções'!$D$43&")X") -> (SELECT concat(cempresa, cbalcao, cnumecta, zdeposit, ccontab_final_ifrs, ccontab_final_pcsb, ccontab_final_cargabal, ccontab_final) AS CHAVE_IT1, zcliente AS CHAVE_IT2, produto AS CAMPO_IT FROM CD_LOAN_TAPES_BCE.LT001_UNIV_OPER WHERE ref_date='${ref_date}' AND nome_perimetro='Individual Local' AND segmento='ESTR' AND ambito='PM' AND entidade='00100')X | K14: =IF(VLOOKUP(B14,'0. Instruções'!$C$27:$G$32,5,FALSE)=0, "(SELECT "&VLOOKUP(B14,'0. Instruções'!$C$27:$G$32,4,FALSE)&" AS CHAVE_SIMUL, "&C14&" AS CAMPO_SIMUL FROM "&F14&" WHERE "&'0. Instruções'!$D$42&")Y", "(SELECT "&VLOOKUP(B14,'0. Instruções'!$C$27:$G$32,4,FALSE)&" AS CHAVE_SIMUL1, "&VLOOKUP(B14,'0. Instruções'!$C$27:$G$32,5,FALSE)&" AS CHAVE_SIMUL2, "&C14&" AS CAMPO_SIMUL FROM "&F14&" WHERE "&'0. Instruções'!$D$42&")Y") -> (SELECT concat(cempresa, cbalcao, cnumecta, zdeposit, ccontab_final_ifrs, ccontab_final_pcsb, ccontab_final_cargabal, ccontab_final) AS CHAVE_SIMUL1, zcliente AS CHAVE_SIMUL2, produto AS CAMPO_SIMUL FROM BU_LOANTAPE_WORK.LT001_UNIV_OPER WHERE ref_date='${ref_date}' AND nome_perimetro='Individual Local' AND segmento='ESTR' AND ambito='PM' AND entidade='00100')Y | L14: =IF(VLOOKUP(B14,'0. Instruções'!$C$27:$G$32,5,FALSE)=0, "ON X.CHAVE_IT=Y.CHAVE_SIMUL", "ON X.CHAVE_IT1=Y.CHAVE_SIMUL1 AND X.CHAVE_IT2=Y.CHAVE_SIMUL2") -> ON X.CHAVE_IT1=Y.CHAVE_SIMUL1 AND X.CHAVE_IT2=Y.CHAVE_SIMUL2 | M14: =+IF(D14="Coerência",+IF(LEFT(H14,5)="FLOAT","SELECT '"&UPPER(B14)&"' AS TABELA, '"&UPPER(D14)&"' AS TIPOLOGIA_TESTE,'"&E14&"' AS TABELA_LT,'"&F14&"' AS TABELA_SIMUL,'"&C14&"' AS CAMPO, "&_xlfn._LONGTEXT("'${ref_date}' AS REF_DATE, COUNT(*) AS NUM_REG, SUM(IF((ABS(COALESCE(CAST(X.CAMPO_IT AS DECIMAL(18,6)),0)-COALESCE(CAST(Y.CAMPO_SIMUL AS DECIMAL(18,6)),0))>0.000001) OR (X.CAMPO_IT IS NULL AND Y.CAMPO_SIMUL IS NOT NULL ) OR (X.CAMPO_IT IS NOT NULL AND Y.C","AMPO_SIMUL IS NULL),1,0)) AS NUM_REG_DIF,'")&MAX('3. Resultados'!K:K)+1&"' AS ID_EXEC, CURRENT_TIMESTAMP() AS TIME_EXEC FROM "&J14&" INNER JOIN "&K14&" "&L14,"SELECT '"&UPPER(B14)&"' AS TABELA, '"&UPPER(D14)&"' AS TIPOLOGIA_TESTE,'"&E14&"' AS TABELA_LT,'"&F14&"' AS TABELA_SIMUL,'"&C14&"' AS CAMPO, "&_xlfn._LONGTEXT("'${ref_date}' AS REF_DATE, COUNT(*) AS NUM_REG, SUM(IF(COALESCE(CAST(X.CAMPO_IT AS STRING),'')<>COALESCE(CAST(Y.CAMPO_SIMUL AS STRING),'') OR (X.CAMPO_IT IS NULL AND Y.CAMPO_SIMUL IS NOT NULL ) OR (X.CAMPO_IT IS NOT NULL AND Y.CAMPO_SIMUL IS NULL),1,0)) A","S NUM_REG_DIF,'")&MAX('3. Resultados'!L:L)+1&"' AS ID_EXEC, CURRENT_TIMESTAMP() AS TIME_EXEC FROM "&J14&" INNER JOIN "&K14&" "&L14)) -> SELECT 'UNIV_OPER' AS TABELA, 'COERÊNCIA' AS TIPOLOGIA_TESTE,'CD_LOAN_TAPES_BCE.LT001_UNIV_OPER' AS TABELA_LT,'BU_LOANTAPE_WORK.LT001_UNIV_OPER' AS TABELA_SIMUL,'produto' AS CAMPO, '${ref_date}' AS REF_DATE, COUNT(*) AS NUM_REG, SUM(IF(COALESCE(CAST(X.CAMPO_IT AS STRING),'')<>COALESCE(CAST(Y.CAMPO_SIMUL AS STRING),'') OR (X.CAMPO_IT IS NULL AND Y.CAMPO_SIMUL IS NOT NULL ) OR (X.CAMPO_IT IS NOT NULL AND Y.CAMPO_SIMUL IS NULL),1,0)) AS NUM_REG_DIF,'1' AS ID_EXEC, CURRENT_TIMESTAMP() AS TIME_EXEC FROM (SELECT concat(cempresa, cbalcao, cnumecta, zdeposit, ccontab_final_ifrs, ccontab_final_pcsb, ccontab_final_cargabal, ccontab_final) AS CHAVE_IT1, zcliente AS CHAVE_IT2, produto AS CAMPO_IT FROM CD_LOAN_TAPES_BCE.LT001_UNIV_OPER WHERE ref_date='${ref_date}' AND nome_perimetro='Individual Local' AND segmento='ESTR' AND ambito='PM' AND entidade='00100')X INNER JOIN (SELECT concat(cempresa, cbalcao, cnumecta, zdeposit, ccontab_final_ifrs, ccontab_final_pcsb, ccontab_final_cargabal, ccontab_final) AS CHAVE_SIMUL1, zcliente AS CHAVE_SIMUL2, produto AS CAMPO_SIMUL FROM BU_LOANTAPE_WORK.LT001_UNIV_OPER WHERE ref_date='${ref_date}' AND nome_perimetro='Individual Local' AND segmento='ESTR' AND ambito='PM' AND entidade='00100')Y ON X.CHAVE_IT1=Y.CHAVE_SIMUL1 AND X.CHAVE_IT2=Y.CHAVE_SIMUL2 | N14: =+"UNION ALL "&M14 -> UNION ALL SELECT 'UNIV_OPER' AS TABELA, 'COERÊNCIA' AS TIPOLOGIA_TESTE,'CD_LOAN_TAPES_BCE.LT001_UNIV_OPER' AS TABELA_LT,'BU_LOANTAPE_WORK.LT001_UNIV_OPER' AS TABELA_SIMUL,'produto' AS CAMPO, '${ref_date}' AS REF_DATE, COUNT(*) AS NUM_REG, SUM(IF(COALESCE(CAST(X.CAMPO_IT AS STRING),'')<>COALESCE(CAST(Y.CAMPO_SIMUL AS STRING),'') OR (X.CAMPO_IT IS NULL AND Y.CAMPO_SIMUL IS NOT NULL ) OR (X.CAMPO_IT IS NOT NULL AND Y.CAMPO_SIMUL IS NULL),1,0)) AS NUM_REG_DIF,'1' AS ID_EXEC, CURRENT_TIMESTAMP() AS TIME_EXEC FROM (SELECT concat(cempresa, cbalcao, cnumecta, zdeposit, ccontab_final_ifrs, ccontab_final_pcsb, ccontab_final_cargabal, ccontab_final) AS CHAVE_IT1, zcliente AS CHAVE_IT2, produto AS CAMPO_IT FROM CD_LOAN_TAPES_BCE.LT001_UNIV_OPER WHERE ref_date='${ref_date}' AND nome_perimetro='Individual Local' AND segmento='ESTR' AND ambito='PM' AND entidade='00100')X INNER JOIN (SELECT concat(cempresa, cbalcao, cnumecta, zdeposit, ccontab_final_ifrs, ccontab_final_pcsb, ccontab_final_cargabal, ccontab_final) AS CHAVE_SIMUL1, zcliente AS CHAVE_SIMUL2, produto AS CAMPO_SIMUL FROM BU_LOANTAPE_WORK.LT001_UNIV_OPER WHERE ref_date='${ref_date}' AND nome_perimetro='Individual Local' AND segmento='ESTR' AND ambito='PM' AND entidade='00100')Y ON X.CHAVE_IT1=Y.CHAVE_SIMUL1 AND X.CHAVE_IT2=Y.CHAVE_SIMUL2
A15: =+B15&C15 -> UNIV_OPERtipo_conta | B15: UNIV_OPER | C15: tipo_conta | D15: Coerência | E15: =+UPPER('0. Instruções'!$D$35&"."&VLOOKUP(B15,'0. Instruções'!$C$27:$D$32,2,FALSE)) -> CD_LOAN_TAPES_BCE.LT001_UNIV_OPER | F15: =+UPPER('0. Instruções'!$D$36&"."&VLOOKUP(B15,'0. Instruções'!$C$27:$E$32,3,FALSE)) -> BU_LOANTAPE_WORK.LT001_UNIV_OPER | J15: =IF(VLOOKUP(B15,'0. Instruções'!$C$27:$G$32,5,FALSE)=0, "(SELECT "&VLOOKUP(B15,'0. Instruções'!$C$27:$G$32,4,FALSE)&" AS CHAVE_IT, "&C15&" AS CAMPO_IT FROM "&E15&" WHERE "&'0. Instruções'!$D$43&")X", "(SELECT "&VLOOKUP(B15,'0. Instruções'!$C$27:$G$32,4,FALSE)&" AS CHAVE_IT1, "&VLOOKUP(B15,'0. Instruções'!$C$27:$G$32,5,FALSE)&" AS CHAVE_IT2, "&C15&" AS CAMPO_IT FROM "&E15&" WHERE "&'0. Instruções'!$D$43&")X") -> (SELECT concat(cempresa, cbalcao, cnumecta, zdeposit, ccontab_final_ifrs, ccontab_final_pcsb, ccontab_final_cargabal, ccontab_final) AS CHAVE_IT1, zcliente AS CHAVE_IT2, tipo_conta AS CAMPO_IT FROM CD_LOAN_TAPES_BCE.LT001_UNIV_OPER WHERE ref_date='${ref_date}' AND nome_perimetro='Individual Local' AND segmento='ESTR' AND ambito='PM' AND entidade='00100')X | K15: =IF(VLOOKUP(B15,'0. Instruções'!$C$27:$G$32,5,FALSE)=0, "(SELECT "&VLOOKUP(B15,'0. Instruções'!$C$27:$G$32,4,FALSE)&" AS CHAVE_SIMUL, "&C15&" AS CAMPO_SIMUL FROM "&F15&" WHERE "&'0. Instruções'!$D$42&")Y", "(SELECT "&VLOOKUP(B15,'0. Instruções'!$C$27:$G$32,4,FALSE)&" AS CHAVE_SIMUL1, "&VLOOKUP(B15,'0. Instruções'!$C$27:$G$32,5,FALSE)&" AS CHAVE_SIMUL2, "&C15&" AS CAMPO_SIMUL FROM "&F15&" WHERE "&'0. Instruções'!$D$42&")Y") -> (SELECT concat(cempresa, cbalcao, cnumecta, zdeposit, ccontab_final_ifrs, ccontab_final_pcsb, ccontab_final_cargabal, ccontab_final) AS CHAVE_SIMUL1, zcliente AS CHAVE_SIMUL2, tipo_conta AS CAMPO_SIMUL FROM BU_LOANTAPE_WORK.LT001_UNIV_OPER WHERE ref_date='${ref_date}' AND nome_perimetro='Individual Local' AND segmento='ESTR' AND ambito='PM' AND entidade='00100')Y | L15: =IF(VLOOKUP(B15,'0. Instruções'!$C$27:$G$32,5,FALSE)=0, "ON X.CHAVE_IT=Y.CHAVE_SIMUL", "ON X.CHAVE_IT1=Y.CHAVE_SIMUL1 AND X.CHAVE_IT2=Y.CHAVE_SIMUL2") -> ON X.CHAVE_IT1=Y.CHAVE_SIMUL1 AND X.CHAVE_IT2=Y.CHAVE_SIMUL2 | M15: =+IF(D15="Coerência",+IF(LEFT(H15,5)="FLOAT","SELECT '"&UPPER(B15)&"' AS TABELA, '"&UPPER(D15)&"' AS TIPOLOGIA_TESTE,'"&E15&"' AS TABELA_LT,'"&F15&"' AS TABELA_SIMUL,'"&C15&"' AS CAMPO, "&_xlfn._LONGTEXT("'${ref_date}' AS REF_DATE, COUNT(*) AS NUM_REG, SUM(IF((ABS(COALESCE(CAST(X.CAMPO_IT AS DECIMAL(18,6)),0)-COALESCE(CAST(Y.CAMPO_SIMUL AS DECIMAL(18,6)),0))>0.000001) OR (X.CAMPO_IT IS NULL AND Y.CAMPO_SIMUL IS NOT NULL ) OR (X.CAMPO_IT IS NOT NULL AND Y.C","AMPO_SIMUL IS NULL),1,0)) AS NUM_REG_DIF,'")&MAX('3. Resultados'!K:K)+1&"' AS ID_EXEC, CURRENT_TIMESTAMP() AS TIME_EXEC FROM "&J15&" INNER JOIN "&K15&" "&L15,"SELECT '"&UPPER(B15)&"' AS TABELA, '"&UPPER(D15)&"' AS TIPOLOGIA_TESTE,'"&E15&"' AS TABELA_LT,'"&F15&"' AS TABELA_SIMUL,'"&C15&"' AS CAMPO, "&_xlfn._LONGTEXT("'${ref_date}' AS REF_DATE, COUNT(*) AS NUM_REG, SUM(IF(COALESCE(CAST(X.CAMPO_IT AS STRING),'')<>COALESCE(CAST(Y.CAMPO_SIMUL AS STRING),'') OR (X.CAMPO_IT IS NULL AND Y.CAMPO_SIMUL IS NOT NULL ) OR (X.CAMPO_IT IS NOT NULL AND Y.CAMPO_SIMUL IS NULL),1,0)) A","S NUM_REG_DIF,'")&MAX('3. Resultados'!L:L)+1&"' AS ID_EXEC, CURRENT_TIMESTAMP() AS TIME_EXEC FROM "&J15&" INNER JOIN "&K15&" "&L15)) -> SELECT 'UNIV_OPER' AS TABELA, 'COERÊNCIA' AS TIPOLOGIA_TESTE,'CD_LOAN_TAPES_BCE.LT001_UNIV_OPER' AS TABELA_LT,'BU_LOANTAPE_WORK.LT001_UNIV_OPER' AS TABELA_SIMUL,'tipo_conta' AS CAMPO, '${ref_date}' AS REF_DATE, COUNT(*) AS NUM_REG, SUM(IF(COALESCE(CAST(X.CAMPO_IT AS STRING),'')<>COALESCE(CAST(Y.CAMPO_SIMUL AS STRING),'') OR (X.CAMPO_IT IS NULL AND Y.CAMPO_SIMUL IS NOT NULL ) OR (X.CAMPO_IT IS NOT NULL AND Y.CAMPO_SIMUL IS NULL),1,0)) AS NUM_REG_DIF,'1' AS ID_EXEC, CURRENT_TIMESTAMP() AS TIME_EXEC FROM (SELECT concat(cempresa, cbalcao, cnumecta, zdeposit, ccontab_final_ifrs, ccontab_final_pcsb, ccontab_final_cargabal, ccontab_final) AS CHAVE_IT1, zcliente AS CHAVE_IT2, tipo_conta AS CAMPO_IT FROM CD_LOAN_TAPES_BCE.LT001_UNIV_OPER WHERE ref_date='${ref_date}' AND nome_perimetro='Individual Local' AND segmento='ESTR' AND ambito='PM' AND entidade='00100')X INNER JOIN (SELECT concat(cempresa, cbalcao, cnumecta, zdeposit, ccontab_final_ifrs, ccontab_final_pcsb, ccontab_final_cargabal, ccontab_final) AS CHAVE_SIMUL1, zcliente AS CHAVE_SIMUL2, tipo_conta AS CAMPO_SIMUL FROM BU_LOANTAPE_WORK.LT001_UNIV_OPER WHERE ref_date='${ref_date}' AND nome_perimetro='Individual Local' AND segmento='ESTR' AND ambito='PM' AND entidade='00100')Y ON X.CHAVE_IT1=Y.CHAVE_SIMUL1 AND X.CHAVE_IT2=Y.CHAVE_SIMUL2 | N15: =+"UNION ALL "&M15 -> UNION ALL SELECT 'UNIV_OPER' AS TABELA, 'COERÊNCIA' AS TIPOLOGIA_TESTE,'CD_LOAN_TAPES_BCE.LT001_UNIV_OPER' AS TABELA_LT,'BU_LOANTAPE_WORK.LT001_UNIV_OPER' AS TABELA_SIMUL,'tipo_conta' AS CAMPO, '${ref_date}' AS REF_DATE, COUNT(*) AS NUM_REG, SUM(IF(COALESCE(CAST(X.CAMPO_IT AS STRING),'')<>COALESCE(CAST(Y.CAMPO_SIMUL AS STRING),'') OR (X.CAMPO_IT IS NULL AND Y.CAMPO_SIMUL IS NOT NULL ) OR (X.CAMPO_IT IS NOT NULL AND Y.CAMPO_SIMUL IS NULL),1,0)) AS NUM_REG_DIF,'1' AS ID_EXEC, CURRENT_TIMESTAMP() AS TIME_EXEC FROM (SELECT concat(cempresa, cbalcao, cnumecta, zdeposit, ccontab_final_ifrs, ccontab_final_pcsb, ccontab_final_cargabal, ccontab_final) AS CHAVE_IT1, zcliente AS CHAVE_IT2, tipo_conta AS CAMPO_IT FROM CD_LOAN_TAPES_BCE.LT001_UNIV_OPER WHERE ref_date='${ref_date}' AND nome_perimetro='Individual Local' AND segmento='ESTR' AND ambito='PM' AND entidade='00100')X INNER JOIN (SELECT concat(cempresa, cbalcao, cnumecta, zdeposit, ccontab_final_ifrs, ccontab_final_pcsb, ccontab_final_cargabal, ccontab_final) AS CHAVE_SIMUL1, zcliente AS CHAVE_SIMUL2, tipo_conta AS CAMPO_SIMUL FROM BU_LOANTAPE_WORK.LT001_UNIV_OPER WHERE ref_date='${ref_date}' AND nome_perimetro='Individual Local' AND segmento='ESTR' AND ambito='PM' AND entidade='00100')Y ON X.CHAVE_IT1=Y.CHAVE_SIMUL1 AND X.CHAVE_IT2=Y.CHAVE_SIMUL2
A16: =+B16&C16 -> UNIV_OPERbruto_imparidade | B16: UNIV_OPER | C16: bruto_imparidade | D16: Coerência | E16: =+UPPER('0. Instruções'!$D$35&"."&VLOOKUP(B16,'0. Instruções'!$C$27:$D$32,2,FALSE)) -> CD_LOAN_TAPES_BCE.LT001_UNIV_OPER | F16: =+UPPER('0. Instruções'!$D$36&"."&VLOOKUP(B16,'0. Instruções'!$C$27:$E$32,3,FALSE)) -> BU_LOANTAPE_WORK.LT001_UNIV_OPER | J16: =IF(VLOOKUP(B16,'0. Instruções'!$C$27:$G$32,5,FALSE)=0, "(SELECT "&VLOOKUP(B16,'0. Instruções'!$C$27:$G$32,4,FALSE)&" AS CHAVE_IT, "&C16&" AS CAMPO_IT FROM "&E16&" WHERE "&'0. Instruções'!$D$43&")X", "(SELECT "&VLOOKUP(B16,'0. Instruções'!$C$27:$G$32,4,FALSE)&" AS CHAVE_IT1, "&VLOOKUP(B16,'0. Instruções'!$C$27:$G$32,5,FALSE)&" AS CHAVE_IT2, "&C16&" AS CAMPO_IT FROM "&E16&" WHERE "&'0. Instruções'!$D$43&")X") -> (SELECT concat(cempresa, cbalcao, cnumecta, zdeposit, ccontab_final_ifrs, ccontab_final_pcsb, ccontab_final_cargabal, ccontab_final) AS CHAVE_IT1, zcliente AS CHAVE_IT2, bruto_imparidade AS CAMPO_IT FROM CD_LOAN_TAPES_BCE.LT001_UNIV_OPER WHERE ref_date='${ref_date}' AND nome_perimetro='Individual Local' AND segmento='ESTR' AND ambito='PM' AND entidade='00100')X | K16: =IF(VLOOKUP(B16,'0. Instruções'!$C$27:$G$32,5,FALSE)=0, "(SELECT "&VLOOKUP(B16,'0. Instruções'!$C$27:$G$32,4,FALSE)&" AS CHAVE_SIMUL, "&C16&" AS CAMPO_SIMUL FROM "&F16&" WHERE "&'0. Instruções'!$D$42&")Y", "(SELECT "&VLOOKUP(B16,'0. Instruções'!$C$27:$G$32,4,FALSE)&" AS CHAVE_SIMUL1, "&VLOOKUP(B16,'0. Instruções'!$C$27:$G$32,5,FALSE)&" AS CHAVE_SIMUL2, "&C16&" AS CAMPO_SIMUL FROM "&F16&" WHERE "&'0. Instruções'!$D$42&")Y") -> (SELECT concat(cempresa, cbalcao, cnumecta, zdeposit, ccontab_final_ifrs, ccontab_final_pcsb, ccontab_final_cargabal, ccontab_final) AS CHAVE_SIMUL1, zcliente AS CHAVE_SIMUL2, bruto_imparidade AS CAMPO_SIMUL FROM BU_LOANTAPE_WORK.LT001_UNIV_OPER WHERE ref_date='${ref_date}' AND nome_perimetro='Individual Local' AND segmento='ESTR' AND ambito='PM' AND entidade='00100')Y | L16: =IF(VLOOKUP(B16,'0. Instruções'!$C$27:$G$32,5,FALSE)=0, "ON X.CHAVE_IT=Y.CHAVE_SIMUL", "ON X.CHAVE_IT1=Y.CHAVE_SIMUL1 AND X.CHAVE_IT2=Y.CHAVE_SIMUL2") -> ON X.CHAVE_IT1=Y.CHAVE_SIMUL1 AND X.CHAVE_IT2=Y.CHAVE_SIMUL2 | M16: =+IF(D16="Coerência",+IF(LEFT(H16,5)="FLOAT","SELECT '"&UPPER(B16)&"' AS TABELA, '"&UPPER(D16)&"' AS TIPOLOGIA_TESTE,'"&E16&"' AS TABELA_LT,'"&F16&"' AS TABELA_SIMUL,'"&C16&"' AS CAMPO, "&_xlfn._LONGTEXT("'${ref_date}' AS REF_DATE, COUNT(*) AS NUM_REG, SUM(IF((ABS(COALESCE(CAST(X.CAMPO_IT AS DECIMAL(18,6)),0)-COALESCE(CAST(Y.CAMPO_SIMUL AS DECIMAL(18,6)),0))>0.000001) OR (X.CAMPO_IT IS NULL AND Y.CAMPO_SIMUL IS NOT NULL ) OR (X.CAMPO_IT IS NOT NULL AND Y.C","AMPO_SIMUL IS NULL),1,0)) AS NUM_REG_DIF,'")&MAX('3. Resultados'!K:K)+1&"' AS ID_EXEC, CURRENT_TIMESTAMP() AS TIME_EXEC FROM "&J16&" INNER JOIN "&K16&" "&L16,"SELECT '"&UPPER(B16)&"' AS TABELA, '"&UPPER(D16)&"' AS TIPOLOGIA_TESTE,'"&E16&"' AS TABELA_LT,'"&F16&"' AS TABELA_SIMUL,'"&C16&"' AS CAMPO, "&_xlfn._LONGTEXT("'${ref_date}' AS REF_DATE, COUNT(*) AS NUM_REG, SUM(IF(COALESCE(CAST(X.CAMPO_IT AS STRING),'')<>COALESCE(CAST(Y.CAMPO_SIMUL AS STRING),'') OR (X.CAMPO_IT IS NULL AND Y.CAMPO_SIMUL IS NOT NULL ) OR (X.CAMPO_IT IS NOT NULL AND Y.CAMPO_SIMUL IS NULL),1,0)) A","S NUM_REG_DIF,'")&MAX('3. Resultados'!L:L)+1&"' AS ID_EXEC, CURRENT_TIMESTAMP() AS TIME_EXEC FROM "&J16&" INNER JOIN "&K16&" "&L16)) -> SELECT 'UNIV_OPER' AS TABELA, 'COERÊNCIA' AS TIPOLOGIA_TESTE,'CD_LOAN_TAPES_BCE.LT001_UNIV_OPER' AS TABELA_LT,'BU_LOANTAPE_WORK.LT001_UNIV_OPER' AS TABELA_SIMUL,'bruto_imparidade' AS CAMPO, '${ref_date}' AS REF_DATE, COUNT(*) AS NUM_REG, SUM(IF(COALESCE(CAST(X.CAMPO_IT AS STRING),'')<>COALESCE(CAST(Y.CAMPO_SIMUL AS STRING),'') OR (X.CAMPO_IT IS NULL AND Y.CAMPO_SIMUL IS NOT NULL ) OR (X.CAMPO_IT IS NOT NULL AND Y.CAMPO_SIMUL IS NULL),1,0)) AS NUM_REG_DIF,'1' AS ID_EXEC, CURRENT_TIMESTAMP() AS TIME_EXEC FROM (SELECT concat(cempresa, cbalcao, cnumecta, zdeposit, ccontab_final_ifrs, ccontab_final_pcsb, ccontab_final_cargabal, ccontab_final) AS CHAVE_IT1, zcliente AS CHAVE_IT2, bruto_imparidade AS CAMPO_IT FROM CD_LOAN_TAPES_BCE.LT001_UNIV_OPER WHERE ref_date='${ref_date}' AND nome_perimetro='Individual Local' AND segmento='ESTR' AND ambito='PM' AND entidade='00100')X INNER JOIN (SELECT concat(cempresa, cbalcao, cnumecta, zdeposit, ccontab_final_ifrs, ccontab_final_pcsb, ccontab_final_cargabal, ccontab_final) AS CHAVE_SIMUL1, zcliente AS CHAVE_SIMUL2, bruto_imparidade AS CAMPO_SIMUL FROM BU_LOANTAPE_WORK.LT001_UNIV_OPER WHERE ref_date='${ref_date}' AND nome_perimetro='Individual Local' AND segmento='ESTR' AND ambito='PM' AND entidade='00100')Y ON X.CHAVE_IT1=Y.CHAVE_SIMUL1 AND X.CHAVE_IT2=Y.CHAVE_SIMUL2 | N16: =+"UNION ALL "&M16 -> UNION ALL SELECT 'UNIV_OPER' AS TABELA, 'COERÊNCIA' AS TIPOLOGIA_TESTE,'CD_LOAN_TAPES_BCE.LT001_UNIV_OPER' AS TABELA_LT,'BU_LOANTAPE_WORK.LT001_UNIV_OPER' AS TABELA_SIMUL,'bruto_imparidade' AS CAMPO, '${ref_date}' AS REF_DATE, COUNT(*) AS NUM_REG, SUM(IF(COALESCE(CAST(X.CAMPO_IT AS STRING),'')<>COALESCE(CAST(Y.CAMPO_SIMUL AS STRING),'') OR (X.CAMPO_IT IS NULL AND Y.CAMPO_SIMUL IS NOT NULL ) OR (X.CAMPO_IT IS NOT NULL AND Y.CAMPO_SIMUL IS NULL),1,0)) AS NUM_REG_DIF,'1' AS ID_EXEC, CURRENT_TIMESTAMP() AS TIME_EXEC FROM (SELECT concat(cempresa, cbalcao, cnumecta, zdeposit, ccontab_final_ifrs, ccontab_final_pcsb, ccontab_final_cargabal, ccontab_final) AS CHAVE_IT1, zcliente AS CHAVE_IT2, bruto_imparidade AS CAMPO_IT FROM CD_LOAN_TAPES_BCE.LT001_UNIV_OPER WHERE ref_date='${ref_date}' AND nome_perimetro='Individual Local' AND segmento='ESTR' AND ambito='PM' AND entidade='00100')X INNER JOIN (SELECT concat(cempresa, cbalcao, cnumecta, zdeposit, ccontab_final_ifrs, ccontab_final_pcsb, ccontab_final_cargabal, ccontab_final) AS CHAVE_SIMUL1, zcliente AS CHAVE_SIMUL2, bruto_imparidade AS CAMPO_SIMUL FROM BU_LOANTAPE_WORK.LT001_UNIV_OPER WHERE ref_date='${ref_date}' AND nome_perimetro='Individual Local' AND segmento='ESTR' AND ambito='PM' AND entidade='00100')Y ON X.CHAVE_IT1=Y.CHAVE_SIMUL1 AND X.CHAVE_IT2=Y.CHAVE_SIMUL2
A17: =+B17&C17 -> UNIV_OPERcomposicao_valor | B17: UNIV_OPER | C17: composicao_valor | D17: Coerência | E17: =+UPPER('0. Instruções'!$D$35&"."&VLOOKUP(B17,'0. Instruções'!$C$27:$D$32,2,FALSE)) -> CD_LOAN_TAPES_BCE.LT001_UNIV_OPER | F17: =+UPPER('0. Instruções'!$D$36&"."&VLOOKUP(B17,'0. Instruções'!$C$27:$E$32,3,FALSE)) -> BU_LOANTAPE_WORK.LT001_UNIV_OPER | J17: =IF(VLOOKUP(B17,'0. Instruções'!$C$27:$G$32,5,FALSE)=0, "(SELECT "&VLOOKUP(B17,'0. Instruções'!$C$27:$G$32,4,FALSE)&" AS CHAVE_IT, "&C17&" AS CAMPO_IT FROM "&E17&" WHERE "&'0. Instruções'!$D$43&")X", "(SELECT "&VLOOKUP(B17,'0. Instruções'!$C$27:$G$32,4,FALSE)&" AS CHAVE_IT1, "&VLOOKUP(B17,'0. Instruções'!$C$27:$G$32,5,FALSE)&" AS CHAVE_IT2, "&C17&" AS CAMPO_IT FROM "&E17&" WHERE "&'0. Instruções'!$D$43&")X") -> (SELECT concat(cempresa, cbalcao, cnumecta, zdeposit, ccontab_final_ifrs, ccontab_final_pcsb, ccontab_final_cargabal, ccontab_final) AS CHAVE_IT1, zcliente AS CHAVE_IT2, composicao_valor AS CAMPO_IT FROM CD_LOAN_TAPES_BCE.LT001_UNIV_OPER WHERE ref_date='${ref_date}' AND nome_perimetro='Individual Local' AND segmento='ESTR' AND ambito='PM' AND entidade='00100')X | K17: =IF(VLOOKUP(B17,'0. Instruções'!$C$27:$G$32,5,FALSE)=0, "(SELECT "&VLOOKUP(B17,'0. Instruções'!$C$27:$G$32,4,FALSE)&" AS CHAVE_SIMUL, "&C17&" AS CAMPO_SIMUL FROM "&F17&" WHERE "&'0. Instruções'!$D$42&")Y", "(SELECT "&VLOOKUP(B17,'0. Instruções'!$C$27:$G$32,4,FALSE)&" AS CHAVE_SIMUL1, "&VLOOKUP(B17,'0. Instruções'!$C$27:$G$32,5,FALSE)&" AS CHAVE_SIMUL2, "&C17&" AS CAMPO_SIMUL FROM "&F17&" WHERE "&'0. Instruções'!$D$42&")Y") -> (SELECT concat(cempresa, cbalcao, cnumecta, zdeposit, ccontab_final_ifrs, ccontab_final_pcsb, ccontab_final_cargabal, ccontab_final) AS CHAVE_SIMUL1, zcliente AS CHAVE_SIMUL2, composicao_valor AS CAMPO_SIMUL FROM BU_LOANTAPE_WORK.LT001_UNIV_OPER WHERE ref_date='${ref_date}' AND nome_perimetro='Individual Local' AND segmento='ESTR' AND ambito='PM' AND entidade='00100')Y | L17: =IF(VLOOKUP(B17,'0. Instruções'!$C$27:$G$32,5,FALSE)=0, "ON X.CHAVE_IT=Y.CHAVE_SIMUL", "ON X.CHAVE_IT1=Y.CHAVE_SIMUL1 AND X.CHAVE_IT2=Y.CHAVE_SIMUL2") -> ON X.CHAVE_IT1=Y.CHAVE_SIMUL1 AND X.CHAVE_IT2=Y.CHAVE_SIMUL2 | M17: =+IF(D17="Coerência",+IF(LEFT(H17,5)="FLOAT","SELECT '"&UPPER(B17)&"' AS TABELA, '"&UPPER(D17)&"' AS TIPOLOGIA_TESTE,'"&E17&"' AS TABELA_LT,'"&F17&"' AS TABELA_SIMUL,'"&C17&"' AS CAMPO, "&_xlfn._LONGTEXT("'${ref_date}' AS REF_DATE, COUNT(*) AS NUM_REG, SUM(IF((ABS(COALESCE(CAST(X.CAMPO_IT AS DECIMAL(18,6)),0)-COALESCE(CAST(Y.CAMPO_SIMUL AS DECIMAL(18,6)),0))>0.000001) OR (X.CAMPO_IT IS NULL AND Y.CAMPO_SIMUL IS NOT NULL ) OR (X.CAMPO_IT IS NOT NULL AND Y.C","AMPO_SIMUL IS NULL),1,0)) AS NUM_REG_DIF,'")&MAX('3. Resultados'!K:K)+1&"' AS ID_EXEC, CURRENT_TIMESTAMP() AS TIME_EXEC FROM "&J17&" INNER JOIN "&K17&" "&L17,"SELECT '"&UPPER(B17)&"' AS TABELA, '"&UPPER(D17)&"' AS TIPOLOGIA_TESTE,'"&E17&"' AS TABELA_LT,'"&F17&"' AS TABELA_SIMUL,'"&C17&"' AS CAMPO, "&_xlfn._LONGTEXT("'${ref_date}' AS REF_DATE, COUNT(*) AS NUM_REG, SUM(IF(COALESCE(CAST(X.CAMPO_IT AS STRING),'')<>COALESCE(CAST(Y.CAMPO_SIMUL AS STRING),'') OR (X.CAMPO_IT IS NULL AND Y.CAMPO_SIMUL IS NOT NULL ) OR (X.CAMPO_IT IS NOT NULL AND Y.CAMPO_SIMUL IS NULL),1,0)) A","S NUM_REG_DIF,'")&MAX('3. Resultados'!L:L)+1&"' AS ID_EXEC, CURRENT_TIMESTAMP() AS TIME_EXEC FROM "&J17&" INNER JOIN "&K17&" "&L17)) -> SELECT 'UNIV_OPER' AS TABELA, 'COERÊNCIA' AS TIPOLOGIA_TESTE,'CD_LOAN_TAPES_BCE.LT001_UNIV_OPER' AS TABELA_LT,'BU_LOANTAPE_WORK.LT001_UNIV_OPER' AS TABELA_SIMUL,'composicao_valor' AS CAMPO, '${ref_date}' AS REF_DATE, COUNT(*) AS NUM_REG, SUM(IF(COALESCE(CAST(X.CAMPO_IT AS STRING),'')<>COALESCE(CAST(Y.CAMPO_SIMUL AS STRING),'') OR (X.CAMPO_IT IS NULL AND Y.CAMPO_SIMUL IS NOT NULL ) OR (X.CAMPO_IT IS NOT NULL AND Y.CAMPO_SIMUL IS NULL),1,0)) AS NUM_REG_DIF,'1' AS ID_EXEC, CURRENT_TIMESTAMP() AS TIME_EXEC FROM (SELECT concat(cempresa, cbalcao, cnumecta, zdeposit, ccontab_final_ifrs, ccontab_final_pcsb, ccontab_final_cargabal, ccontab_final) AS CHAVE_IT1, zcliente AS CHAVE_IT2, composicao_valor AS CAMPO_IT FROM CD_LOAN_TAPES_BCE.LT001_UNIV_OPER WHERE ref_date='${ref_date}' AND nome_perimetro='Individual Local' AND segmento='ESTR' AND ambito='PM' AND entidade='00100')X INNER JOIN (SELECT concat(cempresa, cbalcao, cnumecta, zdeposit, ccontab_final_ifrs, ccontab_final_pcsb, ccontab_final_cargabal, ccontab_final) AS CHAVE_SIMUL1, zcliente AS CHAVE_SIMUL2, composicao_valor AS CAMPO_SIMUL FROM BU_LOANTAPE_WORK.LT001_UNIV_OPER WHERE ref_date='${ref_date}' AND nome_perimetro='Individual Local' AND segmento='ESTR' AND ambito='PM' AND entidade='00100')Y ON X.CHAVE_IT1=Y.CHAVE_SIMUL1 AND X.CHAVE_IT2=Y.CHAVE_SIMUL2 | N17: =+"UNION ALL "&M17 -> UNION ALL SELECT 'UNIV_OPER' AS TABELA, 'COERÊNCIA' AS TIPOLOGIA_TESTE,'CD_LOAN_TAPES_BCE.LT001_UNIV_OPER' AS TABELA_LT,'BU_LOANTAPE_WORK.LT001_UNIV_OPER' AS TABELA_SIMUL,'composicao_valor' AS CAMPO, '${ref_date}' AS REF_DATE, COUNT(*) AS NUM_REG, SUM(IF(COALESCE(CAST(X.CAMPO_IT AS STRING),'')<>COALESCE(CAST(Y.CAMPO_SIMUL AS STRING),'') OR (X.CAMPO_IT IS NULL AND Y.CAMPO_SIMUL IS NOT NULL ) OR (X.CAMPO_IT IS NOT NULL AND Y.CAMPO_SIMUL IS NULL),1,0)) AS NUM_REG_DIF,'1' AS ID_EXEC, CURRENT_TIMESTAMP() AS TIME_EXEC FROM (SELECT concat(cempresa, cbalcao, cnumecta, zdeposit, ccontab_final_ifrs, ccontab_final_pcsb, ccontab_final_cargabal, ccontab_final) AS CHAVE_IT1, zcliente AS CHAVE_IT2, composicao_valor AS CAMPO_IT FROM CD_LOAN_TAPES_BCE.LT001_UNIV_OPER WHERE ref_date='${ref_date}' AND nome_perimetro='Individual Local' AND segmento='ESTR' AND ambito='PM' AND entidade='00100')X INNER JOIN (SELECT concat(cempresa, cbalcao, cnumecta, zdeposit, ccontab_final_ifrs, ccontab_final_pcsb, ccontab_final_cargabal, ccontab_final) AS CHAVE_SIMUL1, zcliente AS CHAVE_SIMUL2, composicao_valor AS CAMPO_SIMUL FROM BU_LOANTAPE_WORK.LT001_UNIV_OPER WHERE ref_date='${ref_date}' AND nome_perimetro='Individual Local' AND segmento='ESTR' AND ambito='PM' AND entidade='00100')Y ON X.CHAVE_IT1=Y.CHAVE_SIMUL1 AND X.CHAVE_IT2=Y.CHAVE_SIMUL2
A18: =+B18&C18 -> UNIV_OPERcolateral | B18: UNIV_OPER | C18: colateral | D18: Coerência | E18: =+UPPER('0. Instruções'!$D$35&"."&VLOOKUP(B18,'0. Instruções'!$C$27:$D$32,2,FALSE)) -> CD_LOAN_TAPES_BCE.LT001_UNIV_OPER | F18: =+UPPER('0. Instruções'!$D$36&"."&VLOOKUP(B18,'0. Instruções'!$C$27:$E$32,3,FALSE)) -> BU_LOANTAPE_WORK.LT001_UNIV_OPER | J18: =IF(VLOOKUP(B18,'0. Instruções'!$C$27:$G$32,5,FALSE)=0, "(SELECT "&VLOOKUP(B18,'0. Instruções'!$C$27:$G$32,4,FALSE)&" AS CHAVE_IT, "&C18&" AS CAMPO_IT FROM "&E18&" WHERE "&'0. Instruções'!$D$43&")X", "(SELECT "&VLOOKUP(B18,'0. Instruções'!$C$27:$G$32,4,FALSE)&" AS CHAVE_IT1, "&VLOOKUP(B18,'0. Instruções'!$C$27:$G$32,5,FALSE)&" AS CHAVE_IT2, "&C18&" AS CAMPO_IT FROM "&E18&" WHERE "&'0. Instruções'!$D$43&")X") -> (SELECT concat(cempresa, cbalcao, cnumecta, zdeposit, ccontab_final_ifrs, ccontab_final_pcsb, ccontab_final_cargabal, ccontab_final) AS CHAVE_IT1, zcliente AS CHAVE_IT2, colateral AS CAMPO_IT FROM CD_LOAN_TAPES_BCE.LT001_UNIV_OPER WHERE ref_date='${ref_date}' AND nome_perimetro='Individual Local' AND segmento='ESTR' AND ambito='PM' AND entidade='00100')X | K18: =IF(VLOOKUP(B18,'0. Instruções'!$C$27:$G$32,5,FALSE)=0, "(SELECT "&VLOOKUP(B18,'0. Instruções'!$C$27:$G$32,4,FALSE)&" AS CHAVE_SIMUL, "&C18&" AS CAMPO_SIMUL FROM "&F18&" WHERE "&'0. Instruções'!$D$42&")Y", "(SELECT "&VLOOKUP(B18,'0. Instruções'!$C$27:$G$32,4,FALSE)&" AS CHAVE_SIMUL1, "&VLOOKUP(B18,'0. Instruções'!$C$27:$G$32,5,FALSE)&" AS CHAVE_SIMUL2, "&C18&" AS CAMPO_SIMUL FROM "&F18&" WHERE "&'0. Instruções'!$D$42&")Y") -> (SELECT concat(cempresa, cbalcao, cnumecta, zdeposit, ccontab_final_ifrs, ccontab_final_pcsb, ccontab_final_cargabal, ccontab_final) AS CHAVE_SIMUL1, zcliente AS CHAVE_SIMUL2, colateral AS CAMPO_SIMUL FROM BU_LOANTAPE_WORK.LT001_UNIV_OPER WHERE ref_date='${ref_date}' AND nome_perimetro='Individual Local' AND segmento='ESTR' AND ambito='PM' AND entidade='00100')Y | L18: =IF(VLOOKUP(B18,'0. Instruções'!$C$27:$G$32,5,FALSE)=0, "ON X.CHAVE_IT=Y.CHAVE_SIMUL", "ON X.CHAVE_IT1=Y.CHAVE_SIMUL1 AND X.CHAVE_IT2=Y.CHAVE_SIMUL2") -> ON X.CHAVE_IT1=Y.CHAVE_SIMUL1 AND X.CHAVE_IT2=Y.CHAVE_SIMUL2 | M18: =+IF(D18="Coerência",+IF(LEFT(H18,5)="FLOAT","SELECT '"&UPPER(B18)&"' AS TABELA, '"&UPPER(D18)&"' AS TIPOLOGIA_TESTE,'"&E18&"' AS TABELA_LT,'"&F18&"' AS TABELA_SIMUL,'"&C18&"' AS CAMPO, "&_xlfn._LONGTEXT("'${ref_date}' AS REF_DATE, COUNT(*) AS NUM_REG, SUM(IF((ABS(COALESCE(CAST(X.CAMPO_IT AS DECIMAL(18,6)),0)-COALESCE(CAST(Y.CAMPO_SIMUL AS DECIMAL(18,6)),0))>0.000001) OR (X.CAMPO_IT IS NULL AND Y.CAMPO_SIMUL IS NOT NULL ) OR (X.CAMPO_IT IS NOT NULL AND Y.C","AMPO_SIMUL IS NULL),1,0)) AS NUM_REG_DIF,'")&MAX('3. Resultados'!K:K)+1&"' AS ID_EXEC, CURRENT_TIMESTAMP() AS TIME_EXEC FROM "&J18&" INNER JOIN "&K18&" "&L18,"SELECT '"&UPPER(B18)&"' AS TABELA, '"&UPPER(D18)&"' AS TIPOLOGIA_TESTE,'"&E18&"' AS TABELA_LT,'"&F18&"' AS TABELA_SIMUL,'"&C18&"' AS CAMPO, "&_xlfn._LONGTEXT("'${ref_date}' AS REF_DATE, COUNT(*) AS NUM_REG, SUM(IF(COALESCE(CAST(X.CAMPO_IT AS STRING),'')<>COALESCE(CAST(Y.CAMPO_SIMUL AS STRING),'') OR (X.CAMPO_IT IS NULL AND Y.CAMPO_SIMUL IS NOT NULL ) OR (X.CAMPO_IT IS NOT NULL AND Y.CAMPO_SIMUL IS NULL),1,0)) A","S NUM_REG_DIF,'")&MAX('3. Resultados'!L:L)+1&"' AS ID_EXEC, CURRENT_TIMESTAMP() AS TIME_EXEC FROM "&J18&" INNER JOIN "&K18&" "&L18)) -> SELECT 'UNIV_OPER' AS TABELA, 'COERÊNCIA' AS TIPOLOGIA_TESTE,'CD_LOAN_TAPES_BCE.LT001_UNIV_OPER' AS TABELA_LT,'BU_LOANTAPE_WORK.LT001_UNIV_OPER' AS TABELA_SIMUL,'colateral' AS CAMPO, '${ref_date}' AS REF_DATE, COUNT(*) AS NUM_REG, SUM(IF(COALESCE(CAST(X.CAMPO_IT AS STRING),'')<>COALESCE(CAST(Y.CAMPO_SIMUL AS STRING),'') OR (X.CAMPO_IT IS NULL AND Y.CAMPO_SIMUL IS NOT NULL ) OR (X.CAMPO_IT IS NOT NULL AND Y.CAMPO_SIMUL IS NULL),1,0)) AS NUM_REG_DIF,'1' AS ID_EXEC, CURRENT_TIMESTAMP() AS TIME_EXEC FROM (SELECT concat(cempresa, cbalcao, cnumecta, zdeposit, ccontab_final_ifrs, ccontab_final_pcsb, ccontab_final_cargabal, ccontab_final) AS CHAVE_IT1, zcliente AS CHAVE_IT2, colateral AS CAMPO_IT FROM CD_LOAN_TAPES_BCE.LT001_UNIV_OPER WHERE ref_date='${ref_date}' AND nome_perimetro='Individual Local' AND segmento='ESTR' AND ambito='PM' AND entidade='00100')X INNER JOIN (SELECT concat(cempresa, cbalcao, cnumecta, zdeposit, ccontab_final_ifrs, ccontab_final_pcsb, ccontab_final_cargabal, ccontab_final) AS CHAVE_SIMUL1, zcliente AS CHAVE_SIMUL2, colateral AS CAMPO_SIMUL FROM BU_LOANTAPE_WORK.LT001_UNIV_OPER WHERE ref_date='${ref_date}' AND nome_perimetro='Individual Local' AND segmento='ESTR' AND ambito='PM' AND entidade='00100')Y ON X.CHAVE_IT1=Y.CHAVE_SIMUL1 AND X.CHAVE_IT2=Y.CHAVE_SIMUL2 | N18: =+"UNION ALL "&M18 -> UNION ALL SELECT 'UNIV_OPER' AS TABELA, 'COERÊNCIA' AS TIPOLOGIA_TESTE,'CD_LOAN_TAPES_BCE.LT001_UNIV_OPER' AS TABELA_LT,'BU_LOANTAPE_WORK.LT001_UNIV_OPER' AS TABELA_SIMUL,'colateral' AS CAMPO, '${ref_date}' AS REF_DATE, COUNT(*) AS NUM_REG, SUM(IF(COALESCE(CAST(X.CAMPO_IT AS STRING),'')<>COALESCE(CAST(Y.CAMPO_SIMUL AS STRING),'') OR (X.CAMPO_IT IS NULL AND Y.CAMPO_SIMUL IS NOT NULL ) OR (X.CAMPO_IT IS NOT NULL AND Y.CAMPO_SIMUL IS NULL),1,0)) AS NUM_REG_DIF,'1' AS ID_EXEC, CURRENT_TIMESTAMP() AS TIME_EXEC FROM (SELECT concat(cempresa, cbalcao, cnumecta, zdeposit, ccontab_final_ifrs, ccontab_final_pcsb, ccontab_final_cargabal, ccontab_final) AS CHAVE_IT1, zcliente AS CHAVE_IT2, colateral AS CAMPO_IT FROM CD_LOAN_TAPES_BCE.LT001_UNIV_OPER WHERE ref_date='${ref_date}' AND nome_perimetro='Individual Local' AND segmento='ESTR' AND ambito='PM' AND entidade='00100')X INNER JOIN (SELECT concat(cempresa, cbalcao, cnumecta, zdeposit, ccontab_final_ifrs, ccontab_final_pcsb, ccontab_final_cargabal, ccontab_final) AS CHAVE_SIMUL1, zcliente AS CHAVE_SIMUL2, colateral AS CAMPO_SIMUL FROM BU_LOANTAPE_WORK.LT001_UNIV_OPER WHERE ref_date='${ref_date}' AND nome_perimetro='Individual Local' AND segmento='ESTR' AND ambito='PM' AND entidade='00100')Y ON X.CHAVE_IT1=Y.CHAVE_SIMUL1 AND X.CHAVE_IT2=Y.CHAVE_SIMUL2
A19: =+B19&C19 -> UNIV_OPERflag_poci | B19: UNIV_OPER | C19: flag_poci | D19: Coerência | E19: =+UPPER('0. Instruções'!$D$35&"."&VLOOKUP(B19,'0. Instruções'!$C$27:$D$32,2,FALSE)) -> CD_LOAN_TAPES_BCE.LT001_UNIV_OPER | F19: =+UPPER('0. Instruções'!$D$36&"."&VLOOKUP(B19,'0. Instruções'!$C$27:$E$32,3,FALSE)) -> BU_LOANTAPE_WORK.LT001_UNIV_OPER | J19: =IF(VLOOKUP(B19,'0. Instruções'!$C$27:$G$32,5,FALSE)=0, "(SELECT "&VLOOKUP(B19,'0. Instruções'!$C$27:$G$32,4,FALSE)&" AS CHAVE_IT, "&C19&" AS CAMPO_IT FROM "&E19&" WHERE "&'0. Instruções'!$D$43&")X", "(SELECT "&VLOOKUP(B19,'0. Instruções'!$C$27:$G$32,4,FALSE)&" AS CHAVE_IT1, "&VLOOKUP(B19,'0. Instruções'!$C$27:$G$32,5,FALSE)&" AS CHAVE_IT2, "&C19&" AS CAMPO_IT FROM "&E19&" WHERE "&'0. Instruções'!$D$43&")X") -> (SELECT concat(cempresa, cbalcao, cnumecta, zdeposit, ccontab_final_ifrs, ccontab_final_pcsb, ccontab_final_cargabal, ccontab_final) AS CHAVE_IT1, zcliente AS CHAVE_IT2, flag_poci AS CAMPO_IT FROM CD_LOAN_TAPES_BCE.LT001_UNIV_OPER WHERE ref_date='${ref_date}' AND nome_perimetro='Individual Local' AND segmento='ESTR' AND ambito='PM' AND entidade='00100')X | K19: =IF(VLOOKUP(B19,'0. Instruções'!$C$27:$G$32,5,FALSE)=0, "(SELECT "&VLOOKUP(B19,'0. Instruções'!$C$27:$G$32,4,FALSE)&" AS CHAVE_SIMUL, "&C19&" AS CAMPO_SIMUL FROM "&F19&" WHERE "&'0. Instruções'!$D$42&")Y", "(SELECT "&VLOOKUP(B19,'0. Instruções'!$C$27:$G$32,4,FALSE)&" AS CHAVE_SIMUL1, "&VLOOKUP(B19,'0. Instruções'!$C$27:$G$32,5,FALSE)&" AS CHAVE_SIMUL2, "&C19&" AS CAMPO_SIMUL FROM "&F19&" WHERE "&'0. Instruções'!$D$42&")Y") -> (SELECT concat(cempresa, cbalcao, cnumecta, zdeposit, ccontab_final_ifrs, ccontab_final_pcsb, ccontab_final_cargabal, ccontab_final) AS CHAVE_SIMUL1, zcliente AS CHAVE_SIMUL2, flag_poci AS CAMPO_SIMUL FROM BU_LOANTAPE_WORK.LT001_UNIV_OPER WHERE ref_date='${ref_date}' AND nome_perimetro='Individual Local' AND segmento='ESTR' AND ambito='PM' AND entidade='00100')Y | L19: =IF(VLOOKUP(B19,'0. Instruções'!$C$27:$G$32,5,FALSE)=0, "ON X.CHAVE_IT=Y.CHAVE_SIMUL", "ON X.CHAVE_IT1=Y.CHAVE_SIMUL1 AND X.CHAVE_IT2=Y.CHAVE_SIMUL2") -> ON X.CHAVE_IT1=Y.CHAVE_SIMUL1 AND X.CHAVE_IT2=Y.CHAVE_SIMUL2 | M19: =+IF(D19="Coerência",+IF(LEFT(H19,5)="FLOAT","SELECT '"&UPPER(B19)&"' AS TABELA, '"&UPPER(D19)&"' AS TIPOLOGIA_TESTE,'"&E19&"' AS TABELA_LT,'"&F19&"' AS TABELA_SIMUL,'"&C19&"' AS CAMPO, "&_xlfn._LONGTEXT("'${ref_date}' AS REF_DATE, COUNT(*) AS NUM_REG, SUM(IF((ABS(COALESCE(CAST(X.CAMPO_IT AS DECIMAL(18,6)),0)-COALESCE(CAST(Y.CAMPO_SIMUL AS DECIMAL(18,6)),0))>0.000001) OR (X.CAMPO_IT IS NULL AND Y.CAMPO_SIMUL IS NOT NULL ) OR (X.CAMPO_IT IS NOT NULL AND Y.C","AMPO_SIMUL IS NULL),1,0)) AS NUM_REG_DIF,'")&MAX('3. Resultados'!K:K)+1&"' AS ID_EXEC, CURRENT_TIMESTAMP() AS TIME_EXEC FROM "&J19&" INNER JOIN "&K19&" "&L19,"SELECT '"&UPPER(B19)&"' AS TABELA, '"&UPPER(D19)&"' AS TIPOLOGIA_TESTE,'"&E19&"' AS TABELA_LT,'"&F19&"' AS TABELA_SIMUL,'"&C19&"' AS CAMPO, "&_xlfn._LONGTEXT("'${ref_date}' AS REF_DATE, COUNT(*) AS NUM_REG, SUM(IF(COALESCE(CAST(X.CAMPO_IT AS STRING),'')<>COALESCE(CAST(Y.CAMPO_SIMUL AS STRING),'') OR (X.CAMPO_IT IS NULL AND Y.CAMPO_SIMUL IS NOT NULL ) OR (X.CAMPO_IT IS NOT NULL AND Y.CAMPO_SIMUL IS NULL),1,0)) A","S NUM_REG_DIF,'")&MAX('3. Resultados'!L:L)+1&"' AS ID_EXEC, CURRENT_TIMESTAMP() AS TIME_EXEC FROM "&J19&" INNER JOIN "&K19&" "&L19)) -> SELECT 'UNIV_OPER' AS TABELA, 'COERÊNCIA' AS TIPOLOGIA_TESTE,'CD_LOAN_TAPES_BCE.LT001_UNIV_OPER' AS TABELA_LT,'BU_LOANTAPE_WORK.LT001_UNIV_OPER' AS TABELA_SIMUL,'flag_poci' AS CAMPO, '${ref_date}' AS REF_DATE, COUNT(*) AS NUM_REG, SUM(IF(COALESCE(CAST(X.CAMPO_IT AS STRING),'')<>COALESCE(CAST(Y.CAMPO_SIMUL AS STRING),'') OR (X.CAMPO_IT IS NULL AND Y.CAMPO_SIMUL IS NOT NULL ) OR (X.CAMPO_IT IS NOT NULL AND Y.CAMPO_SIMUL IS NULL),1,0)) AS NUM_REG_DIF,'1' AS ID_EXEC, CURRENT_TIMESTAMP() AS TIME_EXEC FROM (SELECT concat(cempresa, cbalcao, cnumecta, zdeposit, ccontab_final_ifrs, ccontab_final_pcsb, ccontab_final_cargabal, ccontab_final) AS CHAVE_IT1, zcliente AS CHAVE_IT2, flag_poci AS CAMPO_IT FROM CD_LOAN_TAPES_BCE.LT001_UNIV_OPER WHERE ref_date='${ref_date}' AND nome_perimetro='Individual Local' AND segmento='ESTR' AND ambito='PM' AND entidade='00100')X INNER JOIN (SELECT concat(cempresa, cbalcao, cnumecta, zdeposit, ccontab_final_ifrs, ccontab_final_pcsb, ccontab_final_cargabal, ccontab_final) AS CHAVE_SIMUL1, zcliente AS CHAVE_SIMUL2, flag_poci AS CAMPO_SIMUL FROM BU_LOANTAPE_WORK.LT001_UNIV_OPER WHERE ref_date='${ref_date}' AND nome_perimetro='Individual Local' AND segmento='ESTR' AND ambito='PM' AND entidade='00100')Y ON X.CHAVE_IT1=Y.CHAVE_SIMUL1 AND X.CHAVE_IT2=Y.CHAVE_SIMUL2 | N19: =+"UNION ALL "&M19 -> UNION ALL SELECT 'UNIV_OPER' AS TABELA, 'COERÊNCIA' AS TIPOLOGIA_TESTE,'CD_LOAN_TAPES_BCE.LT001_UNIV_OPER' AS TABELA_LT,'BU_LOANTAPE_WORK.LT001_UNIV_OPER' AS TABELA_SIMUL,'flag_poci' AS CAMPO, '${ref_date}' AS REF_DATE, COUNT(*) AS NUM_REG, SUM(IF(COALESCE(CAST(X.CAMPO_IT AS STRING),'')<>COALESCE(CAST(Y.CAMPO_SIMUL AS STRING),'') OR (X.CAMPO_IT IS NULL AND Y.CAMPO_SIMUL IS NOT NULL ) OR (X.CAMPO_IT IS NOT NULL AND Y.CAMPO_SIMUL IS NULL),1,0)) AS NUM_REG_DIF,'1' AS ID_EXEC, CURRENT_TIMESTAMP() AS TIME_EXEC FROM (SELECT concat(cempresa, cbalcao, cnumecta, zdeposit, ccontab_final_ifrs, ccontab_final_pcsb, ccontab_final_cargabal, ccontab_final) AS CHAVE_IT1, zcliente AS CHAVE_IT2, flag_poci AS CAMPO_IT FROM CD_LOAN_TAPES_BCE.LT001_UNIV_OPER WHERE ref_date='${ref_date}' AND nome_perimetro='Individual Local' AND segmento='ESTR' AND ambito='PM' AND entidade='00100')X INNER JOIN (SELECT concat(cempresa, cbalcao, cnumecta, zdeposit, ccontab_final_ifrs, ccontab_final_pcsb, ccontab_final_cargabal, ccontab_final) AS CHAVE_SIMUL1, zcliente AS CHAVE_SIMUL2, flag_poci AS CAMPO_SIMUL FROM BU_LOANTAPE_WORK.LT001_UNIV_OPER WHERE ref_date='${ref_date}' AND nome_perimetro='Individual Local' AND segmento='ESTR' AND ambito='PM' AND entidade='00100')Y ON X.CHAVE_IT1=Y.CHAVE_SIMUL1 AND X.CHAVE_IT2=Y.CHAVE_SIMUL2
A20: =+B20&C20 -> UNIV_OPERpurpose_code | B20: UNIV_OPER | C20: purpose_code | D20: Coerência | E20: =+UPPER('0. Instruções'!$D$35&"."&VLOOKUP(B20,'0. Instruções'!$C$27:$D$32,2,FALSE)) -> CD_LOAN_TAPES_BCE.LT001_UNIV_OPER | F20: =+UPPER('0. Instruções'!$D$36&"."&VLOOKUP(B20,'0. Instruções'!$C$27:$E$32,3,FALSE)) -> BU_LOANTAPE_WORK.LT001_UNIV_OPER | J20: =IF(VLOOKUP(B20,'0. Instruções'!$C$27:$G$32,5,FALSE)=0, "(SELECT "&VLOOKUP(B20,'0. Instruções'!$C$27:$G$32,4,FALSE)&" AS CHAVE_IT, "&C20&" AS CAMPO_IT FROM "&E20&" WHERE "&'0. Instruções'!$D$43&")X", "(SELECT "&VLOOKUP(B20,'0. Instruções'!$C$27:$G$32,4,FALSE)&" AS CHAVE_IT1, "&VLOOKUP(B20,'0. Instruções'!$C$27:$G$32,5,FALSE)&" AS CHAVE_IT2, "&C20&" AS CAMPO_IT FROM "&E20&" WHERE "&'0. Instruções'!$D$43&")X") -> (SELECT concat(cempresa, cbalcao, cnumecta, zdeposit, ccontab_final_ifrs, ccontab_final_pcsb, ccontab_final_cargabal, ccontab_final) AS CHAVE_IT1, zcliente AS CHAVE_IT2, purpose_code AS CAMPO_IT FROM CD_LOAN_TAPES_BCE.LT001_UNIV_OPER WHERE ref_date='${ref_date}' AND nome_perimetro='Individual Local' AND segmento='ESTR' AND ambito='PM' AND entidade='00100')X | K20: =IF(VLOOKUP(B20,'0. Instruções'!$C$27:$G$32,5,FALSE)=0, "(SELECT "&VLOOKUP(B20,'0. Instruções'!$C$27:$G$32,4,FALSE)&" AS CHAVE_SIMUL, "&C20&" AS CAMPO_SIMUL FROM "&F20&" WHERE "&'0. Instruções'!$D$42&")Y", "(SELECT "&VLOOKUP(B20,'0. Instruções'!$C$27:$G$32,4,FALSE)&" AS CHAVE_SIMUL1, "&VLOOKUP(B20,'0. Instruções'!$C$27:$G$32,5,FALSE)&" AS CHAVE_SIMUL2, "&C20&" AS CAMPO_SIMUL FROM "&F20&" WHERE "&'0. Instruções'!$D$42&")Y") -> (SELECT concat(cempresa, cbalcao, cnumecta, zdeposit, ccontab_final_ifrs, ccontab_final_pcsb, ccontab_final_cargabal, ccontab_final) AS CHAVE_SIMUL1, zcliente AS CHAVE_SIMUL2, purpose_code AS CAMPO_SIMUL FROM BU_LOANTAPE_WORK.LT001_UNIV_OPER WHERE ref_date='${ref_date}' AND nome_perimetro='Individual Local' AND segmento='ESTR' AND ambito='PM' AND entidade='00100')Y | L20: =IF(VLOOKUP(B20,'0. Instruções'!$C$27:$G$32,5,FALSE)=0, "ON X.CHAVE_IT=Y.CHAVE_SIMUL", "ON X.CHAVE_IT1=Y.CHAVE_SIMUL1 AND X.CHAVE_IT2=Y.CHAVE_SIMUL2") -> ON X.CHAVE_IT1=Y.CHAVE_SIMUL1 AND X.CHAVE_IT2=Y.CHAVE_SIMUL2 | M20: =+IF(D20="Coerência",+IF(LEFT(H20,5)="FLOAT","SELECT '"&UPPER(B20)&"' AS TABELA, '"&UPPER(D20)&"' AS TIPOLOGIA_TESTE,'"&E20&"' AS TABELA_LT,'"&F20&"' AS TABELA_SIMUL,'"&C20&"' AS CAMPO, "&_xlfn._LONGTEXT("'${ref_date}' AS REF_DATE, COUNT(*) AS NUM_REG, SUM(IF((ABS(COALESCE(CAST(X.CAMPO_IT AS DECIMAL(18,6)),0)-COALESCE(CAST(Y.CAMPO_SIMUL AS DECIMAL(18,6)),0))>0.000001) OR (X.CAMPO_IT IS NULL AND Y.CAMPO_SIMUL IS NOT NULL ) OR (X.CAMPO_IT IS NOT NULL AND Y.C","AMPO_SIMUL IS NULL),1,0)) AS NUM_REG_DIF,'")&MAX('3. Resultados'!K:K)+1&"' AS ID_EXEC, CURRENT_TIMESTAMP() AS TIME_EXEC FROM "&J20&" INNER JOIN "&K20&" "&L20,"SELECT '"&UPPER(B20)&"' AS TABELA, '"&UPPER(D20)&"' AS TIPOLOGIA_TESTE,'"&E20&"' AS TABELA_LT,'"&F20&"' AS TABELA_SIMUL,'"&C20&"' AS CAMPO, "&_xlfn._LONGTEXT("'${ref_date}' AS REF_DATE, COUNT(*) AS NUM_REG, SUM(IF(COALESCE(CAST(X.CAMPO_IT AS STRING),'')<>COALESCE(CAST(Y.CAMPO_SIMUL AS STRING),'') OR (X.CAMPO_IT IS NULL AND Y.CAMPO_SIMUL IS NOT NULL ) OR (X.CAMPO_IT IS NOT NULL AND Y.CAMPO_SIMUL IS NULL),1,0)) A","S NUM_REG_DIF,'")&MAX('3. Resultados'!L:L)+1&"' AS ID_EXEC, CURRENT_TIMESTAMP() AS TIME_EXEC FROM "&J20&" INNER JOIN "&K20&" "&L20)) -> SELECT 'UNIV_OPER' AS TABELA, 'COERÊNCIA' AS TIPOLOGIA_TESTE,'CD_LOAN_TAPES_BCE.LT001_UNIV_OPER' AS TABELA_LT,'BU_LOANTAPE_WORK.LT001_UNIV_OPER' AS TABELA_SIMUL,'purpose_code' AS CAMPO, '${ref_date}' AS REF_DATE, COUNT(*) AS NUM_REG, SUM(IF(COALESCE(CAST(X.CAMPO_IT AS STRING),'')<>COALESCE(CAST(Y.CAMPO_SIMUL AS STRING),'') OR (X.CAMPO_IT IS NULL AND Y.CAMPO_SIMUL IS NOT NULL ) OR (X.CAMPO_IT IS NOT NULL AND Y.CAMPO_SIMUL IS NULL),1,0)) AS NUM_REG_DIF,'1' AS ID_EXEC, CURRENT_TIMESTAMP() AS TIME_EXEC FROM (SELECT concat(cempresa, cbalcao, cnumecta, zdeposit, ccontab_final_ifrs, ccontab_final_pcsb, ccontab_final_cargabal, ccontab_final) AS CHAVE_IT1, zcliente AS CHAVE_IT2, purpose_code AS CAMPO_IT FROM CD_LOAN_TAPES_BCE.LT001_UNIV_OPER WHERE ref_date='${ref_date}' AND nome_perimetro='Individual Local' AND segmento='ESTR' AND ambito='PM' AND entidade='00100')X INNER JOIN (SELECT concat(cempresa, cbalcao, cnumecta, zdeposit, ccontab_final_ifrs, ccontab_final_pcsb, ccontab_final_cargabal, ccontab_final) AS CHAVE_SIMUL1, zcliente AS CHAVE_SIMUL2, purpose_code AS CAMPO_SIMUL FROM BU_LOANTAPE_WORK.LT001_UNIV_OPER WHERE ref_date='${ref_date}' AND nome_perimetro='Individual Local' AND segmento='ESTR' AND ambito='PM' AND entidade='00100')Y ON X.CHAVE_IT1=Y.CHAVE_SIMUL1 AND X.CHAVE_IT2=Y.CHAVE_SIMUL2 | N20: =+"UNION ALL "&M20 -> UNION ALL SELECT 'UNIV_OPER' AS TABELA, 'COERÊNCIA' AS TIPOLOGIA_TESTE,'CD_LOAN_TAPES_BCE.LT001_UNIV_OPER' AS TABELA_LT,'BU_LOANTAPE_WORK.LT001_UNIV_OPER' AS TABELA_SIMUL,'purpose_code' AS CAMPO, '${ref_date}' AS REF_DATE, COUNT(*) AS NUM_REG, SUM(IF(COALESCE(CAST(X.CAMPO_IT AS STRING),'')<>COALESCE(CAST(Y.CAMPO_SIMUL AS STRING),'') OR (X.CAMPO_IT IS NULL AND Y.CAMPO_SIMUL IS NOT NULL ) OR (X.CAMPO_IT IS NOT NULL AND Y.CAMPO_SIMUL IS NULL),1,0)) AS NUM_REG_DIF,'1' AS ID_EXEC, CURRENT_TIMESTAMP() AS TIME_EXEC FROM (SELECT concat(cempresa, cbalcao, cnumecta, zdeposit, ccontab_final_ifrs, ccontab_final_pcsb, ccontab_final_cargabal, ccontab_final) AS CHAVE_IT1, zcliente AS CHAVE_IT2, purpose_code AS CAMPO_IT FROM CD_LOAN_TAPES_BCE.LT001_UNIV_OPER WHERE ref_date='${ref_date}' AND nome_perimetro='Individual Local' AND segmento='ESTR' AND ambito='PM' AND entidade='00100')X INNER JOIN (SELECT concat(cempresa, cbalcao, cnumecta, zdeposit, ccontab_final_ifrs, ccontab_final_pcsb, ccontab_final_cargabal, ccontab_final) AS CHAVE_SIMUL1, zcliente AS CHAVE_SIMUL2, purpose_code AS CAMPO_SIMUL FROM BU_LOANTAPE_WORK.LT001_UNIV_OPER WHERE ref_date='${ref_date}' AND nome_perimetro='Individual Local' AND segmento='ESTR' AND ambito='PM' AND entidade='00100')Y ON X.CHAVE_IT1=Y.CHAVE_SIMUL1 AND X.CHAVE_IT2=Y.CHAVE_SIMUL2
... A665: =+B665&C665 -> INSTR_PROTcod_soc | B665: INSTR_PROT | C665: cod_soc | D665: Coerência | E665: =+UPPER('0. Instruções'!$D$35&"."&VLOOKUP(B665,'0. Instruções'!$C$27:$D$32,2,FALSE)) -> CD_LOAN_TAPES_BCE.LT006_INSTR_PROT | F665: =+UPPER('0. Instruções'!$D$36&"."&VLOOKUP(B665,'0. Instruções'!$C$27:$E$32,3,FALSE)) -> BU_LOANTAPE_WORK.LT006_INSTR_PROT | J665: =IF(VLOOKUP(B665,'0. Instruções'!$C$27:$G$32,5,FALSE)=0, "(SELECT "&VLOOKUP(B665,'0. Instruções'!$C$27:$G$32,4,FALSE)&" AS CHAVE_IT, "&C665&" AS CAMPO_IT FROM "&E665&" WHERE "&'0. Instruções'!$D$43&")X", "(SELECT "&VLOOKUP(B665,'0. Instruções'!$C$27:$G$32,4,FALSE)&" AS CHAVE_IT1, "&VLOOKUP(B665,'0. Instruções'!$C$27:$G$32,5,FALSE)&" AS CHAVE_IT2, "&C665&" AS CAMPO_IT FROM "&E665&" WHERE "&'0. Instruções'!$D$43&")X") -> (SELECT instrmnt_id AS CHAVE_IT1, prtctn_id AS CHAVE_IT2, cod_soc AS CAMPO_IT FROM CD_LOAN_TAPES_BCE.LT006_INSTR_PROT WHERE ref_date='${ref_date}' AND nome_perimetro='Individual Local' AND segmento='ESTR' AND ambito='PM' AND entidade='00100')X | K665: =IF(VLOOKUP(B665,'0. Instruções'!$C$27:$G$32,5,FALSE)=0, "(SELECT "&VLOOKUP(B665,'0. Instruções'!$C$27:$G$32,4,FALSE)&" AS CHAVE_SIMUL, "&C665&" AS CAMPO_SIMUL FROM "&F665&" WHERE "&'0. Instruções'!$D$42&")Y", "(SELECT "&VLOOKUP(B665,'0. Instruções'!$C$27:$G$32,4,FALSE)&" AS CHAVE_SIMUL1, "&VLOOKUP(B665,'0. Instruções'!$C$27:$G$32,5,FALSE)&" AS CHAVE_SIMUL2, "&C665&" AS CAMPO_SIMUL FROM "&F665&" WHERE "&'0. Instruções'!$D$42&")Y") -> (SELECT instrmnt_id AS CHAVE_SIMUL1, prtctn_id AS CHAVE_SIMUL2, cod_soc AS CAMPO_SIMUL FROM BU_LOANTAPE_WORK.LT006_INSTR_PROT WHERE ref_date='${ref_date}' AND nome_perimetro='Individual Local' AND segmento='ESTR' AND ambito='PM' AND entidade='00100')Y | L665: =IF(VLOOKUP(B665,'0. Instruções'!$C$27:$G$32,5,FALSE)=0, "ON X.CHAVE_IT=Y.CHAVE_SIMUL", "ON X.CHAVE_IT1=Y.CHAVE_SIMUL1 AND X.CHAVE_IT2=Y.CHAVE_SIMUL2") -> ON X.CHAVE_IT1=Y.CHAVE_SIMUL1 AND X.CHAVE_IT2=Y.CHAVE_SIMUL2 | M665: =+IF(D665="Coerência",+IF(LEFT(H665,5)="FLOAT","SELECT '"&UPPER(B665)&"' AS TABELA, '"&UPPER(D665)&"' AS TIPOLOGIA_TESTE,'"&E665&"' AS TABELA_LT,'"&F665&"' AS TABELA_SIMUL,'"&C665&"' AS CAMPO, "&_xlfn._LONGTEXT("'${ref_date}' AS REF_DATE, COUNT(*) AS NUM_REG, SUM(IF((ABS(COALESCE(CAST(X.CAMPO_IT AS DECIMAL(18,6)),0)-COALESCE(CAST(Y.CAMPO_SIMUL AS DECIMAL(18,6)),0))>0.000001) OR (X.CAMPO_IT IS NULL AND Y.CAMPO_SIMUL IS NOT NULL ) OR (X.CAMPO_IT IS NOT NULL AND Y.C","AMPO_SIMUL IS NULL),1,0)) AS NUM_REG_DIF,'")&MAX('3. Resultados'!K:K)+1&"' AS ID_EXEC, CURRENT_TIMESTAMP() AS TIME_EXEC FROM "&J665&" INNER JOIN "&K665&" "&L665,"SELECT '"&UPPER(B665)&"' AS TABELA, '"&UPPER(D665)&"' AS TIPOLOGIA_TESTE,'"&E665&"' AS TABELA_LT,'"&F665&"' AS TABELA_SIMUL,'"&C665&"' AS CAMPO, "&_xlfn._LONGTEXT("'${ref_date}' AS REF_DATE, COUNT(*) AS NUM_REG, SUM(IF(COALESCE(CAST(X.CAMPO_IT AS STRING),'')<>COALESCE(CAST(Y.CAMPO_SIMUL AS STRING),'') OR (X.CAMPO_IT IS NULL AND Y.CAMPO_SIMUL IS NOT NULL ) OR (X.CAMPO_IT IS NOT NULL AND Y.CAMPO_SIMUL IS NULL),1,0)) A","S NUM_REG_DIF,'")&MAX('3. Resultados'!L:L)+1&"' AS ID_EXEC, CURRENT_TIMESTAMP() AS TIME_EXEC FROM "&J665&" INNER JOIN "&K665&" "&L665)) -> SELECT 'INSTR_PROT' AS TABELA, 'COERÊNCIA' AS TIPOLOGIA_TESTE,'CD_LOAN_TAPES_BCE.LT006_INSTR_PROT' AS TABELA_LT,'BU_LOANTAPE_WORK.LT006_INSTR_PROT' AS TABELA_SIMUL,'cod_soc' AS CAMPO, '${ref_date}' AS REF_DATE, COUNT(*) AS NUM_REG, SUM(IF(COALESCE(CAST(X.CAMPO_IT AS STRING),'')<>COALESCE(CAST(Y.CAMPO_SIMUL AS STRING),'') OR (X.CAMPO_IT IS NULL AND Y.CAMPO_SIMUL IS NOT NULL ) OR (X.CAMPO_IT IS NOT NULL AND Y.CAMPO_SIMUL IS NULL),1,0)) AS NUM_REG_DIF,'1' AS ID_EXEC, CURRENT_TIMESTAMP() AS TIME_EXEC FROM (SELECT instrmnt_id AS CHAVE_IT1, prtctn_id AS CHAVE_IT2, cod_soc AS CAMPO_IT FROM CD_LOAN_TAPES_BCE.LT006_INSTR_PROT WHERE ref_date='${ref_date}' AND nome_perimetro='Individual Local' AND segmento='ESTR' AND ambito='PM' AND entidade='00100')X INNER JOIN (SELECT instrmnt_id AS CHAVE_SIMUL1, prtctn_id AS CHAVE_SIMUL2, cod_soc AS CAMPO_SIMUL FROM BU_LOANTAPE_WORK.LT006_INSTR_PROT WHERE ref_date='${ref_date}' AND nome_perimetro='Individual Local' AND segmento='ESTR' AND ambito='PM' AND entidade='00100')Y ON X.CHAVE_IT1=Y.CHAVE_SIMUL1 AND X.CHAVE_IT2=Y.CHAVE_SIMUL2 | N665: =+"UNION ALL "&M665 -> UNION ALL SELECT 'INSTR_PROT' AS TABELA, 'COERÊNCIA' AS TIPOLOGIA_TESTE,'CD_LOAN_TAPES_BCE.LT006_INSTR_PROT' AS TABELA_LT,'BU_LOANTAPE_WORK.LT006_INSTR_PROT' AS TABELA_SIMUL,'cod_soc' AS CAMPO, '${ref_date}' AS REF_DATE, COUNT(*) AS NUM_REG, SUM(IF(COALESCE(CAST(X.CAMPO_IT AS STRING),'')<>COALESCE(CAST(Y.CAMPO_SIMUL AS STRING),'') OR (X.CAMPO_IT IS NULL AND Y.CAMPO_SIMUL IS NOT NULL ) OR (X.CAMPO_IT IS NOT NULL AND Y.CAMPO_SIMUL IS NULL),1,0)) AS NUM_REG_DIF,'1' AS ID_EXEC, CURRENT_TIMESTAMP() AS TIME_EXEC FROM (SELECT instrmnt_id AS CHAVE_IT1, prtctn_id AS CHAVE_IT2, cod_soc AS CAMPO_IT FROM CD_LOAN_TAPES_BCE.LT006_INSTR_PROT WHERE ref_date='${ref_date}' AND nome_perimetro='Individual Local' AND segmento='ESTR' AND ambito='PM' AND entidade='00100')X INNER JOIN (SELECT instrmnt_id AS CHAVE_SIMUL1, prtctn_id AS CHAVE_SIMUL2, cod_soc AS CAMPO_SIMUL FROM BU_LOANTAPE_WORK.LT006_INSTR_PROT WHERE ref_date='${ref_date}' AND nome_perimetro='Individual Local' AND segmento='ESTR' AND ambito='PM' AND entidade='00100')Y ON X.CHAVE_IT1=Y.CHAVE_SIMUL1 AND X.CHAVE_IT2=Y.CHAVE_SIMUL2

Sheet 3. Resultados
C6: 3. Resultados
C8: TABELA | D8: TIPOLOGIA_TESTE | E8: TABELA_LT | F8: TABELA_SIMUL | G8: CAMPO | H8: REF_DATE | I8: NUM_REG | J8: NUM_REG_DIF | K8: ID_EXEC | L8: HTIMEST
A9: =+C9&G9&H9&D9 -> UNIV_OPERmsaldo_final2025-11-30COERÊNCIA | B9: =+C9&G9&H9&D9&K9 -> UNIV_OPERmsaldo_final2025-11-30COERÊNCIA1 | C9: UNIV_OPER | D9: COERÊNCIA | E9: CD_LOAN_TAPES_BCE.LT001_UNIV_OPER | F9: BU_LOANTAPE_WORK.LT001_UNIV_OPER | G9: msaldo_final | H9: 2025-11-30 | I9: 6259282 | J9: 12 | K9: 1 | L9: 2026-01-20 09:28:09.662537000
A10: =+C10&G10&H10&D10 -> UNIV_OPERcarteira_contabilistica2025-11-30COERÊNCIA | B10: =+C10&G10&H10&D10&K10 -> UNIV_OPERcarteira_contabilistica2025-11-30COERÊNCIA1 | C10: UNIV_OPER | D10: COERÊNCIA | E10: CD_LOAN_TAPES_BCE.LT001_UNIV_OPER | F10: BU_LOANTAPE_WORK.LT001_UNIV_OPER | G10: carteira_contabilistica | H10: 2025-11-30 | I10: 6259282 | J10: 0 | K10: 1 | L10: 2026-01-20 09:28:09.662537000
A11: =+C11&G11&H11&D11 -> UNIV_OPERinstrumento_financeiro2025-11-30COERÊNCIA | B11: =+C11&G11&H11&D11&K11 -> UNIV_OPERinstrumento_financeiro2025-11-30COERÊNCIA1 | C11: UNIV_OPER | D11: COERÊNCIA | E11: CD_LOAN_TAPES_BCE.LT001_UNIV_OPER | F11: BU_LOANTAPE_WORK.LT001_UNIV_OPER | G11: instrumento_financeiro | H11: 2025-11-30 | I11: 6259282 | J11: 0 | K11: 1 | L11: 2026-01-20 09:28:09.662537000
A12: =+C12&G12&H12&D12 -> UNIV_OPERcontraparte2025-11-30COERÊNCIA | B12: =+C12&G12&H12&D12&K12 -> UNIV_OPERcontraparte2025-11-30COERÊNCIA1 | C12: UNIV_OPER | D12: COERÊNCIA | E12: CD_LOAN_TAPES_BCE.LT001_UNIV_OPER | F12: BU_LOANTAPE_WORK.LT001_UNIV_OPER | G12: contraparte | H12: 2025-11-30 | I12: 6259282 | J12: 0 | K12: 1 | L12: 2026-01-20 09:28:09.662537000
A13: =+C13&G13&H13&D13 -> UNIV_OPERcontraparte_i2025-11-30COERÊNCIA | B13: =+C13&G13&H13&D13&K13 -> UNIV_OPERcontraparte_i2025-11-30COERÊNCIA1 | C13: UNIV_OPER | D13: COERÊNCIA | E13: CD_LOAN_TAPES_BCE.LT001_UNIV_OPER | F13: BU_LOANTAPE_WORK.LT001_UNIV_OPER | G13: contraparte_i | H13: 2025-11-30 | I13: 6259282 | J13: 0 | K13: 1 | L13: 2026-01-20 09:28:09.662537000
A14: =+C14&G14&H14&D14 -> UNIV_OPERproduto2025-11-30COERÊNCIA | B14: =+C14&G14&H14&D14&K14 -> UNIV_OPERproduto2025-11-30COERÊNCIA1 | C14: UNIV_OPER | D14: COERÊNCIA | E14: CD_LOAN_TAPES_BCE.LT001_UNIV_OPER | F14: BU_LOANTAPE_WORK.LT001_UNIV_OPER | G14: produto | H14: 2025-11-30 | I14: 6259282 | J14: 0 | K14: 1 | L14: 2026-01-20 09:28:09.662537000
A15: =+C15&G15&H15&D15 -> UNIV_OPERtipo_conta2025-11-30COERÊNCIA | B15: =+C15&G15&H15&D15&K15 -> UNIV_OPERtipo_conta2025-11-30COERÊNCIA1 | C15: UNIV_OPER | D15: COERÊNCIA | E15: CD_LOAN_TAPES_BCE.LT001_UNIV_OPER | F15: BU_LOANTAPE_WORK.LT001_UNIV_OPER | G15: tipo_conta | H15: 2025-11-30 | I15: 6259282 | J15: 0 | K15: 1 | L15: 2026-01-20 09:28:09.662537000
A16: =+C16&G16&H16&D16 -> UNIV_OPERbruto_imparidade2025-11-30COERÊNCIA | B16: =+C16&G16&H16&D16&K16 -> UNIV_OPERbruto_imparidade2025-11-30COERÊNCIA1 | C16: UNIV_OPER | D16: COERÊNCIA | E16: CD_LOAN_TAPES_BCE.LT001_UNIV_OPER | F16: BU_LOANTAPE_WORK.LT001_UNIV_OPER | G16: bruto_imparidade | H16: 2025-11-30 | I16: 6259282 | J16: 0 | K16: 1 | L16: 2026-01-20 09:28:09.662537000
A17: =+C17&G17&H17&D17 -> UNIV_OPERcomposicao_valor2025-11-30COERÊNCIA | B17: =+C17&G17&H17&D17&K17 -> UNIV_OPERcomposicao_valor2025-11-30COERÊNCIA1 | C17: UNIV_OPER | D17: COERÊNCIA | E17: CD_LOAN_TAPES_BCE.LT001_UNIV_OPER | F17: BU_LOANTAPE_WORK.LT001_UNIV_OPER | G17: composicao_valor | H17: 2025-11-30 | I17: 6259282 | J17: 0 | K17: 1 | L17: 2026-01-20 09:28:09.662537000
A18: =+C18&G18&H18&D18 -> UNIV_OPERcolateral2025-11-30COERÊNCIA | B18: =+C18&G18&H18&D18&K18 -> UNIV_OPERcolateral2025-11-30COERÊNCIA1 | C18: UNIV_OPER | D18: COERÊNCIA | E18: CD_LOAN_TAPES_BCE.LT001_UNIV_OPER | F18: BU_LOANTAPE_WORK.LT001_UNIV_OPER | G18: colateral | H18: 2025-11-30 | I18: 6259282 | J18: 0 | K18: 1 | L18: 2026-01-20 09:28:09.662537000
A19: =+C19&G19&H19&D19 -> UNIV_OPERflag_poci2025-11-30COERÊNCIA | B19: =+C19&G19&H19&D19&K19 -> UNIV_OPERflag_poci2025-11-30COERÊNCIA1 | C19: UNIV_OPER | D19: COERÊNCIA | E19: CD_LOAN_TAPES_BCE.LT001_UNIV_OPER | F19: BU_LOANTAPE_WORK.LT001_UNIV_OPER | G19: flag_poci | H19: 2025-11-30 | I19: 6259282 | J19: 0 | K19: 1 | L19: 2026-01-20 09:28:09.662537000
A20: =+C20&G20&H20&D20 -> UNIV_OPERpurpose_code2025-11-30COERÊNCIA | B20: =+C20&G20&H20&D20&K20 -> UNIV_OPERpurpose_code2025-11-30COERÊNCIA1 | C20: UNIV_OPER | D20: COERÊNCIA | E20: CD_LOAN_TAPES_BCE.LT001_UNIV_OPER | F20: BU_LOANTAPE_WORK.LT001_UNIV_OPER | G20: purpose_code | H20: 2025-11-30 | I20: 6259282 | J20: 0 | K20: 1 | L20: 2026-01-20 09:28:09.662537000
... A23: =+C23&G23&H23&D23 -> UNIV_OPERstage_atual2025-11-30COERÊNCIA | B23: =+C23&G23&H23&D23&K23 -> UNIV_OPERstage_atual2025-11-30COERÊNCIA1 | C23: UNIV_OPER | D23: COERÊNCIA | E23: CD_LOAN_TAPES_BCE.LT001_UNIV_OPER | F23: BU_LOANTAPE_WORK.LT001_UNIV_OPER | G23: stage_atual | H23: 2025-11-30 | I23: 6259282 | J23: 0 | K23: 1 | L23: 2026-01-20 09:28:09.662537000
A24: =+C24&G24&H24&D24 | B24: =+C24&G24&H24&D24&K24
A25: =+C25&G25&H25&D25 | B25: =+C25&G25&H25&D25&K25
A26: =+C26&G26&H26&D26 | B26: =+C26&G26&H26&D26&K26
A27: =+C27&G27&H27&D27 | B27: =+C27&G27&H27&D27&K27
A28: =+C28&G28&H28&D28 | B28: =+C28&G28&H28&D28&K28
A29: =+C29&G29&H29&D29 | B29: =+C29&G29&H29&D29&K29
A30: =+C30&G30&H30&D30 | B30: =+C30&G30&H30&D30&K30
A31: =+C31&G31&H31&D31 | B31: =+C31&G31&H31&D31&K31
A32: =+C32&G32&H32&D32 | B32: =+C32&G32&H32&D32&K32
A33: =+C33&G33&H33&D33 | B33: =+C33&G33&H33&D33&K33
A34: =+C34&G34&H34&D34 | B34: =+C34&G34&H34&D34&K34
A35: =+C35&G35&H35&D35 | B35: =+C35&G35&H35&D35&K35
... A700: =+C700&G700&H700&D700 | B700: =+C700&G700&H700&D700&K700
