Workbook

Sheet 0. Instruções
B6: 0. Instruções
B8: Projeto | D8: Testes MBDT
B9: Âmbito | D9: Análise dos campo da Loan Tape MBDT
B11: Para a validação dos campos da Loan Tape MBDT é necessário percorrer os seguintes steps:
B14: 1. Atualizar o script de simulação com o campo em análise.
B15: 1.1. Verificar a especificação do campo em análise. Se aplicável, verificar se é necessário reportar valor para ajustes.
B16: 1.2. Montar a simulação do campo tendo atenção aos seguintes pormenores:
B17: a) Não vamos fazer JOIN com a tabela de parametrização (LT803). Em alternativa, montamos um CASE WHEN ou importamos a parametrização.
B18: b) Para operações de ajustes verificar se o campo deve reportar valor.
B19: c) Se for necessário aplicar algum filtro (ou tratamento) que não está na especificação deixar um comentário no código.
B20: d) Garantir que não existem duplicados e deixar no código o número de registos de cada LEFT JOIN.
B21: 2. Executar no HUE (em HIVE) o CREATE TABLE do script de simulação.
B22: 3. Executar no HUE o script de controlo de universo.
B23: a) O número de registos em comum tem de ser igual ao número de registos do teste de coerência. Caso tenhamos registos que não são comuns é necessário ver exemplos para ver o que está a acontecer.
B24: 4. Verificar com IT o nome da tabela a testar e filtros. Caso seja necessário, atualizar as tabelas infra:
C26: Nome da Tabela | D26: Tabela Loan Tape PM | E26: Tabela Simulada | F26: Chave 1 | G26: Chave 2
C27: Univ_Oper | D27: lt001_univ_oper | E27: lt001_univ_oper | F27: concat(cempresa, cbalcao, cnumecta, zdeposit, ccontab_final_ifrs, ccontab_final_pcsb, ccontab_final_cargabal, ccontab_final)
C28: Entity | D28: lt003_entity | E28: lt003_entity | F28: entty_id
C29: Instrument | D29: lt002_instrument | E29: lt002_instrument | F29: instrmnt_id
C30: Protection | D30: lt004_protection | E30: lt004_protection | F30: prtctn_id
C31: INSTR_ENTITY | D31: lt005_instr_ent | E31: lt005_instr_ent | F31: instrmnt_id | G31: entty_id
C32: INSTR_PROTECTION | D32: lt006_instr_prot | E32: lt006_instr_prot | F32: instrmnt_id | G32: prtctn_id
C34: Filtros
C35: Schema Loan Tape PM | D35: cd_loan_tapes_bce
C36: Schema Simulada | D36: bu_loantape_work
C37: nome_perimetro | D37: Individual Local
C38: segmento | D38: ESTR
C39: ambito | D39: PM
C40: ambito | D40: SRB_MBDT
C41: entidade | D41: 00100
C42: Filtro Loan Tape SRB_MBDT | D42: =+"ref_date='${ref_date}'"&" AND "&C37&"='"&D37&"' AND "&C38&"='"&D38&"' AND ambito='"&D40&"'"&" AND "&C41&"='"&D41&"'" -> ref_date='${ref_date}' AND nome_perimetro='Individual Local' AND segmento='ESTR' AND ambito='SRB_MBDT' AND entidade='00100'
C43: Filtro SimuladaFiltro Loan Tape PM | D43: =+"ref_date='${ref_date}'"&" AND "&C37&"='"&D37&"' AND "&C38&"='"&D38&"' AND ambito='"&D39&"'"&" AND "&C41&"='"&D41&"'" -> ref_date='${ref_date}' AND nome_perimetro='Individual Local' AND segmento='ESTR' AND ambito='PM' AND entidade='00100'
B45: 5. Executar no HUE a bateria de testes da sheet 2. Script para o campo em análise
B46: a) Analisar resultados. Caso no teste de coerência conste diferenças é necessário ver exemplos. Deixo abaixo uma query de exemplo:
C48: SELECT *
C49: FROM
C50: (SELECT instrmnt_id,
C51: LNS_CLLTRLZD_CLSSFCTN
C52: FROM BU_LOANTAPE_WORK.LT002_INSTRUMENT
C53: WHERE ref_date='${ref_date}'
C54: AND nome_perimetro='Individual Corporativo'
C55: AND segmento='ESTR'
C56: AND ambito='PILAR3')X
C57: INNER JOIN
C58: (SELECT instrmnt_id AS instrmnt_id_SIMUL,
C59: LNS_CLLTRLZD_CLSSFCTN AS LNS_CLLTRLZD_CLSSFCTN_SIMUL
... C61: WHERE COALESCE(CAST(X.LNS_CLLTRLZD_CLSSFCTN AS STRING),'')<>COALESCE(CAST(Y.LNS_CLLTRLZD_CLSSFCTN_SIMUL AS STRING),'')
B69: 6. XXX
B70: 7. XXX

Sheet 1. Status
H6: 1. Status dos Testes
H8: REF_DATE | I8: 45991
B9: Auxiliar
B10: Coerência | C10: Validade | D10: Caracteres Especiais | E10: Missings | F10: Not applicable | H10: Tabela | I10: Campo | J10: Testes Corridos (#) | K10: Número de Registos ID1. (#) | L10: ID Exec. 1. | M10: 1. Erros de Coerência (#) | N10: Número de Registos ID2&9 (#) | O10: ID Exec. 2 | P10: 2. Erros de Valores Admitidos (#) | Q10: ID Exec. 3. | R10: 3. Erros de Caract. Especiais (#) | S10: ID Exec. 4. | T10: 4. Registos com Missing (#) | U10: ID Exec. 5. | V10: 5. Registos com N/A (#) | W10: 6. Valor Mínimo | X10: 7. Valor Máximo | Y10: Comentário | Z10: Status
A11: =+H11&I11&$I$8 -> UNIV_OPERcempresa45991 | B11: {=+MAX(IF('ID1&5'!A:A='1. Status'!A11&'1. Status'!$B$10,'ID1&5'!K:K))} -> 0 | C11: {=+MAX(IF('ID1&5'!A:A='1. Status'!A11&'1. Status'!$C$10,'ID1&5'!K:K))} -> 0 | D11: {=+MAX(IF('ID1&5'!A:A='1. Status'!A11&'1. Status'!$D$10,'ID1&5'!K:K))} -> 0 | E11: {=+MAX(IF('ID1&5'!A:A='1. Status'!A11&'1. Status'!$E$10,'ID1&5'!K:K))} -> 0 | F11: {=+MAX(IF('ID1&5'!A:A='1. Status'!A11&'1. Status'!$F$10,'ID1&5'!K:K))} -> 0 | H11: UNIV_OPER | I11: cempresa | J11: =+COUNTIF('ID1&5'!G:G,'1. Status'!I11) -> 0 | K11: =+IFERROR(VLOOKUP(CONCATENATE(A11,$B$10,B11),'ID1&5'!B:J,8,FALSE),"-") -> - | L11: =+IFERROR(VLOOKUP(B11,'ID1&5'!K:L,2,FALSE),"-") -> - | M11: =+IFERROR(VLOOKUP(CONCATENATE(A11,$B$10,B11),'ID1&5'!B:J,9,FALSE),"-") -> - | N11: =+IFERROR(VLOOKUP(CONCATENATE(A11,$C$10,C11),'ID1&5'!B:J,8,FALSE),"-") -> - | O11: =+IFERROR(VLOOKUP(C11,'ID1&5'!K:L,2,FALSE),"-") -> - | P11: =+IFERROR(VLOOKUP(CONCATENATE(A11,$C$10,C11),'ID1&5'!B:J,9,FALSE),"-") -> - | Q11: =+IFERROR(VLOOKUP(D11,'ID1&5'!K:L,2,FALSE),"-") -> - | R11: =+IFERROR(VLOOKUP(CONCATENATE(A11,$D$10,D11),'ID1&5'!B:J,9,FALSE),"-") -> - | S11: =+IFERROR(VLOOKUP(E11,'ID1&5'!K:L,2,FALSE),"-") -> - | T11: =+IFERROR(VLOOKUP(CONCATENATE(A11,$E$10,E11),'ID1&5'!B:J,9,FALSE),"-") -> - | U11: =+IFERROR(VLOOKUP(F11,'ID1&5'!K:L,2,FALSE),"-") -> - | V11: =+IFERROR(VLOOKUP(CONCATENATE(A11,$F$10,F11),'ID1&5'!B:J,9,FALSE),"-") -> - | W11: =+IFERROR(VLOOKUP(A11,'ID6&7'!A:I,9,FALSE),"-") -> - | X11: =+IFERROR(VLOOKUP(A11,'ID6&7'!A:J,10,FALSE),"-") -> - | Z11: =+IF(J11=0,"Por iniciar",IF(OR(K11="-",M11="-",P11="-",R11="-",T11="-",V11="-"),"Em testes",IF(AND(M11=0,P11=0,R11=0,T11<>K11,V11<>K11),"OK","NOK"))) -> Por iniciar
A12: =+H12&I12&$I$8 -> UNIV_OPERcbalcao45991 | B12: {=+MAX(IF('ID1&5'!A:A='1. Status'!A12&'1. Status'!$B$10,'ID1&5'!K:K))} -> 0 | C12: {=+MAX(IF('ID1&5'!A:A='1. Status'!A12&'1. Status'!$C$10,'ID1&5'!K:K))} -> 0 | D12: {=+MAX(IF('ID1&5'!A:A='1. Status'!A12&'1. Status'!$D$10,'ID1&5'!K:K))} -> 0 | E12: {=+MAX(IF('ID1&5'!A:A='1. Status'!A12&'1. Status'!$E$10,'ID1&5'!K:K))} -> 0 | F12: {=+MAX(IF('ID1&5'!A:A='1. Status'!A12&'1. Status'!$F$10,'ID1&5'!K:K))} -> 0 | H12: UNIV_OPER | I12: cbalcao | J12: =+COUNTIF('ID1&5'!G:G,'1. Status'!I12) -> 0 | K12: =+IFERROR(VLOOKUP(CONCATENATE(A12,$B$10,B12),'ID1&5'!B:J,8,FALSE),"-") -> - | L12: =+IFERROR(VLOOKUP(B12,'ID1&5'!K:L,2,FALSE),"-") -> - | M12: =+IFERROR(VLOOKUP(CONCATENATE(A12,$B$10,B12),'ID1&5'!B:J,9,FALSE),"-") -> - | N12: =+IFERROR(VLOOKUP(CONCATENATE(A12,$C$10,C12),'ID1&5'!B:J,8,FALSE),"-") -> - | O12: =+IFERROR(VLOOKUP(C12,'ID1&5'!K:L,2,FALSE),"-") -> - | P12: =+IFERROR(VLOOKUP(CONCATENATE(A12,$C$10,C12),'ID1&5'!B:J,9,FALSE),"-") -> - | Q12: =+IFERROR(VLOOKUP(D12,'ID1&5'!K:L,2,FALSE),"-") -> - | R12: =+IFERROR(VLOOKUP(CONCATENATE(A12,$D$10,D12),'ID1&5'!B:J,9,FALSE),"-") -> - | S12: =+IFERROR(VLOOKUP(E12,'ID1&5'!K:L,2,FALSE),"-") -> - | T12: =+IFERROR(VLOOKUP(CONCATENATE(A12,$E$10,E12),'ID1&5'!B:J,9,FALSE),"-") -> - | U12: =+IFERROR(VLOOKUP(F12,'ID1&5'!K:L,2,FALSE),"-") -> - | V12: =+IFERROR(VLOOKUP(CONCATENATE(A12,$F$10,F12),'ID1&5'!B:J,9,FALSE),"-") -> - | W12: =+IFERROR(VLOOKUP(A12,'ID6&7'!A:I,9,FALSE),"-") -> - | X12: =+IFERROR(VLOOKUP(A12,'ID6&7'!A:J,10,FALSE),"-") -> - | Z12: =+IF(J12=0,"Por iniciar",IF(OR(K12="-",M12="-",P12="-",R12="-",T12="-",V12="-"),"Em testes",IF(AND(M12=0,P12=0,R12=0,T12<>K12,V12<>K12),"OK","NOK"))) -> Por iniciar
A13: =+H13&I13&$I$8 -> UNIV_OPERcnumecta45991 | B13: {=+MAX(IF('ID1&5'!A:A='1. Status'!A13&'1. Status'!$B$10,'ID1&5'!K:K))} -> 0 | C13: {=+MAX(IF('ID1&5'!A:A='1. Status'!A13&'1. Status'!$C$10,'ID1&5'!K:K))} -> 0 | D13: {=+MAX(IF('ID1&5'!A:A='1. Status'!A13&'1. Status'!$D$10,'ID1&5'!K:K))} -> 0 | E13: {=+MAX(IF('ID1&5'!A:A='1. Status'!A13&'1. Status'!$E$10,'ID1&5'!K:K))} -> 0 | F13: {=+MAX(IF('ID1&5'!A:A='1. Status'!A13&'1. Status'!$F$10,'ID1&5'!K:K))} -> 0 | H13: UNIV_OPER | I13: cnumecta | J13: =+COUNTIF('ID1&5'!G:G,'1. Status'!I13) -> 0 | K13: =+IFERROR(VLOOKUP(CONCATENATE(A13,$B$10,B13),'ID1&5'!B:J,8,FALSE),"-") -> - | L13: =+IFERROR(VLOOKUP(B13,'ID1&5'!K:L,2,FALSE),"-") -> - | M13: =+IFERROR(VLOOKUP(CONCATENATE(A13,$B$10,B13),'ID1&5'!B:J,9,FALSE),"-") -> - | N13: =+IFERROR(VLOOKUP(CONCATENATE(A13,$C$10,C13),'ID1&5'!B:J,8,FALSE),"-") -> - | O13: =+IFERROR(VLOOKUP(C13,'ID1&5'!K:L,2,FALSE),"-") -> - | P13: =+IFERROR(VLOOKUP(CONCATENATE(A13,$C$10,C13),'ID1&5'!B:J,9,FALSE),"-") -> - | Q13: =+IFERROR(VLOOKUP(D13,'ID1&5'!K:L,2,FALSE),"-") -> - | R13: =+IFERROR(VLOOKUP(CONCATENATE(A13,$D$10,D13),'ID1&5'!B:J,9,FALSE),"-") -> - | S13: =+IFERROR(VLOOKUP(E13,'ID1&5'!K:L,2,FALSE),"-") -> - | T13: =+IFERROR(VLOOKUP(CONCATENATE(A13,$E$10,E13),'ID1&5'!B:J,9,FALSE),"-") -> - | U13: =+IFERROR(VLOOKUP(F13,'ID1&5'!K:L,2,FALSE),"-") -> - | V13: =+IFERROR(VLOOKUP(CONCATENATE(A13,$F$10,F13),'ID1&5'!B:J,9,FALSE),"-") -> - | W13: =+IFERROR(VLOOKUP(A13,'ID6&7'!A:I,9,FALSE),"-") -> - | X13: =+IFERROR(VLOOKUP(A13,'ID6&7'!A:J,10,FALSE),"-") -> - | Z13: =+IF(J13=0,"Por iniciar",IF(OR(K13="-",M13="-",P13="-",R13="-",T13="-",V13="-"),"Em testes",IF(AND(M13=0,P13=0,R13=0,T13<>K13,V13<>K13),"OK","NOK"))) -> Por iniciar
A14: =+H14&I14&$I$8 -> UNIV_OPERzdeposit45991 | B14: {=+MAX(IF('ID1&5'!A:A='1. Status'!A14&'1. Status'!$B$10,'ID1&5'!K:K))} -> 0 | C14: {=+MAX(IF('ID1&5'!A:A='1. Status'!A14&'1. Status'!$C$10,'ID1&5'!K:K))} -> 0 | D14: {=+MAX(IF('ID1&5'!A:A='1. Status'!A14&'1. Status'!$D$10,'ID1&5'!K:K))} -> 0 | E14: {=+MAX(IF('ID1&5'!A:A='1. Status'!A14&'1. Status'!$E$10,'ID1&5'!K:K))} -> 0 | F14: {=+MAX(IF('ID1&5'!A:A='1. Status'!A14&'1. Status'!$F$10,'ID1&5'!K:K))} -> 0 | H14: UNIV_OPER | I14: zdeposit | J14: =+COUNTIF('ID1&5'!G:G,'1. Status'!I14) -> 0 | K14: =+IFERROR(VLOOKUP(CONCATENATE(A14,$B$10,B14),'ID1&5'!B:J,8,FALSE),"-") -> - | L14: =+IFERROR(VLOOKUP(B14,'ID1&5'!K:L,2,FALSE),"-") -> - | M14: =+IFERROR(VLOOKUP(CONCATENATE(A14,$B$10,B14),'ID1&5'!B:J,9,FALSE),"-") -> - | N14: =+IFERROR(VLOOKUP(CONCATENATE(A14,$C$10,C14),'ID1&5'!B:J,8,FALSE),"-") -> - | O14: =+IFERROR(VLOOKUP(C14,'ID1&5'!K:L,2,FALSE),"-") -> - | P14: =+IFERROR(VLOOKUP(CONCATENATE(A14,$C$10,C14),'ID1&5'!B:J,9,FALSE),"-") -> - | Q14: =+IFERROR(VLOOKUP(D14,'ID1&5'!K:L,2,FALSE),"-") -> - | R14: =+IFERROR(VLOOKUP(CONCATENATE(A14,$D$10,D14),'ID1&5'!B:J,9,FALSE),"-") -> - | S14: =+IFERROR(VLOOKUP(E14,'ID1&5'!K:L,2,FALSE),"-") -> - | T14: =+IFERROR(VLOOKUP(CONCATENATE(A14,$E$10,E14),'ID1&5'!B:J,9,FALSE),"-") -> - | U14: =+IFERROR(VLOOKUP(F14,'ID1&5'!K:L,2,FALSE),"-") -> - | V14: =+IFERROR(VLOOKUP(CONCATENATE(A14,$F$10,F14),'ID1&5'!B:J,9,FALSE),"-") -> - | W14: =+IFERROR(VLOOKUP(A14,'ID6&7'!A:I,9,FALSE),"-") -> - | X14: =+IFERROR(VLOOKUP(A14,'ID6&7'!A:J,10,FALSE),"-") -> - | Z14: =+IF(J14=0,"Por iniciar",IF(OR(K14="-",M14="-",P14="-",R14="-",T14="-",V14="-"),"Em testes",IF(AND(M14=0,P14=0,R14=0,T14<>K14,V14<>K14),"OK","NOK"))) -> Por iniciar
A15: =+H15&I15&$I$8 -> UNIV_OPERzcliente45991 | B15: {=+MAX(IF('ID1&5'!A:A='1. Status'!A15&'1. Status'!$B$10,'ID1&5'!K:K))} -> 0 | C15: {=+MAX(IF('ID1&5'!A:A='1. Status'!A15&'1. Status'!$C$10,'ID1&5'!K:K))} -> 0 | D15: {=+MAX(IF('ID1&5'!A:A='1. Status'!A15&'1. Status'!$D$10,'ID1&5'!K:K))} -> 0 | E15: {=+MAX(IF('ID1&5'!A:A='1. Status'!A15&'1. Status'!$E$10,'ID1&5'!K:K))} -> 0 | F15: {=+MAX(IF('ID1&5'!A:A='1. Status'!A15&'1. Status'!$F$10,'ID1&5'!K:K))} -> 0 | H15: UNIV_OPER | I15: zcliente | J15: =+COUNTIF('ID1&5'!G:G,'1. Status'!I15) -> 0 | K15: =+IFERROR(VLOOKUP(CONCATENATE(A15,$B$10,B15),'ID1&5'!B:J,8,FALSE),"-") -> - | L15: =+IFERROR(VLOOKUP(B15,'ID1&5'!K:L,2,FALSE),"-") -> - | M15: =+IFERROR(VLOOKUP(CONCATENATE(A15,$B$10,B15),'ID1&5'!B:J,9,FALSE),"-") -> - | N15: =+IFERROR(VLOOKUP(CONCATENATE(A15,$C$10,C15),'ID1&5'!B:J,8,FALSE),"-") -> - | O15: =+IFERROR(VLOOKUP(C15,'ID1&5'!K:L,2,FALSE),"-") -> - | P15: =+IFERROR(VLOOKUP(CONCATENATE(A15,$C$10,C15),'ID1&5'!B:J,9,FALSE),"-") -> - | Q15: =+IFERROR(VLOOKUP(D15,'ID1&5'!K:L,2,FALSE),"-") -> - | R15: =+IFERROR(VLOOKUP(CONCATENATE(A15,$D$10,D15),'ID1&5'!B:J,9,FALSE),"-") -> - | S15: =+IFERROR(VLOOKUP(E15,'ID1&5'!K:L,2,FALSE),"-") -> - | T15: =+IFERROR(VLOOKUP(CONCATENATE(A15,$E$10,E15),'ID1&5'!B:J,9,FALSE),"-") -> - | U15: =+IFERROR(VLOOKUP(F15,'ID1&5'!K:L,2,FALSE),"-") -> - | V15: =+IFERROR(VLOOKUP(CONCATENATE(A15,$F$10,F15),'ID1&5'!B:J,9,FALSE),"-") -> - | W15: =+IFERROR(VLOOKUP(A15,'ID6&7'!A:I,9,FALSE),"-") -> - | X15: =+IFERROR(VLOOKUP(A15,'ID6&7'!A:J,10,FALSE),"-") -> - | Z15: =+IF(J15=0,"Por iniciar",IF(OR(K15="-",M15="-",P15="-",R15="-",T15="-",V15="-"),"Em testes",IF(AND(M15=0,P15=0,R15=0,T15<>K15,V15<>K15),"OK","NOK"))) -> Por iniciar
A16: =+H16&I16&$I$8 -> UNIV_OPERccontab_final_ifrs45991 | B16: {=+MAX(IF('ID1&5'!A:A='1. Status'!A16&'1. Status'!$B$10,'ID1&5'!K:K))} -> 0 | C16: {=+MAX(IF('ID1&5'!A:A='1. Status'!A16&'1. Status'!$C$10,'ID1&5'!K:K))} -> 0 | D16: {=+MAX(IF('ID1&5'!A:A='1. Status'!A16&'1. Status'!$D$10,'ID1&5'!K:K))} -> 0 | E16: {=+MAX(IF('ID1&5'!A:A='1. Status'!A16&'1. Status'!$E$10,'ID1&5'!K:K))} -> 0 | F16: {=+MAX(IF('ID1&5'!A:A='1. Status'!A16&'1. Status'!$F$10,'ID1&5'!K:K))} -> 0 | H16: UNIV_OPER | I16: ccontab_final_ifrs | J16: =+COUNTIF('ID1&5'!G:G,'1. Status'!I16) -> 0 | K16: =+IFERROR(VLOOKUP(CONCATENATE(A16,$B$10,B16),'ID1&5'!B:J,8,FALSE),"-") -> - | L16: =+IFERROR(VLOOKUP(B16,'ID1&5'!K:L,2,FALSE),"-") -> - | M16: =+IFERROR(VLOOKUP(CONCATENATE(A16,$B$10,B16),'ID1&5'!B:J,9,FALSE),"-") -> - | N16: =+IFERROR(VLOOKUP(CONCATENATE(A16,$C$10,C16),'ID1&5'!B:J,8,FALSE),"-") -> - | O16: =+IFERROR(VLOOKUP(C16,'ID1&5'!K:L,2,FALSE),"-") -> - | P16: =+IFERROR(VLOOKUP(CONCATENATE(A16,$C$10,C16),'ID1&5'!B:J,9,FALSE),"-") -> - | Q16: =+IFERROR(VLOOKUP(D16,'ID1&5'!K:L,2,FALSE),"-") -> - | R16: =+IFERROR(VLOOKUP(CONCATENATE(A16,$D$10,D16),'ID1&5'!B:J,9,FALSE),"-") -> - | S16: =+IFERROR(VLOOKUP(E16,'ID1&5'!K:L,2,FALSE),"-") -> - | T16: =+IFERROR(VLOOKUP(CONCATENATE(A16,$E$10,E16),'ID1&5'!B:J,9,FALSE),"-") -> - | U16: =+IFERROR(VLOOKUP(F16,'ID1&5'!K:L,2,FALSE),"-") -> - | V16: =+IFERROR(VLOOKUP(CONCATENATE(A16,$F$10,F16),'ID1&5'!B:J,9,FALSE),"-") -> - | W16: =+IFERROR(VLOOKUP(A16,'ID6&7'!A:I,9,FALSE),"-") -> - | X16: =+IFERROR(VLOOKUP(A16,'ID6&7'!A:J,10,FALSE),"-") -> - | Z16: =+IF(J16=0,"Por iniciar",IF(OR(K16="-",M16="-",P16="-",R16="-",T16="-",V16="-"),"Em testes",IF(AND(M16=0,P16=0,R16=0,T16<>K16,V16<>K16),"OK","NOK"))) -> Por iniciar
A17: =+H17&I17&$I$8 -> UNIV_OPERccontab_final_pcsb45991 | B17: {=+MAX(IF('ID1&5'!A:A='1. Status'!A17&'1. Status'!$B$10,'ID1&5'!K:K))} -> 0 | C17: {=+MAX(IF('ID1&5'!A:A='1. Status'!A17&'1. Status'!$C$10,'ID1&5'!K:K))} -> 0 | D17: {=+MAX(IF('ID1&5'!A:A='1. Status'!A17&'1. Status'!$D$10,'ID1&5'!K:K))} -> 0 | E17: {=+MAX(IF('ID1&5'!A:A='1. Status'!A17&'1. Status'!$E$10,'ID1&5'!K:K))} -> 0 | F17: {=+MAX(IF('ID1&5'!A:A='1. Status'!A17&'1. Status'!$F$10,'ID1&5'!K:K))} -> 0 | H17: UNIV_OPER | I17: ccontab_final_pcsb | J17: =+COUNTIF('ID1&5'!G:G,'1. Status'!I17) -> 0 | K17: =+IFERROR(VLOOKUP(CONCATENATE(A17,$B$10,B17),'ID1&5'!B:J,8,FALSE),"-") -> - | L17: =+IFERROR(VLOOKUP(B17,'ID1&5'!K:L,2,FALSE),"-") -> - | M17: =+IFERROR(VLOOKUP(CONCATENATE(A17,$B$10,B17),'ID1&5'!B:J,9,FALSE),"-") -> - | N17: =+IFERROR(VLOOKUP(CONCATENATE(A17,$C$10,C17),'ID1&5'!B:J,8,FALSE),"-") -> - | O17: =+IFERROR(VLOOKUP(C17,'ID1&5'!K:L,2,FALSE),"-") -> - | P17: =+IFERROR(VLOOKUP(CONCATENATE(A17,$C$10,C17),'ID1&5'!B:J,9,FALSE),"-") -> - | Q17: =+IFERROR(VLOOKUP(D17,'ID1&5'!K:L,2,FALSE),"-") -> - | R17: =+IFERROR(VLOOKUP(CONCATENATE(A17,$D$10,D17),'ID1&5'!B:J,9,FALSE),"-") -> - | S17: =+IFERROR(VLOOKUP(E17,'ID1&5'!K:L,2,FALSE),"-") -> - | T17: =+IFERROR(VLOOKUP(CONCATENATE(A17,$E$10,E17),'ID1&5'!B:J,9,FALSE),"-") -> - | U17: =+IFERROR(VLOOKUP(F17,'ID1&5'!K:L,2,FALSE),"-") -> - | V17: =+IFERROR(VLOOKUP(CONCATENATE(A17,$F$10,F17),'ID1&5'!B:J,9,FALSE),"-") -> - | W17: =+IFERROR(VLOOKUP(A17,'ID6&7'!A:I,9,FALSE),"-") -> - | X17: =+IFERROR(VLOOKUP(A17,'ID6&7'!A:J,10,FALSE),"-") -> - | Z17: =+IF(J17=0,"Por iniciar",IF(OR(K17="-",M17="-",P17="-",R17="-",T17="-",V17="-"),"Em testes",IF(AND(M17=0,P17=0,R17=0,T17<>K17,V17<>K17),"OK","NOK"))) -> Por iniciar
A18: =+H18&I18&$I$8 -> UNIV_OPERccontab_final_cargabal45991 | B18: {=+MAX(IF('ID1&5'!A:A='1. Status'!A18&'1. Status'!$B$10,'ID1&5'!K:K))} -> 0 | C18: {=+MAX(IF('ID1&5'!A:A='1. Status'!A18&'1. Status'!$C$10,'ID1&5'!K:K))} -> 0 | D18: {=+MAX(IF('ID1&5'!A:A='1. Status'!A18&'1. Status'!$D$10,'ID1&5'!K:K))} -> 0 | E18: {=+MAX(IF('ID1&5'!A:A='1. Status'!A18&'1. Status'!$E$10,'ID1&5'!K:K))} -> 0 | F18: {=+MAX(IF('ID1&5'!A:A='1. Status'!A18&'1. Status'!$F$10,'ID1&5'!K:K))} -> 0 | H18: UNIV_OPER | I18: ccontab_final_cargabal | J18: =+COUNTIF('ID1&5'!G:G,'1. Status'!I18) -> 0 | K18: =+IFERROR(VLOOKUP(CONCATENATE(A18,$B$10,B18),'ID1&5'!B:J,8,FALSE),"-") -> - | L18: =+IFERROR(VLOOKUP(B18,'ID1&5'!K:L,2,FALSE),"-") -> - | M18: =+IFERROR(VLOOKUP(CONCATENATE(A18,$B$10,B18),'ID1&5'!B:J,9,FALSE),"-") -> - | N18: =+IFERROR(VLOOKUP(CONCATENATE(A18,$C$10,C18),'ID1&5'!B:J,8,FALSE),"-") -> - | O18: =+IFERROR(VLOOKUP(C18,'ID1&5'!K:L,2,FALSE),"-") -> - | P18: =+IFERROR(VLOOKUP(CONCATENATE(A18,$C$10,C18),'ID1&5'!B:J,9,FALSE),"-") -> - | Q18: =+IFERROR(VLOOKUP(D18,'ID1&5'!K:L,2,FALSE),"-") -> - | R18: =+IFERROR(VLOOKUP(CONCATENATE(A18,$D$10,D18),'ID1&5'!B:J,9,FALSE),"-") -> - | S18: =+IFERROR(VLOOKUP(E18,'ID1&5'!K:L,2,FALSE),"-") -> - | T18: =+IFERROR(VLOOKUP(CONCATENATE(A18,$E$10,E18),'ID1&5'!B:J,9,FALSE),"-") -> - | U18: =+IFERROR(VLOOKUP(F18,'ID1&5'!K:L,2,FALSE),"-") -> - | V18: =+IFERROR(VLOOKUP(CONCATENATE(A18,$F$10,F18),'ID1&5'!B:J,9,FALSE),"-") -> - | W18: =+IFERROR(VLOOKUP(A18,'ID6&7'!A:I,9,FALSE),"-") -> - | X18: =+IFERROR(VLOOKUP(A18,'ID6&7'!A:J,10,FALSE),"-") -> - | Z18: =+IF(J18=0,"Por iniciar",IF(OR(K18="-",M18="-",P18="-",R18="-",T18="-",V18="-"),"Em testes",IF(AND(M18=0,P18=0,R18=0,T18<>K18,V18<>K18),"OK","NOK"))) -> Por iniciar
A19: =+H19&I19&$I$8 -> UNIV_OPERccontab_final45991 | B19: {=+MAX(IF('ID1&5'!A:A='1. Status'!A19&'1. Status'!$B$10,'ID1&5'!K:K))} -> 0 | C19: {=+MAX(IF('ID1&5'!A:A='1. Status'!A19&'1. Status'!$C$10,'ID1&5'!K:K))} -> 0 | D19: {=+MAX(IF('ID1&5'!A:A='1. Status'!A19&'1. Status'!$D$10,'ID1&5'!K:K))} -> 0 | E19: {=+MAX(IF('ID1&5'!A:A='1. Status'!A19&'1. Status'!$E$10,'ID1&5'!K:K))} -> 0 | F19: {=+MAX(IF('ID1&5'!A:A='1. Status'!A19&'1. Status'!$F$10,'ID1&5'!K:K))} -> 0 | H19: UNIV_OPER | I19: ccontab_final | J19: =+COUNTIF('ID1&5'!G:G,'1. Status'!I19) -> 0 | K19: =+IFERROR(VLOOKUP(CONCATENATE(A19,$B$10,B19),'ID1&5'!B:J,8,FALSE),"-") -> - | L19: =+IFERROR(VLOOKUP(B19,'ID1&5'!K:L,2,FALSE),"-") -> - | M19: =+IFERROR(VLOOKUP(CONCATENATE(A19,$B$10,B19),'ID1&5'!B:J,9,FALSE),"-") -> - | N19: =+IFERROR(VLOOKUP(CONCATENATE(A19,$C$10,C19),'ID1&5'!B:J,8,FALSE),"-") -> - | O19: =+IFERROR(VLOOKUP(C19,'ID1&5'!K:L,2,FALSE),"-") -> - | P19: =+IFERROR(VLOOKUP(CONCATENATE(A19,$C$10,C19),'ID1&5'!B:J,9,FALSE),"-") -> - | Q19: =+IFERROR(VLOOKUP(D19,'ID1&5'!K:L,2,FALSE),"-") -> - | R19: =+IFERROR(VLOOKUP(CONCATENATE(A19,$D$10,D19),'ID1&5'!B:J,9,FALSE),"-") -> - | S19: =+IFERROR(VLOOKUP(E19,'ID1&5'!K:L,2,FALSE),"-") -> - | T19: =+IFERROR(VLOOKUP(CONCATENATE(A19,$E$10,E19),'ID1&5'!B:J,9,FALSE),"-") -> - | U19: =+IFERROR(VLOOKUP(F19,'ID1&5'!K:L,2,FALSE),"-") -> - | V19: =+IFERROR(VLOOKUP(CONCATENATE(A19,$F$10,F19),'ID1&5'!B:J,9,FALSE),"-") -> - | W19: =+IFERROR(VLOOKUP(A19,'ID6&7'!A:I,9,FALSE),"-") -> - | X19: =+IFERROR(VLOOKUP(A19,'ID6&7'!A:J,10,FALSE),"-") -> - | Z19: =+IF(J19=0,"Por iniciar",IF(OR(K19="-",M19="-",P19="-",R19="-",T19="-",V19="-"),"Em testes",IF(AND(M19=0,P19=0,R19=0,T19<>K19,V19<>K19),"OK","NOK"))) -> Por iniciar
A20: =+H20&I20&$I$8 -> UNIV_OPERmsaldo_final45991 | B20: {=+MAX(IF('ID1&5'!A:A='1. Status'!A20&'1. Status'!$B$10,'ID1&5'!K:K))} -> 0 | C20: {=+MAX(IF('ID1&5'!A:A='1. Status'!A20&'1. Status'!$C$10,'ID1&5'!K:K))} -> 0 | D20: {=+MAX(IF('ID1&5'!A:A='1. Status'!A20&'1. Status'!$D$10,'ID1&5'!K:K))} -> 0 | E20: {=+MAX(IF('ID1&5'!A:A='1. Status'!A20&'1. Status'!$E$10,'ID1&5'!K:K))} -> 0 | F20: {=+MAX(IF('ID1&5'!A:A='1. Status'!A20&'1. Status'!$F$10,'ID1&5'!K:K))} -> 0 | H20: UNIV_OPER | I20: msaldo_final | J20: =+COUNTIF('ID1&5'!G:G,'1. Status'!I20) -> 0 | K20: =+IFERROR(VLOOKUP(CONCATENATE(A20,$B$10,B20),'ID1&5'!B:J,8,FALSE),"-") -> - | L20: =+IFERROR(VLOOKUP(B20,'ID1&5'!K:L,2,FALSE),"-") -> - | M20: =+IFERROR(VLOOKUP(CONCATENATE(A20,$B$10,B20),'ID1&5'!B:J,9,FALSE),"-") -> - | N20: =+IFERROR(VLOOKUP(CONCATENATE(A20,$C$10,C20),'ID1&5'!B:J,8,FALSE),"-") -> - | O20: =+IFERROR(VLOOKUP(C20,'ID1&5'!K:L,2,FALSE),"-") -> - | P20: =+IFERROR(VLOOKUP(CONCATENATE(A20,$C$10,C20),'ID1&5'!B:J,9,FALSE),"-") -> - | Q20: =+IFERROR(VLOOKUP(D20,'ID1&5'!K:L,2,FALSE),"-") -> - | R20: =+IFERROR(VLOOKUP(CONCATENATE(A20,$D$10,D20),'ID1&5'!B:J,9,FALSE),"-") -> - | S20: =+IFERROR(VLOOKUP(E20,'ID1&5'!K:L,2,FALSE),"-") -> - | T20: =+IFERROR(VLOOKUP(CONCATENATE(A20,$E$10,E20),'ID1&5'!B:J,9,FALSE),"-") -> - | U20: =+IFERROR(VLOOKUP(F20,'ID1&5'!K:L,2,FALSE),"-") -> - | V20: =+IFERROR(VLOOKUP(CONCATENATE(A20,$F$10,F20),'ID1&5'!B:J,9,FALSE),"-") -> - | W20: =+IFERROR(VLOOKUP(A20,'ID6&7'!A:I,9,FALSE),"-") -> - | X20: =+IFERROR(VLOOKUP(A20,'ID6&7'!A:J,10,FALSE),"-") -> - | Z20: =+IF(J20=0,"Por iniciar",IF(OR(K20="-",M20="-",P20="-",R20="-",T20="-",V20="-"),"Em testes",IF(AND(M20=0,P20=0,R20=0,T20<>K20,V20<>K20),"OK","NOK"))) -> Por iniciar
A21: =+H21&I21&$I$8 -> UNIV_OPERcarteira_contabilistica45991 | B21: {=+MAX(IF('ID1&5'!A:A='1. Status'!A21&'1. Status'!$B$10,'ID1&5'!K:K))} -> 0 | C21: {=+MAX(IF('ID1&5'!A:A='1. Status'!A21&'1. Status'!$C$10,'ID1&5'!K:K))} -> 0 | D21: {=+MAX(IF('ID1&5'!A:A='1. Status'!A21&'1. Status'!$D$10,'ID1&5'!K:K))} -> 0 | E21: {=+MAX(IF('ID1&5'!A:A='1. Status'!A21&'1. Status'!$E$10,'ID1&5'!K:K))} -> 0 | F21: {=+MAX(IF('ID1&5'!A:A='1. Status'!A21&'1. Status'!$F$10,'ID1&5'!K:K))} -> 0 | H21: UNIV_OPER | I21: carteira_contabilistica | J21: =+COUNTIF('ID1&5'!G:G,'1. Status'!I21) -> 0 | K21: =+IFERROR(VLOOKUP(CONCATENATE(A21,$B$10,B21),'ID1&5'!B:J,8,FALSE),"-") -> - | L21: =+IFERROR(VLOOKUP(B21,'ID1&5'!K:L,2,FALSE),"-") -> - | M21: =+IFERROR(VLOOKUP(CONCATENATE(A21,$B$10,B21),'ID1&5'!B:J,9,FALSE),"-") -> - | N21: =+IFERROR(VLOOKUP(CONCATENATE(A21,$C$10,C21),'ID1&5'!B:J,8,FALSE),"-") -> - | O21: =+IFERROR(VLOOKUP(C21,'ID1&5'!K:L,2,FALSE),"-") -> - | P21: =+IFERROR(VLOOKUP(CONCATENATE(A21,$C$10,C21),'ID1&5'!B:J,9,FALSE),"-") -> - | Q21: =+IFERROR(VLOOKUP(D21,'ID1&5'!K:L,2,FALSE),"-") -> - | R21: =+IFERROR(VLOOKUP(CONCATENATE(A21,$D$10,D21),'ID1&5'!B:J,9,FALSE),"-") -> - | S21: =+IFERROR(VLOOKUP(E21,'ID1&5'!K:L,2,FALSE),"-") -> - | T21: =+IFERROR(VLOOKUP(CONCATENATE(A21,$E$10,E21),'ID1&5'!B:J,9,FALSE),"-") -> - | U21: =+IFERROR(VLOOKUP(F21,'ID1&5'!K:L,2,FALSE),"-") -> - | V21: =+IFERROR(VLOOKUP(CONCATENATE(A21,$F$10,F21),'ID1&5'!B:J,9,FALSE),"-") -> - | W21: =+IFERROR(VLOOKUP(A21,'ID6&7'!A:I,9,FALSE),"-") -> - | X21: =+IFERROR(VLOOKUP(A21,'ID6&7'!A:J,10,FALSE),"-") -> - | Z21: =+IF(J21=0,"Por iniciar",IF(OR(K21="-",M21="-",P21="-",R21="-",T21="-",V21="-"),"Em testes",IF(AND(M21=0,P21=0,R21=0,T21<>K21,V21<>K21),"OK","NOK"))) -> Por iniciar
A22: =+H22&I22&$I$8 -> UNIV_OPERinstrumento_financeiro45991 | B22: {=+MAX(IF('ID1&5'!A:A='1. Status'!A22&'1. Status'!$B$10,'ID1&5'!K:K))} -> 0 | C22: {=+MAX(IF('ID1&5'!A:A='1. Status'!A22&'1. Status'!$C$10,'ID1&5'!K:K))} -> 0 | D22: {=+MAX(IF('ID1&5'!A:A='1. Status'!A22&'1. Status'!$D$10,'ID1&5'!K:K))} -> 0 | E22: {=+MAX(IF('ID1&5'!A:A='1. Status'!A22&'1. Status'!$E$10,'ID1&5'!K:K))} -> 0 | F22: {=+MAX(IF('ID1&5'!A:A='1. Status'!A22&'1. Status'!$F$10,'ID1&5'!K:K))} -> 0 | H22: UNIV_OPER | I22: instrumento_financeiro | J22: =+COUNTIF('ID1&5'!G:G,'1. Status'!I22) -> 0 | K22: =+IFERROR(VLOOKUP(CONCATENATE(A22,$B$10,B22),'ID1&5'!B:J,8,FALSE),"-") -> - | L22: =+IFERROR(VLOOKUP(B22,'ID1&5'!K:L,2,FALSE),"-") -> - | M22: =+IFERROR(VLOOKUP(CONCATENATE(A22,$B$10,B22),'ID1&5'!B:J,9,FALSE),"-") -> - | N22: =+IFERROR(VLOOKUP(CONCATENATE(A22,$C$10,C22),'ID1&5'!B:J,8,FALSE),"-") -> - | O22: =+IFERROR(VLOOKUP(C22,'ID1&5'!K:L,2,FALSE),"-") -> - | P22: =+IFERROR(VLOOKUP(CONCATENATE(A22,$C$10,C22),'ID1&5'!B:J,9,FALSE),"-") -> - | Q22: =+IFERROR(VLOOKUP(D22,'ID1&5'!K:L,2,FALSE),"-") -> - | R22: =+IFERROR(VLOOKUP(CONCATENATE(A22,$D$10,D22),'ID1&5'!B:J,9,FALSE),"-") -> - | S22: =+IFERROR(VLOOKUP(E22,'ID1&5'!K:L,2,FALSE),"-") -> - | T22: =+IFERROR(VLOOKUP(CONCATENATE(A22,$E$10,E22),'ID1&5'!B:J,9,FALSE),"-") -> - | U22: =+IFERROR(VLOOKUP(F22,'ID1&5'!K:L,2,FALSE),"-") -> - | V22: =+IFERROR(VLOOKUP(CONCATENATE(A22,$F$10,F22),'ID1&5'!B:J,9,FALSE),"-") -> - | W22: =+IFERROR(VLOOKUP(A22,'ID6&7'!A:I,9,FALSE),"-") -> - | X22: =+IFERROR(VLOOKUP(A22,'ID6&7'!A:J,10,FALSE),"-") -> - | Z22: =+IF(J22=0,"Por iniciar",IF(OR(K22="-",M22="-",P22="-",R22="-",T22="-",V22="-"),"Em testes",IF(AND(M22=0,P22=0,R22=0,T22<>K22,V22<>K22),"OK","NOK"))) -> Por iniciar
... A63: =+H63&I63&$I$8 -> UNIV_OPERidcomb_lt_final45991 | B63: {=+MAX(IF('ID1&5'!A:A='1. Status'!A63&'1. Status'!$B$10,'ID1&5'!K:K))} -> 0 | C63: {=+MAX(IF('ID1&5'!A:A='1. Status'!A63&'1. Status'!$C$10,'ID1&5'!K:K))} -> 0 | D63: {=+MAX(IF('ID1&5'!A:A='1. Status'!A63&'1. Status'!$D$10,'ID1&5'!K:K))} -> 0 | E63: {=+MAX(IF('ID1&5'!A:A='1. Status'!A63&'1. Status'!$E$10,'ID1&5'!K:K))} -> 0 | F63: {=+MAX(IF('ID1&5'!A:A='1. Status'!A63&'1. Status'!$F$10,'ID1&5'!K:K))} -> 0 | H63: UNIV_OPER | I63: idcomb_lt_final | J63: =+COUNTIF('ID1&5'!G:G,'1. Status'!I63) -> 0 | K63: =+IFERROR(VLOOKUP(CONCATENATE(A63,$B$10,B63),'ID1&5'!B:J,8,FALSE),"-") -> - | L63: =+IFERROR(VLOOKUP(B63,'ID1&5'!K:L,2,FALSE),"-") -> - | M63: =+IFERROR(VLOOKUP(CONCATENATE(A63,$B$10,B63),'ID1&5'!B:J,9,FALSE),"-") -> - | N63: =+IFERROR(VLOOKUP(CONCATENATE(A63,$C$10,C63),'ID1&5'!B:J,8,FALSE),"-") -> - | O63: =+IFERROR(VLOOKUP(C63,'ID1&5'!K:L,2,FALSE),"-") -> - | P63: =+IFERROR(VLOOKUP(CONCATENATE(A63,$C$10,C63),'ID1&5'!B:J,9,FALSE),"-") -> - | Q63: =+IFERROR(VLOOKUP(D63,'ID1&5'!K:L,2,FALSE),"-") -> - | R63: =+IFERROR(VLOOKUP(CONCATENATE(A63,$D$10,D63),'ID1&5'!B:J,9,FALSE),"-") -> - | S63: =+IFERROR(VLOOKUP(E63,'ID1&5'!K:L,2,FALSE),"-") -> - | T63: =+IFERROR(VLOOKUP(CONCATENATE(A63,$E$10,E63),'ID1&5'!B:J,9,FALSE),"-") -> - | U63: =+IFERROR(VLOOKUP(F63,'ID1&5'!K:L,2,FALSE),"-") -> - | V63: =+IFERROR(VLOOKUP(CONCATENATE(A63,$F$10,F63),'ID1&5'!B:J,9,FALSE),"-") -> - | W63: =+IFERROR(VLOOKUP(A63,'ID6&7'!A:I,9,FALSE),"-") -> - | X63: =+IFERROR(VLOOKUP(A63,'ID6&7'!A:J,10,FALSE),"-") -> - | Z63: =+IF(J63=0,"Por iniciar",IF(OR(K63="-",M63="-",P63="-",R63="-",T63="-",V63="-"),"Em testes",IF(AND(M63=0,P63=0,R63=0,T63<>K63,V63<>K63),"OK","NOK"))) -> Por iniciar
H64: UNIV_OPER | I64: rank_insolv | J64: =+COUNTIF('ID1&5'!G:G,'1. Status'!I64) -> 0 | K64: =+IFERROR(VLOOKUP(CONCATENATE(A64,$B$10,B64),'ID1&5'!B:J,8,FALSE),"-") -> - | L64: =+IFERROR(VLOOKUP(B64,'ID1&5'!K:L,2,FALSE),"-") -> - | M64: =+IFERROR(VLOOKUP(CONCATENATE(A64,$B$10,B64),'ID1&5'!B:J,9,FALSE),"-") -> - | N64: =+IFERROR(VLOOKUP(CONCATENATE(A64,$C$10,C64),'ID1&5'!B:J,8,FALSE),"-") -> - | O64: =+IFERROR(VLOOKUP(C64,'ID1&5'!K:L,2,FALSE),"-") -> - | P64: =+IFERROR(VLOOKUP(CONCATENATE(A64,$C$10,C64),'ID1&5'!B:J,9,FALSE),"-") -> - | Q64: =+IFERROR(VLOOKUP(D64,'ID1&5'!K:L,2,FALSE),"-") -> - | R64: =+IFERROR(VLOOKUP(CONCATENATE(A64,$D$10,D64),'ID1&5'!B:J,9,FALSE),"-") -> - | S64: =+IFERROR(VLOOKUP(E64,'ID1&5'!K:L,2,FALSE),"-") -> - | T64: =+IFERROR(VLOOKUP(CONCATENATE(A64,$E$10,E64),'ID1&5'!B:J,9,FALSE),"-") -> - | U64: =+IFERROR(VLOOKUP(F64,'ID1&5'!K:L,2,FALSE),"-") -> - | V64: =+IFERROR(VLOOKUP(CONCATENATE(A64,$F$10,F64),'ID1&5'!B:J,9,FALSE),"-") -> - | W64: =+IFERROR(VLOOKUP(A64,'ID6&7'!A:I,9,FALSE),"-") -> - | X64: =+IFERROR(VLOOKUP(A64,'ID6&7'!A:J,10,FALSE),"-") -> - | Z64: =+IF(J64=0,"Por iniciar",IF(OR(K64="-",M64="-",P64="-",R64="-",T64="-",V64="-"),"Em testes",IF(AND(M64=0,P64=0,R64=0,T64<>K64,V64<>K64),"OK","NOK"))) -> Por iniciar
H65: INSTRUMENT | I65: cntrct_id | J65: =+COUNTIF('ID1&5'!G:G,'1. Status'!I65) -> 0 | K65: =+IFERROR(VLOOKUP(CONCATENATE(A65,$B$10,B65),'ID1&5'!B:J,8,FALSE),"-") -> - | L65: =+IFERROR(VLOOKUP(B65,'ID1&5'!K:L,2,FALSE),"-") -> - | M65: =+IFERROR(VLOOKUP(CONCATENATE(A65,$B$10,B65),'ID1&5'!B:J,9,FALSE),"-") -> - | N65: =+IFERROR(VLOOKUP(CONCATENATE(A65,$C$10,C65),'ID1&5'!B:J,8,FALSE),"-") -> - | O65: =+IFERROR(VLOOKUP(C65,'ID1&5'!K:L,2,FALSE),"-") -> - | P65: =+IFERROR(VLOOKUP(CONCATENATE(A65,$C$10,C65),'ID1&5'!B:J,9,FALSE),"-") -> - | Q65: =+IFERROR(VLOOKUP(D65,'ID1&5'!K:L,2,FALSE),"-") -> - | R65: =+IFERROR(VLOOKUP(CONCATENATE(A65,$D$10,D65),'ID1&5'!B:J,9,FALSE),"-") -> - | S65: =+IFERROR(VLOOKUP(E65,'ID1&5'!K:L,2,FALSE),"-") -> - | T65: =+IFERROR(VLOOKUP(CONCATENATE(A65,$E$10,E65),'ID1&5'!B:J,9,FALSE),"-") -> - | U65: =+IFERROR(VLOOKUP(F65,'ID1&5'!K:L,2,FALSE),"-") -> - | V65: =+IFERROR(VLOOKUP(CONCATENATE(A65,$F$10,F65),'ID1&5'!B:J,9,FALSE),"-") -> - | W65: =+IFERROR(VLOOKUP(A65,'ID6&7'!A:I,9,FALSE),"-") -> - | X65: =+IFERROR(VLOOKUP(A65,'ID6&7'!A:J,10,FALSE),"-") -> - | Z65: =+IF(J65=0,"Por iniciar",IF(OR(K65="-",M65="-",P65="-",R65="-",T65="-",V65="-"),"Em testes",IF(AND(M65=0,P65=0,R65=0,T65<>K65,V65<>K65),"OK","NOK"))) -> Por iniciar
H66: INSTRUMENT | I66: crrncy_dnmntn | J66: =+COUNTIF('ID1&5'!G:G,'1. Status'!I66) -> 1 | K66: =+IFERROR(VLOOKUP(CONCATENATE(A66,$B$10,B66),'ID1&5'!B:J,8,FALSE),"-") -> - | L66: =+IFERROR(VLOOKUP(B66,'ID1&5'!K:L,2,FALSE),"-") -> - | M66: =+IFERROR(VLOOKUP(CONCATENATE(A66,$B$10,B66),'ID1&5'!B:J,9,FALSE),"-") -> - | N66: =+IFERROR(VLOOKUP(CONCATENATE(A66,$C$10,C66),'ID1&5'!B:J,8,FALSE),"-") -> - | O66: =+IFERROR(VLOOKUP(C66,'ID1&5'!K:L,2,FALSE),"-") -> - | P66: =+IFERROR(VLOOKUP(CONCATENATE(A66,$C$10,C66),'ID1&5'!B:J,9,FALSE),"-") -> - | Q66: =+IFERROR(VLOOKUP(D66,'ID1&5'!K:L,2,FALSE),"-") -> - | R66: =+IFERROR(VLOOKUP(CONCATENATE(A66,$D$10,D66),'ID1&5'!B:J,9,FALSE),"-") -> - | S66: =+IFERROR(VLOOKUP(E66,'ID1&5'!K:L,2,FALSE),"-") -> - | T66: =+IFERROR(VLOOKUP(CONCATENATE(A66,$E$10,E66),'ID1&5'!B:J,9,FALSE),"-") -> - | U66: =+IFERROR(VLOOKUP(F66,'ID1&5'!K:L,2,FALSE),"-") -> - | V66: =+IFERROR(VLOOKUP(CONCATENATE(A66,$F$10,F66),'ID1&5'!B:J,9,FALSE),"-") -> - | W66: =+IFERROR(VLOOKUP(A66,'ID6&7'!A:I,9,FALSE),"-") -> - | X66: =+IFERROR(VLOOKUP(A66,'ID6&7'!A:J,10,FALSE),"-") -> - | Z66: =+IF(J66=0,"Por iniciar",IF(OR(K66="-",M66="-",P66="-",R66="-",T66="-",V66="-"),"Em testes",IF(AND(M66=0,P66=0,R66=0,T66<>K66,V66<>K66),"OK","NOK"))) -> Em testes
H67: INSTRUMENT | I67: dt_incptn | J67: =+COUNTIF('ID1&5'!G:G,'1. Status'!I67) -> 1 | K67: =+IFERROR(VLOOKUP(CONCATENATE(A67,$B$10,B67),'ID1&5'!B:J,8,FALSE),"-") -> - | L67: =+IFERROR(VLOOKUP(B67,'ID1&5'!K:L,2,FALSE),"-") -> - | M67: =+IFERROR(VLOOKUP(CONCATENATE(A67,$B$10,B67),'ID1&5'!B:J,9,FALSE),"-") -> - | N67: =+IFERROR(VLOOKUP(CONCATENATE(A67,$C$10,C67),'ID1&5'!B:J,8,FALSE),"-") -> - | O67: =+IFERROR(VLOOKUP(C67,'ID1&5'!K:L,2,FALSE),"-") -> - | P67: =+IFERROR(VLOOKUP(CONCATENATE(A67,$C$10,C67),'ID1&5'!B:J,9,FALSE),"-") -> - | Q67: =+IFERROR(VLOOKUP(D67,'ID1&5'!K:L,2,FALSE),"-") -> - | R67: =+IFERROR(VLOOKUP(CONCATENATE(A67,$D$10,D67),'ID1&5'!B:J,9,FALSE),"-") -> - | S67: =+IFERROR(VLOOKUP(E67,'ID1&5'!K:L,2,FALSE),"-") -> - | T67: =+IFERROR(VLOOKUP(CONCATENATE(A67,$E$10,E67),'ID1&5'!B:J,9,FALSE),"-") -> - | U67: =+IFERROR(VLOOKUP(F67,'ID1&5'!K:L,2,FALSE),"-") -> - | V67: =+IFERROR(VLOOKUP(CONCATENATE(A67,$F$10,F67),'ID1&5'!B:J,9,FALSE),"-") -> - | W67: =+IFERROR(VLOOKUP(A67,'ID6&7'!A:I,9,FALSE),"-") -> - | X67: =+IFERROR(VLOOKUP(A67,'ID6&7'!A:J,10,FALSE),"-") -> - | Z67: =+IF(J67=0,"Por iniciar",IF(OR(K67="-",M67="-",P67="-",R67="-",T67="-",V67="-"),"Em testes",IF(AND(M67=0,P67=0,R67=0,T67<>K67,V67<>K67),"OK","NOK"))) -> Em testes
H68: INSTRUMENT | I68: obsrvd_agnt_id | J68: =+COUNTIF('ID1&5'!G:G,'1. Status'!I68) -> 0 | K68: =+IFERROR(VLOOKUP(CONCATENATE(A68,$B$10,B68),'ID1&5'!B:J,8,FALSE),"-") -> - | L68: =+IFERROR(VLOOKUP(B68,'ID1&5'!K:L,2,FALSE),"-") -> - | M68: =+IFERROR(VLOOKUP(CONCATENATE(A68,$B$10,B68),'ID1&5'!B:J,9,FALSE),"-") -> - | N68: =+IFERROR(VLOOKUP(CONCATENATE(A68,$C$10,C68),'ID1&5'!B:J,8,FALSE),"-") -> - | O68: =+IFERROR(VLOOKUP(C68,'ID1&5'!K:L,2,FALSE),"-") -> - | P68: =+IFERROR(VLOOKUP(CONCATENATE(A68,$C$10,C68),'ID1&5'!B:J,9,FALSE),"-") -> - | Q68: =+IFERROR(VLOOKUP(D68,'ID1&5'!K:L,2,FALSE),"-") -> - | R68: =+IFERROR(VLOOKUP(CONCATENATE(A68,$D$10,D68),'ID1&5'!B:J,9,FALSE),"-") -> - | S68: =+IFERROR(VLOOKUP(E68,'ID1&5'!K:L,2,FALSE),"-") -> - | T68: =+IFERROR(VLOOKUP(CONCATENATE(A68,$E$10,E68),'ID1&5'!B:J,9,FALSE),"-") -> - | U68: =+IFERROR(VLOOKUP(F68,'ID1&5'!K:L,2,FALSE),"-") -> - | V68: =+IFERROR(VLOOKUP(CONCATENATE(A68,$F$10,F68),'ID1&5'!B:J,9,FALSE),"-") -> - | W68: =+IFERROR(VLOOKUP(A68,'ID6&7'!A:I,9,FALSE),"-") -> - | X68: =+IFERROR(VLOOKUP(A68,'ID6&7'!A:J,10,FALSE),"-") -> - | Z68: =+IF(J68=0,"Por iniciar",IF(OR(K68="-",M68="-",P68="-",R68="-",T68="-",V68="-"),"Em testes",IF(AND(M68=0,P68=0,R68=0,T68<>K68,V68<>K68),"OK","NOK"))) -> Por iniciar
H69: INSTRUMENT | I69: obsrvd_agnt_nm | J69: =+COUNTIF('ID1&5'!G:G,'1. Status'!I69) -> 0 | K69: =+IFERROR(VLOOKUP(CONCATENATE(A69,$B$10,B69),'ID1&5'!B:J,8,FALSE),"-") -> - | L69: =+IFERROR(VLOOKUP(B69,'ID1&5'!K:L,2,FALSE),"-") -> - | M69: =+IFERROR(VLOOKUP(CONCATENATE(A69,$B$10,B69),'ID1&5'!B:J,9,FALSE),"-") -> - | N69: =+IFERROR(VLOOKUP(CONCATENATE(A69,$C$10,C69),'ID1&5'!B:J,8,FALSE),"-") -> - | O69: =+IFERROR(VLOOKUP(C69,'ID1&5'!K:L,2,FALSE),"-") -> - | P69: =+IFERROR(VLOOKUP(CONCATENATE(A69,$C$10,C69),'ID1&5'!B:J,9,FALSE),"-") -> - | Q69: =+IFERROR(VLOOKUP(D69,'ID1&5'!K:L,2,FALSE),"-") -> - | R69: =+IFERROR(VLOOKUP(CONCATENATE(A69,$D$10,D69),'ID1&5'!B:J,9,FALSE),"-") -> - | S69: =+IFERROR(VLOOKUP(E69,'ID1&5'!K:L,2,FALSE),"-") -> - | T69: =+IFERROR(VLOOKUP(CONCATENATE(A69,$E$10,E69),'ID1&5'!B:J,9,FALSE),"-") -> - | U69: =+IFERROR(VLOOKUP(F69,'ID1&5'!K:L,2,FALSE),"-") -> - | V69: =+IFERROR(VLOOKUP(CONCATENATE(A69,$F$10,F69),'ID1&5'!B:J,9,FALSE),"-") -> - | W69: =+IFERROR(VLOOKUP(A69,'ID6&7'!A:I,9,FALSE),"-") -> - | X69: =+IFERROR(VLOOKUP(A69,'ID6&7'!A:J,10,FALSE),"-") -> - | Z69: =+IF(J69=0,"Por iniciar",IF(OR(K69="-",M69="-",P69="-",R69="-",T69="-",V69="-"),"Em testes",IF(AND(M69=0,P69=0,R69=0,T69<>K69,V69<>K69),"OK","NOK"))) -> Por iniciar
H70: INSTRUMENT | I70: prdct | J70: =+COUNTIF('ID1&5'!G:G,'1. Status'!I70) -> 1 | K70: =+IFERROR(VLOOKUP(CONCATENATE(A70,$B$10,B70),'ID1&5'!B:J,8,FALSE),"-") -> - | L70: =+IFERROR(VLOOKUP(B70,'ID1&5'!K:L,2,FALSE),"-") -> - | M70: =+IFERROR(VLOOKUP(CONCATENATE(A70,$B$10,B70),'ID1&5'!B:J,9,FALSE),"-") -> - | N70: =+IFERROR(VLOOKUP(CONCATENATE(A70,$C$10,C70),'ID1&5'!B:J,8,FALSE),"-") -> - | O70: =+IFERROR(VLOOKUP(C70,'ID1&5'!K:L,2,FALSE),"-") -> - | P70: =+IFERROR(VLOOKUP(CONCATENATE(A70,$C$10,C70),'ID1&5'!B:J,9,FALSE),"-") -> - | Q70: =+IFERROR(VLOOKUP(D70,'ID1&5'!K:L,2,FALSE),"-") -> - | R70: =+IFERROR(VLOOKUP(CONCATENATE(A70,$D$10,D70),'ID1&5'!B:J,9,FALSE),"-") -> - | S70: =+IFERROR(VLOOKUP(E70,'ID1&5'!K:L,2,FALSE),"-") -> - | T70: =+IFERROR(VLOOKUP(CONCATENATE(A70,$E$10,E70),'ID1&5'!B:J,9,FALSE),"-") -> - | U70: =+IFERROR(VLOOKUP(F70,'ID1&5'!K:L,2,FALSE),"-") -> - | V70: =+IFERROR(VLOOKUP(CONCATENATE(A70,$F$10,F70),'ID1&5'!B:J,9,FALSE),"-") -> - | W70: =+IFERROR(VLOOKUP(A70,'ID6&7'!A:I,9,FALSE),"-") -> - | X70: =+IFERROR(VLOOKUP(A70,'ID6&7'!A:J,10,FALSE),"-") -> - | Z70: =+IF(J70=0,"Por iniciar",IF(OR(K70="-",M70="-",P70="-",R70="-",T70="-",V70="-"),"Em testes",IF(AND(M70=0,P70=0,R70=0,T70<>K70,V70<>K70),"OK","NOK"))) -> Em testes
H71: INSTRUMENT | I71: brchd_cvnnts | J71: =+COUNTIF('ID1&5'!G:G,'1. Status'!I71) -> 0 | K71: =+IFERROR(VLOOKUP(CONCATENATE(A71,$B$10,B71),'ID1&5'!B:J,8,FALSE),"-") -> - | L71: =+IFERROR(VLOOKUP(B71,'ID1&5'!K:L,2,FALSE),"-") -> - | M71: =+IFERROR(VLOOKUP(CONCATENATE(A71,$B$10,B71),'ID1&5'!B:J,9,FALSE),"-") -> - | N71: =+IFERROR(VLOOKUP(CONCATENATE(A71,$C$10,C71),'ID1&5'!B:J,8,FALSE),"-") -> - | O71: =+IFERROR(VLOOKUP(C71,'ID1&5'!K:L,2,FALSE),"-") -> - | P71: =+IFERROR(VLOOKUP(CONCATENATE(A71,$C$10,C71),'ID1&5'!B:J,9,FALSE),"-") -> - | Q71: =+IFERROR(VLOOKUP(D71,'ID1&5'!K:L,2,FALSE),"-") -> - | R71: =+IFERROR(VLOOKUP(CONCATENATE(A71,$D$10,D71),'ID1&5'!B:J,9,FALSE),"-") -> - | S71: =+IFERROR(VLOOKUP(E71,'ID1&5'!K:L,2,FALSE),"-") -> - | T71: =+IFERROR(VLOOKUP(CONCATENATE(A71,$E$10,E71),'ID1&5'!B:J,9,FALSE),"-") -> - | U71: =+IFERROR(VLOOKUP(F71,'ID1&5'!K:L,2,FALSE),"-") -> - | V71: =+IFERROR(VLOOKUP(CONCATENATE(A71,$F$10,F71),'ID1&5'!B:J,9,FALSE),"-") -> - | W71: =+IFERROR(VLOOKUP(A71,'ID6&7'!A:I,9,FALSE),"-") -> - | X71: =+IFERROR(VLOOKUP(A71,'ID6&7'!A:J,10,FALSE),"-") -> - | Z71: =+IF(J71=0,"Por iniciar",IF(OR(K71="-",M71="-",P71="-",R71="-",T71="-",V71="-"),"Em testes",IF(AND(M71=0,P71=0,R71=0,T71<>K71,V71<>K71),"OK","NOK"))) -> Por iniciar
H72: INSTRUMENT | I72: chnnl_orgntn | J72: =+COUNTIF('ID1&5'!G:G,'1. Status'!I72) -> 0 | K72: =+IFERROR(VLOOKUP(CONCATENATE(A72,$B$10,B72),'ID1&5'!B:J,8,FALSE),"-") -> - | L72: =+IFERROR(VLOOKUP(B72,'ID1&5'!K:L,2,FALSE),"-") -> - | M72: =+IFERROR(VLOOKUP(CONCATENATE(A72,$B$10,B72),'ID1&5'!B:J,9,FALSE),"-") -> - | N72: =+IFERROR(VLOOKUP(CONCATENATE(A72,$C$10,C72),'ID1&5'!B:J,8,FALSE),"-") -> - | O72: =+IFERROR(VLOOKUP(C72,'ID1&5'!K:L,2,FALSE),"-") -> - | P72: =+IFERROR(VLOOKUP(CONCATENATE(A72,$C$10,C72),'ID1&5'!B:J,9,FALSE),"-") -> - | Q72: =+IFERROR(VLOOKUP(D72,'ID1&5'!K:L,2,FALSE),"-") -> - | R72: =+IFERROR(VLOOKUP(CONCATENATE(A72,$D$10,D72),'ID1&5'!B:J,9,FALSE),"-") -> - | S72: =+IFERROR(VLOOKUP(E72,'ID1&5'!K:L,2,FALSE),"-") -> - | T72: =+IFERROR(VLOOKUP(CONCATENATE(A72,$E$10,E72),'ID1&5'!B:J,9,FALSE),"-") -> - | U72: =+IFERROR(VLOOKUP(F72,'ID1&5'!K:L,2,FALSE),"-") -> - | V72: =+IFERROR(VLOOKUP(CONCATENATE(A72,$F$10,F72),'ID1&5'!B:J,9,FALSE),"-") -> - | W72: =+IFERROR(VLOOKUP(A72,'ID6&7'!A:I,9,FALSE),"-") -> - | X72: =+IFERROR(VLOOKUP(A72,'ID6&7'!A:J,10,FALSE),"-") -> - | Z72: =+IF(J72=0,"Por iniciar",IF(OR(K72="-",M72="-",P72="-",R72="-",T72="-",V72="-"),"Em testes",IF(AND(M72=0,P72=0,R72=0,T72<>K72,V72<>K72),"OK","NOK"))) -> Por iniciar
H73: INSTRUMENT | I73: csh_swp_trp | J73: =+COUNTIF('ID1&5'!G:G,'1. Status'!I73) -> 0 | K73: =+IFERROR(VLOOKUP(CONCATENATE(A73,$B$10,B73),'ID1&5'!B:J,8,FALSE),"-") -> - | L73: =+IFERROR(VLOOKUP(B73,'ID1&5'!K:L,2,FALSE),"-") -> - | M73: =+IFERROR(VLOOKUP(CONCATENATE(A73,$B$10,B73),'ID1&5'!B:J,9,FALSE),"-") -> - | N73: =+IFERROR(VLOOKUP(CONCATENATE(A73,$C$10,C73),'ID1&5'!B:J,8,FALSE),"-") -> - | O73: =+IFERROR(VLOOKUP(C73,'ID1&5'!K:L,2,FALSE),"-") -> - | P73: =+IFERROR(VLOOKUP(CONCATENATE(A73,$C$10,C73),'ID1&5'!B:J,9,FALSE),"-") -> - | Q73: =+IFERROR(VLOOKUP(D73,'ID1&5'!K:L,2,FALSE),"-") -> - | R73: =+IFERROR(VLOOKUP(CONCATENATE(A73,$D$10,D73),'ID1&5'!B:J,9,FALSE),"-") -> - | S73: =+IFERROR(VLOOKUP(E73,'ID1&5'!K:L,2,FALSE),"-") -> - | T73: =+IFERROR(VLOOKUP(CONCATENATE(A73,$E$10,E73),'ID1&5'!B:J,9,FALSE),"-") -> - | U73: =+IFERROR(VLOOKUP(F73,'ID1&5'!K:L,2,FALSE),"-") -> - | V73: =+IFERROR(VLOOKUP(CONCATENATE(A73,$F$10,F73),'ID1&5'!B:J,9,FALSE),"-") -> - | W73: =+IFERROR(VLOOKUP(A73,'ID6&7'!A:I,9,FALSE),"-") -> - | X73: =+IFERROR(VLOOKUP(A73,'ID6&7'!A:J,10,FALSE),"-") -> - | Z73: =+IF(J73=0,"Por iniciar",IF(OR(K73="-",M73="-",P73="-",R73="-",T73="-",V73="-"),"Em testes",IF(AND(M73=0,P73=0,R73=0,T73<>K73,V73<>K73),"OK","NOK"))) -> Por iniciar
H74: INSTRUMENT | I74: cvnnt_stts | J74: =+COUNTIF('ID1&5'!G:G,'1. Status'!I74) -> 0 | K74: =+IFERROR(VLOOKUP(CONCATENATE(A74,$B$10,B74),'ID1&5'!B:J,8,FALSE),"-") -> - | L74: =+IFERROR(VLOOKUP(B74,'ID1&5'!K:L,2,FALSE),"-") -> - | M74: =+IFERROR(VLOOKUP(CONCATENATE(A74,$B$10,B74),'ID1&5'!B:J,9,FALSE),"-") -> - | N74: =+IFERROR(VLOOKUP(CONCATENATE(A74,$C$10,C74),'ID1&5'!B:J,8,FALSE),"-") -> - | O74: =+IFERROR(VLOOKUP(C74,'ID1&5'!K:L,2,FALSE),"-") -> - | P74: =+IFERROR(VLOOKUP(CONCATENATE(A74,$C$10,C74),'ID1&5'!B:J,9,FALSE),"-") -> - | Q74: =+IFERROR(VLOOKUP(D74,'ID1&5'!K:L,2,FALSE),"-") -> - | R74: =+IFERROR(VLOOKUP(CONCATENATE(A74,$D$10,D74),'ID1&5'!B:J,9,FALSE),"-") -> - | S74: =+IFERROR(VLOOKUP(E74,'ID1&5'!K:L,2,FALSE),"-") -> - | T74: =+IFERROR(VLOOKUP(CONCATENATE(A74,$E$10,E74),'ID1&5'!B:J,9,FALSE),"-") -> - | U74: =+IFERROR(VLOOKUP(F74,'ID1&5'!K:L,2,FALSE),"-") -> - | V74: =+IFERROR(VLOOKUP(CONCATENATE(A74,$F$10,F74),'ID1&5'!B:J,9,FALSE),"-") -> - | W74: =+IFERROR(VLOOKUP(A74,'ID6&7'!A:I,9,FALSE),"-") -> - | X74: =+IFERROR(VLOOKUP(A74,'ID6&7'!A:J,10,FALSE),"-") -> - | Z74: =+IF(J74=0,"Por iniciar",IF(OR(K74="-",M74="-",P74="-",R74="-",T74="-",V74="-"),"Em testes",IF(AND(M74=0,P74=0,R74=0,T74<>K74,V74<>K74),"OK","NOK"))) -> Por iniciar
H75: INSTRUMENT | I75: cvnnt_typ | J75: =+COUNTIF('ID1&5'!G:G,'1. Status'!I75) -> 0 | K75: =+IFERROR(VLOOKUP(CONCATENATE(A75,$B$10,B75),'ID1&5'!B:J,8,FALSE),"-") -> - | L75: =+IFERROR(VLOOKUP(B75,'ID1&5'!K:L,2,FALSE),"-") -> - | M75: =+IFERROR(VLOOKUP(CONCATENATE(A75,$B$10,B75),'ID1&5'!B:J,9,FALSE),"-") -> - | N75: =+IFERROR(VLOOKUP(CONCATENATE(A75,$C$10,C75),'ID1&5'!B:J,8,FALSE),"-") -> - | O75: =+IFERROR(VLOOKUP(C75,'ID1&5'!K:L,2,FALSE),"-") -> - | P75: =+IFERROR(VLOOKUP(CONCATENATE(A75,$C$10,C75),'ID1&5'!B:J,9,FALSE),"-") -> - | Q75: =+IFERROR(VLOOKUP(D75,'ID1&5'!K:L,2,FALSE),"-") -> - | R75: =+IFERROR(VLOOKUP(CONCATENATE(A75,$D$10,D75),'ID1&5'!B:J,9,FALSE),"-") -> - | S75: =+IFERROR(VLOOKUP(E75,'ID1&5'!K:L,2,FALSE),"-") -> - | T75: =+IFERROR(VLOOKUP(CONCATENATE(A75,$E$10,E75),'ID1&5'!B:J,9,FALSE),"-") -> - | U75: =+IFERROR(VLOOKUP(F75,'ID1&5'!K:L,2,FALSE),"-") -> - | V75: =+IFERROR(VLOOKUP(CONCATENATE(A75,$F$10,F75),'ID1&5'!B:J,9,FALSE),"-") -> - | W75: =+IFERROR(VLOOKUP(A75,'ID6&7'!A:I,9,FALSE),"-") -> - | X75: =+IFERROR(VLOOKUP(A75,'ID6&7'!A:J,10,FALSE),"-") -> - | Z75: =+IF(J75=0,"Por iniciar",IF(OR(K75="-",M75="-",P75="-",R75="-",T75="-",V75="-"),"Em testes",IF(AND(M75=0,P75=0,R75=0,T75<>K75,V75<>K75),"OK","NOK"))) -> Por iniciar
... H682: INSTR_PROTECTION | I682: cod_soc | J682: =+COUNTIF('ID1&5'!G:G,'1. Status'!I682) -> 4 | K682: =+IFERROR(VLOOKUP(CONCATENATE(A682,$B$10,B682),'ID1&5'!B:J,8,FALSE),"-") -> - | L682: =+IFERROR(VLOOKUP(B682,'ID1&5'!K:L,2,FALSE),"-") -> - | M682: =+IFERROR(VLOOKUP(CONCATENATE(A682,$B$10,B682),'ID1&5'!B:J,9,FALSE),"-") -> - | N682: =+IFERROR(VLOOKUP(CONCATENATE(A682,$C$10,C682),'ID1&5'!B:J,8,FALSE),"-") -> - | O682: =+IFERROR(VLOOKUP(C682,'ID1&5'!K:L,2,FALSE),"-") -> - | P682: =+IFERROR(VLOOKUP(CONCATENATE(A682,$C$10,C682),'ID1&5'!B:J,9,FALSE),"-") -> - | Q682: =+IFERROR(VLOOKUP(D682,'ID1&5'!K:L,2,FALSE),"-") -> - | R682: =+IFERROR(VLOOKUP(CONCATENATE(A682,$D$10,D682),'ID1&5'!B:J,9,FALSE),"-") -> - | S682: =+IFERROR(VLOOKUP(E682,'ID1&5'!K:L,2,FALSE),"-") -> - | T682: =+IFERROR(VLOOKUP(CONCATENATE(A682,$E$10,E682),'ID1&5'!B:J,9,FALSE),"-") -> - | U682: =+IFERROR(VLOOKUP(F682,'ID1&5'!K:L,2,FALSE),"-") -> - | V682: =+IFERROR(VLOOKUP(CONCATENATE(A682,$F$10,F682),'ID1&5'!B:J,9,FALSE),"-") -> - | W682: =+IFERROR(VLOOKUP(A682,'ID6&7'!A:I,9,FALSE),"-") -> - | X682: =+IFERROR(VLOOKUP(A682,'ID6&7'!A:J,10,FALSE),"-") -> - | Z682: =+IF(J682=0,"Por iniciar",IF(OR(K682="-",M682="-",P682="-",R682="-",T682="-",V682="-"),"Em testes",IF(AND(M682=0,P682=0,R682=0,T682<>K682,V682<>K682),"OK","NOK"))) -> Em testes
J683: =+COUNTIF('ID1&5'!G:G,'1. Status'!I683) -> 0 | K683: =+IFERROR(VLOOKUP(CONCATENATE(A683,$B$10,B683),'ID1&5'!B:J,8,FALSE),"-") -> - | L683: =+IFERROR(VLOOKUP(B683,'ID1&5'!K:L,2,FALSE),"-") -> - | M683: =+IFERROR(VLOOKUP(CONCATENATE(A683,$B$10,B683),'ID1&5'!B:J,9,FALSE),"-") -> - | N683: =+IFERROR(VLOOKUP(CONCATENATE(A683,$C$10,C683),'ID1&5'!B:J,8,FALSE),"-") -> - | O683: =+IFERROR(VLOOKUP(C683,'ID1&5'!K:L,2,FALSE),"-") -> - | P683: =+IFERROR(VLOOKUP(CONCATENATE(A683,$C$10,C683),'ID1&5'!B:J,9,FALSE),"-") -> - | Q683: =+IFERROR(VLOOKUP(D683,'ID1&5'!K:L,2,FALSE),"-") -> - | R683: =+IFERROR(VLOOKUP(CONCATENATE(A683,$D$10,D683),'ID1&5'!B:J,9,FALSE),"-") -> - | S683: =+IFERROR(VLOOKUP(E683,'ID1&5'!K:L,2,FALSE),"-") -> - | T683: =+IFERROR(VLOOKUP(CONCATENATE(A683,$E$10,E683),'ID1&5'!B:J,9,FALSE),"-") -> - | U683: =+IFERROR(VLOOKUP(F683,'ID1&5'!K:L,2,FALSE),"-") -> - | V683: =+IFERROR(VLOOKUP(CONCATENATE(A683,$F$10,F683),'ID1&5'!B:J,9,FALSE),"-") -> - | W683: =+IFERROR(VLOOKUP(A683,'ID6&7'!A:I,9,FALSE),"-") -> - | X683: =+IFERROR(VLOOKUP(A683,'ID6&7'!A:J,10,FALSE),"-") -> - | Z683: =+IF(J683=0,"Por iniciar",IF(OR(K683="-",M683="-",P683="-",R683="-",T683="-",V683="-"),"Em testes",IF(AND(M683=0,P683=0,R683=0,T683<>K683,V683<>K683),"OK","NOK"))) -> Por iniciar
J684: =+COUNTIF('ID1&5'!G:G,'1. Status'!I684) -> 0 | K684: =+IFERROR(VLOOKUP(CONCATENATE(A684,$B$10,B684),'ID1&5'!B:J,8,FALSE),"-") -> - | L684: =+IFERROR(VLOOKUP(B684,'ID1&5'!K:L,2,FALSE),"-") -> - | M684: =+IFERROR(VLOOKUP(CONCATENATE(A684,$B$10,B684),'ID1&5'!B:J,9,FALSE),"-") -> - | N684: =+IFERROR(VLOOKUP(CONCATENATE(A684,$C$10,C684),'ID1&5'!B:J,8,FALSE),"-") -> - | O684: =+IFERROR(VLOOKUP(C684,'ID1&5'!K:L,2,FALSE),"-") -> - | P684: =+IFERROR(VLOOKUP(CONCATENATE(A684,$C$10,C684),'ID1&5'!B:J,9,FALSE),"-") -> - | Q684: =+IFERROR(VLOOKUP(D684,'ID1&5'!K:L,2,FALSE),"-") -> - | R684: =+IFERROR(VLOOKUP(CONCATENATE(A684,$D$10,D684),'ID1&5'!B:J,9,FALSE),"-") -> - | S684: =+IFERROR(VLOOKUP(E684,'ID1&5'!K:L,2,FALSE),"-") -> - | T684: =+IFERROR(VLOOKUP(CONCATENATE(A684,$E$10,E684),'ID1&5'!B:J,9,FALSE),"-") -> - | U684: =+IFERROR(VLOOKUP(F684,'ID1&5'!K:L,2,FALSE),"-") -> - | V684: =+IFERROR(VLOOKUP(CONCATENATE(A684,$F$10,F684),'ID1&5'!B:J,9,FALSE),"-") -> - | W684: =+IFERROR(VLOOKUP(A684,'ID6&7'!A:I,9,FALSE),"-") -> - | X684: =+IFERROR(VLOOKUP(A684,'ID6&7'!A:J,10,FALSE),"-") -> - | Z684: =+IF(J684=0,"Por iniciar",IF(OR(K684="-",M684="-",P684="-",R684="-",T684="-",V684="-"),"Em testes",IF(AND(M684=0,P684=0,R684=0,T684<>K684,V684<>K684),"OK","NOK"))) -> Por iniciar
J685: =+COUNTIF('ID1&5'!G:G,'1. Status'!I685) -> 0 | K685: =+IFERROR(VLOOKUP(CONCATENATE(A685,$B$10,B685),'ID1&5'!B:J,8,FALSE),"-") -> - | L685: =+IFERROR(VLOOKUP(B685,'ID1&5'!K:L,2,FALSE),"-") -> - | M685: =+IFERROR(VLOOKUP(CONCATENATE(A685,$B$10,B685),'ID1&5'!B:J,9,FALSE),"-") -> - | N685: =+IFERROR(VLOOKUP(CONCATENATE(A685,$C$10,C685),'ID1&5'!B:J,8,FALSE),"-") -> - | O685: =+IFERROR(VLOOKUP(C685,'ID1&5'!K:L,2,FALSE),"-") -> - | P685: =+IFERROR(VLOOKUP(CONCATENATE(A685,$C$10,C685),'ID1&5'!B:J,9,FALSE),"-") -> - | Q685: =+IFERROR(VLOOKUP(D685,'ID1&5'!K:L,2,FALSE),"-") -> - | R685: =+IFERROR(VLOOKUP(CONCATENATE(A685,$D$10,D685),'ID1&5'!B:J,9,FALSE),"-") -> - | S685: =+IFERROR(VLOOKUP(E685,'ID1&5'!K:L,2,FALSE),"-") -> - | T685: =+IFERROR(VLOOKUP(CONCATENATE(A685,$E$10,E685),'ID1&5'!B:J,9,FALSE),"-") -> - | U685: =+IFERROR(VLOOKUP(F685,'ID1&5'!K:L,2,FALSE),"-") -> - | V685: =+IFERROR(VLOOKUP(CONCATENATE(A685,$F$10,F685),'ID1&5'!B:J,9,FALSE),"-") -> - | W685: =+IFERROR(VLOOKUP(A685,'ID6&7'!A:I,9,FALSE),"-") -> - | X685: =+IFERROR(VLOOKUP(A685,'ID6&7'!A:J,10,FALSE),"-") -> - | Z685: =+IF(J685=0,"Por iniciar",IF(OR(K685="-",M685="-",P685="-",R685="-",T685="-",V685="-"),"Em testes",IF(AND(M685=0,P685=0,R685=0,T685<>K685,V685<>K685),"OK","NOK"))) -> Por iniciar
J686: =+COUNTIF('ID1&5'!G:G,'1. Status'!I686) -> 0 | K686: =+IFERROR(VLOOKUP(CONCATENATE(A686,$B$10,B686),'ID1&5'!B:J,8,FALSE),"-") -> - | L686: =+IFERROR(VLOOKUP(B686,'ID1&5'!K:L,2,FALSE),"-") -> - | M686: =+IFERROR(VLOOKUP(CONCATENATE(A686,$B$10,B686),'ID1&5'!B:J,9,FALSE),"-") -> - | N686: =+IFERROR(VLOOKUP(CONCATENATE(A686,$C$10,C686),'ID1&5'!B:J,8,FALSE),"-") -> - | O686: =+IFERROR(VLOOKUP(C686,'ID1&5'!K:L,2,FALSE),"-") -> - | P686: =+IFERROR(VLOOKUP(CONCATENATE(A686,$C$10,C686),'ID1&5'!B:J,9,FALSE),"-") -> - | Q686: =+IFERROR(VLOOKUP(D686,'ID1&5'!K:L,2,FALSE),"-") -> - | R686: =+IFERROR(VLOOKUP(CONCATENATE(A686,$D$10,D686),'ID1&5'!B:J,9,FALSE),"-") -> - | S686: =+IFERROR(VLOOKUP(E686,'ID1&5'!K:L,2,FALSE),"-") -> - | T686: =+IFERROR(VLOOKUP(CONCATENATE(A686,$E$10,E686),'ID1&5'!B:J,9,FALSE),"-") -> - | U686: =+IFERROR(VLOOKUP(F686,'ID1&5'!K:L,2,FALSE),"-") -> - | V686: =+IFERROR(VLOOKUP(CONCATENATE(A686,$F$10,F686),'ID1&5'!B:J,9,FALSE),"-") -> - | W686: =+IFERROR(VLOOKUP(A686,'ID6&7'!A:I,9,FALSE),"-") -> - | X686: =+IFERROR(VLOOKUP(A686,'ID6&7'!A:J,10,FALSE),"-") -> - | Z686: =+IF(J686=0,"Por iniciar",IF(OR(K686="-",M686="-",P686="-",R686="-",T686="-",V686="-"),"Em testes",IF(AND(M686=0,P686=0,R686=0,T686<>K686,V686<>K686),"OK","NOK"))) -> Por iniciar
J687: =+COUNTIF('ID1&5'!G:G,'1. Status'!I687) -> 0 | K687: =+IFERROR(VLOOKUP(CONCATENATE(A687,$B$10,B687),'ID1&5'!B:J,8,FALSE),"-") -> - | L687: =+IFERROR(VLOOKUP(B687,'ID1&5'!K:L,2,FALSE),"-") -> - | M687: =+IFERROR(VLOOKUP(CONCATENATE(A687,$B$10,B687),'ID1&5'!B:J,9,FALSE),"-") -> - | N687: =+IFERROR(VLOOKUP(CONCATENATE(A687,$C$10,C687),'ID1&5'!B:J,8,FALSE),"-") -> - | O687: =+IFERROR(VLOOKUP(C687,'ID1&5'!K:L,2,FALSE),"-") -> - | P687: =+IFERROR(VLOOKUP(CONCATENATE(A687,$C$10,C687),'ID1&5'!B:J,9,FALSE),"-") -> - | Q687: =+IFERROR(VLOOKUP(D687,'ID1&5'!K:L,2,FALSE),"-") -> - | R687: =+IFERROR(VLOOKUP(CONCATENATE(A687,$D$10,D687),'ID1&5'!B:J,9,FALSE),"-") -> - | S687: =+IFERROR(VLOOKUP(E687,'ID1&5'!K:L,2,FALSE),"-") -> - | T687: =+IFERROR(VLOOKUP(CONCATENATE(A687,$E$10,E687),'ID1&5'!B:J,9,FALSE),"-") -> - | U687: =+IFERROR(VLOOKUP(F687,'ID1&5'!K:L,2,FALSE),"-") -> - | V687: =+IFERROR(VLOOKUP(CONCATENATE(A687,$F$10,F687),'ID1&5'!B:J,9,FALSE),"-") -> - | W687: =+IFERROR(VLOOKUP(A687,'ID6&7'!A:I,9,FALSE),"-") -> - | X687: =+IFERROR(VLOOKUP(A687,'ID6&7'!A:J,10,FALSE),"-") -> - | Z687: =+IF(J687=0,"Por iniciar",IF(OR(K687="-",M687="-",P687="-",R687="-",T687="-",V687="-"),"Em testes",IF(AND(M687=0,P687=0,R687=0,T687<>K687,V687<>K687),"OK","NOK"))) -> Por iniciar

Sheet 2. Script 
B6: 2. Script de Controlos
B8: TABELA | C8: TIPOLOGIA_TESTE | D8: TABELA_LT_PILAR3 | E8: TABELA_SIMUL | F8: CAMPO | G8: FORMATO CAMPO | H8: VALORES CODE LIST | I8: UNIVERSO_PM | J8: UNIVERSO_SIMUL | K8: CRUZAMENTO | L8: QUERY 1 | M8: UNION ALL
A9: =+B9&F9 -> ENTITYPRSN_TYP | B9: ENTITY | C9: Coerência | D9: =+UPPER('0. Instruções'!$D$35&"."&VLOOKUP(B9,'0. Instruções'!$C$27:$D$32,2,FALSE)) -> CD_LOAN_TAPES_BCE.LT003_ENTITY | E9: =+UPPER('0. Instruções'!$D$36&"."&VLOOKUP(B9,'0. Instruções'!$C$27:$E$32,3,FALSE)) -> BU_LOANTAPE_WORK.LT003_ENTITY | F9: PRSN_TYP | I9: ="(SELECT "&VLOOKUP(B9,'0. Instruções'!$C$27:$G$32,4,FALSE)&", "&F9&" FROM "&D9&" WHERE "&'0. Instruções'!$D$42&")X" -> (SELECT entty_id, PRSN_TYP FROM CD_LOAN_TAPES_BCE.LT003_ENTITY WHERE ref_date='${ref_date}' AND nome_perimetro='Individual Local' AND segmento='ESTR' AND ambito='SRB_MBDT' AND entidade='00100')X | J9: ="(SELECT "&VLOOKUP(B9,'0. Instruções'!$C$27:$G$32,4,FALSE)&" AS "&VLOOKUP(B9,'0. Instruções'!$C$27:$G$32,4,FALSE)&"_SIMUL, "&F9&" AS "&F9&"_SIMUL FROM "&E9&" WHERE "&'0. Instruções'!$D$43&")Y" -> (SELECT entty_id AS entty_id_SIMUL, PRSN_TYP AS PRSN_TYP_SIMUL FROM BU_LOANTAPE_WORK.LT003_ENTITY WHERE ref_date='${ref_date}' AND nome_perimetro='Individual Local' AND segmento='ESTR' AND ambito='PM' AND entidade='00100')Y | K9: =+UPPER("ON X."&VLOOKUP(B9,'0. Instruções'!$C$27:$G$32,4,FALSE)&"=Y."&VLOOKUP(B9,'0. Instruções'!$C$27:$G$32,4,FALSE)&"_SIMUL") -> ON X.ENTTY_ID=Y.ENTTY_ID_SIMUL | L9: =+IF(C9="Coerência", +IF(LEFT(G9,5)="FLOAT","SELECT '"&UPPER(B9)&"' AS TABELA, '"&UPPER(C9)&"' AS TIPOLOGIA_TESTE,'"&D9&"' AS TABELA_LT,'"&E9&"' AS TABELA_SIMUL,'"&F9&"' AS CAMPO, "&"'${ref_date}' AS REF_DATE, COUNT(*) AS NUM_REG, SUM(IF((ABS(COALESCE(CAST(X."&F9&" AS DECIMAL(18,6)),0)-COALESCE(CAST(Y."&F9&"_SIMUL AS DECIMAL(18,6)),0))>0.000001) OR (X."&F9&" IS NULL AND Y."&F9&"_SIMUL IS NOT NULL ) OR (X."&F9&" IS NOT NULL AND Y."&F9&"_SIMUL IS NULL),1,0)) AS NUM_REG_DIF,'"&MAX('ID1&5'!K:K)+1&"' AS ID_EXEC, CURRENT_TIMESTAMP() AS TIME_EXEC FROM "&I9&" INNER JOIN "&J9&" "&K9,"SELECT '"&UPPER(B9)&"' AS TABELA, '"&UPPER(C9)&"' AS TIPOLOGIA_TESTE,'"&D9&"' AS TABELA_LT,'"&E9&"' AS TABELA_SIMUL,'"&F9&"' AS CAMPO, "&"'${ref_date}' AS REF_DATE, COUNT(*) AS NUM_REG, SUM(IF(COALESCE(CAST(X."&F9&" AS STRING),'')<>COALESCE(CAST(Y."&F9&"_SIMUL AS STRING),'') OR (X."&F9&" IS NULL AND Y."&F9&"_SIMUL IS NOT NULL ) OR (X."&F9&" IS NOT NULL AND Y."&F9&"_SIMUL IS NULL),1,0)) AS NUM_REG_DIF,'"&MAX('ID1&5'!L:L)+1&"' AS ID_EXEC, CURRENT_TIMESTAMP() AS TIME_EXEC FROM "&I9&" INNER JOIN "&J9&" "&K9), IF(C9="Validade",+IF(G9="Code List","SELECT '"&UPPER(B9)&"' AS TABELA, '"&UPPER(C9)&"' AS TIPOLOGIA_TESTE,'"&D9&"' AS TABELA_LT,'N/A' AS TABELA_SIMUL,'"&F9&"' AS CAMPO, "&"'${ref_date}' AS REF_DATE, COUNT(*) AS NUM_REG, SUM(IF(TRIM(CAST(X."&F9&" AS STRING))='' OR TRIM(CAST(X."&F9&" AS STRING)) IS NULL OR CAST(X."&F9&" AS STRING) NOT "&H9&",1,0)) AS NUM_REG_DIF,'"&MAX('ID1&5'!K:K)+1&"' AS ID_EXEC, CURRENT_TIMESTAMP() AS TIME_EXEC FROM "&I9,"SELECT '"&UPPER(B9)&"' AS TABELA, '"&UPPER(C9)&"' AS TIPOLOGIA_TESTE,'"&D9&"' AS TABELA_LT,'N/A' AS TABELA_SIMUL,'"&F9&"' AS CAMPO, "&"'${ref_date}' AS REF_DATE, COUNT(*) AS NUM_REG, SUM(IF(TRIM(CAST(X."&F9&" AS STRING))='' OR TRIM(CAST(X."&F9&" AS STRING)) IS NULL,1,0)) AS NUM_REG_DIF,'"&MAX('ID1&5'!K:K)+1&"' AS ID_EXEC, CURRENT_TIMESTAMP() AS TIME_EXEC FROM "&I9), IF(C9="Caracteres Especiais",+"SELECT '"&UPPER(B9)&"' AS TABELA, '"&UPPER(C9)&"' AS TIPOLOGIA_TESTE,'"&D9&"' AS TABELA_LT,'N/A' AS TABELA_SIMUL,'"&F9&"' AS CAMPO, "&"'${ref_date}' AS REF_DATE, COUNT(*) AS NUM_REG, SUM(IF(REGEXP_REPLACE(TRIM(CAST(X."&F9&" AS STRING)),'[^a-zA-Z0-9_\\s]','') <>TRIM(CAST(X."&F9&" AS STRING)),1,0)) AS NUM_REG_DIF,'"&MAX('ID1&5'!K:K)+1&"' AS ID_EXEC, CURRENT_TIMESTAMP() AS TIME_EXEC FROM "&I9, IF(C9="Missings",+"SELECT '"&UPPER(B9)&"' AS TABELA, '"&UPPER(C9)&"' AS TIPOLOGIA_TESTE,'"&D9&"' AS TABELA_LT,'N/A' AS TABELA_SIMUL,'"&F9&"' AS CAMPO, "&"'${ref_date}' AS REF_DATE, COUNT(*) AS NUM_REG, SUM(IF(TRIM(CAST(X."&F9&" AS STRING)) IN ('0000-00-00','0001-01-01','9999-12-31','MISS','00000','99999999999','99999999999.00','99999999999.000000'),1,0)) AS NUM_REG_DIF,'"&MAX('ID1&5'!K:K)+1&"' AS ID_EXEC, CURRENT_TIMESTAMP() AS TIME_EXEC FROM "&I9, IF(C9="Not applicable",+"SELECT '"&UPPER(B9)&"' AS TABELA, '"&UPPER(C9)&"' AS TIPOLOGIA_TESTE,'"&D9&"' AS TABELA_LT,'N/A' AS TABELA_SIMUL,'"&F9&"' AS CAMPO, "&"'${ref_date}' AS REF_DATE, COUNT(*) AS NUM_REG, SUM(IF(TRIM(CAST(X."&F9&" AS STRING)) IN ('N/A','11111111111','11111111111.00','11111111111.000000','1111-11-11'),1,0)) AS NUM_REG_DIF,'"&MAX('ID1&5'!K:K)+1&"' AS ID_EXEC, CURRENT_TIMESTAMP() AS TIME_EXEC FROM "&I9, IF(C9="Valores extremos",+"SELECT '"&UPPER(B9)&"' AS TABELA, '"&UPPER(C9)&"' AS TIPOLOGIA_TESTE,'"&D9&"' AS TABELA_LT,'N/A' AS TABELA_SIMUL,'"&F9&"' AS CAMPO, "&"'${ref_date}' AS REF_DATE, CAST(MIN("&F9&") AS STRING) AS VALOR_MIN, CAST(MAX("&F9&") AS STRING) AS VALOR_MAX,'"&MAX('ID1&5'!K:K)+1&"' AS ID_EXEC, CURRENT_TIMESTAMP() AS TIME_EXEC FROM "&MID(I9,1,LEN(I9)-2)&" AND CAST("&F9&" AS STRING) NOT IN ('0000-00-00','0001-01-01','9999-12-31','MISS','00000','99999999999','99999999999.00','99999999999.000000','N/A','11111111111','11111111111.00','11111111111.000000','1111-11-11'))X")))))) -> SELECT 'ENTITY' AS TABELA, 'COERÊNCIA' AS TIPOLOGIA_TESTE,'CD_LOAN_TAPES_BCE.LT003_ENTITY' AS TABELA_LT,'BU_LOANTAPE_WORK.LT003_ENTITY' AS TABELA_SIMUL,'PRSN_TYP' AS CAMPO, '${ref_date}' AS REF_DATE, COUNT(*) AS NUM_REG, SUM(IF(COALESCE(CAST(X.PRSN_TYP AS STRING),'')<>COALESCE(CAST(Y.PRSN_TYP_SIMUL AS STRING),'') OR (X.PRSN_TYP IS NULL AND Y.PRSN_TYP_SIMUL IS NOT NULL ) OR (X.PRSN_TYP IS NOT NULL AND Y.PRSN_TYP_SIMUL IS NULL),1,0)) AS NUM_REG_DIF,'1' AS ID_EXEC, CURRENT_TIMESTAMP() AS TIME_EXEC FROM (SELECT entty_id, PRSN_TYP FROM CD_LOAN_TAPES_BCE.LT003_ENTITY WHERE ref_date='${ref_date}' AND nome_perimetro='Individual Local' AND segmento='ESTR' AND ambito='SRB_MBDT' AND entidade='00100')X INNER JOIN (SELECT entty_id AS entty_id_SIMUL, PRSN_TYP AS PRSN_TYP_SIMUL FROM BU_LOANTAPE_WORK.LT003_ENTITY WHERE ref_date='${ref_date}' AND nome_perimetro='Individual Local' AND segmento='ESTR' AND ambito='PM' AND entidade='00100')Y ON X.ENTTY_ID=Y.ENTTY_ID_SIMUL | M9: =+"UNION ALL "&L9 -> UNION ALL SELECT 'ENTITY' AS TABELA, 'COERÊNCIA' AS TIPOLOGIA_TESTE,'CD_LOAN_TAPES_BCE.LT003_ENTITY' AS TABELA_LT,'BU_LOANTAPE_WORK.LT003_ENTITY' AS TABELA_SIMUL,'PRSN_TYP' AS CAMPO, '${ref_date}' AS REF_DATE, COUNT(*) AS NUM_REG, SUM(IF(COALESCE(CAST(X.PRSN_TYP AS STRING),'')<>COALESCE(CAST(Y.PRSN_TYP_SIMUL AS STRING),'') OR (X.PRSN_TYP IS NULL AND Y.PRSN_TYP_SIMUL IS NOT NULL ) OR (X.PRSN_TYP IS NOT NULL AND Y.PRSN_TYP_SIMUL IS NULL),1,0)) AS NUM_REG_DIF,'1' AS ID_EXEC, CURRENT_TIMESTAMP() AS TIME_EXEC FROM (SELECT entty_id, PRSN_TYP FROM CD_LOAN_TAPES_BCE.LT003_ENTITY WHERE ref_date='${ref_date}' AND nome_perimetro='Individual Local' AND segmento='ESTR' AND ambito='SRB_MBDT' AND entidade='00100')X INNER JOIN (SELECT entty_id AS entty_id_SIMUL, PRSN_TYP AS PRSN_TYP_SIMUL FROM BU_LOANTAPE_WORK.LT003_ENTITY WHERE ref_date='${ref_date}' AND nome_perimetro='Individual Local' AND segmento='ESTR' AND ambito='PM' AND entidade='00100')Y ON X.ENTTY_ID=Y.ENTTY_ID_SIMUL
A10: =+B10&F10 -> ENTITYENTTY_NM | B10: ENTITY | C10: Coerência | D10: =+UPPER('0. Instruções'!$D$35&"."&VLOOKUP(B10,'0. Instruções'!$C$27:$D$32,2,FALSE)) -> CD_LOAN_TAPES_BCE.LT003_ENTITY | E10: =+UPPER('0. Instruções'!$D$36&"."&VLOOKUP(B10,'0. Instruções'!$C$27:$E$32,3,FALSE)) -> BU_LOANTAPE_WORK.LT003_ENTITY | F10: ENTTY_NM | I10: ="(SELECT "&VLOOKUP(B10,'0. Instruções'!$C$27:$G$32,4,FALSE)&", "&F10&" FROM "&D10&" WHERE "&'0. Instruções'!$D$42&")X" -> (SELECT entty_id, ENTTY_NM FROM CD_LOAN_TAPES_BCE.LT003_ENTITY WHERE ref_date='${ref_date}' AND nome_perimetro='Individual Local' AND segmento='ESTR' AND ambito='SRB_MBDT' AND entidade='00100')X | J10: ="(SELECT "&VLOOKUP(B10,'0. Instruções'!$C$27:$G$32,4,FALSE)&" AS "&VLOOKUP(B10,'0. Instruções'!$C$27:$G$32,4,FALSE)&"_SIMUL, "&F10&" AS "&F10&"_SIMUL FROM "&E10&" WHERE "&'0. Instruções'!$D$43&")Y" -> (SELECT entty_id AS entty_id_SIMUL, ENTTY_NM AS ENTTY_NM_SIMUL FROM BU_LOANTAPE_WORK.LT003_ENTITY WHERE ref_date='${ref_date}' AND nome_perimetro='Individual Local' AND segmento='ESTR' AND ambito='PM' AND entidade='00100')Y | K10: =+UPPER("ON X."&VLOOKUP(B10,'0. Instruções'!$C$27:$G$32,4,FALSE)&"=Y."&VLOOKUP(B10,'0. Instruções'!$C$27:$G$32,4,FALSE)&"_SIMUL") -> ON X.ENTTY_ID=Y.ENTTY_ID_SIMUL | L10: =+IF(C10="Coerência", +IF(LEFT(G10,5)="FLOAT","SELECT '"&UPPER(B10)&"' AS TABELA, '"&UPPER(C10)&"' AS TIPOLOGIA_TESTE,'"&D10&"' AS TABELA_LT,'"&E10&"' AS TABELA_SIMUL,'"&F10&"' AS CAMPO, "&"'${ref_date}' AS REF_DATE, COUNT(*) AS NUM_REG, SUM(IF((ABS(COALESCE(CAST(X."&F10&" AS DECIMAL(18,6)),0)-COALESCE(CAST(Y."&F10&"_SIMUL AS DECIMAL(18,6)),0))>0.000001) OR (X."&F10&" IS NULL AND Y."&F10&"_SIMUL IS NOT NULL ) OR (X."&F10&" IS NOT NULL AND Y."&F10&"_SIMUL IS NULL),1,0)) AS NUM_REG_DIF,'"&MAX('ID1&5'!K:K)+1&"' AS ID_EXEC, CURRENT_TIMESTAMP() AS TIME_EXEC FROM "&I10&" INNER JOIN "&J10&" "&K10,"SELECT '"&UPPER(B10)&"' AS TABELA, '"&UPPER(C10)&"' AS TIPOLOGIA_TESTE,'"&D10&"' AS TABELA_LT,'"&E10&"' AS TABELA_SIMUL,'"&F10&"' AS CAMPO, "&"'${ref_date}' AS REF_DATE, COUNT(*) AS NUM_REG, SUM(IF(COALESCE(CAST(X."&F10&" AS STRING),'')<>COALESCE(CAST(Y."&F10&"_SIMUL AS STRING),'') OR (X."&F10&" IS NULL AND Y."&F10&"_SIMUL IS NOT NULL ) OR (X."&F10&" IS NOT NULL AND Y."&F10&"_SIMUL IS NULL),1,0)) AS NUM_REG_DIF,'"&MAX('ID1&5'!L:L)+1&"' AS ID_EXEC, CURRENT_TIMESTAMP() AS TIME_EXEC FROM "&I10&" INNER JOIN "&J10&" "&K10), IF(C10="Validade",+IF(G10="Code List","SELECT '"&UPPER(B10)&"' AS TABELA, '"&UPPER(C10)&"' AS TIPOLOGIA_TESTE,'"&D10&"' AS TABELA_LT,'N/A' AS TABELA_SIMUL,'"&F10&"' AS CAMPO, "&"'${ref_date}' AS REF_DATE, COUNT(*) AS NUM_REG, SUM(IF(TRIM(CAST(X."&F10&" AS STRING))='' OR TRIM(CAST(X."&F10&" AS STRING)) IS NULL OR CAST(X."&F10&" AS STRING) NOT "&H10&",1,0)) AS NUM_REG_DIF,'"&MAX('ID1&5'!K:K)+1&"' AS ID_EXEC, CURRENT_TIMESTAMP() AS TIME_EXEC FROM "&I10,"SELECT '"&UPPER(B10)&"' AS TABELA, '"&UPPER(C10)&"' AS TIPOLOGIA_TESTE,'"&D10&"' AS TABELA_LT,'N/A' AS TABELA_SIMUL,'"&F10&"' AS CAMPO, "&"'${ref_date}' AS REF_DATE, COUNT(*) AS NUM_REG, SUM(IF(TRIM(CAST(X."&F10&" AS STRING))='' OR TRIM(CAST(X."&F10&" AS STRING)) IS NULL,1,0)) AS NUM_REG_DIF,'"&MAX('ID1&5'!K:K)+1&"' AS ID_EXEC, CURRENT_TIMESTAMP() AS TIME_EXEC FROM "&I10), IF(C10="Caracteres Especiais",+"SELECT '"&UPPER(B10)&"' AS TABELA, '"&UPPER(C10)&"' AS TIPOLOGIA_TESTE,'"&D10&"' AS TABELA_LT,'N/A' AS TABELA_SIMUL,'"&F10&"' AS CAMPO, "&"'${ref_date}' AS REF_DATE, COUNT(*) AS NUM_REG, SUM(IF(REGEXP_REPLACE(TRIM(CAST(X."&F10&" AS STRING)),'[^a-zA-Z0-9_\\s]','') <>TRIM(CAST(X."&F10&" AS STRING)),1,0)) AS NUM_REG_DIF,'"&MAX('ID1&5'!K:K)+1&"' AS ID_EXEC, CURRENT_TIMESTAMP() AS TIME_EXEC FROM "&I10, IF(C10="Missings",+"SELECT '"&UPPER(B10)&"' AS TABELA, '"&UPPER(C10)&"' AS TIPOLOGIA_TESTE,'"&D10&"' AS TABELA_LT,'N/A' AS TABELA_SIMUL,'"&F10&"' AS CAMPO, "&"'${ref_date}' AS REF_DATE, COUNT(*) AS NUM_REG, SUM(IF(TRIM(CAST(X."&F10&" AS STRING)) IN ('0000-00-00','0001-01-01','9999-12-31','MISS','00000','99999999999','99999999999.00','99999999999.000000'),1,0)) AS NUM_REG_DIF,'"&MAX('ID1&5'!K:K)+1&"' AS ID_EXEC, CURRENT_TIMESTAMP() AS TIME_EXEC FROM "&I10, IF(C10="Not applicable",+"SELECT '"&UPPER(B10)&"' AS TABELA, '"&UPPER(C10)&"' AS TIPOLOGIA_TESTE,'"&D10&"' AS TABELA_LT,'N/A' AS TABELA_SIMUL,'"&F10&"' AS CAMPO, "&"'${ref_date}' AS REF_DATE, COUNT(*) AS NUM_REG, SUM(IF(TRIM(CAST(X."&F10&" AS STRING)) IN ('N/A','11111111111','11111111111.00','11111111111.000000','1111-11-11'),1,0)) AS NUM_REG_DIF,'"&MAX('ID1&5'!K:K)+1&"' AS ID_EXEC, CURRENT_TIMESTAMP() AS TIME_EXEC FROM "&I10, IF(C10="Valores extremos",+"SELECT '"&UPPER(B10)&"' AS TABELA, '"&UPPER(C10)&"' AS TIPOLOGIA_TESTE,'"&D10&"' AS TABELA_LT,'N/A' AS TABELA_SIMUL,'"&F10&"' AS CAMPO, "&"'${ref_date}' AS REF_DATE, CAST(MIN("&F10&") AS STRING) AS VALOR_MIN, CAST(MAX("&F10&") AS STRING) AS VALOR_MAX,'"&MAX('ID1&5'!K:K)+1&"' AS ID_EXEC, CURRENT_TIMESTAMP() AS TIME_EXEC FROM "&MID(I10,1,LEN(I10)-2)&" AND CAST("&F10&" AS STRING) NOT IN ('0000-00-00','0001-01-01','9999-12-31','MISS','00000','99999999999','99999999999.00','99999999999.000000','N/A','11111111111','11111111111.00','11111111111.000000','1111-11-11'))X")))))) -> SELECT 'ENTITY' AS TABELA, 'COERÊNCIA' AS TIPOLOGIA_TESTE,'CD_LOAN_TAPES_BCE.LT003_ENTITY' AS TABELA_LT,'BU_LOANTAPE_WORK.LT003_ENTITY' AS TABELA_SIMUL,'ENTTY_NM' AS CAMPO, '${ref_date}' AS REF_DATE, COUNT(*) AS NUM_REG, SUM(IF(COALESCE(CAST(X.ENTTY_NM AS STRING),'')<>COALESCE(CAST(Y.ENTTY_NM_SIMUL AS STRING),'') OR (X.ENTTY_NM IS NULL AND Y.ENTTY_NM_SIMUL IS NOT NULL ) OR (X.ENTTY_NM IS NOT NULL AND Y.ENTTY_NM_SIMUL IS NULL),1,0)) AS NUM_REG_DIF,'1' AS ID_EXEC, CURRENT_TIMESTAMP() AS TIME_EXEC FROM (SELECT entty_id, ENTTY_NM FROM CD_LOAN_TAPES_BCE.LT003_ENTITY WHERE ref_date='${ref_date}' AND nome_perimetro='Individual Local' AND segmento='ESTR' AND ambito='SRB_MBDT' AND entidade='00100')X INNER JOIN (SELECT entty_id AS entty_id_SIMUL, ENTTY_NM AS ENTTY_NM_SIMUL FROM BU_LOANTAPE_WORK.LT003_ENTITY WHERE ref_date='${ref_date}' AND nome_perimetro='Individual Local' AND segmento='ESTR' AND ambito='PM' AND entidade='00100')Y ON X.ENTTY_ID=Y.ENTTY_ID_SIMUL | M10: =+"UNION ALL "&L10 -> UNION ALL SELECT 'ENTITY' AS TABELA, 'COERÊNCIA' AS TIPOLOGIA_TESTE,'CD_LOAN_TAPES_BCE.LT003_ENTITY' AS TABELA_LT,'BU_LOANTAPE_WORK.LT003_ENTITY' AS TABELA_SIMUL,'ENTTY_NM' AS CAMPO, '${ref_date}' AS REF_DATE, COUNT(*) AS NUM_REG, SUM(IF(COALESCE(CAST(X.ENTTY_NM AS STRING),'')<>COALESCE(CAST(Y.ENTTY_NM_SIMUL AS STRING),'') OR (X.ENTTY_NM IS NULL AND Y.ENTTY_NM_SIMUL IS NOT NULL ) OR (X.ENTTY_NM IS NOT NULL AND Y.ENTTY_NM_SIMUL IS NULL),1,0)) AS NUM_REG_DIF,'1' AS ID_EXEC, CURRENT_TIMESTAMP() AS TIME_EXEC FROM (SELECT entty_id, ENTTY_NM FROM CD_LOAN_TAPES_BCE.LT003_ENTITY WHERE ref_date='${ref_date}' AND nome_perimetro='Individual Local' AND segmento='ESTR' AND ambito='SRB_MBDT' AND entidade='00100')X INNER JOIN (SELECT entty_id AS entty_id_SIMUL, ENTTY_NM AS ENTTY_NM_SIMUL FROM BU_LOANTAPE_WORK.LT003_ENTITY WHERE ref_date='${ref_date}' AND nome_perimetro='Individual Local' AND segmento='ESTR' AND ambito='PM' AND entidade='00100')Y ON X.ENTTY_ID=Y.ENTTY_ID_SIMUL
A11: =+B11&F11 -> ENTITYLEI | B11: ENTITY | C11: Coerência | D11: =+UPPER('0. Instruções'!$D$35&"."&VLOOKUP(B11,'0. Instruções'!$C$27:$D$32,2,FALSE)) -> CD_LOAN_TAPES_BCE.LT003_ENTITY | E11: =+UPPER('0. Instruções'!$D$36&"."&VLOOKUP(B11,'0. Instruções'!$C$27:$E$32,3,FALSE)) -> BU_LOANTAPE_WORK.LT003_ENTITY | F11: LEI | I11: ="(SELECT "&VLOOKUP(B11,'0. Instruções'!$C$27:$G$32,4,FALSE)&", "&F11&" FROM "&D11&" WHERE "&'0. Instruções'!$D$42&")X" -> (SELECT entty_id, LEI FROM CD_LOAN_TAPES_BCE.LT003_ENTITY WHERE ref_date='${ref_date}' AND nome_perimetro='Individual Local' AND segmento='ESTR' AND ambito='SRB_MBDT' AND entidade='00100')X | J11: ="(SELECT "&VLOOKUP(B11,'0. Instruções'!$C$27:$G$32,4,FALSE)&" AS "&VLOOKUP(B11,'0. Instruções'!$C$27:$G$32,4,FALSE)&"_SIMUL, "&F11&" AS "&F11&"_SIMUL FROM "&E11&" WHERE "&'0. Instruções'!$D$43&")Y" -> (SELECT entty_id AS entty_id_SIMUL, LEI AS LEI_SIMUL FROM BU_LOANTAPE_WORK.LT003_ENTITY WHERE ref_date='${ref_date}' AND nome_perimetro='Individual Local' AND segmento='ESTR' AND ambito='PM' AND entidade='00100')Y | K11: =+UPPER("ON X."&VLOOKUP(B11,'0. Instruções'!$C$27:$G$32,4,FALSE)&"=Y."&VLOOKUP(B11,'0. Instruções'!$C$27:$G$32,4,FALSE)&"_SIMUL") -> ON X.ENTTY_ID=Y.ENTTY_ID_SIMUL | L11: =+IF(C11="Coerência", +IF(LEFT(G11,5)="FLOAT","SELECT '"&UPPER(B11)&"' AS TABELA, '"&UPPER(C11)&"' AS TIPOLOGIA_TESTE,'"&D11&"' AS TABELA_LT,'"&E11&"' AS TABELA_SIMUL,'"&F11&"' AS CAMPO, "&"'${ref_date}' AS REF_DATE, COUNT(*) AS NUM_REG, SUM(IF((ABS(COALESCE(CAST(X."&F11&" AS DECIMAL(18,6)),0)-COALESCE(CAST(Y."&F11&"_SIMUL AS DECIMAL(18,6)),0))>0.000001) OR (X."&F11&" IS NULL AND Y."&F11&"_SIMUL IS NOT NULL ) OR (X."&F11&" IS NOT NULL AND Y."&F11&"_SIMUL IS NULL),1,0)) AS NUM_REG_DIF,'"&MAX('ID1&5'!K:K)+1&"' AS ID_EXEC, CURRENT_TIMESTAMP() AS TIME_EXEC FROM "&I11&" INNER JOIN "&J11&" "&K11,"SELECT '"&UPPER(B11)&"' AS TABELA, '"&UPPER(C11)&"' AS TIPOLOGIA_TESTE,'"&D11&"' AS TABELA_LT,'"&E11&"' AS TABELA_SIMUL,'"&F11&"' AS CAMPO, "&"'${ref_date}' AS REF_DATE, COUNT(*) AS NUM_REG, SUM(IF(COALESCE(CAST(X."&F11&" AS STRING),'')<>COALESCE(CAST(Y."&F11&"_SIMUL AS STRING),'') OR (X."&F11&" IS NULL AND Y."&F11&"_SIMUL IS NOT NULL ) OR (X."&F11&" IS NOT NULL AND Y."&F11&"_SIMUL IS NULL),1,0)) AS NUM_REG_DIF,'"&MAX('ID1&5'!L:L)+1&"' AS ID_EXEC, CURRENT_TIMESTAMP() AS TIME_EXEC FROM "&I11&" INNER JOIN "&J11&" "&K11), IF(C11="Validade",+IF(G11="Code List","SELECT '"&UPPER(B11)&"' AS TABELA, '"&UPPER(C11)&"' AS TIPOLOGIA_TESTE,'"&D11&"' AS TABELA_LT,'N/A' AS TABELA_SIMUL,'"&F11&"' AS CAMPO, "&"'${ref_date}' AS REF_DATE, COUNT(*) AS NUM_REG, SUM(IF(TRIM(CAST(X."&F11&" AS STRING))='' OR TRIM(CAST(X."&F11&" AS STRING)) IS NULL OR CAST(X."&F11&" AS STRING) NOT "&H11&",1,0)) AS NUM_REG_DIF,'"&MAX('ID1&5'!K:K)+1&"' AS ID_EXEC, CURRENT_TIMESTAMP() AS TIME_EXEC FROM "&I11,"SELECT '"&UPPER(B11)&"' AS TABELA, '"&UPPER(C11)&"' AS TIPOLOGIA_TESTE,'"&D11&"' AS TABELA_LT,'N/A' AS TABELA_SIMUL,'"&F11&"' AS CAMPO, "&"'${ref_date}' AS REF_DATE, COUNT(*) AS NUM_REG, SUM(IF(TRIM(CAST(X."&F11&" AS STRING))='' OR TRIM(CAST(X."&F11&" AS STRING)) IS NULL,1,0)) AS NUM_REG_DIF,'"&MAX('ID1&5'!K:K)+1&"' AS ID_EXEC, CURRENT_TIMESTAMP() AS TIME_EXEC FROM "&I11), IF(C11="Caracteres Especiais",+"SELECT '"&UPPER(B11)&"' AS TABELA, '"&UPPER(C11)&"' AS TIPOLOGIA_TESTE,'"&D11&"' AS TABELA_LT,'N/A' AS TABELA_SIMUL,'"&F11&"' AS CAMPO, "&"'${ref_date}' AS REF_DATE, COUNT(*) AS NUM_REG, SUM(IF(REGEXP_REPLACE(TRIM(CAST(X."&F11&" AS STRING)),'[^a-zA-Z0-9_\\s]','') <>TRIM(CAST(X."&F11&" AS STRING)),1,0)) AS NUM_REG_DIF,'"&MAX('ID1&5'!K:K)+1&"' AS ID_EXEC, CURRENT_TIMESTAMP() AS TIME_EXEC FROM "&I11, IF(C11="Missings",+"SELECT '"&UPPER(B11)&"' AS TABELA, '"&UPPER(C11)&"' AS TIPOLOGIA_TESTE,'"&D11&"' AS TABELA_LT,'N/A' AS TABELA_SIMUL,'"&F11&"' AS CAMPO, "&"'${ref_date}' AS REF_DATE, COUNT(*) AS NUM_REG, SUM(IF(TRIM(CAST(X."&F11&" AS STRING)) IN ('0000-00-00','0001-01-01','9999-12-31','MISS','00000','99999999999','99999999999.00','99999999999.000000'),1,0)) AS NUM_REG_DIF,'"&MAX('ID1&5'!K:K)+1&"' AS ID_EXEC, CURRENT_TIMESTAMP() AS TIME_EXEC FROM "&I11, IF(C11="Not applicable",+"SELECT '"&UPPER(B11)&"' AS TABELA, '"&UPPER(C11)&"' AS TIPOLOGIA_TESTE,'"&D11&"' AS TABELA_LT,'N/A' AS TABELA_SIMUL,'"&F11&"' AS CAMPO, "&"'${ref_date}' AS REF_DATE, COUNT(*) AS NUM_REG, SUM(IF(TRIM(CAST(X."&F11&" AS STRING)) IN ('N/A','11111111111','11111111111.00','11111111111.000000','1111-11-11'),1,0)) AS NUM_REG_DIF,'"&MAX('ID1&5'!K:K)+1&"' AS ID_EXEC, CURRENT_TIMESTAMP() AS TIME_EXEC FROM "&I11, IF(C11="Valores extremos",+"SELECT '"&UPPER(B11)&"' AS TABELA, '"&UPPER(C11)&"' AS TIPOLOGIA_TESTE,'"&D11&"' AS TABELA_LT,'N/A' AS TABELA_SIMUL,'"&F11&"' AS CAMPO, "&"'${ref_date}' AS REF_DATE, CAST(MIN("&F11&") AS STRING) AS VALOR_MIN, CAST(MAX("&F11&") AS STRING) AS VALOR_MAX,'"&MAX('ID1&5'!K:K)+1&"' AS ID_EXEC, CURRENT_TIMESTAMP() AS TIME_EXEC FROM "&MID(I11,1,LEN(I11)-2)&" AND CAST("&F11&" AS STRING) NOT IN ('0000-00-00','0001-01-01','9999-12-31','MISS','00000','99999999999','99999999999.00','99999999999.000000','N/A','11111111111','11111111111.00','11111111111.000000','1111-11-11'))X")))))) -> SELECT 'ENTITY' AS TABELA, 'COERÊNCIA' AS TIPOLOGIA_TESTE,'CD_LOAN_TAPES_BCE.LT003_ENTITY' AS TABELA_LT,'BU_LOANTAPE_WORK.LT003_ENTITY' AS TABELA_SIMUL,'LEI' AS CAMPO, '${ref_date}' AS REF_DATE, COUNT(*) AS NUM_REG, SUM(IF(COALESCE(CAST(X.LEI AS STRING),'')<>COALESCE(CAST(Y.LEI_SIMUL AS STRING),'') OR (X.LEI IS NULL AND Y.LEI_SIMUL IS NOT NULL ) OR (X.LEI IS NOT NULL AND Y.LEI_SIMUL IS NULL),1,0)) AS NUM_REG_DIF,'1' AS ID_EXEC, CURRENT_TIMESTAMP() AS TIME_EXEC FROM (SELECT entty_id, LEI FROM CD_LOAN_TAPES_BCE.LT003_ENTITY WHERE ref_date='${ref_date}' AND nome_perimetro='Individual Local' AND segmento='ESTR' AND ambito='SRB_MBDT' AND entidade='00100')X INNER JOIN (SELECT entty_id AS entty_id_SIMUL, LEI AS LEI_SIMUL FROM BU_LOANTAPE_WORK.LT003_ENTITY WHERE ref_date='${ref_date}' AND nome_perimetro='Individual Local' AND segmento='ESTR' AND ambito='PM' AND entidade='00100')Y ON X.ENTTY_ID=Y.ENTTY_ID_SIMUL | M11: =+"UNION ALL "&L11 -> UNION ALL SELECT 'ENTITY' AS TABELA, 'COERÊNCIA' AS TIPOLOGIA_TESTE,'CD_LOAN_TAPES_BCE.LT003_ENTITY' AS TABELA_LT,'BU_LOANTAPE_WORK.LT003_ENTITY' AS TABELA_SIMUL,'LEI' AS CAMPO, '${ref_date}' AS REF_DATE, COUNT(*) AS NUM_REG, SUM(IF(COALESCE(CAST(X.LEI AS STRING),'')<>COALESCE(CAST(Y.LEI_SIMUL AS STRING),'') OR (X.LEI IS NULL AND Y.LEI_SIMUL IS NOT NULL ) OR (X.LEI IS NOT NULL AND Y.LEI_SIMUL IS NULL),1,0)) AS NUM_REG_DIF,'1' AS ID_EXEC, CURRENT_TIMESTAMP() AS TIME_EXEC FROM (SELECT entty_id, LEI FROM CD_LOAN_TAPES_BCE.LT003_ENTITY WHERE ref_date='${ref_date}' AND nome_perimetro='Individual Local' AND segmento='ESTR' AND ambito='SRB_MBDT' AND entidade='00100')X INNER JOIN (SELECT entty_id AS entty_id_SIMUL, LEI AS LEI_SIMUL FROM BU_LOANTAPE_WORK.LT003_ENTITY WHERE ref_date='${ref_date}' AND nome_perimetro='Individual Local' AND segmento='ESTR' AND ambito='PM' AND entidade='00100')Y ON X.ENTTY_ID=Y.ENTTY_ID_SIMUL
A12: =+B12&F12 -> ENTITYCNTRY | B12: ENTITY | C12: Coerência | D12: =+UPPER('0. Instruções'!$D$35&"."&VLOOKUP(B12,'0. Instruções'!$C$27:$D$32,2,FALSE)) -> CD_LOAN_TAPES_BCE.LT003_ENTITY | E12: =+UPPER('0. Instruções'!$D$36&"."&VLOOKUP(B12,'0. Instruções'!$C$27:$E$32,3,FALSE)) -> BU_LOANTAPE_WORK.LT003_ENTITY | F12: CNTRY | I12: ="(SELECT "&VLOOKUP(B12,'0. Instruções'!$C$27:$G$32,4,FALSE)&", "&F12&" FROM "&D12&" WHERE "&'0. Instruções'!$D$42&")X" -> (SELECT entty_id, CNTRY FROM CD_LOAN_TAPES_BCE.LT003_ENTITY WHERE ref_date='${ref_date}' AND nome_perimetro='Individual Local' AND segmento='ESTR' AND ambito='SRB_MBDT' AND entidade='00100')X | J12: ="(SELECT "&VLOOKUP(B12,'0. Instruções'!$C$27:$G$32,4,FALSE)&" AS "&VLOOKUP(B12,'0. Instruções'!$C$27:$G$32,4,FALSE)&"_SIMUL, "&F12&" AS "&F12&"_SIMUL FROM "&E12&" WHERE "&'0. Instruções'!$D$43&")Y" -> (SELECT entty_id AS entty_id_SIMUL, CNTRY AS CNTRY_SIMUL FROM BU_LOANTAPE_WORK.LT003_ENTITY WHERE ref_date='${ref_date}' AND nome_perimetro='Individual Local' AND segmento='ESTR' AND ambito='PM' AND entidade='00100')Y | K12: =+UPPER("ON X."&VLOOKUP(B12,'0. Instruções'!$C$27:$G$32,4,FALSE)&"=Y."&VLOOKUP(B12,'0. Instruções'!$C$27:$G$32,4,FALSE)&"_SIMUL") -> ON X.ENTTY_ID=Y.ENTTY_ID_SIMUL | L12: =+IF(C12="Coerência", +IF(LEFT(G12,5)="FLOAT","SELECT '"&UPPER(B12)&"' AS TABELA, '"&UPPER(C12)&"' AS TIPOLOGIA_TESTE,'"&D12&"' AS TABELA_LT,'"&E12&"' AS TABELA_SIMUL,'"&F12&"' AS CAMPO, "&"'${ref_date}' AS REF_DATE, COUNT(*) AS NUM_REG, SUM(IF((ABS(COALESCE(CAST(X."&F12&" AS DECIMAL(18,6)),0)-COALESCE(CAST(Y."&F12&"_SIMUL AS DECIMAL(18,6)),0))>0.000001) OR (X."&F12&" IS NULL AND Y."&F12&"_SIMUL IS NOT NULL ) OR (X."&F12&" IS NOT NULL AND Y."&F12&"_SIMUL IS NULL),1,0)) AS NUM_REG_DIF,'"&MAX('ID1&5'!K:K)+1&"' AS ID_EXEC, CURRENT_TIMESTAMP() AS TIME_EXEC FROM "&I12&" INNER JOIN "&J12&" "&K12,"SELECT '"&UPPER(B12)&"' AS TABELA, '"&UPPER(C12)&"' AS TIPOLOGIA_TESTE,'"&D12&"' AS TABELA_LT,'"&E12&"' AS TABELA_SIMUL,'"&F12&"' AS CAMPO, "&"'${ref_date}' AS REF_DATE, COUNT(*) AS NUM_REG, SUM(IF(COALESCE(CAST(X."&F12&" AS STRING),'')<>COALESCE(CAST(Y."&F12&"_SIMUL AS STRING),'') OR (X."&F12&" IS NULL AND Y."&F12&"_SIMUL IS NOT NULL ) OR (X."&F12&" IS NOT NULL AND Y."&F12&"_SIMUL IS NULL),1,0)) AS NUM_REG_DIF,'"&MAX('ID1&5'!L:L)+1&"' AS ID_EXEC, CURRENT_TIMESTAMP() AS TIME_EXEC FROM "&I12&" INNER JOIN "&J12&" "&K12), IF(C12="Validade",+IF(G12="Code List","SELECT '"&UPPER(B12)&"' AS TABELA, '"&UPPER(C12)&"' AS TIPOLOGIA_TESTE,'"&D12&"' AS TABELA_LT,'N/A' AS TABELA_SIMUL,'"&F12&"' AS CAMPO, "&"'${ref_date}' AS REF_DATE, COUNT(*) AS NUM_REG, SUM(IF(TRIM(CAST(X."&F12&" AS STRING))='' OR TRIM(CAST(X."&F12&" AS STRING)) IS NULL OR CAST(X."&F12&" AS STRING) NOT "&H12&",1,0)) AS NUM_REG_DIF,'"&MAX('ID1&5'!K:K)+1&"' AS ID_EXEC, CURRENT_TIMESTAMP() AS TIME_EXEC FROM "&I12,"SELECT '"&UPPER(B12)&"' AS TABELA, '"&UPPER(C12)&"' AS TIPOLOGIA_TESTE,'"&D12&"' AS TABELA_LT,'N/A' AS TABELA_SIMUL,'"&F12&"' AS CAMPO, "&"'${ref_date}' AS REF_DATE, COUNT(*) AS NUM_REG, SUM(IF(TRIM(CAST(X."&F12&" AS STRING))='' OR TRIM(CAST(X."&F12&" AS STRING)) IS NULL,1,0)) AS NUM_REG_DIF,'"&MAX('ID1&5'!K:K)+1&"' AS ID_EXEC, CURRENT_TIMESTAMP() AS TIME_EXEC FROM "&I12), IF(C12="Caracteres Especiais",+"SELECT '"&UPPER(B12)&"' AS TABELA, '"&UPPER(C12)&"' AS TIPOLOGIA_TESTE,'"&D12&"' AS TABELA_LT,'N/A' AS TABELA_SIMUL,'"&F12&"' AS CAMPO, "&"'${ref_date}' AS REF_DATE, COUNT(*) AS NUM_REG, SUM(IF(REGEXP_REPLACE(TRIM(CAST(X."&F12&" AS STRING)),'[^a-zA-Z0-9_\\s]','') <>TRIM(CAST(X."&F12&" AS STRING)),1,0)) AS NUM_REG_DIF,'"&MAX('ID1&5'!K:K)+1&"' AS ID_EXEC, CURRENT_TIMESTAMP() AS TIME_EXEC FROM "&I12, IF(C12="Missings",+"SELECT '"&UPPER(B12)&"' AS TABELA, '"&UPPER(C12)&"' AS TIPOLOGIA_TESTE,'"&D12&"' AS TABELA_LT,'N/A' AS TABELA_SIMUL,'"&F12&"' AS CAMPO, "&"'${ref_date}' AS REF_DATE, COUNT(*) AS NUM_REG, SUM(IF(TRIM(CAST(X."&F12&" AS STRING)) IN ('0000-00-00','0001-01-01','9999-12-31','MISS','00000','99999999999','99999999999.00','99999999999.000000'),1,0)) AS NUM_REG_DIF,'"&MAX('ID1&5'!K:K)+1&"' AS ID_EXEC, CURRENT_TIMESTAMP() AS TIME_EXEC FROM "&I12, IF(C12="Not applicable",+"SELECT '"&UPPER(B12)&"' AS TABELA, '"&UPPER(C12)&"' AS TIPOLOGIA_TESTE,'"&D12&"' AS TABELA_LT,'N/A' AS TABELA_SIMUL,'"&F12&"' AS CAMPO, "&"'${ref_date}' AS REF_DATE, COUNT(*) AS NUM_REG, SUM(IF(TRIM(CAST(X."&F12&" AS STRING)) IN ('N/A','11111111111','11111111111.00','11111111111.000000','1111-11-11'),1,0)) AS NUM_REG_DIF,'"&MAX('ID1&5'!K:K)+1&"' AS ID_EXEC, CURRENT_TIMESTAMP() AS TIME_EXEC FROM "&I12, IF(C12="Valores extremos",+"SELECT '"&UPPER(B12)&"' AS TABELA, '"&UPPER(C12)&"' AS TIPOLOGIA_TESTE,'"&D12&"' AS TABELA_LT,'N/A' AS TABELA_SIMUL,'"&F12&"' AS CAMPO, "&"'${ref_date}' AS REF_DATE, CAST(MIN("&F12&") AS STRING) AS VALOR_MIN, CAST(MAX("&F12&") AS STRING) AS VALOR_MAX,'"&MAX('ID1&5'!K:K)+1&"' AS ID_EXEC, CURRENT_TIMESTAMP() AS TIME_EXEC FROM "&MID(I12,1,LEN(I12)-2)&" AND CAST("&F12&" AS STRING) NOT IN ('0000-00-00','0001-01-01','9999-12-31','MISS','00000','99999999999','99999999999.00','99999999999.000000','N/A','11111111111','11111111111.00','11111111111.000000','1111-11-11'))X")))))) -> SELECT 'ENTITY' AS TABELA, 'COERÊNCIA' AS TIPOLOGIA_TESTE,'CD_LOAN_TAPES_BCE.LT003_ENTITY' AS TABELA_LT,'BU_LOANTAPE_WORK.LT003_ENTITY' AS TABELA_SIMUL,'CNTRY' AS CAMPO, '${ref_date}' AS REF_DATE, COUNT(*) AS NUM_REG, SUM(IF(COALESCE(CAST(X.CNTRY AS STRING),'')<>COALESCE(CAST(Y.CNTRY_SIMUL AS STRING),'') OR (X.CNTRY IS NULL AND Y.CNTRY_SIMUL IS NOT NULL ) OR (X.CNTRY IS NOT NULL AND Y.CNTRY_SIMUL IS NULL),1,0)) AS NUM_REG_DIF,'1' AS ID_EXEC, CURRENT_TIMESTAMP() AS TIME_EXEC FROM (SELECT entty_id, CNTRY FROM CD_LOAN_TAPES_BCE.LT003_ENTITY WHERE ref_date='${ref_date}' AND nome_perimetro='Individual Local' AND segmento='ESTR' AND ambito='SRB_MBDT' AND entidade='00100')X INNER JOIN (SELECT entty_id AS entty_id_SIMUL, CNTRY AS CNTRY_SIMUL FROM BU_LOANTAPE_WORK.LT003_ENTITY WHERE ref_date='${ref_date}' AND nome_perimetro='Individual Local' AND segmento='ESTR' AND ambito='PM' AND entidade='00100')Y ON X.ENTTY_ID=Y.ENTTY_ID_SIMUL | M12: =+"UNION ALL "&L12 -> UNION ALL SELECT 'ENTITY' AS TABELA, 'COERÊNCIA' AS TIPOLOGIA_TESTE,'CD_LOAN_TAPES_BCE.LT003_ENTITY' AS TABELA_LT,'BU_LOANTAPE_WORK.LT003_ENTITY' AS TABELA_SIMUL,'CNTRY' AS CAMPO, '${ref_date}' AS REF_DATE, COUNT(*) AS NUM_REG, SUM(IF(COALESCE(CAST(X.CNTRY AS STRING),'')<>COALESCE(CAST(Y.CNTRY_SIMUL AS STRING),'') OR (X.CNTRY IS NULL AND Y.CNTRY_SIMUL IS NOT NULL ) OR (X.CNTRY IS NOT NULL AND Y.CNTRY_SIMUL IS NULL),1,0)) AS NUM_REG_DIF,'1' AS ID_EXEC, CURRENT_TIMESTAMP() AS TIME_EXEC FROM (SELECT entty_id, CNTRY FROM CD_LOAN_TAPES_BCE.LT003_ENTITY WHERE ref_date='${ref_date}' AND nome_perimetro='Individual Local' AND segmento='ESTR' AND ambito='SRB_MBDT' AND entidade='00100')X INNER JOIN (SELECT entty_id AS entty_id_SIMUL, CNTRY AS CNTRY_SIMUL FROM BU_LOANTAPE_WORK.LT003_ENTITY WHERE ref_date='${ref_date}' AND nome_perimetro='Individual Local' AND segmento='ESTR' AND ambito='PM' AND entidade='00100')Y ON X.ENTTY_ID=Y.ENTTY_ID_SIMUL
A13: =+B13&F13 -> INSTRUMENTISIN | B13: INSTRUMENT | C13: Coerência | D13: =+UPPER('0. Instruções'!$D$35&"."&VLOOKUP(B13,'0. Instruções'!$C$27:$D$32,2,FALSE)) -> CD_LOAN_TAPES_BCE.LT002_INSTRUMENT | E13: =+UPPER('0. Instruções'!$D$36&"."&VLOOKUP(B13,'0. Instruções'!$C$27:$E$32,3,FALSE)) -> BU_LOANTAPE_WORK.LT002_INSTRUMENT | F13: ISIN | I13: ="(SELECT "&VLOOKUP(B13,'0. Instruções'!$C$27:$G$32,4,FALSE)&", "&F13&" FROM "&D13&" WHERE "&'0. Instruções'!$D$42&")X" -> (SELECT instrmnt_id, ISIN FROM CD_LOAN_TAPES_BCE.LT002_INSTRUMENT WHERE ref_date='${ref_date}' AND nome_perimetro='Individual Local' AND segmento='ESTR' AND ambito='SRB_MBDT' AND entidade='00100')X | J13: ="(SELECT "&VLOOKUP(B13,'0. Instruções'!$C$27:$G$32,4,FALSE)&" AS "&VLOOKUP(B13,'0. Instruções'!$C$27:$G$32,4,FALSE)&"_SIMUL, "&F13&" AS "&F13&"_SIMUL FROM "&E13&" WHERE "&'0. Instruções'!$D$43&")Y" -> (SELECT instrmnt_id AS instrmnt_id_SIMUL, ISIN AS ISIN_SIMUL FROM BU_LOANTAPE_WORK.LT002_INSTRUMENT WHERE ref_date='${ref_date}' AND nome_perimetro='Individual Local' AND segmento='ESTR' AND ambito='PM' AND entidade='00100')Y | K13: =+UPPER("ON X."&VLOOKUP(B13,'0. Instruções'!$C$27:$G$32,4,FALSE)&"=Y."&VLOOKUP(B13,'0. Instruções'!$C$27:$G$32,4,FALSE)&"_SIMUL") -> ON X.INSTRMNT_ID=Y.INSTRMNT_ID_SIMUL | L13: =+IF(C13="Coerência", +IF(LEFT(G13,5)="FLOAT","SELECT '"&UPPER(B13)&"' AS TABELA, '"&UPPER(C13)&"' AS TIPOLOGIA_TESTE,'"&D13&"' AS TABELA_LT,'"&E13&"' AS TABELA_SIMUL,'"&F13&"' AS CAMPO, "&"'${ref_date}' AS REF_DATE, COUNT(*) AS NUM_REG, SUM(IF((ABS(COALESCE(CAST(X."&F13&" AS DECIMAL(18,6)),0)-COALESCE(CAST(Y."&F13&"_SIMUL AS DECIMAL(18,6)),0))>0.000001) OR (X."&F13&" IS NULL AND Y."&F13&"_SIMUL IS NOT NULL ) OR (X."&F13&" IS NOT NULL AND Y."&F13&"_SIMUL IS NULL),1,0)) AS NUM_REG_DIF,'"&MAX('ID1&5'!K:K)+1&"' AS ID_EXEC, CURRENT_TIMESTAMP() AS TIME_EXEC FROM "&I13&" INNER JOIN "&J13&" "&K13,"SELECT '"&UPPER(B13)&"' AS TABELA, '"&UPPER(C13)&"' AS TIPOLOGIA_TESTE,'"&D13&"' AS TABELA_LT,'"&E13&"' AS TABELA_SIMUL,'"&F13&"' AS CAMPO, "&"'${ref_date}' AS REF_DATE, COUNT(*) AS NUM_REG, SUM(IF(COALESCE(CAST(X."&F13&" AS STRING),'')<>COALESCE(CAST(Y."&F13&"_SIMUL AS STRING),'') OR (X."&F13&" IS NULL AND Y."&F13&"_SIMUL IS NOT NULL ) OR (X."&F13&" IS NOT NULL AND Y."&F13&"_SIMUL IS NULL),1,0)) AS NUM_REG_DIF,'"&MAX('ID1&5'!L:L)+1&"' AS ID_EXEC, CURRENT_TIMESTAMP() AS TIME_EXEC FROM "&I13&" INNER JOIN "&J13&" "&K13), IF(C13="Validade",+IF(G13="Code List","SELECT '"&UPPER(B13)&"' AS TABELA, '"&UPPER(C13)&"' AS TIPOLOGIA_TESTE,'"&D13&"' AS TABELA_LT,'N/A' AS TABELA_SIMUL,'"&F13&"' AS CAMPO, "&"'${ref_date}' AS REF_DATE, COUNT(*) AS NUM_REG, SUM(IF(TRIM(CAST(X."&F13&" AS STRING))='' OR TRIM(CAST(X."&F13&" AS STRING)) IS NULL OR CAST(X."&F13&" AS STRING) NOT "&H13&",1,0)) AS NUM_REG_DIF,'"&MAX('ID1&5'!K:K)+1&"' AS ID_EXEC, CURRENT_TIMESTAMP() AS TIME_EXEC FROM "&I13,"SELECT '"&UPPER(B13)&"' AS TABELA, '"&UPPER(C13)&"' AS TIPOLOGIA_TESTE,'"&D13&"' AS TABELA_LT,'N/A' AS TABELA_SIMUL,'"&F13&"' AS CAMPO, "&"'${ref_date}' AS REF_DATE, COUNT(*) AS NUM_REG, SUM(IF(TRIM(CAST(X."&F13&" AS STRING))='' OR TRIM(CAST(X."&F13&" AS STRING)) IS NULL,1,0)) AS NUM_REG_DIF,'"&MAX('ID1&5'!K:K)+1&"' AS ID_EXEC, CURRENT_TIMESTAMP() AS TIME_EXEC FROM "&I13), IF(C13="Caracteres Especiais",+"SELECT '"&UPPER(B13)&"' AS TABELA, '"&UPPER(C13)&"' AS TIPOLOGIA_TESTE,'"&D13&"' AS TABELA_LT,'N/A' AS TABELA_SIMUL,'"&F13&"' AS CAMPO, "&"'${ref_date}' AS REF_DATE, COUNT(*) AS NUM_REG, SUM(IF(REGEXP_REPLACE(TRIM(CAST(X."&F13&" AS STRING)),'[^a-zA-Z0-9_\\s]','') <>TRIM(CAST(X."&F13&" AS STRING)),1,0)) AS NUM_REG_DIF,'"&MAX('ID1&5'!K:K)+1&"' AS ID_EXEC, CURRENT_TIMESTAMP() AS TIME_EXEC FROM "&I13, IF(C13="Missings",+"SELECT '"&UPPER(B13)&"' AS TABELA, '"&UPPER(C13)&"' AS TIPOLOGIA_TESTE,'"&D13&"' AS TABELA_LT,'N/A' AS TABELA_SIMUL,'"&F13&"' AS CAMPO, "&"'${ref_date}' AS REF_DATE, COUNT(*) AS NUM_REG, SUM(IF(TRIM(CAST(X."&F13&" AS STRING)) IN ('0000-00-00','0001-01-01','9999-12-31','MISS','00000','99999999999','99999999999.00','99999999999.000000'),1,0)) AS NUM_REG_DIF,'"&MAX('ID1&5'!K:K)+1&"' AS ID_EXEC, CURRENT_TIMESTAMP() AS TIME_EXEC FROM "&I13, IF(C13="Not applicable",+"SELECT '"&UPPER(B13)&"' AS TABELA, '"&UPPER(C13)&"' AS TIPOLOGIA_TESTE,'"&D13&"' AS TABELA_LT,'N/A' AS TABELA_SIMUL,'"&F13&"' AS CAMPO, "&"'${ref_date}' AS REF_DATE, COUNT(*) AS NUM_REG, SUM(IF(TRIM(CAST(X."&F13&" AS STRING)) IN ('N/A','11111111111','11111111111.00','11111111111.000000','1111-11-11'),1,0)) AS NUM_REG_DIF,'"&MAX('ID1&5'!K:K)+1&"' AS ID_EXEC, CURRENT_TIMESTAMP() AS TIME_EXEC FROM "&I13, IF(C13="Valores extremos",+"SELECT '"&UPPER(B13)&"' AS TABELA, '"&UPPER(C13)&"' AS TIPOLOGIA_TESTE,'"&D13&"' AS TABELA_LT,'N/A' AS TABELA_SIMUL,'"&F13&"' AS CAMPO, "&"'${ref_date}' AS REF_DATE, CAST(MIN("&F13&") AS STRING) AS VALOR_MIN, CAST(MAX("&F13&") AS STRING) AS VALOR_MAX,'"&MAX('ID1&5'!K:K)+1&"' AS ID_EXEC, CURRENT_TIMESTAMP() AS TIME_EXEC FROM "&MID(I13,1,LEN(I13)-2)&" AND CAST("&F13&" AS STRING) NOT IN ('0000-00-00','0001-01-01','9999-12-31','MISS','00000','99999999999','99999999999.00','99999999999.000000','N/A','11111111111','11111111111.00','11111111111.000000','1111-11-11'))X")))))) -> SELECT 'INSTRUMENT' AS TABELA, 'COERÊNCIA' AS TIPOLOGIA_TESTE,'CD_LOAN_TAPES_BCE.LT002_INSTRUMENT' AS TABELA_LT,'BU_LOANTAPE_WORK.LT002_INSTRUMENT' AS TABELA_SIMUL,'ISIN' AS CAMPO, '${ref_date}' AS REF_DATE, COUNT(*) AS NUM_REG, SUM(IF(COALESCE(CAST(X.ISIN AS STRING),'')<>COALESCE(CAST(Y.ISIN_SIMUL AS STRING),'') OR (X.ISIN IS NULL AND Y.ISIN_SIMUL IS NOT NULL ) OR (X.ISIN IS NOT NULL AND Y.ISIN_SIMUL IS NULL),1,0)) AS NUM_REG_DIF,'1' AS ID_EXEC, CURRENT_TIMESTAMP() AS TIME_EXEC FROM (SELECT instrmnt_id, ISIN FROM CD_LOAN_TAPES_BCE.LT002_INSTRUMENT WHERE ref_date='${ref_date}' AND nome_perimetro='Individual Local' AND segmento='ESTR' AND ambito='SRB_MBDT' AND entidade='00100')X INNER JOIN (SELECT instrmnt_id AS instrmnt_id_SIMUL, ISIN AS ISIN_SIMUL FROM BU_LOANTAPE_WORK.LT002_INSTRUMENT WHERE ref_date='${ref_date}' AND nome_perimetro='Individual Local' AND segmento='ESTR' AND ambito='PM' AND entidade='00100')Y ON X.INSTRMNT_ID=Y.INSTRMNT_ID_SIMUL | M13: =+"UNION ALL "&L13 -> UNION ALL SELECT 'INSTRUMENT' AS TABELA, 'COERÊNCIA' AS TIPOLOGIA_TESTE,'CD_LOAN_TAPES_BCE.LT002_INSTRUMENT' AS TABELA_LT,'BU_LOANTAPE_WORK.LT002_INSTRUMENT' AS TABELA_SIMUL,'ISIN' AS CAMPO, '${ref_date}' AS REF_DATE, COUNT(*) AS NUM_REG, SUM(IF(COALESCE(CAST(X.ISIN AS STRING),'')<>COALESCE(CAST(Y.ISIN_SIMUL AS STRING),'') OR (X.ISIN IS NULL AND Y.ISIN_SIMUL IS NOT NULL ) OR (X.ISIN IS NOT NULL AND Y.ISIN_SIMUL IS NULL),1,0)) AS NUM_REG_DIF,'1' AS ID_EXEC, CURRENT_TIMESTAMP() AS TIME_EXEC FROM (SELECT instrmnt_id, ISIN FROM CD_LOAN_TAPES_BCE.LT002_INSTRUMENT WHERE ref_date='${ref_date}' AND nome_perimetro='Individual Local' AND segmento='ESTR' AND ambito='SRB_MBDT' AND entidade='00100')X INNER JOIN (SELECT instrmnt_id AS instrmnt_id_SIMUL, ISIN AS ISIN_SIMUL FROM BU_LOANTAPE_WORK.LT002_INSTRUMENT WHERE ref_date='${ref_date}' AND nome_perimetro='Individual Local' AND segmento='ESTR' AND ambito='PM' AND entidade='00100')Y ON X.INSTRMNT_ID=Y.INSTRMNT_ID_SIMUL
A14: =+B14&F14 -> INSTRUMENTCRRNCY_DNMNTN | B14: INSTRUMENT | C14: Coerência | D14: =+UPPER('0. Instruções'!$D$35&"."&VLOOKUP(B14,'0. Instruções'!$C$27:$D$32,2,FALSE)) -> CD_LOAN_TAPES_BCE.LT002_INSTRUMENT | E14: =+UPPER('0. Instruções'!$D$36&"."&VLOOKUP(B14,'0. Instruções'!$C$27:$E$32,3,FALSE)) -> BU_LOANTAPE_WORK.LT002_INSTRUMENT | F14: CRRNCY_DNMNTN | I14: ="(SELECT "&VLOOKUP(B14,'0. Instruções'!$C$27:$G$32,4,FALSE)&", "&F14&" FROM "&D14&" WHERE "&'0. Instruções'!$D$42&")X" -> (SELECT instrmnt_id, CRRNCY_DNMNTN FROM CD_LOAN_TAPES_BCE.LT002_INSTRUMENT WHERE ref_date='${ref_date}' AND nome_perimetro='Individual Local' AND segmento='ESTR' AND ambito='SRB_MBDT' AND entidade='00100')X | J14: ="(SELECT "&VLOOKUP(B14,'0. Instruções'!$C$27:$G$32,4,FALSE)&" AS "&VLOOKUP(B14,'0. Instruções'!$C$27:$G$32,4,FALSE)&"_SIMUL, "&F14&" AS "&F14&"_SIMUL FROM "&E14&" WHERE "&'0. Instruções'!$D$43&")Y" -> (SELECT instrmnt_id AS instrmnt_id_SIMUL, CRRNCY_DNMNTN AS CRRNCY_DNMNTN_SIMUL FROM BU_LOANTAPE_WORK.LT002_INSTRUMENT WHERE ref_date='${ref_date}' AND nome_perimetro='Individual Local' AND segmento='ESTR' AND ambito='PM' AND entidade='00100')Y | K14: =+UPPER("ON X."&VLOOKUP(B14,'0. Instruções'!$C$27:$G$32,4,FALSE)&"=Y."&VLOOKUP(B14,'0. Instruções'!$C$27:$G$32,4,FALSE)&"_SIMUL") -> ON X.INSTRMNT_ID=Y.INSTRMNT_ID_SIMUL | L14: =+IF(C14="Coerência", +IF(LEFT(G14,5)="FLOAT","SELECT '"&UPPER(B14)&"' AS TABELA, '"&UPPER(C14)&"' AS TIPOLOGIA_TESTE,'"&D14&"' AS TABELA_LT,'"&E14&"' AS TABELA_SIMUL,'"&F14&"' AS CAMPO, "&"'${ref_date}' AS REF_DATE, COUNT(*) AS NUM_REG, SUM(IF((ABS(COALESCE(CAST(X."&F14&" AS DECIMAL(18,6)),0)-COALESCE(CAST(Y."&F14&"_SIMUL AS DECIMAL(18,6)),0))>0.000001) OR (X."&F14&" IS NULL AND Y."&F14&"_SIMUL IS NOT NULL ) OR (X."&F14&" IS NOT NULL AND Y."&F14&"_SIMUL IS NULL),1,0)) AS NUM_REG_DIF,'"&MAX('ID1&5'!K:K)+1&"' AS ID_EXEC, CURRENT_TIMESTAMP() AS TIME_EXEC FROM "&I14&" INNER JOIN "&J14&" "&K14,"SELECT '"&UPPER(B14)&"' AS TABELA, '"&UPPER(C14)&"' AS TIPOLOGIA_TESTE,'"&D14&"' AS TABELA_LT,'"&E14&"' AS TABELA_SIMUL,'"&F14&"' AS CAMPO, "&"'${ref_date}' AS REF_DATE, COUNT(*) AS NUM_REG, SUM(IF(COALESCE(CAST(X."&F14&" AS STRING),'')<>COALESCE(CAST(Y."&F14&"_SIMUL AS STRING),'') OR (X."&F14&" IS NULL AND Y."&F14&"_SIMUL IS NOT NULL ) OR (X."&F14&" IS NOT NULL AND Y."&F14&"_SIMUL IS NULL),1,0)) AS NUM_REG_DIF,'"&MAX('ID1&5'!L:L)+1&"' AS ID_EXEC, CURRENT_TIMESTAMP() AS TIME_EXEC FROM "&I14&" INNER JOIN "&J14&" "&K14), IF(C14="Validade",+IF(G14="Code List","SELECT '"&UPPER(B14)&"' AS TABELA, '"&UPPER(C14)&"' AS TIPOLOGIA_TESTE,'"&D14&"' AS TABELA_LT,'N/A' AS TABELA_SIMUL,'"&F14&"' AS CAMPO, "&"'${ref_date}' AS REF_DATE, COUNT(*) AS NUM_REG, SUM(IF(TRIM(CAST(X."&F14&" AS STRING))='' OR TRIM(CAST(X."&F14&" AS STRING)) IS NULL OR CAST(X."&F14&" AS STRING) NOT "&H14&",1,0)) AS NUM_REG_DIF,'"&MAX('ID1&5'!K:K)+1&"' AS ID_EXEC, CURRENT_TIMESTAMP() AS TIME_EXEC FROM "&I14,"SELECT '"&UPPER(B14)&"' AS TABELA, '"&UPPER(C14)&"' AS TIPOLOGIA_TESTE,'"&D14&"' AS TABELA_LT,'N/A' AS TABELA_SIMUL,'"&F14&"' AS CAMPO, "&"'${ref_date}' AS REF_DATE, COUNT(*) AS NUM_REG, SUM(IF(TRIM(CAST(X."&F14&" AS STRING))='' OR TRIM(CAST(X."&F14&" AS STRING)) IS NULL,1,0)) AS NUM_REG_DIF,'"&MAX('ID1&5'!K:K)+1&"' AS ID_EXEC, CURRENT_TIMESTAMP() AS TIME_EXEC FROM "&I14), IF(C14="Caracteres Especiais",+"SELECT '"&UPPER(B14)&"' AS TABELA, '"&UPPER(C14)&"' AS TIPOLOGIA_TESTE,'"&D14&"' AS TABELA_LT,'N/A' AS TABELA_SIMUL,'"&F14&"' AS CAMPO, "&"'${ref_date}' AS REF_DATE, COUNT(*) AS NUM_REG, SUM(IF(REGEXP_REPLACE(TRIM(CAST(X."&F14&" AS STRING)),'[^a-zA-Z0-9_\\s]','') <>TRIM(CAST(X."&F14&" AS STRING)),1,0)) AS NUM_REG_DIF,'"&MAX('ID1&5'!K:K)+1&"' AS ID_EXEC, CURRENT_TIMESTAMP() AS TIME_EXEC FROM "&I14, IF(C14="Missings",+"SELECT '"&UPPER(B14)&"' AS TABELA, '"&UPPER(C14)&"' AS TIPOLOGIA_TESTE,'"&D14&"' AS TABELA_LT,'N/A' AS TABELA_SIMUL,'"&F14&"' AS CAMPO, "&"'${ref_date}' AS REF_DATE, COUNT(*) AS NUM_REG, SUM(IF(TRIM(CAST(X."&F14&" AS STRING)) IN ('0000-00-00','0001-01-01','9999-12-31','MISS','00000','99999999999','99999999999.00','99999999999.000000'),1,0)) AS NUM_REG_DIF,'"&MAX('ID1&5'!K:K)+1&"' AS ID_EXEC, CURRENT_TIMESTAMP() AS TIME_EXEC FROM "&I14, IF(C14="Not applicable",+"SELECT '"&UPPER(B14)&"' AS TABELA, '"&UPPER(C14)&"' AS TIPOLOGIA_TESTE,'"&D14&"' AS TABELA_LT,'N/A' AS TABELA_SIMUL,'"&F14&"' AS CAMPO, "&"'${ref_date}' AS REF_DATE, COUNT(*) AS NUM_REG, SUM(IF(TRIM(CAST(X."&F14&" AS STRING)) IN ('N/A','11111111111','11111111111.00','11111111111.000000','1111-11-11'),1,0)) AS NUM_REG_DIF,'"&MAX('ID1&5'!K:K)+1&"' AS ID_EXEC, CURRENT_TIMESTAMP() AS TIME_EXEC FROM "&I14, IF(C14="Valores extremos",+"SELECT '"&UPPER(B14)&"' AS TABELA, '"&UPPER(C14)&"' AS TIPOLOGIA_TESTE,'"&D14&"' AS TABELA_LT,'N/A' AS TABELA_SIMUL,'"&F14&"' AS CAMPO, "&"'${ref_date}' AS REF_DATE, CAST(MIN("&F14&") AS STRING) AS VALOR_MIN, CAST(MAX("&F14&") AS STRING) AS VALOR_MAX,'"&MAX('ID1&5'!K:K)+1&"' AS ID_EXEC, CURRENT_TIMESTAMP() AS TIME_EXEC FROM "&MID(I14,1,LEN(I14)-2)&" AND CAST("&F14&" AS STRING) NOT IN ('0000-00-00','0001-01-01','9999-12-31','MISS','00000','99999999999','99999999999.00','99999999999.000000','N/A','11111111111','11111111111.00','11111111111.000000','1111-11-11'))X")))))) -> SELECT 'INSTRUMENT' AS TABELA, 'COERÊNCIA' AS TIPOLOGIA_TESTE,'CD_LOAN_TAPES_BCE.LT002_INSTRUMENT' AS TABELA_LT,'BU_LOANTAPE_WORK.LT002_INSTRUMENT' AS TABELA_SIMUL,'CRRNCY_DNMNTN' AS CAMPO, '${ref_date}' AS REF_DATE, COUNT(*) AS NUM_REG, SUM(IF(COALESCE(CAST(X.CRRNCY_DNMNTN AS STRING),'')<>COALESCE(CAST(Y.CRRNCY_DNMNTN_SIMUL AS STRING),'') OR (X.CRRNCY_DNMNTN IS NULL AND Y.CRRNCY_DNMNTN_SIMUL IS NOT NULL ) OR (X.CRRNCY_DNMNTN IS NOT NULL AND Y.CRRNCY_DNMNTN_SIMUL IS NULL),1,0)) AS NUM_REG_DIF,'1' AS ID_EXEC, CURRENT_TIMESTAMP() AS TIME_EXEC FROM (SELECT instrmnt_id, CRRNCY_DNMNTN FROM CD_LOAN_TAPES_BCE.LT002_INSTRUMENT WHERE ref_date='${ref_date}' AND nome_perimetro='Individual Local' AND segmento='ESTR' AND ambito='SRB_MBDT' AND entidade='00100')X INNER JOIN (SELECT instrmnt_id AS instrmnt_id_SIMUL, CRRNCY_DNMNTN AS CRRNCY_DNMNTN_SIMUL FROM BU_LOANTAPE_WORK.LT002_INSTRUMENT WHERE ref_date='${ref_date}' AND nome_perimetro='Individual Local' AND segmento='ESTR' AND ambito='PM' AND entidade='00100')Y ON X.INSTRMNT_ID=Y.INSTRMNT_ID_SIMUL | M14: =+"UNION ALL "&L14 -> UNION ALL SELECT 'INSTRUMENT' AS TABELA, 'COERÊNCIA' AS TIPOLOGIA_TESTE,'CD_LOAN_TAPES_BCE.LT002_INSTRUMENT' AS TABELA_LT,'BU_LOANTAPE_WORK.LT002_INSTRUMENT' AS TABELA_SIMUL,'CRRNCY_DNMNTN' AS CAMPO, '${ref_date}' AS REF_DATE, COUNT(*) AS NUM_REG, SUM(IF(COALESCE(CAST(X.CRRNCY_DNMNTN AS STRING),'')<>COALESCE(CAST(Y.CRRNCY_DNMNTN_SIMUL AS STRING),'') OR (X.CRRNCY_DNMNTN IS NULL AND Y.CRRNCY_DNMNTN_SIMUL IS NOT NULL ) OR (X.CRRNCY_DNMNTN IS NOT NULL AND Y.CRRNCY_DNMNTN_SIMUL IS NULL),1,0)) AS NUM_REG_DIF,'1' AS ID_EXEC, CURRENT_TIMESTAMP() AS TIME_EXEC FROM (SELECT instrmnt_id, CRRNCY_DNMNTN FROM CD_LOAN_TAPES_BCE.LT002_INSTRUMENT WHERE ref_date='${ref_date}' AND nome_perimetro='Individual Local' AND segmento='ESTR' AND ambito='SRB_MBDT' AND entidade='00100')X INNER JOIN (SELECT instrmnt_id AS instrmnt_id_SIMUL, CRRNCY_DNMNTN AS CRRNCY_DNMNTN_SIMUL FROM BU_LOANTAPE_WORK.LT002_INSTRUMENT WHERE ref_date='${ref_date}' AND nome_perimetro='Individual Local' AND segmento='ESTR' AND ambito='PM' AND entidade='00100')Y ON X.INSTRMNT_ID=Y.INSTRMNT_ID_SIMUL
A15: =+B15&F15 -> INSTRUMENTACCRD_INTRST_INSTRMNT | B15: INSTRUMENT | C15: Coerência | D15: =+UPPER('0. Instruções'!$D$35&"."&VLOOKUP(B15,'0. Instruções'!$C$27:$D$32,2,FALSE)) -> CD_LOAN_TAPES_BCE.LT002_INSTRUMENT | E15: =+UPPER('0. Instruções'!$D$36&"."&VLOOKUP(B15,'0. Instruções'!$C$27:$E$32,3,FALSE)) -> BU_LOANTAPE_WORK.LT002_INSTRUMENT | F15: ACCRD_INTRST_INSTRMNT | I15: ="(SELECT "&VLOOKUP(B15,'0. Instruções'!$C$27:$G$32,4,FALSE)&", "&F15&" FROM "&D15&" WHERE "&'0. Instruções'!$D$42&")X" -> (SELECT instrmnt_id, ACCRD_INTRST_INSTRMNT FROM CD_LOAN_TAPES_BCE.LT002_INSTRUMENT WHERE ref_date='${ref_date}' AND nome_perimetro='Individual Local' AND segmento='ESTR' AND ambito='SRB_MBDT' AND entidade='00100')X | J15: ="(SELECT "&VLOOKUP(B15,'0. Instruções'!$C$27:$G$32,4,FALSE)&" AS "&VLOOKUP(B15,'0. Instruções'!$C$27:$G$32,4,FALSE)&"_SIMUL, "&F15&" AS "&F15&"_SIMUL FROM "&E15&" WHERE "&'0. Instruções'!$D$43&")Y" -> (SELECT instrmnt_id AS instrmnt_id_SIMUL, ACCRD_INTRST_INSTRMNT AS ACCRD_INTRST_INSTRMNT_SIMUL FROM BU_LOANTAPE_WORK.LT002_INSTRUMENT WHERE ref_date='${ref_date}' AND nome_perimetro='Individual Local' AND segmento='ESTR' AND ambito='PM' AND entidade='00100')Y | K15: =+UPPER("ON X."&VLOOKUP(B15,'0. Instruções'!$C$27:$G$32,4,FALSE)&"=Y."&VLOOKUP(B15,'0. Instruções'!$C$27:$G$32,4,FALSE)&"_SIMUL") -> ON X.INSTRMNT_ID=Y.INSTRMNT_ID_SIMUL | L15: =+IF(C15="Coerência", +IF(LEFT(G15,5)="FLOAT","SELECT '"&UPPER(B15)&"' AS TABELA, '"&UPPER(C15)&"' AS TIPOLOGIA_TESTE,'"&D15&"' AS TABELA_LT,'"&E15&"' AS TABELA_SIMUL,'"&F15&"' AS CAMPO, "&"'${ref_date}' AS REF_DATE, COUNT(*) AS NUM_REG, SUM(IF((ABS(COALESCE(CAST(X."&F15&" AS DECIMAL(18,6)),0)-COALESCE(CAST(Y."&F15&"_SIMUL AS DECIMAL(18,6)),0))>0.000001) OR (X."&F15&" IS NULL AND Y."&F15&"_SIMUL IS NOT NULL ) OR (X."&F15&" IS NOT NULL AND Y."&F15&"_SIMUL IS NULL),1,0)) AS NUM_REG_DIF,'"&MAX('ID1&5'!K:K)+1&"' AS ID_EXEC, CURRENT_TIMESTAMP() AS TIME_EXEC FROM "&I15&" INNER JOIN "&J15&" "&K15,"SELECT '"&UPPER(B15)&"' AS TABELA, '"&UPPER(C15)&"' AS TIPOLOGIA_TESTE,'"&D15&"' AS TABELA_LT,'"&E15&"' AS TABELA_SIMUL,'"&F15&"' AS CAMPO, "&"'${ref_date}' AS REF_DATE, COUNT(*) AS NUM_REG, SUM(IF(COALESCE(CAST(X."&F15&" AS STRING),'')<>COALESCE(CAST(Y."&F15&"_SIMUL AS STRING),'') OR (X."&F15&" IS NULL AND Y."&F15&"_SIMUL IS NOT NULL ) OR (X."&F15&" IS NOT NULL AND Y."&F15&"_SIMUL IS NULL),1,0)) AS NUM_REG_DIF,'"&MAX('ID1&5'!L:L)+1&"' AS ID_EXEC, CURRENT_TIMESTAMP() AS TIME_EXEC FROM "&I15&" INNER JOIN "&J15&" "&K15), IF(C15="Validade",+IF(G15="Code List","SELECT '"&UPPER(B15)&"' AS TABELA, '"&UPPER(C15)&"' AS TIPOLOGIA_TESTE,'"&D15&"' AS TABELA_LT,'N/A' AS TABELA_SIMUL,'"&F15&"' AS CAMPO, "&"'${ref_date}' AS REF_DATE, COUNT(*) AS NUM_REG, SUM(IF(TRIM(CAST(X."&F15&" AS STRING))='' OR TRIM(CAST(X."&F15&" AS STRING)) IS NULL OR CAST(X."&F15&" AS STRING) NOT "&H15&",1,0)) AS NUM_REG_DIF,'"&MAX('ID1&5'!K:K)+1&"' AS ID_EXEC, CURRENT_TIMESTAMP() AS TIME_EXEC FROM "&I15,"SELECT '"&UPPER(B15)&"' AS TABELA, '"&UPPER(C15)&"' AS TIPOLOGIA_TESTE,'"&D15&"' AS TABELA_LT,'N/A' AS TABELA_SIMUL,'"&F15&"' AS CAMPO, "&"'${ref_date}' AS REF_DATE, COUNT(*) AS NUM_REG, SUM(IF(TRIM(CAST(X."&F15&" AS STRING))='' OR TRIM(CAST(X."&F15&" AS STRING)) IS NULL,1,0)) AS NUM_REG_DIF,'"&MAX('ID1&5'!K:K)+1&"' AS ID_EXEC, CURRENT_TIMESTAMP() AS TIME_EXEC FROM "&I15), IF(C15="Caracteres Especiais",+"SELECT '"&UPPER(B15)&"' AS TABELA, '"&UPPER(C15)&"' AS TIPOLOGIA_TESTE,'"&D15&"' AS TABELA_LT,'N/A' AS TABELA_SIMUL,'"&F15&"' AS CAMPO, "&"'${ref_date}' AS REF_DATE, COUNT(*) AS NUM_REG, SUM(IF(REGEXP_REPLACE(TRIM(CAST(X."&F15&" AS STRING)),'[^a-zA-Z0-9_\\s]','') <>TRIM(CAST(X."&F15&" AS STRING)),1,0)) AS NUM_REG_DIF,'"&MAX('ID1&5'!K:K)+1&"' AS ID_EXEC, CURRENT_TIMESTAMP() AS TIME_EXEC FROM "&I15, IF(C15="Missings",+"SELECT '"&UPPER(B15)&"' AS TABELA, '"&UPPER(C15)&"' AS TIPOLOGIA_TESTE,'"&D15&"' AS TABELA_LT,'N/A' AS TABELA_SIMUL,'"&F15&"' AS CAMPO, "&"'${ref_date}' AS REF_DATE, COUNT(*) AS NUM_REG, SUM(IF(TRIM(CAST(X."&F15&" AS STRING)) IN ('0000-00-00','0001-01-01','9999-12-31','MISS','00000','99999999999','99999999999.00','99999999999.000000'),1,0)) AS NUM_REG_DIF,'"&MAX('ID1&5'!K:K)+1&"' AS ID_EXEC, CURRENT_TIMESTAMP() AS TIME_EXEC FROM "&I15, IF(C15="Not applicable",+"SELECT '"&UPPER(B15)&"' AS TABELA, '"&UPPER(C15)&"' AS TIPOLOGIA_TESTE,'"&D15&"' AS TABELA_LT,'N/A' AS TABELA_SIMUL,'"&F15&"' AS CAMPO, "&"'${ref_date}' AS REF_DATE, COUNT(*) AS NUM_REG, SUM(IF(TRIM(CAST(X."&F15&" AS STRING)) IN ('N/A','11111111111','11111111111.00','11111111111.000000','1111-11-11'),1,0)) AS NUM_REG_DIF,'"&MAX('ID1&5'!K:K)+1&"' AS ID_EXEC, CURRENT_TIMESTAMP() AS TIME_EXEC FROM "&I15, IF(C15="Valores extremos",+"SELECT '"&UPPER(B15)&"' AS TABELA, '"&UPPER(C15)&"' AS TIPOLOGIA_TESTE,'"&D15&"' AS TABELA_LT,'N/A' AS TABELA_SIMUL,'"&F15&"' AS CAMPO, "&"'${ref_date}' AS REF_DATE, CAST(MIN("&F15&") AS STRING) AS VALOR_MIN, CAST(MAX("&F15&") AS STRING) AS VALOR_MAX,'"&MAX('ID1&5'!K:K)+1&"' AS ID_EXEC, CURRENT_TIMESTAMP() AS TIME_EXEC FROM "&MID(I15,1,LEN(I15)-2)&" AND CAST("&F15&" AS STRING) NOT IN ('0000-00-00','0001-01-01','9999-12-31','MISS','00000','99999999999','99999999999.00','99999999999.000000','N/A','11111111111','11111111111.00','11111111111.000000','1111-11-11'))X")))))) -> SELECT 'INSTRUMENT' AS TABELA, 'COERÊNCIA' AS TIPOLOGIA_TESTE,'CD_LOAN_TAPES_BCE.LT002_INSTRUMENT' AS TABELA_LT,'BU_LOANTAPE_WORK.LT002_INSTRUMENT' AS TABELA_SIMUL,'ACCRD_INTRST_INSTRMNT' AS CAMPO, '${ref_date}' AS REF_DATE, COUNT(*) AS NUM_REG, SUM(IF(COALESCE(CAST(X.ACCRD_INTRST_INSTRMNT AS STRING),'')<>COALESCE(CAST(Y.ACCRD_INTRST_INSTRMNT_SIMUL AS STRING),'') OR (X.ACCRD_INTRST_INSTRMNT IS NULL AND Y.ACCRD_INTRST_INSTRMNT_SIMUL IS NOT NULL ) OR (X.ACCRD_INTRST_INSTRMNT IS NOT NULL AND Y.ACCRD_INTRST_INSTRMNT_SIMUL IS NULL),1,0)) AS NUM_REG_DIF,'1' AS ID_EXEC, CURRENT_TIMESTAMP() AS TIME_EXEC FROM (SELECT instrmnt_id, ACCRD_INTRST_INSTRMNT FROM CD_LOAN_TAPES_BCE.LT002_INSTRUMENT WHERE ref_date='${ref_date}' AND nome_perimetro='Individual Local' AND segmento='ESTR' AND ambito='SRB_MBDT' AND entidade='00100')X INNER JOIN (SELECT instrmnt_id AS instrmnt_id_SIMUL, ACCRD_INTRST_INSTRMNT AS ACCRD_INTRST_INSTRMNT_SIMUL FROM BU_LOANTAPE_WORK.LT002_INSTRUMENT WHERE ref_date='${ref_date}' AND nome_perimetro='Individual Local' AND segmento='ESTR' AND ambito='PM' AND entidade='00100')Y ON X.INSTRMNT_ID=Y.INSTRMNT_ID_SIMUL | M15: =+"UNION ALL "&L15 -> UNION ALL SELECT 'INSTRUMENT' AS TABELA, 'COERÊNCIA' AS TIPOLOGIA_TESTE,'CD_LOAN_TAPES_BCE.LT002_INSTRUMENT' AS TABELA_LT,'BU_LOANTAPE_WORK.LT002_INSTRUMENT' AS TABELA_SIMUL,'ACCRD_INTRST_INSTRMNT' AS CAMPO, '${ref_date}' AS REF_DATE, COUNT(*) AS NUM_REG, SUM(IF(COALESCE(CAST(X.ACCRD_INTRST_INSTRMNT AS STRING),'')<>COALESCE(CAST(Y.ACCRD_INTRST_INSTRMNT_SIMUL AS STRING),'') OR (X.ACCRD_INTRST_INSTRMNT IS NULL AND Y.ACCRD_INTRST_INSTRMNT_SIMUL IS NOT NULL ) OR (X.ACCRD_INTRST_INSTRMNT IS NOT NULL AND Y.ACCRD_INTRST_INSTRMNT_SIMUL IS NULL),1,0)) AS NUM_REG_DIF,'1' AS ID_EXEC, CURRENT_TIMESTAMP() AS TIME_EXEC FROM (SELECT instrmnt_id, ACCRD_INTRST_INSTRMNT FROM CD_LOAN_TAPES_BCE.LT002_INSTRUMENT WHERE ref_date='${ref_date}' AND nome_perimetro='Individual Local' AND segmento='ESTR' AND ambito='SRB_MBDT' AND entidade='00100')X INNER JOIN (SELECT instrmnt_id AS instrmnt_id_SIMUL, ACCRD_INTRST_INSTRMNT AS ACCRD_INTRST_INSTRMNT_SIMUL FROM BU_LOANTAPE_WORK.LT002_INSTRUMENT WHERE ref_date='${ref_date}' AND nome_perimetro='Individual Local' AND segmento='ESTR' AND ambito='PM' AND entidade='00100')Y ON X.INSTRMNT_ID=Y.INSTRMNT_ID_SIMUL
A16: =+B16&F16 -> INSTRUMENTTYP_INSTRMNT | B16: INSTRUMENT | C16: Coerência | D16: =+UPPER('0. Instruções'!$D$35&"."&VLOOKUP(B16,'0. Instruções'!$C$27:$D$32,2,FALSE)) -> CD_LOAN_TAPES_BCE.LT002_INSTRUMENT | E16: =+UPPER('0. Instruções'!$D$36&"."&VLOOKUP(B16,'0. Instruções'!$C$27:$E$32,3,FALSE)) -> BU_LOANTAPE_WORK.LT002_INSTRUMENT | F16: TYP_INSTRMNT | I16: ="(SELECT "&VLOOKUP(B16,'0. Instruções'!$C$27:$G$32,4,FALSE)&", "&F16&" FROM "&D16&" WHERE "&'0. Instruções'!$D$42&")X" -> (SELECT instrmnt_id, TYP_INSTRMNT FROM CD_LOAN_TAPES_BCE.LT002_INSTRUMENT WHERE ref_date='${ref_date}' AND nome_perimetro='Individual Local' AND segmento='ESTR' AND ambito='SRB_MBDT' AND entidade='00100')X | J16: ="(SELECT "&VLOOKUP(B16,'0. Instruções'!$C$27:$G$32,4,FALSE)&" AS "&VLOOKUP(B16,'0. Instruções'!$C$27:$G$32,4,FALSE)&"_SIMUL, "&F16&" AS "&F16&"_SIMUL FROM "&E16&" WHERE "&'0. Instruções'!$D$43&")Y" -> (SELECT instrmnt_id AS instrmnt_id_SIMUL, TYP_INSTRMNT AS TYP_INSTRMNT_SIMUL FROM BU_LOANTAPE_WORK.LT002_INSTRUMENT WHERE ref_date='${ref_date}' AND nome_perimetro='Individual Local' AND segmento='ESTR' AND ambito='PM' AND entidade='00100')Y | K16: =+UPPER("ON X."&VLOOKUP(B16,'0. Instruções'!$C$27:$G$32,4,FALSE)&"=Y."&VLOOKUP(B16,'0. Instruções'!$C$27:$G$32,4,FALSE)&"_SIMUL") -> ON X.INSTRMNT_ID=Y.INSTRMNT_ID_SIMUL | L16: =+IF(C16="Coerência", +IF(LEFT(G16,5)="FLOAT","SELECT '"&UPPER(B16)&"' AS TABELA, '"&UPPER(C16)&"' AS TIPOLOGIA_TESTE,'"&D16&"' AS TABELA_LT,'"&E16&"' AS TABELA_SIMUL,'"&F16&"' AS CAMPO, "&"'${ref_date}' AS REF_DATE, COUNT(*) AS NUM_REG, SUM(IF((ABS(COALESCE(CAST(X."&F16&" AS DECIMAL(18,6)),0)-COALESCE(CAST(Y."&F16&"_SIMUL AS DECIMAL(18,6)),0))>0.000001) OR (X."&F16&" IS NULL AND Y."&F16&"_SIMUL IS NOT NULL ) OR (X."&F16&" IS NOT NULL AND Y."&F16&"_SIMUL IS NULL),1,0)) AS NUM_REG_DIF,'"&MAX('ID1&5'!K:K)+1&"' AS ID_EXEC, CURRENT_TIMESTAMP() AS TIME_EXEC FROM "&I16&" INNER JOIN "&J16&" "&K16,"SELECT '"&UPPER(B16)&"' AS TABELA, '"&UPPER(C16)&"' AS TIPOLOGIA_TESTE,'"&D16&"' AS TABELA_LT,'"&E16&"' AS TABELA_SIMUL,'"&F16&"' AS CAMPO, "&"'${ref_date}' AS REF_DATE, COUNT(*) AS NUM_REG, SUM(IF(COALESCE(CAST(X."&F16&" AS STRING),'')<>COALESCE(CAST(Y."&F16&"_SIMUL AS STRING),'') OR (X."&F16&" IS NULL AND Y."&F16&"_SIMUL IS NOT NULL ) OR (X."&F16&" IS NOT NULL AND Y."&F16&"_SIMUL IS NULL),1,0)) AS NUM_REG_DIF,'"&MAX('ID1&5'!L:L)+1&"' AS ID_EXEC, CURRENT_TIMESTAMP() AS TIME_EXEC FROM "&I16&" INNER JOIN "&J16&" "&K16), IF(C16="Validade",+IF(G16="Code List","SELECT '"&UPPER(B16)&"' AS TABELA, '"&UPPER(C16)&"' AS TIPOLOGIA_TESTE,'"&D16&"' AS TABELA_LT,'N/A' AS TABELA_SIMUL,'"&F16&"' AS CAMPO, "&"'${ref_date}' AS REF_DATE, COUNT(*) AS NUM_REG, SUM(IF(TRIM(CAST(X."&F16&" AS STRING))='' OR TRIM(CAST(X."&F16&" AS STRING)) IS NULL OR CAST(X."&F16&" AS STRING) NOT "&H16&",1,0)) AS NUM_REG_DIF,'"&MAX('ID1&5'!K:K)+1&"' AS ID_EXEC, CURRENT_TIMESTAMP() AS TIME_EXEC FROM "&I16,"SELECT '"&UPPER(B16)&"' AS TABELA, '"&UPPER(C16)&"' AS TIPOLOGIA_TESTE,'"&D16&"' AS TABELA_LT,'N/A' AS TABELA_SIMUL,'"&F16&"' AS CAMPO, "&"'${ref_date}' AS REF_DATE, COUNT(*) AS NUM_REG, SUM(IF(TRIM(CAST(X."&F16&" AS STRING))='' OR TRIM(CAST(X."&F16&" AS STRING)) IS NULL,1,0)) AS NUM_REG_DIF,'"&MAX('ID1&5'!K:K)+1&"' AS ID_EXEC, CURRENT_TIMESTAMP() AS TIME_EXEC FROM "&I16), IF(C16="Caracteres Especiais",+"SELECT '"&UPPER(B16)&"' AS TABELA, '"&UPPER(C16)&"' AS TIPOLOGIA_TESTE,'"&D16&"' AS TABELA_LT,'N/A' AS TABELA_SIMUL,'"&F16&"' AS CAMPO, "&"'${ref_date}' AS REF_DATE, COUNT(*) AS NUM_REG, SUM(IF(REGEXP_REPLACE(TRIM(CAST(X."&F16&" AS STRING)),'[^a-zA-Z0-9_\\s]','') <>TRIM(CAST(X."&F16&" AS STRING)),1,0)) AS NUM_REG_DIF,'"&MAX('ID1&5'!K:K)+1&"' AS ID_EXEC, CURRENT_TIMESTAMP() AS TIME_EXEC FROM "&I16, IF(C16="Missings",+"SELECT '"&UPPER(B16)&"' AS TABELA, '"&UPPER(C16)&"' AS TIPOLOGIA_TESTE,'"&D16&"' AS TABELA_LT,'N/A' AS TABELA_SIMUL,'"&F16&"' AS CAMPO, "&"'${ref_date}' AS REF_DATE, COUNT(*) AS NUM_REG, SUM(IF(TRIM(CAST(X."&F16&" AS STRING)) IN ('0000-00-00','0001-01-01','9999-12-31','MISS','00000','99999999999','99999999999.00','99999999999.000000'),1,0)) AS NUM_REG_DIF,'"&MAX('ID1&5'!K:K)+1&"' AS ID_EXEC, CURRENT_TIMESTAMP() AS TIME_EXEC FROM "&I16, IF(C16="Not applicable",+"SELECT '"&UPPER(B16)&"' AS TABELA, '"&UPPER(C16)&"' AS TIPOLOGIA_TESTE,'"&D16&"' AS TABELA_LT,'N/A' AS TABELA_SIMUL,'"&F16&"' AS CAMPO, "&"'${ref_date}' AS REF_DATE, COUNT(*) AS NUM_REG, SUM(IF(TRIM(CAST(X."&F16&" AS STRING)) IN ('N/A','11111111111','11111111111.00','11111111111.000000','1111-11-11'),1,0)) AS NUM_REG_DIF,'"&MAX('ID1&5'!K:K)+1&"' AS ID_EXEC, CURRENT_TIMESTAMP() AS TIME_EXEC FROM "&I16, IF(C16="Valores extremos",+"SELECT '"&UPPER(B16)&"' AS TABELA, '"&UPPER(C16)&"' AS TIPOLOGIA_TESTE,'"&D16&"' AS TABELA_LT,'N/A' AS TABELA_SIMUL,'"&F16&"' AS CAMPO, "&"'${ref_date}' AS REF_DATE, CAST(MIN("&F16&") AS STRING) AS VALOR_MIN, CAST(MAX("&F16&") AS STRING) AS VALOR_MAX,'"&MAX('ID1&5'!K:K)+1&"' AS ID_EXEC, CURRENT_TIMESTAMP() AS TIME_EXEC FROM "&MID(I16,1,LEN(I16)-2)&" AND CAST("&F16&" AS STRING) NOT IN ('0000-00-00','0001-01-01','9999-12-31','MISS','00000','99999999999','99999999999.00','99999999999.000000','N/A','11111111111','11111111111.00','11111111111.000000','1111-11-11'))X")))))) -> SELECT 'INSTRUMENT' AS TABELA, 'COERÊNCIA' AS TIPOLOGIA_TESTE,'CD_LOAN_TAPES_BCE.LT002_INSTRUMENT' AS TABELA_LT,'BU_LOANTAPE_WORK.LT002_INSTRUMENT' AS TABELA_SIMUL,'TYP_INSTRMNT' AS CAMPO, '${ref_date}' AS REF_DATE, COUNT(*) AS NUM_REG, SUM(IF(COALESCE(CAST(X.TYP_INSTRMNT AS STRING),'')<>COALESCE(CAST(Y.TYP_INSTRMNT_SIMUL AS STRING),'') OR (X.TYP_INSTRMNT IS NULL AND Y.TYP_INSTRMNT_SIMUL IS NOT NULL ) OR (X.TYP_INSTRMNT IS NOT NULL AND Y.TYP_INSTRMNT_SIMUL IS NULL),1,0)) AS NUM_REG_DIF,'1' AS ID_EXEC, CURRENT_TIMESTAMP() AS TIME_EXEC FROM (SELECT instrmnt_id, TYP_INSTRMNT FROM CD_LOAN_TAPES_BCE.LT002_INSTRUMENT WHERE ref_date='${ref_date}' AND nome_perimetro='Individual Local' AND segmento='ESTR' AND ambito='SRB_MBDT' AND entidade='00100')X INNER JOIN (SELECT instrmnt_id AS instrmnt_id_SIMUL, TYP_INSTRMNT AS TYP_INSTRMNT_SIMUL FROM BU_LOANTAPE_WORK.LT002_INSTRUMENT WHERE ref_date='${ref_date}' AND nome_perimetro='Individual Local' AND segmento='ESTR' AND ambito='PM' AND entidade='00100')Y ON X.INSTRMNT_ID=Y.INSTRMNT_ID_SIMUL | M16: =+"UNION ALL "&L16 -> UNION ALL SELECT 'INSTRUMENT' AS TABELA, 'COERÊNCIA' AS TIPOLOGIA_TESTE,'CD_LOAN_TAPES_BCE.LT002_INSTRUMENT' AS TABELA_LT,'BU_LOANTAPE_WORK.LT002_INSTRUMENT' AS TABELA_SIMUL,'TYP_INSTRMNT' AS CAMPO, '${ref_date}' AS REF_DATE, COUNT(*) AS NUM_REG, SUM(IF(COALESCE(CAST(X.TYP_INSTRMNT AS STRING),'')<>COALESCE(CAST(Y.TYP_INSTRMNT_SIMUL AS STRING),'') OR (X.TYP_INSTRMNT IS NULL AND Y.TYP_INSTRMNT_SIMUL IS NOT NULL ) OR (X.TYP_INSTRMNT IS NOT NULL AND Y.TYP_INSTRMNT_SIMUL IS NULL),1,0)) AS NUM_REG_DIF,'1' AS ID_EXEC, CURRENT_TIMESTAMP() AS TIME_EXEC FROM (SELECT instrmnt_id, TYP_INSTRMNT FROM CD_LOAN_TAPES_BCE.LT002_INSTRUMENT WHERE ref_date='${ref_date}' AND nome_perimetro='Individual Local' AND segmento='ESTR' AND ambito='SRB_MBDT' AND entidade='00100')X INNER JOIN (SELECT instrmnt_id AS instrmnt_id_SIMUL, TYP_INSTRMNT AS TYP_INSTRMNT_SIMUL FROM BU_LOANTAPE_WORK.LT002_INSTRUMENT WHERE ref_date='${ref_date}' AND nome_perimetro='Individual Local' AND segmento='ESTR' AND ambito='PM' AND entidade='00100')Y ON X.INSTRMNT_ID=Y.INSTRMNT_ID_SIMUL
A17: =+B17&F17 -> INSTRUMENTDT_INCPTN | B17: INSTRUMENT | C17: Coerência | D17: =+UPPER('0. Instruções'!$D$35&"."&VLOOKUP(B17,'0. Instruções'!$C$27:$D$32,2,FALSE)) -> CD_LOAN_TAPES_BCE.LT002_INSTRUMENT | E17: =+UPPER('0. Instruções'!$D$36&"."&VLOOKUP(B17,'0. Instruções'!$C$27:$E$32,3,FALSE)) -> BU_LOANTAPE_WORK.LT002_INSTRUMENT | F17: DT_INCPTN | I17: ="(SELECT "&VLOOKUP(B17,'0. Instruções'!$C$27:$G$32,4,FALSE)&", "&F17&" FROM "&D17&" WHERE "&'0. Instruções'!$D$42&")X" -> (SELECT instrmnt_id, DT_INCPTN FROM CD_LOAN_TAPES_BCE.LT002_INSTRUMENT WHERE ref_date='${ref_date}' AND nome_perimetro='Individual Local' AND segmento='ESTR' AND ambito='SRB_MBDT' AND entidade='00100')X | J17: ="(SELECT "&VLOOKUP(B17,'0. Instruções'!$C$27:$G$32,4,FALSE)&" AS "&VLOOKUP(B17,'0. Instruções'!$C$27:$G$32,4,FALSE)&"_SIMUL, "&F17&" AS "&F17&"_SIMUL FROM "&E17&" WHERE "&'0. Instruções'!$D$43&")Y" -> (SELECT instrmnt_id AS instrmnt_id_SIMUL, DT_INCPTN AS DT_INCPTN_SIMUL FROM BU_LOANTAPE_WORK.LT002_INSTRUMENT WHERE ref_date='${ref_date}' AND nome_perimetro='Individual Local' AND segmento='ESTR' AND ambito='PM' AND entidade='00100')Y | K17: =+UPPER("ON X."&VLOOKUP(B17,'0. Instruções'!$C$27:$G$32,4,FALSE)&"=Y."&VLOOKUP(B17,'0. Instruções'!$C$27:$G$32,4,FALSE)&"_SIMUL") -> ON X.INSTRMNT_ID=Y.INSTRMNT_ID_SIMUL | L17: =+IF(C17="Coerência", +IF(LEFT(G17,5)="FLOAT","SELECT '"&UPPER(B17)&"' AS TABELA, '"&UPPER(C17)&"' AS TIPOLOGIA_TESTE,'"&D17&"' AS TABELA_LT,'"&E17&"' AS TABELA_SIMUL,'"&F17&"' AS CAMPO, "&"'${ref_date}' AS REF_DATE, COUNT(*) AS NUM_REG, SUM(IF((ABS(COALESCE(CAST(X."&F17&" AS DECIMAL(18,6)),0)-COALESCE(CAST(Y."&F17&"_SIMUL AS DECIMAL(18,6)),0))>0.000001) OR (X."&F17&" IS NULL AND Y."&F17&"_SIMUL IS NOT NULL ) OR (X."&F17&" IS NOT NULL AND Y."&F17&"_SIMUL IS NULL),1,0)) AS NUM_REG_DIF,'"&MAX('ID1&5'!K:K)+1&"' AS ID_EXEC, CURRENT_TIMESTAMP() AS TIME_EXEC FROM "&I17&" INNER JOIN "&J17&" "&K17,"SELECT '"&UPPER(B17)&"' AS TABELA, '"&UPPER(C17)&"' AS TIPOLOGIA_TESTE,'"&D17&"' AS TABELA_LT,'"&E17&"' AS TABELA_SIMUL,'"&F17&"' AS CAMPO, "&"'${ref_date}' AS REF_DATE, COUNT(*) AS NUM_REG, SUM(IF(COALESCE(CAST(X."&F17&" AS STRING),'')<>COALESCE(CAST(Y."&F17&"_SIMUL AS STRING),'') OR (X."&F17&" IS NULL AND Y."&F17&"_SIMUL IS NOT NULL ) OR (X."&F17&" IS NOT NULL AND Y."&F17&"_SIMUL IS NULL),1,0)) AS NUM_REG_DIF,'"&MAX('ID1&5'!L:L)+1&"' AS ID_EXEC, CURRENT_TIMESTAMP() AS TIME_EXEC FROM "&I17&" INNER JOIN "&J17&" "&K17), IF(C17="Validade",+IF(G17="Code List","SELECT '"&UPPER(B17)&"' AS TABELA, '"&UPPER(C17)&"' AS TIPOLOGIA_TESTE,'"&D17&"' AS TABELA_LT,'N/A' AS TABELA_SIMUL,'"&F17&"' AS CAMPO, "&"'${ref_date}' AS REF_DATE, COUNT(*) AS NUM_REG, SUM(IF(TRIM(CAST(X."&F17&" AS STRING))='' OR TRIM(CAST(X."&F17&" AS STRING)) IS NULL OR CAST(X."&F17&" AS STRING) NOT "&H17&",1,0)) AS NUM_REG_DIF,'"&MAX('ID1&5'!K:K)+1&"' AS ID_EXEC, CURRENT_TIMESTAMP() AS TIME_EXEC FROM "&I17,"SELECT '"&UPPER(B17)&"' AS TABELA, '"&UPPER(C17)&"' AS TIPOLOGIA_TESTE,'"&D17&"' AS TABELA_LT,'N/A' AS TABELA_SIMUL,'"&F17&"' AS CAMPO, "&"'${ref_date}' AS REF_DATE, COUNT(*) AS NUM_REG, SUM(IF(TRIM(CAST(X."&F17&" AS STRING))='' OR TRIM(CAST(X."&F17&" AS STRING)) IS NULL,1,0)) AS NUM_REG_DIF,'"&MAX('ID1&5'!K:K)+1&"' AS ID_EXEC, CURRENT_TIMESTAMP() AS TIME_EXEC FROM "&I17), IF(C17="Caracteres Especiais",+"SELECT '"&UPPER(B17)&"' AS TABELA, '"&UPPER(C17)&"' AS TIPOLOGIA_TESTE,'"&D17&"' AS TABELA_LT,'N/A' AS TABELA_SIMUL,'"&F17&"' AS CAMPO, "&"'${ref_date}' AS REF_DATE, COUNT(*) AS NUM_REG, SUM(IF(REGEXP_REPLACE(TRIM(CAST(X."&F17&" AS STRING)),'[^a-zA-Z0-9_\\s]','') <>TRIM(CAST(X."&F17&" AS STRING)),1,0)) AS NUM_REG_DIF,'"&MAX('ID1&5'!K:K)+1&"' AS ID_EXEC, CURRENT_TIMESTAMP() AS TIME_EXEC FROM "&I17, IF(C17="Missings",+"SELECT '"&UPPER(B17)&"' AS TABELA, '"&UPPER(C17)&"' AS TIPOLOGIA_TESTE,'"&D17&"' AS TABELA_LT,'N/A' AS TABELA_SIMUL,'"&F17&"' AS CAMPO, "&"'${ref_date}' AS REF_DATE, COUNT(*) AS NUM_REG, SUM(IF(TRIM(CAST(X."&F17&" AS STRING)) IN ('0000-00-00','0001-01-01','9999-12-31','MISS','00000','99999999999','99999999999.00','99999999999.000000'),1,0)) AS NUM_REG_DIF,'"&MAX('ID1&5'!K:K)+1&"' AS ID_EXEC, CURRENT_TIMESTAMP() AS TIME_EXEC FROM "&I17, IF(C17="Not applicable",+"SELECT '"&UPPER(B17)&"' AS TABELA, '"&UPPER(C17)&"' AS TIPOLOGIA_TESTE,'"&D17&"' AS TABELA_LT,'N/A' AS TABELA_SIMUL,'"&F17&"' AS CAMPO, "&"'${ref_date}' AS REF_DATE, COUNT(*) AS NUM_REG, SUM(IF(TRIM(CAST(X."&F17&" AS STRING)) IN ('N/A','11111111111','11111111111.00','11111111111.000000','1111-11-11'),1,0)) AS NUM_REG_DIF,'"&MAX('ID1&5'!K:K)+1&"' AS ID_EXEC, CURRENT_TIMESTAMP() AS TIME_EXEC FROM "&I17, IF(C17="Valores extremos",+"SELECT '"&UPPER(B17)&"' AS TABELA, '"&UPPER(C17)&"' AS TIPOLOGIA_TESTE,'"&D17&"' AS TABELA_LT,'N/A' AS TABELA_SIMUL,'"&F17&"' AS CAMPO, "&"'${ref_date}' AS REF_DATE, CAST(MIN("&F17&") AS STRING) AS VALOR_MIN, CAST(MAX("&F17&") AS STRING) AS VALOR_MAX,'"&MAX('ID1&5'!K:K)+1&"' AS ID_EXEC, CURRENT_TIMESTAMP() AS TIME_EXEC FROM "&MID(I17,1,LEN(I17)-2)&" AND CAST("&F17&" AS STRING) NOT IN ('0000-00-00','0001-01-01','9999-12-31','MISS','00000','99999999999','99999999999.00','99999999999.000000','N/A','11111111111','11111111111.00','11111111111.000000','1111-11-11'))X")))))) -> SELECT 'INSTRUMENT' AS TABELA, 'COERÊNCIA' AS TIPOLOGIA_TESTE,'CD_LOAN_TAPES_BCE.LT002_INSTRUMENT' AS TABELA_LT,'BU_LOANTAPE_WORK.LT002_INSTRUMENT' AS TABELA_SIMUL,'DT_INCPTN' AS CAMPO, '${ref_date}' AS REF_DATE, COUNT(*) AS NUM_REG, SUM(IF(COALESCE(CAST(X.DT_INCPTN AS STRING),'')<>COALESCE(CAST(Y.DT_INCPTN_SIMUL AS STRING),'') OR (X.DT_INCPTN IS NULL AND Y.DT_INCPTN_SIMUL IS NOT NULL ) OR (X.DT_INCPTN IS NOT NULL AND Y.DT_INCPTN_SIMUL IS NULL),1,0)) AS NUM_REG_DIF,'1' AS ID_EXEC, CURRENT_TIMESTAMP() AS TIME_EXEC FROM (SELECT instrmnt_id, DT_INCPTN FROM CD_LOAN_TAPES_BCE.LT002_INSTRUMENT WHERE ref_date='${ref_date}' AND nome_perimetro='Individual Local' AND segmento='ESTR' AND ambito='SRB_MBDT' AND entidade='00100')X INNER JOIN (SELECT instrmnt_id AS instrmnt_id_SIMUL, DT_INCPTN AS DT_INCPTN_SIMUL FROM BU_LOANTAPE_WORK.LT002_INSTRUMENT WHERE ref_date='${ref_date}' AND nome_perimetro='Individual Local' AND segmento='ESTR' AND ambito='PM' AND entidade='00100')Y ON X.INSTRMNT_ID=Y.INSTRMNT_ID_SIMUL | M17: =+"UNION ALL "&L17 -> UNION ALL SELECT 'INSTRUMENT' AS TABELA, 'COERÊNCIA' AS TIPOLOGIA_TESTE,'CD_LOAN_TAPES_BCE.LT002_INSTRUMENT' AS TABELA_LT,'BU_LOANTAPE_WORK.LT002_INSTRUMENT' AS TABELA_SIMUL,'DT_INCPTN' AS CAMPO, '${ref_date}' AS REF_DATE, COUNT(*) AS NUM_REG, SUM(IF(COALESCE(CAST(X.DT_INCPTN AS STRING),'')<>COALESCE(CAST(Y.DT_INCPTN_SIMUL AS STRING),'') OR (X.DT_INCPTN IS NULL AND Y.DT_INCPTN_SIMUL IS NOT NULL ) OR (X.DT_INCPTN IS NOT NULL AND Y.DT_INCPTN_SIMUL IS NULL),1,0)) AS NUM_REG_DIF,'1' AS ID_EXEC, CURRENT_TIMESTAMP() AS TIME_EXEC FROM (SELECT instrmnt_id, DT_INCPTN FROM CD_LOAN_TAPES_BCE.LT002_INSTRUMENT WHERE ref_date='${ref_date}' AND nome_perimetro='Individual Local' AND segmento='ESTR' AND ambito='SRB_MBDT' AND entidade='00100')X INNER JOIN (SELECT instrmnt_id AS instrmnt_id_SIMUL, DT_INCPTN AS DT_INCPTN_SIMUL FROM BU_LOANTAPE_WORK.LT002_INSTRUMENT WHERE ref_date='${ref_date}' AND nome_perimetro='Individual Local' AND segmento='ESTR' AND ambito='PM' AND entidade='00100')Y ON X.INSTRMNT_ID=Y.INSTRMNT_ID_SIMUL
A18: =+B18&F18 -> INSTRUMENTDT_LGL_FNL_MTRTY | B18: INSTRUMENT | C18: Coerência | D18: =+UPPER('0. Instruções'!$D$35&"."&VLOOKUP(B18,'0. Instruções'!$C$27:$D$32,2,FALSE)) -> CD_LOAN_TAPES_BCE.LT002_INSTRUMENT | E18: =+UPPER('0. Instruções'!$D$36&"."&VLOOKUP(B18,'0. Instruções'!$C$27:$E$32,3,FALSE)) -> BU_LOANTAPE_WORK.LT002_INSTRUMENT | F18: DT_LGL_FNL_MTRTY | I18: ="(SELECT "&VLOOKUP(B18,'0. Instruções'!$C$27:$G$32,4,FALSE)&", "&F18&" FROM "&D18&" WHERE "&'0. Instruções'!$D$42&")X" -> (SELECT instrmnt_id, DT_LGL_FNL_MTRTY FROM CD_LOAN_TAPES_BCE.LT002_INSTRUMENT WHERE ref_date='${ref_date}' AND nome_perimetro='Individual Local' AND segmento='ESTR' AND ambito='SRB_MBDT' AND entidade='00100')X | J18: ="(SELECT "&VLOOKUP(B18,'0. Instruções'!$C$27:$G$32,4,FALSE)&" AS "&VLOOKUP(B18,'0. Instruções'!$C$27:$G$32,4,FALSE)&"_SIMUL, "&F18&" AS "&F18&"_SIMUL FROM "&E18&" WHERE "&'0. Instruções'!$D$43&")Y" -> (SELECT instrmnt_id AS instrmnt_id_SIMUL, DT_LGL_FNL_MTRTY AS DT_LGL_FNL_MTRTY_SIMUL FROM BU_LOANTAPE_WORK.LT002_INSTRUMENT WHERE ref_date='${ref_date}' AND nome_perimetro='Individual Local' AND segmento='ESTR' AND ambito='PM' AND entidade='00100')Y | K18: =+UPPER("ON X."&VLOOKUP(B18,'0. Instruções'!$C$27:$G$32,4,FALSE)&"=Y."&VLOOKUP(B18,'0. Instruções'!$C$27:$G$32,4,FALSE)&"_SIMUL") -> ON X.INSTRMNT_ID=Y.INSTRMNT_ID_SIMUL | L18: =+IF(C18="Coerência", +IF(LEFT(G18,5)="FLOAT","SELECT '"&UPPER(B18)&"' AS TABELA, '"&UPPER(C18)&"' AS TIPOLOGIA_TESTE,'"&D18&"' AS TABELA_LT,'"&E18&"' AS TABELA_SIMUL,'"&F18&"' AS CAMPO, "&"'${ref_date}' AS REF_DATE, COUNT(*) AS NUM_REG, SUM(IF((ABS(COALESCE(CAST(X."&F18&" AS DECIMAL(18,6)),0)-COALESCE(CAST(Y."&F18&"_SIMUL AS DECIMAL(18,6)),0))>0.000001) OR (X."&F18&" IS NULL AND Y."&F18&"_SIMUL IS NOT NULL ) OR (X."&F18&" IS NOT NULL AND Y."&F18&"_SIMUL IS NULL),1,0)) AS NUM_REG_DIF,'"&MAX('ID1&5'!K:K)+1&"' AS ID_EXEC, CURRENT_TIMESTAMP() AS TIME_EXEC FROM "&I18&" INNER JOIN "&J18&" "&K18,"SELECT '"&UPPER(B18)&"' AS TABELA, '"&UPPER(C18)&"' AS TIPOLOGIA_TESTE,'"&D18&"' AS TABELA_LT,'"&E18&"' AS TABELA_SIMUL,'"&F18&"' AS CAMPO, "&"'${ref_date}' AS REF_DATE, COUNT(*) AS NUM_REG, SUM(IF(COALESCE(CAST(X."&F18&" AS STRING),'')<>COALESCE(CAST(Y."&F18&"_SIMUL AS STRING),'') OR (X."&F18&" IS NULL AND Y."&F18&"_SIMUL IS NOT NULL ) OR (X."&F18&" IS NOT NULL AND Y."&F18&"_SIMUL IS NULL),1,0)) AS NUM_REG_DIF,'"&MAX('ID1&5'!L:L)+1&"' AS ID_EXEC, CURRENT_TIMESTAMP() AS TIME_EXEC FROM "&I18&" INNER JOIN "&J18&" "&K18), IF(C18="Validade",+IF(G18="Code List","SELECT '"&UPPER(B18)&"' AS TABELA, '"&UPPER(C18)&"' AS TIPOLOGIA_TESTE,'"&D18&"' AS TABELA_LT,'N/A' AS TABELA_SIMUL,'"&F18&"' AS CAMPO, "&"'${ref_date}' AS REF_DATE, COUNT(*) AS NUM_REG, SUM(IF(TRIM(CAST(X."&F18&" AS STRING))='' OR TRIM(CAST(X."&F18&" AS STRING)) IS NULL OR CAST(X."&F18&" AS STRING) NOT "&H18&",1,0)) AS NUM_REG_DIF,'"&MAX('ID1&5'!K:K)+1&"' AS ID_EXEC, CURRENT_TIMESTAMP() AS TIME_EXEC FROM "&I18,"SELECT '"&UPPER(B18)&"' AS TABELA, '"&UPPER(C18)&"' AS TIPOLOGIA_TESTE,'"&D18&"' AS TABELA_LT,'N/A' AS TABELA_SIMUL,'"&F18&"' AS CAMPO, "&"'${ref_date}' AS REF_DATE, COUNT(*) AS NUM_REG, SUM(IF(TRIM(CAST(X."&F18&" AS STRING))='' OR TRIM(CAST(X."&F18&" AS STRING)) IS NULL,1,0)) AS NUM_REG_DIF,'"&MAX('ID1&5'!K:K)+1&"' AS ID_EXEC, CURRENT_TIMESTAMP() AS TIME_EXEC FROM "&I18), IF(C18="Caracteres Especiais",+"SELECT '"&UPPER(B18)&"' AS TABELA, '"&UPPER(C18)&"' AS TIPOLOGIA_TESTE,'"&D18&"' AS TABELA_LT,'N/A' AS TABELA_SIMUL,'"&F18&"' AS CAMPO, "&"'${ref_date}' AS REF_DATE, COUNT(*) AS NUM_REG, SUM(IF(REGEXP_REPLACE(TRIM(CAST(X."&F18&" AS STRING)),'[^a-zA-Z0-9_\\s]','') <>TRIM(CAST(X."&F18&" AS STRING)),1,0)) AS NUM_REG_DIF,'"&MAX('ID1&5'!K:K)+1&"' AS ID_EXEC, CURRENT_TIMESTAMP() AS TIME_EXEC FROM "&I18, IF(C18="Missings",+"SELECT '"&UPPER(B18)&"' AS TABELA, '"&UPPER(C18)&"' AS TIPOLOGIA_TESTE,'"&D18&"' AS TABELA_LT,'N/A' AS TABELA_SIMUL,'"&F18&"' AS CAMPO, "&"'${ref_date}' AS REF_DATE, COUNT(*) AS NUM_REG, SUM(IF(TRIM(CAST(X."&F18&" AS STRING)) IN ('0000-00-00','0001-01-01','9999-12-31','MISS','00000','99999999999','99999999999.00','99999999999.000000'),1,0)) AS NUM_REG_DIF,'"&MAX('ID1&5'!K:K)+1&"' AS ID_EXEC, CURRENT_TIMESTAMP() AS TIME_EXEC FROM "&I18, IF(C18="Not applicable",+"SELECT '"&UPPER(B18)&"' AS TABELA, '"&UPPER(C18)&"' AS TIPOLOGIA_TESTE,'"&D18&"' AS TABELA_LT,'N/A' AS TABELA_SIMUL,'"&F18&"' AS CAMPO, "&"'${ref_date}' AS REF_DATE, COUNT(*) AS NUM_REG, SUM(IF(TRIM(CAST(X."&F18&" AS STRING)) IN ('N/A','11111111111','11111111111.00','11111111111.000000','1111-11-11'),1,0)) AS NUM_REG_DIF,'"&MAX('ID1&5'!K:K)+1&"' AS ID_EXEC, CURRENT_TIMESTAMP() AS TIME_EXEC FROM "&I18, IF(C18="Valores extremos",+"SELECT '"&UPPER(B18)&"' AS TABELA, '"&UPPER(C18)&"' AS TIPOLOGIA_TESTE,'"&D18&"' AS TABELA_LT,'N/A' AS TABELA_SIMUL,'"&F18&"' AS CAMPO, "&"'${ref_date}' AS REF_DATE, CAST(MIN("&F18&") AS STRING) AS VALOR_MIN, CAST(MAX("&F18&") AS STRING) AS VALOR_MAX,'"&MAX('ID1&5'!K:K)+1&"' AS ID_EXEC, CURRENT_TIMESTAMP() AS TIME_EXEC FROM "&MID(I18,1,LEN(I18)-2)&" AND CAST("&F18&" AS STRING) NOT IN ('0000-00-00','0001-01-01','9999-12-31','MISS','00000','99999999999','99999999999.00','99999999999.000000','N/A','11111111111','11111111111.00','11111111111.000000','1111-11-11'))X")))))) -> SELECT 'INSTRUMENT' AS TABELA, 'COERÊNCIA' AS TIPOLOGIA_TESTE,'CD_LOAN_TAPES_BCE.LT002_INSTRUMENT' AS TABELA_LT,'BU_LOANTAPE_WORK.LT002_INSTRUMENT' AS TABELA_SIMUL,'DT_LGL_FNL_MTRTY' AS CAMPO, '${ref_date}' AS REF_DATE, COUNT(*) AS NUM_REG, SUM(IF(COALESCE(CAST(X.DT_LGL_FNL_MTRTY AS STRING),'')<>COALESCE(CAST(Y.DT_LGL_FNL_MTRTY_SIMUL AS STRING),'') OR (X.DT_LGL_FNL_MTRTY IS NULL AND Y.DT_LGL_FNL_MTRTY_SIMUL IS NOT NULL ) OR (X.DT_LGL_FNL_MTRTY IS NOT NULL AND Y.DT_LGL_FNL_MTRTY_SIMUL IS NULL),1,0)) AS NUM_REG_DIF,'1' AS ID_EXEC, CURRENT_TIMESTAMP() AS TIME_EXEC FROM (SELECT instrmnt_id, DT_LGL_FNL_MTRTY FROM CD_LOAN_TAPES_BCE.LT002_INSTRUMENT WHERE ref_date='${ref_date}' AND nome_perimetro='Individual Local' AND segmento='ESTR' AND ambito='SRB_MBDT' AND entidade='00100')X INNER JOIN (SELECT instrmnt_id AS instrmnt_id_SIMUL, DT_LGL_FNL_MTRTY AS DT_LGL_FNL_MTRTY_SIMUL FROM BU_LOANTAPE_WORK.LT002_INSTRUMENT WHERE ref_date='${ref_date}' AND nome_perimetro='Individual Local' AND segmento='ESTR' AND ambito='PM' AND entidade='00100')Y ON X.INSTRMNT_ID=Y.INSTRMNT_ID_SIMUL | M18: =+"UNION ALL "&L18 -> UNION ALL SELECT 'INSTRUMENT' AS TABELA, 'COERÊNCIA' AS TIPOLOGIA_TESTE,'CD_LOAN_TAPES_BCE.LT002_INSTRUMENT' AS TABELA_LT,'BU_LOANTAPE_WORK.LT002_INSTRUMENT' AS TABELA_SIMUL,'DT_LGL_FNL_MTRTY' AS CAMPO, '${ref_date}' AS REF_DATE, COUNT(*) AS NUM_REG, SUM(IF(COALESCE(CAST(X.DT_LGL_FNL_MTRTY AS STRING),'')<>COALESCE(CAST(Y.DT_LGL_FNL_MTRTY_SIMUL AS STRING),'') OR (X.DT_LGL_FNL_MTRTY IS NULL AND Y.DT_LGL_FNL_MTRTY_SIMUL IS NOT NULL ) OR (X.DT_LGL_FNL_MTRTY IS NOT NULL AND Y.DT_LGL_FNL_MTRTY_SIMUL IS NULL),1,0)) AS NUM_REG_DIF,'1' AS ID_EXEC, CURRENT_TIMESTAMP() AS TIME_EXEC FROM (SELECT instrmnt_id, DT_LGL_FNL_MTRTY FROM CD_LOAN_TAPES_BCE.LT002_INSTRUMENT WHERE ref_date='${ref_date}' AND nome_perimetro='Individual Local' AND segmento='ESTR' AND ambito='SRB_MBDT' AND entidade='00100')X INNER JOIN (SELECT instrmnt_id AS instrmnt_id_SIMUL, DT_LGL_FNL_MTRTY AS DT_LGL_FNL_MTRTY_SIMUL FROM BU_LOANTAPE_WORK.LT002_INSTRUMENT WHERE ref_date='${ref_date}' AND nome_perimetro='Individual Local' AND segmento='ESTR' AND ambito='PM' AND entidade='00100')Y ON X.INSTRMNT_ID=Y.INSTRMNT_ID_SIMUL
A19: =+B19&F19 -> INSTRUMENTGOVERNING_LAW | B19: INSTRUMENT | C19: Coerência | D19: =+UPPER('0. Instruções'!$D$35&"."&VLOOKUP(B19,'0. Instruções'!$C$27:$D$32,2,FALSE)) -> CD_LOAN_TAPES_BCE.LT002_INSTRUMENT | E19: =+UPPER('0. Instruções'!$D$36&"."&VLOOKUP(B19,'0. Instruções'!$C$27:$E$32,3,FALSE)) -> BU_LOANTAPE_WORK.LT002_INSTRUMENT | F19: GOVERNING_LAW | I19: ="(SELECT "&VLOOKUP(B19,'0. Instruções'!$C$27:$G$32,4,FALSE)&", "&F19&" FROM "&D19&" WHERE "&'0. Instruções'!$D$42&")X" -> (SELECT instrmnt_id, GOVERNING_LAW FROM CD_LOAN_TAPES_BCE.LT002_INSTRUMENT WHERE ref_date='${ref_date}' AND nome_perimetro='Individual Local' AND segmento='ESTR' AND ambito='SRB_MBDT' AND entidade='00100')X | J19: ="(SELECT "&VLOOKUP(B19,'0. Instruções'!$C$27:$G$32,4,FALSE)&" AS "&VLOOKUP(B19,'0. Instruções'!$C$27:$G$32,4,FALSE)&"_SIMUL, "&F19&" AS "&F19&"_SIMUL FROM "&E19&" WHERE "&'0. Instruções'!$D$43&")Y" -> (SELECT instrmnt_id AS instrmnt_id_SIMUL, GOVERNING_LAW AS GOVERNING_LAW_SIMUL FROM BU_LOANTAPE_WORK.LT002_INSTRUMENT WHERE ref_date='${ref_date}' AND nome_perimetro='Individual Local' AND segmento='ESTR' AND ambito='PM' AND entidade='00100')Y | K19: =+UPPER("ON X."&VLOOKUP(B19,'0. Instruções'!$C$27:$G$32,4,FALSE)&"=Y."&VLOOKUP(B19,'0. Instruções'!$C$27:$G$32,4,FALSE)&"_SIMUL") -> ON X.INSTRMNT_ID=Y.INSTRMNT_ID_SIMUL | L19: =+IF(C19="Coerência", +IF(LEFT(G19,5)="FLOAT","SELECT '"&UPPER(B19)&"' AS TABELA, '"&UPPER(C19)&"' AS TIPOLOGIA_TESTE,'"&D19&"' AS TABELA_LT,'"&E19&"' AS TABELA_SIMUL,'"&F19&"' AS CAMPO, "&"'${ref_date}' AS REF_DATE, COUNT(*) AS NUM_REG, SUM(IF((ABS(COALESCE(CAST(X."&F19&" AS DECIMAL(18,6)),0)-COALESCE(CAST(Y."&F19&"_SIMUL AS DECIMAL(18,6)),0))>0.000001) OR (X."&F19&" IS NULL AND Y."&F19&"_SIMUL IS NOT NULL ) OR (X."&F19&" IS NOT NULL AND Y."&F19&"_SIMUL IS NULL),1,0)) AS NUM_REG_DIF,'"&MAX('ID1&5'!K:K)+1&"' AS ID_EXEC, CURRENT_TIMESTAMP() AS TIME_EXEC FROM "&I19&" INNER JOIN "&J19&" "&K19,"SELECT '"&UPPER(B19)&"' AS TABELA, '"&UPPER(C19)&"' AS TIPOLOGIA_TESTE,'"&D19&"' AS TABELA_LT,'"&E19&"' AS TABELA_SIMUL,'"&F19&"' AS CAMPO, "&"'${ref_date}' AS REF_DATE, COUNT(*) AS NUM_REG, SUM(IF(COALESCE(CAST(X."&F19&" AS STRING),'')<>COALESCE(CAST(Y."&F19&"_SIMUL AS STRING),'') OR (X."&F19&" IS NULL AND Y."&F19&"_SIMUL IS NOT NULL ) OR (X."&F19&" IS NOT NULL AND Y."&F19&"_SIMUL IS NULL),1,0)) AS NUM_REG_DIF,'"&MAX('ID1&5'!L:L)+1&"' AS ID_EXEC, CURRENT_TIMESTAMP() AS TIME_EXEC FROM "&I19&" INNER JOIN "&J19&" "&K19), IF(C19="Validade",+IF(G19="Code List","SELECT '"&UPPER(B19)&"' AS TABELA, '"&UPPER(C19)&"' AS TIPOLOGIA_TESTE,'"&D19&"' AS TABELA_LT,'N/A' AS TABELA_SIMUL,'"&F19&"' AS CAMPO, "&"'${ref_date}' AS REF_DATE, COUNT(*) AS NUM_REG, SUM(IF(TRIM(CAST(X."&F19&" AS STRING))='' OR TRIM(CAST(X."&F19&" AS STRING)) IS NULL OR CAST(X."&F19&" AS STRING) NOT "&H19&",1,0)) AS NUM_REG_DIF,'"&MAX('ID1&5'!K:K)+1&"' AS ID_EXEC, CURRENT_TIMESTAMP() AS TIME_EXEC FROM "&I19,"SELECT '"&UPPER(B19)&"' AS TABELA, '"&UPPER(C19)&"' AS TIPOLOGIA_TESTE,'"&D19&"' AS TABELA_LT,'N/A' AS TABELA_SIMUL,'"&F19&"' AS CAMPO, "&"'${ref_date}' AS REF_DATE, COUNT(*) AS NUM_REG, SUM(IF(TRIM(CAST(X."&F19&" AS STRING))='' OR TRIM(CAST(X."&F19&" AS STRING)) IS NULL,1,0)) AS NUM_REG_DIF,'"&MAX('ID1&5'!K:K)+1&"' AS ID_EXEC, CURRENT_TIMESTAMP() AS TIME_EXEC FROM "&I19), IF(C19="Caracteres Especiais",+"SELECT '"&UPPER(B19)&"' AS TABELA, '"&UPPER(C19)&"' AS TIPOLOGIA_TESTE,'"&D19&"' AS TABELA_LT,'N/A' AS TABELA_SIMUL,'"&F19&"' AS CAMPO, "&"'${ref_date}' AS REF_DATE, COUNT(*) AS NUM_REG, SUM(IF(REGEXP_REPLACE(TRIM(CAST(X."&F19&" AS STRING)),'[^a-zA-Z0-9_\\s]','') <>TRIM(CAST(X."&F19&" AS STRING)),1,0)) AS NUM_REG_DIF,'"&MAX('ID1&5'!K:K)+1&"' AS ID_EXEC, CURRENT_TIMESTAMP() AS TIME_EXEC FROM "&I19, IF(C19="Missings",+"SELECT '"&UPPER(B19)&"' AS TABELA, '"&UPPER(C19)&"' AS TIPOLOGIA_TESTE,'"&D19&"' AS TABELA_LT,'N/A' AS TABELA_SIMUL,'"&F19&"' AS CAMPO, "&"'${ref_date}' AS REF_DATE, COUNT(*) AS NUM_REG, SUM(IF(TRIM(CAST(X."&F19&" AS STRING)) IN ('0000-00-00','0001-01-01','9999-12-31','MISS','00000','99999999999','99999999999.00','99999999999.000000'),1,0)) AS NUM_REG_DIF,'"&MAX('ID1&5'!K:K)+1&"' AS ID_EXEC, CURRENT_TIMESTAMP() AS TIME_EXEC FROM "&I19, IF(C19="Not applicable",+"SELECT '"&UPPER(B19)&"' AS TABELA, '"&UPPER(C19)&"' AS TIPOLOGIA_TESTE,'"&D19&"' AS TABELA_LT,'N/A' AS TABELA_SIMUL,'"&F19&"' AS CAMPO, "&"'${ref_date}' AS REF_DATE, COUNT(*) AS NUM_REG, SUM(IF(TRIM(CAST(X."&F19&" AS STRING)) IN ('N/A','11111111111','11111111111.00','11111111111.000000','1111-11-11'),1,0)) AS NUM_REG_DIF,'"&MAX('ID1&5'!K:K)+1&"' AS ID_EXEC, CURRENT_TIMESTAMP() AS TIME_EXEC FROM "&I19, IF(C19="Valores extremos",+"SELECT '"&UPPER(B19)&"' AS TABELA, '"&UPPER(C19)&"' AS TIPOLOGIA_TESTE,'"&D19&"' AS TABELA_LT,'N/A' AS TABELA_SIMUL,'"&F19&"' AS CAMPO, "&"'${ref_date}' AS REF_DATE, CAST(MIN("&F19&") AS STRING) AS VALOR_MIN, CAST(MAX("&F19&") AS STRING) AS VALOR_MAX,'"&MAX('ID1&5'!K:K)+1&"' AS ID_EXEC, CURRENT_TIMESTAMP() AS TIME_EXEC FROM "&MID(I19,1,LEN(I19)-2)&" AND CAST("&F19&" AS STRING) NOT IN ('0000-00-00','0001-01-01','9999-12-31','MISS','00000','99999999999','99999999999.00','99999999999.000000','N/A','11111111111','11111111111.00','11111111111.000000','1111-11-11'))X")))))) -> SELECT 'INSTRUMENT' AS TABELA, 'COERÊNCIA' AS TIPOLOGIA_TESTE,'CD_LOAN_TAPES_BCE.LT002_INSTRUMENT' AS TABELA_LT,'BU_LOANTAPE_WORK.LT002_INSTRUMENT' AS TABELA_SIMUL,'GOVERNING_LAW' AS CAMPO, '${ref_date}' AS REF_DATE, COUNT(*) AS NUM_REG, SUM(IF(COALESCE(CAST(X.GOVERNING_LAW AS STRING),'')<>COALESCE(CAST(Y.GOVERNING_LAW_SIMUL AS STRING),'') OR (X.GOVERNING_LAW IS NULL AND Y.GOVERNING_LAW_SIMUL IS NOT NULL ) OR (X.GOVERNING_LAW IS NOT NULL AND Y.GOVERNING_LAW_SIMUL IS NULL),1,0)) AS NUM_REG_DIF,'1' AS ID_EXEC, CURRENT_TIMESTAMP() AS TIME_EXEC FROM (SELECT instrmnt_id, GOVERNING_LAW FROM CD_LOAN_TAPES_BCE.LT002_INSTRUMENT WHERE ref_date='${ref_date}' AND nome_perimetro='Individual Local' AND segmento='ESTR' AND ambito='SRB_MBDT' AND entidade='00100')X INNER JOIN (SELECT instrmnt_id AS instrmnt_id_SIMUL, GOVERNING_LAW AS GOVERNING_LAW_SIMUL FROM BU_LOANTAPE_WORK.LT002_INSTRUMENT WHERE ref_date='${ref_date}' AND nome_perimetro='Individual Local' AND segmento='ESTR' AND ambito='PM' AND entidade='00100')Y ON X.INSTRMNT_ID=Y.INSTRMNT_ID_SIMUL | M19: =+"UNION ALL "&L19 -> UNION ALL SELECT 'INSTRUMENT' AS TABELA, 'COERÊNCIA' AS TIPOLOGIA_TESTE,'CD_LOAN_TAPES_BCE.LT002_INSTRUMENT' AS TABELA_LT,'BU_LOANTAPE_WORK.LT002_INSTRUMENT' AS TABELA_SIMUL,'GOVERNING_LAW' AS CAMPO, '${ref_date}' AS REF_DATE, COUNT(*) AS NUM_REG, SUM(IF(COALESCE(CAST(X.GOVERNING_LAW AS STRING),'')<>COALESCE(CAST(Y.GOVERNING_LAW_SIMUL AS STRING),'') OR (X.GOVERNING_LAW IS NULL AND Y.GOVERNING_LAW_SIMUL IS NOT NULL ) OR (X.GOVERNING_LAW IS NOT NULL AND Y.GOVERNING_LAW_SIMUL IS NULL),1,0)) AS NUM_REG_DIF,'1' AS ID_EXEC, CURRENT_TIMESTAMP() AS TIME_EXEC FROM (SELECT instrmnt_id, GOVERNING_LAW FROM CD_LOAN_TAPES_BCE.LT002_INSTRUMENT WHERE ref_date='${ref_date}' AND nome_perimetro='Individual Local' AND segmento='ESTR' AND ambito='SRB_MBDT' AND entidade='00100')X INNER JOIN (SELECT instrmnt_id AS instrmnt_id_SIMUL, GOVERNING_LAW AS GOVERNING_LAW_SIMUL FROM BU_LOANTAPE_WORK.LT002_INSTRUMENT WHERE ref_date='${ref_date}' AND nome_perimetro='Individual Local' AND segmento='ESTR' AND ambito='PM' AND entidade='00100')Y ON X.INSTRMNT_ID=Y.INSTRMNT_ID_SIMUL
A20: =+B20&F20 -> INSTRUMENTCRRYNG_AMNT_INSTRMNT | B20: INSTRUMENT | C20: Coerência | D20: =+UPPER('0. Instruções'!$D$35&"."&VLOOKUP(B20,'0. Instruções'!$C$27:$D$32,2,FALSE)) -> CD_LOAN_TAPES_BCE.LT002_INSTRUMENT | E20: =+UPPER('0. Instruções'!$D$36&"."&VLOOKUP(B20,'0. Instruções'!$C$27:$E$32,3,FALSE)) -> BU_LOANTAPE_WORK.LT002_INSTRUMENT | F20: CRRYNG_AMNT_INSTRMNT | I20: ="(SELECT "&VLOOKUP(B20,'0. Instruções'!$C$27:$G$32,4,FALSE)&", "&F20&" FROM "&D20&" WHERE "&'0. Instruções'!$D$42&")X" -> (SELECT instrmnt_id, CRRYNG_AMNT_INSTRMNT FROM CD_LOAN_TAPES_BCE.LT002_INSTRUMENT WHERE ref_date='${ref_date}' AND nome_perimetro='Individual Local' AND segmento='ESTR' AND ambito='SRB_MBDT' AND entidade='00100')X | J20: ="(SELECT "&VLOOKUP(B20,'0. Instruções'!$C$27:$G$32,4,FALSE)&" AS "&VLOOKUP(B20,'0. Instruções'!$C$27:$G$32,4,FALSE)&"_SIMUL, "&F20&" AS "&F20&"_SIMUL FROM "&E20&" WHERE "&'0. Instruções'!$D$43&")Y" -> (SELECT instrmnt_id AS instrmnt_id_SIMUL, CRRYNG_AMNT_INSTRMNT AS CRRYNG_AMNT_INSTRMNT_SIMUL FROM BU_LOANTAPE_WORK.LT002_INSTRUMENT WHERE ref_date='${ref_date}' AND nome_perimetro='Individual Local' AND segmento='ESTR' AND ambito='PM' AND entidade='00100')Y | K20: =+UPPER("ON X."&VLOOKUP(B20,'0. Instruções'!$C$27:$G$32,4,FALSE)&"=Y."&VLOOKUP(B20,'0. Instruções'!$C$27:$G$32,4,FALSE)&"_SIMUL") -> ON X.INSTRMNT_ID=Y.INSTRMNT_ID_SIMUL | L20: =+IF(C20="Coerência", +IF(LEFT(G20,5)="FLOAT","SELECT '"&UPPER(B20)&"' AS TABELA, '"&UPPER(C20)&"' AS TIPOLOGIA_TESTE,'"&D20&"' AS TABELA_LT,'"&E20&"' AS TABELA_SIMUL,'"&F20&"' AS CAMPO, "&"'${ref_date}' AS REF_DATE, COUNT(*) AS NUM_REG, SUM(IF((ABS(COALESCE(CAST(X."&F20&" AS DECIMAL(18,6)),0)-COALESCE(CAST(Y."&F20&"_SIMUL AS DECIMAL(18,6)),0))>0.000001) OR (X."&F20&" IS NULL AND Y."&F20&"_SIMUL IS NOT NULL ) OR (X."&F20&" IS NOT NULL AND Y."&F20&"_SIMUL IS NULL),1,0)) AS NUM_REG_DIF,'"&MAX('ID1&5'!K:K)+1&"' AS ID_EXEC, CURRENT_TIMESTAMP() AS TIME_EXEC FROM "&I20&" INNER JOIN "&J20&" "&K20,"SELECT '"&UPPER(B20)&"' AS TABELA, '"&UPPER(C20)&"' AS TIPOLOGIA_TESTE,'"&D20&"' AS TABELA_LT,'"&E20&"' AS TABELA_SIMUL,'"&F20&"' AS CAMPO, "&"'${ref_date}' AS REF_DATE, COUNT(*) AS NUM_REG, SUM(IF(COALESCE(CAST(X."&F20&" AS STRING),'')<>COALESCE(CAST(Y."&F20&"_SIMUL AS STRING),'') OR (X."&F20&" IS NULL AND Y."&F20&"_SIMUL IS NOT NULL ) OR (X."&F20&" IS NOT NULL AND Y."&F20&"_SIMUL IS NULL),1,0)) AS NUM_REG_DIF,'"&MAX('ID1&5'!L:L)+1&"' AS ID_EXEC, CURRENT_TIMESTAMP() AS TIME_EXEC FROM "&I20&" INNER JOIN "&J20&" "&K20), IF(C20="Validade",+IF(G20="Code List","SELECT '"&UPPER(B20)&"' AS TABELA, '"&UPPER(C20)&"' AS TIPOLOGIA_TESTE,'"&D20&"' AS TABELA_LT,'N/A' AS TABELA_SIMUL,'"&F20&"' AS CAMPO, "&"'${ref_date}' AS REF_DATE, COUNT(*) AS NUM_REG, SUM(IF(TRIM(CAST(X."&F20&" AS STRING))='' OR TRIM(CAST(X."&F20&" AS STRING)) IS NULL OR CAST(X."&F20&" AS STRING) NOT "&H20&",1,0)) AS NUM_REG_DIF,'"&MAX('ID1&5'!K:K)+1&"' AS ID_EXEC, CURRENT_TIMESTAMP() AS TIME_EXEC FROM "&I20,"SELECT '"&UPPER(B20)&"' AS TABELA, '"&UPPER(C20)&"' AS TIPOLOGIA_TESTE,'"&D20&"' AS TABELA_LT,'N/A' AS TABELA_SIMUL,'"&F20&"' AS CAMPO, "&"'${ref_date}' AS REF_DATE, COUNT(*) AS NUM_REG, SUM(IF(TRIM(CAST(X."&F20&" AS STRING))='' OR TRIM(CAST(X."&F20&" AS STRING)) IS NULL,1,0)) AS NUM_REG_DIF,'"&MAX('ID1&5'!K:K)+1&"' AS ID_EXEC, CURRENT_TIMESTAMP() AS TIME_EXEC FROM "&I20), IF(C20="Caracteres Especiais",+"SELECT '"&UPPER(B20)&"' AS TABELA, '"&UPPER(C20)&"' AS TIPOLOGIA_TESTE,'"&D20&"' AS TABELA_LT,'N/A' AS TABELA_SIMUL,'"&F20&"' AS CAMPO, "&"'${ref_date}' AS REF_DATE, COUNT(*) AS NUM_REG, SUM(IF(REGEXP_REPLACE(TRIM(CAST(X."&F20&" AS STRING)),'[^a-zA-Z0-9_\\s]','') <>TRIM(CAST(X."&F20&" AS STRING)),1,0)) AS NUM_REG_DIF,'"&MAX('ID1&5'!K:K)+1&"' AS ID_EXEC, CURRENT_TIMESTAMP() AS TIME_EXEC FROM "&I20, IF(C20="Missings",+"SELECT '"&UPPER(B20)&"' AS TABELA, '"&UPPER(C20)&"' AS TIPOLOGIA_TESTE,'"&D20&"' AS TABELA_LT,'N/A' AS TABELA_SIMUL,'"&F20&"' AS CAMPO, "&"'${ref_date}' AS REF_DATE, COUNT(*) AS NUM_REG, SUM(IF(TRIM(CAST(X."&F20&" AS STRING)) IN ('0000-00-00','0001-01-01','9999-12-31','MISS','00000','99999999999','99999999999.00','99999999999.000000'),1,0)) AS NUM_REG_DIF,'"&MAX('ID1&5'!K:K)+1&"' AS ID_EXEC, CURRENT_TIMESTAMP() AS TIME_EXEC FROM "&I20, IF(C20="Not applicable",+"SELECT '"&UPPER(B20)&"' AS TABELA, '"&UPPER(C20)&"' AS TIPOLOGIA_TESTE,'"&D20&"' AS TABELA_LT,'N/A' AS TABELA_SIMUL,'"&F20&"' AS CAMPO, "&"'${ref_date}' AS REF_DATE, COUNT(*) AS NUM_REG, SUM(IF(TRIM(CAST(X."&F20&" AS STRING)) IN ('N/A','11111111111','11111111111.00','11111111111.000000','1111-11-11'),1,0)) AS NUM_REG_DIF,'"&MAX('ID1&5'!K:K)+1&"' AS ID_EXEC, CURRENT_TIMESTAMP() AS TIME_EXEC FROM "&I20, IF(C20="Valores extremos",+"SELECT '"&UPPER(B20)&"' AS TABELA, '"&UPPER(C20)&"' AS TIPOLOGIA_TESTE,'"&D20&"' AS TABELA_LT,'N/A' AS TABELA_SIMUL,'"&F20&"' AS CAMPO, "&"'${ref_date}' AS REF_DATE, CAST(MIN("&F20&") AS STRING) AS VALOR_MIN, CAST(MAX("&F20&") AS STRING) AS VALOR_MAX,'"&MAX('ID1&5'!K:K)+1&"' AS ID_EXEC, CURRENT_TIMESTAMP() AS TIME_EXEC FROM "&MID(I20,1,LEN(I20)-2)&" AND CAST("&F20&" AS STRING) NOT IN ('0000-00-00','0001-01-01','9999-12-31','MISS','00000','99999999999','99999999999.00','99999999999.000000','N/A','11111111111','11111111111.00','11111111111.000000','1111-11-11'))X")))))) -> SELECT 'INSTRUMENT' AS TABELA, 'COERÊNCIA' AS TIPOLOGIA_TESTE,'CD_LOAN_TAPES_BCE.LT002_INSTRUMENT' AS TABELA_LT,'BU_LOANTAPE_WORK.LT002_INSTRUMENT' AS TABELA_SIMUL,'CRRYNG_AMNT_INSTRMNT' AS CAMPO, '${ref_date}' AS REF_DATE, COUNT(*) AS NUM_REG, SUM(IF(COALESCE(CAST(X.CRRYNG_AMNT_INSTRMNT AS STRING),'')<>COALESCE(CAST(Y.CRRYNG_AMNT_INSTRMNT_SIMUL AS STRING),'') OR (X.CRRYNG_AMNT_INSTRMNT IS NULL AND Y.CRRYNG_AMNT_INSTRMNT_SIMUL IS NOT NULL ) OR (X.CRRYNG_AMNT_INSTRMNT IS NOT NULL AND Y.CRRYNG_AMNT_INSTRMNT_SIMUL IS NULL),1,0)) AS NUM_REG_DIF,'1' AS ID_EXEC, CURRENT_TIMESTAMP() AS TIME_EXEC FROM (SELECT instrmnt_id, CRRYNG_AMNT_INSTRMNT FROM CD_LOAN_TAPES_BCE.LT002_INSTRUMENT WHERE ref_date='${ref_date}' AND nome_perimetro='Individual Local' AND segmento='ESTR' AND ambito='SRB_MBDT' AND entidade='00100')X INNER JOIN (SELECT instrmnt_id AS instrmnt_id_SIMUL, CRRYNG_AMNT_INSTRMNT AS CRRYNG_AMNT_INSTRMNT_SIMUL FROM BU_LOANTAPE_WORK.LT002_INSTRUMENT WHERE ref_date='${ref_date}' AND nome_perimetro='Individual Local' AND segmento='ESTR' AND ambito='PM' AND entidade='00100')Y ON X.INSTRMNT_ID=Y.INSTRMNT_ID_SIMUL | M20: =+"UNION ALL "&L20 -> UNION ALL SELECT 'INSTRUMENT' AS TABELA, 'COERÊNCIA' AS TIPOLOGIA_TESTE,'CD_LOAN_TAPES_BCE.LT002_INSTRUMENT' AS TABELA_LT,'BU_LOANTAPE_WORK.LT002_INSTRUMENT' AS TABELA_SIMUL,'CRRYNG_AMNT_INSTRMNT' AS CAMPO, '${ref_date}' AS REF_DATE, COUNT(*) AS NUM_REG, SUM(IF(COALESCE(CAST(X.CRRYNG_AMNT_INSTRMNT AS STRING),'')<>COALESCE(CAST(Y.CRRYNG_AMNT_INSTRMNT_SIMUL AS STRING),'') OR (X.CRRYNG_AMNT_INSTRMNT IS NULL AND Y.CRRYNG_AMNT_INSTRMNT_SIMUL IS NOT NULL ) OR (X.CRRYNG_AMNT_INSTRMNT IS NOT NULL AND Y.CRRYNG_AMNT_INSTRMNT_SIMUL IS NULL),1,0)) AS NUM_REG_DIF,'1' AS ID_EXEC, CURRENT_TIMESTAMP() AS TIME_EXEC FROM (SELECT instrmnt_id, CRRYNG_AMNT_INSTRMNT FROM CD_LOAN_TAPES_BCE.LT002_INSTRUMENT WHERE ref_date='${ref_date}' AND nome_perimetro='Individual Local' AND segmento='ESTR' AND ambito='SRB_MBDT' AND entidade='00100')X INNER JOIN (SELECT instrmnt_id AS instrmnt_id_SIMUL, CRRYNG_AMNT_INSTRMNT AS CRRYNG_AMNT_INSTRMNT_SIMUL FROM BU_LOANTAPE_WORK.LT002_INSTRUMENT WHERE ref_date='${ref_date}' AND nome_perimetro='Individual Local' AND segmento='ESTR' AND ambito='PM' AND entidade='00100')Y ON X.INSTRMNT_ID=Y.INSTRMNT_ID_SIMUL
... A23: =+B23&F23 -> PROTECTIONPRTCTN_PRVDR_ID | B23: PROTECTION | C23: Coerência | D23: =+UPPER('0. Instruções'!$D$35&"."&VLOOKUP(B23,'0. Instruções'!$C$27:$D$32,2,FALSE)) -> CD_LOAN_TAPES_BCE.LT004_PROTECTION | E23: =+UPPER('0. Instruções'!$D$36&"."&VLOOKUP(B23,'0. Instruções'!$C$27:$E$32,3,FALSE)) -> BU_LOANTAPE_WORK.LT004_PROTECTION | F23: PRTCTN_PRVDR_ID | I23: ="(SELECT "&VLOOKUP(B23,'0. Instruções'!$C$27:$G$32,4,FALSE)&", "&F23&" FROM "&D23&" WHERE "&'0. Instruções'!$D$42&")X" -> (SELECT prtctn_id, PRTCTN_PRVDR_ID FROM CD_LOAN_TAPES_BCE.LT004_PROTECTION WHERE ref_date='${ref_date}' AND nome_perimetro='Individual Local' AND segmento='ESTR' AND ambito='SRB_MBDT' AND entidade='00100')X | J23: ="(SELECT "&VLOOKUP(B23,'0. Instruções'!$C$27:$G$32,4,FALSE)&" AS "&VLOOKUP(B23,'0. Instruções'!$C$27:$G$32,4,FALSE)&"_SIMUL, "&F23&" AS "&F23&"_SIMUL FROM "&E23&" WHERE "&'0. Instruções'!$D$43&")Y" -> (SELECT prtctn_id AS prtctn_id_SIMUL, PRTCTN_PRVDR_ID AS PRTCTN_PRVDR_ID_SIMUL FROM BU_LOANTAPE_WORK.LT004_PROTECTION WHERE ref_date='${ref_date}' AND nome_perimetro='Individual Local' AND segmento='ESTR' AND ambito='PM' AND entidade='00100')Y | K23: =+UPPER("ON X."&VLOOKUP(B23,'0. Instruções'!$C$27:$G$32,4,FALSE)&"=Y."&VLOOKUP(B23,'0. Instruções'!$C$27:$G$32,4,FALSE)&"_SIMUL") -> ON X.PRTCTN_ID=Y.PRTCTN_ID_SIMUL | L23: =+IF(C23="Coerência", +IF(LEFT(G23,5)="FLOAT","SELECT '"&UPPER(B23)&"' AS TABELA, '"&UPPER(C23)&"' AS TIPOLOGIA_TESTE,'"&D23&"' AS TABELA_LT,'"&E23&"' AS TABELA_SIMUL,'"&F23&"' AS CAMPO, "&"'${ref_date}' AS REF_DATE, COUNT(*) AS NUM_REG, SUM(IF((ABS(COALESCE(CAST(X."&F23&" AS DECIMAL(18,6)),0)-COALESCE(CAST(Y."&F23&"_SIMUL AS DECIMAL(18,6)),0))>0.000001) OR (X."&F23&" IS NULL AND Y."&F23&"_SIMUL IS NOT NULL ) OR (X."&F23&" IS NOT NULL AND Y."&F23&"_SIMUL IS NULL),1,0)) AS NUM_REG_DIF,'"&MAX('ID1&5'!K:K)+1&"' AS ID_EXEC, CURRENT_TIMESTAMP() AS TIME_EXEC FROM "&I23&" INNER JOIN "&J23&" "&K23,"SELECT '"&UPPER(B23)&"' AS TABELA, '"&UPPER(C23)&"' AS TIPOLOGIA_TESTE,'"&D23&"' AS TABELA_LT,'"&E23&"' AS TABELA_SIMUL,'"&F23&"' AS CAMPO, "&"'${ref_date}' AS REF_DATE, COUNT(*) AS NUM_REG, SUM(IF(COALESCE(CAST(X."&F23&" AS STRING),'')<>COALESCE(CAST(Y."&F23&"_SIMUL AS STRING),'') OR (X."&F23&" IS NULL AND Y."&F23&"_SIMUL IS NOT NULL ) OR (X."&F23&" IS NOT NULL AND Y."&F23&"_SIMUL IS NULL),1,0)) AS NUM_REG_DIF,'"&MAX('ID1&5'!L:L)+1&"' AS ID_EXEC, CURRENT_TIMESTAMP() AS TIME_EXEC FROM "&I23&" INNER JOIN "&J23&" "&K23), IF(C23="Validade",+IF(G23="Code List","SELECT '"&UPPER(B23)&"' AS TABELA, '"&UPPER(C23)&"' AS TIPOLOGIA_TESTE,'"&D23&"' AS TABELA_LT,'N/A' AS TABELA_SIMUL,'"&F23&"' AS CAMPO, "&"'${ref_date}' AS REF_DATE, COUNT(*) AS NUM_REG, SUM(IF(TRIM(CAST(X."&F23&" AS STRING))='' OR TRIM(CAST(X."&F23&" AS STRING)) IS NULL OR CAST(X."&F23&" AS STRING) NOT "&H23&",1,0)) AS NUM_REG_DIF,'"&MAX('ID1&5'!K:K)+1&"' AS ID_EXEC, CURRENT_TIMESTAMP() AS TIME_EXEC FROM "&I23,"SELECT '"&UPPER(B23)&"' AS TABELA, '"&UPPER(C23)&"' AS TIPOLOGIA_TESTE,'"&D23&"' AS TABELA_LT,'N/A' AS TABELA_SIMUL,'"&F23&"' AS CAMPO, "&"'${ref_date}' AS REF_DATE, COUNT(*) AS NUM_REG, SUM(IF(TRIM(CAST(X."&F23&" AS STRING))='' OR TRIM(CAST(X."&F23&" AS STRING)) IS NULL,1,0)) AS NUM_REG_DIF,'"&MAX('ID1&5'!K:K)+1&"' AS ID_EXEC, CURRENT_TIMESTAMP() AS TIME_EXEC FROM "&I23), IF(C23="Caracteres Especiais",+"SELECT '"&UPPER(B23)&"' AS TABELA, '"&UPPER(C23)&"' AS TIPOLOGIA_TESTE,'"&D23&"' AS TABELA_LT,'N/A' AS TABELA_SIMUL,'"&F23&"' AS CAMPO, "&"'${ref_date}' AS REF_DATE, COUNT(*) AS NUM_REG, SUM(IF(REGEXP_REPLACE(TRIM(CAST(X."&F23&" AS STRING)),'[^a-zA-Z0-9_\\s]','') <>TRIM(CAST(X."&F23&" AS STRING)),1,0)) AS NUM_REG_DIF,'"&MAX('ID1&5'!K:K)+1&"' AS ID_EXEC, CURRENT_TIMESTAMP() AS TIME_EXEC FROM "&I23, IF(C23="Missings",+"SELECT '"&UPPER(B23)&"' AS TABELA, '"&UPPER(C23)&"' AS TIPOLOGIA_TESTE,'"&D23&"' AS TABELA_LT,'N/A' AS TABELA_SIMUL,'"&F23&"' AS CAMPO, "&"'${ref_date}' AS REF_DATE, COUNT(*) AS NUM_REG, SUM(IF(TRIM(CAST(X."&F23&" AS STRING)) IN ('0000-00-00','0001-01-01','9999-12-31','MISS','00000','99999999999','99999999999.00','99999999999.000000'),1,0)) AS NUM_REG_DIF,'"&MAX('ID1&5'!K:K)+1&"' AS ID_EXEC, CURRENT_TIMESTAMP() AS TIME_EXEC FROM "&I23, IF(C23="Not applicable",+"SELECT '"&UPPER(B23)&"' AS TABELA, '"&UPPER(C23)&"' AS TIPOLOGIA_TESTE,'"&D23&"' AS TABELA_LT,'N/A' AS TABELA_SIMUL,'"&F23&"' AS CAMPO, "&"'${ref_date}' AS REF_DATE, COUNT(*) AS NUM_REG, SUM(IF(TRIM(CAST(X."&F23&" AS STRING)) IN ('N/A','11111111111','11111111111.00','11111111111.000000','1111-11-11'),1,0)) AS NUM_REG_DIF,'"&MAX('ID1&5'!K:K)+1&"' AS ID_EXEC, CURRENT_TIMESTAMP() AS TIME_EXEC FROM "&I23, IF(C23="Valores extremos",+"SELECT '"&UPPER(B23)&"' AS TABELA, '"&UPPER(C23)&"' AS TIPOLOGIA_TESTE,'"&D23&"' AS TABELA_LT,'N/A' AS TABELA_SIMUL,'"&F23&"' AS CAMPO, "&"'${ref_date}' AS REF_DATE, CAST(MIN("&F23&") AS STRING) AS VALOR_MIN, CAST(MAX("&F23&") AS STRING) AS VALOR_MAX,'"&MAX('ID1&5'!K:K)+1&"' AS ID_EXEC, CURRENT_TIMESTAMP() AS TIME_EXEC FROM "&MID(I23,1,LEN(I23)-2)&" AND CAST("&F23&" AS STRING) NOT IN ('0000-00-00','0001-01-01','9999-12-31','MISS','00000','99999999999','99999999999.00','99999999999.000000','N/A','11111111111','11111111111.00','11111111111.000000','1111-11-11'))X")))))) -> SELECT 'PROTECTION' AS TABELA, 'COERÊNCIA' AS TIPOLOGIA_TESTE,'CD_LOAN_TAPES_BCE.LT004_PROTECTION' AS TABELA_LT,'BU_LOANTAPE_WORK.LT004_PROTECTION' AS TABELA_SIMUL,'PRTCTN_PRVDR_ID' AS CAMPO, '${ref_date}' AS REF_DATE, COUNT(*) AS NUM_REG, SUM(IF(COALESCE(CAST(X.PRTCTN_PRVDR_ID AS STRING),'')<>COALESCE(CAST(Y.PRTCTN_PRVDR_ID_SIMUL AS STRING),'') OR (X.PRTCTN_PRVDR_ID IS NULL AND Y.PRTCTN_PRVDR_ID_SIMUL IS NOT NULL ) OR (X.PRTCTN_PRVDR_ID IS NOT NULL AND Y.PRTCTN_PRVDR_ID_SIMUL IS NULL),1,0)) AS NUM_REG_DIF,'1' AS ID_EXEC, CURRENT_TIMESTAMP() AS TIME_EXEC FROM (SELECT prtctn_id, PRTCTN_PRVDR_ID FROM CD_LOAN_TAPES_BCE.LT004_PROTECTION WHERE ref_date='${ref_date}' AND nome_perimetro='Individual Local' AND segmento='ESTR' AND ambito='SRB_MBDT' AND entidade='00100')X INNER JOIN (SELECT prtctn_id AS prtctn_id_SIMUL, PRTCTN_PRVDR_ID AS PRTCTN_PRVDR_ID_SIMUL FROM BU_LOANTAPE_WORK.LT004_PROTECTION WHERE ref_date='${ref_date}' AND nome_perimetro='Individual Local' AND segmento='ESTR' AND ambito='PM' AND entidade='00100')Y ON X.PRTCTN_ID=Y.PRTCTN_ID_SIMUL | M23: =+"UNION ALL "&L23 -> UNION ALL SELECT 'PROTECTION' AS TABELA, 'COERÊNCIA' AS TIPOLOGIA_TESTE,'CD_LOAN_TAPES_BCE.LT004_PROTECTION' AS TABELA_LT,'BU_LOANTAPE_WORK.LT004_PROTECTION' AS TABELA_SIMUL,'PRTCTN_PRVDR_ID' AS CAMPO, '${ref_date}' AS REF_DATE, COUNT(*) AS NUM_REG, SUM(IF(COALESCE(CAST(X.PRTCTN_PRVDR_ID AS STRING),'')<>COALESCE(CAST(Y.PRTCTN_PRVDR_ID_SIMUL AS STRING),'') OR (X.PRTCTN_PRVDR_ID IS NULL AND Y.PRTCTN_PRVDR_ID_SIMUL IS NOT NULL ) OR (X.PRTCTN_PRVDR_ID IS NOT NULL AND Y.PRTCTN_PRVDR_ID_SIMUL IS NULL),1,0)) AS NUM_REG_DIF,'1' AS ID_EXEC, CURRENT_TIMESTAMP() AS TIME_EXEC FROM (SELECT prtctn_id, PRTCTN_PRVDR_ID FROM CD_LOAN_TAPES_BCE.LT004_PROTECTION WHERE ref_date='${ref_date}' AND nome_perimetro='Individual Local' AND segmento='ESTR' AND ambito='SRB_MBDT' AND entidade='00100')X INNER JOIN (SELECT prtctn_id AS prtctn_id_SIMUL, PRTCTN_PRVDR_ID AS PRTCTN_PRVDR_ID_SIMUL FROM BU_LOANTAPE_WORK.LT004_PROTECTION WHERE ref_date='${ref_date}' AND nome_perimetro='Individual Local' AND segmento='ESTR' AND ambito='PM' AND entidade='00100')Y ON X.PRTCTN_ID=Y.PRTCTN_ID_SIMUL
A24: =+B24&F24 -> INSTR_PROTECTIONPRTCTN_ALLCTD_VL | B24: INSTR_PROTECTION | C24: Coerência | D24: =+UPPER('0. Instruções'!$D$35&"."&VLOOKUP(B24,'0. Instruções'!$C$27:$D$32,2,FALSE)) -> CD_LOAN_TAPES_BCE.LT006_INSTR_PROT | E24: =+UPPER('0. Instruções'!$D$36&"."&VLOOKUP(B24,'0. Instruções'!$C$27:$E$32,3,FALSE)) -> BU_LOANTAPE_WORK.LT006_INSTR_PROT | F24: PRTCTN_ALLCTD_VL | I24: =IF(VLOOKUP(B24,'0. Instruções'!$C$27:$G$32,5,FALSE)=0, "(SELECT "&VLOOKUP(B24,'0. Instruções'!$C$27:$G$32,4,FALSE)&" AS CHAVE_IT, "&F24&" AS CAMPO_IT FROM "&D24&" WHERE "&'0. Instruções'!$D$43&")X", "(SELECT "&VLOOKUP(B24,'0. Instruções'!$C$27:$G$32,4,FALSE)&" AS CHAVE_IT1, "&VLOOKUP(B24,'0. Instruções'!$C$27:$G$32,5,FALSE)&" AS CHAVE_IT2, "&F24&" AS CAMPO_IT FROM "&D24&" WHERE "&'0. Instruções'!$D$43&")X") -> (SELECT instrmnt_id AS CHAVE_IT1, prtctn_id AS CHAVE_IT2, PRTCTN_ALLCTD_VL AS CAMPO_IT FROM CD_LOAN_TAPES_BCE.LT006_INSTR_PROT WHERE ref_date='${ref_date}' AND nome_perimetro='Individual Local' AND segmento='ESTR' AND ambito='PM' AND entidade='00100')X | J24: =IF(VLOOKUP(B24,'0. Instruções'!$C$27:$G$32,5,FALSE)=0, "(SELECT "&VLOOKUP(B24,'0. Instruções'!$C$27:$G$32,4,FALSE)&" AS CHAVE_SIMUL, "&F24&" AS CAMPO_SIMUL FROM "&E24&" WHERE "&'0. Instruções'!$D$42&")Y", "(SELECT "&VLOOKUP(B24,'0. Instruções'!$C$27:$G$32,4,FALSE)&" AS CHAVE_SIMUL1, "&VLOOKUP(B24,'0. Instruções'!$C$27:$G$32,5,FALSE)&" AS CHAVE_SIMUL2, "&F24&" AS CAMPO_SIMUL FROM "&E24&" WHERE "&'0. Instruções'!$D$42&")Y") -> (SELECT instrmnt_id AS CHAVE_SIMUL1, prtctn_id AS CHAVE_SIMUL2, PRTCTN_ALLCTD_VL AS CAMPO_SIMUL FROM BU_LOANTAPE_WORK.LT006_INSTR_PROT WHERE ref_date='${ref_date}' AND nome_perimetro='Individual Local' AND segmento='ESTR' AND ambito='SRB_MBDT' AND entidade='00100')Y | K24: =IF(VLOOKUP(B24,'0. Instruções'!$C$27:$G$32,5,FALSE)=0, "ON X.CHAVE_IT=Y.CHAVE_SIMUL", "ON X.CHAVE_IT1=Y.CHAVE_SIMUL1 AND X.CHAVE_IT2=Y.CHAVE_SIMUL2") -> ON X.CHAVE_IT1=Y.CHAVE_SIMUL1 AND X.CHAVE_IT2=Y.CHAVE_SIMUL2 | L24: =+IF(C24="Coerência",+IF(LEFT(G24,5)="FLOAT","SELECT '"&UPPER(B24)&"' AS TABELA, '"&UPPER(C24)&"' AS TIPOLOGIA_TESTE,'"&D24&"' AS TABELA_LT,'"&E24&"' AS TABELA_SIMUL,'"&F24&"' AS CAMPO, "&_xlfn._LONGTEXT("'${ref_date}' AS REF_DATE, COUNT(*) AS NUM_REG, SUM(IF((ABS(COALESCE(CAST(X.CAMPO_IT AS DECIMAL(18,6)),0)-COALESCE(CAST(Y.CAMPO_SIMUL AS DECIMAL(18,6)),0))>0.000001) OR (X.CAMPO_IT IS NULL AND Y.CAMPO_SIMUL IS NOT NULL ) OR (X.CAMPO_IT IS NOT NULL AND Y.C","AMPO_SIMUL IS NULL),1,0)) AS NUM_REG_DIF,'")&MAX('ID1&5'!K:K)+1&"' AS ID_EXEC, CURRENT_TIMESTAMP() AS TIME_EXEC FROM "&I24&" INNER JOIN "&J24&" "&K24,"SELECT '"&UPPER(B24)&"' AS TABELA, '"&UPPER(C24)&"' AS TIPOLOGIA_TESTE,'"&D24&"' AS TABELA_LT,'"&E24&"' AS TABELA_SIMUL,'"&F24&"' AS CAMPO, "&_xlfn._LONGTEXT("'${ref_date}' AS REF_DATE, COUNT(*) AS NUM_REG, SUM(IF(COALESCE(CAST(X.CAMPO_IT AS STRING),'')<>COALESCE(CAST(Y.CAMPO_SIMUL AS STRING),'') OR (X.CAMPO_IT IS NULL AND Y.CAMPO_SIMUL IS NOT NULL ) OR (X.CAMPO_IT IS NOT NULL AND Y.CAMPO_SIMUL IS NULL),1,0)) A","S NUM_REG_DIF,'")&MAX('ID1&5'!L:L)+1&"' AS ID_EXEC, CURRENT_TIMESTAMP() AS TIME_EXEC FROM "&I24&" INNER JOIN "&J24&" "&K24)) -> SELECT 'INSTR_PROTECTION' AS TABELA, 'COERÊNCIA' AS TIPOLOGIA_TESTE,'CD_LOAN_TAPES_BCE.LT006_INSTR_PROT' AS TABELA_LT,'BU_LOANTAPE_WORK.LT006_INSTR_PROT' AS TABELA_SIMUL,'PRTCTN_ALLCTD_VL' AS CAMPO, '${ref_date}' AS REF_DATE, COUNT(*) AS NUM_REG, SUM(IF(COALESCE(CAST(X.CAMPO_IT AS STRING),'')<>COALESCE(CAST(Y.CAMPO_SIMUL AS STRING),'') OR (X.CAMPO_IT IS NULL AND Y.CAMPO_SIMUL IS NOT NULL ) OR (X.CAMPO_IT IS NOT NULL AND Y.CAMPO_SIMUL IS NULL),1,0)) AS NUM_REG_DIF,'1' AS ID_EXEC, CURRENT_TIMESTAMP() AS TIME_EXEC FROM (SELECT instrmnt_id AS CHAVE_IT1, prtctn_id AS CHAVE_IT2, PRTCTN_ALLCTD_VL AS CAMPO_IT FROM CD_LOAN_TAPES_BCE.LT006_INSTR_PROT WHERE ref_date='${ref_date}' AND nome_perimetro='Individual Local' AND segmento='ESTR' AND ambito='PM' AND entidade='00100')X INNER JOIN (SELECT instrmnt_id AS CHAVE_SIMUL1, prtctn_id AS CHAVE_SIMUL2, PRTCTN_ALLCTD_VL AS CAMPO_SIMUL FROM BU_LOANTAPE_WORK.LT006_INSTR_PROT WHERE ref_date='${ref_date}' AND nome_perimetro='Individual Local' AND segmento='ESTR' AND ambito='SRB_MBDT' AND entidade='00100')Y ON X.CHAVE_IT1=Y.CHAVE_SIMUL1 AND X.CHAVE_IT2=Y.CHAVE_SIMUL2 | M24: =+"UNION ALL "&L24 -> UNION ALL SELECT 'INSTR_PROTECTION' AS TABELA, 'COERÊNCIA' AS TIPOLOGIA_TESTE,'CD_LOAN_TAPES_BCE.LT006_INSTR_PROT' AS TABELA_LT,'BU_LOANTAPE_WORK.LT006_INSTR_PROT' AS TABELA_SIMUL,'PRTCTN_ALLCTD_VL' AS CAMPO, '${ref_date}' AS REF_DATE, COUNT(*) AS NUM_REG, SUM(IF(COALESCE(CAST(X.CAMPO_IT AS STRING),'')<>COALESCE(CAST(Y.CAMPO_SIMUL AS STRING),'') OR (X.CAMPO_IT IS NULL AND Y.CAMPO_SIMUL IS NOT NULL ) OR (X.CAMPO_IT IS NOT NULL AND Y.CAMPO_SIMUL IS NULL),1,0)) AS NUM_REG_DIF,'1' AS ID_EXEC, CURRENT_TIMESTAMP() AS TIME_EXEC FROM (SELECT instrmnt_id AS CHAVE_IT1, prtctn_id AS CHAVE_IT2, PRTCTN_ALLCTD_VL AS CAMPO_IT FROM CD_LOAN_TAPES_BCE.LT006_INSTR_PROT WHERE ref_date='${ref_date}' AND nome_perimetro='Individual Local' AND segmento='ESTR' AND ambito='PM' AND entidade='00100')X INNER JOIN (SELECT instrmnt_id AS CHAVE_SIMUL1, prtctn_id AS CHAVE_SIMUL2, PRTCTN_ALLCTD_VL AS CAMPO_SIMUL FROM BU_LOANTAPE_WORK.LT006_INSTR_PROT WHERE ref_date='${ref_date}' AND nome_perimetro='Individual Local' AND segmento='ESTR' AND ambito='SRB_MBDT' AND entidade='00100')Y ON X.CHAVE_IT1=Y.CHAVE_SIMUL1 AND X.CHAVE_IT2=Y.CHAVE_SIMUL2
A25: =+B25&F25 -> UNIV_OPERFLAG_GAR_INTRG_SAN | B25: UNIV_OPER | C25: Coerência | D25: =+UPPER('0. Instruções'!$D$35&"."&VLOOKUP(B25,'0. Instruções'!$C$27:$D$32,2,FALSE)) -> CD_LOAN_TAPES_BCE.LT001_UNIV_OPER | E25: =+UPPER('0. Instruções'!$D$36&"."&VLOOKUP(B25,'0. Instruções'!$C$27:$E$32,3,FALSE)) -> BU_LOANTAPE_WORK.LT001_UNIV_OPER | F25: FLAG_GAR_INTRG_SAN | I25: =IF(VLOOKUP(B25,'0. Instruções'!$C$27:$G$32,5,FALSE)=0, "(SELECT "&VLOOKUP(B25,'0. Instruções'!$C$27:$G$32,4,FALSE)&" AS CHAVE_IT, "&F25&" AS CAMPO_IT FROM "&D25&" WHERE "&'0. Instruções'!$D$43&")X", "(SELECT "&VLOOKUP(B25,'0. Instruções'!$C$27:$G$32,4,FALSE)&" AS CHAVE_IT1, "&VLOOKUP(B25,'0. Instruções'!$C$27:$G$32,5,FALSE)&" AS CHAVE_IT2, "&F25&" AS CAMPO_IT FROM "&D25&" WHERE "&'0. Instruções'!$D$43&")X") -> (SELECT concat(cempresa, cbalcao, cnumecta, zdeposit, ccontab_final_ifrs, ccontab_final_pcsb, ccontab_final_cargabal, ccontab_final) AS CHAVE_IT, FLAG_GAR_INTRG_SAN AS CAMPO_IT FROM CD_LOAN_TAPES_BCE.LT001_UNIV_OPER WHERE ref_date='${ref_date}' AND nome_perimetro='Individual Local' AND segmento='ESTR' AND ambito='PM' AND entidade='00100')X | J25: =IF(VLOOKUP(B25,'0. Instruções'!$C$27:$G$32,5,FALSE)=0, "(SELECT "&VLOOKUP(B25,'0. Instruções'!$C$27:$G$32,4,FALSE)&" AS CHAVE_SIMUL, "&F25&" AS CAMPO_SIMUL FROM "&E25&" WHERE "&'0. Instruções'!$D$42&")Y", "(SELECT "&VLOOKUP(B25,'0. Instruções'!$C$27:$G$32,4,FALSE)&" AS CHAVE_SIMUL1, "&VLOOKUP(B25,'0. Instruções'!$C$27:$G$32,5,FALSE)&" AS CHAVE_SIMUL2, "&F25&" AS CAMPO_SIMUL FROM "&E25&" WHERE "&'0. Instruções'!$D$42&")Y") -> (SELECT concat(cempresa, cbalcao, cnumecta, zdeposit, ccontab_final_ifrs, ccontab_final_pcsb, ccontab_final_cargabal, ccontab_final) AS CHAVE_SIMUL, FLAG_GAR_INTRG_SAN AS CAMPO_SIMUL FROM BU_LOANTAPE_WORK.LT001_UNIV_OPER WHERE ref_date='${ref_date}' AND nome_perimetro='Individual Local' AND segmento='ESTR' AND ambito='SRB_MBDT' AND entidade='00100')Y | K25: =IF(VLOOKUP(B25,'0. Instruções'!$C$27:$G$32,5,FALSE)=0, "ON X.CHAVE_IT=Y.CHAVE_SIMUL", "ON X.CHAVE_IT1=Y.CHAVE_SIMUL1 AND X.CHAVE_IT2=Y.CHAVE_SIMUL2") -> ON X.CHAVE_IT=Y.CHAVE_SIMUL | L25: =+IF(C25="Coerência",+IF(LEFT(G25,5)="FLOAT","SELECT '"&UPPER(B25)&"' AS TABELA, '"&UPPER(C25)&"' AS TIPOLOGIA_TESTE,'"&D25&"' AS TABELA_LT,'"&E25&"' AS TABELA_SIMUL,'"&F25&"' AS CAMPO, "&_xlfn._LONGTEXT("'${ref_date}' AS REF_DATE, COUNT(*) AS NUM_REG, SUM(IF((ABS(COALESCE(CAST(X.CAMPO_IT AS DECIMAL(18,6)),0)-COALESCE(CAST(Y.CAMPO_SIMUL AS DECIMAL(18,6)),0))>0.000001) OR (X.CAMPO_IT IS NULL AND Y.CAMPO_SIMUL IS NOT NULL ) OR (X.CAMPO_IT IS NOT NULL AND Y.C","AMPO_SIMUL IS NULL),1,0)) AS NUM_REG_DIF,'")&MAX('ID1&5'!K:K)+1&"' AS ID_EXEC, CURRENT_TIMESTAMP() AS TIME_EXEC FROM "&I25&" INNER JOIN "&J25&" "&K25,"SELECT '"&UPPER(B25)&"' AS TABELA, '"&UPPER(C25)&"' AS TIPOLOGIA_TESTE,'"&D25&"' AS TABELA_LT,'"&E25&"' AS TABELA_SIMUL,'"&F25&"' AS CAMPO, "&_xlfn._LONGTEXT("'${ref_date}' AS REF_DATE, COUNT(*) AS NUM_REG, SUM(IF(COALESCE(CAST(X.CAMPO_IT AS STRING),'')<>COALESCE(CAST(Y.CAMPO_SIMUL AS STRING),'') OR (X.CAMPO_IT IS NULL AND Y.CAMPO_SIMUL IS NOT NULL ) OR (X.CAMPO_IT IS NOT NULL AND Y.CAMPO_SIMUL IS NULL),1,0)) A","S NUM_REG_DIF,'")&MAX('ID1&5'!L:L)+1&"' AS ID_EXEC, CURRENT_TIMESTAMP() AS TIME_EXEC FROM "&I25&" INNER JOIN "&J25&" "&K25)) -> SELECT 'UNIV_OPER' AS TABELA, 'COERÊNCIA' AS TIPOLOGIA_TESTE,'CD_LOAN_TAPES_BCE.LT001_UNIV_OPER' AS TABELA_LT,'BU_LOANTAPE_WORK.LT001_UNIV_OPER' AS TABELA_SIMUL,'FLAG_GAR_INTRG_SAN' AS CAMPO, '${ref_date}' AS REF_DATE, COUNT(*) AS NUM_REG, SUM(IF(COALESCE(CAST(X.CAMPO_IT AS STRING),'')<>COALESCE(CAST(Y.CAMPO_SIMUL AS STRING),'') OR (X.CAMPO_IT IS NULL AND Y.CAMPO_SIMUL IS NOT NULL ) OR (X.CAMPO_IT IS NOT NULL AND Y.CAMPO_SIMUL IS NULL),1,0)) AS NUM_REG_DIF,'1' AS ID_EXEC, CURRENT_TIMESTAMP() AS TIME_EXEC FROM (SELECT concat(cempresa, cbalcao, cnumecta, zdeposit, ccontab_final_ifrs, ccontab_final_pcsb, ccontab_final_cargabal, ccontab_final) AS CHAVE_IT, FLAG_GAR_INTRG_SAN AS CAMPO_IT FROM CD_LOAN_TAPES_BCE.LT001_UNIV_OPER WHERE ref_date='${ref_date}' AND nome_perimetro='Individual Local' AND segmento='ESTR' AND ambito='PM' AND entidade='00100')X INNER JOIN (SELECT concat(cempresa, cbalcao, cnumecta, zdeposit, ccontab_final_ifrs, ccontab_final_pcsb, ccontab_final_cargabal, ccontab_final) AS CHAVE_SIMUL, FLAG_GAR_INTRG_SAN AS CAMPO_SIMUL FROM BU_LOANTAPE_WORK.LT001_UNIV_OPER WHERE ref_date='${ref_date}' AND nome_perimetro='Individual Local' AND segmento='ESTR' AND ambito='SRB_MBDT' AND entidade='00100')Y ON X.CHAVE_IT=Y.CHAVE_SIMUL | M25: =+"UNION ALL "&L25 -> UNION ALL SELECT 'UNIV_OPER' AS TABELA, 'COERÊNCIA' AS TIPOLOGIA_TESTE,'CD_LOAN_TAPES_BCE.LT001_UNIV_OPER' AS TABELA_LT,'BU_LOANTAPE_WORK.LT001_UNIV_OPER' AS TABELA_SIMUL,'FLAG_GAR_INTRG_SAN' AS CAMPO, '${ref_date}' AS REF_DATE, COUNT(*) AS NUM_REG, SUM(IF(COALESCE(CAST(X.CAMPO_IT AS STRING),'')<>COALESCE(CAST(Y.CAMPO_SIMUL AS STRING),'') OR (X.CAMPO_IT IS NULL AND Y.CAMPO_SIMUL IS NOT NULL ) OR (X.CAMPO_IT IS NOT NULL AND Y.CAMPO_SIMUL IS NULL),1,0)) AS NUM_REG_DIF,'1' AS ID_EXEC, CURRENT_TIMESTAMP() AS TIME_EXEC FROM (SELECT concat(cempresa, cbalcao, cnumecta, zdeposit, ccontab_final_ifrs, ccontab_final_pcsb, ccontab_final_cargabal, ccontab_final) AS CHAVE_IT, FLAG_GAR_INTRG_SAN AS CAMPO_IT FROM CD_LOAN_TAPES_BCE.LT001_UNIV_OPER WHERE ref_date='${ref_date}' AND nome_perimetro='Individual Local' AND segmento='ESTR' AND ambito='PM' AND entidade='00100')X INNER JOIN (SELECT concat(cempresa, cbalcao, cnumecta, zdeposit, ccontab_final_ifrs, ccontab_final_pcsb, ccontab_final_cargabal, ccontab_final) AS CHAVE_SIMUL, FLAG_GAR_INTRG_SAN AS CAMPO_SIMUL FROM BU_LOANTAPE_WORK.LT001_UNIV_OPER WHERE ref_date='${ref_date}' AND nome_perimetro='Individual Local' AND segmento='ESTR' AND ambito='SRB_MBDT' AND entidade='00100')Y ON X.CHAVE_IT=Y.CHAVE_SIMUL
A26: =+B26&F26 -> UNIV_OPERFLAG_INST_TITULOS | B26: UNIV_OPER | C26: Coerência | D26: =+UPPER('0. Instruções'!$D$35&"."&VLOOKUP(B26,'0. Instruções'!$C$27:$D$32,2,FALSE)) -> CD_LOAN_TAPES_BCE.LT001_UNIV_OPER | E26: =+UPPER('0. Instruções'!$D$36&"."&VLOOKUP(B26,'0. Instruções'!$C$27:$E$32,3,FALSE)) -> BU_LOANTAPE_WORK.LT001_UNIV_OPER | F26: FLAG_INST_TITULOS | I26: =IF(VLOOKUP(B26,'0. Instruções'!$C$27:$G$32,5,FALSE)=0, "(SELECT "&VLOOKUP(B26,'0. Instruções'!$C$27:$G$32,4,FALSE)&" AS CHAVE_IT, "&F26&" AS CAMPO_IT FROM "&D26&" WHERE "&'0. Instruções'!$D$43&")X", "(SELECT "&VLOOKUP(B26,'0. Instruções'!$C$27:$G$32,4,FALSE)&" AS CHAVE_IT1, "&VLOOKUP(B26,'0. Instruções'!$C$27:$G$32,5,FALSE)&" AS CHAVE_IT2, "&F26&" AS CAMPO_IT FROM "&D26&" WHERE "&'0. Instruções'!$D$43&")X") -> (SELECT concat(cempresa, cbalcao, cnumecta, zdeposit, ccontab_final_ifrs, ccontab_final_pcsb, ccontab_final_cargabal, ccontab_final) AS CHAVE_IT, FLAG_INST_TITULOS AS CAMPO_IT FROM CD_LOAN_TAPES_BCE.LT001_UNIV_OPER WHERE ref_date='${ref_date}' AND nome_perimetro='Individual Local' AND segmento='ESTR' AND ambito='PM' AND entidade='00100')X | J26: =IF(VLOOKUP(B26,'0. Instruções'!$C$27:$G$32,5,FALSE)=0, "(SELECT "&VLOOKUP(B26,'0. Instruções'!$C$27:$G$32,4,FALSE)&" AS CHAVE_SIMUL, "&F26&" AS CAMPO_SIMUL FROM "&E26&" WHERE "&'0. Instruções'!$D$42&")Y", "(SELECT "&VLOOKUP(B26,'0. Instruções'!$C$27:$G$32,4,FALSE)&" AS CHAVE_SIMUL1, "&VLOOKUP(B26,'0. Instruções'!$C$27:$G$32,5,FALSE)&" AS CHAVE_SIMUL2, "&F26&" AS CAMPO_SIMUL FROM "&E26&" WHERE "&'0. Instruções'!$D$42&")Y") -> (SELECT concat(cempresa, cbalcao, cnumecta, zdeposit, ccontab_final_ifrs, ccontab_final_pcsb, ccontab_final_cargabal, ccontab_final) AS CHAVE_SIMUL, FLAG_INST_TITULOS AS CAMPO_SIMUL FROM BU_LOANTAPE_WORK.LT001_UNIV_OPER WHERE ref_date='${ref_date}' AND nome_perimetro='Individual Local' AND segmento='ESTR' AND ambito='SRB_MBDT' AND entidade='00100')Y | K26: =IF(VLOOKUP(B26,'0. Instruções'!$C$27:$G$32,5,FALSE)=0, "ON X.CHAVE_IT=Y.CHAVE_SIMUL", "ON X.CHAVE_IT1=Y.CHAVE_SIMUL1 AND X.CHAVE_IT2=Y.CHAVE_SIMUL2") -> ON X.CHAVE_IT=Y.CHAVE_SIMUL | L26: =+IF(C26="Coerência",+IF(LEFT(G26,5)="FLOAT","SELECT '"&UPPER(B26)&"' AS TABELA, '"&UPPER(C26)&"' AS TIPOLOGIA_TESTE,'"&D26&"' AS TABELA_LT,'"&E26&"' AS TABELA_SIMUL,'"&F26&"' AS CAMPO, "&_xlfn._LONGTEXT("'${ref_date}' AS REF_DATE, COUNT(*) AS NUM_REG, SUM(IF((ABS(COALESCE(CAST(X.CAMPO_IT AS DECIMAL(18,6)),0)-COALESCE(CAST(Y.CAMPO_SIMUL AS DECIMAL(18,6)),0))>0.000001) OR (X.CAMPO_IT IS NULL AND Y.CAMPO_SIMUL IS NOT NULL ) OR (X.CAMPO_IT IS NOT NULL AND Y.C","AMPO_SIMUL IS NULL),1,0)) AS NUM_REG_DIF,'")&MAX('ID1&5'!K:K)+1&"' AS ID_EXEC, CURRENT_TIMESTAMP() AS TIME_EXEC FROM "&I26&" INNER JOIN "&J26&" "&K26,"SELECT '"&UPPER(B26)&"' AS TABELA, '"&UPPER(C26)&"' AS TIPOLOGIA_TESTE,'"&D26&"' AS TABELA_LT,'"&E26&"' AS TABELA_SIMUL,'"&F26&"' AS CAMPO, "&_xlfn._LONGTEXT("'${ref_date}' AS REF_DATE, COUNT(*) AS NUM_REG, SUM(IF(COALESCE(CAST(X.CAMPO_IT AS STRING),'')<>COALESCE(CAST(Y.CAMPO_SIMUL AS STRING),'') OR (X.CAMPO_IT IS NULL AND Y.CAMPO_SIMUL IS NOT NULL ) OR (X.CAMPO_IT IS NOT NULL AND Y.CAMPO_SIMUL IS NULL),1,0)) A","S NUM_REG_DIF,'")&MAX('ID1&5'!L:L)+1&"' AS ID_EXEC, CURRENT_TIMESTAMP() AS TIME_EXEC FROM "&I26&" INNER JOIN "&J26&" "&K26)) -> SELECT 'UNIV_OPER' AS TABELA, 'COERÊNCIA' AS TIPOLOGIA_TESTE,'CD_LOAN_TAPES_BCE.LT001_UNIV_OPER' AS TABELA_LT,'BU_LOANTAPE_WORK.LT001_UNIV_OPER' AS TABELA_SIMUL,'FLAG_INST_TITULOS' AS CAMPO, '${ref_date}' AS REF_DATE, COUNT(*) AS NUM_REG, SUM(IF(COALESCE(CAST(X.CAMPO_IT AS STRING),'')<>COALESCE(CAST(Y.CAMPO_SIMUL AS STRING),'') OR (X.CAMPO_IT IS NULL AND Y.CAMPO_SIMUL IS NOT NULL ) OR (X.CAMPO_IT IS NOT NULL AND Y.CAMPO_SIMUL IS NULL),1,0)) AS NUM_REG_DIF,'1' AS ID_EXEC, CURRENT_TIMESTAMP() AS TIME_EXEC FROM (SELECT concat(cempresa, cbalcao, cnumecta, zdeposit, ccontab_final_ifrs, ccontab_final_pcsb, ccontab_final_cargabal, ccontab_final) AS CHAVE_IT, FLAG_INST_TITULOS AS CAMPO_IT FROM CD_LOAN_TAPES_BCE.LT001_UNIV_OPER WHERE ref_date='${ref_date}' AND nome_perimetro='Individual Local' AND segmento='ESTR' AND ambito='PM' AND entidade='00100')X INNER JOIN (SELECT concat(cempresa, cbalcao, cnumecta, zdeposit, ccontab_final_ifrs, ccontab_final_pcsb, ccontab_final_cargabal, ccontab_final) AS CHAVE_SIMUL, FLAG_INST_TITULOS AS CAMPO_SIMUL FROM BU_LOANTAPE_WORK.LT001_UNIV_OPER WHERE ref_date='${ref_date}' AND nome_perimetro='Individual Local' AND segmento='ESTR' AND ambito='SRB_MBDT' AND entidade='00100')Y ON X.CHAVE_IT=Y.CHAVE_SIMUL | M26: =+"UNION ALL "&L26 -> UNION ALL SELECT 'UNIV_OPER' AS TABELA, 'COERÊNCIA' AS TIPOLOGIA_TESTE,'CD_LOAN_TAPES_BCE.LT001_UNIV_OPER' AS TABELA_LT,'BU_LOANTAPE_WORK.LT001_UNIV_OPER' AS TABELA_SIMUL,'FLAG_INST_TITULOS' AS CAMPO, '${ref_date}' AS REF_DATE, COUNT(*) AS NUM_REG, SUM(IF(COALESCE(CAST(X.CAMPO_IT AS STRING),'')<>COALESCE(CAST(Y.CAMPO_SIMUL AS STRING),'') OR (X.CAMPO_IT IS NULL AND Y.CAMPO_SIMUL IS NOT NULL ) OR (X.CAMPO_IT IS NOT NULL AND Y.CAMPO_SIMUL IS NULL),1,0)) AS NUM_REG_DIF,'1' AS ID_EXEC, CURRENT_TIMESTAMP() AS TIME_EXEC FROM (SELECT concat(cempresa, cbalcao, cnumecta, zdeposit, ccontab_final_ifrs, ccontab_final_pcsb, ccontab_final_cargabal, ccontab_final) AS CHAVE_IT, FLAG_INST_TITULOS AS CAMPO_IT FROM CD_LOAN_TAPES_BCE.LT001_UNIV_OPER WHERE ref_date='${ref_date}' AND nome_perimetro='Individual Local' AND segmento='ESTR' AND ambito='PM' AND entidade='00100')X INNER JOIN (SELECT concat(cempresa, cbalcao, cnumecta, zdeposit, ccontab_final_ifrs, ccontab_final_pcsb, ccontab_final_cargabal, ccontab_final) AS CHAVE_SIMUL, FLAG_INST_TITULOS AS CAMPO_SIMUL FROM BU_LOANTAPE_WORK.LT001_UNIV_OPER WHERE ref_date='${ref_date}' AND nome_perimetro='Individual Local' AND segmento='ESTR' AND ambito='SRB_MBDT' AND entidade='00100')Y ON X.CHAVE_IT=Y.CHAVE_SIMUL
A27: =+B27&F27 -> INSTRUMENTGRSS_CRRYNG_AMNT_INSTRMNT | B27: INSTRUMENT | C27: Coerência | D27: =+UPPER('0. Instruções'!$D$35&"."&VLOOKUP(B27,'0. Instruções'!$C$27:$D$32,2,FALSE)) -> CD_LOAN_TAPES_BCE.LT002_INSTRUMENT | E27: =+UPPER('0. Instruções'!$D$36&"."&VLOOKUP(B27,'0. Instruções'!$C$27:$E$32,3,FALSE)) -> BU_LOANTAPE_WORK.LT002_INSTRUMENT | F27: GRSS_CRRYNG_AMNT_INSTRMNT | I27: ="(SELECT "&VLOOKUP(B27,'0. Instruções'!$C$27:$G$32,4,FALSE)&", "&F27&" FROM "&D27&" WHERE "&'0. Instruções'!$D$42&")X" -> (SELECT instrmnt_id, GRSS_CRRYNG_AMNT_INSTRMNT FROM CD_LOAN_TAPES_BCE.LT002_INSTRUMENT WHERE ref_date='${ref_date}' AND nome_perimetro='Individual Local' AND segmento='ESTR' AND ambito='SRB_MBDT' AND entidade='00100')X | J27: ="(SELECT "&VLOOKUP(B27,'0. Instruções'!$C$27:$G$32,4,FALSE)&" AS "&VLOOKUP(B27,'0. Instruções'!$C$27:$G$32,4,FALSE)&"_SIMUL, "&F27&" AS "&F27&"_SIMUL FROM "&E27&" WHERE "&'0. Instruções'!$D$43&")Y" -> (SELECT instrmnt_id AS instrmnt_id_SIMUL, GRSS_CRRYNG_AMNT_INSTRMNT AS GRSS_CRRYNG_AMNT_INSTRMNT_SIMUL FROM BU_LOANTAPE_WORK.LT002_INSTRUMENT WHERE ref_date='${ref_date}' AND nome_perimetro='Individual Local' AND segmento='ESTR' AND ambito='PM' AND entidade='00100')Y | K27: =+UPPER("ON X."&VLOOKUP(B27,'0. Instruções'!$C$27:$G$32,4,FALSE)&"=Y."&VLOOKUP(B27,'0. Instruções'!$C$27:$G$32,4,FALSE)&"_SIMUL") -> ON X.INSTRMNT_ID=Y.INSTRMNT_ID_SIMUL | L27: =+IF(C27="Coerência", +IF(LEFT(G27,5)="FLOAT","SELECT '"&UPPER(B27)&"' AS TABELA, '"&UPPER(C27)&"' AS TIPOLOGIA_TESTE,'"&D27&"' AS TABELA_LT,'"&E27&"' AS TABELA_SIMUL,'"&F27&"' AS CAMPO, "&"'${ref_date}' AS REF_DATE, COUNT(*) AS NUM_REG, SUM(IF((ABS(COALESCE(CAST(X."&F27&" AS DECIMAL(18,6)),0)-COALESCE(CAST(Y."&F27&"_SIMUL AS DECIMAL(18,6)),0))>0.000001) OR (X."&F27&" IS NULL AND Y."&F27&"_SIMUL IS NOT NULL ) OR (X."&F27&" IS NOT NULL AND Y."&F27&"_SIMUL IS NULL),1,0)) AS NUM_REG_DIF,'"&MAX('ID1&5'!K:K)+1&"' AS ID_EXEC, CURRENT_TIMESTAMP() AS TIME_EXEC FROM "&I27&" INNER JOIN "&J27&" "&K27,"SELECT '"&UPPER(B27)&"' AS TABELA, '"&UPPER(C27)&"' AS TIPOLOGIA_TESTE,'"&D27&"' AS TABELA_LT,'"&E27&"' AS TABELA_SIMUL,'"&F27&"' AS CAMPO, "&"'${ref_date}' AS REF_DATE, COUNT(*) AS NUM_REG, SUM(IF(COALESCE(CAST(X."&F27&" AS STRING),'')<>COALESCE(CAST(Y."&F27&"_SIMUL AS STRING),'') OR (X."&F27&" IS NULL AND Y."&F27&"_SIMUL IS NOT NULL ) OR (X."&F27&" IS NOT NULL AND Y."&F27&"_SIMUL IS NULL),1,0)) AS NUM_REG_DIF,'"&MAX('ID1&5'!L:L)+1&"' AS ID_EXEC, CURRENT_TIMESTAMP() AS TIME_EXEC FROM "&I27&" INNER JOIN "&J27&" "&K27), IF(C27="Validade",+IF(G27="Code List","SELECT '"&UPPER(B27)&"' AS TABELA, '"&UPPER(C27)&"' AS TIPOLOGIA_TESTE,'"&D27&"' AS TABELA_LT,'N/A' AS TABELA_SIMUL,'"&F27&"' AS CAMPO, "&"'${ref_date}' AS REF_DATE, COUNT(*) AS NUM_REG, SUM(IF(TRIM(CAST(X."&F27&" AS STRING))='' OR TRIM(CAST(X."&F27&" AS STRING)) IS NULL OR CAST(X."&F27&" AS STRING) NOT "&H27&",1,0)) AS NUM_REG_DIF,'"&MAX('ID1&5'!K:K)+1&"' AS ID_EXEC, CURRENT_TIMESTAMP() AS TIME_EXEC FROM "&I27,"SELECT '"&UPPER(B27)&"' AS TABELA, '"&UPPER(C27)&"' AS TIPOLOGIA_TESTE,'"&D27&"' AS TABELA_LT,'N/A' AS TABELA_SIMUL,'"&F27&"' AS CAMPO, "&"'${ref_date}' AS REF_DATE, COUNT(*) AS NUM_REG, SUM(IF(TRIM(CAST(X."&F27&" AS STRING))='' OR TRIM(CAST(X."&F27&" AS STRING)) IS NULL,1,0)) AS NUM_REG_DIF,'"&MAX('ID1&5'!K:K)+1&"' AS ID_EXEC, CURRENT_TIMESTAMP() AS TIME_EXEC FROM "&I27), IF(C27="Caracteres Especiais",+"SELECT '"&UPPER(B27)&"' AS TABELA, '"&UPPER(C27)&"' AS TIPOLOGIA_TESTE,'"&D27&"' AS TABELA_LT,'N/A' AS TABELA_SIMUL,'"&F27&"' AS CAMPO, "&"'${ref_date}' AS REF_DATE, COUNT(*) AS NUM_REG, SUM(IF(REGEXP_REPLACE(TRIM(CAST(X."&F27&" AS STRING)),'[^a-zA-Z0-9_\\s]','') <>TRIM(CAST(X."&F27&" AS STRING)),1,0)) AS NUM_REG_DIF,'"&MAX('ID1&5'!K:K)+1&"' AS ID_EXEC, CURRENT_TIMESTAMP() AS TIME_EXEC FROM "&I27, IF(C27="Missings",+"SELECT '"&UPPER(B27)&"' AS TABELA, '"&UPPER(C27)&"' AS TIPOLOGIA_TESTE,'"&D27&"' AS TABELA_LT,'N/A' AS TABELA_SIMUL,'"&F27&"' AS CAMPO, "&"'${ref_date}' AS REF_DATE, COUNT(*) AS NUM_REG, SUM(IF(TRIM(CAST(X."&F27&" AS STRING)) IN ('0000-00-00','0001-01-01','9999-12-31','MISS','00000','99999999999','99999999999.00','99999999999.000000'),1,0)) AS NUM_REG_DIF,'"&MAX('ID1&5'!K:K)+1&"' AS ID_EXEC, CURRENT_TIMESTAMP() AS TIME_EXEC FROM "&I27, IF(C27="Not applicable",+"SELECT '"&UPPER(B27)&"' AS TABELA, '"&UPPER(C27)&"' AS TIPOLOGIA_TESTE,'"&D27&"' AS TABELA_LT,'N/A' AS TABELA_SIMUL,'"&F27&"' AS CAMPO, "&"'${ref_date}' AS REF_DATE, COUNT(*) AS NUM_REG, SUM(IF(TRIM(CAST(X."&F27&" AS STRING)) IN ('N/A','11111111111','11111111111.00','11111111111.000000','1111-11-11'),1,0)) AS NUM_REG_DIF,'"&MAX('ID1&5'!K:K)+1&"' AS ID_EXEC, CURRENT_TIMESTAMP() AS TIME_EXEC FROM "&I27, IF(C27="Valores extremos",+"SELECT '"&UPPER(B27)&"' AS TABELA, '"&UPPER(C27)&"' AS TIPOLOGIA_TESTE,'"&D27&"' AS TABELA_LT,'N/A' AS TABELA_SIMUL,'"&F27&"' AS CAMPO, "&"'${ref_date}' AS REF_DATE, CAST(MIN("&F27&") AS STRING) AS VALOR_MIN, CAST(MAX("&F27&") AS STRING) AS VALOR_MAX,'"&MAX('ID1&5'!K:K)+1&"' AS ID_EXEC, CURRENT_TIMESTAMP() AS TIME_EXEC FROM "&MID(I27,1,LEN(I27)-2)&" AND CAST("&F27&" AS STRING) NOT IN ('0000-00-00','0001-01-01','9999-12-31','MISS','00000','99999999999','99999999999.00','99999999999.000000','N/A','11111111111','11111111111.00','11111111111.000000','1111-11-11'))X")))))) -> SELECT 'INSTRUMENT' AS TABELA, 'COERÊNCIA' AS TIPOLOGIA_TESTE,'CD_LOAN_TAPES_BCE.LT002_INSTRUMENT' AS TABELA_LT,'BU_LOANTAPE_WORK.LT002_INSTRUMENT' AS TABELA_SIMUL,'GRSS_CRRYNG_AMNT_INSTRMNT' AS CAMPO, '${ref_date}' AS REF_DATE, COUNT(*) AS NUM_REG, SUM(IF(COALESCE(CAST(X.GRSS_CRRYNG_AMNT_INSTRMNT AS STRING),'')<>COALESCE(CAST(Y.GRSS_CRRYNG_AMNT_INSTRMNT_SIMUL AS STRING),'') OR (X.GRSS_CRRYNG_AMNT_INSTRMNT IS NULL AND Y.GRSS_CRRYNG_AMNT_INSTRMNT_SIMUL IS NOT NULL ) OR (X.GRSS_CRRYNG_AMNT_INSTRMNT IS NOT NULL AND Y.GRSS_CRRYNG_AMNT_INSTRMNT_SIMUL IS NULL),1,0)) AS NUM_REG_DIF,'1' AS ID_EXEC, CURRENT_TIMESTAMP() AS TIME_EXEC FROM (SELECT instrmnt_id, GRSS_CRRYNG_AMNT_INSTRMNT FROM CD_LOAN_TAPES_BCE.LT002_INSTRUMENT WHERE ref_date='${ref_date}' AND nome_perimetro='Individual Local' AND segmento='ESTR' AND ambito='SRB_MBDT' AND entidade='00100')X INNER JOIN (SELECT instrmnt_id AS instrmnt_id_SIMUL, GRSS_CRRYNG_AMNT_INSTRMNT AS GRSS_CRRYNG_AMNT_INSTRMNT_SIMUL FROM BU_LOANTAPE_WORK.LT002_INSTRUMENT WHERE ref_date='${ref_date}' AND nome_perimetro='Individual Local' AND segmento='ESTR' AND ambito='PM' AND entidade='00100')Y ON X.INSTRMNT_ID=Y.INSTRMNT_ID_SIMUL | M27: =+"UNION ALL "&L27 -> UNION ALL SELECT 'INSTRUMENT' AS TABELA, 'COERÊNCIA' AS TIPOLOGIA_TESTE,'CD_LOAN_TAPES_BCE.LT002_INSTRUMENT' AS TABELA_LT,'BU_LOANTAPE_WORK.LT002_INSTRUMENT' AS TABELA_SIMUL,'GRSS_CRRYNG_AMNT_INSTRMNT' AS CAMPO, '${ref_date}' AS REF_DATE, COUNT(*) AS NUM_REG, SUM(IF(COALESCE(CAST(X.GRSS_CRRYNG_AMNT_INSTRMNT AS STRING),'')<>COALESCE(CAST(Y.GRSS_CRRYNG_AMNT_INSTRMNT_SIMUL AS STRING),'') OR (X.GRSS_CRRYNG_AMNT_INSTRMNT IS NULL AND Y.GRSS_CRRYNG_AMNT_INSTRMNT_SIMUL IS NOT NULL ) OR (X.GRSS_CRRYNG_AMNT_INSTRMNT IS NOT NULL AND Y.GRSS_CRRYNG_AMNT_INSTRMNT_SIMUL IS NULL),1,0)) AS NUM_REG_DIF,'1' AS ID_EXEC, CURRENT_TIMESTAMP() AS TIME_EXEC FROM (SELECT instrmnt_id, GRSS_CRRYNG_AMNT_INSTRMNT FROM CD_LOAN_TAPES_BCE.LT002_INSTRUMENT WHERE ref_date='${ref_date}' AND nome_perimetro='Individual Local' AND segmento='ESTR' AND ambito='SRB_MBDT' AND entidade='00100')X INNER JOIN (SELECT instrmnt_id AS instrmnt_id_SIMUL, GRSS_CRRYNG_AMNT_INSTRMNT AS GRSS_CRRYNG_AMNT_INSTRMNT_SIMUL FROM BU_LOANTAPE_WORK.LT002_INSTRUMENT WHERE ref_date='${ref_date}' AND nome_perimetro='Individual Local' AND segmento='ESTR' AND ambito='PM' AND entidade='00100')Y ON X.INSTRMNT_ID=Y.INSTRMNT_ID_SIMUL
A28: =+B28&F28 -> INSTRUMENTINTRNL_RTNG | B28: INSTRUMENT | C28: Coerência | D28: =+UPPER('0. Instruções'!$D$35&"."&VLOOKUP(B28,'0. Instruções'!$C$27:$D$32,2,FALSE)) -> CD_LOAN_TAPES_BCE.LT002_INSTRUMENT | E28: =+UPPER('0. Instruções'!$D$36&"."&VLOOKUP(B28,'0. Instruções'!$C$27:$E$32,3,FALSE)) -> BU_LOANTAPE_WORK.LT002_INSTRUMENT | F28: INTRNL_RTNG | I28: ="(SELECT "&VLOOKUP(B28,'0. Instruções'!$C$27:$G$32,4,FALSE)&", "&F28&" FROM "&D28&" WHERE "&'0. Instruções'!$D$42&")X" -> (SELECT instrmnt_id, INTRNL_RTNG FROM CD_LOAN_TAPES_BCE.LT002_INSTRUMENT WHERE ref_date='${ref_date}' AND nome_perimetro='Individual Local' AND segmento='ESTR' AND ambito='SRB_MBDT' AND entidade='00100')X | J28: ="(SELECT "&VLOOKUP(B28,'0. Instruções'!$C$27:$G$32,4,FALSE)&" AS "&VLOOKUP(B28,'0. Instruções'!$C$27:$G$32,4,FALSE)&"_SIMUL, "&F28&" AS "&F28&"_SIMUL FROM "&E28&" WHERE "&'0. Instruções'!$D$43&")Y" -> (SELECT instrmnt_id AS instrmnt_id_SIMUL, INTRNL_RTNG AS INTRNL_RTNG_SIMUL FROM BU_LOANTAPE_WORK.LT002_INSTRUMENT WHERE ref_date='${ref_date}' AND nome_perimetro='Individual Local' AND segmento='ESTR' AND ambito='PM' AND entidade='00100')Y | K28: =+UPPER("ON X."&VLOOKUP(B28,'0. Instruções'!$C$27:$G$32,4,FALSE)&"=Y."&VLOOKUP(B28,'0. Instruções'!$C$27:$G$32,4,FALSE)&"_SIMUL") -> ON X.INSTRMNT_ID=Y.INSTRMNT_ID_SIMUL | L28: =+IF(C28="Coerência", +IF(LEFT(G28,5)="FLOAT","SELECT '"&UPPER(B28)&"' AS TABELA, '"&UPPER(C28)&"' AS TIPOLOGIA_TESTE,'"&D28&"' AS TABELA_LT,'"&E28&"' AS TABELA_SIMUL,'"&F28&"' AS CAMPO, "&"'${ref_date}' AS REF_DATE, COUNT(*) AS NUM_REG, SUM(IF((ABS(COALESCE(CAST(X."&F28&" AS DECIMAL(18,6)),0)-COALESCE(CAST(Y."&F28&"_SIMUL AS DECIMAL(18,6)),0))>0.000001) OR (X."&F28&" IS NULL AND Y."&F28&"_SIMUL IS NOT NULL ) OR (X."&F28&" IS NOT NULL AND Y."&F28&"_SIMUL IS NULL),1,0)) AS NUM_REG_DIF,'"&MAX('ID1&5'!K:K)+1&"' AS ID_EXEC, CURRENT_TIMESTAMP() AS TIME_EXEC FROM "&I28&" INNER JOIN "&J28&" "&K28,"SELECT '"&UPPER(B28)&"' AS TABELA, '"&UPPER(C28)&"' AS TIPOLOGIA_TESTE,'"&D28&"' AS TABELA_LT,'"&E28&"' AS TABELA_SIMUL,'"&F28&"' AS CAMPO, "&"'${ref_date}' AS REF_DATE, COUNT(*) AS NUM_REG, SUM(IF(COALESCE(CAST(X."&F28&" AS STRING),'')<>COALESCE(CAST(Y."&F28&"_SIMUL AS STRING),'') OR (X."&F28&" IS NULL AND Y."&F28&"_SIMUL IS NOT NULL ) OR (X."&F28&" IS NOT NULL AND Y."&F28&"_SIMUL IS NULL),1,0)) AS NUM_REG_DIF,'"&MAX('ID1&5'!L:L)+1&"' AS ID_EXEC, CURRENT_TIMESTAMP() AS TIME_EXEC FROM "&I28&" INNER JOIN "&J28&" "&K28), IF(C28="Validade",+IF(G28="Code List","SELECT '"&UPPER(B28)&"' AS TABELA, '"&UPPER(C28)&"' AS TIPOLOGIA_TESTE,'"&D28&"' AS TABELA_LT,'N/A' AS TABELA_SIMUL,'"&F28&"' AS CAMPO, "&"'${ref_date}' AS REF_DATE, COUNT(*) AS NUM_REG, SUM(IF(TRIM(CAST(X."&F28&" AS STRING))='' OR TRIM(CAST(X."&F28&" AS STRING)) IS NULL OR CAST(X."&F28&" AS STRING) NOT "&H28&",1,0)) AS NUM_REG_DIF,'"&MAX('ID1&5'!K:K)+1&"' AS ID_EXEC, CURRENT_TIMESTAMP() AS TIME_EXEC FROM "&I28,"SELECT '"&UPPER(B28)&"' AS TABELA, '"&UPPER(C28)&"' AS TIPOLOGIA_TESTE,'"&D28&"' AS TABELA_LT,'N/A' AS TABELA_SIMUL,'"&F28&"' AS CAMPO, "&"'${ref_date}' AS REF_DATE, COUNT(*) AS NUM_REG, SUM(IF(TRIM(CAST(X."&F28&" AS STRING))='' OR TRIM(CAST(X."&F28&" AS STRING)) IS NULL,1,0)) AS NUM_REG_DIF,'"&MAX('ID1&5'!K:K)+1&"' AS ID_EXEC, CURRENT_TIMESTAMP() AS TIME_EXEC FROM "&I28), IF(C28="Caracteres Especiais",+"SELECT '"&UPPER(B28)&"' AS TABELA, '"&UPPER(C28)&"' AS TIPOLOGIA_TESTE,'"&D28&"' AS TABELA_LT,'N/A' AS TABELA_SIMUL,'"&F28&"' AS CAMPO, "&"'${ref_date}' AS REF_DATE, COUNT(*) AS NUM_REG, SUM(IF(REGEXP_REPLACE(TRIM(CAST(X."&F28&" AS STRING)),'[^a-zA-Z0-9_\\s]','') <>TRIM(CAST(X."&F28&" AS STRING)),1,0)) AS NUM_REG_DIF,'"&MAX('ID1&5'!K:K)+1&"' AS ID_EXEC, CURRENT_TIMESTAMP() AS TIME_EXEC FROM "&I28, IF(C28="Missings",+"SELECT '"&UPPER(B28)&"' AS TABELA, '"&UPPER(C28)&"' AS TIPOLOGIA_TESTE,'"&D28&"' AS TABELA_LT,'N/A' AS TABELA_SIMUL,'"&F28&"' AS CAMPO, "&"'${ref_date}' AS REF_DATE, COUNT(*) AS NUM_REG, SUM(IF(TRIM(CAST(X."&F28&" AS STRING)) IN ('0000-00-00','0001-01-01','9999-12-31','MISS','00000','99999999999','99999999999.00','99999999999.000000'),1,0)) AS NUM_REG_DIF,'"&MAX('ID1&5'!K:K)+1&"' AS ID_EXEC, CURRENT_TIMESTAMP() AS TIME_EXEC FROM "&I28, IF(C28="Not applicable",+"SELECT '"&UPPER(B28)&"' AS TABELA, '"&UPPER(C28)&"' AS TIPOLOGIA_TESTE,'"&D28&"' AS TABELA_LT,'N/A' AS TABELA_SIMUL,'"&F28&"' AS CAMPO, "&"'${ref_date}' AS REF_DATE, COUNT(*) AS NUM_REG, SUM(IF(TRIM(CAST(X."&F28&" AS STRING)) IN ('N/A','11111111111','11111111111.00','11111111111.000000','1111-11-11'),1,0)) AS NUM_REG_DIF,'"&MAX('ID1&5'!K:K)+1&"' AS ID_EXEC, CURRENT_TIMESTAMP() AS TIME_EXEC FROM "&I28, IF(C28="Valores extremos",+"SELECT '"&UPPER(B28)&"' AS TABELA, '"&UPPER(C28)&"' AS TIPOLOGIA_TESTE,'"&D28&"' AS TABELA_LT,'N/A' AS TABELA_SIMUL,'"&F28&"' AS CAMPO, "&"'${ref_date}' AS REF_DATE, CAST(MIN("&F28&") AS STRING) AS VALOR_MIN, CAST(MAX("&F28&") AS STRING) AS VALOR_MAX,'"&MAX('ID1&5'!K:K)+1&"' AS ID_EXEC, CURRENT_TIMESTAMP() AS TIME_EXEC FROM "&MID(I28,1,LEN(I28)-2)&" AND CAST("&F28&" AS STRING) NOT IN ('0000-00-00','0001-01-01','9999-12-31','MISS','00000','99999999999','99999999999.00','99999999999.000000','N/A','11111111111','11111111111.00','11111111111.000000','1111-11-11'))X")))))) -> SELECT 'INSTRUMENT' AS TABELA, 'COERÊNCIA' AS TIPOLOGIA_TESTE,'CD_LOAN_TAPES_BCE.LT002_INSTRUMENT' AS TABELA_LT,'BU_LOANTAPE_WORK.LT002_INSTRUMENT' AS TABELA_SIMUL,'INTRNL_RTNG' AS CAMPO, '${ref_date}' AS REF_DATE, COUNT(*) AS NUM_REG, SUM(IF(COALESCE(CAST(X.INTRNL_RTNG AS STRING),'')<>COALESCE(CAST(Y.INTRNL_RTNG_SIMUL AS STRING),'') OR (X.INTRNL_RTNG IS NULL AND Y.INTRNL_RTNG_SIMUL IS NOT NULL ) OR (X.INTRNL_RTNG IS NOT NULL AND Y.INTRNL_RTNG_SIMUL IS NULL),1,0)) AS NUM_REG_DIF,'1' AS ID_EXEC, CURRENT_TIMESTAMP() AS TIME_EXEC FROM (SELECT instrmnt_id, INTRNL_RTNG FROM CD_LOAN_TAPES_BCE.LT002_INSTRUMENT WHERE ref_date='${ref_date}' AND nome_perimetro='Individual Local' AND segmento='ESTR' AND ambito='SRB_MBDT' AND entidade='00100')X INNER JOIN (SELECT instrmnt_id AS instrmnt_id_SIMUL, INTRNL_RTNG AS INTRNL_RTNG_SIMUL FROM BU_LOANTAPE_WORK.LT002_INSTRUMENT WHERE ref_date='${ref_date}' AND nome_perimetro='Individual Local' AND segmento='ESTR' AND ambito='PM' AND entidade='00100')Y ON X.INSTRMNT_ID=Y.INSTRMNT_ID_SIMUL | M28: =+"UNION ALL "&L28 -> UNION ALL SELECT 'INSTRUMENT' AS TABELA, 'COERÊNCIA' AS TIPOLOGIA_TESTE,'CD_LOAN_TAPES_BCE.LT002_INSTRUMENT' AS TABELA_LT,'BU_LOANTAPE_WORK.LT002_INSTRUMENT' AS TABELA_SIMUL,'INTRNL_RTNG' AS CAMPO, '${ref_date}' AS REF_DATE, COUNT(*) AS NUM_REG, SUM(IF(COALESCE(CAST(X.INTRNL_RTNG AS STRING),'')<>COALESCE(CAST(Y.INTRNL_RTNG_SIMUL AS STRING),'') OR (X.INTRNL_RTNG IS NULL AND Y.INTRNL_RTNG_SIMUL IS NOT NULL ) OR (X.INTRNL_RTNG IS NOT NULL AND Y.INTRNL_RTNG_SIMUL IS NULL),1,0)) AS NUM_REG_DIF,'1' AS ID_EXEC, CURRENT_TIMESTAMP() AS TIME_EXEC FROM (SELECT instrmnt_id, INTRNL_RTNG FROM CD_LOAN_TAPES_BCE.LT002_INSTRUMENT WHERE ref_date='${ref_date}' AND nome_perimetro='Individual Local' AND segmento='ESTR' AND ambito='SRB_MBDT' AND entidade='00100')X INNER JOIN (SELECT instrmnt_id AS instrmnt_id_SIMUL, INTRNL_RTNG AS INTRNL_RTNG_SIMUL FROM BU_LOANTAPE_WORK.LT002_INSTRUMENT WHERE ref_date='${ref_date}' AND nome_perimetro='Individual Local' AND segmento='ESTR' AND ambito='PM' AND entidade='00100')Y ON X.INSTRMNT_ID=Y.INSTRMNT_ID_SIMUL
A29: =+B29&F29 -> INSTRUMENTOTSTNDNG_NMNL_AMNT_INSTRMNT | B29: INSTRUMENT | C29: Coerência | D29: =+UPPER('0. Instruções'!$D$35&"."&VLOOKUP(B29,'0. Instruções'!$C$27:$D$32,2,FALSE)) -> CD_LOAN_TAPES_BCE.LT002_INSTRUMENT | E29: =+UPPER('0. Instruções'!$D$36&"."&VLOOKUP(B29,'0. Instruções'!$C$27:$E$32,3,FALSE)) -> BU_LOANTAPE_WORK.LT002_INSTRUMENT | F29: OTSTNDNG_NMNL_AMNT_INSTRMNT | I29: ="(SELECT "&VLOOKUP(B29,'0. Instruções'!$C$27:$G$32,4,FALSE)&", "&F29&" FROM "&D29&" WHERE "&'0. Instruções'!$D$42&")X" -> (SELECT instrmnt_id, OTSTNDNG_NMNL_AMNT_INSTRMNT FROM CD_LOAN_TAPES_BCE.LT002_INSTRUMENT WHERE ref_date='${ref_date}' AND nome_perimetro='Individual Local' AND segmento='ESTR' AND ambito='SRB_MBDT' AND entidade='00100')X | J29: ="(SELECT "&VLOOKUP(B29,'0. Instruções'!$C$27:$G$32,4,FALSE)&" AS "&VLOOKUP(B29,'0. Instruções'!$C$27:$G$32,4,FALSE)&"_SIMUL, "&F29&" AS "&F29&"_SIMUL FROM "&E29&" WHERE "&'0. Instruções'!$D$43&")Y" -> (SELECT instrmnt_id AS instrmnt_id_SIMUL, OTSTNDNG_NMNL_AMNT_INSTRMNT AS OTSTNDNG_NMNL_AMNT_INSTRMNT_SIMUL FROM BU_LOANTAPE_WORK.LT002_INSTRUMENT WHERE ref_date='${ref_date}' AND nome_perimetro='Individual Local' AND segmento='ESTR' AND ambito='PM' AND entidade='00100')Y | K29: =+UPPER("ON X."&VLOOKUP(B29,'0. Instruções'!$C$27:$G$32,4,FALSE)&"=Y."&VLOOKUP(B29,'0. Instruções'!$C$27:$G$32,4,FALSE)&"_SIMUL") -> ON X.INSTRMNT_ID=Y.INSTRMNT_ID_SIMUL | L29: =+IF(C29="Coerência", +IF(LEFT(G29,5)="FLOAT","SELECT '"&UPPER(B29)&"' AS TABELA, '"&UPPER(C29)&"' AS TIPOLOGIA_TESTE,'"&D29&"' AS TABELA_LT,'"&E29&"' AS TABELA_SIMUL,'"&F29&"' AS CAMPO, "&"'${ref_date}' AS REF_DATE, COUNT(*) AS NUM_REG, SUM(IF((ABS(COALESCE(CAST(X."&F29&" AS DECIMAL(18,6)),0)-COALESCE(CAST(Y."&F29&"_SIMUL AS DECIMAL(18,6)),0))>0.000001) OR (X."&F29&" IS NULL AND Y."&F29&"_SIMUL IS NOT NULL ) OR (X."&F29&" IS NOT NULL AND Y."&F29&"_SIMUL IS NULL),1,0)) AS NUM_REG_DIF,'"&MAX('ID1&5'!K:K)+1&"' AS ID_EXEC, CURRENT_TIMESTAMP() AS TIME_EXEC FROM "&I29&" INNER JOIN "&J29&" "&K29,"SELECT '"&UPPER(B29)&"' AS TABELA, '"&UPPER(C29)&"' AS TIPOLOGIA_TESTE,'"&D29&"' AS TABELA_LT,'"&E29&"' AS TABELA_SIMUL,'"&F29&"' AS CAMPO, "&"'${ref_date}' AS REF_DATE, COUNT(*) AS NUM_REG, SUM(IF(COALESCE(CAST(X."&F29&" AS STRING),'')<>COALESCE(CAST(Y."&F29&"_SIMUL AS STRING),'') OR (X."&F29&" IS NULL AND Y."&F29&"_SIMUL IS NOT NULL ) OR (X."&F29&" IS NOT NULL AND Y."&F29&"_SIMUL IS NULL),1,0)) AS NUM_REG_DIF,'"&MAX('ID1&5'!L:L)+1&"' AS ID_EXEC, CURRENT_TIMESTAMP() AS TIME_EXEC FROM "&I29&" INNER JOIN "&J29&" "&K29), IF(C29="Validade",+IF(G29="Code List","SELECT '"&UPPER(B29)&"' AS TABELA, '"&UPPER(C29)&"' AS TIPOLOGIA_TESTE,'"&D29&"' AS TABELA_LT,'N/A' AS TABELA_SIMUL,'"&F29&"' AS CAMPO, "&"'${ref_date}' AS REF_DATE, COUNT(*) AS NUM_REG, SUM(IF(TRIM(CAST(X."&F29&" AS STRING))='' OR TRIM(CAST(X."&F29&" AS STRING)) IS NULL OR CAST(X."&F29&" AS STRING) NOT "&H29&",1,0)) AS NUM_REG_DIF,'"&MAX('ID1&5'!K:K)+1&"' AS ID_EXEC, CURRENT_TIMESTAMP() AS TIME_EXEC FROM "&I29,"SELECT '"&UPPER(B29)&"' AS TABELA, '"&UPPER(C29)&"' AS TIPOLOGIA_TESTE,'"&D29&"' AS TABELA_LT,'N/A' AS TABELA_SIMUL,'"&F29&"' AS CAMPO, "&"'${ref_date}' AS REF_DATE, COUNT(*) AS NUM_REG, SUM(IF(TRIM(CAST(X."&F29&" AS STRING))='' OR TRIM(CAST(X."&F29&" AS STRING)) IS NULL,1,0)) AS NUM_REG_DIF,'"&MAX('ID1&5'!K:K)+1&"' AS ID_EXEC, CURRENT_TIMESTAMP() AS TIME_EXEC FROM "&I29), IF(C29="Caracteres Especiais",+"SELECT '"&UPPER(B29)&"' AS TABELA, '"&UPPER(C29)&"' AS TIPOLOGIA_TESTE,'"&D29&"' AS TABELA_LT,'N/A' AS TABELA_SIMUL,'"&F29&"' AS CAMPO, "&"'${ref_date}' AS REF_DATE, COUNT(*) AS NUM_REG, SUM(IF(REGEXP_REPLACE(TRIM(CAST(X."&F29&" AS STRING)),'[^a-zA-Z0-9_\\s]','') <>TRIM(CAST(X."&F29&" AS STRING)),1,0)) AS NUM_REG_DIF,'"&MAX('ID1&5'!K:K)+1&"' AS ID_EXEC, CURRENT_TIMESTAMP() AS TIME_EXEC FROM "&I29, IF(C29="Missings",+"SELECT '"&UPPER(B29)&"' AS TABELA, '"&UPPER(C29)&"' AS TIPOLOGIA_TESTE,'"&D29&"' AS TABELA_LT,'N/A' AS TABELA_SIMUL,'"&F29&"' AS CAMPO, "&"'${ref_date}' AS REF_DATE, COUNT(*) AS NUM_REG, SUM(IF(TRIM(CAST(X."&F29&" AS STRING)) IN ('0000-00-00','0001-01-01','9999-12-31','MISS','00000','99999999999','99999999999.00','99999999999.000000'),1,0)) AS NUM_REG_DIF,'"&MAX('ID1&5'!K:K)+1&"' AS ID_EXEC, CURRENT_TIMESTAMP() AS TIME_EXEC FROM "&I29, IF(C29="Not applicable",+"SELECT '"&UPPER(B29)&"' AS TABELA, '"&UPPER(C29)&"' AS TIPOLOGIA_TESTE,'"&D29&"' AS TABELA_LT,'N/A' AS TABELA_SIMUL,'"&F29&"' AS CAMPO, "&"'${ref_date}' AS REF_DATE, COUNT(*) AS NUM_REG, SUM(IF(TRIM(CAST(X."&F29&" AS STRING)) IN ('N/A','11111111111','11111111111.00','11111111111.000000','1111-11-11'),1,0)) AS NUM_REG_DIF,'"&MAX('ID1&5'!K:K)+1&"' AS ID_EXEC, CURRENT_TIMESTAMP() AS TIME_EXEC FROM "&I29, IF(C29="Valores extremos",+"SELECT '"&UPPER(B29)&"' AS TABELA, '"&UPPER(C29)&"' AS TIPOLOGIA_TESTE,'"&D29&"' AS TABELA_LT,'N/A' AS TABELA_SIMUL,'"&F29&"' AS CAMPO, "&"'${ref_date}' AS REF_DATE, CAST(MIN("&F29&") AS STRING) AS VALOR_MIN, CAST(MAX("&F29&") AS STRING) AS VALOR_MAX,'"&MAX('ID1&5'!K:K)+1&"' AS ID_EXEC, CURRENT_TIMESTAMP() AS TIME_EXEC FROM "&MID(I29,1,LEN(I29)-2)&" AND CAST("&F29&" AS STRING) NOT IN ('0000-00-00','0001-01-01','9999-12-31','MISS','00000','99999999999','99999999999.00','99999999999.000000','N/A','11111111111','11111111111.00','11111111111.000000','1111-11-11'))X")))))) -> SELECT 'INSTRUMENT' AS TABELA, 'COERÊNCIA' AS TIPOLOGIA_TESTE,'CD_LOAN_TAPES_BCE.LT002_INSTRUMENT' AS TABELA_LT,'BU_LOANTAPE_WORK.LT002_INSTRUMENT' AS TABELA_SIMUL,'OTSTNDNG_NMNL_AMNT_INSTRMNT' AS CAMPO, '${ref_date}' AS REF_DATE, COUNT(*) AS NUM_REG, SUM(IF(COALESCE(CAST(X.OTSTNDNG_NMNL_AMNT_INSTRMNT AS STRING),'')<>COALESCE(CAST(Y.OTSTNDNG_NMNL_AMNT_INSTRMNT_SIMUL AS STRING),'') OR (X.OTSTNDNG_NMNL_AMNT_INSTRMNT IS NULL AND Y.OTSTNDNG_NMNL_AMNT_INSTRMNT_SIMUL IS NOT NULL ) OR (X.OTSTNDNG_NMNL_AMNT_INSTRMNT IS NOT NULL AND Y.OTSTNDNG_NMNL_AMNT_INSTRMNT_SIMUL IS NULL),1,0)) AS NUM_REG_DIF,'1' AS ID_EXEC, CURRENT_TIMESTAMP() AS TIME_EXEC FROM (SELECT instrmnt_id, OTSTNDNG_NMNL_AMNT_INSTRMNT FROM CD_LOAN_TAPES_BCE.LT002_INSTRUMENT WHERE ref_date='${ref_date}' AND nome_perimetro='Individual Local' AND segmento='ESTR' AND ambito='SRB_MBDT' AND entidade='00100')X INNER JOIN (SELECT instrmnt_id AS instrmnt_id_SIMUL, OTSTNDNG_NMNL_AMNT_INSTRMNT AS OTSTNDNG_NMNL_AMNT_INSTRMNT_SIMUL FROM BU_LOANTAPE_WORK.LT002_INSTRUMENT WHERE ref_date='${ref_date}' AND nome_perimetro='Individual Local' AND segmento='ESTR' AND ambito='PM' AND entidade='00100')Y ON X.INSTRMNT_ID=Y.INSTRMNT_ID_SIMUL | M29: =+"UNION ALL "&L29 -> UNION ALL SELECT 'INSTRUMENT' AS TABELA, 'COERÊNCIA' AS TIPOLOGIA_TESTE,'CD_LOAN_TAPES_BCE.LT002_INSTRUMENT' AS TABELA_LT,'BU_LOANTAPE_WORK.LT002_INSTRUMENT' AS TABELA_SIMUL,'OTSTNDNG_NMNL_AMNT_INSTRMNT' AS CAMPO, '${ref_date}' AS REF_DATE, COUNT(*) AS NUM_REG, SUM(IF(COALESCE(CAST(X.OTSTNDNG_NMNL_AMNT_INSTRMNT AS STRING),'')<>COALESCE(CAST(Y.OTSTNDNG_NMNL_AMNT_INSTRMNT_SIMUL AS STRING),'') OR (X.OTSTNDNG_NMNL_AMNT_INSTRMNT IS NULL AND Y.OTSTNDNG_NMNL_AMNT_INSTRMNT_SIMUL IS NOT NULL ) OR (X.OTSTNDNG_NMNL_AMNT_INSTRMNT IS NOT NULL AND Y.OTSTNDNG_NMNL_AMNT_INSTRMNT_SIMUL IS NULL),1,0)) AS NUM_REG_DIF,'1' AS ID_EXEC, CURRENT_TIMESTAMP() AS TIME_EXEC FROM (SELECT instrmnt_id, OTSTNDNG_NMNL_AMNT_INSTRMNT FROM CD_LOAN_TAPES_BCE.LT002_INSTRUMENT WHERE ref_date='${ref_date}' AND nome_perimetro='Individual Local' AND segmento='ESTR' AND ambito='SRB_MBDT' AND entidade='00100')X INNER JOIN (SELECT instrmnt_id AS instrmnt_id_SIMUL, OTSTNDNG_NMNL_AMNT_INSTRMNT AS OTSTNDNG_NMNL_AMNT_INSTRMNT_SIMUL FROM BU_LOANTAPE_WORK.LT002_INSTRUMENT WHERE ref_date='${ref_date}' AND nome_perimetro='Individual Local' AND segmento='ESTR' AND ambito='PM' AND entidade='00100')Y ON X.INSTRMNT_ID=Y.INSTRMNT_ID_SIMUL
A30: =+B30&F30 -> INSTRUMENTPRDCT | B30: INSTRUMENT | C30: Coerência | D30: =+UPPER('0. Instruções'!$D$35&"."&VLOOKUP(B30,'0. Instruções'!$C$27:$D$32,2,FALSE)) -> CD_LOAN_TAPES_BCE.LT002_INSTRUMENT | E30: =+UPPER('0. Instruções'!$D$36&"."&VLOOKUP(B30,'0. Instruções'!$C$27:$E$32,3,FALSE)) -> BU_LOANTAPE_WORK.LT002_INSTRUMENT | F30: PRDCT | I30: ="(SELECT "&VLOOKUP(B30,'0. Instruções'!$C$27:$G$32,4,FALSE)&", "&F30&" FROM "&D30&" WHERE "&'0. Instruções'!$D$42&")X" -> (SELECT instrmnt_id, PRDCT FROM CD_LOAN_TAPES_BCE.LT002_INSTRUMENT WHERE ref_date='${ref_date}' AND nome_perimetro='Individual Local' AND segmento='ESTR' AND ambito='SRB_MBDT' AND entidade='00100')X | J30: ="(SELECT "&VLOOKUP(B30,'0. Instruções'!$C$27:$G$32,4,FALSE)&" AS "&VLOOKUP(B30,'0. Instruções'!$C$27:$G$32,4,FALSE)&"_SIMUL, "&F30&" AS "&F30&"_SIMUL FROM "&E30&" WHERE "&'0. Instruções'!$D$43&")Y" -> (SELECT instrmnt_id AS instrmnt_id_SIMUL, PRDCT AS PRDCT_SIMUL FROM BU_LOANTAPE_WORK.LT002_INSTRUMENT WHERE ref_date='${ref_date}' AND nome_perimetro='Individual Local' AND segmento='ESTR' AND ambito='PM' AND entidade='00100')Y | K30: =+UPPER("ON X."&VLOOKUP(B30,'0. Instruções'!$C$27:$G$32,4,FALSE)&"=Y."&VLOOKUP(B30,'0. Instruções'!$C$27:$G$32,4,FALSE)&"_SIMUL") -> ON X.INSTRMNT_ID=Y.INSTRMNT_ID_SIMUL | L30: =+IF(C30="Coerência", +IF(LEFT(G30,5)="FLOAT","SELECT '"&UPPER(B30)&"' AS TABELA, '"&UPPER(C30)&"' AS TIPOLOGIA_TESTE,'"&D30&"' AS TABELA_LT,'"&E30&"' AS TABELA_SIMUL,'"&F30&"' AS CAMPO, "&"'${ref_date}' AS REF_DATE, COUNT(*) AS NUM_REG, SUM(IF((ABS(COALESCE(CAST(X."&F30&" AS DECIMAL(18,6)),0)-COALESCE(CAST(Y."&F30&"_SIMUL AS DECIMAL(18,6)),0))>0.000001) OR (X."&F30&" IS NULL AND Y."&F30&"_SIMUL IS NOT NULL ) OR (X."&F30&" IS NOT NULL AND Y."&F30&"_SIMUL IS NULL),1,0)) AS NUM_REG_DIF,'"&MAX('ID1&5'!K:K)+1&"' AS ID_EXEC, CURRENT_TIMESTAMP() AS TIME_EXEC FROM "&I30&" INNER JOIN "&J30&" "&K30,"SELECT '"&UPPER(B30)&"' AS TABELA, '"&UPPER(C30)&"' AS TIPOLOGIA_TESTE,'"&D30&"' AS TABELA_LT,'"&E30&"' AS TABELA_SIMUL,'"&F30&"' AS CAMPO, "&"'${ref_date}' AS REF_DATE, COUNT(*) AS NUM_REG, SUM(IF(COALESCE(CAST(X."&F30&" AS STRING),'')<>COALESCE(CAST(Y."&F30&"_SIMUL AS STRING),'') OR (X."&F30&" IS NULL AND Y."&F30&"_SIMUL IS NOT NULL ) OR (X."&F30&" IS NOT NULL AND Y."&F30&"_SIMUL IS NULL),1,0)) AS NUM_REG_DIF,'"&MAX('ID1&5'!L:L)+1&"' AS ID_EXEC, CURRENT_TIMESTAMP() AS TIME_EXEC FROM "&I30&" INNER JOIN "&J30&" "&K30), IF(C30="Validade",+IF(G30="Code List","SELECT '"&UPPER(B30)&"' AS TABELA, '"&UPPER(C30)&"' AS TIPOLOGIA_TESTE,'"&D30&"' AS TABELA_LT,'N/A' AS TABELA_SIMUL,'"&F30&"' AS CAMPO, "&"'${ref_date}' AS REF_DATE, COUNT(*) AS NUM_REG, SUM(IF(TRIM(CAST(X."&F30&" AS STRING))='' OR TRIM(CAST(X."&F30&" AS STRING)) IS NULL OR CAST(X."&F30&" AS STRING) NOT "&H30&",1,0)) AS NUM_REG_DIF,'"&MAX('ID1&5'!K:K)+1&"' AS ID_EXEC, CURRENT_TIMESTAMP() AS TIME_EXEC FROM "&I30,"SELECT '"&UPPER(B30)&"' AS TABELA, '"&UPPER(C30)&"' AS TIPOLOGIA_TESTE,'"&D30&"' AS TABELA_LT,'N/A' AS TABELA_SIMUL,'"&F30&"' AS CAMPO, "&"'${ref_date}' AS REF_DATE, COUNT(*) AS NUM_REG, SUM(IF(TRIM(CAST(X."&F30&" AS STRING))='' OR TRIM(CAST(X."&F30&" AS STRING)) IS NULL,1,0)) AS NUM_REG_DIF,'"&MAX('ID1&5'!K:K)+1&"' AS ID_EXEC, CURRENT_TIMESTAMP() AS TIME_EXEC FROM "&I30), IF(C30="Caracteres Especiais",+"SELECT '"&UPPER(B30)&"' AS TABELA, '"&UPPER(C30)&"' AS TIPOLOGIA_TESTE,'"&D30&"' AS TABELA_LT,'N/A' AS TABELA_SIMUL,'"&F30&"' AS CAMPO, "&"'${ref_date}' AS REF_DATE, COUNT(*) AS NUM_REG, SUM(IF(REGEXP_REPLACE(TRIM(CAST(X."&F30&" AS STRING)),'[^a-zA-Z0-9_\\s]','') <>TRIM(CAST(X."&F30&" AS STRING)),1,0)) AS NUM_REG_DIF,'"&MAX('ID1&5'!K:K)+1&"' AS ID_EXEC, CURRENT_TIMESTAMP() AS TIME_EXEC FROM "&I30, IF(C30="Missings",+"SELECT '"&UPPER(B30)&"' AS TABELA, '"&UPPER(C30)&"' AS TIPOLOGIA_TESTE,'"&D30&"' AS TABELA_LT,'N/A' AS TABELA_SIMUL,'"&F30&"' AS CAMPO, "&"'${ref_date}' AS REF_DATE, COUNT(*) AS NUM_REG, SUM(IF(TRIM(CAST(X."&F30&" AS STRING)) IN ('0000-00-00','0001-01-01','9999-12-31','MISS','00000','99999999999','99999999999.00','99999999999.000000'),1,0)) AS NUM_REG_DIF,'"&MAX('ID1&5'!K:K)+1&"' AS ID_EXEC, CURRENT_TIMESTAMP() AS TIME_EXEC FROM "&I30, IF(C30="Not applicable",+"SELECT '"&UPPER(B30)&"' AS TABELA, '"&UPPER(C30)&"' AS TIPOLOGIA_TESTE,'"&D30&"' AS TABELA_LT,'N/A' AS TABELA_SIMUL,'"&F30&"' AS CAMPO, "&"'${ref_date}' AS REF_DATE, COUNT(*) AS NUM_REG, SUM(IF(TRIM(CAST(X."&F30&" AS STRING)) IN ('N/A','11111111111','11111111111.00','11111111111.000000','1111-11-11'),1,0)) AS NUM_REG_DIF,'"&MAX('ID1&5'!K:K)+1&"' AS ID_EXEC, CURRENT_TIMESTAMP() AS TIME_EXEC FROM "&I30, IF(C30="Valores extremos",+"SELECT '"&UPPER(B30)&"' AS TABELA, '"&UPPER(C30)&"' AS TIPOLOGIA_TESTE,'"&D30&"' AS TABELA_LT,'N/A' AS TABELA_SIMUL,'"&F30&"' AS CAMPO, "&"'${ref_date}' AS REF_DATE, CAST(MIN("&F30&") AS STRING) AS VALOR_MIN, CAST(MAX("&F30&") AS STRING) AS VALOR_MAX,'"&MAX('ID1&5'!K:K)+1&"' AS ID_EXEC, CURRENT_TIMESTAMP() AS TIME_EXEC FROM "&MID(I30,1,LEN(I30)-2)&" AND CAST("&F30&" AS STRING) NOT IN ('0000-00-00','0001-01-01','9999-12-31','MISS','00000','99999999999','99999999999.00','99999999999.000000','N/A','11111111111','11111111111.00','11111111111.000000','1111-11-11'))X")))))) -> SELECT 'INSTRUMENT' AS TABELA, 'COERÊNCIA' AS TIPOLOGIA_TESTE,'CD_LOAN_TAPES_BCE.LT002_INSTRUMENT' AS TABELA_LT,'BU_LOANTAPE_WORK.LT002_INSTRUMENT' AS TABELA_SIMUL,'PRDCT' AS CAMPO, '${ref_date}' AS REF_DATE, COUNT(*) AS NUM_REG, SUM(IF(COALESCE(CAST(X.PRDCT AS STRING),'')<>COALESCE(CAST(Y.PRDCT_SIMUL AS STRING),'') OR (X.PRDCT IS NULL AND Y.PRDCT_SIMUL IS NOT NULL ) OR (X.PRDCT IS NOT NULL AND Y.PRDCT_SIMUL IS NULL),1,0)) AS NUM_REG_DIF,'1' AS ID_EXEC, CURRENT_TIMESTAMP() AS TIME_EXEC FROM (SELECT instrmnt_id, PRDCT FROM CD_LOAN_TAPES_BCE.LT002_INSTRUMENT WHERE ref_date='${ref_date}' AND nome_perimetro='Individual Local' AND segmento='ESTR' AND ambito='SRB_MBDT' AND entidade='00100')X INNER JOIN (SELECT instrmnt_id AS instrmnt_id_SIMUL, PRDCT AS PRDCT_SIMUL FROM BU_LOANTAPE_WORK.LT002_INSTRUMENT WHERE ref_date='${ref_date}' AND nome_perimetro='Individual Local' AND segmento='ESTR' AND ambito='PM' AND entidade='00100')Y ON X.INSTRMNT_ID=Y.INSTRMNT_ID_SIMUL | M30: =+"UNION ALL "&L30 -> UNION ALL SELECT 'INSTRUMENT' AS TABELA, 'COERÊNCIA' AS TIPOLOGIA_TESTE,'CD_LOAN_TAPES_BCE.LT002_INSTRUMENT' AS TABELA_LT,'BU_LOANTAPE_WORK.LT002_INSTRUMENT' AS TABELA_SIMUL,'PRDCT' AS CAMPO, '${ref_date}' AS REF_DATE, COUNT(*) AS NUM_REG, SUM(IF(COALESCE(CAST(X.PRDCT AS STRING),'')<>COALESCE(CAST(Y.PRDCT_SIMUL AS STRING),'') OR (X.PRDCT IS NULL AND Y.PRDCT_SIMUL IS NOT NULL ) OR (X.PRDCT IS NOT NULL AND Y.PRDCT_SIMUL IS NULL),1,0)) AS NUM_REG_DIF,'1' AS ID_EXEC, CURRENT_TIMESTAMP() AS TIME_EXEC FROM (SELECT instrmnt_id, PRDCT FROM CD_LOAN_TAPES_BCE.LT002_INSTRUMENT WHERE ref_date='${ref_date}' AND nome_perimetro='Individual Local' AND segmento='ESTR' AND ambito='SRB_MBDT' AND entidade='00100')X INNER JOIN (SELECT instrmnt_id AS instrmnt_id_SIMUL, PRDCT AS PRDCT_SIMUL FROM BU_LOANTAPE_WORK.LT002_INSTRUMENT WHERE ref_date='${ref_date}' AND nome_perimetro='Individual Local' AND segmento='ESTR' AND ambito='PM' AND entidade='00100')Y ON X.INSTRMNT_ID=Y.INSTRMNT_ID_SIMUL
A31: =+B31&F31 -> INSTRUMENTCOD_SOC | B31: INSTRUMENT | C31: Coerência | D31: =+UPPER('0. Instruções'!$D$35&"."&VLOOKUP(B31,'0. Instruções'!$C$27:$D$32,2,FALSE)) -> CD_LOAN_TAPES_BCE.LT002_INSTRUMENT | E31: =+UPPER('0. Instruções'!$D$36&"."&VLOOKUP(B31,'0. Instruções'!$C$27:$E$32,3,FALSE)) -> BU_LOANTAPE_WORK.LT002_INSTRUMENT | F31: COD_SOC | I31: ="(SELECT "&VLOOKUP(B31,'0. Instruções'!$C$27:$G$32,4,FALSE)&", "&F31&" FROM "&D31&" WHERE "&'0. Instruções'!$D$42&")X" -> (SELECT instrmnt_id, COD_SOC FROM CD_LOAN_TAPES_BCE.LT002_INSTRUMENT WHERE ref_date='${ref_date}' AND nome_perimetro='Individual Local' AND segmento='ESTR' AND ambito='SRB_MBDT' AND entidade='00100')X | J31: ="(SELECT "&VLOOKUP(B31,'0. Instruções'!$C$27:$G$32,4,FALSE)&" AS "&VLOOKUP(B31,'0. Instruções'!$C$27:$G$32,4,FALSE)&"_SIMUL, "&F31&" AS "&F31&"_SIMUL FROM "&E31&" WHERE "&'0. Instruções'!$D$43&")Y" -> (SELECT instrmnt_id AS instrmnt_id_SIMUL, COD_SOC AS COD_SOC_SIMUL FROM BU_LOANTAPE_WORK.LT002_INSTRUMENT WHERE ref_date='${ref_date}' AND nome_perimetro='Individual Local' AND segmento='ESTR' AND ambito='PM' AND entidade='00100')Y | K31: =+UPPER("ON X."&VLOOKUP(B31,'0. Instruções'!$C$27:$G$32,4,FALSE)&"=Y."&VLOOKUP(B31,'0. Instruções'!$C$27:$G$32,4,FALSE)&"_SIMUL") -> ON X.INSTRMNT_ID=Y.INSTRMNT_ID_SIMUL | L31: =+IF(C31="Coerência", +IF(LEFT(G31,5)="FLOAT","SELECT '"&UPPER(B31)&"' AS TABELA, '"&UPPER(C31)&"' AS TIPOLOGIA_TESTE,'"&D31&"' AS TABELA_LT,'"&E31&"' AS TABELA_SIMUL,'"&F31&"' AS CAMPO, "&"'${ref_date}' AS REF_DATE, COUNT(*) AS NUM_REG, SUM(IF((ABS(COALESCE(CAST(X."&F31&" AS DECIMAL(18,6)),0)-COALESCE(CAST(Y."&F31&"_SIMUL AS DECIMAL(18,6)),0))>0.000001) OR (X."&F31&" IS NULL AND Y."&F31&"_SIMUL IS NOT NULL ) OR (X."&F31&" IS NOT NULL AND Y."&F31&"_SIMUL IS NULL),1,0)) AS NUM_REG_DIF,'"&MAX('ID1&5'!K:K)+1&"' AS ID_EXEC, CURRENT_TIMESTAMP() AS TIME_EXEC FROM "&I31&" INNER JOIN "&J31&" "&K31,"SELECT '"&UPPER(B31)&"' AS TABELA, '"&UPPER(C31)&"' AS TIPOLOGIA_TESTE,'"&D31&"' AS TABELA_LT,'"&E31&"' AS TABELA_SIMUL,'"&F31&"' AS CAMPO, "&"'${ref_date}' AS REF_DATE, COUNT(*) AS NUM_REG, SUM(IF(COALESCE(CAST(X."&F31&" AS STRING),'')<>COALESCE(CAST(Y."&F31&"_SIMUL AS STRING),'') OR (X."&F31&" IS NULL AND Y."&F31&"_SIMUL IS NOT NULL ) OR (X."&F31&" IS NOT NULL AND Y."&F31&"_SIMUL IS NULL),1,0)) AS NUM_REG_DIF,'"&MAX('ID1&5'!L:L)+1&"' AS ID_EXEC, CURRENT_TIMESTAMP() AS TIME_EXEC FROM "&I31&" INNER JOIN "&J31&" "&K31), IF(C31="Validade",+IF(G31="Code List","SELECT '"&UPPER(B31)&"' AS TABELA, '"&UPPER(C31)&"' AS TIPOLOGIA_TESTE,'"&D31&"' AS TABELA_LT,'N/A' AS TABELA_SIMUL,'"&F31&"' AS CAMPO, "&"'${ref_date}' AS REF_DATE, COUNT(*) AS NUM_REG, SUM(IF(TRIM(CAST(X."&F31&" AS STRING))='' OR TRIM(CAST(X."&F31&" AS STRING)) IS NULL OR CAST(X."&F31&" AS STRING) NOT "&H31&",1,0)) AS NUM_REG_DIF,'"&MAX('ID1&5'!K:K)+1&"' AS ID_EXEC, CURRENT_TIMESTAMP() AS TIME_EXEC FROM "&I31,"SELECT '"&UPPER(B31)&"' AS TABELA, '"&UPPER(C31)&"' AS TIPOLOGIA_TESTE,'"&D31&"' AS TABELA_LT,'N/A' AS TABELA_SIMUL,'"&F31&"' AS CAMPO, "&"'${ref_date}' AS REF_DATE, COUNT(*) AS NUM_REG, SUM(IF(TRIM(CAST(X."&F31&" AS STRING))='' OR TRIM(CAST(X."&F31&" AS STRING)) IS NULL,1,0)) AS NUM_REG_DIF,'"&MAX('ID1&5'!K:K)+1&"' AS ID_EXEC, CURRENT_TIMESTAMP() AS TIME_EXEC FROM "&I31), IF(C31="Caracteres Especiais",+"SELECT '"&UPPER(B31)&"' AS TABELA, '"&UPPER(C31)&"' AS TIPOLOGIA_TESTE,'"&D31&"' AS TABELA_LT,'N/A' AS TABELA_SIMUL,'"&F31&"' AS CAMPO, "&"'${ref_date}' AS REF_DATE, COUNT(*) AS NUM_REG, SUM(IF(REGEXP_REPLACE(TRIM(CAST(X."&F31&" AS STRING)),'[^a-zA-Z0-9_\\s]','') <>TRIM(CAST(X."&F31&" AS STRING)),1,0)) AS NUM_REG_DIF,'"&MAX('ID1&5'!K:K)+1&"' AS ID_EXEC, CURRENT_TIMESTAMP() AS TIME_EXEC FROM "&I31, IF(C31="Missings",+"SELECT '"&UPPER(B31)&"' AS TABELA, '"&UPPER(C31)&"' AS TIPOLOGIA_TESTE,'"&D31&"' AS TABELA_LT,'N/A' AS TABELA_SIMUL,'"&F31&"' AS CAMPO, "&"'${ref_date}' AS REF_DATE, COUNT(*) AS NUM_REG, SUM(IF(TRIM(CAST(X."&F31&" AS STRING)) IN ('0000-00-00','0001-01-01','9999-12-31','MISS','00000','99999999999','99999999999.00','99999999999.000000'),1,0)) AS NUM_REG_DIF,'"&MAX('ID1&5'!K:K)+1&"' AS ID_EXEC, CURRENT_TIMESTAMP() AS TIME_EXEC FROM "&I31, IF(C31="Not applicable",+"SELECT '"&UPPER(B31)&"' AS TABELA, '"&UPPER(C31)&"' AS TIPOLOGIA_TESTE,'"&D31&"' AS TABELA_LT,'N/A' AS TABELA_SIMUL,'"&F31&"' AS CAMPO, "&"'${ref_date}' AS REF_DATE, COUNT(*) AS NUM_REG, SUM(IF(TRIM(CAST(X."&F31&" AS STRING)) IN ('N/A','11111111111','11111111111.00','11111111111.000000','1111-11-11'),1,0)) AS NUM_REG_DIF,'"&MAX('ID1&5'!K:K)+1&"' AS ID_EXEC, CURRENT_TIMESTAMP() AS TIME_EXEC FROM "&I31, IF(C31="Valores extremos",+"SELECT '"&UPPER(B31)&"' AS TABELA, '"&UPPER(C31)&"' AS TIPOLOGIA_TESTE,'"&D31&"' AS TABELA_LT,'N/A' AS TABELA_SIMUL,'"&F31&"' AS CAMPO, "&"'${ref_date}' AS REF_DATE, CAST(MIN("&F31&") AS STRING) AS VALOR_MIN, CAST(MAX("&F31&") AS STRING) AS VALOR_MAX,'"&MAX('ID1&5'!K:K)+1&"' AS ID_EXEC, CURRENT_TIMESTAMP() AS TIME_EXEC FROM "&MID(I31,1,LEN(I31)-2)&" AND CAST("&F31&" AS STRING) NOT IN ('0000-00-00','0001-01-01','9999-12-31','MISS','00000','99999999999','99999999999.00','99999999999.000000','N/A','11111111111','11111111111.00','11111111111.000000','1111-11-11'))X")))))) -> SELECT 'INSTRUMENT' AS TABELA, 'COERÊNCIA' AS TIPOLOGIA_TESTE,'CD_LOAN_TAPES_BCE.LT002_INSTRUMENT' AS TABELA_LT,'BU_LOANTAPE_WORK.LT002_INSTRUMENT' AS TABELA_SIMUL,'COD_SOC' AS CAMPO, '${ref_date}' AS REF_DATE, COUNT(*) AS NUM_REG, SUM(IF(COALESCE(CAST(X.COD_SOC AS STRING),'')<>COALESCE(CAST(Y.COD_SOC_SIMUL AS STRING),'') OR (X.COD_SOC IS NULL AND Y.COD_SOC_SIMUL IS NOT NULL ) OR (X.COD_SOC IS NOT NULL AND Y.COD_SOC_SIMUL IS NULL),1,0)) AS NUM_REG_DIF,'1' AS ID_EXEC, CURRENT_TIMESTAMP() AS TIME_EXEC FROM (SELECT instrmnt_id, COD_SOC FROM CD_LOAN_TAPES_BCE.LT002_INSTRUMENT WHERE ref_date='${ref_date}' AND nome_perimetro='Individual Local' AND segmento='ESTR' AND ambito='SRB_MBDT' AND entidade='00100')X INNER JOIN (SELECT instrmnt_id AS instrmnt_id_SIMUL, COD_SOC AS COD_SOC_SIMUL FROM BU_LOANTAPE_WORK.LT002_INSTRUMENT WHERE ref_date='${ref_date}' AND nome_perimetro='Individual Local' AND segmento='ESTR' AND ambito='PM' AND entidade='00100')Y ON X.INSTRMNT_ID=Y.INSTRMNT_ID_SIMUL | M31: =+"UNION ALL "&L31 -> UNION ALL SELECT 'INSTRUMENT' AS TABELA, 'COERÊNCIA' AS TIPOLOGIA_TESTE,'CD_LOAN_TAPES_BCE.LT002_INSTRUMENT' AS TABELA_LT,'BU_LOANTAPE_WORK.LT002_INSTRUMENT' AS TABELA_SIMUL,'COD_SOC' AS CAMPO, '${ref_date}' AS REF_DATE, COUNT(*) AS NUM_REG, SUM(IF(COALESCE(CAST(X.COD_SOC AS STRING),'')<>COALESCE(CAST(Y.COD_SOC_SIMUL AS STRING),'') OR (X.COD_SOC IS NULL AND Y.COD_SOC_SIMUL IS NOT NULL ) OR (X.COD_SOC IS NOT NULL AND Y.COD_SOC_SIMUL IS NULL),1,0)) AS NUM_REG_DIF,'1' AS ID_EXEC, CURRENT_TIMESTAMP() AS TIME_EXEC FROM (SELECT instrmnt_id, COD_SOC FROM CD_LOAN_TAPES_BCE.LT002_INSTRUMENT WHERE ref_date='${ref_date}' AND nome_perimetro='Individual Local' AND segmento='ESTR' AND ambito='SRB_MBDT' AND entidade='00100')X INNER JOIN (SELECT instrmnt_id AS instrmnt_id_SIMUL, COD_SOC AS COD_SOC_SIMUL FROM BU_LOANTAPE_WORK.LT002_INSTRUMENT WHERE ref_date='${ref_date}' AND nome_perimetro='Individual Local' AND segmento='ESTR' AND ambito='PM' AND entidade='00100')Y ON X.INSTRMNT_ID=Y.INSTRMNT_ID_SIMUL
