Workbook

Sheet GD- LT atual
B2: Categoria GD | C2: Code | D2: Descritivo
B3: AGFGR001 | C3: SCA01010101 | D3: Renewable energy production
B4: AGFGR001 | C4: SCA01010102 | D4: Hydrogen and Bioenergy production
B5: AGFGR001 | C5: SCA01010103 | D5: Transmission and distribution of electricity
B6: AGFGR001 | C6: SCA01010104 | D6: Energy Storage
B7: AGFGR002 | C7: SCA0101020101 | D7: Land Transport - Purchase
B8: AGFGR002 | C8: SCA0101020102 | D8: Land Transport - Renovation
B9: AGFGR002 | C9: SCA0101020103 | D9: Land Transport - Purchase and renovation
B10: AGFGR002 | C10: SCA0101020201 | D10: Water Transport - Purchase
B11: AGFGR002 | C11: SCA0101020202 | D11: Water Transport - Renovation
B12: AGFGR002 | C12: SCA0101020203 | D12: Water Transport - Purchase and renovation
B13: AGFGR003 | C13: SCA01010203 | D13: Transport Infrastructure
... B47: AGFSO001 | C47: SCA010210 | D47: Social - Default
C48: SCA010301 | D48: Mortgages
C49: SCA010302 | D49: Building renovation loan
C50: SCA010303 | D50: Motor vehicle loans
C51: SCA010304 | D51: Others
B52: AGFSL001 | C52: SCA020101 | D52: ESG Rating Linked
B53: AGFSL001 | C53: SCA02010201 | D53: KPI Linked - Green
B54: AGFSL001 | C54: SCA02010202 | D54: KPI Linked - Green & Social
B55: AGFSL001 | C55: SCA02010203 | D55: KPI Linked - Social
B56: AGFSL001 | C56: SCA02010301 | D56: KPI & ESG Rating Linked - Green
B57: AGFSL001 | C57: SCA02010302 | D57: KPI & ESG Rating Linked - Green & Social
B58: AGFSL001 | C58: SCA02010303 | D58: KPI & ESG Rating Linked - Social
B59: AGFSL001 | C59: SCA020104 | D59: Sustainability Linked Finance - Default
C60: SCA020201 | D60: Pure Green counterparty - Default
B61: AGFSR001 | C61: SCA020301 | D61: Sustainable Responsible - Default
B62: AGFSD001 | C62: SCA0204 | D62: General Purpose - Default

Sheet SFICS e LT
B2: Categorias SFICS | D2: Ficheiro Corporativo Loan Tape Dezembro | F2: Ficheiro Corporativo Loan Tape Atual
B3: Code | C3: Descritivo | D3: Code | E3: Descritivo | F3: Code | G3: Descritivo | H3: Categoria GD
B4: A.1. | C4: Energy | E4: Energy
B5: A.1.1. | C5: Electricity generation using solar photovoltaic technology | D5: 210101 | E5: Electricity generation using solar photovoltaic technology | F5: SCA01010101 | G5: Renewable energy production | H5: =INDEX('GD- LT atual'!$B$2:$D$62,MATCH('SFICS e LT'!F5,'GD- LT atual'!$C$2:$C$62,0),1) -> AGFGR001
B6: A.1.2. | C6: Electricity generation using concentrated solar power (CSP) technology | D6: 210102 | E6: Electricity generation using concentrated solar power (CSP) technology | F6: SCA01010101 | G6: Renewable energy production | H6: =INDEX('GD- LT atual'!$B$2:$D$62,MATCH('SFICS e LT'!F6,'GD- LT atual'!$C$2:$C$62,0),1) -> AGFGR001
B7: A.1.3. | C7: Electricity generation from wind power | D7: 210103 | E7: Electricity generation from wind power | F7: SCA01010101 | G7: Renewable energy production | H7: =INDEX('GD- LT atual'!$B$2:$D$62,MATCH('SFICS e LT'!F7,'GD- LT atual'!$C$2:$C$62,0),1) -> AGFGR001
B8: A.1.4. | C8: Electricity generation from ocean energy technologies | D8: 210104 | E8: Electricity generation from ocean energy technologies | F8: SCA01010101 | G8: Renewable energy production | H8: =INDEX('GD- LT atual'!$B$2:$D$62,MATCH('SFICS e LT'!F8,'GD- LT atual'!$C$2:$C$62,0),1) -> AGFGR001
B9: A.1.5. | C9: Electricity generation from hydropower | D9: 210105 | E9: Electricity generation from hydropower | F9: SCA01010101 | G9: Renewable energy production | H9: =INDEX('GD- LT atual'!$B$2:$D$62,MATCH('SFICS e LT'!F9,'GD- LT atual'!$C$2:$C$62,0),1) -> AGFGR001
B10: A.1.6. | C10: Electricity generation from geothermal energy | D10: 210106 | E10: Electricity generation from geothermal energy | F10: SCA01010101 | G10: Renewable energy production | H10: =INDEX('GD- LT atual'!$B$2:$D$62,MATCH('SFICS e LT'!F10,'GD- LT atual'!$C$2:$C$62,0),1) -> AGFGR001
B11: A.1.7. | C11: Electricity generation from renewable non-fossil gaseous and liquid fuels | D11: 210201 | E11: Electricity generation from renewable non-fossil gaseous and liquid fuels | F11: SCA01010101 | G11: Renewable energy production | H11: =INDEX('GD- LT atual'!$B$2:$D$62,MATCH('SFICS e LT'!F11,'GD- LT atual'!$C$2:$C$62,0),1) -> AGFGR001
B12: A.1.8. | C12: Electricity generation from bioenergy | D12: 210202 | E12: Electricity generation from bioenergy | F12: SCA01010101 | G12: Renewable energy production | H12: =INDEX('GD- LT atual'!$B$2:$D$62,MATCH('SFICS e LT'!F12,'GD- LT atual'!$C$2:$C$62,0),1) -> AGFGR001
B13: A.1.9. | C13: Transmission and distribution of electricity | D13: 210419 | E13: Transmission and distribution of electricity | F13: SCA01010103 | G13: Transmission and distribution of electricity | H13: =INDEX('GD- LT atual'!$B$2:$D$62,MATCH('SFICS e LT'!F13,'GD- LT atual'!$C$2:$C$62,0),1) -> AGFGR001
B14: A.1.10. | C14: Storage of electricity | D14: 210601 | E14: Storage of electricity | F14: SCA01010104 | G14: Energy Storage | H14: =INDEX('GD- LT atual'!$B$2:$D$62,MATCH('SFICS e LT'!F14,'GD- LT atual'!$C$2:$C$62,0),1) -> AGFGR001
B15: A.1.11. | C15: Storage of thermal energy | D15: 210602 | E15: Storage of thermal energy | F15: SCA01010104 | G15: Energy Storage | H15: =INDEX('GD- LT atual'!$B$2:$D$62,MATCH('SFICS e LT'!F15,'GD- LT atual'!$C$2:$C$62,0),1) -> AGFGR001
B16: A.1.12. | C16: Storage of hydrogen | D16: 210603 | E16: Storage of hydrogen | F16: SCA01010104 | G16: Energy Storage | H16: =INDEX('GD- LT atual'!$B$2:$D$62,MATCH('SFICS e LT'!F16,'GD- LT atual'!$C$2:$C$62,0),1) -> AGFGR001
B17: A.1.13. | C17: Manufacture of biogas and biofuels for use in transport and of bioliquids | D17: 210203 | E17: Manufacture of biogas and biofuels for use in transport and of bioliquids | F17: SCA01010102 | G17: Hydrogen and Bioenergy production | H17: =INDEX('GD- LT atual'!$B$2:$D$62,MATCH('SFICS e LT'!F17,'GD- LT atual'!$C$2:$C$62,0),1) -> AGFGR001
... B29: A.1.25. | C29: Production of heat/cool using waste heat | D29: 210208 | E29: Production of heat/cool using waste heat | F29: SCA01010101 | G29: Renewable energy production | H29: =INDEX('GD- LT atual'!$B$2:$D$62,MATCH('SFICS e LT'!F29,'GD- LT atual'!$C$2:$C$62,0),1) -> AGFGR001
B30: A.1.26. | C30: Pre-commercial stages of advanced technologies to produce energy from nuclear processes with minimal waste from the fuel cycle | D30: 210301 | E30: Pre-commercial stages of advanced technologies to produce energy from nuclear processes with minimal waste from the fuel cycle | F30: - | H30: =INDEX('GD- LT atual'!$B$2:$D$62,MATCH('SFICS e LT'!F30,'GD- LT atual'!$C$2:$C$62,0),1) -> #N/A
B31: A.1.27. | C31: Construction and safe operation of new nuclear power plants, for the generation of electricity and/or heat, including for hydrogen production, using best-available technologies | D31: 210302 | E31: Construction and safe operation of new nuclear power plants, for the generation of electricity and/or heat, including for hydrogen production, using best-available technologies | F31: SCA01010102 | G31: Hydrogen and Bioenergy production | H31: =INDEX('GD- LT atual'!$B$2:$D$62,MATCH('SFICS e LT'!F31,'GD- LT atual'!$C$2:$C$62,0),1) -> AGFGR001
B32: A.1.28. | C32: Electricity generation from nuclear energy in existing installations | D32: 210303 | E32: Electricity generation from nuclear energy in existing installations | F32: - | H32: =INDEX('GD- LT atual'!$B$2:$D$62,MATCH('SFICS e LT'!F32,'GD- LT atual'!$C$2:$C$62,0),1) -> #N/A
B33: A.1.29. | C33: Electricity generation from fossil gaseous fuels | D33: 210304 | E33: Electricity generation from fossil gaseous fuels | F33: - | H33: =INDEX('GD- LT atual'!$B$2:$D$62,MATCH('SFICS e LT'!F33,'GD- LT atual'!$C$2:$C$62,0),1) -> #N/A
B34: A.1.30. | C34: Production of heat/cool from fossil gaseous fuels in an efficient district heating and cooling system | D34: 210305 | E34: Production of heat/cool from fossil gaseous fuels in an efficient district heating and cooling system | F34: - | H34: =INDEX('GD- LT atual'!$B$2:$D$62,MATCH('SFICS e LT'!F34,'GD- LT atual'!$C$2:$C$62,0),1) -> #N/A
B35: A.1.31. | C35: High-efficiency co-generation of heat/cool and power from fossil gaseous fuels | D35: 210306 | E35: High-efficiency co-generation of heat/cool and power from fossil gaseous fuels | F35: - | H35: =INDEX('GD- LT atual'!$B$2:$D$62,MATCH('SFICS e LT'!F35,'GD- LT atual'!$C$2:$C$62,0),1) -> #N/A
B36: A.1.32. | C36: Renewable Energy Procurement | D36: 210701 | E36: Renewable Energy Procurement | F36: SCA010204 | G36: Social - Energy | H36: =INDEX('GD- LT atual'!$B$2:$D$62,MATCH('SFICS e LT'!F36,'GD- LT atual'!$C$2:$C$62,0),1) -> AGFSO001
B37: A.1.33. | C37: Terminology definitions | D37: - | F37: - | H37: =INDEX('GD- LT atual'!$B$2:$D$62,MATCH('SFICS e LT'!F37,'GD- LT atual'!$C$2:$C$62,0),1) -> #N/A
B38: A.2. | C38: Transport | E38: Transport | H38: =INDEX('GD- LT atual'!$B$2:$D$62,MATCH('SFICS e LT'!F38,'GD- LT atual'!$C$2:$C$62,0),1) -> #N/A
B39: A.2.1. | C39: Passenger interurban rail transport | D39: 220101 | E39: Passenger interurban rail transport | F39: SCA0101020101 | G39: Land Transport - Purchase | H39: =INDEX('GD- LT atual'!$B$2:$D$62,MATCH('SFICS e LT'!F39,'GD- LT atual'!$C$2:$C$62,0),1) -> AGFGR002
B40: A.2.2. | C40: Freight rail transport | D40: 220102 | E40: Freight rail transport | F40: SCA0101020101 | G40: Land Transport - Purchase | H40: =INDEX('GD- LT atual'!$B$2:$D$62,MATCH('SFICS e LT'!F40,'GD- LT atual'!$C$2:$C$62,0),1) -> AGFGR002
B41: A.2.3. | C41: Urban and suburban transport, road passenger transport | D41: 220103 | E41: Urban and suburban transport, road passenger transport | F41: SCA0101020101 | G41: Land Transport - Purchase | H41: =INDEX('GD- LT atual'!$B$2:$D$62,MATCH('SFICS e LT'!F41,'GD- LT atual'!$C$2:$C$62,0),1) -> AGFGR002
B42: A.2.4. | C42: Operation of personal mobility devices, cycle logistics | D42: 220104 | E42: Operation of personal mobility devices, cycle logistics | F42: SCA01010203 | G42: Transport Infrastructure | H42: =INDEX('GD- LT atual'!$B$2:$D$62,MATCH('SFICS e LT'!F42,'GD- LT atual'!$C$2:$C$62,0),1) -> AGFGR003
B43: A.2.5. | C43: Transport by motorbikes, passenger cars and light commercial vehicles | D43: 220105 | E43: Transport by motorbikes, passenger cars and light commercial vehicles | F43: SCA01010203 | G43: Transport Infrastructure | H43: =INDEX('GD- LT atual'!$B$2:$D$62,MATCH('SFICS e LT'!F43,'GD- LT atual'!$C$2:$C$62,0),1) -> AGFGR003
B44: A.2.6. | C44: Freight transport services by road | D44: 220106 | E44: Freight transport services by road | F44: SCA0101020101 | G44: Land Transport - Purchase | H44: =INDEX('GD- LT atual'!$B$2:$D$62,MATCH('SFICS e LT'!F44,'GD- LT atual'!$C$2:$C$62,0),1) -> AGFGR002
B45: A.2.7. | C45: Inland passenger water transport | D45: 220201 | E45: Inland passenger water transport | F45: SCA0101020201 | G45: Water Transport - Purchase | H45: =INDEX('GD- LT atual'!$B$2:$D$62,MATCH('SFICS e LT'!F45,'GD- LT atual'!$C$2:$C$62,0),1) -> AGFGR002
B46: A.2.8. | C46: Inland freight water transport | D46: 220202 | E46: Inland freight water transport | F46: SCA0101020201 | G46: Water Transport - Purchase | H46: =INDEX('GD- LT atual'!$B$2:$D$62,MATCH('SFICS e LT'!F46,'GD- LT atual'!$C$2:$C$62,0),1) -> AGFGR002
B47: A.2.9. | C47: Retrofitting of inland water passenger and freight transport | D47: 220203 | E47: Retrofitting of inland water passenger and freight transport | F47: SCA0101020202 | G47: Water Transport - Renovation | H47: =INDEX('GD- LT atual'!$B$2:$D$62,MATCH('SFICS e LT'!F47,'GD- LT atual'!$C$2:$C$62,0),1) -> AGFGR002
B48: A.2.10. | C48: Sea and coastal freight water transport, vessels for port operations and auxiliary activities | D48: 220204 | E48: Sea and coastal freight water transport, vessels for port operations and auxiliary activities | F48: SCA0101020201 | G48: Water Transport - Purchase | H48: =INDEX('GD- LT atual'!$B$2:$D$62,MATCH('SFICS e LT'!F48,'GD- LT atual'!$C$2:$C$62,0),1) -> AGFGR002
B49: A.2.11. | C49: Sea and coastal passenger water transport | D49: 220205 | E49: Sea and coastal passenger water transport | F49: SCA0101020201 | G49: Water Transport - Purchase | H49: =INDEX('GD- LT atual'!$B$2:$D$62,MATCH('SFICS e LT'!F49,'GD- LT atual'!$C$2:$C$62,0),1) -> AGFGR002
B50: A.2.12. | C50: Retrofitting of sea and coastal freight and passenger water transport | D50: 220206 | E50: Retrofitting of sea and coastal freight and passenger water transport | F50: SCA0101020202 | G50: Water Transport - Renovation | H50: =INDEX('GD- LT atual'!$B$2:$D$62,MATCH('SFICS e LT'!F50,'GD- LT atual'!$C$2:$C$62,0),1) -> AGFGR002
... B54: A.2.16. | C54: Infrastructure enabling low carbon water transport | D54: 220403 | E54: Infrastructure enabling low carbon water transport | F54: SCA01010203 | G54: Transport Infrastructure | H54: =INDEX('GD- LT atual'!$B$2:$D$62,MATCH('SFICS e LT'!F54,'GD- LT atual'!$C$2:$C$62,0),1) -> AGFGR003
B55: A.2.17. | C55: Low carbon airport infrastructure | D55: 220404 | E55: Low carbon airport infrastructure | F55: SCA01010203 | G55: Transport Infrastructure | H55: =INDEX('GD- LT atual'!$B$2:$D$62,MATCH('SFICS e LT'!F55,'GD- LT atual'!$C$2:$C$62,0),1) -> AGFGR003
B56: A.2.18. | C56: Leasing of aircraft | D56: 220301 | E56: Leasing of aircraft | F56: SCA01010203 | G56: Transport Infrastructure | H56: =INDEX('GD- LT atual'!$B$2:$D$62,MATCH('SFICS e LT'!F56,'GD- LT atual'!$C$2:$C$62,0),1) -> AGFGR003
B57: A.2.19. | C57: Passenger and freight air transport | D57: 220302 | E57: Passenger and freight air transport | F57: SCA01010203 | G57: Transport Infrastructure | H57: =INDEX('GD- LT atual'!$B$2:$D$62,MATCH('SFICS e LT'!F57,'GD- LT atual'!$C$2:$C$62,0),1) -> AGFGR003
B58: A.2.20. | C58: Air transport ground handling operations | D58: 220303 | E58: Air transport ground handling operations | F58: SCA0101020102 | G58: Land Transport - Purchase | H58: =INDEX('GD- LT atual'!$B$2:$D$62,MATCH('SFICS e LT'!F58,'GD- LT atual'!$C$2:$C$62,0),1) -> AGFGR002
B59: A.2.21. | C59: Hydrogen powered-vehicles | D59: 220501 | E59: Hydrogen powered-vehicles | F59: SCA0101020101 | G59: Land Transport - Purchase | H59: =INDEX('GD- LT atual'!$B$2:$D$62,MATCH('SFICS e LT'!F59,'GD- LT atual'!$C$2:$C$62,0),1) -> AGFGR002
B60: A.2.22. | C60: Terminology definitions | D60: - | F60: - | H60: =INDEX('GD- LT atual'!$B$2:$D$62,MATCH('SFICS e LT'!F60,'GD- LT atual'!$C$2:$C$62,0),1) -> #N/A
B61: A.3. | C61: Construction and Real Estate | E61: Construction and Real Estate | H61: =INDEX('GD- LT atual'!$B$2:$D$62,MATCH('SFICS e LT'!F61,'GD- LT atual'!$C$2:$C$62,0),1) -> #N/A
B62: A.3.1. | C62: Construction of new buildings | D62: 2301 | E62: Construction of new buildings | F62: SCA0101050101 | G62: Construction, refurbishment and purchase of “green” buildings - Purchase | H62: =INDEX('GD- LT atual'!$B$2:$D$62,MATCH('SFICS e LT'!F62,'GD- LT atual'!$C$2:$C$62,0),1) -> AGFGR006
B63: A.3.2. | C63: Renovation of existing buildings | D63: 2302 | E63: Renovation of existing buildings | F63: SCA0101050102 | G63: Construction, refurbishment and purchase of “green” buildings - Renovation | H63: =INDEX('GD- LT atual'!$B$2:$D$62,MATCH('SFICS e LT'!F63,'GD- LT atual'!$C$2:$C$62,0),1) -> AGFGR007
B64: A.3.3. | C64: Installation, maintenance and repair of energy efficiency equipment | D64: 230301 | E64: Installation, maintenance and repair of energy efficiency equipment | F64: SCA01010502 | G64: Energy efficiency equipment in buildings | H64: =INDEX('GD- LT atual'!$B$2:$D$62,MATCH('SFICS e LT'!F64,'GD- LT atual'!$C$2:$C$62,0),1) -> AGFGR007
B65: A.3.4. | C65: Installation, maintenance and repair of charging stations for electric vehicles in buildings (and parking spaces attached to buildings) | D65: 230302 | E65: Installation, maintenance and repair of charging stations for electric vehicles in buildings (and parking spaces attached to buildings) | F65: SCA01010503 | G65: Renewable energy infrastructure in buildings | H65: =INDEX('GD- LT atual'!$B$2:$D$62,MATCH('SFICS e LT'!F65,'GD- LT atual'!$C$2:$C$62,0),1) -> AGFGR008
B66: A.3.5. | C66: Installation, maintenance and repair of instruments and devices for measuring, regulation and controlling energy performance of buildings | D66: 230303 | E66: Installation, maintenance and repair of instruments and devices for measuring, regulation and controlling energy performance of buildings | F66: SCA01010503 | G66: Renewable energy infrastructure in buildings | H66: =INDEX('GD- LT atual'!$B$2:$D$62,MATCH('SFICS e LT'!F66,'GD- LT atual'!$C$2:$C$62,0),1) -> AGFGR008
B67: A.3.6. | C67: Installation, maintenance and repair of renewable energy technologies | D67: 230304 | E67: Installation, maintenance and repair of renewable energy technologies | F67: SCA01010503 | G67: Renewable energy infrastructure in buildings | H67: =INDEX('GD- LT atual'!$B$2:$D$62,MATCH('SFICS e LT'!F67,'GD- LT atual'!$C$2:$C$62,0),1) -> AGFGR008
B68: A.3.7. | C68: Acquisition and ownership | D68: 2304 | E68: Acquisition and ownership | F68: SCA010206 | G68: Social - Real Estate | H68: =INDEX('GD- LT atual'!$B$2:$D$62,MATCH('SFICS e LT'!F68,'GD- LT atual'!$C$2:$C$62,0),1) -> AGFSO001
B69: A.3.8. | C69: Demolition and wrecking of buildings and other structures | D69: 2305 | E69: Demolition and wrecking of buildings and other structures | F69: SCA01010603 | G69: Reparation activities | H69: =INDEX('GD- LT atual'!$B$2:$D$62,MATCH('SFICS e LT'!F69,'GD- LT atual'!$C$2:$C$62,0),1) -> AGFGR009
B70: A.3.9. | C70: Maintenance of roads and motorways | D70: 230601 | E70: Maintenance of roads and motorways | F70: SCA01010603 | G70: Reparation activities | H70: =INDEX('GD- LT atual'!$B$2:$D$62,MATCH('SFICS e LT'!F70,'GD- LT atual'!$C$2:$C$62,0),1) -> AGFGR009
B71: A.3.10. | C71: Use of concrete in civil engineering | D71: 230602 | E71: Use of concrete in civil engineering | F71: SCA010206 | G71: Social - Real Estate | H71: =INDEX('GD- LT atual'!$B$2:$D$62,MATCH('SFICS e LT'!F71,'GD- LT atual'!$C$2:$C$62,0),1) -> AGFSO001
B72: A.3.11. | C72: Terminology definitions | D72: - | F72: - | H72: =INDEX('GD- LT atual'!$B$2:$D$62,MATCH('SFICS e LT'!F72,'GD- LT atual'!$C$2:$C$62,0),1) -> #N/A
B73: A.4. | C73: Professional, Scientific and Technical Activities | E73: Professional, Scientific and Technical Activities | F73: - | H73: =INDEX('GD- LT atual'!$B$2:$D$62,MATCH('SFICS e LT'!F73,'GD- LT atual'!$C$2:$C$62,0),1) -> #N/A
B74: A.4.1. | C74: Professional services related to energy performance of buildings | D74: 2401 | E74: Professional services related to energy performance of buildings | F74: SCA010204 | G74: Social - Energy | H74: =INDEX('GD- LT atual'!$B$2:$D$62,MATCH('SFICS e LT'!F74,'GD- LT atual'!$C$2:$C$62,0),1) -> AGFSO001
B75: A.5. | C75: Disaster Risk Management | E75: Disaster Risk Management | H75: =INDEX('GD- LT atual'!$B$2:$D$62,MATCH('SFICS e LT'!F75,'GD- LT atual'!$C$2:$C$62,0),1) -> #N/A
B76: A.5.1. | C76: Nature-based solutions for flood and drought risk prevention and protection | D76: 2501 | E76: Nature-based solutions for flood and drought risk prevention and protection | F76: SCA010205 | G76: Social - Water and Waste Management | H76: =INDEX('GD- LT atual'!$B$2:$D$62,MATCH('SFICS e LT'!F76,'GD- LT atual'!$C$2:$C$62,0),1) -> AGFSO001
B77: A.5.2. | C77: Emergency services | D77: 2502 | E77: Emergency services | F77: SCA010210 | G77: Social - Default | H77: =INDEX('GD- LT atual'!$B$2:$D$62,MATCH('SFICS e LT'!F77,'GD- LT atual'!$C$2:$C$62,0),1) -> AGFSO001
B78: A.5.3. | C78: Flood risk prevention and protection infrastructure | D78: 2503 | E78: Flood risk prevention and protection infrastructure | F78: SCA010205 | G78: Social - Water and Waste Management | H78: =INDEX('GD- LT atual'!$B$2:$D$62,MATCH('SFICS e LT'!F78,'GD- LT atual'!$C$2:$C$62,0),1) -> AGFSO001
B79: A.6. | C79: Water and Waste | E79: Water and Waste | H79: =INDEX('GD- LT atual'!$B$2:$D$62,MATCH('SFICS e LT'!F79,'GD- LT atual'!$C$2:$C$62,0),1) -> #N/A
B80: A.6.1. | C80: Water collection, treatment and supply systems | D80: 260101 | E80: Water collection, treatment and supply systems | F80: SCA010205 | G80: Social - Water and Waste Management | H80: =INDEX('GD- LT atual'!$B$2:$D$62,MATCH('SFICS e LT'!F80,'GD- LT atual'!$C$2:$C$62,0),1) -> AGFSO001
B81: A.6.2. | C81: Sustainable Water Management | D81: 260104 | E81: Sustainable Water Management | F81: SCA010205 | G81: Social - Water and Waste Management | H81: =INDEX('GD- LT atual'!$B$2:$D$62,MATCH('SFICS e LT'!F81,'GD- LT atual'!$C$2:$C$62,0),1) -> AGFSO001
B82: A.6.3. | C82: Waste water collection and treatment | D82: 260201 | E82: Waste water collection and treatment | F82: SCA010205 | G82: Social - Water and Waste Management | H82: =INDEX('GD- LT atual'!$B$2:$D$62,MATCH('SFICS e LT'!F82,'GD- LT atual'!$C$2:$C$62,0),1) -> AGFSO001
B83: A.6.4. | C83: Collection and transport of non-hazardous waste in source segregated fractions | D83: 260401 | E83: Collection and transport of non-hazardous waste in source segregated fractions | F83: SCA010205 | G83: Social - Water and Waste Management | H83: =INDEX('GD- LT atual'!$B$2:$D$62,MATCH('SFICS e LT'!F83,'GD- LT atual'!$C$2:$C$62,0),1) -> AGFSO001
B84: A.6.5. | C84: Anaerobic digestion of sewage sludge | D84: 260301 | E84: Anaerobic digestion of sewage sludge | F84: SCA010205 | G84: Social - Water and Waste Management | H84: =INDEX('GD- LT atual'!$B$2:$D$62,MATCH('SFICS e LT'!F84,'GD- LT atual'!$C$2:$C$62,0),1) -> AGFSO001
B85: A.6.6. | C85: Anaerobic digestion of bio-waste | D85: 260302 | E85: Anaerobic digestion of bio-waste | F85: SCA010205 | G85: Social - Water and Waste Management | H85: =INDEX('GD- LT atual'!$B$2:$D$62,MATCH('SFICS e LT'!F85,'GD- LT atual'!$C$2:$C$62,0),1) -> AGFSO001
B86: A.6.7. | C86: Composting of bio-waste | D86: 260303 | E86: Composting of bio-waste | F86: SCA010205 | G86: Social - Water and Waste Management | H86: =INDEX('GD- LT atual'!$B$2:$D$62,MATCH('SFICS e LT'!F86,'GD- LT atual'!$C$2:$C$62,0),1) -> AGFSO001
B87: A.6.8. | C87: Material recovery from non-hazardous waste | D87: 260402 | E87: Material recovery from non-hazardous waste | F87: SCA010205 | G87: Social - Water and Waste Management | H87: =INDEX('GD- LT atual'!$B$2:$D$62,MATCH('SFICS e LT'!F87,'GD- LT atual'!$C$2:$C$62,0),1) -> AGFSO001
B88: A.6.9. | C88: Landfill gas capture and utilisation | D88: 260304 | E88: Landfill gas capture and utilisation | F88: SCA01010805 | G88: Carbon markets | H88: =INDEX('GD- LT atual'!$B$2:$D$62,MATCH('SFICS e LT'!F88,'GD- LT atual'!$C$2:$C$62,0),1) -> AGFGR011
B89: A.6.10. | C89: Transport of CO2 | D89: 260601 | E89: Transport of CO2 | F89: SCA01010805 | G89: Carbon markets | H89: =INDEX('GD- LT atual'!$B$2:$D$62,MATCH('SFICS e LT'!F89,'GD- LT atual'!$C$2:$C$62,0),1) -> AGFGR011
B90: A.6.11. | C90: Underground permanent geological storage of CO2 | D90: 260602 | E90: Underground permanent geological storage of CO2 | F90: SCA01010805 | G90: Carbon markets | H90: =INDEX('GD- LT atual'!$B$2:$D$62,MATCH('SFICS e LT'!F90,'GD- LT atual'!$C$2:$C$62,0),1) -> AGFGR011
B91: A.6.12. | C91: Desalination | D91: 260102 | E91: Desalination | F91: SCA010205 | G91: Social - Water and Waste Management | H91: =INDEX('GD- LT atual'!$B$2:$D$62,MATCH('SFICS e LT'!F91,'GD- LT atual'!$C$2:$C$62,0),1) -> AGFSO001
B92: A.6.13. | C92: Water Supply | D92: 260103 | E92: Water Supply | F92: SCA010205 | G92: Social - Water and Waste Management | H92: =INDEX('GD- LT atual'!$B$2:$D$62,MATCH('SFICS e LT'!F92,'GD- LT atual'!$C$2:$C$62,0),1) -> AGFSO001
B93: A.6.14. | C93: Urban Waste Water Treatment | D93: 260202 | E93: Urban Waste Water Treatment | F93: SCA010205 | G93: Social - Water and Waste Management | H93: =INDEX('GD- LT atual'!$B$2:$D$62,MATCH('SFICS e LT'!F93,'GD- LT atual'!$C$2:$C$62,0),1) -> AGFSO001
... B96: A.6.17. | C96: Production of alternative water resources for purposes other than human consumption | D96: 260205 | E96: Production of alternative water resources for purposes other than human consumption | F96: SCA010205 | G96: Social - Water and Waste Management | H96: =INDEX('GD- LT atual'!$B$2:$D$62,MATCH('SFICS e LT'!F96,'GD- LT atual'!$C$2:$C$62,0),1) -> AGFSO001
B97: A.6.18. | C97: Collection and transport of non-hazardous and hazardous waste | D97: 260403 | E97: Collection and transport of non-hazardous and hazardous waste | F97: SCA010205 | G97: Social - Water and Waste Management | H97: =INDEX('GD- LT atual'!$B$2:$D$62,MATCH('SFICS e LT'!F97,'GD- LT atual'!$C$2:$C$62,0),1) -> AGFSO001
B98: A.6.19. | C98: Treatment of hazardous waste | D98: 260404 | E98: Treatment of hazardous waste | F98: SCA010205 | G98: Social - Water and Waste Management | H98: =INDEX('GD- LT atual'!$B$2:$D$62,MATCH('SFICS e LT'!F98,'GD- LT atual'!$C$2:$C$62,0),1) -> AGFSO001
B99: A.6.20. | C99: Recovery of bio-waste by anaerobic digestion or composting | D99: 260305 | E99: Recovery of bio-waste by anaerobic digestion or composting | F99: SCA010205 | G99: Social - Water and Waste Management | H99: =INDEX('GD- LT atual'!$B$2:$D$62,MATCH('SFICS e LT'!F99,'GD- LT atual'!$C$2:$C$62,0),1) -> AGFSO001
B100: A.6.21. | C100: Sorting of non-hazardous waste | D100: 260406 | E100: Sorting of non-hazardous waste | F100: SCA010205 | G100: Social - Water and Waste Management | H100: =INDEX('GD- LT atual'!$B$2:$D$62,MATCH('SFICS e LT'!F100,'GD- LT atual'!$C$2:$C$62,0),1) -> AGFSO001
B101: A.6.22. | C101: Depollution and dismantling of end-of-life products | D101: 260405 | E101: Depollution and dismantling of end-of-life products | F101: SCA010205 | G101: Social - Water and Waste Management | H101: =INDEX('GD- LT atual'!$B$2:$D$62,MATCH('SFICS e LT'!F101,'GD- LT atual'!$C$2:$C$62,0),1) -> AGFSO001
B102: A.6.23. | C102: Collection and transport of hazardous waste | D102: 260407 | E102: Collection and transport of hazardous waste | F102: SCA010205 | G102: Social - Water and Waste Management | H102: =INDEX('GD- LT atual'!$B$2:$D$62,MATCH('SFICS e LT'!F102,'GD- LT atual'!$C$2:$C$62,0),1) -> AGFSO001
B103: A.6.24. | C103: Remediation of legally non-conforming landfills and abandoned or illegal waste dumps | D103: 260501 | E103: Remediation of legally non-conforming landfills and abandoned or illegal waste dumps | F103: SCA010205 | G103: Social - Water and Waste Management | H103: =INDEX('GD- LT atual'!$B$2:$D$62,MATCH('SFICS e LT'!F103,'GD- LT atual'!$C$2:$C$62,0),1) -> AGFSO001
B104: A.6.25. | C104: Remediation of contaminated sites and areas | D104: 260502 | E104: Remediation of contaminated sites and areas | F104: SCA010205 | G104: Social - Water and Waste Management | H104: =INDEX('GD- LT atual'!$B$2:$D$62,MATCH('SFICS e LT'!F104,'GD- LT atual'!$C$2:$C$62,0),1) -> AGFSO001
B105: A.6.26. | C105: Terminology definitions | D105: - | F105: - | H105: =INDEX('GD- LT atual'!$B$2:$D$62,MATCH('SFICS e LT'!F105,'GD- LT atual'!$C$2:$C$62,0),1) -> #N/A
B106: A.7. | C106: Agriculture | E106: Agriculture | H106: =INDEX('GD- LT atual'!$B$2:$D$62,MATCH('SFICS e LT'!F106,'GD- LT atual'!$C$2:$C$62,0),1) -> #N/A
B107: A.7.1. | C107: Afforestation | D107: 270101 | E107: Afforestation | F107: SCA01010404 | G107: Afforestation / Reforestation | H107: =INDEX('GD- LT atual'!$B$2:$D$62,MATCH('SFICS e LT'!F107,'GD- LT atual'!$C$2:$C$62,0),1) -> AGFGR005
B108: A.7.2. | C108: Rehabilitation and restoration of forests, including reforestation and natural forest regeneration after an extreme event | D108: 270201 | E108: Rehabilitation and restoration of forests, including reforestation and natural forest regeneration after an extreme event | F108: SCA01010405 | G108: Land conservation and restoration & Soil Remediation | H108: =INDEX('GD- LT atual'!$B$2:$D$62,MATCH('SFICS e LT'!F108,'GD- LT atual'!$C$2:$C$62,0),1) -> AGFGR005
B109: A.7.3. | C109: Forest management | D109: 270102 | E109: Forest management | F109: SCA01010404 | G109: Afforestation / Reforestation | H109: =INDEX('GD- LT atual'!$B$2:$D$62,MATCH('SFICS e LT'!F109,'GD- LT atual'!$C$2:$C$62,0),1) -> AGFGR005
B110: A.7.4. | C110: Conservation forestry | D110: 270202 | E110: Conservation forestry | F110: SCA01010405 | G110: Land conservation and restoration & Soil Remediation | H110: =INDEX('GD- LT atual'!$B$2:$D$62,MATCH('SFICS e LT'!F110,'GD- LT atual'!$C$2:$C$62,0),1) -> AGFGR005
B111: A.7.5. | C111: Restoration of wetlands | D111: 270203 | E111: Restoration of wetlands | F111: SCA01010402 | G111: Sustainable agriculture | H111: =INDEX('GD- LT atual'!$B$2:$D$62,MATCH('SFICS e LT'!F111,'GD- LT atual'!$C$2:$C$62,0),1) -> AGFGR005
B112: A.7.6. | C112: Conservation, including restoration, of habitats, ecosystems and species | D112: 270204 | E112: Conservation, including restoration, of habitats, ecosystems and species | F112: SCA01010405 | G112: Land conservation and restoration & Soil Remediation | H112: =INDEX('GD- LT atual'!$B$2:$D$62,MATCH('SFICS e LT'!F112,'GD- LT atual'!$C$2:$C$62,0),1) -> AGFGR005
B113: A.7.7. | C113: Sustainable growing of crops | D113: 270301 | E113: Sustainable growing of crops | F113: SCA01010402 | G113: Sustainable agriculture | H113: =INDEX('GD- LT atual'!$B$2:$D$62,MATCH('SFICS e LT'!F113,'GD- LT atual'!$C$2:$C$62,0),1) -> AGFGR005
B114: A.7.8. | C114: Soil Remediation | D114: 270302 | E114: Soil Remediation | F114: SCA01010405 | G114: Land conservation and restoration & Soil Remediation | H114: =INDEX('GD- LT atual'!$B$2:$D$62,MATCH('SFICS e LT'!F114,'GD- LT atual'!$C$2:$C$62,0),1) -> AGFGR005
B115: A.7.9. | C115: Low-carbon agricultural technologies to improve efficiency (e.g. techniques used in precision farming, hydroponics farming, aeroponics farming) | D115: 270303 | E115: Low-carbon agricultural technologies to improve efficiency (e.g. techniques used in precision farming, hydroponics farming, aeroponics farming) | F115: SCA01010402 | G115: Sustainable agriculture | H115: =INDEX('GD- LT atual'!$B$2:$D$62,MATCH('SFICS e LT'!F115,'GD- LT atual'!$C$2:$C$62,0),1) -> AGFGR005
B116: A.7.10. | C116: Efficient electric machinery, excluding tech for livestock production | D116: 270304 | E116: Efficient electric machinery, excluding tech for livestock production | F116: SCA01010406 | G116: Animal husbandry | H116: =INDEX('GD- LT atual'!$B$2:$D$62,MATCH('SFICS e LT'!F116,'GD- LT atual'!$C$2:$C$62,0),1) -> AGFGR005
B117: A.7.11. | C117: Regenerative Farming | D117: 270305 | E117: Regenerative Farming | F117: SCA01010406 | G117: Animal husbandry | H117: =INDEX('GD- LT atual'!$B$2:$D$62,MATCH('SFICS e LT'!F117,'GD- LT atual'!$C$2:$C$62,0),1) -> AGFGR005
...

Sheet Mapeamento FC
E1: Categoria GD | F1: AGFSO001
B2: Code | C2: Categoria GD | H2: GD | I2: Descritivo | J2: SSTNBL_CTGRY
B3: 210101 | C3: AGFGR001 | E3: Row Labels | H3: 'AGFGR001' | I3: Energy | J3: ('210101','210102','210103','210104','210105','210106','210107','210108','210109','210110','210201','210202','210203','210204','210205','210206','210207','210208','210302','210419','210420','210421','210501','210601','210602','210603','280201','280202','280203') | K3: =_xlfn.CONCAT("WHEN ",$J$2," IN ",$J3," THEN ",$H3) -> WHEN SSTNBL_CTGRY IN ('210101','210102','210103','210104','210105','210106','210107','210108','210109','210110','210201','210202','210203','210204','210205','210206','210207','210208','210302','210419','210420','210421','210501','210601','210602','210603','280201','280202','280203') THEN 'AGFGR001'
B4: 210102 | C4: AGFGR001 | E4: 2401 | F4: =_xlfn.CONCAT("'",E4,"'",",") -> '2401', | H4: 'AGFGR002' | I4: Transport | J4: ('220501','220101','220102','220103','220106','220201','220202','220203','220204','220205','220206','220303') | K4: =_xlfn.CONCAT("WHEN ",$J$2," IN ",$J4," THEN ",$H4) -> WHEN SSTNBL_CTGRY IN ('220501','220101','220102','220103','220106','220201','220202','220203','220204','220205','220206','220303') THEN 'AGFGR002'
B5: 210103 | C5: AGFGR001 | E5: 2502 | F5: =_xlfn.CONCAT("'",E5,"'",",") -> '2502', | H5: 'AGFGR003' | I5: Transport | J5: ('220404','220104','220105','220301','220302','220401','220402','220403','220405') | K5: =_xlfn.CONCAT("WHEN ",$J$2," IN ",$J5," THEN ",$H5) -> WHEN SSTNBL_CTGRY IN ('220404','220104','220105','220301','220302','220401','220402','220403','220405') THEN 'AGFGR003'
B6: 210104 | C6: AGFGR001 | E6: 2503 | F6: =_xlfn.CONCAT("'",E6,"'",",") -> '2503', | H6: 'AGFGR005' | I6: Agriculture | J6: ('2704','2705','270201','270203','270204','270301','270302','270303','270304','270305','270306','270307','270308','270309','270310','270311','270101','270102','270202') | K6: =_xlfn.CONCAT("WHEN ",$J$2," IN ",$J6," THEN ",$H6) -> WHEN SSTNBL_CTGRY IN ('2704','2705','270201','270203','270204','270301','270302','270303','270304','270305','270306','270307','270308','270309','270310','270311','270101','270102','270202') THEN 'AGFGR005'
B7: 210105 | C7: AGFGR001 | E7: 3001 | F7: =_xlfn.CONCAT("'",E7,"'",",") -> '3001', | H7: 'AGFGR006' | I7: Construction and Real Estate | J7: ('2301') | K7: =_xlfn.CONCAT("WHEN ",$J$2," IN ",$J7," THEN ",$H7) -> WHEN SSTNBL_CTGRY IN ('2301') THEN 'AGFGR006'
B8: 210106 | C8: AGFGR001 | E8: 3102 | F8: =_xlfn.CONCAT("'",E8,"'",",") -> '3102', | H8: 'AGFGR007' | I8: Construction and Real Estate | J8: ('2302','230301') | K8: =_xlfn.CONCAT("WHEN ",$J$2," IN ",$J8," THEN ",$H8) -> WHEN SSTNBL_CTGRY IN ('2302','230301') THEN 'AGFGR007'
B9: 210201 | C9: AGFGR001 | E9: 210701 | F9: =_xlfn.CONCAT("'",E9,"'",",") -> '210701', | H9: 'AGFGR008' | I9: Construction and Real Estate | J9: ('230302','230303','230304') | K9: =_xlfn.CONCAT("WHEN ",$J$2," IN ",$J9," THEN ",$H9) -> WHEN SSTNBL_CTGRY IN ('230302','230303','230304') THEN 'AGFGR008'
B10: 210202 | C10: AGFGR001 | E10: 260104 | F10: =_xlfn.CONCAT("'",E10,"'",",") -> '260104', | H10: 'AGFGR009' | I10: Water and Waste | J10: ('2305','230601','280101') | K10: =_xlfn.CONCAT("WHEN ",$J$2," IN ",$J10," THEN ",$H10) -> WHEN SSTNBL_CTGRY IN ('2305','230601','280101') THEN 'AGFGR009'
B11: 210419 | C11: AGFGR001 | E11: 260403 | F11: =_xlfn.CONCAT("'",E11,"'",",") -> '260403', | H11: 'AGFGR010' | I11: Manufacturing | J11: ('280302','280303','280304','280504','280706','280107','2804','280501','280503','280505','280601','280602','280603','280701','280702','280703','280704','280705','280801','280802','280901','280902') | K11: =_xlfn.CONCAT("WHEN ",$J$2," IN ",$J11," THEN ",$H11) -> WHEN SSTNBL_CTGRY IN ('280302','280303','280304','280504','280706','280107','2804','280501','280503','280505','280601','280602','280603','280701','280702','280703','280704','280705','280801','280802','280901','280902') THEN 'AGFGR010'
B12: 210601 | C12: AGFGR001 | E12: 300201 | F12: =_xlfn.CONCAT("'",E12,"'",",") -> '300201', | H12: 'AGFGR011' | I12: Other Sectors | J12: ('2706','3101','280301','281001','260304','260601','260602','280502','280604','3104') | K12: =_xlfn.CONCAT("WHEN ",$J$2," IN ",$J12," THEN ",$H12) -> WHEN SSTNBL_CTGRY IN ('2706','3101','280301','281001','260304','260601','260602','280502','280604','3104') THEN 'AGFGR011'
B13: 210602 | C13: AGFGR001 | E13: 2304 | F13: =_xlfn.CONCAT("'",E13,"'",",") -> '2304', | H13: 'AGFSO001' | I13: Social | J13: ('2401','2502','2503','3001','3102','210701','260104','260403','300201','2304','230602','2501','260101','260102','260103','260201','260202','260203','260204','260205','260301','260302','260303','260305','260401','260402','260404','260405','260406','260407','260501','260502','300202','3103') | K13: =_xlfn.CONCAT("WHEN ",$J$2," IN ",$J13," THEN ",$H13) -> WHEN SSTNBL_CTGRY IN ('2401','2502','2503','3001','3102','210701','260104','260403','300201','2304','230602','2501','260101','260102','260103','260201','260202','260203','260204','260205','260301','260302','260303','260305','260401','260402','260404','260405','260406','260407','260501','260502','300202','3103') THEN 'AGFSO001'
B14: 210603 | C14: AGFGR001 | E14: 230602 | F14: =_xlfn.CONCAT("'",E14,"'",",") -> '230602',
B15: 210203 | C15: AGFGR001 | E15: 2501 | F15: =_xlfn.CONCAT("'",E15,"'",",") -> '2501 ',
B16: 210420 | C16: AGFGR001 | E16: 260101 | F16: =_xlfn.CONCAT("'",E16,"'",",") -> '260101',
B17: 210421 | C17: AGFGR001 | E17: 260102 | F17: =_xlfn.CONCAT("'",E17,"'",",") -> '260102',
B18: 210501 | C18: AGFGR001 | E18: 260103 | F18: =_xlfn.CONCAT("'",E18,"'",",") -> '260103',
B19: 210107 | C19: AGFGR001 | E19: 260201 | F19: =_xlfn.CONCAT("'",E19,"'",",") -> '260201',
B20: 210108 | C20: AGFGR001 | E20: 260202 | F20: =_xlfn.CONCAT("'",E20,"'",",") -> '260202',
B21: 210204 | C21: AGFGR001 | E21: 260203 | F21: =_xlfn.CONCAT("'",E21,"'",",") -> '260203',
B22: 210205 | C22: AGFGR001 | E22: 260204 | F22: =_xlfn.CONCAT("'",E22,"'",",") -> '260204',
B23: 210109 | C23: AGFGR001 | E23: 260205 | F23: =_xlfn.CONCAT("'",E23,"'",",") -> '260205',
B24: 210110 | C24: AGFGR001 | E24: 260301 | F24: =_xlfn.CONCAT("'",E24,"'",",") -> '260301',
B25: 210206 | C25: AGFGR001 | E25: 260302 | F25: =_xlfn.CONCAT("'",E25,"'",",") -> '260302',
... B28: 210302 | C28: AGFGR001 | E28: 260401 | F28: =_xlfn.CONCAT("'",E28,"'",",") -> '260401',
B29: 210701 | C29: AGFSO001 | E29: 260402 | F29: =_xlfn.CONCAT("'",E29,"'",",") -> '260402',
B30: 220101 | C30: AGFGR002 | E30: 260404 | F30: =_xlfn.CONCAT("'",E30,"'",",") -> '260404',
B31: 220102 | C31: AGFGR002 | E31: 260405 | F31: =_xlfn.CONCAT("'",E31,"'",",") -> '260405',
B32: 220103 | C32: AGFGR002 | E32: 260406 | F32: =_xlfn.CONCAT("'",E32,"'",",") -> '260406',
B33: 220104 | C33: AGFGR003 | E33: 260407 | F33: =_xlfn.CONCAT("'",E33,"'",",") -> '260407',
B34: 220105 | C34: AGFGR003 | E34: 260501 | F34: =_xlfn.CONCAT("'",E34,"'",",") -> '260501',
B35: 220106 | C35: AGFGR002 | E35: 260502 | F35: =_xlfn.CONCAT("'",E35,"'",",") -> '260502',
B36: 220201 | C36: AGFGR002 | E36: 300202 | F36: =_xlfn.CONCAT("'",E36,"'",",") -> '300202',
B37: 220202 | C37: AGFGR002 | E37: 3103 | F37: =_xlfn.CONCAT("'",E37,"'",",") -> '3103 ',
B38: 220203 | C38: AGFGR002 | E38: Grand Total
B39: 220204 | C39: AGFGR002
B40: 220205 | C40: AGFGR002
B41: 220206 | C41: AGFGR002
B42: 220401 | C42: AGFGR003
B43: 220405 | C43: AGFGR003
B44: 220402 | C44: AGFGR003
B45: 220403 | C45: AGFGR003
B46: 220404 | C46: AGFGR003
B47: 220301 | C47: AGFGR003
B48: 220302 | C48: AGFGR003
B49: 220303 | C49: AGFGR002
B50: 220501 | C50: AGFGR002
B51: 2301 | C51: AGFGR006
B52: 2302 | C52: AGFGR007
B53: 230301 | C53: AGFGR007
B54: 230302 | C54: AGFGR008
B55: 230303 | C55: AGFGR008
B56: 230304 | C56: AGFGR008
B57: 2304 | C57: AGFSO001
B58: 2305 | C58: AGFGR009
B59: 230601 | C59: AGFGR009
B60: 230602 | C60: AGFSO001
B61: 2401 | C61: AGFSO001
B62: 2501 | C62: AGFSO001
B63: 2502 | C63: AGFSO001
B64: 2503 | C64: AGFSO001
B65: 260101 | C65: AGFSO001
B66: 260104 | C66: AGFSO001
B67: 260201 | C67: AGFSO001
B68: 260401 | C68: AGFSO001
B69: 260301 | C69: AGFSO001
B70: 260302 | C70: AGFSO001
B71: 260303 | C71: AGFSO001
B72: 260402 | C72: AGFSO001
B73: 260304 | C73: AGFGR011
B74: 260601 | C74: AGFGR011
B75: 260602 | C75: AGFGR011
B76: 260102 | C76: AGFSO001
B77: 260103 | C77: AGFSO001
B78: 260202 | C78: AGFSO001
... B81: 260205 | C81: AGFSO001
B82: 260403 | C82: AGFSO001
B83: 260404 | C83: AGFSO001
B84: 260305 | C84: AGFSO001
B85: 260406 | C85: AGFSO001
B86: 260405 | C86: AGFSO001
B87: 260407 | C87: AGFSO001
B88: 260501 | C88: AGFSO001
B89: 260502 | C89: AGFSO001
B90: 270101 | C90: AGFGR005
B91: 270201 | C91: AGFGR005
B92: 270102 | C92: AGFGR005
B93: 270202 | C93: AGFGR005
B94: 270203 | C94: AGFGR005
B95: 270204 | C95: AGFGR005
B96: 270301 | C96: AGFGR005
B97: 270302 | C97: AGFGR005
B98: 270303 | C98: AGFGR005
B99: 270304 | C99: AGFGR005
B100: 270305 | C100: AGFGR005
B101: 270306 | C101: AGFGR005
B102: 270307 | C102: AGFGR005
B103: 270308 | C103: AGFGR005
B104: 2704 | C104: AGFGR005
...

Sheet Resultados LT
