Workbook

Sheet 0. Instructions
B2: Instructions
B3: In order facilitate reaching an understanding of the data requirements a description of the functionality of each column is provided below:
B5: Data Compilation
B6: Metric Name: Name given to the data
B7: Metric Description: Functional description of the data
B9: Operational Information
B10: Scope Business: Customer segment for which it is required to provision the data
B11: Level: level of granularity of the information required (Counterparty, Contract,etc)
B12: Frequency: frequency with which data is required
B13: Deadline for data availability: when data need to be available to be consumed for be used in pilot or reporting
B14: Related Standard: if data is used in other standard or regulation (e.g. FINREP). In affirmative case, data should be aligned with the data used in other standard
B16: Pillar III
... B44: If the balance sheet of the last 24 months is not available, previous balance sheet will be used, following the same priority as explained before.

Sheet 1. Data dictionary
A1: Cardinality | C1: Data Compilation | G1: Sourcing | M1: Pillar III: Uses and Guidelines | Q1: Data Quality Indicators (DQIs)
Q2: Completeness | R2: Accuracy | V2: Consistency | X2: Comments
A3: Metric | B3: Applicability to units | C3: Metric Name | D3: Metric Description | E3: Scope Business | F3: Level (op, client,…) | G3: Estrategical Source | H3: Loan tapes inclusion | I3: External Data Providers referenced by HQ | J3: Needed to report a tactical to HQ? | K3: Needed to be reported to HQ by the Unit | M3: Template | N3: Satelite | O3: HQ functional guidelines | P3: Use of variable | R3: Format checking | S3: Ranges and dimensions validation | T3: Integrity checks between correlated data | U3: Duplicates detection | V3: Key data elements conciliation against other reporting | W3: Consistency checks with external data
K4: Origin Source | L4: Local Data Owner
A5: 1 | B5: All | C5: GHG Financed Emissions: Scope 1 | D5: Scope 1 emissions are direct greenhouse (GHG) emissions that occur from sources that are controlled or owned by an organization (e.g., emissions associated with fuel combustion in boilers, furnaces, vehicles). | E5: Banking Book: Non-Financial Corporation | F5: Client | G5: This metric has been requested to be included in BDR. Comments on whether or not they will be included are pending. All units will be notified as soon as we receive it. | H5: Yes | I5: CDP & PCAF | J5: No | K5: TBD | L5: TBD | M5: T1 | N5: GHGE_GHG Financed emissions | O5: Functional guidelines will be provided by HQ for sourcing this variable. | Q5: x | R5: Numeric (CO2 tonnes (TCO2)) | S5: >=0. In case value = 0 or <0, review if it is correct. | T5: - If scope 2 informed, scope 1 should be informed - If scope 3 informed, scope 1&2 should be informed. | X5: Real data preferred (published by counterparty) to estimations (sector/country average, PCAF), thus required effort to identify based on counterparty's publications.
A6: 2 | B6: All | C6: GHG Financed Emissions: Scope 2 | D6: Scope 2 emissions are indirect emissions from the generation of purchased energy, from a utility provider. In other words, all GHG emissions released in the atmosphere, from the consumption of purchased electricity, steam, heat and cooling. For most organizations, electricity will be the unique source of scope 2 emissions. | E6: Banking Book: Non-Financial Corporation | F6: Client | G6: This metric has been requested to be included in BDR. Comments on whether or not they will be included are pending. All units will be notified as soon as we receive it. | H6: Yes | I6: CDP & PCAF | J6: No | K6: TBD | L6: TBD | M6: T1 | N6: GHGE_GHG Financed emissions | O6: Functional guidelines will be provided by HQ for sourcing this variable.
A7: 3 | B7: All | C7: GHG Financed Emissions: Scope 3 | D7: Counterparties’ scope 3 emissions associated with lending and investment activities. Scope 3 emissions shall be disclosed on a best effort basis covering the most relevant sectors for example in line with PCAF approach and the phased-in approach for scope 3. Financial institutions shall start disclosing information scope 3 emissions, when available, for the oil, gas, and mining sectors from 2021 onward and additional sectors will be added subsequently. Information on scope 3 emissions of the counterparty for all sectors included in the template shall be disclosed as of 30 June 2024 first disclosure reference date. For sectors where data and methodological challenges exist, banks shall follow the GHG protocol and its 15 stages, both upstream and downstream, as presented in the Commission Guidelines on non-financial reporting: supplement on reporting climate related information. | E7: Banking Book: Non-Financial Corporation | F7: Client | G7: This metric has been requested to be included in BDR. Comments on whether or not they will be included are pending. All units will be notified as soon as we receive it. | H7: Yes | I7: CDP & PCAF | J7: No | K7: TBD | L7: TBD | M7: T1 | N7: GHGE_GHG Financed emissions | O7: Functional guidelines will be provided by HQ for sourcing this variable.
A8: 4 | B8: For units in Europe | C8: Geography of the collateral: NUTS | D8: Location of the collateral's country, geographical or administrative region (maximum level of available breakdown) where activities of the counterparty are located. For EU countries + UK the level of divisions indicated in Nomenclature of Territorial Units for Statistics (NUTS) shall be used. The NUTS classification is a hierarchical system for dividing up the economic territory of the EU and the UK: - NUTS 1: major socio-economic regions - NUTS 2: basic regions for the application of regional policies - NUTS 3: small regions for specific diagnoses In the following link NUTs codes are available: https://ec.europa.eu/eurostat/documents/3859598/10967554/KS-GQ-20-092-EN-N.pdf/9d57ae79-3ee7-3c14-da3e-34726da385cf?t=1591285035000 For non EU countries equivalent classification shall be used. | E8: Banking Book: Non-Financial Corporation, Households (Commercial and Residential) and Repossessed Collaterals | F8: Collateral | G8: This metric has been requested to be included in BDR. Comments on whether or not they will be included are pending. All units will be notified as soon as we receive it. | H8: Yes | J8: Yes | K8: Table: cd_estruturais.tat91_tabelas where tayd91c0_ctabela = 'J48' Var: tayd91c0_nelemc05 (NUT3) NOTA: When there is no information for NUTS3, it is used NUTS1. For countries outside the EU, it is used the 3 digits ISO code. | L8: CDO | M8: T2 T5 | N8: CESG_CNAE_ESG ENPC_Energy_Performance_Certificate | Q8: x | R8: Numeric | S8: All codes are part of the reference pre-defined list of values (NUT3, Postal Code or equivalent)
A9: 5 | B9: All | C9: Geography of the collateral: ZIP Code | D9: Postal Code associated to the location of the collateral | E9: Banking Book: Non-Financial Corporation, Households (Commercial and Residential) and Repossessed Collaterals | F9: Collateral | G9: BDR: Table: JM_GARA_REAL Var: codposgr | H9: Yes | J9: Yes | K9: Table: cd_garantias.gt009_bens_imov Var: cpost | L9: CDO | M9: T2 T5 | N9: CESG_CNAE_ESG ENPC_Energy_Performance_Certificate | Q9: x | R9: Numeric | S9: All codes are part of the reference pre-defined list of values (NUT3, Postal Code or equivalent)
A10: 6 | B10: Not necessary at the moment. Having the zip code or the NUTS is enough | C10: Geography of the collateral: Full Address | D10: Full address associated to the location of the collateral | E10: Banking Book: Non-Financial Corporation, Households (Commercial and Residential) and Repossessed Collaterals | F10: Collateral | G10: This metric has been requested to be included in BDR. Comments on whether or not they will be included are pending. All units will be notified as soon as we receive it. | H10: Yes | J10: No | K10: N/A | L10: N/A | M10: T2 T5 | N10: CESG_CNAE_ESG ENPC_Energy_Performance_Certificate | Q10: x | R10: Numeric | S10: All codes are part of the reference pre-defined list of values (NUT3, Postal Code or equivalent)
A11: 7 | B11: Only for ESP, PT and UK | C11: EPC label | D11: Letter code representing the energy performance of the collateral (from A to G) regarding the energy consumption. For EU countries, the label of the energy performance certificate (EPC) recognised by a Member State or by a legal person designated by it, which indicates the energy performance of a building or building unit, calculated according to the methodology set out in Annex I of 2010/31/EU Directive. For exposures outside the EU, the label of the EPC of the collateral as defined in the relevant regulation, where a mapping to the EU EPC label exists. | E11: Banking Book: Households (Commercial and Residential) and Repossessed Collaterals | F11: Collateral | G11: This metric has been requested to be included in BDR. Comments on whether or not they will be included are pending. All units will be notified as soon as we receive it. | H11: Yes | I11: Landmark & Gloval | J11: Yes | K11: External Provider | L11: N/A | M11: T2 | N11: ENPC_Energy_Performance_Certificate | O11: Functional guidelines will be provided by HQ for sourcing this variable. | Q11: x | R11: Text | S11: All possible labels are part of the reference Group list of EPCs. Possible values: A-G | U11: Only an EPC label can be declared by property | X11: Changes > +/- 10% to be justified (i.e. changes in the composition of the portfolio due to the acquisition of material CRE, periodic updates of overduew EPC labels). Se va a pedir One-Off, no se si es viable ver tendencias o evoluciones
A12: 8 | B12: Only for ESP, PT, UK and POL | C12: EP Score | D12: Specific energy consumption of a collateral in kWh/m² per year, as indicated in the EPC label of the collateral. | E12: Banking Book: Households (Commercial and Residential) and Repossessed Collaterals | F12: Collateral | G12: This metric has been requested to be included in BDR. Comments on whether or not they will be included are pending. All units will be notified as soon as we receive it. | H12: Yes | I12: Landmark & Gloval | J12: Yes | K12: External Provider | L12: N/A | M12: T2 | N12: ENPC_Energy_Performance_Certificate | O12: Functional guidelines will be provided by HQ for sourcing this variable. | Q12: x | R12: Numeric (kWh/m² ) | S12: >=0 | X12: -To be informed at least when EPC is required by local applicable law / internal bank's procedures. - Ideally for all potential existing cases. Same criteria as for EPC label.
A13: 9 | B13: Only for ESP, PT and UK | C13: EPC Label: Flag original / calculated | D13: This flag allows to identify if the EPC Label data is original or calculated. Original data means that the EPC data asigned to the collateral is a real value of the EPC label vs "calculated", meaning that the institution has applied some kind of methodology to estimate the EPC related data. | E13: Banking Book: Households (Commercial and Residential) and Repossessed Collaterals | F13: Collateral | G13: This metric has been requested to be included in BDR. Comments on whether or not they will be included are pending. All units will be notified as soon as we receive it. | H13: Yes | I13: Landmark & Gloval | J13: Yes | K13: External Provider | L13: N/A | M13: T2 | N13: ENPC_Energy_Performance_Certificate | O13: Functional guidelines will be provided by HQ for sourcing this variable. | Q13: x
A14: 10 | B14: Only for ESP, PT, UK and POL | C14: EP Score: Flag original / calculated | D14: This flag allows to identify if the EPC score data is original or calculated. Original data means that the EPC data asigned to the collateral is a real value of the EPC score vs "calculated", meaning that the institution has applied some kind of methodology to estimate the EPC related data. | E14: Banking Book: Households (Commercial and Residential) and Repossessed Collaterals | F14: Collateral | G14: This metric has been requested to be included in BDR. Comments on whether or not they will be included are pending. All units will be notified as soon as we receive it. | H14: Yes | I14: Landmark & Gloval | K14: External Provider | L14: N/A | M14: T2 | N14: ENPC_Energy_Performance_Certificate | O14: Functional guidelines will be provided by HQ for sourcing this variable. | Q14: x
A15: 11 | B15: Only for ESP, PT and UK | C15: EPC CO2 emissions | D15: Specific emissions of a collateral in kgCO2/m² per year, as indicated in the EPC label of the collateral. | E15: Banking Book: Households (Commercial and Residential) and Repossessed Collaterals | F15: Collateral | G15: This metric has been requested to be included in BDR. Comments on whether or not they will be included are pending. All units will be notified as soon as we receive it. | H15: No | J15: No | K15: External Provider | L15: N/A | M15: T1 T3 | N15: N/A - Variable not reported in the satelite, used as an input | O15: Functional guidelines will be provided by HQ for sourcing this variable. | P15: For financed emissions: Commercial Real Estate | Q15: x | R15: Numeric (kgCO2/m²) | S15: >=0
A16: 12 | B16: All | C16: Non-performing | D16: Credit risk classification of the exposure that meets at least one of the following criteria: a) An exposure in respect of which a default is considered to have occurred in accordance with CRR, Article 178 (Default of an Obligor). Where the institution has on-balance-sheet exposures to an obligor that are past due by more than 90 days and that represent more than 20 % of all on-balance-sheet exposures to that obligor, all on- and off-balance-sheet exposures to that obligor shall be considered to be non-performing. (b) An exposure which is considered to be impaired in accordance with the applicable accounting framework; (c) An exposure under probation, where additional forbearance measures are granted or where the exposure becomes more than 30 days past due; (d) An exposure in the form of a commitment that, were it drawn down or otherwise used, would likely not be paid back in full without realisation of collateral; (e) An exposure in form of a financial guarantee that is likely to be called by the guaranteed party, including where the underlying guaranteed exposure meets the criteria to be considered as non-performing. | E16: Banking Book: Financial Corporations, Non-Financial Corporations, Credit Institutions, Households (Commercial and Residential), General Governments | F16: Contract | G16: BDR Table: JM_CTO_AJ_REG Var: O9209_INDMORA1 | H16: No (esperaría que ya esté incluida) | J16: No | K16: Table: cd_captools.fr004_cto Var: stage_atual | L16: Risk | M16: T1 T5 | N16: CESG_CNAE_ESG | Q16: x
A17: 13 | B17: All | C17: Gross carrying amount | D17: Exposures must be reported on a gross carrying amount basis | E17: Banking Book: Financial Corporations, Non-Financial Corporations, Credit Institutions, Households (Commercial and Residential), General Governments | F17: Contract | G17: This metric has been requested to be included in BDR. Comments on whether or not they will be included are pending. All units will be notified as soon as we receive it. | H17: No (esperaría que ya esté incluida) | J17: No | K17: Table: cd_captools.fr004_cto Var: valor_bruto_on_a | L17: Accounting | M17: T1, T2, T3, T4, T5, T6, T7, T8, T9, T10 | N17: CESG_CNAE_ESG ENPC_Energy_Performance_Certificate MITI_Mitigation actions GARB_GAR & BTAR GHGE_GHG Financed emissions | Q17: x
A18: 14 | B18: All | C18: Main NACE code | D18: National Classification of Economic Activities, prepared according to the conditions contained in the EC regulation 1893/2006 for the approval of the Statistical Nomenclature of Economic Activities of the European Community (NACE). The counterparty NACE sector allocation shall be based on the nature of the immediate counterparty. Each counterparty has to be mapped to one single sector based on its principle activity NACE code has to be completed with NACE level 4 detail | E18: Banking Book: Non-Financial Corporations | F18: Client | G18: BDR Table: JM_CLIENT_BII Var: G4093_COD_SECT | H18: Yes at a NACE4 level | J18: Yes | K18: Table: cd_captools.ct003_univ_cli Var: nace_code | L18: Accounting | M18: T1 T3 T5 T7 | N18: CESG_CNAE_ESG ENPC_Energy_Performance_Certificate GARB_GAR & BTAR GHGE_GHG Financed emissions | O18: Functional guidelines will be provided by HQ for sourcing this variable. | Q18: x | R18: Numeric | S18: -All codes are part of the reference Group list of NACE codes -Level 3 NACEs are required as a minimum. Level 4 is highly recommended (mandatory in future). | V18: Same as reported in FINREP | W18: Review with evidence of the total portfolio segmented by client relevance in which we see that the NACE is correct (external data, public information, risk analysts). Ensure that the NACE described is aligned with the main activity of the company
A19: 15 | B19: All | C19: NACE Code ESG | D19: The counterparty NACE sector allocation shall be based on the nature of the immediate counterparty. When the counterparty is a holding company, institutions shall consider the NACE sector of the specific obligor under the holding company (if different than the holding company itself) which receives the funding (i.e., the specific subsidiary of the holding company in question) rather than that of the holding company; particularly in those cases where the obligor that is benefiting from the financing is a non-financial corporate. Similarly, when the direct counterparty (the obligor) is a special purpose vehicle (SPV), institution shall disclose the relevant information under the NACE sector associated with the economic activity of the parent company of the SPV. The classification of the exposures incurred jointly by more than one obligor shall be done based on the characteristics of the obligor that was the more relevant, or determinant, for the institution to grant the exposure. The distribution of jointly incurred exposures by NACE codes shall be driven by the characteristics of the more relevant or determinant obligor. NACE code ESG has to be completed with NACE level 4 detail | E19: Banking Book: Non-Financial Corporations | F19: Client | G19: This metric has been requested to be included in BDR. Comments on whether or not they will be included are pending. All units will be notified as soon as we receive it. | H19: Yes | J19: Yes | K19: Table: cd_captools.ct003_univ_cli Var: nace_code | L19: Accounting | M19: T1 T3 T5 T7 | N19: CESG_CNAE_ESG ENPC_Energy_Performance_Certificate GARB_GAR & BTAR GHGE_GHG Financed emissions | O19: Functional guidelines will be provided by HQ for sourcing this variable. | Q19: x | R19: Numeric | S19: -All codes are part of the reference Group list of NACE codes -Level 4 NACEs are required as a minimum. | V19: Same as reported in FINREP unless Counterparty under SPV or Holding Company with different NACE | W19: Review with evidence of the total portfolio segmented by client relevance in which we see that the NACE is correct (external data, public information, risk analysts). Ensure that the NACE described is aligned with the main activity of the company
A20: 16 | B20: All | C20: % Collateralised | D20: Percentage of the gross carrying amount of the collateral that can be considered arising from loans collateralised by residential or commercial immovable property. Residential property is defined as a residence which is occupied by the owner or the lessee of the residence, including the right to inhabit an apartment in housing cooperatives located in Sweden. Loans collateralised by comercial immovable property shall include loans secured by pledges of immovable property other than residential, including offices and commercial premises and other types of commercial immovable property. | E20: Banking Book: Households (Commercial and Residential) and Repossessed Collaterals | F20: Contract | G20: BDR: Table:(JM_GARANT_CTO) Var:(G4124_PORCOBER) | H20: No (esperaría que ya esté incluida) | J20: No | K20: Table: cd_garantias.gt018_rateio_aval Var: per_cobert | L20: CDO | M20: T2 T5 T6 T7 T8 T9.1 T9.2 | N20: CESG_CNAE_ESG ENPC_Energy_Performance_Certificate MITI_Mitigation actions GARB_GAR & BTAR | Q20: x
A21: 17 | B21: All | C21: Accumulated impairment | D21: Accumulated changes in fair value due to credit risk where the accumulated net change is negative. The accumulated net change in fair value due to credit risk shall be calculated by adding all negative and positive changes in fair value due to credit risk that have occurred since recognition of the debt instrument. That amount shall only be reported where the addition of positive and negative changes in fair value due to credit risk results in a negative amount. The valuation of the debt instruments shall be performed on the level of single financial instruments. | E21: Banking Book: Financial Corporations, Non-Financial Corporations, Credit Institutions, Households (Commercial and Residential), General Governments | F21: Contract | G21: BDR: Table: JM_CTO_AJ_REG Var: O9209_IPROVISI | H21: No (esperaría que ya esté incluida) | J21: No | K21: Table: cd_captools.fr004_cto Var: provisao | L21: Risk | M21: T1 T5 | N21: CESG_CNAE_ESG | Q21: x
A22: 18 | B22: All | C22: Type of activity | D22: Transitional activity: must not have a technologically and economically feasible low-carbon alternative but supports the transition to a climate-neutral economy consistent with a pathway to limit the temperature increase to 1,5 ºC above pre- industrial levels, including by phasing out greenhouse gas emissions, in particular emissions from solid fossil fuels, and where that activity: (a) has greenhouse gas emission levels that correspond to the best performance in the sector or industry; (b) does not hamper the development and deployment of low-carbon alternatives; and (c) does not lead to a lock-in of carbon-intensive assets, considering the economic lifetime of those assets. This kind of activity shall also qualify as contributing substantially to the objective of climate change mitigation Adaptation activity: (a) include adaptation solutions that either substantially reduce the risk of the adverse impact of the current climate and the expected future climate on that economic activity or substantially reduce that adverse impact, without increasing the risk of an adverse impact on people, nature or assets; or (b) provides adaptation solutions that, in addition to satisfying the conditions set out in Article 16, contribute substantially to preventing or reducing the risk of the adverse impact of the current climate and the expected future climate on people, nature or assets, without increasing the risk of an adverse impact on other people, nature or assets. This kind of activity shall also qualify as contributing substantially to the objective of climate change adaptation Enabling activity: must be contributing substantially to one or more of the environmental objectives set out in the Taxonomy Regulation by directly enabling other activities to make a substantial contribution to one or more of those objectives, provided that such economic activity: (a) does not lead to a lock-in of assets that undermine long-term environmental goals, considering the economic lifetime of those assets; and (b) has a substantial positive environmental impact, on the basis of life-cycle considerations. This kind of activity shall also qualify as contributing substantially to the objective of climate change mitigation or adaptation None of these activities: If none of this characteristics apply | E22: Banking Book: Financial Corporations, Non-Financial Corporations, Credit Institutions, Households (Commercial and Residential), General Governments | F22: Contract | G22: This metric has been requested to be included in BDR. Comments on whether or not they will be included are pending. All units will be notified as soon as we receive it. | H22: Yes | J22: No | K22: TBD | L22: TBD | M22: T7 T8 T9.1 T9.2 T9.3 | N22: GARB_GAR & BTAR | O22: Functional guidelines will be provided by HQ for sourcing this variable. | Q22: x
A23: 19 | B23: All | C23: Type of asset | D23: Breakdown of immovable properties obtained by taking posession, distinguising: - Residential property. Residential property is defined as a residence which is occupied by the owner or the lessee of the residence, including the right to inhabit an apartment in housing cooperatives located in Sweden. - Commercial property. Immovable property other than residential, including offices and commercial premises and other types of commercial immovable property - Other. When a collateral is neither classified as residential nor commercial property. | E23: Banking Book: Repossessed Collaterals | F23: Contract | G23: BDR Table: JM_INM_POSADJ Var: O9220_TIP_ACT | H23: No (esperaría que ya esté incluida) | J23: No | K23: Table: cd_garantias.gt009_bens_imov Var: cfinbem, ctipbem | L23: CDO | M23: T2 T5 T6 T7 T8 T9.1 T9.2 T9.3 | N23: CESG_CNAE_ESG ENPC_Energy_Performance_Certificate GARB_GAR & BTAR | Q23: x
A24: 20 | B24: All | C24: Flag: Companies excluded from EU Paris-aligned benchmarks | D24: This flag allows to identify which counterparties that are excluded from the EU Paris-aligned Benchmarks as specified in Article 12.1, points (d) to (g) and Article 12.2 of Commission Delegated Regulation (EU) 2020/1818: d) companies that derive 1 % or more of their revenues from exploration, mining, extraction, distribution or refining of hard coal and lignite; (e) companies that derive 10 % or more of their revenues from the exploration, extraction, distribution or refining of oil fuels; (f) companies that derive 50 % or more of their revenues from the exploration, extraction, manufacturing or distribution of gaseous fuels; (g) companies that derive 50 % or more of their revenues from electricity generation with a GHG intensity of more than 100 g CO2 e/kWh. Companies to significantly harm one or more of the environmental objectives referred to in Article 9 of Regulation (EU) 2020/852 of the European Parliament and of the Council (8), in accordance with the rules on estimations laid down in Article 13(2) of this Regulation | E24: Banking Book: Non-Financial Corporations | F24: Client | G24: This metric has been requested to be included in BDR. Comments on whether or not they will be included are pending. All units will be notified as soon as we receive it. | H24: Yes | I24: S&P | J24: No | K24: File provided by HQ | L24: N/A | M24: T1 | N24: CESG_CNAE_ESG | O24: Functional guidelines will be provided by HQ for sourcing this variable. | Q24: x
A25: 21 | B25: All | C25: Flag of NFRD applicability | D25: This flag allows to identify if the NFRD is applicable: '- NFCs subject to NFRD disclosure obligations. Large corporations and quasi-corporations not engaged in financial intermediation but principally in the production of market goods and non-financial services, considered public interest entities exceeding on their balance sheet dates the criterion of the average number of 500 employees during the financial year. '- SMEs and NFC (other than SMEs) not subject to NFRD disclosure obligations. For disclosures involving corporates not subject to NFRD disclosure obligations, including SMEs, when assessing general purpose lending/financing with unknown use of proceeds, institutions shall follow a simplified approach and focus their assessment on the main economic activity of the corporate, that is, on their main source of turnover, in order to determine the overall alignment of the exposures with the Taxonomy Regulation. In the case of specialised lending the assessment shall be based on the extent and proportion to which the specific project funded qualify as contributing substantially to climate change mitigation or adaptation (project specific information). | E25: Banking Book: Non-Financial Corporations | F25: Client | G25: This metric has been requested to be included in BDR. Comments on whether or not they will be included are pending. All units will be notified as soon as we receive it. | H25: Yes | J25: No | K25: TBD | L25: TBD | M25: T6 T7 T8 T9.1 T9.2 T9.3 | N25: GARB_GAR & BTAR | O25: Functional guidelines will be provided by HQ for sourcing this variable. | Q25: x
A26: 22 | B26: For units in Europe | C26: Geography of the counterparty: NUTS | D26: Location of the counterparty's country, geographical or administrative region (maximum level of available breakdown) where activities of the counterparty are located. For EU countries + UK the level of divisions indicated in Nomenclature of Territorial Units for Statistics (NUTS) shall be used. The NUTS classification is a hierarchical system for dividing up the economic territory of the EU and the UK: - NUTS 1: major socio-economic regions - NUTS 2: basic regions for the application of regional policies - NUTS 3: small regions for specific diagnoses In the following link NUTs codes are available: https://ec.europa.eu/eurostat/documents/3859598/10967554/KS-GQ-20-092-EN-N.pdf/9d57ae79-3ee7-3c14-da3e-34726da385cf?t=1591285035000 For non EU countries equivalent classification shall be used. | E26: Banking Book: Non-Financial Corporation, Households (Commercial and Residential) and Repossessed Collaterals | F26: Client | G26: This metric has been requested to be included in BDR. Comments on whether or not they will be included are pending. All units will be notified as soon as we receive it. | H26: Yes | J26: Yes | K26: Table: cd_estruturais.tat91_tables where tayd91c0_ctable = 'J48' Var: tayd91c0_nelemc05 | L26: CDO | M26: T5 | N26: CESG_CNAE_ESG | Q26: x | R26: Numeric | S26: All codes are part of the reference pre-defined list of values (NUT3, Postal Code or equivalent)
A27: 23 | B27: All | C27: Geography of the counterparty: ZIP Code | D27: Postal Code associated to the location of the counterparty's country, geographical or administrative region where activities of the counterparty are located. | E27: Banking Book: Non-Financial Corporation, Households (Commercial and Residential) and Repossessed Collaterals | F27: Client | G27: BDR Table: JM_CLIENT_BII Var: G4093_CDPOSTAL | H27: Yes | J27: Yes | K27: Table cd_estruturais.interface_moradas Var: clyr7003_cpostal + clyr7003_cp3 | L27: CDO | M27: T2, T5 | N27: CESG_CNAE_ESG ENPC_Energy_Performance_Certificate | Q27: x | R27: Numeric | S27: All codes are part of the reference pre-defined list of values (NUT3, Postal Code or equivalent)
A28: 24 | B28: Not necessary at the moment. Having the zip code or the NUTS is enough | C28: Geography of the counterparty: Full Address | D28: Full address associated to the location of the counterparty's country, geographical or administrative region where activities of the counterparty are located. | E28: Banking Book: Non-Financial Corporation, Households (Commercial and Residential) and Repossessed Collaterals | F28: Client | G28: This metric has been requested to be included in BDR. Comments on whether or not they will be included are pending. All units will be notified as soon as we receive it. | H28: Yes | J28: No | K28: TBD | L28: TBD | M28: T2, T5 | N28: CESG_CNAE_ESG ENPC_Energy_Performance_Certificate | Q28: x | R28: Numeric | S28: All codes are part of the reference pre-defined list of values (NUT3, Postal Code or equivalent)
A29: 25 | B29: All | C29: GHG Reported Emissions - scope 1: flag original / calculated | D29: This flag allows to identify if the data is original data refered to counterparties’ scope 1 emissions associated with lending and investment activities based on information disclosed by the Group's counterparties or reported to the Group on bilateral basis. | E29: Banking Book: Non-Financial Corporations | F29: Client | G29: This metric has been requested to be included in BDR. Comments on whether or not they will be included are pending. All units will be notified as soon as we receive it. | H29: Yes | I29: CDP & PCAF | J29: No | K29: TBD | L29: TBD | M29: T1 | N29: GHGE_GHG Financed emissions | O29: Functional guidelines will be provided by HQ for sourcing this variable. | Q29: x
A30: 26 | B30: All | C30: GHG Reported Emissions - scope 2: flag original / calculated | D30: This flag allows to identify if the data is original data refered to counterparties’ scope 2 emissions associated with lending and investment activities based on information disclosed by the Group's counterparties or reported to the Group on bilateral basis. | E30: Banking Book: Non-Financial Corporations | F30: Client | G30: This metric has been requested to be included in BDR. Comments on whether or not they will be included are pending. All units will be notified as soon as we receive it. | H30: Yes | I30: CDP & PCAF | J30: No | K30: TBD | L30: TBD | M30: T1 | N30: GHGE_GHG Financed emissions | O30: Functional guidelines will be provided by HQ for sourcing this variable. | Q30: x
A31: 27 | B31: All | C31: GHG Reported Emissions - scope 3: flag original / calculated | D31: This flag allows to identify if the data is original data refered to counterparties’ scope 3 emissions associated with lending and investment activities based on information disclosed by the Group's counterparties or reported to the Group on bilateral basis. | E31: Banking Book: Non-Financial Corporations | F31: Client | G31: This metric has been requested to be included in BDR. Comments on whether or not they will be included are pending. All units will be notified as soon as we receive it. | H31: Yes | I31: CDP & PCAF | J31: No | K31: TBD | L31: TBD | M31: T1 | N31: GHGE_GHG Financed emissions | O31: Functional guidelines will be provided by HQ for sourcing this variable. | Q31: x
A32: 28 | B32: All | C32: Maturity | D32: End date of the financial instrument, taking into account the following: i) Where the amount is repaid in instalments, date corresponding to the last instalment; ii) Where an exposure has no stated maturity for reasons other than the counterparty having the choice of the repayment date, or in the case of equity holdings, do not report (leave blank); | E32: Banking Book: Non-Financial Corporation, Households (Commercial and Residential) and Repossessed Collaterals | F32: Contract | G32: BDR Table: JM_CTO_AJ_REG Var: O9209_MATUPOSM | H32: No (esperaría que ya esté incluida) | J32: No | K32: Table: cd_captools.fr004_cto Var: data_vencimento | L32: N/A | M32: T1 T4 T5 | N32: CESG_CNAE_ESG | O32: Functional guidelines will be provided by HQ for sourcing this variable. | Q32: x
A33: 29 | B33: All | C33: Flag of specialised lending | D33: This flag allows to identify specialised lending transactions. Specialised lending or project finance transactions refer to those exposures which possess the following characteristics: (a) the exposure is to an entity which was created specifically to finance or operate physical assets or is an economically comparable exposure; (b) the contractual arrangements give the lender a substantial degree of control over the assets and the income that they generate; (c) the primary source of repayment of the obligation is the income generated by the assets being financed, rather than the independent capacity of a broader commercial enterprise. | E33: Banking Book: Financial Corporations, Non-Financial Corporations, Credit Institutions, Households (Commercial and Residential), General Governments | F33: Contract | G33: BDR Table: JM_CTO_AJ_REG Var: O9209_CAT_MSTA | H33: No (esperaría que ya esté incluida) | J33: No | K33: Table: cd_captools.fr004_cto Var: flag_project_finance | L33: Accounting | M33: T7 T8 T9.1 T9.2 T9.3 | N33: GARB_GAR & BTAR | Q33: x | S33: Possible values: 0,1 | V33: Same as reported in FINREP
A34: 30 | B34: All | C34: Stage 2 IFRS 9 | D34: Credit risk classification of exposure, as defined in IFRS 9. | E34: Banking Book: Financial Corporations, Non-Financial Corporations, Credit Institutions, Households (Commercial and Residential), General Governments | F34: Contract | G34: BDR Table: JM_CTO_STAGE Var: T2420_STAGEFIN | H34: No (esperaría que ya esté incluida) | J34: No | K34: Table: cd_captools.fr004_cto Var: stage_atual | L34: Risk | M34: T1 T5 | N34: CESG_CNAE_ESG | Q34: x
A35: 31 | B35: All | C35: Taken possession | D35: Identifier of residential and commercial immovable properties obtained by taking possession | E35: Banking Book: Repossessed Collaterals | F35: Collateral | G35: This metric has been requested to be included in BDR. Comments on whether or not they will be included are pending. All units will be notified as soon as we receive it. | H35: No (esperaría que ya esté incluida) | J35: No | K35: DL Capital Tools Table: cd_captools.fr802_pl_contas All operations with : tipo_conta = 'A' and carteira_contabilistica = 'ativos nao correntes detidos para venda' and conta in ('191000', '1991000', '19910024') | L35: Recuperações/Desinvestimento | M35: T2 T5 T6 T7 T8 T9.1 T9.2 T9.3 | N35: ENPC_Energy_Performance_Certificate CESG_CNAE_ESG GARB_GAR & BTAR | Q35: x
A36: 32 | B36: All | C36: Type of collateral | D36: Breakdown of pledges backing loans, distinguising: - Residential property. Residential property is defined as a residence which is occupied by the owner or the lessee of the residence, including the right to inhabit an apartment in housing cooperatives located in Sweden. - Commercial property. Immovable property other than residential, including offices and commercial premises and other types of commercial immovable property - Other. When a collateral is neither classified as residential nor commercial property. | E36: Banking Book: Households (Commercial and Residential) | F36: Contract | G36: BDR Table: JM_INMUEBLES Var: O9270_TIP_PPDA | H36: No (esperaría que ya esté incluida) | J36: No | K36: Table: cd_captools.fr801_tip_garan Var: subtipo_garantia | L36: Accounting | M36: T2 T5 T6 T7 T8 T9.1 T9.2 T9.3 | N36: CESG_CNAE_ESG ENPC_Energy_Performance_Certificate GARB_GAR & BTAR | Q36: x
A37: 33 | B37: All | C37: Type of counterparty | D37: Breakdown of information by type of counterparty, including: - Financial corporations (FC) -- Credit institutions -- Other financial corporations --- Of which investment firms --- Of which management companies --- Of which insurance undertakings - Non Financial corporations (NFC) - Households - Local governments | E37: Banking Book: Financial Corporations, Non-Financial Corporations, Credit Institutions, Households (Commercial and Residential), General Governments | F37: Client | G37: BDR Table: JM_CLIGLO_CUA Var: T2888_TIPENTID | H37: No (esperaría que ya esté incluida) | J37: No | K37: Table: cd_captools.fr004_cto Var: contraparte | L37: Accounting | M37: T1 T2 T3 T5 T6 T7 T8 T9.1 T9.2 T9.3 T10 | N37: CESG_CNAE_ESG ENPC_Energy_Performance_Certificate GARB_GAR & BTAR MITI_Mitigation actions | Q37: x
A38: 34 | B38: All | C38: Type of product | D38: - Loans and advances: debt instruments held by the institutions that are not securities. That item includes loans as well as advances that cannot be classified as “loans”. - Debt securities: debt instruments held by the institution issued as securities that are not loans - Equity instruments: any contract that evidences an interest in the asset of an entity. | E38: Banking Book: Financial Corporations, Non-Financial Corporations, Credit Institutions, Households (Commercial and Residential), General Governments | F38: Contract | G38: This metric has not been requested to be included in BDR for this evolution of the model. It will be requested next year for the following evolution. Until then, this information should be stored in local systems. All units will be notified as soon as we receive it. | H38: No (esperaría que ya esté incluida) | J38: No | K38: DL Capital Tools Table: cd_captools.fr802_pl_contas All operations with : tipo_conta = 'A' and 1) Intrumento financeiro = 'credito concedido e outros ativos financeiros' => Loans and advances (F18) 2) Intrumento financeiro = 'instrumentos de capital' => Debt securities (F18) 3) Intrumento financeiro = 'instrumentos de divida' => Equity instruments (F04) | L38: Accounting | M38: T2 T6 T7 T8 T9.1 T9.2 T9.3 T10 | N38: ENPC_Energy_Performance_Certificate GARB_GAR & BTAR MITI_Mitigation actions | Q38: x
A39: 35 | B39: All | C39: Climate change physical risk | D39: Type of climate risk that is being mitigated with a specific loan or debt: climate change physical risk. ‘Physical risk’, is defined as the risk of losses arising from any negative financial impact on the institution stemming from the current or prospective impacts of the physical effects of environmental factors on the institution’s counterparties or invested assets. | E39: Banking Book: Non-Financial Corporation, Households (Commercial and Residential) and Repossessed Collaterals | F39: Contract | G39: This metric has not been requested to be included in BDR for this evolution of the model. It will be requested next year for the following evolution. Until then, this information should be stored in local systems. All units will be notified as soon as we receive it. | H39: Yes | I39: Munich RE | J39: No | K39: File provided by HQ | L39: N/A | M39: T10 | N39: MITI_Mitigation actions | O39: Functional guidelines will be provided by HQ for sourcing this variable. | Q39: x
A40: 36 | B40: All | C40: Climate change transition risk | D40: Type of climate risk that is being mitigated with a specific loan or debt: climate change transition risk. 'Transition risk’ is defined as the risk of losses arising from any negative financial impact on the institution stemming from the current or prospective impacts of the transition to an environmentally sustainable economy on its counterparties or invested assets. | E40: Banking Book: Non-Financial Corporation, Households (Commercial and Residential) and Repossessed Collaterals | F40: Contract | G40: This metric has not been requested to be included in BDR for this evolution of the model. It will be requested next year for the following evolution. Until then, this information should be stored in local systems. All units will be notified as soon as we receive it. | H40: Yes | I40: Munich RE | J40: No | K40: File provided by HQ | L40: N/A | M40: T10 | N40: MITI_Mitigation actions | O40: Functional guidelines will be provided by HQ for sourcing this variable. | Q40: x
A41: 37 | B41: All | C41: Usable surface | D41: Surface of the elements or elements constructions associated with the buidling in case of built farms (interger - in square meters) | E41: Banking Book: Households (Commercial and Residential) and Repossessed Collaterals | F41: Collateral | G41: This metric has been requested to be included in BDR. Comments on whether or not they will be included are pending. All units will be notified as soon as we receive it. | H41: No | J41: No | K41: N/A | L41: N/A | M41: T1 T3 | N41: N/A - Variable not reported in the satelite, used as an input | P41: For financed emissions: Commercial Real Estate | Q41: x | R41: Numeric (m2) | S41: >0 | X41: Validate top/bottom 1% cases per type of property, to ensure units expressed are appropriate
A42: 38 | B42: All | C42: Building category | D42: Building category. E.g, according to the Energy Performance of Buildings Directive 2010/31/EU (EPBD): (a) single-family houses of different types; (b) apartment blocks; (c) offices; (d) educational buildings; (e) hospitals; (f) hotels and restaurants; (g) sports facilities; (h) wholesale and retail trade services buildings; (i) other types of energy-consuming buildings | E42: Banking Book: Households (Commercial and Residential) and Repossessed Collaterals | F42: Collateral | G42: This metric has been requested to be included in BDR. Comments on whether or not they will be included are pending. All units will be notified as soon as we receive it. | H42: No | J42: No | K42: N/A | L42: N/A | N42: N/A - Variable not reported in the satelite, used as an input | P42: For financed emissions: Commercial Real Estate | Q42: x | S42: All codes are part of the reference pre-defined list of values (type, use)
A43: 39 | B43: All | C43: Brand of the vehicle | D43: Brand of a specific vehicle | E43: Banking Book: Non-Financial Corporations | F43: Contract | G43: This metric has been requested to be included in BDR. Comments on whether or not they will be included are pending. All units will be notified as soon as we receive it. | H43: No | J43: No | K43: N/A | L43: N/A | M43: T1 T3 | N43: N/A - Variable not reported in the satelite, used as an input | P43: For financed emissions: motor vehice loans | Q43: x
A44: 40 | B44: All | C44: Type of fuel | D44: Type of fuel used for transport. Example: gasoil | E44: Banking Book: Non-Financial Corporations | F44: Contract | G44: This metric has been requested to be included in BDR. Comments on whether or not they will be included are pending. All units will be notified as soon as we receive it. | H44: No | J44: No | K44: N/A | L44: N/A | M44: T1 T3 | N44: N/A - Variable not reported in the satelite, used as an input | P44: For financed emissions: motor vehice loans | Q44: x
A45: 41 | B45: All | C45: Type of vehicle | D45: Type of vehicle | E45: Banking Book: Non-Financial Corporations | F45: Contract | G45: This metric has been requested to be included in BDR. Comments on whether or not they will be included are pending. All units will be notified as soon as we receive it. | H45: No | J45: No | K45: N/A | L45: N/A | M45: T1 T3 | N45: N/A - Variable not reported in the satelite, used as an input | P45: For financed emissions: motor vehice loans | Q45: x
A46: 42 | B46: All | C46: Model of the vehicle | D46: Model of a specific vehicle | E46: Banking Book: Non-Financial Corporations | F46: Contract | G46: This metric has been requested to be included in BDR. Comments on whether or not they will be included are pending. All units will be notified as soon as we receive it. | H46: No | J46: No | K46: N/A | L46: N/A | M46: T1 T3 | N46: N/A - Variable not reported in the satelite, used as an input | P46: For financed emissions: motor vehice loans | Q46: x
A47: 43 | B47: All | C47: Average carbon emissions | D47: Average carbon emissions per vehicle mesured in CO2e/km. | E47: Banking Book: Non-Financial Corporations (auto loans) | F47: Contract | G47: This metric has been requested to be included in BDR. Comments on whether or not they will be included are pending. All units will be notified as soon as we receive it. | H47: No | J47: No | K47: N/A | L47: N/A | M47: T1 T3 | N47: N/A - Variable not reported in the satelite, used as an input | P47: For financed emissions: motor vehice loans | Q47: x | R47: Numeric | T47: - Same average CO2 emissions for Autos with same characteristics (brand, model, type of vehicle, kind of fuel) - No changes in the characteristics of the Auto
A48: 44 | B48: All | C48: Appraisal value | D48: Value of the property estimated independently from the bank’s mortgage acquisition, loan processing and loan decision process. | E48: Banking Book: Households (Commercial and Residential) and Repossessed Collaterals | F48: Collateral | G48: This metric has been requested to be included in BDR. Comments on whether or not they will be included are pending. All units will be notified as soon as we receive it. | H48: No | J48: No | K48: N/A | L48: N/A | M48: T1 T3 | N48: N/A - Variable not reported in the satelite, used as an input | P48: For financed emissions: Commercial Real Estate | Q48: x | R48: Expressed in currency | X48: Min / Max outliers (bottom/top 1%) to be reviewed to ensure reasonable figures (i.e. no matters related to currency and/or units)
A49: 45 | B49: All | C49: Client's debt securities issued | D49: Liabilities of a company, according to its annual financial statements. | E49: Banking Book: Non-Financial Corporations | F49: Client | G49: BDR: Table: JM_CLIEN_JURI Var: G5508_TDEUDACL | H49: No (esperaría que ya esté incluida) | J49: No | K49: N/A | L49: N/A | N49: N/A - Variable not reported in the satelite, used as an input | P49: For financed emissions: attribution factor | Q49: x | R49: Expressed in currency | T49: Counterparty's debt securities issued < Group's debt securities issued
A50: 46 | B50: All | C50: Client's group debt securities issued | D50: Liabilities of the last parent of each of your customers. | E50: Banking Book: Non-Financial Corporations | F50: Last Parent | G50: BDR: Table: JM_GRUP_ECONO Var: G5512_TDEUDAGR | H50: No (esperaría que ya esté incluida) | J50: No | K50: N/A | L50: N/A | N50: N/A - Variable not reported in the satelite, used as an input | P50: For financed emissions: attribution factor | Q50: x | R50: Expressed in currency
A51: 47 | B51: All | C51: Client's Turnover | D51: Revenues of a company, according to its annual financial statements. | E51: Banking Book: Non-Financial Corporations | F51: Client | G51: BDR: Table: JM_CLIEN_JURI Var: G5508_IMPFACTM | H51: No (esperaría que ya esté incluida) | J51: No | K51: Table: cd_captools.ct063_univ_pme var: fatr_indv | L51: N/A | M51: T1 T3 T6 T7 T8 T9.1 T9.2 T9.3 | N51: N/A - Variable not reported in the satelite, used as an input | P51: - For financed emissions: attribution factor - For the NFRD flag | Q51: x | R51: Expressed in currency | T51: Counterparty's turnover < Group's turnover
A52: 48 | B52: All | C52: Client's Group Turnover | D52: It is needed to record the revenues of the last parent of each of your customers. | E52: Banking Book: Non-Financial Corporations | F52: Last Parent | G52: BDR: Table: JM_GRUP_ECONO Var: G5512_IMPFACTM | H52: No (esperaría que ya esté incluida) | J52: No | K52: Table: cd_captools.ct063_univ_pme var: fatr_grup | L52: N/A | M52: T1 T3 T6 T7 T8 T9.1 T9.2 T9.3 | N52: N/A - Variable not reported in the satelite, used as an input | P52: - For financed emissions: attribution factor - For the NFRD flag | Q52: x | R52: Expressed in currency
A53: 49 | B53: All | C53: Contracted kilometers | D53: Contracted kilometers for a car in a renting contract. If the car drives more kilometers than the contracted kilometers, an extra fee will be applied for each kilometer driven, and if the car drives less, an amount will be refunded for each kilometer not driven. | E53: Banking Book: Non-Financial Corporations (auto loans) | F53: Contract | G53: This metric has been requested to be included in BDR. Comments on whether or not they will be included are pending. All units will be notified as soon as we receive it. | H53: No | J53: No | K53: N/A | L53: N/A | M53: T1 T3 | N53: N/A - Variable not reported in the satelite, used as an input | P53: For financed emissions: motor vehice loans | Q53: x
A54: 50 | B54: All | C54: Asset value at origination | D54: Initial fair value of the adquiered asset in an auto loan. | E54: Banking Book: Non-Financial Corporations (auto loans) | F54: Contract | G54: This metric has been requested to be included in BDR. Comments on whether or not they will be included are pending. All units will be notified as soon as we receive it. | H54: No | J54: No | K54: N/A | L54: N/A | M54: T1 T3 | N54: N/A - Variable not reported in the satelite, used as an input | P54: For financed emissions: motor vehice loans | Q54: x | R54: Expressed in currency
A55: 51 | B55: All | C55: Client's own funds | D55: All those elements that constitute the company's accounting equity. | E55: Banking Book: Non-Financial Corporations | F55: Client | G55: BDR: Table: JM_CLIEN_JURI Var: G5508_TOT_EQTY | H55: No (esperaría que ya esté incluida) | J55: No | K55: Table: cd_riscos.rsv176sa1_balanco var: VCPIM | L55: Risk | M55: T1 T3 | N55: N/A - Variable not reported in the satelite, used as an input | P55: - For financed emissions: attribution factor - For the NFRD flag | Q55: x | R55: Expressed in currency | T55: Counterparty's own funds < Group's own funds
A56: 52 | B56: All | C56: Client's Group own funds | D56: It is needed to record the own funds of the last parent of each of your customers. | E56: Banking Book: Non-Financial Corporations | F56: Last Parent | G56: BDR: Table: JM_CLIEN_JURI Var: G5508_TOT_EQTY | H56: No (esperaría que ya esté incluida) | J56: No | K56: N/A | L56: N/A | M56: T1 T3 | N56: N/A - Variable not reported in the satelite, used as an input | P56: - For financed emissions: attribution factor - For the NFRD flag | Q56: x | R56: Expressed in currency
A57: 53 | B57: All | C57: Client's number of employees | D57: Number of workers in the firm. | E57: Banking Book: Non-Financial Corporations | F57: Client | G57: BDR: Table: JM_CLIEN_JURI Var: G5508_NUM_EMPL | H57: No (esperaría que ya esté incluida) | J57: No | K57: Table: cd_captools.ct063_univ_pme var: num_empg_indv | L57: N/A | M57: T6 T7 T8 T9.1 T9.2 T9.3 | N57: N/A - Variable not reported in the satelite, used as an input | P57: For the NFRD flag | Q57: x | R57: Numeric | T57: Counterparty's total employees < Groups's total employees
A58: 54 | B58: All | C58: Client's Group number of employees | D58: It is needed to record the number of employees of the last parent of each of your customers. | E58: Banking Book: Non-Financial Corporations | F58: Last Parent | G58: BDR: Table: JM_GRUP_ECONO Var: G5512_NUM_EMPL | H58: No (esperaría que ya esté incluida) | J58: No | K58: Table: cd_captools.ct063_univ_pme var: num_empg_grup | L58: N/A | M58: T6 T7 T8 T9.1 T9.2 T9.3 | N58: N/A - Variable not reported in the satelite, used as an input | P58: For the NFRD flag | Q58: x | R58: Numeric
A59: 55 | B59: All | C59: Use of proceeds | D59: If the use of proceeds is unknown, the type of financing is considered to be general purpose. If the use of proceeds is known, the first level of this category will be taken (e.g. Energy, Transport, Real Estate, Manufacturing, etc). | E59: Banking Book: Non-Financial Corporation, Households (Commercial and Residential) and General Governments | F59: Contract | G59: This metric has been requested to be included in BDR. Comments on whether or not they will be included are pending. All units will be notified as soon as we receive it. | H59: Yes | J59: No | K59: TBD | L59: TBD | M59: T1 T3 T7 T8 T9.1 T9.2 T9.3 | N59: GARB_GAR & BTAR | O59: Functional guidelines will be provided by HQ for sourcing this variable. | Q59: x
A60: 56 | B60: All | C60: Financing Category (according to the SFCS) | D60: Financing Category (level 2) - required to identify the concept of Sustainability Linked Finance (Template 10 - Other Mitigating actions). Sustainability Linked Finance: transactions whose financing does not necessary have a specific purpose and are designated to incentivize clients to achieve their sustainability goals and commitments. Their structure is based on the achievement of pre-determined sustainability performance targets (SPTs) | E60: Banking Book: Financial Corporations and Non-Financial Corporations | F60: Contract | H60: Yes | K60: TBD | L60: TBD | M60: T10 | N60: MdD_83_MITI_Mitigation actions | Q60: x | S60: Possible values: - Sustainability Linked Finance - Other
A61: 57 | B61: All | C61: Environmental objective | D61: The Taxonomy Regulation establishes six environmental objectives, our of which for now only 2 have been developed (climate change mitigation and climate change adaptation). Required breakdown according to the contribution of a specific transaction to the environmental objectives stablished by the EU Taxonomy Regulation: - Climate change mitigation, meaning that the transaction contributes substantially to the stabilisation of greenhouse gas emissions by avoiding or reducing them or by enhancing greenhouse gas removals. - Climate change adaptation: the transaction reduces or prevents the adverse impact of the present of future climate, or the risks of such adverse impact on the activity itself, or on people, nature or assets. - The exposure does not contribute to any objective. Other 4 objectives are still under development (Sustainable use and protection of water and marine resources, Transition to a circular economy, Pollution prevention and control, Protection and restoration of biodiversity and ecosystems). Where the same exposure is relevant for two environmental objectives, it shall be allocated to the most relevant objective. | E61: Banking Book: Financial Corporations, Non-Financial Corporations, Credit Institutions, Households (Commercial and Residential), General Governments | F61: Contract | G61: This metric has been requested to be included in BDR. Comments on whether or not they will be included are pending. All units will be notified as soon as we receive it. | H61: Yes | J61: No | K61: TBD | L61: TBD | M61: T1 T6 T7 T8 T9.1 T9.2 T9.3 T.10 | N61: GARB_GAR & BTAR | O61: Functional guidelines will be provided by HQ for sourcing this variable. | Q61: x | S61: Possible values: - Climate change mitigation (CCM), - Climate change adaptation (CCA) - None of these
A62: 58 | B62: All | C62: Flag aligned under SFCS | D62: This flag allows to identify exposures that are considered green from a management perspective. I.e. not only uder EU Taxonomy criteria, understood as meeting the SFCS criteria. | E62: Banking Book: Financial Corporations, Non-Financial Corporations, Credit Institutions, Households (Commercial and Residential), General Governments | F62: Contract | G62: This metric has been requested to be included in BDR. Comments on whether or not they will be included are pending. All units will be notified as soon as we receive it. | H62: Yes | J62: No | K62: TBD | L62: TBD | M62: T6 T7 T8 T9.1 T9.2 T9.3 T.10 | N62: GARB_GAR & BTAR | O62: Functional guidelines will be provided by HQ for sourcing this variable. | Q62: x
A63: 59 | B63: All | C63: Flag eligible under EU Taxonomy | D63: This flag allows to identify the eligible exposures towards sectors (4 level NACE codes) relevant for the corresponding environmental objective according to the Taxonomy, as specified in the technical annex to the Commission Delegated Regulation18 on technical screening criteria for determining the conditions under which an economic activity qualifies as environmentally sustainable. Institutions shall disclose exposures towards relevant sectors under the objective of climate change mitigation in accordance with Article 9, point (a)and Article 10 of Regulation (EU) 2020/852. Or under the objective of climate change adaptation in accordance with Article 9, point (b) and Article 11 of Regulation (EU) 2020/852. | E63: Banking Book: Financial Corporations, Non-Financial Corporations, Credit Institutions, Households (Commercial and Residential), General Governments | F63: Contract | G63: This metric has been requested to be included in BDR. Comments on whether or not they will be included are pending. All units will be notified as soon as we receive it. | H63: Yes | J63: No | K63: TBD | L63: TBD | M63: T6 T7 T8 T9.1 T9.2 T9.3 | N63: GARB_GAR & BTAR | O63: Functional guidelines will be provided by HQ for sourcing this variable. | Q63: x
A64: 60 | B64: All | C64: Environmentally sustainable activity | D64: Economic activity breakdown for the purposes of the technical screening criteria for determining the conditions under which an economic activity qualifies as contributing substantially to climate change mitigation or climate change adaptation and for determining whether that economic activity causes no significant harm to any of the other environmental objectives, as staged in the Comission Delegated Regulation (EU) 2021/2139, Annex I and Annex II. E.g. Manufacture of renewable energy technologies, Manufacture of equipment for the production and use of hydrogen... etc (find the whole list of published economic activities here: https://eur-lex.europa.eu/legal-content/EN/TXT/?uri=PI_COM%3AC%282021%292800). | E64: Banking Book: Financial Corporations, Non-Financial Corporations, Credit Institutions, Households (Commercial and Residential), General Governments | F64: Contract | G64: This metric has been requested to be included in BDR. Comments on whether or not they will be included are pending. All units will be notified as soon as we receive it. | H64: Yes | J64: No | K64: TBD | L64: TBD | M64: T4 T6 T7 T8 T9.1 T9.2 T9.3 | N64: GARB_GAR & BTAR | Q64: x
A65: 61 | B65: All | C65: Flag aligned under EU Taxonomy | D65: This flag allows to identify the gross carrying amount of eligible exposures that are environmentally sustainable, as specified in the technical annex to the Commission Delegated Regulation on technical screening criteria for determining the conditions under which an economic activity qualifies as environmentally sustainable. Institutions shall disclose environmentally sustainable exposures under the objective of climate change mitigation in accordance with Article 9, point (a) and Article 10 of Regulation (EU) 2020/852. Or under objective of climate change adaptation in accordance with Article 9, point (b) and Article 11 of Regulation (EU) 2020/852. This variable applies when the use of proceeds is known (specialised lending, e.g. project finance loans). It should be disclosed to the extent to which the exposure is environmentally sustainable based on the extent and proportion to which the project funded contributes substantially to climate change mitigation, in accordance with Article 10, or is an enabling activity in accordance with Article 16, and meets the criteria specified in Article 3 of the same regulation. So far, only 2 out of the 6 objectives of the EU Taxonomy have been released. | E65: Banking Book: Financial Corporations, Non-Financial Corporations, Credit Institutions, Households (Commercial and Residential), General Governments | F65: Contract | G65: This metric has been requested to be included in BDR. Comments on whether or not they will be included are pending. All units will be notified as soon as we receive it. | H65: Yes | J65: No | K65: TBD | L65: TBD | M65: T6 T7 T8 T9.1 T9.2 T9.3 T.10 | N65: GARB_GAR & BTAR | O65: Functional guidelines will be provided by HQ for sourcing this variable. | Q65: x | S65: Posible values: 0,1
A66: 62 | B66: All | C66: Taxonomy-eligible Capex | D66: Proportion of Capex eligible according to European Taxonomy, that is, that might make a sustantial contribution to an objective of the EU Taxonomy. This variable applies when the use of proceeds is unknown. | E66: Banking Book: Non-Financial Corporations | F66: Client | G66: This metric has been requested to be included in BDR. Comments on whether or not they will be included are pending. All units will be notified as soon as we receive it. | H66: Yes | J66: No | K66: N/A | L66: N/A | M66: T6 T7 T8 T9.1 T9.2 T9.3 | N66: N/A - Variable not reported in the satelite, used as an input | O66: Functional guidelines will be provided by HQ for sourcing this variable. | Q66: x | R66: %
A67: 63 | B67: All | C67: Taxonomy-eligible Turnover | D67: Proportion of Turnover eligible according to European Taxonomy, that is, that might make a sustantial contribution to an objective of the EU Taxonomy. This variable applies when the use of proceeds is unknown. | E67: Banking Book: Non-Financial Corporations | F67: Client | G67: This metric has been requested to be included in BDR. Comments on whether or not they will be included are pending. All units will be notified as soon as we receive it. | H67: Yes | J67: No | K67: N/A | L67: N/A | M67: T6 T7 T8 T9.1 T9.2 T9.3 | N67: N/A - Variable not reported in the satelite, used as an input | O67: Functional guidelines will be provided by HQ for sourcing this variable. | Q67: x | R67: %
A68: 64 | B68: All | C68: Taxonomy-aligned Capex | D68: Proportion of Capex that is aligned with the European Taxonomy. Capex represents the proportion of the capital expenditure of an activity that is either already taxonomy-aligned or is part of a credible plan to extend or reach taxonomy-alignment. This variable applies when the use of proceeds is unknown. | E68: Banking Book: Non-Financial Corporations | F68: Client | G68: This metric has been requested to be included in BDR. Comments on whether or not they will be included are pending. All units will be notified as soon as we receive it. | H68: Yes | J68: No | K68: N/A | L68: N/A | M68: T6 T7 T8 T9.1 T9.2 T9.3 | N68: N/A - Variable not reported in the satelite, used as an input | O68: Functional guidelines will be provided by HQ for sourcing this variable. | Q68: x | R68: %
A69: 65 | B69: All | C69: Taxonomy-aligned Turnover | D69: Proportion of Turnover that is aligned with the European Taxonomy. Turnover represents the proportion of the net turnover derived from products or services, including intangibles, associated with Taxonomy-aligned economic activities, divided by the net turnover. This variable applies when the use of proceeds is unknown. | E69: Banking Book: Non-Financial Corporations | F69: Client | G69: This metric has been requested to be included in BDR. Comments on whether or not they will be included are pending. All units will be notified as soon as we receive it. | H69: Yes | J69: No | K69: N/A | L69: N/A | M69: T6 T7 T8 T9.1 T9.2 T9.3 | N69: N/A - Variable not reported in the satelite, used as an input | O69: Functional guidelines will be provided by HQ for sourcing this variable. | Q69: x | R69: %
A70: 66 | B70: All | C70: Eligibility ratio | D70: What percentage of assets is eligible according to the European Taxonomy These are the following eligibility ratios according to each Financial Corporation: - ) Credit institutions - Green Asset Ratio - ) Asset Managers - Green Investment Ratio - ) Investment Firms - KPI for their core investment services and activities - ) Insurers/reinsurers - KPIs related to their investments and underwriting activities | E70: Banking Book: Financial Corporations, Non-Financial Corporations, Credit Institutions, Households (Commercial and Residential), General Governments | F70: Client | G70: This metric has been requested to be included in BDR. Comments on whether or not they will be included are pending. All units will be notified as soon as we receive it. | H70: Yes | J70: No | K70: N/A | L70: N/A | M70: T6 T7 T8 T9.1 T9.2 T9.3 | N70: N/A - Variable not reported in the satelite, used as an input | Q70: x
A71: 67 | B71: All | C71: KPI for Financial Institutions | D71: What percentage of assets is aligned with the European Taxonomy. These are the following alignment ratios according to each Financial Corporation: - ) Credit institutions - Green Asset Ratio - ) Asset Managers - Green Investment Ratio - ) Investment Firms - KPI for their core investment services and activities - ) Insurers/reinsurers - KPIs related to their investments and underwriting activities | E71: Banking Book: Financial Corporations, Non-Financial Corporations, Credit Institutions, Households (Commercial and Residential), General Governments | F71: Client | G71: This metric has been requested to be included in BDR. Comments on whether or not they will be included are pending. All units will be notified as soon as we receive it. | H71: Yes | J71: No | K71: TBD | L71: TBD | M71: T6 T7 T8 T9.1 T9.2 T9.3 | N71: GARB_GAR & BTAR | Q71: x
A72: 68 | B72: All | C72: SFCS Category | D72: SFCS category two levels of information. E.g.: Energy (level 01) & Renewable energy production (level 02) or Transport (level 01) & Land transport (level 02) | E72: Banking Book: Financial Corporations, Non-Financial Corporations, Credit Institutions, Households (Commercial and Residential), General Governments | F72: Contract | G72: This metric has been requested to be included in BDR. Comments on whether or not they will be included are pending. All units will be notified as soon as we receive it. | H72: Yes | J72: No | K72: TBD | L72: TBD | M72: T6 T7 T8 T9.1 T9.2 T9.3 T.10 | N72: GARB_GAR & BTAR MITI_Mitigation actions | Q72: x
A73: 69 | B73: All | C73: LEI | D73: The Legal Entity Identifier (LEI) is a 20-character, alpha-numeric code based on the ISO 17442 standard. It connects to key reference information that enables clear and unique identification of legal entities participating in financial transactions. Each LEI contains information about an entity’s ownership structure and thus answers the questions of 'who is who’ and ‘who owns whom’. | E73: Banking Book: Non-Financial Corporation | F73: Client | G73: This metric has not been requested to be included in BDR for this evolution of the model. It will be requested next year for the following evolution. Until then, this information should be stored in local systems. All units will be notified as soon as we receive it. | H73: Yes | J73: No | K73: table: Ct003_univ_cli Var: clei | L73: N/A | M73: T1 T3 T4 | N73: N/A - Variable not reported in the satelite, used as an input | P73: For Paris excluded companies | Q73: x
A74: 70 | B74: All | C74: Flag audited of financial statements | D74: This flag allows to identify audited financial statements of the counterparty. | E74: Banking Book: Non-Financial Corporations | F74: Client & Last Parent | G74: BDR: Table: JM_CLIEN_JURI Var: G5508_ORIG_FAC | H74: No (esperaría que ya esté incluida) | J74: No | K74: Table: JM_CLIEN_JURI Var: ORIG_FAC | L74: Capital | M74: T3 T6 T7 T8 T9.1 T9.2 T9.3 | N74: N/A - Variable not reported in the satelite, used as an input | P74: For financed emissions: DQS | Q74: x | S74: Possible values: 0,1
A75: 71 | B75: All | C75: Date of reference of financial statements | D75: Date of reference of the fnancial statetements of the counterparty. | E75: Banking Book: Non-Financial Corporations | F75: Client | G75: BDR: Table: JM_CLIEN_JURI Var: G5508_INFFECHA | H75: No (esperaría que ya esté incluida) | J75: No | K75: Table: JM_CLIEN_JURI Var: INFFECHA | L75: Risk | M75: T3 T6 T7 T8 T9.1 T9.2 T9.3 | N75: N/A - Variable not reported in the satelite, used as an input | P75: For financed emissions | Q75: x | S75: Possible values: 0,1
A76: 72 | B76: All | C76: Flag of Listed Company in a EU Regulated Market | D76: This flag allows to identify companies whose transferable securities are admitted to trading on a regulated market of any Member State. | E76: Banking Book: Non-Financial Corporations | F76: Client | G76: This metric has not been requested to be included in BDR for this evolution of the model. It will be requested next year for the following evolution. Until then, this information should be stored in local systems. All units will be notified as soon as we receive it. | H76: Yes | J76: No | K76: Table: cd_captools.CT610_titulos Var: bolsa_valores | L76: Market risk / ALM | M76: T6 T7 T8 T9.1 T9.2 T9.3 | N76: N/A - Variable not reported in the satelite, used as an input | O76: Functional guidelines will be provided by HQ for sourcing this variable. | P76: For the NFRD flag | Q76: x | S76: Possible values: 0,1
A77: 73 | B77: All | C77: Client's total assets on the balance sheet | D77: Total assets of the company according to is annual financial statements. | E77: Banking Book: Non-Financial Corporations | F77: Client | G77: BDR: Table: JM_CLIEN_JURI Var: G5508_TOT_ACTI | H77: No (esperaría que ya esté incluida) | J77: No | K77: Table: cd_captools.ct063_univ_pme var: ativo_indv | L77: N/A | M77: T7 T8 T9.1 T9.2 T9.3 | N77: N/A - Variable not reported in the satelite, used as an input | P77: - For financed emissions: attribution factor - For the NFRD flag | Q77: x | R77: Expressed in currency | T77: Counterparty's total assets < Group's total assets
A78: 74 | B78: All | C78: Client's group total assets on the balance sheet | D78: It is needed to record the total assets of the last parent of each of your customers | E78: Banking Book: Non-Financial Corporations | F78: Last Parent | G78: BDR: Table: JM_GRUP_ECONO Var: G5512_TOT_ACTI | H78: No (esperaría que ya esté incluida) | J78: No | K78: Table: cd_captools.ct063_univ_pme var: ativo_grup | L78: N/A | M78: T7 T8 T9.1 T9.2 T9.3 | N78: N/A - Variable not reported in the satelite, used as an input | P78: - For financed emissions: attribution factor - For the NFRD flag | Q78: x | R78: Expressed in currency
A79: 75 | B79: All | C79: ISIN of the issuer | D79: The ISIN number (ISO 6166) is a globally recognised identifier used for recognising particular financial instruments such as securities, bonds, futures, stocks, trusts and more. The ISIN is an extended version of the US Committee on Uniform Security Identification Procedures (CUSIP number). Part of the ISIN code of the financial instrument allows to identify the issuer. | E79: Banking Book: Non-Financial Corporations | F79: Client | G79: This metric has not been requested to be included in BDR for this evolution of the model. It will be requested next year for the following evolution. Until then, this information should be stored in local systems. All units will be notified as soon as we receive it. | H79: Yes | J79: No | K79: cd_captools.ct610_titulos var: ISIN | L79: Market risk / ALM | M79: T1 T3 T4 | N79: N/A - Variable not reported in the satelite, used as an input | P79: - For Paris excluded companies '- For financed emissions: real emissions | Q79: x
A80: 76 | B80: All | C80: GHG reported emissions: Scope 1 | D80: Information reported by companies on GHG financed emissions expressed in tonnes of carbon dioxide equivalent (tCO2e). It requires a breakdown by its 3 scopes: - Scope 1 covers direct emissions from owned or controlled sources of the reporting company. - Scope 2 covers indirect emissions from the generation of purchased electricity, steam, heating and cooling consumed by the reporting company. - Scope 3 covers indirect emissions in all sectors (except power). For financial institutions, this is scope 1, 2 and 3 of their counterparties. All this information comes directly from the company, or from external databases such as Trucost and CDP. | E80: Banking Book: Non-Financial Corporations | F80: Client | G80: This metric has been requested to be included in BDR. Comments on whether or not they will be included are pending. All units will be notified as soon as we receive it. | H80: Yes | I80: CDP & PCAF | J80: No | K80: TBD | L80: TBD | M80: T1 | N80: GHGE_GHG Financed emissions | Q80: x
A81: 77 | B81: All | C81: GHG reported emissions: Scope 2 | D81: Information reported by companies on GHG financed emissions expressed in tonnes of carbon dioxide equivalent (tCO2e). It requires a breakdown by its 3 scopes: - Scope 1 covers direct emissions from owned or controlled sources of the reporting company. - Scope 2 covers indirect emissions from the generation of purchased electricity, steam, heating and cooling consumed by the reporting company. - Scope 3 covers indirect emissions in all sectors (except power). For financial institutions, this is scope 1, 2 and 3 of their counterparties. All this information comes directly from the company, or from external databases such as Trucost and CDP. | E81: Banking Book: Non-Financial Corporations | F81: Client | G81: This metric has been requested to be included in BDR. Comments on whether or not they will be included are pending. All units will be notified as soon as we receive it. | H81: Yes | I81: CDP & PCAF | J81: No | K81: TBD | L81: TBD | M81: T1 | N81: GHGE_GHG Financed emissions | Q81: x
A82: 78 | B82: All | C82: GHG reported emissions: Scope 3 | D82: Information reported by companies on GHG financed emissions expressed in tonnes of carbon dioxide equivalent (tCO2e). It requires a breakdown by its 3 scopes: - Scope 1 covers direct emissions from owned or controlled sources of the reporting company. - Scope 2 covers indirect emissions from the generation of purchased electricity, steam, heating and cooling consumed by the reporting company. - Scope 3 covers indirect emissions in all sectors (except power). For financial institutions, this is scope 1, 2 and 3 of their counterparties. All this information comes directly from the company, or from external databases such as Trucost and CDP. | E82: Banking Book: Non-Financial Corporations | F82: Client | G82: This metric has been requested to be included in BDR. Comments on whether or not they will be included are pending. All units will be notified as soon as we receive it. | H82: Yes | I82: CDP & PCAF | J82: No | K82: TBD | L82: TBD | M82: T1 | N82: GHGE_GHG Financed emissions | Q82: x
A83: 79 | B83: All | C83: Flag: Banking book | D83: This flag allows to identify the Banking book, which comprises the following FINREP portfolios: - Loans and receivables and held-to-maturity investments - Non-trading non-derivative financial assets measured at fair value to equity - Non-trading debt instruments measured at a cost-based method - Other non-trading non-derivative financial assets | E83: Banking Book: Financial Corporations, Non-Financial Corporations, Credit Institutions, Households (Commercial and Residential), General Governments | F83: Contract | G83: This metric has not been requested to be included in BDR for this evolution of the model. It will be requested next year for the following evolution. Until then, this information should be stored in local systems. All units will be notified as soon as we receive it. | H83: No (esperaría que ya esté incluida) | J83: No | K83: Table: cd_captools.fr802_pl_contas All operations with : tipo_conta = 'A' and ( caretira_contabilistica <> 'ativos financeiros detidos para negociacao' or (caretira_contabilistica = 'ativos financeiros detidos para negociacao' and subcarteira_contabilistica = NEGCE) or (caretira_contabilistica = 'ativos financeiros detidos para negociacao' and portfoloio = ST_RT_LIQ_DERIV) ) Nota: o portfólio existe na tabela de swaps cambiais cd_alm.al005_det_swapc | L83: Accounting | M83: T1 T2 T3 T4 T5 T6 T7 T8 T9.1 T9.2 T9.3 T10 | N83: CESG_CNAE_ESG ENPC_Energy_Performance_Certificate GARB_GAR & BTAR GHGE_GHG Financed emissions | Q83: x
A84: 80 | B84: All | C84: Sensitive to impact from acute climate change events | D84: - Indicator of exposure prone to impact from acute climate (extreme) climate-relate hazards, including hazards that may cause sudden damage to properties, disruption of supply chains, depreciation of assets as well as result in operational downtime and lost manufacturing for fixed assets. Acute climate events include: - Heatwaves - Coldwaves/frost -Wildfire - Cyclone, hurricane, typhoon, storm and tornado - Droughts - Heavy precipitation (rain, hail, snow/ice) - Floods - Landslide and subsidence | E84: Banking Book: Non-Financial Corporation, Households (Commercial and Residential) and Repossessed Collaterals | F84: Collateral / Client (exposures not collateralized) | G84: This metric has not been requested to be included in BDR for this evolution of the model. It will be requested next year for the following evolution. Until then, this information should be stored in local systems. All units will be notified as soon as we receive it. | H84: Yes | J84: No | K84: TBD | L84: TBD | M84: T5 | N84: CESG_CNAE_ESG | Q84: x
A85: 81 | B85: All | C85: Sensitive to impact from chronic climate change events | D85: Indicator of exposure prone to impact from chronic (incremental, slow-onset) climate-related hazards, including hazards relating to gradual changes in weather and climate and having a possible impact on economic output and productivity. Chronic climate change events include: - changing temperature (air, freshwater, marine water) - heat stress and permafrost thawing - changing wind patterns - changing precipitation patterns and types (rain, hail, snow/ice) - sea level rise - water stress - soil and coastal erosion - soil degradation | E85: Banking Book: Non-Financial Corporation, Households (Commercial and Residential) and Repossessed Collaterals | F85: Collateral / Client (exposures not collateralized) | G85: This metric has not been requested to be included in BDR for this evolution of the model. It will be requested next year for the following evolution. Until then, this information should be stored in local systems. All units will be notified as soon as we receive it. | H85: Yes | J85: No | K85: TBD | L85: TBD | M85: T5 | N85: CESG_CNAE_ESG | Q85: x
A86: 82 | B86: All | C86: Purpose ESG | D86: Potential breakdown for households and local government purposes (Building Renovation Loans, Motor Vehicles Loans, Other Househodkds Purpose and Other) | E86: Banking Book: Households (Commercial and Residential) and General Governments | F86: Contract | H86: Yes | K86: TBD | L86: TBD | M86: T6 T7 T8 T9.1 T9.2 T9.3 T10 | N86: GARB_GAR & BTAR MITI_Mitigation actions
A87: 83 | B87: All | C87: Reference date of the information | D87: The defined point in time to collect all available information/live contracts as of that date | E87: Banking Book: Financial Corporations, Non-Financial Corporations, Credit Institutions, Households (Commercial and Residential), General Governments | F87: Contract | H87: Yes | K87: table cd_captools.fr004_cto var:ref_date | L87: N/A | M87: T6 T7 T8 T9.1 T9.2 T9.3 | N87: GARB_GAR & BTAR
A88: 84 | B88: All | C88: Date of origination | D88: Opening date of the operation | E88: Banking Book: Financial Corporations, Non-Financial Corporations, Credit Institutions, Households (Commercial and Residential), General Governments | F88: Contract | G88: BDR Table: JM_CONTR_BIS Var: G4095_FECHAPER | H88: Yes | K88: table cd_captools.fr004_cto var: data_abertura | L88: N/A | M88: T6 T7 T8 T9.1 T9.2 T9.3 | N88: GARB_GAR & BTAR
A89: 85 | B89: All | C89: DQ score emissions scope 1 | D89: Data quality is one of the key components highlighted by the standard, in which data quality score tables rank for each defined asset class from 1 (Highest Data Quality) to 5 (Lowest Data Quality). | E89: Banking Book: Non-Financial Corporations | F89: Client | G89: This metric has been requested to be included in BDR. Comments on whether or not they will be included are pending. All units will be notified as soon as we receive it. | H89: Yes | I89: CDP & PCAF | J89: No | K89: TBD | L89: TBD | M89: T1 | N89: GHGE_GHG Financed emissions | O89: Functional guidelines will be provided by HQ for sourcing this variable.
A90: 86 | B90: All | C90: DQ score emissions scope 2 | D90: Data quality is one of the key components highlighted by the standard, in which data quality score tables rank for each defined asset class from 1 (Highest Data Quality) to 5 (Lowest Data Quality). | E90: Banking Book: Non-Financial Corporations | F90: Client | G90: This metric has been requested to be included in BDR. Comments on whether or not they will be included are pending. All units will be notified as soon as we receive it. | H90: Yes | I90: CDP & PCAF | J90: No | K90: TBD | L90: TBD | M90: T1 | N90: GHGE_GHG Financed emissions | O90: Functional guidelines will be provided by HQ for sourcing this variable.
A91: 87 | B91: All | C91: DQ score emissions scope 3 | D91: Data quality is one of the key components highlighted by the standard, in which data quality score tables rank for each defined asset class from 1 (Highest Data Quality) to 5 (Lowest Data Quality). | E91: Banking Book: Non-Financial Corporations | F91: Client | G91: This metric has been requested to be included in BDR. Comments on whether or not they will be included are pending. All units will be notified as soon as we receive it. | H91: Yes | I91: CDP & PCAF | J91: No | K91: TBD | L91: TBD | M91: T1 | N91: GHGE_GHG Financed emissions | O91: Functional guidelines will be provided by HQ for sourcing this variable.
A92: 88 | B92: All | C92: Technology generation | D92: Technologies that contribute to climate change. Example: Eg. Wind, renewable energies, etc | E92: Banking Book: Non-Financial Corporations | F92: Contract | G92: This metric has been requested to be included in BDR. Comments on whether or not they will be included are pending. All units will be notified as soon as we receive it. | H92: No | I92: CDP & PCAF | J92: No | K92: N/A | L92: N/A | M92: T1 | N92: N/A - Variable not reported in the satelite, used as an input | O92: Functional guidelines will be provided by HQ for sourcing this variable. | P92: For financed emissions: project finance | Q92: x
A93: 89 | B93: All | C93: Installed capacity | D93: Amount of power that is recognized to the generating plants considering the technical availability of their facilities. It is measured in MegaWatts (MW) power units. | E93: Banking Book: Non-Financial Corporations | F93: Contract | G93: This metric has been requested to be included in BDR. Comments on whether or not they will be included are pending. All units will be notified as soon as we receive it. | H93: No | I93: CDP & PCAF | J93: No | K93: N/A | L93: N/A | M93: T1 | N93: N/A - Variable not reported in the satelite, used as an input | O93: Functional guidelines will be provided by HQ for sourcing this variable. | P93: For financed emissions: project finance | Q93: x
A94: 90 | B94: All | C94: Energy generated per year | D94: Total energy generated in a year measured in megawatts per hour (MWh) | E94: Banking Book: Non-Financial Corporations | F94: Contract | G94: This metric has been requested to be included in BDR. Comments on whether or not they will be included are pending. All units will be notified as soon as we receive it. | H94: No | I94: CDP & PCAF | J94: No | K94: N/A | L94: N/A | M94: T1 | N94: N/A - Variable not reported in the satelite, used as an input | O94: Functional guidelines will be provided by HQ for sourcing this variable. | P94: For financed emissions: project finance | Q94: x
A95: 91 | B95: All | C95: National identification number | D95: Unique counterparty identifier according to local legislation. E.g. in Spain it is the CIF. | E95: Banking Book: Non-Financial Corporations | F95: Client | G95: BDR Table: JM_CLIENT_BII Var: G4093_IDENTPER, G4093_CODIDPER | H95: Yes | J95: No | K95: N/A | L95: N/A | M95: - | N95: N/A - Variable not reported in the satelite, used as an input | Q95: x
A96: 92 | B96: All | C96: Interest Income | D96: Real financial income / expenditure generated from interests | E96: Banking Book: Non Financial Corporations | F96: Contract | H96: Yes | J96: No | K96: TBD | L96: TBD | M96: STE | N96: IESG_Interest and Commissions
A97: 93 | B97: All | C97: European Union | D97: Institutions shall disclose the total gross carrying amounts wth breakdown by location EU vs non-EU area | E97: Banking Book: Financial Corporations, Non-Financial Corporations, Credit Institutions, Households (Commercial and Residential), General Governments | F97: Client | H97: Yes | J97: No | K97: DL Capital Tools table: cd_captools.ct003_univ_cli Var: cpais_residencia | L97: N/A | M97: T1 T2 T5 T6 T7 T8 T9.1 T9.2 T9.3 T10 | N97: CESG_CNAE_ESG ENPC_Energy_Performance_Certificate GARB_GAR & BTAR GHGE_GHG Financed emissions
A98: 94 | B98: All | C98: Calculation approach | D98: The calculation of financed emissions depends on the portfolio, which can be: - Corporate finance - Project Finance - Commercial Real Estate - Motor Vehicle Loans - Mortgages | E98: Banking Book: Non Financial Corporations | F98: Client | H98: Yes | J98: No | K98: TBD | L98: TBD | M98: T1 | N98: GHGE_GHG Financed emissions | O98: Functional guidelines will be provided by HQ for sourcing this variable.
A99: 95 | B99: All | C99: Fees and commisions income | D99: Non-financial gross fee and commission income (amount that is allocated in the P&L) accrued by the instrument during the reporting month (included in Green Finance Business Book instructions: Net Fees/Customer Fees). | E99: Banking Book: Non Financial Corporations | F99: Contract | H99: Yes | J99: No | K99: TBD | L99: TBD | M99: STE | N99: IESG_Interest and Commissions

Sheet Sheet1
B2: Banking Book: Non-Financial Corporation
B3: Banking Book: Non-Financial Corporation, Households (Commercial and Residential) and Repossessed Collaterals
B4: Banking Book: Households (Commercial and Residential) and Repossessed Collaterals
B5: Banking Book: Financial Corporations, Non-Financial Corporations, Credit Institutions, Households (Commercial and Residential), General Governments
B6: Banking Book: Non-Financial Corporations
B7: Banking Book: Repossessed Collaterals
B8: Banking Book: Households (Commercial and Residential)

Sheet 2. Track Changes V4
B2: Track changes v4
B3: Campo | C3: Cambios (ES)
B4: Cadastral ID | C4: Quitamos la métrica porque es para estimación de EPCs
B5: Year of construction | C5: Quitamos la métrica porque es para estimación de EPCs
B6: Floor | C6: Quitamos la métrica porque es para estimación de EPCs
B7: Type of reform | C7: Quitamos la métrica porque es para estimación de EPCs
B8: Year of renovation | C8: Quitamos la métrica porque es para estimación de EPCs
B9: Climate zone | C9: Quitamos la métrica porque es para estimación de EPCs
B10: Altitude | C10: Quitamos la métrica porque es para estimación de EPCs
B11: Inhabitants | C11: Quitamos la métrica porque es para estimación de EPCs
B12: Income | C12: Quitamos la métrica porque es para estimación de EPCs
B13: Taxpayers | C13: Quitamos la métrica porque es para estimación de EPCs
B14: Gross carrying amount | C14: Añadimos su uso en las templates 5 y 10
... B42: Risk Mitigated CCP | C42: Quitamos debido a estar duplicada con Climate change physical risk

Sheet 2) Check dicc. y satelites 
B2: ID Metric | C2: Metric | D2: CAMBIOS | E2: Metric Name
B3: =+VLOOKUP(E3,'3) Todos satelites '!$C$6:$F$58,4,0) -> #N/A | C3: 1 | E3: GHG Financed Emissions: Scope 1
B4: =+VLOOKUP(E4,'3) Todos satelites '!$C$6:$F$58,4,0) -> #N/A | C4: 2 | E4: GHG Financed Emissions: Scope 2
B5: =+VLOOKUP(E5,'3) Todos satelites '!$C$6:$F$58,4,0) -> #N/A | C5: 3 | E5: GHG Financed Emissions: Scope 3
B6: =+VLOOKUP(E6,'3) Todos satelites '!$C$6:$F$58,4,0) -> #N/A | C6: 4 | E6: Geography of the collateral: NUTS
B7: =+VLOOKUP(E7,'3) Todos satelites '!$C$6:$F$58,4,0) -> #N/A | C7: 5 | E7: Geography of the collateral: ZIP Code
B8: =+VLOOKUP(E8,'3) Todos satelites '!$C$6:$F$58,4,0) -> #N/A | C8: 6 | D8: Si ya tenemos el NUTS y el Zip, queremos el address? | E8: Geography of the collateral: Full Address
B9: =+VLOOKUP(E9,'3) Todos satelites '!$C$6:$F$58,4,0) -> EPCL | C9: 7 | E9: EPC label
B10: =+VLOOKUP(E10,'3) Todos satelites '!$C$6:$F$58,4,0) -> EPSC | C10: 8 | E10: EP Score
B11: =+VLOOKUP(E11,'3) Todos satelites '!$C$6:$F$58,4,0) -> #N/A | C11: 9 | E11: EPC Label: Flag original / calculated
B12: =+VLOOKUP(E12,'3) Todos satelites '!$C$6:$F$58,4,0) -> #N/A | C12: 10 | E12: EP Score: Flag original / calculated
B13: =+VLOOKUP(E13,'3) Todos satelites '!$C$6:$F$58,4,0) -> #N/A | C13: 11 | D13: Se pueden usar para calcular las emisiones financiadas para CRE. Si no calculamos emisiones para esta cartera, no es una métrica necesaria | E13: EPC CO2 emissions
B14: =+VLOOKUP(E14,'3) Todos satelites '!$C$6:$F$58,4,0) -> #N/A | C14: 12 | E14: Non-performing
B15: =+VLOOKUP(E15,'3) Todos satelites '!$C$6:$F$58,4,0) -> #N/A | C15: 13 | E15: Gross carrying amount
B16: =+VLOOKUP(E16,'3) Todos satelites '!$C$6:$F$58,4,0) -> #N/A | C16: 14 | E16: Main NACE code
B17: =+VLOOKUP(E17,'3) Todos satelites '!$C$6:$F$58,4,0) -> NACE | C17: 15 | E17: NACE Code ESG
B18: =+VLOOKUP(E18,'3) Todos satelites '!$C$6:$F$58,4,0) -> #N/A | C18: 16 | E18: % Collateralised
B19: =+VLOOKUP(E19,'3) Todos satelites '!$C$6:$F$58,4,0) -> #N/A | C19: 17 | E19: Accumulated impairment
B20: =+VLOOKUP(E20,'3) Todos satelites '!$C$6:$F$58,4,0) -> #N/A | C20: 18 | E20: Type of activity
B21: =+VLOOKUP(E21,'3) Todos satelites '!$C$6:$F$58,4,0) -> #N/A | C21: 19 | E21: Type of asset
B22: =+VLOOKUP(E22,'3) Todos satelites '!$C$6:$F$58,4,0) -> #N/A | C22: 20 | E22: Flag: Companies excluded from EU Paris-aligned benchmarks
B23: =+VLOOKUP(E23,'3) Todos satelites '!$C$6:$F$58,4,0) -> #N/A | C23: 21 | E23: Flag of NFRD applicability
B24: =+VLOOKUP(E24,'3) Todos satelites '!$C$6:$F$58,4,0) -> #N/A | C24: 22 | E24: Geography of the counterparty: NUTS
B25: =+VLOOKUP(E25,'3) Todos satelites '!$C$6:$F$58,4,0) -> #N/A | C25: 23 | E25: Geography of the counterparty: ZIP Code
B26: =+VLOOKUP(E26,'3) Todos satelites '!$C$6:$F$58,4,0) -> #N/A | C26: 24 | D26: Si ya tenemos el NUTS y el Zip, queremos el address? | E26: Geography of the counterparty: Full Address
B27: =+VLOOKUP(E27,'3) Todos satelites '!$C$6:$F$58,4,0) -> #N/A | C27: 25 | E27: GHG Reported Emissions - scope 1: flag original / calculated
B28: =+VLOOKUP(E28,'3) Todos satelites '!$C$6:$F$58,4,0) -> #N/A | C28: 26 | E28: GHG Reported Emissions - scope 2: flag original / calculated
B29: =+VLOOKUP(E29,'3) Todos satelites '!$C$6:$F$58,4,0) -> #N/A | C29: 27 | E29: GHG Reported Emissions - scope 3: flag original / calculated
B30: =+VLOOKUP(E30,'3) Todos satelites '!$C$6:$F$58,4,0) -> #N/A | C30: 28 | E30: Maturity
B31: =+VLOOKUP(E31,'3) Todos satelites '!$C$6:$F$58,4,0) -> #N/A | C31: 29 | E31: Flag of specialised lending
B32: =+VLOOKUP(E32,'3) Todos satelites '!$C$6:$F$58,4,0) -> #N/A | C32: 30 | E32: Stage 2 IFRS 9
B33: =+VLOOKUP(E33,'3) Todos satelites '!$C$6:$F$58,4,0) -> #N/A | C33: 31 | E33: Taken possession
B34: =+VLOOKUP(E34,'3) Todos satelites '!$C$6:$F$58,4,0) -> #N/A | C34: 32 | E34: Type of collateral
B35: =+VLOOKUP(E35,'3) Todos satelites '!$C$6:$F$58,4,0) -> #N/A | C35: 33 | E35: Type of counterparty
B36: =+VLOOKUP(E36,'3) Todos satelites '!$C$6:$F$58,4,0) -> #N/A | C36: 34 | E36: Type of product
B37: =+VLOOKUP(E37,'3) Todos satelites '!$C$6:$F$58,4,0) -> #N/A | C37: 35 | E37: Climate change physical risk
B38: =+VLOOKUP(E38,'3) Todos satelites '!$C$6:$F$58,4,0) -> #N/A | C38: 36 | E38: Climate change transition risk
... B92: =+VLOOKUP(E92,'3) Todos satelites '!$C$6:$F$58,4,0) -> RMCP | C92: 90 | E92: Risk Mitigated CCP
B93: =+VLOOKUP(E93,'3) Todos satelites '!$C$6:$F$58,4,0) -> INC | E93: Interest commisions
B94: =+VLOOKUP(E94,'3) Todos satelites '!$C$6:$F$58,4,0) -> GEO | E94: Physical risk_Geographical Area
B95: =+VLOOKUP(E95,'3) Todos satelites '!$C$6:$F$58,4,0) -> CNAEL | E95: NACE_Level1

Sheet 3) Todos satelites 
C2: Metricas encontradas con nombre similares
C3: Metricas con nombre diferentes o no encontradas
B5: ID | C5: Metric | D5: ID | E5: ENCONTRADO EN DICCIONARIO | F5: ID
B6: INC | C6: Interest commisions | D6: INC | E6: =+VLOOKUP(C6,'2) Check dicc. y satelites '!$E$3:$E$95,1,0) -> Interest commisions | F6: INC
B7: EU | C7: European Union | D7: EU | E7: No need | F7: EU
B8: GEO | C8: Physical risk_Geographical Area | D8: GEO | E8: =+VLOOKUP(C8,'2) Check dicc. y satelites '!$E$3:$E$95,1,0) -> Physical risk_Geographical Area | F8: GEO
B9: CNAEL | C9: NACE_Level1 | D9: CNAEL | E9: =+VLOOKUP(C9,'2) Check dicc. y satelites '!$E$3:$E$95,1,0) -> NACE_Level1 | F9: CNAEL
B10: NACE | C10: NACE Code ESG | D10: NACE | E10: =+VLOOKUP(C10,'2) Check dicc. y satelites '!$E$3:$E$95,1,0) -> NACE Code ESG | F10: NACE
B11: EXC | C11: Excluded from EU Paris-aligned benchmark | D11: EXC | E11: =+'2) Check dicc. y satelites '!E22 -> Flag: Companies excluded from EU Paris-aligned benchmarks | F11: EXC
B12: ENSM | C12: Environmentally sustainable CCM | D12: ENSM | E12: =+'2) Check dicc. y satelites '!E62 -> Environmentally sustainable activity | F12: ENSM
B13: GEO | C13: Physical risk_Geographical Area | D13: GEO | E13: =+VLOOKUP(C13,'2) Check dicc. y satelites '!$E$3:$E$95,1,0) -> Physical risk_Geographical Area | F13: GEO
B14: CHRO | C14: Chronic changes | D14: CHRO | E14: =+'2) Check dicc. y satelites '!E83 -> Sensitive to impact from chronic climate change events | F14: CHRO
B15: ACUT | C15: Acute changes | D15: ACUT | E15: =+'2) Check dicc. y satelites '!E82 -> Sensitive to impact from acute climate change events | F15: ACUT
B16: MESG | C16: Maturity ESG | D16: MESG | E16: =+'2) Check dicc. y satelites '!E30 -> Maturity | F16: MESG
B17: CNAEL | C17: NACE_Level1 | D17: CNAEL | E17: =+VLOOKUP(C17,'2) Check dicc. y satelites '!$E$3:$E$95,1,0) -> NACE_Level1 | F17: CNAEL
B18: NACE | C18: NACE Code ESG | D18: NACE | E18: =+VLOOKUP(C18,'2) Check dicc. y satelites '!$E$3:$E$95,1,0) -> NACE Code ESG | F18: NACE
B19: AVEG | C19: Average weighted maturity | D19: AVEG | E19: Se calcula con MESG | F19: AVEG
B20: EPSD | C20: EP Score Data | D20: EPSD | E20: =+'2) Check dicc. y satelites '!E10 -> EP Score | F20: EPSD
B21: EPSC | C21: EP Score | D21: EPSC | E21: =+VLOOKUP(C21,'2) Check dicc. y satelites '!$E$3:$E$95,1,0) -> EP Score | F21: EPSC
B22: EPCD | C22: EPC Label Data | D22: EPCD | E22: =+'2) Check dicc. y satelites '!E9 -> EPC label | F22: EPCD
B23: EPCL | C23: EPC Label | D23: EPCL | E23: =+VLOOKUP(C23,'2) Check dicc. y satelites '!$E$3:$E$95,1,0) -> EPC label | F23: EPCL
B24: EU | C24: European Union | D24: EU | E24: No need | F24: EU
B25: GFI | C25: Green Financial Instrument | D25: GFI | E25: =+VLOOKUP(C25,'2) Check dicc. y satelites '!$E$3:$E$95,1,0) -> #N/A | F25: GFI
B26: PESG | C26: Purpose ESG | D26: PESG | E26: =+VLOOKUP(C26,'2) Check dicc. y satelites '!$E$3:$E$95,1,0) -> Purpose ESG | F26: PESG
B27: FUTY | C27: Funding type | D27: FUTY | E27: =+VLOOKUP(C27,'2) Check dicc. y satelites '!$E$3:$E$95,1,0) -> Funding Type | F27: FUTY
B28: RMCT | C28: Risk Mitigated CCT | D28: RMCT | E28: =+VLOOKUP(C28,'2) Check dicc. y satelites '!$E$3:$E$95,1,0) -> Risk Mitigated CCT | F28: RMCT
B29: RMCP | C29: Risk Mitigated CCP | D29: RMCP | E29: =+VLOOKUP(C29,'2) Check dicc. y satelites '!$E$3:$E$95,1,0) -> Risk Mitigated CCP | F29: RMCP
B30: DCON | C30: Comment | D30: DCON | E30: No need | F30: DCON
B31: ESGS | C31: ESG Subsector | D31: ESGS | E31: =+VLOOKUP(C31,'2) Check dicc. y satelites '!$E$3:$E$95,1,0) -> #N/A | F31: ESGS
B32: PESG | C32: Purpose ESG | D32: PESG | E32: =+VLOOKUP(C32,'2) Check dicc. y satelites '!$E$3:$E$95,1,0) -> Purpose ESG | F32: PESG
B33: NFRD | C33: NFRD disclosures | D33: NFRD | E33: =+'2) Check dicc. y satelites '!E23 -> Flag of NFRD applicability | F33: NFRD
B34: EU | C34: European Union | D34: EU | E34: No need | F34: EU
B35: CCM | C35: Climate Change Mitigation | D35: CCM | E35: =+'2) Check dicc. y satelites '!E59 -> Environmental objective | F35: CCM
B36: CCA | C36: Climate Change Adaptation | D36: CCA | E36: =+'2) Check dicc. y satelites '!E59 -> Environmental objective | F36: CCA
B37: GSPUR | C37: General_Specific purpose | D37: GSPUR | E37: =+VLOOKUP(C37,'2) Check dicc. y satelites '!$E$3:$E$95,1,0) -> #N/A | F37: GSPUR
B38: ENSM | C38: Environmentally sustainable CCM | D38: ENSM | E38: =+'2) Check dicc. y satelites '!E59 -> Environmental objective | F38: ENSM
B39: ENSA | C39: Environmentally sustainable CCA | D39: ENSA | E39: =+'2) Check dicc. y satelites '!E59 -> Environmental objective | F39: ENSA
B40: SPLE | C40: Specialised lending | D40: SPLE | E40: =+'2) Check dicc. y satelites '!E31 -> Flag of specialised lending | F40: SPLE
B41: TRNS | C41: Transitional | D41: TRNS | E41: =+VLOOKUP(C41,'2) Check dicc. y satelites '!$E$3:$E$95,1,0) -> #N/A | F41: TRNS
B42: ENAB | C42: Enabling CCM | D42: ENAB | E42: =+VLOOKUP(C42,'2) Check dicc. y satelites '!$E$3:$E$95,1,0) -> #N/A | F42: ENAB
B43: ENAA | C43: Enabling CCA | D43: ENAA | E43: =+VLOOKUP(C43,'2) Check dicc. y satelites '!$E$3:$E$95,1,0) -> #N/A | F43: ENAA
B44: ORDP | C44: Originated during period | D44: ORDP | E44: =+VLOOKUP(C44,'2) Check dicc. y satelites '!$E$3:$E$95,1,0) -> #N/A | F44: ORDP
B45: CCCM | C45: Amount using Capex (CCM) | D45: CCCM | E45: =+'2) Check dicc. y satelites '!E68 -> Eligibility ratio | F45: CCCM
B46: TCCM | C46: Amount using Turnover (CCM) | D46: TCCM | E46: =+VLOOKUP(C46,'2) Check dicc. y satelites '!$E$3:$E$95,1,0) -> #N/A | F46: TCCM
B47: CCCA | C47: Amount using Capex (CCA) | D47: CCCA | E47: =+'2) Check dicc. y satelites '!E68 -> Eligibility ratio | F47: CCCA
B48: TCCA | C48: Amount using Turnover (CCA) | D48: TCCA | E48: =+VLOOKUP(C48,'2) Check dicc. y satelites '!$E$3:$E$95,1,0) -> #N/A | F48: TCCA
B49: SOUR | C49: Source emission | D49: SOUR | E49: =+VLOOKUP(C49,'2) Check dicc. y satelites '!$E$3:$E$95,1,0) -> #N/A | F49: SOUR
B50: DQS | C50: Data quality score | D50: DQS | E50: =+VLOOKUP(C50,'2) Check dicc. y satelites '!$E$3:$E$95,1,0) -> #N/A | F50: DQS
B51: CNAEL | C51: NACE_Level1 | D51: CNAEL | E51: =+VLOOKUP(C51,'2) Check dicc. y satelites '!$E$3:$E$95,1,0) -> NACE_Level1 | F51: CNAEL
B52: NACE | C52: NACE Code ESG | D52: NACE | E52: =+VLOOKUP(C52,'2) Check dicc. y satelites '!$E$3:$E$95,1,0) -> NACE Code ESG | F52: NACE
B53: ASCI | C53: Amount used Scope 1 | D53: ASCI | E53: =+'2) Check dicc. y satelites '!E27 -> GHG Reported Emissions - scope 1: flag original / calculated | F53: ASCI
B54: GESI | C54: GHG Financed Emissions Scope 1 | D54: GESI | E54: =+'2) Check dicc. y satelites '!E3 -> GHG Financed Emissions: Scope 1 | F54: GESI
B55: ASCII | C55: Amount used Scope 2 | D55: ASCII | E55: =+'2) Check dicc. y satelites '!E28 -> GHG Reported Emissions - scope 2: flag original / calculated | F55: ASCII
B56: GESII | C56: GHG Financed Emissions Scope 2 | D56: GESII | E56: =+'2) Check dicc. y satelites '!E4 -> GHG Financed Emissions: Scope 2 | F56: GESII
B57: ASCIII | C57: Amount used Scope 3 | D57: ASCIII | E57: =+'2) Check dicc. y satelites '!E29 -> GHG Reported Emissions - scope 3: flag original / calculated | F57: ASCIII
B58: GESIII | C58: GHG Financed Emissions Scope 3 | D58: GESIII | E58: =+'2) Check dicc. y satelites '!E5 -> GHG Financed Emissions: Scope 3 | F58: GESIII
