Workbook

Sheet 1. Status Resumo
D11: Resumo de Testes
D13: Streams | F13: Semana Atual | L13: Highlights
F14: Por iniciar | G14: Em curso | H14: Concluído | I14: Com Incidências | J14: Pendente de desenvolv.
C15: A. Novos Campos | D15: B02.00
C16: B1. Re-especificação de campos de Sindicados | D16: Loan Tape | F16: =COUNTIFS('2. Status Detalhe Campos'!B:B,"B02.00",'2. Status Detalhe Campos'!C:C,"Loan Tape",'2. Status Detalhe Campos'!J:J,'1. Status Resumo'!$F$14) -> 0 | G16: =COUNTIFS('2. Status Detalhe Campos'!B:B,"B02.00",'2. Status Detalhe Campos'!C:C,"Loan Tape",'2. Status Detalhe Campos'!J:J,'1. Status Resumo'!$G$14) -> 12 | H16: =COUNTIFS('2. Status Detalhe Campos'!B:B,"B02.00",'2. Status Detalhe Campos'!C:C,"Loan Tape",'2. Status Detalhe Campos'!J:J,'1. Status Resumo'!$H$14) -> 6 | I16: =COUNTIFS('2. Status Detalhe Campos'!B:B,"B02.00",'2. Status Detalhe Campos'!C:C,"Loan Tape",'2. Status Detalhe Campos'!J:J,'1. Status Resumo'!$I$14) -> 7 | J16: =COUNTIFS('2. Status Detalhe Campos'!B:B,"B02.00",'2. Status Detalhe Campos'!C:C,"Loan Tape",'2. Status Detalhe Campos'!J:J,'1. Status Resumo'!$J$14) -> 3 | K16: =SUM(F16:J16) -> 28
C17: B2. Re-especificação de outros campos | D17: Tabela Output | F17: =COUNTIFS('2. Status Detalhe Campos'!B:B,"B02.00",'2. Status Detalhe Campos'!C:C,"Tabela Output",'2. Status Detalhe Campos'!J:J,'1. Status Resumo'!F14) -> 0 | G17: =COUNTIFS('2. Status Detalhe Campos'!B:B,"B02.00",'2. Status Detalhe Campos'!C:C,"Tabela Output",'2. Status Detalhe Campos'!J:J,'1. Status Resumo'!G14) -> 5 | H17: =COUNTIFS('2. Status Detalhe Campos'!B:B,"B02.00",'2. Status Detalhe Campos'!C:C,"Tabela Output",'2. Status Detalhe Campos'!J:J,'1. Status Resumo'!H14) -> 61 | I17: =COUNTIFS('2. Status Detalhe Campos'!B:B,"B02.00",'2. Status Detalhe Campos'!C:C,"Tabela Output",'2. Status Detalhe Campos'!J:J,'1. Status Resumo'!I14) -> 7 | J17: =COUNTIFS('2. Status Detalhe Campos'!B:B,"B02.00",'2. Status Detalhe Campos'!C:C,"Tabela Output",'2. Status Detalhe Campos'!J:J,'1. Status Resumo'!J14) -> 8 | K17: =SUM(F17:J17) -> 81
C18: F4. Fora âmbito | Re-especificação de campos complexos - Dem. Fin. CIB | D18: Total | F18: =SUM(F16:F17) -> 0 | G18: =SUM(G16:G17) -> 17 | H18: =SUM(H16:H17) -> 67 | I18: =SUM(I16:I17) -> 14 | J18: =SUM(J16:J17) -> 11 | K18: =SUM(F18:J18) -> 109
C19: C. Campos em testes ou c/ incidências | D19: B05.00
C20: D. Campos com NOK controlos Corporativos | D20: Loan Tape | F20: =COUNTIFS('2. Status Detalhe Campos'!B:B,"B05.00",'2. Status Detalhe Campos'!C:C,"Loan Tape",'2. Status Detalhe Campos'!J:J,'1. Status Resumo'!F14) -> 2 | G20: =COUNTIFS('2. Status Detalhe Campos'!B:B,"B05.00",'2. Status Detalhe Campos'!C:C,"Loan Tape",'2. Status Detalhe Campos'!J:J,'1. Status Resumo'!G14) -> 0 | H20: =COUNTIFS('2. Status Detalhe Campos'!B:B,"B05.00",'2. Status Detalhe Campos'!C:C,"Loan Tape",'2. Status Detalhe Campos'!J:J,'1. Status Resumo'!H14) -> 0 | I20: =COUNTIFS('2. Status Detalhe Campos'!B:B,"B05.00",'2. Status Detalhe Campos'!C:C,"Loan Tape",'2. Status Detalhe Campos'!J:J,'1. Status Resumo'!I14) -> 0 | J20: =COUNTIFS('2. Status Detalhe Campos'!B:B,"B05.00",'2. Status Detalhe Campos'!C:C,"Loan Tape",'2. Status Detalhe Campos'!J:J,'1. Status Resumo'!J14) -> 2 | K20: =SUM(F20:J20) -> 4
C21: E. Campos com outras possíveis alterações - Dependente de decisões OSI | D21: Tabela Output | F21: =COUNTIFS('2. Status Detalhe Campos'!B:B,"B05.00",'2. Status Detalhe Campos'!C:C,"Tabela Output",'2. Status Detalhe Campos'!J:J,'1. Status Resumo'!F14) -> 13 | G21: =COUNTIFS('2. Status Detalhe Campos'!B:B,"B05.00",'2. Status Detalhe Campos'!C:C,"Tabela Output",'2. Status Detalhe Campos'!J:J,'1. Status Resumo'!G14) -> 0 | H21: =COUNTIFS('2. Status Detalhe Campos'!B:B,"B05.00",'2. Status Detalhe Campos'!C:C,"Tabela Output",'2. Status Detalhe Campos'!J:J,'1. Status Resumo'!H14) -> 0 | I21: =COUNTIFS('2. Status Detalhe Campos'!B:B,"B05.00",'2. Status Detalhe Campos'!C:C,"Tabela Output",'2. Status Detalhe Campos'!J:J,'1. Status Resumo'!I14) -> 0 | J21: =COUNTIFS('2. Status Detalhe Campos'!B:B,"B05.00",'2. Status Detalhe Campos'!C:C,"Tabela Output",'2. Status Detalhe Campos'!J:J,'1. Status Resumo'!J14) -> 2 | K21: =SUM(F21:J21) -> 15
C22: F4. Fora âmbito | Re-especificação de campos complexos - Dem. Fin. CIB | D22: Total | F22: =SUM(F20:F21) -> 15 | G22: =SUM(G20:G21) -> 0 | H22: =SUM(H20:H21) -> 0 | I22: =SUM(I20:I21) -> 0 | J22: =SUM(J20:J21) -> 4 | K22: =SUM(F22:J22) -> 19
C23: F1. Fora âmbito | Campos concluídos - Sem necessidade de espec. | D23: B90.00
C24: F2. Fora âmbito | Campos em testes ou c/ incidências (LT - PM) | D24: Loan Tape | F24: =COUNTIFS('2. Status Detalhe Campos'!B:B,"B90.00",'2. Status Detalhe Campos'!C:C,"Loan Tape",'2. Status Detalhe Campos'!J:J,'1. Status Resumo'!$F$14) -> 1 | G24: =COUNTIFS('2. Status Detalhe Campos'!B:B,"B90.00",'2. Status Detalhe Campos'!C:C,"Loan Tape",'2. Status Detalhe Campos'!J:J,'1. Status Resumo'!$G$14) -> 8 | H24: =COUNTIFS('2. Status Detalhe Campos'!B:B,"B90.00",'2. Status Detalhe Campos'!C:C,"Loan Tape",'2. Status Detalhe Campos'!J:J,'1. Status Resumo'!$H$14) -> 0 | I24: =COUNTIFS('2. Status Detalhe Campos'!B:B,"B90.00",'2. Status Detalhe Campos'!C:C,"Loan Tape",'2. Status Detalhe Campos'!J:J,'1. Status Resumo'!$I$14) -> 0 | J24: =COUNTIFS('2. Status Detalhe Campos'!B:B,"B90.00",'2. Status Detalhe Campos'!C:C,"Loan Tape",'2. Status Detalhe Campos'!J:J,'1. Status Resumo'!$J$14) -> 2 | K24: =SUM(F24:J24) -> 11
C25: F3. Fora âmbito | Fonte manual LF | D25: Tabela Output | F25: =COUNTIFS('2. Status Detalhe Campos'!B:B,"B90.00",'2. Status Detalhe Campos'!C:C,"Tabela Output",'2. Status Detalhe Campos'!J:J,'1. Status Resumo'!$F$14) -> 0 | G25: =COUNTIFS('2. Status Detalhe Campos'!B:B,"B90.00",'2. Status Detalhe Campos'!C:C,"Tabela Output",'2. Status Detalhe Campos'!J:J,'1. Status Resumo'!$G$14) -> 3 | H25: =COUNTIFS('2. Status Detalhe Campos'!B:B,"B90.00",'2. Status Detalhe Campos'!C:C,"Tabela Output",'2. Status Detalhe Campos'!J:J,'1. Status Resumo'!$H$14) -> 0 | I25: =COUNTIFS('2. Status Detalhe Campos'!B:B,"B90.00",'2. Status Detalhe Campos'!C:C,"Tabela Output",'2. Status Detalhe Campos'!J:J,'1. Status Resumo'!$I$14) -> 0 | J25: =COUNTIFS('2. Status Detalhe Campos'!B:B,"B90.00",'2. Status Detalhe Campos'!C:C,"Tabela Output",'2. Status Detalhe Campos'!J:J,'1. Status Resumo'!$J$14) -> 8 | K25: =SUM(F25:J25) -> 11
C26: F4. Fora âmbito | Re-especificação de campos complexos - Dem. Fin. CIB | D26: Total | F26: =SUM(F24:F25) -> 1 | G26: =SUM(G24:G25) -> 11 | H26: =SUM(H24:H25) -> 0 | I26: =SUM(I24:I25) -> 0 | J26: =SUM(J24:J25) -> 10 | K26: =SUM(F26:J26) -> 22
D28: Resumo de Controlos
D30: Streams | F30: Semana Atual
F31: Por iniciar | G31: Em curso | H31: Concluído | I31: Com Incidências | J31: Pendente de desenvolv.
D32: B02.00 | F32: =COUNTIFS('2. Status Detalhe Campos'!$B:$B,$D$32,'2. Status Detalhe Campos'!$C:$C,"Controlos",'2. Status Detalhe Campos'!$J:$J,F$31) -> 29 | G32: =COUNTIFS('2. Status Detalhe Campos'!$B:$B,$D$32,'2. Status Detalhe Campos'!$C:$C,"Controlos",'2. Status Detalhe Campos'!$J:$J,G$31) -> 0 | H32: =COUNTIFS('2. Status Detalhe Campos'!$B:$B,$D$32,'2. Status Detalhe Campos'!$C:$C,"Controlos",'2. Status Detalhe Campos'!$J:$J,H$31) -> 92 | I32: =COUNTIFS('2. Status Detalhe Campos'!$B:$B,$D$32,'2. Status Detalhe Campos'!$C:$C,"Controlos",'2. Status Detalhe Campos'!$J:$J,I$31) -> 6 | J32: =COUNTIFS('2. Status Detalhe Campos'!$B:$B,$D$32,'2. Status Detalhe Campos'!$C:$C,"Controlos",'2. Status Detalhe Campos'!$J:$J,J$31) -> 27 | K32: =SUM(F32:J32) -> 154
D33: B05.00 | F33: 18 | G33: =COUNTIFS('2. Status Detalhe Campos'!$B:$B,$D$33,'2. Status Detalhe Campos'!$C:$C,"Controlos",'2. Status Detalhe Campos'!$J:$J,G$31) -> 0 | H33: =COUNTIFS('2. Status Detalhe Campos'!$B:$B,$D$33,'2. Status Detalhe Campos'!$C:$C,"Controlos",'2. Status Detalhe Campos'!$J:$J,H$31) -> 0 | I33: =COUNTIFS('2. Status Detalhe Campos'!$B:$B,$D$33,'2. Status Detalhe Campos'!$C:$C,"Controlos",'2. Status Detalhe Campos'!$J:$J,I$31) -> 0 | J33: 3 | K33: =SUM(F33:J33) -> 21
D34: B90.00 | F34: 13 | G34: =COUNTIFS('2. Status Detalhe Campos'!$B:$B,$D$34,'2. Status Detalhe Campos'!$C:$C,"Controlos",'2. Status Detalhe Campos'!$J:$J,G$31) -> 0 | H34: =COUNTIFS('2. Status Detalhe Campos'!$B:$B,$D$34,'2. Status Detalhe Campos'!$C:$C,"Controlos",'2. Status Detalhe Campos'!$J:$J,H$31) -> 0 | I34: =COUNTIFS('2. Status Detalhe Campos'!$B:$B,$D$34,'2. Status Detalhe Campos'!$C:$C,"Controlos",'2. Status Detalhe Campos'!$J:$J,I$31) -> 0 | J34: 3 | K34: =SUM(F34:J34) -> 16
D35: Total | F35: =SUM(F32:F34) -> 60 | G35: =SUM(G32:G34) -> 0 | H35: =SUM(H32:H34) -> 92 | I35: =SUM(I32:I34) -> 6 | J35: =SUM(J32:J34) -> 33 | K35: =SUM(F35:J35) -> 191
D37: Resumo do Dry-run
D39: Streams | F39: Semana Atual
F40: Concluído com ajuste | G40: Concluído sem ajuste | H40: Em curso | I40: Pendente de ajuste
D41: B02.00 | F41: =COUNTIFS('2. Status Detalhe Campos'!$B:$B,'1. Status Resumo'!$D$41,'2. Status Detalhe Campos'!$I:$I,'1. Status Resumo'!F40) -> 13 | G41: =COUNTIFS('2. Status Detalhe Campos'!$B:$B,'1. Status Resumo'!$D$41,'2. Status Detalhe Campos'!$I:$I,'1. Status Resumo'!G40) -> 61 | H41: =COUNTIFS('2. Status Detalhe Campos'!$B:$B,'1. Status Resumo'!$D$41,'2. Status Detalhe Campos'!$I:$I,'1. Status Resumo'!H40) -> 0 | I41: =COUNTIFS('2. Status Detalhe Campos'!$B:$B,'1. Status Resumo'!$D$41,'2. Status Detalhe Campos'!$I:$I,'1. Status Resumo'!I40) -> 7 | J41: =SUM(E41:I41) -> 81
D42: B90.00 | F42: =COUNTIFS('2. Status Detalhe Campos'!$B:$B,'1. Status Resumo'!$D$42,'2. Status Detalhe Campos'!$I:$I,'1. Status Resumo'!F40) -> 6 | G42: =COUNTIFS('2. Status Detalhe Campos'!$B:$B,'1. Status Resumo'!$D$42,'2. Status Detalhe Campos'!$I:$I,'1. Status Resumo'!G40) -> 4 | H42: =COUNTIFS('2. Status Detalhe Campos'!$B:$B,'1. Status Resumo'!$D$42,'2. Status Detalhe Campos'!$I:$I,'1. Status Resumo'!H40) -> 0 | I42: =COUNTIFS('2. Status Detalhe Campos'!$B:$B,'1. Status Resumo'!$D$42,'2. Status Detalhe Campos'!$I:$I,'1. Status Resumo'!I40) -> 1 | J42: =SUM(E42:I42) -> 11
D43: Total | F43: =SUM(F41:F42) -> 19 | G43: =SUM(G41:G42) -> 65 | H43: =SUM(H41:H42) -> 0 | I43: =SUM(I41:I42) -> 8
D45: Controlos | F45: # Controlos Totais | G45: Controlos NOK
D46: Level 1 | F46: =+SUM(F47:F48) -> 40 | G46: =+SUM(G47:G48) -> 0 | H46: =+G46/F46 -> 0
D47: B02.00 | F47: 39 | G47: 0 | H47: =+G47/F47 -> 0 | I47: 0180_dt_nxt_intrst_pymnt
D48: B90.00 | F48: 1 | G48: 0 | H48: =+G48/F48 -> 0
D49: Level 2 | F49: =+SUM(F50:F51) -> 40 | G49: =+SUM(G50:G51) -> 0 | H49: =+G49/F49 -> 0
D50: B02.00 | F50: 36 | G50: 0 | H50: =+G50/F50 -> 0 | I50: 0530_typ_own_fnds_ind_lvl, 0550_typ_own_fnds_cnsldtd_lvl
D51: B90.00 | F51: 4 | G51: 0 | H51: =+G51/F51 -> 0 | I51: 0090_CNTRY_CNTRPRTY STRING, 0100_RLVNT_AMNT_WDC
D57: B02.00
P60: Highlights
C61: A. Novos Campos | P61: Resumo semana atual: Tabela de Operações (lt002_instrument): Foram testados 3 campos onde foram verificadas as seguintes incidências: - Campo typ_own_fnds_indvdl_lvl - Registos com valor null. Necessidade de ajustar a parametrização lt804_conf_dflt. - Campo orgnl_amnt_fx - Todos os registos com valor default (99999999999.00). Necessidade de ajustar a parametrização lt804_conf_dflt. - Campo accntng_clssfctn - Todos os registos com valor default (99999999999). Necessidade de ajustar as parametrizações lt829_regras_conversao e lt830_conversoes. - Campo isin - O campo não está de acordo com a especificação de PM (valores de N/A para quando flag_inst_div = 0) - Campo typ_instrmnt - Todos os registos não respeitam a code list.Necessidade de ajustar as parametrizações lt829_regras_conversao e lt830_conversoes. Tabela Output (out_b0200_main_liabilities): Foram testados 48 campos onde foram verificadas 5 campos com incidências: - Campo 0020_uniq_id - 1 operação duplicada; - Campo 0030_uniq_id_knwn_cntrprty - Campo com incidências - Campo 0140_ntr_lblty - Todos os registos mapeados com valores que não respeitam code list. - Campo 0060_orgnl_amnt_fx - Todos os registos mapeados com um valor default. - Campo 0530_typ_own_fnds_ind_lvl - 2 registos com valores não válidos (null). - Campo 0550_typ_own_fnds_cnsldtd_lvl - 2 registos com valores não válidos (null). - Campo 0620_blnc_sht_ifrs - Todos os registos mapeados com um valor default. Após o ajuste das parametrizações no LT é expectável a resolução das incidência reportadas (exceto a operação duplicada). Todos os temas supramencionados já foram endereçados com a equipa de IT.
C62: B1. Re-especificação de campos de Sindicados
C63: B2. Re-especificação de outros campos
C65: F4. Fora âmbito | Re-especificação de campos complexos - Dem. Fin. CIB
D74: Status (campos) | E74: 45959 | F74: 45968 | G74: ∆ | J74: Status (campos) | K74: 45959 | L74: 45968 | M74: ∆
D75: Por iniciar | E75: =COUNTIFS('2. Status Detalhe Campos'!B:B,"B02.00",'2. Status Detalhe Campos'!C:C,"Loan Tape",'2. Status Detalhe Campos'!K:K,"Por iniciar") -> 0 | F75: =COUNTIFS('2. Status Detalhe Campos'!B:B,"B02.00",'2. Status Detalhe Campos'!C:C,"Loan Tape",'2. Status Detalhe Campos'!J:J,"Por iniciar") -> 0 | G75: =+F75-E75 -> 0 | H75: =+IF(F75=0,NA(),F75) -> #N/A | J75: Por iniciar | K75: =COUNTIFS('2. Status Detalhe Campos'!B:B,"B02.00",'2. Status Detalhe Campos'!C:C,"Tabela Output",'2. Status Detalhe Campos'!K:K,"Por iniciar") -> 0 | L75: =COUNTIFS('2. Status Detalhe Campos'!B:B,"B02.00",'2. Status Detalhe Campos'!C:C,"Tabela Output",'2. Status Detalhe Campos'!J:J,"Por iniciar") -> 0 | M75: =+L75-K75 -> 0 | N75: =+IF(L75=0,NA(),L75) -> #N/A
D76: Em curso | E76: =COUNTIFS('2. Status Detalhe Campos'!B:B,"B02.00",'2. Status Detalhe Campos'!C:C,"Loan Tape",'2. Status Detalhe Campos'!K:K,"Em curso") -> 12 | F76: =COUNTIFS('2. Status Detalhe Campos'!B:B,"B02.00",'2. Status Detalhe Campos'!C:C,"Loan Tape",'2. Status Detalhe Campos'!J:J,"Em curso") -> 12 | G76: =+F76-E76 -> 0 | H76: =+IF(F76=0,NA(),F76) -> 12 | J76: Em curso | K76: =COUNTIFS('2. Status Detalhe Campos'!B:B,"B02.00",'2. Status Detalhe Campos'!C:C,"Tabela Output",'2. Status Detalhe Campos'!K:K,"Em curso") -> 5 | L76: =COUNTIFS('2. Status Detalhe Campos'!B:B,"B02.00",'2. Status Detalhe Campos'!C:C,"Tabela Output",'2. Status Detalhe Campos'!J:J,"Em curso") -> 5 | M76: =+L76-K76 -> 0 | N76: =+IF(L76=0,NA(),L76) -> 5
D77: Concluídos | E77: =COUNTIFS('2. Status Detalhe Campos'!B:B,"B02.00",'2. Status Detalhe Campos'!C:C,"Loan Tape",'2. Status Detalhe Campos'!K:K,"Concluído") -> 6 | F77: =COUNTIFS('2. Status Detalhe Campos'!B:B,"B02.00",'2. Status Detalhe Campos'!C:C,"Loan Tape",'2. Status Detalhe Campos'!J:J,"Concluído") -> 6 | G77: =+F77-E77 -> 0 | H77: =+IF(F77=0,NA(),F77) -> 6 | J77: Concluídos | K77: =COUNTIFS('2. Status Detalhe Campos'!B:B,"B02.00",'2. Status Detalhe Campos'!C:C,"Tabela Output",'2. Status Detalhe Campos'!K:K,"Concluído") -> 61 | L77: =COUNTIFS('2. Status Detalhe Campos'!B:B,"B02.00",'2. Status Detalhe Campos'!C:C,"Tabela Output",'2. Status Detalhe Campos'!J:J,"Concluído") -> 61 | M77: =+L77-K77 -> 0 | N77: =+IF(L77=0,NA(),L77) -> 61
D78: Pendente de desenvolv. | E78: =COUNTIFS('2. Status Detalhe Campos'!B:B,"B02.00",'2. Status Detalhe Campos'!C:C,"Loan Tape",'2. Status Detalhe Campos'!K:K,"Pendente de desenvolv.") -> 3 | F78: =COUNTIFS('2. Status Detalhe Campos'!B:B,"B02.00",'2. Status Detalhe Campos'!C:C,"Loan Tape",'2. Status Detalhe Campos'!J:J,"Pendente de desenvolv.") -> 3 | G78: =+F78-E78 -> 0 | H78: =+IF(F78=0,NA(),F78) -> 3 | J78: Pendente de desenvolv. | K78: =COUNTIFS('2. Status Detalhe Campos'!B:B,"B02.00",'2. Status Detalhe Campos'!C:C,"Tabela Output",'2. Status Detalhe Campos'!K:K,"Pendente de desenvolv.") -> 8 | L78: =COUNTIFS('2. Status Detalhe Campos'!B:B,"B02.00",'2. Status Detalhe Campos'!C:C,"Tabela Output",'2. Status Detalhe Campos'!J:J,"Pendente de desenvolv.") -> 8 | M78: =+L78-K78 -> 0 | N78: =+IF(L78=0,NA(),L78) -> 8
D79: Com Incidências. | E79: =COUNTIFS('2. Status Detalhe Campos'!B:B,"B02.00",'2. Status Detalhe Campos'!C:C,"Loan Tape",'2. Status Detalhe Campos'!K:K,"Com incidências") -> 7 | F79: =COUNTIFS('2. Status Detalhe Campos'!B:B,"B02.00",'2. Status Detalhe Campos'!C:C,"Loan Tape",'2. Status Detalhe Campos'!J:J,"Com incidências") -> 7 | G79: =+F79-E79 -> 0 | H79: =+IF(F79=0,NA(),F79) -> 7 | J79: Com Incidências. | K79: =COUNTIFS('2. Status Detalhe Campos'!B:B,"B02.00",'2. Status Detalhe Campos'!C:C,"Tabela Output",'2. Status Detalhe Campos'!K:K,"Com incidências") -> 7 | L79: =COUNTIFS('2. Status Detalhe Campos'!B:B,"B02.00",'2. Status Detalhe Campos'!C:C,"Tabela Output",'2. Status Detalhe Campos'!J:J,"Com incidências") -> 7 | M79: =+L79-K79 -> 0 | N79: =+IF(L79=0,NA(),L79) -> 7
D80: Total | E80: =SUM(E75:E79) -> 28 | F80: =SUM(F75:F79) -> 28 | G80: =+F80-E80 -> 0 | J80: Total | K80: =SUM(K75:K79) -> 81 | L80: =SUM(L75:L79) -> 81 | M80: =+L80-K80 -> 0
D83: B05.00
P86: Highlights
C87: A. Novos Campos | P87: Resumo semana atual: Tabelas LT: - Sem avanços na presente semana. Tabela Output (out_b0500_guarantees): - Sem avanços na presente semana.
C88: B1. Re-especificação de campos de Sindicados
C89: B2. Re-especificação de outros campos
C91: F4. Fora âmbito | Re-especificação de campos complexos - Dem. Fin. CIB
D100: Status (campos) | E100: 45952 | F100: 45968 | G100: ∆ | J100: Status (campos) | K100: 45952 | L100: 45968 | M100: ∆
D101: Por iniciar | E101: =COUNTIFS('2. Status Detalhe Campos'!B:B,"B05.00",'2. Status Detalhe Campos'!C:C,"Loan Tape",'2. Status Detalhe Campos'!K:K,"Por iniciar") -> 2 | F101: =COUNTIFS('2. Status Detalhe Campos'!B:B,"B05.00",'2. Status Detalhe Campos'!C:C,"Loan Tape",'2. Status Detalhe Campos'!J:J,"Por iniciar") -> 2 | G101: =+F101-E101 -> 0 | H101: =+IF(F101=0,NA(),F101) -> 2 | J101: Por iniciar | K101: =COUNTIFS('2. Status Detalhe Campos'!B:B,"B05.00",'2. Status Detalhe Campos'!C:C,"Tabela Output",'2. Status Detalhe Campos'!K:K,"Por iniciar") -> 13 | L101: =COUNTIFS('2. Status Detalhe Campos'!B:B,"B05.00",'2. Status Detalhe Campos'!C:C,"Tabela Output",'2. Status Detalhe Campos'!J:J,"Por iniciar") -> 13 | M101: =+L101-K101 -> 0 | N101: =+IF(L101=0,NA(),L101) -> 13
D102: Em curso | E102: =COUNTIFS('2. Status Detalhe Campos'!B:B,"B05.00",'2. Status Detalhe Campos'!C:C,"Loan Tape",'2. Status Detalhe Campos'!K:K,"Em curso") -> 0 | F102: =COUNTIFS('2. Status Detalhe Campos'!B:B,"B05.00",'2. Status Detalhe Campos'!C:C,"Loan Tape",'2. Status Detalhe Campos'!J:J,"Em curso") -> 0 | G102: =+F102-E102 -> 0 | H102: =+IF(F102=0,NA(),F102) -> #N/A | J102: Em curso | K102: =COUNTIFS('2. Status Detalhe Campos'!B:B,"B05.00",'2. Status Detalhe Campos'!C:C,"Tabela Output",'2. Status Detalhe Campos'!K:K,"Em curso") -> 0 | L102: =COUNTIFS('2. Status Detalhe Campos'!B:B,"B05.00",'2. Status Detalhe Campos'!C:C,"Tabela Output",'2. Status Detalhe Campos'!J:J,"Em curso") -> 0 | M102: =+L102-K102 -> 0 | N102: =+IF(L102=0,NA(),L102) -> #N/A
D103: Concluídos | E103: =COUNTIFS('2. Status Detalhe Campos'!B:B,"B05.00",'2. Status Detalhe Campos'!C:C,"Loan Tape",'2. Status Detalhe Campos'!K:K,"Concluídos") -> 0 | F103: =COUNTIFS('2. Status Detalhe Campos'!B:B,"B05.00",'2. Status Detalhe Campos'!C:C,"Loan Tape",'2. Status Detalhe Campos'!J:J,"Concluídos") -> 0 | G103: =+F103-E103 -> 0 | H103: =+IF(F103=0,NA(),F103) -> #N/A | J103: Concluídos | K103: =COUNTIFS('2. Status Detalhe Campos'!B:B,"B05.00",'2. Status Detalhe Campos'!C:C,"Tabela Output",'2. Status Detalhe Campos'!K:K,"Concluídos") -> 0 | L103: =COUNTIFS('2. Status Detalhe Campos'!B:B,"B05.00",'2. Status Detalhe Campos'!C:C,"Tabela Output",'2. Status Detalhe Campos'!J:J,"Concluídos") -> 0 | M103: =+L103-K103 -> 0 | N103: =+IF(L103=0,NA(),L103) -> #N/A
D104: Pendente de desenvolv. | E104: =COUNTIFS('2. Status Detalhe Campos'!B:B,"B05.00",'2. Status Detalhe Campos'!C:C,"Loan Tape",'2. Status Detalhe Campos'!K:K,"Pendente de desenvolv.") -> 2 | F104: =COUNTIFS('2. Status Detalhe Campos'!B:B,"B05.00",'2. Status Detalhe Campos'!C:C,"Loan Tape",'2. Status Detalhe Campos'!J:J,"Pendente de desenvolv.") -> 2 | G104: =+F104-E104 -> 0 | H104: =+IF(F104=0,NA(),F104) -> 2 | J104: Pendente de desenvolv. | K104: =COUNTIFS('2. Status Detalhe Campos'!B:B,"B05.00",'2. Status Detalhe Campos'!C:C,"Tabela Output",'2. Status Detalhe Campos'!K:K,"Pendente de desenvolv.") -> 2 | L104: =COUNTIFS('2. Status Detalhe Campos'!B:B,"B05.00",'2. Status Detalhe Campos'!C:C,"Tabela Output",'2. Status Detalhe Campos'!J:J,"Pendente de desenvolv.") -> 2 | M104: =+L104-K104 -> 0 | N104: =+IF(L104=0,NA(),L104) -> 2
D105: Com Incidências. | E105: =COUNTIFS('2. Status Detalhe Campos'!B:B,"B05.00",'2. Status Detalhe Campos'!C:C,"Loan Tape",'2. Status Detalhe Campos'!K:K,"Com incidências") -> 0 | F105: =COUNTIFS('2. Status Detalhe Campos'!B:B,"B05.00",'2. Status Detalhe Campos'!C:C,"Loan Tape",'2. Status Detalhe Campos'!J:J,"Com incidências") -> 0 | G105: =+F105-E105 -> 0 | H105: =+IF(F105=0,NA(),F105) -> #N/A | J105: Com Incidências. | K105: =COUNTIFS('2. Status Detalhe Campos'!B:B,"B05.00",'2. Status Detalhe Campos'!C:C,"Tabela Output",'2. Status Detalhe Campos'!K:K,"Com incidências") -> 0 | L105: =COUNTIFS('2. Status Detalhe Campos'!B:B,"B05.00",'2. Status Detalhe Campos'!C:C,"Tabela Output",'2. Status Detalhe Campos'!J:J,"Com incidências") -> 0 | M105: =+L105-K105 -> 0 | N105: =+IF(L105=0,NA(),L105) -> #N/A
D106: Total | E106: =SUM(E101:E105) -> 4 | F106: =SUM(F101:F105) -> 4 | G106: =SUM(G101:G105) -> 0 | J106: Total | K106: =SUM(K101:K105) -> 15 | L106: =SUM(L101:L105) -> 15 | M106: =SUM(M101:M105) -> 0
D108: B90.00
P111: Highlights
C112: A. Novos Campos | P112: Resumo semana atual: Tabelas LT: - Simulação de 8 campos. Tabela Output (out_b9000_counterparties): - Foram testados e sem incidências um total de 3 campos com referência ao mapa B02.00.
C113: B1. Re-especificação de campos de Sindicados
C114: B2. Re-especificação de outros campos
C116: F4. Fora âmbito | Re-especificação de campos complexos - Dem. Fin. CIB
D125: Status (campos) | E125: 45952 | F125: 45968 | G125: ∆ | J125: Status (campos) | K125: 45952 | L125: 45968 | M125: ∆
D126: Por iniciar | E126: =COUNTIFS('2. Status Detalhe Campos'!B:B,"B90.00",'2. Status Detalhe Campos'!C:C,"Loan Tape",'2. Status Detalhe Campos'!K:K,"Por iniciar") -> 1 | F126: =COUNTIFS('2. Status Detalhe Campos'!B:B,"B90.00",'2. Status Detalhe Campos'!C:C,"Loan Tape",'2. Status Detalhe Campos'!J:J,"Por iniciar") -> 1 | G126: =+F126-E126 -> 0 | H126: =+IF(F126=0,NA(),F126) -> 1 | J126: Por iniciar | K126: =COUNTIFS('2. Status Detalhe Campos'!B:B,"B90.00",'2. Status Detalhe Campos'!C:C,"Tabela Output",'2. Status Detalhe Campos'!K:K,"Por iniciar") -> 0 | L126: =COUNTIFS('2. Status Detalhe Campos'!B:B,"B90.00",'2. Status Detalhe Campos'!C:C,"Tabela Output",'2. Status Detalhe Campos'!J:J,"Por iniciar") -> 0 | M126: =+L126-K126 -> 0 | N126: =+IF(L126=0,NA(),L126) -> #N/A
D127: Em curso | E127: =COUNTIFS('2. Status Detalhe Campos'!B:B,"B90.00",'2. Status Detalhe Campos'!C:C,"Loan Tape",'2. Status Detalhe Campos'!K:K,"Em curso") -> 8 | F127: =COUNTIFS('2. Status Detalhe Campos'!B:B,"B90.00",'2. Status Detalhe Campos'!C:C,"Loan Tape",'2. Status Detalhe Campos'!J:J,"Em curso") -> 8 | G127: =+F127-E127 -> 0 | H127: =+IF(F127=0,NA(),F127) -> 8 | J127: Em curso | K127: =COUNTIFS('2. Status Detalhe Campos'!B:B,"B90.00",'2. Status Detalhe Campos'!C:C,"Tabela Output",'2. Status Detalhe Campos'!K:K,"Em curso") -> 3 | L127: =COUNTIFS('2. Status Detalhe Campos'!B:B,"B90.00",'2. Status Detalhe Campos'!C:C,"Tabela Output",'2. Status Detalhe Campos'!J:J,"Em curso") -> 3 | M127: =+L127-K127 -> 0 | N127: =+IF(L127=0,NA(),L127) -> 3
D128: Concluídos | E128: =COUNTIFS('2. Status Detalhe Campos'!B:B,"B90.00",'2. Status Detalhe Campos'!C:C,"Loan Tape",'2. Status Detalhe Campos'!K:K,"Concluídos") -> 0 | F128: =COUNTIFS('2. Status Detalhe Campos'!B:B,"B90.00",'2. Status Detalhe Campos'!C:C,"Loan Tape",'2. Status Detalhe Campos'!J:J,"Concluídos") -> 0 | G128: =+F128-E128 -> 0 | H128: =+IF(F128=0,NA(),F128) -> #N/A | J128: Concluídos | K128: =COUNTIFS('2. Status Detalhe Campos'!B:B,"B90.00",'2. Status Detalhe Campos'!C:C,"Tabela Output",'2. Status Detalhe Campos'!K:K,"Concluídos") -> 0 | L128: =COUNTIFS('2. Status Detalhe Campos'!B:B,"B90.00",'2. Status Detalhe Campos'!C:C,"Tabela Output",'2. Status Detalhe Campos'!J:J,"Concluídos") -> 0 | M128: =+L128-K128 -> 0 | N128: =+IF(L128=0,NA(),L128) -> #N/A
D129: Pendente de desenvolv. | E129: =COUNTIFS('2. Status Detalhe Campos'!B:B,"B90.00",'2. Status Detalhe Campos'!C:C,"Loan Tape",'2. Status Detalhe Campos'!K:K,"Pendente de desenvolv.") -> 2 | F129: =COUNTIFS('2. Status Detalhe Campos'!B:B,"B90.00",'2. Status Detalhe Campos'!C:C,"Loan Tape",'2. Status Detalhe Campos'!J:J,"Pendente de desenvolv.") -> 2 | G129: =+F129-E129 -> 0 | H129: =+IF(F129=0,NA(),F129) -> 2 | J129: Pendente de desenvolv. | K129: =COUNTIFS('2. Status Detalhe Campos'!B:B,"B90.00",'2. Status Detalhe Campos'!C:C,"Tabela Output",'2. Status Detalhe Campos'!K:K,"Pendente de desenvolv.") -> 8 | L129: =COUNTIFS('2. Status Detalhe Campos'!B:B,"B90.00",'2. Status Detalhe Campos'!C:C,"Tabela Output",'2. Status Detalhe Campos'!J:J,"Pendente de desenvolv.") -> 8 | M129: =+L129-K129 -> 0 | N129: =+IF(L129=0,NA(),L129) -> 8
D130: Com Incidências. | E130: =COUNTIFS('2. Status Detalhe Campos'!B:B,"B90.00",'2. Status Detalhe Campos'!C:C,"Loan Tape",'2. Status Detalhe Campos'!K:K,"Com incidências") -> 0 | F130: =COUNTIFS('2. Status Detalhe Campos'!B:B,"B90.00",'2. Status Detalhe Campos'!C:C,"Loan Tape",'2. Status Detalhe Campos'!J:J,"Com incidências") -> 0 | G130: =+F130-E130 -> 0 | H130: =+IF(F130=0,NA(),F130) -> #N/A | J130: Com Incidências. | K130: =COUNTIFS('2. Status Detalhe Campos'!B:B,"B90.00",'2. Status Detalhe Campos'!C:C,"Tabela Output",'2. Status Detalhe Campos'!K:K,"Com incidências") -> 0 | L130: =COUNTIFS('2. Status Detalhe Campos'!B:B,"B90.00",'2. Status Detalhe Campos'!C:C,"Tabela Output",'2. Status Detalhe Campos'!J:J,"Com incidências") -> 0 | M130: =+L130-K130 -> 0 | N130: =+IF(L130=0,NA(),L130) -> #N/A
D131: Total | E131: =SUM(E126:E130) -> 11 | F131: =SUM(F126:F130) -> 11 | G131: =SUM(G126:G130) -> 0 | J131: Total | K131: =SUM(K126:K130) -> 11 | L131: =SUM(L126:L130) -> 11 | M131: =SUM(M126:M130) -> 0
D138: Status dos Controlos
D140: Tipo de Controlo | F140: #Controlos Totais | G140: #Controlos Por iniciar | H140: #Controlos OK | I140: #Controlos NOK | K140: Observações (relativas aos NOK) | N140: Highlights
I141: #Controlos por justificar | J141: #Controlos justificados | N141: Resumo semana atual: De acordo com o Anexo II, forma identificados controlos de 3 categorias: - Nível 1; - Nível 2; - Formatos. Por sua vez se repartem em função dos mapas: - 156 controlos para o mapa B02.00; - 21 controlos para o mapa B05.00; - 16 controlos para o mapa B90.00. Tabela Output out_b0200_main_liabilities: Foram desenvolvidos todos os controlos previstos, contudo, considerando apenas os campos concluídos por tecnologia e sem incidêncicas na simulação, foram verificadas as seguintes incidências: - Os campos 0141_ntr_lblty_othr, 0340_id_clltrl, 0351_typ_clltrl_othr, 0462_csd_othr, 0640_blnc_sht_ngaap: estão com valor fixo 'Not applicable' mas no Anexo II não prevê nenhum valor no caso de não aplicável e/ou não disponível. - O campo 0150_flg_strctrlly_sbrdntd: está com 'Not applicable' mas devia respeitar uma code list (TRUE/FALSE); Tabelas Output out_b0500_guarantees e out_b9000_counterparties: não foi dada prioridade nos controlos relativos a estas duas tabelas, dada a prioridade aos campos alvos ao exercício do dry-run.
D142: B02.00 | F142: =+SUM(F143,F146,F149) -> 156 | G142: =+SUM(G143,G146,G149)/$F$142 -> 0.42948718 | H142: =+SUM(H143,H146,H149)/$F$142 -> 0.53205128 | I142: =+SUM(I143,I146,I149)/$F$142 -> 0.038461538 | J142: =+SUM(J143,J146,J149)/$F$142 -> 0
D143: Nível I | F143: =+SUM(F144:F145) -> 39 | G143: =+SUM(G144:G145) -> 21 | H143: =+SUM(H144:H145) -> 18 | I143: =+SUM(I144:I145) -> 0 | J143: =+SUM(J144:J145) -> 0
D144: High Severity | F144: 30 | G144: =IF(F144-SUM(H144:J144)<0,"REVER -->",F144-SUM(H144:J144)) -> 15 | H144: 15 | I144: 0 | J144: 0
D145: Warning | F145: 9 | G145: =+F145-SUM(H145:J145) -> 6 | H145: 3 | I145: 0 | J145: 0
D146: Nível II | F146: =+SUM(F147:F148) -> 36 | G146: =+SUM(G147:G148) -> 21 | H146: =+SUM(H147:H148) -> 15 | I146: 0 | J146: =+SUM(J147:J148) -> 0
D147: High Severity | F147: 33 | G147: =+F147-SUM(H147:J147) -> 19 | H147: 14 | I147: 0 | J147: 0
D148: Warning | F148: 3 | G148: =+F148-SUM(H148:J148) -> 2 | H148: 1 | I148: 0 | J148: 0
D149: Formatos | F149: 81 | G149: =+F149-SUM(H149:J149) -> 25 | H149: 50 | I149: 6 | J149: 0 | K149: 0141, 0340, 0351, 0462, 0640, 0150
D150: B05.00 | F150: =+SUM(F151,F154,F157) -> 21 | G150: =+SUM(G151,G154,G157)/$F$150 -> 1 | H150: =+SUM(H151,H154,H157)/$F$142 -> 0 | I150: =+SUM(I151,I154,I157)/$F$142 -> 0 | J150: =+SUM(J151,J154,J157)/$F$142 -> 0
D151: Nível I | F151: =+SUM(F152:F153) -> 0 | G151: =+SUM(G152:G153) -> 0 | H151: =+SUM(H152:H153) -> 0 | I151: =+SUM(I152:I153) -> 0 | J151: =+SUM(J152:J153) -> 0
D152: High Severity | F152: 0 | G152: =+F152-SUM(H152:J152) -> 0 | H152: 0 | I152: 0 | J152: 0
D153: Warning | F153: 0 | G153: =+F153-SUM(H153:J153) -> 0 | H153: 0 | I153: 0 | J153: 0
D154: Nível II | F154: =+SUM(F155:F156) -> 5 | G154: =+SUM(G155:G156) -> 5 | H154: =+SUM(H155:H156) -> 0 | I154: =+SUM(I155:I156) -> 0 | J154: =+SUM(J155:J156) -> 0
D155: High Severity | F155: 5 | G155: =+F155-SUM(H155:J155) -> 5 | H155: 0 | I155: 0 | J155: 0
D156: Warning | F156: 0 | G156: =+F156-SUM(H156:J156) -> 0 | H156: 0 | I156: 0 | J156: 0
D157: Formatos | F157: 16 | G157: =+F157-SUM(H157:J157) -> 16 | H157: 0 | I157: 0 | J157: 0
D158: B90.00 | F158: =+SUM(F159,F162,F165) -> 16 | G158: =+SUM(G159,G162,G165)/$F$158 -> 1 | H158: =+SUM(H159,H162,H165)/$F$142 -> 0 | I158: =+SUM(I159,I162,I165)/$F$142 -> 0 | J158: =+SUM(J159,J162,J165)/$F$142 -> 0
D159: Nível I | F159: =+SUM(F160:F161) -> 1 | G159: =+SUM(G160:G161) -> 1 | H159: =+SUM(H160:H161) -> 0 | I159: =+SUM(I160:I161) -> 0 | J159: =+SUM(J160:J161) -> 0
D160: High Severity | F160: 1 | G160: =+F160-SUM(H160:J160) -> 1 | H160: 0 | I160: 0 | J160: 0
D161: Warning | F161: 0 | G161: =+F161-SUM(H161:J161) -> 0 | H161: 0 | I161: 0 | J161: 0
D162: Nível II | F162: =+SUM(F163:F164) -> 4 | G162: =+SUM(G163:G164) -> 4 | H162: =+SUM(H163:H164) -> 0 | I162: =+SUM(I163:I164) -> 0 | J162: =+SUM(J163:J164) -> 0
D163: High Severity | F163: 3 | G163: =+F163-SUM(H163:J163) -> 3 | H163: 0 | I163: 0 | J163: 0
D164: Warning | F164: 1 | G164: =+F164-SUM(H164:J164) -> 1 | H164: 0 | I164: 0 | J164: 0
...

Sheet 2. Status Detalhe Campos
B7: Stream | C7: Sub-stream | D7: Loan Tape/Output Table | E7: Data field | F7: Field Status | G7: Status Especificação | H7: Status Desenvolvimento | I7: Status Dry-run | J7: Status Atual | K7: Status Anterior | L7: Data entrega IT (real) | M7: Data conclusão | N7: Observações
B8: B02.00 | C8: Loan Tape | D8: lt002_instrument | E8: instrmnt_id | F8: Campo já existente no LT | G8: Concluído | H8: Concluído | J8: Com Incidências | K8: Com Incidências
B9: B02.00 | C9: Loan Tape | D9: lt002_instrument | E9: isin | F9: Campo já existente no LT | G9: Concluído | H9: Concluído | J9: Com Incidências | K9: Com Incidências
B10: B02.00 | C10: Loan Tape | D10: lt002_instrument | E10: orgnl_amnt_eur | F10: Campo novo no LT | G10: Concluído | H10: Concluído | J10: Concluído | K10: Concluído
B11: B02.00 | C11: Loan Tape | D11: lt002_instrument | E11: orgnl_amnt_fx | F11: Campo novo no LT | G11: Concluído | H11: Concluído | J11: Com Incidências | K11: Com Incidências
B12: B02.00 | C12: Loan Tape | D12: lt002_instrument | E12: crrncy_dnmntn | F12: Campo já existente no LT | G12: Concluído | H12: Concluído | J12: Concluído | K12: Concluído
B13: B02.00 | C13: Loan Tape | D13: lt005_instr_ent. | E13: otstndng_prncpl_amnt | F13: Campo novo no LT | G13: Concluído | H13: Não Concluído | J13: Pendente de desenvolv. | K13: Pendente de desenvolv.
B14: B02.00 | C14: Loan Tape | D14: lt005_instr_ent. | E14: prtn_amnt_rprtng_entty | F14: Campo novo no LT | G14: Concluído | H14: Não Concluído | J14: Pendente de desenvolv. | K14: Pendente de desenvolv.
B15: B02.00 | C15: Loan Tape | D15: lt002_instrument | E15: accrd_intrst_instrmnt | F15: Campo já existente no LT - Nova Especificação | G15: Concluído | H15: Não Concluído | J15: Em curso | K15: Em curso
B16: B02.00 | C16: Loan Tape | D16: lt005_instr_ent | E16: accrd_intrst_instrmnt | F16: Campo já existente no LT - Nova Especificação | G16: Concluído | H16: Não Concluído | J16: Em curso | K16: Em curso
B17: B02.00 | C17: Loan Tape | D17: lt002_instrument | E17: typ_instrmnt | F17: Campo já existente no LT | G17: Concluído | H17: Concluído | J17: Com Incidências | K17: Com Incidências
B18: B02.00 | C18: Loan Tape | D18: lt002_instrument | E18: rank_insolv | F18: Campo novo no LT | G18: Concluído | H18: Concluído | J18: Em curso | K18: Em curso
B19: B02.00 | C19: Loan Tape | D19: lt002_instrument | E19: dt_incptn | F19: Campo já existente no LT | G19: Concluído | H19: Concluído | J19: Concluído | K19: Concluído
... B35: B02.00 | C35: Loan Tape | D35: lt801_param_segm | E35: flag_inst_titulos | F35: Campo já existente no LT | G35: Concluído | H35: Concluído | J35: Em curso | K35: Em curso
B36: B02.00 | C36: Tabela Output | D36: out_b0200_main_liabilities | E36: 0010_row_nmbr | F36: Campo não LT (apenas tabela Output) | G36: Concluído | H36: =+VLOOKUP(B36&"_"&E36,'B02.00'!A:X,24,FALSE) -> Concluído | I36: Concluído sem ajuste | J36: Concluído | K36: Concluído
B37: B02.00 | C37: Tabela Output | D37: out_b0200_main_liabilities | E37: 0020_uniq_id | F37: Campo já existente no LT | G37: Concluído | H37: =+VLOOKUP(B37&"_"&E37,'B02.00'!A:X,24,FALSE) -> Concluído | I37: Concluído sem ajuste | J37: Com Incidências | K37: Com Incidências
B38: B02.00 | C38: Tabela Output | D38: out_b0200_main_liabilities | E38: 0030_uniq_id_knwn_cntrprty | F38: Campo já existente no LT | G38: Concluído | H38: =+VLOOKUP(B38&"_"&E38,'B02.00'!A:X,24,FALSE) -> Concluído | I38: Concluído sem ajuste | J38: Com Incidências | K38: Com Incidências
B39: B02.00 | C39: Tabela Output | D39: out_b0200_main_liabilities | E39: 0040_typ_uniq_id_knwn_cntrprty | F39: Campo não LT (apenas tabela Output) | G39: Concluído | H39: =+VLOOKUP(B39&"_"&E39,'B02.00'!A:X,24,FALSE) -> Concluído | I39: Concluído sem ajuste | J39: Concluído | K39: Concluído
B40: B02.00 | C40: Tabela Output | D40: out_b0200_main_liabilities | E40: 0050_orgnl_amnt_eur | F40: Campo novo no LT | G40: Concluído | H40: =+VLOOKUP(B40&"_"&E40,'B02.00'!A:X,24,FALSE) -> Concluído | I40: Concluído sem ajuste | J40: Concluído | K40: Concluído
B41: B02.00 | C41: Tabela Output | D41: out_b0200_main_liabilities | E41: 0060_orgnl_amnt_fx | F41: Campo novo no LT | G41: Concluído | H41: =+VLOOKUP(B41&"_"&E41,'B02.00'!A:X,24,FALSE) -> Concluído | I41: Concluído sem ajuste | J41: Com Incidências | K41: Com Incidências
B42: B02.00 | C42: Tabela Output | D42: out_b0200_main_liabilities | E42: 0070_cntrct_crrncy | F42: Campo já existente no LT | G42: Concluído | H42: =+VLOOKUP(B42&"_"&E42,'B02.00'!A:X,24,FALSE) -> Concluído | I42: Concluído sem ajuste | J42: Concluído | K42: Concluído
B43: B02.00 | C43: Tabela Output | D43: out_b0200_main_liabilities | E43: 0080_otstndng_prncpl_amnt | F43: Campo novo no LT | G43: Concluído | H43: =+VLOOKUP(B43&"_"&E43,'B02.00'!A:X,24,FALSE) -> Não Concluído | I43: Concluído com ajuste | J43: Pendente de desenvolv. | K43: Pendente de desenvolv.
B44: B02.00 | C44: Tabela Output | D44: out_b0200_main_liabilities | E44: 0090_prtn_amnt_rprtng_entty | F44: Campo novo no LT | G44: Concluído | H44: =+VLOOKUP(B44&"_"&E44,'B02.00'!A:X,24,FALSE) -> Não Concluído | I44: Concluído sem ajuste | J44: Pendente de desenvolv. | K44: Pendente de desenvolv.
B45: B02.00 | C45: Tabela Output | D45: out_b0200_main_liabilities | E45: 0100_accrd_intrst_instrmnt | F45: Campo já existente no LT - Nova Especificação | G45: Concluído | H45: =+VLOOKUP(B45&"_"&E45,'B02.00'!A:X,24,FALSE) -> Concluído | I45: Pendente de ajuste | J45: Em curso | K45: Em curso
B46: B02.00 | C46: Tabela Output | D46: out_b0200_main_liabilities | E46: 0110_applcbl_fees_charges | F46: Campo não LT (apenas tabela Output) | G46: Concluído | H46: =+VLOOKUP(B46&"_"&E46,'B02.00'!A:X,24,FALSE) -> Concluído | I46: Concluído sem ajuste | J46: Concluído | K46: Concluído
B47: B02.00 | C47: Tabela Output | D47: out_b0200_main_liabilities | E47: 0120_otstndng_amnt | F47: Campo não LT (apenas tabela Output) | G47: Concluído | H47: =+VLOOKUP(B47&"_"&E47,'B02.00'!A:X,24,FALSE) -> Não Concluído | I47: Pendente de ajuste | J47: Pendente de desenvolv. | K47: Pendente de desenvolv.
... B63: B02.00 | C63: Tabela Output | D63: out_b0200_main_liabilities | E63: 0250_strctrd_prdct | F63: Campo não LT (apenas tabela Output) | G63: Concluído | H63: =+VLOOKUP(B63&"_"&E63,'B02.00'!A:X,24,FALSE) -> Concluído | I63: Concluído sem ajuste | J63: Concluído | K63: Concluído
B64: B02.00 | C64: Tabela Output | D64: out_b0200_main_liabilities | E64: 0260_grntd_min_amnt_strctrd_prdc | F64: Campo não LT (apenas tabela Output) | G64: Concluído | H64: Concluído | I64: Concluído sem ajuste | J64: Concluído | K64: Concluído
B65: B02.00 | C65: Tabela Output | D65: out_b0200_main_liabilities | E65: 0270_fv_amnt_strctrd_prdct | F65: Campo não LT (apenas tabela Output) | G65: Concluído | H65: =+VLOOKUP(B65&"_"&E65,'B02.00'!A:X,24,FALSE) -> Concluído | I65: Concluído sem ajuste | J65: Concluído | K65: Concluído
B66: B02.00 | C66: Tabela Output | D66: out_b0200_main_liabilities | E66: 0280_flg_ncnp_dpsts | F66: Campo não LT (apenas tabela Output) | G66: Concluído | H66: =+VLOOKUP(B66&"_"&E66,'B02.00'!A:X,24,FALSE) -> Concluído | I66: Concluído sem ajuste | J66: Concluído | K66: Concluído
B67: B02.00 | C67: Tabela Output | D67: out_b0200_main_liabilities | E67: 0290_flg_ncbp_dpsts | F67: Campo não LT (apenas tabela Output) | G67: Concluído | H67: =+VLOOKUP(B67&"_"&E67,'B02.00'!A:X,24,FALSE) -> Concluído | I67: Concluído sem ajuste | J67: Concluído | K67: Concluído
B68: B02.00 | C68: Tabela Output | D68: out_b0200_main_liabilities | E68: 0300_amnt_cvrd_elgbl_dpsts | F68: Campo não LT (apenas tabela Output) | G68: Concluído | H68: =+VLOOKUP(B68&"_"&E68,'B02.00'!A:X,24,FALSE) -> Concluído | I68: Concluído sem ajuste | J68: Concluído | K68: Concluído
B69: B02.00 | C69: Tabela Output | D69: out_b0200_main_liabilities | E69: 0310_flg_clltrl_agrmnts | F69: Campo não LT (apenas tabela Output) | G69: Concluído | H69: =+VLOOKUP(B69&"_"&E69,'B02.00'!A:X,24,FALSE) -> Concluído | I69: Concluído sem ajuste | J69: Concluído | K69: Concluído
B70: B02.00 | C70: Tabela Output | D70: out_b0200_main_liabilities | E70: 0320_amnt_clltrl | F70: Campo não LT (apenas tabela Output) | G70: Concluído | H70: =+VLOOKUP(B70&"_"&E70,'B02.00'!A:X,24,FALSE) -> Concluído | I70: Concluído sem ajuste | J70: Concluído | K70: Concluído
B71: B02.00 | C71: Tabela Output | D71: out_b0200_main_liabilities | E71: 0330_amnt_unclltrlzd | F71: Campo não LT (apenas tabela Output) | G71: Concluído | H71: =+VLOOKUP(B71&"_"&E71,'B02.00'!A:X,24,FALSE) -> Concluído | I71: Concluído sem ajuste | J71: Concluído | K71: Concluído
B72: B02.00 | C72: Tabela Output | D72: out_b0200_main_liabilities | E72: 0340_id_clltrl | F72: Campo não LT (apenas tabela Output) | G72: Concluído | H72: =+VLOOKUP(B72&"_"&E72,'B02.00'!A:X,24,FALSE) -> Concluído | I72: Concluído sem ajuste | J72: Concluído | K72: Concluído
B73: B02.00 | C73: Tabela Output | D73: out_b0200_main_liabilities | E73: 0350_typ_clltrl | F73: Campo não LT (apenas tabela Output) | G73: Concluído | H73: =+VLOOKUP(B73&"_"&E73,'B02.00'!A:X,24,FALSE) -> Concluído | I73: Concluído sem ajuste | J73: Concluído | K73: Concluído
B74: B02.00 | C74: Tabela Output | D74: out_b0200_main_liabilities | E74: 0351_typ_clltrl_othr | F74: Campo não LT (apenas tabela Output) | G74: Concluído | H74: =+VLOOKUP(B74&"_"&E74,'B02.00'!A:X,24,FALSE) -> Concluído | I74: Concluído sem ajuste | J74: Concluído | K74: Concluído
B75: B02.00 | C75: Tabela Output | D75: out_b0200_main_liabilities | E75: 0360_trdng_mthd | F75: Em curso | G75: Não Concluído | H75: =+VLOOKUP(B75&"_"&E75,'B02.00'!A:X,24,FALSE) -> Não Concluído | I75: Concluído com ajuste | J75: Pendente de desenvolv. | K75: Pendente de desenvolv.
B76: B02.00 | C76: Tabela Output | D76: out_b0200_main_liabilities | E76: 0370_amnt_scrty_eur | F76: Campo novo no LT | G76: Concluído | H76: =+VLOOKUP(B76&"_"&E76,'B02.00'!A:X,24,FALSE) -> Concluído | I76: Concluído sem ajuste | J76: Concluído | K76: Concluído
... B116: B02.00 | C116: Tabela Output | D116: out_b0200_main_liabilities | E116: 5010_flg_art21_7a_srmr | F116: Campo não LT (apenas tabela Output) | G116: Concluído | H116: =+VLOOKUP(B116&"_"&E116,'B02.00'!A:X,24,FALSE) -> Concluído | I116: Concluído sem ajuste | J116: Concluído | K116: Concluído
B117: B05.00 | C117: Loan Tape | D117: lt006_instr_prot | E117: instrmnt_id | F117: Campo já existente no LT | G117: Concluído | H117: Concluído | J117: Por iniciar | K117: Por iniciar
B118: B05.00 | C118: Loan Tape | D118: lt006_instr_prot | E118: prtctn_allctd_vl | F118: Campo já existente no LT | G118: Concluído | H118: Concluído | J118: Por iniciar | K118: Por iniciar
B119: B05.00 | C119: Loan Tape | D119: lt004_protection | E119: flg_scrd | F119: Campo novo no LT | G119: Concluído | H119: Não Concluído | J119: Pendente de desenvolv. | K119: Pendente de desenvolv.
B120: B05.00 | C120: Loan Tape | D120: lt004_protection | E120: dt_mtrty_prtctn | F120: Em curso | G120: Não Concluído | H120: Não Concluído | J120: Pendente de desenvolv. | K120: Pendente de desenvolv.
B121: B05.00 | C121: Tabela Output | D121: out_b0500_guarantees | E121: 0010_row_nmbr | F121: Campo não LT (apenas tabela Output) | G121: Concluído | H121: Concluído | J121: Por iniciar | K121: Por iniciar
B122: B05.00 | C122: Tabela Output | D122: out_b0500_guarantees | E122: 0020_uniq_id_guarantee | F122: Campo já existente no LT | G122: Concluído | H122: Concluído | J122: Por iniciar | K122: Por iniciar
B123: B05.00 | C123: Tabela Output | D123: out_b0500_guarantees | E123: 0030_governing_law | F123: Campo não LT (apenas tabela Output) | G123: Concluído | H123: Concluído | J123: Por iniciar | K123: Por iniciar
B124: B05.00 | C124: Tabela Output | D124: out_b0500_guarantees | E124: 0040_flg_art12g_3_srmr | F124: Campo não LT (apenas tabela Output) | G124: Concluído | H124: Concluído | J124: Por iniciar | K124: Por iniciar
B125: B05.00 | C125: Tabela Output | D125: out_b0500_guarantees | E125: 0050_typ_guarantee | F125: Campo não LT (apenas tabela Output) | G125: Concluído | H125: Concluído | J125: Por iniciar | K125: Por iniciar
B126: B05.00 | C126: Tabela Output | D126: out_b0500_guarantees | E126: 0060_max_amnt_guarantee | F126: Campo já existente no LT | G126: Concluído | H126: Concluído | J126: Por iniciar | K126: Por iniciar
B127: B05.00 | C127: Tabela Output | D127: out_b0500_guarantees | E127: 0070_flg_scrd | F127: Campo novo no LT | G127: Concluído | H127: Não Concluído | J127: Pendente de desenvolv. | K127: Pendente de desenvolv.
B128: B05.00 | C128: Tabela Output | D128: out_b0500_guarantees | E128: 0080_amnt_clltrl | F128: Campo não LT (apenas tabela Output) | G128: Concluído | H128: Concluído | J128: Por iniciar | K128: Por iniciar
... B146: B90.00 | C146: Loan Tape | D146: lt006_instr_pro | E146: prtctn_allctd_vl | F146: Campo já existente no LT | G146: Concluído | H146: Concluído | J146: Em curso | K146: Em curso
B147: B90.00 | C147: Tabela Output | D147: out_b9000_counterparties | E147: 0010_row_nmbr | F147: Campo não LT (apenas tabela Output) | G147: Concluído | H147: Concluído | I147: Concluído sem ajuste | J147: Em curso | K147: Em curso
B148: B90.00 | C148: Tabela Output | D148: out_b9000_counterparties | E148: 0011_tab_origin | F148: Campo não LT (apenas tabela Output) | G148: Concluído | H148: Concluído | I148: Concluído sem ajuste | J148: Em curso | K148: Em curso
B149: B90.00 | C149: Tabela Output | D149: out_b9000_counterparties | E149: 0020_uniq_id_knwn_cntrprty | F149: Campo não LT (apenas tabela Output) | G149: Concluído | H149: Concluído | I149: Concluído sem ajuste | J149: Em curso | K149: Em curso
B150: B90.00 | C150: Tabela Output | D150: out_b9000_counterparties | E150: 0030_cntrprty_rsltn_grp | F150: Campo novo no LT | G150: Concluído | H150: Não Concluído | I150: Concluído com ajuste | J150: Pendente de desenvolv. | K150: Pendente de desenvolv.
B151: B90.00 | C151: Tabela Output | D151: out_b9000_counterparties | E151: 0040_cntrprty_nm | F151: Campo já existente no LT | G151: Concluído | H151: Não Concluído | I151: Concluído com ajuste | J151: Pendente de desenvolv. | K151: Pendente de desenvolv.
B152: B90.00 | C152: Tabela Output | D152: out_b9000_counterparties | E152: 0050_cntrprty_lei | F152: Campo já existente no LT | G152: Concluído | H152: Não Concluído | I152: Concluído com ajuste | J152: Pendente de desenvolv. | K152: Pendente de desenvolv.
B153: B90.00 | C153: Tabela Output | D153: out_b9000_counterparties | E153: 0060_typ_cntrprty_id | F153: Campo não LT (apenas tabela Output) | G153: Concluído | H153: Não Concluído | I153: Concluído com ajuste | J153: Pendente de desenvolv. | K153: Pendente de desenvolv.
B154: B90.00 | C154: Tabela Output | D154: out_b9000_counterparties | E154: 0070_cntrprty_id | F154: Campo já existente no LT | G154: Concluído | H154: Não Concluído | I154: Concluído sem ajuste | J154: Pendente de desenvolv. | K154: Pendente de desenvolv.
B155: B90.00 | C155: Tabela Output | D155: out_b9000_counterparties | E155: 0080_cntrprty_typ | F155: Por iniciar | G155: Não Concluído | H155: Não Concluído | I155: Concluído com ajuste | J155: Pendente de desenvolv. | K155: Pendente de desenvolv.
B156: B90.00 | C156: Tabela Output | D156: out_b9000_counterparties | E156: 0090_cntry_cntrprty | F156: Em curso | G156: Não Concluído | H156: Não Concluído | I156: Concluído com ajuste | J156: Pendente de desenvolv. | K156: Pendente de desenvolv.
B157: B90.00 | C157: Tabela Output | D157: out_b9000_counterparties | E157: 0100_rlvnt_amnt_wdc | F157: Campo não LT (apenas tabela Output) | G157: Concluído | H157: Não Concluído | I157: Pendente de ajuste | J157: Pendente de desenvolv. | K157: Pendente de desenvolv.
B158: B02.00 | C158: Controlos | D158: out_b0200_main_liabilities | E158: lvl1_h_0010_row_nmbr | F158: Não aplicável | G158: Não aplicável | H158: Não aplicável | J158: =+VLOOKUP(E158,Controlos!A:I,9,FALSE) -> Concluído | K158: Concluído
B159: B02.00 | C159: Controlos | D159: out_b0200_main_liabilities | E159: lvl1_h_0030_uniq_id_knwn_cntrprty | F159: Não aplicável | G159: Não aplicável | H159: Não aplicável | J159: =+VLOOKUP(E159,Controlos!A:I,9,FALSE) -> Por iniciar | K159: Por iniciar
B160: B02.00 | C160: Controlos | D160: out_b0200_main_liabilities | E160: lvl1_h_0040_typ_uniq_id_knwn_cntrprty | F160: Não aplicável | G160: Não aplicável | H160: Não aplicável | J160: =+VLOOKUP(E160,Controlos!A:I,9,FALSE) -> Concluído | K160: Concluído
B161: B02.00 | C161: Controlos | D161: out_b0200_main_liabilities | E161: lvl1_h_0070_cntrct_crrncy | F161: Não aplicável | G161: Não aplicável | H161: Não aplicável | J161: =+VLOOKUP(E161,Controlos!A:I,9,FALSE) -> Concluído | K161: Concluído
B162: B02.00 | C162: Controlos | D162: out_b0200_main_liabilities | E162: lvl1_h_0080_otstndng_prncpl_amnt | F162: Não aplicável | G162: Não aplicável | H162: Não aplicável | J162: =+VLOOKUP(E162,Controlos!A:I,9,FALSE) -> Pendente de desenvolv. | K162: Pendente de desenvolv.
B163: B02.00 | C163: Controlos | D163: out_b0200_main_liabilities | E163: lvl1_w_0080_otstndng_prncpl_amnt | F163: Não aplicável | G163: Não aplicável | H163: Não aplicável | J163: =+VLOOKUP(E163,Controlos!A:I,9,FALSE) -> Pendente de desenvolv. | K163: Pendente de desenvolv.
B164: B02.00 | C164: Controlos | D164: out_b0200_main_liabilities | E164: lvl1_h_0090_prtn_amnt_rprtng_entty | F164: Não aplicável | G164: Não aplicável | H164: Não aplicável | J164: =+VLOOKUP(E164,Controlos!A:I,9,FALSE) -> Pendente de desenvolv. | K164: Pendente de desenvolv.
B165: B02.00 | C165: Controlos | D165: out_b0200_main_liabilities | E165: lvl1_h_0100_accrd_intrst_instrmnt | F165: Não aplicável | G165: Não aplicável | H165: Não aplicável | J165: =+VLOOKUP(E165,Controlos!A:I,9,FALSE) -> Por iniciar | K165: Por iniciar
B166: B02.00 | C166: Controlos | D166: out_b0200_main_liabilities | E166: lvl1_w_0100_accrd_intrst_instrmnt | F166: Não aplicável | G166: Não aplicável | H166: Não aplicável | J166: =+VLOOKUP(E166,Controlos!A:I,9,FALSE) -> Por iniciar | K166: Por iniciar
B167: B02.00 | C167: Controlos | D167: out_b0200_main_liabilities | E167: lvl1_h_0120_otstndng_amnt | F167: Não aplicável | G167: Não aplicável | H167: Não aplicável | J167: =+VLOOKUP(E167,Controlos!A:I,9,FALSE) -> Pendente de desenvolv. | K167: Pendente de desenvolv.
B168: B02.00 | C168: Controlos | D168: out_b0200_main_liabilities | E168: lvl1_w_0120_otstndng_amnt | F168: Não aplicável | G168: Não aplicável | H168: Não aplicável | J168: =+VLOOKUP(E168,Controlos!A:I,9,FALSE) -> Pendente de desenvolv. | K168: Pendente de desenvolv.
B169: B02.00 | C169: Controlos | D169: out_b0200_main_liabilities | E169: lvl1_h_0130_rlvnt_amnt_wdc | F169: Não aplicável | G169: Não aplicável | H169: Não aplicável | J169: =+VLOOKUP(E169,Controlos!A:I,9,FALSE) -> Pendente de desenvolv. | K169: Pendente de desenvolv.
... B206: B02.00 | C206: Controlos | D206: out_b0200_main_liabilities | E206: lvl2_h_0160_rank_insolv | F206: Não aplicável | G206: Não aplicável | H206: Não aplicável | J206: =+VLOOKUP(E206,Controlos!A:I,9,FALSE) -> Concluído | K206: Concluído
A207: x | B207: B02.00 | C207: Controlos | D207: out_b0200_main_liabilities | E207: lvl2_h_0170_dt_incptn | F207: Não aplicável | G207: Não aplicável | H207: Não aplicável | J207: =+VLOOKUP(E207,Controlos!A:I,9,FALSE) -> Concluído | K207: Por iniciar
A208: x | B208: B02.00 | C208: Controlos | D208: out_b0200_main_liabilities | E208: lvl2_h_0170_dt_incptn | F208: Não aplicável | G208: Não aplicável | H208: Não aplicável | J208: =+VLOOKUP(E208,Controlos!A:I,9,FALSE) -> Concluído | K208: Por iniciar
B209: B02.00 | C209: Controlos | D209: out_b0200_main_liabilities | E209: lvl2_h_0180_dt_nxt_intrst_pymnt | F209: Não aplicável | G209: Não aplicável | H209: Não aplicável | J209: =+VLOOKUP(E209,Controlos!A:I,9,FALSE) -> Por iniciar | K209: Por iniciar
B210: B02.00 | C210: Controlos | D210: out_b0200_main_liabilities | E210: lvl2_h_0200_dt_erlst_rdmptn | F210: Não aplicável | G210: Não aplicável | H210: Não aplicável | J210: =+VLOOKUP(E210,Controlos!A:I,9,FALSE) -> Concluído | K210: Concluído
B211: B02.00 | C211: Controlos | D211: out_b0200_main_liabilities | E211: lvl2_h_0210_dt_lgl_fnl_mtrty | F211: Não aplicável | G211: Não aplicável | H211: Não aplicável | J211: =+VLOOKUP(E211,Controlos!A:I,9,FALSE) -> Concluído | K211: Por iniciar
B212: B02.00 | C212: Controlos | D212: out_b0200_main_liabilities | E212: lvl2_h_0220_governing_law | F212: Não aplicável | G212: Não aplicável | H212: Não aplicável | J212: =+VLOOKUP(E212,Controlos!A:I,9,FALSE) -> Concluído | K212: Concluído
B213: B02.00 | C213: Controlos | D213: out_b0200_main_liabilities | E213: lvl2_h_0230_bail_in_rcgntn_cls | F213: Não aplicável | G213: Não aplicável | H213: Não aplicável | J213: =+VLOOKUP(E213,Controlos!A:I,9,FALSE) -> Concluído | K213: Concluído
B214: B02.00 | C214: Controlos | D214: out_b0200_main_liabilities | E214: lvl2_h_0250_strctrd_prdct | F214: Não aplicável | G214: Não aplicável | H214: Não aplicável | J214: =+VLOOKUP(E214,Controlos!A:I,9,FALSE) -> Concluído | K214: Concluído
B215: B02.00 | C215: Controlos | D215: out_b0200_main_liabilities | E215: lvl2_h_0310_flg_clltrl_agrmnts | F215: Não aplicável | G215: Não aplicável | H215: Não aplicável | J215: =+VLOOKUP(E215,Controlos!A:I,9,FALSE) -> Pendente de desenvolv. | K215: Concluído
B216: B02.00 | C216: Controlos | D216: out_b0200_main_liabilities | E216: lvl2_h_0330_amnt_unclltrlzd | F216: Não aplicável | G216: Não aplicável | H216: Não aplicável | J216: =+VLOOKUP(E216,Controlos!A:I,9,FALSE) -> Concluído | K216: Concluído
B217: B02.00 | C217: Controlos | D217: out_b0200_main_liabilities | E217: lvl2_h_0330_amnt_unclltrlzd | F217: Não aplicável | G217: Não aplicável | H217: Não aplicável | J217: =+VLOOKUP(E217,Controlos!A:I,9,FALSE) -> Concluído | K217: Concluído
B218: B02.00 | C218: Controlos | D218: out_b0200_main_liabilities | E218: lvl2_h_0350_typ_clltrl | F218: Não aplicável | G218: Não aplicável | H218: Não aplicável | J218: =+VLOOKUP(E218,Controlos!A:I,9,FALSE) -> Concluído | K218: Concluído
B219: B02.00 | C219: Controlos | D219: out_b0200_main_liabilities | E219: lvl2_h_0350_typ_clltrl | F219: Não aplicável | G219: Não aplicável | H219: Não aplicável | J219: =+VLOOKUP(E219,Controlos!A:I,9,FALSE) -> Concluído | K219: Concluído
B220: B02.00 | C220: Controlos | D220: out_b0200_main_liabilities | E220: lvl2_h_0440_ntr_glbl_nt | F220: Não aplicável | G220: Não aplicável | H220: Não aplicável | J220: =+VLOOKUP(E220,Controlos!A:I,9,FALSE) -> Concluído | K220: Concluído
... B313: B02.00 | C313: Controlos | D313: out_b0200_main_liabilities | E313: LVL2_H_0210_dt_lgl_fnl_mtrty | F313: Não aplicável | G313: Não aplicável | H313: Não aplicável | J313: =+VLOOKUP(E313,Controlos!A:I,9,FALSE) -> Concluído | K313: Por iniciar

Sheet Aux
B7: Field Status
B9: Campo já existente no LT
B10: Campo já existente no LT - Nova Especificação
B11: Campo novo no LT
B12: Campo via Holístico
B13: Campo não LT (apenas tabela Output)
B14: Não aplicável
B15: Em curso
B17: Status Especificação/Desenvolvimento
B18: Em curso
B19: Concluído
B20: Não aplicável
... B36: Não aplicável

Sheet 3. Status Testes
A1: wvg
I6: 1. Status dos Testes
I8: Âmbito | J8: Bail-In
B9: Auxiliar
B10: Coerência | C10: Validade | D10: Caracteres Especiais | E10: Missings | F10: Not applicable | G10: Min/Max | I10: Tabela | J10: Campo | K10: Status especificação | L10: Status desenvolvimento | M10: Testes Corridos (#) | N10: Data de Referência | O10: Número de Registos ID1. (#) | P10: ID Exec. 1. | Q10: 1. Erros de Coerência (#) | R10: Número de Registos ID2&9 (#) | S10: ID Exec. 2 | T10: 2. Erros de Valores Admitidos (#) | U10: ID Exec. 3. | V10: 3. Erros de Caract. Especiais (#) | W10: ID Exec. 4. | X10: 4. Registos com Missing (#) | Y10: % de Missings | Z10: ID Exec. 5. | AA10: 5. Registos com N/A (#) | AB10: % de N/A | AC10: 6. Valor Mínimo | AD10: 7. Valor Máximo | AE10: 8. Controlos Regulamentares (#) | AF10: 9. Controlos de Formatos (#) | AG10: Comentário | AH10: Status
A11: =+I11&J11 -> B02.000010_ROW_NMBR | B11: =+VLOOKUP(I11&J11,[1]Auxiliar!B:C,2,FALSE) -> 2 | C11: =+VLOOKUP(I11&J11,[1]Auxiliar!E:F,2,FALSE) -> 2 | D11: =+VLOOKUP(I11&J11,[1]Auxiliar!H:I,2,FALSE) -> 2 | E11: =+VLOOKUP(I11&J11,[1]Auxiliar!K:L,2,FALSE) -> 2 | F11: =+VLOOKUP(I11&J11,[1]Auxiliar!N:O,2,FALSE) -> 2 | G11: =+VLOOKUP(I11&J11,[1]Auxiliar!Q:R,2,FALSE) -> 2 | H11: =+"c"&LEFT(J11,4) -> c0010 | I11: B02.00 | J11: 0010_ROW_NMBR | L11: =+VLOOKUP(J11,#REF!,3,FALSE) -> #REF! | N11: 2025-10-31 | O11: 8 | P11: =+IFERROR(VLOOKUP(B11,'[1]ID1&5'!K:L,2,FALSE),"-") -> - | Q11: 0 | R11: =+IFERROR(VLOOKUP(CONCATENATE(A11,$C$10,C11),'[1]ID1&5'!B:J,8,FALSE),"-") -> - | S11: =+IFERROR(VLOOKUP(C11,'[1]ID1&5'!K:L,2,FALSE),"-") -> - | T11: 0 | U11: =+IFERROR(VLOOKUP(D11,'[1]ID1&5'!K:L,2,FALSE),"-") -> - | V11: 0 | W11: =+IFERROR(VLOOKUP(E11,'[1]ID1&5'!K:L,2,FALSE),"-") -> - | X11: 0 | Y11: =+X11/O11 -> 0 | Z11: =+IFERROR(VLOOKUP(F11,'[1]ID1&5'!K:L,2,FALSE),"-") -> - | AA11: 0 | AB11: =+AA11/O11 -> 0 | AC11: 1 | AD11: 8 | AE11: 0 | AF11: 0 | AH11: OK | AI11: Concluído
A12: =+I12&J12 -> B02.000020_UNIQ_ID | B12: =+VLOOKUP(I12&J12,[1]Auxiliar!B:C,2,FALSE) -> 2 | C12: =+VLOOKUP(I12&J12,[1]Auxiliar!E:F,2,FALSE) -> 2 | D12: =+VLOOKUP(I12&J12,[1]Auxiliar!H:I,2,FALSE) -> 2 | E12: =+VLOOKUP(I12&J12,[1]Auxiliar!K:L,2,FALSE) -> 2 | F12: =+VLOOKUP(I12&J12,[1]Auxiliar!N:O,2,FALSE) -> 2 | G12: =+VLOOKUP(I12&J12,[1]Auxiliar!Q:R,2,FALSE) -> 2 | H12: =+"c"&LEFT(J12,4) -> c0020 | I12: B02.00 | J12: 0020_UNIQ_ID | L12: =+VLOOKUP(J12,#REF!,3,FALSE) -> #REF! | N12: 2025-10-31 | O12: 8 | P12: =+IFERROR(VLOOKUP(B12,'[1]ID1&5'!K:L,2,FALSE),"-") -> - | Q12: 0 | R12: =+IFERROR(VLOOKUP(CONCATENATE(A12,$C$10,C12),'[1]ID1&5'!B:J,8,FALSE),"-") -> - | S12: =+IFERROR(VLOOKUP(C12,'[1]ID1&5'!K:L,2,FALSE),"-") -> - | T12: 0 | U12: =+IFERROR(VLOOKUP(D12,'[1]ID1&5'!K:L,2,FALSE),"-") -> - | V12: 0 | W12: =+IFERROR(VLOOKUP(E12,'[1]ID1&5'!K:L,2,FALSE),"-") -> - | X12: 0 | Y12: =+X12/O12 -> 0 | Z12: =+IFERROR(VLOOKUP(F12,'[1]ID1&5'!K:L,2,FALSE),"-") -> - | AA12: 0 | AB12: =+AA12/O12 -> 0 | AC12: 31641600000000000PTBSREOM0028000 | AD12: 31641600005800007PTSTOCOM0007000 | AE12: 0 | AF12: 0 | AH12: OK | AI12: Com Incidências
A13: =+I13&J13 -> B02.000030_UNIQ_ID_KNWN_CNTRPRTY | B13: =+VLOOKUP(I13&J13,[1]Auxiliar!B:C,2,FALSE) -> 2 | C13: =+VLOOKUP(I13&J13,[1]Auxiliar!E:F,2,FALSE) -> 2 | D13: =+VLOOKUP(I13&J13,[1]Auxiliar!H:I,2,FALSE) -> 2 | E13: =+VLOOKUP(I13&J13,[1]Auxiliar!K:L,2,FALSE) -> 2 | F13: =+VLOOKUP(I13&J13,[1]Auxiliar!N:O,2,FALSE) -> 2 | G13: =+VLOOKUP(I13&J13,[1]Auxiliar!Q:R,2,FALSE) -> 2 | H13: =+"c"&LEFT(J13,4) -> c0030 | I13: B02.00 | J13: 0030_UNIQ_ID_KNWN_CNTRPRTY | L13: =+VLOOKUP(J13,#REF!,3,FALSE) -> #REF! | N13: 2025-10-31 | O13: 8 | P13: =+IFERROR(VLOOKUP(B13,'[1]ID1&5'!K:L,2,FALSE),"-") -> - | Q13: 0 | R13: =+IFERROR(VLOOKUP(CONCATENATE(A13,$C$10,C13),'[1]ID1&5'!B:J,8,FALSE),"-") -> - | S13: =+IFERROR(VLOOKUP(C13,'[1]ID1&5'!K:L,2,FALSE),"-") -> - | T13: 0 | U13: =+IFERROR(VLOOKUP(D13,'[1]ID1&5'!K:L,2,FALSE),"-") -> - | V13: 0 | W13: =+IFERROR(VLOOKUP(E13,'[1]ID1&5'!K:L,2,FALSE),"-") -> - | X13: 0 | Y13: =+X13/O13 -> 0 | Z13: =+IFERROR(VLOOKUP(F13,'[1]ID1&5'!K:L,2,FALSE),"-") -> - | AA13: 0 | AB13: =+AA13/O13 -> 0 | AC13: PTBSRDOM0037 | AD13: PTSTOHOM0002 | AE13: 0 | AF13: 0 | AH13: OK | AI13: Com Incidências
A14: =+I14&J14 -> B02.000040_TYP_UNIQ_ID_KNWN_CNTRPRTY | B14: =+VLOOKUP(I14&J14,[1]Auxiliar!B:C,2,FALSE) -> 2 | C14: =+VLOOKUP(I14&J14,[1]Auxiliar!E:F,2,FALSE) -> 2 | D14: =+VLOOKUP(I14&J14,[1]Auxiliar!H:I,2,FALSE) -> 2 | E14: =+VLOOKUP(I14&J14,[1]Auxiliar!K:L,2,FALSE) -> 2 | F14: =+VLOOKUP(I14&J14,[1]Auxiliar!N:O,2,FALSE) -> 2 | G14: =+VLOOKUP(I14&J14,[1]Auxiliar!Q:R,2,FALSE) -> 2 | H14: =+"c"&LEFT(J14,4) -> c0040 | I14: B02.00 | J14: 0040_TYP_UNIQ_ID_KNWN_CNTRPRTY | L14: =+VLOOKUP(J14,#REF!,3,FALSE) -> #REF! | N14: 2025-10-31 | O14: 8 | P14: =+IFERROR(VLOOKUP(B14,'[1]ID1&5'!K:L,2,FALSE),"-") -> - | Q14: 0 | R14: =+IFERROR(VLOOKUP(CONCATENATE(A14,$C$10,C14),'[1]ID1&5'!B:J,8,FALSE),"-") -> - | S14: =+IFERROR(VLOOKUP(C14,'[1]ID1&5'!K:L,2,FALSE),"-") -> - | T14: 0 | U14: =+IFERROR(VLOOKUP(D14,'[1]ID1&5'!K:L,2,FALSE),"-") -> - | V14: 0 | W14: =+IFERROR(VLOOKUP(E14,'[1]ID1&5'!K:L,2,FALSE),"-") -> - | X14: 0 | Y14: =+X14/O14 -> 0 | Z14: =+IFERROR(VLOOKUP(F14,'[1]ID1&5'!K:L,2,FALSE),"-") -> - | AA14: 0 | AB14: =+AA14/O14 -> 0 | AC14: ISIN | AD14: ISIN | AE14: 0 | AF14: 0 | AH14: OK | AI14: Concluído
A15: =+I15&J15 -> B02.000050_ORGNL_AMNT_EUR | B15: =+VLOOKUP(I15&J15,[1]Auxiliar!B:C,2,FALSE) -> 2 | C15: =+VLOOKUP(I15&J15,[1]Auxiliar!E:F,2,FALSE) -> 2 | D15: =+VLOOKUP(I15&J15,[1]Auxiliar!H:I,2,FALSE) -> 2 | E15: =+VLOOKUP(I15&J15,[1]Auxiliar!K:L,2,FALSE) -> 2 | F15: =+VLOOKUP(I15&J15,[1]Auxiliar!N:O,2,FALSE) -> 2 | G15: =+VLOOKUP(I15&J15,[1]Auxiliar!Q:R,2,FALSE) -> 2 | H15: =+"c"&LEFT(J15,4) -> c0050 | I15: B02.00 | J15: 0050_ORGNL_AMNT_EUR | L15: =+VLOOKUP(J15,#REF!,3,FALSE) -> #REF! | N15: 2025-10-31 | O15: 8 | P15: =+IFERROR(VLOOKUP(B15,'[1]ID1&5'!K:L,2,FALSE),"-") -> - | Q15: 0 | R15: =+IFERROR(VLOOKUP(CONCATENATE(A15,$C$10,C15),'[1]ID1&5'!B:J,8,FALSE),"-") -> - | S15: =+IFERROR(VLOOKUP(C15,'[1]ID1&5'!K:L,2,FALSE),"-") -> - | T15: 0 | U15: =+IFERROR(VLOOKUP(D15,'[1]ID1&5'!K:L,2,FALSE),"-") -> - | V15: 0 | W15: =+IFERROR(VLOOKUP(E15,'[1]ID1&5'!K:L,2,FALSE),"-") -> - | X15: 0 | Y15: =+X15/O15 -> 0 | Z15: =+IFERROR(VLOOKUP(F15,'[1]ID1&5'!K:L,2,FALSE),"-") -> - | AA15: 0 | AB15: =+AA15/O15 -> 0 | AC15: 7599000.00 | AD15: 1391779674.00 | AE15: 0 | AF15: 0 | AH15: OK | AI15: Concluído
A16: =+I16&J16 -> B02.000060_ORGNL_AMNT_FX | B16: =+VLOOKUP(I16&J16,[1]Auxiliar!B:C,2,FALSE) -> 2 | C16: =+VLOOKUP(I16&J16,[1]Auxiliar!E:F,2,FALSE) -> 2 | D16: =+VLOOKUP(I16&J16,[1]Auxiliar!H:I,2,FALSE) -> 2 | E16: =+VLOOKUP(I16&J16,[1]Auxiliar!K:L,2,FALSE) -> 2 | F16: =+VLOOKUP(I16&J16,[1]Auxiliar!N:O,2,FALSE) -> 2 | G16: =+VLOOKUP(I16&J16,[1]Auxiliar!Q:R,2,FALSE) -> 2 | H16: =+"c"&LEFT(J16,4) -> c0060 | I16: B02.00 | J16: 0060_ORGNL_AMNT_FX | L16: =+VLOOKUP(J16,#REF!,3,FALSE) -> #REF! | N16: 2025-10-31 | O16: 8 | P16: =+IFERROR(VLOOKUP(B16,'[1]ID1&5'!K:L,2,FALSE),"-") -> - | Q16: 0 | R16: =+IFERROR(VLOOKUP(CONCATENATE(A16,$C$10,C16),'[1]ID1&5'!B:J,8,FALSE),"-") -> - | S16: =+IFERROR(VLOOKUP(C16,'[1]ID1&5'!K:L,2,FALSE),"-") -> - | T16: 0 | U16: =+IFERROR(VLOOKUP(D16,'[1]ID1&5'!K:L,2,FALSE),"-") -> - | V16: 0 | W16: =+IFERROR(VLOOKUP(E16,'[1]ID1&5'!K:L,2,FALSE),"-") -> - | X16: 0 | Y16: =+X16/O16 -> 0 | Z16: =+IFERROR(VLOOKUP(F16,'[1]ID1&5'!K:L,2,FALSE),"-") -> - | AA16: 8 | AB16: =+AA16/O16 -> 1 | AC16: 999999999999999.00 | AD16: 999999999999999.00 | AE16: 0 | AF16: 0 | AG16: Comentário 14/11 - Todos os registos estão classificador como não aplicável pois o campo refere-se ao montante em moeda estrangeira. | AH16: OK | AI16: Com Incidências
A17: =+I17&J17 -> B02.000070_CNTRCT_CRRNCY | B17: =+VLOOKUP(I17&J17,[1]Auxiliar!B:C,2,FALSE) -> 2 | C17: =+VLOOKUP(I17&J17,[1]Auxiliar!E:F,2,FALSE) -> 2 | D17: =+VLOOKUP(I17&J17,[1]Auxiliar!H:I,2,FALSE) -> 2 | E17: =+VLOOKUP(I17&J17,[1]Auxiliar!K:L,2,FALSE) -> 2 | F17: =+VLOOKUP(I17&J17,[1]Auxiliar!N:O,2,FALSE) -> 2 | G17: =+VLOOKUP(I17&J17,[1]Auxiliar!Q:R,2,FALSE) -> 2 | H17: =+"c"&LEFT(J17,4) -> c0070 | I17: B02.00 | J17: 0070_CNTRCT_CRRNCY | L17: =+VLOOKUP(J17,#REF!,3,FALSE) -> #REF! | N17: 2025-10-31 | O17: 8 | P17: =+IFERROR(VLOOKUP(B17,'[1]ID1&5'!K:L,2,FALSE),"-") -> - | Q17: 0 | R17: =+IFERROR(VLOOKUP(CONCATENATE(A17,$C$10,C17),'[1]ID1&5'!B:J,8,FALSE),"-") -> - | S17: =+IFERROR(VLOOKUP(C17,'[1]ID1&5'!K:L,2,FALSE),"-") -> - | T17: 0 | U17: =+IFERROR(VLOOKUP(D17,'[1]ID1&5'!K:L,2,FALSE),"-") -> - | V17: 0 | W17: =+IFERROR(VLOOKUP(E17,'[1]ID1&5'!K:L,2,FALSE),"-") -> - | X17: 0 | Y17: =+X17/O17 -> 0 | Z17: =+IFERROR(VLOOKUP(F17,'[1]ID1&5'!K:L,2,FALSE),"-") -> - | AA17: 0 | AB17: =+AA17/O17 -> 0 | AC17: EUR | AD17: EUR | AE17: 0 | AF17: 0 | AH17: OK | AI17: Concluído
A18: =+I18&J18 -> B02.000080_OTSTNDNG_PRNCPL_AMNT | B18: =+VLOOKUP(I18&J18,[1]Auxiliar!B:C,2,FALSE) -> 2 | C18: =+VLOOKUP(I18&J18,[1]Auxiliar!E:F,2,FALSE) -> 2 | D18: =+VLOOKUP(I18&J18,[1]Auxiliar!H:I,2,FALSE) -> 2 | E18: =+VLOOKUP(I18&J18,[1]Auxiliar!K:L,2,FALSE) -> 2 | F18: =+VLOOKUP(I18&J18,[1]Auxiliar!N:O,2,FALSE) -> 2 | G18: =+VLOOKUP(I18&J18,[1]Auxiliar!Q:R,2,FALSE) -> 2 | H18: =+"c"&LEFT(J18,4) -> c0080 | I18: B02.00 | J18: 0080_OTSTNDNG_PRNCPL_AMNT | L18: =+VLOOKUP(J18,#REF!,3,FALSE) -> #REF! | N18: 2025-10-31 | O18: 8 | P18: =+IFERROR(VLOOKUP(B18,'[1]ID1&5'!K:L,2,FALSE),"-") -> - | Q18: 8 | R18: =+IFERROR(VLOOKUP(CONCATENATE(A18,$C$10,C18),'[1]ID1&5'!B:J,8,FALSE),"-") -> - | S18: =+IFERROR(VLOOKUP(C18,'[1]ID1&5'!K:L,2,FALSE),"-") -> - | T18: 0 | U18: =+IFERROR(VLOOKUP(D18,'[1]ID1&5'!K:L,2,FALSE),"-") -> - | V18: 0 | W18: =+IFERROR(VLOOKUP(E18,'[1]ID1&5'!K:L,2,FALSE),"-") -> - | X18: 0 | Y18: =+X18/O18 -> 0 | Z18: =+IFERROR(VLOOKUP(F18,'[1]ID1&5'!K:L,2,FALSE),"-") -> - | AA18: 0 | AB18: =+AA18/O18 -> 0 | AC18: 7599000.00 | AD18: 1385452938.00 | AE18: 0 | AF18: 0 | AH18: OK | AI18: Pendente de desenvolv.
A19: =+I19&J19 -> B02.000090_PRTN_AMNT_RPRTNG_ENTTY | B19: =+VLOOKUP(I19&J19,[1]Auxiliar!B:C,2,FALSE) -> 2 | C19: =+VLOOKUP(I19&J19,[1]Auxiliar!E:F,2,FALSE) -> 2 | D19: =+VLOOKUP(I19&J19,[1]Auxiliar!H:I,2,FALSE) -> 2 | E19: =+VLOOKUP(I19&J19,[1]Auxiliar!K:L,2,FALSE) -> 2 | F19: =+VLOOKUP(I19&J19,[1]Auxiliar!N:O,2,FALSE) -> 2 | G19: =+VLOOKUP(I19&J19,[1]Auxiliar!Q:R,2,FALSE) -> 2 | H19: =+"c"&LEFT(J19,4) -> c0090 | I19: B02.00 | J19: 0090_PRTN_AMNT_RPRTNG_ENTTY | L19: =+VLOOKUP(J19,#REF!,3,FALSE) -> #REF! | N19: 2025-10-31 | O19: 8 | P19: =+IFERROR(VLOOKUP(B19,'[1]ID1&5'!K:L,2,FALSE),"-") -> - | Q19: 8 | R19: =+IFERROR(VLOOKUP(CONCATENATE(A19,$C$10,C19),'[1]ID1&5'!B:J,8,FALSE),"-") -> - | S19: =+IFERROR(VLOOKUP(C19,'[1]ID1&5'!K:L,2,FALSE),"-") -> - | T19: 0 | U19: =+IFERROR(VLOOKUP(D19,'[1]ID1&5'!K:L,2,FALSE),"-") -> - | V19: 0 | W19: =+IFERROR(VLOOKUP(E19,'[1]ID1&5'!K:L,2,FALSE),"-") -> - | X19: 0 | Y19: =+X19/O19 -> 0 | Z19: =+IFERROR(VLOOKUP(F19,'[1]ID1&5'!K:L,2,FALSE),"-") -> - | AA19: 0 | AB19: =+AA19/O19 -> 0 | AC19: 0.00 | AD19: 6326736.00 | AE19: 0 | AF19: 0 | AH19: OK | AI19: Pendente de desenvolv.
A20: =+I20&J20 -> B02.000100_ACCRD_INTRST_INSTRMNT | B20: =+VLOOKUP(I20&J20,[1]Auxiliar!B:C,2,FALSE) -> 2 | C20: =+VLOOKUP(I20&J20,[1]Auxiliar!E:F,2,FALSE) -> 2 | D20: =+VLOOKUP(I20&J20,[1]Auxiliar!H:I,2,FALSE) -> 2 | E20: =+VLOOKUP(I20&J20,[1]Auxiliar!K:L,2,FALSE) -> 2 | F20: =+VLOOKUP(I20&J20,[1]Auxiliar!N:O,2,FALSE) -> 2 | G20: =+VLOOKUP(I20&J20,[1]Auxiliar!Q:R,2,FALSE) -> 2 | H20: =+"c"&LEFT(J20,4) -> c0100 | I20: B02.00 | J20: 0100_ACCRD_INTRST_INSTRMNT | L20: =+VLOOKUP(J20,#REF!,3,FALSE) -> #REF! | N20: 2025-10-31 | O20: 8 | P20: =+IFERROR(VLOOKUP(B20,'[1]ID1&5'!K:L,2,FALSE),"-") -> - | Q20: 4 | R20: =+IFERROR(VLOOKUP(CONCATENATE(A20,$C$10,C20),'[1]ID1&5'!B:J,8,FALSE),"-") -> - | S20: =+IFERROR(VLOOKUP(C20,'[1]ID1&5'!K:L,2,FALSE),"-") -> - | T20: 0 | U20: =+IFERROR(VLOOKUP(D20,'[1]ID1&5'!K:L,2,FALSE),"-") -> - | V20: 0 | W20: =+IFERROR(VLOOKUP(E20,'[1]ID1&5'!K:L,2,FALSE),"-") -> - | X20: 0 | Y20: =+X20/O20 -> 0 | Z20: =+IFERROR(VLOOKUP(F20,'[1]ID1&5'!K:L,2,FALSE),"-") -> - | AA20: 0 | AB20: =+AA20/O20 -> 0 | AC20: 0.00 | AD20: 7640186.30 | AE20: 0 | AF20: 0 | AH20: OK | AI20: Em curso
A21: =+I21&J21 -> B02.000110_APPLCBL_FEES_CHARGES | B21: =+VLOOKUP(I21&J21,[1]Auxiliar!B:C,2,FALSE) -> 2 | C21: =+VLOOKUP(I21&J21,[1]Auxiliar!E:F,2,FALSE) -> 2 | D21: =+VLOOKUP(I21&J21,[1]Auxiliar!H:I,2,FALSE) -> 2 | E21: =+VLOOKUP(I21&J21,[1]Auxiliar!K:L,2,FALSE) -> 2 | F21: =+VLOOKUP(I21&J21,[1]Auxiliar!N:O,2,FALSE) -> 2 | G21: =+VLOOKUP(I21&J21,[1]Auxiliar!Q:R,2,FALSE) -> 2 | H21: =+"c"&LEFT(J21,4) -> c0110 | I21: B02.00 | J21: 0110_APPLCBL_FEES_CHARGES | L21: =+VLOOKUP(J21,#REF!,3,FALSE) -> #REF! | N21: 2025-10-31 | O21: 8 | P21: =+IFERROR(VLOOKUP(B21,'[1]ID1&5'!K:L,2,FALSE),"-") -> - | Q21: 0 | R21: =+IFERROR(VLOOKUP(CONCATENATE(A21,$C$10,C21),'[1]ID1&5'!B:J,8,FALSE),"-") -> - | S21: =+IFERROR(VLOOKUP(C21,'[1]ID1&5'!K:L,2,FALSE),"-") -> - | T21: 0 | U21: =+IFERROR(VLOOKUP(D21,'[1]ID1&5'!K:L,2,FALSE),"-") -> - | V21: 0 | W21: =+IFERROR(VLOOKUP(E21,'[1]ID1&5'!K:L,2,FALSE),"-") -> - | X21: 0 | Y21: =+X21/O21 -> 0 | Z21: =+IFERROR(VLOOKUP(F21,'[1]ID1&5'!K:L,2,FALSE),"-") -> - | AA21: 0 | AB21: =+AA21/O21 -> 0 | AC21: 0.00 | AD21: 0.00 | AE21: 0 | AF21: 0 | AH21: OK | AI21: Concluído
A22: =+I22&J22 -> B02.000120_OTSTNDNG_AMNT | B22: =+VLOOKUP(I22&J22,[1]Auxiliar!B:C,2,FALSE) -> 2 | C22: =+VLOOKUP(I22&J22,[1]Auxiliar!E:F,2,FALSE) -> 2 | D22: =+VLOOKUP(I22&J22,[1]Auxiliar!H:I,2,FALSE) -> 2 | E22: =+VLOOKUP(I22&J22,[1]Auxiliar!K:L,2,FALSE) -> 2 | F22: =+VLOOKUP(I22&J22,[1]Auxiliar!N:O,2,FALSE) -> 2 | G22: =+VLOOKUP(I22&J22,[1]Auxiliar!Q:R,2,FALSE) -> 2 | H22: =+"c"&LEFT(J22,4) -> c0120 | I22: B02.00 | J22: 0120_OTSTNDNG_AMNT | L22: =+VLOOKUP(J22,#REF!,3,FALSE) -> #REF! | N22: 2025-10-31 | O22: 8 | P22: =+IFERROR(VLOOKUP(B22,'[1]ID1&5'!K:L,2,FALSE),"-") -> - | Q22: 8 | R22: =+IFERROR(VLOOKUP(CONCATENATE(A22,$C$10,C22),'[1]ID1&5'!B:J,8,FALSE),"-") -> - | S22: =+IFERROR(VLOOKUP(C22,'[1]ID1&5'!K:L,2,FALSE),"-") -> - | T22: 0 | U22: =+IFERROR(VLOOKUP(D22,'[1]ID1&5'!K:L,2,FALSE),"-") -> - | V22: 0 | W22: =+IFERROR(VLOOKUP(E22,'[1]ID1&5'!K:L,2,FALSE),"-") -> - | X22: 0 | Y22: =+X22/O22 -> 0 | Z22: =+IFERROR(VLOOKUP(F22,'[1]ID1&5'!K:L,2,FALSE),"-") -> - | AA22: 0 | AB22: =+AA22/O22 -> 0 | AC22: 7639597.40 | AD22: 1385452938.00 | AE22: 0 | AF22: 0 | AH22: OK | AI22: Pendente de desenvolv.
A23: =+I23&J23 -> B02.000130_RLVNT_AMNT_WDC | B23: =+VLOOKUP(I23&J23,[1]Auxiliar!B:C,2,FALSE) -> 2 | C23: =+VLOOKUP(I23&J23,[1]Auxiliar!E:F,2,FALSE) -> 2 | D23: =+VLOOKUP(I23&J23,[1]Auxiliar!H:I,2,FALSE) -> 2 | E23: =+VLOOKUP(I23&J23,[1]Auxiliar!K:L,2,FALSE) -> 2 | F23: =+VLOOKUP(I23&J23,[1]Auxiliar!N:O,2,FALSE) -> 2 | G23: =+VLOOKUP(I23&J23,[1]Auxiliar!Q:R,2,FALSE) -> 2 | H23: =+"c"&LEFT(J23,4) -> c0130 | I23: B02.00 | J23: 0130_RLVNT_AMNT_WDC | L23: =+VLOOKUP(J23,#REF!,3,FALSE) -> #REF! | N23: 2025-10-31 | O23: 8 | P23: =+IFERROR(VLOOKUP(B23,'[1]ID1&5'!K:L,2,FALSE),"-") -> - | Q23: 8 | R23: =+IFERROR(VLOOKUP(CONCATENATE(A23,$C$10,C23),'[1]ID1&5'!B:J,8,FALSE),"-") -> - | S23: =+IFERROR(VLOOKUP(C23,'[1]ID1&5'!K:L,2,FALSE),"-") -> - | T23: 0 | U23: =+IFERROR(VLOOKUP(D23,'[1]ID1&5'!K:L,2,FALSE),"-") -> - | V23: 0 | W23: =+IFERROR(VLOOKUP(E23,'[1]ID1&5'!K:L,2,FALSE),"-") -> - | X23: 0 | Y23: =+X23/O23 -> 0 | Z23: =+IFERROR(VLOOKUP(F23,'[1]ID1&5'!K:L,2,FALSE),"-") -> - | AA23: 0 | AB23: =+AA23/O23 -> 0 | AC23: 7639597.40 | AD23: 1385452938.00 | AE23: 0 | AF23: 0 | AH23: OK | AI23: Pendente de desenvolv.
A24: =+I24&J24 -> B02.000140_NTR_LBLTY | B24: =+VLOOKUP(I24&J24,[1]Auxiliar!B:C,2,FALSE) -> 2 | C24: =+VLOOKUP(I24&J24,[1]Auxiliar!E:F,2,FALSE) -> 2 | D24: =+VLOOKUP(I24&J24,[1]Auxiliar!H:I,2,FALSE) -> 2 | E24: =+VLOOKUP(I24&J24,[1]Auxiliar!K:L,2,FALSE) -> 2 | F24: =+VLOOKUP(I24&J24,[1]Auxiliar!N:O,2,FALSE) -> 2 | G24: =+VLOOKUP(I24&J24,[1]Auxiliar!Q:R,2,FALSE) -> 2 | H24: =+"c"&LEFT(J24,4) -> c0140 | I24: B02.00 | J24: 0140_NTR_LBLTY | L24: =+VLOOKUP(J24,#REF!,3,FALSE) -> #REF! | N24: 2025-10-31 | O24: 8 | P24: =+IFERROR(VLOOKUP(B24,'[1]ID1&5'!K:L,2,FALSE),"-") -> - | Q24: 4 | R24: =+IFERROR(VLOOKUP(CONCATENATE(A24,$C$10,C24),'[1]ID1&5'!B:J,8,FALSE),"-") -> - | S24: =+IFERROR(VLOOKUP(C24,'[1]ID1&5'!K:L,2,FALSE),"-") -> - | T24: 0 | U24: =+IFERROR(VLOOKUP(D24,'[1]ID1&5'!K:L,2,FALSE),"-") -> - | V24: 0 | W24: =+IFERROR(VLOOKUP(E24,'[1]ID1&5'!K:L,2,FALSE),"-") -> - | X24: 0 | Y24: =+X24/O24 -> 0 | Z24: =+IFERROR(VLOOKUP(F24,'[1]ID1&5'!K:L,2,FALSE),"-") -> - | AA24: 0 | AB24: =+AA24/O24 -> 0 | AC24: Registered Bond | AD24: Title of ownership | AE24: 0 | AF24: 0 | AH24: OK | AI24: Com Incidências
A25: =+I25&J25 -> B02.000141_NTR_LBLTY_OTHR | B25: =+VLOOKUP(I25&J25,[1]Auxiliar!B:C,2,FALSE) -> 2 | C25: =+VLOOKUP(I25&J25,[1]Auxiliar!E:F,2,FALSE) -> 2 | D25: =+VLOOKUP(I25&J25,[1]Auxiliar!H:I,2,FALSE) -> 2 | E25: =+VLOOKUP(I25&J25,[1]Auxiliar!K:L,2,FALSE) -> 2 | F25: =+VLOOKUP(I25&J25,[1]Auxiliar!N:O,2,FALSE) -> 2 | G25: =+VLOOKUP(I25&J25,[1]Auxiliar!Q:R,2,FALSE) -> 2 | H25: =+"c"&LEFT(J25,4) -> c0141 | I25: B02.00 | J25: 0141_NTR_LBLTY_OTHR | L25: =+VLOOKUP(J25,#REF!,3,FALSE) -> #REF! | N25: 2025-10-31 | O25: 8 | P25: =+IFERROR(VLOOKUP(B25,'[1]ID1&5'!K:L,2,FALSE),"-") -> - | Q25: 0 | R25: =+IFERROR(VLOOKUP(CONCATENATE(A25,$C$10,C25),'[1]ID1&5'!B:J,8,FALSE),"-") -> - | S25: =+IFERROR(VLOOKUP(C25,'[1]ID1&5'!K:L,2,FALSE),"-") -> - | T25: 0 | U25: =+IFERROR(VLOOKUP(D25,'[1]ID1&5'!K:L,2,FALSE),"-") -> - | V25: 0 | W25: =+IFERROR(VLOOKUP(E25,'[1]ID1&5'!K:L,2,FALSE),"-") -> - | X25: 0 | Y25: =+X25/O25 -> 0 | Z25: =+IFERROR(VLOOKUP(F25,'[1]ID1&5'!K:L,2,FALSE),"-") -> - | AA25: 8 | AB25: =+AA25/O25 -> 1 | AC25: Not applicable | AD25: Not applicable | AE25: 0 | AF25: 1 | AG25: Comentário 14/11 - Campo com valor fixo de not applicable conforme a especificação funcional. | AH25: OK | AI25: Concluído
A26: =+I26&J26 -> B02.000150_FLG_STRCTRLLY_SBRDNTD | B26: =+VLOOKUP(I26&J26,[1]Auxiliar!B:C,2,FALSE) -> 2 | C26: =+VLOOKUP(I26&J26,[1]Auxiliar!E:F,2,FALSE) -> 2 | D26: =+VLOOKUP(I26&J26,[1]Auxiliar!H:I,2,FALSE) -> 2 | E26: =+VLOOKUP(I26&J26,[1]Auxiliar!K:L,2,FALSE) -> 2 | F26: =+VLOOKUP(I26&J26,[1]Auxiliar!N:O,2,FALSE) -> 2 | G26: =+VLOOKUP(I26&J26,[1]Auxiliar!Q:R,2,FALSE) -> 2 | H26: =+"c"&LEFT(J26,4) -> c0150 | I26: B02.00 | J26: 0150_FLG_STRCTRLLY_SBRDNTD | L26: =+VLOOKUP(J26,#REF!,3,FALSE) -> #REF! | N26: 2025-10-31 | O26: 8 | P26: =+IFERROR(VLOOKUP(B26,'[1]ID1&5'!K:L,2,FALSE),"-") -> - | Q26: 0 | R26: =+IFERROR(VLOOKUP(CONCATENATE(A26,$C$10,C26),'[1]ID1&5'!B:J,8,FALSE),"-") -> - | S26: =+IFERROR(VLOOKUP(C26,'[1]ID1&5'!K:L,2,FALSE),"-") -> - | T26: 0 | U26: =+IFERROR(VLOOKUP(D26,'[1]ID1&5'!K:L,2,FALSE),"-") -> - | V26: 0 | W26: =+IFERROR(VLOOKUP(E26,'[1]ID1&5'!K:L,2,FALSE),"-") -> - | X26: 0 | Y26: =+X26/O26 -> 0 | Z26: =+IFERROR(VLOOKUP(F26,'[1]ID1&5'!K:L,2,FALSE),"-") -> - | AA26: 8 | AB26: =+AA26/O26 -> 1 | AC26: Not applicable | AD26: Not applicable | AE26: 0 | AF26: 1 | AG26: Comentário 14/11 - Campo com valor fixo de not applicable conforme a especificação funcional. | AH26: OK | AI26: Concluído
A27: =+I27&J27 -> B02.000160_RANK_INSOLV | B27: =+VLOOKUP(I27&J27,[1]Auxiliar!B:C,2,FALSE) -> 2 | C27: =+VLOOKUP(I27&J27,[1]Auxiliar!E:F,2,FALSE) -> 2 | D27: =+VLOOKUP(I27&J27,[1]Auxiliar!H:I,2,FALSE) -> 2 | E27: =+VLOOKUP(I27&J27,[1]Auxiliar!K:L,2,FALSE) -> 2 | F27: =+VLOOKUP(I27&J27,[1]Auxiliar!N:O,2,FALSE) -> 2 | G27: =+VLOOKUP(I27&J27,[1]Auxiliar!Q:R,2,FALSE) -> 2 | H27: =+"c"&LEFT(J27,4) -> c0160 | I27: B02.00 | J27: 0160_RANK_INSOLV | L27: =+VLOOKUP(J27,#REF!,3,FALSE) -> #REF! | N27: 2025-10-31 | O27: 8 | P27: =+IFERROR(VLOOKUP(B27,'[1]ID1&5'!K:L,2,FALSE),"-") -> - | Q27: 0 | R27: =+IFERROR(VLOOKUP(CONCATENATE(A27,$C$10,C27),'[1]ID1&5'!B:J,8,FALSE),"-") -> - | S27: =+IFERROR(VLOOKUP(C27,'[1]ID1&5'!K:L,2,FALSE),"-") -> - | T27: 0 | U27: =+IFERROR(VLOOKUP(D27,'[1]ID1&5'!K:L,2,FALSE),"-") -> - | V27: 0 | W27: =+IFERROR(VLOOKUP(E27,'[1]ID1&5'!K:L,2,FALSE),"-") -> - | X27: 0 | Y27: =+X27/O27 -> 0 | Z27: =+IFERROR(VLOOKUP(F27,'[1]ID1&5'!K:L,2,FALSE),"-") -> - | AA27: 0 | AB27: =+AA27/O27 -> 0 | AC27: 1 | AD27: 8 | AE27: 0 | AF27: 0 | AH27: OK | AI27: Concluído
A28: =+I28&J28 -> B02.000161_CNTRCTL_SBRDNTN | B28: =+VLOOKUP(I28&J28,[1]Auxiliar!B:C,2,FALSE) -> 2 | C28: =+VLOOKUP(I28&J28,[1]Auxiliar!E:F,2,FALSE) -> 2 | D28: =+VLOOKUP(I28&J28,[1]Auxiliar!H:I,2,FALSE) -> 2 | E28: =+VLOOKUP(I28&J28,[1]Auxiliar!K:L,2,FALSE) -> 2 | F28: =+VLOOKUP(I28&J28,[1]Auxiliar!N:O,2,FALSE) -> 2 | G28: =+VLOOKUP(I28&J28,[1]Auxiliar!Q:R,2,FALSE) -> 2 | H28: =+"c"&LEFT(J28,4) -> c0161 | I28: B02.00 | J28: 0161_CNTRCTL_SBRDNTN | L28: =+VLOOKUP(J28,#REF!,3,FALSE) -> #REF! | N28: 2025-10-31 | O28: 8 | P28: =+IFERROR(VLOOKUP(B28,'[1]ID1&5'!K:L,2,FALSE),"-") -> - | Q28: 0 | R28: =+IFERROR(VLOOKUP(CONCATENATE(A28,$C$10,C28),'[1]ID1&5'!B:J,8,FALSE),"-") -> - | S28: =+IFERROR(VLOOKUP(C28,'[1]ID1&5'!K:L,2,FALSE),"-") -> - | T28: 0 | U28: =+IFERROR(VLOOKUP(D28,'[1]ID1&5'!K:L,2,FALSE),"-") -> - | V28: 0 | W28: =+IFERROR(VLOOKUP(E28,'[1]ID1&5'!K:L,2,FALSE),"-") -> - | X28: 0 | Y28: =+X28/O28 -> 0 | Z28: =+IFERROR(VLOOKUP(F28,'[1]ID1&5'!K:L,2,FALSE),"-") -> - | AA28: 8 | AB28: =+AA28/O28 -> 1 | AC28: 999999999999999.00 | AD28: 999999999999999.00 | AE28: 0 | AF28: 0 | AG28: Comentário 14/11 - Campo com valor fixo de not applicable conforme a especificação funcional. | AH28: OK | AI28: Concluído
A29: =+I29&J29 -> B02.000162_BAIL_IN_CASCADE | B29: =+VLOOKUP(I29&J29,[1]Auxiliar!B:C,2,FALSE) -> 2 | C29: =+VLOOKUP(I29&J29,[1]Auxiliar!E:F,2,FALSE) -> 2 | D29: =+VLOOKUP(I29&J29,[1]Auxiliar!H:I,2,FALSE) -> 2 | E29: =+VLOOKUP(I29&J29,[1]Auxiliar!K:L,2,FALSE) -> 2 | F29: =+VLOOKUP(I29&J29,[1]Auxiliar!N:O,2,FALSE) -> 2 | G29: =+VLOOKUP(I29&J29,[1]Auxiliar!Q:R,2,FALSE) -> 2 | H29: =+"c"&LEFT(J29,4) -> c0162 | I29: B02.00 | J29: 0162_BAIL_IN_CASCADE | L29: =+VLOOKUP(J29,#REF!,3,FALSE) -> #REF! | N29: 2025-10-31 | O29: 8 | P29: =+IFERROR(VLOOKUP(B29,'[1]ID1&5'!K:L,2,FALSE),"-") -> - | Q29: 0 | R29: =+IFERROR(VLOOKUP(CONCATENATE(A29,$C$10,C29),'[1]ID1&5'!B:J,8,FALSE),"-") -> - | S29: =+IFERROR(VLOOKUP(C29,'[1]ID1&5'!K:L,2,FALSE),"-") -> - | T29: 0 | U29: =+IFERROR(VLOOKUP(D29,'[1]ID1&5'!K:L,2,FALSE),"-") -> - | V29: 0 | W29: =+IFERROR(VLOOKUP(E29,'[1]ID1&5'!K:L,2,FALSE),"-") -> - | X29: 0 | Y29: =+X29/O29 -> 0 | Z29: =+IFERROR(VLOOKUP(F29,'[1]ID1&5'!K:L,2,FALSE),"-") -> - | AA29: 0 | AB29: =+AA29/O29 -> 0 | AC29: 1 | AD29: 8 | AE29: 0 | AF29: 0 | AH29: OK | AI29: Concluído
A30: =+I30&J30 -> B02.000170_DT_INCPTN | B30: =+VLOOKUP(I30&J30,[1]Auxiliar!B:C,2,FALSE) -> 2 | C30: =+VLOOKUP(I30&J30,[1]Auxiliar!E:F,2,FALSE) -> 2 | D30: =+VLOOKUP(I30&J30,[1]Auxiliar!H:I,2,FALSE) -> 2 | E30: =+VLOOKUP(I30&J30,[1]Auxiliar!K:L,2,FALSE) -> 2 | F30: =+VLOOKUP(I30&J30,[1]Auxiliar!N:O,2,FALSE) -> 2 | G30: =+VLOOKUP(I30&J30,[1]Auxiliar!Q:R,2,FALSE) -> 2 | H30: =+"c"&LEFT(J30,4) -> c0170 | I30: B02.00 | J30: 0170_DT_INCPTN | L30: =+VLOOKUP(J30,#REF!,3,FALSE) -> #REF! | N30: 2025-10-31 | O30: 8 | P30: =+IFERROR(VLOOKUP(B30,'[1]ID1&5'!K:L,2,FALSE),"-") -> - | Q30: 0 | R30: =+IFERROR(VLOOKUP(CONCATENATE(A30,$C$10,C30),'[1]ID1&5'!B:J,8,FALSE),"-") -> - | S30: =+IFERROR(VLOOKUP(C30,'[1]ID1&5'!K:L,2,FALSE),"-") -> - | T30: 0 | U30: =+IFERROR(VLOOKUP(D30,'[1]ID1&5'!K:L,2,FALSE),"-") -> - | V30: 0 | W30: =+IFERROR(VLOOKUP(E30,'[1]ID1&5'!K:L,2,FALSE),"-") -> - | X30: 0 | Y30: =+X30/O30 -> 0 | Z30: =+IFERROR(VLOOKUP(F30,'[1]ID1&5'!K:L,2,FALSE),"-") -> - | AA30: 0 | AB30: =+AA30/O30 -> 0 | AC30: 33608 | AD30: 45806 | AE30: 1 | AF30: 0 | AH30: OK | AI30: Concluído
A31: =+I31&J31 -> B02.000180_DT_NXT_INTRST_PYMNT | B31: =+VLOOKUP(I31&J31,[1]Auxiliar!B:C,2,FALSE) -> 2 | C31: =+VLOOKUP(I31&J31,[1]Auxiliar!E:F,2,FALSE) -> 2 | D31: =+VLOOKUP(I31&J31,[1]Auxiliar!H:I,2,FALSE) -> 2 | E31: =+VLOOKUP(I31&J31,[1]Auxiliar!K:L,2,FALSE) -> 2 | F31: =+VLOOKUP(I31&J31,[1]Auxiliar!N:O,2,FALSE) -> 2 | G31: =+VLOOKUP(I31&J31,[1]Auxiliar!Q:R,2,FALSE) -> 2 | H31: =+"c"&LEFT(J31,4) -> c0180 | I31: B02.00 | J31: 0180_DT_NXT_INTRST_PYMNT | L31: =+VLOOKUP(J31,#REF!,3,FALSE) -> #REF! | N31: 2025-10-31 | O31: 8 | P31: =+IFERROR(VLOOKUP(B31,'[1]ID1&5'!K:L,2,FALSE),"-") -> - | Q31: 8 | R31: =+IFERROR(VLOOKUP(CONCATENATE(A31,$C$10,C31),'[1]ID1&5'!B:J,8,FALSE),"-") -> - | S31: =+IFERROR(VLOOKUP(C31,'[1]ID1&5'!K:L,2,FALSE),"-") -> - | T31: 0 | U31: =+IFERROR(VLOOKUP(D31,'[1]ID1&5'!K:L,2,FALSE),"-") -> - | V31: 0 | W31: =+IFERROR(VLOOKUP(E31,'[1]ID1&5'!K:L,2,FALSE),"-") -> - | X31: 0 | Y31: =+X31/O31 -> 0 | Z31: =+IFERROR(VLOOKUP(F31,'[1]ID1&5'!K:L,2,FALSE),"-") -> - | AA31: 4 | AB31: =+AA31/O31 -> 0.5 | AC31: 0001-01-01 | AD31: 2026-06-10 | AE31: 0 | AF31: 0 | AG31: Comentário 14/11 - Os registos referem-se a instrumentos de capital e não é expectável que exista uma data | AH31: OK | AI31: Em curso
A32: =+I32&J32 -> B02.000190_DT_NXT_RDMPTN_PYMNT | B32: =+VLOOKUP(I32&J32,[1]Auxiliar!B:C,2,FALSE) -> 2 | C32: =+VLOOKUP(I32&J32,[1]Auxiliar!E:F,2,FALSE) -> 2 | D32: =+VLOOKUP(I32&J32,[1]Auxiliar!H:I,2,FALSE) -> 2 | E32: =+VLOOKUP(I32&J32,[1]Auxiliar!K:L,2,FALSE) -> 2 | F32: =+VLOOKUP(I32&J32,[1]Auxiliar!N:O,2,FALSE) -> 2 | G32: =+VLOOKUP(I32&J32,[1]Auxiliar!Q:R,2,FALSE) -> 2 | H32: =+"c"&LEFT(J32,4) -> c0190 | I32: B02.00 | J32: 0190_DT_NXT_RDMPTN_PYMNT | L32: =+VLOOKUP(J32,#REF!,3,FALSE) -> #REF! | N32: 2025-10-31 | O32: 8 | P32: =+IFERROR(VLOOKUP(B32,'[1]ID1&5'!K:L,2,FALSE),"-") -> - | Q32: 1 | R32: =+IFERROR(VLOOKUP(CONCATENATE(A32,$C$10,C32),'[1]ID1&5'!B:J,8,FALSE),"-") -> - | S32: =+IFERROR(VLOOKUP(C32,'[1]ID1&5'!K:L,2,FALSE),"-") -> - | T32: 0 | U32: =+IFERROR(VLOOKUP(D32,'[1]ID1&5'!K:L,2,FALSE),"-") -> - | V32: 0 | W32: =+IFERROR(VLOOKUP(E32,'[1]ID1&5'!K:L,2,FALSE),"-") -> - | X32: 0 | Y32: =+X32/O32 -> 0 | Z32: =+IFERROR(VLOOKUP(F32,'[1]ID1&5'!K:L,2,FALSE),"-") -> - | AA32: 4 | AB32: =+AA32/O32 -> 0.5 | AC32: 0001-01-01 | AD32: 2030-07-30 | AE32: 0 | AF32: 0 | AG32: Comentário 14/11 - 3 registos referem-se a instrumentos sem maturidade contratualizada (cd_captools.fr004_cto, data_vencimento='9999-12-%'). 1 registo com o valor '2069-01-14', que se refere à data de perpetuidade, no entanto por indicação de Pedro Mendes, em sede de reunião, foi alterado para '0001-01-01'. | AH32: OK | AI32: Concluído
A33: =+I33&J33 -> B02.000200_DT_ERLST_RDMPTN | B33: =+VLOOKUP(I33&J33,[1]Auxiliar!B:C,2,FALSE) -> 2 | C33: =+VLOOKUP(I33&J33,[1]Auxiliar!E:F,2,FALSE) -> 2 | D33: =+VLOOKUP(I33&J33,[1]Auxiliar!H:I,2,FALSE) -> 2 | E33: =+VLOOKUP(I33&J33,[1]Auxiliar!K:L,2,FALSE) -> 2 | F33: =+VLOOKUP(I33&J33,[1]Auxiliar!N:O,2,FALSE) -> 2 | G33: =+VLOOKUP(I33&J33,[1]Auxiliar!Q:R,2,FALSE) -> 2 | H33: =+"c"&LEFT(J33,4) -> c0200 | I33: B02.00 | J33: 0200_DT_ERLST_RDMPTN | L33: =+VLOOKUP(J33,#REF!,3,FALSE) -> #REF! | N33: 2025-10-31 | O33: 8 | P33: =+IFERROR(VLOOKUP(B33,'[1]ID1&5'!K:L,2,FALSE),"-") -> - | Q33: 0 | R33: =+IFERROR(VLOOKUP(CONCATENATE(A33,$C$10,C33),'[1]ID1&5'!B:J,8,FALSE),"-") -> - | S33: =+IFERROR(VLOOKUP(C33,'[1]ID1&5'!K:L,2,FALSE),"-") -> - | T33: 0 | U33: =+IFERROR(VLOOKUP(D33,'[1]ID1&5'!K:L,2,FALSE),"-") -> - | V33: 0 | W33: =+IFERROR(VLOOKUP(E33,'[1]ID1&5'!K:L,2,FALSE),"-") -> - | X33: 0 | Y33: =+X33/O33 -> 0 | Z33: =+IFERROR(VLOOKUP(F33,'[1]ID1&5'!K:L,2,FALSE),"-") -> - | AA33: 8 | AB33: =+AA33/O33 -> 1 | AC33: 0001-01-01 | AD33: 0001-01-01 | AE33: 0 | AF33: 0 | AG33: Comentário 14/11 - Campo com valor fixo de not applicable conforme a especificação funcional. | AH33: OK | AI33: Concluído
A34: =+I34&J34 -> B02.000210_DT_LGL_FNL_MTRTY | B34: =+VLOOKUP(I34&J34,[1]Auxiliar!B:C,2,FALSE) -> 2 | C34: =+VLOOKUP(I34&J34,[1]Auxiliar!E:F,2,FALSE) -> 2 | D34: =+VLOOKUP(I34&J34,[1]Auxiliar!H:I,2,FALSE) -> 2 | E34: =+VLOOKUP(I34&J34,[1]Auxiliar!K:L,2,FALSE) -> 2 | F34: =+VLOOKUP(I34&J34,[1]Auxiliar!N:O,2,FALSE) -> 2 | G34: =+VLOOKUP(I34&J34,[1]Auxiliar!Q:R,2,FALSE) -> 2 | H34: =+"c"&LEFT(J34,4) -> c0210 | I34: B02.00 | J34: 0210_DT_LGL_FNL_MTRTY | L34: =+VLOOKUP(J34,#REF!,3,FALSE) -> #REF! | N34: 2025-10-31 | O34: 8 | P34: =+IFERROR(VLOOKUP(B34,'[1]ID1&5'!K:L,2,FALSE),"-") -> - | Q34: 1 | R34: =+IFERROR(VLOOKUP(CONCATENATE(A34,$C$10,C34),'[1]ID1&5'!B:J,8,FALSE),"-") -> - | S34: =+IFERROR(VLOOKUP(C34,'[1]ID1&5'!K:L,2,FALSE),"-") -> - | T34: 0 | U34: =+IFERROR(VLOOKUP(D34,'[1]ID1&5'!K:L,2,FALSE),"-") -> - | V34: 0 | W34: =+IFERROR(VLOOKUP(E34,'[1]ID1&5'!K:L,2,FALSE),"-") -> - | X34: 0 | Y34: =+X34/O34 -> 0 | Z34: =+IFERROR(VLOOKUP(F34,'[1]ID1&5'!K:L,2,FALSE),"-") -> - | AA34: 4 | AB34: =+AA34/O34 -> 0.5 | AC34: 0001-01-01 | AD34: 2030-07-30 | AE34: 0 | AF34: 0 | AG34: Comentário 14/11 - 3 registos referem-se a instrumentos sem maturidade contratualizada (cd_captools.fr004_cto, data_vencimento='9999-12-%'). 1 registo com o valor '2069-01-14', que se refere à data de perpetuidade, no entanto por indicação de Pedro Mendes, em sede de reunião, foi alterado para '0001-01-01'. | AH34: OK | AI34: Concluído
A35: =+I35&J35 -> B02.000220_GOVERNING_LAW | B35: =+VLOOKUP(I35&J35,[1]Auxiliar!B:C,2,FALSE) -> 2 | C35: =+VLOOKUP(I35&J35,[1]Auxiliar!E:F,2,FALSE) -> 2 | D35: =+VLOOKUP(I35&J35,[1]Auxiliar!H:I,2,FALSE) -> 2 | E35: =+VLOOKUP(I35&J35,[1]Auxiliar!K:L,2,FALSE) -> 2 | F35: =+VLOOKUP(I35&J35,[1]Auxiliar!N:O,2,FALSE) -> 2 | G35: =+VLOOKUP(I35&J35,[1]Auxiliar!Q:R,2,FALSE) -> 2 | H35: =+"c"&LEFT(J35,4) -> c0220 | I35: B02.00 | J35: 0220_GOVERNING_LAW | L35: =+VLOOKUP(J35,#REF!,3,FALSE) -> #REF! | N35: 2025-10-31 | O35: 8 | P35: =+IFERROR(VLOOKUP(B35,'[1]ID1&5'!K:L,2,FALSE),"-") -> - | Q35: 0 | R35: =+IFERROR(VLOOKUP(CONCATENATE(A35,$C$10,C35),'[1]ID1&5'!B:J,8,FALSE),"-") -> - | S35: =+IFERROR(VLOOKUP(C35,'[1]ID1&5'!K:L,2,FALSE),"-") -> - | T35: 0 | U35: =+IFERROR(VLOOKUP(D35,'[1]ID1&5'!K:L,2,FALSE),"-") -> - | V35: 0 | W35: =+IFERROR(VLOOKUP(E35,'[1]ID1&5'!K:L,2,FALSE),"-") -> - | X35: 0 | Y35: =+X35/O35 -> 0 | Z35: =+IFERROR(VLOOKUP(F35,'[1]ID1&5'!K:L,2,FALSE),"-") -> - | AA35: 0 | AB35: =+AA35/O35 -> 0 | AC35: PT | AD35: PT | AE35: 0 | AF35: 0 | AH35: OK | AI35: Concluído
A36: =+I36&J36 -> B02.000230_BAIL_IN_RCGNTN_CLS | B36: =+VLOOKUP(I36&J36,[1]Auxiliar!B:C,2,FALSE) -> 2 | C36: =+VLOOKUP(I36&J36,[1]Auxiliar!E:F,2,FALSE) -> 2 | D36: =+VLOOKUP(I36&J36,[1]Auxiliar!H:I,2,FALSE) -> 2 | E36: =+VLOOKUP(I36&J36,[1]Auxiliar!K:L,2,FALSE) -> 2 | F36: =+VLOOKUP(I36&J36,[1]Auxiliar!N:O,2,FALSE) -> 2 | G36: =+VLOOKUP(I36&J36,[1]Auxiliar!Q:R,2,FALSE) -> 2 | H36: =+"c"&LEFT(J36,4) -> c0230 | I36: B02.00 | J36: 0230_BAIL_IN_RCGNTN_CLS | L36: =+VLOOKUP(J36,#REF!,3,FALSE) -> #REF! | N36: 2025-10-31 | O36: 8 | P36: =+IFERROR(VLOOKUP(B36,'[1]ID1&5'!K:L,2,FALSE),"-") -> - | Q36: 0 | R36: =+IFERROR(VLOOKUP(CONCATENATE(A36,$C$10,C36),'[1]ID1&5'!B:J,8,FALSE),"-") -> - | S36: =+IFERROR(VLOOKUP(C36,'[1]ID1&5'!K:L,2,FALSE),"-") -> - | T36: 0 | U36: =+IFERROR(VLOOKUP(D36,'[1]ID1&5'!K:L,2,FALSE),"-") -> - | V36: 0 | W36: =+IFERROR(VLOOKUP(E36,'[1]ID1&5'!K:L,2,FALSE),"-") -> - | X36: 0 | Y36: =+X36/O36 -> 0 | Z36: =+IFERROR(VLOOKUP(F36,'[1]ID1&5'!K:L,2,FALSE),"-") -> - | AA36: 0 | AB36: =+AA36/O36 -> 0 | AC36: Yes, supported by Legal Opinion | AD36: Yes, supported by Legal Opinion | AE36: 0 | AF36: 0 | AH36: OK | AI36: Concluído
A37: =+I37&J37 -> B02.000240_ZERO_COUPON | B37: =+VLOOKUP(I37&J37,[1]Auxiliar!B:C,2,FALSE) -> 2 | C37: =+VLOOKUP(I37&J37,[1]Auxiliar!E:F,2,FALSE) -> 2 | D37: =+VLOOKUP(I37&J37,[1]Auxiliar!H:I,2,FALSE) -> 2 | E37: =+VLOOKUP(I37&J37,[1]Auxiliar!K:L,2,FALSE) -> 2 | F37: =+VLOOKUP(I37&J37,[1]Auxiliar!N:O,2,FALSE) -> 2 | G37: =+VLOOKUP(I37&J37,[1]Auxiliar!Q:R,2,FALSE) -> 2 | H37: =+"c"&LEFT(J37,4) -> c0240 | I37: B02.00 | J37: 0240_ZERO_COUPON | L37: =+VLOOKUP(J37,#REF!,3,FALSE) -> #REF! | N37: 2025-10-31 | O37: 8 | P37: =+IFERROR(VLOOKUP(B37,'[1]ID1&5'!K:L,2,FALSE),"-") -> - | Q37: 0 | R37: =+IFERROR(VLOOKUP(CONCATENATE(A37,$C$10,C37),'[1]ID1&5'!B:J,8,FALSE),"-") -> - | S37: =+IFERROR(VLOOKUP(C37,'[1]ID1&5'!K:L,2,FALSE),"-") -> - | T37: 0 | U37: =+IFERROR(VLOOKUP(D37,'[1]ID1&5'!K:L,2,FALSE),"-") -> - | V37: 0 | W37: =+IFERROR(VLOOKUP(E37,'[1]ID1&5'!K:L,2,FALSE),"-") -> - | X37: 0 | Y37: =+X37/O37 -> 0 | Z37: =+IFERROR(VLOOKUP(F37,'[1]ID1&5'!K:L,2,FALSE),"-") -> - | AA37: 0 | AB37: =+AA37/O37 -> 0 | AC37: No ZCB | AD37: No ZCB | AE37: 0 | AF37: 0 | AH37: OK | AI37: Concluído
A38: =+I38&J38 -> B02.000250_STRCTRD_PRDCT | B38: =+VLOOKUP(I38&J38,[1]Auxiliar!B:C,2,FALSE) -> 2 | C38: =+VLOOKUP(I38&J38,[1]Auxiliar!E:F,2,FALSE) -> 2 | D38: =+VLOOKUP(I38&J38,[1]Auxiliar!H:I,2,FALSE) -> 2 | E38: =+VLOOKUP(I38&J38,[1]Auxiliar!K:L,2,FALSE) -> 2 | F38: =+VLOOKUP(I38&J38,[1]Auxiliar!N:O,2,FALSE) -> 2 | G38: =+VLOOKUP(I38&J38,[1]Auxiliar!Q:R,2,FALSE) -> 2 | H38: =+"c"&LEFT(J38,4) -> c0250 | I38: B02.00 | J38: 0250_STRCTRD_PRDCT | L38: =+VLOOKUP(J38,#REF!,3,FALSE) -> #REF! | N38: 2025-10-31 | O38: 8 | P38: =+IFERROR(VLOOKUP(B38,'[1]ID1&5'!K:L,2,FALSE),"-") -> - | Q38: 0 | R38: =+IFERROR(VLOOKUP(CONCATENATE(A38,$C$10,C38),'[1]ID1&5'!B:J,8,FALSE),"-") -> - | S38: =+IFERROR(VLOOKUP(C38,'[1]ID1&5'!K:L,2,FALSE),"-") -> - | T38: 0 | U38: =+IFERROR(VLOOKUP(D38,'[1]ID1&5'!K:L,2,FALSE),"-") -> - | V38: 0 | W38: =+IFERROR(VLOOKUP(E38,'[1]ID1&5'!K:L,2,FALSE),"-") -> - | X38: 0 | Y38: =+X38/O38 -> 0 | Z38: =+IFERROR(VLOOKUP(F38,'[1]ID1&5'!K:L,2,FALSE),"-") -> - | AA38: 0 | AB38: =+AA38/O38 -> 0 | AC38: Non-structured/Vanilla | AD38: Non-structured/Vanilla | AE38: 0 | AF38: 0 | AH38: OK | AI38: Concluído
A39: =+I39&J39 -> B02.000260_GRNTD_MIN_AMNT_STRCTRD_PRDCT | B39: =+VLOOKUP(I39&J39,[1]Auxiliar!B:C,2,FALSE) -> 2 | C39: =+VLOOKUP(I39&J39,[1]Auxiliar!E:F,2,FALSE) -> 2 | D39: =+VLOOKUP(I39&J39,[1]Auxiliar!H:I,2,FALSE) -> 2 | E39: =+VLOOKUP(I39&J39,[1]Auxiliar!K:L,2,FALSE) -> 2 | F39: =+VLOOKUP(I39&J39,[1]Auxiliar!N:O,2,FALSE) -> 2 | G39: =+VLOOKUP(I39&J39,[1]Auxiliar!Q:R,2,FALSE) -> 2 | H39: =+"c"&LEFT(J39,4) -> c0260 | I39: B02.00 | J39: 0260_GRNTD_MIN_AMNT_STRCTRD_PRDCT | L39: =+VLOOKUP(J39,#REF!,3,FALSE) -> #REF! | N39: 2025-10-31 | O39: 8 | P39: =+IFERROR(VLOOKUP(B39,'[1]ID1&5'!K:L,2,FALSE),"-") -> - | Q39: 0 | R39: =+IFERROR(VLOOKUP(CONCATENATE(A39,$C$10,C39),'[1]ID1&5'!B:J,8,FALSE),"-") -> - | S39: =+IFERROR(VLOOKUP(C39,'[1]ID1&5'!K:L,2,FALSE),"-") -> - | T39: 0 | U39: =+IFERROR(VLOOKUP(D39,'[1]ID1&5'!K:L,2,FALSE),"-") -> - | V39: 0 | W39: =+IFERROR(VLOOKUP(E39,'[1]ID1&5'!K:L,2,FALSE),"-") -> - | X39: 0 | Y39: =+X39/O39 -> 0 | Z39: =+IFERROR(VLOOKUP(F39,'[1]ID1&5'!K:L,2,FALSE),"-") -> - | AA39: 8 | AB39: =+AA39/O39 -> 1 | AC39: 999999999999999.00 | AD39: 999999999999999.00 | AE39: 0 | AF39: 0 | AG39: Comentário 14/11 - Campo com valor fixo de not applicable conforme a especificação funcional. | AH39: OK | AI39: Concluído
A40: =+I40&J40 -> B02.000270_FV_AMNT_STRCTRD_PRDCT | B40: =+VLOOKUP(I40&J40,[1]Auxiliar!B:C,2,FALSE) -> 2 | C40: =+VLOOKUP(I40&J40,[1]Auxiliar!E:F,2,FALSE) -> 2 | D40: =+VLOOKUP(I40&J40,[1]Auxiliar!H:I,2,FALSE) -> 2 | E40: =+VLOOKUP(I40&J40,[1]Auxiliar!K:L,2,FALSE) -> 2 | F40: =+VLOOKUP(I40&J40,[1]Auxiliar!N:O,2,FALSE) -> 2 | G40: =+VLOOKUP(I40&J40,[1]Auxiliar!Q:R,2,FALSE) -> 2 | H40: =+"c"&LEFT(J40,4) -> c0270 | I40: B02.00 | J40: 0270_FV_AMNT_STRCTRD_PRDCT | L40: =+VLOOKUP(J40,#REF!,3,FALSE) -> #REF! | N40: 2025-10-31 | O40: 8 | P40: =+IFERROR(VLOOKUP(B40,'[1]ID1&5'!K:L,2,FALSE),"-") -> - | Q40: 0 | R40: =+IFERROR(VLOOKUP(CONCATENATE(A40,$C$10,C40),'[1]ID1&5'!B:J,8,FALSE),"-") -> - | S40: =+IFERROR(VLOOKUP(C40,'[1]ID1&5'!K:L,2,FALSE),"-") -> - | T40: 0 | U40: =+IFERROR(VLOOKUP(D40,'[1]ID1&5'!K:L,2,FALSE),"-") -> - | V40: 0 | W40: =+IFERROR(VLOOKUP(E40,'[1]ID1&5'!K:L,2,FALSE),"-") -> - | X40: 0 | Y40: =+X40/O40 -> 0 | Z40: =+IFERROR(VLOOKUP(F40,'[1]ID1&5'!K:L,2,FALSE),"-") -> - | AA40: 8 | AB40: =+AA40/O40 -> 1 | AC40: 999999999999999.00 | AD40: 999999999999999.00 | AE40: 0 | AF40: 0 | AG40: Comentário 14/11 - Campo com valor fixo de not applicable conforme a especificação funcional. | AH40: OK | AI40: Concluído
A41: =+I41&J41 -> B02.000280_FLG_NCNP_DPSTS | B41: =+VLOOKUP(I41&J41,[1]Auxiliar!B:C,2,FALSE) -> 2 | C41: =+VLOOKUP(I41&J41,[1]Auxiliar!E:F,2,FALSE) -> 2 | D41: =+VLOOKUP(I41&J41,[1]Auxiliar!H:I,2,FALSE) -> 2 | E41: =+VLOOKUP(I41&J41,[1]Auxiliar!K:L,2,FALSE) -> 2 | F41: =+VLOOKUP(I41&J41,[1]Auxiliar!N:O,2,FALSE) -> 2 | G41: =+VLOOKUP(I41&J41,[1]Auxiliar!Q:R,2,FALSE) -> 2 | H41: =+"c"&LEFT(J41,4) -> c0280 | I41: B02.00 | J41: 0280_FLG_NCNP_DPSTS | L41: =+VLOOKUP(J41,#REF!,3,FALSE) -> #REF! | N41: 2025-10-31 | O41: 8 | P41: =+IFERROR(VLOOKUP(B41,'[1]ID1&5'!K:L,2,FALSE),"-") -> - | Q41: 0 | R41: =+IFERROR(VLOOKUP(CONCATENATE(A41,$C$10,C41),'[1]ID1&5'!B:J,8,FALSE),"-") -> - | S41: =+IFERROR(VLOOKUP(C41,'[1]ID1&5'!K:L,2,FALSE),"-") -> - | T41: 0 | U41: =+IFERROR(VLOOKUP(D41,'[1]ID1&5'!K:L,2,FALSE),"-") -> - | V41: 0 | W41: =+IFERROR(VLOOKUP(E41,'[1]ID1&5'!K:L,2,FALSE),"-") -> - | X41: 0 | Y41: =+X41/O41 -> 0 | Z41: =+IFERROR(VLOOKUP(F41,'[1]ID1&5'!K:L,2,FALSE),"-") -> - | AA41: 0 | AB41: =+AA41/O41 -> 0 | AC41: FALSE | AD41: FALSE | AE41: 0 | AF41: 0 | AH41: OK | AI41: Concluído
A42: =+I42&J42 -> B02.000290_FLG_NCBP_DPSTS | B42: =+VLOOKUP(I42&J42,[1]Auxiliar!B:C,2,FALSE) -> 2 | C42: =+VLOOKUP(I42&J42,[1]Auxiliar!E:F,2,FALSE) -> 2 | D42: =+VLOOKUP(I42&J42,[1]Auxiliar!H:I,2,FALSE) -> 2 | E42: =+VLOOKUP(I42&J42,[1]Auxiliar!K:L,2,FALSE) -> 2 | F42: =+VLOOKUP(I42&J42,[1]Auxiliar!N:O,2,FALSE) -> 2 | G42: =+VLOOKUP(I42&J42,[1]Auxiliar!Q:R,2,FALSE) -> 2 | H42: =+"c"&LEFT(J42,4) -> c0290 | I42: B02.00 | J42: 0290_FLG_NCBP_DPSTS | L42: =+VLOOKUP(J42,#REF!,3,FALSE) -> #REF! | N42: 2025-10-31 | O42: 8 | P42: =+IFERROR(VLOOKUP(B42,'[1]ID1&5'!K:L,2,FALSE),"-") -> - | Q42: 0 | R42: =+IFERROR(VLOOKUP(CONCATENATE(A42,$C$10,C42),'[1]ID1&5'!B:J,8,FALSE),"-") -> - | S42: =+IFERROR(VLOOKUP(C42,'[1]ID1&5'!K:L,2,FALSE),"-") -> - | T42: 0 | U42: =+IFERROR(VLOOKUP(D42,'[1]ID1&5'!K:L,2,FALSE),"-") -> - | V42: 0 | W42: =+IFERROR(VLOOKUP(E42,'[1]ID1&5'!K:L,2,FALSE),"-") -> - | X42: 0 | Y42: =+X42/O42 -> 0 | Z42: =+IFERROR(VLOOKUP(F42,'[1]ID1&5'!K:L,2,FALSE),"-") -> - | AA42: 0 | AB42: =+AA42/O42 -> 0 | AC42: FALSE | AD42: FALSE | AE42: 0 | AF42: 0 | AH42: OK | AI42: Concluído
A43: =+I43&J43 -> B02.000300_AMNT_CVRD_ELGBL_DPSTS | B43: =+VLOOKUP(I43&J43,[1]Auxiliar!B:C,2,FALSE) -> 2 | C43: =+VLOOKUP(I43&J43,[1]Auxiliar!E:F,2,FALSE) -> 2 | D43: =+VLOOKUP(I43&J43,[1]Auxiliar!H:I,2,FALSE) -> 2 | E43: =+VLOOKUP(I43&J43,[1]Auxiliar!K:L,2,FALSE) -> 2 | F43: =+VLOOKUP(I43&J43,[1]Auxiliar!N:O,2,FALSE) -> 2 | G43: =+VLOOKUP(I43&J43,[1]Auxiliar!Q:R,2,FALSE) -> 2 | H43: =+"c"&LEFT(J43,4) -> c0300 | I43: B02.00 | J43: 0300_AMNT_CVRD_ELGBL_DPSTS | L43: =+VLOOKUP(J43,#REF!,3,FALSE) -> #REF! | N43: 2025-10-31 | O43: 8 | P43: =+IFERROR(VLOOKUP(B43,'[1]ID1&5'!K:L,2,FALSE),"-") -> - | Q43: 0 | R43: =+IFERROR(VLOOKUP(CONCATENATE(A43,$C$10,C43),'[1]ID1&5'!B:J,8,FALSE),"-") -> - | S43: =+IFERROR(VLOOKUP(C43,'[1]ID1&5'!K:L,2,FALSE),"-") -> - | T43: 0 | U43: =+IFERROR(VLOOKUP(D43,'[1]ID1&5'!K:L,2,FALSE),"-") -> - | V43: 0 | W43: =+IFERROR(VLOOKUP(E43,'[1]ID1&5'!K:L,2,FALSE),"-") -> - | X43: 0 | Y43: =+X43/O43 -> 0 | Z43: =+IFERROR(VLOOKUP(F43,'[1]ID1&5'!K:L,2,FALSE),"-") -> - | AA43: 8 | AB43: =+AA43/O43 -> 1 | AC43: 999999999999999.00 | AD43: 999999999999999.00 | AE43: 0 | AF43: 0 | AG43: Comentário 14/11 - Campo com valor fixo de not applicable conforme a especificação funcional. | AH43: OK | AI43: Concluído
A44: =+I44&J44 -> B02.000310_FLG_CLLTRL_AGRMNTS | B44: =+VLOOKUP(I44&J44,[1]Auxiliar!B:C,2,FALSE) -> 2 | C44: =+VLOOKUP(I44&J44,[1]Auxiliar!E:F,2,FALSE) -> 2 | D44: =+VLOOKUP(I44&J44,[1]Auxiliar!H:I,2,FALSE) -> 2 | E44: =+VLOOKUP(I44&J44,[1]Auxiliar!K:L,2,FALSE) -> 2 | F44: =+VLOOKUP(I44&J44,[1]Auxiliar!N:O,2,FALSE) -> 2 | G44: =+VLOOKUP(I44&J44,[1]Auxiliar!Q:R,2,FALSE) -> 2 | H44: =+"c"&LEFT(J44,4) -> c0310 | I44: B02.00 | J44: 0310_FLG_CLLTRL_AGRMNTS | L44: =+VLOOKUP(J44,#REF!,3,FALSE) -> #REF! | N44: 2025-10-31 | O44: 8 | P44: =+IFERROR(VLOOKUP(B44,'[1]ID1&5'!K:L,2,FALSE),"-") -> - | Q44: 0 | R44: =+IFERROR(VLOOKUP(CONCATENATE(A44,$C$10,C44),'[1]ID1&5'!B:J,8,FALSE),"-") -> - | S44: =+IFERROR(VLOOKUP(C44,'[1]ID1&5'!K:L,2,FALSE),"-") -> - | T44: 0 | U44: =+IFERROR(VLOOKUP(D44,'[1]ID1&5'!K:L,2,FALSE),"-") -> - | V44: 0 | W44: =+IFERROR(VLOOKUP(E44,'[1]ID1&5'!K:L,2,FALSE),"-") -> - | X44: 0 | Y44: =+X44/O44 -> 0 | Z44: =+IFERROR(VLOOKUP(F44,'[1]ID1&5'!K:L,2,FALSE),"-") -> - | AA44: 0 | AB44: =+AA44/O44 -> 0 | AC44: Unsecured | AD44: Unsecured | AE44: 0 | AF44: 0 | AH44: OK | AI44: Concluído
A45: =+I45&J45 -> B02.000320_AMNT_CLLTRL | B45: =+VLOOKUP(I45&J45,[1]Auxiliar!B:C,2,FALSE) -> 2 | C45: =+VLOOKUP(I45&J45,[1]Auxiliar!E:F,2,FALSE) -> 2 | D45: =+VLOOKUP(I45&J45,[1]Auxiliar!H:I,2,FALSE) -> 2 | E45: =+VLOOKUP(I45&J45,[1]Auxiliar!K:L,2,FALSE) -> 2 | F45: =+VLOOKUP(I45&J45,[1]Auxiliar!N:O,2,FALSE) -> 2 | G45: =+VLOOKUP(I45&J45,[1]Auxiliar!Q:R,2,FALSE) -> 2 | H45: =+"c"&LEFT(J45,4) -> c0320 | I45: B02.00 | J45: 0320_AMNT_CLLTRL | L45: =+VLOOKUP(J45,#REF!,3,FALSE) -> #REF! | N45: 2025-10-31 | O45: 8 | P45: =+IFERROR(VLOOKUP(B45,'[1]ID1&5'!K:L,2,FALSE),"-") -> - | Q45: 0 | R45: =+IFERROR(VLOOKUP(CONCATENATE(A45,$C$10,C45),'[1]ID1&5'!B:J,8,FALSE),"-") -> - | S45: =+IFERROR(VLOOKUP(C45,'[1]ID1&5'!K:L,2,FALSE),"-") -> - | T45: 0 | U45: =+IFERROR(VLOOKUP(D45,'[1]ID1&5'!K:L,2,FALSE),"-") -> - | V45: 0 | W45: =+IFERROR(VLOOKUP(E45,'[1]ID1&5'!K:L,2,FALSE),"-") -> - | X45: 0 | Y45: =+X45/O45 -> 0 | Z45: =+IFERROR(VLOOKUP(F45,'[1]ID1&5'!K:L,2,FALSE),"-") -> - | AA45: 8 | AB45: =+AA45/O45 -> 1 | AC45: 999999999999999.00 | AD45: 999999999999999.00 | AE45: 0 | AF45: 0 | AG45: Comentário 14/11 - Campo com valor fixo de not applicable conforme a especificação funcional. | AH45: OK | AI45: Concluído
A46: =+I46&J46 -> B02.000330_AMNT_UNCLLTRLZD | B46: =+VLOOKUP(I46&J46,[1]Auxiliar!B:C,2,FALSE) -> 2 | C46: =+VLOOKUP(I46&J46,[1]Auxiliar!E:F,2,FALSE) -> 2 | D46: =+VLOOKUP(I46&J46,[1]Auxiliar!H:I,2,FALSE) -> 2 | E46: =+VLOOKUP(I46&J46,[1]Auxiliar!K:L,2,FALSE) -> 2 | F46: =+VLOOKUP(I46&J46,[1]Auxiliar!N:O,2,FALSE) -> 2 | G46: =+VLOOKUP(I46&J46,[1]Auxiliar!Q:R,2,FALSE) -> 2 | H46: =+"c"&LEFT(J46,4) -> c0330 | I46: B02.00 | J46: 0330_AMNT_UNCLLTRLZD | L46: =+VLOOKUP(J46,#REF!,3,FALSE) -> #REF! | N46: 2025-10-31 | O46: 8 | P46: =+IFERROR(VLOOKUP(B46,'[1]ID1&5'!K:L,2,FALSE),"-") -> - | Q46: 0 | R46: =+IFERROR(VLOOKUP(CONCATENATE(A46,$C$10,C46),'[1]ID1&5'!B:J,8,FALSE),"-") -> - | S46: =+IFERROR(VLOOKUP(C46,'[1]ID1&5'!K:L,2,FALSE),"-") -> - | T46: 0 | U46: =+IFERROR(VLOOKUP(D46,'[1]ID1&5'!K:L,2,FALSE),"-") -> - | V46: 0 | W46: =+IFERROR(VLOOKUP(E46,'[1]ID1&5'!K:L,2,FALSE),"-") -> - | X46: 0 | Y46: =+X46/O46 -> 0 | Z46: =+IFERROR(VLOOKUP(F46,'[1]ID1&5'!K:L,2,FALSE),"-") -> - | AA46: 8 | AB46: =+AA46/O46 -> 1 | AC46: 999999999999999.00 | AD46: 999999999999999.00 | AE46: 0 | AF46: 0 | AG46: Comentário 14/11 - Campo com valor fixo de not applicable conforme a especificação funcional. | AH46: OK | AI46: Concluído
A47: =+I47&J47 -> B02.000340_ID_CLLTRL | B47: =+VLOOKUP(I47&J47,[1]Auxiliar!B:C,2,FALSE) -> 2 | C47: =+VLOOKUP(I47&J47,[1]Auxiliar!E:F,2,FALSE) -> 2 | D47: =+VLOOKUP(I47&J47,[1]Auxiliar!H:I,2,FALSE) -> 2 | E47: =+VLOOKUP(I47&J47,[1]Auxiliar!K:L,2,FALSE) -> 2 | F47: =+VLOOKUP(I47&J47,[1]Auxiliar!N:O,2,FALSE) -> 2 | G47: =+VLOOKUP(I47&J47,[1]Auxiliar!Q:R,2,FALSE) -> 2 | H47: =+"c"&LEFT(J47,4) -> c0340 | I47: B02.00 | J47: 0340_ID_CLLTRL | L47: =+VLOOKUP(J47,#REF!,3,FALSE) -> #REF! | N47: 2025-10-31 | O47: 8 | P47: =+IFERROR(VLOOKUP(B47,'[1]ID1&5'!K:L,2,FALSE),"-") -> - | Q47: 0 | R47: =+IFERROR(VLOOKUP(CONCATENATE(A47,$C$10,C47),'[1]ID1&5'!B:J,8,FALSE),"-") -> - | S47: =+IFERROR(VLOOKUP(C47,'[1]ID1&5'!K:L,2,FALSE),"-") -> - | T47: 0 | U47: =+IFERROR(VLOOKUP(D47,'[1]ID1&5'!K:L,2,FALSE),"-") -> - | V47: 0 | W47: =+IFERROR(VLOOKUP(E47,'[1]ID1&5'!K:L,2,FALSE),"-") -> - | X47: 0 | Y47: =+X47/O47 -> 0 | Z47: =+IFERROR(VLOOKUP(F47,'[1]ID1&5'!K:L,2,FALSE),"-") -> - | AA47: 8 | AB47: =+AA47/O47 -> 1 | AC47: Not applicable | AD47: Not applicable | AE47: 0 | AF47: 1 | AG47: Comentário 14/11 - Campo com valor fixo de not applicable conforme a especificação funcional. | AH47: OK | AI47: Concluído
A48: =+I48&J48 -> B02.000350_TYP_CLLTRL | B48: =+VLOOKUP(I48&J48,[1]Auxiliar!B:C,2,FALSE) -> 2 | C48: =+VLOOKUP(I48&J48,[1]Auxiliar!E:F,2,FALSE) -> 2 | D48: =+VLOOKUP(I48&J48,[1]Auxiliar!H:I,2,FALSE) -> 2 | E48: =+VLOOKUP(I48&J48,[1]Auxiliar!K:L,2,FALSE) -> 2 | F48: =+VLOOKUP(I48&J48,[1]Auxiliar!N:O,2,FALSE) -> 2 | G48: =+VLOOKUP(I48&J48,[1]Auxiliar!Q:R,2,FALSE) -> 2 | H48: =+"c"&LEFT(J48,4) -> c0350 | I48: B02.00 | J48: 0350_TYP_CLLTRL | L48: =+VLOOKUP(J48,#REF!,3,FALSE) -> #REF! | N48: 2025-10-31 | O48: 8 | P48: =+IFERROR(VLOOKUP(B48,'[1]ID1&5'!K:L,2,FALSE),"-") -> - | Q48: 0 | R48: =+IFERROR(VLOOKUP(CONCATENATE(A48,$C$10,C48),'[1]ID1&5'!B:J,8,FALSE),"-") -> - | S48: =+IFERROR(VLOOKUP(C48,'[1]ID1&5'!K:L,2,FALSE),"-") -> - | T48: 0 | U48: =+IFERROR(VLOOKUP(D48,'[1]ID1&5'!K:L,2,FALSE),"-") -> - | V48: 0 | W48: =+IFERROR(VLOOKUP(E48,'[1]ID1&5'!K:L,2,FALSE),"-") -> - | X48: 0 | Y48: =+X48/O48 -> 0 | Z48: =+IFERROR(VLOOKUP(F48,'[1]ID1&5'!K:L,2,FALSE),"-") -> - | AA48: 8 | AB48: =+AA48/O48 -> 1 | AC48: Not applicable | AD48: Not applicable | AE48: 0 | AF48: 0 | AG48: Comentário 14/11 - Campo com valor fixo de not applicable conforme a especificação funcional. | AH48: OK | AI48: Concluído
A49: =+I49&J49 -> B02.000351_TYP_CLLTRL_OTHR | B49: =+VLOOKUP(I49&J49,[1]Auxiliar!B:C,2,FALSE) -> 2 | C49: =+VLOOKUP(I49&J49,[1]Auxiliar!E:F,2,FALSE) -> 2 | D49: =+VLOOKUP(I49&J49,[1]Auxiliar!H:I,2,FALSE) -> 2 | E49: =+VLOOKUP(I49&J49,[1]Auxiliar!K:L,2,FALSE) -> 2 | F49: =+VLOOKUP(I49&J49,[1]Auxiliar!N:O,2,FALSE) -> 2 | G49: =+VLOOKUP(I49&J49,[1]Auxiliar!Q:R,2,FALSE) -> 2 | H49: =+"c"&LEFT(J49,4) -> c0351 | I49: B02.00 | J49: 0351_TYP_CLLTRL_OTHR | L49: =+VLOOKUP(J49,#REF!,3,FALSE) -> #REF! | N49: 2025-10-31 | O49: 8 | P49: =+IFERROR(VLOOKUP(B49,'[1]ID1&5'!K:L,2,FALSE),"-") -> - | Q49: 0 | R49: =+IFERROR(VLOOKUP(CONCATENATE(A49,$C$10,C49),'[1]ID1&5'!B:J,8,FALSE),"-") -> - | S49: =+IFERROR(VLOOKUP(C49,'[1]ID1&5'!K:L,2,FALSE),"-") -> - | T49: 0 | U49: =+IFERROR(VLOOKUP(D49,'[1]ID1&5'!K:L,2,FALSE),"-") -> - | V49: 0 | W49: =+IFERROR(VLOOKUP(E49,'[1]ID1&5'!K:L,2,FALSE),"-") -> - | X49: 0 | Y49: =+X49/O49 -> 0 | Z49: =+IFERROR(VLOOKUP(F49,'[1]ID1&5'!K:L,2,FALSE),"-") -> - | AA49: 8 | AB49: =+AA49/O49 -> 1 | AC49: Not applicable | AD49: Not applicable | AE49: 0 | AF49: 1 | AG49: Comentário 14/11 - Campo com valor fixo de not applicable conforme a especificação funcional. | AH49: OK | AI49: Concluído
A50: =+I50&J50 -> B02.000360_TRDNG_MTHD | B50: =+VLOOKUP(I50&J50,[1]Auxiliar!B:C,2,FALSE) -> 2 | C50: =+VLOOKUP(I50&J50,[1]Auxiliar!E:F,2,FALSE) -> 2 | D50: =+VLOOKUP(I50&J50,[1]Auxiliar!H:I,2,FALSE) -> 2 | E50: =+VLOOKUP(I50&J50,[1]Auxiliar!K:L,2,FALSE) -> 2 | F50: =+VLOOKUP(I50&J50,[1]Auxiliar!N:O,2,FALSE) -> 2 | G50: =+VLOOKUP(I50&J50,[1]Auxiliar!Q:R,2,FALSE) -> 2 | H50: =+"c"&LEFT(J50,4) -> c0360 | I50: B02.00 | J50: 0360_TRDNG_MTHD | L50: =+VLOOKUP(J50,#REF!,3,FALSE) -> #REF! | N50: 2025-10-31 | O50: 8 | P50: =+IFERROR(VLOOKUP(B50,'[1]ID1&5'!K:L,2,FALSE),"-") -> - | Q50: 8 | R50: =+IFERROR(VLOOKUP(CONCATENATE(A50,$C$10,C50),'[1]ID1&5'!B:J,8,FALSE),"-") -> - | S50: =+IFERROR(VLOOKUP(C50,'[1]ID1&5'!K:L,2,FALSE),"-") -> - | T50: 0 | U50: =+IFERROR(VLOOKUP(D50,'[1]ID1&5'!K:L,2,FALSE),"-") -> - | V50: 0 | W50: =+IFERROR(VLOOKUP(E50,'[1]ID1&5'!K:L,2,FALSE),"-") -> - | X50: 0 | Y50: =+X50/O50 -> 0 | Z50: =+IFERROR(VLOOKUP(F50,'[1]ID1&5'!K:L,2,FALSE),"-") -> - | AA50: 0 | AB50: =+AA50/O50 -> 0 | AC50: Nominal | AD50: Unit | AE50: 0 | AF50: 0 | AH50: OK | AI50: Pendente de desenvolv.
A51: =+I51&J51 -> B02.000370_AMNT_SCRTY_EUR | B51: =+VLOOKUP(I51&J51,[1]Auxiliar!B:C,2,FALSE) -> 2 | C51: =+VLOOKUP(I51&J51,[1]Auxiliar!E:F,2,FALSE) -> 2 | D51: =+VLOOKUP(I51&J51,[1]Auxiliar!H:I,2,FALSE) -> 2 | E51: =+VLOOKUP(I51&J51,[1]Auxiliar!K:L,2,FALSE) -> 2 | F51: =+VLOOKUP(I51&J51,[1]Auxiliar!N:O,2,FALSE) -> 2 | G51: =+VLOOKUP(I51&J51,[1]Auxiliar!Q:R,2,FALSE) -> 2 | H51: =+"c"&LEFT(J51,4) -> c0370 | I51: B02.00 | J51: 0370_AMNT_SCRTY_EUR | L51: =+VLOOKUP(J51,#REF!,3,FALSE) -> #REF! | N51: 2025-10-31 | O51: 8 | P51: =+IFERROR(VLOOKUP(B51,'[1]ID1&5'!K:L,2,FALSE),"-") -> - | Q51: 0 | R51: =+IFERROR(VLOOKUP(CONCATENATE(A51,$C$10,C51),'[1]ID1&5'!B:J,8,FALSE),"-") -> - | S51: =+IFERROR(VLOOKUP(C51,'[1]ID1&5'!K:L,2,FALSE),"-") -> - | T51: 0 | U51: =+IFERROR(VLOOKUP(D51,'[1]ID1&5'!K:L,2,FALSE),"-") -> - | V51: 0 | W51: =+IFERROR(VLOOKUP(E51,'[1]ID1&5'!K:L,2,FALSE),"-") -> - | X51: 0 | Y51: =+X51/O51 -> 0 | Z51: =+IFERROR(VLOOKUP(F51,'[1]ID1&5'!K:L,2,FALSE),"-") -> - | AA51: 0 | AB51: =+AA51/O51 -> 0 | AC51: 1.00 | AD51: 100000.00 | AE51: 0 | AF51: 0 | AH51: OK | AI51: Concluído
A52: =+I52&J52 -> B02.000380_AMNT_SCRTY_FX | B52: =+VLOOKUP(I52&J52,[1]Auxiliar!B:C,2,FALSE) -> 2 | C52: =+VLOOKUP(I52&J52,[1]Auxiliar!E:F,2,FALSE) -> 2 | D52: =+VLOOKUP(I52&J52,[1]Auxiliar!H:I,2,FALSE) -> 2 | E52: =+VLOOKUP(I52&J52,[1]Auxiliar!K:L,2,FALSE) -> 2 | F52: =+VLOOKUP(I52&J52,[1]Auxiliar!N:O,2,FALSE) -> 2 | G52: =+VLOOKUP(I52&J52,[1]Auxiliar!Q:R,2,FALSE) -> 2 | H52: =+"c"&LEFT(J52,4) -> c0380 | I52: B02.00 | J52: 0380_AMNT_SCRTY_FX | L52: =+VLOOKUP(J52,#REF!,3,FALSE) -> #REF! | N52: 2025-10-31 | O52: 8 | P52: =+IFERROR(VLOOKUP(B52,'[1]ID1&5'!K:L,2,FALSE),"-") -> - | Q52: 0 | R52: =+IFERROR(VLOOKUP(CONCATENATE(A52,$C$10,C52),'[1]ID1&5'!B:J,8,FALSE),"-") -> - | S52: =+IFERROR(VLOOKUP(C52,'[1]ID1&5'!K:L,2,FALSE),"-") -> - | T52: 0 | U52: =+IFERROR(VLOOKUP(D52,'[1]ID1&5'!K:L,2,FALSE),"-") -> - | V52: 0 | W52: =+IFERROR(VLOOKUP(E52,'[1]ID1&5'!K:L,2,FALSE),"-") -> - | X52: 0 | Y52: =+X52/O52 -> 0 | Z52: =+IFERROR(VLOOKUP(F52,'[1]ID1&5'!K:L,2,FALSE),"-") -> - | AA52: 0 | AB52: =+AA52/O52 -> 0 | AC52: 1.00 | AD52: 100000.00 | AE52: 0 | AF52: 0 | AH52: OK | AI52: Em curso
A53: =+I53&J53 -> B02.000390_NMBR_SCRTS_NOT_RPRTNG_ENTTY | B53: =+VLOOKUP(I53&J53,[1]Auxiliar!B:C,2,FALSE) -> 2 | C53: =+VLOOKUP(I53&J53,[1]Auxiliar!E:F,2,FALSE) -> 2 | D53: =+VLOOKUP(I53&J53,[1]Auxiliar!H:I,2,FALSE) -> 2 | E53: =+VLOOKUP(I53&J53,[1]Auxiliar!K:L,2,FALSE) -> 2 | F53: =+VLOOKUP(I53&J53,[1]Auxiliar!N:O,2,FALSE) -> 2 | G53: =+VLOOKUP(I53&J53,[1]Auxiliar!Q:R,2,FALSE) -> 2 | H53: =+"c"&LEFT(J53,4) -> c0390 | I53: B02.00 | J53: 0390_NMBR_SCRTS_NOT_RPRTNG_ENTTY | L53: =+VLOOKUP(J53,#REF!,3,FALSE) -> #REF! | N53: 2025-10-31 | O53: 8 | P53: =+IFERROR(VLOOKUP(B53,'[1]ID1&5'!K:L,2,FALSE),"-") -> - | Q53: 8 | R53: =+IFERROR(VLOOKUP(CONCATENATE(A53,$C$10,C53),'[1]ID1&5'!B:J,8,FALSE),"-") -> - | S53: =+IFERROR(VLOOKUP(C53,'[1]ID1&5'!K:L,2,FALSE),"-") -> - | T53: 0 | U53: =+IFERROR(VLOOKUP(D53,'[1]ID1&5'!K:L,2,FALSE),"-") -> - | V53: 0 | W53: =+IFERROR(VLOOKUP(E53,'[1]ID1&5'!K:L,2,FALSE),"-") -> - | X53: 0 | Y53: =+X53/O53 -> 0 | Z53: =+IFERROR(VLOOKUP(F53,'[1]ID1&5'!K:L,2,FALSE),"-") -> - | AA53: 0 | AB53: =+AA53/O53 -> 0 | AC53: 2000 | AD53: 1385452938 | AE53: 0 | AF53: 0 | AH53: OK | AI53: Pendente de desenvolv.
A54: =+I54&J54 -> B02.000391_NMBR_SCRTS_RPRTNG_ENTTY | B54: =+VLOOKUP(I54&J54,[1]Auxiliar!B:C,2,FALSE) -> 2 | C54: =+VLOOKUP(I54&J54,[1]Auxiliar!E:F,2,FALSE) -> 2 | D54: =+VLOOKUP(I54&J54,[1]Auxiliar!H:I,2,FALSE) -> 2 | E54: =+VLOOKUP(I54&J54,[1]Auxiliar!K:L,2,FALSE) -> 2 | F54: =+VLOOKUP(I54&J54,[1]Auxiliar!N:O,2,FALSE) -> 2 | G54: =+VLOOKUP(I54&J54,[1]Auxiliar!Q:R,2,FALSE) -> 2 | H54: =+"c"&LEFT(J54,4) -> c0391 | I54: B02.00 | J54: 0391_NMBR_SCRTS_RPRTNG_ENTTY | L54: =+VLOOKUP(J54,#REF!,3,FALSE) -> #REF! | N54: 2025-10-31 | O54: 8 | P54: =+IFERROR(VLOOKUP(B54,'[1]ID1&5'!K:L,2,FALSE),"-") -> - | Q54: 8 | R54: =+IFERROR(VLOOKUP(CONCATENATE(A54,$C$10,C54),'[1]ID1&5'!B:J,8,FALSE),"-") -> - | S54: =+IFERROR(VLOOKUP(C54,'[1]ID1&5'!K:L,2,FALSE),"-") -> - | T54: 0 | U54: =+IFERROR(VLOOKUP(D54,'[1]ID1&5'!K:L,2,FALSE),"-") -> - | V54: 0 | W54: =+IFERROR(VLOOKUP(E54,'[1]ID1&5'!K:L,2,FALSE),"-") -> - | X54: 0 | Y54: =+X54/O54 -> 0 | Z54: =+IFERROR(VLOOKUP(F54,'[1]ID1&5'!K:L,2,FALSE),"-") -> - | AA54: 0 | AB54: =+AA54/O54 -> 0 | AC54: 0 | AD54: 6326736 | AE54: 0 | AF54: 0 | AH54: OK | AI54: Pendente de desenvolv.
A55: =+I55&J55 -> B02.000400_ACCRD_INTRST_SCRTY | B55: =+VLOOKUP(I55&J55,[1]Auxiliar!B:C,2,FALSE) -> 2 | C55: =+VLOOKUP(I55&J55,[1]Auxiliar!E:F,2,FALSE) -> 2 | D55: =+VLOOKUP(I55&J55,[1]Auxiliar!H:I,2,FALSE) -> 2 | E55: =+VLOOKUP(I55&J55,[1]Auxiliar!K:L,2,FALSE) -> 2 | F55: =+VLOOKUP(I55&J55,[1]Auxiliar!N:O,2,FALSE) -> 2 | G55: =+VLOOKUP(I55&J55,[1]Auxiliar!Q:R,2,FALSE) -> 2 | H55: =+"c"&LEFT(J55,4) -> c0400 | I55: B02.00 | J55: 0400_ACCRD_INTRST_SCRTY | L55: =+VLOOKUP(J55,#REF!,3,FALSE) -> #REF! | N55: 2025-10-31 | O55: 8 | P55: =+IFERROR(VLOOKUP(B55,'[1]ID1&5'!K:L,2,FALSE),"-") -> - | Q55: 8 | R55: =+IFERROR(VLOOKUP(CONCATENATE(A55,$C$10,C55),'[1]ID1&5'!B:J,8,FALSE),"-") -> - | S55: =+IFERROR(VLOOKUP(C55,'[1]ID1&5'!K:L,2,FALSE),"-") -> - | T55: 0 | U55: =+IFERROR(VLOOKUP(D55,'[1]ID1&5'!K:L,2,FALSE),"-") -> - | V55: 0 | W55: =+IFERROR(VLOOKUP(E55,'[1]ID1&5'!K:L,2,FALSE),"-") -> - | X55: 0 | Y55: =+X55/O55 -> 0 | Z55: =+IFERROR(VLOOKUP(F55,'[1]ID1&5'!K:L,2,FALSE),"-") -> - | AA55: 0 | AB55: =+AA55/O55 -> 0 | AC55: 0.0000 | AD55: 1872.6849 | AE55: 0 | AF55: 0 | AH55: OK | AI55: Pendente de desenvolv.
A56: =+I56&J56 -> B02.000410_FEES_CHARGES_SCRTY | B56: =+VLOOKUP(I56&J56,[1]Auxiliar!B:C,2,FALSE) -> 2 | C56: =+VLOOKUP(I56&J56,[1]Auxiliar!E:F,2,FALSE) -> 2 | D56: =+VLOOKUP(I56&J56,[1]Auxiliar!H:I,2,FALSE) -> 2 | E56: =+VLOOKUP(I56&J56,[1]Auxiliar!K:L,2,FALSE) -> 2 | F56: =+VLOOKUP(I56&J56,[1]Auxiliar!N:O,2,FALSE) -> 2 | G56: =+VLOOKUP(I56&J56,[1]Auxiliar!Q:R,2,FALSE) -> 2 | H56: =+"c"&LEFT(J56,4) -> c0410 | I56: B02.00 | J56: 0410_FEES_CHARGES_SCRTY | L56: =+VLOOKUP(J56,#REF!,3,FALSE) -> #REF! | N56: 2025-10-31 | O56: 8 | P56: =+IFERROR(VLOOKUP(B56,'[1]ID1&5'!K:L,2,FALSE),"-") -> - | Q56: 0 | R56: =+IFERROR(VLOOKUP(CONCATENATE(A56,$C$10,C56),'[1]ID1&5'!B:J,8,FALSE),"-") -> - | S56: =+IFERROR(VLOOKUP(C56,'[1]ID1&5'!K:L,2,FALSE),"-") -> - | T56: 0 | U56: =+IFERROR(VLOOKUP(D56,'[1]ID1&5'!K:L,2,FALSE),"-") -> - | V56: 0 | W56: =+IFERROR(VLOOKUP(E56,'[1]ID1&5'!K:L,2,FALSE),"-") -> - | X56: 0 | Y56: =+X56/O56 -> 0 | Z56: =+IFERROR(VLOOKUP(F56,'[1]ID1&5'!K:L,2,FALSE),"-") -> - | AA56: 0 | AB56: =+AA56/O56 -> 0 | AC56: 0.0000 | AD56: 0.0000 | AE56: 0 | AF56: 0 | AG56: Comentário 14/11 - Campo com valor fixo de not applicable conforme a especificação funcional. | AH56: OK | AI56: Concluído
A57: =+I57&J57 -> B02.000420_FV_AMNT_SCRTY | B57: =+VLOOKUP(I57&J57,[1]Auxiliar!B:C,2,FALSE) -> 2 | C57: =+VLOOKUP(I57&J57,[1]Auxiliar!E:F,2,FALSE) -> 2 | D57: =+VLOOKUP(I57&J57,[1]Auxiliar!H:I,2,FALSE) -> 2 | E57: =+VLOOKUP(I57&J57,[1]Auxiliar!K:L,2,FALSE) -> 2 | F57: =+VLOOKUP(I57&J57,[1]Auxiliar!N:O,2,FALSE) -> 2 | G57: =+VLOOKUP(I57&J57,[1]Auxiliar!Q:R,2,FALSE) -> 2 | H57: =+"c"&LEFT(J57,4) -> c0420 | I57: B02.00 | J57: 0420_FV_AMNT_SCRTY | L57: =+VLOOKUP(J57,#REF!,3,FALSE) -> #REF! | N57: 2025-10-31 | O57: 8 | P57: =+IFERROR(VLOOKUP(B57,'[1]ID1&5'!K:L,2,FALSE),"-") -> - | Q57: 0 | R57: =+IFERROR(VLOOKUP(CONCATENATE(A57,$C$10,C57),'[1]ID1&5'!B:J,8,FALSE),"-") -> - | S57: =+IFERROR(VLOOKUP(C57,'[1]ID1&5'!K:L,2,FALSE),"-") -> - | T57: 0 | U57: =+IFERROR(VLOOKUP(D57,'[1]ID1&5'!K:L,2,FALSE),"-") -> - | V57: 0 | W57: =+IFERROR(VLOOKUP(E57,'[1]ID1&5'!K:L,2,FALSE),"-") -> - | X57: 0 | Y57: =+X57/O57 -> 0 | Z57: =+IFERROR(VLOOKUP(F57,'[1]ID1&5'!K:L,2,FALSE),"-") -> - | AA57: 8 | AB57: =+AA57/O57 -> 1 | AC57: 999999999999999.0000 | AD57: 999999999999999.0000 | AE57: 0 | AF57: 0 | AG57: Comentário 14/11 - Campo com valor fixo de not applicable conforme a especificação funcional. | AH57: OK | AI57: Concluído
A58: =+I58&J58 -> B02.000430_PRNCPL_AMNT_GLBL_NT_EUR | B58: =+VLOOKUP(I58&J58,[1]Auxiliar!B:C,2,FALSE) -> 2 | C58: =+VLOOKUP(I58&J58,[1]Auxiliar!E:F,2,FALSE) -> 2 | D58: =+VLOOKUP(I58&J58,[1]Auxiliar!H:I,2,FALSE) -> 2 | E58: =+VLOOKUP(I58&J58,[1]Auxiliar!K:L,2,FALSE) -> 2 | F58: =+VLOOKUP(I58&J58,[1]Auxiliar!N:O,2,FALSE) -> 2 | G58: =+VLOOKUP(I58&J58,[1]Auxiliar!Q:R,2,FALSE) -> 2 | H58: =+"c"&LEFT(J58,4) -> c0430 | I58: B02.00 | J58: 0430_PRNCPL_AMNT_GLBL_NT_EUR | L58: =+VLOOKUP(J58,#REF!,3,FALSE) -> #REF! | N58: 2025-10-31 | O58: 8 | P58: =+IFERROR(VLOOKUP(B58,'[1]ID1&5'!K:L,2,FALSE),"-") -> - | Q58: 0 | R58: =+IFERROR(VLOOKUP(CONCATENATE(A58,$C$10,C58),'[1]ID1&5'!B:J,8,FALSE),"-") -> - | S58: =+IFERROR(VLOOKUP(C58,'[1]ID1&5'!K:L,2,FALSE),"-") -> - | T58: 0 | U58: =+IFERROR(VLOOKUP(D58,'[1]ID1&5'!K:L,2,FALSE),"-") -> - | V58: 0 | W58: =+IFERROR(VLOOKUP(E58,'[1]ID1&5'!K:L,2,FALSE),"-") -> - | X58: 0 | Y58: =+X58/O58 -> 0 | Z58: =+IFERROR(VLOOKUP(F58,'[1]ID1&5'!K:L,2,FALSE),"-") -> - | AA58: 8 | AB58: =+AA58/O58 -> 1 | AC58: 999999999999999.00 | AD58: 999999999999999.00 | AE58: 0 | AF58: 0 | AG58: Comentário 14/11 - Campo com valor fixo de not applicable conforme a especificação funcional. | AH58: OK | AI58: Concluído
A59: =+I59&J59 -> B02.000431_PRNCPL_AMNT_GLBL_NT_FX | B59: =+VLOOKUP(I59&J59,[1]Auxiliar!B:C,2,FALSE) -> 2 | C59: =+VLOOKUP(I59&J59,[1]Auxiliar!E:F,2,FALSE) -> 2 | D59: =+VLOOKUP(I59&J59,[1]Auxiliar!H:I,2,FALSE) -> 2 | E59: =+VLOOKUP(I59&J59,[1]Auxiliar!K:L,2,FALSE) -> 2 | F59: =+VLOOKUP(I59&J59,[1]Auxiliar!N:O,2,FALSE) -> 2 | G59: =+VLOOKUP(I59&J59,[1]Auxiliar!Q:R,2,FALSE) -> 2 | H59: =+"c"&LEFT(J59,4) -> c0431 | I59: B02.00 | J59: 0431_PRNCPL_AMNT_GLBL_NT_FX | L59: =+VLOOKUP(J59,#REF!,3,FALSE) -> #REF! | N59: 2025-10-31 | O59: 8 | P59: =+IFERROR(VLOOKUP(B59,'[1]ID1&5'!K:L,2,FALSE),"-") -> - | Q59: 0 | R59: =+IFERROR(VLOOKUP(CONCATENATE(A59,$C$10,C59),'[1]ID1&5'!B:J,8,FALSE),"-") -> - | S59: =+IFERROR(VLOOKUP(C59,'[1]ID1&5'!K:L,2,FALSE),"-") -> - | T59: 0 | U59: =+IFERROR(VLOOKUP(D59,'[1]ID1&5'!K:L,2,FALSE),"-") -> - | V59: 0 | W59: =+IFERROR(VLOOKUP(E59,'[1]ID1&5'!K:L,2,FALSE),"-") -> - | X59: 0 | Y59: =+X59/O59 -> 0 | Z59: =+IFERROR(VLOOKUP(F59,'[1]ID1&5'!K:L,2,FALSE),"-") -> - | AA59: 8 | AB59: =+AA59/O59 -> 1 | AC59: 999999999999999.00 | AD59: 999999999999999.00 | AE59: 0 | AF59: 0 | AG59: Comentário 14/11 - Campo com valor fixo de not applicable conforme a especificação funcional. | AH59: OK | AI59: Concluído
A60: =+I60&J60 -> B02.000440_NTR_GLBL_NT | B60: =+VLOOKUP(I60&J60,[1]Auxiliar!B:C,2,FALSE) -> 2 | C60: =+VLOOKUP(I60&J60,[1]Auxiliar!E:F,2,FALSE) -> 2 | D60: =+VLOOKUP(I60&J60,[1]Auxiliar!H:I,2,FALSE) -> 2 | E60: =+VLOOKUP(I60&J60,[1]Auxiliar!K:L,2,FALSE) -> 2 | F60: =+VLOOKUP(I60&J60,[1]Auxiliar!N:O,2,FALSE) -> 2 | G60: =+VLOOKUP(I60&J60,[1]Auxiliar!Q:R,2,FALSE) -> 2 | H60: =+"c"&LEFT(J60,4) -> c0440 | I60: B02.00 | J60: 0440_NTR_GLBL_NT | L60: =+VLOOKUP(J60,#REF!,3,FALSE) -> #REF! | N60: 2025-10-31 | O60: 8 | P60: =+IFERROR(VLOOKUP(B60,'[1]ID1&5'!K:L,2,FALSE),"-") -> - | Q60: 0 | R60: =+IFERROR(VLOOKUP(CONCATENATE(A60,$C$10,C60),'[1]ID1&5'!B:J,8,FALSE),"-") -> - | S60: =+IFERROR(VLOOKUP(C60,'[1]ID1&5'!K:L,2,FALSE),"-") -> - | T60: 0 | U60: =+IFERROR(VLOOKUP(D60,'[1]ID1&5'!K:L,2,FALSE),"-") -> - | V60: 0 | W60: =+IFERROR(VLOOKUP(E60,'[1]ID1&5'!K:L,2,FALSE),"-") -> - | X60: 0 | Y60: =+X60/O60 -> 0 | Z60: =+IFERROR(VLOOKUP(F60,'[1]ID1&5'!K:L,2,FALSE),"-") -> - | AA60: 8 | AB60: =+AA60/O60 -> 1 | AC60: Not applicable | AD60: Not applicable | AE60: 0 | AF60: 0 | AG60: Comentário 14/11 - Campo com valor fixo de not applicable conforme a especificação funcional. | AH60: OK | AI60: Concluído
A61: =+I61&J61 -> B02.000450_CRRNT_POOL_FCTR | B61: =+VLOOKUP(I61&J61,[1]Auxiliar!B:C,2,FALSE) -> 2 | C61: =+VLOOKUP(I61&J61,[1]Auxiliar!E:F,2,FALSE) -> 2 | D61: =+VLOOKUP(I61&J61,[1]Auxiliar!H:I,2,FALSE) -> 2 | E61: =+VLOOKUP(I61&J61,[1]Auxiliar!K:L,2,FALSE) -> 2 | F61: =+VLOOKUP(I61&J61,[1]Auxiliar!N:O,2,FALSE) -> 2 | G61: =+VLOOKUP(I61&J61,[1]Auxiliar!Q:R,2,FALSE) -> 2 | H61: =+"c"&LEFT(J61,4) -> c0450 | I61: B02.00 | J61: 0450_CRRNT_POOL_FCTR | L61: =+VLOOKUP(J61,#REF!,3,FALSE) -> #REF! | N61: 2025-10-31 | O61: 8 | P61: =+IFERROR(VLOOKUP(B61,'[1]ID1&5'!K:L,2,FALSE),"-") -> - | Q61: 0 | R61: =+IFERROR(VLOOKUP(CONCATENATE(A61,$C$10,C61),'[1]ID1&5'!B:J,8,FALSE),"-") -> - | S61: =+IFERROR(VLOOKUP(C61,'[1]ID1&5'!K:L,2,FALSE),"-") -> - | T61: 0 | U61: =+IFERROR(VLOOKUP(D61,'[1]ID1&5'!K:L,2,FALSE),"-") -> - | V61: 0 | W61: =+IFERROR(VLOOKUP(E61,'[1]ID1&5'!K:L,2,FALSE),"-") -> - | X61: 0 | Y61: =+X61/O61 -> 0 | Z61: =+IFERROR(VLOOKUP(F61,'[1]ID1&5'!K:L,2,FALSE),"-") -> - | AA61: 8 | AB61: =+AA61/O61 -> 1 | AC61: -9999.999999999 | AD61: -9999.999999999 | AE61: 0 | AF61: 0 | AG61: Comentário 14/11 - Campo com valor fixo de not applicable conforme a especificação funcional. | AH61: OK | AI61: Concluído
A62: =+I62&J62 -> B02.000460_CSD | B62: =+VLOOKUP(I62&J62,[1]Auxiliar!B:C,2,FALSE) -> 2 | C62: =+VLOOKUP(I62&J62,[1]Auxiliar!E:F,2,FALSE) -> 2 | D62: =+VLOOKUP(I62&J62,[1]Auxiliar!H:I,2,FALSE) -> 2 | E62: =+VLOOKUP(I62&J62,[1]Auxiliar!K:L,2,FALSE) -> 2 | F62: =+VLOOKUP(I62&J62,[1]Auxiliar!N:O,2,FALSE) -> 2 | G62: =+VLOOKUP(I62&J62,[1]Auxiliar!Q:R,2,FALSE) -> 2 | H62: =+"c"&LEFT(J62,4) -> c0460 | I62: B02.00 | J62: 0460_CSD | L62: =+VLOOKUP(J62,#REF!,3,FALSE) -> #REF! | N62: 2025-10-31 | O62: 8 | P62: =+IFERROR(VLOOKUP(B62,'[1]ID1&5'!K:L,2,FALSE),"-") -> - | Q62: 0 | R62: =+IFERROR(VLOOKUP(CONCATENATE(A62,$C$10,C62),'[1]ID1&5'!B:J,8,FALSE),"-") -> - | S62: =+IFERROR(VLOOKUP(C62,'[1]ID1&5'!K:L,2,FALSE),"-") -> - | T62: 0 | U62: =+IFERROR(VLOOKUP(D62,'[1]ID1&5'!K:L,2,FALSE),"-") -> - | V62: 0 | W62: =+IFERROR(VLOOKUP(E62,'[1]ID1&5'!K:L,2,FALSE),"-") -> - | X62: 0 | Y62: =+X62/O62 -> 0 | Z62: =+IFERROR(VLOOKUP(F62,'[1]ID1&5'!K:L,2,FALSE),"-") -> - | AA62: 0 | AB62: =+AA62/O62 -> 0 | AC62: INTERBOLSA_PT | AD62: INTERBOLSA_PT | AE62: 0 | AF62: 0 | AH62: OK | AI62: Concluído
A63: =+I63&J63 -> B02.000461_CSD_LEI | B63: =+VLOOKUP(I63&J63,[1]Auxiliar!B:C,2,FALSE) -> 2 | C63: =+VLOOKUP(I63&J63,[1]Auxiliar!E:F,2,FALSE) -> 2 | D63: =+VLOOKUP(I63&J63,[1]Auxiliar!H:I,2,FALSE) -> 2 | E63: =+VLOOKUP(I63&J63,[1]Auxiliar!K:L,2,FALSE) -> 2 | F63: =+VLOOKUP(I63&J63,[1]Auxiliar!N:O,2,FALSE) -> 2 | G63: =+VLOOKUP(I63&J63,[1]Auxiliar!Q:R,2,FALSE) -> 2 | H63: =+"c"&LEFT(J63,4) -> c0461 | I63: B02.00 | J63: 0461_CSD_LEI | L63: =+VLOOKUP(J63,#REF!,3,FALSE) -> #REF! | N63: 2025-10-31 | O63: 8 | P63: =+IFERROR(VLOOKUP(B63,'[1]ID1&5'!K:L,2,FALSE),"-") -> - | Q63: 0 | R63: =+IFERROR(VLOOKUP(CONCATENATE(A63,$C$10,C63),'[1]ID1&5'!B:J,8,FALSE),"-") -> - | S63: =+IFERROR(VLOOKUP(C63,'[1]ID1&5'!K:L,2,FALSE),"-") -> - | T63: 0 | U63: =+IFERROR(VLOOKUP(D63,'[1]ID1&5'!K:L,2,FALSE),"-") -> - | V63: 0 | W63: =+IFERROR(VLOOKUP(E63,'[1]ID1&5'!K:L,2,FALSE),"-") -> - | X63: 0 | Y63: =+X63/O63 -> 0 | Z63: =+IFERROR(VLOOKUP(F63,'[1]ID1&5'!K:L,2,FALSE),"-") -> - | AA63: 0 | AB63: =+AA63/O63 -> 0 | AC63: 529900LG70TCAGWCXT47 | AD63: 529900LG70TCAGWCXT47 | AE63: 0 | AF63: 0 | AH63: OK | AI63: Concluído
A64: =+I64&J64 -> B02.000462_CSD_OTHR | B64: =+VLOOKUP(I64&J64,[1]Auxiliar!B:C,2,FALSE) -> 2 | C64: =+VLOOKUP(I64&J64,[1]Auxiliar!E:F,2,FALSE) -> 2 | D64: =+VLOOKUP(I64&J64,[1]Auxiliar!H:I,2,FALSE) -> 2 | E64: =+VLOOKUP(I64&J64,[1]Auxiliar!K:L,2,FALSE) -> 2 | F64: =+VLOOKUP(I64&J64,[1]Auxiliar!N:O,2,FALSE) -> 2 | G64: =+VLOOKUP(I64&J64,[1]Auxiliar!Q:R,2,FALSE) -> 2 | H64: =+"c"&LEFT(J64,4) -> c0462 | I64: B02.00 | J64: 0462_CSD_OTHR | L64: =+VLOOKUP(J64,#REF!,3,FALSE) -> #REF! | N64: 2025-10-31 | O64: 8 | P64: =+IFERROR(VLOOKUP(B64,'[1]ID1&5'!K:L,2,FALSE),"-") -> - | Q64: 0 | R64: =+IFERROR(VLOOKUP(CONCATENATE(A64,$C$10,C64),'[1]ID1&5'!B:J,8,FALSE),"-") -> - | S64: =+IFERROR(VLOOKUP(C64,'[1]ID1&5'!K:L,2,FALSE),"-") -> - | T64: 0 | U64: =+IFERROR(VLOOKUP(D64,'[1]ID1&5'!K:L,2,FALSE),"-") -> - | V64: 0 | W64: =+IFERROR(VLOOKUP(E64,'[1]ID1&5'!K:L,2,FALSE),"-") -> - | X64: 0 | Y64: =+X64/O64 -> 0 | Z64: =+IFERROR(VLOOKUP(F64,'[1]ID1&5'!K:L,2,FALSE),"-") -> - | AA64: 8 | AB64: =+AA64/O64 -> 1 | AC64: Not applicable | AD64: Not applicable | AE64: 0 | AF64: 1 | AG64: Comentário 14/11 - Campo com valor fixo de not applicable conforme a especificação funcional. | AH64: OK | AI64: Concluído
A65: =+I65&J65 -> B02.000470_PYNG_AGNT | B65: =+VLOOKUP(I65&J65,[1]Auxiliar!B:C,2,FALSE) -> 2 | C65: =+VLOOKUP(I65&J65,[1]Auxiliar!E:F,2,FALSE) -> 2 | D65: =+VLOOKUP(I65&J65,[1]Auxiliar!H:I,2,FALSE) -> 2 | E65: =+VLOOKUP(I65&J65,[1]Auxiliar!K:L,2,FALSE) -> 2 | F65: =+VLOOKUP(I65&J65,[1]Auxiliar!N:O,2,FALSE) -> 2 | G65: =+VLOOKUP(I65&J65,[1]Auxiliar!Q:R,2,FALSE) -> 2 | H65: =+"c"&LEFT(J65,4) -> c0470 | I65: B02.00 | J65: 0470_PYNG_AGNT | L65: =+VLOOKUP(J65,#REF!,3,FALSE) -> #REF! | N65: 2025-10-31 | O65: 8 | P65: =+IFERROR(VLOOKUP(B65,'[1]ID1&5'!K:L,2,FALSE),"-") -> - | Q65: 0 | R65: =+IFERROR(VLOOKUP(CONCATENATE(A65,$C$10,C65),'[1]ID1&5'!B:J,8,FALSE),"-") -> - | S65: =+IFERROR(VLOOKUP(C65,'[1]ID1&5'!K:L,2,FALSE),"-") -> - | T65: 0 | U65: =+IFERROR(VLOOKUP(D65,'[1]ID1&5'!K:L,2,FALSE),"-") -> - | V65: 0 | W65: =+IFERROR(VLOOKUP(E65,'[1]ID1&5'!K:L,2,FALSE),"-") -> - | X65: 0 | Y65: =+X65/O65 -> 0 | Z65: =+IFERROR(VLOOKUP(F65,'[1]ID1&5'!K:L,2,FALSE),"-") -> - | AA65: 0 | AB65: =+AA65/O65 -> 0 | AC65: BANCO SANTANDER TOTTA S.A. | AD65: BANCO SANTANDER TOTTA S.A. | AE65: 0 | AF65: 0 | AH65: OK | AI65: Concluído
A66: =+I66&J66 -> B02.000471_PYNG_AGNT_LEI | B66: =+VLOOKUP(I66&J66,[1]Auxiliar!B:C,2,FALSE) -> 2 | C66: =+VLOOKUP(I66&J66,[1]Auxiliar!E:F,2,FALSE) -> 2 | D66: =+VLOOKUP(I66&J66,[1]Auxiliar!H:I,2,FALSE) -> 2 | E66: =+VLOOKUP(I66&J66,[1]Auxiliar!K:L,2,FALSE) -> 2 | F66: =+VLOOKUP(I66&J66,[1]Auxiliar!N:O,2,FALSE) -> 2 | G66: =+VLOOKUP(I66&J66,[1]Auxiliar!Q:R,2,FALSE) -> 2 | H66: =+"c"&LEFT(J66,4) -> c0471 | I66: B02.00 | J66: 0471_PYNG_AGNT_LEI | L66: =+VLOOKUP(J66,#REF!,3,FALSE) -> #REF! | N66: 2025-10-31 | O66: 8 | P66: =+IFERROR(VLOOKUP(B66,'[1]ID1&5'!K:L,2,FALSE),"-") -> - | Q66: 0 | R66: =+IFERROR(VLOOKUP(CONCATENATE(A66,$C$10,C66),'[1]ID1&5'!B:J,8,FALSE),"-") -> - | S66: =+IFERROR(VLOOKUP(C66,'[1]ID1&5'!K:L,2,FALSE),"-") -> - | T66: 0 | U66: =+IFERROR(VLOOKUP(D66,'[1]ID1&5'!K:L,2,FALSE),"-") -> - | V66: 0 | W66: =+IFERROR(VLOOKUP(E66,'[1]ID1&5'!K:L,2,FALSE),"-") -> - | X66: 0 | Y66: =+X66/O66 -> 0 | Z66: =+IFERROR(VLOOKUP(F66,'[1]ID1&5'!K:L,2,FALSE),"-") -> - | AA66: 0 | AB66: =+AA66/O66 -> 0 | AC66: 549300URJH9VSI58CS32 | AD66: 549300URJH9VSI58CS32 | AE66: 0 | AF66: 0 | AH66: OK | AI66: Concluído
A67: =+I67&J67 -> B02.000480_TRDNG_VN | B67: =+VLOOKUP(I67&J67,[1]Auxiliar!B:C,2,FALSE) -> 2 | C67: =+VLOOKUP(I67&J67,[1]Auxiliar!E:F,2,FALSE) -> 2 | D67: =+VLOOKUP(I67&J67,[1]Auxiliar!H:I,2,FALSE) -> 2 | E67: =+VLOOKUP(I67&J67,[1]Auxiliar!K:L,2,FALSE) -> 2 | F67: =+VLOOKUP(I67&J67,[1]Auxiliar!N:O,2,FALSE) -> 2 | G67: =+VLOOKUP(I67&J67,[1]Auxiliar!Q:R,2,FALSE) -> 2 | H67: =+"c"&LEFT(J67,4) -> c0480 | I67: B02.00 | J67: 0480_TRDNG_VN | L67: =+VLOOKUP(J67,#REF!,3,FALSE) -> #REF! | N67: 2025-10-31 | O67: 8 | P67: =+IFERROR(VLOOKUP(B67,'[1]ID1&5'!K:L,2,FALSE),"-") -> - | Q67: 0 | R67: =+IFERROR(VLOOKUP(CONCATENATE(A67,$C$10,C67),'[1]ID1&5'!B:J,8,FALSE),"-") -> - | S67: =+IFERROR(VLOOKUP(C67,'[1]ID1&5'!K:L,2,FALSE),"-") -> - | T67: 0 | U67: =+IFERROR(VLOOKUP(D67,'[1]ID1&5'!K:L,2,FALSE),"-") -> - | V67: 0 | W67: =+IFERROR(VLOOKUP(E67,'[1]ID1&5'!K:L,2,FALSE),"-") -> - | X67: 0 | Y67: =+X67/O67 -> 0 | Z67: =+IFERROR(VLOOKUP(F67,'[1]ID1&5'!K:L,2,FALSE),"-") -> - | AA67: 8 | AB67: =+AA67/O67 -> 1 | AC67: Not applicable | AD67: Not applicable | AE67: 0 | AF67: 0 | AG67: Comentário 14/11 - Campo com valor fixo de not applicable conforme a especificação funcional. | AH67: OK | AI67: Concluído
A68: =+I68&J68 -> B02.000481_TRDNG_VN_LEI | B68: =+VLOOKUP(I68&J68,[1]Auxiliar!B:C,2,FALSE) -> 2 | C68: =+VLOOKUP(I68&J68,[1]Auxiliar!E:F,2,FALSE) -> 2 | D68: =+VLOOKUP(I68&J68,[1]Auxiliar!H:I,2,FALSE) -> 2 | E68: =+VLOOKUP(I68&J68,[1]Auxiliar!K:L,2,FALSE) -> 2 | F68: =+VLOOKUP(I68&J68,[1]Auxiliar!N:O,2,FALSE) -> 2 | G68: =+VLOOKUP(I68&J68,[1]Auxiliar!Q:R,2,FALSE) -> 2 | H68: =+"c"&LEFT(J68,4) -> c0481 | I68: B02.00 | J68: 0481_TRDNG_VN_LEI | L68: =+VLOOKUP(J68,#REF!,3,FALSE) -> #REF! | N68: 2025-10-31 | O68: 8 | P68: =+IFERROR(VLOOKUP(B68,'[1]ID1&5'!K:L,2,FALSE),"-") -> - | Q68: 0 | R68: =+IFERROR(VLOOKUP(CONCATENATE(A68,$C$10,C68),'[1]ID1&5'!B:J,8,FALSE),"-") -> - | S68: =+IFERROR(VLOOKUP(C68,'[1]ID1&5'!K:L,2,FALSE),"-") -> - | T68: 0 | U68: =+IFERROR(VLOOKUP(D68,'[1]ID1&5'!K:L,2,FALSE),"-") -> - | V68: 0 | W68: =+IFERROR(VLOOKUP(E68,'[1]ID1&5'!K:L,2,FALSE),"-") -> - | X68: 0 | Y68: =+X68/O68 -> 0 | Z68: =+IFERROR(VLOOKUP(F68,'[1]ID1&5'!K:L,2,FALSE),"-") -> - | AA68: 8 | AB68: =+AA68/O68 -> 1 | AC68: Not applicable | AD68: Not applicable | AE68: 0 | AF68: 0 | AG68: Comentário 14/11 - Campo com valor fixo de not applicable conforme a especificação funcional. | AH68: OK | AI68: Concluído
A69: =+I69&J69 -> B02.000490_RGSTRR | B69: =+VLOOKUP(I69&J69,[1]Auxiliar!B:C,2,FALSE) -> 1 | C69: =+VLOOKUP(I69&J69,[1]Auxiliar!E:F,2,FALSE) -> 1 | D69: =+VLOOKUP(I69&J69,[1]Auxiliar!H:I,2,FALSE) -> 1 | E69: =+VLOOKUP(I69&J69,[1]Auxiliar!K:L,2,FALSE) -> 1 | F69: =+VLOOKUP(I69&J69,[1]Auxiliar!N:O,2,FALSE) -> 1 | G69: =+VLOOKUP(I69&J69,[1]Auxiliar!Q:R,2,FALSE) -> 1 | H69: =+"c"&LEFT(J69,4) -> c0490 | I69: B02.00 | J69: 0490_RGSTRR | L69: =+VLOOKUP(J69,#REF!,3,FALSE) -> #REF! | N69: 2025-10-31 | O69: 8 | P69: =+IFERROR(VLOOKUP(B69,'[1]ID1&5'!K:L,2,FALSE),"-") -> - | Q69: 0 | R69: =+IFERROR(VLOOKUP(CONCATENATE(A69,$C$10,C69),'[1]ID1&5'!B:J,8,FALSE),"-") -> - | S69: =+IFERROR(VLOOKUP(C69,'[1]ID1&5'!K:L,2,FALSE),"-") -> - | T69: 0 | U69: =+IFERROR(VLOOKUP(D69,'[1]ID1&5'!K:L,2,FALSE),"-") -> - | V69: 0 | W69: =+IFERROR(VLOOKUP(E69,'[1]ID1&5'!K:L,2,FALSE),"-") -> - | X69: 0 | Y69: =+X69/O69 -> 0 | Z69: =+IFERROR(VLOOKUP(F69,'[1]ID1&5'!K:L,2,FALSE),"-") -> - | AA69: 0 | AB69: =+AA69/O69 -> 0 | AC69: INTERBOLSA_PT | AD69: INTERBOLSA_PT | AE69: 0 | AF69: 0 | AH69: OK | AI69: Concluído
A70: =+I70&J70 -> B02.000491_RGSTRR_LEI | B70: =+VLOOKUP(I70&J70,[1]Auxiliar!B:C,2,FALSE) -> 2 | C70: =+VLOOKUP(I70&J70,[1]Auxiliar!E:F,2,FALSE) -> 2 | D70: =+VLOOKUP(I70&J70,[1]Auxiliar!H:I,2,FALSE) -> 2 | E70: =+VLOOKUP(I70&J70,[1]Auxiliar!K:L,2,FALSE) -> 2 | F70: =+VLOOKUP(I70&J70,[1]Auxiliar!N:O,2,FALSE) -> 2 | G70: =+VLOOKUP(I70&J70,[1]Auxiliar!Q:R,2,FALSE) -> 2 | H70: =+"c"&LEFT(J70,4) -> c0491 | I70: B02.00 | J70: 0491_RGSTRR_LEI | L70: =+VLOOKUP(J70,#REF!,3,FALSE) -> #REF! | N70: 2025-10-31 | O70: 8 | P70: =+IFERROR(VLOOKUP(B70,'[1]ID1&5'!K:L,2,FALSE),"-") -> - | Q70: 0 | R70: =+IFERROR(VLOOKUP(CONCATENATE(A70,$C$10,C70),'[1]ID1&5'!B:J,8,FALSE),"-") -> - | S70: =+IFERROR(VLOOKUP(C70,'[1]ID1&5'!K:L,2,FALSE),"-") -> - | T70: 0 | U70: =+IFERROR(VLOOKUP(D70,'[1]ID1&5'!K:L,2,FALSE),"-") -> - | V70: 0 | W70: =+IFERROR(VLOOKUP(E70,'[1]ID1&5'!K:L,2,FALSE),"-") -> - | X70: 0 | Y70: =+X70/O70 -> 0 | Z70: =+IFERROR(VLOOKUP(F70,'[1]ID1&5'!K:L,2,FALSE),"-") -> - | AA70: 0 | AB70: =+AA70/O70 -> 0 | AC70: 529900LG70TCAGWCXT47 | AD70: 529900LG70TCAGWCXT47 | AE70: 0 | AF70: 0 | AH70: OK | AI70: Concluído
A71: =+I71&J71 -> B02.000500_NNA | B71: =+VLOOKUP(I71&J71,[1]Auxiliar!B:C,2,FALSE) -> 2 | C71: =+VLOOKUP(I71&J71,[1]Auxiliar!E:F,2,FALSE) -> 2 | D71: =+VLOOKUP(I71&J71,[1]Auxiliar!H:I,2,FALSE) -> 2 | E71: =+VLOOKUP(I71&J71,[1]Auxiliar!K:L,2,FALSE) -> 2 | F71: =+VLOOKUP(I71&J71,[1]Auxiliar!N:O,2,FALSE) -> 2 | G71: =+VLOOKUP(I71&J71,[1]Auxiliar!Q:R,2,FALSE) -> 2 | H71: =+"c"&LEFT(J71,4) -> c0500 | I71: B02.00 | J71: 0500_NNA | L71: =+VLOOKUP(J71,#REF!,3,FALSE) -> #REF! | N71: 2025-10-31 | O71: 8 | P71: =+IFERROR(VLOOKUP(B71,'[1]ID1&5'!K:L,2,FALSE),"-") -> - | Q71: 0 | R71: =+IFERROR(VLOOKUP(CONCATENATE(A71,$C$10,C71),'[1]ID1&5'!B:J,8,FALSE),"-") -> - | S71: =+IFERROR(VLOOKUP(C71,'[1]ID1&5'!K:L,2,FALSE),"-") -> - | T71: 0 | U71: =+IFERROR(VLOOKUP(D71,'[1]ID1&5'!K:L,2,FALSE),"-") -> - | V71: 0 | W71: =+IFERROR(VLOOKUP(E71,'[1]ID1&5'!K:L,2,FALSE),"-") -> - | X71: 0 | Y71: =+X71/O71 -> 0 | Z71: =+IFERROR(VLOOKUP(F71,'[1]ID1&5'!K:L,2,FALSE),"-") -> - | AA71: 0 | AB71: =+AA71/O71 -> 0 | AC71: INTERBOLSA_PT | AD71: INTERBOLSA_PT | AE71: 0 | AF71: 0 | AH71: OK | AI71: Concluído
A72: =+I72&J72 -> B02.000501_NNA_LEI | B72: =+VLOOKUP(I72&J72,[1]Auxiliar!B:C,2,FALSE) -> 2 | C72: =+VLOOKUP(I72&J72,[1]Auxiliar!E:F,2,FALSE) -> 2 | D72: =+VLOOKUP(I72&J72,[1]Auxiliar!H:I,2,FALSE) -> 2 | E72: =+VLOOKUP(I72&J72,[1]Auxiliar!K:L,2,FALSE) -> 2 | F72: =+VLOOKUP(I72&J72,[1]Auxiliar!N:O,2,FALSE) -> 2 | G72: =+VLOOKUP(I72&J72,[1]Auxiliar!Q:R,2,FALSE) -> 2 | H72: =+"c"&LEFT(J72,4) -> c0501 | I72: B02.00 | J72: 0501_NNA_LEI | L72: =+VLOOKUP(J72,#REF!,3,FALSE) -> #REF! | N72: 2025-10-31 | O72: 8 | P72: =+IFERROR(VLOOKUP(B72,'[1]ID1&5'!K:L,2,FALSE),"-") -> - | Q72: 0 | R72: =+IFERROR(VLOOKUP(CONCATENATE(A72,$C$10,C72),'[1]ID1&5'!B:J,8,FALSE),"-") -> - | S72: =+IFERROR(VLOOKUP(C72,'[1]ID1&5'!K:L,2,FALSE),"-") -> - | T72: 0 | U72: =+IFERROR(VLOOKUP(D72,'[1]ID1&5'!K:L,2,FALSE),"-") -> - | V72: 0 | W72: =+IFERROR(VLOOKUP(E72,'[1]ID1&5'!K:L,2,FALSE),"-") -> - | X72: 0 | Y72: =+X72/O72 -> 0 | Z72: =+IFERROR(VLOOKUP(F72,'[1]ID1&5'!K:L,2,FALSE),"-") -> - | AA72: 0 | AB72: =+AA72/O72 -> 0 | AC72: 529900LG70TCAGWCXT47 | AD72: 529900LG70TCAGWCXT47 | AE72: 0 | AF72: 0 | AH72: OK | AI72: Concluído
A73: =+I73&J73 -> B02.000510_CMMN_DPSTRY | B73: =+VLOOKUP(I73&J73,[1]Auxiliar!B:C,2,FALSE) -> 2 | C73: =+VLOOKUP(I73&J73,[1]Auxiliar!E:F,2,FALSE) -> 2 | D73: =+VLOOKUP(I73&J73,[1]Auxiliar!H:I,2,FALSE) -> 2 | E73: =+VLOOKUP(I73&J73,[1]Auxiliar!K:L,2,FALSE) -> 2 | F73: =+VLOOKUP(I73&J73,[1]Auxiliar!N:O,2,FALSE) -> 2 | G73: =+VLOOKUP(I73&J73,[1]Auxiliar!Q:R,2,FALSE) -> 2 | H73: =+"c"&LEFT(J73,4) -> c0510 | I73: B02.00 | J73: 0510_CMMN_DPSTRY | L73: =+VLOOKUP(J73,#REF!,3,FALSE) -> #REF! | N73: 2025-10-31 | O73: 8 | P73: =+IFERROR(VLOOKUP(B73,'[1]ID1&5'!K:L,2,FALSE),"-") -> - | Q73: 0 | R73: =+IFERROR(VLOOKUP(CONCATENATE(A73,$C$10,C73),'[1]ID1&5'!B:J,8,FALSE),"-") -> - | S73: =+IFERROR(VLOOKUP(C73,'[1]ID1&5'!K:L,2,FALSE),"-") -> - | T73: 0 | U73: =+IFERROR(VLOOKUP(D73,'[1]ID1&5'!K:L,2,FALSE),"-") -> - | V73: 0 | W73: =+IFERROR(VLOOKUP(E73,'[1]ID1&5'!K:L,2,FALSE),"-") -> - | X73: 0 | Y73: =+X73/O73 -> 0 | Z73: =+IFERROR(VLOOKUP(F73,'[1]ID1&5'!K:L,2,FALSE),"-") -> - | AA73: 8 | AB73: =+AA73/O73 -> 1 | AC73: Not applicable | AD73: Not applicable | AE73: 0 | AF73: 0 | AG73: Comentário 14/11 - Campo com valor fixo de not applicable conforme a especificação funcional. | AH73: OK | AI73: Concluído
A74: =+I74&J74 -> B02.000511_CMMN_DPSTRY_LEI | B74: =+VLOOKUP(I74&J74,[1]Auxiliar!B:C,2,FALSE) -> 2 | C74: =+VLOOKUP(I74&J74,[1]Auxiliar!E:F,2,FALSE) -> 2 | D74: =+VLOOKUP(I74&J74,[1]Auxiliar!H:I,2,FALSE) -> 2 | E74: =+VLOOKUP(I74&J74,[1]Auxiliar!K:L,2,FALSE) -> 2 | F74: =+VLOOKUP(I74&J74,[1]Auxiliar!N:O,2,FALSE) -> 2 | G74: =+VLOOKUP(I74&J74,[1]Auxiliar!Q:R,2,FALSE) -> 2 | H74: =+"c"&LEFT(J74,4) -> c0511 | I74: B02.00 | J74: 0511_CMMN_DPSTRY_LEI | L74: =+VLOOKUP(J74,#REF!,3,FALSE) -> #REF! | N74: 2025-10-31 | O74: 8 | P74: =+IFERROR(VLOOKUP(B74,'[1]ID1&5'!K:L,2,FALSE),"-") -> - | Q74: 0 | R74: =+IFERROR(VLOOKUP(CONCATENATE(A74,$C$10,C74),'[1]ID1&5'!B:J,8,FALSE),"-") -> - | S74: =+IFERROR(VLOOKUP(C74,'[1]ID1&5'!K:L,2,FALSE),"-") -> - | T74: 0 | U74: =+IFERROR(VLOOKUP(D74,'[1]ID1&5'!K:L,2,FALSE),"-") -> - | V74: 0 | W74: =+IFERROR(VLOOKUP(E74,'[1]ID1&5'!K:L,2,FALSE),"-") -> - | X74: 0 | Y74: =+X74/O74 -> 0 | Z74: =+IFERROR(VLOOKUP(F74,'[1]ID1&5'!K:L,2,FALSE),"-") -> - | AA74: 8 | AB74: =+AA74/O74 -> 1 | AC74: Not applicable | AD74: Not applicable | AE74: 0 | AF74: 0 | AG74: Comentário 14/11 - Campo com valor fixo de not applicable conforme a especificação funcional. | AH74: OK | AI74: Concluído
A75: =+I75&J75 -> B02.000520_CMMN_SRVC_PRVDR | B75: =+VLOOKUP(I75&J75,[1]Auxiliar!B:C,2,FALSE) -> 2 | C75: =+VLOOKUP(I75&J75,[1]Auxiliar!E:F,2,FALSE) -> 2 | D75: =+VLOOKUP(I75&J75,[1]Auxiliar!H:I,2,FALSE) -> 2 | E75: =+VLOOKUP(I75&J75,[1]Auxiliar!K:L,2,FALSE) -> 2 | F75: =+VLOOKUP(I75&J75,[1]Auxiliar!N:O,2,FALSE) -> 2 | G75: =+VLOOKUP(I75&J75,[1]Auxiliar!Q:R,2,FALSE) -> 2 | H75: =+"c"&LEFT(J75,4) -> c0520 | I75: B02.00 | J75: 0520_CMMN_SRVC_PRVDR | L75: =+VLOOKUP(J75,#REF!,3,FALSE) -> #REF! | N75: 2025-10-31 | O75: 8 | P75: =+IFERROR(VLOOKUP(B75,'[1]ID1&5'!K:L,2,FALSE),"-") -> - | Q75: 0 | R75: =+IFERROR(VLOOKUP(CONCATENATE(A75,$C$10,C75),'[1]ID1&5'!B:J,8,FALSE),"-") -> - | S75: =+IFERROR(VLOOKUP(C75,'[1]ID1&5'!K:L,2,FALSE),"-") -> - | T75: 0 | U75: =+IFERROR(VLOOKUP(D75,'[1]ID1&5'!K:L,2,FALSE),"-") -> - | V75: 0 | W75: =+IFERROR(VLOOKUP(E75,'[1]ID1&5'!K:L,2,FALSE),"-") -> - | X75: 0 | Y75: =+X75/O75 -> 0 | Z75: =+IFERROR(VLOOKUP(F75,'[1]ID1&5'!K:L,2,FALSE),"-") -> - | AA75: 8 | AB75: =+AA75/O75 -> 1 | AC75: Not applicable | AD75: Not applicable | AE75: 0 | AF75: 0 | AG75: Comentário 14/11 - Campo com valor fixo de not applicable conforme a especificação funcional. | AH75: OK | AI75: Concluído
A76: =+I76&J76 -> B02.000521_CMMN_SRVC_PRVDR_LEI | B76: =+VLOOKUP(I76&J76,[1]Auxiliar!B:C,2,FALSE) -> 2 | C76: =+VLOOKUP(I76&J76,[1]Auxiliar!E:F,2,FALSE) -> 2 | D76: =+VLOOKUP(I76&J76,[1]Auxiliar!H:I,2,FALSE) -> 2 | E76: =+VLOOKUP(I76&J76,[1]Auxiliar!K:L,2,FALSE) -> 2 | F76: =+VLOOKUP(I76&J76,[1]Auxiliar!N:O,2,FALSE) -> 2 | G76: =+VLOOKUP(I76&J76,[1]Auxiliar!Q:R,2,FALSE) -> 2 | H76: =+"c"&LEFT(J76,4) -> c0521 | I76: B02.00 | J76: 0521_CMMN_SRVC_PRVDR_LEI | L76: =+VLOOKUP(J76,#REF!,3,FALSE) -> #REF! | N76: 2025-10-31 | O76: 8 | P76: =+IFERROR(VLOOKUP(B76,'[1]ID1&5'!K:L,2,FALSE),"-") -> - | Q76: 0 | R76: =+IFERROR(VLOOKUP(CONCATENATE(A76,$C$10,C76),'[1]ID1&5'!B:J,8,FALSE),"-") -> - | S76: =+IFERROR(VLOOKUP(C76,'[1]ID1&5'!K:L,2,FALSE),"-") -> - | T76: 0 | U76: =+IFERROR(VLOOKUP(D76,'[1]ID1&5'!K:L,2,FALSE),"-") -> - | V76: 0 | W76: =+IFERROR(VLOOKUP(E76,'[1]ID1&5'!K:L,2,FALSE),"-") -> - | X76: 0 | Y76: =+X76/O76 -> 0 | Z76: =+IFERROR(VLOOKUP(F76,'[1]ID1&5'!K:L,2,FALSE),"-") -> - | AA76: 8 | AB76: =+AA76/O76 -> 1 | AC76: Not applicable | AD76: Not applicable | AE76: 0 | AF76: 0 | AG76: Comentário 14/11 - Campo com valor fixo de not applicable conforme a especificação funcional. | AH76: OK | AI76: Concluído
A77: =+I77&J77 -> B02.000530_TYP_OWN_FNDS_IND_LVL | B77: =+VLOOKUP(I77&J77,[1]Auxiliar!B:C,2,FALSE) -> 2 | C77: =+VLOOKUP(I77&J77,[1]Auxiliar!E:F,2,FALSE) -> 2 | D77: =+VLOOKUP(I77&J77,[1]Auxiliar!H:I,2,FALSE) -> 2 | E77: =+VLOOKUP(I77&J77,[1]Auxiliar!K:L,2,FALSE) -> 2 | F77: =+VLOOKUP(I77&J77,[1]Auxiliar!N:O,2,FALSE) -> 2 | G77: =+VLOOKUP(I77&J77,[1]Auxiliar!Q:R,2,FALSE) -> 2 | H77: =+"c"&LEFT(J77,4) -> c0530 | I77: B02.00 | J77: 0530_TYP_OWN_FNDS_IND_LVL | L77: =+VLOOKUP(J77,#REF!,3,FALSE) -> #REF! | N77: 2025-10-31 | O77: 8 | P77: =+IFERROR(VLOOKUP(B77,'[1]ID1&5'!K:L,2,FALSE),"-") -> - | Q77: 2 | R77: =+IFERROR(VLOOKUP(CONCATENATE(A77,$C$10,C77),'[1]ID1&5'!B:J,8,FALSE),"-") -> - | S77: =+IFERROR(VLOOKUP(C77,'[1]ID1&5'!K:L,2,FALSE),"-") -> - | T77: 0 | U77: =+IFERROR(VLOOKUP(D77,'[1]ID1&5'!K:L,2,FALSE),"-") -> - | V77: 0 | W77: =+IFERROR(VLOOKUP(E77,'[1]ID1&5'!K:L,2,FALSE),"-") -> - | X77: 0 | Y77: =+X77/O77 -> 0 | Z77: =+IFERROR(VLOOKUP(F77,'[1]ID1&5'!K:L,2,FALSE),"-") -> - | AA77: 0 | AB77: =+AA77/O77 -> 0 | AC77: CET1 | AD77: Fully Compliant T2 | AE77: 0 | AF77: 0 | AH77: OK | AI77: Com Incidências
A78: =+I78&J78 -> B02.000540_ELGBL_AMNT_OWN_FNDS_IND_LVL | B78: =+VLOOKUP(I78&J78,[1]Auxiliar!B:C,2,FALSE) -> 2 | C78: =+VLOOKUP(I78&J78,[1]Auxiliar!E:F,2,FALSE) -> 2 | D78: =+VLOOKUP(I78&J78,[1]Auxiliar!H:I,2,FALSE) -> 2 | E78: =+VLOOKUP(I78&J78,[1]Auxiliar!K:L,2,FALSE) -> 2 | F78: =+VLOOKUP(I78&J78,[1]Auxiliar!N:O,2,FALSE) -> 2 | G78: =+VLOOKUP(I78&J78,[1]Auxiliar!Q:R,2,FALSE) -> 2 | H78: =+"c"&LEFT(J78,4) -> c0540 | I78: B02.00 | J78: 0540_ELGBL_AMNT_OWN_FNDS_IND_LVL | L78: =+VLOOKUP(J78,#REF!,3,FALSE) -> #REF! | N78: 2025-10-31 | O78: 8 | P78: =+IFERROR(VLOOKUP(B78,'[1]ID1&5'!K:L,2,FALSE),"-") -> - | Q78: 0 | R78: =+IFERROR(VLOOKUP(CONCATENATE(A78,$C$10,C78),'[1]ID1&5'!B:J,8,FALSE),"-") -> - | S78: =+IFERROR(VLOOKUP(C78,'[1]ID1&5'!K:L,2,FALSE),"-") -> - | T78: 0 | U78: =+IFERROR(VLOOKUP(D78,'[1]ID1&5'!K:L,2,FALSE),"-") -> - | V78: 0 | W78: =+IFERROR(VLOOKUP(E78,'[1]ID1&5'!K:L,2,FALSE),"-") -> - | X78: 0 | Y78: =+X78/O78 -> 0 | Z78: =+IFERROR(VLOOKUP(F78,'[1]ID1&5'!K:L,2,FALSE),"-") -> - | AA78: 0 | AB78: =+AA78/O78 -> 0 | AC78: 0.00 | AD78: 1256723284.00 | AE78: 0 | AF78: 0 | AH78: OK | AI78: Em curso
A79: =+I79&J79 -> B02.000550_TYP_OWN_FNDS_CNSLDTD_LVL | B79: =+VLOOKUP(I79&J79,[1]Auxiliar!B:C,2,FALSE) -> 2 | C79: =+VLOOKUP(I79&J79,[1]Auxiliar!E:F,2,FALSE) -> 2 | D79: =+VLOOKUP(I79&J79,[1]Auxiliar!H:I,2,FALSE) -> 2 | E79: =+VLOOKUP(I79&J79,[1]Auxiliar!K:L,2,FALSE) -> 2 | F79: =+VLOOKUP(I79&J79,[1]Auxiliar!N:O,2,FALSE) -> 2 | G79: =+VLOOKUP(I79&J79,[1]Auxiliar!Q:R,2,FALSE) -> 2 | H79: =+"c"&LEFT(J79,4) -> c0550 | I79: B02.00 | J79: 0550_TYP_OWN_FNDS_CNSLDTD_LVL | L79: =+VLOOKUP(J79,#REF!,3,FALSE) -> #REF! | N79: 2025-10-31 | O79: 8 | P79: =+IFERROR(VLOOKUP(B79,'[1]ID1&5'!K:L,2,FALSE),"-") -> - | Q79: 2 | R79: =+IFERROR(VLOOKUP(CONCATENATE(A79,$C$10,C79),'[1]ID1&5'!B:J,8,FALSE),"-") -> - | S79: =+IFERROR(VLOOKUP(C79,'[1]ID1&5'!K:L,2,FALSE),"-") -> - | T79: 0 | U79: =+IFERROR(VLOOKUP(D79,'[1]ID1&5'!K:L,2,FALSE),"-") -> - | V79: 0 | W79: =+IFERROR(VLOOKUP(E79,'[1]ID1&5'!K:L,2,FALSE),"-") -> - | X79: 0 | Y79: =+X79/O79 -> 0 | Z79: =+IFERROR(VLOOKUP(F79,'[1]ID1&5'!K:L,2,FALSE),"-") -> - | AA79: 0 | AB79: =+AA79/O79 -> 0 | AC79: CET1 | AD79: Fully Compliant T2 | AE79: 0 | AF79: 0 | AH79: OK | AI79: Com Incidências
A80: =+I80&J80 -> B02.000560_ELGBL_AMNT_OWN_FNDS_CNSLDTD_LVL | B80: =+VLOOKUP(I80&J80,[1]Auxiliar!B:C,2,FALSE) -> 2 | C80: =+VLOOKUP(I80&J80,[1]Auxiliar!E:F,2,FALSE) -> 2 | D80: =+VLOOKUP(I80&J80,[1]Auxiliar!H:I,2,FALSE) -> 2 | E80: =+VLOOKUP(I80&J80,[1]Auxiliar!K:L,2,FALSE) -> 2 | F80: =+VLOOKUP(I80&J80,[1]Auxiliar!N:O,2,FALSE) -> 2 | G80: =+VLOOKUP(I80&J80,[1]Auxiliar!Q:R,2,FALSE) -> 2 | H80: =+"c"&LEFT(J80,4) -> c0560 | I80: B02.00 | J80: 0560_ELGBL_AMNT_OWN_FNDS_CNSLDTD_LVL | L80: =+VLOOKUP(J80,#REF!,3,FALSE) -> #REF! | N80: 2025-10-31 | O80: 8 | P80: =+IFERROR(VLOOKUP(B80,'[1]ID1&5'!K:L,2,FALSE),"-") -> - | Q80: 0 | R80: =+IFERROR(VLOOKUP(CONCATENATE(A80,$C$10,C80),'[1]ID1&5'!B:J,8,FALSE),"-") -> - | S80: =+IFERROR(VLOOKUP(C80,'[1]ID1&5'!K:L,2,FALSE),"-") -> - | T80: 0 | U80: =+IFERROR(VLOOKUP(D80,'[1]ID1&5'!K:L,2,FALSE),"-") -> - | V80: 0 | W80: =+IFERROR(VLOOKUP(E80,'[1]ID1&5'!K:L,2,FALSE),"-") -> - | X80: 0 | Y80: =+X80/O80 -> 0 | Z80: =+IFERROR(VLOOKUP(F80,'[1]ID1&5'!K:L,2,FALSE),"-") -> - | AA80: 0 | AB80: =+AA80/O80 -> 0 | AC80: 0.00 | AD80: 1256723284.00 | AE80: 0 | AF80: 0 | AH80: OK | AI80: Concluído
A81: =+I81&J81 -> B02.000570_AMNT_SCRTY_INTRST_PRVDD | B81: =+VLOOKUP(I81&J81,[1]Auxiliar!B:C,2,FALSE) -> 2 | C81: =+VLOOKUP(I81&J81,[1]Auxiliar!E:F,2,FALSE) -> 2 | D81: =+VLOOKUP(I81&J81,[1]Auxiliar!H:I,2,FALSE) -> 2 | E81: =+VLOOKUP(I81&J81,[1]Auxiliar!K:L,2,FALSE) -> 2 | F81: =+VLOOKUP(I81&J81,[1]Auxiliar!N:O,2,FALSE) -> 2 | G81: =+VLOOKUP(I81&J81,[1]Auxiliar!Q:R,2,FALSE) -> 2 | H81: =+"c"&LEFT(J81,4) -> c0570 | I81: B02.00 | J81: 0570_AMNT_SCRTY_INTRST_PRVDD | L81: =+VLOOKUP(J81,#REF!,3,FALSE) -> #REF! | N81: 2025-10-31 | O81: 8 | P81: =+IFERROR(VLOOKUP(B81,'[1]ID1&5'!K:L,2,FALSE),"-") -> - | Q81: 0 | R81: =+IFERROR(VLOOKUP(CONCATENATE(A81,$C$10,C81),'[1]ID1&5'!B:J,8,FALSE),"-") -> - | S81: =+IFERROR(VLOOKUP(C81,'[1]ID1&5'!K:L,2,FALSE),"-") -> - | T81: 0 | U81: =+IFERROR(VLOOKUP(D81,'[1]ID1&5'!K:L,2,FALSE),"-") -> - | V81: 0 | W81: =+IFERROR(VLOOKUP(E81,'[1]ID1&5'!K:L,2,FALSE),"-") -> - | X81: 0 | Y81: =+X81/O81 -> 0 | Z81: =+IFERROR(VLOOKUP(F81,'[1]ID1&5'!K:L,2,FALSE),"-") -> - | AA81: 0 | AB81: =+AA81/O81 -> 0 | AC81: 0.00 | AD81: 0.00 | AE81: 0 | AF81: 0 | AG81: Comentário 14/11 - Campo com valor fixo de not applicable conforme a especificação funcional. | AH81: OK | AI81: Concluído
A82: =+I82&J82 -> B02.000580_SCRTY_INTRST_PRVDR | B82: =+VLOOKUP(I82&J82,[1]Auxiliar!B:C,2,FALSE) -> 2 | C82: =+VLOOKUP(I82&J82,[1]Auxiliar!E:F,2,FALSE) -> 2 | D82: =+VLOOKUP(I82&J82,[1]Auxiliar!H:I,2,FALSE) -> 2 | E82: =+VLOOKUP(I82&J82,[1]Auxiliar!K:L,2,FALSE) -> 2 | F82: =+VLOOKUP(I82&J82,[1]Auxiliar!N:O,2,FALSE) -> 2 | G82: =+VLOOKUP(I82&J82,[1]Auxiliar!Q:R,2,FALSE) -> 2 | H82: =+"c"&LEFT(J82,4) -> c0580 | I82: B02.00 | J82: 0580_SCRTY_INTRST_PRVDR | L82: =+VLOOKUP(J82,#REF!,3,FALSE) -> #REF! | N82: 2025-10-31 | O82: 8 | P82: =+IFERROR(VLOOKUP(B82,'[1]ID1&5'!K:L,2,FALSE),"-") -> - | Q82: 0 | R82: =+IFERROR(VLOOKUP(CONCATENATE(A82,$C$10,C82),'[1]ID1&5'!B:J,8,FALSE),"-") -> - | S82: =+IFERROR(VLOOKUP(C82,'[1]ID1&5'!K:L,2,FALSE),"-") -> - | T82: 0 | U82: =+IFERROR(VLOOKUP(D82,'[1]ID1&5'!K:L,2,FALSE),"-") -> - | V82: 0 | W82: =+IFERROR(VLOOKUP(E82,'[1]ID1&5'!K:L,2,FALSE),"-") -> - | X82: 0 | Y82: =+X82/O82 -> 0 | Z82: =+IFERROR(VLOOKUP(F82,'[1]ID1&5'!K:L,2,FALSE),"-") -> - | AA82: 8 | AB82: =+AA82/O82 -> 1 | AC82: Not applicable | AD82: Not applicable | AE82: 0 | AF82: 0 | AG82: Comentário 14/11 - Campo com valor fixo de not applicable conforme a especificação funcional. | AH82: OK | AI82: Concluído
A83: =+I83&J83 -> B02.000581_SCRTY_INTRST_PRVDR_LEI | B83: =+VLOOKUP(I83&J83,[1]Auxiliar!B:C,2,FALSE) -> 2 | C83: =+VLOOKUP(I83&J83,[1]Auxiliar!E:F,2,FALSE) -> 2 | D83: =+VLOOKUP(I83&J83,[1]Auxiliar!H:I,2,FALSE) -> 2 | E83: =+VLOOKUP(I83&J83,[1]Auxiliar!K:L,2,FALSE) -> 2 | F83: =+VLOOKUP(I83&J83,[1]Auxiliar!N:O,2,FALSE) -> 2 | G83: =+VLOOKUP(I83&J83,[1]Auxiliar!Q:R,2,FALSE) -> 2 | H83: =+"c"&LEFT(J83,4) -> c0581 | I83: B02.00 | J83: 0581_SCRTY_INTRST_PRVDR_LEI | L83: =+VLOOKUP(J83,#REF!,3,FALSE) -> #REF! | N83: 2025-10-31 | O83: 8 | P83: =+IFERROR(VLOOKUP(B83,'[1]ID1&5'!K:L,2,FALSE),"-") -> - | Q83: 0 | R83: =+IFERROR(VLOOKUP(CONCATENATE(A83,$C$10,C83),'[1]ID1&5'!B:J,8,FALSE),"-") -> - | S83: =+IFERROR(VLOOKUP(C83,'[1]ID1&5'!K:L,2,FALSE),"-") -> - | T83: 0 | U83: =+IFERROR(VLOOKUP(D83,'[1]ID1&5'!K:L,2,FALSE),"-") -> - | V83: 0 | W83: =+IFERROR(VLOOKUP(E83,'[1]ID1&5'!K:L,2,FALSE),"-") -> - | X83: 0 | Y83: =+X83/O83 -> 0 | Z83: =+IFERROR(VLOOKUP(F83,'[1]ID1&5'!K:L,2,FALSE),"-") -> - | AA83: 8 | AB83: =+AA83/O83 -> 1 | AC83: Not applicable | AD83: Not applicable | AE83: 0 | AF83: 0 | AG83: Comentário 14/11 - Campo com valor fixo de not applicable conforme a especificação funcional. | AH83: OK | AI83: Concluído
A84: =+I84&J84 -> B02.000590_TYP_SCRTY_INTRST_PRVDD | B84: =+VLOOKUP(I84&J84,[1]Auxiliar!B:C,2,FALSE) -> 2 | C84: =+VLOOKUP(I84&J84,[1]Auxiliar!E:F,2,FALSE) -> 2 | D84: =+VLOOKUP(I84&J84,[1]Auxiliar!H:I,2,FALSE) -> 2 | E84: =+VLOOKUP(I84&J84,[1]Auxiliar!K:L,2,FALSE) -> 2 | F84: =+VLOOKUP(I84&J84,[1]Auxiliar!N:O,2,FALSE) -> 2 | G84: =+VLOOKUP(I84&J84,[1]Auxiliar!Q:R,2,FALSE) -> 2 | H84: =+"c"&LEFT(J84,4) -> c0590 | I84: B02.00 | J84: 0590_TYP_SCRTY_INTRST_PRVDD | L84: =+VLOOKUP(J84,#REF!,3,FALSE) -> #REF! | N84: 2025-10-31 | O84: 8 | P84: =+IFERROR(VLOOKUP(B84,'[1]ID1&5'!K:L,2,FALSE),"-") -> - | Q84: 0 | R84: =+IFERROR(VLOOKUP(CONCATENATE(A84,$C$10,C84),'[1]ID1&5'!B:J,8,FALSE),"-") -> - | S84: =+IFERROR(VLOOKUP(C84,'[1]ID1&5'!K:L,2,FALSE),"-") -> - | T84: 0 | U84: =+IFERROR(VLOOKUP(D84,'[1]ID1&5'!K:L,2,FALSE),"-") -> - | V84: 0 | W84: =+IFERROR(VLOOKUP(E84,'[1]ID1&5'!K:L,2,FALSE),"-") -> - | X84: 0 | Y84: =+X84/O84 -> 0 | Z84: =+IFERROR(VLOOKUP(F84,'[1]ID1&5'!K:L,2,FALSE),"-") -> - | AA84: 8 | AB84: =+AA84/O84 -> 1 | AC84: Not applicable | AD84: Not applicable | AE84: 0 | AF84: 0 | AG84: Comentário 14/11 - Campo com valor fixo de not applicable conforme a especificação funcional. | AH84: OK | AI84: Concluído
A85: =+I85&J85 -> B02.000600_FLG_CLLTRL_ASST_PSTN | B85: =+VLOOKUP(I85&J85,[1]Auxiliar!B:C,2,FALSE) -> 2 | C85: =+VLOOKUP(I85&J85,[1]Auxiliar!E:F,2,FALSE) -> 2 | D85: =+VLOOKUP(I85&J85,[1]Auxiliar!H:I,2,FALSE) -> 2 | E85: =+VLOOKUP(I85&J85,[1]Auxiliar!K:L,2,FALSE) -> 2 | F85: =+VLOOKUP(I85&J85,[1]Auxiliar!N:O,2,FALSE) -> 2 | G85: =+VLOOKUP(I85&J85,[1]Auxiliar!Q:R,2,FALSE) -> 2 | H85: =+"c"&LEFT(J85,4) -> c0600 | I85: B02.00 | J85: 0600_FLG_CLLTRL_ASST_PSTN | L85: =+VLOOKUP(J85,#REF!,3,FALSE) -> #REF! | N85: 2025-10-31 | O85: 8 | P85: =+IFERROR(VLOOKUP(B85,'[1]ID1&5'!K:L,2,FALSE),"-") -> - | Q85: 0 | R85: =+IFERROR(VLOOKUP(CONCATENATE(A85,$C$10,C85),'[1]ID1&5'!B:J,8,FALSE),"-") -> - | S85: =+IFERROR(VLOOKUP(C85,'[1]ID1&5'!K:L,2,FALSE),"-") -> - | T85: 0 | U85: =+IFERROR(VLOOKUP(D85,'[1]ID1&5'!K:L,2,FALSE),"-") -> - | V85: 0 | W85: =+IFERROR(VLOOKUP(E85,'[1]ID1&5'!K:L,2,FALSE),"-") -> - | X85: 0 | Y85: =+X85/O85 -> 0 | Z85: =+IFERROR(VLOOKUP(F85,'[1]ID1&5'!K:L,2,FALSE),"-") -> - | AA85: 0 | AB85: =+AA85/O85 -> 0 | AC85: FALSE | AD85: FALSE | AE85: 0 | AF85: 0 | AG85: Comentário 14/11 - Campo com valor fixo de not applicable conforme a especificação funcional. | AH85: OK | AI85: Concluído
A86: =+I86&J86 -> B02.000610_CRRYNG_AMNT_IFRS | B86: =+VLOOKUP(I86&J86,[1]Auxiliar!B:C,2,FALSE) -> 2 | C86: =+VLOOKUP(I86&J86,[1]Auxiliar!E:F,2,FALSE) -> 2 | D86: =+VLOOKUP(I86&J86,[1]Auxiliar!H:I,2,FALSE) -> 2 | E86: =+VLOOKUP(I86&J86,[1]Auxiliar!K:L,2,FALSE) -> 2 | F86: =+VLOOKUP(I86&J86,[1]Auxiliar!N:O,2,FALSE) -> 2 | G86: =+VLOOKUP(I86&J86,[1]Auxiliar!Q:R,2,FALSE) -> 2 | H86: =+"c"&LEFT(J86,4) -> c0610 | I86: B02.00 | J86: 0610_CRRYNG_AMNT_IFRS | L86: =+VLOOKUP(J86,#REF!,3,FALSE) -> #REF! | N86: 2025-10-31 | O86: 8 | P86: =+IFERROR(VLOOKUP(B86,'[1]ID1&5'!K:L,2,FALSE),"-") -> - | Q86: 0 | R86: =+IFERROR(VLOOKUP(CONCATENATE(A86,$C$10,C86),'[1]ID1&5'!B:J,8,FALSE),"-") -> - | S86: =+IFERROR(VLOOKUP(C86,'[1]ID1&5'!K:L,2,FALSE),"-") -> - | T86: 0 | U86: =+IFERROR(VLOOKUP(D86,'[1]ID1&5'!K:L,2,FALSE),"-") -> - | V86: 0 | W86: =+IFERROR(VLOOKUP(E86,'[1]ID1&5'!K:L,2,FALSE),"-") -> - | X86: 0 | Y86: =+X86/O86 -> 0 | Z86: =+IFERROR(VLOOKUP(F86,'[1]ID1&5'!K:L,2,FALSE),"-") -> - | AA86: 0 | AB86: =+AA86/O86 -> 0 | AC86: 7639597.4 | AD86: 1372632707.59 | AE86: 0 | AF86: 0 | AH86: OK | AI86: Em curso
A87: =+I87&J87 -> B02.000620_BLNC_SHT_IFRS | B87: =+VLOOKUP(I87&J87,[1]Auxiliar!B:C,2,FALSE) -> 2 | C87: =+VLOOKUP(I87&J87,[1]Auxiliar!E:F,2,FALSE) -> 2 | D87: =+VLOOKUP(I87&J87,[1]Auxiliar!H:I,2,FALSE) -> 2 | E87: =+VLOOKUP(I87&J87,[1]Auxiliar!K:L,2,FALSE) -> 2 | F87: =+VLOOKUP(I87&J87,[1]Auxiliar!N:O,2,FALSE) -> 2 | G87: =+VLOOKUP(I87&J87,[1]Auxiliar!Q:R,2,FALSE) -> 2 | H87: =+"c"&LEFT(J87,4) -> c0620 | I87: B02.00 | J87: 0620_BLNC_SHT_IFRS | L87: =+VLOOKUP(J87,#REF!,3,FALSE) -> #REF! | N87: 2025-10-31 | O87: 8 | P87: =+IFERROR(VLOOKUP(B87,'[1]ID1&5'!K:L,2,FALSE),"-") -> - | Q87: 0 | R87: =+IFERROR(VLOOKUP(CONCATENATE(A87,$C$10,C87),'[1]ID1&5'!B:J,8,FALSE),"-") -> - | S87: =+IFERROR(VLOOKUP(C87,'[1]ID1&5'!K:L,2,FALSE),"-") -> - | T87: 0 | U87: =+IFERROR(VLOOKUP(D87,'[1]ID1&5'!K:L,2,FALSE),"-") -> - | V87: 0 | W87: =+IFERROR(VLOOKUP(E87,'[1]ID1&5'!K:L,2,FALSE),"-") -> - | X87: 0 | Y87: =+X87/O87 -> 0 | Z87: =+IFERROR(VLOOKUP(F87,'[1]ID1&5'!K:L,2,FALSE),"-") -> - | AA87: 0 | AB87: =+AA87/O87 -> 0 | AC87: 110 Financial liabilities at amortized cost | AD87: 300 Total equity | AE87: 0 | AF87: 0 | AH87: OK | AI87: Com Incidências
A88: =+I88&J88 -> B02.000630_CRRYING_AMNT_NGAAP | B88: =+VLOOKUP(I88&J88,[1]Auxiliar!B:C,2,FALSE) -> 2 | C88: =+VLOOKUP(I88&J88,[1]Auxiliar!E:F,2,FALSE) -> 2 | D88: =+VLOOKUP(I88&J88,[1]Auxiliar!H:I,2,FALSE) -> 2 | E88: =+VLOOKUP(I88&J88,[1]Auxiliar!K:L,2,FALSE) -> 2 | F88: =+VLOOKUP(I88&J88,[1]Auxiliar!N:O,2,FALSE) -> 2 | G88: =+VLOOKUP(I88&J88,[1]Auxiliar!Q:R,2,FALSE) -> 2 | H88: =+"c"&LEFT(J88,4) -> c0630 | I88: B02.00 | J88: 0630_CRRYING_AMNT_NGAAP | L88: =+VLOOKUP(J88,#REF!,3,FALSE) -> #REF! | N88: 2025-10-31 | O88: 8 | P88: =+IFERROR(VLOOKUP(B88,'[1]ID1&5'!K:L,2,FALSE),"-") -> - | Q88: 0 | R88: =+IFERROR(VLOOKUP(CONCATENATE(A88,$C$10,C88),'[1]ID1&5'!B:J,8,FALSE),"-") -> - | S88: =+IFERROR(VLOOKUP(C88,'[1]ID1&5'!K:L,2,FALSE),"-") -> - | T88: 0 | U88: =+IFERROR(VLOOKUP(D88,'[1]ID1&5'!K:L,2,FALSE),"-") -> - | V88: 0 | W88: =+IFERROR(VLOOKUP(E88,'[1]ID1&5'!K:L,2,FALSE),"-") -> - | X88: 0 | Y88: =+X88/O88 -> 0 | Z88: =+IFERROR(VLOOKUP(F88,'[1]ID1&5'!K:L,2,FALSE),"-") -> - | AA88: 8 | AB88: =+AA88/O88 -> 1 | AC88: 999999999999999.00 | AD88: 999999999999999.00 | AE88: 0 | AF88: 0 | AG88: Comentário 14/11 - Campo com valor fixo de not applicable conforme a especificação funcional. | AH88: OK | AI88: Concluído
A89: =+I89&J89 -> B02.000640_BLNC_SHT_NGAAP | B89: =+VLOOKUP(I89&J89,[1]Auxiliar!B:C,2,FALSE) -> 2 | C89: =+VLOOKUP(I89&J89,[1]Auxiliar!E:F,2,FALSE) -> 2 | D89: =+VLOOKUP(I89&J89,[1]Auxiliar!H:I,2,FALSE) -> 2 | E89: =+VLOOKUP(I89&J89,[1]Auxiliar!K:L,2,FALSE) -> 2 | F89: =+VLOOKUP(I89&J89,[1]Auxiliar!N:O,2,FALSE) -> 2 | G89: =+VLOOKUP(I89&J89,[1]Auxiliar!Q:R,2,FALSE) -> 2 | H89: =+"c"&LEFT(J89,4) -> c0640 | I89: B02.00 | J89: 0640_BLNC_SHT_NGAAP | L89: =+VLOOKUP(J89,#REF!,3,FALSE) -> #REF! | N89: 2025-10-31 | O89: 8 | P89: =+IFERROR(VLOOKUP(B89,'[1]ID1&5'!K:L,2,FALSE),"-") -> - | Q89: 0 | R89: =+IFERROR(VLOOKUP(CONCATENATE(A89,$C$10,C89),'[1]ID1&5'!B:J,8,FALSE),"-") -> - | S89: =+IFERROR(VLOOKUP(C89,'[1]ID1&5'!K:L,2,FALSE),"-") -> - | T89: 0 | U89: =+IFERROR(VLOOKUP(D89,'[1]ID1&5'!K:L,2,FALSE),"-") -> - | V89: 0 | W89: =+IFERROR(VLOOKUP(E89,'[1]ID1&5'!K:L,2,FALSE),"-") -> - | X89: 0 | Y89: =+X89/O89 -> 0 | Z89: =+IFERROR(VLOOKUP(F89,'[1]ID1&5'!K:L,2,FALSE),"-") -> - | AA89: 8 | AB89: =+AA89/O89 -> 1 | AC89: Not applicable | AD89: Not applicable | AE89: 0 | AF89: 0 | AG89: Comentário 14/11 - Campo com valor fixo de not applicable conforme a especificação funcional. | AH89: OK | AI89: Concluído
A90: =+I90&J90 -> B02.005000_FLG_SHRHLDR_NOT_RSLTN_GRP | B90: =+VLOOKUP(I90&J90,[1]Auxiliar!B:C,2,FALSE) -> 2 | C90: =+VLOOKUP(I90&J90,[1]Auxiliar!E:F,2,FALSE) -> 2 | D90: =+VLOOKUP(I90&J90,[1]Auxiliar!H:I,2,FALSE) -> 2 | E90: =+VLOOKUP(I90&J90,[1]Auxiliar!K:L,2,FALSE) -> 2 | F90: =+VLOOKUP(I90&J90,[1]Auxiliar!N:O,2,FALSE) -> 2 | G90: =+VLOOKUP(I90&J90,[1]Auxiliar!Q:R,2,FALSE) -> 2 | H90: =+"c"&LEFT(J90,4) -> c5000 | I90: B02.00 | J90: 5000_FLG_SHRHLDR_NOT_RSLTN_GRP | L90: =+VLOOKUP(J90,#REF!,3,FALSE) -> #REF! | N90: 2025-10-31 | O90: 8 | P90: =+IFERROR(VLOOKUP(B90,'[1]ID1&5'!K:L,2,FALSE),"-") -> - | Q90: 0 | R90: =+IFERROR(VLOOKUP(CONCATENATE(A90,$C$10,C90),'[1]ID1&5'!B:J,8,FALSE),"-") -> - | S90: =+IFERROR(VLOOKUP(C90,'[1]ID1&5'!K:L,2,FALSE),"-") -> - | T90: 0 | U90: =+IFERROR(VLOOKUP(D90,'[1]ID1&5'!K:L,2,FALSE),"-") -> - | V90: 0 | W90: =+IFERROR(VLOOKUP(E90,'[1]ID1&5'!K:L,2,FALSE),"-") -> - | X90: 0 | Y90: =+X90/O90 -> 0 | Z90: =+IFERROR(VLOOKUP(F90,'[1]ID1&5'!K:L,2,FALSE),"-") -> - | AA90: 0 | AB90: =+AA90/O90 -> 0 | AC90: FALSE | AD90: FALSE | AE90: 0 | AF90: 0 | AG90: Comentário 14/11 - Campo com valor fixo de not applicable conforme a especificação funcional. | AH90: OK | AI90: Concluído
A91: =+I91&J91 -> B02.005010_FLG_ART21_7A_SRMR | B91: =+VLOOKUP(I91&J91,[1]Auxiliar!B:C,2,FALSE) -> 2 | C91: =+VLOOKUP(I91&J91,[1]Auxiliar!E:F,2,FALSE) -> 2 | D91: =+VLOOKUP(I91&J91,[1]Auxiliar!H:I,2,FALSE) -> 2 | E91: =+VLOOKUP(I91&J91,[1]Auxiliar!K:L,2,FALSE) -> 2 | F91: =+VLOOKUP(I91&J91,[1]Auxiliar!N:O,2,FALSE) -> 2 | G91: =+VLOOKUP(I91&J91,[1]Auxiliar!Q:R,2,FALSE) -> 2 | H91: =+"c"&LEFT(J91,4) -> c5010 | I91: B02.00 | J91: 5010_FLG_ART21_7A_SRMR | L91: =+VLOOKUP(J91,#REF!,3,FALSE) -> #REF! | N91: 2025-10-31 | O91: 8 | P91: =+IFERROR(VLOOKUP(B91,'[1]ID1&5'!K:L,2,FALSE),"-") -> - | Q91: 0 | R91: =+IFERROR(VLOOKUP(CONCATENATE(A91,$C$10,C91),'[1]ID1&5'!B:J,8,FALSE),"-") -> - | S91: =+IFERROR(VLOOKUP(C91,'[1]ID1&5'!K:L,2,FALSE),"-") -> - | T91: 0 | U91: =+IFERROR(VLOOKUP(D91,'[1]ID1&5'!K:L,2,FALSE),"-") -> - | V91: 0 | W91: =+IFERROR(VLOOKUP(E91,'[1]ID1&5'!K:L,2,FALSE),"-") -> - | X91: 0 | Y91: =+X91/O91 -> 0 | Z91: =+IFERROR(VLOOKUP(F91,'[1]ID1&5'!K:L,2,FALSE),"-") -> - | AA91: 0 | AB91: =+AA91/O91 -> 0 | AC91: TRUE | AD91: TRUE | AE91: 0 | AF91: 0 | AG91: Comentário 14/11 - Campo com valor fixo de not applicable conforme a especificação funcional. | AH91: OK | AI91: Concluído
H92: =+"c"&LEFT(J92,4) -> c0010 | I92: B90.00 | J92: 0010_ROW_NMBR | L92: =+VLOOKUP(J92,#REF!,3,FALSE) -> #REF! | N92: 2025-10-31 | O92: 10 | P92: =+IFERROR(VLOOKUP(B92,'[1]ID1&5'!K:L,2,FALSE),"-") -> - | Q92: 0 | R92: =+IFERROR(VLOOKUP(CONCATENATE(A92,$C$10,C92),'[1]ID1&5'!B:J,8,FALSE),"-") -> - | S92: =+IFERROR(VLOOKUP(C92,'[1]ID1&5'!K:L,2,FALSE),"-") -> - | T92: 0 | U92: =+IFERROR(VLOOKUP(D92,'[1]ID1&5'!K:L,2,FALSE),"-") -> - | V92: 0 | W92: =+IFERROR(VLOOKUP(E92,'[1]ID1&5'!K:L,2,FALSE),"-") -> - | X92: 0 | Y92: =+X92/O92 -> 0 | Z92: =+IFERROR(VLOOKUP(F92,'[1]ID1&5'!K:L,2,FALSE),"-") -> - | AA92: 0 | AB92: =+AA92/O92 -> 0 | AC92: 1 | AD92: 10 | AE92: 0 | AF92: 0 | AH92: OK | AI92: Concluído
H93: =+"c"&LEFT(J93,4) -> c0011 | I93: B90.00 | J93: 0011_TAB_ORIGIN | N93: 2025-10-31 | O93: 10 | P93: =+IFERROR(VLOOKUP(B93,'[1]ID1&5'!K:L,2,FALSE),"-") -> - | Q93: 0 | R93: =+IFERROR(VLOOKUP(CONCATENATE(A93,$C$10,C93),'[1]ID1&5'!B:J,8,FALSE),"-") -> - | S93: =+IFERROR(VLOOKUP(C93,'[1]ID1&5'!K:L,2,FALSE),"-") -> - | T93: 0 | U93: =+IFERROR(VLOOKUP(D93,'[1]ID1&5'!K:L,2,FALSE),"-") -> - | V93: 0 | W93: =+IFERROR(VLOOKUP(E93,'[1]ID1&5'!K:L,2,FALSE),"-") -> - | X93: 0 | Y93: =+X93/O93 -> 0 | Z93: =+IFERROR(VLOOKUP(F93,'[1]ID1&5'!K:L,2,FALSE),"-") -> - | AA93: 0 | AB93: =+AA93/O93 -> 0 | AC93: B0200 | AD93: B0200 | AE93: 0 | AF93: 0 | AH93: OK | AI93: Concluído
H94: =+"c"&LEFT(J94,4) -> c0020 | I94: B90.00 | J94: 0020_UNIQ_ID_KNWN_CNTRPRTY | N94: 2025-10-31 | O94: 10 | P94: =+IFERROR(VLOOKUP(B94,'[1]ID1&5'!K:L,2,FALSE),"-") -> - | Q94: 0 | R94: =+IFERROR(VLOOKUP(CONCATENATE(A94,$C$10,C94),'[1]ID1&5'!B:J,8,FALSE),"-") -> - | S94: =+IFERROR(VLOOKUP(C94,'[1]ID1&5'!K:L,2,FALSE),"-") -> - | T94: 0 | U94: =+IFERROR(VLOOKUP(D94,'[1]ID1&5'!K:L,2,FALSE),"-") -> - | V94: 0 | W94: =+IFERROR(VLOOKUP(E94,'[1]ID1&5'!K:L,2,FALSE),"-") -> - | X94: 0 | Y94: =+X94/O94 -> 0 | Z94: =+IFERROR(VLOOKUP(F94,'[1]ID1&5'!K:L,2,FALSE),"-") -> - | AA94: 0 | AB94: =+AA94/O94 -> 0 | AC94: PTBSRDOM0037 | AD94: PTSTOHOM0002 | AE94: 0 | AF94: 0 | AH94: OK | AI94: Concluído
H95: =+"c"&LEFT(J95,4) -> c0030 | I95: B90.00 | J95: 0030_CNTRPRTY_RSLTN_GRP | N95: 2025-10-31 | O95: 10 | P95: =+IFERROR(VLOOKUP(B95,'[1]ID1&5'!K:L,2,FALSE),"-") -> - | Q95: 10 | R95: =+IFERROR(VLOOKUP(CONCATENATE(A95,$C$10,C95),'[1]ID1&5'!B:J,8,FALSE),"-") -> - | S95: =+IFERROR(VLOOKUP(C95,'[1]ID1&5'!K:L,2,FALSE),"-") -> - | T95: 0 | U95: =+IFERROR(VLOOKUP(D95,'[1]ID1&5'!K:L,2,FALSE),"-") -> - | V95: 0 | W95: =+IFERROR(VLOOKUP(E95,'[1]ID1&5'!K:L,2,FALSE),"-") -> - | X95: 0 | Y95: =+X95/O95 -> 0 | Z95: =+IFERROR(VLOOKUP(F95,'[1]ID1&5'!K:L,2,FALSE),"-") -> - | AA95: 0 | AB95: =+AA95/O95 -> 0 | AC95: Intragroup and intra-resolution group | AD95: No | AE95: 0 | AF95: 0 | AH95: OK | AI95: Concluído
H96: =+"c"&LEFT(J96,4) -> c0040 | I96: B90.00 | J96: 0040_CNTRPRTY_NM | N96: 2025-10-31 | O96: 10 | P96: =+IFERROR(VLOOKUP(B96,'[1]ID1&5'!K:L,2,FALSE),"-") -> - | Q96: 10 | R96: =+IFERROR(VLOOKUP(CONCATENATE(A96,$C$10,C96),'[1]ID1&5'!B:J,8,FALSE),"-") -> - | S96: =+IFERROR(VLOOKUP(C96,'[1]ID1&5'!K:L,2,FALSE),"-") -> - | T96: 0 | U96: =+IFERROR(VLOOKUP(D96,'[1]ID1&5'!K:L,2,FALSE),"-") -> - | V96: 0 | W96: =+IFERROR(VLOOKUP(E96,'[1]ID1&5'!K:L,2,FALSE),"-") -> - | X96: 0 | Y96: =+X96/O96 -> 0 | Z96: =+IFERROR(VLOOKUP(F96,'[1]ID1&5'!K:L,2,FALSE),"-") -> - | AA96: 2 | AB96: =+AA96/O96 -> 0.2 | AC96: BANCO SANTANDER SA | AD96: Not applicable | AE96: 0 | AF96: 0 | AG96: Comentário 14/11 - Os registos são classificados como não aplicável por serem relativos à entidade de ajustes '0000000000'. | AH96: OK | AI96: Concluído
H97: =+"c"&LEFT(J97,4) -> c0050 | I97: B90.00 | J97: 0050_CNTRPRTY_LEI | N97: 2025-10-31 | O97: 10 | P97: =+IFERROR(VLOOKUP(B97,'[1]ID1&5'!K:L,2,FALSE),"-") -> - | Q97: 10 | R97: =+IFERROR(VLOOKUP(CONCATENATE(A97,$C$10,C97),'[1]ID1&5'!B:J,8,FALSE),"-") -> - | S97: =+IFERROR(VLOOKUP(C97,'[1]ID1&5'!K:L,2,FALSE),"-") -> - | T97: 0 | U97: =+IFERROR(VLOOKUP(D97,'[1]ID1&5'!K:L,2,FALSE),"-") -> - | V97: 0 | W97: =+IFERROR(VLOOKUP(E97,'[1]ID1&5'!K:L,2,FALSE),"-") -> - | X97: 0 | Y97: =+X97/O97 -> 0 | Z97: =+IFERROR(VLOOKUP(F97,'[1]ID1&5'!K:L,2,FALSE),"-") -> - | AA97: 2 | AB97: =+AA97/O97 -> 0.2 | AC97: 549300URJH9VSI58CS32 | AD97: Not applicable | AE97: 0 | AF97: 0 | AG97: Comentário 14/11 - Os registos são classificados como não aplicável por serem relativos à entidade de ajustes '0000000000'. | AH97: OK | AI97: Concluído
H98: =+"c"&LEFT(J98,4) -> c0060 | I98: B90.00 | J98: 0060_TYP_CNTRPRTY_ID | N98: 2025-10-31 | O98: 10 | P98: =+IFERROR(VLOOKUP(B98,'[1]ID1&5'!K:L,2,FALSE),"-") -> - | Q98: 2 | R98: =+IFERROR(VLOOKUP(CONCATENATE(A98,$C$10,C98),'[1]ID1&5'!B:J,8,FALSE),"-") -> - | S98: =+IFERROR(VLOOKUP(C98,'[1]ID1&5'!K:L,2,FALSE),"-") -> - | T98: 0 | U98: =+IFERROR(VLOOKUP(D98,'[1]ID1&5'!K:L,2,FALSE),"-") -> - | V98: 0 | W98: =+IFERROR(VLOOKUP(E98,'[1]ID1&5'!K:L,2,FALSE),"-") -> - | X98: 0 | Y98: =+X98/O98 -> 0 | Z98: =+IFERROR(VLOOKUP(F98,'[1]ID1&5'!K:L,2,FALSE),"-") -> - | AA98: 2 | AB98: =+AA98/O98 -> 0.2 | AC98: LEI | AD98: Not applicable | AE98: 0 | AF98: 0 | AG98: Comentário 14/11 - Os registos são classificados como não aplicável por serem relativos à entidade de ajustes '0000000000'. | AH98: OK | AI98: Concluído
H99: =+"c"&LEFT(J99,4) -> c0070 | I99: B90.00 | J99: 0070_CNTRPRTY_ID | N99: 2025-10-31 | O99: 10 | P99: =+IFERROR(VLOOKUP(B99,'[1]ID1&5'!K:L,2,FALSE),"-") -> - | Q99: 0 | R99: =+IFERROR(VLOOKUP(CONCATENATE(A99,$C$10,C99),'[1]ID1&5'!B:J,8,FALSE),"-") -> - | S99: =+IFERROR(VLOOKUP(C99,'[1]ID1&5'!K:L,2,FALSE),"-") -> - | T99: 0 | U99: =+IFERROR(VLOOKUP(D99,'[1]ID1&5'!K:L,2,FALSE),"-") -> - | V99: 0 | W99: =+IFERROR(VLOOKUP(E99,'[1]ID1&5'!K:L,2,FALSE),"-") -> - | X99: 0 | Y99: =+X99/O99 -> 0 | Z99: =+IFERROR(VLOOKUP(F99,'[1]ID1&5'!K:L,2,FALSE),"-") -> - | AA99: 2 | AB99: =+AA99/O99 -> 0.2 | AC99: 0000003686 | AD99: Not applicable | AE99: 0 | AF99: 1 | AG99: Comentário 14/11 - Os registos são classificados como não aplicável por serem relativos à entidade de ajustes '0000000000'. | AH99: OK | AI99: Concluído
H100: =+"c"&LEFT(J100,4) -> c0080 | I100: B90.00 | J100: 0080_CNTRPRTY_TYP | N100: 2025-10-31 | O100: 10 | P100: =+IFERROR(VLOOKUP(B100,'[1]ID1&5'!K:L,2,FALSE),"-") -> - | Q100: 10 | R100: =+IFERROR(VLOOKUP(CONCATENATE(A100,$C$10,C100),'[1]ID1&5'!B:J,8,FALSE),"-") -> - | S100: =+IFERROR(VLOOKUP(C100,'[1]ID1&5'!K:L,2,FALSE),"-") -> - | T100: 0 | U100: =+IFERROR(VLOOKUP(D100,'[1]ID1&5'!K:L,2,FALSE),"-") -> - | V100: 0 | W100: =+IFERROR(VLOOKUP(E100,'[1]ID1&5'!K:L,2,FALSE),"-") -> - | X100: 0 | Y100: =+X100/O100 -> 0 | Z100: =+IFERROR(VLOOKUP(F100,'[1]ID1&5'!K:L,2,FALSE),"-") -> - | AA100: 0 | AB100: =+AA100/O100 -> 0 | AC100: Institutions | AD100: Non identified, not listed on an exchange platform | AE100: 0 | AF100: 0 | AH100: OK | AI100: Concluído
H101: =+"c"&LEFT(J101,4) -> c0090 | I101: B90.00 | J101: 0090_CNTRY_CNTRPRTY | N101: 2025-10-31 | O101: 10 | P101: =+IFERROR(VLOOKUP(B101,'[1]ID1&5'!K:L,2,FALSE),"-") -> - | Q101: 10 | R101: =+IFERROR(VLOOKUP(CONCATENATE(A101,$C$10,C101),'[1]ID1&5'!B:J,8,FALSE),"-") -> - | S101: =+IFERROR(VLOOKUP(C101,'[1]ID1&5'!K:L,2,FALSE),"-") -> - | T101: 0 | U101: =+IFERROR(VLOOKUP(D101,'[1]ID1&5'!K:L,2,FALSE),"-") -> - | V101: 0 | W101: =+IFERROR(VLOOKUP(E101,'[1]ID1&5'!K:L,2,FALSE),"-") -> - | X101: 0 | Y101: =+X101/O101 -> 0 | Z101: =+IFERROR(VLOOKUP(F101,'[1]ID1&5'!K:L,2,FALSE),"-") -> - | AA101: 2 | AB101: =+AA101/O101 -> 0.2 | AC101: 99 | AD101: PT | AE101: 1 | AF101: 0 | AG101: Comentário 14/11 - Os registos são classificados como não aplicável por serem relativos à entidade de ajustes '0000000000'. | AH101: OK | AI101: Concluído
H102: =+"c"&LEFT(J102,4) -> c0100 | I102: B90.00 | J102: 0100_RLVNT_AMNT_WDC | N102: 2025-10-31 | O102: 10 | P102: =+IFERROR(VLOOKUP(B102,'[1]ID1&5'!K:L,2,FALSE),"-") -> - | Q102: 10 | R102: =+IFERROR(VLOOKUP(CONCATENATE(A102,$C$10,C102),'[1]ID1&5'!B:J,8,FALSE),"-") -> - | S102: =+IFERROR(VLOOKUP(C102,'[1]ID1&5'!K:L,2,FALSE),"-") -> - | T102: 0 | U102: =+IFERROR(VLOOKUP(D102,'[1]ID1&5'!K:L,2,FALSE),"-") -> - | V102: 0 | W102: =+IFERROR(VLOOKUP(E102,'[1]ID1&5'!K:L,2,FALSE),"-") -> - | X102: 0 | Y102: =+X102/O102 -> 0 | Z102: =+IFERROR(VLOOKUP(F102,'[1]ID1&5'!K:L,2,FALSE),"-") -> - | AA102: 0 | AB102: =+AA102/O102 -> 0 | AC102: 0 | AD102: 1383690177 | AE102: 1 | AF102: 0 | AH102: OK | AI102: Concluído
I104: LT003 | J104: CNTRPRTY_RSLTN_GRP | M104: =+COUNTIF('[1]ID1&5'!A:A,'3. Status Testes'!I104&'[1]1. Status'!J104)+COUNTIF('[1]ID6&7'!A:A,'[1]1. Status'!I104&'[1]1. Status'!J104) -> #VALUE! | N104: =+IFERROR(VLOOKUP(CONCATENATE(A104,$B$10,B104),'[1]ID1&5'!B:J,7,FALSE),"-") -> - | O104: =+IFERROR(VLOOKUP(CONCATENATE(A104,$B$10,B104),'[1]ID1&5'!B:J,8,FALSE),"-") -> - | P104: =+IFERROR(VLOOKUP(B104,'[1]ID1&5'!K:L,2,FALSE),"-") -> - | Q104: =+IFERROR(VLOOKUP(CONCATENATE(A104,$B$10,B104),'[1]ID1&5'!B:J,9,FALSE),"-") -> - | R104: =+IFERROR(VLOOKUP(CONCATENATE(A104,$C$10,C104),'[1]ID1&5'!B:J,8,FALSE),"-") -> - | S104: =+IFERROR(VLOOKUP(C104,'[1]ID1&5'!K:L,2,FALSE),"-") -> - | T104: =+IFERROR(VLOOKUP(CONCATENATE(A104,$C$10,C104),'[1]ID1&5'!B:J,9,FALSE),"-") -> - | U104: =+IFERROR(VLOOKUP(D104,'[1]ID1&5'!K:L,2,FALSE),"-") -> - | V104: =+IFERROR(VLOOKUP(CONCATENATE(A104,$D$10,D104),'[1]ID1&5'!B:J,9,FALSE),"-") -> - | W104: =+IFERROR(VLOOKUP(E104,'[1]ID1&5'!K:L,2,FALSE),"-") -> - | X104: =+IFERROR(VLOOKUP(CONCATENATE(A104,$E$10,E104),'[1]ID1&5'!B:J,9,FALSE),"-") -> - | Y104: =+X104/O104 -> #VALUE! | Z104: =+IFERROR(VLOOKUP(F104,'[1]ID1&5'!K:L,2,FALSE),"-") -> - | AA104: =+IFERROR(VLOOKUP(CONCATENATE(A104,$F$10,F104),'[1]ID1&5'!B:J,9,FALSE),"-") -> - | AB104: =+AA104/O104 -> #VALUE! | AC104: =+IFERROR(VLOOKUP(A104&G104,'[1]ID6&7'!B:J,8,FALSE),"-") -> - | AD104: =+IFERROR(VLOOKUP(A104&G104,'[1]ID6&7'!B:J,9,FALSE),"-") -> - | AE104: =+IF(IFERROR(VLOOKUP(J104,'[1]ID8&9'!G:G,1,FALSE),"")=J104,IF(VLOOKUP(J104,'[1]ID8&9'!G:J,3,FALSE)+VLOOKUP(J104,'[1]ID8&9'!G:J,4,FALSE)=2,_xlfn.MAXIFS('[1]ID8&9'!D:D,'[1]ID8&9'!G:G,J104,'[1]ID8&9'!H:H,8,'[1]ID8&9'!I:I,1,'[1]ID8&9'!J:J,1),"Campo por concluir"),"Sem aplicabilidade") -> Sem aplicabilidade | AF104: =+IF(IFERROR(VLOOKUP(J104,'[1]ID8&9'!G:G,1,FALSE),"")=J104,IF(VLOOKUP(J104,'[1]ID8&9'!G:J,3,FALSE)+VLOOKUP(J104,'[1]ID8&9'!G:J,4,FALSE)=2,_xlfn.MAXIFS('[1]ID8&9'!D:D,'[1]ID8&9'!G:G,J104,'[1]ID8&9'!H:H,9,'[1]ID8&9'!I:I,1,'[1]ID8&9'!J:J,1),"Campo por concluir"),"Sem aplicabilidade") -> Sem aplicabilidade | AH104: OK | AI104: Concluído
I105: LT003 | J105: PRSN_TYP | M105: =+COUNTIF('[1]ID1&5'!A:A,'3. Status Testes'!I105&'[1]1. Status'!J105)+COUNTIF('[1]ID6&7'!A:A,'[1]1. Status'!I105&'[1]1. Status'!J105) -> #VALUE! | N105: =+IFERROR(VLOOKUP(CONCATENATE(A105,$B$10,B105),'[1]ID1&5'!B:J,7,FALSE),"-") -> - | O105: =+IFERROR(VLOOKUP(CONCATENATE(A105,$B$10,B105),'[1]ID1&5'!B:J,8,FALSE),"-") -> - | P105: =+IFERROR(VLOOKUP(B105,'[1]ID1&5'!K:L,2,FALSE),"-") -> - | Q105: =+IFERROR(VLOOKUP(CONCATENATE(A105,$B$10,B105),'[1]ID1&5'!B:J,9,FALSE),"-") -> - | R105: =+IFERROR(VLOOKUP(CONCATENATE(A105,$C$10,C105),'[1]ID1&5'!B:J,8,FALSE),"-") -> - | S105: =+IFERROR(VLOOKUP(C105,'[1]ID1&5'!K:L,2,FALSE),"-") -> - | T105: =+IFERROR(VLOOKUP(CONCATENATE(A105,$C$10,C105),'[1]ID1&5'!B:J,9,FALSE),"-") -> - | U105: =+IFERROR(VLOOKUP(D105,'[1]ID1&5'!K:L,2,FALSE),"-") -> - | V105: =+IFERROR(VLOOKUP(CONCATENATE(A105,$D$10,D105),'[1]ID1&5'!B:J,9,FALSE),"-") -> - | W105: =+IFERROR(VLOOKUP(E105,'[1]ID1&5'!K:L,2,FALSE),"-") -> - | X105: =+IFERROR(VLOOKUP(CONCATENATE(A105,$E$10,E105),'[1]ID1&5'!B:J,9,FALSE),"-") -> - | Y105: =+X105/O105 -> #VALUE! | Z105: =+IFERROR(VLOOKUP(F105,'[1]ID1&5'!K:L,2,FALSE),"-") -> - | AA105: =+IFERROR(VLOOKUP(CONCATENATE(A105,$F$10,F105),'[1]ID1&5'!B:J,9,FALSE),"-") -> - | AB105: =+AA105/O105 -> #VALUE! | AC105: =+IFERROR(VLOOKUP(A105&G105,'[1]ID6&7'!B:J,8,FALSE),"-") -> - | AD105: =+IFERROR(VLOOKUP(A105&G105,'[1]ID6&7'!B:J,9,FALSE),"-") -> - | AE105: =+IF(IFERROR(VLOOKUP(J105,'[1]ID8&9'!G:G,1,FALSE),"")=J105,IF(VLOOKUP(J105,'[1]ID8&9'!G:J,3,FALSE)+VLOOKUP(J105,'[1]ID8&9'!G:J,4,FALSE)=2,_xlfn.MAXIFS('[1]ID8&9'!D:D,'[1]ID8&9'!G:G,J105,'[1]ID8&9'!H:H,8,'[1]ID8&9'!I:I,1,'[1]ID8&9'!J:J,1),"Campo por concluir"),"Sem aplicabilidade") -> Sem aplicabilidade | AF105: =+IF(IFERROR(VLOOKUP(J105,'[1]ID8&9'!G:G,1,FALSE),"")=J105,IF(VLOOKUP(J105,'[1]ID8&9'!G:J,3,FALSE)+VLOOKUP(J105,'[1]ID8&9'!G:J,4,FALSE)=2,_xlfn.MAXIFS('[1]ID8&9'!D:D,'[1]ID8&9'!G:G,J105,'[1]ID8&9'!H:H,9,'[1]ID8&9'!I:I,1,'[1]ID8&9'!J:J,1),"Campo por concluir"),"Sem aplicabilidade") -> Sem aplicabilidade | AH105: OK | AI105: Concluído
I106: LT003 | J106: ENTTY_NM | M106: =+COUNTIF('[1]ID1&5'!A:A,'3. Status Testes'!I106&'[1]1. Status'!J106)+COUNTIF('[1]ID6&7'!A:A,'[1]1. Status'!I106&'[1]1. Status'!J106) -> #VALUE! | N106: =+IFERROR(VLOOKUP(CONCATENATE(A106,$B$10,B106),'[1]ID1&5'!B:J,7,FALSE),"-") -> - | O106: =+IFERROR(VLOOKUP(CONCATENATE(A106,$B$10,B106),'[1]ID1&5'!B:J,8,FALSE),"-") -> - | P106: =+IFERROR(VLOOKUP(B106,'[1]ID1&5'!K:L,2,FALSE),"-") -> - | Q106: =+IFERROR(VLOOKUP(CONCATENATE(A106,$B$10,B106),'[1]ID1&5'!B:J,9,FALSE),"-") -> - | R106: =+IFERROR(VLOOKUP(CONCATENATE(A106,$C$10,C106),'[1]ID1&5'!B:J,8,FALSE),"-") -> - | S106: =+IFERROR(VLOOKUP(C106,'[1]ID1&5'!K:L,2,FALSE),"-") -> - | T106: =+IFERROR(VLOOKUP(CONCATENATE(A106,$C$10,C106),'[1]ID1&5'!B:J,9,FALSE),"-") -> - | U106: =+IFERROR(VLOOKUP(D106,'[1]ID1&5'!K:L,2,FALSE),"-") -> - | V106: =+IFERROR(VLOOKUP(CONCATENATE(A106,$D$10,D106),'[1]ID1&5'!B:J,9,FALSE),"-") -> - | W106: =+IFERROR(VLOOKUP(E106,'[1]ID1&5'!K:L,2,FALSE),"-") -> - | X106: =+IFERROR(VLOOKUP(CONCATENATE(A106,$E$10,E106),'[1]ID1&5'!B:J,9,FALSE),"-") -> - | Y106: =+X106/O106 -> #VALUE! | Z106: =+IFERROR(VLOOKUP(F106,'[1]ID1&5'!K:L,2,FALSE),"-") -> - | AA106: =+IFERROR(VLOOKUP(CONCATENATE(A106,$F$10,F106),'[1]ID1&5'!B:J,9,FALSE),"-") -> - | AB106: =+AA106/O106 -> #VALUE! | AC106: =+IFERROR(VLOOKUP(A106&G106,'[1]ID6&7'!B:J,8,FALSE),"-") -> - | AD106: =+IFERROR(VLOOKUP(A106&G106,'[1]ID6&7'!B:J,9,FALSE),"-") -> - | AE106: =+IF(IFERROR(VLOOKUP(J106,'[1]ID8&9'!G:G,1,FALSE),"")=J106,IF(VLOOKUP(J106,'[1]ID8&9'!G:J,3,FALSE)+VLOOKUP(J106,'[1]ID8&9'!G:J,4,FALSE)=2,_xlfn.MAXIFS('[1]ID8&9'!D:D,'[1]ID8&9'!G:G,J106,'[1]ID8&9'!H:H,8,'[1]ID8&9'!I:I,1,'[1]ID8&9'!J:J,1),"Campo por concluir"),"Sem aplicabilidade") -> Sem aplicabilidade | AF106: =+IF(IFERROR(VLOOKUP(J106,'[1]ID8&9'!G:G,1,FALSE),"")=J106,IF(VLOOKUP(J106,'[1]ID8&9'!G:J,3,FALSE)+VLOOKUP(J106,'[1]ID8&9'!G:J,4,FALSE)=2,_xlfn.MAXIFS('[1]ID8&9'!D:D,'[1]ID8&9'!G:G,J106,'[1]ID8&9'!H:H,9,'[1]ID8&9'!I:I,1,'[1]ID8&9'!J:J,1),"Campo por concluir"),"Sem aplicabilidade") -> Sem aplicabilidade | AH106: OK | AI106: Concluído
...

Sheet Detalhe Especificação ->

Sheet B02.00
B1: B02.00 - Main Liabilities: the tab includes the data points requested at resolution entity (point of entry) level for the implementation of the bail-in tool, or at non resolution entity level (up to the Senior Non-Preferred layer)11 for monitoring and implementing the loss transfer and recapitalisation mechanisms. Generally, the data points in this tab are requested at individual level12. However, some specific data points may be requested at consolidated level on an adhoc basis by the IRT
B2: SRB Instructions | J2: Especificação IT
J3: Fase 1 - Granular (Loan Tape) | O3: Fase 2 - Agregada (Não Loan Tape) | Q3: Comentários/Histórico EF
A4: Aux_sheet_Status | B4: Data Point | C4: ID | D4: Data type | E4: Constrain | F4: Description | G4: Treatment of "Not applicable" (if cell is grey out, input is not expected) | H4: Treatment of "Not available" (if cell is grey out, input is not expected) | J4: Novo campo? | K4: Nome campo | L4: Missing Value (LT804) | M4: Not Applicable Value (LT804) | N4: Regra campo | O4: Nome campo | P4: Regra campo | R4: Estado Especificação | S4: Estado Desenvolvimento
A5: ="B02.00_"&MID(O5,28,LEN(O5)) -> B02.00_0010_row_nmbr | B5: Row number | C5: 0010 | D5: Numeric | E5: Integer | F5: The unique number / primary key to identify the row items (the number must be an integer). | J5: Não | O5: out_b0200_main_liabilities.0010_row_nmbr | P5: Sequenciador a implementar na tabela de output out_b0200_main_liabilities Nota: A cada execução não deverão ser gerados Row numbers diferentes pelo que provisoriamente deverá ser feito um order by instrmnt_id | Q5: Reunião 2025-06-16 Luís Capitão-Mor, Pedro Mendes, Luísa Sousa | R5: Campo não LT (apenas tabela Output) | S5: Concluído | T5: Concluído | U5: ok | X5: =+S5 -> Concluído | Y5: =+P5 -> Sequenciador a implementar na tabela de output out_b0200_main_liabilities Nota: A cada execução não deverão ser gerados Row numbers diferentes pelo que provisoriamente deverá ser feito um order by instrmnt_id
A6: ="B02.00_"&MID(O6,28,LEN(O6)) -> B02.00_0020_uniq_id | B6: Unique internal identification number | C6: 0020 | D6: String | E6: Free text | F6: The unique internal identifier of the instrument/liability. For deposits reported on an aggregate level, please indicate: ▪ ‘NCNP’ for the aggregated not covered not preferential deposits (field c0280 = TRUE); and ▪ ‘NCBP’ for the aggregated not covered but preferential deposits (field c0290 = TRUE). | J6: Não | K6: lt002_instrument.instrmnt_id | M6: Not applicable | O6: out_b0200_main_liabilities.0020_uniq_id | P6: lt002_instrument.instrmnt_id | Q6: Reunião 2025-06-16 Luís Capitão-Mor, Pedro Mendes, Luísa Sousa | R6: Campo já existente no LT | S6: Concluído | T6: Concluído | U6: ok | X6: =+S6 -> Concluído | Y6: =+P6 -> lt002_instrument.instrmnt_id
A7: ="B02.00_"&MID(O7,28,LEN(O7)) -> B02.00_0030_uniq_id_knwn_cntrprty | B7: Unique identification number (known to the counterparty) | C7: 0030 | D7: String | E7: Free text | F7: The unique identifier of the instrument/liability that would allow the counterparty to conclude that it will be affected by the potential resolution action, without external third parties being able to identify the creditor. For securities, the ISIN code must be indicated where available (other identifiers need only be provided in the absence of an ISIN). For deposits and other liabilities, the account/contract number should be reported. In the event of multiple tranches (multiple counterparties) of one promissory-note loan (e.g. Schuldscheindarlehen) or a syndicated loan, a unique ID must be allocated to each tranche. For deposits reported on an aggregate level, please indicate: ▪ ‘NCNP’ for the aggregated not covered not preferential deposits (field c0280 = TRUE); and ▪ ‘NCBP’ for the aggregated not covered but preferential deposits (field c0290 = TRUE). | J7: Não | K7: lt002_instrument.isin | M7: Not applicable | O7: out_b0200_main_liabilities.0030_uniq_id_knwn_cntrprty | P7: lt002_instrument.isin | Q7: Reunião 2025-06-16 Luís Capitão-Mor, Pedro Mendes, Luísa Sousa | R7: Campo já existente no LT | S7: Concluído | T7: Concluído | U7: ok | X7: =+S7 -> Concluído | Y7: =+P7 -> lt002_instrument.isin
A8: ="B02.00_"&MID(O8,28,LEN(O8)) -> B02.00_0040_typ_uniq_id_knwn_cntrprty | B8: Type of the unique identifier (known to the counterparty) | C8: 0040 | D8: String | E8: Free text, but fixed values for specific items | F8: Free text, to indicate what type of identifier has been used in data point c0020, e.g. if the identifier is an ISIN, please input ‘ISIN’; if the identifier is an account number, please input ‘Account number’; if the identifier is a contract number, please input ‘Contract number’. For deposits reported on an aggregate level, please indicate ‘Aggregated’. | J8: Não | O8: out_b0200_main_liabilities.0040_typ_uniq_id_knwn_cntrprty | P8: Valor fixo 'ISIN' | Q8: Reunião 2025-06-16 Luís Capitão-Mor, Pedro Mendes, Luísa Sousa: Neste caso não faz sentido criar o campo no Loan Tape quando ele já existe, portanto será criado apenas na tabela output out_b0200_main_liabilities. Caso contrário haveria um princípio de colisão, pois estar-se-ia a repetir conceitos de campos. | R8: Campo não LT (apenas tabela Output) | S8: Concluído | T8: Concluído | U8: ok | X8: =+S8 -> Concluído | Y8: =+P8 -> Valor fixo 'ISIN'
A9: ="B02.00_"&MID(O9,28,LEN(O9)) -> B02.00_0050_orgnl_amnt_eur | B9: Original amount issued in EUR | C9: 50 | D9: Numeric | E9: 2 decimals | F9: The EUR (counter)value of the total issue size of the instrument, irrespective of the effective issuance dates, i.e. the total nominal amount / face value of a specific liability. For shares, it should reflect the face value / carrying amount of the shares. If a nominal value does not exist, this field is not applicable. This data point is not applicable for cash accounts / saving accounts and deposits reported in aggregated form (Submission A). If a value is reported in a foreign currency (c0060), the amount must additionally be converted into euros and reported in the corresponding EUR field (c0050), using the euro reference exchange rate published by the ECB on the date for which the information is reported40. In the case of foreign currencies for which no euro reference exchange rate is available, a customary market reference rate must be used. If such other customary reference exchange rates are used, a uniform source must be used wherever possible. | G9: Input 999999999999999 | J9: Sim | K9: lt002_instrument.orgnl_amnt_eur | M9: 999999999999999 | N9: Se flag_inst_titulos = '1': Obter campo nom_tot_inic da ct610_titulos. Adicionalmente, efetuar conversão via tabela cambios, seguindo a lógica definida nos restantes processos, dado que o campo nom_tot_inic está expresso na moeda original (campo cmoeda). Exemplo de query que utiliza a tabela cambios para converter moeda original em moeda eur (quando é eur a tcmbme é 1 pelo que o valor é igual): SELECT DISTINCT concat(cempresa,cbalcao, cnumecta, zdeposit), (ct610.nom_tot_inic / cambios.tcmbme) AS orgnl_amnt_eur FROM (SELECT cempresa,cbalcao, cnumecta, zdeposit, nom_tot_inic, cmoeda FROM cd_captools.ct610_titulos WHERE ref_date='${ref_date}' and concat(cempresa,cbalcao, cnumecta, zdeposit) IN ( '31641600000000000PTSTOGOM0003000', '31641600005800007PTBSRDOM0037000', '31641600005800007PTSTOCOM0007000', '31641600005800007PTCPP0AM0007000', '31641600000000000PTSTOEOM0021000', '31641600000000000PTSTOHOM0002000', '31641600000000000PTBSREOM0028000', '31641600000000000PTSTOFOM0004000')) ct610 LEFT JOIN (SELECT cmoeda, tcmbme FROM cd_captools.cambios WHERE data_date_part = '${ref_date}' AND dcambio = '${ref_date}' AND zseqcamb = 99 AND ctbcamb = 'F' AND cmarca = 'BT') cambios ON cambios.cmoeda = ct610.cmoeda; Se flag_inst_titulos = '0': Not applicable. O respetivo valor default de Not applicable deverá ser parametrizado na lt804_conf_dflt. | O9: out_b0200_main_liabilities.0050_orgnl_amnt_eur | P9: lt002_instrument.orgnl_amnt_eur | Q9: Reunião 2025-08-04 Luís Capitão-Mor, Pedro Mendes, Luísa Sousa | R9: Campo novo no LT | S9: Concluído | T9: Campo de montante | U9: ok | X9: =+S9 -> Concluído | Y9: =+P9 -> lt002_instrument.orgnl_amnt_eur
A10: ="B02.00_"&MID(O10,28,LEN(O10)) -> B02.00_0060_orgnl_amnt_fx | B10: Original amount issued in foreign currency | C10: 0060 | D10: Numeric | E10: 2 decimals | F10: Same as c0050 above, but in the foreign currency (where relevant). Please also report the EUR-converted amount in the corresponding EUR field (c0050). This data point is not applicable for cash accounts / savings accounts and deposits reported in aggregated form (Submission A). | G10: Input 999999999999999 | J10: Sim | K10: lt002_instrument.orgnl_amnt_fx | M10: 999999999999999 | N10: Se flag_inst_titulos = '1' e se campo cmoeda da ct610_titulos = '978' (eur): Not applicable. O respetivo valor default de Not applicable deverá ser parametrizado na lt804_conf_dflt. Se flag_inst_titulos = '1' e se campo cmoeda da ct610_titulos <> '978' (eur): Obter campo nom_tot_inic da ct610_titulos Se flag_inst_titulos = '0': Not applicable. O respetivo valor default de Not applicable deverá ser parametrizado na lt804_conf_dflt. | O10: out_b0200_main_liabilities.0060_orgnl_amnt_fx | P10: lt002_instrument.orgnl_amnt_fx | Q10: Reunião 2025-08-04 Luís Capitão-Mor, Pedro Mendes, Luísa Sousa | R10: Campo novo no LT | S10: Concluído | T10: Campo de montante | U10: ok | X10: =+S10 -> Concluído | Y10: =+P10 -> lt002_instrument.orgnl_amnt_fx
A11: ="B02.00_"&MID(O11,28,LEN(O11)) -> B02.00_0070_cntrct_crrncy | B11: Contract currency | C11: 0070 | D11: String | E11: 3-letters ISO 4217 | F11: The currency in which the instrument/liability is issued. The currency must be reported with its 3-letter ISO 4217 code. For deposits reported on an aggregate level, please indicate ‘XXX’. | G11: Input "XXX" | J11: Não | K11: lt002_instrument.crrncy_dnmntn | M11: XXX | O11: out_b0200_main_liabilities.0070_cntrct_crrncy | P11: lt002_instrument.crrncy_dnmntn | Q11: Reunião 2025-06-16 Luís Capitão-Mor, Pedro Mendes, Luísa Sousa | R11: Campo já existente no LT | S11: Concluído | T11: Concluído | U11: ok | X11: =+S11 -> Concluído | Y11: =+P11 -> lt002_instrument.crrncy_dnmntn
A12: ="B02.00_"&MID(O12,28,LEN(O12)) -> B02.00_0080_otstndng_prncpl_amnt | B12: Outstanding principal amount | C12: 80 | D12: Numeric | E12: 2 decimals | F12: The EUR (counter)value of the outstanding principal amount of the instrument/liability. The difference between the original amount issued and the outstanding principal amount may be due to partial buybacks of the instrument, amortising instruments, etc. The portion of eligible liabilities subscribed by intragroup entities and excluded under Article 27(3)(h) SRMR must be included in the outstanding principal amount. Only claims against other parties must be reported (i.e. excluding the portion held by the entity itself, which must be reported in field c0090). For zero coupon bonds issued at discount (i.e. c0240 = ZCB issued at discount) the final redemption amount should be reported. | J12: Sim | K12: lt005_instr_ent.otstndng_prncpl_amnt | M12: 999999999999999 | N12: Se flag_inst_titulos = '1': Passo 1: Verificar para cada "entty_id" (de um determinado "instrmnt_id") da lt005_instr_ent se o mesmo consta no vetor "zcliente_investidor" da ct610_titulos (desse "instrmnt_id"). Se constar, identificar em que posição consta e em seguida obter do vetor "nom_tot_ini_investe" da ct610_titulos o montante que consta nessa posição; Passo 2: Verificar se a soma dos vários "nom_tot_ini_investe" é igual ao "nom_tot_inic", da ct610_titulos -> Se for igual: Não é necessária ação adicional -> Se for diferente: Somar essa diferença no "entty_id" 0000000000 Passo 3: Dado que o "outstanding principal amount" que se pretende é o atual e não o inicial, então terá de se multiplicar os vários "nom_tot_ini_investe" pelo rácio "nom_tot_atual"/"nom_tot_inic", da ct610_titulos. Nota: O Universo do MBDT terá sempre este rácio=1 e portanto o valor inicial será igual ao valor atual, contudo, se existissem titularizações (onde se aplica o conceito de pool factor), o valor inicial seria diferente do valor atual (porque o "pool_factor" seria diferente de 1). Passo 4: Converter o montante obtido para eur pela tabela de cambios (ver query de conversão já definida no campo Original amount issued in EUR (0050)) Se flag_inst_titulos = '0': Not applicable. O respetivo valor default de Not applicable deverá ser parametrizado na lt804_conf_dflt. Na sheet "Aux Campos Montante" consta um exemplo com a aplicação desta lógica. | O12: out_b0200_main_liabilities.0080_otstndng_prncpl_amnt | P12: Soma "otstndng_prncpl_amnt" - Soma "portion_amnt_rprtng_entty", por cada instrmnt_id da lt005_instr_ent Na sheet "Aux Campos Montante" consta um exemplo com a aplicação desta lógica. | Q12: Reunião 2025-10-09 Luís Capitão-Mor, Pedro Mendes Reunião 2025-09-22 e 2025-09-18 Luís Capitão-Mor, Pedro Mendes: Segundo Luís Capitão-Mor não se pode utilizar o campo OTSTNDNG_NMNL_AMNT_INSTRMNT da lt002_instrument dado que esse campo é contabilístico (a pedido do guia do BCE) e o SRB não pede contabilístico. Adicionalmente, interpretou-se da definição dada pelo SRB que se pretende retirar as recompras do BST e deve-se incluir o que está no Santander S.A (ou seja não deve se retirar o que está no Santander S.A.). Exemplo 1: Emissão de 1000M eur em que: 100M eur estão recomprados pelo BST 900M eur estão no mercado (e destes 900M eur, 500M eur estão no Santander S.A.) Ou seja, neste exemplo o Outstanding principal amount deverá ser 900M eur. Exemplo 2: Emissão 1000M eur a 95% (abaixo do par), portanto 950M eur. Na contabilidade na data inicial consta Outstanding principal amount=950M eur mas na ct610_titulos constam 1000M eur. Ou seja, o valor contabilístico nem sempre é igual ao não contabilístico. | R12: Campo novo no LT | S12: Não Concluído | T12: Campo de montante | U12: ok | X12: =+S12 -> Não Concluído | Y12: =+P12 -> Soma "otstndng_prncpl_amnt" - Soma "portion_amnt_rprtng_entty", por cada instrmnt_id da lt005_instr_ent Na sheet "Aux Campos Montante" consta um exemplo com a aplicação desta lógica.
A13: ="B02.00_"&MID(O13,28,LEN(O13)) -> B02.00_0090_prtn_amnt_rprtng_entty | B13: Portion of instrument or liability held by the reporting entity | C13: 0090 | D13: Numeric | E13: 2 decimals | F13: The EUR amount related to the portion of the liability held by the reporting entity itself. The amount can either be defined as the principal amount plus accrued interest and fees and charges, or as the relevant portion of fair value held by the reporting entity itself, in the event that field c0250 applies. This data point is only relevant for securities. | G13: Input 999999999999999 | J13: Sim | K13: lt005_instr_ent.prtn_amnt_rprtng_entty | M13: 999999999999999 | N13: Se flag_inst_titulos = '1': Verificar para cada "entty_id" (de um determinado "instrmnt_id") da lt005_instr_ent se o mesmo corresponde ao "zcliente_emitente" da ct610_titulos (desse "instrmnt_id"). Se não corresponder: Reportar 0 Se corresponder: Verificar se esse "entty_id" consta no vetor "zcliente_investidor" da ct610_titulos. Se constar: Passo 1: Identificar em que posição consta no vetor "zcliente_investidor" e em seguida obter do vetor "nom_tot_ini_investe" da ct610_titulos o montante que consta nessa posição; Passo 2: Dado que o "Portion of instrument or liability held by the reporting entity" que se pretende é o atual e não o inicial, então terá de se multiplicar o montante obtido no passo anterior pelo rácio "nom_tot_atual"/"nom_tot_inic", da ct610_titulos; Passo 3: Converter para eur pela tabela de cambios (ver query de conversão já definida no campo Original amount issued in EUR (0050)). Se não constar: Reportar 0 Se flag_inst_titulos = '0': Not applicable. O respetivo valor default de Not applicable deverá ser parametrizado na lt804_conf_dflt. Na sheet "Aux Campos Montante" consta um exemplo com a aplicação desta lógica. | O13: out_b0200_main_liabilities.0090_prtn_amnt_rprtng_entty | P13: Soma "prtn_amnt_rprtng_entty", por cada instrmnt_id da lt005_instr_ent Na sheet "Aux Campos Montante" consta um exemplo com a aplicação desta lógica. | Q13: Reunião 2025-10-09 Luís Capitão-Mor, Pedro Mendes Reunião 2025-09-22 e 2025-09-18 Luís Capitão-Mor, Pedro Mendes | R13: Campo novo no LT | S13: Não Concluído | T13: Campo de montante | U13: ok | X13: =+S13 -> Não Concluído | Y13: =+P13 -> Soma "prtn_amnt_rprtng_entty", por cada instrmnt_id da lt005_instr_ent Na sheet "Aux Campos Montante" consta um exemplo com a aplicação desta lógica.
A14: ="B02.00_"&MID(O14,28,LEN(O14)) -> B02.00_0100_accrd_intrst_instrmnt | B14: Accrued interest | C14: 100 | D14: Numeric | E14: 2 decimals | F14: The EUR (counter)value of the outstanding accrued interest on the instrument. In jurisdictions where accrued interests do not rank pari passu to the principal liability amount, the relevant NRAs have the option to request the reporting of interest accruals on separate line items (41). Only claims against third parties must be reported (i.e. excluding the proportion held by the entity itself, which must be reported in field c0090). In case the field is not applicable (e.g. shares, zero coupon bonds issued at discount), please refer to the specific instructions in the Technical Annex. (41) - In such cases, please refer to the specific reporting example in Annex II, paragraph 3.7. | G14: Input 999999999999999 | H14: Leave blank | J14: Sim | K14: lt002_instrument.accrd_intrst_instrmnt (campo já existente a alterar) lt005_instr_ent.accrd_intrst_instrmnt (campo novo a criar) | M14: 999999999999999 | N14: lt002_instrument.accrd_intrst_instrmnt (campo já existente a alterar): O campo accrd_intrst_instrmnt (da lt002_instrument) está atualmente a sair com valor 0 para estes registos de Títulos Passivos (o que não é suposto dado que existem registos que deveriam ter valor). O campo accrd_intrst_instrmnt (da lt002_instrument) alimenta-se do campo juros_corridos (da lt001_univ_oper) e é calculado atualmente da seguinte forma (segundo "Especificação - BCE Loan Tape_20250915 LF + ESTR"): NVL ( SUM(-1*juros_corridos) ,0 ) O campo juros_corridos (da lt001_univ_oper) será calculado da seguinte forma (segundo re-especificação solicitada por Gonçalo Filipe, email 5 de agosto de 2025 12:58): SUM(MSALDO_FINAL) WHERE COD_PLANO = 'BST_IND' AND CCONTAB_FINAL_PCSB NOT LIKE '28%' AND COMPOSICAO_VALOR = 'juros/rendimentos a receber' AND TIPO_CONTA = 'A' AND CARTEIRA_CONTABILISTICA IN ('ativos financeiros ao custo amortizado','ativos financeiros ao justo valor atraves de outro rendimento integral','ativos financeiros ao justo valor atraves de resultados') Constata-se portanto que o campo juros_corridos (da lt001_univ_oper) não contempla atualmente o Passivo (razão pela qual o campo sai com valor 0), pelo que deverá ser adicionada a condição do "OR" abaixo: SUM(MSALDO_FINAL) WHERE ( COD_PLANO = 'BST_IND' AND CCONTAB_FINAL_PCSB NOT LIKE '28%' AND COMPOSICAO_VALOR = 'juros/rendimentos a receber' AND TIPO_CONTA = 'A' AND CARTEIRA_CONTABILISTICA IN ('ativos financeiros ao custo amortizado','ativos financeiros ao justo valor atraves de outro rendimento integral','ativos financeiros ao justo valor atraves de resultados') ) OR ( COD_PLANO = 'BST_IND' AND COMPOSICAO_VALOR = 'juros/encargos a pagar' AND TIPO_CONTA = 'P' AND CARTEIRA_CONTABILISTICA IN ('passivos financeiros ao custo amortizado') ) - Luís Capitão-Mor, Luísa Sousa, Gonçalo Filipe e Dora Roxo não identificaram impacto nesta alteração. lt005_instr_ent.accrd_intrst_instrmnt (campo novo a criar): 'Se flag_inst_titulos = '1': Efetuar exatamente a mesma especificação da lt002_instrument.accrd_intrst_instrmnt mas obtendo o valor por cada "entty_id" (na lt001_univ_oper). Ex: Para o contrato 'A' (cempresa, cbalcao, cnumecta, zdeposit) temos 3 linhas com a seguinte distribuição de juros_corridos na lt001_univ_oper: cempresa+cbalcao+cnumecta+zdeposit= 'A' | zcliente='1' | juros_corridos = 10 cempresa+cbalcao+cnumecta+zdeposit= 'A' | zcliente='2' | juros_corridos = 20 cempresa+cbalcao+cnumecta+zdeposit= 'A' | zcliente='3' | juros_corridos = 30 Atualmente o campo accrd_intrst_instrmnt da lt002_instrument calcula simplesmente a soma dos vários montantes de juros_corridos por contrato, ou seja, na lt002_instrument é apresentado uma única linha: instrmnt_id= 'A' | accrd_intrst_instrmnt = 60 O que se pretende no novo campo accrd_intrst_instrmnt a criar na lt005_instr_ent: instrmnt_id= 'A' | entty_id=1 | accrd_intrst_instrmnt = 10 instrmnt_id= 'A' | entty_id=2 | accrd_intrst_instrmnt = 20 instrmnt_id= 'A' | entty_id=3 | accrd_intrst_instrmnt = 30 Se flag_inst_titulos = '0': Not applicable. O respetivo valor default de Not applicable deverá ser parametrizado na lt804_conf_dflt. | O14: out_b0200_main_liabilities.0100_accrd_intrst_instrmnt | P14: (-1) * Soma "accrd_intrst_instrmnt ", por cada instrmnt_id da lt005_instr_ent Nota: Esta multiplicação por -1, deve-se ao facto de no Loan Tape o campo accrd_intrst_instrmnt apresentar valores negativos (para o caso destes registos de Títulos Passivos) e neste report pretenderem-se valores positivos (segundo Pedro Mendes). Ex: O contrato 31 6416 00000000000 PTBSREOM0028000 (para 2025-06-30) tem saldo de juros +418465.480000 na fr001_univ_saldo e terá +418465.480000 na lt001_univ_oper (após a nova re-especificação do Gonçalo Filipe, atualmente tem -418465.480000) e terá -418465.480000 na lt002_instrument (dada a fórmula NVL ( SUM(-1*juros_corridos) ,0 )). É portanto necessária a multiplicação por -1, ficando assim +418465.480000. Deverá ser feita a multiplicação por -1 e não o valor absoluto (abs), dado que poderá vir a existir algum contrato contra natura. | Q14: Reunião 2025-10-09 Luís Capitão-Mor, Pedro Mendes Reunião 2025-09-16 Luís Capitão-Mor, Pedro Mendes, Luísa Sousa | R14: Campo já existente no LT - Nova Especificação | S14: Concluído | T14: Campo de montante | U14: ok | X14: =+S14 -> Concluído | Y14: =+P14 -> (-1) * Soma "accrd_intrst_instrmnt ", por cada instrmnt_id da lt005_instr_ent Nota: Esta multiplicação por -1, deve-se ao facto de no Loan Tape o campo accrd_intrst_instrmnt apresentar valores negativos (para o caso destes registos de Títulos Passivos) e neste report pretenderem-se valores positivos (segundo Pedro Mendes). Ex: O contrato 31 6416 00000000000 PTBSREOM0028000 (para 2025-06-30) tem saldo de juros +418465.480000 na fr001_univ_saldo e terá +418465.480000 na lt001_univ_oper (após a nova re-especificação do Gonçalo Filipe, atualmente tem -418465.480000) e terá -418465.480000 na lt002_instrument (dada a fórmula NVL ( SUM(-1*juros_corridos) ,0 )). É portanto necessária a multiplicação por -1, ficando assim +418465.480000. Deverá ser feita a multiplicação por -1 e não o valor absoluto (abs), dado que poderá vir a existir algum contrato contra natura.
A15: ="B02.00_"&MID(O15,28,LEN(O15)) -> B02.00_0110_applcbl_fees_charges | B15: Applicable fees and charges | C15: 110 | D15: Numeric | E15: 2 decimals | F15: Total EUR amount of applicable fees and charges (e.g. contractual fees for late payments) linked to the instrument, if the fee or charge is payable and due, but not yet settled with the counterparty as of the request date. This is to the extent that the fee or charge is not covered within the outstanding principal amount, the accrued interest or a separate liability. Fees and charges do not include agios or fees in conjunction with the listing of an instrument. Only claims against third parties must be reported (i.e. excluding the proportion held by the entity itself, which must be reported in field c0090). In case the field is not applicable (e.g. shares), please refer to the specific instructions in the Technical Annex. | G15: Input 999999999999999 | H15: Leave blank | J15: Não | O15: out_b0200_main_liabilities.0110_applcbl_fees_charges | P15: Valor fixo 0 | Q15: Reunião 2025-09-22 Luís Capitão-Mor, Pedro Mendes, Luísa Sousa Solução 1: Dado que o BST não tem comissões que ainda não tenham sido pagas/liquidadas (not yet settled) neste Universo de Títulos, reportar neste campo valor fixo 0 na tabela final (out_b0200_main_liabilities). Segundo Pedro Mendes, nem sequer existem comissões iniciais neste Universo de Títulos dado que é tudo feito internamente ou com o Banco Santander S.A.. Solução 2: Trazer as comissões periodificadas da Contabilidade, contudo, essas comissões periodificadas podem ter sido pagas ou não, pelo que não é exatamente o que o SRB pede, dado que o SRB refere que quer as não pagas. Esta solução implicaria criar um campo novo no Loan Tape e trazer um conceito que não é o que o SRB solicita. Adicionalmente o resultado deste campo seria um conjunto vazio para este Universo de Títulos. Solução 3: Criar um campo novo na ct610_titulos. Contudo, este campo seria dinâmico pelo que também não seria uma boa solução. Dadas as soluções apresentadas, optou-se pela solução 1. OLD: Reunião 31/10/2024 Luís Capitão-Mor, Pedro Mendes: Segundo Luís Capitão-Mor, Pedro Mendes, este campo aplica-se aos custos periodificados do banco (ainda não pagos, que estão pendentes de pagar) nas emissões que o Banco faz de covered bonds, seniores,... (estão no Passivo do Banco), tem de se pagar aos Advogados, etc. Naturalmente, este campo não se aplica a Depósitos. Ações solicitadas por Luís Capitão-Mor: - Agendar reunião com Rafael Pessoa/Carlos Fernandes para ver onde constam estes custos na fr802 (devem ter uma conta contabilistica), levando para a reunião 2 exemplos de covered bonds: 1) Identificar esses 2 exemplos para uma data mais recente; 2) Verificar na ct001 quais as contas PCSB (uma conta 50%) e IFRS associadas; 3) Verificar se para essas contas consta na composicao_valor ou noutro campo da fr802 a indicação de comissão ou despesa 4) Verificar se esta comissão ficou ou não incluida no gross carrying amount (provavelmente foi incluido). 5) Verificar na fr004 se já existe lá este conceito de comissão (só seria para adicionar na fr004 caso fosse um conceito que faça sentido para a contabilidade) 6) Tabela de conceitos ct872 (tem os conceitos com base em campos da fr802): criar nesta tabela o conceito caso ele não exista. | R15: Campo não LT (apenas tabela Output) | S15: Concluído | T15: Campo de montante | U15: ok | X15: =+S15 -> Concluído | Y15: =+P15 -> Valor fixo 0
A16: ="B02.00_"&MID(O16,28,LEN(O16)) -> B02.00_0120_otstndng_amnt | B16: Outstanding amount | C16: 0120 | D16: Numeric | E16: 2 decimals | F16: Total EUR value of the outstanding amount of the instrument/deposit held by the counterparty, calculated as the sum of the amounts reported in data points c0080, c0100 and c0110 (where applicable). The amount is in fact the aggregate of the outstanding principal amount plus, if applicable, interest accrued up to the reference date, and fees and charges, irrespective of whether and to what extent the relevant principal, interest or fee-and-charge liability was already due as at the reference date and whether it is required to be recognised as a liability item in the relevant entity’s balance sheet drawn up in accordance with the applicable accounting principles. In jurisdictions where accrued interest may not rank pari passu to the liability amount, the relevant NRA may request the reporting of interest accruals on separate line items. | G16: Input 999999999999999 | J16: Não | O16: out_b0200_main_liabilities.0120_otstndng_amnt | P16: Soma dos 3 campos acima (0080, 0100 e 0110 ): Outstanding principal amount + Accrued interest + Applicable fees and charges | Q16: Reunião 2025-10-09 Luís Capitão-Mor, Pedro Mendes Reunião 2025-09-22 Luís Capitão-Mor, Pedro Mendes, Luísa Sousa: Tem de se ter presente que neste campo vamos somar o "Outstanding principal amount" (que não é contabilístico, vem da ct610_titulos) com o "Accrued interest" (que é contabilístico) e com o "Applicable fees and charges" (que é contabilístico). Ou seja, 2 campos vão-se buscar à Contabilidade mas 1 campo não se vai buscar à Contabilidade, o que não é totalmente coerente. Contudo, não se vê tema dado que o SRB não refere que este campo tem de "bater" com a Contabilidade. | R16: Campo não LT (apenas tabela Output) | S16: Não Concluído | T16: Campo de montante | U16: ok | X16: =+S16 -> Não Concluído | Y16: =+P16 -> Soma dos 3 campos acima (0080, 0100 e 0110 ): Outstanding principal amount + Accrued interest + Applicable fees and charges
A17: ="B02.00_"&MID(O17,28,LEN(O17)) -> B02.00_0130_rlvnt_amnt_wdc | B17: Relevant amount for Bail-in/WDC | C17: 0130 | D17: Numeric | E17: 2 decimals | F17: Total EUR value of the amount eligible for write-down / conversion. Pursuant to Article 48(1) BRRD, resolution authorities shall exercise the write-down and conversion powers in accordance with the cascade set out in letters (a) to (e) of Article 48(1) BRRD. Article 48(2) BRRD further provides that "when applying the write down or conversion powers, resolution authorities shall allocate the losses [...] by reducing the principal amount of, or outstanding amount payable in respect of, those shares or other instruments of ownership and bail-inable liabilities to the same extent pro rata to their value (42) […]". The portion of eligible liabilities subscribed by intragroup entities and excluded under Article 27(3)(h) SRMR must not be reported as part of the relevant amount for bail-in / WDC. When determining the relevant amount for bail-in, entities shall take into account national laws that transpose the BRRD. If those provisions do not provide complete and clear guidance for determining the relevant amount for bail-in, careful consideration should in general be given to how the item in question is dealt with under applicable insolvency legislation43. Furthermore, the contractual terms governing each liability might provide additional insight when performing this assessment. For debt instruments with embedded derivatives, the following list of items shall be considered: ▪ Any contractually defined floor or cap to the final redemption amount. ▪ Any contractually defined early termination amount, if such amount is deemed to represent the investor’s claim in insolvency/resolution. ▪ The performance of the underlying, whenever it impacts the repayment of the principal amount. ▪ The contractual provisions ruling the payment of interests, to assess whether the accrued component can be properly determined and is relevant for bail-in purposes. ▪ The inclusion of an Article 12c(2)(b) SRMR clause. ▪ Any element relevant to Article 12c(2)(a) SRMR. ▪ Any settlement/close out costs. ▪ Any other term, condition, rule, mechanism or element affecting the making, timing and amount of any kind of payment owed to the holders of the debt instruments with embedded derivatives (please specify). Without prejudice to the considerations above, in principle: • the relevant amount for bail-in is defined as the outstanding amount (including accrued interest and fees, when applicable) less any existing components subject to exemptions according to Article 27(3) SRMR (e.g. covered share for bail-inable deposits indicated in data point c0300), or other factors affecting the conversion amount (e.g. safeguards under Articles 76 to 80 BRRD, as applicable); • for zero coupon bonds issued at discount (i.e. c0240 = ZCB issued at discount), the amount to be reported is the amortised face value (i.e. initially paid up amount plus accrued component of the discount) plus any applicable fees and charges (c0110); and • for structured instruments, the amount reported in field c0270 minus the value of the collateral (if given) should in principle be considered the relevant amount. In case of products where the derivative component is only affecting the coupon payment (i.e. c0250 = Only structured coupon), please refer to the points above.applicable insolvency legislation43. Furthermore, the contractual terms governing each liability might provide additional insight when performing this assessment. For debt instruments with embedded derivatives, the following list of items shall be considered: ▪ Any contractually defined floor or cap to the final redemption amount. ▪ Any contractually defined early termination amount, if such amount is deemed to represent the investor’s claim in insolvency/resolution. ▪ The performance of the underlying, whenever it impacts the repayment of the principal amount. ▪ The contractual provisions ruling the payment of interests, to assess whether the accrued component can be properly determined and is relevant for bail-in purposes. ▪ The inclusion of an Article 12c(2)(b) SRMR clause. ▪ Any element relevant to Article 12c(2)(a) SRMR. ▪ Any settlement/close out costs. ▪ Any other term, condition, rule, mechanism or element affecting the making, timing and amount of any kind of payment owed to the holders of the debt instruments with embedded derivatives (please specify). Without prejudice to the considerations above, in principle: • the relevant amount for bail-in is defined as the outstanding amount (including accrued interest and fees, when applicable) less any existing components subject to exemptions according to Article 27(3) SRMR (e.g. covered share for bail-inable deposits indicated in data point c0300), or other factors affecting the conversion amount (e.g. safeguards under Articles 76 to 80 BRRD, as applicable); • for zero coupon bonds issued at discount (i.e. c0240 = ZCB issued at discount), the amount to be reported is the amortised face value (i.e. initially paid up amount plus accrued component of the discount) plus any applicable fees and charges (c0110); and • for structured instruments, the amount reported in field c0270 minus the value of the collateral (if given) should in principle be considered the relevant amount. In case of products where the derivative component is only affecting the coupon payment (i.e. c0250 = Only structured coupon), please refer to the points above. In jurisdictions where accrued interest may not rank pari passu to the liability amount, the relevant NRA may request the reporting of interest accruals on separate line items. Own holdings (identified in field c0090) should be deducted. (42) - For the definition of ‘value’, please refer to EBA Q&A 2017_3629 (https://www.eba.europa.eu/single-rule-book-qa/- /qna/view/publicId/2017_3629). | J17: Não | O17: out_b0200_main_liabilities.0130_rlvnt_amnt_wdc | P17: Reportar Outstanding amount (0120) | Q17: Reunião 2025-09-24 Luís Capitão-Mor, Pedro Mendes: Segundo Pedro Mendes, neste campo deve reportar-se o mesmo que é reportado no Outstanding amount (0120). O Outstanding amount (0120) é a Soma de 3 campos: Outstanding principal amount (0080) + Accrued interest (0100) + Applicable fees and charges (0110). Não se deve reportar o Outstanding principal amount (0040) dado que não contém juros, e segundo Pedro Mendes em caso de resolução os juros devem ser considerados (apesar de na definição não ser referido pelo SRB que se pretende juros), como tal, deve apontar-se para o Outstanding amount (0120), que contém juros. O Outstanding amount (0120) também contém Applicable fees and charges (0110), mas esse campo conterá valor fixo 0. | R17: Campo não LT (apenas tabela Output) | S17: Não Concluído | T17: Campo de montante | U17: ok | X17: =+S17 -> Não Concluído | Y17: =+P17 -> Reportar Outstanding amount (0120)
