Workbook
Name _Toc51154475: Mapeamentos!$B$3
Name _Toc51154476: Mapeamentos!#REF!
Name _Toc51154477: Mapeamentos!#REF!
Name _Toc51154478: Mapeamentos!#REF!
Name _Toc51154479: Mapeamentos!#REF!
Name _Toc51154480: Mapeamentos!#REF!
Name _Toc51154482: Mapeamentos!#REF!
Name _Toc51154483: Mapeamentos!#REF!
Name _Toc51154484: Mapeamentos!#REF!
Name _Toc51154485: Mapeamentos!#REF!

Sheet PDS
E1: Estado Especificação | V1: Estado Desenvolvimento
C2: Total | E2: Concluido | G2: Mapeamento com LT fechado, mas parametrização pendente | I2: Novo campo, mapeamento datalake fechado, com necessidade de criar parametrização | K2: Novo campo, mapeamento datalake fechado, sem necessidade de criar parametrização | M2: Novo campo, mapeamento datalake pendente, com necessidade de criar parametrização | O2: Novo campo, mapeamento datalake pendente, sem necessidade de criar parametrização | Q2: Em curso | S2: Por iniciar | U2: Total | V2: Concluido | X2: Em curso | Z2: Por iniciar
B3: Submódulo | C3: abs | D3: Total (%) | E3: abs | F3: % | G3: abs | H3: % | I3: abs | J3: % | K3: abs | L3: % | M3: abs | N3: % | O3: abs | P3: % | Q3: abs | R3: % | S3: abs | T3: % | V3: abs | W3: % | X3: abs | Y3: % | Z3: abs | AA3: %
B4: DATA POINTS FOR IDENTIFICATION | C4: 13 | D4: =SUM(F4,H4,J4,L4,N4,O4,P4,R4,T4) -> 1 | E4: =COUNTIF(Mapeamentos!J4:J16,"Concluido") -> 13 | F4: =E4/C4 -> 1 | G4: =COUNTIF(Mapeamentos!AF4:AF16,"Mapeamento com LT fechado, mas parametrização pendente") -> 0 | H4: =G4/C4 -> 0 | I4: =COUNTIF(Mapeamentos!AF4:AH16,"Novo campo, mapeamento datalake fechado, com necessidade de criar parametrização") -> 0 | J4: =COUNTIF(Mapeamentos!AO10:AT12,"Mapeamento com LT fechado, mas parametrização pendente") -> 0 | K4: =COUNTIF(Mapeamentos!AF4:AF16,"Novo campo, mapeamento datalake fechado, sem necessidade de criar parametrização") -> 0 | L4: =COUNTIF(Mapeamentos!AW10:BD10,"Mapeamento com LT fechado, mas parametrização pendente") -> 0 | M4: =COUNTIF(Mapeamentos!AF4:AF16,"Novo campo, mapeamento datalake pendente, com necessidade de criar parametrização") -> 0 | N4: =COUNTIF(Mapeamentos!BK10:CB10,"Mapeamento com LT fechado, mas parametrização pendente") -> 0 | O4: =COUNTIF(Mapeamentos!AF4:AF16,"Novo campo, mapeamento datalake pendente, sem necessidade de criar parametrização") -> 0 | P4: =O4/C4 -> 0 | Q4: =COUNTIF(Mapeamentos!J4:J16,"Em curso") -> 0 | R4: =Q4/C4 -> 0 | S4: =COUNTIF(Mapeamentos!J4:J16,"Por iniciar") -> 0 | T4: =S4/C4 -> 0 | U4: =SUM(G4,E4,I4,K4,M4,O4,S4) -> 13 | V4: =COUNTIF(Mapeamentos!K4:K16,"Concluido") -> 13 | W4: =V4/C4 -> 1 | X4: =COUNTIF(Mapeamentos!K4:K16,"Em curso") -> 0 | Y4: =X4/C4 -> 0 | Z4: =COUNTIF(Mapeamentos!K4:K16,"Por iniciar") -> 0 | AA4: =Z4/C4 -> 0
B5: DATA POINTS FOR LINK WITH OWN FUNDS | C5: 6 | D5: =SUM(F5,H5,J5,L5,N5,O5,P5,R5,T5) -> 1 | E5: =COUNTIF(Mapeamentos!J17:J22,"Concluido") -> 6 | F5: =E5/C5 -> 1 | G5: =COUNTIF(Mapeamentos!AF17:AF22,"Mapeamento com LT fechado, mas parametrização pendente") -> 0 | H5: =G5/C5 -> 0 | I5: =COUNTIF(Mapeamentos!AF17:AF22,"Novo campo, mapeamento datalake fechado, com necessidade de criar parametrização") -> 0 | J5: =COUNTIF(Mapeamentos!AO12:AT14,"Mapeamento com LT fechado, mas parametrização pendente") -> 0 | K5: =COUNTIF(Mapeamentos!AF17:AF22,"Novo campo, mapeamento datalake fechado, sem necessidade de criar parametrização") -> 0 | L5: =COUNTIF(Mapeamentos!AW11:BD11,"Mapeamento com LT fechado, mas parametrização pendente") -> 0 | M5: =COUNTIF(Mapeamentos!AF17:AF22,"Novo campo, mapeamento datalake pendente, com necessidade de criar parametrização") -> 0 | N5: =COUNTIF(Mapeamentos!BK11:CB11,"Mapeamento com LT fechado, mas parametrização pendente") -> 0 | O5: =COUNTIF(Mapeamentos!AF17:AF22,"Novo campo, mapeamento datalake pendente, sem necessidade de criar parametrização") -> 0 | P5: =O5/C5 -> 0 | Q5: =COUNTIF(Mapeamentos!J17:J22,"Em curso") -> 0 | R5: =Q5/C5 -> 0 | S5: =COUNTIF(Mapeamentos!J17:J22,"Por iniciar") -> 0 | T5: =S5/C5 -> 0 | U5: =SUM(G5,E5,I5,K5,M5,O5,S5) -> 6 | V5: =COUNTIF(Mapeamentos!K17:K22,"Concluido") -> 6 | W5: =V5/C5 -> 1 | X5: =COUNTIF(Mapeamentos!K17:K22,"Em curso") -> 0 | Y5: =X5/C5 -> 0 | Z5: =COUNTIF(Mapeamentos!K17:K22,"Por iniciar") -> 0 | AA5: =Z5/C5 -> 0
B6: DATA POINTS FOR LINK WITH ACCOUNTING | C6: 2 | D6: =SUM(F6,H6,J6,L6,N6,O6,P6,R6,T6) -> 1 | E6: =COUNTIF(Mapeamentos!J23:J24,"Concluido") -> 2 | F6: =E6/C6 -> 1 | G6: =COUNTIF(Mapeamentos!AF23:AF24,"Mapeamento com LT fechado, mas parametrização pendente") -> 0 | H6: =G6/C6 -> 0 | I6: =COUNTIF(Mapeamentos!AF23:AF24,"Novo campo, mapeamento datalake fechado, com necessidade de criar parametrização") -> 0 | J6: =COUNTIF(Mapeamentos!AO12:AT14,"Mapeamento com LT fechado, mas parametrização pendente") -> 0 | K6: =COUNTIF(Mapeamentos!AF23:AF24,"Novo campo, mapeamento datalake fechado, sem necessidade de criar parametrização") -> 0 | L6: =COUNTIF(Mapeamentos!AW12:BD12,"Mapeamento com LT fechado, mas parametrização pendente") -> 0 | M6: =COUNTIF(Mapeamentos!AF23:AF24,"Novo campo, mapeamento datalake pendente, com necessidade de criar parametrização") -> 0 | N6: =COUNTIF(Mapeamentos!BK12:CB12,"Mapeamento com LT fechado, mas parametrização pendente") -> 0 | O6: =COUNTIF(Mapeamentos!AF23:AF24,"Novo campo, mapeamento datalake pendente, sem necessidade de criar parametrização") -> 0 | P6: =O6/C6 -> 0 | Q6: =COUNTIF(Mapeamentos!J23:J24,"Em curso") -> 0 | R6: =Q6/C6 -> 0 | S6: =COUNTIF(Mapeamentos!J23:J24,"Por iniciar") -> 0 | T6: =S6/C6 -> 0 | U6: =SUM(G6,E6,I6,K6,M6,O6,S6) -> 2 | V6: =COUNTIF(Mapeamentos!K23:K24,"Concluido") -> 2 | W6: =V6/C6 -> 1 | X6: =COUNTIF(Mapeamentos!K23:K24,"Em curso") -> 0 | Y6: =X6/C6 -> 0 | Z6: =COUNTIF(Mapeamentos!K23:K24,"Por iniciar") -> 0 | AA6: =Z6/C6 -> 0
B7: DATA POINTS FOR AMOUNTS REQUIRED FOR CALCULATION | C7: 8 | D7: =SUM(F7,H7,J7,L7,N7,O7,P7,R7,T7) -> 1 | E7: =COUNTIF(Mapeamentos!J25:J32,"Concluido") -> 8 | F7: =E7/C7 -> 1 | G7: =COUNTIF(Mapeamentos!AF25:AF32,"Mapeamento com LT fechado, mas parametrização pendente") -> 0 | H7: =G7/C7 -> 0 | I7: =COUNTIF(Mapeamentos!AF25:AF32,"Novo campo, mapeamento datalake fechado, com necessidade de criar parametrização") -> 0 | J7: =COUNTIF(Mapeamentos!AO13:AT15,"Mapeamento com LT fechado, mas parametrização pendente") -> 0 | K7: =COUNTIF(Mapeamentos!AF25:AF32,"Novo campo, mapeamento datalake fechado, sem necessidade de criar parametrização") -> 0 | L7: =COUNTIF(Mapeamentos!AW13:BD13,"Mapeamento com LT fechado, mas parametrização pendente") -> 0 | M7: =COUNTIF(Mapeamentos!AF25:AF32,"Novo campo, mapeamento datalake pendente, com necessidade de criar parametrização") -> 0 | N7: =COUNTIF(Mapeamentos!BK13:CB13,"Mapeamento com LT fechado, mas parametrização pendente") -> 0 | O7: =COUNTIF(Mapeamentos!AF25:AF32,"Novo campo, mapeamento datalake pendente, sem necessidade de criar parametrização") -> 0 | P7: =O7/C7 -> 0 | Q7: =COUNTIF(Mapeamentos!J25:J32,"Em curso") -> 0 | R7: =Q7/C7 -> 0 | S7: =COUNTIF(Mapeamentos!J25:J32,"Por iniciar") -> 0 | T7: =S7/C7 -> 0 | U7: =SUM(G7,E7,I7,K7,M7,O7,S7) -> 8 | V7: =COUNTIF(Mapeamentos!K25:K32,"Concluido") -> 8 | W7: =V7/C7 -> 1 | X7: =COUNTIF(Mapeamentos!K25:K32,"Em curso") -> 0 | Y7: =X7/C7 -> 0 | Z7: =COUNTIF(Mapeamentos!K25:K32,"Por iniciar") -> 0 | AA7: =Z7/C7 -> 0
B8: DATA POINTS FOR INFORMATION ON THE INVESTOR/CREDITOR | C8: 6 | D8: =SUM(F8,H8,J8,L8,N8,O8,P8,R8,T8) -> 1 | E8: =COUNTIF(Mapeamentos!J33:J38,"Concluido") -> 6 | F8: =E8/C8 -> 1 | G8: =COUNTIF(Mapeamentos!AF33:AF38,"Mapeamento com LT fechado, mas parametrização pendente") -> 0 | H8: =G8/C8 -> 0 | I8: =COUNTIF(Mapeamentos!AF33:AF38,"Novo campo, mapeamento datalake fechado, com necessidade de criar parametrização") -> 0 | J8: =COUNTIF(Mapeamentos!AO14:AT16,"Mapeamento com LT fechado, mas parametrização pendente") -> 0 | K8: =COUNTIF(Mapeamentos!AF33:AF38,"Novo campo, mapeamento datalake fechado, sem necessidade de criar parametrização") -> 0 | L8: =COUNTIF(Mapeamentos!AW14:BD14,"Mapeamento com LT fechado, mas parametrização pendente") -> 0 | M8: =COUNTIF(Mapeamentos!AF33:AF38,"Novo campo, mapeamento datalake pendente, com necessidade de criar parametrização") -> 0 | N8: =COUNTIF(Mapeamentos!BK14:CB14,"Mapeamento com LT fechado, mas parametrização pendente") -> 0 | O8: =COUNTIF(Mapeamentos!AF33:AF38,"Novo campo, mapeamento datalake pendente, sem necessidade de criar parametrização") -> 0 | P8: =O8/C8 -> 0 | Q8: =COUNTIF(Mapeamentos!J33:J38,"Em curso") -> 0 | R8: =Q8/C8 -> 0 | S8: =COUNTIF(Mapeamentos!J33:J38,"Por iniciar") -> 0 | T8: =S8/C8 -> 0 | U8: =SUM(G8,E8,I8,K8,M8,O8,S8) -> 6 | V8: =COUNTIF(Mapeamentos!K33:K38,"Concluido") -> 6 | W8: =V8/C8 -> 1 | X8: =COUNTIF(Mapeamentos!K33:K38,"Em curso") -> 0 | Y8: =X8/C8 -> 0 | Z8: =COUNTIF(Mapeamentos!K33:K38,"Por iniciar") -> 0 | AA8: =Z8/C8 -> 0
B9: DATA POINTS FOR GUARANTEES | C9: 18 | D9: =SUM(F9,H9,J9,L9,N9,O9,P9,R9,T9) -> 1 | E9: =COUNTIF(Mapeamentos!J39:J56,"Concluido") -> 18 | F9: =E9/C9 -> 1 | G9: =COUNTIF(Mapeamentos!AF39:AF56,"Mapeamento com LT fechado, mas parametrização pendente") -> 0 | H9: =G9/C9 -> 0 | I9: =COUNTIF(Mapeamentos!AF39:AF56,"Novo campo, mapeamento datalake fechado, com necessidade de criar parametrização") -> 0 | J9: =COUNTIF(Mapeamentos!AO15:AT17,"Mapeamento com LT fechado, mas parametrização pendente") -> 0 | K9: =COUNTIF(Mapeamentos!AF39:AF56,"Novo campo, mapeamento datalake fechado, sem necessidade de criar parametrização") -> 0 | L9: =COUNTIF(Mapeamentos!AW15:BD15,"Mapeamento com LT fechado, mas parametrização pendente") -> 0 | M9: =COUNTIF(Mapeamentos!AF39:AF56,"Novo campo, mapeamento datalake pendente, com necessidade de criar parametrização") -> 0 | N9: =COUNTIF(Mapeamentos!BK15:CB15,"Mapeamento com LT fechado, mas parametrização pendente") -> 0 | O9: =COUNTIF(Mapeamentos!AF39:AF56,"Novo campo, mapeamento datalake pendente, sem necessidade de criar parametrização") -> 0 | P9: =O9/C9 -> 0 | Q9: =COUNTIF(Mapeamentos!J39:J56,"Em curso") -> 0 | R9: =Q9/C9 -> 0 | S9: =COUNTIF(Mapeamentos!J39:J56,"Por iniciar") -> 0 | T9: =S9/C9 -> 0 | U9: =SUM(G9,E9,I9,K9,M9,O9,S9) -> 18 | V9: =COUNTIF(Mapeamentos!K39:K56,"Concluido") -> 18 | W9: =V9/C9 -> 1 | X9: =COUNTIF(Mapeamentos!K39:K56,"Em curso") -> 0 | Y9: =X9/C9 -> 0 | Z9: =COUNTIF(Mapeamentos!K39:K56,"Por iniciar") -> 0 | AA9: =Z9/C9 -> 0
B10: Total | C10: =SUM(C4:C9) -> 53 | D10: =SUM(F10,H10,J10,L10,N10,O10,P10,R10,T10) -> 1 | E10: =SUM(E4:E9) -> 53 | F10: =E10/C10 -> 1 | G10: =SUM(G4:G9) -> 0 | H10: =G10/C10 -> 0 | I10: =SUM(I4:I9) -> 0 | J10: =I10/C10 -> 0 | K10: =SUM(K4:K9) -> 0 | L10: =K10/C10 -> 0 | M10: =SUM(M4:M9) -> 0 | N10: =M10/C10 -> 0 | O10: =SUM(O4:O9) -> 0 | P10: =O10/C10 -> 0 | Q10: =SUM(Q4:Q9) -> 0 | R10: =Q10/C10 -> 0 | S10: =SUM(S4:S9) -> 0 | T10: =S10/C10 -> 0 | V10: =SUM(V4:V9) -> 53 | W10: =V10/C10 -> 1 | X10: =SUM(X4:X9) -> 0 | Y10: =X10/C10 -> 0 | Z10: =SUM(Z4:Z9) -> 0 | AA10: =Z10/C10 -> 0

Sheet Mapeamentos
B2: Instruções SRB - Bail-in data set | G2: Análise IT | N2: Instruções SRB - Novo Bail-in (MBDT) | Q2: Análise IT (Comparativo com o novo MBDT) | Z2: Análise IT + CDO (Old) | AH2: Mapeamento Financeira
B3: Tipo | C3: SRB_ID | D3: Data Point | E3: Attribute | F3: Definition | G3: Nome do campo na tabela bu_captools_work.bail_in_srb | H3: Mapeamento | I3: Comentários | J3: Estado Especificação | K3: Estado Desenvolvimento | L3: Estado Validação | N3: Ficheiro | O3: Data Point | P3: Definition | Q3: Definição igual? | R3: Estado especificação Anterior | S3: Mapeamento Anterior | T3: Requer reanálise no Novo Bail-in? | U3: Comentário | X3: Pertence/ Não Pertence ao novo Bail-in? | Z3: Nome do campo na tabela | AA3: Nome do campo no ficheiro | AB3: Desdodrável? | AC3: Mapeamento LT / Comentários | AD3: Description LT | AE3: Field Definition LT | AF3: Estado especificação | AH3: Tabela Data Lake | AI3: Campo Data Lake | AJ3: Comentário
B4: 4.2.1. DATA POINTS FOR IDENTIFICATION | C4: 1 | D4: Legal entity | E4: [Entity name] | F4: Name of the subsidiary. Free-form text identification of incorporation name of the entity for which the table is reported. Please state the official name as it is listed in corporate acts, including the indication of the incorporation form. | G4: legal_entity | H4: Campo Fixo: "BANCO SANTANDER TOTTA, S.A" | I4: Reunião Pedro Mendes 2025-01-21 | J4: Concluido | K4: Concluido | L4: OK | N4: B99.00 | O4: Name of Legal Entity | P4: Free-form text identification of the incorporation name of the entity for which the table is reported. Please state the official name as listed in corporate registry, including the indication of the company form. | Q4: Sim | R4: Concluido | S4: Novo campo lt002_instrument.entidade_desc | T4: Não | U4: No novo Bail-in este campo constará no ficheiro B99.00 que será produzido manualmente pelo Pedro Mendes | X4: 1 - Pertence ao novo Bail-in | AB4: Não | AC4: Reunião 02/10/2024 Luís Capitão-Mor, Pedro Mendes: Novo campo lt002_instrument.entidade_desc Este novo campo converterá o campo lt002_instrument.entidade que contém os códigos de Entidade Locais ('00100', '00110', ...) para o respetivo descritivo ('BANCO SANTANDER TOTTA' , 'SANTANDER-PENSOES-SOC.GEST.FUNDOS' , ...). Para tal, será necessário recorrer à tabela cd_captools.perimetro ligando o campo lt002_instrument.entidade com o campo "cod_soc_cpus", e obter o campo "descricao". Nota: Bruno Matos procedeu à alteração na tabela cd_captools.perimetro da descrição "BANCO SANTANDER TOTTA" para "BANCO SANTANDER TOTTA, S.A." no caso de cod_soc_cpus 00100 (email de Bruno Matos 31/10/2024 12:11) | AF4: Concluido | AJ4: Campo Fixo - "Banco Santander Totta S.A."
B5: 4.2.1. DATA POINTS FOR IDENTIFICATION | C5: =+C4+1 -> 2 | D5: Legal entity identifier | E5: [LEI code] | F5: LEI code (unique code) identifying the reporting entity. | G5: lei_code | H5: Campo Fixo: "549300URJH9VSI58CS32" | I5: Reunião Pedro Mendes 2025-01-21 | J5: Concluido | K5: Concluido | L5: OK | N5: B99.00 | O5: LEI of Legal Entity | P5: The unique LEI code for the entity, in line with the requirements of EMIR or the Dodd-Frank Act, for which the report is submitted. In the absence of an LEI, the ECB Monetary Financial Institutions unique Identifier (MFI ID) of the entity for use in RIAD (Register of Institutions and Affiliates Database) should be used. In the absence of both such identifiers, a local identifier must be used. | Q5: Não Contudo, aparenta ser o mesmo | R5: Concluido | S5: Novo campo lt002_instrument.lei_rprtng_entty. | T5: Não | U5: No novo Bail-in este campo constará no ficheiro B99.00 que será produzido manualmente pelo Pedro Mendes | X5: 1 - Pertence ao novo Bail-in | AB5: Não | AC5: Reunião 02/10/2024 Luís Capitão-Mor, Pedro Mendes: Novo campo lt002_instrument.lei_rprtng_entty. Partindo do campo entidade (codigo da entidade local) da lt002_instrument : 1) Identificam-se os zcliente's associados a cada consolpt (codigo da entidade local) através da tabela cd_captools.clientes_intragrupo; 2) Identificam-se os ccli_grupo's associados a esses zcliente's através da tabela cd_captools.ct003_univ_cli; 3) Identificam-se os zcliente's associados a esses ccli_grupo's através da tabela cd_captools.ct003_univ_cli; 4) Retiram-se os zcliente's com clei = '#'; 5) Para o caso de uma entidade apresentar mais do que um clei, utilizar a mesma regra que atualmente se aplica no campo lei da tabela lt003_entity (com o objetivo de se selecionar apenas um único clei). | AF5: Concluido | AJ5: Campo Fixo - "549300URJH9VSI58CS32"
B6: 4.2.1. DATA POINTS FOR IDENTIFICATION | C6: =+C5+1 -> 3 | D6: Unique identification number for the liability | E6: [ISIN/Specific ID] | F6: ID provided by the resolution entity for a liability (e.g. ISIN, contract number, account number). | G6: id_liability | H6: concat(cempresa, cbalcao, cnumecta, zdeposit) da cd_captools.fr004_cto | I6: Reunião Pedro Mendes 2025-01-21 | J6: Concluido | K6: Concluido | L6: OK | N6: B02.00 | O6: Unique internal identification number ou Unique identification number (known to the counterparty) | P6: The unique internal identifier of the instrument/liability. For deposits reported on an aggregate level, please indicate: ‘NCNP’ for the aggregated not covered not preferential deposits (field c0280 = TRUE); and ▪ ‘NCBP’ for the aggregated not covered but preferential deposits (field c0290 = TRUE). ou The unique identifier of the instrument/liability that would allow the counterparty to conclude that it will be affected by the potential resolution action, without external third parties being able to identify the creditor. For securities, the ISIN code must be indicated where available (other identifiers need only be provided in the absence of an ISIN). For deposits and other liabilities, the account/contract number should be reported. In the event of multiple tranches (multiple counterparties) of one promissory-note loan (e.g. Schuldscheindarlehen) or a syndicated loan, a unique ID must be allocated to each tranche. For deposits reported on an aggregate level, please indicate: ▪ ‘NCNP’ for the aggregated not covered not preferential deposits (field c0280 = TRUE); and ▪ ‘NCBP’ for the aggregated not covered but preferential deposits (field c0290 = TRUE). | Q6: Não | R6: Concluido | S6: lt002_instrument.instrmnt_id | T6: Sim | U6: Novo campo lt002_instrument.instrmnt_id_knwn_cntrprty em que -Se títulos: isin -Se não títulos: instrmnt_id | X6: 1 - Pertence ao novo Bail-in | AB6: Não | AC6: Reunião 02/10/2024 Luís Capitão-Mor, Pedro Mendes: lt002_instrument.instrmnt_id | AD6: Instrument ID | AE6: LT002_INSTRUMENT.INSTRMNT_ID: An identifier applied by the reporting agent to uniquely identify each instrument under a single contract. Each instrument must have one instrument identifier. This value will not change over time and cannot be used as the instrument identifier for any other instrument under the same contract. Supervised Insitutions are asked to furnish the INSTRMNT_ID with the exact same value as it is reported to AnaCredit (or any similar central credit register). If this is not available, the value shall be reported as it is internally used. If an instrument is not reported to AnaCredit but requested for the purposes of the on-site inspection please provide the bank-internally used value. | AF6: Concluido | AH6: AL029_CNT_CORE / AL030_SLD_CORE_M CT610_titulos | AI6: Chave cempresa_cbalcao_cnumecta_zdeposit para ALM isin para emissões (títulos) | AJ6: Para todos os produtos menos emissões (títulos) Para emissões (títulos)
B7: 4.2.1. DATA POINTS FOR IDENTIFICATION | C7: =+C6+1 -> 4 | D7: Nature of the instrument | E7: [e.g. bond, shares, reserves, contingent liability] | F7: Information on the nature of the liability | G7: nature_instrument | H7: 1) Para os registos que estão na cd_captools.ct610_titulos obter o campo tipo_titulo; 2) Para os registos que não estão na cd_captools.ct610_titulos aplicar a seguinte lógica: Partindo do cproduto da cd_captools.fr004_cto, obter o respetivo descritivo na cd_estruturais.tat91_tabelas (TAYD91C0_CTABELA = '023') no campo tayd91c0_gelemtab (ligando por tayd91c0_celemtab) 3) Por último, fazer o seguinte mapeamento: CARTOES MISTOS -> Other CONFIRMING -> Other CONTA CHEQUE FORNECEDORES -> Other CONTABILIZACAO CARTEIRA PROPRIA-TITULOS -> Other CONTAS CORRENTES - M.N. -> Other CONTAS CORRENTES - M/E -> Other CONTAS INTERNAS - M.N. -> Other CONTAS INTERNAS - MOEDA ESTRANGEIRA (NOSTROS) -> Other D.O. ESPECIAL -> Cash account/saving account DEP.ORDEM ME (OFFSHORE MADEIRA) -> Cash account/saving account DEP.ORDEM MN(OFFSHORE MADEIRA) -> Cash account/saving account DEPOSITO A ORDEM - M.N. (OFFSHORE CAYMAN) -> Cash account/saving account DEPOSITO A ORDEM - M.N. -> Cash account/saving account DEPOSITO A ORDEM - MOEDA ESTRANGEIRA OFFSHORE -> Cash account/saving account DEPOSITO A ORDEM - MOEDA ESTRANGEIRA -> Cash account/saving account DEPOSITO A PRAZO EM MOEDA NACIONAL -> Term deposit DEPOSITOS A PRAZO - M.E. -> Term deposit DEPOSITOS A PRAZO - M.N. (OFFSHORE) -> Term deposit DEPOSITOS A PRAZO - POUPANCA REFORMA -> Term deposit DEPOSITOS A PRAZO - PRODUTOS ESTRUTURADOS -> Term deposit DEPOSITOS A PRAZO EM MOEDA ESTRANGEIRA -> Term deposit DEPOSITOS A PRAZO EM MOEDA NACIONAL -> Term deposit DEPOSITOS DE POUPANCA -> Term deposit DEVEDORES / CREDORES DIVERSOS -> Other EMPRESTIMOS -> Other ESTRANGEIRO-AVALES E GARANTIAS -> Other FACTORING -> Other Obrigacao Hipotecaria -> Registered Bond Obrigacao Senior -> Registered Bond Obrigacao Subordinada -> Registered Bond PRODUTO GESTAO BALCAO -> Other PRODUTOS ESTRANGEIRO - CREDITOS DOCUMENTARIOS IMPORTACAO -> Other RESERVADO PARA NOVA APLICACAO DE TESOURARIA -> Borrower Note Loan SANTANDER - PRODUTOS TESOURARIA -> Other SUPER SATISFACAO RECARREGAVEL -> Other Titularizacao Sintetica -> Registered Bond Titularizacao -> Registered Bond Acao Ordinaria -> Title of ownership Acao Preferencial -> Title of ownership Emprestimo Subordinado -> Registered Bond Instrumento Fundos Proprios Adicionais Nivel 1 (AT1) -> Registered Bond Prestacao Suplementar -> Title of ownership Suprimento -> Title of ownership NULL ->MISS | I7: Reunião Pedro Mendes 2025-02-17 1) Estes cprodutos não têm tradução na TAT023, contudo, sabe-se que o cproduto 0V0 é Factoring portanto, nesse caso, o descritivo será "Factoring". Ou seja sobram apenas 33315+5 registos sem cproduto e que não vão ter nature instrument (0,77% do Universo). cproduto count(*) 33315 0V0 34797 96 5 | J7: Concluido | K7: Concluido | L7: OK | N7: B02.00 | O7: Nature of the liability | P7: The corresponding category of the instrument/liability. Value to be chosen from the following drop-down list: • Registered Bond • Bearer Bond • Borrower Note Loan • Certificate of Deposit / Commercial paper • Title of ownership44 • Cash account/saving account 45 • Term deposit 46 • Loan • Bill of exchange • Other For deposits reported on an aggregated level (Submission A), please indicate ‘Other’. | Q7: Não | R7: Em curso | S7: lt002_instrument .typ_instrmnt | T7: Sim | U7: Anteriormente a Contabilidade iria preencher o instrumento_financeiro e depois terìamos de ter um mapeamento desses valores na lt809_typ_instrmnt. Contudo, no novo Bail-in existe uma drop-down a respeitar, pelo que este campo terá de ser reanalisado. | X7: 1 - Pertence ao novo Bail-in | AB7: Não | AC7: Campo comum ao Valuation Reunião 21/11/2024 Luís Capitão-Mor, Pedro Mendes, Nuno Pinheiro, Rafael Pessoa: A solução passará por adicionar novas linhas à lt809_typ_instrmnt, concretamente, no campo "instrmnt_fncr" em que se colocarão os instrumentos financeiros de tipo_conta='P' e 'C'. Garantir que a nova parametrização não vai modificar nenhum valor atual dos Contratos do Loan Tape Estrutural. Nota: Existem mais códigos que a Corporação/BCE definiu para além dos que estão na lt809_typ_instrmnt PR: 1) distinct instrumento_finaceiro da fr802 quando tipo_conta=P, C (No caso do tipo_conta=C enviou-se email a 02/12/2024 12:19 a Rafael Pessoa/Nuno Pinheiro a solicitar o preenchimento do campo instrumento_financeiro) 2) mapear instrumento_financeiro com o código typ_instrmnt da lt809 3) fazer novo mapeamento da LT809 (ou a nova multivariável ) e o mapeamento LT829 (para Inglês) Reunião 25/10/2024 Luís Capitão-Mor, Luísa Quendera, Flávia Pinho: Identificar a tabela mais completa da 925, 926, 927; a granularidade que permite responder a todos CRC, Contabilidade, Loan Tape. Cria-se uma TAT nova Este produto/subproduto (nelem1 CRC, nelem2 Contabilidade, ...) Solução1 (não será esta a seguir devido a interferência com CRC): - Perceber a agrupação/classificação que é feita na CRC atualmente (falar com Sandra Lopes). A CRC não tem o Ativo todo (por ex: papel comercial, outros devedores, ...); - Proposta de códigos para o que falta do Ativo (Sandra Lopes); - Perceber a granularidade que o SRB quer no Bail-in (Flávia/Pedro) e fazerem uma proposta de códigos; - Ver se existe um nelem que não esteja a ser utilizado Solução 4 (será esta a seguir): Ações pedidas por Luís Capitão-Mor: 1- Papel Comercial: Ver como está a sair no LT no campo typ_instrmnt (Ver com o gonçalo marques e no limite gerar: derivados, títulos, ...) : -> Verificou-se que existe o campo instrumento_financeiro na tabela na lt809_typ_instrmnt. No caso do campo instrumento_financeiro da LT001 ='instrumentos de divida' (que é o caso dos contratos de Papel Comercial), o campo typ_instrmnt será 1005 (Debt securities) 2- Tipologias que o FINREP faz de Ativo e Passivo -> O produto que é apresentado no FINREP corresponde ao campo produto da fr802_pl_contas. Exemplo: : "Deposits" na sheet F 08.01.a do FINREP -> instrumento_financeiro="depositos" "Current accounts / overnight deposits" na sheet F 08.01.a do FINREP -> produto='depositos a ordem, overnights' Nuno Pinheiro, 24/10/2024 via teams: "a 926 tem a lista dos nossos produtos/subprodutos e no campo NELEM6 colocamos um codigo auxiliar ao mapemaneto para os produtos FINREP Através desse mapeamento, as subcontas contabilisticas de cada produto FINREP são populadas através da GLT12" Este tema foi discutido na reunião de dia 02/10/2024 e na de 24/10/2024 Reunião 02/10/2024 Luís Capitão-Mor, Pedro Mendes: O campo a utilizar será lt002_instrument.typ_instrmnt. Este campo atualmente é construído partindo da concatenação dos campos cproduto, subproduto da tabela lt001_univ_oper, cruzando com o campo tayd91c0_celemtab, obtendo depois o substr(tat91.tayd91c0_nelemc19,2,4) , ligando posteriormente com o campo c_typ_instmnt da tabela cd_loan_tapes_bce.lt809_typ_instrmnt, obtendo assim o campo typ_instrmnt Temas identificados: 1) O campo tayd91c0_nelemc19 (agregador de produtos) terá de ser preenchido para passivo. 2) Teriam de ser adicionadas novas parametrizações à tabela cd_loan_tapes_bce.lt809_typ_instrmnt, contudo, o campo typ_instrmnt contém apenas códigos numéricos, mas o bail-in pede descritivos [e.g. bond, shares, reserves, contingent liability] Query draft: select distinct concat(lt001.cempresa, lt001.cbalcao, lt001.cnumecta, lt001.zdeposit), lt809.typ_instrmnt from (select * from cd_loan_tapes_bce.lt001_univ_oper where ref_date='2024-06-30' and concat(cempresa,cbalcao,cnumecta,zdeposit)='31000601388398096000000000000000') lt001 left join (select * from cd_estruturais.tat91_tabelas where data_date_part='2024-06-28' and TAYD91C0_CTABELA = '927') tat91 on concat(lt001.cproduto, lt001.subproduto) = tat91.TAYD91C0_CELEMTAB left join (select * from cd_loan_tapes_bce.lt809_typ_instrmnt where ref_date='2024-06-30') lt809 on SUBSTR(tat91.TAYD91C0_NELEMC19,2,4) = lt809.c_typ_instmnt ; select distinct instrmnt_id,typ_instrmnt from cd_loan_tapes_bce.lt002_instrument where ref_date='2024-06-30' and instrmnt_id='31000601388398096000000000000000' ; | AF7: Em curso | AH7: AL029_CNT_CORE / AL030_SLD_CORE_M CT610_titulos | AI7: cproduto / csubproduto / origem Origem | AJ7: Code list dependendo do produto
B8: 4.2.1. DATA POINTS FOR IDENTIFICATION | C8: =+C7+1 -> 5 | D8: Jurisdiction governing the contract of the claim | E8: [e.g. FR, IT] | F8: ISO 3166-1 alpha 2-country c ode. The name of the country whose law governs the instrument. If the contract is governed by the law of more than one country, the jurisdiction, which has the highest relevance for the recognition of write down and conversion powers shall be reported. If required, IRT might also request the ISO 3166-2 to ensure more granular information (e.g. state level). | G8: governing_law | H8: 1) Para os registos que estão na cd_captools.ct610_titulos obter o campo lei_aplicavel; 2) Para os registos que não estão na cd_captools.ct610_titulos colocar valor fixo 'PT'. | I8: Reunião Pedro Mendes 2025-01-21 Query: select distinct bail_in.contract_id,ct610.lei_aplicavel, coalesce(tat91.tayd91c0_nelemc09, 'PT') from (select * from bu_captools_work.universo_temp ) bail_in left join (select CONCAT(cempresa,cbalcao,cnumecta,zdeposit) as contract_id,* from cd_captools.ct610_titulos where ref_date='2024-11-30') ct610 on bail_in.contract_id = ct610.contract_id left join (select * from cd_estruturais.tat91_tabelas where data_date_part='2024-09-30' and TAYD91C0_CTABELA ='015') tat91 on ct610.lei_aplicavel = tat91.tayd91c0_celemtab; --------------------------------------------------------------------------------------------------------------------------- query para traduzir o campo lei_aplicavel (ex: 620) para ISO 3166-1 alpha 2-country code (ex: PT): select distinct ct610.lei_aplicavel, tat91.tayd91c0_nelemc09 from (select * from cd_captools.ct610_titulos where ref_date='2024-11-30') ct610 left join (select * from cd_estruturais.tat91_tabelas where data_date_part='2024-09-30' and TAYD91C0_CTABELA ='015') tat91 on ct610.lei_aplicavel = tat91.tayd91c0_celemtab | J8: Concluido | K8: Concluido | L8: OK | N8: B02.00 | O8: Governing law | P8: The ISO 3166-1 alpha-2 code of the country whose law governs the instrument (please use the ISO 3166-2 code when the law of an administrative subdivision is relevant, e.g. ‘US-NY’). If the contract is governed by the law of more than one country, the country whose law has the highest relevance for the recognition of writedown and conversion powers must be reported. For deposits reported on an aggregate level, please indicate ‘XX’. | Q8: Não Contudo, aparenta ser o mesmo | R8: Em curso | S8: Novo campo lt002_instrument (nome por definir) | T8: Sim | U8: Na nova definição é indicado: "For deposits reported on an aggregate level, please indicate ‘XX’." | X8: 1 - Pertence ao novo Bail-in | AB8: Não | AC8: Reunião 27/11/2024 com Luís Capitão-Mor, Pedro Mendes e Reunião 15/11/2024 com Luís Capitão-Mor, Pedro Mendes, Pedro Henriques, Luís Henriques, Rogério Sacadura, Sandra Santos: Títulos: campo "lei_aplicavel" da cd_captools.ct610_titulos Papel Comercial (SIGOM): Novo campo na al007_prog_ppc. Este novo campo (de preenchimento obrigatório) será acrescentado no(s) ecrã(s) respetivo do SIGOM e depois será enviado nos ficheiros sigom_ppc e sigom_irl_ppc que o ALM consome (Reunião 21/11/2024 com Luís Gatinho, Luís Capitão-Mor, Luís Henriques, Rogério Sacadura, Luís Baptista). Derivados e REPOs (SIGOM): Novo campo na al012_cq_alm. Este novo campo (de preenchimento obrigatório) será acrescentado no(s) ecrã(s) respetivo do SIGOM e depois será enviado no ficheiro cq_isda que o ALM consome (Reunião 21/11/2024 com Luís Gatinho, Luís Capitão-Mor, Luís Henriques, Rogério Sacadura, Luís Baptista) Email 26/11/2024 10:11 de Luís Capitão-Mor com a indicação das tabelas de ALM onde deverá constar este campo (al007_prog_ppc e al012_cq_alm) - Luís Capitão-Mor solicitou a Luís Henriques que envie um email com (para o Papel Comercial e Derivados/REPOs): 1) Requisitos 2) Estimativa 3) Calendário de entrega Depósitos: Segundo Pedro Mendes, deverá ser reportado 'PT' para todos os depósitos (DPs, CRPs, DOs, Estruturados, Poupança). Email recebido de Pedro Mendes a 02/12/2024 14:32. Money Market e Loan and Depo: Pedro Mendes referiu " Deverá ficar a lei do país da contraparte. Ou seja, se for com um Banco cujo país é França deve ficar “FR”, Alemanha “DE”, etc," Questões LCM: 1) Questão genérica: Qual a melhor forma de filtrar os sub universos ( derivados, titulos, depósitos, money market, papel comercial, etc ) -> pela fr802 ? Para Money Market e Loan and Depos: , Pedro Mendes referiu " Deverá ficar a lei do país da contraparte. Ou seja, se for com um Banco cujo país é França deve ficar “FR”, Alemanha “DE”, etc," . 2) Para Money Market, pode-se utilizar o campo "gpais_contraparte" da tabela al004_det_mm ? 3) Para Loan and Depos, pode-se utilizar o campo "zcliente" da tabela al010_loandepos, e em seguida ir à tabela ct003_univ_cli, e trazer o campo "cpais_residencia" ? 4) lei_aplicavel da ct610 está atualmente no formato ISO 3166-1 de 3 dígitos (ex: 620), contudo, no pedido que se fez ao SIGOM não se definiu o formato, mas deveria ser o mesmo em todo o lado: os 3 dígitos (ex: 620) ou 2 dígitos (ex: PT). Caso fossem os 3 dígitos, na tabela de parametrização multivariada transformaríamos para os 2 digitos solicitados pelo SRB. 5) ISO 3166-2 não se aplica no nosso caso, certo? -> nivel informação distritos ( PT-11 -> Lisboa, PT-13 -> Porto, etc ... ) | AF8: Em curso | AH8: CT610_titulos | AI8: lei_aplicavel | AJ8: Para todos os produtos menos emissões (títulos) - "PT" Para emissões (títulos)
B9: 4.2.1. DATA POINTS FOR IDENTIFICATION | C9: =+C8+1 -> 6 | D9: Contract currency | E9: [e.g. EUR, USD] | F9: ISO 4217 currency code. The currency in which the instrument is issued. | G9: contract_currency | H9: 1) Para os registos que estão na cd_captools.ct610_titulos obter o campo cmoeda; 2) Para os registos que não estão na cd_captools.ct610_titulos obter o campo cmoeda1 da cd_captools.fr004_cto. Adicionalmente, converter os campos cmoeda/cmoeda1 nos respetivos descritivos, que constam na cd_estruturais.tat91_tabelas (TAYD91C0_CTABELA = '206') no campo tayd91c0_gelemtab (ligando por tayd91c0_celemtab). Nota: Se o campo cmoeda1 = 'NULL' ou ' ' , forçar 'EUR'. | I9: Reunião Pedro Mendes 2025-01-21 Query para traduzir o caso do campo cmoeda1 (ex: 978) para o ISO4217 (ex: EUR): select distinct fr004_cto.cmoeda1, coalesce(tat91.TAYD91C0_NELEMC01, 'EUR') from (select * from cd_captools.fr004_cto where ref_date='2024-09-30') fr004_cto left join (select * from cd_estruturais.tat91_tabelas where data_date_part='2024-09-30' and TAYD91C0_CTABELA = '206') tat91 on fr004_cto.cmoeda1 = tat91.tayd91c0_celemtab | J9: Concluido | K9: Concluido | L9: OK | N9: B02.00 | O9: Contract currency | P9: The currency in which the instrument/liability is issued. The currency must be reported with its 3-letter ISO 4217 code. For deposits reported on an aggregate level, please indicate ‘XXX’._x000D_ | Q9: Não Contudo, aparenta ser o mesmo | R9: Concluido | S9: LT002_INSTRUMENT.CRRNCY_DNMNTN | T9: Sim | U9: Na nova definição é indicado: "For deposits reported on an aggregate level, please indicate ‘XX’." | X9: 1 - Pertence ao novo Bail-in | AB9: Não | AC9: Reunião 02/10/2024 Luís Capitão-Mor, Pedro Mendes: LT002_INSTRUMENT.CRRNCY_DNMNTN | AD9: Currency denomination | AE9: Currency denomination of instruments, in accordance with the ISO 4217 standard. | AF9: Concluido | AH9: AL029_CNT_CORE / AL030_SLD_CORE_M CT610_titulos | AI9: cmoeda_pass cmoeda | AJ9: Para todos os produtos menos emissões (títulos) Para emissões (títulos)
B10: 4.2.1. DATA POINTS FOR IDENTIFICATION | C10: =+C9+1 -> 7 | D10: Issuance Date | E10: [date] | F10: Date of the original issuance of the instrument | G10: issuance_date | H10: 1) Para os registos que estão na cd_captools.ct610_titulos obter o campo campo dt_emissao. Adicionalmente, deverá converter-se o formato do campo dt_emissao para aaaa-mm-dd (atualmente encontra-se no formato dd-mm-aaaa). 2) Para os registos que não estão na cd_captools.ct610_titulos obter o campo campo data_abertura da cd_captools.fr004_cto. | I10: Reunião Pedro Mendes 2025-01-21 Query: SELECT ct610.contract_id,concat(substr(ct610.dt_emissao,7,4),substr(ct610.dt_emissao,3,4),substr(ct610.dt_emissao,1,2)) AS dt_emissao, coalesce(concat(substr(ct610.dt_emissao,7,4),substr(ct610.dt_emissao,3,4),substr(ct610.dt_emissao,1,2)),fr004.data_abertura) AS data_emissao_final FROM (SELECT CONCAT(cempresa,cbalcao,cnumecta,zdeposit) AS contract_id,* FROM cd_captools.fr004_cto WHERE ref_date = '2024-09-30') fr004 INNER JOIN (SELECT CONCAT(cempresa,cbalcao,cnumecta,zdeposit) AS contract_id,* FROM cd_captools.ct610_titulos WHERE ref_date = '2024-09-30') ct610 ON fr004.contract_id = ct610.contract_id; Notas: verificámos que: --ref_date='2024-09-30' --#384 contratos na ct610 --#205 contratos estao na fr004 --#179 contratos não estao na fr004 Não deveriam estar todos os titulos na fr004? Aplicando os filtros definidos pela Contablidade temos apenas 64 títulos: select count( distinct ct610.contract_id) from (select * from bu_captools_work.bail_in_univ_cto) univ inner join (select CONCAT(cempresa,cbalcao,cnumecta,zdeposit) as contract_id, * from cd_captools.ct610_titulos where ref_date = '2024-09-30') ct610 on univ.contract_id = ct610.contract_id ; | J10: Concluido | K10: Concluido | L10: OK | N10: B02.00 | O10: Date of issuance | P10: Date of the original issuance of the liability. Format required: yyyy-mm-dd. This field is not applicable for liabilities of the type ‘Cash account/saving account’ (c0140) and deposits reported in aggregated form (Submission A). For securities issued as part of a tap issue, i.e. an issuance of additional securities under an ISIN that already exists, there should only be one row including all securities under that ISIN. The date of issuance should be the issuance date of the first issue under that ISIN. | Q10: Não Contudo, aparenta ser o mesmo | R10: Concluido | S10: LT002_INSTRUMENT.DT_INCPTN | T10: Sim | U10: Na nova definição é indicado: "This field is not applicable for liabilities of the type ‘Cash account/saving account’ (c0140) and deposits reported in aggregated form (Submission A)" | X10: 1 - Pertence ao novo Bail-in | AB10: Não | AC10: Reunião 02/10/2024 Luís Capitão-Mor, Pedro Mendes: LT002_INSTRUMENT.DT_INCPTN | AD10: Date of inception | AE10: The date on which the contractual relationship originated, i.e. the date on which the contract agreement becomes binding for all parties | AF10: Concluido | AH10: AL029_CNT_CORE / AL030_SLD_CORE_M CT610_titulos | AI10: dinicio dt_emissão | AJ10: Para todos os produtos menos emissões (títulos) Para emissões (títulos)
B11: 4.2.1. DATA POINTS FOR IDENTIFICATION | C11: =+C10+1 -> 8 | D11: Legal Maturity Date | E11: [date] | F11: Date of the legal, final maturity of the instrument. For perpetual instruments, this should be ‘2099-01-31’. | G11: legal_maturity_date | H11: 1) Para os registos que estão na cd_captools.ct610_titulos obter o campo campo dt_vencim. Adicionalmente, deverá converter-se o formato do campo dt_vencim para aaaa-mm-dd (atualmente encontra-se no formato dd-mm-aaaa). 2) Para os registos que não estão na cd_captools.ct610_titulos obter o campo campo data_vencimento da cd_captools.fr004_cto. | I11: Reunião Pedro Mendes 2025-02-10 Query: Aplicar mesma lógica do campo acima. | J11: Concluido | K11: Concluido | L11: OK | N11: B02.00 | O11: Legal maturity | P11: Date of the legal, final maturity of the instrument or liability (including term deposits). Format required: yyyy-mm-dd. For perpetual instruments, the bank should report ‘2099-01-31’. If not applicable, the bank should report ‘0001-01-01’. This field is not applicable for liabilities of the type ‘Cash account/saving account’ (c0140) and for deposits reported in aggregated form (Submission A). | Q11: Não Contudo, aparenta ser o mesmo | R11: Concluido | S11: LT002_INSTRUMENT.DT_LGL_FNL_MTRTY | T11: Sim | U11: Na nova definição é indicado: "This field is not applicable for liabilities of the type ‘Cash account/saving account’ (c0140) and for deposits reported in aggregated form (Submission A)." | X11: 1 - Pertence ao novo Bail-in | AB11: Não | AC11: Reunião 02/10/2024 Luís Capitão-Mor, Pedro Mendes: LT002_INSTRUMENT.DT_LGL_FNL_MTRTY | AD11: Legal final maturity date (latest repayment date) | AE11: The contractual maturity date of the instrument, taking into account any agreements amending initial contracts. As for retail revolving credit facilities this attribute is to be reported "not applicable". | AF11: Concluido | AH11: AL029_CNT_CORE / AL030_SLD_CORE_M CT610_titulos | AI11: dfim dt_vencim | AJ11: Para todos os produtos menos emissões (títulos) Para emissões (títulos)
B12: 4.2.1. DATA POINTS FOR IDENTIFICATION | C12: =+C11+1 -> 9 | D12: Earliest redemption date | E12: [date] | F12: If an option exists for the holders of the instrument to request early reimbursement, or conditions for early reimbursement are contractually foreseen, the earliest occurrence date should be completed. If the early reimbursement relates to only a portion of the liability (e.g. early reimbursement of 50% of the nominal amount), the liability should be split to take into account this partial early redemption clause. | G12: earliest_redemption_date | H12: 1) Para os registos que estão na cd_captools.ct610_titulos obter o campo dt_prim_amrt_ant_inv. 2) Para os registos que não estão na cd_captools.ct610_titulos colocar valor fixo 'N/A' (Varchar Default value for not applicable fields). Nota: Caso campo dt_prim_amrt_ant_inv da cd_captools.ct610_titulos = NULL colocar 'N/A' | J12: Concluido | K12: Concluido | L12: OK | N12: B02.00 | O12: Earliest redemption date | P12: If an option exists for holders of the instrument to request early reimbursement, or conditions for early reimbursement are contractually provided, the earliest occurrence date should be reported. Format required: yyyy-mm-dd. If that date corresponds to the legal maturity (c0210), please report the latter. If not applicable, the bank should report ‘0001-01-01’. This field is not applicable for liabilities of the type ‘Cash account/saving account’ (c0140) and for deposits reported in aggregated form (Submission A). | Q12: Não Contudo, aparenta ser o mesmo | R12: Em curso | S12: Em curso | T12: Sim | U12: Na nova definição é indicado: "If that date corresponds to the legal maturity (c0210), please report the latter. If not applicable, the bank should report ‘0001-01-01’. This field is not applicable for liabilities of the type ‘Cash account/saving account’ (c0140) and for deposits reported in aggregated form (Submission A)." | X12: 1 - Pertence ao novo Bail-in | AB12: Não | AC12: Reunião 29/11/2024, 27/11/2024 e 02/10/2024 Luís Capitão-Mor, Pedro Mendes: Terão de ser adicionados 2 campos na ct004_univ_cto/ fr004_cto, no entanto, o Loan Tape apenas consumirá o campo 2 (nesta fase estará preenchido apenas para o Ativo): Campo 1: 1ª data de quando será possível a mobilização antecipada (data de abertura + 1 ) Campo 2: Próxima data de quando será possível a mobilização antecipada (data de referência +1) - Para títulos: 1) Luis Capitão-Mor, solicitou que se verifique se a codificação dos campos de frequência da tabela al029_cnt_core_m são todos traduzidos pelas TAT's ( 248,785) Campo 1: campo dt_prim_amrt_ant_inv da ct610_titulos (primeira data possível de amortização antecipada por opção do investidores) Campo 2: campo dt_prim_amrt_ant_inv e de forma iterativa, somar campo frq_amrt_ant_inv até ultrapassar data de referência e menor que a data de vencimento. Ex: data de referência dos dados: 2024-11-30 dt_prim_amrt_ant_inv= 2024-11-15 frq_amrt_ant_inv= 201 (MENSAL) ( este campo pode assumir mais valores, Men, Diario,Trimens campo 1= 2024-11-15 campo 2= 2024-12-05 -> 2024-11-15 + ( Códigos:212,202,206,101,201,203,301) Contudo, estes dois campos estão sempre a N/A ou NULL (Pedro Mendes terá de falar com Miguel para que estes campos passem a vir preenchidos); - Para Depósitos: a) Para DPs ( alguns DPs estruturados só permitem mobilização antecipada em certos momentos) e CRPs (no fundo são DPs com pagamentos intercalares que permite reforços): Ver com a Andreia Pontífice. Ver se os interfaces DCT001, DCT02, ...(PR vai analisar tabelas do datalake). Se não encontrarmos, falar com a Andreia Pontífice (Sandra Lopes podes ajudar na conversa). Luís Capitão-Mor sabe que ela consegue acrescentar o campo sem grande dificuldade (claro que depois tem de se alterar a ingesta). Se não existir, seriam 2 campos novos no interface: Campo 1: 1ª data de quando será possível a mobilização antecipada (data de abertura + 1 ) Campo 2: Próxima data de quando será possível a mobilização antecipada (data de referência +1) Para os DPs que não permitam mobilização antecipada ficariam a N/A? (Mas para isso precisávamos de um Campo 3 que seria uma flag que indicaria se o depósito permite ou não mobilização antecipada) b) Para DOs (não terá de se adicionar nenhum campo novo pois estes 2 campos ficarão hard coded na ct004) Campo 1: data de abertura + 1 Campo 2: data de referência+1 -Falar com o João Godinho, no modelo comum de dados, quais foram as tabelas input ( indentificar as chaves,características) que foram definidas. Para DO's, DP's,CRP's Pedro Mendes: - Deverá verificar se há mais produtos em que se aplique este campo Questões LCM: Campo 1 na ct004/fr004: data de abertura + 1 Campo 2 na ct004/fr004: data de referência+1 (será este que o LT consome) | AF12: Em curso | AH12: AL029_CNT_CORE / AL030_SLD_CORE_M | AJ12: Para todos produtos é o dia seguinte à data de referência com exceção de títulos emitidos e derivados que é igual
B13: 4.2.1. DATA POINTS FOR IDENTIFICATION | C13: =+C12+1 -> 10 | D13: Date of the next interest payment | E13: [date] | F13: The payment date from which the income distribution is made available for payment by the bank. | G13: payment_interest_date | H13: Tabela cd_alm.al029_cnt_core_m: - se tipo balanço = P, buscar campo dt_prox_liq_juros_pas Nota: Usar Tradutores FINREP, ALM. | I13: Reunião Pedro Mendes 2025-01-21 | J13: Concluido | K13: Concluido | L13: OK | N13: B02.00 | O13: Date of the next interest payment | P13: The payment date from which the income distribution is made available for payment by the reporting entity. Format required: yyyy-mm-dd. If not applicable (e.g. shares), the bank should report ‘0001-01-01’. This field is not applicable for deposits reported in aggregated form (Submission A). | Q13: Não Contudo, aparenta ser o mesmo | R13: Concluido | S13: Novo campo lt002_instrument (nome por definir) | T13: Sim | U13: Na nova definição é indicado: "If not applicable (e.g. shares), the bank should report ‘0001-01-01’. This field is not applicable for deposits reported in aggregated form (Submission A)." | X13: 1 - Pertence ao novo Bail-in | AB13: Não | AC13: Reunião 15/10/2024: Luís Capitão-Mor, Pedro Mendes: Tabela cd_alm.al029_cnt_core_m: - se tipo balanço = P, buscar campo dt_prox_liq_juros_pas - se tipo balanço = A, buscar campo dt_prox_liq_juros_act | AF13: Concluido | AH13: AL029_CNT_CORE / AL030_SLD_CORE_M CT610_titulos | AI13: dt_prox_liq_jur_pass dt_proc_liq_jur | AJ13: Para todos os produtos menos emissões (títulos) Para emissões (títulos)
B14: 4.2.1. DATA POINTS FOR IDENTIFICATION | C14: =+C13+1 -> 11 | D14: Outstanding amount | E14: [Euro amount] | F14: The amount is the aggregate of the outstanding principal amount as at the request date plus, if applicable, interest accrued up to the request date and fees and charges, irrespective of whether and to what extent the relevant principal, interest or fees and charges liability was already due as at the request date and whether it is required to be recognised as an item of liabilities in the balance sheet of the subsidiary of the resolution entity prepared in accordance with the applicable accounting principles. | G14: outstanding_amount | H14: Campo msaldo_final da cd_captools.fr001_univ_saldo | I14: Mapeamento novo Reunião Pedro Mendes 2025-03-31: Campo msaldo_final da cd_captools.fr001_univ_saldo (para reconciliar com o FINREP) Mapeamento antigo Reunião Pedro Mendes 2025-02-04: Campo valor_bruto_on_p da cd_captools.fr004_cto No Loan Tape, GRSS_CRRYNG_AMNT_INSTRMNT= NVL ( SUM(-1*VALOR_BRUTO_ON) ; 0) | J14: Concluido | K14: Concluido | L14: OK | N14: B02.00 | O14: Outstanding amount | P14: Total EUR value of the outstanding amount of the instrument/deposit held by the counterparty, calculated as the sum of the amounts reported in data points c0080, c0100 and c0110 (where applicable). The amount is in fact the aggregate of the outstanding principal amount plus, if applicable, interest accrued up to the reference date, and fees and charges, irrespective of whether and to what extent the relevant principal, interest or fee-and-charge liability was already due as at the reference date and whether it is required to be recognised as a liability item in the relevant entity’s balance sheet drawn up in accordance with the applicable accounting principles. In jurisdictions where accrued interest may not rank pari passu to the liability amount, the relevant NRA may request the reporting of interest accruals on separate line items. | Q14: Não Contudo, aparenta ser o mesmo | R14: Concluido | S14: Reunião 13/12/2024: Luís Capitão-Mor, Pedro Mendes: Novo campo LT002_INSTRUMENT.GRSS_CRRYNG_AMNT_INSTRMNT_VECTOR Reunião 15/10/2024: Luís Capitão-Mor, Pedro Mendes: 'LT002_INSTRUMENT.GRSS_CRRYNG_AMNT_INSTRMNT | T14: Sim | X14: 1 - Pertence ao novo Bail-in | AB14: Sim, Montante | AC14: Reunião 13/12/2024: Luís Capitão-Mor, Pedro Mendes: Novo campo LT002_INSTRUMENT.GRSS_CRRYNG_AMNT_INSTRMNT_VECTOR Reunião 15/10/2024: Luís Capitão-Mor, Pedro Mendes: 'LT002_INSTRUMENT.GRSS_CRRYNG_AMNT_INSTRMNT | AD14: Gross carrying amount | AE14: Reported gross carrying amount for the instrument according to definition in Annex V to Implementing Regulation (EU) No 680/2014. | AF14: Concluido | AH14: AL029_CNT_CORE / AL030_SLD_CORE_M | AI14: mon_cap_st1_vivo
B15: 4.2.1. DATA POINTS FOR IDENTIFICATION | C15: =+C14+1 -> 12 | D15: Rank of liability (on- and -off balance sheet) within the national insolvency ranking | E15: [number] | F15: Rank of liability according to the national insolvency ranking. | G15: insolvency_ranking | H15: 1) Para os registos que estão na cd_captools.ct610_titulos obter o campo rank_insolv. Nota: Caso campo rank_insolv = NULL, preencher 'MISS'. 2) Para os registos que não estão na cd_captools.ct610_titulos, mapear: CARTOES MISTOS -> Ranking 14 CONFIRMING -> Ranking 9 CONTA CHEQUE FORNECEDORES -> Ranking 14 CONTABILIZACAO CARTEIRA PROPRIA-TITULOS -> Ranking 9 CONTAS CORRENTES - M.N. -> Ranking 9 CONTAS CORRENTES - M/E -> Ranking 9 CONTAS INTERNAS - M.N. -> Ranking 9 CONTAS INTERNAS - MOEDA ESTRANGEIRA (NOSTROS) -> Ranking 9 DEVEDORES / CREDORES DIVERSOS -> Ranking 14 EMPRESTIMOS -> Ranking 9 ESTRANGEIRO-AVALES E GARANTIAS -> Ranking 9 FACTORING -> Ranking 9 NULL -> Ranking 14 PRODUTO GESTAO BALCAO -> Ranking 14 PRODUTOS ESTRANGEIRO - CREDITOS DOCUMENTARIOS IMPORTACAO -> Ranking 9 RESERVADO PARA NOVA APLICACAO DE TESOURARIA -> Ranking 20 SUPER SATISFACAO RECARREGAVEL -> Ranking 12 SANTANDER - PRODUTOS TESOURARIA -> Ranking 9 Registos que estejam na fg001 e que não tenham ( calinea = '#' e flag_ativo = '1') -> Ranking 12 Nota: Os produtos apresentados acima, resultam do campo nature_instrument (SRB_ID='4') antes da conversão para Inglês. 3) Para os registos que se encontrem na tabela cd_alm.fg001_fgd com calinea = ‘#’ e flag_ativo = ‘1’: 3.1) Mapear ranking 14 (depósitos elegiveis para FGD). 3.2) Se sum(campo mtot_nao_coberto_por_depositante) por contrato da cd_alm.fg001_fgd > 0 e se SME(campo cod_empr_pme da business_sme2003361.out_sme_2003_361 in ('1','2','3')) ou Households(campo SRB_ID_34 = 'Households (1)'), criar um vector com a seguinte estrutura (14;13), ou seja, nestes casos, teremos um contrato com dois ranking's, 14 e 13. 3.3) Para os restantes, criar um vector com a seguinte estrutura (14;12), ou seja, nestes casos, teremos um contrato com dois ranking's, 14 e 12. 4) Para os restantes registos, preencher 'MISS'. 5) Para os Registos com cproduto = '020' (nature_instrument = 'Cash account/saving account') com ranking = 'MISS', mapear com ranking 9. | I15: Reunião Pedro Mendes 2025-02-17 Nota: Existem 299 registos com cproduto = '020' ( nature_instrument = 'Cash account/saving account') com ranking = 'MISS' (para ref_date='2024-12-31'). Questionou-se a Sandra Brito, no sentido de perceber qual o motivo de não estarem na tabela fg001 (email enviado 2025-03-07). Sandra Brito respondeu, dando a justificação pela qual não constam na tabela fg001 tais registos. Segundo mail enviado por Pedro Mendes ( 2025-03-14) os registos que tenham cproduto = '020' e nature_instrument = 'Cash account/saving account', deverão ter ranking 9. | J15: Concluido | K15: Concluido | N15: B02.00 | O15: Insolvency ranking_x000D_ | P15: The corresponding insolvency ranking of the instrument. Numeric value (e.g. integer of 1 or more) | Q15: Não Contudo, aparenta ser o mesmo | R15: Em curso | S15: Em curso | T15: Sim | U15: No novo Bail-in este campo poderá ir apenas até ao ranking 8 (a confirmar) | X15: 1 - Pertence ao novo Bail-in | AB15: Sim | AC15: Reunião 06/12/2024: Luís Capitão-Mor, Pedro Mendes: (O) Reunião 15/10/2024: Luís Capitão-Mor, Pedro Mendes: - Tabela de parametrização em que os campos desta tabela representam critérios: Esta tabela constará no bloco de resolução do Front-end na mesma localização da tabela de parametrização do campo abaixo (SRB_ID 13) Owner da cd_alm.fg001_fgd é a Sandra Brito Depósitos: -> 14 Covered deposits (deposits guaranteed by the FGD, up to the coverage level): if ‘calinea’ = ‘#’ and flag_ativo =‘1’ and mtot_coberto_por_depositante <= 100.000 (cd_alm.fg001_fgd) ->13 Deposits that would be eligible deposits from natural persons,micro, small and medium-sized enterprises were they not made through branches located outside the EU of institutions established within the EU Questão: O BST tem balcões foram da União Europeia? O Totta Ireland está na Irelanda portanto pertence à União Europeia. Se não houver mais balcões fora de PT para alé do Totta Ireland, então este valor de ranking não se aplica. -> 13 Eligible deposits above EUR 100,000 held by natural persons and micro, small and medium sized enterprises. if ‘calinea’ = ‘#’ and flag_ativo =‘1’ and mtot_coberto_por_depositante > 100.000 (da tabela cd_alm.fg001_fgd) if itip_cli='F' (da tabela cd_captools.ct003_univ_cli) and cod_empr_pme in ('1','2','3') (da tabela out_sme_2003_361) -> Deposits above EUR 100,000 that are not held by natural persons and micro, small and medium sized enterprises (i.e., deposits held by larger companies and some excluded deposits, such as deposits made on behalf and for the account of credit institutions), except if such deposits result from: • Operations pertaining to which a criminal court decision has been issued on account of money laundering; • The depositor has not been identified pursuant to the antimoney laundering legislation in force; and • Deposits held by persons or entities that have, in the two years before the date on which deposits became unavailable or on which a resolution measure was adopted, a direct or indirect holding which represents at least 2% of the share capital of the credit institution or have been members of the management body of the credit institution, except if proven that they did cause through their action or failure to act the financial difficulties experienced by the credit institution or helped to aggravate that situation. if ‘calinea’ = ‘#’ and flag_ativo =‘1’ and mtot_coberto_por_depositante > 100.000 (da tabela cd_alm.fg001_fgd) if itip_cli='J' (da tabela cd_captools.ct003_univ_cli) and cod_empr_pme in ('0') (da tabela out_sme_2003_361) Segundo o documento funcional do FGD (LCM partilhou e consta na pasta do Teams da documentação): "Os registos de depósito que beneficiam da cobertura pelo FGD podem identificar-se na tabela de output cd_alm.fg001_fgd considerando as condições ‘calinea’ = ‘#’ e flag_ativo = ‘1’, pelo que desconsiderando os registos que (i) tenham, automaticamente, a alínea (campo ‘calinea’) igual ao artigo 165º - “Depósitos excluídos da garantia” do Decreto-Lei 298/92 - Regime Geral das Instituições de Crédito e Sociedades Financeiras, ou em que (ii) o utilizador tenha excluído manualmente o respetivo titular na tabela de parametrização cd_alm.fg801_filtro_cli. - No PDF em anexo extraído do site de SRB, temos o Insolvency Ranking mais recente. Necessário perceber a fonte dos rankings mencionados. - existe o campo rank_insolv na tabela CT610_TITULOS, contudo verifica-se que nos útlimos dois meses, existiam mais rankings NULL's do que 3 e 17 (Pedro Mendes terá de solicitar a Miguel Silva para atualizar): ref_date rank_insolv count(*) 2024-09-30 NULL 263 2024-09-30 17 113 2024-09-30 3 8 2024-08-31 NULL 247 2024-08-31 3 8 2024-08-31 17 113 | AF15: Em curso | AH15: AL029_CNT_CORE / AL030_SLD_CORE_M CT610_titulos | AI15: cproduto / csubproduto / origem Origem | AJ15: Code list dependendo do produto
B16: 4.2.1. DATA POINTS FOR IDENTIFICATION | C16: =+C15+1 -> 13 | D16: Instrument/liability is issued to or bought by an existing shareholder that is not part of the same resolution group | E16: [yes/no] | F16: Flag to identify if a liability is issued to or bought by an existing shareholder that is not part of the same resolution group according to Article 12g(2)a point i SRMR. | G16: flag_same_resol_group | H16: - 'yes' para a lista de zclientes abaixo (não fazem parte do mesmo grupo de resolução do BST) - 'no' para todos os restantes zclientes 1) Para os registos que estão na cd_captools.ct610_titulos obter o campo zcliente_investidor 2) Para os registos que não estão na cd_captools.ct610_titulos obter o campo zcliente da cd_captools.fr004_cto Lista de zclientes (não fazem parte do mesmo grupo de resolução do BST): 0000238954 6511000505 7400416271 7400416353 7400416520 7400416611 7400416763 7400507283 7400701625 7401474691 7401536276 8037849269 8043363752 8044173594 8046250676 8046296743 8046334916 9001925092 | I16: Reunião Pedro Mendes 2025-01-21 | J16: Concluido | K16: Concluido | L16: OK | N16: B02.00 | O16: Instrument/liability is issued to or bought by an existing shareholder that is not part of the same resolution group | P16: Flag to identify whether a liability is issued to or bought by an existing shareholder that is not part of the same resolution group according to Article 12g(2)(a)(i) SRMR. The value to be reported is a TRUE/FALSE Boolean | Q16: Não Contudo, aparenta ser o mesmo | R16: Em curso | S16: Em curso | T16: Sim | U16: Na nova definição é indicado: "The value to be reported is a TRUE/FALSE Boolean". No antigo era: "[yes/no]" | X16: 1 - Pertence ao novo Bail-in | AB16: Não | AC16: Reunião 18/12/2024 (Luís Capitão-Mor, Pedro Mendes, Nuno Pinheiro e Paulo Cavaleiro), 31/10/2024 e 17/10/2024 com Luís Capitão-Mor, Pedro Mendes: A tabela cd_alm.rr802_hier_ent (disponível no Front-end no Módulo do Universo - separador Parametrizações), em princípio, será alterada (saem os campos metodo, tipo_rela e flag_controlo) para conter os seguintes campos: nome_perimetro, entidade_pai, entidade_filho, participacao_direta, participacao_efetiva, ckutulmo, htimest e ref_date. 1) A Contabilidade deverá preencher 2 secções: • 1ª secção: entidade_pai, entidade_filho e participacao_direta • 2ª secção: nome_perimetro, entidade_filho, participacao_efetiva deverá proceder às seguintes alterações no ficheiro: No ficheiro enviado no email de 11/12/2024 00:06 de Nuno Pinheiro: - retirar o 'I_' dos campos entidade_pai e entidade_filho (ou seja, não deverá constar 'I_00001' mas sim '00001') ; - atualizar as designações dos perímetros; - atualizar as designações dos campos que constam no ficheiro para os que constam na tabela cd_alm.rr802_hier_ent. Ou seja, não deverá constar perimetro, holding company, investee, %direct e %effective mas sim nome_perimetro, entidade_pai, entidade_filho, participacao_direta, participacao_efetiva. 2) Verificar com Carlos Isidoro se existe impacto no processo SAS ao se alterar a estrutura da tabela (neste caso retirar campos). Se não tiver impacto, nada tem que ser feito do lado do SAS. Contudo, se tiver impacto, para além de alterar o SAS para a nova estrutura da tabela deverá dar também esta nova informação ao Paulo Cavaleiro. Pressionar email de Paulo Cavaleiro 18/12/2024 11:37 para obter resposta de Carlos Isidoro 3) Confirmar se a tabela é não é de Parametrização, ou seja é mesmo 600 ou é 800 (o comportamento é diferente). Terá de ser 800 4) Deveria alterar-se já em Janeiro por causa do freeze do bahia. Lógica Processo: 1) Terá de ser criada uma Tabela de parametrização que não estará no Loan Tape (ou seja não será uma tabela LT%) dado que é transversal. Luís Capitão-Mor solicitou que se fale com o João Bernardes para discutir o nome e a BD da mesma. Conterá os seguintes campos: Código Entidade Cargabal Pai ( teria sempre o valor '00001', ou seja, o Banco Santander S.A. -> este campo será necessário apenas para o campo SRB_ID 35), Número do Grupo de Resolução, Código Entidade Cargabal, ckutulmo, htimest e ref_date. Nesta fase, a tabela será preenchida apenas para o grupo de resolução onde consta o BST (cada grupo de resolução pode ter 1 ou mais Entidades). Esta tabela constará no Front_end no bloco "Resolução", existindo uma 3ª linha a seguir às linhas "SRB Valuation Data Set", "SRB Bail-in Data Set" (terá de se definir o nome desta 3ª linha). Esta tabela será mensal e terá de ser atualizada automaticamente todos os meses em d+1, em que se copiará a parametrização do mês anterior. Naturalmente que o Utilizador poderá depois alterar a parametrização (tal como se faz na ct805); 2) Parte-se do contrato da tabela LT001 que tem um zcliente associado, depois converte-se esse zcliente no respetivo codigo Entidade Local através da Tabela clientes_intragrupo. A ligação entre estas 2 tabelas é feita por zcliente. O Código da Entidade Local consta no campo "consolpt" da Tabela clientes_intragrupo; 3) Aceder à tabela cd_alm.rr802_hier_ent ligando o campo "entidade_filho" (que representa o código da Entidade filho Local) ao campo "consolpt" da Tabela clientes_intragrupo; 4) Identificar todas as "entidade_pai" (que representa o código da Entidade pai Local), de forma recursiva, associadas a cada entidade_filho do passo anterior, até chegar à última "entidade_pai" ( ex: entidade_filho = '00100' tem "entidade_pai" = 01000', e entidade_filho='00100' tem "entidade_pai='00001', ou seja entidade_filho='00100' tem dois ascendentes ( '01000','00001') (ver folha digarama_estrutura_accionista); 6) Converter todos os código da "entidade_pai" ( que se encontram com o código local), para o respetivo código corporativo, através do campo "consoles" da tabela clientes_intragrupo); 7) Verificar se todos os códigos do campo "entidade_pai" do passo anterior, se encontram na tabela de parametrização, caso algum dos códigos não se encontre, então o valor da Flag do campo pretendido, ficará a Não. Caso contrário, Flag ficará a sim. A lógica será: 1) parte-se do contrato da tabela LT001 que tem um zcliente associado, depois converte-se esse zcliente no respetivo codigo Entidade Cargabal através da Tabela clientes_intragrupo. A ligação entre estas 2 tabelas é feita por zcliente. O Código da Entidade Cargabal consta no campo "consoles" da Tabela clientes_intragrupo. 2) Verificar se esse código da Entidade Cargabal É ou NÃO É accionista? (O acionista do BST é o Banco Santander S.A. que tem o código da Entidade Cargabal 00001) Condição1: Se não for accionista, ou seja, se tiver um código da Entidade Cargabal <> 00001 então flag='no' Condição 2: Se for accionista, ou seja, se tiver um código da Entidade Cargabal = 00001. Verificar se esse código da Entidade Cargabal consta na tabela de Parametrização: Se constar, significa que essa entidade faz parte do mesm o grupo de resolução que o BST (isto porque nesta fase a tabela de parametrização será preenchida apenas para o grupo de resolução onde consta o BST), então flag='no' Se não constar, significa que essa entidade não faz parte do mesm o grupo de resolução que o BST (isto porque nesta fase a tabela de parametrização será preenchida apenas para o grupo de resolução onde consta o BST), então flag='yes' O Acionista do BST é o Banco Santander S.A.. Logo terá de se equacionar se o Acionista fica hardcoded ou se se vai beber esta informação do acionista a essa tabela. Dúvidas: Tem de se partir do zcliente emitente/zcliente investidor da Tabela ct610 ou parte-se do zcliente da lt001? | AF16: Em curso | AH16: AL029_CNT_CORE / AL030_SLD_CORE_M CT610_titulos | AI16: cproduto / csubproduto / origem Origem | AJ16: Code list dependendo do produto
B17: 4.2.2. DATA POINTS FOR LINK WITH OWN FUNDS | C17: 14 | D17: Type of own funds at subsidiary level | E17: [acc. LDR guidance] | F17: According to existing LDR guidance value can be ‘CET1’, ‘Fully Compliant AT1’, ‘Grandfathered AT1’, ‘Fully Compliant T2’, ‘Grandfathered T2’, ‘T2 in phase-out’ or ‘Partially AT1 and T2’. | G17: type_own_funds | H17: 1) Para os registos que estão na cd_captools.ct610_titulos obter o campo eleg_fund_prop. 2) Para os registos que não estão na cd_captools.ct610_titulos colocar valor fixo 'N/A' (Varchar Default value for not applicable fields) . Nota: Na ct610_titulos, caso se obtenham registos a ' ' ou a 'NULL', colocar valor fixo 'N/A' (Varchar Default value for not applicable fields). | I17: Reunião Pedro Mendes 2025-01-21 | J17: Concluido | K17: Concluido | L17: OK | N17: B02.00 | O17: Type of own funds at individual level ou Type of own funds at consolidated level | P17: Indicate the type of own funds, as classified at individual level: • T2 in phase-out; • Grandfathered T2; • Fully Compliant T2; • Partially (A)T1 and T2; • Grandfathered AT1; • Fully Compliant AT1; • CET1; • No. In the list of options, the term ‘phase-out’ refers to the period of 5 years before maturity of any given T2 instrument, during which there is only proportionate recognition based on the time remaining until maturity. ‘Grandfathered’ should be understood as any transitional measure applicable to a T2 instrument, not including the ‘phase-out’. During this ‘grandfathering’, recognition may be full or partial. If the instrument is not classified as own funds, please indicate ‘No’ ou Indicate the type of own funds, as classified at consolidated level: • T2 in phase-out; • Grandfathered T2; • Fully Compliant T2; • Partially (A)T1 and T2; • Grandfathered AT1; • Fully Compliant AT1; • CET1; • No. In the list of options, the term ‘phase-out’ refers to the period of 5 years before maturity of any given T2 instrument, during which there is only proportionate recognition based on the time remaining until maturity. ‘Grandfathered’ should be understood as any transitional measure applicable to a T2 instrument, not including the ‘phase-out’. During this ‘grandfathering’, recognition may be full or partial. If the instrument is not classified as own funds, please indicate ‘No’. | Q17: Não | R17: Concluido | S17: Novo campo lt002_instrument (nome por definir) | T17: Sim | U17: Existem 2 campos no novo Bail-in. | X17: 1 - Pertence ao novo Bail-in | AB17: sim | AC17: Reunião 02/10/2024 e 22/10/2024 Luís Capitão-Mor, Pedro Mendes: - campo eleg_fund_prop da tabela cd_captools.ct610_titulos., contudo verifica-se que nos útlimos dois meses, existiam mais tipo NULL's do que AT1, CET1, GF2: ref_date eleg_fund_prop count(*) 2024-09-30 AT1 5 2024-09-30 CET1 3 2024-09-30 GF2 8 2024-09-30 NULL 368 2024-08-31 AT1 5 2024-08-31 CET1 3 2024-08-31 GF2 8 2024-08-31 NULL 352 Pedro Mendes solicitará a Miguel Silva para preencher este campo com os valores exactos do SRB: ‘CET1’, ‘Fully Compliant AT1’, ‘Grandfathered AT1’, ‘Fully Compliant T2’, ‘Grandfathered T2’, ‘T2 in phase-out’ or ‘Partially AT1 and T2’. Só tem titulos. Há muitos titulos de passivos ( tudo o que é ativo é null) fazer ligação à cd_captools.ct610_titulos. | AF17: Concluido | AH17: CT610_titulos | AI17: Origem | AJ17: Code list dependendo do produto
B18: 4.2.2. DATA POINTS FOR LINK WITH OWN FUNDS | C18: 15 | D18: Amount eligible as own funds at subsidiary level. | F18: The actual amount in EUR of the instrument qualifying as own funds, taking into account phase-out as applicable. | G18: amount_own_funds | H18: 1) Para os registos que estão na cd_captools.ct610_titulos obter o campo mon_fund_prop. 2) Para os registos que não estão na cd_captools.ct610_titulos colocar valor fixo 0. Nota: Na ct610_titulos, caso se obtenham registos a ' ' ou a 'NULL', colocar valor fixo 0. | I18: Reunião Pedro Mendes 2025-01-21 | J18: Concluido | K18: Concluido | L18: OK | N18: B02.00 | O18: Eligible amount for own funds at individual level ou Eligible amount for own funds at consolidated level | P18: The actual amount in EUR of the instrument qualifying as own funds at individual level. ou The actual amount in EUR of the instrument qualifying as own funds at consolidated level. | Q18: Não | R18: Concluido | S18: Novo campo lt002_instrument (nome por definir) | T18: Sim | U18: Existem 2 campos no novo Bail-in. | X18: 1 - Pertence ao novo Bail-in | AB18: Sim, Montante | AC18: Reunião 22/10/2024 Capitão-Mor, Pedro Mendes: campo mon_fund_prop na tabela CT610_Titulos Pedro Mendes solicitará a Miguel Silva para preencher este campo | AF18: Concluido | AH18: AL030_SLD_CORE_M | AI18: mon_cap_st1_vivo + mon_jur_st1 | AJ18: Fórmula dependendo do campo "origem" da CT610_títulos - 0 para que não tiver na CT610 o valor para o que tiver
B19: 4.2.2. DATA POINTS FOR LINK WITH OWN FUNDS | C19: 16 | D19: Amount of subordinated liabilities not eligible as own funds at subsidiary level | E19: [Euro amount] | F19: The actual amount in EUR of the subordinated debt instrument not qualifying as own funds | G19: amount_subord_liabil_not_own_funds | H19: Campo fixo: 0 | I19: Reunião Pedro Mendes 2025-01-21 | J19: Concluido | K19: Concluido | L19: OK | R19: Por iniciar | X19: 2 - Não pertence ao novo Bail-in | AC19: Este campo é N/A (comentário financeira) ???? | AF19: Por iniciar | AH19: n/a | AI19: n/a | AJ19: n/a
B20: 4.2.2. DATA POINTS FOR LINK WITH OWN FUNDS | C20: 17 | D20: If liability is, at the level of the subsidiary, assigned to more than one own funds component, indication of the second own funds component | E20: [AT1/T2] | F20: This data point is requested for the case that the liability is assigned to more than one own funds component and is needed to calculate the impact of the write-down and conversion powers / bail-in tool on the own funds. | G20: second_own_funds_component | H20: Campo Fixo: 'N/A' | I20: Reunião Pedro Mendes 2025-02-04 | J20: Concluido | K20: Concluido | L20: OK | R20: Por iniciar | X20: 2 - Não pertence ao novo Bail-in | AC20: ??? | AF20: Por iniciar | AH20: CT610_titulos | AI20: Origem | AJ20: Code list dependendo do produto
B21: 4.2.2. DATA POINTS FOR LINK WITH OWN FUNDS | C21: 18 | D21: Eligible amount for own funds component according to point above | E21: [Euro amount] | F21: This data point is requested for the case that not the full amount of the liability is eligible as own funds. | G21: amount_own_funds_component | H21: Campo fixo: 0 | I21: Reunião Pedro Mendes 2025-02-04 | J21: Concluido | K21: Concluido | L21: OK | R21: Por iniciar | X21: 2 - Não pertence ao novo Bail-in | AC21: ??? (este data Point está relacionado com o data point acima) | AF21: Por iniciar | AH21: AL030_SLD_CORE_M | AI21: mon_cap_st1_vivo + mon_jur_st1 | AJ21: Fórmula dependendo do campo "origem" da CT610_títulos - 0 para que não tiver na CT610 o valor para o que tiver
B22: 4.2.2. DATA POINTS FOR LINK WITH OWN FUNDS | C22: 19 | D22: If own funds, agio of the liability/instrument | E22: [Euro amount] | F22: To the extent relevant under (national) GAAP, bond premium classified in capital reserves. | G22: agio_own_funds | H22: Campo fixo: 0 | I22: Reunião Pedro Mendes 2025-02-04 | J22: Concluido | K22: Concluido | L22: OK | R22: Por iniciar | X22: 2 - Não pertence ao novo Bail-in | AC22: ??? | AF22: Por iniciar | AH22: AL030_SLD_CORE_M | AI22: mon_cap_st1_vivo + mon_jur_st1 | AJ22: Fórmula dependendo do campo "origem" da CT610_títulos - 0 para que não tiver na CT610 o valor para o que tiver
B23: 4.2.3. DATA POINTS FOR LINK WITH ACCOUNTING | C23: 20 | D23: Carrying amount IFRS | E23: [Euro amount] | F23: To the extent relevant for the bank, carrying amount under IFRS. | G23: carrying_amount_ifrs | H23: Campo msaldo_final da cd_captools.fr001_univ_saldo | I23: Mapeamento novo Reunião Pedro Mendes 2025-03-31: Campo msaldo_final da cd_captools.fr001_univ_saldo (para reconciliar com o FINREP) Mapeamento antigo Reunião Pedro Mendes 2025-02-04: Campo valor_bruto_on_p da cd_captools.fr004_cto No LT: CRRYNG_AMNT_INSTRMNT= GRSS_CRRYNG_AMNT_INSTRMNT - ACCMLTD_IMPRMNT_INSTRMNT GRSS_CRRYNG_AMNT_INSTRMNT= NVL ( SUM(-1*VALOR_BRUTO_ON) ; 0) ACCMLTD_IMPRMNT_INSTRMNT= PROVISAO_ON (segundo rafael pessoa não existe provisões de passivo) | J23: Concluido | K23: Concluido | L23: OK | N23: B02.00 | O23: Carrying amount IFRS | P23: To the extent relevant for the bank, the carrying amount under IFRS58. nota58:When precise values are not available, estimates can be used to fill this data point | Q23: Não Contudo, aparenta ser o mesmo | R23: Concluido | S23: "Reunião 13/12/2024: Luís Capitão-Mor, Pedro Mendes: LT002_INSTRUMENT.GRSS_CRRYNG_AMNT_INSTRMNT 'Reunião 28/10/2024: Luís Capitão-Mor, Pedro Mendes: LT002_INSTRUMENT.CRRYNG_AMNT_INSTRMNT" | T23: Sim | X23: 1 - Pertence ao novo Bail-in | AB23: Sim, Montante | AC23: Reunião 13/12/2024: Luís Capitão-Mor, Pedro Mendes: LT002_INSTRUMENT.GRSS_CRRYNG_AMNT_INSTRMNT 'Reunião 28/10/2024: Luís Capitão-Mor, Pedro Mendes: LT002_INSTRUMENT.CRRYNG_AMNT_INSTRMNT | AD23: CRRYNG_AMNT_INSTRMNT: Carrying amount | AE23: CRRYNG_AMNT_INSTRMNT: Net carrying amount including accrued interest as laid down in Annex 5 Regulation 680/2014. | AF23: Concluido | AH23: AL030_SLD_CORE_M | AI23: mon_cap_st1_vivo + mon_jur_st1 | AJ23: Fórmula dependendo do campo "origem" da CT610_títulos - 0 para que não tiver na CT610 o valor para o que tiver
B24: 4.2.3. DATA POINTS FOR LINK WITH ACCOUNTING | C24: 21 | D24: Carrying amount national GAAP | E24: [Euro amount] | F24: Carrying amount under national GAAP | G24: carrying_amount_national_gaap | H24: Campo msaldo_final da cd_captools.fr001_univ_saldo | I24: Mapeamento novo Reunião Pedro Mendes 2025-03-31: Campo msaldo_final da cd_captools.fr001_univ_saldo (para reconciliar com o FINREP) Mapeamento antigo Reunião Pedro Mendes 2025-02-04: Campo valor_bruto_on_p da cd_captools.fr004_cto Reunião 2024-10-28: Luís Capitão-Mor, Pedro Mendes: Pedro Mendes questionou Graça Vale via Teams a 28/10/2024-> Segundo Graça Vale não existe diferença entre o IFRS e o national GAAP. Referiu também que reportaria o mesmo valor nestes 2 campos (Carrying amount IFRS e Carrying amount national GAAP). | J24: Concluido | K24: Concluido | L24: OK | N24: B02.00 | O24: Carrying amount national GAAP | P24: Carrying amount under national GAAP (where applicable)59. Nota59:When precise values are not available, estimates can be used to fill this data point. | Q24: Não | R24: Concluido | S24: Reunião 28/10/2024: Luís Capitão-Mor, Pedro Mendes: Pedro Mendes questionou Graça Vale via Teams a 28/10/2024-> Segundo Graça Vale não existe diferença entre o IFRS e o national GAAP. Referiu também que reportaria o mesmo valor nestes 2 campos (Carrying amount IFRS e Carrying amount national GAAP). Será portanto um campo novo LT002_INSTRUMENT.CRRYNG_AMNT_NGAAP_INSTRMNT que conterá o valor do campo anterior (LT002_INSTRUMENT.CRRYNG_AMNT_INSTRMNT). | T24: Sim | U24: Na nova definição é indicado: "where applicable". Portanto, se no nosso caso iríamos anteriormente mapear com o campo acima, agora se calhar deveríamos preencher not applicable. | X24: 1 - Pertence ao novo Bail-in | AB24: Sim, Montante | AC24: Reunião 28/10/2024: Luís Capitão-Mor, Pedro Mendes: Pedro Mendes questionou Graça Vale via Teams a 28/10/2024-> Segundo Graça Vale não existe diferença entre o IFRS e o national GAAP. Referiu também que reportaria o mesmo valor nestes 2 campos (Carrying amount IFRS e Carrying amount national GAAP). Será portanto um campo novo LT002_INSTRUMENT.CRRYNG_AMNT_NGAAP_INSTRMNT que conterá o valor do campo anterior (LT002_INSTRUMENT.CRRYNG_AMNT_INSTRMNT). | AF24: Concluido | AH24: AL030_SLD_CORE_M | AI24: mon_cap_st1_vivo + mon_jur_st1 | AJ24: Fórmula dependendo do campo "origem" da CT610_títulos - 0 para que não tiver na CT610 o valor para o que tiver
B25: 4.2.4. DATA POINTS FOR AMOUNTS REQUIRED FOR CALCULATION | C25: 22 | D25: Original amount issued in EUR | E25: [Euro amount] | F25: Original amount issued in EUR. | G25: original_amount_issued_eur | H25: 1) Para os registos que estão na cd_captools.ct610_titulos obter o campo nom_tot_inic. 2) Para os registos que não estão na cd_captools.ct610_titulos colocar valor fixo 0. | I25: Reunião Pedro Mendes 2025-01-29 | J25: Concluido | K25: Concluido | L25: OK | N25: B02.00 | O25: Original amount issued in EUR | P25: The EUR (counter)value of the total issue size of the instrument, irrespective of the effective issuance dates, i.e. the total nominal amount / face value of a specific liability. For shares, it should reflect the face value / carrying amount of the shares. If a nominal value does not exist, this field is not applicable. This data point is not applicable for cash accounts / saving accounts and deposits reported in aggregated form (Submission A). If a value is reported in a foreign currency (c0060), the amount must additionally be converted into euros and reported in the corresponding EUR field (c0050), using the euro reference exchange rate published by the ECB on the date for which the information is reported40. In the case of foreign currencies for which no euro reference exchange rate is available, a customary market reference rate must be used. If such other customary reference exchange rates are used, a uniform source must be used wherever possible. | Q25: Não | R25: Em curso | S25: Em curso | T25: Sim | X25: 1 - Pertence ao novo Bail-in | AB25: Sim, Montante | AC25: Reunião 28/10/2024: Luís Capitão-Mor, Pedro Mendes: Por exemplo, um CRP foi aberto com um montante inicial de 1000 eur, entretanto o Cliente efetuou vários reforços e atualmente tem 5000 eur. O montante que se pede aqui são os 1000 eur. Dora Roxo comentou que existe um campo no LT sobre o montante inicial, contudo, é apenas sobre Crédito (Ativo): cmmtmnt_instrmnt_incptin Abordagens sugeridas por Luís Capitão-Mor: Abordagem 1) Passar a ter um campo na ct004 com este conceito (capital inicial) tal como existe o campo ddvencim_orig (data de vencimento original). E depois o LT consumiria este campo. Abordagem 2) Novo campo no LT original amount issued: Para Títulos: campo nom_tot_inic da ct610_titulos? (definição do campo: Nominal total da emissão do título, na data de emissão. É, pois, um valor que se deve manter igual ao longo do tempo.) Para DOs: Reportar sempre 0 Para o que não é Títulos: Identificar data de início do instrumento e obter o valor que tinha na ct001 nessa data: Para DPs (Simulação): --Total DPs 2024-09-30: #1055722 (há #34 com dabertur a vazio) --Total DPs 2024-09-30 para os quais se encontra a ref_date de final de mes correspondente à data de abertura na ct001: #507667 (ou seja, #548055 que não se encontram) --Total DPs 2024-09-30 para os quais se encontra a ref_date de final de mes correspondente à data de abertura na ct083: #148668 (ou seja, #148668 que não se encontram) Para Derivados: --Total Derivados 2024-09-30: #653 (há #28 com dabertur a vazio) --para os quais se encontra a ref_date de final de mes correspondente à data de abertura na ct001: #440 Questões adicionais LCM: - Não chegámos a falar sobre Depósitos estruturados, Depósitos com Pré-Aviso, Depósitos Poupança, CRPs -> seria para aplicar a mesma lógica de DPs -Como filtrar os sub-universos: Títulos, DOs, DPs, CRPs: Será pelo fr802_pl_contas Query: DPs: select count(distinct concat(ct001.cempresa, ct001.cbalcao, ct001.cnumecta, ct001.zdeposit)) --select distinct concat(ct001.cempresa, ct001.cbalcao, ct001.cnumecta, ct001.zdeposit), ct004.dabertur, ct001_semdata.ref_date, ct001_semdata.msaldo_final --select * from (select * from cd_captools.ct001_univ_saldo where ref_Date='2024-09-30') ct001 inner join (select * from cd_captools.fr802_pl_contas where ref_Date='2024-09-30' and cod_plano='BST_IND' and tipo_conta='P' and instrumento_financeiro='depositos' and produto='depositos a prazo') fr802 --(select * from cd_captools.fr802_pl_contas where ref_Date='2024-09-30' and cod_plano='BST_IND' and tipo_conta='P' and instrumento_financeiro='titulos de divida emitidos') fr802 on ct001.ccontab_final_ifrs = fr802.conta inner join (select * from cd_captools.ct004_univ_cto where ref_Date='2024-09-30') ct004 on concat(ct001.cempresa, ct001.cbalcao, ct001.cnumecta, ct001.zdeposit) = concat(ct004.cempresa, ct004.cbalcao, ct004.cnumecta, ct004.zdeposit) --left join inner join (select * from cd_captools.ct001_univ_saldo --where --cnaturic='C' ) ct001_semdata --(select * from cd_captools.ct083_univ_sal_d where cnaturic='C') ct083 on concat(ct001.cempresa, ct001.cbalcao, ct001.cnumecta, ct001.zdeposit)= concat(ct001_semdata.cempresa, ct001_semdata.cbalcao, ct001_semdata.cnumecta, ct001_semdata.zdeposit) --on concat(ct001.cempresa, ct001.cbalcao, ct001.cnumecta, ct001.zdeposit)= concat(ct083.cempresa, ct083.cbalcao, ct083.cnumecta, ct083.zdeposit) and strleft(ct004.dabertur, 7) = strleft(ct001_semdata.ref_date, 7) --and ct004.dabertur = ct083.ref_date --where concat(ct001_semdata.cempresa, ct001_semdata.cbalcao, ct001_semdata.cnumecta, ct001_semdata.zdeposit) is null ; Derivados: select count(distinct concat(ct001.cempresa, ct001.cbalcao, ct001.cnumecta, ct001.zdeposit)) --select distinct concat(ct001.cempresa, ct001.cbalcao, ct001.cnumecta, ct001.zdeposit), ct004.dabertur, ct001_semdata.ref_date, ct001_semdata.msaldo_final --select * from (select * from cd_captools.ct001_univ_saldo where ref_Date='2024-09-30') ct001 inner join (select * from cd_captools.fr802_pl_contas where ref_Date='2024-09-30' and cod_plano='BST_IND' and tipo_conta='P' --and instrumento_financeiro='depositos' and produto='depositos a prazo' and instrumento_financeiro='derivados' ) fr802 --(select * from cd_captools.fr802_pl_contas where ref_Date='2024-09-30' and cod_plano='BST_IND' and tipo_conta='P' and instrumento_financeiro='titulos de divida emitidos') fr802 on ct001.ccontab_final_ifrs = fr802.conta inner join (select * from cd_captools.ct004_univ_cto where ref_Date='2024-09-30') ct004 on concat(ct001.cempresa, ct001.cbalcao, ct001.cnumecta, ct001.zdeposit) = concat(ct004.cempresa, ct004.cbalcao, ct004.cnumecta, ct004.zdeposit) where ct004.dabertur='' or ct004.dabertur is null --left join inner join (select * from cd_captools.ct001_univ_saldo where cnaturic='C') ct001_semdata --(select * from cd_captools.ct083_univ_sal_d where cnaturic='C') ct083 on concat(ct001.cempresa, ct001.cbalcao, ct001.cnumecta, ct001.zdeposit)= concat(ct001_semdata.cempresa, ct001_semdata.cbalcao, ct001_semdata.cnumecta, ct001_semdata.zdeposit) --on concat(ct001.cempresa, ct001.cbalcao, ct001.cnumecta, ct001.zdeposit)= concat(ct083.cempresa, ct083.cbalcao, ct083.cnumecta, ct083.zdeposit) and strleft(ct004.dabertur, 7) = strleft(ct001_semdata.ref_date, 7) --and ct004.dabertur = ct083.ref_date --where concat(ct001_semdata.cempresa, ct001_semdata.cbalcao, ct001_semdata.cnumecta, ct001_semdata.zdeposit) is null ; DO's : depositos a ordem, overnights Atacar com cnaturic=C | AF25: Em curso
B26: 4.2.4. DATA POINTS FOR AMOUNTS REQUIRED FOR CALCULATION | C26: 23 | D26: Original amount issued in foreign currency, if applicable | E26: [Amount in FX] | F26: Original amount issued in foreign currency. | G26: original_amount_issued_currency | H26: Campo fixo: 0 | I26: Reunião Pedro Mendes 2025-01-29 | J26: Concluido | K26: Concluido | L26: OK | N26: B02.00 | O26: Original amount issued in foreign currency | P26: Same as c0050 above, but in the foreign currency (where relevant). Please also report the EUR-converted amount in the corresponding EUR field (c0050). This data point is not applicable for cash accounts / savings accounts and deposits reported in aggregated form (Submission A). | Q26: Não | R26: Em curso | S26: Em curso | T26: Sim | X26: 1 - Pertence ao novo Bail-in | AB26: Sim, Montante | AC26: Este campo é igual ao campo acima, mas em moeda estrangeira | AF26: Em curso
B27: 4.2.4. DATA POINTS FOR AMOUNTS REQUIRED FOR CALCULATION | C27: 24 | D27: Outstanding principal amount | E27: [Euro amount] | F27: Value of the outstanding principal amount of the instrument. | G27: outstanding_principal_amount | H27: Outstanding principal amount = Outstanding amount (SRB_ID 11) - Accrued interest (SRB_ID 25) | I27: Reunião Pedro Mendes 2025-02-21 Lógica LT: 'OTSTNDNG_NMNL_AMNT_INSTRMNT=GRSS_CRRYNG_AMNT_INSTRMNT - ACCRD_INTRST_INSTRMNT 'No nosso caso, seria: Campo valor_bruto_on_p da cd_captools.fr004_cto - ACCRD_INTRST_INSTRMNT (definido abaixo, ver como fazer no nosso caso) GRSS_CRRYNG_AMNT_INSTRMNT: VALOR_BRUTO_ON da cd_captools.fr004_cto | J27: Concluido | K27: Concluido | L27: OK | N27: B02.00 | O27: Outstanding principal amount | P27: The EUR (counter)value of the outstanding principal amount of the instrument/liability. The difference between the original amount issued and the outstanding principal amount may be due to partial buybacks of the instrument, amortising instruments, etc. The portion of eligible liabilities subscribed by intragroup entities and excluded under Article 27(3)(h) SRMR must be included in the outstanding principal amount. Only claims against other parties must be reported (i.e. excluding the portion held by the entity itself, which must be reported in field c0090). For zero coupon bonds issued at discount (i.e. c0240 = ZCB issued at discount) the final redemption amount should be reported. | Q27: Não | R27: Concluido | S27: LT002_INSTRUMENT.OTSTNDNG_NMNL_AMNT_INSTRMNT | T27: Sim | X27: 1 - Pertence ao novo Bail-in | AB27: Sim, Montante | AC27: Reunião 29/10/2024 Luís Capitão-Mor, Pedro Mendes: LT002_INSTRUMENT.OTSTNDNG_NMNL_AMNT_INSTRMNT | AD27: Outstanding gross nominal amount | AE27: Principal amount outstanding at the end of the reporting reference date, including unpaid past due interest but excluding accrued interest. The outstanding nominal amount must be reported net of write-offs and write-downs as determined by the relevant accounting practices. | AF27: Concluido | AH27: AL030_SLD_CORE_M | AI27: mon_cap_st1_vivo
B28: 4.2.4. DATA POINTS FOR AMOUNTS REQUIRED FOR CALCULATION | C28: 25 | D28: Accrued interest | E28: [Euro amount] | F28: Value of the outstanding accrued interest on the instrument. | G28: accrued_interest | H28: Aplicar a seguinte query: SELECT CONCAT(cempresa,cbalcao,cnumecta,zdeposit) AS contract_id, NVL(SUM(MSALDO_FINAL), 0) as accrued_interest FROM (SELECT * FROM cd_captools.fr001_univ_saldo WHERE ref_date ='${ref_date}' ) AS fr001 INNER JOIN (SELECT * FROM cd_captools.fr802_pl_contas WHERE ref_date = '${ref_date}' AND cod_plano = 'BST_IND' AND COMPOSICAO_VALOR = 'juros/encargos a pagar' AND (tipo_conta='P' OR (tipo_conta='C' AND instrumento_financeiro='instrumentos de capital')) ) AS fr802 ON fr001.ccontab_final_ifrs = fr802.conta GROUP BY 1 | I28: Reunião Pedro Mendes 2025-02-21 | J28: Concluido | K28: Concluido | L28: OK | N28: B02.00 | O28: Accrued interest | P28: The EUR (counter)value of the outstanding accrued interest on the instrument. In jurisdictions where accrued interests do not rank pari passu to the principal liability amount, the relevant NRAs have the option to request the reporting of interest accruals on separate line items41. Only claims against third parties must be reported (i.e. excluding the proportion held by the entity itself, which must be reported in field c0090). In case the field is not applicable (e.g. shares, zero coupon bonds issued at discount), please refer to the specific instructions in the Technical Annex. | Q28: Não | R28: Concluido | S28: LT002_INSTRUMENT.ACCRD_INTRST_INSTRMNT | T28: Sim | X28: 1 - Pertence ao novo Bail-in | AB28: Sim, Montante | AC28: Reunião 29/10/2024 Luís Capitão-Mor, Pedro Mendes: LT002_INSTRUMENT.ACCRD_INTRST_INSTRMNT | AD28: Accrued interest balance as recognised on the balance sheet | AE28: The amount of accrued interest on loans at the reporting reference date as defined in Regulation (EU) No 1071/2013 (ECB/2013/33). In accordance with the general principle of accruals accounting, interest receivable on instruments should be subject to on-balance sheet recording as it accrues (i.e. on an accruals basis) rather than when it is actually received (i.e. on a cash basis). | AF28: Concluido | AH28: AL030_SLD_CORE_M | AI28: mon_jur_st1
B29: 4.2.4. DATA POINTS FOR AMOUNTS REQUIRED FOR CALCULATION | C29: 26 | D29: Relevant amount for write-down/conversion | E29: [Euro amount] | F29: Amount eligible for calculation of write-down / conversion rate. Defined as the outstanding amount of the liability (including accrued interest) less existing components not subject to write-down / conversion power according to Article 21 SRMR. In jurisdictions where accrued interest may not rank pari passu to the liability amount, jurisdictions may want to request reporting of interest accruals on separate line items | G29: amount_writedown | H29: 1) Para os registos que estão na cd_captools.ct610_titulos com rank_insolv in ('1','2','3','8') obter Campo msaldo_final da cd_captools.fr001_univ_saldo (para reconciliar com o FINREP) 2) Para os restantes registos colocar valor fixo 0. | I29: Mapeamento novo Reunião Pedro Mendes 2025-03-31: 1) Para os registos que estão na cd_captools.ct610_titulos com rank_insolv in ('1','2','3','8') obter valor_bruto_on_p da cd_captools.fr004_cto 2) Para os restantes registos colocar valor fixo 0. Mapeamento antigo Reunião Pedro Mendes 2025-02-17: 1) Para os registos que estão na cd_captools.ct610_titulos com rank_insolv in ('1','2','3','8') obter valor_bruto_on_p da cd_captools.fr004_cto 2) Para os restantes registos colocar valor fixo 0. | J29: Concluido | K29: Concluido | L29: OK | N29: B02.00 | O29: Relevant amount for Bail-in/WDC | P29: Total EUR value of the amount eligible for write-down / conversion. Pursuant to Article 48(1) BRRD, resolution authorities shall exercise the write-down and conversion powers in accordance with the cascade set out in letters (a) to (e) of Article 48(1) BRRD. Article 48(2) BRRD further provides that "when applying the write down or conversion powers, resolution authorities shall allocate the losses [...] by reducing the principal amount of, or outstanding amount payable in respect of, those shares or other instruments of ownership and bail-inable liabilities to the same extent pro rata to their value42 […]". The portion of eligible liabilities subscribed by intragroup entities and excluded under Article 27(3)(h) SRMR must not be reported as part of the relevant amount for bail-in / WDC. When determining the relevant amount for bail-in, entities shall take into account national laws that transpose the BRRD. If those provisions do not provide complete and clear guidance for determining the relevant amount for bail-in, careful consideration should in general be given to how the item in question is dealt with under applicable insolvency legislation43. Furthermore, the contractual terms governing each liability might provide additional insight when performing this assessment. For debt instruments with embedded derivatives, the following list of items shall be considered: ▪ Any contractually defined floor or cap to the final redemption amount. ▪ Any contractually defined early termination amount, if such amount is deemed to represent the investor’s claim in insolvency/resolution. ▪ The performance of the underlying, whenever it impacts the repayment of the principal amount. ▪ The contractual provisions ruling the payment of interests, to assess whether the accrued component can be properly determined and is relevant for bail-in purposes. ▪ The inclusion of an Article 12c(2)(b) SRMR clause. ▪ Any element relevant to Article 12c(2)(a) SRMR. ▪ Any settlement/close out costs. ▪ Any other term, condition, rule, mechanism or element affecting the making, timing and amount of any kind of payment owed to the holders of the debt instruments with embedded derivatives (please specify). Without prejudice to the considerations above, in principle: • the relevant amount for bail-in is defined as the outstanding amount (including accrued interest and fees, when applicable) less any existing components subject to exemptions according to Article 27(3) SRMR (e.g. covered share for bail-inable deposits indicated in data point c0300), or other factors affecting the conversion amount (e.g. safeguards under Articles 76 to 80 BRRD, as applicable); • for zero coupon bonds issued at discount (i.e. c0240 = ZCB issued at discount), the amount to be reported is the amortised face value (i.e. initially paid up amount plus accrued component of the discount) plus any applicable fees and charges (c0110); and • for structured instruments, the amount reported in field c0270 minus the value of the collateral (if given) should in principle be considered the relevant amount. In case of products where the derivative component is only affecting the coupon payment (i.e. c0250 = Only structured coupon), please refer to the points above. In jurisdictions where accrued interest may not rank pari passu to the liability amount, the relevant NRA may request the reporting of interest accruals on separate line items. Own holdings (identified in field c0090) should be deducted. | Q29: Não | R29: Em curso | S29: Em curso | T29: Sim | U29: Obter mon_cap_st1_vivo e somar com o campo mon_jur_st1 da tabela cd_alm.al030_sld_core_m | X29: 1 - Pertence ao novo Bail-in | AB29: Sim, Montante | AC29: Reunião 29/10/2024 Luís Capitão-Mor, Pedro Mendes: Tem de ser analisado em conjunto com o ranking de insolvência. | AF29: Em curso | AH29: AL030_SLD_CORE_M | AI29: mon_cap_st1_vivo + mon_jur_st1 | AJ29: Fórmula dependendo do campo "origem" da CT610_títulos - 0 para que não tiver na CT610 o valor para o que tiver
B30: 4.2.4. DATA POINTS FOR AMOUNTS REQUIRED FOR CALCULATION | C30: 27 | D30: Portion of the liability held by the subsidiary itself for external issuances | E30: [Euro amount] | F30: Portion of the liability held by the subsidiary itself as principal amount plus accrued interest and fees and charges (if applicable) | G30: portion_liabil_external_issuances | H30: Campo fixo: 0 | I30: Reunião Pedro Mendes 2025-01-21 | J30: Concluido | K30: Concluido | L30: OK | N30: B02.00 | O30: Portion of instrument or liability held by the reporting entity | P30: The EUR amount related to the portion of the liability held by the reporting entity itself. The amount can either be defined as the principal amount plus accrued interest and fees and charges, or as the relevant portion of fair value held by the reporting entity itself, in the event that field c0250 applies. This data point is only relevant for securities. | Q30: Não | R30: Concluido | S30: Novo campo. Valor fixo 0 | T30: Sim | X30: 1 - Pertence ao novo Bail-in | AB30: Sim, Montante | AC30: Reunião 29/10/2024 Luís Capitão-Mor, Pedro Mendes: Novo campo. Valor fixo 0 | AF30: Concluido | AJ30: Sempre 0
B31: 4.2.4. DATA POINTS FOR AMOUNTS REQUIRED FOR CALCULATION | C31: 28 | D31: Instrument/liability meets the requirements of Article 21(7a) SRMR | E31: [yes/no] | F31: Flag to identify if a liability fulfils the criteria laid down in Article 21(7)a SRMR (conditions referred to in point (a) of Article 12g(2) SRMR, except the condition related to the remaining maturity of liabilities as set out in Article 72c(1) CRR). | G31: flag_requirements_srmr | H31: - 'yes' se valor do campo Rank of liability (SRB_ID = 12) <= 8 - 'no' para os restantes | I31: Reunião Pedro Mendes 2025-02-04 | J31: Concluido | K31: Concluido | L31: OK | N31: B02.00 | O31: Instrument/liability meets the requirements of Art. 21(7a) SRMR | P31: Flag to identify whether a liability fulfils the criteria laid down in Article 21(7a) SRMR (conditions referred to in point Article 12g(2)(a) SRMR, except the condition relating to the remaining maturity of liabilities as set out in Article 72c(1) CRR). The value to be reported is a TRUE/FALSE Boolean. This data point is especially relevant if the scope of collection is expanded, as mentioned in the first paragraph of this annex. | Q31: Não | R31: Em curso | S31: Em curso | T31: Sim | X31: 1 - Pertence ao novo Bail-in | AB31: sim | AC31: Reunião 31/10/2024 Luís Capitão-Mor, Pedro Mendes: Novo campo na tabela de parametrização do ranking insolvência, com valor 0/1 para indicar se o instrumento cumpre ou não o critério presente neste campo (Ranking de insolvência já indica se o instrumento cumpre ou não critério presente no artigo 12g(2) SRMR, segundo Pedro Mendes. Luis Capitão-Mor, refere que será o Pedro Mendes a carregar estes valores nesta nova coluna da tabela parametrização. Pedro Mendes comentou : "deverá ser “yes” para títulos de fundos próprios e um tipo especifico de emissões. Deverá incluir-se na ct610?" email 02/12/2024 11:10) Questões Pedro Mendes / Luis Capitão-Mor: 1) Este campo apenas se aplica a titulos ? Se sim, adicionar este campo a ct610_titulos, implica Miguel Silva passar a preencher este novo campo. 2) Para o que não for titulos, a flag fica a 'no' ? | AF31: Em curso | AH31: CT610_titulos | AI31: Origem | AJ31: Code list dependendo do produto
B32: 4.2.4. DATA POINTS FOR AMOUNTS REQUIRED FOR CALCULATION | C32: 29 | D32: Applicable fees and charges | E32: [Euro amount] | F32: Total amount of applicable fees and charges (e.g. contractual fees for late payments) linked to the instrument, if the fee or charge is payable and due, but not yet settled with the counterparty as of the request date. This is to the extent that the fee or charge is not covered within the outstanding principal amount or the accrued interest or a separate liability. Fees and charges do not comprise agios or fees in conjunction with the listing of an instrument. | G32: total_amount_fees_charges | H32: Aplicar a seguinte query: SELECT CONCAT(cempresa,cbalcao,cnumecta,zdeposit) AS contract_id, NVL(SUM(MSALDO_FINAL), 0) as total_amount_fees_charges FROM (SELECT * FROM cd_captools.fr001_univ_saldo WHERE ref_date ='${ref_date}' ) AS fr001 INNER JOIN (SELECT * FROM cd_captools.fr802_pl_contas WHERE ref_date = '${ref_date}' AND cod_plano = 'BST_IND' AND (tipo_conta='P' OR (tipo_conta='C' AND instrumento_financeiro='instrumentos de capital')) AND COMPOSICAO_VALOR = 'despesas/comissoes com encargo diferido associadas ao custo amortizado' ) AS fr802 ON fr001.ccontab_final_ifrs = fr802.conta GROUP BY 1 | I32: Reunião Pedro Mendes 2025-02-21 | J32: Concluido | K32: Concluido | L32: OK | N32: B02.00 | O32: Applicable fees and charges_x000D_ | P32: Total EUR amount of applicable fees and charges (e.g. contractual fees for late payments) linked to the instrument, if the fee or charge is payable and due, but not yet settled with the counterparty as of the request date. This is to the extent that the fee or charge is not covered within the outstanding principal amount, the accrued interest or a separate liability. Fees and charges do not include agios or fees in conjunction with the listing of an instrument. Only claims against third parties must be reported (i.e. excluding the proportion held by the entity itself, which must be reported in field c0090). In case the field is not applicable (e.g. shares), please refer to the specific instructions in the Technical Annex. | Q32: Não | R32: Em curso | S32: Em curso | T32: Sim | X32: 1 - Pertence ao novo Bail-in | AB32: Sim, Montante | AC32: Reunião 31/10/2024 Luís Capitão-Mor, Pedro Mendes: Segundo Luís Capitão-Mor, Pedro Mendes, este campo aplica-se aos custos periodificados do banco (ainda não pagos, que estão pendentes de pagar) nas emissões que o Banco faz de covered bonds, seniores,... (estão no Passivo do Banco), tem de se pagar aos Advogados, etc. Naturalmente, este campo não se aplica a Depósitos. Ações solicitadas por Luís Capitão-Mor: - Agendar reunião com Rafael Pessoa/Carlos Fernandes para ver onde constam estes custos na fr802 (devem ter uma conta contabilistica), levando para a reunião 2 exemplos de covered bonds: 1) Identificar esses 2 exemplos para uma data mais recente; 2) Verificar na ct001 quais as contas PCSB (uma conta 50%) e IFRS associadas; 3) Verificar se para essas contas consta na composicao_valor ou noutro campo da fr802 tem a indicação de comissão ou despesa 4) Verificar se esta comissão ficou ou não incluida no gross carrying amount (provavelmente foi incluido). 5) Verificar na fr004 se já existe lá este conceito de comissão (só seria para adicionar na fr004 caso fosse um conceito que faça sentido para a contabilidade) 6) Tabela de conceitos ct872 (tem os conceitos com base em campos da fr802): criar nesta tabela o conceito caso ele não exista. | AF32: Em curso | AH32: AL030_SLD_CORE_M | AI32: mon_comissões + mon_despesas
B33: 4.2.5. DATA POINTS FOR INFORMATION ON THE INVESTOR/CREDITOR | C33: 30 | D33: Country of contracting party | E33: [Country Code] | F33: Home State of the counterparty (investor/creditor). | G33: country_contracting_party | H33: Obter campo cpais_residencia da tabela cd_captools.ct003_univ_cli ligando por zcliente: 1) Para os registos que estão na cd_captools.ct610_titulos obter o campo zcliente_investidor Nota: Obter o 1º zcliente para os casos em que este campo está no formato vector. (Ex: zcliente_investidor= 5100011001;7400066405;8044901277 então zcliente_investidor=5100011001) 2) Para os registos que não estão na cd_captools.ct610_titulos obter o campo zcliente da cd_captools.fr004_cto Adicionalmente, converter o campo cpais_residencia no respetivo ISO 3166-1 alpha-2 code. | I33: Reunião Pedro Mendes 2025-01-21 Query para traduzir cpais_residencia em ISO3166 - alpha 1 code: select distinct ct003.cpais_residencia,tat91.tayd91c0_nelemc09 from (select cpais_residencia from cd_captools.ct003_univ_cli where ref_date = '2024-09-30') ct003 left join (select * from cd_estruturais.tat91_tabelas where data_date_part='2024-09-30' and TAYD91C0_CTABELA ='015') tat91 on ct003.cpais_residencia = tat91.tayd91c0_celemtab ; Observa-se que existem registos contendo caracteres invalidos neste contexto (*,#): cpais_residencia count(cpais_residencia) * 3658 # 3527 | J33: Concluido | K33: Concluido | L33: OK | N33: B90.00 | O33: Country of the counterparty | P33: Indicate the ISO 3166-1 alpha-2 code of the home state of the counterparty. If unavailable, it may be replaced by the tax residence of the counterparty. If the liability is held by an international/supranational organisation, such as the European Union or the European Central Bank, please enter ‘XX’. For deposits reported on an aggregate level, please indicate ‘XX’. | Q33: Não | R33: Concluido | S33: Reunião 07/11/2024 Luís Capitão-Mor, Flávia Pinho: LT003_ENTITY.CNTRY (atenção que até aqui tinham sido campos da tabela de instrumentos, e agora passamos à ter campos da tabela de entidades). | T33: Sim | U33: No novo Bail-in este campo constará no ficheiro B90.00 (ficheiro de contrapartes) e não no ficheiro B02.00 (ficheiro de contratos). Ou seja, no antigo Bail-in iríamos colocar o campo na LT002, contudo, no novo já não faz sentido colocar na LT002. Adicionalmente, verifica-se que no antigo Bail-in tínhamos 2 campos que foram fundidos num único campo no novo Bail-in | X33: 1 - Pertence ao novo Bail-in | AB33: sim | AC33: Atenção Reunião 07/11/2024 Luís Capitão-Mor, Flávia Pinho: LT003_ENTITY.CNTRY (atenção que até aqui tinham sido campos da tabela de instrumentos, e agora passamos à ter campos da tabela de entidades). | AD33: Country of counterparty residence | AE33: Country of counterparty residence. | AF33: Concluido | AH33: ct003_univ_cli | AI33: cpais_doc_residencia | AJ33: code list com base neste campo
B34: 4.2.5. DATA POINTS FOR INFORMATION ON THE INVESTOR/CREDITOR | C34: 31 | D34: Tax residence of contracting party | E34: [Country Code] | F34: Tax residence of the counterparty (investor/creditor), if Home State of the counterparty is not available. | G34: tax_residence_contracting_party | H34: Reportar o mesmo campo que o SRB_ID = 30 ( Country of contracting party) | I34: Reunião Pedro Mendes 2025-01-29 | J34: Concluido | K34: Concluido | L34: OK | N34: B90.00 | O34: Country of the counterparty_x000D_ | P34: Indicate the ISO 3166-1 alpha-2 code of the home state of the counterparty. If unavailable, it may be replaced by the tax residence of the counterparty. If the liability is held by an international/supranational organisation, such as the European Union or the European Central Bank, please enter ‘XX’. For deposits reported on an aggregate level, please indicate ‘XX’. | Q34: Não | R34: Por iniciar | S34: Por iniciar | T34: Sim | X34: 2 - Não pertence ao novo Bail-in | AC34: No campo acima, está-se a a pedir o País da Morada de Residência. Neste campo, aparentemente está-se a pedir o País da Morada Fiscal. Na lt003 existe apenas o campo cntry que contém atualmente o País da Morada de Residência. Ou seja, aparentemente será necessário criar um novo campo na lt003 com o País da Morada Fiscal. Não faz sentido adicionar esse novo campo estando apenas preenchido quando o campo do País da Morada de Residência não tiver preenchido, ou seja, deveria estar sempre preenchido. A ser mesm o necessário (confirmar com a Corporação) haveria depois um tratamento manual do ficheiro. | AF34: Por iniciar | AH34: ct003_univ_cli | AI34: cpais_doc_identif1 | AJ34: code list com base neste campo
B35: 4.2.5. DATA POINTS FOR INFORMATION ON THE INVESTOR/CREDITOR | C35: 32 | D35: Name of contracting party | E35: [Name] | F35: The name of the investor/creditor | G35: name_contracting_party | H35: Obter campo gcliente da cd_captools.ct003_univ_cli ligando por zcliente: 1) Para os registos que estão na cd_captools.ct610_titulos obter o campo zcliente_investidor Nota: Obter o 1º zcliente para os casos em que este campo está no formato vector. (Ex: zcliente_investidor= 5100011001;7400066405;8044901277 então zcliente_investidor=5100011001) 2) Para os registos que não estão na cd_captools.ct610_titulos obter o campo zcliente da cd_captools.fr004_cto Adicionalmente, se campo itip_cli= 'F' da cd_captools.ct003_univ_cli colocar campo fixo: 'Natural Customer' | I35: Reunião Pedro Mendes 2025-01-21 | J35: Concluido | K35: Concluido | L35: OK | N35: B90.00 | O35: Counterparty name | P35: When available, indicate the name of the counterparty/investor/creditor. When deemed relevant to ensure compliance with GDPR requirements, in case of natural persons the name of the counterparty shall be anonymised by the reporting entity. For deposits reported on an aggregate level, please indicate ‘Aggregated’. | Q35: Não | R35: Concluido | S35: Reunião 07/11/2024 Luís Capitão-Mor, Flávia Pinho: LT003_ENTITY.ENTTY_NM | T35: Sim | U35: No novo Bail-in este campo constará no ficheiro B90.00 (ficheiro de contrapartes) e não no ficheiro B02.00 (ficheiro de contratos). Ou seja, no antigo Bail-in iríamos colocar o campo na LT002, contudo, no novo já não faz sentido colocar na LT002. Adicionalmente, verifica-se que no novo Bail-in existe uma necessidade extra ao nível do nome das Natural Persons (). | X35: 1 - Pertence ao novo Bail-in | AB35: sim | AC35: Reunião 07/11/2024 Luís Capitão-Mor, Flávia Pinho: LT003_ENTITY.ENTTY_NM | AD35: Name Counterparty | AE35: Name counterparty. | AF35: Concluido | AH35: ct003_univ_cli | AI35: gcliente
B36: 4.2.5. DATA POINTS FOR INFORMATION ON THE INVESTOR/CREDITOR | C36: 33 | D36: Identifier of contracting party | E36: [LEI code/MFI ID/ Other ID] | F36: u | G36: id_contracting_party | H36: Obter campo clei da cd_captools.ct003_univ_cli ligando por zcliente: 1) Para os registos que estão na cd_captools.ct610_titulos obter o campo zcliente_investidor Nota: Obter o 1º zcliente para os casos em que este campo está no formato vector. (Ex: zcliente_investidor= 5100011001;7400066405;8044901277 então zcliente_investidor=5100011001) 2) Para os registos que não estão na cd_captools.ct610_titulos obter o campo zcliente da cd_captools.fr004_cto Adicionalmente, se campo itip_cli= 'F' da cd_captools.ct003_univ_cli colocar campo fixo: 'Natural Customer' Caso não tenha clei preenchido, obter zcliente. | I36: Reunião Pedro Mendes 2025-01-21: | J36: Concluido | K36: Concluido | N36: B90.00 | O36: Counterparty identifier (preferably LEI) | P36: Please report the creditor’s LEI code (when available), issued by the Global Legal Entity Identifier Foundation and recommended by the FSB65. In the absence of an LEI, for banks, the ECB Monetary Financial Institutions identifier (MFI ID) used in RIAD should be reported. For the deposits reported on an aggregate level, this data point is not applicable. When deemed relevant to ensure compliance with GDPR requirements, in case of natural persons the identifier of the counterparty shall be anonymised by the reporting entity. For deposits reported on an aggregate level, please indicate ‘Aggregated’. | Q36: Não | R36: Em curso | S36: ISSR_ID já existe no Report Valuation, portanto, este campo deverá ser viste em conjunto nos 2 reports | T36: Sim | X36: 1 - Pertence ao novo Bail-in | AB36: sim | AC36: 'Atenção: o campo ISSR_ID já existe no Report Valuation, portanto, este campo deverá ser viste em conjunto nos 2 reports Para títulos, o zcliente que ser quer aqui é o do investidor não é o zcliente do emitente (continuar conversa com Miguel) Reunião 07/11/2024 Luís Capitão-Mor, Flávia Pinho: Existe o campo LT003_ENTITY.LEI, contudo, é referido [LEI code/MFI ID/ Other ID]. Portanto, se é referido Other ID então, em princípio, deveria utilizar-se o campo LT002_INSTRUMENT.ISSR_ID pois é mais abrangente (pode ser o LEI ou o contribuinte ou....) Contudo, o LT002_INSTRUMENT.ISSR_ID atualmente está a N/A para uma parte do Universo. Este tema já foi identificado no Valuation e terá de ser visto em conjunto nos 2 reports. | AF36: Em curso | AH36: ct003_univ_cli | AI36: clei
B37: 4.2.5. DATA POINTS FOR INFORMATION ON THE INVESTOR/CREDITOR | C37: 34 | D37: Counterparty type for the externally issued liabilities | E37: Drop-down: Households (1) Non-financial corporations (SMEs) (2) Non-financial corporations (non-SMEs) (3) Credit institutions (4) Other financial corporations (5) General governments & Central banks (6) Non-identified counterparties (listed on an exchange platform) (7) Non identified, not listed on an exchange platform. (8) | F37: Counterparty of the liability, i.e. households, non-financial corporations (SMEs), non-financial corporations (non-SMEs), Credit institutions, Other financial corporations, General governments & Central banks, non-identified counterparties (listed on an exchange platform) or others. | G37: counterparty_type | H37: Obter campo contraparte da cd_captools.ct003_univ_cli ligando por zcliente: 1) Para os registos que estão na cd_captools.ct610_titulos obter o campo zcliente_investidor Nota: Obter o 1º zcliente para os casos em que este campo está no formato vector. (Ex: zcliente_investidor= 5100011001;7400066405;8044901277 então zcliente_investidor=5100011001) 2) Para os registos que não estão na cd_captools.ct610_titulos obter o campo zcliente da cd_captools.fr004_cto. 3) Fazer mapeamento da seguinte forma: 3.1) campo contraparte= 'particulares' -> Households (1) 3.2) campo contraparte= 'outras empresas nao financeiras' and campo cod_empr_pme da business_sme2003361.out_sme_2003_361 in ('1','2','3') -> Non-financial corporations (SMEs) (2) 3.3) campo contraparte= 'outras empresas nao financeiras' and campo cod_empr_pme da business_sme2003361.out_sme_2003_361 in ('0') -> Non-financial corporations (non-SMEs) (3) 3.4) campo contraparte='instituicoes de credito' -> Credit institutions (4) 3.5) campo contraparte='outras instituicoes financeiras' -> Other financial corporations (5) 3.6) campo contraparte='bancos centrais' -> General governments & Central banks (6) 3.7) campo contraparte='setor publico' -> General governments & Central banks (6) | I37: Reunião Pedro Mendes 2025-01-29 | J37: Concluido | K37: Concluido | L37: OK - Pedro Ramos | N37: B90.00 | O37: Counterparty type | P37: Indicate the type of counterparty, as per the categories listed below: • Households; • Micro & SME; • Corporates; • Institutions; • Other financial corporations; • Insurance firms & pension funds; • Government, central banks & supranationals; • Non identified, listed on an exchange platform; • Non identified, not listed on an exchange platform. | Q37: Não | R37: Em curso | S37: Em curso | T37: Sim | X37: 1 - Pertence ao novo Bail-in | AB37: sim | AC37: Questões LCM: 1) Ver sheet2 do report Valuation. ->Atenção este campo já existe no Report Valuation, portanto, este campo deverá ser visto em conjunto nos 2 reports (têm granularidades diferentes: ) Reunião 20/11/2024 e dia 07/11/2024 Luís Capitão-Mor, Flávia Pinho: Parecido com o segmento FINREP, campo INTRNL_SGMNT da tabela LT002_INSTRUMENT. Contém os seguintes valores: particulares outras empresas nao financeiras instituicoes de credito outras instituicoes financeiras bancos centrais setor publico N/A None Campo SME_FNRP18 da LT002_INSTRUMENT é o campo da flag que indica se é ou não SME? Contudo, este campo está na tabela de contratos... 7 não vamos preencher. Os titulos passivos têm zcliente 0000000 -> Seriam 8 Luís Capitão-Mor solicitou: 1) Ver com Rafael Pessoa se o segmento FINREP é apenas para Ativo. -> Segundo o Rafael Pessoa o segmento FINREP é para Ativo, Passivo e Extrapatrimoniais. 2) Verificar na ct004 o que sai no campo contraparte para o casos dos Depósitos -> Verificou-se que todos os registos têm contraparte preenchida Resultado: contraparte count(*) outras empresas nao financeiras 662756 outras instituicoes financeiras 10377 particulares 3497919 instituicoes de credito 20337 bancos centrais 2 setor publico 10474 query: select t3.contraparte, count(*) from (select * from cd_captools.ct001_univ_saldo where ref_date='2024-09-30') t1 inner join (select * from cd_captools.fr802_pl_contas where ref_date='2024-09-30' and cod_plano='BST_IND' and instrumento_financeiro='depositos' ) t2 on t1.ccontab_final_ifrs = t2.conta inner join (select * from cd_captools.ct004_univ_cto where ref_date='2024-09-30') t3 on concat(t1.cempresa, t1.cbalcao, t1.cnumecta, t1.zdeposit) = concat(t3.cempresa, t3.cbalcao, t3.cnumecta, t3.zdeposit) group by contraparte | AF37: Em curso | AH37: ct003_univ_cli | AI37: contraparte
B38: 4.2.5. DATA POINTS FOR INFORMATION ON THE INVESTOR/CREDITOR | C38: 35 | D38: Counterparty within the resolution group | E38: Drop-down: - Intragroup and intra-resolution group (1) - Intragroup but not intra-resolution group (2) - No | F38: Flag whether the counterparty is part of the resolution group. | G38: counterparty_resol_group | H38: - 'No' se zcliente não estiver na tabela cd_captools.clientes_intragrupo - 'Intragroup and intra-resolution group (1)' se zcliente estiver na tabela cd_captools.clientes_intragrupo e não constar na lista abaixo de zclientes - 'Intragroup but not intra-resolution group (2)' se zcliente estiver na tabela cd_captools.clientes_intragrupo e constar na lista abaixo de zclientes 1) Para os registos que estão na cd_captools.ct610_titulos obter o campo zcliente_investidor Nota: Obter o 1º zcliente para os casos em que este campo está no formato vector. (Ex: zcliente_investidor= 5100011001;7400066405;8044901277 então zcliente_investidor=5100011001) 2) Para os registos que não estão na cd_captools.ct610_titulos obter o campo zcliente da cd_captools.fr004_cto Lista de zclientes (não fazem parte do mesmo grupo de resolução do BST): 0000238954 6511000505 7400416271 7400416353 7400416520 7400416611 7400416763 7400507283 7400701625 7401474691 7401536276 8037849269 8043363752 8044173594 8046250676 8046296743 8046334916 9001925092 | I38: Reunião Pedro Mendes 2025-01-29 | J38: Concluido | K38: Concluido | L38: OK OK - Pedro Ramos | N38: B90.00 | O38: Counterparty within the resolution group | P38: Indicate whether the counterparty of the (portion of) instrument/liability is: • ‘Intragroup and intra-resolution group’ = to be used for counterparties that are both intragroup and part of the same resolution group64; • ‘Intragroup but not intra-resolution group’ = to be used for counterparties that are intragroup but not part of the same resolution group; • ‘No’ = to be used for counterparties which are external to the group. 64=Resolution Group within the meaning of Article 2(1)(83b) BRRD. | Q38: Não Contudo, aparenta ser o mesmo | R38: Em curso | S38: Em curso | T38: Sim | X38: 1 - Pertence ao novo Bail-in | AB38: sim | AC38: Reunião 13/11/2024 Luís Capitão-Mor, Pedro Mendes,Flávia Pinho: Utilizar a nova tabela de parametrização definida no campo SRB_ID 13 em que: Código Entidade Cargabal Pai ( teria sempre o valor '00001', ou seja, o Banco Santander S.A), Número do Grupo de Resolução, Código Entidade Cargabal, ckutulmo, htimest e ref_date. Depois ir a ct086_univ_per_d clientes_intragrupo Lógica Processo: 1) Parte-se do contrato da tabela LT001 que tem um zcliente associado, depois converte-se esse zcliente no respetivo codigo corporativo ( consoles) através da Tabela clientes_intragrupo. A ligação entre estas 2 tabelas é feita por zcliente. 2) Utilizar a tabela de parametrização definida no campo SRB_ID 13 em que: Código Entidade Cargabal Pai ( teria sempre o valor '00001', ou seja, o Banco Santander S.A), Número do Grupo de Resolução, Código Entidade Cargabal, ckutulmo, htimest e ref_date. E verificar se nesta tabela de parametrização, para cada um dos zclientes associados ao respetivo código corporativo, existe código entidade cargabal pai, se não existir, flag -> não. Se código entidade cargabal pai existir, flag -> sim | AF38: Em curso | AH38: ct003_univ_cli | AI38: zcliente | AJ38: code list com base neste campo. Há uma flag se diz isto mas só se quer alguns dos intragrupos, não todos
B39: 4.2.6. DATA POINTS FOR GUARANTEES | C39: 36 | D39: Identifier of the guarantee issued by the resolution entity, which is owed to the subsidiary/affiliated entity | E39: [Internal identification number] | F39: Identification number of the guaranteed liability in the group entity. | G39: id_guarantee | H39: Campo Fixo: 'N/A' | I39: Reunião Pedro Mendes 2025-01-21 | J39: Concluido | K39: Concluido | L39: OK - Pedro Ramos | N39: B05.00 | O39: Unique (internal) identifier of the guarantee provided to the Non-Resolution Entity | P39: Internal identifier of the guarantee and of the financial support arrangement, if applicable. | Q39: Não | R39: Em curso | S39: Valor fixo 'N/A' | T39: Sim | X39: 1 - Pertence ao novo Bail-in | AB39: N/A | AC39: Reunião 20/11/2024 Luís Capitão-Mor, Pedro Mendes, Flávia Pinho: Novo campo. Valor fixo N/A, aplicável a todos os campos de DATA POINTS FOR GUARANTEES. Dado que estes campos podem deixar de ser N/A, definiu-se uma nova tabela (LT6%) que permitirá definir os INSERTs ou os INSERTs OVERWRITEs nas tabelas de Output do Loan Tap, possibilitando assim ao Utilizador inserir manualmente valores: Campo1: tabela destino; Campo2 : campo destino; Campo3: valor; Campo4: perímetro distinto; Campo5: flag controlo ( exemplo:1,2,3) -> A definir. Agendar conversa com Mariana para em seguida se agendar reunião com Luís Capitão-Mor para aprovação da tabela. | AF39: Em curso
B40: 4.2.6. DATA POINTS FOR GUARANTEES | C40: 37 | D40: Group counterparty identifier | E40: [LEI of the counterparty] | F40: LEI of the resolution entity or other entities of the group providing the guarantees. | G40: group_counterparty_id | H40: Campo Fixo: 'N/A' | I40: Reunião Pedro Mendes 2025-01-21 | J40: Concluido | K40: Concluido | L40: OK - Pedro Ramos | N40: B05.00 | O40: Identifier of the securities used as a collateral for the guarantee | P40: Identification number of the securities used as collateral for the guarantee. In the event of multiple entries, please separate them with a vertical bar. | Q40: Não | R40: Concluido | S40: Valor fixo 'N/A' | T40: Sim | X40: 1 - Pertence ao novo Bail-in | AB40: N/A | AC40: Reunião 20/11/2024 Luís Capitão-Mor, Pedro Mendes, Flávia Pinho: Novo campo. Valor fixo N/A | AF40: Concluido
B41: 4.2.6. DATA POINTS FOR GUARANTEES | C41: 38 | D41: Amount of the guarantee provided by the resolution entity or other entities of the group, which is owed to the subsidiary/affiliated entity | E41: [Euro amount] | F41: Outstanding amount guaranteed by the resolution entity | G41: amount_guarantee | H41: Campo fixo: 0 | I41: Reunião Pedro Mendes 2025-01-21 | J41: Concluido | K41: Concluido | L41: OK - Pedro Ramos | N41: B06.00 | O41: Identifier of the guarantee | P41: ISIN or internal identifier of the guarantee provided by the resolution entity to the bondholders of the instrument(s) issued by the SPV. | R41: Por iniciar | X41: 2 - Não pertence ao novo Bail-in | AF41: Por iniciar
B42: 4.2.6. DATA POINTS FOR GUARANTEES | C42: 39 | D42: Maximum amount of the guarantee | E42: [Euro amount] | F42: Maximum amount guaranteed by the resolution entity. | G42: maximum_amount_guarantee | H42: Campo fixo: 0 | I42: Reunião Pedro Mendes 2025-01-21 | J42: Concluido | K42: Concluido | L42: OK - Pedro Ramos | N42: B05.00 | O42: Maximum amount of the guarantee | P42: The EUR (counter)value of the maximum amount (if any) covered by the guarantee / financial support arrangement. | Q42: Não Contudo, aparenta ser o mesmo | R42: Concluido | S42: Valor fixo 'N/A' | T42: Sim | X42: 1 - Pertence ao novo Bail-in | AB42: N/A | AC42: Reunião 20/11/2024 Luís Capitão-Mor, Pedro Mendes, Flávia Pinho: Novo campo. Valor fixo N/A | AF42: Concluido
B43: 4.2.6. DATA POINTS FOR GUARANTEES | C43: 40 | D43: Type of guarantee | E43: Drop down: - Issuance (1) - Counterparty (2) - Unlimited (3) - Other (4) | F43: The type of guarantee from a predefined list, either: - ‘Issuance’ for guarantees on specific instruments/liabilities that have been issued; - ‘Counterparty’ for guarantees granted to a specific counterparty of the institution; - ‘Unlimited’ for general guarantees not limited to a fixed amount; - ‘Other types of guarantee than issuance guarantees, counterparty guarantees and unlimited guarantees’. | G43: type_guarantee | H43: Campo Fixo: 'N/A' | I43: Reunião Pedro Mendes 2025-01-21 | J43: Concluido | K43: Concluido | L43: OK - Pedro Ramos | N43: B05.00 | O43: Type of guarantee | P43: Indicate the type of guarantee using one of the values from the Liability Data Report, namely: • Issuance = for guarantees on specific instruments/liabilities that have been issued; • Counterparty = for guarantees granted to a specific counterparty of the institution; • Unlimited = for general guarantees not limited to a fixed amount; • Other types of guarantee than issuance guarantees, counterparty guarantees and unlimited guarantees. | Q43: Não Contudo, aparenta ser o mesmo | R43: Concluido | S43: Valor fixo 'N/A' | T43: Sim | X43: 1 - Pertence ao novo Bail-in | AB43: N/A | AC43: Reunião 20/11/2024 Luís Capitão-Mor, Pedro Mendes, Flávia Pinho: Novo campo. Valor fixo N/A | AF43: Concluido
B44: 4.2.6. DATA POINTS FOR GUARANTEES | C44: 41 | D44: Guarantee Trigger | E44: Drop down: - Default (1) - Solvency-related (2) - Liquidity-related (3) - Other (4) | F44: Provide the type of event triggering the activation of the guarantee/financial support, i.e. the event enabling the right for the counterparty to execute the guarantee, either ‘Default’, ‘Solvency-related’, Liquidity related’ or ‘Other’ from a predefined list. | G44: guarantee_trigger | H44: Campo Fixo: 'N/A' | I44: Reunião Pedro Mendes 2025-01-21 | J44: Concluido | K44: Concluido | L44: OK - Pedro Ramos | N44: B05.00 | O44: Guarantee trigger | P44: Provide the type(s) of event(s) triggering the activation of the guarantee / financial support, i.e. the event(s) enabling the right for the counterparty to execute the guarantee, choosing from: • Default; • Solvency-related; • Liquidity-related; • Other than default, solvency-related or liquidity-related. In case of multiple entries, please separate them with a vertical bar. | Q44: Não | R44: Concluido | S44: Valor fixo 'N/A' | T44: Sim | X44: 1 - Pertence ao novo Bail-in | AB44: N/A | AC44: Reunião 20/11/2024 Luís Capitão-Mor, Pedro Mendes, Flávia Pinho: Novo campo. Valor fixo N/A | AF44: Concluido
B45: 4.2.6. DATA POINTS FOR GUARANTEES | C45: 42 | D45: Guarantee fulfils the requirements pursuant to Article 12g(3) SRMR | E45: [Yes/No] | F45: Guarantee fulfils the requirements pursuant to Article 12g(3) SRMR. “Yes” should be selected only if the SRB officially recognised that all necessary requirements have been fulfilled | G45: flag_guarantee_requirements_srmr | H45: Campo Fixo: 'N/A' | I45: Reunião Pedro Mendes 2025-01-21 | J45: Concluido | K45: Concluido | L45: OK - Pedro Ramos | N45: B05.00 | O45: Guarantee fulfils the requirements pursuant to art. 12g(3) SRMR | P45: Indicate whether the guarantee fulfils the requirements pursuant to Article 12g(3) SRMR. The value to be reported is a TRUE/FALSE Boolean. ‘TRUE’ should be selected only if the SRB has officially recognised that all necessary requirements have been fulfilled. | Q45: Sim | R45: Concluido | S45: Valor fixo 'N/A' | T45: Não | X45: 1 - Pertence ao novo Bail-in | AB45: N/A | AC45: Reunião 20/11/2024 Luís Capitão-Mor, Pedro Mendes, Flávia Pinho: Novo campo. Valor fixo N/A | AF45: Concluido
B46: 4.2.6. DATA POINTS FOR GUARANTEES | C46: 43 | D46: Percentage of collateralisation of the guarantee provided by the resolution entity through a financial collateral arrangement | E46: [% of Euro amount] | F46: A financial collateral arrangement means a title transfer financial collateral arrangement or a security financial collateral arrangement whether or not these are covered by a master agreement or general terms and conditions. | G46: percentage_collateralisation | H46: 1) Para os registos que estão na cd_alm.al602_repos_alm: [(haircut_tit / 100) + 1 ] * 100 2) Para os registos que não estão na cd_alm.al602_repos_alm colocar valor fixo 0. | I46: Reunião Pedro Mendes 2025-02-10 | J46: Concluido | K46: Concluido | L46: OK - Pedro Ramos | R46: Por iniciar | X46: 2 - Não pertence ao novo Bail-in | AF46: Por iniciar
B47: 4.2.6. DATA POINTS FOR GUARANTEES | C47: 44 | D47: Issuance Date of the collateral | E47: [date] | F47: Date of the original issuance of the collateral. | G47: issuance_date_collateral | H47: 1) Para os registos que estão na cd_alm.al602_repos_alm obter o campo dt_inicio. 2) Para os registos que não estão na cd_alm.al602_repos_alm colocar valor fixo 'N/A' (Varchar Default value for not applicable fields). | I47: Reunião Pedro Mendes 2025-01-21 | J47: Concluido | K47: Concluido | L47: OK - Pedro Ramos | R47: Por iniciar | X47: 2 - Não pertence ao novo Bail-in | AF47: Por iniciar
B48: 4.2.6. DATA POINTS FOR GUARANTEES | C48: 45 | D48: Legal Maturity date | E48: [date] | F48: Date of the legal, final maturity of the collateral. | G48: maturity_date_collateral | H48: 1) Para os registos que estão na cd_alm.al602_repos_alm obter o campo dt_fim. 2) Para os registos que não estão na cd_alm.al602_repos_alm colocar valor fixo 'N/A' (Varchar Default value for not applicable fields). | I48: Reunião Pedro Mendes 2025-01-21 | J48: Concluido | K48: Concluido | L48: OK - Pedro Ramos | R48: Por iniciar | X48: 2 - Não pertence ao novo Bail-in | AF48: Por iniciar
B49: 4.2.6. DATA POINTS FOR GUARANTEES | C49: 46 | D49: Identifier of the securities used as a collateral for the guarantee | E49: [Internal identification number] | F49: Identification number of the securities used as collateral for the guarantee. | G49: id_securities_collateral | H49: 1) Para os registos que estão na cd_alm.al602_repos_alm obter concat(cempresa_tit,cbalcao_tit, cnumecta_tit,zdeposit_tit). 2) Para os registos que não estão na cd_alm.al602_repos_alm colocar valor fixo 'N/A' (Varchar Default value for not applicable fields). | I49: Reunião Pedro Mendes 2025-01-21 | J49: Concluido | K49: Concluido | L49: OK - Pedro Ramos | R49: Por iniciar | X49: 2 - Não pertence ao novo Bail-in | AF49: Por iniciar
B50: 4.2.6. DATA POINTS FOR GUARANTEES | C50: 47 | D50: Collateralisation by assets of the resolution entity | E50: [Yes/No] | F50: Identifier of whether liability has been collateralised by assets of the institution under resolution itself. | G50: flag_collateral_assets_resol_entity | H50: 1) Para os registos que estão na cd_alm.al602_repos_alm e que têm concat(cempresa_tit,cbalcao_tit, cnumecta_tit,zdeposit_tit) preenchido, colocar valor fixo 'Yes'. 2) Para os registos que não estão na cd_alm.al602_repos_alm colocar valor fixo 'No'. | I50: Reunião Pedro Mendes 2025-01-21 | J50: Concluido | K50: Concluido | L50: OK - Pedro Ramos | R50: Por iniciar | X50: 2 - Não pertence ao novo Bail-in | AF50: Por iniciar
B51: 4.2.6. DATA POINTS FOR GUARANTEES | C51: 48 | D51: Location of the security | E51: [e.g. FR, IT] | F51: ISO 3166-1 alpha 2 country code (ISO 3166-1 alpha-2 codes of the country where the security is located). | G51: location_security | H51: 1) Para os registos que estão na cd_alm.al602_repos_alm e que têm concat(cempresa_tit,cbalcao_tit, cnumecta_tit,zdeposit_tit) preenchido, colocar valor fixo 'PT'. 2) Para os registos que não estão na cd_alm.al602_repos_alm colocar valor fixo 'N/A' (Varchar Default value for not applicable fields). | I51: Reunião Pedro Mendes 2025-01-21 | J51: Concluido | K51: Concluido | L51: OK - Pedro Ramos | R51: Por iniciar | X51: 2 - Não pertence ao novo Bail-in | AF51: Por iniciar
B52: 4.2.6. DATA POINTS FOR GUARANTEES | C52: 49 | D52: Type of collateralisation | E52: [e.g. securities, loans] | F52: Specify type of collateral as defined per Article 12g(3)(f) of SRMR and Article 197 CRR2. | G52: type_collateralisation | H52: 1) Para os registos que estão na cd_alm.al602_repos_alm e que têm concat(cempresa_tit,cbalcao_tit, cnumecta_tit,zdeposit_tit) preenchido, colocar valor fixo 'securities'. 2) Para os registos que não estão na cd_alm.al602_repos_alm colocar valor fixo 'N/A' (Varchar Default value for not applicable fields). | I52: Reunião Pedro Mendes 2025-01-21 | J52: Concluido | K52: Concluido | L52: OK - Pedro Ramos | R52: Por iniciar | X52: 2 - Não pertence ao novo Bail-in | AF52: Por iniciar
B53: 4.2.6. DATA POINTS FOR GUARANTEES | C53: 50 | D53: Value of collateral | E53: [Euro amount] | F53: The amount of the value of the collateral as determined for the relevant ‘type of collateral value’. For unsecured liabilities, this category shall be reported as zero. | G53: value_collateral | H53: 1) Para os registos que estão na cd_alm.al602_repos_alm e que têm concat(cempresa_tit,cbalcao_tit, cnumecta_tit,zdeposit_tit) preenchido obter o campo mon_nom_atu_tit. 2) Para os registos que não estão na cd_alm.al602_repos_alm colocar valor fixo 0. | I53: Reunião Pedro Mendes 2025-01-21 | J53: Concluido | K53: Concluido | L53: OK - Pedro Ramos | N53: B03.00 | O53: Net value of collateral posted | P53: The net market value of collateral positions under a netting set (i.e. collateral posted decreased by any collateral received). This should include any margin accounts under the netting arrangements. It should be reported as a positive value for net collateral posted to counterparties. | R53: Por iniciar | X53: 2 - Não pertence ao novo Bail-in | AF53: Por iniciar
B54: 4.2.6. DATA POINTS FOR GUARANTEES | C54: 51 | D54: Type of protection value | E54: Drop-down: - Notional amount (1) - Fair value (2) - Market value (3) - Long-term sustainable value (4) - Other protection value (5) | F54: Identification of the type of value as it appears in the data attribute ‘Value of collateral’. | G54: type_protection_value | H54: 1) Para os registos que estão na cd_alm.al602_repos_alm e que têm concat(cempresa_tit,cbalcao_tit, cnumecta_tit,zdeposit_tit) preenchido colocar valor fixo 'Market value (3)'. 2) Para os registos que não estão na cd_alm.al602_repos_alm colocar valor fixo 'N/A' (Varchar Default value for not applicable fields). | I54: Reunião Pedro Mendes 2025-01-21 | J54: Concluido | K54: Concluido | L54: OK - Pedro Ramos | R54: Por iniciar | X54: 2 - Não pertence ao novo Bail-in | AF54: Por iniciar
B55: 4.2.6. DATA POINTS FOR GUARANTEES | C55: 52 | D55: Date of the value of the security | E55: [date] | F55: The date on which the most recent estimate or valuation of the collateral was carried out before the reporting reference date | G55: date_value_security | H55: 1) Para os registos que estão na cd_alm.al602_repos_alm e que têm concat(cempresa_tit,cbalcao_tit, cnumecta_tit,zdeposit_tit) preenchido: ref_date -1 mês ex: ref_date=2024-12-31 então 2024-11-30 2) Para os registos que não estão na cd_alm.al602_repos_alm colocar valor fixo 'N/A' (Varchar Default value for not applicable fields). | I55: Reunião Pedro Mendes 2025-01-21 | J55: Concluido | K55: Concluido | L55: OK - Pedro Ramos | R55: Por iniciar | X55: 2 - Não pertence ao novo Bail-in | AF55: Por iniciar
B56: 4.2.6. DATA POINTS FOR GUARANTEES | C56: 53 | D56: Protection valuation approach | E56: Drop-down: - Mark-to-market valuation (1) - Counterparty estimation (2) - Creditor valuation (3) - Third party valuation (4) | F56: The type of collateral assessment to determine their fair value. | G56: protection_valuation_approach | H56: 1) Para os registos que estão na cd_alm.al602_repos_alm e que têm concat(cempresa_tit,cbalcao_tit, cnumecta_tit,zdeposit_tit) preenchido colocar valor fixo 'Mark-to-market valuation (1)'. 2) Para os registos que não estão na cd_alm.al602_repos_alm colocar valor fixo 'N/A' (Varchar Default value for not applicable fields). | I56: Reunião Pedro Mendes 2025-01-21 | J56: Concluido | K56: Concluido | L56: OK - Pedro Ramos | R56: Por iniciar | X56: 2 - Não pertence ao novo Bail-in | AF56: Por iniciar

Sheet Notas LT002
A1: O Bail-in constará na Tabela LT002 em que:
A2: - Os campos desdobráveis (os que têm mais do que 1 valor para o mesmo contrato) terão os valores separados por ;? O separador de campos num CSV já é ; pelo que se deveria selecionar outro separador.
A3: - Terão de se identificar os campos desdobráveis
A4: - Existem campos que não estão preparados para desdobrar (Gross carrying amount)
A5: Se em algum momento a Corporação/SRB exigirem o desdobramento, terá depois se efetuar um desenvolvimento que pega no vetor e faz o desdobramento
A7: Temos 3 tipos de campos:
A8: - Os que já existem atualmente no LT e que vão que ter que ser desdobrados -> vamos ter de alterar estes campos para poderem desdobrar (G) dado que não se quer criar campos novos iguais mas que desdobrem
A9: - Os que vão manter o valor (ou seja o valor repete-se) e que não são vetores -> não tem de se fazer nada
A10: - Os que são desdobráveis
A13: LT002 As Is
A14: contrato | B14: GCA
A15: 32023234234234300 | B15: 30000
A17: LT002 Intermédia
A18: contrato | B18: zcliente | C18: segmento_xpto | D18: GCA
A19: 32023234234234300 | B19: 123 | C19: A | D19: 30000
A20: 32023234234234300 | B20: 123 | C20: B | D20: 30000
A21: 32023234234234300 | B21: 1234 | C21: C | D21: 30000
A23: LT002 To Be
A24: contrato | B24: zcliente | C24: segmento_xpto | D24: GCA
A25: 32023234234234300 | B25: 123;123;1234 | C25: A;B;C | D25: 30000
A27: Se for preciso abrir no futuro:
A28: contrato | B28: zcliente | C28: segmento_xpto | D28: GCA
A29: 32023234234234300 | B29: 123 | C29: A | D29: 10000
A30: 32023234234234300 | B30: 123 | C30: B | D30: 10000
A31: 32023234234234300 | B31: 1234 | C31: C | D31: 10000

Sheet Notas Financeira
A1: # | B1: Comentário | C1: Data set
A2: 1 | B2: Terá de atacar as tabelas fazendo o filtro para passivo com exceção do Data point 5 que tem uma parte de extrapatrimonial | C2: TODOS
A3: =+A2+1 -> 2 | B3: Os depósitos de clientes terá de ser feito um cruzamento com a tabela do FGD (FG001_FGD no cap tools). Os depósitos depois são divididos entre cobertos e não cobertos sendo que têm tratamento diferente consoante o caso. | C3: TODOS
A4: =+A3+1 -> 3 | B4: Para a parte das emissões de títulos, a ligação entre a AL029/AL030 e a CT610 deverá ser feita por ISIN/ZDEPOSIT | C4: 1. DATA POINTS FOR IDENTIFICATION

Sheet Diagrama_Estrutura_Accionista
A3: FALSE

Sheet draft
A1: lt809_typ_instrmnt | G1: lt829_regras_conversao
A2: instrmnt_fncr | B2: c_typ_instmnt | C2: ordem | D2: typ_instrmnt | E2: descritivo | G2: tabela | H2: campo_conceito | I2: regra_conversao | J2: valor_conceito | K2: valor_final | L2: descritivo_valor_ final
A3: NULL | B3: 110 | C3: 1 | D3: 1004 | E3: Loans other than overdrafts, convenience credit, extended credit, credit card credit, revolving credit other than credit card credit, reverse repurchase agreements, trade receivables and financial leases | H3: typ_instrmnt | J3: 1004 | K3: Loans other than overdrafts, convenience credit, extended credit, credit card credit, revolving credit other than credit card credit, reverse repurchase agreements, trade receivables and financial leases
A4: NULL | B4: 120 | C4: 1 | D4: 1004 | E4: Loans other than overdrafts, convenience credit, extended credit, credit card credit, revolving credit other than credit card credit, reverse repurchase agreements, trade receivables and financial leases | H4: typ_instrmnt | J4: =D4 -> 1004 | K4: Loans other than overdrafts, convenience credit, extended credit, credit card credit, revolving credit other than credit card credit, reverse repurchase agreements, trade receivables and financial leases
A5: NULL | B5: 130 | C5: 1 | D5: 1004 | E5: Loans other than overdrafts, convenience credit, extended credit, credit card credit, revolving credit other than credit card credit, reverse repurchase agreements, trade receivables and financial leases | H5: typ_instrmnt | J5: =D5 -> 1004 | K5: Loans other than overdrafts, convenience credit, extended credit, credit card credit, revolving credit other than credit card credit, reverse repurchase agreements, trade receivables and financial leases
A6: NULL | B6: 140 | C6: 1 | D6: 1004 | E6: Loans other than overdrafts, convenience credit, extended credit, credit card credit, revolving credit other than credit card credit, reverse repurchase agreements, trade receivables and financial leases | H6: typ_instrmnt | J6: =D6 -> 1004 | K6: Loans other than overdrafts, convenience credit, extended credit, credit card credit, revolving credit other than credit card credit, reverse repurchase agreements, trade receivables and financial leases
A7: NULL | B7: 150 | C7: 1 | D7: 1004 | E7: Loans other than overdrafts, convenience credit, extended credit, credit card credit, revolving credit other than credit card credit, reverse repurchase agreements, trade receivables and financial leases | H7: typ_instrmnt | J7: =D7 -> 1004 | K7: Loans other than overdrafts, convenience credit, extended credit, credit card credit, revolving credit other than credit card credit, reverse repurchase agreements, trade receivables and financial leases
A8: NULL | B8: 160 | C8: 1 | D8: 1004 | E8: Loans other than overdrafts, convenience credit, extended credit, credit card credit, revolving credit other than credit card credit, reverse repurchase agreements, trade receivables and financial leases | H8: typ_instrmnt | J8: =D8 -> 1004 | K8: Loans other than overdrafts, convenience credit, extended credit, credit card credit, revolving credit other than credit card credit, reverse repurchase agreements, trade receivables and financial leases
A9: NULL | B9: 170 | C9: 1 | D9: 1004 | E9: Loans other than overdrafts, convenience credit, extended credit, credit card credit, revolving credit other than credit card credit, reverse repurchase agreements, trade receivables and financial leases | H9: typ_instrmnt | J9: =D9 -> 1004 | K9: Loans other than overdrafts, convenience credit, extended credit, credit card credit, revolving credit other than credit card credit, reverse repurchase agreements, trade receivables and financial leases
A10: NULL | B10: 180 | C10: 1 | D10: 1004 | E10: Loans other than overdrafts, convenience credit, extended credit, credit card credit, revolving credit other than credit card credit, reverse repurchase agreements, trade receivables and financial leases | H10: typ_instrmnt | J10: =D10 -> 1004 | K10: Loans other than overdrafts, convenience credit, extended credit, credit card credit, revolving credit other than credit card credit, reverse repurchase agreements, trade receivables and financial leases
A11: NULL | B11: 200 | C11: 1 | D11: 1004 | E11: Loans other than overdrafts, convenience credit, extended credit, credit card credit, revolving credit other than credit card credit, reverse repurchase agreements, trade receivables and financial leases | H11: typ_instrmnt | J11: =D11 -> 1004 | K11: Loans other than overdrafts, convenience credit, extended credit, credit card credit, revolving credit other than credit card credit, reverse repurchase agreements, trade receivables and financial leases
A12: NULL | B12: 1000 | C12: 1 | D12: 1004 | E12: Loans other than overdrafts, convenience credit, extended credit, credit card credit, revolving credit other than credit card credit, reverse repurchase agreements, trade receivables and financial leases | H12: typ_instrmnt | J12: =D12 -> 1004 | K12: Loans other than overdrafts, convenience credit, extended credit, credit card credit, revolving credit other than credit card credit, reverse repurchase agreements, trade receivables and financial leases
A13: NULL | B13: 51 | C13: 1 | D13: 1001 | E13: Revolving credit other than overdrafts and credit card debt | H13: typ_instrmnt | J13: =D13 -> 1001 | K13: =E13 -> Revolving credit other than overdrafts and credit card debt
A14: NULL | B14: 52 | C14: 1 | D14: 1001 | E14: Revolving credit other than overdrafts and credit card debt | H14: typ_instrmnt | J14: =D14 -> 1001 | K14: =E14 -> Revolving credit other than overdrafts and credit card debt
A15: NULL | B15: 60 | C15: 1 | D15: 1002 | E15: Credit lines other than revolving credit | H15: typ_instrmnt | J15: =D15 -> 1002 | K15: =E15 -> Credit lines other than revolving credit
A16: NULL | B16: 70 | C16: 1 | D16: 1003 | E16: Reverse repurchase agreements | H16: typ_instrmnt | J16: =D16 -> 1003 | K16: =E16 -> Reverse repurchase agreements
A17: NULL | B17: 81 | C17: 1 | D17: 71 | E17: Trade receivables | H17: typ_instrmnt | J17: =D17 -> 71 | K17: =E17 -> Trade receivables
A18: NULL | B18: 30 | C18: 1 | D18: 20 | E18: Overdrafts | H18: typ_instrmnt | J18: =D18 -> 20 | K18: =E18 -> Overdrafts
A19: NULL | B19: 31 | C19: 1 | D19: 20 | E19: Overdrafts | H19: typ_instrmnt | J19: =D19 -> 20 | K19: =E19 -> Overdrafts
A20: NULL | B20: 32 | C20: 1 | D20: 20 | E20: Overdrafts | H20: typ_instrmnt | J20: =D20 -> 20 | K20: =E20 -> Overdrafts
A21: NULL | B21: 33 | C21: 1 | D21: 20 | E21: Overdrafts | H21: typ_instrmnt | J21: =D21 -> 20 | K21: =E21 -> Overdrafts
A22: NULL | B22: 34 | C22: 1 | D22: 20 | E22: Overdrafts | H22: typ_instrmnt | J22: =D22 -> 20 | K22: =E22 -> Overdrafts
A23: NULL | B23: 40 | C23: 1 | D23: 51 | E23: Credit card debt | H23: typ_instrmnt | J23: =D23 -> 51 | K23: =E23 -> Credit card debt
A24: NULL | B24: 41 | C24: 1 | D24: 51 | E24: Credit card debt | H24: typ_instrmnt | J24: =D24 -> 51 | K24: =E24 -> Credit card debt
... A32: NULL | B32: 100 | C32: 1 | D32: 1004 | E32: Loans other than overdrafts, convenience credit, extended credit, credit card credit, revolving credit other than credit card credit, reverse repurchase agreements, trade receivables and financial leases | H32: typ_instrmnt | J32: =D32 -> 1004 | K32: =E32 -> Loans other than overdrafts, convenience credit, extended credit, credit card credit, revolving credit other than credit card credit, reverse repurchase agreements, trade receivables and financial leases
A33: instrumentos de divida | B33: NULL | C33: 2 | D33: 1005 | E33: Debt securities | H33: typ_instrmnt | J33: =D33 -> 1005 | K33: =E33 -> Debt securities
A34: instrumentos de divida | B34: NULL | C34: 2 | D34: 1005 | E34: Debt securities | H34: typ_instrmnt | J34: =D34 -> 1005 | K34: =E34 -> Debt securities
A35: instrumentos de divida | B35: **** | C35: 2 | D35: 1005 | E35: Debt securities | H35: typ_instrmnt | J35: =D35 -> 1005 | K35: =E35 -> Debt securities
A36: NULL | B36: 10 | C36: 1 | D36: 1000 | E36: Deposits other than reverse repurchase agreements | H36: typ_instrmnt | J36: =D36 -> 1000 | K36: =E36 -> Deposits other than reverse repurchase agreements
A37: NULL | B37: 20 | C37: 1 | D37: 20 | E37: Overdrafts | H37: typ_instrmnt | J37: =D37 -> 20 | K37: =E37 -> Overdrafts

Sheet Sheet1
L1: Column1 | M1: Column2 | N1: Column3 | O1: Column4 | P1: Column5 | R1: Column1 | S1: Column2
L2: freq | M2: freq_traduzida_246 | N2: freq_traduzida_247 | O2: freq_traduzida_248 | P2: freq_traduzida_785 | R2: tayd91c0_celemtab | S2: tayd91c0_gelemtab
M3: NULL | N3: NULL | O3: NULL | P3: NULL | R3: 212 | S3: ANUAL
L4: M16 | M4: NULL | N4: NULL | O4: NULL | P4: 16 MESES | R4: 202 | S4: BIMENSAL
L5: 200 | M5: NULL | N5: NULL | O5: NULL | P5: NULL | R5: 206 | S5: SEMESTRAL
M6: NULL | N6: NULL | O6: NULL | P6: NULL | R6: 101 | S6: DIARIO
L7: M86 | M7: NULL | N7: NULL | O7: NULL | P7: NULL | R7: 201 | S7: MENSAL
L8: 401 | M8: NULL | N8: NULL | O8: NULL | P8: NULL | R8: 203 | S8: TRIMESTRAL
A9: SELECT DISTINCT tayd91c0_celemtab, tayd91c0_gelemtab--tayd91c0_celemtab, tayd91c0_gelemtab as freq_traduzida_248 | L9: M42 | M9: NULL | N9: NULL | O9: NULL | P9: NULL | R9: 301 | S9: ANUAL
A10: FROM cd_estruturais.tat91_tabelas | L10: 45335 | M10: NULL | N10: NULL | O10: NULL | P10: NULL
A11: WHERE data_date_part = (SELECT MAX(data_date_part) FROM cd_estruturais.tat91_tabelas) | L11: M14 | M11: NULL | N11: NULL | O11: NULL | P11: 14 MESES
A12: AND tayd91c0_ctabela = '248' | L12: 208 | M12: NULL | N12: NULL | O12: 8 MESES | P12: NULL
A13: AND tayd91c0_gelemtab in ('TRIMESTRAL','SEMESTRAL','MENSAL','DIARIO','BIMENSAL','ANUAL') | L13: N05 | M13: NULL | N13: NULL | O13: NULL | P13: 5 ANOS | R13: SELECT DISTINCT tayd91c0_celemtab, tayd91c0_gelemtab--tayd91c0_celemtab, tayd91c0_gelemtab as freq_traduzida_248
A14: tayd91c0_celemtab | B14: tayd91c0_gelemtab | L14: 312 | M14: NULL | N14: NULL | O14: NULL | P14: NULL | R14: FROM cd_estruturais.tat91_tabelas
A15: 212 | B15: ANUAL | L15: NULL | M15: NULL | N15: NULL | O15: NULL | P15: NULL | R15: WHERE data_date_part = (SELECT MAX(data_date_part) FROM cd_estruturais.tat91_tabelas)
A16: 202 | B16: BIMENSAL | L16: M70 | M16: NULL | N16: NULL | O16: NULL | P16: NULL | R16: AND tayd91c0_ctabela = '248'
A17: 203 | B17: TRIMESTRAL | L17: M18 | M17: NULL | N17: NULL | O17: NULL | P17: 18 MESES | R17: AND tayd91c0_gelemtab in ('TRIMESTRAL','SEMESTRAL','MENSAL','DIARIO','BIMENSAL','ANUAL')
A18: 301 | B18: ANUAL | L18: M30 | M18: NULL | N18: NULL | O18: NULL | P18: 30 MESES
A19: 201 | B19: MENSAL | L19: M01 | M19: NULL | N19: NULL | O19: NULL | P19: 1 MES
A20: 101 | B20: DIARIO | L20: 303 | M20: NULL | N20: TRES ANOS | O20: 3 ANOS | P20: NULL
A21: 206 | B21: SEMESTRAL | L21: M02 | M21: NULL | N21: NULL | O21: NULL | P21: 2 MESES
L22: 248 | M22: NULL | N22: NULL | O22: 48 MESES | P22: NULL
L23: M07 | M23: NULL | N23: NULL | O23: NULL | P23: 7 MESES
L24: M36 | M24: NULL | N24: NULL | O24: NULL | P24: 36 MESES
L25: 45344 | M25: NULL | N25: NULL | O25: NULL | P25: NULL
L26: M11 | M26: NULL | N26: NULL | O26: NULL | P26: 11 MESES
L27: M06 | M27: NULL | N27: NULL | O27: NULL | P27: 6 MESES
L28: 45425 | M28: NULL | N28: NULL | O28: NULL | P28: NULL
L29: 215 | M29: NULL | N29: NULL | O29: 15 MESES | P29: NULL
L30: M85 | M30: NULL | N30: NULL | O30: NULL | P30: NULL
L31: M09 | M31: NULL | N31: NULL | O31: NULL | P31: 9 MESES
L32: 206 | M32: NULL | N32: 6 MESES | O32: SEMESTRAL | P32: NULL
L33: M08 | M33: NULL | N33: NULL | O33: NULL | P33: 8 MESES
L34: M60 | M34: NULL | N34: NULL | O34: NULL | P34: NULL
L35: 309 | M35: NULL | N35: NULL | O35: NULL | P35: NULL
L36: M05 | M36: NULL | N36: NULL | O36: NULL | P36: 5 MESES
L37: M03 | M37: NULL | N37: NULL | O37: NULL | P37: 3 MESES
L38: 45440 | M38: NULL | N38: NULL | O38: NULL | P38: NULL
L39: M91 | M39: NULL | N39: NULL | O39: NULL | P39: NULL
L40: 204 | M40: NULL | N40: NULL | O40: 4 MESES | P40: NULL
L41: 45323 | M41: NULL | N41: NULL | O41: NULL | P41: NULL
L42: M10 | M42: NULL | N42: NULL | O42: NULL | P42: 10 MESES
L43: 237 | M43: NULL | N43: NULL | O43: 37 MESES | P43: NULL
L44: M04 | M44: NULL | N44: NULL | O44: NULL | P44: 4 MESES
L45: 101 | M45: NULL | N45: DIARIO | O45: DIARIO | P45: NULL
L46: 304 | M46: NULL | N46: 4 ANOS | O46: NULL | P46: NULL
L47: M39 | M47: NULL | N47: NULL | O47: NULL | P47: NULL
L48: N01 | M48: NULL | N48: NULL | O48: NULL | P48: 1 ANO
L49: VEN | M49: NULL | N49: NULL | O49: NULL | P49: NULL
L50: M17 | M50: NULL | N50: NULL | O50: NULL | P50: 17 MESES
L51: 201 | M51: NULL | N51: MENSAL | O51: MENSAL | P51: NULL
L52: 212 | M52: NULL | N52: ANUAL | O52: ANUAL | P52: NULL
L53: 310 | M53: NULL | N53: NULL | O53: NULL | P53: NULL
L54: M48 | M54: NULL | N54: NULL | O54: NULL | P54: NULL
L55: 296 | M55: NULL | N55: NULL | O55: 96 MESES | P55: NULL
L56: 272 | M56: NULL | N56: NULL | O56: 72 MESES | P56: NULL
L57: 45350 | M57: NULL | N57: NULL | O57: NULL | P57: NULL
L58: A01 | M58: NULL | N58: NULL | O58: NULL | P58: NULL
L59: M26 | M59: NULL | N59: NULL | O59: NULL | P59: 26 MESES
L60: 45434 | M60: NULL | N60: NULL | O60: NULL | P60: NULL
L61: M72 | M61: NULL | N61: NULL | O61: NULL | P61: NULL
L62: 45415 | M62: NULL | N62: NULL | O62: NULL | P62: NULL
L63: 203 | M63: NULL | N63: TRIMESTRAL | O63: TRIMESTRAL | P63: NULL
L64: M54 | M64: NULL | N64: NULL | O64: NULL | P64: NULL
L65: M19 | M65: NULL | N65: NULL | O65: NULL | P65: 19 MESES
L66: 45378 | M66: NULL | N66: NULL | O66: NULL | P66: NULL
L67: 236 | M67: NULL | N67: NULL | O67: 36 MESES | P67: NULL
L68: 284 | M68: NULL | N68: NULL | O68: 84 MESES | P68: NULL
L69: M23 | M69: NULL | N69: NULL | O69: NULL | P69: 23 MESES
L70: M24 | M70: NULL | N70: NULL | O70: NULL | P70: 24 MESES
L71: M99 | M71: NULL | N71: NULL | O71: NULL | P71: NULL
L72: M46 | M72: NULL | N72: NULL | O72: NULL | P72: NULL
L73: 218 | M73: NULL | N73: 18 MESES | O73: 18 MESES | P73: NULL
L74: M20 | M74: NULL | N74: NULL | O74: NULL | P74: 20 MESES
M75: NULL | N75: NULL | O75: NULL | P75: NULL
L76: M12 | M76: NULL | N76: NULL | O76: NULL | P76: 12 MESES
L77: D07 | M77: NULL | N77: NULL | O77: NULL | P77: 7 DIAS
L78: M96 | M78: NULL | N78: NULL | O78: NULL | P78: NULL
L79: M21 | M79: NULL | N79: NULL | O79: NULL | P79: 21 MESES
L80: M15 | M80: NULL | N80: NULL | O80: NULL | P80: 15 MESES
L81: M52 | M81: NULL | N81: NULL | O81: NULL | P81: NULL
L82: 224 | M82: NULL | N82: 2 ANOS | O82: 24 MESES | P82: NULL
L83: 301 | M83: NULL | N83: ANUAL | O83: ANUAL | P83: NULL
L84: 305 | M84: NULL | N84: 5 ANOS | O84: 5 ANOS | P84: NULL
L85: M13 | M85: NULL | N85: NULL | O85: NULL | P85: 13 MESES
L86: M84 | M86: NULL | N86: NULL | O86: NULL | P86: NULL
L87: M22 | M87: NULL | N87: NULL | O87: NULL | P87: 22 MESES
L88: 45471 | M88: NULL | N88: NULL | O88: NULL | P88: NULL
L89: M59 | M89: NULL | N89: NULL | O89: NULL | P89: NULL
L90: 260 | M90: NULL | N90: NULL | O90: 60 MESES | P90: NULL
L91: 45473 | M91: NULL | N91: NULL | O91: NULL | P91: NULL
L92: 308 | M92: NULL | N92: NULL | O92: NULL | P92: NULL
L95: SELECT
L96: freq, freq_traduzida_246, freq_traduzida_247, freq_traduzida_248, freq_traduzida_785
L97: FROM
L98: (
L99: SELECT DISTINCT cod_freq_taxa_act as freq
L100: FROM cd_alm.al029_cnt_core_m
L101: WHERE ref_date > '2024'
L102: UNION
...

Sheet AUX
A1: Estados possiveis | J1: Estados de desenvolvimento possiveis
A2: Concluido | J2: Concluido
A3: Mapeamento com LT fechado, mas parametrização pendente | J3: Pronto a desenvolver
A4: Novo campo, mapeamento datalake fechado, com necessidade de criar parametrização | J4: Aguarda desenvolvimento de outras equipas
A5: Novo campo, mapeamento datalake fechado, sem necessidade de criar parametrização | J5: Por iniciar
A6: Novo campo, mapeamento datalake pendente, com necessidade de criar parametrização
A7: Novo campo, mapeamento datalake pendente, sem necessidade de criar parametrização
A8: Em curso
A9: Por iniciar

Sheet CREATE TABLE bail_in_srb
A1: ############## Create table ###############
A2: CREATE TABLE bu_captools_work.bail_in_srb ( legal_entity STRING, lei_code STRING, id_liability STRING, nature_instrument STRING, governing_law STRING, contract_currency STRING, issuance_date STRING, legal_maturity_date STRING, earliest_redemption_date STRING, payment_interest_date STRING, outstanding_amount DECIMAL(38,6), insolvency_ranking STRING, flag_same_resol_group STRING, type_own_funds STRING, amount_own_funds DECIMAL(17,2), amount_subord_liabil_not_own_funds DECIMAL(17,2), second_own_funds_component STRING, amount_own_funds_component DECIMAL(17,2), agio_own_funds DECIMAL(17,2), carrying_amount_ifrs DECIMAL(38,6), carrying_amount_national_gaap DECIMAL(38,6), original_amount_issued_eur DECIMAL(21,6), original_amount_issued_currency DECIMAL(21,6), outstanding_principal_amount DECIMAL(38,6), accrued_interest DECIMAL(38,6), amount_writedown DECIMAL(38,6), portion_liabil_external_issuances DECIMAL(21,6), flag_requirements_srmr STRING, total_amount_fees_charges DECIMAL(38,6), country_contracting_party STRING, tax_residence_contracting_party STRING, name_contracting_party STRING, id_contracting_party STRING, counterparty_type STRING, counterparty_resol_group STRING, id_guarantee STRING, group_counterparty_id STRING, amount_guarantee DECIMAL(21,6), maximum_amount_guarantee DECIMAL(21,6), type_guarantee STRING, guarantee_trigger STRING, flag_guarantee_requirements_srmr STRING, percentage_collateralisation DECIMAL(27,17), issuance_date_collateral STRING, maturity_date_collateral STRING, id_securities_collateral STRING, flag_collateral_assets_resol_entity STRING, location_security STRING, type_collateralisation STRING, value_collateral STRING, type_protection_value STRING, date_value_security STRING, protection_valuation_approach STRING, ckutulmo STRING, htimest STRING ) PARTITIONED BY ( ref_date STRING )

Sheet CREATE & INSERT temps
A1: ############## CREATE TABLE universo_temp ############### | M1: Data Type | N1: Default value for missing data | O1: Default value for not applicable fields
A2: CREATE TABLE bu_captools_work.universo_temp (contract_id STRING, msaldo_final DECIMAL(38,6)) | M2: Varchar (includes Varchar Code List) | N2: MISS | O2: N/A
M3: Numeric (includes numeric Code List) | N3: 99999999999 | O3: 11111111111
A5: ##############INSERT INTO bu_captools_work.universo_temp ###############
A6: INSERT INTO bu_captools_work.universo_temp SELECT concat(fr001.cempresa, fr001.cbalcao, fr001.cnumecta, fr001.zdeposit) as contract_id, sum(msaldo_final) FROM (SELECT * FROM cd_captools.fr001_univ_saldo WHERE ref_date ='${ref_date}' AND cempresa IN ('31','82','89') ) fr001 INNER JOIN (SELECT * FROM cd_captools.fr802_pl_contas WHERE ref_date = '${ref_date}' AND cod_plano = 'BST_IND' AND ( --Para a totalidade da sheet F01.02 do FINREP (Passivo): tipo_conta='P' OR --Para parte da sheet F01.03 do FINREP (Equity): --Paid up capital (0020): (tipo_conta='C' AND carteira_contabilistica='capital' AND instrumento_financeiro='instrumentos de capital') OR --Other equity instruments issued (0070): (tipo_conta='C' AND carteira_contabilistica='outros instrumentos de capital' AND instrumento_financeiro='instrumentos de capital') OR --(-) Treasury shares (0240): (tipo_conta='C' AND carteira_contabilistica='acoes proprias') ) ) AS fr802 ON fr001.ccontab_final_ifrs = fr802.conta group by 1
A11: ############## CREATE TABLE date_next_int_pay_temp ###############
A12: create table bu_captools_work.date_next_int_pay_temp ( contract_id string,payment_interest_date string);
A14: ##############INSERT INTO date_next_int_pay_temp ###############
A15: INSERT into TABLE bu_captools_work.date_next_int_pay_temp select ty.contract_id, ty.payment_interest_date from ( SELECT tx.contract_id, tx.payment_interest_date, (row_number() over (partition BY tx.contract_id ORDER BY tx.contract_id,tx.payment_interest_date)) as rownumb FROM (SELECT contract_id, al029.chave_alm, IF(al029.tipo_balanco='P', al029.dt_prox_liq_juros_pas, 'N/A') AS payment_interest_date FROM (SELECT * FROM bu_captools_work.universo_temp ) universo_temp --4 343 408 LEFT JOIN (SELECT chave_finrep, chave_alm FROM (SELECT concat(cempresa_fr, cbalcao_fr, cnumecta_fr, zdeposit_fr) AS chave_finrep, concat(cempresa, cbalcao, cnumecta, zdeposit) AS chave_master FROM cd_captools.kt_chaves_finrep WHERE ref_date='${ref_date}' ) kt_chaves_finrep LEFT JOIN (SELECT concat(cempresa, cbalcao, cnumecta, zdeposit) AS chave_alm, concat(cempresa_master, cbalcao_master, cnumecta_master, zdeposit_master) AS chave_master FROM cd_alm.kt_chaves_alm_m WHERE ref_date='${ref_date}') kt_chaves_alm_m ON kt_chaves_finrep.chave_master = kt_chaves_alm_m.chave_master) trad ON universo_temp.contract_id = trad.chave_finrep LEFT JOIN (SELECT *, concat(cempresa, cbalcao, cnumecta, zdeposit) AS chave_alm FROM cd_alm.al029_cnt_core_m WHERE ref_date='${ref_date}') al029 ON trad.chave_alm = al029.chave_alm) tx) ty where rownumb = 1;
A131: INSERT into TABLE bu_captools_work.temp_date_next_int_pay
A132: select ty.contract_id,
A133: ty.payment_interest_date
A134: from
A135: (
A136: SELECT tx.contract_id,
... A227: AND dt_prim_amrt_ant_inv IS NOT NULL;

Sheet INSERT bail_in_srb
Q1: Varchar (includes Varchar Code List) | R1: MISS | S1: N/A
Q2: Numeric (includes numeric Code List) | R2: 99999999999 | S2: 11111111111
A5: INSERT OVERWRITE TABLE bu_captools_work.bail_in_srb PARTITION (ref_date='${ref_date}') SELECT DISTINCT legal_entity, lei_code, id_liability, nature_instrument, governing_law, contract_currency, issuance_date, legal_maturity_date, earliest_redemption_date, payment_interest_date, outstanding_amount, if(query2.insolvency_ranking = 'MISS' and query2.nature_instrument = 'Cash account/saving account','9',query2.insolvency_ranking) AS insolvency_ranking, flag_same_resol_group, type_own_funds, amount_own_funds, amount_subord_liabil_not_own_funds, second_own_funds_component, amount_own_funds_component, agio_own_funds, carrying_amount_ifrs, carrying_amount_national_gaap, original_amount_issued_eur, original_amount_issued_currency, outstanding_principal_amount, accrued_interest, amount_writedown, portion_liabil_external_issuances, if(cast(query2.insolvency_ranking AS int) <= 8,'yes','no') AS flag_requirements_srmr, total_amount_fees_charges, country_contracting_party, tax_residence_contracting_party, name_contracting_party, id_contracting_party, counterparty_type, counterparty_resol_group, id_guarantee, group_counterparty_id, amount_guarantee, maximum_amount_guarantee, type_guarantee, guarantee_trigger, flag_guarantee_requirements_srmr, percentage_collateralisation, issuance_date_collateral, maturity_date_collateral, id_securities_collateral, flag_collateral_assets_resol_entity, location_security, type_collateralisation, value_collateral, type_protection_value, date_value_security, protection_valuation_approach, ckutulmo, htimest FROM (SELECT legal_entity, lei_code, id_liability, CASE WHEN query1.nature_instrument = 'CARTOES MISTOS' THEN 'Other' WHEN query1.nature_instrument = 'CONFIRMING' THEN 'Other' WHEN query1.nature_instrument = 'CONTA CHEQUE FORNECEDORES' THEN 'Other' WHEN query1.nature_instrument = 'CONTABILIZACAO CARTEIRA PROPRIA-TITULOS' THEN 'Other' WHEN query1.nature_instrument = 'CONTAS CORRENTES - M.N.' THEN 'Other' WHEN query1.nature_instrument = 'CONTAS CORRENTES - M/E' THEN 'Other' WHEN query1.nature_instrument = 'CONTAS INTERNAS - M.N.' THEN 'Other' WHEN query1.nature_instrument = 'CONTAS INTERNAS - MOEDA ESTRANGEIRA (NOSTROS)' THEN 'Other' WHEN query1.nature_instrument = 'D.O. ESPECIAL' THEN 'Cash account/saving account' WHEN query1.nature_instrument = 'DEP.ORDEM ME (OFFSHORE MADEIRA)' THEN 'Cash account/saving account' WHEN query1.nature_instrument = 'DEP.ORDEM MN(OFFSHORE MADEIRA)' THEN 'Cash account/saving account' WHEN query1.nature_instrument = 'DEPOSITO A ORDEM - M.N. (OFFSHORE CAYMAN)' THEN 'Cash account/saving account' WHEN query1.nature_instrument = 'DEPOSITO A ORDEM - M.N.' THEN 'Cash account/saving account' WHEN query1.nature_instrument = 'DEPOSITO A ORDEM - MOEDA ESTRANGEIRA OFFSHORE' THEN 'Cash account/saving account' WHEN query1.nature_instrument = 'DEPOSITO A ORDEM - MOEDA ESTRANGEIRA' THEN 'Cash account/saving account' WHEN query1.nature_instrument = 'DEPOSITO A PRAZO EM MOEDA NACIONAL' THEN 'Term deposit' WHEN query1.nature_instrument = 'DEPOSITOS A PRAZO - M.E.' THEN 'Term deposit' WHEN query1.nature_instrument = 'DEPOSITOS A PRAZO - M.N. (OFFSHORE)' THEN 'Term deposit' WHEN query1.nature_instrument = 'DEPOSITOS A PRAZO - POUPANCA REFORMA' THEN 'Term deposit' WHEN query1.nature_instrument = 'DEPOSITOS A PRAZO - PRODUTOS ESTRUTURADOS' THEN 'Term deposit' WHEN query1.nature_instrument = 'DEPOSITOS A PRAZO EM MOEDA ESTRANGEIRA' THEN 'Term deposit' WHEN query1.nature_instrument = 'DEPOSITOS A PRAZO EM MOEDA NACIONAL' THEN 'Term deposit' WHEN query1.nature_instrument = 'DEPOSITOS DE POUPANCA' THEN 'Term deposit' WHEN query1.nature_instrument = 'DEVEDORES / CREDORES DIVERSOS' THEN 'Other' WHEN query1.nature_instrument = 'EMPRESTIMOS' THEN 'Other' WHEN query1.nature_instrument = 'ESTRANGEIRO-AVALES E GARANTIAS' THEN 'Other' WHEN query1.nature_instrument = 'FACTORING' THEN 'Other' WHEN query1.nature_instrument = 'Obrigacao Hipotecaria' THEN 'Registered Bond' WHEN query1.nature_instrument = 'Obrigacao Senior' THEN 'Registered Bond' WHEN query1.nature_instrument = 'Obrigacao Subordinada' THEN 'Registered Bond' WHEN query1.nature_instrument = 'PRODUTO GESTAO BALCAO' THEN 'Other' WHEN query1.nature_instrument = 'PRODUTOS ESTRANGEIRO - CREDITOS DOCUMENTARIOS IMPORTACAO' THEN 'Other' WHEN query1.nature_instrument = 'RESERVADO PARA NOVA APLICACAO DE TESOURARIA' THEN 'Borrower Note Loan' WHEN query1.nature_instrument = 'SANTANDER - PRODUTOS TESOURARIA' THEN 'Other' WHEN query1.nature_instrument = 'SUPER SATISFACAO RECARREGAVEL' THEN 'Other' WHEN query1.nature_instrument = 'Titularizacao Sintetica' THEN 'Registered Bond' WHEN query1.nature_instrument = 'Titularizacao' THEN 'Registered Bond' WHEN query1.nature_instrument = 'Acao Ordinaria' THEN 'Title of ownership' WHEN query1.nature_instrument = 'Acao Preferencial' THEN 'Title of ownership' WHEN query1.nature_instrument = 'Emprestimo Subordinado' THEN 'Registered Bond' WHEN query1.nature_instrument = 'Instrumento Fundos Proprios Adicionais Nivel 1 (AT1)' THEN 'Registered Bond' WHEN query1.nature_instrument = 'Prestacao Suplementar' THEN 'Title of ownership' WHEN query1.nature_instrument = 'Suprimento' THEN 'Title of ownership' WHEN query1.nature_instrument IS NULL THEN 'MISS' ELSE query1.nature_instrument END AS nature_instrument, governing_law, contract_currency, issuance_date, legal_maturity_date, earliest_redemption_date, payment_interest_date, outstanding_amount, CASE WHEN query1.contrato_ct610_aux IS NOT NULL THEN query1.rank_insolv_aux1 WHEN query1.nature_instrument = 'CARTOES MISTOS' THEN '14' WHEN query1.nature_instrument = 'CONFIRMING' THEN '9' WHEN query1.nature_instrument = 'CONTA CHEQUE FORNECEDORES' THEN '14' WHEN query1.nature_instrument = 'CONTABILIZACAO CARTEIRA PROPRIA-TITULOS' THEN '9' WHEN query1.nature_instrument = 'CONTAS CORRENTES - M.N.' THEN '9' WHEN query1.nature_instrument = 'CONTAS CORRENTES - M/E' THEN '9' WHEN query1.nature_instrument = 'CONTAS INTERNAS - M.N.' THEN '9' WHEN query1.nature_instrument = 'CONTAS INTERNAS - MOEDA ESTRANGEIRA (NOSTROS)' THEN '9' WHEN query1.nature_instrument = 'DEVEDORES / CREDORES DIVERSOS' THEN '14' WHEN query1.nature_instrument = 'EMPRESTIMOS' THEN '9' WHEN query1.nature_instrument = 'ESTRANGEIRO-AVALES E GARANTIAS' THEN '9' WHEN query1.nature_instrument = 'FACTORING' THEN '9' WHEN query1.nature_instrument IS NULL THEN '14' WHEN query1.nature_instrument = 'PRODUTO GESTAO BALCAO' THEN '14' WHEN query1.nature_instrument = 'PRODUTOS ESTRANGEIRO - CREDITOS DOCUMENTARIOS IMPORTACAO' THEN '9' WHEN query1.nature_instrument = 'RESERVADO PARA NOVA APLICACAO DE TESOURARIA' THEN '20' WHEN query1.nature_instrument = 'SUPER SATISFACAO RECARREGAVEL' THEN '12' WHEN query1.nature_instrument = 'SANTANDER - PRODUTOS TESOURARIA' THEN '9' WHEN query1.contrato_fg001_aux2 IS NOT NULL AND query1.mtot_nao_coberto_por_depositante_aux3 > 0 AND (query1.pme_aux4 IN (1,2,3) OR query1.counterparty_type = 'Households (1)') THEN '14;13' WHEN query1.contrato_fg001_aux2 IS NOT NULL AND query1.mtot_nao_coberto_por_depositante_aux3 > 0 AND !(query1.pme_aux4 IN (1,2,3) OR query1.counterparty_type = 'Households (1)') THEN '14;12' WHEN query1.contrato_fg001_aux2 IS NOT NULL THEN '14' WHEN query1.contrato_nao_existe_fg001 is NOT NULL THEN '12' ELSE 'MISS' END AS insolvency_ranking, flag_same_resol_group, type_own_funds, amount_own_funds, amount_subord_liabil_not_own_funds, second_own_funds_component, amount_own_funds_component, agio_own_funds, carrying_amount_ifrs, carrying_amount_national_gaap, original_amount_issued_eur, original_amount_issued_currency, -- 2 contratos que Pedro Mendes pediu para se incluir no universo de contratos bail-in query1.outstanding_amount - query1.accrued_interest AS outstanding_principal_amount, accrued_interest, amount_writedown, portion_liabil_external_issuances, total_amount_fees_charges, country_contracting_party, tax_residence_contracting_party, name_contracting_party, id_contracting_party, counterparty_type, counterparty_resol_group, id_guarantee, group_counterparty_id, amount_guarantee, maximum_amount_guarantee, type_guarantee, guarantee_trigger, flag_guarantee_requirements_srmr, percentage_collateralisation, issuance_date_collateral, maturity_date_collateral, id_securities_collateral, flag_collateral_assets_resol_entity, location_security, type_collateralisation, value_collateral, type_protection_value, date_value_security, protection_valuation_approach, ckutulmo, htimest FROM (SELECT 'BANCO SANTANDER TOTTA, S.A' AS legal_entity, '549300URJH9VSI58CS32' AS lei_code, temp.contract_id AS id_liability, if(fr004.cproduto = '0V0','FACTORING',coalesce(ct610.tipo_titulo,tat91_023.tayd91c0_gelemtab)) AS nature_instrument, coalesce(tat91_015.tayd91c0_nelemc09, 'PT') AS governing_law, coalesce(tat91_206.TAYD91C0_NELEMC01, 'EUR') AS contract_currency, CASE WHEN trim(coalesce(concat(substr(ct610.dt_emissao,7,4),substr(ct610.dt_emissao,3,4),substr(ct610.dt_emissao,1,2)),fr004.data_abertura)) = '' THEN 'MISS' ELSE coalesce(concat(substr(ct610.dt_emissao,7,4),substr(ct610.dt_emissao,3,4),substr(ct610.dt_emissao,1,2)),fr004.data_abertura) END AS issuance_date, CASE WHEN trim(coalesce(concat(substr(ct610.dt_vencim,7,4),substr(ct610.dt_vencim,3,4),substr(ct610.dt_vencim,1,2)),fr004.data_vencimento)) = '' THEN 'MISS' ELSE coalesce(concat(substr(ct610.dt_vencim,7,4),substr(ct610.dt_vencim,3,4),substr(ct610.dt_vencim,1,2)),fr004.data_vencimento) END AS legal_maturity_date, coalesce(concat(substr(ct610.dt_prim_amrt_ant_inv,7,4),substr(ct610.dt_prim_amrt_ant_inv,3,4),substr(ct610.dt_prim_amrt_ant_inv,1,2)),'N/A') AS earliest_redemption_date, CASE WHEN trim(date_next_int_pay_temp.payment_interest_date) = '' THEN 'MISS' ELSE coalesce(date_next_int_pay_temp.payment_interest_date,'MISS') END AS payment_interest_date, -- 2 contratos que Pedro Mendes pediu para se incluir no universo de contratos bail-in coalesce(TEMP.msaldo_final,0) AS outstanding_amount, ct610.contrato_ct610 AS contrato_ct610_aux, ct610.rank_insolv AS rank_insolv_aux1, fg001.contrato_fg001 AS contrato_fg001_aux2, fg001.mtot_nao_coberto_por_depositante AS mtot_nao_coberto_por_depositante_aux3, fg001_nao_cobertos.contratos_n_cobertos_fg001 AS contrato_nao_existe_fg001, busme.cod_empr_pme AS pme_aux4, IF (coalesce(substring(ct610.zcliente_investidor,1,10),fr004.zcliente) IN ('0000238954', '6511000505', '7400416271', '7400416353', '7400416520', '7400416611', '7400416763', '7400507283', '7400701625', '7401474691', '7401536276', '8037849269', '8043363752', '8044173594', '8046250676', '8046296743', '8046334916', '9001925092'),'yes', 'no') AS flag_same_resol_group, coalesce(ct610.eleg_fund_prop,'N/A') AS type_own_funds, coalesce(ct610.mon_fund_prop,0) AS amount_own_funds, 0 AS amount_subord_liabil_not_own_funds, 'N/A' AS second_own_funds_component, 0 AS amount_own_funds_component, 0 AS agio_own_funds, -- 2 contratos que Pedro Mendes pediu para se incluir no universo de contratos bail-in coalesce(TEMP.msaldo_final,99999999999.99) AS carrying_amount_ifrs, coalesce(TEMP.msaldo_final,99999999999.99) AS carrying_amount_national_gaap, coalesce(ct610.nom_tot_inic,0) AS original_amount_issued_eur, 0 AS original_amount_issued_currency, coalesce(accrued_interest,0) AS accrued_interest, -- 2 contratos que Pedro Mendes pediu para se incluir no universo de contratos bail-in IF(ct610.rank_insolv IN ('1','2','3','8'),TEMP.msaldo_final,0) AS amount_writedown, 0 AS portion_liabil_external_issuances, coalesce(total_amount_fees_charges,0) AS total_amount_fees_charges, coalesce(tat91_015_pais.tayd91c0_nelemc09,'MISS') AS country_contracting_party, coalesce(tat91_015_pais.tayd91c0_nelemc09,'MISS') AS tax_residence_contracting_party, coalesce(IF(ct003.itip_cli= 'F','Natural Customer',ct003.gcliente),'MISS') AS name_contracting_party, coalesce(IF((IF(ct003.itip_cli= 'F','Natural Customer',ct003.clei)) = '#',coalesce(substring(ct610.zcliente_investidor,1,10),ct003.zcliente),IF(ct003.itip_cli= 'F','Natural Customer',ct003.clei)),'MISS') AS id_contracting_party, CASE WHEN ct003.contraparte = 'particulares' THEN 'Households (1)' WHEN ct003.contraparte = 'outras empresas nao financeiras' THEN IF(busme.cod_empr_pme IN (1,2,3),'Non-financial corporations (SMEs) (2)','Non-financial corporations (non-SMEs) (3)') WHEN ct003.contraparte = 'instituicoes de credito' THEN 'Credit institutions (4)' WHEN ct003.contraparte = 'outras instituicoes financeiras ' THEN 'Other financial corporations (5)' WHEN ct003.contraparte = 'bancos centrais' THEN 'General governments & Central banks (6)' WHEN ct003.contraparte = 'setor publico' THEN 'General governments & Central banks (6)' ELSE 'MISS' END AS counterparty_type, coalesce(IF(clientes_intragrupo.zcliente = coalesce(substring(ct610.zcliente_investidor,1,10),fr004.zcliente),IF(clientes_intragrupo.zcliente IN ('0000238954', '6511000505', '7400416271', '7400416353', '7400416520', '7400416611', '7400416763', '7400507283', '7400701625', '7401474691', '7401536276', '8037849269', '8043363752', '8044173594', '8046250676', '8046296743', '8046334916', '9001925092'), 'Intragroup but not intra-resolution group (2)','Intragroup and intra-resolution group (1)'), 'No'),'MISS') AS counterparty_resol_group, 'N/A' AS id_guarantee, 'N/A' AS group_counterparty_id, 0 AS amount_guarantee, 0 AS maximum_amount_guarantee, 'N/A' AS type_guarantee, 'N/A' AS guarantee_trigger, 'N/A' AS flag_guarantee_requirements_srmr, coalesce((((al602.haircut_tit / 100) + 1) * 100),0) AS percentage_collateralisation, coalesce(al602.dt_inicio,'N/A') AS issuance_date_collateral, coalesce(al602.dt_fim,'N/A') AS maturity_date_collateral, coalesce(concat(al602.cempresa_tit,al602.cbalcao_tit,al602.cnumecta_tit,zdeposit_tit),'N/A') AS id_securities_collateral, coalesce(If(concat(al602.cempresa_tit,al602.cbalcao_tit,al602.cnumecta_tit,zdeposit_tit) != 'NULL', 'Yes', 'No'),'MISS') AS flag_collateral_assets_resol_entity, coalesce(If(concat(al602.cempresa_tit,al602.cbalcao_tit,al602.cnumecta_tit,zdeposit_tit) != 'NULL', 'PT', 'N/A'),'MISS') AS location_security, coalesce(If(concat(al602.cempresa_tit,al602.cbalcao_tit,al602.cnumecta_tit,zdeposit_tit) != 'NULL', 'securities', 'N/A'),'MISS') AS type_collateralisation, cast(If(concat(al602.cempresa_tit,al602.cbalcao_tit,al602.cnumecta_tit,zdeposit_tit) != 'NULL', al602.mon_nom_atu_tit, 0) AS STRING) AS value_collateral, coalesce(If(concat(al602.cempresa_tit,al602.cbalcao_tit,al602.cnumecta_tit,zdeposit_tit) != 'NULL', 'Market value (3)', 'N/A'),'MISS') AS type_protection_value, coalesce(If(concat(al602.cempresa_tit,al602.cbalcao_tit,al602.cnumecta_tit,zdeposit_tit) != 'NULL', substr(cast(add_months(cast('${ref_date}' AS TIMESTAMP), -1) AS STRING),1,10), 'N/A'),'MISS') AS date_value_security, coalesce(If(concat(al602.cempresa_tit,al602.cbalcao_tit,al602.cnumecta_tit,zdeposit_tit) != 'NULL', 'Mark-to-market valuation (1)', 'N/A'),'MISS') AS protection_valuation_approach, 'servdlakep' AS ckutulmo, cast(current_timestamp() AS STRING) AS htimest FROM bu_captools_work.universo_temp TEMP LEFT JOIN (SELECT * FROM cd_captools.fr004_cto WHERE ref_date='${ref_date}') fr004 ON temp.contract_id = concat(fr004.cempresa,fr004.cbalcao,fr004.cnumecta,fr004.zdeposit) LEFT JOIN (SELECT *, concat(cempresa,cbalcao,cnumecta,zdeposit) AS contrato_ct610 FROM cd_captools.ct610_titulos WHERE ref_date='${ref_date}' AND cempresa = '31') ct610 ON concat(ct610.cempresa,ct610.cbalcao,ct610.cnumecta,ct610.zdeposit) = concat(fr004.cempresa,fr004.cbalcao,fr004.cnumecta,fr004.zdeposit) LEFT JOIN (SELECT * FROM cd_captools.ct003_univ_cli WHERE ref_date='${ref_date}') ct003 ON ct003.zcliente = coalesce(substring(ct610.zcliente_investidor,1,10),fr004.zcliente) LEFT JOIN -- Faz-se max(data_date_part) para se obter os dados mais recentes da tabela (SELECT t1.* FROM (SELECT * FROM cd_estruturais.tat91_tabelas WHERE tayd91c0_ctabela='015') t1 INNER JOIN (SELECT max(data_date_part) AS data_date_part FROM cd_estruturais.tat91_tabelas WHERE tayd91c0_ctabela='015') t2 ON t1.data_date_part = t2.data_date_part) tat91_015 ON ct610.lei_aplicavel = tat91_015.tayd91c0_celemtab LEFT JOIN -- Faz-se max(data_date_part) para se obter os dados mais recentes da tabela (SELECT t1.* FROM (SELECT * FROM cd_estruturais.tat91_tabelas WHERE tayd91c0_ctabela='015') t1 INNER JOIN (SELECT max(data_date_part) AS data_date_part FROM cd_estruturais.tat91_tabelas WHERE tayd91c0_ctabela='015') t2 ON t1.data_date_part = t2.data_date_part)tat91_015_pais ON tat91_015_pais.tayd91c0_celemtab = ct003.cpais_residencia LEFT JOIN -- Faz-se max(data_date_part) para se obter os dados mais recentes da tabela (SELECT t1.* FROM (SELECT * FROM cd_estruturais.tat91_tabelas WHERE tayd91c0_ctabela='023') t1 INNER JOIN (SELECT max(data_date_part) AS data_date_part FROM cd_estruturais.tat91_tabelas WHERE tayd91c0_ctabela='023') t2 ON t1.data_date_part = t2.data_date_part) tat91_023 ON fr004.cproduto = tat91_023.tayd91c0_celemtab LEFT JOIN -- Faz-se max(data_date_part) para se obter os dados mais recentes da tabela (SELECT t1.* FROM (SELECT * FROM cd_estruturais.tat91_tabelas WHERE tayd91c0_ctabela='206') t1 INNER JOIN (SELECT max(data_date_part) AS data_date_part FROM cd_estruturais.tat91_tabelas WHERE tayd91c0_ctabela='206') t2 ON t1.data_date_part = t2.data_date_part) tat91_206 ON tat91_206.tayd91c0_celemtab = coalesce(ct610.cmoeda,fr004.cmoeda1) LEFT JOIN (SELECT * FROM cd_alm.al602_repos_alm WHERE ref_date='${ref_date}') al602 ON concat(fr004.cempresa,fr004.cbalcao,fr004.cnumecta,fr004.zdeposit)= concat(al602.cempresa,al602.cbalcao,al602.cnumecta,al602.zdeposit) LEFT JOIN (SELECT * FROM cd_captools.clientes_intragrupo WHERE data_date_part='${ref_date}') clientes_intragrupo ON clientes_intragrupo.zcliente = coalesce(substring(ct610.zcliente_investidor,1,10),fr004.zcliente) LEFT JOIN (SELECT * FROM business_sme2003361.out_sme_2003_361 WHERE ref_date='${ref_date}') busme ON busme.zcliente = coalesce(substring(ct610.zcliente_investidor,1,10),fr004.zcliente) LEFT JOIN (SELECT concat(cempresa,cbalcao,cnumecta,zdeposit) AS contrato_fg001, sum(mtot_nao_coberto_por_depositante) AS mtot_nao_coberto_por_depositante FROM cd_alm.fg001_fgd WHERE ref_date='${ref_date}' AND calinea = '#' AND flag_ativo = '1' GROUP BY cempresa, cbalcao, cnumecta, zdeposit) fg001 ON contrato_fg001 = concat(fr004.cempresa,fr004.cbalcao,fr004.cnumecta,fr004.zdeposit) LEFT JOIN (SELECT concat(cempresa,cbalcao,cnumecta,zdeposit) AS contratos_n_cobertos_fg001 FROM cd_alm.fg001_fgd WHERE ref_date='${ref_date}' AND !(calinea = '#' AND flag_ativo = '1' )) fg001_nao_cobertos on contratos_n_cobertos_fg001 = concat(fr004.cempresa,fr004.cbalcao,fr004.cnumecta,fr004.zdeposit) LEFT JOIN (SELECT * FROM bu_captools_work.date_next_int_pay_temp) date_next_int_pay_temp ON date_next_int_pay_temp.contract_id = temp.contract_id LEFT JOIN (SELECT CONCAT(cempresa,cbalcao,cnumecta,zdeposit) AS contract_id, NVL(SUM(MSALDO_FINAL), 0) AS accrued_interest FROM (SELECT * FROM cd_captools.fr001_univ_saldo WHERE ref_date ='${ref_date}' ) AS fr001 INNER JOIN (SELECT * FROM cd_captools.fr802_pl_contas WHERE ref_date = '${ref_date}' AND cod_plano = 'BST_IND' AND COMPOSICAO_VALOR = 'juros/encargos a pagar' AND (tipo_conta='P' OR (tipo_conta='C' AND instrumento_financeiro='instrumentos de capital')) ) AS fr802 ON fr001.ccontab_final_ifrs = fr802.conta GROUP BY cempresa, cbalcao, cnumecta, zdeposit) t_accrued_interest ON t_accrued_interest.contract_id = temp.contract_id LEFT JOIN (SELECT CONCAT(cempresa,cbalcao,cnumecta,zdeposit) AS contract_id, NVL(SUM(MSALDO_FINAL), 0) AS total_amount_fees_charges FROM (SELECT * FROM cd_captools.fr001_univ_saldo WHERE ref_date ='${ref_date}' ) AS fr001 INNER JOIN (SELECT * FROM cd_captools.fr802_pl_contas WHERE ref_date = '${ref_date}' AND cod_plano = 'BST_IND' AND (tipo_conta='P' OR (tipo_conta='C' AND instrumento_financeiro='instrumentos de capital')) AND COMPOSICAO_VALOR = 'despesas/comissoes com encargo diferido associadas ao custo amortizado' ) AS fr802 ON fr001.ccontab_final_ifrs = fr802.conta GROUP BY cempresa, cbalcao, cnumecta, zdeposit) t_total_amount_fees_charges ON t_total_amount_fees_charges.contract_id = temp.contract_id) AS query1) AS query2;
