Workbook

Sheet Plano_V1
B6: Re-testes - input | D6: 0.2 | M6: =M7-M10 -> 0 | N6: =N7-N10 -> 0 | O6: =O7-O10 -> 0 | P6: =P7-P10 -> 0 | Q6: =Q7-Q10 -> 0 | R6: =R7-R10 -> 0 | S6: =S7-S10 -> 0 | T6: =T7-T10 -> 0 | ... FK6: =FK7-FK10 -> 0
B7: Re-testes - output | D7: =50%*25% -> 0.125 | L7: =AVERAGE(M7:EL7) -> 2.4923077 | M7: 3 | N7: 3 | O7: 3 | P7: 3 | Q7: 3 | R7: 2 | S7: 2 | T7: 2 | U7: 2 | V7: 2 | W7: 2 | X7: 2 | Y7: 2 | Z7: 2 | AA7: 2 | AB7: 2 | AC7: 2 | AD7: 1 | AE7: 1 | AF7: 1 | AG7: 3 | AH7: 3 | AI7: 3 | AJ7: 3 | AK7: 2 | AL7: 3 | AM7: 3 | AN7: 3 | AO7: 3 | AP7: 3 | AQ7: 2 | AR7: 2 | AS7: 2 | AT7: 0 | AU7: 1 | AV7: 1 | AW7: 0 | AX7: 1 | AY7: 1 | AZ7: 1 | BA7: 2 | BB7: 2 | BC7: 2 | BD7: 2 | BE7: 2 | BF7: 2 | BG7: 2 | BH7: 2 | BI7: 2 | BJ7: 2 | BK7: 2 | BL7: 2 | BM7: 2 | BN7: 2 | BO7: 2 | BP7: 3 | BQ7: 3 | BR7: 3 | BS7: 3 | BT7: 3 | BU7: 3 | BV7: 3 | BW7: 3 | BX7: 3 | BY7: 3 | BZ7: 3 | CA7: 3 | CB7: 3 | CC7: 3 | CD7: 3 | CE7: 3 | CF7: 3 | CG7: 3 | CH7: 3 | CI7: 3 | CJ7: 3 | CK7: 3 | CL7: 3 | CM7: 3 | CN7: 3 | CO7: 3 | CP7: 3 | CQ7: 3 | CR7: 3 | CS7: 3 | CT7: 3 | CU7: 3 | CV7: 3 | CW7: 3 | CX7: 3 | CY7: 3 | CZ7: 3 | DA7: 3 | DB7: 3 | DC7: 3 | DD7: 3 | DE7: 3 | DF7: 3 | DG7: 3 | DH7: 3 | DI7: 3 | DJ7: 3 | DK7: 3 | DL7: 3 | DM7: 3 | DN7: 2 | DO7: 3 | DP7: 3 | DQ7: 3 | DR7: 3 | DS7: 3 | DT7: 3 | DU7: 3 | DV7: 3 | DW7: 3 | DX7: 3 | DY7: 3 | DZ7: 3 | EA7: 3 | EB7: 3 | EC7: 3 | ED7: 3 | EE7: 3 | EF7: 3 | EG7: 3 | EH7: 3 | EI7: 0 | EJ7: 0 | EK7: 0 | EL7: 0 | EM7: 0 | EN7: 0 | EO7: 0 | EP7: 3 | EQ7: 3 | ER7: 3 | ES7: 3 | ET7: 3 | EU7: 3 | EV7: 3 | EW7: 3 | EX7: 3 | EY7: 3 | EZ7: 3 | FA7: 3 | FB7: 3 | FC7: 3 | FD7: 3 | FE7: 3 | FF7: 3 | FG7: 3 | FH7: 3 | FI7: 3 | FJ7: 3 | FK7: 3
M10: =SUBTOTAL(9,M14:M636) -> 3 | N10: =SUBTOTAL(9,N14:N636) -> 3 | O10: =SUBTOTAL(9,O14:O636) -> 3 | P10: =SUBTOTAL(9,P14:P636) -> 3 | Q10: =SUBTOTAL(9,Q14:Q636) -> 3 | R10: =SUBTOTAL(9,R14:R636) -> 2 | S10: =SUBTOTAL(9,S14:S636) -> 2 | T10: =SUBTOTAL(9,T14:T636) -> 2 | ... FK10: =SUBTOTAL(9,FK14:FK636) -> 3
M11: Julho | W11: Julho | AJ11: Agosto | BF11: Setembro | CA11: Outubro | CX11: Novembro | DS11: Dezembro | EO11: Janeiro
M12: =M13 -> 45474 | N12: =N13 -> 45475 | O12: =O13 -> 45476 | P12: =P13 -> 45477 | Q12: =Q13 -> 45478 | R12: =R13 -> 45481 | S12: =S13 -> 45482 | T12: =T13 -> 45483 | ... FK12: =FK13 -> 45688
B13: Âmbito | C13: Sub-âmbito | D13: Tipo de teste | E13: Tabela | F13: Campo | G13: Status | H13: Status2 | I13: Horas | J13: Dias | K13: Pendências | L13: Val | M13: 45474 | N13: =WORKDAY(M13,1) -> 45475 | O13: =WORKDAY(N13,1) -> 45476 | P13: =WORKDAY(O13,1) -> 45477 | Q13: =WORKDAY(P13,1) -> 45478 | R13: =WORKDAY(Q13,1) -> 45481 | S13: =WORKDAY(R13,1) -> 45482 | T13: =WORKDAY(S13,1) -> 45483 | U13: =WORKDAY(T13,1) -> 45484 | ... FK13: =WORKDAY(FJ13,1) -> 45688
B14: 1. Assessment | I14: =SUM(I15:I18) -> 280 | J14: =SUM(J15:J18) -> 35
B15: Pilar III | C15: Bens Imóveis | G15: 7. Por iniciar | I15: =J15*8 -> 40 | J15: 5 | L15: =J15-SUM(M15:FK15) -> 0 | W15: 1 | X15: 1 | Y15: 1 | Z15: 1 | AA15: 1
B16: Pilar III | C16: Modelo Verde | G16: 7. Por iniciar | I16: =J16*8 -> 80 | J16: 10 | L16: =J16-SUM(M16:FK16) -> 0 | R16: 2 | S16: 2 | T16: 2 | U16: 2 | V16: 2
B17: Pilar III | C17: Pilar III | G17: 7. Por iniciar | I17: =J17*8 -> 40 | J17: 5 | L17: =J17-SUM(M17:FK17) -> 0 | AB17: 1 | AC17: 1 | AD17: 1 | AE17: 1 | AF17: 0.5 | AG17: 0.5
B18: GD | C18: GD | G18: 7. Por iniciar | I18: =J18*8 -> 120 | J18: 15 | L18: =J18-SUM(M18:FK18) -> 0 | M18: 3 | N18: 3 | O18: 3 | P18: 3 | Q18: 3
B20: 2. Re-especificação | I20: =SUM(I21:I23) -> 120 | J20: =SUM(J21:J23) -> 15
B21: Pilar III | C21: Bens Imóveis | G21: 7. Por iniciar | I21: =J21*8 -> 40 | J21: 5 | L21: =J21-SUM(M21:FK21) -> 0 | W21: 0.5 | AB21: 0.5 | AG21: 0.5 | AL21: 0.5 | AQ21: 0.5 | AV21: 0.5 | BA21: 0.5 | BF21: 0.5 | BK21: 0.5 | BP21: 0.5
B22: Pilar III | C22: Modelo Verde | G22: 7. Por iniciar | I22: =J22*8 -> 40 | J22: 5 | L22: =J22-SUM(M22:FK22) -> 0 | W22: 0.5 | AB22: 0.5 | AG22: 0.5 | AL22: 0.5 | AQ22: 0.5 | AV22: 0.5 | BA22: 0.5 | BF22: 0.5 | BK22: 0.5 | BP22: 0.5
B23: Pilar III | C23: Pilar III | G23: 7. Por iniciar | I23: =J23*8 -> 40 | J23: 5 | L23: =J23-SUM(M23:FK23) -> 0 | BF23: 0.5 | BK23: 0.5 | BP23: 0.5 | BU23: 0.5 | BZ23: 0.5 | CE23: 0.5 | CJ23: 0.5 | CO23: 0.5 | CT23: 0.5 | CY23: 0.5
B25: 3. Testes / Re-testes | I25: =I26+I27+I42+I198+I362+I447 -> 1188.2 | J25: =J26+J27+J42+J198+J362+J447 -> 150
B26: Testes Regressivos | G26: 7. Por iniciar | I26: =4*22 -> 88 | J26: =I26/8 -> 11 | L26: =J26-SUM(M26:FK26) -> 0 | AA26: 0.5 | AF26: 0.5 | AK26: 0.5 | AP26: 0.5 | AU26: 0.5 | AZ26: 0.5 | BE26: 0.5 | BJ26: 0.5 | BO26: 0.5 | BT26: 0.5 | BY26: 0.5 | CD26: 0.5 | CI26: 0.5 | CN26: 0.5 | CS26: 0.5 | CX26: 0.5 | DC26: 0.5 | DH26: 0.5 | DM26: 0.5 | DR26: 0.5 | DW26: 0.5 | EB26: 0.5
B27: Pilar III | C27: Bens Imóveis - Input | I27: =SUM(I28:I41) -> 0 | J27: =ROUNDUP(I27/8,0) -> 0 | L27: =J27-SUM(M27:FK27) -> -3 | X27: 0.5 | Y27: 0.5 | AC27: 0.5 | AG27: 1 | AH27: 0.5
A28: =E28&F28 -> cd_imv_inp_certif_estimativan.a. | B28: Pilar III | C28: Bens Imóveis - Input | D28: 1. Universo | E28: cd_imv_inp_certif_estimativa | F28: n.a. | G28: =INDEX(Auxiliar!$B$16:$B$24,MATCH(Plano_V1!H28,Auxiliar!$C$16:$C$24,0),1) -> #N/A | H28: =VLOOKUP(A28,'Aux - pivots1'!$A:$B,2,0) -> #N/A | I28: =SUMIFS(Table1[Estimação (horas)],Table1[Tabela],Plano_V1!E28,Table1[Campo],Plano_V1!F28) -> 0 | J28: =I28/8 -> 0 | K28: sem pendencia | L28: =J28-SUM(M28:FK28) -> 0
A29: =E29&F29 -> cd_imv_inp_certif_estimativacempbem | B29: Pilar III | C29: Bens Imóveis - Input | D29: 2. Campo | E29: cd_imv_inp_certif_estimativa | F29: cempbem | G29: =INDEX(Auxiliar!$B$16:$B$24,MATCH(Plano_V1!H29,Auxiliar!$C$16:$C$24,0),1) -> #N/A | H29: =VLOOKUP(A29,'Aux - pivots1'!$A:$B,2,0) -> #N/A | I29: =SUMIFS(Table1[Estimação (horas)],Table1[Tabela],Plano_V1!E29,Table1[Campo],Plano_V1!F29) -> 0 | J29: =I29/8 -> 0 | K29: sem pendencia | L29: =J29-SUM(M29:FK29) -> 0
A30: =E30&F30 -> cd_imv_inp_certif_estimativachave_encriptada | B30: Pilar III | C30: Bens Imóveis - Input | D30: 2. Campo | E30: cd_imv_inp_certif_estimativa | F30: chave_encriptada | G30: =INDEX(Auxiliar!$B$16:$B$24,MATCH(Plano_V1!H30,Auxiliar!$C$16:$C$24,0),1) -> #N/A | H30: =VLOOKUP(A30,'Aux - pivots1'!$A:$B,2,0) -> #N/A | I30: =SUMIFS(Table1[Estimação (horas)],Table1[Tabela],Plano_V1!E30,Table1[Campo],Plano_V1!F30) -> 0 | J30: =I30/8 -> 0 | K30: sem pendencia | L30: =J30-SUM(M30:FK30) -> 0
A31: =E31&F31 -> cd_imv_inp_certif_estimativackbalbem | B31: Pilar III | C31: Bens Imóveis - Input | D31: 2. Campo | E31: cd_imv_inp_certif_estimativa | F31: ckbalbem | G31: =INDEX(Auxiliar!$B$16:$B$24,MATCH(Plano_V1!H31,Auxiliar!$C$16:$C$24,0),1) -> #N/A | H31: =VLOOKUP(A31,'Aux - pivots1'!$A:$B,2,0) -> #N/A | I31: =SUMIFS(Table1[Estimação (horas)],Table1[Tabela],Plano_V1!E31,Table1[Campo],Plano_V1!F31) -> 0 | J31: =I31/8 -> 0 | K31: sem pendencia | L31: =J31-SUM(M31:FK31) -> 0
A32: =E32&F32 -> cd_imv_inp_certif_estimativackctabem | B32: Pilar III | C32: Bens Imóveis - Input | D32: 2. Campo | E32: cd_imv_inp_certif_estimativa | F32: ckctabem | G32: =INDEX(Auxiliar!$B$16:$B$24,MATCH(Plano_V1!H32,Auxiliar!$C$16:$C$24,0),1) -> #N/A | H32: =VLOOKUP(A32,'Aux - pivots1'!$A:$B,2,0) -> #N/A | I32: =SUMIFS(Table1[Estimação (horas)],Table1[Tabela],Plano_V1!E32,Table1[Campo],Plano_V1!F32) -> 0 | J32: =I32/8 -> 0 | K32: sem pendencia | L32: =J32-SUM(M32:FK32) -> 0
A33: =E33&F33 -> cd_imv_inp_certif_estimativackrefbem | B33: Pilar III | C33: Bens Imóveis - Input | D33: 2. Campo | E33: cd_imv_inp_certif_estimativa | F33: ckrefbem | G33: =INDEX(Auxiliar!$B$16:$B$24,MATCH(Plano_V1!H33,Auxiliar!$C$16:$C$24,0),1) -> #N/A | H33: =VLOOKUP(A33,'Aux - pivots1'!$A:$B,2,0) -> #N/A | I33: =SUMIFS(Table1[Estimação (horas)],Table1[Tabela],Plano_V1!E33,Table1[Campo],Plano_V1!F33) -> 0 | J33: =I33/8 -> 0 | K33: sem pendencia | L33: =J33-SUM(M33:FK33) -> 0
A34: =E34&F34 -> cd_imv_inp_certif_estimativadata_extraccao_info | B34: Pilar III | C34: Bens Imóveis - Input | D34: 2. Campo | E34: cd_imv_inp_certif_estimativa | F34: data_extraccao_info | G34: =INDEX(Auxiliar!$B$16:$B$24,MATCH(Plano_V1!H34,Auxiliar!$C$16:$C$24,0),1) -> #N/A | H34: =VLOOKUP(A34,'Aux - pivots1'!$A:$B,2,0) -> #N/A | I34: =SUMIFS(Table1[Estimação (horas)],Table1[Tabela],Plano_V1!E34,Table1[Campo],Plano_V1!F34) -> 0 | J34: =I34/8 -> 0 | K34: sem pendencia | L34: =J34-SUM(M34:FK34) -> 0
A35: =E35&F35 -> cd_imv_inp_certif_estimativaepc | B35: Pilar III | C35: Bens Imóveis - Input | D35: 2. Campo | E35: cd_imv_inp_certif_estimativa | F35: epc | G35: =INDEX(Auxiliar!$B$16:$B$24,MATCH(Plano_V1!H35,Auxiliar!$C$16:$C$24,0),1) -> #N/A | H35: =VLOOKUP(A35,'Aux - pivots1'!$A:$B,2,0) -> #N/A | I35: =SUMIFS(Table1[Estimação (horas)],Table1[Tabela],Plano_V1!E35,Table1[Campo],Plano_V1!F35) -> 0 | J35: =I35/8 -> 0 | K35: sem pendencia | L35: =J35-SUM(M35:FK35) -> 0
A36: =E36&F36 -> cd_imv_inp_certif_estimativafornecedor | B36: Pilar III | C36: Bens Imóveis - Input | D36: 2. Campo | E36: cd_imv_inp_certif_estimativa | F36: fornecedor | G36: =INDEX(Auxiliar!$B$16:$B$24,MATCH(Plano_V1!H36,Auxiliar!$C$16:$C$24,0),1) -> #N/A | H36: =VLOOKUP(A36,'Aux - pivots1'!$A:$B,2,0) -> #N/A | I36: =SUMIFS(Table1[Estimação (horas)],Table1[Tabela],Plano_V1!E36,Table1[Campo],Plano_V1!F36) -> 0 | J36: =I36/8 -> 0 | K36: sem pendencia | L36: =J36-SUM(M36:FK36) -> 0
A37: =E37&F37 -> cd_imv_inp_certif_estimativametodo_info | B37: Pilar III | C37: Bens Imóveis - Input | D37: 2. Campo | E37: cd_imv_inp_certif_estimativa | F37: metodo_info | G37: =INDEX(Auxiliar!$B$16:$B$24,MATCH(Plano_V1!H37,Auxiliar!$C$16:$C$24,0),1) -> #N/A | H37: =VLOOKUP(A37,'Aux - pivots1'!$A:$B,2,0) -> #N/A | I37: =SUMIFS(Table1[Estimação (horas)],Table1[Tabela],Plano_V1!E37,Table1[Campo],Plano_V1!F37) -> 0 | J37: =I37/8 -> 0 | K37: sem pendencia | L37: =J37-SUM(M37:FK37) -> 0
A38: =E38&F38 -> cd_imv_inp_certif_estimativascore_qualidade | B38: Pilar III | C38: Bens Imóveis - Input | D38: 2. Campo | E38: cd_imv_inp_certif_estimativa | F38: score_qualidade | G38: =INDEX(Auxiliar!$B$16:$B$24,MATCH(Plano_V1!H38,Auxiliar!$C$16:$C$24,0),1) -> #N/A | H38: =VLOOKUP(A38,'Aux - pivots1'!$A:$B,2,0) -> #N/A | I38: =SUMIFS(Table1[Estimação (horas)],Table1[Tabela],Plano_V1!E38,Table1[Campo],Plano_V1!F38) -> 0 | J38: =I38/8 -> 0 | K38: sem pendencia | L38: =J38-SUM(M38:FK38) -> 0
A39: =E39&F39 -> cd_imv_inp_certif_estimativavlr_cnsm_ano | B39: Pilar III | C39: Bens Imóveis - Input | D39: 2. Campo | E39: cd_imv_inp_certif_estimativa | F39: vlr_cnsm_ano | G39: =INDEX(Auxiliar!$B$16:$B$24,MATCH(Plano_V1!H39,Auxiliar!$C$16:$C$24,0),1) -> #N/A | H39: =VLOOKUP(A39,'Aux - pivots1'!$A:$B,2,0) -> #N/A | I39: =SUMIFS(Table1[Estimação (horas)],Table1[Tabela],Plano_V1!E39,Table1[Campo],Plano_V1!F39) -> 0 | J39: =I39/8 -> 0 | K39: sem pendencia | L39: =J39-SUM(M39:FK39) -> 0
A40: =E40&F40 -> cd_imv_inp_certif_estimativavlr_emss_ano | B40: Pilar III | C40: Bens Imóveis - Input | D40: 2. Campo | E40: cd_imv_inp_certif_estimativa | F40: vlr_emss_ano | G40: =INDEX(Auxiliar!$B$16:$B$24,MATCH(Plano_V1!H40,Auxiliar!$C$16:$C$24,0),1) -> #N/A | H40: =VLOOKUP(A40,'Aux - pivots1'!$A:$B,2,0) -> #N/A | I40: =SUMIFS(Table1[Estimação (horas)],Table1[Tabela],Plano_V1!E40,Table1[Campo],Plano_V1!F40) -> 0 | J40: =I40/8 -> 0 | K40: sem pendencia | L40: =J40-SUM(M40:FK40) -> 0
A41: =E41&F41 -> Re-testesn.a. | B41: Pilar III | C41: Bens Imóveis - Input | D41: 2. Campo | E41: Re-testes | F41: n.a. | G41: 7. Por iniciar | I41: =SUM(I28:I40)*D6 -> 0 | J41: =I41/8 -> 0 | K41: sem pendencia | L41: =J41-SUM(M41:FK41) -> 0
A42: =E42&F42 | B42: Pilar III | C42: Bens Imóveis - Output | I42: =SUM(I43:I197) -> 0 | J42: =ROUNDUP(I42/8,0) -> 0 | L42: =J42-SUM(M42:FK42) -> -100 | AH42: 0.5 | AI42: 1 | AJ42: 1 | AM42: 1 | AN42: 1 | AO42: 1 | AP42: 0.5 | AR42: 1 | AS42: 2 | AU42: 0.5 | AX42: 1 | AY42: 1 | AZ42: 0.5 | BA42: 1 | BB42: 2 | BC42: 2 | BD42: 2 | BE42: 1.5 | BF42: 0.5 | BG42: 2 | BH42: 2 | BI42: 2 | BJ42: 1.5 | BK42: 0.5 | BL42: 2 | BM42: 2 | BN42: 2 | BO42: 1.5 | BP42: 1.5 | BQ42: 2 | BR42: 2 | BS42: 2 | BT42: 2 | BU42: 2 | BV42: 2 | BW42: 2 | BX42: 2 | BY42: 2 | BZ42: 2 | CA42: 2 | CB42: 2 | CC42: 2 | CD42: 2 | CE42: 2 | CF42: 2 | CG42: 2 | CH42: 2 | CI42: 2 | CJ42: 2 | CK42: 2 | CL42: 2 | CM42: 2 | CN42: 2 | CO42: 2 | CP42: 2 | CQ42: 2 | CR42: 2 | CS42: 2 | CT42: 2 | CU42: 2
A43: =E43&F43 -> cd_imv_out_prcn.a. | B43: Pilar III | C43: Bens Imóveis - Output | D43: 1. Universo | E43: cd_imv_out_prc | F43: n.a. | G43: =INDEX(Auxiliar!$B$16:$B$24,MATCH(Plano_V1!H43,Auxiliar!$C$16:$C$24,0),1) -> #N/A | H43: =VLOOKUP(A43,'Aux - pivots1'!$A:$B,2,0) -> #N/A | I43: =SUMIFS(Table1[Estimação (horas)],Table1[Tabela],Plano_V1!E43,Table1[Campo],Plano_V1!F43) -> 0 | J43: =I43/8 -> 0 | K43: cd_imv_out_trz_cred_prc | L43: =J43-SUM(M43:FK43) -> 0
A44: =E44&F44 -> cd_imv_out_prccempresa | B44: Pilar III | C44: Bens Imóveis - Output | D44: 2. Campo | E44: cd_imv_out_prc | F44: cempresa | G44: =INDEX(Auxiliar!$B$16:$B$24,MATCH(Plano_V1!H44,Auxiliar!$C$16:$C$24,0),1) -> #N/A | H44: =VLOOKUP(A44,'Aux - pivots1'!$A:$B,2,0) -> #N/A | I44: =SUMIFS(Table1[Estimação (horas)],Table1[Tabela],Plano_V1!E44,Table1[Campo],Plano_V1!F44) -> 0 | J44: =I44/8 -> 0 | K44: cd_imv_out_trz_cred_prc | L44: =J44-SUM(M44:FK44) -> 0
A45: =E45&F45 -> cd_imv_out_prcckbalcao | B45: Pilar III | C45: Bens Imóveis - Output | D45: 2. Campo | E45: cd_imv_out_prc | F45: ckbalcao | G45: =INDEX(Auxiliar!$B$16:$B$24,MATCH(Plano_V1!H45,Auxiliar!$C$16:$C$24,0),1) -> #N/A | H45: =VLOOKUP(A45,'Aux - pivots1'!$A:$B,2,0) -> #N/A | I45: =SUMIFS(Table1[Estimação (horas)],Table1[Tabela],Plano_V1!E45,Table1[Campo],Plano_V1!F45) -> 0 | J45: =I45/8 -> 0 | K45: cd_imv_out_trz_cred_prc | L45: =J45-SUM(M45:FK45) -> 0
A46: =E46&F46 -> cd_imv_out_prccknumcta | B46: Pilar III | C46: Bens Imóveis - Output | D46: 2. Campo | E46: cd_imv_out_prc | F46: cknumcta | G46: =INDEX(Auxiliar!$B$16:$B$24,MATCH(Plano_V1!H46,Auxiliar!$C$16:$C$24,0),1) -> #N/A | H46: =VLOOKUP(A46,'Aux - pivots1'!$A:$B,2,0) -> #N/A | I46: =SUMIFS(Table1[Estimação (horas)],Table1[Tabela],Plano_V1!E46,Table1[Campo],Plano_V1!F46) -> 0 | J46: =I46/8 -> 0 | K46: cd_imv_out_trz_cred_prc | L46: =J46-SUM(M46:FK46) -> 0
A47: =E47&F47 -> cd_imv_out_prccod_estd_prcs | B47: Pilar III | C47: Bens Imóveis - Output | D47: 2. Campo | E47: cd_imv_out_prc | F47: cod_estd_prcs | G47: =INDEX(Auxiliar!$B$16:$B$24,MATCH(Plano_V1!H47,Auxiliar!$C$16:$C$24,0),1) -> #N/A | H47: =VLOOKUP(A47,'Aux - pivots1'!$A:$B,2,0) -> #N/A | I47: 0 | J47: =I47/8 -> 0 | K47: cd_imv_out_trz_cred_prc | L47: =J47-SUM(M47:FK47) -> 0
A48: =E48&F48 -> cd_imv_out_prccod_grt | B48: Pilar III | C48: Bens Imóveis - Output | D48: 2. Campo | E48: cd_imv_out_prc | F48: cod_grt | G48: =INDEX(Auxiliar!$B$16:$B$24,MATCH(Plano_V1!H48,Auxiliar!$C$16:$C$24,0),1) -> #N/A | H48: =VLOOKUP(A48,'Aux - pivots1'!$A:$B,2,0) -> #N/A | I48: =SUMIFS(Table1[Estimação (horas)],Table1[Tabela],Plano_V1!E48,Table1[Campo],Plano_V1!F48) -> 0 | J48: =I48/8 -> 0 | K48: cd_imv_out_trz_cred_prc | L48: =J48-SUM(M48:FK48) -> 0
A49: =E49&F49 -> cd_imv_out_prccod_moeda | B49: Pilar III | C49: Bens Imóveis - Output | D49: 2. Campo | E49: cd_imv_out_prc | F49: cod_moeda | G49: =INDEX(Auxiliar!$B$16:$B$24,MATCH(Plano_V1!H49,Auxiliar!$C$16:$C$24,0),1) -> #N/A | H49: =VLOOKUP(A49,'Aux - pivots1'!$A:$B,2,0) -> #N/A | I49: =SUMIFS(Table1[Estimação (horas)],Table1[Tabela],Plano_V1!E49,Table1[Campo],Plano_V1!F49) -> 0 | J49: =I49/8 -> 0 | K49: cd_imv_out_trz_cred_prc | L49: =J49-SUM(M49:FK49) -> 0
A50: =E50&F50 -> cd_imv_out_prccod_observacao | B50: Pilar III | C50: Bens Imóveis - Output | D50: 2. Campo | E50: cd_imv_out_prc | F50: cod_observacao | G50: =INDEX(Auxiliar!$B$16:$B$24,MATCH(Plano_V1!H50,Auxiliar!$C$16:$C$24,0),1) -> #N/A | H50: =VLOOKUP(A50,'Aux - pivots1'!$A:$B,2,0) -> #N/A | I50: =SUMIFS(Table1[Estimação (horas)],Table1[Tabela],Plano_V1!E50,Table1[Campo],Plano_V1!F50) -> 0 | J50: =I50/8 -> 0 | K50: cd_imv_out_trz_cred_prc | L50: =J50-SUM(M50:FK50) -> 0
A51: =E51&F51 -> cd_imv_out_prccod_prd_grnt | B51: Pilar III | C51: Bens Imóveis - Output | D51: 2. Campo | E51: cd_imv_out_prc | F51: cod_prd_grnt | G51: =INDEX(Auxiliar!$B$16:$B$24,MATCH(Plano_V1!H51,Auxiliar!$C$16:$C$24,0),1) -> #N/A | H51: =VLOOKUP(A51,'Aux - pivots1'!$A:$B,2,0) -> #N/A | I51: =SUMIFS(Table1[Estimação (horas)],Table1[Tabela],Plano_V1!E51,Table1[Campo],Plano_V1!F51) -> 0 | J51: =I51/8 -> 0 | K51: cd_imv_out_trz_cred_prc | L51: =J51-SUM(M51:FK51) -> 0
A52: =E52&F52 -> cd_imv_out_prccod_sprd_grnt | B52: Pilar III | C52: Bens Imóveis - Output | D52: 2. Campo | E52: cd_imv_out_prc | F52: cod_sprd_grnt | G52: =INDEX(Auxiliar!$B$16:$B$24,MATCH(Plano_V1!H52,Auxiliar!$C$16:$C$24,0),1) -> #N/A | H52: =VLOOKUP(A52,'Aux - pivots1'!$A:$B,2,0) -> #N/A | I52: =SUMIFS(Table1[Estimação (horas)],Table1[Tabela],Plano_V1!E52,Table1[Campo],Plano_V1!F52) -> 0 | J52: =I52/8 -> 0 | K52: cd_imv_out_trz_cred_prc | L52: =J52-SUM(M52:FK52) -> 0
A53: =E53&F53 -> cd_imv_out_prccod_tipo | B53: Pilar III | C53: Bens Imóveis - Output | D53: 2. Campo | E53: cd_imv_out_prc | F53: cod_tipo | G53: =INDEX(Auxiliar!$B$16:$B$24,MATCH(Plano_V1!H53,Auxiliar!$C$16:$C$24,0),1) -> #N/A | H53: =VLOOKUP(A53,'Aux - pivots1'!$A:$B,2,0) -> #N/A | I53: =SUMIFS(Table1[Estimação (horas)],Table1[Tabela],Plano_V1!E53,Table1[Campo],Plano_V1!F53) -> 0 | J53: =I53/8 -> 0 | K53: cd_imv_out_trz_cred_prc | L53: =J53-SUM(M53:FK53) -> 0
A54: =E54&F54 -> cd_imv_out_prccomp_id_gar | B54: Pilar III | C54: Bens Imóveis - Output | D54: 2. Campo | E54: cd_imv_out_prc | F54: comp_id_gar | G54: =INDEX(Auxiliar!$B$16:$B$24,MATCH(Plano_V1!H54,Auxiliar!$C$16:$C$24,0),1) -> #N/A | H54: =VLOOKUP(A54,'Aux - pivots1'!$A:$B,2,0) -> #N/A | I54: =SUMIFS(Table1[Estimação (horas)],Table1[Tabela],Plano_V1!E54,Table1[Campo],Plano_V1!F54) -> 0 | J54: =I54/8 -> 0 | K54: cd_imv_out_trz_cred_prc | L54: =J54-SUM(M54:FK54) -> 0
A55: =E55&F55 -> cd_imv_out_prcdata_inicio | B55: Pilar III | C55: Bens Imóveis - Output | D55: 2. Campo | E55: cd_imv_out_prc | F55: data_inicio | G55: =INDEX(Auxiliar!$B$16:$B$24,MATCH(Plano_V1!H55,Auxiliar!$C$16:$C$24,0),1) -> #N/A | H55: =VLOOKUP(A55,'Aux - pivots1'!$A:$B,2,0) -> #N/A | I55: =SUMIFS(Table1[Estimação (horas)],Table1[Tabela],Plano_V1!E55,Table1[Campo],Plano_V1!F55) -> 0 | J55: =I55/8 -> 0 | K55: cd_imv_out_trz_cred_prc | L55: =J55-SUM(M55:FK55) -> 0
A56: =E56&F56 -> cd_imv_out_prcdata_vcmt | B56: Pilar III | C56: Bens Imóveis - Output | D56: 2. Campo | E56: cd_imv_out_prc | F56: data_vcmt | G56: =INDEX(Auxiliar!$B$16:$B$24,MATCH(Plano_V1!H56,Auxiliar!$C$16:$C$24,0),1) -> #N/A | H56: =VLOOKUP(A56,'Aux - pivots1'!$A:$B,2,0) -> #N/A | I56: =SUMIFS(Table1[Estimação (horas)],Table1[Tabela],Plano_V1!E56,Table1[Campo],Plano_V1!F56) -> 0 | J56: =I56/8 -> 0 | K56: cd_imv_out_trz_cred_prc | L56: =J56-SUM(M56:FK56) -> 0
A57: =E57&F57 -> cd_imv_out_prcmontante_eur | B57: Pilar III | C57: Bens Imóveis - Output | D57: 2. Campo | E57: cd_imv_out_prc | F57: montante_eur | G57: =INDEX(Auxiliar!$B$16:$B$24,MATCH(Plano_V1!H57,Auxiliar!$C$16:$C$24,0),1) -> #N/A | H57: =VLOOKUP(A57,'Aux - pivots1'!$A:$B,2,0) -> #N/A | I57: 0 | J57: =I57/8 -> 0 | K57: cd_imv_out_trz_cred_prc | L57: =J57-SUM(M57:FK57) -> 0
A58: =E58&F58 -> cd_imv_out_prcmontante_org | B58: Pilar III | C58: Bens Imóveis - Output | D58: 2. Campo | E58: cd_imv_out_prc | F58: montante_org | G58: =INDEX(Auxiliar!$B$16:$B$24,MATCH(Plano_V1!H58,Auxiliar!$C$16:$C$24,0),1) -> #N/A | H58: =VLOOKUP(A58,'Aux - pivots1'!$A:$B,2,0) -> #N/A | I58: 0 | J58: =I58/8 -> 0 | K58: cd_imv_out_trz_cred_prc | L58: =J58-SUM(M58:FK58) -> 0
A59: =E59&F59 -> cd_imv_out_prcorigem | B59: Pilar III | C59: Bens Imóveis - Output | D59: 2. Campo | E59: cd_imv_out_prc | F59: origem | G59: =INDEX(Auxiliar!$B$16:$B$24,MATCH(Plano_V1!H59,Auxiliar!$C$16:$C$24,0),1) -> #N/A | H59: =VLOOKUP(A59,'Aux - pivots1'!$A:$B,2,0) -> #N/A | I59: =SUMIFS(Table1[Estimação (horas)],Table1[Tabela],Plano_V1!E59,Table1[Campo],Plano_V1!F59) -> 0 | J59: =I59/8 -> 0 | K59: cd_imv_out_trz_cred_prc | L59: =J59-SUM(M59:FK59) -> 0
A60: =E60&F60 -> cd_imv_out_prcref_date | B60: Pilar III | C60: Bens Imóveis - Output | D60: 2. Campo | E60: cd_imv_out_prc | F60: ref_date | G60: =INDEX(Auxiliar!$B$16:$B$24,MATCH(Plano_V1!H60,Auxiliar!$C$16:$C$24,0),1) -> #N/A | H60: =VLOOKUP(A60,'Aux - pivots1'!$A:$B,2,0) -> #N/A | I60: =SUMIFS(Table1[Estimação (horas)],Table1[Tabela],Plano_V1!E60,Table1[Campo],Plano_V1!F60) -> 0 | J60: =I60/8 -> 0 | K60: cd_imv_out_trz_cred_prc | L60: =J60-SUM(M60:FK60) -> 0
A61: =E61&F61 -> cd_imv_out_trz_cred_prcn.a. | B61: Pilar III | C61: Bens Imóveis - Output | D61: 1. Universo | E61: cd_imv_out_trz_cred_prc | F61: n.a. | G61: =INDEX(Auxiliar!$B$16:$B$24,MATCH(Plano_V1!H61,Auxiliar!$C$16:$C$24,0),1) -> #N/A | H61: =VLOOKUP(A61,'Aux - pivots1'!$A:$B,2,0) -> #N/A | I61: =SUMIFS(Table1[Estimação (horas)],Table1[Tabela],Plano_V1!E61,Table1[Campo],Plano_V1!F61) -> 0 | J61: =I61/8 -> 0 | K61: sem pendencia | L61: =J61-SUM(M61:FK61) -> 0
A62: =E62&F62 -> cd_imv_out_trz_cred_prccempresa | B62: Pilar III | C62: Bens Imóveis - Output | D62: 2. Campo | E62: cd_imv_out_trz_cred_prc | F62: cempresa | G62: =INDEX(Auxiliar!$B$16:$B$24,MATCH(Plano_V1!H62,Auxiliar!$C$16:$C$24,0),1) -> #N/A | H62: =VLOOKUP(A62,'Aux - pivots1'!$A:$B,2,0) -> #N/A | I62: =SUMIFS(Table1[Estimação (horas)],Table1[Tabela],Plano_V1!E62,Table1[Campo],Plano_V1!F62) -> 0 | J62: =I62/8 -> 0 | K62: sem pendencia | L62: =J62-SUM(M62:FK62) -> 0
A63: =E63&F63 -> cd_imv_out_trz_cred_prccempresp | B63: Pilar III | C63: Bens Imóveis - Output | D63: 2. Campo | E63: cd_imv_out_trz_cred_prc | F63: cempresp | G63: =INDEX(Auxiliar!$B$16:$B$24,MATCH(Plano_V1!H63,Auxiliar!$C$16:$C$24,0),1) -> #N/A | H63: =VLOOKUP(A63,'Aux - pivots1'!$A:$B,2,0) -> #N/A | I63: =SUMIFS(Table1[Estimação (horas)],Table1[Tabela],Plano_V1!E63,Table1[Campo],Plano_V1!F63) -> 0 | J63: =I63/8 -> 0 | K63: sem pendencia | L63: =J63-SUM(M63:FK63) -> 0
A64: =E64&F64 -> cd_imv_out_trz_cred_prcckbalcao | B64: Pilar III | C64: Bens Imóveis - Output | D64: 2. Campo | E64: cd_imv_out_trz_cred_prc | F64: ckbalcao | G64: =INDEX(Auxiliar!$B$16:$B$24,MATCH(Plano_V1!H64,Auxiliar!$C$16:$C$24,0),1) -> #N/A | H64: =VLOOKUP(A64,'Aux - pivots1'!$A:$B,2,0) -> #N/A | I64: =SUMIFS(Table1[Estimação (horas)],Table1[Tabela],Plano_V1!E64,Table1[Campo],Plano_V1!F64) -> 0 | J64: =I64/8 -> 0 | K64: sem pendencia | L64: =J64-SUM(M64:FK64) -> 0
A65: =E65&F65 -> cd_imv_out_trz_cred_prcckbalres | B65: Pilar III | C65: Bens Imóveis - Output | D65: 2. Campo | E65: cd_imv_out_trz_cred_prc | F65: ckbalres | G65: =INDEX(Auxiliar!$B$16:$B$24,MATCH(Plano_V1!H65,Auxiliar!$C$16:$C$24,0),1) -> #N/A | H65: =VLOOKUP(A65,'Aux - pivots1'!$A:$B,2,0) -> #N/A | I65: =SUMIFS(Table1[Estimação (horas)],Table1[Tabela],Plano_V1!E65,Table1[Campo],Plano_V1!F65) -> 0 | J65: =I65/8 -> 0 | K65: sem pendencia | L65: =J65-SUM(M65:FK65) -> 0
A66: =E66&F66 -> cd_imv_out_trz_cred_prcckctares | B66: Pilar III | C66: Bens Imóveis - Output | D66: 2. Campo | E66: cd_imv_out_trz_cred_prc | F66: ckctares | G66: =INDEX(Auxiliar!$B$16:$B$24,MATCH(Plano_V1!H66,Auxiliar!$C$16:$C$24,0),1) -> #N/A | H66: =VLOOKUP(A66,'Aux - pivots1'!$A:$B,2,0) -> #N/A | I66: =SUMIFS(Table1[Estimação (horas)],Table1[Tabela],Plano_V1!E66,Table1[Campo],Plano_V1!F66) -> 0 | J66: =I66/8 -> 0 | K66: sem pendencia | L66: =J66-SUM(M66:FK66) -> 0
A67: =E67&F67 -> cd_imv_out_trz_cred_prccknumcta | B67: Pilar III | C67: Bens Imóveis - Output | D67: 2. Campo | E67: cd_imv_out_trz_cred_prc | F67: cknumcta | G67: =INDEX(Auxiliar!$B$16:$B$24,MATCH(Plano_V1!H67,Auxiliar!$C$16:$C$24,0),1) -> #N/A | H67: =VLOOKUP(A67,'Aux - pivots1'!$A:$B,2,0) -> #N/A | I67: =SUMIFS(Table1[Estimação (horas)],Table1[Tabela],Plano_V1!E67,Table1[Campo],Plano_V1!F67) -> 0 | J67: =I67/8 -> 0 | K67: sem pendencia | L67: =J67-SUM(M67:FK67) -> 0
A68: =E68&F68 -> cd_imv_out_trz_cred_prcckrefresp | B68: Pilar III | C68: Bens Imóveis - Output | D68: 2. Campo | E68: cd_imv_out_trz_cred_prc | F68: ckrefresp | G68: =INDEX(Auxiliar!$B$16:$B$24,MATCH(Plano_V1!H68,Auxiliar!$C$16:$C$24,0),1) -> #N/A | H68: =VLOOKUP(A68,'Aux - pivots1'!$A:$B,2,0) -> #N/A | I68: =SUMIFS(Table1[Estimação (horas)],Table1[Tabela],Plano_V1!E68,Table1[Campo],Plano_V1!F68) -> 0 | J68: =I68/8 -> 0 | K68: sem pendencia | L68: =J68-SUM(M68:FK68) -> 0
A69: =E69&F69 -> cd_imv_out_trz_cred_prccod_fnld | B69: Pilar III | C69: Bens Imóveis - Output | D69: 2. Campo | E69: cd_imv_out_trz_cred_prc | F69: cod_fnld | G69: =INDEX(Auxiliar!$B$16:$B$24,MATCH(Plano_V1!H69,Auxiliar!$C$16:$C$24,0),1) -> #N/A | H69: =VLOOKUP(A69,'Aux - pivots1'!$A:$B,2,0) -> #N/A | I69: =SUMIFS(Table1[Estimação (horas)],Table1[Tabela],Plano_V1!E69,Table1[Campo],Plano_V1!F69) -> 0 | J69: =I69/8 -> 0 | K69: sem pendencia | L69: =J69-SUM(M69:FK69) -> 0
A70: =E70&F70 -> cd_imv_out_trz_cred_prccod_ocupacao | B70: Pilar III | C70: Bens Imóveis - Output | D70: 2. Campo | E70: cd_imv_out_trz_cred_prc | F70: cod_ocupacao | G70: =INDEX(Auxiliar!$B$16:$B$24,MATCH(Plano_V1!H70,Auxiliar!$C$16:$C$24,0),1) -> #N/A | H70: =VLOOKUP(A70,'Aux - pivots1'!$A:$B,2,0) -> #N/A | I70: =SUMIFS(Table1[Estimação (horas)],Table1[Tabela],Plano_V1!E70,Table1[Campo],Plano_V1!F70) -> 0 | J70: =I70/8 -> 0 | K70: sem pendencia | L70: =J70-SUM(M70:FK70) -> 0
A71: =E71&F71 -> cd_imv_out_trz_cred_prccod_prd_resp | B71: Pilar III | C71: Bens Imóveis - Output | D71: 2. Campo | E71: cd_imv_out_trz_cred_prc | F71: cod_prd_resp | G71: =INDEX(Auxiliar!$B$16:$B$24,MATCH(Plano_V1!H71,Auxiliar!$C$16:$C$24,0),1) -> #N/A | H71: =VLOOKUP(A71,'Aux - pivots1'!$A:$B,2,0) -> #N/A | I71: =SUMIFS(Table1[Estimação (horas)],Table1[Tabela],Plano_V1!E71,Table1[Campo],Plano_V1!F71) -> 0 | J71: =I71/8 -> 0 | K71: sem pendencia | L71: =J71-SUM(M71:FK71) -> 0
A72: =E72&F72 -> cd_imv_out_trz_cred_prccod_sit | B72: Pilar III | C72: Bens Imóveis - Output | D72: 2. Campo | E72: cd_imv_out_trz_cred_prc | F72: cod_sit | G72: =INDEX(Auxiliar!$B$16:$B$24,MATCH(Plano_V1!H72,Auxiliar!$C$16:$C$24,0),1) -> #N/A | H72: =VLOOKUP(A72,'Aux - pivots1'!$A:$B,2,0) -> #N/A | I72: 0 | J72: =I72/8 -> 0 | K72: sem pendencia | L72: =J72-SUM(M72:FK72) -> 0
A73: =E73&F73 -> cd_imv_out_trz_cred_prccod_sprd_resp | B73: Pilar III | C73: Bens Imóveis - Output | D73: 2. Campo | E73: cd_imv_out_trz_cred_prc | F73: cod_sprd_resp | G73: =INDEX(Auxiliar!$B$16:$B$24,MATCH(Plano_V1!H73,Auxiliar!$C$16:$C$24,0),1) -> #N/A | H73: =VLOOKUP(A73,'Aux - pivots1'!$A:$B,2,0) -> #N/A | I73: =SUMIFS(Table1[Estimação (horas)],Table1[Tabela],Plano_V1!E73,Table1[Campo],Plano_V1!F73) -> 0 | J73: =I73/8 -> 0 | K73: sem pendencia | L73: =J73-SUM(M73:FK73) -> 0
A74: =E74&F74 -> cd_imv_out_trz_cred_prccomp_id_gar | B74: Pilar III | C74: Bens Imóveis - Output | D74: 2. Campo | E74: cd_imv_out_trz_cred_prc | F74: comp_id_gar | G74: =INDEX(Auxiliar!$B$16:$B$24,MATCH(Plano_V1!H74,Auxiliar!$C$16:$C$24,0),1) -> #N/A | H74: =VLOOKUP(A74,'Aux - pivots1'!$A:$B,2,0) -> #N/A | I74: =SUMIFS(Table1[Estimação (horas)],Table1[Tabela],Plano_V1!E74,Table1[Campo],Plano_V1!F74) -> 0 | J74: =I74/8 -> 0 | K74: sem pendencia | L74: =J74-SUM(M74:FK74) -> 0
A75: =E75&F75 -> cd_imv_out_trz_cred_prcdata_fim | B75: Pilar III | C75: Bens Imóveis - Output | D75: 2. Campo | E75: cd_imv_out_trz_cred_prc | F75: data_fim | G75: =INDEX(Auxiliar!$B$16:$B$24,MATCH(Plano_V1!H75,Auxiliar!$C$16:$C$24,0),1) -> #N/A | H75: =VLOOKUP(A75,'Aux - pivots1'!$A:$B,2,0) -> #N/A | I75: =SUMIFS(Table1[Estimação (horas)],Table1[Tabela],Plano_V1!E75,Table1[Campo],Plano_V1!F75) -> 0 | J75: =I75/8 -> 0 | K75: sem pendencia | L75: =J75-SUM(M75:FK75) -> 0
A76: =E76&F76 -> cd_imv_out_trz_cred_prcdata_inicio | B76: Pilar III | C76: Bens Imóveis - Output | D76: 2. Campo | E76: cd_imv_out_trz_cred_prc | F76: data_inicio | G76: =INDEX(Auxiliar!$B$16:$B$24,MATCH(Plano_V1!H76,Auxiliar!$C$16:$C$24,0),1) -> #N/A | H76: =VLOOKUP(A76,'Aux - pivots1'!$A:$B,2,0) -> #N/A | I76: =SUMIFS(Table1[Estimação (horas)],Table1[Tabela],Plano_V1!E76,Table1[Campo],Plano_V1!F76) -> 0 | J76: =I76/8 -> 0 | K76: sem pendencia | L76: =J76-SUM(M76:FK76) -> 0
A77: =E77&F77 -> cd_imv_out_trz_cred_prcdata_vcmt | B77: Pilar III | C77: Bens Imóveis - Output | D77: 2. Campo | E77: cd_imv_out_trz_cred_prc | F77: data_vcmt | G77: =INDEX(Auxiliar!$B$16:$B$24,MATCH(Plano_V1!H77,Auxiliar!$C$16:$C$24,0),1) -> #N/A | H77: =VLOOKUP(A77,'Aux - pivots1'!$A:$B,2,0) -> #N/A | I77: =SUMIFS(Table1[Estimação (horas)],Table1[Tabela],Plano_V1!E77,Table1[Campo],Plano_V1!F77) -> 0 | J77: =I77/8 -> 0 | K77: sem pendencia | L77: =J77-SUM(M77:FK77) -> 0
A78: =E78&F78 -> cd_imv_out_trz_cred_prcidetgar | B78: Pilar III | C78: Bens Imóveis - Output | D78: 2. Campo | E78: cd_imv_out_trz_cred_prc | F78: idetgar | G78: =INDEX(Auxiliar!$B$16:$B$24,MATCH(Plano_V1!H78,Auxiliar!$C$16:$C$24,0),1) -> #N/A | H78: =VLOOKUP(A78,'Aux - pivots1'!$A:$B,2,0) -> #N/A | I78: 0 | J78: =I78/8 -> 0 | K78: sem pendencia | L78: =J78-SUM(M78:FK78) -> 0
A79: =E79&F79 -> cd_imv_out_trz_cred_prcnum_prop | B79: Pilar III | C79: Bens Imóveis - Output | D79: 2. Campo | E79: cd_imv_out_trz_cred_prc | F79: num_prop | G79: =INDEX(Auxiliar!$B$16:$B$24,MATCH(Plano_V1!H79,Auxiliar!$C$16:$C$24,0),1) -> #N/A | H79: =VLOOKUP(A79,'Aux - pivots1'!$A:$B,2,0) -> #N/A | I79: 0 | J79: =I79/8 -> 0 | K79: sem pendencia | L79: =J79-SUM(M79:FK79) -> 0
A80: =E80&F80 -> cd_imv_out_trz_cred_prcorigem | B80: Pilar III | C80: Bens Imóveis - Output | D80: 2. Campo | E80: cd_imv_out_trz_cred_prc | F80: origem | G80: =INDEX(Auxiliar!$B$16:$B$24,MATCH(Plano_V1!H80,Auxiliar!$C$16:$C$24,0),1) -> #N/A | H80: =VLOOKUP(A80,'Aux - pivots1'!$A:$B,2,0) -> #N/A | I80: =SUMIFS(Table1[Estimação (horas)],Table1[Tabela],Plano_V1!E80,Table1[Campo],Plano_V1!F80) -> 0 | J80: =I80/8 -> 0 | K80: sem pendencia | L80: =J80-SUM(M80:FK80) -> 0
A81: =E81&F81 -> cd_imv_out_trz_cred_prcref_date | B81: Pilar III | C81: Bens Imóveis - Output | D81: 2. Campo | E81: cd_imv_out_trz_cred_prc | F81: ref_date | G81: =INDEX(Auxiliar!$B$16:$B$24,MATCH(Plano_V1!H81,Auxiliar!$C$16:$C$24,0),1) -> #N/A | H81: =VLOOKUP(A81,'Aux - pivots1'!$A:$B,2,0) -> #N/A | I81: =SUMIFS(Table1[Estimação (horas)],Table1[Tabela],Plano_V1!E81,Table1[Campo],Plano_V1!F81) -> 0 | J81: =I81/8 -> 0 | K81: sem pendencia | L81: =J81-SUM(M81:FK81) -> 0
A82: =E82&F82 -> cd_imv_out_trz_prc_bens_imvn.a. | B82: Pilar III | C82: Bens Imóveis - Output | D82: 1. Universo | E82: cd_imv_out_trz_prc_bens_imv | F82: n.a. | G82: =INDEX(Auxiliar!$B$16:$B$24,MATCH(Plano_V1!H82,Auxiliar!$C$16:$C$24,0),1) -> #N/A | H82: =VLOOKUP(A82,'Aux - pivots1'!$A:$B,2,0) -> #N/A | I82: =SUMIFS(Table1[Estimação (horas)],Table1[Tabela],Plano_V1!E82,Table1[Campo],Plano_V1!F82) -> 0 | J82: =I82/8 -> 0 | K82: cd_imv_out_trz_cred_prc | L82: =J82-SUM(M82:FK82) -> 0
A83: =E83&F83 -> cd_imv_out_trz_prc_bens_imvcempbem | B83: Pilar III | C83: Bens Imóveis - Output | D83: 2. Campo | E83: cd_imv_out_trz_prc_bens_imv | F83: cempbem | G83: =INDEX(Auxiliar!$B$16:$B$24,MATCH(Plano_V1!H83,Auxiliar!$C$16:$C$24,0),1) -> #N/A | H83: =VLOOKUP(A83,'Aux - pivots1'!$A:$B,2,0) -> #N/A | I83: =SUMIFS(Table1[Estimação (horas)],Table1[Tabela],Plano_V1!E83,Table1[Campo],Plano_V1!F83) -> 0 | J83: =I83/8 -> 0 | K83: cd_imv_out_trz_cred_prc | L83: =J83-SUM(M83:FK83) -> 0
A84: =E84&F84 -> cd_imv_out_trz_prc_bens_imvcempresa | B84: Pilar III | C84: Bens Imóveis - Output | D84: 2. Campo | E84: cd_imv_out_trz_prc_bens_imv | F84: cempresa | G84: =INDEX(Auxiliar!$B$16:$B$24,MATCH(Plano_V1!H84,Auxiliar!$C$16:$C$24,0),1) -> #N/A | H84: =VLOOKUP(A84,'Aux - pivots1'!$A:$B,2,0) -> #N/A | I84: =SUMIFS(Table1[Estimação (horas)],Table1[Tabela],Plano_V1!E84,Table1[Campo],Plano_V1!F84) -> 0 | J84: =I84/8 -> 0 | K84: cd_imv_out_trz_cred_prc | L84: =J84-SUM(M84:FK84) -> 0
A85: =E85&F85 -> cd_imv_out_trz_prc_bens_imvckbalbem | B85: Pilar III | C85: Bens Imóveis - Output | D85: 2. Campo | E85: cd_imv_out_trz_prc_bens_imv | F85: ckbalbem | G85: =INDEX(Auxiliar!$B$16:$B$24,MATCH(Plano_V1!H85,Auxiliar!$C$16:$C$24,0),1) -> #N/A | H85: =VLOOKUP(A85,'Aux - pivots1'!$A:$B,2,0) -> #N/A | I85: =SUMIFS(Table1[Estimação (horas)],Table1[Tabela],Plano_V1!E85,Table1[Campo],Plano_V1!F85) -> 0 | J85: =I85/8 -> 0 | K85: cd_imv_out_trz_cred_prc | L85: =J85-SUM(M85:FK85) -> 0
A86: =E86&F86 -> cd_imv_out_trz_prc_bens_imvckbalcao | B86: Pilar III | C86: Bens Imóveis - Output | D86: 2. Campo | E86: cd_imv_out_trz_prc_bens_imv | F86: ckbalcao | G86: =INDEX(Auxiliar!$B$16:$B$24,MATCH(Plano_V1!H86,Auxiliar!$C$16:$C$24,0),1) -> #N/A | H86: =VLOOKUP(A86,'Aux - pivots1'!$A:$B,2,0) -> #N/A | I86: =SUMIFS(Table1[Estimação (horas)],Table1[Tabela],Plano_V1!E86,Table1[Campo],Plano_V1!F86) -> 0 | J86: =I86/8 -> 0 | K86: cd_imv_out_trz_cred_prc | L86: =J86-SUM(M86:FK86) -> 0
A87: =E87&F87 -> cd_imv_out_trz_prc_bens_imvckctabem | B87: Pilar III | C87: Bens Imóveis - Output | D87: 2. Campo | E87: cd_imv_out_trz_prc_bens_imv | F87: ckctabem | G87: =INDEX(Auxiliar!$B$16:$B$24,MATCH(Plano_V1!H87,Auxiliar!$C$16:$C$24,0),1) -> #N/A | H87: =VLOOKUP(A87,'Aux - pivots1'!$A:$B,2,0) -> #N/A | I87: =SUMIFS(Table1[Estimação (horas)],Table1[Tabela],Plano_V1!E87,Table1[Campo],Plano_V1!F87) -> 0 | J87: =I87/8 -> 0 | K87: cd_imv_out_trz_cred_prc | L87: =J87-SUM(M87:FK87) -> 0
A88: =E88&F88 -> cd_imv_out_trz_prc_bens_imvcknumcta | B88: Pilar III | C88: Bens Imóveis - Output | D88: 2. Campo | E88: cd_imv_out_trz_prc_bens_imv | F88: cknumcta | G88: =INDEX(Auxiliar!$B$16:$B$24,MATCH(Plano_V1!H88,Auxiliar!$C$16:$C$24,0),1) -> #N/A | H88: =VLOOKUP(A88,'Aux - pivots1'!$A:$B,2,0) -> #N/A | I88: =SUMIFS(Table1[Estimação (horas)],Table1[Tabela],Plano_V1!E88,Table1[Campo],Plano_V1!F88) -> 0 | J88: =I88/8 -> 0 | K88: cd_imv_out_trz_cred_prc | L88: =J88-SUM(M88:FK88) -> 0
A89: =E89&F89 -> cd_imv_out_trz_prc_bens_imvckrefbem | B89: Pilar III | C89: Bens Imóveis - Output | D89: 2. Campo | E89: cd_imv_out_trz_prc_bens_imv | F89: ckrefbem | G89: =INDEX(Auxiliar!$B$16:$B$24,MATCH(Plano_V1!H89,Auxiliar!$C$16:$C$24,0),1) -> #N/A | H89: =VLOOKUP(A89,'Aux - pivots1'!$A:$B,2,0) -> #N/A | I89: =SUMIFS(Table1[Estimação (horas)],Table1[Tabela],Plano_V1!E89,Table1[Campo],Plano_V1!F89) -> 0 | J89: =I89/8 -> 0 | K89: cd_imv_out_trz_cred_prc | L89: =J89-SUM(M89:FK89) -> 0
A90: =E90&F90 -> cd_imv_out_trz_prc_bens_imvcomp_id_gar | B90: Pilar III | C90: Bens Imóveis - Output | D90: 2. Campo | E90: cd_imv_out_trz_prc_bens_imv | F90: comp_id_gar | G90: =INDEX(Auxiliar!$B$16:$B$24,MATCH(Plano_V1!H90,Auxiliar!$C$16:$C$24,0),1) -> #N/A | H90: =VLOOKUP(A90,'Aux - pivots1'!$A:$B,2,0) -> #N/A | I90: =SUMIFS(Table1[Estimação (horas)],Table1[Tabela],Plano_V1!E90,Table1[Campo],Plano_V1!F90) -> 0 | J90: =I90/8 -> 0 | K90: cd_imv_out_trz_cred_prc | L90: =J90-SUM(M90:FK90) -> 0
A91: =E91&F91 -> cd_imv_out_trz_prc_bens_imvdata_assc | B91: Pilar III | C91: Bens Imóveis - Output | D91: 2. Campo | E91: cd_imv_out_trz_prc_bens_imv | F91: data_assc | G91: =INDEX(Auxiliar!$B$16:$B$24,MATCH(Plano_V1!H91,Auxiliar!$C$16:$C$24,0),1) -> #N/A | H91: =VLOOKUP(A91,'Aux - pivots1'!$A:$B,2,0) -> #N/A | I91: 0 | J91: =I91/8 -> 0 | K91: cd_imv_out_trz_cred_prc | L91: =J91-SUM(M91:FK91) -> 0
A92: =E92&F92 -> cd_imv_out_trz_prc_bens_imvflg_adj | B92: Pilar III | C92: Bens Imóveis - Output | D92: 2. Campo | E92: cd_imv_out_trz_prc_bens_imv | F92: flg_adj | G92: =INDEX(Auxiliar!$B$16:$B$24,MATCH(Plano_V1!H92,Auxiliar!$C$16:$C$24,0),1) -> #N/A | H92: =VLOOKUP(A92,'Aux - pivots1'!$A:$B,2,0) -> #N/A | I92: =SUMIFS(Table1[Estimação (horas)],Table1[Tabela],Plano_V1!E92,Table1[Campo],Plano_V1!F92) -> 0 | J92: =I92/8 -> 0 | K92: cd_imv_out_trz_cred_prc | L92: =J92-SUM(M92:FK92) -> 0
A93: =E93&F93 -> cd_imv_out_trz_prc_bens_imvflg_col | B93: Pilar III | C93: Bens Imóveis - Output | D93: 2. Campo | E93: cd_imv_out_trz_prc_bens_imv | F93: flg_col | G93: =INDEX(Auxiliar!$B$16:$B$24,MATCH(Plano_V1!H93,Auxiliar!$C$16:$C$24,0),1) -> #N/A | H93: =VLOOKUP(A93,'Aux - pivots1'!$A:$B,2,0) -> #N/A | I93: =SUMIFS(Table1[Estimação (horas)],Table1[Tabela],Plano_V1!E93,Table1[Campo],Plano_V1!F93) -> 0 | J93: =I93/8 -> 0 | K93: cd_imv_out_trz_cred_prc | L93: =J93-SUM(M93:FK93) -> 0
A94: =E94&F94 -> cd_imv_out_trz_prc_bens_imvflg_fin | B94: Pilar III | C94: Bens Imóveis - Output | D94: 2. Campo | E94: cd_imv_out_trz_prc_bens_imv | F94: flg_fin | G94: =INDEX(Auxiliar!$B$16:$B$24,MATCH(Plano_V1!H94,Auxiliar!$C$16:$C$24,0),1) -> #N/A | H94: =VLOOKUP(A94,'Aux - pivots1'!$A:$B,2,0) -> #N/A | I94: =SUMIFS(Table1[Estimação (horas)],Table1[Tabela],Plano_V1!E94,Table1[Campo],Plano_V1!F94) -> 0 | J94: =I94/8 -> 0 | K94: cd_imv_out_trz_cred_prc | L94: =J94-SUM(M94:FK94) -> 0
A95: =E95&F95 -> cd_imv_out_trz_prc_bens_imvflg_pro | B95: Pilar III | C95: Bens Imóveis - Output | D95: 2. Campo | E95: cd_imv_out_trz_prc_bens_imv | F95: flg_pro | G95: =INDEX(Auxiliar!$B$16:$B$24,MATCH(Plano_V1!H95,Auxiliar!$C$16:$C$24,0),1) -> #N/A | H95: =VLOOKUP(A95,'Aux - pivots1'!$A:$B,2,0) -> #N/A | I95: =SUMIFS(Table1[Estimação (horas)],Table1[Tabela],Plano_V1!E95,Table1[Campo],Plano_V1!F95) -> 0 | J95: =I95/8 -> 0 | K95: cd_imv_out_trz_cred_prc | L95: =J95-SUM(M95:FK95) -> 0
A96: =E96&F96 -> cd_imv_out_trz_prc_bens_imvorigem | B96: Pilar III | C96: Bens Imóveis - Output | D96: 2. Campo | E96: cd_imv_out_trz_prc_bens_imv | F96: origem | G96: =INDEX(Auxiliar!$B$16:$B$24,MATCH(Plano_V1!H96,Auxiliar!$C$16:$C$24,0),1) -> #N/A | H96: =VLOOKUP(A96,'Aux - pivots1'!$A:$B,2,0) -> #N/A | I96: =SUMIFS(Table1[Estimação (horas)],Table1[Tabela],Plano_V1!E96,Table1[Campo],Plano_V1!F96) -> 0 | J96: =I96/8 -> 0 | K96: cd_imv_out_trz_cred_prc | L96: =J96-SUM(M96:FK96) -> 0
A97: =E97&F97 -> cd_imv_out_trz_prc_bens_imvref_date | B97: Pilar III | C97: Bens Imóveis - Output | D97: 2. Campo | E97: cd_imv_out_trz_prc_bens_imv | F97: ref_date | G97: =INDEX(Auxiliar!$B$16:$B$24,MATCH(Plano_V1!H97,Auxiliar!$C$16:$C$24,0),1) -> #N/A | H97: =VLOOKUP(A97,'Aux - pivots1'!$A:$B,2,0) -> #N/A | I97: =SUMIFS(Table1[Estimação (horas)],Table1[Tabela],Plano_V1!E97,Table1[Campo],Plano_V1!F97) -> 0 | J97: =I97/8 -> 0 | K97: cd_imv_out_trz_cred_prc | L97: =J97-SUM(M97:FK97) -> 0
A98: =E98&F98 -> cd_imv_out_bensn.a. | B98: Pilar III | C98: Bens Imóveis - Output | D98: 1. Universo | E98: cd_imv_out_bens | F98: n.a. | G98: =INDEX(Auxiliar!$B$16:$B$24,MATCH(Plano_V1!H98,Auxiliar!$C$16:$C$24,0),1) -> #N/A | H98: =VLOOKUP(A98,'Aux - pivots1'!$A:$B,2,0) -> #N/A | I98: =SUMIFS(Table1[Estimação (horas)],Table1[Tabela],Plano_V1!E98,Table1[Campo],Plano_V1!F98) -> 0 | J98: =I98/8 -> 0 | K98: cd_imv_out_trz_prc_bens_imv ; cd_imv_out_prc ; cd_imv_out_trz_cred_prc | L98: =J98-SUM(M98:FK98) -> 0
A99: =E99&F99 -> cd_imv_out_bensano_construcao | B99: Pilar III | C99: Bens Imóveis - Output | D99: 2. Campo | E99: cd_imv_out_bens | F99: ano_construcao | G99: =INDEX(Auxiliar!$B$16:$B$24,MATCH(Plano_V1!H99,Auxiliar!$C$16:$C$24,0),1) -> #N/A | H99: =VLOOKUP(A99,'Aux - pivots1'!$A:$B,2,0) -> #N/A | I99: 0 | J99: =I99/8 -> 0 | K99: cd_imv_out_trz_prc_bens_imv ; cd_imv_out_prc ; cd_imv_out_trz_cred_prc | L99: =J99-SUM(M99:FK99) -> 0
A100: =E100&F100 -> cd_imv_out_bensarea_util | B100: Pilar III | C100: Bens Imóveis - Output | D100: 2. Campo | E100: cd_imv_out_bens | F100: area_util | G100: =INDEX(Auxiliar!$B$16:$B$24,MATCH(Plano_V1!H100,Auxiliar!$C$16:$C$24,0),1) -> #N/A | H100: =VLOOKUP(A100,'Aux - pivots1'!$A:$B,2,0) -> #N/A | I100: =SUMIFS(Table1[Estimação (horas)],Table1[Tabela],Plano_V1!E100,Table1[Campo],Plano_V1!F100) -> 0 | J100: =I100/8 -> 0 | K100: cd_imv_out_trz_prc_bens_imv ; cd_imv_out_prc ; cd_imv_out_trz_cred_prc | L100: =J100-SUM(M100:FK100) -> 0
A101: =E101&F101 -> cd_imv_out_benscempbem | B101: Pilar III | C101: Bens Imóveis - Output | D101: 2. Campo | E101: cd_imv_out_bens | F101: cempbem | G101: =INDEX(Auxiliar!$B$16:$B$24,MATCH(Plano_V1!H101,Auxiliar!$C$16:$C$24,0),1) -> #N/A | H101: =VLOOKUP(A101,'Aux - pivots1'!$A:$B,2,0) -> #N/A | I101: =SUMIFS(Table1[Estimação (horas)],Table1[Tabela],Plano_V1!E101,Table1[Campo],Plano_V1!F101) -> 0 | J101: =I101/8 -> 0 | K101: cd_imv_out_trz_prc_bens_imv ; cd_imv_out_prc ; cd_imv_out_trz_cred_prc | L101: =J101-SUM(M101:FK101) -> 0
A102: =E102&F102 -> cd_imv_out_bensckbalbem | B102: Pilar III | C102: Bens Imóveis - Output | D102: 2. Campo | E102: cd_imv_out_bens | F102: ckbalbem | G102: =INDEX(Auxiliar!$B$16:$B$24,MATCH(Plano_V1!H102,Auxiliar!$C$16:$C$24,0),1) -> #N/A | H102: =VLOOKUP(A102,'Aux - pivots1'!$A:$B,2,0) -> #N/A | I102: =SUMIFS(Table1[Estimação (horas)],Table1[Tabela],Plano_V1!E102,Table1[Campo],Plano_V1!F102) -> 0 | J102: =I102/8 -> 0 | K102: cd_imv_out_trz_prc_bens_imv ; cd_imv_out_prc ; cd_imv_out_trz_cred_prc | L102: =J102-SUM(M102:FK102) -> 0
A103: =E103&F103 -> cd_imv_out_bensckctabem | B103: Pilar III | C103: Bens Imóveis - Output | D103: 2. Campo | E103: cd_imv_out_bens | F103: ckctabem | G103: =INDEX(Auxiliar!$B$16:$B$24,MATCH(Plano_V1!H103,Auxiliar!$C$16:$C$24,0),1) -> #N/A | H103: =VLOOKUP(A103,'Aux - pivots1'!$A:$B,2,0) -> #N/A | I103: =SUMIFS(Table1[Estimação (horas)],Table1[Tabela],Plano_V1!E103,Table1[Campo],Plano_V1!F103) -> 0 | J103: =I103/8 -> 0 | K103: cd_imv_out_trz_prc_bens_imv ; cd_imv_out_prc ; cd_imv_out_trz_cred_prc | L103: =J103-SUM(M103:FK103) -> 0
A104: =E104&F104 -> cd_imv_out_bensckrefbem | B104: Pilar III | C104: Bens Imóveis - Output | D104: 2. Campo | E104: cd_imv_out_bens | F104: ckrefbem | G104: =INDEX(Auxiliar!$B$16:$B$24,MATCH(Plano_V1!H104,Auxiliar!$C$16:$C$24,0),1) -> #N/A | H104: =VLOOKUP(A104,'Aux - pivots1'!$A:$B,2,0) -> #N/A | I104: =SUMIFS(Table1[Estimação (horas)],Table1[Tabela],Plano_V1!E104,Table1[Campo],Plano_V1!F104) -> 0 | J104: =I104/8 -> 0 | K104: cd_imv_out_trz_prc_bens_imv ; cd_imv_out_prc ; cd_imv_out_trz_cred_prc | L104: =J104-SUM(M104:FK104) -> 0
A105: =E105&F105 -> cd_imv_out_benscod_art_matr | B105: Pilar III | C105: Bens Imóveis - Output | D105: 2. Campo | E105: cd_imv_out_bens | F105: cod_art_matr | G105: =INDEX(Auxiliar!$B$16:$B$24,MATCH(Plano_V1!H105,Auxiliar!$C$16:$C$24,0),1) -> #N/A | H105: =VLOOKUP(A105,'Aux - pivots1'!$A:$B,2,0) -> #N/A | I105: =SUMIFS(Table1[Estimação (horas)],Table1[Tabela],Plano_V1!E105,Table1[Campo],Plano_V1!F105) -> 0 | J105: =I105/8 -> 0 | K105: cd_imv_out_trz_prc_bens_imv ; cd_imv_out_prc ; cd_imv_out_trz_cred_prc | L105: =J105-SUM(M105:FK105) -> 0
A106: =E106&F106 -> cd_imv_out_benscod_avl | B106: Pilar III | C106: Bens Imóveis - Output | D106: 2. Campo | E106: cd_imv_out_bens | F106: cod_avl | G106: =INDEX(Auxiliar!$B$16:$B$24,MATCH(Plano_V1!H106,Auxiliar!$C$16:$C$24,0),1) -> #N/A | H106: =VLOOKUP(A106,'Aux - pivots1'!$A:$B,2,0) -> #N/A | I106: =SUMIFS(Table1[Estimação (horas)],Table1[Tabela],Plano_V1!E106,Table1[Campo],Plano_V1!F106) -> 0 | J106: =I106/8 -> 0 | K106: cd_imv_out_trz_prc_bens_imv ; cd_imv_out_prc ; cd_imv_out_trz_cred_prc | L106: =J106-SUM(M106:FK106) -> 0
A107: =E107&F107 -> cd_imv_out_benscod_bem | B107: Pilar III | C107: Bens Imóveis - Output | D107: 2. Campo | E107: cd_imv_out_bens | F107: cod_bem | G107: =INDEX(Auxiliar!$B$16:$B$24,MATCH(Plano_V1!H107,Auxiliar!$C$16:$C$24,0),1) -> #N/A | H107: =VLOOKUP(A107,'Aux - pivots1'!$A:$B,2,0) -> #N/A | I107: 0 | J107: =I107/8 -> 0 | K107: cd_imv_out_trz_prc_bens_imv ; cd_imv_out_prc ; cd_imv_out_trz_cred_prc | L107: =J107-SUM(M107:FK107) -> 0
A108: =E108&F108 -> cd_imv_out_benscod_disconf | B108: Pilar III | C108: Bens Imóveis - Output | D108: 2. Campo | E108: cd_imv_out_bens | F108: cod_disconf | G108: =INDEX(Auxiliar!$B$16:$B$24,MATCH(Plano_V1!H108,Auxiliar!$C$16:$C$24,0),1) -> #N/A | H108: =VLOOKUP(A108,'Aux - pivots1'!$A:$B,2,0) -> #N/A | I108: =SUMIFS(Table1[Estimação (horas)],Table1[Tabela],Plano_V1!E108,Table1[Campo],Plano_V1!F108) -> 0 | J108: =I108/8 -> 0 | K108: cd_imv_out_trz_prc_bens_imv ; cd_imv_out_prc ; cd_imv_out_trz_cred_prc | L108: =J108-SUM(M108:FK108) -> 0
A109: =E109&F109 -> cd_imv_out_benscod_fin_bem | B109: Pilar III | C109: Bens Imóveis - Output | D109: 2. Campo | E109: cd_imv_out_bens | F109: cod_fin_bem | G109: =INDEX(Auxiliar!$B$16:$B$24,MATCH(Plano_V1!H109,Auxiliar!$C$16:$C$24,0),1) -> #N/A | H109: =VLOOKUP(A109,'Aux - pivots1'!$A:$B,2,0) -> #N/A | I109: =SUMIFS(Table1[Estimação (horas)],Table1[Tabela],Plano_V1!E109,Table1[Campo],Plano_V1!F109) -> 0 | J109: =I109/8 -> 0 | K109: cd_imv_out_trz_prc_bens_imv ; cd_imv_out_prc ; cd_imv_out_trz_cred_prc | L109: =J109-SUM(M109:FK109) -> 0
...

Sheet 1. Status Resumo FY24
B6: 1. Sumário Executivo |28 de março a 4 de abril
B8: 1 | AG8: 1
C9: Resumo de entregas de Especificações | P9: Detalhe Packages planeados | X9: Highlights
E10: 0 | H10: 1 | L10: Package 20 | X10: Resumo semana atual: 1. Modelo de Bens Imóveis: - Foi concluída a especificação do campo ep_score. 2. Modelo Verde: - Entrega da tabela tabela de output de Macação Verde do Modelo Verde (03/04); - Continuação dos testes aos 13 campos da tabela de output de Macação Verde do Modelo Verde. 3. Loan Tape: Dos 13 campos com incidências da semana passada: - 2 foram concluídos; - 4 foram testados e foram encontradas incidências; - 7 encontram-se em testes com previsão de conclusão na próxima 2f (07/04). Denote-se que estes campos são depedentes do Modelo Verde e foram estrategicamente planeados de modo a considerar a entrega da tabela de output de Marcação Verde (entregue por IT no dia 03/04) e o reprocessamento de dados mais recente das restantes tabelas do Modelo Verde. Dos 9 campos entregues por IT na presente semana: - 2 foram concluídos; - 6 foram testados e foram encontradas incidências (incidências relacionadas com os valores válidos a permitir no campo); - 1 encontra-se em teste com previsão de conclusão na próxima 2f (07/04). Denote-se que este campo foi alvo do planeamento supramencionado do Modelo Verde. Semana Seguinte: 1. Modelo Bens Imóveis: - Em virtude do e-mail da Corporação acerca dos consumos (ep_score) rever a necessidade ou não de re-especificação deste campo. 2. Modelo Verde: - Continuar os testes da tabela de output de Marcação Verde. 3. Loan Tape - Testar universos; - Re-testar os campos reportados com incidências.
C11: Âmbito | E11: Entregas Semana Anterior | H11: Entregas Semana Atual | L11: Entregas Semana Seguinte | Q11: Dt. Prev. | R11: Req. FY25 | T11: Req. FY25 (atualiz.) | V11: Status
E12: Planeado | F12: Real | G12: ∆ | H12: Semana Ant. | I12: Planeado | J12: Real | K12: ∆ | L12: Semana Ant. | M12: Planeado | N12: Total | O12: 1 | P12: Package 1 | Q12: 27/jan | R12: 20 | T12: =+COUNTIFS('2. Status Detalhe Campos FY24'!$C:$C,"*Pilar*",'2. Status Detalhe Campos FY24'!$J:$J,"*"&O12&"*",'2. Status Detalhe Campos FY24'!Y:Y,"*Novo Plano*") -> 20 | V12: OK
C13: Modelo de Bens Imóveis | E13: 0 | F13: 0 | G13: 0 | H13: 0 | I13: 1 | J13: 1 | K13: =J13-(I13+H13) -> 0 | L13: =+IF(K13<0,-K13,0) -> 0 | M13: 0 | N13: =+M13+L13 -> 0 | O13: 2 | P13: Package 2 | Q13: 4/fev | R13: 15 | T13: =+COUNTIFS('2. Status Detalhe Campos FY24'!$C:$C,"*Pilar*",'2. Status Detalhe Campos FY24'!$J:$J,"*"&O13&"*",'2. Status Detalhe Campos FY24'!Y:Y,"*Novo Plano*") -> 14 | V13: OK
C14: Requisitos FY24 | E14: 0 | F14: 1 | G14: 0 | H14: 0 | I14: 1 | J14: 1 | K14: =J14-(I14+H14) -> 0 | L14: =+IF(K14<0,-K14,0) -> 0 | M14: 0 | N14: 0 | O14: 3 | P14: Package 3 | Q14: 5/fev | R14: 14 | T14: =+COUNTIFS('2. Status Detalhe Campos FY24'!$C:$C,"*Pilar*",'2. Status Detalhe Campos FY24'!$J:$J,"*"&O14&"*",'2. Status Detalhe Campos FY24'!Y:Y,"*Novo Plano*") -> 16 | V14: OK
C15: Novos Requisitos FY25 | E15: 0 | F15: 0 | G15: 0 | H15: 0 | I15: 0 | J15: 0 | K15: =J15-(I15+H15) -> 0 | L15: =+IF(K15<0,-K15,0) -> 0 | M15: =+COUNTIFS('2. Status Detalhe Campos FY24'!$C:$C,"*Bens Imóveis*",'2. Status Detalhe Campos FY24'!$J:$J,"*"&$L$10&"*",'2. Status Detalhe Campos FY24'!Y:Y,"*Novo Plano*") -> 0 | N15: =+M15+L15 -> 0 | O15: 4 | P15: Package 4 | Q15: 11/fev | R15: 13 | T15: =+COUNTIFS('2. Status Detalhe Campos FY24'!$C:$C,"*Pilar*",'2. Status Detalhe Campos FY24'!$J:$J,"*"&O15&"*",'2. Status Detalhe Campos FY24'!Y:Y,"*Novo Plano*") -> 14 | V15: OK
C16: Modelo Verde | E16: 0 | F16: 0 | G16: 0 | H16: 0 | I16: 0 | J16: 0 | K16: =J16-(I16+H16) -> 0 | L16: =+IF(K16<0,-K16,0) -> 0 | M16: 0 | N16: =+M16+L16 -> 0 | O16: 5 | P16: Package 5 | Q16: 17/fev | R16: 6 | T16: =+COUNTIFS('2. Status Detalhe Campos FY24'!$C:$C,"*Pilar*",'2. Status Detalhe Campos FY24'!$J:$J,"*"&O16&"*",'2. Status Detalhe Campos FY24'!Y:Y,"*Novo Plano*") -> 7 | V16: OK
C17: Requisitos FY24 | E17: 0 | F17: 0 | G17: 0 | H17: 0 | I17: 0 | J17: 0 | K17: =J17-(I17+H17) -> 0 | L17: =+IF(K17<0,-K17,0) -> 0 | M17: 0 | N17: =+M17+L17 -> 0 | P17: Total | R17: =+SUM(R12:S16) -> 68 | T17: =+SUM(T12:T16) -> 71
C18: Novos Requisitos FY25 | E18: 0 | F18: 0 | G18: 0 | H18: 0 | I18: 0 | J18: 0 | K18: =J18-(I18+H18) -> 0 | L18: =+IF(K18<0,-K18,0) -> 0 | M18: =+COUNTIFS('2. Status Detalhe Campos FY24'!$C:$C,"*Verde*",'2. Status Detalhe Campos FY24'!$J:$J,"*"&$L$10&"*",'2. Status Detalhe Campos FY24'!Y:Y,"*Novo Plano*") -> 0 | N18: =+M18+L18 -> 0
C19: Loan Tape | E19: 0 | F19: 0 | G19: 0 | H19: 0 | I19: 0 | J19: 0 | K19: =J19-(I19+H19) -> 0 | L19: 0 | M19: =+COUNTIFS('2. Status Detalhe Campos FY24'!$C:$C,"*Verde*",'2. Status Detalhe Campos FY24'!$J:$J,"*"&$L$10&"*") -> 0 | N19: =+M19+L19 -> 0
C20: Requisitos FY24 | E20: 0 | F20: 0 | G20: 0 | H20: 0 | I20: 0 | J20: 0 | K20: =J20-(I20+H20) -> 0 | L20: =+IF(K20<0,-K20,0) -> 0 | M20: =+COUNTIFS('2. Status Detalhe Campos FY24'!$C:$C,"*Verde*",'2. Status Detalhe Campos FY24'!$J:$J,"*"&$L$10&"*",'2. Status Detalhe Campos FY24'!Y:Y,"*anterior*") -> 0 | N20: =+M20+L20 -> 0
C21: Novos Requisitos FY25 | E21: 0 | F21: 0 | G21: 0 | H21: 0 | I21: 0 | J21: 0 | K21: =J21-(I21+H21) -> 0 | L21: =+IF(K21<0,-K21,0) -> 0 | M21: 0 | N21: =+M21+L21 -> 0
C22: Total | E22: 0 | F22: 0 | G22: 0 | H22: 0 | I22: 1 | J22: 1 | K22: =J22-(I22+H22) -> 0 | L22: =+SUM(L13,L16,L19) -> 0 | M22: =+SUM(M13,M16,M19) -> 0 | N22: =+SUM(N13,N16,N19) -> 0
C24: Resumo de Testes
E25: 1 | I25: 1 | P25: 1000
C26: Âmbito | E26: Semana Anterior | J26: Semana Atual | P26: Semana Seguinte
E27: Planeado | F27: Com Incidên. | G27: Sem Incidên. | H27: Outros | I27: ∆ | J27: Semana Ant. | K27: Planeado | L27: Com Incidên. | M27: Sem Incidên. | N27: Outros | O27: ∆ | P27: Semana Ant. | Q27: Planeado | R27: Total
C28: Modelo de Bens Imóveis | E28: 0 | F28: 0 | G28: 0 | H28: 0 | I28: 0 | J28: 0 | K28: 0 | L28: 0 | M28: 0 | N28: 0 | O28: 0 | P28: 0 | Q28: =+COUNTIFS('2. Status Detalhe Campos FY24'!$C:$C,"*Bens Imóveis*",'2. Status Detalhe Campos FY24'!$K:$K,"*"&$P$25&"*") -> 0 | R28: =+Q28+P28 -> 0
C29: RequisItos FY24 | E29: 0 | F29: 0 | G29: 0 | H29: 0 | I29: 0 | J29: 0 | K29: 0 | L29: 0 | M29: 0 | N29: 0 | O29: 0 | P29: =+COUNTIFS('2. Status Detalhe Campos FY24'!$C:$C,"*Bens Imóveis*",'2. Status Detalhe Campos FY24'!$K:$K,"*"&$P$25&"*",'2. Status Detalhe Campos FY24'!X:X,"*anterior*") -> 0 | Q29: =+COUNTIFS('2. Status Detalhe Campos FY24'!$C:$C,"*Bens Imóveis*",'2. Status Detalhe Campos FY24'!$K:$K,"*"&$P$25&"*",'2. Status Detalhe Campos FY24'!Y:Y,"*anterior*") -> 0 | R29: =+Q29+P29 -> 0
C30: Novos Requisitos FY25 | E30: 0 | F30: 0 | G30: 0 | H30: 0 | I30: 0 | J30: 0 | K30: 0 | L30: 0 | M30: 0 | N30: 0 | O30: 0 | P30: =+COUNTIFS('2. Status Detalhe Campos FY24'!$C:$C,"*Bens Imóveis*",'2. Status Detalhe Campos FY24'!$K:$K,"*"&$P$25&"*",'2. Status Detalhe Campos FY24'!X:X,"*anterior*") -> 0 | Q30: =+COUNTIFS('2. Status Detalhe Campos FY24'!$C:$C,"*Bens Imóveis*",'2. Status Detalhe Campos FY24'!$K:$K,"*"&$P$25&"*",'2. Status Detalhe Campos FY24'!Y:Y,"*Novo Plano*") -> 0 | R30: =+Q30+P30 -> 0
C31: Modelo Verde | E31: 59 | F31: 0 | G31: 44 | H31: 13 | I31: 0 | J31: 13 | K31: 0 | L31: 0 | M31: 0 | N31: 13 | O31: 13 | P31: 13 | Q31: =+COUNTIFS('2. Status Detalhe Campos FY24'!$C:$C,"*Verde*",'2. Status Detalhe Campos FY24'!$K:$K,"*"&$P$25&"*") -> 0 | R31: =+Q31+P31 -> 13
C32: RequisItos FY24 | E32: 59 | F32: 0 | G32: 44 | H32: 13 | I32: 0 | J32: 13 | K32: 0 | L32: 0 | M32: 0 | N32: 13 | O32: 13 | P32: 13 | Q32: =+COUNTIFS('2. Status Detalhe Campos FY24'!$C:$C,"*Verde*",'2. Status Detalhe Campos FY24'!$K:$K,"*"&$P$25&"*",'2. Status Detalhe Campos FY24'!Y:Y,"*anterior*") -> 0 | R32: =+Q32+P32 -> 13
C33: Novos Requisitos FY25 | E33: 0 | F33: 0 | G33: 0 | H33: 0 | I33: 0 | J33: 0 | K33: 0 | L33: 0 | M33: 0 | N33: 0 | O33: 0 | P33: =+COUNTIFS('2. Status Detalhe Campos FY24'!$C:$C,"*Verde*",'2. Status Detalhe Campos FY24'!$K:$K,"*"&$P$25&"*",'2. Status Detalhe Campos FY24'!X:X,"*anterior*") -> 0 | Q33: =+COUNTIFS('2. Status Detalhe Campos FY24'!$C:$C,"*Verde*",'2. Status Detalhe Campos FY24'!$K:$K,"*"&$P$25&"*",'2. Status Detalhe Campos FY24'!Y:Y,"*Novo Plano*") -> 0 | R33: =+Q33+P33 -> 0
C34: Loan Tape | E34: 15 | F34: 12 | G34: 2 | H34: 1 | I34: 0 | J34: 13 | K34: 9 | L34: =4+6 -> 10 | M34: =2+2 -> 4 | N34: =7+1 -> 8 | O34: 0 | P34: =+L34 -> 10 | Q34: =+COUNTIFS('2. Status Detalhe Campos FY24'!$C:$C,"*Pilar*",'2. Status Detalhe Campos FY24'!$K:$K,"*"&$P$25&"*") -> 0 | R34: =+Q34+P34 -> 10
C35: RequisItos FY24 | E35: 8 | F35: 3 | G35: 0 | H35: 1 | I35: 0 | J35: 4 | K35: 1 | L35: =4+0 -> 4 | M35: =0+0 -> 0 | N35: =4+1 -> 5 | O35: 0 | P35: =+L35 -> 4 | Q35: =+COUNTIFS('2. Status Detalhe Campos FY24'!$C:$C,"*Pilar*",'2. Status Detalhe Campos FY24'!$K:$K,"*"&$P$25&"*",'2. Status Detalhe Campos FY24'!Y:Y,"*anterior*") -> 0 | R35: =+Q35+P35 -> 4
C36: Novos Requisitos FY25 | E36: 7 | F36: 5 | G36: 2 | H36: 0 | I36: 0 | J36: 5 | K36: 8 | L36: =0+6 -> 6 | M36: =2+2 -> 4 | N36: =3+0 -> 3 | O36: 0 | P36: =+L36 -> 6 | Q36: =+COUNTIFS('2. Status Detalhe Campos FY24'!$C:$C,"*Pilar*",'2. Status Detalhe Campos FY24'!$K:$K,"*"&$P$25&"*",'2. Status Detalhe Campos FY24'!Y:Y,"*Novo Plano*") -> 0 | R36: =+Q36+P36 -> 6
C37: Total | E37: 18 | F37: 12 | G37: 46 | H37: 14 | I37: 0 | J37: 26 | K37: 9 | L37: =+L34+L31+L28 -> 10 | M37: =+M34+M31+M28 -> 4 | N37: =+N34+N31+N28 -> 21 | O37: 0 | P37: =+SUM(P28,P31,P34) -> 23 | Q37: =+SUM(Q28,Q31,Q34) -> 0 | R37: =+SUM(R28,R31,R34) -> 23
B46: 1 | AG46: 1
B48: 1. Modelo de Bens Imóveis | G48: Bens Imóveis - Input | H48: Bens Imóveis - Output | I48: Modelo Verde - Input | J48: Modelo Verde - Output | K48: Pilar III
C51: Resumo | G51: Detalhe por Tabela | P51: Status (campos) | T51: 45744 | U51: =T51+7 -> 45751 | V51: ∆ | X51: Highlights
P52: 0. Cancelado | T52: =COUNTIFS('2. Status Detalhe Campos FY24'!$H$7:$H$740,'1. Status Resumo FY24'!$P52,'2. Status Detalhe Campos FY24'!$C$7:$C$740,'1. Status Resumo FY24'!$G$48,'2. Status Detalhe Campos FY24'!$D$7:$D$740,"2. Campo")+COUNTIFS('2. Status Detalhe Campos FY24'!$H$7:$H$740,'1. Status Resumo FY24'!$P52,'2. Status Detalhe Campos FY24'!$C$7:$C$740,'1. Status Resumo FY24'!$H$48,'2. Status Detalhe Campos FY24'!$D$7:$D$740,"2. Campo") -> 12 | U52: =COUNTIFS('2. Status Detalhe Campos FY24'!$G$7:$G$740,'1. Status Resumo FY24'!$P52,'2. Status Detalhe Campos FY24'!$C$7:$C$740,'1. Status Resumo FY24'!$G$48,'2. Status Detalhe Campos FY24'!$D$7:$D$740,"2. Campo")+COUNTIFS('2. Status Detalhe Campos FY24'!$G$7:$G$740,'1. Status Resumo FY24'!$P52,'2. Status Detalhe Campos FY24'!$C$7:$C$740,'1. Status Resumo FY24'!$H$48,'2. Status Detalhe Campos FY24'!$D$7:$D$740,"2. Campo") -> 12 | V52: =U52-T52 -> 0 | X52: 1. Tabela de certificados: - Em virtude do e-mail da Corporação acerca dos consumos (ep_score) rever a necessidade ou não de re-especificação deste campo.
P53: RequisItos FY24 | T53: =COUNTIFS('2. Status Detalhe Campos FY24'!$H$7:$H$740,'1. Status Resumo FY24'!$P52,'2. Status Detalhe Campos FY24'!$C$7:$C$740,'1. Status Resumo FY24'!$G$48,'2. Status Detalhe Campos FY24'!$D$7:$D$740,"2. Campo",'2. Status Detalhe Campos FY24'!$Y$7:$Y$740,"*Plano anterior*") +COUNTIFS('2. Status Detalhe Campos FY24'!$H$7:$H$740,'1. Status Resumo FY24'!$P52,'2. Status Detalhe Campos FY24'!$C$7:$C$740,'1. Status Resumo FY24'!$H$48,'2. Status Detalhe Campos FY24'!$D$7:$D$740,"2. Campo",'2. Status Detalhe Campos FY24'!$Y$7:$Y$740,"*Plano anterior*") -> 12 | U53: =COUNTIFS('2. Status Detalhe Campos FY24'!$G$7:$G$740,'1. Status Resumo FY24'!$P52,'2. Status Detalhe Campos FY24'!$C$7:$C$740,'1. Status Resumo FY24'!$G$48,'2. Status Detalhe Campos FY24'!$D$7:$D$740,"2. Campo",'2. Status Detalhe Campos FY24'!$Y$7:$Y$740,"*Plano anterior*") +COUNTIFS('2. Status Detalhe Campos FY24'!$G$7:$G$740,'1. Status Resumo FY24'!$P52,'2. Status Detalhe Campos FY24'!$C$7:$C$740,'1. Status Resumo FY24'!$H$48,'2. Status Detalhe Campos FY24'!$D$7:$D$740,"2. Campo",'2. Status Detalhe Campos FY24'!$Y$7:$Y$740,"*Plano anterior*") -> 12 | V53: =U53-T53 -> 0
P54: Novos Requisitos FY25 | T54: =COUNTIFS('2. Status Detalhe Campos FY24'!$H$7:$H$740,'1. Status Resumo FY24'!$P53,'2. Status Detalhe Campos FY24'!$C$7:$C$740,'1. Status Resumo FY24'!$G$48,'2. Status Detalhe Campos FY24'!$D$7:$D$740,"2. Campo",'2. Status Detalhe Campos FY24'!$Y$7:$Y$740,"*Novo Plano*") +COUNTIFS('2. Status Detalhe Campos FY24'!$H$7:$H$740,'1. Status Resumo FY24'!$P53,'2. Status Detalhe Campos FY24'!$C$7:$C$740,'1. Status Resumo FY24'!$H$48,'2. Status Detalhe Campos FY24'!$D$7:$D$740,"2. Campo",'2. Status Detalhe Campos FY24'!$Y$7:$Y$740,"*Novo Plano*") -> 0 | U54: =COUNTIFS('2. Status Detalhe Campos FY24'!$G$7:$G$740,'1. Status Resumo FY24'!$P52,'2. Status Detalhe Campos FY24'!$C$7:$C$740,'1. Status Resumo FY24'!$G$48,'2. Status Detalhe Campos FY24'!$D$7:$D$740,"2. Campo",'2. Status Detalhe Campos FY24'!$Y$7:$Y$740,"*Novo Plano*") +COUNTIFS('2. Status Detalhe Campos FY24'!$G$7:$G$740,'1. Status Resumo FY24'!$P52,'2. Status Detalhe Campos FY24'!$C$7:$C$740,'1. Status Resumo FY24'!$H$48,'2. Status Detalhe Campos FY24'!$D$7:$D$740,"2. Campo",'2. Status Detalhe Campos FY24'!$Y$7:$Y$740,"*Novo Plano*") -> 0 | V54: =U54-T54 -> 0
P55: 1. Concluído | T55: =COUNTIFS('2. Status Detalhe Campos FY24'!$H$7:$H$740,'1. Status Resumo FY24'!$P55,'2. Status Detalhe Campos FY24'!$C$7:$C$740,'1. Status Resumo FY24'!$G$48,'2. Status Detalhe Campos FY24'!$D$7:$D$740,"2. Campo")+COUNTIFS('2. Status Detalhe Campos FY24'!$H$7:$H$740,'1. Status Resumo FY24'!$P55,'2. Status Detalhe Campos FY24'!$C$7:$C$740,'1. Status Resumo FY24'!$H$48,'2. Status Detalhe Campos FY24'!$D$7:$D$740,"2. Campo") -> 195 | U55: =COUNTIFS('2. Status Detalhe Campos FY24'!$G$7:$G$740,'1. Status Resumo FY24'!$P55,'2. Status Detalhe Campos FY24'!$C$7:$C$740,'1. Status Resumo FY24'!$G$48,'2. Status Detalhe Campos FY24'!$D$7:$D$740,"2. Campo")+COUNTIFS('2. Status Detalhe Campos FY24'!$G$7:$G$740,'1. Status Resumo FY24'!$P55,'2. Status Detalhe Campos FY24'!$C$7:$C$740,'1. Status Resumo FY24'!$H$48,'2. Status Detalhe Campos FY24'!$D$7:$D$740,"2. Campo") -> 195 | V55: =U55-T55 -> 0
P56: RequisItos FY24 | T56: =COUNTIFS('2. Status Detalhe Campos FY24'!$H$7:$H$740,'1. Status Resumo FY24'!$P55,'2. Status Detalhe Campos FY24'!$C$7:$C$740,'1. Status Resumo FY24'!$G$48,'2. Status Detalhe Campos FY24'!$D$7:$D$740,"2. Campo",'2. Status Detalhe Campos FY24'!$Y$7:$Y$740,"*Plano anterior*") +COUNTIFS('2. Status Detalhe Campos FY24'!$H$7:$H$740,'1. Status Resumo FY24'!$P55,'2. Status Detalhe Campos FY24'!$C$7:$C$740,'1. Status Resumo FY24'!$H$48,'2. Status Detalhe Campos FY24'!$D$7:$D$740,"2. Campo",'2. Status Detalhe Campos FY24'!$Y$7:$Y$740,"*Plano anterior*") -> 195 | U56: =COUNTIFS('2. Status Detalhe Campos FY24'!$G$7:$G$740,'1. Status Resumo FY24'!$P55,'2. Status Detalhe Campos FY24'!$C$7:$C$740,'1. Status Resumo FY24'!$G$48,'2. Status Detalhe Campos FY24'!$D$7:$D$740,"2. Campo",'2. Status Detalhe Campos FY24'!$Y$7:$Y$740,"*Plano anterior*") +COUNTIFS('2. Status Detalhe Campos FY24'!$G$7:$G$740,'1. Status Resumo FY24'!$P55,'2. Status Detalhe Campos FY24'!$C$7:$C$740,'1. Status Resumo FY24'!$H$48,'2. Status Detalhe Campos FY24'!$D$7:$D$740,"2. Campo",'2. Status Detalhe Campos FY24'!$Y$7:$Y$740,"*Plano anterior*") -> 195 | V56: =U56-T56 -> 0
P57: Novos Requisitos FY25 | T57: =COUNTIFS('2. Status Detalhe Campos FY24'!$H$7:$H$740,'1. Status Resumo FY24'!$P56,'2. Status Detalhe Campos FY24'!$C$7:$C$740,'1. Status Resumo FY24'!$G$48,'2. Status Detalhe Campos FY24'!$D$7:$D$740,"2. Campo",'2. Status Detalhe Campos FY24'!$Y$7:$Y$740,"*Novo Plano*") +COUNTIFS('2. Status Detalhe Campos FY24'!$H$7:$H$740,'1. Status Resumo FY24'!$P56,'2. Status Detalhe Campos FY24'!$C$7:$C$740,'1. Status Resumo FY24'!$H$48,'2. Status Detalhe Campos FY24'!$D$7:$D$740,"2. Campo",'2. Status Detalhe Campos FY24'!$Y$7:$Y$740,"*Novo Plano*") -> 0 | U57: =COUNTIFS('2. Status Detalhe Campos FY24'!$G$7:$G$740,'1. Status Resumo FY24'!$P55,'2. Status Detalhe Campos FY24'!$C$7:$C$740,'1. Status Resumo FY24'!$G$48,'2. Status Detalhe Campos FY24'!$D$7:$D$740,"2. Campo",'2. Status Detalhe Campos FY24'!$Y$7:$Y$740,"*Novo Plano*") +COUNTIFS('2. Status Detalhe Campos FY24'!$G$7:$G$740,'1. Status Resumo FY24'!$P55,'2. Status Detalhe Campos FY24'!$C$7:$C$740,'1. Status Resumo FY24'!$H$48,'2. Status Detalhe Campos FY24'!$D$7:$D$740,"2. Campo",'2. Status Detalhe Campos FY24'!$Y$7:$Y$740,"*Novo Plano*") -> 0 | V57: =U57-T57 -> 0
P58: 2.1 Em Teste | T58: =COUNTIFS('2. Status Detalhe Campos FY24'!$H$7:$H$740,'1. Status Resumo FY24'!$P58,'2. Status Detalhe Campos FY24'!$C$7:$C$740,'1. Status Resumo FY24'!$G$48,'2. Status Detalhe Campos FY24'!$D$7:$D$740,"2. Campo")+COUNTIFS('2. Status Detalhe Campos FY24'!$H$7:$H$740,'1. Status Resumo FY24'!$P58,'2. Status Detalhe Campos FY24'!$C$7:$C$740,'1. Status Resumo FY24'!$H$48,'2. Status Detalhe Campos FY24'!$D$7:$D$740,"2. Campo") -> 0 | U58: =COUNTIFS('2. Status Detalhe Campos FY24'!$G$7:$G$740,'1. Status Resumo FY24'!$P58,'2. Status Detalhe Campos FY24'!$C$7:$C$740,'1. Status Resumo FY24'!$G$48,'2. Status Detalhe Campos FY24'!$D$7:$D$740,"2. Campo")+COUNTIFS('2. Status Detalhe Campos FY24'!$G$7:$G$740,'1. Status Resumo FY24'!$P58,'2. Status Detalhe Campos FY24'!$C$7:$C$740,'1. Status Resumo FY24'!$H$48,'2. Status Detalhe Campos FY24'!$D$7:$D$740,"2. Campo") -> 0 | V58: =U58-T58 -> 0
P59: RequisItos FY24 | T59: =COUNTIFS('2. Status Detalhe Campos FY24'!$H$7:$H$740,'1. Status Resumo FY24'!$P58,'2. Status Detalhe Campos FY24'!$C$7:$C$740,'1. Status Resumo FY24'!$G$48,'2. Status Detalhe Campos FY24'!$D$7:$D$740,"2. Campo",'2. Status Detalhe Campos FY24'!$Y$7:$Y$740,"*Plano anterior*") +COUNTIFS('2. Status Detalhe Campos FY24'!$H$7:$H$740,'1. Status Resumo FY24'!$P58,'2. Status Detalhe Campos FY24'!$C$7:$C$740,'1. Status Resumo FY24'!$H$48,'2. Status Detalhe Campos FY24'!$D$7:$D$740,"2. Campo",'2. Status Detalhe Campos FY24'!$Y$7:$Y$740,"*Plano anterior*") -> 0 | U59: =COUNTIFS('2. Status Detalhe Campos FY24'!$G$7:$G$740,'1. Status Resumo FY24'!$P58,'2. Status Detalhe Campos FY24'!$C$7:$C$740,'1. Status Resumo FY24'!$G$48,'2. Status Detalhe Campos FY24'!$D$7:$D$740,"2. Campo",'2. Status Detalhe Campos FY24'!$Y$7:$Y$740,"*Plano anterior*") +COUNTIFS('2. Status Detalhe Campos FY24'!$G$7:$G$740,'1. Status Resumo FY24'!$P58,'2. Status Detalhe Campos FY24'!$C$7:$C$740,'1. Status Resumo FY24'!$H$48,'2. Status Detalhe Campos FY24'!$D$7:$D$740,"2. Campo",'2. Status Detalhe Campos FY24'!$Y$7:$Y$740,"*Plano anterior*") -> 0 | V59: =U59-T59 -> 0
P60: Novos Requisitos FY25 | T60: =COUNTIFS('2. Status Detalhe Campos FY24'!$H$7:$H$740,'1. Status Resumo FY24'!$P59,'2. Status Detalhe Campos FY24'!$C$7:$C$740,'1. Status Resumo FY24'!$G$48,'2. Status Detalhe Campos FY24'!$D$7:$D$740,"2. Campo",'2. Status Detalhe Campos FY24'!$Y$7:$Y$740,"*Novo Plano*") +COUNTIFS('2. Status Detalhe Campos FY24'!$H$7:$H$740,'1. Status Resumo FY24'!$P59,'2. Status Detalhe Campos FY24'!$C$7:$C$740,'1. Status Resumo FY24'!$H$48,'2. Status Detalhe Campos FY24'!$D$7:$D$740,"2. Campo",'2. Status Detalhe Campos FY24'!$Y$7:$Y$740,"*Novo Plano*") -> 0 | U60: =COUNTIFS('2. Status Detalhe Campos FY24'!$G$7:$G$740,'1. Status Resumo FY24'!$P58,'2. Status Detalhe Campos FY24'!$C$7:$C$740,'1. Status Resumo FY24'!$G$48,'2. Status Detalhe Campos FY24'!$D$7:$D$740,"2. Campo",'2. Status Detalhe Campos FY24'!$Y$7:$Y$740,"*Novo Plano*") +COUNTIFS('2. Status Detalhe Campos FY24'!$G$7:$G$740,'1. Status Resumo FY24'!$P58,'2. Status Detalhe Campos FY24'!$C$7:$C$740,'1. Status Resumo FY24'!$H$48,'2. Status Detalhe Campos FY24'!$D$7:$D$740,"2. Campo",'2. Status Detalhe Campos FY24'!$Y$7:$Y$740,"*Novo Plano*") -> 0 | V60: =U60-T60 -> 0
D61: ="# "&U79 -> # 208 | P61: 2.2 Em especificação | T61: =COUNTIFS('2. Status Detalhe Campos FY24'!$H$7:$H$740,'1. Status Resumo FY24'!$P61,'2. Status Detalhe Campos FY24'!$C$7:$C$740,'1. Status Resumo FY24'!$G$48,'2. Status Detalhe Campos FY24'!$D$7:$D$740,"2. Campo")+COUNTIFS('2. Status Detalhe Campos FY24'!$H$7:$H$740,'1. Status Resumo FY24'!$P61,'2. Status Detalhe Campos FY24'!$C$7:$C$740,'1. Status Resumo FY24'!$H$48,'2. Status Detalhe Campos FY24'!$D$7:$D$740,"2. Campo") -> 0 | U61: =COUNTIFS('2. Status Detalhe Campos FY24'!$G$7:$G$740,'1. Status Resumo FY24'!$P61,'2. Status Detalhe Campos FY24'!$C$7:$C$740,'1. Status Resumo FY24'!$G$48,'2. Status Detalhe Campos FY24'!$D$7:$D$740,"2. Campo")+COUNTIFS('2. Status Detalhe Campos FY24'!$G$7:$G$740,'1. Status Resumo FY24'!$P61,'2. Status Detalhe Campos FY24'!$C$7:$C$740,'1. Status Resumo FY24'!$H$48,'2. Status Detalhe Campos FY24'!$D$7:$D$740,"2. Campo") -> 0 | V61: =U61-T61 -> 0
P62: RequisItos FY24 | T62: =COUNTIFS('2. Status Detalhe Campos FY24'!$H$7:$H$740,'1. Status Resumo FY24'!$P61,'2. Status Detalhe Campos FY24'!$C$7:$C$740,'1. Status Resumo FY24'!$G$48,'2. Status Detalhe Campos FY24'!$D$7:$D$740,"2. Campo",'2. Status Detalhe Campos FY24'!$Y$7:$Y$740,"*Plano anterior*") +COUNTIFS('2. Status Detalhe Campos FY24'!$H$7:$H$740,'1. Status Resumo FY24'!$P61,'2. Status Detalhe Campos FY24'!$C$7:$C$740,'1. Status Resumo FY24'!$H$48,'2. Status Detalhe Campos FY24'!$D$7:$D$740,"2. Campo",'2. Status Detalhe Campos FY24'!$Y$7:$Y$740,"*Plano anterior*") -> 0 | U62: =COUNTIFS('2. Status Detalhe Campos FY24'!$G$7:$G$740,'1. Status Resumo FY24'!$P61,'2. Status Detalhe Campos FY24'!$C$7:$C$740,'1. Status Resumo FY24'!$G$48,'2. Status Detalhe Campos FY24'!$D$7:$D$740,"2. Campo",'2. Status Detalhe Campos FY24'!$Y$7:$Y$740,"*Plano anterior*") +COUNTIFS('2. Status Detalhe Campos FY24'!$G$7:$G$740,'1. Status Resumo FY24'!$P61,'2. Status Detalhe Campos FY24'!$C$7:$C$740,'1. Status Resumo FY24'!$H$48,'2. Status Detalhe Campos FY24'!$D$7:$D$740,"2. Campo",'2. Status Detalhe Campos FY24'!$Y$7:$Y$740,"*Plano anterior*") -> 0 | V62: =U62-T62 -> 0
P63: Novos Requisitos FY25 | T63: =COUNTIFS('2. Status Detalhe Campos FY24'!$H$7:$H$740,'1. Status Resumo FY24'!$P62,'2. Status Detalhe Campos FY24'!$C$7:$C$740,'1. Status Resumo FY24'!$G$48,'2. Status Detalhe Campos FY24'!$D$7:$D$740,"2. Campo",'2. Status Detalhe Campos FY24'!$Y$7:$Y$740,"*Novo Plano*") +COUNTIFS('2. Status Detalhe Campos FY24'!$H$7:$H$740,'1. Status Resumo FY24'!$P62,'2. Status Detalhe Campos FY24'!$C$7:$C$740,'1. Status Resumo FY24'!$H$48,'2. Status Detalhe Campos FY24'!$D$7:$D$740,"2. Campo",'2. Status Detalhe Campos FY24'!$Y$7:$Y$740,"*Novo Plano*") -> 0 | U63: =COUNTIFS('2. Status Detalhe Campos FY24'!$G$7:$G$740,'1. Status Resumo FY24'!$P61,'2. Status Detalhe Campos FY24'!$C$7:$C$740,'1. Status Resumo FY24'!$G$48,'2. Status Detalhe Campos FY24'!$D$7:$D$740,"2. Campo",'2. Status Detalhe Campos FY24'!$Y$7:$Y$740,"*Novo Plano*") +COUNTIFS('2. Status Detalhe Campos FY24'!$G$7:$G$740,'1. Status Resumo FY24'!$P61,'2. Status Detalhe Campos FY24'!$C$7:$C$740,'1. Status Resumo FY24'!$H$48,'2. Status Detalhe Campos FY24'!$D$7:$D$740,"2. Campo",'2. Status Detalhe Campos FY24'!$Y$7:$Y$740,"*Novo Plano*") -> 0 | V63: =U63-T63 -> 0
P64: 3. Pendente de outros desenvolvimentos | T64: =COUNTIFS('2. Status Detalhe Campos FY24'!$H$7:$H$740,'1. Status Resumo FY24'!$P64,'2. Status Detalhe Campos FY24'!$C$7:$C$740,'1. Status Resumo FY24'!$G$48,'2. Status Detalhe Campos FY24'!$D$7:$D$740,"2. Campo")+COUNTIFS('2. Status Detalhe Campos FY24'!$H$7:$H$740,'1. Status Resumo FY24'!$P64,'2. Status Detalhe Campos FY24'!$C$7:$C$740,'1. Status Resumo FY24'!$H$48,'2. Status Detalhe Campos FY24'!$D$7:$D$740,"2. Campo") -> 0 | U64: =COUNTIFS('2. Status Detalhe Campos FY24'!$G$7:$G$740,'1. Status Resumo FY24'!$P64,'2. Status Detalhe Campos FY24'!$C$7:$C$740,'1. Status Resumo FY24'!$G$48,'2. Status Detalhe Campos FY24'!$D$7:$D$740,"2. Campo")+COUNTIFS('2. Status Detalhe Campos FY24'!$G$7:$G$740,'1. Status Resumo FY24'!$P64,'2. Status Detalhe Campos FY24'!$C$7:$C$740,'1. Status Resumo FY24'!$H$48,'2. Status Detalhe Campos FY24'!$D$7:$D$740,"2. Campo") -> 0 | V64: =U64-T64 -> 0
P65: RequisItos FY24 | T65: =COUNTIFS('2. Status Detalhe Campos FY24'!$H$7:$H$740,'1. Status Resumo FY24'!$P64,'2. Status Detalhe Campos FY24'!$C$7:$C$740,'1. Status Resumo FY24'!$G$48,'2. Status Detalhe Campos FY24'!$D$7:$D$740,"2. Campo",'2. Status Detalhe Campos FY24'!$Y$7:$Y$740,"*Plano anterior*") +COUNTIFS('2. Status Detalhe Campos FY24'!$H$7:$H$740,'1. Status Resumo FY24'!$P64,'2. Status Detalhe Campos FY24'!$C$7:$C$740,'1. Status Resumo FY24'!$H$48,'2. Status Detalhe Campos FY24'!$D$7:$D$740,"2. Campo",'2. Status Detalhe Campos FY24'!$Y$7:$Y$740,"*Plano anterior*") -> 0 | U65: =COUNTIFS('2. Status Detalhe Campos FY24'!$G$7:$G$740,'1. Status Resumo FY24'!$P64,'2. Status Detalhe Campos FY24'!$C$7:$C$740,'1. Status Resumo FY24'!$G$48,'2. Status Detalhe Campos FY24'!$D$7:$D$740,"2. Campo",'2. Status Detalhe Campos FY24'!$Y$7:$Y$740,"*Plano anterior*") +COUNTIFS('2. Status Detalhe Campos FY24'!$G$7:$G$740,'1. Status Resumo FY24'!$P64,'2. Status Detalhe Campos FY24'!$C$7:$C$740,'1. Status Resumo FY24'!$H$48,'2. Status Detalhe Campos FY24'!$D$7:$D$740,"2. Campo",'2. Status Detalhe Campos FY24'!$Y$7:$Y$740,"*Plano anterior*") -> 0 | V65: =U65-T65 -> 0
P66: Novos Requisitos FY25 | T66: =COUNTIFS('2. Status Detalhe Campos FY24'!$H$7:$H$740,'1. Status Resumo FY24'!$P65,'2. Status Detalhe Campos FY24'!$C$7:$C$740,'1. Status Resumo FY24'!$G$48,'2. Status Detalhe Campos FY24'!$D$7:$D$740,"2. Campo",'2. Status Detalhe Campos FY24'!$Y$7:$Y$740,"*Novo Plano*") +COUNTIFS('2. Status Detalhe Campos FY24'!$H$7:$H$740,'1. Status Resumo FY24'!$P65,'2. Status Detalhe Campos FY24'!$C$7:$C$740,'1. Status Resumo FY24'!$H$48,'2. Status Detalhe Campos FY24'!$D$7:$D$740,"2. Campo",'2. Status Detalhe Campos FY24'!$Y$7:$Y$740,"*Novo Plano*") -> 0 | U66: =COUNTIFS('2. Status Detalhe Campos FY24'!$G$7:$G$740,'1. Status Resumo FY24'!$P64,'2. Status Detalhe Campos FY24'!$C$7:$C$740,'1. Status Resumo FY24'!$G$48,'2. Status Detalhe Campos FY24'!$D$7:$D$740,"2. Campo",'2. Status Detalhe Campos FY24'!$Y$7:$Y$740,"*Novo Plano*") +COUNTIFS('2. Status Detalhe Campos FY24'!$G$7:$G$740,'1. Status Resumo FY24'!$P64,'2. Status Detalhe Campos FY24'!$C$7:$C$740,'1. Status Resumo FY24'!$H$48,'2. Status Detalhe Campos FY24'!$D$7:$D$740,"2. Campo",'2. Status Detalhe Campos FY24'!$Y$7:$Y$740,"*Novo Plano*") -> 0 | V66: =U66-T66 -> 0
P67: 4. Validação EF | T67: =COUNTIFS('2. Status Detalhe Campos FY24'!$H$7:$H$740,'1. Status Resumo FY24'!$P67,'2. Status Detalhe Campos FY24'!$C$7:$C$740,'1. Status Resumo FY24'!$G$48,'2. Status Detalhe Campos FY24'!$D$7:$D$740,"2. Campo")+COUNTIFS('2. Status Detalhe Campos FY24'!$H$7:$H$740,'1. Status Resumo FY24'!$P67,'2. Status Detalhe Campos FY24'!$C$7:$C$740,'1. Status Resumo FY24'!$H$48,'2. Status Detalhe Campos FY24'!$D$7:$D$740,"2. Campo") -> 1 | U67: =COUNTIFS('2. Status Detalhe Campos FY24'!$G$7:$G$740,'1. Status Resumo FY24'!$P67,'2. Status Detalhe Campos FY24'!$C$7:$C$740,'1. Status Resumo FY24'!$G$48,'2. Status Detalhe Campos FY24'!$D$7:$D$740,"2. Campo")+COUNTIFS('2. Status Detalhe Campos FY24'!$G$7:$G$740,'1. Status Resumo FY24'!$P67,'2. Status Detalhe Campos FY24'!$C$7:$C$740,'1. Status Resumo FY24'!$H$48,'2. Status Detalhe Campos FY24'!$D$7:$D$740,"2. Campo") -> 1 | V67: =U67-T67 -> 0
P68: RequisItos FY24 | T68: =COUNTIFS('2. Status Detalhe Campos FY24'!$H$7:$H$740,'1. Status Resumo FY24'!$P67,'2. Status Detalhe Campos FY24'!$C$7:$C$740,'1. Status Resumo FY24'!$G$48,'2. Status Detalhe Campos FY24'!$D$7:$D$740,"2. Campo",'2. Status Detalhe Campos FY24'!$Y$7:$Y$740,"*Plano anterior*") +COUNTIFS('2. Status Detalhe Campos FY24'!$H$7:$H$740,'1. Status Resumo FY24'!$P67,'2. Status Detalhe Campos FY24'!$C$7:$C$740,'1. Status Resumo FY24'!$H$48,'2. Status Detalhe Campos FY24'!$D$7:$D$740,"2. Campo",'2. Status Detalhe Campos FY24'!$Y$7:$Y$740,"*Plano anterior*") -> 1 | U68: =COUNTIFS('2. Status Detalhe Campos FY24'!$G$7:$G$740,'1. Status Resumo FY24'!$P67,'2. Status Detalhe Campos FY24'!$C$7:$C$740,'1. Status Resumo FY24'!$G$48,'2. Status Detalhe Campos FY24'!$D$7:$D$740,"2. Campo",'2. Status Detalhe Campos FY24'!$Y$7:$Y$740,"*Plano anterior*") +COUNTIFS('2. Status Detalhe Campos FY24'!$G$7:$G$740,'1. Status Resumo FY24'!$P67,'2. Status Detalhe Campos FY24'!$C$7:$C$740,'1. Status Resumo FY24'!$H$48,'2. Status Detalhe Campos FY24'!$D$7:$D$740,"2. Campo",'2. Status Detalhe Campos FY24'!$Y$7:$Y$740,"*Plano anterior*") -> 1 | V68: =U68-T68 -> 0
P69: Novos Requisitos FY25 | T69: =COUNTIFS('2. Status Detalhe Campos FY24'!$H$7:$H$740,'1. Status Resumo FY24'!$P68,'2. Status Detalhe Campos FY24'!$C$7:$C$740,'1. Status Resumo FY24'!$G$48,'2. Status Detalhe Campos FY24'!$D$7:$D$740,"2. Campo",'2. Status Detalhe Campos FY24'!$Y$7:$Y$740,"*Novo Plano*") +COUNTIFS('2. Status Detalhe Campos FY24'!$H$7:$H$740,'1. Status Resumo FY24'!$P68,'2. Status Detalhe Campos FY24'!$C$7:$C$740,'1. Status Resumo FY24'!$H$48,'2. Status Detalhe Campos FY24'!$D$7:$D$740,"2. Campo",'2. Status Detalhe Campos FY24'!$Y$7:$Y$740,"*Novo Plano*") -> 0 | U69: =COUNTIFS('2. Status Detalhe Campos FY24'!$G$7:$G$740,'1. Status Resumo FY24'!$P67,'2. Status Detalhe Campos FY24'!$C$7:$C$740,'1. Status Resumo FY24'!$G$48,'2. Status Detalhe Campos FY24'!$D$7:$D$740,"2. Campo",'2. Status Detalhe Campos FY24'!$Y$7:$Y$740,"*Novo Plano*") +COUNTIFS('2. Status Detalhe Campos FY24'!$G$7:$G$740,'1. Status Resumo FY24'!$P67,'2. Status Detalhe Campos FY24'!$C$7:$C$740,'1. Status Resumo FY24'!$H$48,'2. Status Detalhe Campos FY24'!$D$7:$D$740,"2. Campo",'2. Status Detalhe Campos FY24'!$Y$7:$Y$740,"*Novo Plano*") -> 0 | V69: =U69-T69 -> 0
P70: 5. Em Correção | R70: (incidências) | T70: =COUNTIFS('2. Status Detalhe Campos FY24'!$H$7:$H$740,'1. Status Resumo FY24'!$P70,'2. Status Detalhe Campos FY24'!$C$7:$C$740,'1. Status Resumo FY24'!$G$48,'2. Status Detalhe Campos FY24'!$D$7:$D$740,"2. Campo")+COUNTIFS('2. Status Detalhe Campos FY24'!$H$7:$H$740,'1. Status Resumo FY24'!$P70,'2. Status Detalhe Campos FY24'!$C$7:$C$740,'1. Status Resumo FY24'!$H$48,'2. Status Detalhe Campos FY24'!$D$7:$D$740,"2. Campo") -> 0 | U70: =COUNTIFS('2. Status Detalhe Campos FY24'!$G$7:$G$740,'1. Status Resumo FY24'!$P70,'2. Status Detalhe Campos FY24'!$C$7:$C$740,'1. Status Resumo FY24'!$G$48,'2. Status Detalhe Campos FY24'!$D$7:$D$740,"2. Campo")+COUNTIFS('2. Status Detalhe Campos FY24'!$G$7:$G$740,'1. Status Resumo FY24'!$P70,'2. Status Detalhe Campos FY24'!$C$7:$C$740,'1. Status Resumo FY24'!$H$48,'2. Status Detalhe Campos FY24'!$D$7:$D$740,"2. Campo") -> 0 | V70: =U70-T70 -> 0
P71: RequisItos FY24 | T71: =COUNTIFS('2. Status Detalhe Campos FY24'!$H$7:$H$740,'1. Status Resumo FY24'!$P70,'2. Status Detalhe Campos FY24'!$C$7:$C$740,'1. Status Resumo FY24'!$G$48,'2. Status Detalhe Campos FY24'!$D$7:$D$740,"2. Campo",'2. Status Detalhe Campos FY24'!$Y$7:$Y$740,"*Plano anterior*") +COUNTIFS('2. Status Detalhe Campos FY24'!$H$7:$H$740,'1. Status Resumo FY24'!$P70,'2. Status Detalhe Campos FY24'!$C$7:$C$740,'1. Status Resumo FY24'!$H$48,'2. Status Detalhe Campos FY24'!$D$7:$D$740,"2. Campo",'2. Status Detalhe Campos FY24'!$Y$7:$Y$740,"*Plano anterior*") -> 0 | U71: =COUNTIFS('2. Status Detalhe Campos FY24'!$G$7:$G$740,'1. Status Resumo FY24'!$P70,'2. Status Detalhe Campos FY24'!$C$7:$C$740,'1. Status Resumo FY24'!$G$48,'2. Status Detalhe Campos FY24'!$D$7:$D$740,"2. Campo",'2. Status Detalhe Campos FY24'!$Y$7:$Y$740,"*Plano anterior*") +COUNTIFS('2. Status Detalhe Campos FY24'!$G$7:$G$740,'1. Status Resumo FY24'!$P70,'2. Status Detalhe Campos FY24'!$C$7:$C$740,'1. Status Resumo FY24'!$H$48,'2. Status Detalhe Campos FY24'!$D$7:$D$740,"2. Campo",'2. Status Detalhe Campos FY24'!$Y$7:$Y$740,"*Plano anterior*") -> 0 | V71: =U71-T71 -> 0
P72: Novos Requisitos FY25 | T72: =COUNTIFS('2. Status Detalhe Campos FY24'!$H$7:$H$740,'1. Status Resumo FY24'!$P71,'2. Status Detalhe Campos FY24'!$C$7:$C$740,'1. Status Resumo FY24'!$G$48,'2. Status Detalhe Campos FY24'!$D$7:$D$740,"2. Campo",'2. Status Detalhe Campos FY24'!$Y$7:$Y$740,"*Novo Plano*") +COUNTIFS('2. Status Detalhe Campos FY24'!$H$7:$H$740,'1. Status Resumo FY24'!$P71,'2. Status Detalhe Campos FY24'!$C$7:$C$740,'1. Status Resumo FY24'!$H$48,'2. Status Detalhe Campos FY24'!$D$7:$D$740,"2. Campo",'2. Status Detalhe Campos FY24'!$Y$7:$Y$740,"*Novo Plano*") -> 0 | U72: =COUNTIFS('2. Status Detalhe Campos FY24'!$G$7:$G$740,'1. Status Resumo FY24'!$P70,'2. Status Detalhe Campos FY24'!$C$7:$C$740,'1. Status Resumo FY24'!$G$48,'2. Status Detalhe Campos FY24'!$D$7:$D$740,"2. Campo",'2. Status Detalhe Campos FY24'!$Y$7:$Y$740,"*Novo Plano*") +COUNTIFS('2. Status Detalhe Campos FY24'!$G$7:$G$740,'1. Status Resumo FY24'!$P70,'2. Status Detalhe Campos FY24'!$C$7:$C$740,'1. Status Resumo FY24'!$H$48,'2. Status Detalhe Campos FY24'!$D$7:$D$740,"2. Campo",'2. Status Detalhe Campos FY24'!$Y$7:$Y$740,"*Novo Plano*") -> 0 | V72: =U72-T72 -> 0
P73: 6. Em implementação | T73: =COUNTIFS('2. Status Detalhe Campos FY24'!$H$7:$H$740,'1. Status Resumo FY24'!$P73,'2. Status Detalhe Campos FY24'!$C$7:$C$740,'1. Status Resumo FY24'!$G$48,'2. Status Detalhe Campos FY24'!$D$7:$D$740,"2. Campo")+COUNTIFS('2. Status Detalhe Campos FY24'!$H$7:$H$740,'1. Status Resumo FY24'!$P73,'2. Status Detalhe Campos FY24'!$C$7:$C$740,'1. Status Resumo FY24'!$H$48,'2. Status Detalhe Campos FY24'!$D$7:$D$740,"2. Campo") -> 0 | U73: =COUNTIFS('2. Status Detalhe Campos FY24'!$G$7:$G$740,'1. Status Resumo FY24'!$P73,'2. Status Detalhe Campos FY24'!$C$7:$C$740,'1. Status Resumo FY24'!$G$48,'2. Status Detalhe Campos FY24'!$D$7:$D$740,"2. Campo")+COUNTIFS('2. Status Detalhe Campos FY24'!$G$7:$G$740,'1. Status Resumo FY24'!$P73,'2. Status Detalhe Campos FY24'!$C$7:$C$740,'1. Status Resumo FY24'!$H$48,'2. Status Detalhe Campos FY24'!$D$7:$D$740,"2. Campo") -> 0 | V73: =U73-T73 -> 0
P74: RequisItos FY24 | T74: =COUNTIFS('2. Status Detalhe Campos FY24'!$H$7:$H$740,'1. Status Resumo FY24'!$P73,'2. Status Detalhe Campos FY24'!$C$7:$C$740,'1. Status Resumo FY24'!$G$48,'2. Status Detalhe Campos FY24'!$D$7:$D$740,"2. Campo",'2. Status Detalhe Campos FY24'!$Y$7:$Y$740,"*Plano anterior*") +COUNTIFS('2. Status Detalhe Campos FY24'!$H$7:$H$740,'1. Status Resumo FY24'!$P73,'2. Status Detalhe Campos FY24'!$C$7:$C$740,'1. Status Resumo FY24'!$H$48,'2. Status Detalhe Campos FY24'!$D$7:$D$740,"2. Campo",'2. Status Detalhe Campos FY24'!$Y$7:$Y$740,"*Plano anterior*") -> 0 | U74: =COUNTIFS('2. Status Detalhe Campos FY24'!$G$7:$G$740,'1. Status Resumo FY24'!$P73,'2. Status Detalhe Campos FY24'!$C$7:$C$740,'1. Status Resumo FY24'!$G$48,'2. Status Detalhe Campos FY24'!$D$7:$D$740,"2. Campo",'2. Status Detalhe Campos FY24'!$Y$7:$Y$740,"*Plano anterior*") +COUNTIFS('2. Status Detalhe Campos FY24'!$G$7:$G$740,'1. Status Resumo FY24'!$P73,'2. Status Detalhe Campos FY24'!$C$7:$C$740,'1. Status Resumo FY24'!$H$48,'2. Status Detalhe Campos FY24'!$D$7:$D$740,"2. Campo",'2. Status Detalhe Campos FY24'!$Y$7:$Y$740,"*Plano anterior*") -> 0 | V74: =U74-T74 -> 0
P75: Novos Requisitos FY25 | T75: =COUNTIFS('2. Status Detalhe Campos FY24'!$H$7:$H$740,'1. Status Resumo FY24'!$P74,'2. Status Detalhe Campos FY24'!$C$7:$C$740,'1. Status Resumo FY24'!$G$48,'2. Status Detalhe Campos FY24'!$D$7:$D$740,"2. Campo",'2. Status Detalhe Campos FY24'!$Y$7:$Y$740,"*Novo Plano*") +COUNTIFS('2. Status Detalhe Campos FY24'!$H$7:$H$740,'1. Status Resumo FY24'!$P74,'2. Status Detalhe Campos FY24'!$C$7:$C$740,'1. Status Resumo FY24'!$H$48,'2. Status Detalhe Campos FY24'!$D$7:$D$740,"2. Campo",'2. Status Detalhe Campos FY24'!$Y$7:$Y$740,"*Novo Plano*") -> 0 | U75: =COUNTIFS('2. Status Detalhe Campos FY24'!$G$7:$G$740,'1. Status Resumo FY24'!$P73,'2. Status Detalhe Campos FY24'!$C$7:$C$740,'1. Status Resumo FY24'!$G$48,'2. Status Detalhe Campos FY24'!$D$7:$D$740,"2. Campo",'2. Status Detalhe Campos FY24'!$Y$7:$Y$740,"*Novo Plano*") +COUNTIFS('2. Status Detalhe Campos FY24'!$G$7:$G$740,'1. Status Resumo FY24'!$P73,'2. Status Detalhe Campos FY24'!$C$7:$C$740,'1. Status Resumo FY24'!$H$48,'2. Status Detalhe Campos FY24'!$D$7:$D$740,"2. Campo",'2. Status Detalhe Campos FY24'!$Y$7:$Y$740,"*Novo Plano*") -> 0 | V75: =U75-T75 -> 0
P76: 7. Por iniciar | T76: =COUNTIFS('2. Status Detalhe Campos FY24'!$H$7:$H$740,'1. Status Resumo FY24'!$P76,'2. Status Detalhe Campos FY24'!$C$7:$C$740,'1. Status Resumo FY24'!$G$48,'2. Status Detalhe Campos FY24'!$D$7:$D$740,"2. Campo")+COUNTIFS('2. Status Detalhe Campos FY24'!$H$7:$H$740,'1. Status Resumo FY24'!$P76,'2. Status Detalhe Campos FY24'!$C$7:$C$740,'1. Status Resumo FY24'!$H$48,'2. Status Detalhe Campos FY24'!$D$7:$D$740,"2. Campo") -> 0 | U76: =COUNTIFS('2. Status Detalhe Campos FY24'!$G$7:$G$740,'1. Status Resumo FY24'!$P76,'2. Status Detalhe Campos FY24'!$C$7:$C$740,'1. Status Resumo FY24'!$G$48,'2. Status Detalhe Campos FY24'!$D$7:$D$740,"2. Campo")+COUNTIFS('2. Status Detalhe Campos FY24'!$G$7:$G$740,'1. Status Resumo FY24'!$P76,'2. Status Detalhe Campos FY24'!$C$7:$C$740,'1. Status Resumo FY24'!$H$48,'2. Status Detalhe Campos FY24'!$D$7:$D$740,"2. Campo") -> 0 | V76: =U76-T76 -> 0
P77: RequisItos FY24 | T77: =COUNTIFS('2. Status Detalhe Campos FY24'!$H$7:$H$740,'1. Status Resumo FY24'!$P76,'2. Status Detalhe Campos FY24'!$C$7:$C$740,'1. Status Resumo FY24'!$G$48,'2. Status Detalhe Campos FY24'!$D$7:$D$740,"2. Campo",'2. Status Detalhe Campos FY24'!$Y$7:$Y$740,"*Plano anterior*") +COUNTIFS('2. Status Detalhe Campos FY24'!$H$7:$H$740,'1. Status Resumo FY24'!$P76,'2. Status Detalhe Campos FY24'!$C$7:$C$740,'1. Status Resumo FY24'!$H$48,'2. Status Detalhe Campos FY24'!$D$7:$D$740,"2. Campo",'2. Status Detalhe Campos FY24'!$Y$7:$Y$740,"*Plano anterior*") -> 0 | U77: =COUNTIFS('2. Status Detalhe Campos FY24'!$G$7:$G$740,'1. Status Resumo FY24'!$P76,'2. Status Detalhe Campos FY24'!$C$7:$C$740,'1. Status Resumo FY24'!$G$48,'2. Status Detalhe Campos FY24'!$D$7:$D$740,"2. Campo",'2. Status Detalhe Campos FY24'!$Y$7:$Y$740,"*Plano anterior*") +COUNTIFS('2. Status Detalhe Campos FY24'!$G$7:$G$740,'1. Status Resumo FY24'!$P76,'2. Status Detalhe Campos FY24'!$C$7:$C$740,'1. Status Resumo FY24'!$H$48,'2. Status Detalhe Campos FY24'!$D$7:$D$740,"2. Campo",'2. Status Detalhe Campos FY24'!$Y$7:$Y$740,"*Plano anterior*") -> 0 | V77: =U77-T77 -> 0
P78: Novos Requisitos FY25 | T78: =COUNTIFS('2. Status Detalhe Campos FY24'!$H$7:$H$740,'1. Status Resumo FY24'!$P77,'2. Status Detalhe Campos FY24'!$C$7:$C$740,'1. Status Resumo FY24'!$G$48,'2. Status Detalhe Campos FY24'!$D$7:$D$740,"2. Campo",'2. Status Detalhe Campos FY24'!$Y$7:$Y$740,"*Novo Plano*") +COUNTIFS('2. Status Detalhe Campos FY24'!$H$7:$H$740,'1. Status Resumo FY24'!$P77,'2. Status Detalhe Campos FY24'!$C$7:$C$740,'1. Status Resumo FY24'!$H$48,'2. Status Detalhe Campos FY24'!$D$7:$D$740,"2. Campo",'2. Status Detalhe Campos FY24'!$Y$7:$Y$740,"*Novo Plano*") -> 0 | U78: =COUNTIFS('2. Status Detalhe Campos FY24'!$G$7:$G$740,'1. Status Resumo FY24'!$P76,'2. Status Detalhe Campos FY24'!$C$7:$C$740,'1. Status Resumo FY24'!$G$48,'2. Status Detalhe Campos FY24'!$D$7:$D$740,"2. Campo",'2. Status Detalhe Campos FY24'!$Y$7:$Y$740,"*Novo Plano*") +COUNTIFS('2. Status Detalhe Campos FY24'!$G$7:$G$740,'1. Status Resumo FY24'!$P76,'2. Status Detalhe Campos FY24'!$C$7:$C$740,'1. Status Resumo FY24'!$H$48,'2. Status Detalhe Campos FY24'!$D$7:$D$740,"2. Campo",'2. Status Detalhe Campos FY24'!$Y$7:$Y$740,"*Novo Plano*") -> 0 | V78: =U78-T78 -> 0
P79: Total | T79: =+SUM(T52,T55,T58,T64,T67,T70,T73,T76,T61) -> 208 | U79: =+SUM(U52,U55,U58,U64,U67,U70,U73,U76,U61) -> 208 | V79: =+U79-T79 -> 0
P80: RequisItos FY24 | T80: =+SUM(T53,T56,T59,T62,T65,T68,T71,T74,T77) -> 208 | U80: =+SUM(U53,U56,U59,U62,U65,U68,U71,U74,U77) -> 208 | V80: =+U80-T80 -> 0
P81: Novos Requisitos FY25 | T81: =+SUM(T54,T57,T60,T63,T66,T69,T72,T75,T78) -> 0 | U81: =+SUM(U54,U57,U60,U63,U66,U69,U72,U75,U78) -> 0 | V81: =+U81-T81 -> 0
G83: Status (Tabelas) | P83: Status (Universos)
F84: > | G84: Tabela de Bens Imóveis | L84: OK | O84: > | P84: Universo Bens Colateralizados (MUG) | T84: OK
F85: > | G85: Tabelas de Processos Imobiliários | L85: OK | O85: > | P85: Universo Bens Não Colateralizados (GP) | T85: OK
F86: > | G86: Tabela de Traçabilidade Processo -Bem | L86: OK | O86: > | P86: Universo Bens Adjudicados | T86: Não serão testados neste projeto
F87: > | G87: Tabela de Traçabilidade Crédito - Processo | L87: OK
F88: > | G88: Tabela input de Cerificados Energéticos (Gloval) | L88: OK
F89: > | G89: Tabela Output de Cerificados Energéticos | L89: Validação EF
B93: 2. Modelo Verde | G93: Modelo Verde - Input | H93: Modelo Verde - Output
C96: Resumo | G96: Detalhe por Tabela | P96: Status (campos) | T96: =T51 -> 45744 | U96: =U51 -> 45751 | V96: ∆ | X96: Highlights
P97: 0. Cancelado | T97: =COUNTIFS('2. Status Detalhe Campos FY24'!$H$7:$H$740,'1. Status Resumo FY24'!$P97,'2. Status Detalhe Campos FY24'!$C$7:$C$740,'1. Status Resumo FY24'!$G$93,'2. Status Detalhe Campos FY24'!$D$7:$D$740,"2. Campo")+COUNTIFS('2. Status Detalhe Campos FY24'!$H$7:$H$740,'1. Status Resumo FY24'!$P97,'2. Status Detalhe Campos FY24'!$C$7:$C$740,'1. Status Resumo FY24'!$H$93,'2. Status Detalhe Campos FY24'!$D$7:$D$740,"2. Campo") -> 19 | U97: =COUNTIFS('2. Status Detalhe Campos FY24'!$G$7:$G$740,'1. Status Resumo FY24'!$P97,'2. Status Detalhe Campos FY24'!$C$7:$C$740,'1. Status Resumo FY24'!$G$93,'2. Status Detalhe Campos FY24'!$D$7:$D$740,"2. Campo")+COUNTIFS('2. Status Detalhe Campos FY24'!$G$7:$G$740,'1. Status Resumo FY24'!$P97,'2. Status Detalhe Campos FY24'!$C$7:$C$740,'1. Status Resumo FY24'!$H$93,'2. Status Detalhe Campos FY24'!$D$7:$D$740,"2. Campo") -> 19 | V97: =U97-T97 -> 0 | X97: 1. Tabela de Clientes: - Continuação dos testes dos 13 campos da tabela de output de Marcação Verde.
P98: Requisitos FY24 | T98: =COUNTIFS('2. Status Detalhe Campos FY24'!$H$7:$H$740,'1. Status Resumo FY24'!$P97,'2. Status Detalhe Campos FY24'!$C$7:$C$740,'1. Status Resumo FY24'!$G$93,'2. Status Detalhe Campos FY24'!$D$7:$D$740,"2. Campo",'2. Status Detalhe Campos FY24'!$Y$7:$Y$740,"*Plano anterior*") +COUNTIFS('2. Status Detalhe Campos FY24'!$H$7:$H$740,'1. Status Resumo FY24'!$P97,'2. Status Detalhe Campos FY24'!$C$7:$C$740,'1. Status Resumo FY24'!$H$93,'2. Status Detalhe Campos FY24'!$D$7:$D$740,"2. Campo",'2. Status Detalhe Campos FY24'!$Y$7:$Y$740,"*Plano anterior*") -> 19 | U98: =COUNTIFS('2. Status Detalhe Campos FY24'!$G$7:$G$740,'1. Status Resumo FY24'!$P97,'2. Status Detalhe Campos FY24'!$C$7:$C$740,'1. Status Resumo FY24'!$G$93,'2. Status Detalhe Campos FY24'!$D$7:$D$740,"2. Campo",'2. Status Detalhe Campos FY24'!$Y$7:$Y$740,"*Plano anterior*") +COUNTIFS('2. Status Detalhe Campos FY24'!$G$7:$G$740,'1. Status Resumo FY24'!$P97,'2. Status Detalhe Campos FY24'!$C$7:$C$740,'1. Status Resumo FY24'!$H$93,'2. Status Detalhe Campos FY24'!$D$7:$D$740,"2. Campo",'2. Status Detalhe Campos FY24'!$Y$7:$Y$740,"*Plano anterior*") -> 19 | V98: =U98-T98 -> 0
P99: Novos Requisitos FY25 | T99: =COUNTIFS('2. Status Detalhe Campos FY24'!$H$7:$H$740,'1. Status Resumo FY24'!$P97,'2. Status Detalhe Campos FY24'!$C$7:$C$740,'1. Status Resumo FY24'!$G$93,'2. Status Detalhe Campos FY24'!$D$7:$D$740,"2. Campo",'2. Status Detalhe Campos FY24'!$Y$7:$Y$740,"*Novo Plano*") +COUNTIFS('2. Status Detalhe Campos FY24'!$H$7:$H$740,'1. Status Resumo FY24'!$P97,'2. Status Detalhe Campos FY24'!$C$7:$C$740,'1. Status Resumo FY24'!$H$93,'2. Status Detalhe Campos FY24'!$D$7:$D$740,"2. Campo",'2. Status Detalhe Campos FY24'!$Y$7:$Y$740,"*Novo Plano*") -> 0 | U99: =COUNTIFS('2. Status Detalhe Campos FY24'!$G$7:$G$740,'1. Status Resumo FY24'!$P97,'2. Status Detalhe Campos FY24'!$C$7:$C$740,'1. Status Resumo FY24'!$G$93,'2. Status Detalhe Campos FY24'!$D$7:$D$740,"2. Campo",'2. Status Detalhe Campos FY24'!$Y$7:$Y$740,"*Novo Plano*") +COUNTIFS('2. Status Detalhe Campos FY24'!$G$7:$G$740,'1. Status Resumo FY24'!$P97,'2. Status Detalhe Campos FY24'!$C$7:$C$740,'1. Status Resumo FY24'!$H$93,'2. Status Detalhe Campos FY24'!$D$7:$D$740,"2. Campo",'2. Status Detalhe Campos FY24'!$Y$7:$Y$740,"*Novo Plano*") -> 0 | V99: =U99-T99 -> 0
P100: 1. Concluído | T100: =COUNTIFS('2. Status Detalhe Campos FY24'!$H$7:$H$740,'1. Status Resumo FY24'!$P100,'2. Status Detalhe Campos FY24'!$C$7:$C$740,'1. Status Resumo FY24'!$G$93,'2. Status Detalhe Campos FY24'!$D$7:$D$740,"2. Campo")+COUNTIFS('2. Status Detalhe Campos FY24'!$H$7:$H$740,'1. Status Resumo FY24'!$P100,'2. Status Detalhe Campos FY24'!$C$7:$C$740,'1. Status Resumo FY24'!$H$93,'2. Status Detalhe Campos FY24'!$D$7:$D$740,"2. Campo") -> 270 | U100: =COUNTIFS('2. Status Detalhe Campos FY24'!$G$7:$G$740,'1. Status Resumo FY24'!$P100,'2. Status Detalhe Campos FY24'!$C$7:$C$740,'1. Status Resumo FY24'!$G$93,'2. Status Detalhe Campos FY24'!$D$7:$D$740,"2. Campo")+COUNTIFS('2. Status Detalhe Campos FY24'!$G$7:$G$740,'1. Status Resumo FY24'!$P100,'2. Status Detalhe Campos FY24'!$C$7:$C$740,'1. Status Resumo FY24'!$H$93,'2. Status Detalhe Campos FY24'!$D$7:$D$740,"2. Campo") -> 270 | V100: =U100-T100 -> 0
P101: Requisitos FY24 | T101: =COUNTIFS('2. Status Detalhe Campos FY24'!$H$7:$H$740,'1. Status Resumo FY24'!$P100,'2. Status Detalhe Campos FY24'!$C$7:$C$740,'1. Status Resumo FY24'!$G$93,'2. Status Detalhe Campos FY24'!$D$7:$D$740,"2. Campo",'2. Status Detalhe Campos FY24'!$Y$7:$Y$740,"*Plano anterior*") +COUNTIFS('2. Status Detalhe Campos FY24'!$H$7:$H$740,'1. Status Resumo FY24'!$P100,'2. Status Detalhe Campos FY24'!$C$7:$C$740,'1. Status Resumo FY24'!$H$93,'2. Status Detalhe Campos FY24'!$D$7:$D$740,"2. Campo",'2. Status Detalhe Campos FY24'!$Y$7:$Y$740,"*Plano anterior*") -> 245 | U101: =COUNTIFS('2. Status Detalhe Campos FY24'!$G$7:$G$740,'1. Status Resumo FY24'!$P100,'2. Status Detalhe Campos FY24'!$C$7:$C$740,'1. Status Resumo FY24'!$G$93,'2. Status Detalhe Campos FY24'!$D$7:$D$740,"2. Campo",'2. Status Detalhe Campos FY24'!$Y$7:$Y$740,"*Plano anterior*") +COUNTIFS('2. Status Detalhe Campos FY24'!$G$7:$G$740,'1. Status Resumo FY24'!$P100,'2. Status Detalhe Campos FY24'!$C$7:$C$740,'1. Status Resumo FY24'!$H$93,'2. Status Detalhe Campos FY24'!$D$7:$D$740,"2. Campo",'2. Status Detalhe Campos FY24'!$Y$7:$Y$740,"*Plano anterior*") -> 245 | V101: =U101-T101 -> 0
P102: Novos Requisitos FY25 | T102: =COUNTIFS('2. Status Detalhe Campos FY24'!$H$7:$H$740,'1. Status Resumo FY24'!$P100,'2. Status Detalhe Campos FY24'!$C$7:$C$740,'1. Status Resumo FY24'!$G$93,'2. Status Detalhe Campos FY24'!$D$7:$D$740,"2. Campo",'2. Status Detalhe Campos FY24'!$Y$7:$Y$740,"*Novo Plano*") +COUNTIFS('2. Status Detalhe Campos FY24'!$H$7:$H$740,'1. Status Resumo FY24'!$P100,'2. Status Detalhe Campos FY24'!$C$7:$C$740,'1. Status Resumo FY24'!$H$93,'2. Status Detalhe Campos FY24'!$D$7:$D$740,"2. Campo",'2. Status Detalhe Campos FY24'!$Y$7:$Y$740,"*Novo Plano*") -> 25 | U102: =COUNTIFS('2. Status Detalhe Campos FY24'!$G$7:$G$740,'1. Status Resumo FY24'!$P100,'2. Status Detalhe Campos FY24'!$C$7:$C$740,'1. Status Resumo FY24'!$G$93,'2. Status Detalhe Campos FY24'!$D$7:$D$740,"2. Campo",'2. Status Detalhe Campos FY24'!$Y$7:$Y$740,"*Novo Plano*") +COUNTIFS('2. Status Detalhe Campos FY24'!$G$7:$G$740,'1. Status Resumo FY24'!$P100,'2. Status Detalhe Campos FY24'!$C$7:$C$740,'1. Status Resumo FY24'!$H$93,'2. Status Detalhe Campos FY24'!$D$7:$D$740,"2. Campo",'2. Status Detalhe Campos FY24'!$Y$7:$Y$740,"*Novo Plano*") -> 25 | V102: =U102-T102 -> 0
P103: 2.1 Em Teste | T103: =COUNTIFS('2. Status Detalhe Campos FY24'!$H$7:$H$740,'1. Status Resumo FY24'!$P103,'2. Status Detalhe Campos FY24'!$C$7:$C$740,'1. Status Resumo FY24'!$G$93,'2. Status Detalhe Campos FY24'!$D$7:$D$740,"2. Campo")+COUNTIFS('2. Status Detalhe Campos FY24'!$H$7:$H$740,'1. Status Resumo FY24'!$P103,'2. Status Detalhe Campos FY24'!$C$7:$C$740,'1. Status Resumo FY24'!$H$93,'2. Status Detalhe Campos FY24'!$D$7:$D$740,"2. Campo") -> 13 | U103: =COUNTIFS('2. Status Detalhe Campos FY24'!$G$7:$G$740,'1. Status Resumo FY24'!$P103,'2. Status Detalhe Campos FY24'!$C$7:$C$740,'1. Status Resumo FY24'!$G$93,'2. Status Detalhe Campos FY24'!$D$7:$D$740,"2. Campo")+COUNTIFS('2. Status Detalhe Campos FY24'!$G$7:$G$740,'1. Status Resumo FY24'!$P103,'2. Status Detalhe Campos FY24'!$C$7:$C$740,'1. Status Resumo FY24'!$H$93,'2. Status Detalhe Campos FY24'!$D$7:$D$740,"2. Campo") -> 13 | V103: =U103-T103 -> 0
P104: Requisitos FY24 | T104: =COUNTIFS('2. Status Detalhe Campos FY24'!$H$7:$H$740,'1. Status Resumo FY24'!$P103,'2. Status Detalhe Campos FY24'!$C$7:$C$740,'1. Status Resumo FY24'!$G$93,'2. Status Detalhe Campos FY24'!$D$7:$D$740,"2. Campo",'2. Status Detalhe Campos FY24'!$Y$7:$Y$740,"*Plano anterior*") +COUNTIFS('2. Status Detalhe Campos FY24'!$H$7:$H$740,'1. Status Resumo FY24'!$P103,'2. Status Detalhe Campos FY24'!$C$7:$C$740,'1. Status Resumo FY24'!$H$93,'2. Status Detalhe Campos FY24'!$D$7:$D$740,"2. Campo",'2. Status Detalhe Campos FY24'!$Y$7:$Y$740,"*Plano anterior*") -> 13 | U104: =COUNTIFS('2. Status Detalhe Campos FY24'!$G$7:$G$740,'1. Status Resumo FY24'!$P103,'2. Status Detalhe Campos FY24'!$C$7:$C$740,'1. Status Resumo FY24'!$G$93,'2. Status Detalhe Campos FY24'!$D$7:$D$740,"2. Campo",'2. Status Detalhe Campos FY24'!$Y$7:$Y$740,"*Plano anterior*") +COUNTIFS('2. Status Detalhe Campos FY24'!$G$7:$G$740,'1. Status Resumo FY24'!$P103,'2. Status Detalhe Campos FY24'!$C$7:$C$740,'1. Status Resumo FY24'!$H$93,'2. Status Detalhe Campos FY24'!$D$7:$D$740,"2. Campo",'2. Status Detalhe Campos FY24'!$Y$7:$Y$740,"*Plano anterior*") -> 13 | V104: =U104-T104 -> 0
P105: Novos Requisitos FY25 | T105: =COUNTIFS('2. Status Detalhe Campos FY24'!$H$7:$H$740,'1. Status Resumo FY24'!$P103,'2. Status Detalhe Campos FY24'!$C$7:$C$740,'1. Status Resumo FY24'!$G$93,'2. Status Detalhe Campos FY24'!$D$7:$D$740,"2. Campo",'2. Status Detalhe Campos FY24'!$Y$7:$Y$740,"*Novo Plano*") +COUNTIFS('2. Status Detalhe Campos FY24'!$H$7:$H$740,'1. Status Resumo FY24'!$P103,'2. Status Detalhe Campos FY24'!$C$7:$C$740,'1. Status Resumo FY24'!$H$93,'2. Status Detalhe Campos FY24'!$D$7:$D$740,"2. Campo",'2. Status Detalhe Campos FY24'!$Y$7:$Y$740,"*Novo Plano*") -> 0 | U105: =COUNTIFS('2. Status Detalhe Campos FY24'!$G$7:$G$740,'1. Status Resumo FY24'!$P103,'2. Status Detalhe Campos FY24'!$C$7:$C$740,'1. Status Resumo FY24'!$G$93,'2. Status Detalhe Campos FY24'!$D$7:$D$740,"2. Campo",'2. Status Detalhe Campos FY24'!$Y$7:$Y$740,"*Novo Plano*") +COUNTIFS('2. Status Detalhe Campos FY24'!$G$7:$G$740,'1. Status Resumo FY24'!$P103,'2. Status Detalhe Campos FY24'!$C$7:$C$740,'1. Status Resumo FY24'!$H$93,'2. Status Detalhe Campos FY24'!$D$7:$D$740,"2. Campo",'2. Status Detalhe Campos FY24'!$Y$7:$Y$740,"*Novo Plano*") -> 0 | V105: =U105-T105 -> 0
P106: 2.2 Em especificação | T106: =COUNTIFS('2. Status Detalhe Campos FY24'!$H$7:$H$740,'1. Status Resumo FY24'!$P106,'2. Status Detalhe Campos FY24'!$C$7:$C$740,'1. Status Resumo FY24'!$G$93,'2. Status Detalhe Campos FY24'!$D$7:$D$740,"2. Campo")+COUNTIFS('2. Status Detalhe Campos FY24'!$H$7:$H$740,'1. Status Resumo FY24'!$P106,'2. Status Detalhe Campos FY24'!$C$7:$C$740,'1. Status Resumo FY24'!$H$93,'2. Status Detalhe Campos FY24'!$D$7:$D$740,"2. Campo") -> 0 | U106: =COUNTIFS('2. Status Detalhe Campos FY24'!$G$7:$G$740,'1. Status Resumo FY24'!$P106,'2. Status Detalhe Campos FY24'!$C$7:$C$740,'1. Status Resumo FY24'!$G$93,'2. Status Detalhe Campos FY24'!$D$7:$D$740,"2. Campo")+COUNTIFS('2. Status Detalhe Campos FY24'!$G$7:$G$740,'1. Status Resumo FY24'!$P106,'2. Status Detalhe Campos FY24'!$C$7:$C$740,'1. Status Resumo FY24'!$H$93,'2. Status Detalhe Campos FY24'!$D$7:$D$740,"2. Campo") -> 0 | V106: =U106-T106 -> 0
P107: Requisitos FY24 | T107: =COUNTIFS('2. Status Detalhe Campos FY24'!$H$7:$H$740,'1. Status Resumo FY24'!$P106,'2. Status Detalhe Campos FY24'!$C$7:$C$740,'1. Status Resumo FY24'!$G$93,'2. Status Detalhe Campos FY24'!$D$7:$D$740,"2. Campo",'2. Status Detalhe Campos FY24'!$Y$7:$Y$740,"*Plano anterior*") +COUNTIFS('2. Status Detalhe Campos FY24'!$H$7:$H$740,'1. Status Resumo FY24'!$P106,'2. Status Detalhe Campos FY24'!$C$7:$C$740,'1. Status Resumo FY24'!$H$93,'2. Status Detalhe Campos FY24'!$D$7:$D$740,"2. Campo",'2. Status Detalhe Campos FY24'!$Y$7:$Y$740,"*Plano anterior*") -> 0 | U107: =COUNTIFS('2. Status Detalhe Campos FY24'!$G$7:$G$740,'1. Status Resumo FY24'!$P106,'2. Status Detalhe Campos FY24'!$C$7:$C$740,'1. Status Resumo FY24'!$G$93,'2. Status Detalhe Campos FY24'!$D$7:$D$740,"2. Campo",'2. Status Detalhe Campos FY24'!$Y$7:$Y$740,"*Plano anterior*") +COUNTIFS('2. Status Detalhe Campos FY24'!$G$7:$G$740,'1. Status Resumo FY24'!$P106,'2. Status Detalhe Campos FY24'!$C$7:$C$740,'1. Status Resumo FY24'!$H$93,'2. Status Detalhe Campos FY24'!$D$7:$D$740,"2. Campo",'2. Status Detalhe Campos FY24'!$Y$7:$Y$740,"*Plano anterior*") -> 0 | V107: =U107-T107 -> 0
P108: Novos Requisitos FY25 | T108: =COUNTIFS('2. Status Detalhe Campos FY24'!$H$7:$H$740,'1. Status Resumo FY24'!$P106,'2. Status Detalhe Campos FY24'!$C$7:$C$740,'1. Status Resumo FY24'!$G$93,'2. Status Detalhe Campos FY24'!$D$7:$D$740,"2. Campo",'2. Status Detalhe Campos FY24'!$Y$7:$Y$740,"*Novo Plano*") +COUNTIFS('2. Status Detalhe Campos FY24'!$H$7:$H$740,'1. Status Resumo FY24'!$P106,'2. Status Detalhe Campos FY24'!$C$7:$C$740,'1. Status Resumo FY24'!$H$93,'2. Status Detalhe Campos FY24'!$D$7:$D$740,"2. Campo",'2. Status Detalhe Campos FY24'!$Y$7:$Y$740,"*Novo Plano*") -> 0 | U108: =COUNTIFS('2. Status Detalhe Campos FY24'!$G$7:$G$740,'1. Status Resumo FY24'!$P106,'2. Status Detalhe Campos FY24'!$C$7:$C$740,'1. Status Resumo FY24'!$G$93,'2. Status Detalhe Campos FY24'!$D$7:$D$740,"2. Campo",'2. Status Detalhe Campos FY24'!$Y$7:$Y$740,"*Novo Plano*") +COUNTIFS('2. Status Detalhe Campos FY24'!$G$7:$G$740,'1. Status Resumo FY24'!$P106,'2. Status Detalhe Campos FY24'!$C$7:$C$740,'1. Status Resumo FY24'!$H$93,'2. Status Detalhe Campos FY24'!$D$7:$D$740,"2. Campo",'2. Status Detalhe Campos FY24'!$Y$7:$Y$740,"*Novo Plano*") -> 0 | V108: =U108-T108 -> 0
D109: =+"#"&$U$124 -> #302 | P109: 3. Pendente de outros desenvolvimentos | T109: =COUNTIFS('2. Status Detalhe Campos FY24'!$H$7:$H$740,'1. Status Resumo FY24'!$P109,'2. Status Detalhe Campos FY24'!$C$7:$C$740,'1. Status Resumo FY24'!$G$93,'2. Status Detalhe Campos FY24'!$D$7:$D$740,"2. Campo")+COUNTIFS('2. Status Detalhe Campos FY24'!$H$7:$H$740,'1. Status Resumo FY24'!$P109,'2. Status Detalhe Campos FY24'!$C$7:$C$740,'1. Status Resumo FY24'!$H$93,'2. Status Detalhe Campos FY24'!$D$7:$D$740,"2. Campo") -> 0 | U109: =COUNTIFS('2. Status Detalhe Campos FY24'!$G$7:$G$740,'1. Status Resumo FY24'!$P109,'2. Status Detalhe Campos FY24'!$C$7:$C$740,'1. Status Resumo FY24'!$G$93,'2. Status Detalhe Campos FY24'!$D$7:$D$740,"2. Campo")+COUNTIFS('2. Status Detalhe Campos FY24'!$G$7:$G$740,'1. Status Resumo FY24'!$P109,'2. Status Detalhe Campos FY24'!$C$7:$C$740,'1. Status Resumo FY24'!$H$93,'2. Status Detalhe Campos FY24'!$D$7:$D$740,"2. Campo") -> 0 | V109: =U109-T109 -> 0
P110: Requisitos FY24 | T110: =COUNTIFS('2. Status Detalhe Campos FY24'!$H$7:$H$740,'1. Status Resumo FY24'!$P109,'2. Status Detalhe Campos FY24'!$C$7:$C$740,'1. Status Resumo FY24'!$G$93,'2. Status Detalhe Campos FY24'!$D$7:$D$740,"2. Campo",'2. Status Detalhe Campos FY24'!$Y$7:$Y$740,"*Plano anterior*") +COUNTIFS('2. Status Detalhe Campos FY24'!$H$7:$H$740,'1. Status Resumo FY24'!$P109,'2. Status Detalhe Campos FY24'!$C$7:$C$740,'1. Status Resumo FY24'!$H$93,'2. Status Detalhe Campos FY24'!$D$7:$D$740,"2. Campo",'2. Status Detalhe Campos FY24'!$Y$7:$Y$740,"*Plano anterior*") -> 0 | U110: =COUNTIFS('2. Status Detalhe Campos FY24'!$G$7:$G$740,'1. Status Resumo FY24'!$P109,'2. Status Detalhe Campos FY24'!$C$7:$C$740,'1. Status Resumo FY24'!$G$93,'2. Status Detalhe Campos FY24'!$D$7:$D$740,"2. Campo",'2. Status Detalhe Campos FY24'!$Y$7:$Y$740,"*Plano anterior*") +COUNTIFS('2. Status Detalhe Campos FY24'!$G$7:$G$740,'1. Status Resumo FY24'!$P109,'2. Status Detalhe Campos FY24'!$C$7:$C$740,'1. Status Resumo FY24'!$H$93,'2. Status Detalhe Campos FY24'!$D$7:$D$740,"2. Campo",'2. Status Detalhe Campos FY24'!$Y$7:$Y$740,"*Plano anterior*") -> 0 | V110: =U110-T110 -> 0
P111: Novos Requisitos FY25 | T111: =COUNTIFS('2. Status Detalhe Campos FY24'!$H$7:$H$740,'1. Status Resumo FY24'!$P109,'2. Status Detalhe Campos FY24'!$C$7:$C$740,'1. Status Resumo FY24'!$G$93,'2. Status Detalhe Campos FY24'!$D$7:$D$740,"2. Campo",'2. Status Detalhe Campos FY24'!$Y$7:$Y$740,"*Novo Plano*") +COUNTIFS('2. Status Detalhe Campos FY24'!$H$7:$H$740,'1. Status Resumo FY24'!$P109,'2. Status Detalhe Campos FY24'!$C$7:$C$740,'1. Status Resumo FY24'!$H$93,'2. Status Detalhe Campos FY24'!$D$7:$D$740,"2. Campo",'2. Status Detalhe Campos FY24'!$Y$7:$Y$740,"*Novo Plano*") -> 0 | U111: =COUNTIFS('2. Status Detalhe Campos FY24'!$G$7:$G$740,'1. Status Resumo FY24'!$P109,'2. Status Detalhe Campos FY24'!$C$7:$C$740,'1. Status Resumo FY24'!$G$93,'2. Status Detalhe Campos FY24'!$D$7:$D$740,"2. Campo",'2. Status Detalhe Campos FY24'!$Y$7:$Y$740,"*Novo Plano*") +COUNTIFS('2. Status Detalhe Campos FY24'!$G$7:$G$740,'1. Status Resumo FY24'!$P109,'2. Status Detalhe Campos FY24'!$C$7:$C$740,'1. Status Resumo FY24'!$H$93,'2. Status Detalhe Campos FY24'!$D$7:$D$740,"2. Campo",'2. Status Detalhe Campos FY24'!$Y$7:$Y$740,"*Novo Plano*") -> 0 | V111: =U111-T111 -> 0
P112: 4. Validação EF | T112: =COUNTIFS('2. Status Detalhe Campos FY24'!$H$7:$H$740,'1. Status Resumo FY24'!$P112,'2. Status Detalhe Campos FY24'!$C$7:$C$740,'1. Status Resumo FY24'!$G$93,'2. Status Detalhe Campos FY24'!$D$7:$D$740,"2. Campo")+COUNTIFS('2. Status Detalhe Campos FY24'!$H$7:$H$740,'1. Status Resumo FY24'!$P112,'2. Status Detalhe Campos FY24'!$C$7:$C$740,'1. Status Resumo FY24'!$H$93,'2. Status Detalhe Campos FY24'!$D$7:$D$740,"2. Campo") -> 0 | U112: =COUNTIFS('2. Status Detalhe Campos FY24'!$G$7:$G$740,'1. Status Resumo FY24'!$P112,'2. Status Detalhe Campos FY24'!$C$7:$C$740,'1. Status Resumo FY24'!$G$93,'2. Status Detalhe Campos FY24'!$D$7:$D$740,"2. Campo")+COUNTIFS('2. Status Detalhe Campos FY24'!$G$7:$G$740,'1. Status Resumo FY24'!$P112,'2. Status Detalhe Campos FY24'!$C$7:$C$740,'1. Status Resumo FY24'!$H$93,'2. Status Detalhe Campos FY24'!$D$7:$D$740,"2. Campo") -> 0 | V112: =U112-T112 -> 0
P113: Requisitos FY24 | T113: =COUNTIFS('2. Status Detalhe Campos FY24'!$H$7:$H$740,'1. Status Resumo FY24'!$P112,'2. Status Detalhe Campos FY24'!$C$7:$C$740,'1. Status Resumo FY24'!$G$93,'2. Status Detalhe Campos FY24'!$D$7:$D$740,"2. Campo",'2. Status Detalhe Campos FY24'!$Y$7:$Y$740,"*Plano anterior*") +COUNTIFS('2. Status Detalhe Campos FY24'!$H$7:$H$740,'1. Status Resumo FY24'!$P112,'2. Status Detalhe Campos FY24'!$C$7:$C$740,'1. Status Resumo FY24'!$H$93,'2. Status Detalhe Campos FY24'!$D$7:$D$740,"2. Campo",'2. Status Detalhe Campos FY24'!$Y$7:$Y$740,"*Plano anterior*") -> 0 | U113: =COUNTIFS('2. Status Detalhe Campos FY24'!$G$7:$G$740,'1. Status Resumo FY24'!$P112,'2. Status Detalhe Campos FY24'!$C$7:$C$740,'1. Status Resumo FY24'!$G$93,'2. Status Detalhe Campos FY24'!$D$7:$D$740,"2. Campo",'2. Status Detalhe Campos FY24'!$Y$7:$Y$740,"*Plano anterior*") +COUNTIFS('2. Status Detalhe Campos FY24'!$G$7:$G$740,'1. Status Resumo FY24'!$P112,'2. Status Detalhe Campos FY24'!$C$7:$C$740,'1. Status Resumo FY24'!$H$93,'2. Status Detalhe Campos FY24'!$D$7:$D$740,"2. Campo",'2. Status Detalhe Campos FY24'!$Y$7:$Y$740,"*Plano anterior*") -> 0 | V113: =U113-T113 -> 0
P114: Novos Requisitos FY25 | T114: =COUNTIFS('2. Status Detalhe Campos FY24'!$H$7:$H$740,'1. Status Resumo FY24'!$P112,'2. Status Detalhe Campos FY24'!$C$7:$C$740,'1. Status Resumo FY24'!$G$93,'2. Status Detalhe Campos FY24'!$D$7:$D$740,"2. Campo",'2. Status Detalhe Campos FY24'!$Y$7:$Y$740,"*Novo Plano*") +COUNTIFS('2. Status Detalhe Campos FY24'!$H$7:$H$740,'1. Status Resumo FY24'!$P112,'2. Status Detalhe Campos FY24'!$C$7:$C$740,'1. Status Resumo FY24'!$H$93,'2. Status Detalhe Campos FY24'!$D$7:$D$740,"2. Campo",'2. Status Detalhe Campos FY24'!$Y$7:$Y$740,"*Novo Plano*") -> 0 | U114: =COUNTIFS('2. Status Detalhe Campos FY24'!$G$7:$G$740,'1. Status Resumo FY24'!$P112,'2. Status Detalhe Campos FY24'!$C$7:$C$740,'1. Status Resumo FY24'!$G$93,'2. Status Detalhe Campos FY24'!$D$7:$D$740,"2. Campo",'2. Status Detalhe Campos FY24'!$Y$7:$Y$740,"*Novo Plano*") +COUNTIFS('2. Status Detalhe Campos FY24'!$G$7:$G$740,'1. Status Resumo FY24'!$P112,'2. Status Detalhe Campos FY24'!$C$7:$C$740,'1. Status Resumo FY24'!$H$93,'2. Status Detalhe Campos FY24'!$D$7:$D$740,"2. Campo",'2. Status Detalhe Campos FY24'!$Y$7:$Y$740,"*Novo Plano*") -> 0 | V114: =U114-T114 -> 0
P115: 5. Em Correção | R115: (incidências) | T115: =COUNTIFS('2. Status Detalhe Campos FY24'!$H$7:$H$740,'1. Status Resumo FY24'!$P115,'2. Status Detalhe Campos FY24'!$C$7:$C$740,'1. Status Resumo FY24'!$G$93,'2. Status Detalhe Campos FY24'!$D$7:$D$740,"2. Campo")+COUNTIFS('2. Status Detalhe Campos FY24'!$H$7:$H$740,'1. Status Resumo FY24'!$P115,'2. Status Detalhe Campos FY24'!$C$7:$C$740,'1. Status Resumo FY24'!$H$93,'2. Status Detalhe Campos FY24'!$D$7:$D$740,"2. Campo") -> 0 | U115: =COUNTIFS('2. Status Detalhe Campos FY24'!$G$7:$G$740,'1. Status Resumo FY24'!$P115,'2. Status Detalhe Campos FY24'!$C$7:$C$740,'1. Status Resumo FY24'!$G$93,'2. Status Detalhe Campos FY24'!$D$7:$D$740,"2. Campo")+COUNTIFS('2. Status Detalhe Campos FY24'!$G$7:$G$740,'1. Status Resumo FY24'!$P115,'2. Status Detalhe Campos FY24'!$C$7:$C$740,'1. Status Resumo FY24'!$H$93,'2. Status Detalhe Campos FY24'!$D$7:$D$740,"2. Campo") -> 0 | V115: =U115-T115 -> 0
P116: Requisitos FY24 | T116: =COUNTIFS('2. Status Detalhe Campos FY24'!$H$7:$H$740,'1. Status Resumo FY24'!$P115,'2. Status Detalhe Campos FY24'!$C$7:$C$740,'1. Status Resumo FY24'!$G$93,'2. Status Detalhe Campos FY24'!$D$7:$D$740,"2. Campo",'2. Status Detalhe Campos FY24'!$Y$7:$Y$740,"*Plano anterior*") +COUNTIFS('2. Status Detalhe Campos FY24'!$H$7:$H$740,'1. Status Resumo FY24'!$P115,'2. Status Detalhe Campos FY24'!$C$7:$C$740,'1. Status Resumo FY24'!$H$93,'2. Status Detalhe Campos FY24'!$D$7:$D$740,"2. Campo",'2. Status Detalhe Campos FY24'!$Y$7:$Y$740,"*Plano anterior*") -> 0 | U116: =COUNTIFS('2. Status Detalhe Campos FY24'!$G$7:$G$740,'1. Status Resumo FY24'!$P115,'2. Status Detalhe Campos FY24'!$C$7:$C$740,'1. Status Resumo FY24'!$G$93,'2. Status Detalhe Campos FY24'!$D$7:$D$740,"2. Campo",'2. Status Detalhe Campos FY24'!$Y$7:$Y$740,"*Plano anterior*") +COUNTIFS('2. Status Detalhe Campos FY24'!$G$7:$G$740,'1. Status Resumo FY24'!$P115,'2. Status Detalhe Campos FY24'!$C$7:$C$740,'1. Status Resumo FY24'!$H$93,'2. Status Detalhe Campos FY24'!$D$7:$D$740,"2. Campo",'2. Status Detalhe Campos FY24'!$Y$7:$Y$740,"*Plano anterior*") -> 0 | V116: =U116-T116 -> 0
P117: Novos Requisitos FY25 | T117: =COUNTIFS('2. Status Detalhe Campos FY24'!$H$7:$H$740,'1. Status Resumo FY24'!$P115,'2. Status Detalhe Campos FY24'!$C$7:$C$740,'1. Status Resumo FY24'!$G$93,'2. Status Detalhe Campos FY24'!$D$7:$D$740,"2. Campo",'2. Status Detalhe Campos FY24'!$Y$7:$Y$740,"*Novo Plano*") +COUNTIFS('2. Status Detalhe Campos FY24'!$H$7:$H$740,'1. Status Resumo FY24'!$P115,'2. Status Detalhe Campos FY24'!$C$7:$C$740,'1. Status Resumo FY24'!$H$93,'2. Status Detalhe Campos FY24'!$D$7:$D$740,"2. Campo",'2. Status Detalhe Campos FY24'!$Y$7:$Y$740,"*Novo Plano*") -> 0 | U117: =COUNTIFS('2. Status Detalhe Campos FY24'!$G$7:$G$740,'1. Status Resumo FY24'!$P115,'2. Status Detalhe Campos FY24'!$C$7:$C$740,'1. Status Resumo FY24'!$G$93,'2. Status Detalhe Campos FY24'!$D$7:$D$740,"2. Campo",'2. Status Detalhe Campos FY24'!$Y$7:$Y$740,"*Novo Plano*") +COUNTIFS('2. Status Detalhe Campos FY24'!$G$7:$G$740,'1. Status Resumo FY24'!$P115,'2. Status Detalhe Campos FY24'!$C$7:$C$740,'1. Status Resumo FY24'!$H$93,'2. Status Detalhe Campos FY24'!$D$7:$D$740,"2. Campo",'2. Status Detalhe Campos FY24'!$Y$7:$Y$740,"*Novo Plano*") -> 0 | V117: =U117-T117 -> 0
P118: 6. Em implementação | T118: =COUNTIFS('2. Status Detalhe Campos FY24'!$H$7:$H$740,'1. Status Resumo FY24'!$P118,'2. Status Detalhe Campos FY24'!$C$7:$C$740,'1. Status Resumo FY24'!$G$93,'2. Status Detalhe Campos FY24'!$D$7:$D$740,"2. Campo")+COUNTIFS('2. Status Detalhe Campos FY24'!$H$7:$H$740,'1. Status Resumo FY24'!$P118,'2. Status Detalhe Campos FY24'!$C$7:$C$740,'1. Status Resumo FY24'!$H$93,'2. Status Detalhe Campos FY24'!$D$7:$D$740,"2. Campo") -> 0 | U118: =COUNTIFS('2. Status Detalhe Campos FY24'!$G$7:$G$740,'1. Status Resumo FY24'!$P118,'2. Status Detalhe Campos FY24'!$C$7:$C$740,'1. Status Resumo FY24'!$G$93,'2. Status Detalhe Campos FY24'!$D$7:$D$740,"2. Campo")+COUNTIFS('2. Status Detalhe Campos FY24'!$G$7:$G$740,'1. Status Resumo FY24'!$P118,'2. Status Detalhe Campos FY24'!$C$7:$C$740,'1. Status Resumo FY24'!$H$93,'2. Status Detalhe Campos FY24'!$D$7:$D$740,"2. Campo") -> 0 | V118: =U118-T118 -> 0
P119: Requisitos FY24 | T119: =COUNTIFS('2. Status Detalhe Campos FY24'!$H$7:$H$740,'1. Status Resumo FY24'!$P118,'2. Status Detalhe Campos FY24'!$C$7:$C$740,'1. Status Resumo FY24'!$G$93,'2. Status Detalhe Campos FY24'!$D$7:$D$740,"2. Campo",'2. Status Detalhe Campos FY24'!$Y$7:$Y$740,"*Plano anterior*") +COUNTIFS('2. Status Detalhe Campos FY24'!$H$7:$H$740,'1. Status Resumo FY24'!$P118,'2. Status Detalhe Campos FY24'!$C$7:$C$740,'1. Status Resumo FY24'!$H$93,'2. Status Detalhe Campos FY24'!$D$7:$D$740,"2. Campo",'2. Status Detalhe Campos FY24'!$Y$7:$Y$740,"*Plano anterior*") -> 0 | U119: =COUNTIFS('2. Status Detalhe Campos FY24'!$G$7:$G$740,'1. Status Resumo FY24'!$P118,'2. Status Detalhe Campos FY24'!$C$7:$C$740,'1. Status Resumo FY24'!$G$93,'2. Status Detalhe Campos FY24'!$D$7:$D$740,"2. Campo",'2. Status Detalhe Campos FY24'!$Y$7:$Y$740,"*Plano anterior*") +COUNTIFS('2. Status Detalhe Campos FY24'!$G$7:$G$740,'1. Status Resumo FY24'!$P118,'2. Status Detalhe Campos FY24'!$C$7:$C$740,'1. Status Resumo FY24'!$H$93,'2. Status Detalhe Campos FY24'!$D$7:$D$740,"2. Campo",'2. Status Detalhe Campos FY24'!$Y$7:$Y$740,"*Plano anterior*") -> 0 | V119: =U119-T119 -> 0
P120: Novos Requisitos FY25 | T120: =COUNTIFS('2. Status Detalhe Campos FY24'!$H$7:$H$740,'1. Status Resumo FY24'!$P118,'2. Status Detalhe Campos FY24'!$C$7:$C$740,'1. Status Resumo FY24'!$G$93,'2. Status Detalhe Campos FY24'!$D$7:$D$740,"2. Campo",'2. Status Detalhe Campos FY24'!$Y$7:$Y$740,"*Novo Plano*") +COUNTIFS('2. Status Detalhe Campos FY24'!$H$7:$H$740,'1. Status Resumo FY24'!$P118,'2. Status Detalhe Campos FY24'!$C$7:$C$740,'1. Status Resumo FY24'!$H$93,'2. Status Detalhe Campos FY24'!$D$7:$D$740,"2. Campo",'2. Status Detalhe Campos FY24'!$Y$7:$Y$740,"*Novo Plano*") -> 0 | U120: =COUNTIFS('2. Status Detalhe Campos FY24'!$G$7:$G$740,'1. Status Resumo FY24'!$P118,'2. Status Detalhe Campos FY24'!$C$7:$C$740,'1. Status Resumo FY24'!$G$93,'2. Status Detalhe Campos FY24'!$D$7:$D$740,"2. Campo",'2. Status Detalhe Campos FY24'!$Y$7:$Y$740,"*Novo Plano*") +COUNTIFS('2. Status Detalhe Campos FY24'!$G$7:$G$740,'1. Status Resumo FY24'!$P118,'2. Status Detalhe Campos FY24'!$C$7:$C$740,'1. Status Resumo FY24'!$H$93,'2. Status Detalhe Campos FY24'!$D$7:$D$740,"2. Campo",'2. Status Detalhe Campos FY24'!$Y$7:$Y$740,"*Novo Plano*") -> 0 | V120: =U120-T120 -> 0
P121: 7. Por iniciar | T121: =COUNTIFS('2. Status Detalhe Campos FY24'!$H$7:$H$740,'1. Status Resumo FY24'!$P121,'2. Status Detalhe Campos FY24'!$C$7:$C$740,'1. Status Resumo FY24'!$G$93,'2. Status Detalhe Campos FY24'!$D$7:$D$740,"2. Campo")+COUNTIFS('2. Status Detalhe Campos FY24'!$H$7:$H$740,'1. Status Resumo FY24'!$P121,'2. Status Detalhe Campos FY24'!$C$7:$C$740,'1. Status Resumo FY24'!$H$93,'2. Status Detalhe Campos FY24'!$D$7:$D$740,"2. Campo") -> 0 | U121: =COUNTIFS('2. Status Detalhe Campos FY24'!$G$7:$G$740,'1. Status Resumo FY24'!$P121,'2. Status Detalhe Campos FY24'!$C$7:$C$740,'1. Status Resumo FY24'!$G$93,'2. Status Detalhe Campos FY24'!$D$7:$D$740,"2. Campo")+COUNTIFS('2. Status Detalhe Campos FY24'!$G$7:$G$740,'1. Status Resumo FY24'!$P121,'2. Status Detalhe Campos FY24'!$C$7:$C$740,'1. Status Resumo FY24'!$H$93,'2. Status Detalhe Campos FY24'!$D$7:$D$740,"2. Campo") -> 0 | V121: =U121-T121 -> 0
P122: Requisitos FY24 | T122: =COUNTIFS('2. Status Detalhe Campos FY24'!$H$7:$H$740,'1. Status Resumo FY24'!$P121,'2. Status Detalhe Campos FY24'!$C$7:$C$740,'1. Status Resumo FY24'!$G$93,'2. Status Detalhe Campos FY24'!$D$7:$D$740,"2. Campo",'2. Status Detalhe Campos FY24'!$Y$7:$Y$740,"*Plano anterior*") +COUNTIFS('2. Status Detalhe Campos FY24'!$H$7:$H$740,'1. Status Resumo FY24'!$P121,'2. Status Detalhe Campos FY24'!$C$7:$C$740,'1. Status Resumo FY24'!$H$93,'2. Status Detalhe Campos FY24'!$D$7:$D$740,"2. Campo",'2. Status Detalhe Campos FY24'!$Y$7:$Y$740,"*Plano anterior*") -> 0 | U122: =COUNTIFS('2. Status Detalhe Campos FY24'!$G$7:$G$740,'1. Status Resumo FY24'!$P121,'2. Status Detalhe Campos FY24'!$C$7:$C$740,'1. Status Resumo FY24'!$G$93,'2. Status Detalhe Campos FY24'!$D$7:$D$740,"2. Campo",'2. Status Detalhe Campos FY24'!$Y$7:$Y$740,"*Plano anterior*") +COUNTIFS('2. Status Detalhe Campos FY24'!$G$7:$G$740,'1. Status Resumo FY24'!$P121,'2. Status Detalhe Campos FY24'!$C$7:$C$740,'1. Status Resumo FY24'!$H$93,'2. Status Detalhe Campos FY24'!$D$7:$D$740,"2. Campo",'2. Status Detalhe Campos FY24'!$Y$7:$Y$740,"*Plano anterior*") -> 0 | V122: =U122-T122 -> 0
P123: Novos Requisitos FY25 | T123: =COUNTIFS('2. Status Detalhe Campos FY24'!$H$7:$H$740,'1. Status Resumo FY24'!$P121,'2. Status Detalhe Campos FY24'!$C$7:$C$740,'1. Status Resumo FY24'!$G$93,'2. Status Detalhe Campos FY24'!$D$7:$D$740,"2. Campo",'2. Status Detalhe Campos FY24'!$Y$7:$Y$740,"*Novo Plano*") +COUNTIFS('2. Status Detalhe Campos FY24'!$H$7:$H$740,'1. Status Resumo FY24'!$P121,'2. Status Detalhe Campos FY24'!$C$7:$C$740,'1. Status Resumo FY24'!$H$93,'2. Status Detalhe Campos FY24'!$D$7:$D$740,"2. Campo",'2. Status Detalhe Campos FY24'!$Y$7:$Y$740,"*Novo Plano*") -> 0 | U123: =COUNTIFS('2. Status Detalhe Campos FY24'!$G$7:$G$740,'1. Status Resumo FY24'!$P121,'2. Status Detalhe Campos FY24'!$C$7:$C$740,'1. Status Resumo FY24'!$G$93,'2. Status Detalhe Campos FY24'!$D$7:$D$740,"2. Campo",'2. Status Detalhe Campos FY24'!$Y$7:$Y$740,"*Novo Plano*") +COUNTIFS('2. Status Detalhe Campos FY24'!$G$7:$G$740,'1. Status Resumo FY24'!$P121,'2. Status Detalhe Campos FY24'!$C$7:$C$740,'1. Status Resumo FY24'!$H$93,'2. Status Detalhe Campos FY24'!$D$7:$D$740,"2. Campo",'2. Status Detalhe Campos FY24'!$Y$7:$Y$740,"*Novo Plano*") -> 0 | V123: =U123-T123 -> 0
P124: Total | T124: =+SUM(T97,T100,T103,T109,T112,T115,T118,T121,T106) -> 302 | U124: =+SUM(U97,U100,U103,U109,U112,U115,U118,U121,U106) -> 302 | V124: =+U124-T124 -> 0
...

Sheet Auxiliar
D2: Estimação Horas
B3: Tipologia de testes | D3: Complexidade
B4: Categorização de Testes | C4: Descrição | D4: Baixa | E4: Média | F4: Alta | H4: Baixa | I4: Média | J4: Alta
B5: 1. Teste de universo | C5: 1. Validação de universo de contratos (quando comparado âmbito "CDG" e "PM", e numero de registos) 2. Controlos sobre o desdobramento de chaves nas relações FR-MIS | D5: 8 | E5: 8 | F5: 8 | H5: 1 | I5: 3 | J5: 8
B6: 2. Simulação | C6: Simulação da especificação funcional. Suplementarmente, realizar reuniões de validações e esclarecimentos funcionais junto do negócio/owner. | D6: 2 | E6: 4 | F6: 8 | H6: 1 | I6: 3 | J6: 4
B7: 3. Testes comparativos (Espec. VS Impl.) | C7: A partir da simulação realizada, comparar resultados com a implementação de IT. | D7: 2 | E7: 4 | F7: 8 | H7: 1 | I7: 1 | J7: 2
B8: 4. Validação de parametrizações | C8: A partir da simulação realizada, comparar com as parametrizações implementadas por IT. | D8: 2 | E8: 4 | F8: 8 | H8: 2 | I8: 4 | J8: 4
B9: 5. Teste comparativos com LT | C9: Garantir que a informação do campo da LT-ESTR âmbito 'PM' está espelhado no âmbito 'CDG'. | D9: 1 | E9: 1 | F9: 1
B10: 6. Validação de formatos | C10: Validação de formato de acordo com o que é esperado pela Corporação (incluindo validação de codelists, missing e default values) Validar especificação e controlos da especificação vs o que está implementado | D10: 0.1 | E10: 0.1 | F10: 0.1 | H10: 0.1 | I10: 0.5 | J10: 0.5
B11: 7. Validação de controlos corporativos | C11: Validar controlos corporativos e se a especificação cumpre os requisitos. | D11: 1 | E11: 2 | F11: 2
B12: 8. Teste de Carregamento | C12: Garantir que o carregamento do ficheiro é realizado com sucesso no Front. | D12: 0.5 | E12: 0.5 | F12: 0.5 | H12: 0.5 | I12: 0.5 | J12: 0.5
B13: 9. Teste de Integridade | C13: Garantir integridade entre o ficheiro importado pela equipa de testes e o ficheiro de tecnologia (Ex: Garantir que a informação de todos os campos está correta de acordo com os dados corporativos) | D13: 0.5 | E13: 0.5 | F13: 0.5 | H13: 0.5 | I13: 0.5 | J13: 0.5
B15: Status
B16: 1. Concluído | C16: =_xlfn.NUMBERVALUE(LEFT(B16,1)) -> 1 | D16: 1 | E16: 1
A17: Pendente de outros campos/tabelas | B17: 3. Pendente de outros desenvolvimentos | C17: 4 | D17: 0.25 | E17: 0
B18: 7. Por iniciar | C18: 8 | D18: 0 | E18: 0
B19: 2.1 Em Teste | C19: =_xlfn.NUMBERVALUE(LEFT(B19,1)) -> 2 | D19: 0.5 | E19: 0.25
B20: 2.2 Em especificação | C20: 3 | D20: 0.5 | E20: 0
A21: Validação da Susana/LCM/Corp/conceito/alterações | B21: 4. Validação EF | C21: 5 | D21: 0.25 | E21: 0.25
A22: Por IT | B22: 5. Em Correção | C22: 6 | D22: 0.25 | E22: 0
A23: Por IT | B23: 6. Em implementação | C23: 7 | D23: 0.25 | E23: 0
A24: Campo eliminado | B24: 0. Cancelado | C24: =_xlfn.NUMBERVALUE(LEFT(B24,1)) -> 0 | D24: 0 | E24: 0

Sheet 2. Status Detalhe Campos FY24
J5: APAGAR | K5: APAGAR | O5: APAGAR | U5: APAGAR | V5: APAGAR | X5: APAGAR | Y5: APAGAR | Z5: APAGAR
B6: Âmbito | C6: Sub-âmbito | D6: Tipo de teste | E6: Tabela | F6: Campo | G6: Status Atual | H6: Status Anterior | I6: Fase | J6: Observações - Especificações | K6: Observações - Testes | L6: Data Final - Entrega IT | M6: Data Final - Validação Testes | N6: Tipologia Teste | O6: Observações - Testes sem visibilidade | P6: Data de Pedido correção/esclarecimento | Q6: Data de correção prevista | R6: Data de correção efetiva | S6: Data Prevista de Re-especificação | T6: Data Prevista de Teste | U6: Projeto (Aux JB) | V6: LT Âmbito | W6: Âmbito Testes | X6: LT Âmbito- Aux | Y6: Plano | Z6: Owner
A7: =E7&F7 -> PROPERTY_ENERGY_CERTIFICATECURRENT_ENERGY_RATING_PERCENTAGE | B7: Pilar III | C7: Bens Imóveis - Output | D7: 2. Campo | E7: PROPERTY_ENERGY_CERTIFICATE | F7: CURRENT_ENERGY_RATING_PERCENTAGE | G7: =VLOOKUP(A7,Plano_V3!$A$26:$G$768,7,0) -> 1. Concluído | H7: 1. Concluído | J7: Package 1 | K7: Package 22 | L7: 45730 | M7: 45737 | P7: =IF(VLOOKUP(A7,'Aux - pivots1'!$A:$E,3,0)=0, "",VLOOKUP(A7,'Aux - pivots1'!$A:$E,3,0)) | Q7: =IF(VLOOKUP(A7,'Aux - pivots1'!$A:$E,4,0)=0, "",VLOOKUP(A7,'Aux - pivots1'!$A:$E,4,0)) | R7: =IF(VLOOKUP(A7,'Aux - pivots1'!$A:$E,5,0)=0, "",VLOOKUP(A7,'Aux - pivots1'!$A:$E,5,0)) | Y7: Plano anterior | Z7: HF
A8: =E8&F8 -> lt002_instrumentOFF_BLNC_SHT_AMNT_INSTRMNT | B8: Pilar III | C8: Pilar III | D8: 2. Campo | E8: lt002_instrument | F8: OFF_BLNC_SHT_AMNT_INSTRMNT | G8: =VLOOKUP(A8,Plano_V3!$A$26:$G$768,7,0) -> 6. Em implementação | H8: 6. Em implementação | J8: Package 4 | K8: Package 26 | L8: 45764 | M8: 45771 | N8: Testes Regressivos (LT Estr) | P8: =IF(VLOOKUP(A8,'Aux - pivots1'!$A:$E,3,0)=0, "",VLOOKUP(A8,'Aux - pivots1'!$A:$E,3,0)) | Q8: =IF(VLOOKUP(A8,'Aux - pivots1'!$A:$E,4,0)=0, "",VLOOKUP(A8,'Aux - pivots1'!$A:$E,4,0)) | R8: =IF(VLOOKUP(A8,'Aux - pivots1'!$A:$E,5,0)=0, "",VLOOKUP(A8,'Aux - pivots1'!$A:$E,5,0)) | U8: Novo Projeto - Em especificação | V8: ESTR, GD, GF, ESG e LF | W8: FY25 | X8: Novos Requisitos FY25 - Âmbito ESTR e (ou) LF | Y8: Novo Plano | Z8: HF
A9: =E9&F9 -> lt003_entityec_grp_id | B9: Pilar III | C9: Pilar III | D9: 2. Campo | E9: lt003_entity | F9: ec_grp_id | G9: =VLOOKUP(A9,Plano_V3!$A$26:$G$768,7,0) -> 5. Em Correção | H9: 5. Em Correção | J9: Package 4 | K9: Package 23 | L9: 45744 | M9: 45751 | N9: Testes Regressivos (LT Estr) | P9: =IF(VLOOKUP(A9,'Aux - pivots1'!$A:$E,3,0)=0, "",VLOOKUP(A9,'Aux - pivots1'!$A:$E,3,0)) | Q9: =IF(VLOOKUP(A9,'Aux - pivots1'!$A:$E,4,0)=0, "",VLOOKUP(A9,'Aux - pivots1'!$A:$E,4,0)) | R9: =IF(VLOOKUP(A9,'Aux - pivots1'!$A:$E,5,0)=0, "",VLOOKUP(A9,'Aux - pivots1'!$A:$E,5,0)) | U9: Novo Projeto - Em especificação | V9: ESTR, P3, GF e LF | W9: FY25 | X9: Novos Requisitos FY25 - Âmbito ESTR e (ou) LF | Y9: Novo Plano | Z9: JB
A10: =E10&F10 -> lt003_entityec_grp_nm | B10: Pilar III | C10: Pilar III | D10: 2. Campo | E10: lt003_entity | F10: ec_grp_nm | G10: =VLOOKUP(A10,Plano_V3!$A$26:$G$768,7,0) -> 5. Em Correção | H10: 5. Em Correção | J10: Package 4 | K10: Package 23 | L10: 45744 | M10: 45751 | N10: Testes Regressivos (LT Estr) | P10: =IF(VLOOKUP(A10,'Aux - pivots1'!$A:$E,3,0)=0, "",VLOOKUP(A10,'Aux - pivots1'!$A:$E,3,0)) | Q10: =IF(VLOOKUP(A10,'Aux - pivots1'!$A:$E,4,0)=0, "",VLOOKUP(A10,'Aux - pivots1'!$A:$E,4,0)) | R10: =IF(VLOOKUP(A10,'Aux - pivots1'!$A:$E,5,0)=0, "",VLOOKUP(A10,'Aux - pivots1'!$A:$E,5,0)) | U10: Novo Projeto - Em especificação | V10: ESTR, P3, GF e LF | W10: FY25 | X10: Novos Requisitos FY25 - Âmbito ESTR e (ou) LF | Y10: Novo Plano | Z10: JB
A11: =E11&F11 -> lt004_protectionRL_ESTT_ADDRSS | B11: Pilar III | C11: Pilar III | D11: 2. Campo | E11: lt004_protection | F11: RL_ESTT_ADDRSS | G11: =VLOOKUP(A11,Plano_V3!$A$26:$G$768,7,0) -> 5. Em Correção | H11: 5. Em Correção | J11: Package 4 | K11: Package 23 | L11: 45744 | M11: 45751 | N11: Testes Regressivos (LT Estr) | P11: =IF(VLOOKUP(A11,'Aux - pivots1'!$A:$E,3,0)=0, "",VLOOKUP(A11,'Aux - pivots1'!$A:$E,3,0)) | Q11: =IF(VLOOKUP(A11,'Aux - pivots1'!$A:$E,4,0)=0, "",VLOOKUP(A11,'Aux - pivots1'!$A:$E,4,0)) | R11: =IF(VLOOKUP(A11,'Aux - pivots1'!$A:$E,5,0)=0, "",VLOOKUP(A11,'Aux - pivots1'!$A:$E,5,0)) | U11: Novo Projeto - Em especificação | V11: ESTR e ESG | W11: FY25 | X11: Novos Requisitos FY25 - Âmbito ESTR e (ou) LF | Y11: Novo Plano | Z11: JB
A12: =E12&F12 -> lt004_protectionRL_ESTT_CLLTRL_LCTN_INT | B12: Pilar III | C12: Pilar III | D12: 2. Campo | E12: lt004_protection | F12: RL_ESTT_CLLTRL_LCTN_INT | G12: =VLOOKUP(A12,Plano_V3!$A$26:$G$768,7,0) -> 1. Concluído | H12: 1. Concluído | J12: Package 5 | K12: Package 23 | L12: 45744 | M12: 45751 | N12: Testes Regressivos (LT Estr) | P12: =IF(VLOOKUP(A12,'Aux - pivots1'!$A:$E,3,0)=0, "",VLOOKUP(A12,'Aux - pivots1'!$A:$E,3,0)) | Q12: =IF(VLOOKUP(A12,'Aux - pivots1'!$A:$E,4,0)=0, "",VLOOKUP(A12,'Aux - pivots1'!$A:$E,4,0)) | R12: =IF(VLOOKUP(A12,'Aux - pivots1'!$A:$E,5,0)=0, "",VLOOKUP(A12,'Aux - pivots1'!$A:$E,5,0)) | U12: Novo Projeto - Em especificação | V12: ESTR e ESG | W12: FY25 | X12: Novos Requisitos FY25 - Âmbito ESTR e (ou) LF | Y12: Novo Plano | Z12: JB
A13: =E13&F13 -> lt004_protectionRL_ESTT_CTY | B13: Pilar III | C13: Pilar III | D13: 2. Campo | E13: lt004_protection | F13: RL_ESTT_CTY | G13: =VLOOKUP(A13,Plano_V3!$A$26:$G$768,7,0) -> 1. Concluído | H13: 1. Concluído | J13: Package 3 | K13: Package 23 | L13: 45744 | M13: 45751 | N13: Testes Regressivos (LT Estr) | P13: =IF(VLOOKUP(A13,'Aux - pivots1'!$A:$E,3,0)=0, "",VLOOKUP(A13,'Aux - pivots1'!$A:$E,3,0)) | Q13: =IF(VLOOKUP(A13,'Aux - pivots1'!$A:$E,4,0)=0, "",VLOOKUP(A13,'Aux - pivots1'!$A:$E,4,0)) | R13: =IF(VLOOKUP(A13,'Aux - pivots1'!$A:$E,5,0)=0, "",VLOOKUP(A13,'Aux - pivots1'!$A:$E,5,0)) | U13: Novo Projeto - Em especificação | V13: ESTR e ESG | W13: FY25 | X13: Novos Requisitos FY25 - Âmbito ESTR e (ou) LF | Y13: Novo Plano | Z13: JB
A14: =E14&F14 -> lt004_protectionYR_CNSTRCTN | B14: Pilar III | C14: Pilar III | D14: 2. Campo | E14: lt004_protection | F14: YR_CNSTRCTN | G14: =VLOOKUP(A14,Plano_V3!$A$26:$G$768,7,0) -> 5. Em Correção | H14: 5. Em Correção | J14: Package 3 | K14: Package 23 | L14: 45744 | M14: 45751 | N14: Testes Regressivos (LT Estr) | P14: =IF(VLOOKUP(A14,'Aux - pivots1'!$A:$E,3,0)=0, "",VLOOKUP(A14,'Aux - pivots1'!$A:$E,3,0)) | Q14: =IF(VLOOKUP(A14,'Aux - pivots1'!$A:$E,4,0)=0, "",VLOOKUP(A14,'Aux - pivots1'!$A:$E,4,0)) | R14: =IF(VLOOKUP(A14,'Aux - pivots1'!$A:$E,5,0)=0, "",VLOOKUP(A14,'Aux - pivots1'!$A:$E,5,0)) | U14: Novo Projeto - Em especificação | V14: ESTR, P3 e ESG | W14: FY25 | X14: Novos Requisitos FY25 - Âmbito ESTR e (ou) LF | Y14: Novo Plano | Z14: JB
A15: =E15&F15 -> lt004_protectionBLDNG_AR | B15: Pilar III | C15: Pilar III | D15: 2. Campo | E15: lt004_protection | F15: BLDNG_AR | G15: =VLOOKUP(A15,Plano_V3!$A$26:$G$768,7,0) -> 5. Em Correção | H15: 5. Em Correção | J15: Package 3 | K15: Package 23 | L15: 45744 | M15: 45751 | N15: Teste ao campo | P15: =IF(VLOOKUP(A15,'Aux - pivots1'!$A:$E,3,0)=0, "",VLOOKUP(A15,'Aux - pivots1'!$A:$E,3,0)) | Q15: =IF(VLOOKUP(A15,'Aux - pivots1'!$A:$E,4,0)=0, "",VLOOKUP(A15,'Aux - pivots1'!$A:$E,4,0)) | R15: =IF(VLOOKUP(A15,'Aux - pivots1'!$A:$E,5,0)=0, "",VLOOKUP(A15,'Aux - pivots1'!$A:$E,5,0)) | U15: Novo Projeto - Em especificação | V15: P3 e ESG | W15: FY25 | X15: Novos Requisitos FY25 - Outros | Y15: Novo Plano | Z15: JB
A16: =E16&F16 -> lt002_instrumentNW_BSNSS | B16: Pilar III | C16: Pilar III | D16: 2. Campo | E16: lt002_instrument | F16: NW_BSNSS | G16: =VLOOKUP(A16,Plano_V3!$A$26:$G$768,7,0) -> 6. Em implementação | H16: 6. Em implementação | J16: Package 5 | K16: Sem Teste | L16: 45793 | M16: N/A | N16: Não testar | P16: =IF(VLOOKUP(A16,'Aux - pivots1'!$A:$E,3,0)=0, "",VLOOKUP(A16,'Aux - pivots1'!$A:$E,3,0)) | Q16: =IF(VLOOKUP(A16,'Aux - pivots1'!$A:$E,4,0)=0, "",VLOOKUP(A16,'Aux - pivots1'!$A:$E,4,0)) | R16: =IF(VLOOKUP(A16,'Aux - pivots1'!$A:$E,5,0)=0, "",VLOOKUP(A16,'Aux - pivots1'!$A:$E,5,0)) | U16: Novo Projeto - Em especificação | V16: GD, P3 e GF | W16: FY25 | X16: Novos Requisitos FY25 - Outros | Y16: Novo Plano | Z16: RC
A17: =E17&F17 -> lt002_instrumentCNCLLD_INSTRMNT_STTS | B17: Pilar III | C17: Pilar III | D17: 2. Campo | E17: lt002_instrument | F17: CNCLLD_INSTRMNT_STTS | G17: =VLOOKUP(A17,Plano_V3!$A$26:$G$768,7,0) -> 6. Em implementação | H17: 6. Em implementação | J17: Package 5 | K17: Sem Teste | L17: 45793 | M17: N/A | N17: Não testar | P17: =IF(VLOOKUP(A17,'Aux - pivots1'!$A:$E,3,0)=0, "",VLOOKUP(A17,'Aux - pivots1'!$A:$E,3,0)) | Q17: =IF(VLOOKUP(A17,'Aux - pivots1'!$A:$E,4,0)=0, "",VLOOKUP(A17,'Aux - pivots1'!$A:$E,4,0)) | R17: =IF(VLOOKUP(A17,'Aux - pivots1'!$A:$E,5,0)=0, "",VLOOKUP(A17,'Aux - pivots1'!$A:$E,5,0)) | U17: Novo Projeto - Em especificação | V17: GD, P3 e GF | W17: FY25 | X17: Novos Requisitos FY25 - Outros | Y17: Novo Plano | Z17: RC
A18: =E18&F18 -> lt002_instrumentTYP_OFF_BLNC_PRDCT | B18: Pilar III | C18: Pilar III | D18: 2. Campo | E18: lt002_instrument | F18: TYP_OFF_BLNC_PRDCT | G18: =VLOOKUP(A18,Plano_V3!$A$26:$G$768,7,0) -> 6. Em implementação | H18: 6. Em implementação | J18: Package 4 --> Não está especificado no LT - não conseguimos testar | K18: Sem Teste | L18: 45793 | M18: N/A | N18: Não testar | P18: =IF(VLOOKUP(A18,'Aux - pivots1'!$A:$E,3,0)=0, "",VLOOKUP(A18,'Aux - pivots1'!$A:$E,3,0)) | Q18: =IF(VLOOKUP(A18,'Aux - pivots1'!$A:$E,4,0)=0, "",VLOOKUP(A18,'Aux - pivots1'!$A:$E,4,0)) | R18: =IF(VLOOKUP(A18,'Aux - pivots1'!$A:$E,5,0)=0, "",VLOOKUP(A18,'Aux - pivots1'!$A:$E,5,0)) | U18: Novo Projeto - Em especificação | V18: ESTR, GD, P3 e LF | W18: FY25 | X18: Novos Requisitos FY25 - Âmbito ESTR e (ou) LF | Y18: Novo Plano | Z18: JB
A19: =E19&F19 -> modesg_out_empr_info_nfinppc_trnvr_ttl_elgbl | B19: Pilar III | C19: Modelo Verde - Output | D19: 2. Campo | E19: modesg_out_empr_info_nfin | F19: ppc_trnvr_ttl_elgbl | G19: =VLOOKUP(A19,Plano_V3!$A$26:$G$768,7,0) -> 1. Concluído | H19: 1. Concluído | J19: Package 1 | P19: =IF(VLOOKUP(A19,'Aux - pivots1'!$A:$E,3,0)=0, "",VLOOKUP(A19,'Aux - pivots1'!$A:$E,3,0)) | Q19: =IF(VLOOKUP(A19,'Aux - pivots1'!$A:$E,4,0)=0, "",VLOOKUP(A19,'Aux - pivots1'!$A:$E,4,0)) | R19: =IF(VLOOKUP(A19,'Aux - pivots1'!$A:$E,5,0)=0, "",VLOOKUP(A19,'Aux - pivots1'!$A:$E,5,0)) | Y19: Novo Plano
A20: =E20&F20 -> modesg_out_empr_info_nfinppc_turnover_own_prfrmnce_algnd | B20: Pilar III | C20: Modelo Verde - Output | D20: 2. Campo | E20: modesg_out_empr_info_nfin | F20: ppc_turnover_own_prfrmnce_algnd | G20: =VLOOKUP(A20,Plano_V3!$A$26:$G$768,7,0) -> 1. Concluído | H20: 1. Concluído | J20: Package 1 | P20: =IF(VLOOKUP(A20,'Aux - pivots1'!$A:$E,3,0)=0, "",VLOOKUP(A20,'Aux - pivots1'!$A:$E,3,0)) | Q20: =IF(VLOOKUP(A20,'Aux - pivots1'!$A:$E,4,0)=0, "",VLOOKUP(A20,'Aux - pivots1'!$A:$E,4,0)) | R20: =IF(VLOOKUP(A20,'Aux - pivots1'!$A:$E,5,0)=0, "",VLOOKUP(A20,'Aux - pivots1'!$A:$E,5,0)) | Y20: Novo Plano
A21: =E21&F21 -> modesg_out_empr_info_nfinppc_capex_ttl_elgbl | B21: Pilar III | C21: Modelo Verde - Output | D21: 2. Campo | E21: modesg_out_empr_info_nfin | F21: ppc_capex_ttl_elgbl | G21: =VLOOKUP(A21,Plano_V3!$A$26:$G$768,7,0) -> 1. Concluído | H21: 1. Concluído | J21: Package 1 | P21: =IF(VLOOKUP(A21,'Aux - pivots1'!$A:$E,3,0)=0, "",VLOOKUP(A21,'Aux - pivots1'!$A:$E,3,0)) | Q21: =IF(VLOOKUP(A21,'Aux - pivots1'!$A:$E,4,0)=0, "",VLOOKUP(A21,'Aux - pivots1'!$A:$E,4,0)) | R21: =IF(VLOOKUP(A21,'Aux - pivots1'!$A:$E,5,0)=0, "",VLOOKUP(A21,'Aux - pivots1'!$A:$E,5,0)) | Y21: Novo Plano
A22: =E22&F22 -> modesg_out_empr_info_nfinppc_capex_own_prfrmnce_algnd | B22: Pilar III | C22: Modelo Verde - Output | D22: 2. Campo | E22: modesg_out_empr_info_nfin | F22: ppc_capex_own_prfrmnce_algnd | G22: =VLOOKUP(A22,Plano_V3!$A$26:$G$768,7,0) -> 1. Concluído | H22: 1. Concluído | J22: Package 1 | P22: =IF(VLOOKUP(A22,'Aux - pivots1'!$A:$E,3,0)=0, "",VLOOKUP(A22,'Aux - pivots1'!$A:$E,3,0)) | Q22: =IF(VLOOKUP(A22,'Aux - pivots1'!$A:$E,4,0)=0, "",VLOOKUP(A22,'Aux - pivots1'!$A:$E,4,0)) | R22: =IF(VLOOKUP(A22,'Aux - pivots1'!$A:$E,5,0)=0, "",VLOOKUP(A22,'Aux - pivots1'!$A:$E,5,0)) | Y22: Novo Plano
A23: =E23&F23 -> modesg_out_empr_info_nfinbio_trnvr_ttl_elgbl | B23: Pilar III | C23: Modelo Verde - Output | D23: 2. Campo | E23: modesg_out_empr_info_nfin | F23: bio_trnvr_ttl_elgbl | G23: =VLOOKUP(A23,Plano_V3!$A$26:$G$768,7,0) -> 1. Concluído | H23: 1. Concluído | J23: Package 1 | P23: =IF(VLOOKUP(A23,'Aux - pivots1'!$A:$E,3,0)=0, "",VLOOKUP(A23,'Aux - pivots1'!$A:$E,3,0)) | Q23: =IF(VLOOKUP(A23,'Aux - pivots1'!$A:$E,4,0)=0, "",VLOOKUP(A23,'Aux - pivots1'!$A:$E,4,0)) | R23: =IF(VLOOKUP(A23,'Aux - pivots1'!$A:$E,5,0)=0, "",VLOOKUP(A23,'Aux - pivots1'!$A:$E,5,0)) | Y23: Novo Plano
A24: =E24&F24 -> modesg_out_empr_info_nfinbio_turnover_own_prfrmnce_algnd | B24: Pilar III | C24: Modelo Verde - Output | D24: 2. Campo | E24: modesg_out_empr_info_nfin | F24: bio_turnover_own_prfrmnce_algnd | G24: =VLOOKUP(A24,Plano_V3!$A$26:$G$768,7,0) -> 1. Concluído | H24: 1. Concluído | J24: Package 1 | P24: =IF(VLOOKUP(A24,'Aux - pivots1'!$A:$E,3,0)=0, "",VLOOKUP(A24,'Aux - pivots1'!$A:$E,3,0)) | Q24: =IF(VLOOKUP(A24,'Aux - pivots1'!$A:$E,4,0)=0, "",VLOOKUP(A24,'Aux - pivots1'!$A:$E,4,0)) | R24: =IF(VLOOKUP(A24,'Aux - pivots1'!$A:$E,5,0)=0, "",VLOOKUP(A24,'Aux - pivots1'!$A:$E,5,0)) | Y24: Novo Plano
A25: =E25&F25 -> modesg_out_empr_info_nfinbio_capex_ttl_elgbl | B25: Pilar III | C25: Modelo Verde - Output | D25: 2. Campo | E25: modesg_out_empr_info_nfin | F25: bio_capex_ttl_elgbl | G25: =VLOOKUP(A25,Plano_V3!$A$26:$G$768,7,0) -> 1. Concluído | H25: 1. Concluído | J25: Package 1 | P25: =IF(VLOOKUP(A25,'Aux - pivots1'!$A:$E,3,0)=0, "",VLOOKUP(A25,'Aux - pivots1'!$A:$E,3,0)) | Q25: =IF(VLOOKUP(A25,'Aux - pivots1'!$A:$E,4,0)=0, "",VLOOKUP(A25,'Aux - pivots1'!$A:$E,4,0)) | R25: =IF(VLOOKUP(A25,'Aux - pivots1'!$A:$E,5,0)=0, "",VLOOKUP(A25,'Aux - pivots1'!$A:$E,5,0)) | Y25: Novo Plano
A26: =E26&F26 -> modesg_out_empr_info_nfinbio_capex_own_prfrmnce_algnd | B26: Pilar III | C26: Modelo Verde - Output | D26: 2. Campo | E26: modesg_out_empr_info_nfin | F26: bio_capex_own_prfrmnce_algnd | G26: =VLOOKUP(A26,Plano_V3!$A$26:$G$768,7,0) -> 1. Concluído | H26: 1. Concluído | J26: Package 1 | P26: =IF(VLOOKUP(A26,'Aux - pivots1'!$A:$E,3,0)=0, "",VLOOKUP(A26,'Aux - pivots1'!$A:$E,3,0)) | Q26: =IF(VLOOKUP(A26,'Aux - pivots1'!$A:$E,4,0)=0, "",VLOOKUP(A26,'Aux - pivots1'!$A:$E,4,0)) | R26: =IF(VLOOKUP(A26,'Aux - pivots1'!$A:$E,5,0)=0, "",VLOOKUP(A26,'Aux - pivots1'!$A:$E,5,0)) | Y26: Novo Plano
A27: =E27&F27 -> modesg_out_empr_info_nfinwtr_trnvr_ttl_elgbl | B27: Pilar III | C27: Modelo Verde - Output | D27: 2. Campo | E27: modesg_out_empr_info_nfin | F27: wtr_trnvr_ttl_elgbl | G27: =VLOOKUP(A27,Plano_V3!$A$26:$G$768,7,0) -> 1. Concluído | H27: 1. Concluído | J27: Package 1 | P27: =IF(VLOOKUP(A27,'Aux - pivots1'!$A:$E,3,0)=0, "",VLOOKUP(A27,'Aux - pivots1'!$A:$E,3,0)) | Q27: =IF(VLOOKUP(A27,'Aux - pivots1'!$A:$E,4,0)=0, "",VLOOKUP(A27,'Aux - pivots1'!$A:$E,4,0)) | R27: =IF(VLOOKUP(A27,'Aux - pivots1'!$A:$E,5,0)=0, "",VLOOKUP(A27,'Aux - pivots1'!$A:$E,5,0)) | Y27: Novo Plano
A28: =E28&F28 -> modesg_out_empr_info_nfinwtr_trnvr_enblng_alignd | B28: Pilar III | C28: Modelo Verde - Output | D28: 2. Campo | E28: modesg_out_empr_info_nfin | F28: wtr_trnvr_enblng_alignd | G28: =VLOOKUP(A28,Plano_V3!$A$26:$G$768,7,0) -> 1. Concluído | H28: 1. Concluído | J28: Package 1 | P28: =IF(VLOOKUP(A28,'Aux - pivots1'!$A:$E,3,0)=0, "",VLOOKUP(A28,'Aux - pivots1'!$A:$E,3,0)) | Q28: =IF(VLOOKUP(A28,'Aux - pivots1'!$A:$E,4,0)=0, "",VLOOKUP(A28,'Aux - pivots1'!$A:$E,4,0)) | R28: =IF(VLOOKUP(A28,'Aux - pivots1'!$A:$E,5,0)=0, "",VLOOKUP(A28,'Aux - pivots1'!$A:$E,5,0)) | Y28: Novo Plano
A29: =E29&F29 -> modesg_out_empr_info_nfinwtr_turnover_own_prfrmnce_algnd | B29: Pilar III | C29: Modelo Verde - Output | D29: 2. Campo | E29: modesg_out_empr_info_nfin | F29: wtr_turnover_own_prfrmnce_algnd | G29: =VLOOKUP(A29,Plano_V3!$A$26:$G$768,7,0) -> 1. Concluído | H29: 1. Concluído | J29: Package 1 | P29: =IF(VLOOKUP(A29,'Aux - pivots1'!$A:$E,3,0)=0, "",VLOOKUP(A29,'Aux - pivots1'!$A:$E,3,0)) | Q29: =IF(VLOOKUP(A29,'Aux - pivots1'!$A:$E,4,0)=0, "",VLOOKUP(A29,'Aux - pivots1'!$A:$E,4,0)) | R29: =IF(VLOOKUP(A29,'Aux - pivots1'!$A:$E,5,0)=0, "",VLOOKUP(A29,'Aux - pivots1'!$A:$E,5,0)) | Y29: Novo Plano
A30: =E30&F30 -> modesg_out_empr_info_nfinwtr_capex_ttl_elgbl | B30: Pilar III | C30: Modelo Verde - Output | D30: 2. Campo | E30: modesg_out_empr_info_nfin | F30: wtr_capex_ttl_elgbl | G30: =VLOOKUP(A30,Plano_V3!$A$26:$G$768,7,0) -> 1. Concluído | H30: 1. Concluído | J30: Package 1 | P30: =IF(VLOOKUP(A30,'Aux - pivots1'!$A:$E,3,0)=0, "",VLOOKUP(A30,'Aux - pivots1'!$A:$E,3,0)) | Q30: =IF(VLOOKUP(A30,'Aux - pivots1'!$A:$E,4,0)=0, "",VLOOKUP(A30,'Aux - pivots1'!$A:$E,4,0)) | R30: =IF(VLOOKUP(A30,'Aux - pivots1'!$A:$E,5,0)=0, "",VLOOKUP(A30,'Aux - pivots1'!$A:$E,5,0)) | Y30: Novo Plano
... A38: =E38&F38 -> modesg_out_empr_info_nfince_capex_own_prfrmnce_algnd | B38: Pilar III | C38: Modelo Verde - Output | D38: 2. Campo | E38: modesg_out_empr_info_nfin | F38: ce_capex_own_prfrmnce_algnd | G38: =VLOOKUP(A38,Plano_V3!$A$26:$G$768,7,0) -> 1. Concluído | H38: 1. Concluído | J38: Package 1 | P38: =IF(VLOOKUP(A38,'Aux - pivots1'!$A:$E,3,0)=0, "",VLOOKUP(A38,'Aux - pivots1'!$A:$E,3,0)) | Q38: =IF(VLOOKUP(A38,'Aux - pivots1'!$A:$E,4,0)=0, "",VLOOKUP(A38,'Aux - pivots1'!$A:$E,4,0)) | R38: =IF(VLOOKUP(A38,'Aux - pivots1'!$A:$E,5,0)=0, "",VLOOKUP(A38,'Aux - pivots1'!$A:$E,5,0)) | Y38: Novo Plano
A39: =E39&F39 -> lt007_instr_activityPRCNTG_ACTVTY | B39: Pilar III | C39: Pilar III | D39: 2. Campo | E39: lt007_instr_activity | F39: PRCNTG_ACTVTY | G39: =VLOOKUP(A39,Plano_V3!$A$26:$G$768,7,0) -> 6. Em implementação | H39: 6. Em implementação | J39: Package 5 | K39: Package 26 | L39: 45764 | M39: 45771 | N39: Teste ao campo | P39: =IF(VLOOKUP(A39,'Aux - pivots1'!$A:$E,3,0)=0, "",VLOOKUP(A39,'Aux - pivots1'!$A:$E,3,0)) | Q39: =IF(VLOOKUP(A39,'Aux - pivots1'!$A:$E,4,0)=0, "",VLOOKUP(A39,'Aux - pivots1'!$A:$E,4,0)) | R39: =IF(VLOOKUP(A39,'Aux - pivots1'!$A:$E,5,0)=0, "",VLOOKUP(A39,'Aux - pivots1'!$A:$E,5,0)) | U39: Novo Projeto - Em especificação | V39: GD, P3 e GF | W39: FY25 | X39: Novos Requisitos FY25 - Outros | Y39: Novo Plano | Z39: RC
A40: =E40&F40 -> lt007_instr_activityFLG_SBSTNTL_CNTRBTN | B40: Pilar III | C40: Pilar III | D40: 2. Campo | E40: lt007_instr_activity | F40: FLG_SBSTNTL_CNTRBTN | G40: =VLOOKUP(A40,Plano_V3!$A$26:$G$768,7,0) -> 6. Em implementação | H40: 6. Em implementação | J40: Package 5 | K40: Package 26 | L40: 45764 | M40: 45771 | N40: Teste ao campo | P40: =IF(VLOOKUP(A40,'Aux - pivots1'!$A:$E,3,0)=0, "",VLOOKUP(A40,'Aux - pivots1'!$A:$E,3,0)) | Q40: =IF(VLOOKUP(A40,'Aux - pivots1'!$A:$E,4,0)=0, "",VLOOKUP(A40,'Aux - pivots1'!$A:$E,4,0)) | R40: =IF(VLOOKUP(A40,'Aux - pivots1'!$A:$E,5,0)=0, "",VLOOKUP(A40,'Aux - pivots1'!$A:$E,5,0)) | U40: Novo Projeto - Em especificação | V40: P3 | W40: FY25 | X40: Novos Requisitos FY25 - Outros | Y40: Novo Plano | Z40: RC
A41: =E41&F41 -> lt003_entitygrp_ecnmc_actvty | B41: Pilar III | C41: Pilar III | D41: 2. Campo | E41: lt003_entity | F41: grp_ecnmc_actvty | G41: =VLOOKUP(A41,Plano_V3!$A$26:$G$768,7,0) -> 5. Em Correção | H41: 5. Em Correção | J41: Package 5 | K41: Package 23 | L41: 45744 | M41: 45751 | N41: Teste ao campo | P41: =IF(VLOOKUP(A41,'Aux - pivots1'!$A:$E,3,0)=0, "",VLOOKUP(A41,'Aux - pivots1'!$A:$E,3,0)) | Q41: =IF(VLOOKUP(A41,'Aux - pivots1'!$A:$E,4,0)=0, "",VLOOKUP(A41,'Aux - pivots1'!$A:$E,4,0)) | R41: =IF(VLOOKUP(A41,'Aux - pivots1'!$A:$E,5,0)=0, "",VLOOKUP(A41,'Aux - pivots1'!$A:$E,5,0)) | U41: Novo Projeto - Em especificação | V41: P3, GF e ESG | W41: FY25 | X41: Novos Requisitos FY25 - Outros | Y41: Novo Plano | Z41: JB
A42: =E42&F42 -> lt006_instr_protTYP_RLTN | B42: Pilar III | C42: Pilar III | D42: 2. Campo | E42: lt006_instr_prot | F42: TYP_RLTN | G42: =VLOOKUP(A42,Plano_V3!$A$26:$G$768,7,0) -> 6. Em implementação | H42: 6. Em implementação | J42: Package 5 | K42: Package 26 | L42: 45764 | M42: 45771 | N42: Testes Regressivos (LT GD) | P42: =IF(VLOOKUP(A33,'Aux - pivots1'!$A:$E,3,0)=0, "",VLOOKUP(A33,'Aux - pivots1'!$A:$E,3,0)) | Q42: =IF(VLOOKUP(A33,'Aux - pivots1'!$A:$E,4,0)=0, "",VLOOKUP(A33,'Aux - pivots1'!$A:$E,4,0)) | R42: =IF(VLOOKUP(A33,'Aux - pivots1'!$A:$E,5,0)=0, "",VLOOKUP(A33,'Aux - pivots1'!$A:$E,5,0)) | U42: Novo Projeto - Em especificação | V42: GD e P3 | W42: FY25 | X42: Novos Requisitos FY25 - Outros | Y42: Novo Plano | Z42: JB
A43: =E43&F43 -> lt004_protectionEPC_EMSSNS_LBL | B43: Pilar III | C43: Pilar III | D43: 2. Campo | E43: lt004_protection | F43: EPC_EMSSNS_LBL | G43: =VLOOKUP(A43,Plano_V3!$A$26:$G$768,7,0) -> 6. Em implementação | H43: 6. Em implementação | J43: Package 4 | K43: Package 25 | L43: 45758 | M43: 45765 | N43: Teste ao campo | P43: =IF(VLOOKUP(A43,'Aux - pivots1'!$A:$E,3,0)=0, "",VLOOKUP(A43,'Aux - pivots1'!$A:$E,3,0)) | Q43: =IF(VLOOKUP(A43,'Aux - pivots1'!$A:$E,4,0)=0, "",VLOOKUP(A43,'Aux - pivots1'!$A:$E,4,0)) | R43: =IF(VLOOKUP(A43,'Aux - pivots1'!$A:$E,5,0)=0, "",VLOOKUP(A43,'Aux - pivots1'!$A:$E,5,0)) | U43: Novo Projeto - Em especificação | V43: ESG | W43: FY25 | X43: Novos Requisitos FY25 - Outros | Y43: Novo Plano | Z43: JB
A44: =E44&F44 -> lt004_protectionTYP_EMSSNS_SCR | B44: Pilar III | C44: Pilar III | D44: 2. Campo | E44: lt004_protection | F44: TYP_EMSSNS_SCR | G44: =VLOOKUP(A44,Plano_V3!$A$26:$G$768,7,0) -> 6. Em implementação | H44: 6. Em implementação | J44: Package 4 | K44: Package 25 | L44: 45758 | M44: 45765 | N44: Teste ao campo | P44: =IF(VLOOKUP(A44,'Aux - pivots1'!$A:$E,3,0)=0, "",VLOOKUP(A44,'Aux - pivots1'!$A:$E,3,0)) | Q44: =IF(VLOOKUP(A44,'Aux - pivots1'!$A:$E,4,0)=0, "",VLOOKUP(A44,'Aux - pivots1'!$A:$E,4,0)) | R44: =IF(VLOOKUP(A44,'Aux - pivots1'!$A:$E,5,0)=0, "",VLOOKUP(A44,'Aux - pivots1'!$A:$E,5,0)) | U44: Novo Projeto - Em especificação | V44: ESG | W44: FY25 | X44: Novos Requisitos FY25 - Outros | Y44: Novo Plano | Z44: JB
A45: =E45&F45 -> lt004_protectionEPC_EMSSNS_SCR | B45: Pilar III | C45: Pilar III | D45: 2. Campo | E45: lt004_protection | F45: EPC_EMSSNS_SCR | G45: =VLOOKUP(A45,Plano_V3!$A$26:$G$768,7,0) -> 6. Em implementação | H45: 6. Em implementação | J45: Package 4 | K45: Package 25 | L45: 45758 | M45: 45765 | N45: Teste ao campo | P45: =IF(VLOOKUP(A45,'Aux - pivots1'!$A:$E,3,0)=0, "",VLOOKUP(A45,'Aux - pivots1'!$A:$E,3,0)) | Q45: =IF(VLOOKUP(A45,'Aux - pivots1'!$A:$E,4,0)=0, "",VLOOKUP(A45,'Aux - pivots1'!$A:$E,4,0)) | R45: =IF(VLOOKUP(A45,'Aux - pivots1'!$A:$E,5,0)=0, "",VLOOKUP(A45,'Aux - pivots1'!$A:$E,5,0)) | U45: Novo Projeto - Em especificação | V45: ESG | W45: FY25 | X45: Novos Requisitos FY25 - Outros | Y45: Novo Plano | Z45: JB
A46: =E46&F46 -> lt004_protectionTYP_VHCL | B46: Pilar III | C46: Pilar III | D46: 2. Campo | E46: lt004_protection | F46: TYP_VHCL | G46: =VLOOKUP(A46,Plano_V3!$A$26:$G$768,7,0) -> 6. Em implementação | H46: 6. Em implementação | J46: Package 4 | K46: Package 25 | L46: 45758 | M46: 45765 | N46: Teste ao campo | P46: =IF(VLOOKUP(A46,'Aux - pivots1'!$A:$E,3,0)=0, "",VLOOKUP(A46,'Aux - pivots1'!$A:$E,3,0)) | Q46: =IF(VLOOKUP(A46,'Aux - pivots1'!$A:$E,4,0)=0, "",VLOOKUP(A46,'Aux - pivots1'!$A:$E,4,0)) | R46: =IF(VLOOKUP(A46,'Aux - pivots1'!$A:$E,5,0)=0, "",VLOOKUP(A46,'Aux - pivots1'!$A:$E,5,0)) | U46: Novo Projeto - Em especificação | V46: GD, P3 e ESG | W46: FY25 | X46: Novos Requisitos FY25 - Outros | Y46: Novo Plano | Z46: JB
A47: =E47&F47 -> lt004_protectionPRMRY_ENRGY_DMND_TTL | B47: Pilar III | C47: Pilar III | D47: 2. Campo | E47: lt004_protection | F47: PRMRY_ENRGY_DMND_TTL | G47: =VLOOKUP(A47,Plano_V3!$A$26:$G$768,7,0) -> 6. Em implementação | H47: 6. Em implementação | J47: Package 4 | K47: Package 25 | L47: 45758 | M47: 45765 | N47: Teste ao campo | P47: =IF(VLOOKUP(A47,'Aux - pivots1'!$A:$E,3,0)=0, "",VLOOKUP(A47,'Aux - pivots1'!$A:$E,3,0)) | Q47: =IF(VLOOKUP(A47,'Aux - pivots1'!$A:$E,4,0)=0, "",VLOOKUP(A47,'Aux - pivots1'!$A:$E,4,0)) | R47: =IF(VLOOKUP(A47,'Aux - pivots1'!$A:$E,5,0)=0, "",VLOOKUP(A47,'Aux - pivots1'!$A:$E,5,0)) | U47: Novo Projeto - Em especificação | V47: P3 e ESG | W47: FY25 | X47: Novos Requisitos FY25 - Outros | Y47: Novo Plano | Z47: HF
A48: =E48&F48 -> lt004_protectionPRMRY_ENRGY_DMND_RFRNC_VL | B48: Pilar III | C48: Pilar III | D48: 2. Campo | E48: lt004_protection | F48: PRMRY_ENRGY_DMND_RFRNC_VL | G48: =VLOOKUP(A48,Plano_V3!$A$26:$G$768,7,0) -> 6. Em implementação | H48: 6. Em implementação | J48: Package 4 | K48: Package 25 | L48: 45758 | M48: 45765 | N48: Teste ao campo | P48: =IF(VLOOKUP(A48,'Aux - pivots1'!$A:$E,3,0)=0, "",VLOOKUP(A48,'Aux - pivots1'!$A:$E,3,0)) | Q48: =IF(VLOOKUP(A48,'Aux - pivots1'!$A:$E,4,0)=0, "",VLOOKUP(A48,'Aux - pivots1'!$A:$E,4,0)) | R48: =IF(VLOOKUP(A48,'Aux - pivots1'!$A:$E,5,0)=0, "",VLOOKUP(A48,'Aux - pivots1'!$A:$E,5,0)) | U48: Novo Projeto - Em especificação | V48: P3 e ESG | W48: FY25 | X48: Novos Requisitos FY25 - Outros | Y48: Novo Plano | Z48: HF
A49: =E49&F49 -> lt004_protectionRL_ESTT_CLMT_ZN | B49: Pilar III | C49: Pilar III | D49: 2. Campo | E49: lt004_protection | F49: RL_ESTT_CLMT_ZN | G49: =VLOOKUP(A49,Plano_V3!$A$26:$G$768,7,0) -> 6. Em implementação | H49: 6. Em implementação | J49: Package 4 | K49: Package 25 | L49: 45758 | M49: 45765 | N49: Teste ao campo | P49: =IF(VLOOKUP(A49,'Aux - pivots1'!$A:$E,3,0)=0, "",VLOOKUP(A49,'Aux - pivots1'!$A:$E,3,0)) | Q49: =IF(VLOOKUP(A49,'Aux - pivots1'!$A:$E,4,0)=0, "",VLOOKUP(A49,'Aux - pivots1'!$A:$E,4,0)) | R49: =IF(VLOOKUP(A49,'Aux - pivots1'!$A:$E,5,0)=0, "",VLOOKUP(A49,'Aux - pivots1'!$A:$E,5,0)) | U49: Novo Projeto - Em especificação | V49: P3 e ESG | W49: FY25 | X49: Novos Requisitos FY25 - Outros | Y49: Novo Plano | Z49: JB
A50: =E50&F50 -> ENERGY_CERTIFICATE_EST_INPUTCHAVE_GLOVAL | B50: Pilar III | C50: Bens Imóveis - Input | D50: 2. Campo | E50: ENERGY_CERTIFICATE_EST_INPUT | F50: CHAVE_GLOVAL | G50: =VLOOKUP(A50,Plano_V3!$A$26:$G$768,7,0) -> 1. Concluído | H50: 1. Concluído | I50: Fase I | J50: Package 1 | P50: =IF(VLOOKUP(A50,'Aux - pivots1'!$A:$E,3,0)=0, "",VLOOKUP(A50,'Aux - pivots1'!$A:$E,3,0)) | Q50: =IF(VLOOKUP(A50,'Aux - pivots1'!$A:$E,4,0)=0, "",VLOOKUP(A50,'Aux - pivots1'!$A:$E,4,0)) | R50: =IF(VLOOKUP(A50,'Aux - pivots1'!$A:$E,5,0)=0, "",VLOOKUP(A50,'Aux - pivots1'!$A:$E,5,0)) | Y50: Plano anterior (alteração nome)
A51: =E51&F51 -> ENERGY_CERTIFICATE_EST_INPUTPROPERTY_BANK_ID | B51: Pilar III | C51: Bens Imóveis - Input | D51: 2. Campo | E51: ENERGY_CERTIFICATE_EST_INPUT | F51: PROPERTY_BANK_ID | G51: =VLOOKUP(A51,Plano_V3!$A$26:$G$768,7,0) -> 1. Concluído | H51: 1. Concluído | I51: Fase I | J51: Package 1 | P51: =IF(VLOOKUP(A51,'Aux - pivots1'!$A:$E,3,0)=0, "",VLOOKUP(A51,'Aux - pivots1'!$A:$E,3,0)) | Q51: =IF(VLOOKUP(A51,'Aux - pivots1'!$A:$E,4,0)=0, "",VLOOKUP(A51,'Aux - pivots1'!$A:$E,4,0)) | R51: =IF(VLOOKUP(A51,'Aux - pivots1'!$A:$E,5,0)=0, "",VLOOKUP(A51,'Aux - pivots1'!$A:$E,5,0)) | Y51: Plano anterior
A52: =E52&F52 -> ENERGY_CERTIFICATE_EST_INPUTPROPERTY_BRANCH_CODE | B52: Pilar III | C52: Bens Imóveis - Input | D52: 2. Campo | E52: ENERGY_CERTIFICATE_EST_INPUT | F52: PROPERTY_BRANCH_CODE | G52: =VLOOKUP(A52,Plano_V3!$A$26:$G$768,7,0) -> 1. Concluído | H52: 1. Concluído | I52: Fase I | J52: Package 1 | P52: =IF(VLOOKUP(A52,'Aux - pivots1'!$A:$E,3,0)=0, "",VLOOKUP(A52,'Aux - pivots1'!$A:$E,3,0)) | Q52: =IF(VLOOKUP(A52,'Aux - pivots1'!$A:$E,4,0)=0, "",VLOOKUP(A52,'Aux - pivots1'!$A:$E,4,0)) | R52: =IF(VLOOKUP(A52,'Aux - pivots1'!$A:$E,5,0)=0, "",VLOOKUP(A52,'Aux - pivots1'!$A:$E,5,0)) | Y52: Plano anterior
A53: =E53&F53 -> ENERGY_CERTIFICATE_EST_INPUTPROPERTY_CONTRACT_ID | B53: Pilar III | C53: Bens Imóveis - Input | D53: 2. Campo | E53: ENERGY_CERTIFICATE_EST_INPUT | F53: PROPERTY_CONTRACT_ID | G53: =VLOOKUP(A53,Plano_V3!$A$26:$G$768,7,0) -> 1. Concluído | H53: 1. Concluído | I53: Fase I | J53: Package 1 | P53: =IF(VLOOKUP(A53,'Aux - pivots1'!$A:$E,3,0)=0, "",VLOOKUP(A53,'Aux - pivots1'!$A:$E,3,0)) | Q53: =IF(VLOOKUP(A53,'Aux - pivots1'!$A:$E,4,0)=0, "",VLOOKUP(A53,'Aux - pivots1'!$A:$E,4,0)) | R53: =IF(VLOOKUP(A53,'Aux - pivots1'!$A:$E,5,0)=0, "",VLOOKUP(A53,'Aux - pivots1'!$A:$E,5,0)) | Y53: Plano anterior
A54: =E54&F54 -> ENERGY_CERTIFICATE_EST_INPUTPROPERTY_REFERENCE_CODE | B54: Pilar III | C54: Bens Imóveis - Input | D54: 2. Campo | E54: ENERGY_CERTIFICATE_EST_INPUT | F54: PROPERTY_REFERENCE_CODE | G54: =VLOOKUP(A54,Plano_V3!$A$26:$G$768,7,0) -> 1. Concluído | H54: 1. Concluído | I54: Fase I | J54: Package 1 | P54: =IF(VLOOKUP(A54,'Aux - pivots1'!$A:$E,3,0)=0, "",VLOOKUP(A54,'Aux - pivots1'!$A:$E,3,0)) | Q54: =IF(VLOOKUP(A54,'Aux - pivots1'!$A:$E,4,0)=0, "",VLOOKUP(A54,'Aux - pivots1'!$A:$E,4,0)) | R54: =IF(VLOOKUP(A54,'Aux - pivots1'!$A:$E,5,0)=0, "",VLOOKUP(A54,'Aux - pivots1'!$A:$E,5,0)) | Y54: Plano anterior
A55: =E55&F55 -> ENERGY_CERTIFICATE_EST_INPUTCÓDIGO_DISTRITO | B55: Pilar III | C55: Bens Imóveis - Input | D55: 2. Campo | E55: ENERGY_CERTIFICATE_EST_INPUT | F55: CÓDIGO_DISTRITO | G55: =VLOOKUP(A55,Plano_V3!$A$26:$G$768,7,0) -> 1. Concluído | H55: 1. Concluído | I55: Fase I | J55: Package 1 | P55: =IF(VLOOKUP(A55,'Aux - pivots1'!$A:$E,3,0)=0, "",VLOOKUP(A55,'Aux - pivots1'!$A:$E,3,0)) | Q55: =IF(VLOOKUP(A55,'Aux - pivots1'!$A:$E,4,0)=0, "",VLOOKUP(A55,'Aux - pivots1'!$A:$E,4,0)) | R55: =IF(VLOOKUP(A55,'Aux - pivots1'!$A:$E,5,0)=0, "",VLOOKUP(A55,'Aux - pivots1'!$A:$E,5,0)) | Y55: Plano anterior (sem visibilidade no PdS enviado 17/01)
A56: =E56&F56 -> ENERGY_CERTIFICATE_EST_INPUTNOMBRE_DISTRITO | B56: Pilar III | C56: Bens Imóveis - Input | D56: 2. Campo | E56: ENERGY_CERTIFICATE_EST_INPUT | F56: NOMBRE_DISTRITO | G56: =VLOOKUP(A56,Plano_V3!$A$26:$G$768,7,0) -> 1. Concluído | H56: 1. Concluído | I56: Fase I | J56: Package 1 | P56: =IF(VLOOKUP(A56,'Aux - pivots1'!$A:$E,3,0)=0, "",VLOOKUP(A56,'Aux - pivots1'!$A:$E,3,0)) | Q56: =IF(VLOOKUP(A56,'Aux - pivots1'!$A:$E,4,0)=0, "",VLOOKUP(A56,'Aux - pivots1'!$A:$E,4,0)) | R56: =IF(VLOOKUP(A56,'Aux - pivots1'!$A:$E,5,0)=0, "",VLOOKUP(A56,'Aux - pivots1'!$A:$E,5,0)) | Y56: Plano anterior (sem visibilidade no PdS enviado 17/01)
A57: =E57&F57 -> ENERGY_CERTIFICATE_EST_INPUTCÓDIGO_CONCEJO | B57: Pilar III | C57: Bens Imóveis - Input | D57: 2. Campo | E57: ENERGY_CERTIFICATE_EST_INPUT | F57: CÓDIGO_CONCEJO | G57: =VLOOKUP(A57,Plano_V3!$A$26:$G$768,7,0) -> 1. Concluído | H57: 1. Concluído | I57: Fase I | J57: Package 1 | P57: =IF(VLOOKUP(A57,'Aux - pivots1'!$A:$E,3,0)=0, "",VLOOKUP(A57,'Aux - pivots1'!$A:$E,3,0)) | Q57: =IF(VLOOKUP(A57,'Aux - pivots1'!$A:$E,4,0)=0, "",VLOOKUP(A57,'Aux - pivots1'!$A:$E,4,0)) | R57: =IF(VLOOKUP(A57,'Aux - pivots1'!$A:$E,5,0)=0, "",VLOOKUP(A57,'Aux - pivots1'!$A:$E,5,0)) | Y57: Plano anterior (sem visibilidade no PdS enviado 17/01)
A58: =E58&F58 -> ENERGY_CERTIFICATE_EST_INPUTNOMBRE_CONCEJO | B58: Pilar III | C58: Bens Imóveis - Input | D58: 2. Campo | E58: ENERGY_CERTIFICATE_EST_INPUT | F58: NOMBRE_CONCEJO | G58: =VLOOKUP(A58,Plano_V3!$A$26:$G$768,7,0) -> 1. Concluído | H58: 1. Concluído | I58: Fase I | J58: Package 1 | P58: =IF(VLOOKUP(A58,'Aux - pivots1'!$A:$E,3,0)=0, "",VLOOKUP(A58,'Aux - pivots1'!$A:$E,3,0)) | Q58: =IF(VLOOKUP(A58,'Aux - pivots1'!$A:$E,4,0)=0, "",VLOOKUP(A58,'Aux - pivots1'!$A:$E,4,0)) | R58: =IF(VLOOKUP(A58,'Aux - pivots1'!$A:$E,5,0)=0, "",VLOOKUP(A58,'Aux - pivots1'!$A:$E,5,0)) | Y58: Plano anterior (sem visibilidade no PdS enviado 17/01)
A59: =E59&F59 -> ENERGY_CERTIFICATE_EST_INPUTCÓDIGO_FREGUESIA | B59: Pilar III | C59: Bens Imóveis - Input | D59: 2. Campo | E59: ENERGY_CERTIFICATE_EST_INPUT | F59: CÓDIGO_FREGUESIA | G59: =VLOOKUP(A59,Plano_V3!$A$26:$G$768,7,0) -> 1. Concluído | H59: 1. Concluído | I59: Fase I | J59: Package 1 | P59: =IF(VLOOKUP(A59,'Aux - pivots1'!$A:$E,3,0)=0, "",VLOOKUP(A59,'Aux - pivots1'!$A:$E,3,0)) | Q59: =IF(VLOOKUP(A59,'Aux - pivots1'!$A:$E,4,0)=0, "",VLOOKUP(A59,'Aux - pivots1'!$A:$E,4,0)) | R59: =IF(VLOOKUP(A59,'Aux - pivots1'!$A:$E,5,0)=0, "",VLOOKUP(A59,'Aux - pivots1'!$A:$E,5,0)) | Y59: Plano anterior (sem visibilidade no PdS enviado 17/01)
A60: =E60&F60 -> ENERGY_CERTIFICATE_EST_INPUTNOMBRE_FREGUESIA | B60: Pilar III | C60: Bens Imóveis - Input | D60: 2. Campo | E60: ENERGY_CERTIFICATE_EST_INPUT | F60: NOMBRE_FREGUESIA | G60: =VLOOKUP(A60,Plano_V3!$A$26:$G$768,7,0) -> 1. Concluído | H60: 1. Concluído | I60: Fase I | J60: Package 1 | P60: =IF(VLOOKUP(A60,'Aux - pivots1'!$A:$E,3,0)=0, "",VLOOKUP(A60,'Aux - pivots1'!$A:$E,3,0)) | Q60: =IF(VLOOKUP(A60,'Aux - pivots1'!$A:$E,4,0)=0, "",VLOOKUP(A60,'Aux - pivots1'!$A:$E,4,0)) | R60: =IF(VLOOKUP(A60,'Aux - pivots1'!$A:$E,5,0)=0, "",VLOOKUP(A60,'Aux - pivots1'!$A:$E,5,0)) | Y60: Plano anterior (sem visibilidade no PdS enviado 17/01)
A61: =E61&F61 -> ENERGY_CERTIFICATE_EST_INPUTLOCALIDADE | B61: Pilar III | C61: Bens Imóveis - Input | D61: 2. Campo | E61: ENERGY_CERTIFICATE_EST_INPUT | F61: LOCALIDADE | G61: =VLOOKUP(A61,Plano_V3!$A$26:$G$768,7,0) -> 1. Concluído | H61: 1. Concluído | I61: Fase I | J61: Package 1 | P61: =IF(VLOOKUP(A61,'Aux - pivots1'!$A:$E,3,0)=0, "",VLOOKUP(A61,'Aux - pivots1'!$A:$E,3,0)) | Q61: =IF(VLOOKUP(A61,'Aux - pivots1'!$A:$E,4,0)=0, "",VLOOKUP(A61,'Aux - pivots1'!$A:$E,4,0)) | R61: =IF(VLOOKUP(A61,'Aux - pivots1'!$A:$E,5,0)=0, "",VLOOKUP(A61,'Aux - pivots1'!$A:$E,5,0)) | Y61: Plano anterior (sem visibilidade no PdS enviado 17/01)
... A93: =E93&F93 -> ENERGY_CERTIFICATE_EST_INPUTDATA_ENVIO | B93: Pilar III | C93: Bens Imóveis - Input | D93: 2. Campo | E93: ENERGY_CERTIFICATE_EST_INPUT | F93: DATA_ENVIO | G93: =VLOOKUP(A93,Plano_V3!$A$26:$G$768,7,0) -> 1. Concluído | H93: 1. Concluído | I93: Fase I | J93: Package 1 | P93: =IF(VLOOKUP(A93,'Aux - pivots1'!$A:$E,3,0)=0, "",VLOOKUP(A93,'Aux - pivots1'!$A:$E,3,0)) | Q93: =IF(VLOOKUP(A93,'Aux - pivots1'!$A:$E,4,0)=0, "",VLOOKUP(A93,'Aux - pivots1'!$A:$E,4,0)) | R93: =IF(VLOOKUP(A93,'Aux - pivots1'!$A:$E,5,0)=0, "",VLOOKUP(A93,'Aux - pivots1'!$A:$E,5,0)) | Y93: Plano anterior (alteração nome)
A94: =E94&F94 -> PROPERTY_ENERGY_CERTIFICATEEPC | B94: Pilar III | C94: Bens Imóveis - Output | D94: 2. Campo | E94: PROPERTY_ENERGY_CERTIFICATE | F94: EPC | G94: =VLOOKUP(A94,Plano_V3!$A$26:$G$768,7,0) -> 1. Concluído | H94: 1. Concluído | J94: Package 1 | P94: =IF(VLOOKUP(A94,'Aux - pivots1'!$A:$E,3,0)=0, "",VLOOKUP(A94,'Aux - pivots1'!$A:$E,3,0)) | Q94: =IF(VLOOKUP(A94,'Aux - pivots1'!$A:$E,4,0)=0, "",VLOOKUP(A94,'Aux - pivots1'!$A:$E,4,0)) | R94: =IF(VLOOKUP(A94,'Aux - pivots1'!$A:$E,5,0)=0, "",VLOOKUP(A94,'Aux - pivots1'!$A:$E,5,0)) | Y94: Plano anterior
A95: =E95&F95 -> PROPERTY_ENERGY_CERTIFICATEPRMRY_ENRGY_DMND_RFRNC_VL | B95: Pilar III | C95: Bens Imóveis - Output | D95: 2. Campo | E95: PROPERTY_ENERGY_CERTIFICATE | F95: PRMRY_ENRGY_DMND_RFRNC_VL | G95: =VLOOKUP(A95,Plano_V3!$A$26:$G$768,7,0) -> 1. Concluído | H95: 1. Concluído | P95: =IF(VLOOKUP(A95,'Aux - pivots1'!$A:$E,3,0)=0, "",VLOOKUP(A95,'Aux - pivots1'!$A:$E,3,0)) | Q95: =IF(VLOOKUP(A95,'Aux - pivots1'!$A:$E,4,0)=0, "",VLOOKUP(A95,'Aux - pivots1'!$A:$E,4,0)) | R95: =IF(VLOOKUP(A95,'Aux - pivots1'!$A:$E,5,0)=0, "",VLOOKUP(A95,'Aux - pivots1'!$A:$E,5,0)) | Y95: Plano anterior
A96: =E96&F96 -> PROPERTY_ENERGY_CERTIFICATECARBON_EMISSION_VALUE_YEAR | B96: Pilar III | C96: Bens Imóveis - Output | D96: 2. Campo | E96: PROPERTY_ENERGY_CERTIFICATE | F96: CARBON_EMISSION_VALUE_YEAR | G96: =VLOOKUP(A96,Plano_V3!$A$26:$G$768,7,0) -> 1. Concluído | H96: 1. Concluído | J96: Package 8 | K96: Package 22 | L96: 45730 | M96: 45737 | P96: =IF(VLOOKUP(A96,'Aux - pivots1'!$A:$E,3,0)=0, "",VLOOKUP(A96,'Aux - pivots1'!$A:$E,3,0)) | Q96: =IF(VLOOKUP(A96,'Aux - pivots1'!$A:$E,4,0)=0, "",VLOOKUP(A96,'Aux - pivots1'!$A:$E,4,0)) | R96: =IF(VLOOKUP(A96,'Aux - pivots1'!$A:$E,5,0)=0, "",VLOOKUP(A96,'Aux - pivots1'!$A:$E,5,0)) | Y96: Plano anterior
A97: =E97&F97 -> modesg_inp_risco_fisico_zipcodecod_pais | B97: Pilar III | C97: Modelo Verde - Input | D97: 2. Campo | E97: modesg_inp_risco_fisico_zipcode | F97: cod_pais | G97: =VLOOKUP(A97,Plano_V3!$A$26:$G$768,7,0) -> 1. Concluído | H97: 1. Concluído | J97: Package 2 | P97: =IF(VLOOKUP(A97,'Aux - pivots1'!$A:$E,3,0)=0, "",VLOOKUP(A97,'Aux - pivots1'!$A:$E,3,0)) | Q97: =IF(VLOOKUP(A97,'Aux - pivots1'!$A:$E,4,0)=0, "",VLOOKUP(A97,'Aux - pivots1'!$A:$E,4,0)) | R97: =IF(VLOOKUP(A97,'Aux - pivots1'!$A:$E,5,0)=0, "",VLOOKUP(A97,'Aux - pivots1'!$A:$E,5,0)) | U97: Novo Projeto - Em especificação | Y97: Novo Plano | Z97: HF
A98: =E98&F98 -> modesg_inp_risco_fisico_zipcodelocalizacao | B98: Pilar III | C98: Modelo Verde - Input | D98: 2. Campo | E98: modesg_inp_risco_fisico_zipcode | F98: localizacao | G98: =VLOOKUP(A98,Plano_V3!$A$26:$G$768,7,0) -> 1. Concluído | H98: 1. Concluído | J98: Package 2 | P98: =IF(VLOOKUP(A98,'Aux - pivots1'!$A:$E,3,0)=0, "",VLOOKUP(A98,'Aux - pivots1'!$A:$E,3,0)) | Q98: =IF(VLOOKUP(A98,'Aux - pivots1'!$A:$E,4,0)=0, "",VLOOKUP(A98,'Aux - pivots1'!$A:$E,4,0)) | R98: =IF(VLOOKUP(A98,'Aux - pivots1'!$A:$E,5,0)=0, "",VLOOKUP(A98,'Aux - pivots1'!$A:$E,5,0)) | U98: Novo Projeto - Em especificação | Y98: Novo Plano | Z98: HF
A99: =E99&F99 -> modesg_inp_risco_fisico_zipcodecod_nace_esg | B99: Pilar III | C99: Modelo Verde - Input | D99: 2. Campo | E99: modesg_inp_risco_fisico_zipcode | F99: cod_nace_esg | G99: =VLOOKUP(A99,Plano_V3!$A$26:$G$768,7,0) -> 1. Concluído | H99: 1. Concluído | J99: Package 2 | P99: =IF(VLOOKUP(A99,'Aux - pivots1'!$A:$E,3,0)=0, "",VLOOKUP(A99,'Aux - pivots1'!$A:$E,3,0)) | Q99: =IF(VLOOKUP(A99,'Aux - pivots1'!$A:$E,4,0)=0, "",VLOOKUP(A99,'Aux - pivots1'!$A:$E,4,0)) | R99: =IF(VLOOKUP(A99,'Aux - pivots1'!$A:$E,5,0)=0, "",VLOOKUP(A99,'Aux - pivots1'!$A:$E,5,0)) | U99: Novo Projeto - Em especificação | Y99: Novo Plano | Z99: HF
A100: =E100&F100 -> modesg_inp_risco_fisico_zipcodeflg_rsc_fsc_agd | B100: Pilar III | C100: Modelo Verde - Input | D100: 2. Campo | E100: modesg_inp_risco_fisico_zipcode | F100: flg_rsc_fsc_agd | G100: =VLOOKUP(A100,Plano_V3!$A$26:$G$768,7,0) -> 1. Concluído | H100: 1. Concluído | J100: Package 2 | P100: =IF(VLOOKUP(A100,'Aux - pivots1'!$A:$E,3,0)=0, "",VLOOKUP(A100,'Aux - pivots1'!$A:$E,3,0)) | Q100: =IF(VLOOKUP(A100,'Aux - pivots1'!$A:$E,4,0)=0, "",VLOOKUP(A100,'Aux - pivots1'!$A:$E,4,0)) | R100: =IF(VLOOKUP(A100,'Aux - pivots1'!$A:$E,5,0)=0, "",VLOOKUP(A100,'Aux - pivots1'!$A:$E,5,0)) | U100: Novo Projeto - Em especificação | Y100: Novo Plano | Z100: HF
A101: =E101&F101 -> modesg_inp_risco_fisico_zipcodeflg_rsc_fsc_crnc | B101: Pilar III | C101: Modelo Verde - Input | D101: 2. Campo | E101: modesg_inp_risco_fisico_zipcode | F101: flg_rsc_fsc_crnc | G101: =VLOOKUP(A101,Plano_V3!$A$26:$G$768,7,0) -> 1. Concluído | H101: 1. Concluído | J101: Package 2 | P101: =IF(VLOOKUP(A101,'Aux - pivots1'!$A:$E,3,0)=0, "",VLOOKUP(A101,'Aux - pivots1'!$A:$E,3,0)) | Q101: =IF(VLOOKUP(A101,'Aux - pivots1'!$A:$E,4,0)=0, "",VLOOKUP(A101,'Aux - pivots1'!$A:$E,4,0)) | R101: =IF(VLOOKUP(A101,'Aux - pivots1'!$A:$E,5,0)=0, "",VLOOKUP(A101,'Aux - pivots1'!$A:$E,5,0)) | U101: Novo Projeto - Em especificação | Y101: Novo Plano | Z101: HF
A102: =E102&F102 -> modesg_out_bens_imoveisflg_rsc_fsc_agd | B102: Pilar III | C102: Modelo Verde - Output | D102: 2. Campo | E102: modesg_out_bens_imoveis | F102: flg_rsc_fsc_agd | G102: =VLOOKUP(A102,Plano_V3!$A$26:$G$768,7,0) -> 1. Concluído | H102: 1. Concluído | J102: Package 2 | K102: Package x | P102: =IF(VLOOKUP(A93,'Aux - pivots1'!$A:$E,3,0)=0, "",VLOOKUP(A93,'Aux - pivots1'!$A:$E,3,0)) | Q102: =IF(VLOOKUP(A93,'Aux - pivots1'!$A:$E,4,0)=0, "",VLOOKUP(A93,'Aux - pivots1'!$A:$E,4,0)) | R102: =IF(VLOOKUP(A93,'Aux - pivots1'!$A:$E,5,0)=0, "",VLOOKUP(A93,'Aux - pivots1'!$A:$E,5,0)) | U102: Novo Projeto - Em especificação | Y102: Plano anterior | Z102: HF
A103: =E103&F103 -> modesg_out_bens_imoveisflg_rsc_fsc_crnc | B103: Pilar III | C103: Modelo Verde - Output | D103: 2. Campo | E103: modesg_out_bens_imoveis | F103: flg_rsc_fsc_crnc | G103: =VLOOKUP(A103,Plano_V3!$A$26:$G$768,7,0) -> 1. Concluído | H103: 1. Concluído | J103: Package 2 | K103: Package x | P103: =IF(VLOOKUP(A94,'Aux - pivots1'!$A:$E,3,0)=0, "",VLOOKUP(A94,'Aux - pivots1'!$A:$E,3,0)) | Q103: =IF(VLOOKUP(A94,'Aux - pivots1'!$A:$E,4,0)=0, "",VLOOKUP(A94,'Aux - pivots1'!$A:$E,4,0)) | R103: =IF(VLOOKUP(A94,'Aux - pivots1'!$A:$E,5,0)=0, "",VLOOKUP(A94,'Aux - pivots1'!$A:$E,5,0)) | U103: Novo Projeto - Em especificação | Y103: Plano anterior | Z103: HF
A104: =E104&F104 -> modesg_out_bens_imoveisorigem_flg_rsc_fsc_agd | B104: Pilar III | C104: Modelo Verde - Output | D104: 2. Campo | E104: modesg_out_bens_imoveis | F104: origem_flg_rsc_fsc_agd | G104: =VLOOKUP(A104,Plano_V3!$A$26:$G$768,7,0) -> 1. Concluído | H104: 1. Concluído | J104: Package 2 | K104: Package x | P104: =IF(VLOOKUP(A95,'Aux - pivots1'!$A:$E,3,0)=0, "",VLOOKUP(A95,'Aux - pivots1'!$A:$E,3,0)) | Q104: =IF(VLOOKUP(A95,'Aux - pivots1'!$A:$E,4,0)=0, "",VLOOKUP(A95,'Aux - pivots1'!$A:$E,4,0)) | R104: =IF(VLOOKUP(A95,'Aux - pivots1'!$A:$E,5,0)=0, "",VLOOKUP(A95,'Aux - pivots1'!$A:$E,5,0)) | U104: Novo Projeto - Em especificação | Y104: Plano anterior
A105: =E105&F105 -> modesg_out_bens_imoveisorigem_flg_rsc_fsc_crnc | B105: Pilar III | C105: Modelo Verde - Output | D105: 2. Campo | E105: modesg_out_bens_imoveis | F105: origem_flg_rsc_fsc_crnc | G105: =VLOOKUP(A105,Plano_V3!$A$26:$G$768,7,0) -> 1. Concluído | H105: 1. Concluído | J105: Package 2 | K105: Package x | P105: =IF(VLOOKUP(A96,'Aux - pivots1'!$A:$E,3,0)=0, "",VLOOKUP(A96,'Aux - pivots1'!$A:$E,3,0)) | Q105: =IF(VLOOKUP(A96,'Aux - pivots1'!$A:$E,4,0)=0, "",VLOOKUP(A96,'Aux - pivots1'!$A:$E,4,0)) | R105: =IF(VLOOKUP(A96,'Aux - pivots1'!$A:$E,5,0)=0, "",VLOOKUP(A96,'Aux - pivots1'!$A:$E,5,0)) | U105: Novo Projeto - Em especificação | Y105: Plano anterior
A106: =E106&F106 -> modesg_out_empr_info_nfinorigem_scp1_emss | B106: Pilar III | C106: Modelo Verde - Output | D106: 2. Campo | E106: modesg_out_empr_info_nfin | F106: origem_scp1_emss | G106: =VLOOKUP(A106,Plano_V3!$A$26:$G$768,7,0) -> 1. Concluído | H106: 1. Concluído | K106: Package x | P106: =IF(VLOOKUP(A97,'Aux - pivots1'!$A:$E,3,0)=0, "",VLOOKUP(A97,'Aux - pivots1'!$A:$E,3,0)) | Q106: =IF(VLOOKUP(A97,'Aux - pivots1'!$A:$E,4,0)=0, "",VLOOKUP(A97,'Aux - pivots1'!$A:$E,4,0)) | R106: =IF(VLOOKUP(A97,'Aux - pivots1'!$A:$E,5,0)=0, "",VLOOKUP(A97,'Aux - pivots1'!$A:$E,5,0)) | Y106: Plano anterior | Z106: HF
A107: =E107&F107 -> modesg_out_empr_info_nfinorigem_scp2_emss | B107: Pilar III | C107: Modelo Verde - Output | D107: 2. Campo | E107: modesg_out_empr_info_nfin | F107: origem_scp2_emss | G107: =VLOOKUP(A107,Plano_V3!$A$26:$G$768,7,0) -> 1. Concluído | H107: 1. Concluído | K107: Package x | P107: =IF(VLOOKUP(A98,'Aux - pivots1'!$A:$E,3,0)=0, "",VLOOKUP(A98,'Aux - pivots1'!$A:$E,3,0)) | Q107: =IF(VLOOKUP(A98,'Aux - pivots1'!$A:$E,4,0)=0, "",VLOOKUP(A98,'Aux - pivots1'!$A:$E,4,0)) | R107: =IF(VLOOKUP(A98,'Aux - pivots1'!$A:$E,5,0)=0, "",VLOOKUP(A98,'Aux - pivots1'!$A:$E,5,0)) | Y107: Plano anterior | Z107: HF
A108: =E108&F108 -> modesg_out_empr_info_nfinorigem_scp3_emss | B108: Pilar III | C108: Modelo Verde - Output | D108: 2. Campo | E108: modesg_out_empr_info_nfin | F108: origem_scp3_emss | G108: =VLOOKUP(A108,Plano_V3!$A$26:$G$768,7,0) -> 1. Concluído | H108: 1. Concluído | K108: Package x | P108: =IF(VLOOKUP(A99,'Aux - pivots1'!$A:$E,3,0)=0, "",VLOOKUP(A99,'Aux - pivots1'!$A:$E,3,0)) | Q108: =IF(VLOOKUP(A99,'Aux - pivots1'!$A:$E,4,0)=0, "",VLOOKUP(A99,'Aux - pivots1'!$A:$E,4,0)) | R108: =IF(VLOOKUP(A99,'Aux - pivots1'!$A:$E,5,0)=0, "",VLOOKUP(A99,'Aux - pivots1'!$A:$E,5,0)) | Y108: Plano anterior | Z108: HF
A109: =E109&F109 -> modesg_out_empr_info_nfinscp1_emss | B109: Pilar III | C109: Modelo Verde - Output | D109: 2. Campo | E109: modesg_out_empr_info_nfin | F109: scp1_emss | G109: =VLOOKUP(A109,Plano_V3!$A$26:$G$768,7,0) -> 1. Concluído | H109: 1. Concluído | K109: Package x | P109: =IF(VLOOKUP(A100,'Aux - pivots1'!$A:$E,3,0)=0, "",VLOOKUP(A100,'Aux - pivots1'!$A:$E,3,0)) | Q109: =IF(VLOOKUP(A100,'Aux - pivots1'!$A:$E,4,0)=0, "",VLOOKUP(A100,'Aux - pivots1'!$A:$E,4,0)) | R109: =IF(VLOOKUP(A100,'Aux - pivots1'!$A:$E,5,0)=0, "",VLOOKUP(A100,'Aux - pivots1'!$A:$E,5,0)) | Y109: Plano anterior | Z109: HF
A110: =E110&F110 -> modesg_out_empr_info_nfinscp2_emss | B110: Pilar III | C110: Modelo Verde - Output | D110: 2. Campo | E110: modesg_out_empr_info_nfin | F110: scp2_emss | G110: =VLOOKUP(A110,Plano_V3!$A$26:$G$768,7,0) -> 1. Concluído | H110: 1. Concluído | K110: Package x | P110: =IF(VLOOKUP(A101,'Aux - pivots1'!$A:$E,3,0)=0, "",VLOOKUP(A101,'Aux - pivots1'!$A:$E,3,0)) | Q110: =IF(VLOOKUP(A101,'Aux - pivots1'!$A:$E,4,0)=0, "",VLOOKUP(A101,'Aux - pivots1'!$A:$E,4,0)) | R110: =IF(VLOOKUP(A101,'Aux - pivots1'!$A:$E,5,0)=0, "",VLOOKUP(A101,'Aux - pivots1'!$A:$E,5,0)) | Y110: Plano anterior | Z110: HF
A111: =E111&F111 -> modesg_out_empr_info_nfinscp3_emss | B111: Pilar III | C111: Modelo Verde - Output | D111: 2. Campo | E111: modesg_out_empr_info_nfin | F111: scp3_emss | G111: =VLOOKUP(A111,Plano_V3!$A$26:$G$768,7,0) -> 1. Concluído | H111: 1. Concluído | K111: Package x | P111: =IF(VLOOKUP(A101,'Aux - pivots1'!$A:$E,3,0)=0, "",VLOOKUP(A101,'Aux - pivots1'!$A:$E,3,0)) | Q111: =IF(VLOOKUP(A101,'Aux - pivots1'!$A:$E,4,0)=0, "",VLOOKUP(A101,'Aux - pivots1'!$A:$E,4,0)) | R111: =IF(VLOOKUP(A101,'Aux - pivots1'!$A:$E,5,0)=0, "",VLOOKUP(A101,'Aux - pivots1'!$A:$E,5,0)) | Y111: Plano anterior | Z111: HF
A112: =E112&F112 -> modesg_out_empr_info_nfindivida_total | B112: Pilar III | C112: Modelo Verde - Output | D112: 2. Campo | E112: modesg_out_empr_info_nfin | F112: divida_total | G112: =VLOOKUP(A112,Plano_V3!$A$26:$G$768,7,0) -> 1. Concluído | H112: 1. Concluído | K112: Package x | P112: =IF(VLOOKUP(A101,'Aux - pivots1'!$A:$E,3,0)=0, "",VLOOKUP(A101,'Aux - pivots1'!$A:$E,3,0)) | Q112: =IF(VLOOKUP(A101,'Aux - pivots1'!$A:$E,4,0)=0, "",VLOOKUP(A101,'Aux - pivots1'!$A:$E,4,0)) | R112: =IF(VLOOKUP(A101,'Aux - pivots1'!$A:$E,5,0)=0, "",VLOOKUP(A101,'Aux - pivots1'!$A:$E,5,0)) | Y112: Plano anterior | Z112: HF
A113: =E113&F113 -> modesg_out_empr_info_nfincapital_proprio | B113: Pilar III | C113: Modelo Verde - Output | D113: 2. Campo | E113: modesg_out_empr_info_nfin | F113: capital_proprio | G113: =VLOOKUP(A113,Plano_V3!$A$26:$G$768,7,0) -> 1. Concluído | H113: 1. Concluído | K113: Package x | P113: =IF(VLOOKUP(A102,'Aux - pivots1'!$A:$E,3,0)=0, "",VLOOKUP(A102,'Aux - pivots1'!$A:$E,3,0)) | Q113: =IF(VLOOKUP(A102,'Aux - pivots1'!$A:$E,4,0)=0, "",VLOOKUP(A102,'Aux - pivots1'!$A:$E,4,0)) | R113: =IF(VLOOKUP(A102,'Aux - pivots1'!$A:$E,5,0)=0, "",VLOOKUP(A102,'Aux - pivots1'!$A:$E,5,0)) | Y113: Plano anterior | Z113: HF
A114: =E114&F114 -> lt004_protectionflg_act_physcl_rsk | B114: Pilar III | C114: Pilar III | D114: 2. Campo | E114: lt004_protection | F114: flg_act_physcl_rsk | G114: =VLOOKUP(A114,Plano_V3!$A$26:$G$768,7,0) -> 1. Concluído | H114: 1. Concluído | K114: Package x | P114: =IF(VLOOKUP(A105,'Aux - pivots1'!$A:$E,3,0)=0, "",VLOOKUP(A105,'Aux - pivots1'!$A:$E,3,0)) | Q114: =IF(VLOOKUP(A105,'Aux - pivots1'!$A:$E,4,0)=0, "",VLOOKUP(A105,'Aux - pivots1'!$A:$E,4,0)) | R114: =IF(VLOOKUP(A105,'Aux - pivots1'!$A:$E,5,0)=0, "",VLOOKUP(A105,'Aux - pivots1'!$A:$E,5,0)) | Y114: Plano anterior
A115: =E115&F115 -> lt004_protectionflg_chrnc_physcl_rsk | B115: Pilar III | C115: Pilar III | D115: 2. Campo | E115: lt004_protection | F115: flg_chrnc_physcl_rsk | G115: =VLOOKUP(A115,Plano_V3!$A$26:$G$768,7,0) -> 1. Concluído | H115: 1. Concluído | K115: Package x | P115: =IF(VLOOKUP(A106,'Aux - pivots1'!$A:$E,3,0)=0, "",VLOOKUP(A106,'Aux - pivots1'!$A:$E,3,0)) | Q115: =IF(VLOOKUP(A106,'Aux - pivots1'!$A:$E,4,0)=0, "",VLOOKUP(A106,'Aux - pivots1'!$A:$E,4,0)) | R115: =IF(VLOOKUP(A106,'Aux - pivots1'!$A:$E,5,0)=0, "",VLOOKUP(A106,'Aux - pivots1'!$A:$E,5,0)) | Y115: Plano anterior
A116: =E116&F116 -> modesg_out_empr_info_nfincod_nace_esg | B116: Pilar III | C116: Modelo Verde - Output | D116: 2. Campo | E116: modesg_out_empr_info_nfin | F116: cod_nace_esg | G116: =VLOOKUP(A116,Plano_V3!$A$26:$G$768,7,0) -> 1. Concluído | H116: 1. Concluído | J116: Package 1 | K116: Package x | P116: =IF(VLOOKUP(A87,'Aux - pivots1'!$A:$E,3,0)=0, "",VLOOKUP(A87,'Aux - pivots1'!$A:$E,3,0)) | Q116: =IF(VLOOKUP(A87,'Aux - pivots1'!$A:$E,4,0)=0, "",VLOOKUP(A87,'Aux - pivots1'!$A:$E,4,0)) | R116: =IF(VLOOKUP(A87,'Aux - pivots1'!$A:$E,5,0)=0, "",VLOOKUP(A87,'Aux - pivots1'!$A:$E,5,0)) | Y116: Plano anterior | Z116: JB
A117: =E117&F117 -> modesg_out_empr_info_nfinflg_rsc_fsc_agd | B117: Pilar III | C117: Modelo Verde - Output | D117: 2. Campo | E117: modesg_out_empr_info_nfin | F117: flg_rsc_fsc_agd | G117: =VLOOKUP(A117,Plano_V3!$A$26:$G$768,7,0) -> 1. Concluído | H117: 1. Concluído | J117: Package 2 | K117: Package x | P117: =IF(VLOOKUP(A88,'Aux - pivots1'!$A:$E,3,0)=0, "",VLOOKUP(A88,'Aux - pivots1'!$A:$E,3,0)) | Q117: =IF(VLOOKUP(A88,'Aux - pivots1'!$A:$E,4,0)=0, "",VLOOKUP(A88,'Aux - pivots1'!$A:$E,4,0)) | R117: =IF(VLOOKUP(A88,'Aux - pivots1'!$A:$E,5,0)=0, "",VLOOKUP(A88,'Aux - pivots1'!$A:$E,5,0)) | U117: Novo Projeto - Em especificação | Y117: Plano anterior (mas na proposta) | Z117: HF
A118: =E118&F118 -> modesg_out_empr_info_nfinflg_rsc_fsc_crnc | B118: Pilar III | C118: Modelo Verde - Output | D118: 2. Campo | E118: modesg_out_empr_info_nfin | F118: flg_rsc_fsc_crnc | G118: =VLOOKUP(A118,Plano_V3!$A$26:$G$768,7,0) -> 1. Concluído | H118: 1. Concluído | J118: Package 2 | K118: Package x | P118: =IF(VLOOKUP(A89,'Aux - pivots1'!$A:$E,3,0)=0, "",VLOOKUP(A89,'Aux - pivots1'!$A:$E,3,0)) | Q118: =IF(VLOOKUP(A89,'Aux - pivots1'!$A:$E,4,0)=0, "",VLOOKUP(A89,'Aux - pivots1'!$A:$E,4,0)) | R118: =IF(VLOOKUP(A89,'Aux - pivots1'!$A:$E,5,0)=0, "",VLOOKUP(A89,'Aux - pivots1'!$A:$E,5,0)) | U118: Novo Projeto - Em especificação | Y118: Plano anterior (mas na proposta) | Z118: HF
A119: =E119&F119 -> modesg_out_empr_info_nfinorigem_flg_rsc_fsc_agd | B119: Pilar III | C119: Modelo Verde - Output | D119: 2. Campo | E119: modesg_out_empr_info_nfin | F119: origem_flg_rsc_fsc_agd | G119: =VLOOKUP(A119,Plano_V3!$A$26:$G$768,7,0) -> 1. Concluído | H119: 1. Concluído | J119: Package 2 | K119: Package x | P119: =IF(VLOOKUP(A90,'Aux - pivots1'!$A:$E,3,0)=0, "",VLOOKUP(A90,'Aux - pivots1'!$A:$E,3,0)) | Q119: =IF(VLOOKUP(A90,'Aux - pivots1'!$A:$E,4,0)=0, "",VLOOKUP(A90,'Aux - pivots1'!$A:$E,4,0)) | R119: =IF(VLOOKUP(A90,'Aux - pivots1'!$A:$E,5,0)=0, "",VLOOKUP(A90,'Aux - pivots1'!$A:$E,5,0)) | U119: Novo Projeto - Em especificação | Y119: Plano anterior (mas na proposta) | Z119: HF
A120: =E120&F120 -> modesg_out_empr_info_nfinorigem_flg_rsc_fsc_crnc | B120: Pilar III | C120: Modelo Verde - Output | D120: 2. Campo | E120: modesg_out_empr_info_nfin | F120: origem_flg_rsc_fsc_crnc | G120: =VLOOKUP(A120,Plano_V3!$A$26:$G$768,7,0) -> 1. Concluído | H120: 1. Concluído | J120: Package 2 | K120: Package x | P120: =IF(VLOOKUP(A111,'Aux - pivots1'!$A:$E,3,0)=0, "",VLOOKUP(A111,'Aux - pivots1'!$A:$E,3,0)) | Q120: =IF(VLOOKUP(A111,'Aux - pivots1'!$A:$E,4,0)=0, "",VLOOKUP(A111,'Aux - pivots1'!$A:$E,4,0)) | R120: =IF(VLOOKUP(A111,'Aux - pivots1'!$A:$E,5,0)=0, "",VLOOKUP(A111,'Aux - pivots1'!$A:$E,5,0)) | U120: Novo Projeto - Em especificação | Y120: Plano anterior (mas na proposta) | Z120: HF
A121: =E121&F121 -> PROPERTY_ENERGY_CERTIFICATEEP_SCORE | B121: Pilar III | C121: Bens Imóveis - Output | D121: 2. Campo | E121: PROPERTY_ENERGY_CERTIFICATE | F121: EP_SCORE | G121: =VLOOKUP(A121,Plano_V3!$A$26:$G$768,7,0) -> 4. Validação EF | H121: 4. Validação EF | J121: Package 6 | K121: Package 22 | L121: A confirmar data de entrega | M121: 45737 | P121: =IF(VLOOKUP(A121,'Aux - pivots1'!$A:$E,3,0)=0, "",VLOOKUP(A121,'Aux - pivots1'!$A:$E,3,0)) | Q121: =IF(VLOOKUP(A121,'Aux - pivots1'!$A:$E,4,0)=0, "",VLOOKUP(A121,'Aux - pivots1'!$A:$E,4,0)) | R121: =IF(VLOOKUP(A121,'Aux - pivots1'!$A:$E,5,0)=0, "",VLOOKUP(A121,'Aux - pivots1'!$A:$E,5,0)) | Y121: Plano anterior
A122: =E122&F122 -> PROPERTY_ENERGY_CERTIFICATEENERGY_CONSUMPTION_VALUE_YEAR | B122: Pilar III | C122: Bens Imóveis - Output | D122: 2. Campo | E122: PROPERTY_ENERGY_CERTIFICATE | F122: ENERGY_CONSUMPTION_VALUE_YEAR | G122: =VLOOKUP(A122,Plano_V3!$A$26:$G$768,7,0) -> 1. Concluído | H122: 1. Concluído | J122: Package 6 | K122: Package 22 | L122: 45730 | M122: 45737 | P122: =IF(VLOOKUP(A122,'Aux - pivots1'!$A:$E,3,0)=0, "",VLOOKUP(A122,'Aux - pivots1'!$A:$E,3,0)) | Q122: =IF(VLOOKUP(A122,'Aux - pivots1'!$A:$E,4,0)=0, "",VLOOKUP(A122,'Aux - pivots1'!$A:$E,4,0)) | R122: =IF(VLOOKUP(A122,'Aux - pivots1'!$A:$E,5,0)=0, "",VLOOKUP(A122,'Aux - pivots1'!$A:$E,5,0)) | Y122: Plano anterior
A123: =E123&F123 -> modesg_param_sfics_taxon_europeiacod_regra | B123: Pilar III | C123: Modelo Verde - Input | D123: 2. Campo | E123: modesg_param_sfics_taxon_europeia | F123: cod_regra | G123: =VLOOKUP(A123,Plano_V3!$A$26:$G$768,7,0) -> 1. Concluído | H123: 1. Concluído | K123: Package 22 | L123: A confirmar data de entrega | M123: 45737 | P123: =IF(VLOOKUP(A123,'Aux - pivots1'!$A:$E,3,0)=0, "",VLOOKUP(A123,'Aux - pivots1'!$A:$E,3,0)) | Q123: =IF(VLOOKUP(A123,'Aux - pivots1'!$A:$E,4,0)=0, "",VLOOKUP(A123,'Aux - pivots1'!$A:$E,4,0)) | R123: =IF(VLOOKUP(A123,'Aux - pivots1'!$A:$E,5,0)=0, "",VLOOKUP(A123,'Aux - pivots1'!$A:$E,5,0)) | Y123: Plano anterior | Z123: RC
A124: =E124&F124 -> modesg_param_sfics_taxon_europeianivel | B124: Pilar III | C124: Modelo Verde - Input | D124: 2. Campo | E124: modesg_param_sfics_taxon_europeia | F124: nivel | G124: =VLOOKUP(A124,Plano_V3!$A$26:$G$768,7,0) -> 0. Cancelado | H124: 0. Cancelado | P124: =IF(VLOOKUP(A124,'Aux - pivots1'!$A:$E,3,0)=0, "",VLOOKUP(A124,'Aux - pivots1'!$A:$E,3,0)) | Q124: =IF(VLOOKUP(A124,'Aux - pivots1'!$A:$E,4,0)=0, "",VLOOKUP(A124,'Aux - pivots1'!$A:$E,4,0)) | R124: =IF(VLOOKUP(A124,'Aux - pivots1'!$A:$E,5,0)=0, "",VLOOKUP(A124,'Aux - pivots1'!$A:$E,5,0)) | Y124: Plano anterior | Z124: RC
A125: =E125&F125 -> modesg_param_sfics_taxon_europeiagrupo_regra | B125: Pilar III | C125: Modelo Verde - Input | D125: 2. Campo | E125: modesg_param_sfics_taxon_europeia | F125: grupo_regra | G125: =VLOOKUP(A125,Plano_V3!$A$26:$G$768,7,0) -> 0. Cancelado | H125: 0. Cancelado | K125: Package 22 | L125: 45733 | M125: 45737 | P125: =IF(VLOOKUP(A125,'Aux - pivots1'!$A:$E,3,0)=0, "",VLOOKUP(A125,'Aux - pivots1'!$A:$E,3,0)) | Q125: =IF(VLOOKUP(A125,'Aux - pivots1'!$A:$E,4,0)=0, "",VLOOKUP(A125,'Aux - pivots1'!$A:$E,4,0)) | R125: =IF(VLOOKUP(A125,'Aux - pivots1'!$A:$E,5,0)=0, "",VLOOKUP(A125,'Aux - pivots1'!$A:$E,5,0)) | Y125: Plano anterior (campo adicionado 21/02)
A126: =E126&F126 -> modesg_param_sfics_taxon_europeiadscrc | B126: Pilar III | C126: Modelo Verde - Input | D126: 2. Campo | E126: modesg_param_sfics_taxon_europeia | F126: dscrc | G126: =VLOOKUP(A126,Plano_V3!$A$26:$G$768,7,0) -> 1. Concluído | H126: 1. Concluído | K126: Package 22 | L126: A confirmar data de entrega | M126: 45737 | P126: =IF(VLOOKUP(A126,'Aux - pivots1'!$A:$E,3,0)=0, "",VLOOKUP(A126,'Aux - pivots1'!$A:$E,3,0)) | Q126: =IF(VLOOKUP(A126,'Aux - pivots1'!$A:$E,4,0)=0, "",VLOOKUP(A126,'Aux - pivots1'!$A:$E,4,0)) | R126: =IF(VLOOKUP(A126,'Aux - pivots1'!$A:$E,5,0)=0, "",VLOOKUP(A126,'Aux - pivots1'!$A:$E,5,0)) | Y126: Plano anterior | Z126: RC
A127: =E127&F127 -> modesg_param_sfics_taxon_europeiacomite | B127: Pilar III | C127: Modelo Verde - Input | D127: 2. Campo | E127: modesg_param_sfics_taxon_europeia | F127: comite | G127: =VLOOKUP(A127,Plano_V3!$A$26:$G$768,7,0) -> 1. Concluído | H127: 1. Concluído | K127: Package 22 | L127: A confirmar data de entrega | M127: 45737 | P127: =IF(VLOOKUP(A127,'Aux - pivots1'!$A:$E,3,0)=0, "",VLOOKUP(A127,'Aux - pivots1'!$A:$E,3,0)) | Q127: =IF(VLOOKUP(A127,'Aux - pivots1'!$A:$E,4,0)=0, "",VLOOKUP(A127,'Aux - pivots1'!$A:$E,4,0)) | R127: =IF(VLOOKUP(A127,'Aux - pivots1'!$A:$E,5,0)=0, "",VLOOKUP(A127,'Aux - pivots1'!$A:$E,5,0)) | Y127: Plano anterior | Z127: RC
A128: =E128&F128 -> modesg_param_sfics_taxon_europeiadata_aprvc | B128: Pilar III | C128: Modelo Verde - Input | D128: 2. Campo | E128: modesg_param_sfics_taxon_europeia | F128: data_aprvc | G128: =VLOOKUP(A128,Plano_V3!$A$26:$G$768,7,0) -> 1. Concluído | H128: 1. Concluído | K128: Package 22 | L128: A confirmar data de entrega | M128: 45737 | P128: =IF(VLOOKUP(A128,'Aux - pivots1'!$A:$E,3,0)=0, "",VLOOKUP(A128,'Aux - pivots1'!$A:$E,3,0)) | Q128: =IF(VLOOKUP(A128,'Aux - pivots1'!$A:$E,4,0)=0, "",VLOOKUP(A128,'Aux - pivots1'!$A:$E,4,0)) | R128: =IF(VLOOKUP(A128,'Aux - pivots1'!$A:$E,5,0)=0, "",VLOOKUP(A128,'Aux - pivots1'!$A:$E,5,0)) | Y128: Plano anterior | Z128: RC
A129: =E129&F129 -> modesg_param_sfics_taxon_europeiadata_inicial | B129: Pilar III | C129: Modelo Verde - Input | D129: 2. Campo | E129: modesg_param_sfics_taxon_europeia | F129: data_inicial | G129: =VLOOKUP(A129,Plano_V3!$A$26:$G$768,7,0) -> 1. Concluído | H129: 1. Concluído | K129: Package 22 | L129: A confirmar data de entrega | M129: 45737 | P129: =IF(VLOOKUP(A129,'Aux - pivots1'!$A:$E,3,0)=0, "",VLOOKUP(A129,'Aux - pivots1'!$A:$E,3,0)) | Q129: =IF(VLOOKUP(A129,'Aux - pivots1'!$A:$E,4,0)=0, "",VLOOKUP(A129,'Aux - pivots1'!$A:$E,4,0)) | R129: =IF(VLOOKUP(A129,'Aux - pivots1'!$A:$E,5,0)=0, "",VLOOKUP(A129,'Aux - pivots1'!$A:$E,5,0)) | Y129: Plano anterior | Z129: RC
A130: =E130&F130 -> modesg_param_sfics_taxon_europeiadata_final | B130: Pilar III | C130: Modelo Verde - Input | D130: 2. Campo | E130: modesg_param_sfics_taxon_europeia | F130: data_final | G130: =VLOOKUP(A130,Plano_V3!$A$26:$G$768,7,0) -> 1. Concluído | H130: 1. Concluído | K130: Package 22 | L130: A confirmar data de entrega | M130: 45737 | P130: =IF(VLOOKUP(A130,'Aux - pivots1'!$A:$E,3,0)=0, "",VLOOKUP(A130,'Aux - pivots1'!$A:$E,3,0)) | Q130: =IF(VLOOKUP(A130,'Aux - pivots1'!$A:$E,4,0)=0, "",VLOOKUP(A130,'Aux - pivots1'!$A:$E,4,0)) | R130: =IF(VLOOKUP(A130,'Aux - pivots1'!$A:$E,5,0)=0, "",VLOOKUP(A130,'Aux - pivots1'!$A:$E,5,0)) | Y130: Plano anterior | Z130: RC
A131: =E131&F131 -> modesg_param_sfics_taxon_europeiazcliente | B131: Pilar III | C131: Modelo Verde - Input | D131: 2. Campo | E131: modesg_param_sfics_taxon_europeia | F131: zcliente | G131: =VLOOKUP(A131,Plano_V3!$A$26:$G$768,7,0) -> 1. Concluído | H131: 1. Concluído | K131: Package 22 | L131: A confirmar data de entrega | M131: 45737 | P131: =IF(VLOOKUP(A131,'Aux - pivots1'!$A:$E,3,0)=0, "",VLOOKUP(A131,'Aux - pivots1'!$A:$E,3,0)) | Q131: =IF(VLOOKUP(A131,'Aux - pivots1'!$A:$E,4,0)=0, "",VLOOKUP(A131,'Aux - pivots1'!$A:$E,4,0)) | R131: =IF(VLOOKUP(A131,'Aux - pivots1'!$A:$E,5,0)=0, "",VLOOKUP(A131,'Aux - pivots1'!$A:$E,5,0)) | Y131: Plano anterior | Z131: RC
A132: =E132&F132 -> modesg_param_sfics_taxon_europeiacempcta | B132: Pilar III | C132: Modelo Verde - Input | D132: 2. Campo | E132: modesg_param_sfics_taxon_europeia | F132: cempcta | G132: =VLOOKUP(A132,Plano_V3!$A$26:$G$768,7,0) -> 1. Concluído | H132: 1. Concluído | K132: Package 22 | L132: A confirmar data de entrega | M132: 45737 | P132: =IF(VLOOKUP(A132,'Aux - pivots1'!$A:$E,3,0)=0, "",VLOOKUP(A132,'Aux - pivots1'!$A:$E,3,0)) | Q132: =IF(VLOOKUP(A132,'Aux - pivots1'!$A:$E,4,0)=0, "",VLOOKUP(A132,'Aux - pivots1'!$A:$E,4,0)) | R132: =IF(VLOOKUP(A132,'Aux - pivots1'!$A:$E,5,0)=0, "",VLOOKUP(A132,'Aux - pivots1'!$A:$E,5,0)) | Y132: Plano anterior (sem visibilidade no PdS enviado 17/01) | Z132: RC
A133: =E133&F133 -> modesg_param_sfics_taxon_europeiackbalcao | B133: Pilar III | C133: Modelo Verde - Input | D133: 2. Campo | E133: modesg_param_sfics_taxon_europeia | F133: ckbalcao | G133: =VLOOKUP(A133,Plano_V3!$A$26:$G$768,7,0) -> 1. Concluído | H133: 1. Concluído | K133: Package 22 | L133: A confirmar data de entrega | M133: 45737 | P133: =IF(VLOOKUP(A133,'Aux - pivots1'!$A:$E,3,0)=0, "",VLOOKUP(A133,'Aux - pivots1'!$A:$E,3,0)) | Q133: =IF(VLOOKUP(A133,'Aux - pivots1'!$A:$E,4,0)=0, "",VLOOKUP(A133,'Aux - pivots1'!$A:$E,4,0)) | R133: =IF(VLOOKUP(A133,'Aux - pivots1'!$A:$E,5,0)=0, "",VLOOKUP(A133,'Aux - pivots1'!$A:$E,5,0)) | Y133: Plano anterior | Z133: RC
A134: =E134&F134 -> modesg_param_sfics_taxon_europeiacknumcta | B134: Pilar III | C134: Modelo Verde - Input | D134: 2. Campo | E134: modesg_param_sfics_taxon_europeia | F134: cknumcta | G134: =VLOOKUP(A134,Plano_V3!$A$26:$G$768,7,0) -> 1. Concluído | H134: 1. Concluído | K134: Package 22 | L134: A confirmar data de entrega | M134: 45737 | P134: =IF(VLOOKUP(A134,'Aux - pivots1'!$A:$E,3,0)=0, "",VLOOKUP(A134,'Aux - pivots1'!$A:$E,3,0)) | Q134: =IF(VLOOKUP(A134,'Aux - pivots1'!$A:$E,4,0)=0, "",VLOOKUP(A134,'Aux - pivots1'!$A:$E,4,0)) | R134: =IF(VLOOKUP(A134,'Aux - pivots1'!$A:$E,5,0)=0, "",VLOOKUP(A134,'Aux - pivots1'!$A:$E,5,0)) | Y134: Plano anterior | Z134: RC
A135: =E135&F135 -> modesg_param_sfics_taxon_europeiazdeposit | B135: Pilar III | C135: Modelo Verde - Input | D135: 2. Campo | E135: modesg_param_sfics_taxon_europeia | F135: zdeposit | G135: =VLOOKUP(A135,Plano_V3!$A$26:$G$768,7,0) -> 1. Concluído | H135: 1. Concluído | K135: Package 22 | L135: A confirmar data de entrega | M135: 45737 | P135: =IF(VLOOKUP(A135,'Aux - pivots1'!$A:$E,3,0)=0, "",VLOOKUP(A135,'Aux - pivots1'!$A:$E,3,0)) | Q135: =IF(VLOOKUP(A135,'Aux - pivots1'!$A:$E,4,0)=0, "",VLOOKUP(A135,'Aux - pivots1'!$A:$E,4,0)) | R135: =IF(VLOOKUP(A135,'Aux - pivots1'!$A:$E,5,0)=0, "",VLOOKUP(A135,'Aux - pivots1'!$A:$E,5,0)) | Y135: Plano anterior | Z135: RC
A136: =E136&F136 -> modesg_param_sfics_taxon_europeiackmetamis | B136: Pilar III | C136: Modelo Verde - Input | D136: 2. Campo | E136: modesg_param_sfics_taxon_europeia | F136: ckmetamis | G136: =VLOOKUP(A136,Plano_V3!$A$26:$G$768,7,0) -> 1. Concluído | H136: 1. Concluído | K136: Package 22 | L136: A confirmar data de entrega | M136: 45737 | P136: =IF(VLOOKUP(A136,'Aux - pivots1'!$A:$E,3,0)=0, "",VLOOKUP(A136,'Aux - pivots1'!$A:$E,3,0)) | Q136: =IF(VLOOKUP(A136,'Aux - pivots1'!$A:$E,4,0)=0, "",VLOOKUP(A136,'Aux - pivots1'!$A:$E,4,0)) | R136: =IF(VLOOKUP(A136,'Aux - pivots1'!$A:$E,5,0)=0, "",VLOOKUP(A136,'Aux - pivots1'!$A:$E,5,0)) | Y136: Plano anterior | Z136: RC
A137: =E137&F137 -> modesg_param_sfics_taxon_europeiackprodmi | B137: Pilar III | C137: Modelo Verde - Input | D137: 2. Campo | E137: modesg_param_sfics_taxon_europeia | F137: ckprodmi | G137: =VLOOKUP(A137,Plano_V3!$A$26:$G$768,7,0) -> 1. Concluído | H137: 1. Concluído | K137: Package 22 | L137: A confirmar data de entrega | M137: 45737 | P137: =IF(VLOOKUP(A137,'Aux - pivots1'!$A:$E,3,0)=0, "",VLOOKUP(A137,'Aux - pivots1'!$A:$E,3,0)) | Q137: =IF(VLOOKUP(A137,'Aux - pivots1'!$A:$E,4,0)=0, "",VLOOKUP(A137,'Aux - pivots1'!$A:$E,4,0)) | R137: =IF(VLOOKUP(A137,'Aux - pivots1'!$A:$E,5,0)=0, "",VLOOKUP(A137,'Aux - pivots1'!$A:$E,5,0)) | Y137: Plano anterior | Z137: RC
... A157: =E157&F157 -> modesg_param_sfics_taxon_europeiaref_date | B157: Pilar III | C157: Modelo Verde - Input | D157: 2. Campo | E157: modesg_param_sfics_taxon_europeia | F157: ref_date | G157: =VLOOKUP(A157,Plano_V3!$A$26:$G$768,7,0) -> 1. Concluído | H157: 1. Concluído | K157: Package 22 | L157: A confirmar data de entrega | M157: 45737 | P157: =IF(VLOOKUP(A157,'Aux - pivots1'!$A:$E,3,0)=0, "",VLOOKUP(A157,'Aux - pivots1'!$A:$E,3,0)) | Q157: =IF(VLOOKUP(A157,'Aux - pivots1'!$A:$E,4,0)=0, "",VLOOKUP(A157,'Aux - pivots1'!$A:$E,4,0)) | R157: =IF(VLOOKUP(A157,'Aux - pivots1'!$A:$E,5,0)=0, "",VLOOKUP(A157,'Aux - pivots1'!$A:$E,5,0)) | Y157: Plano anterior (sem visibilidade no PdS enviado 17/01) | Z157: RC
A158: =E158&F158 -> modesg_param_sfics_taxon_europeiacfinalidad | B158: Pilar III | C158: Modelo Verde - Input | D158: 2. Campo | E158: modesg_param_sfics_taxon_europeia | F158: cfinalidad | G158: =VLOOKUP(A158,Plano_V3!$A$26:$G$768,7,0) -> 1. Concluído | H158: 1. Concluído | K158: Package 22 | L158: A confirmar data de entrega | M158: 45737 | Y158: Plano anterior
A159: =E159&F159 -> modesg_param_sfics_taxon_europeiasst_indctr_aux | B159: Pilar III | C159: Modelo Verde - Input | D159: 2. Campo | E159: modesg_param_sfics_taxon_europeia | F159: sst_indctr_aux | G159: =VLOOKUP(A159,Plano_V3!$A$26:$G$768,7,0) -> 1. Concluído | H159: 1. Concluído | K159: Package 22 | L159: A confirmar data de entrega | M159: 45737 | P159: =IF(VLOOKUP(A159,'Aux - pivots1'!$A:$E,3,0)=0, "",VLOOKUP(A159,'Aux - pivots1'!$A:$E,3,0)) | Q159: =IF(VLOOKUP(A159,'Aux - pivots1'!$A:$E,4,0)=0, "",VLOOKUP(A159,'Aux - pivots1'!$A:$E,4,0)) | R159: =IF(VLOOKUP(A159,'Aux - pivots1'!$A:$E,5,0)=0, "",VLOOKUP(A159,'Aux - pivots1'!$A:$E,5,0)) | Y159: Plano anterior (campo adicionado 21/02)
A160: =E160&F160 -> modesg_param_sfics_taxon_europeiaquality_score | B160: Pilar III | C160: Modelo Verde - Input | D160: 2. Campo | E160: modesg_param_sfics_taxon_europeia | F160: quality_score | G160: =VLOOKUP(A160,Plano_V3!$A$26:$G$768,7,0) -> 1. Concluído | H160: 1. Concluído | K160: Package 22 | L160: A confirmar data de entrega | M160: 45737 | P160: =IF(VLOOKUP(A160,'Aux - pivots1'!$A:$E,3,0)=0, "",VLOOKUP(A160,'Aux - pivots1'!$A:$E,3,0)) | Q160: =IF(VLOOKUP(A160,'Aux - pivots1'!$A:$E,4,0)=0, "",VLOOKUP(A160,'Aux - pivots1'!$A:$E,4,0)) | R160: =IF(VLOOKUP(A160,'Aux - pivots1'!$A:$E,5,0)=0, "",VLOOKUP(A160,'Aux - pivots1'!$A:$E,5,0)) | Y160: Plano anterior (sem visibilidade no PdS enviado 17/01) | Z160: RC
A161: =E161&F161 -> modesg_param_sfics_taxon_europeiaprimary_energy_req_value | B161: Pilar III | C161: Modelo Verde - Input | D161: 2. Campo | E161: modesg_param_sfics_taxon_europeia | F161: primary_energy_req_value | G161: =VLOOKUP(A161,Plano_V3!$A$26:$G$768,7,0) -> 1. Concluído | H161: 1. Concluído | K161: Package 22 | L161: A confirmar data de entrega | M161: 45737 | P161: =IF(VLOOKUP(A161,'Aux - pivots1'!$A:$E,3,0)=0, "",VLOOKUP(A161,'Aux - pivots1'!$A:$E,3,0)) | Q161: =IF(VLOOKUP(A161,'Aux - pivots1'!$A:$E,4,0)=0, "",VLOOKUP(A161,'Aux - pivots1'!$A:$E,4,0)) | R161: =IF(VLOOKUP(A161,'Aux - pivots1'!$A:$E,5,0)=0, "",VLOOKUP(A161,'Aux - pivots1'!$A:$E,5,0)) | Y161: Plano anterior | Z161: RC
...

Sheet Caderno Testes FY24
N7: (alterar quando necessário) | R7: (data default - Dez2023)
B8: Âmbito | C8: Sub-âmbito | D8: Origem | E8: Campo Origem | F8: Tabela | G8: Campo | H8: concat | I8: Status | J8: Status2 | K8: Tipologia_Testes | L8: Necessidade de re-especificação? (campo) | M8: Complexidade | N8: Data de Alteração Status | O8: Estimação (horas) | P8: Notas | Q8: Owner | R8: Data alteração especificação | S8: Data de inicio testes | T8: Data de incidência / pedido esclarecimento | U8: Data de correção/resposta prevista | V8: Data de correção/resposta efetiva | W8: Horas efetivas | X8: Query | Y8: Aux
A9: =+Table1[[#This Row],[Tabela]]&Table1[[#This Row],[Campo]] -> ENERGY_CERTIFICATE_EST_INPUTn.a. | B9: Pilar III | C9: Bens Imóveis - Input | D9: bu_esg_work.kt_chave_gloval; bu_esg_work.gloval_clase_energetica_dez23 | E9: n.a. | F9: ENERGY_CERTIFICATE_EST_INPUT | G9: n.a. | H9: =Table1[[#This Row],[Tabela]]&Table1[[#This Row],[Campo]] -> ENERGY_CERTIFICATE_EST_INPUTn.a. | I9: 1. Concluído | J9: =VLOOKUP(Table1[[#This Row],[Status]],Auxiliar!$B$16:$C$24,2,0) -> 1 | K9: 1. Teste de universo | L9: Não | M9: Baixa | N9: 45716 | O9: =INDEX(Auxiliar!$D$5:$F$13,MATCH(Table1[[#This Row],[Tipologia_Testes]],Auxiliar!$B$5:$B$13,0),MATCH(Table1[[#This Row],[Complexidade]],Auxiliar!$D$4:$F$4,0)) -> 8 | R9: 45261 | T9: 45510 | U9: 45624 | W9: =VLOOKUP(Table1[[#This Row],[Status]],Auxiliar!$B$16:$D$24,3,0)*Table1[[#This Row],[Estimação (horas)]] -> 8 | X9: =+VLOOKUP(CONCATENATE(Table1[[#This Row],[Tabela]],Table1[[#This Row],[Campo]]),'2. Status Detalhe Campos FY24'!A:J,9,FALSE) -> Fase I | Y9: =+VLOOKUP(A9,#REF!,1,FALSE) -> #REF!
A10: =+Table1[[#This Row],[Tabela]]&Table1[[#This Row],[Campo]] -> ENERGY_CERTIFICATE_EST_INPUTDATA_PROVIDER | B10: Pilar III | C10: Bens Imóveis - Input | D10: bu_esg_work.kt_chave_gloval; bu_esg_work.gloval_clase_energetica_dez23 | E10: n.a. | F10: ENERGY_CERTIFICATE_EST_INPUT | G10: DATA_PROVIDER | H10: =Table1[[#This Row],[Tabela]]&Table1[[#This Row],[Campo]] -> ENERGY_CERTIFICATE_EST_INPUTDATA_PROVIDER | I10: 0. Cancelado | J10: =VLOOKUP(Table1[[#This Row],[Status]],Auxiliar!$B$16:$C$24,2,0) -> 0 | N10: 45688 | O10: =INDEX(Auxiliar!$D$5:$F$11,MATCH(Table1[[#This Row],[Tipologia_Testes]],Auxiliar!$B$5:$B$11,0),MATCH(Table1[[#This Row],[Complexidade]],Auxiliar!$D$4:$F$4,0)) -> #N/A | W10: =VLOOKUP(Table1[[#This Row],[Status]],Auxiliar!$B$16:$D$24,3,0)*Table1[[#This Row],[Estimação (horas)]] -> #N/A | X10: =+VLOOKUP(CONCATENATE(Table1[[#This Row],[Tabela]],Table1[[#This Row],[Campo]]),'2. Status Detalhe Campos FY24'!A:J,9,FALSE) -> Fase I | Y10: =+VLOOKUP(A10,#REF!,1,FALSE) -> #REF!
A11: =+Table1[[#This Row],[Tabela]]&Table1[[#This Row],[Campo]] -> ENERGY_CERTIFICATE_EST_INPUTACTUAL_VALUE_IND | B11: Pilar III | C11: Bens Imóveis - Input | D11: bu_esg_work.kt_chave_gloval; bu_esg_work.gloval_clase_energetica_dez23 | E11: n.a. | F11: ENERGY_CERTIFICATE_EST_INPUT | G11: ACTUAL_VALUE_IND | H11: =Table1[[#This Row],[Tabela]]&Table1[[#This Row],[Campo]] -> ENERGY_CERTIFICATE_EST_INPUTACTUAL_VALUE_IND | I11: 0. Cancelado | J11: =VLOOKUP(Table1[[#This Row],[Status]],Auxiliar!$B$16:$C$24,2,0) -> 0 | N11: 45688 | O11: =INDEX(Auxiliar!$D$5:$F$11,MATCH(Table1[[#This Row],[Tipologia_Testes]],Auxiliar!$B$5:$B$11,0),MATCH(Table1[[#This Row],[Complexidade]],Auxiliar!$D$4:$F$4,0)) -> #N/A | W11: =VLOOKUP(Table1[[#This Row],[Status]],Auxiliar!$B$16:$D$24,3,0)*Table1[[#This Row],[Estimação (horas)]] -> #N/A | X11: =+VLOOKUP(CONCATENATE(Table1[[#This Row],[Tabela]],Table1[[#This Row],[Campo]]),'2. Status Detalhe Campos FY24'!A:J,9,FALSE) -> Fase I | Y11: =+VLOOKUP(A11,#REF!,1,FALSE) -> #REF!
A12: =+Table1[[#This Row],[Tabela]]&Table1[[#This Row],[Campo]] -> ENERGY_CERTIFICATE_EST_INPUTCHAVE_GLOVAL | B12: Pilar III | C12: Bens Imóveis - Input | D12: bu_esg_work.kt_chave_gloval; bu_esg_work.gloval_clase_energetica_dez23 | E12: n.a. | F12: ENERGY_CERTIFICATE_EST_INPUT | G12: CHAVE_GLOVAL | H12: =Table1[[#This Row],[Tabela]]&Table1[[#This Row],[Campo]] -> ENERGY_CERTIFICATE_EST_INPUTCHAVE_GLOVAL | I12: 1. Concluído | J12: =VLOOKUP(Table1[[#This Row],[Status]],Auxiliar!$B$16:$C$24,2,0) -> 1 | K12: 6. Validação de formatos | L12: Sim | M12: Baixa | N12: 45716 | O12: =INDEX(Auxiliar!$D$5:$F$13,MATCH(Table1[[#This Row],[Tipologia_Testes]],Auxiliar!$B$5:$B$13,0),MATCH(Table1[[#This Row],[Complexidade]],Auxiliar!$D$4:$F$4,0)) -> 0.1 | R12: 45261 | T12: 45510 | U12: 45624 | W12: =VLOOKUP(Table1[[#This Row],[Status]],Auxiliar!$B$16:$D$24,3,0)*Table1[[#This Row],[Estimação (horas)]] -> 0.1 | X12: =+VLOOKUP(CONCATENATE(Table1[[#This Row],[Tabela]],Table1[[#This Row],[Campo]]),'2. Status Detalhe Campos FY24'!A:J,9,FALSE) -> Fase I | Y12: =+VLOOKUP(A12,#REF!,1,FALSE) -> #REF!
A13: =+Table1[[#This Row],[Tabela]]&Table1[[#This Row],[Campo]] -> ENERGY_CERTIFICATE_EST_INPUTPROPERTY_BANK_ID | B13: Pilar III | C13: Bens Imóveis - Input | D13: bu_esg_work.kt_chave_gloval; bu_esg_work.gloval_clase_energetica_dez23 | E13: n.a. | F13: ENERGY_CERTIFICATE_EST_INPUT | G13: PROPERTY_BANK_ID | H13: =Table1[[#This Row],[Tabela]]&Table1[[#This Row],[Campo]] -> ENERGY_CERTIFICATE_EST_INPUTPROPERTY_BANK_ID | I13: 1. Concluído | J13: =VLOOKUP(Table1[[#This Row],[Status]],Auxiliar!$B$16:$C$24,2,0) -> 1 | K13: 6. Validação de formatos | L13: Sim | M13: Baixa | N13: 45716 | O13: =INDEX(Auxiliar!$D$5:$F$13,MATCH(Table1[[#This Row],[Tipologia_Testes]],Auxiliar!$B$5:$B$13,0),MATCH(Table1[[#This Row],[Complexidade]],Auxiliar!$D$4:$F$4,0)) -> 0.1 | P13: Comentário da Susana ao paralelo: Efetivamente recebemos informação da Gloval mas para este efeito devemos apenas tomar os dados reais (e não as estimativas); existe um campo que indica essa situação | R13: 45261 | T13: 45510 | U13: 45624 | W13: =VLOOKUP(Table1[[#This Row],[Status]],Auxiliar!$B$16:$D$24,3,0)*Table1[[#This Row],[Estimação (horas)]] -> 0.1 | X13: =+VLOOKUP(CONCATENATE(Table1[[#This Row],[Tabela]],Table1[[#This Row],[Campo]]),'2. Status Detalhe Campos FY24'!A:J,9,FALSE) -> Fase I | Y13: =+VLOOKUP(A13,#REF!,1,FALSE) -> #REF!
A14: =+Table1[[#This Row],[Tabela]]&Table1[[#This Row],[Campo]] -> ENERGY_CERTIFICATE_EST_INPUTPROPERTY_BRANCH_CODE | B14: Pilar III | C14: Bens Imóveis - Input | D14: bu_esg_work.kt_chave_gloval; bu_esg_work.gloval_clase_energetica_dez23 | E14: n.a. | F14: ENERGY_CERTIFICATE_EST_INPUT | G14: PROPERTY_BRANCH_CODE | H14: =Table1[[#This Row],[Tabela]]&Table1[[#This Row],[Campo]] -> ENERGY_CERTIFICATE_EST_INPUTPROPERTY_BRANCH_CODE | I14: 1. Concluído | J14: =VLOOKUP(Table1[[#This Row],[Status]],Auxiliar!$B$16:$C$24,2,0) -> 1 | K14: 6. Validação de formatos | L14: Sim | M14: Baixa | N14: 45716 | O14: =INDEX(Auxiliar!$D$5:$F$13,MATCH(Table1[[#This Row],[Tipologia_Testes]],Auxiliar!$B$5:$B$13,0),MATCH(Table1[[#This Row],[Complexidade]],Auxiliar!$D$4:$F$4,0)) -> 0.1 | P14: Cempresa não está incluída na chave - mas a especificação no excel diz: Chave encriptada do bem, gerada com base na concatenação das variáveis cempbem, ckbalbem, ckctabem e ckrefbem | R14: 45261 | T14: 45510 | U14: 45624 | W14: =VLOOKUP(Table1[[#This Row],[Status]],Auxiliar!$B$16:$D$24,3,0)*Table1[[#This Row],[Estimação (horas)]] -> 0.1 | X14: =+VLOOKUP(CONCATENATE(Table1[[#This Row],[Tabela]],Table1[[#This Row],[Campo]]),'2. Status Detalhe Campos FY24'!A:J,9,FALSE) -> Fase I | Y14: =+VLOOKUP(A14,#REF!,1,FALSE) -> #REF!
A15: =+Table1[[#This Row],[Tabela]]&Table1[[#This Row],[Campo]] -> ENERGY_CERTIFICATE_EST_INPUTPROPERTY_CONTRACT_ID | B15: Pilar III | C15: Bens Imóveis - Input | D15: bu_esg_work.kt_chave_gloval; bu_esg_work.gloval_clase_energetica_dez23 | E15: n.a. | F15: ENERGY_CERTIFICATE_EST_INPUT | G15: PROPERTY_CONTRACT_ID | H15: =Table1[[#This Row],[Tabela]]&Table1[[#This Row],[Campo]] -> ENERGY_CERTIFICATE_EST_INPUTPROPERTY_CONTRACT_ID | I15: 1. Concluído | J15: =VLOOKUP(Table1[[#This Row],[Status]],Auxiliar!$B$16:$C$24,2,0) -> 1 | K15: 6. Validação de formatos | L15: Sim | M15: Baixa | N15: 45716 | O15: =INDEX(Auxiliar!$D$5:$F$13,MATCH(Table1[[#This Row],[Tipologia_Testes]],Auxiliar!$B$5:$B$13,0),MATCH(Table1[[#This Row],[Complexidade]],Auxiliar!$D$4:$F$4,0)) -> 0.1 | P15: Cempresa não está incluída na chave - mas a especificação no excel diz: Chave encriptada do bem, gerada com base na concatenação das variáveis cempbem, ckbalbem, ckctabem e ckrefbem | R15: 45261 | T15: 45510 | U15: 45624 | W15: =VLOOKUP(Table1[[#This Row],[Status]],Auxiliar!$B$16:$D$24,3,0)*Table1[[#This Row],[Estimação (horas)]] -> 0.1 | X15: =+VLOOKUP(CONCATENATE(Table1[[#This Row],[Tabela]],Table1[[#This Row],[Campo]]),'2. Status Detalhe Campos FY24'!A:J,9,FALSE) -> Fase I | Y15: =+VLOOKUP(A15,#REF!,1,FALSE) -> #REF!
A16: =+Table1[[#This Row],[Tabela]]&Table1[[#This Row],[Campo]] -> ENERGY_CERTIFICATE_EST_INPUTPROPERTY_REFERENCE_CODE | B16: Pilar III | C16: Bens Imóveis - Input | D16: bu_esg_work.kt_chave_gloval; bu_esg_work.gloval_clase_energetica_dez23 | E16: n.a. | F16: ENERGY_CERTIFICATE_EST_INPUT | G16: PROPERTY_REFERENCE_CODE | H16: =Table1[[#This Row],[Tabela]]&Table1[[#This Row],[Campo]] -> ENERGY_CERTIFICATE_EST_INPUTPROPERTY_REFERENCE_CODE | I16: 1. Concluído | J16: =VLOOKUP(Table1[[#This Row],[Status]],Auxiliar!$B$16:$C$24,2,0) -> 1 | K16: 6. Validação de formatos | L16: Sim | M16: Baixa | N16: 45716 | O16: =INDEX(Auxiliar!$D$5:$F$13,MATCH(Table1[[#This Row],[Tipologia_Testes]],Auxiliar!$B$5:$B$13,0),MATCH(Table1[[#This Row],[Complexidade]],Auxiliar!$D$4:$F$4,0)) -> 0.1 | R16: 45261 | T16: 45510 | U16: 45624 | W16: =VLOOKUP(Table1[[#This Row],[Status]],Auxiliar!$B$16:$D$24,3,0)*Table1[[#This Row],[Estimação (horas)]] -> 0.1 | X16: =+VLOOKUP(CONCATENATE(Table1[[#This Row],[Tabela]],Table1[[#This Row],[Campo]]),'2. Status Detalhe Campos FY24'!A:J,9,FALSE) -> Fase I | Y16: =+VLOOKUP(A16,#REF!,1,FALSE) -> #REF!
A17: =+Table1[[#This Row],[Tabela]]&Table1[[#This Row],[Campo]] -> ENERGY_CERTIFICATE_EST_INPUTCÓDIGO_DISTRITO | B17: Pilar III | C17: Bens Imóveis - Input | D17: bu_esg_work.kt_chave_gloval; bu_esg_work.gloval_clase_energetica_dez23 | E17: n.a. | F17: ENERGY_CERTIFICATE_EST_INPUT | G17: CÓDIGO_DISTRITO | H17: =Table1[[#This Row],[Tabela]]&Table1[[#This Row],[Campo]] -> ENERGY_CERTIFICATE_EST_INPUTCÓDIGO_DISTRITO | I17: 1. Concluído | J17: =VLOOKUP(Table1[[#This Row],[Status]],Auxiliar!$B$16:$C$24,2,0) -> 1 | K17: 6. Validação de formatos | L17: Sim | M17: Baixa | N17: 45716 | O17: =INDEX(Auxiliar!$D$5:$F$13,MATCH(Table1[[#This Row],[Tipologia_Testes]],Auxiliar!$B$5:$B$13,0),MATCH(Table1[[#This Row],[Complexidade]],Auxiliar!$D$4:$F$4,0)) -> 0.1 | R17: 45261 | T17: 45510 | U17: 45624 | W17: =VLOOKUP(Table1[[#This Row],[Status]],Auxiliar!$B$16:$D$24,3,0)*Table1[[#This Row],[Estimação (horas)]] -> 0.1 | X17: =+VLOOKUP(CONCATENATE(Table1[[#This Row],[Tabela]],Table1[[#This Row],[Campo]]),'2. Status Detalhe Campos FY24'!A:J,9,FALSE) -> Fase I | Y17: =+VLOOKUP(A17,#REF!,1,FALSE) -> #REF!
A18: =+Table1[[#This Row],[Tabela]]&Table1[[#This Row],[Campo]] -> ENERGY_CERTIFICATE_EST_INPUTNOMBRE_DISTRITO | B18: Pilar III | C18: Bens Imóveis - Input | D18: bu_esg_work.kt_chave_gloval; bu_esg_work.gloval_clase_energetica_dez23 | E18: n.a. | F18: ENERGY_CERTIFICATE_EST_INPUT | G18: NOMBRE_DISTRITO | H18: =Table1[[#This Row],[Tabela]]&Table1[[#This Row],[Campo]] -> ENERGY_CERTIFICATE_EST_INPUTNOMBRE_DISTRITO | I18: 1. Concluído | J18: =VLOOKUP(Table1[[#This Row],[Status]],Auxiliar!$B$16:$C$24,2,0) -> 1 | K18: 6. Validação de formatos | L18: Sim | M18: Baixa | N18: 45716 | O18: =INDEX(Auxiliar!$D$5:$F$13,MATCH(Table1[[#This Row],[Tipologia_Testes]],Auxiliar!$B$5:$B$13,0),MATCH(Table1[[#This Row],[Complexidade]],Auxiliar!$D$4:$F$4,0)) -> 0.1 | R18: 45261 | T18: 45510 | U18: 45624 | W18: =VLOOKUP(Table1[[#This Row],[Status]],Auxiliar!$B$16:$D$24,3,0)*Table1[[#This Row],[Estimação (horas)]] -> 0.1 | X18: =+VLOOKUP(CONCATENATE(Table1[[#This Row],[Tabela]],Table1[[#This Row],[Campo]]),'2. Status Detalhe Campos FY24'!A:J,9,FALSE) -> Fase I | Y18: =+VLOOKUP(A18,#REF!,1,FALSE) -> #REF!
A19: =+Table1[[#This Row],[Tabela]]&Table1[[#This Row],[Campo]] -> ENERGY_CERTIFICATE_EST_INPUTCÓDIGO_CONCEJO | B19: Pilar III | C19: Bens Imóveis - Input | D19: bu_esg_work.kt_chave_gloval; bu_esg_work.gloval_clase_energetica_dez23 | E19: n.a. | F19: ENERGY_CERTIFICATE_EST_INPUT | G19: CÓDIGO_CONCEJO | H19: =Table1[[#This Row],[Tabela]]&Table1[[#This Row],[Campo]] -> ENERGY_CERTIFICATE_EST_INPUTCÓDIGO_CONCEJO | I19: 1. Concluído | J19: =VLOOKUP(Table1[[#This Row],[Status]],Auxiliar!$B$16:$C$24,2,0) -> 1 | K19: 6. Validação de formatos | L19: Sim | M19: Baixa | N19: 45716 | O19: =INDEX(Auxiliar!$D$5:$F$13,MATCH(Table1[[#This Row],[Tipologia_Testes]],Auxiliar!$B$5:$B$13,0),MATCH(Table1[[#This Row],[Complexidade]],Auxiliar!$D$4:$F$4,0)) -> 0.1 | R19: 45261 | T19: 45510 | U19: 45624 | W19: =VLOOKUP(Table1[[#This Row],[Status]],Auxiliar!$B$16:$D$24,3,0)*Table1[[#This Row],[Estimação (horas)]] -> 0.1 | X19: =+VLOOKUP(CONCATENATE(Table1[[#This Row],[Tabela]],Table1[[#This Row],[Campo]]),'2. Status Detalhe Campos FY24'!A:J,9,FALSE) -> Fase I | Y19: =+VLOOKUP(A19,#REF!,1,FALSE) -> #REF!
A20: =+Table1[[#This Row],[Tabela]]&Table1[[#This Row],[Campo]] -> ENERGY_CERTIFICATE_EST_INPUTNOMBRE_CONCEJO | B20: Pilar III | C20: Bens Imóveis - Input | D20: bu_esg_work.kt_chave_gloval; bu_esg_work.gloval_clase_energetica_dez23 | E20: n.a. | F20: ENERGY_CERTIFICATE_EST_INPUT | G20: NOMBRE_CONCEJO | H20: =Table1[[#This Row],[Tabela]]&Table1[[#This Row],[Campo]] -> ENERGY_CERTIFICATE_EST_INPUTNOMBRE_CONCEJO | I20: 1. Concluído | J20: =VLOOKUP(Table1[[#This Row],[Status]],Auxiliar!$B$16:$C$24,2,0) -> 1 | K20: 6. Validação de formatos | L20: Sim | M20: Baixa | N20: 45716 | O20: =INDEX(Auxiliar!$D$5:$F$13,MATCH(Table1[[#This Row],[Tipologia_Testes]],Auxiliar!$B$5:$B$13,0),MATCH(Table1[[#This Row],[Complexidade]],Auxiliar!$D$4:$F$4,0)) -> 0.1 | R20: 45261 | T20: 45510 | U20: 45624 | W20: =VLOOKUP(Table1[[#This Row],[Status]],Auxiliar!$B$16:$D$24,3,0)*Table1[[#This Row],[Estimação (horas)]] -> 0.1 | X20: =+VLOOKUP(CONCATENATE(Table1[[#This Row],[Tabela]],Table1[[#This Row],[Campo]]),'2. Status Detalhe Campos FY24'!A:J,9,FALSE) -> Fase I | Y20: =+VLOOKUP(A20,#REF!,1,FALSE) -> #REF!
A21: =+Table1[[#This Row],[Tabela]]&Table1[[#This Row],[Campo]] -> ENERGY_CERTIFICATE_EST_INPUTCÓDIGO_FREGUESIA | B21: Pilar III | C21: Bens Imóveis - Input | D21: bu_esg_work.kt_chave_gloval; bu_esg_work.gloval_clase_energetica_dez23 | E21: n.a. | F21: ENERGY_CERTIFICATE_EST_INPUT | G21: CÓDIGO_FREGUESIA | H21: =Table1[[#This Row],[Tabela]]&Table1[[#This Row],[Campo]] -> ENERGY_CERTIFICATE_EST_INPUTCÓDIGO_FREGUESIA | I21: 1. Concluído | J21: =VLOOKUP(Table1[[#This Row],[Status]],Auxiliar!$B$16:$C$24,2,0) -> 1 | K21: 6. Validação de formatos | L21: Sim | M21: Baixa | N21: 45716 | O21: =INDEX(Auxiliar!$D$5:$F$13,MATCH(Table1[[#This Row],[Tipologia_Testes]],Auxiliar!$B$5:$B$13,0),MATCH(Table1[[#This Row],[Complexidade]],Auxiliar!$D$4:$F$4,0)) -> 0.1 | R21: 45261 | T21: 45510 | U21: 45624 | W21: =VLOOKUP(Table1[[#This Row],[Status]],Auxiliar!$B$16:$D$24,3,0)*Table1[[#This Row],[Estimação (horas)]] -> 0.1 | X21: =+VLOOKUP(CONCATENATE(Table1[[#This Row],[Tabela]],Table1[[#This Row],[Campo]]),'2. Status Detalhe Campos FY24'!A:J,9,FALSE) -> Fase I | Y21: =+VLOOKUP(A21,#REF!,1,FALSE) -> #REF!
A22: =+Table1[[#This Row],[Tabela]]&Table1[[#This Row],[Campo]] -> ENERGY_CERTIFICATE_EST_INPUTNOMBRE_FREGUESIA | B22: Pilar III | C22: Bens Imóveis - Input | D22: bu_esg_work.kt_chave_gloval; bu_esg_work.gloval_clase_energetica_dez23 | E22: n.a. | F22: ENERGY_CERTIFICATE_EST_INPUT | G22: NOMBRE_FREGUESIA | H22: =Table1[[#This Row],[Tabela]]&Table1[[#This Row],[Campo]] -> ENERGY_CERTIFICATE_EST_INPUTNOMBRE_FREGUESIA | I22: 1. Concluído | J22: =VLOOKUP(Table1[[#This Row],[Status]],Auxiliar!$B$16:$C$24,2,0) -> 1 | K22: 6. Validação de formatos | L22: Sim | M22: Baixa | N22: 45716 | O22: =INDEX(Auxiliar!$D$5:$F$13,MATCH(Table1[[#This Row],[Tipologia_Testes]],Auxiliar!$B$5:$B$13,0),MATCH(Table1[[#This Row],[Complexidade]],Auxiliar!$D$4:$F$4,0)) -> 0.1 | R22: 45261 | T22: 45510 | U22: 45624 | W22: =VLOOKUP(Table1[[#This Row],[Status]],Auxiliar!$B$16:$D$24,3,0)*Table1[[#This Row],[Estimação (horas)]] -> 0.1 | X22: =+VLOOKUP(CONCATENATE(Table1[[#This Row],[Tabela]],Table1[[#This Row],[Campo]]),'2. Status Detalhe Campos FY24'!A:J,9,FALSE) -> Fase I | Y22: =+VLOOKUP(A22,#REF!,1,FALSE) -> #REF!
