Workbook
Name Ambito: #REF!
Name ÁREA: #REF!
Name ÁREA: #REF!
Name ÁREA: #REF!
Name ÁREA: #REF!
Name ÁREA: #REF!
Name ÁREA: #REF!
Name ÁREA: #REF!
Name asefadf: #REF!
Name bn: '[3]Code List'!#REF!
Name Default_values: #REF!
Name Estados: [5]!Table7[Estados]
Name Estados_testes: #REF!
Name Estados_testes: #REF!
Name Estados_testes: #REF!
Name Estados_testes: #REF!
Name Estados_testes: #REF!
Name Estados_testes: #REF!
Name Estados_testes: #REF!
Name Pendências: [5]!Table6[Pendências]
Name TABELA: #REF!
Name TABELA: #REF!
Name TABELA: #REF!
Name TABELA: #REF!
Name TABELA: #REF!
Name TABELA: #REF!
Name TABELA: #REF!
Name Validações_Especificas: #REF!
Name Validaçoes_Genericas: #REF!

Sheet Capa
B4: BCE Loan Tape
B5: Modelo Consolidado de Garantias | Testes
B8: Lisboa, | C8: 45068
B10: Análise e testes de Modelo em produção a 30 Abril 2023, com respeito a 30 Abril 2023 real

Sheet 1. Resumo Universo
B5: 1. Análises Universos
C7: Data de referência | D7: 45046
C8: Data de atualização | D8: 45032
B11: Universo BIYR 2500 | J11: Universo BIYR9500
C13: tipo | D13: biyr2500_caplic | E13: biyr2500_tipgargblbg | F13: num_resp_proc | H13: biyr2500_mavaliaa
C14: F | D14: DC | E14: 2 | F14: 2080 | H14: 97220800 | J14: =(H14-'Dados Fevereiro | 16-04-23'!H14)/'Dados Fevereiro | 16-04-23'!H14 -> -0.076691745
C15: F | D15: DP | E15: 2 | F15: 1959 | H15: 1.9725246e+08 | J15: =(H15-'Dados Fevereiro | 16-04-23'!H15)/'Dados Fevereiro | 16-04-23'!H15 -> -0.026380262
C16: F | D16: FU | E16: 2 | F16: 1910 | H16: 2.3319971e+08 | J16: =(H16-'Dados Fevereiro | 16-04-23'!H16)/'Dados Fevereiro | 16-04-23'!H16 -> 0.034782
C17: F | D17: SG | E17: 2 | F17: 1111 | H17: 88514777 | J17: =(H17-'Dados Fevereiro | 16-04-23'!H17)/'Dados Fevereiro | 16-04-23'!H17 -> -0.034271906
C18: F | D18: TT | E18: 2 | F18: 59 | H18: 60749720 | J18: =(H18-'Dados Fevereiro | 16-04-23'!H18)/'Dados Fevereiro | 16-04-23'!H18 -> 0.025215979
C19: FAC | D19: FAC | E19: 1 | F19: 931 | H19: 1.0599748e+08 | J19: =(H19-'Dados Fevereiro | 16-04-23'!H19)/'Dados Fevereiro | 16-04-23'!H19 -> 0.18094528
C20: I | D20: CS | E20: 2 | F20: 1519 | H20: 5.013535e+09 | J20: =(H20-'Dados Fevereiro | 16-04-23'!H20)/'Dados Fevereiro | 16-04-23'!H20 -> 0.1983807
C21: I | D21: GP | E21: 2 | F21: 364116 | H21: 5.3228846e+10 | J21: =(H21-'Dados Fevereiro | 16-04-23'!H21)/'Dados Fevereiro | 16-04-23'!H21 -> -0.0095344758
C22: LEA | D22: LEA | E22: 1 | F22: 21454 | H22: 1.6449139e+09 | J22: =(H22-'Dados Fevereiro | 16-04-23'!H22)/'Dados Fevereiro | 16-04-23'!H22 -> -0.01556773
C23: LEA | D23: LEA | E23: 2 | F23: 5155 | H23: 1.516394e+09 | J23: =(H23-'Dados Fevereiro | 16-04-23'!H23)/'Dados Fevereiro | 16-04-23'!H23 -> -0.0075587664
C24: P | D24: CLI | E24: 1 | F24: 90394 | H24: 8.6205061e+09 | J24: =(H24-'Dados Fevereiro | 16-04-23'!H24)/'Dados Fevereiro | 16-04-23'!H24 -> -0.026368522
C25: P | D25: CS | E25: 1 | F25: 35116 | H25: 4.7796841e+09 | J25: =(H25-'Dados Fevereiro | 16-04-23'!H25)/'Dados Fevereiro | 16-04-23'!H25 -> 0.097850144
... C27: TBD | D27: CS | E27: 2 | F27: 396 | H27: 5.4768751e+08 | J27: =(H27-'Dados Fevereiro | 16-04-23'!H27)/'Dados Fevereiro | 16-04-23'!H27 -> 0.014774663
B29: Universo Modelo
C31: tipo | D31: origem | E31: num_resp_proc | F31: mavaliaa | H31: Variação face à execução anterior
C32: F | D32: CS | E32: 7419 | F32: 6.7978282e+08 | H32: =E32-'Dados Fevereiro | 16-04-23'!E32 -> -378 | I32: =F32-'Dados Fevereiro | 16-04-23'!F32 -> -9217284.6 | J32: =I32/'Dados Fevereiro | 16-04-23'!F32 -> -0.01337777
C33: I | D33: CS | E33: 966 | F33: 4.3973813e+09 | H33: =E33-'Dados Fevereiro | 16-04-23'!E33 -> -31 | I33: =F33-'Dados Fevereiro | 16-04-23'!F33 -> 7.3954507e+08 | J33: =I33/'Dados Fevereiro | 16-04-23'!F33 -> 0.20218102
C34: I | D34: GP | E34: 399722 | F34: 5.3143386e+10 | H34: =E34-'Dados Fevereiro | 16-04-23'!E34 -> -4115 | I34: =F34-'Dados Fevereiro | 16-04-23'!F34 -> -4.8950923e+08 | J34: =I34/'Dados Fevereiro | 16-04-23'!F34 -> -0.0091270334
C35: I | D35: LEA | E35: 4941 | F35: 1.4928783e+09 | H35: =E35-'Dados Fevereiro | 16-04-23'!E35 -> -64 | I35: =F35-'Dados Fevereiro | 16-04-23'!F35 -> -10946367 | J35: =I35/'Dados Fevereiro | 16-04-23'!F35 -> -0.0072790178
C36: P | D36: CS | E36: 107594 | F36: 1.3872364e+10 | H36: =E36-'Dados Fevereiro | 16-04-23'!E36 -> -1561 | I36: =F36-'Dados Fevereiro | 16-04-23'!F36 -> -1.9971591e+08 | J36: =I36/'Dados Fevereiro | 16-04-23'!F36 -> -0.014192352
C37: P | D37: FAC | E37: 11174 | F37: 1.0599739e+08 | H37: =E37-'Dados Fevereiro | 16-04-23'!E37 -> 2133 | I37: =F37-'Dados Fevereiro | 16-04-23'!F37 -> 16239423 | J37: =I37/'Dados Fevereiro | 16-04-23'!F37 -> 0.18092458
C38: P | D38: GP | E38: 98371 | F38: 8.4670604e+09 | H38: =E38-'Dados Fevereiro | 16-04-23'!E38 -> -2186 | I38: =F38-'Dados Fevereiro | 16-04-23'!F38 -> -2.1656789e+08 | J38: =I38/'Dados Fevereiro | 16-04-23'!F38 -> -0.024939793
C39: P | D39: LEA | E39: 17437 | F39: 1.5863997e+09 | H39: =E39-'Dados Fevereiro | 16-04-23'!E39 -> -26 | I39: =F39-'Dados Fevereiro | 16-04-23'!F39 -> -2609044.2 | J39: =I39/'Dados Fevereiro | 16-04-23'!F39 -> -0.0016419319
E40: =SUM(E32:E39) -> 647624
C43: Valores originais
D45: BIYR9500 | F45: Novo Modelo de Garantias
C46: Tipo | D46: # Responsabilidade/ Processo | E46: MAVALIAA | F46: # Responsabilidade/ Processo | H46: MAVALIAA | I46: ∆ Responsabilidade/ Processo | J46: ∆ MAVALIAA
C47: Factoring | D47: =F19 -> 931 | E47: =H19 -> 1.0599748e+08 | F47: =E37 -> 11174 | H47: =F37 -> 1.0599739e+08 | I47: =F47-D47 -> 10243 | J47: =H47-E47 -> -86.1
C48: Pessoais | D48: =SUM(F24:F26) -> 248175 | E48: =SUM(H24:H26) -> 3.3810922e+10 | F48: =E36+E38 -> 205965 | H48: =F36+F38 -> 2.2339424e+10 | I48: =F48-D48 -> -42210 | J48: =H48-E48 -> -1.1471497e+10
C49: Financeiras | D49: =SUM(F14:F18)+F27 -> 7515 | E49: =SUM(H14:H18)+H27 -> 1.224625e+09 | F49: =SUM(E32) -> 7419 | H49: =SUM(F32) -> 6.7978282e+08 | I49: =F49-D49 -> -96 | J49: =H49-E49 -> -5.4484215e+08
C50: Imóveis | D50: =SUM(F20:F21) -> 365635 | E50: =SUM(H20:H21) -> 5.8242381e+10 | F50: =SUM(E33:E34) -> 400688 | H50: =SUM(F33:F34) -> 5.7540768e+10 | I50: =F50-D50 -> 35053 | J50: =H50-E50 -> -7.016135e+08
C51: Leasing - Imóveis | D51: =F23 -> 5155 | E51: =H23 -> 1.516394e+09 | F51: =E35 -> 4941 | H51: =F35 -> 1.4928783e+09 | I51: =F51-D51 -> -214 | J51: =H51-E51 -> -23515645
C52: Leasing - Pessoais | D52: =F22 -> 21454 | E52: =H22 -> 1.6449139e+09 | F52: =E39 -> 17437 | H52: =F39 -> 1.5863997e+09 | I52: =F52-D52 -> -4017 | J52: =H52-E52 -> -58514159
C53: Total | D53: =SUM(D47:D52) -> 648865 | E53: =SUM(E47:E52) -> 9.6545233e+10 | F53: =SUM(F47:F52) -> 647624 | H53: =SUM(H47:H52) -> 8.374525e+10 | I53: =SUM(I47:I52) -> -1241 | J53: =SUM(J47:J52) -> -1.2799983e+10
B55: Comparação entre o BIYR2500 e o Novo Modelo de Garantias
D57: BIYR9500 (1) | F57: Novo Modelo de Garantias (2)
C58: Tipo | D58: # Responsabilidade/ Processo | E58: MAVALIAA | F58: # Responsabilidade/ Processo | H58: MAVALIAA | I58: ∆ Responsabilidade/ Processo | J58: ∆ MAVALIAA | K58: % Diferenças MAVALIAA
C59: Factoring* | D59: =D47 -> 931 | E59: =E47 -> 1.0599748e+08 | F59: =F47 -> 11174 | H59: =H47 -> 1.0599739e+08 | I59: =F59-D59 -> 10243 | J59: =H59-E59 -> -86.1 | K59: =J59/E59 -> -8.1228346e-07
C60: Pessoais* | D60: ='1.1.Pessoais'!G42 -> 393158 | E60: =E48 -> 3.3810922e+10 | F60: ='1.1.Pessoais'!E42 -> 358877 | H60: =H48 -> 2.2339424e+10 | I60: =F60-D60 -> -34281 | J60: =H60-E60 -> -1.1471497e+10 | K60: =J60/E60 -> -0.33928377
C61: Financeiras | D61: =D49 -> 7515 | E61: =E49 -> 1.224625e+09 | F61: =F49 -> 7419 | H61: =H49 -> 6.7978282e+08 | I61: =F61-D61 -> -96 | J61: =H61-E61 -> -5.4484215e+08 | K61: =J61/E61 -> -0.44490531
C62: Imóveis | D62: =D50 -> 365635 | E62: =H20+H21 -> 5.8242381e+10 | F62: =F50 -> 400688 | H62: =H50 -> 5.7540768e+10 | I62: =F62-D62 -> 35053 | J62: =H62-E62 -> -7.016135e+08 | K62: =J62/E62 -> -0.012046443
C63: Leasing - Pessoais* | D63: ='1.5.Pessoais - LEA'!G22 -> 37874 | E63: =E52 -> 1.6449139e+09 | F63: ='1.5.Pessoais - LEA'!E22 -> 33492 | H63: =H52 -> 1.5863997e+09 | I63: =F63-D63 -> -4382 | J63: =H63-E63 -> -58514159 | K63: =J63/E63 -> -0.03557278
C64: Leasing - Imóveis | D64: =D51 -> 5155 | E64: =E51 -> 1.516394e+09 | F64: =F51 -> 4941 | H64: =H51 -> 1.4928783e+09 | I64: =F64-D64 -> -214 | J64: =H64-E64 -> -23515645 | K64: =J64/E64 -> -0.015507609
C65: Total | D65: =SUM(D59:D64) -> 810268 | E65: =SUM(E59:E64) -> 9.6545233e+10 | F65: =SUM(F59:F64) -> 816591 | H65: =SUM(H59:H64) -> 8.374525e+10 | I65: =SUM(I59:I64) -> 6323 | J65: =SUM(J59:J64) -> -1.2799983e+10
C66: * Numero de registos ao nível do bem - Cliente
B68: Alterações que foram realizadas no modelo face à situação que existe atualmente no BIYR9500 com impacto nos resultados:
C70: ID | D70: Temas | J70: # Responsabilidade/ Processo | K70: Diferenças de MAVALIAA
C71: 1 | D71: Apenas serão contempladas responsabilidades/processos com bens associados e com datas de vencimento válidas (exceto bens com origem leasing). | J71: ='1.3.Financeiras'!G18+'1.3.Financeiras'!G19+'1.2.Imóveis'!F44+'1.2.Imóveis'!F49+'1.1.Pessoais'!G19+'1.2.Imóveis'!F46+'1.2.Imóveis'!F33+'1.2.Imóveis'!F37 -> 2374 | K71: =-('1.2.Imóveis'!I44+'1.2.Imóveis'!I49+'1.3.Financeiras'!H18+'1.3.Financeiras'!H19+'1.1.Pessoais'!H19+'1.2.Imóveis'!I46)+'1.2.Imóveis'!J33+'1.2.Imóveis'!J37 -> -8.9218331e+08
C72: 2 | D72: Todos os titulares, utilizados atualmente como garantias pessoais, serão excluídos. | J72: ='1.1.Pessoais'!G20+'1.1.Pessoais'!G18+'1.5.Pessoais - LEA'!G15 -> 63429 | K72: =-('1.1.Pessoais'!H18+'1.1.Pessoais'!H20+'1.5.Pessoais - LEA'!H15) -> -5.1678637e+09
C73: 3 | D73: O algoritmos de apuramento de saldos das responsabilidades, relevantes para a distribuição dos montantes das garantias, passará a contemplar contas contabilisticas de juros e despesas vencidas. | J73: ='1.1.Pessoais'!E57+'1.1.Pessoais'!E58+'1.1.Pessoais'!E59+'1.1.Pessoais'!E60 -> 206584 | K73: ='1.1.Pessoais'!I57+'1.1.Pessoais'!I58+'1.1.Pessoais'!I59+'1.1.Pessoais'!I60 -> 28337689
C74: 4 | D74: A metodologia de aprovisionamento de montantes de avaliação para fomentos à construção e IFRRUs, manter-se-á como no BIYR9500, à exceção da percentagem de avaliação atribuida ao BST (será como base o financiamento inicial do IFRRU e não no saldo em dívida atual). A mesma será revista após o rácio de Abril. | J74: ='1.2.Imóveis'!F32 -> 242 | K74: ='1.2.Imóveis'!J32 -> 57230945
C75: 5 | D75: O montante considerado em garantias pessoais deve ser o da responsabilidade e não o do processo. | J75: =SUM('1.1.Pessoais'!E49:E56) -> 121833 | K75: =SUM('1.1.Pessoais'!M49:M56) -> -5.636508e+09
C76: 6 | D76: No caso das garantias financeiras, serão descartadas as garantias cuja data de vencimento seja inferior à data do rácio, mesmo tendo uma data de cativo válida (uma vez que a data de cativo pode ser referente à DO e não ao bem contratualizado incialmente com o cliente). Metodologia que será aplicada após quantificação de impactos. | J76: Por quantificar | K76: Por quantificar
C77: 7 | D77: Apenas serão contemplados bens com datas de avaliação válidas (exceto bens com origem leasing). | J77: =('1.2.Imóveis'!F45+'1.2.Imóveis'!F50+'1.2.Imóveis'!F51+'1.2.Imóveis'!F52) -> 323 | K77: =-('1.2.Imóveis'!I45+'1.2.Imóveis'!I50+'1.2.Imóveis'!I51+'1.2.Imóveis'!I52) -> -83177937
C78: 8 | D78: A metodologia de aprovisionamento de montantes/datas de avaliação aplicada a Fomentos à Construção deve ser igual para todas as origens. | J78: ='1.2.Imóveis'!F21 -> 11 | K78: ='1.2.Imóveis'!J21 -> -1.6055035e+08
C79: 9 | D79: O rateio dos bens pelos processos/responsabilidades deve ser feito independentemente da origem e deve ser realizado com base no valor atual da responsabilidade e não pela percentagem de cobertura calculada no momento da contratação. | J79: ='1.2.Imóveis'!F22+'1.2.Imóveis'!F34+'1.2.Imóveis'!F23 -> 267 | K79: ='1.2.Imóveis'!J34+'1.2.Imóveis'!J22+'1.2.Imóveis'!J23 -> -2.7494578e+08
C80: 10 | D80: Saldos de bens financeiros utilizados no modelo apresentam lag de um dia face ao BIYR (BIYR utiliza saldos de D+1). | J80: ='1.3.Financeiras'!E13+'1.3.Financeiras'!E15 -> 2894 | K80: ='1.3.Financeiras'!I13+'1.3.Financeiras'!I15 -> -509730.38
C81: 11 | D81: São consideradas todas as garantias financeiras válidas dentro da mesma caução, independentemente da sua tipologia (exemplo, DO e TT). | J81: ='1.3.Financeiras'!E12 -> 0 | K81: ='1.3.Financeiras'!I12 -> 0
C82: 12 | D82: Apenas serão contempladas garantias manuais de PPC com caução carregada para o respetivo emitente/programa. Nos títulos as cauções são as mesmas. | J82: ='1.1.Pessoais'!G21 -> 61 | K82: ='1.1.Pessoais'!I21 -> -193133818
C83: 13 | D83: O montante das garantias pessoais será o resultado após a multiplicação do valor da responsabilidade pela percentagem de cobertura do cliente (bem). | J83: =SUM('1.1.Pessoais'!E49:E56) -> 121833 | K83: =SUM('1.1.Pessoais'!N49:N56) -> -4.9451472e+08
C84: 14 | D84: Deve ser considerado o valor de avaliação mais recente, independentemente do seu montante (inclusão de avaliações com montante igual a zero). | J84: ='1.2.Imóveis'!F24+'1.2.Imóveis'!F35 -> 52 | K84: ='1.2.Imóveis'!J24+'1.2.Imóveis'!J35 -> -16155461
B85: Novo | C85: 15 | D85: Apenas serão contemplados empréstimos e processos formalizados. | J85: ='1.2.Imóveis'!F54+'1.2.Imóveis'!F53 -> 3 | K85: ='1.2.Imóveis'!J54+'1.2.Imóveis'!J53 -> -1621265.6
B86: Novo | C86: 16 | D86: Cauções de garantias manuais de PPC selecionadas de acordo com a nova parametrização (cauções mais recentes carregadas por emitente/programa). | J86: ='1.1.Pessoais'!G22+'1.1.Pessoais'!E34+'1.1.Pessoais'!E35+'1.1.Pessoais'!E36 -> 58 | K86: ='1.1.Pessoais'!I22+'1.1.Pessoais'!I34+'1.1.Pessoais'!I35+'1.1.Pessoais'!I36 -> 97028307
B89: 2. Resumo de Casuísticas
B92: Garantias Pessoais (excluindo Leasing e Factoring):
C94: Universo | D94: # Responsabilidade/ Processo/Cliente | E94: MAVALIAA
C95: Novo Modelo de Garantias | D95: ='1.1.Pessoais'!E42 -> 358877 | E95: ='1.1.Pessoais'!F42 -> 2.2339424e+10
C96: BIYR9500 | D96: =D60 -> 393158 | E96: =E60 -> 3.3810922e+10
C99: Universos | D99: Casuística | E99: # Responsabilidade/ Processo/Cliente | F99: ∆ Follow up | H99: MAVALIAA - Novo Modelo de garantias | I99: MAVALIAA - BIYR9500 | J99: Diferenças
C100: 1) Universo Comum | D100: Sem diferenças de mavaliaa | E100: ='1.1.Pessoais'!E10 -> 27026 | H100: ='1.1.Pessoais'!F10 -> 1.90134e+09 | I100: ='1.1.Pessoais'!H10 -> 1.90134e+09 | J100: =H100-I100 -> 0
D101: Diferenças de metodologia | E101: =SUM('1.1.Pessoais'!E11:E13) -> 328417 | H101: =SUM('1.1.Pessoais'!F11:F13) -> 2.0090766e+10 | I101: =SUM('1.1.Pessoais'!H11:H13) -> 2.6193455e+10 | J101: =H101-I101 -> -6.1026897e+09
D102: Em resolução - requisitos definidos e planificados | E102: ='1.1.Pessoais'!E14+'1.1.Pessoais'!E15 -> 1678 | H102: ='1.1.Pessoais'!F14+'1.1.Pessoais'!F15 -> 1.3074236e+08 | I102: ='1.1.Pessoais'!H14+'1.1.Pessoais'!H15 -> 65730248 | J102: =H102-I102 -> 65012114
D103: Em análise | E103: ='1.1.Pessoais'!E16 -> 1 | H103: ='1.1.Pessoais'!F16 -> 26429.25 | I103: ='1.1.Pessoais'!H16 -> 18472.25 | J103: =H103-I103 -> 7957
D104: Total | E104: =SUM(E100:E103) -> 357122 | H104: =SUM(H100:H103) -> 2.2122874e+10 | I104: =SUM(I100:I103) -> 2.8160544e+10 | J104: =SUM(J100:J103) -> -6.0376696e+09
C105: 2) Exclusivo Novo Modelo de Garantias | D105: Diferenças de metodologia | E105: =SUM('1.1.Pessoais'!E34:E36) -> 51 | H105: =SUM('1.1.Pessoais'!F34:F36) -> 1.3702831e+08 | J105: =H105-I105 -> 1.3702831e+08
D106: Em resolução - requisitos definidos e planificados | E106: ='1.1.Pessoais'!E37 -> 5 | H106: =SUM('1.1.Pessoais'!F37) -> 49840.86 | J106: =H106-I106 -> 49840.86
D107: Em resolução - definição de requisitos em curso | E107: ='1.1.Pessoais'!E38+'1.1.Pessoais'!E39 -> 263 | H107: ='1.1.Pessoais'!F38+'1.1.Pessoais'!F39 -> 53042568 | J107: =H107-I107 -> 53042568
D108: Em análise | E108: ='1.1.Pessoais'!E40 -> 1436 | H108: ='1.1.Pessoais'!F40 -> 26429373 | J108: =H108-I108 -> 26429373
D109: Total | E109: =SUM(E105:E108) -> 1755 | H109: =SUM(H105:H108) -> 2.1655009e+08 | J109: =H109-I109 -> 2.1655009e+08
C110: 3) Exclusivo BIYR2500 | D110: Diferenças de metodologia | E110: =SUM('1.1.Pessoais'!G18:G22)+SUM('1.1.Pessoais'!G24:G26) -> 60346 | I110: =SUM('1.1.Pessoais'!H18:H22)+SUM('1.1.Pessoais'!H24:H26) -> 5.4628189e+09 | J110: =H110-I110 -> -5.4628189e+09
D111: Em resolução - requisitos definidos e planificados | E111: =SUM('1.1.Pessoais'!G23,'1.1.Pessoais'!G27:G28) -> 2448 | I111: =SUM('1.1.Pessoais'!H23,'1.1.Pessoais'!H27:H28) -> 1.7734282e+08 | J111: =H111-I111 -> -1.7734282e+08
D112: Em resolução - definição de requisitos em curso | E112: =SUM('1.1.Pessoais'!G29:G31) -> 108 | I112: =SUM('1.1.Pessoais'!H29:H31) -> 2276054.5 | J112: =H112-I112 -> -2276054.5
D113: Em análise | E113: =SUM('1.1.Pessoais'!G32) -> 29 | I113: =SUM('1.1.Pessoais'!H32) -> 7939808.3 | J113: =H113-I113 -> -7939808.3
D114: Total | E114: =SUM(E110:E113) -> 62931 | I114: =SUM(I110:I113) -> 5.6503775e+09 | J114: =H114-I114 -> -5.6503775e+09
E115: =E104+E109 -> 358877 | F115: =E115-F60 -> 0 | H115: =H104+H109 -> 2.2339424e+10 | I115: =I104+I114 -> 3.3810922e+10
H116: =H115-H60 -> 0 | I116: =I115-E60 -> 0
B117: Garantias Financeiras:
C119: Universos | D119: Casuística | E119: # Responsabilidade/ Processo | F119: ∆ Follow up | H119: MAVALIAA - Novo Modelo de garantias | I119: MAVALIAA - BIYR9500 | J119: Diferenças
C120: 1) Universo Comum | D120: Sem diferenças de mavaliaa | E120: ='1.3.Financeiras'!E10 -> 4235 | H120: ='1.3.Financeiras'!F10 -> 3.5247266e+08 | I120: ='1.3.Financeiras'!H10 -> 3.5247266e+08 | J120: =H120-I120 -> 0
D121: Diferenças de metodologia | E121: =SUM('1.3.Financeiras'!E11:E13,'1.3.Financeiras'!E15) -> 2952 | H121: =SUM('1.3.Financeiras'!F11:F13,'1.3.Financeiras'!F15) -> 3.0377847e+08 | I121: =SUM('1.3.Financeiras'!H11:H13,'1.3.Financeiras'!H15) -> 3.042882e+08 | J121: =H121-I121 -> -509730.38
D122: Em resolução - requisitos definidos e planificados | E122: ='1.3.Financeiras'!E14 -> 0 | H122: ='1.3.Financeiras'!F14 -> 0 | I122: ='1.3.Financeiras'!H14 -> 0 | J122: =H122-I122 -> 0
D123: Em análise | E123: ='1.3.Financeiras'!E16 -> 205 | H123: ='1.3.Financeiras'!F16 -> 22601119 | I123: ='1.3.Financeiras'!H16 -> 20173285 | J123: =H123-I123 -> 2427834.4
D124: Total | E124: =SUM(E120:E123) -> 7392 | H124: =SUM(H120:H123) -> 6.7885224e+08 | I124: =SUM(I120:I123) -> 6.7693414e+08 | J124: =SUM(J120:J123) -> 1918104.1
C125: 2) Exclusivo Novo Modelo de Garantias | D125: Diferenças de metodologia | E125: 0 | H125: -
D126: Correções concluídas | E126: 0 | H126: -
...

Sheet 1.1.Pessoais
B5: 1.1 Garantias Pessoais
E7: EXECUÇÃO abril | 16-04-2023
B8: Validação Universos | C8: Casuística | E8: Número de registos | Modelo | F8: Mavalia Modelo | G8: Número de registos | biyr (2500) | H8: Mavalia Biyr (2500) | I8: Diferenças | J8: BIYR 9500 | K8: DIFERENÇA (2500-9500)
B10: 1) Universo Comum | C10: Sem diferenças de mavaliaa | E10: 27026 | F10: 1.90134e+09 | G10: 27026 | H10: 1.90134e+09 | I10: 0
C11: Garantias Manuais | E11: 6 | F11: 3.9336433e+08 | G11: 6 | H11: 472000000 | I11: -78635670
C12: Diferenças na metdologia de cálculo das CSs | E12: 144517 | F12: 1.1378349e+10 | G12: 135918 | H12: 1.7428231e+10 | I12: =F12-H12 -> -6.0498812e+09
C13: Diferenças na metdologia de cálculo das GPs | E13: 183894 | F13: 8.3190518e+09 | G13: 165607 | H13: 8.2932246e+09 | I13: 25827205
C14: Duplicados - CSs | E14: 18 | F14: 1037142.2 | G14: 9 | H14: 877638.1 | I14: 159504.09
C15: Saldo da responsabilidade duplicado no Modelo - CSs | E15: 1660 | F15: 1.2970522e+08 | G15: 1660 | H15: 64852610 | I15: 64852610
C16: Em analise | E16: 1 | F16: 26429.25 | G16: 1 | H16: 18472.25 | I16: 7957
B18: 3) Exclusivo BIYR2500 | C18: Titulares excluidos do novo modelo de garantias | G18: 59257 | H18: 5.0825446e+09 | I18: -5.0825446e+09
C19: Não existe bem pessoal CS | G19: 962 | H19: 1.2189169e+08 | I19: -1.2189169e+08
C20: Garantias Manuais - Titulares excluidos do novo modelo de garantias | G20: 7 | H20: 1456901 | I20: -1456901
C21: Garantias Manuais - Não existe caução carregada. Documentação em revisão pela respetiva área | G21: 61 | H21: 193133818 | I21: -193133818
C22: Garantias Manuais - Garantes diferentes nas cauções | G22: 7 | H22: 40000000 | I22: -40000000
C23: Garantias Manuais - atualizar parametrização de garantias manuais
C24: Ex-cliente | G24: 42 | H24: 8182539.8 | I24: -8182539.8
C25: Caução de PPC aplicada a DOs incorretamente | G25: 1 | H25: 12500000 | I25: -12500000
C26: Sem saldo nas carteiras | G26: 9 | H26: 3109256 | I26: -3109256
C27: Empréstimo Partenon | G27: 1134 | H27: 52759041 | I27: -52759041
C28: Empréstimo sem processo formalizado (GP) | G28: 1314 | H28: 1.2458378e+08 | I28: -1.2458378e+08
C29: Duplicados CS eliminados incorretamente do Modelo
C30: Garantes eliminados da clt18
C31: Produtos diferentes de empréstimos com garantes (sem caução) | G31: 108 | H31: 2276054.5 | I31: -2276054.5
C32: Em analise | G32: 29 | H32: 7939808.3 | I32: -7939808.3
B34: 2) Exclusivo Modelo | C34: Garantias Manuais - Garantes diferentes nas cauções | E34: 6 | F34: 20108600 | I34: 20108600
C35: Garantias Manuais - Zdeposit da parametrização BIYR desatualizado | E35: 6 | F35: 62710951 | I35: 62710951
C36: Garantias Manuais - Caução PPC parametrizada por BIYR com relação cancelada | E36: 39 | F36: 54208756 | I36: 54208756
C37: Titulares ainda não excluidos do novo modelo de garantias | E37: 5 | F37: 49840.86 | I37: 49840.86
C38: Biyr exclui cauções com o mesmo produto | E38: 262 | F38: 48516318 | I38: 48516318
C39: Garantias Manuais - Modelo aplica caução diferente da parameterização | E39: 1 | F39: 4526250 | I39: 4526250
C40: Em analise | E40: 1436 | F40: 26429373 | I40: 26429373
C42: Total | E42: 358877 | F42: =SUM(F10:F40) -> 2.2339424e+10 | G42: 393158 | H42: 3.3810922e+10 | I42: -1.1471492e+10
B45: Validação Universos | C45: Casuística | E45: Número de registos | Modelo | F45: Mavalia Modelo | G45: Número de registos | biyr (2500) | H45: Mavalia Biyr (2500) | I45: Diferenças | J45: BIYR 9500 | K45: DIFERENÇA (2500-9500)
B46: 1) Universo Comum | C46: Sem diferenças de mavaliaa | E46: 27026 | F46: 1.90134e+09 | G46: 27026 | H46: 1.90134e+09 | I46: =F46-H46 -> 0 | J46: 1.7721834e+09 | K46: 1.905074e+09 | M46: N/A | N46: N/A
C47: CS - Caução duplicada no Modelo | E47: 18 | F47: 1037142.2 | G47: 9 | H47: 877638.1 | I47: =F47-H47 -> 159504.09 | J47: 877638.1 | K47: 931075.07 | M47: N/A | N47: N/A
C48: CS - Valor da responsabilidade incorreto no Modelo | E48: 1660 | F48: 1.2970522e+08 | G48: 1660 | H48: 64852610 | I48: =F48-H48 -> 64852610 | J48: 64852610 | K48: 1.3295522e+08 | M48: N/A | N48: N/A
C49: Garantias Manuais - Valor da responsabilidade <> valor da cuação / percentagem cobertura 100% | E49: 6 | F49: 3.9336433e+08 | G49: 6 | H49: 472000000 | I49: =F49-H49 -> -78635670 | J49: 472000000 | K49: 3.9336433e+08 | M49: =I49-N49 -> -78635670 | N49: =F49-K49 -> 0
C50: CS - Valor da responsabilidade <> valor da cuação / percentagem cobertura 100% | E50: 108860 | F50: 9.4844154e+09 | G50: 101715 | H50: 1.4999949e+10 | I50: =F50-H50 -> -5.5155339e+09 | J50: 1.5196769e+10 | K50: 9.4844154e+09 | M50: =I50-N50 -> -5.5155339e+09 | N50: =F50-K50 -> 0
C51: CS - Valor da responsabilidade <> valor da cuação / percentagem cobertura diferente de 100% (campo da % coerente no Biyr e no modelo) | E51: 10465 | F51: 8.0455314e+08 | G51: 9969 | H51: 1.2346095e+09 | I51: =F51-H51 -> -4.3005635e+08 | J51: 1.2346095e+09 | K51: 1.2154199e+09 | M51: =I51-N51 -> -19189556 | N51: =F51-K51 -> -4.1086679e+08
C52: CS - Valor da responsabilidade <> valor da cuação / percentagem cobertura diferente de 100% (campo da % alterado no Biyr) | E52: 1040 | F52: 0 | G52: 1040 | H52: 69079046 | I52: =F52-H52 -> -69079046 | J52: 82485107 | K52: 45061476 | M52: =I52-N52 -> -24017570 | N52: =F52-K52 -> -45061476
C53: CS - Valor da responsabilidade <> valor da cuação / percentagem cobertura diferente de 100% (campo da % forçado no Biyr e no modelo) | E53: 1 | F53: 900575.27 | G53: 1 | H53: 1125000 | I53: =F53-H53 -> -224424.73 | J53: 1125000 | K53: 900575.27 | M53: =I53-N53 -> -224424.73 | N53: =F53-K53 -> 0
C54: CS - Valor da responsabilidade <> valor da cuação / percentagem de cobertura diferente porque caução diferente | E54: 1 | F54: 2500000 | G54: 1 | H54: 1416858 | I54: =F54-H54 -> 1083142 | J54: 1416858 | K54: 2500000 | M54: =I54-N54 -> 1083142 | N54: =F54-K54 -> 0
C55: CS - Valor da responsabilidade = valor da cuação / percentagem cobertura diferente de 100% (campo da % alterado no Biyr) | E55: 1414 | F55: 0 | G55: 1414 | H55: 34096920 | I55: =F55-H55 -> -34096920 | J55: 34106896 | K55: 34106896 | M55: =I55-N55 -> 9976.05 | N55: =F55-K55 -> -34106896
C56: CS - Valor da responsabilidade = valor da cuação / percentagem cobertura diferente de 100% (campo da % coerente no Biyr e no modelo) | E56: 46 | F56: 8754610.9 | G56: 46 | H56: 13234169 | I56: =F56-H56 -> -4479558.4 | J56: 13234169 | K56: 13234169 | M56: =I56-N56 -> 0 | N56: =F56-K56 -> -4479558.4
C57: CS - saldo de despesas/comissões/juros | E57: 22640 | F57: 1.0769509e+09 | G57: 21715 | H57: 1.0744436e+09 | I57: =F57-H57 -> 2507251.7 | J57: 1.9064301e+09 | K57: 1.5014555e+09 | M57: N/A | N57: N/A
C58: CS - saldo de despesas/comissões/juros/custo aquisicao(capital) | E58: 50 | F58: 279490.69 | G58: 17 | H58: 276257.99 | I58: =F58-H58 -> 3232.7 | J58: 518581.23 | K58: 301764.01 | M58: N/A | N58: N/A
C59: GP - saldo de despesas/comissões/juros | E59: 178424 | F59: 8.2588525e+09 | G59: 164153 | H59: 8.2334654e+09 | I59: =F59-H59 -> 25387085 | J59: 0 | K59: 8.2588525e+09 | M59: N/A | N59: N/A
C60: GP - saldo de despesas/comissões/juros/custo aquisicao(capital) | E60: 5470 | F60: 60199270 | G60: 1454 | H60: 59759150 | I60: =F60-H60 -> 440119.53 | J60: 0 | K60: 60199270 | M60: N/A | N60: N/A
C61: Em analise | E61: 1 | F61: 26429.25 | G61: 1 | H61: 18472.25 | I61: =F61-H61 -> 7957 | J61: 35000 | K61: 26429.25 | M61: N/A | N61: N/A

Sheet 1.2.Imóveis
B5: 1.2 Garantias Imóveis
B7: val_universos | C7: origem | D7: num_reg_total | F7: num_reg_biyr | G7: total_biyr2500_mavaliaa | H7: total_modelo_mavaliaa | I7: dif_mavaliaa
B8: COMUM | C8: CS | D8: 855 | F8: 761 | G8: 4.7578658e+09 | H8: 4.3967462e+09 | I8: -3.6111962e+08
B9: COMUM | C9: GP | D9: 399722 | F9: 363631 | G9: 5.3175168e+10 | H9: 5.3143386e+10 | I9: -31781337
B10: EXCL_BIYR | C10: CS | D10: 758 | F10: 758 | G10: 2.5566917e+08
B11: EXCL_BIYR | C11: GP | D11: 485 | F11: 485 | G11: 53678519
B12: EXCL_MODELO | C12: CS | D12: 111 | F12: 1 | H12: 635144.6
B13: EXCL_MODELO | C13: GP | D13: 0 | F13: 0 | H13: 0
F15: EXECUÇÃO abril | 16-04-2023
B16: Validação Universos | C16: Origem/Casuística | F16: Número de registos | Modelo | G16: Número de registos | biyr | H16: Mavalia Modelo | I16: Mavalia Biyr | J16: Diferenças
C18: CS | F18: =D8 -> 855 | G18: =F8 -> 761 | H18: =H8 -> 4.3967462e+09 | I18: =G8 -> 4.7578658e+09 | J18: =I8 -> -3.6111962e+08
C19: Sem diferenças de mavaliaa | F19: 557 | G19: 490 | H19: 3.1732958e+09 | I19: 3.1732958e+09 | J19: =H19-I19 -> 0
C20: Diferenças de rateio | F20: 82 | G20: 75 | H20: 688478056 | I20: 688478056 | J20: =H20-I20 -> 0
C21: Outros Fomentos à Construção | F21: 11 | G21: 10 | H21: 29360905 | I21: 1.8991125e+08 | J21: =H21-I21 -> -1.6055035e+08
C22: Processo de rateio incorreto no BIYR | F22: 54 | G22: 48 | H22: 67921882 | I22: 263590047 | J22: =H22-I22 -> -1.9566817e+08
C23: Percentagem da CST05 ao invés do rateio por responsabilidade | F23: 130 | G23: 118 | H23: 58585567 | I23: 50515870 | J23: =H23-I23 -> 8069697.1
C24: Valor de avaliação mais recente a zero no modelo | F24: 7 | G24: 7 | H24: 0 | I24: 13020419 | J24: =H24-I24 -> -13020419
C25: Erro no cálculo do mavaliaa do lado do modelo | F25: 9 | G25: 9 | H25: 3.7882e+08 | I25: 378820000 | J25: =H25-I25 -> 0.0099999905
B26: 1) Universo Comum | C26: Em análise | F26: =F18-SUM(F19:F25) -> 5 | G26: =G18-SUM(G19:G25) -> 4 | H26: =H18-SUM(H19:H25) -> 283924.15 | I26: =I18-SUM(I19:I25) -> 234311.04 | J26: =J18-SUM(J19:J25) -> 49613.11
C27: GP | F27: =D9 -> 399722 | G27: =F9 -> 363631 | H27: =H9 -> 5.3143386e+10 | I27: =G9 -> 5.3175168e+10 | J27: =I9 -> -31781337
B28: 1) Universo Comum | C28: Sem diferenças de mavaliaa | F28: 246910 | G28: 228862 | H28: 4.0515735e+10 | I28: 4.0515735e+10 | J28: =H28-I28 -> 0
C29: Diferenças de rateio | F29: =SUM(F77:F78) -> 129582 | G29: =SUM(G77:G78) -> 120178 | H29: =SUM(H77:H78) -> 10487467287 | I29: =SUM(I77:I78) -> 1.0487512e+10 | J29: =H29-I29 -> -44873.47
C30: Diferenças de rateio + Erro no cálculo do mavaliaa do lado do modelo | F30: 22743 | G30: 14209 | H30: 1.122253e+09 | I30: 1.122253e+09 | J30: =H30-I30 -> 0.11000013
C31: Erro no cálculo do mavaliaa do lado do modelo | F31: 0 | G31: 0 | H31: 0 | I31: 0 | J31: =H31-I31 -> 0
C32: IFRRU | F32: 242 | G32: 183 | H32: 4.0288241e+08 | I32: 3.4565146e+08 | J32: =H32-I32 -> 57230945
C33: Mapeamento de avaliações por processo e não bem do lado do biyr | F33: =SUM(F80:F81) -> 87 | G33: =SUM(G80:G81) -> 70 | H33: =SUM(H80:H81) -> 11376030 | I33: =SUM(I80:I81) -> 10055039 | J33: =H33-I33 -> 1320991.4
C34: Processo de rateio incorreto no BIYR | F34: 83 | G34: 71 | H34: 4.3399278e+08 | I34: 5.2134009e+08 | J34: =H34-I34 -> -87347311
C35: Valor de avaliação mais recente a zero no modelo | F35: 45 | G35: 38 | H35: 1.5019964e+08 | I35: 1.5333468e+08 | J35: =H35-I35 -> -3135042
C36: Bem IFRRU associado a um segundo empréstimo | F36: 8 | G36: 7 | H36: 11568788 | I36: 11576446 | J36: =H36-I36 -> -7658.28
C37: Rateio realizado por contratos exclusivos do BIYR | F37: 12 | G37: 5 | H37: 5877228.5 | I37: 5253843.9 | J37: =H37-I37 -> 623384.59
B38: 1) Universo Comum | C38: Em análise | F38: =F27-SUM(F28:F37) -> 10 | G38: =G27-SUM(G28:G37) -> 8 | H38: =H27-SUM(H28:H37) -> 2034051.1 | I38: =I27-SUM(I28:I37) -> 2455824.4 | J38: =H38-I38 -> -421773.24
B40: 2) Exclusivo Modelo | C40: CS | F40: =D12 -> 111 | G40: =F12 -> 1 | H40: =H12 -> 635144.6 | J40: =H40-I40 -> 635144.6
B41: 2) Exclusivo Modelo | C41: Em análise | F41: 111 | G41: 1 | H41: 635144.6 | J41: =H41-I41 -> 635144.6
B43: 3) Exclusivo BIYR2500 | C43: CS | F43: =D10 -> 758 | G43: =F10 -> 758 | I43: =G10 -> 2.5566917e+08 | J43: =H43-I43 -> -2.5566917e+08
B44: 3) Exclusivo BIYR2500 | C44: Processos sem bens associados | F44: 562 | G44: 562 | I44: 1.4882485e+08 | J44: =H44-I44 -> -1.4882485e+08
C45: Bens CS com datas de avaliação inválidas | F45: =SUM(F68:F71) -> 194 | G45: =SUM(G68:G71) -> 194 | I45: =SUM(I68:I71) -> 62277314 | J45: =H45-I45 -> -62277314
C46: Inclusão de avaliações sobre processos não formalizados | F46: 2 | G46: 2 | I46: 44567000 | J46: =H46-I46 -> -44567000
C47: Em análise | F47: =F43-SUM(F44:F46) -> 0 | G47: =G43-SUM(G44:G46) -> 0 | I47: =I43-SUM(I44:I46) -> 0 | J47: =H47-I47 -> 0
B48: 3) Exclusivo BIYR2500 | C48: GP | F48: =D11 -> 485 | G48: =F11 -> 485 | I48: =G11 -> 53678519 | J48: =H48-I48 -> -53678519
C49: Processos sem bens associados | F49: =SUM(F73:F75) -> 353 | G49: =SUM(G73:G75) -> 353 | I49: =SUM(I73:I75) -> 31156631 | J49: =H49-I49 -> -31156631
C50: Bens GP excluídos do modelo - datas de avaliação inválidas | F50: 57 | G50: 57 | I50: 15630300 | J50: =H50-I50 -> -15630300
C51: Bens GP excluídos do modelo - sem avaliações/reavaliações nas GPT | F51: 50 | G51: 50 | I51: 3689868.5 | J51: =H51-I51 -> -3689868.5
C52: Bens GP excluídos do modelo - reavaliações sem R, V ou A | F52: 22 | G52: 22 | I52: 1580454.4 | J52: =H52-I52 -> -1580454.4
C53: Empréstimo excluído do modelo por situação do contrato - CSITCTA | F53: 2 | G53: 2 | I53: 208001 | J53: =H53-I53 -> -208001
C54: Processo excluído do modelo por estado do processo - CODEST | F54: 1 | G54: 1 | I54: 1413264.6 | J54: =H54-I54 -> -1413264.6
B55: 3) Exclusivo BIYR2500 | C55: Em análise | F55: =F48-SUM(F49:F54) -> 0 | G55: =G48-SUM(G49:G54) -> 0 | I55: =I48-SUM(I49:I54) -> 0 | J55: =H55-I55 -> 0
D57: Total | F57: =F48+F43+F40+F27+F18 -> 401931 | G57: =G48+G43+G40+G27+G18 -> 365636 | H57: =H48+H43+H40+H27+H18 -> 5.7540768e+10 | I57: =I48+I43+I40+I27+I18 -> 5.8242381e+10 | J57: =J48+J43+J40+J27+J18 -> -7.016135e+08
B58: Legenda: | J58: =J57/I57 -> -0.012046443
B59: Diferenças de metodologia
B60: Correções concluídas
B61: Em resolução - requisitos definidos e planificados
B62: Em resolução - definição de requisitos em curso
B63: Em análise
B65: Auxiliar
B67: Casuística | C67: Subcasuísticas | F67: Número de registos | Modelo | G67: Número de registos | biyr | H67: Mavalia Modelo | I67: Mavalia Biyr
B68: Bens CS com datas de avaliação inválidas | C68: Bens CS com chave GP associada excluídos do modelo - data e montantes inválidos | F68: 5 | G68: 5 | H68: NULL | I68: 2904767.1
C69: Bens CS com chave GP associada excluídos do modelo - data inválida mas montantes válidos | F69: 5 | G69: 5 | H69: NULL | I69: 25065563
C70: Bens CS com chave GP associada excluídos do modelo - montantes da CST08 no BIYR | F70: 1 | G70: 1 | H70: NULL | I70: 1071700
C71: Bens CS sem chave GP associada excluídos do modelo - data inválida | F71: 183 | G71: 183 | H71: NULL | I71: 33235284
B73: Processos sem bens associados | C73: Processos sem bens associados | F73: 60 | G73: 60 | H73: NULL | I73: 6864814
C74: Processos sem bens associados - Responsabilidades com outros tipos de garantia | F74: 47 | G74: 47 | H74: NULL | I74: 4009629.2
C75: Processos sem bens associados - Traçabilidade incompleta no modelo | F75: 246 | G75: 246 | H75: NULL | I75: 20282188
B77: Diferenças de rateio | C77: Diferenças de rateio | F77: 106192 | G77: 103813 | H77: 9.1990643e+09 | I77: 9.1990643e+09
C78: Diferenças de rateio - V2 | F78: 23390 | G78: 16365 | H78: 1.288403e+09 | I78: 1.2884479e+09
B80: Mapeamento de avaliações por processo e não bem do lado do biyr | C80: Mapeamento de avaliações por processo e não bem do lado do biyr | F80: 72 | G80: 57 | H80: 8903030.5 | I80: 8126405.3
C81: Mapeamento de avaliações por processo e não bem do lado do biyr - V2 | F81: 15 | G81: 13 | H81: 2473000 | I81: 1928633.8

Sheet 1.3.Financeiras
B5: 1.3 Garantias Financeiras
E7: EXECUÇÃO abril | 16-04-2023
B8: Validação Universos | C8: Casuística | E8: Número de registos | Modelo | F8: Mavalia Modelo | G8: Número de registos | biyr (2500) | H8: Mavalia Biyr (2500) | I8: Diferenças
B10: 1) Universo Comum | C10: Sem diferenças de mavaliaa | E10: 4235 | F10: 3.5247266e+08 | G10: 4115 | H10: 3.5247266e+08 | I10: 0
C11: Diferenças de repartição | E11: 58 | F11: 3428802.3 | G11: 51 | H11: 3428802.3 | I11: 0
C12: Garantias de outras tipologias
C13: Diferença de saldo - cativo de D+1 | E13: 2894 | F13: 3.0034966e+08 | G13: 2768 | H13: 3.0085939e+08 | I13: -509730.38
C14: Diferença de saldo - cativo de D+1/ Fx Rate
C15: Diferença de saldo - cativo de D+1/ Fx Rate/ Percentagem repartição
C16: Em análise | E16: 205 | F16: 22601119 | G16: 183 | H16: 20173285 | I16: 2427834.4
B18: 3) Exclusivo BIYR2500 | C18: Não existe bem associado | G18: 370 | H18: 5.4650689e+08 | I18: -5.4650689e+08
C19: Data de Cativo vencida | G19: 26 | H19: 1180615.1 | I19: -1180615.1
C20: Em analise | G20: 2 | H20: 3333.3 | I20: -3333.3
B22: 2) Exclusivo Modelo | C22: Em analise | E22: 27 | F22: 930585.01 | I22: 1232874.8
C24: Total | E24: 7419 | F24: 6.7978282e+08 | G24: 7515 | H24: 1.224625e+09 | I24: -5.4484215e+08

Sheet 1.4.Imóveis - LEA
B5: 1.4 Garantias Imóveis - LEA
B7: val_universos | C7: origem | D7: num_reg_total | F7: total_biyr2500_mavaliaa | G7: total_modelo_mavaliaa | H7: dif_mavaliaa
B8: COMUM | C8: LEA | D8: 4941 | F8: 1.4915268e+09 | G8: 1.4928783e+09 | H8: 1351495.8
B9: EXCL_BIYR | C9: LEA | D9: 214 | F9: 24867141 | G9: NULL | H9: NULL
B10: EXCL_MODELO | C10: LEA | D10: 0 | G10: 0
F12: EXECUÇÃO abril | 16-04-2023
B13: Validação Universos | C13: Origem/Casuística | F13: Número de registos (chave_cruzamento) | G13: Mavalia Modelo | H13: Mavalia Biyr | I13: Diferenças
B15: 1) Universo Comum | C15: Total | F15: =D8 -> 4941 | G15: =G8 -> 1.4928783e+09 | H15: =F8 -> 1.4915268e+09 | I15: =H8 -> 1351495.8
B16: 1) Universo Comum | C16: Sem diferenças de mavaliaa | F16: 4926 | G16: 1.4907692e+09 | H16: 1.4907692e+09 | I16: 0
C17: Em análise | F17: =F15-SUM(F16:F16) -> 15 | G17: =G15-SUM(G16:G16) -> 2109095.8 | H17: =H15-SUM(H16:H16) -> 757600 | I17: =G17-H17 -> 1351495.8
B19: 2) Exclusivo Modelo | C19: Total | F19: =D10 -> 0 | G19: =G10 -> 0
C20: Em análise | F20: =F19 -> 0 | G20: =G19 -> 0
B22: 3) Exclusivo BIYR2500 | C22: Total | F22: =D9 -> 214 | H22: =F9 -> 24867141 | I22: =G22-H22 -> -24867141
C23: Datas de vencimento inferiores à data de rácio | F23: 0 | H23: 0 | I23: =G23-H23 -> 0
C24: Universo não existente na CL001 | F24: 0 | H24: 0 | I24: =G24-H24 -> 0
C25: Bens LEA sem chave GP associada na LGT03 | F25: 190 | H25: 22705006 | I25: =G25-H25 -> -22705006
C26: CGARANT = 502 - Garantias financeiras excluidas do modelo | F26: 24 | H26: 2162135.1 | I26: =G26-H26 -> -2162135.1
C27: Em análise | F27: =F22-SUM(F23:F26) -> 0 | H27: =H22-SUM(H23:H26) -> 0 | I27: =G27-H27 -> 0
D29: Total | F29: =F15+F19+F22 -> 5155 | G29: =G15+G19+G22 -> 1.4928783e+09 | H29: =H15+H19+H22 -> 1.516394e+09 | I29: =I15+I19+I22 -> -23515645
B31: Legenda
B32: Diferenças de metodologia
B33: Correções concluídas
B34: Em resolução - requisitos definidos e planificados
B35: Em resolução - definição de requisitos em curso
B36: Em análise

Sheet 1.5.Pessoais - LEA
B5: 1.5 Garantias Pessoais- LEA
E7: EXECUÇÃO abril | 16-04-2023
B8: Validação Universos | C8: Casuística | E8: Número de registos | Modelo | F8: Mavalia Modelo | G8: Número de registos | biyr (2500) | H8: Mavalia Biyr (2500) | I8: Diferenças
B10: 1) Universo Comum | C10: Sem diferenças de mavaliaa | E10: 2352 | F10: 17384623 | G10: 2352 | H10: 17384623 | I10: 0
C11: Contas de juros,comissoes | E11: 29796 | F11: 1.4135821e+09 | G11: 29796 | H11: 1.4099095e+09 | I11: 3672643.3
C12: Contas de juros,comissoes e capital(28) | E12: 62 | F12: 10480063 | G12: 62 | H12: 5404960.4 | I12: 5075102.4
C13: Contas em analise | E13: 1282 | F13: 1.4495291e+08 | G13: 1282 | H13: 1.2006287e+08 | I13: 24890040
B15: 3) Exclusivo BIYR2500 | C15: Titulares excluidos do novo modelo de garantias | G15: 4165 | H15: 83862122 | I15: -83862122
C16: Ex - cliente | G16: 184 | H16: 8262922.5 | I16: -8262922.5
C17: A operação não existe no Biyr1500 (Leasing) | G17: 32 | H17: 900.12 | I17: -900.12
C18: Em analise | G18: 1 | H18: 26000 | I18: -26000
B20: 2) Exclusivo Modelo | C20: Em analise
C22: Total | E22: =SUM(E10:E20) -> 33492 | F22: =SUM(F10:F20) -> 1.5863997e+09 | G22: =SUM(G10:G20) -> 37874 | H22: =SUM(H10:H20) -> 1.6449139e+09 | I22: =SUM(I10:I20) -> -58514159
B25: Legenda
B26: Diferenças de metodologia
B27: Correções concluídas
B28: Em resolução - requisitos definidos e planificados
B29: Em resolução - definição de requisitos em curso
B30: Em análise

Sheet 1.6.Factoring
B5: 1.6 Factoring
E7: EXECUÇÃO abril | 16-04-2023
B8: Validação Universos | C8: Casuística | E8: Número de registos | Modelo | F8: Mavalia Modelo | G8: Número de registos | biyr (2500) | H8: Mavalia Biyr (2500) | I8: Diferenças | K8: BIYR 9500 | L8: DIFERENÇA BIYRs
B10: 1) Universo Comum | C10: Sem diferenças de mavaliaa | E10: 11158 | F10: 1.0598608e+08 | G10: 603 | H10: 1.0598608e+08 | I10: 0
C11: Em analise | E11: 16 | F11: 11311.21 | G11: 1 | H11: 11397.31 | I11: -86.1
B13: 3) Exclusivo BIYR2500 | C13: Faturas sem saldo | G13: 327 | H13: 0 | I13: 0
B15: 2) Exclusivo Modelo | C15: Em analise
C17: Total | E17: 11174 | F17: 1.0599739e+08 | G17: 931 | H17: 1.0599748e+08 | I17: -86.1
B21: Legenda
B22: Diferenças de metodologia
B23: Correções concluídas
B24: Em resolução - requisitos definidos e planificados
B25: Em resolução - definição de requisitos em curso
B26: Em análise

Sheet Dados Fevereiro | 16-04-23
B5: 1. Análises Universos
C7: Data de referência | D7: 44985
C8: Data de atualização | D8: 45032
B11: Universo BIYR 2500 | J11: Universo BIYR9500
C13: tipo | D13: biyr2500_caplic | E13: biyr2500_tipgargblbg | F13: num_resp_proc | H13: biyr2500_mavaliaa
C14: F | D14: DC | E14: 2 | F14: 2224 | H14: 1.0529615e+08 | J14: 2224 | K14: 1.0529615e+08 | M14: 0 | N14: 0
C15: F | D15: DP | E15: 2 | F15: 2023 | H15: 2.0259703e+08 | J15: 2023 | K15: 2.0259703e+08 | M15: 0 | N15: 0
C16: F | D16: FU | E16: 2 | F16: 1970 | H16: 2.2536119e+08 | J16: 1970 | K16: 2.2536119e+08 | M16: 0 | N16: 0
C17: F | D17: SG | E17: 2 | F17: 1158 | H17: 91656003 | J17: 1158 | K17: 91656003 | M17: 0 | N17: 0
C18: F | D18: TT | E18: 2 | F18: 59 | H18: 59255534 | J18: 59 | K18: 59255534 | M18: 0 | N18: 0
C19: FAC | D19: FAC | E19: 1 | F19: 908 | H19: 89756471 | J19: 908 | K19: 89756471 | M19: 0 | N19: 0
C20: I | D20: CS | E20: 2 | F20: 1544 | H20: 4.1835912e+09 | J20: 1544 | K20: 4.1835912e+09 | M20: 0 | N20: 0
C21: I | D21: GP | E21: 2 | F21: 367686 | H21: 5.3741241e+10 | J21: 367686 | K21: 5.3741241e+10 | M21: 0 | N21: 0
C22: LEA | D22: LEA | E22: 1 | F22: 21585 | H22: 1.6709264e+09 | J22: 21585 | K22: 1.6709264e+09 | M22: 0 | N22: 0
C23: LEA | D23: LEA | E23: 2 | F23: 5224 | H23: 1.5279433e+09 | J23: 5224 | K23: 1.5279433e+09 | M23: 0 | N23: 0
C24: P | D24: CLI | E24: 1 | F24: 92235 | H24: 8.8539723e+09 | J24: 92235 | K24: 8.8539723e+09 | M24: 0 | N24: 0
C25: P | D25: CS | E25: 1 | F25: 36189 | H25: 4.3536762e+09 | J25: 36189 | K25: 4.3237217e+09 | M25: 0 | N25: -29954520
... C27: TBD | D27: CS | E27: 2 | F27: 394 | H27: 5.3971342e+08 | J27: 394 | K27: 5.3971342e+08 | M27: 0 | N27: 0
B29: Universo Modelo
C31: tipo | D31: origem | E31: num_resp_proc | F31: mavaliaa | H31: Variação face à execução anterior
C32: F | D32: CS | E32: 7797 | F32: 6.8900011e+08 | H32: -128 | I32: -23263880
C33: I | D33: CS | E33: 997 | F33: 3.6578362e+09 | H33: -6 | I33: 32819882
C34: I | D34: GP | E34: 403837 | F34: 5.3632896e+10 | H34: -572 | I34: -1.9325523e+08
C35: I | D35: LEA | E35: 5005 | F35: 1.5038247e+09 | H35: -36 | I35: -25110208
C36: P | D36: CS | E36: 109155 | F36: 1.407208e+10 | H36: -57 | I36: -98348613
C37: P | D37: FAC | E37: 9041 | F37: 89757971 | H37: 567 | I37: 10499982
C38: P | D38: GP | E38: 100557 | F38: 8.6836283e+09 | H38: -378 | I38: -1.0063296e+08
C39: P | D39: LEA | E39: 17463 | F39: 1.5890088e+09 | H39: -38 | I39: 1.4284615e+09
E40: 653852
C43: Valores originais
D45: BIYR9500 | F45: Novo Modelo de Garantias
C46: Tipo | D46: # Responsabilidade/ Processo | E46: MAVALIAA | F46: # Responsabilidade/ Processo | H46: MAVALIAA | I46: ∆ Responsabilidade/ Processo | J46: ∆ MAVALIAA
C47: Factoring | D47: 908 | E47: 89756471 | F47: 9041 | H47: 89757971 | I47: 8133 | J47: 1500
C48: Pessoais | D48: 253562 | E48: 3.5128683e+10 | F48: 209712 | H48: 2.2755708e+10 | I48: -43850 | J48: -1.2372974e+10
C49: Financeiras | D49: 7828 | E49: 1.2238793e+09 | F49: 7797 | H49: 6.8900011e+08 | I49: -31 | J49: -5.3487922e+08
C50: Imóveis | D50: 369230 | E50: 5.7924832e+10 | F50: 404834 | H50: 5.7290732e+10 | I50: 35604 | J50: -6.3410014e+08
C51: Leasing - Imóveis | D51: 5224 | E51: 1.5279433e+09 | F51: 5005 | H51: 1.5038247e+09 | I51: -219 | J51: -24118645
C52: Leasing - Pessoais | D52: 21585 | E52: 1.6709264e+09 | F52: 17463 | H52: 1.5890088e+09 | I52: -4122 | J52: -81917646
C53: Total | D53: 658337 | E53: 9.756602e+10 | F53: 653852 | H53: 8.3918032e+10 | I53: -4485 | J53: -1.3647988e+10
C55: Para Steering
D57: BIYR9500 (1) | F57: Novo Modelo de Garantias (2)
C58: Tipo | D58: # Responsabilidade/ Processo | E58: MAVALIAA | F58: # Responsabilidade/ Processo | H58: MAVALIAA | I58: ∆ Responsabilidade/ Processo | J58: ∆ MAVALIAA
C59: Factoring* | D59: 908 | E59: 89756471 | F59: 9041 | H59: 89757971 | I59: 8133 | J59: 1500
C60: Pessoais* | D60: 401166 | E60: 3.5128683e+10 | F60: 365599 | H60: 2.2755708e+10 | I60: -35567 | J60: -1.2372974e+10
C61: Financeiras | D61: 7828 | E61: 1.2238793e+09 | F61: 7797 | H61: 6.8900011e+08 | I61: -31 | J61: -5.3487922e+08
C62: Imóveis | D62: 369230 | E62: 5.7924832e+10 | F62: 404834 | H62: 5.7290732e+10 | I62: 35604 | J62: -6.3410014e+08
C63: Leasing - Pessoais* | D63: 38217 | E63: 1.6709264e+09 | F63: 33731 | H63: 1.5890088e+09 | I63: -4486 | J63: -81917646
C64: Leasing - Imóveis | D64: 5224 | E64: 1.5279433e+09 | F64: 5005 | H64: 1.5038247e+09 | I64: -219 | J64: -24118645
C65: Total | D65: 822573 | E65: 9.756602e+10 | F65: 826007 | H65: 8.3918032e+10 | I65: 3434 | J65: -1.3647988e+10
C66: * Numero de registos ao nível do bem - Cliente
C68: Temas a ser contemplados no novo modelo
C70: ID | D70: Temas | J70: # Responsabilidade/Processo | L70: Diferenças de MAVALIAA
C71: 1 | D71: Apenas serão contempladas responsabilidades/processos com bens associados e com datas de vencimento válidas (exceto bens com origem leasing). | J71: 2506 | L71: -8.8693731e+08
C72: 2 | D72: Todos os titulares, utilizados atualmente como garantias pessoais, serão excluídos. | J72: 65461 | L72: -4.6834725e+09
C73: 3 | D73: O algoritmos de apuramento de saldos das responsabilidades, relevantes para a distribuição dos montantes das garantias, passará a contemplar contas contabilisticas de juros e despesas vencidas. | J73: 188298 | L73: 21626230
C74: 4 | D74: A metodologia de aprovisionamento de montantes de avaliação para fomentos à construção e IFRRUs, manter-se-á como no BIYR9500, à exceção da percentagem de avaliação atribuida ao BST (será como base o financiamento inicial do IFRRU e não no saldo em dívida atual). A mesma será revista após o rácio de Abril. | J74: 233 | L74: 47114506
C75: 5 | D75: O montante considerado em garantias pessoais deve ser o da responsabilidade e não o do processo. | J75: 149237 | L75: -6.3764062e+09
C76: 6 | D76: No caso das garantias financeiras, serão descartadas as garantias cuja data de vencimento seja inferior à data do rácio, mesmo tendo uma data de cativo válida (uma vez que a data de cativo pode ser referente à DO e não ao bem contratualizado incialmente com o cliente). Metodologia que será aplicada após quantificação de impactos. | J76: Por quantificar | L76: Por quantificar
C77: 7 | D77: Apenas serão contemplados bens com datas de avaliação válidas (exceto bens com origem leasing). | J77: 329 | L77: -90881145
C78: 8 | D78: A metodologia de aprovisionamento de montantes/datas de avaliação aplicada a Fomentos à Construção deve ser igual para todas as origens. | J78: 10 | L78: -1.5951735e+08
C79: 9 | D79: O rateio dos bens pelos processos/responsabilidades deve ser feito independentemente da origem e deve ser realizado com base no valor atual da responsabilidade e não pela percentagem de cobertura calculada no momento da contratação. | J79: 279 | L79: -1.8941887e+08
C80: 10 | D80: Saldos de bens financeiros utilizados no modelo apresentam lag de um dia face ao BIYR (BIYR utiliza saldos de D+1). | J80: 3079 | L80: 1081238.6
C81: 11 | D81: São consideradas todas as garantias financeiras válidas dentro da mesma caução, independentemente da sua tipologia (exemplo, DO e TT). | J81: 3 | L81: 118763.27
C82: 12 | D82: Apenas serão contempladas garantias manuais de PPC com caução carregada para o respetivo emitente/programa. Nos títulos as cauções são as mesmas. | J82: 73 | L82: -1.9844788e+08
C83: 13 | D83: O montante das garantias pessoais será o resultado após a multiplicação do valor da responsabilidade pela percentagem de cobertura do cliente (bem). | J83: 149237 | L83: -9.5314914e+08
C84: 14 | D84: Deve ser considerado o valor de avaliação mais recente, independentemente do seu montante (inclusão de avaliações com montante igual a zero). | J84: 55 | L84: -16258323
B85: Novo | C85: 15 | D85: Apenas serão contemplados empréstimos e processos formalizados. | J85: 3 | L85: -1621716.1
B86: Novo | C86: 16 | D86: Cauções de garantias manuais de PPC selecionadas de acordo com a nova parametrização (cauções mais recentes carregadas por emitente/programa). | J86: 73 | L86: 25968613
C87: 17 | D87: Em caso da percentagem de cobertura do cliente ser 0% na fonte de garantias pessoais, o modelo não vai forçar a percentagem para 100% (ao contrário da metodologia do biyr). | J87: Por quantificar | L87: Por quantificar
B90: 2. Resumo de Casuísticas
B93: Garantias Pessoais (excluindo Leasing e Factoring):
C95: Universo | D95: # Responsabilidade/ Processo/Cliente | E95: MAVALIAA
C96: Novo Modelo de Garantias | D96: 365599 | E96: 2.2755708e+10
C97: BIYR9500 | D97: 401166 | E97: 3.5128683e+10
C100: Universos | D100: Casuística | E100: # Responsabilidade/ Processo/Cliente | F100: ∆ Follow up | H100: MAVALIAA - Novo Modelo de garantias | I100: MAVALIAA - BIYR9500 | J100: Diferenças
C101: 1) Universo Comum | D101: Sem diferenças de mavaliaa | E101: 26962 | H101: 1.978657e+09 | I101: 1.978657e+09 | J101: 0
D102: Diferenças de metodologia | E102: 337535 | H102: 2.0501401e+10 | I102: 2.780933e+10 | J102: -7.3079291e+09
D103: Em resolução - requisitos definidos e planificados | E103: 18 | H103: 1037387.1 | I103: 877638.1 | J103: 159748.98
D104: Em análise | E104: 9 | H104: 15662211 | I104: 15657244 | J104: 4966.64
D105: Total | E105: 364524 | H105: 2.2496758e+10 | I105: 2.9804522e+10 | J105: -7.3077644e+09
C106: 2) Exclusivo Novo Modelo de Garantias | D106: Diferenças de metodologia | E106: 33 | H106: 1.5933478e+08 | J106: 1.5933478e+08
D107: Em resolução - requisitos definidos e planificados | E107: 197 | H107: 26759366 | J107: 26759366
D108: Em resolução - definição de requisitos em curso | E108: 261 | H108: 51894748 | J108: 51894748
D109: Em análise | E109: 584 | H109: 20961833 | J109: 20961833
D110: Total | E110: 1075 | H110: 2.5895073e+08 | J110: 2.5895073e+08
C111: 3) Exclusivo BIYR2500 | D111: Diferenças de metodologia | E111: 62346 | I111: 5.0852739e+09 | J111: -5.0852739e+09 | P111: -
D112: Em resolução - requisitos definidos e planificados | E112: 2465 | I112: 1.8229404e+08 | J112: -1.8229404e+08
D113: Em resolução - definição de requisitos em curso | E113: 503 | I113: 48504637 | J113: -48504637
D114: Em análise | E114: 33 | I114: 8088056.9 | J114: -8088056.9
D115: Total | E115: 65347 | I115: 5.3241606e+09 | J115: -5.3241606e+09
E116: 365599 | F116: 0 | H116: 2.2755708e+10 | I116: 3.5128683e+10
H117: 0 | I117: 0
B118: Garantias Financeiras:
C120: Universos | D120: Casuística | E120: # Responsabilidade/ Processo | F120: ∆ Follow up | H120: MAVALIAA - Novo Modelo de garantias | I120: MAVALIAA - BIYR9500 | J120: Diferenças
C121: 1) Universo Comum | D121: Sem diferenças de mavaliaa | E121: 4421 | H121: 3.9988868e+08 | I121: 3.9988868e+08 | J121: 0
D122: Diferenças de metodologia | E122: 3149 | H122: 2.6277433e+08 | I122: 2.6157433e+08 | J122: 1200001.9
D123: Em resolução - requisitos definidos e planificados | E123: 42 | H123: 8360586.2 | I123: 8360925.4 | J123: -339.2
D124: Em análise | E124: 152 | H124: 16743636 | I124: 14338634 | J124: 2405002
D125: Total | E125: 7764 | H125: 6.8776723e+08 | I125: 6.8416257e+08 | J125: 3604664.7
C126: 2) Exclusivo Novo Modelo de Garantias | D126: Diferenças de metodologia | E126: 0 | H126: -
...
