Workbook

Sheet 0. Instruções
B6: 0. Instruções
B8: Projeto | D8: Testes MBDT
B9: Âmbito | D9: Análise dos campo da Loan Tape MBDT
B11: Para a validação dos campos da Loan Tape MBDT é necessário percorrer os seguintes steps:
B14: 1. Atualizar o script de simulação com o campo em análise.
B15: 1.1. Verificar a especificação do campo em análise. Se aplicável, verificar se é necessário reportar valor para ajustes.
B16: 1.2. Montar a simulação do campo tendo atenção aos seguintes pormenores:
B17: a) Não vamos fazer JOIN com a tabela de parametrização (LT803). Em alternativa, montamos um CASE WHEN ou importamos a parametrização.
B18: b) Para operações de ajustes verificar se o campo deve reportar valor.
B19: c) Se for necessário aplicar algum filtro (ou tratamento) que não está na especificação deixar um comentário no código.
B20: d) Garantir que não existem duplicados e deixar no código o número de registos de cada LEFT JOIN.
B21: 2. Executar no HUE (em HIVE) o CREATE TABLE do script de simulação.
B22: 3. Executar no HUE o script de controlo de universo.
B23: a) O número de registos em comum tem de ser igual ao número de registos do teste de coerência. Caso tenhamos registos que não são comuns é necessário ver exemplos para ver o que está a acontecer.
B24: 4. Verificar com IT o nome da tabela a testar e filtros. Caso seja necessário, atualizar as tabelas infra:
C26: Nome da Tabela | D26: Tabela Loan Tape Pilar 3 | E26: Tabela Simulada | F26: Chave 1 | G26: Chave 2
C27: Univ_Oper | D27: lt001_univ_oper | E27: simul_lt001 | F27: a | G27: b
C28: Entity | D28: lt003_entity | E28: simul_lt003_entity | F28: entty_id
C29: Instrument | D29: lt002_instrument | E29: simul_lt002_instrument | F29: instrmnt_id
C30: Protection | D30: lt004_protection | E30: simul_lt004 | F30: prtctn_id
C31: INSTR_ENTITY | D31: lt005_instr_ent | E31: simul_lt005_instr_ent | F31: instrmnt_id | G31: entty_id
C32: INSTR_PROTECTION | D32: lt006_instr_prot | E32: simul_lt006_instr_prot | F32: instrmnt_id | G32: prtctn_id
C34: Filtros
C35: Schema Loan Tape Pilar 3 | D35: bu_loantape_work
C36: Schema Simulada | D36: bu_loantape_work
C37: nome_perimetro | D37: Individual Local
C38: segmento | D38: ESTR
C39: ambito | D39: SRB_MBDT
C40: ambito | D40: PILAR3
C41: entidade | D41: 00100
C42: Filtro Loan Tape Pilar 3 | D42: =+"ref_date='${ref_date}'"&" AND "&C37&"='"&D37&"' AND "&C38&"='"&D38&"' AND ambito='"&D39&"'"&" AND "&C41&"='"&D41&"'" -> ref_date='${ref_date}' AND nome_perimetro='Individual Local' AND segmento='ESTR' AND ambito='SRB_MBDT' AND entidade='00100'
C43: Filtro Simulada | D43: =+"ref_date='${ref_date}'"&" AND "&C37&"='"&D37&"' AND "&C38&"='"&D38&"' AND ambito='"&D40&"'"&" AND "&C41&"='"&D41&"'" -> ref_date='${ref_date}' AND nome_perimetro='Individual Local' AND segmento='ESTR' AND ambito='PILAR3' AND entidade='00100'
B45: 5. Executar no HUE a bateria de testes da sheet 2. Script para o campo em análise
B46: a) Analisar resultados. Caso no teste de coerência conste diferenças é necessário ver exemplos. Deixo abaixo uma query de exemplo:
C48: SELECT *
C49: FROM
C50: (SELECT instrmnt_id,
C51: LNS_CLLTRLZD_CLSSFCTN
C52: FROM BU_LOANTAPE_WORK.LT002_INSTRUMENT
C53: WHERE ref_date='${ref_date}'
C54: AND nome_perimetro='Individual Corporativo'
C55: AND segmento='ESTR'
C56: AND ambito='PILAR3')X
C57: INNER JOIN
C58: (SELECT instrmnt_id AS instrmnt_id_SIMUL,
C59: LNS_CLLTRLZD_CLSSFCTN AS LNS_CLLTRLZD_CLSSFCTN_SIMUL
... C61: WHERE COALESCE(CAST(X.LNS_CLLTRLZD_CLSSFCTN AS STRING),'')<>COALESCE(CAST(Y.LNS_CLLTRLZD_CLSSFCTN_SIMUL AS STRING),'')
B69: 6. XXX
B70: 7. XXX

Sheet 1. Status
H6: 1. Status dos Testes
H8: REF_DATE | I8: 45991
B9: Auxiliar
B10: Coerência | C10: Validade | D10: Caracteres Especiais | E10: Missings | F10: Not applicable | H10: Tabela | I10: Campo | J10: Testes Corridos (#) | K10: Número de Registos ID1. (#) | L10: ID Exec. 1. | M10: 1. Erros de Coerência (#) | N10: Número de Registos ID2&9 (#) | O10: ID Exec. 2 | P10: 2. Erros de Valores Admitidos (#) | Q10: ID Exec. 3. | R10: 3. Erros de Caract. Especiais (#) | S10: ID Exec. 4. | T10: 4. Registos com Missing (#) | U10: ID Exec. 5. | V10: 5. Registos com N/A (#) | W10: 6. Valor Mínimo | X10: 7. Valor Máximo | Y10: Comentário | Z10: Status
A11: =+H11&I11&$I$8 -> UNIV_OPERcempresa45991 | B11: {=+MAX(IF('ID1&5'!A:A='1. Status'!A11&'1. Status'!$B$10,'ID1&5'!K:K))} -> 0 | C11: {=+MAX(IF('ID1&5'!A:A='1. Status'!A11&'1. Status'!$C$10,'ID1&5'!K:K))} -> 0 | D11: {=+MAX(IF('ID1&5'!A:A='1. Status'!A11&'1. Status'!$D$10,'ID1&5'!K:K))} -> 0 | E11: {=+MAX(IF('ID1&5'!A:A='1. Status'!A11&'1. Status'!$E$10,'ID1&5'!K:K))} -> 0 | F11: {=+MAX(IF('ID1&5'!A:A='1. Status'!A11&'1. Status'!$F$10,'ID1&5'!K:K))} -> 0 | H11: UNIV_OPER | I11: cempresa | J11: =+COUNTIF('ID1&5'!G:G,'1. Status'!I11) -> 0 | K11: =+IFERROR(VLOOKUP(CONCATENATE(A11,$B$10,B11),'ID1&5'!B:J,8,FALSE),"-") -> - | L11: =+IFERROR(VLOOKUP(B11,'ID1&5'!K:L,2,FALSE),"-") -> - | M11: =+IFERROR(VLOOKUP(CONCATENATE(A11,$B$10,B11),'ID1&5'!B:J,9,FALSE),"-") -> - | N11: =+IFERROR(VLOOKUP(CONCATENATE(A11,$C$10,C11),'ID1&5'!B:J,8,FALSE),"-") -> - | O11: =+IFERROR(VLOOKUP(C11,'ID1&5'!K:L,2,FALSE),"-") -> - | P11: =+IFERROR(VLOOKUP(CONCATENATE(A11,$C$10,C11),'ID1&5'!B:J,9,FALSE),"-") -> - | Q11: =+IFERROR(VLOOKUP(D11,'ID1&5'!K:L,2,FALSE),"-") -> - | R11: =+IFERROR(VLOOKUP(CONCATENATE(A11,$D$10,D11),'ID1&5'!B:J,9,FALSE),"-") -> - | S11: =+IFERROR(VLOOKUP(E11,'ID1&5'!K:L,2,FALSE),"-") -> - | T11: =+IFERROR(VLOOKUP(CONCATENATE(A11,$E$10,E11),'ID1&5'!B:J,9,FALSE),"-") -> - | U11: =+IFERROR(VLOOKUP(F11,'ID1&5'!K:L,2,FALSE),"-") -> - | V11: =+IFERROR(VLOOKUP(CONCATENATE(A11,$F$10,F11),'ID1&5'!B:J,9,FALSE),"-") -> - | W11: =+IFERROR(VLOOKUP(A11,'ID6&7'!A:I,9,FALSE),"-") -> - | X11: =+IFERROR(VLOOKUP(A11,'ID6&7'!A:J,10,FALSE),"-") -> - | Z11: =+IF(J11=0,"Por iniciar",IF(OR(K11="-",M11="-",P11="-",R11="-",T11="-",V11="-"),"Em testes",IF(AND(M11=0,P11=0,R11=0,T11<>K11,V11<>K11),"OK","NOK"))) -> Por iniciar
A12: =+H12&I12&$I$8 -> UNIV_OPERcbalcao45991 | B12: {=+MAX(IF('ID1&5'!A:A='1. Status'!A12&'1. Status'!$B$10,'ID1&5'!K:K))} -> 0 | C12: {=+MAX(IF('ID1&5'!A:A='1. Status'!A12&'1. Status'!$C$10,'ID1&5'!K:K))} -> 0 | D12: {=+MAX(IF('ID1&5'!A:A='1. Status'!A12&'1. Status'!$D$10,'ID1&5'!K:K))} -> 0 | E12: {=+MAX(IF('ID1&5'!A:A='1. Status'!A12&'1. Status'!$E$10,'ID1&5'!K:K))} -> 0 | F12: {=+MAX(IF('ID1&5'!A:A='1. Status'!A12&'1. Status'!$F$10,'ID1&5'!K:K))} -> 0 | H12: UNIV_OPER | I12: cbalcao | J12: =+COUNTIF('ID1&5'!G:G,'1. Status'!I12) -> 0 | K12: =+IFERROR(VLOOKUP(CONCATENATE(A12,$B$10,B12),'ID1&5'!B:J,8,FALSE),"-") -> - | L12: =+IFERROR(VLOOKUP(B12,'ID1&5'!K:L,2,FALSE),"-") -> - | M12: =+IFERROR(VLOOKUP(CONCATENATE(A12,$B$10,B12),'ID1&5'!B:J,9,FALSE),"-") -> - | N12: =+IFERROR(VLOOKUP(CONCATENATE(A12,$C$10,C12),'ID1&5'!B:J,8,FALSE),"-") -> - | O12: =+IFERROR(VLOOKUP(C12,'ID1&5'!K:L,2,FALSE),"-") -> - | P12: =+IFERROR(VLOOKUP(CONCATENATE(A12,$C$10,C12),'ID1&5'!B:J,9,FALSE),"-") -> - | Q12: =+IFERROR(VLOOKUP(D12,'ID1&5'!K:L,2,FALSE),"-") -> - | R12: =+IFERROR(VLOOKUP(CONCATENATE(A12,$D$10,D12),'ID1&5'!B:J,9,FALSE),"-") -> - | S12: =+IFERROR(VLOOKUP(E12,'ID1&5'!K:L,2,FALSE),"-") -> - | T12: =+IFERROR(VLOOKUP(CONCATENATE(A12,$E$10,E12),'ID1&5'!B:J,9,FALSE),"-") -> - | U12: =+IFERROR(VLOOKUP(F12,'ID1&5'!K:L,2,FALSE),"-") -> - | V12: =+IFERROR(VLOOKUP(CONCATENATE(A12,$F$10,F12),'ID1&5'!B:J,9,FALSE),"-") -> - | W12: =+IFERROR(VLOOKUP(A12,'ID6&7'!A:I,9,FALSE),"-") -> - | X12: =+IFERROR(VLOOKUP(A12,'ID6&7'!A:J,10,FALSE),"-") -> - | Z12: =+IF(J12=0,"Por iniciar",IF(OR(K12="-",M12="-",P12="-",R12="-",T12="-",V12="-"),"Em testes",IF(AND(M12=0,P12=0,R12=0,T12<>K12,V12<>K12),"OK","NOK"))) -> Por iniciar
A13: =+H13&I13&$I$8 -> UNIV_OPERcnumecta45991 | B13: {=+MAX(IF('ID1&5'!A:A='1. Status'!A13&'1. Status'!$B$10,'ID1&5'!K:K))} -> 0 | C13: {=+MAX(IF('ID1&5'!A:A='1. Status'!A13&'1. Status'!$C$10,'ID1&5'!K:K))} -> 0 | D13: {=+MAX(IF('ID1&5'!A:A='1. Status'!A13&'1. Status'!$D$10,'ID1&5'!K:K))} -> 0 | E13: {=+MAX(IF('ID1&5'!A:A='1. Status'!A13&'1. Status'!$E$10,'ID1&5'!K:K))} -> 0 | F13: {=+MAX(IF('ID1&5'!A:A='1. Status'!A13&'1. Status'!$F$10,'ID1&5'!K:K))} -> 0 | H13: UNIV_OPER | I13: cnumecta | J13: =+COUNTIF('ID1&5'!G:G,'1. Status'!I13) -> 0 | K13: =+IFERROR(VLOOKUP(CONCATENATE(A13,$B$10,B13),'ID1&5'!B:J,8,FALSE),"-") -> - | L13: =+IFERROR(VLOOKUP(B13,'ID1&5'!K:L,2,FALSE),"-") -> - | M13: =+IFERROR(VLOOKUP(CONCATENATE(A13,$B$10,B13),'ID1&5'!B:J,9,FALSE),"-") -> - | N13: =+IFERROR(VLOOKUP(CONCATENATE(A13,$C$10,C13),'ID1&5'!B:J,8,FALSE),"-") -> - | O13: =+IFERROR(VLOOKUP(C13,'ID1&5'!K:L,2,FALSE),"-") -> - | P13: =+IFERROR(VLOOKUP(CONCATENATE(A13,$C$10,C13),'ID1&5'!B:J,9,FALSE),"-") -> - | Q13: =+IFERROR(VLOOKUP(D13,'ID1&5'!K:L,2,FALSE),"-") -> - | R13: =+IFERROR(VLOOKUP(CONCATENATE(A13,$D$10,D13),'ID1&5'!B:J,9,FALSE),"-") -> - | S13: =+IFERROR(VLOOKUP(E13,'ID1&5'!K:L,2,FALSE),"-") -> - | T13: =+IFERROR(VLOOKUP(CONCATENATE(A13,$E$10,E13),'ID1&5'!B:J,9,FALSE),"-") -> - | U13: =+IFERROR(VLOOKUP(F13,'ID1&5'!K:L,2,FALSE),"-") -> - | V13: =+IFERROR(VLOOKUP(CONCATENATE(A13,$F$10,F13),'ID1&5'!B:J,9,FALSE),"-") -> - | W13: =+IFERROR(VLOOKUP(A13,'ID6&7'!A:I,9,FALSE),"-") -> - | X13: =+IFERROR(VLOOKUP(A13,'ID6&7'!A:J,10,FALSE),"-") -> - | Z13: =+IF(J13=0,"Por iniciar",IF(OR(K13="-",M13="-",P13="-",R13="-",T13="-",V13="-"),"Em testes",IF(AND(M13=0,P13=0,R13=0,T13<>K13,V13<>K13),"OK","NOK"))) -> Por iniciar
A14: =+H14&I14&$I$8 -> UNIV_OPERzdeposit45991 | B14: {=+MAX(IF('ID1&5'!A:A='1. Status'!A14&'1. Status'!$B$10,'ID1&5'!K:K))} -> 0 | C14: {=+MAX(IF('ID1&5'!A:A='1. Status'!A14&'1. Status'!$C$10,'ID1&5'!K:K))} -> 0 | D14: {=+MAX(IF('ID1&5'!A:A='1. Status'!A14&'1. Status'!$D$10,'ID1&5'!K:K))} -> 0 | E14: {=+MAX(IF('ID1&5'!A:A='1. Status'!A14&'1. Status'!$E$10,'ID1&5'!K:K))} -> 0 | F14: {=+MAX(IF('ID1&5'!A:A='1. Status'!A14&'1. Status'!$F$10,'ID1&5'!K:K))} -> 0 | H14: UNIV_OPER | I14: zdeposit | J14: =+COUNTIF('ID1&5'!G:G,'1. Status'!I14) -> 0 | K14: =+IFERROR(VLOOKUP(CONCATENATE(A14,$B$10,B14),'ID1&5'!B:J,8,FALSE),"-") -> - | L14: =+IFERROR(VLOOKUP(B14,'ID1&5'!K:L,2,FALSE),"-") -> - | M14: =+IFERROR(VLOOKUP(CONCATENATE(A14,$B$10,B14),'ID1&5'!B:J,9,FALSE),"-") -> - | N14: =+IFERROR(VLOOKUP(CONCATENATE(A14,$C$10,C14),'ID1&5'!B:J,8,FALSE),"-") -> - | O14: =+IFERROR(VLOOKUP(C14,'ID1&5'!K:L,2,FALSE),"-") -> - | P14: =+IFERROR(VLOOKUP(CONCATENATE(A14,$C$10,C14),'ID1&5'!B:J,9,FALSE),"-") -> - | Q14: =+IFERROR(VLOOKUP(D14,'ID1&5'!K:L,2,FALSE),"-") -> - | R14: =+IFERROR(VLOOKUP(CONCATENATE(A14,$D$10,D14),'ID1&5'!B:J,9,FALSE),"-") -> - | S14: =+IFERROR(VLOOKUP(E14,'ID1&5'!K:L,2,FALSE),"-") -> - | T14: =+IFERROR(VLOOKUP(CONCATENATE(A14,$E$10,E14),'ID1&5'!B:J,9,FALSE),"-") -> - | U14: =+IFERROR(VLOOKUP(F14,'ID1&5'!K:L,2,FALSE),"-") -> - | V14: =+IFERROR(VLOOKUP(CONCATENATE(A14,$F$10,F14),'ID1&5'!B:J,9,FALSE),"-") -> - | W14: =+IFERROR(VLOOKUP(A14,'ID6&7'!A:I,9,FALSE),"-") -> - | X14: =+IFERROR(VLOOKUP(A14,'ID6&7'!A:J,10,FALSE),"-") -> - | Z14: =+IF(J14=0,"Por iniciar",IF(OR(K14="-",M14="-",P14="-",R14="-",T14="-",V14="-"),"Em testes",IF(AND(M14=0,P14=0,R14=0,T14<>K14,V14<>K14),"OK","NOK"))) -> Por iniciar
A15: =+H15&I15&$I$8 -> UNIV_OPERzcliente45991 | B15: {=+MAX(IF('ID1&5'!A:A='1. Status'!A15&'1. Status'!$B$10,'ID1&5'!K:K))} -> 0 | C15: {=+MAX(IF('ID1&5'!A:A='1. Status'!A15&'1. Status'!$C$10,'ID1&5'!K:K))} -> 0 | D15: {=+MAX(IF('ID1&5'!A:A='1. Status'!A15&'1. Status'!$D$10,'ID1&5'!K:K))} -> 0 | E15: {=+MAX(IF('ID1&5'!A:A='1. Status'!A15&'1. Status'!$E$10,'ID1&5'!K:K))} -> 0 | F15: {=+MAX(IF('ID1&5'!A:A='1. Status'!A15&'1. Status'!$F$10,'ID1&5'!K:K))} -> 0 | H15: UNIV_OPER | I15: zcliente | J15: =+COUNTIF('ID1&5'!G:G,'1. Status'!I15) -> 0 | K15: =+IFERROR(VLOOKUP(CONCATENATE(A15,$B$10,B15),'ID1&5'!B:J,8,FALSE),"-") -> - | L15: =+IFERROR(VLOOKUP(B15,'ID1&5'!K:L,2,FALSE),"-") -> - | M15: =+IFERROR(VLOOKUP(CONCATENATE(A15,$B$10,B15),'ID1&5'!B:J,9,FALSE),"-") -> - | N15: =+IFERROR(VLOOKUP(CONCATENATE(A15,$C$10,C15),'ID1&5'!B:J,8,FALSE),"-") -> - | O15: =+IFERROR(VLOOKUP(C15,'ID1&5'!K:L,2,FALSE),"-") -> - | P15: =+IFERROR(VLOOKUP(CONCATENATE(A15,$C$10,C15),'ID1&5'!B:J,9,FALSE),"-") -> - | Q15: =+IFERROR(VLOOKUP(D15,'ID1&5'!K:L,2,FALSE),"-") -> - | R15: =+IFERROR(VLOOKUP(CONCATENATE(A15,$D$10,D15),'ID1&5'!B:J,9,FALSE),"-") -> - | S15: =+IFERROR(VLOOKUP(E15,'ID1&5'!K:L,2,FALSE),"-") -> - | T15: =+IFERROR(VLOOKUP(CONCATENATE(A15,$E$10,E15),'ID1&5'!B:J,9,FALSE),"-") -> - | U15: =+IFERROR(VLOOKUP(F15,'ID1&5'!K:L,2,FALSE),"-") -> - | V15: =+IFERROR(VLOOKUP(CONCATENATE(A15,$F$10,F15),'ID1&5'!B:J,9,FALSE),"-") -> - | W15: =+IFERROR(VLOOKUP(A15,'ID6&7'!A:I,9,FALSE),"-") -> - | X15: =+IFERROR(VLOOKUP(A15,'ID6&7'!A:J,10,FALSE),"-") -> - | Z15: =+IF(J15=0,"Por iniciar",IF(OR(K15="-",M15="-",P15="-",R15="-",T15="-",V15="-"),"Em testes",IF(AND(M15=0,P15=0,R15=0,T15<>K15,V15<>K15),"OK","NOK"))) -> Por iniciar
A16: =+H16&I16&$I$8 -> UNIV_OPERccontab_final_ifrs45991 | B16: {=+MAX(IF('ID1&5'!A:A='1. Status'!A16&'1. Status'!$B$10,'ID1&5'!K:K))} -> 0 | C16: {=+MAX(IF('ID1&5'!A:A='1. Status'!A16&'1. Status'!$C$10,'ID1&5'!K:K))} -> 0 | D16: {=+MAX(IF('ID1&5'!A:A='1. Status'!A16&'1. Status'!$D$10,'ID1&5'!K:K))} -> 0 | E16: {=+MAX(IF('ID1&5'!A:A='1. Status'!A16&'1. Status'!$E$10,'ID1&5'!K:K))} -> 0 | F16: {=+MAX(IF('ID1&5'!A:A='1. Status'!A16&'1. Status'!$F$10,'ID1&5'!K:K))} -> 0 | H16: UNIV_OPER | I16: ccontab_final_ifrs | J16: =+COUNTIF('ID1&5'!G:G,'1. Status'!I16) -> 0 | K16: =+IFERROR(VLOOKUP(CONCATENATE(A16,$B$10,B16),'ID1&5'!B:J,8,FALSE),"-") -> - | L16: =+IFERROR(VLOOKUP(B16,'ID1&5'!K:L,2,FALSE),"-") -> - | M16: =+IFERROR(VLOOKUP(CONCATENATE(A16,$B$10,B16),'ID1&5'!B:J,9,FALSE),"-") -> - | N16: =+IFERROR(VLOOKUP(CONCATENATE(A16,$C$10,C16),'ID1&5'!B:J,8,FALSE),"-") -> - | O16: =+IFERROR(VLOOKUP(C16,'ID1&5'!K:L,2,FALSE),"-") -> - | P16: =+IFERROR(VLOOKUP(CONCATENATE(A16,$C$10,C16),'ID1&5'!B:J,9,FALSE),"-") -> - | Q16: =+IFERROR(VLOOKUP(D16,'ID1&5'!K:L,2,FALSE),"-") -> - | R16: =+IFERROR(VLOOKUP(CONCATENATE(A16,$D$10,D16),'ID1&5'!B:J,9,FALSE),"-") -> - | S16: =+IFERROR(VLOOKUP(E16,'ID1&5'!K:L,2,FALSE),"-") -> - | T16: =+IFERROR(VLOOKUP(CONCATENATE(A16,$E$10,E16),'ID1&5'!B:J,9,FALSE),"-") -> - | U16: =+IFERROR(VLOOKUP(F16,'ID1&5'!K:L,2,FALSE),"-") -> - | V16: =+IFERROR(VLOOKUP(CONCATENATE(A16,$F$10,F16),'ID1&5'!B:J,9,FALSE),"-") -> - | W16: =+IFERROR(VLOOKUP(A16,'ID6&7'!A:I,9,FALSE),"-") -> - | X16: =+IFERROR(VLOOKUP(A16,'ID6&7'!A:J,10,FALSE),"-") -> - | Z16: =+IF(J16=0,"Por iniciar",IF(OR(K16="-",M16="-",P16="-",R16="-",T16="-",V16="-"),"Em testes",IF(AND(M16=0,P16=0,R16=0,T16<>K16,V16<>K16),"OK","NOK"))) -> Por iniciar
A17: =+H17&I17&$I$8 -> UNIV_OPERccontab_final_pcsb45991 | B17: {=+MAX(IF('ID1&5'!A:A='1. Status'!A17&'1. Status'!$B$10,'ID1&5'!K:K))} -> 0 | C17: {=+MAX(IF('ID1&5'!A:A='1. Status'!A17&'1. Status'!$C$10,'ID1&5'!K:K))} -> 0 | D17: {=+MAX(IF('ID1&5'!A:A='1. Status'!A17&'1. Status'!$D$10,'ID1&5'!K:K))} -> 0 | E17: {=+MAX(IF('ID1&5'!A:A='1. Status'!A17&'1. Status'!$E$10,'ID1&5'!K:K))} -> 0 | F17: {=+MAX(IF('ID1&5'!A:A='1. Status'!A17&'1. Status'!$F$10,'ID1&5'!K:K))} -> 0 | H17: UNIV_OPER | I17: ccontab_final_pcsb | J17: =+COUNTIF('ID1&5'!G:G,'1. Status'!I17) -> 0 | K17: =+IFERROR(VLOOKUP(CONCATENATE(A17,$B$10,B17),'ID1&5'!B:J,8,FALSE),"-") -> - | L17: =+IFERROR(VLOOKUP(B17,'ID1&5'!K:L,2,FALSE),"-") -> - | M17: =+IFERROR(VLOOKUP(CONCATENATE(A17,$B$10,B17),'ID1&5'!B:J,9,FALSE),"-") -> - | N17: =+IFERROR(VLOOKUP(CONCATENATE(A17,$C$10,C17),'ID1&5'!B:J,8,FALSE),"-") -> - | O17: =+IFERROR(VLOOKUP(C17,'ID1&5'!K:L,2,FALSE),"-") -> - | P17: =+IFERROR(VLOOKUP(CONCATENATE(A17,$C$10,C17),'ID1&5'!B:J,9,FALSE),"-") -> - | Q17: =+IFERROR(VLOOKUP(D17,'ID1&5'!K:L,2,FALSE),"-") -> - | R17: =+IFERROR(VLOOKUP(CONCATENATE(A17,$D$10,D17),'ID1&5'!B:J,9,FALSE),"-") -> - | S17: =+IFERROR(VLOOKUP(E17,'ID1&5'!K:L,2,FALSE),"-") -> - | T17: =+IFERROR(VLOOKUP(CONCATENATE(A17,$E$10,E17),'ID1&5'!B:J,9,FALSE),"-") -> - | U17: =+IFERROR(VLOOKUP(F17,'ID1&5'!K:L,2,FALSE),"-") -> - | V17: =+IFERROR(VLOOKUP(CONCATENATE(A17,$F$10,F17),'ID1&5'!B:J,9,FALSE),"-") -> - | W17: =+IFERROR(VLOOKUP(A17,'ID6&7'!A:I,9,FALSE),"-") -> - | X17: =+IFERROR(VLOOKUP(A17,'ID6&7'!A:J,10,FALSE),"-") -> - | Z17: =+IF(J17=0,"Por iniciar",IF(OR(K17="-",M17="-",P17="-",R17="-",T17="-",V17="-"),"Em testes",IF(AND(M17=0,P17=0,R17=0,T17<>K17,V17<>K17),"OK","NOK"))) -> Por iniciar
A18: =+H18&I18&$I$8 -> UNIV_OPERccontab_final_cargabal45991 | B18: {=+MAX(IF('ID1&5'!A:A='1. Status'!A18&'1. Status'!$B$10,'ID1&5'!K:K))} -> 0 | C18: {=+MAX(IF('ID1&5'!A:A='1. Status'!A18&'1. Status'!$C$10,'ID1&5'!K:K))} -> 0 | D18: {=+MAX(IF('ID1&5'!A:A='1. Status'!A18&'1. Status'!$D$10,'ID1&5'!K:K))} -> 0 | E18: {=+MAX(IF('ID1&5'!A:A='1. Status'!A18&'1. Status'!$E$10,'ID1&5'!K:K))} -> 0 | F18: {=+MAX(IF('ID1&5'!A:A='1. Status'!A18&'1. Status'!$F$10,'ID1&5'!K:K))} -> 0 | H18: UNIV_OPER | I18: ccontab_final_cargabal | J18: =+COUNTIF('ID1&5'!G:G,'1. Status'!I18) -> 0 | K18: =+IFERROR(VLOOKUP(CONCATENATE(A18,$B$10,B18),'ID1&5'!B:J,8,FALSE),"-") -> - | L18: =+IFERROR(VLOOKUP(B18,'ID1&5'!K:L,2,FALSE),"-") -> - | M18: =+IFERROR(VLOOKUP(CONCATENATE(A18,$B$10,B18),'ID1&5'!B:J,9,FALSE),"-") -> - | N18: =+IFERROR(VLOOKUP(CONCATENATE(A18,$C$10,C18),'ID1&5'!B:J,8,FALSE),"-") -> - | O18: =+IFERROR(VLOOKUP(C18,'ID1&5'!K:L,2,FALSE),"-") -> - | P18: =+IFERROR(VLOOKUP(CONCATENATE(A18,$C$10,C18),'ID1&5'!B:J,9,FALSE),"-") -> - | Q18: =+IFERROR(VLOOKUP(D18,'ID1&5'!K:L,2,FALSE),"-") -> - | R18: =+IFERROR(VLOOKUP(CONCATENATE(A18,$D$10,D18),'ID1&5'!B:J,9,FALSE),"-") -> - | S18: =+IFERROR(VLOOKUP(E18,'ID1&5'!K:L,2,FALSE),"-") -> - | T18: =+IFERROR(VLOOKUP(CONCATENATE(A18,$E$10,E18),'ID1&5'!B:J,9,FALSE),"-") -> - | U18: =+IFERROR(VLOOKUP(F18,'ID1&5'!K:L,2,FALSE),"-") -> - | V18: =+IFERROR(VLOOKUP(CONCATENATE(A18,$F$10,F18),'ID1&5'!B:J,9,FALSE),"-") -> - | W18: =+IFERROR(VLOOKUP(A18,'ID6&7'!A:I,9,FALSE),"-") -> - | X18: =+IFERROR(VLOOKUP(A18,'ID6&7'!A:J,10,FALSE),"-") -> - | Z18: =+IF(J18=0,"Por iniciar",IF(OR(K18="-",M18="-",P18="-",R18="-",T18="-",V18="-"),"Em testes",IF(AND(M18=0,P18=0,R18=0,T18<>K18,V18<>K18),"OK","NOK"))) -> Por iniciar
A19: =+H19&I19&$I$8 -> UNIV_OPERccontab_final45991 | B19: {=+MAX(IF('ID1&5'!A:A='1. Status'!A19&'1. Status'!$B$10,'ID1&5'!K:K))} -> 0 | C19: {=+MAX(IF('ID1&5'!A:A='1. Status'!A19&'1. Status'!$C$10,'ID1&5'!K:K))} -> 0 | D19: {=+MAX(IF('ID1&5'!A:A='1. Status'!A19&'1. Status'!$D$10,'ID1&5'!K:K))} -> 0 | E19: {=+MAX(IF('ID1&5'!A:A='1. Status'!A19&'1. Status'!$E$10,'ID1&5'!K:K))} -> 0 | F19: {=+MAX(IF('ID1&5'!A:A='1. Status'!A19&'1. Status'!$F$10,'ID1&5'!K:K))} -> 0 | H19: UNIV_OPER | I19: ccontab_final | J19: =+COUNTIF('ID1&5'!G:G,'1. Status'!I19) -> 0 | K19: =+IFERROR(VLOOKUP(CONCATENATE(A19,$B$10,B19),'ID1&5'!B:J,8,FALSE),"-") -> - | L19: =+IFERROR(VLOOKUP(B19,'ID1&5'!K:L,2,FALSE),"-") -> - | M19: =+IFERROR(VLOOKUP(CONCATENATE(A19,$B$10,B19),'ID1&5'!B:J,9,FALSE),"-") -> - | N19: =+IFERROR(VLOOKUP(CONCATENATE(A19,$C$10,C19),'ID1&5'!B:J,8,FALSE),"-") -> - | O19: =+IFERROR(VLOOKUP(C19,'ID1&5'!K:L,2,FALSE),"-") -> - | P19: =+IFERROR(VLOOKUP(CONCATENATE(A19,$C$10,C19),'ID1&5'!B:J,9,FALSE),"-") -> - | Q19: =+IFERROR(VLOOKUP(D19,'ID1&5'!K:L,2,FALSE),"-") -> - | R19: =+IFERROR(VLOOKUP(CONCATENATE(A19,$D$10,D19),'ID1&5'!B:J,9,FALSE),"-") -> - | S19: =+IFERROR(VLOOKUP(E19,'ID1&5'!K:L,2,FALSE),"-") -> - | T19: =+IFERROR(VLOOKUP(CONCATENATE(A19,$E$10,E19),'ID1&5'!B:J,9,FALSE),"-") -> - | U19: =+IFERROR(VLOOKUP(F19,'ID1&5'!K:L,2,FALSE),"-") -> - | V19: =+IFERROR(VLOOKUP(CONCATENATE(A19,$F$10,F19),'ID1&5'!B:J,9,FALSE),"-") -> - | W19: =+IFERROR(VLOOKUP(A19,'ID6&7'!A:I,9,FALSE),"-") -> - | X19: =+IFERROR(VLOOKUP(A19,'ID6&7'!A:J,10,FALSE),"-") -> - | Z19: =+IF(J19=0,"Por iniciar",IF(OR(K19="-",M19="-",P19="-",R19="-",T19="-",V19="-"),"Em testes",IF(AND(M19=0,P19=0,R19=0,T19<>K19,V19<>K19),"OK","NOK"))) -> Por iniciar
A20: =+H20&I20&$I$8 -> UNIV_OPERmsaldo_final45991 | B20: {=+MAX(IF('ID1&5'!A:A='1. Status'!A20&'1. Status'!$B$10,'ID1&5'!K:K))} -> 0 | C20: {=+MAX(IF('ID1&5'!A:A='1. Status'!A20&'1. Status'!$C$10,'ID1&5'!K:K))} -> 0 | D20: {=+MAX(IF('ID1&5'!A:A='1. Status'!A20&'1. Status'!$D$10,'ID1&5'!K:K))} -> 0 | E20: {=+MAX(IF('ID1&5'!A:A='1. Status'!A20&'1. Status'!$E$10,'ID1&5'!K:K))} -> 0 | F20: {=+MAX(IF('ID1&5'!A:A='1. Status'!A20&'1. Status'!$F$10,'ID1&5'!K:K))} -> 0 | H20: UNIV_OPER | I20: msaldo_final | J20: =+COUNTIF('ID1&5'!G:G,'1. Status'!I20) -> 0 | K20: =+IFERROR(VLOOKUP(CONCATENATE(A20,$B$10,B20),'ID1&5'!B:J,8,FALSE),"-") -> - | L20: =+IFERROR(VLOOKUP(B20,'ID1&5'!K:L,2,FALSE),"-") -> - | M20: =+IFERROR(VLOOKUP(CONCATENATE(A20,$B$10,B20),'ID1&5'!B:J,9,FALSE),"-") -> - | N20: =+IFERROR(VLOOKUP(CONCATENATE(A20,$C$10,C20),'ID1&5'!B:J,8,FALSE),"-") -> - | O20: =+IFERROR(VLOOKUP(C20,'ID1&5'!K:L,2,FALSE),"-") -> - | P20: =+IFERROR(VLOOKUP(CONCATENATE(A20,$C$10,C20),'ID1&5'!B:J,9,FALSE),"-") -> - | Q20: =+IFERROR(VLOOKUP(D20,'ID1&5'!K:L,2,FALSE),"-") -> - | R20: =+IFERROR(VLOOKUP(CONCATENATE(A20,$D$10,D20),'ID1&5'!B:J,9,FALSE),"-") -> - | S20: =+IFERROR(VLOOKUP(E20,'ID1&5'!K:L,2,FALSE),"-") -> - | T20: =+IFERROR(VLOOKUP(CONCATENATE(A20,$E$10,E20),'ID1&5'!B:J,9,FALSE),"-") -> - | U20: =+IFERROR(VLOOKUP(F20,'ID1&5'!K:L,2,FALSE),"-") -> - | V20: =+IFERROR(VLOOKUP(CONCATENATE(A20,$F$10,F20),'ID1&5'!B:J,9,FALSE),"-") -> - | W20: =+IFERROR(VLOOKUP(A20,'ID6&7'!A:I,9,FALSE),"-") -> - | X20: =+IFERROR(VLOOKUP(A20,'ID6&7'!A:J,10,FALSE),"-") -> - | Z20: =+IF(J20=0,"Por iniciar",IF(OR(K20="-",M20="-",P20="-",R20="-",T20="-",V20="-"),"Em testes",IF(AND(M20=0,P20=0,R20=0,T20<>K20,V20<>K20),"OK","NOK"))) -> Por iniciar
A21: =+H21&I21&$I$8 -> UNIV_OPERcarteira_contabilistica45991 | B21: {=+MAX(IF('ID1&5'!A:A='1. Status'!A21&'1. Status'!$B$10,'ID1&5'!K:K))} -> 0 | C21: {=+MAX(IF('ID1&5'!A:A='1. Status'!A21&'1. Status'!$C$10,'ID1&5'!K:K))} -> 0 | D21: {=+MAX(IF('ID1&5'!A:A='1. Status'!A21&'1. Status'!$D$10,'ID1&5'!K:K))} -> 0 | E21: {=+MAX(IF('ID1&5'!A:A='1. Status'!A21&'1. Status'!$E$10,'ID1&5'!K:K))} -> 0 | F21: {=+MAX(IF('ID1&5'!A:A='1. Status'!A21&'1. Status'!$F$10,'ID1&5'!K:K))} -> 0 | H21: UNIV_OPER | I21: carteira_contabilistica | J21: =+COUNTIF('ID1&5'!G:G,'1. Status'!I21) -> 0 | K21: =+IFERROR(VLOOKUP(CONCATENATE(A21,$B$10,B21),'ID1&5'!B:J,8,FALSE),"-") -> - | L21: =+IFERROR(VLOOKUP(B21,'ID1&5'!K:L,2,FALSE),"-") -> - | M21: =+IFERROR(VLOOKUP(CONCATENATE(A21,$B$10,B21),'ID1&5'!B:J,9,FALSE),"-") -> - | N21: =+IFERROR(VLOOKUP(CONCATENATE(A21,$C$10,C21),'ID1&5'!B:J,8,FALSE),"-") -> - | O21: =+IFERROR(VLOOKUP(C21,'ID1&5'!K:L,2,FALSE),"-") -> - | P21: =+IFERROR(VLOOKUP(CONCATENATE(A21,$C$10,C21),'ID1&5'!B:J,9,FALSE),"-") -> - | Q21: =+IFERROR(VLOOKUP(D21,'ID1&5'!K:L,2,FALSE),"-") -> - | R21: =+IFERROR(VLOOKUP(CONCATENATE(A21,$D$10,D21),'ID1&5'!B:J,9,FALSE),"-") -> - | S21: =+IFERROR(VLOOKUP(E21,'ID1&5'!K:L,2,FALSE),"-") -> - | T21: =+IFERROR(VLOOKUP(CONCATENATE(A21,$E$10,E21),'ID1&5'!B:J,9,FALSE),"-") -> - | U21: =+IFERROR(VLOOKUP(F21,'ID1&5'!K:L,2,FALSE),"-") -> - | V21: =+IFERROR(VLOOKUP(CONCATENATE(A21,$F$10,F21),'ID1&5'!B:J,9,FALSE),"-") -> - | W21: =+IFERROR(VLOOKUP(A21,'ID6&7'!A:I,9,FALSE),"-") -> - | X21: =+IFERROR(VLOOKUP(A21,'ID6&7'!A:J,10,FALSE),"-") -> - | Z21: =+IF(J21=0,"Por iniciar",IF(OR(K21="-",M21="-",P21="-",R21="-",T21="-",V21="-"),"Em testes",IF(AND(M21=0,P21=0,R21=0,T21<>K21,V21<>K21),"OK","NOK"))) -> Por iniciar
A22: =+H22&I22&$I$8 -> UNIV_OPERinstrumento_financeiro45991 | B22: {=+MAX(IF('ID1&5'!A:A='1. Status'!A22&'1. Status'!$B$10,'ID1&5'!K:K))} -> 0 | C22: {=+MAX(IF('ID1&5'!A:A='1. Status'!A22&'1. Status'!$C$10,'ID1&5'!K:K))} -> 0 | D22: {=+MAX(IF('ID1&5'!A:A='1. Status'!A22&'1. Status'!$D$10,'ID1&5'!K:K))} -> 0 | E22: {=+MAX(IF('ID1&5'!A:A='1. Status'!A22&'1. Status'!$E$10,'ID1&5'!K:K))} -> 0 | F22: {=+MAX(IF('ID1&5'!A:A='1. Status'!A22&'1. Status'!$F$10,'ID1&5'!K:K))} -> 0 | H22: UNIV_OPER | I22: instrumento_financeiro | J22: =+COUNTIF('ID1&5'!G:G,'1. Status'!I22) -> 0 | K22: =+IFERROR(VLOOKUP(CONCATENATE(A22,$B$10,B22),'ID1&5'!B:J,8,FALSE),"-") -> - | L22: =+IFERROR(VLOOKUP(B22,'ID1&5'!K:L,2,FALSE),"-") -> - | M22: =+IFERROR(VLOOKUP(CONCATENATE(A22,$B$10,B22),'ID1&5'!B:J,9,FALSE),"-") -> - | N22: =+IFERROR(VLOOKUP(CONCATENATE(A22,$C$10,C22),'ID1&5'!B:J,8,FALSE),"-") -> - | O22: =+IFERROR(VLOOKUP(C22,'ID1&5'!K:L,2,FALSE),"-") -> - | P22: =+IFERROR(VLOOKUP(CONCATENATE(A22,$C$10,C22),'ID1&5'!B:J,9,FALSE),"-") -> - | Q22: =+IFERROR(VLOOKUP(D22,'ID1&5'!K:L,2,FALSE),"-") -> - | R22: =+IFERROR(VLOOKUP(CONCATENATE(A22,$D$10,D22),'ID1&5'!B:J,9,FALSE),"-") -> - | S22: =+IFERROR(VLOOKUP(E22,'ID1&5'!K:L,2,FALSE),"-") -> - | T22: =+IFERROR(VLOOKUP(CONCATENATE(A22,$E$10,E22),'ID1&5'!B:J,9,FALSE),"-") -> - | U22: =+IFERROR(VLOOKUP(F22,'ID1&5'!K:L,2,FALSE),"-") -> - | V22: =+IFERROR(VLOOKUP(CONCATENATE(A22,$F$10,F22),'ID1&5'!B:J,9,FALSE),"-") -> - | W22: =+IFERROR(VLOOKUP(A22,'ID6&7'!A:I,9,FALSE),"-") -> - | X22: =+IFERROR(VLOOKUP(A22,'ID6&7'!A:J,10,FALSE),"-") -> - | Z22: =+IF(J22=0,"Por iniciar",IF(OR(K22="-",M22="-",P22="-",R22="-",T22="-",V22="-"),"Em testes",IF(AND(M22=0,P22=0,R22=0,T22<>K22,V22<>K22),"OK","NOK"))) -> Por iniciar
... A63: =+H63&I63&$I$8 -> UNIV_OPERidcomb_lt_final45991 | B63: {=+MAX(IF('ID1&5'!A:A='1. Status'!A63&'1. Status'!$B$10,'ID1&5'!K:K))} -> 0 | C63: {=+MAX(IF('ID1&5'!A:A='1. Status'!A63&'1. Status'!$C$10,'ID1&5'!K:K))} -> 0 | D63: {=+MAX(IF('ID1&5'!A:A='1. Status'!A63&'1. Status'!$D$10,'ID1&5'!K:K))} -> 0 | E63: {=+MAX(IF('ID1&5'!A:A='1. Status'!A63&'1. Status'!$E$10,'ID1&5'!K:K))} -> 0 | F63: {=+MAX(IF('ID1&5'!A:A='1. Status'!A63&'1. Status'!$F$10,'ID1&5'!K:K))} -> 0 | H63: UNIV_OPER | I63: idcomb_lt_final | J63: =+COUNTIF('ID1&5'!G:G,'1. Status'!I63) -> 0 | K63: =+IFERROR(VLOOKUP(CONCATENATE(A63,$B$10,B63),'ID1&5'!B:J,8,FALSE),"-") -> - | L63: =+IFERROR(VLOOKUP(B63,'ID1&5'!K:L,2,FALSE),"-") -> - | M63: =+IFERROR(VLOOKUP(CONCATENATE(A63,$B$10,B63),'ID1&5'!B:J,9,FALSE),"-") -> - | N63: =+IFERROR(VLOOKUP(CONCATENATE(A63,$C$10,C63),'ID1&5'!B:J,8,FALSE),"-") -> - | O63: =+IFERROR(VLOOKUP(C63,'ID1&5'!K:L,2,FALSE),"-") -> - | P63: =+IFERROR(VLOOKUP(CONCATENATE(A63,$C$10,C63),'ID1&5'!B:J,9,FALSE),"-") -> - | Q63: =+IFERROR(VLOOKUP(D63,'ID1&5'!K:L,2,FALSE),"-") -> - | R63: =+IFERROR(VLOOKUP(CONCATENATE(A63,$D$10,D63),'ID1&5'!B:J,9,FALSE),"-") -> - | S63: =+IFERROR(VLOOKUP(E63,'ID1&5'!K:L,2,FALSE),"-") -> - | T63: =+IFERROR(VLOOKUP(CONCATENATE(A63,$E$10,E63),'ID1&5'!B:J,9,FALSE),"-") -> - | U63: =+IFERROR(VLOOKUP(F63,'ID1&5'!K:L,2,FALSE),"-") -> - | V63: =+IFERROR(VLOOKUP(CONCATENATE(A63,$F$10,F63),'ID1&5'!B:J,9,FALSE),"-") -> - | W63: =+IFERROR(VLOOKUP(A63,'ID6&7'!A:I,9,FALSE),"-") -> - | X63: =+IFERROR(VLOOKUP(A63,'ID6&7'!A:J,10,FALSE),"-") -> - | Z63: =+IF(J63=0,"Por iniciar",IF(OR(K63="-",M63="-",P63="-",R63="-",T63="-",V63="-"),"Em testes",IF(AND(M63=0,P63=0,R63=0,T63<>K63,V63<>K63),"OK","NOK"))) -> Por iniciar
H64: UNIV_OPER | I64: rank_insolv | J64: =+COUNTIF('ID1&5'!G:G,'1. Status'!I64) -> 0 | K64: =+IFERROR(VLOOKUP(CONCATENATE(A64,$B$10,B64),'ID1&5'!B:J,8,FALSE),"-") -> - | L64: =+IFERROR(VLOOKUP(B64,'ID1&5'!K:L,2,FALSE),"-") -> - | M64: =+IFERROR(VLOOKUP(CONCATENATE(A64,$B$10,B64),'ID1&5'!B:J,9,FALSE),"-") -> - | N64: =+IFERROR(VLOOKUP(CONCATENATE(A64,$C$10,C64),'ID1&5'!B:J,8,FALSE),"-") -> - | O64: =+IFERROR(VLOOKUP(C64,'ID1&5'!K:L,2,FALSE),"-") -> - | P64: =+IFERROR(VLOOKUP(CONCATENATE(A64,$C$10,C64),'ID1&5'!B:J,9,FALSE),"-") -> - | Q64: =+IFERROR(VLOOKUP(D64,'ID1&5'!K:L,2,FALSE),"-") -> - | R64: =+IFERROR(VLOOKUP(CONCATENATE(A64,$D$10,D64),'ID1&5'!B:J,9,FALSE),"-") -> - | S64: =+IFERROR(VLOOKUP(E64,'ID1&5'!K:L,2,FALSE),"-") -> - | T64: =+IFERROR(VLOOKUP(CONCATENATE(A64,$E$10,E64),'ID1&5'!B:J,9,FALSE),"-") -> - | U64: =+IFERROR(VLOOKUP(F64,'ID1&5'!K:L,2,FALSE),"-") -> - | V64: =+IFERROR(VLOOKUP(CONCATENATE(A64,$F$10,F64),'ID1&5'!B:J,9,FALSE),"-") -> - | W64: =+IFERROR(VLOOKUP(A64,'ID6&7'!A:I,9,FALSE),"-") -> - | X64: =+IFERROR(VLOOKUP(A64,'ID6&7'!A:J,10,FALSE),"-") -> - | Z64: =+IF(J64=0,"Por iniciar",IF(OR(K64="-",M64="-",P64="-",R64="-",T64="-",V64="-"),"Em testes",IF(AND(M64=0,P64=0,R64=0,T64<>K64,V64<>K64),"OK","NOK"))) -> Por iniciar
H65: INSTRUMENT | I65: cntrct_id | J65: =+COUNTIF('ID1&5'!G:G,'1. Status'!I65) -> 0 | K65: =+IFERROR(VLOOKUP(CONCATENATE(A65,$B$10,B65),'ID1&5'!B:J,8,FALSE),"-") -> - | L65: =+IFERROR(VLOOKUP(B65,'ID1&5'!K:L,2,FALSE),"-") -> - | M65: =+IFERROR(VLOOKUP(CONCATENATE(A65,$B$10,B65),'ID1&5'!B:J,9,FALSE),"-") -> - | N65: =+IFERROR(VLOOKUP(CONCATENATE(A65,$C$10,C65),'ID1&5'!B:J,8,FALSE),"-") -> - | O65: =+IFERROR(VLOOKUP(C65,'ID1&5'!K:L,2,FALSE),"-") -> - | P65: =+IFERROR(VLOOKUP(CONCATENATE(A65,$C$10,C65),'ID1&5'!B:J,9,FALSE),"-") -> - | Q65: =+IFERROR(VLOOKUP(D65,'ID1&5'!K:L,2,FALSE),"-") -> - | R65: =+IFERROR(VLOOKUP(CONCATENATE(A65,$D$10,D65),'ID1&5'!B:J,9,FALSE),"-") -> - | S65: =+IFERROR(VLOOKUP(E65,'ID1&5'!K:L,2,FALSE),"-") -> - | T65: =+IFERROR(VLOOKUP(CONCATENATE(A65,$E$10,E65),'ID1&5'!B:J,9,FALSE),"-") -> - | U65: =+IFERROR(VLOOKUP(F65,'ID1&5'!K:L,2,FALSE),"-") -> - | V65: =+IFERROR(VLOOKUP(CONCATENATE(A65,$F$10,F65),'ID1&5'!B:J,9,FALSE),"-") -> - | W65: =+IFERROR(VLOOKUP(A65,'ID6&7'!A:I,9,FALSE),"-") -> - | X65: =+IFERROR(VLOOKUP(A65,'ID6&7'!A:J,10,FALSE),"-") -> - | Z65: =+IF(J65=0,"Por iniciar",IF(OR(K65="-",M65="-",P65="-",R65="-",T65="-",V65="-"),"Em testes",IF(AND(M65=0,P65=0,R65=0,T65<>K65,V65<>K65),"OK","NOK"))) -> Por iniciar
H66: INSTRUMENT | I66: crrncy_dnmntn | J66: =+COUNTIF('ID1&5'!G:G,'1. Status'!I66) -> 0 | K66: =+IFERROR(VLOOKUP(CONCATENATE(A66,$B$10,B66),'ID1&5'!B:J,8,FALSE),"-") -> - | L66: =+IFERROR(VLOOKUP(B66,'ID1&5'!K:L,2,FALSE),"-") -> - | M66: =+IFERROR(VLOOKUP(CONCATENATE(A66,$B$10,B66),'ID1&5'!B:J,9,FALSE),"-") -> - | N66: =+IFERROR(VLOOKUP(CONCATENATE(A66,$C$10,C66),'ID1&5'!B:J,8,FALSE),"-") -> - | O66: =+IFERROR(VLOOKUP(C66,'ID1&5'!K:L,2,FALSE),"-") -> - | P66: =+IFERROR(VLOOKUP(CONCATENATE(A66,$C$10,C66),'ID1&5'!B:J,9,FALSE),"-") -> - | Q66: =+IFERROR(VLOOKUP(D66,'ID1&5'!K:L,2,FALSE),"-") -> - | R66: =+IFERROR(VLOOKUP(CONCATENATE(A66,$D$10,D66),'ID1&5'!B:J,9,FALSE),"-") -> - | S66: =+IFERROR(VLOOKUP(E66,'ID1&5'!K:L,2,FALSE),"-") -> - | T66: =+IFERROR(VLOOKUP(CONCATENATE(A66,$E$10,E66),'ID1&5'!B:J,9,FALSE),"-") -> - | U66: =+IFERROR(VLOOKUP(F66,'ID1&5'!K:L,2,FALSE),"-") -> - | V66: =+IFERROR(VLOOKUP(CONCATENATE(A66,$F$10,F66),'ID1&5'!B:J,9,FALSE),"-") -> - | W66: =+IFERROR(VLOOKUP(A66,'ID6&7'!A:I,9,FALSE),"-") -> - | X66: =+IFERROR(VLOOKUP(A66,'ID6&7'!A:J,10,FALSE),"-") -> - | Z66: =+IF(J66=0,"Por iniciar",IF(OR(K66="-",M66="-",P66="-",R66="-",T66="-",V66="-"),"Em testes",IF(AND(M66=0,P66=0,R66=0,T66<>K66,V66<>K66),"OK","NOK"))) -> Por iniciar
H67: INSTRUMENT | I67: dt_incptn | J67: =+COUNTIF('ID1&5'!G:G,'1. Status'!I67) -> 0 | K67: =+IFERROR(VLOOKUP(CONCATENATE(A67,$B$10,B67),'ID1&5'!B:J,8,FALSE),"-") -> - | L67: =+IFERROR(VLOOKUP(B67,'ID1&5'!K:L,2,FALSE),"-") -> - | M67: =+IFERROR(VLOOKUP(CONCATENATE(A67,$B$10,B67),'ID1&5'!B:J,9,FALSE),"-") -> - | N67: =+IFERROR(VLOOKUP(CONCATENATE(A67,$C$10,C67),'ID1&5'!B:J,8,FALSE),"-") -> - | O67: =+IFERROR(VLOOKUP(C67,'ID1&5'!K:L,2,FALSE),"-") -> - | P67: =+IFERROR(VLOOKUP(CONCATENATE(A67,$C$10,C67),'ID1&5'!B:J,9,FALSE),"-") -> - | Q67: =+IFERROR(VLOOKUP(D67,'ID1&5'!K:L,2,FALSE),"-") -> - | R67: =+IFERROR(VLOOKUP(CONCATENATE(A67,$D$10,D67),'ID1&5'!B:J,9,FALSE),"-") -> - | S67: =+IFERROR(VLOOKUP(E67,'ID1&5'!K:L,2,FALSE),"-") -> - | T67: =+IFERROR(VLOOKUP(CONCATENATE(A67,$E$10,E67),'ID1&5'!B:J,9,FALSE),"-") -> - | U67: =+IFERROR(VLOOKUP(F67,'ID1&5'!K:L,2,FALSE),"-") -> - | V67: =+IFERROR(VLOOKUP(CONCATENATE(A67,$F$10,F67),'ID1&5'!B:J,9,FALSE),"-") -> - | W67: =+IFERROR(VLOOKUP(A67,'ID6&7'!A:I,9,FALSE),"-") -> - | X67: =+IFERROR(VLOOKUP(A67,'ID6&7'!A:J,10,FALSE),"-") -> - | Z67: =+IF(J67=0,"Por iniciar",IF(OR(K67="-",M67="-",P67="-",R67="-",T67="-",V67="-"),"Em testes",IF(AND(M67=0,P67=0,R67=0,T67<>K67,V67<>K67),"OK","NOK"))) -> Por iniciar
H68: INSTRUMENT | I68: obsrvd_agnt_id | J68: =+COUNTIF('ID1&5'!G:G,'1. Status'!I68) -> 0 | K68: =+IFERROR(VLOOKUP(CONCATENATE(A68,$B$10,B68),'ID1&5'!B:J,8,FALSE),"-") -> - | L68: =+IFERROR(VLOOKUP(B68,'ID1&5'!K:L,2,FALSE),"-") -> - | M68: =+IFERROR(VLOOKUP(CONCATENATE(A68,$B$10,B68),'ID1&5'!B:J,9,FALSE),"-") -> - | N68: =+IFERROR(VLOOKUP(CONCATENATE(A68,$C$10,C68),'ID1&5'!B:J,8,FALSE),"-") -> - | O68: =+IFERROR(VLOOKUP(C68,'ID1&5'!K:L,2,FALSE),"-") -> - | P68: =+IFERROR(VLOOKUP(CONCATENATE(A68,$C$10,C68),'ID1&5'!B:J,9,FALSE),"-") -> - | Q68: =+IFERROR(VLOOKUP(D68,'ID1&5'!K:L,2,FALSE),"-") -> - | R68: =+IFERROR(VLOOKUP(CONCATENATE(A68,$D$10,D68),'ID1&5'!B:J,9,FALSE),"-") -> - | S68: =+IFERROR(VLOOKUP(E68,'ID1&5'!K:L,2,FALSE),"-") -> - | T68: =+IFERROR(VLOOKUP(CONCATENATE(A68,$E$10,E68),'ID1&5'!B:J,9,FALSE),"-") -> - | U68: =+IFERROR(VLOOKUP(F68,'ID1&5'!K:L,2,FALSE),"-") -> - | V68: =+IFERROR(VLOOKUP(CONCATENATE(A68,$F$10,F68),'ID1&5'!B:J,9,FALSE),"-") -> - | W68: =+IFERROR(VLOOKUP(A68,'ID6&7'!A:I,9,FALSE),"-") -> - | X68: =+IFERROR(VLOOKUP(A68,'ID6&7'!A:J,10,FALSE),"-") -> - | Z68: =+IF(J68=0,"Por iniciar",IF(OR(K68="-",M68="-",P68="-",R68="-",T68="-",V68="-"),"Em testes",IF(AND(M68=0,P68=0,R68=0,T68<>K68,V68<>K68),"OK","NOK"))) -> Por iniciar
H69: INSTRUMENT | I69: obsrvd_agnt_nm | J69: =+COUNTIF('ID1&5'!G:G,'1. Status'!I69) -> 0 | K69: =+IFERROR(VLOOKUP(CONCATENATE(A69,$B$10,B69),'ID1&5'!B:J,8,FALSE),"-") -> - | L69: =+IFERROR(VLOOKUP(B69,'ID1&5'!K:L,2,FALSE),"-") -> - | M69: =+IFERROR(VLOOKUP(CONCATENATE(A69,$B$10,B69),'ID1&5'!B:J,9,FALSE),"-") -> - | N69: =+IFERROR(VLOOKUP(CONCATENATE(A69,$C$10,C69),'ID1&5'!B:J,8,FALSE),"-") -> - | O69: =+IFERROR(VLOOKUP(C69,'ID1&5'!K:L,2,FALSE),"-") -> - | P69: =+IFERROR(VLOOKUP(CONCATENATE(A69,$C$10,C69),'ID1&5'!B:J,9,FALSE),"-") -> - | Q69: =+IFERROR(VLOOKUP(D69,'ID1&5'!K:L,2,FALSE),"-") -> - | R69: =+IFERROR(VLOOKUP(CONCATENATE(A69,$D$10,D69),'ID1&5'!B:J,9,FALSE),"-") -> - | S69: =+IFERROR(VLOOKUP(E69,'ID1&5'!K:L,2,FALSE),"-") -> - | T69: =+IFERROR(VLOOKUP(CONCATENATE(A69,$E$10,E69),'ID1&5'!B:J,9,FALSE),"-") -> - | U69: =+IFERROR(VLOOKUP(F69,'ID1&5'!K:L,2,FALSE),"-") -> - | V69: =+IFERROR(VLOOKUP(CONCATENATE(A69,$F$10,F69),'ID1&5'!B:J,9,FALSE),"-") -> - | W69: =+IFERROR(VLOOKUP(A69,'ID6&7'!A:I,9,FALSE),"-") -> - | X69: =+IFERROR(VLOOKUP(A69,'ID6&7'!A:J,10,FALSE),"-") -> - | Z69: =+IF(J69=0,"Por iniciar",IF(OR(K69="-",M69="-",P69="-",R69="-",T69="-",V69="-"),"Em testes",IF(AND(M69=0,P69=0,R69=0,T69<>K69,V69<>K69),"OK","NOK"))) -> Por iniciar
H70: INSTRUMENT | I70: prdct | J70: =+COUNTIF('ID1&5'!G:G,'1. Status'!I70) -> 0 | K70: =+IFERROR(VLOOKUP(CONCATENATE(A70,$B$10,B70),'ID1&5'!B:J,8,FALSE),"-") -> - | L70: =+IFERROR(VLOOKUP(B70,'ID1&5'!K:L,2,FALSE),"-") -> - | M70: =+IFERROR(VLOOKUP(CONCATENATE(A70,$B$10,B70),'ID1&5'!B:J,9,FALSE),"-") -> - | N70: =+IFERROR(VLOOKUP(CONCATENATE(A70,$C$10,C70),'ID1&5'!B:J,8,FALSE),"-") -> - | O70: =+IFERROR(VLOOKUP(C70,'ID1&5'!K:L,2,FALSE),"-") -> - | P70: =+IFERROR(VLOOKUP(CONCATENATE(A70,$C$10,C70),'ID1&5'!B:J,9,FALSE),"-") -> - | Q70: =+IFERROR(VLOOKUP(D70,'ID1&5'!K:L,2,FALSE),"-") -> - | R70: =+IFERROR(VLOOKUP(CONCATENATE(A70,$D$10,D70),'ID1&5'!B:J,9,FALSE),"-") -> - | S70: =+IFERROR(VLOOKUP(E70,'ID1&5'!K:L,2,FALSE),"-") -> - | T70: =+IFERROR(VLOOKUP(CONCATENATE(A70,$E$10,E70),'ID1&5'!B:J,9,FALSE),"-") -> - | U70: =+IFERROR(VLOOKUP(F70,'ID1&5'!K:L,2,FALSE),"-") -> - | V70: =+IFERROR(VLOOKUP(CONCATENATE(A70,$F$10,F70),'ID1&5'!B:J,9,FALSE),"-") -> - | W70: =+IFERROR(VLOOKUP(A70,'ID6&7'!A:I,9,FALSE),"-") -> - | X70: =+IFERROR(VLOOKUP(A70,'ID6&7'!A:J,10,FALSE),"-") -> - | Z70: =+IF(J70=0,"Por iniciar",IF(OR(K70="-",M70="-",P70="-",R70="-",T70="-",V70="-"),"Em testes",IF(AND(M70=0,P70=0,R70=0,T70<>K70,V70<>K70),"OK","NOK"))) -> Por iniciar
H71: INSTRUMENT | I71: brchd_cvnnts | J71: =+COUNTIF('ID1&5'!G:G,'1. Status'!I71) -> 0 | K71: =+IFERROR(VLOOKUP(CONCATENATE(A71,$B$10,B71),'ID1&5'!B:J,8,FALSE),"-") -> - | L71: =+IFERROR(VLOOKUP(B71,'ID1&5'!K:L,2,FALSE),"-") -> - | M71: =+IFERROR(VLOOKUP(CONCATENATE(A71,$B$10,B71),'ID1&5'!B:J,9,FALSE),"-") -> - | N71: =+IFERROR(VLOOKUP(CONCATENATE(A71,$C$10,C71),'ID1&5'!B:J,8,FALSE),"-") -> - | O71: =+IFERROR(VLOOKUP(C71,'ID1&5'!K:L,2,FALSE),"-") -> - | P71: =+IFERROR(VLOOKUP(CONCATENATE(A71,$C$10,C71),'ID1&5'!B:J,9,FALSE),"-") -> - | Q71: =+IFERROR(VLOOKUP(D71,'ID1&5'!K:L,2,FALSE),"-") -> - | R71: =+IFERROR(VLOOKUP(CONCATENATE(A71,$D$10,D71),'ID1&5'!B:J,9,FALSE),"-") -> - | S71: =+IFERROR(VLOOKUP(E71,'ID1&5'!K:L,2,FALSE),"-") -> - | T71: =+IFERROR(VLOOKUP(CONCATENATE(A71,$E$10,E71),'ID1&5'!B:J,9,FALSE),"-") -> - | U71: =+IFERROR(VLOOKUP(F71,'ID1&5'!K:L,2,FALSE),"-") -> - | V71: =+IFERROR(VLOOKUP(CONCATENATE(A71,$F$10,F71),'ID1&5'!B:J,9,FALSE),"-") -> - | W71: =+IFERROR(VLOOKUP(A71,'ID6&7'!A:I,9,FALSE),"-") -> - | X71: =+IFERROR(VLOOKUP(A71,'ID6&7'!A:J,10,FALSE),"-") -> - | Z71: =+IF(J71=0,"Por iniciar",IF(OR(K71="-",M71="-",P71="-",R71="-",T71="-",V71="-"),"Em testes",IF(AND(M71=0,P71=0,R71=0,T71<>K71,V71<>K71),"OK","NOK"))) -> Por iniciar
H72: INSTRUMENT | I72: chnnl_orgntn | J72: =+COUNTIF('ID1&5'!G:G,'1. Status'!I72) -> 0 | K72: =+IFERROR(VLOOKUP(CONCATENATE(A72,$B$10,B72),'ID1&5'!B:J,8,FALSE),"-") -> - | L72: =+IFERROR(VLOOKUP(B72,'ID1&5'!K:L,2,FALSE),"-") -> - | M72: =+IFERROR(VLOOKUP(CONCATENATE(A72,$B$10,B72),'ID1&5'!B:J,9,FALSE),"-") -> - | N72: =+IFERROR(VLOOKUP(CONCATENATE(A72,$C$10,C72),'ID1&5'!B:J,8,FALSE),"-") -> - | O72: =+IFERROR(VLOOKUP(C72,'ID1&5'!K:L,2,FALSE),"-") -> - | P72: =+IFERROR(VLOOKUP(CONCATENATE(A72,$C$10,C72),'ID1&5'!B:J,9,FALSE),"-") -> - | Q72: =+IFERROR(VLOOKUP(D72,'ID1&5'!K:L,2,FALSE),"-") -> - | R72: =+IFERROR(VLOOKUP(CONCATENATE(A72,$D$10,D72),'ID1&5'!B:J,9,FALSE),"-") -> - | S72: =+IFERROR(VLOOKUP(E72,'ID1&5'!K:L,2,FALSE),"-") -> - | T72: =+IFERROR(VLOOKUP(CONCATENATE(A72,$E$10,E72),'ID1&5'!B:J,9,FALSE),"-") -> - | U72: =+IFERROR(VLOOKUP(F72,'ID1&5'!K:L,2,FALSE),"-") -> - | V72: =+IFERROR(VLOOKUP(CONCATENATE(A72,$F$10,F72),'ID1&5'!B:J,9,FALSE),"-") -> - | W72: =+IFERROR(VLOOKUP(A72,'ID6&7'!A:I,9,FALSE),"-") -> - | X72: =+IFERROR(VLOOKUP(A72,'ID6&7'!A:J,10,FALSE),"-") -> - | Z72: =+IF(J72=0,"Por iniciar",IF(OR(K72="-",M72="-",P72="-",R72="-",T72="-",V72="-"),"Em testes",IF(AND(M72=0,P72=0,R72=0,T72<>K72,V72<>K72),"OK","NOK"))) -> Por iniciar
H73: INSTRUMENT | I73: csh_swp_trp | J73: =+COUNTIF('ID1&5'!G:G,'1. Status'!I73) -> 0 | K73: =+IFERROR(VLOOKUP(CONCATENATE(A73,$B$10,B73),'ID1&5'!B:J,8,FALSE),"-") -> - | L73: =+IFERROR(VLOOKUP(B73,'ID1&5'!K:L,2,FALSE),"-") -> - | M73: =+IFERROR(VLOOKUP(CONCATENATE(A73,$B$10,B73),'ID1&5'!B:J,9,FALSE),"-") -> - | N73: =+IFERROR(VLOOKUP(CONCATENATE(A73,$C$10,C73),'ID1&5'!B:J,8,FALSE),"-") -> - | O73: =+IFERROR(VLOOKUP(C73,'ID1&5'!K:L,2,FALSE),"-") -> - | P73: =+IFERROR(VLOOKUP(CONCATENATE(A73,$C$10,C73),'ID1&5'!B:J,9,FALSE),"-") -> - | Q73: =+IFERROR(VLOOKUP(D73,'ID1&5'!K:L,2,FALSE),"-") -> - | R73: =+IFERROR(VLOOKUP(CONCATENATE(A73,$D$10,D73),'ID1&5'!B:J,9,FALSE),"-") -> - | S73: =+IFERROR(VLOOKUP(E73,'ID1&5'!K:L,2,FALSE),"-") -> - | T73: =+IFERROR(VLOOKUP(CONCATENATE(A73,$E$10,E73),'ID1&5'!B:J,9,FALSE),"-") -> - | U73: =+IFERROR(VLOOKUP(F73,'ID1&5'!K:L,2,FALSE),"-") -> - | V73: =+IFERROR(VLOOKUP(CONCATENATE(A73,$F$10,F73),'ID1&5'!B:J,9,FALSE),"-") -> - | W73: =+IFERROR(VLOOKUP(A73,'ID6&7'!A:I,9,FALSE),"-") -> - | X73: =+IFERROR(VLOOKUP(A73,'ID6&7'!A:J,10,FALSE),"-") -> - | Z73: =+IF(J73=0,"Por iniciar",IF(OR(K73="-",M73="-",P73="-",R73="-",T73="-",V73="-"),"Em testes",IF(AND(M73=0,P73=0,R73=0,T73<>K73,V73<>K73),"OK","NOK"))) -> Por iniciar
H74: INSTRUMENT | I74: cvnnt_stts | J74: =+COUNTIF('ID1&5'!G:G,'1. Status'!I74) -> 0 | K74: =+IFERROR(VLOOKUP(CONCATENATE(A74,$B$10,B74),'ID1&5'!B:J,8,FALSE),"-") -> - | L74: =+IFERROR(VLOOKUP(B74,'ID1&5'!K:L,2,FALSE),"-") -> - | M74: =+IFERROR(VLOOKUP(CONCATENATE(A74,$B$10,B74),'ID1&5'!B:J,9,FALSE),"-") -> - | N74: =+IFERROR(VLOOKUP(CONCATENATE(A74,$C$10,C74),'ID1&5'!B:J,8,FALSE),"-") -> - | O74: =+IFERROR(VLOOKUP(C74,'ID1&5'!K:L,2,FALSE),"-") -> - | P74: =+IFERROR(VLOOKUP(CONCATENATE(A74,$C$10,C74),'ID1&5'!B:J,9,FALSE),"-") -> - | Q74: =+IFERROR(VLOOKUP(D74,'ID1&5'!K:L,2,FALSE),"-") -> - | R74: =+IFERROR(VLOOKUP(CONCATENATE(A74,$D$10,D74),'ID1&5'!B:J,9,FALSE),"-") -> - | S74: =+IFERROR(VLOOKUP(E74,'ID1&5'!K:L,2,FALSE),"-") -> - | T74: =+IFERROR(VLOOKUP(CONCATENATE(A74,$E$10,E74),'ID1&5'!B:J,9,FALSE),"-") -> - | U74: =+IFERROR(VLOOKUP(F74,'ID1&5'!K:L,2,FALSE),"-") -> - | V74: =+IFERROR(VLOOKUP(CONCATENATE(A74,$F$10,F74),'ID1&5'!B:J,9,FALSE),"-") -> - | W74: =+IFERROR(VLOOKUP(A74,'ID6&7'!A:I,9,FALSE),"-") -> - | X74: =+IFERROR(VLOOKUP(A74,'ID6&7'!A:J,10,FALSE),"-") -> - | Z74: =+IF(J74=0,"Por iniciar",IF(OR(K74="-",M74="-",P74="-",R74="-",T74="-",V74="-"),"Em testes",IF(AND(M74=0,P74=0,R74=0,T74<>K74,V74<>K74),"OK","NOK"))) -> Por iniciar
H75: INSTRUMENT | I75: cvnnt_typ | J75: =+COUNTIF('ID1&5'!G:G,'1. Status'!I75) -> 0 | K75: =+IFERROR(VLOOKUP(CONCATENATE(A75,$B$10,B75),'ID1&5'!B:J,8,FALSE),"-") -> - | L75: =+IFERROR(VLOOKUP(B75,'ID1&5'!K:L,2,FALSE),"-") -> - | M75: =+IFERROR(VLOOKUP(CONCATENATE(A75,$B$10,B75),'ID1&5'!B:J,9,FALSE),"-") -> - | N75: =+IFERROR(VLOOKUP(CONCATENATE(A75,$C$10,C75),'ID1&5'!B:J,8,FALSE),"-") -> - | O75: =+IFERROR(VLOOKUP(C75,'ID1&5'!K:L,2,FALSE),"-") -> - | P75: =+IFERROR(VLOOKUP(CONCATENATE(A75,$C$10,C75),'ID1&5'!B:J,9,FALSE),"-") -> - | Q75: =+IFERROR(VLOOKUP(D75,'ID1&5'!K:L,2,FALSE),"-") -> - | R75: =+IFERROR(VLOOKUP(CONCATENATE(A75,$D$10,D75),'ID1&5'!B:J,9,FALSE),"-") -> - | S75: =+IFERROR(VLOOKUP(E75,'ID1&5'!K:L,2,FALSE),"-") -> - | T75: =+IFERROR(VLOOKUP(CONCATENATE(A75,$E$10,E75),'ID1&5'!B:J,9,FALSE),"-") -> - | U75: =+IFERROR(VLOOKUP(F75,'ID1&5'!K:L,2,FALSE),"-") -> - | V75: =+IFERROR(VLOOKUP(CONCATENATE(A75,$F$10,F75),'ID1&5'!B:J,9,FALSE),"-") -> - | W75: =+IFERROR(VLOOKUP(A75,'ID6&7'!A:I,9,FALSE),"-") -> - | X75: =+IFERROR(VLOOKUP(A75,'ID6&7'!A:J,10,FALSE),"-") -> - | Z75: =+IF(J75=0,"Por iniciar",IF(OR(K75="-",M75="-",P75="-",R75="-",T75="-",V75="-"),"Em testes",IF(AND(M75=0,P75=0,R75=0,T75<>K75,V75<>K75),"OK","NOK"))) -> Por iniciar
... H682: INSTR_PROTECTION | I682: cod_soc | J682: =+COUNTIF('ID1&5'!G:G,'1. Status'!I682) -> 0 | K682: =+IFERROR(VLOOKUP(CONCATENATE(A682,$B$10,B682),'ID1&5'!B:J,8,FALSE),"-") -> - | L682: =+IFERROR(VLOOKUP(B682,'ID1&5'!K:L,2,FALSE),"-") -> - | M682: =+IFERROR(VLOOKUP(CONCATENATE(A682,$B$10,B682),'ID1&5'!B:J,9,FALSE),"-") -> - | N682: =+IFERROR(VLOOKUP(CONCATENATE(A682,$C$10,C682),'ID1&5'!B:J,8,FALSE),"-") -> - | O682: =+IFERROR(VLOOKUP(C682,'ID1&5'!K:L,2,FALSE),"-") -> - | P682: =+IFERROR(VLOOKUP(CONCATENATE(A682,$C$10,C682),'ID1&5'!B:J,9,FALSE),"-") -> - | Q682: =+IFERROR(VLOOKUP(D682,'ID1&5'!K:L,2,FALSE),"-") -> - | R682: =+IFERROR(VLOOKUP(CONCATENATE(A682,$D$10,D682),'ID1&5'!B:J,9,FALSE),"-") -> - | S682: =+IFERROR(VLOOKUP(E682,'ID1&5'!K:L,2,FALSE),"-") -> - | T682: =+IFERROR(VLOOKUP(CONCATENATE(A682,$E$10,E682),'ID1&5'!B:J,9,FALSE),"-") -> - | U682: =+IFERROR(VLOOKUP(F682,'ID1&5'!K:L,2,FALSE),"-") -> - | V682: =+IFERROR(VLOOKUP(CONCATENATE(A682,$F$10,F682),'ID1&5'!B:J,9,FALSE),"-") -> - | W682: =+IFERROR(VLOOKUP(A682,'ID6&7'!A:I,9,FALSE),"-") -> - | X682: =+IFERROR(VLOOKUP(A682,'ID6&7'!A:J,10,FALSE),"-") -> - | Z682: =+IF(J682=0,"Por iniciar",IF(OR(K682="-",M682="-",P682="-",R682="-",T682="-",V682="-"),"Em testes",IF(AND(M682=0,P682=0,R682=0,T682<>K682,V682<>K682),"OK","NOK"))) -> Por iniciar
J683: =+COUNTIF('ID1&5'!G:G,'1. Status'!I683) -> 0 | K683: =+IFERROR(VLOOKUP(CONCATENATE(A683,$B$10,B683),'ID1&5'!B:J,8,FALSE),"-") -> - | L683: =+IFERROR(VLOOKUP(B683,'ID1&5'!K:L,2,FALSE),"-") -> - | M683: =+IFERROR(VLOOKUP(CONCATENATE(A683,$B$10,B683),'ID1&5'!B:J,9,FALSE),"-") -> - | N683: =+IFERROR(VLOOKUP(CONCATENATE(A683,$C$10,C683),'ID1&5'!B:J,8,FALSE),"-") -> - | O683: =+IFERROR(VLOOKUP(C683,'ID1&5'!K:L,2,FALSE),"-") -> - | P683: =+IFERROR(VLOOKUP(CONCATENATE(A683,$C$10,C683),'ID1&5'!B:J,9,FALSE),"-") -> - | Q683: =+IFERROR(VLOOKUP(D683,'ID1&5'!K:L,2,FALSE),"-") -> - | R683: =+IFERROR(VLOOKUP(CONCATENATE(A683,$D$10,D683),'ID1&5'!B:J,9,FALSE),"-") -> - | S683: =+IFERROR(VLOOKUP(E683,'ID1&5'!K:L,2,FALSE),"-") -> - | T683: =+IFERROR(VLOOKUP(CONCATENATE(A683,$E$10,E683),'ID1&5'!B:J,9,FALSE),"-") -> - | U683: =+IFERROR(VLOOKUP(F683,'ID1&5'!K:L,2,FALSE),"-") -> - | V683: =+IFERROR(VLOOKUP(CONCATENATE(A683,$F$10,F683),'ID1&5'!B:J,9,FALSE),"-") -> - | W683: =+IFERROR(VLOOKUP(A683,'ID6&7'!A:I,9,FALSE),"-") -> - | X683: =+IFERROR(VLOOKUP(A683,'ID6&7'!A:J,10,FALSE),"-") -> - | Z683: =+IF(J683=0,"Por iniciar",IF(OR(K683="-",M683="-",P683="-",R683="-",T683="-",V683="-"),"Em testes",IF(AND(M683=0,P683=0,R683=0,T683<>K683,V683<>K683),"OK","NOK"))) -> Por iniciar
J684: =+COUNTIF('ID1&5'!G:G,'1. Status'!I684) -> 0 | K684: =+IFERROR(VLOOKUP(CONCATENATE(A684,$B$10,B684),'ID1&5'!B:J,8,FALSE),"-") -> - | L684: =+IFERROR(VLOOKUP(B684,'ID1&5'!K:L,2,FALSE),"-") -> - | M684: =+IFERROR(VLOOKUP(CONCATENATE(A684,$B$10,B684),'ID1&5'!B:J,9,FALSE),"-") -> - | N684: =+IFERROR(VLOOKUP(CONCATENATE(A684,$C$10,C684),'ID1&5'!B:J,8,FALSE),"-") -> - | O684: =+IFERROR(VLOOKUP(C684,'ID1&5'!K:L,2,FALSE),"-") -> - | P684: =+IFERROR(VLOOKUP(CONCATENATE(A684,$C$10,C684),'ID1&5'!B:J,9,FALSE),"-") -> - | Q684: =+IFERROR(VLOOKUP(D684,'ID1&5'!K:L,2,FALSE),"-") -> - | R684: =+IFERROR(VLOOKUP(CONCATENATE(A684,$D$10,D684),'ID1&5'!B:J,9,FALSE),"-") -> - | S684: =+IFERROR(VLOOKUP(E684,'ID1&5'!K:L,2,FALSE),"-") -> - | T684: =+IFERROR(VLOOKUP(CONCATENATE(A684,$E$10,E684),'ID1&5'!B:J,9,FALSE),"-") -> - | U684: =+IFERROR(VLOOKUP(F684,'ID1&5'!K:L,2,FALSE),"-") -> - | V684: =+IFERROR(VLOOKUP(CONCATENATE(A684,$F$10,F684),'ID1&5'!B:J,9,FALSE),"-") -> - | W684: =+IFERROR(VLOOKUP(A684,'ID6&7'!A:I,9,FALSE),"-") -> - | X684: =+IFERROR(VLOOKUP(A684,'ID6&7'!A:J,10,FALSE),"-") -> - | Z684: =+IF(J684=0,"Por iniciar",IF(OR(K684="-",M684="-",P684="-",R684="-",T684="-",V684="-"),"Em testes",IF(AND(M684=0,P684=0,R684=0,T684<>K684,V684<>K684),"OK","NOK"))) -> Por iniciar
J685: =+COUNTIF('ID1&5'!G:G,'1. Status'!I685) -> 0 | K685: =+IFERROR(VLOOKUP(CONCATENATE(A685,$B$10,B685),'ID1&5'!B:J,8,FALSE),"-") -> - | L685: =+IFERROR(VLOOKUP(B685,'ID1&5'!K:L,2,FALSE),"-") -> - | M685: =+IFERROR(VLOOKUP(CONCATENATE(A685,$B$10,B685),'ID1&5'!B:J,9,FALSE),"-") -> - | N685: =+IFERROR(VLOOKUP(CONCATENATE(A685,$C$10,C685),'ID1&5'!B:J,8,FALSE),"-") -> - | O685: =+IFERROR(VLOOKUP(C685,'ID1&5'!K:L,2,FALSE),"-") -> - | P685: =+IFERROR(VLOOKUP(CONCATENATE(A685,$C$10,C685),'ID1&5'!B:J,9,FALSE),"-") -> - | Q685: =+IFERROR(VLOOKUP(D685,'ID1&5'!K:L,2,FALSE),"-") -> - | R685: =+IFERROR(VLOOKUP(CONCATENATE(A685,$D$10,D685),'ID1&5'!B:J,9,FALSE),"-") -> - | S685: =+IFERROR(VLOOKUP(E685,'ID1&5'!K:L,2,FALSE),"-") -> - | T685: =+IFERROR(VLOOKUP(CONCATENATE(A685,$E$10,E685),'ID1&5'!B:J,9,FALSE),"-") -> - | U685: =+IFERROR(VLOOKUP(F685,'ID1&5'!K:L,2,FALSE),"-") -> - | V685: =+IFERROR(VLOOKUP(CONCATENATE(A685,$F$10,F685),'ID1&5'!B:J,9,FALSE),"-") -> - | W685: =+IFERROR(VLOOKUP(A685,'ID6&7'!A:I,9,FALSE),"-") -> - | X685: =+IFERROR(VLOOKUP(A685,'ID6&7'!A:J,10,FALSE),"-") -> - | Z685: =+IF(J685=0,"Por iniciar",IF(OR(K685="-",M685="-",P685="-",R685="-",T685="-",V685="-"),"Em testes",IF(AND(M685=0,P685=0,R685=0,T685<>K685,V685<>K685),"OK","NOK"))) -> Por iniciar
J686: =+COUNTIF('ID1&5'!G:G,'1. Status'!I686) -> 0 | K686: =+IFERROR(VLOOKUP(CONCATENATE(A686,$B$10,B686),'ID1&5'!B:J,8,FALSE),"-") -> - | L686: =+IFERROR(VLOOKUP(B686,'ID1&5'!K:L,2,FALSE),"-") -> - | M686: =+IFERROR(VLOOKUP(CONCATENATE(A686,$B$10,B686),'ID1&5'!B:J,9,FALSE),"-") -> - | N686: =+IFERROR(VLOOKUP(CONCATENATE(A686,$C$10,C686),'ID1&5'!B:J,8,FALSE),"-") -> - | O686: =+IFERROR(VLOOKUP(C686,'ID1&5'!K:L,2,FALSE),"-") -> - | P686: =+IFERROR(VLOOKUP(CONCATENATE(A686,$C$10,C686),'ID1&5'!B:J,9,FALSE),"-") -> - | Q686: =+IFERROR(VLOOKUP(D686,'ID1&5'!K:L,2,FALSE),"-") -> - | R686: =+IFERROR(VLOOKUP(CONCATENATE(A686,$D$10,D686),'ID1&5'!B:J,9,FALSE),"-") -> - | S686: =+IFERROR(VLOOKUP(E686,'ID1&5'!K:L,2,FALSE),"-") -> - | T686: =+IFERROR(VLOOKUP(CONCATENATE(A686,$E$10,E686),'ID1&5'!B:J,9,FALSE),"-") -> - | U686: =+IFERROR(VLOOKUP(F686,'ID1&5'!K:L,2,FALSE),"-") -> - | V686: =+IFERROR(VLOOKUP(CONCATENATE(A686,$F$10,F686),'ID1&5'!B:J,9,FALSE),"-") -> - | W686: =+IFERROR(VLOOKUP(A686,'ID6&7'!A:I,9,FALSE),"-") -> - | X686: =+IFERROR(VLOOKUP(A686,'ID6&7'!A:J,10,FALSE),"-") -> - | Z686: =+IF(J686=0,"Por iniciar",IF(OR(K686="-",M686="-",P686="-",R686="-",T686="-",V686="-"),"Em testes",IF(AND(M686=0,P686=0,R686=0,T686<>K686,V686<>K686),"OK","NOK"))) -> Por iniciar
J687: =+COUNTIF('ID1&5'!G:G,'1. Status'!I687) -> 0 | K687: =+IFERROR(VLOOKUP(CONCATENATE(A687,$B$10,B687),'ID1&5'!B:J,8,FALSE),"-") -> - | L687: =+IFERROR(VLOOKUP(B687,'ID1&5'!K:L,2,FALSE),"-") -> - | M687: =+IFERROR(VLOOKUP(CONCATENATE(A687,$B$10,B687),'ID1&5'!B:J,9,FALSE),"-") -> - | N687: =+IFERROR(VLOOKUP(CONCATENATE(A687,$C$10,C687),'ID1&5'!B:J,8,FALSE),"-") -> - | O687: =+IFERROR(VLOOKUP(C687,'ID1&5'!K:L,2,FALSE),"-") -> - | P687: =+IFERROR(VLOOKUP(CONCATENATE(A687,$C$10,C687),'ID1&5'!B:J,9,FALSE),"-") -> - | Q687: =+IFERROR(VLOOKUP(D687,'ID1&5'!K:L,2,FALSE),"-") -> - | R687: =+IFERROR(VLOOKUP(CONCATENATE(A687,$D$10,D687),'ID1&5'!B:J,9,FALSE),"-") -> - | S687: =+IFERROR(VLOOKUP(E687,'ID1&5'!K:L,2,FALSE),"-") -> - | T687: =+IFERROR(VLOOKUP(CONCATENATE(A687,$E$10,E687),'ID1&5'!B:J,9,FALSE),"-") -> - | U687: =+IFERROR(VLOOKUP(F687,'ID1&5'!K:L,2,FALSE),"-") -> - | V687: =+IFERROR(VLOOKUP(CONCATENATE(A687,$F$10,F687),'ID1&5'!B:J,9,FALSE),"-") -> - | W687: =+IFERROR(VLOOKUP(A687,'ID6&7'!A:I,9,FALSE),"-") -> - | X687: =+IFERROR(VLOOKUP(A687,'ID6&7'!A:J,10,FALSE),"-") -> - | Z687: =+IF(J687=0,"Por iniciar",IF(OR(K687="-",M687="-",P687="-",R687="-",T687="-",V687="-"),"Em testes",IF(AND(M687=0,P687=0,R687=0,T687<>K687,V687<>K687),"OK","NOK"))) -> Por iniciar

Sheet 2. Script 
B6: 2. Script de Controlos
B8: TABELA | C8: TIPOLOGIA_TESTE | D8: TABELA_LT_PILAR3 | E8: TABELA_SIMUL | F8: CAMPO | G8: FORMATO CAMPO | H8: VALORES CODE LIST | I8: UNIVERSO_PILAR3 | J8: UNIVERSO_SIMUL | K8: CRUZAMENTO | L8: QUERY 1 | M8: UNION ALL
A9: =+B9&F9 -> UNIV_OPERcempresa | B9: UNIV_OPER | C9: Coerência | D9: =+UPPER('0. Instruções'!$D$35&"."&VLOOKUP(B9,'0. Instruções'!$C$27:$D$32,2,FALSE)) -> BU_LOANTAPE_WORK.LT001_UNIV_OPER | E9: =+UPPER('0. Instruções'!$D$36&"."&VLOOKUP(B9,'0. Instruções'!$C$27:$E$32,3,FALSE)) -> BU_LOANTAPE_WORK.SIMUL_LT001 | F9: cempresa | I9: ="(SELECT "&VLOOKUP(B9,'0. Instruções'!$C$27:$G$32,4,FALSE)&", "&F9&" FROM "&D9&" WHERE "&'0. Instruções'!$D$42&")X" -> (SELECT a, cempresa FROM BU_LOANTAPE_WORK.LT001_UNIV_OPER WHERE ref_date='${ref_date}' AND nome_perimetro='Individual Local' AND segmento='ESTR' AND ambito='SRB_MBDT' AND entidade='00100')X | J9: ="(SELECT "&VLOOKUP(B9,'0. Instruções'!$C$27:$G$32,4,FALSE)&" AS "&VLOOKUP(B9,'0. Instruções'!$C$27:$G$32,4,FALSE)&"_SIMUL, "&F9&" AS "&F9&"_SIMUL FROM "&E9&" WHERE "&'0. Instruções'!$D$43&")Y" -> (SELECT a AS a_SIMUL, cempresa AS cempresa_SIMUL FROM BU_LOANTAPE_WORK.SIMUL_LT001 WHERE ref_date='${ref_date}' AND nome_perimetro='Individual Local' AND segmento='ESTR' AND ambito='PILAR3' AND entidade='00100')Y | K9: =+UPPER("ON X."&VLOOKUP(B9,'0. Instruções'!$C$27:$G$32,4,FALSE)&"=Y."&VLOOKUP(B9,'0. Instruções'!$C$27:$G$32,4,FALSE)&"_SIMUL") -> ON X.A=Y.A_SIMUL | L9: =+IF(C9="Coerência", +IF(LEFT(G9,5)="FLOAT","SELECT '"&UPPER(B9)&"' AS TABELA, '"&UPPER(C9)&"' AS TIPOLOGIA_TESTE,'"&D9&"' AS TABELA_LT,'"&E9&"' AS TABELA_SIMUL,'"&F9&"' AS CAMPO, "&"'${ref_date}' AS REF_DATE, COUNT(*) AS NUM_REG, SUM(IF((ABS(COALESCE(CAST(X."&F9&" AS DECIMAL(18,6)),0)-COALESCE(CAST(Y."&F9&"_SIMUL AS DECIMAL(18,6)),0))>0.000001) OR (X."&F9&" IS NULL AND Y."&F9&"_SIMUL IS NOT NULL ) OR (X."&F9&" IS NOT NULL AND Y."&F9&"_SIMUL IS NULL),1,0)) AS NUM_REG_DIF,'"&MAX('ID1&5'!K:K)+1&"' AS ID_EXEC, CURRENT_TIMESTAMP() AS TIME_EXEC FROM "&I9&" INNER JOIN "&J9&" "&K9,"SELECT '"&UPPER(B9)&"' AS TABELA, '"&UPPER(C9)&"' AS TIPOLOGIA_TESTE,'"&D9&"' AS TABELA_LT,'"&E9&"' AS TABELA_SIMUL,'"&F9&"' AS CAMPO, "&"'${ref_date}' AS REF_DATE, COUNT(*) AS NUM_REG, SUM(IF(COALESCE(CAST(X."&F9&" AS STRING),'')<>COALESCE(CAST(Y."&F9&"_SIMUL AS STRING),'') OR (X."&F9&" IS NULL AND Y."&F9&"_SIMUL IS NOT NULL ) OR (X."&F9&" IS NOT NULL AND Y."&F9&"_SIMUL IS NULL),1,0)) AS NUM_REG_DIF,'"&MAX('ID1&5'!L:L)+1&"' AS ID_EXEC, CURRENT_TIMESTAMP() AS TIME_EXEC FROM "&I9&" INNER JOIN "&J9&" "&K9), IF(C9="Validade",+IF(G9="Code List","SELECT '"&UPPER(B9)&"' AS TABELA, '"&UPPER(C9)&"' AS TIPOLOGIA_TESTE,'"&D9&"' AS TABELA_LT,'N/A' AS TABELA_SIMUL,'"&F9&"' AS CAMPO, "&"'${ref_date}' AS REF_DATE, COUNT(*) AS NUM_REG, SUM(IF(TRIM(CAST(X."&F9&" AS STRING))='' OR TRIM(CAST(X."&F9&" AS STRING)) IS NULL OR CAST(X."&F9&" AS STRING) NOT "&H9&",1,0)) AS NUM_REG_DIF,'"&MAX('ID1&5'!K:K)+1&"' AS ID_EXEC, CURRENT_TIMESTAMP() AS TIME_EXEC FROM "&I9,"SELECT '"&UPPER(B9)&"' AS TABELA, '"&UPPER(C9)&"' AS TIPOLOGIA_TESTE,'"&D9&"' AS TABELA_LT,'N/A' AS TABELA_SIMUL,'"&F9&"' AS CAMPO, "&"'${ref_date}' AS REF_DATE, COUNT(*) AS NUM_REG, SUM(IF(TRIM(CAST(X."&F9&" AS STRING))='' OR TRIM(CAST(X."&F9&" AS STRING)) IS NULL,1,0)) AS NUM_REG_DIF,'"&MAX('ID1&5'!K:K)+1&"' AS ID_EXEC, CURRENT_TIMESTAMP() AS TIME_EXEC FROM "&I9), IF(C9="Caracteres Especiais",+"SELECT '"&UPPER(B9)&"' AS TABELA, '"&UPPER(C9)&"' AS TIPOLOGIA_TESTE,'"&D9&"' AS TABELA_LT,'N/A' AS TABELA_SIMUL,'"&F9&"' AS CAMPO, "&"'${ref_date}' AS REF_DATE, COUNT(*) AS NUM_REG, SUM(IF(REGEXP_REPLACE(TRIM(CAST(X."&F9&" AS STRING)),'[^a-zA-Z0-9_\\s]','') <>TRIM(CAST(X."&F9&" AS STRING)),1,0)) AS NUM_REG_DIF,'"&MAX('ID1&5'!K:K)+1&"' AS ID_EXEC, CURRENT_TIMESTAMP() AS TIME_EXEC FROM "&I9, IF(C9="Missings",+"SELECT '"&UPPER(B9)&"' AS TABELA, '"&UPPER(C9)&"' AS TIPOLOGIA_TESTE,'"&D9&"' AS TABELA_LT,'N/A' AS TABELA_SIMUL,'"&F9&"' AS CAMPO, "&"'${ref_date}' AS REF_DATE, COUNT(*) AS NUM_REG, SUM(IF(TRIM(CAST(X."&F9&" AS STRING)) IN ('0000-00-00','0001-01-01','9999-12-31','MISS','00000','99999999999','99999999999.00','99999999999.000000'),1,0)) AS NUM_REG_DIF,'"&MAX('ID1&5'!K:K)+1&"' AS ID_EXEC, CURRENT_TIMESTAMP() AS TIME_EXEC FROM "&I9, IF(C9="Not applicable",+"SELECT '"&UPPER(B9)&"' AS TABELA, '"&UPPER(C9)&"' AS TIPOLOGIA_TESTE,'"&D9&"' AS TABELA_LT,'N/A' AS TABELA_SIMUL,'"&F9&"' AS CAMPO, "&"'${ref_date}' AS REF_DATE, COUNT(*) AS NUM_REG, SUM(IF(TRIM(CAST(X."&F9&" AS STRING)) IN ('N/A','11111111111','11111111111.00','11111111111.000000','1111-11-11'),1,0)) AS NUM_REG_DIF,'"&MAX('ID1&5'!K:K)+1&"' AS ID_EXEC, CURRENT_TIMESTAMP() AS TIME_EXEC FROM "&I9, IF(C9="Valores extremos",+"SELECT '"&UPPER(B9)&"' AS TABELA, '"&UPPER(C9)&"' AS TIPOLOGIA_TESTE,'"&D9&"' AS TABELA_LT,'N/A' AS TABELA_SIMUL,'"&F9&"' AS CAMPO, "&"'${ref_date}' AS REF_DATE, CAST(MIN("&F9&") AS STRING) AS VALOR_MIN, CAST(MAX("&F9&") AS STRING) AS VALOR_MAX,'"&MAX('ID1&5'!K:K)+1&"' AS ID_EXEC, CURRENT_TIMESTAMP() AS TIME_EXEC FROM "&MID(I9,1,LEN(I9)-2)&" AND CAST("&F9&" AS STRING) NOT IN ('0000-00-00','0001-01-01','9999-12-31','MISS','00000','99999999999','99999999999.00','99999999999.000000','N/A','11111111111','11111111111.00','11111111111.000000','1111-11-11'))X")))))) -> SELECT 'UNIV_OPER' AS TABELA, 'COERÊNCIA' AS TIPOLOGIA_TESTE,'BU_LOANTAPE_WORK.LT001_UNIV_OPER' AS TABELA_LT,'BU_LOANTAPE_WORK.SIMUL_LT001' AS TABELA_SIMUL,'cempresa' AS CAMPO, '${ref_date}' AS REF_DATE, COUNT(*) AS NUM_REG, SUM(IF(COALESCE(CAST(X.cempresa AS STRING),'')<>COALESCE(CAST(Y.cempresa_SIMUL AS STRING),'') OR (X.cempresa IS NULL AND Y.cempresa_SIMUL IS NOT NULL ) OR (X.cempresa IS NOT NULL AND Y.cempresa_SIMUL IS NULL),1,0)) AS NUM_REG_DIF,'1' AS ID_EXEC, CURRENT_TIMESTAMP() AS TIME_EXEC FROM (SELECT a, cempresa FROM BU_LOANTAPE_WORK.LT001_UNIV_OPER WHERE ref_date='${ref_date}' AND nome_perimetro='Individual Local' AND segmento='ESTR' AND ambito='SRB_MBDT' AND entidade='00100')X INNER JOIN (SELECT a AS a_SIMUL, cempresa AS cempresa_SIMUL FROM BU_LOANTAPE_WORK.SIMUL_LT001 WHERE ref_date='${ref_date}' AND nome_perimetro='Individual Local' AND segmento='ESTR' AND ambito='PILAR3' AND entidade='00100')Y ON X.A=Y.A_SIMUL | M9: =+"UNION ALL "&L9 -> UNION ALL SELECT 'UNIV_OPER' AS TABELA, 'COERÊNCIA' AS TIPOLOGIA_TESTE,'BU_LOANTAPE_WORK.LT001_UNIV_OPER' AS TABELA_LT,'BU_LOANTAPE_WORK.SIMUL_LT001' AS TABELA_SIMUL,'cempresa' AS CAMPO, '${ref_date}' AS REF_DATE, COUNT(*) AS NUM_REG, SUM(IF(COALESCE(CAST(X.cempresa AS STRING),'')<>COALESCE(CAST(Y.cempresa_SIMUL AS STRING),'') OR (X.cempresa IS NULL AND Y.cempresa_SIMUL IS NOT NULL ) OR (X.cempresa IS NOT NULL AND Y.cempresa_SIMUL IS NULL),1,0)) AS NUM_REG_DIF,'1' AS ID_EXEC, CURRENT_TIMESTAMP() AS TIME_EXEC FROM (SELECT a, cempresa FROM BU_LOANTAPE_WORK.LT001_UNIV_OPER WHERE ref_date='${ref_date}' AND nome_perimetro='Individual Local' AND segmento='ESTR' AND ambito='SRB_MBDT' AND entidade='00100')X INNER JOIN (SELECT a AS a_SIMUL, cempresa AS cempresa_SIMUL FROM BU_LOANTAPE_WORK.SIMUL_LT001 WHERE ref_date='${ref_date}' AND nome_perimetro='Individual Local' AND segmento='ESTR' AND ambito='PILAR3' AND entidade='00100')Y ON X.A=Y.A_SIMUL
A10: =+B10&F10 -> UNIV_OPERcbalcao | B10: UNIV_OPER | C10: Coerência | D10: =+UPPER('0. Instruções'!$D$35&"."&VLOOKUP(B10,'0. Instruções'!$C$27:$D$32,2,FALSE)) -> BU_LOANTAPE_WORK.LT001_UNIV_OPER | E10: =+UPPER('0. Instruções'!$D$36&"."&VLOOKUP(B10,'0. Instruções'!$C$27:$E$32,3,FALSE)) -> BU_LOANTAPE_WORK.SIMUL_LT001 | F10: cbalcao | I10: ="(SELECT "&VLOOKUP(B10,'0. Instruções'!$C$27:$G$32,4,FALSE)&", "&F10&" FROM "&D10&" WHERE "&'0. Instruções'!$D$42&")X" -> (SELECT a, cbalcao FROM BU_LOANTAPE_WORK.LT001_UNIV_OPER WHERE ref_date='${ref_date}' AND nome_perimetro='Individual Local' AND segmento='ESTR' AND ambito='SRB_MBDT' AND entidade='00100')X | J10: ="(SELECT "&VLOOKUP(B10,'0. Instruções'!$C$27:$G$32,4,FALSE)&" AS "&VLOOKUP(B10,'0. Instruções'!$C$27:$G$32,4,FALSE)&"_SIMUL, "&F10&" AS "&F10&"_SIMUL FROM "&E10&" WHERE "&'0. Instruções'!$D$43&")Y" -> (SELECT a AS a_SIMUL, cbalcao AS cbalcao_SIMUL FROM BU_LOANTAPE_WORK.SIMUL_LT001 WHERE ref_date='${ref_date}' AND nome_perimetro='Individual Local' AND segmento='ESTR' AND ambito='PILAR3' AND entidade='00100')Y | K10: =+UPPER("ON X."&VLOOKUP(B10,'0. Instruções'!$C$27:$G$32,4,FALSE)&"=Y."&VLOOKUP(B10,'0. Instruções'!$C$27:$G$32,4,FALSE)&"_SIMUL") -> ON X.A=Y.A_SIMUL | L10: =+IF(C10="Coerência", +IF(LEFT(G10,5)="FLOAT","SELECT '"&UPPER(B10)&"' AS TABELA, '"&UPPER(C10)&"' AS TIPOLOGIA_TESTE,'"&D10&"' AS TABELA_LT,'"&E10&"' AS TABELA_SIMUL,'"&F10&"' AS CAMPO, "&"'${ref_date}' AS REF_DATE, COUNT(*) AS NUM_REG, SUM(IF((ABS(COALESCE(CAST(X."&F10&" AS DECIMAL(18,6)),0)-COALESCE(CAST(Y."&F10&"_SIMUL AS DECIMAL(18,6)),0))>0.000001) OR (X."&F10&" IS NULL AND Y."&F10&"_SIMUL IS NOT NULL ) OR (X."&F10&" IS NOT NULL AND Y."&F10&"_SIMUL IS NULL),1,0)) AS NUM_REG_DIF,'"&MAX('ID1&5'!K:K)+1&"' AS ID_EXEC, CURRENT_TIMESTAMP() AS TIME_EXEC FROM "&I10&" INNER JOIN "&J10&" "&K10,"SELECT '"&UPPER(B10)&"' AS TABELA, '"&UPPER(C10)&"' AS TIPOLOGIA_TESTE,'"&D10&"' AS TABELA_LT,'"&E10&"' AS TABELA_SIMUL,'"&F10&"' AS CAMPO, "&"'${ref_date}' AS REF_DATE, COUNT(*) AS NUM_REG, SUM(IF(COALESCE(CAST(X."&F10&" AS STRING),'')<>COALESCE(CAST(Y."&F10&"_SIMUL AS STRING),'') OR (X."&F10&" IS NULL AND Y."&F10&"_SIMUL IS NOT NULL ) OR (X."&F10&" IS NOT NULL AND Y."&F10&"_SIMUL IS NULL),1,0)) AS NUM_REG_DIF,'"&MAX('ID1&5'!L:L)+1&"' AS ID_EXEC, CURRENT_TIMESTAMP() AS TIME_EXEC FROM "&I10&" INNER JOIN "&J10&" "&K10), IF(C10="Validade",+IF(G10="Code List","SELECT '"&UPPER(B10)&"' AS TABELA, '"&UPPER(C10)&"' AS TIPOLOGIA_TESTE,'"&D10&"' AS TABELA_LT,'N/A' AS TABELA_SIMUL,'"&F10&"' AS CAMPO, "&"'${ref_date}' AS REF_DATE, COUNT(*) AS NUM_REG, SUM(IF(TRIM(CAST(X."&F10&" AS STRING))='' OR TRIM(CAST(X."&F10&" AS STRING)) IS NULL OR CAST(X."&F10&" AS STRING) NOT "&H10&",1,0)) AS NUM_REG_DIF,'"&MAX('ID1&5'!K:K)+1&"' AS ID_EXEC, CURRENT_TIMESTAMP() AS TIME_EXEC FROM "&I10,"SELECT '"&UPPER(B10)&"' AS TABELA, '"&UPPER(C10)&"' AS TIPOLOGIA_TESTE,'"&D10&"' AS TABELA_LT,'N/A' AS TABELA_SIMUL,'"&F10&"' AS CAMPO, "&"'${ref_date}' AS REF_DATE, COUNT(*) AS NUM_REG, SUM(IF(TRIM(CAST(X."&F10&" AS STRING))='' OR TRIM(CAST(X."&F10&" AS STRING)) IS NULL,1,0)) AS NUM_REG_DIF,'"&MAX('ID1&5'!K:K)+1&"' AS ID_EXEC, CURRENT_TIMESTAMP() AS TIME_EXEC FROM "&I10), IF(C10="Caracteres Especiais",+"SELECT '"&UPPER(B10)&"' AS TABELA, '"&UPPER(C10)&"' AS TIPOLOGIA_TESTE,'"&D10&"' AS TABELA_LT,'N/A' AS TABELA_SIMUL,'"&F10&"' AS CAMPO, "&"'${ref_date}' AS REF_DATE, COUNT(*) AS NUM_REG, SUM(IF(REGEXP_REPLACE(TRIM(CAST(X."&F10&" AS STRING)),'[^a-zA-Z0-9_\\s]','') <>TRIM(CAST(X."&F10&" AS STRING)),1,0)) AS NUM_REG_DIF,'"&MAX('ID1&5'!K:K)+1&"' AS ID_EXEC, CURRENT_TIMESTAMP() AS TIME_EXEC FROM "&I10, IF(C10="Missings",+"SELECT '"&UPPER(B10)&"' AS TABELA, '"&UPPER(C10)&"' AS TIPOLOGIA_TESTE,'"&D10&"' AS TABELA_LT,'N/A' AS TABELA_SIMUL,'"&F10&"' AS CAMPO, "&"'${ref_date}' AS REF_DATE, COUNT(*) AS NUM_REG, SUM(IF(TRIM(CAST(X."&F10&" AS STRING)) IN ('0000-00-00','0001-01-01','9999-12-31','MISS','00000','99999999999','99999999999.00','99999999999.000000'),1,0)) AS NUM_REG_DIF,'"&MAX('ID1&5'!K:K)+1&"' AS ID_EXEC, CURRENT_TIMESTAMP() AS TIME_EXEC FROM "&I10, IF(C10="Not applicable",+"SELECT '"&UPPER(B10)&"' AS TABELA, '"&UPPER(C10)&"' AS TIPOLOGIA_TESTE,'"&D10&"' AS TABELA_LT,'N/A' AS TABELA_SIMUL,'"&F10&"' AS CAMPO, "&"'${ref_date}' AS REF_DATE, COUNT(*) AS NUM_REG, SUM(IF(TRIM(CAST(X."&F10&" AS STRING)) IN ('N/A','11111111111','11111111111.00','11111111111.000000','1111-11-11'),1,0)) AS NUM_REG_DIF,'"&MAX('ID1&5'!K:K)+1&"' AS ID_EXEC, CURRENT_TIMESTAMP() AS TIME_EXEC FROM "&I10, IF(C10="Valores extremos",+"SELECT '"&UPPER(B10)&"' AS TABELA, '"&UPPER(C10)&"' AS TIPOLOGIA_TESTE,'"&D10&"' AS TABELA_LT,'N/A' AS TABELA_SIMUL,'"&F10&"' AS CAMPO, "&"'${ref_date}' AS REF_DATE, CAST(MIN("&F10&") AS STRING) AS VALOR_MIN, CAST(MAX("&F10&") AS STRING) AS VALOR_MAX,'"&MAX('ID1&5'!K:K)+1&"' AS ID_EXEC, CURRENT_TIMESTAMP() AS TIME_EXEC FROM "&MID(I10,1,LEN(I10)-2)&" AND CAST("&F10&" AS STRING) NOT IN ('0000-00-00','0001-01-01','9999-12-31','MISS','00000','99999999999','99999999999.00','99999999999.000000','N/A','11111111111','11111111111.00','11111111111.000000','1111-11-11'))X")))))) -> SELECT 'UNIV_OPER' AS TABELA, 'COERÊNCIA' AS TIPOLOGIA_TESTE,'BU_LOANTAPE_WORK.LT001_UNIV_OPER' AS TABELA_LT,'BU_LOANTAPE_WORK.SIMUL_LT001' AS TABELA_SIMUL,'cbalcao' AS CAMPO, '${ref_date}' AS REF_DATE, COUNT(*) AS NUM_REG, SUM(IF(COALESCE(CAST(X.cbalcao AS STRING),'')<>COALESCE(CAST(Y.cbalcao_SIMUL AS STRING),'') OR (X.cbalcao IS NULL AND Y.cbalcao_SIMUL IS NOT NULL ) OR (X.cbalcao IS NOT NULL AND Y.cbalcao_SIMUL IS NULL),1,0)) AS NUM_REG_DIF,'1' AS ID_EXEC, CURRENT_TIMESTAMP() AS TIME_EXEC FROM (SELECT a, cbalcao FROM BU_LOANTAPE_WORK.LT001_UNIV_OPER WHERE ref_date='${ref_date}' AND nome_perimetro='Individual Local' AND segmento='ESTR' AND ambito='SRB_MBDT' AND entidade='00100')X INNER JOIN (SELECT a AS a_SIMUL, cbalcao AS cbalcao_SIMUL FROM BU_LOANTAPE_WORK.SIMUL_LT001 WHERE ref_date='${ref_date}' AND nome_perimetro='Individual Local' AND segmento='ESTR' AND ambito='PILAR3' AND entidade='00100')Y ON X.A=Y.A_SIMUL | M10: =+"UNION ALL "&L10 -> UNION ALL SELECT 'UNIV_OPER' AS TABELA, 'COERÊNCIA' AS TIPOLOGIA_TESTE,'BU_LOANTAPE_WORK.LT001_UNIV_OPER' AS TABELA_LT,'BU_LOANTAPE_WORK.SIMUL_LT001' AS TABELA_SIMUL,'cbalcao' AS CAMPO, '${ref_date}' AS REF_DATE, COUNT(*) AS NUM_REG, SUM(IF(COALESCE(CAST(X.cbalcao AS STRING),'')<>COALESCE(CAST(Y.cbalcao_SIMUL AS STRING),'') OR (X.cbalcao IS NULL AND Y.cbalcao_SIMUL IS NOT NULL ) OR (X.cbalcao IS NOT NULL AND Y.cbalcao_SIMUL IS NULL),1,0)) AS NUM_REG_DIF,'1' AS ID_EXEC, CURRENT_TIMESTAMP() AS TIME_EXEC FROM (SELECT a, cbalcao FROM BU_LOANTAPE_WORK.LT001_UNIV_OPER WHERE ref_date='${ref_date}' AND nome_perimetro='Individual Local' AND segmento='ESTR' AND ambito='SRB_MBDT' AND entidade='00100')X INNER JOIN (SELECT a AS a_SIMUL, cbalcao AS cbalcao_SIMUL FROM BU_LOANTAPE_WORK.SIMUL_LT001 WHERE ref_date='${ref_date}' AND nome_perimetro='Individual Local' AND segmento='ESTR' AND ambito='PILAR3' AND entidade='00100')Y ON X.A=Y.A_SIMUL
A11: =+B11&F11 -> UNIV_OPERcnumecta | B11: UNIV_OPER | C11: Coerência | D11: =+UPPER('0. Instruções'!$D$35&"."&VLOOKUP(B11,'0. Instruções'!$C$27:$D$32,2,FALSE)) -> BU_LOANTAPE_WORK.LT001_UNIV_OPER | E11: =+UPPER('0. Instruções'!$D$36&"."&VLOOKUP(B11,'0. Instruções'!$C$27:$E$32,3,FALSE)) -> BU_LOANTAPE_WORK.SIMUL_LT001 | F11: cnumecta | I11: ="(SELECT "&VLOOKUP(B11,'0. Instruções'!$C$27:$G$32,4,FALSE)&", "&F11&" FROM "&D11&" WHERE "&'0. Instruções'!$D$42&")X" -> (SELECT a, cnumecta FROM BU_LOANTAPE_WORK.LT001_UNIV_OPER WHERE ref_date='${ref_date}' AND nome_perimetro='Individual Local' AND segmento='ESTR' AND ambito='SRB_MBDT' AND entidade='00100')X | J11: ="(SELECT "&VLOOKUP(B11,'0. Instruções'!$C$27:$G$32,4,FALSE)&" AS "&VLOOKUP(B11,'0. Instruções'!$C$27:$G$32,4,FALSE)&"_SIMUL, "&F11&" AS "&F11&"_SIMUL FROM "&E11&" WHERE "&'0. Instruções'!$D$43&")Y" -> (SELECT a AS a_SIMUL, cnumecta AS cnumecta_SIMUL FROM BU_LOANTAPE_WORK.SIMUL_LT001 WHERE ref_date='${ref_date}' AND nome_perimetro='Individual Local' AND segmento='ESTR' AND ambito='PILAR3' AND entidade='00100')Y | K11: =+UPPER("ON X."&VLOOKUP(B11,'0. Instruções'!$C$27:$G$32,4,FALSE)&"=Y."&VLOOKUP(B11,'0. Instruções'!$C$27:$G$32,4,FALSE)&"_SIMUL") -> ON X.A=Y.A_SIMUL | L11: =+IF(C11="Coerência", +IF(LEFT(G11,5)="FLOAT","SELECT '"&UPPER(B11)&"' AS TABELA, '"&UPPER(C11)&"' AS TIPOLOGIA_TESTE,'"&D11&"' AS TABELA_LT,'"&E11&"' AS TABELA_SIMUL,'"&F11&"' AS CAMPO, "&"'${ref_date}' AS REF_DATE, COUNT(*) AS NUM_REG, SUM(IF((ABS(COALESCE(CAST(X."&F11&" AS DECIMAL(18,6)),0)-COALESCE(CAST(Y."&F11&"_SIMUL AS DECIMAL(18,6)),0))>0.000001) OR (X."&F11&" IS NULL AND Y."&F11&"_SIMUL IS NOT NULL ) OR (X."&F11&" IS NOT NULL AND Y."&F11&"_SIMUL IS NULL),1,0)) AS NUM_REG_DIF,'"&MAX('ID1&5'!K:K)+1&"' AS ID_EXEC, CURRENT_TIMESTAMP() AS TIME_EXEC FROM "&I11&" INNER JOIN "&J11&" "&K11,"SELECT '"&UPPER(B11)&"' AS TABELA, '"&UPPER(C11)&"' AS TIPOLOGIA_TESTE,'"&D11&"' AS TABELA_LT,'"&E11&"' AS TABELA_SIMUL,'"&F11&"' AS CAMPO, "&"'${ref_date}' AS REF_DATE, COUNT(*) AS NUM_REG, SUM(IF(COALESCE(CAST(X."&F11&" AS STRING),'')<>COALESCE(CAST(Y."&F11&"_SIMUL AS STRING),'') OR (X."&F11&" IS NULL AND Y."&F11&"_SIMUL IS NOT NULL ) OR (X."&F11&" IS NOT NULL AND Y."&F11&"_SIMUL IS NULL),1,0)) AS NUM_REG_DIF,'"&MAX('ID1&5'!L:L)+1&"' AS ID_EXEC, CURRENT_TIMESTAMP() AS TIME_EXEC FROM "&I11&" INNER JOIN "&J11&" "&K11), IF(C11="Validade",+IF(G11="Code List","SELECT '"&UPPER(B11)&"' AS TABELA, '"&UPPER(C11)&"' AS TIPOLOGIA_TESTE,'"&D11&"' AS TABELA_LT,'N/A' AS TABELA_SIMUL,'"&F11&"' AS CAMPO, "&"'${ref_date}' AS REF_DATE, COUNT(*) AS NUM_REG, SUM(IF(TRIM(CAST(X."&F11&" AS STRING))='' OR TRIM(CAST(X."&F11&" AS STRING)) IS NULL OR CAST(X."&F11&" AS STRING) NOT "&H11&",1,0)) AS NUM_REG_DIF,'"&MAX('ID1&5'!K:K)+1&"' AS ID_EXEC, CURRENT_TIMESTAMP() AS TIME_EXEC FROM "&I11,"SELECT '"&UPPER(B11)&"' AS TABELA, '"&UPPER(C11)&"' AS TIPOLOGIA_TESTE,'"&D11&"' AS TABELA_LT,'N/A' AS TABELA_SIMUL,'"&F11&"' AS CAMPO, "&"'${ref_date}' AS REF_DATE, COUNT(*) AS NUM_REG, SUM(IF(TRIM(CAST(X."&F11&" AS STRING))='' OR TRIM(CAST(X."&F11&" AS STRING)) IS NULL,1,0)) AS NUM_REG_DIF,'"&MAX('ID1&5'!K:K)+1&"' AS ID_EXEC, CURRENT_TIMESTAMP() AS TIME_EXEC FROM "&I11), IF(C11="Caracteres Especiais",+"SELECT '"&UPPER(B11)&"' AS TABELA, '"&UPPER(C11)&"' AS TIPOLOGIA_TESTE,'"&D11&"' AS TABELA_LT,'N/A' AS TABELA_SIMUL,'"&F11&"' AS CAMPO, "&"'${ref_date}' AS REF_DATE, COUNT(*) AS NUM_REG, SUM(IF(REGEXP_REPLACE(TRIM(CAST(X."&F11&" AS STRING)),'[^a-zA-Z0-9_\\s]','') <>TRIM(CAST(X."&F11&" AS STRING)),1,0)) AS NUM_REG_DIF,'"&MAX('ID1&5'!K:K)+1&"' AS ID_EXEC, CURRENT_TIMESTAMP() AS TIME_EXEC FROM "&I11, IF(C11="Missings",+"SELECT '"&UPPER(B11)&"' AS TABELA, '"&UPPER(C11)&"' AS TIPOLOGIA_TESTE,'"&D11&"' AS TABELA_LT,'N/A' AS TABELA_SIMUL,'"&F11&"' AS CAMPO, "&"'${ref_date}' AS REF_DATE, COUNT(*) AS NUM_REG, SUM(IF(TRIM(CAST(X."&F11&" AS STRING)) IN ('0000-00-00','0001-01-01','9999-12-31','MISS','00000','99999999999','99999999999.00','99999999999.000000'),1,0)) AS NUM_REG_DIF,'"&MAX('ID1&5'!K:K)+1&"' AS ID_EXEC, CURRENT_TIMESTAMP() AS TIME_EXEC FROM "&I11, IF(C11="Not applicable",+"SELECT '"&UPPER(B11)&"' AS TABELA, '"&UPPER(C11)&"' AS TIPOLOGIA_TESTE,'"&D11&"' AS TABELA_LT,'N/A' AS TABELA_SIMUL,'"&F11&"' AS CAMPO, "&"'${ref_date}' AS REF_DATE, COUNT(*) AS NUM_REG, SUM(IF(TRIM(CAST(X."&F11&" AS STRING)) IN ('N/A','11111111111','11111111111.00','11111111111.000000','1111-11-11'),1,0)) AS NUM_REG_DIF,'"&MAX('ID1&5'!K:K)+1&"' AS ID_EXEC, CURRENT_TIMESTAMP() AS TIME_EXEC FROM "&I11, IF(C11="Valores extremos",+"SELECT '"&UPPER(B11)&"' AS TABELA, '"&UPPER(C11)&"' AS TIPOLOGIA_TESTE,'"&D11&"' AS TABELA_LT,'N/A' AS TABELA_SIMUL,'"&F11&"' AS CAMPO, "&"'${ref_date}' AS REF_DATE, CAST(MIN("&F11&") AS STRING) AS VALOR_MIN, CAST(MAX("&F11&") AS STRING) AS VALOR_MAX,'"&MAX('ID1&5'!K:K)+1&"' AS ID_EXEC, CURRENT_TIMESTAMP() AS TIME_EXEC FROM "&MID(I11,1,LEN(I11)-2)&" AND CAST("&F11&" AS STRING) NOT IN ('0000-00-00','0001-01-01','9999-12-31','MISS','00000','99999999999','99999999999.00','99999999999.000000','N/A','11111111111','11111111111.00','11111111111.000000','1111-11-11'))X")))))) -> SELECT 'UNIV_OPER' AS TABELA, 'COERÊNCIA' AS TIPOLOGIA_TESTE,'BU_LOANTAPE_WORK.LT001_UNIV_OPER' AS TABELA_LT,'BU_LOANTAPE_WORK.SIMUL_LT001' AS TABELA_SIMUL,'cnumecta' AS CAMPO, '${ref_date}' AS REF_DATE, COUNT(*) AS NUM_REG, SUM(IF(COALESCE(CAST(X.cnumecta AS STRING),'')<>COALESCE(CAST(Y.cnumecta_SIMUL AS STRING),'') OR (X.cnumecta IS NULL AND Y.cnumecta_SIMUL IS NOT NULL ) OR (X.cnumecta IS NOT NULL AND Y.cnumecta_SIMUL IS NULL),1,0)) AS NUM_REG_DIF,'1' AS ID_EXEC, CURRENT_TIMESTAMP() AS TIME_EXEC FROM (SELECT a, cnumecta FROM BU_LOANTAPE_WORK.LT001_UNIV_OPER WHERE ref_date='${ref_date}' AND nome_perimetro='Individual Local' AND segmento='ESTR' AND ambito='SRB_MBDT' AND entidade='00100')X INNER JOIN (SELECT a AS a_SIMUL, cnumecta AS cnumecta_SIMUL FROM BU_LOANTAPE_WORK.SIMUL_LT001 WHERE ref_date='${ref_date}' AND nome_perimetro='Individual Local' AND segmento='ESTR' AND ambito='PILAR3' AND entidade='00100')Y ON X.A=Y.A_SIMUL | M11: =+"UNION ALL "&L11 -> UNION ALL SELECT 'UNIV_OPER' AS TABELA, 'COERÊNCIA' AS TIPOLOGIA_TESTE,'BU_LOANTAPE_WORK.LT001_UNIV_OPER' AS TABELA_LT,'BU_LOANTAPE_WORK.SIMUL_LT001' AS TABELA_SIMUL,'cnumecta' AS CAMPO, '${ref_date}' AS REF_DATE, COUNT(*) AS NUM_REG, SUM(IF(COALESCE(CAST(X.cnumecta AS STRING),'')<>COALESCE(CAST(Y.cnumecta_SIMUL AS STRING),'') OR (X.cnumecta IS NULL AND Y.cnumecta_SIMUL IS NOT NULL ) OR (X.cnumecta IS NOT NULL AND Y.cnumecta_SIMUL IS NULL),1,0)) AS NUM_REG_DIF,'1' AS ID_EXEC, CURRENT_TIMESTAMP() AS TIME_EXEC FROM (SELECT a, cnumecta FROM BU_LOANTAPE_WORK.LT001_UNIV_OPER WHERE ref_date='${ref_date}' AND nome_perimetro='Individual Local' AND segmento='ESTR' AND ambito='SRB_MBDT' AND entidade='00100')X INNER JOIN (SELECT a AS a_SIMUL, cnumecta AS cnumecta_SIMUL FROM BU_LOANTAPE_WORK.SIMUL_LT001 WHERE ref_date='${ref_date}' AND nome_perimetro='Individual Local' AND segmento='ESTR' AND ambito='PILAR3' AND entidade='00100')Y ON X.A=Y.A_SIMUL
A12: =+B12&F12 -> UNIV_OPERzdeposit | B12: UNIV_OPER | C12: Coerência | D12: =+UPPER('0. Instruções'!$D$35&"."&VLOOKUP(B12,'0. Instruções'!$C$27:$D$32,2,FALSE)) -> BU_LOANTAPE_WORK.LT001_UNIV_OPER | E12: =+UPPER('0. Instruções'!$D$36&"."&VLOOKUP(B12,'0. Instruções'!$C$27:$E$32,3,FALSE)) -> BU_LOANTAPE_WORK.SIMUL_LT001 | F12: zdeposit | I12: ="(SELECT "&VLOOKUP(B12,'0. Instruções'!$C$27:$G$32,4,FALSE)&", "&F12&" FROM "&D12&" WHERE "&'0. Instruções'!$D$42&")X" -> (SELECT a, zdeposit FROM BU_LOANTAPE_WORK.LT001_UNIV_OPER WHERE ref_date='${ref_date}' AND nome_perimetro='Individual Local' AND segmento='ESTR' AND ambito='SRB_MBDT' AND entidade='00100')X | J12: ="(SELECT "&VLOOKUP(B12,'0. Instruções'!$C$27:$G$32,4,FALSE)&" AS "&VLOOKUP(B12,'0. Instruções'!$C$27:$G$32,4,FALSE)&"_SIMUL, "&F12&" AS "&F12&"_SIMUL FROM "&E12&" WHERE "&'0. Instruções'!$D$43&")Y" -> (SELECT a AS a_SIMUL, zdeposit AS zdeposit_SIMUL FROM BU_LOANTAPE_WORK.SIMUL_LT001 WHERE ref_date='${ref_date}' AND nome_perimetro='Individual Local' AND segmento='ESTR' AND ambito='PILAR3' AND entidade='00100')Y | K12: =+UPPER("ON X."&VLOOKUP(B12,'0. Instruções'!$C$27:$G$32,4,FALSE)&"=Y."&VLOOKUP(B12,'0. Instruções'!$C$27:$G$32,4,FALSE)&"_SIMUL") -> ON X.A=Y.A_SIMUL | L12: =+IF(C12="Coerência", +IF(LEFT(G12,5)="FLOAT","SELECT '"&UPPER(B12)&"' AS TABELA, '"&UPPER(C12)&"' AS TIPOLOGIA_TESTE,'"&D12&"' AS TABELA_LT,'"&E12&"' AS TABELA_SIMUL,'"&F12&"' AS CAMPO, "&"'${ref_date}' AS REF_DATE, COUNT(*) AS NUM_REG, SUM(IF((ABS(COALESCE(CAST(X."&F12&" AS DECIMAL(18,6)),0)-COALESCE(CAST(Y."&F12&"_SIMUL AS DECIMAL(18,6)),0))>0.000001) OR (X."&F12&" IS NULL AND Y."&F12&"_SIMUL IS NOT NULL ) OR (X."&F12&" IS NOT NULL AND Y."&F12&"_SIMUL IS NULL),1,0)) AS NUM_REG_DIF,'"&MAX('ID1&5'!K:K)+1&"' AS ID_EXEC, CURRENT_TIMESTAMP() AS TIME_EXEC FROM "&I12&" INNER JOIN "&J12&" "&K12,"SELECT '"&UPPER(B12)&"' AS TABELA, '"&UPPER(C12)&"' AS TIPOLOGIA_TESTE,'"&D12&"' AS TABELA_LT,'"&E12&"' AS TABELA_SIMUL,'"&F12&"' AS CAMPO, "&"'${ref_date}' AS REF_DATE, COUNT(*) AS NUM_REG, SUM(IF(COALESCE(CAST(X."&F12&" AS STRING),'')<>COALESCE(CAST(Y."&F12&"_SIMUL AS STRING),'') OR (X."&F12&" IS NULL AND Y."&F12&"_SIMUL IS NOT NULL ) OR (X."&F12&" IS NOT NULL AND Y."&F12&"_SIMUL IS NULL),1,0)) AS NUM_REG_DIF,'"&MAX('ID1&5'!L:L)+1&"' AS ID_EXEC, CURRENT_TIMESTAMP() AS TIME_EXEC FROM "&I12&" INNER JOIN "&J12&" "&K12), IF(C12="Validade",+IF(G12="Code List","SELECT '"&UPPER(B12)&"' AS TABELA, '"&UPPER(C12)&"' AS TIPOLOGIA_TESTE,'"&D12&"' AS TABELA_LT,'N/A' AS TABELA_SIMUL,'"&F12&"' AS CAMPO, "&"'${ref_date}' AS REF_DATE, COUNT(*) AS NUM_REG, SUM(IF(TRIM(CAST(X."&F12&" AS STRING))='' OR TRIM(CAST(X."&F12&" AS STRING)) IS NULL OR CAST(X."&F12&" AS STRING) NOT "&H12&",1,0)) AS NUM_REG_DIF,'"&MAX('ID1&5'!K:K)+1&"' AS ID_EXEC, CURRENT_TIMESTAMP() AS TIME_EXEC FROM "&I12,"SELECT '"&UPPER(B12)&"' AS TABELA, '"&UPPER(C12)&"' AS TIPOLOGIA_TESTE,'"&D12&"' AS TABELA_LT,'N/A' AS TABELA_SIMUL,'"&F12&"' AS CAMPO, "&"'${ref_date}' AS REF_DATE, COUNT(*) AS NUM_REG, SUM(IF(TRIM(CAST(X."&F12&" AS STRING))='' OR TRIM(CAST(X."&F12&" AS STRING)) IS NULL,1,0)) AS NUM_REG_DIF,'"&MAX('ID1&5'!K:K)+1&"' AS ID_EXEC, CURRENT_TIMESTAMP() AS TIME_EXEC FROM "&I12), IF(C12="Caracteres Especiais",+"SELECT '"&UPPER(B12)&"' AS TABELA, '"&UPPER(C12)&"' AS TIPOLOGIA_TESTE,'"&D12&"' AS TABELA_LT,'N/A' AS TABELA_SIMUL,'"&F12&"' AS CAMPO, "&"'${ref_date}' AS REF_DATE, COUNT(*) AS NUM_REG, SUM(IF(REGEXP_REPLACE(TRIM(CAST(X."&F12&" AS STRING)),'[^a-zA-Z0-9_\\s]','') <>TRIM(CAST(X."&F12&" AS STRING)),1,0)) AS NUM_REG_DIF,'"&MAX('ID1&5'!K:K)+1&"' AS ID_EXEC, CURRENT_TIMESTAMP() AS TIME_EXEC FROM "&I12, IF(C12="Missings",+"SELECT '"&UPPER(B12)&"' AS TABELA, '"&UPPER(C12)&"' AS TIPOLOGIA_TESTE,'"&D12&"' AS TABELA_LT,'N/A' AS TABELA_SIMUL,'"&F12&"' AS CAMPO, "&"'${ref_date}' AS REF_DATE, COUNT(*) AS NUM_REG, SUM(IF(TRIM(CAST(X."&F12&" AS STRING)) IN ('0000-00-00','0001-01-01','9999-12-31','MISS','00000','99999999999','99999999999.00','99999999999.000000'),1,0)) AS NUM_REG_DIF,'"&MAX('ID1&5'!K:K)+1&"' AS ID_EXEC, CURRENT_TIMESTAMP() AS TIME_EXEC FROM "&I12, IF(C12="Not applicable",+"SELECT '"&UPPER(B12)&"' AS TABELA, '"&UPPER(C12)&"' AS TIPOLOGIA_TESTE,'"&D12&"' AS TABELA_LT,'N/A' AS TABELA_SIMUL,'"&F12&"' AS CAMPO, "&"'${ref_date}' AS REF_DATE, COUNT(*) AS NUM_REG, SUM(IF(TRIM(CAST(X."&F12&" AS STRING)) IN ('N/A','11111111111','11111111111.00','11111111111.000000','1111-11-11'),1,0)) AS NUM_REG_DIF,'"&MAX('ID1&5'!K:K)+1&"' AS ID_EXEC, CURRENT_TIMESTAMP() AS TIME_EXEC FROM "&I12, IF(C12="Valores extremos",+"SELECT '"&UPPER(B12)&"' AS TABELA, '"&UPPER(C12)&"' AS TIPOLOGIA_TESTE,'"&D12&"' AS TABELA_LT,'N/A' AS TABELA_SIMUL,'"&F12&"' AS CAMPO, "&"'${ref_date}' AS REF_DATE, CAST(MIN("&F12&") AS STRING) AS VALOR_MIN, CAST(MAX("&F12&") AS STRING) AS VALOR_MAX,'"&MAX('ID1&5'!K:K)+1&"' AS ID_EXEC, CURRENT_TIMESTAMP() AS TIME_EXEC FROM "&MID(I12,1,LEN(I12)-2)&" AND CAST("&F12&" AS STRING) NOT IN ('0000-00-00','0001-01-01','9999-12-31','MISS','00000','99999999999','99999999999.00','99999999999.000000','N/A','11111111111','11111111111.00','11111111111.000000','1111-11-11'))X")))))) -> SELECT 'UNIV_OPER' AS TABELA, 'COERÊNCIA' AS TIPOLOGIA_TESTE,'BU_LOANTAPE_WORK.LT001_UNIV_OPER' AS TABELA_LT,'BU_LOANTAPE_WORK.SIMUL_LT001' AS TABELA_SIMUL,'zdeposit' AS CAMPO, '${ref_date}' AS REF_DATE, COUNT(*) AS NUM_REG, SUM(IF(COALESCE(CAST(X.zdeposit AS STRING),'')<>COALESCE(CAST(Y.zdeposit_SIMUL AS STRING),'') OR (X.zdeposit IS NULL AND Y.zdeposit_SIMUL IS NOT NULL ) OR (X.zdeposit IS NOT NULL AND Y.zdeposit_SIMUL IS NULL),1,0)) AS NUM_REG_DIF,'1' AS ID_EXEC, CURRENT_TIMESTAMP() AS TIME_EXEC FROM (SELECT a, zdeposit FROM BU_LOANTAPE_WORK.LT001_UNIV_OPER WHERE ref_date='${ref_date}' AND nome_perimetro='Individual Local' AND segmento='ESTR' AND ambito='SRB_MBDT' AND entidade='00100')X INNER JOIN (SELECT a AS a_SIMUL, zdeposit AS zdeposit_SIMUL FROM BU_LOANTAPE_WORK.SIMUL_LT001 WHERE ref_date='${ref_date}' AND nome_perimetro='Individual Local' AND segmento='ESTR' AND ambito='PILAR3' AND entidade='00100')Y ON X.A=Y.A_SIMUL | M12: =+"UNION ALL "&L12 -> UNION ALL SELECT 'UNIV_OPER' AS TABELA, 'COERÊNCIA' AS TIPOLOGIA_TESTE,'BU_LOANTAPE_WORK.LT001_UNIV_OPER' AS TABELA_LT,'BU_LOANTAPE_WORK.SIMUL_LT001' AS TABELA_SIMUL,'zdeposit' AS CAMPO, '${ref_date}' AS REF_DATE, COUNT(*) AS NUM_REG, SUM(IF(COALESCE(CAST(X.zdeposit AS STRING),'')<>COALESCE(CAST(Y.zdeposit_SIMUL AS STRING),'') OR (X.zdeposit IS NULL AND Y.zdeposit_SIMUL IS NOT NULL ) OR (X.zdeposit IS NOT NULL AND Y.zdeposit_SIMUL IS NULL),1,0)) AS NUM_REG_DIF,'1' AS ID_EXEC, CURRENT_TIMESTAMP() AS TIME_EXEC FROM (SELECT a, zdeposit FROM BU_LOANTAPE_WORK.LT001_UNIV_OPER WHERE ref_date='${ref_date}' AND nome_perimetro='Individual Local' AND segmento='ESTR' AND ambito='SRB_MBDT' AND entidade='00100')X INNER JOIN (SELECT a AS a_SIMUL, zdeposit AS zdeposit_SIMUL FROM BU_LOANTAPE_WORK.SIMUL_LT001 WHERE ref_date='${ref_date}' AND nome_perimetro='Individual Local' AND segmento='ESTR' AND ambito='PILAR3' AND entidade='00100')Y ON X.A=Y.A_SIMUL
A13: =+B13&F13 -> UNIV_OPERzcliente | B13: UNIV_OPER | C13: Coerência | D13: =+UPPER('0. Instruções'!$D$35&"."&VLOOKUP(B13,'0. Instruções'!$C$27:$D$32,2,FALSE)) -> BU_LOANTAPE_WORK.LT001_UNIV_OPER | E13: =+UPPER('0. Instruções'!$D$36&"."&VLOOKUP(B13,'0. Instruções'!$C$27:$E$32,3,FALSE)) -> BU_LOANTAPE_WORK.SIMUL_LT001 | F13: zcliente | I13: ="(SELECT "&VLOOKUP(B13,'0. Instruções'!$C$27:$G$32,4,FALSE)&", "&F13&" FROM "&D13&" WHERE "&'0. Instruções'!$D$42&")X" -> (SELECT a, zcliente FROM BU_LOANTAPE_WORK.LT001_UNIV_OPER WHERE ref_date='${ref_date}' AND nome_perimetro='Individual Local' AND segmento='ESTR' AND ambito='SRB_MBDT' AND entidade='00100')X | J13: ="(SELECT "&VLOOKUP(B13,'0. Instruções'!$C$27:$G$32,4,FALSE)&" AS "&VLOOKUP(B13,'0. Instruções'!$C$27:$G$32,4,FALSE)&"_SIMUL, "&F13&" AS "&F13&"_SIMUL FROM "&E13&" WHERE "&'0. Instruções'!$D$43&")Y" -> (SELECT a AS a_SIMUL, zcliente AS zcliente_SIMUL FROM BU_LOANTAPE_WORK.SIMUL_LT001 WHERE ref_date='${ref_date}' AND nome_perimetro='Individual Local' AND segmento='ESTR' AND ambito='PILAR3' AND entidade='00100')Y | K13: =+UPPER("ON X."&VLOOKUP(B13,'0. Instruções'!$C$27:$G$32,4,FALSE)&"=Y."&VLOOKUP(B13,'0. Instruções'!$C$27:$G$32,4,FALSE)&"_SIMUL") -> ON X.A=Y.A_SIMUL | L13: =+IF(C13="Coerência", +IF(LEFT(G13,5)="FLOAT","SELECT '"&UPPER(B13)&"' AS TABELA, '"&UPPER(C13)&"' AS TIPOLOGIA_TESTE,'"&D13&"' AS TABELA_LT,'"&E13&"' AS TABELA_SIMUL,'"&F13&"' AS CAMPO, "&"'${ref_date}' AS REF_DATE, COUNT(*) AS NUM_REG, SUM(IF((ABS(COALESCE(CAST(X."&F13&" AS DECIMAL(18,6)),0)-COALESCE(CAST(Y."&F13&"_SIMUL AS DECIMAL(18,6)),0))>0.000001) OR (X."&F13&" IS NULL AND Y."&F13&"_SIMUL IS NOT NULL ) OR (X."&F13&" IS NOT NULL AND Y."&F13&"_SIMUL IS NULL),1,0)) AS NUM_REG_DIF,'"&MAX('ID1&5'!K:K)+1&"' AS ID_EXEC, CURRENT_TIMESTAMP() AS TIME_EXEC FROM "&I13&" INNER JOIN "&J13&" "&K13,"SELECT '"&UPPER(B13)&"' AS TABELA, '"&UPPER(C13)&"' AS TIPOLOGIA_TESTE,'"&D13&"' AS TABELA_LT,'"&E13&"' AS TABELA_SIMUL,'"&F13&"' AS CAMPO, "&"'${ref_date}' AS REF_DATE, COUNT(*) AS NUM_REG, SUM(IF(COALESCE(CAST(X."&F13&" AS STRING),'')<>COALESCE(CAST(Y."&F13&"_SIMUL AS STRING),'') OR (X."&F13&" IS NULL AND Y."&F13&"_SIMUL IS NOT NULL ) OR (X."&F13&" IS NOT NULL AND Y."&F13&"_SIMUL IS NULL),1,0)) AS NUM_REG_DIF,'"&MAX('ID1&5'!L:L)+1&"' AS ID_EXEC, CURRENT_TIMESTAMP() AS TIME_EXEC FROM "&I13&" INNER JOIN "&J13&" "&K13), IF(C13="Validade",+IF(G13="Code List","SELECT '"&UPPER(B13)&"' AS TABELA, '"&UPPER(C13)&"' AS TIPOLOGIA_TESTE,'"&D13&"' AS TABELA_LT,'N/A' AS TABELA_SIMUL,'"&F13&"' AS CAMPO, "&"'${ref_date}' AS REF_DATE, COUNT(*) AS NUM_REG, SUM(IF(TRIM(CAST(X."&F13&" AS STRING))='' OR TRIM(CAST(X."&F13&" AS STRING)) IS NULL OR CAST(X."&F13&" AS STRING) NOT "&H13&",1,0)) AS NUM_REG_DIF,'"&MAX('ID1&5'!K:K)+1&"' AS ID_EXEC, CURRENT_TIMESTAMP() AS TIME_EXEC FROM "&I13,"SELECT '"&UPPER(B13)&"' AS TABELA, '"&UPPER(C13)&"' AS TIPOLOGIA_TESTE,'"&D13&"' AS TABELA_LT,'N/A' AS TABELA_SIMUL,'"&F13&"' AS CAMPO, "&"'${ref_date}' AS REF_DATE, COUNT(*) AS NUM_REG, SUM(IF(TRIM(CAST(X."&F13&" AS STRING))='' OR TRIM(CAST(X."&F13&" AS STRING)) IS NULL,1,0)) AS NUM_REG_DIF,'"&MAX('ID1&5'!K:K)+1&"' AS ID_EXEC, CURRENT_TIMESTAMP() AS TIME_EXEC FROM "&I13), IF(C13="Caracteres Especiais",+"SELECT '"&UPPER(B13)&"' AS TABELA, '"&UPPER(C13)&"' AS TIPOLOGIA_TESTE,'"&D13&"' AS TABELA_LT,'N/A' AS TABELA_SIMUL,'"&F13&"' AS CAMPO, "&"'${ref_date}' AS REF_DATE, COUNT(*) AS NUM_REG, SUM(IF(REGEXP_REPLACE(TRIM(CAST(X."&F13&" AS STRING)),'[^a-zA-Z0-9_\\s]','') <>TRIM(CAST(X."&F13&" AS STRING)),1,0)) AS NUM_REG_DIF,'"&MAX('ID1&5'!K:K)+1&"' AS ID_EXEC, CURRENT_TIMESTAMP() AS TIME_EXEC FROM "&I13, IF(C13="Missings",+"SELECT '"&UPPER(B13)&"' AS TABELA, '"&UPPER(C13)&"' AS TIPOLOGIA_TESTE,'"&D13&"' AS TABELA_LT,'N/A' AS TABELA_SIMUL,'"&F13&"' AS CAMPO, "&"'${ref_date}' AS REF_DATE, COUNT(*) AS NUM_REG, SUM(IF(TRIM(CAST(X."&F13&" AS STRING)) IN ('0000-00-00','0001-01-01','9999-12-31','MISS','00000','99999999999','99999999999.00','99999999999.000000'),1,0)) AS NUM_REG_DIF,'"&MAX('ID1&5'!K:K)+1&"' AS ID_EXEC, CURRENT_TIMESTAMP() AS TIME_EXEC FROM "&I13, IF(C13="Not applicable",+"SELECT '"&UPPER(B13)&"' AS TABELA, '"&UPPER(C13)&"' AS TIPOLOGIA_TESTE,'"&D13&"' AS TABELA_LT,'N/A' AS TABELA_SIMUL,'"&F13&"' AS CAMPO, "&"'${ref_date}' AS REF_DATE, COUNT(*) AS NUM_REG, SUM(IF(TRIM(CAST(X."&F13&" AS STRING)) IN ('N/A','11111111111','11111111111.00','11111111111.000000','1111-11-11'),1,0)) AS NUM_REG_DIF,'"&MAX('ID1&5'!K:K)+1&"' AS ID_EXEC, CURRENT_TIMESTAMP() AS TIME_EXEC FROM "&I13, IF(C13="Valores extremos",+"SELECT '"&UPPER(B13)&"' AS TABELA, '"&UPPER(C13)&"' AS TIPOLOGIA_TESTE,'"&D13&"' AS TABELA_LT,'N/A' AS TABELA_SIMUL,'"&F13&"' AS CAMPO, "&"'${ref_date}' AS REF_DATE, CAST(MIN("&F13&") AS STRING) AS VALOR_MIN, CAST(MAX("&F13&") AS STRING) AS VALOR_MAX,'"&MAX('ID1&5'!K:K)+1&"' AS ID_EXEC, CURRENT_TIMESTAMP() AS TIME_EXEC FROM "&MID(I13,1,LEN(I13)-2)&" AND CAST("&F13&" AS STRING) NOT IN ('0000-00-00','0001-01-01','9999-12-31','MISS','00000','99999999999','99999999999.00','99999999999.000000','N/A','11111111111','11111111111.00','11111111111.000000','1111-11-11'))X")))))) -> SELECT 'UNIV_OPER' AS TABELA, 'COERÊNCIA' AS TIPOLOGIA_TESTE,'BU_LOANTAPE_WORK.LT001_UNIV_OPER' AS TABELA_LT,'BU_LOANTAPE_WORK.SIMUL_LT001' AS TABELA_SIMUL,'zcliente' AS CAMPO, '${ref_date}' AS REF_DATE, COUNT(*) AS NUM_REG, SUM(IF(COALESCE(CAST(X.zcliente AS STRING),'')<>COALESCE(CAST(Y.zcliente_SIMUL AS STRING),'') OR (X.zcliente IS NULL AND Y.zcliente_SIMUL IS NOT NULL ) OR (X.zcliente IS NOT NULL AND Y.zcliente_SIMUL IS NULL),1,0)) AS NUM_REG_DIF,'1' AS ID_EXEC, CURRENT_TIMESTAMP() AS TIME_EXEC FROM (SELECT a, zcliente FROM BU_LOANTAPE_WORK.LT001_UNIV_OPER WHERE ref_date='${ref_date}' AND nome_perimetro='Individual Local' AND segmento='ESTR' AND ambito='SRB_MBDT' AND entidade='00100')X INNER JOIN (SELECT a AS a_SIMUL, zcliente AS zcliente_SIMUL FROM BU_LOANTAPE_WORK.SIMUL_LT001 WHERE ref_date='${ref_date}' AND nome_perimetro='Individual Local' AND segmento='ESTR' AND ambito='PILAR3' AND entidade='00100')Y ON X.A=Y.A_SIMUL | M13: =+"UNION ALL "&L13 -> UNION ALL SELECT 'UNIV_OPER' AS TABELA, 'COERÊNCIA' AS TIPOLOGIA_TESTE,'BU_LOANTAPE_WORK.LT001_UNIV_OPER' AS TABELA_LT,'BU_LOANTAPE_WORK.SIMUL_LT001' AS TABELA_SIMUL,'zcliente' AS CAMPO, '${ref_date}' AS REF_DATE, COUNT(*) AS NUM_REG, SUM(IF(COALESCE(CAST(X.zcliente AS STRING),'')<>COALESCE(CAST(Y.zcliente_SIMUL AS STRING),'') OR (X.zcliente IS NULL AND Y.zcliente_SIMUL IS NOT NULL ) OR (X.zcliente IS NOT NULL AND Y.zcliente_SIMUL IS NULL),1,0)) AS NUM_REG_DIF,'1' AS ID_EXEC, CURRENT_TIMESTAMP() AS TIME_EXEC FROM (SELECT a, zcliente FROM BU_LOANTAPE_WORK.LT001_UNIV_OPER WHERE ref_date='${ref_date}' AND nome_perimetro='Individual Local' AND segmento='ESTR' AND ambito='SRB_MBDT' AND entidade='00100')X INNER JOIN (SELECT a AS a_SIMUL, zcliente AS zcliente_SIMUL FROM BU_LOANTAPE_WORK.SIMUL_LT001 WHERE ref_date='${ref_date}' AND nome_perimetro='Individual Local' AND segmento='ESTR' AND ambito='PILAR3' AND entidade='00100')Y ON X.A=Y.A_SIMUL
A14: =+B14&F14 -> UNIV_OPERccontab_final_ifrs | B14: UNIV_OPER | C14: Coerência | D14: =+UPPER('0. Instruções'!$D$35&"."&VLOOKUP(B14,'0. Instruções'!$C$27:$D$32,2,FALSE)) -> BU_LOANTAPE_WORK.LT001_UNIV_OPER | E14: =+UPPER('0. Instruções'!$D$36&"."&VLOOKUP(B14,'0. Instruções'!$C$27:$E$32,3,FALSE)) -> BU_LOANTAPE_WORK.SIMUL_LT001 | F14: ccontab_final_ifrs | I14: ="(SELECT "&VLOOKUP(B14,'0. Instruções'!$C$27:$G$32,4,FALSE)&", "&F14&" FROM "&D14&" WHERE "&'0. Instruções'!$D$42&")X" -> (SELECT a, ccontab_final_ifrs FROM BU_LOANTAPE_WORK.LT001_UNIV_OPER WHERE ref_date='${ref_date}' AND nome_perimetro='Individual Local' AND segmento='ESTR' AND ambito='SRB_MBDT' AND entidade='00100')X | J14: ="(SELECT "&VLOOKUP(B14,'0. Instruções'!$C$27:$G$32,4,FALSE)&" AS "&VLOOKUP(B14,'0. Instruções'!$C$27:$G$32,4,FALSE)&"_SIMUL, "&F14&" AS "&F14&"_SIMUL FROM "&E14&" WHERE "&'0. Instruções'!$D$43&")Y" -> (SELECT a AS a_SIMUL, ccontab_final_ifrs AS ccontab_final_ifrs_SIMUL FROM BU_LOANTAPE_WORK.SIMUL_LT001 WHERE ref_date='${ref_date}' AND nome_perimetro='Individual Local' AND segmento='ESTR' AND ambito='PILAR3' AND entidade='00100')Y | K14: =+UPPER("ON X."&VLOOKUP(B14,'0. Instruções'!$C$27:$G$32,4,FALSE)&"=Y."&VLOOKUP(B14,'0. Instruções'!$C$27:$G$32,4,FALSE)&"_SIMUL") -> ON X.A=Y.A_SIMUL | L14: =+IF(C14="Coerência", +IF(LEFT(G14,5)="FLOAT","SELECT '"&UPPER(B14)&"' AS TABELA, '"&UPPER(C14)&"' AS TIPOLOGIA_TESTE,'"&D14&"' AS TABELA_LT,'"&E14&"' AS TABELA_SIMUL,'"&F14&"' AS CAMPO, "&"'${ref_date}' AS REF_DATE, COUNT(*) AS NUM_REG, SUM(IF((ABS(COALESCE(CAST(X."&F14&" AS DECIMAL(18,6)),0)-COALESCE(CAST(Y."&F14&"_SIMUL AS DECIMAL(18,6)),0))>0.000001) OR (X."&F14&" IS NULL AND Y."&F14&"_SIMUL IS NOT NULL ) OR (X."&F14&" IS NOT NULL AND Y."&F14&"_SIMUL IS NULL),1,0)) AS NUM_REG_DIF,'"&MAX('ID1&5'!K:K)+1&"' AS ID_EXEC, CURRENT_TIMESTAMP() AS TIME_EXEC FROM "&I14&" INNER JOIN "&J14&" "&K14,"SELECT '"&UPPER(B14)&"' AS TABELA, '"&UPPER(C14)&"' AS TIPOLOGIA_TESTE,'"&D14&"' AS TABELA_LT,'"&E14&"' AS TABELA_SIMUL,'"&F14&"' AS CAMPO, "&"'${ref_date}' AS REF_DATE, COUNT(*) AS NUM_REG, SUM(IF(COALESCE(CAST(X."&F14&" AS STRING),'')<>COALESCE(CAST(Y."&F14&"_SIMUL AS STRING),'') OR (X."&F14&" IS NULL AND Y."&F14&"_SIMUL IS NOT NULL ) OR (X."&F14&" IS NOT NULL AND Y."&F14&"_SIMUL IS NULL),1,0)) AS NUM_REG_DIF,'"&MAX('ID1&5'!L:L)+1&"' AS ID_EXEC, CURRENT_TIMESTAMP() AS TIME_EXEC FROM "&I14&" INNER JOIN "&J14&" "&K14), IF(C14="Validade",+IF(G14="Code List","SELECT '"&UPPER(B14)&"' AS TABELA, '"&UPPER(C14)&"' AS TIPOLOGIA_TESTE,'"&D14&"' AS TABELA_LT,'N/A' AS TABELA_SIMUL,'"&F14&"' AS CAMPO, "&"'${ref_date}' AS REF_DATE, COUNT(*) AS NUM_REG, SUM(IF(TRIM(CAST(X."&F14&" AS STRING))='' OR TRIM(CAST(X."&F14&" AS STRING)) IS NULL OR CAST(X."&F14&" AS STRING) NOT "&H14&",1,0)) AS NUM_REG_DIF,'"&MAX('ID1&5'!K:K)+1&"' AS ID_EXEC, CURRENT_TIMESTAMP() AS TIME_EXEC FROM "&I14,"SELECT '"&UPPER(B14)&"' AS TABELA, '"&UPPER(C14)&"' AS TIPOLOGIA_TESTE,'"&D14&"' AS TABELA_LT,'N/A' AS TABELA_SIMUL,'"&F14&"' AS CAMPO, "&"'${ref_date}' AS REF_DATE, COUNT(*) AS NUM_REG, SUM(IF(TRIM(CAST(X."&F14&" AS STRING))='' OR TRIM(CAST(X."&F14&" AS STRING)) IS NULL,1,0)) AS NUM_REG_DIF,'"&MAX('ID1&5'!K:K)+1&"' AS ID_EXEC, CURRENT_TIMESTAMP() AS TIME_EXEC FROM "&I14), IF(C14="Caracteres Especiais",+"SELECT '"&UPPER(B14)&"' AS TABELA, '"&UPPER(C14)&"' AS TIPOLOGIA_TESTE,'"&D14&"' AS TABELA_LT,'N/A' AS TABELA_SIMUL,'"&F14&"' AS CAMPO, "&"'${ref_date}' AS REF_DATE, COUNT(*) AS NUM_REG, SUM(IF(REGEXP_REPLACE(TRIM(CAST(X."&F14&" AS STRING)),'[^a-zA-Z0-9_\\s]','') <>TRIM(CAST(X."&F14&" AS STRING)),1,0)) AS NUM_REG_DIF,'"&MAX('ID1&5'!K:K)+1&"' AS ID_EXEC, CURRENT_TIMESTAMP() AS TIME_EXEC FROM "&I14, IF(C14="Missings",+"SELECT '"&UPPER(B14)&"' AS TABELA, '"&UPPER(C14)&"' AS TIPOLOGIA_TESTE,'"&D14&"' AS TABELA_LT,'N/A' AS TABELA_SIMUL,'"&F14&"' AS CAMPO, "&"'${ref_date}' AS REF_DATE, COUNT(*) AS NUM_REG, SUM(IF(TRIM(CAST(X."&F14&" AS STRING)) IN ('0000-00-00','0001-01-01','9999-12-31','MISS','00000','99999999999','99999999999.00','99999999999.000000'),1,0)) AS NUM_REG_DIF,'"&MAX('ID1&5'!K:K)+1&"' AS ID_EXEC, CURRENT_TIMESTAMP() AS TIME_EXEC FROM "&I14, IF(C14="Not applicable",+"SELECT '"&UPPER(B14)&"' AS TABELA, '"&UPPER(C14)&"' AS TIPOLOGIA_TESTE,'"&D14&"' AS TABELA_LT,'N/A' AS TABELA_SIMUL,'"&F14&"' AS CAMPO, "&"'${ref_date}' AS REF_DATE, COUNT(*) AS NUM_REG, SUM(IF(TRIM(CAST(X."&F14&" AS STRING)) IN ('N/A','11111111111','11111111111.00','11111111111.000000','1111-11-11'),1,0)) AS NUM_REG_DIF,'"&MAX('ID1&5'!K:K)+1&"' AS ID_EXEC, CURRENT_TIMESTAMP() AS TIME_EXEC FROM "&I14, IF(C14="Valores extremos",+"SELECT '"&UPPER(B14)&"' AS TABELA, '"&UPPER(C14)&"' AS TIPOLOGIA_TESTE,'"&D14&"' AS TABELA_LT,'N/A' AS TABELA_SIMUL,'"&F14&"' AS CAMPO, "&"'${ref_date}' AS REF_DATE, CAST(MIN("&F14&") AS STRING) AS VALOR_MIN, CAST(MAX("&F14&") AS STRING) AS VALOR_MAX,'"&MAX('ID1&5'!K:K)+1&"' AS ID_EXEC, CURRENT_TIMESTAMP() AS TIME_EXEC FROM "&MID(I14,1,LEN(I14)-2)&" AND CAST("&F14&" AS STRING) NOT IN ('0000-00-00','0001-01-01','9999-12-31','MISS','00000','99999999999','99999999999.00','99999999999.000000','N/A','11111111111','11111111111.00','11111111111.000000','1111-11-11'))X")))))) -> SELECT 'UNIV_OPER' AS TABELA, 'COERÊNCIA' AS TIPOLOGIA_TESTE,'BU_LOANTAPE_WORK.LT001_UNIV_OPER' AS TABELA_LT,'BU_LOANTAPE_WORK.SIMUL_LT001' AS TABELA_SIMUL,'ccontab_final_ifrs' AS CAMPO, '${ref_date}' AS REF_DATE, COUNT(*) AS NUM_REG, SUM(IF(COALESCE(CAST(X.ccontab_final_ifrs AS STRING),'')<>COALESCE(CAST(Y.ccontab_final_ifrs_SIMUL AS STRING),'') OR (X.ccontab_final_ifrs IS NULL AND Y.ccontab_final_ifrs_SIMUL IS NOT NULL ) OR (X.ccontab_final_ifrs IS NOT NULL AND Y.ccontab_final_ifrs_SIMUL IS NULL),1,0)) AS NUM_REG_DIF,'1' AS ID_EXEC, CURRENT_TIMESTAMP() AS TIME_EXEC FROM (SELECT a, ccontab_final_ifrs FROM BU_LOANTAPE_WORK.LT001_UNIV_OPER WHERE ref_date='${ref_date}' AND nome_perimetro='Individual Local' AND segmento='ESTR' AND ambito='SRB_MBDT' AND entidade='00100')X INNER JOIN (SELECT a AS a_SIMUL, ccontab_final_ifrs AS ccontab_final_ifrs_SIMUL FROM BU_LOANTAPE_WORK.SIMUL_LT001 WHERE ref_date='${ref_date}' AND nome_perimetro='Individual Local' AND segmento='ESTR' AND ambito='PILAR3' AND entidade='00100')Y ON X.A=Y.A_SIMUL | M14: =+"UNION ALL "&L14 -> UNION ALL SELECT 'UNIV_OPER' AS TABELA, 'COERÊNCIA' AS TIPOLOGIA_TESTE,'BU_LOANTAPE_WORK.LT001_UNIV_OPER' AS TABELA_LT,'BU_LOANTAPE_WORK.SIMUL_LT001' AS TABELA_SIMUL,'ccontab_final_ifrs' AS CAMPO, '${ref_date}' AS REF_DATE, COUNT(*) AS NUM_REG, SUM(IF(COALESCE(CAST(X.ccontab_final_ifrs AS STRING),'')<>COALESCE(CAST(Y.ccontab_final_ifrs_SIMUL AS STRING),'') OR (X.ccontab_final_ifrs IS NULL AND Y.ccontab_final_ifrs_SIMUL IS NOT NULL ) OR (X.ccontab_final_ifrs IS NOT NULL AND Y.ccontab_final_ifrs_SIMUL IS NULL),1,0)) AS NUM_REG_DIF,'1' AS ID_EXEC, CURRENT_TIMESTAMP() AS TIME_EXEC FROM (SELECT a, ccontab_final_ifrs FROM BU_LOANTAPE_WORK.LT001_UNIV_OPER WHERE ref_date='${ref_date}' AND nome_perimetro='Individual Local' AND segmento='ESTR' AND ambito='SRB_MBDT' AND entidade='00100')X INNER JOIN (SELECT a AS a_SIMUL, ccontab_final_ifrs AS ccontab_final_ifrs_SIMUL FROM BU_LOANTAPE_WORK.SIMUL_LT001 WHERE ref_date='${ref_date}' AND nome_perimetro='Individual Local' AND segmento='ESTR' AND ambito='PILAR3' AND entidade='00100')Y ON X.A=Y.A_SIMUL
A15: =+B15&F15 -> UNIV_OPERccontab_final_pcsb | B15: UNIV_OPER | C15: Coerência | D15: =+UPPER('0. Instruções'!$D$35&"."&VLOOKUP(B15,'0. Instruções'!$C$27:$D$32,2,FALSE)) -> BU_LOANTAPE_WORK.LT001_UNIV_OPER | E15: =+UPPER('0. Instruções'!$D$36&"."&VLOOKUP(B15,'0. Instruções'!$C$27:$E$32,3,FALSE)) -> BU_LOANTAPE_WORK.SIMUL_LT001 | F15: ccontab_final_pcsb | I15: ="(SELECT "&VLOOKUP(B15,'0. Instruções'!$C$27:$G$32,4,FALSE)&", "&F15&" FROM "&D15&" WHERE "&'0. Instruções'!$D$42&")X" -> (SELECT a, ccontab_final_pcsb FROM BU_LOANTAPE_WORK.LT001_UNIV_OPER WHERE ref_date='${ref_date}' AND nome_perimetro='Individual Local' AND segmento='ESTR' AND ambito='SRB_MBDT' AND entidade='00100')X | J15: ="(SELECT "&VLOOKUP(B15,'0. Instruções'!$C$27:$G$32,4,FALSE)&" AS "&VLOOKUP(B15,'0. Instruções'!$C$27:$G$32,4,FALSE)&"_SIMUL, "&F15&" AS "&F15&"_SIMUL FROM "&E15&" WHERE "&'0. Instruções'!$D$43&")Y" -> (SELECT a AS a_SIMUL, ccontab_final_pcsb AS ccontab_final_pcsb_SIMUL FROM BU_LOANTAPE_WORK.SIMUL_LT001 WHERE ref_date='${ref_date}' AND nome_perimetro='Individual Local' AND segmento='ESTR' AND ambito='PILAR3' AND entidade='00100')Y | K15: =+UPPER("ON X."&VLOOKUP(B15,'0. Instruções'!$C$27:$G$32,4,FALSE)&"=Y."&VLOOKUP(B15,'0. Instruções'!$C$27:$G$32,4,FALSE)&"_SIMUL") -> ON X.A=Y.A_SIMUL | L15: =+IF(C15="Coerência", +IF(LEFT(G15,5)="FLOAT","SELECT '"&UPPER(B15)&"' AS TABELA, '"&UPPER(C15)&"' AS TIPOLOGIA_TESTE,'"&D15&"' AS TABELA_LT,'"&E15&"' AS TABELA_SIMUL,'"&F15&"' AS CAMPO, "&"'${ref_date}' AS REF_DATE, COUNT(*) AS NUM_REG, SUM(IF((ABS(COALESCE(CAST(X."&F15&" AS DECIMAL(18,6)),0)-COALESCE(CAST(Y."&F15&"_SIMUL AS DECIMAL(18,6)),0))>0.000001) OR (X."&F15&" IS NULL AND Y."&F15&"_SIMUL IS NOT NULL ) OR (X."&F15&" IS NOT NULL AND Y."&F15&"_SIMUL IS NULL),1,0)) AS NUM_REG_DIF,'"&MAX('ID1&5'!K:K)+1&"' AS ID_EXEC, CURRENT_TIMESTAMP() AS TIME_EXEC FROM "&I15&" INNER JOIN "&J15&" "&K15,"SELECT '"&UPPER(B15)&"' AS TABELA, '"&UPPER(C15)&"' AS TIPOLOGIA_TESTE,'"&D15&"' AS TABELA_LT,'"&E15&"' AS TABELA_SIMUL,'"&F15&"' AS CAMPO, "&"'${ref_date}' AS REF_DATE, COUNT(*) AS NUM_REG, SUM(IF(COALESCE(CAST(X."&F15&" AS STRING),'')<>COALESCE(CAST(Y."&F15&"_SIMUL AS STRING),'') OR (X."&F15&" IS NULL AND Y."&F15&"_SIMUL IS NOT NULL ) OR (X."&F15&" IS NOT NULL AND Y."&F15&"_SIMUL IS NULL),1,0)) AS NUM_REG_DIF,'"&MAX('ID1&5'!L:L)+1&"' AS ID_EXEC, CURRENT_TIMESTAMP() AS TIME_EXEC FROM "&I15&" INNER JOIN "&J15&" "&K15), IF(C15="Validade",+IF(G15="Code List","SELECT '"&UPPER(B15)&"' AS TABELA, '"&UPPER(C15)&"' AS TIPOLOGIA_TESTE,'"&D15&"' AS TABELA_LT,'N/A' AS TABELA_SIMUL,'"&F15&"' AS CAMPO, "&"'${ref_date}' AS REF_DATE, COUNT(*) AS NUM_REG, SUM(IF(TRIM(CAST(X."&F15&" AS STRING))='' OR TRIM(CAST(X."&F15&" AS STRING)) IS NULL OR CAST(X."&F15&" AS STRING) NOT "&H15&",1,0)) AS NUM_REG_DIF,'"&MAX('ID1&5'!K:K)+1&"' AS ID_EXEC, CURRENT_TIMESTAMP() AS TIME_EXEC FROM "&I15,"SELECT '"&UPPER(B15)&"' AS TABELA, '"&UPPER(C15)&"' AS TIPOLOGIA_TESTE,'"&D15&"' AS TABELA_LT,'N/A' AS TABELA_SIMUL,'"&F15&"' AS CAMPO, "&"'${ref_date}' AS REF_DATE, COUNT(*) AS NUM_REG, SUM(IF(TRIM(CAST(X."&F15&" AS STRING))='' OR TRIM(CAST(X."&F15&" AS STRING)) IS NULL,1,0)) AS NUM_REG_DIF,'"&MAX('ID1&5'!K:K)+1&"' AS ID_EXEC, CURRENT_TIMESTAMP() AS TIME_EXEC FROM "&I15), IF(C15="Caracteres Especiais",+"SELECT '"&UPPER(B15)&"' AS TABELA, '"&UPPER(C15)&"' AS TIPOLOGIA_TESTE,'"&D15&"' AS TABELA_LT,'N/A' AS TABELA_SIMUL,'"&F15&"' AS CAMPO, "&"'${ref_date}' AS REF_DATE, COUNT(*) AS NUM_REG, SUM(IF(REGEXP_REPLACE(TRIM(CAST(X."&F15&" AS STRING)),'[^a-zA-Z0-9_\\s]','') <>TRIM(CAST(X."&F15&" AS STRING)),1,0)) AS NUM_REG_DIF,'"&MAX('ID1&5'!K:K)+1&"' AS ID_EXEC, CURRENT_TIMESTAMP() AS TIME_EXEC FROM "&I15, IF(C15="Missings",+"SELECT '"&UPPER(B15)&"' AS TABELA, '"&UPPER(C15)&"' AS TIPOLOGIA_TESTE,'"&D15&"' AS TABELA_LT,'N/A' AS TABELA_SIMUL,'"&F15&"' AS CAMPO, "&"'${ref_date}' AS REF_DATE, COUNT(*) AS NUM_REG, SUM(IF(TRIM(CAST(X."&F15&" AS STRING)) IN ('0000-00-00','0001-01-01','9999-12-31','MISS','00000','99999999999','99999999999.00','99999999999.000000'),1,0)) AS NUM_REG_DIF,'"&MAX('ID1&5'!K:K)+1&"' AS ID_EXEC, CURRENT_TIMESTAMP() AS TIME_EXEC FROM "&I15, IF(C15="Not applicable",+"SELECT '"&UPPER(B15)&"' AS TABELA, '"&UPPER(C15)&"' AS TIPOLOGIA_TESTE,'"&D15&"' AS TABELA_LT,'N/A' AS TABELA_SIMUL,'"&F15&"' AS CAMPO, "&"'${ref_date}' AS REF_DATE, COUNT(*) AS NUM_REG, SUM(IF(TRIM(CAST(X."&F15&" AS STRING)) IN ('N/A','11111111111','11111111111.00','11111111111.000000','1111-11-11'),1,0)) AS NUM_REG_DIF,'"&MAX('ID1&5'!K:K)+1&"' AS ID_EXEC, CURRENT_TIMESTAMP() AS TIME_EXEC FROM "&I15, IF(C15="Valores extremos",+"SELECT '"&UPPER(B15)&"' AS TABELA, '"&UPPER(C15)&"' AS TIPOLOGIA_TESTE,'"&D15&"' AS TABELA_LT,'N/A' AS TABELA_SIMUL,'"&F15&"' AS CAMPO, "&"'${ref_date}' AS REF_DATE, CAST(MIN("&F15&") AS STRING) AS VALOR_MIN, CAST(MAX("&F15&") AS STRING) AS VALOR_MAX,'"&MAX('ID1&5'!K:K)+1&"' AS ID_EXEC, CURRENT_TIMESTAMP() AS TIME_EXEC FROM "&MID(I15,1,LEN(I15)-2)&" AND CAST("&F15&" AS STRING) NOT IN ('0000-00-00','0001-01-01','9999-12-31','MISS','00000','99999999999','99999999999.00','99999999999.000000','N/A','11111111111','11111111111.00','11111111111.000000','1111-11-11'))X")))))) -> SELECT 'UNIV_OPER' AS TABELA, 'COERÊNCIA' AS TIPOLOGIA_TESTE,'BU_LOANTAPE_WORK.LT001_UNIV_OPER' AS TABELA_LT,'BU_LOANTAPE_WORK.SIMUL_LT001' AS TABELA_SIMUL,'ccontab_final_pcsb' AS CAMPO, '${ref_date}' AS REF_DATE, COUNT(*) AS NUM_REG, SUM(IF(COALESCE(CAST(X.ccontab_final_pcsb AS STRING),'')<>COALESCE(CAST(Y.ccontab_final_pcsb_SIMUL AS STRING),'') OR (X.ccontab_final_pcsb IS NULL AND Y.ccontab_final_pcsb_SIMUL IS NOT NULL ) OR (X.ccontab_final_pcsb IS NOT NULL AND Y.ccontab_final_pcsb_SIMUL IS NULL),1,0)) AS NUM_REG_DIF,'1' AS ID_EXEC, CURRENT_TIMESTAMP() AS TIME_EXEC FROM (SELECT a, ccontab_final_pcsb FROM BU_LOANTAPE_WORK.LT001_UNIV_OPER WHERE ref_date='${ref_date}' AND nome_perimetro='Individual Local' AND segmento='ESTR' AND ambito='SRB_MBDT' AND entidade='00100')X INNER JOIN (SELECT a AS a_SIMUL, ccontab_final_pcsb AS ccontab_final_pcsb_SIMUL FROM BU_LOANTAPE_WORK.SIMUL_LT001 WHERE ref_date='${ref_date}' AND nome_perimetro='Individual Local' AND segmento='ESTR' AND ambito='PILAR3' AND entidade='00100')Y ON X.A=Y.A_SIMUL | M15: =+"UNION ALL "&L15 -> UNION ALL SELECT 'UNIV_OPER' AS TABELA, 'COERÊNCIA' AS TIPOLOGIA_TESTE,'BU_LOANTAPE_WORK.LT001_UNIV_OPER' AS TABELA_LT,'BU_LOANTAPE_WORK.SIMUL_LT001' AS TABELA_SIMUL,'ccontab_final_pcsb' AS CAMPO, '${ref_date}' AS REF_DATE, COUNT(*) AS NUM_REG, SUM(IF(COALESCE(CAST(X.ccontab_final_pcsb AS STRING),'')<>COALESCE(CAST(Y.ccontab_final_pcsb_SIMUL AS STRING),'') OR (X.ccontab_final_pcsb IS NULL AND Y.ccontab_final_pcsb_SIMUL IS NOT NULL ) OR (X.ccontab_final_pcsb IS NOT NULL AND Y.ccontab_final_pcsb_SIMUL IS NULL),1,0)) AS NUM_REG_DIF,'1' AS ID_EXEC, CURRENT_TIMESTAMP() AS TIME_EXEC FROM (SELECT a, ccontab_final_pcsb FROM BU_LOANTAPE_WORK.LT001_UNIV_OPER WHERE ref_date='${ref_date}' AND nome_perimetro='Individual Local' AND segmento='ESTR' AND ambito='SRB_MBDT' AND entidade='00100')X INNER JOIN (SELECT a AS a_SIMUL, ccontab_final_pcsb AS ccontab_final_pcsb_SIMUL FROM BU_LOANTAPE_WORK.SIMUL_LT001 WHERE ref_date='${ref_date}' AND nome_perimetro='Individual Local' AND segmento='ESTR' AND ambito='PILAR3' AND entidade='00100')Y ON X.A=Y.A_SIMUL
A16: =+B16&F16 -> UNIV_OPERccontab_final_cargabal | B16: UNIV_OPER | C16: Coerência | D16: =+UPPER('0. Instruções'!$D$35&"."&VLOOKUP(B16,'0. Instruções'!$C$27:$D$32,2,FALSE)) -> BU_LOANTAPE_WORK.LT001_UNIV_OPER | E16: =+UPPER('0. Instruções'!$D$36&"."&VLOOKUP(B16,'0. Instruções'!$C$27:$E$32,3,FALSE)) -> BU_LOANTAPE_WORK.SIMUL_LT001 | F16: ccontab_final_cargabal | I16: ="(SELECT "&VLOOKUP(B16,'0. Instruções'!$C$27:$G$32,4,FALSE)&", "&F16&" FROM "&D16&" WHERE "&'0. Instruções'!$D$42&")X" -> (SELECT a, ccontab_final_cargabal FROM BU_LOANTAPE_WORK.LT001_UNIV_OPER WHERE ref_date='${ref_date}' AND nome_perimetro='Individual Local' AND segmento='ESTR' AND ambito='SRB_MBDT' AND entidade='00100')X | J16: ="(SELECT "&VLOOKUP(B16,'0. Instruções'!$C$27:$G$32,4,FALSE)&" AS "&VLOOKUP(B16,'0. Instruções'!$C$27:$G$32,4,FALSE)&"_SIMUL, "&F16&" AS "&F16&"_SIMUL FROM "&E16&" WHERE "&'0. Instruções'!$D$43&")Y" -> (SELECT a AS a_SIMUL, ccontab_final_cargabal AS ccontab_final_cargabal_SIMUL FROM BU_LOANTAPE_WORK.SIMUL_LT001 WHERE ref_date='${ref_date}' AND nome_perimetro='Individual Local' AND segmento='ESTR' AND ambito='PILAR3' AND entidade='00100')Y | K16: =+UPPER("ON X."&VLOOKUP(B16,'0. Instruções'!$C$27:$G$32,4,FALSE)&"=Y."&VLOOKUP(B16,'0. Instruções'!$C$27:$G$32,4,FALSE)&"_SIMUL") -> ON X.A=Y.A_SIMUL | L16: =+IF(C16="Coerência", +IF(LEFT(G16,5)="FLOAT","SELECT '"&UPPER(B16)&"' AS TABELA, '"&UPPER(C16)&"' AS TIPOLOGIA_TESTE,'"&D16&"' AS TABELA_LT,'"&E16&"' AS TABELA_SIMUL,'"&F16&"' AS CAMPO, "&"'${ref_date}' AS REF_DATE, COUNT(*) AS NUM_REG, SUM(IF((ABS(COALESCE(CAST(X."&F16&" AS DECIMAL(18,6)),0)-COALESCE(CAST(Y."&F16&"_SIMUL AS DECIMAL(18,6)),0))>0.000001) OR (X."&F16&" IS NULL AND Y."&F16&"_SIMUL IS NOT NULL ) OR (X."&F16&" IS NOT NULL AND Y."&F16&"_SIMUL IS NULL),1,0)) AS NUM_REG_DIF,'"&MAX('ID1&5'!K:K)+1&"' AS ID_EXEC, CURRENT_TIMESTAMP() AS TIME_EXEC FROM "&I16&" INNER JOIN "&J16&" "&K16,"SELECT '"&UPPER(B16)&"' AS TABELA, '"&UPPER(C16)&"' AS TIPOLOGIA_TESTE,'"&D16&"' AS TABELA_LT,'"&E16&"' AS TABELA_SIMUL,'"&F16&"' AS CAMPO, "&"'${ref_date}' AS REF_DATE, COUNT(*) AS NUM_REG, SUM(IF(COALESCE(CAST(X."&F16&" AS STRING),'')<>COALESCE(CAST(Y."&F16&"_SIMUL AS STRING),'') OR (X."&F16&" IS NULL AND Y."&F16&"_SIMUL IS NOT NULL ) OR (X."&F16&" IS NOT NULL AND Y."&F16&"_SIMUL IS NULL),1,0)) AS NUM_REG_DIF,'"&MAX('ID1&5'!L:L)+1&"' AS ID_EXEC, CURRENT_TIMESTAMP() AS TIME_EXEC FROM "&I16&" INNER JOIN "&J16&" "&K16), IF(C16="Validade",+IF(G16="Code List","SELECT '"&UPPER(B16)&"' AS TABELA, '"&UPPER(C16)&"' AS TIPOLOGIA_TESTE,'"&D16&"' AS TABELA_LT,'N/A' AS TABELA_SIMUL,'"&F16&"' AS CAMPO, "&"'${ref_date}' AS REF_DATE, COUNT(*) AS NUM_REG, SUM(IF(TRIM(CAST(X."&F16&" AS STRING))='' OR TRIM(CAST(X."&F16&" AS STRING)) IS NULL OR CAST(X."&F16&" AS STRING) NOT "&H16&",1,0)) AS NUM_REG_DIF,'"&MAX('ID1&5'!K:K)+1&"' AS ID_EXEC, CURRENT_TIMESTAMP() AS TIME_EXEC FROM "&I16,"SELECT '"&UPPER(B16)&"' AS TABELA, '"&UPPER(C16)&"' AS TIPOLOGIA_TESTE,'"&D16&"' AS TABELA_LT,'N/A' AS TABELA_SIMUL,'"&F16&"' AS CAMPO, "&"'${ref_date}' AS REF_DATE, COUNT(*) AS NUM_REG, SUM(IF(TRIM(CAST(X."&F16&" AS STRING))='' OR TRIM(CAST(X."&F16&" AS STRING)) IS NULL,1,0)) AS NUM_REG_DIF,'"&MAX('ID1&5'!K:K)+1&"' AS ID_EXEC, CURRENT_TIMESTAMP() AS TIME_EXEC FROM "&I16), IF(C16="Caracteres Especiais",+"SELECT '"&UPPER(B16)&"' AS TABELA, '"&UPPER(C16)&"' AS TIPOLOGIA_TESTE,'"&D16&"' AS TABELA_LT,'N/A' AS TABELA_SIMUL,'"&F16&"' AS CAMPO, "&"'${ref_date}' AS REF_DATE, COUNT(*) AS NUM_REG, SUM(IF(REGEXP_REPLACE(TRIM(CAST(X."&F16&" AS STRING)),'[^a-zA-Z0-9_\\s]','') <>TRIM(CAST(X."&F16&" AS STRING)),1,0)) AS NUM_REG_DIF,'"&MAX('ID1&5'!K:K)+1&"' AS ID_EXEC, CURRENT_TIMESTAMP() AS TIME_EXEC FROM "&I16, IF(C16="Missings",+"SELECT '"&UPPER(B16)&"' AS TABELA, '"&UPPER(C16)&"' AS TIPOLOGIA_TESTE,'"&D16&"' AS TABELA_LT,'N/A' AS TABELA_SIMUL,'"&F16&"' AS CAMPO, "&"'${ref_date}' AS REF_DATE, COUNT(*) AS NUM_REG, SUM(IF(TRIM(CAST(X."&F16&" AS STRING)) IN ('0000-00-00','0001-01-01','9999-12-31','MISS','00000','99999999999','99999999999.00','99999999999.000000'),1,0)) AS NUM_REG_DIF,'"&MAX('ID1&5'!K:K)+1&"' AS ID_EXEC, CURRENT_TIMESTAMP() AS TIME_EXEC FROM "&I16, IF(C16="Not applicable",+"SELECT '"&UPPER(B16)&"' AS TABELA, '"&UPPER(C16)&"' AS TIPOLOGIA_TESTE,'"&D16&"' AS TABELA_LT,'N/A' AS TABELA_SIMUL,'"&F16&"' AS CAMPO, "&"'${ref_date}' AS REF_DATE, COUNT(*) AS NUM_REG, SUM(IF(TRIM(CAST(X."&F16&" AS STRING)) IN ('N/A','11111111111','11111111111.00','11111111111.000000','1111-11-11'),1,0)) AS NUM_REG_DIF,'"&MAX('ID1&5'!K:K)+1&"' AS ID_EXEC, CURRENT_TIMESTAMP() AS TIME_EXEC FROM "&I16, IF(C16="Valores extremos",+"SELECT '"&UPPER(B16)&"' AS TABELA, '"&UPPER(C16)&"' AS TIPOLOGIA_TESTE,'"&D16&"' AS TABELA_LT,'N/A' AS TABELA_SIMUL,'"&F16&"' AS CAMPO, "&"'${ref_date}' AS REF_DATE, CAST(MIN("&F16&") AS STRING) AS VALOR_MIN, CAST(MAX("&F16&") AS STRING) AS VALOR_MAX,'"&MAX('ID1&5'!K:K)+1&"' AS ID_EXEC, CURRENT_TIMESTAMP() AS TIME_EXEC FROM "&MID(I16,1,LEN(I16)-2)&" AND CAST("&F16&" AS STRING) NOT IN ('0000-00-00','0001-01-01','9999-12-31','MISS','00000','99999999999','99999999999.00','99999999999.000000','N/A','11111111111','11111111111.00','11111111111.000000','1111-11-11'))X")))))) -> SELECT 'UNIV_OPER' AS TABELA, 'COERÊNCIA' AS TIPOLOGIA_TESTE,'BU_LOANTAPE_WORK.LT001_UNIV_OPER' AS TABELA_LT,'BU_LOANTAPE_WORK.SIMUL_LT001' AS TABELA_SIMUL,'ccontab_final_cargabal' AS CAMPO, '${ref_date}' AS REF_DATE, COUNT(*) AS NUM_REG, SUM(IF(COALESCE(CAST(X.ccontab_final_cargabal AS STRING),'')<>COALESCE(CAST(Y.ccontab_final_cargabal_SIMUL AS STRING),'') OR (X.ccontab_final_cargabal IS NULL AND Y.ccontab_final_cargabal_SIMUL IS NOT NULL ) OR (X.ccontab_final_cargabal IS NOT NULL AND Y.ccontab_final_cargabal_SIMUL IS NULL),1,0)) AS NUM_REG_DIF,'1' AS ID_EXEC, CURRENT_TIMESTAMP() AS TIME_EXEC FROM (SELECT a, ccontab_final_cargabal FROM BU_LOANTAPE_WORK.LT001_UNIV_OPER WHERE ref_date='${ref_date}' AND nome_perimetro='Individual Local' AND segmento='ESTR' AND ambito='SRB_MBDT' AND entidade='00100')X INNER JOIN (SELECT a AS a_SIMUL, ccontab_final_cargabal AS ccontab_final_cargabal_SIMUL FROM BU_LOANTAPE_WORK.SIMUL_LT001 WHERE ref_date='${ref_date}' AND nome_perimetro='Individual Local' AND segmento='ESTR' AND ambito='PILAR3' AND entidade='00100')Y ON X.A=Y.A_SIMUL | M16: =+"UNION ALL "&L16 -> UNION ALL SELECT 'UNIV_OPER' AS TABELA, 'COERÊNCIA' AS TIPOLOGIA_TESTE,'BU_LOANTAPE_WORK.LT001_UNIV_OPER' AS TABELA_LT,'BU_LOANTAPE_WORK.SIMUL_LT001' AS TABELA_SIMUL,'ccontab_final_cargabal' AS CAMPO, '${ref_date}' AS REF_DATE, COUNT(*) AS NUM_REG, SUM(IF(COALESCE(CAST(X.ccontab_final_cargabal AS STRING),'')<>COALESCE(CAST(Y.ccontab_final_cargabal_SIMUL AS STRING),'') OR (X.ccontab_final_cargabal IS NULL AND Y.ccontab_final_cargabal_SIMUL IS NOT NULL ) OR (X.ccontab_final_cargabal IS NOT NULL AND Y.ccontab_final_cargabal_SIMUL IS NULL),1,0)) AS NUM_REG_DIF,'1' AS ID_EXEC, CURRENT_TIMESTAMP() AS TIME_EXEC FROM (SELECT a, ccontab_final_cargabal FROM BU_LOANTAPE_WORK.LT001_UNIV_OPER WHERE ref_date='${ref_date}' AND nome_perimetro='Individual Local' AND segmento='ESTR' AND ambito='SRB_MBDT' AND entidade='00100')X INNER JOIN (SELECT a AS a_SIMUL, ccontab_final_cargabal AS ccontab_final_cargabal_SIMUL FROM BU_LOANTAPE_WORK.SIMUL_LT001 WHERE ref_date='${ref_date}' AND nome_perimetro='Individual Local' AND segmento='ESTR' AND ambito='PILAR3' AND entidade='00100')Y ON X.A=Y.A_SIMUL
A17: =+B17&F17 -> UNIV_OPERccontab_final | B17: UNIV_OPER | C17: Coerência | D17: =+UPPER('0. Instruções'!$D$35&"."&VLOOKUP(B17,'0. Instruções'!$C$27:$D$32,2,FALSE)) -> BU_LOANTAPE_WORK.LT001_UNIV_OPER | E17: =+UPPER('0. Instruções'!$D$36&"."&VLOOKUP(B17,'0. Instruções'!$C$27:$E$32,3,FALSE)) -> BU_LOANTAPE_WORK.SIMUL_LT001 | F17: ccontab_final | I17: ="(SELECT "&VLOOKUP(B17,'0. Instruções'!$C$27:$G$32,4,FALSE)&", "&F17&" FROM "&D17&" WHERE "&'0. Instruções'!$D$42&")X" -> (SELECT a, ccontab_final FROM BU_LOANTAPE_WORK.LT001_UNIV_OPER WHERE ref_date='${ref_date}' AND nome_perimetro='Individual Local' AND segmento='ESTR' AND ambito='SRB_MBDT' AND entidade='00100')X | J17: ="(SELECT "&VLOOKUP(B17,'0. Instruções'!$C$27:$G$32,4,FALSE)&" AS "&VLOOKUP(B17,'0. Instruções'!$C$27:$G$32,4,FALSE)&"_SIMUL, "&F17&" AS "&F17&"_SIMUL FROM "&E17&" WHERE "&'0. Instruções'!$D$43&")Y" -> (SELECT a AS a_SIMUL, ccontab_final AS ccontab_final_SIMUL FROM BU_LOANTAPE_WORK.SIMUL_LT001 WHERE ref_date='${ref_date}' AND nome_perimetro='Individual Local' AND segmento='ESTR' AND ambito='PILAR3' AND entidade='00100')Y | K17: =+UPPER("ON X."&VLOOKUP(B17,'0. Instruções'!$C$27:$G$32,4,FALSE)&"=Y."&VLOOKUP(B17,'0. Instruções'!$C$27:$G$32,4,FALSE)&"_SIMUL") -> ON X.A=Y.A_SIMUL | L17: =+IF(C17="Coerência", +IF(LEFT(G17,5)="FLOAT","SELECT '"&UPPER(B17)&"' AS TABELA, '"&UPPER(C17)&"' AS TIPOLOGIA_TESTE,'"&D17&"' AS TABELA_LT,'"&E17&"' AS TABELA_SIMUL,'"&F17&"' AS CAMPO, "&"'${ref_date}' AS REF_DATE, COUNT(*) AS NUM_REG, SUM(IF((ABS(COALESCE(CAST(X."&F17&" AS DECIMAL(18,6)),0)-COALESCE(CAST(Y."&F17&"_SIMUL AS DECIMAL(18,6)),0))>0.000001) OR (X."&F17&" IS NULL AND Y."&F17&"_SIMUL IS NOT NULL ) OR (X."&F17&" IS NOT NULL AND Y."&F17&"_SIMUL IS NULL),1,0)) AS NUM_REG_DIF,'"&MAX('ID1&5'!K:K)+1&"' AS ID_EXEC, CURRENT_TIMESTAMP() AS TIME_EXEC FROM "&I17&" INNER JOIN "&J17&" "&K17,"SELECT '"&UPPER(B17)&"' AS TABELA, '"&UPPER(C17)&"' AS TIPOLOGIA_TESTE,'"&D17&"' AS TABELA_LT,'"&E17&"' AS TABELA_SIMUL,'"&F17&"' AS CAMPO, "&"'${ref_date}' AS REF_DATE, COUNT(*) AS NUM_REG, SUM(IF(COALESCE(CAST(X."&F17&" AS STRING),'')<>COALESCE(CAST(Y."&F17&"_SIMUL AS STRING),'') OR (X."&F17&" IS NULL AND Y."&F17&"_SIMUL IS NOT NULL ) OR (X."&F17&" IS NOT NULL AND Y."&F17&"_SIMUL IS NULL),1,0)) AS NUM_REG_DIF,'"&MAX('ID1&5'!L:L)+1&"' AS ID_EXEC, CURRENT_TIMESTAMP() AS TIME_EXEC FROM "&I17&" INNER JOIN "&J17&" "&K17), IF(C17="Validade",+IF(G17="Code List","SELECT '"&UPPER(B17)&"' AS TABELA, '"&UPPER(C17)&"' AS TIPOLOGIA_TESTE,'"&D17&"' AS TABELA_LT,'N/A' AS TABELA_SIMUL,'"&F17&"' AS CAMPO, "&"'${ref_date}' AS REF_DATE, COUNT(*) AS NUM_REG, SUM(IF(TRIM(CAST(X."&F17&" AS STRING))='' OR TRIM(CAST(X."&F17&" AS STRING)) IS NULL OR CAST(X."&F17&" AS STRING) NOT "&H17&",1,0)) AS NUM_REG_DIF,'"&MAX('ID1&5'!K:K)+1&"' AS ID_EXEC, CURRENT_TIMESTAMP() AS TIME_EXEC FROM "&I17,"SELECT '"&UPPER(B17)&"' AS TABELA, '"&UPPER(C17)&"' AS TIPOLOGIA_TESTE,'"&D17&"' AS TABELA_LT,'N/A' AS TABELA_SIMUL,'"&F17&"' AS CAMPO, "&"'${ref_date}' AS REF_DATE, COUNT(*) AS NUM_REG, SUM(IF(TRIM(CAST(X."&F17&" AS STRING))='' OR TRIM(CAST(X."&F17&" AS STRING)) IS NULL,1,0)) AS NUM_REG_DIF,'"&MAX('ID1&5'!K:K)+1&"' AS ID_EXEC, CURRENT_TIMESTAMP() AS TIME_EXEC FROM "&I17), IF(C17="Caracteres Especiais",+"SELECT '"&UPPER(B17)&"' AS TABELA, '"&UPPER(C17)&"' AS TIPOLOGIA_TESTE,'"&D17&"' AS TABELA_LT,'N/A' AS TABELA_SIMUL,'"&F17&"' AS CAMPO, "&"'${ref_date}' AS REF_DATE, COUNT(*) AS NUM_REG, SUM(IF(REGEXP_REPLACE(TRIM(CAST(X."&F17&" AS STRING)),'[^a-zA-Z0-9_\\s]','') <>TRIM(CAST(X."&F17&" AS STRING)),1,0)) AS NUM_REG_DIF,'"&MAX('ID1&5'!K:K)+1&"' AS ID_EXEC, CURRENT_TIMESTAMP() AS TIME_EXEC FROM "&I17, IF(C17="Missings",+"SELECT '"&UPPER(B17)&"' AS TABELA, '"&UPPER(C17)&"' AS TIPOLOGIA_TESTE,'"&D17&"' AS TABELA_LT,'N/A' AS TABELA_SIMUL,'"&F17&"' AS CAMPO, "&"'${ref_date}' AS REF_DATE, COUNT(*) AS NUM_REG, SUM(IF(TRIM(CAST(X."&F17&" AS STRING)) IN ('0000-00-00','0001-01-01','9999-12-31','MISS','00000','99999999999','99999999999.00','99999999999.000000'),1,0)) AS NUM_REG_DIF,'"&MAX('ID1&5'!K:K)+1&"' AS ID_EXEC, CURRENT_TIMESTAMP() AS TIME_EXEC FROM "&I17, IF(C17="Not applicable",+"SELECT '"&UPPER(B17)&"' AS TABELA, '"&UPPER(C17)&"' AS TIPOLOGIA_TESTE,'"&D17&"' AS TABELA_LT,'N/A' AS TABELA_SIMUL,'"&F17&"' AS CAMPO, "&"'${ref_date}' AS REF_DATE, COUNT(*) AS NUM_REG, SUM(IF(TRIM(CAST(X."&F17&" AS STRING)) IN ('N/A','11111111111','11111111111.00','11111111111.000000','1111-11-11'),1,0)) AS NUM_REG_DIF,'"&MAX('ID1&5'!K:K)+1&"' AS ID_EXEC, CURRENT_TIMESTAMP() AS TIME_EXEC FROM "&I17, IF(C17="Valores extremos",+"SELECT '"&UPPER(B17)&"' AS TABELA, '"&UPPER(C17)&"' AS TIPOLOGIA_TESTE,'"&D17&"' AS TABELA_LT,'N/A' AS TABELA_SIMUL,'"&F17&"' AS CAMPO, "&"'${ref_date}' AS REF_DATE, CAST(MIN("&F17&") AS STRING) AS VALOR_MIN, CAST(MAX("&F17&") AS STRING) AS VALOR_MAX,'"&MAX('ID1&5'!K:K)+1&"' AS ID_EXEC, CURRENT_TIMESTAMP() AS TIME_EXEC FROM "&MID(I17,1,LEN(I17)-2)&" AND CAST("&F17&" AS STRING) NOT IN ('0000-00-00','0001-01-01','9999-12-31','MISS','00000','99999999999','99999999999.00','99999999999.000000','N/A','11111111111','11111111111.00','11111111111.000000','1111-11-11'))X")))))) -> SELECT 'UNIV_OPER' AS TABELA, 'COERÊNCIA' AS TIPOLOGIA_TESTE,'BU_LOANTAPE_WORK.LT001_UNIV_OPER' AS TABELA_LT,'BU_LOANTAPE_WORK.SIMUL_LT001' AS TABELA_SIMUL,'ccontab_final' AS CAMPO, '${ref_date}' AS REF_DATE, COUNT(*) AS NUM_REG, SUM(IF(COALESCE(CAST(X.ccontab_final AS STRING),'')<>COALESCE(CAST(Y.ccontab_final_SIMUL AS STRING),'') OR (X.ccontab_final IS NULL AND Y.ccontab_final_SIMUL IS NOT NULL ) OR (X.ccontab_final IS NOT NULL AND Y.ccontab_final_SIMUL IS NULL),1,0)) AS NUM_REG_DIF,'1' AS ID_EXEC, CURRENT_TIMESTAMP() AS TIME_EXEC FROM (SELECT a, ccontab_final FROM BU_LOANTAPE_WORK.LT001_UNIV_OPER WHERE ref_date='${ref_date}' AND nome_perimetro='Individual Local' AND segmento='ESTR' AND ambito='SRB_MBDT' AND entidade='00100')X INNER JOIN (SELECT a AS a_SIMUL, ccontab_final AS ccontab_final_SIMUL FROM BU_LOANTAPE_WORK.SIMUL_LT001 WHERE ref_date='${ref_date}' AND nome_perimetro='Individual Local' AND segmento='ESTR' AND ambito='PILAR3' AND entidade='00100')Y ON X.A=Y.A_SIMUL | M17: =+"UNION ALL "&L17 -> UNION ALL SELECT 'UNIV_OPER' AS TABELA, 'COERÊNCIA' AS TIPOLOGIA_TESTE,'BU_LOANTAPE_WORK.LT001_UNIV_OPER' AS TABELA_LT,'BU_LOANTAPE_WORK.SIMUL_LT001' AS TABELA_SIMUL,'ccontab_final' AS CAMPO, '${ref_date}' AS REF_DATE, COUNT(*) AS NUM_REG, SUM(IF(COALESCE(CAST(X.ccontab_final AS STRING),'')<>COALESCE(CAST(Y.ccontab_final_SIMUL AS STRING),'') OR (X.ccontab_final IS NULL AND Y.ccontab_final_SIMUL IS NOT NULL ) OR (X.ccontab_final IS NOT NULL AND Y.ccontab_final_SIMUL IS NULL),1,0)) AS NUM_REG_DIF,'1' AS ID_EXEC, CURRENT_TIMESTAMP() AS TIME_EXEC FROM (SELECT a, ccontab_final FROM BU_LOANTAPE_WORK.LT001_UNIV_OPER WHERE ref_date='${ref_date}' AND nome_perimetro='Individual Local' AND segmento='ESTR' AND ambito='SRB_MBDT' AND entidade='00100')X INNER JOIN (SELECT a AS a_SIMUL, ccontab_final AS ccontab_final_SIMUL FROM BU_LOANTAPE_WORK.SIMUL_LT001 WHERE ref_date='${ref_date}' AND nome_perimetro='Individual Local' AND segmento='ESTR' AND ambito='PILAR3' AND entidade='00100')Y ON X.A=Y.A_SIMUL
A18: =+B18&F18 -> UNIV_OPERmsaldo_final | B18: UNIV_OPER | C18: Coerência | D18: =+UPPER('0. Instruções'!$D$35&"."&VLOOKUP(B18,'0. Instruções'!$C$27:$D$32,2,FALSE)) -> BU_LOANTAPE_WORK.LT001_UNIV_OPER | E18: =+UPPER('0. Instruções'!$D$36&"."&VLOOKUP(B18,'0. Instruções'!$C$27:$E$32,3,FALSE)) -> BU_LOANTAPE_WORK.SIMUL_LT001 | F18: msaldo_final | I18: ="(SELECT "&VLOOKUP(B18,'0. Instruções'!$C$27:$G$32,4,FALSE)&", "&F18&" FROM "&D18&" WHERE "&'0. Instruções'!$D$42&")X" -> (SELECT a, msaldo_final FROM BU_LOANTAPE_WORK.LT001_UNIV_OPER WHERE ref_date='${ref_date}' AND nome_perimetro='Individual Local' AND segmento='ESTR' AND ambito='SRB_MBDT' AND entidade='00100')X | J18: ="(SELECT "&VLOOKUP(B18,'0. Instruções'!$C$27:$G$32,4,FALSE)&" AS "&VLOOKUP(B18,'0. Instruções'!$C$27:$G$32,4,FALSE)&"_SIMUL, "&F18&" AS "&F18&"_SIMUL FROM "&E18&" WHERE "&'0. Instruções'!$D$43&")Y" -> (SELECT a AS a_SIMUL, msaldo_final AS msaldo_final_SIMUL FROM BU_LOANTAPE_WORK.SIMUL_LT001 WHERE ref_date='${ref_date}' AND nome_perimetro='Individual Local' AND segmento='ESTR' AND ambito='PILAR3' AND entidade='00100')Y | K18: =+UPPER("ON X."&VLOOKUP(B18,'0. Instruções'!$C$27:$G$32,4,FALSE)&"=Y."&VLOOKUP(B18,'0. Instruções'!$C$27:$G$32,4,FALSE)&"_SIMUL") -> ON X.A=Y.A_SIMUL | L18: =+IF(C18="Coerência", +IF(LEFT(G18,5)="FLOAT","SELECT '"&UPPER(B18)&"' AS TABELA, '"&UPPER(C18)&"' AS TIPOLOGIA_TESTE,'"&D18&"' AS TABELA_LT,'"&E18&"' AS TABELA_SIMUL,'"&F18&"' AS CAMPO, "&"'${ref_date}' AS REF_DATE, COUNT(*) AS NUM_REG, SUM(IF((ABS(COALESCE(CAST(X."&F18&" AS DECIMAL(18,6)),0)-COALESCE(CAST(Y."&F18&"_SIMUL AS DECIMAL(18,6)),0))>0.000001) OR (X."&F18&" IS NULL AND Y."&F18&"_SIMUL IS NOT NULL ) OR (X."&F18&" IS NOT NULL AND Y."&F18&"_SIMUL IS NULL),1,0)) AS NUM_REG_DIF,'"&MAX('ID1&5'!K:K)+1&"' AS ID_EXEC, CURRENT_TIMESTAMP() AS TIME_EXEC FROM "&I18&" INNER JOIN "&J18&" "&K18,"SELECT '"&UPPER(B18)&"' AS TABELA, '"&UPPER(C18)&"' AS TIPOLOGIA_TESTE,'"&D18&"' AS TABELA_LT,'"&E18&"' AS TABELA_SIMUL,'"&F18&"' AS CAMPO, "&"'${ref_date}' AS REF_DATE, COUNT(*) AS NUM_REG, SUM(IF(COALESCE(CAST(X."&F18&" AS STRING),'')<>COALESCE(CAST(Y."&F18&"_SIMUL AS STRING),'') OR (X."&F18&" IS NULL AND Y."&F18&"_SIMUL IS NOT NULL ) OR (X."&F18&" IS NOT NULL AND Y."&F18&"_SIMUL IS NULL),1,0)) AS NUM_REG_DIF,'"&MAX('ID1&5'!L:L)+1&"' AS ID_EXEC, CURRENT_TIMESTAMP() AS TIME_EXEC FROM "&I18&" INNER JOIN "&J18&" "&K18), IF(C18="Validade",+IF(G18="Code List","SELECT '"&UPPER(B18)&"' AS TABELA, '"&UPPER(C18)&"' AS TIPOLOGIA_TESTE,'"&D18&"' AS TABELA_LT,'N/A' AS TABELA_SIMUL,'"&F18&"' AS CAMPO, "&"'${ref_date}' AS REF_DATE, COUNT(*) AS NUM_REG, SUM(IF(TRIM(CAST(X."&F18&" AS STRING))='' OR TRIM(CAST(X."&F18&" AS STRING)) IS NULL OR CAST(X."&F18&" AS STRING) NOT "&H18&",1,0)) AS NUM_REG_DIF,'"&MAX('ID1&5'!K:K)+1&"' AS ID_EXEC, CURRENT_TIMESTAMP() AS TIME_EXEC FROM "&I18,"SELECT '"&UPPER(B18)&"' AS TABELA, '"&UPPER(C18)&"' AS TIPOLOGIA_TESTE,'"&D18&"' AS TABELA_LT,'N/A' AS TABELA_SIMUL,'"&F18&"' AS CAMPO, "&"'${ref_date}' AS REF_DATE, COUNT(*) AS NUM_REG, SUM(IF(TRIM(CAST(X."&F18&" AS STRING))='' OR TRIM(CAST(X."&F18&" AS STRING)) IS NULL,1,0)) AS NUM_REG_DIF,'"&MAX('ID1&5'!K:K)+1&"' AS ID_EXEC, CURRENT_TIMESTAMP() AS TIME_EXEC FROM "&I18), IF(C18="Caracteres Especiais",+"SELECT '"&UPPER(B18)&"' AS TABELA, '"&UPPER(C18)&"' AS TIPOLOGIA_TESTE,'"&D18&"' AS TABELA_LT,'N/A' AS TABELA_SIMUL,'"&F18&"' AS CAMPO, "&"'${ref_date}' AS REF_DATE, COUNT(*) AS NUM_REG, SUM(IF(REGEXP_REPLACE(TRIM(CAST(X."&F18&" AS STRING)),'[^a-zA-Z0-9_\\s]','') <>TRIM(CAST(X."&F18&" AS STRING)),1,0)) AS NUM_REG_DIF,'"&MAX('ID1&5'!K:K)+1&"' AS ID_EXEC, CURRENT_TIMESTAMP() AS TIME_EXEC FROM "&I18, IF(C18="Missings",+"SELECT '"&UPPER(B18)&"' AS TABELA, '"&UPPER(C18)&"' AS TIPOLOGIA_TESTE,'"&D18&"' AS TABELA_LT,'N/A' AS TABELA_SIMUL,'"&F18&"' AS CAMPO, "&"'${ref_date}' AS REF_DATE, COUNT(*) AS NUM_REG, SUM(IF(TRIM(CAST(X."&F18&" AS STRING)) IN ('0000-00-00','0001-01-01','9999-12-31','MISS','00000','99999999999','99999999999.00','99999999999.000000'),1,0)) AS NUM_REG_DIF,'"&MAX('ID1&5'!K:K)+1&"' AS ID_EXEC, CURRENT_TIMESTAMP() AS TIME_EXEC FROM "&I18, IF(C18="Not applicable",+"SELECT '"&UPPER(B18)&"' AS TABELA, '"&UPPER(C18)&"' AS TIPOLOGIA_TESTE,'"&D18&"' AS TABELA_LT,'N/A' AS TABELA_SIMUL,'"&F18&"' AS CAMPO, "&"'${ref_date}' AS REF_DATE, COUNT(*) AS NUM_REG, SUM(IF(TRIM(CAST(X."&F18&" AS STRING)) IN ('N/A','11111111111','11111111111.00','11111111111.000000','1111-11-11'),1,0)) AS NUM_REG_DIF,'"&MAX('ID1&5'!K:K)+1&"' AS ID_EXEC, CURRENT_TIMESTAMP() AS TIME_EXEC FROM "&I18, IF(C18="Valores extremos",+"SELECT '"&UPPER(B18)&"' AS TABELA, '"&UPPER(C18)&"' AS TIPOLOGIA_TESTE,'"&D18&"' AS TABELA_LT,'N/A' AS TABELA_SIMUL,'"&F18&"' AS CAMPO, "&"'${ref_date}' AS REF_DATE, CAST(MIN("&F18&") AS STRING) AS VALOR_MIN, CAST(MAX("&F18&") AS STRING) AS VALOR_MAX,'"&MAX('ID1&5'!K:K)+1&"' AS ID_EXEC, CURRENT_TIMESTAMP() AS TIME_EXEC FROM "&MID(I18,1,LEN(I18)-2)&" AND CAST("&F18&" AS STRING) NOT IN ('0000-00-00','0001-01-01','9999-12-31','MISS','00000','99999999999','99999999999.00','99999999999.000000','N/A','11111111111','11111111111.00','11111111111.000000','1111-11-11'))X")))))) -> SELECT 'UNIV_OPER' AS TABELA, 'COERÊNCIA' AS TIPOLOGIA_TESTE,'BU_LOANTAPE_WORK.LT001_UNIV_OPER' AS TABELA_LT,'BU_LOANTAPE_WORK.SIMUL_LT001' AS TABELA_SIMUL,'msaldo_final' AS CAMPO, '${ref_date}' AS REF_DATE, COUNT(*) AS NUM_REG, SUM(IF(COALESCE(CAST(X.msaldo_final AS STRING),'')<>COALESCE(CAST(Y.msaldo_final_SIMUL AS STRING),'') OR (X.msaldo_final IS NULL AND Y.msaldo_final_SIMUL IS NOT NULL ) OR (X.msaldo_final IS NOT NULL AND Y.msaldo_final_SIMUL IS NULL),1,0)) AS NUM_REG_DIF,'1' AS ID_EXEC, CURRENT_TIMESTAMP() AS TIME_EXEC FROM (SELECT a, msaldo_final FROM BU_LOANTAPE_WORK.LT001_UNIV_OPER WHERE ref_date='${ref_date}' AND nome_perimetro='Individual Local' AND segmento='ESTR' AND ambito='SRB_MBDT' AND entidade='00100')X INNER JOIN (SELECT a AS a_SIMUL, msaldo_final AS msaldo_final_SIMUL FROM BU_LOANTAPE_WORK.SIMUL_LT001 WHERE ref_date='${ref_date}' AND nome_perimetro='Individual Local' AND segmento='ESTR' AND ambito='PILAR3' AND entidade='00100')Y ON X.A=Y.A_SIMUL | M18: =+"UNION ALL "&L18 -> UNION ALL SELECT 'UNIV_OPER' AS TABELA, 'COERÊNCIA' AS TIPOLOGIA_TESTE,'BU_LOANTAPE_WORK.LT001_UNIV_OPER' AS TABELA_LT,'BU_LOANTAPE_WORK.SIMUL_LT001' AS TABELA_SIMUL,'msaldo_final' AS CAMPO, '${ref_date}' AS REF_DATE, COUNT(*) AS NUM_REG, SUM(IF(COALESCE(CAST(X.msaldo_final AS STRING),'')<>COALESCE(CAST(Y.msaldo_final_SIMUL AS STRING),'') OR (X.msaldo_final IS NULL AND Y.msaldo_final_SIMUL IS NOT NULL ) OR (X.msaldo_final IS NOT NULL AND Y.msaldo_final_SIMUL IS NULL),1,0)) AS NUM_REG_DIF,'1' AS ID_EXEC, CURRENT_TIMESTAMP() AS TIME_EXEC FROM (SELECT a, msaldo_final FROM BU_LOANTAPE_WORK.LT001_UNIV_OPER WHERE ref_date='${ref_date}' AND nome_perimetro='Individual Local' AND segmento='ESTR' AND ambito='SRB_MBDT' AND entidade='00100')X INNER JOIN (SELECT a AS a_SIMUL, msaldo_final AS msaldo_final_SIMUL FROM BU_LOANTAPE_WORK.SIMUL_LT001 WHERE ref_date='${ref_date}' AND nome_perimetro='Individual Local' AND segmento='ESTR' AND ambito='PILAR3' AND entidade='00100')Y ON X.A=Y.A_SIMUL
A19: =+B19&F19 -> UNIV_OPERcarteira_contabilistica | B19: UNIV_OPER | C19: Coerência | D19: =+UPPER('0. Instruções'!$D$35&"."&VLOOKUP(B19,'0. Instruções'!$C$27:$D$32,2,FALSE)) -> BU_LOANTAPE_WORK.LT001_UNIV_OPER | E19: =+UPPER('0. Instruções'!$D$36&"."&VLOOKUP(B19,'0. Instruções'!$C$27:$E$32,3,FALSE)) -> BU_LOANTAPE_WORK.SIMUL_LT001 | F19: carteira_contabilistica | I19: ="(SELECT "&VLOOKUP(B19,'0. Instruções'!$C$27:$G$32,4,FALSE)&", "&F19&" FROM "&D19&" WHERE "&'0. Instruções'!$D$42&")X" -> (SELECT a, carteira_contabilistica FROM BU_LOANTAPE_WORK.LT001_UNIV_OPER WHERE ref_date='${ref_date}' AND nome_perimetro='Individual Local' AND segmento='ESTR' AND ambito='SRB_MBDT' AND entidade='00100')X | J19: ="(SELECT "&VLOOKUP(B19,'0. Instruções'!$C$27:$G$32,4,FALSE)&" AS "&VLOOKUP(B19,'0. Instruções'!$C$27:$G$32,4,FALSE)&"_SIMUL, "&F19&" AS "&F19&"_SIMUL FROM "&E19&" WHERE "&'0. Instruções'!$D$43&")Y" -> (SELECT a AS a_SIMUL, carteira_contabilistica AS carteira_contabilistica_SIMUL FROM BU_LOANTAPE_WORK.SIMUL_LT001 WHERE ref_date='${ref_date}' AND nome_perimetro='Individual Local' AND segmento='ESTR' AND ambito='PILAR3' AND entidade='00100')Y | K19: =+UPPER("ON X."&VLOOKUP(B19,'0. Instruções'!$C$27:$G$32,4,FALSE)&"=Y."&VLOOKUP(B19,'0. Instruções'!$C$27:$G$32,4,FALSE)&"_SIMUL") -> ON X.A=Y.A_SIMUL | L19: =+IF(C19="Coerência", +IF(LEFT(G19,5)="FLOAT","SELECT '"&UPPER(B19)&"' AS TABELA, '"&UPPER(C19)&"' AS TIPOLOGIA_TESTE,'"&D19&"' AS TABELA_LT,'"&E19&"' AS TABELA_SIMUL,'"&F19&"' AS CAMPO, "&"'${ref_date}' AS REF_DATE, COUNT(*) AS NUM_REG, SUM(IF((ABS(COALESCE(CAST(X."&F19&" AS DECIMAL(18,6)),0)-COALESCE(CAST(Y."&F19&"_SIMUL AS DECIMAL(18,6)),0))>0.000001) OR (X."&F19&" IS NULL AND Y."&F19&"_SIMUL IS NOT NULL ) OR (X."&F19&" IS NOT NULL AND Y."&F19&"_SIMUL IS NULL),1,0)) AS NUM_REG_DIF,'"&MAX('ID1&5'!K:K)+1&"' AS ID_EXEC, CURRENT_TIMESTAMP() AS TIME_EXEC FROM "&I19&" INNER JOIN "&J19&" "&K19,"SELECT '"&UPPER(B19)&"' AS TABELA, '"&UPPER(C19)&"' AS TIPOLOGIA_TESTE,'"&D19&"' AS TABELA_LT,'"&E19&"' AS TABELA_SIMUL,'"&F19&"' AS CAMPO, "&"'${ref_date}' AS REF_DATE, COUNT(*) AS NUM_REG, SUM(IF(COALESCE(CAST(X."&F19&" AS STRING),'')<>COALESCE(CAST(Y."&F19&"_SIMUL AS STRING),'') OR (X."&F19&" IS NULL AND Y."&F19&"_SIMUL IS NOT NULL ) OR (X."&F19&" IS NOT NULL AND Y."&F19&"_SIMUL IS NULL),1,0)) AS NUM_REG_DIF,'"&MAX('ID1&5'!L:L)+1&"' AS ID_EXEC, CURRENT_TIMESTAMP() AS TIME_EXEC FROM "&I19&" INNER JOIN "&J19&" "&K19), IF(C19="Validade",+IF(G19="Code List","SELECT '"&UPPER(B19)&"' AS TABELA, '"&UPPER(C19)&"' AS TIPOLOGIA_TESTE,'"&D19&"' AS TABELA_LT,'N/A' AS TABELA_SIMUL,'"&F19&"' AS CAMPO, "&"'${ref_date}' AS REF_DATE, COUNT(*) AS NUM_REG, SUM(IF(TRIM(CAST(X."&F19&" AS STRING))='' OR TRIM(CAST(X."&F19&" AS STRING)) IS NULL OR CAST(X."&F19&" AS STRING) NOT "&H19&",1,0)) AS NUM_REG_DIF,'"&MAX('ID1&5'!K:K)+1&"' AS ID_EXEC, CURRENT_TIMESTAMP() AS TIME_EXEC FROM "&I19,"SELECT '"&UPPER(B19)&"' AS TABELA, '"&UPPER(C19)&"' AS TIPOLOGIA_TESTE,'"&D19&"' AS TABELA_LT,'N/A' AS TABELA_SIMUL,'"&F19&"' AS CAMPO, "&"'${ref_date}' AS REF_DATE, COUNT(*) AS NUM_REG, SUM(IF(TRIM(CAST(X."&F19&" AS STRING))='' OR TRIM(CAST(X."&F19&" AS STRING)) IS NULL,1,0)) AS NUM_REG_DIF,'"&MAX('ID1&5'!K:K)+1&"' AS ID_EXEC, CURRENT_TIMESTAMP() AS TIME_EXEC FROM "&I19), IF(C19="Caracteres Especiais",+"SELECT '"&UPPER(B19)&"' AS TABELA, '"&UPPER(C19)&"' AS TIPOLOGIA_TESTE,'"&D19&"' AS TABELA_LT,'N/A' AS TABELA_SIMUL,'"&F19&"' AS CAMPO, "&"'${ref_date}' AS REF_DATE, COUNT(*) AS NUM_REG, SUM(IF(REGEXP_REPLACE(TRIM(CAST(X."&F19&" AS STRING)),'[^a-zA-Z0-9_\\s]','') <>TRIM(CAST(X."&F19&" AS STRING)),1,0)) AS NUM_REG_DIF,'"&MAX('ID1&5'!K:K)+1&"' AS ID_EXEC, CURRENT_TIMESTAMP() AS TIME_EXEC FROM "&I19, IF(C19="Missings",+"SELECT '"&UPPER(B19)&"' AS TABELA, '"&UPPER(C19)&"' AS TIPOLOGIA_TESTE,'"&D19&"' AS TABELA_LT,'N/A' AS TABELA_SIMUL,'"&F19&"' AS CAMPO, "&"'${ref_date}' AS REF_DATE, COUNT(*) AS NUM_REG, SUM(IF(TRIM(CAST(X."&F19&" AS STRING)) IN ('0000-00-00','0001-01-01','9999-12-31','MISS','00000','99999999999','99999999999.00','99999999999.000000'),1,0)) AS NUM_REG_DIF,'"&MAX('ID1&5'!K:K)+1&"' AS ID_EXEC, CURRENT_TIMESTAMP() AS TIME_EXEC FROM "&I19, IF(C19="Not applicable",+"SELECT '"&UPPER(B19)&"' AS TABELA, '"&UPPER(C19)&"' AS TIPOLOGIA_TESTE,'"&D19&"' AS TABELA_LT,'N/A' AS TABELA_SIMUL,'"&F19&"' AS CAMPO, "&"'${ref_date}' AS REF_DATE, COUNT(*) AS NUM_REG, SUM(IF(TRIM(CAST(X."&F19&" AS STRING)) IN ('N/A','11111111111','11111111111.00','11111111111.000000','1111-11-11'),1,0)) AS NUM_REG_DIF,'"&MAX('ID1&5'!K:K)+1&"' AS ID_EXEC, CURRENT_TIMESTAMP() AS TIME_EXEC FROM "&I19, IF(C19="Valores extremos",+"SELECT '"&UPPER(B19)&"' AS TABELA, '"&UPPER(C19)&"' AS TIPOLOGIA_TESTE,'"&D19&"' AS TABELA_LT,'N/A' AS TABELA_SIMUL,'"&F19&"' AS CAMPO, "&"'${ref_date}' AS REF_DATE, CAST(MIN("&F19&") AS STRING) AS VALOR_MIN, CAST(MAX("&F19&") AS STRING) AS VALOR_MAX,'"&MAX('ID1&5'!K:K)+1&"' AS ID_EXEC, CURRENT_TIMESTAMP() AS TIME_EXEC FROM "&MID(I19,1,LEN(I19)-2)&" AND CAST("&F19&" AS STRING) NOT IN ('0000-00-00','0001-01-01','9999-12-31','MISS','00000','99999999999','99999999999.00','99999999999.000000','N/A','11111111111','11111111111.00','11111111111.000000','1111-11-11'))X")))))) -> SELECT 'UNIV_OPER' AS TABELA, 'COERÊNCIA' AS TIPOLOGIA_TESTE,'BU_LOANTAPE_WORK.LT001_UNIV_OPER' AS TABELA_LT,'BU_LOANTAPE_WORK.SIMUL_LT001' AS TABELA_SIMUL,'carteira_contabilistica' AS CAMPO, '${ref_date}' AS REF_DATE, COUNT(*) AS NUM_REG, SUM(IF(COALESCE(CAST(X.carteira_contabilistica AS STRING),'')<>COALESCE(CAST(Y.carteira_contabilistica_SIMUL AS STRING),'') OR (X.carteira_contabilistica IS NULL AND Y.carteira_contabilistica_SIMUL IS NOT NULL ) OR (X.carteira_contabilistica IS NOT NULL AND Y.carteira_contabilistica_SIMUL IS NULL),1,0)) AS NUM_REG_DIF,'1' AS ID_EXEC, CURRENT_TIMESTAMP() AS TIME_EXEC FROM (SELECT a, carteira_contabilistica FROM BU_LOANTAPE_WORK.LT001_UNIV_OPER WHERE ref_date='${ref_date}' AND nome_perimetro='Individual Local' AND segmento='ESTR' AND ambito='SRB_MBDT' AND entidade='00100')X INNER JOIN (SELECT a AS a_SIMUL, carteira_contabilistica AS carteira_contabilistica_SIMUL FROM BU_LOANTAPE_WORK.SIMUL_LT001 WHERE ref_date='${ref_date}' AND nome_perimetro='Individual Local' AND segmento='ESTR' AND ambito='PILAR3' AND entidade='00100')Y ON X.A=Y.A_SIMUL | M19: =+"UNION ALL "&L19 -> UNION ALL SELECT 'UNIV_OPER' AS TABELA, 'COERÊNCIA' AS TIPOLOGIA_TESTE,'BU_LOANTAPE_WORK.LT001_UNIV_OPER' AS TABELA_LT,'BU_LOANTAPE_WORK.SIMUL_LT001' AS TABELA_SIMUL,'carteira_contabilistica' AS CAMPO, '${ref_date}' AS REF_DATE, COUNT(*) AS NUM_REG, SUM(IF(COALESCE(CAST(X.carteira_contabilistica AS STRING),'')<>COALESCE(CAST(Y.carteira_contabilistica_SIMUL AS STRING),'') OR (X.carteira_contabilistica IS NULL AND Y.carteira_contabilistica_SIMUL IS NOT NULL ) OR (X.carteira_contabilistica IS NOT NULL AND Y.carteira_contabilistica_SIMUL IS NULL),1,0)) AS NUM_REG_DIF,'1' AS ID_EXEC, CURRENT_TIMESTAMP() AS TIME_EXEC FROM (SELECT a, carteira_contabilistica FROM BU_LOANTAPE_WORK.LT001_UNIV_OPER WHERE ref_date='${ref_date}' AND nome_perimetro='Individual Local' AND segmento='ESTR' AND ambito='SRB_MBDT' AND entidade='00100')X INNER JOIN (SELECT a AS a_SIMUL, carteira_contabilistica AS carteira_contabilistica_SIMUL FROM BU_LOANTAPE_WORK.SIMUL_LT001 WHERE ref_date='${ref_date}' AND nome_perimetro='Individual Local' AND segmento='ESTR' AND ambito='PILAR3' AND entidade='00100')Y ON X.A=Y.A_SIMUL
A20: =+B20&F20 -> UNIV_OPERinstrumento_financeiro | B20: UNIV_OPER | C20: Coerência | D20: =+UPPER('0. Instruções'!$D$35&"."&VLOOKUP(B20,'0. Instruções'!$C$27:$D$32,2,FALSE)) -> BU_LOANTAPE_WORK.LT001_UNIV_OPER | E20: =+UPPER('0. Instruções'!$D$36&"."&VLOOKUP(B20,'0. Instruções'!$C$27:$E$32,3,FALSE)) -> BU_LOANTAPE_WORK.SIMUL_LT001 | F20: instrumento_financeiro | I20: ="(SELECT "&VLOOKUP(B20,'0. Instruções'!$C$27:$G$32,4,FALSE)&", "&F20&" FROM "&D20&" WHERE "&'0. Instruções'!$D$42&")X" -> (SELECT a, instrumento_financeiro FROM BU_LOANTAPE_WORK.LT001_UNIV_OPER WHERE ref_date='${ref_date}' AND nome_perimetro='Individual Local' AND segmento='ESTR' AND ambito='SRB_MBDT' AND entidade='00100')X | J20: ="(SELECT "&VLOOKUP(B20,'0. Instruções'!$C$27:$G$32,4,FALSE)&" AS "&VLOOKUP(B20,'0. Instruções'!$C$27:$G$32,4,FALSE)&"_SIMUL, "&F20&" AS "&F20&"_SIMUL FROM "&E20&" WHERE "&'0. Instruções'!$D$43&")Y" -> (SELECT a AS a_SIMUL, instrumento_financeiro AS instrumento_financeiro_SIMUL FROM BU_LOANTAPE_WORK.SIMUL_LT001 WHERE ref_date='${ref_date}' AND nome_perimetro='Individual Local' AND segmento='ESTR' AND ambito='PILAR3' AND entidade='00100')Y | K20: =+UPPER("ON X."&VLOOKUP(B20,'0. Instruções'!$C$27:$G$32,4,FALSE)&"=Y."&VLOOKUP(B20,'0. Instruções'!$C$27:$G$32,4,FALSE)&"_SIMUL") -> ON X.A=Y.A_SIMUL | L20: =+IF(C20="Coerência", +IF(LEFT(G20,5)="FLOAT","SELECT '"&UPPER(B20)&"' AS TABELA, '"&UPPER(C20)&"' AS TIPOLOGIA_TESTE,'"&D20&"' AS TABELA_LT,'"&E20&"' AS TABELA_SIMUL,'"&F20&"' AS CAMPO, "&"'${ref_date}' AS REF_DATE, COUNT(*) AS NUM_REG, SUM(IF((ABS(COALESCE(CAST(X."&F20&" AS DECIMAL(18,6)),0)-COALESCE(CAST(Y."&F20&"_SIMUL AS DECIMAL(18,6)),0))>0.000001) OR (X."&F20&" IS NULL AND Y."&F20&"_SIMUL IS NOT NULL ) OR (X."&F20&" IS NOT NULL AND Y."&F20&"_SIMUL IS NULL),1,0)) AS NUM_REG_DIF,'"&MAX('ID1&5'!K:K)+1&"' AS ID_EXEC, CURRENT_TIMESTAMP() AS TIME_EXEC FROM "&I20&" INNER JOIN "&J20&" "&K20,"SELECT '"&UPPER(B20)&"' AS TABELA, '"&UPPER(C20)&"' AS TIPOLOGIA_TESTE,'"&D20&"' AS TABELA_LT,'"&E20&"' AS TABELA_SIMUL,'"&F20&"' AS CAMPO, "&"'${ref_date}' AS REF_DATE, COUNT(*) AS NUM_REG, SUM(IF(COALESCE(CAST(X."&F20&" AS STRING),'')<>COALESCE(CAST(Y."&F20&"_SIMUL AS STRING),'') OR (X."&F20&" IS NULL AND Y."&F20&"_SIMUL IS NOT NULL ) OR (X."&F20&" IS NOT NULL AND Y."&F20&"_SIMUL IS NULL),1,0)) AS NUM_REG_DIF,'"&MAX('ID1&5'!L:L)+1&"' AS ID_EXEC, CURRENT_TIMESTAMP() AS TIME_EXEC FROM "&I20&" INNER JOIN "&J20&" "&K20), IF(C20="Validade",+IF(G20="Code List","SELECT '"&UPPER(B20)&"' AS TABELA, '"&UPPER(C20)&"' AS TIPOLOGIA_TESTE,'"&D20&"' AS TABELA_LT,'N/A' AS TABELA_SIMUL,'"&F20&"' AS CAMPO, "&"'${ref_date}' AS REF_DATE, COUNT(*) AS NUM_REG, SUM(IF(TRIM(CAST(X."&F20&" AS STRING))='' OR TRIM(CAST(X."&F20&" AS STRING)) IS NULL OR CAST(X."&F20&" AS STRING) NOT "&H20&",1,0)) AS NUM_REG_DIF,'"&MAX('ID1&5'!K:K)+1&"' AS ID_EXEC, CURRENT_TIMESTAMP() AS TIME_EXEC FROM "&I20,"SELECT '"&UPPER(B20)&"' AS TABELA, '"&UPPER(C20)&"' AS TIPOLOGIA_TESTE,'"&D20&"' AS TABELA_LT,'N/A' AS TABELA_SIMUL,'"&F20&"' AS CAMPO, "&"'${ref_date}' AS REF_DATE, COUNT(*) AS NUM_REG, SUM(IF(TRIM(CAST(X."&F20&" AS STRING))='' OR TRIM(CAST(X."&F20&" AS STRING)) IS NULL,1,0)) AS NUM_REG_DIF,'"&MAX('ID1&5'!K:K)+1&"' AS ID_EXEC, CURRENT_TIMESTAMP() AS TIME_EXEC FROM "&I20), IF(C20="Caracteres Especiais",+"SELECT '"&UPPER(B20)&"' AS TABELA, '"&UPPER(C20)&"' AS TIPOLOGIA_TESTE,'"&D20&"' AS TABELA_LT,'N/A' AS TABELA_SIMUL,'"&F20&"' AS CAMPO, "&"'${ref_date}' AS REF_DATE, COUNT(*) AS NUM_REG, SUM(IF(REGEXP_REPLACE(TRIM(CAST(X."&F20&" AS STRING)),'[^a-zA-Z0-9_\\s]','') <>TRIM(CAST(X."&F20&" AS STRING)),1,0)) AS NUM_REG_DIF,'"&MAX('ID1&5'!K:K)+1&"' AS ID_EXEC, CURRENT_TIMESTAMP() AS TIME_EXEC FROM "&I20, IF(C20="Missings",+"SELECT '"&UPPER(B20)&"' AS TABELA, '"&UPPER(C20)&"' AS TIPOLOGIA_TESTE,'"&D20&"' AS TABELA_LT,'N/A' AS TABELA_SIMUL,'"&F20&"' AS CAMPO, "&"'${ref_date}' AS REF_DATE, COUNT(*) AS NUM_REG, SUM(IF(TRIM(CAST(X."&F20&" AS STRING)) IN ('0000-00-00','0001-01-01','9999-12-31','MISS','00000','99999999999','99999999999.00','99999999999.000000'),1,0)) AS NUM_REG_DIF,'"&MAX('ID1&5'!K:K)+1&"' AS ID_EXEC, CURRENT_TIMESTAMP() AS TIME_EXEC FROM "&I20, IF(C20="Not applicable",+"SELECT '"&UPPER(B20)&"' AS TABELA, '"&UPPER(C20)&"' AS TIPOLOGIA_TESTE,'"&D20&"' AS TABELA_LT,'N/A' AS TABELA_SIMUL,'"&F20&"' AS CAMPO, "&"'${ref_date}' AS REF_DATE, COUNT(*) AS NUM_REG, SUM(IF(TRIM(CAST(X."&F20&" AS STRING)) IN ('N/A','11111111111','11111111111.00','11111111111.000000','1111-11-11'),1,0)) AS NUM_REG_DIF,'"&MAX('ID1&5'!K:K)+1&"' AS ID_EXEC, CURRENT_TIMESTAMP() AS TIME_EXEC FROM "&I20, IF(C20="Valores extremos",+"SELECT '"&UPPER(B20)&"' AS TABELA, '"&UPPER(C20)&"' AS TIPOLOGIA_TESTE,'"&D20&"' AS TABELA_LT,'N/A' AS TABELA_SIMUL,'"&F20&"' AS CAMPO, "&"'${ref_date}' AS REF_DATE, CAST(MIN("&F20&") AS STRING) AS VALOR_MIN, CAST(MAX("&F20&") AS STRING) AS VALOR_MAX,'"&MAX('ID1&5'!K:K)+1&"' AS ID_EXEC, CURRENT_TIMESTAMP() AS TIME_EXEC FROM "&MID(I20,1,LEN(I20)-2)&" AND CAST("&F20&" AS STRING) NOT IN ('0000-00-00','0001-01-01','9999-12-31','MISS','00000','99999999999','99999999999.00','99999999999.000000','N/A','11111111111','11111111111.00','11111111111.000000','1111-11-11'))X")))))) -> SELECT 'UNIV_OPER' AS TABELA, 'COERÊNCIA' AS TIPOLOGIA_TESTE,'BU_LOANTAPE_WORK.LT001_UNIV_OPER' AS TABELA_LT,'BU_LOANTAPE_WORK.SIMUL_LT001' AS TABELA_SIMUL,'instrumento_financeiro' AS CAMPO, '${ref_date}' AS REF_DATE, COUNT(*) AS NUM_REG, SUM(IF(COALESCE(CAST(X.instrumento_financeiro AS STRING),'')<>COALESCE(CAST(Y.instrumento_financeiro_SIMUL AS STRING),'') OR (X.instrumento_financeiro IS NULL AND Y.instrumento_financeiro_SIMUL IS NOT NULL ) OR (X.instrumento_financeiro IS NOT NULL AND Y.instrumento_financeiro_SIMUL IS NULL),1,0)) AS NUM_REG_DIF,'1' AS ID_EXEC, CURRENT_TIMESTAMP() AS TIME_EXEC FROM (SELECT a, instrumento_financeiro FROM BU_LOANTAPE_WORK.LT001_UNIV_OPER WHERE ref_date='${ref_date}' AND nome_perimetro='Individual Local' AND segmento='ESTR' AND ambito='SRB_MBDT' AND entidade='00100')X INNER JOIN (SELECT a AS a_SIMUL, instrumento_financeiro AS instrumento_financeiro_SIMUL FROM BU_LOANTAPE_WORK.SIMUL_LT001 WHERE ref_date='${ref_date}' AND nome_perimetro='Individual Local' AND segmento='ESTR' AND ambito='PILAR3' AND entidade='00100')Y ON X.A=Y.A_SIMUL | M20: =+"UNION ALL "&L20 -> UNION ALL SELECT 'UNIV_OPER' AS TABELA, 'COERÊNCIA' AS TIPOLOGIA_TESTE,'BU_LOANTAPE_WORK.LT001_UNIV_OPER' AS TABELA_LT,'BU_LOANTAPE_WORK.SIMUL_LT001' AS TABELA_SIMUL,'instrumento_financeiro' AS CAMPO, '${ref_date}' AS REF_DATE, COUNT(*) AS NUM_REG, SUM(IF(COALESCE(CAST(X.instrumento_financeiro AS STRING),'')<>COALESCE(CAST(Y.instrumento_financeiro_SIMUL AS STRING),'') OR (X.instrumento_financeiro IS NULL AND Y.instrumento_financeiro_SIMUL IS NOT NULL ) OR (X.instrumento_financeiro IS NOT NULL AND Y.instrumento_financeiro_SIMUL IS NULL),1,0)) AS NUM_REG_DIF,'1' AS ID_EXEC, CURRENT_TIMESTAMP() AS TIME_EXEC FROM (SELECT a, instrumento_financeiro FROM BU_LOANTAPE_WORK.LT001_UNIV_OPER WHERE ref_date='${ref_date}' AND nome_perimetro='Individual Local' AND segmento='ESTR' AND ambito='SRB_MBDT' AND entidade='00100')X INNER JOIN (SELECT a AS a_SIMUL, instrumento_financeiro AS instrumento_financeiro_SIMUL FROM BU_LOANTAPE_WORK.SIMUL_LT001 WHERE ref_date='${ref_date}' AND nome_perimetro='Individual Local' AND segmento='ESTR' AND ambito='PILAR3' AND entidade='00100')Y ON X.A=Y.A_SIMUL
... A56: =+B56&F56 -> UNIV_OPERjuros_corridos | B56: UNIV_OPER | C56: Coerência | D56: =+UPPER('0. Instruções'!$D$35&"."&VLOOKUP(B56,'0. Instruções'!$C$27:$D$32,2,FALSE)) -> BU_LOANTAPE_WORK.LT001_UNIV_OPER | E56: =+UPPER('0. Instruções'!$D$36&"."&VLOOKUP(B56,'0. Instruções'!$C$27:$E$32,3,FALSE)) -> BU_LOANTAPE_WORK.SIMUL_LT001 | F56: juros_corridos | I56: ="(SELECT "&VLOOKUP(B56,'0. Instruções'!$C$27:$G$32,4,FALSE)&", "&F56&" FROM "&D56&" WHERE "&'0. Instruções'!$D$42&")X" -> (SELECT a, juros_corridos FROM BU_LOANTAPE_WORK.LT001_UNIV_OPER WHERE ref_date='${ref_date}' AND nome_perimetro='Individual Local' AND segmento='ESTR' AND ambito='SRB_MBDT' AND entidade='00100')X | J56: ="(SELECT "&VLOOKUP(B56,'0. Instruções'!$C$27:$G$32,4,FALSE)&" AS "&VLOOKUP(B56,'0. Instruções'!$C$27:$G$32,4,FALSE)&"_SIMUL, "&F56&" AS "&F56&"_SIMUL FROM "&E56&" WHERE "&'0. Instruções'!$D$43&")Y" -> (SELECT a AS a_SIMUL, juros_corridos AS juros_corridos_SIMUL FROM BU_LOANTAPE_WORK.SIMUL_LT001 WHERE ref_date='${ref_date}' AND nome_perimetro='Individual Local' AND segmento='ESTR' AND ambito='PILAR3' AND entidade='00100')Y | K56: =+UPPER("ON X."&VLOOKUP(B56,'0. Instruções'!$C$27:$G$32,4,FALSE)&"=Y."&VLOOKUP(B56,'0. Instruções'!$C$27:$G$32,4,FALSE)&"_SIMUL") -> ON X.A=Y.A_SIMUL | L56: =+IF(C56="Coerência", +IF(LEFT(G56,5)="FLOAT","SELECT '"&UPPER(B56)&"' AS TABELA, '"&UPPER(C56)&"' AS TIPOLOGIA_TESTE,'"&D56&"' AS TABELA_LT,'"&E56&"' AS TABELA_SIMUL,'"&F56&"' AS CAMPO, "&"'${ref_date}' AS REF_DATE, COUNT(*) AS NUM_REG, SUM(IF((ABS(COALESCE(CAST(X."&F56&" AS DECIMAL(18,6)),0)-COALESCE(CAST(Y."&F56&"_SIMUL AS DECIMAL(18,6)),0))>0.000001) OR (X."&F56&" IS NULL AND Y."&F56&"_SIMUL IS NOT NULL ) OR (X."&F56&" IS NOT NULL AND Y."&F56&"_SIMUL IS NULL),1,0)) AS NUM_REG_DIF,'"&MAX('ID1&5'!K:K)+1&"' AS ID_EXEC, CURRENT_TIMESTAMP() AS TIME_EXEC FROM "&I56&" INNER JOIN "&J56&" "&K56,"SELECT '"&UPPER(B56)&"' AS TABELA, '"&UPPER(C56)&"' AS TIPOLOGIA_TESTE,'"&D56&"' AS TABELA_LT,'"&E56&"' AS TABELA_SIMUL,'"&F56&"' AS CAMPO, "&"'${ref_date}' AS REF_DATE, COUNT(*) AS NUM_REG, SUM(IF(COALESCE(CAST(X."&F56&" AS STRING),'')<>COALESCE(CAST(Y."&F56&"_SIMUL AS STRING),'') OR (X."&F56&" IS NULL AND Y."&F56&"_SIMUL IS NOT NULL ) OR (X."&F56&" IS NOT NULL AND Y."&F56&"_SIMUL IS NULL),1,0)) AS NUM_REG_DIF,'"&MAX('ID1&5'!L:L)+1&"' AS ID_EXEC, CURRENT_TIMESTAMP() AS TIME_EXEC FROM "&I56&" INNER JOIN "&J56&" "&K56), IF(C56="Validade",+IF(G56="Code List","SELECT '"&UPPER(B56)&"' AS TABELA, '"&UPPER(C56)&"' AS TIPOLOGIA_TESTE,'"&D56&"' AS TABELA_LT,'N/A' AS TABELA_SIMUL,'"&F56&"' AS CAMPO, "&"'${ref_date}' AS REF_DATE, COUNT(*) AS NUM_REG, SUM(IF(TRIM(CAST(X."&F56&" AS STRING))='' OR TRIM(CAST(X."&F56&" AS STRING)) IS NULL OR CAST(X."&F56&" AS STRING) NOT "&H56&",1,0)) AS NUM_REG_DIF,'"&MAX('ID1&5'!K:K)+1&"' AS ID_EXEC, CURRENT_TIMESTAMP() AS TIME_EXEC FROM "&I56,"SELECT '"&UPPER(B56)&"' AS TABELA, '"&UPPER(C56)&"' AS TIPOLOGIA_TESTE,'"&D56&"' AS TABELA_LT,'N/A' AS TABELA_SIMUL,'"&F56&"' AS CAMPO, "&"'${ref_date}' AS REF_DATE, COUNT(*) AS NUM_REG, SUM(IF(TRIM(CAST(X."&F56&" AS STRING))='' OR TRIM(CAST(X."&F56&" AS STRING)) IS NULL,1,0)) AS NUM_REG_DIF,'"&MAX('ID1&5'!K:K)+1&"' AS ID_EXEC, CURRENT_TIMESTAMP() AS TIME_EXEC FROM "&I56), IF(C56="Caracteres Especiais",+"SELECT '"&UPPER(B56)&"' AS TABELA, '"&UPPER(C56)&"' AS TIPOLOGIA_TESTE,'"&D56&"' AS TABELA_LT,'N/A' AS TABELA_SIMUL,'"&F56&"' AS CAMPO, "&"'${ref_date}' AS REF_DATE, COUNT(*) AS NUM_REG, SUM(IF(REGEXP_REPLACE(TRIM(CAST(X."&F56&" AS STRING)),'[^a-zA-Z0-9_\\s]','') <>TRIM(CAST(X."&F56&" AS STRING)),1,0)) AS NUM_REG_DIF,'"&MAX('ID1&5'!K:K)+1&"' AS ID_EXEC, CURRENT_TIMESTAMP() AS TIME_EXEC FROM "&I56, IF(C56="Missings",+"SELECT '"&UPPER(B56)&"' AS TABELA, '"&UPPER(C56)&"' AS TIPOLOGIA_TESTE,'"&D56&"' AS TABELA_LT,'N/A' AS TABELA_SIMUL,'"&F56&"' AS CAMPO, "&"'${ref_date}' AS REF_DATE, COUNT(*) AS NUM_REG, SUM(IF(TRIM(CAST(X."&F56&" AS STRING)) IN ('0000-00-00','0001-01-01','9999-12-31','MISS','00000','99999999999','99999999999.00','99999999999.000000'),1,0)) AS NUM_REG_DIF,'"&MAX('ID1&5'!K:K)+1&"' AS ID_EXEC, CURRENT_TIMESTAMP() AS TIME_EXEC FROM "&I56, IF(C56="Not applicable",+"SELECT '"&UPPER(B56)&"' AS TABELA, '"&UPPER(C56)&"' AS TIPOLOGIA_TESTE,'"&D56&"' AS TABELA_LT,'N/A' AS TABELA_SIMUL,'"&F56&"' AS CAMPO, "&"'${ref_date}' AS REF_DATE, COUNT(*) AS NUM_REG, SUM(IF(TRIM(CAST(X."&F56&" AS STRING)) IN ('N/A','11111111111','11111111111.00','11111111111.000000','1111-11-11'),1,0)) AS NUM_REG_DIF,'"&MAX('ID1&5'!K:K)+1&"' AS ID_EXEC, CURRENT_TIMESTAMP() AS TIME_EXEC FROM "&I56, IF(C56="Valores extremos",+"SELECT '"&UPPER(B56)&"' AS TABELA, '"&UPPER(C56)&"' AS TIPOLOGIA_TESTE,'"&D56&"' AS TABELA_LT,'N/A' AS TABELA_SIMUL,'"&F56&"' AS CAMPO, "&"'${ref_date}' AS REF_DATE, CAST(MIN("&F56&") AS STRING) AS VALOR_MIN, CAST(MAX("&F56&") AS STRING) AS VALOR_MAX,'"&MAX('ID1&5'!K:K)+1&"' AS ID_EXEC, CURRENT_TIMESTAMP() AS TIME_EXEC FROM "&MID(I56,1,LEN(I56)-2)&" AND CAST("&F56&" AS STRING) NOT IN ('0000-00-00','0001-01-01','9999-12-31','MISS','00000','99999999999','99999999999.00','99999999999.000000','N/A','11111111111','11111111111.00','11111111111.000000','1111-11-11'))X")))))) -> SELECT 'UNIV_OPER' AS TABELA, 'COERÊNCIA' AS TIPOLOGIA_TESTE,'BU_LOANTAPE_WORK.LT001_UNIV_OPER' AS TABELA_LT,'BU_LOANTAPE_WORK.SIMUL_LT001' AS TABELA_SIMUL,'juros_corridos' AS CAMPO, '${ref_date}' AS REF_DATE, COUNT(*) AS NUM_REG, SUM(IF(COALESCE(CAST(X.juros_corridos AS STRING),'')<>COALESCE(CAST(Y.juros_corridos_SIMUL AS STRING),'') OR (X.juros_corridos IS NULL AND Y.juros_corridos_SIMUL IS NOT NULL ) OR (X.juros_corridos IS NOT NULL AND Y.juros_corridos_SIMUL IS NULL),1,0)) AS NUM_REG_DIF,'1' AS ID_EXEC, CURRENT_TIMESTAMP() AS TIME_EXEC FROM (SELECT a, juros_corridos FROM BU_LOANTAPE_WORK.LT001_UNIV_OPER WHERE ref_date='${ref_date}' AND nome_perimetro='Individual Local' AND segmento='ESTR' AND ambito='SRB_MBDT' AND entidade='00100')X INNER JOIN (SELECT a AS a_SIMUL, juros_corridos AS juros_corridos_SIMUL FROM BU_LOANTAPE_WORK.SIMUL_LT001 WHERE ref_date='${ref_date}' AND nome_perimetro='Individual Local' AND segmento='ESTR' AND ambito='PILAR3' AND entidade='00100')Y ON X.A=Y.A_SIMUL | M56: =+"UNION ALL "&L56 -> UNION ALL SELECT 'UNIV_OPER' AS TABELA, 'COERÊNCIA' AS TIPOLOGIA_TESTE,'BU_LOANTAPE_WORK.LT001_UNIV_OPER' AS TABELA_LT,'BU_LOANTAPE_WORK.SIMUL_LT001' AS TABELA_SIMUL,'juros_corridos' AS CAMPO, '${ref_date}' AS REF_DATE, COUNT(*) AS NUM_REG, SUM(IF(COALESCE(CAST(X.juros_corridos AS STRING),'')<>COALESCE(CAST(Y.juros_corridos_SIMUL AS STRING),'') OR (X.juros_corridos IS NULL AND Y.juros_corridos_SIMUL IS NOT NULL ) OR (X.juros_corridos IS NOT NULL AND Y.juros_corridos_SIMUL IS NULL),1,0)) AS NUM_REG_DIF,'1' AS ID_EXEC, CURRENT_TIMESTAMP() AS TIME_EXEC FROM (SELECT a, juros_corridos FROM BU_LOANTAPE_WORK.LT001_UNIV_OPER WHERE ref_date='${ref_date}' AND nome_perimetro='Individual Local' AND segmento='ESTR' AND ambito='SRB_MBDT' AND entidade='00100')X INNER JOIN (SELECT a AS a_SIMUL, juros_corridos AS juros_corridos_SIMUL FROM BU_LOANTAPE_WORK.SIMUL_LT001 WHERE ref_date='${ref_date}' AND nome_perimetro='Individual Local' AND segmento='ESTR' AND ambito='PILAR3' AND entidade='00100')Y ON X.A=Y.A_SIMUL
B57: UNIV_OPER | C57: Coerência | D57: =+UPPER('0. Instruções'!$D$35&"."&VLOOKUP(B57,'0. Instruções'!$C$27:$D$32,2,FALSE)) -> BU_LOANTAPE_WORK.LT001_UNIV_OPER | E57: =+UPPER('0. Instruções'!$D$36&"."&VLOOKUP(B57,'0. Instruções'!$C$27:$E$32,3,FALSE)) -> BU_LOANTAPE_WORK.SIMUL_LT001 | F57: juros_corridos_prvs | I57: ="(SELECT "&VLOOKUP(B57,'0. Instruções'!$C$27:$G$32,4,FALSE)&", "&F57&" FROM "&D57&" WHERE "&'0. Instruções'!$D$42&")X" -> (SELECT a, juros_corridos_prvs FROM BU_LOANTAPE_WORK.LT001_UNIV_OPER WHERE ref_date='${ref_date}' AND nome_perimetro='Individual Local' AND segmento='ESTR' AND ambito='SRB_MBDT' AND entidade='00100')X | J57: ="(SELECT "&VLOOKUP(B57,'0. Instruções'!$C$27:$G$32,4,FALSE)&" AS "&VLOOKUP(B57,'0. Instruções'!$C$27:$G$32,4,FALSE)&"_SIMUL, "&F57&" AS "&F57&"_SIMUL FROM "&E57&" WHERE "&'0. Instruções'!$D$43&")Y" -> (SELECT a AS a_SIMUL, juros_corridos_prvs AS juros_corridos_prvs_SIMUL FROM BU_LOANTAPE_WORK.SIMUL_LT001 WHERE ref_date='${ref_date}' AND nome_perimetro='Individual Local' AND segmento='ESTR' AND ambito='PILAR3' AND entidade='00100')Y | K57: =+UPPER("ON X."&VLOOKUP(B57,'0. Instruções'!$C$27:$G$32,4,FALSE)&"=Y."&VLOOKUP(B57,'0. Instruções'!$C$27:$G$32,4,FALSE)&"_SIMUL") -> ON X.A=Y.A_SIMUL | L57: =+IF(C57="Coerência", +IF(LEFT(G57,5)="FLOAT","SELECT '"&UPPER(B57)&"' AS TABELA, '"&UPPER(C57)&"' AS TIPOLOGIA_TESTE,'"&D57&"' AS TABELA_LT,'"&E57&"' AS TABELA_SIMUL,'"&F57&"' AS CAMPO, "&"'${ref_date}' AS REF_DATE, COUNT(*) AS NUM_REG, SUM(IF((ABS(COALESCE(CAST(X."&F57&" AS DECIMAL(18,6)),0)-COALESCE(CAST(Y."&F57&"_SIMUL AS DECIMAL(18,6)),0))>0.000001) OR (X."&F57&" IS NULL AND Y."&F57&"_SIMUL IS NOT NULL ) OR (X."&F57&" IS NOT NULL AND Y."&F57&"_SIMUL IS NULL),1,0)) AS NUM_REG_DIF,'"&MAX('ID1&5'!K:K)+1&"' AS ID_EXEC, CURRENT_TIMESTAMP() AS TIME_EXEC FROM "&I57&" INNER JOIN "&J57&" "&K57,"SELECT '"&UPPER(B57)&"' AS TABELA, '"&UPPER(C57)&"' AS TIPOLOGIA_TESTE,'"&D57&"' AS TABELA_LT,'"&E57&"' AS TABELA_SIMUL,'"&F57&"' AS CAMPO, "&"'${ref_date}' AS REF_DATE, COUNT(*) AS NUM_REG, SUM(IF(COALESCE(CAST(X."&F57&" AS STRING),'')<>COALESCE(CAST(Y."&F57&"_SIMUL AS STRING),'') OR (X."&F57&" IS NULL AND Y."&F57&"_SIMUL IS NOT NULL ) OR (X."&F57&" IS NOT NULL AND Y."&F57&"_SIMUL IS NULL),1,0)) AS NUM_REG_DIF,'"&MAX('ID1&5'!L:L)+1&"' AS ID_EXEC, CURRENT_TIMESTAMP() AS TIME_EXEC FROM "&I57&" INNER JOIN "&J57&" "&K57), IF(C57="Validade",+IF(G57="Code List","SELECT '"&UPPER(B57)&"' AS TABELA, '"&UPPER(C57)&"' AS TIPOLOGIA_TESTE,'"&D57&"' AS TABELA_LT,'N/A' AS TABELA_SIMUL,'"&F57&"' AS CAMPO, "&"'${ref_date}' AS REF_DATE, COUNT(*) AS NUM_REG, SUM(IF(TRIM(CAST(X."&F57&" AS STRING))='' OR TRIM(CAST(X."&F57&" AS STRING)) IS NULL OR CAST(X."&F57&" AS STRING) NOT "&H57&",1,0)) AS NUM_REG_DIF,'"&MAX('ID1&5'!K:K)+1&"' AS ID_EXEC, CURRENT_TIMESTAMP() AS TIME_EXEC FROM "&I57,"SELECT '"&UPPER(B57)&"' AS TABELA, '"&UPPER(C57)&"' AS TIPOLOGIA_TESTE,'"&D57&"' AS TABELA_LT,'N/A' AS TABELA_SIMUL,'"&F57&"' AS CAMPO, "&"'${ref_date}' AS REF_DATE, COUNT(*) AS NUM_REG, SUM(IF(TRIM(CAST(X."&F57&" AS STRING))='' OR TRIM(CAST(X."&F57&" AS STRING)) IS NULL,1,0)) AS NUM_REG_DIF,'"&MAX('ID1&5'!K:K)+1&"' AS ID_EXEC, CURRENT_TIMESTAMP() AS TIME_EXEC FROM "&I57), IF(C57="Caracteres Especiais",+"SELECT '"&UPPER(B57)&"' AS TABELA, '"&UPPER(C57)&"' AS TIPOLOGIA_TESTE,'"&D57&"' AS TABELA_LT,'N/A' AS TABELA_SIMUL,'"&F57&"' AS CAMPO, "&"'${ref_date}' AS REF_DATE, COUNT(*) AS NUM_REG, SUM(IF(REGEXP_REPLACE(TRIM(CAST(X."&F57&" AS STRING)),'[^a-zA-Z0-9_\\s]','') <>TRIM(CAST(X."&F57&" AS STRING)),1,0)) AS NUM_REG_DIF,'"&MAX('ID1&5'!K:K)+1&"' AS ID_EXEC, CURRENT_TIMESTAMP() AS TIME_EXEC FROM "&I57, IF(C57="Missings",+"SELECT '"&UPPER(B57)&"' AS TABELA, '"&UPPER(C57)&"' AS TIPOLOGIA_TESTE,'"&D57&"' AS TABELA_LT,'N/A' AS TABELA_SIMUL,'"&F57&"' AS CAMPO, "&"'${ref_date}' AS REF_DATE, COUNT(*) AS NUM_REG, SUM(IF(TRIM(CAST(X."&F57&" AS STRING)) IN ('0000-00-00','0001-01-01','9999-12-31','MISS','00000','99999999999','99999999999.00','99999999999.000000'),1,0)) AS NUM_REG_DIF,'"&MAX('ID1&5'!K:K)+1&"' AS ID_EXEC, CURRENT_TIMESTAMP() AS TIME_EXEC FROM "&I57, IF(C57="Not applicable",+"SELECT '"&UPPER(B57)&"' AS TABELA, '"&UPPER(C57)&"' AS TIPOLOGIA_TESTE,'"&D57&"' AS TABELA_LT,'N/A' AS TABELA_SIMUL,'"&F57&"' AS CAMPO, "&"'${ref_date}' AS REF_DATE, COUNT(*) AS NUM_REG, SUM(IF(TRIM(CAST(X."&F57&" AS STRING)) IN ('N/A','11111111111','11111111111.00','11111111111.000000','1111-11-11'),1,0)) AS NUM_REG_DIF,'"&MAX('ID1&5'!K:K)+1&"' AS ID_EXEC, CURRENT_TIMESTAMP() AS TIME_EXEC FROM "&I57, IF(C57="Valores extremos",+"SELECT '"&UPPER(B57)&"' AS TABELA, '"&UPPER(C57)&"' AS TIPOLOGIA_TESTE,'"&D57&"' AS TABELA_LT,'N/A' AS TABELA_SIMUL,'"&F57&"' AS CAMPO, "&"'${ref_date}' AS REF_DATE, CAST(MIN("&F57&") AS STRING) AS VALOR_MIN, CAST(MAX("&F57&") AS STRING) AS VALOR_MAX,'"&MAX('ID1&5'!K:K)+1&"' AS ID_EXEC, CURRENT_TIMESTAMP() AS TIME_EXEC FROM "&MID(I57,1,LEN(I57)-2)&" AND CAST("&F57&" AS STRING) NOT IN ('0000-00-00','0001-01-01','9999-12-31','MISS','00000','99999999999','99999999999.00','99999999999.000000','N/A','11111111111','11111111111.00','11111111111.000000','1111-11-11'))X")))))) -> SELECT 'UNIV_OPER' AS TABELA, 'COERÊNCIA' AS TIPOLOGIA_TESTE,'BU_LOANTAPE_WORK.LT001_UNIV_OPER' AS TABELA_LT,'BU_LOANTAPE_WORK.SIMUL_LT001' AS TABELA_SIMUL,'juros_corridos_prvs' AS CAMPO, '${ref_date}' AS REF_DATE, COUNT(*) AS NUM_REG, SUM(IF(COALESCE(CAST(X.juros_corridos_prvs AS STRING),'')<>COALESCE(CAST(Y.juros_corridos_prvs_SIMUL AS STRING),'') OR (X.juros_corridos_prvs IS NULL AND Y.juros_corridos_prvs_SIMUL IS NOT NULL ) OR (X.juros_corridos_prvs IS NOT NULL AND Y.juros_corridos_prvs_SIMUL IS NULL),1,0)) AS NUM_REG_DIF,'1' AS ID_EXEC, CURRENT_TIMESTAMP() AS TIME_EXEC FROM (SELECT a, juros_corridos_prvs FROM BU_LOANTAPE_WORK.LT001_UNIV_OPER WHERE ref_date='${ref_date}' AND nome_perimetro='Individual Local' AND segmento='ESTR' AND ambito='SRB_MBDT' AND entidade='00100')X INNER JOIN (SELECT a AS a_SIMUL, juros_corridos_prvs AS juros_corridos_prvs_SIMUL FROM BU_LOANTAPE_WORK.SIMUL_LT001 WHERE ref_date='${ref_date}' AND nome_perimetro='Individual Local' AND segmento='ESTR' AND ambito='PILAR3' AND entidade='00100')Y ON X.A=Y.A_SIMUL | M57: =+"UNION ALL "&L57 -> UNION ALL SELECT 'UNIV_OPER' AS TABELA, 'COERÊNCIA' AS TIPOLOGIA_TESTE,'BU_LOANTAPE_WORK.LT001_UNIV_OPER' AS TABELA_LT,'BU_LOANTAPE_WORK.SIMUL_LT001' AS TABELA_SIMUL,'juros_corridos_prvs' AS CAMPO, '${ref_date}' AS REF_DATE, COUNT(*) AS NUM_REG, SUM(IF(COALESCE(CAST(X.juros_corridos_prvs AS STRING),'')<>COALESCE(CAST(Y.juros_corridos_prvs_SIMUL AS STRING),'') OR (X.juros_corridos_prvs IS NULL AND Y.juros_corridos_prvs_SIMUL IS NOT NULL ) OR (X.juros_corridos_prvs IS NOT NULL AND Y.juros_corridos_prvs_SIMUL IS NULL),1,0)) AS NUM_REG_DIF,'1' AS ID_EXEC, CURRENT_TIMESTAMP() AS TIME_EXEC FROM (SELECT a, juros_corridos_prvs FROM BU_LOANTAPE_WORK.LT001_UNIV_OPER WHERE ref_date='${ref_date}' AND nome_perimetro='Individual Local' AND segmento='ESTR' AND ambito='SRB_MBDT' AND entidade='00100')X INNER JOIN (SELECT a AS a_SIMUL, juros_corridos_prvs AS juros_corridos_prvs_SIMUL FROM BU_LOANTAPE_WORK.SIMUL_LT001 WHERE ref_date='${ref_date}' AND nome_perimetro='Individual Local' AND segmento='ESTR' AND ambito='PILAR3' AND entidade='00100')Y ON X.A=Y.A_SIMUL
B58: UNIV_OPER | C58: Coerência | D58: =+UPPER('0. Instruções'!$D$35&"."&VLOOKUP(B58,'0. Instruções'!$C$27:$D$32,2,FALSE)) -> BU_LOANTAPE_WORK.LT001_UNIV_OPER | E58: =+UPPER('0. Instruções'!$D$36&"."&VLOOKUP(B58,'0. Instruções'!$C$27:$E$32,3,FALSE)) -> BU_LOANTAPE_WORK.SIMUL_LT001 | F58: subportfolio_id_inicial | I58: ="(SELECT "&VLOOKUP(B58,'0. Instruções'!$C$27:$G$32,4,FALSE)&", "&F58&" FROM "&D58&" WHERE "&'0. Instruções'!$D$42&")X" -> (SELECT a, subportfolio_id_inicial FROM BU_LOANTAPE_WORK.LT001_UNIV_OPER WHERE ref_date='${ref_date}' AND nome_perimetro='Individual Local' AND segmento='ESTR' AND ambito='SRB_MBDT' AND entidade='00100')X | J58: ="(SELECT "&VLOOKUP(B58,'0. Instruções'!$C$27:$G$32,4,FALSE)&" AS "&VLOOKUP(B58,'0. Instruções'!$C$27:$G$32,4,FALSE)&"_SIMUL, "&F58&" AS "&F58&"_SIMUL FROM "&E58&" WHERE "&'0. Instruções'!$D$43&")Y" -> (SELECT a AS a_SIMUL, subportfolio_id_inicial AS subportfolio_id_inicial_SIMUL FROM BU_LOANTAPE_WORK.SIMUL_LT001 WHERE ref_date='${ref_date}' AND nome_perimetro='Individual Local' AND segmento='ESTR' AND ambito='PILAR3' AND entidade='00100')Y | K58: =+UPPER("ON X."&VLOOKUP(B58,'0. Instruções'!$C$27:$G$32,4,FALSE)&"=Y."&VLOOKUP(B58,'0. Instruções'!$C$27:$G$32,4,FALSE)&"_SIMUL") -> ON X.A=Y.A_SIMUL | L58: =+IF(C58="Coerência", +IF(LEFT(G58,5)="FLOAT","SELECT '"&UPPER(B58)&"' AS TABELA, '"&UPPER(C58)&"' AS TIPOLOGIA_TESTE,'"&D58&"' AS TABELA_LT,'"&E58&"' AS TABELA_SIMUL,'"&F58&"' AS CAMPO, "&"'${ref_date}' AS REF_DATE, COUNT(*) AS NUM_REG, SUM(IF((ABS(COALESCE(CAST(X."&F58&" AS DECIMAL(18,6)),0)-COALESCE(CAST(Y."&F58&"_SIMUL AS DECIMAL(18,6)),0))>0.000001) OR (X."&F58&" IS NULL AND Y."&F58&"_SIMUL IS NOT NULL ) OR (X."&F58&" IS NOT NULL AND Y."&F58&"_SIMUL IS NULL),1,0)) AS NUM_REG_DIF,'"&MAX('ID1&5'!K:K)+1&"' AS ID_EXEC, CURRENT_TIMESTAMP() AS TIME_EXEC FROM "&I58&" INNER JOIN "&J58&" "&K58,"SELECT '"&UPPER(B58)&"' AS TABELA, '"&UPPER(C58)&"' AS TIPOLOGIA_TESTE,'"&D58&"' AS TABELA_LT,'"&E58&"' AS TABELA_SIMUL,'"&F58&"' AS CAMPO, "&"'${ref_date}' AS REF_DATE, COUNT(*) AS NUM_REG, SUM(IF(COALESCE(CAST(X."&F58&" AS STRING),'')<>COALESCE(CAST(Y."&F58&"_SIMUL AS STRING),'') OR (X."&F58&" IS NULL AND Y."&F58&"_SIMUL IS NOT NULL ) OR (X."&F58&" IS NOT NULL AND Y."&F58&"_SIMUL IS NULL),1,0)) AS NUM_REG_DIF,'"&MAX('ID1&5'!L:L)+1&"' AS ID_EXEC, CURRENT_TIMESTAMP() AS TIME_EXEC FROM "&I58&" INNER JOIN "&J58&" "&K58), IF(C58="Validade",+IF(G58="Code List","SELECT '"&UPPER(B58)&"' AS TABELA, '"&UPPER(C58)&"' AS TIPOLOGIA_TESTE,'"&D58&"' AS TABELA_LT,'N/A' AS TABELA_SIMUL,'"&F58&"' AS CAMPO, "&"'${ref_date}' AS REF_DATE, COUNT(*) AS NUM_REG, SUM(IF(TRIM(CAST(X."&F58&" AS STRING))='' OR TRIM(CAST(X."&F58&" AS STRING)) IS NULL OR CAST(X."&F58&" AS STRING) NOT "&H58&",1,0)) AS NUM_REG_DIF,'"&MAX('ID1&5'!K:K)+1&"' AS ID_EXEC, CURRENT_TIMESTAMP() AS TIME_EXEC FROM "&I58,"SELECT '"&UPPER(B58)&"' AS TABELA, '"&UPPER(C58)&"' AS TIPOLOGIA_TESTE,'"&D58&"' AS TABELA_LT,'N/A' AS TABELA_SIMUL,'"&F58&"' AS CAMPO, "&"'${ref_date}' AS REF_DATE, COUNT(*) AS NUM_REG, SUM(IF(TRIM(CAST(X."&F58&" AS STRING))='' OR TRIM(CAST(X."&F58&" AS STRING)) IS NULL,1,0)) AS NUM_REG_DIF,'"&MAX('ID1&5'!K:K)+1&"' AS ID_EXEC, CURRENT_TIMESTAMP() AS TIME_EXEC FROM "&I58), IF(C58="Caracteres Especiais",+"SELECT '"&UPPER(B58)&"' AS TABELA, '"&UPPER(C58)&"' AS TIPOLOGIA_TESTE,'"&D58&"' AS TABELA_LT,'N/A' AS TABELA_SIMUL,'"&F58&"' AS CAMPO, "&"'${ref_date}' AS REF_DATE, COUNT(*) AS NUM_REG, SUM(IF(REGEXP_REPLACE(TRIM(CAST(X."&F58&" AS STRING)),'[^a-zA-Z0-9_\\s]','') <>TRIM(CAST(X."&F58&" AS STRING)),1,0)) AS NUM_REG_DIF,'"&MAX('ID1&5'!K:K)+1&"' AS ID_EXEC, CURRENT_TIMESTAMP() AS TIME_EXEC FROM "&I58, IF(C58="Missings",+"SELECT '"&UPPER(B58)&"' AS TABELA, '"&UPPER(C58)&"' AS TIPOLOGIA_TESTE,'"&D58&"' AS TABELA_LT,'N/A' AS TABELA_SIMUL,'"&F58&"' AS CAMPO, "&"'${ref_date}' AS REF_DATE, COUNT(*) AS NUM_REG, SUM(IF(TRIM(CAST(X."&F58&" AS STRING)) IN ('0000-00-00','0001-01-01','9999-12-31','MISS','00000','99999999999','99999999999.00','99999999999.000000'),1,0)) AS NUM_REG_DIF,'"&MAX('ID1&5'!K:K)+1&"' AS ID_EXEC, CURRENT_TIMESTAMP() AS TIME_EXEC FROM "&I58, IF(C58="Not applicable",+"SELECT '"&UPPER(B58)&"' AS TABELA, '"&UPPER(C58)&"' AS TIPOLOGIA_TESTE,'"&D58&"' AS TABELA_LT,'N/A' AS TABELA_SIMUL,'"&F58&"' AS CAMPO, "&"'${ref_date}' AS REF_DATE, COUNT(*) AS NUM_REG, SUM(IF(TRIM(CAST(X."&F58&" AS STRING)) IN ('N/A','11111111111','11111111111.00','11111111111.000000','1111-11-11'),1,0)) AS NUM_REG_DIF,'"&MAX('ID1&5'!K:K)+1&"' AS ID_EXEC, CURRENT_TIMESTAMP() AS TIME_EXEC FROM "&I58, IF(C58="Valores extremos",+"SELECT '"&UPPER(B58)&"' AS TABELA, '"&UPPER(C58)&"' AS TIPOLOGIA_TESTE,'"&D58&"' AS TABELA_LT,'N/A' AS TABELA_SIMUL,'"&F58&"' AS CAMPO, "&"'${ref_date}' AS REF_DATE, CAST(MIN("&F58&") AS STRING) AS VALOR_MIN, CAST(MAX("&F58&") AS STRING) AS VALOR_MAX,'"&MAX('ID1&5'!K:K)+1&"' AS ID_EXEC, CURRENT_TIMESTAMP() AS TIME_EXEC FROM "&MID(I58,1,LEN(I58)-2)&" AND CAST("&F58&" AS STRING) NOT IN ('0000-00-00','0001-01-01','9999-12-31','MISS','00000','99999999999','99999999999.00','99999999999.000000','N/A','11111111111','11111111111.00','11111111111.000000','1111-11-11'))X")))))) -> SELECT 'UNIV_OPER' AS TABELA, 'COERÊNCIA' AS TIPOLOGIA_TESTE,'BU_LOANTAPE_WORK.LT001_UNIV_OPER' AS TABELA_LT,'BU_LOANTAPE_WORK.SIMUL_LT001' AS TABELA_SIMUL,'subportfolio_id_inicial' AS CAMPO, '${ref_date}' AS REF_DATE, COUNT(*) AS NUM_REG, SUM(IF(COALESCE(CAST(X.subportfolio_id_inicial AS STRING),'')<>COALESCE(CAST(Y.subportfolio_id_inicial_SIMUL AS STRING),'') OR (X.subportfolio_id_inicial IS NULL AND Y.subportfolio_id_inicial_SIMUL IS NOT NULL ) OR (X.subportfolio_id_inicial IS NOT NULL AND Y.subportfolio_id_inicial_SIMUL IS NULL),1,0)) AS NUM_REG_DIF,'1' AS ID_EXEC, CURRENT_TIMESTAMP() AS TIME_EXEC FROM (SELECT a, subportfolio_id_inicial FROM BU_LOANTAPE_WORK.LT001_UNIV_OPER WHERE ref_date='${ref_date}' AND nome_perimetro='Individual Local' AND segmento='ESTR' AND ambito='SRB_MBDT' AND entidade='00100')X INNER JOIN (SELECT a AS a_SIMUL, subportfolio_id_inicial AS subportfolio_id_inicial_SIMUL FROM BU_LOANTAPE_WORK.SIMUL_LT001 WHERE ref_date='${ref_date}' AND nome_perimetro='Individual Local' AND segmento='ESTR' AND ambito='PILAR3' AND entidade='00100')Y ON X.A=Y.A_SIMUL | M58: =+"UNION ALL "&L58 -> UNION ALL SELECT 'UNIV_OPER' AS TABELA, 'COERÊNCIA' AS TIPOLOGIA_TESTE,'BU_LOANTAPE_WORK.LT001_UNIV_OPER' AS TABELA_LT,'BU_LOANTAPE_WORK.SIMUL_LT001' AS TABELA_SIMUL,'subportfolio_id_inicial' AS CAMPO, '${ref_date}' AS REF_DATE, COUNT(*) AS NUM_REG, SUM(IF(COALESCE(CAST(X.subportfolio_id_inicial AS STRING),'')<>COALESCE(CAST(Y.subportfolio_id_inicial_SIMUL AS STRING),'') OR (X.subportfolio_id_inicial IS NULL AND Y.subportfolio_id_inicial_SIMUL IS NOT NULL ) OR (X.subportfolio_id_inicial IS NOT NULL AND Y.subportfolio_id_inicial_SIMUL IS NULL),1,0)) AS NUM_REG_DIF,'1' AS ID_EXEC, CURRENT_TIMESTAMP() AS TIME_EXEC FROM (SELECT a, subportfolio_id_inicial FROM BU_LOANTAPE_WORK.LT001_UNIV_OPER WHERE ref_date='${ref_date}' AND nome_perimetro='Individual Local' AND segmento='ESTR' AND ambito='SRB_MBDT' AND entidade='00100')X INNER JOIN (SELECT a AS a_SIMUL, subportfolio_id_inicial AS subportfolio_id_inicial_SIMUL FROM BU_LOANTAPE_WORK.SIMUL_LT001 WHERE ref_date='${ref_date}' AND nome_perimetro='Individual Local' AND segmento='ESTR' AND ambito='PILAR3' AND entidade='00100')Y ON X.A=Y.A_SIMUL
B59: UNIV_OPER | C59: Coerência | D59: =+UPPER('0. Instruções'!$D$35&"."&VLOOKUP(B59,'0. Instruções'!$C$27:$D$32,2,FALSE)) -> BU_LOANTAPE_WORK.LT001_UNIV_OPER | E59: =+UPPER('0. Instruções'!$D$36&"."&VLOOKUP(B59,'0. Instruções'!$C$27:$E$32,3,FALSE)) -> BU_LOANTAPE_WORK.SIMUL_LT001 | F59: subportfolio_id_final | I59: ="(SELECT "&VLOOKUP(B59,'0. Instruções'!$C$27:$G$32,4,FALSE)&", "&F59&" FROM "&D59&" WHERE "&'0. Instruções'!$D$42&")X" -> (SELECT a, subportfolio_id_final FROM BU_LOANTAPE_WORK.LT001_UNIV_OPER WHERE ref_date='${ref_date}' AND nome_perimetro='Individual Local' AND segmento='ESTR' AND ambito='SRB_MBDT' AND entidade='00100')X | J59: ="(SELECT "&VLOOKUP(B59,'0. Instruções'!$C$27:$G$32,4,FALSE)&" AS "&VLOOKUP(B59,'0. Instruções'!$C$27:$G$32,4,FALSE)&"_SIMUL, "&F59&" AS "&F59&"_SIMUL FROM "&E59&" WHERE "&'0. Instruções'!$D$43&")Y" -> (SELECT a AS a_SIMUL, subportfolio_id_final AS subportfolio_id_final_SIMUL FROM BU_LOANTAPE_WORK.SIMUL_LT001 WHERE ref_date='${ref_date}' AND nome_perimetro='Individual Local' AND segmento='ESTR' AND ambito='PILAR3' AND entidade='00100')Y | K59: =+UPPER("ON X."&VLOOKUP(B59,'0. Instruções'!$C$27:$G$32,4,FALSE)&"=Y."&VLOOKUP(B59,'0. Instruções'!$C$27:$G$32,4,FALSE)&"_SIMUL") -> ON X.A=Y.A_SIMUL | L59: =+IF(C59="Coerência", +IF(LEFT(G59,5)="FLOAT","SELECT '"&UPPER(B59)&"' AS TABELA, '"&UPPER(C59)&"' AS TIPOLOGIA_TESTE,'"&D59&"' AS TABELA_LT,'"&E59&"' AS TABELA_SIMUL,'"&F59&"' AS CAMPO, "&"'${ref_date}' AS REF_DATE, COUNT(*) AS NUM_REG, SUM(IF((ABS(COALESCE(CAST(X."&F59&" AS DECIMAL(18,6)),0)-COALESCE(CAST(Y."&F59&"_SIMUL AS DECIMAL(18,6)),0))>0.000001) OR (X."&F59&" IS NULL AND Y."&F59&"_SIMUL IS NOT NULL ) OR (X."&F59&" IS NOT NULL AND Y."&F59&"_SIMUL IS NULL),1,0)) AS NUM_REG_DIF,'"&MAX('ID1&5'!K:K)+1&"' AS ID_EXEC, CURRENT_TIMESTAMP() AS TIME_EXEC FROM "&I59&" INNER JOIN "&J59&" "&K59,"SELECT '"&UPPER(B59)&"' AS TABELA, '"&UPPER(C59)&"' AS TIPOLOGIA_TESTE,'"&D59&"' AS TABELA_LT,'"&E59&"' AS TABELA_SIMUL,'"&F59&"' AS CAMPO, "&"'${ref_date}' AS REF_DATE, COUNT(*) AS NUM_REG, SUM(IF(COALESCE(CAST(X."&F59&" AS STRING),'')<>COALESCE(CAST(Y."&F59&"_SIMUL AS STRING),'') OR (X."&F59&" IS NULL AND Y."&F59&"_SIMUL IS NOT NULL ) OR (X."&F59&" IS NOT NULL AND Y."&F59&"_SIMUL IS NULL),1,0)) AS NUM_REG_DIF,'"&MAX('ID1&5'!L:L)+1&"' AS ID_EXEC, CURRENT_TIMESTAMP() AS TIME_EXEC FROM "&I59&" INNER JOIN "&J59&" "&K59), IF(C59="Validade",+IF(G59="Code List","SELECT '"&UPPER(B59)&"' AS TABELA, '"&UPPER(C59)&"' AS TIPOLOGIA_TESTE,'"&D59&"' AS TABELA_LT,'N/A' AS TABELA_SIMUL,'"&F59&"' AS CAMPO, "&"'${ref_date}' AS REF_DATE, COUNT(*) AS NUM_REG, SUM(IF(TRIM(CAST(X."&F59&" AS STRING))='' OR TRIM(CAST(X."&F59&" AS STRING)) IS NULL OR CAST(X."&F59&" AS STRING) NOT "&H59&",1,0)) AS NUM_REG_DIF,'"&MAX('ID1&5'!K:K)+1&"' AS ID_EXEC, CURRENT_TIMESTAMP() AS TIME_EXEC FROM "&I59,"SELECT '"&UPPER(B59)&"' AS TABELA, '"&UPPER(C59)&"' AS TIPOLOGIA_TESTE,'"&D59&"' AS TABELA_LT,'N/A' AS TABELA_SIMUL,'"&F59&"' AS CAMPO, "&"'${ref_date}' AS REF_DATE, COUNT(*) AS NUM_REG, SUM(IF(TRIM(CAST(X."&F59&" AS STRING))='' OR TRIM(CAST(X."&F59&" AS STRING)) IS NULL,1,0)) AS NUM_REG_DIF,'"&MAX('ID1&5'!K:K)+1&"' AS ID_EXEC, CURRENT_TIMESTAMP() AS TIME_EXEC FROM "&I59), IF(C59="Caracteres Especiais",+"SELECT '"&UPPER(B59)&"' AS TABELA, '"&UPPER(C59)&"' AS TIPOLOGIA_TESTE,'"&D59&"' AS TABELA_LT,'N/A' AS TABELA_SIMUL,'"&F59&"' AS CAMPO, "&"'${ref_date}' AS REF_DATE, COUNT(*) AS NUM_REG, SUM(IF(REGEXP_REPLACE(TRIM(CAST(X."&F59&" AS STRING)),'[^a-zA-Z0-9_\\s]','') <>TRIM(CAST(X."&F59&" AS STRING)),1,0)) AS NUM_REG_DIF,'"&MAX('ID1&5'!K:K)+1&"' AS ID_EXEC, CURRENT_TIMESTAMP() AS TIME_EXEC FROM "&I59, IF(C59="Missings",+"SELECT '"&UPPER(B59)&"' AS TABELA, '"&UPPER(C59)&"' AS TIPOLOGIA_TESTE,'"&D59&"' AS TABELA_LT,'N/A' AS TABELA_SIMUL,'"&F59&"' AS CAMPO, "&"'${ref_date}' AS REF_DATE, COUNT(*) AS NUM_REG, SUM(IF(TRIM(CAST(X."&F59&" AS STRING)) IN ('0000-00-00','0001-01-01','9999-12-31','MISS','00000','99999999999','99999999999.00','99999999999.000000'),1,0)) AS NUM_REG_DIF,'"&MAX('ID1&5'!K:K)+1&"' AS ID_EXEC, CURRENT_TIMESTAMP() AS TIME_EXEC FROM "&I59, IF(C59="Not applicable",+"SELECT '"&UPPER(B59)&"' AS TABELA, '"&UPPER(C59)&"' AS TIPOLOGIA_TESTE,'"&D59&"' AS TABELA_LT,'N/A' AS TABELA_SIMUL,'"&F59&"' AS CAMPO, "&"'${ref_date}' AS REF_DATE, COUNT(*) AS NUM_REG, SUM(IF(TRIM(CAST(X."&F59&" AS STRING)) IN ('N/A','11111111111','11111111111.00','11111111111.000000','1111-11-11'),1,0)) AS NUM_REG_DIF,'"&MAX('ID1&5'!K:K)+1&"' AS ID_EXEC, CURRENT_TIMESTAMP() AS TIME_EXEC FROM "&I59, IF(C59="Valores extremos",+"SELECT '"&UPPER(B59)&"' AS TABELA, '"&UPPER(C59)&"' AS TIPOLOGIA_TESTE,'"&D59&"' AS TABELA_LT,'N/A' AS TABELA_SIMUL,'"&F59&"' AS CAMPO, "&"'${ref_date}' AS REF_DATE, CAST(MIN("&F59&") AS STRING) AS VALOR_MIN, CAST(MAX("&F59&") AS STRING) AS VALOR_MAX,'"&MAX('ID1&5'!K:K)+1&"' AS ID_EXEC, CURRENT_TIMESTAMP() AS TIME_EXEC FROM "&MID(I59,1,LEN(I59)-2)&" AND CAST("&F59&" AS STRING) NOT IN ('0000-00-00','0001-01-01','9999-12-31','MISS','00000','99999999999','99999999999.00','99999999999.000000','N/A','11111111111','11111111111.00','11111111111.000000','1111-11-11'))X")))))) -> SELECT 'UNIV_OPER' AS TABELA, 'COERÊNCIA' AS TIPOLOGIA_TESTE,'BU_LOANTAPE_WORK.LT001_UNIV_OPER' AS TABELA_LT,'BU_LOANTAPE_WORK.SIMUL_LT001' AS TABELA_SIMUL,'subportfolio_id_final' AS CAMPO, '${ref_date}' AS REF_DATE, COUNT(*) AS NUM_REG, SUM(IF(COALESCE(CAST(X.subportfolio_id_final AS STRING),'')<>COALESCE(CAST(Y.subportfolio_id_final_SIMUL AS STRING),'') OR (X.subportfolio_id_final IS NULL AND Y.subportfolio_id_final_SIMUL IS NOT NULL ) OR (X.subportfolio_id_final IS NOT NULL AND Y.subportfolio_id_final_SIMUL IS NULL),1,0)) AS NUM_REG_DIF,'1' AS ID_EXEC, CURRENT_TIMESTAMP() AS TIME_EXEC FROM (SELECT a, subportfolio_id_final FROM BU_LOANTAPE_WORK.LT001_UNIV_OPER WHERE ref_date='${ref_date}' AND nome_perimetro='Individual Local' AND segmento='ESTR' AND ambito='SRB_MBDT' AND entidade='00100')X INNER JOIN (SELECT a AS a_SIMUL, subportfolio_id_final AS subportfolio_id_final_SIMUL FROM BU_LOANTAPE_WORK.SIMUL_LT001 WHERE ref_date='${ref_date}' AND nome_perimetro='Individual Local' AND segmento='ESTR' AND ambito='PILAR3' AND entidade='00100')Y ON X.A=Y.A_SIMUL | M59: =+"UNION ALL "&L59 -> UNION ALL SELECT 'UNIV_OPER' AS TABELA, 'COERÊNCIA' AS TIPOLOGIA_TESTE,'BU_LOANTAPE_WORK.LT001_UNIV_OPER' AS TABELA_LT,'BU_LOANTAPE_WORK.SIMUL_LT001' AS TABELA_SIMUL,'subportfolio_id_final' AS CAMPO, '${ref_date}' AS REF_DATE, COUNT(*) AS NUM_REG, SUM(IF(COALESCE(CAST(X.subportfolio_id_final AS STRING),'')<>COALESCE(CAST(Y.subportfolio_id_final_SIMUL AS STRING),'') OR (X.subportfolio_id_final IS NULL AND Y.subportfolio_id_final_SIMUL IS NOT NULL ) OR (X.subportfolio_id_final IS NOT NULL AND Y.subportfolio_id_final_SIMUL IS NULL),1,0)) AS NUM_REG_DIF,'1' AS ID_EXEC, CURRENT_TIMESTAMP() AS TIME_EXEC FROM (SELECT a, subportfolio_id_final FROM BU_LOANTAPE_WORK.LT001_UNIV_OPER WHERE ref_date='${ref_date}' AND nome_perimetro='Individual Local' AND segmento='ESTR' AND ambito='SRB_MBDT' AND entidade='00100')X INNER JOIN (SELECT a AS a_SIMUL, subportfolio_id_final AS subportfolio_id_final_SIMUL FROM BU_LOANTAPE_WORK.SIMUL_LT001 WHERE ref_date='${ref_date}' AND nome_perimetro='Individual Local' AND segmento='ESTR' AND ambito='PILAR3' AND entidade='00100')Y ON X.A=Y.A_SIMUL
B60: UNIV_OPER | C60: Coerência | D60: =+UPPER('0. Instruções'!$D$35&"."&VLOOKUP(B60,'0. Instruções'!$C$27:$D$32,2,FALSE)) -> BU_LOANTAPE_WORK.LT001_UNIV_OPER | E60: =+UPPER('0. Instruções'!$D$36&"."&VLOOKUP(B60,'0. Instruções'!$C$27:$E$32,3,FALSE)) -> BU_LOANTAPE_WORK.SIMUL_LT001 | F60: idcomb_lt_inicial | I60: ="(SELECT "&VLOOKUP(B60,'0. Instruções'!$C$27:$G$32,4,FALSE)&", "&F60&" FROM "&D60&" WHERE "&'0. Instruções'!$D$42&")X" -> (SELECT a, idcomb_lt_inicial FROM BU_LOANTAPE_WORK.LT001_UNIV_OPER WHERE ref_date='${ref_date}' AND nome_perimetro='Individual Local' AND segmento='ESTR' AND ambito='SRB_MBDT' AND entidade='00100')X | J60: ="(SELECT "&VLOOKUP(B60,'0. Instruções'!$C$27:$G$32,4,FALSE)&" AS "&VLOOKUP(B60,'0. Instruções'!$C$27:$G$32,4,FALSE)&"_SIMUL, "&F60&" AS "&F60&"_SIMUL FROM "&E60&" WHERE "&'0. Instruções'!$D$43&")Y" -> (SELECT a AS a_SIMUL, idcomb_lt_inicial AS idcomb_lt_inicial_SIMUL FROM BU_LOANTAPE_WORK.SIMUL_LT001 WHERE ref_date='${ref_date}' AND nome_perimetro='Individual Local' AND segmento='ESTR' AND ambito='PILAR3' AND entidade='00100')Y | K60: =+UPPER("ON X."&VLOOKUP(B60,'0. Instruções'!$C$27:$G$32,4,FALSE)&"=Y."&VLOOKUP(B60,'0. Instruções'!$C$27:$G$32,4,FALSE)&"_SIMUL") -> ON X.A=Y.A_SIMUL | L60: =+IF(C60="Coerência", +IF(LEFT(G60,5)="FLOAT","SELECT '"&UPPER(B60)&"' AS TABELA, '"&UPPER(C60)&"' AS TIPOLOGIA_TESTE,'"&D60&"' AS TABELA_LT,'"&E60&"' AS TABELA_SIMUL,'"&F60&"' AS CAMPO, "&"'${ref_date}' AS REF_DATE, COUNT(*) AS NUM_REG, SUM(IF((ABS(COALESCE(CAST(X."&F60&" AS DECIMAL(18,6)),0)-COALESCE(CAST(Y."&F60&"_SIMUL AS DECIMAL(18,6)),0))>0.000001) OR (X."&F60&" IS NULL AND Y."&F60&"_SIMUL IS NOT NULL ) OR (X."&F60&" IS NOT NULL AND Y."&F60&"_SIMUL IS NULL),1,0)) AS NUM_REG_DIF,'"&MAX('ID1&5'!K:K)+1&"' AS ID_EXEC, CURRENT_TIMESTAMP() AS TIME_EXEC FROM "&I60&" INNER JOIN "&J60&" "&K60,"SELECT '"&UPPER(B60)&"' AS TABELA, '"&UPPER(C60)&"' AS TIPOLOGIA_TESTE,'"&D60&"' AS TABELA_LT,'"&E60&"' AS TABELA_SIMUL,'"&F60&"' AS CAMPO, "&"'${ref_date}' AS REF_DATE, COUNT(*) AS NUM_REG, SUM(IF(COALESCE(CAST(X."&F60&" AS STRING),'')<>COALESCE(CAST(Y."&F60&"_SIMUL AS STRING),'') OR (X."&F60&" IS NULL AND Y."&F60&"_SIMUL IS NOT NULL ) OR (X."&F60&" IS NOT NULL AND Y."&F60&"_SIMUL IS NULL),1,0)) AS NUM_REG_DIF,'"&MAX('ID1&5'!L:L)+1&"' AS ID_EXEC, CURRENT_TIMESTAMP() AS TIME_EXEC FROM "&I60&" INNER JOIN "&J60&" "&K60), IF(C60="Validade",+IF(G60="Code List","SELECT '"&UPPER(B60)&"' AS TABELA, '"&UPPER(C60)&"' AS TIPOLOGIA_TESTE,'"&D60&"' AS TABELA_LT,'N/A' AS TABELA_SIMUL,'"&F60&"' AS CAMPO, "&"'${ref_date}' AS REF_DATE, COUNT(*) AS NUM_REG, SUM(IF(TRIM(CAST(X."&F60&" AS STRING))='' OR TRIM(CAST(X."&F60&" AS STRING)) IS NULL OR CAST(X."&F60&" AS STRING) NOT "&H60&",1,0)) AS NUM_REG_DIF,'"&MAX('ID1&5'!K:K)+1&"' AS ID_EXEC, CURRENT_TIMESTAMP() AS TIME_EXEC FROM "&I60,"SELECT '"&UPPER(B60)&"' AS TABELA, '"&UPPER(C60)&"' AS TIPOLOGIA_TESTE,'"&D60&"' AS TABELA_LT,'N/A' AS TABELA_SIMUL,'"&F60&"' AS CAMPO, "&"'${ref_date}' AS REF_DATE, COUNT(*) AS NUM_REG, SUM(IF(TRIM(CAST(X."&F60&" AS STRING))='' OR TRIM(CAST(X."&F60&" AS STRING)) IS NULL,1,0)) AS NUM_REG_DIF,'"&MAX('ID1&5'!K:K)+1&"' AS ID_EXEC, CURRENT_TIMESTAMP() AS TIME_EXEC FROM "&I60), IF(C60="Caracteres Especiais",+"SELECT '"&UPPER(B60)&"' AS TABELA, '"&UPPER(C60)&"' AS TIPOLOGIA_TESTE,'"&D60&"' AS TABELA_LT,'N/A' AS TABELA_SIMUL,'"&F60&"' AS CAMPO, "&"'${ref_date}' AS REF_DATE, COUNT(*) AS NUM_REG, SUM(IF(REGEXP_REPLACE(TRIM(CAST(X."&F60&" AS STRING)),'[^a-zA-Z0-9_\\s]','') <>TRIM(CAST(X."&F60&" AS STRING)),1,0)) AS NUM_REG_DIF,'"&MAX('ID1&5'!K:K)+1&"' AS ID_EXEC, CURRENT_TIMESTAMP() AS TIME_EXEC FROM "&I60, IF(C60="Missings",+"SELECT '"&UPPER(B60)&"' AS TABELA, '"&UPPER(C60)&"' AS TIPOLOGIA_TESTE,'"&D60&"' AS TABELA_LT,'N/A' AS TABELA_SIMUL,'"&F60&"' AS CAMPO, "&"'${ref_date}' AS REF_DATE, COUNT(*) AS NUM_REG, SUM(IF(TRIM(CAST(X."&F60&" AS STRING)) IN ('0000-00-00','0001-01-01','9999-12-31','MISS','00000','99999999999','99999999999.00','99999999999.000000'),1,0)) AS NUM_REG_DIF,'"&MAX('ID1&5'!K:K)+1&"' AS ID_EXEC, CURRENT_TIMESTAMP() AS TIME_EXEC FROM "&I60, IF(C60="Not applicable",+"SELECT '"&UPPER(B60)&"' AS TABELA, '"&UPPER(C60)&"' AS TIPOLOGIA_TESTE,'"&D60&"' AS TABELA_LT,'N/A' AS TABELA_SIMUL,'"&F60&"' AS CAMPO, "&"'${ref_date}' AS REF_DATE, COUNT(*) AS NUM_REG, SUM(IF(TRIM(CAST(X."&F60&" AS STRING)) IN ('N/A','11111111111','11111111111.00','11111111111.000000','1111-11-11'),1,0)) AS NUM_REG_DIF,'"&MAX('ID1&5'!K:K)+1&"' AS ID_EXEC, CURRENT_TIMESTAMP() AS TIME_EXEC FROM "&I60, IF(C60="Valores extremos",+"SELECT '"&UPPER(B60)&"' AS TABELA, '"&UPPER(C60)&"' AS TIPOLOGIA_TESTE,'"&D60&"' AS TABELA_LT,'N/A' AS TABELA_SIMUL,'"&F60&"' AS CAMPO, "&"'${ref_date}' AS REF_DATE, CAST(MIN("&F60&") AS STRING) AS VALOR_MIN, CAST(MAX("&F60&") AS STRING) AS VALOR_MAX,'"&MAX('ID1&5'!K:K)+1&"' AS ID_EXEC, CURRENT_TIMESTAMP() AS TIME_EXEC FROM "&MID(I60,1,LEN(I60)-2)&" AND CAST("&F60&" AS STRING) NOT IN ('0000-00-00','0001-01-01','9999-12-31','MISS','00000','99999999999','99999999999.00','99999999999.000000','N/A','11111111111','11111111111.00','11111111111.000000','1111-11-11'))X")))))) -> SELECT 'UNIV_OPER' AS TABELA, 'COERÊNCIA' AS TIPOLOGIA_TESTE,'BU_LOANTAPE_WORK.LT001_UNIV_OPER' AS TABELA_LT,'BU_LOANTAPE_WORK.SIMUL_LT001' AS TABELA_SIMUL,'idcomb_lt_inicial' AS CAMPO, '${ref_date}' AS REF_DATE, COUNT(*) AS NUM_REG, SUM(IF(COALESCE(CAST(X.idcomb_lt_inicial AS STRING),'')<>COALESCE(CAST(Y.idcomb_lt_inicial_SIMUL AS STRING),'') OR (X.idcomb_lt_inicial IS NULL AND Y.idcomb_lt_inicial_SIMUL IS NOT NULL ) OR (X.idcomb_lt_inicial IS NOT NULL AND Y.idcomb_lt_inicial_SIMUL IS NULL),1,0)) AS NUM_REG_DIF,'1' AS ID_EXEC, CURRENT_TIMESTAMP() AS TIME_EXEC FROM (SELECT a, idcomb_lt_inicial FROM BU_LOANTAPE_WORK.LT001_UNIV_OPER WHERE ref_date='${ref_date}' AND nome_perimetro='Individual Local' AND segmento='ESTR' AND ambito='SRB_MBDT' AND entidade='00100')X INNER JOIN (SELECT a AS a_SIMUL, idcomb_lt_inicial AS idcomb_lt_inicial_SIMUL FROM BU_LOANTAPE_WORK.SIMUL_LT001 WHERE ref_date='${ref_date}' AND nome_perimetro='Individual Local' AND segmento='ESTR' AND ambito='PILAR3' AND entidade='00100')Y ON X.A=Y.A_SIMUL | M60: =+"UNION ALL "&L60 -> UNION ALL SELECT 'UNIV_OPER' AS TABELA, 'COERÊNCIA' AS TIPOLOGIA_TESTE,'BU_LOANTAPE_WORK.LT001_UNIV_OPER' AS TABELA_LT,'BU_LOANTAPE_WORK.SIMUL_LT001' AS TABELA_SIMUL,'idcomb_lt_inicial' AS CAMPO, '${ref_date}' AS REF_DATE, COUNT(*) AS NUM_REG, SUM(IF(COALESCE(CAST(X.idcomb_lt_inicial AS STRING),'')<>COALESCE(CAST(Y.idcomb_lt_inicial_SIMUL AS STRING),'') OR (X.idcomb_lt_inicial IS NULL AND Y.idcomb_lt_inicial_SIMUL IS NOT NULL ) OR (X.idcomb_lt_inicial IS NOT NULL AND Y.idcomb_lt_inicial_SIMUL IS NULL),1,0)) AS NUM_REG_DIF,'1' AS ID_EXEC, CURRENT_TIMESTAMP() AS TIME_EXEC FROM (SELECT a, idcomb_lt_inicial FROM BU_LOANTAPE_WORK.LT001_UNIV_OPER WHERE ref_date='${ref_date}' AND nome_perimetro='Individual Local' AND segmento='ESTR' AND ambito='SRB_MBDT' AND entidade='00100')X INNER JOIN (SELECT a AS a_SIMUL, idcomb_lt_inicial AS idcomb_lt_inicial_SIMUL FROM BU_LOANTAPE_WORK.SIMUL_LT001 WHERE ref_date='${ref_date}' AND nome_perimetro='Individual Local' AND segmento='ESTR' AND ambito='PILAR3' AND entidade='00100')Y ON X.A=Y.A_SIMUL
B61: UNIV_OPER | C61: Coerência | D61: =+UPPER('0. Instruções'!$D$35&"."&VLOOKUP(B61,'0. Instruções'!$C$27:$D$32,2,FALSE)) -> BU_LOANTAPE_WORK.LT001_UNIV_OPER | E61: =+UPPER('0. Instruções'!$D$36&"."&VLOOKUP(B61,'0. Instruções'!$C$27:$E$32,3,FALSE)) -> BU_LOANTAPE_WORK.SIMUL_LT001 | F61: idcomb_lt_final | I61: ="(SELECT "&VLOOKUP(B61,'0. Instruções'!$C$27:$G$32,4,FALSE)&", "&F61&" FROM "&D61&" WHERE "&'0. Instruções'!$D$42&")X" -> (SELECT a, idcomb_lt_final FROM BU_LOANTAPE_WORK.LT001_UNIV_OPER WHERE ref_date='${ref_date}' AND nome_perimetro='Individual Local' AND segmento='ESTR' AND ambito='SRB_MBDT' AND entidade='00100')X | J61: ="(SELECT "&VLOOKUP(B61,'0. Instruções'!$C$27:$G$32,4,FALSE)&" AS "&VLOOKUP(B61,'0. Instruções'!$C$27:$G$32,4,FALSE)&"_SIMUL, "&F61&" AS "&F61&"_SIMUL FROM "&E61&" WHERE "&'0. Instruções'!$D$43&")Y" -> (SELECT a AS a_SIMUL, idcomb_lt_final AS idcomb_lt_final_SIMUL FROM BU_LOANTAPE_WORK.SIMUL_LT001 WHERE ref_date='${ref_date}' AND nome_perimetro='Individual Local' AND segmento='ESTR' AND ambito='PILAR3' AND entidade='00100')Y | K61: =+UPPER("ON X."&VLOOKUP(B61,'0. Instruções'!$C$27:$G$32,4,FALSE)&"=Y."&VLOOKUP(B61,'0. Instruções'!$C$27:$G$32,4,FALSE)&"_SIMUL") -> ON X.A=Y.A_SIMUL | L61: =+IF(C61="Coerência", +IF(LEFT(G61,5)="FLOAT","SELECT '"&UPPER(B61)&"' AS TABELA, '"&UPPER(C61)&"' AS TIPOLOGIA_TESTE,'"&D61&"' AS TABELA_LT,'"&E61&"' AS TABELA_SIMUL,'"&F61&"' AS CAMPO, "&"'${ref_date}' AS REF_DATE, COUNT(*) AS NUM_REG, SUM(IF((ABS(COALESCE(CAST(X."&F61&" AS DECIMAL(18,6)),0)-COALESCE(CAST(Y."&F61&"_SIMUL AS DECIMAL(18,6)),0))>0.000001) OR (X."&F61&" IS NULL AND Y."&F61&"_SIMUL IS NOT NULL ) OR (X."&F61&" IS NOT NULL AND Y."&F61&"_SIMUL IS NULL),1,0)) AS NUM_REG_DIF,'"&MAX('ID1&5'!K:K)+1&"' AS ID_EXEC, CURRENT_TIMESTAMP() AS TIME_EXEC FROM "&I61&" INNER JOIN "&J61&" "&K61,"SELECT '"&UPPER(B61)&"' AS TABELA, '"&UPPER(C61)&"' AS TIPOLOGIA_TESTE,'"&D61&"' AS TABELA_LT,'"&E61&"' AS TABELA_SIMUL,'"&F61&"' AS CAMPO, "&"'${ref_date}' AS REF_DATE, COUNT(*) AS NUM_REG, SUM(IF(COALESCE(CAST(X."&F61&" AS STRING),'')<>COALESCE(CAST(Y."&F61&"_SIMUL AS STRING),'') OR (X."&F61&" IS NULL AND Y."&F61&"_SIMUL IS NOT NULL ) OR (X."&F61&" IS NOT NULL AND Y."&F61&"_SIMUL IS NULL),1,0)) AS NUM_REG_DIF,'"&MAX('ID1&5'!L:L)+1&"' AS ID_EXEC, CURRENT_TIMESTAMP() AS TIME_EXEC FROM "&I61&" INNER JOIN "&J61&" "&K61), IF(C61="Validade",+IF(G61="Code List","SELECT '"&UPPER(B61)&"' AS TABELA, '"&UPPER(C61)&"' AS TIPOLOGIA_TESTE,'"&D61&"' AS TABELA_LT,'N/A' AS TABELA_SIMUL,'"&F61&"' AS CAMPO, "&"'${ref_date}' AS REF_DATE, COUNT(*) AS NUM_REG, SUM(IF(TRIM(CAST(X."&F61&" AS STRING))='' OR TRIM(CAST(X."&F61&" AS STRING)) IS NULL OR CAST(X."&F61&" AS STRING) NOT "&H61&",1,0)) AS NUM_REG_DIF,'"&MAX('ID1&5'!K:K)+1&"' AS ID_EXEC, CURRENT_TIMESTAMP() AS TIME_EXEC FROM "&I61,"SELECT '"&UPPER(B61)&"' AS TABELA, '"&UPPER(C61)&"' AS TIPOLOGIA_TESTE,'"&D61&"' AS TABELA_LT,'N/A' AS TABELA_SIMUL,'"&F61&"' AS CAMPO, "&"'${ref_date}' AS REF_DATE, COUNT(*) AS NUM_REG, SUM(IF(TRIM(CAST(X."&F61&" AS STRING))='' OR TRIM(CAST(X."&F61&" AS STRING)) IS NULL,1,0)) AS NUM_REG_DIF,'"&MAX('ID1&5'!K:K)+1&"' AS ID_EXEC, CURRENT_TIMESTAMP() AS TIME_EXEC FROM "&I61), IF(C61="Caracteres Especiais",+"SELECT '"&UPPER(B61)&"' AS TABELA, '"&UPPER(C61)&"' AS TIPOLOGIA_TESTE,'"&D61&"' AS TABELA_LT,'N/A' AS TABELA_SIMUL,'"&F61&"' AS CAMPO, "&"'${ref_date}' AS REF_DATE, COUNT(*) AS NUM_REG, SUM(IF(REGEXP_REPLACE(TRIM(CAST(X."&F61&" AS STRING)),'[^a-zA-Z0-9_\\s]','') <>TRIM(CAST(X."&F61&" AS STRING)),1,0)) AS NUM_REG_DIF,'"&MAX('ID1&5'!K:K)+1&"' AS ID_EXEC, CURRENT_TIMESTAMP() AS TIME_EXEC FROM "&I61, IF(C61="Missings",+"SELECT '"&UPPER(B61)&"' AS TABELA, '"&UPPER(C61)&"' AS TIPOLOGIA_TESTE,'"&D61&"' AS TABELA_LT,'N/A' AS TABELA_SIMUL,'"&F61&"' AS CAMPO, "&"'${ref_date}' AS REF_DATE, COUNT(*) AS NUM_REG, SUM(IF(TRIM(CAST(X."&F61&" AS STRING)) IN ('0000-00-00','0001-01-01','9999-12-31','MISS','00000','99999999999','99999999999.00','99999999999.000000'),1,0)) AS NUM_REG_DIF,'"&MAX('ID1&5'!K:K)+1&"' AS ID_EXEC, CURRENT_TIMESTAMP() AS TIME_EXEC FROM "&I61, IF(C61="Not applicable",+"SELECT '"&UPPER(B61)&"' AS TABELA, '"&UPPER(C61)&"' AS TIPOLOGIA_TESTE,'"&D61&"' AS TABELA_LT,'N/A' AS TABELA_SIMUL,'"&F61&"' AS CAMPO, "&"'${ref_date}' AS REF_DATE, COUNT(*) AS NUM_REG, SUM(IF(TRIM(CAST(X."&F61&" AS STRING)) IN ('N/A','11111111111','11111111111.00','11111111111.000000','1111-11-11'),1,0)) AS NUM_REG_DIF,'"&MAX('ID1&5'!K:K)+1&"' AS ID_EXEC, CURRENT_TIMESTAMP() AS TIME_EXEC FROM "&I61, IF(C61="Valores extremos",+"SELECT '"&UPPER(B61)&"' AS TABELA, '"&UPPER(C61)&"' AS TIPOLOGIA_TESTE,'"&D61&"' AS TABELA_LT,'N/A' AS TABELA_SIMUL,'"&F61&"' AS CAMPO, "&"'${ref_date}' AS REF_DATE, CAST(MIN("&F61&") AS STRING) AS VALOR_MIN, CAST(MAX("&F61&") AS STRING) AS VALOR_MAX,'"&MAX('ID1&5'!K:K)+1&"' AS ID_EXEC, CURRENT_TIMESTAMP() AS TIME_EXEC FROM "&MID(I61,1,LEN(I61)-2)&" AND CAST("&F61&" AS STRING) NOT IN ('0000-00-00','0001-01-01','9999-12-31','MISS','00000','99999999999','99999999999.00','99999999999.000000','N/A','11111111111','11111111111.00','11111111111.000000','1111-11-11'))X")))))) -> SELECT 'UNIV_OPER' AS TABELA, 'COERÊNCIA' AS TIPOLOGIA_TESTE,'BU_LOANTAPE_WORK.LT001_UNIV_OPER' AS TABELA_LT,'BU_LOANTAPE_WORK.SIMUL_LT001' AS TABELA_SIMUL,'idcomb_lt_final' AS CAMPO, '${ref_date}' AS REF_DATE, COUNT(*) AS NUM_REG, SUM(IF(COALESCE(CAST(X.idcomb_lt_final AS STRING),'')<>COALESCE(CAST(Y.idcomb_lt_final_SIMUL AS STRING),'') OR (X.idcomb_lt_final IS NULL AND Y.idcomb_lt_final_SIMUL IS NOT NULL ) OR (X.idcomb_lt_final IS NOT NULL AND Y.idcomb_lt_final_SIMUL IS NULL),1,0)) AS NUM_REG_DIF,'1' AS ID_EXEC, CURRENT_TIMESTAMP() AS TIME_EXEC FROM (SELECT a, idcomb_lt_final FROM BU_LOANTAPE_WORK.LT001_UNIV_OPER WHERE ref_date='${ref_date}' AND nome_perimetro='Individual Local' AND segmento='ESTR' AND ambito='SRB_MBDT' AND entidade='00100')X INNER JOIN (SELECT a AS a_SIMUL, idcomb_lt_final AS idcomb_lt_final_SIMUL FROM BU_LOANTAPE_WORK.SIMUL_LT001 WHERE ref_date='${ref_date}' AND nome_perimetro='Individual Local' AND segmento='ESTR' AND ambito='PILAR3' AND entidade='00100')Y ON X.A=Y.A_SIMUL | M61: =+"UNION ALL "&L61 -> UNION ALL SELECT 'UNIV_OPER' AS TABELA, 'COERÊNCIA' AS TIPOLOGIA_TESTE,'BU_LOANTAPE_WORK.LT001_UNIV_OPER' AS TABELA_LT,'BU_LOANTAPE_WORK.SIMUL_LT001' AS TABELA_SIMUL,'idcomb_lt_final' AS CAMPO, '${ref_date}' AS REF_DATE, COUNT(*) AS NUM_REG, SUM(IF(COALESCE(CAST(X.idcomb_lt_final AS STRING),'')<>COALESCE(CAST(Y.idcomb_lt_final_SIMUL AS STRING),'') OR (X.idcomb_lt_final IS NULL AND Y.idcomb_lt_final_SIMUL IS NOT NULL ) OR (X.idcomb_lt_final IS NOT NULL AND Y.idcomb_lt_final_SIMUL IS NULL),1,0)) AS NUM_REG_DIF,'1' AS ID_EXEC, CURRENT_TIMESTAMP() AS TIME_EXEC FROM (SELECT a, idcomb_lt_final FROM BU_LOANTAPE_WORK.LT001_UNIV_OPER WHERE ref_date='${ref_date}' AND nome_perimetro='Individual Local' AND segmento='ESTR' AND ambito='SRB_MBDT' AND entidade='00100')X INNER JOIN (SELECT a AS a_SIMUL, idcomb_lt_final AS idcomb_lt_final_SIMUL FROM BU_LOANTAPE_WORK.SIMUL_LT001 WHERE ref_date='${ref_date}' AND nome_perimetro='Individual Local' AND segmento='ESTR' AND ambito='PILAR3' AND entidade='00100')Y ON X.A=Y.A_SIMUL
B62: UNIV_OPER | C62: Coerência | D62: =+UPPER('0. Instruções'!$D$35&"."&VLOOKUP(B62,'0. Instruções'!$C$27:$D$32,2,FALSE)) -> BU_LOANTAPE_WORK.LT001_UNIV_OPER | E62: =+UPPER('0. Instruções'!$D$36&"."&VLOOKUP(B62,'0. Instruções'!$C$27:$E$32,3,FALSE)) -> BU_LOANTAPE_WORK.SIMUL_LT001 | F62: rank_insolv | I62: ="(SELECT "&VLOOKUP(B62,'0. Instruções'!$C$27:$G$32,4,FALSE)&", "&F62&" FROM "&D62&" WHERE "&'0. Instruções'!$D$42&")X" -> (SELECT a, rank_insolv FROM BU_LOANTAPE_WORK.LT001_UNIV_OPER WHERE ref_date='${ref_date}' AND nome_perimetro='Individual Local' AND segmento='ESTR' AND ambito='SRB_MBDT' AND entidade='00100')X | J62: ="(SELECT "&VLOOKUP(B62,'0. Instruções'!$C$27:$G$32,4,FALSE)&" AS "&VLOOKUP(B62,'0. Instruções'!$C$27:$G$32,4,FALSE)&"_SIMUL, "&F62&" AS "&F62&"_SIMUL FROM "&E62&" WHERE "&'0. Instruções'!$D$43&")Y" -> (SELECT a AS a_SIMUL, rank_insolv AS rank_insolv_SIMUL FROM BU_LOANTAPE_WORK.SIMUL_LT001 WHERE ref_date='${ref_date}' AND nome_perimetro='Individual Local' AND segmento='ESTR' AND ambito='PILAR3' AND entidade='00100')Y | K62: =+UPPER("ON X."&VLOOKUP(B62,'0. Instruções'!$C$27:$G$32,4,FALSE)&"=Y."&VLOOKUP(B62,'0. Instruções'!$C$27:$G$32,4,FALSE)&"_SIMUL") -> ON X.A=Y.A_SIMUL | L62: =+IF(C62="Coerência", +IF(LEFT(G62,5)="FLOAT","SELECT '"&UPPER(B62)&"' AS TABELA, '"&UPPER(C62)&"' AS TIPOLOGIA_TESTE,'"&D62&"' AS TABELA_LT,'"&E62&"' AS TABELA_SIMUL,'"&F62&"' AS CAMPO, "&"'${ref_date}' AS REF_DATE, COUNT(*) AS NUM_REG, SUM(IF((ABS(COALESCE(CAST(X."&F62&" AS DECIMAL(18,6)),0)-COALESCE(CAST(Y."&F62&"_SIMUL AS DECIMAL(18,6)),0))>0.000001) OR (X."&F62&" IS NULL AND Y."&F62&"_SIMUL IS NOT NULL ) OR (X."&F62&" IS NOT NULL AND Y."&F62&"_SIMUL IS NULL),1,0)) AS NUM_REG_DIF,'"&MAX('ID1&5'!K:K)+1&"' AS ID_EXEC, CURRENT_TIMESTAMP() AS TIME_EXEC FROM "&I62&" INNER JOIN "&J62&" "&K62,"SELECT '"&UPPER(B62)&"' AS TABELA, '"&UPPER(C62)&"' AS TIPOLOGIA_TESTE,'"&D62&"' AS TABELA_LT,'"&E62&"' AS TABELA_SIMUL,'"&F62&"' AS CAMPO, "&"'${ref_date}' AS REF_DATE, COUNT(*) AS NUM_REG, SUM(IF(COALESCE(CAST(X."&F62&" AS STRING),'')<>COALESCE(CAST(Y."&F62&"_SIMUL AS STRING),'') OR (X."&F62&" IS NULL AND Y."&F62&"_SIMUL IS NOT NULL ) OR (X."&F62&" IS NOT NULL AND Y."&F62&"_SIMUL IS NULL),1,0)) AS NUM_REG_DIF,'"&MAX('ID1&5'!L:L)+1&"' AS ID_EXEC, CURRENT_TIMESTAMP() AS TIME_EXEC FROM "&I62&" INNER JOIN "&J62&" "&K62), IF(C62="Validade",+IF(G62="Code List","SELECT '"&UPPER(B62)&"' AS TABELA, '"&UPPER(C62)&"' AS TIPOLOGIA_TESTE,'"&D62&"' AS TABELA_LT,'N/A' AS TABELA_SIMUL,'"&F62&"' AS CAMPO, "&"'${ref_date}' AS REF_DATE, COUNT(*) AS NUM_REG, SUM(IF(TRIM(CAST(X."&F62&" AS STRING))='' OR TRIM(CAST(X."&F62&" AS STRING)) IS NULL OR CAST(X."&F62&" AS STRING) NOT "&H62&",1,0)) AS NUM_REG_DIF,'"&MAX('ID1&5'!K:K)+1&"' AS ID_EXEC, CURRENT_TIMESTAMP() AS TIME_EXEC FROM "&I62,"SELECT '"&UPPER(B62)&"' AS TABELA, '"&UPPER(C62)&"' AS TIPOLOGIA_TESTE,'"&D62&"' AS TABELA_LT,'N/A' AS TABELA_SIMUL,'"&F62&"' AS CAMPO, "&"'${ref_date}' AS REF_DATE, COUNT(*) AS NUM_REG, SUM(IF(TRIM(CAST(X."&F62&" AS STRING))='' OR TRIM(CAST(X."&F62&" AS STRING)) IS NULL,1,0)) AS NUM_REG_DIF,'"&MAX('ID1&5'!K:K)+1&"' AS ID_EXEC, CURRENT_TIMESTAMP() AS TIME_EXEC FROM "&I62), IF(C62="Caracteres Especiais",+"SELECT '"&UPPER(B62)&"' AS TABELA, '"&UPPER(C62)&"' AS TIPOLOGIA_TESTE,'"&D62&"' AS TABELA_LT,'N/A' AS TABELA_SIMUL,'"&F62&"' AS CAMPO, "&"'${ref_date}' AS REF_DATE, COUNT(*) AS NUM_REG, SUM(IF(REGEXP_REPLACE(TRIM(CAST(X."&F62&" AS STRING)),'[^a-zA-Z0-9_\\s]','') <>TRIM(CAST(X."&F62&" AS STRING)),1,0)) AS NUM_REG_DIF,'"&MAX('ID1&5'!K:K)+1&"' AS ID_EXEC, CURRENT_TIMESTAMP() AS TIME_EXEC FROM "&I62, IF(C62="Missings",+"SELECT '"&UPPER(B62)&"' AS TABELA, '"&UPPER(C62)&"' AS TIPOLOGIA_TESTE,'"&D62&"' AS TABELA_LT,'N/A' AS TABELA_SIMUL,'"&F62&"' AS CAMPO, "&"'${ref_date}' AS REF_DATE, COUNT(*) AS NUM_REG, SUM(IF(TRIM(CAST(X."&F62&" AS STRING)) IN ('0000-00-00','0001-01-01','9999-12-31','MISS','00000','99999999999','99999999999.00','99999999999.000000'),1,0)) AS NUM_REG_DIF,'"&MAX('ID1&5'!K:K)+1&"' AS ID_EXEC, CURRENT_TIMESTAMP() AS TIME_EXEC FROM "&I62, IF(C62="Not applicable",+"SELECT '"&UPPER(B62)&"' AS TABELA, '"&UPPER(C62)&"' AS TIPOLOGIA_TESTE,'"&D62&"' AS TABELA_LT,'N/A' AS TABELA_SIMUL,'"&F62&"' AS CAMPO, "&"'${ref_date}' AS REF_DATE, COUNT(*) AS NUM_REG, SUM(IF(TRIM(CAST(X."&F62&" AS STRING)) IN ('N/A','11111111111','11111111111.00','11111111111.000000','1111-11-11'),1,0)) AS NUM_REG_DIF,'"&MAX('ID1&5'!K:K)+1&"' AS ID_EXEC, CURRENT_TIMESTAMP() AS TIME_EXEC FROM "&I62, IF(C62="Valores extremos",+"SELECT '"&UPPER(B62)&"' AS TABELA, '"&UPPER(C62)&"' AS TIPOLOGIA_TESTE,'"&D62&"' AS TABELA_LT,'N/A' AS TABELA_SIMUL,'"&F62&"' AS CAMPO, "&"'${ref_date}' AS REF_DATE, CAST(MIN("&F62&") AS STRING) AS VALOR_MIN, CAST(MAX("&F62&") AS STRING) AS VALOR_MAX,'"&MAX('ID1&5'!K:K)+1&"' AS ID_EXEC, CURRENT_TIMESTAMP() AS TIME_EXEC FROM "&MID(I62,1,LEN(I62)-2)&" AND CAST("&F62&" AS STRING) NOT IN ('0000-00-00','0001-01-01','9999-12-31','MISS','00000','99999999999','99999999999.00','99999999999.000000','N/A','11111111111','11111111111.00','11111111111.000000','1111-11-11'))X")))))) -> SELECT 'UNIV_OPER' AS TABELA, 'COERÊNCIA' AS TIPOLOGIA_TESTE,'BU_LOANTAPE_WORK.LT001_UNIV_OPER' AS TABELA_LT,'BU_LOANTAPE_WORK.SIMUL_LT001' AS TABELA_SIMUL,'rank_insolv' AS CAMPO, '${ref_date}' AS REF_DATE, COUNT(*) AS NUM_REG, SUM(IF(COALESCE(CAST(X.rank_insolv AS STRING),'')<>COALESCE(CAST(Y.rank_insolv_SIMUL AS STRING),'') OR (X.rank_insolv IS NULL AND Y.rank_insolv_SIMUL IS NOT NULL ) OR (X.rank_insolv IS NOT NULL AND Y.rank_insolv_SIMUL IS NULL),1,0)) AS NUM_REG_DIF,'1' AS ID_EXEC, CURRENT_TIMESTAMP() AS TIME_EXEC FROM (SELECT a, rank_insolv FROM BU_LOANTAPE_WORK.LT001_UNIV_OPER WHERE ref_date='${ref_date}' AND nome_perimetro='Individual Local' AND segmento='ESTR' AND ambito='SRB_MBDT' AND entidade='00100')X INNER JOIN (SELECT a AS a_SIMUL, rank_insolv AS rank_insolv_SIMUL FROM BU_LOANTAPE_WORK.SIMUL_LT001 WHERE ref_date='${ref_date}' AND nome_perimetro='Individual Local' AND segmento='ESTR' AND ambito='PILAR3' AND entidade='00100')Y ON X.A=Y.A_SIMUL | M62: =+"UNION ALL "&L62 -> UNION ALL SELECT 'UNIV_OPER' AS TABELA, 'COERÊNCIA' AS TIPOLOGIA_TESTE,'BU_LOANTAPE_WORK.LT001_UNIV_OPER' AS TABELA_LT,'BU_LOANTAPE_WORK.SIMUL_LT001' AS TABELA_SIMUL,'rank_insolv' AS CAMPO, '${ref_date}' AS REF_DATE, COUNT(*) AS NUM_REG, SUM(IF(COALESCE(CAST(X.rank_insolv AS STRING),'')<>COALESCE(CAST(Y.rank_insolv_SIMUL AS STRING),'') OR (X.rank_insolv IS NULL AND Y.rank_insolv_SIMUL IS NOT NULL ) OR (X.rank_insolv IS NOT NULL AND Y.rank_insolv_SIMUL IS NULL),1,0)) AS NUM_REG_DIF,'1' AS ID_EXEC, CURRENT_TIMESTAMP() AS TIME_EXEC FROM (SELECT a, rank_insolv FROM BU_LOANTAPE_WORK.LT001_UNIV_OPER WHERE ref_date='${ref_date}' AND nome_perimetro='Individual Local' AND segmento='ESTR' AND ambito='SRB_MBDT' AND entidade='00100')X INNER JOIN (SELECT a AS a_SIMUL, rank_insolv AS rank_insolv_SIMUL FROM BU_LOANTAPE_WORK.SIMUL_LT001 WHERE ref_date='${ref_date}' AND nome_perimetro='Individual Local' AND segmento='ESTR' AND ambito='PILAR3' AND entidade='00100')Y ON X.A=Y.A_SIMUL
B63: INSTRUMENT | C63: Coerência | D63: =+UPPER('0. Instruções'!$D$35&"."&VLOOKUP(B63,'0. Instruções'!$C$27:$D$32,2,FALSE)) -> BU_LOANTAPE_WORK.LT002_INSTRUMENT | E63: =+UPPER('0. Instruções'!$D$36&"."&VLOOKUP(B63,'0. Instruções'!$C$27:$E$32,3,FALSE)) -> BU_LOANTAPE_WORK.SIMUL_LT002_INSTRUMENT | F63: cntrct_id | I63: ="(SELECT "&VLOOKUP(B63,'0. Instruções'!$C$27:$G$32,4,FALSE)&", "&F63&" FROM "&D63&" WHERE "&'0. Instruções'!$D$42&")X" -> (SELECT instrmnt_id, cntrct_id FROM BU_LOANTAPE_WORK.LT002_INSTRUMENT WHERE ref_date='${ref_date}' AND nome_perimetro='Individual Local' AND segmento='ESTR' AND ambito='SRB_MBDT' AND entidade='00100')X | J63: ="(SELECT "&VLOOKUP(B63,'0. Instruções'!$C$27:$G$32,4,FALSE)&" AS "&VLOOKUP(B63,'0. Instruções'!$C$27:$G$32,4,FALSE)&"_SIMUL, "&F63&" AS "&F63&"_SIMUL FROM "&E63&" WHERE "&'0. Instruções'!$D$43&")Y" -> (SELECT instrmnt_id AS instrmnt_id_SIMUL, cntrct_id AS cntrct_id_SIMUL FROM BU_LOANTAPE_WORK.SIMUL_LT002_INSTRUMENT WHERE ref_date='${ref_date}' AND nome_perimetro='Individual Local' AND segmento='ESTR' AND ambito='PILAR3' AND entidade='00100')Y | K63: =+UPPER("ON X."&VLOOKUP(B63,'0. Instruções'!$C$27:$G$32,4,FALSE)&"=Y."&VLOOKUP(B63,'0. Instruções'!$C$27:$G$32,4,FALSE)&"_SIMUL") -> ON X.INSTRMNT_ID=Y.INSTRMNT_ID_SIMUL | L63: =+IF(C63="Coerência", +IF(LEFT(G63,5)="FLOAT","SELECT '"&UPPER(B63)&"' AS TABELA, '"&UPPER(C63)&"' AS TIPOLOGIA_TESTE,'"&D63&"' AS TABELA_LT,'"&E63&"' AS TABELA_SIMUL,'"&F63&"' AS CAMPO, "&"'${ref_date}' AS REF_DATE, COUNT(*) AS NUM_REG, SUM(IF((ABS(COALESCE(CAST(X."&F63&" AS DECIMAL(18,6)),0)-COALESCE(CAST(Y."&F63&"_SIMUL AS DECIMAL(18,6)),0))>0.000001) OR (X."&F63&" IS NULL AND Y."&F63&"_SIMUL IS NOT NULL ) OR (X."&F63&" IS NOT NULL AND Y."&F63&"_SIMUL IS NULL),1,0)) AS NUM_REG_DIF,'"&MAX('ID1&5'!K:K)+1&"' AS ID_EXEC, CURRENT_TIMESTAMP() AS TIME_EXEC FROM "&I63&" INNER JOIN "&J63&" "&K63,"SELECT '"&UPPER(B63)&"' AS TABELA, '"&UPPER(C63)&"' AS TIPOLOGIA_TESTE,'"&D63&"' AS TABELA_LT,'"&E63&"' AS TABELA_SIMUL,'"&F63&"' AS CAMPO, "&"'${ref_date}' AS REF_DATE, COUNT(*) AS NUM_REG, SUM(IF(COALESCE(CAST(X."&F63&" AS STRING),'')<>COALESCE(CAST(Y."&F63&"_SIMUL AS STRING),'') OR (X."&F63&" IS NULL AND Y."&F63&"_SIMUL IS NOT NULL ) OR (X."&F63&" IS NOT NULL AND Y."&F63&"_SIMUL IS NULL),1,0)) AS NUM_REG_DIF,'"&MAX('ID1&5'!L:L)+1&"' AS ID_EXEC, CURRENT_TIMESTAMP() AS TIME_EXEC FROM "&I63&" INNER JOIN "&J63&" "&K63), IF(C63="Validade",+IF(G63="Code List","SELECT '"&UPPER(B63)&"' AS TABELA, '"&UPPER(C63)&"' AS TIPOLOGIA_TESTE,'"&D63&"' AS TABELA_LT,'N/A' AS TABELA_SIMUL,'"&F63&"' AS CAMPO, "&"'${ref_date}' AS REF_DATE, COUNT(*) AS NUM_REG, SUM(IF(TRIM(CAST(X."&F63&" AS STRING))='' OR TRIM(CAST(X."&F63&" AS STRING)) IS NULL OR CAST(X."&F63&" AS STRING) NOT "&H63&",1,0)) AS NUM_REG_DIF,'"&MAX('ID1&5'!K:K)+1&"' AS ID_EXEC, CURRENT_TIMESTAMP() AS TIME_EXEC FROM "&I63,"SELECT '"&UPPER(B63)&"' AS TABELA, '"&UPPER(C63)&"' AS TIPOLOGIA_TESTE,'"&D63&"' AS TABELA_LT,'N/A' AS TABELA_SIMUL,'"&F63&"' AS CAMPO, "&"'${ref_date}' AS REF_DATE, COUNT(*) AS NUM_REG, SUM(IF(TRIM(CAST(X."&F63&" AS STRING))='' OR TRIM(CAST(X."&F63&" AS STRING)) IS NULL,1,0)) AS NUM_REG_DIF,'"&MAX('ID1&5'!K:K)+1&"' AS ID_EXEC, CURRENT_TIMESTAMP() AS TIME_EXEC FROM "&I63), IF(C63="Caracteres Especiais",+"SELECT '"&UPPER(B63)&"' AS TABELA, '"&UPPER(C63)&"' AS TIPOLOGIA_TESTE,'"&D63&"' AS TABELA_LT,'N/A' AS TABELA_SIMUL,'"&F63&"' AS CAMPO, "&"'${ref_date}' AS REF_DATE, COUNT(*) AS NUM_REG, SUM(IF(REGEXP_REPLACE(TRIM(CAST(X."&F63&" AS STRING)),'[^a-zA-Z0-9_\\s]','') <>TRIM(CAST(X."&F63&" AS STRING)),1,0)) AS NUM_REG_DIF,'"&MAX('ID1&5'!K:K)+1&"' AS ID_EXEC, CURRENT_TIMESTAMP() AS TIME_EXEC FROM "&I63, IF(C63="Missings",+"SELECT '"&UPPER(B63)&"' AS TABELA, '"&UPPER(C63)&"' AS TIPOLOGIA_TESTE,'"&D63&"' AS TABELA_LT,'N/A' AS TABELA_SIMUL,'"&F63&"' AS CAMPO, "&"'${ref_date}' AS REF_DATE, COUNT(*) AS NUM_REG, SUM(IF(TRIM(CAST(X."&F63&" AS STRING)) IN ('0000-00-00','0001-01-01','9999-12-31','MISS','00000','99999999999','99999999999.00','99999999999.000000'),1,0)) AS NUM_REG_DIF,'"&MAX('ID1&5'!K:K)+1&"' AS ID_EXEC, CURRENT_TIMESTAMP() AS TIME_EXEC FROM "&I63, IF(C63="Not applicable",+"SELECT '"&UPPER(B63)&"' AS TABELA, '"&UPPER(C63)&"' AS TIPOLOGIA_TESTE,'"&D63&"' AS TABELA_LT,'N/A' AS TABELA_SIMUL,'"&F63&"' AS CAMPO, "&"'${ref_date}' AS REF_DATE, COUNT(*) AS NUM_REG, SUM(IF(TRIM(CAST(X."&F63&" AS STRING)) IN ('N/A','11111111111','11111111111.00','11111111111.000000','1111-11-11'),1,0)) AS NUM_REG_DIF,'"&MAX('ID1&5'!K:K)+1&"' AS ID_EXEC, CURRENT_TIMESTAMP() AS TIME_EXEC FROM "&I63, IF(C63="Valores extremos",+"SELECT '"&UPPER(B63)&"' AS TABELA, '"&UPPER(C63)&"' AS TIPOLOGIA_TESTE,'"&D63&"' AS TABELA_LT,'N/A' AS TABELA_SIMUL,'"&F63&"' AS CAMPO, "&"'${ref_date}' AS REF_DATE, CAST(MIN("&F63&") AS STRING) AS VALOR_MIN, CAST(MAX("&F63&") AS STRING) AS VALOR_MAX,'"&MAX('ID1&5'!K:K)+1&"' AS ID_EXEC, CURRENT_TIMESTAMP() AS TIME_EXEC FROM "&MID(I63,1,LEN(I63)-2)&" AND CAST("&F63&" AS STRING) NOT IN ('0000-00-00','0001-01-01','9999-12-31','MISS','00000','99999999999','99999999999.00','99999999999.000000','N/A','11111111111','11111111111.00','11111111111.000000','1111-11-11'))X")))))) -> SELECT 'INSTRUMENT' AS TABELA, 'COERÊNCIA' AS TIPOLOGIA_TESTE,'BU_LOANTAPE_WORK.LT002_INSTRUMENT' AS TABELA_LT,'BU_LOANTAPE_WORK.SIMUL_LT002_INSTRUMENT' AS TABELA_SIMUL,'cntrct_id' AS CAMPO, '${ref_date}' AS REF_DATE, COUNT(*) AS NUM_REG, SUM(IF(COALESCE(CAST(X.cntrct_id AS STRING),'')<>COALESCE(CAST(Y.cntrct_id_SIMUL AS STRING),'') OR (X.cntrct_id IS NULL AND Y.cntrct_id_SIMUL IS NOT NULL ) OR (X.cntrct_id IS NOT NULL AND Y.cntrct_id_SIMUL IS NULL),1,0)) AS NUM_REG_DIF,'1' AS ID_EXEC, CURRENT_TIMESTAMP() AS TIME_EXEC FROM (SELECT instrmnt_id, cntrct_id FROM BU_LOANTAPE_WORK.LT002_INSTRUMENT WHERE ref_date='${ref_date}' AND nome_perimetro='Individual Local' AND segmento='ESTR' AND ambito='SRB_MBDT' AND entidade='00100')X INNER JOIN (SELECT instrmnt_id AS instrmnt_id_SIMUL, cntrct_id AS cntrct_id_SIMUL FROM BU_LOANTAPE_WORK.SIMUL_LT002_INSTRUMENT WHERE ref_date='${ref_date}' AND nome_perimetro='Individual Local' AND segmento='ESTR' AND ambito='PILAR3' AND entidade='00100')Y ON X.INSTRMNT_ID=Y.INSTRMNT_ID_SIMUL | M63: =+"UNION ALL "&L63 -> UNION ALL SELECT 'INSTRUMENT' AS TABELA, 'COERÊNCIA' AS TIPOLOGIA_TESTE,'BU_LOANTAPE_WORK.LT002_INSTRUMENT' AS TABELA_LT,'BU_LOANTAPE_WORK.SIMUL_LT002_INSTRUMENT' AS TABELA_SIMUL,'cntrct_id' AS CAMPO, '${ref_date}' AS REF_DATE, COUNT(*) AS NUM_REG, SUM(IF(COALESCE(CAST(X.cntrct_id AS STRING),'')<>COALESCE(CAST(Y.cntrct_id_SIMUL AS STRING),'') OR (X.cntrct_id IS NULL AND Y.cntrct_id_SIMUL IS NOT NULL ) OR (X.cntrct_id IS NOT NULL AND Y.cntrct_id_SIMUL IS NULL),1,0)) AS NUM_REG_DIF,'1' AS ID_EXEC, CURRENT_TIMESTAMP() AS TIME_EXEC FROM (SELECT instrmnt_id, cntrct_id FROM BU_LOANTAPE_WORK.LT002_INSTRUMENT WHERE ref_date='${ref_date}' AND nome_perimetro='Individual Local' AND segmento='ESTR' AND ambito='SRB_MBDT' AND entidade='00100')X INNER JOIN (SELECT instrmnt_id AS instrmnt_id_SIMUL, cntrct_id AS cntrct_id_SIMUL FROM BU_LOANTAPE_WORK.SIMUL_LT002_INSTRUMENT WHERE ref_date='${ref_date}' AND nome_perimetro='Individual Local' AND segmento='ESTR' AND ambito='PILAR3' AND entidade='00100')Y ON X.INSTRMNT_ID=Y.INSTRMNT_ID_SIMUL
