Workbook

Sheet 0. Instruções
B6: 0. Instruções
B8: Projeto | D8: Testes GD & Pilar 3
B9: Âmbito | D9: Análise dos campo da Loan Tape Pilar III
B11: Para a validação dos campos da Loan Tape Pilar III é necessário percorrer os seguintes steps:
B14: 1. Atualizar o script de simulação com o campo em análise.
B15: 1.1. Verificar a especificação do campo em análise. Se aplicável, verificar se é necessário reportar valor para ajustes.
B16: 1.2. Montar a simulação do campo tendo atenção aos seguintes pormenores:
B17: a) Não vamos fazer JOIN com a tabela de parametrização (LT803). Em alternativa, montamos um CASE WHEN ou importamos a parametrização.
B18: b) Para operações de ajustes verificar se o campo deve reportar valor.
B19: c) Se for necessário aplicar algum filtro (ou tratamento) que não está na especificação deixar um comentário no código.
B20: d) Garantir que não existem duplicados e deixar no código o número de registos de cada LEFT JOIN.
B21: 2. Executar no HUE (em HIVE) o CREATE TABLE do script de simulação.
B22: 3. Executar no HUE o script de controlo de universo.
B23: a) O número de registos em comum tem de ser igual ao número de registos do teste de coerência. Caso tenhamos registos que não são comuns é necessário ver exemplos para ver o que está a acontecer.
B24: 4. Verificar com IT o nome da tabela a testar e filtros. Caso seja necessário, atualizar as tabelas infra:
C26: Nome da Tabela | D26: Tabela Loan Tape Pilar 3 | E26: Tabela Simulada | F26: Chave 1 | G26: Chave 2
C27: Entity | D27: lt003_entity | E27: lt003_entity | F27: entty_id
C28: Instrument | D28: lt002_instrument | E28: lt002_instrument | F28: instrmnt_id
C29: Protection | D29: lt004_protection | E29: lt004_protection | F29: prtctn_id
C30: INSTR_ENTITY | D30: lt005_instr_ent | E30: lt005_instr_ent | F30: instrmnt_id | G30: entty_id
C31: INSTR_PROTECTION | D31: lt006_instr_prot | E31: lt006_instr_prot | F31: instrmnt_id | G31: prtctn_id
C32: Instr_activity | D32: lt007_instr_activity | E32: lt007_instr_activity | F32: instrmnt_id
C34: Filtros
C35: Schema Loan Tape Pilar 3 | D35: cd_loan_tapes_bce
C36: Schema Simulada | D36: bu_loantape_work
C37: nome_perimetro | D37: Individual Corporativo
C38: segmento | D38: ESTR
C39: ambito (Pilar 3) | D39: PM
C40: ambito (PM) | D40: PM
C41: entidade | D41: 00100
C42: Filtro Loan Tape Pilar 3 | D42: =+"ref_date='${ref_date}'"&" AND "&C37&"='"&D37&"' AND "&C38&"='"&D38&"' AND ambito='"&D39&"'"&" AND "&C41&"='"&D41&"'" -> ref_date='${ref_date}' AND nome_perimetro='Individual Corporativo' AND segmento='ESTR' AND ambito='PM' AND entidade='00100'
C43: Filtro Simulada | D43: =+"ref_date='${ref_date}'"&" AND "&C37&"='"&D37&"' AND "&C38&"='"&D38&"' AND ambito='"&D39&"'"&" AND "&C41&"='"&D41&"'" -> ref_date='${ref_date}' AND nome_perimetro='Individual Corporativo' AND segmento='ESTR' AND ambito='PM' AND entidade='00100'
B45: 5. Executar no HUE a bateria de testes da sheet 2. Script para o campo em análise
B46: a) Analisar resultados. Caso no teste de coerência conste diferenças é necessário ver exemplos. Deixo abaixo uma query de exemplo:
C48: SELECT *
C49: FROM
C50: (SELECT instrmnt_id,
C51: LNS_CLLTRLZD_CLSSFCTN
C52: FROM BU_LOANTAPE_WORK.LT002_INSTRUMENT
C53: WHERE ref_date='${ref_date}'
C54: AND nome_perimetro='Individual Corporativo'
C55: AND segmento='ESTR'
C56: AND ambito='PILAR3')X
C57: INNER JOIN
C58: (SELECT instrmnt_id AS instrmnt_id_SIMUL,
C59: LNS_CLLTRLZD_CLSSFCTN AS LNS_CLLTRLZD_CLSSFCTN_SIMUL
... C61: WHERE COALESCE(CAST(X.LNS_CLLTRLZD_CLSSFCTN AS STRING),'')<>COALESCE(CAST(Y.LNS_CLLTRLZD_CLSSFCTN_SIMUL AS STRING),'')
B69: 6. XXX
B70: 7. XXX

Sheet 1. Status
L2: Instr_activity
H6: 1. Status dos Testes
H8: REF_DATE | I8: 45596
B9: Auxiliar
B10: Coerência | C10: Validade | D10: Caracteres Especiais | E10: Missings | F10: Not applicable | H10: Tabela | I10: Campo | J10: Testes Corridos (#) | K10: Número de Registos ID1. (#) | L10: ID Exec. 1. | M10: 1. Erros de Coerência (#) | N10: Número de Registos ID2&9 (#) | O10: ID Exec. 2 | P10: 2. Erros de Valores Admitidos (#) | Q10: ID Exec. 3. | R10: 3. Erros de Caract. Especiais (#) | S10: ID Exec. 4. | T10: 4. Registos com Missing (#) | U10: ID Exec. 5. | V10: 5. Registos com N/A (#) | W10: 6. Valor Mínimo | X10: 7. Valor Máximo | Y10: Comentário | Z10: Status
A11: =+H11&I11&$I$8 -> ENTITYCOD_SOC45596 | H11: ENTITY | I11: COD_SOC | J11: =+COUNTIF('ID1&5'!G:G,'1. Status'!I11) -> 0 | K11: =+IFERROR(VLOOKUP(CONCATENATE(A11,$B$10,B11),'ID1&5'!B:J,8,FALSE),"-") -> - | L11: =+IFERROR(VLOOKUP(B11,'ID1&5'!K:L,2,FALSE),"-") -> - | M11: =+IFERROR(VLOOKUP(CONCATENATE(A11,$B$10,B11),'ID1&5'!B:J,9,FALSE),"-") -> - | N11: =+IFERROR(VLOOKUP(CONCATENATE(A11,$C$10,C11),'ID1&5'!B:J,8,FALSE),"-") -> - | O11: =+IFERROR(VLOOKUP(C11,'ID1&5'!K:L,2,FALSE),"-") -> - | P11: =+IFERROR(VLOOKUP(CONCATENATE(A11,$C$10,C11),'ID1&5'!B:J,9,FALSE),"-") -> - | Q11: =+IFERROR(VLOOKUP(D11,'ID1&5'!K:L,2,FALSE),"-") -> - | R11: =+IFERROR(VLOOKUP(CONCATENATE(A11,$D$10,D11),'ID1&5'!B:J,9,FALSE),"-") -> - | S11: =+IFERROR(VLOOKUP(E11,'ID1&5'!K:L,2,FALSE),"-") -> - | T11: =+IFERROR(VLOOKUP(CONCATENATE(A11,$E$10,E11),'ID1&5'!B:J,9,FALSE),"-") -> - | U11: =+IFERROR(VLOOKUP(F11,'ID1&5'!K:L,2,FALSE),"-") -> - | V11: =+IFERROR(VLOOKUP(CONCATENATE(A11,$F$10,F11),'ID1&5'!B:J,9,FALSE),"-") -> - | W11: =+IFERROR(VLOOKUP(A11,'ID6&7'!A:I,9,FALSE),"-") -> - | X11: =+IFERROR(VLOOKUP(A11,'ID6&7'!A:J,10,FALSE),"-") -> - | Z11: =+IF(J11=0,"Por iniciar",IF(OR(K11="-",M11="-",P11="-",R11="-",T11="-",V11="-"),"Em testes",IF(AND(M11=0,P11=0,R11=0,T11<>K11,V11<>K11),"OK","NOK"))) -> Por iniciar
A12: =+H12&I12&$I$8 -> ENTITYCNTRY45596 | H12: ENTITY | I12: CNTRY | J12: =+COUNTIF('ID1&5'!G:G,'1. Status'!I12) -> 0 | K12: =+IFERROR(VLOOKUP(CONCATENATE(A12,$B$10,B12),'ID1&5'!B:J,8,FALSE),"-") -> - | L12: =+IFERROR(VLOOKUP(B12,'ID1&5'!K:L,2,FALSE),"-") -> - | M12: =+IFERROR(VLOOKUP(CONCATENATE(A12,$B$10,B12),'ID1&5'!B:J,9,FALSE),"-") -> - | N12: =+IFERROR(VLOOKUP(CONCATENATE(A12,$C$10,C12),'ID1&5'!B:J,8,FALSE),"-") -> - | O12: =+IFERROR(VLOOKUP(C12,'ID1&5'!K:L,2,FALSE),"-") -> - | P12: =+IFERROR(VLOOKUP(CONCATENATE(A12,$C$10,C12),'ID1&5'!B:J,9,FALSE),"-") -> - | Q12: =+IFERROR(VLOOKUP(D12,'ID1&5'!K:L,2,FALSE),"-") -> - | R12: =+IFERROR(VLOOKUP(CONCATENATE(A12,$D$10,D12),'ID1&5'!B:J,9,FALSE),"-") -> - | S12: =+IFERROR(VLOOKUP(E12,'ID1&5'!K:L,2,FALSE),"-") -> - | T12: =+IFERROR(VLOOKUP(CONCATENATE(A12,$E$10,E12),'ID1&5'!B:J,9,FALSE),"-") -> - | U12: =+IFERROR(VLOOKUP(F12,'ID1&5'!K:L,2,FALSE),"-") -> - | V12: =+IFERROR(VLOOKUP(CONCATENATE(A12,$F$10,F12),'ID1&5'!B:J,9,FALSE),"-") -> - | W12: =+IFERROR(VLOOKUP(A12,'ID6&7'!A:I,9,FALSE),"-") -> - | X12: =+IFERROR(VLOOKUP(A12,'ID6&7'!A:J,10,FALSE),"-") -> - | Z12: =+IF(J12=0,"Por iniciar",IF(OR(K12="-",M12="-",P12="-",R12="-",T12="-",V12="-"),"Em testes",IF(AND(M12=0,P12=0,R12=0,T12<>K12,V12<>K12),"OK","NOK"))) -> Por iniciar
A13: =+H13&I13&$I$8 -> ENTITYDT_BRTH45596 | H13: ENTITY | I13: DT_BRTH | J13: =+COUNTIF('ID1&5'!G:G,'1. Status'!I13) -> 0 | K13: =+IFERROR(VLOOKUP(CONCATENATE(A13,$B$10,B13),'ID1&5'!B:J,8,FALSE),"-") -> - | L13: =+IFERROR(VLOOKUP(B13,'ID1&5'!K:L,2,FALSE),"-") -> - | M13: =+IFERROR(VLOOKUP(CONCATENATE(A13,$B$10,B13),'ID1&5'!B:J,9,FALSE),"-") -> - | N13: =+IFERROR(VLOOKUP(CONCATENATE(A13,$C$10,C13),'ID1&5'!B:J,8,FALSE),"-") -> - | O13: =+IFERROR(VLOOKUP(C13,'ID1&5'!K:L,2,FALSE),"-") -> - | P13: =+IFERROR(VLOOKUP(CONCATENATE(A13,$C$10,C13),'ID1&5'!B:J,9,FALSE),"-") -> - | Q13: =+IFERROR(VLOOKUP(D13,'ID1&5'!K:L,2,FALSE),"-") -> - | R13: =+IFERROR(VLOOKUP(CONCATENATE(A13,$D$10,D13),'ID1&5'!B:J,9,FALSE),"-") -> - | S13: =+IFERROR(VLOOKUP(E13,'ID1&5'!K:L,2,FALSE),"-") -> - | T13: =+IFERROR(VLOOKUP(CONCATENATE(A13,$E$10,E13),'ID1&5'!B:J,9,FALSE),"-") -> - | U13: =+IFERROR(VLOOKUP(F13,'ID1&5'!K:L,2,FALSE),"-") -> - | V13: =+IFERROR(VLOOKUP(CONCATENATE(A13,$F$10,F13),'ID1&5'!B:J,9,FALSE),"-") -> - | W13: =+IFERROR(VLOOKUP(A13,'ID6&7'!A:I,9,FALSE),"-") -> - | X13: =+IFERROR(VLOOKUP(A13,'ID6&7'!A:J,10,FALSE),"-") -> - | Z13: =+IF(J13=0,"Por iniciar",IF(OR(K13="-",M13="-",P13="-",R13="-",T13="-",V13="-"),"Em testes",IF(AND(M13=0,P13=0,R13=0,T13<>K13,V13<>K13),"OK","NOK"))) -> Por iniciar
A14: =+H14&I14&$I$8 -> ENTITYDT_DFLT_STTS45596 | H14: ENTITY | I14: DT_DFLT_STTS | J14: =+COUNTIF('ID1&5'!G:G,'1. Status'!I14) -> 0 | K14: =+IFERROR(VLOOKUP(CONCATENATE(A14,$B$10,B14),'ID1&5'!B:J,8,FALSE),"-") -> - | L14: =+IFERROR(VLOOKUP(B14,'ID1&5'!K:L,2,FALSE),"-") -> - | M14: =+IFERROR(VLOOKUP(CONCATENATE(A14,$B$10,B14),'ID1&5'!B:J,9,FALSE),"-") -> - | N14: =+IFERROR(VLOOKUP(CONCATENATE(A14,$C$10,C14),'ID1&5'!B:J,8,FALSE),"-") -> - | O14: =+IFERROR(VLOOKUP(C14,'ID1&5'!K:L,2,FALSE),"-") -> - | P14: =+IFERROR(VLOOKUP(CONCATENATE(A14,$C$10,C14),'ID1&5'!B:J,9,FALSE),"-") -> - | Q14: =+IFERROR(VLOOKUP(D14,'ID1&5'!K:L,2,FALSE),"-") -> - | R14: =+IFERROR(VLOOKUP(CONCATENATE(A14,$D$10,D14),'ID1&5'!B:J,9,FALSE),"-") -> - | S14: =+IFERROR(VLOOKUP(E14,'ID1&5'!K:L,2,FALSE),"-") -> - | T14: =+IFERROR(VLOOKUP(CONCATENATE(A14,$E$10,E14),'ID1&5'!B:J,9,FALSE),"-") -> - | U14: =+IFERROR(VLOOKUP(F14,'ID1&5'!K:L,2,FALSE),"-") -> - | V14: =+IFERROR(VLOOKUP(CONCATENATE(A14,$F$10,F14),'ID1&5'!B:J,9,FALSE),"-") -> - | W14: =+IFERROR(VLOOKUP(A14,'ID6&7'!A:I,9,FALSE),"-") -> - | X14: =+IFERROR(VLOOKUP(A14,'ID6&7'!A:J,10,FALSE),"-") -> - | Z14: =+IF(J14=0,"Por iniciar",IF(OR(K14="-",M14="-",P14="-",R14="-",T14="-",V14="-"),"Em testes",IF(AND(M14=0,P14=0,R14=0,T14<>K14,V14<>K14),"OK","NOK"))) -> Por iniciar
A15: =+H15&I15&$I$8 -> ENTITYDT_FNNCL_STTMTS45596 | H15: ENTITY | I15: DT_FNNCL_STTMTS | J15: =+COUNTIF('ID1&5'!G:G,'1. Status'!I15) -> 0 | K15: =+IFERROR(VLOOKUP(CONCATENATE(A15,$B$10,B15),'ID1&5'!B:J,8,FALSE),"-") -> - | L15: =+IFERROR(VLOOKUP(B15,'ID1&5'!K:L,2,FALSE),"-") -> - | M15: =+IFERROR(VLOOKUP(CONCATENATE(A15,$B$10,B15),'ID1&5'!B:J,9,FALSE),"-") -> - | N15: =+IFERROR(VLOOKUP(CONCATENATE(A15,$C$10,C15),'ID1&5'!B:J,8,FALSE),"-") -> - | O15: =+IFERROR(VLOOKUP(C15,'ID1&5'!K:L,2,FALSE),"-") -> - | P15: =+IFERROR(VLOOKUP(CONCATENATE(A15,$C$10,C15),'ID1&5'!B:J,9,FALSE),"-") -> - | Q15: =+IFERROR(VLOOKUP(D15,'ID1&5'!K:L,2,FALSE),"-") -> - | R15: =+IFERROR(VLOOKUP(CONCATENATE(A15,$D$10,D15),'ID1&5'!B:J,9,FALSE),"-") -> - | S15: =+IFERROR(VLOOKUP(E15,'ID1&5'!K:L,2,FALSE),"-") -> - | T15: =+IFERROR(VLOOKUP(CONCATENATE(A15,$E$10,E15),'ID1&5'!B:J,9,FALSE),"-") -> - | U15: =+IFERROR(VLOOKUP(F15,'ID1&5'!K:L,2,FALSE),"-") -> - | V15: =+IFERROR(VLOOKUP(CONCATENATE(A15,$F$10,F15),'ID1&5'!B:J,9,FALSE),"-") -> - | W15: =+IFERROR(VLOOKUP(A15,'ID6&7'!A:I,9,FALSE),"-") -> - | X15: =+IFERROR(VLOOKUP(A15,'ID6&7'!A:J,10,FALSE),"-") -> - | Z15: =+IF(J15=0,"Por iniciar",IF(OR(K15="-",M15="-",P15="-",R15="-",T15="-",V15="-"),"Em testes",IF(AND(M15=0,P15=0,R15=0,T15<>K15,V15<>K15),"OK","NOK"))) -> Por iniciar
A16: =+H16&I16&$I$8 -> ENTITYDT_FNNCL_STTMTS_PRVS45596 | H16: ENTITY | I16: DT_FNNCL_STTMTS_PRVS | J16: =+COUNTIF('ID1&5'!G:G,'1. Status'!I16) -> 0 | K16: =+IFERROR(VLOOKUP(CONCATENATE(A16,$B$10,B16),'ID1&5'!B:J,8,FALSE),"-") -> - | L16: =+IFERROR(VLOOKUP(B16,'ID1&5'!K:L,2,FALSE),"-") -> - | M16: =+IFERROR(VLOOKUP(CONCATENATE(A16,$B$10,B16),'ID1&5'!B:J,9,FALSE),"-") -> - | N16: =+IFERROR(VLOOKUP(CONCATENATE(A16,$C$10,C16),'ID1&5'!B:J,8,FALSE),"-") -> - | O16: =+IFERROR(VLOOKUP(C16,'ID1&5'!K:L,2,FALSE),"-") -> - | P16: =+IFERROR(VLOOKUP(CONCATENATE(A16,$C$10,C16),'ID1&5'!B:J,9,FALSE),"-") -> - | Q16: =+IFERROR(VLOOKUP(D16,'ID1&5'!K:L,2,FALSE),"-") -> - | R16: =+IFERROR(VLOOKUP(CONCATENATE(A16,$D$10,D16),'ID1&5'!B:J,9,FALSE),"-") -> - | S16: =+IFERROR(VLOOKUP(E16,'ID1&5'!K:L,2,FALSE),"-") -> - | T16: =+IFERROR(VLOOKUP(CONCATENATE(A16,$E$10,E16),'ID1&5'!B:J,9,FALSE),"-") -> - | U16: =+IFERROR(VLOOKUP(F16,'ID1&5'!K:L,2,FALSE),"-") -> - | V16: =+IFERROR(VLOOKUP(CONCATENATE(A16,$F$10,F16),'ID1&5'!B:J,9,FALSE),"-") -> - | W16: =+IFERROR(VLOOKUP(A16,'ID6&7'!A:I,9,FALSE),"-") -> - | X16: =+IFERROR(VLOOKUP(A16,'ID6&7'!A:J,10,FALSE),"-") -> - | Z16: =+IF(J16=0,"Por iniciar",IF(OR(K16="-",M16="-",P16="-",R16="-",T16="-",V16="-"),"Em testes",IF(AND(M16=0,P16=0,R16=0,T16<>K16,V16<>K16),"OK","NOK"))) -> Por iniciar
A17: =+H17&I17&$I$8 -> ENTITYDT_INTTN_LGL_PRCDNGS_LE45596 | H17: ENTITY | I17: DT_INTTN_LGL_PRCDNGS_LE | J17: =+COUNTIF('ID1&5'!G:G,'1. Status'!I17) -> 0 | K17: =+IFERROR(VLOOKUP(CONCATENATE(A17,$B$10,B17),'ID1&5'!B:J,8,FALSE),"-") -> - | L17: =+IFERROR(VLOOKUP(B17,'ID1&5'!K:L,2,FALSE),"-") -> - | M17: =+IFERROR(VLOOKUP(CONCATENATE(A17,$B$10,B17),'ID1&5'!B:J,9,FALSE),"-") -> - | N17: =+IFERROR(VLOOKUP(CONCATENATE(A17,$C$10,C17),'ID1&5'!B:J,8,FALSE),"-") -> - | O17: =+IFERROR(VLOOKUP(C17,'ID1&5'!K:L,2,FALSE),"-") -> - | P17: =+IFERROR(VLOOKUP(CONCATENATE(A17,$C$10,C17),'ID1&5'!B:J,9,FALSE),"-") -> - | Q17: =+IFERROR(VLOOKUP(D17,'ID1&5'!K:L,2,FALSE),"-") -> - | R17: =+IFERROR(VLOOKUP(CONCATENATE(A17,$D$10,D17),'ID1&5'!B:J,9,FALSE),"-") -> - | S17: =+IFERROR(VLOOKUP(E17,'ID1&5'!K:L,2,FALSE),"-") -> - | T17: =+IFERROR(VLOOKUP(CONCATENATE(A17,$E$10,E17),'ID1&5'!B:J,9,FALSE),"-") -> - | U17: =+IFERROR(VLOOKUP(F17,'ID1&5'!K:L,2,FALSE),"-") -> - | V17: =+IFERROR(VLOOKUP(CONCATENATE(A17,$F$10,F17),'ID1&5'!B:J,9,FALSE),"-") -> - | W17: =+IFERROR(VLOOKUP(A17,'ID6&7'!A:I,9,FALSE),"-") -> - | X17: =+IFERROR(VLOOKUP(A17,'ID6&7'!A:J,10,FALSE),"-") -> - | Z17: =+IF(J17=0,"Por iniciar",IF(OR(K17="-",M17="-",P17="-",R17="-",T17="-",V17="-"),"Em testes",IF(AND(M17=0,P17=0,R17=0,T17<>K17,V17<>K17),"OK","NOK"))) -> Por iniciar
A18: =+H18&I18&$I$8 -> ENTITYDT_PRFRMNG_STTS_LE45596 | H18: ENTITY | I18: DT_PRFRMNG_STTS_LE | J18: =+COUNTIF('ID1&5'!G:G,'1. Status'!I18) -> 0 | K18: =+IFERROR(VLOOKUP(CONCATENATE(A18,$B$10,B18),'ID1&5'!B:J,8,FALSE),"-") -> - | L18: =+IFERROR(VLOOKUP(B18,'ID1&5'!K:L,2,FALSE),"-") -> - | M18: =+IFERROR(VLOOKUP(CONCATENATE(A18,$B$10,B18),'ID1&5'!B:J,9,FALSE),"-") -> - | N18: =+IFERROR(VLOOKUP(CONCATENATE(A18,$C$10,C18),'ID1&5'!B:J,8,FALSE),"-") -> - | O18: =+IFERROR(VLOOKUP(C18,'ID1&5'!K:L,2,FALSE),"-") -> - | P18: =+IFERROR(VLOOKUP(CONCATENATE(A18,$C$10,C18),'ID1&5'!B:J,9,FALSE),"-") -> - | Q18: =+IFERROR(VLOOKUP(D18,'ID1&5'!K:L,2,FALSE),"-") -> - | R18: =+IFERROR(VLOOKUP(CONCATENATE(A18,$D$10,D18),'ID1&5'!B:J,9,FALSE),"-") -> - | S18: =+IFERROR(VLOOKUP(E18,'ID1&5'!K:L,2,FALSE),"-") -> - | T18: =+IFERROR(VLOOKUP(CONCATENATE(A18,$E$10,E18),'ID1&5'!B:J,9,FALSE),"-") -> - | U18: =+IFERROR(VLOOKUP(F18,'ID1&5'!K:L,2,FALSE),"-") -> - | V18: =+IFERROR(VLOOKUP(CONCATENATE(A18,$F$10,F18),'ID1&5'!B:J,9,FALSE),"-") -> - | W18: =+IFERROR(VLOOKUP(A18,'ID6&7'!A:I,9,FALSE),"-") -> - | X18: =+IFERROR(VLOOKUP(A18,'ID6&7'!A:J,10,FALSE),"-") -> - | Z18: =+IF(J18=0,"Por iniciar",IF(OR(K18="-",M18="-",P18="-",R18="-",T18="-",V18="-"),"Em testes",IF(AND(M18=0,P18=0,R18=0,T18<>K18,V18<>K18),"OK","NOK"))) -> Por iniciar
A19: =+H19&I19&$I$8 -> ENTITYGCC_PRNT_ID45596 | H19: ENTITY | I19: GCC_PRNT_ID | J19: =+COUNTIF('ID1&5'!G:G,'1. Status'!I19) -> 0 | K19: =+IFERROR(VLOOKUP(CONCATENATE(A19,$B$10,B19),'ID1&5'!B:J,8,FALSE),"-") -> - | L19: =+IFERROR(VLOOKUP(B19,'ID1&5'!K:L,2,FALSE),"-") -> - | M19: =+IFERROR(VLOOKUP(CONCATENATE(A19,$B$10,B19),'ID1&5'!B:J,9,FALSE),"-") -> - | N19: =+IFERROR(VLOOKUP(CONCATENATE(A19,$C$10,C19),'ID1&5'!B:J,8,FALSE),"-") -> - | O19: =+IFERROR(VLOOKUP(C19,'ID1&5'!K:L,2,FALSE),"-") -> - | P19: =+IFERROR(VLOOKUP(CONCATENATE(A19,$C$10,C19),'ID1&5'!B:J,9,FALSE),"-") -> - | Q19: =+IFERROR(VLOOKUP(D19,'ID1&5'!K:L,2,FALSE),"-") -> - | R19: =+IFERROR(VLOOKUP(CONCATENATE(A19,$D$10,D19),'ID1&5'!B:J,9,FALSE),"-") -> - | S19: =+IFERROR(VLOOKUP(E19,'ID1&5'!K:L,2,FALSE),"-") -> - | T19: =+IFERROR(VLOOKUP(CONCATENATE(A19,$E$10,E19),'ID1&5'!B:J,9,FALSE),"-") -> - | U19: =+IFERROR(VLOOKUP(F19,'ID1&5'!K:L,2,FALSE),"-") -> - | V19: =+IFERROR(VLOOKUP(CONCATENATE(A19,$F$10,F19),'ID1&5'!B:J,9,FALSE),"-") -> - | W19: =+IFERROR(VLOOKUP(A19,'ID6&7'!A:I,9,FALSE),"-") -> - | X19: =+IFERROR(VLOOKUP(A19,'ID6&7'!A:J,10,FALSE),"-") -> - | Z19: =+IF(J19=0,"Por iniciar",IF(OR(K19="-",M19="-",P19="-",R19="-",T19="-",V19="-"),"Em testes",IF(AND(M19=0,P19=0,R19=0,T19<>K19,V19<>K19),"OK","NOK"))) -> Por iniciar
A20: =+H20&I20&$I$8 -> ENTITYGCC_PRNT_NM45596 | H20: ENTITY | I20: GCC_PRNT_NM | J20: =+COUNTIF('ID1&5'!G:G,'1. Status'!I20) -> 0 | K20: =+IFERROR(VLOOKUP(CONCATENATE(A20,$B$10,B20),'ID1&5'!B:J,8,FALSE),"-") -> - | L20: =+IFERROR(VLOOKUP(B20,'ID1&5'!K:L,2,FALSE),"-") -> - | M20: =+IFERROR(VLOOKUP(CONCATENATE(A20,$B$10,B20),'ID1&5'!B:J,9,FALSE),"-") -> - | N20: =+IFERROR(VLOOKUP(CONCATENATE(A20,$C$10,C20),'ID1&5'!B:J,8,FALSE),"-") -> - | O20: =+IFERROR(VLOOKUP(C20,'ID1&5'!K:L,2,FALSE),"-") -> - | P20: =+IFERROR(VLOOKUP(CONCATENATE(A20,$C$10,C20),'ID1&5'!B:J,9,FALSE),"-") -> - | Q20: =+IFERROR(VLOOKUP(D20,'ID1&5'!K:L,2,FALSE),"-") -> - | R20: =+IFERROR(VLOOKUP(CONCATENATE(A20,$D$10,D20),'ID1&5'!B:J,9,FALSE),"-") -> - | S20: =+IFERROR(VLOOKUP(E20,'ID1&5'!K:L,2,FALSE),"-") -> - | T20: =+IFERROR(VLOOKUP(CONCATENATE(A20,$E$10,E20),'ID1&5'!B:J,9,FALSE),"-") -> - | U20: =+IFERROR(VLOOKUP(F20,'ID1&5'!K:L,2,FALSE),"-") -> - | V20: =+IFERROR(VLOOKUP(CONCATENATE(A20,$F$10,F20),'ID1&5'!B:J,9,FALSE),"-") -> - | W20: =+IFERROR(VLOOKUP(A20,'ID6&7'!A:I,9,FALSE),"-") -> - | X20: =+IFERROR(VLOOKUP(A20,'ID6&7'!A:J,10,FALSE),"-") -> - | Z20: =+IF(J20=0,"Por iniciar",IF(OR(K20="-",M20="-",P20="-",R20="-",T20="-",V20="-"),"Em testes",IF(AND(M20=0,P20=0,R20=0,T20<>K20,V20<>K20),"OK","NOK"))) -> Por iniciar
A21: =+H21&I21&$I$8 -> ENTITYINTRNL_SGMNT45596 | H21: ENTITY | I21: INTRNL_SGMNT | J21: =+COUNTIF('ID1&5'!G:G,'1. Status'!I21) -> 0 | K21: =+IFERROR(VLOOKUP(CONCATENATE(A21,$B$10,B21),'ID1&5'!B:J,8,FALSE),"-") -> - | L21: =+IFERROR(VLOOKUP(B21,'ID1&5'!K:L,2,FALSE),"-") -> - | M21: =+IFERROR(VLOOKUP(CONCATENATE(A21,$B$10,B21),'ID1&5'!B:J,9,FALSE),"-") -> - | N21: =+IFERROR(VLOOKUP(CONCATENATE(A21,$C$10,C21),'ID1&5'!B:J,8,FALSE),"-") -> - | O21: =+IFERROR(VLOOKUP(C21,'ID1&5'!K:L,2,FALSE),"-") -> - | P21: =+IFERROR(VLOOKUP(CONCATENATE(A21,$C$10,C21),'ID1&5'!B:J,9,FALSE),"-") -> - | Q21: =+IFERROR(VLOOKUP(D21,'ID1&5'!K:L,2,FALSE),"-") -> - | R21: =+IFERROR(VLOOKUP(CONCATENATE(A21,$D$10,D21),'ID1&5'!B:J,9,FALSE),"-") -> - | S21: =+IFERROR(VLOOKUP(E21,'ID1&5'!K:L,2,FALSE),"-") -> - | T21: =+IFERROR(VLOOKUP(CONCATENATE(A21,$E$10,E21),'ID1&5'!B:J,9,FALSE),"-") -> - | U21: =+IFERROR(VLOOKUP(F21,'ID1&5'!K:L,2,FALSE),"-") -> - | V21: =+IFERROR(VLOOKUP(CONCATENATE(A21,$F$10,F21),'ID1&5'!B:J,9,FALSE),"-") -> - | W21: =+IFERROR(VLOOKUP(A21,'ID6&7'!A:I,9,FALSE),"-") -> - | X21: =+IFERROR(VLOOKUP(A21,'ID6&7'!A:J,10,FALSE),"-") -> - | Z21: =+IF(J21=0,"Por iniciar",IF(OR(K21="-",M21="-",P21="-",R21="-",T21="-",V21="-"),"Em testes",IF(AND(M21=0,P21=0,R21=0,T21<>K21,V21<>K21),"OK","NOK"))) -> Por iniciar
A22: =+H22&I22&$I$8 -> ENTITYINTRNL_UNT45596 | H22: ENTITY | I22: INTRNL_UNT | J22: =+COUNTIF('ID1&5'!G:G,'1. Status'!I22) -> 0 | K22: =+IFERROR(VLOOKUP(CONCATENATE(A22,$B$10,B22),'ID1&5'!B:J,8,FALSE),"-") -> - | L22: =+IFERROR(VLOOKUP(B22,'ID1&5'!K:L,2,FALSE),"-") -> - | M22: =+IFERROR(VLOOKUP(CONCATENATE(A22,$B$10,B22),'ID1&5'!B:J,9,FALSE),"-") -> - | N22: =+IFERROR(VLOOKUP(CONCATENATE(A22,$C$10,C22),'ID1&5'!B:J,8,FALSE),"-") -> - | O22: =+IFERROR(VLOOKUP(C22,'ID1&5'!K:L,2,FALSE),"-") -> - | P22: =+IFERROR(VLOOKUP(CONCATENATE(A22,$C$10,C22),'ID1&5'!B:J,9,FALSE),"-") -> - | Q22: =+IFERROR(VLOOKUP(D22,'ID1&5'!K:L,2,FALSE),"-") -> - | R22: =+IFERROR(VLOOKUP(CONCATENATE(A22,$D$10,D22),'ID1&5'!B:J,9,FALSE),"-") -> - | S22: =+IFERROR(VLOOKUP(E22,'ID1&5'!K:L,2,FALSE),"-") -> - | T22: =+IFERROR(VLOOKUP(CONCATENATE(A22,$E$10,E22),'ID1&5'!B:J,9,FALSE),"-") -> - | U22: =+IFERROR(VLOOKUP(F22,'ID1&5'!K:L,2,FALSE),"-") -> - | V22: =+IFERROR(VLOOKUP(CONCATENATE(A22,$F$10,F22),'ID1&5'!B:J,9,FALSE),"-") -> - | W22: =+IFERROR(VLOOKUP(A22,'ID6&7'!A:I,9,FALSE),"-") -> - | X22: =+IFERROR(VLOOKUP(A22,'ID6&7'!A:J,10,FALSE),"-") -> - | Z22: =+IF(J22=0,"Por iniciar",IF(OR(K22="-",M22="-",P22="-",R22="-",T22="-",V22="-"),"Em testes",IF(AND(M22=0,P22=0,R22=0,T22<>K22,V22<>K22),"OK","NOK"))) -> Por iniciar
... A88: =+H88&I88&$I$8 -> ENTITYDBT_SRVC_RT45596 | H88: ENTITY | I88: DBT_SRVC_RT | J88: =+COUNTIF('ID1&5'!G:G,'1. Status'!I88) -> 0 | K88: =+IFERROR(VLOOKUP(CONCATENATE(A88,$B$10,B88),'ID1&5'!B:J,8,FALSE),"-") -> - | L88: =+IFERROR(VLOOKUP(B88,'ID1&5'!K:L,2,FALSE),"-") -> - | M88: =+IFERROR(VLOOKUP(CONCATENATE(A88,$B$10,B88),'ID1&5'!B:J,9,FALSE),"-") -> - | N88: =+IFERROR(VLOOKUP(CONCATENATE(A88,$C$10,C88),'ID1&5'!B:J,8,FALSE),"-") -> - | O88: =+IFERROR(VLOOKUP(C88,'ID1&5'!K:L,2,FALSE),"-") -> - | P88: =+IFERROR(VLOOKUP(CONCATENATE(A88,$C$10,C88),'ID1&5'!B:J,9,FALSE),"-") -> - | Q88: =+IFERROR(VLOOKUP(D88,'ID1&5'!K:L,2,FALSE),"-") -> - | R88: =+IFERROR(VLOOKUP(CONCATENATE(A88,$D$10,D88),'ID1&5'!B:J,9,FALSE),"-") -> - | S88: =+IFERROR(VLOOKUP(E88,'ID1&5'!K:L,2,FALSE),"-") -> - | T88: =+IFERROR(VLOOKUP(CONCATENATE(A88,$E$10,E88),'ID1&5'!B:J,9,FALSE),"-") -> - | U88: =+IFERROR(VLOOKUP(F88,'ID1&5'!K:L,2,FALSE),"-") -> - | V88: =+IFERROR(VLOOKUP(CONCATENATE(A88,$F$10,F88),'ID1&5'!B:J,9,FALSE),"-") -> - | W88: =+IFERROR(VLOOKUP(A88,'ID6&7'!A:I,9,FALSE),"-") -> - | X88: =+IFERROR(VLOOKUP(A88,'ID6&7'!A:J,10,FALSE),"-") -> - | Z88: =+IF(J88=0,"Por iniciar",IF(OR(K88="-",M88="-",P88="-",R88="-",T88="-",V88="-"),"Em testes",IF(AND(M88=0,P88=0,R88=0,T88<>K88,V88<>K88),"OK","NOK"))) -> Por iniciar
A89: =+H89&I89&$I$8 -> ENTITYDBT_SRVC_RT_12M45596 | B89: {=+MAX(IF('ID1&5'!A:A='1. Status'!A89&'1. Status'!$B$10,'ID1&5'!K:K))} -> 0 | C89: {=+MAX(IF('ID1&5'!A:A='1. Status'!A89&'1. Status'!$C$10,'ID1&5'!K:K))} -> 0 | D89: {=+MAX(IF('ID1&5'!A:A='1. Status'!A89&'1. Status'!$D$10,'ID1&5'!K:K))} -> 0 | E89: {=+MAX(IF('ID1&5'!A:A='1. Status'!A89&'1. Status'!$E$10,'ID1&5'!K:K))} -> 0 | F89: {=+MAX(IF('ID1&5'!A:A='1. Status'!A89&'1. Status'!$F$10,'ID1&5'!K:K))} -> 0 | H89: ENTITY | I89: DBT_SRVC_RT_12M | J89: =+COUNTIF('ID1&5'!G:G,'1. Status'!I89) -> 0 | K89: =+IFERROR(VLOOKUP(CONCATENATE(A89,$B$10,B89),'ID1&5'!B:J,8,FALSE),"-") -> - | L89: =+IFERROR(VLOOKUP(B89,'ID1&5'!K:L,2,FALSE),"-") -> - | M89: =+IFERROR(VLOOKUP(CONCATENATE(A89,$B$10,B89),'ID1&5'!B:J,9,FALSE),"-") -> - | N89: =+IFERROR(VLOOKUP(CONCATENATE(A89,$C$10,C89),'ID1&5'!B:J,8,FALSE),"-") -> - | O89: =+IFERROR(VLOOKUP(C89,'ID1&5'!K:L,2,FALSE),"-") -> - | P89: =+IFERROR(VLOOKUP(CONCATENATE(A89,$C$10,C89),'ID1&5'!B:J,9,FALSE),"-") -> - | Q89: =+IFERROR(VLOOKUP(D89,'ID1&5'!K:L,2,FALSE),"-") -> - | R89: =+IFERROR(VLOOKUP(CONCATENATE(A89,$D$10,D89),'ID1&5'!B:J,9,FALSE),"-") -> - | S89: =+IFERROR(VLOOKUP(E89,'ID1&5'!K:L,2,FALSE),"-") -> - | T89: =+IFERROR(VLOOKUP(CONCATENATE(A89,$E$10,E89),'ID1&5'!B:J,9,FALSE),"-") -> - | U89: =+IFERROR(VLOOKUP(F89,'ID1&5'!K:L,2,FALSE),"-") -> - | V89: =+IFERROR(VLOOKUP(CONCATENATE(A89,$F$10,F89),'ID1&5'!B:J,9,FALSE),"-") -> - | W89: =+IFERROR(VLOOKUP(A89,'ID6&7'!A:I,9,FALSE),"-") -> - | X89: =+IFERROR(VLOOKUP(A89,'ID6&7'!A:J,10,FALSE),"-") -> - | Z89: =+IF(J89=0,"Por iniciar",IF(OR(K89="-",M89="-",P89="-",R89="-",T89="-",V89="-"),"Em testes",IF(AND(M89=0,P89=0,R89=0,T89<>K89,V89<>K89),"OK","NOK"))) -> Por iniciar
A90: =+H90&I90&$I$8 -> ENTITYPD_CRR_RD45596 | B90: {=+MAX(IF('ID1&5'!A:A='1. Status'!A90&'1. Status'!$B$10,'ID1&5'!K:K))} -> 0 | C90: {=+MAX(IF('ID1&5'!A:A='1. Status'!A90&'1. Status'!$C$10,'ID1&5'!K:K))} -> 0 | D90: {=+MAX(IF('ID1&5'!A:A='1. Status'!A90&'1. Status'!$D$10,'ID1&5'!K:K))} -> 0 | E90: {=+MAX(IF('ID1&5'!A:A='1. Status'!A90&'1. Status'!$E$10,'ID1&5'!K:K))} -> 0 | F90: {=+MAX(IF('ID1&5'!A:A='1. Status'!A90&'1. Status'!$F$10,'ID1&5'!K:K))} -> 0 | H90: ENTITY | I90: PD_CRR_RD | J90: =+COUNTIF('ID1&5'!G:G,'1. Status'!I90) -> 0 | K90: =+IFERROR(VLOOKUP(CONCATENATE(A90,$B$10,B90),'ID1&5'!B:J,8,FALSE),"-") -> - | L90: =+IFERROR(VLOOKUP(B90,'ID1&5'!K:L,2,FALSE),"-") -> - | M90: =+IFERROR(VLOOKUP(CONCATENATE(A90,$B$10,B90),'ID1&5'!B:J,9,FALSE),"-") -> - | N90: =+IFERROR(VLOOKUP(CONCATENATE(A90,$C$10,C90),'ID1&5'!B:J,8,FALSE),"-") -> - | O90: =+IFERROR(VLOOKUP(C90,'ID1&5'!K:L,2,FALSE),"-") -> - | P90: =+IFERROR(VLOOKUP(CONCATENATE(A90,$C$10,C90),'ID1&5'!B:J,9,FALSE),"-") -> - | Q90: =+IFERROR(VLOOKUP(D90,'ID1&5'!K:L,2,FALSE),"-") -> - | R90: =+IFERROR(VLOOKUP(CONCATENATE(A90,$D$10,D90),'ID1&5'!B:J,9,FALSE),"-") -> - | S90: =+IFERROR(VLOOKUP(E90,'ID1&5'!K:L,2,FALSE),"-") -> - | T90: =+IFERROR(VLOOKUP(CONCATENATE(A90,$E$10,E90),'ID1&5'!B:J,9,FALSE),"-") -> - | U90: =+IFERROR(VLOOKUP(F90,'ID1&5'!K:L,2,FALSE),"-") -> - | V90: =+IFERROR(VLOOKUP(CONCATENATE(A90,$F$10,F90),'ID1&5'!B:J,9,FALSE),"-") -> - | W90: =+IFERROR(VLOOKUP(A90,'ID6&7'!A:I,9,FALSE),"-") -> - | X90: =+IFERROR(VLOOKUP(A90,'ID6&7'!A:J,10,FALSE),"-") -> - | Z90: =+IF(J90=0,"Por iniciar",IF(OR(K90="-",M90="-",P90="-",R90="-",T90="-",V90="-"),"Em testes",IF(AND(M90=0,P90=0,R90=0,T90<>K90,V90<>K90),"OK","NOK"))) -> Por iniciar
A91: =+H91&I91&$I$8 -> ENTITYPD_IFRS9_12M_RD45596 | B91: {=+MAX(IF('ID1&5'!A:A='1. Status'!A91&'1. Status'!$B$10,'ID1&5'!K:K))} -> 0 | C91: {=+MAX(IF('ID1&5'!A:A='1. Status'!A91&'1. Status'!$C$10,'ID1&5'!K:K))} -> 0 | D91: {=+MAX(IF('ID1&5'!A:A='1. Status'!A91&'1. Status'!$D$10,'ID1&5'!K:K))} -> 0 | E91: {=+MAX(IF('ID1&5'!A:A='1. Status'!A91&'1. Status'!$E$10,'ID1&5'!K:K))} -> 0 | F91: {=+MAX(IF('ID1&5'!A:A='1. Status'!A91&'1. Status'!$F$10,'ID1&5'!K:K))} -> 0 | H91: ENTITY | I91: PD_IFRS9_12M_RD | J91: =+COUNTIF('ID1&5'!G:G,'1. Status'!I91) -> 0 | K91: =+IFERROR(VLOOKUP(CONCATENATE(A91,$B$10,B91),'ID1&5'!B:J,8,FALSE),"-") -> - | L91: =+IFERROR(VLOOKUP(B91,'ID1&5'!K:L,2,FALSE),"-") -> - | M91: =+IFERROR(VLOOKUP(CONCATENATE(A91,$B$10,B91),'ID1&5'!B:J,9,FALSE),"-") -> - | N91: =+IFERROR(VLOOKUP(CONCATENATE(A91,$C$10,C91),'ID1&5'!B:J,8,FALSE),"-") -> - | O91: =+IFERROR(VLOOKUP(C91,'ID1&5'!K:L,2,FALSE),"-") -> - | P91: =+IFERROR(VLOOKUP(CONCATENATE(A91,$C$10,C91),'ID1&5'!B:J,9,FALSE),"-") -> - | Q91: =+IFERROR(VLOOKUP(D91,'ID1&5'!K:L,2,FALSE),"-") -> - | R91: =+IFERROR(VLOOKUP(CONCATENATE(A91,$D$10,D91),'ID1&5'!B:J,9,FALSE),"-") -> - | S91: =+IFERROR(VLOOKUP(E91,'ID1&5'!K:L,2,FALSE),"-") -> - | T91: =+IFERROR(VLOOKUP(CONCATENATE(A91,$E$10,E91),'ID1&5'!B:J,9,FALSE),"-") -> - | U91: =+IFERROR(VLOOKUP(F91,'ID1&5'!K:L,2,FALSE),"-") -> - | V91: =+IFERROR(VLOOKUP(CONCATENATE(A91,$F$10,F91),'ID1&5'!B:J,9,FALSE),"-") -> - | W91: =+IFERROR(VLOOKUP(A91,'ID6&7'!A:I,9,FALSE),"-") -> - | X91: =+IFERROR(VLOOKUP(A91,'ID6&7'!A:J,10,FALSE),"-") -> - | Z91: =+IF(J91=0,"Por iniciar",IF(OR(K91="-",M91="-",P91="-",R91="-",T91="-",V91="-"),"Em testes",IF(AND(M91=0,P91=0,R91=0,T91<>K91,V91<>K91),"OK","NOK"))) -> Por iniciar
A92: =+H92&I92&$I$8 -> ENTITYPD_IFRS9_12M_RD_T145596 | B92: {=+MAX(IF('ID1&5'!A:A='1. Status'!A92&'1. Status'!$B$10,'ID1&5'!K:K))} -> 0 | C92: {=+MAX(IF('ID1&5'!A:A='1. Status'!A92&'1. Status'!$C$10,'ID1&5'!K:K))} -> 0 | D92: {=+MAX(IF('ID1&5'!A:A='1. Status'!A92&'1. Status'!$D$10,'ID1&5'!K:K))} -> 0 | E92: {=+MAX(IF('ID1&5'!A:A='1. Status'!A92&'1. Status'!$E$10,'ID1&5'!K:K))} -> 0 | F92: {=+MAX(IF('ID1&5'!A:A='1. Status'!A92&'1. Status'!$F$10,'ID1&5'!K:K))} -> 0 | H92: ENTITY | I92: PD_IFRS9_12M_RD_T1 | J92: =+COUNTIF('ID1&5'!G:G,'1. Status'!I92) -> 0 | K92: =+IFERROR(VLOOKUP(CONCATENATE(A92,$B$10,B92),'ID1&5'!B:J,8,FALSE),"-") -> - | L92: =+IFERROR(VLOOKUP(B92,'ID1&5'!K:L,2,FALSE),"-") -> - | M92: =+IFERROR(VLOOKUP(CONCATENATE(A92,$B$10,B92),'ID1&5'!B:J,9,FALSE),"-") -> - | N92: =+IFERROR(VLOOKUP(CONCATENATE(A92,$C$10,C92),'ID1&5'!B:J,8,FALSE),"-") -> - | O92: =+IFERROR(VLOOKUP(C92,'ID1&5'!K:L,2,FALSE),"-") -> - | P92: =+IFERROR(VLOOKUP(CONCATENATE(A92,$C$10,C92),'ID1&5'!B:J,9,FALSE),"-") -> - | Q92: =+IFERROR(VLOOKUP(D92,'ID1&5'!K:L,2,FALSE),"-") -> - | R92: =+IFERROR(VLOOKUP(CONCATENATE(A92,$D$10,D92),'ID1&5'!B:J,9,FALSE),"-") -> - | S92: =+IFERROR(VLOOKUP(E92,'ID1&5'!K:L,2,FALSE),"-") -> - | T92: =+IFERROR(VLOOKUP(CONCATENATE(A92,$E$10,E92),'ID1&5'!B:J,9,FALSE),"-") -> - | U92: =+IFERROR(VLOOKUP(F92,'ID1&5'!K:L,2,FALSE),"-") -> - | V92: =+IFERROR(VLOOKUP(CONCATENATE(A92,$F$10,F92),'ID1&5'!B:J,9,FALSE),"-") -> - | W92: =+IFERROR(VLOOKUP(A92,'ID6&7'!A:I,9,FALSE),"-") -> - | X92: =+IFERROR(VLOOKUP(A92,'ID6&7'!A:J,10,FALSE),"-") -> - | Z92: =+IF(J92=0,"Por iniciar",IF(OR(K92="-",M92="-",P92="-",R92="-",T92="-",V92="-"),"Em testes",IF(AND(M92=0,P92=0,R92=0,T92<>K92,V92<>K92),"OK","NOK"))) -> Por iniciar
A93: =+H93&I93&$I$8 -> ENTITYTAX_ID45596 | B93: {=+MAX(IF('ID1&5'!A:A='1. Status'!A93&'1. Status'!$B$10,'ID1&5'!K:K))} -> 0 | C93: {=+MAX(IF('ID1&5'!A:A='1. Status'!A93&'1. Status'!$C$10,'ID1&5'!K:K))} -> 0 | D93: {=+MAX(IF('ID1&5'!A:A='1. Status'!A93&'1. Status'!$D$10,'ID1&5'!K:K))} -> 0 | E93: {=+MAX(IF('ID1&5'!A:A='1. Status'!A93&'1. Status'!$E$10,'ID1&5'!K:K))} -> 0 | F93: {=+MAX(IF('ID1&5'!A:A='1. Status'!A93&'1. Status'!$F$10,'ID1&5'!K:K))} -> 0 | H93: ENTITY | I93: TAX_ID | J93: =+COUNTIF('ID1&5'!G:G,'1. Status'!I93) -> 0 | K93: =+IFERROR(VLOOKUP(CONCATENATE(A93,$B$10,B93),'ID1&5'!B:J,8,FALSE),"-") -> - | L93: =+IFERROR(VLOOKUP(B93,'ID1&5'!K:L,2,FALSE),"-") -> - | M93: =+IFERROR(VLOOKUP(CONCATENATE(A93,$B$10,B93),'ID1&5'!B:J,9,FALSE),"-") -> - | N93: =+IFERROR(VLOOKUP(CONCATENATE(A93,$C$10,C93),'ID1&5'!B:J,8,FALSE),"-") -> - | O93: =+IFERROR(VLOOKUP(C93,'ID1&5'!K:L,2,FALSE),"-") -> - | P93: =+IFERROR(VLOOKUP(CONCATENATE(A93,$C$10,C93),'ID1&5'!B:J,9,FALSE),"-") -> - | Q93: =+IFERROR(VLOOKUP(D93,'ID1&5'!K:L,2,FALSE),"-") -> - | R93: =+IFERROR(VLOOKUP(CONCATENATE(A93,$D$10,D93),'ID1&5'!B:J,9,FALSE),"-") -> - | S93: =+IFERROR(VLOOKUP(E93,'ID1&5'!K:L,2,FALSE),"-") -> - | T93: =+IFERROR(VLOOKUP(CONCATENATE(A93,$E$10,E93),'ID1&5'!B:J,9,FALSE),"-") -> - | U93: =+IFERROR(VLOOKUP(F93,'ID1&5'!K:L,2,FALSE),"-") -> - | V93: =+IFERROR(VLOOKUP(CONCATENATE(A93,$F$10,F93),'ID1&5'!B:J,9,FALSE),"-") -> - | W93: =+IFERROR(VLOOKUP(A93,'ID6&7'!A:I,9,FALSE),"-") -> - | X93: =+IFERROR(VLOOKUP(A93,'ID6&7'!A:J,10,FALSE),"-") -> - | Z93: =+IF(J93=0,"Por iniciar",IF(OR(K93="-",M93="-",P93="-",R93="-",T93="-",V93="-"),"Em testes",IF(AND(M93=0,P93=0,R93=0,T93<>K93,V93<>K93),"OK","NOK"))) -> Por iniciar
A94: =+H94&I94&$I$8 -> ENTITYANNL_TRNVR_LE_BDR45596 | B94: {=+MAX(IF('ID1&5'!A:A='1. Status'!A94&'1. Status'!$B$10,'ID1&5'!K:K))} -> 0 | C94: {=+MAX(IF('ID1&5'!A:A='1. Status'!A94&'1. Status'!$C$10,'ID1&5'!K:K))} -> 0 | D94: {=+MAX(IF('ID1&5'!A:A='1. Status'!A94&'1. Status'!$D$10,'ID1&5'!K:K))} -> 0 | E94: {=+MAX(IF('ID1&5'!A:A='1. Status'!A94&'1. Status'!$E$10,'ID1&5'!K:K))} -> 0 | F94: {=+MAX(IF('ID1&5'!A:A='1. Status'!A94&'1. Status'!$F$10,'ID1&5'!K:K))} -> 0 | H94: ENTITY | I94: ANNL_TRNVR_LE_BDR | J94: =+COUNTIF('ID1&5'!G:G,'1. Status'!I94) -> 0 | K94: =+IFERROR(VLOOKUP(CONCATENATE(A94,$B$10,B94),'ID1&5'!B:J,8,FALSE),"-") -> - | L94: =+IFERROR(VLOOKUP(B94,'ID1&5'!K:L,2,FALSE),"-") -> - | M94: =+IFERROR(VLOOKUP(CONCATENATE(A94,$B$10,B94),'ID1&5'!B:J,9,FALSE),"-") -> - | N94: =+IFERROR(VLOOKUP(CONCATENATE(A94,$C$10,C94),'ID1&5'!B:J,8,FALSE),"-") -> - | O94: =+IFERROR(VLOOKUP(C94,'ID1&5'!K:L,2,FALSE),"-") -> - | P94: =+IFERROR(VLOOKUP(CONCATENATE(A94,$C$10,C94),'ID1&5'!B:J,9,FALSE),"-") -> - | Q94: =+IFERROR(VLOOKUP(D94,'ID1&5'!K:L,2,FALSE),"-") -> - | R94: =+IFERROR(VLOOKUP(CONCATENATE(A94,$D$10,D94),'ID1&5'!B:J,9,FALSE),"-") -> - | S94: =+IFERROR(VLOOKUP(E94,'ID1&5'!K:L,2,FALSE),"-") -> - | T94: =+IFERROR(VLOOKUP(CONCATENATE(A94,$E$10,E94),'ID1&5'!B:J,9,FALSE),"-") -> - | U94: =+IFERROR(VLOOKUP(F94,'ID1&5'!K:L,2,FALSE),"-") -> - | V94: =+IFERROR(VLOOKUP(CONCATENATE(A94,$F$10,F94),'ID1&5'!B:J,9,FALSE),"-") -> - | W94: =+IFERROR(VLOOKUP(A94,'ID6&7'!A:I,9,FALSE),"-") -> - | X94: =+IFERROR(VLOOKUP(A94,'ID6&7'!A:J,10,FALSE),"-") -> - | Z94: =+IF(J94=0,"Por iniciar",IF(OR(K94="-",M94="-",P94="-",R94="-",T94="-",V94="-"),"Em testes",IF(AND(M94=0,P94=0,R94=0,T94<>K94,V94<>K94),"OK","NOK"))) -> Por iniciar
A95: =+H95&I95&$I$8 -> ENTITYANNL_TRNVR_PRVS_BDR45596 | B95: {=+MAX(IF('ID1&5'!A:A='1. Status'!A95&'1. Status'!$B$10,'ID1&5'!K:K))} -> 0 | C95: {=+MAX(IF('ID1&5'!A:A='1. Status'!A95&'1. Status'!$C$10,'ID1&5'!K:K))} -> 0 | D95: {=+MAX(IF('ID1&5'!A:A='1. Status'!A95&'1. Status'!$D$10,'ID1&5'!K:K))} -> 0 | E95: {=+MAX(IF('ID1&5'!A:A='1. Status'!A95&'1. Status'!$E$10,'ID1&5'!K:K))} -> 0 | F95: {=+MAX(IF('ID1&5'!A:A='1. Status'!A95&'1. Status'!$F$10,'ID1&5'!K:K))} -> 0 | H95: ENTITY | I95: ANNL_TRNVR_PRVS_BDR | J95: =+COUNTIF('ID1&5'!G:G,'1. Status'!I95) -> 0 | K95: =+IFERROR(VLOOKUP(CONCATENATE(A95,$B$10,B95),'ID1&5'!B:J,8,FALSE),"-") -> - | L95: =+IFERROR(VLOOKUP(B95,'ID1&5'!K:L,2,FALSE),"-") -> - | M95: =+IFERROR(VLOOKUP(CONCATENATE(A95,$B$10,B95),'ID1&5'!B:J,9,FALSE),"-") -> - | N95: =+IFERROR(VLOOKUP(CONCATENATE(A95,$C$10,C95),'ID1&5'!B:J,8,FALSE),"-") -> - | O95: =+IFERROR(VLOOKUP(C95,'ID1&5'!K:L,2,FALSE),"-") -> - | P95: =+IFERROR(VLOOKUP(CONCATENATE(A95,$C$10,C95),'ID1&5'!B:J,9,FALSE),"-") -> - | Q95: =+IFERROR(VLOOKUP(D95,'ID1&5'!K:L,2,FALSE),"-") -> - | R95: =+IFERROR(VLOOKUP(CONCATENATE(A95,$D$10,D95),'ID1&5'!B:J,9,FALSE),"-") -> - | S95: =+IFERROR(VLOOKUP(E95,'ID1&5'!K:L,2,FALSE),"-") -> - | T95: =+IFERROR(VLOOKUP(CONCATENATE(A95,$E$10,E95),'ID1&5'!B:J,9,FALSE),"-") -> - | U95: =+IFERROR(VLOOKUP(F95,'ID1&5'!K:L,2,FALSE),"-") -> - | V95: =+IFERROR(VLOOKUP(CONCATENATE(A95,$F$10,F95),'ID1&5'!B:J,9,FALSE),"-") -> - | W95: =+IFERROR(VLOOKUP(A95,'ID6&7'!A:I,9,FALSE),"-") -> - | X95: =+IFERROR(VLOOKUP(A95,'ID6&7'!A:J,10,FALSE),"-") -> - | Z95: =+IF(J95=0,"Por iniciar",IF(OR(K95="-",M95="-",P95="-",R95="-",T95="-",V95="-"),"Em testes",IF(AND(M95=0,P95=0,R95=0,T95<>K95,V95<>K95),"OK","NOK"))) -> Por iniciar
A96: =+H96&I96&$I$8 -> ENTITYOSI_ID45596 | B96: {=+MAX(IF('ID1&5'!A:A='1. Status'!A96&'1. Status'!$B$10,'ID1&5'!K:K))} -> 0 | C96: {=+MAX(IF('ID1&5'!A:A='1. Status'!A96&'1. Status'!$C$10,'ID1&5'!K:K))} -> 0 | D96: {=+MAX(IF('ID1&5'!A:A='1. Status'!A96&'1. Status'!$D$10,'ID1&5'!K:K))} -> 0 | E96: {=+MAX(IF('ID1&5'!A:A='1. Status'!A96&'1. Status'!$E$10,'ID1&5'!K:K))} -> 0 | F96: {=+MAX(IF('ID1&5'!A:A='1. Status'!A96&'1. Status'!$F$10,'ID1&5'!K:K))} -> 0 | H96: ENTITY | I96: OSI_ID | J96: =+COUNTIF('ID1&5'!G:G,'1. Status'!I96) -> 0 | K96: =+IFERROR(VLOOKUP(CONCATENATE(A96,$B$10,B96),'ID1&5'!B:J,8,FALSE),"-") -> - | L96: =+IFERROR(VLOOKUP(B96,'ID1&5'!K:L,2,FALSE),"-") -> - | M96: =+IFERROR(VLOOKUP(CONCATENATE(A96,$B$10,B96),'ID1&5'!B:J,9,FALSE),"-") -> - | N96: =+IFERROR(VLOOKUP(CONCATENATE(A96,$C$10,C96),'ID1&5'!B:J,8,FALSE),"-") -> - | O96: =+IFERROR(VLOOKUP(C96,'ID1&5'!K:L,2,FALSE),"-") -> - | P96: =+IFERROR(VLOOKUP(CONCATENATE(A96,$C$10,C96),'ID1&5'!B:J,9,FALSE),"-") -> - | Q96: =+IFERROR(VLOOKUP(D96,'ID1&5'!K:L,2,FALSE),"-") -> - | R96: =+IFERROR(VLOOKUP(CONCATENATE(A96,$D$10,D96),'ID1&5'!B:J,9,FALSE),"-") -> - | S96: =+IFERROR(VLOOKUP(E96,'ID1&5'!K:L,2,FALSE),"-") -> - | T96: =+IFERROR(VLOOKUP(CONCATENATE(A96,$E$10,E96),'ID1&5'!B:J,9,FALSE),"-") -> - | U96: =+IFERROR(VLOOKUP(F96,'ID1&5'!K:L,2,FALSE),"-") -> - | V96: =+IFERROR(VLOOKUP(CONCATENATE(A96,$F$10,F96),'ID1&5'!B:J,9,FALSE),"-") -> - | W96: =+IFERROR(VLOOKUP(A96,'ID6&7'!A:I,9,FALSE),"-") -> - | X96: =+IFERROR(VLOOKUP(A96,'ID6&7'!A:J,10,FALSE),"-") -> - | Z96: =+IF(J96=0,"Por iniciar",IF(OR(K96="-",M96="-",P96="-",R96="-",T96="-",V96="-"),"Em testes",IF(AND(M96=0,P96=0,R96=0,T96<>K96,V96<>K96),"OK","NOK"))) -> Por iniciar
A97: =+H97&I97&$I$8 -> ENTITYPD_CRR_RD_T145596 | B97: {=+MAX(IF('ID1&5'!A:A='1. Status'!A97&'1. Status'!$B$10,'ID1&5'!K:K))} -> 0 | C97: {=+MAX(IF('ID1&5'!A:A='1. Status'!A97&'1. Status'!$C$10,'ID1&5'!K:K))} -> 0 | D97: {=+MAX(IF('ID1&5'!A:A='1. Status'!A97&'1. Status'!$D$10,'ID1&5'!K:K))} -> 0 | E97: {=+MAX(IF('ID1&5'!A:A='1. Status'!A97&'1. Status'!$E$10,'ID1&5'!K:K))} -> 0 | F97: {=+MAX(IF('ID1&5'!A:A='1. Status'!A97&'1. Status'!$F$10,'ID1&5'!K:K))} -> 0 | H97: ENTITY | I97: PD_CRR_RD_T1 | J97: =+COUNTIF('ID1&5'!G:G,'1. Status'!I97) -> 0 | K97: =+IFERROR(VLOOKUP(CONCATENATE(A97,$B$10,B97),'ID1&5'!B:J,8,FALSE),"-") -> - | L97: =+IFERROR(VLOOKUP(B97,'ID1&5'!K:L,2,FALSE),"-") -> - | M97: =+IFERROR(VLOOKUP(CONCATENATE(A97,$B$10,B97),'ID1&5'!B:J,9,FALSE),"-") -> - | N97: =+IFERROR(VLOOKUP(CONCATENATE(A97,$C$10,C97),'ID1&5'!B:J,8,FALSE),"-") -> - | O97: =+IFERROR(VLOOKUP(C97,'ID1&5'!K:L,2,FALSE),"-") -> - | P97: =+IFERROR(VLOOKUP(CONCATENATE(A97,$C$10,C97),'ID1&5'!B:J,9,FALSE),"-") -> - | Q97: =+IFERROR(VLOOKUP(D97,'ID1&5'!K:L,2,FALSE),"-") -> - | R97: =+IFERROR(VLOOKUP(CONCATENATE(A97,$D$10,D97),'ID1&5'!B:J,9,FALSE),"-") -> - | S97: =+IFERROR(VLOOKUP(E97,'ID1&5'!K:L,2,FALSE),"-") -> - | T97: =+IFERROR(VLOOKUP(CONCATENATE(A97,$E$10,E97),'ID1&5'!B:J,9,FALSE),"-") -> - | U97: =+IFERROR(VLOOKUP(F97,'ID1&5'!K:L,2,FALSE),"-") -> - | V97: =+IFERROR(VLOOKUP(CONCATENATE(A97,$F$10,F97),'ID1&5'!B:J,9,FALSE),"-") -> - | W97: =+IFERROR(VLOOKUP(A97,'ID6&7'!A:I,9,FALSE),"-") -> - | X97: =+IFERROR(VLOOKUP(A97,'ID6&7'!A:J,10,FALSE),"-") -> - | Z97: =+IF(J97=0,"Por iniciar",IF(OR(K97="-",M97="-",P97="-",R97="-",T97="-",V97="-"),"Em testes",IF(AND(M97=0,P97=0,R97=0,T97<>K97,V97<>K97),"OK","NOK"))) -> Por iniciar
A98: =+H98&I98&$I$8 -> ENTITYEC_GRP_ID45596 | B98: {=+MAX(IF('ID1&5'!A:A='1. Status'!A98&'1. Status'!$B$10,'ID1&5'!K:K))} -> 0 | C98: {=+MAX(IF('ID1&5'!A:A='1. Status'!A98&'1. Status'!$C$10,'ID1&5'!K:K))} -> 0 | D98: {=+MAX(IF('ID1&5'!A:A='1. Status'!A98&'1. Status'!$D$10,'ID1&5'!K:K))} -> 0 | E98: {=+MAX(IF('ID1&5'!A:A='1. Status'!A98&'1. Status'!$E$10,'ID1&5'!K:K))} -> 0 | F98: {=+MAX(IF('ID1&5'!A:A='1. Status'!A98&'1. Status'!$F$10,'ID1&5'!K:K))} -> 0 | H98: ENTITY | I98: EC_GRP_ID | J98: =+COUNTIF('ID1&5'!G:G,'1. Status'!I98) -> 0 | K98: =+IFERROR(VLOOKUP(CONCATENATE(A98,$B$10,B98),'ID1&5'!B:J,8,FALSE),"-") -> - | L98: =+IFERROR(VLOOKUP(B98,'ID1&5'!K:L,2,FALSE),"-") -> - | M98: =+IFERROR(VLOOKUP(CONCATENATE(A98,$B$10,B98),'ID1&5'!B:J,9,FALSE),"-") -> - | N98: =+IFERROR(VLOOKUP(CONCATENATE(A98,$C$10,C98),'ID1&5'!B:J,8,FALSE),"-") -> - | O98: =+IFERROR(VLOOKUP(C98,'ID1&5'!K:L,2,FALSE),"-") -> - | P98: =+IFERROR(VLOOKUP(CONCATENATE(A98,$C$10,C98),'ID1&5'!B:J,9,FALSE),"-") -> - | Q98: =+IFERROR(VLOOKUP(D98,'ID1&5'!K:L,2,FALSE),"-") -> - | R98: =+IFERROR(VLOOKUP(CONCATENATE(A98,$D$10,D98),'ID1&5'!B:J,9,FALSE),"-") -> - | S98: =+IFERROR(VLOOKUP(E98,'ID1&5'!K:L,2,FALSE),"-") -> - | T98: =+IFERROR(VLOOKUP(CONCATENATE(A98,$E$10,E98),'ID1&5'!B:J,9,FALSE),"-") -> - | U98: =+IFERROR(VLOOKUP(F98,'ID1&5'!K:L,2,FALSE),"-") -> - | V98: =+IFERROR(VLOOKUP(CONCATENATE(A98,$F$10,F98),'ID1&5'!B:J,9,FALSE),"-") -> - | W98: =+IFERROR(VLOOKUP(A98,'ID6&7'!A:I,9,FALSE),"-") -> - | X98: =+IFERROR(VLOOKUP(A98,'ID6&7'!A:J,10,FALSE),"-") -> - | Z98: =+IF(J98=0,"Por iniciar",IF(OR(K98="-",M98="-",P98="-",R98="-",T98="-",V98="-"),"Em testes",IF(AND(M98=0,P98=0,R98=0,T98<>K98,V98<>K98),"OK","NOK"))) -> Por iniciar
A99: =+H99&I99&$I$8 -> ENTITYEC_GRP_NM45596 | B99: {=+MAX(IF('ID1&5'!A:A='1. Status'!A99&'1. Status'!$B$10,'ID1&5'!K:K))} -> 0 | C99: {=+MAX(IF('ID1&5'!A:A='1. Status'!A99&'1. Status'!$C$10,'ID1&5'!K:K))} -> 0 | D99: {=+MAX(IF('ID1&5'!A:A='1. Status'!A99&'1. Status'!$D$10,'ID1&5'!K:K))} -> 0 | E99: {=+MAX(IF('ID1&5'!A:A='1. Status'!A99&'1. Status'!$E$10,'ID1&5'!K:K))} -> 0 | F99: {=+MAX(IF('ID1&5'!A:A='1. Status'!A99&'1. Status'!$F$10,'ID1&5'!K:K))} -> 0 | H99: ENTITY | I99: EC_GRP_NM | J99: =+COUNTIF('ID1&5'!G:G,'1. Status'!I99) -> 0 | K99: =+IFERROR(VLOOKUP(CONCATENATE(A99,$B$10,B99),'ID1&5'!B:J,8,FALSE),"-") -> - | L99: =+IFERROR(VLOOKUP(B99,'ID1&5'!K:L,2,FALSE),"-") -> - | M99: =+IFERROR(VLOOKUP(CONCATENATE(A99,$B$10,B99),'ID1&5'!B:J,9,FALSE),"-") -> - | N99: =+IFERROR(VLOOKUP(CONCATENATE(A99,$C$10,C99),'ID1&5'!B:J,8,FALSE),"-") -> - | O99: =+IFERROR(VLOOKUP(C99,'ID1&5'!K:L,2,FALSE),"-") -> - | P99: =+IFERROR(VLOOKUP(CONCATENATE(A99,$C$10,C99),'ID1&5'!B:J,9,FALSE),"-") -> - | Q99: =+IFERROR(VLOOKUP(D99,'ID1&5'!K:L,2,FALSE),"-") -> - | R99: =+IFERROR(VLOOKUP(CONCATENATE(A99,$D$10,D99),'ID1&5'!B:J,9,FALSE),"-") -> - | S99: =+IFERROR(VLOOKUP(E99,'ID1&5'!K:L,2,FALSE),"-") -> - | T99: =+IFERROR(VLOOKUP(CONCATENATE(A99,$E$10,E99),'ID1&5'!B:J,9,FALSE),"-") -> - | U99: =+IFERROR(VLOOKUP(F99,'ID1&5'!K:L,2,FALSE),"-") -> - | V99: =+IFERROR(VLOOKUP(CONCATENATE(A99,$F$10,F99),'ID1&5'!B:J,9,FALSE),"-") -> - | W99: =+IFERROR(VLOOKUP(A99,'ID6&7'!A:I,9,FALSE),"-") -> - | X99: =+IFERROR(VLOOKUP(A99,'ID6&7'!A:J,10,FALSE),"-") -> - | Z99: =+IF(J99=0,"Por iniciar",IF(OR(K99="-",M99="-",P99="-",R99="-",T99="-",V99="-"),"Em testes",IF(AND(M99=0,P99=0,R99=0,T99<>K99,V99<>K99),"OK","NOK"))) -> Por iniciar
A100: =+H100&I100&$I$8 -> ENTITYPRSN_TYP45596 | B100: {=+MAX(IF('ID1&5'!A:A='1. Status'!A100&'1. Status'!$B$10,'ID1&5'!K:K))} -> 0 | C100: {=+MAX(IF('ID1&5'!A:A='1. Status'!A100&'1. Status'!$C$10,'ID1&5'!K:K))} -> 0 | D100: {=+MAX(IF('ID1&5'!A:A='1. Status'!A100&'1. Status'!$D$10,'ID1&5'!K:K))} -> 0 | E100: {=+MAX(IF('ID1&5'!A:A='1. Status'!A100&'1. Status'!$E$10,'ID1&5'!K:K))} -> 0 | F100: {=+MAX(IF('ID1&5'!A:A='1. Status'!A100&'1. Status'!$F$10,'ID1&5'!K:K))} -> 0 | H100: ENTITY | I100: PRSN_TYP | J100: =+COUNTIF('ID1&5'!G:G,'1. Status'!I100) -> 0 | K100: =+IFERROR(VLOOKUP(CONCATENATE(A100,$B$10,B100),'ID1&5'!B:J,8,FALSE),"-") -> - | L100: =+IFERROR(VLOOKUP(B100,'ID1&5'!K:L,2,FALSE),"-") -> - | M100: =+IFERROR(VLOOKUP(CONCATENATE(A100,$B$10,B100),'ID1&5'!B:J,9,FALSE),"-") -> - | N100: =+IFERROR(VLOOKUP(CONCATENATE(A100,$C$10,C100),'ID1&5'!B:J,8,FALSE),"-") -> - | O100: =+IFERROR(VLOOKUP(C100,'ID1&5'!K:L,2,FALSE),"-") -> - | P100: =+IFERROR(VLOOKUP(CONCATENATE(A100,$C$10,C100),'ID1&5'!B:J,9,FALSE),"-") -> - | Q100: =+IFERROR(VLOOKUP(D100,'ID1&5'!K:L,2,FALSE),"-") -> - | R100: =+IFERROR(VLOOKUP(CONCATENATE(A100,$D$10,D100),'ID1&5'!B:J,9,FALSE),"-") -> - | S100: =+IFERROR(VLOOKUP(E100,'ID1&5'!K:L,2,FALSE),"-") -> - | T100: =+IFERROR(VLOOKUP(CONCATENATE(A100,$E$10,E100),'ID1&5'!B:J,9,FALSE),"-") -> - | U100: =+IFERROR(VLOOKUP(F100,'ID1&5'!K:L,2,FALSE),"-") -> - | V100: =+IFERROR(VLOOKUP(CONCATENATE(A100,$F$10,F100),'ID1&5'!B:J,9,FALSE),"-") -> - | W100: =+IFERROR(VLOOKUP(A100,'ID6&7'!A:I,9,FALSE),"-") -> - | X100: =+IFERROR(VLOOKUP(A100,'ID6&7'!A:J,10,FALSE),"-") -> - | Z100: =+IF(J100=0,"Por iniciar",IF(OR(K100="-",M100="-",P100="-",R100="-",T100="-",V100="-"),"Em testes",IF(AND(M100=0,P100=0,R100=0,T100<>K100,V100<>K100),"OK","NOK"))) -> Por iniciar
... A110: =+H110&I110&$I$8 -> ENTITYHD_OFFC_UNDRTKNG_ID45596 | B110: {=+MAX(IF('ID1&5'!A:A='1. Status'!A110&'1. Status'!$B$10,'ID1&5'!K:K))} -> 0 | C110: {=+MAX(IF('ID1&5'!A:A='1. Status'!A110&'1. Status'!$C$10,'ID1&5'!K:K))} -> 0 | D110: {=+MAX(IF('ID1&5'!A:A='1. Status'!A110&'1. Status'!$D$10,'ID1&5'!K:K))} -> 0 | E110: {=+MAX(IF('ID1&5'!A:A='1. Status'!A110&'1. Status'!$E$10,'ID1&5'!K:K))} -> 0 | F110: {=+MAX(IF('ID1&5'!A:A='1. Status'!A110&'1. Status'!$F$10,'ID1&5'!K:K))} -> 0 | H110: ENTITY | I110: HD_OFFC_UNDRTKNG_ID | J110: =+COUNTIF('ID1&5'!G:G,'1. Status'!I110) -> 0 | K110: =+IFERROR(VLOOKUP(CONCATENATE(A110,$B$10,B110),'ID1&5'!B:J,8,FALSE),"-") -> - | L110: =+IFERROR(VLOOKUP(B110,'ID1&5'!K:L,2,FALSE),"-") -> - | M110: =+IFERROR(VLOOKUP(CONCATENATE(A110,$B$10,B110),'ID1&5'!B:J,9,FALSE),"-") -> - | N110: =+IFERROR(VLOOKUP(CONCATENATE(A110,$C$10,C110),'ID1&5'!B:J,8,FALSE),"-") -> - | O110: =+IFERROR(VLOOKUP(C110,'ID1&5'!K:L,2,FALSE),"-") -> - | P110: =+IFERROR(VLOOKUP(CONCATENATE(A110,$C$10,C110),'ID1&5'!B:J,9,FALSE),"-") -> - | Q110: =+IFERROR(VLOOKUP(D110,'ID1&5'!K:L,2,FALSE),"-") -> - | R110: =+IFERROR(VLOOKUP(CONCATENATE(A110,$D$10,D110),'ID1&5'!B:J,9,FALSE),"-") -> - | S110: =+IFERROR(VLOOKUP(E110,'ID1&5'!K:L,2,FALSE),"-") -> - | T110: =+IFERROR(VLOOKUP(CONCATENATE(A110,$E$10,E110),'ID1&5'!B:J,9,FALSE),"-") -> - | U110: =+IFERROR(VLOOKUP(F110,'ID1&5'!K:L,2,FALSE),"-") -> - | V110: =+IFERROR(VLOOKUP(CONCATENATE(A110,$F$10,F110),'ID1&5'!B:J,9,FALSE),"-") -> - | W110: =+IFERROR(VLOOKUP(A110,'ID6&7'!A:I,9,FALSE),"-") -> - | X110: =+IFERROR(VLOOKUP(A110,'ID6&7'!A:J,10,FALSE),"-") -> - | Z110: =+IF(J110=0,"Por iniciar",IF(OR(K110="-",M110="-",P110="-",R110="-",T110="-",V110="-"),"Em testes",IF(AND(M110=0,P110=0,R110=0,T110<>K110,V110<>K110),"OK","NOK"))) -> Por iniciar
A111: =+H111&I111&$I$8 -> ENTITYIMMDT_PRNT_UNDRTKNG_ID45596 | H111: ENTITY | I111: IMMDT_PRNT_UNDRTKNG_ID | J111: =+COUNTIF('ID1&5'!G:G,'1. Status'!I111) -> 0 | K111: =+IFERROR(VLOOKUP(CONCATENATE(A111,$B$10,B111),'ID1&5'!B:J,8,FALSE),"-") -> - | L111: =+IFERROR(VLOOKUP(B111,'ID1&5'!K:L,2,FALSE),"-") -> - | M111: =+IFERROR(VLOOKUP(CONCATENATE(A111,$B$10,B111),'ID1&5'!B:J,9,FALSE),"-") -> - | N111: =+IFERROR(VLOOKUP(CONCATENATE(A111,$C$10,C111),'ID1&5'!B:J,8,FALSE),"-") -> - | O111: =+IFERROR(VLOOKUP(C111,'ID1&5'!K:L,2,FALSE),"-") -> - | P111: =+IFERROR(VLOOKUP(CONCATENATE(A111,$C$10,C111),'ID1&5'!B:J,9,FALSE),"-") -> - | Q111: =+IFERROR(VLOOKUP(D111,'ID1&5'!K:L,2,FALSE),"-") -> - | R111: =+IFERROR(VLOOKUP(CONCATENATE(A111,$D$10,D111),'ID1&5'!B:J,9,FALSE),"-") -> - | S111: =+IFERROR(VLOOKUP(E111,'ID1&5'!K:L,2,FALSE),"-") -> - | T111: =+IFERROR(VLOOKUP(CONCATENATE(A111,$E$10,E111),'ID1&5'!B:J,9,FALSE),"-") -> - | U111: =+IFERROR(VLOOKUP(F111,'ID1&5'!K:L,2,FALSE),"-") -> - | V111: =+IFERROR(VLOOKUP(CONCATENATE(A111,$F$10,F111),'ID1&5'!B:J,9,FALSE),"-") -> - | W111: =+IFERROR(VLOOKUP(A111,'ID6&7'!A:I,9,FALSE),"-") -> - | X111: =+IFERROR(VLOOKUP(A111,'ID6&7'!A:J,10,FALSE),"-") -> - | Z111: =+IF(J111=0,"Por iniciar",IF(OR(K111="-",M111="-",P111="-",R111="-",T111="-",V111="-"),"Em testes",IF(AND(M111=0,P111=0,R111=0,T111<>K111,V111<>K111),"OK","NOK"))) -> Por iniciar
A112: =+H112&I112&$I$8 -> ENTITYULTMT_PRNT_UNDRTKNG_ID45596 | B112: {=+MAX(IF('ID1&5'!A:A='1. Status'!A112&'1. Status'!$B$10,'ID1&5'!K:K))} -> 0 | C112: {=+MAX(IF('ID1&5'!A:A='1. Status'!A112&'1. Status'!$C$10,'ID1&5'!K:K))} -> 0 | D112: {=+MAX(IF('ID1&5'!A:A='1. Status'!A112&'1. Status'!$D$10,'ID1&5'!K:K))} -> 0 | E112: {=+MAX(IF('ID1&5'!A:A='1. Status'!A112&'1. Status'!$E$10,'ID1&5'!K:K))} -> 0 | F112: {=+MAX(IF('ID1&5'!A:A='1. Status'!A112&'1. Status'!$F$10,'ID1&5'!K:K))} -> 0 | H112: ENTITY | I112: ULTMT_PRNT_UNDRTKNG_ID | J112: =+COUNTIF('ID1&5'!G:G,'1. Status'!I112) -> 0 | K112: =+IFERROR(VLOOKUP(CONCATENATE(A112,$B$10,B112),'ID1&5'!B:J,8,FALSE),"-") -> - | L112: =+IFERROR(VLOOKUP(B112,'ID1&5'!K:L,2,FALSE),"-") -> - | M112: =+IFERROR(VLOOKUP(CONCATENATE(A112,$B$10,B112),'ID1&5'!B:J,9,FALSE),"-") -> - | N112: =+IFERROR(VLOOKUP(CONCATENATE(A112,$C$10,C112),'ID1&5'!B:J,8,FALSE),"-") -> - | O112: =+IFERROR(VLOOKUP(C112,'ID1&5'!K:L,2,FALSE),"-") -> - | P112: =+IFERROR(VLOOKUP(CONCATENATE(A112,$C$10,C112),'ID1&5'!B:J,9,FALSE),"-") -> - | Q112: =+IFERROR(VLOOKUP(D112,'ID1&5'!K:L,2,FALSE),"-") -> - | R112: =+IFERROR(VLOOKUP(CONCATENATE(A112,$D$10,D112),'ID1&5'!B:J,9,FALSE),"-") -> - | S112: =+IFERROR(VLOOKUP(E112,'ID1&5'!K:L,2,FALSE),"-") -> - | T112: =+IFERROR(VLOOKUP(CONCATENATE(A112,$E$10,E112),'ID1&5'!B:J,9,FALSE),"-") -> - | U112: =+IFERROR(VLOOKUP(F112,'ID1&5'!K:L,2,FALSE),"-") -> - | V112: =+IFERROR(VLOOKUP(CONCATENATE(A112,$F$10,F112),'ID1&5'!B:J,9,FALSE),"-") -> - | W112: =+IFERROR(VLOOKUP(A112,'ID6&7'!A:I,9,FALSE),"-") -> - | X112: =+IFERROR(VLOOKUP(A112,'ID6&7'!A:J,10,FALSE),"-") -> - | Z112: =+IF(J112=0,"Por iniciar",IF(OR(K112="-",M112="-",P112="-",R112="-",T112="-",V112="-"),"Em testes",IF(AND(M112=0,P112=0,R112=0,T112<>K112,V112<>K112),"OK","NOK"))) -> Por iniciar
A113: =+H113&I113&$I$8 -> ENTITYTTL_ASSTS45596 | B113: {=+MAX(IF('ID1&5'!A:A='1. Status'!A113&'1. Status'!$B$10,'ID1&5'!K:K))} -> 0 | C113: {=+MAX(IF('ID1&5'!A:A='1. Status'!A113&'1. Status'!$C$10,'ID1&5'!K:K))} -> 0 | D113: {=+MAX(IF('ID1&5'!A:A='1. Status'!A113&'1. Status'!$D$10,'ID1&5'!K:K))} -> 0 | E113: {=+MAX(IF('ID1&5'!A:A='1. Status'!A113&'1. Status'!$E$10,'ID1&5'!K:K))} -> 0 | F113: {=+MAX(IF('ID1&5'!A:A='1. Status'!A113&'1. Status'!$F$10,'ID1&5'!K:K))} -> 0 | H113: ENTITY | I113: TTL_ASSTS | J113: =+COUNTIF('ID1&5'!G:G,'1. Status'!I113) -> 0 | K113: =+IFERROR(VLOOKUP(CONCATENATE(A113,$B$10,B113),'ID1&5'!B:J,8,FALSE),"-") -> - | L113: =+IFERROR(VLOOKUP(B113,'ID1&5'!K:L,2,FALSE),"-") -> - | M113: =+IFERROR(VLOOKUP(CONCATENATE(A113,$B$10,B113),'ID1&5'!B:J,9,FALSE),"-") -> - | N113: =+IFERROR(VLOOKUP(CONCATENATE(A113,$C$10,C113),'ID1&5'!B:J,8,FALSE),"-") -> - | O113: =+IFERROR(VLOOKUP(C113,'ID1&5'!K:L,2,FALSE),"-") -> - | P113: =+IFERROR(VLOOKUP(CONCATENATE(A113,$C$10,C113),'ID1&5'!B:J,9,FALSE),"-") -> - | Q113: =+IFERROR(VLOOKUP(D113,'ID1&5'!K:L,2,FALSE),"-") -> - | R113: =+IFERROR(VLOOKUP(CONCATENATE(A113,$D$10,D113),'ID1&5'!B:J,9,FALSE),"-") -> - | S113: =+IFERROR(VLOOKUP(E113,'ID1&5'!K:L,2,FALSE),"-") -> - | T113: =+IFERROR(VLOOKUP(CONCATENATE(A113,$E$10,E113),'ID1&5'!B:J,9,FALSE),"-") -> - | U113: =+IFERROR(VLOOKUP(F113,'ID1&5'!K:L,2,FALSE),"-") -> - | V113: =+IFERROR(VLOOKUP(CONCATENATE(A113,$F$10,F113),'ID1&5'!B:J,9,FALSE),"-") -> - | W113: =+IFERROR(VLOOKUP(A113,'ID6&7'!A:I,9,FALSE),"-") -> - | X113: =+IFERROR(VLOOKUP(A113,'ID6&7'!A:J,10,FALSE),"-") -> - | Z113: =+IF(J113=0,"Por iniciar",IF(OR(K113="-",M113="-",P113="-",R113="-",T113="-",V113="-"),"Em testes",IF(AND(M113=0,P113=0,R113=0,T113<>K113,V113<>K113),"OK","NOK"))) -> Por iniciar
A114: =+H114&I114&$I$8 -> ENTITYENTTY_ID_BDR45596 | B114: {=+MAX(IF('ID1&5'!A:A='1. Status'!A114&'1. Status'!$B$10,'ID1&5'!K:K))} -> 0 | C114: {=+MAX(IF('ID1&5'!A:A='1. Status'!A114&'1. Status'!$C$10,'ID1&5'!K:K))} -> 0 | D114: {=+MAX(IF('ID1&5'!A:A='1. Status'!A114&'1. Status'!$D$10,'ID1&5'!K:K))} -> 0 | E114: {=+MAX(IF('ID1&5'!A:A='1. Status'!A114&'1. Status'!$E$10,'ID1&5'!K:K))} -> 0 | F114: {=+MAX(IF('ID1&5'!A:A='1. Status'!A114&'1. Status'!$F$10,'ID1&5'!K:K))} -> 0 | H114: ENTITY | I114: ENTTY_ID_BDR | J114: =+COUNTIF('ID1&5'!G:G,'1. Status'!I114) -> 0 | K114: =+IFERROR(VLOOKUP(CONCATENATE(A114,$B$10,B114),'ID1&5'!B:J,8,FALSE),"-") -> - | L114: =+IFERROR(VLOOKUP(B114,'ID1&5'!K:L,2,FALSE),"-") -> - | M114: =+IFERROR(VLOOKUP(CONCATENATE(A114,$B$10,B114),'ID1&5'!B:J,9,FALSE),"-") -> - | N114: =+IFERROR(VLOOKUP(CONCATENATE(A114,$C$10,C114),'ID1&5'!B:J,8,FALSE),"-") -> - | O114: =+IFERROR(VLOOKUP(C114,'ID1&5'!K:L,2,FALSE),"-") -> - | P114: =+IFERROR(VLOOKUP(CONCATENATE(A114,$C$10,C114),'ID1&5'!B:J,9,FALSE),"-") -> - | Q114: =+IFERROR(VLOOKUP(D114,'ID1&5'!K:L,2,FALSE),"-") -> - | R114: =+IFERROR(VLOOKUP(CONCATENATE(A114,$D$10,D114),'ID1&5'!B:J,9,FALSE),"-") -> - | S114: =+IFERROR(VLOOKUP(E114,'ID1&5'!K:L,2,FALSE),"-") -> - | T114: =+IFERROR(VLOOKUP(CONCATENATE(A114,$E$10,E114),'ID1&5'!B:J,9,FALSE),"-") -> - | U114: =+IFERROR(VLOOKUP(F114,'ID1&5'!K:L,2,FALSE),"-") -> - | V114: =+IFERROR(VLOOKUP(CONCATENATE(A114,$F$10,F114),'ID1&5'!B:J,9,FALSE),"-") -> - | W114: =+IFERROR(VLOOKUP(A114,'ID6&7'!A:I,9,FALSE),"-") -> - | X114: =+IFERROR(VLOOKUP(A114,'ID6&7'!A:J,10,FALSE),"-") -> - | Z114: =+IF(J114=0,"Por iniciar",IF(OR(K114="-",M114="-",P114="-",R114="-",T114="-",V114="-"),"Em testes",IF(AND(M114=0,P114=0,R114=0,T114<>K114,V114<>K114),"OK","NOK"))) -> Por iniciar
A115: =+H115&I115&$I$8 -> INSTR_ENTITYCOD_SOC45596 | B115: {=+MAX(IF('ID1&5'!A:A='1. Status'!A115&'1. Status'!$B$10,'ID1&5'!K:K))} -> 0 | C115: {=+MAX(IF('ID1&5'!A:A='1. Status'!A115&'1. Status'!$C$10,'ID1&5'!K:K))} -> 0 | D115: {=+MAX(IF('ID1&5'!A:A='1. Status'!A115&'1. Status'!$D$10,'ID1&5'!K:K))} -> 0 | E115: {=+MAX(IF('ID1&5'!A:A='1. Status'!A115&'1. Status'!$E$10,'ID1&5'!K:K))} -> 0 | F115: {=+MAX(IF('ID1&5'!A:A='1. Status'!A115&'1. Status'!$F$10,'ID1&5'!K:K))} -> 0 | H115: INSTR_ENTITY | I115: COD_SOC | J115: =+COUNTIF('ID1&5'!G:G,'1. Status'!I115) -> 0 | K115: =+IFERROR(VLOOKUP(CONCATENATE(A115,$B$10,B115),'ID1&5'!B:J,8,FALSE),"-") -> - | L115: =+IFERROR(VLOOKUP(B115,'ID1&5'!K:L,2,FALSE),"-") -> - | M115: =+IFERROR(VLOOKUP(CONCATENATE(A115,$B$10,B115),'ID1&5'!B:J,9,FALSE),"-") -> - | N115: =+IFERROR(VLOOKUP(CONCATENATE(A115,$C$10,C115),'ID1&5'!B:J,8,FALSE),"-") -> - | O115: =+IFERROR(VLOOKUP(C115,'ID1&5'!K:L,2,FALSE),"-") -> - | P115: =+IFERROR(VLOOKUP(CONCATENATE(A115,$C$10,C115),'ID1&5'!B:J,9,FALSE),"-") -> - | Q115: =+IFERROR(VLOOKUP(D115,'ID1&5'!K:L,2,FALSE),"-") -> - | R115: =+IFERROR(VLOOKUP(CONCATENATE(A115,$D$10,D115),'ID1&5'!B:J,9,FALSE),"-") -> - | S115: =+IFERROR(VLOOKUP(E115,'ID1&5'!K:L,2,FALSE),"-") -> - | T115: =+IFERROR(VLOOKUP(CONCATENATE(A115,$E$10,E115),'ID1&5'!B:J,9,FALSE),"-") -> - | U115: =+IFERROR(VLOOKUP(F115,'ID1&5'!K:L,2,FALSE),"-") -> - | V115: =+IFERROR(VLOOKUP(CONCATENATE(A115,$F$10,F115),'ID1&5'!B:J,9,FALSE),"-") -> - | W115: =+IFERROR(VLOOKUP(A115,'ID6&7'!A:I,9,FALSE),"-") -> - | X115: =+IFERROR(VLOOKUP(A115,'ID6&7'!A:J,10,FALSE),"-") -> - | Z115: =+IF(J115=0,"Por iniciar",IF(OR(K115="-",M115="-",P115="-",R115="-",T115="-",V115="-"),"Em testes",IF(AND(M115=0,P115=0,R115=0,T115<>K115,V115<>K115),"OK","NOK"))) -> Por iniciar
A116: =+H116&I116&$I$8 -> INSTR_ENTITYJNT_LBLTY_AMNT45596 | B116: {=+MAX(IF('ID1&5'!A:A='1. Status'!A116&'1. Status'!$B$10,'ID1&5'!K:K))} -> 0 | C116: {=+MAX(IF('ID1&5'!A:A='1. Status'!A116&'1. Status'!$C$10,'ID1&5'!K:K))} -> 0 | D116: {=+MAX(IF('ID1&5'!A:A='1. Status'!A116&'1. Status'!$D$10,'ID1&5'!K:K))} -> 0 | E116: {=+MAX(IF('ID1&5'!A:A='1. Status'!A116&'1. Status'!$E$10,'ID1&5'!K:K))} -> 0 | F116: {=+MAX(IF('ID1&5'!A:A='1. Status'!A116&'1. Status'!$F$10,'ID1&5'!K:K))} -> 0 | H116: INSTR_ENTITY | I116: JNT_LBLTY_AMNT | J116: =+COUNTIF('ID1&5'!G:G,'1. Status'!I116) -> 0 | K116: =+IFERROR(VLOOKUP(CONCATENATE(A116,$B$10,B116),'ID1&5'!B:J,8,FALSE),"-") -> - | L116: =+IFERROR(VLOOKUP(B116,'ID1&5'!K:L,2,FALSE),"-") -> - | M116: =+IFERROR(VLOOKUP(CONCATENATE(A116,$B$10,B116),'ID1&5'!B:J,9,FALSE),"-") -> - | N116: =+IFERROR(VLOOKUP(CONCATENATE(A116,$C$10,C116),'ID1&5'!B:J,8,FALSE),"-") -> - | O116: =+IFERROR(VLOOKUP(C116,'ID1&5'!K:L,2,FALSE),"-") -> - | P116: =+IFERROR(VLOOKUP(CONCATENATE(A116,$C$10,C116),'ID1&5'!B:J,9,FALSE),"-") -> - | Q116: =+IFERROR(VLOOKUP(D116,'ID1&5'!K:L,2,FALSE),"-") -> - | R116: =+IFERROR(VLOOKUP(CONCATENATE(A116,$D$10,D116),'ID1&5'!B:J,9,FALSE),"-") -> - | S116: =+IFERROR(VLOOKUP(E116,'ID1&5'!K:L,2,FALSE),"-") -> - | T116: =+IFERROR(VLOOKUP(CONCATENATE(A116,$E$10,E116),'ID1&5'!B:J,9,FALSE),"-") -> - | U116: =+IFERROR(VLOOKUP(F116,'ID1&5'!K:L,2,FALSE),"-") -> - | V116: =+IFERROR(VLOOKUP(CONCATENATE(A116,$F$10,F116),'ID1&5'!B:J,9,FALSE),"-") -> - | W116: =+IFERROR(VLOOKUP(A116,'ID6&7'!A:I,9,FALSE),"-") -> - | X116: =+IFERROR(VLOOKUP(A116,'ID6&7'!A:J,10,FALSE),"-") -> - | Z116: =+IF(J116=0,"Por iniciar",IF(OR(K116="-",M116="-",P116="-",R116="-",T116="-",V116="-"),"Em testes",IF(AND(M116=0,P116=0,R116=0,T116<>K116,V116<>K116),"OK","NOK"))) -> Por iniciar
A117: =+H117&I117&$I$8 -> INSTR_ENTITYMN_ENTTY_ID45596 | B117: {=+MAX(IF('ID1&5'!A:A='1. Status'!A117&'1. Status'!$B$10,'ID1&5'!K:K))} -> 0 | C117: {=+MAX(IF('ID1&5'!A:A='1. Status'!A117&'1. Status'!$C$10,'ID1&5'!K:K))} -> 0 | D117: {=+MAX(IF('ID1&5'!A:A='1. Status'!A117&'1. Status'!$D$10,'ID1&5'!K:K))} -> 0 | E117: {=+MAX(IF('ID1&5'!A:A='1. Status'!A117&'1. Status'!$E$10,'ID1&5'!K:K))} -> 0 | F117: {=+MAX(IF('ID1&5'!A:A='1. Status'!A117&'1. Status'!$F$10,'ID1&5'!K:K))} -> 0 | H117: INSTR_ENTITY | I117: MN_ENTTY_ID | J117: =+COUNTIF('ID1&5'!G:G,'1. Status'!I117) -> 0 | K117: =+IFERROR(VLOOKUP(CONCATENATE(A117,$B$10,B117),'ID1&5'!B:J,8,FALSE),"-") -> - | L117: =+IFERROR(VLOOKUP(B117,'ID1&5'!K:L,2,FALSE),"-") -> - | M117: =+IFERROR(VLOOKUP(CONCATENATE(A117,$B$10,B117),'ID1&5'!B:J,9,FALSE),"-") -> - | N117: =+IFERROR(VLOOKUP(CONCATENATE(A117,$C$10,C117),'ID1&5'!B:J,8,FALSE),"-") -> - | O117: =+IFERROR(VLOOKUP(C117,'ID1&5'!K:L,2,FALSE),"-") -> - | P117: =+IFERROR(VLOOKUP(CONCATENATE(A117,$C$10,C117),'ID1&5'!B:J,9,FALSE),"-") -> - | Q117: =+IFERROR(VLOOKUP(D117,'ID1&5'!K:L,2,FALSE),"-") -> - | R117: =+IFERROR(VLOOKUP(CONCATENATE(A117,$D$10,D117),'ID1&5'!B:J,9,FALSE),"-") -> - | S117: =+IFERROR(VLOOKUP(E117,'ID1&5'!K:L,2,FALSE),"-") -> - | T117: =+IFERROR(VLOOKUP(CONCATENATE(A117,$E$10,E117),'ID1&5'!B:J,9,FALSE),"-") -> - | U117: =+IFERROR(VLOOKUP(F117,'ID1&5'!K:L,2,FALSE),"-") -> - | V117: =+IFERROR(VLOOKUP(CONCATENATE(A117,$F$10,F117),'ID1&5'!B:J,9,FALSE),"-") -> - | W117: =+IFERROR(VLOOKUP(A117,'ID6&7'!A:I,9,FALSE),"-") -> - | X117: =+IFERROR(VLOOKUP(A117,'ID6&7'!A:J,10,FALSE),"-") -> - | Z117: =+IF(J117=0,"Por iniciar",IF(OR(K117="-",M117="-",P117="-",R117="-",T117="-",V117="-"),"Em testes",IF(AND(M117=0,P117=0,R117=0,T117<>K117,V117<>K117),"OK","NOK"))) -> Por iniciar
A118: =+H118&I118&$I$8 -> INSTRUMENTCOD_SOC45596 | B118: {=+MAX(IF('ID1&5'!A:A='1. Status'!A118&'1. Status'!$B$10,'ID1&5'!K:K))} -> 0 | C118: {=+MAX(IF('ID1&5'!A:A='1. Status'!A118&'1. Status'!$C$10,'ID1&5'!K:K))} -> 0 | D118: {=+MAX(IF('ID1&5'!A:A='1. Status'!A118&'1. Status'!$D$10,'ID1&5'!K:K))} -> 0 | E118: {=+MAX(IF('ID1&5'!A:A='1. Status'!A118&'1. Status'!$E$10,'ID1&5'!K:K))} -> 0 | F118: {=+MAX(IF('ID1&5'!A:A='1. Status'!A118&'1. Status'!$F$10,'ID1&5'!K:K))} -> 0 | H118: INSTRUMENT | I118: COD_SOC | J118: =+COUNTIF('ID1&5'!G:G,'1. Status'!I118) -> 0 | K118: =+IFERROR(VLOOKUP(CONCATENATE(A118,$B$10,B118),'ID1&5'!B:J,8,FALSE),"-") -> - | L118: =+IFERROR(VLOOKUP(B118,'ID1&5'!K:L,2,FALSE),"-") -> - | M118: =+IFERROR(VLOOKUP(CONCATENATE(A118,$B$10,B118),'ID1&5'!B:J,9,FALSE),"-") -> - | N118: =+IFERROR(VLOOKUP(CONCATENATE(A118,$C$10,C118),'ID1&5'!B:J,8,FALSE),"-") -> - | O118: =+IFERROR(VLOOKUP(C118,'ID1&5'!K:L,2,FALSE),"-") -> - | P118: =+IFERROR(VLOOKUP(CONCATENATE(A118,$C$10,C118),'ID1&5'!B:J,9,FALSE),"-") -> - | Q118: =+IFERROR(VLOOKUP(D118,'ID1&5'!K:L,2,FALSE),"-") -> - | R118: =+IFERROR(VLOOKUP(CONCATENATE(A118,$D$10,D118),'ID1&5'!B:J,9,FALSE),"-") -> - | S118: =+IFERROR(VLOOKUP(E118,'ID1&5'!K:L,2,FALSE),"-") -> - | T118: =+IFERROR(VLOOKUP(CONCATENATE(A118,$E$10,E118),'ID1&5'!B:J,9,FALSE),"-") -> - | U118: =+IFERROR(VLOOKUP(F118,'ID1&5'!K:L,2,FALSE),"-") -> - | V118: =+IFERROR(VLOOKUP(CONCATENATE(A118,$F$10,F118),'ID1&5'!B:J,9,FALSE),"-") -> - | W118: =+IFERROR(VLOOKUP(A118,'ID6&7'!A:I,9,FALSE),"-") -> - | X118: =+IFERROR(VLOOKUP(A118,'ID6&7'!A:J,10,FALSE),"-") -> - | Z118: =+IF(J118=0,"Por iniciar",IF(OR(K118="-",M118="-",P118="-",R118="-",T118="-",V118="-"),"Em testes",IF(AND(M118=0,P118=0,R118=0,T118<>K118,V118<>K118),"OK","NOK"))) -> Por iniciar
A119: =+H119&I119&$I$8 -> INSTRUMENTSUBPORTFOLIO_ID45596 | B119: {=+MAX(IF('ID1&5'!A:A='1. Status'!A119&'1. Status'!$B$10,'ID1&5'!K:K))} -> 0 | C119: {=+MAX(IF('ID1&5'!A:A='1. Status'!A119&'1. Status'!$C$10,'ID1&5'!K:K))} -> 0 | D119: {=+MAX(IF('ID1&5'!A:A='1. Status'!A119&'1. Status'!$D$10,'ID1&5'!K:K))} -> 0 | E119: {=+MAX(IF('ID1&5'!A:A='1. Status'!A119&'1. Status'!$E$10,'ID1&5'!K:K))} -> 0 | F119: {=+MAX(IF('ID1&5'!A:A='1. Status'!A119&'1. Status'!$F$10,'ID1&5'!K:K))} -> 0 | H119: INSTRUMENT | I119: SUBPORTFOLIO_ID | J119: =+COUNTIF('ID1&5'!G:G,'1. Status'!I119) -> 0 | K119: =+IFERROR(VLOOKUP(CONCATENATE(A119,$B$10,B119),'ID1&5'!B:J,8,FALSE),"-") -> - | L119: =+IFERROR(VLOOKUP(B119,'ID1&5'!K:L,2,FALSE),"-") -> - | M119: =+IFERROR(VLOOKUP(CONCATENATE(A119,$B$10,B119),'ID1&5'!B:J,9,FALSE),"-") -> - | N119: =+IFERROR(VLOOKUP(CONCATENATE(A119,$C$10,C119),'ID1&5'!B:J,8,FALSE),"-") -> - | O119: =+IFERROR(VLOOKUP(C119,'ID1&5'!K:L,2,FALSE),"-") -> - | P119: =+IFERROR(VLOOKUP(CONCATENATE(A119,$C$10,C119),'ID1&5'!B:J,9,FALSE),"-") -> - | Q119: =+IFERROR(VLOOKUP(D119,'ID1&5'!K:L,2,FALSE),"-") -> - | R119: =+IFERROR(VLOOKUP(CONCATENATE(A119,$D$10,D119),'ID1&5'!B:J,9,FALSE),"-") -> - | S119: =+IFERROR(VLOOKUP(E119,'ID1&5'!K:L,2,FALSE),"-") -> - | T119: =+IFERROR(VLOOKUP(CONCATENATE(A119,$E$10,E119),'ID1&5'!B:J,9,FALSE),"-") -> - | U119: =+IFERROR(VLOOKUP(F119,'ID1&5'!K:L,2,FALSE),"-") -> - | V119: =+IFERROR(VLOOKUP(CONCATENATE(A119,$F$10,F119),'ID1&5'!B:J,9,FALSE),"-") -> - | W119: =+IFERROR(VLOOKUP(A119,'ID6&7'!A:I,9,FALSE),"-") -> - | X119: =+IFERROR(VLOOKUP(A119,'ID6&7'!A:J,10,FALSE),"-") -> - | Z119: =+IF(J119=0,"Por iniciar",IF(OR(K119="-",M119="-",P119="-",R119="-",T119="-",V119="-"),"Em testes",IF(AND(M119=0,P119=0,R119=0,T119<>K119,V119<>K119),"OK","NOK"))) -> Por iniciar
A120: =+H120&I120&$I$8 -> INSTRUMENTCRE_FNRP1845596 | H120: INSTRUMENT | I120: CRE_FNRP18 | J120: =+COUNTIF('ID1&5'!G:G,'1. Status'!I120) -> 0 | K120: =+IFERROR(VLOOKUP(CONCATENATE(A120,$B$10,B120),'ID1&5'!B:J,8,FALSE),"-") -> - | L120: =+IFERROR(VLOOKUP(B120,'ID1&5'!K:L,2,FALSE),"-") -> - | M120: =+IFERROR(VLOOKUP(CONCATENATE(A120,$B$10,B120),'ID1&5'!B:J,9,FALSE),"-") -> - | N120: =+IFERROR(VLOOKUP(CONCATENATE(A120,$C$10,C120),'ID1&5'!B:J,8,FALSE),"-") -> - | O120: =+IFERROR(VLOOKUP(C120,'ID1&5'!K:L,2,FALSE),"-") -> - | P120: =+IFERROR(VLOOKUP(CONCATENATE(A120,$C$10,C120),'ID1&5'!B:J,9,FALSE),"-") -> - | Q120: =+IFERROR(VLOOKUP(D120,'ID1&5'!K:L,2,FALSE),"-") -> - | R120: =+IFERROR(VLOOKUP(CONCATENATE(A120,$D$10,D120),'ID1&5'!B:J,9,FALSE),"-") -> - | S120: =+IFERROR(VLOOKUP(E120,'ID1&5'!K:L,2,FALSE),"-") -> - | T120: =+IFERROR(VLOOKUP(CONCATENATE(A120,$E$10,E120),'ID1&5'!B:J,9,FALSE),"-") -> - | U120: =+IFERROR(VLOOKUP(F120,'ID1&5'!K:L,2,FALSE),"-") -> - | V120: =+IFERROR(VLOOKUP(CONCATENATE(A120,$F$10,F120),'ID1&5'!B:J,9,FALSE),"-") -> - | W120: =+IFERROR(VLOOKUP(A120,'ID6&7'!A:I,9,FALSE),"-") -> - | X120: =+IFERROR(VLOOKUP(A120,'ID6&7'!A:J,10,FALSE),"-") -> - | Z120: =+IF(J120=0,"Por iniciar",IF(OR(K120="-",M120="-",P120="-",R120="-",T120="-",V120="-"),"Em testes",IF(AND(M120=0,P120=0,R120=0,T120<>K120,V120<>K120),"OK","NOK"))) -> Por iniciar
A121: =+H121&I121&$I$8 -> INSTRUMENTSME_FNRP1845596 | H121: INSTRUMENT | I121: SME_FNRP18 | J121: =+COUNTIF('ID1&5'!G:G,'1. Status'!I121) -> 0 | K121: =+IFERROR(VLOOKUP(CONCATENATE(A121,$B$10,B121),'ID1&5'!B:J,8,FALSE),"-") -> - | L121: =+IFERROR(VLOOKUP(B121,'ID1&5'!K:L,2,FALSE),"-") -> - | M121: =+IFERROR(VLOOKUP(CONCATENATE(A121,$B$10,B121),'ID1&5'!B:J,9,FALSE),"-") -> - | N121: =+IFERROR(VLOOKUP(CONCATENATE(A121,$C$10,C121),'ID1&5'!B:J,8,FALSE),"-") -> - | O121: =+IFERROR(VLOOKUP(C121,'ID1&5'!K:L,2,FALSE),"-") -> - | P121: =+IFERROR(VLOOKUP(CONCATENATE(A121,$C$10,C121),'ID1&5'!B:J,9,FALSE),"-") -> - | Q121: =+IFERROR(VLOOKUP(D121,'ID1&5'!K:L,2,FALSE),"-") -> - | R121: =+IFERROR(VLOOKUP(CONCATENATE(A121,$D$10,D121),'ID1&5'!B:J,9,FALSE),"-") -> - | S121: =+IFERROR(VLOOKUP(E121,'ID1&5'!K:L,2,FALSE),"-") -> - | T121: =+IFERROR(VLOOKUP(CONCATENATE(A121,$E$10,E121),'ID1&5'!B:J,9,FALSE),"-") -> - | U121: =+IFERROR(VLOOKUP(F121,'ID1&5'!K:L,2,FALSE),"-") -> - | V121: =+IFERROR(VLOOKUP(CONCATENATE(A121,$F$10,F121),'ID1&5'!B:J,9,FALSE),"-") -> - | W121: =+IFERROR(VLOOKUP(A121,'ID6&7'!A:I,9,FALSE),"-") -> - | X121: =+IFERROR(VLOOKUP(A121,'ID6&7'!A:J,10,FALSE),"-") -> - | Z121: =+IF(J121=0,"Por iniciar",IF(OR(K121="-",M121="-",P121="-",R121="-",T121="-",V121="-"),"Em testes",IF(AND(M121=0,P121=0,R121=0,T121<>K121,V121<>K121),"OK","NOK"))) -> Por iniciar
A122: =+H122&I122&$I$8 -> INSTRUMENTRRE_FNRP1845596 | H122: INSTRUMENT | I122: RRE_FNRP18 | J122: =+COUNTIF('ID1&5'!G:G,'1. Status'!I122) -> 0 | K122: =+IFERROR(VLOOKUP(CONCATENATE(A122,$B$10,B122),'ID1&5'!B:J,8,FALSE),"-") -> - | L122: =+IFERROR(VLOOKUP(B122,'ID1&5'!K:L,2,FALSE),"-") -> - | M122: =+IFERROR(VLOOKUP(CONCATENATE(A122,$B$10,B122),'ID1&5'!B:J,9,FALSE),"-") -> - | N122: =+IFERROR(VLOOKUP(CONCATENATE(A122,$C$10,C122),'ID1&5'!B:J,8,FALSE),"-") -> - | O122: =+IFERROR(VLOOKUP(C122,'ID1&5'!K:L,2,FALSE),"-") -> - | P122: =+IFERROR(VLOOKUP(CONCATENATE(A122,$C$10,C122),'ID1&5'!B:J,9,FALSE),"-") -> - | Q122: =+IFERROR(VLOOKUP(D122,'ID1&5'!K:L,2,FALSE),"-") -> - | R122: =+IFERROR(VLOOKUP(CONCATENATE(A122,$D$10,D122),'ID1&5'!B:J,9,FALSE),"-") -> - | S122: =+IFERROR(VLOOKUP(E122,'ID1&5'!K:L,2,FALSE),"-") -> - | T122: =+IFERROR(VLOOKUP(CONCATENATE(A122,$E$10,E122),'ID1&5'!B:J,9,FALSE),"-") -> - | U122: =+IFERROR(VLOOKUP(F122,'ID1&5'!K:L,2,FALSE),"-") -> - | V122: =+IFERROR(VLOOKUP(CONCATENATE(A122,$F$10,F122),'ID1&5'!B:J,9,FALSE),"-") -> - | W122: =+IFERROR(VLOOKUP(A122,'ID6&7'!A:I,9,FALSE),"-") -> - | X122: =+IFERROR(VLOOKUP(A122,'ID6&7'!A:J,10,FALSE),"-") -> - | Z122: =+IF(J122=0,"Por iniciar",IF(OR(K122="-",M122="-",P122="-",R122="-",T122="-",V122="-"),"Em testes",IF(AND(M122=0,P122=0,R122=0,T122<>K122,V122<>K122),"OK","NOK"))) -> Por iniciar
A123: =+H123&I123&$I$8 -> INSTRUMENTCNSMPTN_FNRP1845596 | H123: INSTRUMENT | I123: CNSMPTN_FNRP18 | J123: =+COUNTIF('ID1&5'!G:G,'1. Status'!I123) -> 0 | K123: =+IFERROR(VLOOKUP(CONCATENATE(A123,$B$10,B123),'ID1&5'!B:J,8,FALSE),"-") -> - | L123: =+IFERROR(VLOOKUP(B123,'ID1&5'!K:L,2,FALSE),"-") -> - | M123: =+IFERROR(VLOOKUP(CONCATENATE(A123,$B$10,B123),'ID1&5'!B:J,9,FALSE),"-") -> - | N123: =+IFERROR(VLOOKUP(CONCATENATE(A123,$C$10,C123),'ID1&5'!B:J,8,FALSE),"-") -> - | O123: =+IFERROR(VLOOKUP(C123,'ID1&5'!K:L,2,FALSE),"-") -> - | P123: =+IFERROR(VLOOKUP(CONCATENATE(A123,$C$10,C123),'ID1&5'!B:J,9,FALSE),"-") -> - | Q123: =+IFERROR(VLOOKUP(D123,'ID1&5'!K:L,2,FALSE),"-") -> - | R123: =+IFERROR(VLOOKUP(CONCATENATE(A123,$D$10,D123),'ID1&5'!B:J,9,FALSE),"-") -> - | S123: =+IFERROR(VLOOKUP(E123,'ID1&5'!K:L,2,FALSE),"-") -> - | T123: =+IFERROR(VLOOKUP(CONCATENATE(A123,$E$10,E123),'ID1&5'!B:J,9,FALSE),"-") -> - | U123: =+IFERROR(VLOOKUP(F123,'ID1&5'!K:L,2,FALSE),"-") -> - | V123: =+IFERROR(VLOOKUP(CONCATENATE(A123,$F$10,F123),'ID1&5'!B:J,9,FALSE),"-") -> - | W123: =+IFERROR(VLOOKUP(A123,'ID6&7'!A:I,9,FALSE),"-") -> - | X123: =+IFERROR(VLOOKUP(A123,'ID6&7'!A:J,10,FALSE),"-") -> - | Z123: =+IF(J123=0,"Por iniciar",IF(OR(K123="-",M123="-",P123="-",R123="-",T123="-",V123="-"),"Em testes",IF(AND(M123=0,P123=0,R123=0,T123<>K123,V123<>K123),"OK","NOK"))) -> Por iniciar
A124: =+H124&I124&$I$8 -> INSTRUMENTCNTRCT_ID45596 | H124: INSTRUMENT | I124: CNTRCT_ID | J124: =+COUNTIF('ID1&5'!G:G,'1. Status'!I124) -> 0 | K124: =+IFERROR(VLOOKUP(CONCATENATE(A124,$B$10,B124),'ID1&5'!B:J,8,FALSE),"-") -> - | L124: =+IFERROR(VLOOKUP(B124,'ID1&5'!K:L,2,FALSE),"-") -> - | M124: =+IFERROR(VLOOKUP(CONCATENATE(A124,$B$10,B124),'ID1&5'!B:J,9,FALSE),"-") -> - | N124: =+IFERROR(VLOOKUP(CONCATENATE(A124,$C$10,C124),'ID1&5'!B:J,8,FALSE),"-") -> - | O124: =+IFERROR(VLOOKUP(C124,'ID1&5'!K:L,2,FALSE),"-") -> - | P124: =+IFERROR(VLOOKUP(CONCATENATE(A124,$C$10,C124),'ID1&5'!B:J,9,FALSE),"-") -> - | Q124: =+IFERROR(VLOOKUP(D124,'ID1&5'!K:L,2,FALSE),"-") -> - | R124: =+IFERROR(VLOOKUP(CONCATENATE(A124,$D$10,D124),'ID1&5'!B:J,9,FALSE),"-") -> - | S124: =+IFERROR(VLOOKUP(E124,'ID1&5'!K:L,2,FALSE),"-") -> - | T124: =+IFERROR(VLOOKUP(CONCATENATE(A124,$E$10,E124),'ID1&5'!B:J,9,FALSE),"-") -> - | U124: =+IFERROR(VLOOKUP(F124,'ID1&5'!K:L,2,FALSE),"-") -> - | V124: =+IFERROR(VLOOKUP(CONCATENATE(A124,$F$10,F124),'ID1&5'!B:J,9,FALSE),"-") -> - | W124: =+IFERROR(VLOOKUP(A124,'ID6&7'!A:I,9,FALSE),"-") -> - | X124: =+IFERROR(VLOOKUP(A124,'ID6&7'!A:J,10,FALSE),"-") -> - | Z124: =+IF(J124=0,"Por iniciar",IF(OR(K124="-",M124="-",P124="-",R124="-",T124="-",V124="-"),"Em testes",IF(AND(M124=0,P124=0,R124=0,T124<>K124,V124<>K124),"OK","NOK"))) -> Por iniciar
A125: =+H125&I125&$I$8 -> INSTRUMENTCRRNCY_DNMNTN45596 | H125: INSTRUMENT | I125: CRRNCY_DNMNTN | J125: =+COUNTIF('ID1&5'!G:G,'1. Status'!I125) -> 0 | K125: =+IFERROR(VLOOKUP(CONCATENATE(A125,$B$10,B125),'ID1&5'!B:J,8,FALSE),"-") -> - | L125: =+IFERROR(VLOOKUP(B125,'ID1&5'!K:L,2,FALSE),"-") -> - | M125: =+IFERROR(VLOOKUP(CONCATENATE(A125,$B$10,B125),'ID1&5'!B:J,9,FALSE),"-") -> - | N125: =+IFERROR(VLOOKUP(CONCATENATE(A125,$C$10,C125),'ID1&5'!B:J,8,FALSE),"-") -> - | O125: =+IFERROR(VLOOKUP(C125,'ID1&5'!K:L,2,FALSE),"-") -> - | P125: =+IFERROR(VLOOKUP(CONCATENATE(A125,$C$10,C125),'ID1&5'!B:J,9,FALSE),"-") -> - | Q125: =+IFERROR(VLOOKUP(D125,'ID1&5'!K:L,2,FALSE),"-") -> - | R125: =+IFERROR(VLOOKUP(CONCATENATE(A125,$D$10,D125),'ID1&5'!B:J,9,FALSE),"-") -> - | S125: =+IFERROR(VLOOKUP(E125,'ID1&5'!K:L,2,FALSE),"-") -> - | T125: =+IFERROR(VLOOKUP(CONCATENATE(A125,$E$10,E125),'ID1&5'!B:J,9,FALSE),"-") -> - | U125: =+IFERROR(VLOOKUP(F125,'ID1&5'!K:L,2,FALSE),"-") -> - | V125: =+IFERROR(VLOOKUP(CONCATENATE(A125,$F$10,F125),'ID1&5'!B:J,9,FALSE),"-") -> - | W125: =+IFERROR(VLOOKUP(A125,'ID6&7'!A:I,9,FALSE),"-") -> - | X125: =+IFERROR(VLOOKUP(A125,'ID6&7'!A:J,10,FALSE),"-") -> - | Z125: =+IF(J125=0,"Por iniciar",IF(OR(K125="-",M125="-",P125="-",R125="-",T125="-",V125="-"),"Em testes",IF(AND(M125=0,P125=0,R125=0,T125<>K125,V125<>K125),"OK","NOK"))) -> Por iniciar
A126: =+H126&I126&$I$8 -> INSTRUMENTDT_INCPTN45596 | H126: INSTRUMENT | I126: DT_INCPTN | J126: =+COUNTIF('ID1&5'!G:G,'1. Status'!I126) -> 0 | K126: =+IFERROR(VLOOKUP(CONCATENATE(A126,$B$10,B126),'ID1&5'!B:J,8,FALSE),"-") -> - | L126: =+IFERROR(VLOOKUP(B126,'ID1&5'!K:L,2,FALSE),"-") -> - | M126: =+IFERROR(VLOOKUP(CONCATENATE(A126,$B$10,B126),'ID1&5'!B:J,9,FALSE),"-") -> - | N126: =+IFERROR(VLOOKUP(CONCATENATE(A126,$C$10,C126),'ID1&5'!B:J,8,FALSE),"-") -> - | O126: =+IFERROR(VLOOKUP(C126,'ID1&5'!K:L,2,FALSE),"-") -> - | P126: =+IFERROR(VLOOKUP(CONCATENATE(A126,$C$10,C126),'ID1&5'!B:J,9,FALSE),"-") -> - | Q126: =+IFERROR(VLOOKUP(D126,'ID1&5'!K:L,2,FALSE),"-") -> - | R126: =+IFERROR(VLOOKUP(CONCATENATE(A126,$D$10,D126),'ID1&5'!B:J,9,FALSE),"-") -> - | S126: =+IFERROR(VLOOKUP(E126,'ID1&5'!K:L,2,FALSE),"-") -> - | T126: =+IFERROR(VLOOKUP(CONCATENATE(A126,$E$10,E126),'ID1&5'!B:J,9,FALSE),"-") -> - | U126: =+IFERROR(VLOOKUP(F126,'ID1&5'!K:L,2,FALSE),"-") -> - | V126: =+IFERROR(VLOOKUP(CONCATENATE(A126,$F$10,F126),'ID1&5'!B:J,9,FALSE),"-") -> - | W126: =+IFERROR(VLOOKUP(A126,'ID6&7'!A:I,9,FALSE),"-") -> - | X126: =+IFERROR(VLOOKUP(A126,'ID6&7'!A:J,10,FALSE),"-") -> - | Z126: =+IF(J126=0,"Por iniciar",IF(OR(K126="-",M126="-",P126="-",R126="-",T126="-",V126="-"),"Em testes",IF(AND(M126=0,P126=0,R126=0,T126<>K126,V126<>K126),"OK","NOK"))) -> Por iniciar
A127: =+H127&I127&$I$8 -> INSTRUMENTOBSRVD_AGNT_ID45596 | H127: INSTRUMENT | I127: OBSRVD_AGNT_ID | J127: =+COUNTIF('ID1&5'!G:G,'1. Status'!I127) -> 0 | K127: =+IFERROR(VLOOKUP(CONCATENATE(A127,$B$10,B127),'ID1&5'!B:J,8,FALSE),"-") -> - | L127: =+IFERROR(VLOOKUP(B127,'ID1&5'!K:L,2,FALSE),"-") -> - | M127: =+IFERROR(VLOOKUP(CONCATENATE(A127,$B$10,B127),'ID1&5'!B:J,9,FALSE),"-") -> - | N127: =+IFERROR(VLOOKUP(CONCATENATE(A127,$C$10,C127),'ID1&5'!B:J,8,FALSE),"-") -> - | O127: =+IFERROR(VLOOKUP(C127,'ID1&5'!K:L,2,FALSE),"-") -> - | P127: =+IFERROR(VLOOKUP(CONCATENATE(A127,$C$10,C127),'ID1&5'!B:J,9,FALSE),"-") -> - | Q127: =+IFERROR(VLOOKUP(D127,'ID1&5'!K:L,2,FALSE),"-") -> - | R127: =+IFERROR(VLOOKUP(CONCATENATE(A127,$D$10,D127),'ID1&5'!B:J,9,FALSE),"-") -> - | S127: =+IFERROR(VLOOKUP(E127,'ID1&5'!K:L,2,FALSE),"-") -> - | T127: =+IFERROR(VLOOKUP(CONCATENATE(A127,$E$10,E127),'ID1&5'!B:J,9,FALSE),"-") -> - | U127: =+IFERROR(VLOOKUP(F127,'ID1&5'!K:L,2,FALSE),"-") -> - | V127: =+IFERROR(VLOOKUP(CONCATENATE(A127,$F$10,F127),'ID1&5'!B:J,9,FALSE),"-") -> - | W127: =+IFERROR(VLOOKUP(A127,'ID6&7'!A:I,9,FALSE),"-") -> - | X127: =+IFERROR(VLOOKUP(A127,'ID6&7'!A:J,10,FALSE),"-") -> - | Z127: =+IF(J127=0,"Por iniciar",IF(OR(K127="-",M127="-",P127="-",R127="-",T127="-",V127="-"),"Em testes",IF(AND(M127=0,P127=0,R127=0,T127<>K127,V127<>K127),"OK","NOK"))) -> Por iniciar
A128: =+H128&I128&$I$8 -> INSTRUMENTOBSRVD_AGNT_NM45596 | H128: INSTRUMENT | I128: OBSRVD_AGNT_NM | J128: =+COUNTIF('ID1&5'!G:G,'1. Status'!I128) -> 0 | K128: =+IFERROR(VLOOKUP(CONCATENATE(A128,$B$10,B128),'ID1&5'!B:J,8,FALSE),"-") -> - | L128: =+IFERROR(VLOOKUP(B128,'ID1&5'!K:L,2,FALSE),"-") -> - | M128: =+IFERROR(VLOOKUP(CONCATENATE(A128,$B$10,B128),'ID1&5'!B:J,9,FALSE),"-") -> - | N128: =+IFERROR(VLOOKUP(CONCATENATE(A128,$C$10,C128),'ID1&5'!B:J,8,FALSE),"-") -> - | O128: =+IFERROR(VLOOKUP(C128,'ID1&5'!K:L,2,FALSE),"-") -> - | P128: =+IFERROR(VLOOKUP(CONCATENATE(A128,$C$10,C128),'ID1&5'!B:J,9,FALSE),"-") -> - | Q128: =+IFERROR(VLOOKUP(D128,'ID1&5'!K:L,2,FALSE),"-") -> - | R128: =+IFERROR(VLOOKUP(CONCATENATE(A128,$D$10,D128),'ID1&5'!B:J,9,FALSE),"-") -> - | S128: =+IFERROR(VLOOKUP(E128,'ID1&5'!K:L,2,FALSE),"-") -> - | T128: =+IFERROR(VLOOKUP(CONCATENATE(A128,$E$10,E128),'ID1&5'!B:J,9,FALSE),"-") -> - | U128: =+IFERROR(VLOOKUP(F128,'ID1&5'!K:L,2,FALSE),"-") -> - | V128: =+IFERROR(VLOOKUP(CONCATENATE(A128,$F$10,F128),'ID1&5'!B:J,9,FALSE),"-") -> - | W128: =+IFERROR(VLOOKUP(A128,'ID6&7'!A:I,9,FALSE),"-") -> - | X128: =+IFERROR(VLOOKUP(A128,'ID6&7'!A:J,10,FALSE),"-") -> - | Z128: =+IF(J128=0,"Por iniciar",IF(OR(K128="-",M128="-",P128="-",R128="-",T128="-",V128="-"),"Em testes",IF(AND(M128=0,P128=0,R128=0,T128<>K128,V128<>K128),"OK","NOK"))) -> Por iniciar
A129: =+H129&I129&$I$8 -> INSTRUMENTPRDCT45596 | H129: INSTRUMENT | I129: PRDCT | J129: =+COUNTIF('ID1&5'!G:G,'1. Status'!I129) -> 0 | K129: =+IFERROR(VLOOKUP(CONCATENATE(A129,$B$10,B129),'ID1&5'!B:J,8,FALSE),"-") -> - | L129: =+IFERROR(VLOOKUP(B129,'ID1&5'!K:L,2,FALSE),"-") -> - | M129: =+IFERROR(VLOOKUP(CONCATENATE(A129,$B$10,B129),'ID1&5'!B:J,9,FALSE),"-") -> - | N129: =+IFERROR(VLOOKUP(CONCATENATE(A129,$C$10,C129),'ID1&5'!B:J,8,FALSE),"-") -> - | O129: =+IFERROR(VLOOKUP(C129,'ID1&5'!K:L,2,FALSE),"-") -> - | P129: =+IFERROR(VLOOKUP(CONCATENATE(A129,$C$10,C129),'ID1&5'!B:J,9,FALSE),"-") -> - | Q129: =+IFERROR(VLOOKUP(D129,'ID1&5'!K:L,2,FALSE),"-") -> - | R129: =+IFERROR(VLOOKUP(CONCATENATE(A129,$D$10,D129),'ID1&5'!B:J,9,FALSE),"-") -> - | S129: =+IFERROR(VLOOKUP(E129,'ID1&5'!K:L,2,FALSE),"-") -> - | T129: =+IFERROR(VLOOKUP(CONCATENATE(A129,$E$10,E129),'ID1&5'!B:J,9,FALSE),"-") -> - | U129: =+IFERROR(VLOOKUP(F129,'ID1&5'!K:L,2,FALSE),"-") -> - | V129: =+IFERROR(VLOOKUP(CONCATENATE(A129,$F$10,F129),'ID1&5'!B:J,9,FALSE),"-") -> - | W129: =+IFERROR(VLOOKUP(A129,'ID6&7'!A:I,9,FALSE),"-") -> - | X129: =+IFERROR(VLOOKUP(A129,'ID6&7'!A:J,10,FALSE),"-") -> - | Z129: =+IF(J129=0,"Por iniciar",IF(OR(K129="-",M129="-",P129="-",R129="-",T129="-",V129="-"),"Em testes",IF(AND(M129=0,P129=0,R129=0,T129<>K129,V129<>K129),"OK","NOK"))) -> Por iniciar
A130: =+H130&I130&$I$8 -> INSTRUMENTBRCHD_CVNNTS45596 | H130: INSTRUMENT | I130: BRCHD_CVNNTS | J130: =+COUNTIF('ID1&5'!G:G,'1. Status'!I130) -> 0 | K130: =+IFERROR(VLOOKUP(CONCATENATE(A130,$B$10,B130),'ID1&5'!B:J,8,FALSE),"-") -> - | L130: =+IFERROR(VLOOKUP(B130,'ID1&5'!K:L,2,FALSE),"-") -> - | M130: =+IFERROR(VLOOKUP(CONCATENATE(A130,$B$10,B130),'ID1&5'!B:J,9,FALSE),"-") -> - | N130: =+IFERROR(VLOOKUP(CONCATENATE(A130,$C$10,C130),'ID1&5'!B:J,8,FALSE),"-") -> - | O130: =+IFERROR(VLOOKUP(C130,'ID1&5'!K:L,2,FALSE),"-") -> - | P130: =+IFERROR(VLOOKUP(CONCATENATE(A130,$C$10,C130),'ID1&5'!B:J,9,FALSE),"-") -> - | Q130: =+IFERROR(VLOOKUP(D130,'ID1&5'!K:L,2,FALSE),"-") -> - | R130: =+IFERROR(VLOOKUP(CONCATENATE(A130,$D$10,D130),'ID1&5'!B:J,9,FALSE),"-") -> - | S130: =+IFERROR(VLOOKUP(E130,'ID1&5'!K:L,2,FALSE),"-") -> - | T130: =+IFERROR(VLOOKUP(CONCATENATE(A130,$E$10,E130),'ID1&5'!B:J,9,FALSE),"-") -> - | U130: =+IFERROR(VLOOKUP(F130,'ID1&5'!K:L,2,FALSE),"-") -> - | V130: =+IFERROR(VLOOKUP(CONCATENATE(A130,$F$10,F130),'ID1&5'!B:J,9,FALSE),"-") -> - | W130: =+IFERROR(VLOOKUP(A130,'ID6&7'!A:I,9,FALSE),"-") -> - | X130: =+IFERROR(VLOOKUP(A130,'ID6&7'!A:J,10,FALSE),"-") -> - | Z130: =+IF(J130=0,"Por iniciar",IF(OR(K130="-",M130="-",P130="-",R130="-",T130="-",V130="-"),"Em testes",IF(AND(M130=0,P130=0,R130=0,T130<>K130,V130<>K130),"OK","NOK"))) -> Por iniciar
A131: =+H131&I131&$I$8 -> INSTRUMENTCHNNL_ORGNTN45596 | H131: INSTRUMENT | I131: CHNNL_ORGNTN | J131: =+COUNTIF('ID1&5'!G:G,'1. Status'!I131) -> 0 | K131: =+IFERROR(VLOOKUP(CONCATENATE(A131,$B$10,B131),'ID1&5'!B:J,8,FALSE),"-") -> - | L131: =+IFERROR(VLOOKUP(B131,'ID1&5'!K:L,2,FALSE),"-") -> - | M131: =+IFERROR(VLOOKUP(CONCATENATE(A131,$B$10,B131),'ID1&5'!B:J,9,FALSE),"-") -> - | N131: =+IFERROR(VLOOKUP(CONCATENATE(A131,$C$10,C131),'ID1&5'!B:J,8,FALSE),"-") -> - | O131: =+IFERROR(VLOOKUP(C131,'ID1&5'!K:L,2,FALSE),"-") -> - | P131: =+IFERROR(VLOOKUP(CONCATENATE(A131,$C$10,C131),'ID1&5'!B:J,9,FALSE),"-") -> - | Q131: =+IFERROR(VLOOKUP(D131,'ID1&5'!K:L,2,FALSE),"-") -> - | R131: =+IFERROR(VLOOKUP(CONCATENATE(A131,$D$10,D131),'ID1&5'!B:J,9,FALSE),"-") -> - | S131: =+IFERROR(VLOOKUP(E131,'ID1&5'!K:L,2,FALSE),"-") -> - | T131: =+IFERROR(VLOOKUP(CONCATENATE(A131,$E$10,E131),'ID1&5'!B:J,9,FALSE),"-") -> - | U131: =+IFERROR(VLOOKUP(F131,'ID1&5'!K:L,2,FALSE),"-") -> - | V131: =+IFERROR(VLOOKUP(CONCATENATE(A131,$F$10,F131),'ID1&5'!B:J,9,FALSE),"-") -> - | W131: =+IFERROR(VLOOKUP(A131,'ID6&7'!A:I,9,FALSE),"-") -> - | X131: =+IFERROR(VLOOKUP(A131,'ID6&7'!A:J,10,FALSE),"-") -> - | Z131: =+IF(J131=0,"Por iniciar",IF(OR(K131="-",M131="-",P131="-",R131="-",T131="-",V131="-"),"Em testes",IF(AND(M131=0,P131=0,R131=0,T131<>K131,V131<>K131),"OK","NOK"))) -> Por iniciar
... A311: =+H311&I311&$I$8 -> INSTRUMENTLTI_INSTRMNT45596 | H311: INSTRUMENT | I311: LTI_INSTRMNT | J311: =+COUNTIF('ID1&5'!G:G,'1. Status'!I311) -> 0 | K311: =+IFERROR(VLOOKUP(CONCATENATE(A311,$B$10,B311),'ID1&5'!B:J,8,FALSE),"-") -> - | L311: =+IFERROR(VLOOKUP(B311,'ID1&5'!K:L,2,FALSE),"-") -> - | M311: =+IFERROR(VLOOKUP(CONCATENATE(A311,$B$10,B311),'ID1&5'!B:J,9,FALSE),"-") -> - | N311: =+IFERROR(VLOOKUP(CONCATENATE(A311,$C$10,C311),'ID1&5'!B:J,8,FALSE),"-") -> - | O311: =+IFERROR(VLOOKUP(C311,'ID1&5'!K:L,2,FALSE),"-") -> - | P311: =+IFERROR(VLOOKUP(CONCATENATE(A311,$C$10,C311),'ID1&5'!B:J,9,FALSE),"-") -> - | Q311: =+IFERROR(VLOOKUP(D311,'ID1&5'!K:L,2,FALSE),"-") -> - | R311: =+IFERROR(VLOOKUP(CONCATENATE(A311,$D$10,D311),'ID1&5'!B:J,9,FALSE),"-") -> - | S311: =+IFERROR(VLOOKUP(E311,'ID1&5'!K:L,2,FALSE),"-") -> - | T311: =+IFERROR(VLOOKUP(CONCATENATE(A311,$E$10,E311),'ID1&5'!B:J,9,FALSE),"-") -> - | U311: =+IFERROR(VLOOKUP(F311,'ID1&5'!K:L,2,FALSE),"-") -> - | V311: =+IFERROR(VLOOKUP(CONCATENATE(A311,$F$10,F311),'ID1&5'!B:J,9,FALSE),"-") -> - | W311: =+IFERROR(VLOOKUP(A311,'ID6&7'!A:I,9,FALSE),"-") -> - | X311: =+IFERROR(VLOOKUP(A311,'ID6&7'!A:J,10,FALSE),"-") -> - | Z311: =+IF(J311=0,"Por iniciar",IF(OR(K311="-",M311="-",P311="-",R311="-",T311="-",V311="-"),"Em testes",IF(AND(M311=0,P311=0,R311=0,T311<>K311,V311<>K311),"OK","NOK"))) -> Por iniciar
A312: =+H312&I312&$I$8 -> INSTRUMENTCPN_RT45596 | H312: INSTRUMENT | I312: CPN_RT | J312: =+COUNTIF('ID1&5'!G:G,'1. Status'!I312) -> 0 | K312: =+IFERROR(VLOOKUP(CONCATENATE(A312,$B$10,B312),'ID1&5'!B:J,8,FALSE),"-") -> - | L312: =+IFERROR(VLOOKUP(B312,'ID1&5'!K:L,2,FALSE),"-") -> - | M312: =+IFERROR(VLOOKUP(CONCATENATE(A312,$B$10,B312),'ID1&5'!B:J,9,FALSE),"-") -> - | N312: =+IFERROR(VLOOKUP(CONCATENATE(A312,$C$10,C312),'ID1&5'!B:J,8,FALSE),"-") -> - | O312: =+IFERROR(VLOOKUP(C312,'ID1&5'!K:L,2,FALSE),"-") -> - | P312: =+IFERROR(VLOOKUP(CONCATENATE(A312,$C$10,C312),'ID1&5'!B:J,9,FALSE),"-") -> - | Q312: =+IFERROR(VLOOKUP(D312,'ID1&5'!K:L,2,FALSE),"-") -> - | R312: =+IFERROR(VLOOKUP(CONCATENATE(A312,$D$10,D312),'ID1&5'!B:J,9,FALSE),"-") -> - | S312: =+IFERROR(VLOOKUP(E312,'ID1&5'!K:L,2,FALSE),"-") -> - | T312: =+IFERROR(VLOOKUP(CONCATENATE(A312,$E$10,E312),'ID1&5'!B:J,9,FALSE),"-") -> - | U312: =+IFERROR(VLOOKUP(F312,'ID1&5'!K:L,2,FALSE),"-") -> - | V312: =+IFERROR(VLOOKUP(CONCATENATE(A312,$F$10,F312),'ID1&5'!B:J,9,FALSE),"-") -> - | W312: =+IFERROR(VLOOKUP(A312,'ID6&7'!A:I,9,FALSE),"-") -> - | X312: =+IFERROR(VLOOKUP(A312,'ID6&7'!A:J,10,FALSE),"-") -> - | Y312: 17/02: Este campo não estava no ficheiro da Corporação. No entanto, estava no ficheiro do GF | Z312: =+IF(J312=0,"Por iniciar",IF(OR(K312="-",M312="-",P312="-",R312="-",T312="-",V312="-"),"Em testes",IF(AND(M312=0,P312=0,R312=0,T312<>K312,V312<>K312),"OK","NOK"))) -> Por iniciar
A313: =+H313&I313&$I$8 -> INSTRUMENTRFRNC_RT45596 | H313: INSTRUMENT | I313: RFRNC_RT | J313: =+COUNTIF('ID1&5'!G:G,'1. Status'!I313) -> 0 | K313: =+IFERROR(VLOOKUP(CONCATENATE(A313,$B$10,B313),'ID1&5'!B:J,8,FALSE),"-") -> - | L313: =+IFERROR(VLOOKUP(B313,'ID1&5'!K:L,2,FALSE),"-") -> - | M313: =+IFERROR(VLOOKUP(CONCATENATE(A313,$B$10,B313),'ID1&5'!B:J,9,FALSE),"-") -> - | N313: =+IFERROR(VLOOKUP(CONCATENATE(A313,$C$10,C313),'ID1&5'!B:J,8,FALSE),"-") -> - | O313: =+IFERROR(VLOOKUP(C313,'ID1&5'!K:L,2,FALSE),"-") -> - | P313: =+IFERROR(VLOOKUP(CONCATENATE(A313,$C$10,C313),'ID1&5'!B:J,9,FALSE),"-") -> - | Q313: =+IFERROR(VLOOKUP(D313,'ID1&5'!K:L,2,FALSE),"-") -> - | R313: =+IFERROR(VLOOKUP(CONCATENATE(A313,$D$10,D313),'ID1&5'!B:J,9,FALSE),"-") -> - | S313: =+IFERROR(VLOOKUP(E313,'ID1&5'!K:L,2,FALSE),"-") -> - | T313: =+IFERROR(VLOOKUP(CONCATENATE(A313,$E$10,E313),'ID1&5'!B:J,9,FALSE),"-") -> - | U313: =+IFERROR(VLOOKUP(F313,'ID1&5'!K:L,2,FALSE),"-") -> - | V313: =+IFERROR(VLOOKUP(CONCATENATE(A313,$F$10,F313),'ID1&5'!B:J,9,FALSE),"-") -> - | W313: =+IFERROR(VLOOKUP(A313,'ID6&7'!A:I,9,FALSE),"-") -> - | X313: =+IFERROR(VLOOKUP(A313,'ID6&7'!A:J,10,FALSE),"-") -> - | Z313: =+IF(J313=0,"Por iniciar",IF(OR(K313="-",M313="-",P313="-",R313="-",T313="-",V313="-"),"Em testes",IF(AND(M313=0,P313=0,R313=0,T313<>K313,V313<>K313),"OK","NOK"))) -> Por iniciar
A314: =+H314&I314&$I$8 -> INSTRUMENTCPN_RT_FXD45596 | B314: {=+MAX(IF('ID1&5'!A:A='1. Status'!A314&'1. Status'!$B$10,'ID1&5'!K:K))} -> 0 | C314: {=+MAX(IF('ID1&5'!A:A='1. Status'!A314&'1. Status'!$C$10,'ID1&5'!K:K))} -> 0 | D314: {=+MAX(IF('ID1&5'!A:A='1. Status'!A314&'1. Status'!$D$10,'ID1&5'!K:K))} -> 0 | E314: {=+MAX(IF('ID1&5'!A:A='1. Status'!A314&'1. Status'!$E$10,'ID1&5'!K:K))} -> 0 | F314: {=+MAX(IF('ID1&5'!A:A='1. Status'!A314&'1. Status'!$F$10,'ID1&5'!K:K))} -> 0 | H314: INSTRUMENT | I314: CPN_RT_FXD | J314: =+COUNTIF('ID1&5'!G:G,'1. Status'!I314) -> 0 | K314: =+IFERROR(VLOOKUP(CONCATENATE(A314,$B$10,B314),'ID1&5'!B:J,8,FALSE),"-") -> - | L314: =+IFERROR(VLOOKUP(B314,'ID1&5'!K:L,2,FALSE),"-") -> - | M314: =+IFERROR(VLOOKUP(CONCATENATE(A314,$B$10,B314),'ID1&5'!B:J,9,FALSE),"-") -> - | N314: =+IFERROR(VLOOKUP(CONCATENATE(A314,$C$10,C314),'ID1&5'!B:J,8,FALSE),"-") -> - | O314: =+IFERROR(VLOOKUP(C314,'ID1&5'!K:L,2,FALSE),"-") -> - | P314: =+IFERROR(VLOOKUP(CONCATENATE(A314,$C$10,C314),'ID1&5'!B:J,9,FALSE),"-") -> - | Q314: =+IFERROR(VLOOKUP(D314,'ID1&5'!K:L,2,FALSE),"-") -> - | R314: =+IFERROR(VLOOKUP(CONCATENATE(A314,$D$10,D314),'ID1&5'!B:J,9,FALSE),"-") -> - | S314: =+IFERROR(VLOOKUP(E314,'ID1&5'!K:L,2,FALSE),"-") -> - | T314: =+IFERROR(VLOOKUP(CONCATENATE(A314,$E$10,E314),'ID1&5'!B:J,9,FALSE),"-") -> - | U314: =+IFERROR(VLOOKUP(F314,'ID1&5'!K:L,2,FALSE),"-") -> - | V314: =+IFERROR(VLOOKUP(CONCATENATE(A314,$F$10,F314),'ID1&5'!B:J,9,FALSE),"-") -> - | W314: =+IFERROR(VLOOKUP(A314,'ID6&7'!A:I,9,FALSE),"-") -> - | X314: =+IFERROR(VLOOKUP(A314,'ID6&7'!A:J,10,FALSE),"-") -> - | Z314: =+IF(J314=0,"Por iniciar",IF(OR(K314="-",M314="-",P314="-",R314="-",T314="-",V314="-"),"Em testes",IF(AND(M314=0,P314=0,R314=0,T314<>K314,V314<>K314),"OK","NOK"))) -> Por iniciar
A315: =+H315&I315&$I$8 -> INSTRUMENTCPN_RT_FLTNG45596 | B315: {=+MAX(IF('ID1&5'!A:A='1. Status'!A315&'1. Status'!$B$10,'ID1&5'!K:K))} -> 0 | C315: {=+MAX(IF('ID1&5'!A:A='1. Status'!A315&'1. Status'!$C$10,'ID1&5'!K:K))} -> 0 | D315: {=+MAX(IF('ID1&5'!A:A='1. Status'!A315&'1. Status'!$D$10,'ID1&5'!K:K))} -> 0 | E315: {=+MAX(IF('ID1&5'!A:A='1. Status'!A315&'1. Status'!$E$10,'ID1&5'!K:K))} -> 0 | F315: {=+MAX(IF('ID1&5'!A:A='1. Status'!A315&'1. Status'!$F$10,'ID1&5'!K:K))} -> 0 | H315: INSTRUMENT | I315: CPN_RT_FLTNG | J315: =+COUNTIF('ID1&5'!G:G,'1. Status'!I315) -> 0 | K315: =+IFERROR(VLOOKUP(CONCATENATE(A315,$B$10,B315),'ID1&5'!B:J,8,FALSE),"-") -> - | L315: =+IFERROR(VLOOKUP(B315,'ID1&5'!K:L,2,FALSE),"-") -> - | M315: =+IFERROR(VLOOKUP(CONCATENATE(A315,$B$10,B315),'ID1&5'!B:J,9,FALSE),"-") -> - | N315: =+IFERROR(VLOOKUP(CONCATENATE(A315,$C$10,C315),'ID1&5'!B:J,8,FALSE),"-") -> - | O315: =+IFERROR(VLOOKUP(C315,'ID1&5'!K:L,2,FALSE),"-") -> - | P315: =+IFERROR(VLOOKUP(CONCATENATE(A315,$C$10,C315),'ID1&5'!B:J,9,FALSE),"-") -> - | Q315: =+IFERROR(VLOOKUP(D315,'ID1&5'!K:L,2,FALSE),"-") -> - | R315: =+IFERROR(VLOOKUP(CONCATENATE(A315,$D$10,D315),'ID1&5'!B:J,9,FALSE),"-") -> - | S315: =+IFERROR(VLOOKUP(E315,'ID1&5'!K:L,2,FALSE),"-") -> - | T315: =+IFERROR(VLOOKUP(CONCATENATE(A315,$E$10,E315),'ID1&5'!B:J,9,FALSE),"-") -> - | U315: =+IFERROR(VLOOKUP(F315,'ID1&5'!K:L,2,FALSE),"-") -> - | V315: =+IFERROR(VLOOKUP(CONCATENATE(A315,$F$10,F315),'ID1&5'!B:J,9,FALSE),"-") -> - | W315: =+IFERROR(VLOOKUP(A315,'ID6&7'!A:I,9,FALSE),"-") -> - | X315: =+IFERROR(VLOOKUP(A315,'ID6&7'!A:J,10,FALSE),"-") -> - | Z315: =+IF(J315=0,"Por iniciar",IF(OR(K315="-",M315="-",P315="-",R315="-",T315="-",V315="-"),"Em testes",IF(AND(M315=0,P315=0,R315=0,T315<>K315,V315<>K315),"OK","NOK"))) -> Por iniciar
A316: =+H316&I316&$I$8 -> INSTRUMENTINTRST_RT_CP45596 | B316: {=+MAX(IF('ID1&5'!A:A='1. Status'!A316&'1. Status'!$B$10,'ID1&5'!K:K))} -> 0 | C316: {=+MAX(IF('ID1&5'!A:A='1. Status'!A316&'1. Status'!$C$10,'ID1&5'!K:K))} -> 0 | D316: {=+MAX(IF('ID1&5'!A:A='1. Status'!A316&'1. Status'!$D$10,'ID1&5'!K:K))} -> 0 | E316: {=+MAX(IF('ID1&5'!A:A='1. Status'!A316&'1. Status'!$E$10,'ID1&5'!K:K))} -> 0 | F316: {=+MAX(IF('ID1&5'!A:A='1. Status'!A316&'1. Status'!$F$10,'ID1&5'!K:K))} -> 0 | H316: INSTRUMENT | I316: INTRST_RT_CP | J316: =+COUNTIF('ID1&5'!G:G,'1. Status'!I316) -> 0 | K316: =+IFERROR(VLOOKUP(CONCATENATE(A316,$B$10,B316),'ID1&5'!B:J,8,FALSE),"-") -> - | L316: =+IFERROR(VLOOKUP(B316,'ID1&5'!K:L,2,FALSE),"-") -> - | M316: =+IFERROR(VLOOKUP(CONCATENATE(A316,$B$10,B316),'ID1&5'!B:J,9,FALSE),"-") -> - | N316: =+IFERROR(VLOOKUP(CONCATENATE(A316,$C$10,C316),'ID1&5'!B:J,8,FALSE),"-") -> - | O316: =+IFERROR(VLOOKUP(C316,'ID1&5'!K:L,2,FALSE),"-") -> - | P316: =+IFERROR(VLOOKUP(CONCATENATE(A316,$C$10,C316),'ID1&5'!B:J,9,FALSE),"-") -> - | Q316: =+IFERROR(VLOOKUP(D316,'ID1&5'!K:L,2,FALSE),"-") -> - | R316: =+IFERROR(VLOOKUP(CONCATENATE(A316,$D$10,D316),'ID1&5'!B:J,9,FALSE),"-") -> - | S316: =+IFERROR(VLOOKUP(E316,'ID1&5'!K:L,2,FALSE),"-") -> - | T316: =+IFERROR(VLOOKUP(CONCATENATE(A316,$E$10,E316),'ID1&5'!B:J,9,FALSE),"-") -> - | U316: =+IFERROR(VLOOKUP(F316,'ID1&5'!K:L,2,FALSE),"-") -> - | V316: =+IFERROR(VLOOKUP(CONCATENATE(A316,$F$10,F316),'ID1&5'!B:J,9,FALSE),"-") -> - | W316: =+IFERROR(VLOOKUP(A316,'ID6&7'!A:I,9,FALSE),"-") -> - | X316: =+IFERROR(VLOOKUP(A316,'ID6&7'!A:J,10,FALSE),"-") -> - | Z316: =+IF(J316=0,"Por iniciar",IF(OR(K316="-",M316="-",P316="-",R316="-",T316="-",V316="-"),"Em testes",IF(AND(M316=0,P316=0,R316=0,T316<>K316,V316<>K316),"OK","NOK"))) -> Por iniciar
A317: =+H317&I317&$I$8 -> INSTRUMENTINTRST_RT_FLR45596 | B317: {=+MAX(IF('ID1&5'!A:A='1. Status'!A317&'1. Status'!$B$10,'ID1&5'!K:K))} -> 0 | C317: {=+MAX(IF('ID1&5'!A:A='1. Status'!A317&'1. Status'!$C$10,'ID1&5'!K:K))} -> 0 | D317: {=+MAX(IF('ID1&5'!A:A='1. Status'!A317&'1. Status'!$D$10,'ID1&5'!K:K))} -> 0 | E317: {=+MAX(IF('ID1&5'!A:A='1. Status'!A317&'1. Status'!$E$10,'ID1&5'!K:K))} -> 0 | F317: {=+MAX(IF('ID1&5'!A:A='1. Status'!A317&'1. Status'!$F$10,'ID1&5'!K:K))} -> 0 | H317: INSTRUMENT | I317: INTRST_RT_FLR | J317: =+COUNTIF('ID1&5'!G:G,'1. Status'!I317) -> 0 | K317: =+IFERROR(VLOOKUP(CONCATENATE(A317,$B$10,B317),'ID1&5'!B:J,8,FALSE),"-") -> - | L317: =+IFERROR(VLOOKUP(B317,'ID1&5'!K:L,2,FALSE),"-") -> - | M317: =+IFERROR(VLOOKUP(CONCATENATE(A317,$B$10,B317),'ID1&5'!B:J,9,FALSE),"-") -> - | N317: =+IFERROR(VLOOKUP(CONCATENATE(A317,$C$10,C317),'ID1&5'!B:J,8,FALSE),"-") -> - | O317: =+IFERROR(VLOOKUP(C317,'ID1&5'!K:L,2,FALSE),"-") -> - | P317: =+IFERROR(VLOOKUP(CONCATENATE(A317,$C$10,C317),'ID1&5'!B:J,9,FALSE),"-") -> - | Q317: =+IFERROR(VLOOKUP(D317,'ID1&5'!K:L,2,FALSE),"-") -> - | R317: =+IFERROR(VLOOKUP(CONCATENATE(A317,$D$10,D317),'ID1&5'!B:J,9,FALSE),"-") -> - | S317: =+IFERROR(VLOOKUP(E317,'ID1&5'!K:L,2,FALSE),"-") -> - | T317: =+IFERROR(VLOOKUP(CONCATENATE(A317,$E$10,E317),'ID1&5'!B:J,9,FALSE),"-") -> - | U317: =+IFERROR(VLOOKUP(F317,'ID1&5'!K:L,2,FALSE),"-") -> - | V317: =+IFERROR(VLOOKUP(CONCATENATE(A317,$F$10,F317),'ID1&5'!B:J,9,FALSE),"-") -> - | W317: =+IFERROR(VLOOKUP(A317,'ID6&7'!A:I,9,FALSE),"-") -> - | X317: =+IFERROR(VLOOKUP(A317,'ID6&7'!A:J,10,FALSE),"-") -> - | Z317: =+IF(J317=0,"Por iniciar",IF(OR(K317="-",M317="-",P317="-",R317="-",T317="-",V317="-"),"Em testes",IF(AND(M317=0,P317=0,R317=0,T317<>K317,V317<>K317),"OK","NOK"))) -> Por iniciar
A318: =+H318&I318&$I$8 -> INSTRUMENTNMNL_INTRST_RT_FEE45596 | B318: {=+MAX(IF('ID1&5'!A:A='1. Status'!A318&'1. Status'!$B$10,'ID1&5'!K:K))} -> 0 | C318: {=+MAX(IF('ID1&5'!A:A='1. Status'!A318&'1. Status'!$C$10,'ID1&5'!K:K))} -> 0 | D318: {=+MAX(IF('ID1&5'!A:A='1. Status'!A318&'1. Status'!$D$10,'ID1&5'!K:K))} -> 0 | E318: {=+MAX(IF('ID1&5'!A:A='1. Status'!A318&'1. Status'!$E$10,'ID1&5'!K:K))} -> 0 | F318: {=+MAX(IF('ID1&5'!A:A='1. Status'!A318&'1. Status'!$F$10,'ID1&5'!K:K))} -> 0 | H318: INSTRUMENT | I318: NMNL_INTRST_RT_FEE | J318: =+COUNTIF('ID1&5'!G:G,'1. Status'!I318) -> 0 | K318: =+IFERROR(VLOOKUP(CONCATENATE(A318,$B$10,B318),'ID1&5'!B:J,8,FALSE),"-") -> - | L318: =+IFERROR(VLOOKUP(B318,'ID1&5'!K:L,2,FALSE),"-") -> - | M318: =+IFERROR(VLOOKUP(CONCATENATE(A318,$B$10,B318),'ID1&5'!B:J,9,FALSE),"-") -> - | N318: =+IFERROR(VLOOKUP(CONCATENATE(A318,$C$10,C318),'ID1&5'!B:J,8,FALSE),"-") -> - | O318: =+IFERROR(VLOOKUP(C318,'ID1&5'!K:L,2,FALSE),"-") -> - | P318: =+IFERROR(VLOOKUP(CONCATENATE(A318,$C$10,C318),'ID1&5'!B:J,9,FALSE),"-") -> - | Q318: =+IFERROR(VLOOKUP(D318,'ID1&5'!K:L,2,FALSE),"-") -> - | R318: =+IFERROR(VLOOKUP(CONCATENATE(A318,$D$10,D318),'ID1&5'!B:J,9,FALSE),"-") -> - | S318: =+IFERROR(VLOOKUP(E318,'ID1&5'!K:L,2,FALSE),"-") -> - | T318: =+IFERROR(VLOOKUP(CONCATENATE(A318,$E$10,E318),'ID1&5'!B:J,9,FALSE),"-") -> - | U318: =+IFERROR(VLOOKUP(F318,'ID1&5'!K:L,2,FALSE),"-") -> - | V318: =+IFERROR(VLOOKUP(CONCATENATE(A318,$F$10,F318),'ID1&5'!B:J,9,FALSE),"-") -> - | W318: =+IFERROR(VLOOKUP(A318,'ID6&7'!A:I,9,FALSE),"-") -> - | X318: =+IFERROR(VLOOKUP(A318,'ID6&7'!A:J,10,FALSE),"-") -> - | Z318: =+IF(J318=0,"Por iniciar",IF(OR(K318="-",M318="-",P318="-",R318="-",T318="-",V318="-"),"Em testes",IF(AND(M318=0,P318=0,R318=0,T318<>K318,V318<>K318),"OK","NOK"))) -> Por iniciar
A319: =+H319&I319&$I$8 -> INSTRUMENTDT_STTLMNT45596 | B319: {=+MAX(IF('ID1&5'!A:A='1. Status'!A319&'1. Status'!$B$10,'ID1&5'!K:K))} -> 0 | C319: {=+MAX(IF('ID1&5'!A:A='1. Status'!A319&'1. Status'!$C$10,'ID1&5'!K:K))} -> 0 | D319: {=+MAX(IF('ID1&5'!A:A='1. Status'!A319&'1. Status'!$D$10,'ID1&5'!K:K))} -> 0 | E319: {=+MAX(IF('ID1&5'!A:A='1. Status'!A319&'1. Status'!$E$10,'ID1&5'!K:K))} -> 0 | F319: {=+MAX(IF('ID1&5'!A:A='1. Status'!A319&'1. Status'!$F$10,'ID1&5'!K:K))} -> 0 | H319: INSTRUMENT | I319: DT_STTLMNT | J319: =+COUNTIF('ID1&5'!G:G,'1. Status'!I319) -> 0 | K319: =+IFERROR(VLOOKUP(CONCATENATE(A319,$B$10,B319),'ID1&5'!B:J,8,FALSE),"-") -> - | L319: =+IFERROR(VLOOKUP(B319,'ID1&5'!K:L,2,FALSE),"-") -> - | M319: =+IFERROR(VLOOKUP(CONCATENATE(A319,$B$10,B319),'ID1&5'!B:J,9,FALSE),"-") -> - | N319: =+IFERROR(VLOOKUP(CONCATENATE(A319,$C$10,C319),'ID1&5'!B:J,8,FALSE),"-") -> - | O319: =+IFERROR(VLOOKUP(C319,'ID1&5'!K:L,2,FALSE),"-") -> - | P319: =+IFERROR(VLOOKUP(CONCATENATE(A319,$C$10,C319),'ID1&5'!B:J,9,FALSE),"-") -> - | Q319: =+IFERROR(VLOOKUP(D319,'ID1&5'!K:L,2,FALSE),"-") -> - | R319: =+IFERROR(VLOOKUP(CONCATENATE(A319,$D$10,D319),'ID1&5'!B:J,9,FALSE),"-") -> - | S319: =+IFERROR(VLOOKUP(E319,'ID1&5'!K:L,2,FALSE),"-") -> - | T319: =+IFERROR(VLOOKUP(CONCATENATE(A319,$E$10,E319),'ID1&5'!B:J,9,FALSE),"-") -> - | U319: =+IFERROR(VLOOKUP(F319,'ID1&5'!K:L,2,FALSE),"-") -> - | V319: =+IFERROR(VLOOKUP(CONCATENATE(A319,$F$10,F319),'ID1&5'!B:J,9,FALSE),"-") -> - | W319: =+IFERROR(VLOOKUP(A319,'ID6&7'!A:I,9,FALSE),"-") -> - | X319: =+IFERROR(VLOOKUP(A319,'ID6&7'!A:J,10,FALSE),"-") -> - | Z319: =+IF(J319=0,"Por iniciar",IF(OR(K319="-",M319="-",P319="-",R319="-",T319="-",V319="-"),"Em testes",IF(AND(M319=0,P319=0,R319=0,T319<>K319,V319<>K319),"OK","NOK"))) -> Por iniciar
A320: =+H320&I320&$I$8 -> INSTRUMENTTRNSFRRD_AMNT45596 | B320: {=+MAX(IF('ID1&5'!A:A='1. Status'!A320&'1. Status'!$B$10,'ID1&5'!K:K))} -> 0 | C320: {=+MAX(IF('ID1&5'!A:A='1. Status'!A320&'1. Status'!$C$10,'ID1&5'!K:K))} -> 0 | D320: {=+MAX(IF('ID1&5'!A:A='1. Status'!A320&'1. Status'!$D$10,'ID1&5'!K:K))} -> 0 | E320: {=+MAX(IF('ID1&5'!A:A='1. Status'!A320&'1. Status'!$E$10,'ID1&5'!K:K))} -> 0 | F320: {=+MAX(IF('ID1&5'!A:A='1. Status'!A320&'1. Status'!$F$10,'ID1&5'!K:K))} -> 0 | H320: INSTRUMENT | I320: TRNSFRRD_AMNT | J320: =+COUNTIF('ID1&5'!G:G,'1. Status'!I320) -> 0 | K320: =+IFERROR(VLOOKUP(CONCATENATE(A320,$B$10,B320),'ID1&5'!B:J,8,FALSE),"-") -> - | L320: =+IFERROR(VLOOKUP(B320,'ID1&5'!K:L,2,FALSE),"-") -> - | M320: =+IFERROR(VLOOKUP(CONCATENATE(A320,$B$10,B320),'ID1&5'!B:J,9,FALSE),"-") -> - | N320: =+IFERROR(VLOOKUP(CONCATENATE(A320,$C$10,C320),'ID1&5'!B:J,8,FALSE),"-") -> - | O320: =+IFERROR(VLOOKUP(C320,'ID1&5'!K:L,2,FALSE),"-") -> - | P320: =+IFERROR(VLOOKUP(CONCATENATE(A320,$C$10,C320),'ID1&5'!B:J,9,FALSE),"-") -> - | Q320: =+IFERROR(VLOOKUP(D320,'ID1&5'!K:L,2,FALSE),"-") -> - | R320: =+IFERROR(VLOOKUP(CONCATENATE(A320,$D$10,D320),'ID1&5'!B:J,9,FALSE),"-") -> - | S320: =+IFERROR(VLOOKUP(E320,'ID1&5'!K:L,2,FALSE),"-") -> - | T320: =+IFERROR(VLOOKUP(CONCATENATE(A320,$E$10,E320),'ID1&5'!B:J,9,FALSE),"-") -> - | U320: =+IFERROR(VLOOKUP(F320,'ID1&5'!K:L,2,FALSE),"-") -> - | V320: =+IFERROR(VLOOKUP(CONCATENATE(A320,$F$10,F320),'ID1&5'!B:J,9,FALSE),"-") -> - | W320: =+IFERROR(VLOOKUP(A320,'ID6&7'!A:I,9,FALSE),"-") -> - | X320: =+IFERROR(VLOOKUP(A320,'ID6&7'!A:J,10,FALSE),"-") -> - | Z320: =+IF(J320=0,"Por iniciar",IF(OR(K320="-",M320="-",P320="-",R320="-",T320="-",V320="-"),"Em testes",IF(AND(M320=0,P320=0,R320=0,T320<>K320,V320<>K320),"OK","NOK"))) -> Por iniciar
A321: =+H321&I321&$I$8 -> INSTRUMENTTYP_SCRTZTN45596 | B321: {=+MAX(IF('ID1&5'!A:A='1. Status'!A321&'1. Status'!$B$10,'ID1&5'!K:K))} -> 0 | C321: {=+MAX(IF('ID1&5'!A:A='1. Status'!A321&'1. Status'!$C$10,'ID1&5'!K:K))} -> 0 | D321: {=+MAX(IF('ID1&5'!A:A='1. Status'!A321&'1. Status'!$D$10,'ID1&5'!K:K))} -> 0 | E321: {=+MAX(IF('ID1&5'!A:A='1. Status'!A321&'1. Status'!$E$10,'ID1&5'!K:K))} -> 0 | F321: {=+MAX(IF('ID1&5'!A:A='1. Status'!A321&'1. Status'!$F$10,'ID1&5'!K:K))} -> 0 | H321: INSTRUMENT | I321: TYP_SCRTZTN | J321: =+COUNTIF('ID1&5'!G:G,'1. Status'!I321) -> 0 | K321: =+IFERROR(VLOOKUP(CONCATENATE(A321,$B$10,B321),'ID1&5'!B:J,8,FALSE),"-") -> - | L321: =+IFERROR(VLOOKUP(B321,'ID1&5'!K:L,2,FALSE),"-") -> - | M321: =+IFERROR(VLOOKUP(CONCATENATE(A321,$B$10,B321),'ID1&5'!B:J,9,FALSE),"-") -> - | N321: =+IFERROR(VLOOKUP(CONCATENATE(A321,$C$10,C321),'ID1&5'!B:J,8,FALSE),"-") -> - | O321: =+IFERROR(VLOOKUP(C321,'ID1&5'!K:L,2,FALSE),"-") -> - | P321: =+IFERROR(VLOOKUP(CONCATENATE(A321,$C$10,C321),'ID1&5'!B:J,9,FALSE),"-") -> - | Q321: =+IFERROR(VLOOKUP(D321,'ID1&5'!K:L,2,FALSE),"-") -> - | R321: =+IFERROR(VLOOKUP(CONCATENATE(A321,$D$10,D321),'ID1&5'!B:J,9,FALSE),"-") -> - | S321: =+IFERROR(VLOOKUP(E321,'ID1&5'!K:L,2,FALSE),"-") -> - | T321: =+IFERROR(VLOOKUP(CONCATENATE(A321,$E$10,E321),'ID1&5'!B:J,9,FALSE),"-") -> - | U321: =+IFERROR(VLOOKUP(F321,'ID1&5'!K:L,2,FALSE),"-") -> - | V321: =+IFERROR(VLOOKUP(CONCATENATE(A321,$F$10,F321),'ID1&5'!B:J,9,FALSE),"-") -> - | W321: =+IFERROR(VLOOKUP(A321,'ID6&7'!A:I,9,FALSE),"-") -> - | X321: =+IFERROR(VLOOKUP(A321,'ID6&7'!A:J,10,FALSE),"-") -> - | Z321: =+IF(J321=0,"Por iniciar",IF(OR(K321="-",M321="-",P321="-",R321="-",T321="-",V321="-"),"Em testes",IF(AND(M321=0,P321=0,R321=0,T321<>K321,V321<>K321),"OK","NOK"))) -> Por iniciar
A322: =+H322&I322&$I$8 -> INSTRUMENTTYP_OFF_BLNC_PRDCT45596 | B322: {=+MAX(IF('ID1&5'!A:A='1. Status'!A322&'1. Status'!$B$10,'ID1&5'!K:K))} -> 0 | C322: {=+MAX(IF('ID1&5'!A:A='1. Status'!A322&'1. Status'!$C$10,'ID1&5'!K:K))} -> 0 | D322: {=+MAX(IF('ID1&5'!A:A='1. Status'!A322&'1. Status'!$D$10,'ID1&5'!K:K))} -> 0 | E322: {=+MAX(IF('ID1&5'!A:A='1. Status'!A322&'1. Status'!$E$10,'ID1&5'!K:K))} -> 0 | F322: {=+MAX(IF('ID1&5'!A:A='1. Status'!A322&'1. Status'!$F$10,'ID1&5'!K:K))} -> 0 | H322: INSTRUMENT | I322: TYP_OFF_BLNC_PRDCT | J322: =+COUNTIF('ID1&5'!G:G,'1. Status'!I322) -> 0 | K322: =+IFERROR(VLOOKUP(CONCATENATE(A322,$B$10,B322),'ID1&5'!B:J,8,FALSE),"-") -> - | L322: =+IFERROR(VLOOKUP(B322,'ID1&5'!K:L,2,FALSE),"-") -> - | M322: =+IFERROR(VLOOKUP(CONCATENATE(A322,$B$10,B322),'ID1&5'!B:J,9,FALSE),"-") -> - | N322: =+IFERROR(VLOOKUP(CONCATENATE(A322,$C$10,C322),'ID1&5'!B:J,8,FALSE),"-") -> - | O322: =+IFERROR(VLOOKUP(C322,'ID1&5'!K:L,2,FALSE),"-") -> - | P322: =+IFERROR(VLOOKUP(CONCATENATE(A322,$C$10,C322),'ID1&5'!B:J,9,FALSE),"-") -> - | Q322: =+IFERROR(VLOOKUP(D322,'ID1&5'!K:L,2,FALSE),"-") -> - | R322: =+IFERROR(VLOOKUP(CONCATENATE(A322,$D$10,D322),'ID1&5'!B:J,9,FALSE),"-") -> - | S322: =+IFERROR(VLOOKUP(E322,'ID1&5'!K:L,2,FALSE),"-") -> - | T322: =+IFERROR(VLOOKUP(CONCATENATE(A322,$E$10,E322),'ID1&5'!B:J,9,FALSE),"-") -> - | U322: =+IFERROR(VLOOKUP(F322,'ID1&5'!K:L,2,FALSE),"-") -> - | V322: =+IFERROR(VLOOKUP(CONCATENATE(A322,$F$10,F322),'ID1&5'!B:J,9,FALSE),"-") -> - | W322: =+IFERROR(VLOOKUP(A322,'ID6&7'!A:I,9,FALSE),"-") -> - | X322: =+IFERROR(VLOOKUP(A322,'ID6&7'!A:J,10,FALSE),"-") -> - | Z322: =+IF(J322=0,"Por iniciar",IF(OR(K322="-",M322="-",P322="-",R322="-",T322="-",V322="-"),"Em testes",IF(AND(M322=0,P322=0,R322=0,T322<>K322,V322<>K322),"OK","NOK"))) -> Por iniciar
A323: =+H323&I323&$I$8 -> INSTRUMENTBLNC_SHT_RCGNTN45596 | B323: {=+MAX(IF('ID1&5'!A:A='1. Status'!A323&'1. Status'!$B$10,'ID1&5'!K:K))} -> 0 | C323: {=+MAX(IF('ID1&5'!A:A='1. Status'!A323&'1. Status'!$C$10,'ID1&5'!K:K))} -> 0 | D323: {=+MAX(IF('ID1&5'!A:A='1. Status'!A323&'1. Status'!$D$10,'ID1&5'!K:K))} -> 0 | E323: {=+MAX(IF('ID1&5'!A:A='1. Status'!A323&'1. Status'!$E$10,'ID1&5'!K:K))} -> 0 | F323: {=+MAX(IF('ID1&5'!A:A='1. Status'!A323&'1. Status'!$F$10,'ID1&5'!K:K))} -> 0 | H323: INSTRUMENT | I323: BLNC_SHT_RCGNTN | J323: =+COUNTIF('ID1&5'!G:G,'1. Status'!I323) -> 0 | K323: =+IFERROR(VLOOKUP(CONCATENATE(A323,$B$10,B323),'ID1&5'!B:J,8,FALSE),"-") -> - | L323: =+IFERROR(VLOOKUP(B323,'ID1&5'!K:L,2,FALSE),"-") -> - | M323: =+IFERROR(VLOOKUP(CONCATENATE(A323,$B$10,B323),'ID1&5'!B:J,9,FALSE),"-") -> - | N323: =+IFERROR(VLOOKUP(CONCATENATE(A323,$C$10,C323),'ID1&5'!B:J,8,FALSE),"-") -> - | O323: =+IFERROR(VLOOKUP(C323,'ID1&5'!K:L,2,FALSE),"-") -> - | P323: =+IFERROR(VLOOKUP(CONCATENATE(A323,$C$10,C323),'ID1&5'!B:J,9,FALSE),"-") -> - | Q323: =+IFERROR(VLOOKUP(D323,'ID1&5'!K:L,2,FALSE),"-") -> - | R323: =+IFERROR(VLOOKUP(CONCATENATE(A323,$D$10,D323),'ID1&5'!B:J,9,FALSE),"-") -> - | S323: =+IFERROR(VLOOKUP(E323,'ID1&5'!K:L,2,FALSE),"-") -> - | T323: =+IFERROR(VLOOKUP(CONCATENATE(A323,$E$10,E323),'ID1&5'!B:J,9,FALSE),"-") -> - | U323: =+IFERROR(VLOOKUP(F323,'ID1&5'!K:L,2,FALSE),"-") -> - | V323: =+IFERROR(VLOOKUP(CONCATENATE(A323,$F$10,F323),'ID1&5'!B:J,9,FALSE),"-") -> - | W323: =+IFERROR(VLOOKUP(A323,'ID6&7'!A:I,9,FALSE),"-") -> - | X323: =+IFERROR(VLOOKUP(A323,'ID6&7'!A:J,10,FALSE),"-") -> - | Z323: =+IF(J323=0,"Por iniciar",IF(OR(K323="-",M323="-",P323="-",R323="-",T323="-",V323="-"),"Em testes",IF(AND(M323=0,P323=0,R323=0,T323<>K323,V323<>K323),"OK","NOK"))) -> Por iniciar
A324: =+H324&I324&$I$8 -> INSTRUMENTFLG_DFLT45596 | B324: {=+MAX(IF('ID1&5'!A:A='1. Status'!A324&'1. Status'!$B$10,'ID1&5'!K:K))} -> 0 | C324: {=+MAX(IF('ID1&5'!A:A='1. Status'!A324&'1. Status'!$C$10,'ID1&5'!K:K))} -> 0 | D324: {=+MAX(IF('ID1&5'!A:A='1. Status'!A324&'1. Status'!$D$10,'ID1&5'!K:K))} -> 0 | E324: {=+MAX(IF('ID1&5'!A:A='1. Status'!A324&'1. Status'!$E$10,'ID1&5'!K:K))} -> 0 | F324: {=+MAX(IF('ID1&5'!A:A='1. Status'!A324&'1. Status'!$F$10,'ID1&5'!K:K))} -> 0 | H324: INSTRUMENT | I324: FLG_DFLT | J324: =+COUNTIF('ID1&5'!G:G,'1. Status'!I324) -> 0 | K324: =+IFERROR(VLOOKUP(CONCATENATE(A324,$B$10,B324),'ID1&5'!B:J,8,FALSE),"-") -> - | L324: =+IFERROR(VLOOKUP(B324,'ID1&5'!K:L,2,FALSE),"-") -> - | M324: =+IFERROR(VLOOKUP(CONCATENATE(A324,$B$10,B324),'ID1&5'!B:J,9,FALSE),"-") -> - | N324: =+IFERROR(VLOOKUP(CONCATENATE(A324,$C$10,C324),'ID1&5'!B:J,8,FALSE),"-") -> - | O324: =+IFERROR(VLOOKUP(C324,'ID1&5'!K:L,2,FALSE),"-") -> - | P324: =+IFERROR(VLOOKUP(CONCATENATE(A324,$C$10,C324),'ID1&5'!B:J,9,FALSE),"-") -> - | Q324: =+IFERROR(VLOOKUP(D324,'ID1&5'!K:L,2,FALSE),"-") -> - | R324: =+IFERROR(VLOOKUP(CONCATENATE(A324,$D$10,D324),'ID1&5'!B:J,9,FALSE),"-") -> - | S324: =+IFERROR(VLOOKUP(E324,'ID1&5'!K:L,2,FALSE),"-") -> - | T324: =+IFERROR(VLOOKUP(CONCATENATE(A324,$E$10,E324),'ID1&5'!B:J,9,FALSE),"-") -> - | U324: =+IFERROR(VLOOKUP(F324,'ID1&5'!K:L,2,FALSE),"-") -> - | V324: =+IFERROR(VLOOKUP(CONCATENATE(A324,$F$10,F324),'ID1&5'!B:J,9,FALSE),"-") -> - | W324: =+IFERROR(VLOOKUP(A324,'ID6&7'!A:I,9,FALSE),"-") -> - | X324: =+IFERROR(VLOOKUP(A324,'ID6&7'!A:J,10,FALSE),"-") -> - | Z324: =+IF(J324=0,"Por iniciar",IF(OR(K324="-",M324="-",P324="-",R324="-",T324="-",V324="-"),"Em testes",IF(AND(M324=0,P324=0,R324=0,T324<>K324,V324<>K324),"OK","NOK"))) -> Por iniciar
A325: =+H325&I325&$I$8 -> INSTRUMENTFLG_HGH_RSK45596 | B325: {=+MAX(IF('ID1&5'!A:A='1. Status'!A325&'1. Status'!$B$10,'ID1&5'!K:K))} -> 0 | C325: {=+MAX(IF('ID1&5'!A:A='1. Status'!A325&'1. Status'!$C$10,'ID1&5'!K:K))} -> 0 | D325: {=+MAX(IF('ID1&5'!A:A='1. Status'!A325&'1. Status'!$D$10,'ID1&5'!K:K))} -> 0 | E325: {=+MAX(IF('ID1&5'!A:A='1. Status'!A325&'1. Status'!$E$10,'ID1&5'!K:K))} -> 0 | F325: {=+MAX(IF('ID1&5'!A:A='1. Status'!A325&'1. Status'!$F$10,'ID1&5'!K:K))} -> 0 | H325: INSTRUMENT | I325: FLG_HGH_RSK | J325: =+COUNTIF('ID1&5'!G:G,'1. Status'!I325) -> 0 | K325: =+IFERROR(VLOOKUP(CONCATENATE(A325,$B$10,B325),'ID1&5'!B:J,8,FALSE),"-") -> - | L325: =+IFERROR(VLOOKUP(B325,'ID1&5'!K:L,2,FALSE),"-") -> - | M325: =+IFERROR(VLOOKUP(CONCATENATE(A325,$B$10,B325),'ID1&5'!B:J,9,FALSE),"-") -> - | N325: =+IFERROR(VLOOKUP(CONCATENATE(A325,$C$10,C325),'ID1&5'!B:J,8,FALSE),"-") -> - | O325: =+IFERROR(VLOOKUP(C325,'ID1&5'!K:L,2,FALSE),"-") -> - | P325: =+IFERROR(VLOOKUP(CONCATENATE(A325,$C$10,C325),'ID1&5'!B:J,9,FALSE),"-") -> - | Q325: =+IFERROR(VLOOKUP(D325,'ID1&5'!K:L,2,FALSE),"-") -> - | R325: =+IFERROR(VLOOKUP(CONCATENATE(A325,$D$10,D325),'ID1&5'!B:J,9,FALSE),"-") -> - | S325: =+IFERROR(VLOOKUP(E325,'ID1&5'!K:L,2,FALSE),"-") -> - | T325: =+IFERROR(VLOOKUP(CONCATENATE(A325,$E$10,E325),'ID1&5'!B:J,9,FALSE),"-") -> - | U325: =+IFERROR(VLOOKUP(F325,'ID1&5'!K:L,2,FALSE),"-") -> - | V325: =+IFERROR(VLOOKUP(CONCATENATE(A325,$F$10,F325),'ID1&5'!B:J,9,FALSE),"-") -> - | W325: =+IFERROR(VLOOKUP(A325,'ID6&7'!A:I,9,FALSE),"-") -> - | X325: =+IFERROR(VLOOKUP(A325,'ID6&7'!A:J,10,FALSE),"-") -> - | Z325: =+IF(J325=0,"Por iniciar",IF(OR(K325="-",M325="-",P325="-",R325="-",T325="-",V325="-"),"Em testes",IF(AND(M325=0,P325=0,R325=0,T325<>K325,V325<>K325),"OK","NOK"))) -> Por iniciar
... A378: =+H378&I378&$I$8 -> INSTR_ACTIVITYPRCNTG_ACTVTY45596 | B378: {=+MAX(IF('ID1&5'!A:A='1. Status'!A378&'1. Status'!$B$10,'ID1&5'!K:K))} -> 0 | C378: {=+MAX(IF('ID1&5'!A:A='1. Status'!A378&'1. Status'!$C$10,'ID1&5'!K:K))} -> 0 | D378: {=+MAX(IF('ID1&5'!A:A='1. Status'!A378&'1. Status'!$D$10,'ID1&5'!K:K))} -> 0 | E378: {=+MAX(IF('ID1&5'!A:A='1. Status'!A378&'1. Status'!$E$10,'ID1&5'!K:K))} -> 0 | F378: {=+MAX(IF('ID1&5'!A:A='1. Status'!A378&'1. Status'!$F$10,'ID1&5'!K:K))} -> 0 | H378: INSTR_ACTIVITY | I378: PRCNTG_ACTVTY | J378: =+COUNTIF('ID1&5'!G:G,'1. Status'!I378) -> 0 | K378: =+IFERROR(VLOOKUP(CONCATENATE(A378,$B$10,B378),'ID1&5'!B:J,8,FALSE),"-") -> - | L378: =+IFERROR(VLOOKUP(B378,'ID1&5'!K:L,2,FALSE),"-") -> - | M378: =+IFERROR(VLOOKUP(CONCATENATE(A378,$B$10,B378),'ID1&5'!B:J,9,FALSE),"-") -> - | N378: =+IFERROR(VLOOKUP(CONCATENATE(A378,$C$10,C378),'ID1&5'!B:J,8,FALSE),"-") -> - | O378: =+IFERROR(VLOOKUP(C378,'ID1&5'!K:L,2,FALSE),"-") -> - | P378: =+IFERROR(VLOOKUP(CONCATENATE(A378,$C$10,C378),'ID1&5'!B:J,9,FALSE),"-") -> - | Q378: =+IFERROR(VLOOKUP(D378,'ID1&5'!K:L,2,FALSE),"-") -> - | R378: =+IFERROR(VLOOKUP(CONCATENATE(A378,$D$10,D378),'ID1&5'!B:J,9,FALSE),"-") -> - | S378: =+IFERROR(VLOOKUP(E378,'ID1&5'!K:L,2,FALSE),"-") -> - | T378: =+IFERROR(VLOOKUP(CONCATENATE(A378,$E$10,E378),'ID1&5'!B:J,9,FALSE),"-") -> - | U378: =+IFERROR(VLOOKUP(F378,'ID1&5'!K:L,2,FALSE),"-") -> - | V378: =+IFERROR(VLOOKUP(CONCATENATE(A378,$F$10,F378),'ID1&5'!B:J,9,FALSE),"-") -> - | W378: =+IFERROR(VLOOKUP(A378,'ID6&7'!A:I,9,FALSE),"-") -> - | X378: =+IFERROR(VLOOKUP(A378,'ID6&7'!A:J,10,FALSE),"-") -> - | Z378: =+IF(J378=0,"Por iniciar",IF(OR(K378="-",M378="-",P378="-",R378="-",T378="-",V378="-"),"Em testes",IF(AND(M378=0,P378=0,R378=0,T378<>K378,V378<>K378),"OK","NOK"))) -> Por iniciar

Sheet 2. Script 
B6: 2. Script de Controlos
B8: TABELA | C8: TIPOLOGIA_TESTE | D8: TABELA_LT_PILAR3 | E8: TABELA_SIMUL | F8: CAMPO | G8: FORMATO CAMPO | H8: VALORES CODE LIST | I8: UNIVERSO_PILAR3 | J8: UNIVERSO_SIMUL | K8: CRUZAMENTO | L8: QUERY 1 | M8: UNION ALL
B9: ENTITY | C9: Coerência | D9: =+UPPER('0. Instruções'!$D$35&"."&VLOOKUP(B9,'0. Instruções'!$C$27:$D$32,2,FALSE)) -> CD_LOAN_TAPES_BCE.LT003_ENTITY | E9: =+UPPER('0. Instruções'!$D$36&"."&VLOOKUP(B9,'0. Instruções'!$C$27:$E$32,3,FALSE)) -> BU_LOANTAPE_WORK.LT003_ENTITY | F9: COD_SOC | H9: VARCHAR2(5) | I9: ="(SELECT "&VLOOKUP(B9,'0. Instruções'!$C$27:$G$32,4,FALSE)&", "&F9&" FROM "&D9&" WHERE "&'0. Instruções'!$D$42&")X" -> (SELECT entty_id, COD_SOC FROM CD_LOAN_TAPES_BCE.LT003_ENTITY WHERE ref_date='${ref_date}' AND nome_perimetro='Individual Corporativo' AND segmento='ESTR' AND ambito='PM' AND entidade='00100')X | J9: ="(SELECT "&VLOOKUP(B9,'0. Instruções'!$C$27:$G$32,4,FALSE)&" AS "&VLOOKUP(B9,'0. Instruções'!$C$27:$G$32,4,FALSE)&"_SIMUL, "&F9&" AS "&F9&"_SIMUL FROM "&E9&" WHERE "&'0. Instruções'!$D$43&")Y" -> (SELECT entty_id AS entty_id_SIMUL, COD_SOC AS COD_SOC_SIMUL FROM BU_LOANTAPE_WORK.LT003_ENTITY WHERE ref_date='${ref_date}' AND nome_perimetro='Individual Corporativo' AND segmento='ESTR' AND ambito='PM' AND entidade='00100')Y | K9: =+UPPER("ON X."&VLOOKUP(B9,'0. Instruções'!$C$27:$G$32,4,FALSE)&"=Y."&VLOOKUP(B9,'0. Instruções'!$C$27:$G$32,4,FALSE)&"_SIMUL") -> ON X.ENTTY_ID=Y.ENTTY_ID_SIMUL | L9: =+IF(C9="Coerência", +IF(LEFT(G9,5)="FLOAT","SELECT '"&UPPER(B9)&"' AS TABELA, '"&UPPER(C9)&"' AS TIPOLOGIA_TESTE,'"&D9&"' AS TABELA_LT,'"&E9&"' AS TABELA_SIMUL,'"&F9&"' AS CAMPO, "&"'${ref_date}' AS REF_DATE, COUNT(*) AS NUM_REG, SUM(IF((ABS(COALESCE(CAST(X."&F9&" AS DECIMAL(18,6)),0)-COALESCE(CAST(Y."&F9&"_SIMUL AS DECIMAL(18,6)),0))>0.000001) OR (X."&F9&" IS NULL AND Y."&F9&"_SIMUL IS NOT NULL ) OR (X."&F9&" IS NOT NULL AND Y."&F9&"_SIMUL IS NULL),1,0)) AS NUM_REG_DIF,'"&MAX('ID1&5'!K:K)+1&"' AS ID_EXEC, CURRENT_TIMESTAMP() AS TIME_EXEC FROM "&I9&" INNER JOIN "&J9&" "&K9,"SELECT '"&UPPER(B9)&"' AS TABELA, '"&UPPER(C9)&"' AS TIPOLOGIA_TESTE,'"&D9&"' AS TABELA_LT,'"&E9&"' AS TABELA_SIMUL,'"&F9&"' AS CAMPO, "&"'${ref_date}' AS REF_DATE, COUNT(*) AS NUM_REG, SUM(IF(COALESCE(CAST(X."&F9&" AS STRING),'')<>COALESCE(CAST(Y."&F9&"_SIMUL AS STRING),'') OR (X."&F9&" IS NULL AND Y."&F9&"_SIMUL IS NOT NULL ) OR (X."&F9&" IS NOT NULL AND Y."&F9&"_SIMUL IS NULL),1,0)) AS NUM_REG_DIF,'"&MAX('ID1&5'!L:L)+1&"' AS ID_EXEC, CURRENT_TIMESTAMP() AS TIME_EXEC FROM "&I9&" INNER JOIN "&J9&" "&K9), IF(C9="Validade",+IF(G9="Code List","SELECT '"&UPPER(B9)&"' AS TABELA, '"&UPPER(C9)&"' AS TIPOLOGIA_TESTE,'"&D9&"' AS TABELA_LT,'N/A' AS TABELA_SIMUL,'"&F9&"' AS CAMPO, "&"'${ref_date}' AS REF_DATE, COUNT(*) AS NUM_REG, SUM(IF(TRIM(CAST(X."&F9&" AS STRING))='' OR TRIM(CAST(X."&F9&" AS STRING)) IS NULL OR CAST(X."&F9&" AS STRING) NOT "&H9&",1,0)) AS NUM_REG_DIF,'"&MAX('ID1&5'!K:K)+1&"' AS ID_EXEC, CURRENT_TIMESTAMP() AS TIME_EXEC FROM "&I9,"SELECT '"&UPPER(B9)&"' AS TABELA, '"&UPPER(C9)&"' AS TIPOLOGIA_TESTE,'"&D9&"' AS TABELA_LT,'N/A' AS TABELA_SIMUL,'"&F9&"' AS CAMPO, "&"'${ref_date}' AS REF_DATE, COUNT(*) AS NUM_REG, SUM(IF(TRIM(CAST(X."&F9&" AS STRING))='' OR TRIM(CAST(X."&F9&" AS STRING)) IS NULL,1,0)) AS NUM_REG_DIF,'"&MAX('ID1&5'!K:K)+1&"' AS ID_EXEC, CURRENT_TIMESTAMP() AS TIME_EXEC FROM "&I9), IF(C9="Caracteres Especiais",+"SELECT '"&UPPER(B9)&"' AS TABELA, '"&UPPER(C9)&"' AS TIPOLOGIA_TESTE,'"&D9&"' AS TABELA_LT,'N/A' AS TABELA_SIMUL,'"&F9&"' AS CAMPO, "&"'${ref_date}' AS REF_DATE, COUNT(*) AS NUM_REG, SUM(IF(REGEXP_REPLACE(TRIM(CAST(X."&F9&" AS STRING)),'[^a-zA-Z0-9_\\s]','') <>TRIM(CAST(X."&F9&" AS STRING)),1,0)) AS NUM_REG_DIF,'"&MAX('ID1&5'!K:K)+1&"' AS ID_EXEC, CURRENT_TIMESTAMP() AS TIME_EXEC FROM "&I9, IF(C9="Missings",+"SELECT '"&UPPER(B9)&"' AS TABELA, '"&UPPER(C9)&"' AS TIPOLOGIA_TESTE,'"&D9&"' AS TABELA_LT,'N/A' AS TABELA_SIMUL,'"&F9&"' AS CAMPO, "&"'${ref_date}' AS REF_DATE, COUNT(*) AS NUM_REG, SUM(IF(TRIM(CAST(X."&F9&" AS STRING)) IN ('0000-00-00','0001-01-01','9999-12-31','MISS','00000','99999999999','99999999999.00','99999999999.000000'),1,0)) AS NUM_REG_DIF,'"&MAX('ID1&5'!K:K)+1&"' AS ID_EXEC, CURRENT_TIMESTAMP() AS TIME_EXEC FROM "&I9, IF(C9="Not applicable",+"SELECT '"&UPPER(B9)&"' AS TABELA, '"&UPPER(C9)&"' AS TIPOLOGIA_TESTE,'"&D9&"' AS TABELA_LT,'N/A' AS TABELA_SIMUL,'"&F9&"' AS CAMPO, "&"'${ref_date}' AS REF_DATE, COUNT(*) AS NUM_REG, SUM(IF(TRIM(CAST(X."&F9&" AS STRING)) IN ('N/A','11111111111','11111111111.00','11111111111.000000','1111-11-11'),1,0)) AS NUM_REG_DIF,'"&MAX('ID1&5'!K:K)+1&"' AS ID_EXEC, CURRENT_TIMESTAMP() AS TIME_EXEC FROM "&I9, IF(C9="Valores extremos",+"SELECT '"&UPPER(B9)&"' AS TABELA, '"&UPPER(C9)&"' AS TIPOLOGIA_TESTE,'"&D9&"' AS TABELA_LT,'N/A' AS TABELA_SIMUL,'"&F9&"' AS CAMPO, "&"'${ref_date}' AS REF_DATE, CAST(MIN("&F9&") AS STRING) AS VALOR_MIN, CAST(MAX("&F9&") AS STRING) AS VALOR_MAX,'"&MAX('ID1&5'!K:K)+1&"' AS ID_EXEC, CURRENT_TIMESTAMP() AS TIME_EXEC FROM "&MID(I9,1,LEN(I9)-2)&" AND CAST("&F9&" AS STRING) NOT IN ('0000-00-00','0001-01-01','9999-12-31','MISS','00000','99999999999','99999999999.00','99999999999.000000','N/A','11111111111','11111111111.00','11111111111.000000','1111-11-11'))X")))))) -> SELECT 'ENTITY' AS TABELA, 'COERÊNCIA' AS TIPOLOGIA_TESTE,'CD_LOAN_TAPES_BCE.LT003_ENTITY' AS TABELA_LT,'BU_LOANTAPE_WORK.LT003_ENTITY' AS TABELA_SIMUL,'COD_SOC' AS CAMPO, '${ref_date}' AS REF_DATE, COUNT(*) AS NUM_REG, SUM(IF(COALESCE(CAST(X.COD_SOC AS STRING),'')<>COALESCE(CAST(Y.COD_SOC_SIMUL AS STRING),'') OR (X.COD_SOC IS NULL AND Y.COD_SOC_SIMUL IS NOT NULL ) OR (X.COD_SOC IS NOT NULL AND Y.COD_SOC_SIMUL IS NULL),1,0)) AS NUM_REG_DIF,'1' AS ID_EXEC, CURRENT_TIMESTAMP() AS TIME_EXEC FROM (SELECT entty_id, COD_SOC FROM CD_LOAN_TAPES_BCE.LT003_ENTITY WHERE ref_date='${ref_date}' AND nome_perimetro='Individual Corporativo' AND segmento='ESTR' AND ambito='PM' AND entidade='00100')X INNER JOIN (SELECT entty_id AS entty_id_SIMUL, COD_SOC AS COD_SOC_SIMUL FROM BU_LOANTAPE_WORK.LT003_ENTITY WHERE ref_date='${ref_date}' AND nome_perimetro='Individual Corporativo' AND segmento='ESTR' AND ambito='PM' AND entidade='00100')Y ON X.ENTTY_ID=Y.ENTTY_ID_SIMUL | M9: =+"UNION ALL "&L9 -> UNION ALL SELECT 'ENTITY' AS TABELA, 'COERÊNCIA' AS TIPOLOGIA_TESTE,'CD_LOAN_TAPES_BCE.LT003_ENTITY' AS TABELA_LT,'BU_LOANTAPE_WORK.LT003_ENTITY' AS TABELA_SIMUL,'COD_SOC' AS CAMPO, '${ref_date}' AS REF_DATE, COUNT(*) AS NUM_REG, SUM(IF(COALESCE(CAST(X.COD_SOC AS STRING),'')<>COALESCE(CAST(Y.COD_SOC_SIMUL AS STRING),'') OR (X.COD_SOC IS NULL AND Y.COD_SOC_SIMUL IS NOT NULL ) OR (X.COD_SOC IS NOT NULL AND Y.COD_SOC_SIMUL IS NULL),1,0)) AS NUM_REG_DIF,'1' AS ID_EXEC, CURRENT_TIMESTAMP() AS TIME_EXEC FROM (SELECT entty_id, COD_SOC FROM CD_LOAN_TAPES_BCE.LT003_ENTITY WHERE ref_date='${ref_date}' AND nome_perimetro='Individual Corporativo' AND segmento='ESTR' AND ambito='PM' AND entidade='00100')X INNER JOIN (SELECT entty_id AS entty_id_SIMUL, COD_SOC AS COD_SOC_SIMUL FROM BU_LOANTAPE_WORK.LT003_ENTITY WHERE ref_date='${ref_date}' AND nome_perimetro='Individual Corporativo' AND segmento='ESTR' AND ambito='PM' AND entidade='00100')Y ON X.ENTTY_ID=Y.ENTTY_ID_SIMUL
B10: ENTITY | C10: Coerência | D10: =+UPPER('0. Instruções'!$D$35&"."&VLOOKUP(B10,'0. Instruções'!$C$27:$D$32,2,FALSE)) -> CD_LOAN_TAPES_BCE.LT003_ENTITY | E10: =+UPPER('0. Instruções'!$D$36&"."&VLOOKUP(B10,'0. Instruções'!$C$27:$E$32,3,FALSE)) -> BU_LOANTAPE_WORK.LT003_ENTITY | F10: CNTRY | H10: Code List | I10: ="(SELECT "&VLOOKUP(B10,'0. Instruções'!$C$27:$G$32,4,FALSE)&", "&F10&" FROM "&D10&" WHERE "&'0. Instruções'!$D$42&")X" -> (SELECT entty_id, CNTRY FROM CD_LOAN_TAPES_BCE.LT003_ENTITY WHERE ref_date='${ref_date}' AND nome_perimetro='Individual Corporativo' AND segmento='ESTR' AND ambito='PM' AND entidade='00100')X | J10: ="(SELECT "&VLOOKUP(B10,'0. Instruções'!$C$27:$G$32,4,FALSE)&" AS "&VLOOKUP(B10,'0. Instruções'!$C$27:$G$32,4,FALSE)&"_SIMUL, "&F10&" AS "&F10&"_SIMUL FROM "&E10&" WHERE "&'0. Instruções'!$D$43&")Y" -> (SELECT entty_id AS entty_id_SIMUL, CNTRY AS CNTRY_SIMUL FROM BU_LOANTAPE_WORK.LT003_ENTITY WHERE ref_date='${ref_date}' AND nome_perimetro='Individual Corporativo' AND segmento='ESTR' AND ambito='PM' AND entidade='00100')Y | K10: =+UPPER("ON X."&VLOOKUP(B10,'0. Instruções'!$C$27:$G$32,4,FALSE)&"=Y."&VLOOKUP(B10,'0. Instruções'!$C$27:$G$32,4,FALSE)&"_SIMUL") -> ON X.ENTTY_ID=Y.ENTTY_ID_SIMUL | L10: =+IF(C10="Coerência", +IF(LEFT(G10,5)="FLOAT","SELECT '"&UPPER(B10)&"' AS TABELA, '"&UPPER(C10)&"' AS TIPOLOGIA_TESTE,'"&D10&"' AS TABELA_LT,'"&E10&"' AS TABELA_SIMUL,'"&F10&"' AS CAMPO, "&"'${ref_date}' AS REF_DATE, COUNT(*) AS NUM_REG, SUM(IF((ABS(COALESCE(CAST(X."&F10&" AS DECIMAL(18,6)),0)-COALESCE(CAST(Y."&F10&"_SIMUL AS DECIMAL(18,6)),0))>0.000001) OR (X."&F10&" IS NULL AND Y."&F10&"_SIMUL IS NOT NULL ) OR (X."&F10&" IS NOT NULL AND Y."&F10&"_SIMUL IS NULL),1,0)) AS NUM_REG_DIF,'"&MAX('ID1&5'!K:K)+1&"' AS ID_EXEC, CURRENT_TIMESTAMP() AS TIME_EXEC FROM "&I10&" INNER JOIN "&J10&" "&K10,"SELECT '"&UPPER(B10)&"' AS TABELA, '"&UPPER(C10)&"' AS TIPOLOGIA_TESTE,'"&D10&"' AS TABELA_LT,'"&E10&"' AS TABELA_SIMUL,'"&F10&"' AS CAMPO, "&"'${ref_date}' AS REF_DATE, COUNT(*) AS NUM_REG, SUM(IF(COALESCE(CAST(X."&F10&" AS STRING),'')<>COALESCE(CAST(Y."&F10&"_SIMUL AS STRING),'') OR (X."&F10&" IS NULL AND Y."&F10&"_SIMUL IS NOT NULL ) OR (X."&F10&" IS NOT NULL AND Y."&F10&"_SIMUL IS NULL),1,0)) AS NUM_REG_DIF,'"&MAX('ID1&5'!L:L)+1&"' AS ID_EXEC, CURRENT_TIMESTAMP() AS TIME_EXEC FROM "&I10&" INNER JOIN "&J10&" "&K10), IF(C10="Validade",+IF(G10="Code List","SELECT '"&UPPER(B10)&"' AS TABELA, '"&UPPER(C10)&"' AS TIPOLOGIA_TESTE,'"&D10&"' AS TABELA_LT,'N/A' AS TABELA_SIMUL,'"&F10&"' AS CAMPO, "&"'${ref_date}' AS REF_DATE, COUNT(*) AS NUM_REG, SUM(IF(TRIM(CAST(X."&F10&" AS STRING))='' OR TRIM(CAST(X."&F10&" AS STRING)) IS NULL OR CAST(X."&F10&" AS STRING) NOT "&H10&",1,0)) AS NUM_REG_DIF,'"&MAX('ID1&5'!K:K)+1&"' AS ID_EXEC, CURRENT_TIMESTAMP() AS TIME_EXEC FROM "&I10,"SELECT '"&UPPER(B10)&"' AS TABELA, '"&UPPER(C10)&"' AS TIPOLOGIA_TESTE,'"&D10&"' AS TABELA_LT,'N/A' AS TABELA_SIMUL,'"&F10&"' AS CAMPO, "&"'${ref_date}' AS REF_DATE, COUNT(*) AS NUM_REG, SUM(IF(TRIM(CAST(X."&F10&" AS STRING))='' OR TRIM(CAST(X."&F10&" AS STRING)) IS NULL,1,0)) AS NUM_REG_DIF,'"&MAX('ID1&5'!K:K)+1&"' AS ID_EXEC, CURRENT_TIMESTAMP() AS TIME_EXEC FROM "&I10), IF(C10="Caracteres Especiais",+"SELECT '"&UPPER(B10)&"' AS TABELA, '"&UPPER(C10)&"' AS TIPOLOGIA_TESTE,'"&D10&"' AS TABELA_LT,'N/A' AS TABELA_SIMUL,'"&F10&"' AS CAMPO, "&"'${ref_date}' AS REF_DATE, COUNT(*) AS NUM_REG, SUM(IF(REGEXP_REPLACE(TRIM(CAST(X."&F10&" AS STRING)),'[^a-zA-Z0-9_\\s]','') <>TRIM(CAST(X."&F10&" AS STRING)),1,0)) AS NUM_REG_DIF,'"&MAX('ID1&5'!K:K)+1&"' AS ID_EXEC, CURRENT_TIMESTAMP() AS TIME_EXEC FROM "&I10, IF(C10="Missings",+"SELECT '"&UPPER(B10)&"' AS TABELA, '"&UPPER(C10)&"' AS TIPOLOGIA_TESTE,'"&D10&"' AS TABELA_LT,'N/A' AS TABELA_SIMUL,'"&F10&"' AS CAMPO, "&"'${ref_date}' AS REF_DATE, COUNT(*) AS NUM_REG, SUM(IF(TRIM(CAST(X."&F10&" AS STRING)) IN ('0000-00-00','0001-01-01','9999-12-31','MISS','00000','99999999999','99999999999.00','99999999999.000000'),1,0)) AS NUM_REG_DIF,'"&MAX('ID1&5'!K:K)+1&"' AS ID_EXEC, CURRENT_TIMESTAMP() AS TIME_EXEC FROM "&I10, IF(C10="Not applicable",+"SELECT '"&UPPER(B10)&"' AS TABELA, '"&UPPER(C10)&"' AS TIPOLOGIA_TESTE,'"&D10&"' AS TABELA_LT,'N/A' AS TABELA_SIMUL,'"&F10&"' AS CAMPO, "&"'${ref_date}' AS REF_DATE, COUNT(*) AS NUM_REG, SUM(IF(TRIM(CAST(X."&F10&" AS STRING)) IN ('N/A','11111111111','11111111111.00','11111111111.000000','1111-11-11'),1,0)) AS NUM_REG_DIF,'"&MAX('ID1&5'!K:K)+1&"' AS ID_EXEC, CURRENT_TIMESTAMP() AS TIME_EXEC FROM "&I10, IF(C10="Valores extremos",+"SELECT '"&UPPER(B10)&"' AS TABELA, '"&UPPER(C10)&"' AS TIPOLOGIA_TESTE,'"&D10&"' AS TABELA_LT,'N/A' AS TABELA_SIMUL,'"&F10&"' AS CAMPO, "&"'${ref_date}' AS REF_DATE, CAST(MIN("&F10&") AS STRING) AS VALOR_MIN, CAST(MAX("&F10&") AS STRING) AS VALOR_MAX,'"&MAX('ID1&5'!K:K)+1&"' AS ID_EXEC, CURRENT_TIMESTAMP() AS TIME_EXEC FROM "&MID(I10,1,LEN(I10)-2)&" AND CAST("&F10&" AS STRING) NOT IN ('0000-00-00','0001-01-01','9999-12-31','MISS','00000','99999999999','99999999999.00','99999999999.000000','N/A','11111111111','11111111111.00','11111111111.000000','1111-11-11'))X")))))) -> SELECT 'ENTITY' AS TABELA, 'COERÊNCIA' AS TIPOLOGIA_TESTE,'CD_LOAN_TAPES_BCE.LT003_ENTITY' AS TABELA_LT,'BU_LOANTAPE_WORK.LT003_ENTITY' AS TABELA_SIMUL,'CNTRY' AS CAMPO, '${ref_date}' AS REF_DATE, COUNT(*) AS NUM_REG, SUM(IF(COALESCE(CAST(X.CNTRY AS STRING),'')<>COALESCE(CAST(Y.CNTRY_SIMUL AS STRING),'') OR (X.CNTRY IS NULL AND Y.CNTRY_SIMUL IS NOT NULL ) OR (X.CNTRY IS NOT NULL AND Y.CNTRY_SIMUL IS NULL),1,0)) AS NUM_REG_DIF,'1' AS ID_EXEC, CURRENT_TIMESTAMP() AS TIME_EXEC FROM (SELECT entty_id, CNTRY FROM CD_LOAN_TAPES_BCE.LT003_ENTITY WHERE ref_date='${ref_date}' AND nome_perimetro='Individual Corporativo' AND segmento='ESTR' AND ambito='PM' AND entidade='00100')X INNER JOIN (SELECT entty_id AS entty_id_SIMUL, CNTRY AS CNTRY_SIMUL FROM BU_LOANTAPE_WORK.LT003_ENTITY WHERE ref_date='${ref_date}' AND nome_perimetro='Individual Corporativo' AND segmento='ESTR' AND ambito='PM' AND entidade='00100')Y ON X.ENTTY_ID=Y.ENTTY_ID_SIMUL | M10: =+"UNION ALL "&L10 -> UNION ALL SELECT 'ENTITY' AS TABELA, 'COERÊNCIA' AS TIPOLOGIA_TESTE,'CD_LOAN_TAPES_BCE.LT003_ENTITY' AS TABELA_LT,'BU_LOANTAPE_WORK.LT003_ENTITY' AS TABELA_SIMUL,'CNTRY' AS CAMPO, '${ref_date}' AS REF_DATE, COUNT(*) AS NUM_REG, SUM(IF(COALESCE(CAST(X.CNTRY AS STRING),'')<>COALESCE(CAST(Y.CNTRY_SIMUL AS STRING),'') OR (X.CNTRY IS NULL AND Y.CNTRY_SIMUL IS NOT NULL ) OR (X.CNTRY IS NOT NULL AND Y.CNTRY_SIMUL IS NULL),1,0)) AS NUM_REG_DIF,'1' AS ID_EXEC, CURRENT_TIMESTAMP() AS TIME_EXEC FROM (SELECT entty_id, CNTRY FROM CD_LOAN_TAPES_BCE.LT003_ENTITY WHERE ref_date='${ref_date}' AND nome_perimetro='Individual Corporativo' AND segmento='ESTR' AND ambito='PM' AND entidade='00100')X INNER JOIN (SELECT entty_id AS entty_id_SIMUL, CNTRY AS CNTRY_SIMUL FROM BU_LOANTAPE_WORK.LT003_ENTITY WHERE ref_date='${ref_date}' AND nome_perimetro='Individual Corporativo' AND segmento='ESTR' AND ambito='PM' AND entidade='00100')Y ON X.ENTTY_ID=Y.ENTTY_ID_SIMUL
B11: ENTITY | C11: Coerência | D11: =+UPPER('0. Instruções'!$D$35&"."&VLOOKUP(B11,'0. Instruções'!$C$27:$D$32,2,FALSE)) -> CD_LOAN_TAPES_BCE.LT003_ENTITY | E11: =+UPPER('0. Instruções'!$D$36&"."&VLOOKUP(B11,'0. Instruções'!$C$27:$E$32,3,FALSE)) -> BU_LOANTAPE_WORK.LT003_ENTITY | F11: DT_BRTH | H11: DATE | I11: ="(SELECT "&VLOOKUP(B11,'0. Instruções'!$C$27:$G$32,4,FALSE)&", "&F11&" FROM "&D11&" WHERE "&'0. Instruções'!$D$42&")X" -> (SELECT entty_id, DT_BRTH FROM CD_LOAN_TAPES_BCE.LT003_ENTITY WHERE ref_date='${ref_date}' AND nome_perimetro='Individual Corporativo' AND segmento='ESTR' AND ambito='PM' AND entidade='00100')X | J11: ="(SELECT "&VLOOKUP(B11,'0. Instruções'!$C$27:$G$32,4,FALSE)&" AS "&VLOOKUP(B11,'0. Instruções'!$C$27:$G$32,4,FALSE)&"_SIMUL, "&F11&" AS "&F11&"_SIMUL FROM "&E11&" WHERE "&'0. Instruções'!$D$43&")Y" -> (SELECT entty_id AS entty_id_SIMUL, DT_BRTH AS DT_BRTH_SIMUL FROM BU_LOANTAPE_WORK.LT003_ENTITY WHERE ref_date='${ref_date}' AND nome_perimetro='Individual Corporativo' AND segmento='ESTR' AND ambito='PM' AND entidade='00100')Y | K11: =+UPPER("ON X."&VLOOKUP(B11,'0. Instruções'!$C$27:$G$32,4,FALSE)&"=Y."&VLOOKUP(B11,'0. Instruções'!$C$27:$G$32,4,FALSE)&"_SIMUL") -> ON X.ENTTY_ID=Y.ENTTY_ID_SIMUL | L11: =+IF(C11="Coerência", +IF(LEFT(G11,5)="FLOAT","SELECT '"&UPPER(B11)&"' AS TABELA, '"&UPPER(C11)&"' AS TIPOLOGIA_TESTE,'"&D11&"' AS TABELA_LT,'"&E11&"' AS TABELA_SIMUL,'"&F11&"' AS CAMPO, "&"'${ref_date}' AS REF_DATE, COUNT(*) AS NUM_REG, SUM(IF((ABS(COALESCE(CAST(X."&F11&" AS DECIMAL(18,6)),0)-COALESCE(CAST(Y."&F11&"_SIMUL AS DECIMAL(18,6)),0))>0.000001) OR (X."&F11&" IS NULL AND Y."&F11&"_SIMUL IS NOT NULL ) OR (X."&F11&" IS NOT NULL AND Y."&F11&"_SIMUL IS NULL),1,0)) AS NUM_REG_DIF,'"&MAX('ID1&5'!K:K)+1&"' AS ID_EXEC, CURRENT_TIMESTAMP() AS TIME_EXEC FROM "&I11&" INNER JOIN "&J11&" "&K11,"SELECT '"&UPPER(B11)&"' AS TABELA, '"&UPPER(C11)&"' AS TIPOLOGIA_TESTE,'"&D11&"' AS TABELA_LT,'"&E11&"' AS TABELA_SIMUL,'"&F11&"' AS CAMPO, "&"'${ref_date}' AS REF_DATE, COUNT(*) AS NUM_REG, SUM(IF(COALESCE(CAST(X."&F11&" AS STRING),'')<>COALESCE(CAST(Y."&F11&"_SIMUL AS STRING),'') OR (X."&F11&" IS NULL AND Y."&F11&"_SIMUL IS NOT NULL ) OR (X."&F11&" IS NOT NULL AND Y."&F11&"_SIMUL IS NULL),1,0)) AS NUM_REG_DIF,'"&MAX('ID1&5'!L:L)+1&"' AS ID_EXEC, CURRENT_TIMESTAMP() AS TIME_EXEC FROM "&I11&" INNER JOIN "&J11&" "&K11), IF(C11="Validade",+IF(G11="Code List","SELECT '"&UPPER(B11)&"' AS TABELA, '"&UPPER(C11)&"' AS TIPOLOGIA_TESTE,'"&D11&"' AS TABELA_LT,'N/A' AS TABELA_SIMUL,'"&F11&"' AS CAMPO, "&"'${ref_date}' AS REF_DATE, COUNT(*) AS NUM_REG, SUM(IF(TRIM(CAST(X."&F11&" AS STRING))='' OR TRIM(CAST(X."&F11&" AS STRING)) IS NULL OR CAST(X."&F11&" AS STRING) NOT "&H11&",1,0)) AS NUM_REG_DIF,'"&MAX('ID1&5'!K:K)+1&"' AS ID_EXEC, CURRENT_TIMESTAMP() AS TIME_EXEC FROM "&I11,"SELECT '"&UPPER(B11)&"' AS TABELA, '"&UPPER(C11)&"' AS TIPOLOGIA_TESTE,'"&D11&"' AS TABELA_LT,'N/A' AS TABELA_SIMUL,'"&F11&"' AS CAMPO, "&"'${ref_date}' AS REF_DATE, COUNT(*) AS NUM_REG, SUM(IF(TRIM(CAST(X."&F11&" AS STRING))='' OR TRIM(CAST(X."&F11&" AS STRING)) IS NULL,1,0)) AS NUM_REG_DIF,'"&MAX('ID1&5'!K:K)+1&"' AS ID_EXEC, CURRENT_TIMESTAMP() AS TIME_EXEC FROM "&I11), IF(C11="Caracteres Especiais",+"SELECT '"&UPPER(B11)&"' AS TABELA, '"&UPPER(C11)&"' AS TIPOLOGIA_TESTE,'"&D11&"' AS TABELA_LT,'N/A' AS TABELA_SIMUL,'"&F11&"' AS CAMPO, "&"'${ref_date}' AS REF_DATE, COUNT(*) AS NUM_REG, SUM(IF(REGEXP_REPLACE(TRIM(CAST(X."&F11&" AS STRING)),'[^a-zA-Z0-9_\\s]','') <>TRIM(CAST(X."&F11&" AS STRING)),1,0)) AS NUM_REG_DIF,'"&MAX('ID1&5'!K:K)+1&"' AS ID_EXEC, CURRENT_TIMESTAMP() AS TIME_EXEC FROM "&I11, IF(C11="Missings",+"SELECT '"&UPPER(B11)&"' AS TABELA, '"&UPPER(C11)&"' AS TIPOLOGIA_TESTE,'"&D11&"' AS TABELA_LT,'N/A' AS TABELA_SIMUL,'"&F11&"' AS CAMPO, "&"'${ref_date}' AS REF_DATE, COUNT(*) AS NUM_REG, SUM(IF(TRIM(CAST(X."&F11&" AS STRING)) IN ('0000-00-00','0001-01-01','9999-12-31','MISS','00000','99999999999','99999999999.00','99999999999.000000'),1,0)) AS NUM_REG_DIF,'"&MAX('ID1&5'!K:K)+1&"' AS ID_EXEC, CURRENT_TIMESTAMP() AS TIME_EXEC FROM "&I11, IF(C11="Not applicable",+"SELECT '"&UPPER(B11)&"' AS TABELA, '"&UPPER(C11)&"' AS TIPOLOGIA_TESTE,'"&D11&"' AS TABELA_LT,'N/A' AS TABELA_SIMUL,'"&F11&"' AS CAMPO, "&"'${ref_date}' AS REF_DATE, COUNT(*) AS NUM_REG, SUM(IF(TRIM(CAST(X."&F11&" AS STRING)) IN ('N/A','11111111111','11111111111.00','11111111111.000000','1111-11-11'),1,0)) AS NUM_REG_DIF,'"&MAX('ID1&5'!K:K)+1&"' AS ID_EXEC, CURRENT_TIMESTAMP() AS TIME_EXEC FROM "&I11, IF(C11="Valores extremos",+"SELECT '"&UPPER(B11)&"' AS TABELA, '"&UPPER(C11)&"' AS TIPOLOGIA_TESTE,'"&D11&"' AS TABELA_LT,'N/A' AS TABELA_SIMUL,'"&F11&"' AS CAMPO, "&"'${ref_date}' AS REF_DATE, CAST(MIN("&F11&") AS STRING) AS VALOR_MIN, CAST(MAX("&F11&") AS STRING) AS VALOR_MAX,'"&MAX('ID1&5'!K:K)+1&"' AS ID_EXEC, CURRENT_TIMESTAMP() AS TIME_EXEC FROM "&MID(I11,1,LEN(I11)-2)&" AND CAST("&F11&" AS STRING) NOT IN ('0000-00-00','0001-01-01','9999-12-31','MISS','00000','99999999999','99999999999.00','99999999999.000000','N/A','11111111111','11111111111.00','11111111111.000000','1111-11-11'))X")))))) -> SELECT 'ENTITY' AS TABELA, 'COERÊNCIA' AS TIPOLOGIA_TESTE,'CD_LOAN_TAPES_BCE.LT003_ENTITY' AS TABELA_LT,'BU_LOANTAPE_WORK.LT003_ENTITY' AS TABELA_SIMUL,'DT_BRTH' AS CAMPO, '${ref_date}' AS REF_DATE, COUNT(*) AS NUM_REG, SUM(IF(COALESCE(CAST(X.DT_BRTH AS STRING),'')<>COALESCE(CAST(Y.DT_BRTH_SIMUL AS STRING),'') OR (X.DT_BRTH IS NULL AND Y.DT_BRTH_SIMUL IS NOT NULL ) OR (X.DT_BRTH IS NOT NULL AND Y.DT_BRTH_SIMUL IS NULL),1,0)) AS NUM_REG_DIF,'1' AS ID_EXEC, CURRENT_TIMESTAMP() AS TIME_EXEC FROM (SELECT entty_id, DT_BRTH FROM CD_LOAN_TAPES_BCE.LT003_ENTITY WHERE ref_date='${ref_date}' AND nome_perimetro='Individual Corporativo' AND segmento='ESTR' AND ambito='PM' AND entidade='00100')X INNER JOIN (SELECT entty_id AS entty_id_SIMUL, DT_BRTH AS DT_BRTH_SIMUL FROM BU_LOANTAPE_WORK.LT003_ENTITY WHERE ref_date='${ref_date}' AND nome_perimetro='Individual Corporativo' AND segmento='ESTR' AND ambito='PM' AND entidade='00100')Y ON X.ENTTY_ID=Y.ENTTY_ID_SIMUL | M11: =+"UNION ALL "&L11 -> UNION ALL SELECT 'ENTITY' AS TABELA, 'COERÊNCIA' AS TIPOLOGIA_TESTE,'CD_LOAN_TAPES_BCE.LT003_ENTITY' AS TABELA_LT,'BU_LOANTAPE_WORK.LT003_ENTITY' AS TABELA_SIMUL,'DT_BRTH' AS CAMPO, '${ref_date}' AS REF_DATE, COUNT(*) AS NUM_REG, SUM(IF(COALESCE(CAST(X.DT_BRTH AS STRING),'')<>COALESCE(CAST(Y.DT_BRTH_SIMUL AS STRING),'') OR (X.DT_BRTH IS NULL AND Y.DT_BRTH_SIMUL IS NOT NULL ) OR (X.DT_BRTH IS NOT NULL AND Y.DT_BRTH_SIMUL IS NULL),1,0)) AS NUM_REG_DIF,'1' AS ID_EXEC, CURRENT_TIMESTAMP() AS TIME_EXEC FROM (SELECT entty_id, DT_BRTH FROM CD_LOAN_TAPES_BCE.LT003_ENTITY WHERE ref_date='${ref_date}' AND nome_perimetro='Individual Corporativo' AND segmento='ESTR' AND ambito='PM' AND entidade='00100')X INNER JOIN (SELECT entty_id AS entty_id_SIMUL, DT_BRTH AS DT_BRTH_SIMUL FROM BU_LOANTAPE_WORK.LT003_ENTITY WHERE ref_date='${ref_date}' AND nome_perimetro='Individual Corporativo' AND segmento='ESTR' AND ambito='PM' AND entidade='00100')Y ON X.ENTTY_ID=Y.ENTTY_ID_SIMUL
B12: ENTITY | C12: Coerência | D12: =+UPPER('0. Instruções'!$D$35&"."&VLOOKUP(B12,'0. Instruções'!$C$27:$D$32,2,FALSE)) -> CD_LOAN_TAPES_BCE.LT003_ENTITY | E12: =+UPPER('0. Instruções'!$D$36&"."&VLOOKUP(B12,'0. Instruções'!$C$27:$E$32,3,FALSE)) -> BU_LOANTAPE_WORK.LT003_ENTITY | F12: DT_DFLT_STTS | H12: DATE | I12: ="(SELECT "&VLOOKUP(B12,'0. Instruções'!$C$27:$G$32,4,FALSE)&", "&F12&" FROM "&D12&" WHERE "&'0. Instruções'!$D$42&")X" -> (SELECT entty_id, DT_DFLT_STTS FROM CD_LOAN_TAPES_BCE.LT003_ENTITY WHERE ref_date='${ref_date}' AND nome_perimetro='Individual Corporativo' AND segmento='ESTR' AND ambito='PM' AND entidade='00100')X | J12: ="(SELECT "&VLOOKUP(B12,'0. Instruções'!$C$27:$G$32,4,FALSE)&" AS "&VLOOKUP(B12,'0. Instruções'!$C$27:$G$32,4,FALSE)&"_SIMUL, "&F12&" AS "&F12&"_SIMUL FROM "&E12&" WHERE "&'0. Instruções'!$D$43&")Y" -> (SELECT entty_id AS entty_id_SIMUL, DT_DFLT_STTS AS DT_DFLT_STTS_SIMUL FROM BU_LOANTAPE_WORK.LT003_ENTITY WHERE ref_date='${ref_date}' AND nome_perimetro='Individual Corporativo' AND segmento='ESTR' AND ambito='PM' AND entidade='00100')Y | K12: =+UPPER("ON X."&VLOOKUP(B12,'0. Instruções'!$C$27:$G$32,4,FALSE)&"=Y."&VLOOKUP(B12,'0. Instruções'!$C$27:$G$32,4,FALSE)&"_SIMUL") -> ON X.ENTTY_ID=Y.ENTTY_ID_SIMUL | L12: =+IF(C12="Coerência", +IF(LEFT(G12,5)="FLOAT","SELECT '"&UPPER(B12)&"' AS TABELA, '"&UPPER(C12)&"' AS TIPOLOGIA_TESTE,'"&D12&"' AS TABELA_LT,'"&E12&"' AS TABELA_SIMUL,'"&F12&"' AS CAMPO, "&"'${ref_date}' AS REF_DATE, COUNT(*) AS NUM_REG, SUM(IF((ABS(COALESCE(CAST(X."&F12&" AS DECIMAL(18,6)),0)-COALESCE(CAST(Y."&F12&"_SIMUL AS DECIMAL(18,6)),0))>0.000001) OR (X."&F12&" IS NULL AND Y."&F12&"_SIMUL IS NOT NULL ) OR (X."&F12&" IS NOT NULL AND Y."&F12&"_SIMUL IS NULL),1,0)) AS NUM_REG_DIF,'"&MAX('ID1&5'!K:K)+1&"' AS ID_EXEC, CURRENT_TIMESTAMP() AS TIME_EXEC FROM "&I12&" INNER JOIN "&J12&" "&K12,"SELECT '"&UPPER(B12)&"' AS TABELA, '"&UPPER(C12)&"' AS TIPOLOGIA_TESTE,'"&D12&"' AS TABELA_LT,'"&E12&"' AS TABELA_SIMUL,'"&F12&"' AS CAMPO, "&"'${ref_date}' AS REF_DATE, COUNT(*) AS NUM_REG, SUM(IF(COALESCE(CAST(X."&F12&" AS STRING),'')<>COALESCE(CAST(Y."&F12&"_SIMUL AS STRING),'') OR (X."&F12&" IS NULL AND Y."&F12&"_SIMUL IS NOT NULL ) OR (X."&F12&" IS NOT NULL AND Y."&F12&"_SIMUL IS NULL),1,0)) AS NUM_REG_DIF,'"&MAX('ID1&5'!L:L)+1&"' AS ID_EXEC, CURRENT_TIMESTAMP() AS TIME_EXEC FROM "&I12&" INNER JOIN "&J12&" "&K12), IF(C12="Validade",+IF(G12="Code List","SELECT '"&UPPER(B12)&"' AS TABELA, '"&UPPER(C12)&"' AS TIPOLOGIA_TESTE,'"&D12&"' AS TABELA_LT,'N/A' AS TABELA_SIMUL,'"&F12&"' AS CAMPO, "&"'${ref_date}' AS REF_DATE, COUNT(*) AS NUM_REG, SUM(IF(TRIM(CAST(X."&F12&" AS STRING))='' OR TRIM(CAST(X."&F12&" AS STRING)) IS NULL OR CAST(X."&F12&" AS STRING) NOT "&H12&",1,0)) AS NUM_REG_DIF,'"&MAX('ID1&5'!K:K)+1&"' AS ID_EXEC, CURRENT_TIMESTAMP() AS TIME_EXEC FROM "&I12,"SELECT '"&UPPER(B12)&"' AS TABELA, '"&UPPER(C12)&"' AS TIPOLOGIA_TESTE,'"&D12&"' AS TABELA_LT,'N/A' AS TABELA_SIMUL,'"&F12&"' AS CAMPO, "&"'${ref_date}' AS REF_DATE, COUNT(*) AS NUM_REG, SUM(IF(TRIM(CAST(X."&F12&" AS STRING))='' OR TRIM(CAST(X."&F12&" AS STRING)) IS NULL,1,0)) AS NUM_REG_DIF,'"&MAX('ID1&5'!K:K)+1&"' AS ID_EXEC, CURRENT_TIMESTAMP() AS TIME_EXEC FROM "&I12), IF(C12="Caracteres Especiais",+"SELECT '"&UPPER(B12)&"' AS TABELA, '"&UPPER(C12)&"' AS TIPOLOGIA_TESTE,'"&D12&"' AS TABELA_LT,'N/A' AS TABELA_SIMUL,'"&F12&"' AS CAMPO, "&"'${ref_date}' AS REF_DATE, COUNT(*) AS NUM_REG, SUM(IF(REGEXP_REPLACE(TRIM(CAST(X."&F12&" AS STRING)),'[^a-zA-Z0-9_\\s]','') <>TRIM(CAST(X."&F12&" AS STRING)),1,0)) AS NUM_REG_DIF,'"&MAX('ID1&5'!K:K)+1&"' AS ID_EXEC, CURRENT_TIMESTAMP() AS TIME_EXEC FROM "&I12, IF(C12="Missings",+"SELECT '"&UPPER(B12)&"' AS TABELA, '"&UPPER(C12)&"' AS TIPOLOGIA_TESTE,'"&D12&"' AS TABELA_LT,'N/A' AS TABELA_SIMUL,'"&F12&"' AS CAMPO, "&"'${ref_date}' AS REF_DATE, COUNT(*) AS NUM_REG, SUM(IF(TRIM(CAST(X."&F12&" AS STRING)) IN ('0000-00-00','0001-01-01','9999-12-31','MISS','00000','99999999999','99999999999.00','99999999999.000000'),1,0)) AS NUM_REG_DIF,'"&MAX('ID1&5'!K:K)+1&"' AS ID_EXEC, CURRENT_TIMESTAMP() AS TIME_EXEC FROM "&I12, IF(C12="Not applicable",+"SELECT '"&UPPER(B12)&"' AS TABELA, '"&UPPER(C12)&"' AS TIPOLOGIA_TESTE,'"&D12&"' AS TABELA_LT,'N/A' AS TABELA_SIMUL,'"&F12&"' AS CAMPO, "&"'${ref_date}' AS REF_DATE, COUNT(*) AS NUM_REG, SUM(IF(TRIM(CAST(X."&F12&" AS STRING)) IN ('N/A','11111111111','11111111111.00','11111111111.000000','1111-11-11'),1,0)) AS NUM_REG_DIF,'"&MAX('ID1&5'!K:K)+1&"' AS ID_EXEC, CURRENT_TIMESTAMP() AS TIME_EXEC FROM "&I12, IF(C12="Valores extremos",+"SELECT '"&UPPER(B12)&"' AS TABELA, '"&UPPER(C12)&"' AS TIPOLOGIA_TESTE,'"&D12&"' AS TABELA_LT,'N/A' AS TABELA_SIMUL,'"&F12&"' AS CAMPO, "&"'${ref_date}' AS REF_DATE, CAST(MIN("&F12&") AS STRING) AS VALOR_MIN, CAST(MAX("&F12&") AS STRING) AS VALOR_MAX,'"&MAX('ID1&5'!K:K)+1&"' AS ID_EXEC, CURRENT_TIMESTAMP() AS TIME_EXEC FROM "&MID(I12,1,LEN(I12)-2)&" AND CAST("&F12&" AS STRING) NOT IN ('0000-00-00','0001-01-01','9999-12-31','MISS','00000','99999999999','99999999999.00','99999999999.000000','N/A','11111111111','11111111111.00','11111111111.000000','1111-11-11'))X")))))) -> SELECT 'ENTITY' AS TABELA, 'COERÊNCIA' AS TIPOLOGIA_TESTE,'CD_LOAN_TAPES_BCE.LT003_ENTITY' AS TABELA_LT,'BU_LOANTAPE_WORK.LT003_ENTITY' AS TABELA_SIMUL,'DT_DFLT_STTS' AS CAMPO, '${ref_date}' AS REF_DATE, COUNT(*) AS NUM_REG, SUM(IF(COALESCE(CAST(X.DT_DFLT_STTS AS STRING),'')<>COALESCE(CAST(Y.DT_DFLT_STTS_SIMUL AS STRING),'') OR (X.DT_DFLT_STTS IS NULL AND Y.DT_DFLT_STTS_SIMUL IS NOT NULL ) OR (X.DT_DFLT_STTS IS NOT NULL AND Y.DT_DFLT_STTS_SIMUL IS NULL),1,0)) AS NUM_REG_DIF,'1' AS ID_EXEC, CURRENT_TIMESTAMP() AS TIME_EXEC FROM (SELECT entty_id, DT_DFLT_STTS FROM CD_LOAN_TAPES_BCE.LT003_ENTITY WHERE ref_date='${ref_date}' AND nome_perimetro='Individual Corporativo' AND segmento='ESTR' AND ambito='PM' AND entidade='00100')X INNER JOIN (SELECT entty_id AS entty_id_SIMUL, DT_DFLT_STTS AS DT_DFLT_STTS_SIMUL FROM BU_LOANTAPE_WORK.LT003_ENTITY WHERE ref_date='${ref_date}' AND nome_perimetro='Individual Corporativo' AND segmento='ESTR' AND ambito='PM' AND entidade='00100')Y ON X.ENTTY_ID=Y.ENTTY_ID_SIMUL | M12: =+"UNION ALL "&L12 -> UNION ALL SELECT 'ENTITY' AS TABELA, 'COERÊNCIA' AS TIPOLOGIA_TESTE,'CD_LOAN_TAPES_BCE.LT003_ENTITY' AS TABELA_LT,'BU_LOANTAPE_WORK.LT003_ENTITY' AS TABELA_SIMUL,'DT_DFLT_STTS' AS CAMPO, '${ref_date}' AS REF_DATE, COUNT(*) AS NUM_REG, SUM(IF(COALESCE(CAST(X.DT_DFLT_STTS AS STRING),'')<>COALESCE(CAST(Y.DT_DFLT_STTS_SIMUL AS STRING),'') OR (X.DT_DFLT_STTS IS NULL AND Y.DT_DFLT_STTS_SIMUL IS NOT NULL ) OR (X.DT_DFLT_STTS IS NOT NULL AND Y.DT_DFLT_STTS_SIMUL IS NULL),1,0)) AS NUM_REG_DIF,'1' AS ID_EXEC, CURRENT_TIMESTAMP() AS TIME_EXEC FROM (SELECT entty_id, DT_DFLT_STTS FROM CD_LOAN_TAPES_BCE.LT003_ENTITY WHERE ref_date='${ref_date}' AND nome_perimetro='Individual Corporativo' AND segmento='ESTR' AND ambito='PM' AND entidade='00100')X INNER JOIN (SELECT entty_id AS entty_id_SIMUL, DT_DFLT_STTS AS DT_DFLT_STTS_SIMUL FROM BU_LOANTAPE_WORK.LT003_ENTITY WHERE ref_date='${ref_date}' AND nome_perimetro='Individual Corporativo' AND segmento='ESTR' AND ambito='PM' AND entidade='00100')Y ON X.ENTTY_ID=Y.ENTTY_ID_SIMUL
B13: ENTITY | C13: Coerência | D13: =+UPPER('0. Instruções'!$D$35&"."&VLOOKUP(B13,'0. Instruções'!$C$27:$D$32,2,FALSE)) -> CD_LOAN_TAPES_BCE.LT003_ENTITY | E13: =+UPPER('0. Instruções'!$D$36&"."&VLOOKUP(B13,'0. Instruções'!$C$27:$E$32,3,FALSE)) -> BU_LOANTAPE_WORK.LT003_ENTITY | F13: DT_FNNCL_STTMTS | H13: DATE | I13: ="(SELECT "&VLOOKUP(B13,'0. Instruções'!$C$27:$G$32,4,FALSE)&", "&F13&" FROM "&D13&" WHERE "&'0. Instruções'!$D$42&")X" -> (SELECT entty_id, DT_FNNCL_STTMTS FROM CD_LOAN_TAPES_BCE.LT003_ENTITY WHERE ref_date='${ref_date}' AND nome_perimetro='Individual Corporativo' AND segmento='ESTR' AND ambito='PM' AND entidade='00100')X | J13: ="(SELECT "&VLOOKUP(B13,'0. Instruções'!$C$27:$G$32,4,FALSE)&" AS "&VLOOKUP(B13,'0. Instruções'!$C$27:$G$32,4,FALSE)&"_SIMUL, "&F13&" AS "&F13&"_SIMUL FROM "&E13&" WHERE "&'0. Instruções'!$D$43&")Y" -> (SELECT entty_id AS entty_id_SIMUL, DT_FNNCL_STTMTS AS DT_FNNCL_STTMTS_SIMUL FROM BU_LOANTAPE_WORK.LT003_ENTITY WHERE ref_date='${ref_date}' AND nome_perimetro='Individual Corporativo' AND segmento='ESTR' AND ambito='PM' AND entidade='00100')Y | K13: =+UPPER("ON X."&VLOOKUP(B13,'0. Instruções'!$C$27:$G$32,4,FALSE)&"=Y."&VLOOKUP(B13,'0. Instruções'!$C$27:$G$32,4,FALSE)&"_SIMUL") -> ON X.ENTTY_ID=Y.ENTTY_ID_SIMUL | L13: =+IF(C13="Coerência", +IF(LEFT(G13,5)="FLOAT","SELECT '"&UPPER(B13)&"' AS TABELA, '"&UPPER(C13)&"' AS TIPOLOGIA_TESTE,'"&D13&"' AS TABELA_LT,'"&E13&"' AS TABELA_SIMUL,'"&F13&"' AS CAMPO, "&"'${ref_date}' AS REF_DATE, COUNT(*) AS NUM_REG, SUM(IF((ABS(COALESCE(CAST(X."&F13&" AS DECIMAL(18,6)),0)-COALESCE(CAST(Y."&F13&"_SIMUL AS DECIMAL(18,6)),0))>0.000001) OR (X."&F13&" IS NULL AND Y."&F13&"_SIMUL IS NOT NULL ) OR (X."&F13&" IS NOT NULL AND Y."&F13&"_SIMUL IS NULL),1,0)) AS NUM_REG_DIF,'"&MAX('ID1&5'!K:K)+1&"' AS ID_EXEC, CURRENT_TIMESTAMP() AS TIME_EXEC FROM "&I13&" INNER JOIN "&J13&" "&K13,"SELECT '"&UPPER(B13)&"' AS TABELA, '"&UPPER(C13)&"' AS TIPOLOGIA_TESTE,'"&D13&"' AS TABELA_LT,'"&E13&"' AS TABELA_SIMUL,'"&F13&"' AS CAMPO, "&"'${ref_date}' AS REF_DATE, COUNT(*) AS NUM_REG, SUM(IF(COALESCE(CAST(X."&F13&" AS STRING),'')<>COALESCE(CAST(Y."&F13&"_SIMUL AS STRING),'') OR (X."&F13&" IS NULL AND Y."&F13&"_SIMUL IS NOT NULL ) OR (X."&F13&" IS NOT NULL AND Y."&F13&"_SIMUL IS NULL),1,0)) AS NUM_REG_DIF,'"&MAX('ID1&5'!L:L)+1&"' AS ID_EXEC, CURRENT_TIMESTAMP() AS TIME_EXEC FROM "&I13&" INNER JOIN "&J13&" "&K13), IF(C13="Validade",+IF(G13="Code List","SELECT '"&UPPER(B13)&"' AS TABELA, '"&UPPER(C13)&"' AS TIPOLOGIA_TESTE,'"&D13&"' AS TABELA_LT,'N/A' AS TABELA_SIMUL,'"&F13&"' AS CAMPO, "&"'${ref_date}' AS REF_DATE, COUNT(*) AS NUM_REG, SUM(IF(TRIM(CAST(X."&F13&" AS STRING))='' OR TRIM(CAST(X."&F13&" AS STRING)) IS NULL OR CAST(X."&F13&" AS STRING) NOT "&H13&",1,0)) AS NUM_REG_DIF,'"&MAX('ID1&5'!K:K)+1&"' AS ID_EXEC, CURRENT_TIMESTAMP() AS TIME_EXEC FROM "&I13,"SELECT '"&UPPER(B13)&"' AS TABELA, '"&UPPER(C13)&"' AS TIPOLOGIA_TESTE,'"&D13&"' AS TABELA_LT,'N/A' AS TABELA_SIMUL,'"&F13&"' AS CAMPO, "&"'${ref_date}' AS REF_DATE, COUNT(*) AS NUM_REG, SUM(IF(TRIM(CAST(X."&F13&" AS STRING))='' OR TRIM(CAST(X."&F13&" AS STRING)) IS NULL,1,0)) AS NUM_REG_DIF,'"&MAX('ID1&5'!K:K)+1&"' AS ID_EXEC, CURRENT_TIMESTAMP() AS TIME_EXEC FROM "&I13), IF(C13="Caracteres Especiais",+"SELECT '"&UPPER(B13)&"' AS TABELA, '"&UPPER(C13)&"' AS TIPOLOGIA_TESTE,'"&D13&"' AS TABELA_LT,'N/A' AS TABELA_SIMUL,'"&F13&"' AS CAMPO, "&"'${ref_date}' AS REF_DATE, COUNT(*) AS NUM_REG, SUM(IF(REGEXP_REPLACE(TRIM(CAST(X."&F13&" AS STRING)),'[^a-zA-Z0-9_\\s]','') <>TRIM(CAST(X."&F13&" AS STRING)),1,0)) AS NUM_REG_DIF,'"&MAX('ID1&5'!K:K)+1&"' AS ID_EXEC, CURRENT_TIMESTAMP() AS TIME_EXEC FROM "&I13, IF(C13="Missings",+"SELECT '"&UPPER(B13)&"' AS TABELA, '"&UPPER(C13)&"' AS TIPOLOGIA_TESTE,'"&D13&"' AS TABELA_LT,'N/A' AS TABELA_SIMUL,'"&F13&"' AS CAMPO, "&"'${ref_date}' AS REF_DATE, COUNT(*) AS NUM_REG, SUM(IF(TRIM(CAST(X."&F13&" AS STRING)) IN ('0000-00-00','0001-01-01','9999-12-31','MISS','00000','99999999999','99999999999.00','99999999999.000000'),1,0)) AS NUM_REG_DIF,'"&MAX('ID1&5'!K:K)+1&"' AS ID_EXEC, CURRENT_TIMESTAMP() AS TIME_EXEC FROM "&I13, IF(C13="Not applicable",+"SELECT '"&UPPER(B13)&"' AS TABELA, '"&UPPER(C13)&"' AS TIPOLOGIA_TESTE,'"&D13&"' AS TABELA_LT,'N/A' AS TABELA_SIMUL,'"&F13&"' AS CAMPO, "&"'${ref_date}' AS REF_DATE, COUNT(*) AS NUM_REG, SUM(IF(TRIM(CAST(X."&F13&" AS STRING)) IN ('N/A','11111111111','11111111111.00','11111111111.000000','1111-11-11'),1,0)) AS NUM_REG_DIF,'"&MAX('ID1&5'!K:K)+1&"' AS ID_EXEC, CURRENT_TIMESTAMP() AS TIME_EXEC FROM "&I13, IF(C13="Valores extremos",+"SELECT '"&UPPER(B13)&"' AS TABELA, '"&UPPER(C13)&"' AS TIPOLOGIA_TESTE,'"&D13&"' AS TABELA_LT,'N/A' AS TABELA_SIMUL,'"&F13&"' AS CAMPO, "&"'${ref_date}' AS REF_DATE, CAST(MIN("&F13&") AS STRING) AS VALOR_MIN, CAST(MAX("&F13&") AS STRING) AS VALOR_MAX,'"&MAX('ID1&5'!K:K)+1&"' AS ID_EXEC, CURRENT_TIMESTAMP() AS TIME_EXEC FROM "&MID(I13,1,LEN(I13)-2)&" AND CAST("&F13&" AS STRING) NOT IN ('0000-00-00','0001-01-01','9999-12-31','MISS','00000','99999999999','99999999999.00','99999999999.000000','N/A','11111111111','11111111111.00','11111111111.000000','1111-11-11'))X")))))) -> SELECT 'ENTITY' AS TABELA, 'COERÊNCIA' AS TIPOLOGIA_TESTE,'CD_LOAN_TAPES_BCE.LT003_ENTITY' AS TABELA_LT,'BU_LOANTAPE_WORK.LT003_ENTITY' AS TABELA_SIMUL,'DT_FNNCL_STTMTS' AS CAMPO, '${ref_date}' AS REF_DATE, COUNT(*) AS NUM_REG, SUM(IF(COALESCE(CAST(X.DT_FNNCL_STTMTS AS STRING),'')<>COALESCE(CAST(Y.DT_FNNCL_STTMTS_SIMUL AS STRING),'') OR (X.DT_FNNCL_STTMTS IS NULL AND Y.DT_FNNCL_STTMTS_SIMUL IS NOT NULL ) OR (X.DT_FNNCL_STTMTS IS NOT NULL AND Y.DT_FNNCL_STTMTS_SIMUL IS NULL),1,0)) AS NUM_REG_DIF,'1' AS ID_EXEC, CURRENT_TIMESTAMP() AS TIME_EXEC FROM (SELECT entty_id, DT_FNNCL_STTMTS FROM CD_LOAN_TAPES_BCE.LT003_ENTITY WHERE ref_date='${ref_date}' AND nome_perimetro='Individual Corporativo' AND segmento='ESTR' AND ambito='PM' AND entidade='00100')X INNER JOIN (SELECT entty_id AS entty_id_SIMUL, DT_FNNCL_STTMTS AS DT_FNNCL_STTMTS_SIMUL FROM BU_LOANTAPE_WORK.LT003_ENTITY WHERE ref_date='${ref_date}' AND nome_perimetro='Individual Corporativo' AND segmento='ESTR' AND ambito='PM' AND entidade='00100')Y ON X.ENTTY_ID=Y.ENTTY_ID_SIMUL | M13: =+"UNION ALL "&L13 -> UNION ALL SELECT 'ENTITY' AS TABELA, 'COERÊNCIA' AS TIPOLOGIA_TESTE,'CD_LOAN_TAPES_BCE.LT003_ENTITY' AS TABELA_LT,'BU_LOANTAPE_WORK.LT003_ENTITY' AS TABELA_SIMUL,'DT_FNNCL_STTMTS' AS CAMPO, '${ref_date}' AS REF_DATE, COUNT(*) AS NUM_REG, SUM(IF(COALESCE(CAST(X.DT_FNNCL_STTMTS AS STRING),'')<>COALESCE(CAST(Y.DT_FNNCL_STTMTS_SIMUL AS STRING),'') OR (X.DT_FNNCL_STTMTS IS NULL AND Y.DT_FNNCL_STTMTS_SIMUL IS NOT NULL ) OR (X.DT_FNNCL_STTMTS IS NOT NULL AND Y.DT_FNNCL_STTMTS_SIMUL IS NULL),1,0)) AS NUM_REG_DIF,'1' AS ID_EXEC, CURRENT_TIMESTAMP() AS TIME_EXEC FROM (SELECT entty_id, DT_FNNCL_STTMTS FROM CD_LOAN_TAPES_BCE.LT003_ENTITY WHERE ref_date='${ref_date}' AND nome_perimetro='Individual Corporativo' AND segmento='ESTR' AND ambito='PM' AND entidade='00100')X INNER JOIN (SELECT entty_id AS entty_id_SIMUL, DT_FNNCL_STTMTS AS DT_FNNCL_STTMTS_SIMUL FROM BU_LOANTAPE_WORK.LT003_ENTITY WHERE ref_date='${ref_date}' AND nome_perimetro='Individual Corporativo' AND segmento='ESTR' AND ambito='PM' AND entidade='00100')Y ON X.ENTTY_ID=Y.ENTTY_ID_SIMUL
B14: ENTITY | C14: Coerência | D14: =+UPPER('0. Instruções'!$D$35&"."&VLOOKUP(B14,'0. Instruções'!$C$27:$D$32,2,FALSE)) -> CD_LOAN_TAPES_BCE.LT003_ENTITY | E14: =+UPPER('0. Instruções'!$D$36&"."&VLOOKUP(B14,'0. Instruções'!$C$27:$E$32,3,FALSE)) -> BU_LOANTAPE_WORK.LT003_ENTITY | F14: DT_FNNCL_STTMTS_PRVS | H14: DATE | I14: ="(SELECT "&VLOOKUP(B14,'0. Instruções'!$C$27:$G$32,4,FALSE)&", "&F14&" FROM "&D14&" WHERE "&'0. Instruções'!$D$42&")X" -> (SELECT entty_id, DT_FNNCL_STTMTS_PRVS FROM CD_LOAN_TAPES_BCE.LT003_ENTITY WHERE ref_date='${ref_date}' AND nome_perimetro='Individual Corporativo' AND segmento='ESTR' AND ambito='PM' AND entidade='00100')X | J14: ="(SELECT "&VLOOKUP(B14,'0. Instruções'!$C$27:$G$32,4,FALSE)&" AS "&VLOOKUP(B14,'0. Instruções'!$C$27:$G$32,4,FALSE)&"_SIMUL, "&F14&" AS "&F14&"_SIMUL FROM "&E14&" WHERE "&'0. Instruções'!$D$43&")Y" -> (SELECT entty_id AS entty_id_SIMUL, DT_FNNCL_STTMTS_PRVS AS DT_FNNCL_STTMTS_PRVS_SIMUL FROM BU_LOANTAPE_WORK.LT003_ENTITY WHERE ref_date='${ref_date}' AND nome_perimetro='Individual Corporativo' AND segmento='ESTR' AND ambito='PM' AND entidade='00100')Y | K14: =+UPPER("ON X."&VLOOKUP(B14,'0. Instruções'!$C$27:$G$32,4,FALSE)&"=Y."&VLOOKUP(B14,'0. Instruções'!$C$27:$G$32,4,FALSE)&"_SIMUL") -> ON X.ENTTY_ID=Y.ENTTY_ID_SIMUL | L14: =+IF(C14="Coerência", +IF(LEFT(G14,5)="FLOAT","SELECT '"&UPPER(B14)&"' AS TABELA, '"&UPPER(C14)&"' AS TIPOLOGIA_TESTE,'"&D14&"' AS TABELA_LT,'"&E14&"' AS TABELA_SIMUL,'"&F14&"' AS CAMPO, "&"'${ref_date}' AS REF_DATE, COUNT(*) AS NUM_REG, SUM(IF((ABS(COALESCE(CAST(X."&F14&" AS DECIMAL(18,6)),0)-COALESCE(CAST(Y."&F14&"_SIMUL AS DECIMAL(18,6)),0))>0.000001) OR (X."&F14&" IS NULL AND Y."&F14&"_SIMUL IS NOT NULL ) OR (X."&F14&" IS NOT NULL AND Y."&F14&"_SIMUL IS NULL),1,0)) AS NUM_REG_DIF,'"&MAX('ID1&5'!K:K)+1&"' AS ID_EXEC, CURRENT_TIMESTAMP() AS TIME_EXEC FROM "&I14&" INNER JOIN "&J14&" "&K14,"SELECT '"&UPPER(B14)&"' AS TABELA, '"&UPPER(C14)&"' AS TIPOLOGIA_TESTE,'"&D14&"' AS TABELA_LT,'"&E14&"' AS TABELA_SIMUL,'"&F14&"' AS CAMPO, "&"'${ref_date}' AS REF_DATE, COUNT(*) AS NUM_REG, SUM(IF(COALESCE(CAST(X."&F14&" AS STRING),'')<>COALESCE(CAST(Y."&F14&"_SIMUL AS STRING),'') OR (X."&F14&" IS NULL AND Y."&F14&"_SIMUL IS NOT NULL ) OR (X."&F14&" IS NOT NULL AND Y."&F14&"_SIMUL IS NULL),1,0)) AS NUM_REG_DIF,'"&MAX('ID1&5'!L:L)+1&"' AS ID_EXEC, CURRENT_TIMESTAMP() AS TIME_EXEC FROM "&I14&" INNER JOIN "&J14&" "&K14), IF(C14="Validade",+IF(G14="Code List","SELECT '"&UPPER(B14)&"' AS TABELA, '"&UPPER(C14)&"' AS TIPOLOGIA_TESTE,'"&D14&"' AS TABELA_LT,'N/A' AS TABELA_SIMUL,'"&F14&"' AS CAMPO, "&"'${ref_date}' AS REF_DATE, COUNT(*) AS NUM_REG, SUM(IF(TRIM(CAST(X."&F14&" AS STRING))='' OR TRIM(CAST(X."&F14&" AS STRING)) IS NULL OR CAST(X."&F14&" AS STRING) NOT "&H14&",1,0)) AS NUM_REG_DIF,'"&MAX('ID1&5'!K:K)+1&"' AS ID_EXEC, CURRENT_TIMESTAMP() AS TIME_EXEC FROM "&I14,"SELECT '"&UPPER(B14)&"' AS TABELA, '"&UPPER(C14)&"' AS TIPOLOGIA_TESTE,'"&D14&"' AS TABELA_LT,'N/A' AS TABELA_SIMUL,'"&F14&"' AS CAMPO, "&"'${ref_date}' AS REF_DATE, COUNT(*) AS NUM_REG, SUM(IF(TRIM(CAST(X."&F14&" AS STRING))='' OR TRIM(CAST(X."&F14&" AS STRING)) IS NULL,1,0)) AS NUM_REG_DIF,'"&MAX('ID1&5'!K:K)+1&"' AS ID_EXEC, CURRENT_TIMESTAMP() AS TIME_EXEC FROM "&I14), IF(C14="Caracteres Especiais",+"SELECT '"&UPPER(B14)&"' AS TABELA, '"&UPPER(C14)&"' AS TIPOLOGIA_TESTE,'"&D14&"' AS TABELA_LT,'N/A' AS TABELA_SIMUL,'"&F14&"' AS CAMPO, "&"'${ref_date}' AS REF_DATE, COUNT(*) AS NUM_REG, SUM(IF(REGEXP_REPLACE(TRIM(CAST(X."&F14&" AS STRING)),'[^a-zA-Z0-9_\\s]','') <>TRIM(CAST(X."&F14&" AS STRING)),1,0)) AS NUM_REG_DIF,'"&MAX('ID1&5'!K:K)+1&"' AS ID_EXEC, CURRENT_TIMESTAMP() AS TIME_EXEC FROM "&I14, IF(C14="Missings",+"SELECT '"&UPPER(B14)&"' AS TABELA, '"&UPPER(C14)&"' AS TIPOLOGIA_TESTE,'"&D14&"' AS TABELA_LT,'N/A' AS TABELA_SIMUL,'"&F14&"' AS CAMPO, "&"'${ref_date}' AS REF_DATE, COUNT(*) AS NUM_REG, SUM(IF(TRIM(CAST(X."&F14&" AS STRING)) IN ('0000-00-00','0001-01-01','9999-12-31','MISS','00000','99999999999','99999999999.00','99999999999.000000'),1,0)) AS NUM_REG_DIF,'"&MAX('ID1&5'!K:K)+1&"' AS ID_EXEC, CURRENT_TIMESTAMP() AS TIME_EXEC FROM "&I14, IF(C14="Not applicable",+"SELECT '"&UPPER(B14)&"' AS TABELA, '"&UPPER(C14)&"' AS TIPOLOGIA_TESTE,'"&D14&"' AS TABELA_LT,'N/A' AS TABELA_SIMUL,'"&F14&"' AS CAMPO, "&"'${ref_date}' AS REF_DATE, COUNT(*) AS NUM_REG, SUM(IF(TRIM(CAST(X."&F14&" AS STRING)) IN ('N/A','11111111111','11111111111.00','11111111111.000000','1111-11-11'),1,0)) AS NUM_REG_DIF,'"&MAX('ID1&5'!K:K)+1&"' AS ID_EXEC, CURRENT_TIMESTAMP() AS TIME_EXEC FROM "&I14, IF(C14="Valores extremos",+"SELECT '"&UPPER(B14)&"' AS TABELA, '"&UPPER(C14)&"' AS TIPOLOGIA_TESTE,'"&D14&"' AS TABELA_LT,'N/A' AS TABELA_SIMUL,'"&F14&"' AS CAMPO, "&"'${ref_date}' AS REF_DATE, CAST(MIN("&F14&") AS STRING) AS VALOR_MIN, CAST(MAX("&F14&") AS STRING) AS VALOR_MAX,'"&MAX('ID1&5'!K:K)+1&"' AS ID_EXEC, CURRENT_TIMESTAMP() AS TIME_EXEC FROM "&MID(I14,1,LEN(I14)-2)&" AND CAST("&F14&" AS STRING) NOT IN ('0000-00-00','0001-01-01','9999-12-31','MISS','00000','99999999999','99999999999.00','99999999999.000000','N/A','11111111111','11111111111.00','11111111111.000000','1111-11-11'))X")))))) -> SELECT 'ENTITY' AS TABELA, 'COERÊNCIA' AS TIPOLOGIA_TESTE,'CD_LOAN_TAPES_BCE.LT003_ENTITY' AS TABELA_LT,'BU_LOANTAPE_WORK.LT003_ENTITY' AS TABELA_SIMUL,'DT_FNNCL_STTMTS_PRVS' AS CAMPO, '${ref_date}' AS REF_DATE, COUNT(*) AS NUM_REG, SUM(IF(COALESCE(CAST(X.DT_FNNCL_STTMTS_PRVS AS STRING),'')<>COALESCE(CAST(Y.DT_FNNCL_STTMTS_PRVS_SIMUL AS STRING),'') OR (X.DT_FNNCL_STTMTS_PRVS IS NULL AND Y.DT_FNNCL_STTMTS_PRVS_SIMUL IS NOT NULL ) OR (X.DT_FNNCL_STTMTS_PRVS IS NOT NULL AND Y.DT_FNNCL_STTMTS_PRVS_SIMUL IS NULL),1,0)) AS NUM_REG_DIF,'1' AS ID_EXEC, CURRENT_TIMESTAMP() AS TIME_EXEC FROM (SELECT entty_id, DT_FNNCL_STTMTS_PRVS FROM CD_LOAN_TAPES_BCE.LT003_ENTITY WHERE ref_date='${ref_date}' AND nome_perimetro='Individual Corporativo' AND segmento='ESTR' AND ambito='PM' AND entidade='00100')X INNER JOIN (SELECT entty_id AS entty_id_SIMUL, DT_FNNCL_STTMTS_PRVS AS DT_FNNCL_STTMTS_PRVS_SIMUL FROM BU_LOANTAPE_WORK.LT003_ENTITY WHERE ref_date='${ref_date}' AND nome_perimetro='Individual Corporativo' AND segmento='ESTR' AND ambito='PM' AND entidade='00100')Y ON X.ENTTY_ID=Y.ENTTY_ID_SIMUL | M14: =+"UNION ALL "&L14 -> UNION ALL SELECT 'ENTITY' AS TABELA, 'COERÊNCIA' AS TIPOLOGIA_TESTE,'CD_LOAN_TAPES_BCE.LT003_ENTITY' AS TABELA_LT,'BU_LOANTAPE_WORK.LT003_ENTITY' AS TABELA_SIMUL,'DT_FNNCL_STTMTS_PRVS' AS CAMPO, '${ref_date}' AS REF_DATE, COUNT(*) AS NUM_REG, SUM(IF(COALESCE(CAST(X.DT_FNNCL_STTMTS_PRVS AS STRING),'')<>COALESCE(CAST(Y.DT_FNNCL_STTMTS_PRVS_SIMUL AS STRING),'') OR (X.DT_FNNCL_STTMTS_PRVS IS NULL AND Y.DT_FNNCL_STTMTS_PRVS_SIMUL IS NOT NULL ) OR (X.DT_FNNCL_STTMTS_PRVS IS NOT NULL AND Y.DT_FNNCL_STTMTS_PRVS_SIMUL IS NULL),1,0)) AS NUM_REG_DIF,'1' AS ID_EXEC, CURRENT_TIMESTAMP() AS TIME_EXEC FROM (SELECT entty_id, DT_FNNCL_STTMTS_PRVS FROM CD_LOAN_TAPES_BCE.LT003_ENTITY WHERE ref_date='${ref_date}' AND nome_perimetro='Individual Corporativo' AND segmento='ESTR' AND ambito='PM' AND entidade='00100')X INNER JOIN (SELECT entty_id AS entty_id_SIMUL, DT_FNNCL_STTMTS_PRVS AS DT_FNNCL_STTMTS_PRVS_SIMUL FROM BU_LOANTAPE_WORK.LT003_ENTITY WHERE ref_date='${ref_date}' AND nome_perimetro='Individual Corporativo' AND segmento='ESTR' AND ambito='PM' AND entidade='00100')Y ON X.ENTTY_ID=Y.ENTTY_ID_SIMUL
B15: ENTITY | C15: Coerência | D15: =+UPPER('0. Instruções'!$D$35&"."&VLOOKUP(B15,'0. Instruções'!$C$27:$D$32,2,FALSE)) -> CD_LOAN_TAPES_BCE.LT003_ENTITY | E15: =+UPPER('0. Instruções'!$D$36&"."&VLOOKUP(B15,'0. Instruções'!$C$27:$E$32,3,FALSE)) -> BU_LOANTAPE_WORK.LT003_ENTITY | F15: DT_INTTN_LGL_PRCDNGS_LE | H15: DATE | I15: ="(SELECT "&VLOOKUP(B15,'0. Instruções'!$C$27:$G$32,4,FALSE)&", "&F15&" FROM "&D15&" WHERE "&'0. Instruções'!$D$42&")X" -> (SELECT entty_id, DT_INTTN_LGL_PRCDNGS_LE FROM CD_LOAN_TAPES_BCE.LT003_ENTITY WHERE ref_date='${ref_date}' AND nome_perimetro='Individual Corporativo' AND segmento='ESTR' AND ambito='PM' AND entidade='00100')X | J15: ="(SELECT "&VLOOKUP(B15,'0. Instruções'!$C$27:$G$32,4,FALSE)&" AS "&VLOOKUP(B15,'0. Instruções'!$C$27:$G$32,4,FALSE)&"_SIMUL, "&F15&" AS "&F15&"_SIMUL FROM "&E15&" WHERE "&'0. Instruções'!$D$43&")Y" -> (SELECT entty_id AS entty_id_SIMUL, DT_INTTN_LGL_PRCDNGS_LE AS DT_INTTN_LGL_PRCDNGS_LE_SIMUL FROM BU_LOANTAPE_WORK.LT003_ENTITY WHERE ref_date='${ref_date}' AND nome_perimetro='Individual Corporativo' AND segmento='ESTR' AND ambito='PM' AND entidade='00100')Y | K15: =+UPPER("ON X."&VLOOKUP(B15,'0. Instruções'!$C$27:$G$32,4,FALSE)&"=Y."&VLOOKUP(B15,'0. Instruções'!$C$27:$G$32,4,FALSE)&"_SIMUL") -> ON X.ENTTY_ID=Y.ENTTY_ID_SIMUL | L15: =+IF(C15="Coerência", +IF(LEFT(G15,5)="FLOAT","SELECT '"&UPPER(B15)&"' AS TABELA, '"&UPPER(C15)&"' AS TIPOLOGIA_TESTE,'"&D15&"' AS TABELA_LT,'"&E15&"' AS TABELA_SIMUL,'"&F15&"' AS CAMPO, "&"'${ref_date}' AS REF_DATE, COUNT(*) AS NUM_REG, SUM(IF((ABS(COALESCE(CAST(X."&F15&" AS DECIMAL(18,6)),0)-COALESCE(CAST(Y."&F15&"_SIMUL AS DECIMAL(18,6)),0))>0.000001) OR (X."&F15&" IS NULL AND Y."&F15&"_SIMUL IS NOT NULL ) OR (X."&F15&" IS NOT NULL AND Y."&F15&"_SIMUL IS NULL),1,0)) AS NUM_REG_DIF,'"&MAX('ID1&5'!K:K)+1&"' AS ID_EXEC, CURRENT_TIMESTAMP() AS TIME_EXEC FROM "&I15&" INNER JOIN "&J15&" "&K15,"SELECT '"&UPPER(B15)&"' AS TABELA, '"&UPPER(C15)&"' AS TIPOLOGIA_TESTE,'"&D15&"' AS TABELA_LT,'"&E15&"' AS TABELA_SIMUL,'"&F15&"' AS CAMPO, "&"'${ref_date}' AS REF_DATE, COUNT(*) AS NUM_REG, SUM(IF(COALESCE(CAST(X."&F15&" AS STRING),'')<>COALESCE(CAST(Y."&F15&"_SIMUL AS STRING),'') OR (X."&F15&" IS NULL AND Y."&F15&"_SIMUL IS NOT NULL ) OR (X."&F15&" IS NOT NULL AND Y."&F15&"_SIMUL IS NULL),1,0)) AS NUM_REG_DIF,'"&MAX('ID1&5'!L:L)+1&"' AS ID_EXEC, CURRENT_TIMESTAMP() AS TIME_EXEC FROM "&I15&" INNER JOIN "&J15&" "&K15), IF(C15="Validade",+IF(G15="Code List","SELECT '"&UPPER(B15)&"' AS TABELA, '"&UPPER(C15)&"' AS TIPOLOGIA_TESTE,'"&D15&"' AS TABELA_LT,'N/A' AS TABELA_SIMUL,'"&F15&"' AS CAMPO, "&"'${ref_date}' AS REF_DATE, COUNT(*) AS NUM_REG, SUM(IF(TRIM(CAST(X."&F15&" AS STRING))='' OR TRIM(CAST(X."&F15&" AS STRING)) IS NULL OR CAST(X."&F15&" AS STRING) NOT "&H15&",1,0)) AS NUM_REG_DIF,'"&MAX('ID1&5'!K:K)+1&"' AS ID_EXEC, CURRENT_TIMESTAMP() AS TIME_EXEC FROM "&I15,"SELECT '"&UPPER(B15)&"' AS TABELA, '"&UPPER(C15)&"' AS TIPOLOGIA_TESTE,'"&D15&"' AS TABELA_LT,'N/A' AS TABELA_SIMUL,'"&F15&"' AS CAMPO, "&"'${ref_date}' AS REF_DATE, COUNT(*) AS NUM_REG, SUM(IF(TRIM(CAST(X."&F15&" AS STRING))='' OR TRIM(CAST(X."&F15&" AS STRING)) IS NULL,1,0)) AS NUM_REG_DIF,'"&MAX('ID1&5'!K:K)+1&"' AS ID_EXEC, CURRENT_TIMESTAMP() AS TIME_EXEC FROM "&I15), IF(C15="Caracteres Especiais",+"SELECT '"&UPPER(B15)&"' AS TABELA, '"&UPPER(C15)&"' AS TIPOLOGIA_TESTE,'"&D15&"' AS TABELA_LT,'N/A' AS TABELA_SIMUL,'"&F15&"' AS CAMPO, "&"'${ref_date}' AS REF_DATE, COUNT(*) AS NUM_REG, SUM(IF(REGEXP_REPLACE(TRIM(CAST(X."&F15&" AS STRING)),'[^a-zA-Z0-9_\\s]','') <>TRIM(CAST(X."&F15&" AS STRING)),1,0)) AS NUM_REG_DIF,'"&MAX('ID1&5'!K:K)+1&"' AS ID_EXEC, CURRENT_TIMESTAMP() AS TIME_EXEC FROM "&I15, IF(C15="Missings",+"SELECT '"&UPPER(B15)&"' AS TABELA, '"&UPPER(C15)&"' AS TIPOLOGIA_TESTE,'"&D15&"' AS TABELA_LT,'N/A' AS TABELA_SIMUL,'"&F15&"' AS CAMPO, "&"'${ref_date}' AS REF_DATE, COUNT(*) AS NUM_REG, SUM(IF(TRIM(CAST(X."&F15&" AS STRING)) IN ('0000-00-00','0001-01-01','9999-12-31','MISS','00000','99999999999','99999999999.00','99999999999.000000'),1,0)) AS NUM_REG_DIF,'"&MAX('ID1&5'!K:K)+1&"' AS ID_EXEC, CURRENT_TIMESTAMP() AS TIME_EXEC FROM "&I15, IF(C15="Not applicable",+"SELECT '"&UPPER(B15)&"' AS TABELA, '"&UPPER(C15)&"' AS TIPOLOGIA_TESTE,'"&D15&"' AS TABELA_LT,'N/A' AS TABELA_SIMUL,'"&F15&"' AS CAMPO, "&"'${ref_date}' AS REF_DATE, COUNT(*) AS NUM_REG, SUM(IF(TRIM(CAST(X."&F15&" AS STRING)) IN ('N/A','11111111111','11111111111.00','11111111111.000000','1111-11-11'),1,0)) AS NUM_REG_DIF,'"&MAX('ID1&5'!K:K)+1&"' AS ID_EXEC, CURRENT_TIMESTAMP() AS TIME_EXEC FROM "&I15, IF(C15="Valores extremos",+"SELECT '"&UPPER(B15)&"' AS TABELA, '"&UPPER(C15)&"' AS TIPOLOGIA_TESTE,'"&D15&"' AS TABELA_LT,'N/A' AS TABELA_SIMUL,'"&F15&"' AS CAMPO, "&"'${ref_date}' AS REF_DATE, CAST(MIN("&F15&") AS STRING) AS VALOR_MIN, CAST(MAX("&F15&") AS STRING) AS VALOR_MAX,'"&MAX('ID1&5'!K:K)+1&"' AS ID_EXEC, CURRENT_TIMESTAMP() AS TIME_EXEC FROM "&MID(I15,1,LEN(I15)-2)&" AND CAST("&F15&" AS STRING) NOT IN ('0000-00-00','0001-01-01','9999-12-31','MISS','00000','99999999999','99999999999.00','99999999999.000000','N/A','11111111111','11111111111.00','11111111111.000000','1111-11-11'))X")))))) -> SELECT 'ENTITY' AS TABELA, 'COERÊNCIA' AS TIPOLOGIA_TESTE,'CD_LOAN_TAPES_BCE.LT003_ENTITY' AS TABELA_LT,'BU_LOANTAPE_WORK.LT003_ENTITY' AS TABELA_SIMUL,'DT_INTTN_LGL_PRCDNGS_LE' AS CAMPO, '${ref_date}' AS REF_DATE, COUNT(*) AS NUM_REG, SUM(IF(COALESCE(CAST(X.DT_INTTN_LGL_PRCDNGS_LE AS STRING),'')<>COALESCE(CAST(Y.DT_INTTN_LGL_PRCDNGS_LE_SIMUL AS STRING),'') OR (X.DT_INTTN_LGL_PRCDNGS_LE IS NULL AND Y.DT_INTTN_LGL_PRCDNGS_LE_SIMUL IS NOT NULL ) OR (X.DT_INTTN_LGL_PRCDNGS_LE IS NOT NULL AND Y.DT_INTTN_LGL_PRCDNGS_LE_SIMUL IS NULL),1,0)) AS NUM_REG_DIF,'1' AS ID_EXEC, CURRENT_TIMESTAMP() AS TIME_EXEC FROM (SELECT entty_id, DT_INTTN_LGL_PRCDNGS_LE FROM CD_LOAN_TAPES_BCE.LT003_ENTITY WHERE ref_date='${ref_date}' AND nome_perimetro='Individual Corporativo' AND segmento='ESTR' AND ambito='PM' AND entidade='00100')X INNER JOIN (SELECT entty_id AS entty_id_SIMUL, DT_INTTN_LGL_PRCDNGS_LE AS DT_INTTN_LGL_PRCDNGS_LE_SIMUL FROM BU_LOANTAPE_WORK.LT003_ENTITY WHERE ref_date='${ref_date}' AND nome_perimetro='Individual Corporativo' AND segmento='ESTR' AND ambito='PM' AND entidade='00100')Y ON X.ENTTY_ID=Y.ENTTY_ID_SIMUL | M15: =+"UNION ALL "&L15 -> UNION ALL SELECT 'ENTITY' AS TABELA, 'COERÊNCIA' AS TIPOLOGIA_TESTE,'CD_LOAN_TAPES_BCE.LT003_ENTITY' AS TABELA_LT,'BU_LOANTAPE_WORK.LT003_ENTITY' AS TABELA_SIMUL,'DT_INTTN_LGL_PRCDNGS_LE' AS CAMPO, '${ref_date}' AS REF_DATE, COUNT(*) AS NUM_REG, SUM(IF(COALESCE(CAST(X.DT_INTTN_LGL_PRCDNGS_LE AS STRING),'')<>COALESCE(CAST(Y.DT_INTTN_LGL_PRCDNGS_LE_SIMUL AS STRING),'') OR (X.DT_INTTN_LGL_PRCDNGS_LE IS NULL AND Y.DT_INTTN_LGL_PRCDNGS_LE_SIMUL IS NOT NULL ) OR (X.DT_INTTN_LGL_PRCDNGS_LE IS NOT NULL AND Y.DT_INTTN_LGL_PRCDNGS_LE_SIMUL IS NULL),1,0)) AS NUM_REG_DIF,'1' AS ID_EXEC, CURRENT_TIMESTAMP() AS TIME_EXEC FROM (SELECT entty_id, DT_INTTN_LGL_PRCDNGS_LE FROM CD_LOAN_TAPES_BCE.LT003_ENTITY WHERE ref_date='${ref_date}' AND nome_perimetro='Individual Corporativo' AND segmento='ESTR' AND ambito='PM' AND entidade='00100')X INNER JOIN (SELECT entty_id AS entty_id_SIMUL, DT_INTTN_LGL_PRCDNGS_LE AS DT_INTTN_LGL_PRCDNGS_LE_SIMUL FROM BU_LOANTAPE_WORK.LT003_ENTITY WHERE ref_date='${ref_date}' AND nome_perimetro='Individual Corporativo' AND segmento='ESTR' AND ambito='PM' AND entidade='00100')Y ON X.ENTTY_ID=Y.ENTTY_ID_SIMUL
B16: ENTITY | C16: Coerência | D16: =+UPPER('0. Instruções'!$D$35&"."&VLOOKUP(B16,'0. Instruções'!$C$27:$D$32,2,FALSE)) -> CD_LOAN_TAPES_BCE.LT003_ENTITY | E16: =+UPPER('0. Instruções'!$D$36&"."&VLOOKUP(B16,'0. Instruções'!$C$27:$E$32,3,FALSE)) -> BU_LOANTAPE_WORK.LT003_ENTITY | F16: DT_PRFRMNG_STTS_LE | H16: DATE | I16: ="(SELECT "&VLOOKUP(B16,'0. Instruções'!$C$27:$G$32,4,FALSE)&", "&F16&" FROM "&D16&" WHERE "&'0. Instruções'!$D$42&")X" -> (SELECT entty_id, DT_PRFRMNG_STTS_LE FROM CD_LOAN_TAPES_BCE.LT003_ENTITY WHERE ref_date='${ref_date}' AND nome_perimetro='Individual Corporativo' AND segmento='ESTR' AND ambito='PM' AND entidade='00100')X | J16: ="(SELECT "&VLOOKUP(B16,'0. Instruções'!$C$27:$G$32,4,FALSE)&" AS "&VLOOKUP(B16,'0. Instruções'!$C$27:$G$32,4,FALSE)&"_SIMUL, "&F16&" AS "&F16&"_SIMUL FROM "&E16&" WHERE "&'0. Instruções'!$D$43&")Y" -> (SELECT entty_id AS entty_id_SIMUL, DT_PRFRMNG_STTS_LE AS DT_PRFRMNG_STTS_LE_SIMUL FROM BU_LOANTAPE_WORK.LT003_ENTITY WHERE ref_date='${ref_date}' AND nome_perimetro='Individual Corporativo' AND segmento='ESTR' AND ambito='PM' AND entidade='00100')Y | K16: =+UPPER("ON X."&VLOOKUP(B16,'0. Instruções'!$C$27:$G$32,4,FALSE)&"=Y."&VLOOKUP(B16,'0. Instruções'!$C$27:$G$32,4,FALSE)&"_SIMUL") -> ON X.ENTTY_ID=Y.ENTTY_ID_SIMUL | L16: =+IF(C16="Coerência", +IF(LEFT(G16,5)="FLOAT","SELECT '"&UPPER(B16)&"' AS TABELA, '"&UPPER(C16)&"' AS TIPOLOGIA_TESTE,'"&D16&"' AS TABELA_LT,'"&E16&"' AS TABELA_SIMUL,'"&F16&"' AS CAMPO, "&"'${ref_date}' AS REF_DATE, COUNT(*) AS NUM_REG, SUM(IF((ABS(COALESCE(CAST(X."&F16&" AS DECIMAL(18,6)),0)-COALESCE(CAST(Y."&F16&"_SIMUL AS DECIMAL(18,6)),0))>0.000001) OR (X."&F16&" IS NULL AND Y."&F16&"_SIMUL IS NOT NULL ) OR (X."&F16&" IS NOT NULL AND Y."&F16&"_SIMUL IS NULL),1,0)) AS NUM_REG_DIF,'"&MAX('ID1&5'!K:K)+1&"' AS ID_EXEC, CURRENT_TIMESTAMP() AS TIME_EXEC FROM "&I16&" INNER JOIN "&J16&" "&K16,"SELECT '"&UPPER(B16)&"' AS TABELA, '"&UPPER(C16)&"' AS TIPOLOGIA_TESTE,'"&D16&"' AS TABELA_LT,'"&E16&"' AS TABELA_SIMUL,'"&F16&"' AS CAMPO, "&"'${ref_date}' AS REF_DATE, COUNT(*) AS NUM_REG, SUM(IF(COALESCE(CAST(X."&F16&" AS STRING),'')<>COALESCE(CAST(Y."&F16&"_SIMUL AS STRING),'') OR (X."&F16&" IS NULL AND Y."&F16&"_SIMUL IS NOT NULL ) OR (X."&F16&" IS NOT NULL AND Y."&F16&"_SIMUL IS NULL),1,0)) AS NUM_REG_DIF,'"&MAX('ID1&5'!L:L)+1&"' AS ID_EXEC, CURRENT_TIMESTAMP() AS TIME_EXEC FROM "&I16&" INNER JOIN "&J16&" "&K16), IF(C16="Validade",+IF(G16="Code List","SELECT '"&UPPER(B16)&"' AS TABELA, '"&UPPER(C16)&"' AS TIPOLOGIA_TESTE,'"&D16&"' AS TABELA_LT,'N/A' AS TABELA_SIMUL,'"&F16&"' AS CAMPO, "&"'${ref_date}' AS REF_DATE, COUNT(*) AS NUM_REG, SUM(IF(TRIM(CAST(X."&F16&" AS STRING))='' OR TRIM(CAST(X."&F16&" AS STRING)) IS NULL OR CAST(X."&F16&" AS STRING) NOT "&H16&",1,0)) AS NUM_REG_DIF,'"&MAX('ID1&5'!K:K)+1&"' AS ID_EXEC, CURRENT_TIMESTAMP() AS TIME_EXEC FROM "&I16,"SELECT '"&UPPER(B16)&"' AS TABELA, '"&UPPER(C16)&"' AS TIPOLOGIA_TESTE,'"&D16&"' AS TABELA_LT,'N/A' AS TABELA_SIMUL,'"&F16&"' AS CAMPO, "&"'${ref_date}' AS REF_DATE, COUNT(*) AS NUM_REG, SUM(IF(TRIM(CAST(X."&F16&" AS STRING))='' OR TRIM(CAST(X."&F16&" AS STRING)) IS NULL,1,0)) AS NUM_REG_DIF,'"&MAX('ID1&5'!K:K)+1&"' AS ID_EXEC, CURRENT_TIMESTAMP() AS TIME_EXEC FROM "&I16), IF(C16="Caracteres Especiais",+"SELECT '"&UPPER(B16)&"' AS TABELA, '"&UPPER(C16)&"' AS TIPOLOGIA_TESTE,'"&D16&"' AS TABELA_LT,'N/A' AS TABELA_SIMUL,'"&F16&"' AS CAMPO, "&"'${ref_date}' AS REF_DATE, COUNT(*) AS NUM_REG, SUM(IF(REGEXP_REPLACE(TRIM(CAST(X."&F16&" AS STRING)),'[^a-zA-Z0-9_\\s]','') <>TRIM(CAST(X."&F16&" AS STRING)),1,0)) AS NUM_REG_DIF,'"&MAX('ID1&5'!K:K)+1&"' AS ID_EXEC, CURRENT_TIMESTAMP() AS TIME_EXEC FROM "&I16, IF(C16="Missings",+"SELECT '"&UPPER(B16)&"' AS TABELA, '"&UPPER(C16)&"' AS TIPOLOGIA_TESTE,'"&D16&"' AS TABELA_LT,'N/A' AS TABELA_SIMUL,'"&F16&"' AS CAMPO, "&"'${ref_date}' AS REF_DATE, COUNT(*) AS NUM_REG, SUM(IF(TRIM(CAST(X."&F16&" AS STRING)) IN ('0000-00-00','0001-01-01','9999-12-31','MISS','00000','99999999999','99999999999.00','99999999999.000000'),1,0)) AS NUM_REG_DIF,'"&MAX('ID1&5'!K:K)+1&"' AS ID_EXEC, CURRENT_TIMESTAMP() AS TIME_EXEC FROM "&I16, IF(C16="Not applicable",+"SELECT '"&UPPER(B16)&"' AS TABELA, '"&UPPER(C16)&"' AS TIPOLOGIA_TESTE,'"&D16&"' AS TABELA_LT,'N/A' AS TABELA_SIMUL,'"&F16&"' AS CAMPO, "&"'${ref_date}' AS REF_DATE, COUNT(*) AS NUM_REG, SUM(IF(TRIM(CAST(X."&F16&" AS STRING)) IN ('N/A','11111111111','11111111111.00','11111111111.000000','1111-11-11'),1,0)) AS NUM_REG_DIF,'"&MAX('ID1&5'!K:K)+1&"' AS ID_EXEC, CURRENT_TIMESTAMP() AS TIME_EXEC FROM "&I16, IF(C16="Valores extremos",+"SELECT '"&UPPER(B16)&"' AS TABELA, '"&UPPER(C16)&"' AS TIPOLOGIA_TESTE,'"&D16&"' AS TABELA_LT,'N/A' AS TABELA_SIMUL,'"&F16&"' AS CAMPO, "&"'${ref_date}' AS REF_DATE, CAST(MIN("&F16&") AS STRING) AS VALOR_MIN, CAST(MAX("&F16&") AS STRING) AS VALOR_MAX,'"&MAX('ID1&5'!K:K)+1&"' AS ID_EXEC, CURRENT_TIMESTAMP() AS TIME_EXEC FROM "&MID(I16,1,LEN(I16)-2)&" AND CAST("&F16&" AS STRING) NOT IN ('0000-00-00','0001-01-01','9999-12-31','MISS','00000','99999999999','99999999999.00','99999999999.000000','N/A','11111111111','11111111111.00','11111111111.000000','1111-11-11'))X")))))) -> SELECT 'ENTITY' AS TABELA, 'COERÊNCIA' AS TIPOLOGIA_TESTE,'CD_LOAN_TAPES_BCE.LT003_ENTITY' AS TABELA_LT,'BU_LOANTAPE_WORK.LT003_ENTITY' AS TABELA_SIMUL,'DT_PRFRMNG_STTS_LE' AS CAMPO, '${ref_date}' AS REF_DATE, COUNT(*) AS NUM_REG, SUM(IF(COALESCE(CAST(X.DT_PRFRMNG_STTS_LE AS STRING),'')<>COALESCE(CAST(Y.DT_PRFRMNG_STTS_LE_SIMUL AS STRING),'') OR (X.DT_PRFRMNG_STTS_LE IS NULL AND Y.DT_PRFRMNG_STTS_LE_SIMUL IS NOT NULL ) OR (X.DT_PRFRMNG_STTS_LE IS NOT NULL AND Y.DT_PRFRMNG_STTS_LE_SIMUL IS NULL),1,0)) AS NUM_REG_DIF,'1' AS ID_EXEC, CURRENT_TIMESTAMP() AS TIME_EXEC FROM (SELECT entty_id, DT_PRFRMNG_STTS_LE FROM CD_LOAN_TAPES_BCE.LT003_ENTITY WHERE ref_date='${ref_date}' AND nome_perimetro='Individual Corporativo' AND segmento='ESTR' AND ambito='PM' AND entidade='00100')X INNER JOIN (SELECT entty_id AS entty_id_SIMUL, DT_PRFRMNG_STTS_LE AS DT_PRFRMNG_STTS_LE_SIMUL FROM BU_LOANTAPE_WORK.LT003_ENTITY WHERE ref_date='${ref_date}' AND nome_perimetro='Individual Corporativo' AND segmento='ESTR' AND ambito='PM' AND entidade='00100')Y ON X.ENTTY_ID=Y.ENTTY_ID_SIMUL | M16: =+"UNION ALL "&L16 -> UNION ALL SELECT 'ENTITY' AS TABELA, 'COERÊNCIA' AS TIPOLOGIA_TESTE,'CD_LOAN_TAPES_BCE.LT003_ENTITY' AS TABELA_LT,'BU_LOANTAPE_WORK.LT003_ENTITY' AS TABELA_SIMUL,'DT_PRFRMNG_STTS_LE' AS CAMPO, '${ref_date}' AS REF_DATE, COUNT(*) AS NUM_REG, SUM(IF(COALESCE(CAST(X.DT_PRFRMNG_STTS_LE AS STRING),'')<>COALESCE(CAST(Y.DT_PRFRMNG_STTS_LE_SIMUL AS STRING),'') OR (X.DT_PRFRMNG_STTS_LE IS NULL AND Y.DT_PRFRMNG_STTS_LE_SIMUL IS NOT NULL ) OR (X.DT_PRFRMNG_STTS_LE IS NOT NULL AND Y.DT_PRFRMNG_STTS_LE_SIMUL IS NULL),1,0)) AS NUM_REG_DIF,'1' AS ID_EXEC, CURRENT_TIMESTAMP() AS TIME_EXEC FROM (SELECT entty_id, DT_PRFRMNG_STTS_LE FROM CD_LOAN_TAPES_BCE.LT003_ENTITY WHERE ref_date='${ref_date}' AND nome_perimetro='Individual Corporativo' AND segmento='ESTR' AND ambito='PM' AND entidade='00100')X INNER JOIN (SELECT entty_id AS entty_id_SIMUL, DT_PRFRMNG_STTS_LE AS DT_PRFRMNG_STTS_LE_SIMUL FROM BU_LOANTAPE_WORK.LT003_ENTITY WHERE ref_date='${ref_date}' AND nome_perimetro='Individual Corporativo' AND segmento='ESTR' AND ambito='PM' AND entidade='00100')Y ON X.ENTTY_ID=Y.ENTTY_ID_SIMUL
B17: ENTITY | C17: Coerência | D17: =+UPPER('0. Instruções'!$D$35&"."&VLOOKUP(B17,'0. Instruções'!$C$27:$D$32,2,FALSE)) -> CD_LOAN_TAPES_BCE.LT003_ENTITY | E17: =+UPPER('0. Instruções'!$D$36&"."&VLOOKUP(B17,'0. Instruções'!$C$27:$E$32,3,FALSE)) -> BU_LOANTAPE_WORK.LT003_ENTITY | F17: GCC_PRNT_ID | H17: VARCHAR2(255) | I17: ="(SELECT "&VLOOKUP(B17,'0. Instruções'!$C$27:$G$32,4,FALSE)&", "&F17&" FROM "&D17&" WHERE "&'0. Instruções'!$D$42&")X" -> (SELECT entty_id, GCC_PRNT_ID FROM CD_LOAN_TAPES_BCE.LT003_ENTITY WHERE ref_date='${ref_date}' AND nome_perimetro='Individual Corporativo' AND segmento='ESTR' AND ambito='PM' AND entidade='00100')X | J17: ="(SELECT "&VLOOKUP(B17,'0. Instruções'!$C$27:$G$32,4,FALSE)&" AS "&VLOOKUP(B17,'0. Instruções'!$C$27:$G$32,4,FALSE)&"_SIMUL, "&F17&" AS "&F17&"_SIMUL FROM "&E17&" WHERE "&'0. Instruções'!$D$43&")Y" -> (SELECT entty_id AS entty_id_SIMUL, GCC_PRNT_ID AS GCC_PRNT_ID_SIMUL FROM BU_LOANTAPE_WORK.LT003_ENTITY WHERE ref_date='${ref_date}' AND nome_perimetro='Individual Corporativo' AND segmento='ESTR' AND ambito='PM' AND entidade='00100')Y | K17: =+UPPER("ON X."&VLOOKUP(B17,'0. Instruções'!$C$27:$G$32,4,FALSE)&"=Y."&VLOOKUP(B17,'0. Instruções'!$C$27:$G$32,4,FALSE)&"_SIMUL") -> ON X.ENTTY_ID=Y.ENTTY_ID_SIMUL | L17: =+IF(C17="Coerência", +IF(LEFT(G17,5)="FLOAT","SELECT '"&UPPER(B17)&"' AS TABELA, '"&UPPER(C17)&"' AS TIPOLOGIA_TESTE,'"&D17&"' AS TABELA_LT,'"&E17&"' AS TABELA_SIMUL,'"&F17&"' AS CAMPO, "&"'${ref_date}' AS REF_DATE, COUNT(*) AS NUM_REG, SUM(IF((ABS(COALESCE(CAST(X."&F17&" AS DECIMAL(18,6)),0)-COALESCE(CAST(Y."&F17&"_SIMUL AS DECIMAL(18,6)),0))>0.000001) OR (X."&F17&" IS NULL AND Y."&F17&"_SIMUL IS NOT NULL ) OR (X."&F17&" IS NOT NULL AND Y."&F17&"_SIMUL IS NULL),1,0)) AS NUM_REG_DIF,'"&MAX('ID1&5'!K:K)+1&"' AS ID_EXEC, CURRENT_TIMESTAMP() AS TIME_EXEC FROM "&I17&" INNER JOIN "&J17&" "&K17,"SELECT '"&UPPER(B17)&"' AS TABELA, '"&UPPER(C17)&"' AS TIPOLOGIA_TESTE,'"&D17&"' AS TABELA_LT,'"&E17&"' AS TABELA_SIMUL,'"&F17&"' AS CAMPO, "&"'${ref_date}' AS REF_DATE, COUNT(*) AS NUM_REG, SUM(IF(COALESCE(CAST(X."&F17&" AS STRING),'')<>COALESCE(CAST(Y."&F17&"_SIMUL AS STRING),'') OR (X."&F17&" IS NULL AND Y."&F17&"_SIMUL IS NOT NULL ) OR (X."&F17&" IS NOT NULL AND Y."&F17&"_SIMUL IS NULL),1,0)) AS NUM_REG_DIF,'"&MAX('ID1&5'!L:L)+1&"' AS ID_EXEC, CURRENT_TIMESTAMP() AS TIME_EXEC FROM "&I17&" INNER JOIN "&J17&" "&K17), IF(C17="Validade",+IF(G17="Code List","SELECT '"&UPPER(B17)&"' AS TABELA, '"&UPPER(C17)&"' AS TIPOLOGIA_TESTE,'"&D17&"' AS TABELA_LT,'N/A' AS TABELA_SIMUL,'"&F17&"' AS CAMPO, "&"'${ref_date}' AS REF_DATE, COUNT(*) AS NUM_REG, SUM(IF(TRIM(CAST(X."&F17&" AS STRING))='' OR TRIM(CAST(X."&F17&" AS STRING)) IS NULL OR CAST(X."&F17&" AS STRING) NOT "&H17&",1,0)) AS NUM_REG_DIF,'"&MAX('ID1&5'!K:K)+1&"' AS ID_EXEC, CURRENT_TIMESTAMP() AS TIME_EXEC FROM "&I17,"SELECT '"&UPPER(B17)&"' AS TABELA, '"&UPPER(C17)&"' AS TIPOLOGIA_TESTE,'"&D17&"' AS TABELA_LT,'N/A' AS TABELA_SIMUL,'"&F17&"' AS CAMPO, "&"'${ref_date}' AS REF_DATE, COUNT(*) AS NUM_REG, SUM(IF(TRIM(CAST(X."&F17&" AS STRING))='' OR TRIM(CAST(X."&F17&" AS STRING)) IS NULL,1,0)) AS NUM_REG_DIF,'"&MAX('ID1&5'!K:K)+1&"' AS ID_EXEC, CURRENT_TIMESTAMP() AS TIME_EXEC FROM "&I17), IF(C17="Caracteres Especiais",+"SELECT '"&UPPER(B17)&"' AS TABELA, '"&UPPER(C17)&"' AS TIPOLOGIA_TESTE,'"&D17&"' AS TABELA_LT,'N/A' AS TABELA_SIMUL,'"&F17&"' AS CAMPO, "&"'${ref_date}' AS REF_DATE, COUNT(*) AS NUM_REG, SUM(IF(REGEXP_REPLACE(TRIM(CAST(X."&F17&" AS STRING)),'[^a-zA-Z0-9_\\s]','') <>TRIM(CAST(X."&F17&" AS STRING)),1,0)) AS NUM_REG_DIF,'"&MAX('ID1&5'!K:K)+1&"' AS ID_EXEC, CURRENT_TIMESTAMP() AS TIME_EXEC FROM "&I17, IF(C17="Missings",+"SELECT '"&UPPER(B17)&"' AS TABELA, '"&UPPER(C17)&"' AS TIPOLOGIA_TESTE,'"&D17&"' AS TABELA_LT,'N/A' AS TABELA_SIMUL,'"&F17&"' AS CAMPO, "&"'${ref_date}' AS REF_DATE, COUNT(*) AS NUM_REG, SUM(IF(TRIM(CAST(X."&F17&" AS STRING)) IN ('0000-00-00','0001-01-01','9999-12-31','MISS','00000','99999999999','99999999999.00','99999999999.000000'),1,0)) AS NUM_REG_DIF,'"&MAX('ID1&5'!K:K)+1&"' AS ID_EXEC, CURRENT_TIMESTAMP() AS TIME_EXEC FROM "&I17, IF(C17="Not applicable",+"SELECT '"&UPPER(B17)&"' AS TABELA, '"&UPPER(C17)&"' AS TIPOLOGIA_TESTE,'"&D17&"' AS TABELA_LT,'N/A' AS TABELA_SIMUL,'"&F17&"' AS CAMPO, "&"'${ref_date}' AS REF_DATE, COUNT(*) AS NUM_REG, SUM(IF(TRIM(CAST(X."&F17&" AS STRING)) IN ('N/A','11111111111','11111111111.00','11111111111.000000','1111-11-11'),1,0)) AS NUM_REG_DIF,'"&MAX('ID1&5'!K:K)+1&"' AS ID_EXEC, CURRENT_TIMESTAMP() AS TIME_EXEC FROM "&I17, IF(C17="Valores extremos",+"SELECT '"&UPPER(B17)&"' AS TABELA, '"&UPPER(C17)&"' AS TIPOLOGIA_TESTE,'"&D17&"' AS TABELA_LT,'N/A' AS TABELA_SIMUL,'"&F17&"' AS CAMPO, "&"'${ref_date}' AS REF_DATE, CAST(MIN("&F17&") AS STRING) AS VALOR_MIN, CAST(MAX("&F17&") AS STRING) AS VALOR_MAX,'"&MAX('ID1&5'!K:K)+1&"' AS ID_EXEC, CURRENT_TIMESTAMP() AS TIME_EXEC FROM "&MID(I17,1,LEN(I17)-2)&" AND CAST("&F17&" AS STRING) NOT IN ('0000-00-00','0001-01-01','9999-12-31','MISS','00000','99999999999','99999999999.00','99999999999.000000','N/A','11111111111','11111111111.00','11111111111.000000','1111-11-11'))X")))))) -> SELECT 'ENTITY' AS TABELA, 'COERÊNCIA' AS TIPOLOGIA_TESTE,'CD_LOAN_TAPES_BCE.LT003_ENTITY' AS TABELA_LT,'BU_LOANTAPE_WORK.LT003_ENTITY' AS TABELA_SIMUL,'GCC_PRNT_ID' AS CAMPO, '${ref_date}' AS REF_DATE, COUNT(*) AS NUM_REG, SUM(IF(COALESCE(CAST(X.GCC_PRNT_ID AS STRING),'')<>COALESCE(CAST(Y.GCC_PRNT_ID_SIMUL AS STRING),'') OR (X.GCC_PRNT_ID IS NULL AND Y.GCC_PRNT_ID_SIMUL IS NOT NULL ) OR (X.GCC_PRNT_ID IS NOT NULL AND Y.GCC_PRNT_ID_SIMUL IS NULL),1,0)) AS NUM_REG_DIF,'1' AS ID_EXEC, CURRENT_TIMESTAMP() AS TIME_EXEC FROM (SELECT entty_id, GCC_PRNT_ID FROM CD_LOAN_TAPES_BCE.LT003_ENTITY WHERE ref_date='${ref_date}' AND nome_perimetro='Individual Corporativo' AND segmento='ESTR' AND ambito='PM' AND entidade='00100')X INNER JOIN (SELECT entty_id AS entty_id_SIMUL, GCC_PRNT_ID AS GCC_PRNT_ID_SIMUL FROM BU_LOANTAPE_WORK.LT003_ENTITY WHERE ref_date='${ref_date}' AND nome_perimetro='Individual Corporativo' AND segmento='ESTR' AND ambito='PM' AND entidade='00100')Y ON X.ENTTY_ID=Y.ENTTY_ID_SIMUL | M17: =+"UNION ALL "&L17 -> UNION ALL SELECT 'ENTITY' AS TABELA, 'COERÊNCIA' AS TIPOLOGIA_TESTE,'CD_LOAN_TAPES_BCE.LT003_ENTITY' AS TABELA_LT,'BU_LOANTAPE_WORK.LT003_ENTITY' AS TABELA_SIMUL,'GCC_PRNT_ID' AS CAMPO, '${ref_date}' AS REF_DATE, COUNT(*) AS NUM_REG, SUM(IF(COALESCE(CAST(X.GCC_PRNT_ID AS STRING),'')<>COALESCE(CAST(Y.GCC_PRNT_ID_SIMUL AS STRING),'') OR (X.GCC_PRNT_ID IS NULL AND Y.GCC_PRNT_ID_SIMUL IS NOT NULL ) OR (X.GCC_PRNT_ID IS NOT NULL AND Y.GCC_PRNT_ID_SIMUL IS NULL),1,0)) AS NUM_REG_DIF,'1' AS ID_EXEC, CURRENT_TIMESTAMP() AS TIME_EXEC FROM (SELECT entty_id, GCC_PRNT_ID FROM CD_LOAN_TAPES_BCE.LT003_ENTITY WHERE ref_date='${ref_date}' AND nome_perimetro='Individual Corporativo' AND segmento='ESTR' AND ambito='PM' AND entidade='00100')X INNER JOIN (SELECT entty_id AS entty_id_SIMUL, GCC_PRNT_ID AS GCC_PRNT_ID_SIMUL FROM BU_LOANTAPE_WORK.LT003_ENTITY WHERE ref_date='${ref_date}' AND nome_perimetro='Individual Corporativo' AND segmento='ESTR' AND ambito='PM' AND entidade='00100')Y ON X.ENTTY_ID=Y.ENTTY_ID_SIMUL
B18: ENTITY | C18: Coerência | D18: =+UPPER('0. Instruções'!$D$35&"."&VLOOKUP(B18,'0. Instruções'!$C$27:$D$32,2,FALSE)) -> CD_LOAN_TAPES_BCE.LT003_ENTITY | E18: =+UPPER('0. Instruções'!$D$36&"."&VLOOKUP(B18,'0. Instruções'!$C$27:$E$32,3,FALSE)) -> BU_LOANTAPE_WORK.LT003_ENTITY | F18: GCC_PRNT_NM | H18: VARCHAR2(255) | I18: ="(SELECT "&VLOOKUP(B18,'0. Instruções'!$C$27:$G$32,4,FALSE)&", "&F18&" FROM "&D18&" WHERE "&'0. Instruções'!$D$42&")X" -> (SELECT entty_id, GCC_PRNT_NM FROM CD_LOAN_TAPES_BCE.LT003_ENTITY WHERE ref_date='${ref_date}' AND nome_perimetro='Individual Corporativo' AND segmento='ESTR' AND ambito='PM' AND entidade='00100')X | J18: ="(SELECT "&VLOOKUP(B18,'0. Instruções'!$C$27:$G$32,4,FALSE)&" AS "&VLOOKUP(B18,'0. Instruções'!$C$27:$G$32,4,FALSE)&"_SIMUL, "&F18&" AS "&F18&"_SIMUL FROM "&E18&" WHERE "&'0. Instruções'!$D$43&")Y" -> (SELECT entty_id AS entty_id_SIMUL, GCC_PRNT_NM AS GCC_PRNT_NM_SIMUL FROM BU_LOANTAPE_WORK.LT003_ENTITY WHERE ref_date='${ref_date}' AND nome_perimetro='Individual Corporativo' AND segmento='ESTR' AND ambito='PM' AND entidade='00100')Y | K18: =+UPPER("ON X."&VLOOKUP(B18,'0. Instruções'!$C$27:$G$32,4,FALSE)&"=Y."&VLOOKUP(B18,'0. Instruções'!$C$27:$G$32,4,FALSE)&"_SIMUL") -> ON X.ENTTY_ID=Y.ENTTY_ID_SIMUL | L18: =+IF(C18="Coerência", +IF(LEFT(G18,5)="FLOAT","SELECT '"&UPPER(B18)&"' AS TABELA, '"&UPPER(C18)&"' AS TIPOLOGIA_TESTE,'"&D18&"' AS TABELA_LT,'"&E18&"' AS TABELA_SIMUL,'"&F18&"' AS CAMPO, "&"'${ref_date}' AS REF_DATE, COUNT(*) AS NUM_REG, SUM(IF((ABS(COALESCE(CAST(X."&F18&" AS DECIMAL(18,6)),0)-COALESCE(CAST(Y."&F18&"_SIMUL AS DECIMAL(18,6)),0))>0.000001) OR (X."&F18&" IS NULL AND Y."&F18&"_SIMUL IS NOT NULL ) OR (X."&F18&" IS NOT NULL AND Y."&F18&"_SIMUL IS NULL),1,0)) AS NUM_REG_DIF,'"&MAX('ID1&5'!K:K)+1&"' AS ID_EXEC, CURRENT_TIMESTAMP() AS TIME_EXEC FROM "&I18&" INNER JOIN "&J18&" "&K18,"SELECT '"&UPPER(B18)&"' AS TABELA, '"&UPPER(C18)&"' AS TIPOLOGIA_TESTE,'"&D18&"' AS TABELA_LT,'"&E18&"' AS TABELA_SIMUL,'"&F18&"' AS CAMPO, "&"'${ref_date}' AS REF_DATE, COUNT(*) AS NUM_REG, SUM(IF(COALESCE(CAST(X."&F18&" AS STRING),'')<>COALESCE(CAST(Y."&F18&"_SIMUL AS STRING),'') OR (X."&F18&" IS NULL AND Y."&F18&"_SIMUL IS NOT NULL ) OR (X."&F18&" IS NOT NULL AND Y."&F18&"_SIMUL IS NULL),1,0)) AS NUM_REG_DIF,'"&MAX('ID1&5'!L:L)+1&"' AS ID_EXEC, CURRENT_TIMESTAMP() AS TIME_EXEC FROM "&I18&" INNER JOIN "&J18&" "&K18), IF(C18="Validade",+IF(G18="Code List","SELECT '"&UPPER(B18)&"' AS TABELA, '"&UPPER(C18)&"' AS TIPOLOGIA_TESTE,'"&D18&"' AS TABELA_LT,'N/A' AS TABELA_SIMUL,'"&F18&"' AS CAMPO, "&"'${ref_date}' AS REF_DATE, COUNT(*) AS NUM_REG, SUM(IF(TRIM(CAST(X."&F18&" AS STRING))='' OR TRIM(CAST(X."&F18&" AS STRING)) IS NULL OR CAST(X."&F18&" AS STRING) NOT "&H18&",1,0)) AS NUM_REG_DIF,'"&MAX('ID1&5'!K:K)+1&"' AS ID_EXEC, CURRENT_TIMESTAMP() AS TIME_EXEC FROM "&I18,"SELECT '"&UPPER(B18)&"' AS TABELA, '"&UPPER(C18)&"' AS TIPOLOGIA_TESTE,'"&D18&"' AS TABELA_LT,'N/A' AS TABELA_SIMUL,'"&F18&"' AS CAMPO, "&"'${ref_date}' AS REF_DATE, COUNT(*) AS NUM_REG, SUM(IF(TRIM(CAST(X."&F18&" AS STRING))='' OR TRIM(CAST(X."&F18&" AS STRING)) IS NULL,1,0)) AS NUM_REG_DIF,'"&MAX('ID1&5'!K:K)+1&"' AS ID_EXEC, CURRENT_TIMESTAMP() AS TIME_EXEC FROM "&I18), IF(C18="Caracteres Especiais",+"SELECT '"&UPPER(B18)&"' AS TABELA, '"&UPPER(C18)&"' AS TIPOLOGIA_TESTE,'"&D18&"' AS TABELA_LT,'N/A' AS TABELA_SIMUL,'"&F18&"' AS CAMPO, "&"'${ref_date}' AS REF_DATE, COUNT(*) AS NUM_REG, SUM(IF(REGEXP_REPLACE(TRIM(CAST(X."&F18&" AS STRING)),'[^a-zA-Z0-9_\\s]','') <>TRIM(CAST(X."&F18&" AS STRING)),1,0)) AS NUM_REG_DIF,'"&MAX('ID1&5'!K:K)+1&"' AS ID_EXEC, CURRENT_TIMESTAMP() AS TIME_EXEC FROM "&I18, IF(C18="Missings",+"SELECT '"&UPPER(B18)&"' AS TABELA, '"&UPPER(C18)&"' AS TIPOLOGIA_TESTE,'"&D18&"' AS TABELA_LT,'N/A' AS TABELA_SIMUL,'"&F18&"' AS CAMPO, "&"'${ref_date}' AS REF_DATE, COUNT(*) AS NUM_REG, SUM(IF(TRIM(CAST(X."&F18&" AS STRING)) IN ('0000-00-00','0001-01-01','9999-12-31','MISS','00000','99999999999','99999999999.00','99999999999.000000'),1,0)) AS NUM_REG_DIF,'"&MAX('ID1&5'!K:K)+1&"' AS ID_EXEC, CURRENT_TIMESTAMP() AS TIME_EXEC FROM "&I18, IF(C18="Not applicable",+"SELECT '"&UPPER(B18)&"' AS TABELA, '"&UPPER(C18)&"' AS TIPOLOGIA_TESTE,'"&D18&"' AS TABELA_LT,'N/A' AS TABELA_SIMUL,'"&F18&"' AS CAMPO, "&"'${ref_date}' AS REF_DATE, COUNT(*) AS NUM_REG, SUM(IF(TRIM(CAST(X."&F18&" AS STRING)) IN ('N/A','11111111111','11111111111.00','11111111111.000000','1111-11-11'),1,0)) AS NUM_REG_DIF,'"&MAX('ID1&5'!K:K)+1&"' AS ID_EXEC, CURRENT_TIMESTAMP() AS TIME_EXEC FROM "&I18, IF(C18="Valores extremos",+"SELECT '"&UPPER(B18)&"' AS TABELA, '"&UPPER(C18)&"' AS TIPOLOGIA_TESTE,'"&D18&"' AS TABELA_LT,'N/A' AS TABELA_SIMUL,'"&F18&"' AS CAMPO, "&"'${ref_date}' AS REF_DATE, CAST(MIN("&F18&") AS STRING) AS VALOR_MIN, CAST(MAX("&F18&") AS STRING) AS VALOR_MAX,'"&MAX('ID1&5'!K:K)+1&"' AS ID_EXEC, CURRENT_TIMESTAMP() AS TIME_EXEC FROM "&MID(I18,1,LEN(I18)-2)&" AND CAST("&F18&" AS STRING) NOT IN ('0000-00-00','0001-01-01','9999-12-31','MISS','00000','99999999999','99999999999.00','99999999999.000000','N/A','11111111111','11111111111.00','11111111111.000000','1111-11-11'))X")))))) -> SELECT 'ENTITY' AS TABELA, 'COERÊNCIA' AS TIPOLOGIA_TESTE,'CD_LOAN_TAPES_BCE.LT003_ENTITY' AS TABELA_LT,'BU_LOANTAPE_WORK.LT003_ENTITY' AS TABELA_SIMUL,'GCC_PRNT_NM' AS CAMPO, '${ref_date}' AS REF_DATE, COUNT(*) AS NUM_REG, SUM(IF(COALESCE(CAST(X.GCC_PRNT_NM AS STRING),'')<>COALESCE(CAST(Y.GCC_PRNT_NM_SIMUL AS STRING),'') OR (X.GCC_PRNT_NM IS NULL AND Y.GCC_PRNT_NM_SIMUL IS NOT NULL ) OR (X.GCC_PRNT_NM IS NOT NULL AND Y.GCC_PRNT_NM_SIMUL IS NULL),1,0)) AS NUM_REG_DIF,'1' AS ID_EXEC, CURRENT_TIMESTAMP() AS TIME_EXEC FROM (SELECT entty_id, GCC_PRNT_NM FROM CD_LOAN_TAPES_BCE.LT003_ENTITY WHERE ref_date='${ref_date}' AND nome_perimetro='Individual Corporativo' AND segmento='ESTR' AND ambito='PM' AND entidade='00100')X INNER JOIN (SELECT entty_id AS entty_id_SIMUL, GCC_PRNT_NM AS GCC_PRNT_NM_SIMUL FROM BU_LOANTAPE_WORK.LT003_ENTITY WHERE ref_date='${ref_date}' AND nome_perimetro='Individual Corporativo' AND segmento='ESTR' AND ambito='PM' AND entidade='00100')Y ON X.ENTTY_ID=Y.ENTTY_ID_SIMUL | M18: =+"UNION ALL "&L18 -> UNION ALL SELECT 'ENTITY' AS TABELA, 'COERÊNCIA' AS TIPOLOGIA_TESTE,'CD_LOAN_TAPES_BCE.LT003_ENTITY' AS TABELA_LT,'BU_LOANTAPE_WORK.LT003_ENTITY' AS TABELA_SIMUL,'GCC_PRNT_NM' AS CAMPO, '${ref_date}' AS REF_DATE, COUNT(*) AS NUM_REG, SUM(IF(COALESCE(CAST(X.GCC_PRNT_NM AS STRING),'')<>COALESCE(CAST(Y.GCC_PRNT_NM_SIMUL AS STRING),'') OR (X.GCC_PRNT_NM IS NULL AND Y.GCC_PRNT_NM_SIMUL IS NOT NULL ) OR (X.GCC_PRNT_NM IS NOT NULL AND Y.GCC_PRNT_NM_SIMUL IS NULL),1,0)) AS NUM_REG_DIF,'1' AS ID_EXEC, CURRENT_TIMESTAMP() AS TIME_EXEC FROM (SELECT entty_id, GCC_PRNT_NM FROM CD_LOAN_TAPES_BCE.LT003_ENTITY WHERE ref_date='${ref_date}' AND nome_perimetro='Individual Corporativo' AND segmento='ESTR' AND ambito='PM' AND entidade='00100')X INNER JOIN (SELECT entty_id AS entty_id_SIMUL, GCC_PRNT_NM AS GCC_PRNT_NM_SIMUL FROM BU_LOANTAPE_WORK.LT003_ENTITY WHERE ref_date='${ref_date}' AND nome_perimetro='Individual Corporativo' AND segmento='ESTR' AND ambito='PM' AND entidade='00100')Y ON X.ENTTY_ID=Y.ENTTY_ID_SIMUL
B19: ENTITY | C19: Coerência | D19: =+UPPER('0. Instruções'!$D$35&"."&VLOOKUP(B19,'0. Instruções'!$C$27:$D$32,2,FALSE)) -> CD_LOAN_TAPES_BCE.LT003_ENTITY | E19: =+UPPER('0. Instruções'!$D$36&"."&VLOOKUP(B19,'0. Instruções'!$C$27:$E$32,3,FALSE)) -> BU_LOANTAPE_WORK.LT003_ENTITY | F19: INTRNL_SGMNT | H19: VARCHAR2(255) | I19: ="(SELECT "&VLOOKUP(B19,'0. Instruções'!$C$27:$G$32,4,FALSE)&", "&F19&" FROM "&D19&" WHERE "&'0. Instruções'!$D$42&")X" -> (SELECT entty_id, INTRNL_SGMNT FROM CD_LOAN_TAPES_BCE.LT003_ENTITY WHERE ref_date='${ref_date}' AND nome_perimetro='Individual Corporativo' AND segmento='ESTR' AND ambito='PM' AND entidade='00100')X | J19: ="(SELECT "&VLOOKUP(B19,'0. Instruções'!$C$27:$G$32,4,FALSE)&" AS "&VLOOKUP(B19,'0. Instruções'!$C$27:$G$32,4,FALSE)&"_SIMUL, "&F19&" AS "&F19&"_SIMUL FROM "&E19&" WHERE "&'0. Instruções'!$D$43&")Y" -> (SELECT entty_id AS entty_id_SIMUL, INTRNL_SGMNT AS INTRNL_SGMNT_SIMUL FROM BU_LOANTAPE_WORK.LT003_ENTITY WHERE ref_date='${ref_date}' AND nome_perimetro='Individual Corporativo' AND segmento='ESTR' AND ambito='PM' AND entidade='00100')Y | K19: =+UPPER("ON X."&VLOOKUP(B19,'0. Instruções'!$C$27:$G$32,4,FALSE)&"=Y."&VLOOKUP(B19,'0. Instruções'!$C$27:$G$32,4,FALSE)&"_SIMUL") -> ON X.ENTTY_ID=Y.ENTTY_ID_SIMUL | L19: =+IF(C19="Coerência", +IF(LEFT(G19,5)="FLOAT","SELECT '"&UPPER(B19)&"' AS TABELA, '"&UPPER(C19)&"' AS TIPOLOGIA_TESTE,'"&D19&"' AS TABELA_LT,'"&E19&"' AS TABELA_SIMUL,'"&F19&"' AS CAMPO, "&"'${ref_date}' AS REF_DATE, COUNT(*) AS NUM_REG, SUM(IF((ABS(COALESCE(CAST(X."&F19&" AS DECIMAL(18,6)),0)-COALESCE(CAST(Y."&F19&"_SIMUL AS DECIMAL(18,6)),0))>0.000001) OR (X."&F19&" IS NULL AND Y."&F19&"_SIMUL IS NOT NULL ) OR (X."&F19&" IS NOT NULL AND Y."&F19&"_SIMUL IS NULL),1,0)) AS NUM_REG_DIF,'"&MAX('ID1&5'!K:K)+1&"' AS ID_EXEC, CURRENT_TIMESTAMP() AS TIME_EXEC FROM "&I19&" INNER JOIN "&J19&" "&K19,"SELECT '"&UPPER(B19)&"' AS TABELA, '"&UPPER(C19)&"' AS TIPOLOGIA_TESTE,'"&D19&"' AS TABELA_LT,'"&E19&"' AS TABELA_SIMUL,'"&F19&"' AS CAMPO, "&"'${ref_date}' AS REF_DATE, COUNT(*) AS NUM_REG, SUM(IF(COALESCE(CAST(X."&F19&" AS STRING),'')<>COALESCE(CAST(Y."&F19&"_SIMUL AS STRING),'') OR (X."&F19&" IS NULL AND Y."&F19&"_SIMUL IS NOT NULL ) OR (X."&F19&" IS NOT NULL AND Y."&F19&"_SIMUL IS NULL),1,0)) AS NUM_REG_DIF,'"&MAX('ID1&5'!L:L)+1&"' AS ID_EXEC, CURRENT_TIMESTAMP() AS TIME_EXEC FROM "&I19&" INNER JOIN "&J19&" "&K19), IF(C19="Validade",+IF(G19="Code List","SELECT '"&UPPER(B19)&"' AS TABELA, '"&UPPER(C19)&"' AS TIPOLOGIA_TESTE,'"&D19&"' AS TABELA_LT,'N/A' AS TABELA_SIMUL,'"&F19&"' AS CAMPO, "&"'${ref_date}' AS REF_DATE, COUNT(*) AS NUM_REG, SUM(IF(TRIM(CAST(X."&F19&" AS STRING))='' OR TRIM(CAST(X."&F19&" AS STRING)) IS NULL OR CAST(X."&F19&" AS STRING) NOT "&H19&",1,0)) AS NUM_REG_DIF,'"&MAX('ID1&5'!K:K)+1&"' AS ID_EXEC, CURRENT_TIMESTAMP() AS TIME_EXEC FROM "&I19,"SELECT '"&UPPER(B19)&"' AS TABELA, '"&UPPER(C19)&"' AS TIPOLOGIA_TESTE,'"&D19&"' AS TABELA_LT,'N/A' AS TABELA_SIMUL,'"&F19&"' AS CAMPO, "&"'${ref_date}' AS REF_DATE, COUNT(*) AS NUM_REG, SUM(IF(TRIM(CAST(X."&F19&" AS STRING))='' OR TRIM(CAST(X."&F19&" AS STRING)) IS NULL,1,0)) AS NUM_REG_DIF,'"&MAX('ID1&5'!K:K)+1&"' AS ID_EXEC, CURRENT_TIMESTAMP() AS TIME_EXEC FROM "&I19), IF(C19="Caracteres Especiais",+"SELECT '"&UPPER(B19)&"' AS TABELA, '"&UPPER(C19)&"' AS TIPOLOGIA_TESTE,'"&D19&"' AS TABELA_LT,'N/A' AS TABELA_SIMUL,'"&F19&"' AS CAMPO, "&"'${ref_date}' AS REF_DATE, COUNT(*) AS NUM_REG, SUM(IF(REGEXP_REPLACE(TRIM(CAST(X."&F19&" AS STRING)),'[^a-zA-Z0-9_\\s]','') <>TRIM(CAST(X."&F19&" AS STRING)),1,0)) AS NUM_REG_DIF,'"&MAX('ID1&5'!K:K)+1&"' AS ID_EXEC, CURRENT_TIMESTAMP() AS TIME_EXEC FROM "&I19, IF(C19="Missings",+"SELECT '"&UPPER(B19)&"' AS TABELA, '"&UPPER(C19)&"' AS TIPOLOGIA_TESTE,'"&D19&"' AS TABELA_LT,'N/A' AS TABELA_SIMUL,'"&F19&"' AS CAMPO, "&"'${ref_date}' AS REF_DATE, COUNT(*) AS NUM_REG, SUM(IF(TRIM(CAST(X."&F19&" AS STRING)) IN ('0000-00-00','0001-01-01','9999-12-31','MISS','00000','99999999999','99999999999.00','99999999999.000000'),1,0)) AS NUM_REG_DIF,'"&MAX('ID1&5'!K:K)+1&"' AS ID_EXEC, CURRENT_TIMESTAMP() AS TIME_EXEC FROM "&I19, IF(C19="Not applicable",+"SELECT '"&UPPER(B19)&"' AS TABELA, '"&UPPER(C19)&"' AS TIPOLOGIA_TESTE,'"&D19&"' AS TABELA_LT,'N/A' AS TABELA_SIMUL,'"&F19&"' AS CAMPO, "&"'${ref_date}' AS REF_DATE, COUNT(*) AS NUM_REG, SUM(IF(TRIM(CAST(X."&F19&" AS STRING)) IN ('N/A','11111111111','11111111111.00','11111111111.000000','1111-11-11'),1,0)) AS NUM_REG_DIF,'"&MAX('ID1&5'!K:K)+1&"' AS ID_EXEC, CURRENT_TIMESTAMP() AS TIME_EXEC FROM "&I19, IF(C19="Valores extremos",+"SELECT '"&UPPER(B19)&"' AS TABELA, '"&UPPER(C19)&"' AS TIPOLOGIA_TESTE,'"&D19&"' AS TABELA_LT,'N/A' AS TABELA_SIMUL,'"&F19&"' AS CAMPO, "&"'${ref_date}' AS REF_DATE, CAST(MIN("&F19&") AS STRING) AS VALOR_MIN, CAST(MAX("&F19&") AS STRING) AS VALOR_MAX,'"&MAX('ID1&5'!K:K)+1&"' AS ID_EXEC, CURRENT_TIMESTAMP() AS TIME_EXEC FROM "&MID(I19,1,LEN(I19)-2)&" AND CAST("&F19&" AS STRING) NOT IN ('0000-00-00','0001-01-01','9999-12-31','MISS','00000','99999999999','99999999999.00','99999999999.000000','N/A','11111111111','11111111111.00','11111111111.000000','1111-11-11'))X")))))) -> SELECT 'ENTITY' AS TABELA, 'COERÊNCIA' AS TIPOLOGIA_TESTE,'CD_LOAN_TAPES_BCE.LT003_ENTITY' AS TABELA_LT,'BU_LOANTAPE_WORK.LT003_ENTITY' AS TABELA_SIMUL,'INTRNL_SGMNT' AS CAMPO, '${ref_date}' AS REF_DATE, COUNT(*) AS NUM_REG, SUM(IF(COALESCE(CAST(X.INTRNL_SGMNT AS STRING),'')<>COALESCE(CAST(Y.INTRNL_SGMNT_SIMUL AS STRING),'') OR (X.INTRNL_SGMNT IS NULL AND Y.INTRNL_SGMNT_SIMUL IS NOT NULL ) OR (X.INTRNL_SGMNT IS NOT NULL AND Y.INTRNL_SGMNT_SIMUL IS NULL),1,0)) AS NUM_REG_DIF,'1' AS ID_EXEC, CURRENT_TIMESTAMP() AS TIME_EXEC FROM (SELECT entty_id, INTRNL_SGMNT FROM CD_LOAN_TAPES_BCE.LT003_ENTITY WHERE ref_date='${ref_date}' AND nome_perimetro='Individual Corporativo' AND segmento='ESTR' AND ambito='PM' AND entidade='00100')X INNER JOIN (SELECT entty_id AS entty_id_SIMUL, INTRNL_SGMNT AS INTRNL_SGMNT_SIMUL FROM BU_LOANTAPE_WORK.LT003_ENTITY WHERE ref_date='${ref_date}' AND nome_perimetro='Individual Corporativo' AND segmento='ESTR' AND ambito='PM' AND entidade='00100')Y ON X.ENTTY_ID=Y.ENTTY_ID_SIMUL | M19: =+"UNION ALL "&L19 -> UNION ALL SELECT 'ENTITY' AS TABELA, 'COERÊNCIA' AS TIPOLOGIA_TESTE,'CD_LOAN_TAPES_BCE.LT003_ENTITY' AS TABELA_LT,'BU_LOANTAPE_WORK.LT003_ENTITY' AS TABELA_SIMUL,'INTRNL_SGMNT' AS CAMPO, '${ref_date}' AS REF_DATE, COUNT(*) AS NUM_REG, SUM(IF(COALESCE(CAST(X.INTRNL_SGMNT AS STRING),'')<>COALESCE(CAST(Y.INTRNL_SGMNT_SIMUL AS STRING),'') OR (X.INTRNL_SGMNT IS NULL AND Y.INTRNL_SGMNT_SIMUL IS NOT NULL ) OR (X.INTRNL_SGMNT IS NOT NULL AND Y.INTRNL_SGMNT_SIMUL IS NULL),1,0)) AS NUM_REG_DIF,'1' AS ID_EXEC, CURRENT_TIMESTAMP() AS TIME_EXEC FROM (SELECT entty_id, INTRNL_SGMNT FROM CD_LOAN_TAPES_BCE.LT003_ENTITY WHERE ref_date='${ref_date}' AND nome_perimetro='Individual Corporativo' AND segmento='ESTR' AND ambito='PM' AND entidade='00100')X INNER JOIN (SELECT entty_id AS entty_id_SIMUL, INTRNL_SGMNT AS INTRNL_SGMNT_SIMUL FROM BU_LOANTAPE_WORK.LT003_ENTITY WHERE ref_date='${ref_date}' AND nome_perimetro='Individual Corporativo' AND segmento='ESTR' AND ambito='PM' AND entidade='00100')Y ON X.ENTTY_ID=Y.ENTTY_ID_SIMUL
B20: ENTITY | C20: Coerência | D20: =+UPPER('0. Instruções'!$D$35&"."&VLOOKUP(B20,'0. Instruções'!$C$27:$D$32,2,FALSE)) -> CD_LOAN_TAPES_BCE.LT003_ENTITY | E20: =+UPPER('0. Instruções'!$D$36&"."&VLOOKUP(B20,'0. Instruções'!$C$27:$E$32,3,FALSE)) -> BU_LOANTAPE_WORK.LT003_ENTITY | F20: INTRNL_UNT | H20: VARCHAR2(255) | I20: ="(SELECT "&VLOOKUP(B20,'0. Instruções'!$C$27:$G$32,4,FALSE)&", "&F20&" FROM "&D20&" WHERE "&'0. Instruções'!$D$42&")X" -> (SELECT entty_id, INTRNL_UNT FROM CD_LOAN_TAPES_BCE.LT003_ENTITY WHERE ref_date='${ref_date}' AND nome_perimetro='Individual Corporativo' AND segmento='ESTR' AND ambito='PM' AND entidade='00100')X | J20: ="(SELECT "&VLOOKUP(B20,'0. Instruções'!$C$27:$G$32,4,FALSE)&" AS "&VLOOKUP(B20,'0. Instruções'!$C$27:$G$32,4,FALSE)&"_SIMUL, "&F20&" AS "&F20&"_SIMUL FROM "&E20&" WHERE "&'0. Instruções'!$D$43&")Y" -> (SELECT entty_id AS entty_id_SIMUL, INTRNL_UNT AS INTRNL_UNT_SIMUL FROM BU_LOANTAPE_WORK.LT003_ENTITY WHERE ref_date='${ref_date}' AND nome_perimetro='Individual Corporativo' AND segmento='ESTR' AND ambito='PM' AND entidade='00100')Y | K20: =+UPPER("ON X."&VLOOKUP(B20,'0. Instruções'!$C$27:$G$32,4,FALSE)&"=Y."&VLOOKUP(B20,'0. Instruções'!$C$27:$G$32,4,FALSE)&"_SIMUL") -> ON X.ENTTY_ID=Y.ENTTY_ID_SIMUL | L20: =+IF(C20="Coerência", +IF(LEFT(G20,5)="FLOAT","SELECT '"&UPPER(B20)&"' AS TABELA, '"&UPPER(C20)&"' AS TIPOLOGIA_TESTE,'"&D20&"' AS TABELA_LT,'"&E20&"' AS TABELA_SIMUL,'"&F20&"' AS CAMPO, "&"'${ref_date}' AS REF_DATE, COUNT(*) AS NUM_REG, SUM(IF((ABS(COALESCE(CAST(X."&F20&" AS DECIMAL(18,6)),0)-COALESCE(CAST(Y."&F20&"_SIMUL AS DECIMAL(18,6)),0))>0.000001) OR (X."&F20&" IS NULL AND Y."&F20&"_SIMUL IS NOT NULL ) OR (X."&F20&" IS NOT NULL AND Y."&F20&"_SIMUL IS NULL),1,0)) AS NUM_REG_DIF,'"&MAX('ID1&5'!K:K)+1&"' AS ID_EXEC, CURRENT_TIMESTAMP() AS TIME_EXEC FROM "&I20&" INNER JOIN "&J20&" "&K20,"SELECT '"&UPPER(B20)&"' AS TABELA, '"&UPPER(C20)&"' AS TIPOLOGIA_TESTE,'"&D20&"' AS TABELA_LT,'"&E20&"' AS TABELA_SIMUL,'"&F20&"' AS CAMPO, "&"'${ref_date}' AS REF_DATE, COUNT(*) AS NUM_REG, SUM(IF(COALESCE(CAST(X."&F20&" AS STRING),'')<>COALESCE(CAST(Y."&F20&"_SIMUL AS STRING),'') OR (X."&F20&" IS NULL AND Y."&F20&"_SIMUL IS NOT NULL ) OR (X."&F20&" IS NOT NULL AND Y."&F20&"_SIMUL IS NULL),1,0)) AS NUM_REG_DIF,'"&MAX('ID1&5'!L:L)+1&"' AS ID_EXEC, CURRENT_TIMESTAMP() AS TIME_EXEC FROM "&I20&" INNER JOIN "&J20&" "&K20), IF(C20="Validade",+IF(G20="Code List","SELECT '"&UPPER(B20)&"' AS TABELA, '"&UPPER(C20)&"' AS TIPOLOGIA_TESTE,'"&D20&"' AS TABELA_LT,'N/A' AS TABELA_SIMUL,'"&F20&"' AS CAMPO, "&"'${ref_date}' AS REF_DATE, COUNT(*) AS NUM_REG, SUM(IF(TRIM(CAST(X."&F20&" AS STRING))='' OR TRIM(CAST(X."&F20&" AS STRING)) IS NULL OR CAST(X."&F20&" AS STRING) NOT "&H20&",1,0)) AS NUM_REG_DIF,'"&MAX('ID1&5'!K:K)+1&"' AS ID_EXEC, CURRENT_TIMESTAMP() AS TIME_EXEC FROM "&I20,"SELECT '"&UPPER(B20)&"' AS TABELA, '"&UPPER(C20)&"' AS TIPOLOGIA_TESTE,'"&D20&"' AS TABELA_LT,'N/A' AS TABELA_SIMUL,'"&F20&"' AS CAMPO, "&"'${ref_date}' AS REF_DATE, COUNT(*) AS NUM_REG, SUM(IF(TRIM(CAST(X."&F20&" AS STRING))='' OR TRIM(CAST(X."&F20&" AS STRING)) IS NULL,1,0)) AS NUM_REG_DIF,'"&MAX('ID1&5'!K:K)+1&"' AS ID_EXEC, CURRENT_TIMESTAMP() AS TIME_EXEC FROM "&I20), IF(C20="Caracteres Especiais",+"SELECT '"&UPPER(B20)&"' AS TABELA, '"&UPPER(C20)&"' AS TIPOLOGIA_TESTE,'"&D20&"' AS TABELA_LT,'N/A' AS TABELA_SIMUL,'"&F20&"' AS CAMPO, "&"'${ref_date}' AS REF_DATE, COUNT(*) AS NUM_REG, SUM(IF(REGEXP_REPLACE(TRIM(CAST(X."&F20&" AS STRING)),'[^a-zA-Z0-9_\\s]','') <>TRIM(CAST(X."&F20&" AS STRING)),1,0)) AS NUM_REG_DIF,'"&MAX('ID1&5'!K:K)+1&"' AS ID_EXEC, CURRENT_TIMESTAMP() AS TIME_EXEC FROM "&I20, IF(C20="Missings",+"SELECT '"&UPPER(B20)&"' AS TABELA, '"&UPPER(C20)&"' AS TIPOLOGIA_TESTE,'"&D20&"' AS TABELA_LT,'N/A' AS TABELA_SIMUL,'"&F20&"' AS CAMPO, "&"'${ref_date}' AS REF_DATE, COUNT(*) AS NUM_REG, SUM(IF(TRIM(CAST(X."&F20&" AS STRING)) IN ('0000-00-00','0001-01-01','9999-12-31','MISS','00000','99999999999','99999999999.00','99999999999.000000'),1,0)) AS NUM_REG_DIF,'"&MAX('ID1&5'!K:K)+1&"' AS ID_EXEC, CURRENT_TIMESTAMP() AS TIME_EXEC FROM "&I20, IF(C20="Not applicable",+"SELECT '"&UPPER(B20)&"' AS TABELA, '"&UPPER(C20)&"' AS TIPOLOGIA_TESTE,'"&D20&"' AS TABELA_LT,'N/A' AS TABELA_SIMUL,'"&F20&"' AS CAMPO, "&"'${ref_date}' AS REF_DATE, COUNT(*) AS NUM_REG, SUM(IF(TRIM(CAST(X."&F20&" AS STRING)) IN ('N/A','11111111111','11111111111.00','11111111111.000000','1111-11-11'),1,0)) AS NUM_REG_DIF,'"&MAX('ID1&5'!K:K)+1&"' AS ID_EXEC, CURRENT_TIMESTAMP() AS TIME_EXEC FROM "&I20, IF(C20="Valores extremos",+"SELECT '"&UPPER(B20)&"' AS TABELA, '"&UPPER(C20)&"' AS TIPOLOGIA_TESTE,'"&D20&"' AS TABELA_LT,'N/A' AS TABELA_SIMUL,'"&F20&"' AS CAMPO, "&"'${ref_date}' AS REF_DATE, CAST(MIN("&F20&") AS STRING) AS VALOR_MIN, CAST(MAX("&F20&") AS STRING) AS VALOR_MAX,'"&MAX('ID1&5'!K:K)+1&"' AS ID_EXEC, CURRENT_TIMESTAMP() AS TIME_EXEC FROM "&MID(I20,1,LEN(I20)-2)&" AND CAST("&F20&" AS STRING) NOT IN ('0000-00-00','0001-01-01','9999-12-31','MISS','00000','99999999999','99999999999.00','99999999999.000000','N/A','11111111111','11111111111.00','11111111111.000000','1111-11-11'))X")))))) -> SELECT 'ENTITY' AS TABELA, 'COERÊNCIA' AS TIPOLOGIA_TESTE,'CD_LOAN_TAPES_BCE.LT003_ENTITY' AS TABELA_LT,'BU_LOANTAPE_WORK.LT003_ENTITY' AS TABELA_SIMUL,'INTRNL_UNT' AS CAMPO, '${ref_date}' AS REF_DATE, COUNT(*) AS NUM_REG, SUM(IF(COALESCE(CAST(X.INTRNL_UNT AS STRING),'')<>COALESCE(CAST(Y.INTRNL_UNT_SIMUL AS STRING),'') OR (X.INTRNL_UNT IS NULL AND Y.INTRNL_UNT_SIMUL IS NOT NULL ) OR (X.INTRNL_UNT IS NOT NULL AND Y.INTRNL_UNT_SIMUL IS NULL),1,0)) AS NUM_REG_DIF,'1' AS ID_EXEC, CURRENT_TIMESTAMP() AS TIME_EXEC FROM (SELECT entty_id, INTRNL_UNT FROM CD_LOAN_TAPES_BCE.LT003_ENTITY WHERE ref_date='${ref_date}' AND nome_perimetro='Individual Corporativo' AND segmento='ESTR' AND ambito='PM' AND entidade='00100')X INNER JOIN (SELECT entty_id AS entty_id_SIMUL, INTRNL_UNT AS INTRNL_UNT_SIMUL FROM BU_LOANTAPE_WORK.LT003_ENTITY WHERE ref_date='${ref_date}' AND nome_perimetro='Individual Corporativo' AND segmento='ESTR' AND ambito='PM' AND entidade='00100')Y ON X.ENTTY_ID=Y.ENTTY_ID_SIMUL | M20: =+"UNION ALL "&L20 -> UNION ALL SELECT 'ENTITY' AS TABELA, 'COERÊNCIA' AS TIPOLOGIA_TESTE,'CD_LOAN_TAPES_BCE.LT003_ENTITY' AS TABELA_LT,'BU_LOANTAPE_WORK.LT003_ENTITY' AS TABELA_SIMUL,'INTRNL_UNT' AS CAMPO, '${ref_date}' AS REF_DATE, COUNT(*) AS NUM_REG, SUM(IF(COALESCE(CAST(X.INTRNL_UNT AS STRING),'')<>COALESCE(CAST(Y.INTRNL_UNT_SIMUL AS STRING),'') OR (X.INTRNL_UNT IS NULL AND Y.INTRNL_UNT_SIMUL IS NOT NULL ) OR (X.INTRNL_UNT IS NOT NULL AND Y.INTRNL_UNT_SIMUL IS NULL),1,0)) AS NUM_REG_DIF,'1' AS ID_EXEC, CURRENT_TIMESTAMP() AS TIME_EXEC FROM (SELECT entty_id, INTRNL_UNT FROM CD_LOAN_TAPES_BCE.LT003_ENTITY WHERE ref_date='${ref_date}' AND nome_perimetro='Individual Corporativo' AND segmento='ESTR' AND ambito='PM' AND entidade='00100')X INNER JOIN (SELECT entty_id AS entty_id_SIMUL, INTRNL_UNT AS INTRNL_UNT_SIMUL FROM BU_LOANTAPE_WORK.LT003_ENTITY WHERE ref_date='${ref_date}' AND nome_perimetro='Individual Corporativo' AND segmento='ESTR' AND ambito='PM' AND entidade='00100')Y ON X.ENTTY_ID=Y.ENTTY_ID_SIMUL
... B112: ENTITY | C112: Coerência | D112: =+UPPER('0. Instruções'!$D$35&"."&VLOOKUP(B112,'0. Instruções'!$C$27:$D$32,2,FALSE)) -> CD_LOAN_TAPES_BCE.LT003_ENTITY | E112: =+UPPER('0. Instruções'!$D$36&"."&VLOOKUP(B112,'0. Instruções'!$C$27:$E$32,3,FALSE)) -> BU_LOANTAPE_WORK.LT003_ENTITY | F112: ENTTY_ID_BDR | H112: VARCHAR2(60) | I112: ="(SELECT "&VLOOKUP(B112,'0. Instruções'!$C$27:$G$32,4,FALSE)&", "&F112&" FROM "&D112&" WHERE "&'0. Instruções'!$D$42&")X" -> (SELECT entty_id, ENTTY_ID_BDR FROM CD_LOAN_TAPES_BCE.LT003_ENTITY WHERE ref_date='${ref_date}' AND nome_perimetro='Individual Corporativo' AND segmento='ESTR' AND ambito='PM' AND entidade='00100')X | J112: ="(SELECT "&VLOOKUP(B112,'0. Instruções'!$C$27:$G$32,4,FALSE)&" AS "&VLOOKUP(B112,'0. Instruções'!$C$27:$G$32,4,FALSE)&"_SIMUL, "&F112&" AS "&F112&"_SIMUL FROM "&E112&" WHERE "&'0. Instruções'!$D$43&")Y" -> (SELECT entty_id AS entty_id_SIMUL, ENTTY_ID_BDR AS ENTTY_ID_BDR_SIMUL FROM BU_LOANTAPE_WORK.LT003_ENTITY WHERE ref_date='${ref_date}' AND nome_perimetro='Individual Corporativo' AND segmento='ESTR' AND ambito='PM' AND entidade='00100')Y | K112: =+UPPER("ON X."&VLOOKUP(B112,'0. Instruções'!$C$27:$G$32,4,FALSE)&"=Y."&VLOOKUP(B112,'0. Instruções'!$C$27:$G$32,4,FALSE)&"_SIMUL") -> ON X.ENTTY_ID=Y.ENTTY_ID_SIMUL | L112: =+IF(C112="Coerência", +IF(LEFT(G112,5)="FLOAT","SELECT '"&UPPER(B112)&"' AS TABELA, '"&UPPER(C112)&"' AS TIPOLOGIA_TESTE,'"&D112&"' AS TABELA_LT,'"&E112&"' AS TABELA_SIMUL,'"&F112&"' AS CAMPO, "&"'${ref_date}' AS REF_DATE, COUNT(*) AS NUM_REG, SUM(IF((ABS(COALESCE(CAST(X."&F112&" AS DECIMAL(18,6)),0)-COALESCE(CAST(Y."&F112&"_SIMUL AS DECIMAL(18,6)),0))>0.000001) OR (X."&F112&" IS NULL AND Y."&F112&"_SIMUL IS NOT NULL ) OR (X."&F112&" IS NOT NULL AND Y."&F112&"_SIMUL IS NULL),1,0)) AS NUM_REG_DIF,'"&MAX('ID1&5'!K:K)+1&"' AS ID_EXEC, CURRENT_TIMESTAMP() AS TIME_EXEC FROM "&I112&" INNER JOIN "&J112&" "&K112,"SELECT '"&UPPER(B112)&"' AS TABELA, '"&UPPER(C112)&"' AS TIPOLOGIA_TESTE,'"&D112&"' AS TABELA_LT,'"&E112&"' AS TABELA_SIMUL,'"&F112&"' AS CAMPO, "&"'${ref_date}' AS REF_DATE, COUNT(*) AS NUM_REG, SUM(IF(COALESCE(CAST(X."&F112&" AS STRING),'')<>COALESCE(CAST(Y."&F112&"_SIMUL AS STRING),'') OR (X."&F112&" IS NULL AND Y."&F112&"_SIMUL IS NOT NULL ) OR (X."&F112&" IS NOT NULL AND Y."&F112&"_SIMUL IS NULL),1,0)) AS NUM_REG_DIF,'"&MAX('ID1&5'!L:L)+1&"' AS ID_EXEC, CURRENT_TIMESTAMP() AS TIME_EXEC FROM "&I112&" INNER JOIN "&J112&" "&K112), IF(C112="Validade",+IF(G112="Code List","SELECT '"&UPPER(B112)&"' AS TABELA, '"&UPPER(C112)&"' AS TIPOLOGIA_TESTE,'"&D112&"' AS TABELA_LT,'N/A' AS TABELA_SIMUL,'"&F112&"' AS CAMPO, "&"'${ref_date}' AS REF_DATE, COUNT(*) AS NUM_REG, SUM(IF(TRIM(CAST(X."&F112&" AS STRING))='' OR TRIM(CAST(X."&F112&" AS STRING)) IS NULL OR CAST(X."&F112&" AS STRING) NOT "&H112&",1,0)) AS NUM_REG_DIF,'"&MAX('ID1&5'!K:K)+1&"' AS ID_EXEC, CURRENT_TIMESTAMP() AS TIME_EXEC FROM "&I112,"SELECT '"&UPPER(B112)&"' AS TABELA, '"&UPPER(C112)&"' AS TIPOLOGIA_TESTE,'"&D112&"' AS TABELA_LT,'N/A' AS TABELA_SIMUL,'"&F112&"' AS CAMPO, "&"'${ref_date}' AS REF_DATE, COUNT(*) AS NUM_REG, SUM(IF(TRIM(CAST(X."&F112&" AS STRING))='' OR TRIM(CAST(X."&F112&" AS STRING)) IS NULL,1,0)) AS NUM_REG_DIF,'"&MAX('ID1&5'!K:K)+1&"' AS ID_EXEC, CURRENT_TIMESTAMP() AS TIME_EXEC FROM "&I112), IF(C112="Caracteres Especiais",+"SELECT '"&UPPER(B112)&"' AS TABELA, '"&UPPER(C112)&"' AS TIPOLOGIA_TESTE,'"&D112&"' AS TABELA_LT,'N/A' AS TABELA_SIMUL,'"&F112&"' AS CAMPO, "&"'${ref_date}' AS REF_DATE, COUNT(*) AS NUM_REG, SUM(IF(REGEXP_REPLACE(TRIM(CAST(X."&F112&" AS STRING)),'[^a-zA-Z0-9_\\s]','') <>TRIM(CAST(X."&F112&" AS STRING)),1,0)) AS NUM_REG_DIF,'"&MAX('ID1&5'!K:K)+1&"' AS ID_EXEC, CURRENT_TIMESTAMP() AS TIME_EXEC FROM "&I112, IF(C112="Missings",+"SELECT '"&UPPER(B112)&"' AS TABELA, '"&UPPER(C112)&"' AS TIPOLOGIA_TESTE,'"&D112&"' AS TABELA_LT,'N/A' AS TABELA_SIMUL,'"&F112&"' AS CAMPO, "&"'${ref_date}' AS REF_DATE, COUNT(*) AS NUM_REG, SUM(IF(TRIM(CAST(X."&F112&" AS STRING)) IN ('0000-00-00','0001-01-01','9999-12-31','MISS','00000','99999999999','99999999999.00','99999999999.000000'),1,0)) AS NUM_REG_DIF,'"&MAX('ID1&5'!K:K)+1&"' AS ID_EXEC, CURRENT_TIMESTAMP() AS TIME_EXEC FROM "&I112, IF(C112="Not applicable",+"SELECT '"&UPPER(B112)&"' AS TABELA, '"&UPPER(C112)&"' AS TIPOLOGIA_TESTE,'"&D112&"' AS TABELA_LT,'N/A' AS TABELA_SIMUL,'"&F112&"' AS CAMPO, "&"'${ref_date}' AS REF_DATE, COUNT(*) AS NUM_REG, SUM(IF(TRIM(CAST(X."&F112&" AS STRING)) IN ('N/A','11111111111','11111111111.00','11111111111.000000','1111-11-11'),1,0)) AS NUM_REG_DIF,'"&MAX('ID1&5'!K:K)+1&"' AS ID_EXEC, CURRENT_TIMESTAMP() AS TIME_EXEC FROM "&I112, IF(C112="Valores extremos",+"SELECT '"&UPPER(B112)&"' AS TABELA, '"&UPPER(C112)&"' AS TIPOLOGIA_TESTE,'"&D112&"' AS TABELA_LT,'N/A' AS TABELA_SIMUL,'"&F112&"' AS CAMPO, "&"'${ref_date}' AS REF_DATE, CAST(MIN("&F112&") AS STRING) AS VALOR_MIN, CAST(MAX("&F112&") AS STRING) AS VALOR_MAX,'"&MAX('ID1&5'!K:K)+1&"' AS ID_EXEC, CURRENT_TIMESTAMP() AS TIME_EXEC FROM "&MID(I112,1,LEN(I112)-2)&" AND CAST("&F112&" AS STRING) NOT IN ('0000-00-00','0001-01-01','9999-12-31','MISS','00000','99999999999','99999999999.00','99999999999.000000','N/A','11111111111','11111111111.00','11111111111.000000','1111-11-11'))X")))))) -> SELECT 'ENTITY' AS TABELA, 'COERÊNCIA' AS TIPOLOGIA_TESTE,'CD_LOAN_TAPES_BCE.LT003_ENTITY' AS TABELA_LT,'BU_LOANTAPE_WORK.LT003_ENTITY' AS TABELA_SIMUL,'ENTTY_ID_BDR' AS CAMPO, '${ref_date}' AS REF_DATE, COUNT(*) AS NUM_REG, SUM(IF(COALESCE(CAST(X.ENTTY_ID_BDR AS STRING),'')<>COALESCE(CAST(Y.ENTTY_ID_BDR_SIMUL AS STRING),'') OR (X.ENTTY_ID_BDR IS NULL AND Y.ENTTY_ID_BDR_SIMUL IS NOT NULL ) OR (X.ENTTY_ID_BDR IS NOT NULL AND Y.ENTTY_ID_BDR_SIMUL IS NULL),1,0)) AS NUM_REG_DIF,'1' AS ID_EXEC, CURRENT_TIMESTAMP() AS TIME_EXEC FROM (SELECT entty_id, ENTTY_ID_BDR FROM CD_LOAN_TAPES_BCE.LT003_ENTITY WHERE ref_date='${ref_date}' AND nome_perimetro='Individual Corporativo' AND segmento='ESTR' AND ambito='PM' AND entidade='00100')X INNER JOIN (SELECT entty_id AS entty_id_SIMUL, ENTTY_ID_BDR AS ENTTY_ID_BDR_SIMUL FROM BU_LOANTAPE_WORK.LT003_ENTITY WHERE ref_date='${ref_date}' AND nome_perimetro='Individual Corporativo' AND segmento='ESTR' AND ambito='PM' AND entidade='00100')Y ON X.ENTTY_ID=Y.ENTTY_ID_SIMUL | M112: =+"UNION ALL "&L112 -> UNION ALL SELECT 'ENTITY' AS TABELA, 'COERÊNCIA' AS TIPOLOGIA_TESTE,'CD_LOAN_TAPES_BCE.LT003_ENTITY' AS TABELA_LT,'BU_LOANTAPE_WORK.LT003_ENTITY' AS TABELA_SIMUL,'ENTTY_ID_BDR' AS CAMPO, '${ref_date}' AS REF_DATE, COUNT(*) AS NUM_REG, SUM(IF(COALESCE(CAST(X.ENTTY_ID_BDR AS STRING),'')<>COALESCE(CAST(Y.ENTTY_ID_BDR_SIMUL AS STRING),'') OR (X.ENTTY_ID_BDR IS NULL AND Y.ENTTY_ID_BDR_SIMUL IS NOT NULL ) OR (X.ENTTY_ID_BDR IS NOT NULL AND Y.ENTTY_ID_BDR_SIMUL IS NULL),1,0)) AS NUM_REG_DIF,'1' AS ID_EXEC, CURRENT_TIMESTAMP() AS TIME_EXEC FROM (SELECT entty_id, ENTTY_ID_BDR FROM CD_LOAN_TAPES_BCE.LT003_ENTITY WHERE ref_date='${ref_date}' AND nome_perimetro='Individual Corporativo' AND segmento='ESTR' AND ambito='PM' AND entidade='00100')X INNER JOIN (SELECT entty_id AS entty_id_SIMUL, ENTTY_ID_BDR AS ENTTY_ID_BDR_SIMUL FROM BU_LOANTAPE_WORK.LT003_ENTITY WHERE ref_date='${ref_date}' AND nome_perimetro='Individual Corporativo' AND segmento='ESTR' AND ambito='PM' AND entidade='00100')Y ON X.ENTTY_ID=Y.ENTTY_ID_SIMUL
