Workbook

Sheet 1. Tipologias Testes GD
B8: Âmbito | C8: Origem | D8: Campo | E8: Status | F8: Tipologia_Testes | G8: Necessidade de re-especificação? | H8: Complexidade | I8: Estimação (horas) | J8: Notas
B9: GD | C9: - | D9: n.a. | F9: 1. Teste de universo | H9: Alta | I9: =INDEX(Auxiliar!$D$5:$F$11,MATCH(Table1[[#This Row],[Tipologia_Testes]],Auxiliar!$B$5:$B$11,0),MATCH(Table1[[#This Row],[Complexidade]],Auxiliar!$D$4:$F$4,0)) -> 8
B10: GD | C10: Modelo Verde | D10: SSTNBL_CTGRY | E10: Concluído | F10: 2. Simulação | I10: =INDEX(Auxiliar!$D$5:$F$11,MATCH(Table1[[#This Row],[Tipologia_Testes]],Auxiliar!$B$5:$B$11,0),MATCH(Table1[[#This Row],[Complexidade]],Auxiliar!$D$4:$F$4,0)) -> #N/A
B11: GD | C11: Modelo Verde | D11: SSTNBL_CTGRY | E11: Concluído | F11: 3. Testes comparativos (Espec. VS Impl.) | I11: =INDEX(Auxiliar!$D$5:$F$11,MATCH(Table1[[#This Row],[Tipologia_Testes]],Auxiliar!$B$5:$B$11,0),MATCH(Table1[[#This Row],[Complexidade]],Auxiliar!$D$4:$F$4,0)) -> #N/A
B12: GD | C12: Modelo Verde | D12: SSTNBL_CTGRY | E12: Concluído | F12: 4. Validação de parametrizações | I12: =INDEX(Auxiliar!$D$5:$F$11,MATCH(Table1[[#This Row],[Tipologia_Testes]],Auxiliar!$B$5:$B$11,0),MATCH(Table1[[#This Row],[Complexidade]],Auxiliar!$D$4:$F$4,0)) -> #N/A
B13: GD | C13: Modelo Verde | D13: SSTNBL_CTGRY | E13: Concluído | F13: 6. Validação de formatos | I13: =INDEX(Auxiliar!$D$5:$F$11,MATCH(Table1[[#This Row],[Tipologia_Testes]],Auxiliar!$B$5:$B$11,0),MATCH(Table1[[#This Row],[Complexidade]],Auxiliar!$D$4:$F$4,0)) -> #N/A
B14: GD | C14: Modelo Verde | D14: SSTNBL_CTGRY | E14: Concluído | F14: 7. Validação de controlos corporativos | I14: =INDEX(Auxiliar!$D$5:$F$11,MATCH(Table1[[#This Row],[Tipologia_Testes]],Auxiliar!$B$5:$B$11,0),MATCH(Table1[[#This Row],[Complexidade]],Auxiliar!$D$4:$F$4,0)) -> #N/A
B15: GD | C15: LT ESTR | D15: DFLT_STTS_INSTRMNT | E15: Concluído | F15: 5. Teste comparativos com LT | I15: =INDEX(Auxiliar!$D$5:$F$11,MATCH(Table1[[#This Row],[Tipologia_Testes]],Auxiliar!$B$5:$B$11,0),MATCH(Table1[[#This Row],[Complexidade]],Auxiliar!$D$4:$F$4,0)) -> #N/A
B16: GD | C16: LT ESTR | D16: ACCMLTD_CHNGS_FV_CR_INSTRMNT | E16: Concluído | F16: 5. Teste comparativos com LT | I16: =INDEX(Auxiliar!$D$5:$F$11,MATCH(Table1[[#This Row],[Tipologia_Testes]],Auxiliar!$B$5:$B$11,0),MATCH(Table1[[#This Row],[Complexidade]],Auxiliar!$D$4:$F$4,0)) -> #N/A
B17: GD | C17: LT ESTR | D17: ACCMLTD_IMPRMNT_INSTRMNT | E17: Concluído | F17: 5. Teste comparativos com LT | I17: =INDEX(Auxiliar!$D$5:$F$11,MATCH(Table1[[#This Row],[Tipologia_Testes]],Auxiliar!$B$5:$B$11,0),MATCH(Table1[[#This Row],[Complexidade]],Auxiliar!$D$4:$F$4,0)) -> #N/A
B18: GD | C18: LT ESTR | D18: ACCNTNG_CLSSFCTN | E18: Concluído | F18: 5. Teste comparativos com LT | I18: =INDEX(Auxiliar!$D$5:$F$11,MATCH(Table1[[#This Row],[Tipologia_Testes]],Auxiliar!$B$5:$B$11,0),MATCH(Table1[[#This Row],[Complexidade]],Auxiliar!$D$4:$F$4,0)) -> #N/A
B19: GD | C19: LT ESTR | D19: COD_SOC | E19: Concluído | F19: 5. Teste comparativos com LT | I19: =INDEX(Auxiliar!$D$5:$F$11,MATCH(Table1[[#This Row],[Tipologia_Testes]],Auxiliar!$B$5:$B$11,0),MATCH(Table1[[#This Row],[Complexidade]],Auxiliar!$D$4:$F$4,0)) -> #N/A
B20: GD | C20: LT ESTR | D20: DT_RFRNC | E20: Concluído | F20: 5. Teste comparativos com LT | I20: =INDEX(Auxiliar!$D$5:$F$11,MATCH(Table1[[#This Row],[Tipologia_Testes]],Auxiliar!$B$5:$B$11,0),MATCH(Table1[[#This Row],[Complexidade]],Auxiliar!$D$4:$F$4,0)) -> #N/A
B21: GD | C21: LT ESTR | D21: GRSS_CRRYNG_AMNT_INSTRMNT | E21: Concluído | F21: 5. Teste comparativos com LT | I21: =INDEX(Auxiliar!$D$5:$F$11,MATCH(Table1[[#This Row],[Tipologia_Testes]],Auxiliar!$B$5:$B$11,0),MATCH(Table1[[#This Row],[Complexidade]],Auxiliar!$D$4:$F$4,0)) -> #N/A
... B23: GD | C23: LT ESTR | D23: IMPRMNT_STTS | E23: Concluído | F23: 5. Teste comparativos com LT | I23: =INDEX(Auxiliar!$D$5:$F$11,MATCH(Table1[[#This Row],[Tipologia_Testes]],Auxiliar!$B$5:$B$11,0),MATCH(Table1[[#This Row],[Complexidade]],Auxiliar!$D$4:$F$4,0)) -> #N/A
B24: GD | C24: Outro | D24: INSTRMNT_ID | E24: Em Teste | F24: 2. Simulação | G24: Sim | H24: Alta | I24: =INDEX(Auxiliar!$D$5:$F$11,MATCH(Table1[[#This Row],[Tipologia_Testes]],Auxiliar!$B$5:$B$11,0),MATCH(Table1[[#This Row],[Complexidade]],Auxiliar!$D$4:$F$4,0)) -> 8 | J24: Pendente de Business_area
B25: GD | C25: Outro | D25: INSTRMNT_ID | E25: Em Teste | F25: 3. Testes comparativos (Espec. VS Impl.) | G25: Sim | H25: Alta | I25: =INDEX(Auxiliar!$D$5:$F$11,MATCH(Table1[[#This Row],[Tipologia_Testes]],Auxiliar!$B$5:$B$11,0),MATCH(Table1[[#This Row],[Complexidade]],Auxiliar!$D$4:$F$4,0)) -> 8 | J25: Pendente de Business_area
B26: GD | C26: Outro | D26: INSTRMNT_ID | E26: Em Teste | F26: 6. Validação de formatos | G26: Sim | H26: Alta | I26: =INDEX(Auxiliar!$D$5:$F$11,MATCH(Table1[[#This Row],[Tipologia_Testes]],Auxiliar!$B$5:$B$11,0),MATCH(Table1[[#This Row],[Complexidade]],Auxiliar!$D$4:$F$4,0)) -> 1 | J26: Pendente de Business_area
B27: GD | C27: LT ESTR | D27: LCL_INSTMRNT_ID | E27: Concluído | F27: 5. Teste comparativos com LT | I27: =INDEX(Auxiliar!$D$5:$F$11,MATCH(Table1[[#This Row],[Tipologia_Testes]],Auxiliar!$B$5:$B$11,0),MATCH(Table1[[#This Row],[Complexidade]],Auxiliar!$D$4:$F$4,0)) -> #N/A
B28: GD | C28: LT ESTR | D28: OFF_BLNC_SHT_AMNT_INSTRMNT | E28: Concluído | F28: 5. Teste comparativos com LT | I28: =INDEX(Auxiliar!$D$5:$F$11,MATCH(Table1[[#This Row],[Tipologia_Testes]],Auxiliar!$B$5:$B$11,0),MATCH(Table1[[#This Row],[Complexidade]],Auxiliar!$D$4:$F$4,0)) -> #N/A
B29: GD | C29: LT ESTR | D29: PRFRMNG_STTS | E29: Concluído | F29: 5. Teste comparativos com LT | I29: =INDEX(Auxiliar!$D$5:$F$11,MATCH(Table1[[#This Row],[Tipologia_Testes]],Auxiliar!$B$5:$B$11,0),MATCH(Table1[[#This Row],[Complexidade]],Auxiliar!$D$4:$F$4,0)) -> #N/A
B30: GD | C30: LT ESTR | D30: PRVSNS_OFF_BLNC_SHT | E30: Concluído | F30: 5. Teste comparativos com LT | I30: =INDEX(Auxiliar!$D$5:$F$11,MATCH(Table1[[#This Row],[Tipologia_Testes]],Auxiliar!$B$5:$B$11,0),MATCH(Table1[[#This Row],[Complexidade]],Auxiliar!$D$4:$F$4,0)) -> #N/A
B31: GD | C31: LT ESTR | D31: SUBPORTFOLIO_ID | E31: Concluído | F31: 5. Teste comparativos com LT | I31: =INDEX(Auxiliar!$D$5:$F$11,MATCH(Table1[[#This Row],[Tipologia_Testes]],Auxiliar!$B$5:$B$11,0),MATCH(Table1[[#This Row],[Complexidade]],Auxiliar!$D$4:$F$4,0)) -> #N/A
B32: GD | C32: LT ESTR | D32: TYP_INSTRMNT | E32: Concluído | F32: 5. Teste comparativos com LT | I32: =INDEX(Auxiliar!$D$5:$F$11,MATCH(Table1[[#This Row],[Tipologia_Testes]],Auxiliar!$B$5:$B$11,0),MATCH(Table1[[#This Row],[Complexidade]],Auxiliar!$D$4:$F$4,0)) -> #N/A
B33: GD | C33: LT ESTR | D33: RWA | E33: Concluído | F33: 5. Teste comparativos com LT | I33: =INDEX(Auxiliar!$D$5:$F$11,MATCH(Table1[[#This Row],[Tipologia_Testes]],Auxiliar!$B$5:$B$11,0),MATCH(Table1[[#This Row],[Complexidade]],Auxiliar!$D$4:$F$4,0)) -> #N/A
B34: GD | C34: LT ESTR | D34: COD_SOC_INTRGRP | E34: Concluído | F34: 5. Teste comparativos com LT | I34: =INDEX(Auxiliar!$D$5:$F$11,MATCH(Table1[[#This Row],[Tipologia_Testes]],Auxiliar!$B$5:$B$11,0),MATCH(Table1[[#This Row],[Complexidade]],Auxiliar!$D$4:$F$4,0)) -> #N/A
B35: GD | C35: Corporativo | D35: BSNSS_AREA_DSTNTN | E35: Concluído | F35: 2. Simulação | I35: =INDEX(Auxiliar!$D$5:$F$11,MATCH(Table1[[#This Row],[Tipologia_Testes]],Auxiliar!$B$5:$B$11,0),MATCH(Table1[[#This Row],[Complexidade]],Auxiliar!$D$4:$F$4,0)) -> #N/A
B36: GD | C36: Corporativo | D36: BSNSS_AREA_DSTNTN | E36: Concluído | F36: 3. Testes comparativos (Espec. VS Impl.) | I36: =INDEX(Auxiliar!$D$5:$F$11,MATCH(Table1[[#This Row],[Tipologia_Testes]],Auxiliar!$B$5:$B$11,0),MATCH(Table1[[#This Row],[Complexidade]],Auxiliar!$D$4:$F$4,0)) -> #N/A
B37: GD | C37: Corporativo | D37: BSNSS_AREA_DSTNTN | E37: Concluído | F37: 6. Validação de formatos | I37: =INDEX(Auxiliar!$D$5:$F$11,MATCH(Table1[[#This Row],[Tipologia_Testes]],Auxiliar!$B$5:$B$11,0),MATCH(Table1[[#This Row],[Complexidade]],Auxiliar!$D$4:$F$4,0)) -> #N/A
B38: GD | C38: Corporativo | D38: BSNSS_AREA_DSTNTN | E38: Concluído | F38: 7. Validação de controlos corporativos | I38: =INDEX(Auxiliar!$D$5:$F$11,MATCH(Table1[[#This Row],[Tipologia_Testes]],Auxiliar!$B$5:$B$11,0),MATCH(Table1[[#This Row],[Complexidade]],Auxiliar!$D$4:$F$4,0)) -> #N/A
... B50: GD | C50: Corporativo | D50: COD_SOC_DSTNTN | E50: Concluído | F50: 7. Validação de controlos corporativos | I50: =INDEX(Auxiliar!$D$5:$F$11,MATCH(Table1[[#This Row],[Tipologia_Testes]],Auxiliar!$B$5:$B$11,0),MATCH(Table1[[#This Row],[Complexidade]],Auxiliar!$D$4:$F$4,0)) -> #N/A
B51: GD | C51: Corporativo | D51: RWA_OFF_BLNC | E51: Concluído | F51: 2. Simulação | I51: =INDEX(Auxiliar!$D$5:$F$11,MATCH(Table1[[#This Row],[Tipologia_Testes]],Auxiliar!$B$5:$B$11,0),MATCH(Table1[[#This Row],[Complexidade]],Auxiliar!$D$4:$F$4,0)) -> #N/A | J51: 27/03/2024 (Corp): Deve ser aprovisionado localmente com o valor correspondente de não aplicável (11111111111)
B52: GD | C52: Corporativo | D52: RWA_OFF_BLNC | E52: Concluído | F52: 3. Testes comparativos (Espec. VS Impl.) | I52: =INDEX(Auxiliar!$D$5:$F$11,MATCH(Table1[[#This Row],[Tipologia_Testes]],Auxiliar!$B$5:$B$11,0),MATCH(Table1[[#This Row],[Complexidade]],Auxiliar!$D$4:$F$4,0)) -> #N/A | J52: =J51 -> 27/03/2024 (Corp): Deve ser aprovisionado localmente com o valor correspondente de não aplicável (11111111111)
B53: GD | C53: Corporativo | D53: RWA_OFF_BLNC | E53: Concluído | F53: 6. Validação de formatos | I53: =INDEX(Auxiliar!$D$5:$F$11,MATCH(Table1[[#This Row],[Tipologia_Testes]],Auxiliar!$B$5:$B$11,0),MATCH(Table1[[#This Row],[Complexidade]],Auxiliar!$D$4:$F$4,0)) -> #N/A | J53: =J52 -> 27/03/2024 (Corp): Deve ser aprovisionado localmente com o valor correspondente de não aplicável (11111111111)
B54: GD | C54: Corporativo | D54: RWA_OFF_BLNC | E54: Concluído | F54: 7. Validação de controlos corporativos | I54: =INDEX(Auxiliar!$D$5:$F$11,MATCH(Table1[[#This Row],[Tipologia_Testes]],Auxiliar!$B$5:$B$11,0),MATCH(Table1[[#This Row],[Complexidade]],Auxiliar!$D$4:$F$4,0)) -> #N/A | J54: =J53 -> 27/03/2024 (Corp): Deve ser aprovisionado localmente com o valor correspondente de não aplicável (11111111111)
B55: GD | C55: Rentabilidade | D55: INTRNL_TRNSFR_RT_OFF_BLNC | E55: Concluído | F55: 2. Simulação | I55: =INDEX(Auxiliar!$D$5:$F$11,MATCH(Table1[[#This Row],[Tipologia_Testes]],Auxiliar!$B$5:$B$11,0),MATCH(Table1[[#This Row],[Complexidade]],Auxiliar!$D$4:$F$4,0)) -> #N/A | J55: 27/03/2024 (Corp): O campo Internal transfer rate from off balance amounts não está incluído no âmbito de contratos do Santander Portugal. Assim, o campo deverá ser aprovisionado com o valor correspondente a não aplicável (11111111111).
B56: GD | C56: Rentabilidade | D56: INTRNL_TRNSFR_RT_OFF_BLNC | E56: Concluído | F56: 3. Testes comparativos (Espec. VS Impl.) | I56: =INDEX(Auxiliar!$D$5:$F$11,MATCH(Table1[[#This Row],[Tipologia_Testes]],Auxiliar!$B$5:$B$11,0),MATCH(Table1[[#This Row],[Complexidade]],Auxiliar!$D$4:$F$4,0)) -> #N/A | J56: =J55 -> 27/03/2024 (Corp): O campo Internal transfer rate from off balance amounts não está incluído no âmbito de contratos do Santander Portugal. Assim, o campo deverá ser aprovisionado com o valor correspondente a não aplicável (11111111111).
B57: GD | C57: Rentabilidade | D57: INTRNL_TRNSFR_RT_OFF_BLNC | E57: Concluído | F57: 6. Validação de formatos | I57: =INDEX(Auxiliar!$D$5:$F$11,MATCH(Table1[[#This Row],[Tipologia_Testes]],Auxiliar!$B$5:$B$11,0),MATCH(Table1[[#This Row],[Complexidade]],Auxiliar!$D$4:$F$4,0)) -> #N/A | J57: =J56 -> 27/03/2024 (Corp): O campo Internal transfer rate from off balance amounts não está incluído no âmbito de contratos do Santander Portugal. Assim, o campo deverá ser aprovisionado com o valor correspondente a não aplicável (11111111111).
B58: GD | C58: Rentabilidade | D58: INTRNL_TRNSFR_RT_OFF_BLNC | E58: Concluído | F58: 7. Validação de controlos corporativos | I58: =INDEX(Auxiliar!$D$5:$F$11,MATCH(Table1[[#This Row],[Tipologia_Testes]],Auxiliar!$B$5:$B$11,0),MATCH(Table1[[#This Row],[Complexidade]],Auxiliar!$D$4:$F$4,0)) -> #N/A | J58: =J57 -> 27/03/2024 (Corp): O campo Internal transfer rate from off balance amounts não está incluído no âmbito de contratos do Santander Portugal. Assim, o campo deverá ser aprovisionado com o valor correspondente a não aplicável (11111111111).
B59: GD | C59: Rentabilidade | D59: BSNSS_AREA | E59: Em Teste | F59: 2. Simulação | H59: Alta | I59: =INDEX(Auxiliar!$D$5:$F$11,MATCH(Table1[[#This Row],[Tipologia_Testes]],Auxiliar!$B$5:$B$11,0),MATCH(Table1[[#This Row],[Complexidade]],Auxiliar!$D$4:$F$4,0)) -> 8 | J59: Pendente de decisão
B60: GD | C60: Rentabilidade | D60: BSNSS_AREA | E60: Em Teste | F60: 3. Testes comparativos (Espec. VS Impl.) | H60: Alta | I60: =INDEX(Auxiliar!$D$5:$F$11,MATCH(Table1[[#This Row],[Tipologia_Testes]],Auxiliar!$B$5:$B$11,0),MATCH(Table1[[#This Row],[Complexidade]],Auxiliar!$D$4:$F$4,0)) -> 8 | J60: Pendente de decisão
B61: GD | C61: Rentabilidade | D61: BSNSS_AREA | E61: Em Teste | F61: 4. Validação de parametrizações | H61: Alta | I61: =INDEX(Auxiliar!$D$5:$F$11,MATCH(Table1[[#This Row],[Tipologia_Testes]],Auxiliar!$B$5:$B$11,0),MATCH(Table1[[#This Row],[Complexidade]],Auxiliar!$D$4:$F$4,0)) -> 8 | J61: Pendente de decisão
B62: GD | C62: Rentabilidade | D62: BSNSS_AREA | E62: Em Teste | F62: 6. Validação de formatos | H62: Alta | I62: =INDEX(Auxiliar!$D$5:$F$11,MATCH(Table1[[#This Row],[Tipologia_Testes]],Auxiliar!$B$5:$B$11,0),MATCH(Table1[[#This Row],[Complexidade]],Auxiliar!$D$4:$F$4,0)) -> 1 | J62: Pendente de decisão
B63: GD | C63: Rentabilidade | D63: BSNSS_AREA | E63: Em Teste | F63: 7. Validação de controlos corporativos | H63: Alta | I63: =INDEX(Auxiliar!$D$5:$F$11,MATCH(Table1[[#This Row],[Tipologia_Testes]],Auxiliar!$B$5:$B$11,0),MATCH(Table1[[#This Row],[Complexidade]],Auxiliar!$D$4:$F$4,0)) -> 8 | J63: Pendente de decisão
B64: GD | C64: Rentabilidade | D64: AVRG_BLNC | E64: Em Teste | F64: 2. Simulação | I64: =INDEX(Auxiliar!$D$5:$F$11,MATCH(Table1[[#This Row],[Tipologia_Testes]],Auxiliar!$B$5:$B$11,0),MATCH(Table1[[#This Row],[Complexidade]],Auxiliar!$D$4:$F$4,0)) -> #N/A
B65: GD | C65: Rentabilidade | D65: AVRG_BLNC | E65: Em Teste | F65: 3. Testes comparativos (Espec. VS Impl.) | I65: =INDEX(Auxiliar!$D$5:$F$11,MATCH(Table1[[#This Row],[Tipologia_Testes]],Auxiliar!$B$5:$B$11,0),MATCH(Table1[[#This Row],[Complexidade]],Auxiliar!$D$4:$F$4,0)) -> #N/A
B66: GD | C66: Rentabilidade | D66: AVRG_BLNC | E66: Em Teste | F66: 4. Validação de parametrizações | I66: =INDEX(Auxiliar!$D$5:$F$11,MATCH(Table1[[#This Row],[Tipologia_Testes]],Auxiliar!$B$5:$B$11,0),MATCH(Table1[[#This Row],[Complexidade]],Auxiliar!$D$4:$F$4,0)) -> #N/A
B67: GD | C67: Rentabilidade | D67: AVRG_BLNC | E67: Em Teste | F67: 6. Validação de formatos | I67: =INDEX(Auxiliar!$D$5:$F$11,MATCH(Table1[[#This Row],[Tipologia_Testes]],Auxiliar!$B$5:$B$11,0),MATCH(Table1[[#This Row],[Complexidade]],Auxiliar!$D$4:$F$4,0)) -> #N/A
B68: GD | C68: Rentabilidade | D68: AVRG_BLNC | E68: Em Teste | F68: 7. Validação de controlos corporativos | I68: =INDEX(Auxiliar!$D$5:$F$11,MATCH(Table1[[#This Row],[Tipologia_Testes]],Auxiliar!$B$5:$B$11,0),MATCH(Table1[[#This Row],[Complexidade]],Auxiliar!$D$4:$F$4,0)) -> #N/A
B69: GD | C69: Rentabilidade | D69: NT_LN_LSS_PRVSN | E69: Em Teste | F69: 2. Simulação | I69: =INDEX(Auxiliar!$D$5:$F$11,MATCH(Table1[[#This Row],[Tipologia_Testes]],Auxiliar!$B$5:$B$11,0),MATCH(Table1[[#This Row],[Complexidade]],Auxiliar!$D$4:$F$4,0)) -> #N/A
B70: GD | C70: Rentabilidade | D70: NT_LN_LSS_PRVSN | E70: Em Teste | F70: 3. Testes comparativos (Espec. VS Impl.) | I70: =INDEX(Auxiliar!$D$5:$F$11,MATCH(Table1[[#This Row],[Tipologia_Testes]],Auxiliar!$B$5:$B$11,0),MATCH(Table1[[#This Row],[Complexidade]],Auxiliar!$D$4:$F$4,0)) -> #N/A
B71: GD | C71: Rentabilidade | D71: NT_LN_LSS_PRVSN | E71: Em Teste | F71: 4. Validação de parametrizações | I71: =INDEX(Auxiliar!$D$5:$F$11,MATCH(Table1[[#This Row],[Tipologia_Testes]],Auxiliar!$B$5:$B$11,0),MATCH(Table1[[#This Row],[Complexidade]],Auxiliar!$D$4:$F$4,0)) -> #N/A
A72: ** | B72: GD | C72: Rentabilidade | D72: NT_LN_LSS_PRVSN | E72: Em Teste | F72: 6. Validação de formatos | I72: =INDEX(Auxiliar!$D$5:$F$11,MATCH(Table1[[#This Row],[Tipologia_Testes]],Auxiliar!$B$5:$B$11,0),MATCH(Table1[[#This Row],[Complexidade]],Auxiliar!$D$4:$F$4,0)) -> #N/A
A73: ** | B73: GD | C73: Rentabilidade | D73: NT_LN_LSS_PRVSN | E73: Em Teste | F73: 7. Validação de controlos corporativos | I73: =INDEX(Auxiliar!$D$5:$F$11,MATCH(Table1[[#This Row],[Tipologia_Testes]],Auxiliar!$B$5:$B$11,0),MATCH(Table1[[#This Row],[Complexidade]],Auxiliar!$D$4:$F$4,0)) -> #N/A
A74: ** | B74: GD | C74: Rentabilidade | D74: MNGMNT_PRDCT | E74: Em Teste | F74: 2. Simulação | I74: =INDEX(Auxiliar!$D$5:$F$11,MATCH(Table1[[#This Row],[Tipologia_Testes]],Auxiliar!$B$5:$B$11,0),MATCH(Table1[[#This Row],[Complexidade]],Auxiliar!$D$4:$F$4,0)) -> #N/A
A75: ** | B75: GD | C75: Rentabilidade | D75: MNGMNT_PRDCT | E75: Em Teste | F75: 3. Testes comparativos (Espec. VS Impl.) | I75: =INDEX(Auxiliar!$D$5:$F$11,MATCH(Table1[[#This Row],[Tipologia_Testes]],Auxiliar!$B$5:$B$11,0),MATCH(Table1[[#This Row],[Complexidade]],Auxiliar!$D$4:$F$4,0)) -> #N/A
A76: ** | B76: GD | C76: Rentabilidade | D76: MNGMNT_PRDCT | E76: Em Teste | F76: 4. Validação de parametrizações | I76: =INDEX(Auxiliar!$D$5:$F$11,MATCH(Table1[[#This Row],[Tipologia_Testes]],Auxiliar!$B$5:$B$11,0),MATCH(Table1[[#This Row],[Complexidade]],Auxiliar!$D$4:$F$4,0)) -> #N/A
A77: ** | B77: GD | C77: Rentabilidade | D77: MNGMNT_PRDCT | E77: Em Teste | F77: 6. Validação de formatos | I77: =INDEX(Auxiliar!$D$5:$F$11,MATCH(Table1[[#This Row],[Tipologia_Testes]],Auxiliar!$B$5:$B$11,0),MATCH(Table1[[#This Row],[Complexidade]],Auxiliar!$D$4:$F$4,0)) -> #N/A
B78: GD | C78: Rentabilidade | D78: MNGMNT_PRDCT | E78: Em Teste | F78: 7. Validação de controlos corporativos | I78: =INDEX(Auxiliar!$D$5:$F$11,MATCH(Table1[[#This Row],[Tipologia_Testes]],Auxiliar!$B$5:$B$11,0),MATCH(Table1[[#This Row],[Complexidade]],Auxiliar!$D$4:$F$4,0)) -> #N/A
B79: GD | C79: Rentabilidade | D79: NW_BSNSS | E79: Em Teste | F79: 2. Simulação | I79: =INDEX(Auxiliar!$D$5:$F$11,MATCH(Table1[[#This Row],[Tipologia_Testes]],Auxiliar!$B$5:$B$11,0),MATCH(Table1[[#This Row],[Complexidade]],Auxiliar!$D$4:$F$4,0)) -> #N/A
B80: GD | C80: Rentabilidade | D80: NW_BSNSS | E80: Em Teste | F80: 3. Testes comparativos (Espec. VS Impl.) | I80: =INDEX(Auxiliar!$D$5:$F$11,MATCH(Table1[[#This Row],[Tipologia_Testes]],Auxiliar!$B$5:$B$11,0),MATCH(Table1[[#This Row],[Complexidade]],Auxiliar!$D$4:$F$4,0)) -> #N/A
B81: GD | C81: Rentabilidade | D81: NW_BSNSS | E81: Em Teste | F81: 4. Validação de parametrizações | I81: =INDEX(Auxiliar!$D$5:$F$11,MATCH(Table1[[#This Row],[Tipologia_Testes]],Auxiliar!$B$5:$B$11,0),MATCH(Table1[[#This Row],[Complexidade]],Auxiliar!$D$4:$F$4,0)) -> #N/A
A82: ** | B82: GD | C82: Rentabilidade | D82: NW_BSNSS | E82: Em Teste | F82: 6. Validação de formatos | I82: =INDEX(Auxiliar!$D$5:$F$11,MATCH(Table1[[#This Row],[Tipologia_Testes]],Auxiliar!$B$5:$B$11,0),MATCH(Table1[[#This Row],[Complexidade]],Auxiliar!$D$4:$F$4,0)) -> #N/A
A83: ** | B83: GD | C83: Rentabilidade | D83: NW_BSNSS | E83: Em Teste | F83: 7. Validação de controlos corporativos | I83: =INDEX(Auxiliar!$D$5:$F$11,MATCH(Table1[[#This Row],[Tipologia_Testes]],Auxiliar!$B$5:$B$11,0),MATCH(Table1[[#This Row],[Complexidade]],Auxiliar!$D$4:$F$4,0)) -> #N/A
A84: ** | B84: GD | C84: Rentabilidade | D84: GRSS_INTRST_INCM_CCRR | E84: Em Teste | F84: 2. Simulação | I84: =INDEX(Auxiliar!$D$5:$F$11,MATCH(Table1[[#This Row],[Tipologia_Testes]],Auxiliar!$B$5:$B$11,0),MATCH(Table1[[#This Row],[Complexidade]],Auxiliar!$D$4:$F$4,0)) -> #N/A
A85: ** | B85: GD | C85: Rentabilidade | D85: GRSS_INTRST_INCM_CCRR | E85: Em Teste | F85: 3. Testes comparativos (Espec. VS Impl.) | I85: =INDEX(Auxiliar!$D$5:$F$11,MATCH(Table1[[#This Row],[Tipologia_Testes]],Auxiliar!$B$5:$B$11,0),MATCH(Table1[[#This Row],[Complexidade]],Auxiliar!$D$4:$F$4,0)) -> #N/A
B86: GD | C86: Rentabilidade | D86: GRSS_INTRST_INCM_CCRR | E86: Em Teste | F86: 4. Validação de parametrizações | I86: =INDEX(Auxiliar!$D$5:$F$11,MATCH(Table1[[#This Row],[Tipologia_Testes]],Auxiliar!$B$5:$B$11,0),MATCH(Table1[[#This Row],[Complexidade]],Auxiliar!$D$4:$F$4,0)) -> #N/A
B87: GD | C87: Rentabilidade | D87: GRSS_INTRST_INCM_CCRR | E87: Em Teste | F87: 6. Validação de formatos | I87: =INDEX(Auxiliar!$D$5:$F$11,MATCH(Table1[[#This Row],[Tipologia_Testes]],Auxiliar!$B$5:$B$11,0),MATCH(Table1[[#This Row],[Complexidade]],Auxiliar!$D$4:$F$4,0)) -> #N/A
B88: GD | C88: Rentabilidade | D88: GRSS_INTRST_INCM_CCRR | E88: Em Teste | F88: 7. Validação de controlos corporativos | I88: =INDEX(Auxiliar!$D$5:$F$11,MATCH(Table1[[#This Row],[Tipologia_Testes]],Auxiliar!$B$5:$B$11,0),MATCH(Table1[[#This Row],[Complexidade]],Auxiliar!$D$4:$F$4,0)) -> #N/A
B89: GD | C89: Rentabilidade | D89: NT_LN_LSS_PRVSN_OFF_BLNC | E89: Em Teste | F89: 2. Simulação | I89: =INDEX(Auxiliar!$D$5:$F$11,MATCH(Table1[[#This Row],[Tipologia_Testes]],Auxiliar!$B$5:$B$11,0),MATCH(Table1[[#This Row],[Complexidade]],Auxiliar!$D$4:$F$4,0)) -> #N/A
A90: ** | B90: GD | C90: Rentabilidade | D90: NT_LN_LSS_PRVSN_OFF_BLNC | E90: Em Teste | F90: 3. Testes comparativos (Espec. VS Impl.) | I90: =INDEX(Auxiliar!$D$5:$F$11,MATCH(Table1[[#This Row],[Tipologia_Testes]],Auxiliar!$B$5:$B$11,0),MATCH(Table1[[#This Row],[Complexidade]],Auxiliar!$D$4:$F$4,0)) -> #N/A
B91: GD | C91: Rentabilidade | D91: NT_LN_LSS_PRVSN_OFF_BLNC | E91: Em Teste | F91: 4. Validação de parametrizações | I91: =INDEX(Auxiliar!$D$5:$F$11,MATCH(Table1[[#This Row],[Tipologia_Testes]],Auxiliar!$B$5:$B$11,0),MATCH(Table1[[#This Row],[Complexidade]],Auxiliar!$D$4:$F$4,0)) -> #N/A
B92: GD | C92: Rentabilidade | D92: NT_LN_LSS_PRVSN_OFF_BLNC | E92: Em Teste | F92: 6. Validação de formatos | I92: =INDEX(Auxiliar!$D$5:$F$11,MATCH(Table1[[#This Row],[Tipologia_Testes]],Auxiliar!$B$5:$B$11,0),MATCH(Table1[[#This Row],[Complexidade]],Auxiliar!$D$4:$F$4,0)) -> #N/A
B93: GD | C93: Rentabilidade | D93: NT_LN_LSS_PRVSN_OFF_BLNC | E93: Em Teste | F93: 7. Validação de controlos corporativos | I93: =INDEX(Auxiliar!$D$5:$F$11,MATCH(Table1[[#This Row],[Tipologia_Testes]],Auxiliar!$B$5:$B$11,0),MATCH(Table1[[#This Row],[Complexidade]],Auxiliar!$D$4:$F$4,0)) -> #N/A
B94: GD | C94: Rentabilidade | D94: AVRG_BLNC_OFF_BLNC | E94: Em Teste | F94: 2. Simulação | I94: =INDEX(Auxiliar!$D$5:$F$11,MATCH(Table1[[#This Row],[Tipologia_Testes]],Auxiliar!$B$5:$B$11,0),MATCH(Table1[[#This Row],[Complexidade]],Auxiliar!$D$4:$F$4,0)) -> #N/A
B95: GD | C95: Rentabilidade | D95: AVRG_BLNC_OFF_BLNC | E95: Em Teste | F95: 3. Testes comparativos (Espec. VS Impl.) | I95: =INDEX(Auxiliar!$D$5:$F$11,MATCH(Table1[[#This Row],[Tipologia_Testes]],Auxiliar!$B$5:$B$11,0),MATCH(Table1[[#This Row],[Complexidade]],Auxiliar!$D$4:$F$4,0)) -> #N/A
B96: GD | C96: Rentabilidade | D96: AVRG_BLNC_OFF_BLNC | E96: Em Teste | F96: 4. Validação de parametrizações | I96: =INDEX(Auxiliar!$D$5:$F$11,MATCH(Table1[[#This Row],[Tipologia_Testes]],Auxiliar!$B$5:$B$11,0),MATCH(Table1[[#This Row],[Complexidade]],Auxiliar!$D$4:$F$4,0)) -> #N/A
B97: GD | C97: Rentabilidade | D97: AVRG_BLNC_OFF_BLNC | E97: Em Teste | F97: 6. Validação de formatos | I97: =INDEX(Auxiliar!$D$5:$F$11,MATCH(Table1[[#This Row],[Tipologia_Testes]],Auxiliar!$B$5:$B$11,0),MATCH(Table1[[#This Row],[Complexidade]],Auxiliar!$D$4:$F$4,0)) -> #N/A
B98: GD | C98: Rentabilidade | D98: AVRG_BLNC_OFF_BLNC | E98: Em Teste | F98: 7. Validação de controlos corporativos | I98: =INDEX(Auxiliar!$D$5:$F$11,MATCH(Table1[[#This Row],[Tipologia_Testes]],Auxiliar!$B$5:$B$11,0),MATCH(Table1[[#This Row],[Complexidade]],Auxiliar!$D$4:$F$4,0)) -> #N/A
B99: GD | C99: Rentabilidade | D99: BSNSS_AREA_CCRR | E99: Em Teste | F99: 2. Simulação | I99: =INDEX(Auxiliar!$D$5:$F$11,MATCH(Table1[[#This Row],[Tipologia_Testes]],Auxiliar!$B$5:$B$11,0),MATCH(Table1[[#This Row],[Complexidade]],Auxiliar!$D$4:$F$4,0)) -> #N/A
B100: GD | C100: Rentabilidade | D100: BSNSS_AREA_CCRR | E100: Em Teste | F100: 3. Testes comparativos (Espec. VS Impl.) | I100: =INDEX(Auxiliar!$D$5:$F$11,MATCH(Table1[[#This Row],[Tipologia_Testes]],Auxiliar!$B$5:$B$11,0),MATCH(Table1[[#This Row],[Complexidade]],Auxiliar!$D$4:$F$4,0)) -> #N/A
B101: GD | C101: Rentabilidade | D101: BSNSS_AREA_CCRR | E101: Em Teste | F101: 4. Validação de parametrizações | I101: =INDEX(Auxiliar!$D$5:$F$11,MATCH(Table1[[#This Row],[Tipologia_Testes]],Auxiliar!$B$5:$B$11,0),MATCH(Table1[[#This Row],[Complexidade]],Auxiliar!$D$4:$F$4,0)) -> #N/A
A102: ** | B102: GD | C102: Rentabilidade | D102: BSNSS_AREA_CCRR | E102: Em Teste | F102: 6. Validação de formatos | I102: =INDEX(Auxiliar!$D$5:$F$11,MATCH(Table1[[#This Row],[Tipologia_Testes]],Auxiliar!$B$5:$B$11,0),MATCH(Table1[[#This Row],[Complexidade]],Auxiliar!$D$4:$F$4,0)) -> #N/A
A103: ** | B103: GD | C103: Rentabilidade | D103: BSNSS_AREA_CCRR | E103: Em Teste | F103: 7. Validação de controlos corporativos | I103: =INDEX(Auxiliar!$D$5:$F$11,MATCH(Table1[[#This Row],[Tipologia_Testes]],Auxiliar!$B$5:$B$11,0),MATCH(Table1[[#This Row],[Complexidade]],Auxiliar!$D$4:$F$4,0)) -> #N/A
A104: ** | B104: GD | C104: Rentabilidade | D104: GRSS_CMMSSN_INCM_OFF_BLNC | E104: Em Teste | F104: 2. Simulação | I104: =INDEX(Auxiliar!$D$5:$F$11,MATCH(Table1[[#This Row],[Tipologia_Testes]],Auxiliar!$B$5:$B$11,0),MATCH(Table1[[#This Row],[Complexidade]],Auxiliar!$D$4:$F$4,0)) -> #N/A
A105: ** | B105: GD | C105: Rentabilidade | D105: GRSS_CMMSSN_INCM_OFF_BLNC | E105: Em Teste | F105: 3. Testes comparativos (Espec. VS Impl.) | I105: =INDEX(Auxiliar!$D$5:$F$11,MATCH(Table1[[#This Row],[Tipologia_Testes]],Auxiliar!$B$5:$B$11,0),MATCH(Table1[[#This Row],[Complexidade]],Auxiliar!$D$4:$F$4,0)) -> #N/A
B106: GD | C106: Rentabilidade | D106: GRSS_CMMSSN_INCM_OFF_BLNC | E106: Em Teste | F106: 4. Validação de parametrizações | I106: =INDEX(Auxiliar!$D$5:$F$11,MATCH(Table1[[#This Row],[Tipologia_Testes]],Auxiliar!$B$5:$B$11,0),MATCH(Table1[[#This Row],[Complexidade]],Auxiliar!$D$4:$F$4,0)) -> #N/A
B107: GD | C107: Rentabilidade | D107: GRSS_CMMSSN_INCM_OFF_BLNC | E107: Em Teste | F107: 6. Validação de formatos | I107: =INDEX(Auxiliar!$D$5:$F$11,MATCH(Table1[[#This Row],[Tipologia_Testes]],Auxiliar!$B$5:$B$11,0),MATCH(Table1[[#This Row],[Complexidade]],Auxiliar!$D$4:$F$4,0)) -> #N/A
B108: GD | C108: Rentabilidade | D108: GRSS_CMMSSN_INCM_OFF_BLNC | E108: Em Teste | F108: 7. Validação de controlos corporativos | I108: =INDEX(Auxiliar!$D$5:$F$11,MATCH(Table1[[#This Row],[Tipologia_Testes]],Auxiliar!$B$5:$B$11,0),MATCH(Table1[[#This Row],[Complexidade]],Auxiliar!$D$4:$F$4,0)) -> #N/A
B109: GD | C109: Rentabilidade | D109: GRSS_CMMSSN_EXPNS_OFF_BLNC_CCRR | E109: Em Teste | F109: 2. Simulação | I109: =INDEX(Auxiliar!$D$5:$F$11,MATCH(Table1[[#This Row],[Tipologia_Testes]],Auxiliar!$B$5:$B$11,0),MATCH(Table1[[#This Row],[Complexidade]],Auxiliar!$D$4:$F$4,0)) -> #N/A
B110: GD | C110: Rentabilidade | D110: GRSS_CMMSSN_EXPNS_OFF_BLNC_CCRR | E110: Em Teste | F110: 3. Testes comparativos (Espec. VS Impl.) | I110: =INDEX(Auxiliar!$D$5:$F$11,MATCH(Table1[[#This Row],[Tipologia_Testes]],Auxiliar!$B$5:$B$11,0),MATCH(Table1[[#This Row],[Complexidade]],Auxiliar!$D$4:$F$4,0)) -> #N/A
B111: GD | C111: Rentabilidade | D111: GRSS_CMMSSN_EXPNS_OFF_BLNC_CCRR | E111: Em Teste | F111: 4. Validação de parametrizações | I111: =INDEX(Auxiliar!$D$5:$F$11,MATCH(Table1[[#This Row],[Tipologia_Testes]],Auxiliar!$B$5:$B$11,0),MATCH(Table1[[#This Row],[Complexidade]],Auxiliar!$D$4:$F$4,0)) -> #N/A
B112: GD | C112: Rentabilidade | D112: GRSS_CMMSSN_EXPNS_OFF_BLNC_CCRR | E112: Em Teste | F112: 6. Validação de formatos | I112: =INDEX(Auxiliar!$D$5:$F$11,MATCH(Table1[[#This Row],[Tipologia_Testes]],Auxiliar!$B$5:$B$11,0),MATCH(Table1[[#This Row],[Complexidade]],Auxiliar!$D$4:$F$4,0)) -> #N/A
B113: GD | C113: Rentabilidade | D113: GRSS_CMMSSN_EXPNS_OFF_BLNC_CCRR | E113: Em Teste | F113: 7. Validação de controlos corporativos | I113: =INDEX(Auxiliar!$D$5:$F$11,MATCH(Table1[[#This Row],[Tipologia_Testes]],Auxiliar!$B$5:$B$11,0),MATCH(Table1[[#This Row],[Complexidade]],Auxiliar!$D$4:$F$4,0)) -> #N/A
A114: ** | B114: GD | C114: Rentabilidade | D114: GRSS_CMMSSN_EXPNS_OFF_BLNC | E114: Em Teste | F114: 2. Simulação | I114: =INDEX(Auxiliar!$D$5:$F$11,MATCH(Table1[[#This Row],[Tipologia_Testes]],Auxiliar!$B$5:$B$11,0),MATCH(Table1[[#This Row],[Complexidade]],Auxiliar!$D$4:$F$4,0)) -> #N/A
A115: ** | B115: GD | C115: Rentabilidade | D115: GRSS_CMMSSN_EXPNS_OFF_BLNC | E115: Em Teste | F115: 3. Testes comparativos (Espec. VS Impl.) | I115: =INDEX(Auxiliar!$D$5:$F$11,MATCH(Table1[[#This Row],[Tipologia_Testes]],Auxiliar!$B$5:$B$11,0),MATCH(Table1[[#This Row],[Complexidade]],Auxiliar!$D$4:$F$4,0)) -> #N/A
A116: ** | B116: GD | C116: Rentabilidade | D116: GRSS_CMMSSN_EXPNS_OFF_BLNC | E116: Em Teste | F116: 4. Validação de parametrizações | I116: =INDEX(Auxiliar!$D$5:$F$11,MATCH(Table1[[#This Row],[Tipologia_Testes]],Auxiliar!$B$5:$B$11,0),MATCH(Table1[[#This Row],[Complexidade]],Auxiliar!$D$4:$F$4,0)) -> #N/A
A117: ** | B117: GD | C117: Rentabilidade | D117: GRSS_CMMSSN_EXPNS_OFF_BLNC | E117: Em Teste | F117: 6. Validação de formatos | I117: =INDEX(Auxiliar!$D$5:$F$11,MATCH(Table1[[#This Row],[Tipologia_Testes]],Auxiliar!$B$5:$B$11,0),MATCH(Table1[[#This Row],[Complexidade]],Auxiliar!$D$4:$F$4,0)) -> #N/A
B118: GD | C118: Rentabilidade | D118: GRSS_CMMSSN_EXPNS_OFF_BLNC | E118: Em Teste | F118: 7. Validação de controlos corporativos | I118: =INDEX(Auxiliar!$D$5:$F$11,MATCH(Table1[[#This Row],[Tipologia_Testes]],Auxiliar!$B$5:$B$11,0),MATCH(Table1[[#This Row],[Complexidade]],Auxiliar!$D$4:$F$4,0)) -> #N/A
B119: GD | C119: Rentabilidade | D119: GRSS_CMMSSN_INCM_OFF_BLNC_CCRR | E119: Em Teste | F119: 2. Simulação | I119: =INDEX(Auxiliar!$D$5:$F$11,MATCH(Table1[[#This Row],[Tipologia_Testes]],Auxiliar!$B$5:$B$11,0),MATCH(Table1[[#This Row],[Complexidade]],Auxiliar!$D$4:$F$4,0)) -> #N/A
...

Sheet 2. Controlos Corporativos
A1: Campo | B1: LT_VALIDATION_LABEL | C1: LT_VALIDATION_DESCRIPTION | D1: LT_VALIDAT_TABLE | E1: LT_VALIDAT_FIELD | F1: LT_VALIDATION_TYPE | G1: LT_PROC_STEP_ID | H1: LT_PROC_VAL_NEW_STATUS | I1: LT_VAL_EXECUTED | J1: LT_VAL_INCIDENTS | K1: VL_PERCENT
A2: =VLOOKUP(E2,Table1[[#All],[Campo]],1,0) -> COD_SOC | B2: LT_C_EN_001_01 | C2: "Entity code of the informing society." should be a Char not null (default values not allowed) | D2: INTRA_N1_EN | E2: COD_SOC | F2: NOT_NULL_CHAR | G2: LT_C_EN | H2: OK | I2: 1096295 | J2: 0 | K2: 0
A3: =VLOOKUP(E3,Table1[[#All],[Campo]],1,0) -> DT_RFRNC | B3: LT_C_EN_009_01 | C3: "Reference date." should be a Date not null (default values not allowed) | D3: INTRA_N1_EN | E3: DT_RFRNC | F3: NOT_NULL_DATE | G3: LT_C_EN | H3: OK | I3: 1096295 | J3: 0 | K3: 0
A4: =VLOOKUP(E4,Table1[[#All],[Campo]],1,0) -> COD_SOC | B4: LT_C_IE_001_01 | C4: "Entity code of the informing society." should be a Char not null (default values not allowed) | D4: INTRA_N1_IE | E4: COD_SOC | F4: NOT_NULL_CHAR | G4: LT_C_IE | H4: OK | I4: 2490665 | J4: 0 | K4: 0
A5: =VLOOKUP(E5,Table1[[#All],[Campo]],1,0) -> DT_RFRNC | B5: LT_C_IE_002_01 | C5: "Reference date" should be a Date not null (default values not allowed) | D5: INTRA_N1_IE | E5: DT_RFRNC | F5: NOT_NULL_DATE | G5: LT_C_IE | H5: OK | I5: 2490665 | J5: 0 | K5: 0
A6: =VLOOKUP(E6,Table1[[#All],[Campo]],1,0) -> INSTRMNT_ID | B6: LT_C_IE_004_01 | C6: "Instrument ID" should be a Char not null (default values not allowed) | D6: INTRA_N1_IE | E6: INSTRMNT_ID | F6: NOT_NULL_CHAR | G6: LT_C_IE | H6: OK | I6: 2490665 | J6: 0 | K6: 0
A7: =VLOOKUP(E7,Table1[[#All],[Campo]],1,0) -> COD_SOC | B7: LT_C_IN_001_01 | C7: "Entity code of the informing society." should be a Char not null (default values not allowed) | D7: INTRA_N1_IN | E7: COD_SOC | F7: NOT_NULL_CHAR | G7: LT_C_IN | H7: OK | I7: 2002411 | J7: 0 | K7: 0
A8: =VLOOKUP(E8,Table1[[#All],[Campo]],1,0) -> DT_RFRNC | B8: LT_C_IN_007_01 | C8: "Reference date" should be a Date not null (default values not allowed) | D8: INTRA_N1_IN | E8: DT_RFRNC | F8: NOT_NULL_DATE | G8: LT_C_IN | H8: OK | I8: 2002411 | J8: 0 | K8: 0
A9: =VLOOKUP(E9,Table1[[#All],[Campo]],1,0) -> INSTRMNT_ID | B9: LT_C_IN_008_01 | C9: "Instrument ID" should be a Char not null (default values not allowed) | D9: INTRA_N1_IN | E9: INSTRMNT_ID | F9: NOT_NULL_CHAR | G9: LT_C_IN | H9: OK | I9: 2002411 | J9: 0 | K9: 0
A10: =VLOOKUP(E10,Table1[[#All],[Campo]],1,0) -> DFLT_STTS_INSTRMNT | B10: LT_C_IN_020_01 | C10: "Default status of the instrument" should be a num not null (default values for not applicable fields not allowed) | D10: INSTRUMENT | E10: DFLT_STTS_INSTRMNT | F10: NOT_NULL_NUM_NA | G10: LT_C_IN | H10: KO | I10: 2002411 | J10: 96182 | K10: 4.8033
A11: =VLOOKUP(E11,Table1[[#All],[Campo]],1,0) -> PRFRMNG_STTS | B11: LT_C_IN_044_01 | C11: "Performing status" should be a num not null (default values for not applicable fields not allowed) | D11: INSTRUMENT | E11: PRFRMNG_STTS | F11: NOT_NULL_NUM_NA | G11: LT_C_IN | H11: OK | I11: 2002411 | J11: 0 | K11: 0
A12: =VLOOKUP(E12,Table1[[#All],[Campo]],1,0) -> LCL_INSTMRNT_ID | B12: LT_C_IN_193_01 | C12: "Local Instrument ID" should be a Char not null (default values not allowed) | D12: INTRA_N1_IN | E12: LCL_INSTMRNT_ID | F12: NOT_NULL_CHAR | G12: LT_C_IN | H12: KO | I12: 2002411 | J12: 2002411 | K12: 100
A13: =VLOOKUP(E13,Table1[[#All],[Campo]],1,0) -> SSTNBL_INDCTR | B13: LT_C_IN_194_01 | C13: "Sustainable Indicator" should be a Char not null (default values for not applicable fields not allowed) | D13: INSTRUMENT | E13: SSTNBL_INDCTR | F13: NOT_NULL_NA | G13: LT_C_IN | H13: KO | I13: 2002318 | J13: 2002318 | K13: 100
... A18: =VLOOKUP(E18,Table1[[#All],[Campo]],1,0) -> BSNSS_AREA_CCRR | B18: LT_C_IN_222_01 | C18: "Business Area related to CIB" should be a Char not null (default values for not applicable fields not allowed) | D18: INSTRUMENT | E18: BSNSS_AREA_CCRR | F18: NOT_NULL_NA | G18: LT_C_IN | H18: KO | I18: 2002411 | J18: 2002411 | K18: 100
A19: CNCLLD_INSTRMNT_STTS | B19: LT_C_IN_245_01 | C19: "Flag of instrument cancelled" should be a Char not null (default values for not applicable fields not allowed) | D19: INSTRUMENT | E19: FLG_INSTRMNT_CNCLLD | F19: NOT_NULL_NA | G19: LT_C_IN | H19: KO | I19: 2002411 | J19: 2002411 | K19: 100
A20: =VLOOKUP(E20,Table1[[#All],[Campo]],1,0) -> IDCMB | B20: LT_C_IN_246_01 | C20: "IDCOMB" should be a Char not null (default values not allowed) | D20: INTRA_N1_IN | E20: IDCMB | F20: NOT_NULL_CHAR | G20: LT_C_IN | H20: KO | I20: 2002411 | J20: 1 | K20: 0
A21: =VLOOKUP(E21,Table1[[#All],[Campo]],1,0) -> COD_SOC | B21: LT_C_IP_001_01 | C21: "Entity code of the informing society." should be a Char not null (default values not allowed) | D21: INTRA_N1_IP | E21: COD_SOC | F21: NOT_NULL_CHAR | G21: LT_C_IP | H21: OK | I21: 731165 | J21: 0 | K21: 0
A22: =VLOOKUP(E22,Table1[[#All],[Campo]],1,0) -> DT_RFRNC | B22: LT_C_IP_002_01 | C22: "Reference date" should be a Date not null (default values not allowed) | D22: INTRA_N1_IP | E22: DT_RFRNC | F22: NOT_NULL_DATE | G22: LT_C_IP | H22: OK | I22: 731165 | J22: 0 | K22: 0
A23: =VLOOKUP(E23,Table1[[#All],[Campo]],1,0) -> INSTRMNT_ID | B23: LT_C_IP_003_01 | C23: "Instrument ID" should be a Char not null (default values not allowed) | D23: INTRA_N1_IP | E23: INSTRMNT_ID | F23: NOT_NULL_CHAR | G23: LT_C_IP | H23: OK | I23: 731165 | J23: 0 | K23: 0
A24: =VLOOKUP(E24,Table1[[#All],[Campo]],1,0) -> COD_SOC | B24: LT_C_PR_001_01 | C24: "Entity code of the informing society." should be a Char not null (default values not allowed) | D24: INTRA_N1_PR | E24: COD_SOC | F24: NOT_NULL_CHAR | G24: LT_C_PR | H24: OK | I24: 456960 | J24: 0 | K24: 0
A25: =VLOOKUP(E25,Table1[[#All],[Campo]],1,0) -> DT_RFRNC | B25: LT_C_PR_003_01 | C25: "Reference date" should be a Date not null (default values not allowed) | D25: INTRA_N1_PR | E25: DT_RFRNC | F25: NOT_NULL_DATE | G25: LT_C_PR | H25: OK | I25: 456960 | J25: 0 | K25: 0
A26: =VLOOKUP(E26,Table1[[#All],[Campo]],1,0) -> INSTRMNT_ID | B26: LT_D_IN_008_01 | C26: Duplicates by "Instrument ID" in INSTRUMENT table | D26: INSTRUMENT | E26: INSTRMNT_ID | F26: DUPLICATES PK | G26: LT_D_ | H26: OK | I26: 2003033 | J26: 0 | K26: 0
A27: =VLOOKUP(E27,Table1[[#All],[Campo]],1,0) -> INSTRMNT_ID | B27: LT_D_IP_003_01 | C27: Duplicates by "Instrument ID" and "Protection ID" in INSTR_PROTECTION table | D27: INSTR_PROTECTION | E27: INSTRMNT_ID | F27: DUPLICATES PK | G27: LT_D_ | H27: OK | I27: 731165 | J27: 0 | K27: 0
A28: =VLOOKUP(E28,Table1[[#All],[Campo]],1,0) -> COD_SOC | B28: LT_F_EN_001_01 | C28: "Entity code of the informing society." should match the information on the Codelist | D28: ENTITY | E28: COD_SOC | F28: LISTA | G28: LT_F_EN | H28: OK | I28: 1096295 | J28: 0 | K28: 0
A29: =VLOOKUP(E29,Table1[[#All],[Campo]],1,0) -> DT_RFRNC | B29: LT_F_EN_009_01 | C29: "Reference date." must have a Date format (yyyy-mm-dd) | D29: ENTITY | E29: DT_RFRNC | F29: FORMAT_DATE | G29: LT_F_EN | H29: OK | I29: 1096295 | J29: 0 | K29: 0
A30: =VLOOKUP(E30,Table1[[#All],[Campo]],1,0) -> COD_SOC | B30: LT_F_IE_001_01 | C30: "Entity code of the informing society." should match the information on the Codelist | D30: INSTR_ENTITY | E30: COD_SOC | F30: LISTA | G30: LT_F_IE | H30: OK | I30: 2490665 | J30: 0 | K30: 0
A31: =VLOOKUP(E31,Table1[[#All],[Campo]],1,0) -> DT_RFRNC | B31: LT_F_IE_002_01 | C31: "Reference date" must have a Date format (yyyy-mm-dd) | D31: INSTR_ENTITY | E31: DT_RFRNC | F31: FORMAT_DATE | G31: LT_F_IE | H31: OK | I31: 2490665 | J31: 0 | K31: 0
... A54: =VLOOKUP(E54,Table1[[#All],[Campo]],1,0) -> GRSS_INTRST_INCM | B54: LT_F_IN_198_01 | C54: "Gross Interest income before distribution to SCIB under the Collabotarion Revenues distribution agreement" should have a Format numeric (2 decimal places) | D54: INSTRUMENT | E54: GRSS_INTRST_INCM | F54: FORMAT_NUM | G54: LT_F_IN | H54: OK | I54: 2003033 | J54: 0 | K54: 0
A55: GRSS_CMMSSN_INCM | B55: LT_F_IN_199_01 | C55: "Gross fee and commission income before distribution to SCIB under the Collabotarion Revenues distribution agreement" should have a Format numeric (2 decimal places) | D55: INSTRUMENT | E55: GRSS_FEE_CMMSSN_INCM | F55: FORMAT_NUM | G55: LT_F_IN | H55: OK | I55: 2003033 | J55: 0 | K55: 0
A56: =VLOOKUP(E56,Table1[[#All],[Campo]],1,0) -> INTRNL_TRNSFR_RT | B56: LT_F_IN_200_01 | C56: "Internal transfer rate amount" should have a Format numeric (2 decimal places) | D56: INSTRUMENT | E56: INTRNL_TRNSFR_RT | F56: FORMAT_NUM | G56: LT_F_IN | H56: OK | I56: 2003033 | J56: 0 | K56: 0
A57: =VLOOKUP(E57,Table1[[#All],[Campo]],1,0) -> NT_LN_LSS_PRVSN | B57: LT_F_IN_201_01 | C57: "Net loan-loss provisions" should have a Format numeric (2 decimal places) | D57: INSTRUMENT | E57: NT_LN_LSS_PRVSN | F57: FORMAT_NUM | G57: LT_F_IN | H57: OK | I57: 2003033 | J57: 0 | K57: 0
A58: =VLOOKUP(E58,Table1[[#All],[Campo]],1,0) -> BSNSS_AREA | B58: LT_F_IN_202_01 | C58: "Business Area" should match the information on the Codelist | D58: INSTRUMENT | E58: BSNSS_AREA | F58: LISTA | G58: LT_F_IN | H58: KO | I58: 2003033 | J58: 2003033 | K58: 100
A59: =VLOOKUP(E59,Table1[[#All],[Campo]],1,0) -> MNGMNT_PRDCT | B59: LT_F_IN_203_01 | C59: "Management Product" should match the information on the Codelist | D59: INSTRUMENT | E59: MNGMNT_PRDCT | F59: LISTA | G59: LT_F_IN | H59: KO | I59: 2003033 | J59: 2003033 | K59: 100
A60: GRSS_CMMSSN_EXPNS | B60: LT_F_IN_204_01 | C60: "Gross fee and commission expense before distribution to SCIB under the Collabotarion Revenues distribution agreement" should have a Format numeric (2 decimal places) | D60: INSTRUMENT | E60: GRSS_FEE_CMMSSN_EXPNS | F60: FORMAT_NUM | G60: LT_F_IN | H60: OK | I60: 2003033 | J60: 0 | K60: 0
A61: =VLOOKUP(E61,Table1[[#All],[Campo]],1,0) -> GNS_FNNCL_TRNSCTN_EXCHNG_DFFRNCS | B61: LT_F_IN_205_01 | C61: "Gains (Losses) On Financial Transaction (gft) And Exchange Differences, before distribution to SCIB under the Collabotarion Revenues distribution agreement" should have a Format numeric (2 decimal places) | D61: INSTRUMENT | E61: GNS_FNNCL_TRNSCTN_EXCHNG_DFFRNCS | F61: FORMAT_NUM | G61: LT_F_IN | H61: OK | I61: 2003033 | J61: 0 | K61: 0
A62: =VLOOKUP(E62,Table1[[#All],[Campo]],1,0) -> FLG_INTRBSNSS | B62: LT_F_IN_206_01 | C62: "Flag of interbusiness" should match the information on the Codelist | D62: INSTRUMENT | E62: FLG_INTRBSNSS | F62: LISTA | G62: LT_F_IN | H62: KO | I62: 2003033 | J62: 2003033 | K62: 100
A63: =VLOOKUP(E63,Table1[[#All],[Campo]],1,0) -> INTRBSNSS_ADJ_COD | B63: LT_F_IN_207_01 | C63: "Interbusiness adjustment code" should match the information on the Codelist | D63: INSTRUMENT | E63: INTRBSNSS_ADJ_COD | F63: LISTA | G63: LT_F_IN | H63: KO | I63: 2003033 | J63: 2003033 | K63: 100
A64: =VLOOKUP(E64,Table1[[#All],[Campo]],1,0) -> COD_SOC_DSTNTN | B64: LT_F_IN_208_01 | C64: "Cargabal identification code of the destination entity" should match the information on the Codelist | D64: INSTRUMENT | E64: COD_SOC_DSTNTN | F64: LISTA | G64: LT_F_IN | H64: KO | I64: 2003033 | J64: 2003033 | K64: 100
A65: =VLOOKUP(E65,Table1[[#All],[Campo]],1,0) -> BSNSS_AREA_DSTNTN | B65: LT_F_IN_209_01 | C65: "Destination Business area" should match the information on the Codelist | D65: INSTRUMENT | E65: BSNSS_AREA_DSTNTN | F65: LISTA | G65: LT_F_IN | H65: KO | I65: 2003033 | J65: 2003033 | K65: 100
A66: =VLOOKUP(E66,Table1[[#All],[Campo]],1,0) -> AVRG_BLNC_OFF_BLNC | B66: LT_F_IN_210_01 | C66: "Average balance corresponding to undrawn balances committed" should have a Format numeric (2 decimal places) | D66: INSTRUMENT | E66: AVRG_BLNC_OFF_BLNC | F66: FORMAT_NUM | G66: LT_F_IN | H66: OK | I66: 2003033 | J66: 0 | K66: 0
A67: =VLOOKUP(E67,Table1[[#All],[Campo]],1,0) -> INTRNL_TRNSFR_RT_OFF_BLNC | B67: LT_F_IN_211_01 | C67: "Internal transfer rate amount" corresponding to undrawn balances committed should have a Format numeric (2 decimal places) | D67: INSTRUMENT | E67: INTRNL_TRNSFR_RT_OFF_BLNC | F67: FORMAT_NUM | G67: LT_F_IN | H67: OK | I67: 2003033 | J67: 0 | K67: 0
A68: GRSS_CMMSSN_INCM_OFF_BLNC | B68: LT_F_IN_212_01 | C68: "Gross fee and commission income corresponding to undrawn balances committed" should have a Format numeric (2 decimal places) | D68: INSTRUMENT | E68: GRSS_FEE_CMMSSN_INCM_OFF_BLNC | F68: FORMAT_NUM | G68: LT_F_IN | H68: OK | I68: 2003033 | J68: 0 | K68: 0
A69: GRSS_CMMSSN_EXPNS_OFF_BLNC | B69: LT_F_IN_213_01 | C69: "Gross fee and commission expense corresponding to undrawn balances committed" should have a Format numeric (2 decimal places) | D69: INSTRUMENT | E69: GRSS_FEE_CMMSSN_EXPNS_OFF_BLNC | F69: FORMAT_NUM | G69: LT_F_IN | H69: OK | I69: 2003033 | J69: 0 | K69: 0
A70: =VLOOKUP(E70,Table1[[#All],[Campo]],1,0) -> RWA_OFF_BLNC | B70: LT_F_IN_214_01 | C70: "RWA Off Balance" should have a Format numeric (2 decimal places) | D70: INSTRUMENT | E70: RWA_OFF_BLNC | F70: FORMAT_NUM | G70: LT_F_IN | H70: OK | I70: 2003033 | J70: 0 | K70: 0
A71: =VLOOKUP(E71,Table1[[#All],[Campo]],1,0) -> GRSS_INTRST_EXPNS | B71: LT_F_IN_215_01 | C71: "Gross Interest expense before distribution to SCIB under the Collabotarion Revenues distribution agreement" should have a Format numeric (2 decimal places) | D71: INSTRUMENT | E71: GRSS_INTRST_EXPNS | F71: FORMAT_NUM | G71: LT_F_IN | H71: OK | I71: 2003033 | J71: 0 | K71: 0
A72: =VLOOKUP(E72,Table1[[#All],[Campo]],1,0) -> NT_LN_LSS_PRVSN_OFF_BLNC | B72: LT_F_IN_216_01 | C72: "Net loan-loss provisions corresponding to undrawn balances committed" should have a Format numeric (2 decimal places) | D72: INSTRUMENT | E72: NT_LN_LSS_PRVSN_OFF_BLNC | F72: FORMAT_NUM | G72: LT_F_IN | H72: OK | I72: 2003033 | J72: 0 | K72: 0
A73: =VLOOKUP(E73,Table1[[#All],[Campo]],1,0) -> GRSS_INTRST_INCM_CCRR | B73: LT_F_IN_217_01 | C73: "Gross Interest income distributed to SCIB under the Collabotarion Revenues distribution agreement" should have a Format numeric (2 decimal places) | D73: INSTRUMENT | E73: GRSS_INTRST_INCM_CCRR | F73: FORMAT_NUM | G73: LT_F_IN | H73: OK | I73: 2003033 | J73: 0 | K73: 0
A74: =VLOOKUP(E74,Table1[[#All],[Campo]],1,0) -> GRSS_INTRST_EXPNS_CCRR | B74: LT_F_IN_218_01 | C74: "Gross Interest expense distributed to SCIB under the Collabotarion Revenues distribution agreement" should have a Format numeric (2 decimal places) | D74: INSTRUMENT | E74: GRSS_INTRST_EXPNS_CCRR | F74: FORMAT_NUM | G74: LT_F_IN | H74: OK | I74: 2003033 | J74: 0 | K74: 0
A75: GRSS_CMMSSN_INCM_CCRR | B75: LT_F_IN_219_01 | C75: "Gross fee and commission income distributed to SCIB under the Collabotarion Revenues distribution agreement" should have a Format numeric (2 decimal places) | D75: INSTRUMENT | E75: GRSS_FEE_CMMSSN_INCM_CCRR | F75: FORMAT_NUM | G75: LT_F_IN | H75: OK | I75: 2003033 | J75: 0 | K75: 0
A76: GRSS_CMMSSN_EXPNS_CCRR | B76: LT_F_IN_220_01 | C76: "Gross fee and commission expense distributed to SCIB under the Collabotarion Revenues distribution agreement" should have a Format numeric (2 decimal places) | D76: INSTRUMENT | E76: GRSS_FEE_CMMSSN_EXPNS_CCRR | F76: FORMAT_NUM | G76: LT_F_IN | H76: OK | I76: 2003033 | J76: 0 | K76: 0
A77: =VLOOKUP(E77,Table1[[#All],[Campo]],1,0) -> GNS_FNNCL_TRNSCTN_EXCHNG_CCRR | B77: LT_F_IN_221_01 | C77: "Gains (Losses) On Financial Transaction (gft) And Exchange Differences distributed to SCIB under the Collabotarion Revenues distribution agreement" should have a Format numeric (2 decimal places) | D77: INSTRUMENT | E77: GNS_FNNCL_TRNSCTN_EXCHNG_CCRR | F77: FORMAT_NUM | G77: LT_F_IN | H77: OK | I77: 2003033 | J77: 0 | K77: 0
A78: =VLOOKUP(E78,Table1[[#All],[Campo]],1,0) -> BSNSS_AREA_CCRR | B78: LT_F_IN_222_01 | C78: "Business Area related to CIB" should match the information on the Codelist | D78: INSTRUMENT | E78: BSNSS_AREA_CCRR | F78: LISTA | G78: LT_F_IN | H78: KO | I78: 2003033 | J78: 2003033 | K78: 100
A79: GRSS_CMMSSN_INCM_OFF_BLNC_CCRR | B79: LT_F_IN_223_01 | C79: "Gross fee and commission income corresponding to undrawn balances committed distributed to SCIB under the Collabotarion Revenues distribution agreement" should have a Format numeric (2 decimal places) | D79: INSTRUMENT | E79: GRSS_FEE_CMMSSN_INCM_OFF_BLNC_CCRR | F79: FORMAT_NUM | G79: LT_F_IN | H79: OK | I79: 2003033 | J79: 0 | K79: 0
A80: GRSS_CMMSSN_EXPNS_OFF_BLNC_CCRR | B80: LT_F_IN_224_01 | C80: "Gross fee and commission expense corresponding to undrawn balances committed distributed to SCIB under the Collabotarion Revenues distribution agreement" should have a Format numeric (2 decimal places) | D80: INSTRUMENT | E80: GRSS_FEE_CMMSSN_EXPNS_OFF_BLNC_CCRR | F80: FORMAT_NUM | G80: LT_F_IN | H80: OK | I80: 2003033 | J80: 0 | K80: 0
A81: CNCLLD_INSTRMNT_STTS | B81: LT_F_IN_245_01 | C81: "Flag of instrument cancelled" should match the information on the Codelist | D81: INSTRUMENT | E81: FLG_INSTRMNT_CNCLLD | F81: LISTA | G81: LT_F_IN | H81: KO | I81: 2003033 | J81: 2003033 | K81: 100
A82: =VLOOKUP(E82,Table1[[#All],[Campo]],1,0) -> IDCMB | B82: LT_F_IN_246_01 | C82: "IDCOMB" should match the information on the Codelist | D82: INSTRUMENT | E82: IDCMB | F82: LISTA | G82: LT_F_IN | H82: KO | I82: 2003033 | J82: 2003033 | K82: 100
A83: =VLOOKUP(E83,Table1[[#All],[Campo]],1,0) -> COD_SOC | B83: LT_F_IP_001_01 | C83: "Entity code of the informing society." should match the information on the Codelist | D83: INSTR_PROTECTION | E83: COD_SOC | F83: LISTA | G83: LT_F_IP | H83: OK | I83: 731165 | J83: 0 | K83: 0
A84: =VLOOKUP(E84,Table1[[#All],[Campo]],1,0) -> DT_RFRNC | B84: LT_F_IP_002_01 | C84: "Reference date" must have a Date format (yyyy-mm-dd) | D84: INSTR_PROTECTION | E84: DT_RFRNC | F84: FORMAT_DATE | G84: LT_F_IP | H84: OK | I84: 731165 | J84: 0 | K84: 0
A85: =VLOOKUP(E85,Table1[[#All],[Campo]],1,0) -> INSTRMNT_ID | B85: LT_F_IP_003_01 | C85: "Instrument ID" should have Char format (variable length allowed between 1 and 60 characters) | D85: INSTR_PROTECTION | E85: INSTRMNT_ID | F85: FORMAT_CHAR | G85: LT_F_IP | H85: OK | I85: 731165 | J85: 0 | K85: 0
A86: =VLOOKUP(E86,Table1[[#All],[Campo]],1,0) -> COD_SOC | B86: LT_F_PR_001_01 | C86: "Entity code of the informing society." should match the information on the Codelist | D86: PROTECTION | E86: COD_SOC | F86: LISTA | G86: LT_F_PR | H86: OK | I86: 456960 | J86: 0 | K86: 0
A87: =VLOOKUP(E87,Table1[[#All],[Campo]],1,0) -> DT_RFRNC | B87: LT_F_PR_003_01 | C87: "Reference date" must have a Date format (yyyy-mm-dd) | D87: PROTECTION | E87: DT_RFRNC | F87: FORMAT_DATE | G87: LT_F_PR | H87: OK | I87: 456960 | J87: 0 | K87: 0
A88: =VLOOKUP(E88,Table1[[#All],[Campo]],1,0) -> INSTRMNT_ID | B88: LT_I_IE_004_01 | C88: Any "Instrument ID" in INSTR_ENTITY table must be linked to at least one record in INSTRUMENT table by "Instrument ID" | D88: INSTR_ENTITY | E88: INSTRMNT_ID | F88: INTEGRITY PK CONSTRAINT | G88: LT_I_ | H88: OK | I88: 2490665 | J88: 0 | K88: 0
A89: =VLOOKUP(E89,Table1[[#All],[Campo]],1,0) -> TYP_INSTRMNT | B89: LT_I_IN_008_01 | C89: For instruments with "Type of instrument" other than 'Missing' and other that '1005 - Debt securities', any "Instrument ID" in INSTRUMENT table must be linked to at least one record in INSTR_ENTITY table by "Instrument ID" | D89: INSTRUMENT | E89: TYP_INSTRMNT | F89: INTEGRITY PK CONSTRAINT | G89: LT_I_ | H89: OK | I89: 2001306 | J89: 0 | K89: 0
A90: =VLOOKUP(E90,Table1[[#All],[Campo]],1,0) -> INSTRMNT_ID | B90: LT_I_IP_003_01 | C90: Any "Instrument ID" in INSTR_PROTECTION table must be linked to at least one record in INSTRUMENT table by "Instrument ID" | D90: INSTR_PROTECTION | E90: INSTRMNT_ID | F90: INTEGRITY PK CONSTRAINT | G90: LT_I_ | H90: OK | I90: 731165 | J90: 0 | K90: 0
A91: =VLOOKUP(E91,Table1[[#All],[Campo]],1,0) -> DT_RFRNC | B91: LT_K_EN_009_01 | C91: "Reference date." must not be later than the current date | D91: INTRA_N1_EN | E91: DT_RFRNC | F91: RELACION_FECHA | G91: LT_K_EN | H91: OK | I91: 1096295 | J91: 0 | K91: 0
A92: =VLOOKUP(E92,Table1[[#All],[Campo]],1,0) -> DT_RFRNC | B92: LT_K_IE_002_01 | C92: "Reference date" must not be later than the current date | D92: INTRA_N1_IE | E92: DT_RFRNC | F92: RELACION_FECHA | G92: LT_K_IE | H92: OK | I92: 2490665 | J92: 0 | K92: 0
A93: =VLOOKUP(E93,Table1[[#All],[Campo]],1,0) -> DT_RFRNC | B93: LT_K_IN_007_01 | C93: "Reference date" must not be later than the current date | D93: INTRA_N1_IN | E93: DT_RFRNC | F93: RELACION_FECHA | G93: LT_K_IN | H93: OK | I93: 2002411 | J93: 0 | K93: 0
... A108: =VLOOKUP(E108,Table1[[#All],[Campo]],1,0) -> GRSS_INTRST_INCM | B108: LT_O_IN_198_01 | C108: "Gross Interest income before distribution to SCIB under the Collabotarion Revenues distribution agreement" shall be larger or equal to 0; Negative values trigger attention | D108: INSTRUMENT | E108: GRSS_INTRST_INCM | F108: RELACION_NUM_DF | G108: LT_O_IN | H108: OK | I108: 2002411 | J108: 0 | K108: 0
A109: GRSS_CMMSSN_INCM | B109: LT_O_IN_199_01 | C109: "Gross fee and commission income before distribution to SCIB under the Collabotarion Revenues distribution agreement" shall be larger or equal to 0; Negative values trigger attention | D109: INSTRUMENT | E109: GRSS_FEE_CMMSSN_INCM | F109: RELACION_NUM_DF | G109: LT_O_IN | H109: OK | I109: 2002411 | J109: 0 | K109: 0
A110: =VLOOKUP(E110,Table1[[#All],[Campo]],1,0) -> INTRNL_TRNSFR_RT | B110: LT_O_IN_200_01 | C110: "Internal transfer rate amount" shall be smaller or equal to 0; Positive values trigger attention | D110: INSTRUMENT | E110: INTRNL_TRNSFR_RT | F110: RELACION_NUM_DF | G110: LT_O_IN | H110: OK | I110: 2002411 | J110: 0 | K110: 0
A111: =VLOOKUP(E111,Table1[[#All],[Campo]],1,0) -> NT_LN_LSS_PRVSN | B111: LT_O_IN_201_01 | C111: "Net loan-loss provisions" shall be larger than or equal to 0; Negative values trigger attention | D111: INSTRUMENT | E111: NT_LN_LSS_PRVSN | F111: RELACION_NUM_DF | G111: LT_O_IN | H111: OK | I111: 2002411 | J111: 0 | K111: 0
A112: GRSS_CMMSSN_EXPNS | B112: LT_O_IN_204_01 | C112: "Gross fee and commission expense before distribution to SCIB under the Collabotarion Revenues distribution agreement" shall be larger or equal to 0; Negative values trigger attention | D112: INSTRUMENT | E112: GRSS_FEE_CMMSSN_EXPNS | F112: RELACION_NUM_DF | G112: LT_O_IN | H112: OK | I112: 2002411 | J112: 0 | K112: 0
A113: =VLOOKUP(E113,Table1[[#All],[Campo]],1,0) -> GNS_FNNCL_TRNSCTN_EXCHNG_DFFRNCS | B113: LT_O_IN_205_01 | C113: "Gains (Losses) On Financial Transaction (gft) And Exchange Differences, before distribution to SCIB under the Collabotarion Revenues distribution agreement" shall be larger or equal to 0; Negative values trigger attention | D113: INSTRUMENT | E113: GNS_FNNCL_TRNSCTN_EXCHNG_DFFRNCS | F113: RELACION_NUM_DF | G113: LT_O_IN | H113: OK | I113: 2002411 | J113: 0 | K113: 0
A114: =VLOOKUP(E114,Table1[[#All],[Campo]],1,0) -> AVRG_BLNC_OFF_BLNC | B114: LT_O_IN_210_01 | C114: "Average balance corresponding to undrawn balances committed" shall be larger or equal to 0; Negative values trigger attention | D114: INSTRUMENT | E114: AVRG_BLNC_OFF_BLNC | F114: RELACION_NUM_DF | G114: LT_O_IN | H114: OK | I114: 2002411 | J114: 0 | K114: 0
A115: =VLOOKUP(E115,Table1[[#All],[Campo]],1,0) -> INTRNL_TRNSFR_RT_OFF_BLNC | B115: LT_O_IN_211_01 | C115: "Internal transfer rate amount corresponding to undrawn balances committed" shall be smaller or equal to 0; Positive values trigger attention | D115: INSTRUMENT | E115: INTRNL_TRNSFR_RT_OFF_BLNC | F115: RELACION_NUM_DF | G115: LT_O_IN | H115: OK | I115: 2002411 | J115: 0 | K115: 0
A116: GRSS_CMMSSN_INCM_OFF_BLNC | B116: LT_O_IN_212_01 | C116: "Gross fee and commission income corresponding to undrawn balances committed" shall be larger or equal to 0; Negative values trigger attention | D116: INSTRUMENT | E116: GRSS_FEE_CMMSSN_INCM_OFF_BLNC | F116: RELACION_NUM_DF | G116: LT_O_IN | H116: OK | I116: 2002411 | J116: 0 | K116: 0
A117: GRSS_CMMSSN_EXPNS_OFF_BLNC | B117: LT_O_IN_213_01 | C117: "Gross fee and commission expense corresponding to undrawn balances committed" shall be larger or equal to 0; Negative values trigger attention | D117: INSTRUMENT | E117: GRSS_FEE_CMMSSN_EXPNS_OFF_BLNC | F117: RELACION_NUM_DF | G117: LT_O_IN | H117: OK | I117: 2002411 | J117: 0 | K117: 0
A118: =VLOOKUP(E118,Table1[[#All],[Campo]],1,0) -> GRSS_INTRST_EXPNS | B118: LT_O_IN_215_01 | C118: "Gross Interest expense before distribution to SCIB under the Collabotarion Revenues distribution agreement" shall be larger or equal to 0; Negative values trigger attention | D118: INSTRUMENT | E118: GRSS_INTRST_EXPNS | F118: RELACION_NUM_DF | G118: LT_O_IN | H118: OK | I118: 2002411 | J118: 0 | K118: 0
A119: =VLOOKUP(E119,Table1[[#All],[Campo]],1,0) -> GRSS_INTRST_INCM_CCRR | B119: LT_O_IN_217_01 | C119: "Gross Interest income distributed to SCIB under the Collabotarion Revenues distribution agreement" shall be larger or equal to 0; Negative values trigger attention | D119: INSTRUMENT | E119: GRSS_INTRST_INCM_CCRR | F119: RELACION_NUM_DF | G119: LT_O_IN | H119: OK | I119: 2002411 | J119: 0 | K119: 0
A120: =VLOOKUP(E120,Table1[[#All],[Campo]],1,0) -> GRSS_INTRST_EXPNS_CCRR | B120: LT_O_IN_218_01 | C120: "Gross Interest expense distributed to SCIB under the Collabotarion Revenues distribution agreement" shall be larger or equal to 0; Negative values trigger attention | D120: INSTRUMENT | E120: GRSS_INTRST_EXPNS_CCRR | F120: RELACION_NUM_DF | G120: LT_O_IN | H120: OK | I120: 2002411 | J120: 0 | K120: 0
A121: GRSS_CMMSSN_INCM_CCRR | B121: LT_O_IN_219_01 | C121: "Gross fee and commission income distributed to SCIB under the Collabotarion Revenues distribution agreement" shall be larger or equal to 0; Negative values trigger attention | D121: INSTRUMENT | E121: GRSS_FEE_CMMSSN_INCM_CCRR | F121: RELACION_NUM_DF | G121: LT_O_IN | H121: OK | I121: 2002411 | J121: 0 | K121: 0
A122: GRSS_CMMSSN_EXPNS_CCRR | B122: LT_O_IN_220_01 | C122: "Gross fee and commission expense distributed to SCIB under the Collabotarion Revenues distribution agreement" shall be larger or equal to 0; Negative values trigger attention | D122: INSTRUMENT | E122: GRSS_FEE_CMMSSN_EXPNS_CCRR | F122: RELACION_NUM_DF | G122: LT_O_IN | H122: OK | I122: 2002411 | J122: 0 | K122: 0
A123: =VLOOKUP(E123,Table1[[#All],[Campo]],1,0) -> GNS_FNNCL_TRNSCTN_EXCHNG_CCRR | B123: LT_O_IN_221_01 | C123: "Gains (Losses) On Financial Transaction (gft) And Exchange Differences distributed to SCIB under the Collabotarion Revenues distribution agreement" shall be larger or equal to 0; Negative values trigger attention | D123: INSTRUMENT | E123: GNS_FNNCL_TRNSCTN_EXCHNG_CCRR | F123: RELACION_NUM_DF | G123: LT_O_IN | H123: OK | I123: 2002411 | J123: 0 | K123: 0
A124: GRSS_CMMSSN_INCM_OFF_BLNC_CCRR | B124: LT_O_IN_223_01 | C124: "Gross fee and commission income corresponding to undrawn balances committed distributed to SCIB under the Collabotarion Revenues distribution agreement" shall be larger than or equal to 0; Negative values trigger attention | D124: INSTRUMENT | E124: GRSS_FEE_CMMSSN_INCM_OFF_BLNC_CCRR | F124: RELACION_NUM_DF | G124: LT_O_IN | H124: OK | I124: 2002411 | J124: 0 | K124: 0
A125: GRSS_CMMSSN_EXPNS_OFF_BLNC_CCRR | B125: LT_O_IN_224_01 | C125: "Gross fee and commission expense corresponding to undrawn balances committed distributed to SCIB under the Collabotarion Revenues distribution agreement" shall be larger than or equal to 0; Negative values trigger attention | D125: INSTRUMENT | E125: GRSS_FEE_CMMSSN_EXPNS_OFF_BLNC_CCRR | F125: RELACION_NUM_DF | G125: LT_O_IN | H125: OK | I125: 2002411 | J125: 0 | K125: 0
A126: =VLOOKUP(E126,Table1[[#All],[Campo]],1,0) -> DT_RFRNC | B126: LT_O_IP_002_01 | C126: "Reference date" must be later than 01 December 2020 | D126: INSTR_PROTECTION | E126: DT_RFRNC | F126: RELACION_FECHA | G126: LT_O_IP | H126: OK | I126: 731165 | J126: 0 | K126: 0
A127: =VLOOKUP(E127,Table1[[#All],[Campo]],1,0) -> DT_RFRNC | B127: LT_O_PR_003_01 | C127: "Reference date" must be later than 01 December 2020 | D127: PROTECTION | E127: DT_RFRNC | F127: RELACION_FECHA | G127: LT_O_PR | H127: OK | I127: 456960 | J127: 0 | K127: 0
A128: =VLOOKUP(E128,Table1[[#All],[Campo]],1,0) -> SUBPORTFOLIO_ID | B128: LT_R_IN_002_01 | C128: If "Leverage finance flag" is set to 'Y' then "Subportfolio ID" must be classified as 'SNF - Non-financial corporations' | D128: INTRA_REL_P_IN | E128: SUBPORTFOLIO_ID | F128: REL_CAMPOS | G128: LT_R_IN | H128: OK | I128: 0 | J128: 0 | K128: 0
A129: =VLOOKUP(E129,Table1[[#All],[Campo]],1,0) -> DFLT_STTS_INSTRMNT | B129: LT_R_IN_020_01 | C129: If "ISDA credit event declared" is equal to 'Y', then "Default status of the instrument" must be set as '18 - Default because both unlikely to pay and more than 90/180 days past due', '19 - Default because unlikely to pay' or '20 - Default because more than 90/180 days past due' | D129: INTER_REL_P_X2 | E129: DFLT_STTS_INSTRMNT | F129: REL_CAMPOS | G129: LT_R_IN | H129: OK | I129: 0 | J129: 0 | K129: 0
A130: =VLOOKUP(E130,Table1[[#All],[Campo]],1,0) -> DFLT_STTS_INSTRMNT | B130: LT_R_IN_020_03 | C130: If "Protection called" is set as 'Y' then "Default status of the instrument" has to be set as '18 - Default because both unlikely to pay and more than 90/180 days past due', '19 - Default because unlikely to pay' or '20 - Default because more than 90/180 days past due' | D130: INTER_REL_P_X3 | E130: DFLT_STTS_INSTRMNT | F130: REL_CAMPOS | G130: LT_R_IN | H130: OK | I130: 0 | J130: 0 | K130: 0
A131: =VLOOKUP(E131,Table1[[#All],[Campo]],1,0) -> DFLT_STTS_INSTRMNT | B131: LT_R_IN_020_04 | C131: If "Leverage finance flag" is set to 'Y' and "Covenant status" is equal to '4 - In breach with at least one material financial covenant' then "Default status of the instrument" must be '18 - Default because both unlikely to pay and more than 90/180 days past due', '19 - Default because unlikely to pay' or '20 - Default because more than 90/180 days past due' | D131: INTRA_REL_P_IN | E131: DFLT_STTS_INSTRMNT | F131: REL_CAMPOS | G131: LT_R_IN | H131: OK | I131: 0 | J131: 0 | K131: 0
A132: =VLOOKUP(E132,Table1[[#All],[Campo]],1,0) -> IMPRMNT_STTS | B132: LT_R_IN_034_01 | C132: if "Days past due at reference date" is between 30 and 90 days and "Subportfolio ID" is not classified as 'VRPL - FV with changes in PL' then "Impairment status" must be '24 - Stage 2 (IFRS)' or '25 - Stage 3 (IFRS)' | D132: INTRA_REL_P_IN | E132: IMPRMNT_STTS | F132: REL_CAMPOS | G132: LT_R_IN | H132: KO | I132: 9703 | J132: 1 | K132: 0.0103
A133: =VLOOKUP(E133,Table1[[#All],[Campo]],1,0) -> IMPRMNT_STTS | B133: LT_R_IN_034_02 | C133: if "Default status of the instrument" is set as '18 - Default because both unlikely to pay and more than 90/180 days past due', '19 - Default because unlikely to pay' or '20 - Default because more than 90/180 days past due' and "Subportfolio ID" is not classified as 'VRPL - FV with changes in PL' then "Impairment status" is set as "25 - Stage 3 (IFRS)" | D133: INTRA_REL_P_IN | E133: IMPRMNT_STTS | F133: REL_CAMPOS | G133: LT_R_IN | H133: KO | I133: 92666 | J133: 3283 | K133: 3.5428
A134: =VLOOKUP(E134,Table1[[#All],[Campo]],1,0) -> IMPRMNT_STTS | B134: LT_R_IN_034_03 | C134: if "Default status of the instrument" is set as '14 - Not in default' and "Subportfolio ID" is not classified as 'VRPL - FV with changes in PL' then "Impairment status" cannot be 25 - Stage 3 (IFRS)' | D134: INTRA_REL_P_IN | E134: IMPRMNT_STTS | F134: REL_CAMPOS | G134: LT_R_IN | H134: KO | I134: 1813562 | J134: 4684 | K134: 0.2583
A135: =VLOOKUP(E135,Table1[[#All],[Campo]],1,0) -> IMPRMNT_STTS | B135: LT_R_IN_034_05 | C135: if "Performing status" is '11 - Performing' and "Subportfolio ID" is not classified as 'VRPL - FV with changes in PL' then "Impairment status" cannot be '25 - Stage 3 (IFRS)' | D135: INTRA_REL_P_IN | E135: IMPRMNT_STTS | F135: REL_CAMPOS | G135: LT_R_IN | H135: OK | I135: 1905178 | J135: 0 | K135: 0
A136: =VLOOKUP(E136,Table1[[#All],[Campo]],1,0) -> IMPRMNT_STTS | B136: LT_R_IN_034_09 | C136: If "Debtor on watch-list (Y/N)" is set as 'Y' and "Subportfolio ID" is not classified as 'VRPL - FV with changes in PL' then "Impairment status" has to be set as '24 - Stage 2 (IFRS)' or '25 - Stage 3 (IFRS)' | D136: INTER_REL_P_X2 | E136: IMPRMNT_STTS | F136: REL_CAMPOS | G136: LT_R_IN | H136: KO | I136: 18441 | J136: 2850 | K136: 15.4547
A137: =VLOOKUP(E137,Table1[[#All],[Campo]],1,0) -> IMPRMNT_STTS | B137: LT_R_IN_034_11 | C137: If "Accounting portfolio"equals '6 - IFRS: Financial assets at amortised cost', '8 - IFRS: Financial assets at fair value through other comprehensive income' or '14 - IFRS: Cash balances at central banks and other demand deposits', then "Impairment status" cannot be 'Not applicable' | D137: INTER_REL_P_X1 | E137: IMPRMNT_STTS | F137: REL_CAMPOS | G137: LT_R_IN | H137: OK | I137: 1724899 | J137: 0 | K137: 0
... A185: =VLOOKUP(E185,Table1[[#All],[Campo]],1,0) -> GRSS_INTRST_INCM | B185: LT_R_IN_198_02 | C185: If "Gross Interest income distributed to SCIB under the Collabotarion Revenues distribution agreement" and "Gross Interest income before distribution to SCIB under the Collabotarion Revenues distribution agreement" are populated with other than default values then "Gross Interest income distributed to SCIB under the Collabotarion Revenues distribution agreement" must be less or equal to "Gross Interest income before distribution to SCIB under the Collabotarion Revenues distribution agreement" | D185: INTRA_REL_P_IN | E185: GRSS_INTRST_INCM | F185: REL_CAMPOS | G185: LT_R_IN | H185: OK | I185: 0 | J185: 0 | K185: 0
A186: GRSS_CMMSSN_INCM | B186: LT_R_IN_199_01 | C186: If "Gross Interest fee and comission income distributed to SCIB under the Collabotarion Revenues distribution agreement" is populated with other than default values then "Gross Interest fee and comission income before distribution to SCIB under the Collabotarion Revenues distribution agreement" cannot be 'Not Applicable | D186: INTRA_REL_P_IN | E186: GRSS_FEE_CMMSSN_INCM | F186: REL_CAMPOS | G186: LT_R_IN | H186: OK | I186: 0 | J186: 0 | K186: 0
A187: GRSS_CMMSSN_INCM | B187: LT_R_IN_199_02 | C187: If "Gross Interest fee and comission income distributed to SCIB under the Collabotarion Revenues distribution agreement" and "Gross Interest fee and comission income before distribution to SCIB under the Collabotarion Revenues distribution agreement" are populated with other than default values then "Gross Interest fee and comission income distributed to SCIB under the Collabotarion Revenues distribution agreement" must be less or equal to "Gross Interest fee and comission income before distribution to SCIB under the Collabotarion Revenues distribution agreement" | D187: INTRA_REL_P_IN | E187: GRSS_FEE_CMMSSN_INCM | F187: REL_CAMPOS | G187: LT_R_IN | H187: OK | I187: 0 | J187: 0 | K187: 0
...

Sheet Auxiliar
B2: Tipologia de testes | D2: Estimação Horas
D3: Complexidade
B4: Categorização de Testes | C4: Descrição | D4: Baixa | E4: Média | F4: Alta
B5: 1. Teste de universo | C5: 1. Validação de universo de contratos quando comparado âmbito "CDG" e "PM" 2. Controlos sobre o desdobramento de chaves nas relações FR-MIS | D5: 8 | E5: 8 | F5: 8
B6: 2. Simulação | C6: Simulação da especificação funcional. Suplementarmente, realizar reuniões de validações e esclarecimentos funcionais junto do negócio/owner. | D6: 2 | E6: 4 | F6: 8
B7: 3. Testes comparativos (Espec. VS Impl.) | C7: A partir da simulação realizada, comparar resultados com a implementação de IT. | D7: 2 | E7: 4 | F7: 8
B8: 4. Validação de parametrizações | C8: A partir da simulação realizada, comparar com as parametrizações implementadas por IT. | D8: 2 | E8: 4 | F8: 8
B9: 5. Teste comparativos com LT | C9: Garantir que a informação do campo da LT-ESTR âmbito 'PM' está espelhado no âmbito 'CDG'. | D9: 1 | E9: 1 | F9: 1
B10: 6. Validação de formatos | C10: Validação de formato de acordo com o que é esperado pela Corporação (incluindo validação de codelists, missing e default values) | D10: 1 | E10: 1 | F10: 1
B11: 7. Validação de controlos corporativos | C11: Validar controlos corporativos e se a especificação cumpre os requisitos. | D11: 2 | E11: 4 | F11: 8
B15: Status
B17: Concluído
B18: Por iniciar
B19: Em Teste
B20: Em Correção
B21: Cancelado

Sheet Tipologias de Testes GD (2)
B8: Origem | C8: Campo | D8: Status | E8: Tipologia de testes | H8: ID Categoria | I8: Categorização de Testes | J8: Descrição
B9: Modelo Verde | C9: SSTNBL_CTGRY | D9: Concluído | E9: 1,2,3,4,6,7 | H9: 1 | I9: Testes End-to-End / Amostragem | J9: - Simulação da EF; - Testes de comparação com o desenvolvido por IT: - Validação de escolha de BSNSS_AREA e construção do instrmnt_id - Validação de saldos associados ao campo em análise - Identificação da origem de incidências.
B10: LT ESTR | C10: DFLT_STTS_INSTRMNT | D10: Concluído | E10: 5.7 | H10: 2 | I10: Testes / Validações Funcionais - EF | J10: - Garantir que o que está desenvolvido se encontra de acordo com a EF do campo; - Validações e esclarecimentos funcionais junto do negócio/owner.
B11: LT ESTR | C11: ACCMLTD_CHNGS_FV_CR_INSTRMNT | D11: Concluído | E11: 5.7 | H11: 3 | I11: Testes / Validações às parametrizações | J11: - Garantir que as parametrizações carregadas se encontram OK; - Validações e esclarecimentos funcionais junto do negócio/owner.
B12: LT ESTR | C12: ACCMLTD_IMPRMNT_INSTRMNT | D12: Concluído | E12: 5.7 | H12: 4 | I12: Testes de Informação Corporativa | J12: - Garantir que a informação do campo corporativo está de acordo com a info que a corporação espera receber.
B13: LT ESTR | C13: ACCNTNG_CLSSFCTN | D13: Concluído | E13: 5.7 | H13: 5 | I13: Testes de Informação LT ESTR - Comparação com 'PM' | J13: - Garantir que a informação do campo da LT-ESTR âmbito 'PM' está espelhado no âmbito 'CDG'.
B14: LT ESTR | C14: COD_SOC | D14: Concluído | E14: 5.7 | H14: 6 | I14: Controlos - Garantir Traçabilidade da tradução de chaves | J14: - Controlos sobre o desdobramento de chaves nas relações FR-MIS (N:N) - Controlos sobre o desdobramento de chaves nas relações MASTER-MIS (N:N)
B15: LT ESTR | C15: DT_RFRNC | D15: Concluído | E15: 5.7 | H15: 7 | I15: Re-Testes | J15: - Re-Teste dos campos com incidência aberta
B16: LT ESTR | C16: GRSS_CRRYNG_AMNT_INSTRMNT | D16: Concluído | E16: 5.7
B17: LT ESTR | C17: IDCMB | D17: Concluído | E17: 5.7
B18: LT ESTR | C18: IMPRMNT_STTS | D18: Concluído | E18: 5.7
B19: LT ESTR | C19: INSTRMNT_ID | D19: Concluído | E19: 5.7
B20: LT ESTR | C20: LCL_INSTMRNT_ID | D20: Concluído | E20: 5.7
B21: LT ESTR | C21: OFF_BLNC_SHT_AMNT_INSTRMNT | D21: Concluído | E21: 5.7
B22: LT ESTR | C22: PRFRMNG_STTS | D22: Concluído | E22: 5.7
B23: LT ESTR | C23: PRVSNS_OFF_BLNC_SHT | D23: Concluído | E23: 5.7
B24: LT ESTR | C24: SUBPORTFOLIO_ID | D24: Concluído | E24: 5.7
B25: LT ESTR | C25: TYP_INSTRMNT | D25: Concluído | E25: 5.7
B26: LT ESTR | C26: RWA | D26: Concluído | E26: 5.7
B27: LT ESTR | C27: COD_SOC_INTRGRP | D27: Concluído | E27: 5.7
... B33: Rentabilidade* | C33: INTRNL_TRNSFR_RT_OFF_BLNC | D33: Concluído | E33: 4.7
B34: Rentabilidade | C34: BSNSS_AREA | D34: Em Teste | E34: 1,2,3,4,6,7
B35: Rentabilidade | C35: AVRG_BLNC | D35: Em Teste | E35: 1,2,3,6,7
B36: Rentabilidade | C36: NT_LN_LSS_PRVSN | D36: Em Teste | E36: 1,2,3,6,7
B37: Rentabilidade | C37: MNGMNT_PRDCT | D37: Em Teste | E37: 1,2,3,4,6,7
B38: Rentabilidade | C38: NW_BSNSS | D38: Em Teste | E38: 1,2,3,6,7
B39: Rentabilidade | C39: GRSS_INTRST_INCM_CCRR | D39: Em Teste | E39: 1,2,3,6,7
B40: Rentabilidade | C40: NT_LN_LSS_PRVSN_OFF_BLNC | D40: Em Teste | E40: 1,2,3,6,7
B41: Rentabilidade | C41: AVRG_BLNC_OFF_BLNC | D41: Em Teste | E41: 1,2,3,6,7
B42: Rentabilidade | C42: BSNSS_AREA_CCRR ** | D42: Em Teste | E42: 1,2,3,4,6,7
B43: Rentabilidade | C43: GRSS_CMMSSN_INCM_OFF_BLNC | D43: Em Teste | E43: 1,2,3,6,7
B44: Rentabilidade | C44: GRSS_CMMSSN_EXPNS_OFF_BLNC_CCRR ** | D44: Em Teste | E44: 1,2,3,6,7
B45: Rentabilidade | C45: GRSS_CMMSSN_EXPNS_OFF_BLNC | D45: Em Teste | E45: 1,2,3,6,7
... B58: Modelo Verde | C58: SSTNBL_INDCTR | D58: Em Correção | E58: 1,2,3,6,7
B62: * Campo com Origem na Rentabilidade mas definido pela corporação
B63: ** Campo desconsiderado com a nova EF - instrmnt_id com sufixo do BSNSS_AREA e reporte de saldo com essa granularidade
