Workbook
Name \a: #REF!
Name \a: #REF!
Name \a: #REF!
Name \b: #REF!
Name \b: #REF!
Name \b: #REF!
Name \c: #REF!
Name \c: #REF!
Name \c: #REF!
Name \d: #REF!
Name \d: #REF!
Name \d: #REF!
Name \e: #REF!
Name \e: #REF!
Name \e: #REF!
Name \m: #REF!
Name \m: #REF!
Name \m: #REF!
Name \p: #REF!
Name \p: #REF!
Name \p: #REF!
Name \q: #REF!
Name \q: #REF!
Name \q: #REF!
Name \s: #REF!
Name \s: #REF!
Name \s: #REF!
Name \v: #REF!
Name \v: #REF!
Name \v: #REF!
Name ___GRUPO_ENVIO: [1]GENMASIVA!$AC$4
Name ___INDEX_SHEET___ASAP_Utilities: #REF!
Name ___INDEX_SHEET___ASAP_Utilities: #REF!
Name ___INDEX_SHEET___ASAP_Utilities: #REF!
Name ___PERIODO: [1]GENMASIVA!$AC$2
Name ___td2: #REF!
Name ___td2: #REF!
Name ___td2: #REF!
Name ___td3: #REF!
Name ___td3: #REF!
Name ___td3: #REF!
Name ___td4: #REF!
Name ___td4: #REF!
Name ___td4: #REF!
Name ___ti1: #REF!
Name ___ti1: #REF!
Name ___ti1: #REF!
Name ___ti2: #REF!
Name ___ti2: #REF!
Name ___ti2: #REF!
Name ___ti3: #REF!
Name ___ti3: #REF!
Name ___ti3: #REF!
Name ___ti4: #REF!
Name ___ti4: #REF!
Name ___ti4: #REF!
Name ___tp1: #REF!
Name ___tp1: #REF!
Name ___tp1: #REF!
Name ___tp2: #REF!

Sheet Comparativo s adjudicados
B8: Tatico
B9: informing_soc | C9: counterparty_soc | D9: adjustment_code | E9: comb_code | F9: amount | G9: eu | H9: chro | I9: acut | J9: geo | K9: cnael | L9: nace
A10: =CONCATENATE(B10,C10,D10,E10) -> 411421BI00411CONT1;HFS2;B01;MC08;TYVA01;INVS4;MESG4 | B10: 411 | C10: 421 | D10: BI00411 | E10: CONT1;HFS2;B01;MC08;TYVA01;INVS4;MESG4 | F10: 450662960 | G10: EU1 | H10: CHRO2 | I10: ACUT2 | J10: GEO18 | O10: =VLOOKUP(A10,$A$27:$A$44,1,FALSE) -> 411421BI00411CONT1;HFS2;B01;MC08;TYVA01;INVS4;MESG4
A11: =CONCATENATE(B11,C11,D11,E11) -> 4113162BI00411CONT1;HFS2;B01;MC08;TYVA01;INVS4;MESG4 | B11: 411 | C11: 3162 | D11: BI00411 | E11: CONT1;HFS2;B01;MC08;TYVA01;INVS4;MESG4 | F11: 7932813 | G11: EU1 | H11: CHRO2 | I11: ACUT2 | J11: GEO3 | O11: =VLOOKUP(A11,$A$27:$A$44,1,FALSE) -> 4113162BI00411CONT1;HFS2;B01;MC08;TYVA01;INVS4;MESG4
A12: =CONCATENATE(B12,C12,D12,E12) -> 4111333BI00411CONT1;HFS2;B01;MC08;TYVA01;INVS4;MESG4 | B12: 411 | C12: 1333 | D12: BI00411 | E12: CONT1;HFS2;B01;MC08;TYVA01;INVS4;MESG4 | F12: 88691496 | G12: EU1 | H12: CHRO2 | I12: ACUT2 | J12: GEO3 | O12: =VLOOKUP(A12,$A$27:$A$44,1,FALSE) -> 4111333BI00411CONT1;HFS2;B01;MC08;TYVA01;INVS4;MESG4
A13: =CONCATENATE(B13,C13,D13,E13) -> 411421BI00411CONT1;HFS2;B01;MC08;TYVA01;MESG4 | B13: 411 | C13: 421 | D13: BI00411 | E13: CONT1;HFS2;B01;MC08;TYVA01;MESG4 | F13: -1 | G13: EU1 | H13: CHRO2 | I13: ACUT2 | J13: GEO18 | O13: =VLOOKUP(A13,$A$27:$A$44,1,FALSE) -> #N/A
A14: =CONCATENATE(B14,C14,D14,E14) -> 411442BI00411CONT1;HFS2;B01;MC08;TYVA01;INVS5;EXC2;MESG4 | B14: 411 | C14: 442 | D14: BI00411 | E14: CONT1;HFS2;B01;MC08;TYVA01;INVS5;EXC2;MESG4 | F14: 99962303 | G14: EU1 | H14: CHRO2 | I14: ACUT2 | J14: GEO3 | K14: CNAEL6 | L14: NACE06010101 | O14: =VLOOKUP(A14,$A$27:$A$44,1,FALSE) -> 411442BI00411CONT1;HFS2;B01;MC08;TYVA01;INVS5;EXC2;MESG4
A15: =CONCATENATE(B15,C15,D15,E15) -> 4110BI00411CONT1;HFS2;B01;MC06;ACPF5;SC0303;TYVA01;EXC2;MESG4 | B15: 411 | C15: 0 | D15: BI00411 | E15: CONT1;HFS2;B01;MC06;ACPF5;SC0303;TYVA01;EXC2;MESG4 | F15: 22684 | G15: EU1 | H15: CHRO2 | I15: ACUT2 | J15: GEO3 | K15: CNAEL18 | L15: NACE19010303 | O15: =VLOOKUP(A15,$A$27:$A$44,1,FALSE) -> 4110BI00411CONT1;HFS2;B01;MC06;ACPF5;SC0303;TYVA01;EXC2;MESG4
A16: =CONCATENATE(B16,C16,D16,E16) -> 4110BI00411CONT1;HFS2;B01;MC06;ACPF3;SC0302;TYVA01;MESG4 | B16: 411 | C16: 0 | D16: BI00411 | E16: CONT1;HFS2;B01;MC06;ACPF3;SC0302;TYVA01;MESG4 | F16: 17085832 | G16: EU1 | H16: CHRO2 | I16: ACUT2 | J16: GEO3 | O16: =VLOOKUP(A16,$A$27:$A$44,1,FALSE) -> 4110BI00411CONT1;HFS2;B01;MC06;ACPF3;SC0302;TYVA01;MESG4
A17: =CONCATENATE(B17,C17,D17,E17) -> 411445BI00411CONT1;HFS2;B01;MC08;TYVA01;INVS4;MESG4 | B17: 411 | C17: 445 | D17: BI00411 | E17: CONT1;HFS2;B01;MC08;TYVA01;INVS4;MESG4 | F17: 49500 | G17: EU1 | H17: CHRO2 | I17: ACUT2 | J17: GEO3 | O17: =VLOOKUP(A17,$A$27:$A$44,1,FALSE) -> 411445BI00411CONT1;HFS2;B01;MC08;TYVA01;INVS4;MESG4
A18: =CONCATENATE(B18,C18,D18,E18) -> 4110BI00411CONT1;HFS2;B01;MC06;ACPF5;SC0303;TYVA01;EXC2;MESG4 | B18: 411 | C18: 0 | D18: BI00411 | E18: CONT1;HFS2;B01;MC06;ACPF5;SC0303;TYVA01;EXC2;MESG4 | F18: 131176 | G18: EU1 | H18: CHRO2 | I18: ACUT2 | J18: GEO18 | K18: CNAEL11 | L18: NACE12010101 | O18: =VLOOKUP(A18,$A$27:$A$44,1,FALSE) -> 4110BI00411CONT1;HFS2;B01;MC06;ACPF5;SC0303;TYVA01;EXC2;MESG4
A19: =CONCATENATE(B19,C19,D19,E19) -> 411442BI00411CONT1;HFS2;B01;MC08;TYVA02;INVS5;EXC2 | B19: 411 | C19: 442 | D19: BI00411 | E19: CONT1;HFS2;B01;MC08;TYVA02;INVS5;EXC2 | F19: -11000000 | G19: EU1 | H19: CHRO2 | I19: ACUT2 | J19: GEO3 | K19: CNAEL6 | L19: NACE06010101 | O19: =VLOOKUP(A19,$A$27:$A$44,1,FALSE) -> 411442BI00411CONT1;HFS2;B01;MC08;TYVA02;INVS5;EXC2
A20: =CONCATENATE(B20,C20,D20,E20) -> 4110BI00411CONT1;HFS2;B01;MC06;ACPF5;SC0302;TYVA01;MESG4 | B20: 411 | C20: 0 | D20: BI00411 | E20: CONT1;HFS2;B01;MC06;ACPF5;SC0302;TYVA01;MESG4 | F20: 2493971 | G20: EU2 | H20: CHRO2 | I20: ACUT2 | J20: GEO2 | O20: =VLOOKUP(A20,$A$27:$A$44,1,FALSE) -> 4110BI00411CONT1;HFS2;B01;MC06;ACPF5;SC0302;TYVA01;MESG4
A21: =CONCATENATE(B21,C21,D21,E21) -> 4110BI00411CONT1;HFS2;B01;MC06;ACPF5;SC0303;TYVA01;EXC2;MESG4 | B21: 411 | C21: 0 | D21: BI00411 | E21: CONT1;HFS2;B01;MC06;ACPF5;SC0303;TYVA01;EXC2;MESG4 | F21: 35578 | G21: EU1 | H21: CHRO2 | I21: ACUT2 | J21: GEO3 | K21: CNAEL3 | L21: NACE03200302 | O21: =VLOOKUP(A21,$A$27:$A$44,1,FALSE) -> 4110BI00411CONT1;HFS2;B01;MC06;ACPF5;SC0303;TYVA01;EXC2;MESG4
A22: =CONCATENATE(B22,C22,D22,E22) -> 4110BI00411CONT1;HFS2;B01;MC06;ACPF5;SC0302;TYVA01;MESG4 | B22: 411 | C22: 0 | D22: BI00411 | E22: CONT1;HFS2;B01;MC06;ACPF5;SC0302;TYVA01;MESG4 | F22: 171653011 | G22: EU1 | H22: CHRO2 | I22: ACUT2 | J22: GEO3 | O22: =VLOOKUP(A22,$A$27:$A$44,1,FALSE) -> 4110BI00411CONT1;HFS2;B01;MC06;ACPF5;SC0302;TYVA01;MESG4
B25: Estrutural
B26: reporting_soc | C26: counterparty_soc | D26: adjustment_code | E26: comb_code | F26: amount | G26: eu | H26: chro | I26: acut | J26: geo | K26: cnael | L26: nace | M26: IDCOMBS vs dez24 | N26: Saldos vs Dez 24 | O26: Casuística Saldo
A27: =CONCATENATE(B27,C27,D27,E27) -> 4110BI00411CONT1;HFS1;B01;MC1005;ORIG4;TYVA01;MESG1 | B27: 411 | C27: 0 | D27: BI00411 | E27: CONT1;HFS1;B01;MC1005;ORIG4;TYVA01;MESG1 | F27: 40660146 | H27: CHRO2 | I27: ACUT2 | J27: GEO19 | M27: =VLOOKUP(E27,$E$10:$F$22,1,FALSE) -> #N/A | N27: =VLOOKUP(F27,$F$10:$G$22,1,FALSE) -> #N/A | Q27: =VLOOKUP(A27,$A$10:$A$22,1,FALSE) -> #N/A
A28: =CONCATENATE(B28,C28,D28,E28) -> 4110BI00411CONT1;HFS1;B01;MC1005;ORIG4;TYVA02;MESG1 | B28: 411 | C28: 0 | D28: BI00411 | E28: CONT1;HFS1;B01;MC1005;ORIG4;TYVA02;MESG1 | F28: -21154251 | H28: CHRO2 | I28: ACUT2 | J28: GEO19 | M28: =VLOOKUP(E28,$E$10:$F$22,1,FALSE) -> #N/A | N28: =VLOOKUP(F28,$F$10:$G$22,1,FALSE) -> #N/A | Q28: =VLOOKUP(A28,$A$10:$A$22,1,FALSE) -> #N/A
A29: =CONCATENATE(B29,C29,D29,E29) -> 4110BI00411CONT1;HFS2;B01;MC06;ACPF3;SC0302;TYVA01;MESG4 | B29: 411 | C29: 0 | D29: BI00411 | E29: CONT1;HFS2;B01;MC06;ACPF3;SC0302;TYVA01;MESG4 | F29: 11163168 | G29: EU1 | H29: CHRO2 | I29: ACUT2 | J29: GEO3 | L29: NACE11030301 | M29: =VLOOKUP(E29,$E$10:$F$22,1,FALSE) -> CONT1;HFS2;B01;MC06;ACPF3;SC0302;TYVA01;MESG4 | N29: =VLOOKUP(F29,$F$10:$G$22,1,FALSE) -> #N/A | Q29: =VLOOKUP(A29,$A$10:$A$22,1,FALSE) -> 4110BI00411CONT1;HFS2;B01;MC06;ACPF3;SC0302;TYVA01;MESG4
A30: =CONCATENATE(B30,C30,D30,E30) -> 4110BI00411CONT1;HFS2;B01;MC06;ACPF3;SC0302;TYVA01;MESG4 | B30: 411 | C30: 0 | D30: BI00411 | E30: CONT1;HFS2;B01;MC06;ACPF3;SC0302;TYVA01;MESG4 | F30: 799901 | G30: EU1 | H30: CHRO2 | I30: ACUT2 | J30: GEO3 | L30: NACE11010403 | M30: =VLOOKUP(E30,$E$10:$F$22,1,FALSE) -> CONT1;HFS2;B01;MC06;ACPF3;SC0302;TYVA01;MESG4 | Q30: =VLOOKUP(A30,$A$10:$A$22,1,FALSE) -> 4110BI00411CONT1;HFS2;B01;MC06;ACPF3;SC0302;TYVA01;MESG4
A31: =CONCATENATE(B31,C31,D31,E31) -> 4110BI00411CONT1;HFS2;B01;MC06;ACPF3;SC0302;TYVA01;MESG4 | B31: 411 | C31: 0 | D31: BI00411 | E31: CONT1;HFS2;B01;MC06;ACPF3;SC0302;TYVA01;MESG4 | F31: 5122764 | G31: EU1 | H31: CHRO2 | I31: ACUT2 | J31: GEO3 | M31: =VLOOKUP(E31,$E$10:$F$22,1,FALSE) -> CONT1;HFS2;B01;MC06;ACPF3;SC0302;TYVA01;MESG4 | N31: =VLOOKUP(F31,$F$10:$G$22,1,FALSE) -> #N/A | Q31: =VLOOKUP(A31,$A$10:$A$22,1,FALSE) -> 4110BI00411CONT1;HFS2;B01;MC06;ACPF3;SC0302;TYVA01;MESG4
A32: =CONCATENATE(B32,C32,D32,E32) -> 4110BI00411CONT1;HFS2;B01;MC06;ACPF5;SC0302;TYVA01;MESG4 | B32: 411 | C32: 0 | D32: BI00411 | E32: CONT1;HFS2;B01;MC06;ACPF5;SC0302;TYVA01;MESG4 | F32: 1 | H32: CHRO2 | I32: ACUT2 | J32: GEO19 | M32: =VLOOKUP(E32,$E$10:$F$22,1,FALSE) -> CONT1;HFS2;B01;MC06;ACPF5;SC0302;TYVA01;MESG4 | N32: =VLOOKUP(F32,$F$10:$G$22,1,FALSE) -> #N/A | Q32: =VLOOKUP(A32,$A$10:$A$22,1,FALSE) -> 4110BI00411CONT1;HFS2;B01;MC06;ACPF5;SC0302;TYVA01;MESG4
A33: =CONCATENATE(B33,C33,D33,E33) -> 4110BI00411CONT1;HFS2;B01;MC06;ACPF5;SC0302;TYVA01;MESG4 | B33: 411 | C33: 0 | D33: BI00411 | E33: CONT1;HFS2;B01;MC06;ACPF5;SC0302;TYVA01;MESG4 | F33: 2493971 | G33: EU2 | H33: CHRO2 | I33: ACUT2 | J33: GEO2 | M33: =VLOOKUP(E33,$E$10:$F$22,1,FALSE) -> CONT1;HFS2;B01;MC06;ACPF5;SC0302;TYVA01;MESG4 | N33: =VLOOKUP(F33,$F$10:$G$22,1,FALSE) -> 2493971 | Q33: =VLOOKUP(A33,$A$10:$A$22,1,FALSE) -> 4110BI00411CONT1;HFS2;B01;MC06;ACPF5;SC0302;TYVA01;MESG4
A34: =CONCATENATE(B34,C34,D34,E34) -> 4110BI00411CONT1;HFS2;B01;MC06;ACPF5;SC0302;TYVA01;MESG4 | B34: 411 | C34: 0 | D34: BI00411 | E34: CONT1;HFS2;B01;MC06;ACPF5;SC0302;TYVA01;MESG4 | F34: 171653012 | G34: EU1 | H34: CHRO2 | I34: ACUT2 | J34: GEO3 | M34: =VLOOKUP(E34,$E$10:$F$22,1,FALSE) -> CONT1;HFS2;B01;MC06;ACPF5;SC0302;TYVA01;MESG4 | N34: =VLOOKUP(F34,$F$10:$G$22,1,FALSE) -> #N/A | Q34: =VLOOKUP(A34,$A$10:$A$22,1,FALSE) -> 4110BI00411CONT1;HFS2;B01;MC06;ACPF5;SC0302;TYVA01;MESG4
A35: =CONCATENATE(B35,C35,D35,E35) -> 4110BI00411CONT1;HFS2;B01;MC06;ACPF5;SC0303;TYVA01;EXC2;MESG4 | B35: 411 | C35: 0 | D35: BI00411 | E35: CONT1;HFS2;B01;MC06;ACPF5;SC0303;TYVA01;EXC2;MESG4 | F35: 35578 | G35: EU1 | H35: CHRO2 | I35: ACUT2 | J35: GEO3 | K35: CNAEL3 | L35: NACE03200302 | M35: =VLOOKUP(E35,$E$10:$F$22,1,FALSE) -> CONT1;HFS2;B01;MC06;ACPF5;SC0303;TYVA01;EXC2;MESG4 | N35: =VLOOKUP(F35,$F$10:$G$22,1,FALSE) -> 35578 | Q35: =VLOOKUP(A35,$A$10:$A$22,1,FALSE) -> 4110BI00411CONT1;HFS2;B01;MC06;ACPF5;SC0303;TYVA01;EXC2;MESG4
A36: =CONCATENATE(B36,C36,D36,E36) -> 4110BI00411CONT1;HFS2;B01;MC06;ACPF5;SC0303;TYVA01;EXC2;MESG4 | B36: 411 | C36: 0 | D36: BI00411 | E36: CONT1;HFS2;B01;MC06;ACPF5;SC0303;TYVA01;EXC2;MESG4 | F36: 131176 | G36: EU1 | H36: CHRO2 | I36: ACUT2 | J36: GEO18 | K36: CNAEL11 | L36: NACE12010101 | M36: =VLOOKUP(E36,$E$10:$F$22,1,FALSE) -> CONT1;HFS2;B01;MC06;ACPF5;SC0303;TYVA01;EXC2;MESG4 | N36: =VLOOKUP(F36,$F$10:$G$22,1,FALSE) -> 131176 | Q36: =VLOOKUP(A36,$A$10:$A$22,1,FALSE) -> 4110BI00411CONT1;HFS2;B01;MC06;ACPF5;SC0303;TYVA01;EXC2;MESG4
A37: =CONCATENATE(B37,C37,D37,E37) -> 4110BI00411CONT1;HFS2;B01;MC06;ACPF5;SC0303;TYVA01;EXC2;MESG4 | B37: 411 | C37: 0 | D37: BI00411 | E37: CONT1;HFS2;B01;MC06;ACPF5;SC0303;TYVA01;EXC2;MESG4 | F37: 22684 | G37: EU1 | H37: CHRO2 | I37: ACUT2 | J37: GEO3 | K37: CNAEL18 | L37: NACE19010303 | M37: =VLOOKUP(E37,$E$10:$F$22,1,FALSE) -> CONT1;HFS2;B01;MC06;ACPF5;SC0303;TYVA01;EXC2;MESG4 | N37: =VLOOKUP(F37,$F$10:$G$22,1,FALSE) -> 22684 | Q37: =VLOOKUP(A37,$A$10:$A$22,1,FALSE) -> 4110BI00411CONT1;HFS2;B01;MC06;ACPF5;SC0303;TYVA01;EXC2;MESG4
A38: =CONCATENATE(B38,C38,D38,E38) -> 4111333BI00411CONT1;HFS2;B01;MC08;TYVA01;INVS4;MESG4 | B38: 411 | C38: 1333 | D38: BI00411 | E38: CONT1;HFS2;B01;MC08;TYVA01;INVS4;MESG4 | F38: 88691496 | G38: EU1 | H38: CHRO2 | I38: ACUT2 | J38: GEO3 | M38: =VLOOKUP(E38,$E$10:$F$22,1,FALSE) -> CONT1;HFS2;B01;MC08;TYVA01;INVS4;MESG4 | N38: =VLOOKUP(F38,$F$10:$G$22,1,FALSE) -> 88691496 | Q38: =VLOOKUP(A38,$A$10:$A$22,1,FALSE) -> 4111333BI00411CONT1;HFS2;B01;MC08;TYVA01;INVS4;MESG4
A39: =CONCATENATE(B39,C39,D39,E39) -> 4113162BI00411CONT1;HFS2;B01;MC08;TYVA01;INVS4;MESG4 | B39: 411 | C39: 3162 | D39: BI00411 | E39: CONT1;HFS2;B01;MC08;TYVA01;INVS4;MESG4 | F39: 7932813 | G39: EU1 | H39: CHRO2 | I39: ACUT2 | J39: GEO3 | M39: =VLOOKUP(E39,$E$10:$F$22,1,FALSE) -> CONT1;HFS2;B01;MC08;TYVA01;INVS4;MESG4 | N39: =VLOOKUP(F39,$F$10:$G$22,1,FALSE) -> 7932813 | Q39: =VLOOKUP(A39,$A$10:$A$22,1,FALSE) -> 4113162BI00411CONT1;HFS2;B01;MC08;TYVA01;INVS4;MESG4
A40: =CONCATENATE(B40,C40,D40,E40) -> 411421BI00411CONT1;HFS2;B01;MC08;TYVA01;;MESG4 | B40: 411 | C40: 421 | D40: BI00411 | E40: CONT1;HFS2;B01;MC08;TYVA01;;MESG4 | F40: -1 | G40: EU1 | H40: CHRO2 | I40: ACUT2 | J40: GEO18 | M40: =VLOOKUP(E40,$E$10:$F$22,1,FALSE) -> #N/A | N40: =VLOOKUP(F40,$F$10:$G$22,1,FALSE) -> -1 | Q40: =VLOOKUP(A40,$A$10:$A$22,1,FALSE) -> #N/A
A41: =CONCATENATE(B41,C41,D41,E41) -> 411421BI00411CONT1;HFS2;B01;MC08;TYVA01;INVS4;MESG4 | B41: 411 | C41: 421 | D41: BI00411 | E41: CONT1;HFS2;B01;MC08;TYVA01;INVS4;MESG4 | F41: 450662960 | G41: EU1 | H41: CHRO2 | I41: ACUT2 | J41: GEO18 | M41: =VLOOKUP(E41,$E$10:$F$22,1,FALSE) -> CONT1;HFS2;B01;MC08;TYVA01;INVS4;MESG4 | N41: =VLOOKUP(F41,$F$10:$G$22,1,FALSE) -> 450662960 | Q41: =VLOOKUP(A41,$A$10:$A$22,1,FALSE) -> 411421BI00411CONT1;HFS2;B01;MC08;TYVA01;INVS4;MESG4
A42: =CONCATENATE(B42,C42,D42,E42) -> 411442BI00411CONT1;HFS2;B01;MC08;TYVA01;INVS5;EXC2;MESG4 | B42: 411 | C42: 442 | D42: BI00411 | E42: CONT1;HFS2;B01;MC08;TYVA01;INVS5;EXC2;MESG4 | F42: 99962303 | G42: EU1 | H42: CHRO2 | I42: ACUT2 | J42: GEO3 | K42: CNAEL6 | L42: NACE06010101 | M42: =VLOOKUP(E42,$E$10:$F$22,1,FALSE) -> CONT1;HFS2;B01;MC08;TYVA01;INVS5;EXC2;MESG4 | N42: =VLOOKUP(F42,$F$10:$G$22,1,FALSE) -> 99962303 | Q42: =VLOOKUP(A42,$A$10:$A$22,1,FALSE) -> 411442BI00411CONT1;HFS2;B01;MC08;TYVA01;INVS5;EXC2;MESG4
A43: =CONCATENATE(B43,C43,D43,E43) -> 411442BI00411CONT1;HFS2;B01;MC08;TYVA02;INVS5;EXC2 | B43: 411 | C43: 442 | D43: BI00411 | E43: CONT1;HFS2;B01;MC08;TYVA02;INVS5;EXC2 | F43: -11000000 | G43: EU1 | H43: CHRO2 | I43: ACUT2 | J43: GEO3 | K43: CNAEL6 | L43: NACE06010101 | M43: =VLOOKUP(E43,$E$10:$F$22,1,FALSE) -> CONT1;HFS2;B01;MC08;TYVA02;INVS5;EXC2 | N43: =VLOOKUP(F43,$F$10:$G$22,1,FALSE) -> -11000000 | Q43: =VLOOKUP(A43,$A$10:$A$22,1,FALSE) -> 411442BI00411CONT1;HFS2;B01;MC08;TYVA02;INVS5;EXC2
A44: =CONCATENATE(B44,C44,D44,E44) -> 411445BI00411CONT1;HFS2;B01;MC08;TYVA01;INVS4;MESG4 | B44: 411 | C44: 445 | D44: BI00411 | E44: CONT1;HFS2;B01;MC08;TYVA01;INVS4;MESG4 | F44: 49500 | G44: EU1 | H44: CHRO2 | I44: ACUT2 | J44: GEO3 | M44: =VLOOKUP(E44,$E$10:$F$22,1,FALSE) -> CONT1;HFS2;B01;MC08;TYVA01;INVS4;MESG4 | N44: =VLOOKUP(F44,$F$10:$G$22,1,FALSE) -> 49500 | Q44: =VLOOKUP(A44,$A$10:$A$22,1,FALSE) -> 411445BI00411CONT1;HFS2;B01;MC08;TYVA01;INVS4;MESG4
B49: evidencia tabela granular exercicio de dez24 a marcar GEO3 em 'outras instituições financeiras'
B50: csatelite | C50: idcomb_satelite | D50: idcomb_fr012 | E50: cempresa_fr012 | F50: cbalcao_fr012 | G50: cnumecta_fr012 | H50: zdeposit_fr012 | I50: cod_ajust | J50: sociedade_contraparte | K50: saldo_fr012 | L50: cempresa_ct | M50: cbalcao_ct | N50: cnumecta_ct | O50: zdeposit_ct | P50: sociedade_contraparte_ct | Q50: idcomb_ct | R50: pcsb_ct | S50: cargabal_ct | T50: ifrs_ct | U50: cod_ajust_ct | V50: saldo_ct | W50: ps_date | X50: dt_rfrnc | Y50: id_corrida | Z50: zcliente | AA50: 28_dt_maturity | AB50: maturity_esg | AC50: flag_maturity | AD50: years_to_maturity | AE50: european_union | AF50: performing_esg | AG50: 22_counterparty_nuts | AH50: 23_counterparty_zipcode | AI50: 14_nace | AJ50: nace_esg_orig | AK50: 12_non_performing | AL50: 17_accumulated_impairment | AM50: 30_stage_ifrs9 | AN50: 51_client_own_funds | AO50: 75_isin | AP50: cpais_residencia | AQ50: 5_collateral_zip_code | AR50: 4_collateral_nuts | AS50: 16_percent_collateral | AT50: 33_counterparty_type | AU50: excluded_paris | AV50: cnael | AW50: nace_esg | AX50: investment_sector | AY50: peso | AZ50: flag_hipotec | BA50: ckbalbem | BB50: ckctabem | BC50: ckrefbem | BD50: amount | BE50: id | BF50: nace_level4 | BG50: zipcode_collateral | BH50: zipcode_counterparty | BI50: nace_esg_aux | BJ50: acute_changes | BK50: chronic_changes | BL50: geo | BM50: saldo_satelite_agrup | BN50: chave
B51: 79 | C51: CONT1;HFS2;B01;MC06;ACPF5;SC0302;TYVA01 | D51: CONT1;HFS2;B01;MC06;PR18;ACPF5;SC0302;ORIG1;ULINK2;TYVA01 | E51: 31 | F51: 6416 | G51: 0 | H51: PTSIB0AM0008000 | I51: BI00411 | J51: 0 | K51: -140000000.000000 | L51: 31 | M51: 6416 | N51: 0 | O51: PTSIB0AM0008000 | Q51: CONT1;HFS2;B01;MC06;PR18;ACPF5;SC0302;ORIG1;ULINK2;TYVA01 | R51: 25701103 | S51: 15313 | T51: 14137 | U51: BI00411 | V51: -71687210.000000 | W51: 45675 | X51: 45657 | Y51: 1 | Z51: 8006098485 | AA51: 2958465 | AB51: MESG4 | AC51: 0 | AD51: NULL | AE51: EU1 | AG51: PT170 | AH51: 1600 | AI51: M70.1.0 | AJ51: K66.2.9 | AK51: no_stage | AL51: 0.000000 | AN51: 141095835.010000 | AO51: PTSIB0AM0008 | AP51: 620 | AQ51: NULL | AR51: NULL | AS51: NULL | AT51: outras instituicoes financeiras | AY51: 1.000000 | AZ51: 0 | BA51: NULL | BB51: NULL | BC51: NULL | BD51: -71687210.000000000000 | BE51: NACE11030203 | BF51: K6629 - Other activities auxiliary to insurance and pension funding | BG51: NULL | BH51: 1600 | BI51: K.66 | BJ51: ACUT2 | BK51: CHRO2 | BL51: GEO3 | BM51: -171653011.480000000000 | BN51: 31641600000000000PTSIB0AM0008000
B52: 79 | C52: CONT1;HFS2;B01;MC06;ACPF5;SC0302;TYVA01 | D52: CONT1;HFS2;B01;MC06;PR18;ACPF5;SC0302;ORIG1;ULINK2;TYVA01 | E52: 31 | F52: 6416 | G52: 0 | H52: PTSIB0AM0008000 | I52: BI00411 | J52: 0 | K52: -140000000.000000 | L52: 31 | M52: 6416 | N52: 0 | O52: PTSIB0AM0008000 | Q52: CONT1;HFS2;B01;MC06;PR18;ACPF5;SC0302;ORIG1;ULINK2;TYVA01 | R52: 4002010 | S52: 15313 | T52: 14130 | U52: BI00411 | V52: -68312790.000000 | W52: 45675 | X52: 45657 | Y52: 1 | Z52: 8006098485 | AA52: 2958465 | AB52: MESG4 | AC52: 0 | AD52: NULL | AE52: EU1 | AG52: PT170 | AH52: 1600 | AI52: M70.1.0 | AJ52: K66.2.9 | AK52: no_stage | AL52: 0.000000 | AN52: 141095835.010000 | AO52: PTSIB0AM0008 | AP52: 620 | AQ52: NULL | AR52: NULL | AS52: NULL | AT52: outras instituicoes financeiras | AY52: 1.000000 | AZ52: 0 | BA52: NULL | BB52: NULL | BC52: NULL | BD52: -68312790.000000000000 | BE52: NACE11030203 | BF52: K6629 - Other activities auxiliary to insurance and pension funding | BG52: NULL | BH52: 1600 | BI52: K.66 | BJ52: ACUT2 | BK52: CHRO2 | BL52: GEO3 | BM52: -171653011.480000000000 | BN52: 31641600000000000PTSIB0AM0008000

Sheet Comparativo - Deltas Granul
B8: Deltas comparativos entre o exercício tático reportado (Dez24) e o Satélite gerado via solução estrutural To Be (Dez24)
B10: informing_soc | C10: counterparty_soc | D10: adjustment_code | E10: comb_code | F10: amount | I10: eu | L10: chro | O10: acut | R10: geo | U10: cnael | X10: nace
F11: Dez24 Tático | G11: Dez24 Estrutural | H11: ∆ | I11: Dez24 Tático | J11: Dez24 Estrutural | K11: ∆ | L11: Dez24 Tático | M11: Dez24 Estrutural | N11: ∆ | O11: Dez24 Tático | P11: Dez24 Estrutural | Q11: ∆ | R11: Dez24 Tático | S11: Dez24 Estrutural | T11: ∆ | U11: Dez24 Tático | V11: Dez24 Estrutural | W11: ∆ | X11: Dez24 Tático | Y11: Dez24 Estrutural | Z11: ∆
A12: =CONCATENATE(B12,C12,D12,E12) -> 4110BI00411CONT1;HFS2;B01;MC06;ACPF3;SC0302;TYVA01;MESG4 | B12: 411 | C12: 0 | D12: BI00411 | E12: CONT1;HFS2;B01;MC06;ACPF3;SC0302;TYVA01;MESG4 | F12: =_xlfn.IFNA(INDEX('Comparativo s adjudicados'!$A$9:$L$22, MATCH('Comparativo - Deltas Granul'!$A12,'Comparativo s adjudicados'!$A$9:$A$22,0), MATCH('Comparativo - Deltas Granul'!F$10,'Comparativo s adjudicados'!$A$9:$L$9,0)),"") -> 17085832 | G12: ='Comparativo s adjudicados'!F29 -> 11163168 | H12: =SUM(G12:G14)-F12 -> 1 | I12: =_xlfn.IFNA(INDEX('Comparativo s adjudicados'!$A$9:$L$22, MATCH('Comparativo - Deltas Granul'!$A12,'Comparativo s adjudicados'!$A$9:$A$22,0), MATCH('Comparativo - Deltas Granul'!I$10,'Comparativo s adjudicados'!$A$9:$L$9,0)),"") -> EU1 | J12: ='Comparativo s adjudicados'!G29 -> EU1 | K12: =I12=J12 -> TRUE | L12: =INDEX('Comparativo s adjudicados'!$A$9:$L$22,MATCH('Comparativo - Deltas Granul'!$A12,'Comparativo s adjudicados'!$A$9:$A$22,0),MATCH('Comparativo - Deltas Granul'!L$10,'Comparativo s adjudicados'!$A$9:$L$9,0)) -> CHRO2 | M12: =INDEX('Comparativo s adjudicados'!$A$26:$O$44, MATCH('Comparativo - Deltas Granul'!$A12,'Comparativo s adjudicados'!$A$26:$A$44,0), MATCH('Comparativo - Deltas Granul'!L$10,'Comparativo s adjudicados'!$A$26:$O$26,0)) -> CHRO2 | N12: =L12=M12 -> TRUE | O12: =INDEX('Comparativo s adjudicados'!$A$9:$L$22,MATCH('Comparativo - Deltas Granul'!$A12,'Comparativo s adjudicados'!$A$9:$A$22,0),MATCH('Comparativo - Deltas Granul'!O$10,'Comparativo s adjudicados'!$A$9:$L$9,0)) -> ACUT2 | P12: =INDEX('Comparativo s adjudicados'!$A$26:$O$44, MATCH('Comparativo - Deltas Granul'!$A12,'Comparativo s adjudicados'!$A$26:$A$44,0), MATCH('Comparativo - Deltas Granul'!O$10,'Comparativo s adjudicados'!$A$26:$O$26,0)) -> ACUT2 | Q12: =O12=P12 -> TRUE | R12: =INDEX('Comparativo s adjudicados'!$A$9:$L$22,MATCH('Comparativo - Deltas Granul'!$A12,'Comparativo s adjudicados'!$A$9:$A$22,0),MATCH('Comparativo - Deltas Granul'!R$10,'Comparativo s adjudicados'!$A$9:$L$9,0)) -> GEO3 | S12: =INDEX('Comparativo s adjudicados'!$A$26:$O$44, MATCH('Comparativo - Deltas Granul'!$A12,'Comparativo s adjudicados'!$A$26:$A$44,0), MATCH('Comparativo - Deltas Granul'!R$10,'Comparativo s adjudicados'!$A$26:$O$26,0)) -> GEO3 | T12: =R12=S12 -> TRUE | W12: =U12=V12 -> TRUE | Y12: ='Comparativo s adjudicados'!L29 -> NACE11030301 | Z12: =Y12=X12 -> FALSE
D13: BI00411 | E13: CONT1;HFS2;B01;MC06;ACPF3;SC0302;TYVA01;MESG4 | G13: ='Comparativo s adjudicados'!F30 -> 799901 | M13: =INDEX('Comparativo s adjudicados'!$A$26:$O$42,MATCH('Comparativo - Deltas Granul'!$A13,'Comparativo s adjudicados'!$A$26:$A$42,0),MATCH('Comparativo - Deltas Granul'!L$10,'Comparativo s adjudicados'!$A$26:$O$26,0)) -> #N/A | N13: =L13=M13 -> #N/A | P13: =INDEX('Comparativo s adjudicados'!$A$26:$O$42,MATCH('Comparativo - Deltas Granul'!$A13,'Comparativo s adjudicados'!$A$26:$A$42,0),MATCH('Comparativo - Deltas Granul'!O$10,'Comparativo s adjudicados'!$A$26:$O$26,0)) -> #N/A | Q13: =O13=P13 -> #N/A | S13: =INDEX('Comparativo s adjudicados'!$A$26:$O$42,MATCH('Comparativo - Deltas Granul'!$A13,'Comparativo s adjudicados'!$A$26:$A$42,0),MATCH('Comparativo - Deltas Granul'!R$10,'Comparativo s adjudicados'!$A$26:$O$26,0)) -> #N/A | T13: =R13=S13 -> #N/A | Y13: ='Comparativo s adjudicados'!L30 -> NACE11010403 | Z13: =Y13=X13 -> FALSE
C14: 0 | D14: BI00411 | E14: CONT1;HFS2;B01;MC06;ACPF3;SC0302;TYVA01;MESG4 | G14: ='Comparativo s adjudicados'!F31 -> 5122764 | Z14: =Y14=X14 -> TRUE
A15: =CONCATENATE(B15,C15,D15,E15) -> 4110BI00411CONT1;HFS2;B01;MC06;ACPF5;SC0302;TYVA01;MESG4 | B15: 411 | C15: 0 | D15: BI00411 | E15: CONT1;HFS2;B01;MC06;ACPF5;SC0302;TYVA01;MESG4 | F15: ='Comparativo s adjudicados'!F20 -> 2493971 | G15: ='Comparativo s adjudicados'!F33 -> 2493971 | H15: =G15-F15 -> 0 | I15: ='Comparativo s adjudicados'!G20 -> EU2 | J15: ='Comparativo s adjudicados'!G33 -> EU2 | K15: =I15=J15 -> TRUE | L15: ='Comparativo s adjudicados'!H20 -> CHRO2 | M15: ='Comparativo s adjudicados'!H33 -> CHRO2 | N15: =L15=M15 -> TRUE | O15: ='Comparativo s adjudicados'!I20 -> ACUT2 | P15: ='Comparativo s adjudicados'!I33 -> ACUT2 | Q15: =O15=P15 -> TRUE | R15: ='Comparativo s adjudicados'!J20 -> GEO2 | S15: ='Comparativo s adjudicados'!J33 -> GEO2 | T15: =R15=S15 -> TRUE | W15: =U15=V15 -> TRUE | Z15: =Y15=X15 -> TRUE
A16: =CONCATENATE(B16,C16,D16,E16) | F16: ='Comparativo s adjudicados'!F22 -> 171653011 | G16: ='Comparativo s adjudicados'!F34 -> 171653012 | H16: =G16-F16 -> 1 | I16: ='Comparativo s adjudicados'!G22 -> EU1 | J16: ='Comparativo s adjudicados'!G34 -> EU1 | K16: =I16=J16 -> TRUE | L16: ='Comparativo s adjudicados'!H22 -> CHRO2 | M16: ='Comparativo s adjudicados'!H34 -> CHRO2 | N16: =L16=M16 -> TRUE | O16: ='Comparativo s adjudicados'!I22 -> ACUT2 | P16: ='Comparativo s adjudicados'!I34 -> ACUT2 | Q16: =O16=P16 -> TRUE | R16: ='Comparativo s adjudicados'!J22 -> GEO3 | S16: ='Comparativo s adjudicados'!J34 -> GEO3 | T16: =R16=S16 -> TRUE | W16: =U16=V16 -> TRUE | Z16: =Y16=X16 -> TRUE
A17: =CONCATENATE(B17,C17,D17,E17) -> 4110BI00411CONT1;HFS2;B01;MC06;ACPF5;SC0303;TYVA01;EXC2;MESG4 | B17: 411 | C17: 0 | D17: BI00411 | E17: CONT1;HFS2;B01;MC06;ACPF5;SC0303;TYVA01;EXC2;MESG4 | F17: ='Comparativo s adjudicados'!F15 -> 22684 | G17: ='Comparativo s adjudicados'!F37 -> 22684 | H17: =G17-F17 -> 0 | I17: ='Comparativo s adjudicados'!G15 -> EU1 | J17: ='Comparativo s adjudicados'!G37 -> EU1 | K17: =I17=J17 -> TRUE | L17: ='Comparativo s adjudicados'!H15 -> CHRO2 | M17: ='Comparativo s adjudicados'!H37 -> CHRO2 | N17: =L17=M17 -> TRUE | O17: ='Comparativo s adjudicados'!I15 -> ACUT2 | P17: ='Comparativo s adjudicados'!I37 -> ACUT2 | Q17: =O17=P17 -> TRUE | R17: ='Comparativo s adjudicados'!J15 -> GEO3 | S17: ='Comparativo s adjudicados'!J37 -> GEO3 | T17: =R17=S17 -> TRUE | U17: ='Comparativo s adjudicados'!K15 -> CNAEL18 | V17: ='Comparativo s adjudicados'!K37 -> CNAEL18 | W17: =U17=V17 -> TRUE | X17: ='Comparativo s adjudicados'!L15 -> NACE19010303 | Y17: ='Comparativo s adjudicados'!L37 -> NACE19010303 | Z17: =Y17=X17 -> TRUE
A18: =CONCATENATE(B18,C18,D18,E18) -> 4110BI00411 | B18: 411 | C18: 0 | D18: BI00411 | F18: ='Comparativo s adjudicados'!F18 -> 131176 | G18: ='Comparativo s adjudicados'!F36 -> 131176 | H18: =G18-F18 -> 0 | J18: =INDEX('Comparativo s adjudicados'!$A$26:$O$42,MATCH('Comparativo - Deltas Granul'!$A18,'Comparativo s adjudicados'!$A$26:$A$42,0),MATCH('Comparativo - Deltas Granul'!I$10,'Comparativo s adjudicados'!$A$26:$O$26,0)) -> #N/A | L18: =INDEX('Comparativo s adjudicados'!$A$9:$L$22,MATCH('Comparativo - Deltas Granul'!$A18,'Comparativo s adjudicados'!$A$9:$A$22,0),MATCH('Comparativo - Deltas Granul'!L$10,'Comparativo s adjudicados'!$A$9:$L$9,0)) -> #N/A | M18: =INDEX('Comparativo s adjudicados'!$A$26:$O$42,MATCH('Comparativo - Deltas Granul'!$A18,'Comparativo s adjudicados'!$A$26:$A$42,0),MATCH('Comparativo - Deltas Granul'!L$10,'Comparativo s adjudicados'!$A$26:$O$26,0)) -> #N/A | N18: =L18=M18 -> #N/A | O18: =INDEX('Comparativo s adjudicados'!$A$9:$L$22,MATCH('Comparativo - Deltas Granul'!$A18,'Comparativo s adjudicados'!$A$9:$A$22,0),MATCH('Comparativo - Deltas Granul'!O$10,'Comparativo s adjudicados'!$A$9:$L$9,0)) -> #N/A | P18: =INDEX('Comparativo s adjudicados'!$A$26:$O$42,MATCH('Comparativo - Deltas Granul'!$A18,'Comparativo s adjudicados'!$A$26:$A$42,0),MATCH('Comparativo - Deltas Granul'!O$10,'Comparativo s adjudicados'!$A$26:$O$26,0)) -> #N/A | Q18: =O18=P18 -> #N/A | R18: ='Comparativo s adjudicados'!J18 -> GEO18 | S18: ='Comparativo s adjudicados'!J36 -> GEO18 | T18: =R18=S18 -> TRUE | U18: ='Comparativo s adjudicados'!K18 -> CNAEL11 | V18: ='Comparativo s adjudicados'!K36 -> CNAEL11 | W18: =U18=V18 -> TRUE | X18: ='Comparativo s adjudicados'!L18 -> NACE12010101 | Y18: ='Comparativo s adjudicados'!L36 -> NACE12010101 | Z18: =Y18=X18 -> TRUE
A19: =CONCATENATE(B19,C19,D19,E19) -> 4110BI00411 | B19: 411 | C19: 0 | D19: BI00411 | F19: ='Comparativo s adjudicados'!F21 -> 35578 | G19: ='Comparativo s adjudicados'!F35 -> 35578 | H19: =G19-F19 -> 0 | J19: ='Comparativo s adjudicados'!G37 -> EU1 | L19: ='Comparativo s adjudicados'!H15 -> CHRO2 | M19: ='Comparativo s adjudicados'!H37 -> CHRO2 | N19: =L19=M19 -> TRUE | O19: ='Comparativo s adjudicados'!I15 -> ACUT2 | P19: ='Comparativo s adjudicados'!I37 -> ACUT2 | Q19: =O19=P19 -> TRUE | R19: ='Comparativo s adjudicados'!J21 -> GEO3 | S19: ='Comparativo s adjudicados'!J35 -> GEO3 | T19: =R19=S19 -> TRUE | U19: ='Comparativo s adjudicados'!K21 -> CNAEL3 | V19: ='Comparativo s adjudicados'!K35 -> CNAEL3 | W19: =U19=V19 -> TRUE | X19: ='Comparativo s adjudicados'!L21 -> NACE03200302 | Y19: ='Comparativo s adjudicados'!L35 -> NACE03200302 | Z19: =Y19=X19 -> TRUE
A20: =CONCATENATE(B20,C20,D20,E20) -> 4111333BI00411CONT1;HFS2;B01;MC08;TYVA01;INVS4;MESG4 | B20: 411 | C20: 1333 | D20: BI00411 | E20: CONT1;HFS2;B01;MC08;TYVA01;INVS4;MESG4 | F20: =_xlfn.IFNA(INDEX('Comparativo s adjudicados'!$A$9:$L$22, MATCH('Comparativo - Deltas Granul'!$A20,'Comparativo s adjudicados'!$A$9:$A$22,0), MATCH('Comparativo - Deltas Granul'!F$10,'Comparativo s adjudicados'!$A$9:$L$9,0)),"") -> 88691496 | G20: =INDEX('Comparativo s adjudicados'!$A$26:$O$44, MATCH('Comparativo - Deltas Granul'!$A20,'Comparativo s adjudicados'!$A$26:$A$44,0), MATCH('Comparativo - Deltas Granul'!F$10,'Comparativo s adjudicados'!$A$26:$O$26,0)) -> 88691496 | H20: =G20-F20 -> 0 | I20: =_xlfn.IFNA(INDEX('Comparativo s adjudicados'!$A$9:$L$22, MATCH('Comparativo - Deltas Granul'!$A20,'Comparativo s adjudicados'!$A$9:$A$22,0), MATCH('Comparativo - Deltas Granul'!I$10,'Comparativo s adjudicados'!$A$9:$L$9,0)),"") -> EU1 | J20: =_xlfn.IFNA(INDEX('Comparativo s adjudicados'!$A$26:$O$44, MATCH('Comparativo - Deltas Granul'!$A20,'Comparativo s adjudicados'!$A$26:$A$44,0), MATCH('Comparativo - Deltas Granul'!I$10,'Comparativo s adjudicados'!$A$26:$O$26,0)),"") -> EU1 | K20: =I20=J20 -> TRUE | L20: =_xlfn.IFNA(INDEX('Comparativo s adjudicados'!$A$9:$L$22,MATCH('Comparativo - Deltas Granul'!$A20,'Comparativo s adjudicados'!$A$9:$A$22,0),MATCH('Comparativo - Deltas Granul'!L$10,'Comparativo s adjudicados'!$A$9:$L$9,0)),"") -> CHRO2 | M20: =_xlfn.IFNA(INDEX('Comparativo s adjudicados'!$A$26:$O$44, MATCH('Comparativo - Deltas Granul'!$A20,'Comparativo s adjudicados'!$A$26:$A$44,0), MATCH('Comparativo - Deltas Granul'!L$10,'Comparativo s adjudicados'!$A$26:$O$26,0)),"") -> CHRO2 | N20: =L20=M20 -> TRUE | O20: =_xlfn.IFNA(INDEX('Comparativo s adjudicados'!$A$9:$L$22,MATCH('Comparativo - Deltas Granul'!$A20,'Comparativo s adjudicados'!$A$9:$A$22,0),MATCH('Comparativo - Deltas Granul'!O$10,'Comparativo s adjudicados'!$A$9:$L$9,0)),"") -> ACUT2 | P20: =_xlfn.IFNA(INDEX('Comparativo s adjudicados'!$A$26:$O$44, MATCH('Comparativo - Deltas Granul'!$A20,'Comparativo s adjudicados'!$A$26:$A$44,0), MATCH('Comparativo - Deltas Granul'!O$10,'Comparativo s adjudicados'!$A$26:$O$26,0)),"") -> ACUT2 | Q20: =O20=P20 -> TRUE | R20: =_xlfn.IFNA(INDEX('Comparativo s adjudicados'!$A$9:$L$22,MATCH('Comparativo - Deltas Granul'!$A20,'Comparativo s adjudicados'!$A$9:$A$22,0),MATCH('Comparativo - Deltas Granul'!R$10,'Comparativo s adjudicados'!$A$9:$L$9,0)),"") -> GEO3 | S20: =_xlfn.IFNA(INDEX('Comparativo s adjudicados'!$A$26:$O$44, MATCH('Comparativo - Deltas Granul'!$A20,'Comparativo s adjudicados'!$A$26:$A$44,0), MATCH('Comparativo - Deltas Granul'!R$10,'Comparativo s adjudicados'!$A$26:$O$26,0)),"") -> GEO3 | T20: =R20=S20 -> TRUE | W20: =U20=V20 -> TRUE | Z20: =Y20=X20 -> TRUE
A21: =CONCATENATE(B21,C21,D21,E21) -> 4113162BI00411CONT1;HFS2;B01;MC08;TYVA01;INVS4;MESG4 | B21: 411 | C21: 3162 | D21: BI00411 | E21: CONT1;HFS2;B01;MC08;TYVA01;INVS4;MESG4 | F21: =_xlfn.IFNA(INDEX('Comparativo s adjudicados'!$A$9:$L$22, MATCH('Comparativo - Deltas Granul'!$A21,'Comparativo s adjudicados'!$A$9:$A$22,0), MATCH('Comparativo - Deltas Granul'!F$10,'Comparativo s adjudicados'!$A$9:$L$9,0)),"") -> 7932813 | G21: =INDEX('Comparativo s adjudicados'!$A$26:$O$44, MATCH('Comparativo - Deltas Granul'!$A21,'Comparativo s adjudicados'!$A$26:$A$44,0), MATCH('Comparativo - Deltas Granul'!F$10,'Comparativo s adjudicados'!$A$26:$O$26,0)) -> 7932813 | H21: =G21-F21 -> 0 | I21: =_xlfn.IFNA(INDEX('Comparativo s adjudicados'!$A$9:$L$22, MATCH('Comparativo - Deltas Granul'!$A21,'Comparativo s adjudicados'!$A$9:$A$22,0), MATCH('Comparativo - Deltas Granul'!I$10,'Comparativo s adjudicados'!$A$9:$L$9,0)),"") -> EU1 | J21: =_xlfn.IFNA(INDEX('Comparativo s adjudicados'!$A$26:$O$44, MATCH('Comparativo - Deltas Granul'!$A21,'Comparativo s adjudicados'!$A$26:$A$44,0), MATCH('Comparativo - Deltas Granul'!I$10,'Comparativo s adjudicados'!$A$26:$O$26,0)),"") -> EU1 | K21: =I21=J21 -> TRUE | L21: =_xlfn.IFNA(INDEX('Comparativo s adjudicados'!$A$9:$L$22,MATCH('Comparativo - Deltas Granul'!$A21,'Comparativo s adjudicados'!$A$9:$A$22,0),MATCH('Comparativo - Deltas Granul'!L$10,'Comparativo s adjudicados'!$A$9:$L$9,0)),"") -> CHRO2 | M21: =_xlfn.IFNA(INDEX('Comparativo s adjudicados'!$A$26:$O$44, MATCH('Comparativo - Deltas Granul'!$A21,'Comparativo s adjudicados'!$A$26:$A$44,0), MATCH('Comparativo - Deltas Granul'!L$10,'Comparativo s adjudicados'!$A$26:$O$26,0)),"") -> CHRO2 | N21: =L21=M21 -> TRUE | O21: =_xlfn.IFNA(INDEX('Comparativo s adjudicados'!$A$9:$L$22,MATCH('Comparativo - Deltas Granul'!$A21,'Comparativo s adjudicados'!$A$9:$A$22,0),MATCH('Comparativo - Deltas Granul'!O$10,'Comparativo s adjudicados'!$A$9:$L$9,0)),"") -> ACUT2 | P21: =_xlfn.IFNA(INDEX('Comparativo s adjudicados'!$A$26:$O$44, MATCH('Comparativo - Deltas Granul'!$A21,'Comparativo s adjudicados'!$A$26:$A$44,0), MATCH('Comparativo - Deltas Granul'!O$10,'Comparativo s adjudicados'!$A$26:$O$26,0)),"") -> ACUT2 | Q21: =O21=P21 -> TRUE | R21: =_xlfn.IFNA(INDEX('Comparativo s adjudicados'!$A$9:$L$22,MATCH('Comparativo - Deltas Granul'!$A21,'Comparativo s adjudicados'!$A$9:$A$22,0),MATCH('Comparativo - Deltas Granul'!R$10,'Comparativo s adjudicados'!$A$9:$L$9,0)),"") -> GEO3 | S21: =_xlfn.IFNA(INDEX('Comparativo s adjudicados'!$A$26:$O$44, MATCH('Comparativo - Deltas Granul'!$A21,'Comparativo s adjudicados'!$A$26:$A$44,0), MATCH('Comparativo - Deltas Granul'!R$10,'Comparativo s adjudicados'!$A$26:$O$26,0)),"") -> GEO3 | T21: =R21=S21 -> TRUE | W21: =U21=V21 -> TRUE | Z21: =Y21=X21 -> TRUE
A22: =CONCATENATE(B22,C22,D22,E22) -> 411421BI00411CONT1;HFS2;B01;MC08;TYVA01;INVS4;MESG4 | B22: 411 | C22: 421 | D22: BI00411 | E22: CONT1;HFS2;B01;MC08;TYVA01;INVS4;MESG4 | F22: =_xlfn.IFNA(INDEX('Comparativo s adjudicados'!$A$9:$L$22, MATCH('Comparativo - Deltas Granul'!$A22,'Comparativo s adjudicados'!$A$9:$A$22,0), MATCH('Comparativo - Deltas Granul'!F$10,'Comparativo s adjudicados'!$A$9:$L$9,0)),"") -> 450662960 | G22: =INDEX('Comparativo s adjudicados'!$A$26:$O$44, MATCH('Comparativo - Deltas Granul'!$A22,'Comparativo s adjudicados'!$A$26:$A$44,0), MATCH('Comparativo - Deltas Granul'!F$10,'Comparativo s adjudicados'!$A$26:$O$26,0)) -> 450662960 | H22: =G22-F22 -> 0 | I22: =_xlfn.IFNA(INDEX('Comparativo s adjudicados'!$A$9:$L$22, MATCH('Comparativo - Deltas Granul'!$A22,'Comparativo s adjudicados'!$A$9:$A$22,0), MATCH('Comparativo - Deltas Granul'!I$10,'Comparativo s adjudicados'!$A$9:$L$9,0)),"") -> EU1 | J22: =_xlfn.IFNA(INDEX('Comparativo s adjudicados'!$A$26:$O$44, MATCH('Comparativo - Deltas Granul'!$A22,'Comparativo s adjudicados'!$A$26:$A$44,0), MATCH('Comparativo - Deltas Granul'!I$10,'Comparativo s adjudicados'!$A$26:$O$26,0)),"") -> EU1 | K22: =I22=J22 -> TRUE | L22: =_xlfn.IFNA(INDEX('Comparativo s adjudicados'!$A$9:$L$22,MATCH('Comparativo - Deltas Granul'!$A22,'Comparativo s adjudicados'!$A$9:$A$22,0),MATCH('Comparativo - Deltas Granul'!L$10,'Comparativo s adjudicados'!$A$9:$L$9,0)),"") -> CHRO2 | M22: =_xlfn.IFNA(INDEX('Comparativo s adjudicados'!$A$26:$O$44, MATCH('Comparativo - Deltas Granul'!$A22,'Comparativo s adjudicados'!$A$26:$A$44,0), MATCH('Comparativo - Deltas Granul'!L$10,'Comparativo s adjudicados'!$A$26:$O$26,0)),"") -> CHRO2 | N22: =L22=M22 -> TRUE | O22: =_xlfn.IFNA(INDEX('Comparativo s adjudicados'!$A$9:$L$22,MATCH('Comparativo - Deltas Granul'!$A22,'Comparativo s adjudicados'!$A$9:$A$22,0),MATCH('Comparativo - Deltas Granul'!O$10,'Comparativo s adjudicados'!$A$9:$L$9,0)),"") -> ACUT2 | P22: =_xlfn.IFNA(INDEX('Comparativo s adjudicados'!$A$26:$O$44, MATCH('Comparativo - Deltas Granul'!$A22,'Comparativo s adjudicados'!$A$26:$A$44,0), MATCH('Comparativo - Deltas Granul'!O$10,'Comparativo s adjudicados'!$A$26:$O$26,0)),"") -> ACUT2 | Q22: =O22=P22 -> TRUE | R22: =_xlfn.IFNA(INDEX('Comparativo s adjudicados'!$A$9:$L$22,MATCH('Comparativo - Deltas Granul'!$A22,'Comparativo s adjudicados'!$A$9:$A$22,0),MATCH('Comparativo - Deltas Granul'!R$10,'Comparativo s adjudicados'!$A$9:$L$9,0)),"") -> GEO18 | S22: =_xlfn.IFNA(INDEX('Comparativo s adjudicados'!$A$26:$O$44, MATCH('Comparativo - Deltas Granul'!$A22,'Comparativo s adjudicados'!$A$26:$A$44,0), MATCH('Comparativo - Deltas Granul'!R$10,'Comparativo s adjudicados'!$A$26:$O$26,0)),"") -> GEO18 | T22: =R22=S22 -> TRUE | W22: =U22=V22 -> TRUE | Z22: =Y22=X22 -> TRUE
A23: =CONCATENATE(B23,C23,D23,E23) -> 411442BI00411CONT1;HFS2;B01;MC08;TYVA01;INVS5;EXC2;MESG4 | B23: 411 | C23: 442 | D23: BI00411 | E23: CONT1;HFS2;B01;MC08;TYVA01;INVS5;EXC2;MESG4 | F23: =_xlfn.IFNA(INDEX('Comparativo s adjudicados'!$A$9:$L$22, MATCH('Comparativo - Deltas Granul'!$A23,'Comparativo s adjudicados'!$A$9:$A$22,0), MATCH('Comparativo - Deltas Granul'!F$10,'Comparativo s adjudicados'!$A$9:$L$9,0)),"") -> 99962303 | G23: =INDEX('Comparativo s adjudicados'!$A$26:$O$44, MATCH('Comparativo - Deltas Granul'!$A23,'Comparativo s adjudicados'!$A$26:$A$44,0), MATCH('Comparativo - Deltas Granul'!F$10,'Comparativo s adjudicados'!$A$26:$O$26,0)) -> 99962303 | H23: =G23-F23 -> 0 | I23: =_xlfn.IFNA(INDEX('Comparativo s adjudicados'!$A$9:$L$22, MATCH('Comparativo - Deltas Granul'!$A23,'Comparativo s adjudicados'!$A$9:$A$22,0), MATCH('Comparativo - Deltas Granul'!I$10,'Comparativo s adjudicados'!$A$9:$L$9,0)),"") -> EU1 | J23: =_xlfn.IFNA(INDEX('Comparativo s adjudicados'!$A$26:$O$44, MATCH('Comparativo - Deltas Granul'!$A23,'Comparativo s adjudicados'!$A$26:$A$44,0), MATCH('Comparativo - Deltas Granul'!I$10,'Comparativo s adjudicados'!$A$26:$O$26,0)),"") -> EU1 | K23: =I23=J23 -> TRUE | L23: =_xlfn.IFNA(INDEX('Comparativo s adjudicados'!$A$9:$L$22,MATCH('Comparativo - Deltas Granul'!$A23,'Comparativo s adjudicados'!$A$9:$A$22,0),MATCH('Comparativo - Deltas Granul'!L$10,'Comparativo s adjudicados'!$A$9:$L$9,0)),"") -> CHRO2 | M23: =_xlfn.IFNA(INDEX('Comparativo s adjudicados'!$A$26:$O$44, MATCH('Comparativo - Deltas Granul'!$A23,'Comparativo s adjudicados'!$A$26:$A$44,0), MATCH('Comparativo - Deltas Granul'!L$10,'Comparativo s adjudicados'!$A$26:$O$26,0)),"") -> CHRO2 | N23: =L23=M23 -> TRUE | O23: =_xlfn.IFNA(INDEX('Comparativo s adjudicados'!$A$9:$L$22,MATCH('Comparativo - Deltas Granul'!$A23,'Comparativo s adjudicados'!$A$9:$A$22,0),MATCH('Comparativo - Deltas Granul'!O$10,'Comparativo s adjudicados'!$A$9:$L$9,0)),"") -> ACUT2 | P23: =_xlfn.IFNA(INDEX('Comparativo s adjudicados'!$A$26:$O$44, MATCH('Comparativo - Deltas Granul'!$A23,'Comparativo s adjudicados'!$A$26:$A$44,0), MATCH('Comparativo - Deltas Granul'!O$10,'Comparativo s adjudicados'!$A$26:$O$26,0)),"") -> ACUT2 | Q23: =O23=P23 -> TRUE | R23: =_xlfn.IFNA(INDEX('Comparativo s adjudicados'!$A$9:$L$22,MATCH('Comparativo - Deltas Granul'!$A23,'Comparativo s adjudicados'!$A$9:$A$22,0),MATCH('Comparativo - Deltas Granul'!R$10,'Comparativo s adjudicados'!$A$9:$L$9,0)),"") -> GEO3 | S23: =_xlfn.IFNA(INDEX('Comparativo s adjudicados'!$A$26:$O$44, MATCH('Comparativo - Deltas Granul'!$A23,'Comparativo s adjudicados'!$A$26:$A$44,0), MATCH('Comparativo - Deltas Granul'!R$10,'Comparativo s adjudicados'!$A$26:$O$26,0)),"") -> GEO3 | T23: =R23=S23 -> TRUE | U23: =_xlfn.IFNA(INDEX('Comparativo s adjudicados'!$A$9:$L$22,MATCH('Comparativo - Deltas Granul'!$A23,'Comparativo s adjudicados'!$A$9:$A$22,0),MATCH('Comparativo - Deltas Granul'!U$10,'Comparativo s adjudicados'!$A$9:$L$9,0)),"") -> CNAEL6 | V23: =_xlfn.IFNA(INDEX('Comparativo s adjudicados'!$A$26:$O$44, MATCH('Comparativo - Deltas Granul'!$A23,'Comparativo s adjudicados'!$A$26:$A$44,0), MATCH('Comparativo - Deltas Granul'!U$10,'Comparativo s adjudicados'!$A$26:$O$26,0)),"") -> CNAEL6 | W23: =U23=V23 -> TRUE | X23: =_xlfn.IFNA(INDEX('Comparativo s adjudicados'!$A$9:$L$22,MATCH('Comparativo - Deltas Granul'!$A23,'Comparativo s adjudicados'!$A$9:$A$22,0),MATCH('Comparativo - Deltas Granul'!X$10,'Comparativo s adjudicados'!$A$9:$L$9,0)),"") -> NACE06010101 | Y23: =_xlfn.IFNA(INDEX('Comparativo s adjudicados'!$A$26:$O$44, MATCH('Comparativo - Deltas Granul'!$A23,'Comparativo s adjudicados'!$A$26:$A$44,0), MATCH('Comparativo - Deltas Granul'!X$10,'Comparativo s adjudicados'!$A$26:$O$26,0)),"") -> NACE06010101 | Z23: =Y23=X23 -> TRUE
A24: =CONCATENATE(B24,C24,D24,E24) -> 411442BI00411CONT1;HFS2;B01;MC08;TYVA02;INVS5;EXC2 | B24: 411 | C24: 442 | D24: BI00411 | E24: CONT1;HFS2;B01;MC08;TYVA02;INVS5;EXC2 | F24: =_xlfn.IFNA(INDEX('Comparativo s adjudicados'!$A$9:$L$22, MATCH('Comparativo - Deltas Granul'!$A24,'Comparativo s adjudicados'!$A$9:$A$22,0), MATCH('Comparativo - Deltas Granul'!F$10,'Comparativo s adjudicados'!$A$9:$L$9,0)),"") -> -11000000 | G24: =INDEX('Comparativo s adjudicados'!$A$26:$O$44, MATCH('Comparativo - Deltas Granul'!$A24,'Comparativo s adjudicados'!$A$26:$A$44,0), MATCH('Comparativo - Deltas Granul'!F$10,'Comparativo s adjudicados'!$A$26:$O$26,0)) -> -11000000 | H24: =G24-F24 -> 0 | I24: =_xlfn.IFNA(INDEX('Comparativo s adjudicados'!$A$9:$L$22, MATCH('Comparativo - Deltas Granul'!$A24,'Comparativo s adjudicados'!$A$9:$A$22,0), MATCH('Comparativo - Deltas Granul'!I$10,'Comparativo s adjudicados'!$A$9:$L$9,0)),"") -> EU1 | J24: =_xlfn.IFNA(INDEX('Comparativo s adjudicados'!$A$26:$O$44, MATCH('Comparativo - Deltas Granul'!$A24,'Comparativo s adjudicados'!$A$26:$A$44,0), MATCH('Comparativo - Deltas Granul'!I$10,'Comparativo s adjudicados'!$A$26:$O$26,0)),"") -> EU1 | K24: =I24=J24 -> TRUE | L24: =_xlfn.IFNA(INDEX('Comparativo s adjudicados'!$A$9:$L$22,MATCH('Comparativo - Deltas Granul'!$A24,'Comparativo s adjudicados'!$A$9:$A$22,0),MATCH('Comparativo - Deltas Granul'!L$10,'Comparativo s adjudicados'!$A$9:$L$9,0)),"") -> CHRO2 | M24: =_xlfn.IFNA(INDEX('Comparativo s adjudicados'!$A$26:$O$44, MATCH('Comparativo - Deltas Granul'!$A24,'Comparativo s adjudicados'!$A$26:$A$44,0), MATCH('Comparativo - Deltas Granul'!L$10,'Comparativo s adjudicados'!$A$26:$O$26,0)),"") -> CHRO2 | N24: =L24=M24 -> TRUE | O24: =_xlfn.IFNA(INDEX('Comparativo s adjudicados'!$A$9:$L$22,MATCH('Comparativo - Deltas Granul'!$A24,'Comparativo s adjudicados'!$A$9:$A$22,0),MATCH('Comparativo - Deltas Granul'!O$10,'Comparativo s adjudicados'!$A$9:$L$9,0)),"") -> ACUT2 | P24: =_xlfn.IFNA(INDEX('Comparativo s adjudicados'!$A$26:$O$44, MATCH('Comparativo - Deltas Granul'!$A24,'Comparativo s adjudicados'!$A$26:$A$44,0), MATCH('Comparativo - Deltas Granul'!O$10,'Comparativo s adjudicados'!$A$26:$O$26,0)),"") -> ACUT2 | Q24: =O24=P24 -> TRUE | R24: =_xlfn.IFNA(INDEX('Comparativo s adjudicados'!$A$9:$L$22,MATCH('Comparativo - Deltas Granul'!$A24,'Comparativo s adjudicados'!$A$9:$A$22,0),MATCH('Comparativo - Deltas Granul'!R$10,'Comparativo s adjudicados'!$A$9:$L$9,0)),"") -> GEO3 | S24: =_xlfn.IFNA(INDEX('Comparativo s adjudicados'!$A$26:$O$44, MATCH('Comparativo - Deltas Granul'!$A24,'Comparativo s adjudicados'!$A$26:$A$44,0), MATCH('Comparativo - Deltas Granul'!R$10,'Comparativo s adjudicados'!$A$26:$O$26,0)),"") -> GEO3 | T24: =R24=S24 -> TRUE | U24: =_xlfn.IFNA(INDEX('Comparativo s adjudicados'!$A$9:$L$22,MATCH('Comparativo - Deltas Granul'!$A24,'Comparativo s adjudicados'!$A$9:$A$22,0),MATCH('Comparativo - Deltas Granul'!U$10,'Comparativo s adjudicados'!$A$9:$L$9,0)),"") -> CNAEL6 | V24: =_xlfn.IFNA(INDEX('Comparativo s adjudicados'!$A$26:$O$44, MATCH('Comparativo - Deltas Granul'!$A24,'Comparativo s adjudicados'!$A$26:$A$44,0), MATCH('Comparativo - Deltas Granul'!U$10,'Comparativo s adjudicados'!$A$26:$O$26,0)),"") -> CNAEL6 | W24: =U24=V24 -> TRUE | X24: =_xlfn.IFNA(INDEX('Comparativo s adjudicados'!$A$9:$L$22,MATCH('Comparativo - Deltas Granul'!$A24,'Comparativo s adjudicados'!$A$9:$A$22,0),MATCH('Comparativo - Deltas Granul'!X$10,'Comparativo s adjudicados'!$A$9:$L$9,0)),"") -> NACE06010101 | Y24: =_xlfn.IFNA(INDEX('Comparativo s adjudicados'!$A$26:$O$44, MATCH('Comparativo - Deltas Granul'!$A24,'Comparativo s adjudicados'!$A$26:$A$44,0), MATCH('Comparativo - Deltas Granul'!X$10,'Comparativo s adjudicados'!$A$26:$O$26,0)),"") -> NACE06010101 | Z24: =Y24=X24 -> TRUE
A25: =CONCATENATE(B25,C25,D25,E25) -> 411445BI00411CONT1;HFS2;B01;MC08;TYVA01;INVS4;MESG4 | B25: 411 | C25: 445 | D25: BI00411 | E25: CONT1;HFS2;B01;MC08;TYVA01;INVS4;MESG4 | F25: =_xlfn.IFNA(INDEX('Comparativo s adjudicados'!$A$9:$L$22, MATCH('Comparativo - Deltas Granul'!$A25,'Comparativo s adjudicados'!$A$9:$A$22,0), MATCH('Comparativo - Deltas Granul'!F$10,'Comparativo s adjudicados'!$A$9:$L$9,0)),"") -> 49500 | G25: =INDEX('Comparativo s adjudicados'!$A$26:$O$44, MATCH('Comparativo - Deltas Granul'!$A25,'Comparativo s adjudicados'!$A$26:$A$44,0), MATCH('Comparativo - Deltas Granul'!F$10,'Comparativo s adjudicados'!$A$26:$O$26,0)) -> 49500 | H25: =G25-F25 -> 0 | I25: =_xlfn.IFNA(INDEX('Comparativo s adjudicados'!$A$9:$L$22, MATCH('Comparativo - Deltas Granul'!$A25,'Comparativo s adjudicados'!$A$9:$A$22,0), MATCH('Comparativo - Deltas Granul'!I$10,'Comparativo s adjudicados'!$A$9:$L$9,0)),"") -> EU1 | J25: =_xlfn.IFNA(INDEX('Comparativo s adjudicados'!$A$26:$O$44, MATCH('Comparativo - Deltas Granul'!$A25,'Comparativo s adjudicados'!$A$26:$A$44,0), MATCH('Comparativo - Deltas Granul'!I$10,'Comparativo s adjudicados'!$A$26:$O$26,0)),"") -> EU1 | K25: =I25=J25 -> TRUE | L25: =_xlfn.IFNA(INDEX('Comparativo s adjudicados'!$A$9:$L$22,MATCH('Comparativo - Deltas Granul'!$A25,'Comparativo s adjudicados'!$A$9:$A$22,0),MATCH('Comparativo - Deltas Granul'!L$10,'Comparativo s adjudicados'!$A$9:$L$9,0)),"") -> CHRO2 | M25: =_xlfn.IFNA(INDEX('Comparativo s adjudicados'!$A$26:$O$44, MATCH('Comparativo - Deltas Granul'!$A25,'Comparativo s adjudicados'!$A$26:$A$44,0), MATCH('Comparativo - Deltas Granul'!L$10,'Comparativo s adjudicados'!$A$26:$O$26,0)),"") -> CHRO2 | N25: =L25=M25 -> TRUE | O25: =_xlfn.IFNA(INDEX('Comparativo s adjudicados'!$A$9:$L$22,MATCH('Comparativo - Deltas Granul'!$A25,'Comparativo s adjudicados'!$A$9:$A$22,0),MATCH('Comparativo - Deltas Granul'!O$10,'Comparativo s adjudicados'!$A$9:$L$9,0)),"") -> ACUT2 | P25: =_xlfn.IFNA(INDEX('Comparativo s adjudicados'!$A$26:$O$44, MATCH('Comparativo - Deltas Granul'!$A25,'Comparativo s adjudicados'!$A$26:$A$44,0), MATCH('Comparativo - Deltas Granul'!O$10,'Comparativo s adjudicados'!$A$26:$O$26,0)),"") -> ACUT2 | Q25: =O25=P25 -> TRUE | R25: =_xlfn.IFNA(INDEX('Comparativo s adjudicados'!$A$9:$L$22,MATCH('Comparativo - Deltas Granul'!$A25,'Comparativo s adjudicados'!$A$9:$A$22,0),MATCH('Comparativo - Deltas Granul'!R$10,'Comparativo s adjudicados'!$A$9:$L$9,0)),"") -> GEO3 | S25: =_xlfn.IFNA(INDEX('Comparativo s adjudicados'!$A$26:$O$44, MATCH('Comparativo - Deltas Granul'!$A25,'Comparativo s adjudicados'!$A$26:$A$44,0), MATCH('Comparativo - Deltas Granul'!R$10,'Comparativo s adjudicados'!$A$26:$O$26,0)),"") -> GEO3 | T25: =R25=S25 -> TRUE | W25: =U25=V25 -> TRUE | Z25: =Y25=X25 -> TRUE
B26: Total | F26: =SUM(F12:F25) -> 827721324 | G26: =SUM(G12:G25) -> 827721326 | H26: =G26-F26 -> 2

Sheet Sat79 - Tático Dez 24
B8: Satélite 79 reportado no exercício tático do Pilar III em ESG - Dezembro 2024
B10: informing_soc | C10: counterparty_soc | D10: adjustment_code | E10: comb_code | F10: amount | G10: eu | H10: chro | I10: acut | J10: geo | K10: cnael | L10: nace
B11: 411 | C11: 421 | D11: BI00411 | E11: CONT1;HFS2;B01;MC08;TYVA01;INVS4;MESG4 | F11: 450662960 | G11: EU1 | H11: CHRO2 | I11: ACUT2 | J11: GEO18
B12: 411 | C12: 3162 | D12: BI00411 | E12: CONT1;HFS2;B01;MC08;TYVA01;INVS4;MESG4 | F12: 7932813 | G12: EU1 | H12: CHRO2 | I12: ACUT2 | J12: GEO3
B13: 411 | C13: 1333 | D13: BI00411 | E13: CONT1;HFS2;B01;MC08;TYVA01;INVS4;MESG4 | F13: 88691496 | G13: EU1 | H13: CHRO2 | I13: ACUT2 | J13: GEO3
B14: 411 | C14: 421 | D14: BI00411 | E14: CONT1;HFS2;B01;MC08;TYVA01;;MESG4 | F14: -1 | G14: EU1 | H14: CHRO2 | I14: ACUT2 | J14: GEO18
B15: 411 | C15: 442 | D15: BI00411 | E15: CONT1;HFS2;B01;MC08;TYVA01;INVS5;EXC2;MESG4 | F15: 99962303 | G15: EU1 | H15: CHRO2 | I15: ACUT2 | J15: GEO3 | K15: CNAEL6 | L15: NACE06010101
B16: 411 | C16: 0 | D16: BI00411 | E16: CONT1;HFS2;B01;MC06;ACPF5;SC0303;TYVA01;EXC2;MESG4 | F16: 22684 | G16: EU1 | H16: CHRO2 | I16: ACUT2 | J16: GEO3 | K16: CNAEL18 | L16: NACE19010303
B17: 411 | C17: 0 | D17: BI00411 | E17: CONT1;HFS2;B01;MC06;ACPF3;SC0302;TYVA01;MESG4 | F17: 17085832 | G17: EU1 | H17: CHRO2 | I17: ACUT2 | J17: GEO3
B18: 411 | C18: 445 | D18: BI00411 | E18: CONT1;HFS2;B01;MC08;TYVA01;INVS4;MESG4 | F18: 49500 | G18: EU1 | H18: CHRO2 | I18: ACUT2 | J18: GEO3
B19: 411 | C19: 0 | D19: BI00411 | E19: CONT1;HFS2;B01;MC06;ACPF5;SC0303;TYVA01;EXC2;MESG4 | F19: 131176 | G19: EU1 | H19: CHRO2 | I19: ACUT2 | J19: GEO18 | K19: CNAEL11 | L19: NACE12010101
B20: 411 | C20: 442 | D20: BI00411 | E20: CONT1;HFS2;B01;MC08;TYVA02;INVS5;EXC2 | F20: -11000000 | G20: EU1 | H20: CHRO2 | I20: ACUT2 | J20: GEO3 | K20: CNAEL6 | L20: NACE06010101
B21: 411 | C21: 0 | D21: BI00411 | E21: CONT1;HFS2;B01;MC06;ACPF5;SC0302;TYVA01;MESG4 | F21: 2493971 | G21: EU2 | H21: CHRO2 | I21: ACUT2 | J21: GEO2
B22: 411 | C22: 0 | D22: BI00411 | E22: CONT1;HFS2;B01;MC06;ACPF5;SC0303;TYVA01;EXC2;MESG4 | F22: 35578 | G22: EU1 | H22: CHRO2 | I22: ACUT2 | J22: GEO3 | K22: CNAEL3 | L22: NACE03200302
B23: 411 | C23: 0 | D23: BI00411 | E23: CONT1;HFS2;B01;MC06;ACPF5;SC0302;TYVA01;MESG4 | F23: 171653011 | G23: EU1 | H23: CHRO2 | I23: ACUT2 | J23: GEO3

Sheet Sat 79 - Sol. Estrutural
B8: Satélite 79 - Satélite gerado pela solução estrutural To Be - Dezembro 2024
B10: reporting_soc | C10: counterparty_soc | D10: adjustment_code | E10: comb_code | F10: amount | G10: eu | H10: chro | I10: acut | J10: geo | K10: cnael | L10: nace
B11: 411 | C11: 0 | D11: BI00411 | E11: CONT1;HFS2;B01;MC06;ACPF3;SC0302;TYVA01;MESG4 | F11: 11163168 | G11: EU1 | H11: CHRO2 | I11: ACUT2 | J11: GEO3 | L11: NACE11030301
B12: 411 | C12: 0 | D12: BI00411 | E12: CONT1;HFS2;B01;MC06;ACPF3;SC0302;TYVA01;MESG4 | F12: 799901 | G12: EU1 | H12: CHRO2 | I12: ACUT2 | J12: GEO3 | L12: NACE11010403
B13: 411 | C13: 0 | D13: BI00411 | E13: CONT1;HFS2;B01;MC06;ACPF3;SC0302;TYVA01;MESG4 | F13: 5122764 | G13: EU1 | H13: CHRO2 | I13: ACUT2 | J13: GEO3
B14: 411 | C14: 0 | D14: BI00411 | E14: CONT1;HFS2;B01;MC06;ACPF5;SC0302;TYVA01;MESG4 | F14: 2493971 | G14: EU2 | H14: CHRO2 | I14: ACUT2 | J14: GEO2
B15: 411 | C15: 0 | D15: BI00411 | E15: CONT1;HFS2;B01;MC06;ACPF5;SC0302;TYVA01;MESG4 | F15: 171653012 | G15: EU1 | H15: CHRO2 | I15: ACUT2 | J15: GEO3
B16: 411 | C16: 0 | D16: BI00411 | E16: CONT1;HFS2;B01;MC06;ACPF5;SC0303;TYVA01;EXC2;MESG4 | F16: 35578 | G16: EU1 | H16: CHRO2 | I16: ACUT2 | J16: GEO3 | K16: CNAEL3 | L16: NACE03200302
B17: 411 | C17: 0 | D17: BI00411 | E17: CONT1;HFS2;B01;MC06;ACPF5;SC0303;TYVA01;EXC2;MESG4 | F17: 131176 | G17: EU1 | H17: CHRO2 | I17: ACUT2 | J17: GEO18 | K17: CNAEL11 | L17: NACE12010101
B18: 411 | C18: 0 | D18: BI00411 | E18: CONT1;HFS2;B01;MC06;ACPF5;SC0303;TYVA01;EXC2;MESG4 | F18: 22684 | G18: EU1 | H18: CHRO2 | I18: ACUT2 | J18: GEO3 | K18: CNAEL18 | L18: NACE19010303
B19: 411 | C19: 1333 | D19: BI00411 | E19: CONT1;HFS2;B01;MC08;TYVA01;INVS4;MESG4 | F19: 88691496 | G19: EU1 | H19: CHRO2 | I19: ACUT2 | J19: GEO3
B20: 411 | C20: 3162 | D20: BI00411 | E20: CONT1;HFS2;B01;MC08;TYVA01;INVS4;MESG4 | F20: 7932813 | G20: EU1 | H20: CHRO2 | I20: ACUT2 | J20: GEO3
B21: 411 | C21: 421 | D21: BI00411 | E21: CONT1;HFS2;B01;MC08;TYVA01;INVS4;MESG4 | F21: 450662960 | G21: EU1 | H21: CHRO2 | I21: ACUT2 | J21: GEO18
B22: 411 | C22: 442 | D22: BI00411 | E22: CONT1;HFS2;B01;MC08;TYVA01;INVS5;EXC2;MESG4 | F22: 99962303 | G22: EU1 | H22: CHRO2 | I22: ACUT2 | J22: GEO3 | K22: CNAEL6 | L22: NACE06010101
B23: 411 | C23: 442 | D23: BI00411 | E23: CONT1;HFS2;B01;MC08;TYVA02;INVS5;EXC2 | F23: -11000000 | G23: EU1 | H23: CHRO2 | I23: ACUT2 | J23: GEO3 | K23: CNAEL6 | L23: NACE06010101
B24: 411 | C24: 445 | D24: BI00411 | E24: CONT1;HFS2;B01;MC08;TYVA01;INVS4;MESG4 | F24: 49500 | G24: EU1 | H24: CHRO2 | I24: ACUT2 | J24: GEO3

Sheet Sat79_dez24
B8: reporting_soc | C8: counterparty_soc | D8: adjustment_code | E8: id_comb | F8: amount | G8: eu | H8: chro | I8: acut | J8: geo | K8: cnael | L8: nace | M8: aveg
B9: 00411 | C9: 00000 | D9: BI00411 | E9: CONT1;HFS2;B01;MC02;ACPF6;SC0303;STAG2;DEFA2;COLL1;TYVA02;FVAD3;PERF1;EXC2 | F9: -22 | G9: EU2 | H9: CHRO2 | I9: ACUT2 | J9: GEO17 | K9: CNAEL7 | L9: NACE07020703
B10: 00411 | C10: 00000 | D10: BI00411 | E10: CONT1;HFS2;B01;MC04;ACPF6;SC0303;STAG1;DEFA2;COLL1;TYVA01;FVAD3;PERF1;EXC2;MESG1 | F10: 4644341 | G10: EU1 | H10: CHRO2 | I10: ACUT2 | J10: GEO3 | K10: CNAEL18 | L10: NACE10040401 | M10: 1
B11: 00411 | C11: 00000 | D11: BI00411 | E11: CONT1;HFS2;B01;MC02;ACPF6;SC0303;STAG1;DEFA2;COLL1;TYVA02;FVAD3;PERF1;EXC2 | F11: -9188 | G11: EU1 | H11: CHRO2 | I11: ACUT2 | J11: GEO3 | K11: CNAEL3 | L11: NACE03140401
B12: 00411 | C12: 00000 | D12: BI00411 | E12: CONT1;HFS2;B01;MC02;ACPF6;SC0303;STAG2;DEFA2;COLL4;TYVA02;FVAD3;PERF1;EXC2 | F12: -121 | G12: EU1 | H12: CHRO1 | I12: ACUT2 | J12: GEO3 | K12: CNAEL3 | L12: NACE03240201
B13: 00411 | C13: 00000 | D13: BI00411 | E13: CONT1;HFS2;B01;MC02;ACPF6;SC0303;STAG1;DEFA2;COLL3;TYVA01;FVAD3;PERF1;EXC2;MESG2 | F13: 118825 | G13: EU1 | H13: CHRO1 | I13: ACUT2 | J13: GEO3 | K13: CNAEL7 | L13: NACE07030505 | M13: 6
B14: 00411 | C14: 00000 | D14: BI00411 | E14: CONT1;HFS2;B01;MC02;ACPF6;SC0303;STAG1;DEFA2;COLL4;TYVA01;FVAD3;PERF1;EXC2;MESG1 | F14: 342170 | G14: EU1 | H14: CHRO2 | I14: ACUT2 | J14: GEO3 | K14: CNAEL12 | L14: NACE13030101 | M14: 3
B15: 00411 | C15: 00000 | D15: BI00411 | E15: CONT1;HFS2;B01;MC02;ACPF6;SC0303;STAG3;DEFA1;COLL4;TYVA02;FVAD3;PERF2;EXC2 | F15: -19996 | G15: EU1 | H15: CHRO2 | I15: ACUT2 | J15: GEO3 | K15: CNAEL16 | L15: NACE17010301
B16: 00411 | C16: 00000 | D16: BI00411 | E16: CONT1;HFS2;B01;MC02;ACPF6;SC0303;STAG1;DEFA2;COLL4;TYVA01;FVAD3;PERF1;EXC2;MESG1 | F16: 55070 | G16: EU1 | H16: CHRO1 | I16: ACUT2 | J16: GEO3 | K16: CNAEL3 | L16: NACE03140802 | M16: 1
B17: 00411 | C17: 00000 | D17: BI00411 | E17: CONT1;HFS2;B01;MC02;ACPF6;SC0303;STAG1;DEFA2;COLL1;TYVA02;FVAD3;PERF1;EXC2 | F17: -2081 | G17: EU1 | H17: CHRO2 | I17: ACUT2 | J17: GEO3 | K17: CNAEL15 | L17: NACE16010601
B18: 00411 | C18: 00000 | D18: BI00411 | E18: CONT1;HFS2;B01;MC02;ACPF6;SC0303;STAG3;DEFA1;COLL3;TYVA01;FVAD3;PERF2;EXC2;MESG1 | F18: 37 | G18: EU1 | H18: CHRO2 | I18: ACUT2 | J18: GEO3 | K18: CNAEL7 | L18: NACE07020701 | M18: 0
B19: 00411 | C19: 00000 | D19: BI00411 | E19: CONT1;HFS2;B01;MC02;ACPF6;SC0303;STAG1;DEFA2;COLL4;TYVA02;FVAD3;PERF1;EXC1 | F19: -9 | G19: EU1 | H19: CHRO2 | I19: ACUT2 | J19: GEO3 | K19: CNAEL12 | L19: NACE13030102
B20: 00411 | C20: 00000 | D20: BI00411 | E20: CONT1;HFS2;B01;MC02;ACPF6;SC0303;STAG3;DEFA1;COLL3;TYVA02;FVAD3;PERF2;EXC2 | F20: -30449 | G20: EU1 | H20: CHRO1 | I20: ACUT2 | J20: GEO3 | K20: CNAEL3 | L20: NACE03040201
B21: 00411 | C21: 00000 | D21: BI00411 | E21: CONT1;HFS2;B01;MC02;ACPF6;SC0303;STAG2;DEFA2;COLL1;TYVA01;FVAD3;PERF1;EXC2;MESG5 | F21: 255474 | G21: EU1 | H21: CHRO2 | I21: ACUT2 | J21: GEO3 | K21: CNAEL6 | L21: NACE06030303
B22: 00411 | C22: 00000 | D22: BI00411 | E22: CONT1;HFS2;B01;MC02;ACPF6;SC0303;STAG2;DEFA2;COLL4;TYVA02;FVAD3;PERF1;EXC2 | F22: -217 | G22: EU1 | H22: CHRO1 | I22: ACUT2 | J22: GEO3 | K22: CNAEL3 | L22: NACE03010103
B23: 00411 | C23: 00000 | D23: BI00411 | E23: CONT1;HFS2;B01;MC02;ACPF6;SC0303;STAG3;DEFA1;COLL3;TYVA02;FVAD3;PERF2;EXC2 | F23: -681 | G23: EU1 | H23: CHRO2 | I23: ACUT2 | J23: GEO3 | K23: CNAEL12 | L23: NACE13060101
B24: 00411 | C24: 00000 | D24: BI00411 | E24: CONT1;HFS2;B01;MC02;ACPF6;SC0303;STAG1;DEFA2;COLL4;TYVA02;FVAD3;PERF1;EXC2 | F24: -4585 | G24: EU1 | H24: CHRO2 | I24: ACUT2 | J24: GEO3 | K24: CNAEL7 | L24: NACE07030708
B25: 00411 | C25: 00000 | D25: BI00411 | E25: CONT1;HFS2;B01;MC02;ACPF6;SC0303;STAG2;DEFA2;COLL4;TYVA01;FVAD3;PERF1;EXC2;MESG1 | F25: 30748 | G25: EU1 | H25: CHRO2 | I25: ACUT2 | J25: GEO3 | K25: CNAEL8 | L25: NACE08040204 | M25: 5
B26: 00411 | C26: 00000 | D26: BI00411 | E26: CONT1;HFS2;B01;MC02;ACPF6;SC0303;STAG2;DEFA2;COLL4;TYVA02;FVAD3;PERF1;EXC2 | F26: -4681 | G26: EU1 | H26: CHRO2 | I26: ACUT2 | J26: GEO3 | K26: CNAEL3 | L26: NACE03110401
B27: 00411 | C27: 00000 | D27: BI00411 | E27: CONT1;HFS2;B01;MC02;ACPF6;SC0303;STAG1;DEFA2;COLL1;TYVA01;FVAD3;PERF1;EXC2;MESG1 | F27: 246120 | G27: EU1 | H27: CHRO2 | I27: ACUT2 | J27: GEO3 | K27: CNAEL10 | L27: NACE10050103 | M27: 2
B28: 00411 | C28: 00000 | D28: BI00411 | E28: CONT1;HFS2;B01;MC02;ACPF6;SC0303;STAG1;DEFA2;COLL1;TYVA01;FVAD3;PERF1;EXC2;MESG1 | F28: 12914804 | G28: EU1 | H28: CHRO2 | I28: ACUT2 | J28: GEO3 | K28: CNAEL10 | L28: NACE10040101 | M28: 1
B29: 00411 | C29: 00000 | D29: BI00411 | E29: CONT1;HFS2;B01;MC02;ACPF6;SC0303;STAG1;DEFA2;COLL1;TYVA01;FVAD3;PERF1;EXC2;MESG1 | F29: 542115 | G29: EU1 | H29: CHRO1 | I29: ACUT2 | J29: GEO3 | K29: CNAEL3 | L29: NACE03160701 | M29: 2
B30: 00411 | C30: 00000 | D30: BI00411 | E30: CONT1;HFS2;B01;MC02;ACPF6;SC0303;STAG2;DEFA2;COLL1;TYVA01;FVAD3;PERF1;EXC2;MESG5 | F30: 66 | G30: EU1 | H30: CHRO2 | I30: ACUT2 | J30: GEO3 | K30: CNAEL3 | L30: NACE03190103
B31: 00411 | C31: 00000 | D31: BI00411 | E31: CONT1;HFS2;B01;MC02;ACPF6;SC0303;STAG1;DEFA2;COLL1;TYVA02;FVAD3;PERF1;EXC2 | F31: -1803 | G31: EU1 | H31: CHRO1 | I31: ACUT2 | J31: GEO3 | K31: CNAEL3 | L31: NACE03170301
B32: 00411 | C32: 00000 | D32: BI00411 | E32: CONT1;HFS2;B01;MC02;ACPF6;SC0303;STAG2;DEFA2;COLL4;TYVA02;FVAD3;PERF1;EXC2 | F32: -2598 | G32: EU1 | H32: CHRO2 | I32: ACUT2 | J32: GEO3 | K32: CNAEL7 | L32: NACE07020204
B33: 00411 | C33: 00000 | D33: BI00411 | E33: CONT1;HFS2;B01;MC02;ACPF6;SC0303;STAG2;DEFA2;COLL1;TYVA01;FVAD3;PERF1;EXC2;MESG1 | F33: 3304605 | G33: EU1 | H33: CHRO1 | I33: ACUT2 | J33: GEO3 | K33: CNAEL3 | L33: NACE03040201 | M33: 2
B34: 00411 | C34: 00000 | D34: BI00411 | E34: CONT1;HFS2;B01;MC02;ACPF6;SC0303;STAG1;DEFA2;COLL1;TYVA02;FVAD3;PERF1;EXC2 | F34: -2351 | G34: EU1 | H34: CHRO1 | I34: ACUT2 | J34: GEO3 | K34: CNAEL6 | L34: NACE06030302
B35: 00411 | C35: 00000 | D35: BI00411 | E35: CONT1;HFS2;B01;MC02;ACPF6;SC0303;STAG3;DEFA1;COLL1;TYVA01;FVAD3;PERF2;EXC2;MESG5 | F35: 1556 | G35: EU1 | H35: CHRO1 | I35: ACUT2 | J35: GEO3 | K35: CNAEL3 | L35: NACE03010703
B36: 00411 | C36: 00000 | D36: BI00411 | E36: CONT1;HFS2;B01;MC02;ACPF6;SC0303;STAG2;DEFA2;COLL1;TYVA01;FVAD3;PERF1;EXC2;MESG2 | F36: 225187 | G36: EU1 | H36: CHRO2 | I36: ACUT2 | J36: GEO3 | K36: CNAEL10 | L36: NACE10020201 | M36: 7
B37: 00411 | C37: 00000 | D37: BI00411 | E37: CONT1;HFS2;B01;MC02;ACPF6;SC0303;STAG1;DEFA2;COLL1;TYVA01;FVAD3;PERF1;EXC2;MESG1 | F37: 5876887 | G37: EU1 | H37: CHRO2 | I37: ACUT2 | J37: GEO3 | K37: CNAEL8 | L37: NACE08040202 | M37: 2
B38: 00411 | C38: 00000 | D38: BI00411 | E38: CONT1;HFS2;B01;MC02;ACPF6;SC0303;STAG2;DEFA2;COLL4;TYVA02;FVAD3;PERF1;EXC2 | F38: -19629 | G38: EU1 | H38: CHRO2 | I38: ACUT2 | J38: GEO3 | K38: CNAEL9 | L38: NACE09010201
B39: 00411 | C39: 00000 | D39: BI00411 | E39: CONT1;HFS2;B01;MC02;ACPF6;SC0303;STAG1;DEFA2;COLL1;TYVA02;FVAD3;PERF1;EXC2 | F39: -16763 | G39: EU1 | H39: CHRO1 | I39: ACUT2 | J39: GEO3 | K39: CNAEL3 | L39: NACE03160803
B40: 00411 | C40: 00000 | D40: BI00411 | E40: CONT1;HFS2;B01;MC02;ACPF6;SC0303;STAG3;DEFA1;COLL1;TYVA01;FVAD3;PERF2;EXC2;MESG5 | F40: 3235 | G40: EU1 | H40: CHRO1 | I40: ACUT2 | J40: GEO3 | K40: CNAEL7 | L40: NACE07030203
B41: 00411 | C41: 00000 | D41: BI00411 | E41: CONT1;HFS2;B01;MC02;ACPF6;SC0303;STAG1;DEFA2;COLL1;TYVA01;FVAD3;PERF1;EXC2;MESG2 | F41: 834339 | G41: EU1 | H41: CHRO2 | I41: ACUT2 | J41: GEO3 | K41: CNAEL9 | L41: NACE09020301 | M41: 7
B42: 00411 | C42: 00000 | D42: BI00411 | E42: CONT1;HFS2;B01;MC02;ACPF6;SC0303;STAG2;DEFA2;COLL4;TYVA02;FVAD3;PERF1;EXC2 | F42: -8 | G42: EU1 | H42: CHRO2 | I42: ACUT2 | J42: GEO3 | K42: CNAEL12 | L42: NACE13040102
B43: 00411 | C43: 00000 | D43: BI00411 | E43: CONT1;HFS2;B01;MC02;ACPF6;SC0303;STAG1;DEFA2;COLL4;TYVA02;FVAD3;PERF1;EXC2 | F43: -1068 | G43: EU1 | H43: CHRO2 | I43: ACUT2 | J43: GEO3 | K43: CNAEL3 | L43: NACE03070101
B44: 00411 | C44: 00000 | D44: BI00411 | E44: CONT1;HFS2;B01;MC02;ACPF6;SC0303;STAG3;DEFA1;COLL4;TYVA01;FVAD3;PERF2;EXC2;MESG1 | F44: 56857 | G44: EU1 | H44: CHRO2 | I44: ACUT2 | J44: GEO3 | K44: CNAEL7 | L44: NACE07020703 | M44: 2
B45: 00411 | C45: 00000 | D45: BI00411 | E45: CONT1;HFS2;B01;MC02;ACPF6;SC0303;STAG2;DEFA2;COLL4;TYVA02;FVAD3;PERF1;EXC2 | F45: -659 | G45: EU1 | H45: CHRO2 | I45: ACUT2 | J45: GEO3 | K45: CNAEL13 | L45: NACE14050203
B46: 00411 | C46: 00000 | D46: BI00411 | E46: CONT1;HFS2;B01;MC02;ACPF6;SC0303;STAG1;DEFA2;COLL1;TYVA01;FVAD3;PERF1;EXC2;MESG1 | F46: 107275 | G46: EU1 | H46: CHRO2 | I46: ACUT1 | J46: GEO3 | K46: CNAEL7 | L46: NACE07010201 | M46: 1
B47: 00411 | C47: 00000 | D47: BI00411 | E47: CONT1;HFS2;B01;MC02;ACPF6;SC0303;STAG1;DEFA2;COLL1;TYVA01;FVAD3;PERF1;EXC2;MESG1 | F47: 9071036 | G47: EU1 | H47: CHRO2 | I47: ACUT2 | J47: GEO3 | K47: CNAEL7 | L47: NACE07020409 | M47: 2
B48: 00411 | C48: 00000 | D48: BI00411 | E48: CONT1;HFS2;B01;MC02;ACPF6;SC0303;STAG1;DEFA2;COLL1;TYVA02;FVAD3;PERF1;EXC2 | F48: -15271 | G48: EU1 | H48: CHRO1 | I48: ACUT2 | J48: GEO3 | K48: CNAEL3 | L48: NACE03010901
B49: 00411 | C49: 00000 | D49: BI00411 | E49: CONT1;HFS2;B01;MC02;ACPF6;SC0303;STAG1;DEFA2;COLL1;TYVA01;FVAD3;PERF1;EXC2;MESG5 | F49: 492 | G49: EU1 | H49: CHRO2 | I49: ACUT2 | J49: GEO6 | K49: CNAEL3 | L49: NACE03010303
B50: 00411 | C50: 00000 | D50: BI00411 | E50: CONT1;HFS2;B01;MC02;ACPF6;SC0303;STAG3;DEFA1;COLL4;TYVA02;FVAD3;PERF2;EXC2 | F50: -4164338 | G50: EU1 | H50: CHRO2 | I50: ACUT2 | J50: GEO3 | K50: CNAEL8 | L50: NACE08030101
B51: 00411 | C51: 00000 | D51: BI00411 | E51: CONT1;HFS2;B01;MC02;ACPF6;SC0303;STAG1;DEFA2;COLL1;TYVA02;FVAD3;PERF1;EXC2 | F51: -10716 | G51: EU1 | H51: CHRO2 | I51: ACUT2 | J51: GEO3 | K51: CNAEL7 | L51: NACE07030901
B52: 00411 | C52: 00000 | D52: BI00411 | E52: CONT1;HFS2;B01;MC02;ACPF6;SC0303;STAG1;DEFA2;COLL1;TYVA02;FVAD3;PERF1;EXC2 | F52: -1511 | G52: EU1 | H52: CHRO2 | I52: ACUT2 | J52: GEO3 | K52: CNAEL18 | L52: NACE12010101
B53: 00411 | C53: 00000 | D53: BI00411 | E53: CONT1;HFS2;B01;MC02;ACPF6;SC0303;STAG2;DEFA2;COLL1;TYVA02;FVAD3;PERF1;EXC2 | F53: -16770 | G53: EU1 | H53: CHRO2 | I53: ACUT2 | J53: GEO3 | K53: CNAEL3 | L53: NACE03070204
B54: 00411 | C54: 00000 | D54: BI00411 | E54: CONT1;HFS2;B01;MC02;ACPF6;SC0303;STAG1;DEFA2;COLL1;TYVA02;FVAD3;PERF1;EXC2 | F54: -100152 | G54: EU1 | H54: CHRO2 | I54: ACUT2 | J54: GEO3 | K54: CNAEL7 | L54: NACE07030703
B55: 00411 | C55: 00000 | D55: BI00411 | E55: CONT1;HFS2;B01;MC02;ACPF6;SC0303;STAG1;DEFA2;COLL1;TYVA01;FVAD3;PERF1;EXC2;MESG5 | F55: 4 | G55: EU1 | H55: CHRO2 | I55: ACUT2 | J55: GEO3 | K55: CNAEL18 | L55: NACE11010102
B56: 00411 | C56: 00000 | D56: BI00411 | E56: CONT1;HFS2;B01;MC02;ACPF6;SC0303;STAG3;DEFA1;COLL1;TYVA01;FVAD3;PERF2;EXC2;MESG1 | F56: 899076 | G56: EU1 | H56: CHRO1 | I56: ACUT2 | J56: GEO3 | K56: CNAEL3 | L56: NACE03160602 | M56: 3
B57: 00411 | C57: 00000 | D57: BI00411 | E57: CONT1;HFS2;B01;MC02;ACPF6;SC0303;STAG3;DEFA1;COLL1;TYVA02;FVAD3;PERF2;EXC2 | F57: -700 | G57: EU1 | H57: CHRO2 | I57: ACUT1 | J57: GEO3 | K57: CNAEL8 | L57: NACE08040205
B58: 00411 | C58: 00000 | D58: BI00411 | E58: CONT1;HFS2;B01;MC02;ACPF6;SC0303;STAG1;DEFA2;COLL1;TYVA01;FVAD3;PERF1;EXC2;MESG1 | F58: 1485459 | G58: EU1 | H58: CHRO2 | I58: ACUT2 | J58: GEO3 | K58: CNAEL3 | L58: NACE03160805 | M58: 3
B59: 00411 | C59: 00000 | D59: BI00411 | E59: CONT1;HFS2;B01;MC02;ACPF6;SC0303;STAG1;DEFA2;COLL1;TYVA02;FVAD3;PERF1;EXC2 | F59: -492 | G59: EU1 | H59: CHRO1 | I59: ACUT1 | J59: GEO3 | K59: CNAEL3 | L59: NACE03140102
B60: 00411 | C60: 00000 | D60: BI00411 | E60: CONT1;HFS2;B01;MC02;ACPF6;SC0303;STAG3;DEFA1;COLL1;TYVA02;FVAD3;PERF2;EXC2 | F60: -64755 | G60: EU1 | H60: CHRO2 | I60: ACUT2 | J60: GEO3 | K60: CNAEL3 | L60: NACE03220102
B61: 00411 | C61: 00000 | D61: BI00411 | E61: CONT1;HFS2;B01;MC02;ACPF6;SC0303;STAG1;DEFA2;COLL4;TYVA02;FVAD3;PERF1;EXC2 | F61: -504 | G61: EU1 | H61: CHRO2 | I61: ACUT2 | J61: GEO3 | K61: CNAEL13 | L61: NACE14010102
B62: 00411 | C62: 00000 | D62: BI00411 | E62: CONT1;HFS2;B01;MC02;ACPF6;SC0303;STAG1;DEFA2;COLL1;TYVA01;FVAD3;PERF1;EXC2;MESG2 | F62: 352046 | G62: EU1 | H62: CHRO2 | I62: ACUT2 | J62: GEO3 | K62: CNAEL7 | L62: NACE07020707 | M62: 6
B63: 00411 | C63: 00000 | D63: BI00411 | E63: CONT1;HFS2;B01;MC02;ACPF6;SC0303;STAG2;DEFA2;COLL1;TYVA02;FVAD3;PERF1;EXC2 | F63: -17096 | G63: EU1 | H63: CHRO2 | I63: ACUT2 | J63: GEO3 | K63: CNAEL7 | L63: NACE07020408
B64: 00411 | C64: 00000 | D64: BI00411 | E64: CONT1;HFS2;B01;MC02;ACPF6;SC0303;STAG1;DEFA2;COLL3;TYVA01;FVAD3;PERF1;EXC2;MESG1 | F64: 23728 | G64: EU1 | H64: CHRO2 | I64: ACUT2 | J64: GEO3 | K64: CNAEL6 | L64: NACE06030305 | M64: 5
B65: 00411 | C65: 00000 | D65: BI00411 | E65: CONT1;HFS2;B01;MC02;ACPF6;SC0303;STAG2;DEFA2;COLL1;TYVA02;FVAD3;PERF1;EXC2 | F65: -2369 | G65: EU1 | H65: CHRO2 | I65: ACUT2 | J65: GEO3 | K65: CNAEL3 | L65: NACE03210501
B66: 00411 | C66: 00000 | D66: BI00411 | E66: CONT1;HFS2;B01;MC02;ACPF6;SC0303;STAG2;DEFA2;COLL3;TYVA02;FVAD3;PERF1;EXC2 | F66: -793 | G66: EU1 | H66: CHRO2 | I66: ACUT2 | J66: GEO3 | K66: CNAEL7 | L66: NACE07030707
B67: 00411 | C67: 00000 | D67: BI00411 | E67: CONT1;HFS2;B01;MC04;ACPF6;SC0303;STAG1;DEFA2;COLL1;TYVA02;FVAD3;PERF1;EXC2 | F67: -13923 | G67: EU1 | H67: CHRO2 | I67: ACUT2 | J67: GEO3 | K67: CNAEL16 | L67: NACE17010202
B68: 00411 | C68: 00000 | D68: BI00411 | E68: CONT1;HFS2;B01;MC02;ACPF6;SC0303;STAG2;DEFA2;COLL3;TYVA01;FVAD3;PERF1;EXC2;MESG1 | F68: 127 | G68: EU1 | H68: CHRO2 | I68: ACUT2 | J68: GEO3 | K68: CNAEL5 | L68: NACE05030302 | M68: 0
B69: 00411 | C69: 00000 | D69: BI00411 | E69: CONT1;HFS2;B01;MC02;ACPF6;SC0303;STAG1;DEFA2;COLL1;TYVA01;FVAD3;PERF1;EXC2;MESG1 | F69: 267116 | G69: EU1 | H69: CHRO1 | I69: ACUT2 | J69: GEO3 | K69: CNAEL7 | L69: NACE07030205 | M69: 4
B70: 00411 | C70: 00000 | D70: BI00411 | E70: CONT1;HFS2;B01;MC02;ACPF6;SC0303;STAG1;DEFA2;COLL1;TYVA01;FVAD3;PERF1;EXC2;MESG5 | F70: 902845 | G70: EU1 | H70: CHRO2 | I70: ACUT2 | J70: GEO3 | K70: CNAEL6 | L70: NACE06020201
B71: 00411 | C71: 00000 | D71: BI00411 | E71: CONT1;HFS2;B01;MC02;ACPF6;SC0303;STAG1;DEFA2;COLL1;TYVA01;FVAD3;PERF1;EXC2;MESG1 | F71: 534 | G71: EU1 | H71: CHRO2 | I71: ACUT2 | J71: GEO3 | K71: CNAEL3 | L71: NACE03170102 | M71: 1
B72: 00411 | C72: 00000 | D72: BI00411 | E72: CONT1;HFS2;B01;MC02;ACPF6;SC0303;STAG1;DEFA2;COLL1;TYVA01;FVAD3;PERF1;EXC2;MESG3 | F72: 340967 | G72: EU1 | H72: CHRO2 | I72: ACUT2 | J72: GEO3 | K72: CNAEL16 | L72: NACE17020101 | M72: 16
B73: 00411 | C73: 00000 | D73: BI00411 | E73: CONT1;HFS2;B01;MC02;ACPF6;SC0303;STAG2;DEFA2;COLL3;TYVA01;FVAD3;PERF1;EXC2;MESG1 | F73: 130315 | G73: EU1 | H73: CHRO2 | I73: ACUT2 | J73: GEO3 | K73: CNAEL16 | L73: NACE17010203 | M73: 3
B74: 00411 | C74: 00000 | D74: BI00411 | E74: CONT1;HFS2;B01;MC02;ACPF6;SC0303;STAG1;DEFA2;COLL1;TYVA01;FVAD3;PERF1;EXC2;MESG1 | F74: 3787525 | G74: EU1 | H74: CHRO2 | I74: ACUT2 | J74: GEO3 | K74: CNAEL7 | L74: NACE07020203 | M74: 2
B75: 00411 | C75: 00000 | D75: BI00411 | E75: CONT1;HFS2;B01;MC02;ACPF6;SC0303;STAG3;DEFA1;COLL4;TYVA01;FVAD3;PERF2;EXC2;MESG1 | F75: 18999 | G75: EU1 | H75: CHRO2 | I75: ACUT2 | J75: GEO3 | K75: CNAEL3 | L75: NACE03070203 | M75: 0
B76: 00411 | C76: 00000 | D76: BI00411 | E76: CONT1;HFS2;B01;MC02;ACPF6;SC0303;STAG2;DEFA2;COLL4;TYVA01;FVAD3;PERF1;EXC2;MESG1 | F76: 56213 | G76: EU1 | H76: CHRO2 | I76: ACUT2 | J76: GEO3 | K76: CNAEL17 | L76: NACE18010102 | M76: 5
B77: 00411 | C77: 00000 | D77: BI00411 | E77: CONT1;HFS2;B01;MC02;ACPF6;SC0303;STAG2;DEFA2;COLL1;TYVA01;FVAD3;PERF1;EXC2;MESG2 | F77: 53131 | G77: EU1 | H77: CHRO2 | I77: ACUT2 | J77: GEO3 | K77: CNAEL7 | L77: NACE07020305 | M77: 6
B78: 00411 | C78: 00000 | D78: BI00411 | E78: CONT1;HFS2;B01;MC02;ACPF6;SC0303;STAG1;DEFA2;COLL1;TYVA01;FVAD3;PERF1;EXC2;MESG5 | F78: 2894 | G78: EU1 | H78: CHRO2 | I78: ACUT2 | J78: GEO3 | K78: CNAEL6 | L78: NACE06020103
B79: 00411 | C79: 00000 | D79: BI00411 | E79: CONT1;HFS2;B01;MC02;ACPF6;SC0303;STAG3;DEFA1;COLL1;TYVA01;FVAD3;PERF2;EXC2;MESG5 | F79: 99 | G79: EU1 | H79: CHRO2 | I79: ACUT1 | J79: GEO3 | K79: CNAEL3 | L79: NACE03240102
B80: 00411 | C80: 00000 | D80: BI00411 | E80: CONT1;HFS2;B01;MC02;ACPF6;SC0303;STAG2;DEFA2;COLL1;TYVA02;FVAD3;PERF1;EXC2 | F80: -121 | G80: EU1 | H80: CHRO2 | I80: ACUT2 | J80: GEO3 | K80: CNAEL3 | L80: NACE03140601
B81: 00411 | C81: 00000 | D81: BI00411 | E81: CONT1;HFS2;B01;MC02;ACPF6;SC0303;STAG1;DEFA2;COLL1;TYVA02;FVAD3;PERF1;EXC2 | F81: -1791 | G81: EU2 | H81: CHRO2 | I81: ACUT2 | J81: GEO8 | K81: CNAEL18 | L81: NACE21010101
B82: 00411 | C82: 00000 | D82: BI00411 | E82: CONT1;HFS2;B01;MC02;ACPF6;SC0303;STAG2;DEFA2;COLL4;TYVA01;FVAD3;PERF1;EXC2;MESG1 | F82: 564121 | G82: EU1 | H82: CHRO2 | I82: ACUT2 | J82: GEO3 | K82: CNAEL12 | L82: NACE13010101 | M82: 5
B83: 00411 | C83: 00000 | D83: BI00411 | E83: CONT1;HFS2;B01;MC02;ACPF6;SC0303;STAG3;DEFA1;COLL1;TYVA01;FVAD3;PERF2;EXC2;MESG5 | F83: 3234 | G83: EU1 | H83: CHRO2 | I83: ACUT2 | J83: GEO3 | K83: CNAEL3 | L83: NACE03180102
B84: 00411 | C84: 00000 | D84: BI00411 | E84: CONT1;HFS2;B01;MC02;ACPF6;SC0303;STAG1;DEFA2;COLL1;TYVA01;FVAD3;PERF1;EXC2;MESG5 | F84: 479536 | G84: EU1 | H84: CHRO1 | I84: ACUT2 | J84: GEO3 | K84: CNAEL1 | L84: NACE01010202
B85: 00411 | C85: 00000 | D85: BI00411 | E85: CONT1;HFS2;B01;MC02;ACPF6;SC0303;STAG1;DEFA2;COLL1;TYVA01;FVAD3;PERF1;EXC2;MESG1 | F85: 56856 | G85: EU1 | H85: CHRO2 | I85: ACUT2 | J85: GEO3 | K85: CNAEL2 | L85: NACE02040101 | M85: 1
B86: 00411 | C86: 00000 | D86: BI00411 | E86: CONT1;HFS2;B01;MC02;ACPF6;SC0303;STAG3;DEFA1;COLL1;TYVA01;FVAD3;PERF2;EXC2;MESG1 | F86: 26007 | G86: EU1 | H86: CHRO1 | I86: ACUT2 | J86: GEO3 | K86: CNAEL3 | L86: NACE03060101 | M86: 1
B87: 00411 | C87: 00000 | D87: BI00411 | E87: CONT1;HFS2;B01;MC02;ACPF6;SC0303;STAG1;DEFA2;COLL1;TYVA01;FVAD3;PERF1;EXC2;MESG5 | F87: 172076 | G87: EU1 | H87: CHRO1 | I87: ACUT2 | J87: GEO3 | K87: CNAEL6 | L87: NACE06030201
B88: 00411 | C88: 00000 | D88: BI00411 | E88: CONT1;HFS2;B01;MC02;ACPF6;SC0303;STAG2;DEFA2;COLL1;TYVA01;FVAD3;PERF1;EXC2;MESG5 | F88: 185709 | G88: EU1 | H88: CHRO1 | I88: ACUT2 | J88: GEO3 | K88: CNAEL7 | L88: NACE07030702
B89: 00411 | C89: 00000 | D89: BI00411 | E89: CONT1;HFS2;B01;MC02;ACPF6;SC0303;STAG3;DEFA1;COLL4;TYVA02;FVAD3;PERF2;EXC2 | F89: -39840 | G89: EU1 | H89: CHRO2 | I89: ACUT2 | J89: GEO3 | K89: CNAEL6 | L89: NACE06030304
B90: 00411 | C90: 00000 | D90: BI00411 | E90: CONT1;HFS2;B01;MC02;ACPF6;SC0303;STAG2;DEFA2;COLL1;TYVA01;FVAD3;PERF1;EXC2;MESG5 | F90: 641109 | G90: EU1 | H90: CHRO2 | I90: ACUT2 | J90: GEO3 | K90: CNAEL7 | L90: NACE07030202
B91: 00411 | C91: 00000 | D91: BI00411 | E91: CONT1;HFS2;B01;MC02;ACPF6;SC0303;STAG1;DEFA2;COLL1;TYVA02;FVAD3;PERF1;EXC2 | F91: -21178 | G91: EU1 | H91: CHRO2 | I91: ACUT2 | J91: GEO3 | K91: CNAEL7 | L91: NACE07020404
B92: 00411 | C92: 00000 | D92: BI00411 | E92: CONT1;HFS2;B01;MC02;ACPF6;SC0303;STAG1;DEFA2;COLL4;TYVA01;FVAD3;PERF1;EXC2;MESG1 | F92: 1005204 | G92: EU1 | H92: CHRO1 | I92: ACUT2 | J92: GEO3 | K92: CNAEL3 | L92: NACE03090102 | M92: 4
B93: 00411 | C93: 00000 | D93: BI00411 | E93: CONT1;HFS2;B01;MC02;ACPF6;SC0303;STAG3;DEFA1;COLL1;TYVA01;FVAD3;PERF2;EXC2;MESG5 | F93: 11125 | G93: EU1 | H93: CHRO2 | I93: ACUT2 | J93: GEO3 | K93: CNAEL3 | L93: NACE03140401
B94: 00411 | C94: 00000 | D94: BI00411 | E94: CONT1;HFS2;B01;MC02;ACPF6;SC0303;STAG2;DEFA2;COLL4;TYVA01;FVAD3;PERF1;EXC2;MESG1 | F94: 24459 | G94: EU1 | H94: CHRO1 | I94: ACUT2 | J94: GEO3 | K94: CNAEL7 | L94: NACE07030401 | M94: 5
B95: 00411 | C95: 00000 | D95: BI00411 | E95: CONT1;HFS2;B01;MC02;ACPF6;SC0303;STAG1;DEFA2;COLL3;TYVA01;FVAD3;PERF1;EXC2;MESG2 | F95: 1141563 | G95: EU1 | H95: CHRO2 | I95: ACUT2 | J95: GEO3 | K95: CNAEL3 | L95: NACE03010701 | M95: 7
B96: 00411 | C96: 00000 | D96: BI00411 | E96: CONT1;HFS2;B01;MC02;ACPF6;SC0303;STAG2;DEFA2;COLL4;TYVA01;FVAD3;PERF1;EXC2;MESG2 | F96: 16438 | G96: EU1 | H96: CHRO2 | I96: ACUT2 | J96: GEO3 | K96: CNAEL18 | L96: NACE19030102 | M96: 6
B97: 00411 | C97: 00000 | D97: BI00411 | E97: CONT1;HFS2;B01;MC02;ACPF6;SC0303;STAG1;DEFA2;COLL3;TYVA02;FVAD3;PERF1;EXC2 | F97: -665 | G97: EU1 | H97: CHRO2 | I97: ACUT2 | J97: GEO3 | K97: CNAEL10 | L97: NACE10030201
B98: 00411 | C98: 00000 | D98: BI00411 | E98: CONT1;HFS2;B01;MC02;ACPF6;SC0303;STAG3;DEFA1;COLL1;TYVA01;FVAD3;PERF2;EXC2;MESG1 | F98: 387382 | G98: EU1 | H98: CHRO1 | I98: ACUT2 | J98: GEO3 | K98: CNAEL3 | L98: NACE03050301 | M98: 2
B99: 00411 | C99: 00000 | D99: BI00411 | E99: CONT1;HFS2;B01;MC02;ACPF6;SC0303;STAG1;DEFA2;COLL1;TYVA01;FVAD3;PERF1;EXC2;MESG1 | F99: 164026 | G99: EU1 | H99: CHRO2 | I99: ACUT2 | J99: GEO3 | K99: CNAEL3 | L99: NACE03200301 | M99: 1
B100: 00411 | C100: 00000 | D100: BI00411 | E100: CONT1;HFS2;B01;MC02;ACPF6;SC0303;STAG1;DEFA2;COLL1;TYVA02;FVAD3;PERF1;EXC2 | F100: -1649 | G100: EU1 | H100: CHRO2 | I100: ACUT2 | J100: GEO3 | K100: CNAEL3 | L100: NACE03190104
B101: 00411 | C101: 00000 | D101: BI00411 | E101: CONT1;HFS2;B01;MC02;ACPF6;SC0303;STAG1;DEFA2;COLL1;TYVA01;FVAD3;PERF1;EXC2;MESG1 | F101: 18112078 | G101: EU1 | H101: CHRO2 | I101: ACUT2 | J101: GEO3 | K101: CNAEL7 | L101: NACE07030708 | M101: 3
B102: 00411 | C102: 00000 | D102: BI00411 | E102: CONT1;HFS2;B01;MC02;ACPF6;SC0303;STAG2;DEFA2;COLL1;TYVA01;FVAD3;PERF1;EXC2;MESG2 | F102: 258445 | G102: EU1 | H102: CHRO2 | I102: ACUT1 | J102: GEO3 | K102: CNAEL5 | L102: NACE05010101 | M102: 6
B103: 00411 | C103: 00000 | D103: BI00411 | E103: CONT1;HFS2;B01;MC02;ACPF6;SC0303;STAG3;DEFA1;COLL4;TYVA01;FVAD3;PERF2;EXC2;MESG1 | F103: 5445 | G103: EU1 | H103: CHRO2 | I103: ACUT2 | J103: GEO3 | K103: CNAEL15 | L103: NACE16010502 | M103: 1
B104: 00411 | C104: 00000 | D104: BI00411 | E104: CONT1;HFS2;B01;MC02;ACPF6;SC0303;STAG2;DEFA2;COLL1;TYVA02;FVAD3;PERF1;EXC2 | F104: -29733 | G104: EU1 | H104: CHRO1 | I104: ACUT2 | J104: GEO3 | K104: CNAEL3 | L104: NACE03130202
B105: 00411 | C105: 00000 | D105: BI00411 | E105: CONT1;HFS2;B01;MC02;ACPF6;SC0303;STAG3;DEFA1;COLL4;TYVA02;FVAD3;PERF2;EXC2 | F105: -161 | G105: EU1 | H105: CHRO2 | I105: ACUT2 | J105: GEO3 | K105: CNAEL3 | L105: NACE03240101
B106: 00411 | C106: 00000 | D106: BI00411 | E106: CONT1;HFS2;B01;MC02;ACPF6;SC0303;STAG1;DEFA2;COLL1;TYVA02;FVAD3;PERF1;EXC2 | F106: -720 | G106: EU1 | H106: CHRO1 | I106: ACUT2 | J106: GEO3 | K106: CNAEL6 | L106: NACE06030301
B107: 00411 | C107: 00000 | D107: BI00411 | E107: CONT1;HFS2;B01;MC02;ACPF6;SC0303;STAG1;DEFA2;COLL1;TYVA01;FVAD3;PERF1;EXC2;MESG5 | F107: 1293389 | G107: EU1 | H107: CHRO2 | I107: ACUT2 | J107: GEO3 | K107: CNAEL12 | L107: NACE13030101
...

Sheet Index
B6: 1. Variables and values for each table
C10: Variables | D10: Value | E10: Comments
C12: Main Sector | D12: SC0303 | E12: "Non financial corporations"
D13: SC0301 | E13: "General Government"
D14: SC0302 | E14: "Other financial Corporation"
D15: SC0304 | E15: "HouseHolds"
C16: Exposures | D16: TYVA01 | E16: "Gross carrying amount"
D17: TYVA02 | E17: "Imparment"
C18: Main Category | D18: MC08 | E18: "Investment sector"
D19: MC10 | E19: "Tangible assets"
C20: Sector | D20: INVS5 | E20: "Non Financial Corporations"
D21: INVS4 | E21: "Other Financial Corporations"
D22: INVS3 | E22: "General Governments"
C23: Stage | D23: STAG2 | E23: "Stage 2"
D24: STAG3 | E24: "Stage 3"
C25: Excluded | D25: EXC1 | E25: "Excluded for Paris Agreement"
C26: Maturity | D26: MESG1 | E26: <5y
D27: MESG2 | E27: >5y & <10y
D28: MESG3 | E28: >10y & <20y
D29: MESG4 | E29: >20y
D30: MESG5 | E30: "Counterparty having the choice of the repayment date"
D31: MESG6 | E31: "Other contracts with no stated maturity"
D32: MESG | E32: No maturity (Provisions)
C33: Chronic Changes | D33: CHRO1 | E33: "Yes"
D34: CHRO2 | E34: "No"
C35: Acute Changes | D35: ACUT1 | E35: "Yes"
D36: ACUT2 | E36: "No"
B38: 2. Formulas for each table
C41: 1.Credit Quality by sector
C43: Total Gross Carrying Amount = ( NACE | SC030(1-4) | TYVA01) + ( NACE | INVS(3-5) | TYVA01 | MC05)
C44: Of which STAGE2 = ( NACE | SC030(1-4) | TYVA01 | STAG2) + ( NACE | INVS(3-5) | TYVA01 | MC05 | STAG2)
C45: Of which STAGE32 = ( NACE | SC030(1-4) | TYVA01 | STAG3) + ( NACE | INVS(3-5) | TYVA01 | MC05 | STAG3)
C46: Acumulated Impairment = ( NACE | SC030(1-4) | TYVA02) + ( NACE | INVS(3-5) | TYVA02 | MC05)
C47: Net Carrying Amount = ( NACE | SC030(1-4)) + ( NACE | INVS(3-5) | MC05)
C50: 2.Exposures of Corp excl_P
C52: Total GCA = ( NACE | SC030(1-4)) + ( NACE | INVS(3-5) | MC05)
C53: Of which excluded from Paris agreement = ( NACE | SC030(1-4) | EXC1) + ( NACE | INVS(3-5) | MC05 | EXC1)
C56: 3.Net Carrying Amt by Maturity
C58: Total net carrying amount = MESG(1-6)
C59: Prone to the impact of chronic climate change events = (MESG(1-6) | CHRO1)
... C68: Net Carrying Amount = ( NACE | SC030(1-4)) + ( NACE | INVS(3-5) | MC05)

Sheet 1. Credit Quality by sector
B8: Credit quality of exposures by sector
B9: Gross Carrying Amount and Accumulated impairment by NACE
B11: Sector | C11: ID | D11: Activity Sector Description | E11: Total Gross Carrying Amount | I11: Of which STAGE1 | M11: Of which STAGE2 | Q11: Of which STAGE3 | U11: Accumulated impairment | Y11: Net Carrying Amount
A12: at | B12: NFC | E12: Satélite Dez24 pós ajustes corp. | F12: Satélite Jun24 pós ajustes corp. | G12: ∆ | H12: ∆ (%) | I12: Satélite Dez24 pós ajustes corp. | J12: Satélite Jun24 pós ajustes corp. | K12: ∆ | L12: ∆ (%) | M12: Satélite Dez24 pós ajustes corp. | N12: Satélite Jun24 pós ajustes corp. | O12: ∆ | P12: ∆ (%) | Q12: Satélite Dez24 pós ajustes corp. | R12: Satélite Jun24 pós ajustes corp. | S12: ∆ | T12: ∆ (%) | U12: Satélite Dez24 pós ajustes corp. | V12: Satélite Jun24 pós ajustes corp. | W12: ∆ | X12: ∆ (%) | Y12: Satélite Dez24 pós ajustes corp. | Z12: Satélite Jun24 pós ajustes corp. | AA12: ∆ | AB12: ∆ (%)
A13: =+LEN(C13) -> 6 | B13: Non Financial Corporations | C13: NACE01 | D13: Agriculture, forestry and fishing | E13: =SUMIFS(#REF!,#REF!,"*" & C13 & "*",#REF!,"*" & Index!$D$12 & "*",#REF!,"*" & Index!$D$16 & "*")+SUMIFS(#REF!,#REF!,"*" & C13 & "*",#REF!,"*" & Index!$D$18 & "*",#REF!,"*" & Index!$D$20 & "*",#REF!,"*" & Index!$D$16 & "*") -> #REF! | F13: 337406183 | G13: =+E13-F13 -> #REF! | H13: =IFERROR(IF(((E13/F13)-1)=0,"-",((E13/F13)-1)),"-") -> - | I13: =+E13-M13-Q13 -> #REF! | J13: 288117379 | K13: =+I13-J13 -> #REF! | L13: =IFERROR(IF(((I13/J13)-1)=0,"-",((I13/J13)-1)),"-") -> - | M13: =SUMIFS(#REF!,#REF!,"*" & $C13 & "*",#REF!,"*" & Index!$D$12 & "*",#REF!,"*" & Index!$D$23 & "*",#REF!,"*" & Index!$D$16 & "*") + SUMIFS(#REF!,#REF!,"*" & $C13 & "*",#REF!,"*" & Index!$D$18 & "*",#REF!,"*" & Index!$D$23 & "*",#REF!,"*" & Index!$D$16 & "*",#REF!,"*" & Index!$D$20 & "*") -> #REF! | N13: 43312234 | O13: =+M13-N13 -> #REF! | P13: =IFERROR(IF(((M13/N13)-1)=0,"-",((M13/N13)-1)),"-") -> - | Q13: =SUMIFS(#REF!,#REF!,"*" & $C13 & "*",#REF!,"*" & Index!$D$12 & "*",#REF!,"*" & Index!$D$24 & "*",#REF!,"*" & Index!$D$16 & "*") + SUMIFS(#REF!,#REF!,"*" & $C13 & "*",#REF!,"*" & Index!$D$18 & "*",#REF!,"*" & Index!$D$24 & "*",#REF!,"*" & Index!$D$16 & "*",#REF!,"*" & Index!$D$20 & "*") -> #REF! | R13: 5976570 | S13: =+Q13-R13 -> #REF! | T13: =IFERROR(IF(((Q13/R13)-1)=0,"-",((Q13/R13)-1)),"-") -> - | U13: =SUMIFS(#REF!,#REF!,"*" & C13 &"*",#REF!,"*" & Index!$D$12 & "*",#REF!,"*" & Index!$D$17 & "*")+SUMIFS(#REF!,#REF!,"*" & C13 &"*",#REF!,"*" & Index!$D$18 & "*",#REF!,"*" & Index!$D$17 & "*",#REF!,"*" & Index!$D$20 & "*") -> #REF! | V13: -7176720 | W13: =+U13-V13 -> #REF! | X13: =IFERROR(IF(((U13/V13)-1)=0,"-",((U13/V13)-1)),"-") -> - | Y13: =SUMIFS(#REF!,#REF!,"*" & C13 & "*",#REF!,"*" & Index!$D$12 & "*")+ SUMIFS(#REF!,#REF!,"*" & C13 & "*",#REF!,"*" & Index!$D$18 & "*",#REF!,"*" & Index!$D$20 & "*") -> #REF! | Z13: 330229463 | AA13: =+Y13-Z13 -> #REF! | AB13: =IFERROR(IF(((Y13/Z13)-1)=0,"-",((Y13/Z13)-1)),"-") -> -
A14: =+LEN(C14) -> 8 | C14: NACE0101 | E14: =SUMIFS(#REF!,#REF!,"*" & C14 & "*",#REF!,"*" & Index!$D$12 & "*",#REF!,"*" & Index!$D$16 & "*")+SUMIFS(#REF!,#REF!,"*" & C14 & "*",#REF!,"*" & Index!$D$18 & "*",#REF!,"*" & Index!$D$20 & "*") -> #REF! | F14: 293599318 | G14: =+E14-F14 -> #REF! | H14: =IFERROR(IF(((E14/F14)-1)=0,"-",((E14/F14)-1)),"-") -> - | I14: =+E14-M14-Q14 -> #REF! | J14: 255451113 | K14: =+I14-J14 -> #REF! | L14: =IFERROR(IF(((I14/J14)-1)=0,"-",((I14/J14)-1)),"-") -> - | M14: =SUMIFS(#REF!,#REF!,"*" & $C14 & "*",#REF!,"*" & Index!$D$12 & "*",#REF!,"*" & Index!$D$23 & "*",#REF!,"*" & Index!$D$16 & "*") + SUMIFS(#REF!,#REF!,"*" & $C14 & "*",#REF!,"*" & Index!$D$18 & "*",#REF!,"*" & Index!$D$23 & "*",#REF!,"*" & Index!$D$16 & "*",#REF!,"*" & Index!$D$20 & "*") -> #REF! | N14: 33492977 | O14: =+M14-N14 -> #REF! | P14: =IFERROR(IF(((M14/N14)-1)=0,"-",((M14/N14)-1)),"-") -> - | Q14: =SUMIFS(#REF!,#REF!,"*" & $C14 & "*",#REF!,"*" & Index!$D$12 & "*",#REF!,"*" & Index!$D$24 & "*",#REF!,"*" & Index!$D$16 & "*") + SUMIFS(#REF!,#REF!,"*" & $C14 & "*",#REF!,"*" & Index!$D$18 & "*",#REF!,"*" & Index!$D$24 & "*",#REF!,"*" & Index!$D$16 & "*",#REF!,"*" & Index!$D$20 & "*") -> #REF! | R14: 4655228 | S14: =+Q14-R14 -> #REF! | T14: =IFERROR(IF(((Q14/R14)-1)=0,"-",((Q14/R14)-1)),"-") -> - | U14: =SUMIFS(#REF!,#REF!,"*" & C14 &"*",#REF!,"*" & Index!$D$12 & "*",#REF!,"*" & Index!$D$17 & "*")+SUMIFS(#REF!,#REF!,"*" & C14 &"*",#REF!,"*" & Index!$D$18 & "*",#REF!,"*" & Index!$D$17 & "*",#REF!,"*" & Index!$D$20 & "*") -> #REF! | V14: -5515592 | W14: =+U14-V14 -> #REF! | X14: =IFERROR(IF(((U14/V14)-1)=0,"-",((U14/V14)-1)),"-") -> - | Y14: =SUMIFS(#REF!,#REF!,"*" & C14 & "*",#REF!,"*" & Index!$D$12 & "*")+ SUMIFS(#REF!,#REF!,"*" & C14 & "*",#REF!,"*" & Index!$D$18 & "*",#REF!,"*" & Index!$D$20 & "*") -> #REF! | Z14: 288083726 | AA14: =+Y14-Z14 -> #REF! | AB14: =IFERROR(IF(((Y14/Z14)-1)=0,"-",((Y14/Z14)-1)),"-") -> -
A15: =+LEN(C15) -> 8 | C15: NACE0102 | E15: =SUMIFS(#REF!,#REF!,"*" & C15 & "*",#REF!,"*" & Index!$D$12 & "*",#REF!,"*" & Index!$D$16 & "*")+SUMIFS(#REF!,#REF!,"*" & C15 & "*",#REF!,"*" & Index!$D$18 & "*",#REF!,"*" & Index!$D$20 & "*") -> #REF! | F15: 39060709 | G15: =+E15-F15 -> #REF! | H15: =IFERROR(IF(((E15/F15)-1)=0,"-",((E15/F15)-1)),"-") -> - | I15: =+E15-M15-Q15 -> #REF! | J15: 28922963 | K15: =+I15-J15 -> #REF! | L15: =IFERROR(IF(((I15/J15)-1)=0,"-",((I15/J15)-1)),"-") -> - | M15: =SUMIFS(#REF!,#REF!,"*" & $C15 & "*",#REF!,"*" & Index!$D$12 & "*",#REF!,"*" & Index!$D$23 & "*",#REF!,"*" & Index!$D$16 & "*") + SUMIFS(#REF!,#REF!,"*" & $C15 & "*",#REF!,"*" & Index!$D$18 & "*",#REF!,"*" & Index!$D$23 & "*",#REF!,"*" & Index!$D$16 & "*",#REF!,"*" & Index!$D$20 & "*") -> #REF! | N15: 8881956 | O15: =+M15-N15 -> #REF! | P15: =IFERROR(IF(((M15/N15)-1)=0,"-",((M15/N15)-1)),"-") -> - | Q15: =SUMIFS(#REF!,#REF!,"*" & $C15 & "*",#REF!,"*" & Index!$D$12 & "*",#REF!,"*" & Index!$D$24 & "*",#REF!,"*" & Index!$D$16 & "*") + SUMIFS(#REF!,#REF!,"*" & $C15 & "*",#REF!,"*" & Index!$D$18 & "*",#REF!,"*" & Index!$D$24 & "*",#REF!,"*" & Index!$D$16 & "*",#REF!,"*" & Index!$D$20 & "*") -> #REF! | R15: 1255790 | S15: =+Q15-R15 -> #REF! | T15: =IFERROR(IF(((Q15/R15)-1)=0,"-",((Q15/R15)-1)),"-") -> - | U15: =SUMIFS(#REF!,#REF!,"*" & C15 &"*",#REF!,"*" & Index!$D$12 & "*",#REF!,"*" & Index!$D$17 & "*")+SUMIFS(#REF!,#REF!,"*" & C15 &"*",#REF!,"*" & Index!$D$18 & "*",#REF!,"*" & Index!$D$17 & "*",#REF!,"*" & Index!$D$20 & "*") -> #REF! | V15: -1572407 | W15: =+U15-V15 -> #REF! | X15: =IFERROR(IF(((U15/V15)-1)=0,"-",((U15/V15)-1)),"-") -> - | Y15: =SUMIFS(#REF!,#REF!,"*" & C15 & "*",#REF!,"*" & Index!$D$12 & "*")+ SUMIFS(#REF!,#REF!,"*" & C15 & "*",#REF!,"*" & Index!$D$18 & "*",#REF!,"*" & Index!$D$20 & "*") -> #REF! | Z15: 37488302 | AA15: =+Y15-Z15 -> #REF! | AB15: =IFERROR(IF(((Y15/Z15)-1)=0,"-",((Y15/Z15)-1)),"-") -> -
A16: =+LEN(C16) -> 8 | C16: NACE0103 | E16: =SUMIFS(#REF!,#REF!,"*" & C16 & "*",#REF!,"*" & Index!$D$12 & "*",#REF!,"*" & Index!$D$16 & "*")+SUMIFS(#REF!,#REF!,"*" & C16 & "*",#REF!,"*" & Index!$D$18 & "*",#REF!,"*" & Index!$D$20 & "*") -> #REF! | F16: 4746156 | G16: =+E16-F16 -> #REF! | H16: =IFERROR(IF(((E16/F16)-1)=0,"-",((E16/F16)-1)),"-") -> - | I16: =+E16-M16-Q16 -> #REF! | J16: 3743303 | K16: =+I16-J16 -> #REF! | L16: =IFERROR(IF(((I16/J16)-1)=0,"-",((I16/J16)-1)),"-") -> - | M16: =SUMIFS(#REF!,#REF!,"*" & $C16 & "*",#REF!,"*" & Index!$D$12 & "*",#REF!,"*" & Index!$D$23 & "*",#REF!,"*" & Index!$D$16 & "*") + SUMIFS(#REF!,#REF!,"*" & $C16 & "*",#REF!,"*" & Index!$D$18 & "*",#REF!,"*" & Index!$D$23 & "*",#REF!,"*" & Index!$D$16 & "*",#REF!,"*" & Index!$D$20 & "*") -> #REF! | N16: 937301 | O16: =+M16-N16 -> #REF! | P16: =IFERROR(IF(((M16/N16)-1)=0,"-",((M16/N16)-1)),"-") -> - | Q16: =SUMIFS(#REF!,#REF!,"*" & $C16 & "*",#REF!,"*" & Index!$D$12 & "*",#REF!,"*" & Index!$D$24 & "*",#REF!,"*" & Index!$D$16 & "*") + SUMIFS(#REF!,#REF!,"*" & $C16 & "*",#REF!,"*" & Index!$D$18 & "*",#REF!,"*" & Index!$D$24 & "*",#REF!,"*" & Index!$D$16 & "*",#REF!,"*" & Index!$D$20 & "*") -> #REF! | R16: 65552 | S16: =+Q16-R16 -> #REF! | T16: =IFERROR(IF(((Q16/R16)-1)=0,"-",((Q16/R16)-1)),"-") -> - | U16: =SUMIFS(#REF!,#REF!,"*" & C16 &"*",#REF!,"*" & Index!$D$12 & "*",#REF!,"*" & Index!$D$17 & "*")+SUMIFS(#REF!,#REF!,"*" & C16 &"*",#REF!,"*" & Index!$D$18 & "*",#REF!,"*" & Index!$D$17 & "*",#REF!,"*" & Index!$D$20 & "*") -> #REF! | V16: -88721 | W16: =+U16-V16 -> #REF! | X16: =IFERROR(IF(((U16/V16)-1)=0,"-",((U16/V16)-1)),"-") -> - | Y16: =SUMIFS(#REF!,#REF!,"*" & C16 & "*",#REF!,"*" & Index!$D$12 & "*")+ SUMIFS(#REF!,#REF!,"*" & C16 & "*",#REF!,"*" & Index!$D$18 & "*",#REF!,"*" & Index!$D$20 & "*") -> #REF! | Z16: 4657435 | AA16: =+Y16-Z16 -> #REF! | AB16: =IFERROR(IF(((Y16/Z16)-1)=0,"-",((Y16/Z16)-1)),"-") -> -
A17: =+LEN(C17) -> 6 | C17: NACE02 | D17: Mining and quarrying | E17: =SUMIFS(#REF!,#REF!,"*" & C17 & "*",#REF!,"*" & Index!$D$12 & "*",#REF!,"*" & Index!$D$16 & "*")+SUMIFS(#REF!,#REF!,"*" & C17 & "*",#REF!,"*" & Index!$D$18 & "*",#REF!,"*" & Index!$D$20 & "*",#REF!,"*" & Index!$D$16 & "*") -> #REF! | F17: 13442698 | G17: =+E17-F17 -> #REF! | H17: =IFERROR(IF(((E17/F17)-1)=0,"-",((E17/F17)-1)),"-") -> - | I17: =+E17-M17-Q17 -> #REF! | J17: 9513074 | K17: =+I17-J17 -> #REF! | L17: =IFERROR(IF(((I17/J17)-1)=0,"-",((I17/J17)-1)),"-") -> - | M17: =SUMIFS(#REF!,#REF!,"*" & $C17 & "*",#REF!,"*" & Index!$D$12 & "*",#REF!,"*" & Index!$D$23 & "*",#REF!,"*" & Index!$D$16 & "*") + SUMIFS(#REF!,#REF!,"*" & $C17 & "*",#REF!,"*" & Index!$D$18 & "*",#REF!,"*" & Index!$D$23 & "*",#REF!,"*" & Index!$D$16 & "*",#REF!,"*" & Index!$D$20 & "*") -> #REF! | N17: 2376255 | O17: =+M17-N17 -> #REF! | P17: =IFERROR(IF(((M17/N17)-1)=0,"-",((M17/N17)-1)),"-") -> - | Q17: =SUMIFS(#REF!,#REF!,"*" & $C17 & "*",#REF!,"*" & Index!$D$12 & "*",#REF!,"*" & Index!$D$24 & "*",#REF!,"*" & Index!$D$16 & "*") + SUMIFS(#REF!,#REF!,"*" & $C17 & "*",#REF!,"*" & Index!$D$18 & "*",#REF!,"*" & Index!$D$24 & "*",#REF!,"*" & Index!$D$16 & "*",#REF!,"*" & Index!$D$20 & "*") -> #REF! | R17: 1553369 | S17: =+Q17-R17 -> #REF! | T17: =IFERROR(IF(((Q17/R17)-1)=0,"-",((Q17/R17)-1)),"-") -> - | U17: =SUMIFS(#REF!,#REF!,"*" & C17 &"*",#REF!,"*" & Index!$D$12 & "*",#REF!,"*" & Index!$D$17 & "*")+SUMIFS(#REF!,#REF!,"*" & C17 &"*",#REF!,"*" & Index!$D$18 & "*",#REF!,"*" & Index!$D$17 & "*",#REF!,"*" & Index!$D$20 & "*") -> #REF! | V17: -1152150 | W17: =+U17-V17 -> #REF! | X17: =IFERROR(IF(((U17/V17)-1)=0,"-",((U17/V17)-1)),"-") -> - | Y17: =SUMIFS(#REF!,#REF!,"*" & C17 & "*",#REF!,"*" & Index!$D$12 & "*")+ SUMIFS(#REF!,#REF!,"*" & C17 & "*",#REF!,"*" & Index!$D$18 & "*",#REF!,"*" & Index!$D$20 & "*") -> #REF! | Z17: 12290548 | AA17: =+Y17-Z17 -> #REF! | AB17: =IFERROR(IF(((Y17/Z17)-1)=0,"-",((Y17/Z17)-1)),"-") -> -
A18: =+LEN(C18) -> 8 | C18: NACE0203 | E18: =SUMIFS(#REF!,#REF!,"*" & C18 & "*",#REF!,"*" & Index!$D$12 & "*",#REF!,"*" & Index!$D$16 & "*")+SUMIFS(#REF!,#REF!,"*" & C18 & "*",#REF!,"*" & Index!$D$18 & "*",#REF!,"*" & Index!$D$20 & "*") -> #REF! | F18: 91384 | G18: =+E18-F18 -> #REF! | H18: =IFERROR(IF(((E18/F18)-1)=0,"-",((E18/F18)-1)),"-") -> - | I18: =+E18-M18-Q18 -> #REF! | J18: 91384 | K18: =+I18-J18 -> #REF! | L18: =IFERROR(IF(((I18/J18)-1)=0,"-",((I18/J18)-1)),"-") -> - | M18: =SUMIFS(#REF!,#REF!,"*" & $C18 & "*",#REF!,"*" & Index!$D$12 & "*",#REF!,"*" & Index!$D$23 & "*",#REF!,"*" & Index!$D$16 & "*") + SUMIFS(#REF!,#REF!,"*" & $C18 & "*",#REF!,"*" & Index!$D$18 & "*",#REF!,"*" & Index!$D$23 & "*",#REF!,"*" & Index!$D$16 & "*",#REF!,"*" & Index!$D$20 & "*") -> #REF! | N18: 0 | O18: =+M18-N18 -> #REF! | P18: =IFERROR(IF(((M18/N18)-1)=0,"-",((M18/N18)-1)),"-") -> - | Q18: =SUMIFS(#REF!,#REF!,"*" & $C18 & "*",#REF!,"*" & Index!$D$12 & "*",#REF!,"*" & Index!$D$24 & "*",#REF!,"*" & Index!$D$16 & "*") + SUMIFS(#REF!,#REF!,"*" & $C18 & "*",#REF!,"*" & Index!$D$18 & "*",#REF!,"*" & Index!$D$24 & "*",#REF!,"*" & Index!$D$16 & "*",#REF!,"*" & Index!$D$20 & "*") -> #REF! | R18: 0 | S18: =+Q18-R18 -> #REF! | T18: =IFERROR(IF(((Q18/R18)-1)=0,"-",((Q18/R18)-1)),"-") -> - | U18: =SUMIFS(#REF!,#REF!,"*" & C18 &"*",#REF!,"*" & Index!$D$12 & "*",#REF!,"*" & Index!$D$17 & "*")+SUMIFS(#REF!,#REF!,"*" & C18 &"*",#REF!,"*" & Index!$D$18 & "*",#REF!,"*" & Index!$D$17 & "*",#REF!,"*" & Index!$D$20 & "*") -> #REF! | V18: -167 | W18: =+U18-V18 -> #REF! | X18: =IFERROR(IF(((U18/V18)-1)=0,"-",((U18/V18)-1)),"-") -> - | Y18: =SUMIFS(#REF!,#REF!,"*" & C18 & "*",#REF!,"*" & Index!$D$12 & "*")+ SUMIFS(#REF!,#REF!,"*" & C18 & "*",#REF!,"*" & Index!$D$18 & "*",#REF!,"*" & Index!$D$20 & "*") -> #REF! | Z18: 91217 | AA18: =+Y18-Z18 -> #REF! | AB18: =IFERROR(IF(((Y18/Z18)-1)=0,"-",((Y18/Z18)-1)),"-") -> -
A19: =+LEN(C19) -> 8 | C19: NACE0204 | E19: =SUMIFS(#REF!,#REF!,"*" & C19 & "*",#REF!,"*" & Index!$D$12 & "*",#REF!,"*" & Index!$D$16 & "*")+SUMIFS(#REF!,#REF!,"*" & C19 & "*",#REF!,"*" & Index!$D$18 & "*",#REF!,"*" & Index!$D$20 & "*") -> #REF! | F19: 13254285 | G19: =+E19-F19 -> #REF! | H19: =IFERROR(IF(((E19/F19)-1)=0,"-",((E19/F19)-1)),"-") -> - | I19: =+E19-M19-Q19 -> #REF! | J19: 9421682 | K19: =+I19-J19 -> #REF! | L19: =IFERROR(IF(((I19/J19)-1)=0,"-",((I19/J19)-1)),"-") -> - | M19: =SUMIFS(#REF!,#REF!,"*" & $C19 & "*",#REF!,"*" & Index!$D$12 & "*",#REF!,"*" & Index!$D$23 & "*",#REF!,"*" & Index!$D$16 & "*") + SUMIFS(#REF!,#REF!,"*" & $C19 & "*",#REF!,"*" & Index!$D$18 & "*",#REF!,"*" & Index!$D$23 & "*",#REF!,"*" & Index!$D$16 & "*",#REF!,"*" & Index!$D$20 & "*") -> #REF! | N19: 2279614 | O19: =+M19-N19 -> #REF! | P19: =IFERROR(IF(((M19/N19)-1)=0,"-",((M19/N19)-1)),"-") -> - | Q19: =SUMIFS(#REF!,#REF!,"*" & $C19 & "*",#REF!,"*" & Index!$D$12 & "*",#REF!,"*" & Index!$D$24 & "*",#REF!,"*" & Index!$D$16 & "*") + SUMIFS(#REF!,#REF!,"*" & $C19 & "*",#REF!,"*" & Index!$D$18 & "*",#REF!,"*" & Index!$D$24 & "*",#REF!,"*" & Index!$D$16 & "*",#REF!,"*" & Index!$D$20 & "*") -> #REF! | R19: 1552989 | S19: =+Q19-R19 -> #REF! | T19: =IFERROR(IF(((Q19/R19)-1)=0,"-",((Q19/R19)-1)),"-") -> - | U19: =SUMIFS(#REF!,#REF!,"*" & C19 &"*",#REF!,"*" & Index!$D$12 & "*",#REF!,"*" & Index!$D$17 & "*")+SUMIFS(#REF!,#REF!,"*" & C19 &"*",#REF!,"*" & Index!$D$18 & "*",#REF!,"*" & Index!$D$17 & "*",#REF!,"*" & Index!$D$20 & "*") -> #REF! | V19: -1150072 | W19: =+U19-V19 -> #REF! | X19: =IFERROR(IF(((U19/V19)-1)=0,"-",((U19/V19)-1)),"-") -> - | Y19: =SUMIFS(#REF!,#REF!,"*" & C19 & "*",#REF!,"*" & Index!$D$12 & "*")+ SUMIFS(#REF!,#REF!,"*" & C19 & "*",#REF!,"*" & Index!$D$18 & "*",#REF!,"*" & Index!$D$20 & "*") -> #REF! | Z19: 12104213 | AA19: =+Y19-Z19 -> #REF! | AB19: =IFERROR(IF(((Y19/Z19)-1)=0,"-",((Y19/Z19)-1)),"-") -> -
A20: =+LEN(C20) -> 8 | C20: NACE0205 | E20: =SUMIFS(#REF!,#REF!,"*" & C20 & "*",#REF!,"*" & Index!$D$12 & "*",#REF!,"*" & Index!$D$16 & "*")+SUMIFS(#REF!,#REF!,"*" & C20 & "*",#REF!,"*" & Index!$D$18 & "*",#REF!,"*" & Index!$D$20 & "*") -> #REF! | F20: 97029 | G20: =+E20-F20 -> #REF! | H20: =IFERROR(IF(((E20/F20)-1)=0,"-",((E20/F20)-1)),"-") -> - | I20: =+E20-M20-Q20 -> #REF! | J20: 8 | K20: =+I20-J20 -> #REF! | L20: =IFERROR(IF(((I20/J20)-1)=0,"-",((I20/J20)-1)),"-") -> - | M20: =SUMIFS(#REF!,#REF!,"*" & $C20 & "*",#REF!,"*" & Index!$D$12 & "*",#REF!,"*" & Index!$D$23 & "*",#REF!,"*" & Index!$D$16 & "*") + SUMIFS(#REF!,#REF!,"*" & $C20 & "*",#REF!,"*" & Index!$D$18 & "*",#REF!,"*" & Index!$D$23 & "*",#REF!,"*" & Index!$D$16 & "*",#REF!,"*" & Index!$D$20 & "*") -> #REF! | N20: 96641 | O20: =+M20-N20 -> #REF! | P20: =IFERROR(IF(((M20/N20)-1)=0,"-",((M20/N20)-1)),"-") -> - | Q20: =SUMIFS(#REF!,#REF!,"*" & $C20 & "*",#REF!,"*" & Index!$D$12 & "*",#REF!,"*" & Index!$D$24 & "*",#REF!,"*" & Index!$D$16 & "*") + SUMIFS(#REF!,#REF!,"*" & $C20 & "*",#REF!,"*" & Index!$D$18 & "*",#REF!,"*" & Index!$D$24 & "*",#REF!,"*" & Index!$D$16 & "*",#REF!,"*" & Index!$D$20 & "*") -> #REF! | R20: 380 | S20: =+Q20-R20 -> #REF! | T20: =IFERROR(IF(((Q20/R20)-1)=0,"-",((Q20/R20)-1)),"-") -> - | U20: =SUMIFS(#REF!,#REF!,"*" & C20 &"*",#REF!,"*" & Index!$D$12 & "*",#REF!,"*" & Index!$D$17 & "*")+SUMIFS(#REF!,#REF!,"*" & C20 &"*",#REF!,"*" & Index!$D$18 & "*",#REF!,"*" & Index!$D$17 & "*",#REF!,"*" & Index!$D$20 & "*") -> #REF! | V20: -1911 | W20: =+U20-V20 -> #REF! | X20: =IFERROR(IF(((U20/V20)-1)=0,"-",((U20/V20)-1)),"-") -> - | Y20: =SUMIFS(#REF!,#REF!,"*" & C20 & "*",#REF!,"*" & Index!$D$12 & "*")+ SUMIFS(#REF!,#REF!,"*" & C20 & "*",#REF!,"*" & Index!$D$18 & "*",#REF!,"*" & Index!$D$20 & "*") -> #REF! | Z20: 95118 | AA20: =+Y20-Z20 -> #REF! | AB20: =IFERROR(IF(((Y20/Z20)-1)=0,"-",((Y20/Z20)-1)),"-") -> -
A21: =+LEN(C21) -> 6 | C21: NACE03 | D21: Manufacturing | E21: =SUMIFS(#REF!,#REF!,"*" & C21 & "*",#REF!,"*" & Index!$D$12 & "*",#REF!,"*" & Index!$D$16 & "*")+SUMIFS(#REF!,#REF!,"*" & C21 & "*",#REF!,"*" & Index!$D$18 & "*",#REF!,"*" & Index!$D$20 & "*",#REF!,"*" & Index!$D$16 & "*") -> #REF! | F21: 2524539509 | G21: =+E21-F21 -> #REF! | H21: =IFERROR(IF(((E21/F21)-1)=0,"-",((E21/F21)-1)),"-") -> - | I21: =+E21-M21-Q21 -> #REF! | J21: 2226715100 | K21: =+I21-J21 -> #REF! | L21: =IFERROR(IF(((I21/J21)-1)=0,"-",((I21/J21)-1)),"-") -> - | M21: =SUMIFS(#REF!,#REF!,"*" & $C21 & "*",#REF!,"*" & Index!$D$12 & "*",#REF!,"*" & Index!$D$23 & "*",#REF!,"*" & Index!$D$16 & "*") + SUMIFS(#REF!,#REF!,"*" & $C21 & "*",#REF!,"*" & Index!$D$18 & "*",#REF!,"*" & Index!$D$23 & "*",#REF!,"*" & Index!$D$16 & "*",#REF!,"*" & Index!$D$20 & "*") -> #REF! | N21: 223870280 | O21: =+M21-N21 -> #REF! | P21: =IFERROR(IF(((M21/N21)-1)=0,"-",((M21/N21)-1)),"-") -> - | Q21: =SUMIFS(#REF!,#REF!,"*" & $C21 & "*",#REF!,"*" & Index!$D$12 & "*",#REF!,"*" & Index!$D$24 & "*",#REF!,"*" & Index!$D$16 & "*") + SUMIFS(#REF!,#REF!,"*" & $C21 & "*",#REF!,"*" & Index!$D$18 & "*",#REF!,"*" & Index!$D$24 & "*",#REF!,"*" & Index!$D$16 & "*",#REF!,"*" & Index!$D$20 & "*") -> #REF! | R21: 73954129 | S21: =+Q21-R21 -> #REF! | T21: =IFERROR(IF(((Q21/R21)-1)=0,"-",((Q21/R21)-1)),"-") -> - | U21: =SUMIFS(#REF!,#REF!,"*" & C21 &"*",#REF!,"*" & Index!$D$12 & "*",#REF!,"*" & Index!$D$17 & "*")+SUMIFS(#REF!,#REF!,"*" & C21 &"*",#REF!,"*" & Index!$D$18 & "*",#REF!,"*" & Index!$D$17 & "*",#REF!,"*" & Index!$D$20 & "*") -> #REF! | V21: -90151536 | W21: =+U21-V21 -> #REF! | X21: =IFERROR(IF(((U21/V21)-1)=0,"-",((U21/V21)-1)),"-") -> - | Y21: =SUMIFS(#REF!,#REF!,"*" & C21 & "*",#REF!,"*" & Index!$D$12 & "*")+ SUMIFS(#REF!,#REF!,"*" & C21 & "*",#REF!,"*" & Index!$D$18 & "*",#REF!,"*" & Index!$D$20 & "*") -> #REF! | Z21: 2434387973 | AA21: =+Y21-Z21 -> #REF! | AB21: =IFERROR(IF(((Y21/Z21)-1)=0,"-",((Y21/Z21)-1)),"-") -> -
A22: =+LEN(C22) -> 8 | C22: NACE0301 | E22: =SUMIFS(#REF!,#REF!,"*" & C22 & "*",#REF!,"*" & Index!$D$12 & "*",#REF!,"*" & Index!$D$16 & "*")+SUMIFS(#REF!,#REF!,"*" & C22 & "*",#REF!,"*" & Index!$D$18 & "*",#REF!,"*" & Index!$D$20 & "*") -> #REF! | F22: 333416925 | G22: =+E22-F22 -> #REF! | H22: =IFERROR(IF(((E22/F22)-1)=0,"-",((E22/F22)-1)),"-") -> - | I22: =+E22-M22-Q22 -> #REF! | J22: 294837778 | K22: =+I22-J22 -> #REF! | L22: =IFERROR(IF(((I22/J22)-1)=0,"-",((I22/J22)-1)),"-") -> - | M22: =SUMIFS(#REF!,#REF!,"*" & $C22 & "*",#REF!,"*" & Index!$D$12 & "*",#REF!,"*" & Index!$D$23 & "*",#REF!,"*" & Index!$D$16 & "*") + SUMIFS(#REF!,#REF!,"*" & $C22 & "*",#REF!,"*" & Index!$D$18 & "*",#REF!,"*" & Index!$D$23 & "*",#REF!,"*" & Index!$D$16 & "*",#REF!,"*" & Index!$D$20 & "*") -> #REF! | N22: 31571750 | O22: =+M22-N22 -> #REF! | P22: =IFERROR(IF(((M22/N22)-1)=0,"-",((M22/N22)-1)),"-") -> - | Q22: =SUMIFS(#REF!,#REF!,"*" & $C22 & "*",#REF!,"*" & Index!$D$12 & "*",#REF!,"*" & Index!$D$24 & "*",#REF!,"*" & Index!$D$16 & "*") + SUMIFS(#REF!,#REF!,"*" & $C22 & "*",#REF!,"*" & Index!$D$18 & "*",#REF!,"*" & Index!$D$24 & "*",#REF!,"*" & Index!$D$16 & "*",#REF!,"*" & Index!$D$20 & "*") -> #REF! | R22: 7007397 | S22: =+Q22-R22 -> #REF! | T22: =IFERROR(IF(((Q22/R22)-1)=0,"-",((Q22/R22)-1)),"-") -> - | U22: =SUMIFS(#REF!,#REF!,"*" & C22 &"*",#REF!,"*" & Index!$D$12 & "*",#REF!,"*" & Index!$D$17 & "*")+SUMIFS(#REF!,#REF!,"*" & C22 &"*",#REF!,"*" & Index!$D$18 & "*",#REF!,"*" & Index!$D$17 & "*",#REF!,"*" & Index!$D$20 & "*") -> #REF! | V22: -9646514 | W22: =+U22-V22 -> #REF! | X22: =IFERROR(IF(((U22/V22)-1)=0,"-",((U22/V22)-1)),"-") -> - | Y22: =SUMIFS(#REF!,#REF!,"*" & C22 & "*",#REF!,"*" & Index!$D$12 & "*")+ SUMIFS(#REF!,#REF!,"*" & C22 & "*",#REF!,"*" & Index!$D$18 & "*",#REF!,"*" & Index!$D$20 & "*") -> #REF! | Z22: 323770411 | AA22: =+Y22-Z22 -> #REF! | AB22: =IFERROR(IF(((Y22/Z22)-1)=0,"-",((Y22/Z22)-1)),"-") -> -
A23: =+LEN(C23) -> 8 | C23: NACE0302 | E23: =SUMIFS(#REF!,#REF!,"*" & C23 & "*",#REF!,"*" & Index!$D$12 & "*",#REF!,"*" & Index!$D$16 & "*")+SUMIFS(#REF!,#REF!,"*" & C23 & "*",#REF!,"*" & Index!$D$18 & "*",#REF!,"*" & Index!$D$20 & "*") -> #REF! | F23: 272073401 | G23: =+E23-F23 -> #REF! | H23: =IFERROR(IF(((E23/F23)-1)=0,"-",((E23/F23)-1)),"-") -> - | I23: =+E23-M23-Q23 -> #REF! | J23: 265934632 | K23: =+I23-J23 -> #REF! | L23: =IFERROR(IF(((I23/J23)-1)=0,"-",((I23/J23)-1)),"-") -> - | M23: =SUMIFS(#REF!,#REF!,"*" & $C23 & "*",#REF!,"*" & Index!$D$12 & "*",#REF!,"*" & Index!$D$23 & "*",#REF!,"*" & Index!$D$16 & "*") + SUMIFS(#REF!,#REF!,"*" & $C23 & "*",#REF!,"*" & Index!$D$18 & "*",#REF!,"*" & Index!$D$23 & "*",#REF!,"*" & Index!$D$16 & "*",#REF!,"*" & Index!$D$20 & "*") -> #REF! | N23: 5265650 | O23: =+M23-N23 -> #REF! | P23: =IFERROR(IF(((M23/N23)-1)=0,"-",((M23/N23)-1)),"-") -> - | Q23: =SUMIFS(#REF!,#REF!,"*" & $C23 & "*",#REF!,"*" & Index!$D$12 & "*",#REF!,"*" & Index!$D$24 & "*",#REF!,"*" & Index!$D$16 & "*") + SUMIFS(#REF!,#REF!,"*" & $C23 & "*",#REF!,"*" & Index!$D$18 & "*",#REF!,"*" & Index!$D$24 & "*",#REF!,"*" & Index!$D$16 & "*",#REF!,"*" & Index!$D$20 & "*") -> #REF! | R23: 873119 | S23: =+Q23-R23 -> #REF! | T23: =IFERROR(IF(((Q23/R23)-1)=0,"-",((Q23/R23)-1)),"-") -> - | U23: =SUMIFS(#REF!,#REF!,"*" & C23 &"*",#REF!,"*" & Index!$D$12 & "*",#REF!,"*" & Index!$D$17 & "*")+SUMIFS(#REF!,#REF!,"*" & C23 &"*",#REF!,"*" & Index!$D$18 & "*",#REF!,"*" & Index!$D$17 & "*",#REF!,"*" & Index!$D$20 & "*") -> #REF! | V23: -1600099 | W23: =+U23-V23 -> #REF! | X23: =IFERROR(IF(((U23/V23)-1)=0,"-",((U23/V23)-1)),"-") -> - | Y23: =SUMIFS(#REF!,#REF!,"*" & C23 & "*",#REF!,"*" & Index!$D$12 & "*")+ SUMIFS(#REF!,#REF!,"*" & C23 & "*",#REF!,"*" & Index!$D$18 & "*",#REF!,"*" & Index!$D$20 & "*") -> #REF! | Z23: 270473302 | AA23: =+Y23-Z23 -> #REF! | AB23: =IFERROR(IF(((Y23/Z23)-1)=0,"-",((Y23/Z23)-1)),"-") -> -
A24: =+LEN(C24) -> 8 | C24: NACE0303 | E24: =SUMIFS(#REF!,#REF!,"*" & C24 & "*",#REF!,"*" & Index!$D$12 & "*",#REF!,"*" & Index!$D$16 & "*")+SUMIFS(#REF!,#REF!,"*" & C24 & "*",#REF!,"*" & Index!$D$18 & "*",#REF!,"*" & Index!$D$20 & "*") -> #REF! | F24: 2589178 | G24: =+E24-F24 -> #REF! | H24: =IFERROR(IF(((E24/F24)-1)=0,"-",((E24/F24)-1)),"-") -> - | I24: =+E24-M24-Q24 -> #REF! | J24: 2589178 | K24: =+I24-J24 -> #REF! | L24: =IFERROR(IF(((I24/J24)-1)=0,"-",((I24/J24)-1)),"-") -> - | M24: =SUMIFS(#REF!,#REF!,"*" & $C24 & "*",#REF!,"*" & Index!$D$12 & "*",#REF!,"*" & Index!$D$23 & "*",#REF!,"*" & Index!$D$16 & "*") + SUMIFS(#REF!,#REF!,"*" & $C24 & "*",#REF!,"*" & Index!$D$18 & "*",#REF!,"*" & Index!$D$23 & "*",#REF!,"*" & Index!$D$16 & "*",#REF!,"*" & Index!$D$20 & "*") -> #REF! | N24: 0 | O24: =+M24-N24 -> #REF! | P24: =IFERROR(IF(((M24/N24)-1)=0,"-",((M24/N24)-1)),"-") -> - | Q24: =SUMIFS(#REF!,#REF!,"*" & $C24 & "*",#REF!,"*" & Index!$D$12 & "*",#REF!,"*" & Index!$D$24 & "*",#REF!,"*" & Index!$D$16 & "*") + SUMIFS(#REF!,#REF!,"*" & $C24 & "*",#REF!,"*" & Index!$D$18 & "*",#REF!,"*" & Index!$D$24 & "*",#REF!,"*" & Index!$D$16 & "*",#REF!,"*" & Index!$D$20 & "*") -> #REF! | R24: 0 | S24: =+Q24-R24 -> #REF! | T24: =IFERROR(IF(((Q24/R24)-1)=0,"-",((Q24/R24)-1)),"-") -> - | U24: =SUMIFS(#REF!,#REF!,"*" & C24 &"*",#REF!,"*" & Index!$D$12 & "*",#REF!,"*" & Index!$D$17 & "*")+SUMIFS(#REF!,#REF!,"*" & C24 &"*",#REF!,"*" & Index!$D$18 & "*",#REF!,"*" & Index!$D$17 & "*",#REF!,"*" & Index!$D$20 & "*") -> #REF! | V24: -6172 | W24: =+U24-V24 -> #REF! | X24: =IFERROR(IF(((U24/V24)-1)=0,"-",((U24/V24)-1)),"-") -> - | Y24: =SUMIFS(#REF!,#REF!,"*" & C24 & "*",#REF!,"*" & Index!$D$12 & "*")+ SUMIFS(#REF!,#REF!,"*" & C24 & "*",#REF!,"*" & Index!$D$18 & "*",#REF!,"*" & Index!$D$20 & "*") -> #REF! | Z24: 2583006 | AA24: =+Y24-Z24 -> #REF! | AB24: =IFERROR(IF(((Y24/Z24)-1)=0,"-",((Y24/Z24)-1)),"-") -> -
A25: =+LEN(C25) -> 8 | C25: NACE0304 | E25: =SUMIFS(#REF!,#REF!,"*" & C25 & "*",#REF!,"*" & Index!$D$12 & "*",#REF!,"*" & Index!$D$16 & "*")+SUMIFS(#REF!,#REF!,"*" & C25 & "*",#REF!,"*" & Index!$D$18 & "*",#REF!,"*" & Index!$D$20 & "*") -> #REF! | F25: 104395029 | G25: =+E25-F25 -> #REF! | H25: =IFERROR(IF(((E25/F25)-1)=0,"-",((E25/F25)-1)),"-") -> - | I25: =+E25-M25-Q25 -> #REF! | J25: 83116123 | K25: =+I25-J25 -> #REF! | L25: =IFERROR(IF(((I25/J25)-1)=0,"-",((I25/J25)-1)),"-") -> - | M25: =SUMIFS(#REF!,#REF!,"*" & $C25 & "*",#REF!,"*" & Index!$D$12 & "*",#REF!,"*" & Index!$D$23 & "*",#REF!,"*" & Index!$D$16 & "*") + SUMIFS(#REF!,#REF!,"*" & $C25 & "*",#REF!,"*" & Index!$D$18 & "*",#REF!,"*" & Index!$D$23 & "*",#REF!,"*" & Index!$D$16 & "*",#REF!,"*" & Index!$D$20 & "*") -> #REF! | N25: 18072849 | O25: =+M25-N25 -> #REF! | P25: =IFERROR(IF(((M25/N25)-1)=0,"-",((M25/N25)-1)),"-") -> - | Q25: =SUMIFS(#REF!,#REF!,"*" & $C25 & "*",#REF!,"*" & Index!$D$12 & "*",#REF!,"*" & Index!$D$24 & "*",#REF!,"*" & Index!$D$16 & "*") + SUMIFS(#REF!,#REF!,"*" & $C25 & "*",#REF!,"*" & Index!$D$18 & "*",#REF!,"*" & Index!$D$24 & "*",#REF!,"*" & Index!$D$16 & "*",#REF!,"*" & Index!$D$20 & "*") -> #REF! | R25: 3206057 | S25: =+Q25-R25 -> #REF! | T25: =IFERROR(IF(((Q25/R25)-1)=0,"-",((Q25/R25)-1)),"-") -> - | U25: =SUMIFS(#REF!,#REF!,"*" & C25 &"*",#REF!,"*" & Index!$D$12 & "*",#REF!,"*" & Index!$D$17 & "*")+SUMIFS(#REF!,#REF!,"*" & C25 &"*",#REF!,"*" & Index!$D$18 & "*",#REF!,"*" & Index!$D$17 & "*",#REF!,"*" & Index!$D$20 & "*") -> #REF! | V25: -4399029 | W25: =+U25-V25 -> #REF! | X25: =IFERROR(IF(((U25/V25)-1)=0,"-",((U25/V25)-1)),"-") -> - | Y25: =SUMIFS(#REF!,#REF!,"*" & C25 & "*",#REF!,"*" & Index!$D$12 & "*")+ SUMIFS(#REF!,#REF!,"*" & C25 & "*",#REF!,"*" & Index!$D$18 & "*",#REF!,"*" & Index!$D$20 & "*") -> #REF! | Z25: 99996000 | AA25: =+Y25-Z25 -> #REF! | AB25: =IFERROR(IF(((Y25/Z25)-1)=0,"-",((Y25/Z25)-1)),"-") -> -
A26: =+LEN(C26) -> 8 | C26: NACE0305 | E26: =SUMIFS(#REF!,#REF!,"*" & C26 & "*",#REF!,"*" & Index!$D$12 & "*",#REF!,"*" & Index!$D$16 & "*")+SUMIFS(#REF!,#REF!,"*" & C26 & "*",#REF!,"*" & Index!$D$18 & "*",#REF!,"*" & Index!$D$20 & "*") -> #REF! | F26: 94181379 | G26: =+E26-F26 -> #REF! | H26: =IFERROR(IF(((E26/F26)-1)=0,"-",((E26/F26)-1)),"-") -> - | I26: =+E26-M26-Q26 -> #REF! | J26: 67761186 | K26: =+I26-J26 -> #REF! | L26: =IFERROR(IF(((I26/J26)-1)=0,"-",((I26/J26)-1)),"-") -> - | M26: =SUMIFS(#REF!,#REF!,"*" & $C26 & "*",#REF!,"*" & Index!$D$12 & "*",#REF!,"*" & Index!$D$23 & "*",#REF!,"*" & Index!$D$16 & "*") + SUMIFS(#REF!,#REF!,"*" & $C26 & "*",#REF!,"*" & Index!$D$18 & "*",#REF!,"*" & Index!$D$23 & "*",#REF!,"*" & Index!$D$16 & "*",#REF!,"*" & Index!$D$20 & "*") -> #REF! | N26: 19296273 | O26: =+M26-N26 -> #REF! | P26: =IFERROR(IF(((M26/N26)-1)=0,"-",((M26/N26)-1)),"-") -> - | Q26: =SUMIFS(#REF!,#REF!,"*" & $C26 & "*",#REF!,"*" & Index!$D$12 & "*",#REF!,"*" & Index!$D$24 & "*",#REF!,"*" & Index!$D$16 & "*") + SUMIFS(#REF!,#REF!,"*" & $C26 & "*",#REF!,"*" & Index!$D$18 & "*",#REF!,"*" & Index!$D$24 & "*",#REF!,"*" & Index!$D$16 & "*",#REF!,"*" & Index!$D$20 & "*") -> #REF! | R26: 7123920 | S26: =+Q26-R26 -> #REF! | T26: =IFERROR(IF(((Q26/R26)-1)=0,"-",((Q26/R26)-1)),"-") -> - | U26: =SUMIFS(#REF!,#REF!,"*" & C26 &"*",#REF!,"*" & Index!$D$12 & "*",#REF!,"*" & Index!$D$17 & "*")+SUMIFS(#REF!,#REF!,"*" & C26 &"*",#REF!,"*" & Index!$D$18 & "*",#REF!,"*" & Index!$D$17 & "*",#REF!,"*" & Index!$D$20 & "*") -> #REF! | V26: -10890183 | W26: =+U26-V26 -> #REF! | X26: =IFERROR(IF(((U26/V26)-1)=0,"-",((U26/V26)-1)),"-") -> - | Y26: =SUMIFS(#REF!,#REF!,"*" & C26 & "*",#REF!,"*" & Index!$D$12 & "*")+ SUMIFS(#REF!,#REF!,"*" & C26 & "*",#REF!,"*" & Index!$D$18 & "*",#REF!,"*" & Index!$D$20 & "*") -> #REF! | Z26: 83291196 | AA26: =+Y26-Z26 -> #REF! | AB26: =IFERROR(IF(((Y26/Z26)-1)=0,"-",((Y26/Z26)-1)),"-") -> -
A27: =+LEN(C27) -> 8 | C27: NACE0306 | E27: =SUMIFS(#REF!,#REF!,"*" & C27 & "*",#REF!,"*" & Index!$D$12 & "*",#REF!,"*" & Index!$D$16 & "*")+SUMIFS(#REF!,#REF!,"*" & C27 & "*",#REF!,"*" & Index!$D$18 & "*",#REF!,"*" & Index!$D$20 & "*") -> #REF! | F27: 54384318 | G27: =+E27-F27 -> #REF! | H27: =IFERROR(IF(((E27/F27)-1)=0,"-",((E27/F27)-1)),"-") -> - | I27: =+E27-M27-Q27 -> #REF! | J27: 36970853 | K27: =+I27-J27 -> #REF! | L27: =IFERROR(IF(((I27/J27)-1)=0,"-",((I27/J27)-1)),"-") -> - | M27: =SUMIFS(#REF!,#REF!,"*" & $C27 & "*",#REF!,"*" & Index!$D$12 & "*",#REF!,"*" & Index!$D$23 & "*",#REF!,"*" & Index!$D$16 & "*") + SUMIFS(#REF!,#REF!,"*" & $C27 & "*",#REF!,"*" & Index!$D$18 & "*",#REF!,"*" & Index!$D$23 & "*",#REF!,"*" & Index!$D$16 & "*",#REF!,"*" & Index!$D$20 & "*") -> #REF! | N27: 10416012 | O27: =+M27-N27 -> #REF! | P27: =IFERROR(IF(((M27/N27)-1)=0,"-",((M27/N27)-1)),"-") -> - | Q27: =SUMIFS(#REF!,#REF!,"*" & $C27 & "*",#REF!,"*" & Index!$D$12 & "*",#REF!,"*" & Index!$D$24 & "*",#REF!,"*" & Index!$D$16 & "*") + SUMIFS(#REF!,#REF!,"*" & $C27 & "*",#REF!,"*" & Index!$D$18 & "*",#REF!,"*" & Index!$D$24 & "*",#REF!,"*" & Index!$D$16 & "*",#REF!,"*" & Index!$D$20 & "*") -> #REF! | R27: 6997453 | S27: =+Q27-R27 -> #REF! | T27: =IFERROR(IF(((Q27/R27)-1)=0,"-",((Q27/R27)-1)),"-") -> - | U27: =SUMIFS(#REF!,#REF!,"*" & C27 &"*",#REF!,"*" & Index!$D$12 & "*",#REF!,"*" & Index!$D$17 & "*")+SUMIFS(#REF!,#REF!,"*" & C27 &"*",#REF!,"*" & Index!$D$18 & "*",#REF!,"*" & Index!$D$17 & "*",#REF!,"*" & Index!$D$20 & "*") -> #REF! | V27: -7653435 | W27: =+U27-V27 -> #REF! | X27: =IFERROR(IF(((U27/V27)-1)=0,"-",((U27/V27)-1)),"-") -> - | Y27: =SUMIFS(#REF!,#REF!,"*" & C27 & "*",#REF!,"*" & Index!$D$12 & "*")+ SUMIFS(#REF!,#REF!,"*" & C27 & "*",#REF!,"*" & Index!$D$18 & "*",#REF!,"*" & Index!$D$20 & "*") -> #REF! | Z27: 46730883 | AA27: =+Y27-Z27 -> #REF! | AB27: =IFERROR(IF(((Y27/Z27)-1)=0,"-",((Y27/Z27)-1)),"-") -> -
A28: =+LEN(C28) -> 8 | C28: NACE0307 | E28: =SUMIFS(#REF!,#REF!,"*" & C28 & "*",#REF!,"*" & Index!$D$12 & "*",#REF!,"*" & Index!$D$16 & "*")+SUMIFS(#REF!,#REF!,"*" & C28 & "*",#REF!,"*" & Index!$D$18 & "*",#REF!,"*" & Index!$D$20 & "*") -> #REF! | F28: 115006402 | G28: =+E28-F28 -> #REF! | H28: =IFERROR(IF(((E28/F28)-1)=0,"-",((E28/F28)-1)),"-") -> - | I28: =+E28-M28-Q28 -> #REF! | J28: 99244647 | K28: =+I28-J28 -> #REF! | L28: =IFERROR(IF(((I28/J28)-1)=0,"-",((I28/J28)-1)),"-") -> - | M28: =SUMIFS(#REF!,#REF!,"*" & $C28 & "*",#REF!,"*" & Index!$D$12 & "*",#REF!,"*" & Index!$D$23 & "*",#REF!,"*" & Index!$D$16 & "*") + SUMIFS(#REF!,#REF!,"*" & $C28 & "*",#REF!,"*" & Index!$D$18 & "*",#REF!,"*" & Index!$D$23 & "*",#REF!,"*" & Index!$D$16 & "*",#REF!,"*" & Index!$D$20 & "*") -> #REF! | N28: 11664424 | O28: =+M28-N28 -> #REF! | P28: =IFERROR(IF(((M28/N28)-1)=0,"-",((M28/N28)-1)),"-") -> - | Q28: =SUMIFS(#REF!,#REF!,"*" & $C28 & "*",#REF!,"*" & Index!$D$12 & "*",#REF!,"*" & Index!$D$24 & "*",#REF!,"*" & Index!$D$16 & "*") + SUMIFS(#REF!,#REF!,"*" & $C28 & "*",#REF!,"*" & Index!$D$18 & "*",#REF!,"*" & Index!$D$24 & "*",#REF!,"*" & Index!$D$16 & "*",#REF!,"*" & Index!$D$20 & "*") -> #REF! | R28: 4097331 | S28: =+Q28-R28 -> #REF! | T28: =IFERROR(IF(((Q28/R28)-1)=0,"-",((Q28/R28)-1)),"-") -> - | U28: =SUMIFS(#REF!,#REF!,"*" & C28 &"*",#REF!,"*" & Index!$D$12 & "*",#REF!,"*" & Index!$D$17 & "*")+SUMIFS(#REF!,#REF!,"*" & C28 &"*",#REF!,"*" & Index!$D$18 & "*",#REF!,"*" & Index!$D$17 & "*",#REF!,"*" & Index!$D$20 & "*") -> #REF! | V28: -4831396 | W28: =+U28-V28 -> #REF! | X28: =IFERROR(IF(((U28/V28)-1)=0,"-",((U28/V28)-1)),"-") -> - | Y28: =SUMIFS(#REF!,#REF!,"*" & C28 & "*",#REF!,"*" & Index!$D$12 & "*")+ SUMIFS(#REF!,#REF!,"*" & C28 & "*",#REF!,"*" & Index!$D$18 & "*",#REF!,"*" & Index!$D$20 & "*") -> #REF! | Z28: 110175006 | AA28: =+Y28-Z28 -> #REF! | AB28: =IFERROR(IF(((Y28/Z28)-1)=0,"-",((Y28/Z28)-1)),"-") -> -
A29: =+LEN(C29) -> 8 | C29: NACE0308 | E29: =SUMIFS(#REF!,#REF!,"*" & C29 & "*",#REF!,"*" & Index!$D$12 & "*",#REF!,"*" & Index!$D$16 & "*")+SUMIFS(#REF!,#REF!,"*" & C29 & "*",#REF!,"*" & Index!$D$18 & "*",#REF!,"*" & Index!$D$20 & "*") -> #REF! | F29: 142798851 | G29: =+E29-F29 -> #REF! | H29: =IFERROR(IF(((E29/F29)-1)=0,"-",((E29/F29)-1)),"-") -> - | I29: =+E29-M29-Q29 -> #REF! | J29: 141360987 | K29: =+I29-J29 -> #REF! | L29: =IFERROR(IF(((I29/J29)-1)=0,"-",((I29/J29)-1)),"-") -> - | M29: =SUMIFS(#REF!,#REF!,"*" & $C29 & "*",#REF!,"*" & Index!$D$12 & "*",#REF!,"*" & Index!$D$23 & "*",#REF!,"*" & Index!$D$16 & "*") + SUMIFS(#REF!,#REF!,"*" & $C29 & "*",#REF!,"*" & Index!$D$18 & "*",#REF!,"*" & Index!$D$23 & "*",#REF!,"*" & Index!$D$16 & "*",#REF!,"*" & Index!$D$20 & "*") -> #REF! | N29: 1370318 | O29: =+M29-N29 -> #REF! | P29: =IFERROR(IF(((M29/N29)-1)=0,"-",((M29/N29)-1)),"-") -> - | Q29: =SUMIFS(#REF!,#REF!,"*" & $C29 & "*",#REF!,"*" & Index!$D$12 & "*",#REF!,"*" & Index!$D$24 & "*",#REF!,"*" & Index!$D$16 & "*") + SUMIFS(#REF!,#REF!,"*" & $C29 & "*",#REF!,"*" & Index!$D$18 & "*",#REF!,"*" & Index!$D$24 & "*",#REF!,"*" & Index!$D$16 & "*",#REF!,"*" & Index!$D$20 & "*") -> #REF! | R29: 67546 | S29: =+Q29-R29 -> #REF! | T29: =IFERROR(IF(((Q29/R29)-1)=0,"-",((Q29/R29)-1)),"-") -> - | U29: =SUMIFS(#REF!,#REF!,"*" & C29 &"*",#REF!,"*" & Index!$D$12 & "*",#REF!,"*" & Index!$D$17 & "*")+SUMIFS(#REF!,#REF!,"*" & C29 &"*",#REF!,"*" & Index!$D$18 & "*",#REF!,"*" & Index!$D$17 & "*",#REF!,"*" & Index!$D$20 & "*") -> #REF! | V29: -199270 | W29: =+U29-V29 -> #REF! | X29: =IFERROR(IF(((U29/V29)-1)=0,"-",((U29/V29)-1)),"-") -> - | Y29: =SUMIFS(#REF!,#REF!,"*" & C29 & "*",#REF!,"*" & Index!$D$12 & "*")+ SUMIFS(#REF!,#REF!,"*" & C29 & "*",#REF!,"*" & Index!$D$18 & "*",#REF!,"*" & Index!$D$20 & "*") -> #REF! | Z29: 142599581 | AA29: =+Y29-Z29 -> #REF! | AB29: =IFERROR(IF(((Y29/Z29)-1)=0,"-",((Y29/Z29)-1)),"-") -> -
A30: =+LEN(C30) -> 8 | C30: NACE0309 | E30: =SUMIFS(#REF!,#REF!,"*" & C30 & "*",#REF!,"*" & Index!$D$12 & "*",#REF!,"*" & Index!$D$16 & "*")+SUMIFS(#REF!,#REF!,"*" & C30 & "*",#REF!,"*" & Index!$D$18 & "*",#REF!,"*" & Index!$D$20 & "*") -> #REF! | F30: 30975685 | G30: =+E30-F30 -> #REF! | H30: =IFERROR(IF(((E30/F30)-1)=0,"-",((E30/F30)-1)),"-") -> - | I30: =+E30-M30-Q30 -> #REF! | J30: 22665833 | K30: =+I30-J30 -> #REF! | L30: =IFERROR(IF(((I30/J30)-1)=0,"-",((I30/J30)-1)),"-") -> - | M30: =SUMIFS(#REF!,#REF!,"*" & $C30 & "*",#REF!,"*" & Index!$D$12 & "*",#REF!,"*" & Index!$D$23 & "*",#REF!,"*" & Index!$D$16 & "*") + SUMIFS(#REF!,#REF!,"*" & $C30 & "*",#REF!,"*" & Index!$D$18 & "*",#REF!,"*" & Index!$D$23 & "*",#REF!,"*" & Index!$D$16 & "*",#REF!,"*" & Index!$D$20 & "*") -> #REF! | N30: 5853159 | O30: =+M30-N30 -> #REF! | P30: =IFERROR(IF(((M30/N30)-1)=0,"-",((M30/N30)-1)),"-") -> - | Q30: =SUMIFS(#REF!,#REF!,"*" & $C30 & "*",#REF!,"*" & Index!$D$12 & "*",#REF!,"*" & Index!$D$24 & "*",#REF!,"*" & Index!$D$16 & "*") + SUMIFS(#REF!,#REF!,"*" & $C30 & "*",#REF!,"*" & Index!$D$18 & "*",#REF!,"*" & Index!$D$24 & "*",#REF!,"*" & Index!$D$16 & "*",#REF!,"*" & Index!$D$20 & "*") -> #REF! | R30: 2456693 | S30: =+Q30-R30 -> #REF! | T30: =IFERROR(IF(((Q30/R30)-1)=0,"-",((Q30/R30)-1)),"-") -> - | U30: =SUMIFS(#REF!,#REF!,"*" & C30 &"*",#REF!,"*" & Index!$D$12 & "*",#REF!,"*" & Index!$D$17 & "*")+SUMIFS(#REF!,#REF!,"*" & C30 &"*",#REF!,"*" & Index!$D$18 & "*",#REF!,"*" & Index!$D$17 & "*",#REF!,"*" & Index!$D$20 & "*") -> #REF! | V30: -2751949 | W30: =+U30-V30 -> #REF! | X30: =IFERROR(IF(((U30/V30)-1)=0,"-",((U30/V30)-1)),"-") -> - | Y30: =SUMIFS(#REF!,#REF!,"*" & C30 & "*",#REF!,"*" & Index!$D$12 & "*")+ SUMIFS(#REF!,#REF!,"*" & C30 & "*",#REF!,"*" & Index!$D$18 & "*",#REF!,"*" & Index!$D$20 & "*") -> #REF! | Z30: 28223736 | AA30: =+Y30-Z30 -> #REF! | AB30: =IFERROR(IF(((Y30/Z30)-1)=0,"-",((Y30/Z30)-1)),"-") -> -
A31: =+LEN(C31) -> 8 | C31: NACE0310 | E31: =SUMIFS(#REF!,#REF!,"*" & C31 & "*",#REF!,"*" & Index!$D$12 & "*",#REF!,"*" & Index!$D$16 & "*")+SUMIFS(#REF!,#REF!,"*" & C31 & "*",#REF!,"*" & Index!$D$18 & "*",#REF!,"*" & Index!$D$20 & "*") -> #REF! | F31: 195382257 | G31: =+E31-F31 -> #REF! | H31: =IFERROR(IF(((E31/F31)-1)=0,"-",((E31/F31)-1)),"-") -> - | I31: =+E31-M31-Q31 -> #REF! | J31: 195177406 | K31: =+I31-J31 -> #REF! | L31: =IFERROR(IF(((I31/J31)-1)=0,"-",((I31/J31)-1)),"-") -> - | M31: =SUMIFS(#REF!,#REF!,"*" & $C31 & "*",#REF!,"*" & Index!$D$12 & "*",#REF!,"*" & Index!$D$23 & "*",#REF!,"*" & Index!$D$16 & "*") + SUMIFS(#REF!,#REF!,"*" & $C31 & "*",#REF!,"*" & Index!$D$18 & "*",#REF!,"*" & Index!$D$23 & "*",#REF!,"*" & Index!$D$16 & "*",#REF!,"*" & Index!$D$20 & "*") -> #REF! | N31: 204162 | O31: =+M31-N31 -> #REF! | P31: =IFERROR(IF(((M31/N31)-1)=0,"-",((M31/N31)-1)),"-") -> - | Q31: =SUMIFS(#REF!,#REF!,"*" & $C31 & "*",#REF!,"*" & Index!$D$12 & "*",#REF!,"*" & Index!$D$24 & "*",#REF!,"*" & Index!$D$16 & "*") + SUMIFS(#REF!,#REF!,"*" & $C31 & "*",#REF!,"*" & Index!$D$18 & "*",#REF!,"*" & Index!$D$24 & "*",#REF!,"*" & Index!$D$16 & "*",#REF!,"*" & Index!$D$20 & "*") -> #REF! | R31: 689 | S31: =+Q31-R31 -> #REF! | T31: =IFERROR(IF(((Q31/R31)-1)=0,"-",((Q31/R31)-1)),"-") -> - | U31: =SUMIFS(#REF!,#REF!,"*" & C31 &"*",#REF!,"*" & Index!$D$12 & "*",#REF!,"*" & Index!$D$17 & "*")+SUMIFS(#REF!,#REF!,"*" & C31 &"*",#REF!,"*" & Index!$D$18 & "*",#REF!,"*" & Index!$D$17 & "*",#REF!,"*" & Index!$D$20 & "*") -> #REF! | V31: -72313 | W31: =+U31-V31 -> #REF! | X31: =IFERROR(IF(((U31/V31)-1)=0,"-",((U31/V31)-1)),"-") -> - | Y31: =SUMIFS(#REF!,#REF!,"*" & C31 & "*",#REF!,"*" & Index!$D$12 & "*")+ SUMIFS(#REF!,#REF!,"*" & C31 & "*",#REF!,"*" & Index!$D$18 & "*",#REF!,"*" & Index!$D$20 & "*") -> #REF! | Z31: 195309944 | AA31: =+Y31-Z31 -> #REF! | AB31: =IFERROR(IF(((Y31/Z31)-1)=0,"-",((Y31/Z31)-1)),"-") -> -
A32: =+LEN(C32) -> 8 | C32: NACE0311 | E32: =SUMIFS(#REF!,#REF!,"*" & C32 & "*",#REF!,"*" & Index!$D$12 & "*",#REF!,"*" & Index!$D$16 & "*")+SUMIFS(#REF!,#REF!,"*" & C32 & "*",#REF!,"*" & Index!$D$18 & "*",#REF!,"*" & Index!$D$20 & "*") -> #REF! | F32: 103118155 | G32: =+E32-F32 -> #REF! | H32: =IFERROR(IF(((E32/F32)-1)=0,"-",((E32/F32)-1)),"-") -> - | I32: =+E32-M32-Q32 -> #REF! | J32: 94453407 | K32: =+I32-J32 -> #REF! | L32: =IFERROR(IF(((I32/J32)-1)=0,"-",((I32/J32)-1)),"-") -> - | M32: =SUMIFS(#REF!,#REF!,"*" & $C32 & "*",#REF!,"*" & Index!$D$12 & "*",#REF!,"*" & Index!$D$23 & "*",#REF!,"*" & Index!$D$16 & "*") + SUMIFS(#REF!,#REF!,"*" & $C32 & "*",#REF!,"*" & Index!$D$18 & "*",#REF!,"*" & Index!$D$23 & "*",#REF!,"*" & Index!$D$16 & "*",#REF!,"*" & Index!$D$20 & "*") -> #REF! | N32: 8226832 | O32: =+M32-N32 -> #REF! | P32: =IFERROR(IF(((M32/N32)-1)=0,"-",((M32/N32)-1)),"-") -> - | Q32: =SUMIFS(#REF!,#REF!,"*" & $C32 & "*",#REF!,"*" & Index!$D$12 & "*",#REF!,"*" & Index!$D$24 & "*",#REF!,"*" & Index!$D$16 & "*") + SUMIFS(#REF!,#REF!,"*" & $C32 & "*",#REF!,"*" & Index!$D$18 & "*",#REF!,"*" & Index!$D$24 & "*",#REF!,"*" & Index!$D$16 & "*",#REF!,"*" & Index!$D$20 & "*") -> #REF! | R32: 437916 | S32: =+Q32-R32 -> #REF! | T32: =IFERROR(IF(((Q32/R32)-1)=0,"-",((Q32/R32)-1)),"-") -> - | U32: =SUMIFS(#REF!,#REF!,"*" & C32 &"*",#REF!,"*" & Index!$D$12 & "*",#REF!,"*" & Index!$D$17 & "*")+SUMIFS(#REF!,#REF!,"*" & C32 &"*",#REF!,"*" & Index!$D$18 & "*",#REF!,"*" & Index!$D$17 & "*",#REF!,"*" & Index!$D$20 & "*") -> #REF! | V32: -1110998 | W32: =+U32-V32 -> #REF! | X32: =IFERROR(IF(((U32/V32)-1)=0,"-",((U32/V32)-1)),"-") -> - | Y32: =SUMIFS(#REF!,#REF!,"*" & C32 & "*",#REF!,"*" & Index!$D$12 & "*")+ SUMIFS(#REF!,#REF!,"*" & C32 & "*",#REF!,"*" & Index!$D$18 & "*",#REF!,"*" & Index!$D$20 & "*") -> #REF! | Z32: 102007157 | AA32: =+Y32-Z32 -> #REF! | AB32: =IFERROR(IF(((Y32/Z32)-1)=0,"-",((Y32/Z32)-1)),"-") -> -
A33: =+LEN(C33) -> 8 | C33: NACE0312 | E33: =SUMIFS(#REF!,#REF!,"*" & C33 & "*",#REF!,"*" & Index!$D$12 & "*",#REF!,"*" & Index!$D$16 & "*")+SUMIFS(#REF!,#REF!,"*" & C33 & "*",#REF!,"*" & Index!$D$18 & "*",#REF!,"*" & Index!$D$20 & "*") -> #REF! | F33: 69749970 | G33: =+E33-F33 -> #REF! | H33: =IFERROR(IF(((E33/F33)-1)=0,"-",((E33/F33)-1)),"-") -> - | I33: =+E33-M33-Q33 -> #REF! | J33: 66965171 | K33: =+I33-J33 -> #REF! | L33: =IFERROR(IF(((I33/J33)-1)=0,"-",((I33/J33)-1)),"-") -> - | M33: =SUMIFS(#REF!,#REF!,"*" & $C33 & "*",#REF!,"*" & Index!$D$12 & "*",#REF!,"*" & Index!$D$23 & "*",#REF!,"*" & Index!$D$16 & "*") + SUMIFS(#REF!,#REF!,"*" & $C33 & "*",#REF!,"*" & Index!$D$18 & "*",#REF!,"*" & Index!$D$23 & "*",#REF!,"*" & Index!$D$16 & "*",#REF!,"*" & Index!$D$20 & "*") -> #REF! | N33: 2784786 | O33: =+M33-N33 -> #REF! | P33: =IFERROR(IF(((M33/N33)-1)=0,"-",((M33/N33)-1)),"-") -> - | Q33: =SUMIFS(#REF!,#REF!,"*" & $C33 & "*",#REF!,"*" & Index!$D$12 & "*",#REF!,"*" & Index!$D$24 & "*",#REF!,"*" & Index!$D$16 & "*") + SUMIFS(#REF!,#REF!,"*" & $C33 & "*",#REF!,"*" & Index!$D$18 & "*",#REF!,"*" & Index!$D$24 & "*",#REF!,"*" & Index!$D$16 & "*",#REF!,"*" & Index!$D$20 & "*") -> #REF! | R33: 13 | S33: =+Q33-R33 -> #REF! | T33: =IFERROR(IF(((Q33/R33)-1)=0,"-",((Q33/R33)-1)),"-") -> - | U33: =SUMIFS(#REF!,#REF!,"*" & C33 &"*",#REF!,"*" & Index!$D$12 & "*",#REF!,"*" & Index!$D$17 & "*")+SUMIFS(#REF!,#REF!,"*" & C33 &"*",#REF!,"*" & Index!$D$18 & "*",#REF!,"*" & Index!$D$17 & "*",#REF!,"*" & Index!$D$20 & "*") -> #REF! | V33: -360730 | W33: =+U33-V33 -> #REF! | X33: =IFERROR(IF(((U33/V33)-1)=0,"-",((U33/V33)-1)),"-") -> - | Y33: =SUMIFS(#REF!,#REF!,"*" & C33 & "*",#REF!,"*" & Index!$D$12 & "*")+ SUMIFS(#REF!,#REF!,"*" & C33 & "*",#REF!,"*" & Index!$D$18 & "*",#REF!,"*" & Index!$D$20 & "*") -> #REF! | Z33: 69389240 | AA33: =+Y33-Z33 -> #REF! | AB33: =IFERROR(IF(((Y33/Z33)-1)=0,"-",((Y33/Z33)-1)),"-") -> -
... A45: =+LEN(C45) -> 8 | C45: NACE0324 | E45: =SUMIFS(#REF!,#REF!,"*" & C45 & "*",#REF!,"*" & Index!$D$12 & "*",#REF!,"*" & Index!$D$16 & "*")+SUMIFS(#REF!,#REF!,"*" & C45 & "*",#REF!,"*" & Index!$D$18 & "*",#REF!,"*" & Index!$D$20 & "*") -> #REF! | F45: 45755330 | G45: =+E45-F45 -> #REF! | H45: =IFERROR(IF(((E45/F45)-1)=0,"-",((E45/F45)-1)),"-") -> - | I45: =+E45-M45-Q45 -> #REF! | J45: 41592763 | K45: =+I45-J45 -> #REF! | L45: =IFERROR(IF(((I45/J45)-1)=0,"-",((I45/J45)-1)),"-") -> - | M45: =SUMIFS(#REF!,#REF!,"*" & $C45 & "*",#REF!,"*" & Index!$D$12 & "*",#REF!,"*" & Index!$D$23 & "*",#REF!,"*" & Index!$D$16 & "*") + SUMIFS(#REF!,#REF!,"*" & $C45 & "*",#REF!,"*" & Index!$D$18 & "*",#REF!,"*" & Index!$D$23 & "*",#REF!,"*" & Index!$D$16 & "*",#REF!,"*" & Index!$D$20 & "*") -> #REF! | N45: 3556884 | O45: =+M45-N45 -> #REF! | P45: =IFERROR(IF(((M45/N45)-1)=0,"-",((M45/N45)-1)),"-") -> - | Q45: =SUMIFS(#REF!,#REF!,"*" & $C45 & "*",#REF!,"*" & Index!$D$12 & "*",#REF!,"*" & Index!$D$24 & "*",#REF!,"*" & Index!$D$16 & "*") + SUMIFS(#REF!,#REF!,"*" & $C45 & "*",#REF!,"*" & Index!$D$18 & "*",#REF!,"*" & Index!$D$24 & "*",#REF!,"*" & Index!$D$16 & "*",#REF!,"*" & Index!$D$20 & "*") -> #REF! | R45: 605683 | S45: =+Q45-R45 -> #REF! | T45: =IFERROR(IF(((Q45/R45)-1)=0,"-",((Q45/R45)-1)),"-") -> - | U45: =SUMIFS(#REF!,#REF!,"*" & C45 &"*",#REF!,"*" & Index!$D$12 & "*",#REF!,"*" & Index!$D$17 & "*")+SUMIFS(#REF!,#REF!,"*" & C45 &"*",#REF!,"*" & Index!$D$18 & "*",#REF!,"*" & Index!$D$17 & "*",#REF!,"*" & Index!$D$20 & "*") -> #REF! | V45: -829046 | W45: =+U45-V45 -> #REF! | X45: =IFERROR(IF(((U45/V45)-1)=0,"-",((U45/V45)-1)),"-") -> - | Y45: =SUMIFS(#REF!,#REF!,"*" & C45 & "*",#REF!,"*" & Index!$D$12 & "*")+ SUMIFS(#REF!,#REF!,"*" & C45 & "*",#REF!,"*" & Index!$D$18 & "*",#REF!,"*" & Index!$D$20 & "*") -> #REF! | Z45: 44926284 | AA45: =+Y45-Z45 -> #REF! | AB45: =IFERROR(IF(((Y45/Z45)-1)=0,"-",((Y45/Z45)-1)),"-") -> -
A46: =+LEN(C46) -> 6 | C46: NACE04 | D46: Electricity, gas, steam and air conditioning supply | E46: =SUMIFS(#REF!,#REF!,"*" & C46 & "*",#REF!,"*" & Index!$D$12 & "*",#REF!,"*" & Index!$D$16 & "*")+SUMIFS(#REF!,#REF!,"*" & C46 & "*",#REF!,"*" & Index!$D$18 & "*",#REF!,"*" & Index!$D$20 & "*",#REF!,"*" & Index!$D$16 & "*") -> #REF! | F46: 394116050 | G46: =+E46-F46 -> #REF! | H46: =IFERROR(IF(((E46/F46)-1)=0,"-",((E46/F46)-1)),"-") -> - | I46: =+E46-M46-Q46 -> #REF! | J46: 389826622 | K46: =+I46-J46 -> #REF! | L46: =IFERROR(IF(((I46/J46)-1)=0,"-",((I46/J46)-1)),"-") -> - | M46: =SUMIFS(#REF!,#REF!,"*" & $C46 & "*",#REF!,"*" & Index!$D$12 & "*",#REF!,"*" & Index!$D$23 & "*",#REF!,"*" & Index!$D$16 & "*") + SUMIFS(#REF!,#REF!,"*" & $C46 & "*",#REF!,"*" & Index!$D$18 & "*",#REF!,"*" & Index!$D$23 & "*",#REF!,"*" & Index!$D$16 & "*",#REF!,"*" & Index!$D$20 & "*") -> #REF! | N46: 4226765 | O46: =+M46-N46 -> #REF! | P46: =IFERROR(IF(((M46/N46)-1)=0,"-",((M46/N46)-1)),"-") -> - | Q46: =SUMIFS(#REF!,#REF!,"*" & $C46 & "*",#REF!,"*" & Index!$D$12 & "*",#REF!,"*" & Index!$D$24 & "*",#REF!,"*" & Index!$D$16 & "*") + SUMIFS(#REF!,#REF!,"*" & $C46 & "*",#REF!,"*" & Index!$D$18 & "*",#REF!,"*" & Index!$D$24 & "*",#REF!,"*" & Index!$D$16 & "*",#REF!,"*" & Index!$D$20 & "*") -> #REF! | R46: 62663 | S46: =+Q46-R46 -> #REF! | T46: =IFERROR(IF(((Q46/R46)-1)=0,"-",((Q46/R46)-1)),"-") -> - | U46: =SUMIFS(#REF!,#REF!,"*" & C46 &"*",#REF!,"*" & Index!$D$12 & "*",#REF!,"*" & Index!$D$17 & "*")+SUMIFS(#REF!,#REF!,"*" & C46 &"*",#REF!,"*" & Index!$D$18 & "*",#REF!,"*" & Index!$D$17 & "*",#REF!,"*" & Index!$D$20 & "*") -> #REF! | V46: -330670 | W46: =+U46-V46 -> #REF! | X46: =IFERROR(IF(((U46/V46)-1)=0,"-",((U46/V46)-1)),"-") -> - | Y46: =SUMIFS(#REF!,#REF!,"*" & C46 & "*",#REF!,"*" & Index!$D$12 & "*")+ SUMIFS(#REF!,#REF!,"*" & C46 & "*",#REF!,"*" & Index!$D$18 & "*",#REF!,"*" & Index!$D$20 & "*") -> #REF! | Z46: 393785380 | AA46: =+Y46-Z46 -> #REF! | AB46: =IFERROR(IF(((Y46/Z46)-1)=0,"-",((Y46/Z46)-1)),"-") -> -
A47: =+LEN(C47) -> 6 | C47: NACE05 | D47: Water supply; sewerage; waste managment and remediation activities | E47: =SUMIFS(#REF!,#REF!,"*" & C47 & "*",#REF!,"*" & Index!$D$12 & "*",#REF!,"*" & Index!$D$16 & "*")+SUMIFS(#REF!,#REF!,"*" & C47 & "*",#REF!,"*" & Index!$D$18 & "*",#REF!,"*" & Index!$D$20 & "*",#REF!,"*" & Index!$D$16 & "*") -> #REF! | F47: 49849440 | G47: =+E47-F47 -> #REF! | H47: =IFERROR(IF(((E47/F47)-1)=0,"-",((E47/F47)-1)),"-") -> - | I47: =+E47-M47-Q47 -> #REF! | J47: 33895370 | K47: =+I47-J47 -> #REF! | L47: =IFERROR(IF(((I47/J47)-1)=0,"-",((I47/J47)-1)),"-") -> - | M47: =SUMIFS(#REF!,#REF!,"*" & $C47 & "*",#REF!,"*" & Index!$D$12 & "*",#REF!,"*" & Index!$D$23 & "*",#REF!,"*" & Index!$D$16 & "*") + SUMIFS(#REF!,#REF!,"*" & $C47 & "*",#REF!,"*" & Index!$D$18 & "*",#REF!,"*" & Index!$D$23 & "*",#REF!,"*" & Index!$D$16 & "*",#REF!,"*" & Index!$D$20 & "*") -> #REF! | N47: 14171842 | O47: =+M47-N47 -> #REF! | P47: =IFERROR(IF(((M47/N47)-1)=0,"-",((M47/N47)-1)),"-") -> - | Q47: =SUMIFS(#REF!,#REF!,"*" & $C47 & "*",#REF!,"*" & Index!$D$12 & "*",#REF!,"*" & Index!$D$24 & "*",#REF!,"*" & Index!$D$16 & "*") + SUMIFS(#REF!,#REF!,"*" & $C47 & "*",#REF!,"*" & Index!$D$18 & "*",#REF!,"*" & Index!$D$24 & "*",#REF!,"*" & Index!$D$16 & "*",#REF!,"*" & Index!$D$20 & "*") -> #REF! | R47: 1782228 | S47: =+Q47-R47 -> #REF! | T47: =IFERROR(IF(((Q47/R47)-1)=0,"-",((Q47/R47)-1)),"-") -> - | U47: =SUMIFS(#REF!,#REF!,"*" & C47 &"*",#REF!,"*" & Index!$D$12 & "*",#REF!,"*" & Index!$D$17 & "*")+SUMIFS(#REF!,#REF!,"*" & C47 &"*",#REF!,"*" & Index!$D$18 & "*",#REF!,"*" & Index!$D$17 & "*",#REF!,"*" & Index!$D$20 & "*") -> #REF! | V47: -1568500 | W47: =+U47-V47 -> #REF! | X47: =IFERROR(IF(((U47/V47)-1)=0,"-",((U47/V47)-1)),"-") -> - | Y47: =SUMIFS(#REF!,#REF!,"*" & C47 & "*",#REF!,"*" & Index!$D$12 & "*")+ SUMIFS(#REF!,#REF!,"*" & C47 & "*",#REF!,"*" & Index!$D$18 & "*",#REF!,"*" & Index!$D$20 & "*") -> #REF! | Z47: 48280940 | AA47: =+Y47-Z47 -> #REF! | AB47: =IFERROR(IF(((Y47/Z47)-1)=0,"-",((Y47/Z47)-1)),"-") -> -
A48: =+LEN(C48) -> 8 | C48: NACE0501 | E48: =SUMIFS(#REF!,#REF!,"*" & C48 & "*",#REF!,"*" & Index!$D$12 & "*",#REF!,"*" & Index!$D$16 & "*")+SUMIFS(#REF!,#REF!,"*" & C48 & "*",#REF!,"*" & Index!$D$18 & "*",#REF!,"*" & Index!$D$20 & "*") -> #REF! | F48: 9370046 | G48: =+E48-F48 -> #REF! | H48: =IFERROR(IF(((E48/F48)-1)=0,"-",((E48/F48)-1)),"-") -> - | I48: =+E48-M48-Q48 -> #REF! | J48: 8637224 | K48: =+I48-J48 -> #REF! | L48: =IFERROR(IF(((I48/J48)-1)=0,"-",((I48/J48)-1)),"-") -> - | M48: =SUMIFS(#REF!,#REF!,"*" & $C48 & "*",#REF!,"*" & Index!$D$12 & "*",#REF!,"*" & Index!$D$23 & "*",#REF!,"*" & Index!$D$16 & "*") + SUMIFS(#REF!,#REF!,"*" & $C48 & "*",#REF!,"*" & Index!$D$18 & "*",#REF!,"*" & Index!$D$23 & "*",#REF!,"*" & Index!$D$16 & "*",#REF!,"*" & Index!$D$20 & "*") -> #REF! | N48: 732689 | O48: =+M48-N48 -> #REF! | P48: =IFERROR(IF(((M48/N48)-1)=0,"-",((M48/N48)-1)),"-") -> - | Q48: =SUMIFS(#REF!,#REF!,"*" & $C48 & "*",#REF!,"*" & Index!$D$12 & "*",#REF!,"*" & Index!$D$24 & "*",#REF!,"*" & Index!$D$16 & "*") + SUMIFS(#REF!,#REF!,"*" & $C48 & "*",#REF!,"*" & Index!$D$18 & "*",#REF!,"*" & Index!$D$24 & "*",#REF!,"*" & Index!$D$16 & "*",#REF!,"*" & Index!$D$20 & "*") -> #REF! | R48: 133 | S48: =+Q48-R48 -> #REF! | T48: =IFERROR(IF(((Q48/R48)-1)=0,"-",((Q48/R48)-1)),"-") -> - | U48: =SUMIFS(#REF!,#REF!,"*" & C48 &"*",#REF!,"*" & Index!$D$12 & "*",#REF!,"*" & Index!$D$17 & "*")+SUMIFS(#REF!,#REF!,"*" & C48 &"*",#REF!,"*" & Index!$D$18 & "*",#REF!,"*" & Index!$D$17 & "*",#REF!,"*" & Index!$D$20 & "*") -> #REF! | V48: -95005 | W48: =+U48-V48 -> #REF! | X48: =IFERROR(IF(((U48/V48)-1)=0,"-",((U48/V48)-1)),"-") -> - | Y48: =SUMIFS(#REF!,#REF!,"*" & C48 & "*",#REF!,"*" & Index!$D$12 & "*")+ SUMIFS(#REF!,#REF!,"*" & C48 & "*",#REF!,"*" & Index!$D$18 & "*",#REF!,"*" & Index!$D$20 & "*") -> #REF! | Z48: 9275041 | AA48: =+Y48-Z48 -> #REF! | AB48: =IFERROR(IF(((Y48/Z48)-1)=0,"-",((Y48/Z48)-1)),"-") -> -
A49: =+LEN(C49) -> 8 | C49: NACE0502 | E49: =SUMIFS(#REF!,#REF!,"*" & C49 & "*",#REF!,"*" & Index!$D$12 & "*",#REF!,"*" & Index!$D$16 & "*")+SUMIFS(#REF!,#REF!,"*" & C49 & "*",#REF!,"*" & Index!$D$18 & "*",#REF!,"*" & Index!$D$20 & "*") -> #REF! | F49: 836950 | G49: =+E49-F49 -> #REF! | H49: =IFERROR(IF(((E49/F49)-1)=0,"-",((E49/F49)-1)),"-") -> - | I49: =+E49-M49-Q49 -> #REF! | J49: 789415 | K49: =+I49-J49 -> #REF! | L49: =IFERROR(IF(((I49/J49)-1)=0,"-",((I49/J49)-1)),"-") -> - | M49: =SUMIFS(#REF!,#REF!,"*" & $C49 & "*",#REF!,"*" & Index!$D$12 & "*",#REF!,"*" & Index!$D$23 & "*",#REF!,"*" & Index!$D$16 & "*") + SUMIFS(#REF!,#REF!,"*" & $C49 & "*",#REF!,"*" & Index!$D$18 & "*",#REF!,"*" & Index!$D$23 & "*",#REF!,"*" & Index!$D$16 & "*",#REF!,"*" & Index!$D$20 & "*") -> #REF! | N49: 21857 | O49: =+M49-N49 -> #REF! | P49: =IFERROR(IF(((M49/N49)-1)=0,"-",((M49/N49)-1)),"-") -> - | Q49: =SUMIFS(#REF!,#REF!,"*" & $C49 & "*",#REF!,"*" & Index!$D$12 & "*",#REF!,"*" & Index!$D$24 & "*",#REF!,"*" & Index!$D$16 & "*") + SUMIFS(#REF!,#REF!,"*" & $C49 & "*",#REF!,"*" & Index!$D$18 & "*",#REF!,"*" & Index!$D$24 & "*",#REF!,"*" & Index!$D$16 & "*",#REF!,"*" & Index!$D$20 & "*") -> #REF! | R49: 25678 | S49: =+Q49-R49 -> #REF! | T49: =IFERROR(IF(((Q49/R49)-1)=0,"-",((Q49/R49)-1)),"-") -> - | U49: =SUMIFS(#REF!,#REF!,"*" & C49 &"*",#REF!,"*" & Index!$D$12 & "*",#REF!,"*" & Index!$D$17 & "*")+SUMIFS(#REF!,#REF!,"*" & C49 &"*",#REF!,"*" & Index!$D$18 & "*",#REF!,"*" & Index!$D$17 & "*",#REF!,"*" & Index!$D$20 & "*") -> #REF! | V49: -17611 | W49: =+U49-V49 -> #REF! | X49: =IFERROR(IF(((U49/V49)-1)=0,"-",((U49/V49)-1)),"-") -> - | Y49: =SUMIFS(#REF!,#REF!,"*" & C49 & "*",#REF!,"*" & Index!$D$12 & "*")+ SUMIFS(#REF!,#REF!,"*" & C49 & "*",#REF!,"*" & Index!$D$18 & "*",#REF!,"*" & Index!$D$20 & "*") -> #REF! | Z49: 819339 | AA49: =+Y49-Z49 -> #REF! | AB49: =IFERROR(IF(((Y49/Z49)-1)=0,"-",((Y49/Z49)-1)),"-") -> -
A50: =+LEN(C50) -> 8 | C50: NACE0503 | E50: =SUMIFS(#REF!,#REF!,"*" & C50 & "*",#REF!,"*" & Index!$D$12 & "*",#REF!,"*" & Index!$D$16 & "*")+SUMIFS(#REF!,#REF!,"*" & C50 & "*",#REF!,"*" & Index!$D$18 & "*",#REF!,"*" & Index!$D$20 & "*") -> #REF! | F50: 39642112 | G50: =+E50-F50 -> #REF! | H50: =IFERROR(IF(((E50/F50)-1)=0,"-",((E50/F50)-1)),"-") -> - | I50: =+E50-M50-Q50 -> #REF! | J50: 24468727 | K50: =+I50-J50 -> #REF! | L50: =IFERROR(IF(((I50/J50)-1)=0,"-",((I50/J50)-1)),"-") -> - | M50: =SUMIFS(#REF!,#REF!,"*" & $C50 & "*",#REF!,"*" & Index!$D$12 & "*",#REF!,"*" & Index!$D$23 & "*",#REF!,"*" & Index!$D$16 & "*") + SUMIFS(#REF!,#REF!,"*" & $C50 & "*",#REF!,"*" & Index!$D$18 & "*",#REF!,"*" & Index!$D$23 & "*",#REF!,"*" & Index!$D$16 & "*",#REF!,"*" & Index!$D$20 & "*") -> #REF! | N50: 13417296 | O50: =+M50-N50 -> #REF! | P50: =IFERROR(IF(((M50/N50)-1)=0,"-",((M50/N50)-1)),"-") -> - | Q50: =SUMIFS(#REF!,#REF!,"*" & $C50 & "*",#REF!,"*" & Index!$D$12 & "*",#REF!,"*" & Index!$D$24 & "*",#REF!,"*" & Index!$D$16 & "*") + SUMIFS(#REF!,#REF!,"*" & $C50 & "*",#REF!,"*" & Index!$D$18 & "*",#REF!,"*" & Index!$D$24 & "*",#REF!,"*" & Index!$D$16 & "*",#REF!,"*" & Index!$D$20 & "*") -> #REF! | R50: 1756089 | S50: =+Q50-R50 -> #REF! | T50: =IFERROR(IF(((Q50/R50)-1)=0,"-",((Q50/R50)-1)),"-") -> - | U50: =SUMIFS(#REF!,#REF!,"*" & C50 &"*",#REF!,"*" & Index!$D$12 & "*",#REF!,"*" & Index!$D$17 & "*")+SUMIFS(#REF!,#REF!,"*" & C50 &"*",#REF!,"*" & Index!$D$18 & "*",#REF!,"*" & Index!$D$17 & "*",#REF!,"*" & Index!$D$20 & "*") -> #REF! | V50: -1455612 | W50: =+U50-V50 -> #REF! | X50: =IFERROR(IF(((U50/V50)-1)=0,"-",((U50/V50)-1)),"-") -> - | Y50: =SUMIFS(#REF!,#REF!,"*" & C50 & "*",#REF!,"*" & Index!$D$12 & "*")+ SUMIFS(#REF!,#REF!,"*" & C50 & "*",#REF!,"*" & Index!$D$18 & "*",#REF!,"*" & Index!$D$20 & "*") -> #REF! | Z50: 38186500 | AA50: =+Y50-Z50 -> #REF! | AB50: =IFERROR(IF(((Y50/Z50)-1)=0,"-",((Y50/Z50)-1)),"-") -> -
A51: =+LEN(C51) -> 8 | C51: NACE0504 | E51: =SUMIFS(#REF!,#REF!,"*" & C51 & "*",#REF!,"*" & Index!$D$12 & "*",#REF!,"*" & Index!$D$16 & "*")+SUMIFS(#REF!,#REF!,"*" & C51 & "*",#REF!,"*" & Index!$D$18 & "*",#REF!,"*" & Index!$D$20 & "*") -> #REF! | F51: 332 | G51: =+E51-F51 -> #REF! | H51: =IFERROR(IF(((E51/F51)-1)=0,"-",((E51/F51)-1)),"-") -> - | I51: =+E51-M51-Q51 -> #REF! | J51: 4 | K51: =+I51-J51 -> #REF! | L51: =IFERROR(IF(((I51/J51)-1)=0,"-",((I51/J51)-1)),"-") -> - | M51: =SUMIFS(#REF!,#REF!,"*" & $C51 & "*",#REF!,"*" & Index!$D$12 & "*",#REF!,"*" & Index!$D$23 & "*",#REF!,"*" & Index!$D$16 & "*") + SUMIFS(#REF!,#REF!,"*" & $C51 & "*",#REF!,"*" & Index!$D$18 & "*",#REF!,"*" & Index!$D$23 & "*",#REF!,"*" & Index!$D$16 & "*",#REF!,"*" & Index!$D$20 & "*") -> #REF! | N51: 0 | O51: =+M51-N51 -> #REF! | P51: =IFERROR(IF(((M51/N51)-1)=0,"-",((M51/N51)-1)),"-") -> - | Q51: =SUMIFS(#REF!,#REF!,"*" & $C51 & "*",#REF!,"*" & Index!$D$12 & "*",#REF!,"*" & Index!$D$24 & "*",#REF!,"*" & Index!$D$16 & "*") + SUMIFS(#REF!,#REF!,"*" & $C51 & "*",#REF!,"*" & Index!$D$18 & "*",#REF!,"*" & Index!$D$24 & "*",#REF!,"*" & Index!$D$16 & "*",#REF!,"*" & Index!$D$20 & "*") -> #REF! | R51: 328 | S51: =+Q51-R51 -> #REF! | T51: =IFERROR(IF(((Q51/R51)-1)=0,"-",((Q51/R51)-1)),"-") -> - | U51: =SUMIFS(#REF!,#REF!,"*" & C51 &"*",#REF!,"*" & Index!$D$12 & "*",#REF!,"*" & Index!$D$17 & "*")+SUMIFS(#REF!,#REF!,"*" & C51 &"*",#REF!,"*" & Index!$D$18 & "*",#REF!,"*" & Index!$D$17 & "*",#REF!,"*" & Index!$D$20 & "*") -> #REF! | V51: -272 | W51: =+U51-V51 -> #REF! | X51: =IFERROR(IF(((U51/V51)-1)=0,"-",((U51/V51)-1)),"-") -> - | Y51: =SUMIFS(#REF!,#REF!,"*" & C51 & "*",#REF!,"*" & Index!$D$12 & "*")+ SUMIFS(#REF!,#REF!,"*" & C51 & "*",#REF!,"*" & Index!$D$18 & "*",#REF!,"*" & Index!$D$20 & "*") -> #REF! | Z51: 60 | AA51: =+Y51-Z51 -> #REF! | AB51: =IFERROR(IF(((Y51/Z51)-1)=0,"-",((Y51/Z51)-1)),"-") -> -
A52: =+LEN(C52) -> 6 | C52: NACE06 | D52: Construction | E52: =SUMIFS(#REF!,#REF!,"*" & C52 & "*",#REF!,"*" & Index!$D$12 & "*",#REF!,"*" & Index!$D$16 & "*")+SUMIFS(#REF!,#REF!,"*" & C52 & "*",#REF!,"*" & Index!$D$18 & "*",#REF!,"*" & Index!$D$20 & "*",#REF!,"*" & Index!$D$16 & "*") -> #REF! | F52: 927972980 | G52: =+E52-F52 -> #REF! | H52: =IFERROR(IF(((E52/F52)-1)=0,"-",((E52/F52)-1)),"-") -> - | I52: =+E52-M52-Q52 -> #REF! | J52: 797445535 | K52: =+I52-J52 -> #REF! | L52: =IFERROR(IF(((I52/J52)-1)=0,"-",((I52/J52)-1)),"-") -> - | M52: =SUMIFS(#REF!,#REF!,"*" & $C52 & "*",#REF!,"*" & Index!$D$12 & "*",#REF!,"*" & Index!$D$23 & "*",#REF!,"*" & Index!$D$16 & "*") + SUMIFS(#REF!,#REF!,"*" & $C52 & "*",#REF!,"*" & Index!$D$18 & "*",#REF!,"*" & Index!$D$23 & "*",#REF!,"*" & Index!$D$16 & "*",#REF!,"*" & Index!$D$20 & "*") -> #REF! | N52: 76446539 | O52: =+M52-N52 -> #REF! | P52: =IFERROR(IF(((M52/N52)-1)=0,"-",((M52/N52)-1)),"-") -> - | Q52: =SUMIFS(#REF!,#REF!,"*" & $C52 & "*",#REF!,"*" & Index!$D$12 & "*",#REF!,"*" & Index!$D$24 & "*",#REF!,"*" & Index!$D$16 & "*") + SUMIFS(#REF!,#REF!,"*" & $C52 & "*",#REF!,"*" & Index!$D$18 & "*",#REF!,"*" & Index!$D$24 & "*",#REF!,"*" & Index!$D$16 & "*",#REF!,"*" & Index!$D$20 & "*") -> #REF! | R52: 54080906 | S52: =+Q52-R52 -> #REF! | T52: =IFERROR(IF(((Q52/R52)-1)=0,"-",((Q52/R52)-1)),"-") -> - | U52: =SUMIFS(#REF!,#REF!,"*" & C52 &"*",#REF!,"*" & Index!$D$12 & "*",#REF!,"*" & Index!$D$17 & "*")+SUMIFS(#REF!,#REF!,"*" & C52 &"*",#REF!,"*" & Index!$D$18 & "*",#REF!,"*" & Index!$D$17 & "*",#REF!,"*" & Index!$D$20 & "*") -> #REF! | V52: -53281851 | W52: =+U52-V52 -> #REF! | X52: =IFERROR(IF(((U52/V52)-1)=0,"-",((U52/V52)-1)),"-") -> - | Y52: =SUMIFS(#REF!,#REF!,"*" & C52 & "*",#REF!,"*" & Index!$D$12 & "*")+ SUMIFS(#REF!,#REF!,"*" & C52 & "*",#REF!,"*" & Index!$D$18 & "*",#REF!,"*" & Index!$D$20 & "*") -> #REF! | Z52: 884691129 | AA52: =+Y52-Z52 -> #REF! | AB52: =IFERROR(IF(((Y52/Z52)-1)=0,"-",((Y52/Z52)-1)),"-") -> -
A53: =+LEN(C53) -> 8 | C53: NACE0601 | E53: =SUMIFS(#REF!,#REF!,"*" & C53 & "*",#REF!,"*" & Index!$D$12 & "*",#REF!,"*" & Index!$D$16 & "*")+SUMIFS(#REF!,#REF!,"*" & C53 & "*",#REF!,"*" & Index!$D$18 & "*",#REF!,"*" & Index!$D$20 & "*") -> #REF! | F53: 625937026 | G53: =+E53-F53 -> #REF! | H53: =IFERROR(IF(((E53/F53)-1)=0,"-",((E53/F53)-1)),"-") -> - | I53: =+E53-M53-Q53 -> #REF! | J53: 531947071 | K53: =+I53-J53 -> #REF! | L53: =IFERROR(IF(((I53/J53)-1)=0,"-",((I53/J53)-1)),"-") -> - | M53: =SUMIFS(#REF!,#REF!,"*" & $C53 & "*",#REF!,"*" & Index!$D$12 & "*",#REF!,"*" & Index!$D$23 & "*",#REF!,"*" & Index!$D$16 & "*") + SUMIFS(#REF!,#REF!,"*" & $C53 & "*",#REF!,"*" & Index!$D$18 & "*",#REF!,"*" & Index!$D$23 & "*",#REF!,"*" & Index!$D$16 & "*",#REF!,"*" & Index!$D$20 & "*") -> #REF! | N53: 46772479 | O53: =+M53-N53 -> #REF! | P53: =IFERROR(IF(((M53/N53)-1)=0,"-",((M53/N53)-1)),"-") -> - | Q53: =SUMIFS(#REF!,#REF!,"*" & $C53 & "*",#REF!,"*" & Index!$D$12 & "*",#REF!,"*" & Index!$D$24 & "*",#REF!,"*" & Index!$D$16 & "*") + SUMIFS(#REF!,#REF!,"*" & $C53 & "*",#REF!,"*" & Index!$D$18 & "*",#REF!,"*" & Index!$D$24 & "*",#REF!,"*" & Index!$D$16 & "*",#REF!,"*" & Index!$D$20 & "*") -> #REF! | R53: 47217476 | S53: =+Q53-R53 -> #REF! | T53: =IFERROR(IF(((Q53/R53)-1)=0,"-",((Q53/R53)-1)),"-") -> - | U53: =SUMIFS(#REF!,#REF!,"*" & C53 &"*",#REF!,"*" & Index!$D$12 & "*",#REF!,"*" & Index!$D$17 & "*")+SUMIFS(#REF!,#REF!,"*" & C53 &"*",#REF!,"*" & Index!$D$18 & "*",#REF!,"*" & Index!$D$17 & "*",#REF!,"*" & Index!$D$20 & "*") -> #REF! | V53: -45629657 | W53: =+U53-V53 -> #REF! | X53: =IFERROR(IF(((U53/V53)-1)=0,"-",((U53/V53)-1)),"-") -> - | Y53: =SUMIFS(#REF!,#REF!,"*" & C53 & "*",#REF!,"*" & Index!$D$12 & "*")+ SUMIFS(#REF!,#REF!,"*" & C53 & "*",#REF!,"*" & Index!$D$18 & "*",#REF!,"*" & Index!$D$20 & "*") -> #REF! | Z53: 590307369 | AA53: =+Y53-Z53 -> #REF! | AB53: =IFERROR(IF(((Y53/Z53)-1)=0,"-",((Y53/Z53)-1)),"-") -> -
A54: =+LEN(C54) -> 8 | C54: NACE0602 | E54: =SUMIFS(#REF!,#REF!,"*" & C54 & "*",#REF!,"*" & Index!$D$12 & "*",#REF!,"*" & Index!$D$16 & "*")+SUMIFS(#REF!,#REF!,"*" & C54 & "*",#REF!,"*" & Index!$D$18 & "*",#REF!,"*" & Index!$D$20 & "*") -> #REF! | F54: 151830349 | G54: =+E54-F54 -> #REF! | H54: =IFERROR(IF(((E54/F54)-1)=0,"-",((E54/F54)-1)),"-") -> - | I54: =+E54-M54-Q54 -> #REF! | J54: 143325812 | K54: =+I54-J54 -> #REF! | L54: =IFERROR(IF(((I54/J54)-1)=0,"-",((I54/J54)-1)),"-") -> - | M54: =SUMIFS(#REF!,#REF!,"*" & $C54 & "*",#REF!,"*" & Index!$D$12 & "*",#REF!,"*" & Index!$D$23 & "*",#REF!,"*" & Index!$D$16 & "*") + SUMIFS(#REF!,#REF!,"*" & $C54 & "*",#REF!,"*" & Index!$D$18 & "*",#REF!,"*" & Index!$D$23 & "*",#REF!,"*" & Index!$D$16 & "*",#REF!,"*" & Index!$D$20 & "*") -> #REF! | N54: 7063476 | O54: =+M54-N54 -> #REF! | P54: =IFERROR(IF(((M54/N54)-1)=0,"-",((M54/N54)-1)),"-") -> - | Q54: =SUMIFS(#REF!,#REF!,"*" & $C54 & "*",#REF!,"*" & Index!$D$12 & "*",#REF!,"*" & Index!$D$24 & "*",#REF!,"*" & Index!$D$16 & "*") + SUMIFS(#REF!,#REF!,"*" & $C54 & "*",#REF!,"*" & Index!$D$18 & "*",#REF!,"*" & Index!$D$24 & "*",#REF!,"*" & Index!$D$16 & "*",#REF!,"*" & Index!$D$20 & "*") -> #REF! | R54: 1441061 | S54: =+Q54-R54 -> #REF! | T54: =IFERROR(IF(((Q54/R54)-1)=0,"-",((Q54/R54)-1)),"-") -> - | U54: =SUMIFS(#REF!,#REF!,"*" & C54 &"*",#REF!,"*" & Index!$D$12 & "*",#REF!,"*" & Index!$D$17 & "*")+SUMIFS(#REF!,#REF!,"*" & C54 &"*",#REF!,"*" & Index!$D$18 & "*",#REF!,"*" & Index!$D$17 & "*",#REF!,"*" & Index!$D$20 & "*") -> #REF! | V54: -1706777 | W54: =+U54-V54 -> #REF! | X54: =IFERROR(IF(((U54/V54)-1)=0,"-",((U54/V54)-1)),"-") -> - | Y54: =SUMIFS(#REF!,#REF!,"*" & C54 & "*",#REF!,"*" & Index!$D$12 & "*")+ SUMIFS(#REF!,#REF!,"*" & C54 & "*",#REF!,"*" & Index!$D$18 & "*",#REF!,"*" & Index!$D$20 & "*") -> #REF! | Z54: 150123572 | AA54: =+Y54-Z54 -> #REF! | AB54: =IFERROR(IF(((Y54/Z54)-1)=0,"-",((Y54/Z54)-1)),"-") -> -
A55: =+LEN(C55) -> 8 | C55: NACE0603 | E55: =SUMIFS(#REF!,#REF!,"*" & C55 & "*",#REF!,"*" & Index!$D$12 & "*",#REF!,"*" & Index!$D$16 & "*")+SUMIFS(#REF!,#REF!,"*" & C55 & "*",#REF!,"*" & Index!$D$18 & "*",#REF!,"*" & Index!$D$20 & "*") -> #REF! | F55: 150205605 | G55: =+E55-F55 -> #REF! | H55: =IFERROR(IF(((E55/F55)-1)=0,"-",((E55/F55)-1)),"-") -> - | I55: =+E55-M55-Q55 -> #REF! | J55: 122172652 | K55: =+I55-J55 -> #REF! | L55: =IFERROR(IF(((I55/J55)-1)=0,"-",((I55/J55)-1)),"-") -> - | M55: =SUMIFS(#REF!,#REF!,"*" & $C55 & "*",#REF!,"*" & Index!$D$12 & "*",#REF!,"*" & Index!$D$23 & "*",#REF!,"*" & Index!$D$16 & "*") + SUMIFS(#REF!,#REF!,"*" & $C55 & "*",#REF!,"*" & Index!$D$18 & "*",#REF!,"*" & Index!$D$23 & "*",#REF!,"*" & Index!$D$16 & "*",#REF!,"*" & Index!$D$20 & "*") -> #REF! | N55: 22610584 | O55: =+M55-N55 -> #REF! | P55: =IFERROR(IF(((M55/N55)-1)=0,"-",((M55/N55)-1)),"-") -> - | Q55: =SUMIFS(#REF!,#REF!,"*" & $C55 & "*",#REF!,"*" & Index!$D$12 & "*",#REF!,"*" & Index!$D$24 & "*",#REF!,"*" & Index!$D$16 & "*") + SUMIFS(#REF!,#REF!,"*" & $C55 & "*",#REF!,"*" & Index!$D$18 & "*",#REF!,"*" & Index!$D$24 & "*",#REF!,"*" & Index!$D$16 & "*",#REF!,"*" & Index!$D$20 & "*") -> #REF! | R55: 5422369 | S55: =+Q55-R55 -> #REF! | T55: =IFERROR(IF(((Q55/R55)-1)=0,"-",((Q55/R55)-1)),"-") -> - | U55: =SUMIFS(#REF!,#REF!,"*" & C55 &"*",#REF!,"*" & Index!$D$12 & "*",#REF!,"*" & Index!$D$17 & "*")+SUMIFS(#REF!,#REF!,"*" & C55 &"*",#REF!,"*" & Index!$D$18 & "*",#REF!,"*" & Index!$D$17 & "*",#REF!,"*" & Index!$D$20 & "*") -> #REF! | V55: -5945417 | W55: =+U55-V55 -> #REF! | X55: =IFERROR(IF(((U55/V55)-1)=0,"-",((U55/V55)-1)),"-") -> - | Y55: =SUMIFS(#REF!,#REF!,"*" & C55 & "*",#REF!,"*" & Index!$D$12 & "*")+ SUMIFS(#REF!,#REF!,"*" & C55 & "*",#REF!,"*" & Index!$D$18 & "*",#REF!,"*" & Index!$D$20 & "*") -> #REF! | Z55: 144260188 | AA55: =+Y55-Z55 -> #REF! | AB55: =IFERROR(IF(((Y55/Z55)-1)=0,"-",((Y55/Z55)-1)),"-") -> -
A56: =+LEN(C56) -> 6 | C56: NACE07 | D56: Wholesale and retail trade; repair of motor vehicles and motorcycles | E56: =SUMIFS(#REF!,#REF!,"*" & C56 & "*",#REF!,"*" & Index!$D$12 & "*",#REF!,"*" & Index!$D$16 & "*")+SUMIFS(#REF!,#REF!,"*" & C56 & "*",#REF!,"*" & Index!$D$18 & "*",#REF!,"*" & Index!$D$20 & "*",#REF!,"*" & Index!$D$16 & "*") -> #REF! | F56: 1988414008 | G56: =+E56-F56 -> #REF! | H56: =IFERROR(IF(((E56/F56)-1)=0,"-",((E56/F56)-1)),"-") -> - | I56: =+E56-M56-Q56 -> #REF! | J56: 1709922608 | K56: =+I56-J56 -> #REF! | L56: =IFERROR(IF(((I56/J56)-1)=0,"-",((I56/J56)-1)),"-") -> - | M56: =SUMIFS(#REF!,#REF!,"*" & $C56 & "*",#REF!,"*" & Index!$D$12 & "*",#REF!,"*" & Index!$D$23 & "*",#REF!,"*" & Index!$D$16 & "*") + SUMIFS(#REF!,#REF!,"*" & $C56 & "*",#REF!,"*" & Index!$D$18 & "*",#REF!,"*" & Index!$D$23 & "*",#REF!,"*" & Index!$D$16 & "*",#REF!,"*" & Index!$D$20 & "*") -> #REF! | N56: 212963369 | O56: =+M56-N56 -> #REF! | P56: =IFERROR(IF(((M56/N56)-1)=0,"-",((M56/N56)-1)),"-") -> - | Q56: =SUMIFS(#REF!,#REF!,"*" & $C56 & "*",#REF!,"*" & Index!$D$12 & "*",#REF!,"*" & Index!$D$24 & "*",#REF!,"*" & Index!$D$16 & "*") + SUMIFS(#REF!,#REF!,"*" & $C56 & "*",#REF!,"*" & Index!$D$18 & "*",#REF!,"*" & Index!$D$24 & "*",#REF!,"*" & Index!$D$16 & "*",#REF!,"*" & Index!$D$20 & "*") -> #REF! | R56: 65528031 | S56: =+Q56-R56 -> #REF! | T56: =IFERROR(IF(((Q56/R56)-1)=0,"-",((Q56/R56)-1)),"-") -> - | U56: =SUMIFS(#REF!,#REF!,"*" & C56 &"*",#REF!,"*" & Index!$D$12 & "*",#REF!,"*" & Index!$D$17 & "*")+SUMIFS(#REF!,#REF!,"*" & C56 &"*",#REF!,"*" & Index!$D$18 & "*",#REF!,"*" & Index!$D$17 & "*",#REF!,"*" & Index!$D$20 & "*") -> #REF! | V56: -63291086 | W56: =+U56-V56 -> #REF! | X56: =IFERROR(IF(((U56/V56)-1)=0,"-",((U56/V56)-1)),"-") -> - | Y56: =SUMIFS(#REF!,#REF!,"*" & C56 & "*",#REF!,"*" & Index!$D$12 & "*")+ SUMIFS(#REF!,#REF!,"*" & C56 & "*",#REF!,"*" & Index!$D$18 & "*",#REF!,"*" & Index!$D$20 & "*") -> #REF! | Z56: 1925122922 | AA56: =+Y56-Z56 -> #REF! | AB56: =IFERROR(IF(((Y56/Z56)-1)=0,"-",((Y56/Z56)-1)),"-") -> -
A57: =+LEN(C57) -> 8 | C57: NACE0701 | E57: =SUMIFS(#REF!,#REF!,"*" & C57 & "*",#REF!,"*" & Index!$D$12 & "*",#REF!,"*" & Index!$D$16 & "*")+SUMIFS(#REF!,#REF!,"*" & C57 & "*",#REF!,"*" & Index!$D$18 & "*",#REF!,"*" & Index!$D$20 & "*") -> #REF! | F57: 253982469 | G57: =+E57-F57 -> #REF! | H57: =IFERROR(IF(((E57/F57)-1)=0,"-",((E57/F57)-1)),"-") -> - | I57: =+E57-M57-Q57 -> #REF! | J57: 216728826 | K57: =+I57-J57 -> #REF! | L57: =IFERROR(IF(((I57/J57)-1)=0,"-",((I57/J57)-1)),"-") -> - | M57: =SUMIFS(#REF!,#REF!,"*" & $C57 & "*",#REF!,"*" & Index!$D$12 & "*",#REF!,"*" & Index!$D$23 & "*",#REF!,"*" & Index!$D$16 & "*") + SUMIFS(#REF!,#REF!,"*" & $C57 & "*",#REF!,"*" & Index!$D$18 & "*",#REF!,"*" & Index!$D$23 & "*",#REF!,"*" & Index!$D$16 & "*",#REF!,"*" & Index!$D$20 & "*") -> #REF! | N57: 33305775 | O57: =+M57-N57 -> #REF! | P57: =IFERROR(IF(((M57/N57)-1)=0,"-",((M57/N57)-1)),"-") -> - | Q57: =SUMIFS(#REF!,#REF!,"*" & $C57 & "*",#REF!,"*" & Index!$D$12 & "*",#REF!,"*" & Index!$D$24 & "*",#REF!,"*" & Index!$D$16 & "*") + SUMIFS(#REF!,#REF!,"*" & $C57 & "*",#REF!,"*" & Index!$D$18 & "*",#REF!,"*" & Index!$D$24 & "*",#REF!,"*" & Index!$D$16 & "*",#REF!,"*" & Index!$D$20 & "*") -> #REF! | R57: 3947868 | S57: =+Q57-R57 -> #REF! | T57: =IFERROR(IF(((Q57/R57)-1)=0,"-",((Q57/R57)-1)),"-") -> - | U57: =SUMIFS(#REF!,#REF!,"*" & C57 &"*",#REF!,"*" & Index!$D$12 & "*",#REF!,"*" & Index!$D$17 & "*")+SUMIFS(#REF!,#REF!,"*" & C57 &"*",#REF!,"*" & Index!$D$18 & "*",#REF!,"*" & Index!$D$17 & "*",#REF!,"*" & Index!$D$20 & "*") -> #REF! | V57: -5880047 | W57: =+U57-V57 -> #REF! | X57: =IFERROR(IF(((U57/V57)-1)=0,"-",((U57/V57)-1)),"-") -> - | Y57: =SUMIFS(#REF!,#REF!,"*" & C57 & "*",#REF!,"*" & Index!$D$12 & "*")+ SUMIFS(#REF!,#REF!,"*" & C57 & "*",#REF!,"*" & Index!$D$18 & "*",#REF!,"*" & Index!$D$20 & "*") -> #REF! | Z57: 248102422 | AA57: =+Y57-Z57 -> #REF! | AB57: =IFERROR(IF(((Y57/Z57)-1)=0,"-",((Y57/Z57)-1)),"-") -> -
A58: =+LEN(C58) -> 8 | C58: NACE0702 | E58: =SUMIFS(#REF!,#REF!,"*" & C58 & "*",#REF!,"*" & Index!$D$12 & "*",#REF!,"*" & Index!$D$16 & "*")+SUMIFS(#REF!,#REF!,"*" & C58 & "*",#REF!,"*" & Index!$D$18 & "*",#REF!,"*" & Index!$D$20 & "*") -> #REF! | F58: 845378484 | G58: =+E58-F58 -> #REF! | H58: =IFERROR(IF(((E58/F58)-1)=0,"-",((E58/F58)-1)),"-") -> - | I58: =+E58-M58-Q58 -> #REF! | J58: 715806376 | K58: =+I58-J58 -> #REF! | L58: =IFERROR(IF(((I58/J58)-1)=0,"-",((I58/J58)-1)),"-") -> - | M58: =SUMIFS(#REF!,#REF!,"*" & $C58 & "*",#REF!,"*" & Index!$D$12 & "*",#REF!,"*" & Index!$D$23 & "*",#REF!,"*" & Index!$D$16 & "*") + SUMIFS(#REF!,#REF!,"*" & $C58 & "*",#REF!,"*" & Index!$D$18 & "*",#REF!,"*" & Index!$D$23 & "*",#REF!,"*" & Index!$D$16 & "*",#REF!,"*" & Index!$D$20 & "*") -> #REF! | N58: 100466576 | O58: =+M58-N58 -> #REF! | P58: =IFERROR(IF(((M58/N58)-1)=0,"-",((M58/N58)-1)),"-") -> - | Q58: =SUMIFS(#REF!,#REF!,"*" & $C58 & "*",#REF!,"*" & Index!$D$12 & "*",#REF!,"*" & Index!$D$24 & "*",#REF!,"*" & Index!$D$16 & "*") + SUMIFS(#REF!,#REF!,"*" & $C58 & "*",#REF!,"*" & Index!$D$18 & "*",#REF!,"*" & Index!$D$24 & "*",#REF!,"*" & Index!$D$16 & "*",#REF!,"*" & Index!$D$20 & "*") -> #REF! | R58: 29105532 | S58: =+Q58-R58 -> #REF! | T58: =IFERROR(IF(((Q58/R58)-1)=0,"-",((Q58/R58)-1)),"-") -> - | U58: =SUMIFS(#REF!,#REF!,"*" & C58 &"*",#REF!,"*" & Index!$D$12 & "*",#REF!,"*" & Index!$D$17 & "*")+SUMIFS(#REF!,#REF!,"*" & C58 &"*",#REF!,"*" & Index!$D$18 & "*",#REF!,"*" & Index!$D$17 & "*",#REF!,"*" & Index!$D$20 & "*") -> #REF! | V58: -32311522 | W58: =+U58-V58 -> #REF! | X58: =IFERROR(IF(((U58/V58)-1)=0,"-",((U58/V58)-1)),"-") -> - | Y58: =SUMIFS(#REF!,#REF!,"*" & C58 & "*",#REF!,"*" & Index!$D$12 & "*")+ SUMIFS(#REF!,#REF!,"*" & C58 & "*",#REF!,"*" & Index!$D$18 & "*",#REF!,"*" & Index!$D$20 & "*") -> #REF! | Z58: 813066962 | AA58: =+Y58-Z58 -> #REF! | AB58: =IFERROR(IF(((Y58/Z58)-1)=0,"-",((Y58/Z58)-1)),"-") -> -
A59: =+LEN(C59) -> 8 | C59: NACE0703 | E59: =SUMIFS(#REF!,#REF!,"*" & C59 & "*",#REF!,"*" & Index!$D$12 & "*",#REF!,"*" & Index!$D$16 & "*")+SUMIFS(#REF!,#REF!,"*" & C59 & "*",#REF!,"*" & Index!$D$18 & "*",#REF!,"*" & Index!$D$20 & "*") -> #REF! | F59: 889053055 | G59: =+E59-F59 -> #REF! | H59: =IFERROR(IF(((E59/F59)-1)=0,"-",((E59/F59)-1)),"-") -> - | I59: =+E59-M59-Q59 -> #REF! | J59: 777387406 | K59: =+I59-J59 -> #REF! | L59: =IFERROR(IF(((I59/J59)-1)=0,"-",((I59/J59)-1)),"-") -> - | M59: =SUMIFS(#REF!,#REF!,"*" & $C59 & "*",#REF!,"*" & Index!$D$12 & "*",#REF!,"*" & Index!$D$23 & "*",#REF!,"*" & Index!$D$16 & "*") + SUMIFS(#REF!,#REF!,"*" & $C59 & "*",#REF!,"*" & Index!$D$18 & "*",#REF!,"*" & Index!$D$23 & "*",#REF!,"*" & Index!$D$16 & "*",#REF!,"*" & Index!$D$20 & "*") -> #REF! | N59: 79191018 | O59: =+M59-N59 -> #REF! | P59: =IFERROR(IF(((M59/N59)-1)=0,"-",((M59/N59)-1)),"-") -> - | Q59: =SUMIFS(#REF!,#REF!,"*" & $C59 & "*",#REF!,"*" & Index!$D$12 & "*",#REF!,"*" & Index!$D$24 & "*",#REF!,"*" & Index!$D$16 & "*") + SUMIFS(#REF!,#REF!,"*" & $C59 & "*",#REF!,"*" & Index!$D$18 & "*",#REF!,"*" & Index!$D$24 & "*",#REF!,"*" & Index!$D$16 & "*",#REF!,"*" & Index!$D$20 & "*") -> #REF! | R59: 32474631 | S59: =+Q59-R59 -> #REF! | T59: =IFERROR(IF(((Q59/R59)-1)=0,"-",((Q59/R59)-1)),"-") -> - | U59: =SUMIFS(#REF!,#REF!,"*" & C59 &"*",#REF!,"*" & Index!$D$12 & "*",#REF!,"*" & Index!$D$17 & "*")+SUMIFS(#REF!,#REF!,"*" & C59 &"*",#REF!,"*" & Index!$D$18 & "*",#REF!,"*" & Index!$D$17 & "*",#REF!,"*" & Index!$D$20 & "*") -> #REF! | V59: -25099517 | W59: =+U59-V59 -> #REF! | X59: =IFERROR(IF(((U59/V59)-1)=0,"-",((U59/V59)-1)),"-") -> - | Y59: =SUMIFS(#REF!,#REF!,"*" & C59 & "*",#REF!,"*" & Index!$D$12 & "*")+ SUMIFS(#REF!,#REF!,"*" & C59 & "*",#REF!,"*" & Index!$D$18 & "*",#REF!,"*" & Index!$D$20 & "*") -> #REF! | Z59: 863953538 | AA59: =+Y59-Z59 -> #REF! | AB59: =IFERROR(IF(((Y59/Z59)-1)=0,"-",((Y59/Z59)-1)),"-") -> -
A60: =+LEN(C60) -> 6 | C60: NACE08 | D60: Transporting and storage | E60: =SUMIFS(#REF!,#REF!,"*" & C60 & "*",#REF!,"*" & Index!$D$12 & "*",#REF!,"*" & Index!$D$16 & "*")+SUMIFS(#REF!,#REF!,"*" & C60 & "*",#REF!,"*" & Index!$D$18 & "*",#REF!,"*" & Index!$D$20 & "*",#REF!,"*" & Index!$D$16 & "*") -> #REF! | F60: 725757727 | G60: =+E60-F60 -> #REF! | H60: =IFERROR(IF(((E60/F60)-1)=0,"-",((E60/F60)-1)),"-") -> - | I60: =+E60-M60-Q60 -> #REF! | J60: 629997250 | K60: =+I60-J60 -> #REF! | L60: =IFERROR(IF(((I60/J60)-1)=0,"-",((I60/J60)-1)),"-") -> - | M60: =SUMIFS(#REF!,#REF!,"*" & $C60 & "*",#REF!,"*" & Index!$D$12 & "*",#REF!,"*" & Index!$D$23 & "*",#REF!,"*" & Index!$D$16 & "*") + SUMIFS(#REF!,#REF!,"*" & $C60 & "*",#REF!,"*" & Index!$D$18 & "*",#REF!,"*" & Index!$D$23 & "*",#REF!,"*" & Index!$D$16 & "*",#REF!,"*" & Index!$D$20 & "*") -> #REF! | N60: 47327454 | O60: =+M60-N60 -> #REF! | P60: =IFERROR(IF(((M60/N60)-1)=0,"-",((M60/N60)-1)),"-") -> - | Q60: =SUMIFS(#REF!,#REF!,"*" & $C60 & "*",#REF!,"*" & Index!$D$12 & "*",#REF!,"*" & Index!$D$24 & "*",#REF!,"*" & Index!$D$16 & "*") + SUMIFS(#REF!,#REF!,"*" & $C60 & "*",#REF!,"*" & Index!$D$18 & "*",#REF!,"*" & Index!$D$24 & "*",#REF!,"*" & Index!$D$16 & "*",#REF!,"*" & Index!$D$20 & "*") -> #REF! | R60: 48433023 | S60: =+Q60-R60 -> #REF! | T60: =IFERROR(IF(((Q60/R60)-1)=0,"-",((Q60/R60)-1)),"-") -> - | U60: =SUMIFS(#REF!,#REF!,"*" & C60 &"*",#REF!,"*" & Index!$D$12 & "*",#REF!,"*" & Index!$D$17 & "*")+SUMIFS(#REF!,#REF!,"*" & C60 &"*",#REF!,"*" & Index!$D$18 & "*",#REF!,"*" & Index!$D$17 & "*",#REF!,"*" & Index!$D$20 & "*") -> #REF! | V60: -34530816 | W60: =+U60-V60 -> #REF! | X60: =IFERROR(IF(((U60/V60)-1)=0,"-",((U60/V60)-1)),"-") -> - | Y60: =SUMIFS(#REF!,#REF!,"*" & C60 & "*",#REF!,"*" & Index!$D$12 & "*")+ SUMIFS(#REF!,#REF!,"*" & C60 & "*",#REF!,"*" & Index!$D$18 & "*",#REF!,"*" & Index!$D$20 & "*") -> #REF! | Z60: 691226911 | AA60: =+Y60-Z60 -> #REF! | AB60: =IFERROR(IF(((Y60/Z60)-1)=0,"-",((Y60/Z60)-1)),"-") -> -
A61: =+LEN(C61) -> 8 | C61: NACE0801 | E61: =SUMIFS(#REF!,#REF!,"*" & C61 & "*",#REF!,"*" & Index!$D$12 & "*",#REF!,"*" & Index!$D$16 & "*")+SUMIFS(#REF!,#REF!,"*" & C61 & "*",#REF!,"*" & Index!$D$18 & "*",#REF!,"*" & Index!$D$20 & "*") -> #REF! | F61: 294134549 | G61: =+E61-F61 -> #REF! | H61: =IFERROR(IF(((E61/F61)-1)=0,"-",((E61/F61)-1)),"-") -> - | I61: =+E61-M61-Q61 -> #REF! | J61: 244416168 | K61: =+I61-J61 -> #REF! | L61: =IFERROR(IF(((I61/J61)-1)=0,"-",((I61/J61)-1)),"-") -> - | M61: =SUMIFS(#REF!,#REF!,"*" & $C61 & "*",#REF!,"*" & Index!$D$12 & "*",#REF!,"*" & Index!$D$23 & "*",#REF!,"*" & Index!$D$16 & "*") + SUMIFS(#REF!,#REF!,"*" & $C61 & "*",#REF!,"*" & Index!$D$18 & "*",#REF!,"*" & Index!$D$23 & "*",#REF!,"*" & Index!$D$16 & "*",#REF!,"*" & Index!$D$20 & "*") -> #REF! | N61: 40816858 | O61: =+M61-N61 -> #REF! | P61: =IFERROR(IF(((M61/N61)-1)=0,"-",((M61/N61)-1)),"-") -> - | Q61: =SUMIFS(#REF!,#REF!,"*" & $C61 & "*",#REF!,"*" & Index!$D$12 & "*",#REF!,"*" & Index!$D$24 & "*",#REF!,"*" & Index!$D$16 & "*") + SUMIFS(#REF!,#REF!,"*" & $C61 & "*",#REF!,"*" & Index!$D$18 & "*",#REF!,"*" & Index!$D$24 & "*",#REF!,"*" & Index!$D$16 & "*",#REF!,"*" & Index!$D$20 & "*") -> #REF! | R61: 8901523 | S61: =+Q61-R61 -> #REF! | T61: =IFERROR(IF(((Q61/R61)-1)=0,"-",((Q61/R61)-1)),"-") -> - | U61: =SUMIFS(#REF!,#REF!,"*" & C61 &"*",#REF!,"*" & Index!$D$12 & "*",#REF!,"*" & Index!$D$17 & "*")+SUMIFS(#REF!,#REF!,"*" & C61 &"*",#REF!,"*" & Index!$D$18 & "*",#REF!,"*" & Index!$D$17 & "*",#REF!,"*" & Index!$D$20 & "*") -> #REF! | V61: -9615919 | W61: =+U61-V61 -> #REF! | X61: =IFERROR(IF(((U61/V61)-1)=0,"-",((U61/V61)-1)),"-") -> - | Y61: =SUMIFS(#REF!,#REF!,"*" & C61 & "*",#REF!,"*" & Index!$D$12 & "*")+ SUMIFS(#REF!,#REF!,"*" & C61 & "*",#REF!,"*" & Index!$D$18 & "*",#REF!,"*" & Index!$D$20 & "*") -> #REF! | Z61: 284518630 | AA61: =+Y61-Z61 -> #REF! | AB61: =IFERROR(IF(((Y61/Z61)-1)=0,"-",((Y61/Z61)-1)),"-") -> -
A62: =+LEN(C62) -> 8 | C62: NACE0802 | E62: =SUMIFS(#REF!,#REF!,"*" & C62 & "*",#REF!,"*" & Index!$D$12 & "*",#REF!,"*" & Index!$D$16 & "*")+SUMIFS(#REF!,#REF!,"*" & C62 & "*",#REF!,"*" & Index!$D$18 & "*",#REF!,"*" & Index!$D$20 & "*") -> #REF! | F62: 5340094 | G62: =+E62-F62 -> #REF! | H62: =IFERROR(IF(((E62/F62)-1)=0,"-",((E62/F62)-1)),"-") -> - | I62: =+E62-M62-Q62 -> #REF! | J62: 5043276 | K62: =+I62-J62 -> #REF! | L62: =IFERROR(IF(((I62/J62)-1)=0,"-",((I62/J62)-1)),"-") -> - | M62: =SUMIFS(#REF!,#REF!,"*" & $C62 & "*",#REF!,"*" & Index!$D$12 & "*",#REF!,"*" & Index!$D$23 & "*",#REF!,"*" & Index!$D$16 & "*") + SUMIFS(#REF!,#REF!,"*" & $C62 & "*",#REF!,"*" & Index!$D$18 & "*",#REF!,"*" & Index!$D$23 & "*",#REF!,"*" & Index!$D$16 & "*",#REF!,"*" & Index!$D$20 & "*") -> #REF! | N62: 276253 | O62: =+M62-N62 -> #REF! | P62: =IFERROR(IF(((M62/N62)-1)=0,"-",((M62/N62)-1)),"-") -> - | Q62: =SUMIFS(#REF!,#REF!,"*" & $C62 & "*",#REF!,"*" & Index!$D$12 & "*",#REF!,"*" & Index!$D$24 & "*",#REF!,"*" & Index!$D$16 & "*") + SUMIFS(#REF!,#REF!,"*" & $C62 & "*",#REF!,"*" & Index!$D$18 & "*",#REF!,"*" & Index!$D$24 & "*",#REF!,"*" & Index!$D$16 & "*",#REF!,"*" & Index!$D$20 & "*") -> #REF! | R62: 20565 | S62: =+Q62-R62 -> #REF! | T62: =IFERROR(IF(((Q62/R62)-1)=0,"-",((Q62/R62)-1)),"-") -> - | U62: =SUMIFS(#REF!,#REF!,"*" & C62 &"*",#REF!,"*" & Index!$D$12 & "*",#REF!,"*" & Index!$D$17 & "*")+SUMIFS(#REF!,#REF!,"*" & C62 &"*",#REF!,"*" & Index!$D$18 & "*",#REF!,"*" & Index!$D$17 & "*",#REF!,"*" & Index!$D$20 & "*") -> #REF! | V62: -38209 | W62: =+U62-V62 -> #REF! | X62: =IFERROR(IF(((U62/V62)-1)=0,"-",((U62/V62)-1)),"-") -> - | Y62: =SUMIFS(#REF!,#REF!,"*" & C62 & "*",#REF!,"*" & Index!$D$12 & "*")+ SUMIFS(#REF!,#REF!,"*" & C62 & "*",#REF!,"*" & Index!$D$18 & "*",#REF!,"*" & Index!$D$20 & "*") -> #REF! | Z62: 5301885 | AA62: =+Y62-Z62 -> #REF! | AB62: =IFERROR(IF(((Y62/Z62)-1)=0,"-",((Y62/Z62)-1)),"-") -> -
A63: =+LEN(C63) -> 8 | C63: NACE0803 | E63: =SUMIFS(#REF!,#REF!,"*" & C63 & "*",#REF!,"*" & Index!$D$12 & "*",#REF!,"*" & Index!$D$16 & "*")+SUMIFS(#REF!,#REF!,"*" & C63 & "*",#REF!,"*" & Index!$D$18 & "*",#REF!,"*" & Index!$D$20 & "*") -> #REF! | F63: 19144538 | G63: =+E63-F63 -> #REF! | H63: =IFERROR(IF(((E63/F63)-1)=0,"-",((E63/F63)-1)),"-") -> - | I63: =+E63-M63-Q63 -> #REF! | J63: 3482706 | K63: =+I63-J63 -> #REF! | L63: =IFERROR(IF(((I63/J63)-1)=0,"-",((I63/J63)-1)),"-") -> - | M63: =SUMIFS(#REF!,#REF!,"*" & $C63 & "*",#REF!,"*" & Index!$D$12 & "*",#REF!,"*" & Index!$D$23 & "*",#REF!,"*" & Index!$D$16 & "*") + SUMIFS(#REF!,#REF!,"*" & $C63 & "*",#REF!,"*" & Index!$D$18 & "*",#REF!,"*" & Index!$D$23 & "*",#REF!,"*" & Index!$D$16 & "*",#REF!,"*" & Index!$D$20 & "*") -> #REF! | N63: 1015 | O63: =+M63-N63 -> #REF! | P63: =IFERROR(IF(((M63/N63)-1)=0,"-",((M63/N63)-1)),"-") -> - | Q63: =SUMIFS(#REF!,#REF!,"*" & $C63 & "*",#REF!,"*" & Index!$D$12 & "*",#REF!,"*" & Index!$D$24 & "*",#REF!,"*" & Index!$D$16 & "*") + SUMIFS(#REF!,#REF!,"*" & $C63 & "*",#REF!,"*" & Index!$D$18 & "*",#REF!,"*" & Index!$D$24 & "*",#REF!,"*" & Index!$D$16 & "*",#REF!,"*" & Index!$D$20 & "*") -> #REF! | R63: 15660817 | S63: =+Q63-R63 -> #REF! | T63: =IFERROR(IF(((Q63/R63)-1)=0,"-",((Q63/R63)-1)),"-") -> - | U63: =SUMIFS(#REF!,#REF!,"*" & C63 &"*",#REF!,"*" & Index!$D$12 & "*",#REF!,"*" & Index!$D$17 & "*")+SUMIFS(#REF!,#REF!,"*" & C63 &"*",#REF!,"*" & Index!$D$18 & "*",#REF!,"*" & Index!$D$17 & "*",#REF!,"*" & Index!$D$20 & "*") -> #REF! | V63: -10405860 | W63: =+U63-V63 -> #REF! | X63: =IFERROR(IF(((U63/V63)-1)=0,"-",((U63/V63)-1)),"-") -> - | Y63: =SUMIFS(#REF!,#REF!,"*" & C63 & "*",#REF!,"*" & Index!$D$12 & "*")+ SUMIFS(#REF!,#REF!,"*" & C63 & "*",#REF!,"*" & Index!$D$18 & "*",#REF!,"*" & Index!$D$20 & "*") -> #REF! | Z63: 8738678 | AA63: =+Y63-Z63 -> #REF! | AB63: =IFERROR(IF(((Y63/Z63)-1)=0,"-",((Y63/Z63)-1)),"-") -> -
A64: =+LEN(C64) -> 8 | C64: NACE0804 | E64: =SUMIFS(#REF!,#REF!,"*" & C64 & "*",#REF!,"*" & Index!$D$12 & "*",#REF!,"*" & Index!$D$16 & "*")+SUMIFS(#REF!,#REF!,"*" & C64 & "*",#REF!,"*" & Index!$D$18 & "*",#REF!,"*" & Index!$D$20 & "*") -> #REF! | F64: 404692550 | G64: =+E64-F64 -> #REF! | H64: =IFERROR(IF(((E64/F64)-1)=0,"-",((E64/F64)-1)),"-") -> - | I64: =+E64-M64-Q64 -> #REF! | J64: 375785673 | K64: =+I64-J64 -> #REF! | L64: =IFERROR(IF(((I64/J64)-1)=0,"-",((I64/J64)-1)),"-") -> - | M64: =SUMIFS(#REF!,#REF!,"*" & $C64 & "*",#REF!,"*" & Index!$D$12 & "*",#REF!,"*" & Index!$D$23 & "*",#REF!,"*" & Index!$D$16 & "*") + SUMIFS(#REF!,#REF!,"*" & $C64 & "*",#REF!,"*" & Index!$D$18 & "*",#REF!,"*" & Index!$D$23 & "*",#REF!,"*" & Index!$D$16 & "*",#REF!,"*" & Index!$D$20 & "*") -> #REF! | N64: 5345092 | O64: =+M64-N64 -> #REF! | P64: =IFERROR(IF(((M64/N64)-1)=0,"-",((M64/N64)-1)),"-") -> - | Q64: =SUMIFS(#REF!,#REF!,"*" & $C64 & "*",#REF!,"*" & Index!$D$12 & "*",#REF!,"*" & Index!$D$24 & "*",#REF!,"*" & Index!$D$16 & "*") + SUMIFS(#REF!,#REF!,"*" & $C64 & "*",#REF!,"*" & Index!$D$18 & "*",#REF!,"*" & Index!$D$24 & "*",#REF!,"*" & Index!$D$16 & "*",#REF!,"*" & Index!$D$20 & "*") -> #REF! | R64: 23561785 | S64: =+Q64-R64 -> #REF! | T64: =IFERROR(IF(((Q64/R64)-1)=0,"-",((Q64/R64)-1)),"-") -> - | U64: =SUMIFS(#REF!,#REF!,"*" & C64 &"*",#REF!,"*" & Index!$D$12 & "*",#REF!,"*" & Index!$D$17 & "*")+SUMIFS(#REF!,#REF!,"*" & C64 &"*",#REF!,"*" & Index!$D$18 & "*",#REF!,"*" & Index!$D$17 & "*",#REF!,"*" & Index!$D$20 & "*") -> #REF! | V64: -14124277 | W64: =+U64-V64 -> #REF! | X64: =IFERROR(IF(((U64/V64)-1)=0,"-",((U64/V64)-1)),"-") -> - | Y64: =SUMIFS(#REF!,#REF!,"*" & C64 & "*",#REF!,"*" & Index!$D$12 & "*")+ SUMIFS(#REF!,#REF!,"*" & C64 & "*",#REF!,"*" & Index!$D$18 & "*",#REF!,"*" & Index!$D$20 & "*") -> #REF! | Z64: 390568273 | AA64: =+Y64-Z64 -> #REF! | AB64: =IFERROR(IF(((Y64/Z64)-1)=0,"-",((Y64/Z64)-1)),"-") -> -
A65: =+LEN(C65) -> 8 | C65: NACE0805 | E65: =SUMIFS(#REF!,#REF!,"*" & C65 & "*",#REF!,"*" & Index!$D$12 & "*",#REF!,"*" & Index!$D$16 & "*")+SUMIFS(#REF!,#REF!,"*" & C65 & "*",#REF!,"*" & Index!$D$18 & "*",#REF!,"*" & Index!$D$20 & "*") -> #REF! | F65: 2445996 | G65: =+E65-F65 -> #REF! | H65: =IFERROR(IF(((E65/F65)-1)=0,"-",((E65/F65)-1)),"-") -> - | I65: =+E65-M65-Q65 -> #REF! | J65: 1269427 | K65: =+I65-J65 -> #REF! | L65: =IFERROR(IF(((I65/J65)-1)=0,"-",((I65/J65)-1)),"-") -> - | M65: =SUMIFS(#REF!,#REF!,"*" & $C65 & "*",#REF!,"*" & Index!$D$12 & "*",#REF!,"*" & Index!$D$23 & "*",#REF!,"*" & Index!$D$16 & "*") + SUMIFS(#REF!,#REF!,"*" & $C65 & "*",#REF!,"*" & Index!$D$18 & "*",#REF!,"*" & Index!$D$23 & "*",#REF!,"*" & Index!$D$16 & "*",#REF!,"*" & Index!$D$20 & "*") -> #REF! | N65: 888236 | O65: =+M65-N65 -> #REF! | P65: =IFERROR(IF(((M65/N65)-1)=0,"-",((M65/N65)-1)),"-") -> - | Q65: =SUMIFS(#REF!,#REF!,"*" & $C65 & "*",#REF!,"*" & Index!$D$12 & "*",#REF!,"*" & Index!$D$24 & "*",#REF!,"*" & Index!$D$16 & "*") + SUMIFS(#REF!,#REF!,"*" & $C65 & "*",#REF!,"*" & Index!$D$18 & "*",#REF!,"*" & Index!$D$24 & "*",#REF!,"*" & Index!$D$16 & "*",#REF!,"*" & Index!$D$20 & "*") -> #REF! | R65: 288333 | S65: =+Q65-R65 -> #REF! | T65: =IFERROR(IF(((Q65/R65)-1)=0,"-",((Q65/R65)-1)),"-") -> - | U65: =SUMIFS(#REF!,#REF!,"*" & C65 &"*",#REF!,"*" & Index!$D$12 & "*",#REF!,"*" & Index!$D$17 & "*")+SUMIFS(#REF!,#REF!,"*" & C65 &"*",#REF!,"*" & Index!$D$18 & "*",#REF!,"*" & Index!$D$17 & "*",#REF!,"*" & Index!$D$20 & "*") -> #REF! | V65: -346551 | W65: =+U65-V65 -> #REF! | X65: =IFERROR(IF(((U65/V65)-1)=0,"-",((U65/V65)-1)),"-") -> - | Y65: =SUMIFS(#REF!,#REF!,"*" & C65 & "*",#REF!,"*" & Index!$D$12 & "*")+ SUMIFS(#REF!,#REF!,"*" & C65 & "*",#REF!,"*" & Index!$D$18 & "*",#REF!,"*" & Index!$D$20 & "*") -> #REF! | Z65: 2099445 | AA65: =+Y65-Z65 -> #REF! | AB65: =IFERROR(IF(((Y65/Z65)-1)=0,"-",((Y65/Z65)-1)),"-") -> -
A66: =+LEN(C66) -> 6 | C66: NACE09 | D66: Accommodation and food service activities | E66: =SUMIFS(#REF!,#REF!,"*" & C66 & "*",#REF!,"*" & Index!$D$12 & "*",#REF!,"*" & Index!$D$16 & "*")+SUMIFS(#REF!,#REF!,"*" & C66 & "*",#REF!,"*" & Index!$D$18 & "*",#REF!,"*" & Index!$D$20 & "*",#REF!,"*" & Index!$D$16 & "*") -> #REF! | F66: 1101909131 | G66: =+E66-F66 -> #REF! | H66: =IFERROR(IF(((E66/F66)-1)=0,"-",((E66/F66)-1)),"-") -> - | I66: =+E66-M66-Q66 -> #REF! | J66: 901127034 | K66: =+I66-J66 -> #REF! | L66: =IFERROR(IF(((I66/J66)-1)=0,"-",((I66/J66)-1)),"-") -> - | M66: =SUMIFS(#REF!,#REF!,"*" & $C66 & "*",#REF!,"*" & Index!$D$12 & "*",#REF!,"*" & Index!$D$23 & "*",#REF!,"*" & Index!$D$16 & "*") + SUMIFS(#REF!,#REF!,"*" & $C66 & "*",#REF!,"*" & Index!$D$18 & "*",#REF!,"*" & Index!$D$23 & "*",#REF!,"*" & Index!$D$16 & "*",#REF!,"*" & Index!$D$20 & "*") -> #REF! | N66: 86441588 | O66: =+M66-N66 -> #REF! | P66: =IFERROR(IF(((M66/N66)-1)=0,"-",((M66/N66)-1)),"-") -> - | Q66: =SUMIFS(#REF!,#REF!,"*" & $C66 & "*",#REF!,"*" & Index!$D$12 & "*",#REF!,"*" & Index!$D$24 & "*",#REF!,"*" & Index!$D$16 & "*") + SUMIFS(#REF!,#REF!,"*" & $C66 & "*",#REF!,"*" & Index!$D$18 & "*",#REF!,"*" & Index!$D$24 & "*",#REF!,"*" & Index!$D$16 & "*",#REF!,"*" & Index!$D$20 & "*") -> #REF! | R66: 114340509 | S66: =+Q66-R66 -> #REF! | T66: =IFERROR(IF(((Q66/R66)-1)=0,"-",((Q66/R66)-1)),"-") -> - | U66: =SUMIFS(#REF!,#REF!,"*" & C66 &"*",#REF!,"*" & Index!$D$12 & "*",#REF!,"*" & Index!$D$17 & "*")+SUMIFS(#REF!,#REF!,"*" & C66 &"*",#REF!,"*" & Index!$D$18 & "*",#REF!,"*" & Index!$D$17 & "*",#REF!,"*" & Index!$D$20 & "*") -> #REF! | V66: -55006185 | W66: =+U66-V66 -> #REF! | X66: =IFERROR(IF(((U66/V66)-1)=0,"-",((U66/V66)-1)),"-") -> - | Y66: =SUMIFS(#REF!,#REF!,"*" & C66 & "*",#REF!,"*" & Index!$D$12 & "*")+ SUMIFS(#REF!,#REF!,"*" & C66 & "*",#REF!,"*" & Index!$D$18 & "*",#REF!,"*" & Index!$D$20 & "*") -> #REF! | Z66: 1046902946 | AA66: =+Y66-Z66 -> #REF! | AB66: =IFERROR(IF(((Y66/Z66)-1)=0,"-",((Y66/Z66)-1)),"-") -> -
A67: =+LEN(C67) -> 8 | C67: NACE0901 | E67: =SUMIFS(#REF!,#REF!,"*" & C67 & "*",#REF!,"*" & Index!$D$12 & "*",#REF!,"*" & Index!$D$16 & "*")+SUMIFS(#REF!,#REF!,"*" & C67 & "*",#REF!,"*" & Index!$D$18 & "*",#REF!,"*" & Index!$D$20 & "*") -> #REF! | F67: 900029539 | G67: =+E67-F67 -> #REF! | H67: =IFERROR(IF(((E67/F67)-1)=0,"-",((E67/F67)-1)),"-") -> - | I67: =+E67-M67-Q67 -> #REF! | J67: 741332093 | K67: =+I67-J67 -> #REF! | L67: =IFERROR(IF(((I67/J67)-1)=0,"-",((I67/J67)-1)),"-") -> - | M67: =SUMIFS(#REF!,#REF!,"*" & $C67 & "*",#REF!,"*" & Index!$D$12 & "*",#REF!,"*" & Index!$D$23 & "*",#REF!,"*" & Index!$D$16 & "*") + SUMIFS(#REF!,#REF!,"*" & $C67 & "*",#REF!,"*" & Index!$D$18 & "*",#REF!,"*" & Index!$D$23 & "*",#REF!,"*" & Index!$D$16 & "*",#REF!,"*" & Index!$D$20 & "*") -> #REF! | N67: 51602610 | O67: =+M67-N67 -> #REF! | P67: =IFERROR(IF(((M67/N67)-1)=0,"-",((M67/N67)-1)),"-") -> - | Q67: =SUMIFS(#REF!,#REF!,"*" & $C67 & "*",#REF!,"*" & Index!$D$12 & "*",#REF!,"*" & Index!$D$24 & "*",#REF!,"*" & Index!$D$16 & "*") + SUMIFS(#REF!,#REF!,"*" & $C67 & "*",#REF!,"*" & Index!$D$18 & "*",#REF!,"*" & Index!$D$24 & "*",#REF!,"*" & Index!$D$16 & "*",#REF!,"*" & Index!$D$20 & "*") -> #REF! | R67: 107094836 | S67: =+Q67-R67 -> #REF! | T67: =IFERROR(IF(((Q67/R67)-1)=0,"-",((Q67/R67)-1)),"-") -> - | U67: =SUMIFS(#REF!,#REF!,"*" & C67 &"*",#REF!,"*" & Index!$D$12 & "*",#REF!,"*" & Index!$D$17 & "*")+SUMIFS(#REF!,#REF!,"*" & C67 &"*",#REF!,"*" & Index!$D$18 & "*",#REF!,"*" & Index!$D$17 & "*",#REF!,"*" & Index!$D$20 & "*") -> #REF! | V67: -46599804 | W67: =+U67-V67 -> #REF! | X67: =IFERROR(IF(((U67/V67)-1)=0,"-",((U67/V67)-1)),"-") -> - | Y67: =SUMIFS(#REF!,#REF!,"*" & C67 & "*",#REF!,"*" & Index!$D$12 & "*")+ SUMIFS(#REF!,#REF!,"*" & C67 & "*",#REF!,"*" & Index!$D$18 & "*",#REF!,"*" & Index!$D$20 & "*") -> #REF! | Z67: 853429735 | AA67: =+Y67-Z67 -> #REF! | AB67: =IFERROR(IF(((Y67/Z67)-1)=0,"-",((Y67/Z67)-1)),"-") -> -
A68: =+LEN(C68) -> 8 | C68: NACE0902 | E68: =SUMIFS(#REF!,#REF!,"*" & C68 & "*",#REF!,"*" & Index!$D$12 & "*",#REF!,"*" & Index!$D$16 & "*")+SUMIFS(#REF!,#REF!,"*" & C68 & "*",#REF!,"*" & Index!$D$18 & "*",#REF!,"*" & Index!$D$20 & "*") -> #REF! | F68: 201879592 | G68: =+E68-F68 -> #REF! | H68: =IFERROR(IF(((E68/F68)-1)=0,"-",((E68/F68)-1)),"-") -> - | I68: =+E68-M68-Q68 -> #REF! | J68: 159794941 | K68: =+I68-J68 -> #REF! | L68: =IFERROR(IF(((I68/J68)-1)=0,"-",((I68/J68)-1)),"-") -> - | M68: =SUMIFS(#REF!,#REF!,"*" & $C68 & "*",#REF!,"*" & Index!$D$12 & "*",#REF!,"*" & Index!$D$23 & "*",#REF!,"*" & Index!$D$16 & "*") + SUMIFS(#REF!,#REF!,"*" & $C68 & "*",#REF!,"*" & Index!$D$18 & "*",#REF!,"*" & Index!$D$23 & "*",#REF!,"*" & Index!$D$16 & "*",#REF!,"*" & Index!$D$20 & "*") -> #REF! | N68: 34838978 | O68: =+M68-N68 -> #REF! | P68: =IFERROR(IF(((M68/N68)-1)=0,"-",((M68/N68)-1)),"-") -> - | Q68: =SUMIFS(#REF!,#REF!,"*" & $C68 & "*",#REF!,"*" & Index!$D$12 & "*",#REF!,"*" & Index!$D$24 & "*",#REF!,"*" & Index!$D$16 & "*") + SUMIFS(#REF!,#REF!,"*" & $C68 & "*",#REF!,"*" & Index!$D$18 & "*",#REF!,"*" & Index!$D$24 & "*",#REF!,"*" & Index!$D$16 & "*",#REF!,"*" & Index!$D$20 & "*") -> #REF! | R68: 7245673 | S68: =+Q68-R68 -> #REF! | T68: =IFERROR(IF(((Q68/R68)-1)=0,"-",((Q68/R68)-1)),"-") -> - | U68: =SUMIFS(#REF!,#REF!,"*" & C68 &"*",#REF!,"*" & Index!$D$12 & "*",#REF!,"*" & Index!$D$17 & "*")+SUMIFS(#REF!,#REF!,"*" & C68 &"*",#REF!,"*" & Index!$D$18 & "*",#REF!,"*" & Index!$D$17 & "*",#REF!,"*" & Index!$D$20 & "*") -> #REF! | V68: -8406381 | W68: =+U68-V68 -> #REF! | X68: =IFERROR(IF(((U68/V68)-1)=0,"-",((U68/V68)-1)),"-") -> - | Y68: =SUMIFS(#REF!,#REF!,"*" & C68 & "*",#REF!,"*" & Index!$D$12 & "*")+ SUMIFS(#REF!,#REF!,"*" & C68 & "*",#REF!,"*" & Index!$D$18 & "*",#REF!,"*" & Index!$D$20 & "*") -> #REF! | Z68: 193473211 | AA68: =+Y68-Z68 -> #REF! | AB68: =IFERROR(IF(((Y68/Z68)-1)=0,"-",((Y68/Z68)-1)),"-") -> -
A69: =+LEN(C69) -> 6 | C69: NACE10 | D69: Information and communication | E69: =SUMIFS(#REF!,#REF!,"*" & C69 & "*",#REF!,"*" & Index!$D$12 & "*",#REF!,"*" & Index!$D$16 & "*")+SUMIFS(#REF!,#REF!,"*" & C69 & "*",#REF!,"*" & Index!$D$18 & "*",#REF!,"*" & Index!$D$20 & "*",#REF!,"*" & Index!$D$16 & "*") -> #REF! | F69: 120857760 | G69: =+E69-F69 -> #REF! | H69: =IFERROR(IF(((E69/F69)-1)=0,"-",((E69/F69)-1)),"-") -> - | I69: =+E69-M69-Q69 -> #REF! | J69: 107892141 | K69: =+I69-J69 -> #REF! | L69: =IFERROR(IF(((I69/J69)-1)=0,"-",((I69/J69)-1)),"-") -> - | M69: =SUMIFS(#REF!,#REF!,"*" & $C69 & "*",#REF!,"*" & Index!$D$12 & "*",#REF!,"*" & Index!$D$23 & "*",#REF!,"*" & Index!$D$16 & "*") + SUMIFS(#REF!,#REF!,"*" & $C69 & "*",#REF!,"*" & Index!$D$18 & "*",#REF!,"*" & Index!$D$23 & "*",#REF!,"*" & Index!$D$16 & "*",#REF!,"*" & Index!$D$20 & "*") -> #REF! | N69: 10743481 | O69: =+M69-N69 -> #REF! | P69: =IFERROR(IF(((M69/N69)-1)=0,"-",((M69/N69)-1)),"-") -> - | Q69: =SUMIFS(#REF!,#REF!,"*" & $C69 & "*",#REF!,"*" & Index!$D$12 & "*",#REF!,"*" & Index!$D$24 & "*",#REF!,"*" & Index!$D$16 & "*") + SUMIFS(#REF!,#REF!,"*" & $C69 & "*",#REF!,"*" & Index!$D$18 & "*",#REF!,"*" & Index!$D$24 & "*",#REF!,"*" & Index!$D$16 & "*",#REF!,"*" & Index!$D$20 & "*") -> #REF! | R69: 2222138 | S69: =+Q69-R69 -> #REF! | T69: =IFERROR(IF(((Q69/R69)-1)=0,"-",((Q69/R69)-1)),"-") -> - | U69: =SUMIFS(#REF!,#REF!,"*" & C69 &"*",#REF!,"*" & Index!$D$12 & "*",#REF!,"*" & Index!$D$17 & "*")+SUMIFS(#REF!,#REF!,"*" & C69 &"*",#REF!,"*" & Index!$D$18 & "*",#REF!,"*" & Index!$D$17 & "*",#REF!,"*" & Index!$D$20 & "*") -> #REF! | V69: -2450425 | W69: =+U69-V69 -> #REF! | X69: =IFERROR(IF(((U69/V69)-1)=0,"-",((U69/V69)-1)),"-") -> - | Y69: =SUMIFS(#REF!,#REF!,"*" & C69 & "*",#REF!,"*" & Index!$D$12 & "*")+ SUMIFS(#REF!,#REF!,"*" & C69 & "*",#REF!,"*" & Index!$D$18 & "*",#REF!,"*" & Index!$D$20 & "*") -> #REF! | Z69: 118407335 | AA69: =+Y69-Z69 -> #REF! | AB69: =IFERROR(IF(((Y69/Z69)-1)=0,"-",((Y69/Z69)-1)),"-") -> -
A70: =+LEN(C70) -> 8 | C70: NACE1001 | E70: =SUMIFS(#REF!,#REF!,"*" & C70 & "*",#REF!,"*" & Index!$D$12 & "*",#REF!,"*" & Index!$D$16 & "*")+SUMIFS(#REF!,#REF!,"*" & C70 & "*",#REF!,"*" & Index!$D$18 & "*",#REF!,"*" & Index!$D$20 & "*") -> #REF! | F70: 5825394 | G70: =+E70-F70 -> #REF! | H70: =IFERROR(IF(((E70/F70)-1)=0,"-",((E70/F70)-1)),"-") -> - | I70: =+E70-M70-Q70 -> #REF! | J70: 3456892 | K70: =+I70-J70 -> #REF! | L70: =IFERROR(IF(((I70/J70)-1)=0,"-",((I70/J70)-1)),"-") -> - | M70: =SUMIFS(#REF!,#REF!,"*" & $C70 & "*",#REF!,"*" & Index!$D$12 & "*",#REF!,"*" & Index!$D$23 & "*",#REF!,"*" & Index!$D$16 & "*") + SUMIFS(#REF!,#REF!,"*" & $C70 & "*",#REF!,"*" & Index!$D$18 & "*",#REF!,"*" & Index!$D$23 & "*",#REF!,"*" & Index!$D$16 & "*",#REF!,"*" & Index!$D$20 & "*") -> #REF! | N70: 1459291 | O70: =+M70-N70 -> #REF! | P70: =IFERROR(IF(((M70/N70)-1)=0,"-",((M70/N70)-1)),"-") -> - | Q70: =SUMIFS(#REF!,#REF!,"*" & $C70 & "*",#REF!,"*" & Index!$D$12 & "*",#REF!,"*" & Index!$D$24 & "*",#REF!,"*" & Index!$D$16 & "*") + SUMIFS(#REF!,#REF!,"*" & $C70 & "*",#REF!,"*" & Index!$D$18 & "*",#REF!,"*" & Index!$D$24 & "*",#REF!,"*" & Index!$D$16 & "*",#REF!,"*" & Index!$D$20 & "*") -> #REF! | R70: 909211 | S70: =+Q70-R70 -> #REF! | T70: =IFERROR(IF(((Q70/R70)-1)=0,"-",((Q70/R70)-1)),"-") -> - | U70: =SUMIFS(#REF!,#REF!,"*" & C70 &"*",#REF!,"*" & Index!$D$12 & "*",#REF!,"*" & Index!$D$17 & "*")+SUMIFS(#REF!,#REF!,"*" & C70 &"*",#REF!,"*" & Index!$D$18 & "*",#REF!,"*" & Index!$D$17 & "*",#REF!,"*" & Index!$D$20 & "*") -> #REF! | V70: -729489 | W70: =+U70-V70 -> #REF! | X70: =IFERROR(IF(((U70/V70)-1)=0,"-",((U70/V70)-1)),"-") -> - | Y70: =SUMIFS(#REF!,#REF!,"*" & C70 & "*",#REF!,"*" & Index!$D$12 & "*")+ SUMIFS(#REF!,#REF!,"*" & C70 & "*",#REF!,"*" & Index!$D$18 & "*",#REF!,"*" & Index!$D$20 & "*") -> #REF! | Z70: 5095905 | AA70: =+Y70-Z70 -> #REF! | AB70: =IFERROR(IF(((Y70/Z70)-1)=0,"-",((Y70/Z70)-1)),"-") -> -
A71: =+LEN(C71) -> 8 | C71: NACE1002 | E71: =SUMIFS(#REF!,#REF!,"*" & C71 & "*",#REF!,"*" & Index!$D$12 & "*",#REF!,"*" & Index!$D$16 & "*")+SUMIFS(#REF!,#REF!,"*" & C71 & "*",#REF!,"*" & Index!$D$18 & "*",#REF!,"*" & Index!$D$20 & "*") -> #REF! | F71: 8390933 | G71: =+E71-F71 -> #REF! | H71: =IFERROR(IF(((E71/F71)-1)=0,"-",((E71/F71)-1)),"-") -> - | I71: =+E71-M71-Q71 -> #REF! | J71: 6254747 | K71: =+I71-J71 -> #REF! | L71: =IFERROR(IF(((I71/J71)-1)=0,"-",((I71/J71)-1)),"-") -> - | M71: =SUMIFS(#REF!,#REF!,"*" & $C71 & "*",#REF!,"*" & Index!$D$12 & "*",#REF!,"*" & Index!$D$23 & "*",#REF!,"*" & Index!$D$16 & "*") + SUMIFS(#REF!,#REF!,"*" & $C71 & "*",#REF!,"*" & Index!$D$18 & "*",#REF!,"*" & Index!$D$23 & "*",#REF!,"*" & Index!$D$16 & "*",#REF!,"*" & Index!$D$20 & "*") -> #REF! | N71: 2061509 | O71: =+M71-N71 -> #REF! | P71: =IFERROR(IF(((M71/N71)-1)=0,"-",((M71/N71)-1)),"-") -> - | Q71: =SUMIFS(#REF!,#REF!,"*" & $C71 & "*",#REF!,"*" & Index!$D$12 & "*",#REF!,"*" & Index!$D$24 & "*",#REF!,"*" & Index!$D$16 & "*") + SUMIFS(#REF!,#REF!,"*" & $C71 & "*",#REF!,"*" & Index!$D$18 & "*",#REF!,"*" & Index!$D$24 & "*",#REF!,"*" & Index!$D$16 & "*",#REF!,"*" & Index!$D$20 & "*") -> #REF! | R71: 74677 | S71: =+Q71-R71 -> #REF! | T71: =IFERROR(IF(((Q71/R71)-1)=0,"-",((Q71/R71)-1)),"-") -> - | U71: =SUMIFS(#REF!,#REF!,"*" & C71 &"*",#REF!,"*" & Index!$D$12 & "*",#REF!,"*" & Index!$D$17 & "*")+SUMIFS(#REF!,#REF!,"*" & C71 &"*",#REF!,"*" & Index!$D$18 & "*",#REF!,"*" & Index!$D$17 & "*",#REF!,"*" & Index!$D$20 & "*") -> #REF! | V71: -199465 | W71: =+U71-V71 -> #REF! | X71: =IFERROR(IF(((U71/V71)-1)=0,"-",((U71/V71)-1)),"-") -> - | Y71: =SUMIFS(#REF!,#REF!,"*" & C71 & "*",#REF!,"*" & Index!$D$12 & "*")+ SUMIFS(#REF!,#REF!,"*" & C71 & "*",#REF!,"*" & Index!$D$18 & "*",#REF!,"*" & Index!$D$20 & "*") -> #REF! | Z71: 8191468 | AA71: =+Y71-Z71 -> #REF! | AB71: =IFERROR(IF(((Y71/Z71)-1)=0,"-",((Y71/Z71)-1)),"-") -> -
A72: =+LEN(C72) -> 8 | C72: NACE1003 | E72: =SUMIFS(#REF!,#REF!,"*" & C72 & "*",#REF!,"*" & Index!$D$12 & "*",#REF!,"*" & Index!$D$16 & "*")+SUMIFS(#REF!,#REF!,"*" & C72 & "*",#REF!,"*" & Index!$D$18 & "*",#REF!,"*" & Index!$D$20 & "*") -> #REF! | F72: 6662716 | G72: =+E72-F72 -> #REF! | H72: =IFERROR(IF(((E72/F72)-1)=0,"-",((E72/F72)-1)),"-") -> - | I72: =+E72-M72-Q72 -> #REF! | J72: 6516472 | K72: =+I72-J72 -> #REF! | L72: =IFERROR(IF(((I72/J72)-1)=0,"-",((I72/J72)-1)),"-") -> - | M72: =SUMIFS(#REF!,#REF!,"*" & $C72 & "*",#REF!,"*" & Index!$D$12 & "*",#REF!,"*" & Index!$D$23 & "*",#REF!,"*" & Index!$D$16 & "*") + SUMIFS(#REF!,#REF!,"*" & $C72 & "*",#REF!,"*" & Index!$D$18 & "*",#REF!,"*" & Index!$D$23 & "*",#REF!,"*" & Index!$D$16 & "*",#REF!,"*" & Index!$D$20 & "*") -> #REF! | N72: 104713 | O72: =+M72-N72 -> #REF! | P72: =IFERROR(IF(((M72/N72)-1)=0,"-",((M72/N72)-1)),"-") -> - | Q72: =SUMIFS(#REF!,#REF!,"*" & $C72 & "*",#REF!,"*" & Index!$D$12 & "*",#REF!,"*" & Index!$D$24 & "*",#REF!,"*" & Index!$D$16 & "*") + SUMIFS(#REF!,#REF!,"*" & $C72 & "*",#REF!,"*" & Index!$D$18 & "*",#REF!,"*" & Index!$D$24 & "*",#REF!,"*" & Index!$D$16 & "*",#REF!,"*" & Index!$D$20 & "*") -> #REF! | R72: 41531 | S72: =+Q72-R72 -> #REF! | T72: =IFERROR(IF(((Q72/R72)-1)=0,"-",((Q72/R72)-1)),"-") -> - | U72: =SUMIFS(#REF!,#REF!,"*" & C72 &"*",#REF!,"*" & Index!$D$12 & "*",#REF!,"*" & Index!$D$17 & "*")+SUMIFS(#REF!,#REF!,"*" & C72 &"*",#REF!,"*" & Index!$D$18 & "*",#REF!,"*" & Index!$D$17 & "*",#REF!,"*" & Index!$D$20 & "*") -> #REF! | V72: -47085 | W72: =+U72-V72 -> #REF! | X72: =IFERROR(IF(((U72/V72)-1)=0,"-",((U72/V72)-1)),"-") -> - | Y72: =SUMIFS(#REF!,#REF!,"*" & C72 & "*",#REF!,"*" & Index!$D$12 & "*")+ SUMIFS(#REF!,#REF!,"*" & C72 & "*",#REF!,"*" & Index!$D$18 & "*",#REF!,"*" & Index!$D$20 & "*") -> #REF! | Z72: 6615631 | AA72: =+Y72-Z72 -> #REF! | AB72: =IFERROR(IF(((Y72/Z72)-1)=0,"-",((Y72/Z72)-1)),"-") -> -
A73: =+LEN(C73) -> 8 | C73: NACE1004 | E73: =SUMIFS(#REF!,#REF!,"*" & C73 & "*",#REF!,"*" & Index!$D$12 & "*",#REF!,"*" & Index!$D$16 & "*")+SUMIFS(#REF!,#REF!,"*" & C73 & "*",#REF!,"*" & Index!$D$18 & "*",#REF!,"*" & Index!$D$20 & "*") -> #REF! | F73: 47399344 | G73: =+E73-F73 -> #REF! | H73: =IFERROR(IF(((E73/F73)-1)=0,"-",((E73/F73)-1)),"-") -> - | I73: =+E73-M73-Q73 -> #REF! | J73: 46410673 | K73: =+I73-J73 -> #REF! | L73: =IFERROR(IF(((I73/J73)-1)=0,"-",((I73/J73)-1)),"-") -> - | M73: =SUMIFS(#REF!,#REF!,"*" & $C73 & "*",#REF!,"*" & Index!$D$12 & "*",#REF!,"*" & Index!$D$23 & "*",#REF!,"*" & Index!$D$16 & "*") + SUMIFS(#REF!,#REF!,"*" & $C73 & "*",#REF!,"*" & Index!$D$18 & "*",#REF!,"*" & Index!$D$23 & "*",#REF!,"*" & Index!$D$16 & "*",#REF!,"*" & Index!$D$20 & "*") -> #REF! | N73: 768458 | O73: =+M73-N73 -> #REF! | P73: =IFERROR(IF(((M73/N73)-1)=0,"-",((M73/N73)-1)),"-") -> - | Q73: =SUMIFS(#REF!,#REF!,"*" & $C73 & "*",#REF!,"*" & Index!$D$12 & "*",#REF!,"*" & Index!$D$24 & "*",#REF!,"*" & Index!$D$16 & "*") + SUMIFS(#REF!,#REF!,"*" & $C73 & "*",#REF!,"*" & Index!$D$18 & "*",#REF!,"*" & Index!$D$24 & "*",#REF!,"*" & Index!$D$16 & "*",#REF!,"*" & Index!$D$20 & "*") -> #REF! | R73: 220213 | S73: =+Q73-R73 -> #REF! | T73: =IFERROR(IF(((Q73/R73)-1)=0,"-",((Q73/R73)-1)),"-") -> - | U73: =SUMIFS(#REF!,#REF!,"*" & C73 &"*",#REF!,"*" & Index!$D$12 & "*",#REF!,"*" & Index!$D$17 & "*")+SUMIFS(#REF!,#REF!,"*" & C73 &"*",#REF!,"*" & Index!$D$18 & "*",#REF!,"*" & Index!$D$17 & "*",#REF!,"*" & Index!$D$20 & "*") -> #REF! | V73: -267188 | W73: =+U73-V73 -> #REF! | X73: =IFERROR(IF(((U73/V73)-1)=0,"-",((U73/V73)-1)),"-") -> - | Y73: =SUMIFS(#REF!,#REF!,"*" & C73 & "*",#REF!,"*" & Index!$D$12 & "*")+ SUMIFS(#REF!,#REF!,"*" & C73 & "*",#REF!,"*" & Index!$D$18 & "*",#REF!,"*" & Index!$D$20 & "*") -> #REF! | Z73: 47132156 | AA73: =+Y73-Z73 -> #REF! | AB73: =IFERROR(IF(((Y73/Z73)-1)=0,"-",((Y73/Z73)-1)),"-") -> -
A74: =+LEN(C74) -> 8 | C74: NACE1005 | E74: =SUMIFS(#REF!,#REF!,"*" & C74 & "*",#REF!,"*" & Index!$D$12 & "*",#REF!,"*" & Index!$D$16 & "*")+SUMIFS(#REF!,#REF!,"*" & C74 & "*",#REF!,"*" & Index!$D$18 & "*",#REF!,"*" & Index!$D$20 & "*") -> #REF! | F74: 48852073 | G74: =+E74-F74 -> #REF! | H74: =IFERROR(IF(((E74/F74)-1)=0,"-",((E74/F74)-1)),"-") -> - | I74: =+E74-M74-Q74 -> #REF! | J74: 42061975 | K74: =+I74-J74 -> #REF! | L74: =IFERROR(IF(((I74/J74)-1)=0,"-",((I74/J74)-1)),"-") -> - | M74: =SUMIFS(#REF!,#REF!,"*" & $C74 & "*",#REF!,"*" & Index!$D$12 & "*",#REF!,"*" & Index!$D$23 & "*",#REF!,"*" & Index!$D$16 & "*") + SUMIFS(#REF!,#REF!,"*" & $C74 & "*",#REF!,"*" & Index!$D$18 & "*",#REF!,"*" & Index!$D$23 & "*",#REF!,"*" & Index!$D$16 & "*",#REF!,"*" & Index!$D$20 & "*") -> #REF! | N74: 5847126 | O74: =+M74-N74 -> #REF! | P74: =IFERROR(IF(((M74/N74)-1)=0,"-",((M74/N74)-1)),"-") -> - | Q74: =SUMIFS(#REF!,#REF!,"*" & $C74 & "*",#REF!,"*" & Index!$D$12 & "*",#REF!,"*" & Index!$D$24 & "*",#REF!,"*" & Index!$D$16 & "*") + SUMIFS(#REF!,#REF!,"*" & $C74 & "*",#REF!,"*" & Index!$D$18 & "*",#REF!,"*" & Index!$D$24 & "*",#REF!,"*" & Index!$D$16 & "*",#REF!,"*" & Index!$D$20 & "*") -> #REF! | R74: 942972 | S74: =+Q74-R74 -> #REF! | T74: =IFERROR(IF(((Q74/R74)-1)=0,"-",((Q74/R74)-1)),"-") -> - | U74: =SUMIFS(#REF!,#REF!,"*" & C74 &"*",#REF!,"*" & Index!$D$12 & "*",#REF!,"*" & Index!$D$17 & "*")+SUMIFS(#REF!,#REF!,"*" & C74 &"*",#REF!,"*" & Index!$D$18 & "*",#REF!,"*" & Index!$D$17 & "*",#REF!,"*" & Index!$D$20 & "*") -> #REF! | V74: -1099539 | W74: =+U74-V74 -> #REF! | X74: =IFERROR(IF(((U74/V74)-1)=0,"-",((U74/V74)-1)),"-") -> - | Y74: =SUMIFS(#REF!,#REF!,"*" & C74 & "*",#REF!,"*" & Index!$D$12 & "*")+ SUMIFS(#REF!,#REF!,"*" & C74 & "*",#REF!,"*" & Index!$D$18 & "*",#REF!,"*" & Index!$D$20 & "*") -> #REF! | Z74: 47752534 | AA74: =+Y74-Z74 -> #REF! | AB74: =IFERROR(IF(((Y74/Z74)-1)=0,"-",((Y74/Z74)-1)),"-") -> -
A75: =+LEN(C75) -> 8 | C75: NACE1006 | E75: =SUMIFS(#REF!,#REF!,"*" & C75 & "*",#REF!,"*" & Index!$D$12 & "*",#REF!,"*" & Index!$D$16 & "*")+SUMIFS(#REF!,#REF!,"*" & C75 & "*",#REF!,"*" & Index!$D$18 & "*",#REF!,"*" & Index!$D$20 & "*") -> #REF! | F75: 3727300 | G75: =+E75-F75 -> #REF! | H75: =IFERROR(IF(((E75/F75)-1)=0,"-",((E75/F75)-1)),"-") -> - | I75: =+E75-M75-Q75 -> #REF! | J75: 3191382 | K75: =+I75-J75 -> #REF! | L75: =IFERROR(IF(((I75/J75)-1)=0,"-",((I75/J75)-1)),"-") -> - | M75: =SUMIFS(#REF!,#REF!,"*" & $C75 & "*",#REF!,"*" & Index!$D$12 & "*",#REF!,"*" & Index!$D$23 & "*",#REF!,"*" & Index!$D$16 & "*") + SUMIFS(#REF!,#REF!,"*" & $C75 & "*",#REF!,"*" & Index!$D$18 & "*",#REF!,"*" & Index!$D$23 & "*",#REF!,"*" & Index!$D$16 & "*",#REF!,"*" & Index!$D$20 & "*") -> #REF! | N75: 502384 | O75: =+M75-N75 -> #REF! | P75: =IFERROR(IF(((M75/N75)-1)=0,"-",((M75/N75)-1)),"-") -> - | Q75: =SUMIFS(#REF!,#REF!,"*" & $C75 & "*",#REF!,"*" & Index!$D$12 & "*",#REF!,"*" & Index!$D$24 & "*",#REF!,"*" & Index!$D$16 & "*") + SUMIFS(#REF!,#REF!,"*" & $C75 & "*",#REF!,"*" & Index!$D$18 & "*",#REF!,"*" & Index!$D$24 & "*",#REF!,"*" & Index!$D$16 & "*",#REF!,"*" & Index!$D$20 & "*") -> #REF! | R75: 33534 | S75: =+Q75-R75 -> #REF! | T75: =IFERROR(IF(((Q75/R75)-1)=0,"-",((Q75/R75)-1)),"-") -> - | U75: =SUMIFS(#REF!,#REF!,"*" & C75 &"*",#REF!,"*" & Index!$D$12 & "*",#REF!,"*" & Index!$D$17 & "*")+SUMIFS(#REF!,#REF!,"*" & C75 &"*",#REF!,"*" & Index!$D$18 & "*",#REF!,"*" & Index!$D$17 & "*",#REF!,"*" & Index!$D$20 & "*") -> #REF! | V75: -107659 | W75: =+U75-V75 -> #REF! | X75: =IFERROR(IF(((U75/V75)-1)=0,"-",((U75/V75)-1)),"-") -> - | Y75: =SUMIFS(#REF!,#REF!,"*" & C75 & "*",#REF!,"*" & Index!$D$12 & "*")+ SUMIFS(#REF!,#REF!,"*" & C75 & "*",#REF!,"*" & Index!$D$18 & "*",#REF!,"*" & Index!$D$20 & "*") -> #REF! | Z75: 3619641 | AA75: =+Y75-Z75 -> #REF! | AB75: =IFERROR(IF(((Y75/Z75)-1)=0,"-",((Y75/Z75)-1)),"-") -> -
A76: =+LEN(C76) -> 6 | C76: NACE11 | D76: Financial and insurance activities | E76: =SUMIFS(#REF!,#REF!,"*" & C76 & "*",#REF!,"*" & Index!$D$12 & "*",#REF!,"*" & Index!$D$16 & "*")+SUMIFS(#REF!,#REF!,"*" & C76 & "*",#REF!,"*" & Index!$D$18 & "*",#REF!,"*" & Index!$D$20 & "*",#REF!,"*" & Index!$D$16 & "*") -> #REF! | F76: 37933189 | G76: =+E76-F76 -> #REF! | H76: =IFERROR(IF(((E76/F76)-1)=0,"-",((E76/F76)-1)),"-") -> - | I76: =+E76-M76-Q76 -> #REF! | J76: 36764813 | K76: =+I76-J76 -> #REF! | L76: =IFERROR(IF(((I76/J76)-1)=0,"-",((I76/J76)-1)),"-") -> - | M76: =SUMIFS(#REF!,#REF!,"*" & $C76 & "*",#REF!,"*" & Index!$D$12 & "*",#REF!,"*" & Index!$D$23 & "*",#REF!,"*" & Index!$D$16 & "*") + SUMIFS(#REF!,#REF!,"*" & $C76 & "*",#REF!,"*" & Index!$D$18 & "*",#REF!,"*" & Index!$D$23 & "*",#REF!,"*" & Index!$D$16 & "*",#REF!,"*" & Index!$D$20 & "*") -> #REF! | N76: 589591 | O76: =+M76-N76 -> #REF! | P76: =IFERROR(IF(((M76/N76)-1)=0,"-",((M76/N76)-1)),"-") -> - | Q76: =SUMIFS(#REF!,#REF!,"*" & $C76 & "*",#REF!,"*" & Index!$D$12 & "*",#REF!,"*" & Index!$D$24 & "*",#REF!,"*" & Index!$D$16 & "*") + SUMIFS(#REF!,#REF!,"*" & $C76 & "*",#REF!,"*" & Index!$D$18 & "*",#REF!,"*" & Index!$D$24 & "*",#REF!,"*" & Index!$D$16 & "*",#REF!,"*" & Index!$D$20 & "*") -> #REF! | R76: 578785 | S76: =+Q76-R76 -> #REF! | T76: =IFERROR(IF(((Q76/R76)-1)=0,"-",((Q76/R76)-1)),"-") -> - | U76: =SUMIFS(#REF!,#REF!,"*" & C76 &"*",#REF!,"*" & Index!$D$12 & "*",#REF!,"*" & Index!$D$17 & "*")+SUMIFS(#REF!,#REF!,"*" & C76 &"*",#REF!,"*" & Index!$D$18 & "*",#REF!,"*" & Index!$D$17 & "*",#REF!,"*" & Index!$D$20 & "*") -> #REF! | V76: -978220 | W76: =+U76-V76 -> #REF! | X76: =IFERROR(IF(((U76/V76)-1)=0,"-",((U76/V76)-1)),"-") -> - | Y76: =SUMIFS(#REF!,#REF!,"*" & C76 & "*",#REF!,"*" & Index!$D$12 & "*")+ SUMIFS(#REF!,#REF!,"*" & C76 & "*",#REF!,"*" & Index!$D$18 & "*",#REF!,"*" & Index!$D$20 & "*") -> #REF! | Z76: 36954969 | AA76: =+Y76-Z76 -> #REF! | AB76: =IFERROR(IF(((Y76/Z76)-1)=0,"-",((Y76/Z76)-1)),"-") -> -
A77: =+LEN(C77) -> 8 | C77: NACE1101 | E77: =SUMIFS(#REF!,#REF!,"*" & C77 & "*",#REF!,"*" & Index!$D$12 & "*",#REF!,"*" & Index!$D$16 & "*")+SUMIFS(#REF!,#REF!,"*" & C77 & "*",#REF!,"*" & Index!$D$18 & "*",#REF!,"*" & Index!$D$20 & "*") -> #REF! | F77: 36950955 | G77: =+E77-F77 -> #REF! | H77: =IFERROR(IF(((E77/F77)-1)=0,"-",((E77/F77)-1)),"-") -> - | I77: =+E77-M77-Q77 -> #REF! | J77: 36319210 | K77: =+I77-J77 -> #REF! | L77: =IFERROR(IF(((I77/J77)-1)=0,"-",((I77/J77)-1)),"-") -> - | M77: =SUMIFS(#REF!,#REF!,"*" & $C77 & "*",#REF!,"*" & Index!$D$12 & "*",#REF!,"*" & Index!$D$23 & "*",#REF!,"*" & Index!$D$16 & "*") + SUMIFS(#REF!,#REF!,"*" & $C77 & "*",#REF!,"*" & Index!$D$18 & "*",#REF!,"*" & Index!$D$23 & "*",#REF!,"*" & Index!$D$16 & "*",#REF!,"*" & Index!$D$20 & "*") -> #REF! | N77: 57674 | O77: =+M77-N77 -> #REF! | P77: =IFERROR(IF(((M77/N77)-1)=0,"-",((M77/N77)-1)),"-") -> - | Q77: =SUMIFS(#REF!,#REF!,"*" & $C77 & "*",#REF!,"*" & Index!$D$12 & "*",#REF!,"*" & Index!$D$24 & "*",#REF!,"*" & Index!$D$16 & "*") + SUMIFS(#REF!,#REF!,"*" & $C77 & "*",#REF!,"*" & Index!$D$18 & "*",#REF!,"*" & Index!$D$24 & "*",#REF!,"*" & Index!$D$16 & "*",#REF!,"*" & Index!$D$20 & "*") -> #REF! | R77: 574071 | S77: =+Q77-R77 -> #REF! | T77: =IFERROR(IF(((Q77/R77)-1)=0,"-",((Q77/R77)-1)),"-") -> - | U77: =SUMIFS(#REF!,#REF!,"*" & C77 &"*",#REF!,"*" & Index!$D$12 & "*",#REF!,"*" & Index!$D$17 & "*")+SUMIFS(#REF!,#REF!,"*" & C77 &"*",#REF!,"*" & Index!$D$18 & "*",#REF!,"*" & Index!$D$17 & "*",#REF!,"*" & Index!$D$20 & "*") -> #REF! | V77: -928888 | W77: =+U77-V77 -> #REF! | X77: =IFERROR(IF(((U77/V77)-1)=0,"-",((U77/V77)-1)),"-") -> - | Y77: =SUMIFS(#REF!,#REF!,"*" & C77 & "*",#REF!,"*" & Index!$D$12 & "*")+ SUMIFS(#REF!,#REF!,"*" & C77 & "*",#REF!,"*" & Index!$D$18 & "*",#REF!,"*" & Index!$D$20 & "*") -> #REF! | Z77: 36022067 | AA77: =+Y77-Z77 -> #REF! | AB77: =IFERROR(IF(((Y77/Z77)-1)=0,"-",((Y77/Z77)-1)),"-") -> -
A78: =+LEN(C78) -> 8 | C78: NACE1102 | E78: =SUMIFS(#REF!,#REF!,"*" & C78 & "*",#REF!,"*" & Index!$D$12 & "*",#REF!,"*" & Index!$D$16 & "*")+SUMIFS(#REF!,#REF!,"*" & C78 & "*",#REF!,"*" & Index!$D$18 & "*",#REF!,"*" & Index!$D$20 & "*") -> #REF! | F78: 564 | G78: =+E78-F78 -> #REF! | H78: =IFERROR(IF(((E78/F78)-1)=0,"-",((E78/F78)-1)),"-") -> - | I78: =+E78-M78-Q78 -> #REF! | J78: 0 | K78: =+I78-J78 -> #REF! | L78: =IFERROR(IF(((I78/J78)-1)=0,"-",((I78/J78)-1)),"-") -> - | M78: =SUMIFS(#REF!,#REF!,"*" & $C78 & "*",#REF!,"*" & Index!$D$12 & "*",#REF!,"*" & Index!$D$23 & "*",#REF!,"*" & Index!$D$16 & "*") + SUMIFS(#REF!,#REF!,"*" & $C78 & "*",#REF!,"*" & Index!$D$18 & "*",#REF!,"*" & Index!$D$23 & "*",#REF!,"*" & Index!$D$16 & "*",#REF!,"*" & Index!$D$20 & "*") -> #REF! | N78: 438 | O78: =+M78-N78 -> #REF! | P78: =IFERROR(IF(((M78/N78)-1)=0,"-",((M78/N78)-1)),"-") -> - | Q78: =SUMIFS(#REF!,#REF!,"*" & $C78 & "*",#REF!,"*" & Index!$D$12 & "*",#REF!,"*" & Index!$D$24 & "*",#REF!,"*" & Index!$D$16 & "*") + SUMIFS(#REF!,#REF!,"*" & $C78 & "*",#REF!,"*" & Index!$D$18 & "*",#REF!,"*" & Index!$D$24 & "*",#REF!,"*" & Index!$D$16 & "*",#REF!,"*" & Index!$D$20 & "*") -> #REF! | R78: 126 | S78: =+Q78-R78 -> #REF! | T78: =IFERROR(IF(((Q78/R78)-1)=0,"-",((Q78/R78)-1)),"-") -> - | U78: =SUMIFS(#REF!,#REF!,"*" & C78 &"*",#REF!,"*" & Index!$D$12 & "*",#REF!,"*" & Index!$D$17 & "*")+SUMIFS(#REF!,#REF!,"*" & C78 &"*",#REF!,"*" & Index!$D$18 & "*",#REF!,"*" & Index!$D$17 & "*",#REF!,"*" & Index!$D$20 & "*") -> #REF! | V78: -244 | W78: =+U78-V78 -> #REF! | X78: =IFERROR(IF(((U78/V78)-1)=0,"-",((U78/V78)-1)),"-") -> - | Y78: =SUMIFS(#REF!,#REF!,"*" & C78 & "*",#REF!,"*" & Index!$D$12 & "*")+ SUMIFS(#REF!,#REF!,"*" & C78 & "*",#REF!,"*" & Index!$D$18 & "*",#REF!,"*" & Index!$D$20 & "*") -> #REF! | Z78: 320 | AA78: =+Y78-Z78 -> #REF! | AB78: =IFERROR(IF(((Y78/Z78)-1)=0,"-",((Y78/Z78)-1)),"-") -> -
A79: =+LEN(C79) -> 8 | C79: NACE1103 | E79: =SUMIFS(#REF!,#REF!,"*" & C79 & "*",#REF!,"*" & Index!$D$12 & "*",#REF!,"*" & Index!$D$16 & "*")+SUMIFS(#REF!,#REF!,"*" & C79 & "*",#REF!,"*" & Index!$D$18 & "*",#REF!,"*" & Index!$D$20 & "*") -> #REF! | F79: 981670 | G79: =+E79-F79 -> #REF! | H79: =IFERROR(IF(((E79/F79)-1)=0,"-",((E79/F79)-1)),"-") -> - | I79: =+E79-M79-Q79 -> #REF! | J79: 445603 | K79: =+I79-J79 -> #REF! | L79: =IFERROR(IF(((I79/J79)-1)=0,"-",((I79/J79)-1)),"-") -> - | M79: =SUMIFS(#REF!,#REF!,"*" & $C79 & "*",#REF!,"*" & Index!$D$12 & "*",#REF!,"*" & Index!$D$23 & "*",#REF!,"*" & Index!$D$16 & "*") + SUMIFS(#REF!,#REF!,"*" & $C79 & "*",#REF!,"*" & Index!$D$18 & "*",#REF!,"*" & Index!$D$23 & "*",#REF!,"*" & Index!$D$16 & "*",#REF!,"*" & Index!$D$20 & "*") -> #REF! | N79: 531479 | O79: =+M79-N79 -> #REF! | P79: =IFERROR(IF(((M79/N79)-1)=0,"-",((M79/N79)-1)),"-") -> - | Q79: =SUMIFS(#REF!,#REF!,"*" & $C79 & "*",#REF!,"*" & Index!$D$12 & "*",#REF!,"*" & Index!$D$24 & "*",#REF!,"*" & Index!$D$16 & "*") + SUMIFS(#REF!,#REF!,"*" & $C79 & "*",#REF!,"*" & Index!$D$18 & "*",#REF!,"*" & Index!$D$24 & "*",#REF!,"*" & Index!$D$16 & "*",#REF!,"*" & Index!$D$20 & "*") -> #REF! | R79: 4588 | S79: =+Q79-R79 -> #REF! | T79: =IFERROR(IF(((Q79/R79)-1)=0,"-",((Q79/R79)-1)),"-") -> - | U79: =SUMIFS(#REF!,#REF!,"*" & C79 &"*",#REF!,"*" & Index!$D$12 & "*",#REF!,"*" & Index!$D$17 & "*")+SUMIFS(#REF!,#REF!,"*" & C79 &"*",#REF!,"*" & Index!$D$18 & "*",#REF!,"*" & Index!$D$17 & "*",#REF!,"*" & Index!$D$20 & "*") -> #REF! | V79: -49088 | W79: =+U79-V79 -> #REF! | X79: =IFERROR(IF(((U79/V79)-1)=0,"-",((U79/V79)-1)),"-") -> - | Y79: =SUMIFS(#REF!,#REF!,"*" & C79 & "*",#REF!,"*" & Index!$D$12 & "*")+ SUMIFS(#REF!,#REF!,"*" & C79 & "*",#REF!,"*" & Index!$D$18 & "*",#REF!,"*" & Index!$D$20 & "*") -> #REF! | Z79: 932582 | AA79: =+Y79-Z79 -> #REF! | AB79: =IFERROR(IF(((Y79/Z79)-1)=0,"-",((Y79/Z79)-1)),"-") -> -
A80: =+LEN(C80) -> 6 | C80: NACE12 | D80: Real estate activities | E80: =SUMIFS(#REF!,#REF!,"*" & C80 & "*",#REF!,"*" & Index!$D$12 & "*",#REF!,"*" & Index!$D$16 & "*")+SUMIFS(#REF!,#REF!,"*" & C80 & "*",#REF!,"*" & Index!$D$18 & "*",#REF!,"*" & Index!$D$20 & "*",#REF!,"*" & Index!$D$16 & "*") -> #REF! | F80: 1298457954 | G80: =+E80-F80 -> #REF! | H80: =IFERROR(IF(((E80/F80)-1)=0,"-",((E80/F80)-1)),"-") -> - | I80: =+E80-M80-Q80 -> #REF! | J80: 1161157012 | K80: =+I80-J80 -> #REF! | L80: =IFERROR(IF(((I80/J80)-1)=0,"-",((I80/J80)-1)),"-") -> - | M80: =SUMIFS(#REF!,#REF!,"*" & $C80 & "*",#REF!,"*" & Index!$D$12 & "*",#REF!,"*" & Index!$D$23 & "*",#REF!,"*" & Index!$D$16 & "*") + SUMIFS(#REF!,#REF!,"*" & $C80 & "*",#REF!,"*" & Index!$D$18 & "*",#REF!,"*" & Index!$D$23 & "*",#REF!,"*" & Index!$D$16 & "*",#REF!,"*" & Index!$D$20 & "*") -> #REF! | N80: 84307199 | O80: =+M80-N80 -> #REF! | P80: =IFERROR(IF(((M80/N80)-1)=0,"-",((M80/N80)-1)),"-") -> - | Q80: =SUMIFS(#REF!,#REF!,"*" & $C80 & "*",#REF!,"*" & Index!$D$12 & "*",#REF!,"*" & Index!$D$24 & "*",#REF!,"*" & Index!$D$16 & "*") + SUMIFS(#REF!,#REF!,"*" & $C80 & "*",#REF!,"*" & Index!$D$18 & "*",#REF!,"*" & Index!$D$24 & "*",#REF!,"*" & Index!$D$16 & "*",#REF!,"*" & Index!$D$20 & "*") -> #REF! | R80: 52993743 | S80: =+Q80-R80 -> #REF! | T80: =IFERROR(IF(((Q80/R80)-1)=0,"-",((Q80/R80)-1)),"-") -> - | U80: =SUMIFS(#REF!,#REF!,"*" & C80 &"*",#REF!,"*" & Index!$D$12 & "*",#REF!,"*" & Index!$D$17 & "*")+SUMIFS(#REF!,#REF!,"*" & C80 &"*",#REF!,"*" & Index!$D$18 & "*",#REF!,"*" & Index!$D$17 & "*",#REF!,"*" & Index!$D$20 & "*") -> #REF! | V80: -38250558 | W80: =+U80-V80 -> #REF! | X80: =IFERROR(IF(((U80/V80)-1)=0,"-",((U80/V80)-1)),"-") -> - | Y80: =SUMIFS(#REF!,#REF!,"*" & C80 & "*",#REF!,"*" & Index!$D$12 & "*")+ SUMIFS(#REF!,#REF!,"*" & C80 & "*",#REF!,"*" & Index!$D$18 & "*",#REF!,"*" & Index!$D$20 & "*") -> #REF! | Z80: 1260207396 | AA80: =+Y80-Z80 -> #REF! | AB80: =IFERROR(IF(((Y80/Z80)-1)=0,"-",((Y80/Z80)-1)),"-") -> -
A81: =+LEN(C81) -> 6 | C81: NACE13 | D81: Professional, scientific and technical activities | E81: =SUMIFS(#REF!,#REF!,"*" & C81 & "*",#REF!,"*" & Index!$D$12 & "*",#REF!,"*" & Index!$D$16 & "*")+SUMIFS(#REF!,#REF!,"*" & C81 & "*",#REF!,"*" & Index!$D$18 & "*",#REF!,"*" & Index!$D$20 & "*",#REF!,"*" & Index!$D$16 & "*") -> #REF! | F81: 1681179184 | G81: =+E81-F81 -> #REF! | H81: =IFERROR(IF(((E81/F81)-1)=0,"-",((E81/F81)-1)),"-") -> - | I81: =+E81-M81-Q81 -> #REF! | J81: 1614721654 | K81: =+I81-J81 -> #REF! | L81: =IFERROR(IF(((I81/J81)-1)=0,"-",((I81/J81)-1)),"-") -> - | M81: =SUMIFS(#REF!,#REF!,"*" & $C81 & "*",#REF!,"*" & Index!$D$12 & "*",#REF!,"*" & Index!$D$23 & "*",#REF!,"*" & Index!$D$16 & "*") + SUMIFS(#REF!,#REF!,"*" & $C81 & "*",#REF!,"*" & Index!$D$18 & "*",#REF!,"*" & Index!$D$23 & "*",#REF!,"*" & Index!$D$16 & "*",#REF!,"*" & Index!$D$20 & "*") -> #REF! | N81: 43729821 | O81: =+M81-N81 -> #REF! | P81: =IFERROR(IF(((M81/N81)-1)=0,"-",((M81/N81)-1)),"-") -> - | Q81: =SUMIFS(#REF!,#REF!,"*" & $C81 & "*",#REF!,"*" & Index!$D$12 & "*",#REF!,"*" & Index!$D$24 & "*",#REF!,"*" & Index!$D$16 & "*") + SUMIFS(#REF!,#REF!,"*" & $C81 & "*",#REF!,"*" & Index!$D$18 & "*",#REF!,"*" & Index!$D$24 & "*",#REF!,"*" & Index!$D$16 & "*",#REF!,"*" & Index!$D$20 & "*") -> #REF! | R81: 22727709 | S81: =+Q81-R81 -> #REF! | T81: =IFERROR(IF(((Q81/R81)-1)=0,"-",((Q81/R81)-1)),"-") -> - | U81: =SUMIFS(#REF!,#REF!,"*" & C81 &"*",#REF!,"*" & Index!$D$12 & "*",#REF!,"*" & Index!$D$17 & "*")+SUMIFS(#REF!,#REF!,"*" & C81 &"*",#REF!,"*" & Index!$D$18 & "*",#REF!,"*" & Index!$D$17 & "*",#REF!,"*" & Index!$D$20 & "*") -> #REF! | V81: -16661374 | W81: =+U81-V81 -> #REF! | X81: =IFERROR(IF(((U81/V81)-1)=0,"-",((U81/V81)-1)),"-") -> - | Y81: =SUMIFS(#REF!,#REF!,"*" & C81 & "*",#REF!,"*" & Index!$D$12 & "*")+ SUMIFS(#REF!,#REF!,"*" & C81 & "*",#REF!,"*" & Index!$D$18 & "*",#REF!,"*" & Index!$D$20 & "*") -> #REF! | Z81: 1664517810 | AA81: =+Y81-Z81 -> #REF! | AB81: =IFERROR(IF(((Y81/Z81)-1)=0,"-",((Y81/Z81)-1)),"-") -> -
A82: =+LEN(C82) -> 8 | C82: NACE1301 | E82: =SUMIFS(#REF!,#REF!,"*" & C82 & "*",#REF!,"*" & Index!$D$12 & "*",#REF!,"*" & Index!$D$16 & "*")+SUMIFS(#REF!,#REF!,"*" & C82 & "*",#REF!,"*" & Index!$D$18 & "*",#REF!,"*" & Index!$D$20 & "*") -> #REF! | F82: 125857948 | G82: =+E82-F82 -> #REF! | H82: =IFERROR(IF(((E82/F82)-1)=0,"-",((E82/F82)-1)),"-") -> - | I82: =+E82-M82-Q82 -> #REF! | J82: 118787490 | K82: =+I82-J82 -> #REF! | L82: =IFERROR(IF(((I82/J82)-1)=0,"-",((I82/J82)-1)),"-") -> - | M82: =SUMIFS(#REF!,#REF!,"*" & $C82 & "*",#REF!,"*" & Index!$D$12 & "*",#REF!,"*" & Index!$D$23 & "*",#REF!,"*" & Index!$D$16 & "*") + SUMIFS(#REF!,#REF!,"*" & $C82 & "*",#REF!,"*" & Index!$D$18 & "*",#REF!,"*" & Index!$D$23 & "*",#REF!,"*" & Index!$D$16 & "*",#REF!,"*" & Index!$D$20 & "*") -> #REF! | N82: 6432250 | O82: =+M82-N82 -> #REF! | P82: =IFERROR(IF(((M82/N82)-1)=0,"-",((M82/N82)-1)),"-") -> - | Q82: =SUMIFS(#REF!,#REF!,"*" & $C82 & "*",#REF!,"*" & Index!$D$12 & "*",#REF!,"*" & Index!$D$24 & "*",#REF!,"*" & Index!$D$16 & "*") + SUMIFS(#REF!,#REF!,"*" & $C82 & "*",#REF!,"*" & Index!$D$18 & "*",#REF!,"*" & Index!$D$24 & "*",#REF!,"*" & Index!$D$16 & "*",#REF!,"*" & Index!$D$20 & "*") -> #REF! | R82: 638208 | S82: =+Q82-R82 -> #REF! | T82: =IFERROR(IF(((Q82/R82)-1)=0,"-",((Q82/R82)-1)),"-") -> - | U82: =SUMIFS(#REF!,#REF!,"*" & C82 &"*",#REF!,"*" & Index!$D$12 & "*",#REF!,"*" & Index!$D$17 & "*")+SUMIFS(#REF!,#REF!,"*" & C82 &"*",#REF!,"*" & Index!$D$18 & "*",#REF!,"*" & Index!$D$17 & "*",#REF!,"*" & Index!$D$20 & "*") -> #REF! | V82: -918504 | W82: =+U82-V82 -> #REF! | X82: =IFERROR(IF(((U82/V82)-1)=0,"-",((U82/V82)-1)),"-") -> - | Y82: =SUMIFS(#REF!,#REF!,"*" & C82 & "*",#REF!,"*" & Index!$D$12 & "*")+ SUMIFS(#REF!,#REF!,"*" & C82 & "*",#REF!,"*" & Index!$D$18 & "*",#REF!,"*" & Index!$D$20 & "*") -> #REF! | Z82: 124939444 | AA82: =+Y82-Z82 -> #REF! | AB82: =IFERROR(IF(((Y82/Z82)-1)=0,"-",((Y82/Z82)-1)),"-") -> -
A83: =+LEN(C83) -> 8 | C83: NACE1302 | E83: =SUMIFS(#REF!,#REF!,"*" & C83 & "*",#REF!,"*" & Index!$D$12 & "*",#REF!,"*" & Index!$D$16 & "*")+SUMIFS(#REF!,#REF!,"*" & C83 & "*",#REF!,"*" & Index!$D$18 & "*",#REF!,"*" & Index!$D$20 & "*") -> #REF! | F83: 1391829712 | G83: =+E83-F83 -> #REF! | H83: =IFERROR(IF(((E83/F83)-1)=0,"-",((E83/F83)-1)),"-") -> - | I83: =+E83-M83-Q83 -> #REF! | J83: 1357626758 | K83: =+I83-J83 -> #REF! | L83: =IFERROR(IF(((I83/J83)-1)=0,"-",((I83/J83)-1)),"-") -> - | M83: =SUMIFS(#REF!,#REF!,"*" & $C83 & "*",#REF!,"*" & Index!$D$12 & "*",#REF!,"*" & Index!$D$23 & "*",#REF!,"*" & Index!$D$16 & "*") + SUMIFS(#REF!,#REF!,"*" & $C83 & "*",#REF!,"*" & Index!$D$18 & "*",#REF!,"*" & Index!$D$23 & "*",#REF!,"*" & Index!$D$16 & "*",#REF!,"*" & Index!$D$20 & "*") -> #REF! | N83: 16416355 | O83: =+M83-N83 -> #REF! | P83: =IFERROR(IF(((M83/N83)-1)=0,"-",((M83/N83)-1)),"-") -> - | Q83: =SUMIFS(#REF!,#REF!,"*" & $C83 & "*",#REF!,"*" & Index!$D$12 & "*",#REF!,"*" & Index!$D$24 & "*",#REF!,"*" & Index!$D$16 & "*") + SUMIFS(#REF!,#REF!,"*" & $C83 & "*",#REF!,"*" & Index!$D$18 & "*",#REF!,"*" & Index!$D$24 & "*",#REF!,"*" & Index!$D$16 & "*",#REF!,"*" & Index!$D$20 & "*") -> #REF! | R83: 17786599 | S83: =+Q83-R83 -> #REF! | T83: =IFERROR(IF(((Q83/R83)-1)=0,"-",((Q83/R83)-1)),"-") -> - | U83: =SUMIFS(#REF!,#REF!,"*" & C83 &"*",#REF!,"*" & Index!$D$12 & "*",#REF!,"*" & Index!$D$17 & "*")+SUMIFS(#REF!,#REF!,"*" & C83 &"*",#REF!,"*" & Index!$D$18 & "*",#REF!,"*" & Index!$D$17 & "*",#REF!,"*" & Index!$D$20 & "*") -> #REF! | V83: -10850280 | W83: =+U83-V83 -> #REF! | X83: =IFERROR(IF(((U83/V83)-1)=0,"-",((U83/V83)-1)),"-") -> - | Y83: =SUMIFS(#REF!,#REF!,"*" & C83 & "*",#REF!,"*" & Index!$D$12 & "*")+ SUMIFS(#REF!,#REF!,"*" & C83 & "*",#REF!,"*" & Index!$D$18 & "*",#REF!,"*" & Index!$D$20 & "*") -> #REF! | Z83: 1380979432 | AA83: =+Y83-Z83 -> #REF! | AB83: =IFERROR(IF(((Y83/Z83)-1)=0,"-",((Y83/Z83)-1)),"-") -> -
A84: =+LEN(C84) -> 8 | C84: NACE1303 | E84: =SUMIFS(#REF!,#REF!,"*" & C84 & "*",#REF!,"*" & Index!$D$12 & "*",#REF!,"*" & Index!$D$16 & "*")+SUMIFS(#REF!,#REF!,"*" & C84 & "*",#REF!,"*" & Index!$D$18 & "*",#REF!,"*" & Index!$D$20 & "*") -> #REF! | F84: 118844158 | G84: =+E84-F84 -> #REF! | H84: =IFERROR(IF(((E84/F84)-1)=0,"-",((E84/F84)-1)),"-") -> - | I84: =+E84-M84-Q84 -> #REF! | J84: 105027630 | K84: =+I84-J84 -> #REF! | L84: =IFERROR(IF(((I84/J84)-1)=0,"-",((I84/J84)-1)),"-") -> - | M84: =SUMIFS(#REF!,#REF!,"*" & $C84 & "*",#REF!,"*" & Index!$D$12 & "*",#REF!,"*" & Index!$D$23 & "*",#REF!,"*" & Index!$D$16 & "*") + SUMIFS(#REF!,#REF!,"*" & $C84 & "*",#REF!,"*" & Index!$D$18 & "*",#REF!,"*" & Index!$D$23 & "*",#REF!,"*" & Index!$D$16 & "*",#REF!,"*" & Index!$D$20 & "*") -> #REF! | N84: 11984738 | O84: =+M84-N84 -> #REF! | P84: =IFERROR(IF(((M84/N84)-1)=0,"-",((M84/N84)-1)),"-") -> - | Q84: =SUMIFS(#REF!,#REF!,"*" & $C84 & "*",#REF!,"*" & Index!$D$12 & "*",#REF!,"*" & Index!$D$24 & "*",#REF!,"*" & Index!$D$16 & "*") + SUMIFS(#REF!,#REF!,"*" & $C84 & "*",#REF!,"*" & Index!$D$18 & "*",#REF!,"*" & Index!$D$24 & "*",#REF!,"*" & Index!$D$16 & "*",#REF!,"*" & Index!$D$20 & "*") -> #REF! | R84: 1831790 | S84: =+Q84-R84 -> #REF! | T84: =IFERROR(IF(((Q84/R84)-1)=0,"-",((Q84/R84)-1)),"-") -> - | U84: =SUMIFS(#REF!,#REF!,"*" & C84 &"*",#REF!,"*" & Index!$D$12 & "*",#REF!,"*" & Index!$D$17 & "*")+SUMIFS(#REF!,#REF!,"*" & C84 &"*",#REF!,"*" & Index!$D$18 & "*",#REF!,"*" & Index!$D$17 & "*",#REF!,"*" & Index!$D$20 & "*") -> #REF! | V84: -2390070 | W84: =+U84-V84 -> #REF! | X84: =IFERROR(IF(((U84/V84)-1)=0,"-",((U84/V84)-1)),"-") -> - | Y84: =SUMIFS(#REF!,#REF!,"*" & C84 & "*",#REF!,"*" & Index!$D$12 & "*")+ SUMIFS(#REF!,#REF!,"*" & C84 & "*",#REF!,"*" & Index!$D$18 & "*",#REF!,"*" & Index!$D$20 & "*") -> #REF! | Z84: 116454088 | AA84: =+Y84-Z84 -> #REF! | AB84: =IFERROR(IF(((Y84/Z84)-1)=0,"-",((Y84/Z84)-1)),"-") -> -
A85: =+LEN(C85) -> 8 | C85: NACE1304 | E85: =SUMIFS(#REF!,#REF!,"*" & C85 & "*",#REF!,"*" & Index!$D$12 & "*",#REF!,"*" & Index!$D$16 & "*")+SUMIFS(#REF!,#REF!,"*" & C85 & "*",#REF!,"*" & Index!$D$18 & "*",#REF!,"*" & Index!$D$20 & "*") -> #REF! | F85: 3549078 | G85: =+E85-F85 -> #REF! | H85: =IFERROR(IF(((E85/F85)-1)=0,"-",((E85/F85)-1)),"-") -> - | I85: =+E85-M85-Q85 -> #REF! | J85: 2302576 | K85: =+I85-J85 -> #REF! | L85: =IFERROR(IF(((I85/J85)-1)=0,"-",((I85/J85)-1)),"-") -> - | M85: =SUMIFS(#REF!,#REF!,"*" & $C85 & "*",#REF!,"*" & Index!$D$12 & "*",#REF!,"*" & Index!$D$23 & "*",#REF!,"*" & Index!$D$16 & "*") + SUMIFS(#REF!,#REF!,"*" & $C85 & "*",#REF!,"*" & Index!$D$18 & "*",#REF!,"*" & Index!$D$23 & "*",#REF!,"*" & Index!$D$16 & "*",#REF!,"*" & Index!$D$20 & "*") -> #REF! | N85: 979190 | O85: =+M85-N85 -> #REF! | P85: =IFERROR(IF(((M85/N85)-1)=0,"-",((M85/N85)-1)),"-") -> - | Q85: =SUMIFS(#REF!,#REF!,"*" & $C85 & "*",#REF!,"*" & Index!$D$12 & "*",#REF!,"*" & Index!$D$24 & "*",#REF!,"*" & Index!$D$16 & "*") + SUMIFS(#REF!,#REF!,"*" & $C85 & "*",#REF!,"*" & Index!$D$18 & "*",#REF!,"*" & Index!$D$24 & "*",#REF!,"*" & Index!$D$16 & "*",#REF!,"*" & Index!$D$20 & "*") -> #REF! | R85: 267312 | S85: =+Q85-R85 -> #REF! | T85: =IFERROR(IF(((Q85/R85)-1)=0,"-",((Q85/R85)-1)),"-") -> - | U85: =SUMIFS(#REF!,#REF!,"*" & C85 &"*",#REF!,"*" & Index!$D$12 & "*",#REF!,"*" & Index!$D$17 & "*")+SUMIFS(#REF!,#REF!,"*" & C85 &"*",#REF!,"*" & Index!$D$18 & "*",#REF!,"*" & Index!$D$17 & "*",#REF!,"*" & Index!$D$20 & "*") -> #REF! | V85: -234068 | W85: =+U85-V85 -> #REF! | X85: =IFERROR(IF(((U85/V85)-1)=0,"-",((U85/V85)-1)),"-") -> - | Y85: =SUMIFS(#REF!,#REF!,"*" & C85 & "*",#REF!,"*" & Index!$D$12 & "*")+ SUMIFS(#REF!,#REF!,"*" & C85 & "*",#REF!,"*" & Index!$D$18 & "*",#REF!,"*" & Index!$D$20 & "*") -> #REF! | Z85: 3315010 | AA85: =+Y85-Z85 -> #REF! | AB85: =IFERROR(IF(((Y85/Z85)-1)=0,"-",((Y85/Z85)-1)),"-") -> -
