Workbook
Name asefadf: #REF!
Name asefadf: #REF!
Name asefadf: #REF!
Name asefadf: #REF!
Name asefadf: #REF!
Name asefadf: #REF!
Name bn: #REF!
Name bn: #REF!
Name bn: #REF!

Sheet PlanoV1.0
H1: =I1/8/5 -> 68.2 | I1: =SUM(J1:AF1) -> 2728 | K1: =K4*8*5 -> 124 | L1: =L4*8*5 -> 124 | M1: =M4*8*5 -> 124 | N1: =N4*8*5 -> 124 | O1: =O4*8*5 -> 124 | P1: =P4*8*5 -> 124 | Q1: =Q4*8*5 -> 124 | R1: =R4*8*5 -> 124 | ... BU1: =BU4*8*5 -> 84
I2: VAL | K2: =K3-K4 -> 0 | L2: =L3-L4 -> 0 | M2: =M3-M4 -> 0 | N2: =N3-N4 -> 0 | O2: =O3-O4 -> 0 | P2: =P3-P4 -> 0 | Q2: =Q3-Q4 -> 0 | R2: =R3-R4 -> 0 | ... BA2: =BA3-BA4 -> 0 | BC2: =BC3-BC4 -> 0 | BD2: =BD3-BD4 -> 0 | BE2: =BE3-BE4 -> 0 | BF2: =BF3-BF4 -> 0 | BG2: =BG3-BG4 -> 0 | BH2: =BH3-BH4 -> 0 | BI2: =BI3-BI4 -> 0 | BJ2: =BJ3-BJ4 -> 0 | ... BU2: =BU3-BU4 -> 0
I3: FTE REAIS | K3: =SUM(K9:K226) -> 3.1 | L3: =SUM(L9:L226) -> 3.1 | M3: =SUM(M9:M226) -> 3.1 | N3: =SUM(N9:N226) -> 3.1 | O3: =SUM(O9:O226) -> 3.1 | P3: =SUM(P9:P226) -> 3.1 | Q3: =SUM(Q9:Q226) -> 3.1 | R3: =SUM(R9:R226) -> 3.1 | ... BA3: =SUM(BA9:BA226) -> 2.1 | BC3: =SUM(BC9:BC226) -> 2.1 | BD3: =SUM(BD9:BD226) -> 2.1 | BE3: =SUM(BE9:BE226) -> 2.1 | BF3: =SUM(BF9:BF226) -> 2.1 | BG3: =SUM(BG9:BG226) -> 2.1 | BH3: =SUM(BH9:BH226) -> 2.1 | BI3: =SUM(BI9:BI226) -> 2.1 | BJ3: =SUM(BJ9:BJ226) -> 2.1 | ... BU3: =SUM(BU9:BU226) -> 2.1
I4: FTE ESP. | K4: 3.1 | L4: 3.1 | M4: 3.1 | N4: 3.1 | O4: 3.1 | P4: 3.1 | Q4: 3.1 | R4: 3.1 | S4: 3.1 | T4: 3.1 | U4: 3.1 | V4: 3.1 | W4: 3.1 | X4: 3.1 | Y4: 3.1 | Z4: 3.1 | AA4: 3.1 | AB4: 3.1 | AC4: 3.1 | AD4: 3.1 | AE4: 3.1 | AF4: 3.1 | AG4: 2.1 | AH4: 2.1 | AI4: 2.1 | AJ4: 2.1 | AK4: 2.1 | AL4: 2.1 | AM4: 2.1 | AN4: 2.1 | AO4: 2.1 | AP4: 2.1 | AQ4: 2.1 | AR4: 2.1 | AS4: 2.1 | AT4: 2.1 | AU4: 2.1 | AV4: 2.1 | AW4: 2.1 | AX4: 2.1 | AY4: 2.1 | AZ4: 2.1 | BA4: 2.1 | BC4: 2.1 | BD4: 2.1 | BE4: 2.1 | BF4: 2.1 | BG4: 2.1 | BH4: 2.1 | BI4: 2.1 | BJ4: 2.1 | BK4: 2.1 | BL4: 2.1 | BM4: 2.1 | BN4: 2.1 | BO4: 2.1 | BP4: 2.1 | BQ4: 2.1 | BR4: 2.1 | BS4: 2.1 | BT4: 2.1 | BU4: 2.1
J5: Janeiro | AG5: Fevereiro | BA5: Março | BV5: Abril
J6: 45649 | K6: 45650 | L6: 45651 | M6: 45652 | N6: 45653 | O6: 45649 | P6: 45650 | Q6: 45651 | R6: 45652 | S6: 45653 | T6: 45649 | U6: 45650 | V6: 45651 | W6: 45652 | X6: 45653 | Y6: 45649 | Z6: 45650 | AA6: 45651 | AB6: 45652 | AC6: 45653 | AD6: 45649 | AE6: 45650 | AF6: 45651 | AG6: 45652 | AH6: 45653 | AI6: 45649 | AJ6: 45650 | AK6: 45651 | AL6: 45652 | AM6: 45653 | AN6: 45649 | AO6: 45650 | AP6: 45651 | AQ6: 45652 | AR6: 45653 | AS6: 45649 | AT6: 45650 | AU6: 45651 | AV6: 45652 | AW6: 45653 | AX6: 45649 | AY6: 45650 | AZ6: 45651 | BA6: 45652 | BB6: 45653 | BC6: 45649 | BD6: 45650 | BE6: 45651 | BF6: 45652 | BG6: 45653 | BH6: 45649 | BI6: 45650 | BJ6: 45651 | BK6: 45652 | BL6: 45653 | BM6: 45649 | BN6: 45650 | BO6: 45651 | BP6: 45652 | BQ6: 45653 | BR6: 45649 | BS6: 45650 | BT6: 45651 | BU6: 45652 | BV6: 45653 | BW6: 45649 | BX6: 45650 | BY6: 45651 | BZ6: 45652 | CA6: 45653 | CB6: 45649 | CC6: 45650 | CD6: 45651 | CE6: 45652 | CF6: 45653 | CG6: 45649 | CH6: 45650 | CI6: 45651 | CJ6: 45652 | CK6: 45653 | CL6: 45649 | CM6: 45650 | CN6: 45651 | CO6: 45652 | CP6: 45653 | CQ6: 45649
I7: 45657 | J7: =WORKDAY(I7,1) -> 45658 | K7: =WORKDAY(J7,1) -> 45659 | L7: =WORKDAY(K7,1) -> 45660 | M7: =WORKDAY(L7,1) -> 45663 | N7: =WORKDAY(M7,1) -> 45664 | O7: =WORKDAY(N7,1) -> 45665 | P7: =WORKDAY(O7,1) -> 45666 | Q7: =WORKDAY(P7,1) -> 45667 | ... X7: =WORKDAY(W7,1) -> 45678
F8: # Campos | G8: Duração (horas) | H8: Duração (Dias) | I8: VAL | J8: =WORKDAY(I7,1) -> 45658 | K8: =WORKDAY(J8,1) -> 45659 | L8: =WORKDAY(K8,1) -> 45660 | M8: =WORKDAY(L8,1) -> 45663 | N8: =WORKDAY(M8,1) -> 45664 | O8: =WORKDAY(N8,1) -> 45665 | P8: =WORKDAY(O8,1) -> 45666 | Q8: =WORKDAY(P8,1) -> 45667 | R8: =WORKDAY(Q8,1) -> 45670 | ... CQ8: =WORKDAY(CP8,1) -> 45777
C10: Gestão Projeto | F10: n.a. | G10: =H10*8*5 -> 0 | H10: =SUM(J10:M10) -> 0
C11: Gestão Projeto | F11: n.a. | G11: =H11*8*5 -> 12 | H11: =SUM(J11:M11) -> 0.3 | I11: =SUM(J11:M11)-H11 -> 0 | K11: 0.1 | L11: 0.1 | M11: 0.1 | N11: 0.1 | O11: 0.1 | P11: 0.1 | Q11: 0.1 | R11: 0.1 | S11: 0.1 | T11: 0.1 | U11: 0.1 | V11: 0.1 | W11: 0.1 | X11: 0.1 | Y11: 0.1 | Z11: 0.1 | AA11: 0.1 | AB11: 0.1 | AC11: 0.1 | AD11: 0.1 | AE11: 0.1 | AF11: 0.1 | AG11: 0.1 | AH11: 0.1 | AI11: 0.1 | AJ11: 0.1 | AK11: 0.1 | AL11: 0.1 | AM11: 0.1 | AN11: 0.1 | AO11: 0.1 | AP11: 0.1 | AQ11: 0.1 | AR11: 0.1 | AS11: 0.1 | AT11: 0.1 | AU11: 0.1 | AV11: 0.1 | AW11: 0.1 | AX11: 0.1 | AY11: 0.1 | AZ11: 0.1 | BA11: 0.1 | BC11: 0.1 | BD11: 0.1 | BE11: 0.1 | BF11: 0.1 | BG11: 0.1 | BH11: 0.1 | BI11: 0.1 | BJ11: 0.1 | BK11: 0.1 | BL11: 0.1 | BM11: 0.1 | BN11: 0.1 | BO11: 0.1 | BP11: 0.1 | BQ11: 0.1 | BR11: 0.1 | BS11: 0.1 | BT11: 0.1 | BU11: 0.1 | BV11: 0.1 | BW11: 0.1 | BX11: 0.1 | BY11: 0.1 | BZ11: 0.1 | CA11: 0.1 | CB11: 0.1 | CC11: 0.1 | CD11: 0.1 | CE11: 0.1 | CF11: 0.1 | CG11: 0.1 | CH11: 0.1 | CJ11: 0.1 | CK11: 0.1 | CL11: 0.1 | CM11: 0.1 | CO11: 0.1 | CP11: 0.1 | CQ11: 0.1
C12: 1. Re-especificações + Simulação + Testes + Re-testes requisitos atuais) | G12: =SUM(G13:G15) -> 128 | H12: =ROUND(SUM(H13:H15),0) -> 16
C13: MunichRe | G13: 16 | H13: =ROUNDUP(G13/8,1) -> 2 | I13: 0 | K13: 3
C14: Gloval - Tabela intermédia | G14: 16 | H14: =ROUNDUP(G14/8,1) -> 2 | I14: 0 | L14: 3
C15: Re-testes | G15: =12*8 -> 96 | H15: =ROUNDUP(G15/8,1) -> 12 | I15: 0 | M15: 3 | N15: 3 | O15: 3 | P15: 3 | Q15: 3 | R15: 3 | S15: 3 | T15: 3 | U15: 3 | V15: 3 | W15: 3 | X15: 3
C16: 2. Novos Campos (Especificação + Simulação + Testes+ Re-testes) | F16: =F17+F66 -> 68 | G16: =G17+G66+G87+G156+G225 -> 311.5 | H16: =H17+H66+H87+H156+H225 -> 46
C17: Especificação de Requisitos - P3 | F17: =COUNTA(E18:E65) -> 48 | G17: =SUM(G18:G55) -> 86 | H17: =ROUND(SUM(H18:H55),0) -> 13
B18: =Table1[[#Headers],[Especificação]] -> Especificação | C18: =D18&"_"&E18 -> ENTITY_TXNMY_ELGBL_CAPEX_W | D18: ENTITY | E18: TXNMY_ELGBL_CAPEX_W | G18: =INDEX(Table1[[Especificação]:[Total Testes]],MATCH(PlanoV1.0!C18,Table1[CONCAT],0),MATCH(PlanoV1.0!B18,Table1[[#Headers],[Especificação]:[Total Testes]],0)) -> 8 | H18: =ROUNDUP(G18/8,1) -> 1 | I18: =SUM(J18:CQ18)-H18 -> 0 | Y18: 1
B19: =Table1[[#Headers],[Especificação]] -> Especificação | C19: =D19&"_"&E19 -> ENTITY_TXNMY_ELGBL_TRNVR_W | D19: ENTITY | E19: TXNMY_ELGBL_TRNVR_W | G19: =INDEX(Table1[[Especificação]:[Total Testes]],MATCH(PlanoV1.0!C19,Table1[CONCAT],0),MATCH(PlanoV1.0!B19,Table1[[#Headers],[Especificação]:[Total Testes]],0)) -> 8 | H19: =ROUNDUP(G19/8,1) -> 1 | I19: =SUM(J19:CQ19)-H19 -> -0.5 | Z19: 0.5
B20: =Table1[[#Headers],[Especificação]] -> Especificação | C20: =D20&"_"&E20 -> ENTITY_TXNMY_ELGBL_CAPEX_P | D20: ENTITY | E20: TXNMY_ELGBL_CAPEX_P | G20: =INDEX(Table1[[Especificação]:[Total Testes]],MATCH(PlanoV1.0!C20,Table1[CONCAT],0),MATCH(PlanoV1.0!B20,Table1[[#Headers],[Especificação]:[Total Testes]],0)) -> 1 | H20: =ROUNDUP(G20/8,1) -> 0.2 | I20: =SUM(J20:CQ20)-H20 -> 0.1 | Z20: 0.3
B21: =Table1[[#Headers],[Especificação]] -> Especificação | C21: =D21&"_"&E21 -> ENTITY_TXNMY_ELGBL_TRNVR_P | D21: ENTITY | E21: TXNMY_ELGBL_TRNVR_P | G21: =INDEX(Table1[[Especificação]:[Total Testes]],MATCH(PlanoV1.0!C21,Table1[CONCAT],0),MATCH(PlanoV1.0!B21,Table1[[#Headers],[Especificação]:[Total Testes]],0)) -> 1 | H21: =ROUNDUP(G21/8,1) -> 0.2 | I21: =SUM(J21:CQ21)-H21 -> 0.1 | Z21: 0.2 | AA21: 0.1
B22: =Table1[[#Headers],[Especificação]] -> Especificação | C22: =D22&"_"&E22 -> ENTITY_TXNMY_ELGBL_CAPEX_B | D22: ENTITY | E22: TXNMY_ELGBL_CAPEX_B | G22: =INDEX(Table1[[Especificação]:[Total Testes]],MATCH(PlanoV1.0!C22,Table1[CONCAT],0),MATCH(PlanoV1.0!B22,Table1[[#Headers],[Especificação]:[Total Testes]],0)) -> 1 | H22: =ROUNDUP(G22/8,1) -> 0.2 | I22: =SUM(J22:CQ22)-H22 -> 0.1 | AA22: 0.3
B23: =Table1[[#Headers],[Especificação]] -> Especificação | C23: =D23&"_"&E23 -> ENTITY_TXNMY_ELGBL_TRNVR_B | D23: ENTITY | E23: TXNMY_ELGBL_TRNVR_B | G23: =INDEX(Table1[[Especificação]:[Total Testes]],MATCH(PlanoV1.0!C23,Table1[CONCAT],0),MATCH(PlanoV1.0!B23,Table1[[#Headers],[Especificação]:[Total Testes]],0)) -> 1 | H23: =ROUNDUP(G23/8,1) -> 0.2 | I23: =SUM(J23:CQ23)-H23 -> 0.1 | AA23: 0.3
B24: =Table1[[#Headers],[Especificação]] -> Especificação | C24: =D24&"_"&E24 -> ENTITY_TXNMY_ELGBL_CAPEX_CE | D24: ENTITY | E24: TXNMY_ELGBL_CAPEX_CE | G24: =INDEX(Table1[[Especificação]:[Total Testes]],MATCH(PlanoV1.0!C24,Table1[CONCAT],0),MATCH(PlanoV1.0!B24,Table1[[#Headers],[Especificação]:[Total Testes]],0)) -> 1 | H24: =ROUNDUP(G24/8,1) -> 0.2 | I24: =SUM(J24:CQ24)-H24 -> 0 | AA24: 0.2
B25: =Table1[[#Headers],[Especificação]] -> Especificação | C25: =D25&"_"&E25 -> ENTITY_TXNMY_ELGBL_TRNVR_CE | D25: ENTITY | E25: TXNMY_ELGBL_TRNVR_CE | G25: =INDEX(Table1[[Especificação]:[Total Testes]],MATCH(PlanoV1.0!C25,Table1[CONCAT],0),MATCH(PlanoV1.0!B25,Table1[[#Headers],[Especificação]:[Total Testes]],0)) -> 1 | H25: =ROUNDUP(G25/8,1) -> 0.2 | I25: =SUM(J25:CQ25)-H25 -> 0 | AA25: 0.1 | AB25: 0.1
B26: =Table1[[#Headers],[Especificação]] -> Especificação | C26: =D26&"_"&E26 -> ENTITY_PURE_CAPEX_P | D26: ENTITY | E26: PURE_CAPEX_P | G26: =INDEX(Table1[[Especificação]:[Total Testes]],MATCH(PlanoV1.0!C26,Table1[CONCAT],0),MATCH(PlanoV1.0!B26,Table1[[#Headers],[Especificação]:[Total Testes]],0)) -> 1 | H26: =ROUNDUP(G26/8,1) -> 0.2 | I26: =SUM(J26:CQ26)-H26 -> 0 | AB26: 0.2
B27: =Table1[[#Headers],[Especificação]] -> Especificação | C27: =D27&"_"&E27 -> ENTITY_PURE_TRNVR_P | D27: ENTITY | E27: PURE_TRNVR_P | G27: =INDEX(Table1[[Especificação]:[Total Testes]],MATCH(PlanoV1.0!C27,Table1[CONCAT],0),MATCH(PlanoV1.0!B27,Table1[[#Headers],[Especificação]:[Total Testes]],0)) -> 1 | H27: =ROUNDUP(G27/8,1) -> 0.2 | I27: =SUM(J27:CQ27)-H27 -> 0 | AB27: 0.2
B28: =Table1[[#Headers],[Especificação]] -> Especificação | C28: =D28&"_"&E28 -> ENTITY_PURE_CAPEX_B | D28: ENTITY | E28: PURE_CAPEX_B | G28: =INDEX(Table1[[Especificação]:[Total Testes]],MATCH(PlanoV1.0!C28,Table1[CONCAT],0),MATCH(PlanoV1.0!B28,Table1[[#Headers],[Especificação]:[Total Testes]],0)) -> 1 | H28: =ROUNDUP(G28/8,1) -> 0.2 | I28: =SUM(J28:CQ28)-H28 -> 0 | AB28: 0.2
B29: =Table1[[#Headers],[Especificação]] -> Especificação | C29: =D29&"_"&E29 -> ENTITY_PURE_TRNVR_B | D29: ENTITY | E29: PURE_TRNVR_B | G29: =INDEX(Table1[[Especificação]:[Total Testes]],MATCH(PlanoV1.0!C29,Table1[CONCAT],0),MATCH(PlanoV1.0!B29,Table1[[#Headers],[Especificação]:[Total Testes]],0)) -> 1 | H29: =ROUNDUP(G29/8,1) -> 0.2 | I29: =SUM(J29:CQ29)-H29 -> 0 | AB29: 0.2
B30: =Table1[[#Headers],[Especificação]] -> Especificação | C30: =D30&"_"&E30 -> ENTITY_PURE_CAPEX_W | D30: ENTITY | E30: PURE_CAPEX_W | G30: =INDEX(Table1[[Especificação]:[Total Testes]],MATCH(PlanoV1.0!C30,Table1[CONCAT],0),MATCH(PlanoV1.0!B30,Table1[[#Headers],[Especificação]:[Total Testes]],0)) -> 1 | H30: =ROUNDUP(G30/8,1) -> 0.2 | I30: =SUM(J30:CQ30)-H30 -> 0 | AB30: 0.1 | AC30: 0.1
B31: =Table1[[#Headers],[Especificação]] -> Especificação | C31: =D31&"_"&E31 -> ENTITY_PURE_TRNVR_W | D31: ENTITY | E31: PURE_TRNVR_W | G31: =INDEX(Table1[[Especificação]:[Total Testes]],MATCH(PlanoV1.0!C31,Table1[CONCAT],0),MATCH(PlanoV1.0!B31,Table1[[#Headers],[Especificação]:[Total Testes]],0)) -> 1 | H31: =ROUNDUP(G31/8,1) -> 0.2 | I31: =SUM(J31:CQ31)-H31 -> 0 | AC31: 0.2
B32: =Table1[[#Headers],[Especificação]] -> Especificação | C32: =D32&"_"&E32 -> ENTITY_PURE_CAPEX_CE | D32: ENTITY | E32: PURE_CAPEX_CE | G32: =INDEX(Table1[[Especificação]:[Total Testes]],MATCH(PlanoV1.0!C32,Table1[CONCAT],0),MATCH(PlanoV1.0!B32,Table1[[#Headers],[Especificação]:[Total Testes]],0)) -> 1 | H32: =ROUNDUP(G32/8,1) -> 0.2 | I32: =SUM(J32:CQ32)-H32 -> 0 | AC32: 0.2
B33: =Table1[[#Headers],[Especificação]] -> Especificação | C33: =D33&"_"&E33 -> ENTITY_PURE_TRNVR_CE | D33: ENTITY | E33: PURE_TRNVR_CE | G33: =INDEX(Table1[[Especificação]:[Total Testes]],MATCH(PlanoV1.0!C33,Table1[CONCAT],0),MATCH(PlanoV1.0!B33,Table1[[#Headers],[Especificação]:[Total Testes]],0)) -> 1 | H33: =ROUNDUP(G33/8,1) -> 0.2 | I33: =SUM(J33:CQ33)-H33 -> 0 | AC33: 0.2
B34: =Table1[[#Headers],[Especificação]] -> Especificação | C34: =D34&"_"&E34 -> ENTITY_ENBLNG_CAPEX_W | D34: ENTITY | E34: ENBLNG_CAPEX_W | G34: =INDEX(Table1[[Especificação]:[Total Testes]],MATCH(PlanoV1.0!C34,Table1[CONCAT],0),MATCH(PlanoV1.0!B34,Table1[[#Headers],[Especificação]:[Total Testes]],0)) -> 1 | H34: =ROUNDUP(G34/8,1) -> 0.2 | I34: =SUM(J34:CQ34)-H34 -> 0 | AC34: 0.2
B35: =Table1[[#Headers],[Especificação]] -> Especificação | C35: =D35&"_"&E35 -> ENTITY_ENBLNG_TRNVR_W | D35: ENTITY | E35: ENBLNG_TRNVR_W | G35: =INDEX(Table1[[Especificação]:[Total Testes]],MATCH(PlanoV1.0!C35,Table1[CONCAT],0),MATCH(PlanoV1.0!B35,Table1[[#Headers],[Especificação]:[Total Testes]],0)) -> 1 | H35: =ROUNDUP(G35/8,1) -> 0.2 | I35: =SUM(J35:CQ35)-H35 -> 0 | AC35: 0.1 | AD35: 0.1
B36: =Table1[[#Headers],[Especificação]] -> Especificação | C36: =D36&"_"&E36 -> ENTITY_ENBLNG_CAPEX_CE | D36: ENTITY | E36: ENBLNG_CAPEX_CE | G36: =INDEX(Table1[[Especificação]:[Total Testes]],MATCH(PlanoV1.0!C36,Table1[CONCAT],0),MATCH(PlanoV1.0!B36,Table1[[#Headers],[Especificação]:[Total Testes]],0)) -> 1 | H36: =ROUNDUP(G36/8,1) -> 0.2 | I36: =SUM(J36:CQ36)-H36 -> 0 | AD36: 0.2
B37: =Table1[[#Headers],[Especificação]] -> Especificação | C37: =D37&"_"&E37 -> ENTITY_ENBLNG_TRNVR_CE | D37: ENTITY | E37: ENBLNG_TRNVR_CE | G37: =INDEX(Table1[[Especificação]:[Total Testes]],MATCH(PlanoV1.0!C37,Table1[CONCAT],0),MATCH(PlanoV1.0!B37,Table1[[#Headers],[Especificação]:[Total Testes]],0)) -> 1 | H37: =ROUNDUP(G37/8,1) -> 0.2 | I37: =SUM(J37:CQ37)-H37 -> 0 | AD37: 0.2
B38: =Table1[[#Headers],[Especificação]] -> Especificação | C38: =D38&"_"&E38 -> INSTRUMENT_TYP_OFF_BLNC_PRDCT | D38: INSTRUMENT | E38: TYP_OFF_BLNC_PRDCT | G38: =INDEX(Table1[[Especificação]:[Total Testes]],MATCH(PlanoV1.0!C38,Table1[CONCAT],0),MATCH(PlanoV1.0!B38,Table1[[#Headers],[Especificação]:[Total Testes]],0)) -> 1 | H38: =ROUNDUP(G38/8,1) -> 0.2 | I38: =SUM(J38:CQ38)-H38 -> 0 | AD38: 0.2
B39: =Table1[[#Headers],[Especificação]] -> Especificação | C39: =D39&"_"&E39 -> INSTRUMENT_FLG_MNMM_SFGRDS | D39: INSTRUMENT | E39: FLG_MNMM_SFGRDS | G39: =INDEX(Table1[[Especificação]:[Total Testes]],MATCH(PlanoV1.0!C39,Table1[CONCAT],0),MATCH(PlanoV1.0!B39,Table1[[#Headers],[Especificação]:[Total Testes]],0)) -> 0 | H39: =ROUNDUP(G39/8,1) -> 0 | I39: =SUM(J39:CQ39)-H39 -> 1.3 | Y39: 1.3
B40: =Table1[[#Headers],[Especificação]] -> Especificação | C40: =D40&"_"&E40 -> INSTR_PROTECTION_TYP_RLTN | D40: INSTR_PROTECTION | E40: TYP_RLTN | G40: =INDEX(Table1[[Especificação]:[Total Testes]],MATCH(PlanoV1.0!C40,Table1[CONCAT],0),MATCH(PlanoV1.0!B40,Table1[[#Headers],[Especificação]:[Total Testes]],0)) -> 4 | H40: =ROUNDUP(G40/8,1) -> 0.5 | I40: =SUM(J40:CQ40)-H40 -> 0 | Y40: 0.5
B41: =Table1[[#Headers],[Especificação]] -> Especificação | C41: =D41&"_"&E41 -> PROTECTION_BLDNG_AR | D41: PROTECTION | E41: BLDNG_AR | G41: =INDEX(Table1[[Especificação]:[Total Testes]],MATCH(PlanoV1.0!C41,Table1[CONCAT],0),MATCH(PlanoV1.0!B41,Table1[[#Headers],[Especificação]:[Total Testes]],0)) -> 2 | H41: =ROUNDUP(G41/8,1) -> 0.3 | I41: =SUM(J41:CQ41)-H41 -> 0 | AD41: 0.3
B42: =Table1[[#Headers],[Especificação]] -> Especificação | C42: =D42&"_"&E42 -> PROTECTION_RL_ESTT_CRTFCTN | D42: PROTECTION | E42: RL_ESTT_CRTFCTN | G42: =INDEX(Table1[[Especificação]:[Total Testes]],MATCH(PlanoV1.0!C42,Table1[CONCAT],0),MATCH(PlanoV1.0!B42,Table1[[#Headers],[Especificação]:[Total Testes]],0)) -> 0 | H42: =ROUNDUP(G42/8,1) -> 0 | I42: =SUM(J42:CQ42)-H42 -> 1 | Z42: 1
B43: =Table1[[#Headers],[Especificação]] -> Especificação | C43: =D43&"_"&E43 -> PROTECTION_TYP_VHCL | D43: PROTECTION | E43: TYP_VHCL | G43: =INDEX(Table1[[Especificação]:[Total Testes]],MATCH(PlanoV1.0!C43,Table1[CONCAT],0),MATCH(PlanoV1.0!B43,Table1[[#Headers],[Especificação]:[Total Testes]],0)) -> 0 | H43: =ROUNDUP(G43/8,1) -> 0 | I43: =SUM(J43:CQ43)-H43 -> 1 | Z43: 1
B44: =Table1[[#Headers],[Especificação]] -> Especificação | C44: =D44&"_"&E44 -> PROTECTION_DT_RGSTRTN | D44: PROTECTION | E44: DT_RGSTRTN | G44: =INDEX(Table1[[Especificação]:[Total Testes]],MATCH(PlanoV1.0!C44,Table1[CONCAT],0),MATCH(PlanoV1.0!B44,Table1[[#Headers],[Especificação]:[Total Testes]],0)) -> 0 | H44: =ROUNDUP(G44/8,1) -> 0 | I44: =SUM(J44:CQ44)-H44 -> 1 | AA44: 1
B45: =Table1[[#Headers],[Especificação]] -> Especificação | C45: =D45&"_"&E45 -> PROTECTION_PRMRY_ENRGY_DMND_NN_RNWBL | D45: PROTECTION | E45: PRMRY_ENRGY_DMND_NN_RNWBL | G45: =INDEX(Table1[[Especificação]:[Total Testes]],MATCH(PlanoV1.0!C45,Table1[CONCAT],0),MATCH(PlanoV1.0!B45,Table1[[#Headers],[Especificação]:[Total Testes]],0)) -> 10 | H45: =ROUNDUP(G45/8,1) -> 1.3 | I45: =SUM(J45:CQ45)-H45 -> 0 | AB45: 1.3
B46: =Table1[[#Headers],[Especificação]] -> Especificação | C46: =D46&"_"&E46 -> PROTECTION_PRMRY_ENRGY_DMND_TTL | D46: PROTECTION | E46: PRMRY_ENRGY_DMND_TTL | G46: =INDEX(Table1[[Especificação]:[Total Testes]],MATCH(PlanoV1.0!C46,Table1[CONCAT],0),MATCH(PlanoV1.0!B46,Table1[[#Headers],[Especificação]:[Total Testes]],0)) -> 8 | H46: =ROUNDUP(G46/8,1) -> 1 | I46: =SUM(J46:CQ46)-H46 -> 0 | AA46: 1
B47: =Table1[[#Headers],[Especificação]] -> Especificação | C47: =D47&"_"&E47 -> PROTECTION_PRMRY_ENRGY_DMND_RFRNC_VL | D47: PROTECTION | E47: PRMRY_ENRGY_DMND_RFRNC_VL | G47: =INDEX(Table1[[Especificação]:[Total Testes]],MATCH(PlanoV1.0!C47,Table1[CONCAT],0),MATCH(PlanoV1.0!B47,Table1[[#Headers],[Especificação]:[Total Testes]],0)) -> 8 | H47: =ROUNDUP(G47/8,1) -> 1 | I47: =SUM(J47:CQ47)-H47 -> 0 | AC47: 1
B48: =Table1[[#Headers],[Especificação]] -> Especificação | C48: =D48&"_"&E48 -> PROTECTION_RL_ESTT_CLMT_ZN | D48: PROTECTION | E48: RL_ESTT_CLMT_ZN | G48: =INDEX(Table1[[Especificação]:[Total Testes]],MATCH(PlanoV1.0!C48,Table1[CONCAT],0),MATCH(PlanoV1.0!B48,Table1[[#Headers],[Especificação]:[Total Testes]],0)) -> 8 | H48: =ROUNDUP(G48/8,1) -> 1 | I48: =SUM(J48:CQ48)-H48 -> 0 | AC48: 0.9 | AD48: 0.1
B49: =Table1[[#Headers],[Especificação]] -> Especificação | C49: =D49&"_"&E49 -> INSTR_ACTIVITY_COD_SOC | D49: INSTR_ACTIVITY | E49: COD_SOC | G49: =INDEX(Table1[[Especificação]:[Total Testes]],MATCH(PlanoV1.0!C49,Table1[CONCAT],0),MATCH(PlanoV1.0!B49,Table1[[#Headers],[Especificação]:[Total Testes]],0)) -> 1 | H49: =ROUNDUP(G49/8,1) -> 0.2 | I49: =SUM(J49:CQ49)-H49 -> 0.1 | AB49: 0.3
B50: =Table1[[#Headers],[Especificação]] -> Especificação | C50: =D50&"_"&E50 -> INSTR_ACTIVITY_DT_RFRNC | D50: INSTR_ACTIVITY | E50: DT_RFRNC | G50: =INDEX(Table1[[Especificação]:[Total Testes]],MATCH(PlanoV1.0!C50,Table1[CONCAT],0),MATCH(PlanoV1.0!B50,Table1[[#Headers],[Especificação]:[Total Testes]],0)) -> 1 | H50: =ROUNDUP(G50/8,1) -> 0.2 | I50: =SUM(J50:CQ50)-H50 -> 0 | Y50: 0.2
B51: =Table1[[#Headers],[Especificação]] -> Especificação | C51: =D51&"_"&E51 -> INSTR_ACTIVITY_INSTRMNT_ID | D51: INSTR_ACTIVITY | E51: INSTRMNT_ID | G51: =INDEX(Table1[[Especificação]:[Total Testes]],MATCH(PlanoV1.0!C51,Table1[CONCAT],0),MATCH(PlanoV1.0!B51,Table1[[#Headers],[Especificação]:[Total Testes]],0)) -> 1 | H51: =ROUNDUP(G51/8,1) -> 0.2 | I51: =SUM(J51:CQ51)-H51 -> 0.1 | AD51: 0.3
B52: =Table1[[#Headers],[Especificação]] -> Especificação | C52: =D52&"_"&E52 -> INSTR_ACTIVITY_PRCNTG_ACTVTY | D52: INSTR_ACTIVITY | E52: PRCNTG_ACTVTY | G52: =INDEX(Table1[[Especificação]:[Total Testes]],MATCH(PlanoV1.0!C52,Table1[CONCAT],0),MATCH(PlanoV1.0!B52,Table1[[#Headers],[Especificação]:[Total Testes]],0)) -> 4 | H52: =ROUNDUP(G52/8,1) -> 0.5 | I52: =SUM(J52:CQ52)-H52 -> 0 | AB52: 0.4 | AC52: 0.1
B53: =Table1[[#Headers],[Especificação]] -> Especificação | C53: =D53&"_"&E53 -> INSTR_ACTIVITY_FLG_SBSTNTL_CNTRBTN | D53: INSTR_ACTIVITY | E53: FLG_SBSTNTL_CNTRBTN | G53: =INDEX(Table1[[Especificação]:[Total Testes]],MATCH(PlanoV1.0!C53,Table1[CONCAT],0),MATCH(PlanoV1.0!B53,Table1[[#Headers],[Especificação]:[Total Testes]],0)) -> 4 | H53: =ROUNDUP(G53/8,1) -> 0.5 | I53: =SUM(J53:CQ53)-H53 -> 0 | AD53: 0.5
B54: =Table1[[#Headers],[Especificação]] -> Especificação | C54: =D54&"_"&E54 -> INSTR_ACTIVITY_FLG_DNSH_CMPLNC | D54: INSTR_ACTIVITY | E54: FLG_DNSH_CMPLNC | G54: =INDEX(Table1[[Especificação]:[Total Testes]],MATCH(PlanoV1.0!C54,Table1[CONCAT],0),MATCH(PlanoV1.0!B54,Table1[[#Headers],[Especificação]:[Total Testes]],0)) -> 0 | H54: =ROUNDUP(G54/8,1) -> 0 | I54: =SUM(J54:CQ54)-H54 -> 1.3 | AD54: 0.1 | AE54: 1.2
B55: =Table1[[#Headers],[Especificação]] -> Especificação | C55: =D55&"_"&E55 -> INSTR_ACTIVITY_DNSH_DTL | D55: INSTR_ACTIVITY | E55: DNSH_DTL | G55: =INDEX(Table1[[Especificação]:[Total Testes]],MATCH(PlanoV1.0!C55,Table1[CONCAT],0),MATCH(PlanoV1.0!B55,Table1[[#Headers],[Especificação]:[Total Testes]],0)) -> 0 | H55: =ROUNDUP(G55/8,1) -> 0 | I55: =SUM(J55:CQ55)-H55 -> 1 | AD55: 1
B56: =Table1[[#Headers],[Especificação]] -> Especificação | C56: =D56&"_"&E56 -> INSTR_ACTIVITY_ENTTY_NM | D56: INSTR_ACTIVITY | E56: ENTTY_NM | G56: 2 | H56: =ROUNDUP(G56/8,1) -> 0.3 | I56: =SUM(J56:CQ56)-H56 -> 0 | AE56: 0.3
B57: =Table1[[#Headers],[Especificação]] -> Especificação | C57: =D57&"_"&E57 -> INSTR_ACTIVITY_EC_GRP_NM | D57: INSTR_ACTIVITY | E57: EC_GRP_NM | G57: 2 | H57: =ROUNDUP(G57/8,1) -> 0.3 | I57: =SUM(J57:CQ57)-H57 -> 0 | AE57: 0.3
B58: =Table1[[#Headers],[Especificação]] -> Especificação | C58: =D58&"_"&E58 -> INSTR_ACTIVITY_FRBRNC_STTS_INSTRMNT | D58: INSTR_ACTIVITY | E58: FRBRNC_STTS_INSTRMNT | G58: 1 | H58: =ROUNDUP(G58/8,1) -> 0.2 | I58: =SUM(J58:CQ58)-H58 -> 0 | AE58: 0.2
B59: =Table1[[#Headers],[Especificação]] -> Especificação | C59: =D59&"_"&E59 -> INSTR_ACTIVITY_IFRS9_BHVRL_MTRTY | D59: INSTR_ACTIVITY | E59: IFRS9_BHVRL_MTRTY | G59: 1 | H59: =ROUNDUP(G59/8,1) -> 0.2 | I59: =SUM(J59:CQ59)-H59 -> 0 | AE59: 0.2
B60: =Table1[[#Headers],[Especificação]] -> Especificação | C60: =D60&"_"&E60 -> INSTR_ACTIVITY_LTV | D60: INSTR_ACTIVITY | E60: LTV | G60: 1 | H60: =ROUNDUP(G60/8,1) -> 0.2 | I60: =SUM(J60:CQ60)-H60 -> 0 | AE60: 0.2
B61: =Table1[[#Headers],[Especificação]] -> Especificação | C61: =D61&"_"&E61 -> INSTR_ACTIVITY_LTV_INCPTN | D61: INSTR_ACTIVITY | E61: LTV_INCPTN | G61: 1 | H61: =ROUNDUP(G61/8,1) -> 0.2 | I61: =SUM(J61:CQ61)-H61 -> 0 | AE61: 0.2
B62: =Table1[[#Headers],[Especificação]] -> Especificação | C62: =D62&"_"&E62 -> INSTR_ACTIVITY_ANNLSD_AGRD_RT | D62: INSTR_ACTIVITY | E62: ANNLSD_AGRD_RT | G62: 1 | H62: =ROUNDUP(G62/8,1) -> 0.2 | I62: =SUM(J62:CQ62)-H62 -> 0 | AE62: 0.2
B63: =Table1[[#Headers],[Especificação]] -> Especificação | C63: =D63&"_"&E63 -> INSTR_ACTIVITY_EIR_INCPTN | D63: INSTR_ACTIVITY | E63: EIR_INCPTN | G63: 1 | H63: =ROUNDUP(G63/8,1) -> 0.2 | I63: =SUM(J63:CQ63)-H63 -> 0 | AE63: 0.2
B64: =Table1[[#Headers],[Especificação]] -> Especificação | C64: =D64&"_"&E64 -> INSTR_ACTIVITY_NW_BSNSS | D64: INSTR_ACTIVITY | E64: NW_BSNSS | G64: 8 | H64: =ROUNDUP(G64/8,1) -> 1 | I64: =SUM(J64:CQ64)-H64 -> 0 | AF64: 1
B65: =Table1[[#Headers],[Especificação]] -> Especificação | C65: =D65&"_"&E65 -> INSTR_ACTIVITY_YR_CNSTRCTN | D65: INSTR_ACTIVITY | E65: YR_CNSTRCTN | G65: 1 | H65: =ROUNDUP(G65/8,1) -> 0.2 | I65: =SUM(J65:CQ65)-H65 -> 0 | AF65: 0.2
C66: Especificação de Requisitos - ESG Risks | F66: =+COUNTA(E67:E86) -> 20 | G66: =SUM(G67:G78) -> 10 | H66: =ROUND(SUM(H67:H78),0) -> 1
B67: =Table1[[#Headers],[Especificação]] -> Especificação | C67: =D67&"_"&E67 -> ENTITY_GRP_ECNMC_ACTVTY | D67: ENTITY | E67: GRP_ECNMC_ACTVTY | G67: =INDEX(Table1[[Especificação]:[Total Testes]],MATCH(PlanoV1.0!C67,Table1[CONCAT],0),MATCH(PlanoV1.0!B67,Table1[[#Headers],[Especificação]:[Total Testes]],0)) -> 2 | H67: =ROUNDUP(G67/8,1) -> 0.3 | I67: =SUM(J67:CQ67)-H67 -> 0 | AF67: 0.3
B68: =Table1[[#Headers],[Especificação]] -> Especificação | C68: =D68&"_"&E68 -> PROTECTION_TYP_EMSSNS_LBL | D68: PROTECTION | E68: TYP_EMSSNS_LBL | G68: =INDEX(Table1[[Especificação]:[Total Testes]],MATCH(PlanoV1.0!C68,Table1[CONCAT],0),MATCH(PlanoV1.0!B68,Table1[[#Headers],[Especificação]:[Total Testes]],0)) -> 0 | H68: =ROUNDUP(G68/8,1) -> 0 | I68: =SUM(J68:CQ68)-H68 -> 0.5 | AF68: 0.5
B69: =Table1[[#Headers],[Especificação]] -> Especificação | C69: =D69&"_"&E69 -> PROTECTION_EPC_EMSSNS_LBL | D69: PROTECTION | E69: EPC_EMSSNS_LBL | G69: =INDEX(Table1[[Especificação]:[Total Testes]],MATCH(PlanoV1.0!C69,Table1[CONCAT],0),MATCH(PlanoV1.0!B69,Table1[[#Headers],[Especificação]:[Total Testes]],0)) -> 2 | H69: =ROUNDUP(G69/8,1) -> 0.3 | I69: =SUM(J69:CQ69)-H69 -> 0 | AG69: 0.3
B70: =Table1[[#Headers],[Especificação]] -> Especificação | C70: =D70&"_"&E70 -> PROTECTION_VHCL_EMSSNS_LBL | D70: PROTECTION | E70: VHCL_EMSSNS_LBL | G70: =INDEX(Table1[[Especificação]:[Total Testes]],MATCH(PlanoV1.0!C70,Table1[CONCAT],0),MATCH(PlanoV1.0!B70,Table1[[#Headers],[Especificação]:[Total Testes]],0)) -> 0 | H70: =ROUNDUP(G70/8,1) -> 0 | I70: =SUM(J70:CQ70)-H70 -> 1 | AF70: 1
B71: =Table1[[#Headers],[Especificação]] -> Especificação | C71: =D71&"_"&E71 -> PROTECTION_TYP_EMSSNS_SCR | D71: PROTECTION | E71: TYP_EMSSNS_SCR | G71: =INDEX(Table1[[Especificação]:[Total Testes]],MATCH(PlanoV1.0!C71,Table1[CONCAT],0),MATCH(PlanoV1.0!B71,Table1[[#Headers],[Especificação]:[Total Testes]],0)) -> 2 | H71: =ROUNDUP(G71/8,1) -> 0.3 | I71: =SUM(J71:CQ71)-H71 -> 0 | AG71: 0.3
B72: =Table1[[#Headers],[Especificação]] -> Especificação | C72: =D72&"_"&E72 -> PROTECTION_EPC_EMSSNS_SCR | D72: PROTECTION | E72: EPC_EMSSNS_SCR | G72: =INDEX(Table1[[Especificação]:[Total Testes]],MATCH(PlanoV1.0!C72,Table1[CONCAT],0),MATCH(PlanoV1.0!B72,Table1[[#Headers],[Especificação]:[Total Testes]],0)) -> 4 | H72: =ROUNDUP(G72/8,1) -> 0.5 | I72: =SUM(J72:CQ72)-H72 -> 0 | AG72: 0.5
B73: =Table1[[#Headers],[Especificação]] -> Especificação | C73: =D73&"_"&E73 -> PROTECTION_VHCL_EMSSNS_SCR | D73: PROTECTION | E73: VHCL_EMSSNS_SCR | G73: =INDEX(Table1[[Especificação]:[Total Testes]],MATCH(PlanoV1.0!C73,Table1[CONCAT],0),MATCH(PlanoV1.0!B73,Table1[[#Headers],[Especificação]:[Total Testes]],0)) -> 0 | H73: =ROUNDUP(G73/8,1) -> 0 | I73: =SUM(J73:CQ73)-H73 -> 1.3 | AG73: 0.9 | AH73: 0.4
B74: =Table1[[#Headers],[Especificação]] -> Especificação | C74: =D74&"_"&E74 -> PROTECTION_INSRNC_ID | D74: PROTECTION | E74: INSRNC_ID | G74: =INDEX(Table1[[Especificação]:[Total Testes]],MATCH(PlanoV1.0!C74,Table1[CONCAT],0),MATCH(PlanoV1.0!B74,Table1[[#Headers],[Especificação]:[Total Testes]],0)) -> 0 | H74: =ROUNDUP(G74/8,1) -> 0 | I74: =SUM(J74:CQ74)-H74 -> 1.3 | AH74: 1.3
B75: =Table1[[#Headers],[Especificação]] -> Especificação | C75: =D75&"_"&E75 -> PROTECTION_TYP_HZRDS_INSRD | D75: PROTECTION | E75: TYP_HZRDS_INSRD | G75: =INDEX(Table1[[Especificação]:[Total Testes]],MATCH(PlanoV1.0!C75,Table1[CONCAT],0),MATCH(PlanoV1.0!B75,Table1[[#Headers],[Especificação]:[Total Testes]],0)) -> 0 | H75: =ROUNDUP(G75/8,1) -> 0 | I75: =SUM(J75:CQ75)-H75 -> 0.5 | AH75: 0.3 | AI75: 0.2
B76: =Table1[[#Headers],[Especificação]] -> Especificação | C76: =D76&"_"&E76 -> PROTECTION_AMNT_CVRD_INSRNC | D76: PROTECTION | E76: AMNT_CVRD_INSRNC | G76: =INDEX(Table1[[Especificação]:[Total Testes]],MATCH(PlanoV1.0!C76,Table1[CONCAT],0),MATCH(PlanoV1.0!B76,Table1[[#Headers],[Especificação]:[Total Testes]],0)) -> 0 | H76: =ROUNDUP(G76/8,1) -> 0 | I76: =SUM(J76:CQ76)-H76 -> 1.3 | AI76: 1.3
B77: =Table1[[#Headers],[Especificação]] -> Especificação | C77: =D77&"_"&E77 -> PROTECTION_DT_MTRTY_INSRNC | D77: PROTECTION | E77: DT_MTRTY_INSRNC | G77: =INDEX(Table1[[Especificação]:[Total Testes]],MATCH(PlanoV1.0!C77,Table1[CONCAT],0),MATCH(PlanoV1.0!B77,Table1[[#Headers],[Especificação]:[Total Testes]],0)) -> 0 | H77: =ROUNDUP(G77/8,1) -> 0 | I77: =SUM(J77:CQ77)-H77 -> 1.3 | AI77: 0.5 | AJ77: 0.8
B78: =Table1[[#Headers],[Especificação]] -> Especificação | C78: =D78&"_"&E78 -> PROTECTION_FLG_FRST_HM | D78: PROTECTION | E78: FLG_FRST_HM | G78: =INDEX(Table1[[Especificação]:[Total Testes]],MATCH(PlanoV1.0!C78,Table1[CONCAT],0),MATCH(PlanoV1.0!B78,Table1[[#Headers],[Especificação]:[Total Testes]],0)) -> 0 | H78: =ROUNDUP(G78/8,1) -> 0 | I78: =SUM(J78:CQ78)-H78 -> 0.5 | AJ78: 0.5
B79: =Table1[[#Headers],[Especificação]] -> Especificação | C79: =D79&"_"&E79 -> PROTECTION_INTRNL_SGMNT | D79: PROTECTION | E79: INTRNL_SGMNT | G79: 2 | H79: =ROUNDUP(G79/8,1) -> 0.3 | I79: =SUM(J79:CQ79)-H79 -> 0 | AJ79: 0.3
B80: =Table1[[#Headers],[Especificação]] -> Especificação | C80: =D80&"_"&E80 -> PROTECTION_EAD | D80: PROTECTION | E80: EAD | G80: 2 | H80: =ROUNDUP(G80/8,1) -> 0.3 | I80: =SUM(J80:CQ80)-H80 -> 0 | AJ80: 0.3
B81: =Table1[[#Headers],[Especificação]] -> Especificação | C81: =D81&"_"&E81 -> PROTECTION_OFF_BLNC_SHT_AMNT_INSTRMNT | D81: PROTECTION | E81: OFF_BLNC_SHT_AMNT_INSTRMNT | G81: 2 | H81: =ROUNDUP(G81/8,1) -> 0.3 | I81: =SUM(J81:CQ81)-H81 -> 0 | AJ81: 0.1 | AK81: 0.2
B82: =Table1[[#Headers],[Especificação]] -> Especificação | C82: =D82&"_"&E82 -> PROTECTION_INTRNL_SGMNT_CAT_MSTA | D82: PROTECTION | E82: INTRNL_SGMNT_CAT_MSTA | G82: 2 | H82: =ROUNDUP(G82/8,1) -> 0.3 | I82: =SUM(J82:CQ82)-H82 -> 0 | AK82: 0.3
B83: =Table1[[#Headers],[Especificação]] -> Especificação | C83: =D83&"_"&E83 -> PROTECTION_INTRNL_SGMNT_CATGSUB | D83: PROTECTION | E83: INTRNL_SGMNT_CATGSUB | G83: 2 | H83: =ROUNDUP(G83/8,1) -> 0.3 | I83: =SUM(J83:CQ83)-H83 -> 0 | AK83: 0.3
B84: =Table1[[#Headers],[Especificação]] -> Especificação | C84: =D84&"_"&E84 -> PROTECTION_RL_ESTT_ADDRSS | D84: PROTECTION | E84: RL_ESTT_ADDRSS | G84: =INDEX(Table1[[Especificação]:[Total Testes]],MATCH(PlanoV1.0!C84,Table1[CONCAT],0),MATCH(PlanoV1.0!B84,Table1[[#Headers],[Especificação]:[Total Testes]],0)) -> 2 | H84: =ROUNDUP(G84/8,1) -> 0.3 | I84: =SUM(J84:CQ84)-H84 -> 0 | AK84: 0.3
B85: =Table1[[#Headers],[Especificação]] -> Especificação | C85: =D85&"_"&E85 -> PROTECTION_RL_ESTT_CLLTRL_LCTN_INT | D85: PROTECTION | E85: RL_ESTT_CLLTRL_LCTN_INT | G85: =INDEX(Table1[[Especificação]:[Total Testes]],MATCH(PlanoV1.0!C85,Table1[CONCAT],0),MATCH(PlanoV1.0!B85,Table1[[#Headers],[Especificação]:[Total Testes]],0)) -> 2 | H85: =ROUNDUP(G85/8,1) -> 0.3 | I85: =SUM(J85:CQ85)-H85 -> 0 | AK85: 0.3
B86: =Table1[[#Headers],[Especificação]] -> Especificação | C86: =D86&"_"&E86 -> PROTECTION_RL_ESTT_CTY | D86: PROTECTION | E86: RL_ESTT_CTY | G86: =INDEX(Table1[[Especificação]:[Total Testes]],MATCH(PlanoV1.0!C86,Table1[CONCAT],0),MATCH(PlanoV1.0!B86,Table1[[#Headers],[Especificação]:[Total Testes]],0)) -> 2 | H86: =ROUNDUP(G86/8,1) -> 0.3 | I86: =SUM(J86:CQ86)-H86 -> 0 | AK86: 0.3
C87: Simulação campos (P3 + ESG Risks) | F87: =COUNTA(E88:E155) -> 68 | G87: =SUM(G88:G137) -> 69.5 | H87: =ROUND(SUM(H88:H137),0) -> 11
B88: =Table1[[#Headers],[Simulação]] -> Simulação | C88: =D88&"_"&E88 -> ENTITY_TXNMY_ELGBL_CAPEX_W | D88: ENTITY | E88: TXNMY_ELGBL_CAPEX_W | G88: =INDEX(Table1[[Especificação]:[Total Testes]],MATCH(PlanoV1.0!C88,Table1[CONCAT],0),MATCH(PlanoV1.0!B88,Table1[[#Headers],[Especificação]:[Total Testes]],0)) -> 6 | H88: =ROUNDUP(G88/8,1) -> 0.8 | I88: =SUM(J88:CQ88)-H88 -> 0 | AK88: 0.3 | AL88: 0.5
B89: =Table1[[#Headers],[Simulação]] -> Simulação | C89: =D89&"_"&E89 -> ENTITY_TXNMY_ELGBL_TRNVR_W | D89: ENTITY | E89: TXNMY_ELGBL_TRNVR_W | G89: =INDEX(Table1[[Especificação]:[Total Testes]],MATCH(PlanoV1.0!C89,Table1[CONCAT],0),MATCH(PlanoV1.0!B89,Table1[[#Headers],[Especificação]:[Total Testes]],0)) -> 6 | H89: =ROUNDUP(G89/8,1) -> 0.8 | I89: =SUM(J89:CQ89)-H89 -> -0.4 | AL89: 0.4
B90: =Table1[[#Headers],[Simulação]] -> Simulação | C90: =D90&"_"&E90 -> ENTITY_TXNMY_ELGBL_CAPEX_P | D90: ENTITY | E90: TXNMY_ELGBL_CAPEX_P | G90: =INDEX(Table1[[Especificação]:[Total Testes]],MATCH(PlanoV1.0!C90,Table1[CONCAT],0),MATCH(PlanoV1.0!B90,Table1[[#Headers],[Especificação]:[Total Testes]],0)) -> 1 | H90: =ROUNDUP(G90/8,1) -> 0.2 | I90: =SUM(J90:CQ90)-H90 -> 0 | AL90: 0.2
B91: =Table1[[#Headers],[Simulação]] -> Simulação | C91: =D91&"_"&E91 -> ENTITY_TXNMY_ELGBL_TRNVR_P | D91: ENTITY | E91: TXNMY_ELGBL_TRNVR_P | G91: =INDEX(Table1[[Especificação]:[Total Testes]],MATCH(PlanoV1.0!C91,Table1[CONCAT],0),MATCH(PlanoV1.0!B91,Table1[[#Headers],[Especificação]:[Total Testes]],0)) -> 1 | H91: =ROUNDUP(G91/8,1) -> 0.2 | I91: =SUM(J91:CQ91)-H91 -> 0 | AL91: 0.2
B92: =Table1[[#Headers],[Simulação]] -> Simulação | C92: =D92&"_"&E92 -> ENTITY_TXNMY_ELGBL_CAPEX_B | D92: ENTITY | E92: TXNMY_ELGBL_CAPEX_B | G92: =INDEX(Table1[[Especificação]:[Total Testes]],MATCH(PlanoV1.0!C92,Table1[CONCAT],0),MATCH(PlanoV1.0!B92,Table1[[#Headers],[Especificação]:[Total Testes]],0)) -> 1 | H92: =ROUNDUP(G92/8,1) -> 0.2 | I92: =SUM(J92:CQ92)-H92 -> 0 | AL92: 0.2
B93: =Table1[[#Headers],[Simulação]] -> Simulação | C93: =D93&"_"&E93 -> ENTITY_TXNMY_ELGBL_TRNVR_B | D93: ENTITY | E93: TXNMY_ELGBL_TRNVR_B | G93: =INDEX(Table1[[Especificação]:[Total Testes]],MATCH(PlanoV1.0!C93,Table1[CONCAT],0),MATCH(PlanoV1.0!B93,Table1[[#Headers],[Especificação]:[Total Testes]],0)) -> 1 | H93: =ROUNDUP(G93/8,1) -> 0.2 | I93: =SUM(J93:CQ93)-H93 -> 0 | AL93: 0.2
B94: =Table1[[#Headers],[Simulação]] -> Simulação | C94: =D94&"_"&E94 -> ENTITY_TXNMY_ELGBL_CAPEX_CE | D94: ENTITY | E94: TXNMY_ELGBL_CAPEX_CE | G94: =INDEX(Table1[[Especificação]:[Total Testes]],MATCH(PlanoV1.0!C94,Table1[CONCAT],0),MATCH(PlanoV1.0!B94,Table1[[#Headers],[Especificação]:[Total Testes]],0)) -> 1 | H94: =ROUNDUP(G94/8,1) -> 0.2 | I94: =SUM(J94:CQ94)-H94 -> 0 | AL94: 0.2
B95: =Table1[[#Headers],[Simulação]] -> Simulação | C95: =D95&"_"&E95 -> ENTITY_TXNMY_ELGBL_TRNVR_CE | D95: ENTITY | E95: TXNMY_ELGBL_TRNVR_CE | G95: =INDEX(Table1[[Especificação]:[Total Testes]],MATCH(PlanoV1.0!C95,Table1[CONCAT],0),MATCH(PlanoV1.0!B95,Table1[[#Headers],[Especificação]:[Total Testes]],0)) -> 1 | H95: =ROUNDUP(G95/8,1) -> 0.2 | I95: =SUM(J95:CQ95)-H95 -> 0 | AL95: 0.1 | AM95: 0.1
B96: =Table1[[#Headers],[Simulação]] -> Simulação | C96: =D96&"_"&E96 -> ENTITY_PURE_CAPEX_P | D96: ENTITY | E96: PURE_CAPEX_P | G96: =INDEX(Table1[[Especificação]:[Total Testes]],MATCH(PlanoV1.0!C96,Table1[CONCAT],0),MATCH(PlanoV1.0!B96,Table1[[#Headers],[Especificação]:[Total Testes]],0)) -> 1 | H96: =ROUNDUP(G96/8,1) -> 0.2 | I96: =SUM(J96:CQ96)-H96 -> 0 | AM96: 0.2
B97: =Table1[[#Headers],[Simulação]] -> Simulação | C97: =D97&"_"&E97 -> ENTITY_PURE_TRNVR_P | D97: ENTITY | E97: PURE_TRNVR_P | G97: =INDEX(Table1[[Especificação]:[Total Testes]],MATCH(PlanoV1.0!C97,Table1[CONCAT],0),MATCH(PlanoV1.0!B97,Table1[[#Headers],[Especificação]:[Total Testes]],0)) -> 1 | H97: =ROUNDUP(G97/8,1) -> 0.2 | I97: =SUM(J97:CQ97)-H97 -> 0 | AM97: 0.2
B98: =Table1[[#Headers],[Simulação]] -> Simulação | C98: =D98&"_"&E98 -> ENTITY_PURE_CAPEX_B | D98: ENTITY | E98: PURE_CAPEX_B | G98: =INDEX(Table1[[Especificação]:[Total Testes]],MATCH(PlanoV1.0!C98,Table1[CONCAT],0),MATCH(PlanoV1.0!B98,Table1[[#Headers],[Especificação]:[Total Testes]],0)) -> 1 | H98: =ROUNDUP(G98/8,1) -> 0.2 | I98: =SUM(J98:CQ98)-H98 -> 0 | AM98: 0.2
B99: =Table1[[#Headers],[Simulação]] -> Simulação | C99: =D99&"_"&E99 -> ENTITY_PURE_TRNVR_B | D99: ENTITY | E99: PURE_TRNVR_B | G99: =INDEX(Table1[[Especificação]:[Total Testes]],MATCH(PlanoV1.0!C99,Table1[CONCAT],0),MATCH(PlanoV1.0!B99,Table1[[#Headers],[Especificação]:[Total Testes]],0)) -> 1 | H99: =ROUNDUP(G99/8,1) -> 0.2 | I99: =SUM(J99:CQ99)-H99 -> 0 | AM99: 0.2
B100: =Table1[[#Headers],[Simulação]] -> Simulação | C100: =D100&"_"&E100 -> ENTITY_PURE_CAPEX_W | D100: ENTITY | E100: PURE_CAPEX_W | G100: =INDEX(Table1[[Especificação]:[Total Testes]],MATCH(PlanoV1.0!C100,Table1[CONCAT],0),MATCH(PlanoV1.0!B100,Table1[[#Headers],[Especificação]:[Total Testes]],0)) -> 1 | H100: =ROUNDUP(G100/8,1) -> 0.2 | I100: =SUM(J100:CQ100)-H100 -> 0 | AM100: 0.2
B101: =Table1[[#Headers],[Simulação]] -> Simulação | C101: =D101&"_"&E101 -> ENTITY_PURE_TRNVR_W | D101: ENTITY | E101: PURE_TRNVR_W | G101: =INDEX(Table1[[Especificação]:[Total Testes]],MATCH(PlanoV1.0!C101,Table1[CONCAT],0),MATCH(PlanoV1.0!B101,Table1[[#Headers],[Especificação]:[Total Testes]],0)) -> 1 | H101: =ROUNDUP(G101/8,1) -> 0.2 | I101: =SUM(J101:CQ101)-H101 -> 0 | AM101: 0.2
...

Sheet Sheet1
H1: =I1/8 -> 150.3 | I1: =SUM(J1:BU1) -> 1202.4 | K1: =K4*8 -> 24.8 | L1: =L4*8 -> 24.8 | M1: =M4*8 -> 24.8 | N1: =N4*8 -> 24.8 | O1: =O4*8 -> 24.8 | P1: =P4*8 -> 24.8 | Q1: =Q4*8 -> 24.8 | R1: =R4*8 -> 24.8 | ... BU1: =BU4*8 -> 1.6
I2: VAL | K2: =K3-K4 -> 0 | L2: =L3-L4 -> 0 | M2: =M3-M4 -> 0 | N2: =N3-N4 -> 0 | O2: =O3-O4 -> 0 | P2: =P3-P4 -> 0 | Q2: =Q3-Q4 -> 0 | R2: =R3-R4 -> 0 | ... BA2: =BA3-BA4 -> 0 | BC2: =BC3-BC4 -> 0 | BD2: =BD3-BD4 -> 0 | BE2: =BE3-BE4 -> 0 | BF2: =BF3-BF4 -> 0 | BG2: =BG3-BG4 -> 0 | BH2: =BH3-BH4 -> 0 | BI2: =BI3-BI4 -> 0 | BJ2: =BJ3-BJ4 -> 0 | ... BU2: =BU3-BU4 -> 0
I3: FTE REAIS | K3: =SUM(K9:K226) -> 3.1 | L3: =SUM(L9:L226) -> 3.1 | M3: =SUM(M9:M226) -> 3.1 | N3: =SUM(N9:N226) -> 3.1 | O3: =SUM(O9:O226) -> 3.1 | P3: =SUM(P9:P226) -> 3.1 | Q3: =SUM(Q9:Q226) -> 3.1 | R3: =SUM(R9:R226) -> 3.1 | ... BA3: =SUM(BA9:BA226) -> 2.1 | BC3: =SUM(BC9:BC226) -> 2.1 | BD3: =SUM(BD9:BD226) -> 2.1 | BE3: =SUM(BE9:BE226) -> 2.1 | BF3: =SUM(BF9:BF226) -> 2.1 | BG3: =SUM(BG9:BG226) -> 2.1 | BH3: =SUM(BH9:BH226) -> 2.1 | BI3: =SUM(BI9:BI226) -> 2.1 | BJ3: =SUM(BJ9:BJ226) -> 2.1 | ... BU3: =SUM(BU9:BU226) -> 0.2
I4: FTE ESP. | K4: 3.1 | L4: 3.1 | M4: 3.1 | N4: 3.1 | O4: 3.1 | P4: 3.1 | Q4: 3.1 | R4: 3.1 | S4: 3.1 | T4: 3.1 | U4: 3.1 | V4: 3.1 | W4: 3.1 | X4: 3.1 | Y4: 3.1 | Z4: 3.1 | AA4: 3.1 | AB4: 3.1 | AC4: 3.1 | AD4: 3.1 | AE4: 3.1 | AF4: 3.1 | AG4: 2.1 | AH4: 2.1 | AI4: 2.1 | AJ4: 2.1 | AK4: 2.1 | AL4: 2.1 | AM4: 2.1 | AN4: 2.1 | AO4: 2.1 | AP4: 2.1 | AQ4: 2.1 | AR4: 2.1 | AS4: 2.1 | AT4: 2.1 | AU4: 2.1 | AV4: 2.1 | AW4: 2.1 | AX4: 2.1 | AY4: 2.1 | AZ4: 2.1 | BA4: 2.1 | BC4: 2.1 | BD4: 2.1 | BE4: 2.1 | BF4: 2.1 | BG4: 2.1 | BH4: 2.1 | BI4: 2.1 | BJ4: 2.1 | BK4: 2.1 | BL4: 2.1 | BM4: 2.1 | BN4: 2.1 | BO4: 2.1 | BP4: 2.1 | BQ4: 2.1 | BR4: 2.1 | BS4: 2.1 | BT4: 2.1 | BU4: 0.2
G5: =G11+G12+G16 -> 545.1 | H5: =H11+H12+H16 -> 68.4 | J5: Janeiro | AG5: Fevereiro | BA5: Março | BV5: Abril
G6: =G5/8 -> 68.1375 | H6: =H5-G6 -> 0.2625 | J6: 45649 | K6: 45650 | L6: 45651 | M6: 45652 | N6: 45653 | O6: 45649 | P6: 45650 | Q6: 45651 | R6: 45652 | S6: 45653 | T6: 45649 | U6: 45650 | V6: 45651 | W6: 45652 | X6: 45653 | Y6: 45649 | Z6: 45650 | AA6: 45651 | AB6: 45652 | AC6: 45653 | AD6: 45649 | AE6: 45650 | AF6: 45651 | AG6: 45652 | AH6: 45653 | AI6: 45649 | AJ6: 45650 | AK6: 45651 | AL6: 45652 | AM6: 45653 | AN6: 45649 | AO6: 45650 | AP6: 45651 | AQ6: 45652 | AR6: 45653 | AS6: 45649 | AT6: 45650 | AU6: 45651 | AV6: 45652 | AW6: 45653 | AX6: 45649 | AY6: 45650 | AZ6: 45651 | BA6: 45652 | BB6: 45653 | BC6: 45649 | BD6: 45650 | BE6: 45651 | BF6: 45652 | BG6: 45653 | BH6: 45649 | BI6: 45650 | BJ6: 45651 | BK6: 45652 | BL6: 45653 | BM6: 45649 | BN6: 45650 | BO6: 45651 | BP6: 45652 | BQ6: 45653 | BR6: 45649 | BS6: 45650 | BT6: 45651 | BU6: 45652 | BV6: 45653 | BW6: 45649 | BX6: 45650 | BY6: 45651 | BZ6: 45652 | CA6: 45653 | CB6: 45649 | CC6: 45650 | CD6: 45651 | CE6: 45652 | CF6: 45653 | CG6: 45649 | CH6: 45650 | CI6: 45651 | CJ6: 45652 | CK6: 45653 | CL6: 45649 | CM6: 45650 | CN6: 45651 | CO6: 45652 | CP6: 45653 | CQ6: 45649
I7: 45657 | J7: =WORKDAY(I7,1) -> 45658 | K7: =WORKDAY(J7,1) -> 45659 | L7: =WORKDAY(K7,1) -> 45660 | M7: =WORKDAY(L7,1) -> 45663 | N7: =WORKDAY(M7,1) -> 45664 | O7: =WORKDAY(N7,1) -> 45665 | P7: =WORKDAY(O7,1) -> 45666 | Q7: =WORKDAY(P7,1) -> 45667 | ... X7: =WORKDAY(W7,1) -> 45678
F8: # Campos | G8: Duração (horas) | H8: Duração (Dias) | I8: VAL | J8: =WORKDAY(I7,1) -> 45658 | K8: =WORKDAY(J8,1) -> 45659 | L8: =WORKDAY(K8,1) -> 45660 | M8: =WORKDAY(L8,1) -> 45663 | N8: =WORKDAY(M8,1) -> 45664 | O8: =WORKDAY(N8,1) -> 45665 | P8: =WORKDAY(O8,1) -> 45666 | Q8: =WORKDAY(P8,1) -> 45667 | R8: =WORKDAY(Q8,1) -> 45670 | ... CQ8: =WORKDAY(CP8,1) -> 45777
C10: Gestão Projeto | F10: n.a. | G10: =H10*8*5 -> 0 | H10: =SUM(J10:M10) -> 0
C11: Gestão Projeto | F11: n.a. | G11: =H11*8 -> 49.6 | H11: =SUM(J11:BU11) -> 6.2 | I11: =SUM(J11:BU11)-H11 -> 0 | K11: 0.1 | L11: 0.1 | M11: 0.1 | N11: 0.1 | O11: 0.1 | P11: 0.1 | Q11: 0.1 | R11: 0.1 | S11: 0.1 | T11: 0.1 | U11: 0.1 | V11: 0.1 | W11: 0.1 | X11: 0.1 | Y11: 0.1 | Z11: 0.1 | AA11: 0.1 | AB11: 0.1 | AC11: 0.1 | AD11: 0.1 | AE11: 0.1 | AF11: 0.1 | AG11: 0.1 | AH11: 0.1 | AI11: 0.1 | AJ11: 0.1 | AK11: 0.1 | AL11: 0.1 | AM11: 0.1 | AN11: 0.1 | AO11: 0.1 | AP11: 0.1 | AQ11: 0.1 | AR11: 0.1 | AS11: 0.1 | AT11: 0.1 | AU11: 0.1 | AV11: 0.1 | AW11: 0.1 | AX11: 0.1 | AY11: 0.1 | AZ11: 0.1 | BA11: 0.1 | BC11: 0.1 | BD11: 0.1 | BE11: 0.1 | BF11: 0.1 | BG11: 0.1 | BH11: 0.1 | BI11: 0.1 | BJ11: 0.1 | BK11: 0.1 | BL11: 0.1 | BM11: 0.1 | BN11: 0.1 | BO11: 0.1 | BP11: 0.1 | BQ11: 0.1 | BR11: 0.1 | BS11: 0.1 | BT11: 0.1 | BU11: 0.1
C12: 1. Re-especificações + Simulação + Testes + Re-testes requisitos atuais) | G12: =SUM(G13:G15) -> 128 | H12: =ROUND(SUM(H13:H15),1) -> 16
C13: MunichRe | G13: 16 | H13: =ROUNDUP(G13/8,1) -> 2 | I13: 0 | K13: 3
C14: Gloval - Tabela intermédia | G14: 16 | H14: =ROUNDUP(G14/8,1) -> 2 | I14: 0 | L14: 3
C15: Re-testes | G15: =12*8 -> 96 | H15: =ROUNDUP(G15/8,1) -> 12 | I15: 0 | M15: 3 | N15: 3 | O15: 3 | P15: 3 | Q15: 3 | R15: 3 | S15: 3 | T15: 3 | U15: 3 | V15: 3 | W15: 3 | X15: 3
C16: 2. Novos Campos (Especificação + Simulação + Testes+ Re-testes) | F16: =F17+F66 -> 68 | G16: =G17+G66+G87+G156+G225 -> 367.5 | H16: =H17+H66+H87+H156+H225 -> 46.2
C17: Especificação de Requisitos - P3 | F17: =COUNTA(E18:E65) -> 48 | G17: =SUM(G18:G65) -> 112 | H17: =ROUND(SUM(H18:H65),1) -> 14.2 | I17: =SUM(J17:CQ17)-H17 -> 6.9 | Y17: 3 | Z17: 3 | AA17: 3 | AB17: 3 | AC17: 3 | AD17: 3 | AE17: 3 | AF17: 0.1
B18: =Table1[[#Headers],[Especificação]] -> Especificação | C18: =D18&"_"&E18 -> ENTITY_TXNMY_ELGBL_CAPEX_W | D18: ENTITY | E18: TXNMY_ELGBL_CAPEX_W | G18: =INDEX(Table1[[Especificação]:[Total Testes]],MATCH(Sheet1!C18,Table1[CONCAT],0),MATCH(Sheet1!B18,Table1[[#Headers],[Especificação]:[Total Testes]],0)) -> 8 | H18: =ROUND(G18/8,2) -> 1
B19: =Table1[[#Headers],[Especificação]] -> Especificação | C19: =D19&"_"&E19 -> ENTITY_TXNMY_ELGBL_TRNVR_W | D19: ENTITY | E19: TXNMY_ELGBL_TRNVR_W | G19: =INDEX(Table1[[Especificação]:[Total Testes]],MATCH(Sheet1!C19,Table1[CONCAT],0),MATCH(Sheet1!B19,Table1[[#Headers],[Especificação]:[Total Testes]],0)) -> 8 | H19: =ROUND(G19/8,2) -> 1
B20: =Table1[[#Headers],[Especificação]] -> Especificação | C20: =D20&"_"&E20 -> ENTITY_TXNMY_ELGBL_CAPEX_P | D20: ENTITY | E20: TXNMY_ELGBL_CAPEX_P | G20: =INDEX(Table1[[Especificação]:[Total Testes]],MATCH(Sheet1!C20,Table1[CONCAT],0),MATCH(Sheet1!B20,Table1[[#Headers],[Especificação]:[Total Testes]],0)) -> 1 | H20: =ROUND(G20/8,2) -> 0.13
B21: =Table1[[#Headers],[Especificação]] -> Especificação | C21: =D21&"_"&E21 -> ENTITY_TXNMY_ELGBL_TRNVR_P | D21: ENTITY | E21: TXNMY_ELGBL_TRNVR_P | G21: =INDEX(Table1[[Especificação]:[Total Testes]],MATCH(Sheet1!C21,Table1[CONCAT],0),MATCH(Sheet1!B21,Table1[[#Headers],[Especificação]:[Total Testes]],0)) -> 1 | H21: =ROUND(G21/8,2) -> 0.13
B22: =Table1[[#Headers],[Especificação]] -> Especificação | C22: =D22&"_"&E22 -> ENTITY_TXNMY_ELGBL_CAPEX_B | D22: ENTITY | E22: TXNMY_ELGBL_CAPEX_B | G22: =INDEX(Table1[[Especificação]:[Total Testes]],MATCH(Sheet1!C22,Table1[CONCAT],0),MATCH(Sheet1!B22,Table1[[#Headers],[Especificação]:[Total Testes]],0)) -> 1 | H22: =ROUND(G22/8,2) -> 0.13
B23: =Table1[[#Headers],[Especificação]] -> Especificação | C23: =D23&"_"&E23 -> ENTITY_TXNMY_ELGBL_TRNVR_B | D23: ENTITY | E23: TXNMY_ELGBL_TRNVR_B | G23: =INDEX(Table1[[Especificação]:[Total Testes]],MATCH(Sheet1!C23,Table1[CONCAT],0),MATCH(Sheet1!B23,Table1[[#Headers],[Especificação]:[Total Testes]],0)) -> 1 | H23: =ROUND(G23/8,2) -> 0.13
B24: =Table1[[#Headers],[Especificação]] -> Especificação | C24: =D24&"_"&E24 -> ENTITY_TXNMY_ELGBL_CAPEX_CE | D24: ENTITY | E24: TXNMY_ELGBL_CAPEX_CE | G24: =INDEX(Table1[[Especificação]:[Total Testes]],MATCH(Sheet1!C24,Table1[CONCAT],0),MATCH(Sheet1!B24,Table1[[#Headers],[Especificação]:[Total Testes]],0)) -> 1 | H24: =ROUND(G24/8,2) -> 0.13
B25: =Table1[[#Headers],[Especificação]] -> Especificação | C25: =D25&"_"&E25 -> ENTITY_TXNMY_ELGBL_TRNVR_CE | D25: ENTITY | E25: TXNMY_ELGBL_TRNVR_CE | G25: =INDEX(Table1[[Especificação]:[Total Testes]],MATCH(Sheet1!C25,Table1[CONCAT],0),MATCH(Sheet1!B25,Table1[[#Headers],[Especificação]:[Total Testes]],0)) -> 1 | H25: =ROUND(G25/8,2) -> 0.13
B26: =Table1[[#Headers],[Especificação]] -> Especificação | C26: =D26&"_"&E26 -> ENTITY_PURE_CAPEX_P | D26: ENTITY | E26: PURE_CAPEX_P | G26: =INDEX(Table1[[Especificação]:[Total Testes]],MATCH(Sheet1!C26,Table1[CONCAT],0),MATCH(Sheet1!B26,Table1[[#Headers],[Especificação]:[Total Testes]],0)) -> 1 | H26: =ROUND(G26/8,2) -> 0.13
B27: =Table1[[#Headers],[Especificação]] -> Especificação | C27: =D27&"_"&E27 -> ENTITY_PURE_TRNVR_P | D27: ENTITY | E27: PURE_TRNVR_P | G27: =INDEX(Table1[[Especificação]:[Total Testes]],MATCH(Sheet1!C27,Table1[CONCAT],0),MATCH(Sheet1!B27,Table1[[#Headers],[Especificação]:[Total Testes]],0)) -> 1 | H27: =ROUND(G27/8,2) -> 0.13
B28: =Table1[[#Headers],[Especificação]] -> Especificação | C28: =D28&"_"&E28 -> ENTITY_PURE_CAPEX_B | D28: ENTITY | E28: PURE_CAPEX_B | G28: =INDEX(Table1[[Especificação]:[Total Testes]],MATCH(Sheet1!C28,Table1[CONCAT],0),MATCH(Sheet1!B28,Table1[[#Headers],[Especificação]:[Total Testes]],0)) -> 1 | H28: =ROUND(G28/8,2) -> 0.13
B29: =Table1[[#Headers],[Especificação]] -> Especificação | C29: =D29&"_"&E29 -> ENTITY_PURE_TRNVR_B | D29: ENTITY | E29: PURE_TRNVR_B | G29: =INDEX(Table1[[Especificação]:[Total Testes]],MATCH(Sheet1!C29,Table1[CONCAT],0),MATCH(Sheet1!B29,Table1[[#Headers],[Especificação]:[Total Testes]],0)) -> 1 | H29: =ROUND(G29/8,2) -> 0.13
... B65: =Table1[[#Headers],[Especificação]] -> Especificação | C65: =D65&"_"&E65 -> PROTECTION_YR_CNSTRCTN | D65: PROTECTION | E65: YR_CNSTRCTN | G65: =INDEX(Table1[[Especificação]:[Total Testes]],MATCH(Sheet1!C65,Table1[CONCAT],0),MATCH(Sheet1!B65,Table1[[#Headers],[Especificação]:[Total Testes]],0)) -> 8 | H65: =ROUND(G65/8,2) -> 1
C66: Especificação de Requisitos - ESG Risks | F66: =+COUNTA(E67:E86) -> 20 | G66: =SUM(G67:G86) -> 25 | H66: =ROUND(SUM(H67:H86),1) -> 3.1 | I66: =SUM(J66:CQ66)-H66 -> 8.3 | AF66: 2.9 | AG66: 2 | AH66: 2 | AI66: 2 | AJ66: 2 | AK66: 0.5
B67: =Table1[[#Headers],[Especificação]] -> Especificação | C67: =D67&"_"&E67 -> ENTITY_GRP_ECNMC_ACTVTY | D67: ENTITY | E67: GRP_ECNMC_ACTVTY | G67: =INDEX(Table1[[Especificação]:[Total Testes]],MATCH(Sheet1!C67,Table1[CONCAT],0),MATCH(Sheet1!B67,Table1[[#Headers],[Especificação]:[Total Testes]],0)) -> 2 | H67: =ROUND(G67/8,2) -> 0.25
B68: =Table1[[#Headers],[Especificação]] -> Especificação | C68: =D68&"_"&E68 -> PROTECTION_TYP_EMSSNS_LBL | D68: PROTECTION | E68: TYP_EMSSNS_LBL | G68: =INDEX(Table1[[Especificação]:[Total Testes]],MATCH(Sheet1!C68,Table1[CONCAT],0),MATCH(Sheet1!B68,Table1[[#Headers],[Especificação]:[Total Testes]],0)) -> 0 | H68: =ROUND(G68/8,2) -> 0
B69: =Table1[[#Headers],[Especificação]] -> Especificação | C69: =D69&"_"&E69 -> PROTECTION_EPC_EMSSNS_LBL | D69: PROTECTION | E69: EPC_EMSSNS_LBL | G69: =INDEX(Table1[[Especificação]:[Total Testes]],MATCH(Sheet1!C69,Table1[CONCAT],0),MATCH(Sheet1!B69,Table1[[#Headers],[Especificação]:[Total Testes]],0)) -> 2 | H69: =ROUND(G69/8,2) -> 0.25
B70: =Table1[[#Headers],[Especificação]] -> Especificação | C70: =D70&"_"&E70 -> PROTECTION_VHCL_EMSSNS_LBL | D70: PROTECTION | E70: VHCL_EMSSNS_LBL | G70: =INDEX(Table1[[Especificação]:[Total Testes]],MATCH(Sheet1!C70,Table1[CONCAT],0),MATCH(Sheet1!B70,Table1[[#Headers],[Especificação]:[Total Testes]],0)) -> 0 | H70: =ROUND(G70/8,2) -> 0
B71: =Table1[[#Headers],[Especificação]] -> Especificação | C71: =D71&"_"&E71 -> PROTECTION_TYP_EMSSNS_SCR | D71: PROTECTION | E71: TYP_EMSSNS_SCR | G71: =INDEX(Table1[[Especificação]:[Total Testes]],MATCH(Sheet1!C71,Table1[CONCAT],0),MATCH(Sheet1!B71,Table1[[#Headers],[Especificação]:[Total Testes]],0)) -> 2 | H71: =ROUND(G71/8,2) -> 0.25
B72: =Table1[[#Headers],[Especificação]] -> Especificação | C72: =D72&"_"&E72 -> PROTECTION_EPC_EMSSNS_SCR | D72: PROTECTION | E72: EPC_EMSSNS_SCR | G72: =INDEX(Table1[[Especificação]:[Total Testes]],MATCH(Sheet1!C72,Table1[CONCAT],0),MATCH(Sheet1!B72,Table1[[#Headers],[Especificação]:[Total Testes]],0)) -> 4 | H72: =ROUND(G72/8,2) -> 0.5
B73: =Table1[[#Headers],[Especificação]] -> Especificação | C73: =D73&"_"&E73 -> PROTECTION_VHCL_EMSSNS_SCR | D73: PROTECTION | E73: VHCL_EMSSNS_SCR | G73: =INDEX(Table1[[Especificação]:[Total Testes]],MATCH(Sheet1!C73,Table1[CONCAT],0),MATCH(Sheet1!B73,Table1[[#Headers],[Especificação]:[Total Testes]],0)) -> 0 | H73: =ROUND(G73/8,2) -> 0
B74: =Table1[[#Headers],[Especificação]] -> Especificação | C74: =D74&"_"&E74 -> PROTECTION_INSRNC_ID | D74: PROTECTION | E74: INSRNC_ID | G74: =INDEX(Table1[[Especificação]:[Total Testes]],MATCH(Sheet1!C74,Table1[CONCAT],0),MATCH(Sheet1!B74,Table1[[#Headers],[Especificação]:[Total Testes]],0)) -> 0 | H74: =ROUND(G74/8,2) -> 0
B75: =Table1[[#Headers],[Especificação]] -> Especificação | C75: =D75&"_"&E75 -> PROTECTION_TYP_HZRDS_INSRD | D75: PROTECTION | E75: TYP_HZRDS_INSRD | G75: =INDEX(Table1[[Especificação]:[Total Testes]],MATCH(Sheet1!C75,Table1[CONCAT],0),MATCH(Sheet1!B75,Table1[[#Headers],[Especificação]:[Total Testes]],0)) -> 0 | H75: =ROUND(G75/8,2) -> 0
B76: =Table1[[#Headers],[Especificação]] -> Especificação | C76: =D76&"_"&E76 -> PROTECTION_AMNT_CVRD_INSRNC | D76: PROTECTION | E76: AMNT_CVRD_INSRNC | G76: =INDEX(Table1[[Especificação]:[Total Testes]],MATCH(Sheet1!C76,Table1[CONCAT],0),MATCH(Sheet1!B76,Table1[[#Headers],[Especificação]:[Total Testes]],0)) -> 0 | H76: =ROUND(G76/8,2) -> 0
B77: =Table1[[#Headers],[Especificação]] -> Especificação | C77: =D77&"_"&E77 -> PROTECTION_DT_MTRTY_INSRNC | D77: PROTECTION | E77: DT_MTRTY_INSRNC | G77: =INDEX(Table1[[Especificação]:[Total Testes]],MATCH(Sheet1!C77,Table1[CONCAT],0),MATCH(Sheet1!B77,Table1[[#Headers],[Especificação]:[Total Testes]],0)) -> 0 | H77: =ROUND(G77/8,2) -> 0
B78: =Table1[[#Headers],[Especificação]] -> Especificação | C78: =D78&"_"&E78 -> PROTECTION_FLG_FRST_HM | D78: PROTECTION | E78: FLG_FRST_HM | G78: =INDEX(Table1[[Especificação]:[Total Testes]],MATCH(Sheet1!C78,Table1[CONCAT],0),MATCH(Sheet1!B78,Table1[[#Headers],[Especificação]:[Total Testes]],0)) -> 0 | H78: =ROUND(G78/8,2) -> 0
... B86: =Table1[[#Headers],[Especificação]] -> Especificação | C86: =D86&"_"&E86 -> PROTECTION_RL_ESTT_CTY | D86: PROTECTION | E86: RL_ESTT_CTY | G86: =INDEX(Table1[[Especificação]:[Total Testes]],MATCH(Sheet1!C86,Table1[CONCAT],0),MATCH(Sheet1!B86,Table1[[#Headers],[Especificação]:[Total Testes]],0)) -> 2 | H86: =ROUND(G86/8,2) -> 0.25
C87: Simulação campos (P3 + ESG Risks) | F87: =COUNTA(E88:E155) -> 68 | G87: =SUM(G88:G155) -> 77.5 | H87: =ROUND(SUM(H88:H155),1) -> 9.8 | I87: =SUM(J87:CQ87)-H87 -> 16 | AK87: 1.5 | AL87: 2 | AM87: 2 | AN87: 2 | AO87: 2 | AP87: 2 | AQ87: 2 | AR87: 2 | AS87: 2 | AT87: 2 | AU87: 2 | AV87: 2 | AW87: 2 | AX87: 0.3
B88: =Table1[[#Headers],[Simulação]] -> Simulação | C88: =D88&"_"&E88 -> ENTITY_TXNMY_ELGBL_CAPEX_W | D88: ENTITY | E88: TXNMY_ELGBL_CAPEX_W | G88: =INDEX(Table1[[Especificação]:[Total Testes]],MATCH(Sheet1!C88,Table1[CONCAT],0),MATCH(Sheet1!B88,Table1[[#Headers],[Especificação]:[Total Testes]],0)) -> 6 | H88: =ROUND(G88/8,2) -> 0.75
B89: =Table1[[#Headers],[Simulação]] -> Simulação | C89: =D89&"_"&E89 -> ENTITY_TXNMY_ELGBL_TRNVR_W | D89: ENTITY | E89: TXNMY_ELGBL_TRNVR_W | G89: =INDEX(Table1[[Especificação]:[Total Testes]],MATCH(Sheet1!C89,Table1[CONCAT],0),MATCH(Sheet1!B89,Table1[[#Headers],[Especificação]:[Total Testes]],0)) -> 6 | H89: =ROUND(G89/8,2) -> 0.75
B90: =Table1[[#Headers],[Simulação]] -> Simulação | C90: =D90&"_"&E90 -> ENTITY_TXNMY_ELGBL_CAPEX_P | D90: ENTITY | E90: TXNMY_ELGBL_CAPEX_P | G90: =INDEX(Table1[[Especificação]:[Total Testes]],MATCH(Sheet1!C90,Table1[CONCAT],0),MATCH(Sheet1!B90,Table1[[#Headers],[Especificação]:[Total Testes]],0)) -> 1 | H90: =ROUND(G90/8,2) -> 0.13
B91: =Table1[[#Headers],[Simulação]] -> Simulação | C91: =D91&"_"&E91 -> ENTITY_TXNMY_ELGBL_TRNVR_P | D91: ENTITY | E91: TXNMY_ELGBL_TRNVR_P | G91: =INDEX(Table1[[Especificação]:[Total Testes]],MATCH(Sheet1!C91,Table1[CONCAT],0),MATCH(Sheet1!B91,Table1[[#Headers],[Especificação]:[Total Testes]],0)) -> 1 | H91: =ROUND(G91/8,2) -> 0.13
B92: =Table1[[#Headers],[Simulação]] -> Simulação | C92: =D92&"_"&E92 -> ENTITY_TXNMY_ELGBL_CAPEX_B | D92: ENTITY | E92: TXNMY_ELGBL_CAPEX_B | G92: =INDEX(Table1[[Especificação]:[Total Testes]],MATCH(Sheet1!C92,Table1[CONCAT],0),MATCH(Sheet1!B92,Table1[[#Headers],[Especificação]:[Total Testes]],0)) -> 1 | H92: =ROUND(G92/8,2) -> 0.13
B93: =Table1[[#Headers],[Simulação]] -> Simulação | C93: =D93&"_"&E93 -> ENTITY_TXNMY_ELGBL_TRNVR_B | D93: ENTITY | E93: TXNMY_ELGBL_TRNVR_B | G93: =INDEX(Table1[[Especificação]:[Total Testes]],MATCH(Sheet1!C93,Table1[CONCAT],0),MATCH(Sheet1!B93,Table1[[#Headers],[Especificação]:[Total Testes]],0)) -> 1 | H93: =ROUND(G93/8,2) -> 0.13
B94: =Table1[[#Headers],[Simulação]] -> Simulação | C94: =D94&"_"&E94 -> ENTITY_TXNMY_ELGBL_CAPEX_CE | D94: ENTITY | E94: TXNMY_ELGBL_CAPEX_CE | G94: =INDEX(Table1[[Especificação]:[Total Testes]],MATCH(Sheet1!C94,Table1[CONCAT],0),MATCH(Sheet1!B94,Table1[[#Headers],[Especificação]:[Total Testes]],0)) -> 1 | H94: =ROUND(G94/8,2) -> 0.13
B95: =Table1[[#Headers],[Simulação]] -> Simulação | C95: =D95&"_"&E95 -> ENTITY_TXNMY_ELGBL_TRNVR_CE | D95: ENTITY | E95: TXNMY_ELGBL_TRNVR_CE | G95: =INDEX(Table1[[Especificação]:[Total Testes]],MATCH(Sheet1!C95,Table1[CONCAT],0),MATCH(Sheet1!B95,Table1[[#Headers],[Especificação]:[Total Testes]],0)) -> 1 | H95: =ROUND(G95/8,2) -> 0.13
B96: =Table1[[#Headers],[Simulação]] -> Simulação | C96: =D96&"_"&E96 -> ENTITY_PURE_CAPEX_P | D96: ENTITY | E96: PURE_CAPEX_P | G96: =INDEX(Table1[[Especificação]:[Total Testes]],MATCH(Sheet1!C96,Table1[CONCAT],0),MATCH(Sheet1!B96,Table1[[#Headers],[Especificação]:[Total Testes]],0)) -> 1 | H96: =ROUND(G96/8,2) -> 0.13
B97: =Table1[[#Headers],[Simulação]] -> Simulação | C97: =D97&"_"&E97 -> ENTITY_PURE_TRNVR_P | D97: ENTITY | E97: PURE_TRNVR_P | G97: =INDEX(Table1[[Especificação]:[Total Testes]],MATCH(Sheet1!C97,Table1[CONCAT],0),MATCH(Sheet1!B97,Table1[[#Headers],[Especificação]:[Total Testes]],0)) -> 1 | H97: =ROUND(G97/8,2) -> 0.13
B98: =Table1[[#Headers],[Simulação]] -> Simulação | C98: =D98&"_"&E98 -> ENTITY_PURE_CAPEX_B | D98: ENTITY | E98: PURE_CAPEX_B | G98: =INDEX(Table1[[Especificação]:[Total Testes]],MATCH(Sheet1!C98,Table1[CONCAT],0),MATCH(Sheet1!B98,Table1[[#Headers],[Especificação]:[Total Testes]],0)) -> 1 | H98: =ROUND(G98/8,2) -> 0.13
B99: =Table1[[#Headers],[Simulação]] -> Simulação | C99: =D99&"_"&E99 -> ENTITY_PURE_TRNVR_B | D99: ENTITY | E99: PURE_TRNVR_B | G99: =INDEX(Table1[[Especificação]:[Total Testes]],MATCH(Sheet1!C99,Table1[CONCAT],0),MATCH(Sheet1!B99,Table1[[#Headers],[Especificação]:[Total Testes]],0)) -> 1 | H99: =ROUND(G99/8,2) -> 0.13
... B155: =Table1[[#Headers],[Simulação]] -> Simulação | C155: =D155&"_"&E155 -> PROTECTION_RL_ESTT_CTY | D155: PROTECTION | E155: RL_ESTT_CTY | G155: =INDEX(Table1[[Especificação]:[Total Testes]],MATCH(Sheet1!C155,Table1[CONCAT],0),MATCH(Sheet1!B155,Table1[[#Headers],[Especificação]:[Total Testes]],0)) -> 0 | H155: =ROUND(G155/8,2) -> 0
C156: Testes Campos (P3 + ESG Risks) | F156: =COUNTA(E157:E224) -> 68 | G156: =SUM(G157:G224) -> 121 | H156: =ROUND(SUM(H157:H224),1) -> 15.1 | I156: =SUM(J156:CQ156)-H156 -> 20.7 | AX156: 1.7 | AY156: 2 | AZ156: 2 | BA156: 2 | BC156: 2 | BD156: 2 | BE156: 2 | BF156: 2 | BG156: 2 | BH156: 2 | BI156: 2 | BJ156: 2 | BK156: 2 | BL156: 2 | BM156: 2 | BN156: 2 | BO156: 2 | BP156: 2 | BQ156: 0.1
B157: =Table1[[#Headers],[Total Testes]] -> Total Testes | C157: =D157&"_"&E157 -> ENTITY_TXNMY_ELGBL_CAPEX_W | D157: ENTITY | E157: TXNMY_ELGBL_CAPEX_W | G157: =INDEX(Table1[[Especificação]:[Total Testes]],MATCH(Sheet1!C157,Table1[CONCAT],0),MATCH(Sheet1!B157,Table1[[#Headers],[Especificação]:[Total Testes]],0)) -> 7.5 | H157: =ROUND(G157/8,2) -> 0.94
B158: =Table1[[#Headers],[Total Testes]] -> Total Testes | C158: =D158&"_"&E158 -> ENTITY_TXNMY_ELGBL_TRNVR_W | D158: ENTITY | E158: TXNMY_ELGBL_TRNVR_W | G158: =INDEX(Table1[[Especificação]:[Total Testes]],MATCH(Sheet1!C158,Table1[CONCAT],0),MATCH(Sheet1!B158,Table1[[#Headers],[Especificação]:[Total Testes]],0)) -> 7.5 | H158: =ROUND(G158/8,2) -> 0.94
B159: =Table1[[#Headers],[Total Testes]] -> Total Testes | C159: =D159&"_"&E159 -> ENTITY_TXNMY_ELGBL_CAPEX_P | D159: ENTITY | E159: TXNMY_ELGBL_CAPEX_P | G159: =INDEX(Table1[[Especificação]:[Total Testes]],MATCH(Sheet1!C159,Table1[CONCAT],0),MATCH(Sheet1!B159,Table1[[#Headers],[Especificação]:[Total Testes]],0)) -> 2.5 | H159: =ROUND(G159/8,2) -> 0.31
B160: =Table1[[#Headers],[Total Testes]] -> Total Testes | C160: =D160&"_"&E160 -> ENTITY_TXNMY_ELGBL_TRNVR_P | D160: ENTITY | E160: TXNMY_ELGBL_TRNVR_P | G160: =INDEX(Table1[[Especificação]:[Total Testes]],MATCH(Sheet1!C160,Table1[CONCAT],0),MATCH(Sheet1!B160,Table1[[#Headers],[Especificação]:[Total Testes]],0)) -> 2.5 | H160: =ROUND(G160/8,2) -> 0.31
B161: =Table1[[#Headers],[Total Testes]] -> Total Testes | C161: =D161&"_"&E161 -> ENTITY_TXNMY_ELGBL_CAPEX_B | D161: ENTITY | E161: TXNMY_ELGBL_CAPEX_B | G161: =INDEX(Table1[[Especificação]:[Total Testes]],MATCH(Sheet1!C161,Table1[CONCAT],0),MATCH(Sheet1!B161,Table1[[#Headers],[Especificação]:[Total Testes]],0)) -> 2.5 | H161: =ROUND(G161/8,2) -> 0.31
B162: =Table1[[#Headers],[Total Testes]] -> Total Testes | C162: =D162&"_"&E162 -> ENTITY_TXNMY_ELGBL_TRNVR_B | D162: ENTITY | E162: TXNMY_ELGBL_TRNVR_B | G162: =INDEX(Table1[[Especificação]:[Total Testes]],MATCH(Sheet1!C162,Table1[CONCAT],0),MATCH(Sheet1!B162,Table1[[#Headers],[Especificação]:[Total Testes]],0)) -> 2.5 | H162: =ROUND(G162/8,2) -> 0.31
B163: =Table1[[#Headers],[Total Testes]] -> Total Testes | C163: =D163&"_"&E163 -> ENTITY_TXNMY_ELGBL_CAPEX_CE | D163: ENTITY | E163: TXNMY_ELGBL_CAPEX_CE | G163: =INDEX(Table1[[Especificação]:[Total Testes]],MATCH(Sheet1!C163,Table1[CONCAT],0),MATCH(Sheet1!B163,Table1[[#Headers],[Especificação]:[Total Testes]],0)) -> 2.5 | H163: =ROUND(G163/8,2) -> 0.31
B164: =Table1[[#Headers],[Total Testes]] -> Total Testes | C164: =D164&"_"&E164 -> ENTITY_TXNMY_ELGBL_TRNVR_CE | D164: ENTITY | E164: TXNMY_ELGBL_TRNVR_CE | G164: =INDEX(Table1[[Especificação]:[Total Testes]],MATCH(Sheet1!C164,Table1[CONCAT],0),MATCH(Sheet1!B164,Table1[[#Headers],[Especificação]:[Total Testes]],0)) -> 2.5 | H164: =ROUND(G164/8,2) -> 0.31
B165: =Table1[[#Headers],[Total Testes]] -> Total Testes | C165: =D165&"_"&E165 -> ENTITY_PURE_CAPEX_P | D165: ENTITY | E165: PURE_CAPEX_P | G165: =INDEX(Table1[[Especificação]:[Total Testes]],MATCH(Sheet1!C165,Table1[CONCAT],0),MATCH(Sheet1!B165,Table1[[#Headers],[Especificação]:[Total Testes]],0)) -> 2.5 | H165: =ROUND(G165/8,2) -> 0.31
B166: =Table1[[#Headers],[Total Testes]] -> Total Testes | C166: =D166&"_"&E166 -> ENTITY_PURE_TRNVR_P | D166: ENTITY | E166: PURE_TRNVR_P | G166: =INDEX(Table1[[Especificação]:[Total Testes]],MATCH(Sheet1!C166,Table1[CONCAT],0),MATCH(Sheet1!B166,Table1[[#Headers],[Especificação]:[Total Testes]],0)) -> 2.5 | H166: =ROUND(G166/8,2) -> 0.31
B167: =Table1[[#Headers],[Total Testes]] -> Total Testes | C167: =D167&"_"&E167 -> ENTITY_PURE_CAPEX_B | D167: ENTITY | E167: PURE_CAPEX_B | G167: =INDEX(Table1[[Especificação]:[Total Testes]],MATCH(Sheet1!C167,Table1[CONCAT],0),MATCH(Sheet1!B167,Table1[[#Headers],[Especificação]:[Total Testes]],0)) -> 2.5 | H167: =ROUND(G167/8,2) -> 0.31
B168: =Table1[[#Headers],[Total Testes]] -> Total Testes | C168: =D168&"_"&E168 -> ENTITY_PURE_TRNVR_B | D168: ENTITY | E168: PURE_TRNVR_B | G168: =INDEX(Table1[[Especificação]:[Total Testes]],MATCH(Sheet1!C168,Table1[CONCAT],0),MATCH(Sheet1!B168,Table1[[#Headers],[Especificação]:[Total Testes]],0)) -> 2.5 | H168: =ROUND(G168/8,2) -> 0.31
... B224: =Table1[[#Headers],[Total Testes]] -> Total Testes | C224: =D224&"_"&E224 -> PROTECTION_RL_ESTT_CTY | D224: PROTECTION | E224: RL_ESTT_CTY | G224: =INDEX(Table1[[Especificação]:[Total Testes]],MATCH(Sheet1!C224,Table1[CONCAT],0),MATCH(Sheet1!B224,Table1[[#Headers],[Especificação]:[Total Testes]],0)) -> 0 | H224: =ROUND(G224/8,2) -> 0
C225: Re-testes | G225: =H225*8 -> 32 | H225: =ROUNDUP(Auxiliar!$E$12*H156,0) -> 4 | I225: =SUM(J225:CQ225)-H225 -> 4 | BQ225: 1.9 | BR225: 2 | BS225: 2 | BT225: 2 | BU225: 0.1
C231: Horas Total
C232: Horas Novos Requisitos

Sheet RESUMO
B2: Leverage Finance = "Y" | C2: =COUNTIFS('LISTA - Setembro2024'!$K$3:$K$539,"Y") -> 174
B4: Alteração | C4: Âmbito | D4: # Campos | E4: Observações | H4: Leveraged Finance | I4: STATUS | J4: AMBITO | K4: Status Data Lake | L4: # Campos
B5: Novo Campo | C5: ESTR (& outros) | D5: =GETPIVOTDATA("[Measures].[Count of ID Data field / Field order]",$H$4,"[Range].[STATUS]","[Range].[STATUS].&[Novo Campo]","[Range].[AMBITO]","[Range].[AMBITO].&[ESTR & GD & PILAR3]","[Range].[Status Data Lake]","[Range].[Status Data Lake].&[n/a]","[Range].[Leveraged Finance]","[Range].[Leveraged Finance].&[Y]") -> 1 | E5: n.a. | H5: N | I5: Campo eliminado | J5: PILAR3 | K5: n/a | L5: 1
C6: LF | D6: =GETPIVOTDATA("[Measures].[Count of ID Data field / Field order]",$H$4,"[Range].[STATUS]","[Range].[STATUS].&[Novo Campo]","[Range].[AMBITO]","[Range].[AMBITO].&[LF]","[Range].[Status Data Lake]","[Range].[Status Data Lake].&[n/a]","[Range].[Leveraged Finance]","[Range].[Leveraged Finance].&[Y]") -> 19 | E6: n.a. | I6: Campo eliminado - troca tabela | J6: GD & PILAR3 | K6: n/a | L6: 2
B7: Sem alterações | C7: ESTR (& outros) | D7: =SUM(L50:L72) -> 154 | E7: De notar que destes campos: - 9 provém da fonte manual de LF (lt601_lev_fin) - 39 estão sem dados/pouca qualidade com necessidades de (re)-especificações (Sindicados, Demonstrações Financeiras CIB, Re-estruturados) - 24 em testes/implementação - 15 com incidências nos controlos corporativos | J7: PILAR3 | K7: n/a | L7: 2
C8: Total | D8: =SUM(D5:D7) -> 174 | I8: Nome campo alterado | J8: PILAR3 | K8: n/a | L8: 2
I9: Nova Tabela | J9: ESTR & GD & PILAR3 | K9: n/a | L9: 1
J10: GD & PILAR3 | K10: n/a | L10: 3
B11: Leverage Finance = "N" | C11: =COUNTIFS('LISTA - Setembro2024'!$K$3:$K$539,"N") -> 362 | J11: PILAR3 | K11: n/a | L11: 3
I12: Nova Tabela - Campo existente | J12: GD & PILAR3 | K12: n/a | L12: 2
J13: PILAR3 | K13: n/a | L13: 2
B14: Alteração | C14: Âmbito | D14: # Campos | E14: Observações | I14: Novo Campo | J14: ESG_RISKS | K14: n/a | L14: 12
B15: Nova tabela | C15: ESTR (& outros) | D15: =GETPIVOTDATA("[Measures].[Count of ID Data field / Field order]",$H$4,"[Range].[STATUS]","[Range].[STATUS].&[Nova Tabela]","[Range].[AMBITO]","[Range].[AMBITO].&[ESTR & GD & PILAR3]","[Range].[Status Data Lake]","[Range].[Status Data Lake].&[n/a]","[Range].[Leveraged Finance]","[Range].[Leveraged Finance].&[N]") -> 1 | E15: Apenas 1 campo reportado na LT estrutural (questionar corporação) >>> é para ESG | J15: ESTR | K15: n/a | L15: 25
C16: GD & PILAR3 | D16: =GETPIVOTDATA("[Measures].[Count of ID Data field / Field order]",$H$4,"[Range].[STATUS]","[Range].[STATUS].&[Nova Tabela]","[Range].[AMBITO]","[Range].[AMBITO].&[GD & PILAR3]","[Range].[Status Data Lake]","[Range].[Status Data Lake].&[n/a]","[Range].[Leveraged Finance]","[Range].[Leveraged Finance].&[N]")+GETPIVOTDATA("[Measures].[Count of ID Data field / Field order]",$H$4,"[Range].[STATUS]","[Range].[STATUS].&[Nova Tabela - Campo existente]","[Range].[AMBITO]","[Range].[AMBITO].&[GD & PILAR3]","[Range].[Status Data Lake]","[Range].[Status Data Lake].&[n/a]","[Range].[Leveraged Finance]","[Range].[Leveraged Finance].&[N]") -> 5 | E16: De notar que 2 campos trocaram de tabela | J16: ESTR & GFINANCE | K16: n/a | L16: 7
C17: PILAR3 | D17: =GETPIVOTDATA("[Measures].[Count of ID Data field / Field order]",$H$4,"[Range].[STATUS]","[Range].[STATUS].&[Nova Tabela]","[Range].[AMBITO]","[Range].[AMBITO].&[PILAR3]","[Range].[Status Data Lake]","[Range].[Status Data Lake].&[n/a]","[Range].[Leveraged Finance]","[Range].[Leveraged Finance].&[N]")+GETPIVOTDATA("[Measures].[Count of ID Data field / Field order]",$H$4,"[Range].[STATUS]","[Range].[STATUS].&[Nova Tabela - Campo existente]","[Range].[AMBITO]","[Range].[AMBITO].&[PILAR3]","[Range].[Status Data Lake]","[Range].[Status Data Lake].&[n/a]","[Range].[Leveraged Finance]","[Range].[Leveraged Finance].&[N]") -> 5 | E17: De notar que 2 campos trocaram de tabela | J17: GD | K17: n/a | L17: 1
B18: Novo Campo | C18: ESTR | D18: =GETPIVOTDATA("[Measures].[Count of ID Data field / Field order]",$H$4,"[Range].[STATUS]","[Range].[STATUS].&[Novo Campo]","[Range].[AMBITO]","[Range].[AMBITO].&[ESTR]","[Range].[Status Data Lake]","[Range].[Status Data Lake].&[n/a]","[Range].[Leveraged Finance]","[Range].[Leveraged Finance].&[N]") -> 25 | E18: n.a. | J18: GD & PILAR3 | K18: n/a | L18: 1
C19: ESTR (& Green Finance) | D19: =GETPIVOTDATA("[Measures].[Count of ID Data field / Field order]",$H$4,"[Range].[STATUS]","[Range].[STATUS].&[Novo Campo]","[Range].[AMBITO]","[Range].[AMBITO].&[ESTR & GFINANCE]","[Range].[Status Data Lake]","[Range].[Status Data Lake].&[n/a]","[Range].[Leveraged Finance]","[Range].[Leveraged Finance].&[N]") -> 7 | E19: n.a. | J19: PILAR3 | K19: n/a | L19: 29
C20: GD & PILAR3 | D20: =GETPIVOTDATA("[Measures].[Count of ID Data field / Field order]",$H$4,"[Range].[STATUS]","[Range].[STATUS].&[Novo Campo]","[Range].[AMBITO]","[Range].[AMBITO].&[GD & PILAR3]","[Range].[Status Data Lake]","[Range].[Status Data Lake].&[n/a]","[Range].[Leveraged Finance]","[Range].[Leveraged Finance].&[N]") -> 1 | E20: n.a. | I20: Sem alteração | J20: ESTR | K20: 1. Especificar | L20: 9
C21: PILAR3 | D21: =GETPIVOTDATA("[Measures].[Count of ID Data field / Field order]",$H$4,"[Range].[STATUS]","[Range].[STATUS].&[Novo Campo]","[Range].[AMBITO]","[Range].[AMBITO].&[PILAR3]","[Range].[Status Data Lake]","[Range].[Status Data Lake].&[n/a]","[Range].[Leveraged Finance]","[Range].[Leveraged Finance].&[N]") -> 29 | E21: n.a. | K21: 2. Alterar especificação | L21: 15
C22: GD | D22: =GETPIVOTDATA("[Measures].[Count of ID Data field / Field order]",$H$4,"[Range].[STATUS]","[Range].[STATUS].&[Novo Campo]","[Range].[AMBITO]","[Range].[AMBITO].&[GD]","[Range].[Status Data Lake]","[Range].[Status Data Lake].&[n/a]","[Range].[Leveraged Finance]","[Range].[Leveraged Finance].&[N]") -> 1 | E22: n.a. | K22: 3. Pendente de decisão | L22: 1
C23: ESG Risks | D23: =GETPIVOTDATA("[Measures].[Count of ID Data field / Field order]",$H$4,"[Range].[STATUS]","[Range].[STATUS].&[Novo Campo]","[Range].[AMBITO]","[Range].[AMBITO].&[ESG_RISKS]","[Range].[Status Data Lake]","[Range].[Status Data Lake].&[n/a]","[Range].[Leveraged Finance]","[Range].[Leveraged Finance].&[N]") -> 12 | E23: Campos adicionados pela Corporação antes de abril e não contemplados no Data Lake. | K23: 4.1 Em implementação - Re-especificação | L23: 13
B24: Nome de campo alterado | C24: PILAR3 | D24: =GETPIVOTDATA("[Measures].[Count of ID Data field / Field order]",$H$4,"[Range].[STATUS]","[Range].[STATUS].&[Nome campo alterado]","[Range].[AMBITO]","[Range].[AMBITO].&[PILAR3]","[Range].[Status Data Lake]","[Range].[Status Data Lake].&[n/a]","[Range].[Leveraged Finance]","[Range].[Leveraged Finance].&[N]") -> 2 | E24: Sem impacto previsto a nível de re-especificação. | K24: 4.2 Em implementação - Incidência | L24: 1
B25: Sem alterações | C25: - | D25: =SUM(L20:L47) -> 269 | E25: De notar que destes campos (âmbito ESTR): - 29 estão sem dados/pouca qualidade com necessidades de (re)-especificações (Salários, Demonstrações Financeiras CIB) - 27 em testes/implementação - 42 com incidências nos controlos corporativos | K25: 5.1 Em testes - Re-especificação | L25: 7
C26: Total (excl. campos elim.) | D26: =SUM(D15:D25) -> 357 | K26: 5.2 Em testes - Incidência | L26: 2
B27: Campo eliminado | C27: GD & PILAR3 | D27: =GETPIVOTDATA("[Measures].[Count of ID Data field / Field order]",$H$4,"[Range].[STATUS]","[Range].[STATUS].&[Campo eliminado - troca tabela]","[Range].[AMBITO]","[Range].[AMBITO].&[GD & PILAR3]","[Range].[Status Data Lake]","[Range].[Status Data Lake].&[n/a]","[Range].[Leveraged Finance]","[Range].[Leveraged Finance].&[N]") -> 2 | E27: De notar que 2 campos trocaram de tabela | K27: 7. Analisar controlos e completude | L27: 36
C28: PILAR3 | D28: =GETPIVOTDATA("[Measures].[Count of ID Data field / Field order]",$H$4,"[Range].[STATUS]","[Range].[STATUS].&[Campo eliminado]","[Range].[AMBITO]","[Range].[AMBITO].&[PILAR3]","[Range].[Status Data Lake]","[Range].[Status Data Lake].&[n/a]","[Range].[Leveraged Finance]","[Range].[Leveraged Finance].&[N]")+GETPIVOTDATA("[Measures].[Count of ID Data field / Field order]",$H$4,"[Range].[STATUS]","[Range].[STATUS].&[Campo eliminado - troca tabela]","[Range].[AMBITO]","[Range].[AMBITO].&[PILAR3]","[Range].[Status Data Lake]","[Range].[Status Data Lake].&[n/a]","[Range].[Leveraged Finance]","[Range].[Leveraged Finance].&[N]") -> 3 | E28: De notar que 2 campos trocaram de tabela | K28: 8. Concluído - sem dados | L28: 6
D29: =D26+SUM(D27:D28) -> 362 | K29: 9. Concluído | L29: 73
J30: ESTR & GD | K30: 5.1 Em testes - Re-especificação | L30: 1
K31: 9. Concluído | L31: 1
J32: ESTR & GD & PILAR3 | K32: 4.1 Em implementação - Re-especificação | L32: 1
K33: 5.2 Em testes - Incidência | L33: 1
K34: 7. Analisar controlos e completude | L34: 3
K35: 9. Concluído | L35: 6
J36: ESTR & GFINANCE | K36: 9. Concluído | L36: 1
J37: ESTR & PILAR3 | K37: 1. Especificar | L37: 1
K38: 2. Alterar especificação | L38: 2
C39: Green finance + ESG Risks o que são e para que são utilizados >> 7+12 | K39: 3. Pendente de decisão | L39: 1
C40: Quem está a solicitar esta informação? >> 25 campos ESTR >> custo à unidade | K40: 4.1 Em implementação - Re-especificação | L40: 1
K41: 7. Analisar controlos e completude | L41: 3
B42: Confirmar com ficheiro enviado pela Raquel > LF | K42: 9. Concluído | L42: 6
B43: Adicionar flag de marcação | J43: GD | K43: 1. Especificar | L43: 1
B44: Ver com a Zeneida se os de CIB podem não ser preenchidos pq vêm do AQUA > corporativo | K44: n/a | L44: 25
J45: GD & PILAR3 | K45: n/a | L45: 4
J46: PILAR3 | K46: 1. Especificar | L46: 1
K47: n/a | L47: 47
H48: Y | I48: Novo Campo | J48: ESTR & GD & PILAR3 | K48: n/a | L48: 1
J49: LF | K49: n/a | L49: 19
I50: Sem alteração | J50: ESTR | K50: 1. Especificar | L50: 6
K51: 2. Alterar especificação | L51: 19
K52: 3. Pendente de decisão | L52: 6
K53: 4.1 Em implementação - Re-especificação | L53: 5
K54: 5.1 Em testes - Re-especificação | L54: 7
K55: 5.2 Em testes - Incidência | L55: 4
K56: 6. Outros Desenvolvimentos | L56: 10
K57: 7. Analisar controlos e completude | L57: 11
K58: 8. Concluído - sem dados | L58: 4
K59: 9. Concluído | L59: 45
J60: ESTR & GD | K60: 5.1 Em testes - Re-especificação | L60: 2
K61: 7. Analisar controlos e completude | L61: 1
K62: 9. Concluído | L62: 1
J63: ESTR & GD & PILAR3 | K63: 2. Alterar especificação | L63: 1
K64: 4.1 Em implementação - Re-especificação | L64: 2
K65: 5.1 Em testes - Re-especificação | L65: 1
K66: 9. Concluído | L66: 8
J67: ESTR & PILAR3 | K67: 1. Especificar | L67: 1
K68: 2. Alterar especificação | L68: 4
K69: 4.1 Em implementação - Re-especificação | L69: 1
K70: 5.2 Em testes - Incidência | L70: 2
K71: 7. Analisar controlos e completude | L71: 3
K72: 9. Concluído | L72: 10

Sheet Sheet1 (2)
H1: =I1/8 -> 81.4 | I1: =SUM(J1:CA1) -> 651.2 | K1: =K4*8 -> 0 | L1: =L4*8 -> 0 | M1: =M4*8 -> 0 | N1: =N4*8 -> 0 | O1: =O4*8 -> 0 | P1: =P4*8 -> 0 | Q1: =Q4*8 -> 0 | R1: =R4*8 -> 0 | ... CA1: =CA4*8 -> 0
I2: VAL | K2: =K3-K4 -> 3.2 | L2: =L3-L4 -> 3.2 | M2: =M3-M4 -> 3.2 | N2: =N3-N4 -> 3.2 | O2: =O3-O4 -> 3.2 | P2: =P3-P4 -> 3.2 | Q2: =Q3-Q4 -> 3.2 | R2: =R3-R4 -> 3.2 | ... BA2: =BA3-BA4 -> 0 | BC2: =BC3-BC4 -> 0 | BD2: =BD3-BD4 -> 0 | BE2: =BE3-BE4 -> 0 | BF2: =BF3-BF4 -> 0 | BG2: =BG3-BG4 -> 0 | BH2: =BH3-BH4 -> -0.9 | BI2: =BI3-BI4 -> -0.9 | BJ2: =BJ3-BJ4 -> -0.9 | ... CA2: =CA3-CA4 -> 0
I3: FTE REAIS | K3: =SUM(K9:K231) -> 3.2 | L3: =SUM(L9:L231) -> 3.2 | M3: =SUM(M9:M231) -> 3.2 | N3: =SUM(N9:N231) -> 3.2 | O3: =SUM(O9:O231) -> 3.2 | P3: =SUM(P9:P231) -> 3.2 | Q3: =SUM(Q9:Q231) -> 3.2 | R3: =SUM(R9:R231) -> 3.2 | ... BA3: =SUM(BA9:BA231) -> 2.2 | BC3: =SUM(BC9:BC231) -> 2.2 | BD3: =SUM(BD9:BD231) -> 2.2 | BE3: =SUM(BE9:BE231) -> 2.2 | BF3: =SUM(BF9:BF231) -> 2.2 | BG3: =SUM(BG9:BG231) -> 2.2 | BH3: =SUM(BH9:BH231) -> 1.3 | BI3: =SUM(BI9:BI231) -> 1.3 | BJ3: =SUM(BJ9:BJ231) -> 1.3 | ... CA3: =SUM(CA9:CA231) -> 0
I4: FTE ESP. | Y4: 2.2 | Z4: 2.2 | AA4: 2.2 | AB4: 2.2 | AC4: 2.2 | AD4: 2.2 | AE4: 2.2 | AF4: 2.2 | AG4: 2.2 | AH4: 2.2 | AI4: 2.2 | AJ4: 2.2 | AK4: 2.2 | AL4: 2.2 | AM4: 2.2 | AN4: 2.2 | AO4: 2.2 | AP4: 2.2 | AQ4: 2.2 | AR4: 2.2 | AS4: 2.2 | AT4: 2.2 | AU4: 2.2 | AV4: 2.2 | AW4: 2.2 | AX4: 2.2 | AY4: 2.2 | AZ4: 2.2 | BA4: 2.2 | BC4: 2.2 | BD4: 2.2 | BE4: 2.2 | BF4: 2.2 | BG4: 2.2 | BH4: 2.2 | BI4: 2.2 | BJ4: 2.2 | BK4: 0 | BL4: 0 | BM4: 0 | BN4: 0 | BO4: 0 | BP4: 0 | BQ4: 0 | BR4: 0 | BS4: 0 | BT4: 0 | BU4: 0 | BV4: 0 | BW4: 0 | BX4: 0 | BY4: 0 | BZ4: 0 | CA4: 0
J5: Janeiro | AG5: Fevereiro | BA5: Março | BV5: Abril
J6: =J8 -> 45658 | K6: =K8 -> 45659 | L6: =L8 -> 45660 | M6: =M8 -> 45663 | N6: =N8 -> 45664 | O6: =O8 -> 45665 | P6: =P8 -> 45666 | Q6: =Q8 -> 45667 | ... CQ6: =CQ8 -> 45777
I7: 45657 | J7: =WORKDAY(I7,1) -> 45658 | K7: =WORKDAY(J7,1) -> 45659 | L7: =WORKDAY(K7,1) -> 45660 | M7: 4 | N7: =WORKDAY(M7,1) -> 5 | O7: =WORKDAY(N7,1) -> 6 | P7: =WORKDAY(O7,1) -> 9 | Q7: =WORKDAY(P7,1) -> 10 | R7: =WORKDAY(Q7,1) -> 11 | S7: =WORKDAY(R7,1) -> 12 | T7: =WORKDAY(S7,1) -> 13 | U7: =WORKDAY(T7,1) -> 16 | ... X7: =WORKDAY(W7,1) -> 19
F8: # Campos | G8: Duração (horas) | H8: Duração (Dias) | I8: VAL | J8: =WORKDAY(I7,1) -> 45658 | K8: =WORKDAY(J8,1) -> 45659 | L8: =WORKDAY(K8,1) -> 45660 | M8: =WORKDAY(L8,1) -> 45663 | N8: =WORKDAY(M8,1) -> 45664 | O8: =WORKDAY(N8,1) -> 45665 | P8: =WORKDAY(O8,1) -> 45666 | Q8: =WORKDAY(P8,1) -> 45667 | R8: =WORKDAY(Q8,1) -> 45670 | ... CQ8: =WORKDAY(CP8,1) -> 45777
C10: Gestão Projeto | F10: n.a. | G10: =H10*8*5 -> 0 | H10: =SUM(J10:M10) -> 0
C11: Gestão Projeto | F11: n.a. | G11: =H11*8 -> 70.4 | H11: =SUM(J11:BU11) -> 8.8 | I11: =SUM(J11:BU11)-H11 -> 0 | K11: 0.2 | L11: 0.2 | M11: 0.2 | N11: 0.2 | O11: 0.2 | P11: 0.2 | Q11: 0.2 | R11: 0.2 | S11: 0.2 | T11: 0.2 | U11: 0.2 | V11: 0.2 | W11: 0.2 | X11: 0.2 | Y11: 0.2 | Z11: 0.2 | AA11: 0.2 | AB11: 0.2 | AC11: 0.2 | AD11: 0.2 | AE11: 0.2 | AF11: 0.2 | AG11: 0.2 | AH11: 0.2 | AI11: 0.2 | AJ11: 0.2 | AK11: 0.2 | AL11: 0.2 | AM11: 0.2 | AU11: 0.2 | AV11: 0.2 | AW11: 0.2 | AX11: 0.2 | AY11: 0.2 | AZ11: 0.2 | BA11: 0.2 | BC11: 0.2 | BD11: 0.2 | BE11: 0.2 | BF11: 0.2 | BG11: 0.2 | BH11: 0.2 | BI11: 0.2 | BJ11: 0.2
C12: 0. Re-especificações + Simulação + Testes + Re-testes requisitos atuais) | G12: =SUM(G13:G14) -> 336 | H12: =ROUND(SUM(H13:H14),1) -> 42 | I12: =SUM(J12:CQ12)-H12 -> 0 | K12: 3 | L12: 3 | M12: 3 | N12: 3 | O12: 3 | P12: 3 | Q12: 3 | R12: 3 | S12: 3 | T12: 3 | U12: 3 | V12: 3 | W12: 3 | X12: 3
C13: Gloval - Tabela intermédia | G13: 16 | H13: =ROUNDUP(G13/8,1) -> 2
C14: Re-testes | G14: =(13*8*3)+8 -> 320 | H14: =ROUNDUP(G14/8,1) -> 40
C15: 1. Re-especificação de MunichRe | G15: =SUM(G16:G20) -> 60 | H15: =ROUND(SUM(H16:H20),1) -> 7.5 | I15: =SUM(I16:I20) -> 0
C16: Especificação novo input | G16: 4 | H16: =ROUND(G16/8,2) -> 0.5 | I16: =SUM(J16:CQ16)-H16 -> 0 | Y16: 0.5
C17: Re-especificação de campos riscos fisicos - Modelo Verde (4) | G17: 8 | H17: =ROUND(G17/8,2) -> 1 | I17: =SUM(J17:CQ17)-H17 -> 0 | Y17: 1
A18: esperar IT | C18: Testar input | G18: 8 | H18: =ROUND(G18/8,2) -> 1 | I18: =SUM(J18:CQ18)-H18 -> 0 | AU18: 1
A19: esperar IT | C19: Testar campos risco MV (4) | G19: =5*8 -> 40 | H19: =ROUND(G19/8,2) -> 5 | I19: =SUM(J19:CQ19)-H19 -> 0 | AU19: 1 | AV19: 1 | AW19: 1 | AX19: 1 | AY19: 1
A20: esperar IT | C20: Testar 4 campos de LT P3 | G20: 0 | H20: =ROUND(G20/8,2) -> 0 | I20: =SUM(J20:CQ20)-H20 -> 0
C21: 2. Novos Campos (Especificação + Simulação + Testes+ Re-testes) | F21: =F22+F71 -> 54 | G21: =G22+G71+G92+G161+G230 -> 367.5 | H21: =H22+H71+H92+H161+H230 -> 46.2
C22: Especificação de Requisitos - P3 | F22: =COUNTA(E23:E64) -> 42 | G22: =SUM(G23:G64) -> 112 | H22: =ROUND(SUM(H23:H64),1) -> 14.2 | I22: =SUM(J22:CQ22)-H22 -> 0 | Y22: 0.5 | Z22: 0.5 | AA22: 0.5 | AB22: 0.5 | AC22: 0.5 | AD22: 0.5 | AE22: 0.5 | AF22: 0.9 | AG22: 1.5 | AH22: 1.5 | AI22: 1.5 | AJ22: 1.5 | AK22: 1.5 | AL22: 1.7 | AM22: 0.6
B23: =Table1[[#Headers],[Especificação]] -> Especificação | C23: =D23&"_"&E23 -> ENTITY_TXNMY_ELGBL_CAPEX_W | D23: ENTITY | E23: TXNMY_ELGBL_CAPEX_W | G23: =INDEX(Table1[[Especificação]:[Total Testes]],MATCH('Sheet1 (2)'!C23,Table1[CONCAT],0),MATCH('Sheet1 (2)'!B23,Table1[[#Headers],[Especificação]:[Total Testes]],0)) -> 8 | H23: =ROUND(G23/8,2) -> 1
B24: =Table1[[#Headers],[Especificação]] -> Especificação | C24: =D24&"_"&E24 -> ENTITY_TXNMY_ELGBL_TRNVR_W | D24: ENTITY | E24: TXNMY_ELGBL_TRNVR_W | G24: =INDEX(Table1[[Especificação]:[Total Testes]],MATCH('Sheet1 (2)'!C24,Table1[CONCAT],0),MATCH('Sheet1 (2)'!B24,Table1[[#Headers],[Especificação]:[Total Testes]],0)) -> 8 | H24: =ROUND(G24/8,2) -> 1
B25: =Table1[[#Headers],[Especificação]] -> Especificação | C25: =D25&"_"&E25 -> ENTITY_TXNMY_ELGBL_CAPEX_P | D25: ENTITY | E25: TXNMY_ELGBL_CAPEX_P | G25: =INDEX(Table1[[Especificação]:[Total Testes]],MATCH('Sheet1 (2)'!C25,Table1[CONCAT],0),MATCH('Sheet1 (2)'!B25,Table1[[#Headers],[Especificação]:[Total Testes]],0)) -> 1 | H25: =ROUND(G25/8,2) -> 0.13
B26: =Table1[[#Headers],[Especificação]] -> Especificação | C26: =D26&"_"&E26 -> ENTITY_TXNMY_ELGBL_TRNVR_P | D26: ENTITY | E26: TXNMY_ELGBL_TRNVR_P | G26: =INDEX(Table1[[Especificação]:[Total Testes]],MATCH('Sheet1 (2)'!C26,Table1[CONCAT],0),MATCH('Sheet1 (2)'!B26,Table1[[#Headers],[Especificação]:[Total Testes]],0)) -> 1 | H26: =ROUND(G26/8,2) -> 0.13
B27: =Table1[[#Headers],[Especificação]] -> Especificação | C27: =D27&"_"&E27 -> ENTITY_TXNMY_ELGBL_CAPEX_B | D27: ENTITY | E27: TXNMY_ELGBL_CAPEX_B | G27: =INDEX(Table1[[Especificação]:[Total Testes]],MATCH('Sheet1 (2)'!C27,Table1[CONCAT],0),MATCH('Sheet1 (2)'!B27,Table1[[#Headers],[Especificação]:[Total Testes]],0)) -> 1 | H27: =ROUND(G27/8,2) -> 0.13
B28: =Table1[[#Headers],[Especificação]] -> Especificação | C28: =D28&"_"&E28 -> ENTITY_TXNMY_ELGBL_TRNVR_B | D28: ENTITY | E28: TXNMY_ELGBL_TRNVR_B | G28: =INDEX(Table1[[Especificação]:[Total Testes]],MATCH('Sheet1 (2)'!C28,Table1[CONCAT],0),MATCH('Sheet1 (2)'!B28,Table1[[#Headers],[Especificação]:[Total Testes]],0)) -> 1 | H28: =ROUND(G28/8,2) -> 0.13
B29: =Table1[[#Headers],[Especificação]] -> Especificação | C29: =D29&"_"&E29 -> ENTITY_TXNMY_ELGBL_CAPEX_CE | D29: ENTITY | E29: TXNMY_ELGBL_CAPEX_CE | G29: =INDEX(Table1[[Especificação]:[Total Testes]],MATCH('Sheet1 (2)'!C29,Table1[CONCAT],0),MATCH('Sheet1 (2)'!B29,Table1[[#Headers],[Especificação]:[Total Testes]],0)) -> 1 | H29: =ROUND(G29/8,2) -> 0.13
B30: =Table1[[#Headers],[Especificação]] -> Especificação | C30: =D30&"_"&E30 -> ENTITY_TXNMY_ELGBL_TRNVR_CE | D30: ENTITY | E30: TXNMY_ELGBL_TRNVR_CE | G30: =INDEX(Table1[[Especificação]:[Total Testes]],MATCH('Sheet1 (2)'!C30,Table1[CONCAT],0),MATCH('Sheet1 (2)'!B30,Table1[[#Headers],[Especificação]:[Total Testes]],0)) -> 1 | H30: =ROUND(G30/8,2) -> 0.13
B31: =Table1[[#Headers],[Especificação]] -> Especificação | C31: =D31&"_"&E31 -> ENTITY_PURE_CAPEX_P | D31: ENTITY | E31: PURE_CAPEX_P | G31: =INDEX(Table1[[Especificação]:[Total Testes]],MATCH('Sheet1 (2)'!C31,Table1[CONCAT],0),MATCH('Sheet1 (2)'!B31,Table1[[#Headers],[Especificação]:[Total Testes]],0)) -> 1 | H31: =ROUND(G31/8,2) -> 0.13
B32: =Table1[[#Headers],[Especificação]] -> Especificação | C32: =D32&"_"&E32 -> ENTITY_PURE_TRNVR_P | D32: ENTITY | E32: PURE_TRNVR_P | G32: =INDEX(Table1[[Especificação]:[Total Testes]],MATCH('Sheet1 (2)'!C32,Table1[CONCAT],0),MATCH('Sheet1 (2)'!B32,Table1[[#Headers],[Especificação]:[Total Testes]],0)) -> 1 | H32: =ROUND(G32/8,2) -> 0.13
B33: =Table1[[#Headers],[Especificação]] -> Especificação | C33: =D33&"_"&E33 -> ENTITY_PURE_CAPEX_B | D33: ENTITY | E33: PURE_CAPEX_B | G33: =INDEX(Table1[[Especificação]:[Total Testes]],MATCH('Sheet1 (2)'!C33,Table1[CONCAT],0),MATCH('Sheet1 (2)'!B33,Table1[[#Headers],[Especificação]:[Total Testes]],0)) -> 1 | H33: =ROUND(G33/8,2) -> 0.13
B34: =Table1[[#Headers],[Especificação]] -> Especificação | C34: =D34&"_"&E34 -> ENTITY_PURE_TRNVR_B | D34: ENTITY | E34: PURE_TRNVR_B | G34: =INDEX(Table1[[Especificação]:[Total Testes]],MATCH('Sheet1 (2)'!C34,Table1[CONCAT],0),MATCH('Sheet1 (2)'!B34,Table1[[#Headers],[Especificação]:[Total Testes]],0)) -> 1 | H34: =ROUND(G34/8,2) -> 0.13
... B70: =Table1[[#Headers],[Especificação]] -> Especificação | C70: =D70&"_"&E70 -> INSTR_ACTIVITY_DNSH_DTL | D70: INSTR_ACTIVITY | E70: DNSH_DTL | G70: =INDEX(Table1[[Especificação]:[Total Testes]],MATCH('Sheet1 (2)'!C70,Table1[CONCAT],0),MATCH('Sheet1 (2)'!B70,Table1[[#Headers],[Especificação]:[Total Testes]],0)) -> 0 | H70: =ROUND(G70/8,2) -> 0
C71: Especificação de Requisitos - ESG Risks | F71: =+COUNTA(E72:E83) -> 12 | G71: =SUM(G72:G83) -> 25 | H71: =ROUND(SUM(H72:H83),1) -> 3.1 | I71: =SUM(J71:CQ71)-H71 -> 0 | Z71: 0.5 | AA71: 0.5 | AB71: 0.5 | AC71: 0.5 | AD71: 0.5 | AE71: 0.5 | AF71: 0.1
B72: =Table1[[#Headers],[Especificação]] -> Especificação | C72: =D72&"_"&E72 -> ENTITY_GRP_ECNMC_ACTVTY | D72: ENTITY | E72: GRP_ECNMC_ACTVTY | G72: =INDEX(Table1[[Especificação]:[Total Testes]],MATCH('Sheet1 (2)'!C72,Table1[CONCAT],0),MATCH('Sheet1 (2)'!B72,Table1[[#Headers],[Especificação]:[Total Testes]],0)) -> 2 | H72: =ROUND(G72/8,2) -> 0.25
B73: =Table1[[#Headers],[Especificação]] -> Especificação | C73: =D73&"_"&E73 -> PROTECTION_EPC_EMSSNS_LBL | D73: PROTECTION | E73: EPC_EMSSNS_LBL | G73: =INDEX(Table1[[Especificação]:[Total Testes]],MATCH('Sheet1 (2)'!C73,Table1[CONCAT],0),MATCH('Sheet1 (2)'!B73,Table1[[#Headers],[Especificação]:[Total Testes]],0)) -> 2 | H73: =ROUND(G73/8,2) -> 0.25
B74: =Table1[[#Headers],[Especificação]] -> Especificação | C74: =D74&"_"&E74 -> PROTECTION_TYP_EMSSNS_SCR | D74: PROTECTION | E74: TYP_EMSSNS_SCR | G74: =INDEX(Table1[[Especificação]:[Total Testes]],MATCH('Sheet1 (2)'!C74,Table1[CONCAT],0),MATCH('Sheet1 (2)'!B74,Table1[[#Headers],[Especificação]:[Total Testes]],0)) -> 2 | H74: =ROUND(G74/8,2) -> 0.25
B75: =Table1[[#Headers],[Especificação]] -> Especificação | C75: =D75&"_"&E75 -> PROTECTION_EPC_EMSSNS_SCR | D75: PROTECTION | E75: EPC_EMSSNS_SCR | G75: =INDEX(Table1[[Especificação]:[Total Testes]],MATCH('Sheet1 (2)'!C75,Table1[CONCAT],0),MATCH('Sheet1 (2)'!B75,Table1[[#Headers],[Especificação]:[Total Testes]],0)) -> 4 | H75: =ROUND(G75/8,2) -> 0.5
B76: =Table1[[#Headers],[Especificação]] -> Especificação | C76: =D76&"_"&E76 -> INSTRUMENT_INTRNL_SGMNT | D76: INSTRUMENT | E76: INTRNL_SGMNT | G76: =INDEX(Table1[[Especificação]:[Total Testes]],MATCH('Sheet1 (2)'!C76,Table1[CONCAT],0),MATCH('Sheet1 (2)'!B76,Table1[[#Headers],[Especificação]:[Total Testes]],0)) -> 2 | H76: =ROUND(G76/8,2) -> 0.25
B77: =Table1[[#Headers],[Especificação]] -> Especificação | C77: =D77&"_"&E77 -> INSTRUMENT_EAD | D77: INSTRUMENT | E77: EAD | G77: =INDEX(Table1[[Especificação]:[Total Testes]],MATCH('Sheet1 (2)'!C77,Table1[CONCAT],0),MATCH('Sheet1 (2)'!B77,Table1[[#Headers],[Especificação]:[Total Testes]],0)) -> 1 | H77: =ROUND(G77/8,2) -> 0.13
B78: =Table1[[#Headers],[Especificação]] -> Especificação | C78: =D78&"_"&E78 -> INSTRUMENT_OFF_BLNC_SHT_AMNT_INSTRMNT | D78: INSTRUMENT | E78: OFF_BLNC_SHT_AMNT_INSTRMNT | G78: =INDEX(Table1[[Especificação]:[Total Testes]],MATCH('Sheet1 (2)'!C78,Table1[CONCAT],0),MATCH('Sheet1 (2)'!B78,Table1[[#Headers],[Especificação]:[Total Testes]],0)) -> 2 | H78: =ROUND(G78/8,2) -> 0.25
B79: =Table1[[#Headers],[Especificação]] -> Especificação | C79: =D79&"_"&E79 -> INSTRUMENT_INTRNL_SGMNT_CAT_MSTA | D79: INSTRUMENT | E79: INTRNL_SGMNT_CAT_MSTA | G79: =INDEX(Table1[[Especificação]:[Total Testes]],MATCH('Sheet1 (2)'!C79,Table1[CONCAT],0),MATCH('Sheet1 (2)'!B79,Table1[[#Headers],[Especificação]:[Total Testes]],0)) -> 2 | H79: =ROUND(G79/8,2) -> 0.25
B80: =Table1[[#Headers],[Especificação]] -> Especificação | C80: =D80&"_"&E80 -> INSTRUMENT_INTRNL_SGMNT_CATGSUB | D80: INSTRUMENT | E80: INTRNL_SGMNT_CATGSUB | G80: =INDEX(Table1[[Especificação]:[Total Testes]],MATCH('Sheet1 (2)'!C80,Table1[CONCAT],0),MATCH('Sheet1 (2)'!B80,Table1[[#Headers],[Especificação]:[Total Testes]],0)) -> 2 | H80: =ROUND(G80/8,2) -> 0.25
B81: =Table1[[#Headers],[Especificação]] -> Especificação | C81: =D81&"_"&E81 -> PROTECTION_RL_ESTT_ADDRSS | D81: PROTECTION | E81: RL_ESTT_ADDRSS | G81: =INDEX(Table1[[Especificação]:[Total Testes]],MATCH('Sheet1 (2)'!C81,Table1[CONCAT],0),MATCH('Sheet1 (2)'!B81,Table1[[#Headers],[Especificação]:[Total Testes]],0)) -> 2 | H81: =ROUND(G81/8,2) -> 0.25
B82: =Table1[[#Headers],[Especificação]] -> Especificação | C82: =D82&"_"&E82 -> PROTECTION_RL_ESTT_CLLTRL_LCTN_INT | D82: PROTECTION | E82: RL_ESTT_CLLTRL_LCTN_INT | G82: =INDEX(Table1[[Especificação]:[Total Testes]],MATCH('Sheet1 (2)'!C82,Table1[CONCAT],0),MATCH('Sheet1 (2)'!B82,Table1[[#Headers],[Especificação]:[Total Testes]],0)) -> 2 | H82: =ROUND(G82/8,2) -> 0.25
B83: =Table1[[#Headers],[Especificação]] -> Especificação | C83: =D83&"_"&E83 -> PROTECTION_RL_ESTT_CTY | D83: PROTECTION | E83: RL_ESTT_CTY | G83: =INDEX(Table1[[Especificação]:[Total Testes]],MATCH('Sheet1 (2)'!C83,Table1[CONCAT],0),MATCH('Sheet1 (2)'!B83,Table1[[#Headers],[Especificação]:[Total Testes]],0)) -> 2 | H83: =ROUND(G83/8,2) -> 0.25
... B91: =Table1[[#Headers],[Especificação]] -> Especificação | C91: =D91&"_"&E91 -> PROTECTION_FLG_FRST_HM | D91: PROTECTION | E91: FLG_FRST_HM | G91: =INDEX(Table1[[Especificação]:[Total Testes]],MATCH('Sheet1 (2)'!C91,Table1[CONCAT],0),MATCH('Sheet1 (2)'!B91,Table1[[#Headers],[Especificação]:[Total Testes]],0)) -> 0 | H91: =ROUND(G91/8,2) -> 0
C92: 3. Simulação campos (P3 + ESG Risks) | F92: =COUNTA(E93:E124) -> 32 | G92: =SUM(G93:G124) -> 77.5 | H92: =ROUND(SUM(H93:H124),1) -> 9.8 | I92: =SUM(J92:CQ92)-H92 -> 0 | Z92: 1 | AA92: 1 | AB92: 1 | AC92: 1 | AD92: 1 | AE92: 1 | AF92: 1 | AG92: 0.5 | AH92: 0.5 | AI92: 0.5 | AJ92: 0.5 | AK92: 0.5 | AL92: 0.3
B93: =Table1[[#Headers],[Simulação]] -> Simulação | C93: =D93&"_"&E93 -> ENTITY_TXNMY_ELGBL_CAPEX_W | D93: ENTITY | E93: TXNMY_ELGBL_CAPEX_W | G93: =INDEX(Table1[[Especificação]:[Total Testes]],MATCH('Sheet1 (2)'!C93,Table1[CONCAT],0),MATCH('Sheet1 (2)'!B93,Table1[[#Headers],[Especificação]:[Total Testes]],0)) -> 6 | H93: =ROUND(G93/8,2) -> 0.75
B94: =Table1[[#Headers],[Simulação]] -> Simulação | C94: =D94&"_"&E94 -> ENTITY_TXNMY_ELGBL_TRNVR_W | D94: ENTITY | E94: TXNMY_ELGBL_TRNVR_W | G94: =INDEX(Table1[[Especificação]:[Total Testes]],MATCH('Sheet1 (2)'!C94,Table1[CONCAT],0),MATCH('Sheet1 (2)'!B94,Table1[[#Headers],[Especificação]:[Total Testes]],0)) -> 6 | H94: =ROUND(G94/8,2) -> 0.75
B95: =Table1[[#Headers],[Simulação]] -> Simulação | C95: =D95&"_"&E95 -> ENTITY_TXNMY_ELGBL_CAPEX_P | D95: ENTITY | E95: TXNMY_ELGBL_CAPEX_P | G95: =INDEX(Table1[[Especificação]:[Total Testes]],MATCH('Sheet1 (2)'!C95,Table1[CONCAT],0),MATCH('Sheet1 (2)'!B95,Table1[[#Headers],[Especificação]:[Total Testes]],0)) -> 1 | H95: =ROUND(G95/8,2) -> 0.13
B96: =Table1[[#Headers],[Simulação]] -> Simulação | C96: =D96&"_"&E96 -> ENTITY_TXNMY_ELGBL_TRNVR_P | D96: ENTITY | E96: TXNMY_ELGBL_TRNVR_P | G96: =INDEX(Table1[[Especificação]:[Total Testes]],MATCH('Sheet1 (2)'!C96,Table1[CONCAT],0),MATCH('Sheet1 (2)'!B96,Table1[[#Headers],[Especificação]:[Total Testes]],0)) -> 1 | H96: =ROUND(G96/8,2) -> 0.13
B97: =Table1[[#Headers],[Simulação]] -> Simulação | C97: =D97&"_"&E97 -> ENTITY_TXNMY_ELGBL_CAPEX_B | D97: ENTITY | E97: TXNMY_ELGBL_CAPEX_B | G97: =INDEX(Table1[[Especificação]:[Total Testes]],MATCH('Sheet1 (2)'!C97,Table1[CONCAT],0),MATCH('Sheet1 (2)'!B97,Table1[[#Headers],[Especificação]:[Total Testes]],0)) -> 1 | H97: =ROUND(G97/8,2) -> 0.13
B98: =Table1[[#Headers],[Simulação]] -> Simulação | C98: =D98&"_"&E98 -> ENTITY_TXNMY_ELGBL_TRNVR_B | D98: ENTITY | E98: TXNMY_ELGBL_TRNVR_B | G98: =INDEX(Table1[[Especificação]:[Total Testes]],MATCH('Sheet1 (2)'!C98,Table1[CONCAT],0),MATCH('Sheet1 (2)'!B98,Table1[[#Headers],[Especificação]:[Total Testes]],0)) -> 1 | H98: =ROUND(G98/8,2) -> 0.13
B99: =Table1[[#Headers],[Simulação]] -> Simulação | C99: =D99&"_"&E99 -> ENTITY_TXNMY_ELGBL_CAPEX_CE | D99: ENTITY | E99: TXNMY_ELGBL_CAPEX_CE | G99: =INDEX(Table1[[Especificação]:[Total Testes]],MATCH('Sheet1 (2)'!C99,Table1[CONCAT],0),MATCH('Sheet1 (2)'!B99,Table1[[#Headers],[Especificação]:[Total Testes]],0)) -> 1 | H99: =ROUND(G99/8,2) -> 0.13
B100: =Table1[[#Headers],[Simulação]] -> Simulação | C100: =D100&"_"&E100 -> ENTITY_TXNMY_ELGBL_TRNVR_CE | D100: ENTITY | E100: TXNMY_ELGBL_TRNVR_CE | G100: =INDEX(Table1[[Especificação]:[Total Testes]],MATCH('Sheet1 (2)'!C100,Table1[CONCAT],0),MATCH('Sheet1 (2)'!B100,Table1[[#Headers],[Especificação]:[Total Testes]],0)) -> 1 | H100: =ROUND(G100/8,2) -> 0.13
B101: =Table1[[#Headers],[Simulação]] -> Simulação | C101: =D101&"_"&E101 -> ENTITY_PURE_CAPEX_P | D101: ENTITY | E101: PURE_CAPEX_P | G101: =INDEX(Table1[[Especificação]:[Total Testes]],MATCH('Sheet1 (2)'!C101,Table1[CONCAT],0),MATCH('Sheet1 (2)'!B101,Table1[[#Headers],[Especificação]:[Total Testes]],0)) -> 1 | H101: =ROUND(G101/8,2) -> 0.13
B102: =Table1[[#Headers],[Simulação]] -> Simulação | C102: =D102&"_"&E102 -> ENTITY_PURE_TRNVR_P | D102: ENTITY | E102: PURE_TRNVR_P | G102: =INDEX(Table1[[Especificação]:[Total Testes]],MATCH('Sheet1 (2)'!C102,Table1[CONCAT],0),MATCH('Sheet1 (2)'!B102,Table1[[#Headers],[Especificação]:[Total Testes]],0)) -> 1 | H102: =ROUND(G102/8,2) -> 0.13
B103: =Table1[[#Headers],[Simulação]] -> Simulação | C103: =D103&"_"&E103 -> ENTITY_PURE_CAPEX_B | D103: ENTITY | E103: PURE_CAPEX_B | G103: =INDEX(Table1[[Especificação]:[Total Testes]],MATCH('Sheet1 (2)'!C103,Table1[CONCAT],0),MATCH('Sheet1 (2)'!B103,Table1[[#Headers],[Especificação]:[Total Testes]],0)) -> 1 | H103: =ROUND(G103/8,2) -> 0.13
B104: =Table1[[#Headers],[Simulação]] -> Simulação | C104: =D104&"_"&E104 -> ENTITY_PURE_TRNVR_B | D104: ENTITY | E104: PURE_TRNVR_B | G104: =INDEX(Table1[[Especificação]:[Total Testes]],MATCH('Sheet1 (2)'!C104,Table1[CONCAT],0),MATCH('Sheet1 (2)'!B104,Table1[[#Headers],[Especificação]:[Total Testes]],0)) -> 1 | H104: =ROUND(G104/8,2) -> 0.13
... B160: =Table1[[#Headers],[Simulação]] -> Simulação | C160: =D160&"_"&E160 -> INSTR_ACTIVITY_DNSH_DTL | D160: INSTR_ACTIVITY | E160: DNSH_DTL | G160: =INDEX(Table1[[Especificação]:[Total Testes]],MATCH('Sheet1 (2)'!C160,Table1[CONCAT],0),MATCH('Sheet1 (2)'!B160,Table1[[#Headers],[Especificação]:[Total Testes]],0)) -> 0 | H160: =ROUND(G160/8,2) -> 0
C161: 4. Testes Campos (P3 + ESG Risks) | F161: =COUNTA(E162:E193) -> 32 | G161: =SUM(G162:G193) -> 121 | H161: =ROUND(SUM(H162:H193),1) -> 15.1 | I161: =SUM(J161:CQ161)-H161 -> 0 | AV161: 1 | AW161: 1 | AX161: 1 | AY161: 1 | AZ161: 2 | BA161: 2 | BC161: 2 | BD161: 2 | BE161: 2 | BF161: 1.1
B162: =Table1[[#Headers],[Total Testes]] -> Total Testes | C162: =D162&"_"&E162 -> ENTITY_TXNMY_ELGBL_CAPEX_W | D162: ENTITY | E162: TXNMY_ELGBL_CAPEX_W | G162: =INDEX(Table1[[Especificação]:[Total Testes]],MATCH('Sheet1 (2)'!C162,Table1[CONCAT],0),MATCH('Sheet1 (2)'!B162,Table1[[#Headers],[Especificação]:[Total Testes]],0)) -> 7.5 | H162: =ROUND(G162/8,2) -> 0.94
B163: =Table1[[#Headers],[Total Testes]] -> Total Testes | C163: =D163&"_"&E163 -> ENTITY_TXNMY_ELGBL_TRNVR_W | D163: ENTITY | E163: TXNMY_ELGBL_TRNVR_W | G163: =INDEX(Table1[[Especificação]:[Total Testes]],MATCH('Sheet1 (2)'!C163,Table1[CONCAT],0),MATCH('Sheet1 (2)'!B163,Table1[[#Headers],[Especificação]:[Total Testes]],0)) -> 7.5 | H163: =ROUND(G163/8,2) -> 0.94
B164: =Table1[[#Headers],[Total Testes]] -> Total Testes | C164: =D164&"_"&E164 -> ENTITY_TXNMY_ELGBL_CAPEX_P | D164: ENTITY | E164: TXNMY_ELGBL_CAPEX_P | G164: =INDEX(Table1[[Especificação]:[Total Testes]],MATCH('Sheet1 (2)'!C164,Table1[CONCAT],0),MATCH('Sheet1 (2)'!B164,Table1[[#Headers],[Especificação]:[Total Testes]],0)) -> 2.5 | H164: =ROUND(G164/8,2) -> 0.31
B165: =Table1[[#Headers],[Total Testes]] -> Total Testes | C165: =D165&"_"&E165 -> ENTITY_TXNMY_ELGBL_TRNVR_P | D165: ENTITY | E165: TXNMY_ELGBL_TRNVR_P | G165: =INDEX(Table1[[Especificação]:[Total Testes]],MATCH('Sheet1 (2)'!C165,Table1[CONCAT],0),MATCH('Sheet1 (2)'!B165,Table1[[#Headers],[Especificação]:[Total Testes]],0)) -> 2.5 | H165: =ROUND(G165/8,2) -> 0.31
B166: =Table1[[#Headers],[Total Testes]] -> Total Testes | C166: =D166&"_"&E166 -> ENTITY_TXNMY_ELGBL_CAPEX_B | D166: ENTITY | E166: TXNMY_ELGBL_CAPEX_B | G166: =INDEX(Table1[[Especificação]:[Total Testes]],MATCH('Sheet1 (2)'!C166,Table1[CONCAT],0),MATCH('Sheet1 (2)'!B166,Table1[[#Headers],[Especificação]:[Total Testes]],0)) -> 2.5 | H166: =ROUND(G166/8,2) -> 0.31
B167: =Table1[[#Headers],[Total Testes]] -> Total Testes | C167: =D167&"_"&E167 -> ENTITY_TXNMY_ELGBL_TRNVR_B | D167: ENTITY | E167: TXNMY_ELGBL_TRNVR_B | G167: =INDEX(Table1[[Especificação]:[Total Testes]],MATCH('Sheet1 (2)'!C167,Table1[CONCAT],0),MATCH('Sheet1 (2)'!B167,Table1[[#Headers],[Especificação]:[Total Testes]],0)) -> 2.5 | H167: =ROUND(G167/8,2) -> 0.31
B168: =Table1[[#Headers],[Total Testes]] -> Total Testes | C168: =D168&"_"&E168 -> ENTITY_TXNMY_ELGBL_CAPEX_CE | D168: ENTITY | E168: TXNMY_ELGBL_CAPEX_CE | G168: =INDEX(Table1[[Especificação]:[Total Testes]],MATCH('Sheet1 (2)'!C168,Table1[CONCAT],0),MATCH('Sheet1 (2)'!B168,Table1[[#Headers],[Especificação]:[Total Testes]],0)) -> 2.5 | H168: =ROUND(G168/8,2) -> 0.31
B169: =Table1[[#Headers],[Total Testes]] -> Total Testes | C169: =D169&"_"&E169 -> ENTITY_TXNMY_ELGBL_TRNVR_CE | D169: ENTITY | E169: TXNMY_ELGBL_TRNVR_CE | G169: =INDEX(Table1[[Especificação]:[Total Testes]],MATCH('Sheet1 (2)'!C169,Table1[CONCAT],0),MATCH('Sheet1 (2)'!B169,Table1[[#Headers],[Especificação]:[Total Testes]],0)) -> 2.5 | H169: =ROUND(G169/8,2) -> 0.31
B170: =Table1[[#Headers],[Total Testes]] -> Total Testes | C170: =D170&"_"&E170 -> ENTITY_PURE_CAPEX_P | D170: ENTITY | E170: PURE_CAPEX_P | G170: =INDEX(Table1[[Especificação]:[Total Testes]],MATCH('Sheet1 (2)'!C170,Table1[CONCAT],0),MATCH('Sheet1 (2)'!B170,Table1[[#Headers],[Especificação]:[Total Testes]],0)) -> 2.5 | H170: =ROUND(G170/8,2) -> 0.31
B171: =Table1[[#Headers],[Total Testes]] -> Total Testes | C171: =D171&"_"&E171 -> ENTITY_PURE_TRNVR_P | D171: ENTITY | E171: PURE_TRNVR_P | G171: =INDEX(Table1[[Especificação]:[Total Testes]],MATCH('Sheet1 (2)'!C171,Table1[CONCAT],0),MATCH('Sheet1 (2)'!B171,Table1[[#Headers],[Especificação]:[Total Testes]],0)) -> 2.5 | H171: =ROUND(G171/8,2) -> 0.31
B172: =Table1[[#Headers],[Total Testes]] -> Total Testes | C172: =D172&"_"&E172 -> ENTITY_PURE_CAPEX_B | D172: ENTITY | E172: PURE_CAPEX_B | G172: =INDEX(Table1[[Especificação]:[Total Testes]],MATCH('Sheet1 (2)'!C172,Table1[CONCAT],0),MATCH('Sheet1 (2)'!B172,Table1[[#Headers],[Especificação]:[Total Testes]],0)) -> 2.5 | H172: =ROUND(G172/8,2) -> 0.31
B173: =Table1[[#Headers],[Total Testes]] -> Total Testes | C173: =D173&"_"&E173 -> ENTITY_PURE_TRNVR_B | D173: ENTITY | E173: PURE_TRNVR_B | G173: =INDEX(Table1[[Especificação]:[Total Testes]],MATCH('Sheet1 (2)'!C173,Table1[CONCAT],0),MATCH('Sheet1 (2)'!B173,Table1[[#Headers],[Especificação]:[Total Testes]],0)) -> 2.5 | H173: =ROUND(G173/8,2) -> 0.31
... B229: =Table1[[#Headers],[Total Testes]] -> Total Testes | C229: =D229&"_"&E229 -> INSTR_ACTIVITY_DNSH_DTL | D229: INSTR_ACTIVITY | E229: DNSH_DTL | G229: =INDEX(Table1[[Especificação]:[Total Testes]],MATCH('Sheet1 (2)'!C229,Table1[CONCAT],0),MATCH('Sheet1 (2)'!B229,Table1[[#Headers],[Especificação]:[Total Testes]],0)) -> 0 | H229: =ROUND(G229/8,2) -> 0
C230: 5. Re-testes | G230: =H230*8 -> 32 | H230: =ROUNDUP(Auxiliar!$E$12*H161,0) -> 4 | I230: =SUM(J230:CQ230)-H230 -> 2.2 | BF230: 0.9 | BG230: 2 | BH230: 1.1 | BI230: 1.1 | BJ230: 1.1
C236: Horas Total | D236: =SUM(K1:CA1) -> 651.2 | E236: SMART TOTAL
C237: Horas Novos Requisitos | E237: SMART NOVOS REQUISITOS
Z239: =9+8 -> 17
Z240: =17/5 -> 3.4
C241: 12,13,14 Março ==> Dias de 'buffer'
C242: 12 a 20 Fevereiro ==> Freeze 'teórico'

Sheet LISTA - Setembro2024
Y1: &
A2: SETEMBRO | F2: ESTR | G2: GD | H2: PILAR3 | I2: GFINANCE | J2: ESG_RISKS | K2: LF | L2: Comparação com lista ATUAL | V2: Comparação com lista ATUAL | AC2: Estimativas
A3: ID Data field / Field order | B3: CONCAT | C3: Table | D3: Data field | E3: Field name | F3: Structural ECB Loan Tape | G3: Green Dashboard | H3: Pillar III ESG | I3: Green Finance | J3: ESG Risks | K3: Leveraged Finance | L3: ATUAL_Structural ECB Loan Tape | M3: val_ESTR | N3: ATUAL_Green Dashboard | O3: val_GD | P3: ATUAL_Pillar III ESG | Q3: val_PILAR3 | R3: ATUAL_Green Finance | S3: ATUAL_ESG Risks | T3: val_ESG_RISKS | U3: ATUAL_Leveraged Finance | V3: Fonte manual LF | W3: Status Data Lake | X3: Status Data Lake (Detalhe) | Y3: AMBITO | Z3: STATUS | AA3: xx | AB3: format | AC3: Complexidade (todos) | AD3: Especificação | AE3: Simulação | AF3: 2. Testes comparativos | AG3: Complexidade (code list) | AH3: 3. Val. Code List | AI3: 4. Val. Formatos | AJ3: 5. Val.Controlos Corp. | AK3: Total Testes | AL3: Observações
A4: EN.001 | B4: =C4&"_"&D4 -> ENTITY_COD_SOC | C4: ENTITY | D4: COD_SOC | E4: Entity code of the informing society. | F4: Y | G4: N | H4: Y | I4: N | J4: Y | K4: Y | L4: =IFERROR(VLOOKUP($B4,'LISTA - Atual'!$B$1:$I$444,5,0),"Novo") -> Y | M4: =IF(L4="Novo","Novo Campo",IF(L4=F4,"Igual","Diferente")) -> Igual | N4: =IFERROR(VLOOKUP($B4,'LISTA - Atual'!$B$1:$I$444,6,0),"Novo") -> N | O4: =IF(N4="Novo","Novo Campo",IF(N4=G4,"Igual","Diferente")) -> Igual | P4: =IFERROR(VLOOKUP($B4,'LISTA - Atual'!$B$1:$I$444,7,0),"Novo") -> Y | Q4: =IF(P4="Novo","Novo Campo",IF(P4=H4,"Igual","Diferente")) -> Igual | R4: n/a | S4: =IFERROR(VLOOKUP($B4,'LISTA - Atual'!$B$1:$I$444,8,0),"Novo") -> Y | T4: =IF(S4="Novo","Novo Campo",IF(S4=J4,"Igual","Diferente")) -> Igual | U4: n/a | V4: N | W4: =IFERROR(VLOOKUP(B4,#REF!,11,0),"n/a") -> n/a | X4: =IFERROR(VLOOKUP(B4,#REF!,8,0),"n/a") -> n/a | Y4: =$F$2&$Y$1&$H$2 -> ESTR & PILAR3 | Z4: Sem alteração | AA4: =VLOOKUP(Table1[[#This Row],[CONCAT]],'Campos Resumo Prop2.0'!A:H,8,0) -> #N/A | AB4: VARCHAR2(5) | AC4: n.a. | AD4: =INDEX(Auxiliar!$D$5:$I$10,MATCH('LISTA - Setembro2024'!AD$3,Auxiliar!$B$5:$B$10,0),MATCH('LISTA - Setembro2024'!$AC4,Auxiliar!$D$4:$I$4,0)) -> 0 | AE4: =INDEX(Auxiliar!$D$5:$I$10,MATCH('LISTA - Setembro2024'!AE$3,Auxiliar!$B$5:$B$10,0),MATCH('LISTA - Setembro2024'!$AC4,Auxiliar!$D$4:$I$4,0)) -> 0 | AF4: =INDEX(Auxiliar!$D$5:$I$10,MATCH('LISTA - Setembro2024'!AF$3,Auxiliar!$B$5:$B$10,0),MATCH('LISTA - Setembro2024'!$AC4,Auxiliar!$D$4:$I$4,0)) -> 0 | AG4: =IF(OR(AB4="Code List",AB4="Y, N"),AC4,"n.a.") -> n.a. | AH4: =INDEX(Auxiliar!$D$5:$I$10,MATCH('LISTA - Setembro2024'!AH$3,Auxiliar!$B$5:$B$10,0),MATCH('LISTA - Setembro2024'!$AG4,Auxiliar!$D$4:$I$4,0)) -> 0 | AI4: =INDEX(Auxiliar!$D$5:$I$10,MATCH('LISTA - Setembro2024'!AI$3,Auxiliar!$B$5:$B$10,0),MATCH('LISTA - Setembro2024'!$AC4,Auxiliar!$D$4:$I$4,0)) -> 0 | AJ4: =INDEX(Auxiliar!$D$5:$I$10,MATCH('LISTA - Setembro2024'!AJ$3,Auxiliar!$B$5:$B$10,0),MATCH('LISTA - Setembro2024'!$AC4,Auxiliar!$D$4:$I$4,0)) -> 0 | AK4: =SUM(AF4,AH4:AJ4) -> 0
A5: EN.002 | B5: =C5&"_"&D5 -> ENTITY_CNTRY | C5: ENTITY | D5: CNTRY | E5: Country of counterparty residence | F5: Y | G5: N | H5: Y | I5: N | J5: Y | K5: Y | L5: =IFERROR(VLOOKUP($B5,'LISTA - Atual'!$B$1:$I$444,5,0),"Novo") -> Y | M5: =IF(L5="Novo","Novo Campo",IF(L5=F5,"Igual","Diferente")) -> Igual | N5: =IFERROR(VLOOKUP($B5,'LISTA - Atual'!$B$1:$I$444,6,0),"Novo") -> N | O5: =IF(N5="Novo","Novo Campo",IF(N5=G5,"Igual","Diferente")) -> Igual | P5: =IFERROR(VLOOKUP($B5,'LISTA - Atual'!$B$1:$I$444,7,0),"Novo") -> Y | Q5: =IF(P5="Novo","Novo Campo",IF(P5=H5,"Igual","Diferente")) -> Igual | R5: n/a | S5: =IFERROR(VLOOKUP($B5,'LISTA - Atual'!$B$1:$I$444,8,0),"Novo") -> Y | T5: =IF(S5="Novo","Novo Campo",IF(S5=J5,"Igual","Diferente")) -> Igual | U5: n/a | V5: N | W5: =IFERROR(VLOOKUP(B5,#REF!,11,0),"n/a") -> n/a | X5: =IFERROR(VLOOKUP(B5,#REF!,8,0),"n/a") -> n/a | Y5: =$F$2&$Y$1&$H$2 -> ESTR & PILAR3 | Z5: Sem alteração | AA5: =VLOOKUP(Table1[[#This Row],[CONCAT]],'Campos Resumo Prop2.0'!A:H,8,0) -> #N/A | AB5: Code List | AC5: n.a. | AD5: =INDEX(Auxiliar!$D$5:$I$10,MATCH('LISTA - Setembro2024'!AD$3,Auxiliar!$B$5:$B$10,0),MATCH('LISTA - Setembro2024'!$AC5,Auxiliar!$D$4:$I$4,0)) -> 0 | AE5: =INDEX(Auxiliar!$D$5:$I$10,MATCH('LISTA - Setembro2024'!AE$3,Auxiliar!$B$5:$B$10,0),MATCH('LISTA - Setembro2024'!$AC5,Auxiliar!$D$4:$I$4,0)) -> 0 | AF5: =INDEX(Auxiliar!$D$5:$I$10,MATCH('LISTA - Setembro2024'!AF$3,Auxiliar!$B$5:$B$10,0),MATCH('LISTA - Setembro2024'!$AC5,Auxiliar!$D$4:$I$4,0)) -> 0 | AG5: =IF(OR(AB5="Code List",AB5="Y, N"),AC5,"n.a.") -> n.a. | AH5: =INDEX(Auxiliar!$D$5:$I$10,MATCH('LISTA - Setembro2024'!AH$3,Auxiliar!$B$5:$B$10,0),MATCH('LISTA - Setembro2024'!$AG5,Auxiliar!$D$4:$I$4,0)) -> 0 | AI5: =INDEX(Auxiliar!$D$5:$I$10,MATCH('LISTA - Setembro2024'!AI$3,Auxiliar!$B$5:$B$10,0),MATCH('LISTA - Setembro2024'!$AC5,Auxiliar!$D$4:$I$4,0)) -> 0 | AJ5: =INDEX(Auxiliar!$D$5:$I$10,MATCH('LISTA - Setembro2024'!AJ$3,Auxiliar!$B$5:$B$10,0),MATCH('LISTA - Setembro2024'!$AC5,Auxiliar!$D$4:$I$4,0)) -> 0 | AK5: =SUM(AF5,AH5:AJ5) -> 0
A6: EN.003 | B6: =C6&"_"&D6 -> ENTITY_DT_BRTH | C6: ENTITY | D6: DT_BRTH | E6: Birth date counterparty | F6: Y | G6: N | H6: N | I6: N | J6: N | K6: N | L6: =IFERROR(VLOOKUP($B6,'LISTA - Atual'!$B$1:$I$444,5,0),"Novo") -> Y | M6: =IF(L6="Novo","Novo Campo",IF(L6=F6,"Igual","Diferente")) -> Igual | N6: =IFERROR(VLOOKUP($B6,'LISTA - Atual'!$B$1:$I$444,6,0),"Novo") -> N | O6: =IF(N6="Novo","Novo Campo",IF(N6=G6,"Igual","Diferente")) -> Igual | P6: =IFERROR(VLOOKUP($B6,'LISTA - Atual'!$B$1:$I$444,7,0),"Novo") -> N | Q6: =IF(P6="Novo","Novo Campo",IF(P6=H6,"Igual","Diferente")) -> Igual | R6: n/a | S6: =IFERROR(VLOOKUP($B6,'LISTA - Atual'!$B$1:$I$444,8,0),"Novo") -> N | T6: =IF(S6="Novo","Novo Campo",IF(S6=J6,"Igual","Diferente")) -> Igual | U6: n/a | V6: N | W6: =IFERROR(VLOOKUP(B6,#REF!,11,0),"n/a") -> n/a | X6: =IFERROR(VLOOKUP(B6,#REF!,8,0),"n/a") -> n/a | Y6: =$F$2 -> ESTR | Z6: Sem alteração | AA6: =VLOOKUP(Table1[[#This Row],[CONCAT]],'Campos Resumo Prop2.0'!A:H,8,0) -> #N/A | AB6: DATE | AC6: n.a. | AD6: =INDEX(Auxiliar!$D$5:$I$10,MATCH('LISTA - Setembro2024'!AD$3,Auxiliar!$B$5:$B$10,0),MATCH('LISTA - Setembro2024'!$AC6,Auxiliar!$D$4:$I$4,0)) -> 0 | AE6: =INDEX(Auxiliar!$D$5:$I$10,MATCH('LISTA - Setembro2024'!AE$3,Auxiliar!$B$5:$B$10,0),MATCH('LISTA - Setembro2024'!$AC6,Auxiliar!$D$4:$I$4,0)) -> 0 | AF6: =INDEX(Auxiliar!$D$5:$I$10,MATCH('LISTA - Setembro2024'!AF$3,Auxiliar!$B$5:$B$10,0),MATCH('LISTA - Setembro2024'!$AC6,Auxiliar!$D$4:$I$4,0)) -> 0 | AG6: =IF(OR(AB6="Code List",AB6="Y, N"),AC6,"n.a.") -> n.a. | AH6: =INDEX(Auxiliar!$D$5:$I$10,MATCH('LISTA - Setembro2024'!AH$3,Auxiliar!$B$5:$B$10,0),MATCH('LISTA - Setembro2024'!$AG6,Auxiliar!$D$4:$I$4,0)) -> 0 | AI6: =INDEX(Auxiliar!$D$5:$I$10,MATCH('LISTA - Setembro2024'!AI$3,Auxiliar!$B$5:$B$10,0),MATCH('LISTA - Setembro2024'!$AC6,Auxiliar!$D$4:$I$4,0)) -> 0 | AJ6: =INDEX(Auxiliar!$D$5:$I$10,MATCH('LISTA - Setembro2024'!AJ$3,Auxiliar!$B$5:$B$10,0),MATCH('LISTA - Setembro2024'!$AC6,Auxiliar!$D$4:$I$4,0)) -> 0 | AK6: =SUM(AF6,AH6:AJ6) -> 0
A7: EN.004 | B7: =C7&"_"&D7 -> ENTITY_DT_DFLT_STTS | C7: ENTITY | D7: DT_DFLT_STTS | E7: Date of default status | F7: Y | G7: N | H7: N | I7: N | J7: N | K7: Y | L7: =IFERROR(VLOOKUP($B7,'LISTA - Atual'!$B$1:$I$444,5,0),"Novo") -> Y | M7: =IF(L7="Novo","Novo Campo",IF(L7=F7,"Igual","Diferente")) -> Igual | N7: =IFERROR(VLOOKUP($B7,'LISTA - Atual'!$B$1:$I$444,6,0),"Novo") -> N | O7: =IF(N7="Novo","Novo Campo",IF(N7=G7,"Igual","Diferente")) -> Igual | P7: =IFERROR(VLOOKUP($B7,'LISTA - Atual'!$B$1:$I$444,7,0),"Novo") -> N | Q7: =IF(P7="Novo","Novo Campo",IF(P7=H7,"Igual","Diferente")) -> Igual | R7: n/a | S7: =IFERROR(VLOOKUP($B7,'LISTA - Atual'!$B$1:$I$444,8,0),"Novo") -> N | T7: =IF(S7="Novo","Novo Campo",IF(S7=J7,"Igual","Diferente")) -> Igual | U7: n/a | V7: N | W7: =IFERROR(VLOOKUP(B7,#REF!,11,0),"n/a") -> n/a | X7: =IFERROR(VLOOKUP(B7,#REF!,8,0),"n/a") -> n/a | Y7: =$F$2 -> ESTR | Z7: Sem alteração | AA7: =VLOOKUP(Table1[[#This Row],[CONCAT]],'Campos Resumo Prop2.0'!A:H,8,0) -> #N/A | AB7: DATE | AC7: n.a. | AD7: =INDEX(Auxiliar!$D$5:$I$10,MATCH('LISTA - Setembro2024'!AD$3,Auxiliar!$B$5:$B$10,0),MATCH('LISTA - Setembro2024'!$AC7,Auxiliar!$D$4:$I$4,0)) -> 0 | AE7: =INDEX(Auxiliar!$D$5:$I$10,MATCH('LISTA - Setembro2024'!AE$3,Auxiliar!$B$5:$B$10,0),MATCH('LISTA - Setembro2024'!$AC7,Auxiliar!$D$4:$I$4,0)) -> 0 | AF7: =INDEX(Auxiliar!$D$5:$I$10,MATCH('LISTA - Setembro2024'!AF$3,Auxiliar!$B$5:$B$10,0),MATCH('LISTA - Setembro2024'!$AC7,Auxiliar!$D$4:$I$4,0)) -> 0 | AG7: =IF(OR(AB7="Code List",AB7="Y, N"),AC7,"n.a.") -> n.a. | AH7: =INDEX(Auxiliar!$D$5:$I$10,MATCH('LISTA - Setembro2024'!AH$3,Auxiliar!$B$5:$B$10,0),MATCH('LISTA - Setembro2024'!$AG7,Auxiliar!$D$4:$I$4,0)) -> 0 | AI7: =INDEX(Auxiliar!$D$5:$I$10,MATCH('LISTA - Setembro2024'!AI$3,Auxiliar!$B$5:$B$10,0),MATCH('LISTA - Setembro2024'!$AC7,Auxiliar!$D$4:$I$4,0)) -> 0 | AJ7: =INDEX(Auxiliar!$D$5:$I$10,MATCH('LISTA - Setembro2024'!AJ$3,Auxiliar!$B$5:$B$10,0),MATCH('LISTA - Setembro2024'!$AC7,Auxiliar!$D$4:$I$4,0)) -> 0 | AK7: =SUM(AF7,AH7:AJ7) -> 0 | AL7: Dependente de decisão
A8: EN.005 | B8: =C8&"_"&D8 -> ENTITY_DT_FNNCL_STTMTS | C8: ENTITY | D8: DT_FNNCL_STTMTS | E8: Date of financial statements | F8: Y | G8: N | H8: N | I8: N | J8: N | K8: Y | L8: =IFERROR(VLOOKUP($B8,'LISTA - Atual'!$B$1:$I$444,5,0),"Novo") -> Y | M8: =IF(L8="Novo","Novo Campo",IF(L8=F8,"Igual","Diferente")) -> Igual | N8: =IFERROR(VLOOKUP($B8,'LISTA - Atual'!$B$1:$I$444,6,0),"Novo") -> N | O8: =IF(N8="Novo","Novo Campo",IF(N8=G8,"Igual","Diferente")) -> Igual | P8: =IFERROR(VLOOKUP($B8,'LISTA - Atual'!$B$1:$I$444,7,0),"Novo") -> N | Q8: =IF(P8="Novo","Novo Campo",IF(P8=H8,"Igual","Diferente")) -> Igual | R8: n/a | S8: =IFERROR(VLOOKUP($B8,'LISTA - Atual'!$B$1:$I$444,8,0),"Novo") -> N | T8: =IF(S8="Novo","Novo Campo",IF(S8=J8,"Igual","Diferente")) -> Igual | U8: n/a | V8: N | W8: =IFERROR(VLOOKUP(B8,#REF!,11,0),"n/a") -> n/a | X8: =IFERROR(VLOOKUP(B8,#REF!,8,0),"n/a") -> n/a | Y8: =$F$2 -> ESTR | Z8: Sem alteração | AA8: =VLOOKUP(Table1[[#This Row],[CONCAT]],'Campos Resumo Prop2.0'!A:H,8,0) -> #N/A | AB8: DATE | AC8: n.a. | AD8: =INDEX(Auxiliar!$D$5:$I$10,MATCH('LISTA - Setembro2024'!AD$3,Auxiliar!$B$5:$B$10,0),MATCH('LISTA - Setembro2024'!$AC8,Auxiliar!$D$4:$I$4,0)) -> 0 | AE8: =INDEX(Auxiliar!$D$5:$I$10,MATCH('LISTA - Setembro2024'!AE$3,Auxiliar!$B$5:$B$10,0),MATCH('LISTA - Setembro2024'!$AC8,Auxiliar!$D$4:$I$4,0)) -> 0 | AF8: =INDEX(Auxiliar!$D$5:$I$10,MATCH('LISTA - Setembro2024'!AF$3,Auxiliar!$B$5:$B$10,0),MATCH('LISTA - Setembro2024'!$AC8,Auxiliar!$D$4:$I$4,0)) -> 0 | AG8: =IF(OR(AB8="Code List",AB8="Y, N"),AC8,"n.a.") -> n.a. | AH8: =INDEX(Auxiliar!$D$5:$I$10,MATCH('LISTA - Setembro2024'!AH$3,Auxiliar!$B$5:$B$10,0),MATCH('LISTA - Setembro2024'!$AG8,Auxiliar!$D$4:$I$4,0)) -> 0 | AI8: =INDEX(Auxiliar!$D$5:$I$10,MATCH('LISTA - Setembro2024'!AI$3,Auxiliar!$B$5:$B$10,0),MATCH('LISTA - Setembro2024'!$AC8,Auxiliar!$D$4:$I$4,0)) -> 0 | AJ8: =INDEX(Auxiliar!$D$5:$I$10,MATCH('LISTA - Setembro2024'!AJ$3,Auxiliar!$B$5:$B$10,0),MATCH('LISTA - Setembro2024'!$AC8,Auxiliar!$D$4:$I$4,0)) -> 0 | AK8: =SUM(AF8,AH8:AJ8) -> 0 | AL8: Dem. Fin
A9: EN.006 | B9: =C9&"_"&D9 -> ENTITY_DT_FNNCL_STTMTS_PRVS | C9: ENTITY | D9: DT_FNNCL_STTMTS_PRVS | E9: Date of previous fiscal year financial statements | F9: Y | G9: N | H9: N | I9: N | J9: N | K9: Y | L9: =IFERROR(VLOOKUP($B9,'LISTA - Atual'!$B$1:$I$444,5,0),"Novo") -> Y | M9: =IF(L9="Novo","Novo Campo",IF(L9=F9,"Igual","Diferente")) -> Igual | N9: =IFERROR(VLOOKUP($B9,'LISTA - Atual'!$B$1:$I$444,6,0),"Novo") -> N | O9: =IF(N9="Novo","Novo Campo",IF(N9=G9,"Igual","Diferente")) -> Igual | P9: =IFERROR(VLOOKUP($B9,'LISTA - Atual'!$B$1:$I$444,7,0),"Novo") -> N | Q9: =IF(P9="Novo","Novo Campo",IF(P9=H9,"Igual","Diferente")) -> Igual | R9: n/a | S9: =IFERROR(VLOOKUP($B9,'LISTA - Atual'!$B$1:$I$444,8,0),"Novo") -> N | T9: =IF(S9="Novo","Novo Campo",IF(S9=J9,"Igual","Diferente")) -> Igual | U9: n/a | V9: N | W9: =IFERROR(VLOOKUP(B9,#REF!,11,0),"n/a") -> n/a | X9: =IFERROR(VLOOKUP(B9,#REF!,8,0),"n/a") -> n/a | Y9: =$F$2 -> ESTR | Z9: Sem alteração | AA9: =VLOOKUP(Table1[[#This Row],[CONCAT]],'Campos Resumo Prop2.0'!A:H,8,0) -> #N/A | AB9: DATE | AC9: n.a. | AD9: =INDEX(Auxiliar!$D$5:$I$10,MATCH('LISTA - Setembro2024'!AD$3,Auxiliar!$B$5:$B$10,0),MATCH('LISTA - Setembro2024'!$AC9,Auxiliar!$D$4:$I$4,0)) -> 0 | AE9: =INDEX(Auxiliar!$D$5:$I$10,MATCH('LISTA - Setembro2024'!AE$3,Auxiliar!$B$5:$B$10,0),MATCH('LISTA - Setembro2024'!$AC9,Auxiliar!$D$4:$I$4,0)) -> 0 | AF9: =INDEX(Auxiliar!$D$5:$I$10,MATCH('LISTA - Setembro2024'!AF$3,Auxiliar!$B$5:$B$10,0),MATCH('LISTA - Setembro2024'!$AC9,Auxiliar!$D$4:$I$4,0)) -> 0 | AG9: =IF(OR(AB9="Code List",AB9="Y, N"),AC9,"n.a.") -> n.a. | AH9: =INDEX(Auxiliar!$D$5:$I$10,MATCH('LISTA - Setembro2024'!AH$3,Auxiliar!$B$5:$B$10,0),MATCH('LISTA - Setembro2024'!$AG9,Auxiliar!$D$4:$I$4,0)) -> 0 | AI9: =INDEX(Auxiliar!$D$5:$I$10,MATCH('LISTA - Setembro2024'!AI$3,Auxiliar!$B$5:$B$10,0),MATCH('LISTA - Setembro2024'!$AC9,Auxiliar!$D$4:$I$4,0)) -> 0 | AJ9: =INDEX(Auxiliar!$D$5:$I$10,MATCH('LISTA - Setembro2024'!AJ$3,Auxiliar!$B$5:$B$10,0),MATCH('LISTA - Setembro2024'!$AC9,Auxiliar!$D$4:$I$4,0)) -> 0 | AK9: =SUM(AF9,AH9:AJ9) -> 0 | AL9: Dem. Fin
A10: EN.007 | B10: =C10&"_"&D10 -> ENTITY_DT_INTTN_LGL_PRCDNGS_LE | C10: ENTITY | D10: DT_INTTN_LGL_PRCDNGS_LE | E10: Date of initiation of legal proceedings counterparty (LE) | F10: Y | G10: N | H10: N | I10: N | J10: N | K10: Y | L10: =IFERROR(VLOOKUP($B10,'LISTA - Atual'!$B$1:$I$444,5,0),"Novo") -> Y | M10: =IF(L10="Novo","Novo Campo",IF(L10=F10,"Igual","Diferente")) -> Igual | N10: =IFERROR(VLOOKUP($B10,'LISTA - Atual'!$B$1:$I$444,6,0),"Novo") -> N | O10: =IF(N10="Novo","Novo Campo",IF(N10=G10,"Igual","Diferente")) -> Igual | P10: =IFERROR(VLOOKUP($B10,'LISTA - Atual'!$B$1:$I$444,7,0),"Novo") -> N | Q10: =IF(P10="Novo","Novo Campo",IF(P10=H10,"Igual","Diferente")) -> Igual | R10: n/a | S10: =IFERROR(VLOOKUP($B10,'LISTA - Atual'!$B$1:$I$444,8,0),"Novo") -> N | T10: =IF(S10="Novo","Novo Campo",IF(S10=J10,"Igual","Diferente")) -> Igual | U10: n/a | V10: N | W10: =IFERROR(VLOOKUP(B10,#REF!,11,0),"n/a") -> n/a | X10: =IFERROR(VLOOKUP(B10,#REF!,8,0),"n/a") -> n/a | Y10: =$F$2 -> ESTR | Z10: Sem alteração | AA10: =VLOOKUP(Table1[[#This Row],[CONCAT]],'Campos Resumo Prop2.0'!A:H,8,0) -> #N/A | AB10: DATE | AC10: n.a. | AD10: =INDEX(Auxiliar!$D$5:$I$10,MATCH('LISTA - Setembro2024'!AD$3,Auxiliar!$B$5:$B$10,0),MATCH('LISTA - Setembro2024'!$AC10,Auxiliar!$D$4:$I$4,0)) -> 0 | AE10: =INDEX(Auxiliar!$D$5:$I$10,MATCH('LISTA - Setembro2024'!AE$3,Auxiliar!$B$5:$B$10,0),MATCH('LISTA - Setembro2024'!$AC10,Auxiliar!$D$4:$I$4,0)) -> 0 | AF10: =INDEX(Auxiliar!$D$5:$I$10,MATCH('LISTA - Setembro2024'!AF$3,Auxiliar!$B$5:$B$10,0),MATCH('LISTA - Setembro2024'!$AC10,Auxiliar!$D$4:$I$4,0)) -> 0 | AG10: =IF(OR(AB10="Code List",AB10="Y, N"),AC10,"n.a.") -> n.a. | AH10: =INDEX(Auxiliar!$D$5:$I$10,MATCH('LISTA - Setembro2024'!AH$3,Auxiliar!$B$5:$B$10,0),MATCH('LISTA - Setembro2024'!$AG10,Auxiliar!$D$4:$I$4,0)) -> 0 | AI10: =INDEX(Auxiliar!$D$5:$I$10,MATCH('LISTA - Setembro2024'!AI$3,Auxiliar!$B$5:$B$10,0),MATCH('LISTA - Setembro2024'!$AC10,Auxiliar!$D$4:$I$4,0)) -> 0 | AJ10: =INDEX(Auxiliar!$D$5:$I$10,MATCH('LISTA - Setembro2024'!AJ$3,Auxiliar!$B$5:$B$10,0),MATCH('LISTA - Setembro2024'!$AC10,Auxiliar!$D$4:$I$4,0)) -> 0 | AK10: =SUM(AF10,AH10:AJ10) -> 0
A11: EN.008 | B11: =C11&"_"&D11 -> ENTITY_DT_PRFRMNG_STTS_LE | C11: ENTITY | D11: DT_PRFRMNG_STTS_LE | E11: Date of performing status | F11: Y | G11: N | H11: N | I11: N | J11: N | K11: Y | L11: =IFERROR(VLOOKUP($B11,'LISTA - Atual'!$B$1:$I$444,5,0),"Novo") -> Y | M11: =IF(L11="Novo","Novo Campo",IF(L11=F11,"Igual","Diferente")) -> Igual | N11: =IFERROR(VLOOKUP($B11,'LISTA - Atual'!$B$1:$I$444,6,0),"Novo") -> N | O11: =IF(N11="Novo","Novo Campo",IF(N11=G11,"Igual","Diferente")) -> Igual | P11: =IFERROR(VLOOKUP($B11,'LISTA - Atual'!$B$1:$I$444,7,0),"Novo") -> N | Q11: =IF(P11="Novo","Novo Campo",IF(P11=H11,"Igual","Diferente")) -> Igual | R11: n/a | S11: =IFERROR(VLOOKUP($B11,'LISTA - Atual'!$B$1:$I$444,8,0),"Novo") -> N | T11: =IF(S11="Novo","Novo Campo",IF(S11=J11,"Igual","Diferente")) -> Igual | U11: n/a | V11: N | W11: =IFERROR(VLOOKUP(B11,#REF!,11,0),"n/a") -> n/a | X11: =IFERROR(VLOOKUP(B11,#REF!,8,0),"n/a") -> n/a | Y11: =$F$2 -> ESTR | Z11: Sem alteração | AA11: =VLOOKUP(Table1[[#This Row],[CONCAT]],'Campos Resumo Prop2.0'!A:H,8,0) -> #N/A | AB11: DATE | AC11: n.a. | AD11: =INDEX(Auxiliar!$D$5:$I$10,MATCH('LISTA - Setembro2024'!AD$3,Auxiliar!$B$5:$B$10,0),MATCH('LISTA - Setembro2024'!$AC11,Auxiliar!$D$4:$I$4,0)) -> 0 | AE11: =INDEX(Auxiliar!$D$5:$I$10,MATCH('LISTA - Setembro2024'!AE$3,Auxiliar!$B$5:$B$10,0),MATCH('LISTA - Setembro2024'!$AC11,Auxiliar!$D$4:$I$4,0)) -> 0 | AF11: =INDEX(Auxiliar!$D$5:$I$10,MATCH('LISTA - Setembro2024'!AF$3,Auxiliar!$B$5:$B$10,0),MATCH('LISTA - Setembro2024'!$AC11,Auxiliar!$D$4:$I$4,0)) -> 0 | AG11: =IF(OR(AB11="Code List",AB11="Y, N"),AC11,"n.a.") -> n.a. | AH11: =INDEX(Auxiliar!$D$5:$I$10,MATCH('LISTA - Setembro2024'!AH$3,Auxiliar!$B$5:$B$10,0),MATCH('LISTA - Setembro2024'!$AG11,Auxiliar!$D$4:$I$4,0)) -> 0 | AI11: =INDEX(Auxiliar!$D$5:$I$10,MATCH('LISTA - Setembro2024'!AI$3,Auxiliar!$B$5:$B$10,0),MATCH('LISTA - Setembro2024'!$AC11,Auxiliar!$D$4:$I$4,0)) -> 0 | AJ11: =INDEX(Auxiliar!$D$5:$I$10,MATCH('LISTA - Setembro2024'!AJ$3,Auxiliar!$B$5:$B$10,0),MATCH('LISTA - Setembro2024'!$AC11,Auxiliar!$D$4:$I$4,0)) -> 0 | AK11: =SUM(AF11,AH11:AJ11) -> 0 | AL11: Dependente de decisão
A12: EN.009 | B12: =C12&"_"&D12 -> ENTITY_DT_RFRNC | C12: ENTITY | D12: DT_RFRNC | E12: Reference date. | F12: Y | G12: N | H12: Y | I12: N | J12: N | K12: Y | L12: =IFERROR(VLOOKUP($B12,'LISTA - Atual'!$B$1:$I$444,5,0),"Novo") -> Y | M12: =IF(L12="Novo","Novo Campo",IF(L12=F12,"Igual","Diferente")) -> Igual | N12: =IFERROR(VLOOKUP($B12,'LISTA - Atual'!$B$1:$I$444,6,0),"Novo") -> N | O12: =IF(N12="Novo","Novo Campo",IF(N12=G12,"Igual","Diferente")) -> Igual | P12: =IFERROR(VLOOKUP($B12,'LISTA - Atual'!$B$1:$I$444,7,0),"Novo") -> Y | Q12: =IF(P12="Novo","Novo Campo",IF(P12=H12,"Igual","Diferente")) -> Igual | R12: n/a | S12: =IFERROR(VLOOKUP($B12,'LISTA - Atual'!$B$1:$I$444,8,0),"Novo") -> N | T12: =IF(S12="Novo","Novo Campo",IF(S12=J12,"Igual","Diferente")) -> Igual | U12: n/a | V12: N | W12: =IFERROR(VLOOKUP(B12,#REF!,11,0),"n/a") -> n/a | X12: =IFERROR(VLOOKUP(B12,#REF!,8,0),"n/a") -> n/a | Y12: =$F$2&$Y$1&$H$2 -> ESTR & PILAR3 | Z12: Sem alteração | AA12: =VLOOKUP(Table1[[#This Row],[CONCAT]],'Campos Resumo Prop2.0'!A:H,8,0) -> #N/A | AB12: DATE | AC12: n.a. | AD12: =INDEX(Auxiliar!$D$5:$I$10,MATCH('LISTA - Setembro2024'!AD$3,Auxiliar!$B$5:$B$10,0),MATCH('LISTA - Setembro2024'!$AC12,Auxiliar!$D$4:$I$4,0)) -> 0 | AE12: =INDEX(Auxiliar!$D$5:$I$10,MATCH('LISTA - Setembro2024'!AE$3,Auxiliar!$B$5:$B$10,0),MATCH('LISTA - Setembro2024'!$AC12,Auxiliar!$D$4:$I$4,0)) -> 0 | AF12: =INDEX(Auxiliar!$D$5:$I$10,MATCH('LISTA - Setembro2024'!AF$3,Auxiliar!$B$5:$B$10,0),MATCH('LISTA - Setembro2024'!$AC12,Auxiliar!$D$4:$I$4,0)) -> 0 | AG12: =IF(OR(AB12="Code List",AB12="Y, N"),AC12,"n.a.") -> n.a. | AH12: =INDEX(Auxiliar!$D$5:$I$10,MATCH('LISTA - Setembro2024'!AH$3,Auxiliar!$B$5:$B$10,0),MATCH('LISTA - Setembro2024'!$AG12,Auxiliar!$D$4:$I$4,0)) -> 0 | AI12: =INDEX(Auxiliar!$D$5:$I$10,MATCH('LISTA - Setembro2024'!AI$3,Auxiliar!$B$5:$B$10,0),MATCH('LISTA - Setembro2024'!$AC12,Auxiliar!$D$4:$I$4,0)) -> 0 | AJ12: =INDEX(Auxiliar!$D$5:$I$10,MATCH('LISTA - Setembro2024'!AJ$3,Auxiliar!$B$5:$B$10,0),MATCH('LISTA - Setembro2024'!$AC12,Auxiliar!$D$4:$I$4,0)) -> 0 | AK12: =SUM(AF12,AH12:AJ12) -> 0
A13: EN.010 | B13: =C13&"_"&D13 -> ENTITY_ENTTY_ID | C13: ENTITY | D13: ENTTY_ID | E13: Entity ID | F13: Y | G13: N | H13: Y | I13: N | J13: Y | K13: Y | L13: =IFERROR(VLOOKUP($B13,'LISTA - Atual'!$B$1:$I$444,5,0),"Novo") -> Y | M13: =IF(L13="Novo","Novo Campo",IF(L13=F13,"Igual","Diferente")) -> Igual | N13: =IFERROR(VLOOKUP($B13,'LISTA - Atual'!$B$1:$I$444,6,0),"Novo") -> N | O13: =IF(N13="Novo","Novo Campo",IF(N13=G13,"Igual","Diferente")) -> Igual | P13: =IFERROR(VLOOKUP($B13,'LISTA - Atual'!$B$1:$I$444,7,0),"Novo") -> Y | Q13: =IF(P13="Novo","Novo Campo",IF(P13=H13,"Igual","Diferente")) -> Igual | R13: n/a | S13: =IFERROR(VLOOKUP($B13,'LISTA - Atual'!$B$1:$I$444,8,0),"Novo") -> Y | T13: =IF(S13="Novo","Novo Campo",IF(S13=J13,"Igual","Diferente")) -> Igual | U13: n/a | V13: N | W13: =IFERROR(VLOOKUP(B13,#REF!,11,0),"n/a") -> n/a | X13: =IFERROR(VLOOKUP(B13,#REF!,8,0),"n/a") -> n/a | Y13: =$F$2&$Y$1&$H$2 -> ESTR & PILAR3 | Z13: Sem alteração | AA13: =VLOOKUP(Table1[[#This Row],[CONCAT]],'Campos Resumo Prop2.0'!A:H,8,0) -> #N/A | AB13: VARCHAR2(255) | AC13: n.a. | AD13: =INDEX(Auxiliar!$D$5:$I$10,MATCH('LISTA - Setembro2024'!AD$3,Auxiliar!$B$5:$B$10,0),MATCH('LISTA - Setembro2024'!$AC13,Auxiliar!$D$4:$I$4,0)) -> 0 | AE13: =INDEX(Auxiliar!$D$5:$I$10,MATCH('LISTA - Setembro2024'!AE$3,Auxiliar!$B$5:$B$10,0),MATCH('LISTA - Setembro2024'!$AC13,Auxiliar!$D$4:$I$4,0)) -> 0 | AF13: =INDEX(Auxiliar!$D$5:$I$10,MATCH('LISTA - Setembro2024'!AF$3,Auxiliar!$B$5:$B$10,0),MATCH('LISTA - Setembro2024'!$AC13,Auxiliar!$D$4:$I$4,0)) -> 0 | AG13: =IF(OR(AB13="Code List",AB13="Y, N"),AC13,"n.a.") -> n.a. | AH13: =INDEX(Auxiliar!$D$5:$I$10,MATCH('LISTA - Setembro2024'!AH$3,Auxiliar!$B$5:$B$10,0),MATCH('LISTA - Setembro2024'!$AG13,Auxiliar!$D$4:$I$4,0)) -> 0 | AI13: =INDEX(Auxiliar!$D$5:$I$10,MATCH('LISTA - Setembro2024'!AI$3,Auxiliar!$B$5:$B$10,0),MATCH('LISTA - Setembro2024'!$AC13,Auxiliar!$D$4:$I$4,0)) -> 0 | AJ13: =INDEX(Auxiliar!$D$5:$I$10,MATCH('LISTA - Setembro2024'!AJ$3,Auxiliar!$B$5:$B$10,0),MATCH('LISTA - Setembro2024'!$AC13,Auxiliar!$D$4:$I$4,0)) -> 0 | AK13: =SUM(AF13,AH13:AJ13) -> 0
A14: EN.011 | B14: =C14&"_"&D14 -> ENTITY_GCC_PRNT_ID | C14: ENTITY | D14: GCC_PRNT_ID | E14: Identifier for the parent entity of a group of connected clients | F14: Y | G14: N | H14: N | I14: N | J14: N | K14: Y | L14: =IFERROR(VLOOKUP($B14,'LISTA - Atual'!$B$1:$I$444,5,0),"Novo") -> Y | M14: =IF(L14="Novo","Novo Campo",IF(L14=F14,"Igual","Diferente")) -> Igual | N14: =IFERROR(VLOOKUP($B14,'LISTA - Atual'!$B$1:$I$444,6,0),"Novo") -> N | O14: =IF(N14="Novo","Novo Campo",IF(N14=G14,"Igual","Diferente")) -> Igual | P14: =IFERROR(VLOOKUP($B14,'LISTA - Atual'!$B$1:$I$444,7,0),"Novo") -> N | Q14: =IF(P14="Novo","Novo Campo",IF(P14=H14,"Igual","Diferente")) -> Igual | R14: n/a | S14: =IFERROR(VLOOKUP($B14,'LISTA - Atual'!$B$1:$I$444,8,0),"Novo") -> N | T14: =IF(S14="Novo","Novo Campo",IF(S14=J14,"Igual","Diferente")) -> Igual | U14: n/a | V14: N | W14: =IFERROR(VLOOKUP(B14,#REF!,11,0),"n/a") -> n/a | X14: =IFERROR(VLOOKUP(B14,#REF!,8,0),"n/a") -> n/a | Y14: =$F$2 -> ESTR | Z14: Sem alteração | AA14: =VLOOKUP(Table1[[#This Row],[CONCAT]],'Campos Resumo Prop2.0'!A:H,8,0) -> #N/A | AB14: VARCHAR2(255) | AC14: n.a. | AD14: =INDEX(Auxiliar!$D$5:$I$10,MATCH('LISTA - Setembro2024'!AD$3,Auxiliar!$B$5:$B$10,0),MATCH('LISTA - Setembro2024'!$AC14,Auxiliar!$D$4:$I$4,0)) -> 0 | AE14: =INDEX(Auxiliar!$D$5:$I$10,MATCH('LISTA - Setembro2024'!AE$3,Auxiliar!$B$5:$B$10,0),MATCH('LISTA - Setembro2024'!$AC14,Auxiliar!$D$4:$I$4,0)) -> 0 | AF14: =INDEX(Auxiliar!$D$5:$I$10,MATCH('LISTA - Setembro2024'!AF$3,Auxiliar!$B$5:$B$10,0),MATCH('LISTA - Setembro2024'!$AC14,Auxiliar!$D$4:$I$4,0)) -> 0 | AG14: =IF(OR(AB14="Code List",AB14="Y, N"),AC14,"n.a.") -> n.a. | AH14: =INDEX(Auxiliar!$D$5:$I$10,MATCH('LISTA - Setembro2024'!AH$3,Auxiliar!$B$5:$B$10,0),MATCH('LISTA - Setembro2024'!$AG14,Auxiliar!$D$4:$I$4,0)) -> 0 | AI14: =INDEX(Auxiliar!$D$5:$I$10,MATCH('LISTA - Setembro2024'!AI$3,Auxiliar!$B$5:$B$10,0),MATCH('LISTA - Setembro2024'!$AC14,Auxiliar!$D$4:$I$4,0)) -> 0 | AJ14: =INDEX(Auxiliar!$D$5:$I$10,MATCH('LISTA - Setembro2024'!AJ$3,Auxiliar!$B$5:$B$10,0),MATCH('LISTA - Setembro2024'!$AC14,Auxiliar!$D$4:$I$4,0)) -> 0 | AK14: =SUM(AF14,AH14:AJ14) -> 0
A15: EN.012 | B15: =C15&"_"&D15 -> ENTITY_GCC_PRNT_NM | C15: ENTITY | D15: GCC_PRNT_NM | E15: Name of the parent entity of a group of connected clients | F15: Y | G15: N | H15: N | I15: N | J15: N | K15: Y | L15: =IFERROR(VLOOKUP($B15,'LISTA - Atual'!$B$1:$I$444,5,0),"Novo") -> Y | M15: =IF(L15="Novo","Novo Campo",IF(L15=F15,"Igual","Diferente")) -> Igual | N15: =IFERROR(VLOOKUP($B15,'LISTA - Atual'!$B$1:$I$444,6,0),"Novo") -> N | O15: =IF(N15="Novo","Novo Campo",IF(N15=G15,"Igual","Diferente")) -> Igual | P15: =IFERROR(VLOOKUP($B15,'LISTA - Atual'!$B$1:$I$444,7,0),"Novo") -> N | Q15: =IF(P15="Novo","Novo Campo",IF(P15=H15,"Igual","Diferente")) -> Igual | R15: n/a | S15: =IFERROR(VLOOKUP($B15,'LISTA - Atual'!$B$1:$I$444,8,0),"Novo") -> N | T15: =IF(S15="Novo","Novo Campo",IF(S15=J15,"Igual","Diferente")) -> Igual | U15: n/a | V15: N | W15: =IFERROR(VLOOKUP(B15,#REF!,11,0),"n/a") -> n/a | X15: =IFERROR(VLOOKUP(B15,#REF!,8,0),"n/a") -> n/a | Y15: =$F$2 -> ESTR | Z15: Sem alteração | AA15: =VLOOKUP(Table1[[#This Row],[CONCAT]],'Campos Resumo Prop2.0'!A:H,8,0) -> #N/A | AB15: VARCHAR2(255) | AC15: n.a. | AD15: =INDEX(Auxiliar!$D$5:$I$10,MATCH('LISTA - Setembro2024'!AD$3,Auxiliar!$B$5:$B$10,0),MATCH('LISTA - Setembro2024'!$AC15,Auxiliar!$D$4:$I$4,0)) -> 0 | AE15: =INDEX(Auxiliar!$D$5:$I$10,MATCH('LISTA - Setembro2024'!AE$3,Auxiliar!$B$5:$B$10,0),MATCH('LISTA - Setembro2024'!$AC15,Auxiliar!$D$4:$I$4,0)) -> 0 | AF15: =INDEX(Auxiliar!$D$5:$I$10,MATCH('LISTA - Setembro2024'!AF$3,Auxiliar!$B$5:$B$10,0),MATCH('LISTA - Setembro2024'!$AC15,Auxiliar!$D$4:$I$4,0)) -> 0 | AG15: =IF(OR(AB15="Code List",AB15="Y, N"),AC15,"n.a.") -> n.a. | AH15: =INDEX(Auxiliar!$D$5:$I$10,MATCH('LISTA - Setembro2024'!AH$3,Auxiliar!$B$5:$B$10,0),MATCH('LISTA - Setembro2024'!$AG15,Auxiliar!$D$4:$I$4,0)) -> 0 | AI15: =INDEX(Auxiliar!$D$5:$I$10,MATCH('LISTA - Setembro2024'!AI$3,Auxiliar!$B$5:$B$10,0),MATCH('LISTA - Setembro2024'!$AC15,Auxiliar!$D$4:$I$4,0)) -> 0 | AJ15: =INDEX(Auxiliar!$D$5:$I$10,MATCH('LISTA - Setembro2024'!AJ$3,Auxiliar!$B$5:$B$10,0),MATCH('LISTA - Setembro2024'!$AC15,Auxiliar!$D$4:$I$4,0)) -> 0 | AK15: =SUM(AF15,AH15:AJ15) -> 0
A16: EN.013 | B16: =C16&"_"&D16 -> ENTITY_INTRNL_SGMNT | C16: ENTITY | D16: INTRNL_SGMNT | E16: Internal code for segment/portfolio | F16: Y | G16: N | H16: N | I16: N | J16: N | K16: Y | L16: =IFERROR(VLOOKUP($B16,'LISTA - Atual'!$B$1:$I$444,5,0),"Novo") -> Y | M16: =IF(L16="Novo","Novo Campo",IF(L16=F16,"Igual","Diferente")) -> Igual | N16: =IFERROR(VLOOKUP($B16,'LISTA - Atual'!$B$1:$I$444,6,0),"Novo") -> N | O16: =IF(N16="Novo","Novo Campo",IF(N16=G16,"Igual","Diferente")) -> Igual | P16: =IFERROR(VLOOKUP($B16,'LISTA - Atual'!$B$1:$I$444,7,0),"Novo") -> N | Q16: =IF(P16="Novo","Novo Campo",IF(P16=H16,"Igual","Diferente")) -> Igual | R16: n/a | S16: =IFERROR(VLOOKUP($B16,'LISTA - Atual'!$B$1:$I$444,8,0),"Novo") -> N | T16: =IF(S16="Novo","Novo Campo",IF(S16=J16,"Igual","Diferente")) -> Igual | U16: n/a | V16: N | W16: =IFERROR(VLOOKUP(B16,#REF!,11,0),"n/a") -> n/a | X16: =IFERROR(VLOOKUP(B16,#REF!,8,0),"n/a") -> n/a | Y16: =$F$2 -> ESTR | Z16: Sem alteração | AA16: =VLOOKUP(Table1[[#This Row],[CONCAT]],'Campos Resumo Prop2.0'!A:H,8,0) -> #N/A | AB16: VARCHAR2(255) | AC16: n.a. | AD16: =INDEX(Auxiliar!$D$5:$I$10,MATCH('LISTA - Setembro2024'!AD$3,Auxiliar!$B$5:$B$10,0),MATCH('LISTA - Setembro2024'!$AC16,Auxiliar!$D$4:$I$4,0)) -> 0 | AE16: =INDEX(Auxiliar!$D$5:$I$10,MATCH('LISTA - Setembro2024'!AE$3,Auxiliar!$B$5:$B$10,0),MATCH('LISTA - Setembro2024'!$AC16,Auxiliar!$D$4:$I$4,0)) -> 0 | AF16: =INDEX(Auxiliar!$D$5:$I$10,MATCH('LISTA - Setembro2024'!AF$3,Auxiliar!$B$5:$B$10,0),MATCH('LISTA - Setembro2024'!$AC16,Auxiliar!$D$4:$I$4,0)) -> 0 | AG16: =IF(OR(AB16="Code List",AB16="Y, N"),AC16,"n.a.") -> n.a. | AH16: =INDEX(Auxiliar!$D$5:$I$10,MATCH('LISTA - Setembro2024'!AH$3,Auxiliar!$B$5:$B$10,0),MATCH('LISTA - Setembro2024'!$AG16,Auxiliar!$D$4:$I$4,0)) -> 0 | AI16: =INDEX(Auxiliar!$D$5:$I$10,MATCH('LISTA - Setembro2024'!AI$3,Auxiliar!$B$5:$B$10,0),MATCH('LISTA - Setembro2024'!$AC16,Auxiliar!$D$4:$I$4,0)) -> 0 | AJ16: =INDEX(Auxiliar!$D$5:$I$10,MATCH('LISTA - Setembro2024'!AJ$3,Auxiliar!$B$5:$B$10,0),MATCH('LISTA - Setembro2024'!$AC16,Auxiliar!$D$4:$I$4,0)) -> 0 | AK16: =SUM(AF16,AH16:AJ16) -> 0
A17: EN.014 | B17: =C17&"_"&D17 -> ENTITY_INTRNL_UNT | C17: ENTITY | D17: INTRNL_UNT | E17: Internal code for business line/unit | F17: Y | G17: N | H17: N | I17: N | J17: N | K17: Y | L17: =IFERROR(VLOOKUP($B17,'LISTA - Atual'!$B$1:$I$444,5,0),"Novo") -> Y | M17: =IF(L17="Novo","Novo Campo",IF(L17=F17,"Igual","Diferente")) -> Igual | N17: =IFERROR(VLOOKUP($B17,'LISTA - Atual'!$B$1:$I$444,6,0),"Novo") -> N | O17: =IF(N17="Novo","Novo Campo",IF(N17=G17,"Igual","Diferente")) -> Igual | P17: =IFERROR(VLOOKUP($B17,'LISTA - Atual'!$B$1:$I$444,7,0),"Novo") -> N | Q17: =IF(P17="Novo","Novo Campo",IF(P17=H17,"Igual","Diferente")) -> Igual | R17: n/a | S17: =IFERROR(VLOOKUP($B17,'LISTA - Atual'!$B$1:$I$444,8,0),"Novo") -> N | T17: =IF(S17="Novo","Novo Campo",IF(S17=J17,"Igual","Diferente")) -> Igual | U17: n/a | V17: N | W17: =IFERROR(VLOOKUP(B17,#REF!,11,0),"n/a") -> n/a | X17: =IFERROR(VLOOKUP(B17,#REF!,8,0),"n/a") -> n/a | Y17: =$F$2 -> ESTR | Z17: Sem alteração | AA17: =VLOOKUP(Table1[[#This Row],[CONCAT]],'Campos Resumo Prop2.0'!A:H,8,0) -> #N/A | AB17: VARCHAR2(255) | AC17: n.a. | AD17: =INDEX(Auxiliar!$D$5:$I$10,MATCH('LISTA - Setembro2024'!AD$3,Auxiliar!$B$5:$B$10,0),MATCH('LISTA - Setembro2024'!$AC17,Auxiliar!$D$4:$I$4,0)) -> 0 | AE17: =INDEX(Auxiliar!$D$5:$I$10,MATCH('LISTA - Setembro2024'!AE$3,Auxiliar!$B$5:$B$10,0),MATCH('LISTA - Setembro2024'!$AC17,Auxiliar!$D$4:$I$4,0)) -> 0 | AF17: =INDEX(Auxiliar!$D$5:$I$10,MATCH('LISTA - Setembro2024'!AF$3,Auxiliar!$B$5:$B$10,0),MATCH('LISTA - Setembro2024'!$AC17,Auxiliar!$D$4:$I$4,0)) -> 0 | AG17: =IF(OR(AB17="Code List",AB17="Y, N"),AC17,"n.a.") -> n.a. | AH17: =INDEX(Auxiliar!$D$5:$I$10,MATCH('LISTA - Setembro2024'!AH$3,Auxiliar!$B$5:$B$10,0),MATCH('LISTA - Setembro2024'!$AG17,Auxiliar!$D$4:$I$4,0)) -> 0 | AI17: =INDEX(Auxiliar!$D$5:$I$10,MATCH('LISTA - Setembro2024'!AI$3,Auxiliar!$B$5:$B$10,0),MATCH('LISTA - Setembro2024'!$AC17,Auxiliar!$D$4:$I$4,0)) -> 0 | AJ17: =INDEX(Auxiliar!$D$5:$I$10,MATCH('LISTA - Setembro2024'!AJ$3,Auxiliar!$B$5:$B$10,0),MATCH('LISTA - Setembro2024'!$AC17,Auxiliar!$D$4:$I$4,0)) -> 0 | AK17: =SUM(AF17,AH17:AJ17) -> 0
A18: EN.015 | B18: =C18&"_"&D18 -> ENTITY_LEI | C18: ENTITY | D18: LEI | E18: Legal entity identifier Counterparty | F18: Y | G18: N | H18: Y | I18: N | J18: N | K18: Y | L18: =IFERROR(VLOOKUP($B18,'LISTA - Atual'!$B$1:$I$444,5,0),"Novo") -> Y | M18: =IF(L18="Novo","Novo Campo",IF(L18=F18,"Igual","Diferente")) -> Igual | N18: =IFERROR(VLOOKUP($B18,'LISTA - Atual'!$B$1:$I$444,6,0),"Novo") -> N | O18: =IF(N18="Novo","Novo Campo",IF(N18=G18,"Igual","Diferente")) -> Igual | P18: =IFERROR(VLOOKUP($B18,'LISTA - Atual'!$B$1:$I$444,7,0),"Novo") -> Y | Q18: =IF(P18="Novo","Novo Campo",IF(P18=H18,"Igual","Diferente")) -> Igual | R18: n/a | S18: =IFERROR(VLOOKUP($B18,'LISTA - Atual'!$B$1:$I$444,8,0),"Novo") -> N | T18: =IF(S18="Novo","Novo Campo",IF(S18=J18,"Igual","Diferente")) -> Igual | U18: n/a | V18: N | W18: =IFERROR(VLOOKUP(B18,#REF!,11,0),"n/a") -> n/a | X18: =IFERROR(VLOOKUP(B18,#REF!,8,0),"n/a") -> n/a | Y18: =$F$2&$Y$1&$H$2 -> ESTR & PILAR3 | Z18: Sem alteração | AA18: =VLOOKUP(Table1[[#This Row],[CONCAT]],'Campos Resumo Prop2.0'!A:H,8,0) -> #N/A | AB18: VARCHAR2(20) | AC18: n.a. | AD18: =INDEX(Auxiliar!$D$5:$I$10,MATCH('LISTA - Setembro2024'!AD$3,Auxiliar!$B$5:$B$10,0),MATCH('LISTA - Setembro2024'!$AC18,Auxiliar!$D$4:$I$4,0)) -> 0 | AE18: =INDEX(Auxiliar!$D$5:$I$10,MATCH('LISTA - Setembro2024'!AE$3,Auxiliar!$B$5:$B$10,0),MATCH('LISTA - Setembro2024'!$AC18,Auxiliar!$D$4:$I$4,0)) -> 0 | AF18: =INDEX(Auxiliar!$D$5:$I$10,MATCH('LISTA - Setembro2024'!AF$3,Auxiliar!$B$5:$B$10,0),MATCH('LISTA - Setembro2024'!$AC18,Auxiliar!$D$4:$I$4,0)) -> 0 | AG18: =IF(OR(AB18="Code List",AB18="Y, N"),AC18,"n.a.") -> n.a. | AH18: =INDEX(Auxiliar!$D$5:$I$10,MATCH('LISTA - Setembro2024'!AH$3,Auxiliar!$B$5:$B$10,0),MATCH('LISTA - Setembro2024'!$AG18,Auxiliar!$D$4:$I$4,0)) -> 0 | AI18: =INDEX(Auxiliar!$D$5:$I$10,MATCH('LISTA - Setembro2024'!AI$3,Auxiliar!$B$5:$B$10,0),MATCH('LISTA - Setembro2024'!$AC18,Auxiliar!$D$4:$I$4,0)) -> 0 | AJ18: =INDEX(Auxiliar!$D$5:$I$10,MATCH('LISTA - Setembro2024'!AJ$3,Auxiliar!$B$5:$B$10,0),MATCH('LISTA - Setembro2024'!$AC18,Auxiliar!$D$4:$I$4,0)) -> 0 | AK18: =SUM(AF18,AH18:AJ18) -> 0
A19: EN.016 | B19: =C19&"_"&D19 -> ENTITY_ENTTY_NM | C19: ENTITY | D19: ENTTY_NM | E19: Name Counterparty | F19: Y | G19: N | H19: Y | I19: N | J19: N | K19: Y | L19: =IFERROR(VLOOKUP($B19,'LISTA - Atual'!$B$1:$I$444,5,0),"Novo") -> Y | M19: =IF(L19="Novo","Novo Campo",IF(L19=F19,"Igual","Diferente")) -> Igual | N19: =IFERROR(VLOOKUP($B19,'LISTA - Atual'!$B$1:$I$444,6,0),"Novo") -> N | O19: =IF(N19="Novo","Novo Campo",IF(N19=G19,"Igual","Diferente")) -> Igual | P19: =IFERROR(VLOOKUP($B19,'LISTA - Atual'!$B$1:$I$444,7,0),"Novo") -> N | Q19: =IF(P19="Novo","Novo Campo",IF(P19=H19,"Igual","Diferente")) -> Diferente | R19: n/a | S19: =IFERROR(VLOOKUP($B19,'LISTA - Atual'!$B$1:$I$444,8,0),"Novo") -> N | T19: =IF(S19="Novo","Novo Campo",IF(S19=J19,"Igual","Diferente")) -> Igual | U19: n/a | V19: N | W19: =IFERROR(VLOOKUP(B19,#REF!,11,0),"n/a") -> n/a | X19: =IFERROR(VLOOKUP(B19,#REF!,8,0),"n/a") -> n/a | Y19: =$F$2&$Y$1&$H$2 -> ESTR & PILAR3 | Z19: Novo Campo | AA19: =VLOOKUP(Table1[[#This Row],[CONCAT]],'Campos Resumo Prop2.0'!A:H,8,0) -> Não será contemplado no âmbito da proposta - Campos do LT ESTR | AB19: VARCHAR2(255) | AC19: M. Baixa | AD19: =INDEX(Auxiliar!$D$5:$I$10,MATCH('LISTA - Setembro2024'!AD$3,Auxiliar!$B$5:$B$10,0),MATCH('LISTA - Setembro2024'!$AC19,Auxiliar!$D$4:$I$4,0)) -> 1 | AE19: 0 | AF19: =INDEX(Auxiliar!$D$5:$I$10,MATCH('LISTA - Setembro2024'!AF$3,Auxiliar!$B$5:$B$10,0),MATCH('LISTA - Setembro2024'!$AC19,Auxiliar!$D$4:$I$4,0)) -> 1 | AG19: =IF(OR(AB19="Code List",AB19="Y, N"),AC19,"n.a.") -> n.a. | AH19: =INDEX(Auxiliar!$D$5:$I$10,MATCH('LISTA - Setembro2024'!AH$3,Auxiliar!$B$5:$B$10,0),MATCH('LISTA - Setembro2024'!$AG19,Auxiliar!$D$4:$I$4,0)) -> 0 | AI19: =INDEX(Auxiliar!$D$5:$I$10,MATCH('LISTA - Setembro2024'!AI$3,Auxiliar!$B$5:$B$10,0),MATCH('LISTA - Setembro2024'!$AC19,Auxiliar!$D$4:$I$4,0)) -> 0.5 | AJ19: =INDEX(Auxiliar!$D$5:$I$10,MATCH('LISTA - Setembro2024'!AJ$3,Auxiliar!$B$5:$B$10,0),MATCH('LISTA - Setembro2024'!$AC19,Auxiliar!$D$4:$I$4,0)) -> 1 | AK19: 0
A20: EN.017 | B20: =C20&"_"&D20 -> ENTITY_EXTRNL_RTNG_NM | C20: ENTITY | D20: EXTRNL_RTNG_NM | E20: Name of external rating agency | F20: Y | G20: N | H20: N | I20: N | J20: N | K20: Y | L20: =IFERROR(VLOOKUP($B20,'LISTA - Atual'!$B$1:$I$444,5,0),"Novo") -> Y | M20: =IF(L20="Novo","Novo Campo",IF(L20=F20,"Igual","Diferente")) -> Igual | N20: =IFERROR(VLOOKUP($B20,'LISTA - Atual'!$B$1:$I$444,6,0),"Novo") -> N | O20: =IF(N20="Novo","Novo Campo",IF(N20=G20,"Igual","Diferente")) -> Igual | P20: =IFERROR(VLOOKUP($B20,'LISTA - Atual'!$B$1:$I$444,7,0),"Novo") -> N | Q20: =IF(P20="Novo","Novo Campo",IF(P20=H20,"Igual","Diferente")) -> Igual | R20: n/a | S20: =IFERROR(VLOOKUP($B20,'LISTA - Atual'!$B$1:$I$444,8,0),"Novo") -> N | T20: =IF(S20="Novo","Novo Campo",IF(S20=J20,"Igual","Diferente")) -> Igual | U20: n/a | V20: N | W20: =IFERROR(VLOOKUP(B20,#REF!,11,0),"n/a") -> n/a | X20: =IFERROR(VLOOKUP(B20,#REF!,8,0),"n/a") -> n/a | Y20: =$F$2 -> ESTR | Z20: Sem alteração | AA20: =VLOOKUP(Table1[[#This Row],[CONCAT]],'Campos Resumo Prop2.0'!A:H,8,0) -> #N/A | AB20: VARCHAR2(255) | AC20: n.a. | AD20: =INDEX(Auxiliar!$D$5:$I$10,MATCH('LISTA - Setembro2024'!AD$3,Auxiliar!$B$5:$B$10,0),MATCH('LISTA - Setembro2024'!$AC20,Auxiliar!$D$4:$I$4,0)) -> 0 | AE20: =INDEX(Auxiliar!$D$5:$I$10,MATCH('LISTA - Setembro2024'!AE$3,Auxiliar!$B$5:$B$10,0),MATCH('LISTA - Setembro2024'!$AC20,Auxiliar!$D$4:$I$4,0)) -> 0 | AF20: =INDEX(Auxiliar!$D$5:$I$10,MATCH('LISTA - Setembro2024'!AF$3,Auxiliar!$B$5:$B$10,0),MATCH('LISTA - Setembro2024'!$AC20,Auxiliar!$D$4:$I$4,0)) -> 0 | AG20: =IF(OR(AB20="Code List",AB20="Y, N"),AC20,"n.a.") -> n.a. | AH20: =INDEX(Auxiliar!$D$5:$I$10,MATCH('LISTA - Setembro2024'!AH$3,Auxiliar!$B$5:$B$10,0),MATCH('LISTA - Setembro2024'!$AG20,Auxiliar!$D$4:$I$4,0)) -> 0 | AI20: =INDEX(Auxiliar!$D$5:$I$10,MATCH('LISTA - Setembro2024'!AI$3,Auxiliar!$B$5:$B$10,0),MATCH('LISTA - Setembro2024'!$AC20,Auxiliar!$D$4:$I$4,0)) -> 0 | AJ20: =INDEX(Auxiliar!$D$5:$I$10,MATCH('LISTA - Setembro2024'!AJ$3,Auxiliar!$B$5:$B$10,0),MATCH('LISTA - Setembro2024'!$AC20,Auxiliar!$D$4:$I$4,0)) -> 0 | AK20: =SUM(AF20,AH20:AJ20) -> 0 | AL20: Mudar N/A
A21: EN.018 | B21: =C21&"_"&D21 -> ENTITY_ACCNTNG_FRMWRK_SL | C21: ENTITY | D21: ACCNTNG_FRMWRK_SL | E21: Accounting standard counterparty | F21: Y | G21: N | H21: N | I21: N | J21: N | K21: Y | L21: =IFERROR(VLOOKUP($B21,'LISTA - Atual'!$B$1:$I$444,5,0),"Novo") -> Y | M21: =IF(L21="Novo","Novo Campo",IF(L21=F21,"Igual","Diferente")) -> Igual | N21: =IFERROR(VLOOKUP($B21,'LISTA - Atual'!$B$1:$I$444,6,0),"Novo") -> N | O21: =IF(N21="Novo","Novo Campo",IF(N21=G21,"Igual","Diferente")) -> Igual | P21: =IFERROR(VLOOKUP($B21,'LISTA - Atual'!$B$1:$I$444,7,0),"Novo") -> N | Q21: =IF(P21="Novo","Novo Campo",IF(P21=H21,"Igual","Diferente")) -> Igual | R21: n/a | S21: =IFERROR(VLOOKUP($B21,'LISTA - Atual'!$B$1:$I$444,8,0),"Novo") -> N | T21: =IF(S21="Novo","Novo Campo",IF(S21=J21,"Igual","Diferente")) -> Igual | U21: n/a | V21: N | W21: =IFERROR(VLOOKUP(B21,#REF!,11,0),"n/a") -> n/a | X21: =IFERROR(VLOOKUP(B21,#REF!,8,0),"n/a") -> n/a | Y21: =$F$2 -> ESTR | Z21: Sem alteração | AA21: =VLOOKUP(Table1[[#This Row],[CONCAT]],'Campos Resumo Prop2.0'!A:H,8,0) -> #N/A | AB21: Code List | AC21: n.a. | AD21: =INDEX(Auxiliar!$D$5:$I$10,MATCH('LISTA - Setembro2024'!AD$3,Auxiliar!$B$5:$B$10,0),MATCH('LISTA - Setembro2024'!$AC21,Auxiliar!$D$4:$I$4,0)) -> 0 | AE21: =INDEX(Auxiliar!$D$5:$I$10,MATCH('LISTA - Setembro2024'!AE$3,Auxiliar!$B$5:$B$10,0),MATCH('LISTA - Setembro2024'!$AC21,Auxiliar!$D$4:$I$4,0)) -> 0 | AF21: =INDEX(Auxiliar!$D$5:$I$10,MATCH('LISTA - Setembro2024'!AF$3,Auxiliar!$B$5:$B$10,0),MATCH('LISTA - Setembro2024'!$AC21,Auxiliar!$D$4:$I$4,0)) -> 0 | AG21: =IF(OR(AB21="Code List",AB21="Y, N"),AC21,"n.a.") -> n.a. | AH21: =INDEX(Auxiliar!$D$5:$I$10,MATCH('LISTA - Setembro2024'!AH$3,Auxiliar!$B$5:$B$10,0),MATCH('LISTA - Setembro2024'!$AG21,Auxiliar!$D$4:$I$4,0)) -> 0 | AI21: =INDEX(Auxiliar!$D$5:$I$10,MATCH('LISTA - Setembro2024'!AI$3,Auxiliar!$B$5:$B$10,0),MATCH('LISTA - Setembro2024'!$AC21,Auxiliar!$D$4:$I$4,0)) -> 0 | AJ21: =INDEX(Auxiliar!$D$5:$I$10,MATCH('LISTA - Setembro2024'!AJ$3,Auxiliar!$B$5:$B$10,0),MATCH('LISTA - Setembro2024'!$AC21,Auxiliar!$D$4:$I$4,0)) -> 0 | AK21: =SUM(AF21,AH21:AJ21) -> 0 | AL21: Dem. Fin
A22: EN.019 | B22: =C22&"_"&D22 -> ENTITY_CR_FLG | C22: ENTITY | D22: CR_FLG | E22: Cure flag for entity which was classified as non-performing in the last 1.5 years and is classified as performing at the reference date | F22: Y | G22: N | H22: N | I22: N | J22: N | K22: N | L22: =IFERROR(VLOOKUP($B22,'LISTA - Atual'!$B$1:$I$444,5,0),"Novo") -> Y | M22: =IF(L22="Novo","Novo Campo",IF(L22=F22,"Igual","Diferente")) -> Igual | N22: =IFERROR(VLOOKUP($B22,'LISTA - Atual'!$B$1:$I$444,6,0),"Novo") -> N | O22: =IF(N22="Novo","Novo Campo",IF(N22=G22,"Igual","Diferente")) -> Igual | P22: =IFERROR(VLOOKUP($B22,'LISTA - Atual'!$B$1:$I$444,7,0),"Novo") -> N | Q22: =IF(P22="Novo","Novo Campo",IF(P22=H22,"Igual","Diferente")) -> Igual | R22: n/a | S22: =IFERROR(VLOOKUP($B22,'LISTA - Atual'!$B$1:$I$444,8,0),"Novo") -> N | T22: =IF(S22="Novo","Novo Campo",IF(S22=J22,"Igual","Diferente")) -> Igual | U22: n/a | V22: N | W22: =IFERROR(VLOOKUP(B22,#REF!,11,0),"n/a") -> n/a | X22: =IFERROR(VLOOKUP(B22,#REF!,8,0),"n/a") -> n/a | Y22: =$F$2 -> ESTR | Z22: Sem alteração | AA22: =VLOOKUP(Table1[[#This Row],[CONCAT]],'Campos Resumo Prop2.0'!A:H,8,0) -> #N/A | AB22: Y, N | AC22: n.a. | AD22: =INDEX(Auxiliar!$D$5:$I$10,MATCH('LISTA - Setembro2024'!AD$3,Auxiliar!$B$5:$B$10,0),MATCH('LISTA - Setembro2024'!$AC22,Auxiliar!$D$4:$I$4,0)) -> 0 | AE22: =INDEX(Auxiliar!$D$5:$I$10,MATCH('LISTA - Setembro2024'!AE$3,Auxiliar!$B$5:$B$10,0),MATCH('LISTA - Setembro2024'!$AC22,Auxiliar!$D$4:$I$4,0)) -> 0 | AF22: =INDEX(Auxiliar!$D$5:$I$10,MATCH('LISTA - Setembro2024'!AF$3,Auxiliar!$B$5:$B$10,0),MATCH('LISTA - Setembro2024'!$AC22,Auxiliar!$D$4:$I$4,0)) -> 0 | AG22: =IF(OR(AB22="Code List",AB22="Y, N"),AC22,"n.a.") -> n.a. | AH22: =INDEX(Auxiliar!$D$5:$I$10,MATCH('LISTA - Setembro2024'!AH$3,Auxiliar!$B$5:$B$10,0),MATCH('LISTA - Setembro2024'!$AG22,Auxiliar!$D$4:$I$4,0)) -> 0 | AI22: =INDEX(Auxiliar!$D$5:$I$10,MATCH('LISTA - Setembro2024'!AI$3,Auxiliar!$B$5:$B$10,0),MATCH('LISTA - Setembro2024'!$AC22,Auxiliar!$D$4:$I$4,0)) -> 0 | AJ22: =INDEX(Auxiliar!$D$5:$I$10,MATCH('LISTA - Setembro2024'!AJ$3,Auxiliar!$B$5:$B$10,0),MATCH('LISTA - Setembro2024'!$AC22,Auxiliar!$D$4:$I$4,0)) -> 0 | AK22: =SUM(AF22,AH22:AJ22) -> 0
A23: EN.020 | B23: =C23&"_"&D23 -> ENTITY_DCSD | C23: ENTITY | D23: DCSD | E23: Entity deceased | F23: Y | G23: N | H23: N | I23: N | J23: N | K23: N | L23: =IFERROR(VLOOKUP($B23,'LISTA - Atual'!$B$1:$I$444,5,0),"Novo") -> Y | M23: =IF(L23="Novo","Novo Campo",IF(L23=F23,"Igual","Diferente")) -> Igual | N23: =IFERROR(VLOOKUP($B23,'LISTA - Atual'!$B$1:$I$444,6,0),"Novo") -> N | O23: =IF(N23="Novo","Novo Campo",IF(N23=G23,"Igual","Diferente")) -> Igual | P23: =IFERROR(VLOOKUP($B23,'LISTA - Atual'!$B$1:$I$444,7,0),"Novo") -> N | Q23: =IF(P23="Novo","Novo Campo",IF(P23=H23,"Igual","Diferente")) -> Igual | R23: n/a | S23: =IFERROR(VLOOKUP($B23,'LISTA - Atual'!$B$1:$I$444,8,0),"Novo") -> N | T23: =IF(S23="Novo","Novo Campo",IF(S23=J23,"Igual","Diferente")) -> Igual | U23: n/a | V23: N | W23: =IFERROR(VLOOKUP(B23,#REF!,11,0),"n/a") -> n/a | X23: =IFERROR(VLOOKUP(B23,#REF!,8,0),"n/a") -> n/a | Y23: =$F$2 -> ESTR | Z23: Sem alteração | AA23: =VLOOKUP(Table1[[#This Row],[CONCAT]],'Campos Resumo Prop2.0'!A:H,8,0) -> #N/A | AB23: Y, N | AC23: n.a. | AD23: =INDEX(Auxiliar!$D$5:$I$10,MATCH('LISTA - Setembro2024'!AD$3,Auxiliar!$B$5:$B$10,0),MATCH('LISTA - Setembro2024'!$AC23,Auxiliar!$D$4:$I$4,0)) -> 0 | AE23: =INDEX(Auxiliar!$D$5:$I$10,MATCH('LISTA - Setembro2024'!AE$3,Auxiliar!$B$5:$B$10,0),MATCH('LISTA - Setembro2024'!$AC23,Auxiliar!$D$4:$I$4,0)) -> 0 | AF23: =INDEX(Auxiliar!$D$5:$I$10,MATCH('LISTA - Setembro2024'!AF$3,Auxiliar!$B$5:$B$10,0),MATCH('LISTA - Setembro2024'!$AC23,Auxiliar!$D$4:$I$4,0)) -> 0 | AG23: =IF(OR(AB23="Code List",AB23="Y, N"),AC23,"n.a.") -> n.a. | AH23: =INDEX(Auxiliar!$D$5:$I$10,MATCH('LISTA - Setembro2024'!AH$3,Auxiliar!$B$5:$B$10,0),MATCH('LISTA - Setembro2024'!$AG23,Auxiliar!$D$4:$I$4,0)) -> 0 | AI23: =INDEX(Auxiliar!$D$5:$I$10,MATCH('LISTA - Setembro2024'!AI$3,Auxiliar!$B$5:$B$10,0),MATCH('LISTA - Setembro2024'!$AC23,Auxiliar!$D$4:$I$4,0)) -> 0 | AJ23: =INDEX(Auxiliar!$D$5:$I$10,MATCH('LISTA - Setembro2024'!AJ$3,Auxiliar!$B$5:$B$10,0),MATCH('LISTA - Setembro2024'!$AC23,Auxiliar!$D$4:$I$4,0)) -> 0 | AK23: =SUM(AF23,AH23:AJ23) -> 0
A24: EN.021 | B24: =C24&"_"&D24 -> ENTITY_DFLT_STTS | C24: ENTITY | D24: DFLT_STTS | E24: Default status of the entity | F24: Y | G24: N | H24: N | I24: N | J24: N | K24: Y | L24: =IFERROR(VLOOKUP($B24,'LISTA - Atual'!$B$1:$I$444,5,0),"Novo") -> Y | M24: =IF(L24="Novo","Novo Campo",IF(L24=F24,"Igual","Diferente")) -> Igual | N24: =IFERROR(VLOOKUP($B24,'LISTA - Atual'!$B$1:$I$444,6,0),"Novo") -> N | O24: =IF(N24="Novo","Novo Campo",IF(N24=G24,"Igual","Diferente")) -> Igual | P24: =IFERROR(VLOOKUP($B24,'LISTA - Atual'!$B$1:$I$444,7,0),"Novo") -> N | Q24: =IF(P24="Novo","Novo Campo",IF(P24=H24,"Igual","Diferente")) -> Igual | R24: n/a | S24: =IFERROR(VLOOKUP($B24,'LISTA - Atual'!$B$1:$I$444,8,0),"Novo") -> N | T24: =IF(S24="Novo","Novo Campo",IF(S24=J24,"Igual","Diferente")) -> Igual | U24: n/a | V24: N | W24: =IFERROR(VLOOKUP(B24,#REF!,11,0),"n/a") -> n/a | X24: =IFERROR(VLOOKUP(B24,#REF!,8,0),"n/a") -> n/a | Y24: =$F$2 -> ESTR | Z24: Sem alteração | AA24: =VLOOKUP(Table1[[#This Row],[CONCAT]],'Campos Resumo Prop2.0'!A:H,8,0) -> #N/A | AB24: Code List | AC24: n.a. | AD24: =INDEX(Auxiliar!$D$5:$I$10,MATCH('LISTA - Setembro2024'!AD$3,Auxiliar!$B$5:$B$10,0),MATCH('LISTA - Setembro2024'!$AC24,Auxiliar!$D$4:$I$4,0)) -> 0 | AE24: =INDEX(Auxiliar!$D$5:$I$10,MATCH('LISTA - Setembro2024'!AE$3,Auxiliar!$B$5:$B$10,0),MATCH('LISTA - Setembro2024'!$AC24,Auxiliar!$D$4:$I$4,0)) -> 0 | AF24: =INDEX(Auxiliar!$D$5:$I$10,MATCH('LISTA - Setembro2024'!AF$3,Auxiliar!$B$5:$B$10,0),MATCH('LISTA - Setembro2024'!$AC24,Auxiliar!$D$4:$I$4,0)) -> 0 | AG24: =IF(OR(AB24="Code List",AB24="Y, N"),AC24,"n.a.") -> n.a. | AH24: =INDEX(Auxiliar!$D$5:$I$10,MATCH('LISTA - Setembro2024'!AH$3,Auxiliar!$B$5:$B$10,0),MATCH('LISTA - Setembro2024'!$AG24,Auxiliar!$D$4:$I$4,0)) -> 0 | AI24: =INDEX(Auxiliar!$D$5:$I$10,MATCH('LISTA - Setembro2024'!AI$3,Auxiliar!$B$5:$B$10,0),MATCH('LISTA - Setembro2024'!$AC24,Auxiliar!$D$4:$I$4,0)) -> 0 | AJ24: =INDEX(Auxiliar!$D$5:$I$10,MATCH('LISTA - Setembro2024'!AJ$3,Auxiliar!$B$5:$B$10,0),MATCH('LISTA - Setembro2024'!$AC24,Auxiliar!$D$4:$I$4,0)) -> 0 | AK24: =SUM(AF24,AH24:AJ24) -> 0 | AL24: Dependente de decisão
A25: EN.022 | B25: =C25&"_"&D25 -> ENTITY_DT_EXTRNL_RTNG | C25: ENTITY | D25: DT_EXTRNL_RTNG | E25: Date of external rating | F25: Y | G25: N | H25: N | I25: N | J25: N | K25: Y | L25: =IFERROR(VLOOKUP($B25,'LISTA - Atual'!$B$1:$I$444,5,0),"Novo") -> Y | M25: =IF(L25="Novo","Novo Campo",IF(L25=F25,"Igual","Diferente")) -> Igual | N25: =IFERROR(VLOOKUP($B25,'LISTA - Atual'!$B$1:$I$444,6,0),"Novo") -> N | O25: =IF(N25="Novo","Novo Campo",IF(N25=G25,"Igual","Diferente")) -> Igual | P25: =IFERROR(VLOOKUP($B25,'LISTA - Atual'!$B$1:$I$444,7,0),"Novo") -> N | Q25: =IF(P25="Novo","Novo Campo",IF(P25=H25,"Igual","Diferente")) -> Igual | R25: n/a | S25: =IFERROR(VLOOKUP($B25,'LISTA - Atual'!$B$1:$I$444,8,0),"Novo") -> N | T25: =IF(S25="Novo","Novo Campo",IF(S25=J25,"Igual","Diferente")) -> Igual | U25: n/a | V25: N | W25: =IFERROR(VLOOKUP(B25,#REF!,11,0),"n/a") -> n/a | X25: =IFERROR(VLOOKUP(B25,#REF!,8,0),"n/a") -> n/a | Y25: =$F$2 -> ESTR | Z25: Sem alteração | AA25: =VLOOKUP(Table1[[#This Row],[CONCAT]],'Campos Resumo Prop2.0'!A:H,8,0) -> #N/A | AB25: DATE | AC25: n.a. | AD25: =INDEX(Auxiliar!$D$5:$I$10,MATCH('LISTA - Setembro2024'!AD$3,Auxiliar!$B$5:$B$10,0),MATCH('LISTA - Setembro2024'!$AC25,Auxiliar!$D$4:$I$4,0)) -> 0 | AE25: =INDEX(Auxiliar!$D$5:$I$10,MATCH('LISTA - Setembro2024'!AE$3,Auxiliar!$B$5:$B$10,0),MATCH('LISTA - Setembro2024'!$AC25,Auxiliar!$D$4:$I$4,0)) -> 0 | AF25: =INDEX(Auxiliar!$D$5:$I$10,MATCH('LISTA - Setembro2024'!AF$3,Auxiliar!$B$5:$B$10,0),MATCH('LISTA - Setembro2024'!$AC25,Auxiliar!$D$4:$I$4,0)) -> 0 | AG25: =IF(OR(AB25="Code List",AB25="Y, N"),AC25,"n.a.") -> n.a. | AH25: =INDEX(Auxiliar!$D$5:$I$10,MATCH('LISTA - Setembro2024'!AH$3,Auxiliar!$B$5:$B$10,0),MATCH('LISTA - Setembro2024'!$AG25,Auxiliar!$D$4:$I$4,0)) -> 0 | AI25: =INDEX(Auxiliar!$D$5:$I$10,MATCH('LISTA - Setembro2024'!AI$3,Auxiliar!$B$5:$B$10,0),MATCH('LISTA - Setembro2024'!$AC25,Auxiliar!$D$4:$I$4,0)) -> 0 | AJ25: =INDEX(Auxiliar!$D$5:$I$10,MATCH('LISTA - Setembro2024'!AJ$3,Auxiliar!$B$5:$B$10,0),MATCH('LISTA - Setembro2024'!$AC25,Auxiliar!$D$4:$I$4,0)) -> 0 | AK25: =SUM(AF25,AH25:AJ25) -> 0 | AL25: Mudar N/A
A26: EN.023 | B26: =C26&"_"&D26 -> ENTITY_DT_INTRNL_RTNG | C26: ENTITY | D26: DT_INTRNL_RTNG | E26: Date of internal rating | F26: Y | G26: N | H26: N | I26: N | J26: N | K26: Y | L26: =IFERROR(VLOOKUP($B26,'LISTA - Atual'!$B$1:$I$444,5,0),"Novo") -> Y | M26: =IF(L26="Novo","Novo Campo",IF(L26=F26,"Igual","Diferente")) -> Igual | N26: =IFERROR(VLOOKUP($B26,'LISTA - Atual'!$B$1:$I$444,6,0),"Novo") -> N | O26: =IF(N26="Novo","Novo Campo",IF(N26=G26,"Igual","Diferente")) -> Igual | P26: =IFERROR(VLOOKUP($B26,'LISTA - Atual'!$B$1:$I$444,7,0),"Novo") -> N | Q26: =IF(P26="Novo","Novo Campo",IF(P26=H26,"Igual","Diferente")) -> Igual | R26: n/a | S26: =IFERROR(VLOOKUP($B26,'LISTA - Atual'!$B$1:$I$444,8,0),"Novo") -> N | T26: =IF(S26="Novo","Novo Campo",IF(S26=J26,"Igual","Diferente")) -> Igual | U26: n/a | V26: N | W26: =IFERROR(VLOOKUP(B26,#REF!,11,0),"n/a") -> n/a | X26: =IFERROR(VLOOKUP(B26,#REF!,8,0),"n/a") -> n/a | Y26: =$F$2 -> ESTR | Z26: Sem alteração | AA26: =VLOOKUP(Table1[[#This Row],[CONCAT]],'Campos Resumo Prop2.0'!A:H,8,0) -> #N/A | AB26: DATE | AC26: n.a. | AD26: 1 | AE26: =INDEX(Auxiliar!$D$5:$I$10,MATCH('LISTA - Setembro2024'!AE$3,Auxiliar!$B$5:$B$10,0),MATCH('LISTA - Setembro2024'!$AC26,Auxiliar!$D$4:$I$4,0)) -> 0 | AF26: =INDEX(Auxiliar!$D$5:$I$10,MATCH('LISTA - Setembro2024'!AF$3,Auxiliar!$B$5:$B$10,0),MATCH('LISTA - Setembro2024'!$AC26,Auxiliar!$D$4:$I$4,0)) -> 0 | AG26: =IF(OR(AB26="Code List",AB26="Y, N"),AC26,"n.a.") -> n.a. | AH26: =INDEX(Auxiliar!$D$5:$I$10,MATCH('LISTA - Setembro2024'!AH$3,Auxiliar!$B$5:$B$10,0),MATCH('LISTA - Setembro2024'!$AG26,Auxiliar!$D$4:$I$4,0)) -> 0 | AI26: =INDEX(Auxiliar!$D$5:$I$10,MATCH('LISTA - Setembro2024'!AI$3,Auxiliar!$B$5:$B$10,0),MATCH('LISTA - Setembro2024'!$AC26,Auxiliar!$D$4:$I$4,0)) -> 0 | AJ26: =INDEX(Auxiliar!$D$5:$I$10,MATCH('LISTA - Setembro2024'!AJ$3,Auxiliar!$B$5:$B$10,0),MATCH('LISTA - Setembro2024'!$AC26,Auxiliar!$D$4:$I$4,0)) -> 0 | AK26: =SUM(AF26,AH26:AJ26) -> 0 | AL26: internal ratings
A27: EN.024 | B27: =C27&"_"&D27 -> ENTITY_ECNMC_ACTVTY | C27: ENTITY | D27: ECNMC_ACTVTY | E27: Economic activity counterparty | F27: Y | G27: N | H27: Y | I27: N | J27: Y | K27: Y | L27: =IFERROR(VLOOKUP($B27,'LISTA - Atual'!$B$1:$I$444,5,0),"Novo") -> Y | M27: =IF(L27="Novo","Novo Campo",IF(L27=F27,"Igual","Diferente")) -> Igual | N27: =IFERROR(VLOOKUP($B27,'LISTA - Atual'!$B$1:$I$444,6,0),"Novo") -> N | O27: =IF(N27="Novo","Novo Campo",IF(N27=G27,"Igual","Diferente")) -> Igual | P27: =IFERROR(VLOOKUP($B27,'LISTA - Atual'!$B$1:$I$444,7,0),"Novo") -> Y | Q27: =IF(P27="Novo","Novo Campo",IF(P27=H27,"Igual","Diferente")) -> Igual | R27: n/a | S27: =IFERROR(VLOOKUP($B27,'LISTA - Atual'!$B$1:$I$444,8,0),"Novo") -> Y | T27: =IF(S27="Novo","Novo Campo",IF(S27=J27,"Igual","Diferente")) -> Igual | U27: n/a | V27: N | W27: =IFERROR(VLOOKUP(B27,#REF!,11,0),"n/a") -> n/a | X27: =IFERROR(VLOOKUP(B27,#REF!,8,0),"n/a") -> n/a | Y27: =$F$2&$Y$1&$H$2 -> ESTR & PILAR3 | Z27: Sem alteração | AA27: =VLOOKUP(Table1[[#This Row],[CONCAT]],'Campos Resumo Prop2.0'!A:H,8,0) -> #N/A | AB27: Code List | AC27: n.a. | AD27: =INDEX(Auxiliar!$D$5:$I$10,MATCH('LISTA - Setembro2024'!AD$3,Auxiliar!$B$5:$B$10,0),MATCH('LISTA - Setembro2024'!$AC27,Auxiliar!$D$4:$I$4,0)) -> 0 | AE27: =INDEX(Auxiliar!$D$5:$I$10,MATCH('LISTA - Setembro2024'!AE$3,Auxiliar!$B$5:$B$10,0),MATCH('LISTA - Setembro2024'!$AC27,Auxiliar!$D$4:$I$4,0)) -> 0 | AF27: =INDEX(Auxiliar!$D$5:$I$10,MATCH('LISTA - Setembro2024'!AF$3,Auxiliar!$B$5:$B$10,0),MATCH('LISTA - Setembro2024'!$AC27,Auxiliar!$D$4:$I$4,0)) -> 0 | AG27: =IF(OR(AB27="Code List",AB27="Y, N"),AC27,"n.a.") -> n.a. | AH27: =INDEX(Auxiliar!$D$5:$I$10,MATCH('LISTA - Setembro2024'!AH$3,Auxiliar!$B$5:$B$10,0),MATCH('LISTA - Setembro2024'!$AG27,Auxiliar!$D$4:$I$4,0)) -> 0 | AI27: =INDEX(Auxiliar!$D$5:$I$10,MATCH('LISTA - Setembro2024'!AI$3,Auxiliar!$B$5:$B$10,0),MATCH('LISTA - Setembro2024'!$AC27,Auxiliar!$D$4:$I$4,0)) -> 0 | AJ27: =INDEX(Auxiliar!$D$5:$I$10,MATCH('LISTA - Setembro2024'!AJ$3,Auxiliar!$B$5:$B$10,0),MATCH('LISTA - Setembro2024'!$AC27,Auxiliar!$D$4:$I$4,0)) -> 0 | AK27: =SUM(AF27,AH27:AJ27) -> 0
A28: EN.025 | B28: =C28&"_"&D28 -> ENTITY_EMPLYMNT_STTS_INTRNL | C28: ENTITY | D28: EMPLYMNT_STTS_INTRNL | E28: Employment status according to bank-internal classification | F28: Y | G28: N | H28: N | I28: N | J28: N | K28: N | L28: =IFERROR(VLOOKUP($B28,'LISTA - Atual'!$B$1:$I$444,5,0),"Novo") -> Y | M28: =IF(L28="Novo","Novo Campo",IF(L28=F28,"Igual","Diferente")) -> Igual | N28: =IFERROR(VLOOKUP($B28,'LISTA - Atual'!$B$1:$I$444,6,0),"Novo") -> N | O28: =IF(N28="Novo","Novo Campo",IF(N28=G28,"Igual","Diferente")) -> Igual | P28: =IFERROR(VLOOKUP($B28,'LISTA - Atual'!$B$1:$I$444,7,0),"Novo") -> N | Q28: =IF(P28="Novo","Novo Campo",IF(P28=H28,"Igual","Diferente")) -> Igual | R28: n/a | S28: =IFERROR(VLOOKUP($B28,'LISTA - Atual'!$B$1:$I$444,8,0),"Novo") -> N | T28: =IF(S28="Novo","Novo Campo",IF(S28=J28,"Igual","Diferente")) -> Igual | U28: n/a | V28: N | W28: =IFERROR(VLOOKUP(B28,#REF!,11,0),"n/a") -> n/a | X28: =IFERROR(VLOOKUP(B28,#REF!,8,0),"n/a") -> n/a | Y28: =$F$2 -> ESTR | Z28: Sem alteração | AA28: =VLOOKUP(Table1[[#This Row],[CONCAT]],'Campos Resumo Prop2.0'!A:H,8,0) -> #N/A | AB28: VARCHAR2(255) | AC28: n.a. | AD28: =INDEX(Auxiliar!$D$5:$I$10,MATCH('LISTA - Setembro2024'!AD$3,Auxiliar!$B$5:$B$10,0),MATCH('LISTA - Setembro2024'!$AC28,Auxiliar!$D$4:$I$4,0)) -> 0 | AE28: =INDEX(Auxiliar!$D$5:$I$10,MATCH('LISTA - Setembro2024'!AE$3,Auxiliar!$B$5:$B$10,0),MATCH('LISTA - Setembro2024'!$AC28,Auxiliar!$D$4:$I$4,0)) -> 0 | AF28: =INDEX(Auxiliar!$D$5:$I$10,MATCH('LISTA - Setembro2024'!AF$3,Auxiliar!$B$5:$B$10,0),MATCH('LISTA - Setembro2024'!$AC28,Auxiliar!$D$4:$I$4,0)) -> 0 | AG28: =IF(OR(AB28="Code List",AB28="Y, N"),AC28,"n.a.") -> n.a. | AH28: =INDEX(Auxiliar!$D$5:$I$10,MATCH('LISTA - Setembro2024'!AH$3,Auxiliar!$B$5:$B$10,0),MATCH('LISTA - Setembro2024'!$AG28,Auxiliar!$D$4:$I$4,0)) -> 0 | AI28: =INDEX(Auxiliar!$D$5:$I$10,MATCH('LISTA - Setembro2024'!AI$3,Auxiliar!$B$5:$B$10,0),MATCH('LISTA - Setembro2024'!$AC28,Auxiliar!$D$4:$I$4,0)) -> 0 | AJ28: =INDEX(Auxiliar!$D$5:$I$10,MATCH('LISTA - Setembro2024'!AJ$3,Auxiliar!$B$5:$B$10,0),MATCH('LISTA - Setembro2024'!$AC28,Auxiliar!$D$4:$I$4,0)) -> 0 | AK28: =SUM(AF28,AH28:AJ28) -> 0
A29: EN.026 | B29: =C29&"_"&D29 -> ENTITY_EMPLYMNT_STTS | C29: ENTITY | D29: EMPLYMNT_STTS | E29: Employment status (Code List) | F29: Y | G29: N | H29: N | I29: N | J29: N | K29: N | L29: =IFERROR(VLOOKUP($B29,'LISTA - Atual'!$B$1:$I$444,5,0),"Novo") -> Y | M29: =IF(L29="Novo","Novo Campo",IF(L29=F29,"Igual","Diferente")) -> Igual | N29: =IFERROR(VLOOKUP($B29,'LISTA - Atual'!$B$1:$I$444,6,0),"Novo") -> N | O29: =IF(N29="Novo","Novo Campo",IF(N29=G29,"Igual","Diferente")) -> Igual | P29: =IFERROR(VLOOKUP($B29,'LISTA - Atual'!$B$1:$I$444,7,0),"Novo") -> N | Q29: =IF(P29="Novo","Novo Campo",IF(P29=H29,"Igual","Diferente")) -> Igual | R29: n/a | S29: =IFERROR(VLOOKUP($B29,'LISTA - Atual'!$B$1:$I$444,8,0),"Novo") -> N | T29: =IF(S29="Novo","Novo Campo",IF(S29=J29,"Igual","Diferente")) -> Igual | U29: n/a | V29: N | W29: =IFERROR(VLOOKUP(B29,#REF!,11,0),"n/a") -> n/a | X29: =IFERROR(VLOOKUP(B29,#REF!,8,0),"n/a") -> n/a | Y29: =$F$2 -> ESTR | Z29: Sem alteração | AA29: =VLOOKUP(Table1[[#This Row],[CONCAT]],'Campos Resumo Prop2.0'!A:H,8,0) -> #N/A | AB29: Code List | AC29: n.a. | AD29: =INDEX(Auxiliar!$D$5:$I$10,MATCH('LISTA - Setembro2024'!AD$3,Auxiliar!$B$5:$B$10,0),MATCH('LISTA - Setembro2024'!$AC29,Auxiliar!$D$4:$I$4,0)) -> 0 | AE29: =INDEX(Auxiliar!$D$5:$I$10,MATCH('LISTA - Setembro2024'!AE$3,Auxiliar!$B$5:$B$10,0),MATCH('LISTA - Setembro2024'!$AC29,Auxiliar!$D$4:$I$4,0)) -> 0 | AF29: =INDEX(Auxiliar!$D$5:$I$10,MATCH('LISTA - Setembro2024'!AF$3,Auxiliar!$B$5:$B$10,0),MATCH('LISTA - Setembro2024'!$AC29,Auxiliar!$D$4:$I$4,0)) -> 0 | AG29: =IF(OR(AB29="Code List",AB29="Y, N"),AC29,"n.a.") -> n.a. | AH29: =INDEX(Auxiliar!$D$5:$I$10,MATCH('LISTA - Setembro2024'!AH$3,Auxiliar!$B$5:$B$10,0),MATCH('LISTA - Setembro2024'!$AG29,Auxiliar!$D$4:$I$4,0)) -> 0 | AI29: =INDEX(Auxiliar!$D$5:$I$10,MATCH('LISTA - Setembro2024'!AI$3,Auxiliar!$B$5:$B$10,0),MATCH('LISTA - Setembro2024'!$AC29,Auxiliar!$D$4:$I$4,0)) -> 0 | AJ29: =INDEX(Auxiliar!$D$5:$I$10,MATCH('LISTA - Setembro2024'!AJ$3,Auxiliar!$B$5:$B$10,0),MATCH('LISTA - Setembro2024'!$AC29,Auxiliar!$D$4:$I$4,0)) -> 0 | AK29: =SUM(AF29,AH29:AJ29) -> 0
A30: EN.027 | B30: =C30&"_"&D30 -> ENTITY_ENTRPRS_SZ_LE | C30: ENTITY | D30: ENTRPRS_SZ_LE | E30: Enterprise size Counterparty (LE) | F30: Y | G30: N | H30: N | I30: N | J30: N | K30: N | L30: =IFERROR(VLOOKUP($B30,'LISTA - Atual'!$B$1:$I$444,5,0),"Novo") -> Y | M30: =IF(L30="Novo","Novo Campo",IF(L30=F30,"Igual","Diferente")) -> Igual | N30: =IFERROR(VLOOKUP($B30,'LISTA - Atual'!$B$1:$I$444,6,0),"Novo") -> N | O30: =IF(N30="Novo","Novo Campo",IF(N30=G30,"Igual","Diferente")) -> Igual | P30: =IFERROR(VLOOKUP($B30,'LISTA - Atual'!$B$1:$I$444,7,0),"Novo") -> N | Q30: =IF(P30="Novo","Novo Campo",IF(P30=H30,"Igual","Diferente")) -> Igual | R30: n/a | S30: =IFERROR(VLOOKUP($B30,'LISTA - Atual'!$B$1:$I$444,8,0),"Novo") -> N | T30: =IF(S30="Novo","Novo Campo",IF(S30=J30,"Igual","Diferente")) -> Igual | U30: n/a | V30: N | W30: =IFERROR(VLOOKUP(B30,#REF!,11,0),"n/a") -> n/a | X30: =IFERROR(VLOOKUP(B30,#REF!,8,0),"n/a") -> n/a | Y30: =$F$2 -> ESTR | Z30: Sem alteração | AA30: =VLOOKUP(Table1[[#This Row],[CONCAT]],'Campos Resumo Prop2.0'!A:H,8,0) -> #N/A | AB30: Code List | AC30: n.a. | AD30: =INDEX(Auxiliar!$D$5:$I$10,MATCH('LISTA - Setembro2024'!AD$3,Auxiliar!$B$5:$B$10,0),MATCH('LISTA - Setembro2024'!$AC30,Auxiliar!$D$4:$I$4,0)) -> 0 | AE30: =INDEX(Auxiliar!$D$5:$I$10,MATCH('LISTA - Setembro2024'!AE$3,Auxiliar!$B$5:$B$10,0),MATCH('LISTA - Setembro2024'!$AC30,Auxiliar!$D$4:$I$4,0)) -> 0 | AF30: =INDEX(Auxiliar!$D$5:$I$10,MATCH('LISTA - Setembro2024'!AF$3,Auxiliar!$B$5:$B$10,0),MATCH('LISTA - Setembro2024'!$AC30,Auxiliar!$D$4:$I$4,0)) -> 0 | AG30: =IF(OR(AB30="Code List",AB30="Y, N"),AC30,"n.a.") -> n.a. | AH30: =INDEX(Auxiliar!$D$5:$I$10,MATCH('LISTA - Setembro2024'!AH$3,Auxiliar!$B$5:$B$10,0),MATCH('LISTA - Setembro2024'!$AG30,Auxiliar!$D$4:$I$4,0)) -> 0 | AI30: =INDEX(Auxiliar!$D$5:$I$10,MATCH('LISTA - Setembro2024'!AI$3,Auxiliar!$B$5:$B$10,0),MATCH('LISTA - Setembro2024'!$AC30,Auxiliar!$D$4:$I$4,0)) -> 0 | AJ30: =INDEX(Auxiliar!$D$5:$I$10,MATCH('LISTA - Setembro2024'!AJ$3,Auxiliar!$B$5:$B$10,0),MATCH('LISTA - Setembro2024'!$AC30,Auxiliar!$D$4:$I$4,0)) -> 0 | AK30: =SUM(AF30,AH30:AJ30) -> 0
A31: EN.028 | B31: =C31&"_"&D31 -> ENTITY_EXTRNL_RTNG | C31: ENTITY | D31: EXTRNL_RTNG | E31: External rating | F31: Y | G31: N | H31: N | I31: N | J31: N | K31: Y | L31: =IFERROR(VLOOKUP($B31,'LISTA - Atual'!$B$1:$I$444,5,0),"Novo") -> Y | M31: =IF(L31="Novo","Novo Campo",IF(L31=F31,"Igual","Diferente")) -> Igual | N31: =IFERROR(VLOOKUP($B31,'LISTA - Atual'!$B$1:$I$444,6,0),"Novo") -> N | O31: =IF(N31="Novo","Novo Campo",IF(N31=G31,"Igual","Diferente")) -> Igual | P31: =IFERROR(VLOOKUP($B31,'LISTA - Atual'!$B$1:$I$444,7,0),"Novo") -> N | Q31: =IF(P31="Novo","Novo Campo",IF(P31=H31,"Igual","Diferente")) -> Igual | R31: n/a | S31: =IFERROR(VLOOKUP($B31,'LISTA - Atual'!$B$1:$I$444,8,0),"Novo") -> N | T31: =IF(S31="Novo","Novo Campo",IF(S31=J31,"Igual","Diferente")) -> Igual | U31: n/a | V31: N | W31: =IFERROR(VLOOKUP(B31,#REF!,11,0),"n/a") -> n/a | X31: =IFERROR(VLOOKUP(B31,#REF!,8,0),"n/a") -> n/a | Y31: =$F$2 -> ESTR | Z31: Sem alteração | AA31: =VLOOKUP(Table1[[#This Row],[CONCAT]],'Campos Resumo Prop2.0'!A:H,8,0) -> #N/A | AB31: Code List | AC31: n.a. | AD31: =INDEX(Auxiliar!$D$5:$I$10,MATCH('LISTA - Setembro2024'!AD$3,Auxiliar!$B$5:$B$10,0),MATCH('LISTA - Setembro2024'!$AC31,Auxiliar!$D$4:$I$4,0)) -> 0 | AE31: =INDEX(Auxiliar!$D$5:$I$10,MATCH('LISTA - Setembro2024'!AE$3,Auxiliar!$B$5:$B$10,0),MATCH('LISTA - Setembro2024'!$AC31,Auxiliar!$D$4:$I$4,0)) -> 0 | AF31: =INDEX(Auxiliar!$D$5:$I$10,MATCH('LISTA - Setembro2024'!AF$3,Auxiliar!$B$5:$B$10,0),MATCH('LISTA - Setembro2024'!$AC31,Auxiliar!$D$4:$I$4,0)) -> 0 | AG31: =IF(OR(AB31="Code List",AB31="Y, N"),AC31,"n.a.") -> n.a. | AH31: =INDEX(Auxiliar!$D$5:$I$10,MATCH('LISTA - Setembro2024'!AH$3,Auxiliar!$B$5:$B$10,0),MATCH('LISTA - Setembro2024'!$AG31,Auxiliar!$D$4:$I$4,0)) -> 0 | AI31: =INDEX(Auxiliar!$D$5:$I$10,MATCH('LISTA - Setembro2024'!AI$3,Auxiliar!$B$5:$B$10,0),MATCH('LISTA - Setembro2024'!$AC31,Auxiliar!$D$4:$I$4,0)) -> 0 | AJ31: =INDEX(Auxiliar!$D$5:$I$10,MATCH('LISTA - Setembro2024'!AJ$3,Auxiliar!$B$5:$B$10,0),MATCH('LISTA - Setembro2024'!$AC31,Auxiliar!$D$4:$I$4,0)) -> 0 | AK31: =SUM(AF31,AH31:AJ31) -> 0 | AL31: Mudar N/A
A32: EN.029 | B32: =C32&"_"&D32 -> ENTITY_EXTRNL_RTNG_PRVS | C32: ENTITY | D32: EXTRNL_RTNG_PRVS | E32: External rating T-1 | F32: Y | G32: N | H32: N | I32: N | J32: N | K32: Y | L32: =IFERROR(VLOOKUP($B32,'LISTA - Atual'!$B$1:$I$444,5,0),"Novo") -> Y | M32: =IF(L32="Novo","Novo Campo",IF(L32=F32,"Igual","Diferente")) -> Igual | N32: =IFERROR(VLOOKUP($B32,'LISTA - Atual'!$B$1:$I$444,6,0),"Novo") -> N | O32: =IF(N32="Novo","Novo Campo",IF(N32=G32,"Igual","Diferente")) -> Igual | P32: =IFERROR(VLOOKUP($B32,'LISTA - Atual'!$B$1:$I$444,7,0),"Novo") -> N | Q32: =IF(P32="Novo","Novo Campo",IF(P32=H32,"Igual","Diferente")) -> Igual | R32: n/a | S32: =IFERROR(VLOOKUP($B32,'LISTA - Atual'!$B$1:$I$444,8,0),"Novo") -> N | T32: =IF(S32="Novo","Novo Campo",IF(S32=J32,"Igual","Diferente")) -> Igual | U32: n/a | V32: N | W32: =IFERROR(VLOOKUP(B32,#REF!,11,0),"n/a") -> n/a | X32: =IFERROR(VLOOKUP(B32,#REF!,8,0),"n/a") -> n/a | Y32: =$F$2 -> ESTR | Z32: Sem alteração | AA32: =VLOOKUP(Table1[[#This Row],[CONCAT]],'Campos Resumo Prop2.0'!A:H,8,0) -> #N/A | AB32: Code List | AC32: n.a. | AD32: =INDEX(Auxiliar!$D$5:$I$10,MATCH('LISTA - Setembro2024'!AD$3,Auxiliar!$B$5:$B$10,0),MATCH('LISTA - Setembro2024'!$AC32,Auxiliar!$D$4:$I$4,0)) -> 0 | AE32: =INDEX(Auxiliar!$D$5:$I$10,MATCH('LISTA - Setembro2024'!AE$3,Auxiliar!$B$5:$B$10,0),MATCH('LISTA - Setembro2024'!$AC32,Auxiliar!$D$4:$I$4,0)) -> 0 | AF32: =INDEX(Auxiliar!$D$5:$I$10,MATCH('LISTA - Setembro2024'!AF$3,Auxiliar!$B$5:$B$10,0),MATCH('LISTA - Setembro2024'!$AC32,Auxiliar!$D$4:$I$4,0)) -> 0 | AG32: =IF(OR(AB32="Code List",AB32="Y, N"),AC32,"n.a.") -> n.a. | AH32: =INDEX(Auxiliar!$D$5:$I$10,MATCH('LISTA - Setembro2024'!AH$3,Auxiliar!$B$5:$B$10,0),MATCH('LISTA - Setembro2024'!$AG32,Auxiliar!$D$4:$I$4,0)) -> 0 | AI32: =INDEX(Auxiliar!$D$5:$I$10,MATCH('LISTA - Setembro2024'!AI$3,Auxiliar!$B$5:$B$10,0),MATCH('LISTA - Setembro2024'!$AC32,Auxiliar!$D$4:$I$4,0)) -> 0 | AJ32: =INDEX(Auxiliar!$D$5:$I$10,MATCH('LISTA - Setembro2024'!AJ$3,Auxiliar!$B$5:$B$10,0),MATCH('LISTA - Setembro2024'!$AC32,Auxiliar!$D$4:$I$4,0)) -> 0 | AK32: =SUM(AF32,AH32:AJ32) -> 0 | AL32: Mudar N/A
A33: EN.030 | B33: =C33&"_"&D33 -> ENTITY_FLG_BNKRPTCY_IN_GRP | C33: ENTITY | D33: FLG_BNKRPTCY_IN_GRP | E33: Any legal entity within the group of connected clients of the debtor (incl. subsidiaries of the debtor) has filed bankruptcy application | F33: Y | G33: N | H33: N | I33: N | J33: N | K33: N | L33: =IFERROR(VLOOKUP($B33,'LISTA - Atual'!$B$1:$I$444,5,0),"Novo") -> Y | M33: =IF(L33="Novo","Novo Campo",IF(L33=F33,"Igual","Diferente")) -> Igual | N33: =IFERROR(VLOOKUP($B33,'LISTA - Atual'!$B$1:$I$444,6,0),"Novo") -> N | O33: =IF(N33="Novo","Novo Campo",IF(N33=G33,"Igual","Diferente")) -> Igual | P33: =IFERROR(VLOOKUP($B33,'LISTA - Atual'!$B$1:$I$444,7,0),"Novo") -> N | Q33: =IF(P33="Novo","Novo Campo",IF(P33=H33,"Igual","Diferente")) -> Igual | R33: n/a | S33: =IFERROR(VLOOKUP($B33,'LISTA - Atual'!$B$1:$I$444,8,0),"Novo") -> N | T33: =IF(S33="Novo","Novo Campo",IF(S33=J33,"Igual","Diferente")) -> Igual | U33: n/a | V33: N | W33: =IFERROR(VLOOKUP(B33,#REF!,11,0),"n/a") -> n/a | X33: =IFERROR(VLOOKUP(B33,#REF!,8,0),"n/a") -> n/a | Y33: =$F$2 -> ESTR | Z33: Sem alteração | AA33: =VLOOKUP(Table1[[#This Row],[CONCAT]],'Campos Resumo Prop2.0'!A:H,8,0) -> #N/A | AB33: Y, N | AC33: n.a. | AD33: =INDEX(Auxiliar!$D$5:$I$10,MATCH('LISTA - Setembro2024'!AD$3,Auxiliar!$B$5:$B$10,0),MATCH('LISTA - Setembro2024'!$AC33,Auxiliar!$D$4:$I$4,0)) -> 0 | AE33: =INDEX(Auxiliar!$D$5:$I$10,MATCH('LISTA - Setembro2024'!AE$3,Auxiliar!$B$5:$B$10,0),MATCH('LISTA - Setembro2024'!$AC33,Auxiliar!$D$4:$I$4,0)) -> 0 | AF33: =INDEX(Auxiliar!$D$5:$I$10,MATCH('LISTA - Setembro2024'!AF$3,Auxiliar!$B$5:$B$10,0),MATCH('LISTA - Setembro2024'!$AC33,Auxiliar!$D$4:$I$4,0)) -> 0 | AG33: =IF(OR(AB33="Code List",AB33="Y, N"),AC33,"n.a.") -> n.a. | AH33: =INDEX(Auxiliar!$D$5:$I$10,MATCH('LISTA - Setembro2024'!AH$3,Auxiliar!$B$5:$B$10,0),MATCH('LISTA - Setembro2024'!$AG33,Auxiliar!$D$4:$I$4,0)) -> 0 | AI33: =INDEX(Auxiliar!$D$5:$I$10,MATCH('LISTA - Setembro2024'!AI$3,Auxiliar!$B$5:$B$10,0),MATCH('LISTA - Setembro2024'!$AC33,Auxiliar!$D$4:$I$4,0)) -> 0 | AJ33: =INDEX(Auxiliar!$D$5:$I$10,MATCH('LISTA - Setembro2024'!AJ$3,Auxiliar!$B$5:$B$10,0),MATCH('LISTA - Setembro2024'!$AC33,Auxiliar!$D$4:$I$4,0)) -> 0 | AK33: =SUM(AF33,AH33:AJ33) -> 0
A34: EN.031 | B34: =C34&"_"&D34 -> ENTITY_FLG_HGH_CDS | C34: ENTITY | D34: FLG_HGH_CDS | E34: 5Y CDS > 1,000bps over the last 12 months | F34: Y | G34: N | H34: N | I34: N | J34: N | K34: N | L34: =IFERROR(VLOOKUP($B34,'LISTA - Atual'!$B$1:$I$444,5,0),"Novo") -> Y | M34: =IF(L34="Novo","Novo Campo",IF(L34=F34,"Igual","Diferente")) -> Igual | N34: =IFERROR(VLOOKUP($B34,'LISTA - Atual'!$B$1:$I$444,6,0),"Novo") -> N | O34: =IF(N34="Novo","Novo Campo",IF(N34=G34,"Igual","Diferente")) -> Igual | P34: =IFERROR(VLOOKUP($B34,'LISTA - Atual'!$B$1:$I$444,7,0),"Novo") -> N | Q34: =IF(P34="Novo","Novo Campo",IF(P34=H34,"Igual","Diferente")) -> Igual | R34: n/a | S34: =IFERROR(VLOOKUP($B34,'LISTA - Atual'!$B$1:$I$444,8,0),"Novo") -> N | T34: =IF(S34="Novo","Novo Campo",IF(S34=J34,"Igual","Diferente")) -> Igual | U34: n/a | V34: N | W34: =IFERROR(VLOOKUP(B34,#REF!,11,0),"n/a") -> n/a | X34: =IFERROR(VLOOKUP(B34,#REF!,8,0),"n/a") -> n/a | Y34: =$F$2 -> ESTR | Z34: Sem alteração | AA34: =VLOOKUP(Table1[[#This Row],[CONCAT]],'Campos Resumo Prop2.0'!A:H,8,0) -> #N/A | AB34: Y, N | AC34: n.a. | AD34: =INDEX(Auxiliar!$D$5:$I$10,MATCH('LISTA - Setembro2024'!AD$3,Auxiliar!$B$5:$B$10,0),MATCH('LISTA - Setembro2024'!$AC34,Auxiliar!$D$4:$I$4,0)) -> 0 | AE34: =INDEX(Auxiliar!$D$5:$I$10,MATCH('LISTA - Setembro2024'!AE$3,Auxiliar!$B$5:$B$10,0),MATCH('LISTA - Setembro2024'!$AC34,Auxiliar!$D$4:$I$4,0)) -> 0 | AF34: =INDEX(Auxiliar!$D$5:$I$10,MATCH('LISTA - Setembro2024'!AF$3,Auxiliar!$B$5:$B$10,0),MATCH('LISTA - Setembro2024'!$AC34,Auxiliar!$D$4:$I$4,0)) -> 0 | AG34: =IF(OR(AB34="Code List",AB34="Y, N"),AC34,"n.a.") -> n.a. | AH34: =INDEX(Auxiliar!$D$5:$I$10,MATCH('LISTA - Setembro2024'!AH$3,Auxiliar!$B$5:$B$10,0),MATCH('LISTA - Setembro2024'!$AG34,Auxiliar!$D$4:$I$4,0)) -> 0 | AI34: =INDEX(Auxiliar!$D$5:$I$10,MATCH('LISTA - Setembro2024'!AI$3,Auxiliar!$B$5:$B$10,0),MATCH('LISTA - Setembro2024'!$AC34,Auxiliar!$D$4:$I$4,0)) -> 0 | AJ34: =INDEX(Auxiliar!$D$5:$I$10,MATCH('LISTA - Setembro2024'!AJ$3,Auxiliar!$B$5:$B$10,0),MATCH('LISTA - Setembro2024'!$AC34,Auxiliar!$D$4:$I$4,0)) -> 0 | AK34: =SUM(AF34,AH34:AJ34) -> 0
A35: EN.032 | B35: =C35&"_"&D35 -> ENTITY_FLG_ISDA_CRDT_EVNT | C35: ENTITY | D35: FLG_ISDA_CRDT_EVNT | E35: ISDA credit event declared | F35: Y | G35: N | H35: N | I35: N | J35: N | K35: N | L35: =IFERROR(VLOOKUP($B35,'LISTA - Atual'!$B$1:$I$444,5,0),"Novo") -> Y | M35: =IF(L35="Novo","Novo Campo",IF(L35=F35,"Igual","Diferente")) -> Igual | N35: =IFERROR(VLOOKUP($B35,'LISTA - Atual'!$B$1:$I$444,6,0),"Novo") -> N | O35: =IF(N35="Novo","Novo Campo",IF(N35=G35,"Igual","Diferente")) -> Igual | P35: =IFERROR(VLOOKUP($B35,'LISTA - Atual'!$B$1:$I$444,7,0),"Novo") -> N | Q35: =IF(P35="Novo","Novo Campo",IF(P35=H35,"Igual","Diferente")) -> Igual | R35: n/a | S35: =IFERROR(VLOOKUP($B35,'LISTA - Atual'!$B$1:$I$444,8,0),"Novo") -> N | T35: =IF(S35="Novo","Novo Campo",IF(S35=J35,"Igual","Diferente")) -> Igual | U35: n/a | V35: N | W35: =IFERROR(VLOOKUP(B35,#REF!,11,0),"n/a") -> n/a | X35: =IFERROR(VLOOKUP(B35,#REF!,8,0),"n/a") -> n/a | Y35: =$F$2 -> ESTR | Z35: Sem alteração | AA35: =VLOOKUP(Table1[[#This Row],[CONCAT]],'Campos Resumo Prop2.0'!A:H,8,0) -> #N/A | AB35: Y, N | AC35: n.a. | AD35: =INDEX(Auxiliar!$D$5:$I$10,MATCH('LISTA - Setembro2024'!AD$3,Auxiliar!$B$5:$B$10,0),MATCH('LISTA - Setembro2024'!$AC35,Auxiliar!$D$4:$I$4,0)) -> 0 | AE35: =INDEX(Auxiliar!$D$5:$I$10,MATCH('LISTA - Setembro2024'!AE$3,Auxiliar!$B$5:$B$10,0),MATCH('LISTA - Setembro2024'!$AC35,Auxiliar!$D$4:$I$4,0)) -> 0 | AF35: =INDEX(Auxiliar!$D$5:$I$10,MATCH('LISTA - Setembro2024'!AF$3,Auxiliar!$B$5:$B$10,0),MATCH('LISTA - Setembro2024'!$AC35,Auxiliar!$D$4:$I$4,0)) -> 0 | AG35: =IF(OR(AB35="Code List",AB35="Y, N"),AC35,"n.a.") -> n.a. | AH35: =INDEX(Auxiliar!$D$5:$I$10,MATCH('LISTA - Setembro2024'!AH$3,Auxiliar!$B$5:$B$10,0),MATCH('LISTA - Setembro2024'!$AG35,Auxiliar!$D$4:$I$4,0)) -> 0 | AI35: =INDEX(Auxiliar!$D$5:$I$10,MATCH('LISTA - Setembro2024'!AI$3,Auxiliar!$B$5:$B$10,0),MATCH('LISTA - Setembro2024'!$AC35,Auxiliar!$D$4:$I$4,0)) -> 0 | AJ35: =INDEX(Auxiliar!$D$5:$I$10,MATCH('LISTA - Setembro2024'!AJ$3,Auxiliar!$B$5:$B$10,0),MATCH('LISTA - Setembro2024'!$AC35,Auxiliar!$D$4:$I$4,0)) -> 0 | AK35: =SUM(AF35,AH35:AJ35) -> 0
A36: EN.033 | B36: =C36&"_"&D36 -> ENTITY_FLG_NN_ACCRL | C36: ENTITY | D36: FLG_NN_ACCRL | E36: Credit obligation on non-accrual status | F36: Y | G36: N | H36: N | I36: N | J36: N | K36: N | L36: =IFERROR(VLOOKUP($B36,'LISTA - Atual'!$B$1:$I$444,5,0),"Novo") -> Y | M36: =IF(L36="Novo","Novo Campo",IF(L36=F36,"Igual","Diferente")) -> Igual | N36: =IFERROR(VLOOKUP($B36,'LISTA - Atual'!$B$1:$I$444,6,0),"Novo") -> N | O36: =IF(N36="Novo","Novo Campo",IF(N36=G36,"Igual","Diferente")) -> Igual | P36: =IFERROR(VLOOKUP($B36,'LISTA - Atual'!$B$1:$I$444,7,0),"Novo") -> N | Q36: =IF(P36="Novo","Novo Campo",IF(P36=H36,"Igual","Diferente")) -> Igual | R36: n/a | S36: =IFERROR(VLOOKUP($B36,'LISTA - Atual'!$B$1:$I$444,8,0),"Novo") -> N | T36: =IF(S36="Novo","Novo Campo",IF(S36=J36,"Igual","Diferente")) -> Igual | U36: n/a | V36: N | W36: =IFERROR(VLOOKUP(B36,#REF!,11,0),"n/a") -> n/a | X36: =IFERROR(VLOOKUP(B36,#REF!,8,0),"n/a") -> n/a | Y36: =$F$2 -> ESTR | Z36: Sem alteração | AA36: =VLOOKUP(Table1[[#This Row],[CONCAT]],'Campos Resumo Prop2.0'!A:H,8,0) -> #N/A | AB36: Y, N | AC36: n.a. | AD36: =INDEX(Auxiliar!$D$5:$I$10,MATCH('LISTA - Setembro2024'!AD$3,Auxiliar!$B$5:$B$10,0),MATCH('LISTA - Setembro2024'!$AC36,Auxiliar!$D$4:$I$4,0)) -> 0 | AE36: =INDEX(Auxiliar!$D$5:$I$10,MATCH('LISTA - Setembro2024'!AE$3,Auxiliar!$B$5:$B$10,0),MATCH('LISTA - Setembro2024'!$AC36,Auxiliar!$D$4:$I$4,0)) -> 0 | AF36: =INDEX(Auxiliar!$D$5:$I$10,MATCH('LISTA - Setembro2024'!AF$3,Auxiliar!$B$5:$B$10,0),MATCH('LISTA - Setembro2024'!$AC36,Auxiliar!$D$4:$I$4,0)) -> 0 | AG36: =IF(OR(AB36="Code List",AB36="Y, N"),AC36,"n.a.") -> n.a. | AH36: =INDEX(Auxiliar!$D$5:$I$10,MATCH('LISTA - Setembro2024'!AH$3,Auxiliar!$B$5:$B$10,0),MATCH('LISTA - Setembro2024'!$AG36,Auxiliar!$D$4:$I$4,0)) -> 0 | AI36: =INDEX(Auxiliar!$D$5:$I$10,MATCH('LISTA - Setembro2024'!AI$3,Auxiliar!$B$5:$B$10,0),MATCH('LISTA - Setembro2024'!$AC36,Auxiliar!$D$4:$I$4,0)) -> 0 | AJ36: =INDEX(Auxiliar!$D$5:$I$10,MATCH('LISTA - Setembro2024'!AJ$3,Auxiliar!$B$5:$B$10,0),MATCH('LISTA - Setembro2024'!$AC36,Auxiliar!$D$4:$I$4,0)) -> 0 | AK36: =SUM(AF36,AH36:AJ36) -> 0
A37: EN.034 | B37: =C37&"_"&D37 -> ENTITY_FLG_RQST_BNKRPTCY | C37: ENTITY | D37: FLG_RQST_BNKRPTCY | E37: Request by the institution for the obligor's bankruptcy | F37: Y | G37: N | H37: N | I37: N | J37: N | K37: N | L37: =IFERROR(VLOOKUP($B37,'LISTA - Atual'!$B$1:$I$444,5,0),"Novo") -> Y | M37: =IF(L37="Novo","Novo Campo",IF(L37=F37,"Igual","Diferente")) -> Igual | N37: =IFERROR(VLOOKUP($B37,'LISTA - Atual'!$B$1:$I$444,6,0),"Novo") -> N | O37: =IF(N37="Novo","Novo Campo",IF(N37=G37,"Igual","Diferente")) -> Igual | P37: =IFERROR(VLOOKUP($B37,'LISTA - Atual'!$B$1:$I$444,7,0),"Novo") -> N | Q37: =IF(P37="Novo","Novo Campo",IF(P37=H37,"Igual","Diferente")) -> Igual | R37: n/a | S37: =IFERROR(VLOOKUP($B37,'LISTA - Atual'!$B$1:$I$444,8,0),"Novo") -> N | T37: =IF(S37="Novo","Novo Campo",IF(S37=J37,"Igual","Diferente")) -> Igual | U37: n/a | V37: N | W37: =IFERROR(VLOOKUP(B37,#REF!,11,0),"n/a") -> n/a | X37: =IFERROR(VLOOKUP(B37,#REF!,8,0),"n/a") -> n/a | Y37: =$F$2 -> ESTR | Z37: Sem alteração | AA37: =VLOOKUP(Table1[[#This Row],[CONCAT]],'Campos Resumo Prop2.0'!A:H,8,0) -> #N/A | AB37: Y, N | AC37: n.a. | AD37: =INDEX(Auxiliar!$D$5:$I$10,MATCH('LISTA - Setembro2024'!AD$3,Auxiliar!$B$5:$B$10,0),MATCH('LISTA - Setembro2024'!$AC37,Auxiliar!$D$4:$I$4,0)) -> 0 | AE37: =INDEX(Auxiliar!$D$5:$I$10,MATCH('LISTA - Setembro2024'!AE$3,Auxiliar!$B$5:$B$10,0),MATCH('LISTA - Setembro2024'!$AC37,Auxiliar!$D$4:$I$4,0)) -> 0 | AF37: =INDEX(Auxiliar!$D$5:$I$10,MATCH('LISTA - Setembro2024'!AF$3,Auxiliar!$B$5:$B$10,0),MATCH('LISTA - Setembro2024'!$AC37,Auxiliar!$D$4:$I$4,0)) -> 0 | AG37: =IF(OR(AB37="Code List",AB37="Y, N"),AC37,"n.a.") -> n.a. | AH37: =INDEX(Auxiliar!$D$5:$I$10,MATCH('LISTA - Setembro2024'!AH$3,Auxiliar!$B$5:$B$10,0),MATCH('LISTA - Setembro2024'!$AG37,Auxiliar!$D$4:$I$4,0)) -> 0 | AI37: =INDEX(Auxiliar!$D$5:$I$10,MATCH('LISTA - Setembro2024'!AI$3,Auxiliar!$B$5:$B$10,0),MATCH('LISTA - Setembro2024'!$AC37,Auxiliar!$D$4:$I$4,0)) -> 0 | AJ37: =INDEX(Auxiliar!$D$5:$I$10,MATCH('LISTA - Setembro2024'!AJ$3,Auxiliar!$B$5:$B$10,0),MATCH('LISTA - Setembro2024'!$AC37,Auxiliar!$D$4:$I$4,0)) -> 0 | AK37: =SUM(AF37,AH37:AJ37) -> 0
A38: EN.035 | B38: =C38&"_"&D38 -> ENTITY_FLG_RQST_DSTRSSD_RSTRCTRNG | C38: ENTITY | D38: FLG_RQST_DSTRSSD_RSTRCTRNG | E38: Request for current concession of forbearance measures as defined in EBA/ITS/2013/03 resulting in distressed restructuring of the credit obligation | F38: Y | G38: N | H38: N | I38: N | J38: N | K38: N | L38: =IFERROR(VLOOKUP($B38,'LISTA - Atual'!$B$1:$I$444,5,0),"Novo") -> Y | M38: =IF(L38="Novo","Novo Campo",IF(L38=F38,"Igual","Diferente")) -> Igual | N38: =IFERROR(VLOOKUP($B38,'LISTA - Atual'!$B$1:$I$444,6,0),"Novo") -> N | O38: =IF(N38="Novo","Novo Campo",IF(N38=G38,"Igual","Diferente")) -> Igual | P38: =IFERROR(VLOOKUP($B38,'LISTA - Atual'!$B$1:$I$444,7,0),"Novo") -> N | Q38: =IF(P38="Novo","Novo Campo",IF(P38=H38,"Igual","Diferente")) -> Igual | R38: n/a | S38: =IFERROR(VLOOKUP($B38,'LISTA - Atual'!$B$1:$I$444,8,0),"Novo") -> N | T38: =IF(S38="Novo","Novo Campo",IF(S38=J38,"Igual","Diferente")) -> Igual | U38: n/a | V38: N | W38: =IFERROR(VLOOKUP(B38,#REF!,11,0),"n/a") -> n/a | X38: =IFERROR(VLOOKUP(B38,#REF!,8,0),"n/a") -> n/a | Y38: =$F$2 -> ESTR | Z38: Sem alteração | AA38: =VLOOKUP(Table1[[#This Row],[CONCAT]],'Campos Resumo Prop2.0'!A:H,8,0) -> #N/A | AB38: Y, N | AC38: n.a. | AD38: =INDEX(Auxiliar!$D$5:$I$10,MATCH('LISTA - Setembro2024'!AD$3,Auxiliar!$B$5:$B$10,0),MATCH('LISTA - Setembro2024'!$AC38,Auxiliar!$D$4:$I$4,0)) -> 0 | AE38: =INDEX(Auxiliar!$D$5:$I$10,MATCH('LISTA - Setembro2024'!AE$3,Auxiliar!$B$5:$B$10,0),MATCH('LISTA - Setembro2024'!$AC38,Auxiliar!$D$4:$I$4,0)) -> 0 | AF38: =INDEX(Auxiliar!$D$5:$I$10,MATCH('LISTA - Setembro2024'!AF$3,Auxiliar!$B$5:$B$10,0),MATCH('LISTA - Setembro2024'!$AC38,Auxiliar!$D$4:$I$4,0)) -> 0 | AG38: =IF(OR(AB38="Code List",AB38="Y, N"),AC38,"n.a.") -> n.a. | AH38: =INDEX(Auxiliar!$D$5:$I$10,MATCH('LISTA - Setembro2024'!AH$3,Auxiliar!$B$5:$B$10,0),MATCH('LISTA - Setembro2024'!$AG38,Auxiliar!$D$4:$I$4,0)) -> 0 | AI38: =INDEX(Auxiliar!$D$5:$I$10,MATCH('LISTA - Setembro2024'!AI$3,Auxiliar!$B$5:$B$10,0),MATCH('LISTA - Setembro2024'!$AC38,Auxiliar!$D$4:$I$4,0)) -> 0 | AJ38: =INDEX(Auxiliar!$D$5:$I$10,MATCH('LISTA - Setembro2024'!AJ$3,Auxiliar!$B$5:$B$10,0),MATCH('LISTA - Setembro2024'!$AC38,Auxiliar!$D$4:$I$4,0)) -> 0 | AK38: =SUM(AF38,AH38:AJ38) -> 0
A39: EN.036 | B39: =C39&"_"&D39 -> ENTITY_FLG_RQST_EMRGNCY_FNDNG | C39: ENTITY | D39: FLG_RQST_EMRGNCY_FNDNG | E39: Request by the debtor for emergency funding from the bank | F39: Y | G39: N | H39: N | I39: N | J39: N | K39: Y | L39: =IFERROR(VLOOKUP($B39,'LISTA - Atual'!$B$1:$I$444,5,0),"Novo") -> Y | M39: =IF(L39="Novo","Novo Campo",IF(L39=F39,"Igual","Diferente")) -> Igual | N39: =IFERROR(VLOOKUP($B39,'LISTA - Atual'!$B$1:$I$444,6,0),"Novo") -> N | O39: =IF(N39="Novo","Novo Campo",IF(N39=G39,"Igual","Diferente")) -> Igual | P39: =IFERROR(VLOOKUP($B39,'LISTA - Atual'!$B$1:$I$444,7,0),"Novo") -> N | Q39: =IF(P39="Novo","Novo Campo",IF(P39=H39,"Igual","Diferente")) -> Igual | R39: n/a | S39: =IFERROR(VLOOKUP($B39,'LISTA - Atual'!$B$1:$I$444,8,0),"Novo") -> N | T39: =IF(S39="Novo","Novo Campo",IF(S39=J39,"Igual","Diferente")) -> Igual | U39: n/a | V39: N | W39: =IFERROR(VLOOKUP(B39,#REF!,11,0),"n/a") -> n/a | X39: =IFERROR(VLOOKUP(B39,#REF!,8,0),"n/a") -> n/a | Y39: =$F$2 -> ESTR | Z39: Sem alteração | AA39: =VLOOKUP(Table1[[#This Row],[CONCAT]],'Campos Resumo Prop2.0'!A:H,8,0) -> #N/A | AB39: Y, N | AC39: n.a. | AD39: =INDEX(Auxiliar!$D$5:$I$10,MATCH('LISTA - Setembro2024'!AD$3,Auxiliar!$B$5:$B$10,0),MATCH('LISTA - Setembro2024'!$AC39,Auxiliar!$D$4:$I$4,0)) -> 0 | AE39: =INDEX(Auxiliar!$D$5:$I$10,MATCH('LISTA - Setembro2024'!AE$3,Auxiliar!$B$5:$B$10,0),MATCH('LISTA - Setembro2024'!$AC39,Auxiliar!$D$4:$I$4,0)) -> 0 | AF39: =INDEX(Auxiliar!$D$5:$I$10,MATCH('LISTA - Setembro2024'!AF$3,Auxiliar!$B$5:$B$10,0),MATCH('LISTA - Setembro2024'!$AC39,Auxiliar!$D$4:$I$4,0)) -> 0 | AG39: =IF(OR(AB39="Code List",AB39="Y, N"),AC39,"n.a.") -> n.a. | AH39: =INDEX(Auxiliar!$D$5:$I$10,MATCH('LISTA - Setembro2024'!AH$3,Auxiliar!$B$5:$B$10,0),MATCH('LISTA - Setembro2024'!$AG39,Auxiliar!$D$4:$I$4,0)) -> 0 | AI39: =INDEX(Auxiliar!$D$5:$I$10,MATCH('LISTA - Setembro2024'!AI$3,Auxiliar!$B$5:$B$10,0),MATCH('LISTA - Setembro2024'!$AC39,Auxiliar!$D$4:$I$4,0)) -> 0 | AJ39: =INDEX(Auxiliar!$D$5:$I$10,MATCH('LISTA - Setembro2024'!AJ$3,Auxiliar!$B$5:$B$10,0),MATCH('LISTA - Setembro2024'!$AC39,Auxiliar!$D$4:$I$4,0)) -> 0 | AK39: =SUM(AF39,AH39:AJ39) -> 0
A40: EN.037 | B40: =C40&"_"&D40 -> ENTITY_FLG_SLL_WTH_LSS | C40: ENTITY | D40: FLG_SLL_WTH_LSS | E40: Sell of a credit obligation with material credit related economic loss (>= 5%) | F40: Y | G40: N | H40: N | I40: N | J40: N | K40: N | L40: =IFERROR(VLOOKUP($B40,'LISTA - Atual'!$B$1:$I$444,5,0),"Novo") -> Y | M40: =IF(L40="Novo","Novo Campo",IF(L40=F40,"Igual","Diferente")) -> Igual | N40: =IFERROR(VLOOKUP($B40,'LISTA - Atual'!$B$1:$I$444,6,0),"Novo") -> N | O40: =IF(N40="Novo","Novo Campo",IF(N40=G40,"Igual","Diferente")) -> Igual | P40: =IFERROR(VLOOKUP($B40,'LISTA - Atual'!$B$1:$I$444,7,0),"Novo") -> N | Q40: =IF(P40="Novo","Novo Campo",IF(P40=H40,"Igual","Diferente")) -> Igual | R40: n/a | S40: =IFERROR(VLOOKUP($B40,'LISTA - Atual'!$B$1:$I$444,8,0),"Novo") -> N | T40: =IF(S40="Novo","Novo Campo",IF(S40=J40,"Igual","Diferente")) -> Igual | U40: n/a | V40: N | W40: =IFERROR(VLOOKUP(B40,#REF!,11,0),"n/a") -> n/a | X40: =IFERROR(VLOOKUP(B40,#REF!,8,0),"n/a") -> n/a | Y40: =$F$2 -> ESTR | Z40: Sem alteração | AA40: =VLOOKUP(Table1[[#This Row],[CONCAT]],'Campos Resumo Prop2.0'!A:H,8,0) -> #N/A | AB40: Y, N | AC40: n.a. | AD40: =INDEX(Auxiliar!$D$5:$I$10,MATCH('LISTA - Setembro2024'!AD$3,Auxiliar!$B$5:$B$10,0),MATCH('LISTA - Setembro2024'!$AC40,Auxiliar!$D$4:$I$4,0)) -> 0 | AE40: =INDEX(Auxiliar!$D$5:$I$10,MATCH('LISTA - Setembro2024'!AE$3,Auxiliar!$B$5:$B$10,0),MATCH('LISTA - Setembro2024'!$AC40,Auxiliar!$D$4:$I$4,0)) -> 0 | AF40: =INDEX(Auxiliar!$D$5:$I$10,MATCH('LISTA - Setembro2024'!AF$3,Auxiliar!$B$5:$B$10,0),MATCH('LISTA - Setembro2024'!$AC40,Auxiliar!$D$4:$I$4,0)) -> 0 | AG40: =IF(OR(AB40="Code List",AB40="Y, N"),AC40,"n.a.") -> n.a. | AH40: =INDEX(Auxiliar!$D$5:$I$10,MATCH('LISTA - Setembro2024'!AH$3,Auxiliar!$B$5:$B$10,0),MATCH('LISTA - Setembro2024'!$AG40,Auxiliar!$D$4:$I$4,0)) -> 0 | AI40: =INDEX(Auxiliar!$D$5:$I$10,MATCH('LISTA - Setembro2024'!AI$3,Auxiliar!$B$5:$B$10,0),MATCH('LISTA - Setembro2024'!$AC40,Auxiliar!$D$4:$I$4,0)) -> 0 | AJ40: =INDEX(Auxiliar!$D$5:$I$10,MATCH('LISTA - Setembro2024'!AJ$3,Auxiliar!$B$5:$B$10,0),MATCH('LISTA - Setembro2024'!$AC40,Auxiliar!$D$4:$I$4,0)) -> 0 | AK40: =SUM(AF40,AH40:AJ40) -> 0
A41: EN.038 | B41: =C41&"_"&D41 -> ENTITY_INCM_SC | C41: ENTITY | D41: INCM_SC | E41: Income self-certified | F41: Y | G41: N | H41: N | I41: N | J41: N | K41: N | L41: =IFERROR(VLOOKUP($B41,'LISTA - Atual'!$B$1:$I$444,5,0),"Novo") -> Y | M41: =IF(L41="Novo","Novo Campo",IF(L41=F41,"Igual","Diferente")) -> Igual | N41: =IFERROR(VLOOKUP($B41,'LISTA - Atual'!$B$1:$I$444,6,0),"Novo") -> N | O41: =IF(N41="Novo","Novo Campo",IF(N41=G41,"Igual","Diferente")) -> Igual | P41: =IFERROR(VLOOKUP($B41,'LISTA - Atual'!$B$1:$I$444,7,0),"Novo") -> N | Q41: =IF(P41="Novo","Novo Campo",IF(P41=H41,"Igual","Diferente")) -> Igual | R41: n/a | S41: =IFERROR(VLOOKUP($B41,'LISTA - Atual'!$B$1:$I$444,8,0),"Novo") -> N | T41: =IF(S41="Novo","Novo Campo",IF(S41=J41,"Igual","Diferente")) -> Igual | U41: n/a | V41: N | W41: =IFERROR(VLOOKUP(B41,#REF!,11,0),"n/a") -> n/a | X41: =IFERROR(VLOOKUP(B41,#REF!,8,0),"n/a") -> n/a | Y41: =$F$2 -> ESTR | Z41: Sem alteração | AA41: =VLOOKUP(Table1[[#This Row],[CONCAT]],'Campos Resumo Prop2.0'!A:H,8,0) -> #N/A | AB41: Y, N | AC41: n.a. | AD41: =INDEX(Auxiliar!$D$5:$I$10,MATCH('LISTA - Setembro2024'!AD$3,Auxiliar!$B$5:$B$10,0),MATCH('LISTA - Setembro2024'!$AC41,Auxiliar!$D$4:$I$4,0)) -> 0 | AE41: =INDEX(Auxiliar!$D$5:$I$10,MATCH('LISTA - Setembro2024'!AE$3,Auxiliar!$B$5:$B$10,0),MATCH('LISTA - Setembro2024'!$AC41,Auxiliar!$D$4:$I$4,0)) -> 0 | AF41: =INDEX(Auxiliar!$D$5:$I$10,MATCH('LISTA - Setembro2024'!AF$3,Auxiliar!$B$5:$B$10,0),MATCH('LISTA - Setembro2024'!$AC41,Auxiliar!$D$4:$I$4,0)) -> 0 | AG41: =IF(OR(AB41="Code List",AB41="Y, N"),AC41,"n.a.") -> n.a. | AH41: =INDEX(Auxiliar!$D$5:$I$10,MATCH('LISTA - Setembro2024'!AH$3,Auxiliar!$B$5:$B$10,0),MATCH('LISTA - Setembro2024'!$AG41,Auxiliar!$D$4:$I$4,0)) -> 0 | AI41: =INDEX(Auxiliar!$D$5:$I$10,MATCH('LISTA - Setembro2024'!AI$3,Auxiliar!$B$5:$B$10,0),MATCH('LISTA - Setembro2024'!$AC41,Auxiliar!$D$4:$I$4,0)) -> 0 | AJ41: =INDEX(Auxiliar!$D$5:$I$10,MATCH('LISTA - Setembro2024'!AJ$3,Auxiliar!$B$5:$B$10,0),MATCH('LISTA - Setembro2024'!$AC41,Auxiliar!$D$4:$I$4,0)) -> 0 | AK41: =SUM(AF41,AH41:AJ41) -> 0
A42: EN.039 | B42: =C42&"_"&D42 -> ENTITY_INTRNL_RTNG | C42: ENTITY | D42: INTRNL_RTNG | E42: Internal rating at reference date | F42: Y | G42: N | H42: N | I42: N | J42: N | K42: Y | L42: =IFERROR(VLOOKUP($B42,'LISTA - Atual'!$B$1:$I$444,5,0),"Novo") -> Y | M42: =IF(L42="Novo","Novo Campo",IF(L42=F42,"Igual","Diferente")) -> Igual | N42: =IFERROR(VLOOKUP($B42,'LISTA - Atual'!$B$1:$I$444,6,0),"Novo") -> N | O42: =IF(N42="Novo","Novo Campo",IF(N42=G42,"Igual","Diferente")) -> Igual | P42: =IFERROR(VLOOKUP($B42,'LISTA - Atual'!$B$1:$I$444,7,0),"Novo") -> N | Q42: =IF(P42="Novo","Novo Campo",IF(P42=H42,"Igual","Diferente")) -> Igual | R42: n/a | S42: =IFERROR(VLOOKUP($B42,'LISTA - Atual'!$B$1:$I$444,8,0),"Novo") -> N | T42: =IF(S42="Novo","Novo Campo",IF(S42=J42,"Igual","Diferente")) -> Igual | U42: n/a | V42: N | W42: =IFERROR(VLOOKUP(B42,#REF!,11,0),"n/a") -> n/a | X42: =IFERROR(VLOOKUP(B42,#REF!,8,0),"n/a") -> n/a | Y42: =$F$2 -> ESTR | Z42: Sem alteração | AA42: =VLOOKUP(Table1[[#This Row],[CONCAT]],'Campos Resumo Prop2.0'!A:H,8,0) -> #N/A | AB42: Code List | AC42: n.a. | AD42: 1 | AE42: =INDEX(Auxiliar!$D$5:$I$10,MATCH('LISTA - Setembro2024'!AE$3,Auxiliar!$B$5:$B$10,0),MATCH('LISTA - Setembro2024'!$AC42,Auxiliar!$D$4:$I$4,0)) -> 0 | AF42: =INDEX(Auxiliar!$D$5:$I$10,MATCH('LISTA - Setembro2024'!AF$3,Auxiliar!$B$5:$B$10,0),MATCH('LISTA - Setembro2024'!$AC42,Auxiliar!$D$4:$I$4,0)) -> 0 | AG42: =IF(OR(AB42="Code List",AB42="Y, N"),AC42,"n.a.") -> n.a. | AH42: =INDEX(Auxiliar!$D$5:$I$10,MATCH('LISTA - Setembro2024'!AH$3,Auxiliar!$B$5:$B$10,0),MATCH('LISTA - Setembro2024'!$AG42,Auxiliar!$D$4:$I$4,0)) -> 0 | AI42: =INDEX(Auxiliar!$D$5:$I$10,MATCH('LISTA - Setembro2024'!AI$3,Auxiliar!$B$5:$B$10,0),MATCH('LISTA - Setembro2024'!$AC42,Auxiliar!$D$4:$I$4,0)) -> 0 | AJ42: =INDEX(Auxiliar!$D$5:$I$10,MATCH('LISTA - Setembro2024'!AJ$3,Auxiliar!$B$5:$B$10,0),MATCH('LISTA - Setembro2024'!$AC42,Auxiliar!$D$4:$I$4,0)) -> 0 | AK42: =SUM(AF42,AH42:AJ42) -> 0 | AL42: internal ratings
A43: EN.040 | B43: =C43&"_"&D43 -> ENTITY_INTRNL_RTNG_PRVS | C43: ENTITY | D43: INTRNL_RTNG_PRVS | E43: Previous internal rating | F43: Y | G43: N | H43: N | I43: N | J43: N | K43: Y | L43: =IFERROR(VLOOKUP($B43,'LISTA - Atual'!$B$1:$I$444,5,0),"Novo") -> Y | M43: =IF(L43="Novo","Novo Campo",IF(L43=F43,"Igual","Diferente")) -> Igual | N43: =IFERROR(VLOOKUP($B43,'LISTA - Atual'!$B$1:$I$444,6,0),"Novo") -> N | O43: =IF(N43="Novo","Novo Campo",IF(N43=G43,"Igual","Diferente")) -> Igual | P43: =IFERROR(VLOOKUP($B43,'LISTA - Atual'!$B$1:$I$444,7,0),"Novo") -> N | Q43: =IF(P43="Novo","Novo Campo",IF(P43=H43,"Igual","Diferente")) -> Igual | R43: n/a | S43: =IFERROR(VLOOKUP($B43,'LISTA - Atual'!$B$1:$I$444,8,0),"Novo") -> N | T43: =IF(S43="Novo","Novo Campo",IF(S43=J43,"Igual","Diferente")) -> Igual | U43: n/a | V43: N | W43: =IFERROR(VLOOKUP(B43,#REF!,11,0),"n/a") -> n/a | X43: =IFERROR(VLOOKUP(B43,#REF!,8,0),"n/a") -> n/a | Y43: =$F$2 -> ESTR | Z43: Sem alteração | AA43: =VLOOKUP(Table1[[#This Row],[CONCAT]],'Campos Resumo Prop2.0'!A:H,8,0) -> #N/A | AB43: Code List | AC43: n.a. | AD43: 1 | AE43: =INDEX(Auxiliar!$D$5:$I$10,MATCH('LISTA - Setembro2024'!AE$3,Auxiliar!$B$5:$B$10,0),MATCH('LISTA - Setembro2024'!$AC43,Auxiliar!$D$4:$I$4,0)) -> 0 | AF43: =INDEX(Auxiliar!$D$5:$I$10,MATCH('LISTA - Setembro2024'!AF$3,Auxiliar!$B$5:$B$10,0),MATCH('LISTA - Setembro2024'!$AC43,Auxiliar!$D$4:$I$4,0)) -> 0 | AG43: =IF(OR(AB43="Code List",AB43="Y, N"),AC43,"n.a.") -> n.a. | AH43: =INDEX(Auxiliar!$D$5:$I$10,MATCH('LISTA - Setembro2024'!AH$3,Auxiliar!$B$5:$B$10,0),MATCH('LISTA - Setembro2024'!$AG43,Auxiliar!$D$4:$I$4,0)) -> 0 | AI43: =INDEX(Auxiliar!$D$5:$I$10,MATCH('LISTA - Setembro2024'!AI$3,Auxiliar!$B$5:$B$10,0),MATCH('LISTA - Setembro2024'!$AC43,Auxiliar!$D$4:$I$4,0)) -> 0 | AJ43: =INDEX(Auxiliar!$D$5:$I$10,MATCH('LISTA - Setembro2024'!AJ$3,Auxiliar!$B$5:$B$10,0),MATCH('LISTA - Setembro2024'!$AC43,Auxiliar!$D$4:$I$4,0)) -> 0 | AK43: =SUM(AF43,AH43:AJ43) -> 0 | AL43: internal ratings
A44: EN.041 | B44: =C44&"_"&D44 -> ENTITY_LGL_PRCDNG_STTS_LE | C44: ENTITY | D44: LGL_PRCDNG_STTS_LE | E44: Legal proceedings status Counterparty (LE) | F44: Y | G44: N | H44: N | I44: N | J44: N | K44: Y | L44: =IFERROR(VLOOKUP($B44,'LISTA - Atual'!$B$1:$I$444,5,0),"Novo") -> Y | M44: =IF(L44="Novo","Novo Campo",IF(L44=F44,"Igual","Diferente")) -> Igual | N44: =IFERROR(VLOOKUP($B44,'LISTA - Atual'!$B$1:$I$444,6,0),"Novo") -> N | O44: =IF(N44="Novo","Novo Campo",IF(N44=G44,"Igual","Diferente")) -> Igual | P44: =IFERROR(VLOOKUP($B44,'LISTA - Atual'!$B$1:$I$444,7,0),"Novo") -> N | Q44: =IF(P44="Novo","Novo Campo",IF(P44=H44,"Igual","Diferente")) -> Igual | R44: n/a | S44: =IFERROR(VLOOKUP($B44,'LISTA - Atual'!$B$1:$I$444,8,0),"Novo") -> N | T44: =IF(S44="Novo","Novo Campo",IF(S44=J44,"Igual","Diferente")) -> Igual | U44: n/a | V44: N | W44: =IFERROR(VLOOKUP(B44,#REF!,11,0),"n/a") -> n/a | X44: =IFERROR(VLOOKUP(B44,#REF!,8,0),"n/a") -> n/a | Y44: =$F$2 -> ESTR | Z44: Sem alteração | AA44: =VLOOKUP(Table1[[#This Row],[CONCAT]],'Campos Resumo Prop2.0'!A:H,8,0) -> #N/A | AB44: Code List | AC44: n.a. | AD44: =INDEX(Auxiliar!$D$5:$I$10,MATCH('LISTA - Setembro2024'!AD$3,Auxiliar!$B$5:$B$10,0),MATCH('LISTA - Setembro2024'!$AC44,Auxiliar!$D$4:$I$4,0)) -> 0 | AE44: =INDEX(Auxiliar!$D$5:$I$10,MATCH('LISTA - Setembro2024'!AE$3,Auxiliar!$B$5:$B$10,0),MATCH('LISTA - Setembro2024'!$AC44,Auxiliar!$D$4:$I$4,0)) -> 0 | AF44: =INDEX(Auxiliar!$D$5:$I$10,MATCH('LISTA - Setembro2024'!AF$3,Auxiliar!$B$5:$B$10,0),MATCH('LISTA - Setembro2024'!$AC44,Auxiliar!$D$4:$I$4,0)) -> 0 | AG44: =IF(OR(AB44="Code List",AB44="Y, N"),AC44,"n.a.") -> n.a. | AH44: =INDEX(Auxiliar!$D$5:$I$10,MATCH('LISTA - Setembro2024'!AH$3,Auxiliar!$B$5:$B$10,0),MATCH('LISTA - Setembro2024'!$AG44,Auxiliar!$D$4:$I$4,0)) -> 0 | AI44: =INDEX(Auxiliar!$D$5:$I$10,MATCH('LISTA - Setembro2024'!AI$3,Auxiliar!$B$5:$B$10,0),MATCH('LISTA - Setembro2024'!$AC44,Auxiliar!$D$4:$I$4,0)) -> 0 | AJ44: =INDEX(Auxiliar!$D$5:$I$10,MATCH('LISTA - Setembro2024'!AJ$3,Auxiliar!$B$5:$B$10,0),MATCH('LISTA - Setembro2024'!$AC44,Auxiliar!$D$4:$I$4,0)) -> 0 | AK44: =SUM(AF44,AH44:AJ44) -> 0
A45: EN.042 | B45: =C45&"_"&D45 -> ENTITY_OWND_BY_SPNSR | C45: ENTITY | D45: OWND_BY_SPNSR | E45: >50% owned by a sponsor as per ECB Guidance on leveraged transactions | F45: Y | G45: N | H45: N | I45: N | J45: N | K45: Y | L45: =IFERROR(VLOOKUP($B45,'LISTA - Atual'!$B$1:$I$444,5,0),"Novo") -> Y | M45: =IF(L45="Novo","Novo Campo",IF(L45=F45,"Igual","Diferente")) -> Igual | N45: =IFERROR(VLOOKUP($B45,'LISTA - Atual'!$B$1:$I$444,6,0),"Novo") -> N | O45: =IF(N45="Novo","Novo Campo",IF(N45=G45,"Igual","Diferente")) -> Igual | P45: =IFERROR(VLOOKUP($B45,'LISTA - Atual'!$B$1:$I$444,7,0),"Novo") -> N | Q45: =IF(P45="Novo","Novo Campo",IF(P45=H45,"Igual","Diferente")) -> Igual | R45: n/a | S45: =IFERROR(VLOOKUP($B45,'LISTA - Atual'!$B$1:$I$444,8,0),"Novo") -> N | T45: =IF(S45="Novo","Novo Campo",IF(S45=J45,"Igual","Diferente")) -> Igual | U45: n/a | V45: Y | W45: =IFERROR(VLOOKUP(B45,#REF!,11,0),"n/a") -> n/a | X45: =IFERROR(VLOOKUP(B45,#REF!,8,0),"n/a") -> n/a | Y45: =$F$2 -> ESTR | Z45: Sem alteração | AA45: =VLOOKUP(Table1[[#This Row],[CONCAT]],'Campos Resumo Prop2.0'!A:H,8,0) -> #N/A | AB45: Y, N | AC45: n.a. | AD45: 10 | AE45: 8 | AF45: =INDEX(Auxiliar!$D$5:$I$10,MATCH('LISTA - Setembro2024'!AF$3,Auxiliar!$B$5:$B$10,0),MATCH('LISTA - Setembro2024'!$AC45,Auxiliar!$D$4:$I$4,0)) -> 0 | AG45: =IF(OR(AB45="Code List",AB45="Y, N"),AC45,"n.a.") -> n.a. | AH45: =INDEX(Auxiliar!$D$5:$I$10,MATCH('LISTA - Setembro2024'!AH$3,Auxiliar!$B$5:$B$10,0),MATCH('LISTA - Setembro2024'!$AG45,Auxiliar!$D$4:$I$4,0)) -> 0 | AI45: =INDEX(Auxiliar!$D$5:$I$10,MATCH('LISTA - Setembro2024'!AI$3,Auxiliar!$B$5:$B$10,0),MATCH('LISTA - Setembro2024'!$AC45,Auxiliar!$D$4:$I$4,0)) -> 0 | AJ45: =INDEX(Auxiliar!$D$5:$I$10,MATCH('LISTA - Setembro2024'!AJ$3,Auxiliar!$B$5:$B$10,0),MATCH('LISTA - Setembro2024'!$AC45,Auxiliar!$D$4:$I$4,0)) -> 0 | AK45: =SUM(AF45,AH45:AJ45) -> 0 | AL45: Leverage finance - Manual
A46: EN.043 | B46: =C46&"_"&D46 -> ENTITY_PRFRMNG_STTS_LE | C46: ENTITY | D46: PRFRMNG_STTS_LE | E46: Performing status | F46: Y | G46: N | H46: N | I46: N | J46: N | K46: Y | L46: =IFERROR(VLOOKUP($B46,'LISTA - Atual'!$B$1:$I$444,5,0),"Novo") -> Y | M46: =IF(L46="Novo","Novo Campo",IF(L46=F46,"Igual","Diferente")) -> Igual | N46: =IFERROR(VLOOKUP($B46,'LISTA - Atual'!$B$1:$I$444,6,0),"Novo") -> N | O46: =IF(N46="Novo","Novo Campo",IF(N46=G46,"Igual","Diferente")) -> Igual | P46: =IFERROR(VLOOKUP($B46,'LISTA - Atual'!$B$1:$I$444,7,0),"Novo") -> N | Q46: =IF(P46="Novo","Novo Campo",IF(P46=H46,"Igual","Diferente")) -> Igual | R46: n/a | S46: =IFERROR(VLOOKUP($B46,'LISTA - Atual'!$B$1:$I$444,8,0),"Novo") -> N | T46: =IF(S46="Novo","Novo Campo",IF(S46=J46,"Igual","Diferente")) -> Igual | U46: n/a | V46: N | W46: =IFERROR(VLOOKUP(B46,#REF!,11,0),"n/a") -> n/a | X46: =IFERROR(VLOOKUP(B46,#REF!,8,0),"n/a") -> n/a | Y46: =$F$2 -> ESTR | Z46: Sem alteração | AA46: =VLOOKUP(Table1[[#This Row],[CONCAT]],'Campos Resumo Prop2.0'!A:H,8,0) -> #N/A | AB46: Code List | AC46: n.a. | AD46: =INDEX(Auxiliar!$D$5:$I$10,MATCH('LISTA - Setembro2024'!AD$3,Auxiliar!$B$5:$B$10,0),MATCH('LISTA - Setembro2024'!$AC46,Auxiliar!$D$4:$I$4,0)) -> 0 | AE46: =INDEX(Auxiliar!$D$5:$I$10,MATCH('LISTA - Setembro2024'!AE$3,Auxiliar!$B$5:$B$10,0),MATCH('LISTA - Setembro2024'!$AC46,Auxiliar!$D$4:$I$4,0)) -> 0 | AF46: =INDEX(Auxiliar!$D$5:$I$10,MATCH('LISTA - Setembro2024'!AF$3,Auxiliar!$B$5:$B$10,0),MATCH('LISTA - Setembro2024'!$AC46,Auxiliar!$D$4:$I$4,0)) -> 0 | AG46: =IF(OR(AB46="Code List",AB46="Y, N"),AC46,"n.a.") -> n.a. | AH46: =INDEX(Auxiliar!$D$5:$I$10,MATCH('LISTA - Setembro2024'!AH$3,Auxiliar!$B$5:$B$10,0),MATCH('LISTA - Setembro2024'!$AG46,Auxiliar!$D$4:$I$4,0)) -> 0 | AI46: =INDEX(Auxiliar!$D$5:$I$10,MATCH('LISTA - Setembro2024'!AI$3,Auxiliar!$B$5:$B$10,0),MATCH('LISTA - Setembro2024'!$AC46,Auxiliar!$D$4:$I$4,0)) -> 0 | AJ46: =INDEX(Auxiliar!$D$5:$I$10,MATCH('LISTA - Setembro2024'!AJ$3,Auxiliar!$B$5:$B$10,0),MATCH('LISTA - Setembro2024'!$AC46,Auxiliar!$D$4:$I$4,0)) -> 0 | AK46: =SUM(AF46,AH46:AJ46) -> 0
A47: EN.044 | B47: =C47&"_"&D47 -> ENTITY_RTNG_MTHD | C47: ENTITY | D47: RTNG_MTHD | E47: Rating method | F47: Y | G47: N | H47: N | I47: N | J47: N | K47: Y | L47: =IFERROR(VLOOKUP($B47,'LISTA - Atual'!$B$1:$I$444,5,0),"Novo") -> Y | M47: =IF(L47="Novo","Novo Campo",IF(L47=F47,"Igual","Diferente")) -> Igual | N47: =IFERROR(VLOOKUP($B47,'LISTA - Atual'!$B$1:$I$444,6,0),"Novo") -> N | O47: =IF(N47="Novo","Novo Campo",IF(N47=G47,"Igual","Diferente")) -> Igual | P47: =IFERROR(VLOOKUP($B47,'LISTA - Atual'!$B$1:$I$444,7,0),"Novo") -> N | Q47: =IF(P47="Novo","Novo Campo",IF(P47=H47,"Igual","Diferente")) -> Igual | R47: n/a | S47: =IFERROR(VLOOKUP($B47,'LISTA - Atual'!$B$1:$I$444,8,0),"Novo") -> N | T47: =IF(S47="Novo","Novo Campo",IF(S47=J47,"Igual","Diferente")) -> Igual | U47: n/a | V47: N | W47: =IFERROR(VLOOKUP(B47,#REF!,11,0),"n/a") -> n/a | X47: =IFERROR(VLOOKUP(B47,#REF!,8,0),"n/a") -> n/a | Y47: =$F$2 -> ESTR | Z47: Sem alteração | AA47: =VLOOKUP(Table1[[#This Row],[CONCAT]],'Campos Resumo Prop2.0'!A:H,8,0) -> #N/A | AB47: Code List | AC47: n.a. | AD47: 1 | AE47: =INDEX(Auxiliar!$D$5:$I$10,MATCH('LISTA - Setembro2024'!AE$3,Auxiliar!$B$5:$B$10,0),MATCH('LISTA - Setembro2024'!$AC47,Auxiliar!$D$4:$I$4,0)) -> 0 | AF47: =INDEX(Auxiliar!$D$5:$I$10,MATCH('LISTA - Setembro2024'!AF$3,Auxiliar!$B$5:$B$10,0),MATCH('LISTA - Setembro2024'!$AC47,Auxiliar!$D$4:$I$4,0)) -> 0 | AG47: =IF(OR(AB47="Code List",AB47="Y, N"),AC47,"n.a.") -> n.a. | AH47: =INDEX(Auxiliar!$D$5:$I$10,MATCH('LISTA - Setembro2024'!AH$3,Auxiliar!$B$5:$B$10,0),MATCH('LISTA - Setembro2024'!$AG47,Auxiliar!$D$4:$I$4,0)) -> 0 | AI47: =INDEX(Auxiliar!$D$5:$I$10,MATCH('LISTA - Setembro2024'!AI$3,Auxiliar!$B$5:$B$10,0),MATCH('LISTA - Setembro2024'!$AC47,Auxiliar!$D$4:$I$4,0)) -> 0 | AJ47: =INDEX(Auxiliar!$D$5:$I$10,MATCH('LISTA - Setembro2024'!AJ$3,Auxiliar!$B$5:$B$10,0),MATCH('LISTA - Setembro2024'!$AC47,Auxiliar!$D$4:$I$4,0)) -> 0 | AK47: =SUM(AF47,AH47:AJ47) -> 0 | AL47: internal ratings
A48: EN.045 | B48: =C48&"_"&D48 -> ENTITY_RTNG_SCL | C48: ENTITY | D48: RTNG_SCL | E48: Rating scale | F48: Y | G48: N | H48: N | I48: N | J48: N | K48: Y | L48: =IFERROR(VLOOKUP($B48,'LISTA - Atual'!$B$1:$I$444,5,0),"Novo") -> Y | M48: =IF(L48="Novo","Novo Campo",IF(L48=F48,"Igual","Diferente")) -> Igual | N48: =IFERROR(VLOOKUP($B48,'LISTA - Atual'!$B$1:$I$444,6,0),"Novo") -> N | O48: =IF(N48="Novo","Novo Campo",IF(N48=G48,"Igual","Diferente")) -> Igual | P48: =IFERROR(VLOOKUP($B48,'LISTA - Atual'!$B$1:$I$444,7,0),"Novo") -> N | Q48: =IF(P48="Novo","Novo Campo",IF(P48=H48,"Igual","Diferente")) -> Igual | R48: n/a | S48: =IFERROR(VLOOKUP($B48,'LISTA - Atual'!$B$1:$I$444,8,0),"Novo") -> N | T48: =IF(S48="Novo","Novo Campo",IF(S48=J48,"Igual","Diferente")) -> Igual | U48: n/a | V48: N | W48: =IFERROR(VLOOKUP(B48,#REF!,11,0),"n/a") -> n/a | X48: =IFERROR(VLOOKUP(B48,#REF!,8,0),"n/a") -> n/a | Y48: =$F$2 -> ESTR | Z48: Sem alteração | AA48: =VLOOKUP(Table1[[#This Row],[CONCAT]],'Campos Resumo Prop2.0'!A:H,8,0) -> #N/A | AB48: Code List | AC48: n.a. | AD48: =INDEX(Auxiliar!$D$5:$I$10,MATCH('LISTA - Setembro2024'!AD$3,Auxiliar!$B$5:$B$10,0),MATCH('LISTA - Setembro2024'!$AC48,Auxiliar!$D$4:$I$4,0)) -> 0 | AE48: =INDEX(Auxiliar!$D$5:$I$10,MATCH('LISTA - Setembro2024'!AE$3,Auxiliar!$B$5:$B$10,0),MATCH('LISTA - Setembro2024'!$AC48,Auxiliar!$D$4:$I$4,0)) -> 0 | AF48: =INDEX(Auxiliar!$D$5:$I$10,MATCH('LISTA - Setembro2024'!AF$3,Auxiliar!$B$5:$B$10,0),MATCH('LISTA - Setembro2024'!$AC48,Auxiliar!$D$4:$I$4,0)) -> 0 | AG48: =IF(OR(AB48="Code List",AB48="Y, N"),AC48,"n.a.") -> n.a. | AH48: =INDEX(Auxiliar!$D$5:$I$10,MATCH('LISTA - Setembro2024'!AH$3,Auxiliar!$B$5:$B$10,0),MATCH('LISTA - Setembro2024'!$AG48,Auxiliar!$D$4:$I$4,0)) -> 0 | AI48: =INDEX(Auxiliar!$D$5:$I$10,MATCH('LISTA - Setembro2024'!AI$3,Auxiliar!$B$5:$B$10,0),MATCH('LISTA - Setembro2024'!$AC48,Auxiliar!$D$4:$I$4,0)) -> 0 | AJ48: =INDEX(Auxiliar!$D$5:$I$10,MATCH('LISTA - Setembro2024'!AJ$3,Auxiliar!$B$5:$B$10,0),MATCH('LISTA - Setembro2024'!$AC48,Auxiliar!$D$4:$I$4,0)) -> 0 | AK48: =SUM(AF48,AH48:AJ48) -> 0
A49: EN.046 | B49: =C49&"_"&D49 -> ENTITY_WTCH_LST | C49: ENTITY | D49: WTCH_LST | E49: Debtor on watch-list (Y/N) | F49: Y | G49: N | H49: N | I49: N | J49: N | K49: Y | L49: =IFERROR(VLOOKUP($B49,'LISTA - Atual'!$B$1:$I$444,5,0),"Novo") -> Y | M49: =IF(L49="Novo","Novo Campo",IF(L49=F49,"Igual","Diferente")) -> Igual | N49: =IFERROR(VLOOKUP($B49,'LISTA - Atual'!$B$1:$I$444,6,0),"Novo") -> N | O49: =IF(N49="Novo","Novo Campo",IF(N49=G49,"Igual","Diferente")) -> Igual | P49: =IFERROR(VLOOKUP($B49,'LISTA - Atual'!$B$1:$I$444,7,0),"Novo") -> N | Q49: =IF(P49="Novo","Novo Campo",IF(P49=H49,"Igual","Diferente")) -> Igual | R49: n/a | S49: =IFERROR(VLOOKUP($B49,'LISTA - Atual'!$B$1:$I$444,8,0),"Novo") -> N | T49: =IF(S49="Novo","Novo Campo",IF(S49=J49,"Igual","Diferente")) -> Igual | U49: n/a | V49: N | W49: =IFERROR(VLOOKUP(B49,#REF!,11,0),"n/a") -> n/a | X49: =IFERROR(VLOOKUP(B49,#REF!,8,0),"n/a") -> n/a | Y49: =$F$2 -> ESTR | Z49: Sem alteração | AA49: =VLOOKUP(Table1[[#This Row],[CONCAT]],'Campos Resumo Prop2.0'!A:H,8,0) -> #N/A | AB49: Y, N | AC49: n.a. | AD49: =INDEX(Auxiliar!$D$5:$I$10,MATCH('LISTA - Setembro2024'!AD$3,Auxiliar!$B$5:$B$10,0),MATCH('LISTA - Setembro2024'!$AC49,Auxiliar!$D$4:$I$4,0)) -> 0 | AE49: =INDEX(Auxiliar!$D$5:$I$10,MATCH('LISTA - Setembro2024'!AE$3,Auxiliar!$B$5:$B$10,0),MATCH('LISTA - Setembro2024'!$AC49,Auxiliar!$D$4:$I$4,0)) -> 0 | AF49: =INDEX(Auxiliar!$D$5:$I$10,MATCH('LISTA - Setembro2024'!AF$3,Auxiliar!$B$5:$B$10,0),MATCH('LISTA - Setembro2024'!$AC49,Auxiliar!$D$4:$I$4,0)) -> 0 | AG49: =IF(OR(AB49="Code List",AB49="Y, N"),AC49,"n.a.") -> n.a. | AH49: =INDEX(Auxiliar!$D$5:$I$10,MATCH('LISTA - Setembro2024'!AH$3,Auxiliar!$B$5:$B$10,0),MATCH('LISTA - Setembro2024'!$AG49,Auxiliar!$D$4:$I$4,0)) -> 0 | AI49: =INDEX(Auxiliar!$D$5:$I$10,MATCH('LISTA - Setembro2024'!AI$3,Auxiliar!$B$5:$B$10,0),MATCH('LISTA - Setembro2024'!$AC49,Auxiliar!$D$4:$I$4,0)) -> 0 | AJ49: =INDEX(Auxiliar!$D$5:$I$10,MATCH('LISTA - Setembro2024'!AJ$3,Auxiliar!$B$5:$B$10,0),MATCH('LISTA - Setembro2024'!$AC49,Auxiliar!$D$4:$I$4,0)) -> 0 | AK49: =SUM(AF49,AH49:AJ49) -> 0
A50: EN.047 | B50: =C50&"_"&D50 -> ENTITY_SNGL_PRPS_VHCL | C50: ENTITY | D50: SNGL_PRPS_VHCL | E50: Type of SPV debtor | F50: Y | G50: N | H50: N | I50: N | J50: N | K50: N | L50: =IFERROR(VLOOKUP($B50,'LISTA - Atual'!$B$1:$I$444,5,0),"Novo") -> Y | M50: =IF(L50="Novo","Novo Campo",IF(L50=F50,"Igual","Diferente")) -> Igual | N50: =IFERROR(VLOOKUP($B50,'LISTA - Atual'!$B$1:$I$444,6,0),"Novo") -> N | O50: =IF(N50="Novo","Novo Campo",IF(N50=G50,"Igual","Diferente")) -> Igual | P50: =IFERROR(VLOOKUP($B50,'LISTA - Atual'!$B$1:$I$444,7,0),"Novo") -> N | Q50: =IF(P50="Novo","Novo Campo",IF(P50=H50,"Igual","Diferente")) -> Igual | R50: n/a | S50: =IFERROR(VLOOKUP($B50,'LISTA - Atual'!$B$1:$I$444,8,0),"Novo") -> N | T50: =IF(S50="Novo","Novo Campo",IF(S50=J50,"Igual","Diferente")) -> Igual | U50: n/a | V50: N | W50: =IFERROR(VLOOKUP(B50,#REF!,11,0),"n/a") -> n/a | X50: =IFERROR(VLOOKUP(B50,#REF!,8,0),"n/a") -> n/a | Y50: =$F$2 -> ESTR | Z50: Sem alteração | AA50: =VLOOKUP(Table1[[#This Row],[CONCAT]],'Campos Resumo Prop2.0'!A:H,8,0) -> #N/A | AB50: Code List | AC50: n.a. | AD50: =INDEX(Auxiliar!$D$5:$I$10,MATCH('LISTA - Setembro2024'!AD$3,Auxiliar!$B$5:$B$10,0),MATCH('LISTA - Setembro2024'!$AC50,Auxiliar!$D$4:$I$4,0)) -> 0 | AE50: =INDEX(Auxiliar!$D$5:$I$10,MATCH('LISTA - Setembro2024'!AE$3,Auxiliar!$B$5:$B$10,0),MATCH('LISTA - Setembro2024'!$AC50,Auxiliar!$D$4:$I$4,0)) -> 0 | AF50: =INDEX(Auxiliar!$D$5:$I$10,MATCH('LISTA - Setembro2024'!AF$3,Auxiliar!$B$5:$B$10,0),MATCH('LISTA - Setembro2024'!$AC50,Auxiliar!$D$4:$I$4,0)) -> 0 | AG50: =IF(OR(AB50="Code List",AB50="Y, N"),AC50,"n.a.") -> n.a. | AH50: =INDEX(Auxiliar!$D$5:$I$10,MATCH('LISTA - Setembro2024'!AH$3,Auxiliar!$B$5:$B$10,0),MATCH('LISTA - Setembro2024'!$AG50,Auxiliar!$D$4:$I$4,0)) -> 0 | AI50: =INDEX(Auxiliar!$D$5:$I$10,MATCH('LISTA - Setembro2024'!AI$3,Auxiliar!$B$5:$B$10,0),MATCH('LISTA - Setembro2024'!$AC50,Auxiliar!$D$4:$I$4,0)) -> 0 | AJ50: =INDEX(Auxiliar!$D$5:$I$10,MATCH('LISTA - Setembro2024'!AJ$3,Auxiliar!$B$5:$B$10,0),MATCH('LISTA - Setembro2024'!$AC50,Auxiliar!$D$4:$I$4,0)) -> 0 | AK50: =SUM(AF50,AH50:AJ50) -> 0
A51: EN.048 | B51: =C51&"_"&D51 -> ENTITY_GRP_EBITDA | C51: ENTITY | D51: GRP_EBITDA | E51: Group's EBITDA at most recent reported figures | F51: Y | G51: N | H51: N | I51: N | J51: N | K51: Y | L51: =IFERROR(VLOOKUP($B51,'LISTA - Atual'!$B$1:$I$444,5,0),"Novo") -> Y | M51: =IF(L51="Novo","Novo Campo",IF(L51=F51,"Igual","Diferente")) -> Igual | N51: =IFERROR(VLOOKUP($B51,'LISTA - Atual'!$B$1:$I$444,6,0),"Novo") -> N | O51: =IF(N51="Novo","Novo Campo",IF(N51=G51,"Igual","Diferente")) -> Igual | P51: =IFERROR(VLOOKUP($B51,'LISTA - Atual'!$B$1:$I$444,7,0),"Novo") -> N | Q51: =IF(P51="Novo","Novo Campo",IF(P51=H51,"Igual","Diferente")) -> Igual | R51: n/a | S51: =IFERROR(VLOOKUP($B51,'LISTA - Atual'!$B$1:$I$444,8,0),"Novo") -> N | T51: =IF(S51="Novo","Novo Campo",IF(S51=J51,"Igual","Diferente")) -> Igual | U51: n/a | V51: N | W51: =IFERROR(VLOOKUP(B51,#REF!,11,0),"n/a") -> n/a | X51: =IFERROR(VLOOKUP(B51,#REF!,8,0),"n/a") -> n/a | Y51: =$F$2 -> ESTR | Z51: Sem alteração | AA51: =VLOOKUP(Table1[[#This Row],[CONCAT]],'Campos Resumo Prop2.0'!A:H,8,0) -> #N/A | AB51: FLOAT 2 decimal places | AC51: n.a. | AD51: =INDEX(Auxiliar!$D$5:$I$10,MATCH('LISTA - Setembro2024'!AD$3,Auxiliar!$B$5:$B$10,0),MATCH('LISTA - Setembro2024'!$AC51,Auxiliar!$D$4:$I$4,0)) -> 0 | AE51: =INDEX(Auxiliar!$D$5:$I$10,MATCH('LISTA - Setembro2024'!AE$3,Auxiliar!$B$5:$B$10,0),MATCH('LISTA - Setembro2024'!$AC51,Auxiliar!$D$4:$I$4,0)) -> 0 | AF51: =INDEX(Auxiliar!$D$5:$I$10,MATCH('LISTA - Setembro2024'!AF$3,Auxiliar!$B$5:$B$10,0),MATCH('LISTA - Setembro2024'!$AC51,Auxiliar!$D$4:$I$4,0)) -> 0 | AG51: =IF(OR(AB51="Code List",AB51="Y, N"),AC51,"n.a.") -> n.a. | AH51: =INDEX(Auxiliar!$D$5:$I$10,MATCH('LISTA - Setembro2024'!AH$3,Auxiliar!$B$5:$B$10,0),MATCH('LISTA - Setembro2024'!$AG51,Auxiliar!$D$4:$I$4,0)) -> 0 | AI51: =INDEX(Auxiliar!$D$5:$I$10,MATCH('LISTA - Setembro2024'!AI$3,Auxiliar!$B$5:$B$10,0),MATCH('LISTA - Setembro2024'!$AC51,Auxiliar!$D$4:$I$4,0)) -> 0 | AJ51: =INDEX(Auxiliar!$D$5:$I$10,MATCH('LISTA - Setembro2024'!AJ$3,Auxiliar!$B$5:$B$10,0),MATCH('LISTA - Setembro2024'!$AC51,Auxiliar!$D$4:$I$4,0)) -> 0 | AK51: =SUM(AF51,AH51:AJ51) -> 0
