Workbook
Name asefadf: #REF!
Name bn: #REF!

Sheet Sheet1
A1: LOANS Efectivo y otros depósitos a la vista / Cash balances and other deposits | B1: (All)
A2: LOANS Administraciones públicas / General governments | B2: (All)
A3: LOANS Entidades de crédito / Credit institutions | B3: (All)
A4: LOANS Otras sociedades financieras / Other financial corporations | B4: (All)
A5: LOANS Sociedad no financieras / Non financial corporations | B5: (All)
A6: LOANS Hogares / Households | B6: (All)
A7: DEBT SECURITIES | B7: (All)
A9: Row Labels | B9: Count of Data field
A10: ENTITY | B10: 85
A11: INSTR_ENTITY | B11: 5
A12: INSTR_PROTECTION | B12: 6
A13: INSTRUMENT | B13: 184
A14: PROTECTION | B14: 39
A15: Grand Total | B15: 319

Sheet READ ME - APPLICABILITY
B5: GUIDANCE ON THE APPLICABILITY OF LOAN TAPE' DATA FIELDS
B7: Corporation has performed an assessment of the applicability of data fields considering two axis:
B8: - counterparty sector (central banks, general governments, credit institutions, other financial corporations, non-financial corporations and households) and
B9: - type of product (cash and other demand deposits, debt securities and loans)
B11: As a consequence, within 'Overview' tab, columns F to M (highlighted in red) determine the applicability of data fields, considering the following rules:
B13: Possible values:
B14: - If remarked as 'Y' = Yes, it does apply, those fields might be applicable, depending on the characteristics of each instrument,entity or protection.
B16: - If remarked as 'N' = No, not applicable, it means that given the counterparty sector or the type of product we conclude that this field is not applicable and therefore,
B17: Unit shall informe these fields as 'Not applicable', with the proper format set up for each field (Date: 1111-11-11 ; Text: N/A ; Numeric: 11111111111).
B19: - If remarked as 'Corporation' = Field to be populated by Corporation, it means that the Unit will inform this field as not applicable, with the proper format
B20: set up for each field (Date: 1111-11-11 ; Text: N/A ; Numeric: 11111111111).
B22: Special case for debt securities:
... B24: given that 'Entity' table might be populated with loan information (in almost all cases, we estimate that the issuer of debt securities acquired will have direct exposures - loans as well).

Sheet Overview
A1: ID Data field / Field order | B1: Table | C1: Category | D1: Anacredit | E1: Data field | F1: Efectivo y otros depósitos a la vista / Cash balances and other deposits | G1: Bancos Centrales / Central Banks | H1: Administraciones públicas / General governments | I1: Entidades de crédito / Credit institutions | J1: Otras sociedades financieras / Other financial corporations | K1: Sociedades no financieras / Non financial corporations | L1: Hogares / Households | M1: DEBT SECURITIES (this column only applies to report the instrument table) | N1: Non-contractual balances and Accounting adjustments (this column only applies to report the instrument table) | O1: Instrument cancelled (this column only applies to report the instrument and instrument activity tables) | P1: Data Types | Q1: Guidance on data types | R1: Default value for missing data | S1: Default value for not applicable fields to be used WHEN the field is applicable for the corresponding segment (F to L columns ) | T1: Default value for not applicable fields to be used WHEN: (1) Non-contractual balances and accounting adjustments (2) If the field is not applicable for the corresponding segment (F to L columns) | U1: Field name | V1: Field Definition / Additional Guidance | W1: BDR Status (*) Not applicable = not identified as available in BDR | X1: BDR Definition | Y1: BDR Comments | Z1: Structural ECB Loan Tape | AA1: Green Dashboard | AB1: Pillar III ESG & CSRD | AC1: Green Finance | AD1: ESG Risks | AE1: Leveraged Finance | AF1: D + 15 [Green Dashboard] | AG1: D + 18 [+ Pillar III ESG] | AH1: > D + 18 [+ ECB Loan Tape]
A2: EN.001 | B2: ENTITY | C2: Cargabal entity | D2: N | E2: COD_SOC | F2: Y | G2: Y | H2: Y | I2: Y | J2: Y | K2: Y | L2: Y | P2: VARCHAR2(5) | Q2: Free (latin) text without special characters (semicolon, quotes, …) | R2: Default value not allowed | S2: Default value not allowed | T2: Default value not allowed | U2: Entity code of the informing society. | V2: Cargabal code or internal identifier of the informing society. | W2: Not applicable | X2: N/A | Y2: - | Z2: Y | AA2: N | AB2: Y | AC2: Y | AD2: Y | AE2: Y | AF2: N | AG2: Y | AH2: Y | AI2: =IF(AND(Z2="Y",AA2="Y",AB2="Y",AC2="Y",AD2="Y",AE2="Y"),"Y","")
A3: EN.002 | B3: ENTITY | C3: General | D3: Y | E3: CNTRY | F3: Y | G3: Y | H3: Y | I3: Y | J3: Y | K3: Y | L3: Y | P3: Code list | Q3: Use codes from the code list sheet | R3: MISS | S3: Default value not allowed | T3: N/A | U3: Country of counterparty residence | V3: Country of counterparty residence. | W3: Yes - Mapping | X3: BDR - Code List | Y3: - | Z3: Y | AA3: N | AB3: Y | AC3: Y | AD3: Y | AE3: Y | AF3: N | AG3: Y | AH3: Y | AI3: =IF(AND(Z3="Y",AA3="Y",AB3="Y",AC3="Y",AD3="Y",AE3="Y"),"Y","")
A4: EN.003 | B4: ENTITY | C4: General | D4: Y | E4: DT_BRTH | F4: N | G4: N | H4: N | I4: N | J4: N | K4: Y | L4: Y | P4: DATE | Q4: YYYY-MM-DD | R4: 0000-00-00 | S4: Default value not allowed | T4: 1111-11-11 | U4: Birth date counterparty | V4: Date when the entity was born / registered. | W4: Yes - Equivalent | X4: JM_CLIENT_BII - G4093_FECNACIM | Y4: - | Z4: Y | AA4: N | AB4: N | AC4: N | AD4: N | AE4: N | AF4: N | AG4: N | AH4: Y | AI4: =IF(AND(Z4="Y",AA4="Y",AB4="Y",AC4="Y",AD4="Y",AE4="Y"),"Y","")
A5: EN.004 | B5: ENTITY | C5: General | D5: Y | E5: DT_DFLT_STTS | F5: Y | G5: Y | H5: Y | I5: Y | J5: Y | K5: Y | L5: Y | P5: DATE | Q5: YYYY-MM-DD | R5: 0000-00-00 | S5: 1111-11-11 | T5: 1111-11-11 | U5: Date of default status | V5: The date on which the default status, as reported in the data attribute “Default status”, is considered to have arisen. If "Not in default" since inception then this attribute is to be reported equally to the inception date. If default classification performed on instrument level then Entity is classified as defaulted when at least one instrument is classified as defaulted. If more than one Instrument is classified as defaulted then the earliest date has to be provided. The definition of default is aligned with Art 178 of Regulation (EU) No 575/2013. | W5: Not applicable | X5: N/A | Y5: - | Z5: Y | AA5: N | AB5: N | AC5: N | AD5: N | AE5: Y | AF5: N | AG5: N | AH5: Y | AI5: =IF(AND(Z5="Y",AA5="Y",AB5="Y",AC5="Y",AD5="Y",AE5="Y"),"Y","")
A6: EN.005 | B6: ENTITY | C6: General | D6: N | E6: DT_FNNCL_STTMTS | F6: Y | G6: Y | H6: Y | I6: Y | J6: Y | K6: Y | L6: N | P6: DATE | Q6: YYYY-MM-DD | R6: 0000-00-00 | S6: 1111-11-11 | T6: 1111-11-11 | U6: Date of financial statements | V6: Date of financial statements. Please report on solo entity level unless advised otherwise. | W6: Not applicable | X6: N/A | Y6: - | Z6: Y | AA6: N | AB6: N | AC6: N | AD6: N | AE6: Y | AF6: N | AG6: N | AH6: Y | AI6: =IF(AND(Z6="Y",AA6="Y",AB6="Y",AC6="Y",AD6="Y",AE6="Y"),"Y","")
A7: EN.006 | B7: ENTITY | C7: General | D7: N | E7: DT_FNNCL_STTMTS_PRVS | F7: Y | G7: Y | H7: Y | I7: Y | J7: Y | K7: Y | L7: N | P7: DATE | Q7: YYYY-MM-DD | R7: 0000-00-00 | S7: 1111-11-11 | T7: 1111-11-11 | U7: Date of previous fiscal year financial statements | V7: Date of previous fiscal year financial statements. Please report on solo entity level unless advised otherwise. | W7: Not applicable | X7: N/A | Y7: - | Z7: Y | AA7: N | AB7: N | AC7: N | AD7: N | AE7: Y | AF7: N | AG7: N | AH7: Y | AI7: =IF(AND(Z7="Y",AA7="Y",AB7="Y",AC7="Y",AD7="Y",AE7="Y"),"Y","")
A8: EN.007 | B8: ENTITY | C8: General | D8: Y | E8: DT_INTTN_LGL_PRCDNGS_LE | F8: Y | G8: Y | H8: Y | I8: Y | J8: Y | K8: Y | L8: Y | P8: DATE | Q8: YYYY-MM-DD | R8: 0000-00-00 | S8: 1111-11-11 | T8: 1111-11-11 | U8: Date of initiation of legal proceedings counterparty (LE) | V8: Date of initiation of legal proceedings counterparty (LE). Only for Retail portfolios: The date when the hard collection process was initiated for given entity. If the hard collection process is defined on the level of instrument or protection and more instruments or protections with status "Other legal measures" are linked to the same entity the oldest date is reported. | W8: Yes - Computed | X8: IF E0623_GEST_SIT in (8;9) THEN E0623_FECULTMO | Y8: - | Z8: Y | AA8: N | AB8: N | AC8: N | AD8: N | AE8: Y | AF8: N | AG8: N | AH8: Y | AI8: =IF(AND(Z8="Y",AA8="Y",AB8="Y",AC8="Y",AD8="Y",AE8="Y"),"Y","")
A9: EN.008 | B9: ENTITY | C9: General | D9: N | E9: DT_PRFRMNG_STTS_LE | F9: Y | G9: Y | H9: Y | I9: Y | J9: Y | K9: Y | L9: Y | P9: DATE | Q9: YYYY-MM-DD | R9: 0000-00-00 | S9: 1111-11-11 | T9: 1111-11-11 | U9: Date of performing status | V9: The date at which the latest change of the performing status according to Part 17 of Annex V to Implementing Regulation (EU) No 680/2014 occurred. For entities performing from inception this date should be equal to inception date. | W9: Not applicable | X9: N/A | Y9: - | Z9: Y | AA9: N | AB9: N | AC9: N | AD9: N | AE9: Y | AF9: N | AG9: N | AH9: Y | AI9: =IF(AND(Z9="Y",AA9="Y",AB9="Y",AC9="Y",AD9="Y",AE9="Y"),"Y","")
A10: EN.009 | B10: ENTITY | C10: General | D10: Y | E10: DT_RFRNC | F10: Y | G10: Y | H10: Y | I10: Y | J10: Y | K10: Y | L10: Y | P10: DATE | Q10: YYYY-MM-DD | R10: Default value not allowed | S10: Default value not allowed | T10: Default value not allowed | U10: Reference date. | V10: Reference date. The reference date can refer to end-of-month, end-of-quarter or end-of-year. The value is fixed for the entire loan tape and will be defined and communicated by the Head of Mission. | W10: Not applicable | X10: N/A | Y10: - | Z10: Y | AA10: N | AB10: Y | AC10: Y | AD10: N | AE10: Y | AF10: N | AG10: Y | AH10: Y | AI10: =IF(AND(Z10="Y",AA10="Y",AB10="Y",AC10="Y",AD10="Y",AE10="Y"),"Y","")
A11: EN.010 | B11: ENTITY | C11: General | D11: Y | E11: ENTTY_ID | F11: Y | G11: Y | H11: Y | I11: Y | J11: Y | K11: Y | L11: Y | P11: VARCHAR2(255) | Q11: Free (latin) text without special characters (semicolon, quotes, …) | R11: Default value not allowed | S11: Default value not allowed | T11: Default value not allowed | U11: Entity ID | V11: An identifier applied by the reporting agent to uniquely identify each counterparty. Each counterparty has a unique and exclusive counterparty identifier. This means that this value will not change over time and can never be used as the counterparty identifier for any other counterparty. | W11: Not applicable | X11: N/A | Y11: - | Z11: Y | AA11: N | AB11: Y | AC11: Y | AD11: Y | AE11: Y | AF11: N | AG11: Y | AH11: Y | AI11: =IF(AND(Z11="Y",AA11="Y",AB11="Y",AC11="Y",AD11="Y",AE11="Y"),"Y","")
A12: EN.011 | B12: ENTITY | C12: General | D12: N | E12: GCC_PRNT_ID | F12: Y | G12: Y | H12: Y | I12: Y | J12: Y | K12: Y | L12: N | P12: VARCHAR2(255) | Q12: Free (latin) text without special characters (semicolon, quotes, …) | R12: MISS | S12: N/A | T12: N/A | U12: Identifier for the parent entity of a group of connected clients | V12: The unique identifier of the group of connected clients according to Art 4 para. 39 of Regulation (EU) No 575/2013. If an entity is part of more than one group of connected clients please report the identifier for the most relevant. | W12: Yes - Equivalent | X12: JM_GRUP_ECONO - G5512_GRUP_ECO | Y12: - | Z12: Y | AA12: N | AB12: N | AC12: N | AD12: N | AE12: Y | AF12: N | AG12: N | AH12: Y | AI12: =IF(AND(Z12="Y",AA12="Y",AB12="Y",AC12="Y",AD12="Y",AE12="Y"),"Y","")
A13: EN.012 | B13: ENTITY | C13: General | D13: N | E13: GCC_PRNT_NM | F13: Y | G13: Y | H13: Y | I13: Y | J13: Y | K13: Y | L13: N | P13: VARCHAR2(255) | Q13: Free (latin) text without special characters (semicolon, quotes, …) | R13: MISS | S13: N/A | T13: N/A | U13: Name of the parent entity of a group of connected clients | V13: The name of the group of connected clients according to Art 4 para. 39 of Regulation (EU) No 575/2013. If an entity is part of more than one group of connected clients please report the name for the most relevant. | W13: Yes - Equivalent | X13: JM_GRUP_ECONO - G5512_DGRUPO | Y13: Report Name of the entity reported in EN.011 | Z13: Y | AA13: N | AB13: N | AC13: N | AD13: N | AE13: Y | AF13: N | AG13: N | AH13: Y | AI13: =IF(AND(Z13="Y",AA13="Y",AB13="Y",AC13="Y",AD13="Y",AE13="Y"),"Y","")
... A18: EN.017 | B18: ENTITY | C18: General | D18: N | E18: EXTRNL_RTNG_NM | F18: Y | G18: Y | H18: Y | I18: Y | J18: Y | K18: Y | L18: N | P18: VARCHAR2(255) | Q18: Free (latin) text without special characters (semicolon, quotes, …) | R18: MISS | S18: N/A | T18: N/A | U18: Name of external rating agency | V18: Name of external rating agency for the external rating at the reference date. | W18: Yes - Equivalent | X18: JM_CAL_EXT_CL - R9415_COD_AGEN | Y18: - | Z18: Y | AA18: N | AB18: N | AC18: N | AD18: N | AE18: Y | AF18: N | AG18: N | AH18: Y | AI18: =IF(AND(Z18="Y",AA18="Y",AB18="Y",AC18="Y",AD18="Y",AE18="Y"),"Y","")
A19: EN.018 | B19: ENTITY | C19: Classification | D19: Y | E19: ACCNTNG_FRMWRK_SL | F19: Y | G19: Y | H19: Y | I19: Y | J19: Y | K19: Y | L19: N | P19: =HYPERLINK("#"&"CodeList!"&ADDRESS(2,MATCH($E19,CodeList!$2:$2,0)+1,),"Code List") -> Code List | Q19: Use codes from the code list sheet | R19: 99999999999 | S19: 11111111111 | T19: 11111111111 | U19: Accounting standard counterparty | V19: Accounting standard counterparty. | W19: Not applicable | X19: N/A | Y19: - | Z19: Y | AA19: N | AB19: N | AC19: N | AD19: N | AE19: Y | AF19: N | AG19: N | AH19: Y | AI19: =IF(AND(Z19="Y",AA19="Y",AB19="Y",AC19="Y",AD19="Y",AE19="Y"),"Y","")
A20: EN.019 | B20: ENTITY | C20: Classification | D20: N | E20: CR_FLG | F20: Y | G20: Y | H20: Y | I20: Y | J20: Y | K20: Y | L20: Y | P20: Y, N | Q20: Boolean: Y/N | R20: MISS | S20: N/A | T20: N/A | U20: Cure flag for entity which was classified as non-performing in the last 1.5 years and is classified as performing at the reference date | V20: The entity is to be classified on the reference date under one of the following categories: performing or non-performing, in accordance with Annex V to Implementing Regulation (EU) No 680/2014. | W20: Yes - Computed | X20: IF H0883_IND_CURA = 1 THEN T; ELSE IF H0883_IND_CURA = 0 THEN F; THEN N/A | Y20: - | Z20: Y | AA20: N | AB20: N | AC20: N | AD20: N | AE20: N | AF20: N | AG20: N | AH20: Y | AI20: =IF(AND(Z20="Y",AA20="Y",AB20="Y",AC20="Y",AD20="Y",AE20="Y"),"Y","")
A21: EN.020 | B21: ENTITY | C21: Classification | D21: N | E21: DCSD | F21: N | G21: N | H21: N | I21: N | J21: N | K21: N | L21: Y | P21: Y, N | Q21: Boolean: Y/N | R21: MISS | S21: N/A | T21: N/A | U21: Entity deceased | V21: Indicator as to whether the Entity has passed away. The data attribute is applicable to natural persons only. | W21: Not applicable | X21: N/A | Y21: - | Z21: Y | AA21: N | AB21: N | AC21: N | AD21: N | AE21: N | AF21: N | AG21: N | AH21: Y | AI21: =IF(AND(Z21="Y",AA21="Y",AB21="Y",AC21="Y",AD21="Y",AE21="Y"),"Y","")
A22: EN.021 | B22: ENTITY | C22: Classification | D22: Y | E22: DFLT_STTS | F22: Y | G22: Y | H22: Y | I22: Y | J22: Y | K22: Y | L22: Y | P22: =HYPERLINK("#"&"CodeList!"&ADDRESS(2,MATCH($E22,CodeList!$2:$2,0)+1,),"Code List") -> Code List | Q22: Use codes from the code list sheet | R22: 99999999999 | S22: 11111111111 | T22: 11111111111 | U22: Default status of the entity | V22: Identification of the default status of the counterparty. Categories describing the motives for which the counterparty can be in default in accordance with Article 178 of Regulation (EU) No 575/2013. For retail only: If default classification performed on instrument level then Entity is classified as defaulted when at least one instrument is classified as defaulted. For corporate, SME, CRE and LF: if default classification performed on instrument level then entity level is "not applicable". | W22: Not applicable | X22: N/A | Y22: - | Z22: Y | AA22: N | AB22: N | AC22: N | AD22: N | AE22: Y | AF22: N | AG22: N | AH22: Y | AI22: =IF(AND(Z22="Y",AA22="Y",AB22="Y",AC22="Y",AD22="Y",AE22="Y"),"Y","")
A23: EN.022 | B23: ENTITY | C23: Classification | D23: N | E23: DT_EXTRNL_RTNG | F23: Y | G23: Y | H23: Y | I23: Y | J23: Y | K23: Y | L23: N | P23: DATE | Q23: YYYY-MM-DD | R23: 0000-00-00 | S23: 1111-11-11 | T23: 1111-11-11 | U23: Date of external rating | V23: Date of the most recent external rating, i.e. applicable at the reference date. | W23: Yes - Equivalent | X23: JM_CAL_EXT_CL - R9415_FECCALIF | Y23: - | Z23: Y | AA23: N | AB23: N | AC23: N | AD23: N | AE23: Y | AF23: N | AG23: N | AH23: Y | AI23: =IF(AND(Z23="Y",AA23="Y",AB23="Y",AC23="Y",AD23="Y",AE23="Y"),"Y","")
A24: EN.023 | B24: ENTITY | C24: Classification | D24: N | E24: DT_INTRNL_RTNG | F24: Y | G24: Y | H24: Y | I24: Y | J24: Y | K24: Y | L24: Y | P24: DATE | Q24: YYYY-MM-DD | R24: 0000-00-00 | S24: 1111-11-11 | T24: 1111-11-11 | U24: Date of internal rating | V24: Date of the most recent internal rating according to Regulation (EU) No 575/2013, i.e. applicable rating as at the reference date. If the rating is assigned on instrument level then provide the rating for the instrument with the highest EAD. | W24: Yes - Equivalent | X24: JM_CAL_IN_CL - E9954_FECCALI | Y24: - | Z24: Y | AA24: N | AB24: N | AC24: N | AD24: N | AE24: Y | AF24: N | AG24: N | AH24: Y | AI24: =IF(AND(Z24="Y",AA24="Y",AB24="Y",AC24="Y",AD24="Y",AE24="Y"),"Y","")
A25: EN.024 | B25: ENTITY | C25: Classification | D25: Y | E25: ECNMC_ACTVTY | F25: N | G25: Y | H25: Y | I25: Y | J25: Y | K25: Y | L25: N | P25: Code list | Q25: Use codes from the code list sheet | R25: MISS | S25: N/A | T25: N/A | U25: Economic activity counterparty | V25: The level four NACE code in accordance with Regulation (EC) No 1893/2006 is generally reported. If the level four NACE code is not available it may be allowed to report a level three or level two NACE code. | W25: Not applicable | X25: N/A | Y25: - | Z25: Y | AA25: N | AB25: Y | AC25: Y | AD25: Y | AE25: Y | AF25: N | AG25: Y | AH25: Y | AI25: =IF(AND(Z25="Y",AA25="Y",AB25="Y",AC25="Y",AD25="Y",AE25="Y"),"Y","")
A26: EN.025 | B26: ENTITY | C26: Classification | D26: N | E26: EMPLYMNT_STTS_INTRNL | F26: N | G26: N | H26: N | I26: N | J26: N | K26: N | L26: Y | P26: VARCHAR2(255) | Q26: Free (latin) text without special characters (semicolon, quotes, …) | R26: MISS | S26: N/A | T26: N/A | U26: Employment status according to bank-internal classification | V26: Employment status according to bank-internal classification. | W26: Not applicable | X26: N/A | Y26: - | Z26: Y | AA26: N | AB26: N | AC26: N | AD26: N | AE26: N | AF26: N | AG26: N | AH26: Y | AI26: =IF(AND(Z26="Y",AA26="Y",AB26="Y",AC26="Y",AD26="Y",AE26="Y"),"Y","")
A27: EN.026 | B27: ENTITY | C27: Classification | D27: N | E27: EMPLYMNT_STTS | F27: N | G27: N | H27: N | I27: N | J27: N | K27: N | L27: Y | P27: =HYPERLINK("#"&"CodeList!"&ADDRESS(2,MATCH($E27,CodeList!$2:$2,0)+1,),"Code List") -> Code List | Q27: Use codes from the code list sheet | R27: 99999999999 | S27: 11111111111 | T27: 11111111111 | U27: Employment status (Code List) | V27: Employment status. | W27: Not applicable | X27: N/A | Y27: - | Z27: Y | AA27: N | AB27: N | AC27: N | AD27: N | AE27: N | AF27: N | AG27: N | AH27: Y | AI27: =IF(AND(Z27="Y",AA27="Y",AB27="Y",AC27="Y",AD27="Y",AE27="Y"),"Y","")
A28: EN.027 | B28: ENTITY | C28: Classification | D28: Y | E28: ENTRPRS_SZ_LE | F28: N | G28: N | H28: N | I28: N | J28: N | K28: Y | L28: N | P28: =HYPERLINK("#"&"CodeList!"&ADDRESS(2,MATCH($E28,CodeList!$2:$2,0)+1,),"Code List") -> Code List | Q28: Use codes from the code list sheet | R28: 99999999999 | S28: 11111111111 | T28: 11111111111 | U28: Enterprise size Counterparty (LE) | V28: Enterprise size counterparty (LE). Classification of enterprises by size, in accordance with the Annex to Commission Recommendation 2003/361/EC. However, if the local NCB decides not to request this attribute as part of the AnaC reporting data set then please report "Not applicable". | W28: Yes - Computed | X28: IF ((G5508_NUM_EMPL IS <250 AND >=50) AND ((G5508_IMPFACTM <=50MM) OR (G5508_TOT_ACTI<=43MM))) THEN 2; ELSE IF ((G5508_NUM_EMPL IS <50 AND >=10) AND ((G5508_IMPFACTM <=10MM) OR (G5508_TOT_ACTI<=10MM))) THEN 3; ELSE IF ((G5508_NUM_EMPL IS <10) AND ((G5508_IMPFACTM <=2MM) OR (G5508_TOT_ACTI<=2MM))) THEN 4; ELSE 1 | Y28: - | Z28: Y | AA28: N | AB28: N | AC28: N | AD28: N | AE28: N | AF28: N | AG28: N | AH28: Y | AI28: =IF(AND(Z28="Y",AA28="Y",AB28="Y",AC28="Y",AD28="Y",AE28="Y"),"Y","")
A29: EN.028 | B29: ENTITY | C29: Classification | D29: N | E29: EXTRNL_RTNG | F29: Y | G29: Y | H29: Y | I29: Y | J29: Y | K29: Y | L29: N | P29: Code List | Q29: Use codes from the code list sheet | R29: 99999999999 | S29: 11111111111 | T29: 11111111111 | U29: External rating | V29: External rating at the reference date. | W29: Yes - Computed | X29: R9415_CALIFMAE following the conditions: 1) In those cases in which more than one ECAI provides an external rating: - Where two credit assessments are available from nominated ECAIs and the two correspond to different risk weights for a rated item, the higher risk weight shall be assigned - Where more than two credit assessments are available from nominated ECAIs for a rated item, the two assessments generating the two lowest risk weights shall be referred to. If the two lowest risk weights are different, the higher risk weight shall be assigned. If the two lowest risk weights are the same, that risk weight shall be assigned 2) If the rating is not available, the unit should report “99999999999” in the Loan Tape. In case, for example, of exposures calculated under the IRB approach, where the external rating does not apply, the expected value is “11111111111” 3) If the client was not part of any applicable portfolio in the prior year, the value informed should be “11111111111”, as not applicable | Y29: - | Z29: Y | AA29: N | AB29: N | AC29: N | AD29: N | AE29: Y | AF29: N | AG29: N | AH29: Y | AI29: =IF(AND(Z29="Y",AA29="Y",AB29="Y",AC29="Y",AD29="Y",AE29="Y"),"Y","")
A30: EN.029 | B30: ENTITY | C30: Classification | D30: N | E30: EXTRNL_RTNG_PRVS | F30: Y | G30: Y | H30: Y | I30: Y | J30: Y | K30: Y | L30: N | P30: Code List | Q30: Use codes from the code list sheet | R30: 99999999999 | S30: 11111111111 | T30: 11111111111 | U30: External rating T-1 | V30: External rating one year prior to the reference date. | W30: Yes - Computed | X30: R9415_CALIFMAE having R9415_CALIFMAE one year prior to the reference date and following the conditions: 1) In those cases in which more than one ECAI provides an external rating: - Where two credit assessments are available from nominated ECAIs and the two correspond to different risk weights for a rated item, the higher risk weight shall be assigned - Where more than two credit assessments are available from nominated ECAIs for a rated item, the two assessments generating the two lowest risk weights shall be referred to. If the two lowest risk weights are different, the higher risk weight shall be assigned. If the two lowest risk weights are the same, that risk weight shall be assigned 2) If the rating is not available, the unit should report “99999999999” in the Loan Tape. In case, for example, of exposures calculated under the IRB approach, where the external rating does not apply, the expected value is “11111111111” 3) If the client was not part of any applicable portfolio in the prior year, the value informed should be “11111111111”, as not applicable | Y30: - | Z30: Y | AA30: N | AB30: N | AC30: N | AD30: N | AE30: Y | AF30: N | AG30: N | AH30: Y | AI30: =IF(AND(Z30="Y",AA30="Y",AB30="Y",AC30="Y",AD30="Y",AE30="Y"),"Y","")
A31: EN.030 | B31: ENTITY | C31: Classification | D31: N | E31: FLG_BNKRPTCY_IN_GRP | F31: N | G31: Y | H31: Y | I31: Y | J31: Y | K31: Y | L31: N | P31: Y, N | Q31: Boolean: Y/N | R31: MISS | S31: N/A | T31: N/A | U31: Any legal entity within the group of connected clients of the debtor (incl. subsidiaries of the debtor) has filed bankruptcy application | V31: Report "Y' if any legal entity within the group of connected clients of the debtor (incl. subsidiaries of the debtor) has filed bankruptcy application according to local insolvency law. | W31: Yes - Computed | X31: IF G4093_UTP_CLI = 00001 for any of the related clientes (necessary to identify the Group of the cliente (E1963_GRUP_ECO) and then all the connected clients (E1963_IDNUMCLI) for this Group) THEN Y; ELSE N | Y31: - | Z31: Y | AA31: N | AB31: N | AC31: N | AD31: N | AE31: N | AF31: N | AG31: N | AH31: Y | AI31: =IF(AND(Z31="Y",AA31="Y",AB31="Y",AC31="Y",AD31="Y",AE31="Y"),"Y","")
A32: EN.031 | B32: ENTITY | C32: Classification | D32: N | E32: FLG_HGH_CDS | F32: Y | G32: Y | H32: Y | I32: Y | J32: Y | K32: Y | L32: N | P32: Y, N | Q32: Boolean: Y/N | R32: MISS | S32: N/A | T32: N/A | U32: 5Y CDS > 1,000bps over the last 12 months | V32: Report "Y" if 5Y CDS > 1,000bps over the last 12 months. The flag would be required to be reported "Y" if the 5y CDS spread of a debtor is at least once greater or equal 1000bps within the last 12 months. | W32: Not applicable | X32: N/A | Y32: - | Z32: Y | AA32: N | AB32: N | AC32: N | AD32: N | AE32: N | AF32: N | AG32: N | AH32: Y | AI32: =IF(AND(Z32="Y",AA32="Y",AB32="Y",AC32="Y",AD32="Y",AE32="Y"),"Y","")
A33: EN.032 | B33: ENTITY | C33: Classification | D33: N | E33: FLG_ISDA_CRDT_EVNT | F33: Y | G33: Y | H33: Y | I33: Y | J33: Y | K33: Y | L33: N | P33: Y, N | Q33: Boolean: Y/N | R33: MISS | S33: N/A | T33: N/A | U33: ISDA credit event declared | V33: The flag would be required to be reported "Y" if a credit event occurred under any ISDA master agreement associated with this debtor. | W33: Not applicable | X33: N/A | Y33: - | Z33: Y | AA33: N | AB33: N | AC33: N | AD33: N | AE33: N | AF33: N | AG33: N | AH33: Y | AI33: =IF(AND(Z33="Y",AA33="Y",AB33="Y",AC33="Y",AD33="Y",AE33="Y"),"Y","")
A34: EN.033 | B34: ENTITY | C34: Classification | D34: N | E34: FLG_NN_ACCRL | F34: N | G34: N | H34: N | I34: N | J34: N | K34: Y | L34: Y | P34: Y, N | Q34: Boolean: Y/N | R34: MISS | S34: N/A | T34: N/A | U34: Credit obligation on non-accrual status | V34: Report "Y" if any credit obligation associated to this debtor is set on non-accrual status. | W34: Not applicable | X34: N/A | Y34: - | Z34: Y | AA34: N | AB34: N | AC34: N | AD34: N | AE34: N | AF34: N | AG34: N | AH34: Y | AI34: =IF(AND(Z34="Y",AA34="Y",AB34="Y",AC34="Y",AD34="Y",AE34="Y"),"Y","")
A35: EN.034 | B35: ENTITY | C35: Classification | D35: N | E35: FLG_RQST_BNKRPTCY | F35: N | G35: Y | H35: Y | I35: Y | J35: Y | K35: Y | L35: N | P35: Y, N | Q35: Boolean: Y/N | R35: MISS | S35: N/A | T35: N/A | U35: Request by the institution for the obligor's bankruptcy | V35: Flag "Y" if bankruptcy proceedings have been initiated by the bank according to local insolvency law, e.g. due to illiquidity, over-indebtedness. | W35: Not applicable | X35: N/A | Y35: - | Z35: Y | AA35: N | AB35: N | AC35: N | AD35: N | AE35: N | AF35: N | AG35: N | AH35: Y | AI35: =IF(AND(Z35="Y",AA35="Y",AB35="Y",AC35="Y",AD35="Y",AE35="Y"),"Y","")
A36: EN.035 | B36: ENTITY | C36: Classification | D36: N | E36: FLG_RQST_DSTRSSD_RSTRCTRNG | F36: N | G36: N | H36: N | I36: N | J36: N | K36: Y | L36: Y | P36: Y, N | Q36: Boolean: Y/N | R36: MISS | S36: N/A | T36: N/A | U36: Request for current concession of forbearance measures as defined in EBA/ITS/2013/03 resulting in distressed restructuring of the credit obligation | V36: Report "Y" if there is a request for current concession of forbearance measures as defined in EBA/ITS/2013/03 resulting in distressed restructuring of the credit obligation. | W36: Not applicable | X36: N/A | Y36: - | Z36: Y | AA36: N | AB36: N | AC36: N | AD36: N | AE36: N | AF36: N | AG36: N | AH36: Y | AI36: =IF(AND(Z36="Y",AA36="Y",AB36="Y",AC36="Y",AD36="Y",AE36="Y"),"Y","")
A37: EN.036 | B37: ENTITY | C37: Classification | D37: N | E37: FLG_RQST_EMRGNCY_FNDNG | F37: N | G37: N | H37: N | I37: N | J37: Y | K37: Y | L37: Y | P37: Y, N | Q37: Boolean: Y/N | R37: MISS | S37: Default value not allowed | T37: N/A | U37: Request by the debtor for emergency funding from the bank | V37: Report "Y" if there is a request by the debtor for emergency funding from the bank. | W37: Not applicable | X37: N/A | Y37: - | Z37: Y | AA37: N | AB37: N | AC37: N | AD37: N | AE37: Y | AF37: N | AG37: N | AH37: Y | AI37: =IF(AND(Z37="Y",AA37="Y",AB37="Y",AC37="Y",AD37="Y",AE37="Y"),"Y","")
A38: EN.037 | B38: ENTITY | C38: Classification | D38: N | E38: FLG_SLL_WTH_LSS | F38: N | G38: Y | H38: Y | I38: Y | J38: Y | K38: Y | L38: N | P38: Y, N | Q38: Boolean: Y/N | R38: MISS | S38: N/A | T38: N/A | U38: Sell of a credit obligation with material credit related economic loss (>= 5%) | V38: Report "Y" if there is a sell of a credit obligation with material credit related economic loss (>= 5%) according to EBA/GL/2016/07 para 44. | W38: Yes - Computed | X38: IF T2437_SITGESND = 23 THEN Y; ELSE N | Y38: - | Z38: Y | AA38: N | AB38: N | AC38: N | AD38: N | AE38: N | AF38: N | AG38: N | AH38: Y | AI38: =IF(AND(Z38="Y",AA38="Y",AB38="Y",AC38="Y",AD38="Y",AE38="Y"),"Y","")
A39: EN.038 | B39: ENTITY | C39: Classification | D39: N | E39: INCM_SC | F39: N | G39: N | H39: N | I39: N | J39: N | K39: N | L39: Y | P39: Y, N | Q39: Boolean: Y/N | R39: MISS | S39: N/A | T39: N/A | U39: Income self-certified | V39: The data field applicable to natural persons only should be flagged "Y" if the counterpart has no other source of income certification than its own personal declaration, e.g. absence of payroll or tax declaration forms. | W39: Yes - Computed | X39: IF H0780_INGCLIEN is informed and H0780_FLGACSLD = 1 THEN Y; ELSE N | Y39: - | Z39: Y | AA39: N | AB39: N | AC39: N | AD39: N | AE39: N | AF39: N | AG39: N | AH39: Y | AI39: =IF(AND(Z39="Y",AA39="Y",AB39="Y",AC39="Y",AD39="Y",AE39="Y"),"Y","")
A40: EN.039 | B40: ENTITY | C40: Classification | D40: N | E40: INTRNL_RTNG | F40: Y | G40: Y | H40: Y | I40: Y | J40: Y | K40: Y | L40: Y | P40: =HYPERLINK("#"&"CodeList!"&ADDRESS(2,MATCH($E40,CodeList!$2:$2,0)+1,),"Code List") -> Code List | Q40: Use codes from the code list sheet | R40: MISS | S40: N/A | T40: N/A | U40: Internal rating at reference date | V40: Internal rating at the reference date according to Regulation (EU) No 575/2013. Please also add in sheet "Code List" the list of values used, i.e. bank-internal masterscale. | W40: Not applicable | X40: N/A | Y40: - | Z40: Y | AA40: N | AB40: N | AC40: N | AD40: N | AE40: Y | AF40: N | AG40: N | AH40: Y | AI40: =IF(AND(Z40="Y",AA40="Y",AB40="Y",AC40="Y",AD40="Y",AE40="Y"),"Y","")
A41: EN.040 | B41: ENTITY | C41: Classification | D41: N | E41: INTRNL_RTNG_PRVS | F41: Y | G41: Y | H41: Y | I41: Y | J41: Y | K41: Y | L41: Y | P41: =HYPERLINK("#"&"CodeList!"&ADDRESS(2,MATCH($E41,CodeList!$2:$2,0)+1,),"Code List") -> Code List | Q41: Use codes from the code list sheet | R41: MISS | S41: N/A | T41: N/A | U41: Previous internal rating | V41: Internal rating according to Regulation (EU) No 575/2013 one year prior to the reference date. | W41: Not applicable | X41: N/A | Y41: - | Z41: Y | AA41: N | AB41: N | AC41: N | AD41: N | AE41: Y | AF41: N | AG41: N | AH41: Y | AI41: =IF(AND(Z41="Y",AA41="Y",AB41="Y",AC41="Y",AD41="Y",AE41="Y"),"Y","")
A42: EN.041 | B42: ENTITY | C42: Classification | D42: Y | E42: LGL_PRCDNG_STTS_LE | F42: Y | G42: Y | H42: Y | I42: Y | J42: Y | K42: Y | L42: Y | P42: =HYPERLINK("#"&"CodeList!"&ADDRESS(2,MATCH($E42,CodeList!$2:$2,0)+1,),"Code List") -> Code List | Q42: Use codes from the code list sheet | R42: 99999999999 | S42: Default value not allowed | T42: Default value not allowed | U42: Legal proceedings status Counterparty (LE) | V42: Legal proceedings status Counterparty (LE). Only for Retail portfolios: Status "No legal action taken" or "Other legal measures" are possible. Status "Other legal measures" is reported when the hard collection process was initiated at the level of a given entity or at the level of any associated instrument or protection of this entity. | W42: Yes - Computed | X42: IF T1824_GEST_SIT in (8) THEN LGL_PRCDNG_STTS = 2; ELSE IF G4093_UTP_CLI = 00001 THEN 3; ELSE 1 | Y42: - | Z42: Y | AA42: N | AB42: N | AC42: N | AD42: N | AE42: Y | AF42: N | AG42: N | AH42: Y | AI42: =IF(AND(Z42="Y",AA42="Y",AB42="Y",AC42="Y",AD42="Y",AE42="Y"),"Y","")
A43: EN.042 | B43: ENTITY | C43: Classification | D43: N | E43: OWND_BY_SPNSR | F43: N | G43: N | H43: N | I43: N | J43: Y | K43: Y | L43: N | P43: Y, N | Q43: Boolean: Y/N | R43: MISS | S43: N/A | T43: N/A | U43: >50% owned by a sponsor as per ECB Guidance on leveraged transactions | V43: In accordance the ECB Guidance on Leveraged Transactions. As per point (37) of Article 4(1) of Regulation (EU) No 575/2013, a financial sponsor is deemed to be the owner if it controls or owns more than 50% of the borrower’s equity. The term “financial sponsor” refers to an investment firm that undertakes private equity investments in and/or leveraged buyouts of companies with the intention of exiting those investments on a mediumterm basis | W43: Not applicable | X43: N/A | Y43: - | Z43: Y | AA43: N | AB43: N | AC43: N | AD43: N | AE43: Y | AF43: N | AG43: N | AH43: Y | AI43: =IF(AND(Z43="Y",AA43="Y",AB43="Y",AC43="Y",AD43="Y",AE43="Y"),"Y","")
A44: EN.043 | B44: ENTITY | C44: Classification | D44: N | E44: PRFRMNG_STTS_LE | F44: Y | G44: Y | H44: Y | I44: Y | J44: Y | K44: Y | L44: Y | P44: =HYPERLINK("#"&"CodeList!"&ADDRESS(2,MATCH($E44,CodeList!$2:$2,0)+1,),"Code List") -> Code List | Q44: Use codes from the code list sheet | R44: 99999999999 | S44: 11111111111 | T44: 11111111111 | U44: Performing status | V44: Performing status. Identification of the performing status of the counterparty. Categories describing the motives for which the counterparty can be non-performing in accordance with Implementing Technical Standard (ITS) on Supervisory Reporting (Forbearance and non-performing exposures). For retail only: If performing classification performed on instrument level then Entity is classified as non-performing when at least one instrument is classified as non-performing For corporate, SME, CRE and LF: if default classification performed on instrument level then entity level is "not applicable". | W44: Not applicable | X44: N/A | Y44: - | Z44: Y | AA44: N | AB44: N | AC44: N | AD44: N | AE44: Y | AF44: N | AG44: N | AH44: Y | AI44: =IF(AND(Z44="Y",AA44="Y",AB44="Y",AC44="Y",AD44="Y",AE44="Y"),"Y","")
A45: EN.044 | B45: ENTITY | C45: Classification | D45: N | E45: RTNG_MTHD | F45: Y | G45: Y | H45: Y | I45: Y | J45: Y | K45: Y | L45: Y | P45: =HYPERLINK("#"&"CodeList!"&ADDRESS(2,MATCH($E45,CodeList!$2:$2,0)+1,),"Code List") -> Code List | Q45: Use codes from the code list sheet | R45: 99999999999 | S45: 11111111111 | T45: 11111111111 | U45: Rating method | V45: Internal definition and name of the rating/scoring model. | W45: Yes - Equivalent | X45: JM_CAL_IN_CL - E9954_TIPMODEL | Y45: - | Z45: Y | AA45: N | AB45: N | AC45: N | AD45: N | AE45: Y | AF45: N | AG45: N | AH45: Y | AI45: =IF(AND(Z45="Y",AA45="Y",AB45="Y",AC45="Y",AD45="Y",AE45="Y"),"Y","")
A46: EN.045 | B46: ENTITY | C46: Classification | D46: N | E46: RTNG_SCL | F46: Corporation | G46: Corporation | H46: Corporation | I46: Corporation | J46: Corporation | K46: Corporation | L46: Corporation | P46: =HYPERLINK("#"&"CodeList!"&ADDRESS(2,MATCH($E46,CodeList!$2:$2,0)+1,),"Code List") -> Code List | Q46: Use codes from the code list sheet | R46: 99999999999 | S46: 11111111111 | T46: 11111111111 | U46: Rating scale | V46: Internal name and definition of the rating master scale. It should be mapped to the assigned rating, i.e. INTRNL_RTNG. | W46: Not applicable | X46: N/A | Y46: - | Z46: Y | AA46: N | AB46: N | AC46: N | AD46: N | AE46: Y | AF46: N | AG46: N | AH46: Y | AI46: =IF(AND(Z46="Y",AA46="Y",AB46="Y",AC46="Y",AD46="Y",AE46="Y"),"Y","")
A47: EN.046 | B47: ENTITY | C47: Classification | D47: N | E47: WTCH_LST | F47: N | G47: Y | H47: Y | I47: Y | J47: Y | K47: Y | L47: Y | P47: Y, N | Q47: Boolean: Y/N | R47: MISS | S47: N/A | T47: N/A | U47: Debtor on watch-list (Y/N) | V47: Report "Y" when the debtor has been added to an internal watch list. | W47: Yes - Computed | X47: IF R8182_EST_FEVE in (02;03;04;05;06;08) THEN Y; ELSE N | Y47: - | Z47: Y | AA47: N | AB47: N | AC47: N | AD47: N | AE47: Y | AF47: N | AG47: N | AH47: Y | AI47: =IF(AND(Z47="Y",AA47="Y",AB47="Y",AC47="Y",AD47="Y",AE47="Y"),"Y","")
A48: EN.047 | B48: ENTITY | C48: Classification | D48: N | E48: SNGL_PRPS_VHCL | F48: N | G48: N | H48: N | I48: N | J48: N | K48: Y | L48: N | P48: =HYPERLINK("#"&"CodeList!"&ADDRESS(2,MATCH($E48,CodeList!$2:$2,0)+1,),"Code List") -> Code List | Q48: Use codes from the code list sheet | R48: 99999999999 | S48: 11111111111 | T48: 11111111111 | U48: Type of SPV debtor | V48: In the CRE development business the debtor can be either a 'SPV with recourse' or a 'SPV without recourse' or an 'Other type of entity'. | W48: Not applicable | X48: N/A | Y48: - | Z48: Y | AA48: N | AB48: N | AC48: N | AD48: N | AE48: N | AF48: N | AG48: N | AH48: Y | AI48: =IF(AND(Z48="Y",AA48="Y",AB48="Y",AC48="Y",AD48="Y",AE48="Y"),"Y","")
A49: EN.048 | B49: ENTITY | C49: Financial Information | D49: N | E49: GRP_EBITDA | F49: Y | G49: Y | H49: Y | I49: Y | J49: Y | K49: Y | L49: N | P49: FLOAT 2 decimal places | Q49: Use decimal point, no thousands seperator | R49: 99999999999 | S49: 11111111111 | T49: 11111111111 | U49: Group's EBITDA at most recent reported figures | V49: EBITDA at latest reported figures. Please report level of the consolidated financial statement of the group accoding to the applicable accounting standard. | W49: Not applicable | X49: N/A | Y49: - | Z49: Y | AA49: N | AB49: N | AC49: N | AD49: N | AE49: Y | AF49: N | AG49: N | AH49: Y | AI49: =IF(AND(Z49="Y",AA49="Y",AB49="Y",AC49="Y",AD49="Y",AE49="Y"),"Y","")
A50: EN.049 | B50: ENTITY | C50: Financial Information | D50: N | E50: GRP_EQTY | F50: Y | G50: Y | H50: Y | I50: Y | J50: Y | K50: Y | L50: N | P50: FLOAT 2 decimal places | Q50: Use decimal point, no thousands seperator | R50: 99999999999 | S50: 11111111111 | T50: 11111111111 | U50: Group's equity at most recent reported figures | V50: Equity at most recent reported figures. Please report level of the consolidated financial statement of the group accoding to the applicable accounting standard. | W50: Not applicable | X50: N/A | Y50: - | Z50: Y | AA50: N | AB50: Y | AC50: N | AD50: N | AE50: Y | AF50: N | AG50: Y | AH50: Y | AI50: =IF(AND(Z50="Y",AA50="Y",AB50="Y",AC50="Y",AD50="Y",AE50="Y"),"Y","")
A51: EN.050 | B51: ENTITY | C51: Financial Information | D51: N | E51: GRP_NT_DBT | F51: Y | G51: Y | H51: Y | I51: Y | J51: Y | K51: Y | L51: N | P51: FLOAT 2 decimal places | Q51: Use decimal point, no thousands seperator | R51: 99999999999 | S51: 11111111111 | T51: 11111111111 | U51: Total net debt at most recent reported figures | V51: Total net debt at most recent reported figures. Please report level of the consolidated financial statement of the group accoding to the applicable accounting standard. | W51: Not applicable | X51: N/A | Y51: - | Z51: Y | AA51: N | AB51: N | AC51: N | AD51: N | AE51: Y | AF51: N | AG51: N | AH51: Y | AI51: =IF(AND(Z51="Y",AA51="Y",AB51="Y",AC51="Y",AD51="Y",AE51="Y"),"Y","")
A52: EN.051 | B52: ENTITY | C52: Financial Information | D52: Y | E52: ANNL_TRNVR_LE | F52: Y | G52: Y | H52: Y | I52: Y | J52: Y | K52: Y | L52: N | P52: FLOAT 2 decimal places | Q52: Use decimal point, no thousands seperator | R52: 99999999999 | S52: 11111111111 | T52: 11111111111 | U52: Annual turnover counterparty (LE) | V52: Annual sales volume net of all discounts and sales taxes in accordance with Recommendation 2003/361/EC. Equivalent to the concept of 'total annual sales' in Article 153(4) of Regulation (EU) No 575/2013. Please report on solo entity level unless advised otherwise. | W52: Not applicable | X52: N/A | Y52: - | Z52: Y | AA52: N | AB52: Y | AC52: N | AD52: N | AE52: Y | AF52: N | AG52: Y | AH52: Y | AI52: =IF(AND(Z52="Y",AA52="Y",AB52="Y",AC52="Y",AD52="Y",AE52="Y"),"Y","")
A53: EN.052 | B53: ENTITY | C53: Financial Information | D53: N | E53: ANNL_TRNVR_PRVS | F53: Y | G53: Y | H53: Y | I53: Y | J53: Y | K53: Y | L53: N | P53: FLOAT 2 decimal places | Q53: Use decimal point, no thousands seperator | R53: 99999999999 | S53: 11111111111 | T53: 11111111111 | U53: Annual turnover counterparty (LE) at previous reporting | V53: Annual sales volume net of all discounts and sales taxes in accordance with Recommendation 2003/361/EC. Equivalent to the concept of 'total annual sales' in Article 153(4) of Regulation (EU) No 575/2013. Please report on solo entity level unless advised otherwise. | W53: Not applicable | X53: N/A | Y53: - | Z53: Y | AA53: N | AB53: N | AC53: N | AD53: N | AE53: Y | AF53: N | AG53: N | AH53: Y | AI53: =IF(AND(Z53="Y",AA53="Y",AB53="Y",AC53="Y",AD53="Y",AE53="Y"),"Y","")
A54: EN.053 | B54: ENTITY | C54: Financial Information | D54: N | E54: CAPEX | F54: Y | G54: Y | H54: Y | I54: Y | J54: Y | K54: Y | L54: N | P54: FLOAT 2 decimal places | Q54: Use decimal point, no thousands seperator | R54: 99999999999 | S54: 11111111111 | T54: 11111111111 | U54: Capital expenditures at most recent reported figures | V54: Capital expenditures at most recent reported figures. Please report on solo entity level unless advised otherwise. | W54: Not applicable | X54: N/A | Y54: - | Z54: Y | AA54: N | AB54: N | AC54: N | AD54: N | AE54: N | AF54: N | AG54: N | AH54: Y | AI54: =IF(AND(Z54="Y",AA54="Y",AB54="Y",AC54="Y",AD54="Y",AE54="Y"),"Y","")
A55: EN.054 | B55: ENTITY | C55: Financial Information | D55: N | E55: CAPEX_PRVS | F55: Y | G55: Y | H55: Y | I55: Y | J55: Y | K55: Y | L55: N | P55: FLOAT 2 decimal places | Q55: Use decimal point, no thousands seperator | R55: 99999999999 | S55: 11111111111 | T55: 11111111111 | U55: Capital expenditures at previous reported figures | V55: Capital expenditures at previous reported figures. Please report on solo entity level unless advised otherwise. | W55: Not applicable | X55: N/A | Y55: - | Z55: Y | AA55: N | AB55: N | AC55: N | AD55: N | AE55: N | AF55: N | AG55: N | AH55: Y | AI55: =IF(AND(Z55="Y",AA55="Y",AB55="Y",AC55="Y",AD55="Y",AE55="Y"),"Y","")
A56: EN.055 | B56: ENTITY | C56: Financial Information | D56: N | E56: CLLCTN_MD | F56: N | G56: Y | H56: Y | I56: Y | J56: Y | K56: Y | L56: Y | P56: =HYPERLINK("#"&"CodeList!"&ADDRESS(2,MATCH($E56,CodeList!$2:$2,0)+1,),"Code List") -> Code List | Q56: Use codes from the code list sheet | R56: 99999999999 | S56: 11111111111 | T56: 11111111111 | U56: Collection mode | V56: Collection mode. Hard collection would be similar to foreclosure proceedings while soft collection means to call the collateral without any legal proceedings. | W56: Not applicable | X56: N/A | Y56: - | Z56: Y | AA56: N | AB56: N | AC56: N | AD56: N | AE56: N | AF56: N | AG56: N | AH56: Y | AI56: =IF(AND(Z56="Y",AA56="Y",AB56="Y",AC56="Y",AD56="Y",AE56="Y"),"Y","")
A57: EN.056 | B57: ENTITY | C57: Financial Information | D57: N | E57: CSH | F57: Y | G57: Y | H57: Y | I57: Y | J57: Y | K57: Y | L57: N | P57: FLOAT 2 decimal places | Q57: Use decimal point, no thousands seperator | R57: 99999999999 | S57: 11111111111 | T57: 11111111111 | U57: Cash and cash equivalents at most recent reported figures | V57: Cash and cash equivalents at most recent reported figures. Please report on solo entity level unless advised otherwise. | W57: Not applicable | X57: N/A | Y57: - | Z57: Y | AA57: N | AB57: N | AC57: N | AD57: N | AE57: N | AF57: N | AG57: N | AH57: Y | AI57: =IF(AND(Z57="Y",AA57="Y",AB57="Y",AC57="Y",AD57="Y",AE57="Y"),"Y","")
A58: EN.057 | B58: ENTITY | C58: Financial Information | D58: N | E58: CSH_PRVS | F58: Y | G58: Y | H58: Y | I58: Y | J58: Y | K58: Y | L58: N | P58: FLOAT 2 decimal places | Q58: Use decimal point, no thousands seperator | R58: 99999999999 | S58: 11111111111 | T58: 11111111111 | U58: Cash and cash equivalents at previous reported figures | V58: Cash and cash equivalents at previous reported figures. Please report on solo entity level unless advised otherwise. | W58: Not applicable | X58: N/A | Y58: - | Z58: Y | AA58: N | AB58: N | AC58: N | AD58: N | AE58: N | AF58: N | AG58: N | AH58: Y | AI58: =IF(AND(Z58="Y",AA58="Y",AB58="Y",AC58="Y",AD58="Y",AE58="Y"),"Y","")
A59: EN.058 | B59: ENTITY | C59: Financial Information | D59: N | E59: EBITDA | F59: Y | G59: Y | H59: Y | I59: Y | J59: Y | K59: Y | L59: N | P59: FLOAT 2 decimal places | Q59: Use decimal point, no thousands seperator | R59: 99999999999 | S59: 11111111111 | T59: 11111111111 | U59: EBITDA at latest reported figures | V59: EBITDA at latest reported figures. Please report on solo entity level unless advised otherwise. | W59: Not applicable | X59: N/A | Y59: - | Z59: Y | AA59: N | AB59: N | AC59: N | AD59: N | AE59: Y | AF59: N | AG59: N | AH59: Y | AI59: =IF(AND(Z59="Y",AA59="Y",AB59="Y",AC59="Y",AD59="Y",AE59="Y"),"Y","")
A60: EN.059 | B60: ENTITY | C60: Financial Information | D60: N | E60: EBITDA_PRVS | F60: Y | G60: Y | H60: Y | I60: Y | J60: Y | K60: Y | L60: N | P60: FLOAT 2 decimal places | Q60: Use decimal point, no thousands seperator | R60: 99999999999 | S60: 11111111111 | T60: 11111111111 | U60: EBITDA at previous reported figures | V60: EBITDA at previous reported figures. Please report on solo entity level unless advised otherwise. | W60: Not applicable | X60: N/A | Y60: - | Z60: Y | AA60: N | AB60: N | AC60: N | AD60: N | AE60: Y | AF60: N | AG60: N | AH60: Y | AI60: =IF(AND(Z60="Y",AA60="Y",AB60="Y",AC60="Y",AD60="Y",AE60="Y"),"Y","")
A61: EN.060 | B61: ENTITY | C61: Financial Information | D61: N | E61: EQTY | F61: Y | G61: Y | H61: Y | I61: Y | J61: Y | K61: Y | L61: N | P61: FLOAT 2 decimal places | Q61: Use decimal point, no thousands seperator | R61: 99999999999 | S61: 11111111111 | T61: 11111111111 | U61: Equity at most recent reported figures | V61: Equity at most recent reported figures. Please report on solo entity level unless advised otherwise. | W61: Not applicable | X61: N/A | Y61: - | Z61: Y | AA61: N | AB61: Y | AC61: N | AD61: N | AE61: Y | AF61: N | AG61: Y | AH61: Y | AI61: =IF(AND(Z61="Y",AA61="Y",AB61="Y",AC61="Y",AD61="Y",AE61="Y"),"Y","")
A62: EN.061 | B62: ENTITY | C62: Financial Information | D62: N | E62: EQTY_PRVS | F62: Y | G62: Y | H62: Y | I62: Y | J62: Y | K62: Y | L62: N | P62: FLOAT 2 decimal places | Q62: Use decimal point, no thousands seperator | R62: 99999999999 | S62: 11111111111 | T62: 11111111111 | U62: Equity at previous reported figures | V62: Equity at previous reported figures. Please report on solo entity level unless advised otherwise. | W62: Not applicable | X62: N/A | Y62: - | Z62: Y | AA62: N | AB62: N | AC62: N | AD62: N | AE62: Y | AF62: N | AG62: N | AH62: Y | AI62: =IF(AND(Z62="Y",AA62="Y",AB62="Y",AC62="Y",AD62="Y",AE62="Y"),"Y","")
A63: EN.062 | B63: ENTITY | C63: Financial Information | D63: N | E63: GRP_TTL_DBT | F63: Y | G63: Y | H63: Y | I63: Y | J63: Y | K63: Y | L63: N | P63: FLOAT 2 decimal places | Q63: Use decimal point, no thousands seperator | R63: 99999999999 | S63: 11111111111 | T63: 11111111111 | U63: Group's total debt at most recent reported figures | V63: Total debt at most recent reported figures. Please report level of the consolidated financial statement of the group accoding to the applicable accounting standard. | W63: Not applicable | X63: N/A | Y63: - | Z63: Y | AA63: N | AB63: Y | AC63: N | AD63: N | AE63: N | AF63: N | AG63: Y | AH63: Y | AI63: =IF(AND(Z63="Y",AA63="Y",AB63="Y",AC63="Y",AD63="Y",AE63="Y"),"Y","")
A64: EN.063 | B64: ENTITY | C64: Financial Information | D64: N | E64: GDWILL | F64: Y | G64: Y | H64: Y | I64: Y | J64: Y | K64: Y | L64: N | P64: FLOAT 2 decimal places | Q64: Use decimal point, no thousands seperator | R64: 99999999999 | S64: 11111111111 | T64: 11111111111 | U64: Goodwill at most recent reported figures | V64: Goodwill at most recent reported figures. Please report on solo entity level unless advised otherwise. | W64: Not applicable | X64: N/A | Y64: - | Z64: Y | AA64: N | AB64: N | AC64: N | AD64: N | AE64: N | AF64: N | AG64: N | AH64: Y | AI64: =IF(AND(Z64="Y",AA64="Y",AB64="Y",AC64="Y",AD64="Y",AE64="Y"),"Y","")
A65: EN.064 | B65: ENTITY | C65: Financial Information | D65: N | E65: GDWILL_PRVS | F65: Y | G65: Y | H65: Y | I65: Y | J65: Y | K65: Y | L65: N | P65: FLOAT 2 decimal places | Q65: Use decimal point, no thousands seperator | R65: 99999999999 | S65: 11111111111 | T65: 11111111111 | U65: Goodwill at previous reported figures | V65: Goodwill at previous reported figures. Please report on solo entity level unless advised otherwise. | W65: Not applicable | X65: N/A | Y65: - | Z65: Y | AA65: N | AB65: N | AC65: N | AD65: N | AE65: N | AF65: N | AG65: N | AH65: Y | AI65: =IF(AND(Z65="Y",AA65="Y",AB65="Y",AC65="Y",AD65="Y",AE65="Y"),"Y","")
A66: EN.065 | B66: ENTITY | C66: Financial Information | D66: N | E66: LTI | F66: N | G66: N | H66: N | I66: N | J66: N | K66: N | L66: Y | P66: FLOAT 6 decimal places | Q66: Use decimal point, no thousands seperator | R66: 99999999999 | S66: 11111111111 | T66: 11111111111 | U66: Loan to income (LTI) | V66: Please report the latest available information according to bank-internal definition. If there was no update since initial loan origination report the information available as at loan origination. Please also add an explanatory note on sheet "Notes" on how the calculation is done. | W66: Not applicable | X66: N/A | Y66: - | Z66: Y | AA66: N | AB66: N | AC66: N | AD66: N | AE66: N | AF66: N | AG66: N | AH66: Y | AI66: =IF(AND(Z66="Y",AA66="Y",AB66="Y",AC66="Y",AD66="Y",AE66="Y"),"Y","")
A67: EN.066 | B67: ENTITY | C67: Financial Information | D67: N | E67: LVRG | F67: Y | G67: Y | H67: Y | I67: Y | J67: Y | K67: Y | L67: N | P67: FLOAT 6 decimal places | Q67: Use decimal point, no thousands seperator | R67: 99999999999 | S67: 11111111111 | T67: 11111111111 | U67: Leverage (net debt / EBITDA) at most recent reported figures | V67: Leverage ratio calculated as net debt divided by EBITDA at most recent reported figures. | W67: Not applicable | X67: N/A | Y67: - | Z67: Y | AA67: N | AB67: N | AC67: N | AD67: N | AE67: Y | AF67: N | AG67: N | AH67: Y | AI67: =IF(AND(Z67="Y",AA67="Y",AB67="Y",AC67="Y",AD67="Y",AE67="Y"),"Y","")
A68: EN.067 | B68: ENTITY | C68: Financial Information | D68: N | E68: LVRG_PRVS | F68: Y | G68: Y | H68: Y | I68: Y | J68: Y | K68: Y | L68: N | P68: FLOAT 6 decimal places | Q68: Use decimal point, no thousands seperator | R68: 99999999999 | S68: 11111111111 | T68: 11111111111 | U68: Leverage (net debt / EBITDA) at previous reported figures | V68: Leverage ratio calculated as net debt divided by EBITDA at previous reported figures. | W68: Not applicable | X68: N/A | Y68: - | Z68: Y | AA68: N | AB68: N | AC68: N | AD68: N | AE68: Y | AF68: N | AG68: N | AH68: Y | AI68: =IF(AND(Z68="Y",AA68="Y",AB68="Y",AC68="Y",AD68="Y",AE68="Y"),"Y","")
... A85: EN.084 | B85: ENTITY | C85: Indicators | D85: N | E85: PD_IFRS9_12M_RD_T1 | F85: Y | G85: Y | H85: Y | I85: Y | J85: Y | K85: Y | L85: Y | P85: FLOAT 6 decimal places | Q85: Use decimal point, no thousands seperator | R85: 99999999999 | S85: 11111111111 | T85: 11111111111 | U85: 12-month PD one year prior to the reporting date according to IFRS 9 | V85: 12-month PD one year prior to the reference date which is used by the bank for the computation of stage 1 ECL or for SICR assessment if the bank uses a 12 month proxy for staging. If the PD is calculated on instruments level please provide an EAD weighted average. | W85: Yes - Computed | X85: SUM for all of client's contracts (T2417_P12IFRS9 * T2417_EADIFRS9) / Total Client T2417_EADIFRS9 | Y85: To be computed using one year previous to the reference date information. (for example, if Reference date: 03/30/2022, information as of 03/30/2021 is used to compute this field) | Z85: Y | AA85: N | AB85: N | AC85: N | AD85: N | AE85: N | AF85: N | AG85: N | AH85: Y | AI85: =IF(AND(Z85="Y",AA85="Y",AB85="Y",AC85="Y",AD85="Y",AE85="Y"),"Y","")
A86: EN.085 | B86: ENTITY | C86: General | D86: N | E86: TAX_ID | F86: Y | G86: Y | H86: Y | I86: Y | J86: Y | K86: Y | L86: Y | P86: VARCHAR2(255) | Q86: Free (latin) text without special characters (semicolon, quotes, …) | R86: MISS | S86: N/A | T86: N/A | U86: Fiscal ID | V86: Fiscal ID (CIF, NIF, Tax number, etc). | W86: Yes - Equivalent | X86: JM_CLIENT_BII - G4093_CODIDPER | Y86: - | Z86: Y | AA86: N | AB86: N | AC86: N | AD86: N | AE86: N | AF86: N | AG86: N | AH86: Y | AI86: =IF(AND(Z86="Y",AA86="Y",AB86="Y",AC86="Y",AD86="Y",AE86="Y"),"Y","")
A87: EN.086 | B87: ENTITY | C87: Financial Information | D87: N | E87: ANNL_TRNVR_LE_BDR | F87: Y | G87: Y | H87: Y | I87: Y | J87: Y | K87: Y | L87: N | P87: FLOAT 2 decimal places | Q87: Use decimal point, no thousands seperator | R87: 99999999999 | S87: 11111111111 | T87: 11111111111 | U87: BDR Annual turnover counterparty (LE) | V87: BDR Annual sales volume net of all discounts and sales taxes in accordance with Recommendation 2003/361/EC. Equivalent to the concept of 'total annual sales' in Article 153(4) of Regulation (EU) No 575/2013. Please report on solo entity level unless advised otherwise. | W87: Yes - Equivalent | X87: JM_CLIEN_JURI - G5508_IMPFACTM | Y87: - | Z87: Y | AA87: N | AB87: N | AC87: N | AD87: N | AE87: N | AF87: N | AG87: N | AH87: Y | AI87: =IF(AND(Z87="Y",AA87="Y",AB87="Y",AC87="Y",AD87="Y",AE87="Y"),"Y","")
A88: EN.087 | B88: ENTITY | C88: Financial Information | D88: N | E88: ANNL_TRNVR_PRVS_BDR | F88: Y | G88: Y | H88: Y | I88: Y | J88: Y | K88: Y | L88: N | P88: FLOAT 2 decimal places | Q88: Use decimal point, no thousands seperator | R88: 99999999999 | S88: 11111111111 | T88: 11111111111 | U88: BDR Annual turnover counterparty (LE) at previous reporting | V88: BDR Annual sales volume net of all discounts and sales taxes in accordance with Recommendation 2003/361/EC. Equivalent to the concept of 'total annual sales' in Article 153(4) of Regulation (EU) No 575/2013. Please report on solo entity level unless advised otherwise. | W88: Yes - Equivalent | X88: JM_CLIEN_JURI - G5508_IMPFACTM | Y88: To be computed using the one at previous reporting | Z88: Y | AA88: N | AB88: N | AC88: N | AD88: N | AE88: N | AF88: N | AG88: N | AH88: Y | AI88: =IF(AND(Z88="Y",AA88="Y",AB88="Y",AC88="Y",AD88="Y",AE88="Y"),"Y","")
A89: EN.088 | B89: ENTITY | C89: General | D89: N | E89: OSI_ID | F89: Corporation | G89: Corporation | H89: Corporation | I89: Corporation | J89: Corporation | K89: Corporation | L89: Corporation | P89: VARCHAR2(255) | Q89: Free (latin) text without special characters (semicolon, quotes, …) | R89: MISS | S89: N/A | T89: N/A | U89: On-site inspection identifier | V89: The identifier that is used to identify an on-site inspection as is referenced in the on-site inspection notification letter head. The value typically follows the convention: "OSI-YYYY-JSTCD-01234". | W89: Not applicable | X89: N/A | Y89: - | Z89: Y | AA89: N | AB89: N | AC89: N | AD89: N | AE89: Y | AF89: N | AG89: N | AH89: Y | AI89: =IF(AND(Z89="Y",AA89="Y",AB89="Y",AC89="Y",AD89="Y",AE89="Y"),"Y","")
A90: EN.089 | B90: ENTITY | C90: Indicators | D90: N | E90: PD_CRR_RD_T1 | F90: Y | G90: Y | H90: Y | I90: Y | J90: Y | K90: Y | L90: Y | P90: FLOAT 6 decimal places | Q90: Use decimal point, no thousands seperator | R90: 99999999999 | S90: 11111111111 | T90: 11111111111 | U90: Probability of default according to CRR one year prior to the reference date | V90: The PD over one year, determined in accordance with Articles 160, 163, 179 and 180 of Regulation (EU) No 575/2013. If the PD is calculated on obligor level then provide the obligor PD. If the PD is calculated on instruments level please provide an EAD weighted average. | W90: Yes - Computed | X90: SUM for all of client's contracts (G7162_IN_PDINI * EAD) / Total Client EAD | Y90: EAD refers to the LT data field IN.074 Report PD one year previous to the reference date. (for example, if Reference date: 03/30/2022, the PD as of 03/30/2021 is reported in this field) | Z90: Y | AA90: N | AB90: N | AC90: N | AD90: N | AE90: N | AF90: N | AG90: N | AH90: Y | AI90: =IF(AND(Z90="Y",AA90="Y",AB90="Y",AC90="Y",AD90="Y",AE90="Y"),"Y","")
A91: EN.090 | B91: ENTITY | C91: General | D91: N | E91: EC_GRP_ID | F91: Y | G91: Y | H91: Y | I91: Y | J91: Y | K91: Y | L91: N | P91: VARCHAR2(255) | Q91: Free (latin) text without special characters (semicolon, quotes, …) | R91: MISS | S91: N/A | T91: N/A | U91: Economic (financial) Group ID | V91: The unit should report the unique identifier of the economic group (ultimate parent entity) of the counterparty. | W91: Yes - Equivalent | X91: JM_GRUP_ECONO - G5512_GRUP_ECO | Z91: Y | AA91: N | AB91: Y | AC91: Y | AD91: N | AE91: Y | AF91: N | AG91: Y | AH91: Y | AI91: =IF(AND(Z91="Y",AA91="Y",AB91="Y",AC91="Y",AD91="Y",AE91="Y"),"Y","")
A92: EN.091 | B92: ENTITY | C92: General | D92: N | E92: EC_GRP_NM | F92: Y | G92: Y | H92: Y | I92: Y | J92: Y | K92: Y | L92: N | P92: VARCHAR2(255) | Q92: Free (latin) text without special characters (semicolon, quotes, …) | R92: MISS | S92: N/A | T92: N/A | U92: Economic (Financial) Group Name | V92: The unit should report the legal/official name of the ultimate parent entity of the counterparty’s economic group | W92: Yes - Equivalent | X92: JM_GRUP_ECONO - G5512_DGRUPO | Y92: Report Name of the entity reported in EN.011 | Z92: Y | AA92: N | AB92: Y | AC92: Y | AD92: N | AE92: Y | AF92: N | AG92: Y | AH92: Y | AI92: =IF(AND(Z92="Y",AA92="Y",AB92="Y",AC92="Y",AD92="Y",AE92="Y"),"Y","")
A93: EN.092 | B93: ENTITY | C93: General | D93: N | E93: PST_CD | F93: N | G93: Y | H93: Y | I93: Y | J93: Y | K93: Y | L93: Y | P93: VARCHAR2(255) | Q93: Free (latin) text without special characters (semicolon, quotes, …) | R93: MISS | S93: N/A | T93: N/A | U93: Post code / ZIP | V93: Post code / ZIP. | W93: Not applicable | X93: N/A | Y93: - | Z93: N | AA93: N | AB93: Y | AC93: N | AD93: Y | AE93: N | AF93: N | AG93: Y | AH93: Y
A94: EN.093 | B94: ENTITY | C94: General | D94: N | E94: ESG_SBSCTR | F94: N | G94: N | H94: Y | I94: N | J94: Y | K94: N | L94: N | P94: =HYPERLINK("#"&"CodeList!"&ADDRESS(2,MATCH($E94,CodeList!$2:$2,0)+1,),"Code List") -> Code List | Q94: Use codes from the code list sheet | R94: MISS | S94: N/A | T94: N/A | U94: ESG Subsector | V94: ESG Subsector is a breakdown of NOPER Annex Segments (General governments and Other Financial Corporation) | W94: Not applicable | X94: N/A | Y94: - | Z94: N | AA94: N | AB94: Y | AC94: N | AD94: N | AE94: N | AF94: N | AG94: Y | AH94: Y
A95: EN.094 | B95: ENTITY | C95: Classification | D95: N | E95: NACE_ESG | F95: N | G95: Y | H95: Y | I95: Y | J95: Y | K95: Y | L95: N | P95: Code list | Q95: Use codes from the code list sheet | R95: MISS | S95: N/A | T95: N/A | U95: Economic activity counterparty ESG | V95: The level four NACE code in accordance with Regulation (EC) No 1893/2006 is generally reported but following the Pilar 3 ESG EBA Guidelines criteria for the NACE allocation. | W95: Not applicable | X95: N/A | Y95: - | Z95: N | AA95: N | AB95: Y | AC95: N | AD95: Y | AE95: N | AF95: N | AG95: Y | AH95: Y
A96: EN.095 | B96: ENTITY | C96: Financial Information | D96: N | E96: TTL_LBLTY | F96: Y | G96: N | H96: Y | I96: Y | J96: Y | K96: Y | L96: N | P96: FLOAT 2 decimal places | Q96: Use decimal point, no thousands seperator | R96: 99999999999 | S96: 11111111111 | T96: 11111111111 | U96: Total Liabilities at latest most recent reported figures | V96: Counterparty’s total liabilities according to its annual financial statements at most recent reported figures | W96: Not applicable | X96: N/A | Y96: - | Z96: N | AA96: N | AB96: Y | AC96: N | AD96: N | AE96: N | AF96: N | AG96: Y | AH96: Y
A97: EN.096 | B97: ENTITY | C97: General | D97: N | E97: TXNMY_ELGBL_CAPEX_CCM | F97: N | G97: N | H97: N | I97: Y | J97: Y | K97: Y | L97: N | P97: FLOAT 6 decimal places | Q97: Use decimal point, no thousands seperator | R97: 99999999999 | S97: 11111111111 | T97: 11111111111 | U97: Taxonomy-eligible CAPEX (CCM) Ratio | V97: Counterparty’s reported proportion of CAPEX eligible according to European Taxonomy and that might make a substantial contribution to an environmental objective of ‘Climate Change Mitigation’. | W97: Not applicable | X97: N/A | Y97: - | Z97: N | AA97: N | AB97: Y | AC97: N | AD97: N | AE97: N | AF97: N | AG97: Y | AH97: Y
A98: EN.097 | B98: ENTITY | C98: General | D98: N | E98: TXNMY_ELGBL_TRNVR_CCM | F98: N | G98: N | H98: N | I98: Y | J98: Y | K98: Y | L98: N | P98: FLOAT 6 decimal places | Q98: Use decimal point, no thousands seperator | R98: 99999999999 | S98: 11111111111 | T98: 11111111111 | U98: Taxonomy-eligible Turnover (CCM) Ratio | V98: Counterparty’s reported proportion of Turnover eligible according to European Taxonomy and that might make a substantial contribution to an environmental objective of ‘Climate Change Mitigation’. | W98: Not applicable | X98: N/A | Y98: - | Z98: N | AA98: N | AB98: Y | AC98: N | AD98: N | AE98: N | AF98: N | AG98: Y | AH98: Y
A99: EN.098 | B99: ENTITY | C99: General | D99: N | E99: TXNMY_ELGBL_CAPEX_CCA | F99: N | G99: N | H99: N | I99: Y | J99: Y | K99: Y | L99: N | P99: FLOAT 6 decimal places | Q99: Use decimal point, no thousands seperator | R99: 99999999999 | S99: 11111111111 | T99: 11111111111 | U99: Taxonomy-eligible CAPEX (CCA) Ratio | V99: Counterparty’s reported proportion of CAPEX eligible according to European Taxonomy and that might make a substantial contribution to an environmental objective of ‘Climate Change Adaptation’. | W99: Not applicable | X99: N/A | Y99: - | Z99: N | AA99: N | AB99: Y | AC99: N | AD99: N | AE99: N | AF99: N | AG99: Y | AH99: Y
A100: EN.099 | B100: ENTITY | C100: General | D100: N | E100: TXNMY_ELGBL_TRNVR_CCA | F100: N | G100: N | H100: N | I100: Y | J100: Y | K100: Y | L100: N | P100: FLOAT 6 decimal places | Q100: Use decimal point, no thousands seperator | R100: 99999999999 | S100: 11111111111 | T100: 11111111111 | U100: Taxonomy-eligible Turnover (CCA) Ratio | V100: Counterparty’s reported proportion of Turnover eligible according to European Taxonomy and that might make a substantial contribution to an environmental objective of ‘Climate Change Adaptation’ | W100: Not applicable | X100: N/A | Y100: - | Z100: N | AA100: N | AB100: Y | AC100: N | AD100: N | AE100: N | AF100: N | AG100: Y | AH100: Y
A101: EN.100 | B101: ENTITY | C101: General | D101: N | E101: ENBLNG_CAPEX_CCM | F101: N | G101: N | H101: N | I101: Y | J101: Y | K101: Y | L101: N | P101: FLOAT 6 decimal places | Q101: Use decimal point, no thousands seperator | R101: 99999999999 | S101: 11111111111 | T101: 11111111111 | U101: Taxonomy-aligned CAPEX (CCM) - Enabling Ratio | V101: Counterparty’s proportion of CAPEX that is Taxonomy-aligned under CCM objective and that enables other activities to make a substantial contribution to one or more of these objectives. | W101: Not applicable | X101: N/A | Y101: - | Z101: N | AA101: N | AB101: Y | AC101: N | AD101: N | AE101: N | AF101: N | AG101: Y | AH101: Y
A102: EN.101 | B102: ENTITY | C102: General | D102: N | E102: ENBLNG_CAPEX_CCA | F102: N | G102: N | H102: N | I102: Y | J102: Y | K102: Y | L102: N | P102: FLOAT 6 decimal places | Q102: Use decimal point, no thousands seperator | R102: 99999999999 | S102: 11111111111 | T102: 11111111111 | U102: Taxonomy-aligned CAPEX (CCA) - Enabling Ratio | V102: Counterparty’s proportion of CAPEX that is Taxonomy-aligned under CCA objective and that enables other activities to make a substantial contribution to one or more of these objectives. | W102: Not applicable | X102: N/A | Y102: - | Z102: N | AA102: N | AB102: Y | AC102: N | AD102: N | AE102: N | AF102: N | AG102: Y | AH102: Y
A103: EN.102 | B103: ENTITY | C103: General | D103: N | E103: TRNSTNL_CAPEX | F103: N | G103: N | H103: N | I103: Y | J103: Y | K103: Y | L103: N | P103: FLOAT 6 decimal places | Q103: Use decimal point, no thousands seperator | R103: 99999999999 | S103: 11111111111 | T103: 11111111111 | U103: Taxonomy-aligned CAPEX (CCM) - Transitional Ratio | V103: Counterparty’s proportion of CAPEX that is Taxonomy-aligned under CCM objective and dedicated to transition activities. | W103: Not applicable | X103: N/A | Y103: - | Z103: N | AA103: N | AB103: Y | AC103: N | AD103: N | AE103: N | AF103: N | AG103: Y | AH103: Y
A104: EN.103 | B104: ENTITY | C104: General | D104: N | E104: PURE_CAPEX_CCM | F104: N | G104: N | H104: N | I104: Y | J104: Y | K104: Y | L104: N | P104: FLOAT 6 decimal places | Q104: Use decimal point, no thousands seperator | R104: 99999999999 | S104: 11111111111 | T104: 11111111111 | U104: Taxonomy-aligned CAPEX (CCM) - Pure Ratio | V104: Counterparty’s proportion of CAPEX that is Taxonomy-aligned under CCM objective and contributes substantially to the objective of climate change mitigation | W104: Not applicable | X104: N/A | Y104: - | Z104: N | AA104: N | AB104: Y | AC104: N | AD104: N | AE104: N | AF104: N | AG104: Y | AH104: Y
A105: EN.104 | B105: ENTITY | C105: General | D105: N | E105: PURE_CAPEX_CCA | F105: N | G105: N | H105: N | I105: Y | J105: Y | K105: Y | L105: N | P105: FLOAT 6 decimal places | Q105: Use decimal point, no thousands seperator | R105: 99999999999 | S105: 11111111111 | T105: 11111111111 | U105: Taxonomy-aligned CAPEX (CCA) - Pure Ratio | V105: Counterparty’s proportion of CAPEX that is Taxonomy-aligned under CCA objective and contributes substantially to the objective of climate change adaptation | W105: Not applicable | X105: N/A | Y105: - | Z105: N | AA105: N | AB105: Y | AC105: N | AD105: N | AE105: N | AF105: N | AG105: Y | AH105: Y
A106: EN.105 | B106: ENTITY | C106: General | D106: N | E106: ENBLNG_TRNVR_CCM | F106: N | G106: N | H106: N | I106: Y | J106: Y | K106: Y | L106: N | P106: FLOAT 6 decimal places | Q106: Use decimal point, no thousands seperator | R106: 99999999999 | S106: 11111111111 | T106: 11111111111 | U106: Taxonomy-aligned Turnover (CCM) - Enabling Ratio | V106: Counterparty’s proportion of Turnover that is Taxonomy-aligned under CCM objective and that enables other activities to make a substantial contribution to one or more of these objectives. | W106: Not applicable | X106: N/A | Y106: - | Z106: N | AA106: N | AB106: Y | AC106: N | AD106: N | AE106: N | AF106: N | AG106: Y | AH106: Y
A107: EN.106 | B107: ENTITY | C107: General | D107: N | E107: ENBLNG_TRNVR_CCA | F107: N | G107: N | H107: N | I107: Y | J107: Y | K107: Y | L107: N | P107: FLOAT 6 decimal places | Q107: Use decimal point, no thousands seperator | R107: 99999999999 | S107: 11111111111 | T107: 11111111111 | U107: Taxonomy-aligned Turnover (CCA) - Enabling Ratio | V107: Counterparty’s proportion of Turnover that is Taxonomy-aligned under CCA objective and that enables other activities to make a substantial contribution to one or more of these objectives. | W107: Not applicable | X107: N/A | Y107: - | Z107: N | AA107: N | AB107: Y | AC107: N | AD107: N | AE107: N | AF107: N | AG107: Y | AH107: Y
... A110: EN.109 | B110: ENTITY | C110: General | D110: N | E110: PURE_TRNVR_CCA | F110: N | G110: N | H110: N | I110: Y | J110: Y | K110: Y | L110: N | P110: FLOAT 6 decimal places | Q110: Use decimal point, no thousands seperator | R110: 99999999999 | S110: 11111111111 | T110: 11111111111 | U110: Taxonomy-aligned turnover (CCA) - Pure Ratio | V110: Counterparty’s proportion of turnover that is Taxonomy-aligned under CCA objective and contributes substantially to the objective of climate change adaptation | W110: Not applicable | X110: N/A | Y110: - | Z110: N | AA110: N | AB110: Y | AC110: N | AD110: N | AE110: N | AF110: N | AG110: Y | AH110: Y
A111: EN.110 | B111: ENTITY | C111: Classification | D111: N | E111: FLG_CSRD_APPLCBLTY | F111: N | G111: N | H111: N | I111: Y | J111: Y | K111: Y | L111: N | P111: Y, N | Q111: Boolean: Y/N | R111: MISS | S111: Default value not allowed | T111: N/A | U111: Flag of CSRD applicability at counterparty level | V111: The Corporate Sustainability Reporting Directive (CSRD) requires a progressive certain amount of companies to disclose information on the way they operate and manage social and environmental challenges. The purpose of the “flag of CSRD applicability at counterparty level” is to identify which counterparties qualify to be subject to disclose a Non-Financial Report. | W111: Not applicable | X111: N/A | Y111: - | Z111: N | AA111: N | AB111: Y | AC111: N | AD111: Y | AE111: N | AF111: N | AG111: Y | AH111: Y
A112: EN.111 | B112: ENTITY | C112: Classification | D112: N | E112: FLG_GRP_CSRD_APPLCBLTY | F112: N | G112: N | H112: N | I112: Y | J112: Y | K112: Y | L112: N | P112: Y, N | Q112: Boolean: Y/N | R112: MISS | S112: Default value not allowed | T112: N/A | U112: Flag of CSRD applicability at Group Level | V112: The Corporate Sustainability Reporting Directive (CSRD) requires a progressive certain amount of companies to disclose information on the way they operate and manage social and environmental challenges. The purpose of the “flag of CSRD applicability at group level” is to identify which Groups qualify to be subject to disclose a Non-Financial Report. | W112: Not applicable | X112: N/A | Y112: - | Z112: N | AA112: N | AB112: Y | AC112: N | AD112: Y | AE112: N | AF112: N | AG112: Y | AH112: Y
A113: EN.112 | B113: ENTITY | C113: Issuer identification | D113: N | E113: ISIN | F113: N | G113: Y | H113: N | I113: Y | J113: N | K113: Y | L113: N | P113: VARCHAR(12) | Q113: Free (latin) text without special characters (semicolon, quotes, …) | R113: MISS | S113: N/A | T113: N/A | U113: ISIN | V113: International Securities Identification Number (ISIN) at entity level. | W113: Not applicable | X113: N/A | Y113: - | Z113: N | AA113: N | AB113: Y | AC113: N | AD113: N | AE113: N | AF113: N | AG113: Y | AH113: Y
A114: EN.113 | B114: ENTITY | C114: Financial Information | D114: N | E114: GRP_ANNL_TRNVR_LE | F114: Y | G114: Y | H114: Y | I114: Y | J114: Y | K114: Y | L114: N | P114: FLOAT 2 decimal places | Q114: Use decimal point, no thousands seperator | R114: 99999999999 | S114: 11111111111 | T114: 11111111111 | U114: Group's annual turnover (LE) | V114: Annual sales volume net of all discounts and sales taxes in accordance with Recommendation 2003/361/EC. Equivalent to the concept of 'total annual sales' in Article 153(4) of Regulation (EU) No 575/2013. Please report at group level | W114: Not applicable | X114: N/A | Y114: - | Z114: N | AA114: N | AB114: Y | AC114: N | AD114: N | AE114: N | AF114: N | AG114: Y | AH114: Y
A115: EN.114 | B115: ENTITY | C115: Financial Information | D115: N | E115: GRP_TTL_LBLTY | F115: Y | G115: Y | H115: Y | I115: Y | J115: Y | K115: Y | L115: N | P115: FLOAT 2 decimal places | Q115: Use decimal point, no thousands seperator | R115: 99999999999 | S115: 11111111111 | T115: 11111111111 | U115: Group's total liability at most recent reported figures | V115: Total liability at most recent reported figures. Please report level of the consolidated financial statement of the group accoding to the applicable accounting standard. | W115: Not applicable | X115: N/A | Y115: - | Z115: N | AA115: N | AB115: Y | AC115: N | AD115: N | AE115: N | AF115: N | AG115: Y | AH115: Y
A116: EN.115 | B116: ENTITY | C116: General | D116: N | E116: CNTRPRTY_EMSSNS_SCP1 | F116: N | G116: N | H116: N | I116: N | J116: N | K116: Y | L116: N | P116: FLOAT 6 decimal places | Q116: Use decimal point, no thousands seperator | R116: 99999999999 | S116: 11111111111 | T116: 11111111111 | U116: Counterparty's emissions scope 1 | V116: Scope 1 emissions corresponding to the Counterparty | W116: Not applicable | X116: N/A | Y116: - | Z116: N | AA116: N | AB116: Y | AC116: N | AD116: Y | AE116: N | AF116: N | AG116: Y | AH116: Y
A117: EN.116 | B117: ENTITY | C117: General | D117: N | E117: CNTRPRTY_EMSSNS_SCP2 | F117: N | G117: N | H117: N | I117: N | J117: N | K117: Y | L117: N | P117: FLOAT 6 decimal places | Q117: Use decimal point, no thousands seperator | R117: 99999999999 | S117: 11111111111 | T117: 11111111111 | U117: Counterparty's emissions scope 2 | V117: Scope 2 emissions corresponding to the Counterparty | W117: Not applicable | X117: N/A | Y117: - | Z117: N | AA117: N | AB117: Y | AC117: N | AD117: Y | AE117: N | AF117: N | AG117: Y | AH117: Y
A118: EN.117 | B118: ENTITY | C118: General | D118: N | E118: CNTRPRTY_EMSSNS_SCP3 | F118: N | G118: N | H118: N | I118: N | J118: N | K118: Y | L118: N | P118: FLOAT 6 decimal places | Q118: Use decimal point, no thousands seperator | R118: 99999999999 | S118: 11111111111 | T118: 11111111111 | U118: Counterparty's emissions scope 3 | V118: Scope 3 emissions corresponding to the Counterparty | W118: Not applicable | X118: N/A | Y118: - | Z118: N | AA118: N | AB118: Y | AC118: N | AD118: Y | AE118: N | AF118: N | AG118: Y | AH118: Y
A119: EN.118 | B119: ENTITY | C119: General | D119: N | E119: FLG_EXCLDD_EU_PRS_ALGND_BNCHMRK | F119: N | G119: N | H119: N | I119: N | J119: N | K119: Y | L119: N | P119: Y, N | Q119: Boolean: Y/N | R119: MISS | S119: Default value not allowed | T119: N/A | U119: Flag Excluded from EU Paris-aligned benchmark | V119: This flag allows to identify whether the entity is excluded from the EU Paris-aligned benchmark | W119: Not applicable | X119: N/A | Y119: - | Z119: N | AA119: N | AB119: Y | AC119: N | AD119: N | AE119: N | AF119: N | AG119: Y | AH119: Y
A120: EN.119 | B120: ENTITY | C120: General | D120: N | E120: GRP_EMSSNS_SCP1 | F120: N | G120: N | H120: N | I120: N | J120: N | K120: Y | L120: N | P120: FLOAT 6 decimal places | Q120: Use decimal point, no thousands seperator | R120: 99999999999 | S120: 11111111111 | T120: 11111111111 | U120: Group's emissions scope 1 | V120: Scope 1 emissions corresponding to the Group | W120: Not applicable | X120: N/A | Y120: - | Z120: N | AA120: N | AB120: Y | AC120: N | AD120: Y | AE120: N | AF120: N | AG120: Y | AH120: Y
A121: EN.120 | B121: ENTITY | C121: General | D121: N | E121: GRP_EMSSNS_SCP2 | F121: N | G121: N | H121: N | I121: N | J121: N | K121: Y | L121: N | P121: FLOAT 6 decimal places | Q121: Use decimal point, no thousands seperator | R121: 99999999999 | S121: 11111111111 | T121: 11111111111 | U121: Group's emissions scope 2 | V121: Scope 2 emissions corresponding to the Group | W121: Not applicable | X121: N/A | Y121: - | Z121: N | AA121: N | AB121: Y | AC121: N | AD121: Y | AE121: N | AF121: N | AG121: Y | AH121: Y
A122: EN.121 | B122: ENTITY | C122: General | D122: N | E122: GRP_EMSSNS_SCP3 | F122: N | G122: N | H122: N | I122: N | J122: N | K122: Y | L122: N | P122: FLOAT 6 decimal places | Q122: Use decimal point, no thousands seperator | R122: 99999999999 | S122: 11111111111 | T122: 11111111111 | U122: Group's emissions scope 3 | V122: Scope 3 emissions corresponding to the Group | W122: Not applicable | X122: N/A | Y122: - | Z122: N | AA122: N | AB122: Y | AC122: N | AD122: Y | AE122: N | AF122: N | AG122: Y | AH122: Y
...

Sheet CodeList
A1: Table | B1: INSTRUMENT | D1: INSTRUMENT / ENTITY | F1: INSTRUMENT / PROTECTION | H1: INSTRUMENT | J1: INSTRUMENT | L1: PROTECTION | N1: PROTECTION | P1: INSTRUMENT | R1: INSTRUMENT | T1: INSTRUMENT | V1: INSTRUMENT | X1: INSTRUMENT | Z1: INSTRUMENT | AB1: INSTRUMENT | AD1: INSTRUMENT | AF1: INSTRUMENT | AH1: INSTRUMENT | AJ1: INSTRUMENT | AL1: INSTRUMENT / ENTITY | AN1: INSTRUMENT / ENTITY | AP1: INSTRUMENT | AR1: INSTRUMENT | AT1: INSTRUMENT | AV1: INSTRUMENT | AX1: INSTRUMENT | AZ1: INSTRUMENT | BB1: INSTRUMENT | BD1: INSTRUMENT | BF1: INSTRUMENT | BH1: INSTRUMENT | BJ1: INSTRUMENT | BL1: INSTRUMENT | BN1: INSTRUMENT | BP1: INSTRUMENT | BR1: INSTRUMENT | BT1: ENTITY | BV1: PROTECTION | BX1: PROTECTION | BZ1: PROTECTION | CB1: PROTECTION | CD1: PROTECTION | CF1: PROTECTION | CH1: ENTITY | CJ1: ENTITY | CL1: ENTITY/PROTECTION | CN1: ENTITY | CP1: ENTITY | CR1: ENTITY | CT1: ENTITY | CV1: ENTITY | CX1: ENTITY | CZ1: INSTRUMENT / ENTITY | DB1: INSTRUMENT | DD1: ENTITY | DF1: INSTRUMENT / ENTITY | DH1: ENTITY | DJ1: INSTRUMENT_C19 | DL1: INSTRUMENT_C19 | DN1: INSTRUMENT_C19 | DP1: INSTRUMENT_C19 | DR1: INSTRUMENT | DT1: INSTRUMENT | DV1: INSTRUMENT | DX1: INSTRUMENT | DZ1: INSTRUMENT | EB1: INSTRUMENT | ED1: INSTRUMENT | EF1: INSTRUMENT | EH1: INSTRUMENT | EJ1: INSTRUMENT | EL1: INSTRUMENT | EN1: INSTRUMENT | EP1: INSTRUMENT | ER1: INSTRUMENT | ET1: INSTRUMENT | EV1: INSTRUMENT | EX1: INSTRUMENT | EZ1: INSTRUMENT | FB1: INSTRUMENT | FD1: PROTECTION | FF1: PROTECTION | FH1: PROTECTION | FJ1: PROTECTION | FL1: ENTITY | FN1: INSTRUMENT | FP1: INSTRUMENT | FR1: INSTRUMENT | FY1: INSTRUMENT | GA1: INSTRUMENT | GC1: INSTRUMENT | GE1: INSTRUMENT | GG1: INSTRUMENT | GI1: INSTRUMENT | GK1: PROTECTION | GM1: PROTECTION | GS1: PROTECTION | GU1: PROTECTION | GW1: INSTRUMENT | GY1: ENTITY | HA1: INSTRUMENT | HC1: INSTRUMENT | HE1: INSTRUMENT | HG1: INSTRUMENT | HI1: INSTRUMENT | HK1: INSTRUMENT | HM1: INSTRUMENT | HO1: INSTRUMENT | HQ1: INSTRUMENT - PROTECTION
A2: Data field | B2: ACCNTNG_CLSSFCTN | D2: CHNNL_ORGNTN | F2: CRRNCY_DNMNTN | H2: CPN_CRRNCY | J2: VLTN_CRRNCY | L2: APPRSL_CRRNCY | N2: CRE_INCM_CRRNCY | P2: CVNNT_STTS | R2: CVNNT_TYP | T2: DFLT_STTS_INSTRMNT | V2: PRFRMNG_STTS | X2: PRFRMNG_STTS_PRVS | Z2: FRBRNC_STTS_INSTRMNT | AB2: IMPRMNT_STTS | AD2: IMPRMNT_STTS_PRVS | AF2: IMPRMNT_ASSSSMNT_MTHD | AH2: IMPRMNT_CLCLTN_MTHD | AJ2: INTRST_RT_RST_FRQNCY | AL2: LGL_PRCDNG_STTS | AN2: LGL_PRCDNG_STTS_LE | AP2: PRJCT_FNNC_LN | AR2: PRPS | AT2: PYMNT_FRQNCY | AV2: RCRS | AX2: RWA_MTHD | AZ2: SICR_ASSSSMNT_MTHD | BB2: STTS_UNDRWRTTN_TRNSCTN | BD2: SYNDCT_RL | BF2: SYNDCTN_TYP | BH2: TRNCH | BJ2: TYP_AMRTSTN | BL2: TYP_CRE_OPRTN | BN2: TYP_INSTRMNT | BP2: TYP_INTRST_RT | BR2: TYP_MRTGG | BT2: EXTRNL_RTNG / EXTRNL_RTNG_PRVS / ISSR_RTNG | BV2: CNSTRCTN_STTS | BX2: DVLPMNT_STTS | BZ2: MN_PRPS | CB2: PRTCTN_VLTN_APPRCH | CD2: TYP_PRTCTN | CF2: TYP_PRTCTN_VL | CH2: ACCNTNG_FRMWRK_SL | CJ2: CLLCTN_MD | CL2: CNTRY/RL_ESTT_CLLTRL_LCTN | CN2: DFLT_STTS | CP2: ECNMC_ACTVTY/GRP_ECNMC_ACTVTY/ISSR_NACE_SCTR/NACE_ESG | CR2: EMPLYMNT_STTS | CT2: ENTRPRS_SZ_LE | CV2: PRFRMNG_STTS_LE | CX2: RTNG_MTHD | CZ2: INTRNL_RTNG | DB2: INTRNL_RTNG_INCPTN | DD2: INTRNL_RTNG_PRVS | DF2: RTNG_SCL | DH2: SNGL_PRPS_VHCL | DJ2: EBA_CMPLNT_MRTR_ST_C19 | DL2: TYP_CMPLNT_MRTR_C19 | DN2: FRBRNC_STTS_C19 | DP2: SBJCT_PBLC_GRNT_SCHM_C19 | DR2: ISSR_ID_TYP | DT2: GRNTR_ID_TYP | DV2: ISSR_CNTRY | DX2: ISSR_ESA_2010 | DZ2: LVRG_FNNC_FLG | EB2: ISSR_TYP | ED2: VLTN_TYP | EF2: INSTRMNT_CLSS | EH2: PRMRY_ASST_CLSSF | EJ2: ASST_SCRT_CLSS | EL2: TYPE_OF_PLCMNT | EN2: INSTR_SNRTY_CLSS | EP2: SRCS_ENCMBRNC | ER2: LCR_BFFR_CTGRY | ET2: PRDNTL_PRTFL | EV2: INTRNL_SGMNT_CAT_MSTA | EX2: INTRNL_SGMNT_CATGSUB | EZ2: RSK_MTGTD_CCT | FB2: RSK_MTGTD_CCP | FD2: TYP_EP_SCR/TYP_EMSSNS_SCR | FF2: EP_SCR | FH2: TYP_EMSSNS_LBL/TYP_EPC_LBL | FJ2: EPC_LBL/EPC_EMSSNS_LBL | FL2: ESG_SBSCTR | FN2: BSNSS_AREA/BSNSS_AREA_DSTNTN/BSNN_AREA_CIB/BSNSS_AREA_CCRR | FP2: SSTNBL_CTGRY_TXNMY | FR2: SSTNBL_CTGRY | FY2: MNGMNT_PRDCT | GA2: ENVRNMNTL_OBJCTV | GC2: TYP_ACTVTY | GE2: LNS_CLLTRLZD_CLSSFCTN | GG2: INTRBSNSS_ADJ_COD | GI2: MTHD_USD_INSTRMNT_SCP_1 / MTHD_USD_INSTRMNT_SCP_2 / MTHD_USD_INSTRMNT_SCP_3 | GK2: MTHD_USD_PRTCTN_SCP_1 / MTHD_USD_PRTCTN_SCP_2 / MTHD_USD_PRTCTN_SCP_3 | GM2: RL_ESTT_CRTFCTN | GO2: DNSH_DTL | GQ2: SSTNBL_INDCTR | GS2: TYP_HZRDS_INSRD | GU2: VHCL_EMSSNS_LBL | GW2: CNCLLD_INSTRMNT_STTS | GY2: PRSN_TYP | HA2: RFRNC_RT | HC2: TYP_SCRTZTN | HE2: TYP_OFF_BLNC_PRDCT | HG2: BLNC_SHT_RCGNTN | HI2: EXCLDD_LF | HK2: US_PRCDS | HM2: TYP_FCLTY | HO2: TYP_CL | HQ2: TYP_RLTN | HS2: RL_ESTT_CLMT_ZN | HU2: SCAN | HW2: TYP_DL | HY2: DSTNTN_FNDS | IA2: TYP_VHCL
CZ3: The rating collected in local databases should be reported. | DB3: The rating collected in local databases should be reported. | DD3: The rating collected in local databases should be reported. | DF3: to be populated by Corporation
A4: Code / Name | B4: ACCNTNG_CLSSFCTN_CD | C4: ACCNTNG_CLSSFCTN_NM | D4: CHNNL_ORGNTN_CD | E4: CHNNL_ORGNTN_NM | F4: CRRNCY_DNMNTN_CD | G4: CRRNCY_DNMNTN_NM | H4: CPN_CRRNCY_CD | I4: CPN_CRRNCY_NM | J4: VLTN_CRRNCY_CD | K4: VLTN_CRRNCY_NM | L4: APPRSL_CRRNCY_CD | M4: APPRSL_CRRNCY_NM | N4: CRE_INCM_CRRNCY_CD | O4: CRE_INCM_CRRNCY_NM | P4: CVNNT_STTS_CD | Q4: CVNNT_STTS_NM | R4: CVNNT_TYP_CD | S4: CVNNT_TYP_NM | T4: DFLT_STTS_INSTRMNT_CD | U4: DFLT_STTS_INSTRMNT_NM | V4: PRFRMNG_STTS_CD | W4: PRFRMNG_STTS_NM | X4: PRFRMNG_STTS_PRVS_CD | Y4: PRFRMNG_STTS_PRVS_NM | Z4: FRBRNC_STTS_CD | AA4: FRBRNC_STTS_NM | AB4: IMPRMNT_STTS_CD | AC4: IMPRMNT_STTS_NM | AD4: IMPRMNT_STTS_PRVS_CD | AE4: IMPRMNT_STTS_PRVS_NM | AF4: IMPRMNT_ASSSSMNT_MTHD_CD | AG4: IMPRMNT_ASSSSMNT_MTHD_NM | AH4: IMPRMNT_CLCLTN_MTHD_CD | AI4: IMPRMNT_CLCLTN_MTHD_NM | AJ4: INTRST_RT_RST_FRQNCY_CD | AK4: INTRST_RT_RST_FRQNCY_NM | AL4: LGL_PRCDNG_STTS_CD | AM4: LGL_PRCDNG_STTS_NM | AN4: LGL_PRCDNG_STTS_LE_CD | AO4: LGL_PRCDNG_STTS_LE_NM | AP4: PRJCT_FNNC_LN_CD | AQ4: PRJCT_FNNC_LN_NM | AR4: PRPS_CD | AS4: PRPS_NM | AT4: PYMNT_FRQNCY_CD | AU4: PYMNT_FRQNCY_NM | AV4: RCRS_CD | AW4: RCRS_NM | AX4: RWA_MTHD_CD | AY4: RWA_MTHD_ID | AZ4: SICR_ASSSSMNT_MTHD_CD | BA4: SICR_ASSSSMNT_MTHD_NM | BB4: STTS_UNDRWRTTN_TRNSCTN_CD | BC4: STTS_UNDRWRTTN_TRNSCTN_ID | BD4: SYNDCT_RL_CD | BE4: SYNDCT_RL_ID | BF4: SYNDCTN_TYP_CD | BG4: SYNDCTN_TYP_ID | BH4: TRNCH_CD | BI4: TRNCH_ID | BJ4: TYP_AMRTSTN_CD | BK4: TYP_AMRTSTN_NM | BL4: TYP_CRE_OPRTN_CD | BM4: TYP_CRE_OPRTN_NM | BN4: TYP_INSTRMNT_CD | BO4: TYP_INSTRMNT_NM | BP4: TYP_INTRST_RT_CD | BQ4: TYP_INTRST_RT_NM | BR4: TYP_MRTGG_CD | BS4: TYP_MRTGG_ID | BT4: EXTRNL_RTNG_CD | BU4: EXTRNL_RTNG_ID | BV4: CNSTRCTN_STTS_CD | BW4: CNSTRCTN_STTS_NM | BX4: DVLPMNT_STTS_CD | BY4: DVLPMNT_STTS_ID | BZ4: MN_PRPS_CD | CA4: MN_PRPS_ID | CB4: PRTCTN_VLTN_APPRCH_CD | CC4: PRTCTN_VLTN_APPRCH_NM | CD4: TYP_PRTCTN_CD | CE4: TYP_PRTCTN_NM | CF4: TYP_PRTCTN_VL_CD | CG4: TYP_PRTCTN_VL_NM | CH4: ACCNTNG_FRMWRK_CD | CI4: ACCNTNG_FRMWRK_NM | CJ4: CLLCTN_MD_CD | CK4: CLLCTN_MD_NM | CL4: CNTRY_CD | CM4: CNTRY_ID | CN4: DFLT_STTS_CD | CO4: DFLT_STTS_ID | CP4: ECNMC_ACTVTY_CD | CQ4: ECNMC_ACTVTY_NM | CR4: EMPLYMNT_STTS_CD | CS4: EMPLYMNT_STTS_ID | CT4: ENTRPRS_SZ_LE_CD | CU4: ENTRPRS_SZ_LE_ID | CV4: PRFRMNG_STTS_LE_CD | CW4: PRFRMNG_STTS_LE_ID | CX4: RTNG_MTHD_CD | CY4: RTNG_MTHD_NM | CZ4: INTRNL_RTNG | DA4: PD | DB4: INTRNL_RTNG_INCPTN | DC4: PD | DD4: INTRNL_RTNG_PRVS | DE4: PD | DF4: RTNG_SCL_CD | DG4: RTNG_SCL_NM | DH4: SNGL_PRPS_VHCL_CD | DI4: SNGL_PRPS_VHCL_NM | DJ4: EBA_CMPLNT_MRTR_ST_C19_CD | DK4: EBA_CMPLNT_MRTR_ST_C19_NM | DL4: TP_CMPLNT_MRTR_C19_CD | DM4: TP_CMPLNT_MRTR_C19_NM | DN4: FRBRNC_STTS_C19_CD | DO4: FRBRNC_STTS_C19_NM | DP4: SBJCT_PBLC_GRNT_SCHM_C19_CD | DQ4: SBJCT_PBLC_GRNT_SCHM_C19_NM | DR4: ISSR_ID_TYP_CD | DS4: ISSR_ID_TYP_NM | DT4: IGRNTR_ID_TYP_CD | DU4: IGRNTR_ID_TYP_NM | DV4: ISSR_CNTRY_CD | DW4: ISSR_CNTRY_NM | DX4: ISSR_ESA_2010_CD | DY4: ISSR_ESA_2010_NM | DZ4: LVRG_FNNC_FLG_CD | EA4: LVRG_FNNC_FLG_NM | EB4: ISSR_TYP_CD | EC4: ISSR_TYP_ID | ED4: VLTN_TYP_CD | EE4: VLTN_TYP_ID | EF4: INSTRMNT_CLSS_CD | EG4: INSTRMNT_CLSS_ID | EH4: PRMRY_ASST_CLSSF_CD | EI4: PRMRY_ASST_CLSSF_ID | EJ4: ASST_SCRT_CLSS_CD | EK4: ASST_SCRT_CLSS_ID | EL4: TYPE_OF_PLCMNT_CD | EM4: TYPE_OF_PLCMNT_ID | EN4: INSTR_SNRTY_CLSS_CD | EO4: INSTR_SNRTY_CLSS_ID | EP4: SRCS_ENCMBRNC_CD | EQ4: SRCS_ENCMBRNC_NM | ER4: LCR_BFFR_CTGRY_CD | ES4: LCR_BFFR_CTGRY_NM | ET4: PRDNTL_PRTFL_CD | EU4: PRDNTL_PRTFL_NM | EV4: INTRNL_SGMNT_CAT_MSTA_CD | EW4: INTRNL_SGMNT_CAT_MSTA_NM | EX4: INTRNL_SGMNT_CATGSUB_CD | EY4: INTRNL_SGMNT_CATGSUB_NM | EZ4: RSK_MTGTD_CCT_CD | FA4: RSK_MTGTD_CCT_NM | FB4: RSK_MTGTD_CCP_CD | FC4: RSK_MTGTD_CCP_NM | FD4: TYP_EP_SCR_CD | FE4: TYP_EP_SCR_NM | FF4: EP_SCR_CD | FG4: EP_SCR_NM | FH4: TYP_EMSSNS_LBL_CD/TYP_EPC_LBL_CD/TYP_EPC_LBL_PRVS_YR_CD/TYP_EP_SCR_PRVS_YR_CD | FI4: TYP_EMSSNS_LBL_NM/TYP_EPC_LBL_NM/TYP_EPC_LBL_PRVS_YR_NM/TYP_EP_SCR_PRVS_YR_NM | FJ4: EPC_LBL_CD/EPC_EMSSNS_LBL_CD/EPC_LBL_PRVS_YR_CD | FK4: EPC_LBL_NM/EPC_EMSSNS_LBL_NM/EPC_LBL_PRVS_YR_NM | FL4: ESG_SBSCTR_CD | FM4: ESG_SBSCTR_NM | FN4: BSNSS_AREA_CD | FO4: BSNSS_AREA_NM | FP4: SSTNBL_CTGRY_TXNMY_CD | FQ4: SSTNBL_CTGRY_TXNMY_NM | FR4: SSTNBL_CTGRY_CD | FT4: SSTNBL_CTGRY_NM | FY4: MNGMNT_PRDCT_CD | FZ4: MNGMNT_PRDCT_NM | GA4: ENVRNMNTL_OBJCTV_CD | GB4: ENVRNMNTL_OBJCTV_NM | GC4: TYP_ACTVTY_CD | GD4: TYP_ACTVTY_NM | GE4: LNS_CLLTRLZD_CLSSFCTN_CD | GF4: LNS_CLLTRLZD_CLSSFCTN_NM | GG4: INTRBSNSS_ADJ_COD_CD | GH4: INTRBSNSS_ADJ_COD_NM | GI4: MTHD_USD_INSTRMNT_SCP_1_CD | GJ4: MTHD_USD_INSTRMNT_SCP_1_NM | GK4: MTHD_USD_PRTCTN_SCP_1 _CD | GL4: MTHD_USD_PRTCTN_SCP_1 _NM | GM4: RL_STT_CRTFCTN_CD | GN4: RL_STT_CRTFCTN _NM | GO4: DNSH_DTL_CD | GP4: DNSH_DTL_NM | GQ4: SSTNBL_INDCTR_CD | GR4: SSTNBL_INDCTR_NM | GS4: TYP_HZRDS_INSRD_CD | GT4: TYP_HZRDS_INSRD_NM | GU4: VHCL_EMSSNS_LBL_CD | GV4: VHCL_EMSSNS_LBL_NM | GW4: CNCLLD_INSTRMNT_STTS_CD | GX4: CNCLLD_INSTRMNT_STTS_NM | GY4: PRSN_TYP_CD | GZ4: PRSN_TYP_NM | HA4: RFRNC_RT_CD | HB4: RFRNC_RT_NM | HC4: TYP_SCRTZTN_CD | HD4: TYP_SCRTZTN_NM | HE4: TYP_OFF_BLNC_PRDCT_CD | HF4: TYP_OFF_BLNC_PRDCT_NM | HG4: BLNC_SHT_RCGNTN_CD | HH4: BLNC_SHT_RCGNTN_NM | HI4: EXCLDD_LF_CD | HJ4: EXCLDD_LF_NM | HK4: US_PRCDS_CD | HL4: US_PRCDS_NM | HM4: FCLTY_TYP_CD | HN4: FCLTY_TYP_NM | HO4: CL_TYP_CD | HP4: FCLTY_TYP_NM | HQ4: TYP_RLTN_CD | HR4: TYP_RLTN_NM | HS4: CLMTC_ZN_CD | HT4: CLMTC_ZN_NM | HU4: SCAN_CD | HV4: SCAN_NM | HW4: TYP_DL_CD | HX4: TYP_DL_NM | HY4: DSTNTN_FNDS_CD | HZ4: DSTNTN_FNDS_NM | IA4: TYP_VHCL_CD | IB4: TYP_VHCL_NM
B5: Code | C5: Description | D5: Code | E5: Description | F5: Code | G5: Description | H5: Code | I5: Description | J5: Code | K5: Description | L5: Code | M5: Description | N5: Code | O5: Description | P5: Code | Q5: Description | R5: Code | S5: Description | T5: Code | U5: Description | V5: Code | W5: Description | X5: Code | Y5: Description | Z5: Code | AA5: Description | AB5: Code | AC5: Description | AD5: Code | AE5: Description | AF5: Code | AG5: Description | AH5: Code | AI5: Description | AJ5: Code | AK5: Description | AL5: Code | AM5: Description | AN5: Code | AO5: Description | AP5: Code | AQ5: Description | AR5: Code | AS5: Description | AT5: Code | AU5: Description | AV5: Code | AW5: Description | AX5: Code | AY5: Description | AZ5: Code | BA5: Description | BB5: Code | BC5: Description | BD5: Code | BE5: Description | BF5: Code | BG5: Description | BH5: Code | BI5: Description | BJ5: Code | BK5: Description | BL5: Code | BM5: Description | BN5: Code | BO5: Description | BP5: Code | BQ5: Description | BR5: Code | BS5: Description | BT5: Code | BU5: Description | BV5: Code | BW5: Description | BX5: Code | BY5: Description | BZ5: Code | CA5: Description | CB5: Code | CC5: Description | CD5: Code | CE5: Description | CF5: Code | CG5: Description | CH5: Code | CI5: Description | CJ5: Code | CK5: Description | CL5: Code | CM5: Description | CN5: Code | CO5: Description | CP5: Code | CQ5: Description | CR5: Code | CS5: Description | CT5: Code | CU5: Description | CV5: Code | CW5: Description | CX5: Code | CY5: Description | CZ5: Code | DA5: Description | DB5: Code | DC5: Description | DD5: Code | DE5: Description | DF5: Code | DG5: Description | DH5: Code | DI5: Description | DJ5: Code | DK5: Description | DL5: Code | DM5: Description | DN5: Code | DO5: Description | DP5: Code | DQ5: Description | DR5: Code | DS5: Description | DT5: Code | DU5: Description | DV5: Code | DW5: Description | DX5: Code | DY5: Description | DZ5: Code | EA5: Description | EB5: Code | EC5: Description | ED5: Code | EE5: Description | EF5: Code | EG5: Description | EH5: Code | EI5: Description | EJ5: Code | EK5: Description | EL5: Code | EM5: Description | EN5: Code | EO5: Description | EP5: Code | EQ5: Description | ER5: Code | ES5: Description | ET5: Code | EU5: Description | EV5: Code | EW5: Description | EX5: Code | EY5: Description | EZ5: Code | FA5: Description | FB5: Code | FC5: Description | FD5: Code | FE5: Description | FF5: Code | FG5: Description | FH5: Code | FI5: Description | FJ5: Code | FK5: Description | FL5: Code | FM5: Description | FN5: Code | FO5: Description | FP5: Code | FQ5: Description | FR5: Code | FS5: Description | FY5: Code | FZ5: Description | GA5: Code | GB5: Description | GC5: Code | GD5: Description | GE5: Code | GF5: Description | GG5: Code | GH5: Description | GI5: Code | GJ5: Description | GK5: Code | GL5: Description | GM5: Code | GN5: Description | GO5: Code | GP5: Description | GQ5: Code | GR5: Description | GS5: Code | GT5: Description | GU5: Code | GV5: Description | GW5: Code | GX5: Description | GY5: Code | GZ5: Description | HA5: Code | HB5: Description | HC5: Code | HD5: Description | HE5: Code | HF5: Description | HG5: Code | HH5: Description | HI5: Code | HJ5: Description | HK5: Code | HL5: Description | HM5: Code | HN5: Description | HO5: Code | HP5: Description | HQ5: Code | HR5: Description | HS5: Code | HT5: Description | HU5: Code | HV5: Description | HW5: Code | HX5: Description | HY5: Code | HZ5: Description | IA5: Code | IB5: Description
B6: 2 | C6: IFRS: Financial assets held for trading | D6: 1 | E6: Branch | F6: AED | G6: UAE Dirham | H6: AED | I6: UAE Dirham | J6: AED | K6: UAE Dirham | L6: AED | M6: UAE Dirham | N6: AED | O6: UAE Dirham | P6: 1 | Q6: No financial covenant to check | R6: 1 | S6: Full Covenant | T6: 14 | U6: Not in default | V6: 1 | W6: Non-performing | X6: 1 | Y6: Non-performing | Z6: 3 | AA6: Forborne: Refinanced debt | AB6: 21 | AC6: General allowances (GAAP) | AD6: 21 | AE6: General allowances (GAAP) | AF6: 1 | AG6: Collectively assessed | AH6: 1 | AI6: Specific. Going concern | AJ6: 1 | AK6: Annual | AL6: 1 | AM6: No legal actions taken | AN6: 1 | AO6: No legal actions taken | AP6: 1 | AQ6: Project finance loan | AR6: 4 | AS6: Margin lending | AT6: 1 | AU6: Annual | AV6: 1 | AW6: Recourse | AX6: 1 | AY6: IRB | AZ6: 1 | BA6: Collective approach | BB6: 1 | BC6: Underwritten or warehoused but not yet syndicated | BD6: 1 | BE6: Lead_arranger | BF6: 1 | BG6: Club_deal | BH6: 1 | BI6: Super-Senior | BJ6: 1 | BK6: French | BL6: 1 | BM6: Property development financing | BN6: 20 | BO6: Overdrafts | BP6: 1 | BQ6: Fixed | BR6: 1 | BS6: First rank fully registered mortgage | BT6: 1 | BU6: Aaa, AAA | BV6: 1 | BW6: Built | BX6: 1 | BY6: Not in construction | BZ6: 1 | CA6: Office | CB6: 1 | CC6: Counterparty estimation | CD6: 2 | CE6: Life insurance policies pledged | CF6: 1 | CG6: Fair value | CH6: 1 | CI6: National GAAP not consistent with IFRS | CJ6: 1 | CK6: Hard collection (judicial procedures engaged) | CL6: __ | CM6: Not assigned yet | CN6: 14 | CO6: Not in default | CP6: A | CQ6: Agriculture, forestry and fishing | CR6: 1 | CS6: Employed | CT6: 1 | CU6: Large enterprise | CV6: 1 | CW6: Non-performing | CX6: 10 | CY6: Rating - Grandes empresas | DH6: 1 | DI6: SPV with recourse | DJ6: 1 | DK6: Requested | DL6: 1 | DM6: Legislative | DN6: 1 | DO6: Requested | DP6: 1 | DQ6: Requested | DR6: BIC | DS6: BIC code | DT6: BIC | DU6: BIC code | DV6: 1C | DW6: IMF (International Monetary Fund) | DX6: S_11 | DY6: Non-financial corporations | DZ6: HLT | EA6: High Leveraged transaction | EB6: 1 | EC6: Other group entity | ED6: 1 | EE6: Mark-to-market | EF6: F_31 | EG6: Short-term debt securities | EH6: D | EI6: Debt - Debt securities are negotiable financial instruments serving as evidence of a debt. They are covered by the financial assets and liabilities (financial instrument) category “debt securities” (F.3) in ESA 2010. | EJ6: 1000 | EK6: Securitisation - Securitisation is the issuance of debt securities for which coupon or principal payments are backed by specified assets or by future income streams. | EL6: 1 | EM6: Public | EO6: Guarantee level | EP6: 1 | EQ6: SRCS_ENCMBRNC_NM | ER6: 1 | ES6: L1 | ET6: 1 | EU6: Trading book | EV6: 1 | EW6: STD - Regional governments or local authorities | EX6: 1 | EY6: Covered Bonds | EZ6: RMCT1 | FA6: Policy and legal risk | FB6: RMCP1 | FC6: Chronic | FD6: EPSD1 | FE6: Real | FF6: EPSC1 | FG6: 0; <= 100 | FH6: EPCD1 | FI6: Real | FJ6: EPCL1 | FK6: A | FL6: ESGS1 | FM6: Local Governments | FN6: BA1 | FO6: Private Banking | FQ6: Non financial corporations | FS6: DEDICATED PURPOSE | FT6: Green | FZ6: On Balance (excluding HfT) | GA6: 22 | GB6: Climate change mitigation | GC6: 02 | GD6: Transitional activity | GE6: FMC1 | GF6: Real estate. Commercial | GG6: 99569 | GH6: Vendor Activity Chile | GJ6: Corporate Funding | GL6: Motor vehicle loans | GM6: ESTT01 | GN6: HQE SB v4. Certification | GO6: DNSH01 | GP6: DNSH1 - Do not significant harm to climate change mitigation objective | GQ6: SSTNBL1 | GR6: Santander Specific | GS6: HZRDS01 | GT6: Cyclone | GU6: VHCL1 | GV6: *codelist to be completed by the Unit based on the local vehicle emissions label codification | GW6: C | GX6: Cancelled | GY6: N | GZ6: Natural person | HA6: ESTR-OVERNIGHT | HB6: ESTR-OVERNIGHT | HC6: SEC01 | HD6: Traditional securitization | HE6: MC41 | HF6: Financial guarantees given | HG6: REC01 | HH6: Entirely recognised | HI6: EXC01 | HJ6: Collective investment undertaking | HK6: USP01 | HL6: LBO/M&A (exclusive purchase financing) | HM6: FCL01 | HN6: Revolving credit Facilities (RCF) | HO6: CLO01 | HP6: Direct holding of CLO | HQ6: REL01 | HR6: The guarantee is the financed asset | HS6: CLM01 | HT6: Climatic Zone α | HU6: SCN01 | HV6: Do not serve | HW6: DEL01 | HX6: Syndicated loan (includes underwritten, best effort, club deals and other syndicated loans) | HY6: DST01 | HZ6: New money new customer | IA6: VEH01 | IB6: M1 - Vehicles used for the carriage of passengers and comprising not more than eight seats in addition to the driver's seat
B7: 3 | C7: nGAAP: Trading Financial assets | D7: 2 | E7: Internet | F7: AFN | G7: Afghani | H7: AFN | I7: Afghani | J7: AFN | K7: Afghani | L7: AFN | M7: Afghani | N7: AFN | O7: Afghani | P7: 2 | Q7: In line with all financial covenants | R7: 2 | S7: Covenant loose | T7: 18 | U7: Default because both unlikely to pay and more than 90/180 days past due | V7: 11 | W7: Performing | X7: 11 | Y7: Performing | Z7: 4 | AA7: Forborne: instruments with modified interest rate below market conditions | AB7: 23 | AC7: Stage 1 (IFRS) | AD7: 23 | AE7: Stage 1 (IFRS) | AF7: 2 | AG7: Individually assessed | AH7: 2 | AI7: Specific. Gone concern | AJ7: 3 | AK7: At creditor discretion | AL7: 2 | AM7: Under judicial administration, receivership or similar measures | AN7: 2 | AO7: Under judicial administration, receivership or similar measures | AP7: 2 | AQ7: Non-project finance loan | AR7: 5 | AS7: Debt financing | AT7: 4 | AU7: Bullet | AV7: 2 | AW7: No recourse | AX7: 2 | AY7: STANDARD | AZ7: 2 | BA7: Individial approach | BB7: 2 | BC7: Syndicated or sold but not yet settled and transferred to investors | BD7: 2 | BE7: Participant | BF7: 2 | BG7: Underwriting | BH7: 2 | BI7: Senior/First Lien | BJ7: 2 | BK7: German | BL7: 2 | BM7: Property investment financing | BN7: 51 | BO7: Credit card debt | BP7: 2 | BQ7: Variable | BR7: 2 | BS7: Subordinated rank fully registered mortgage | BT7: 2 | BU7: Aa1, AA+ | BV7: 2 | BW7: In construction | BX7: 2 | BY7: In construction and not operational | BZ7: 2 | CA7: Hotel | CB7: 2 | CC7: Creditor valuation | CD7: 3 | CE7: Other physical collaterals | CF7: 2 | CG7: Long-term sustainable value | CH7: 2 | CI7: IFRS | CJ7: 2 | CK7: Soft collection (all other) | CL7: AD | CM7: Andorra | CN7: 18 | CO7: Default because both unlikely to pay and more than 90/180 days past due | CP7: 1 | CQ7: Crop and animal production, hunting and related service activities | CR7: 2 | CS7: Employed with partial support (company subsidy) | CT7: 2 | CU7: Medium enterprise | CV7: 11 | CW7: Performing | CX7: 11 | CY7: Rating - Corporativa | DH7: 2 | DI7: SPV without recourse | DJ7: 2 | DK7: Granted | DL7: 2 | DM7: Non-Legislative | DN7: 2 | DO7: Granted | DP7: 2 | DQ7: Covered | DR7: IPF | DS7: Investment/Pension fund identifier | DT7: IPF | DU7: Investment/Pension fund identifier | DV7: 1D | DW7: WTO (World Trade Organisation) | DX7: S_11001 | DY7: Non-financial corporations - public | DZ7: LFT | EA7: Leveraged finance transaction | EB7: 2 | EC7: Third party | ED7: 2 | EE7: Mark-to-model | EF7: F_32 | EG7: Long-term debt securities | EH7: D.1 | EI7: Bond - Bonds and debentures are long-term debt securities that give the holders the unconditional right to fixed payments or contractually determined variable payments on a specified date or dates, that is, the earning of interest is not dependent on earnings of the debtors. Bonds and debentures also give holders the unconditional right to fixed sums as payments to the creditor on a specified date or dates. | EJ7: 1100 | EK7: Asset-backed security (ABS) - A bond, created through securitisation, whose coupon payments and principal repayments are dependent on a pool of assets, either purchased in the secondary market or from the balance sheet of an original asset owner; excluding mortgages. | EL7: 2 | EM7: Private | EN7: 1XX | EO7: Unguaranteed - In case of unguaranteed securities, there are no obligations to guarantors to make payments to the holder of the security if the issuer fails to meet the obligation to make repayments arising under the instrument secured by the guarantor. | EP7: 5 | EQ7: Central bank funding - Central bank funding (of all types, including repos), in accordance with the European Banking Authority’s (EBA) implementing technical standards on asset encumbrance reporting as referred to in Article 99(5) and Article 100 of Regulation (EU) No 575/2013. | ER7: 2 | ES7: L2A | ET7: 2 | EU7: Non-trading book | EV7: 2 | EW7: STD - Public sector entities | EX7: 4 | EY7: Exposures secured by mortgages on immovable property | EZ7: RMCT2 | FA7: Technology risk | FB7: RMCP2 | FC7: Acute | FD7: EPSD2 | FE7: Estimated | FF7: EPSC2 | FG7: > 100; <= 200 | FH7: EPCD2 | FI7: Estimated | FJ7: EPCL2 | FK7: B | FL7: ESGS2 | FM7: Sovereigns | FN7: BA2 | FO7: Individuals | FP7: SCATX01 | FQ7: Non financial corporations - General purpose | FU7: Energy | FZ7: Loans & advances (customers and credit institutions) | GA7: 23 | GB7: Climate change adaptation | GC7: 05 | GD7: Pure Activity | GE7: FMC2 | GF7: Real estate. Residential | GG7: 99505 | GH7: Distribution BdI to Commercial (Eng) | GJ7: Reported emissions | GL7: Actual vehicle - specific emissions | GM7: ESTT02 | GN7: Buildings that have a PED that is 10% below the Net Zero Energy Building CertificationTM (NZEB) | GO7: DNSH02 | GP7: DNSH2 - Do not significant harm to climate change adaptation | GQ7: SSTNBL2 | GR7: Taxonomy Specific | GS7: HZRDS02 | GT7: Winter storm | GU7: VHCL1 | GW7: M | GX7: Interannual cancelled instrument | GY7: L | GZ7: Legal person | HA7: TERM ESTR-1W | HB7: TERM ESTR-1W | HC7: SEC02 | HD7: Synthetic securitization | HE7: MC42 | HF7: Loan commitments given | HG7: REC02 | HH7: Recognised to the extent of the institution’s continuing involvement | HI7: EXC02 | HJ7: Securitisations | HK7: USP02 | HL7: Refinancing | HM7: FCL02 | HN7: Bullet term loans | HO7: CLO02 | HP7: CLO warehousing first lien | HQ7: REL02 | HR7: The guarantee is not the financed asset | HS7: CLM02 | HT7: Climatic Zone A | HU7: SCN02 | HV7: Specialised | HW7: DEL02 | HX7: Bilateral loan | HY7: DST02 | HZ7: New money existing customer | IA7: VEH02 | IB7: M2 - Vehicles used for the carriage of passengers, comprising more than eight seats in addition to the driver's seat, and having a maximum mass not exceeding 5 tonnes
B8: 4 | C8: IFRS: Financial assets designated at fair value through profit or loss | D8: 3 | E8: Broker | F8: ALL | G8: Lek | H8: ALL | I8: Lek | J8: ALL | K8: Lek | L8: ALL | M8: Lek | N8: ALL | O8: Lek | P8: 3 | Q8: In breach with at least one non-material financial covenant | R8: 3 | S8: Covenant light | T8: 19 | U8: Default because unlikely to pay | Z8: 5 | AA8: Forborne: instruments with other modified terms and conditions | AB8: 24 | AC8: Stage 2 (IFRS) | AD8: 24 | AE8: Stage 2 (IFRS) | AH8: 3 | AI8: Specific. Other | AJ8: 8 | AK8: Monthly | AL8: 3 | AM8: Bankruptcy / insolvency | AN8: 3 | AO8: Bankruptcy / insolvency | AR8: 6 | AS8: Imports | AT8: 8 | AU8: Monthly | BB8: 3 | BC8: Final retained hold exposure (incl undrawn RCF) | BD8: 3 | BE8: Other | BF8: 3 | BG8: Best_effort | BH8: 3 | BI8: Subordinated/Second and Third Lien | BJ8: 3 | BK8: Fixed amortisation schedule | BN8: 71 | BO8: Trade receivables | BP8: 3 | BQ8: Mixed | BR8: 3 | BS8: Partly registered mortgage with registered mandate to register the remainder | BT8: 3 | BU8: Aa2, AA | BV8: 3 | BW8: Land bank without zoning permit | BX8: 3 | BY8: In construction and partially operational | BZ8: 3 | CA8: Shopping | CB8: 3 | CC8: Mark-to-market | CD8: 4 | CE8: Credit derivatives | CF8: 3 | CG8: Market value | CH8: 3 | CI8: National GAAP consistent with IFRS | CL8: AE | CM8: United Arab Emirates (the) | CN8: 19 | CO8: Default because unlikely to pay | CP8: 1.1 | CQ8: Growing of non-perennial crops | CR8: 3 | CS8: Protected life-time employment (civil servant) | CT8: 3 | CU8: Small enterprise | CX8: 12 | CY8: Rating - Promotores Inmobiliarios | DH8: 3 | DI8: Other type of entity | DJ8: 3 | DK8: Extended | DN8: 3 | DO8: Extended | DP8: 3 | DQ8: Covered_called | DR8: LEI | DS8: Legal Entity Identifier | DT8: LEI | DU8: Legal Entity Identifier | DV8: 1E | DW8: IBRD (International Bank for Reconstruction and Development) | DX8: S_11002 | DY8: Non-financial corporations - national private | DZ8: NLF | EA8: Not leveraged finance transaction | EH8: D.11 | EI8: Straight bond - A bond without any further special characteristics listed separately. | EJ8: 1101 | EK8: Auto loans ABS - Detailed asset type breakdown of ABSs mainly in accordance with definitions of European and American Securitisation Forum. | EN8: 2XX | EO8: Government / Treasury guarantee - A guarantee is provided by the government / treasury that would oblige the guarantor to make payments to the holder of the security if the issuer fails to meet the obligation to make repayments arising under the instrument secured by the guarantor. | EP8: 6 | EQ8: Exchange traded derivatives - Exchange traded derivatives in accordance with the EBA’s implementing technical standards on asset encumbrance reporting as referred to in Article 99(5) and Article 100 of Regulation (EU) No 575/2013. | ER8: 3 | ES8: L2B | EV8: 3 | EW8: STD - Multilateral Development Banks | EX8: 5 | EY8: Commercial mortgages | EZ8: RMCT3 | FA8: Reputational risk | FB8: RMCP3 | FC8: Non mitigated | FF8: EPSC3 | FG8: > 200; <= 300 | FJ8: EPCL3 | FK8: C | FL8: ESGS3 | FM8: Investment firms | FN8: BA3 | FO8: Companies | FQ8: Non financial corporations - Specific purpose | FV8: Renewable energy | FY8: PRDCT010101 | FZ8: Mortgages | GA8: 24 | GB8: Sustainable use and protection of water and marine resources | GC8: 01 | GD8: Enabling activity | GE8: FMC3 | GF8: Other real collateral | GG8: 99006 | GH8: Sales Activity Portugal | GI8: IM01 | GJ8: Audited emissions of the counterparty | GK8: PM01 | GL8: Based on fuel consumption | GM8: ESTT03 | GN8: Low-Carbon Buildings Climate Bond Initiative (CBI) Certification | GO8: DNSH03 | GP8: DNSH3 - Do not significant harm to sustainable use and protection of water and marine resources | GQ8: SSTNBL3 | GR8: Santander Specific & Taxonomy Specific | GS8: HZRDS03 | GT8: Hail | GU8: VHCL1 | GW8: I | GX8: Intermittent instrument | HA8: TERM ESTR-1M | HB8: TERM ESTR-1M | HC8: SEC03 | HD8: Not securitized | HE8: MC4301 | HF8: Non-financial guarantees given (Other commitments given) | HG8: REC03 | HH8: Entirely derecognized | HI8: EXC03 | HJ8: Credit derivatives | HK8: USP03 | HL8: Recapitalization | HM8: FCL03 | HN8: Amortising term loans | HO8: CLO03 | HP8: CLO warehousing not first lien | HQ8: REL03 | HR8: The financed asset is not the instrument’s guarantee | HS8: CLM03 | HT8: Climatic Zone B | HU8: SCN03 | HV8: Intensive | HW8: DEL03 | HX8: Primary Market Purchases | HY8: DST03 | HZ8: Existing money | IA8: VEH03 | IB8: M3 - Vehicles used for the carriage of passengers, comprising more than eight seats in addition to the driver's seat, and having a maximum mass exceeding 5 tonnes
B9: 5 | C9: nGAAP: Available-for-sale financial assets | D9: 4 | E9: Other | F9: AMD | G9: Armenian Dram | H9: AMD | I9: Armenian Dram | J9: AMD | K9: Armenian Dram | L9: AMD | M9: Armenian Dram | N9: AMD | O9: Armenian Dram | P9: 4 | Q9: In breach with at least one material financial covenant | R9: 4 | S9: No covenant | T9: 20 | U9: Default because more than 90/180 days past due | Z9: 8 | AA9: Not forborne or renegotiated | AB9: 25 | AC9: Stage 3 (IFRS) | AD9: 25 | AE9: Stage 3 (IFRS) | AH9: 4 | AI9: Mixed approaches | AJ9: 12 | AK9: Other than overnight, monthly, quarterly, half yearly, annually or at creditor discretion | AL9: 4 | AM9: Other legal measures | AN9: 4 | AO9: Other legal measures | AR9: 7 | AS9: Exports | AT9: 15 | AU9: Other than monthly, quarterly, half yearly, annually, bullet or zero coupon | BB9: 4 | BC9: Distributed and fully transferred to other lenders/investors | BF9: 4 | BG9: Other | BH9: 4 | BI9: Unsecured (senior or below) | BJ9: 4 | BK9: Bullet | BN9: 80 | BO9: Finance leases | BR9: 4 | BS9: Conditional mortgage | BT9: 4 | BU9: Aa3, AA- | BV9: 4 | BW9: Land bank building permit | BX9: 4 | BY9: Constructed and fully operational | BZ9: 4 | CA9: Leisure | CB9: 4 | CC9: Other type of valuation | CD9: 5 | CE9: Financial guarantees other than credit derivatives | CF9: 4 | CG9: Notional amount | CL9: AF | CM9: Afghanistan | CN9: 20 | CO9: Default because more than 90/180 days past due | CP9: 1.11 | CQ9: Growing of cereals (except rice), leguminous crops and oil seeds | CR9: 4 | CS9: Self-employed | CT9: 4 | CU9: Micro enterprise | CX9: 13 | CY9: Rating - Sector Público | DJ9: 4 | DK9: Expired | DN9: 4 | DO9: Expired | DP9: 4 | DQ9: Extended | DR9: NBR | DS9: National Business register identifier | DT9: NBR | DU9: National Business register identifier | DV9: 1F | DW9: IDA (International Development Association) | DX9: S_11003 | DY9: Non-financial corporations - foreign controlled | EH9: D.12 | EI9: Securitisation bond - Securitisation is the issuance of debt securities for which coupon or principal payments are backed by specified assets or by future income streams. | EJ9: 1102 | EK9: Consumer loans ABS - Detailed asset type breakdown of ABSs mainly in accordance with definitions of European and American Securitisation Forum. | EN9: 8XX | EO9: Other guarantee - A guarantee is provided by a non-government entity that would oblige the guarantor to make payments to the holder of the security if the issuer fails to meet the obligation to make repayments arising under the instrument secured by the guarantor. | EP9: 7 | EQ9: Over-the-counter derivatives - Over-the-counter derivatives in accordance with the EBA’s implementing technical standards on asset encumbrance reporting as referred to in Article 99(5) and Article 100 of Regulation (EU) No 575/2013. | EV9: 4 | EW9: STD - International Organisations | EX9: 11 | EY9: SPL. Project Finance | EZ9: RMCT4 | FA9: Market risk | FF9: EPSC4 | FG9: > 300; <= 400 | FJ9: EPCL4 | FK9: D | FL9: ESGS4 | FM9: Management companies | FN9: BA4 | FO9: SMEs | FP9: SCATX02 | FQ9: Non financial corporations - Specific purpose - Building acquisition - Not eligible | FR9: 210101 | FW9: Solar photovoltaic - Electricity generation | FX9: A.1.1. Electricity generation using solar photovoltaic technology | FZ9: Products Added value CIB | GA9: 25 | GB9: Transition to a circular economy | GE9: FMC4 | GF9: No collateral real | GG9: 99010 | GH9: Holding Peru | GI9: IM02 | GJ9: Audited emissions of the group | GK9: PM02 | GL9: Based on vehicle distance | GM9: ESTT04 | GN9: Leed (Gold or above) | GO9: DNSH04 | GP9: DNSH4 - Do not significant harm to transition to a circular economy | GQ9: SSTNBL4 | GR9: Taxonomy Specific & Aligned under other criteria | GS9: HZRDS04 | GT9: Tornado | GU9: …. | GW9: N | GX9: Not cancelled | HA9: TERM ESTR-3M | HB9: TERM ESTR-3M | HE9: MC4302 | HF9: Other commitments given, rest (Other commitments given) | HI9: EXC04 | HJ9: Trade Finance | HK9: USP04 | HL9: Other | HM9: FCL04 | HN9: High yield bond | HO9: CLO04 | HP9: Other CLOs (direct or indirect) | HS9: CLM04 | HT9: Climatic Zone C | HU9: SCN04 | HV9: Proactive | HW9: DEL04 | HX9: Secondary Markets Purchases | HY9: DST04 | HZ9: Existing money with increase | IA9: VEH04 | IB9: N1 - Vehicles used for the carriage of goods and having a maximum mass not exceeding 3.5 tonnes
B10: 6 | C10: IFRS: Financial assets at amortised cost | F10: ANG | G10: Netherlands Antillean Guilder | H10: ANG | I10: Netherlands Antillean Guilder | J10: ANG | K10: Netherlands Antillean Guilder | L10: ANG | M10: Netherlands Antillean Guilder | N10: ANG | O10: Netherlands Antillean Guilder | Z10: 9 | AA10: Renegotiated instrument without forbearance measures | AB10: 26 | AC10: Specific allowances (GAAP) | AD10: 26 | AE10: Specific allowances (GAAP) | AJ10: 16 | AK10: Overnight | AR10: 8 | AS10: Construction investment | AT10: 18 | AU10: Quarterly | BH10: 5 | BI10: Other (please specify in comments) | BJ10: 5 | BK10: Amortisation types other than French, German, Fixed amortisation schedule or bullet | BN10: 1000 | BO10: Deposits other than reverse repurchase agreements | BR10: 5 | BS10: Other - secured collateral | BT10: 5 | BU10: A1, A+ | BZ10: 5 | CA10: Parking | CB10: 5 | CC10: Third-party valuation | CD10: 7 | CE10: Other protection | CF10: 5 | CG10: Types of protection values other than notional amount, market value, fair value or long-term sustainable value | CL10: AG | CM10: Antigua and Barbuda | CP10: 1.12 | CQ10: Growing of rice | CR10: 5 | CS10: Unemployed | CX10: 14 | CY10: Rating - Entidades Financieras bancos | DP10: 5 | DQ10: Expired | DR10: NCB | DS10: Identifier assigned by the National Central Bank | DT10: NCB | DU10: Identifier assigned by the National Central Bank | DV10: 1G | DW10: ICSID (International Centre for Settlement of Investment Disputes) | DX10: S_121 | DY10: The central bank | EH10: D.121 | EI10: Traditional securitisation - In case of traditional securitisation, the transfer of credit risk takes place by transferring the assets subject to that risk. | EJ10: 1103 | EK10: Credit card receivables ABS - Detailed asset type breakdown of ABSs mainly in accordance with definitions of European and American Securitisation Forum. | EN10: 9XX | EO10: Guarantee level - No detailed information available - To be reported, in case the guarantee level is not available / applicable. | EP10: 8 | EQ10: Deposits - repurchase agreements other than to central banks - Repurchase agreements other than to central banks in accordance with the EBA’s implementing technical standards on asset encumbrance reporting as referred to in Article 99(5) and Article 100 of Regulation (EU) No 575/2013. | EV10: 6 | EW10: STD - Institutions and Corporates with a short-term credit assessment | EX10: 12 | EY10: SPL. Asset Financing | EZ10: RMCT5 | FA10: Non mitigated | FF10: EPSC5 | FG10: > 400; <= 500 | FJ10: EPCL5 | FK10: E | FL10: ESGS5 | FM10: Insurance undertakings | FN10: BA5 | FO10: Institutions | FP10: SCATX03 | FQ10: Non financial corporations - Specific purpose - Building acquisition - Eligible, not aligned | FR10: 210102 | FW10: Concentrated solar power (CSP) - Electricity generation | FX10: A.1.2. Electricity generation using concentrated solar power (CSP) technology | FY10: PRDCT01010201 | FZ10: Project & Acquisition Finance | GA10: 26 | GB10: Pollution prevention and control | GG10: 99809 | GH10: Shared Book NYCHILE | GI10: IM03 | GJ10: Non audited emissions calculated by the counterparty | GL10: Estimated vehicle - specific emissions | GM10: ESTT05 | GN10: BREEAM ((Excellent or above where “Very good” can be acceptable with a minimum score of 70% in the Energy category) | GO10: DNSH05 | GP10: DNSH5 - Do not significant harm to pollution prevention and control | GQ10: SSTNBL5 | GR10: Aligned under other criteria | GS10: HZRDS05 | GT10: Lightning | HA10: TERM ESTR-6M | HB10: TERM ESTR-6M | HI10: EXC05 | HJ10: Specialised Lending | HK10: USP05 | HL10: LBO Others | HM10: FCL05 | HN10: Other facilities (Capex, Mezzanine,…) | HS10: CLM05 | HT10: Climatic Zone D | HU10: SCN05 | HV10: Ordinary | HW10: DEL05 | HX10: Guarantee | HY10: DST05 | HZ10: Existing money with decrease | IA10: VEH05 | IB10: N2 - Vehicles used for the carriage of goods and having a maximum mass exceeding 3.5 tonnes but not exceeding 12 tonnes
B11: 7 | C11: nGAAP: Non-trading non-derivative financial assets measured at fair value through profit or loss | F11: AOA | G11: Kwanza | H11: AOA | I11: Kwanza | J11: AOA | K11: Kwanza | L11: AOA | M11: Kwanza | N11: AOA | O11: Kwanza | AJ11: 18 | AK11: Quarterly | AR11: 9 | AS11: Working capital facility | AT11: 19 | AU11: Semi-annually | BN11: 1001 | BO11: Revolving credit other than overdrafts and credit card debt | BR11: 6 | BS11: Other - unsecured collateral | BT11: 6 | BU11: A2, A | BZ11: 6 | CA11: Logistic | CD11: 8 | CE11: Residential real estate collateral | CL11: AI | CM11: Anguilla | CP11: 1.13 | CQ11: Growing of vegetables and melons, roots and tubers | CR11: 6 | CS11: Student | CX11: 37 | CY11: Rating - Ent.Financ. no bancos (fondos) | DR11: NSA | DS11: National Supervisory Authority code | DT11: NSA | DU11: National Supervisory Authority code | DV11: 1H | DW11: UNESCO (United Nations Educational, Scientific and Cultural Organisation) | DX11: S_122 | DY11: Deposit-taking corporations except the central bank | EH11: D.122 | EI11: Synthetic securitisation - In case of synthetic securitisation, the transfer of credit risk takes place by means of instruments that provide insurance against credit losses, without an actual transfer of assets taking place. | EJ11: 1104 | EK11: Equipment leases ABS - Detailed asset type breakdown of ABSs mainly in accordance with definitions of European and American Securitisation Forum. | EO11: Rank level | EP11: 9 | EQ11: Deposits other than repurchase agreements - Deposits other than repurchase agreements in accordance with the EBA’s implementing technical standards on asset encumbrance reporting as referred to in Article 99(5) and Article 100 of Regulation (EU) No 575/2013. | EV11: 7 | EW11: STD - Units or shares in Collective Investment undertakings | EX11: 13 | EY11: SPL. Financing of basic products | FF11: EPSC6 | FG11: > 500 | FJ11: EPCL6 | FK11: F | FL11: ESGS6 | FM11: Rest of other financial corporation | FN11: BA6 | FO11: Consumer | FP11: SCATX04 | FQ11: Non financial corporations - Specific purpose - Building acquisition - Eligible and aligned | FR11: 210107 | FW11: Solar energy - Cogeneration heat/cool/power | FX11: A.1.17. Cogeneration of heat/cool and power from solar energy | FY11: PRDCT01010202 | FZ11: Syndicated Loans | GA11: 27 | GB11: Protection and restoration of biodiversity and ecosystems. | GG11: 99228 | GH11: Corporate Trade Results Spain | GI11: IM04 | GJ11: Non audited emissions calculated by the group | GK11: PM03 | GL11: Average distance per province/state | GM11: ESTT06 | GN11: DGNB Certification (Gold or above) | GO11: DNSH06 | GP11: DNSH6 - Do not significant harm to protection and restoration of biodiversity and ecosystems. | GQ11: SSTNBL6 | GR11: Not eligible/aligned | GS11: HZRDS06 | GT11: River flood | HA11: TERM ESTR-12M | HB11: TERM ESTR-12M | HI11: EXC06 | HJ11: SME | HS11: CLM06 | HT11: Climatic Zone E | HW11: DEL06 | HX11: Others | IA11: VEH06 | IB11: N3 - Vehicles used for the carriage of goods and having a maximum mass exceeding 12 tonnes
B12: 8 | C12: IFRS: Financial assets at fair value through other comprehensive income | F12: ARS | G12: Argentine Peso | H12: ARS | I12: Argentine Peso | J12: ARS | K12: Argentine Peso | L12: ARS | M12: Argentine Peso | N12: ARS | O12: Argentine Peso | AJ12: 19 | AK12: Semi-annually | AR12: 11 | AS12: Purposes other than real estate purchase, margin lending, debt financing, imports, exports, construction investment, working capital facility | AT12: 22 | AU12: Zero-coupon | BN12: 1002 | BO12: Credit lines other than revolving credit | BT12: 7 | BU12: A3, A- | BZ12: 7 | CA12: Residential | CD12: 9 | CE12: Offices and commercial premises | CL12: AL | CM12: Albania | CP12: 1.14 | CQ12: Growing of sugar cane | CR12: 7 | CS12: Pensioner | CX12: 38 | CY12: Rating - Ent.Fin. no bancos (no fondos) | DR12: NSI | DS12: National Statistical Institute number | DT12: NSI | DU12: National Statistical Institute number | DV12: 1J | DW12: FAO (Food and Agriculture Organisation) | DX12: S_12201 | DY12: Deposit-taking corporations except the central bank - public | EH12: D.129 | EI12: Other securitisation - A securitisation that is of a type not listed separately. | EJ12: 1105 | EK12: Home equity loans ABS - Detailed asset type breakdown of ABSs mainly in accordance with definitions of European and American Securitisation Forum. | EN12: X1X | EO12: Subordinated - Junior level - Subordinated securities have a lower priority than the issuer’s other securities in the event of liquidation. A further differentiation can be made between Junior and Senior level with the Senior level having a higher priority. | EP12: 10 | EQ12: Debt securities issued - covered bonds securities - Covered bonds securities issued in accordance with the EBA’s implementing technical standards on asset encumbrance reporting as referred to in Article 99(5) and Article 100 of Regulation (EU) No 575/2013. | EV12: 8 | EW12: STD - Central Governments or Central Banks | EX12: 14 | EY12: SPL. Financing of root assets generators of income. | FF12: EPSC7 | FG12: Without EP Score | FJ12: EPCL7 | FK12: G | FN12: BA7 | FO12: M & A - Mergers and Acquisitions | FP12: SCATX05 | FQ12: Non financial corporations - Specific purpose - Building renovation - Eligible, not aligned | FR12: 210109 | FW12: Solar thermal - Production of heat/cool | FX12: A.1.21. Production of heat/cool from solar thermal heating | FY12: PRDCT01010203 | FZ12: Capital Finance | GA12: 28 | GB12: The exposure does not contribute to any of the defined objectives | GG12: 99051 | GH12: Remote book Treasury | GJ12: Emissions based on physical activity | GK12: PM04 | GL12: Average distance per country | GM12: ESTT07 | GN12: EDGE (Advanced or Zero Carbon) | GS12: HZRDS07 | GT12: Flash flood | HA12: EURIBOR-1W | HB12: EURIBOR-1W | HI12: EXC07 | HJ12: Companies where Santander exposure is <5MM euros | IA12: VEH07 | IB12: L1 - A two-wheeled vehicle with an engine cylinder capacity not exceeding 50 cm3 and whatever the means of propulsion a maximum design speed not exceeding 50 km/h
B13: 9 | C13: nGAAP: Non-trading non-derivative financial assets measured at fair value to equity | F13: AUD | G13: Australian Dollar | H13: AUD | I13: Australian Dollar | J13: AUD | K13: Australian Dollar | L13: AUD | M13: Australian Dollar | N13: AUD | O13: Australian Dollar | AR13: 12 | AS13: Residential real estate purchase | BN13: 1003 | BO13: Reverse repurchase agreements | BT13: 8 | BU13: Baa1, BBB+ | BZ13: 8 | CA13: Mixed | CD13: 10 | CE13: Commercial real estate collateral | CL13: AM | CM13: Armenia | CP13: 1.15 | CQ13: Growing of tobacco | CR13: 8 | CS13: Other | CX13: 15 | CY13: Rating - Soberanos | DR13: OTHER | DS13: Other identifer type | DT13: OTHER | DU13: Other identifer type | DV13: 1K | DW13: WHO (World Health Organisation) | DX13: S_12202 | DY13: Deposit-taking corporations except the central bank - national private | EH13: D.13 | EI13: Covered bond - Covered bonds are debt securities issued by a financial corporation, or fully guaranteed by a financial corporation. In case of default of the issuing or guarantor financial corporation, bond holders have a priority claim on the cover pool, in addition to their ordinary claim on the financial corporation. | EJ13: 1106 | EK13: Manufactured housing leases ABS - Detailed asset type breakdown of ABSs mainly in accordance with definitions of European and American Securitisation Forum. | EN13: X2X | EO13: Subordinated - Senior level - Subordinated securities have a lower priority than the issuer’s other securities in the event of liquidation. A further differentiation can be made between Junior and Senior level with the Senior level having a higher priority. | EP13: 11 | EQ13: Debt securities issued - asset-backed securities - Asset-backed securities (ABS) issued in accordance with the EBA’s implementing technical standards on asset encumbrance reporting as referred to in Article 99(5) and Article 100 of Regulation (EU) No 575/2013. | EV13: 9 | EW13: IRB - Retail | EX13: 15 | EY13: SPL. Financing of highly volatile retail root assets | FJ13: EPCL8 | FK13: Without EPC label | FN13: BA8 | FO13: ECM - Equity Capital Markets | FP13: SCATX06 | FQ13: Non financial corporations - Specific purpose - Building renovation - Eligible and aligned | FR13: 210103 | FW13: Wind power - Electricity generation | FX13: A.1.3. Electricity generation from wind power | FY13: PRDCT01010204 | FZ13: Asset Based Finance (ABF) | GG13: 99122 | GH13: ACS(Repayable Loans) | GI13: IM05 | GJ13: Based on energy consumption | GL13: Estimated vehicle - unspecific emissions | GM13: ESTT08 | GN13: Passivhaus (Classic or above) | GS13: HZRDS08 | GT13: Storm surge | GU13: VHCL8 | GV13: Without vehicle label | HA13: EURIBOR-1M | HB13: EURIBOR-1M | HI13: EXC08 | HJ13: Financial institutions, public sector entities or similar | IA13: VEH08 | IB13: L2 - A three-wheeled vehicle of any wheel arrangement with an engine cylinder capacity not exceeding 50 cm3 and whatever the means of propulsion a maximum design speed not exceeding 50 km/h
B14: 10 | C14: nGAAP: Loans and receivables | F14: AWG | G14: Aruban Florin | H14: AWG | I14: Aruban Florin | J14: AWG | K14: Aruban Florin | L14: AWG | M14: Aruban Florin | N14: AWG | O14: Aruban Florin | AR14: 13 | AS14: Commercial real estate purchase | BN14: 1004 | BO14: Loans other than overdrafts, convenience credit, extended credit, credit card credit, revolving credit other than credit card credit, reverse repurchase agreements, trade receivables and financial leases | BT14: 9 | BU14: Baa2, BBB | BZ14: 9 | CA14: Other | CD14: 12 | CE14: Securities | CL14: AO | CM14: Angola | CP14: 1.16 | CQ14: Growing of fibre crops | CX14: 16 | CY14: Rating - Project Finance | DR14: PS | DS14: Public sector entity identifier | DT14: PS | DU14: Public sector entity identifier | DV14: 1L | DW14: IFAD (International Fund for Agricultural Development) | DX14: S_12203 | DY14: Deposit-taking corporations except the central bank - foreign controlled | EH14: D.131 | EI14: Jumbo covered bond - Jumbo covered bonds are covered bonds issued in accordance with the requirements in Article 52(4) of Directive 2009/65/EC and with an issuing volume of at least EUR 1 billion, for which at least three market-makers provide regular bid and ask quotes. | EJ14: 1107 | EK14: Small and medium-sized enterprises (SME) loans ABS - Detailed asset type breakdown of ABSs mainly in accordance with definitions of European and American Securitisation Forum. | EN14: X3X | EO14: Subordinated - No further breakdown available - Subordinated securities have a lower priority than the issuer’s other securities in the event of liquidation. A further differentiation can be made between Junior and Senior level with the Senior level having a higher priority. | EP14: 12 | EQ14: Debt securities issued - other than covered bonds and ABSs - Debt securities issued other than covered bonds and ABSs in accordance with the EBA’s implementing technical standards on asset encumbrance reporting as referred to in Article 99(5) and Article 100 of Regulation (EU) No 575/2013. | EV14: 10 | EW14: STD - Institutions | EX14: 16 | EY14: SME (Small & medium companies) | FN14: BA9 | FO14: Corporate Equity Derivatives | FP14: SCATX07 | FQ14: Non financial corporations - Specific purpose - Motor vehicle loans - Eligible, not aligned | FR14: 210104 | FW14: Ocean energy technologies - Electricity generation | FX14: A.1.4. Electricity generation from ocean energy technologies | FY14: PRDCT01010205 | FZ14: Leveraged Finance | GG14: 95001 | GH14: Shared Income London | GI14: IM06 | GJ14: Based on production | GK14: PM05 | GL14: Distance by country/state - known vehicle type | GM14: ESTT09 | GN14: PED within the top 15% | GS14: HZRDS09 | GT14: Sea level rise | HA14: EURIBOR-3M | HB14: EURIBOR-3M | HI14: EXC09 | HJ14: Investment Grade | IA14: VEH09 | IB14: L3 - A two-wheeled vehicle with an engine cylinder capacity in the case of a thermic engine exceeding 50 cm3 or whatever the means of propulsion a maximum design speed exceeding 50 km/h
B15: 12 | C15: nGAAP: Held-to-maturity investments | F15: AZN | G15: Azerbaijanian Manat | H15: AZN | I15: Azerbaijanian Manat | J15: AZN | K15: Azerbaijanian Manat | L15: AZN | M15: Azerbaijanian Manat | N15: AZN | O15: Azerbaijanian Manat | BN15: 1005 | BO15: Debt securities | BT15: 10 | BU15: Baa3, BBB- | CD15: 13 | CE15: Gold | CL15: AQ | CM15: Antarctica | CP15: 1.19 | CQ15: Growing of other non-perennial crops | CX15: 21 | CY15: Rating - Administraciones Públicas | DR15: RIAD | DS15: RIAD Code | DT15: RIAD | DU15: RIAD Code | DV15: 1M | DW15: IFC (International Finance Corporation) | DX15: S_123 | DY15: Money market funds (MMFs) | EH15: D.139 | EI15: Other covered bond - Covered bonds other than jumbo covered bonds. | EJ15: 1108 | EK15: Student loans ABS - Detailed asset type breakdown of ABSs mainly in accordance with definitions of European and American Securitisation Forum. | EN15: X4X | EO15: Senior - Senior securities are required to be repaid before subordinated securities. | EP15: 13 | EQ15: Other sources of encumbrance - Other sources of encumbrance in accordance with the EBA’s implementing technical standards on asset encumbrance reporting as referred to in Article 99(5) and Article 100 of Regulation (EU) No 575/2013. | EV15: 11 | EW15: IRB - Securitisation | EX15: 17 | EY15: Revolving | FN15: BA10 | FO15: Project and Acquisition Finance | FP15: SCATX08 | FQ15: Non financial corporations - Specific purpose - Motor vehicle loans - Eligible and aligned | FR15: 210105 | FW15: Hydropower - Electricity generation | FX15: A.1.5. Electricity generation from hydropower | FY15: PRDCT01010206 | FZ15: Export & Agency Finance | GG15: 95012 | GH15: Equity London | GJ15: Emissions based on economic activity | GK15: PM06 | GL15: Distance by country/state - unknown vehicle type | GM15: ESTT10 | GN15: Green Globes (Three globes or above) | GS15: HZRDS10 | GT15: Wildfire | HA15: EURIBOR-6M | HB15: EURIBOR-6M | IA15: VEH10 | IB15: L4 - A vehicle with three wheels asymmetrically arranged in relation to the longitudinal median plane with an engine cylinder capacity in the case of a thermic engine exceeding 50 cm3 or whatever the means of propulsion a maximum design speed exceeding 50 km/h (motor cycles with sidecars)
B16: 13 | C16: nGAAP: Non-trading non-derivative financial instruments measured at a cost-based method | F16: BAM | G16: Convertible Mark | H16: BAM | I16: Convertible Mark | J16: BAM | K16: Convertible Mark | L16: BAM | M16: Convertible Mark | N16: BAM | O16: Convertible Mark | BN16: 2001 | BO16: Guarantees | BT16: 11 | BU16: Ba1, BB+ | CD16: 15 | CE16: Currency and deposits | CL16: AR | CM16: Argentina | CP16: 1.2 | CQ16: Growing of perennial crops | CX16: 34 | CY16: Rating - Pymes | DR16: TAX | DS16: TAX Code | DT16: TAX | DU16: TAX Code | DV16: 1N | DW16: MIGA (Multilateral Investment Guarantee Agency) | DX16: S_12301 | DY16: Money market funds (MMFs) - public | EH16: D.14 | EI16: Medium-term note - A debt security issued at fixed or floating rates of interest, as part of an overall medium-term note programme. Used by institutions as a source for medium-term funding. | EJ16: 1109 | EK16: Whole Business Securitisation (WBS) ABS - Detailed asset type breakdown of ABSs mainly in accordance with definitions of European and American Securitisation Forum. | EN16: X5X | EO16: ABS Class - Junior - In case of Asset-backed securities, a breakdown of the tranch level is to be provided. | EV16: 12 | EW16: Other exposures with RW = 100% | EX16: 19 | EY16: Shares | FN16: BA11 | FO16: Syndicated loans | FP16: SCATX09 | FQ16: Non financial corporations - Specific purpose - Other purpose - Not eligible | FR16: 210106 | FW16: Geothermal energy - Electricity generation | FX16: A.1.6. Electricity generation from geothermal energy | FY16: PRDCT01010207 | FZ16: Trade & Working Capital Solutions | GG16: 95016 | GH16: Shared Book Treasury NY Mex | GI16: IM07 | GJ16: Based on revenues | GL16: Commercial/residential real estate loans | GM16: ESTT11 | GN16: Living Building Challenges | GS16: HZRDS11 | GT16: Fire weather | HA16: EURIBOR-12M | HB16: EURIBOR-12M | IA16: VEH11 | IB16: L5 - A vehicle with three wheels symmetrically arranged in relation to the longitudinal median plane with an engine cylinder capacity in the case of a thermic engine exceeding 50 cm3 or whatever the means of propulsion a maximum design speed exceeding 50 km/h
B17: 14 | C17: IFRS: Cash balances at central banks and other demand deposits | F17: BBD | G17: Barbados Dollar | H17: BBD | I17: Barbados Dollar | J17: BBD | K17: Barbados Dollar | L17: BBD | M17: Barbados Dollar | N17: BBD | O17: Barbados Dollar | BN17: 2002 | BO17: Derivatives | BT17: 12 | BU17: Ba2, BB | CD17: 16 | CE17: Loans | CL17: AS | CM17: American Samoa | CP17: 1.21 | CQ17: Growing of grapes | CX17: 35 | CY17: Scoring admisión Persona Física - Individuos | DR17: TRD | DS17: Trade register identifier | DT17: TRD | DU17: Trade register identifier | DV17: 1O | DW17: UNICEF (United Nations Children Fund) | DX17: S_12302 | DY17: Money market funds (MMFs) - national private | EH17: D.141 | EI17: Euro medium term notes (EMTN) - A medium-term note denominated in Euro. | EJ17: 1110 | EK17: Mixed ABS - An ABS that is a mix of different ABS types, e.g. combination of auto and consumer loans. | EN17: X6X | EO17: ABS Class - Mezzanine - In case of Asset-backed securities, a breakdown of the tranch level is to be provided. | EV17: 13 | EW17: IRB - Other non-credit obligation assets | EX17: 21 | EY17: SPL. Project Finance Corporates | FN17: BA12 | FO17: Debt Capital Markets - DCM | FP17: SCATX10 | FQ17: Non financial corporations - Specific purpose - Other purpose - Eligible, not aligned | FR17: 210108 | FW17: Geothermal energy - Cogeneration heat/cool/power | FX17: A.1.18. Cogeneration of heat/cool and power from geothermal energy | FY17: PRDCT010103 | FZ17: Other Loans & Advances | GG17: 99456 | GH17: Vendor Activity NY | GI17: IM08 | GJ17: Based on assets | GL17: Actual building emissions | GM17: ESTT12 | GN17: HQE (Excellence or above) | GS17: HZRDS12 | GT17: Drought | HA17: SOFR-OVERNIGHT | HB17: SOFR-OVERNIGHT | IA17: VEH12 | IB17: L6 - A vehicle with four wheels whose unladen mass is not more than 350 kg, not including the mass of the batteries in case of electric vehicles, whose maximum design speed is not more than 45 km/h, and whose engine cylinder capacity does not exceed 50 cm3 for spark (positive) ignition engines, or whose maximum net power output does not exceed 4 kW in the case of other internal combustion engines, or whose maximum continuous rated power does not exceed 4 kW in the case of electric engines.
B18: 15 | C18: nGAAP: Other Non-trading Non-derivative Financial assets | F18: BDT | G18: Taka | H18: BDT | I18: Taka | J18: BDT | K18: Taka | L18: BDT | M18: Taka | N18: BDT | O18: Taka | BN18: 2003 | BO18: FX | BT18: 13 | BU18: Ba3, BB- | CD18: 17 | CE18: Trade receivables | CL18: AT | CM18: Austria | CP18: 1.22 | CQ18: Growing of tropical and subtropical fruits | CX18: 31 | CY18: Scoring admisión Persona Física - negocios | DR18: VAT | DS18: Value added tax identifier | DT18: VAT | DU18: Value added tax identifier | DV18: 1P | DW18: UNHCR (United Nations High Commissioner for Refugees) | DX18: S_12303 | DY18: Money market funds (MMFs) - foreign controlled | EH18: D.149 | EI18: Other MTN - A medium-term note denominated in a currency other than Euro. | EJ18: 1198 | EK18: Other Assets ABS - An ABS that is of a type not listed separately. | EN18: X7X | EO18: ABS Class - Senior - In case of Asset-backed securities, a breakdown of the tranch level is to be provided. | EV18: 14 | EW18: IRB - Institutions | EX18: 22 | EY18: SPL. Asset Financing Corporates | FN18: BA13 | FO18: ABF - Asset based finance | FP18: SCATX11 | FQ18: Non financial corporations - Specific purpose - Other purpose - Eligible and aligned | FR18: 210110 | FW18: Geothermal energy - Production of heat/cool | FX18: A.1.22. Production of heat/cool from geothermal energy | FY18: PRDCT0102 | FZ18: Renting / Operating Leasing | GG18: 99457 | GH18: Vendor Activity Mexico | GJ18: Project finance | GK18: PM07 | GL18: Supplier specific factors and energy consumption | GM18: ESTT13 | GN18: Minergie (Minergie-A and Standard Minergie) | GS18: HZRDS13 | GT18: Heat | HA18: TERM SOFR-1M | HB18: TERM SOFR-1M | IA18: VEH13 | IB18: L7 - A vehicle with four wheels, other than that classified for the category L6, whose unladen mass is not more than 400 kg (550 kg for vehicles intended for carrying goods), not including the mass of batteries in the case of electric vehicles and whose maximum continuous rated power does not exceed 15 kW
B19: 41 | C19: IFRS: Non-trading financial assets mandatorily at fair value through profit or loss | F19: BGN | G19: Bulgarian lev | H19: BGN | I19: Bulgarian lev | J19: BGN | K19: Bulgarian lev | L19: BGN | M19: Bulgarian lev | N19: BGN | O19: Bulgarian lev | BN19: 2004 | BO19: Security Lending | BT19: 14 | BU19: B1, B+ | CD19: 18 | CE19: Equity and investment funds shares | CL19: AU | CM19: Australia | CP19: 1.23 | CQ19: Growing of citrus fruits | CX19: 32 | CY19: Scoring admisión - Persona Jurídica | DV19: 1Q | DW19: UNRWA (United Nations Relief and Works Agency for Palestine) | DX19: S_124 | DY19: Non-MMF investment funds | EH19: D.15 | EI19: Perpetual bond - A debt security that has no stated maturity date. | EJ19: 1199 | EK19: ABS - No detailed classification available - To be reported, in case it is known that the security is a ABS, but the type is unknown. | EN19: X9X | EO19: Rank level - No detailed information available - To be reported, in case the rank level is not available / applicable. | EV19: 16 | EW19: IRB - Company | EX19: 23 | EY19: SPL. Fin. basic products Corporates | FN19: BA14 | FO19: Leveraged Finance | FQ19: Credit institutions & Other financial corporations | FV19: Renewable fuels, bioenergy and waste heat | FY19: PRDCT0103 | FZ19: Bonds Portfolio | GG19: 99383 | GH19: Split Equity London to Latam | GJ19: Reported emissions | GK19: PM08 | GL19: Average emission factors and energy consumption | GM19: ESTT14 | GN19: Aqua-HQE (Excellent or above) | GS19: HZRDS14 | GT19: Precipitation | HA19: TERM SOFR-3M | HB19: TERM SOFR-3M | IA19: VEH14 | IB19: O1 - Trailers with a maximum mass not exceeding 0.75 tonnes
B20: 45 | C20: nGAAP: Cash balances at central banks and other demand deposits | F20: BHD | G20: Bahraini Dinar | H20: BHD | I20: Bahraini Dinar | J20: BHD | K20: Bahraini Dinar | L20: BHD | M20: Bahraini Dinar | N20: BHD | O20: Bahraini Dinar | BN20: 2005 | BO20: Structured Product | BT20: 15 | BU20: B2, B | CD20: 51 | CE20: Auto collateral | CL20: AW | CM20: Aruba | CP20: 1.24 | CQ20: Growing of pome fruits and stone fruits | CX20: 26 | CY20: Scoring comportamiento Persona Física - Individuos | DV20: 1R | DW20: IAEA (International Atomic Energy Agency) | DX20: S_12401 | DY20: Non-MMF investment funds - public | EH20: D.16 | EI20: Linked bond - Linked bonds have their coupon or principal payments (or both) linked to a general price index for goods and services (such as the consumer price index (CPI)), interest rate (such as the London interbank offered rate (LIBOR) or a bond yield), or asset price. | EJ20: 1200 | EK20: Mortgage-backed security (MBS) - A bond, created through securitisation, whose coupon payments and principal repayments are dependent on a pool of mortgages, either purchased in the secondary market or from the balance sheet of an original asset owner. | EO20: Security level | EV20: 17 | EW20: IRB - Central Governments or Central Banks | EX20: 24 | EY20: SPL. Fin. root assets generators Corp. | FN20: BA15 | FO20: Cash Management | FP20: SCATX12 | FQ20: Credit institutions & Other financial corporations - General purpose | FR20: 210202 | FW20: Bioenergy - Electricity generation | FX20: A.1.8. Electricity generation from bioenergy | FZ20: Off Balance | GG20: 99384 | GH20: Split with LATAM, Equity NY | GI20: IM09 | GJ20: Verified emissions of the project | GL20: Estimated based on floor area | GM20: ESTT15 | GN20: Eco-casa (Level 1 or above) | GS20: HZRDS15 | GT20: Landslide | HA20: TERM SOFR-6M | HB20: TERM SOFR-6M | IA20: VEH15 | IB20: O2 - Trailers with a maximum mass exceeding 0.75 tonnes, but not exceeding 3.5 tonnes
B21: 46 | C21: nGAAP: Financial assets held for trading | F21: BIF | G21: Burundi Franc | H21: BIF | I21: Burundi Franc | J21: BIF | K21: Burundi Franc | L21: BIF | M21: Burundi Franc | N21: BIF | O21: Burundi Franc | BN21: 2006 | BO21: Equity | BT21: 16 | BU21: B3, B- | CD21: 52 | CE21: Shipping | CL21: AX | CM21: Aland Islands | CP21: 1.25 | CQ21: Growing of other tree and bush fruits and nuts | CX21: 36 | CY21: Scoring comportamiento Persona Física - negocios | DV21: 1S | DW21: ILO (International Labour Organisation) | DX21: S_12402 | DY21: Non-MMF investment funds - national private | EH21: D.161 | EI21: Inflation-linked bond - Detailed breakdowns by type in accordance with definitions laid down in Handbook of Securities Statistics. | EJ21: 1201 | EK21: Residential mortgage-backed security (RMBS) - Detailed asset type breakdown of MBSs mainly in accordance | EN21: XX1 | EO21: Unsecured - Securities are not backed by assets, future income streams or similar. | EV21: 18 | EW21: Other exposures with RW = 0% | EX21: 25 | EY21: SPL. Fin. highly volatile retail Corp. | FN21: BA16 | FO21: Core Funding/ Basic financing | FQ21: Credit institutions & Other financial corporations - Specific purpose | FR21: 210205 | FW21: Bioenergy - Cogeneration heat/cool/power | FX21: A.1.20. Cogeneration of heat/cool and power from bioenergy | FY21: PRDCT0201 | FZ21: Contingent risks | GG21: 99388 | GH21: Results Structured Finance Corporate Spain | GI21: IM10 | GJ21: Unverified emissions reported | GK21: PM09 | GL21: Average based on EPC label and floor area | GM21: ESTT16 | GN21: NGBS (Gold or above) | GS21: HZRDS16 | GT21: Aridity | HA21: TERM SOFR-12M | HB21: TERM SOFR-12M | IA21: VEH16 | IB21: O3 - Trailers with a maximum mass exceeding 3.5 tonnes, but not exceeding 10 tonnes
B22: 47 | C22: nGAAP: Financial assets designated at fair value through profit or loss | F22: BMD | G22: Bermudian Dollar | H22: BMD | I22: Bermudian Dollar | J22: BMD | K22: Bermudian Dollar | L22: BMD | M22: Bermudian Dollar | N22: BMD | O22: Bermudian Dollar | BN22: 2007 | BO22: Fixed Income | BT22: 17 | BU22: Caa1, CCC+ | CD22: 53 | CE22: Aircraft | CL22: AZ | CM22: Azerbaijan | CP22: 1.26 | CQ22: Growing of oleaginous fruits | CX22: 33 | CY22: Scoring comportamiento - Persona Jurídica | DV22: 1T | DW22: ITU (International Telecommunication Union) | DX22: S_12403 | DY22: Non-MMF investment funds - foreign controlled | EH22: D.162 | EI22: Interest rate-linked bond - Detailed breakdowns by type in accordance with definitions laid down in Handbook of Securities Statistics. | EJ22: 1202 | EK22: Commercial mortgage-backed security (CMBS) - with definitions of European and American Securitisation Forum. | EN22: XX2 | EO22: Secured - Securities are backed by assets, future income streams or similar. | EV22: 19 | EW22: Other exposures with RW = 20% | FN22: BA17 | FO22: Trade & WCS (Working Capital Solutions) | FP22: SCATX13 | FQ22: Credit institutions & Other financial corporations - Specific purpose - Not eligible | FR22: 210207 | FW22: Bioenergy - Production of heat/cool | FX22: A.1.24. Production of heat/cool from bioenergy | FY22: PRDCT0202 | FZ22: Undrawn balances Committed | GG22: 99721 | GH22: Brazil Remote Book Trading | GJ22: Emissions based on physical activity | GK22: PM10 | GL22: Average based on location/building statistical and floor area | GM22: ESTT17 | GN22: Calificacion Energetica de Viviendas CEV (Rating A and B) | GS22: HZRDS17 | GT22: Rainfall soil erosion | HA22: SONIA-OVERNIGHT | HB22: SONIA-OVERNIGHT | IA22: VEH17 | IB22: O4 - Trailers with a maximum mass exceeding 10 tonnes
B23: 48 | C23: nGAAP: Non-trading financial assets mandatorily at fair value through profit or loss | F23: BND | G23: Brunei Dollar | H23: BND | I23: Brunei Dollar | J23: BND | K23: Brunei Dollar | L23: BND | M23: Brunei Dollar | N23: BND | O23: Brunei Dollar | BN23: 2008 | BO23: Repo | BT23: 18 | BU23: Caa2, CCC | CL23: BA | CM23: Bosnia and Herzegovina | CP23: 1.27 | CQ23: Growing of beverage crops | DV23: 1U | DW23: Rest of UN Organisations n.i.e. | DX23: S_125 | DY23: Other financial intermediaries, except ICPFs | EH23: D.163 | EI23: Asset-linked bond - Detailed breakdowns by type in accordance with definitions laid down in Handbook of Securities Statistics. | EJ23: 1203 | EK23: Mixed MBS - An MBS that is a mix of different MBS types, e.g. combination of RMBS and CMBS. | EN23: XX9 | EO23: Security level - No detailed information available - To be reported, in case the security level is not available / applicable. | EV23: 20 | EW23: ENC - Non Financial assets | FN23: BA18 | FO23: Export & Agency Finance | FP23: SCATX14 | FQ23: Credit institutions & Other financial corporations - Specific purpose - Eligible, not aligned | FR23: 210201 | FW23: Renewable fuels- Electricity generation | FX23: A.1.7. Electricity generation from renewable non-fossil gaseous and liquid fuels | FY23: PRDCT0203 | FZ23: Derivatives | GG23: 99722 | GH23: BRAZIL REMOTE BOOK MARKET MAKING | GI23: IM11 | GJ23: Based on energy consumption | GL23: Estimated based on number of buildings | GM23: ESTT18 | GN23: Other sustainable certification | GS23: HZRDS18 | GT23: Shoreline erosion | HA23: TERM SONIA-1M | HB23: TERM SONIA-1M | IA23: VEH18 | IB23: T - Motorised, wheeled or tracked agricultural or forestry vehicle having at least two axles and a maximum design speed of not less than 6 km/h
F24: BOB | G24: Boliviano | H24: BOB | I24: Boliviano | J24: BOB | K24: Boliviano | L24: BOB | M24: Boliviano | N24: BOB | O24: Boliviano | BN24: 2009 | BO24: Cash Flow Matching | BT24: 19 | BU24: Caa3, CCC- | CL24: BB | CM24: Barbados | CP24: 1.28 | CQ24: Growing of spices, aromatic, drug and pharmaceutical crops | DV24: 1W | DW24: World Bank Group | DX24: S_12501 | DY24: Other financial intermediaries, except ICPFs - public | EH24: D.164 | EI24: Currency-linked bond - Detailed breakdowns by type in accordance with definitions laid down in Handbook of Securities Statistics. | EJ24: 1298 | EK24: Other MBS - An MBS that is of a type not listed separately. | EV24: 21 | EW24: ENC - Financial assets weighing 50% | FN24: BA19 | FO24: Sales Markets | FP24: SCATX15 | FQ24: Credit institutions & Other financial corporations - Specific purpose - Eligible and aligned | FR24: 210204 | FW24: Renewable fuels - Cogeneration heat/cool/power | FX24: A.1.19. Cogeneration of heat/cool and power from renewable non-fossil gaseous and liquid fuels | FZ24: Advisory & Facilitation services | GG24: 99603 | GH24: HongKong Income Split to Commercial Banking | GI24: IM12 | GJ24: Based on production | GK24: PM11 | GL24: Average based on number of buildings | GM24: ESTT19 | GN24: One of the sustainable certifications listed above, but it does not comply with scoring required | GS24: HZRDS19 | GT24: Hurricanes | HA24: TERM SONIA-3M | HB24: TERM SONIA-3M | IA24: VEH19 | IB24: G - Off-road vehicles
F25: BOV | G25: Mvdol | H25: BOV | I25: Mvdol | J25: BOV | K25: Mvdol | L25: BOV | M25: Mvdol | N25: BOV | O25: Mvdol | BN25: 2011 | BO25: Commodity | BT25: 20 | BU25: Ca, CC | CL25: BD | CM25: Bangladesh | CP25: 1.29 | CQ25: Growing of other perennial crops | DV25: 4A | DW25: All the European Union Institutions excluding the institutions of the euro area (changing composition) | DX25: S_12502 | DY25: Other financial intermediaries, except ICPFs - national private | EH25: D.165 | EI25: Credit-linked bond - Detailed breakdowns by type in accordance with definitions laid down in Handbook of Securities Statistics. | EJ25: 1299 | EK25: MBS - No detailed classification available - To be reported, in case it is known that the security is a MBS, but the type is unknown. | EN25: Note: The (sub)categories should be provided according to the most granular level of detail possible. | EV25: 22 | EW25: ENC - Financial assets weighing 100% | FN25: BA20 | FO25: ACPM | FQ25: Households | FR25: 210206 | FW25: Renewable fuels - Production of heat/cool | FX25: A.1.23. Production of heat/cool from renewable non-fossil gaseous and liquid fuels | FY25: PRDCT0301 | FZ25: Mergers & Acquisitions (M&A) | GG25: 102481 | GH25: Transfer to SLB Securities Finance books | GJ25: Emissions based on economic activity | GM25: ESTT20 | GN25: Without sustainable real estate certification | GS25: HZRDS20 | GT25: Convective storms | HA25: TERM SONIA-6M | HB25: TERM SONIA-6M | IA25: VEH20 | IB25: S - Interchangeable towed equipment
F26: BRL | G26: Brazilian Real | H26: BRL | I26: Brazilian Real | J26: BRL | K26: Brazilian Real | L26: BRL | M26: Brazilian Real | N26: BRL | O26: Brazilian Real | BN26: 2012 | BO26: Securities Depository / Custody | BT26: 21 | BU26: C, SD/D | CL26: BE | CM26: Belgium | CP26: 1.3 | CQ26: Plant propagation | DV26: 4B | DW26: EMS (European Monetary System) | DX26: S_12503 | DY26: Other financial intermediaries, except ICPFs - foreign controlled | EH26: D.166 | EI26: Exchange traded notes (ETN) - Detailed breakdowns by type in accordance with definitions laid down in Handbook of Securities Statistics. | EJ26: 1300 | EK26: Collateralised Debt Obligation (CDO) - A bond, created through securitisation, whose coupon payments and principal repayments are dependent on a diversified pool of loan and bond instruments, either purchased in the secondary market or from the balance sheet of an original asset owner; excluding mortgages. | EV26: 27 | EW26: STD - Retail | FN26: BA21 | FO26: Financial Management | FP26: SCATX16 | FQ26: Households - General purpose | FR26: 210203 | FW26: Manufacture Biogas/Biofuels for transport | FX26: A.1.13. Manufacture of biogas and biofuels for use in transport and of bioliquids | FY26: PRDCT0302 | FZ26: Equity Capital Markets (ECM) | GG26: 102482 | GH26: Nansa Fees | GI26: IM13 | GJ26: Based on revenues | GM26: ESTT21 | GN26: Home Quality Mark (4 stars or above) | GS26: HZRDS21 | GT26: Tsunamis | HA26: TERM SONIA-12M | HB26: TERM SONIA-12M | IA26: VEH21 | IB26: R - Agricultural trailer
F27: BSD | G27: Bahamian Dollar | H27: BSD | I27: Bahamian Dollar | J27: BSD | K27: Bahamian Dollar | L27: BSD | M27: Bahamian Dollar | N27: BSD | O27: Bahamian Dollar | BN27: 2013 | BO27: Exchange-traded securities | CL27: BF | CM27: Burkina Faso | CP27: 1.4 | CQ27: Animal production | DV27: 4C | DW27: EIB (European Investment Bank) | DX27: S_126 | DY27: Financial auxiliaries | EH27: D.167 | EI27: Exchange traded commodities (ETC) - Detailed breakdowns by type in accordance with definitions laid down in Handbook of Securities Statistics. | EJ27: 1400 | EK27: Collateralised Mortgage Obligation (CMO) - A bond, created through securitisation, whose coupon payments and principal repayments are dependent on a diversified pool of loan and bond instruments of mortgages, either purchased in the secondary market or from the balance sheet of an original asset owner. | EN27: Sources for definitions: Handbook on Securities Statistics, ESA 2010 and Classification of financial instruments (CFI code). | EV27: 28 | EW27: STD - Reg Gov/Local Author treat. Central Bank | FN27: BA22 | FO27: Other Corporate Activities (Holding) | FQ27: Households - Specific purpose | FR27: 210208 | FW27: Waste heat - Production of heat/cool | FX27: A.1.25. Production of heat/cool electric using waste heat | FY27: PRDCT0303 | FZ27: Debt Capital Markets (DCM) | GG27: 99611 | GH27: NYBrazil Shared Book | GI27: IM14 | GJ27: Based on assets | GM27: ESTT22 | GN27: NABERS (4,5 stars or above) | GS27: HZRDS22 | GT27: Frost occurrences | HA27: SARON-OVERNIGHT | HB27: SARON-OVERNIGHT
F28: BTN | G28: Ngultrum | H28: BTN | I28: Ngultrum | J28: BTN | K28: Ngultrum | L28: BTN | M28: Ngultrum | N28: BTN | O28: Ngultrum | BN28: 2014 | BO28: Correspondents | CL28: BG | CM28: Bulgaria | CP28: 1.41 | CQ28: Raising of dairy cattle | DV28: 4D | DW28: European Commission | DX28: S_12601 | DY28: Financial auxiliaries - public | EH28: D.169 | EI28: Other linked bond - Detailed breakdowns by type in accordance with definitions laid down in Handbook of Securities Statistics. | EJ28: 1500 | EK28: Mixed securitisation - A securitisation that is a mix of different securitisation types, e.g. combination of auto loans and mortgages. | EV28: 29 | EW28: STD - Reg Gov/Local Author treat. Institutions | FN28: BA23 | FO28: FX - Foreign Exchange | FP28: SCATX17 | FQ28: Households - Specific purpose - Building acquisition - Not eligible | FV28: Nuclear & Fossil gaseous fuels | FY28: PRDCT0304 | FZ28: Securitization | GG28: 100218 | GH28: Vendor Activity HK | GI28: IM15 | GJ28: Based on Financed assets - Motor vehicle loans | GM28: ESTT23 | GN28: PBE Edificia (ENCE rating B) | GS28: HZRDS23 | GT28: Subsidence | HA28: TONAR-OVERNIGHT | HB28: TONAR-OVERNIGHT
F29: BWP | G29: Pula | H29: BWP | I29: Pula | J29: BWP | K29: Pula | L29: BWP | M29: Pula | N29: BWP | O29: Pula | BN29: 2015 | BO29: Collateral | CL29: BH | CM29: Bahrain | CP29: 1.42 | CQ29: Raising of other cattle and buffaloes | DV29: 4E | DW29: EDF (European Development Fund) | DX29: S_12602 | DY29: Financial auxiliaries - national private | EH29: D.17 | EI29: Strip bond - Separate trading of registered interest and principal of securities (STRIPS) are securities that have been transformed from a principal amount and periodic coupons into a series of zero-coupon bonds, with the range of maturities matching the coupon payment dates and the redemption date of the principal amount. | EJ29: 1800 | EK29: Other securitisation - A securitisation that is of a type not listed separately. | EV29: 30 | EW29: STD - Pub. sector Entities treat. Central Bank | FN29: BA24 | FO29: Rates | FP29: SCATX18 | FQ29: Households - Specific purpose - Building acquisition - Eligible, not aligned | FR29: 210304 | FW29: Fossil gaseous fuels - Electricity generation | FX29: A.1.29. Electricity generation from fossil gaseous fuels | FY29: PRDCT0305 | FZ29: Project & Acquisition Finance (Advisory) | GG29: 100219 | GH29: Ordinal closing costs Toucan, | GI29: IM16 | GJ29: Based on financed assets - Commercial/Residential real estate loans | GM29: ESTT24 | GN29: CCCS CASA Colombia v3.0 | GS29: HZRDS24 | GT29: Others | HA29: TORF-1M | HB29: TORF-1M
F30: BYN | G30: Belarussian Ruble | H30: BYN | I30: Belarussian Ruble | J30: BYN | K30: Belarussian Ruble | L30: BYN | M30: Belarussian Ruble | N30: BYN | O30: Belarussian Ruble | BN30: 2016 | BO30: Securitization | CL30: BI | CM30: Burundi | CP30: 1.43 | CQ30: Raising of horses and other equines | DV30: 4F | DW30: ECB (European Central Bank) | DX30: S_12603 | DY30: Financial auxiliaries - foreign controlled | EH30: D.171 | EI30: Principal strip - A strip bond created for the part of the principal amount. | EJ30: 1900 | EK30: Securitisation - No detailed classification available - To be reported, in case it is known that the security is a securitisation, but the type is unknown. | EV30: 31 | EW30: STD - Pub. sector Entities treat. Reg. Gov. | FN30: BA25 | FO30: Securitization Products | FP30: SCATX19 | FQ30: Households - Specific purpose - Building acquisition - Eligible and aligned | FR30: 210305 | FW30: Fossil gaseous fuels - Production of heat/cool | FX30: A.1.30. Production of heat/cool from fossil gaseous fuels in an efficient district heating and cooling system | FZ30: Liabilities | GG30: 100325 | GH30: Fudis STEP Abbey program | GM30: ESTT25 | GN30: EDGE (Certified - Level 1) for Chile, Brazil, Aregntina, Uruguay, Colombia and Peru. | HA30: TORF-3M | HB30: TORF-3M
F31: BZD | G31: Belize Dollar | H31: BZD | I31: Belize Dollar | J31: BZD | K31: Belize Dollar | L31: BZD | M31: Belize Dollar | N31: BZD | O31: Belize Dollar | BN31: 2017 | BO31: Insurance | CL31: BJ | CM31: Benin | CP31: 1.44 | CQ31: Raising of camels and camelids | DV31: 4G | DW31: EIF (European Investment Fund) | DX31: S_127 | DY31: Captive financial institutions and money lenders | EH31: D.172 | EI31: Coupon strip - A strip bond created for the part of the coupons. | EJ31: 2000 | EK31: Covered Bond - Covered bonds are debt securities issued by a financial corporation, or fully guaranteed by a financial corporation. In case of default of the issuing or guarantor financial corporation, bond holders have a priority claim on the cover pool, in addition to their ordinary claim on the financial corporation. | EV31: 32 | EW31: STD - Multilateral Development Banks Special treatment | FN31: BA26 | FO31: Securitization Finance | FP31: SCATX20 | FQ31: Households - Specific purpose - Building renovation - Eligible, not aligned | FR31: 210306 | FW31: Fossil gaseous fuels - Co-generation of heat/cool and power | FX31: A.1.31. High-efficiency co-generation of heat/cool and power from fossil gaseous fuels | FY31: PRDCT0401 | FZ31: Financing instruments issued | GG31: 102462 | GH31: SC DERIVED GEOGRAPHY BOADILLA AND OTHERS | GM31: ESTT26 | GN31: Lider A (C Level or above, as long it complies with Top 15% more efficient if built before 31 December 2020) | HA31: TORF-6M | HB31: TORF-6M
F32: CAD | G32: Canadian Dollar | H32: CAD | I32: Canadian Dollar | J32: CAD | K32: Canadian Dollar | L32: CAD | M32: Canadian Dollar | N32: CAD | O32: Canadian Dollar | BN32: 2018 | BO32: Spot | CL32: BL | CM32: Saint Barthélemy | CP32: 1.45 | CQ32: Raising of sheep and goats | DV32: 4H | DW32: European Coal and Steel Community | DX32: S_12701 | DY32: Captive financial institutions and money lenders - public | EH32: D.18 | EI32: Structured debt security (Certificates) - Structured debt securities typically combine a debt security, or a basket of debt securities, with a financial derivative, or a basket of financial derivatives. These financial derivatives are typically embedded in and are therefore inseparable from the debt securities. | EJ32: 2100 | EK32: Public sector Covered bond - Detailed asset type breakdown of covered bonds mainly in accordance with definitions of European Covered Bond Council. | EV32: 33 | EW32: Other exposures with RW = 2% | FN32: BA27 | FO32: Bond Syndicate | FP32: SCATX21 | FQ32: Households - Specific purpose - Building renovation - Eligible and aligned | FR32: 210301 | FW32: Nuclear power - Produce energy with minimal waste | FX32: A.1.26. Pre-commercial stages of advanced technologies to produce energy from nuclear processes with minimal waste from the fuel cycle | FY32: PRDCT0402 | FZ32: Deposits | GG32: 100051 | GH32: AACC Milan expenses | GM32: ESTT27 | GN32: Adene Certificação de eficiência energética e qualidade do ar (SCE – A or above classification, as long it represents the top. 15% more efficient if built before 31 December 2020) | HA32: MIBOR-1M | HB32: MIBOR-1M
F33: CDF | G33: Congolese Franc | H33: CDF | I33: Congolese Franc | J33: CDF | K33: Congolese Franc | L33: CDF | M33: Congolese Franc | N33: CDF | O33: Congolese Franc | BN33: 2019 | BO33: Collateral related with global markets business | CL33: BM | CM33: Bermuda | CP33: 1.46 | CQ33: Raising of swine/pigs | DV33: 4I | DW33: Neighbourhood Investment Facility | DX33: S_12702 | DY33: Captive financial institutions and money lenders - national private | EH33: D.181 | EI33: Investment product - The Investment product category of Structured debt securities covers securities where the principal amount is (1) protected and returned at maturity, regardless of the performance of the reference financial instrument; (2) exposed to losses limited to less than the full principal; (3) fully at risk subject to a level of initial loss protection or (4) fully at risk. | EJ33: 2200 | EK33: Mortgage Covered bond - Detailed asset type breakdown of covered bonds mainly in accordance with definitions of European Covered Bond Council. | EV33: 34 | EW33: STD - Technical Infrastructure | FN33: BA28 | FO33: Equity Derivatives | FP33: SCATX22 | FQ33: Households - Specific purpose - Motor vehicle loans - Eligible, not aligned | FR33: 210302 | FW33: Nuclear power - Construction / safe operation | FX33: A.1.27. Construction and safe operation of new nuclear power plants, for the generation of electricity and/or heat, including for hydrogen production, using best-available technologies | FY33: PRDCT0403 | FZ33: Other Liabilities | GG33: 102464 | GH33: SC REPOS GEOGRAPHY BOADILLA AND OTHERS | HA33: MIBOR-3M | HB33: MIBOR-3M
F34: CHE | G34: WIR Euro | H34: CHE | I34: WIR Euro | J34: CHE | K34: WIR Euro | L34: CHE | M34: WIR Euro | N34: CHE | O34: WIR Euro | BN34: 2020 | BO34: Other | CL34: BN | CM34: Brunei Darussalam | CP34: 1.47 | CQ34: Raising of poultry | DV34: 4M | DW34: SRB (Single Resolution Board) | DX34: S_12703 | DY34: Captive financial institutions and money lenders - foreign controlled | EH34: D.1811 | EI34: Capital protection product - Detailed breakdowns of upper category in accordance with categoristion of European Structured Investment Products Association (EUSIPA). | EJ34: 2300 | EK34: Ship Covered bond - Detailed asset type breakdown of covered bonds mainly in accordance with definitions of European Covered Bond Council. | EV34: 35 | EW34: STD - Securitisation | FN34: BA29 | FO34: Commodities | FP34: SCATX23 | FQ34: Households - Specific purpose - Motor vehicle loans - Eligible and aligned | FR34: 210303 | FW34: Nuclear power - Electricity generation | FX34: A.1.28. Electricity generation from nuclear energy in existing installations | GG34: 102465 | GH34: MUP SELL TO SELL GEOGRAPHY BOADILLA AND OTHERS | HA34: MIBOR-6M | HB34: MIBOR-6M
F35: CHF | G35: Swiss franc | H35: CHF | I35: Swiss franc | J35: CHF | K35: Swiss franc | L35: CHF | M35: Swiss franc | N35: CHF | O35: Swiss franc | CL35: BO | CM35: Bolivia (Plurinational State of) | CP35: 1.49 | CQ35: Raising of other animals | DV35: 4R | DW35: EU-Africa Infrastructure Trust Fund | DX35: S_128 | DY35: Insurance corporations (ICs) | EH35: D.1812 | EI35: Yield enhancement product - Detailed breakdowns of upper category in accordance with categoristion of European Structured Investment Products Association (EUSIPA). | EJ35: 2400 | EK35: Aircraft Covered bond - Detailed asset type breakdown of covered bonds mainly in accordance with definitions of European Covered Bond Council. | EV35: 36 | EW35: STD - Companies | FN35: BA30 | FO35: Cash Equity | FQ35: Local governments | FV35: Transmission and distribution | GG35: 100100 | GH35: Exchange Trade Derivatives | HA35: MIBOR-12M | HB35: MIBOR-12M
F36: CHW | G36: WIR Franc | H36: CHW | I36: WIR Franc | J36: CHW | K36: WIR Franc | L36: CHW | M36: WIR Franc | N36: CHW | O36: WIR Franc | CL36: BQ | CM36: Bonaire, Saint Eustatius and Saba | CP36: 1.5 | CQ36: Mixed farming | DV36: 4S | DW36: ESM (European Stability Mechanism) | DX36: S_12801 | DY36: Insurance corporations (ICs) - public | EH36: D.1813 | EI36: Participation product - Detailed breakdowns of upper category in accordance with categoristion of European Structured Investment Products Association (EUSIPA). | EJ36: 2500 | EK36: Mixed Covered bond - A covered bond that is a mix of different covered bond types. | EV36: 37 | EW36: ENC-Active Material | FN36: BA31 | FO36: XVA - X-Value Adjustment | FP36: SCATX24 | FQ36: Local governments - General purpose | FR36: 210419 | FW36: Transmission and distribution of electricity | FX36: A.1.9. Transmission and distribution of electricity | GG36: 100118 | GH36: MADOFF Interest on local debt retrocession | HA36: OTHER SINGLE REFERENCE RATES-OTHER SINGLE REFERENCE RATES | HB36: OTHER SINGLE REFERENCE RATES-OTHER SINGLE REFERENCE RATES
F37: CLF | G37: Unidades de fomento | H37: CLF | I37: Unidades de fomento | J37: CLF | K37: Unidades de fomento | L37: CLF | M37: Unidades de fomento | N37: CLF | O37: Unidades de fomento | CL37: BR | CM37: Brazil | CP37: 1.6 | CQ37: Support activities to agriculture and post-harvest crop activities | DV37: 4U | DW37: EURATOM | DX37: S_12802 | DY37: Insurance corporations (ICs) - national private | EH37: D.1819 | EI37: Other investment product - Detailed breakdowns of upper category in accordance with categoristion of European Structured Investment Products Association (EUSIPA). | EJ37: 2800 | EK37: Other Covered bond - A covered bond that is of a type not listed separately. | EV37: 38 | EW37: ENC- Accrual Accounts | FQ37: Local governments - Specific purpose | FR37: 210420 | FW37: Networks for renewable/low-carbon gases | FX37: A.1.14. Transmission and distribution networks for renewable and low-carbon gases | GG37: 102463 | GH37: MUP REPOS GEOGRAPHY BOADILLA AND OTHERS | HA37: OTHER MULTIPLE REFERENCE RATES-OTHER MULTIPLE REFERENCE RATES | HB37: OTHER MULTIPLE REFERENCE RATES-OTHER MULTIPLE REFERENCE RATES
F38: CLP | G38: Chilean Peso | H38: CLP | I38: Chilean Peso | J38: CLP | K38: Chilean Peso | L38: CLP | M38: Chilean Peso | N38: CLP | O38: Chilean Peso | CL38: BS | CM38: Bahamas (the) | CP38: 1.61 | CQ38: Support activities for crop production | DV38: 4V | DW38: FEMIP (Facility for Euro-Mediterranean Investment and Partnership) | DX38: S_12803 | DY38: Insurance corporations (ICs) - foreign controlled | EH38: D.182 | EI38: Leverage Product - The leverage product category of Structured debt securities covers securities with a large risk compared with the initial investment and that combine an investment in an underlying security with a future or option. | EJ38: 2900 | EK38: Covered Bond - No detailed classification available - To be reported, in case it is known that the security is a covered bond, but the type is unknown. | EV38: 39 | EW38: ENC-Cheques and other assets - Ent Cred | FP38: SCATX25 | FQ38: Local governments - Specific purpose - Building acquisition - Not eligible | FR38: 210421 | FW38: District heating/cooling distribution | FX38: A.1.15. District heating/cooling distribution | GG38: 99902 | GH38: Sellers Activity Brazil
F39: CNY | G39: Yuan Renminbi | H39: CNY | I39: Yuan Renminbi | J39: CNY | K39: Yuan Renminbi | L39: CNY | M39: Yuan Renminbi | N39: CNY | O39: Yuan Renminbi | CL39: BT | CM39: Bhutan | CP39: 1.62 | CQ39: Support activities for animal production | DV39: 4W | DW39: EFSF (European Financial Stability Facility) | DX39: S_129 | DY39: Pension funds (PFs) | EH39: D.1821 | EI39: Leverage product with knock-out - Detailed breakdowns of upper category in accordance with categoristion of European Structured Investment Products Association (EUSIPA). | EV39: 40 | EW39: ENC-Cheques and other assets - Other | FP39: SCATX26 | FQ39: Local governments - Specific purpose - Building acquisition - Eligible, not aligned | FV39: Electric heat pumps installation and operation | GG39: 99921 | GH39: Rio de Janeiro Gas Distributor
F40: COP | G40: Colombian Peso | H40: COP | I40: Colombian Peso | J40: COP | K40: Colombian Peso | L40: COP | M40: Colombian Peso | N40: COP | O40: Colombian Peso | CL40: BV | CM40: Bouvet Island | CP40: 1.63 | CQ40: Post-harvest crop activities | DV40: 5B | DW40: BIS (Bank for International Settlements) | DX40: S_12901 | DY40: Pension funds (PFs) - public | EH40: D.1822 | EI40: Leverage product without knock-out - Detailed breakdowns of upper category in accordance with categoristion of European Structured Investment Products Association (EUSIPA). | EV40: 41 | EW40: ENC- Enclosure | FP40: SCATX27 | FQ40: Local governments - Specific purpose - Building acquisition - Eligible and aligned | FR40: 210501 | FW40: Electric heat pumps installation and operation | FX40: A.1.16. Installation and operation of electric heat pumps | GG40: 99923 | GH40: Asia distribution mrg Latam customers
F41: COU | G41: Unidad de Valor Real | H41: COU | I41: Unidad de Valor Real | J41: COU | K41: Unidad de Valor Real | L41: COU | M41: Unidad de Valor Real | N41: COU | O41: Unidad de Valor Real | CL41: BW | CM41: Botswana | CP41: 1.64 | CQ41: Seed processing for propagation | DV41: 5C | DW41: IADB (Inter-American Development Bank) | DX41: S_12902 | DY41: Pension funds (PFs) - national private | EH41: D.1823 | EI41: Constant leverage product - Detailed breakdowns of upper category in accordance with categoristion of European Structured Investment Products Association (EUSIPA). | EJ41: Note: The (sub)categories should be provided according to the most granular level of detail possible. | EV41: 42 | EW41: ENC-Gold | FP41: SCATX28 | FQ41: Local governments - Specific purpose - Other purpose - Not eligible | FV41: Storage | GG41: 99928 | GH41: Tariff deficit Citibank
F42: CRC | G42: Costa Rican Colon | H42: CRC | I42: Costa Rican Colon | J42: CRC | K42: Costa Rican Colon | L42: CRC | M42: Costa Rican Colon | N42: CRC | O42: Costa Rican Colon | CL42: BY | CM42: Belarus | CP42: 1.7 | CQ42: Hunting, trapping and related service activities | DV42: 5D | DW42: AfDB (African Development Bank) | DX42: S_12903 | DY42: Pension funds (PFs) - foreign controlled | EH42: D.1829 | EI42: Other leverage product - Detailed breakdowns of upper category in accordance with categoristion of European Structured Investment Products Association (EUSIPA). | EV42: 43 | EW42: ENC-Tax Assets | FP42: SCATX29 | FQ42: Local governments - Specific purpose - Other purpose - Eligible, not aligned | FR42: 210601 | FW42: Electricity | FX42: A.1.10. Storage of electricity | GG42: 99930 | GH42: Expenses EU Corporate Affairs
F43: CUC | G43: Peso Convertible | H43: CUC | I43: Peso Convertible | J43: CUC | K43: Peso Convertible | L43: CUC | M43: Peso Convertible | N43: CUC | O43: Peso Convertible | CL43: BZ | CM43: Belize | CP43: 10 | CQ43: Manufacture of food products | DV43: 5E | DW43: AsDB (Asian Development Bank) | DX43: S_13 | DY43: General government | EH43: D.19 | EI43: Other bond - A bond that is of a type not listed separately. | EJ43: Sources for definitions: Handbook on Securities Statistics, European and American Securitisation Forum as well as European Covered Bond Council. | EV43: 44 | EW43: ENC-Derivatives | FP43: SCATX30 | FQ43: Local governments - Specific purpose - Other purpose - Eligible and aligned | FR43: 210602 | FW43: Thermal energy | FX43: A.1.11. Storage of thermal energy | GG43: 99933 | GH43: GBM Business in Branches
F44: CUP | G44: Cuban Peso | H44: CUP | I44: Cuban Peso | J44: CUP | K44: Cuban Peso | L44: CUP | M44: Cuban Peso | N44: CUP | O44: Cuban Peso | CL44: CA | CM44: Canada | CP44: 10.1 | CQ44: Processing and preserving of meat and production of meat products | DV44: 5F | DW44: EBRD (European Bank for Reconstruction and Development) | DX44: S_1311 | DY44: Central government | EH44: D.2 | EI44: Money market instrument - Money market instruments in accordance with Directive 2009/65/EC comprise transferable instruments which are normally dealt in on the money market rather than on the regulated markets. | EV44: 45 | EW44: ENC-CCP | FP44: SCATX31 | FQ44: Rest of exposures | FR44: 210603 | FW44: Hydrogen | FX44: A.1.12. Storage of hydrogen | GG44: 99938 | GH44: Operational risk (Branch 5493)
F45: CVE | G45: Cape Verde Escudo | H45: CVE | I45: Cape Verde Escudo | J45: CVE | K45: Cape Verde Escudo | L45: CVE | M45: Cape Verde Escudo | N45: CVE | O45: Cape Verde Escudo | CL45: CC | CM45: Cocos (Keeling) Islands (the) | CP45: 10.11 | CQ45: Processing and preserving of meat | DV45: 5G | DW45: IIC (Inter-American Investment Corporation) | DX45: S_1312 | DY45: State government | EH45: D.21 | EI45: Bankers acceptance - A negotiable order to pay a specified amount of money on a future date, accepted and guaranteed by a bank and drawn on a deposit at a bank. | EV45: 46 | EW45: ENC-Rest of assets | FV45: Renewable Energy Procurement | GG45: 99983 | GH45: Sonae capital Brasil Ltd
F46: CZK | G46: Czech koruna | H46: CZK | I46: Czech koruna | J46: CZK | K46: Czech koruna | L46: CZK | M46: Czech koruna | N46: CZK | O46: Czech koruna | CL46: CD | CM46: Congo (the Democratic Republic of the) | CP46: 10.12 | CQ46: Processing and preserving of poultry meat | DV46: 5H | DW46: NIB (Nordic Investment Bank) | DX46: S_1313 | DY46: Local government | EH46: D.22 | EI46: Certificate of deposit - Usually a negotiable certificate issued by a bank acknowledging a deposit in that bank for a specified period of time at a specified interest rate. | EV46: 47 | EW46: ENC-Assets Materials Awarded | FR46: 210701 | FW46: Renewable Energy Procurement | FX46: A.1.32. Renewable Energy Procurement | GG46: 99989 | GH46: London Booked Operations
F47: DJF | G47: Djibouti Franc | H47: DJF | I47: Djibouti Franc | J47: DJF | K47: Djibouti Franc | L47: DJF | M47: Djibouti Franc | N47: DJF | O47: Djibouti Franc | CL47: CF | CM47: Central African Republic (the) | CP47: 10.13 | CQ47: Production of meat and poultry meat products | DV47: 5I | DW47: ECCB (Eastern Caribbean Central Bank) | DX47: S_1314 | DY47: Social security funds | EH47: D.23 | EI47: Commercial paper - A discounted and unsecured debt security issued by a corporation whose name appears on the front of the security and who promises to pay to the security holder a certain amount on a stated maturity date. | EV47: 48 | EW47: ENC-Actives Acquired Materials | FU47: Transport | GG47: 100155 | GH47: Commissions Final Terms Issues
F48: DKK | G48: Danish krone | H48: DKK | I48: Danish krone | J48: DKK | K48: Danish krone | L48: DKK | M48: Danish krone | N48: DKK | O48: Danish krone | CL48: CG | CM48: Congo (the) | CP48: 10.2 | CQ48: Processing and preserving of fish, crustaceans and molluscs | DV48: 5J | DW48: IBEC (International Bank for Economic Co-operation) | DX48: S_14 | DY48: Households | EH48: D.231 | EI48: Euro commercial paper (ECP) - A commercial paper denominated in Euro. | EV48: 49 | EW48: STD - Pub Sec Ent - Entities Treatment | FV48: Ground transport | GG48: 100791 | GH48: Corporate Activities Ftra. Intergroup
F49: DOP | G49: Dominican Peso | H49: DOP | I49: Dominican Peso | J49: DOP | K49: Dominican Peso | L49: DOP | M49: Dominican Peso | N49: DOP | O49: Dominican Peso | CL49: CH | CM49: Switzerland | CP49: 10.3 | CQ49: Processing and preserving of fruit and vegetables | DV49: 5K | DW49: IIB (International Investment Bank) | DX49: S_15 | DY49: Non-profit insitutions serving households | EH49: D.232 | EI49: Pagares - Specific type of commercial paper commonly known in Spain. | EV49: 50 | EW49: Balances without capital consumption | FR49: 220101 | FW49: Passenger interurban rail transport | FX49: A.2.1. Passenger interurban rail transport | GG49: 100659 | GH49: Split NY
F50: DZD | G50: Algerian Dinar | H50: DZD | I50: Algerian Dinar | J50: DZD | K50: Algerian Dinar | L50: DZD | M50: Algerian Dinar | N50: DZD | O50: Algerian Dinar | CL50: CI | CM50: Cote d'Ivoire | CP50: 10.31 | CQ50: Processing and preserving of potatoes | DV50: 5L | DW50: CDB (Caribbean Development Bank) | EH50: D.239 | EI50: Other CP - A commercial paper that is of a type not listed separately. | EV50: 51 | EW50: Retail - Special treatment | FR50: 220102 | FW50: Freight rail transport | FX50: A.2.2. Freight rail transport | GG50: 100667 | GH50: New DCM treatment
F51: EGP | G51: Egyptian Pound | H51: EGP | I51: Egyptian Pound | J51: EGP | K51: Egyptian Pound | L51: EGP | M51: Egyptian Pound | N51: EGP | O51: Egyptian Pound | CL51: CK | CM51: Cook Islands (the) | CP51: 10.32 | CQ51: Manufacture of fruit and vegetable juice | DV51: 5M | DW51: AMF (Arab Monetary Fund) | EH51: D.24 | EI51: Treasury bill - A common form of sovereign shortterm debt security that many governments issue. It gives the holder the unconditional right to receive stated fixed sums on a specified date, and is issued at a discount to face value that depends on the rate of interest and the time to maturity. | FR51: 220103 | FW51: Urban and suburban transport, road passenger transport | FX51: A.2.3. Urban and suburban transport, road passenger transport | GG51: 100674 | GH51: Deposit Recognition
F52: ERN | G52: Nakfa | H52: ERN | I52: Nakfa | J52: ERN | K52: Nakfa | L52: ERN | M52: Nakfa | N52: ERN | O52: Nakfa | CL52: CL | CM52: Chile | CP52: 10.39 | CQ52: Other processing and preserving of fruit and vegetables | DV52: 5N | DW52: BADEA (Banque arabe pour le développement économique en Afrique) | EH52: D.29 | EI52: Other money market instrument - A money market instrument that is of a type not listed separately. | FR52: 220104 | FW52: Personal mobility devices, cycle logistics | FX52: A.2.4. Operation of personal mobility devices, cycle logistics | GG52: 100136 | GH52: Golden Book
F53: ETB | G53: Ethiopian Birr | H53: ETB | I53: Ethiopian Birr | J53: ETB | K53: Ethiopian Birr | L53: ETB | M53: Ethiopian Birr | N53: ETB | O53: Ethiopian Birr | CL53: CM | CM53: Cameroon | CP53: 10.4 | CQ53: Manufacture of vegetable and animal oils and fats | DV53: 5O | DW53: BCEAO (Banque Centrale des Etats de l`Afrique de l`Ouest) | EH53: D.3 | EI53: Hybrid debt instrument - Instrument with characteristics of debt and equity which are classified as debt according to their main characteristics. | FR53: 220105 | FW53: Motorbikes, passenger cars and light commercial vehicles | FX53: A.2.5. Transport by motorbikes, passenger cars and light commercial vehicles | GG53: 100382 | GH53: Golden Book UK Origin
F54: EUR | G54: Euro | H54: EUR | I54: Euro | J54: EUR | K54: Euro | L54: EUR | M54: Euro | N54: EUR | O54: Euro | CL54: CN | CM54: China | CP54: 10.41 | CQ54: Manufacture of oils and fats | DV54: 5P | DW54: CASDB (Central African States Development Bank) | EH54: D.31 | EI54: Convertible bond - A fixed interest rate bond that the investor has the option of converting into the equity of the borrower or its parent. | FR54: 220106 | FW54: Freight road transport | FX54: A.2.6. Freight transport services by road | GG54: 100410 | GH54: GENERIC FUND TRANSFER
F55: FJD | G55: Fiji Dollar | H55: FJD | I55: Fiji Dollar | J55: FJD | K55: Fiji Dollar | L55: FJD | M55: Fiji Dollar | N55: FJD | O55: Fiji Dollar | CL55: CO | CM55: Colombia | CP55: 10.42 | CQ55: Manufacture of margarine and similar edible fats | DV55: 5Q | DW55: African Development Fund | EH55: D.311 | EI55: Contingent convertible bonds (CoCo’s) - Contingent convertible securities are hybrid securities issued as debt instruments and automatically converted into equity shares if a contractually pre-defined 'trigger event' occurs. Their defining characteristics are a loss-absorption mechanism (conversion or write-down) and an activation trigger, either based on a mechanical rule or on supervisors’ discretion. | FV55: Water Transport | GG55: 100474 | GH55: Sales Credit Brasil / New York
F56: FKP | G56: Falkland Islands Pound | H56: FKP | I56: Falkland Islands Pound | J56: FKP | K56: Falkland Islands Pound | L56: FKP | M56: Falkland Islands Pound | N56: FKP | O56: Falkland Islands Pound | CL56: CR | CM56: Costa Rica | CP56: 10.5 | CQ56: Manufacture of dairy products | DV56: 5R | DW56: Asian Development Fund | EH56: D.32 | EI56: Bonds with warrants attached - Bonds with warrants attached are debt securities that incorporate warrants giving the holder the option to purchase equity in the issuer or another company during a predetermined period, or at a particular date, and at a fixed contract price. The warrant may be detachable and traded separately from the debt security. | FR56: 220201 | FW56: Inland passenger transport | FX56: A.2.7. Inland passenger water transport | GG56: 100505 | GH56: Commission for participation in issues
F57: GBP | G57: UK pound sterling | H57: GBP | I57: UK pound sterling | J57: GBP | K57: UK pound sterling | L57: GBP | M57: UK pound sterling | N57: GBP | O57: UK pound sterling | CL57: CU | CM57: Cuba | CP57: 10.51 | CQ57: Operation of dairies and cheese making | DV57: 5S | DW57: Fonds spécial unifié de développement | EH57: D.33 | EI57: Stapled debt instrument - Stapled instruments - which, under their terms of issue, are two or more different financial instruments (for example, ordinary equity securities and unsecured notes) coupled together for certain purposes - are usually treated separately as fixed interest rate debt securities and equity securities. However, stapled instruments usually cannot be transferred separately either in the market or as the result of an over-the-counter (OTC) transaction. A parcel consisting of one equity security and one or more notes is traded in the market as though it were a single security, although conceptually the components are regarded as separate. If the components cannot be separately identified, the stapled instrument should be classified according to the predominant component, that is, either as a debt security or an equity security. | FR57: 220202 | FW57: Inland freight transport | FX57: A.2.8. Inland freight water transport | GG57: 102466 | GH57: SC SALE TO VCTO GEOGRAPHY BOADILLA AND OTHERS
F58: GEL | G58: Lari | H58: GEL | I58: Lari | J58: GEL | K58: Lari | L58: GEL | M58: Lari | N58: GEL | O58: Lari | CL58: CV | CM58: Cabo Verde | CP58: 10.52 | CQ58: Manufacture of ice cream | DV58: 5T | DW58: CABEI (Central American Bank for Economic Integration) | EH58: D.34 | EI58: Non-participating (preferred) share - Holders are entitled to receive a fixed dividend, but do not participate in the distribution of the residual value of a corporation on dissolution. | FR58: 220203 | FW58: Retrofitting of inland transport | FX58: A.2.9. Retrofitting of inland water passenger and freight transport | GG58: 100541 | GH58: TRYP
F59: GHS | G59: Ghana Cedi | H59: GHS | I59: Ghana Cedi | J59: GHS | K59: Ghana Cedi | L59: GHS | M59: Ghana Cedi | N59: GHS | O59: Ghana Cedi | CL59: CW | CM59: Curacao | CP59: 10.6 | CQ59: Manufacture of grain mill products, starches and starch products | DV59: 5U | DW59: ADC (Andean Development Corporation) | EH59: D.39 | EI59: Other hybrid debt Instrument - A hybrid debt instrument that is of a type not listed separately. | FR59: 220204 | FW59: Sea and coastal freight transport, vessels for port operations and auxiliary activities | FX59: A.2.10. Sea and coastal freight water transport, vessels for port operations and auxiliary activities | GG59: 100332 | GH59: Equity Southern Europe Revenue Transfer
F60: GIP | G60: Gibraltar Pound | H60: GIP | I60: Gibraltar Pound | J60: GIP | K60: Gibraltar Pound | L60: GIP | M60: Gibraltar Pound | N60: GIP | O60: Gibraltar Pound | CL60: CX | CM60: Christmas Island | CP60: 10.61 | CQ60: Manufacture of grain mill products | DV60: 5W | DW60: BEAC (Banque des Etats de l`Afrique Centrale) | EH60: D.9 | EI60: Other debt - A debt instrument that is of a type not listed separately. | FR60: 220205 | FW60: Sea and coastal passenger transport | FX60: A.2.11. Sea and coastal passenger water transport | GG60: 100350 | GH60: Golden Book origin Chile
F61: GMD | G61: Dalasi | H61: GMD | I61: Dalasi | J61: GMD | K61: Dalasi | L61: GMD | M61: Dalasi | N61: GMD | O61: Dalasi | CL61: CY | CM61: Cyprus | CP61: 10.62 | CQ61: Manufacture of starches and starch products | DV61: 6B | DW61: NATO (North Atlantic Treaty Organisation) | EH61: E | EI61: Equity - Equity securities are negotiable financial instruments that entitle holders to a share of both distributed profits and the residual value of the corporation’s assets in the event of its liquidation. Holders of these financial assets are the collective owners of a corporation. Equity securities are part of the financial assets and liabilities (financial instrument) category “equity and investment fund shares or units” (F.5) and belong to the subcategory “equity” (F.51) in ESA 2010. | FR61: 220206 | FW61: Retrofitting of sea and coastal freight and passenger transport | FX61: A.2.12. Retrofitting of sea and coastal freight and passenger water transport | GG61: 100351 | GH61: Federative Republic of Brazil (Eurocopter and DCNS)
F62: GNF | G62: Guinea Franc | H62: GNF | I62: Guinea Franc | J62: GNF | K62: Guinea Franc | L62: GNF | M62: Guinea Franc | N62: GNF | O62: Guinea Franc | CL62: CZ | CM62: Czechia | CP62: 10.7 | CQ62: Manufacture of bakery and farinaceous products | DV62: 6C | DW62: Council of Europe | EH62: E.1 | EI62: Ordinary / Common share - Ordinary shares (or “common” shares) usually give holders the right to the following: • Holders are generally entitled to participate in the corporation’s general policymaking and have the right to attend, speak, and vote (in the case of voting shares) at general meetings. Holders of ordinary shares can vote on corporate objectives and matters of policy, on stock splits, and to elect the corporation’s board of directors. • Holders are usually entitled to a preferential subscription in the event of a capital increase. Some holders of ordinary shares also receive preemptive rights (a rights issue), which enables them to retain their proportional share in the ownership of a corporation should it issue more stock. • Holders generally have the right to a share in the corporation’s profits. However, no fixed dividends are paid out to ordinary shareholders. Ordinary shareholders’ returns are therefore uncertain and dependent on earnings, corporate reinvestment, and the market’s ability to value and sell stock efficiently. | FV62: Infraestructure | GG62: 100352 | GH62: Golden Book Origin Brazil
F63: GTQ | G63: Quetzal | H63: GTQ | I63: Quetzal | J63: GTQ | K63: Quetzal | L63: GTQ | M63: Quetzal | N63: GTQ | O63: Quetzal | CL63: DE | CM63: Germany | CP63: 10.71 | CQ63: Manufacture of bread; manufacture of fresh pastry goods and cakes | DV63: 6D | DW63: ICRC (International Committee of the Red Cross) | EH63: E.2 | EI63: Preference / Preferred share - Holders of preferred shares have priority over holders of ordinary shares when it comes to laying claim to a corporation’s assets. However, while preferred shares may have priority over ordinary shares in the payment of dividends and in the event of liquidation, they are subordinated to debt securities. | FR63: 220401 | FW63: Personal mobility, cycle logistics | FX63: A.2.13. Infrastructure for personal mobility, cycle logistics | GG63: 100730 | GH63: GOLF CENTER CHILE
F64: GYD | G64: Guyana Dollar | H64: GYD | I64: Guyana Dollar | J64: GYD | K64: Guyana Dollar | L64: GYD | M64: Guyana Dollar | N64: GYD | O64: Guyana Dollar | CL64: DJ | CM64: Djibouti | CP64: 10.72 | CQ64: Manufacture of rusks and biscuits; manufacture of preserved pastry goods and cakes | DV64: 6E | DW64: ESA (European Space Agency) | EH64: E.21 | EI64: Cumulative preferred share - Holders are entitled to receive a fixed dividend ahead of ordinary shares and retain the right to any accumulated preferred dividends that may have built up. | FR64: 220405 | FW64: Rail transport | FX64: A.2.14. Infrastructure for rail transport | GG64: 100741 | GH64: Results from London Rates to Rates Spain
F65: HKD | G65: Hong Kong Dollar | H65: HKD | I65: Hong Kong Dollar | J65: HKD | K65: Hong Kong Dollar | L65: HKD | M65: Hong Kong Dollar | N65: HKD | O65: Hong Kong Dollar | CL65: DK | CM65: Denmark | CP65: 10.73 | CQ65: Manufacture of macaroni, noodles, couscous and similar farinaceous products | DV65: 6F | DW65: EPO (European Patent Office) | EH65: E.22 | EI65: Participating preferred share - Holders are entitled to participate in the profits of a corporation over and above fixed dividends by means of an additional fluctuating dividend. They also participate in the distribution of the residual value of a corporation on dissolution. | FR65: 220402 | FW65: Road transport and public transport | FX65: A.2.15. Infrastructure enabling low-carbon road transport and public transport | GG65: 101368 | GH65: Sales Credits Mexico London
F66: HNL | G66: Lempira | H66: HNL | I66: Lempira | J66: HNL | K66: Lempira | L66: HNL | M66: Lempira | N66: HNL | O66: Lempira | CL66: DM | CM66: Dominica | CP66: 10.8 | CQ66: Manufacture of other food products | DV66: 6G | DW66: EUROCONTROL (European Organisation for the Safety of Air Navigation) | EH66: E.23 | EI66: Cumulative, participating preferred share - A preferred share that fulfils the criteria of cumulative and participating preferred shares at the same time. | FR66: 220403 | FW66: Water transport | FX66: A.2.16. Infrastructure enabling low carbon water transport | GG66: 101376 | GH66: Team Global Agreements
F67: HRK | G67: Croatian kuna | H67: HRK | I67: Croatian kuna | J67: HRK | K67: Croatian kuna | L67: HRK | M67: Croatian kuna | N67: HRK | O67: Croatian kuna | CL67: DO | CM67: Dominican Republic (the) | CP67: 10.81 | CQ67: Manufacture of sugar | DV67: 6H | DW67: EUTELSAT (European Telecommunications Satellite Organisation) | EH67: E.24 | EI67: Redeemable preferred share - These can be redeemed at the request of either the corporation or the shareholder (at a fixed price on a specified date or during a specified period of time). Strict conditions apply to the issuance of redeemable shares and their redemption. Instead of cancelling shares on redemption, a corporation may continue to hold such shares as treasury shares, but no voting rights may be exercised and no dividends are payable. | FR67: 220404 | FW67: Airport | FX67: A.2.17. Low carbon airport infrastructure | GG67: 101388 | GH67: Spread Adjustments / Incentives ESM Repos
F68: HTG | G68: Gourde | H68: HTG | I68: Gourde | J68: HTG | K68: Gourde | L68: HTG | M68: Gourde | N68: HTG | O68: Gourde | CL68: DZ | CM68: Algeria | CP68: 10.82 | CQ68: Manufacture of cocoa, chocolate and sugar confectionery | DV68: 6I | DW68: EMBL (European Molecular Biology Laboratory) | EH68: E.29 | EI68: Other preferred share - A prefered share that is of a type not listed separately. | FV68: Air Transport | GG68: 101390 | GH68: ACPM Remuneration GTB for Liabilities
F69: HUF | G69: Hungarian forint | H69: HUF | I69: Hungarian forint | J69: HUF | K69: Hungarian forint | L69: HUF | M69: Hungarian forint | N69: HUF | O69: Hungarian forint | CL69: EC | CM69: Ecuador | CP69: 10.83 | CQ69: Processing of tea and coffee | DV69: 6J | DW69: INTELSAT (International Telecommunications Satellite Organisation) | EH69: E.3 | EI69: Depository receipt - A financial instrument that allows a nonresident to introduce securities into a market in a form more readily acceptable to the investors in that market. A deposit-taking corporation will purchase the underlying security and then issue receipts in a currency more acceptable to the investor. | FR69: 220301 | FW69: Leasing of aircraft | FX69: A.2.18. Leasing of aircraft | GG69: 101416 | GH69: UK Securitisation Ledger
F70: IDR | G70: Rupiah | H70: IDR | I70: Rupiah | J70: IDR | K70: Rupiah | L70: IDR | M70: Rupiah | N70: IDR | O70: Rupiah | CL70: EE | CM70: Estonia | CP70: 10.84 | CQ70: Manufacture of condiments and seasonings | DV70: 6K | DW70: EBU/UER (European Broadcasting Union/Union européenne de radio-télévision) | EH70: E.31 | EI70: American depository receipt (ADR) - American depository receipts (ADR) are liabilities of the non-U.S. institutional units whose securities underlie the ADR, not of the U.S. financial institutions issuing the ADR. | FR70: 220302 | FW70: Passenger and freight air transport | FX70: A.2.19. Passenger and freight air transport | GG70: 101428 | GH70: Customer Interdealer ROSGIP LIMITED
F71: ILS | G71: New Israeli Sheqel | H71: ILS | I71: New Israeli Sheqel | J71: ILS | K71: New Israeli Sheqel | L71: ILS | M71: New Israeli Sheqel | N71: ILS | O71: New Israeli Sheqel | CL71: EG | CM71: Egypt | CP71: 10.85 | CQ71: Manufacture of prepared meals and dishes | DV71: 6L | DW71: EUMETSAT (European Organisation for the Exploitation of Meteorological Satellites) | EH71: E.32 | EI71: Global depository receipt (GDR) - Global depository receipts (GDR) are securities available in one or more markets outside the corporation’s country of residence. | FR71: 220303 | FW71: Air transport ground handling operations | FX71: A.2.20. Air transport ground handling operations | GG71: 101438 | GH71: Golden Book Origin Peru
F72: INR | G72: Indian Rupee | H72: INR | I72: Indian Rupee | J72: INR | K72: Indian Rupee | L72: INR | M72: Indian Rupee | N72: INR | O72: Indian Rupee | CL72: EH | CM72: Western Sahara | CP72: 10.86 | CQ72: Manufacture of homogenised food preparations and dietetic food | DV72: 6M | DW72: ESO (European Southern Observatory) | EH72: E.39 | EI72: Other depository receipt - A depository receipt that is of a type not listed separately. | FV72: Hydrogen powered-vehicles | GG72: 101440 | GH72: Intercompany business ROSVIT Limit
F73: IQD | G73: Iraqi Dinar | H73: IQD | I73: Iraqi Dinar | J73: IQD | K73: Iraqi Dinar | L73: IQD | M73: Iraqi Dinar | N73: IQD | O73: Iraqi Dinar | CL73: ER | CM73: Eritrea | CP73: 10.89 | CQ73: Manufacture of other food products n.e.c. | DV73: 6N | DW73: ECMWF (European Centre for Medium-Range Weather Forecasts) | EH73: E.4 | EI73: Hybrid equity instrument - Instrument with characteristics of debt and equity which are classified as equity according to their main characteristics. | FR73: 220501 | FW73: Hydrogen powered-vehicles | FX73: A.2.21. Hydrogen powered-vehicles | GG73: 101442 | GH73: Peru Inter Business Destination Peru
F74: IRR | G74: Iranian Rial | H74: IRR | I74: Iranian Rial | J74: IRR | K74: Iranian Rial | L74: IRR | M74: Iranian Rial | N74: IRR | O74: Iranian Rial | CL74: ES | CM74: Spain | CP74: 10.9 | CQ74: Manufacture of prepared animal feeds | DV74: 6O | DW74: OECD (Organisation for Economic Co-operation and Development) | EH74: E.41 | EI74: Participation certificate (Genussschein) - Participation certificates grant their holders participation rights. Participation rights may take various forms, both for equity securities and for debt securities. In many countries, almost no legal restrictions are placed on this type of financial instrument. Depending on their specific features, participation certificates are considered to be either equity securities or debt securities. They are treated as equity securities if the following criteria are met: a) the holder’s claims are subordinated, b)the holder’s remuneration is performance related and c) capital is provided for an unlimited period, or at least on a long-term basis. In light of these criteria, most participation certificates are considered to be equity securities. 3.47 “Genussscheine” (or “Genussrechte”) are a type of participation certificate. These are issued mainly in European countries such as Germany, Austria, and Switzerland. “Genussscheine” sometimes have a stated maturity. | FU74: Construction and Real Estate | GG74: 101460 | GH74: Sales Credit BrazilHong Kong
F75: ISK | G75: Iceland Krona | H75: ISK | I75: Iceland Krona | J75: ISK | K75: Iceland Krona | L75: ISK | M75: Iceland Krona | N75: ISK | O75: Iceland Krona | CL75: ET | CM75: Ethiopia | CP75: 10.91 | CQ75: Manufacture of prepared feeds for farm animals | DV75: 6P | DW75: CERN (European Organisation for Nuclear Research) | EH75: E.42 | EI75: Convertible (preferred) share - Holders are allowed to convert preferred shares into a specified amount of ordinary shares. | FV75: Construction of new buildings | GG75: 101471 | GH75: Interbusiness funding BEI
F76: JMD | G76: Jamaican Dollar | H76: JMD | I76: Jamaican Dollar | J76: JMD | K76: Jamaican Dollar | L76: JMD | M76: Jamaican Dollar | N76: JMD | O76: Jamaican Dollar | CL76: FI | CM76: Finland | CP76: 10.92 | CQ76: Manufacture of prepared pet foods | DV76: 6Q | DW76: IOM (International Organisation for Migration) | EH76: E.43 | EI76: Subscription right - Subscription rights that are traded separately are often given their own separate International Securities Identification Number (ISIN). They are classified as shares, rather than as financial derivatives, since they represent a claim on the residual value of a corporation. Issuers of shares use subscription rights to provide existing shareholders with the opportunity to participate in new issues, which enables them to retain their proportional share in the ownership of the corporation. To make the new shares even more attractive, these subscription rights may also allow existing shareholders to buy the shares at less than the market price. | FR76: 2301 | FW76: - | FX76: A.3.1. Construction of new buildings | GG76: 101477 | GH76: Activity by Sellers Poland
F77: JOD | G77: Jordanian Dinar | H77: JOD | I77: Jordanian Dinar | J77: JOD | K77: Jordanian Dinar | L77: JOD | M77: Jordanian Dinar | N77: JOD | O77: Jordanian Dinar | CL77: FJ | CM77: Fiji | CP77: 11 | CQ77: Manufacture of beverages | DV77: 7B | DW77: IDB (Islamic Development Bank) | EH77: E.49 | EI77: Other hybrid equity instrument - A hybrid equity instrument that is of a type not listed separately. | FV77: Renovation of existing buildings | GG77: 101495 | GH77: SPREA: Private Banking Commission Sharing
F78: JPY | G78: Japanese yen | H78: JPY | I78: Japanese yen | J78: JPY | K78: Japanese yen | L78: JPY | M78: Japanese yen | N78: JPY | O78: Japanese yen | CL78: FK | CM78: Falkland Islands (the) [Malvinas] | CP78: 11.01 | CQ78: Distilling, rectifying and blending of spirits | DV78: 7C | DW78: EDB (Eurasian Development Bank ) | EH78: E.9 | EI78: Other equity - An equity instrument that is of a type not listed separately. This also includes "Other equity" in accordance with ESA 2010 (F.519) that is not in the form of securities. Other equity includes equity in quasi-corporations (such as branches, trusts, and partnerships), as well as notional units representing ownership of real estate. | FR78: 2302 | FW78: - | FX78: A.3.2. Renovation of existing buildings | GG78: 101180 | GH78: Cross Referral Mexico BPI
F79: KES | G79: Kenyan Shilling | H79: KES | I79: Kenyan Shilling | J79: KES | K79: Kenyan Shilling | L79: KES | M79: Kenyan Shilling | N79: KES | O79: Kenyan Shilling | CL79: FM | CM79: Micronesia (Federated States of) | CP79: 11.02 | CQ79: Manufacture of wine from grape | DV79: 7D | DW79: Paris Club Creditor Institutions | EH79: F | EI79: Fund - Investment fund shares are shares of an investment fund if the fund has a corporate structure. They are known as units if the fund is a trust. Investment funds are collective investment undertakings through which investors pool funds for investment in financial and/or non-financial assets. Funds are part of the financial assets and liabilities (financial instrument) category “equity and investment fund shares or units” (F.5) and belong to the subcategory “Investment fund shares or units” (F.52) in ESA 2010. | FV79: Installation, maintenance and repair | GG79: 101182 | GH79: Interdealer Peru operations
F80: KGS | G80: Som | H80: KGS | I80: Som | J80: KGS | K80: Som | L80: KGS | M80: Som | N80: KGS | O80: Som | CL80: FO | CM80: Faroe Islands (the) | CP80: 11.03 | CQ80: Manufacture of cider and other fruit wines | DV80: 7E | DW80: CEB (Council of Europe Development Bank) | EH80: F.1 | EI80: Undertaking for collective investment in transferable securities (UCITS) Fund - Undertakings for Collective Investment in Transferable Securities (UCITS) as defined in Directive 2009/65/EC on the coordination of laws, regulations and administrative provisions relating to UCITS. | FR80: 230301 | FW80: Energy efficiency equipment | FX80: A.3.3. Installation, maintenance and repair of energy efficiency equipment | GG80: 101187 | GH80: Interbusiness COFRA HOLDING AG MexicoFrankfurt
F81: KHR | G81: Riel | H81: KHR | I81: Riel | J81: KHR | K81: Riel | L81: KHR | M81: Riel | N81: KHR | O81: Riel | CL81: FR | CM81: France | CP81: 11.04 | CQ81: Manufacture of other non-distilled fermented beverages | DV81: 7F | DW81: International Union of Credit and Investment Insurers | EH81: F.2 | EI81: Alternative investment fund (AIF) - Alternative investment fund (AIF) as defined in Directive 2011/61/EU on Alternative Investment Fund Managers. | FR81: 230302 | FW81: Electric vehicles Charging stations (buildings & parking spaces) | FX81: A.3.4. Installation, maintenance and repair of charging stations for electric vehicles in buildings (and parking spaces attached to buildings) | GG81: 101220 | GH81: Boadilla08/09 Fees
F82: KMF | G82: Comoro Franc | H82: KMF | I82: Comoro Franc | J82: KMF | K82: Comoro Franc | L82: KMF | M82: Comoro Franc | N82: KMF | O82: Comoro Franc | CL82: GA | CM82: Gabon | CP82: 11.05 | CQ82: Manufacture of beer | DV82: 7G | DW82: Black Sea Trade and Development Banks | EH82: F.9 | EI82: Other fund - A fund that is of a type not listed separately. | FR82: 230303 | FW82: Instruments and devices for energy performance of buildings | FX82: A.3.5. Installation, maintenance and repair of instruments and devices for measuring, regulation and controlling energy performance of buildings | GG82: 101250 | GH82: Expenses Corporate Affairs EU
F83: KPW | G83: North Korean Won | H83: KPW | I83: North Korean Won | J83: KPW | K83: North Korean Won | L83: KPW | M83: North Korean Won | N83: KPW | O83: North Korean Won | CL83: GB | CM83: United Kingdom of Great Britain and Northern Ireland (the) | CP83: 11.06 | CQ83: Manufacture of malt | DV83: 7H | DW83: AFREXIMBANK (African Export-Import Bank) | FR83: 230304 | FW83: Renewable energy technologies | FX83: A.3.6. Installation, maintenance and repair of renewable energy technologies | GG83: 101252 | GH83: Allocation Nordics Expenses
F84: KRW | G84: Won | H84: KRW | I84: Won | J84: KRW | K84: Won | L84: KRW | M84: Won | N84: KRW | O84: Won | CL84: GD | CM84: Grenada | CP84: 11.07 | CQ84: Manufacture of soft drinks; production of mineral waters and other bottled waters | DV84: 7I | DW84: BLADEX (Banco Latino Americano De Comercio Exterior) | FV84: Acquisition and ownership | GG84: 101253 | GH84: Indirect Expenses SCF Division
F85: KWD | G85: Kuwaiti Dinar | H85: KWD | I85: Kuwaiti Dinar | J85: KWD | K85: Kuwaiti Dinar | L85: KWD | M85: Kuwaiti Dinar | N85: KWD | O85: Kuwaiti Dinar | CL85: GE | CM85: Georgia | CP85: 12 | CQ85: Manufacture of tobacco products | DV85: 7J | DW85: FLAR (Fondo Latino Americano de Reservas) | FR85: 2304 | FW85: - | FX85: A.3.7. Acquisition and ownership | GG85: 101259 | GH85: Compensation of Expenses
F86: KYD | G86: Cayman Islands Dollar | H86: KYD | I86: Cayman Islands Dollar | J86: KYD | K86: Cayman Islands Dollar | L86: KYD | M86: Cayman Islands Dollar | N86: KYD | O86: Cayman Islands Dollar | CL86: GF | CM86: French Guiana | CP86: 13 | CQ86: Manufacture of textiles | DV86: 7K | DW86: Fonds Belgo-Congolais d'Amortissement et de Gestion | EH86: Sources for definitions: Handbook on Securities Statistics, ESA 2010, Classification of financial instruments (CFI code) and Asset types of the list of eligible marketable assets (ECB General Documentation). | FV86: Demolition and wrecking | GG86: 100699 | GH86: Sales Credits Brazil Abbey
F87: KZT | G87: Tenge | H87: KZT | I87: Tenge | J87: KZT | K87: Tenge | L87: KZT | M87: Tenge | N87: KZT | O87: Tenge | CL87: GG | CM87: Guernsey | CP87: 13.1 | CQ87: Preparation and spinning of textile fibres | DV87: 7L | DW87: IFFIm (International finance Facility for Immunisation) | FR87: 2305 | FW87: - | FX87: A.3.8. Demolition and wrecking of buildings and other structures | GG87: 100967 | GH87: Treasury Transfer
