Workbook

Sheet Parametrização LT803
A1: campo_lt | B1: valor_origem | C1: valor_lt | D1: descritivo_lt
A2: SECTOR_INST | B2: S11 | C2: Non-financial corporations | D2: Non-financial corporations
A3: SECTOR_INST | B3: S12 | C3: Credit institutions | D3: Credit institutions
A4: SECTOR_INST | B4: S121 | C4: Central Bank | D4: Central Bank
A5: SECTOR_INST | B5: S122 | C5: Deposit-taking corporations other than credit institutions | D5: Deposit-taking corporations other than credit institutions
A6: SECTOR_INST | B6: S1220001 | C6: Deposit-taking corporations other than credit institutions | D6: Deposit-taking corporations other than credit institutions
A7: SECTOR_INST | B7: S1220002 | C7: Deposit-taking corporations other than credit institutions | D7: Deposit-taking corporations other than credit institutions
A8: SECTOR_INST | B8: S1220003 | C8: Deposit-taking corporations other than credit institutions | D8: Deposit-taking corporations other than credit institutions
A9: SECTOR_INST | B9: S1220004 | C9: Deposit-taking corporations other than credit institutions | D9: Deposit-taking corporations other than credit institutions
A10: SECTOR_INST | B10: S123 | C10: Money market funds (MMF) | D10: Money market funds (MMF)
A11: SECTOR_INST | B11: S124 | C11: Non-MMF Investment funds | D11: Non-MMF Investment funds
A12: SECTOR_INST | B12: S1240001 | C12: Non-MMF Investment funds | D12: Non-MMF Investment funds
... A133: SECTOR_INST | B133: S402510 | C133: N/A | D133: N/A

Sheet Opções de Mapeamento SRB
A1: Opções SRB
A2: Non-financial corporations
A3: Central Bank
A4: Credit institutions
A5: Deposit-taking corporations other than credit institutions
A6: Money market funds (MMF)
A7: Non-MMF Investment funds
A8: Financial vehicle corporations (FVCs) engaged in securitisation transactions, Other financial intermediaries, except financial auxiliaries, captive financial institutions and money lenders, insurance corporations, pension funds and financial vehicle corporations engaged in securitisation transactions
A9: Financial auxiliaries
A10: Captive financial institutions and money lenders
A11: Insurance corporations
A12: Pension funds
... A17: Non-profit institutions serving households

Sheet Análise de Mapeamento
A1: tayd91c0_celemtab_t | B1: tayd91c0_gelemtab_y86 | C1: tayd91c0_gelemtab_h01 CRC5G- SETOR INSTITUCIONAL (ID STI) | D1: Conciliando ambas as Parametrizações | E1: Y - Está na ct003; N - Não está | F1: Aplicar o Mapeamento de Loan Tapes a estes sectores institucionais | G1: Tentativa Inicial de mapear os sectores institucionais com as opções dadas pelo SRB
A2: Codigos de sector institucional | B2: PARAM 1 | C2: PARAM 2 | D2: Descrições tat91 ("H01","Y86") | E2: Flag in ct003_univ_cli | F2: Mapeamento realizado no Loan Tape | G2: Mapeamento proposto | H2: Identificação BdP
A3: S11 | B3: SOCIEDADES NAO FINANCEIRAS - R | C3: Sociedades não financeiras | D3: Sociedades não financeiras | E3: Y | F3: Non-financial corporations | G3: Non-financial corporations | H3: =VLOOKUP(A3,'sector BdP'!$A$2:$C$72,3,0) -> Non-financial corporations
A4: S12 | B4: NULL | C4: Sociedades financeiras | D4: Sociedades financeiras | E4: N | F4: #N/A | G4: Credit institutions | H4: =VLOOKUP(A4,'sector BdP'!$A$2:$C$72,3,0) -> Financial corporations
A5: S121 | B5: BANCO CENTRAL - R | C5: Banco central | D5: Banco central | E5: Y | F5: The central bank | G5: Central Bank | H5: =VLOOKUP(A5,'sector BdP'!$A$2:$C$72,3,0) -> Central bank
A6: S122 | B6: ENTIDADES DEPOSITARIAS EXCETO BCO CENTRAL - R | C6: Entidades depositárias exceto o banco central | D6: Entidades depositárias exceto o banco central | E6: Y | F6: Deposit-taking corporations except the central bank | G6: Deposit-taking corporations other than credit institutions | H6: =VLOOKUP(A6,'sector BdP'!$A$2:$C$72,3,0) -> Deposit taking corporations, except the Central bank
A7: S1220001 | B7: NULL | C7: Bancos | D7: Bancos | E7: Y | F7: Deposit-taking corporations except the central bank | G7: Deposit-taking corporations other than credit institutions | H7: =VLOOKUP(A7,'sector BdP'!$A$2:$C$72,3,0) -> Banks
A8: S1220002 | B8: NULL | C8: Caixas de crédito agrícola mútuo | D8: Caixas de crédito agrícola mútuo | E8: N | F8: Deposit-taking corporations except the central bank | G8: Deposit-taking corporations other than credit institutions | H8: =VLOOKUP(A8,'sector BdP'!$A$2:$C$72,3,0) -> Mutual agriculture credit banks
A9: S1220003 | B9: NULL | C9: Caixas económicas | D9: Caixas económicas | E9: N | F9: Deposit-taking corporations except the central bank | G9: Deposit-taking corporations other than credit institutions | H9: =VLOOKUP(A9,'sector BdP'!$A$2:$C$72,3,0) -> Savings banks
A10: S1220004 | B10: NULL | C10: Instituições de moeda electrónica | D10: Instituições de moeda electrónica | E10: N | F10: Deposit-taking corporations except the central bank | G10: Deposit-taking corporations other than credit institutions | H10: =VLOOKUP(A10,'sector BdP'!$A$2:$C$72,3,0) -> Electronic money institutions
A11: S123 | B11: FUNDOS DO MERCADO MONETARIO (FMM) - R | C11: Fundos do mercado monetário (FMM) | D11: Fundos do mercado monetário (FMM) | E11: Y | F11: Money market funds (MMFs) | G11: Money market funds (MMF) | H11: =VLOOKUP(A11,'sector BdP'!$A$2:$C$72,3,0) -> Money market funds (MMF)
A12: S124 | B12: FUNDOS DE INVESTIMENTO EXCETO FMM - R | C12: Fundos de investimento exceto FMM | D12: Fundos de investimento exceto FMM | E12: Y | F12: Non-MMF investment funds | G12: Non-MMF Investment funds | H12: =VLOOKUP(A12,'sector BdP'!$A$2:$C$72,3,0) -> Non-money market funds investment funds
A13: S1240001 | B13: NULL | C13: Fundos de investimento mobiliários | D13: Fundos de investimento mobiliários | E13: N | F13: Non-MMF investment funds | G13: Non-MMF Investment funds | H13: =VLOOKUP(A13,'sector BdP'!$A$2:$C$72,3,0) -> Securities investment funds (except money market funds)
A14: S1240002 | B14: NULL | C14: Fundos de investimento imobiliários | D14: Fundos de investimento imobiliários | E14: N | F14: Non-MMF investment funds | G14: Non-MMF Investment funds | H14: =VLOOKUP(A14,'sector BdP'!$A$2:$C$72,3,0) -> Real estate investment funds
A15: S1240003 | B15: NULL | C15: Fundos de investimento capital de risco | D15: Fundos de investimento capital de risco | E15: N | F15: Non-MMF investment funds | G15: Non-MMF Investment funds | H15: =VLOOKUP(A15,'sector BdP'!$A$2:$C$72,3,0) -> Venture capital funds
A16: S125 | B16: NULL | C16: Outros intermediários financeiros exceto sociedades de seguros e fundos de pensõ | D16: Outros intermediários financeiros exceto sociedades de seguros e fundos de pensõ | E16: N | F16: Other financial intermediaries, except ICPFs | G16: Financial vehicle corporations (FVCs) engaged in securitisation transactions, Other financial intermediaries, except financial auxiliaries, captive financial institutions and money lenders, insurance corporations, pension funds and financial vehicle corporations engaged in securitisation transactions | H16: =VLOOKUP(A16,'sector BdP'!$A$2:$C$72,3,0) -> Other financial intermediaries except insurance corporations and pension funds
... A30: S1250014 | B30: FUNDOS TITULARIZACAO DE CREDITOS - R | C30: Fundos de titularização de créditos | D30: Fundos de titularização de créditos | E30: N | F30: Other financial intermediaries, except ICPFs | G30: Financial vehicle corporations (FVCs) engaged in securitisation transactions, Other financial intermediaries, except financial auxiliaries, captive financial institutions and money lenders, insurance corporations, pension funds and financial vehicle corporations engaged in securitisation transactions | H30: =VLOOKUP(A30,'sector BdP'!$A$2:$C$72,3,0) -> Securitization funds
A31: S1250015 | B31: OUTROS INTERMEDIARIOS FINANCEIROS - OUTROS - R | C31: NULL | D31: OUTROS INTERMEDIARIOS FINANCEIROS - OUTROS - R | E31: Y | F31: Other financial intermediaries, except ICPFs | G31: Financial vehicle corporations (FVCs) engaged in securitisation transactions, Other financial intermediaries, except financial auxiliaries, captive financial institutions and money lenders, insurance corporations, pension funds and financial vehicle corporations engaged in securitisation transactions | H31: Other
A32: S1250019 | B32: OUTROS INTERMEDIARIOS FINANCEIROS-OUTROS - R | C32: Outros intermediários financeiros | D32: Outros intermediários financeiros | E32: Y | F32: Other financial intermediaries, except ICPFs | G32: Financial vehicle corporations (FVCs) engaged in securitisation transactions, Other financial intermediaries, except financial auxiliaries, captive financial institutions and money lenders, insurance corporations, pension funds and financial vehicle corporations engaged in securitisation transactions | H32: =VLOOKUP(A32,'sector BdP'!$A$2:$C$72,3,0) -> Other
A33: S126 | B33: AUXILIARES FINANCEIROS - R | C33: Auxiliares Financeiros | D33: Auxiliares Financeiros | E33: Y | F33: Financial auxiliaries | G33: Financial auxiliaries | H33: =VLOOKUP(A33,'sector BdP'!$A$2:$C$72,3,0) -> Financial auxiliaries
A34: S1260001 | B34: NULL | C34: Auxiliares de seguros | D34: Auxiliares de seguros | E34: N | F34: Financial auxiliaries | G34: Financial auxiliaries | H34: =VLOOKUP(A34,'sector BdP'!$A$2:$C$72,3,0) -> Insurance auxiliaries
A35: S1260002 | B35: NULL | C35: Agencias de câmbios | D35: Agencias de câmbios | E35: N | F35: Financial auxiliaries | G35: Financial auxiliaries | H35: =VLOOKUP(A35,'sector BdP'!$A$2:$C$72,3,0) -> Exchange offices
A36: S1260003 | B36: NULL | C36: Sociedades corretoras | D36: Sociedades corretoras | E36: N | F36: Financial auxiliaries | G36: Financial auxiliaries | H36: =VLOOKUP(A36,'sector BdP'!$A$2:$C$72,3,0) -> Brokers
A37: S1260004 | B37: NULL | C37: Sociedades gestoras de fundos de investimento | D37: Sociedades gestoras de fundos de investimento | E37: N | F37: Financial auxiliaries | G37: Financial auxiliaries | H37: =VLOOKUP(A37,'sector BdP'!$A$2:$C$72,3,0) -> Investment funds managing corporations
A38: S1260005 | B38: NULL | C38: Sociedades gestoras de fundos de titularização de créditos | D38: Sociedades gestoras de fundos de titularização de créditos | E38: N | F38: Financial auxiliaries | G38: Financial auxiliaries | H38: =VLOOKUP(A38,'sector BdP'!$A$2:$C$72,3,0) -> Securitization funds managing corporations
A39: S1260006 | B39: NULL | C39: Sociedades gestoras de fundos de pensões | D39: Sociedades gestoras de fundos de pensões | E39: N | F39: Financial auxiliaries | G39: Financial auxiliaries | H39: =VLOOKUP(A39,'sector BdP'!$A$2:$C$72,3,0) -> Pension funds managing corporations
A40: S1260007 | B40: NULL | C40: Sociedades gestoras de patrimónios | D40: Sociedades gestoras de patrimónios | E40: N | F40: Financial auxiliaries | G40: Financial auxiliaries | H40: =VLOOKUP(A40,'sector BdP'!$A$2:$C$72,3,0) -> Wealth managing corporations
A41: S1260008 | B41: NULL | C41: Sociedades administradoras de compras em grupo | D41: Sociedades administradoras de compras em grupo | E41: N | F41: Financial auxiliaries | G41: Financial auxiliaries | H41: =VLOOKUP(A41,'sector BdP'!$A$2:$C$72,3,0) -> Group-purchase managing corporations
A42: S1260009 | B42: NULL | C42: Sociedades mediadoras do mercado monetário e do mercado de câmbios | D42: Sociedades mediadoras do mercado monetário e do mercado de câmbios | E42: N | F42: Financial auxiliaries | G42: Financial auxiliaries | H42: =VLOOKUP(A42,'sector BdP'!$A$2:$C$72,3,0) -> Foreign exchange and money market mediating corporations
A43: S1260010 | B43: NULL | C43: Sedes sociais de sociedades financeiras | D43: Sedes sociais de sociedades financeiras | E43: N | F43: Financial auxiliaries | G43: Financial auxiliaries | H43: =VLOOKUP(A43,'sector BdP'!$A$2:$C$72,3,0) -> Financial head offices
... A65: S1312122000 | B65: ADM. REGIONAL MADEIRA - R | C65: NULL | D65: ADM. REGIONAL MADEIRA - R | E65: Y | F65: State government | G65: State government | H65: =VLOOKUP(A65,'sector BdP'!$A$2:$C$72,3,0) -> Autonomous Region of Madeira
A66: S1312201 | B66: NULL | C66: Orgãos do governo regional | D66: Orgãos do governo regional | E66: N | F66: State government | G66: State government
A67: S1312202 | B67: NULL | C67: Serviços e fundos autónomos da administração regional | D67: Serviços e fundos autónomos da administração regional | E67: N | F67: State government | G67: State government
A68: S1312203 | B68: NULL | C68: Empresas públicas da administração regional | D68: Empresas públicas da administração regional | E68: N | F68: State government | G68: State government
A69: S1312204 | B69: NULL | C69: Instituições sem fim lucrativo da administração regional | D69: Instituições sem fim lucrativo da administração regional | E69: N | F69: State government | G69: State government
A70: S1313 | B70: NULL | C70: Administracão local | D70: Administracão local | E70: N | F70: Local government | G70: Local government | H70: =VLOOKUP(A70,'sector BdP'!$A$2:$C$72,3,0) -> Local government
A71: S1313131000 | B71: ADM. LOCAL CONTINENTE - R | C71: NULL | D71: ADM. LOCAL CONTINENTE - R | E71: Y | F71: #N/A | G71: Local government | H71: =VLOOKUP(A71,'sector BdP'!$A$2:$C$72,3,0) -> Local Government - Mainland
A72: S1313132000 | B72: ADM. LOCAL ACORES - R | C72: NULL | D72: ADM. LOCAL ACORES - R | E72: Y | F72: #N/A | G72: Local government | H72: =VLOOKUP(A72,'sector BdP'!$A$2:$C$72,3,0) -> Local Government - Azores
A73: S1313133000 | B73: ADM. LOCAL MADEIRA - R | C73: NULL | D73: ADM. LOCAL MADEIRA - R | E73: Y | F73: #N/A | G73: Local government | H73: =VLOOKUP(A73,'sector BdP'!$A$2:$C$72,3,0) -> Local Government - Madeira
A74: S1313201 | B74: NULL | C74: Distritos | D74: Distritos | E74: N | F74: Local government | G74: Local government
A75: S1313202 | B75: NULL | C75: Municipios | D75: Municipios | E75: N | F75: Local government | G75: Local government
A76: S1313203 | B76: NULL | C76: Freguesias | D76: Freguesias | E76: N | F76: Local government | G76: Local government
A77: S1313204 | B77: NULL | C77: Serviços autónomos da Administração local | D77: Serviços autónomos da Administração local | E77: N | F77: Local government | G77: Local government
A78: S1313205 | B78: NULL | C78: Empresas públicas da Administração local | D78: Empresas públicas da Administração local | E78: N | F78: Local government | G78: Local government
A79: S1313206 | B79: NULL | C79: Instituições sem fim lucrativo da Administração local | D79: Instituições sem fim lucrativo da Administração local | E79: N | F79: Local government | G79: Local government
A80: S1314 | B80: FUNDOS DE SEGURANçA SOCIAL - R | C80: Fundos da Segurança Social | D80: Fundos da Segurança Social | E80: Y | F80: Social security funds | G80: Social security funds | H80: =VLOOKUP(A80,'sector BdP'!$A$2:$C$72,3,0) -> Social Security Funds
A81: S14 | B81: FAMíLIAS - R | C81: Famílias | D81: Famílias | E81: Y | F81: Households | G81: N/A | H81: =VLOOKUP(A81,'sector BdP'!$A$2:$C$72,3,0) -> Households
A82: S141 | B82: NULL | C82: Empregadores | D82: Empregadores | E82: N | F82: Households | G82: N/A
A83: S142 | B83: NULL | C83: Trabalhadores por conta própria | D83: Trabalhadores por conta própria | E83: N | F83: Households | G83: N/A
A84: S143 | B84: NULL | C84: Empregados | D84: Empregados | E84: N | F84: Households | G84: N/A
A85: S144 | B85: NULL | C85: Famílias com recursos provenientes de rendimentos de propriedade e transferência | D85: Famílias com recursos provenientes de rendimentos de propriedade e transferência | E85: N | F85: Households | G85: N/A
A86: S1441 | B86: NULL | C86: Famílias com recursos provenientes de rendimentos de propriedade | D86: Famílias com recursos provenientes de rendimentos de propriedade | E86: N | F86: Households | G86: N/A
A87: S1442 | B87: NULL | C87: Famílias com recursos provenientes de pensões | D87: Famílias com recursos provenientes de pensões | E87: N | F87: Households | G87: N/A
A88: S1443 | B88: NULL | C88: Famílias com recursos provenientes de outras transferencias | D88: Famílias com recursos provenientes de outras transferencias | E88: N | F88: Households | G88: N/A
A89: S15 | B89: INST SEM FINS LUCRATIVOS AO SERV DAS FAMILIAS - R | C89: Instituições sem fim lucrativo ao servico das famílias | D89: Instituições sem fim lucrativo ao servico das famílias | E89: Y | F89: Non-profit insitutions serving households | G89: Non-profit institutions serving households | H89: =VLOOKUP(A89,'sector BdP'!$A$2:$C$72,3,0) -> Non Profit Institutions serving households
A90: S16 | B90: EMIGRANTES | C90: NULL | D90: EMIGRANTES | E90: Y | F90: #N/A | G90: N/A | H90: =VLOOKUP(A90,'sector BdP'!$A$2:$C$72,3,0) -> Emigrants
A91: S201 | B91: SOCIEDADES NAO FINANCEIRAS - NR | C91: Sociedades não financeiras não residentes | D91: Sociedades não financeiras não residentes | E91: Y | F91: SOCIEDADES NAO FINANCEIRAS - NR | G91: Non-financial corporations
A92: S202 | B92: NULL | C92: Sociedades financeiras não residentes | D92: Sociedades financeiras não residentes | E92: N | F92: #N/A | G92: Credit institutions
A93: S2021 | B93: BANCO CENTRAL - NR | C93: Bancos centrais não residentes | D93: Bancos centrais não residentes | E93: Y | F93: #N/A | G93: Central Bank
A94: S2022 | B94: NULL | C94: Entidades depositárias não residentes, excepto bancos centrais | D94: Entidades depositárias não residentes, excepto bancos centrais | E94: N | F94: #N/A | G94: Deposit-taking corporations other than credit institutions
A95: S20221 | B95: SEDE E SUCURS DA PROPRIA INSTITUICAO - NR | C95: NULL | D95: SEDE E SUCURS DA PROPRIA INSTITUICAO - NR | E95: Y | F95: #N/A | G95: Deposit-taking corporations other than credit institutions
A96: S202221 | B96: IFM-OUTRAS INST COM RELACAO DE DOMINIO - NR | C96: NULL | D96: IFM-OUTRAS INST COM RELACAO DE DOMINIO - NR | E96: Y | F96: #N/A | G96: Deposit-taking corporations other than credit institutions
A97: S202222 | B97: IFM-OUTRAS - NR | C97: NULL | D97: IFM-OUTRAS - NR | E97: Y | F97: #N/A | G97: Deposit-taking corporations other than credit institutions
A98: S2023 | B98: NULL | C98: Fundos do mercado monetário (FMM) não residentes | D98: Fundos do mercado monetário (FMM) não residentes | E98: N | F98: #N/A | G98: Money market funds (MMF)
A99: S20231 | B99: FMM-OUTRAS INST COM RELACAO DE DOMINIO - NR | C99: NULL | D99: FMM-OUTRAS INST COM RELACAO DE DOMINIO - NR | E99: N | F99: #N/A | G99: Money market funds (MMF)
A100: S20232 | B100: FMM-OUTRAS - NR | C100: NULL | D100: FMM-OUTRAS - NR | E100: N | F100: #N/A | G100: Money market funds (MMF)
A101: S2024 | B101: FUNDOS DE INVESTIMENTO EXCETO FMM - NR | C101: Fundos de investimento, exceto FMM, não residentes | D101: Fundos de investimento, exceto FMM, não residentes | E101: Y | F101: #N/A | G101: Non-MMF Investment funds
A102: S2025 | B102: NULL | C102: Outros intermediários financeiros , excepto SSFP, não residentes | D102: Outros intermediários financeiros , excepto SSFP, não residentes | E102: N | F102: #N/A | G102: Financial vehicle corporations (FVCs) engaged in securitisation transactions, Other financial intermediaries, except financial auxiliaries, captive financial institutions and money lenders, insurance corporations, pension funds and financial vehicle corporations engaged in securitisation transactions
A103: S2025001 | B103: CONTRAPARTES CENTRAIS - NR | C103: NULL | D103: CONTRAPARTES CENTRAIS - NR | E103: Y | F103: #N/A | G103: Financial vehicle corporations (FVCs) engaged in securitisation transactions, Other financial intermediaries, except financial auxiliaries, captive financial institutions and money lenders, insurance corporations, pension funds and financial vehicle corporations engaged in securitisation transactions
... A105: S2025003 | B105: FUNDOS DE TITUL DE CREDITOS - NR | C105: NULL | D105: FUNDOS DE TITUL DE CREDITOS - NR | E105: N | F105: #N/A | G105: Financial vehicle corporations (FVCs) engaged in securitisation transactions, Other financial intermediaries, except financial auxiliaries, captive financial institutions and money lenders, insurance corporations, pension funds and financial vehicle corporations engaged in securitisation transactions
A106: S2025004 | B106: OUTROS INTERMEDIARIOS FINANCEIROS - OUTROS - NR | C106: NULL | D106: OUTROS INTERMEDIARIOS FINANCEIROS - OUTROS - NR | E106: Y | F106: OUTROS INTERMEDIARIOS FINANCEIROS - OUTROS - NR | G106: Financial vehicle corporations (FVCs) engaged in securitisation transactions, Other financial intermediaries, except financial auxiliaries, captive financial institutions and money lenders, insurance corporations, pension funds and financial vehicle corporations engaged in securitisation transactions
A107: S2025009 | B107: OUTROS INTERMEDIARIOS FINANCEIROS-OUTROS - NR | C107: NULL | D107: OUTROS INTERMEDIARIOS FINANCEIROS-OUTROS - NR | E107: Y | F107: #N/A | G107: Financial vehicle corporations (FVCs) engaged in securitisation transactions, Other financial intermediaries, except financial auxiliaries, captive financial institutions and money lenders, insurance corporations, pension funds and financial vehicle corporations engaged in securitisation transactions
A108: S2026 | B108: AUXILIARES FINANCEIROS - NR | C108: Auxiliares Financeiros não residentes | D108: Auxiliares Financeiros não residentes | E108: Y | F108: #N/A | G108: Financial auxiliaries
A109: S2027 | B109: INST FINANC CATIVAS E PRESTAMISTAS - NR | C109: Instituições financeiras cativas e prestamistas não residentes | D109: Instituições financeiras cativas e prestamistas não residentes | E109: Y | F109: #N/A | G109: Captive financial institutions and money lenders
A110: S2028 | B110: SOCIEDADES DE SEGUROS - NR | C110: Sociedades de seguros não residentes | D110: Sociedades de seguros não residentes | E110: Y | F110: #N/A | G110: Insurance corporations
A111: S2029 | B111: FUNDOS DE PENSõES - NR | C111: Fundos de Pensões não residentes | D111: Fundos de Pensões não residentes | E111: Y | F111: #N/A | G111: Pension funds
A112: S203 | B112: NULL | C112: Administrações públicas não residentes | D112: Administrações públicas não residentes | E112: N | F112: #N/A | G112: Central government
A113: S20311 | B113: ADMIN CENTRAL (EXCETO FUNDOS DE SEG SOC) - NR | C113: NULL | D113: ADMIN CENTRAL (EXCETO FUNDOS DE SEG SOC) - NR | E113: Y | F113: ADMIN CENTRAL (EXCETO FUNDOS DE SEG SOC) - NR | G113: Central government
A114: S20312 | B114: ADMINISTRACAO REGIONAL - NR | C114: NULL | D114: ADMINISTRACAO REGIONAL - NR | E114: Y | F114: #N/A | G114: State government
A115: S20313 | B115: ADMINISTRACAO LOCAL - NR | C115: NULL | D115: ADMINISTRACAO LOCAL - NR | E115: Y | F115: #N/A | G115: Local government
A116: S20314 | B116: FUNDOS DE SEGURANCA SOCIAL - NR | C116: NULL | D116: FUNDOS DE SEGURANCA SOCIAL - NR | E116: Y | F116: #N/A | G116: Social security funds
A117: S204 | B117: FAMILIAS - NR | C117: Famílias não residentes | D117: Famílias não residentes | E117: Y | F117: #N/A | G117: N/A
A118: S2041 | B118: NULL | C118: Emigrantes | D118: Emigrantes | E118: N | F118: #N/A | G118: N/A
A119: S2042 | B119: NULL | C119: Famílias não residentes - Outros | D119: Famílias não residentes - Outros | E119: N | F119: #N/A | G119: N/A
A120: S205 | B120: INST SEM FINS LUCRATIVOS AO SERV DAS FAMILIAS - NR | C120: Instituições sem fim lucrativo ao servico das famílias, não residentes | D120: Instituições sem fim lucrativo ao servico das famílias, não residentes | E120: Y | F120: #N/A | G120: Non-profit institutions serving households
A121: S206 | B121: NULL | C121: Organizações internacionais | D121: Organizações internacionais | E121: N | F121: #N/A | G121: N/A
A122: S2061 | B122: NULL | C122: Organizações internacionais não financeiras | D122: Organizações internacionais não financeiras | E122: N | F122: #N/A | G122: N/A
A123: S2062 | B123: NULL | C123: Organizações internacionais financeiras | D123: Organizações internacionais financeiras | E123: N | F123: #N/A | G123: N/A
A124: S20621 | B124: NULL | C124: Banco central europeu | D124: Banco central europeu | E124: N | F124: #N/A | G124: Central Bank
A125: S20622 | B125: NULL | C125: Outras organizações internacionais financeiras | D125: Outras organizações internacionais financeiras | E125: N | F125: #N/A | G125: Credit institutions
A126: S3 | B126: NAO SETORIZADO | C126: NULL | D126: NAO SETORIZADO | E126: Y | F126: #N/A | G126: N/A | H126: Não sectorizado
A127: S401100 | B127: SOCIEDADES NAO FINANCEIRAS SECTOR PUBLICO - RESIDENTES | C127: NULL | D127: SOCIEDADES NAO FINANCEIRAS SECTOR PUBLICO - RESIDENTES | E127: Y | F127: #N/A | G127: Non-financial corporations
A128: S401201 | B128: INSTITUICOES FINANCEIRAS MONETARIAS - SECTOR PUBLICO RESIDENTE | C128: NULL | D128: INSTITUICOES FINANCEIRAS MONETARIAS - SECTOR PUBLICO RESIDENTE | E128: Y | F128: #N/A | G128: Credit institutions
A129: S401311 | B129: OUTROS INT FIN AUX FIN INST FIN CAT PREST - SECTOR PUBLICO RESIDENTE | C129: NULL | D129: OUTROS INT FIN AUX FIN INST FIN CAT PREST - SECTOR PUBLICO RESIDENTE | E129: Y | F129: #N/A | G129: Financial vehicle corporations (FVCs) engaged in securitisation transactions, Other financial intermediaries, except financial auxiliaries, captive financial institutions and money lenders, insurance corporations, pension funds and financial vehicle corporations engaged in securitisation transactions
A130: S401341 | B130: FUNDOS INVESTIMENTO EXCEPTO FUNDOS MERCADO MONETARIO - SECTOR PUBLICO RESIDENTE | C130: NULL | D130: FUNDOS INVESTIMENTO EXCEPTO FUNDOS MERCADO MONETARIO - SECTOR PUBLICO RESIDENTE | E130: Y | F130: #N/A | G130: Non-MMF Investment funds
A131: S4013511 | B131: SOCIEDADES SEGUROS - SECTOR PUBLICO RESIDENTE | C131: NULL | D131: SOCIEDADES SEGUROS - SECTOR PUBLICO RESIDENTE | E131: N | F131: #N/A | G131: Insurance corporations
A132: S4013512 | B132: FUNDOS PENSOES - SECTOR PUBLICO RESIDENTE | C132: NULL | D132: FUNDOS PENSOES - SECTOR PUBLICO RESIDENTE | E132: Y | F132: #N/A | G132: Pension funds
A133: S401510 | B133: EMPRESARIOS EM NOME INDIVIDUAL - R | C133: NULL | D133: EMPRESARIOS EM NOME INDIVIDUAL - R | E133: Y | F133: #N/A | G133: N/A
A134: S402510 | B134: EMPRESARIOS EM NOME INDIVIDUAL - NR | C134: NULL | D134: EMPRESARIOS EM NOME INDIVIDUAL - NR | E134: Y | F134: #N/A | G134: N/A

Sheet sector BdP
A1: Subsetor SEC2010 / Subsector ESA2010 | B1: DESIGNAÇÃO SETOR / SUBSETOR SEC2010 | C1: ESA2010 SECTOR / SUBSECTOR NAME
A2: S11 | B2: Sociedades não financeiras | C2: Non-financial corporations
A3: S12 | B3: Sociedades financeiras | C3: Financial corporations
A4: S121 | B4: Banco central | C4: Central bank
A5: S122 | B5: Entidades depositárias exceto o banco central | C5: Deposit taking corporations, except the Central bank
A6: S1220001 | B6: Bancos | C6: Banks
A7: S1220002 | B7: Caixas de crédito agrícola mútuo | C7: Mutual agriculture credit banks
A8: S1220003 | B8: Caixas económicas | C8: Savings banks
A9: S1220004 | B9: Instituições de moeda electrónica | C9: Electronic money institutions
A10: S123 | B10: Fundos do mercado monetario (FMM) | C10: Money market funds (MMF)
A11: S124 | B11: Fundos de investimento exceto FMM | C11: Non-money market funds investment funds
A12: S1240001 | B12: Fundos de investimento mobiliários (exceto fundos do mercado monetário) | C12: Securities investment funds (except money market funds)
... A72: S2 | B72: Setor não residente | C72: Rest of the world

Sheet Mapeamento LT
A1: ISSR_ESA_2010_CD | B1: ISSR_ESA_2010_NM
A2: Code | B2: Description | C2: SRB
A3: S_11 | B3: Non-financial corporations | C3: ‣ Non-financial corporations
A4: S_11001 | B4: Non-financial corporations - public | C4: ‣ Non-financial corporations
A5: S_11002 | B5: Non-financial corporations - national private | C5: ‣ Non-financial corporations
A6: S_11003 | B6: Non-financial corporations - foreign controlled | C6: ‣ Non-financial corporations
A7: S_121 | B7: The central bank | C7: ‣ Central Bank
A8: S_122 | B8: Deposit-taking corporations except the central bank | C8: ? | D8: ‣ Deposit-taking corporations other than credit institutions
A9: S_12201 | B9: Deposit-taking corporations except the central bank - public | C9: ? | D9: ‣ Deposit-taking corporations other than credit institutions
A10: S_12202 | B10: Deposit-taking corporations except the central bank - national private | C10: ? | D10: ‣ Deposit-taking corporations other than credit institutions
A11: S_12203 | B11: Deposit-taking corporations except the central bank - foreign controlled | C11: ? | D11: ‣ Deposit-taking corporations other than credit institutions
A12: S_123 | B12: Money market funds (MMFs) | C12: ‣ Money market funds (MMF)
A13: S_12301 | B13: Money market funds (MMFs) - public | C13: ‣ Money market funds (MMF)
A14: S_12302 | B14: Money market funds (MMFs) - national private | C14: ‣ Money market funds (MMF)
A15: S_12303 | B15: Money market funds (MMFs) - foreign controlled | C15: ‣ Money market funds (MMF)
A16: S_124 | B16: Non-MMF investment funds | C16: ‣ Non-MMF Investment funds
A17: S_12401 | B17: Non-MMF investment funds - public | C17: ‣ Non-MMF Investment funds
A18: S_12402 | B18: Non-MMF investment funds - national private | C18: ‣ Non-MMF Investment funds
A19: S_12403 | B19: Non-MMF investment funds - foreign controlled | C19: ‣ Non-MMF Investment funds
A20: S_125 | B20: Other financial intermediaries, except ICPFs | C20: ? | D20: ‣ Financial vehicle corporations (FVCs) engaged in securitisation transactions, Other financial intermediaries, except financial auxiliaries, captive financial institutions and money lenders, insurance corporations, pension funds and financial vehicle corporations engaged in securitisation transactions
A21: S_12501 | B21: Other financial intermediaries, except ICPFs - public | C21: ? | D21: ‣ Financial vehicle corporations (FVCs) engaged in securitisation transactions, Other financial intermediaries, except financial auxiliaries, captive financial institutions and money lenders, insurance corporations, pension funds and financial vehicle corporations engaged in securitisation transactions
A22: S_12502 | B22: Other financial intermediaries, except ICPFs - national private | C22: ? | D22: ‣ Financial vehicle corporations (FVCs) engaged in securitisation transactions, Other financial intermediaries, except financial auxiliaries, captive financial institutions and money lenders, insurance corporations, pension funds and financial vehicle corporations engaged in securitisation transactions
A23: S_12503 | B23: Other financial intermediaries, except ICPFs - foreign controlled | C23: ? | D23: ‣ Financial vehicle corporations (FVCs) engaged in securitisation transactions, Other financial intermediaries, except financial auxiliaries, captive financial institutions and money lenders, insurance corporations, pension funds and financial vehicle corporations engaged in securitisation transactions
A24: S_126 | B24: Financial auxiliaries | C24: ‣ Financial auxiliaries
A25: S_12601 | B25: Financial auxiliaries - public | C25: ‣ Financial auxiliaries
A26: S_12602 | B26: Financial auxiliaries - national private | C26: ‣ Financial auxiliaries
A27: S_12603 | B27: Financial auxiliaries - foreign controlled | C27: ‣ Financial auxiliaries
A28: S_127 | B28: Captive financial institutions and money lenders | C28: ‣ Captive financial institutions and money lenders
A29: S_12701 | B29: Captive financial institutions and money lenders - public | C29: ‣ Captive financial institutions and money lenders
A30: S_12702 | B30: Captive financial institutions and money lenders - national private | C30: ‣ Captive financial institutions and money lenders
A31: S_12703 | B31: Captive financial institutions and money lenders - foreign controlled | C31: ‣ Captive financial institutions and money lenders
A32: S_128 | B32: Insurance corporations (ICs) | C32: ‣ Insurance corporations
A33: S_12801 | B33: Insurance corporations (ICs) - public | C33: ‣ Insurance corporations
A34: S_12802 | B34: Insurance corporations (ICs) - national private | C34: ‣ Insurance corporations
A35: S_12803 | B35: Insurance corporations (ICs) - foreign controlled | C35: ‣ Insurance corporations
... A39: S_12903 | B39: Pension funds (PFs) - foreign controlled | C39: ‣ Pension funds
A40: S_13 | B40: General government | C40: ? | D40: ‣ Credit institutions
A41: S_1311 | B41: Central government | C41: ‣ Central government
A42: S_1312 | B42: State government | C42: ‣ State government
A43: S_1313 | B43: Local government | C43: ‣ Local government
A44: S_1314 | B44: Social security funds | C44: ‣ Social security funds
A45: S_14 | B45: Households | C45: ? | D45: ‣ Credit institutions
A46: S_15 | B46: Non-profit insitutions serving households | C46: ‣ Non-profit institutions serving households
