Workbook

Sheet Plano_V1
B6: Re-testes - input | D6: 0.2 | M6: =M7-M10 -> 0 | N6: =N7-N10 -> 0 | O6: =O7-O10 -> 0 | P6: =P7-P10 -> 0 | Q6: =Q7-Q10 -> 0 | R6: =R7-R10 -> 0 | S6: =S7-S10 -> 0 | T6: =T7-T10 -> 0 | ... FK6: =FK7-FK10 -> 0
B7: Re-testes - output | D7: =50%*25% -> 0.125 | L7: =AVERAGE(M7:EL7) -> 2.4923077 | M7: 3 | N7: 3 | O7: 3 | P7: 3 | Q7: 3 | R7: 2 | S7: 2 | T7: 2 | U7: 2 | V7: 2 | W7: 2 | X7: 2 | Y7: 2 | Z7: 2 | AA7: 2 | AB7: 2 | AC7: 2 | AD7: 1 | AE7: 1 | AF7: 1 | AG7: 3 | AH7: 3 | AI7: 3 | AJ7: 3 | AK7: 2 | AL7: 3 | AM7: 3 | AN7: 3 | AO7: 3 | AP7: 3 | AQ7: 2 | AR7: 2 | AS7: 2 | AT7: 0 | AU7: 1 | AV7: 1 | AW7: 0 | AX7: 1 | AY7: 1 | AZ7: 1 | BA7: 2 | BB7: 2 | BC7: 2 | BD7: 2 | BE7: 2 | BF7: 2 | BG7: 2 | BH7: 2 | BI7: 2 | BJ7: 2 | BK7: 2 | BL7: 2 | BM7: 2 | BN7: 2 | BO7: 2 | BP7: 3 | BQ7: 3 | BR7: 3 | BS7: 3 | BT7: 3 | BU7: 3 | BV7: 3 | BW7: 3 | BX7: 3 | BY7: 3 | BZ7: 3 | CA7: 3 | CB7: 3 | CC7: 3 | CD7: 3 | CE7: 3 | CF7: 3 | CG7: 3 | CH7: 3 | CI7: 3 | CJ7: 3 | CK7: 3 | CL7: 3 | CM7: 3 | CN7: 3 | CO7: 3 | CP7: 3 | CQ7: 3 | CR7: 3 | CS7: 3 | CT7: 3 | CU7: 3 | CV7: 3 | CW7: 3 | CX7: 3 | CY7: 3 | CZ7: 3 | DA7: 3 | DB7: 3 | DC7: 3 | DD7: 3 | DE7: 3 | DF7: 3 | DG7: 3 | DH7: 3 | DI7: 3 | DJ7: 3 | DK7: 3 | DL7: 3 | DM7: 3 | DN7: 2 | DO7: 3 | DP7: 3 | DQ7: 3 | DR7: 3 | DS7: 3 | DT7: 3 | DU7: 3 | DV7: 3 | DW7: 3 | DX7: 3 | DY7: 3 | DZ7: 3 | EA7: 3 | EB7: 3 | EC7: 3 | ED7: 3 | EE7: 3 | EF7: 3 | EG7: 3 | EH7: 3 | EI7: 0 | EJ7: 0 | EK7: 0 | EL7: 0 | EM7: 0 | EN7: 0 | EO7: 0 | EP7: 3 | EQ7: 3 | ER7: 3 | ES7: 3 | ET7: 3 | EU7: 3 | EV7: 3 | EW7: 3 | EX7: 3 | EY7: 3 | EZ7: 3 | FA7: 3 | FB7: 3 | FC7: 3 | FD7: 3 | FE7: 3 | FF7: 3 | FG7: 3 | FH7: 3 | FI7: 3 | FJ7: 3 | FK7: 3
M10: =SUBTOTAL(9,M14:M636) -> 3 | N10: =SUBTOTAL(9,N14:N636) -> 3 | O10: =SUBTOTAL(9,O14:O636) -> 3 | P10: =SUBTOTAL(9,P14:P636) -> 3 | Q10: =SUBTOTAL(9,Q14:Q636) -> 3 | R10: =SUBTOTAL(9,R14:R636) -> 2 | S10: =SUBTOTAL(9,S14:S636) -> 2 | T10: =SUBTOTAL(9,T14:T636) -> 2 | ... FK10: =SUBTOTAL(9,FK14:FK636) -> 3
M11: Julho | W11: Julho | AJ11: Agosto | BF11: Setembro | CA11: Outubro | CX11: Novembro | DS11: Dezembro | EO11: Janeiro
M12: =M13 -> 45474 | N12: =N13 -> 45475 | O12: =O13 -> 45476 | P12: =P13 -> 45477 | Q12: =Q13 -> 45478 | R12: =R13 -> 45481 | S12: =S13 -> 45482 | T12: =T13 -> 45483 | ... FK12: =FK13 -> 45688
B13: Âmbito | C13: Sub-âmbito | D13: Tipo de teste | E13: Tabela | F13: Campo | G13: Status | H13: Status2 | I13: Horas | J13: Dias | K13: Pendências | L13: Val | M13: 45474 | N13: =WORKDAY(M13,1) -> 45475 | O13: =WORKDAY(N13,1) -> 45476 | P13: =WORKDAY(O13,1) -> 45477 | Q13: =WORKDAY(P13,1) -> 45478 | R13: =WORKDAY(Q13,1) -> 45481 | S13: =WORKDAY(R13,1) -> 45482 | T13: =WORKDAY(S13,1) -> 45483 | U13: =WORKDAY(T13,1) -> 45484 | ... FK13: =WORKDAY(FJ13,1) -> 45688
B14: 1. Assessment | I14: =SUM(I15:I18) -> 280 | J14: =SUM(J15:J18) -> 35
B15: Pilar III | C15: Bens Imóveis | G15: 7. Por iniciar | I15: =J15*8 -> 40 | J15: 5 | L15: =J15-SUM(M15:FK15) -> 0 | W15: 1 | X15: 1 | Y15: 1 | Z15: 1 | AA15: 1
B16: Pilar III | C16: Modelo Verde | G16: 7. Por iniciar | I16: =J16*8 -> 80 | J16: 10 | L16: =J16-SUM(M16:FK16) -> 0 | R16: 2 | S16: 2 | T16: 2 | U16: 2 | V16: 2
B17: Pilar III | C17: Pilar III | G17: 7. Por iniciar | I17: =J17*8 -> 40 | J17: 5 | L17: =J17-SUM(M17:FK17) -> 0 | AB17: 1 | AC17: 1 | AD17: 1 | AE17: 1 | AF17: 0.5 | AG17: 0.5
B18: GD | C18: GD | G18: 7. Por iniciar | I18: =J18*8 -> 120 | J18: 15 | L18: =J18-SUM(M18:FK18) -> 0 | M18: 3 | N18: 3 | O18: 3 | P18: 3 | Q18: 3
B20: 2. Re-especificação | I20: =SUM(I21:I23) -> 120 | J20: =SUM(J21:J23) -> 15
B21: Pilar III | C21: Bens Imóveis | G21: 7. Por iniciar | I21: =J21*8 -> 40 | J21: 5 | L21: =J21-SUM(M21:FK21) -> 0 | W21: 0.5 | AB21: 0.5 | AG21: 0.5 | AL21: 0.5 | AQ21: 0.5 | AV21: 0.5 | BA21: 0.5 | BF21: 0.5 | BK21: 0.5 | BP21: 0.5
B22: Pilar III | C22: Modelo Verde | G22: 7. Por iniciar | I22: =J22*8 -> 40 | J22: 5 | L22: =J22-SUM(M22:FK22) -> 0 | W22: 0.5 | AB22: 0.5 | AG22: 0.5 | AL22: 0.5 | AQ22: 0.5 | AV22: 0.5 | BA22: 0.5 | BF22: 0.5 | BK22: 0.5 | BP22: 0.5
B23: Pilar III | C23: Pilar III | G23: 7. Por iniciar | I23: =J23*8 -> 40 | J23: 5 | L23: =J23-SUM(M23:FK23) -> 0 | BF23: 0.5 | BK23: 0.5 | BP23: 0.5 | BU23: 0.5 | BZ23: 0.5 | CE23: 0.5 | CJ23: 0.5 | CO23: 0.5 | CT23: 0.5 | CY23: 0.5
B25: 3. Testes / Re-testes | I25: =I26+I27+I42+I198+I362+I447 -> 1341.1875 | J25: =J26+J27+J42+J198+J362+J447 -> 169
B26: Testes Regressivos | G26: 7. Por iniciar | I26: =4*22 -> 88 | J26: =I26/8 -> 11 | L26: =J26-SUM(M26:FK26) -> 0 | AA26: 0.5 | AF26: 0.5 | AK26: 0.5 | AP26: 0.5 | AU26: 0.5 | AZ26: 0.5 | BE26: 0.5 | BJ26: 0.5 | BO26: 0.5 | BT26: 0.5 | BY26: 0.5 | CD26: 0.5 | CI26: 0.5 | CN26: 0.5 | CS26: 0.5 | CX26: 0.5 | DC26: 0.5 | DH26: 0.5 | DM26: 0.5 | DR26: 0.5 | DW26: 0.5 | EB26: 0.5
B27: Pilar III | C27: Bens Imóveis - Input | I27: =SUM(I28:I41) -> 0 | J27: =ROUNDUP(I27/8,0) -> 0 | L27: =J27-SUM(M27:FK27) -> -3 | X27: 0.5 | Y27: 0.5 | AC27: 0.5 | AG27: 1 | AH27: 0.5
A28: =E28&F28 -> cd_imv_inp_certif_estimativan.a. | B28: Pilar III | C28: Bens Imóveis - Input | D28: 1. Universo | E28: cd_imv_inp_certif_estimativa | F28: n.a. | G28: =INDEX(Auxiliar!$B$16:$B$24,MATCH(Plano_V1!H28,Auxiliar!$C$16:$C$24,0),1) -> #N/A | H28: =VLOOKUP(A28,'Aux - pivots1'!$A:$B,2,0) -> #N/A | I28: =SUMIFS(Table1[Estimação (horas)],Table1[Tabela],Plano_V1!E28,Table1[Campo],Plano_V1!F28) -> 0 | J28: =I28/8 -> 0 | K28: sem pendencia | L28: =J28-SUM(M28:FK28) -> 0
A29: =E29&F29 -> cd_imv_inp_certif_estimativacempbem | B29: Pilar III | C29: Bens Imóveis - Input | D29: 2. Campo | E29: cd_imv_inp_certif_estimativa | F29: cempbem | G29: =INDEX(Auxiliar!$B$16:$B$24,MATCH(Plano_V1!H29,Auxiliar!$C$16:$C$24,0),1) -> #N/A | H29: =VLOOKUP(A29,'Aux - pivots1'!$A:$B,2,0) -> #N/A | I29: =SUMIFS(Table1[Estimação (horas)],Table1[Tabela],Plano_V1!E29,Table1[Campo],Plano_V1!F29) -> 0 | J29: =I29/8 -> 0 | K29: sem pendencia | L29: =J29-SUM(M29:FK29) -> 0
A30: =E30&F30 -> cd_imv_inp_certif_estimativachave_encriptada | B30: Pilar III | C30: Bens Imóveis - Input | D30: 2. Campo | E30: cd_imv_inp_certif_estimativa | F30: chave_encriptada | G30: =INDEX(Auxiliar!$B$16:$B$24,MATCH(Plano_V1!H30,Auxiliar!$C$16:$C$24,0),1) -> #N/A | H30: =VLOOKUP(A30,'Aux - pivots1'!$A:$B,2,0) -> #N/A | I30: =SUMIFS(Table1[Estimação (horas)],Table1[Tabela],Plano_V1!E30,Table1[Campo],Plano_V1!F30) -> 0 | J30: =I30/8 -> 0 | K30: sem pendencia | L30: =J30-SUM(M30:FK30) -> 0
A31: =E31&F31 -> cd_imv_inp_certif_estimativackbalbem | B31: Pilar III | C31: Bens Imóveis - Input | D31: 2. Campo | E31: cd_imv_inp_certif_estimativa | F31: ckbalbem | G31: =INDEX(Auxiliar!$B$16:$B$24,MATCH(Plano_V1!H31,Auxiliar!$C$16:$C$24,0),1) -> #N/A | H31: =VLOOKUP(A31,'Aux - pivots1'!$A:$B,2,0) -> #N/A | I31: =SUMIFS(Table1[Estimação (horas)],Table1[Tabela],Plano_V1!E31,Table1[Campo],Plano_V1!F31) -> 0 | J31: =I31/8 -> 0 | K31: sem pendencia | L31: =J31-SUM(M31:FK31) -> 0
A32: =E32&F32 -> cd_imv_inp_certif_estimativackctabem | B32: Pilar III | C32: Bens Imóveis - Input | D32: 2. Campo | E32: cd_imv_inp_certif_estimativa | F32: ckctabem | G32: =INDEX(Auxiliar!$B$16:$B$24,MATCH(Plano_V1!H32,Auxiliar!$C$16:$C$24,0),1) -> #N/A | H32: =VLOOKUP(A32,'Aux - pivots1'!$A:$B,2,0) -> #N/A | I32: =SUMIFS(Table1[Estimação (horas)],Table1[Tabela],Plano_V1!E32,Table1[Campo],Plano_V1!F32) -> 0 | J32: =I32/8 -> 0 | K32: sem pendencia | L32: =J32-SUM(M32:FK32) -> 0
A33: =E33&F33 -> cd_imv_inp_certif_estimativackrefbem | B33: Pilar III | C33: Bens Imóveis - Input | D33: 2. Campo | E33: cd_imv_inp_certif_estimativa | F33: ckrefbem | G33: =INDEX(Auxiliar!$B$16:$B$24,MATCH(Plano_V1!H33,Auxiliar!$C$16:$C$24,0),1) -> #N/A | H33: =VLOOKUP(A33,'Aux - pivots1'!$A:$B,2,0) -> #N/A | I33: =SUMIFS(Table1[Estimação (horas)],Table1[Tabela],Plano_V1!E33,Table1[Campo],Plano_V1!F33) -> 0 | J33: =I33/8 -> 0 | K33: sem pendencia | L33: =J33-SUM(M33:FK33) -> 0
A34: =E34&F34 -> cd_imv_inp_certif_estimativadata_extraccao_info | B34: Pilar III | C34: Bens Imóveis - Input | D34: 2. Campo | E34: cd_imv_inp_certif_estimativa | F34: data_extraccao_info | G34: =INDEX(Auxiliar!$B$16:$B$24,MATCH(Plano_V1!H34,Auxiliar!$C$16:$C$24,0),1) -> #N/A | H34: =VLOOKUP(A34,'Aux - pivots1'!$A:$B,2,0) -> #N/A | I34: =SUMIFS(Table1[Estimação (horas)],Table1[Tabela],Plano_V1!E34,Table1[Campo],Plano_V1!F34) -> 0 | J34: =I34/8 -> 0 | K34: sem pendencia | L34: =J34-SUM(M34:FK34) -> 0
A35: =E35&F35 -> cd_imv_inp_certif_estimativaepc | B35: Pilar III | C35: Bens Imóveis - Input | D35: 2. Campo | E35: cd_imv_inp_certif_estimativa | F35: epc | G35: =INDEX(Auxiliar!$B$16:$B$24,MATCH(Plano_V1!H35,Auxiliar!$C$16:$C$24,0),1) -> #N/A | H35: =VLOOKUP(A35,'Aux - pivots1'!$A:$B,2,0) -> #N/A | I35: =SUMIFS(Table1[Estimação (horas)],Table1[Tabela],Plano_V1!E35,Table1[Campo],Plano_V1!F35) -> 0 | J35: =I35/8 -> 0 | K35: sem pendencia | L35: =J35-SUM(M35:FK35) -> 0
A36: =E36&F36 -> cd_imv_inp_certif_estimativafornecedor | B36: Pilar III | C36: Bens Imóveis - Input | D36: 2. Campo | E36: cd_imv_inp_certif_estimativa | F36: fornecedor | G36: =INDEX(Auxiliar!$B$16:$B$24,MATCH(Plano_V1!H36,Auxiliar!$C$16:$C$24,0),1) -> #N/A | H36: =VLOOKUP(A36,'Aux - pivots1'!$A:$B,2,0) -> #N/A | I36: =SUMIFS(Table1[Estimação (horas)],Table1[Tabela],Plano_V1!E36,Table1[Campo],Plano_V1!F36) -> 0 | J36: =I36/8 -> 0 | K36: sem pendencia | L36: =J36-SUM(M36:FK36) -> 0
A37: =E37&F37 -> cd_imv_inp_certif_estimativametodo_info | B37: Pilar III | C37: Bens Imóveis - Input | D37: 2. Campo | E37: cd_imv_inp_certif_estimativa | F37: metodo_info | G37: =INDEX(Auxiliar!$B$16:$B$24,MATCH(Plano_V1!H37,Auxiliar!$C$16:$C$24,0),1) -> #N/A | H37: =VLOOKUP(A37,'Aux - pivots1'!$A:$B,2,0) -> #N/A | I37: =SUMIFS(Table1[Estimação (horas)],Table1[Tabela],Plano_V1!E37,Table1[Campo],Plano_V1!F37) -> 0 | J37: =I37/8 -> 0 | K37: sem pendencia | L37: =J37-SUM(M37:FK37) -> 0
A38: =E38&F38 -> cd_imv_inp_certif_estimativascore_qualidade | B38: Pilar III | C38: Bens Imóveis - Input | D38: 2. Campo | E38: cd_imv_inp_certif_estimativa | F38: score_qualidade | G38: =INDEX(Auxiliar!$B$16:$B$24,MATCH(Plano_V1!H38,Auxiliar!$C$16:$C$24,0),1) -> #N/A | H38: =VLOOKUP(A38,'Aux - pivots1'!$A:$B,2,0) -> #N/A | I38: =SUMIFS(Table1[Estimação (horas)],Table1[Tabela],Plano_V1!E38,Table1[Campo],Plano_V1!F38) -> 0 | J38: =I38/8 -> 0 | K38: sem pendencia | L38: =J38-SUM(M38:FK38) -> 0
A39: =E39&F39 -> cd_imv_inp_certif_estimativavlr_cnsm_ano | B39: Pilar III | C39: Bens Imóveis - Input | D39: 2. Campo | E39: cd_imv_inp_certif_estimativa | F39: vlr_cnsm_ano | G39: =INDEX(Auxiliar!$B$16:$B$24,MATCH(Plano_V1!H39,Auxiliar!$C$16:$C$24,0),1) -> #N/A | H39: =VLOOKUP(A39,'Aux - pivots1'!$A:$B,2,0) -> #N/A | I39: =SUMIFS(Table1[Estimação (horas)],Table1[Tabela],Plano_V1!E39,Table1[Campo],Plano_V1!F39) -> 0 | J39: =I39/8 -> 0 | K39: sem pendencia | L39: =J39-SUM(M39:FK39) -> 0
A40: =E40&F40 -> cd_imv_inp_certif_estimativavlr_emss_ano | B40: Pilar III | C40: Bens Imóveis - Input | D40: 2. Campo | E40: cd_imv_inp_certif_estimativa | F40: vlr_emss_ano | G40: =INDEX(Auxiliar!$B$16:$B$24,MATCH(Plano_V1!H40,Auxiliar!$C$16:$C$24,0),1) -> #N/A | H40: =VLOOKUP(A40,'Aux - pivots1'!$A:$B,2,0) -> #N/A | I40: =SUMIFS(Table1[Estimação (horas)],Table1[Tabela],Plano_V1!E40,Table1[Campo],Plano_V1!F40) -> 0 | J40: =I40/8 -> 0 | K40: sem pendencia | L40: =J40-SUM(M40:FK40) -> 0
A41: =E41&F41 -> Re-testesn.a. | B41: Pilar III | C41: Bens Imóveis - Input | D41: 2. Campo | E41: Re-testes | F41: n.a. | G41: 7. Por iniciar | I41: =SUM(I28:I40)*D6 -> 0 | J41: =I41/8 -> 0 | K41: sem pendencia | L41: =J41-SUM(M41:FK41) -> 0
A42: =E42&F42 | B42: Pilar III | C42: Bens Imóveis - Output | I42: =SUM(I43:I197) -> 0 | J42: =ROUNDUP(I42/8,0) -> 0 | L42: =J42-SUM(M42:FK42) -> -100 | AH42: 0.5 | AI42: 1 | AJ42: 1 | AM42: 1 | AN42: 1 | AO42: 1 | AP42: 0.5 | AR42: 1 | AS42: 2 | AU42: 0.5 | AX42: 1 | AY42: 1 | AZ42: 0.5 | BA42: 1 | BB42: 2 | BC42: 2 | BD42: 2 | BE42: 1.5 | BF42: 0.5 | BG42: 2 | BH42: 2 | BI42: 2 | BJ42: 1.5 | BK42: 0.5 | BL42: 2 | BM42: 2 | BN42: 2 | BO42: 1.5 | BP42: 1.5 | BQ42: 2 | BR42: 2 | BS42: 2 | BT42: 2 | BU42: 2 | BV42: 2 | BW42: 2 | BX42: 2 | BY42: 2 | BZ42: 2 | CA42: 2 | CB42: 2 | CC42: 2 | CD42: 2 | CE42: 2 | CF42: 2 | CG42: 2 | CH42: 2 | CI42: 2 | CJ42: 2 | CK42: 2 | CL42: 2 | CM42: 2 | CN42: 2 | CO42: 2 | CP42: 2 | CQ42: 2 | CR42: 2 | CS42: 2 | CT42: 2 | CU42: 2
A43: =E43&F43 -> cd_imv_out_prcn.a. | B43: Pilar III | C43: Bens Imóveis - Output | D43: 1. Universo | E43: cd_imv_out_prc | F43: n.a. | G43: =INDEX(Auxiliar!$B$16:$B$24,MATCH(Plano_V1!H43,Auxiliar!$C$16:$C$24,0),1) -> #N/A | H43: =VLOOKUP(A43,'Aux - pivots1'!$A:$B,2,0) -> #N/A | I43: =SUMIFS(Table1[Estimação (horas)],Table1[Tabela],Plano_V1!E43,Table1[Campo],Plano_V1!F43) -> 0 | J43: =I43/8 -> 0 | K43: cd_imv_out_trz_cred_prc | L43: =J43-SUM(M43:FK43) -> 0
A44: =E44&F44 -> cd_imv_out_prccempresa | B44: Pilar III | C44: Bens Imóveis - Output | D44: 2. Campo | E44: cd_imv_out_prc | F44: cempresa | G44: =INDEX(Auxiliar!$B$16:$B$24,MATCH(Plano_V1!H44,Auxiliar!$C$16:$C$24,0),1) -> #N/A | H44: =VLOOKUP(A44,'Aux - pivots1'!$A:$B,2,0) -> #N/A | I44: =SUMIFS(Table1[Estimação (horas)],Table1[Tabela],Plano_V1!E44,Table1[Campo],Plano_V1!F44) -> 0 | J44: =I44/8 -> 0 | K44: cd_imv_out_trz_cred_prc | L44: =J44-SUM(M44:FK44) -> 0
A45: =E45&F45 -> cd_imv_out_prcckbalcao | B45: Pilar III | C45: Bens Imóveis - Output | D45: 2. Campo | E45: cd_imv_out_prc | F45: ckbalcao | G45: =INDEX(Auxiliar!$B$16:$B$24,MATCH(Plano_V1!H45,Auxiliar!$C$16:$C$24,0),1) -> #N/A | H45: =VLOOKUP(A45,'Aux - pivots1'!$A:$B,2,0) -> #N/A | I45: =SUMIFS(Table1[Estimação (horas)],Table1[Tabela],Plano_V1!E45,Table1[Campo],Plano_V1!F45) -> 0 | J45: =I45/8 -> 0 | K45: cd_imv_out_trz_cred_prc | L45: =J45-SUM(M45:FK45) -> 0
A46: =E46&F46 -> cd_imv_out_prccknumcta | B46: Pilar III | C46: Bens Imóveis - Output | D46: 2. Campo | E46: cd_imv_out_prc | F46: cknumcta | G46: =INDEX(Auxiliar!$B$16:$B$24,MATCH(Plano_V1!H46,Auxiliar!$C$16:$C$24,0),1) -> #N/A | H46: =VLOOKUP(A46,'Aux - pivots1'!$A:$B,2,0) -> #N/A | I46: =SUMIFS(Table1[Estimação (horas)],Table1[Tabela],Plano_V1!E46,Table1[Campo],Plano_V1!F46) -> 0 | J46: =I46/8 -> 0 | K46: cd_imv_out_trz_cred_prc | L46: =J46-SUM(M46:FK46) -> 0
A47: =E47&F47 -> cd_imv_out_prccod_estd_prcs | B47: Pilar III | C47: Bens Imóveis - Output | D47: 2. Campo | E47: cd_imv_out_prc | F47: cod_estd_prcs | G47: =INDEX(Auxiliar!$B$16:$B$24,MATCH(Plano_V1!H47,Auxiliar!$C$16:$C$24,0),1) -> #N/A | H47: =VLOOKUP(A47,'Aux - pivots1'!$A:$B,2,0) -> #N/A | I47: 0 | J47: =I47/8 -> 0 | K47: cd_imv_out_trz_cred_prc | L47: =J47-SUM(M47:FK47) -> 0
A48: =E48&F48 -> cd_imv_out_prccod_grt | B48: Pilar III | C48: Bens Imóveis - Output | D48: 2. Campo | E48: cd_imv_out_prc | F48: cod_grt | G48: =INDEX(Auxiliar!$B$16:$B$24,MATCH(Plano_V1!H48,Auxiliar!$C$16:$C$24,0),1) -> #N/A | H48: =VLOOKUP(A48,'Aux - pivots1'!$A:$B,2,0) -> #N/A | I48: =SUMIFS(Table1[Estimação (horas)],Table1[Tabela],Plano_V1!E48,Table1[Campo],Plano_V1!F48) -> 0 | J48: =I48/8 -> 0 | K48: cd_imv_out_trz_cred_prc | L48: =J48-SUM(M48:FK48) -> 0
A49: =E49&F49 -> cd_imv_out_prccod_moeda | B49: Pilar III | C49: Bens Imóveis - Output | D49: 2. Campo | E49: cd_imv_out_prc | F49: cod_moeda | G49: =INDEX(Auxiliar!$B$16:$B$24,MATCH(Plano_V1!H49,Auxiliar!$C$16:$C$24,0),1) -> #N/A | H49: =VLOOKUP(A49,'Aux - pivots1'!$A:$B,2,0) -> #N/A | I49: =SUMIFS(Table1[Estimação (horas)],Table1[Tabela],Plano_V1!E49,Table1[Campo],Plano_V1!F49) -> 0 | J49: =I49/8 -> 0 | K49: cd_imv_out_trz_cred_prc | L49: =J49-SUM(M49:FK49) -> 0
A50: =E50&F50 -> cd_imv_out_prccod_observacao | B50: Pilar III | C50: Bens Imóveis - Output | D50: 2. Campo | E50: cd_imv_out_prc | F50: cod_observacao | G50: =INDEX(Auxiliar!$B$16:$B$24,MATCH(Plano_V1!H50,Auxiliar!$C$16:$C$24,0),1) -> #N/A | H50: =VLOOKUP(A50,'Aux - pivots1'!$A:$B,2,0) -> #N/A | I50: =SUMIFS(Table1[Estimação (horas)],Table1[Tabela],Plano_V1!E50,Table1[Campo],Plano_V1!F50) -> 0 | J50: =I50/8 -> 0 | K50: cd_imv_out_trz_cred_prc | L50: =J50-SUM(M50:FK50) -> 0
A51: =E51&F51 -> cd_imv_out_prccod_prd_grnt | B51: Pilar III | C51: Bens Imóveis - Output | D51: 2. Campo | E51: cd_imv_out_prc | F51: cod_prd_grnt | G51: =INDEX(Auxiliar!$B$16:$B$24,MATCH(Plano_V1!H51,Auxiliar!$C$16:$C$24,0),1) -> #N/A | H51: =VLOOKUP(A51,'Aux - pivots1'!$A:$B,2,0) -> #N/A | I51: =SUMIFS(Table1[Estimação (horas)],Table1[Tabela],Plano_V1!E51,Table1[Campo],Plano_V1!F51) -> 0 | J51: =I51/8 -> 0 | K51: cd_imv_out_trz_cred_prc | L51: =J51-SUM(M51:FK51) -> 0
A52: =E52&F52 -> cd_imv_out_prccod_sprd_grnt | B52: Pilar III | C52: Bens Imóveis - Output | D52: 2. Campo | E52: cd_imv_out_prc | F52: cod_sprd_grnt | G52: =INDEX(Auxiliar!$B$16:$B$24,MATCH(Plano_V1!H52,Auxiliar!$C$16:$C$24,0),1) -> #N/A | H52: =VLOOKUP(A52,'Aux - pivots1'!$A:$B,2,0) -> #N/A | I52: =SUMIFS(Table1[Estimação (horas)],Table1[Tabela],Plano_V1!E52,Table1[Campo],Plano_V1!F52) -> 0 | J52: =I52/8 -> 0 | K52: cd_imv_out_trz_cred_prc | L52: =J52-SUM(M52:FK52) -> 0
A53: =E53&F53 -> cd_imv_out_prccod_tipo | B53: Pilar III | C53: Bens Imóveis - Output | D53: 2. Campo | E53: cd_imv_out_prc | F53: cod_tipo | G53: =INDEX(Auxiliar!$B$16:$B$24,MATCH(Plano_V1!H53,Auxiliar!$C$16:$C$24,0),1) -> #N/A | H53: =VLOOKUP(A53,'Aux - pivots1'!$A:$B,2,0) -> #N/A | I53: =SUMIFS(Table1[Estimação (horas)],Table1[Tabela],Plano_V1!E53,Table1[Campo],Plano_V1!F53) -> 0 | J53: =I53/8 -> 0 | K53: cd_imv_out_trz_cred_prc | L53: =J53-SUM(M53:FK53) -> 0
A54: =E54&F54 -> cd_imv_out_prccomp_id_gar | B54: Pilar III | C54: Bens Imóveis - Output | D54: 2. Campo | E54: cd_imv_out_prc | F54: comp_id_gar | G54: =INDEX(Auxiliar!$B$16:$B$24,MATCH(Plano_V1!H54,Auxiliar!$C$16:$C$24,0),1) -> #N/A | H54: =VLOOKUP(A54,'Aux - pivots1'!$A:$B,2,0) -> #N/A | I54: =SUMIFS(Table1[Estimação (horas)],Table1[Tabela],Plano_V1!E54,Table1[Campo],Plano_V1!F54) -> 0 | J54: =I54/8 -> 0 | K54: cd_imv_out_trz_cred_prc | L54: =J54-SUM(M54:FK54) -> 0
A55: =E55&F55 -> cd_imv_out_prcdata_inicio | B55: Pilar III | C55: Bens Imóveis - Output | D55: 2. Campo | E55: cd_imv_out_prc | F55: data_inicio | G55: =INDEX(Auxiliar!$B$16:$B$24,MATCH(Plano_V1!H55,Auxiliar!$C$16:$C$24,0),1) -> #N/A | H55: =VLOOKUP(A55,'Aux - pivots1'!$A:$B,2,0) -> #N/A | I55: =SUMIFS(Table1[Estimação (horas)],Table1[Tabela],Plano_V1!E55,Table1[Campo],Plano_V1!F55) -> 0 | J55: =I55/8 -> 0 | K55: cd_imv_out_trz_cred_prc | L55: =J55-SUM(M55:FK55) -> 0
A56: =E56&F56 -> cd_imv_out_prcdata_vcmt | B56: Pilar III | C56: Bens Imóveis - Output | D56: 2. Campo | E56: cd_imv_out_prc | F56: data_vcmt | G56: =INDEX(Auxiliar!$B$16:$B$24,MATCH(Plano_V1!H56,Auxiliar!$C$16:$C$24,0),1) -> #N/A | H56: =VLOOKUP(A56,'Aux - pivots1'!$A:$B,2,0) -> #N/A | I56: =SUMIFS(Table1[Estimação (horas)],Table1[Tabela],Plano_V1!E56,Table1[Campo],Plano_V1!F56) -> 0 | J56: =I56/8 -> 0 | K56: cd_imv_out_trz_cred_prc | L56: =J56-SUM(M56:FK56) -> 0
A57: =E57&F57 -> cd_imv_out_prcmontante_eur | B57: Pilar III | C57: Bens Imóveis - Output | D57: 2. Campo | E57: cd_imv_out_prc | F57: montante_eur | G57: =INDEX(Auxiliar!$B$16:$B$24,MATCH(Plano_V1!H57,Auxiliar!$C$16:$C$24,0),1) -> #N/A | H57: =VLOOKUP(A57,'Aux - pivots1'!$A:$B,2,0) -> #N/A | I57: 0 | J57: =I57/8 -> 0 | K57: cd_imv_out_trz_cred_prc | L57: =J57-SUM(M57:FK57) -> 0
A58: =E58&F58 -> cd_imv_out_prcmontante_org | B58: Pilar III | C58: Bens Imóveis - Output | D58: 2. Campo | E58: cd_imv_out_prc | F58: montante_org | G58: =INDEX(Auxiliar!$B$16:$B$24,MATCH(Plano_V1!H58,Auxiliar!$C$16:$C$24,0),1) -> #N/A | H58: =VLOOKUP(A58,'Aux - pivots1'!$A:$B,2,0) -> #N/A | I58: 0 | J58: =I58/8 -> 0 | K58: cd_imv_out_trz_cred_prc | L58: =J58-SUM(M58:FK58) -> 0
A59: =E59&F59 -> cd_imv_out_prcorigem | B59: Pilar III | C59: Bens Imóveis - Output | D59: 2. Campo | E59: cd_imv_out_prc | F59: origem | G59: =INDEX(Auxiliar!$B$16:$B$24,MATCH(Plano_V1!H59,Auxiliar!$C$16:$C$24,0),1) -> #N/A | H59: =VLOOKUP(A59,'Aux - pivots1'!$A:$B,2,0) -> #N/A | I59: =SUMIFS(Table1[Estimação (horas)],Table1[Tabela],Plano_V1!E59,Table1[Campo],Plano_V1!F59) -> 0 | J59: =I59/8 -> 0 | K59: cd_imv_out_trz_cred_prc | L59: =J59-SUM(M59:FK59) -> 0
A60: =E60&F60 -> cd_imv_out_prcref_date | B60: Pilar III | C60: Bens Imóveis - Output | D60: 2. Campo | E60: cd_imv_out_prc | F60: ref_date | G60: =INDEX(Auxiliar!$B$16:$B$24,MATCH(Plano_V1!H60,Auxiliar!$C$16:$C$24,0),1) -> #N/A | H60: =VLOOKUP(A60,'Aux - pivots1'!$A:$B,2,0) -> #N/A | I60: =SUMIFS(Table1[Estimação (horas)],Table1[Tabela],Plano_V1!E60,Table1[Campo],Plano_V1!F60) -> 0 | J60: =I60/8 -> 0 | K60: cd_imv_out_trz_cred_prc | L60: =J60-SUM(M60:FK60) -> 0
A61: =E61&F61 -> cd_imv_out_trz_cred_prcn.a. | B61: Pilar III | C61: Bens Imóveis - Output | D61: 1. Universo | E61: cd_imv_out_trz_cred_prc | F61: n.a. | G61: =INDEX(Auxiliar!$B$16:$B$24,MATCH(Plano_V1!H61,Auxiliar!$C$16:$C$24,0),1) -> #N/A | H61: =VLOOKUP(A61,'Aux - pivots1'!$A:$B,2,0) -> #N/A | I61: =SUMIFS(Table1[Estimação (horas)],Table1[Tabela],Plano_V1!E61,Table1[Campo],Plano_V1!F61) -> 0 | J61: =I61/8 -> 0 | K61: sem pendencia | L61: =J61-SUM(M61:FK61) -> 0
A62: =E62&F62 -> cd_imv_out_trz_cred_prccempresa | B62: Pilar III | C62: Bens Imóveis - Output | D62: 2. Campo | E62: cd_imv_out_trz_cred_prc | F62: cempresa | G62: =INDEX(Auxiliar!$B$16:$B$24,MATCH(Plano_V1!H62,Auxiliar!$C$16:$C$24,0),1) -> #N/A | H62: =VLOOKUP(A62,'Aux - pivots1'!$A:$B,2,0) -> #N/A | I62: =SUMIFS(Table1[Estimação (horas)],Table1[Tabela],Plano_V1!E62,Table1[Campo],Plano_V1!F62) -> 0 | J62: =I62/8 -> 0 | K62: sem pendencia | L62: =J62-SUM(M62:FK62) -> 0
A63: =E63&F63 -> cd_imv_out_trz_cred_prccempresp | B63: Pilar III | C63: Bens Imóveis - Output | D63: 2. Campo | E63: cd_imv_out_trz_cred_prc | F63: cempresp | G63: =INDEX(Auxiliar!$B$16:$B$24,MATCH(Plano_V1!H63,Auxiliar!$C$16:$C$24,0),1) -> #N/A | H63: =VLOOKUP(A63,'Aux - pivots1'!$A:$B,2,0) -> #N/A | I63: =SUMIFS(Table1[Estimação (horas)],Table1[Tabela],Plano_V1!E63,Table1[Campo],Plano_V1!F63) -> 0 | J63: =I63/8 -> 0 | K63: sem pendencia | L63: =J63-SUM(M63:FK63) -> 0
A64: =E64&F64 -> cd_imv_out_trz_cred_prcckbalcao | B64: Pilar III | C64: Bens Imóveis - Output | D64: 2. Campo | E64: cd_imv_out_trz_cred_prc | F64: ckbalcao | G64: =INDEX(Auxiliar!$B$16:$B$24,MATCH(Plano_V1!H64,Auxiliar!$C$16:$C$24,0),1) -> #N/A | H64: =VLOOKUP(A64,'Aux - pivots1'!$A:$B,2,0) -> #N/A | I64: =SUMIFS(Table1[Estimação (horas)],Table1[Tabela],Plano_V1!E64,Table1[Campo],Plano_V1!F64) -> 0 | J64: =I64/8 -> 0 | K64: sem pendencia | L64: =J64-SUM(M64:FK64) -> 0
A65: =E65&F65 -> cd_imv_out_trz_cred_prcckbalres | B65: Pilar III | C65: Bens Imóveis - Output | D65: 2. Campo | E65: cd_imv_out_trz_cred_prc | F65: ckbalres | G65: =INDEX(Auxiliar!$B$16:$B$24,MATCH(Plano_V1!H65,Auxiliar!$C$16:$C$24,0),1) -> #N/A | H65: =VLOOKUP(A65,'Aux - pivots1'!$A:$B,2,0) -> #N/A | I65: =SUMIFS(Table1[Estimação (horas)],Table1[Tabela],Plano_V1!E65,Table1[Campo],Plano_V1!F65) -> 0 | J65: =I65/8 -> 0 | K65: sem pendencia | L65: =J65-SUM(M65:FK65) -> 0
A66: =E66&F66 -> cd_imv_out_trz_cred_prcckctares | B66: Pilar III | C66: Bens Imóveis - Output | D66: 2. Campo | E66: cd_imv_out_trz_cred_prc | F66: ckctares | G66: =INDEX(Auxiliar!$B$16:$B$24,MATCH(Plano_V1!H66,Auxiliar!$C$16:$C$24,0),1) -> #N/A | H66: =VLOOKUP(A66,'Aux - pivots1'!$A:$B,2,0) -> #N/A | I66: =SUMIFS(Table1[Estimação (horas)],Table1[Tabela],Plano_V1!E66,Table1[Campo],Plano_V1!F66) -> 0 | J66: =I66/8 -> 0 | K66: sem pendencia | L66: =J66-SUM(M66:FK66) -> 0
A67: =E67&F67 -> cd_imv_out_trz_cred_prccknumcta | B67: Pilar III | C67: Bens Imóveis - Output | D67: 2. Campo | E67: cd_imv_out_trz_cred_prc | F67: cknumcta | G67: =INDEX(Auxiliar!$B$16:$B$24,MATCH(Plano_V1!H67,Auxiliar!$C$16:$C$24,0),1) -> #N/A | H67: =VLOOKUP(A67,'Aux - pivots1'!$A:$B,2,0) -> #N/A | I67: =SUMIFS(Table1[Estimação (horas)],Table1[Tabela],Plano_V1!E67,Table1[Campo],Plano_V1!F67) -> 0 | J67: =I67/8 -> 0 | K67: sem pendencia | L67: =J67-SUM(M67:FK67) -> 0
A68: =E68&F68 -> cd_imv_out_trz_cred_prcckrefresp | B68: Pilar III | C68: Bens Imóveis - Output | D68: 2. Campo | E68: cd_imv_out_trz_cred_prc | F68: ckrefresp | G68: =INDEX(Auxiliar!$B$16:$B$24,MATCH(Plano_V1!H68,Auxiliar!$C$16:$C$24,0),1) -> #N/A | H68: =VLOOKUP(A68,'Aux - pivots1'!$A:$B,2,0) -> #N/A | I68: =SUMIFS(Table1[Estimação (horas)],Table1[Tabela],Plano_V1!E68,Table1[Campo],Plano_V1!F68) -> 0 | J68: =I68/8 -> 0 | K68: sem pendencia | L68: =J68-SUM(M68:FK68) -> 0
A69: =E69&F69 -> cd_imv_out_trz_cred_prccod_fnld | B69: Pilar III | C69: Bens Imóveis - Output | D69: 2. Campo | E69: cd_imv_out_trz_cred_prc | F69: cod_fnld | G69: =INDEX(Auxiliar!$B$16:$B$24,MATCH(Plano_V1!H69,Auxiliar!$C$16:$C$24,0),1) -> #N/A | H69: =VLOOKUP(A69,'Aux - pivots1'!$A:$B,2,0) -> #N/A | I69: =SUMIFS(Table1[Estimação (horas)],Table1[Tabela],Plano_V1!E69,Table1[Campo],Plano_V1!F69) -> 0 | J69: =I69/8 -> 0 | K69: sem pendencia | L69: =J69-SUM(M69:FK69) -> 0
A70: =E70&F70 -> cd_imv_out_trz_cred_prccod_ocupacao | B70: Pilar III | C70: Bens Imóveis - Output | D70: 2. Campo | E70: cd_imv_out_trz_cred_prc | F70: cod_ocupacao | G70: =INDEX(Auxiliar!$B$16:$B$24,MATCH(Plano_V1!H70,Auxiliar!$C$16:$C$24,0),1) -> #N/A | H70: =VLOOKUP(A70,'Aux - pivots1'!$A:$B,2,0) -> #N/A | I70: =SUMIFS(Table1[Estimação (horas)],Table1[Tabela],Plano_V1!E70,Table1[Campo],Plano_V1!F70) -> 0 | J70: =I70/8 -> 0 | K70: sem pendencia | L70: =J70-SUM(M70:FK70) -> 0
A71: =E71&F71 -> cd_imv_out_trz_cred_prccod_prd_resp | B71: Pilar III | C71: Bens Imóveis - Output | D71: 2. Campo | E71: cd_imv_out_trz_cred_prc | F71: cod_prd_resp | G71: =INDEX(Auxiliar!$B$16:$B$24,MATCH(Plano_V1!H71,Auxiliar!$C$16:$C$24,0),1) -> #N/A | H71: =VLOOKUP(A71,'Aux - pivots1'!$A:$B,2,0) -> #N/A | I71: =SUMIFS(Table1[Estimação (horas)],Table1[Tabela],Plano_V1!E71,Table1[Campo],Plano_V1!F71) -> 0 | J71: =I71/8 -> 0 | K71: sem pendencia | L71: =J71-SUM(M71:FK71) -> 0
A72: =E72&F72 -> cd_imv_out_trz_cred_prccod_sit | B72: Pilar III | C72: Bens Imóveis - Output | D72: 2. Campo | E72: cd_imv_out_trz_cred_prc | F72: cod_sit | G72: =INDEX(Auxiliar!$B$16:$B$24,MATCH(Plano_V1!H72,Auxiliar!$C$16:$C$24,0),1) -> #N/A | H72: =VLOOKUP(A72,'Aux - pivots1'!$A:$B,2,0) -> #N/A | I72: 0 | J72: =I72/8 -> 0 | K72: sem pendencia | L72: =J72-SUM(M72:FK72) -> 0
A73: =E73&F73 -> cd_imv_out_trz_cred_prccod_sprd_resp | B73: Pilar III | C73: Bens Imóveis - Output | D73: 2. Campo | E73: cd_imv_out_trz_cred_prc | F73: cod_sprd_resp | G73: =INDEX(Auxiliar!$B$16:$B$24,MATCH(Plano_V1!H73,Auxiliar!$C$16:$C$24,0),1) -> #N/A | H73: =VLOOKUP(A73,'Aux - pivots1'!$A:$B,2,0) -> #N/A | I73: =SUMIFS(Table1[Estimação (horas)],Table1[Tabela],Plano_V1!E73,Table1[Campo],Plano_V1!F73) -> 0 | J73: =I73/8 -> 0 | K73: sem pendencia | L73: =J73-SUM(M73:FK73) -> 0
A74: =E74&F74 -> cd_imv_out_trz_cred_prccomp_id_gar | B74: Pilar III | C74: Bens Imóveis - Output | D74: 2. Campo | E74: cd_imv_out_trz_cred_prc | F74: comp_id_gar | G74: =INDEX(Auxiliar!$B$16:$B$24,MATCH(Plano_V1!H74,Auxiliar!$C$16:$C$24,0),1) -> #N/A | H74: =VLOOKUP(A74,'Aux - pivots1'!$A:$B,2,0) -> #N/A | I74: =SUMIFS(Table1[Estimação (horas)],Table1[Tabela],Plano_V1!E74,Table1[Campo],Plano_V1!F74) -> 0 | J74: =I74/8 -> 0 | K74: sem pendencia | L74: =J74-SUM(M74:FK74) -> 0
A75: =E75&F75 -> cd_imv_out_trz_cred_prcdata_fim | B75: Pilar III | C75: Bens Imóveis - Output | D75: 2. Campo | E75: cd_imv_out_trz_cred_prc | F75: data_fim | G75: =INDEX(Auxiliar!$B$16:$B$24,MATCH(Plano_V1!H75,Auxiliar!$C$16:$C$24,0),1) -> #N/A | H75: =VLOOKUP(A75,'Aux - pivots1'!$A:$B,2,0) -> #N/A | I75: =SUMIFS(Table1[Estimação (horas)],Table1[Tabela],Plano_V1!E75,Table1[Campo],Plano_V1!F75) -> 0 | J75: =I75/8 -> 0 | K75: sem pendencia | L75: =J75-SUM(M75:FK75) -> 0
A76: =E76&F76 -> cd_imv_out_trz_cred_prcdata_inicio | B76: Pilar III | C76: Bens Imóveis - Output | D76: 2. Campo | E76: cd_imv_out_trz_cred_prc | F76: data_inicio | G76: =INDEX(Auxiliar!$B$16:$B$24,MATCH(Plano_V1!H76,Auxiliar!$C$16:$C$24,0),1) -> #N/A | H76: =VLOOKUP(A76,'Aux - pivots1'!$A:$B,2,0) -> #N/A | I76: =SUMIFS(Table1[Estimação (horas)],Table1[Tabela],Plano_V1!E76,Table1[Campo],Plano_V1!F76) -> 0 | J76: =I76/8 -> 0 | K76: sem pendencia | L76: =J76-SUM(M76:FK76) -> 0
A77: =E77&F77 -> cd_imv_out_trz_cred_prcdata_vcmt | B77: Pilar III | C77: Bens Imóveis - Output | D77: 2. Campo | E77: cd_imv_out_trz_cred_prc | F77: data_vcmt | G77: =INDEX(Auxiliar!$B$16:$B$24,MATCH(Plano_V1!H77,Auxiliar!$C$16:$C$24,0),1) -> #N/A | H77: =VLOOKUP(A77,'Aux - pivots1'!$A:$B,2,0) -> #N/A | I77: =SUMIFS(Table1[Estimação (horas)],Table1[Tabela],Plano_V1!E77,Table1[Campo],Plano_V1!F77) -> 0 | J77: =I77/8 -> 0 | K77: sem pendencia | L77: =J77-SUM(M77:FK77) -> 0
A78: =E78&F78 -> cd_imv_out_trz_cred_prcidetgar | B78: Pilar III | C78: Bens Imóveis - Output | D78: 2. Campo | E78: cd_imv_out_trz_cred_prc | F78: idetgar | G78: =INDEX(Auxiliar!$B$16:$B$24,MATCH(Plano_V1!H78,Auxiliar!$C$16:$C$24,0),1) -> #N/A | H78: =VLOOKUP(A78,'Aux - pivots1'!$A:$B,2,0) -> #N/A | I78: 0 | J78: =I78/8 -> 0 | K78: sem pendencia | L78: =J78-SUM(M78:FK78) -> 0
A79: =E79&F79 -> cd_imv_out_trz_cred_prcnum_prop | B79: Pilar III | C79: Bens Imóveis - Output | D79: 2. Campo | E79: cd_imv_out_trz_cred_prc | F79: num_prop | G79: =INDEX(Auxiliar!$B$16:$B$24,MATCH(Plano_V1!H79,Auxiliar!$C$16:$C$24,0),1) -> #N/A | H79: =VLOOKUP(A79,'Aux - pivots1'!$A:$B,2,0) -> #N/A | I79: 0 | J79: =I79/8 -> 0 | K79: sem pendencia | L79: =J79-SUM(M79:FK79) -> 0
A80: =E80&F80 -> cd_imv_out_trz_cred_prcorigem | B80: Pilar III | C80: Bens Imóveis - Output | D80: 2. Campo | E80: cd_imv_out_trz_cred_prc | F80: origem | G80: =INDEX(Auxiliar!$B$16:$B$24,MATCH(Plano_V1!H80,Auxiliar!$C$16:$C$24,0),1) -> #N/A | H80: =VLOOKUP(A80,'Aux - pivots1'!$A:$B,2,0) -> #N/A | I80: =SUMIFS(Table1[Estimação (horas)],Table1[Tabela],Plano_V1!E80,Table1[Campo],Plano_V1!F80) -> 0 | J80: =I80/8 -> 0 | K80: sem pendencia | L80: =J80-SUM(M80:FK80) -> 0
A81: =E81&F81 -> cd_imv_out_trz_cred_prcref_date | B81: Pilar III | C81: Bens Imóveis - Output | D81: 2. Campo | E81: cd_imv_out_trz_cred_prc | F81: ref_date | G81: =INDEX(Auxiliar!$B$16:$B$24,MATCH(Plano_V1!H81,Auxiliar!$C$16:$C$24,0),1) -> #N/A | H81: =VLOOKUP(A81,'Aux - pivots1'!$A:$B,2,0) -> #N/A | I81: =SUMIFS(Table1[Estimação (horas)],Table1[Tabela],Plano_V1!E81,Table1[Campo],Plano_V1!F81) -> 0 | J81: =I81/8 -> 0 | K81: sem pendencia | L81: =J81-SUM(M81:FK81) -> 0
A82: =E82&F82 -> cd_imv_out_trz_prc_bens_imvn.a. | B82: Pilar III | C82: Bens Imóveis - Output | D82: 1. Universo | E82: cd_imv_out_trz_prc_bens_imv | F82: n.a. | G82: =INDEX(Auxiliar!$B$16:$B$24,MATCH(Plano_V1!H82,Auxiliar!$C$16:$C$24,0),1) -> #N/A | H82: =VLOOKUP(A82,'Aux - pivots1'!$A:$B,2,0) -> #N/A | I82: =SUMIFS(Table1[Estimação (horas)],Table1[Tabela],Plano_V1!E82,Table1[Campo],Plano_V1!F82) -> 0 | J82: =I82/8 -> 0 | K82: cd_imv_out_trz_cred_prc | L82: =J82-SUM(M82:FK82) -> 0
A83: =E83&F83 -> cd_imv_out_trz_prc_bens_imvcempbem | B83: Pilar III | C83: Bens Imóveis - Output | D83: 2. Campo | E83: cd_imv_out_trz_prc_bens_imv | F83: cempbem | G83: =INDEX(Auxiliar!$B$16:$B$24,MATCH(Plano_V1!H83,Auxiliar!$C$16:$C$24,0),1) -> #N/A | H83: =VLOOKUP(A83,'Aux - pivots1'!$A:$B,2,0) -> #N/A | I83: =SUMIFS(Table1[Estimação (horas)],Table1[Tabela],Plano_V1!E83,Table1[Campo],Plano_V1!F83) -> 0 | J83: =I83/8 -> 0 | K83: cd_imv_out_trz_cred_prc | L83: =J83-SUM(M83:FK83) -> 0
A84: =E84&F84 -> cd_imv_out_trz_prc_bens_imvcempresa | B84: Pilar III | C84: Bens Imóveis - Output | D84: 2. Campo | E84: cd_imv_out_trz_prc_bens_imv | F84: cempresa | G84: =INDEX(Auxiliar!$B$16:$B$24,MATCH(Plano_V1!H84,Auxiliar!$C$16:$C$24,0),1) -> #N/A | H84: =VLOOKUP(A84,'Aux - pivots1'!$A:$B,2,0) -> #N/A | I84: =SUMIFS(Table1[Estimação (horas)],Table1[Tabela],Plano_V1!E84,Table1[Campo],Plano_V1!F84) -> 0 | J84: =I84/8 -> 0 | K84: cd_imv_out_trz_cred_prc | L84: =J84-SUM(M84:FK84) -> 0
A85: =E85&F85 -> cd_imv_out_trz_prc_bens_imvckbalbem | B85: Pilar III | C85: Bens Imóveis - Output | D85: 2. Campo | E85: cd_imv_out_trz_prc_bens_imv | F85: ckbalbem | G85: =INDEX(Auxiliar!$B$16:$B$24,MATCH(Plano_V1!H85,Auxiliar!$C$16:$C$24,0),1) -> #N/A | H85: =VLOOKUP(A85,'Aux - pivots1'!$A:$B,2,0) -> #N/A | I85: =SUMIFS(Table1[Estimação (horas)],Table1[Tabela],Plano_V1!E85,Table1[Campo],Plano_V1!F85) -> 0 | J85: =I85/8 -> 0 | K85: cd_imv_out_trz_cred_prc | L85: =J85-SUM(M85:FK85) -> 0
A86: =E86&F86 -> cd_imv_out_trz_prc_bens_imvckbalcao | B86: Pilar III | C86: Bens Imóveis - Output | D86: 2. Campo | E86: cd_imv_out_trz_prc_bens_imv | F86: ckbalcao | G86: =INDEX(Auxiliar!$B$16:$B$24,MATCH(Plano_V1!H86,Auxiliar!$C$16:$C$24,0),1) -> #N/A | H86: =VLOOKUP(A86,'Aux - pivots1'!$A:$B,2,0) -> #N/A | I86: =SUMIFS(Table1[Estimação (horas)],Table1[Tabela],Plano_V1!E86,Table1[Campo],Plano_V1!F86) -> 0 | J86: =I86/8 -> 0 | K86: cd_imv_out_trz_cred_prc | L86: =J86-SUM(M86:FK86) -> 0
A87: =E87&F87 -> cd_imv_out_trz_prc_bens_imvckctabem | B87: Pilar III | C87: Bens Imóveis - Output | D87: 2. Campo | E87: cd_imv_out_trz_prc_bens_imv | F87: ckctabem | G87: =INDEX(Auxiliar!$B$16:$B$24,MATCH(Plano_V1!H87,Auxiliar!$C$16:$C$24,0),1) -> #N/A | H87: =VLOOKUP(A87,'Aux - pivots1'!$A:$B,2,0) -> #N/A | I87: =SUMIFS(Table1[Estimação (horas)],Table1[Tabela],Plano_V1!E87,Table1[Campo],Plano_V1!F87) -> 0 | J87: =I87/8 -> 0 | K87: cd_imv_out_trz_cred_prc | L87: =J87-SUM(M87:FK87) -> 0
A88: =E88&F88 -> cd_imv_out_trz_prc_bens_imvcknumcta | B88: Pilar III | C88: Bens Imóveis - Output | D88: 2. Campo | E88: cd_imv_out_trz_prc_bens_imv | F88: cknumcta | G88: =INDEX(Auxiliar!$B$16:$B$24,MATCH(Plano_V1!H88,Auxiliar!$C$16:$C$24,0),1) -> #N/A | H88: =VLOOKUP(A88,'Aux - pivots1'!$A:$B,2,0) -> #N/A | I88: =SUMIFS(Table1[Estimação (horas)],Table1[Tabela],Plano_V1!E88,Table1[Campo],Plano_V1!F88) -> 0 | J88: =I88/8 -> 0 | K88: cd_imv_out_trz_cred_prc | L88: =J88-SUM(M88:FK88) -> 0
A89: =E89&F89 -> cd_imv_out_trz_prc_bens_imvckrefbem | B89: Pilar III | C89: Bens Imóveis - Output | D89: 2. Campo | E89: cd_imv_out_trz_prc_bens_imv | F89: ckrefbem | G89: =INDEX(Auxiliar!$B$16:$B$24,MATCH(Plano_V1!H89,Auxiliar!$C$16:$C$24,0),1) -> #N/A | H89: =VLOOKUP(A89,'Aux - pivots1'!$A:$B,2,0) -> #N/A | I89: =SUMIFS(Table1[Estimação (horas)],Table1[Tabela],Plano_V1!E89,Table1[Campo],Plano_V1!F89) -> 0 | J89: =I89/8 -> 0 | K89: cd_imv_out_trz_cred_prc | L89: =J89-SUM(M89:FK89) -> 0
A90: =E90&F90 -> cd_imv_out_trz_prc_bens_imvcomp_id_gar | B90: Pilar III | C90: Bens Imóveis - Output | D90: 2. Campo | E90: cd_imv_out_trz_prc_bens_imv | F90: comp_id_gar | G90: =INDEX(Auxiliar!$B$16:$B$24,MATCH(Plano_V1!H90,Auxiliar!$C$16:$C$24,0),1) -> #N/A | H90: =VLOOKUP(A90,'Aux - pivots1'!$A:$B,2,0) -> #N/A | I90: =SUMIFS(Table1[Estimação (horas)],Table1[Tabela],Plano_V1!E90,Table1[Campo],Plano_V1!F90) -> 0 | J90: =I90/8 -> 0 | K90: cd_imv_out_trz_cred_prc | L90: =J90-SUM(M90:FK90) -> 0
A91: =E91&F91 -> cd_imv_out_trz_prc_bens_imvdata_assc | B91: Pilar III | C91: Bens Imóveis - Output | D91: 2. Campo | E91: cd_imv_out_trz_prc_bens_imv | F91: data_assc | G91: =INDEX(Auxiliar!$B$16:$B$24,MATCH(Plano_V1!H91,Auxiliar!$C$16:$C$24,0),1) -> #N/A | H91: =VLOOKUP(A91,'Aux - pivots1'!$A:$B,2,0) -> #N/A | I91: 0 | J91: =I91/8 -> 0 | K91: cd_imv_out_trz_cred_prc | L91: =J91-SUM(M91:FK91) -> 0
A92: =E92&F92 -> cd_imv_out_trz_prc_bens_imvflg_adj | B92: Pilar III | C92: Bens Imóveis - Output | D92: 2. Campo | E92: cd_imv_out_trz_prc_bens_imv | F92: flg_adj | G92: =INDEX(Auxiliar!$B$16:$B$24,MATCH(Plano_V1!H92,Auxiliar!$C$16:$C$24,0),1) -> #N/A | H92: =VLOOKUP(A92,'Aux - pivots1'!$A:$B,2,0) -> #N/A | I92: =SUMIFS(Table1[Estimação (horas)],Table1[Tabela],Plano_V1!E92,Table1[Campo],Plano_V1!F92) -> 0 | J92: =I92/8 -> 0 | K92: cd_imv_out_trz_cred_prc | L92: =J92-SUM(M92:FK92) -> 0
A93: =E93&F93 -> cd_imv_out_trz_prc_bens_imvflg_col | B93: Pilar III | C93: Bens Imóveis - Output | D93: 2. Campo | E93: cd_imv_out_trz_prc_bens_imv | F93: flg_col | G93: =INDEX(Auxiliar!$B$16:$B$24,MATCH(Plano_V1!H93,Auxiliar!$C$16:$C$24,0),1) -> #N/A | H93: =VLOOKUP(A93,'Aux - pivots1'!$A:$B,2,0) -> #N/A | I93: =SUMIFS(Table1[Estimação (horas)],Table1[Tabela],Plano_V1!E93,Table1[Campo],Plano_V1!F93) -> 0 | J93: =I93/8 -> 0 | K93: cd_imv_out_trz_cred_prc | L93: =J93-SUM(M93:FK93) -> 0
A94: =E94&F94 -> cd_imv_out_trz_prc_bens_imvflg_fin | B94: Pilar III | C94: Bens Imóveis - Output | D94: 2. Campo | E94: cd_imv_out_trz_prc_bens_imv | F94: flg_fin | G94: =INDEX(Auxiliar!$B$16:$B$24,MATCH(Plano_V1!H94,Auxiliar!$C$16:$C$24,0),1) -> #N/A | H94: =VLOOKUP(A94,'Aux - pivots1'!$A:$B,2,0) -> #N/A | I94: =SUMIFS(Table1[Estimação (horas)],Table1[Tabela],Plano_V1!E94,Table1[Campo],Plano_V1!F94) -> 0 | J94: =I94/8 -> 0 | K94: cd_imv_out_trz_cred_prc | L94: =J94-SUM(M94:FK94) -> 0
A95: =E95&F95 -> cd_imv_out_trz_prc_bens_imvflg_pro | B95: Pilar III | C95: Bens Imóveis - Output | D95: 2. Campo | E95: cd_imv_out_trz_prc_bens_imv | F95: flg_pro | G95: =INDEX(Auxiliar!$B$16:$B$24,MATCH(Plano_V1!H95,Auxiliar!$C$16:$C$24,0),1) -> #N/A | H95: =VLOOKUP(A95,'Aux - pivots1'!$A:$B,2,0) -> #N/A | I95: =SUMIFS(Table1[Estimação (horas)],Table1[Tabela],Plano_V1!E95,Table1[Campo],Plano_V1!F95) -> 0 | J95: =I95/8 -> 0 | K95: cd_imv_out_trz_cred_prc | L95: =J95-SUM(M95:FK95) -> 0
A96: =E96&F96 -> cd_imv_out_trz_prc_bens_imvorigem | B96: Pilar III | C96: Bens Imóveis - Output | D96: 2. Campo | E96: cd_imv_out_trz_prc_bens_imv | F96: origem | G96: =INDEX(Auxiliar!$B$16:$B$24,MATCH(Plano_V1!H96,Auxiliar!$C$16:$C$24,0),1) -> #N/A | H96: =VLOOKUP(A96,'Aux - pivots1'!$A:$B,2,0) -> #N/A | I96: =SUMIFS(Table1[Estimação (horas)],Table1[Tabela],Plano_V1!E96,Table1[Campo],Plano_V1!F96) -> 0 | J96: =I96/8 -> 0 | K96: cd_imv_out_trz_cred_prc | L96: =J96-SUM(M96:FK96) -> 0
A97: =E97&F97 -> cd_imv_out_trz_prc_bens_imvref_date | B97: Pilar III | C97: Bens Imóveis - Output | D97: 2. Campo | E97: cd_imv_out_trz_prc_bens_imv | F97: ref_date | G97: =INDEX(Auxiliar!$B$16:$B$24,MATCH(Plano_V1!H97,Auxiliar!$C$16:$C$24,0),1) -> #N/A | H97: =VLOOKUP(A97,'Aux - pivots1'!$A:$B,2,0) -> #N/A | I97: =SUMIFS(Table1[Estimação (horas)],Table1[Tabela],Plano_V1!E97,Table1[Campo],Plano_V1!F97) -> 0 | J97: =I97/8 -> 0 | K97: cd_imv_out_trz_cred_prc | L97: =J97-SUM(M97:FK97) -> 0
A98: =E98&F98 -> cd_imv_out_bensn.a. | B98: Pilar III | C98: Bens Imóveis - Output | D98: 1. Universo | E98: cd_imv_out_bens | F98: n.a. | G98: =INDEX(Auxiliar!$B$16:$B$24,MATCH(Plano_V1!H98,Auxiliar!$C$16:$C$24,0),1) -> #N/A | H98: =VLOOKUP(A98,'Aux - pivots1'!$A:$B,2,0) -> #N/A | I98: =SUMIFS(Table1[Estimação (horas)],Table1[Tabela],Plano_V1!E98,Table1[Campo],Plano_V1!F98) -> 0 | J98: =I98/8 -> 0 | K98: cd_imv_out_trz_prc_bens_imv ; cd_imv_out_prc ; cd_imv_out_trz_cred_prc | L98: =J98-SUM(M98:FK98) -> 0
A99: =E99&F99 -> cd_imv_out_bensano_construcao | B99: Pilar III | C99: Bens Imóveis - Output | D99: 2. Campo | E99: cd_imv_out_bens | F99: ano_construcao | G99: =INDEX(Auxiliar!$B$16:$B$24,MATCH(Plano_V1!H99,Auxiliar!$C$16:$C$24,0),1) -> #N/A | H99: =VLOOKUP(A99,'Aux - pivots1'!$A:$B,2,0) -> #N/A | I99: 0 | J99: =I99/8 -> 0 | K99: cd_imv_out_trz_prc_bens_imv ; cd_imv_out_prc ; cd_imv_out_trz_cred_prc | L99: =J99-SUM(M99:FK99) -> 0
A100: =E100&F100 -> cd_imv_out_bensarea_util | B100: Pilar III | C100: Bens Imóveis - Output | D100: 2. Campo | E100: cd_imv_out_bens | F100: area_util | G100: =INDEX(Auxiliar!$B$16:$B$24,MATCH(Plano_V1!H100,Auxiliar!$C$16:$C$24,0),1) -> #N/A | H100: =VLOOKUP(A100,'Aux - pivots1'!$A:$B,2,0) -> #N/A | I100: =SUMIFS(Table1[Estimação (horas)],Table1[Tabela],Plano_V1!E100,Table1[Campo],Plano_V1!F100) -> 0 | J100: =I100/8 -> 0 | K100: cd_imv_out_trz_prc_bens_imv ; cd_imv_out_prc ; cd_imv_out_trz_cred_prc | L100: =J100-SUM(M100:FK100) -> 0
A101: =E101&F101 -> cd_imv_out_benscempbem | B101: Pilar III | C101: Bens Imóveis - Output | D101: 2. Campo | E101: cd_imv_out_bens | F101: cempbem | G101: =INDEX(Auxiliar!$B$16:$B$24,MATCH(Plano_V1!H101,Auxiliar!$C$16:$C$24,0),1) -> #N/A | H101: =VLOOKUP(A101,'Aux - pivots1'!$A:$B,2,0) -> #N/A | I101: =SUMIFS(Table1[Estimação (horas)],Table1[Tabela],Plano_V1!E101,Table1[Campo],Plano_V1!F101) -> 0 | J101: =I101/8 -> 0 | K101: cd_imv_out_trz_prc_bens_imv ; cd_imv_out_prc ; cd_imv_out_trz_cred_prc | L101: =J101-SUM(M101:FK101) -> 0
A102: =E102&F102 -> cd_imv_out_bensckbalbem | B102: Pilar III | C102: Bens Imóveis - Output | D102: 2. Campo | E102: cd_imv_out_bens | F102: ckbalbem | G102: =INDEX(Auxiliar!$B$16:$B$24,MATCH(Plano_V1!H102,Auxiliar!$C$16:$C$24,0),1) -> #N/A | H102: =VLOOKUP(A102,'Aux - pivots1'!$A:$B,2,0) -> #N/A | I102: =SUMIFS(Table1[Estimação (horas)],Table1[Tabela],Plano_V1!E102,Table1[Campo],Plano_V1!F102) -> 0 | J102: =I102/8 -> 0 | K102: cd_imv_out_trz_prc_bens_imv ; cd_imv_out_prc ; cd_imv_out_trz_cred_prc | L102: =J102-SUM(M102:FK102) -> 0
A103: =E103&F103 -> cd_imv_out_bensckctabem | B103: Pilar III | C103: Bens Imóveis - Output | D103: 2. Campo | E103: cd_imv_out_bens | F103: ckctabem | G103: =INDEX(Auxiliar!$B$16:$B$24,MATCH(Plano_V1!H103,Auxiliar!$C$16:$C$24,0),1) -> #N/A | H103: =VLOOKUP(A103,'Aux - pivots1'!$A:$B,2,0) -> #N/A | I103: =SUMIFS(Table1[Estimação (horas)],Table1[Tabela],Plano_V1!E103,Table1[Campo],Plano_V1!F103) -> 0 | J103: =I103/8 -> 0 | K103: cd_imv_out_trz_prc_bens_imv ; cd_imv_out_prc ; cd_imv_out_trz_cred_prc | L103: =J103-SUM(M103:FK103) -> 0
A104: =E104&F104 -> cd_imv_out_bensckrefbem | B104: Pilar III | C104: Bens Imóveis - Output | D104: 2. Campo | E104: cd_imv_out_bens | F104: ckrefbem | G104: =INDEX(Auxiliar!$B$16:$B$24,MATCH(Plano_V1!H104,Auxiliar!$C$16:$C$24,0),1) -> #N/A | H104: =VLOOKUP(A104,'Aux - pivots1'!$A:$B,2,0) -> #N/A | I104: =SUMIFS(Table1[Estimação (horas)],Table1[Tabela],Plano_V1!E104,Table1[Campo],Plano_V1!F104) -> 0 | J104: =I104/8 -> 0 | K104: cd_imv_out_trz_prc_bens_imv ; cd_imv_out_prc ; cd_imv_out_trz_cred_prc | L104: =J104-SUM(M104:FK104) -> 0
A105: =E105&F105 -> cd_imv_out_benscod_art_matr | B105: Pilar III | C105: Bens Imóveis - Output | D105: 2. Campo | E105: cd_imv_out_bens | F105: cod_art_matr | G105: =INDEX(Auxiliar!$B$16:$B$24,MATCH(Plano_V1!H105,Auxiliar!$C$16:$C$24,0),1) -> #N/A | H105: =VLOOKUP(A105,'Aux - pivots1'!$A:$B,2,0) -> #N/A | I105: =SUMIFS(Table1[Estimação (horas)],Table1[Tabela],Plano_V1!E105,Table1[Campo],Plano_V1!F105) -> 0 | J105: =I105/8 -> 0 | K105: cd_imv_out_trz_prc_bens_imv ; cd_imv_out_prc ; cd_imv_out_trz_cred_prc | L105: =J105-SUM(M105:FK105) -> 0
A106: =E106&F106 -> cd_imv_out_benscod_avl | B106: Pilar III | C106: Bens Imóveis - Output | D106: 2. Campo | E106: cd_imv_out_bens | F106: cod_avl | G106: =INDEX(Auxiliar!$B$16:$B$24,MATCH(Plano_V1!H106,Auxiliar!$C$16:$C$24,0),1) -> #N/A | H106: =VLOOKUP(A106,'Aux - pivots1'!$A:$B,2,0) -> #N/A | I106: =SUMIFS(Table1[Estimação (horas)],Table1[Tabela],Plano_V1!E106,Table1[Campo],Plano_V1!F106) -> 0 | J106: =I106/8 -> 0 | K106: cd_imv_out_trz_prc_bens_imv ; cd_imv_out_prc ; cd_imv_out_trz_cred_prc | L106: =J106-SUM(M106:FK106) -> 0
A107: =E107&F107 -> cd_imv_out_benscod_bem | B107: Pilar III | C107: Bens Imóveis - Output | D107: 2. Campo | E107: cd_imv_out_bens | F107: cod_bem | G107: =INDEX(Auxiliar!$B$16:$B$24,MATCH(Plano_V1!H107,Auxiliar!$C$16:$C$24,0),1) -> #N/A | H107: =VLOOKUP(A107,'Aux - pivots1'!$A:$B,2,0) -> #N/A | I107: 0 | J107: =I107/8 -> 0 | K107: cd_imv_out_trz_prc_bens_imv ; cd_imv_out_prc ; cd_imv_out_trz_cred_prc | L107: =J107-SUM(M107:FK107) -> 0
A108: =E108&F108 -> cd_imv_out_benscod_disconf | B108: Pilar III | C108: Bens Imóveis - Output | D108: 2. Campo | E108: cd_imv_out_bens | F108: cod_disconf | G108: =INDEX(Auxiliar!$B$16:$B$24,MATCH(Plano_V1!H108,Auxiliar!$C$16:$C$24,0),1) -> #N/A | H108: =VLOOKUP(A108,'Aux - pivots1'!$A:$B,2,0) -> #N/A | I108: =SUMIFS(Table1[Estimação (horas)],Table1[Tabela],Plano_V1!E108,Table1[Campo],Plano_V1!F108) -> 0 | J108: =I108/8 -> 0 | K108: cd_imv_out_trz_prc_bens_imv ; cd_imv_out_prc ; cd_imv_out_trz_cred_prc | L108: =J108-SUM(M108:FK108) -> 0
A109: =E109&F109 -> cd_imv_out_benscod_fin_bem | B109: Pilar III | C109: Bens Imóveis - Output | D109: 2. Campo | E109: cd_imv_out_bens | F109: cod_fin_bem | G109: =INDEX(Auxiliar!$B$16:$B$24,MATCH(Plano_V1!H109,Auxiliar!$C$16:$C$24,0),1) -> #N/A | H109: =VLOOKUP(A109,'Aux - pivots1'!$A:$B,2,0) -> #N/A | I109: =SUMIFS(Table1[Estimação (horas)],Table1[Tabela],Plano_V1!E109,Table1[Campo],Plano_V1!F109) -> 0 | J109: =I109/8 -> 0 | K109: cd_imv_out_trz_prc_bens_imv ; cd_imv_out_prc ; cd_imv_out_trz_cred_prc | L109: =J109-SUM(M109:FK109) -> 0
...

Sheet 1. Status Resumo
B6: Sumário Executivo |31 de outubro a 08 de novembro
B8: 1. Iniciados os testes à tabela de Output de Certificados Energéticos com uma incidência reportada. Aguardamos feedback do João Almeida. 2. Testes aos 8 campos da tabela de Bens Imóveis do Modelo Verde, tendo sido concluídos 2 campos. Adicionalmente, houve a entrega das atualizações das tabelas de Input e de Parametrização do Modelo Verde pela equipa de Tecnologia 3. Foram concluídas as re-especificações dos campos do Pilar III. Adicionalmente, foram entregues 36 campos pela equipa de Tecnologia. Foi concluído um campo.
B22: 1. Modelo de Bens Imóveis | G22: Bens Imóveis - Input | H22: Bens Imóveis - Output
C25: Resumo | G25: Detalhe por Tabela | P25: Status (campos) | T25: 45596 | U25: =T25+8 -> 45604 | V25: ∆ | X25: Highlights
P26: 0. Cancelado | T26: =COUNTIFS('2. Status Detalhe Campos'!$H$7:$H$574,'1. Status Resumo'!$P26,'2. Status Detalhe Campos'!$C$7:$C$574,'1. Status Resumo'!$G$22,'2. Status Detalhe Campos'!$D$7:$D$574,"2. Campo")+COUNTIFS('2. Status Detalhe Campos'!$H$7:$H$574,'1. Status Resumo'!$P26,'2. Status Detalhe Campos'!$C$7:$C$574,'1. Status Resumo'!$H$22,'2. Status Detalhe Campos'!$D$7:$D$574,"2. Campo") -> 10 | U26: =COUNTIFS('2. Status Detalhe Campos'!$G$7:$G$574,'1. Status Resumo'!$P26,'2. Status Detalhe Campos'!$C$7:$C$574,'1. Status Resumo'!$G$22,'2. Status Detalhe Campos'!$D$7:$D$574,"2. Campo")+COUNTIFS('2. Status Detalhe Campos'!$G$7:$G$574,'1. Status Resumo'!$P26,'2. Status Detalhe Campos'!$C$7:$C$574,'1. Status Resumo'!$H$22,'2. Status Detalhe Campos'!$D$7:$D$574,"2. Campo") -> 10 | V26: =U26-T26 -> 0 | X26: 1. Datas de entrega de Tecnologia: - Reprocessamento da tabela de Output de Certificados Energéticos (sem Gloval) -> Entregue a 04/11/2024 - Disponibilização da tabela de output de Certificados Energéticos (com as 4 fontes de informação): TBD - Disponibilização do carregamento de input da Gloval (via front de Upload de Ficheiros): TBD - Disponibilização de funcionalidades de Pedido de informação para a Gloval: TBD
P27: 1. Concluído | T27: =COUNTIFS('2. Status Detalhe Campos'!$H$7:$H$574,'1. Status Resumo'!$P27,'2. Status Detalhe Campos'!$C$7:$C$574,'1. Status Resumo'!$G$22,'2. Status Detalhe Campos'!$D$7:$D$574,"2. Campo")+COUNTIFS('2. Status Detalhe Campos'!$H$7:$H$574,'1. Status Resumo'!$P27,'2. Status Detalhe Campos'!$C$7:$C$574,'1. Status Resumo'!$H$22,'2. Status Detalhe Campos'!$D$7:$D$574,"2. Campo") -> 124 | U27: =COUNTIFS('2. Status Detalhe Campos'!$G$7:$G$574,'1. Status Resumo'!$P27,'2. Status Detalhe Campos'!$C$7:$C$574,'1. Status Resumo'!$G$22,'2. Status Detalhe Campos'!$D$7:$D$574,"2. Campo")+COUNTIFS('2. Status Detalhe Campos'!$G$7:$G$574,'1. Status Resumo'!$P27,'2. Status Detalhe Campos'!$C$7:$C$574,'1. Status Resumo'!$H$22,'2. Status Detalhe Campos'!$D$7:$D$574,"2. Campo") -> 124 | V27: =U27-T27 -> 0
P28: 2.1 Em Teste | T28: =COUNTIFS('2. Status Detalhe Campos'!$H$7:$H$574,'1. Status Resumo'!$P28,'2. Status Detalhe Campos'!$C$7:$C$574,'1. Status Resumo'!$G$22,'2. Status Detalhe Campos'!$D$7:$D$574,"2. Campo")+COUNTIFS('2. Status Detalhe Campos'!$H$7:$H$574,'1. Status Resumo'!$P28,'2. Status Detalhe Campos'!$C$7:$C$574,'1. Status Resumo'!$H$22,'2. Status Detalhe Campos'!$D$7:$D$574,"2. Campo") -> 0 | U28: =COUNTIFS('2. Status Detalhe Campos'!$G$7:$G$574,'1. Status Resumo'!$P28,'2. Status Detalhe Campos'!$C$7:$C$574,'1. Status Resumo'!$G$22,'2. Status Detalhe Campos'!$D$7:$D$574,"2. Campo")+COUNTIFS('2. Status Detalhe Campos'!$G$7:$G$574,'1. Status Resumo'!$P28,'2. Status Detalhe Campos'!$C$7:$C$574,'1. Status Resumo'!$H$22,'2. Status Detalhe Campos'!$D$7:$D$574,"2. Campo") -> 0 | V28: =U28-T28 -> 0
D29: ="# "&U35 -> # 169 | P29: 2.2 Em Re-especificação | T29: =COUNTIFS('2. Status Detalhe Campos'!$H$7:$H$574,'1. Status Resumo'!$P29,'2. Status Detalhe Campos'!$C$7:$C$574,'1. Status Resumo'!$G$22,'2. Status Detalhe Campos'!$D$7:$D$574,"2. Campo")+COUNTIFS('2. Status Detalhe Campos'!$H$7:$H$574,'1. Status Resumo'!$P29,'2. Status Detalhe Campos'!$C$7:$C$574,'1. Status Resumo'!$H$22,'2. Status Detalhe Campos'!$D$7:$D$574,"2. Campo") -> 0 | U29: =COUNTIFS('2. Status Detalhe Campos'!$G$7:$G$574,'1. Status Resumo'!$P29,'2. Status Detalhe Campos'!$C$7:$C$574,'1. Status Resumo'!$G$22,'2. Status Detalhe Campos'!$D$7:$D$574,"2. Campo")+COUNTIFS('2. Status Detalhe Campos'!$G$7:$G$574,'1. Status Resumo'!$P29,'2. Status Detalhe Campos'!$C$7:$C$574,'1. Status Resumo'!$H$22,'2. Status Detalhe Campos'!$D$7:$D$574,"2. Campo") -> 0 | V29: =U29-T29 -> 0
P30: 3. Pendente de outros desenvolvimentos | T30: =COUNTIFS('2. Status Detalhe Campos'!$H$7:$H$574,'1. Status Resumo'!$P30,'2. Status Detalhe Campos'!$C$7:$C$574,'1. Status Resumo'!$G$22,'2. Status Detalhe Campos'!$D$7:$D$574,"2. Campo")+COUNTIFS('2. Status Detalhe Campos'!$H$7:$H$574,'1. Status Resumo'!$P30,'2. Status Detalhe Campos'!$C$7:$C$574,'1. Status Resumo'!$H$22,'2. Status Detalhe Campos'!$D$7:$D$574,"2. Campo") -> 0 | U30: =COUNTIFS('2. Status Detalhe Campos'!$G$7:$G$574,'1. Status Resumo'!$P30,'2. Status Detalhe Campos'!$C$7:$C$574,'1. Status Resumo'!$G$22,'2. Status Detalhe Campos'!$D$7:$D$574,"2. Campo")+COUNTIFS('2. Status Detalhe Campos'!$G$7:$G$574,'1. Status Resumo'!$P30,'2. Status Detalhe Campos'!$C$7:$C$574,'1. Status Resumo'!$H$22,'2. Status Detalhe Campos'!$D$7:$D$574,"2. Campo") -> 0 | V30: =U30-T30 -> 0
P31: 4. Validação EF | T31: =COUNTIFS('2. Status Detalhe Campos'!$H$7:$H$574,'1. Status Resumo'!$P31,'2. Status Detalhe Campos'!$C$7:$C$574,'1. Status Resumo'!$G$22,'2. Status Detalhe Campos'!$D$7:$D$574,"2. Campo")+COUNTIFS('2. Status Detalhe Campos'!$H$7:$H$574,'1. Status Resumo'!$P31,'2. Status Detalhe Campos'!$C$7:$C$574,'1. Status Resumo'!$H$22,'2. Status Detalhe Campos'!$D$7:$D$574,"2. Campo") -> 22 | U31: =COUNTIFS('2. Status Detalhe Campos'!$G$7:$G$574,'1. Status Resumo'!$P31,'2. Status Detalhe Campos'!$C$7:$C$574,'1. Status Resumo'!$G$22,'2. Status Detalhe Campos'!$D$7:$D$574,"2. Campo")+COUNTIFS('2. Status Detalhe Campos'!$G$7:$G$574,'1. Status Resumo'!$P31,'2. Status Detalhe Campos'!$C$7:$C$574,'1. Status Resumo'!$H$22,'2. Status Detalhe Campos'!$D$7:$D$574,"2. Campo") -> 22 | V31: =U31-T31 -> 0
P32: 5. Em Correção | R32: (incidências) | T32: =COUNTIFS('2. Status Detalhe Campos'!$H$7:$H$574,'1. Status Resumo'!$P32,'2. Status Detalhe Campos'!$C$7:$C$574,'1. Status Resumo'!$G$22,'2. Status Detalhe Campos'!$D$7:$D$574,"2. Campo")+COUNTIFS('2. Status Detalhe Campos'!$H$7:$H$574,'1. Status Resumo'!$P32,'2. Status Detalhe Campos'!$C$7:$C$574,'1. Status Resumo'!$H$22,'2. Status Detalhe Campos'!$D$7:$D$574,"2. Campo") -> 0 | U32: =COUNTIFS('2. Status Detalhe Campos'!$G$7:$G$574,'1. Status Resumo'!$P32,'2. Status Detalhe Campos'!$C$7:$C$574,'1. Status Resumo'!$G$22,'2. Status Detalhe Campos'!$D$7:$D$574,"2. Campo")+COUNTIFS('2. Status Detalhe Campos'!$G$7:$G$574,'1. Status Resumo'!$P32,'2. Status Detalhe Campos'!$C$7:$C$574,'1. Status Resumo'!$H$22,'2. Status Detalhe Campos'!$D$7:$D$574,"2. Campo") -> 0 | V32: =U32-T32 -> 0
P33: 6. Em implementação (re-especificação) | T33: =COUNTIFS('2. Status Detalhe Campos'!$H$7:$H$574,'1. Status Resumo'!$P33,'2. Status Detalhe Campos'!$C$7:$C$574,'1. Status Resumo'!$G$22,'2. Status Detalhe Campos'!$D$7:$D$574,"2. Campo")+COUNTIFS('2. Status Detalhe Campos'!$H$7:$H$574,'1. Status Resumo'!$P33,'2. Status Detalhe Campos'!$C$7:$C$574,'1. Status Resumo'!$H$22,'2. Status Detalhe Campos'!$D$7:$D$574,"2. Campo") -> 13 | U33: =COUNTIFS('2. Status Detalhe Campos'!$G$7:$G$574,'1. Status Resumo'!$P33,'2. Status Detalhe Campos'!$C$7:$C$574,'1. Status Resumo'!$G$22,'2. Status Detalhe Campos'!$D$7:$D$574,"2. Campo")+COUNTIFS('2. Status Detalhe Campos'!$G$7:$G$574,'1. Status Resumo'!$P33,'2. Status Detalhe Campos'!$C$7:$C$574,'1. Status Resumo'!$H$22,'2. Status Detalhe Campos'!$D$7:$D$574,"2. Campo") -> 13 | V33: =U33-T33 -> 0
P34: 7. Por iniciar | T34: =COUNTIFS('2. Status Detalhe Campos'!$H$7:$H$574,'1. Status Resumo'!$P34,'2. Status Detalhe Campos'!$C$7:$C$574,'1. Status Resumo'!$G$22,'2. Status Detalhe Campos'!$D$7:$D$574,"2. Campo")+COUNTIFS('2. Status Detalhe Campos'!$H$7:$H$574,'1. Status Resumo'!$P34,'2. Status Detalhe Campos'!$C$7:$C$574,'1. Status Resumo'!$H$22,'2. Status Detalhe Campos'!$D$7:$D$574,"2. Campo") -> 0 | U34: =COUNTIFS('2. Status Detalhe Campos'!$G$7:$G$574,'1. Status Resumo'!$P34,'2. Status Detalhe Campos'!$C$7:$C$574,'1. Status Resumo'!$G$22,'2. Status Detalhe Campos'!$D$7:$D$574,"2. Campo")+COUNTIFS('2. Status Detalhe Campos'!$G$7:$G$574,'1. Status Resumo'!$P34,'2. Status Detalhe Campos'!$C$7:$C$574,'1. Status Resumo'!$H$22,'2. Status Detalhe Campos'!$D$7:$D$574,"2. Campo") -> 0 | V34: =U34-T34 -> 0
T35: =SUM(T26:T34) -> 169 | U35: =SUM(U26:U34) -> 169
G36: Status (Tabelas) | P36: Status (Universos)
F37: > | G37: Tabela de Bens Imóveis | L37: OK | O37: > | P37: Universo Bens Colateralizados (MUG) | T37: OK
F38: > | G38: Tabelas de Processos Imobiliários | L38: OK | O38: > | P38: Universo Bens Não Colateralizados (GP) | T38: OK
F39: > | G39: Tabela de Traçabilidade Processo -Bem | L39: OK | O39: > | P39: Universo Bens Adjudicados | T39: Não serão testados neste projeto
F40: > | G40: Tabela de Traçabilidade Crédito - Processo | L40: OK
F41: > | G41: Tabela input de Cerificados Energéticos (Gloval) | L41: Em Implementação
F42: > | G42: Tabela Output de Cerificados Energéticos | L42: Validação EF
B48: 2. Modelo Verde | G48: Modelo Verde - Input | H48: Modelo Verde - Output
C51: Resumo | G51: Detalhe por Tabela | P51: Status (campos) | T51: =T25 -> 45596 | U51: =$U$25 -> 45604 | V51: ∆ | X51: Highlights
P52: 0. Cancelado | T52: =COUNTIFS('2. Status Detalhe Campos'!$H$7:$H$574,'1. Status Resumo'!$P52,'2. Status Detalhe Campos'!$C$7:$C$574,'1. Status Resumo'!$G$48,'2. Status Detalhe Campos'!$D$7:$D$574,"2. Campo")+COUNTIFS('2. Status Detalhe Campos'!$H$7:$H$574,'1. Status Resumo'!$P52,'2. Status Detalhe Campos'!$C$7:$C$574,'1. Status Resumo'!$H$48,'2. Status Detalhe Campos'!$D$7:$D$574,"2. Campo") -> 14 | U52: =COUNTIFS('2. Status Detalhe Campos'!$G$7:$G$574,'1. Status Resumo'!$P52,'2. Status Detalhe Campos'!$C$7:$C$574,'1. Status Resumo'!$G$48,'2. Status Detalhe Campos'!$D$7:$D$574,"2. Campo")+COUNTIFS('2. Status Detalhe Campos'!$G$7:$G$574,'1. Status Resumo'!$P52,'2. Status Detalhe Campos'!$C$7:$C$574,'1. Status Resumo'!$H$48,'2. Status Detalhe Campos'!$D$7:$D$574,"2. Campo") -> 14 | V52: =U52-T52 -> 0 | X52: 1. Datas de entrega de Tecnologia: Inputs: Atualização + tabela de parametrização: 07/11 (16 campos) -> Entregue no dia 08/11 Tabela de Bens Imóveis (modesg_out_bens_imoveis): - Emissões de Bens Imóveis: 04/11 (8 campos) -> Entregue no dia 05/11 - Risco Físico de Bens Imóveis: 25/11 (4 campos) Tabela de Veículos (modesg_out_ems_vcls): - Universo e Emissões de veículos: 11/11 (7 campos) Tabela de Clientes (modesg_out_empr_info_nfin): - Clientes (Cod_nace_esg , Exclusão de Paris, NFRD e rácios de eligibilidade): 18/11 (20 campos) - Emissões de Clientes: 25/11 (6 campos) - Risco Físico Clientes: 28/11 (4 campos) Marcação Verde (modesg_out_sfcs_taxon_europeia): - Marcação Verde (tabela de contratos): 28/11 (12 campos)
P53: 1. Concluído | T53: =COUNTIFS('2. Status Detalhe Campos'!$H$7:$H$574,'1. Status Resumo'!$P53,'2. Status Detalhe Campos'!$C$7:$C$574,'1. Status Resumo'!$G$48,'2. Status Detalhe Campos'!$D$7:$D$574,"2. Campo")+COUNTIFS('2. Status Detalhe Campos'!$H$7:$H$574,'1. Status Resumo'!$P53,'2. Status Detalhe Campos'!$C$7:$C$574,'1. Status Resumo'!$H$48,'2. Status Detalhe Campos'!$D$7:$D$574,"2. Campo") -> 156 | U53: =COUNTIFS('2. Status Detalhe Campos'!$G$7:$G$574,'1. Status Resumo'!$P53,'2. Status Detalhe Campos'!$C$7:$C$574,'1. Status Resumo'!$G$48,'2. Status Detalhe Campos'!$D$7:$D$574,"2. Campo")+COUNTIFS('2. Status Detalhe Campos'!$G$7:$G$574,'1. Status Resumo'!$P53,'2. Status Detalhe Campos'!$C$7:$C$574,'1. Status Resumo'!$H$48,'2. Status Detalhe Campos'!$D$7:$D$574,"2. Campo") -> 156 | V53: =U53-T53 -> 0
P54: 2.1 Em Teste | T54: =COUNTIFS('2. Status Detalhe Campos'!$H$7:$H$574,'1. Status Resumo'!$P54,'2. Status Detalhe Campos'!$C$7:$C$574,'1. Status Resumo'!$G$48,'2. Status Detalhe Campos'!$D$7:$D$574,"2. Campo")+COUNTIFS('2. Status Detalhe Campos'!$H$7:$H$574,'1. Status Resumo'!$P54,'2. Status Detalhe Campos'!$C$7:$C$574,'1. Status Resumo'!$H$48,'2. Status Detalhe Campos'!$D$7:$D$574,"2. Campo") -> 22 | U54: =COUNTIFS('2. Status Detalhe Campos'!$G$7:$G$574,'1. Status Resumo'!$P54,'2. Status Detalhe Campos'!$C$7:$C$574,'1. Status Resumo'!$G$48,'2. Status Detalhe Campos'!$D$7:$D$574,"2. Campo")+COUNTIFS('2. Status Detalhe Campos'!$G$7:$G$574,'1. Status Resumo'!$P54,'2. Status Detalhe Campos'!$C$7:$C$574,'1. Status Resumo'!$H$48,'2. Status Detalhe Campos'!$D$7:$D$574,"2. Campo") -> 22 | V54: =U54-T54 -> 0
D55: ="# "&U61 -> # 245 | P55: 2.2 Em Re-especificação | T55: =COUNTIFS('2. Status Detalhe Campos'!$H$7:$H$574,'1. Status Resumo'!$P55,'2. Status Detalhe Campos'!$C$7:$C$574,'1. Status Resumo'!$G$48,'2. Status Detalhe Campos'!$D$7:$D$574,"2. Campo")+COUNTIFS('2. Status Detalhe Campos'!$H$7:$H$574,'1. Status Resumo'!$P55,'2. Status Detalhe Campos'!$C$7:$C$574,'1. Status Resumo'!$H$48,'2. Status Detalhe Campos'!$D$7:$D$574,"2. Campo") -> 0 | U55: =COUNTIFS('2. Status Detalhe Campos'!$G$7:$G$574,'1. Status Resumo'!$P55,'2. Status Detalhe Campos'!$C$7:$C$574,'1. Status Resumo'!$G$48,'2. Status Detalhe Campos'!$D$7:$D$574,"2. Campo")+COUNTIFS('2. Status Detalhe Campos'!$G$7:$G$574,'1. Status Resumo'!$P55,'2. Status Detalhe Campos'!$C$7:$C$574,'1. Status Resumo'!$H$48,'2. Status Detalhe Campos'!$D$7:$D$574,"2. Campo") -> 0 | V55: =U55-T55 -> 0
P56: 3. Pendente de outros desenvolvimentos | T56: =COUNTIFS('2. Status Detalhe Campos'!$H$7:$H$574,'1. Status Resumo'!$P56,'2. Status Detalhe Campos'!$C$7:$C$574,'1. Status Resumo'!$G$48,'2. Status Detalhe Campos'!$D$7:$D$574,"2. Campo")+COUNTIFS('2. Status Detalhe Campos'!$H$7:$H$574,'1. Status Resumo'!$P56,'2. Status Detalhe Campos'!$C$7:$C$574,'1. Status Resumo'!$H$48,'2. Status Detalhe Campos'!$D$7:$D$574,"2. Campo") -> 0 | U56: =COUNTIFS('2. Status Detalhe Campos'!$G$7:$G$574,'1. Status Resumo'!$P56,'2. Status Detalhe Campos'!$C$7:$C$574,'1. Status Resumo'!$G$48,'2. Status Detalhe Campos'!$D$7:$D$574,"2. Campo")+COUNTIFS('2. Status Detalhe Campos'!$G$7:$G$574,'1. Status Resumo'!$P56,'2. Status Detalhe Campos'!$C$7:$C$574,'1. Status Resumo'!$H$48,'2. Status Detalhe Campos'!$D$7:$D$574,"2. Campo") -> 0 | V56: =U56-T56 -> 0
P57: 4. Validação EF | T57: =COUNTIFS('2. Status Detalhe Campos'!$H$7:$H$574,'1. Status Resumo'!$P57,'2. Status Detalhe Campos'!$C$7:$C$574,'1. Status Resumo'!$G$48,'2. Status Detalhe Campos'!$D$7:$D$574,"2. Campo")+COUNTIFS('2. Status Detalhe Campos'!$H$7:$H$574,'1. Status Resumo'!$P57,'2. Status Detalhe Campos'!$C$7:$C$574,'1. Status Resumo'!$H$48,'2. Status Detalhe Campos'!$D$7:$D$574,"2. Campo") -> 0 | U57: =COUNTIFS('2. Status Detalhe Campos'!$G$7:$G$574,'1. Status Resumo'!$P57,'2. Status Detalhe Campos'!$C$7:$C$574,'1. Status Resumo'!$G$48,'2. Status Detalhe Campos'!$D$7:$D$574,"2. Campo")+COUNTIFS('2. Status Detalhe Campos'!$G$7:$G$574,'1. Status Resumo'!$P57,'2. Status Detalhe Campos'!$C$7:$C$574,'1. Status Resumo'!$H$48,'2. Status Detalhe Campos'!$D$7:$D$574,"2. Campo") -> 0 | V57: =U57-T57 -> 0
P58: 5. Em Correção | R58: (incidências) | T58: =COUNTIFS('2. Status Detalhe Campos'!$H$7:$H$574,'1. Status Resumo'!$P58,'2. Status Detalhe Campos'!$C$7:$C$574,'1. Status Resumo'!$G$48,'2. Status Detalhe Campos'!$D$7:$D$574,"2. Campo")+COUNTIFS('2. Status Detalhe Campos'!$H$7:$H$574,'1. Status Resumo'!$P58,'2. Status Detalhe Campos'!$C$7:$C$574,'1. Status Resumo'!$H$48,'2. Status Detalhe Campos'!$D$7:$D$574,"2. Campo") -> 0 | U58: =COUNTIFS('2. Status Detalhe Campos'!$G$7:$G$574,'1. Status Resumo'!$P58,'2. Status Detalhe Campos'!$C$7:$C$574,'1. Status Resumo'!$G$48,'2. Status Detalhe Campos'!$D$7:$D$574,"2. Campo")+COUNTIFS('2. Status Detalhe Campos'!$G$7:$G$574,'1. Status Resumo'!$P58,'2. Status Detalhe Campos'!$C$7:$C$574,'1. Status Resumo'!$H$48,'2. Status Detalhe Campos'!$D$7:$D$574,"2. Campo") -> 0 | V58: =U58-T58 -> 0
P59: 6. Em implementação (re-especificação) | T59: =COUNTIFS('2. Status Detalhe Campos'!$H$7:$H$574,'1. Status Resumo'!$P59,'2. Status Detalhe Campos'!$C$7:$C$574,'1. Status Resumo'!$G$48,'2. Status Detalhe Campos'!$D$7:$D$574,"2. Campo")+COUNTIFS('2. Status Detalhe Campos'!$H$7:$H$574,'1. Status Resumo'!$P59,'2. Status Detalhe Campos'!$C$7:$C$574,'1. Status Resumo'!$H$48,'2. Status Detalhe Campos'!$D$7:$D$574,"2. Campo") -> 53 | U59: =COUNTIFS('2. Status Detalhe Campos'!$G$7:$G$574,'1. Status Resumo'!$P59,'2. Status Detalhe Campos'!$C$7:$C$574,'1. Status Resumo'!$G$48,'2. Status Detalhe Campos'!$D$7:$D$574,"2. Campo")+COUNTIFS('2. Status Detalhe Campos'!$G$7:$G$574,'1. Status Resumo'!$P59,'2. Status Detalhe Campos'!$C$7:$C$574,'1. Status Resumo'!$H$48,'2. Status Detalhe Campos'!$D$7:$D$574,"2. Campo") -> 53 | V59: =U59-T59 -> 0
P60: 7. Por iniciar | T60: =COUNTIFS('2. Status Detalhe Campos'!$H$7:$H$574,'1. Status Resumo'!$P60,'2. Status Detalhe Campos'!$C$7:$C$574,'1. Status Resumo'!$G$48,'2. Status Detalhe Campos'!$D$7:$D$574,"2. Campo")+COUNTIFS('2. Status Detalhe Campos'!$H$7:$H$574,'1. Status Resumo'!$P60,'2. Status Detalhe Campos'!$C$7:$C$574,'1. Status Resumo'!$H$48,'2. Status Detalhe Campos'!$D$7:$D$574,"2. Campo") -> 0 | U60: =COUNTIFS('2. Status Detalhe Campos'!$G$7:$G$574,'1. Status Resumo'!$P60,'2. Status Detalhe Campos'!$C$7:$C$574,'1. Status Resumo'!$G$48,'2. Status Detalhe Campos'!$D$7:$D$574,"2. Campo")+COUNTIFS('2. Status Detalhe Campos'!$G$7:$G$574,'1. Status Resumo'!$P60,'2. Status Detalhe Campos'!$C$7:$C$574,'1. Status Resumo'!$H$48,'2. Status Detalhe Campos'!$D$7:$D$574,"2. Campo") -> 0 | V60: =U60-T60 -> 0
T61: =SUM(T52:T60) -> 245 | U61: =SUM(U52:U60) -> 245
P63: Status (Universos - Inputs)
O64: > | P64: modesg_inp_risco_fisico | T64: OK
O65: > | P65: modesg_inp_nfrd_alinhamento_tax | T65: OK
O66: > | P66: modesg_inp_km_medios_emss_vcls | T66: OK
O67: > | P67: modesg_inp_emss_vcls | T67: OK
O68: > | P68: modesg_inp_emss_scib | T68: OK
O69: > | P69: modesg_inp_emss_nace | T69: OK
O70: > | P70: modesg_inp_emss_bens_imoveis | T70: OK
O71: > | P71: modesg_inp_empr_excl_paris | T71: OK
O72: > | P72: modesg_param_sfcs_taxon_europeia | T72: Em Implementação (re-especificação)
O73: > | P73: Input Munich Re | T73: Em Implementação
P75: Status (Universos - Outputs)
O76: > | P76: modesg_out_ems_vcls | T76: Em Implementação (re-especificação)
O77: > | P77: modesg_out_bens_imoveis | T77: OK (coerente com Modelo de Bens Imóveis)
O78: > | P78: modesg_out_empr_info_nfin | T78: OK
O79: > | P79: modesg_out_sfcs_taxon_europeia | T79: Em Implementação (re-especificação)
B83: 3. Loan Tape | Pilar III | G83: Pilar III
C86: Resumo | G86: Detalhe por Tabela | P86: Status (campos) | T86: =T25 -> 45596 | U86: =$U$25 -> 45604 | V86: ∆ | X86: Highlights
P87: 0. Cancelado | T87: =COUNTIFS(Table4[Status Anterior],'1. Status Resumo'!$P87,Table4[Sub-âmbito],'1. Status Resumo'!$G$83,Table4[Tipo de teste],"2. Campo") -> 0 | U87: =COUNTIFS(Table4[Status Atual],'1. Status Resumo'!$P87,Table4[Sub-âmbito],'1. Status Resumo'!$G$83,Table4[Tipo de teste],"2. Campo") -> 0 | V87: =U87-T87 -> 0 | X87: 1. Iniciámos a simulação da tabela Protection. 2. Foi realizada a sessão de validação com o LCM e fechadas as re-especificações. 3. Datas de Entrega de Tecnologia: Tabela Entity (lt003_entity): - Nace ESG, Rácios de Eligibilidade, Flag NFRD Grupo, Flag Exclusão de Paris, Risco Físico, Código Postal, Emissões de clientes e Emissões Grupo campos: 31/10 (25 campos) -> Entregue no dia 31/10 - Flg NFRD Cliente e Rácios de eligibilidade: 15/11 (5 campos) - Liabilities do Cliente: 28/11 (1 campo) da lt003_entity (28/11) Tabela Protection (lt004_protection): - Emissões, Risco Físico e EPCs: 31/10 (11 campos) -> Entregue no dia 31/10 - Universo, Campos de Caracterização imóvel: 15/11 (5 campos) - Valor Proteção e Flgs Imóveis: 28/11 (5 campos) Tabela Instrument ( lt002_instrument) - Métodos de Emissões e Categoria Verde: 15/11 (5 campos) - Mitigação Risco: 28/11 (1 campo) Tabela Instrument Activity (lt007_instr_activity): 28/11 Tabela Parametrização (lt827_mthd_usd_instrmnt): 15/11
P88: 1. Concluído | T88: =COUNTIFS(Table4[Status Anterior],'1. Status Resumo'!$P88,Table4[Sub-âmbito],'1. Status Resumo'!$G$83,Table4[Tipo de teste],"2. Campo") -> 54 | U88: =COUNTIFS(Table4[Status Atual],'1. Status Resumo'!$P88,Table4[Sub-âmbito],'1. Status Resumo'!$G$83,Table4[Tipo de teste],"2. Campo") -> 54 | V88: =U88-T88 -> 0
P89: 2.1 Em Teste | T89: =COUNTIFS(Table4[Status Anterior],'1. Status Resumo'!$P89,Table4[Sub-âmbito],'1. Status Resumo'!$G$83,Table4[Tipo de teste],"2. Campo") -> 6 | U89: =COUNTIFS(Table4[Status Atual],'1. Status Resumo'!$P89,Table4[Sub-âmbito],'1. Status Resumo'!$G$83,Table4[Tipo de teste],"2. Campo") -> 6 | V89: =U89-T89 -> 0
D90: ="# "&U96 -> # 135 | P90: 2.2 Em Re-especificação | T90: =COUNTIFS(Table4[Status Anterior],'1. Status Resumo'!$P90,Table4[Sub-âmbito],'1. Status Resumo'!$G$83,Table4[Tipo de teste],"2. Campo") -> 0 | U90: =COUNTIFS(Table4[Status Atual],'1. Status Resumo'!$P90,Table4[Sub-âmbito],'1. Status Resumo'!$G$83,Table4[Tipo de teste],"2. Campo") -> 0 | V90: =U90-T90 -> 0
P91: 3. Pendente de outros desenvolvimentos | T91: =COUNTIFS(Table4[Status Anterior],'1. Status Resumo'!$P91,Table4[Sub-âmbito],'1. Status Resumo'!$G$83,Table4[Tipo de teste],"2. Campo") -> 26 | U91: =COUNTIFS(Table4[Status Atual],'1. Status Resumo'!$P91,Table4[Sub-âmbito],'1. Status Resumo'!$G$83,Table4[Tipo de teste],"2. Campo") -> 26 | V91: =U91-T91 -> 0
P92: 4. Validação EF | T92: =COUNTIFS(Table4[Status Anterior],'1. Status Resumo'!$P92,Table4[Sub-âmbito],'1. Status Resumo'!$G$83,Table4[Tipo de teste],"2. Campo") -> 0 | U92: =COUNTIFS(Table4[Status Atual],'1. Status Resumo'!$P92,Table4[Sub-âmbito],'1. Status Resumo'!$G$83,Table4[Tipo de teste],"2. Campo") -> 0 | V92: =U92-T92 -> 0
P93: 5. Em Correção | R93: (incidências) | T93: =COUNTIFS(Table4[Status Anterior],'1. Status Resumo'!$P93,Table4[Sub-âmbito],'1. Status Resumo'!$G$83,Table4[Tipo de teste],"2. Campo") -> 0 | U93: =COUNTIFS(Table4[Status Atual],'1. Status Resumo'!$P93,Table4[Sub-âmbito],'1. Status Resumo'!$G$83,Table4[Tipo de teste],"2. Campo") -> 0 | V93: =U93-T93 -> 0
P94: 6. Em implementação (re-especificação) | T94: =COUNTIFS(Table4[Status Anterior],'1. Status Resumo'!$P94,Table4[Sub-âmbito],'1. Status Resumo'!$G$83,Table4[Tipo de teste],"2. Campo") -> 49 | U94: =COUNTIFS(Table4[Status Atual],'1. Status Resumo'!$P94,Table4[Sub-âmbito],'1. Status Resumo'!$G$83,Table4[Tipo de teste],"2. Campo") -> 49 | V94: =U94-T94 -> 0
P95: 7. Por iniciar | T95: =COUNTIFS(Table4[Status Anterior],'1. Status Resumo'!$P95,Table4[Sub-âmbito],'1. Status Resumo'!$G$83,Table4[Tipo de teste],"2. Campo") -> 0 | U95: =COUNTIFS(Table4[Status Atual],'1. Status Resumo'!$P95,Table4[Sub-âmbito],'1. Status Resumo'!$G$83,Table4[Tipo de teste],"2. Campo") -> 0 | V95: =U95-T95 -> 0
T96: =SUM(T87:T95) -> 135 | U96: =SUM(U87:U95) -> 135
P98: Status (Tabelas)
O99: > | P99: lt002_instrument | T99: Em Curso
O100: > | P100: lt003_entity | T100: Em Curso
O101: > | P101: lt004_protection | T101: Em Curso
O102: > | P102: lt005_instr_ent | T102: OK
O103: > | P103: lt006_instr_prot | T103: OK
O104: > | P104: lt007_instr_activity | T104: Em Implementação
O105: > | P105: lt827_mthd_usd_instrmnt | T105: Em Implementação
O106: > | P106: lt826_esg_sbsctr | T106: OK

Sheet 2. Status Detalhe Campos
B6: Âmbito | C6: Sub-âmbito | D6: Tipo de teste | E6: Tabela | F6: Campo | G6: Status Atual | H6: Status Anterior | I6: Observações | J6: Data de Pedido correção/esclarecimento | K6: Data de correção prevista | L6: Data de correção efetiva | M6: Data Prevista de Re-especificação | N6: Data Prevista de Teste
A7: =E7&F7 -> ENERGY_CERTIFICATE_EST_INPUTn.a. | B7: Pilar III | C7: Bens Imóveis - Input | D7: 1. Universo | E7: ENERGY_CERTIFICATE_EST_INPUT | F7: n.a. | G7: =VLOOKUP(A7,Plano_V3!$A$26:$G$592,7,0) -> 6. Em implementação (re-especificação) | H7: 6. Em implementação (re-especificação) | I7: Apesar da data de correção ser 28/11 a data que importa é 24/10, uma vez que a última implementação não é relevanta para iniciar os testes à tabela | J7: =IF(VLOOKUP(A7,'Aux - pivots1'!$A:$E,3,0)=0, "",VLOOKUP(A7,'Aux - pivots1'!$A:$E,3,0)) -> 45510 | K7: =IF(VLOOKUP(A7,'Aux - pivots1'!$A:$E,4,0)=0, "",VLOOKUP(A7,'Aux - pivots1'!$A:$E,4,0)) -> 45624 | L7: =IF(VLOOKUP(A7,'Aux - pivots1'!$A:$E,5,0)=0, "",VLOOKUP(A7,'Aux - pivots1'!$A:$E,5,0))
A8: =E8&F8 -> ENERGY_CERTIFICATE_EST_INPUTPROPERTY_BANK_ID | B8: Pilar III | C8: Bens Imóveis - Input | D8: 2. Campo | E8: ENERGY_CERTIFICATE_EST_INPUT | F8: PROPERTY_BANK_ID | G8: =VLOOKUP(A8,Plano_V3!$A$26:$G$592,7,0) -> 6. Em implementação (re-especificação) | H8: 6. Em implementação (re-especificação) | I8: Apesar da data de correção ser 28/11 a data que importa é 24/10, uma vez que a última implementação não é relevanta para iniciar os testes à tabela | J8: =IF(VLOOKUP(A8,'Aux - pivots1'!$A:$E,3,0)=0, "",VLOOKUP(A8,'Aux - pivots1'!$A:$E,3,0)) -> 45510 | K8: =IF(VLOOKUP(A8,'Aux - pivots1'!$A:$E,4,0)=0, "",VLOOKUP(A8,'Aux - pivots1'!$A:$E,4,0)) -> 45624 | L8: =IF(VLOOKUP(A8,'Aux - pivots1'!$A:$E,5,0)=0, "",VLOOKUP(A8,'Aux - pivots1'!$A:$E,5,0))
A9: =E9&F9 -> ENERGY_CERTIFICATE_EST_INPUTENCRYPTED_KEY | B9: Pilar III | C9: Bens Imóveis - Input | D9: 2. Campo | E9: ENERGY_CERTIFICATE_EST_INPUT | F9: ENCRYPTED_KEY | G9: =VLOOKUP(A9,Plano_V3!$A$26:$G$592,7,0) -> 6. Em implementação (re-especificação) | H9: 6. Em implementação (re-especificação) | I9: Apesar da data de correção ser 28/11 a data que importa é 24/10, uma vez que a última implementação não é relevanta para iniciar os testes à tabela | J9: =IF(VLOOKUP(A9,'Aux - pivots1'!$A:$E,3,0)=0, "",VLOOKUP(A9,'Aux - pivots1'!$A:$E,3,0)) -> 45510 | K9: =IF(VLOOKUP(A9,'Aux - pivots1'!$A:$E,4,0)=0, "",VLOOKUP(A9,'Aux - pivots1'!$A:$E,4,0)) -> 45624 | L9: =IF(VLOOKUP(A9,'Aux - pivots1'!$A:$E,5,0)=0, "",VLOOKUP(A9,'Aux - pivots1'!$A:$E,5,0))
A10: =E10&F10 -> ENERGY_CERTIFICATE_EST_INPUTPROPERTY_BRANCH_CODE | B10: Pilar III | C10: Bens Imóveis - Input | D10: 2. Campo | E10: ENERGY_CERTIFICATE_EST_INPUT | F10: PROPERTY_BRANCH_CODE | G10: =VLOOKUP(A10,Plano_V3!$A$26:$G$592,7,0) -> 6. Em implementação (re-especificação) | H10: 6. Em implementação (re-especificação) | I10: Apesar da data de correção ser 28/11 a data que importa é 24/10, uma vez que a última implementação não é relevanta para iniciar os testes à tabela | J10: =IF(VLOOKUP(A10,'Aux - pivots1'!$A:$E,3,0)=0, "",VLOOKUP(A10,'Aux - pivots1'!$A:$E,3,0)) -> 45510 | K10: =IF(VLOOKUP(A10,'Aux - pivots1'!$A:$E,4,0)=0, "",VLOOKUP(A10,'Aux - pivots1'!$A:$E,4,0)) -> 45624 | L10: =IF(VLOOKUP(A10,'Aux - pivots1'!$A:$E,5,0)=0, "",VLOOKUP(A10,'Aux - pivots1'!$A:$E,5,0))
A11: =E11&F11 -> ENERGY_CERTIFICATE_EST_INPUTPROPERTY_CONTRACT_ID | B11: Pilar III | C11: Bens Imóveis - Input | D11: 2. Campo | E11: ENERGY_CERTIFICATE_EST_INPUT | F11: PROPERTY_CONTRACT_ID | G11: =VLOOKUP(A11,Plano_V3!$A$26:$G$592,7,0) -> 6. Em implementação (re-especificação) | H11: 6. Em implementação (re-especificação) | I11: Apesar da data de correção ser 28/11 a data que importa é 24/10, uma vez que a última implementação não é relevanta para iniciar os testes à tabela | J11: =IF(VLOOKUP(A11,'Aux - pivots1'!$A:$E,3,0)=0, "",VLOOKUP(A11,'Aux - pivots1'!$A:$E,3,0)) -> 45510 | K11: =IF(VLOOKUP(A11,'Aux - pivots1'!$A:$E,4,0)=0, "",VLOOKUP(A11,'Aux - pivots1'!$A:$E,4,0)) -> 45624 | L11: =IF(VLOOKUP(A11,'Aux - pivots1'!$A:$E,5,0)=0, "",VLOOKUP(A11,'Aux - pivots1'!$A:$E,5,0))
A12: =E12&F12 -> ENERGY_CERTIFICATE_EST_INPUTPROPERTY_REFERENCE_CODE | B12: Pilar III | C12: Bens Imóveis - Input | D12: 2. Campo | E12: ENERGY_CERTIFICATE_EST_INPUT | F12: PROPERTY_REFERENCE_CODE | G12: =VLOOKUP(A12,Plano_V3!$A$26:$G$592,7,0) -> 6. Em implementação (re-especificação) | H12: 6. Em implementação (re-especificação) | I12: Apesar da data de correção ser 28/11 a data que importa é 24/10, uma vez que a última implementação não é relevanta para iniciar os testes à tabela | J12: =IF(VLOOKUP(A12,'Aux - pivots1'!$A:$E,3,0)=0, "",VLOOKUP(A12,'Aux - pivots1'!$A:$E,3,0)) -> 45510 | K12: =IF(VLOOKUP(A12,'Aux - pivots1'!$A:$E,4,0)=0, "",VLOOKUP(A12,'Aux - pivots1'!$A:$E,4,0)) -> 45624 | L12: =IF(VLOOKUP(A12,'Aux - pivots1'!$A:$E,5,0)=0, "",VLOOKUP(A12,'Aux - pivots1'!$A:$E,5,0))
A13: =E13&F13 -> ENERGY_CERTIFICATE_EST_INPUTDATA_EXTRACTION_DATE | B13: Pilar III | C13: Bens Imóveis - Input | D13: 2. Campo | E13: ENERGY_CERTIFICATE_EST_INPUT | F13: DATA_EXTRACTION_DATE | G13: =VLOOKUP(A13,Plano_V3!$A$26:$G$592,7,0) -> 6. Em implementação (re-especificação) | H13: 6. Em implementação (re-especificação) | I13: Apesar da data de correção ser 28/11 a data que importa é 24/10, uma vez que a última implementação não é relevanta para iniciar os testes à tabela | J13: =IF(VLOOKUP(A13,'Aux - pivots1'!$A:$E,3,0)=0, "",VLOOKUP(A13,'Aux - pivots1'!$A:$E,3,0)) -> 45510 | K13: =IF(VLOOKUP(A13,'Aux - pivots1'!$A:$E,4,0)=0, "",VLOOKUP(A13,'Aux - pivots1'!$A:$E,4,0)) -> 45624 | L13: =IF(VLOOKUP(A13,'Aux - pivots1'!$A:$E,5,0)=0, "",VLOOKUP(A13,'Aux - pivots1'!$A:$E,5,0))
A14: =E14&F14 -> ENERGY_CERTIFICATE_EST_INPUTEPC | B14: Pilar III | C14: Bens Imóveis - Input | D14: 2. Campo | E14: ENERGY_CERTIFICATE_EST_INPUT | F14: EPC | G14: =VLOOKUP(A14,Plano_V3!$A$26:$G$592,7,0) -> 6. Em implementação (re-especificação) | H14: 6. Em implementação (re-especificação) | I14: Apesar da data de correção ser 28/11 a data que importa é 24/10, uma vez que a última implementação não é relevanta para iniciar os testes à tabela | J14: =IF(VLOOKUP(A14,'Aux - pivots1'!$A:$E,3,0)=0, "",VLOOKUP(A14,'Aux - pivots1'!$A:$E,3,0)) -> 45510 | K14: =IF(VLOOKUP(A14,'Aux - pivots1'!$A:$E,4,0)=0, "",VLOOKUP(A14,'Aux - pivots1'!$A:$E,4,0)) -> 45624 | L14: =IF(VLOOKUP(A14,'Aux - pivots1'!$A:$E,5,0)=0, "",VLOOKUP(A14,'Aux - pivots1'!$A:$E,5,0))
A15: =E15&F15 -> ENERGY_CERTIFICATE_EST_INPUTDATA_PROVIDER | B15: Pilar III | C15: Bens Imóveis - Input | D15: 2. Campo | E15: ENERGY_CERTIFICATE_EST_INPUT | F15: DATA_PROVIDER | G15: =VLOOKUP(A15,Plano_V3!$A$26:$G$592,7,0) -> 6. Em implementação (re-especificação) | H15: 6. Em implementação (re-especificação) | I15: Apesar da data de correção ser 28/11 a data que importa é 24/10, uma vez que a última implementação não é relevanta para iniciar os testes à tabela | J15: =IF(VLOOKUP(A15,'Aux - pivots1'!$A:$E,3,0)=0, "",VLOOKUP(A15,'Aux - pivots1'!$A:$E,3,0)) -> 45510 | K15: =IF(VLOOKUP(A15,'Aux - pivots1'!$A:$E,4,0)=0, "",VLOOKUP(A15,'Aux - pivots1'!$A:$E,4,0)) -> 45624 | L15: =IF(VLOOKUP(A15,'Aux - pivots1'!$A:$E,5,0)=0, "",VLOOKUP(A15,'Aux - pivots1'!$A:$E,5,0))
A16: =E16&F16 -> ENERGY_CERTIFICATE_EST_INPUTACTUAL_VALUE_IND | B16: Pilar III | C16: Bens Imóveis - Input | D16: 2. Campo | E16: ENERGY_CERTIFICATE_EST_INPUT | F16: ACTUAL_VALUE_IND | G16: =VLOOKUP(A16,Plano_V3!$A$26:$G$592,7,0) -> 6. Em implementação (re-especificação) | H16: 6. Em implementação (re-especificação) | I16: Apesar da data de correção ser 28/11 a data que importa é 24/10, uma vez que a última implementação não é relevanta para iniciar os testes à tabela | J16: =IF(VLOOKUP(A16,'Aux - pivots1'!$A:$E,3,0)=0, "",VLOOKUP(A16,'Aux - pivots1'!$A:$E,3,0)) -> 45510 | K16: =IF(VLOOKUP(A16,'Aux - pivots1'!$A:$E,4,0)=0, "",VLOOKUP(A16,'Aux - pivots1'!$A:$E,4,0)) -> 45624 | L16: =IF(VLOOKUP(A16,'Aux - pivots1'!$A:$E,5,0)=0, "",VLOOKUP(A16,'Aux - pivots1'!$A:$E,5,0))
A17: =E17&F17 -> ENERGY_CERTIFICATE_EST_INPUTQUALITY_SCORE | B17: Pilar III | C17: Bens Imóveis - Input | D17: 2. Campo | E17: ENERGY_CERTIFICATE_EST_INPUT | F17: QUALITY_SCORE | G17: =VLOOKUP(A17,Plano_V3!$A$26:$G$592,7,0) -> 6. Em implementação (re-especificação) | H17: 6. Em implementação (re-especificação) | I17: Apesar da data de correção ser 28/11 a data que importa é 24/10, uma vez que a última implementação não é relevanta para iniciar os testes à tabela | J17: =IF(VLOOKUP(A17,'Aux - pivots1'!$A:$E,3,0)=0, "",VLOOKUP(A17,'Aux - pivots1'!$A:$E,3,0)) -> 45510 | K17: =IF(VLOOKUP(A17,'Aux - pivots1'!$A:$E,4,0)=0, "",VLOOKUP(A17,'Aux - pivots1'!$A:$E,4,0)) -> 45624 | L17: =IF(VLOOKUP(A17,'Aux - pivots1'!$A:$E,5,0)=0, "",VLOOKUP(A17,'Aux - pivots1'!$A:$E,5,0))
A18: =E18&F18 -> ENERGY_CERTIFICATE_EST_INPUTENERGY_CONSUMPTION_VALUE_YEAR | B18: Pilar III | C18: Bens Imóveis - Input | D18: 2. Campo | E18: ENERGY_CERTIFICATE_EST_INPUT | F18: ENERGY_CONSUMPTION_VALUE_YEAR | G18: =VLOOKUP(A18,Plano_V3!$A$26:$G$592,7,0) -> 6. Em implementação (re-especificação) | H18: 6. Em implementação (re-especificação) | I18: Apesar da data de correção ser 28/11 a data que importa é 24/10, uma vez que a última implementação não é relevanta para iniciar os testes à tabela | J18: =IF(VLOOKUP(A18,'Aux - pivots1'!$A:$E,3,0)=0, "",VLOOKUP(A18,'Aux - pivots1'!$A:$E,3,0)) -> 45510 | K18: =IF(VLOOKUP(A18,'Aux - pivots1'!$A:$E,4,0)=0, "",VLOOKUP(A18,'Aux - pivots1'!$A:$E,4,0)) -> 45624 | L18: =IF(VLOOKUP(A18,'Aux - pivots1'!$A:$E,5,0)=0, "",VLOOKUP(A18,'Aux - pivots1'!$A:$E,5,0))
A19: =E19&F19 -> ENERGY_CERTIFICATE_EST_INPUTCARBON_EMISSION_VALUE_YEAR | B19: Pilar III | C19: Bens Imóveis - Input | D19: 2. Campo | E19: ENERGY_CERTIFICATE_EST_INPUT | F19: CARBON_EMISSION_VALUE_YEAR | G19: =VLOOKUP(A19,Plano_V3!$A$26:$G$592,7,0) -> 6. Em implementação (re-especificação) | H19: 6. Em implementação (re-especificação) | I19: Apesar da data de correção ser 28/11 a data que importa é 24/10, uma vez que a última implementação não é relevanta para iniciar os testes à tabela | J19: =IF(VLOOKUP(A19,'Aux - pivots1'!$A:$E,3,0)=0, "",VLOOKUP(A19,'Aux - pivots1'!$A:$E,3,0)) -> 45510 | K19: =IF(VLOOKUP(A19,'Aux - pivots1'!$A:$E,4,0)=0, "",VLOOKUP(A19,'Aux - pivots1'!$A:$E,4,0)) -> 45624 | L19: =IF(VLOOKUP(A19,'Aux - pivots1'!$A:$E,5,0)=0, "",VLOOKUP(A19,'Aux - pivots1'!$A:$E,5,0))
A20: =E20&F20 -> PROCESSn.a. | B20: Pilar III | C20: Bens Imóveis - Output | D20: 1. Universo | E20: PROCESS | F20: n.a. | G20: =VLOOKUP(A20,Plano_V3!$A$26:$G$592,7,0) -> 1. Concluído | H20: 1. Concluído | J20: =IF(VLOOKUP(A20,'Aux - pivots1'!$A:$E,3,0)=0, "",VLOOKUP(A20,'Aux - pivots1'!$A:$E,3,0)) | K20: =IF(VLOOKUP(A20,'Aux - pivots1'!$A:$E,4,0)=0, "",VLOOKUP(A20,'Aux - pivots1'!$A:$E,4,0)) | L20: =IF(VLOOKUP(A20,'Aux - pivots1'!$A:$E,5,0)=0, "",VLOOKUP(A20,'Aux - pivots1'!$A:$E,5,0))
A21: =E21&F21 -> PROCESSPROCESS_BANK_ID | B21: Pilar III | C21: Bens Imóveis - Output | D21: 2. Campo | E21: PROCESS | F21: PROCESS_BANK_ID | G21: =VLOOKUP(A21,Plano_V3!$A$26:$G$592,7,0) -> 1. Concluído | H21: 1. Concluído | I21: 26/07/2024: Conclusão de testes ao universo MUG e GP. Adjudicados fora de âmbito deste projeto. | J21: =IF(VLOOKUP(A21,'Aux - pivots1'!$A:$E,3,0)=0, "",VLOOKUP(A21,'Aux - pivots1'!$A:$E,3,0)) | K21: =IF(VLOOKUP(A21,'Aux - pivots1'!$A:$E,4,0)=0, "",VLOOKUP(A21,'Aux - pivots1'!$A:$E,4,0)) | L21: =IF(VLOOKUP(A21,'Aux - pivots1'!$A:$E,5,0)=0, "",VLOOKUP(A21,'Aux - pivots1'!$A:$E,5,0))
A22: =E22&F22 -> PROCESSPROCESS_BRANCH_CODE | B22: Pilar III | C22: Bens Imóveis - Output | D22: 2. Campo | E22: PROCESS | F22: PROCESS_BRANCH_CODE | G22: =VLOOKUP(A22,Plano_V3!$A$26:$G$592,7,0) -> 1. Concluído | H22: 1. Concluído | I22: 26/07/2024: Conclusão de testes ao universo MUG e GP. Adjudicados fora de âmbito deste projeto. | J22: =IF(VLOOKUP(A22,'Aux - pivots1'!$A:$E,3,0)=0, "",VLOOKUP(A22,'Aux - pivots1'!$A:$E,3,0)) | K22: =IF(VLOOKUP(A22,'Aux - pivots1'!$A:$E,4,0)=0, "",VLOOKUP(A22,'Aux - pivots1'!$A:$E,4,0)) | L22: =IF(VLOOKUP(A22,'Aux - pivots1'!$A:$E,5,0)=0, "",VLOOKUP(A22,'Aux - pivots1'!$A:$E,5,0))
A23: =E23&F23 -> PROCESSPROCESS_ACCOUNT_ID | B23: Pilar III | C23: Bens Imóveis - Output | D23: 2. Campo | E23: PROCESS | F23: PROCESS_ACCOUNT_ID | G23: =VLOOKUP(A23,Plano_V3!$A$26:$G$592,7,0) -> 1. Concluído | H23: 1. Concluído | I23: 26/07/2024: Conclusão de testes ao universo MUG e GP. Adjudicados fora de âmbito deste projeto. | J23: =IF(VLOOKUP(A23,'Aux - pivots1'!$A:$E,3,0)=0, "",VLOOKUP(A23,'Aux - pivots1'!$A:$E,3,0)) | K23: =IF(VLOOKUP(A23,'Aux - pivots1'!$A:$E,4,0)=0, "",VLOOKUP(A23,'Aux - pivots1'!$A:$E,4,0)) | L23: =IF(VLOOKUP(A23,'Aux - pivots1'!$A:$E,5,0)=0, "",VLOOKUP(A23,'Aux - pivots1'!$A:$E,5,0))
A24: =E24&F24 -> PROCESScod_estd_prcs | B24: Pilar III | C24: Bens Imóveis - Output | D24: 2. Campo | E24: PROCESS | F24: cod_estd_prcs | G24: =VLOOKUP(A24,Plano_V3!$A$26:$G$592,7,0) -> 0. Cancelado | H24: 0. Cancelado | I24: 19/07/2024: Campo eliminado do Modelo para garantir coerência com MUG | J24: =IF(VLOOKUP(A24,'Aux - pivots1'!$A:$E,3,0)=0, "",VLOOKUP(A24,'Aux - pivots1'!$A:$E,3,0)) | K24: =IF(VLOOKUP(A24,'Aux - pivots1'!$A:$E,4,0)=0, "",VLOOKUP(A24,'Aux - pivots1'!$A:$E,4,0)) | L24: =IF(VLOOKUP(A24,'Aux - pivots1'!$A:$E,5,0)=0, "",VLOOKUP(A24,'Aux - pivots1'!$A:$E,5,0))
A25: =E25&F25 -> PROCESSGUARANTEE_CODE | B25: Pilar III | C25: Bens Imóveis - Output | D25: 2. Campo | E25: PROCESS | F25: GUARANTEE_CODE | G25: =VLOOKUP(A25,Plano_V3!$A$26:$G$592,7,0) -> 1. Concluído | H25: 1. Concluído | J25: =IF(VLOOKUP(A25,'Aux - pivots1'!$A:$E,3,0)=0, "",VLOOKUP(A25,'Aux - pivots1'!$A:$E,3,0)) | K25: =IF(VLOOKUP(A25,'Aux - pivots1'!$A:$E,4,0)=0, "",VLOOKUP(A25,'Aux - pivots1'!$A:$E,4,0)) | L25: =IF(VLOOKUP(A25,'Aux - pivots1'!$A:$E,5,0)=0, "",VLOOKUP(A25,'Aux - pivots1'!$A:$E,5,0))
A26: =E26&F26 -> PROCESSCURRENCY_CODE | B26: Pilar III | C26: Bens Imóveis - Output | D26: 2. Campo | E26: PROCESS | F26: CURRENCY_CODE | G26: =VLOOKUP(A26,Plano_V3!$A$26:$G$592,7,0) -> 1. Concluído | H26: 1. Concluído | J26: =IF(VLOOKUP(A26,'Aux - pivots1'!$A:$E,3,0)=0, "",VLOOKUP(A26,'Aux - pivots1'!$A:$E,3,0)) -> 45512 | K26: =IF(VLOOKUP(A26,'Aux - pivots1'!$A:$E,4,0)=0, "",VLOOKUP(A26,'Aux - pivots1'!$A:$E,4,0)) -> 45526 | L26: =IF(VLOOKUP(A26,'Aux - pivots1'!$A:$E,5,0)=0, "",VLOOKUP(A26,'Aux - pivots1'!$A:$E,5,0))
A27: =E27&F27 -> PROCESSPROCESS_CAMPAIGN_CODE | B27: Pilar III | C27: Bens Imóveis - Output | D27: 2. Campo | E27: PROCESS | F27: PROCESS_CAMPAIGN_CODE | G27: =VLOOKUP(A27,Plano_V3!$A$26:$G$592,7,0) -> 1. Concluído | H27: 1. Concluído | J27: =IF(VLOOKUP(A27,'Aux - pivots1'!$A:$E,3,0)=0, "",VLOOKUP(A27,'Aux - pivots1'!$A:$E,3,0)) | K27: =IF(VLOOKUP(A27,'Aux - pivots1'!$A:$E,4,0)=0, "",VLOOKUP(A27,'Aux - pivots1'!$A:$E,4,0)) | L27: =IF(VLOOKUP(A27,'Aux - pivots1'!$A:$E,5,0)=0, "",VLOOKUP(A27,'Aux - pivots1'!$A:$E,5,0))
A28: =E28&F28 -> PROCESSPROCESS_PRODUCT_ID | B28: Pilar III | C28: Bens Imóveis - Output | D28: 2. Campo | E28: PROCESS | F28: PROCESS_PRODUCT_ID | G28: =VLOOKUP(A28,Plano_V3!$A$26:$G$592,7,0) -> 1. Concluído | H28: 1. Concluído | J28: =IF(VLOOKUP(A28,'Aux - pivots1'!$A:$E,3,0)=0, "",VLOOKUP(A28,'Aux - pivots1'!$A:$E,3,0)) | K28: =IF(VLOOKUP(A28,'Aux - pivots1'!$A:$E,4,0)=0, "",VLOOKUP(A28,'Aux - pivots1'!$A:$E,4,0)) | L28: =IF(VLOOKUP(A28,'Aux - pivots1'!$A:$E,5,0)=0, "",VLOOKUP(A28,'Aux - pivots1'!$A:$E,5,0))
A29: =E29&F29 -> PROCESSPROCESS_SUBPRODUCT_ID | B29: Pilar III | C29: Bens Imóveis - Output | D29: 2. Campo | E29: PROCESS | F29: PROCESS_SUBPRODUCT_ID | G29: =VLOOKUP(A29,Plano_V3!$A$26:$G$592,7,0) -> 1. Concluído | H29: 1. Concluído | J29: =IF(VLOOKUP(A29,'Aux - pivots1'!$A:$E,3,0)=0, "",VLOOKUP(A29,'Aux - pivots1'!$A:$E,3,0)) | K29: =IF(VLOOKUP(A29,'Aux - pivots1'!$A:$E,4,0)=0, "",VLOOKUP(A29,'Aux - pivots1'!$A:$E,4,0)) | L29: =IF(VLOOKUP(A29,'Aux - pivots1'!$A:$E,5,0)=0, "",VLOOKUP(A29,'Aux - pivots1'!$A:$E,5,0))
A30: =E30&F30 -> PROCESSGUARANTEE_TYPE_CODE | B30: Pilar III | C30: Bens Imóveis - Output | D30: 2. Campo | E30: PROCESS | F30: GUARANTEE_TYPE_CODE | G30: =VLOOKUP(A30,Plano_V3!$A$26:$G$592,7,0) -> 1. Concluído | H30: 1. Concluído | J30: =IF(VLOOKUP(A30,'Aux - pivots1'!$A:$E,3,0)=0, "",VLOOKUP(A30,'Aux - pivots1'!$A:$E,3,0)) | K30: =IF(VLOOKUP(A30,'Aux - pivots1'!$A:$E,4,0)=0, "",VLOOKUP(A30,'Aux - pivots1'!$A:$E,4,0)) | L30: =IF(VLOOKUP(A30,'Aux - pivots1'!$A:$E,5,0)=0, "",VLOOKUP(A30,'Aux - pivots1'!$A:$E,5,0))
A31: =E31&F31 -> PROCESSPROCESS_REFERENCE_CODE | B31: Pilar III | C31: Bens Imóveis - Output | D31: 2. Campo | E31: PROCESS | F31: PROCESS_REFERENCE_CODE | G31: =VLOOKUP(A31,Plano_V3!$A$26:$G$592,7,0) -> 1. Concluído | H31: 1. Concluído | J31: =IF(VLOOKUP(A31,'Aux - pivots1'!$A:$E,3,0)=0, "",VLOOKUP(A31,'Aux - pivots1'!$A:$E,3,0)) | K31: =IF(VLOOKUP(A31,'Aux - pivots1'!$A:$E,4,0)=0, "",VLOOKUP(A31,'Aux - pivots1'!$A:$E,4,0)) | L31: =IF(VLOOKUP(A31,'Aux - pivots1'!$A:$E,5,0)=0, "",VLOOKUP(A31,'Aux - pivots1'!$A:$E,5,0))
A32: =E32&F32 -> PROCESSPROCESS_START_DATE | B32: Pilar III | C32: Bens Imóveis - Output | D32: 2. Campo | E32: PROCESS | F32: PROCESS_START_DATE | G32: =VLOOKUP(A32,Plano_V3!$A$26:$G$592,7,0) -> 1. Concluído | H32: 1. Concluído | J32: =IF(VLOOKUP(A32,'Aux - pivots1'!$A:$E,3,0)=0, "",VLOOKUP(A32,'Aux - pivots1'!$A:$E,3,0)) | K32: =IF(VLOOKUP(A32,'Aux - pivots1'!$A:$E,4,0)=0, "",VLOOKUP(A32,'Aux - pivots1'!$A:$E,4,0)) | L32: =IF(VLOOKUP(A32,'Aux - pivots1'!$A:$E,5,0)=0, "",VLOOKUP(A32,'Aux - pivots1'!$A:$E,5,0))
A33: =E33&F33 -> PROCESSPROCESS_DUE_DATE | B33: Pilar III | C33: Bens Imóveis - Output | D33: 2. Campo | E33: PROCESS | F33: PROCESS_DUE_DATE | G33: =VLOOKUP(A33,Plano_V3!$A$26:$G$592,7,0) -> 1. Concluído | H33: 1. Concluído | J33: =IF(VLOOKUP(A33,'Aux - pivots1'!$A:$E,3,0)=0, "",VLOOKUP(A33,'Aux - pivots1'!$A:$E,3,0)) | K33: =IF(VLOOKUP(A33,'Aux - pivots1'!$A:$E,4,0)=0, "",VLOOKUP(A33,'Aux - pivots1'!$A:$E,4,0)) | L33: =IF(VLOOKUP(A33,'Aux - pivots1'!$A:$E,5,0)=0, "",VLOOKUP(A33,'Aux - pivots1'!$A:$E,5,0))
A34: =E34&F34 -> PROCESSmontante_eur | B34: Pilar III | C34: Bens Imóveis - Output | D34: 2. Campo | E34: PROCESS | F34: montante_eur | G34: =VLOOKUP(A34,Plano_V3!$A$26:$G$592,7,0) -> 0. Cancelado | H34: 0. Cancelado | I34: 19/07/2024: Campo eliminado do Modelo para garantir coerência com MUG | J34: =IF(VLOOKUP(A34,'Aux - pivots1'!$A:$E,3,0)=0, "",VLOOKUP(A34,'Aux - pivots1'!$A:$E,3,0)) | K34: =IF(VLOOKUP(A34,'Aux - pivots1'!$A:$E,4,0)=0, "",VLOOKUP(A34,'Aux - pivots1'!$A:$E,4,0)) | L34: =IF(VLOOKUP(A34,'Aux - pivots1'!$A:$E,5,0)=0, "",VLOOKUP(A34,'Aux - pivots1'!$A:$E,5,0))
A35: =E35&F35 -> PROCESSmontante_org | B35: Pilar III | C35: Bens Imóveis - Output | D35: 2. Campo | E35: PROCESS | F35: montante_org | G35: =VLOOKUP(A35,Plano_V3!$A$26:$G$592,7,0) -> 0. Cancelado | H35: 0. Cancelado | I35: 19/07/2024: Campo eliminado do Modelo para garantir coerência com MUG | J35: =IF(VLOOKUP(A35,'Aux - pivots1'!$A:$E,3,0)=0, "",VLOOKUP(A35,'Aux - pivots1'!$A:$E,3,0)) | K35: =IF(VLOOKUP(A35,'Aux - pivots1'!$A:$E,4,0)=0, "",VLOOKUP(A35,'Aux - pivots1'!$A:$E,4,0)) | L35: =IF(VLOOKUP(A35,'Aux - pivots1'!$A:$E,5,0)=0, "",VLOOKUP(A35,'Aux - pivots1'!$A:$E,5,0))
A36: =E36&F36 -> PROCESSorigem | B36: Pilar III | C36: Bens Imóveis - Output | D36: 2. Campo | E36: PROCESS | F36: origem | G36: =VLOOKUP(A36,Plano_V3!$A$26:$G$592,7,0) -> 0. Cancelado | H36: 0. Cancelado | I36: 08/08/2024: Campo eliminado de modo a garantir a coerência com o atualmente realizado no Modelo Único de Garantias. | J36: =IF(VLOOKUP(A36,'Aux - pivots1'!$A:$E,3,0)=0, "",VLOOKUP(A36,'Aux - pivots1'!$A:$E,3,0)) | K36: =IF(VLOOKUP(A36,'Aux - pivots1'!$A:$E,4,0)=0, "",VLOOKUP(A36,'Aux - pivots1'!$A:$E,4,0)) | L36: =IF(VLOOKUP(A36,'Aux - pivots1'!$A:$E,5,0)=0, "",VLOOKUP(A36,'Aux - pivots1'!$A:$E,5,0))
A37: =E37&F37 -> PROCESSDATA_DATE_PART | B37: Pilar III | C37: Bens Imóveis - Output | D37: 2. Campo | E37: PROCESS | F37: DATA_DATE_PART | G37: =VLOOKUP(A37,Plano_V3!$A$26:$G$592,7,0) -> 1. Concluído | H37: 1. Concluído | J37: =IF(VLOOKUP(A37,'Aux - pivots1'!$A:$E,3,0)=0, "",VLOOKUP(A37,'Aux - pivots1'!$A:$E,3,0)) | K37: =IF(VLOOKUP(A37,'Aux - pivots1'!$A:$E,4,0)=0, "",VLOOKUP(A37,'Aux - pivots1'!$A:$E,4,0)) | L37: =IF(VLOOKUP(A37,'Aux - pivots1'!$A:$E,5,0)=0, "",VLOOKUP(A37,'Aux - pivots1'!$A:$E,5,0))
A38: =E38&F38 -> RESPONSIBILITY_PROCESS_RELn.a. | B38: Pilar III | C38: Bens Imóveis - Output | D38: 1. Universo | E38: RESPONSIBILITY_PROCESS_REL | F38: n.a. | G38: =VLOOKUP(A38,Plano_V3!$A$26:$G$592,7,0) -> 1. Concluído | H38: 1. Concluído | J38: =IF(VLOOKUP(A38,'Aux - pivots1'!$A:$E,3,0)=0, "",VLOOKUP(A38,'Aux - pivots1'!$A:$E,3,0)) | K38: =IF(VLOOKUP(A38,'Aux - pivots1'!$A:$E,4,0)=0, "",VLOOKUP(A38,'Aux - pivots1'!$A:$E,4,0)) | L38: =IF(VLOOKUP(A38,'Aux - pivots1'!$A:$E,5,0)=0, "",VLOOKUP(A38,'Aux - pivots1'!$A:$E,5,0))
A39: =E39&F39 -> RESPONSIBILITY_PROCESS_RELPROCESS_BANK_ID | B39: Pilar III | C39: Bens Imóveis - Output | D39: 2. Campo | E39: RESPONSIBILITY_PROCESS_REL | F39: PROCESS_BANK_ID | G39: =VLOOKUP(A39,Plano_V3!$A$26:$G$592,7,0) -> 1. Concluído | H39: 1. Concluído | I39: 26/07/2024: Conclusão de testes ao universo MUG e GP. Adjudicados fora de âmbito deste projeto. | J39: =IF(VLOOKUP(A39,'Aux - pivots1'!$A:$E,3,0)=0, "",VLOOKUP(A39,'Aux - pivots1'!$A:$E,3,0)) | K39: =IF(VLOOKUP(A39,'Aux - pivots1'!$A:$E,4,0)=0, "",VLOOKUP(A39,'Aux - pivots1'!$A:$E,4,0)) | L39: =IF(VLOOKUP(A39,'Aux - pivots1'!$A:$E,5,0)=0, "",VLOOKUP(A39,'Aux - pivots1'!$A:$E,5,0))
A40: =E40&F40 -> RESPONSIBILITY_PROCESS_RELBANK_ID | B40: Pilar III | C40: Bens Imóveis - Output | D40: 2. Campo | E40: RESPONSIBILITY_PROCESS_REL | F40: BANK_ID | G40: =VLOOKUP(A40,Plano_V3!$A$26:$G$592,7,0) -> 1. Concluído | H40: 1. Concluído | I40: 26/07/2024: Conclusão de testes ao universo MUG e GP. Adjudicados fora de âmbito deste projeto. | J40: =IF(VLOOKUP(A40,'Aux - pivots1'!$A:$E,3,0)=0, "",VLOOKUP(A40,'Aux - pivots1'!$A:$E,3,0)) | K40: =IF(VLOOKUP(A40,'Aux - pivots1'!$A:$E,4,0)=0, "",VLOOKUP(A40,'Aux - pivots1'!$A:$E,4,0)) | L40: =IF(VLOOKUP(A40,'Aux - pivots1'!$A:$E,5,0)=0, "",VLOOKUP(A40,'Aux - pivots1'!$A:$E,5,0))
A41: =E41&F41 -> RESPONSIBILITY_PROCESS_RELPROCESS_BRANCH_CODE | B41: Pilar III | C41: Bens Imóveis - Output | D41: 2. Campo | E41: RESPONSIBILITY_PROCESS_REL | F41: PROCESS_BRANCH_CODE | G41: =VLOOKUP(A41,Plano_V3!$A$26:$G$592,7,0) -> 1. Concluído | H41: 1. Concluído | I41: 26/07/2024: Conclusão de testes ao universo MUG e GP. Adjudicados fora de âmbito deste projeto. | J41: =IF(VLOOKUP(A41,'Aux - pivots1'!$A:$E,3,0)=0, "",VLOOKUP(A41,'Aux - pivots1'!$A:$E,3,0)) | K41: =IF(VLOOKUP(A41,'Aux - pivots1'!$A:$E,4,0)=0, "",VLOOKUP(A41,'Aux - pivots1'!$A:$E,4,0)) | L41: =IF(VLOOKUP(A41,'Aux - pivots1'!$A:$E,5,0)=0, "",VLOOKUP(A41,'Aux - pivots1'!$A:$E,5,0))
A42: =E42&F42 -> RESPONSIBILITY_PROCESS_RELBRANCH_CODE | B42: Pilar III | C42: Bens Imóveis - Output | D42: 2. Campo | E42: RESPONSIBILITY_PROCESS_REL | F42: BRANCH_CODE | G42: =VLOOKUP(A42,Plano_V3!$A$26:$G$592,7,0) -> 1. Concluído | H42: 1. Concluído | I42: 26/07/2024: Conclusão de testes ao universo MUG e GP. Adjudicados fora de âmbito deste projeto. | J42: =IF(VLOOKUP(A42,'Aux - pivots1'!$A:$E,3,0)=0, "",VLOOKUP(A42,'Aux - pivots1'!$A:$E,3,0)) | K42: =IF(VLOOKUP(A42,'Aux - pivots1'!$A:$E,4,0)=0, "",VLOOKUP(A42,'Aux - pivots1'!$A:$E,4,0)) | L42: =IF(VLOOKUP(A42,'Aux - pivots1'!$A:$E,5,0)=0, "",VLOOKUP(A42,'Aux - pivots1'!$A:$E,5,0))
A43: =E43&F43 -> RESPONSIBILITY_PROCESS_RELCONTRACT_ID | B43: Pilar III | C43: Bens Imóveis - Output | D43: 2. Campo | E43: RESPONSIBILITY_PROCESS_REL | F43: CONTRACT_ID | G43: =VLOOKUP(A43,Plano_V3!$A$26:$G$592,7,0) -> 1. Concluído | H43: 1. Concluído | I43: 26/07/2024: Conclusão de testes ao universo MUG e GP. Adjudicados fora de âmbito deste projeto. | J43: =IF(VLOOKUP(A43,'Aux - pivots1'!$A:$E,3,0)=0, "",VLOOKUP(A43,'Aux - pivots1'!$A:$E,3,0)) | K43: =IF(VLOOKUP(A43,'Aux - pivots1'!$A:$E,4,0)=0, "",VLOOKUP(A43,'Aux - pivots1'!$A:$E,4,0)) | L43: =IF(VLOOKUP(A43,'Aux - pivots1'!$A:$E,5,0)=0, "",VLOOKUP(A43,'Aux - pivots1'!$A:$E,5,0))
A44: =E44&F44 -> RESPONSIBILITY_PROCESS_RELPROCESS_ACCOUNT_ID | B44: Pilar III | C44: Bens Imóveis - Output | D44: 2. Campo | E44: RESPONSIBILITY_PROCESS_REL | F44: PROCESS_ACCOUNT_ID | G44: =VLOOKUP(A44,Plano_V3!$A$26:$G$592,7,0) -> 1. Concluído | H44: 1. Concluído | I44: 26/07/2024: Conclusão de testes ao universo MUG e GP. Adjudicados fora de âmbito deste projeto. | J44: =IF(VLOOKUP(A44,'Aux - pivots1'!$A:$E,3,0)=0, "",VLOOKUP(A44,'Aux - pivots1'!$A:$E,3,0)) | K44: =IF(VLOOKUP(A44,'Aux - pivots1'!$A:$E,4,0)=0, "",VLOOKUP(A44,'Aux - pivots1'!$A:$E,4,0)) | L44: =IF(VLOOKUP(A44,'Aux - pivots1'!$A:$E,5,0)=0, "",VLOOKUP(A44,'Aux - pivots1'!$A:$E,5,0))
A45: =E45&F45 -> RESPONSIBILITY_PROCESS_RELREFERENCE_CODE | B45: Pilar III | C45: Bens Imóveis - Output | D45: 2. Campo | E45: RESPONSIBILITY_PROCESS_REL | F45: REFERENCE_CODE | G45: =VLOOKUP(A45,Plano_V3!$A$26:$G$592,7,0) -> 1. Concluído | H45: 1. Concluído | I45: 26/07/2024: Conclusão de testes ao universo MUG e GP. Adjudicados fora de âmbito deste projeto. | J45: =IF(VLOOKUP(A45,'Aux - pivots1'!$A:$E,3,0)=0, "",VLOOKUP(A45,'Aux - pivots1'!$A:$E,3,0)) | K45: =IF(VLOOKUP(A45,'Aux - pivots1'!$A:$E,4,0)=0, "",VLOOKUP(A45,'Aux - pivots1'!$A:$E,4,0)) | L45: =IF(VLOOKUP(A45,'Aux - pivots1'!$A:$E,5,0)=0, "",VLOOKUP(A45,'Aux - pivots1'!$A:$E,5,0))
A46: =E46&F46 -> RESPONSIBILITY_PROCESS_RELPURPOSE_CODE | B46: Pilar III | C46: Bens Imóveis - Output | D46: 2. Campo | E46: RESPONSIBILITY_PROCESS_REL | F46: PURPOSE_CODE | G46: =VLOOKUP(A46,Plano_V3!$A$26:$G$592,7,0) -> 1. Concluído | H46: 1. Concluído | J46: =IF(VLOOKUP(A46,'Aux - pivots1'!$A:$E,3,0)=0, "",VLOOKUP(A46,'Aux - pivots1'!$A:$E,3,0)) | K46: =IF(VLOOKUP(A46,'Aux - pivots1'!$A:$E,4,0)=0, "",VLOOKUP(A46,'Aux - pivots1'!$A:$E,4,0)) | L46: =IF(VLOOKUP(A46,'Aux - pivots1'!$A:$E,5,0)=0, "",VLOOKUP(A46,'Aux - pivots1'!$A:$E,5,0))
A47: =E47&F47 -> RESPONSIBILITY_PROCESS_RELINDIVIDUAL_OCCUPATION_CODE | B47: Pilar III | C47: Bens Imóveis - Output | D47: 2. Campo | E47: RESPONSIBILITY_PROCESS_REL | F47: INDIVIDUAL_OCCUPATION_CODE | G47: =VLOOKUP(A47,Plano_V3!$A$26:$G$592,7,0) -> 1. Concluído | H47: 1. Concluído | J47: =IF(VLOOKUP(A47,'Aux - pivots1'!$A:$E,3,0)=0, "",VLOOKUP(A47,'Aux - pivots1'!$A:$E,3,0)) | K47: =IF(VLOOKUP(A47,'Aux - pivots1'!$A:$E,4,0)=0, "",VLOOKUP(A47,'Aux - pivots1'!$A:$E,4,0)) | L47: =IF(VLOOKUP(A47,'Aux - pivots1'!$A:$E,5,0)=0, "",VLOOKUP(A47,'Aux - pivots1'!$A:$E,5,0))
A48: =E48&F48 -> RESPONSIBILITY_PROCESS_RELPRODUCT_ID | B48: Pilar III | C48: Bens Imóveis - Output | D48: 2. Campo | E48: RESPONSIBILITY_PROCESS_REL | F48: PRODUCT_ID | G48: =VLOOKUP(A48,Plano_V3!$A$26:$G$592,7,0) -> 1. Concluído | H48: 1. Concluído | J48: =IF(VLOOKUP(A48,'Aux - pivots1'!$A:$E,3,0)=0, "",VLOOKUP(A48,'Aux - pivots1'!$A:$E,3,0)) | K48: =IF(VLOOKUP(A48,'Aux - pivots1'!$A:$E,4,0)=0, "",VLOOKUP(A48,'Aux - pivots1'!$A:$E,4,0)) | L48: =IF(VLOOKUP(A48,'Aux - pivots1'!$A:$E,5,0)=0, "",VLOOKUP(A48,'Aux - pivots1'!$A:$E,5,0))
A49: =E49&F49 -> RESPONSIBILITY_PROCESS_RELcod_sit | B49: Pilar III | C49: Bens Imóveis - Output | D49: 2. Campo | E49: RESPONSIBILITY_PROCESS_REL | F49: cod_sit | G49: =VLOOKUP(A49,Plano_V3!$A$26:$G$592,7,0) -> 0. Cancelado | H49: 0. Cancelado | I49: 19/07/2024: Campo eliminado do Modelo para garantir coerência com MUG | J49: =IF(VLOOKUP(A49,'Aux - pivots1'!$A:$E,3,0)=0, "",VLOOKUP(A49,'Aux - pivots1'!$A:$E,3,0)) | K49: =IF(VLOOKUP(A49,'Aux - pivots1'!$A:$E,4,0)=0, "",VLOOKUP(A49,'Aux - pivots1'!$A:$E,4,0)) | L49: =IF(VLOOKUP(A49,'Aux - pivots1'!$A:$E,5,0)=0, "",VLOOKUP(A49,'Aux - pivots1'!$A:$E,5,0))
A50: =E50&F50 -> RESPONSIBILITY_PROCESS_RELSUBPRODUCT_ID | B50: Pilar III | C50: Bens Imóveis - Output | D50: 2. Campo | E50: RESPONSIBILITY_PROCESS_REL | F50: SUBPRODUCT_ID | G50: =VLOOKUP(A50,Plano_V3!$A$26:$G$592,7,0) -> 1. Concluído | H50: 1. Concluído | J50: =IF(VLOOKUP(A50,'Aux - pivots1'!$A:$E,3,0)=0, "",VLOOKUP(A50,'Aux - pivots1'!$A:$E,3,0)) | K50: =IF(VLOOKUP(A50,'Aux - pivots1'!$A:$E,4,0)=0, "",VLOOKUP(A50,'Aux - pivots1'!$A:$E,4,0)) | L50: =IF(VLOOKUP(A50,'Aux - pivots1'!$A:$E,5,0)=0, "",VLOOKUP(A50,'Aux - pivots1'!$A:$E,5,0))
A51: =E51&F51 -> RESPONSIBILITY_PROCESS_RELPROCESS_REFERENCE_CODE | B51: Pilar III | C51: Bens Imóveis - Output | D51: 2. Campo | E51: RESPONSIBILITY_PROCESS_REL | F51: PROCESS_REFERENCE_CODE | G51: =VLOOKUP(A51,Plano_V3!$A$26:$G$592,7,0) -> 1. Concluído | H51: 1. Concluído | J51: =IF(VLOOKUP(A51,'Aux - pivots1'!$A:$E,3,0)=0, "",VLOOKUP(A51,'Aux - pivots1'!$A:$E,3,0)) | K51: =IF(VLOOKUP(A51,'Aux - pivots1'!$A:$E,4,0)=0, "",VLOOKUP(A51,'Aux - pivots1'!$A:$E,4,0)) | L51: =IF(VLOOKUP(A51,'Aux - pivots1'!$A:$E,5,0)=0, "",VLOOKUP(A51,'Aux - pivots1'!$A:$E,5,0))
A52: =E52&F52 -> RESPONSIBILITY_PROCESS_RELEFFECTIVE_RELATION_END_DATE | B52: Pilar III | C52: Bens Imóveis - Output | D52: 2. Campo | E52: RESPONSIBILITY_PROCESS_REL | F52: EFFECTIVE_RELATION_END_DATE | G52: =VLOOKUP(A52,Plano_V3!$A$26:$G$592,7,0) -> 1. Concluído | H52: 1. Concluído | J52: =IF(VLOOKUP(A52,'Aux - pivots1'!$A:$E,3,0)=0, "",VLOOKUP(A52,'Aux - pivots1'!$A:$E,3,0)) | K52: =IF(VLOOKUP(A52,'Aux - pivots1'!$A:$E,4,0)=0, "",VLOOKUP(A52,'Aux - pivots1'!$A:$E,4,0)) | L52: =IF(VLOOKUP(A52,'Aux - pivots1'!$A:$E,5,0)=0, "",VLOOKUP(A52,'Aux - pivots1'!$A:$E,5,0))
A53: =E53&F53 -> RESPONSIBILITY_PROCESS_RELPROCESS_START_DATE | B53: Pilar III | C53: Bens Imóveis - Output | D53: 2. Campo | E53: RESPONSIBILITY_PROCESS_REL | F53: PROCESS_START_DATE | G53: =VLOOKUP(A53,Plano_V3!$A$26:$G$592,7,0) -> 1. Concluído | H53: 1. Concluído | J53: =IF(VLOOKUP(A53,'Aux - pivots1'!$A:$E,3,0)=0, "",VLOOKUP(A53,'Aux - pivots1'!$A:$E,3,0)) | K53: =IF(VLOOKUP(A53,'Aux - pivots1'!$A:$E,4,0)=0, "",VLOOKUP(A53,'Aux - pivots1'!$A:$E,4,0)) | L53: =IF(VLOOKUP(A53,'Aux - pivots1'!$A:$E,5,0)=0, "",VLOOKUP(A53,'Aux - pivots1'!$A:$E,5,0))
A54: =E54&F54 -> RESPONSIBILITY_PROCESS_RELPROCESS_DUE_DATE | B54: Pilar III | C54: Bens Imóveis - Output | D54: 2. Campo | E54: RESPONSIBILITY_PROCESS_REL | F54: PROCESS_DUE_DATE | G54: =VLOOKUP(A54,Plano_V3!$A$26:$G$592,7,0) -> 1. Concluído | H54: 1. Concluído | J54: =IF(VLOOKUP(A54,'Aux - pivots1'!$A:$E,3,0)=0, "",VLOOKUP(A54,'Aux - pivots1'!$A:$E,3,0)) | K54: =IF(VLOOKUP(A54,'Aux - pivots1'!$A:$E,4,0)=0, "",VLOOKUP(A54,'Aux - pivots1'!$A:$E,4,0)) | L54: =IF(VLOOKUP(A54,'Aux - pivots1'!$A:$E,5,0)=0, "",VLOOKUP(A54,'Aux - pivots1'!$A:$E,5,0))
A55: =E55&F55 -> RESPONSIBILITY_PROCESS_RELidetgar | B55: Pilar III | C55: Bens Imóveis - Output | D55: 2. Campo | E55: RESPONSIBILITY_PROCESS_REL | F55: idetgar | G55: =VLOOKUP(A55,Plano_V3!$A$26:$G$592,7,0) -> 0. Cancelado | H55: 0. Cancelado | I55: 19/07/2024: Campo eliminado do Modelo para garantir coerência com MUG | J55: =IF(VLOOKUP(A55,'Aux - pivots1'!$A:$E,3,0)=0, "",VLOOKUP(A55,'Aux - pivots1'!$A:$E,3,0)) | K55: =IF(VLOOKUP(A55,'Aux - pivots1'!$A:$E,4,0)=0, "",VLOOKUP(A55,'Aux - pivots1'!$A:$E,4,0)) | L55: =IF(VLOOKUP(A55,'Aux - pivots1'!$A:$E,5,0)=0, "",VLOOKUP(A55,'Aux - pivots1'!$A:$E,5,0))
A56: =E56&F56 -> RESPONSIBILITY_PROCESS_RELnum_prop | B56: Pilar III | C56: Bens Imóveis - Output | D56: 2. Campo | E56: RESPONSIBILITY_PROCESS_REL | F56: num_prop | G56: =VLOOKUP(A56,Plano_V3!$A$26:$G$592,7,0) -> 0. Cancelado | H56: 0. Cancelado | I56: 19/07/2024: Campo eliminado do Modelo para garantir coerência com MUG | J56: =IF(VLOOKUP(A56,'Aux - pivots1'!$A:$E,3,0)=0, "",VLOOKUP(A56,'Aux - pivots1'!$A:$E,3,0)) | K56: =IF(VLOOKUP(A56,'Aux - pivots1'!$A:$E,4,0)=0, "",VLOOKUP(A56,'Aux - pivots1'!$A:$E,4,0)) | L56: =IF(VLOOKUP(A56,'Aux - pivots1'!$A:$E,5,0)=0, "",VLOOKUP(A56,'Aux - pivots1'!$A:$E,5,0))
A57: =E57&F57 -> RESPONSIBILITY_PROCESS_RELSOURCE_CODE | B57: Pilar III | C57: Bens Imóveis - Output | D57: 2. Campo | E57: RESPONSIBILITY_PROCESS_REL | F57: SOURCE_CODE | G57: =VLOOKUP(A57,Plano_V3!$A$26:$G$592,7,0) -> 1. Concluído | H57: 1. Concluído | J57: =IF(VLOOKUP(A57,'Aux - pivots1'!$A:$E,3,0)=0, "",VLOOKUP(A57,'Aux - pivots1'!$A:$E,3,0)) | K57: =IF(VLOOKUP(A57,'Aux - pivots1'!$A:$E,4,0)=0, "",VLOOKUP(A57,'Aux - pivots1'!$A:$E,4,0)) | L57: =IF(VLOOKUP(A57,'Aux - pivots1'!$A:$E,5,0)=0, "",VLOOKUP(A57,'Aux - pivots1'!$A:$E,5,0))
A58: =E58&F58 -> RESPONSIBILITY_PROCESS_RELDATA_DATE_PART | B58: Pilar III | C58: Bens Imóveis - Output | D58: 2. Campo | E58: RESPONSIBILITY_PROCESS_REL | F58: DATA_DATE_PART | G58: =VLOOKUP(A58,Plano_V3!$A$26:$G$592,7,0) -> 1. Concluído | H58: 1. Concluído | J58: =IF(VLOOKUP(A58,'Aux - pivots1'!$A:$E,3,0)=0, "",VLOOKUP(A58,'Aux - pivots1'!$A:$E,3,0)) | K58: =IF(VLOOKUP(A58,'Aux - pivots1'!$A:$E,4,0)=0, "",VLOOKUP(A58,'Aux - pivots1'!$A:$E,4,0)) | L58: =IF(VLOOKUP(A58,'Aux - pivots1'!$A:$E,5,0)=0, "",VLOOKUP(A58,'Aux - pivots1'!$A:$E,5,0))
A59: =E59&F59 -> PROCESS_PROPERTY_RELn.a. | B59: Pilar III | C59: Bens Imóveis - Output | D59: 1. Universo | E59: PROCESS_PROPERTY_REL | F59: n.a. | G59: =VLOOKUP(A59,Plano_V3!$A$26:$G$592,7,0) -> 1. Concluído | H59: 1. Concluído | J59: =IF(VLOOKUP(A59,'Aux - pivots1'!$A:$E,3,0)=0, "",VLOOKUP(A59,'Aux - pivots1'!$A:$E,3,0)) | K59: =IF(VLOOKUP(A59,'Aux - pivots1'!$A:$E,4,0)=0, "",VLOOKUP(A59,'Aux - pivots1'!$A:$E,4,0)) | L59: =IF(VLOOKUP(A59,'Aux - pivots1'!$A:$E,5,0)=0, "",VLOOKUP(A59,'Aux - pivots1'!$A:$E,5,0))
A60: =E60&F60 -> PROCESS_PROPERTY_RELPROPERTY_BANK_ID | B60: Pilar III | C60: Bens Imóveis - Output | D60: 2. Campo | E60: PROCESS_PROPERTY_REL | F60: PROPERTY_BANK_ID | G60: =VLOOKUP(A60,Plano_V3!$A$26:$G$592,7,0) -> 1. Concluído | H60: 1. Concluído | J60: =IF(VLOOKUP(A60,'Aux - pivots1'!$A:$E,3,0)=0, "",VLOOKUP(A60,'Aux - pivots1'!$A:$E,3,0)) | K60: =IF(VLOOKUP(A60,'Aux - pivots1'!$A:$E,4,0)=0, "",VLOOKUP(A60,'Aux - pivots1'!$A:$E,4,0)) | L60: =IF(VLOOKUP(A60,'Aux - pivots1'!$A:$E,5,0)=0, "",VLOOKUP(A60,'Aux - pivots1'!$A:$E,5,0))
A61: =E61&F61 -> PROCESS_PROPERTY_RELPROCESS_BANK_ID | B61: Pilar III | C61: Bens Imóveis - Output | D61: 2. Campo | E61: PROCESS_PROPERTY_REL | F61: PROCESS_BANK_ID | G61: =VLOOKUP(A61,Plano_V3!$A$26:$G$592,7,0) -> 1. Concluído | H61: 1. Concluído | I61: 26/07/2024: Conclusão de testes ao universo MUG e GP. Adjudicados fora de âmbito deste projeto. | J61: =IF(VLOOKUP(A61,'Aux - pivots1'!$A:$E,3,0)=0, "",VLOOKUP(A61,'Aux - pivots1'!$A:$E,3,0)) | K61: =IF(VLOOKUP(A61,'Aux - pivots1'!$A:$E,4,0)=0, "",VLOOKUP(A61,'Aux - pivots1'!$A:$E,4,0)) | L61: =IF(VLOOKUP(A61,'Aux - pivots1'!$A:$E,5,0)=0, "",VLOOKUP(A61,'Aux - pivots1'!$A:$E,5,0))
A62: =E62&F62 -> PROCESS_PROPERTY_RELPROPERTY_BRANCH_CODE | B62: Pilar III | C62: Bens Imóveis - Output | D62: 2. Campo | E62: PROCESS_PROPERTY_REL | F62: PROPERTY_BRANCH_CODE | G62: =VLOOKUP(A62,Plano_V3!$A$26:$G$592,7,0) -> 1. Concluído | H62: 1. Concluído | I62: 26/07/2024: Conclusão de testes ao universo MUG e GP. Adjudicados fora de âmbito deste projeto. | J62: =IF(VLOOKUP(A62,'Aux - pivots1'!$A:$E,3,0)=0, "",VLOOKUP(A62,'Aux - pivots1'!$A:$E,3,0)) | K62: =IF(VLOOKUP(A62,'Aux - pivots1'!$A:$E,4,0)=0, "",VLOOKUP(A62,'Aux - pivots1'!$A:$E,4,0)) | L62: =IF(VLOOKUP(A62,'Aux - pivots1'!$A:$E,5,0)=0, "",VLOOKUP(A62,'Aux - pivots1'!$A:$E,5,0))
A63: =E63&F63 -> PROCESS_PROPERTY_RELPROCESS_BRANCH_CODE | B63: Pilar III | C63: Bens Imóveis - Output | D63: 2. Campo | E63: PROCESS_PROPERTY_REL | F63: PROCESS_BRANCH_CODE | G63: =VLOOKUP(A63,Plano_V3!$A$26:$G$592,7,0) -> 1. Concluído | H63: 1. Concluído | I63: 26/07/2024: Conclusão de testes ao universo MUG e GP. Adjudicados fora de âmbito deste projeto. | J63: =IF(VLOOKUP(A63,'Aux - pivots1'!$A:$E,3,0)=0, "",VLOOKUP(A63,'Aux - pivots1'!$A:$E,3,0)) | K63: =IF(VLOOKUP(A63,'Aux - pivots1'!$A:$E,4,0)=0, "",VLOOKUP(A63,'Aux - pivots1'!$A:$E,4,0)) | L63: =IF(VLOOKUP(A63,'Aux - pivots1'!$A:$E,5,0)=0, "",VLOOKUP(A63,'Aux - pivots1'!$A:$E,5,0))
A64: =E64&F64 -> PROCESS_PROPERTY_RELPROPERTY_CONTRACT_ID | B64: Pilar III | C64: Bens Imóveis - Output | D64: 2. Campo | E64: PROCESS_PROPERTY_REL | F64: PROPERTY_CONTRACT_ID | G64: =VLOOKUP(A64,Plano_V3!$A$26:$G$592,7,0) -> 1. Concluído | H64: 1. Concluído | I64: 26/07/2024: Conclusão de testes ao universo MUG e GP. Adjudicados fora de âmbito deste projeto. | J64: =IF(VLOOKUP(A64,'Aux - pivots1'!$A:$E,3,0)=0, "",VLOOKUP(A64,'Aux - pivots1'!$A:$E,3,0)) | K64: =IF(VLOOKUP(A64,'Aux - pivots1'!$A:$E,4,0)=0, "",VLOOKUP(A64,'Aux - pivots1'!$A:$E,4,0)) | L64: =IF(VLOOKUP(A64,'Aux - pivots1'!$A:$E,5,0)=0, "",VLOOKUP(A64,'Aux - pivots1'!$A:$E,5,0))
A65: =E65&F65 -> PROCESS_PROPERTY_RELPROCESS_ACCOUNT_ID | B65: Pilar III | C65: Bens Imóveis - Output | D65: 2. Campo | E65: PROCESS_PROPERTY_REL | F65: PROCESS_ACCOUNT_ID | G65: =VLOOKUP(A65,Plano_V3!$A$26:$G$592,7,0) -> 1. Concluído | H65: 1. Concluído | I65: 26/07/2024: Conclusão de testes ao universo MUG e GP. Adjudicados fora de âmbito deste projeto. | J65: =IF(VLOOKUP(A65,'Aux - pivots1'!$A:$E,3,0)=0, "",VLOOKUP(A65,'Aux - pivots1'!$A:$E,3,0)) | K65: =IF(VLOOKUP(A65,'Aux - pivots1'!$A:$E,4,0)=0, "",VLOOKUP(A65,'Aux - pivots1'!$A:$E,4,0)) | L65: =IF(VLOOKUP(A65,'Aux - pivots1'!$A:$E,5,0)=0, "",VLOOKUP(A65,'Aux - pivots1'!$A:$E,5,0))
A66: =E66&F66 -> PROCESS_PROPERTY_RELPROPERTY_REFERENCE_CODE | B66: Pilar III | C66: Bens Imóveis - Output | D66: 2. Campo | E66: PROCESS_PROPERTY_REL | F66: PROPERTY_REFERENCE_CODE | G66: =VLOOKUP(A66,Plano_V3!$A$26:$G$592,7,0) -> 1. Concluído | H66: 1. Concluído | J66: =IF(VLOOKUP(A66,'Aux - pivots1'!$A:$E,3,0)=0, "",VLOOKUP(A66,'Aux - pivots1'!$A:$E,3,0)) | K66: =IF(VLOOKUP(A66,'Aux - pivots1'!$A:$E,4,0)=0, "",VLOOKUP(A66,'Aux - pivots1'!$A:$E,4,0)) | L66: =IF(VLOOKUP(A66,'Aux - pivots1'!$A:$E,5,0)=0, "",VLOOKUP(A66,'Aux - pivots1'!$A:$E,5,0))
A67: =E67&F67 -> PROCESS_PROPERTY_RELPROCESS_REFERENCE_CODE | B67: Pilar III | C67: Bens Imóveis - Output | D67: 2. Campo | E67: PROCESS_PROPERTY_REL | F67: PROCESS_REFERENCE_CODE | G67: =VLOOKUP(A67,Plano_V3!$A$26:$G$592,7,0) -> 1. Concluído | H67: 1. Concluído | J67: =IF(VLOOKUP(A67,'Aux - pivots1'!$A:$E,3,0)=0, "",VLOOKUP(A67,'Aux - pivots1'!$A:$E,3,0)) | K67: =IF(VLOOKUP(A67,'Aux - pivots1'!$A:$E,4,0)=0, "",VLOOKUP(A67,'Aux - pivots1'!$A:$E,4,0)) | L67: =IF(VLOOKUP(A67,'Aux - pivots1'!$A:$E,5,0)=0, "",VLOOKUP(A67,'Aux - pivots1'!$A:$E,5,0))
A68: =E68&F68 -> PROCESS_PROPERTY_RELdata_assc | B68: Pilar III | C68: Bens Imóveis - Output | D68: 2. Campo | E68: PROCESS_PROPERTY_REL | F68: data_assc | G68: =VLOOKUP(A68,Plano_V3!$A$26:$G$592,7,0) -> 0. Cancelado | H68: 0. Cancelado | I68: 19/07/2024: Campo eliminado do Modelo para garantir coerência com MUG | J68: =IF(VLOOKUP(A68,'Aux - pivots1'!$A:$E,3,0)=0, "",VLOOKUP(A68,'Aux - pivots1'!$A:$E,3,0)) | K68: =IF(VLOOKUP(A68,'Aux - pivots1'!$A:$E,4,0)=0, "",VLOOKUP(A68,'Aux - pivots1'!$A:$E,4,0)) | L68: =IF(VLOOKUP(A68,'Aux - pivots1'!$A:$E,5,0)=0, "",VLOOKUP(A68,'Aux - pivots1'!$A:$E,5,0))
A69: =E69&F69 -> PROCESS_PROPERTY_RELSEIZED_PROPERTY_IND | B69: Pilar III | C69: Bens Imóveis - Output | D69: 2. Campo | E69: PROCESS_PROPERTY_REL | F69: SEIZED_PROPERTY_IND | G69: =VLOOKUP(A69,Plano_V3!$A$26:$G$592,7,0) -> 1. Concluído | H69: 1. Concluído | J69: =IF(VLOOKUP(A69,'Aux - pivots1'!$A:$E,3,0)=0, "",VLOOKUP(A69,'Aux - pivots1'!$A:$E,3,0)) | K69: =IF(VLOOKUP(A69,'Aux - pivots1'!$A:$E,4,0)=0, "",VLOOKUP(A69,'Aux - pivots1'!$A:$E,4,0)) | L69: =IF(VLOOKUP(A69,'Aux - pivots1'!$A:$E,5,0)=0, "",VLOOKUP(A69,'Aux - pivots1'!$A:$E,5,0))
A70: =E70&F70 -> PROCESS_PROPERTY_RELCOLLATERAL_PROPERTY_IND | B70: Pilar III | C70: Bens Imóveis - Output | D70: 2. Campo | E70: PROCESS_PROPERTY_REL | F70: COLLATERAL_PROPERTY_IND | G70: =VLOOKUP(A70,Plano_V3!$A$26:$G$592,7,0) -> 1. Concluído | H70: 1. Concluído | J70: =IF(VLOOKUP(A70,'Aux - pivots1'!$A:$E,3,0)=0, "",VLOOKUP(A70,'Aux - pivots1'!$A:$E,3,0)) | K70: =IF(VLOOKUP(A70,'Aux - pivots1'!$A:$E,4,0)=0, "",VLOOKUP(A70,'Aux - pivots1'!$A:$E,4,0)) | L70: =IF(VLOOKUP(A70,'Aux - pivots1'!$A:$E,5,0)=0, "",VLOOKUP(A70,'Aux - pivots1'!$A:$E,5,0))
A71: =E71&F71 -> PROCESS_PROPERTY_RELFINANCED_PROPERTY_IND | B71: Pilar III | C71: Bens Imóveis - Output | D71: 2. Campo | E71: PROCESS_PROPERTY_REL | F71: FINANCED_PROPERTY_IND | G71: =VLOOKUP(A71,Plano_V3!$A$26:$G$592,7,0) -> 1. Concluído | H71: 1. Concluído | J71: =IF(VLOOKUP(A71,'Aux - pivots1'!$A:$E,3,0)=0, "",VLOOKUP(A71,'Aux - pivots1'!$A:$E,3,0)) | K71: =IF(VLOOKUP(A71,'Aux - pivots1'!$A:$E,4,0)=0, "",VLOOKUP(A71,'Aux - pivots1'!$A:$E,4,0)) | L71: =IF(VLOOKUP(A71,'Aux - pivots1'!$A:$E,5,0)=0, "",VLOOKUP(A71,'Aux - pivots1'!$A:$E,5,0))
A72: =E72&F72 -> PROCESS_PROPERTY_RELOWNED_PROPERTY_IND | B72: Pilar III | C72: Bens Imóveis - Output | D72: 2. Campo | E72: PROCESS_PROPERTY_REL | F72: OWNED_PROPERTY_IND | G72: =VLOOKUP(A72,Plano_V3!$A$26:$G$592,7,0) -> 1. Concluído | H72: 1. Concluído | J72: =IF(VLOOKUP(A72,'Aux - pivots1'!$A:$E,3,0)=0, "",VLOOKUP(A72,'Aux - pivots1'!$A:$E,3,0)) | K72: =IF(VLOOKUP(A72,'Aux - pivots1'!$A:$E,4,0)=0, "",VLOOKUP(A72,'Aux - pivots1'!$A:$E,4,0)) | L72: =IF(VLOOKUP(A72,'Aux - pivots1'!$A:$E,5,0)=0, "",VLOOKUP(A72,'Aux - pivots1'!$A:$E,5,0))
A73: =E73&F73 -> PROCESS_PROPERTY_RELSOURCE_CODE | B73: Pilar III | C73: Bens Imóveis - Output | D73: 2. Campo | E73: PROCESS_PROPERTY_REL | F73: SOURCE_CODE | G73: =VLOOKUP(A73,Plano_V3!$A$26:$G$592,7,0) -> 1. Concluído | H73: 1. Concluído | J73: =IF(VLOOKUP(A73,'Aux - pivots1'!$A:$E,3,0)=0, "",VLOOKUP(A73,'Aux - pivots1'!$A:$E,3,0)) | K73: =IF(VLOOKUP(A73,'Aux - pivots1'!$A:$E,4,0)=0, "",VLOOKUP(A73,'Aux - pivots1'!$A:$E,4,0)) | L73: =IF(VLOOKUP(A73,'Aux - pivots1'!$A:$E,5,0)=0, "",VLOOKUP(A73,'Aux - pivots1'!$A:$E,5,0))
A74: =E74&F74 -> PROCESS_PROPERTY_RELDATA_DATE_PART | B74: Pilar III | C74: Bens Imóveis - Output | D74: 2. Campo | E74: PROCESS_PROPERTY_REL | F74: DATA_DATE_PART | G74: =VLOOKUP(A74,Plano_V3!$A$26:$G$592,7,0) -> 1. Concluído | H74: 1. Concluído | J74: =IF(VLOOKUP(A74,'Aux - pivots1'!$A:$E,3,0)=0, "",VLOOKUP(A74,'Aux - pivots1'!$A:$E,3,0)) | K74: =IF(VLOOKUP(A74,'Aux - pivots1'!$A:$E,4,0)=0, "",VLOOKUP(A74,'Aux - pivots1'!$A:$E,4,0)) | L74: =IF(VLOOKUP(A74,'Aux - pivots1'!$A:$E,5,0)=0, "",VLOOKUP(A74,'Aux - pivots1'!$A:$E,5,0))
A75: =E75&F75 -> PROPERTYn.a. | B75: Pilar III | C75: Bens Imóveis - Output | D75: 1. Universo | E75: PROPERTY | F75: n.a. | G75: =VLOOKUP(A75,Plano_V3!$A$26:$G$592,7,0) -> 1. Concluído | H75: 1. Concluído | J75: =IF(VLOOKUP(A75,'Aux - pivots1'!$A:$E,3,0)=0, "",VLOOKUP(A75,'Aux - pivots1'!$A:$E,3,0)) | K75: =IF(VLOOKUP(A75,'Aux - pivots1'!$A:$E,4,0)=0, "",VLOOKUP(A75,'Aux - pivots1'!$A:$E,4,0)) | L75: =IF(VLOOKUP(A75,'Aux - pivots1'!$A:$E,5,0)=0, "",VLOOKUP(A75,'Aux - pivots1'!$A:$E,5,0))
A76: =E76&F76 -> PROPERTYCONSTRUCTION_YEAR | B76: Pilar III | C76: Bens Imóveis - Output | D76: 2. Campo | E76: PROPERTY | F76: CONSTRUCTION_YEAR | G76: =VLOOKUP(A76,Plano_V3!$A$26:$G$592,7,0) -> 1. Concluído | H76: 1. Concluído | J76: =IF(VLOOKUP(A76,'Aux - pivots1'!$A:$E,3,0)=0, "",VLOOKUP(A76,'Aux - pivots1'!$A:$E,3,0)) | K76: =IF(VLOOKUP(A76,'Aux - pivots1'!$A:$E,4,0)=0, "",VLOOKUP(A76,'Aux - pivots1'!$A:$E,4,0)) | L76: =IF(VLOOKUP(A76,'Aux - pivots1'!$A:$E,5,0)=0, "",VLOOKUP(A76,'Aux - pivots1'!$A:$E,5,0))
A77: =E77&F77 -> PROPERTYNET_FLOOR_AREA | B77: Pilar III | C77: Bens Imóveis - Output | D77: 2. Campo | E77: PROPERTY | F77: NET_FLOOR_AREA | G77: =VLOOKUP(A77,Plano_V3!$A$26:$G$592,7,0) -> 1. Concluído | H77: 1. Concluído | J77: =IF(VLOOKUP(A77,'Aux - pivots1'!$A:$E,3,0)=0, "",VLOOKUP(A77,'Aux - pivots1'!$A:$E,3,0)) | K77: =IF(VLOOKUP(A77,'Aux - pivots1'!$A:$E,4,0)=0, "",VLOOKUP(A77,'Aux - pivots1'!$A:$E,4,0)) | L77: =IF(VLOOKUP(A77,'Aux - pivots1'!$A:$E,5,0)=0, "",VLOOKUP(A77,'Aux - pivots1'!$A:$E,5,0))
A78: =E78&F78 -> PROPERTYPROPERTY_BANK_ID | B78: Pilar III | C78: Bens Imóveis - Output | D78: 2. Campo | E78: PROPERTY | F78: PROPERTY_BANK_ID | G78: =VLOOKUP(A78,Plano_V3!$A$26:$G$592,7,0) -> 1. Concluído | H78: 1. Concluído | J78: =IF(VLOOKUP(A78,'Aux - pivots1'!$A:$E,3,0)=0, "",VLOOKUP(A78,'Aux - pivots1'!$A:$E,3,0)) | K78: =IF(VLOOKUP(A78,'Aux - pivots1'!$A:$E,4,0)=0, "",VLOOKUP(A78,'Aux - pivots1'!$A:$E,4,0)) | L78: =IF(VLOOKUP(A78,'Aux - pivots1'!$A:$E,5,0)=0, "",VLOOKUP(A78,'Aux - pivots1'!$A:$E,5,0))
A79: =E79&F79 -> PROPERTYPROPERTY_BRANCH_CODE | B79: Pilar III | C79: Bens Imóveis - Output | D79: 2. Campo | E79: PROPERTY | F79: PROPERTY_BRANCH_CODE | G79: =VLOOKUP(A79,Plano_V3!$A$26:$G$592,7,0) -> 1. Concluído | H79: 1. Concluído | J79: =IF(VLOOKUP(A79,'Aux - pivots1'!$A:$E,3,0)=0, "",VLOOKUP(A79,'Aux - pivots1'!$A:$E,3,0)) | K79: =IF(VLOOKUP(A79,'Aux - pivots1'!$A:$E,4,0)=0, "",VLOOKUP(A79,'Aux - pivots1'!$A:$E,4,0)) | L79: =IF(VLOOKUP(A79,'Aux - pivots1'!$A:$E,5,0)=0, "",VLOOKUP(A79,'Aux - pivots1'!$A:$E,5,0))
A80: =E80&F80 -> PROPERTYPROPERTY_CONTRACT_ID | B80: Pilar III | C80: Bens Imóveis - Output | D80: 2. Campo | E80: PROPERTY | F80: PROPERTY_CONTRACT_ID | G80: =VLOOKUP(A80,Plano_V3!$A$26:$G$592,7,0) -> 1. Concluído | H80: 1. Concluído | J80: =IF(VLOOKUP(A80,'Aux - pivots1'!$A:$E,3,0)=0, "",VLOOKUP(A80,'Aux - pivots1'!$A:$E,3,0)) | K80: =IF(VLOOKUP(A80,'Aux - pivots1'!$A:$E,4,0)=0, "",VLOOKUP(A80,'Aux - pivots1'!$A:$E,4,0)) | L80: =IF(VLOOKUP(A80,'Aux - pivots1'!$A:$E,5,0)=0, "",VLOOKUP(A80,'Aux - pivots1'!$A:$E,5,0))
... A83: =E83&F83 -> PROPERTYAPPRAISAL_CODE | B83: Pilar III | C83: Bens Imóveis - Output | D83: 2. Campo | E83: PROPERTY | F83: APPRAISAL_CODE | G83: =VLOOKUP(A83,Plano_V3!$A$26:$G$592,7,0) -> 1. Concluído | H83: 1. Concluído | J83: =IF(VLOOKUP(A83,'Aux - pivots1'!$A:$E,3,0)=0, "",VLOOKUP(A83,'Aux - pivots1'!$A:$E,3,0)) | K83: =IF(VLOOKUP(A83,'Aux - pivots1'!$A:$E,4,0)=0, "",VLOOKUP(A83,'Aux - pivots1'!$A:$E,4,0)) | L83: =IF(VLOOKUP(A83,'Aux - pivots1'!$A:$E,5,0)=0, "",VLOOKUP(A83,'Aux - pivots1'!$A:$E,5,0))
A84: =E84&F84 -> PROPERTYcod_bem | B84: Pilar III | C84: Bens Imóveis - Output | D84: 2. Campo | E84: PROPERTY | F84: cod_bem | G84: =VLOOKUP(A84,Plano_V3!$A$26:$G$592,7,0) -> 0. Cancelado | H84: 0. Cancelado | I84: 19/07/2024: Campo eliminado do Modelo para garantir coerência com MUG | J84: =IF(VLOOKUP(A84,'Aux - pivots1'!$A:$E,3,0)=0, "",VLOOKUP(A84,'Aux - pivots1'!$A:$E,3,0)) | K84: =IF(VLOOKUP(A84,'Aux - pivots1'!$A:$E,4,0)=0, "",VLOOKUP(A84,'Aux - pivots1'!$A:$E,4,0)) | L84: =IF(VLOOKUP(A84,'Aux - pivots1'!$A:$E,5,0)=0, "",VLOOKUP(A84,'Aux - pivots1'!$A:$E,5,0))
A85: =E85&F85 -> PROPERTYDISTRICT_MUNICIP_PARISH_CODE | B85: Pilar III | C85: Bens Imóveis - Output | D85: 2. Campo | E85: PROPERTY | F85: DISTRICT_MUNICIP_PARISH_CODE | G85: =VLOOKUP(A85,Plano_V3!$A$26:$G$592,7,0) -> 1. Concluído | H85: 1. Concluído | J85: =IF(VLOOKUP(A85,'Aux - pivots1'!$A:$E,3,0)=0, "",VLOOKUP(A85,'Aux - pivots1'!$A:$E,3,0)) | K85: =IF(VLOOKUP(A85,'Aux - pivots1'!$A:$E,4,0)=0, "",VLOOKUP(A85,'Aux - pivots1'!$A:$E,4,0)) | L85: =IF(VLOOKUP(A85,'Aux - pivots1'!$A:$E,5,0)=0, "",VLOOKUP(A85,'Aux - pivots1'!$A:$E,5,0))
A86: =E86&F86 -> PROPERTYPROPERTY_PURPOSE_CODE | B86: Pilar III | C86: Bens Imóveis - Output | D86: 2. Campo | E86: PROPERTY | F86: PROPERTY_PURPOSE_CODE | G86: =VLOOKUP(A86,Plano_V3!$A$26:$G$592,7,0) -> 1. Concluído | H86: 1. Concluído | J86: =IF(VLOOKUP(A86,'Aux - pivots1'!$A:$E,3,0)=0, "",VLOOKUP(A86,'Aux - pivots1'!$A:$E,3,0)) | K86: =IF(VLOOKUP(A86,'Aux - pivots1'!$A:$E,4,0)=0, "",VLOOKUP(A86,'Aux - pivots1'!$A:$E,4,0)) | L86: =IF(VLOOKUP(A86,'Aux - pivots1'!$A:$E,5,0)=0, "",VLOOKUP(A86,'Aux - pivots1'!$A:$E,5,0))
A87: =E87&F87 -> PROPERTYPROPERTY_LIFETIME_CODE | B87: Pilar III | C87: Bens Imóveis - Output | D87: 2. Campo | E87: PROPERTY | F87: PROPERTY_LIFETIME_CODE | G87: =VLOOKUP(A87,Plano_V3!$A$26:$G$592,7,0) -> 1. Concluído | H87: 1. Concluído | J87: =IF(VLOOKUP(A87,'Aux - pivots1'!$A:$E,3,0)=0, "",VLOOKUP(A87,'Aux - pivots1'!$A:$E,3,0)) | K87: =IF(VLOOKUP(A87,'Aux - pivots1'!$A:$E,4,0)=0, "",VLOOKUP(A87,'Aux - pivots1'!$A:$E,4,0)) | L87: =IF(VLOOKUP(A87,'Aux - pivots1'!$A:$E,5,0)=0, "",VLOOKUP(A87,'Aux - pivots1'!$A:$E,5,0))
A88: =E88&F88 -> PROPERTYADDRESS_CODE | B88: Pilar III | C88: Bens Imóveis - Output | D88: 2. Campo | E88: PROPERTY | F88: ADDRESS_CODE | G88: =VLOOKUP(A88,Plano_V3!$A$26:$G$592,7,0) -> 1. Concluído | H88: 1. Concluído | J88: =IF(VLOOKUP(A88,'Aux - pivots1'!$A:$E,3,0)=0, "",VLOOKUP(A88,'Aux - pivots1'!$A:$E,3,0)) | K88: =IF(VLOOKUP(A88,'Aux - pivots1'!$A:$E,4,0)=0, "",VLOOKUP(A88,'Aux - pivots1'!$A:$E,4,0)) | L88: =IF(VLOOKUP(A88,'Aux - pivots1'!$A:$E,5,0)=0, "",VLOOKUP(A88,'Aux - pivots1'!$A:$E,5,0))
A89: =E89&F89 -> PROPERTYCOUNTRY_CODE | B89: Pilar III | C89: Bens Imóveis - Output | D89: 2. Campo | E89: PROPERTY | F89: COUNTRY_CODE | G89: =VLOOKUP(A89,Plano_V3!$A$26:$G$592,7,0) -> 1. Concluído | H89: 1. Concluído | J89: =IF(VLOOKUP(A89,'Aux - pivots1'!$A:$E,3,0)=0, "",VLOOKUP(A89,'Aux - pivots1'!$A:$E,3,0)) | K89: =IF(VLOOKUP(A89,'Aux - pivots1'!$A:$E,4,0)=0, "",VLOOKUP(A89,'Aux - pivots1'!$A:$E,4,0)) | L89: =IF(VLOOKUP(A89,'Aux - pivots1'!$A:$E,5,0)=0, "",VLOOKUP(A89,'Aux - pivots1'!$A:$E,5,0))
A90: =E90&F90 -> PROPERTYPOSTAL_CODE | B90: Pilar III | C90: Bens Imóveis - Output | D90: 2. Campo | E90: PROPERTY | F90: POSTAL_CODE | G90: =VLOOKUP(A90,Plano_V3!$A$26:$G$592,7,0) -> 1. Concluído | H90: 1. Concluído | J90: =IF(VLOOKUP(A90,'Aux - pivots1'!$A:$E,3,0)=0, "",VLOOKUP(A90,'Aux - pivots1'!$A:$E,3,0)) | K90: =IF(VLOOKUP(A90,'Aux - pivots1'!$A:$E,4,0)=0, "",VLOOKUP(A90,'Aux - pivots1'!$A:$E,4,0)) | L90: =IF(VLOOKUP(A90,'Aux - pivots1'!$A:$E,5,0)=0, "",VLOOKUP(A90,'Aux - pivots1'!$A:$E,5,0))
A91: =E91&F91 -> PROPERTYPROPERTY_TYPE_CODE | B91: Pilar III | C91: Bens Imóveis - Output | D91: 2. Campo | E91: PROPERTY | F91: PROPERTY_TYPE_CODE | G91: =VLOOKUP(A91,Plano_V3!$A$26:$G$592,7,0) -> 1. Concluído | H91: 1. Concluído | J91: =IF(VLOOKUP(A91,'Aux - pivots1'!$A:$E,3,0)=0, "",VLOOKUP(A91,'Aux - pivots1'!$A:$E,3,0)) | K91: =IF(VLOOKUP(A91,'Aux - pivots1'!$A:$E,4,0)=0, "",VLOOKUP(A91,'Aux - pivots1'!$A:$E,4,0)) | L91: =IF(VLOOKUP(A91,'Aux - pivots1'!$A:$E,5,0)=0, "",VLOOKUP(A91,'Aux - pivots1'!$A:$E,5,0))
A92: =E92&F92 -> PROPERTYLAST_APPRAISAL_DATE | B92: Pilar III | C92: Bens Imóveis - Output | D92: 2. Campo | E92: PROPERTY | F92: LAST_APPRAISAL_DATE | G92: =VLOOKUP(A92,Plano_V3!$A$26:$G$592,7,0) -> 1. Concluído | H92: 1. Concluído | J92: =IF(VLOOKUP(A92,'Aux - pivots1'!$A:$E,3,0)=0, "",VLOOKUP(A92,'Aux - pivots1'!$A:$E,3,0)) | K92: =IF(VLOOKUP(A92,'Aux - pivots1'!$A:$E,4,0)=0, "",VLOOKUP(A92,'Aux - pivots1'!$A:$E,4,0)) | L92: =IF(VLOOKUP(A92,'Aux - pivots1'!$A:$E,5,0)=0, "",VLOOKUP(A92,'Aux - pivots1'!$A:$E,5,0))
A93: =E93&F93 -> PROPERTYUSAGE_PERMIT_START_DATE | B93: Pilar III | C93: Bens Imóveis - Output | D93: 2. Campo | E93: PROPERTY | F93: USAGE_PERMIT_START_DATE | G93: =VLOOKUP(A93,Plano_V3!$A$26:$G$592,7,0) -> 1. Concluído | H93: 1. Concluído | J93: =IF(VLOOKUP(A93,'Aux - pivots1'!$A:$E,3,0)=0, "",VLOOKUP(A93,'Aux - pivots1'!$A:$E,3,0)) | K93: =IF(VLOOKUP(A93,'Aux - pivots1'!$A:$E,4,0)=0, "",VLOOKUP(A93,'Aux - pivots1'!$A:$E,4,0)) | L93: =IF(VLOOKUP(A93,'Aux - pivots1'!$A:$E,5,0)=0, "",VLOOKUP(A93,'Aux - pivots1'!$A:$E,5,0))
A94: =E94&F94 -> PROPERTYCONSERVATORY_REG_FILE_ID | B94: Pilar III | C94: Bens Imóveis - Output | D94: 2. Campo | E94: PROPERTY | F94: CONSERVATORY_REG_FILE_ID | G94: =VLOOKUP(A94,Plano_V3!$A$26:$G$592,7,0) -> 1. Concluído | H94: 1. Concluído | J94: =IF(VLOOKUP(A94,'Aux - pivots1'!$A:$E,3,0)=0, "",VLOOKUP(A94,'Aux - pivots1'!$A:$E,3,0)) | K94: =IF(VLOOKUP(A94,'Aux - pivots1'!$A:$E,4,0)=0, "",VLOOKUP(A94,'Aux - pivots1'!$A:$E,4,0)) | L94: =IF(VLOOKUP(A94,'Aux - pivots1'!$A:$E,5,0)=0, "",VLOOKUP(A94,'Aux - pivots1'!$A:$E,5,0))
A95: =E95&F95 -> PROPERTYFLOOR_NUMBER | B95: Pilar III | C95: Bens Imóveis - Output | D95: 2. Campo | E95: PROPERTY | F95: FLOOR_NUMBER | G95: =VLOOKUP(A95,Plano_V3!$A$26:$G$592,7,0) -> 1. Concluído | H95: 1. Concluído | J95: =IF(VLOOKUP(A95,'Aux - pivots1'!$A:$E,3,0)=0, "",VLOOKUP(A95,'Aux - pivots1'!$A:$E,3,0)) | K95: =IF(VLOOKUP(A95,'Aux - pivots1'!$A:$E,4,0)=0, "",VLOOKUP(A95,'Aux - pivots1'!$A:$E,4,0)) | L95: =IF(VLOOKUP(A95,'Aux - pivots1'!$A:$E,5,0)=0, "",VLOOKUP(A95,'Aux - pivots1'!$A:$E,5,0))
A96: =E96&F96 -> PROPERTYLOCALITY | B96: Pilar III | C96: Bens Imóveis - Output | D96: 2. Campo | E96: PROPERTY | F96: LOCALITY | G96: =VLOOKUP(A96,Plano_V3!$A$26:$G$592,7,0) -> 1. Concluído | H96: 1. Concluído | J96: =IF(VLOOKUP(A96,'Aux - pivots1'!$A:$E,3,0)=0, "",VLOOKUP(A96,'Aux - pivots1'!$A:$E,3,0)) | K96: =IF(VLOOKUP(A96,'Aux - pivots1'!$A:$E,4,0)=0, "",VLOOKUP(A96,'Aux - pivots1'!$A:$E,4,0)) | L96: =IF(VLOOKUP(A96,'Aux - pivots1'!$A:$E,5,0)=0, "",VLOOKUP(A96,'Aux - pivots1'!$A:$E,5,0))
... A102: =E102&F102 -> PROPERTYPROPERTY_NUMBER | B102: Pilar III | C102: Bens Imóveis - Output | D102: 2. Campo | E102: PROPERTY | F102: PROPERTY_NUMBER | G102: =VLOOKUP(A102,Plano_V3!$A$26:$G$592,7,0) -> 1. Concluído | H102: 1. Concluído | J102: =IF(VLOOKUP(A102,'Aux - pivots1'!$A:$E,3,0)=0, "",VLOOKUP(A102,'Aux - pivots1'!$A:$E,3,0)) | K102: =IF(VLOOKUP(A102,'Aux - pivots1'!$A:$E,4,0)=0, "",VLOOKUP(A102,'Aux - pivots1'!$A:$E,4,0)) | L102: =IF(VLOOKUP(A102,'Aux - pivots1'!$A:$E,5,0)=0, "",VLOOKUP(A102,'Aux - pivots1'!$A:$E,5,0))
A103: =E103&F103 -> PROPERTYOrigem | B103: Pilar III | C103: Bens Imóveis - Output | D103: 2. Campo | E103: PROPERTY | F103: Origem | G103: =VLOOKUP(A103,Plano_V3!$A$26:$G$592,7,0) -> 0. Cancelado | H103: 0. Cancelado | I103: 08/08/2024: Campo eliminado de modo a garantir a coerência com o atualmente realizado no Modelo Único de Garantias. | J103: =IF(VLOOKUP(A103,'Aux - pivots1'!$A:$E,3,0)=0, "",VLOOKUP(A103,'Aux - pivots1'!$A:$E,3,0)) | K103: =IF(VLOOKUP(A103,'Aux - pivots1'!$A:$E,4,0)=0, "",VLOOKUP(A103,'Aux - pivots1'!$A:$E,4,0)) | L103: =IF(VLOOKUP(A103,'Aux - pivots1'!$A:$E,5,0)=0, "",VLOOKUP(A103,'Aux - pivots1'!$A:$E,5,0))
A104: =E104&F104 -> PROPERTYCURRENT_CONSTRUCTION_PCT | B104: Pilar III | C104: Bens Imóveis - Output | D104: 2. Campo | E104: PROPERTY | F104: CURRENT_CONSTRUCTION_PCT | G104: =VLOOKUP(A104,Plano_V3!$A$26:$G$592,7,0) -> 1. Concluído | H104: 1. Concluído | I104: 22/07/2024: Entrega de campo para testes | J104: =IF(VLOOKUP(A104,'Aux - pivots1'!$A:$E,3,0)=0, "",VLOOKUP(A104,'Aux - pivots1'!$A:$E,3,0)) -> 45491 | K104: =IF(VLOOKUP(A104,'Aux - pivots1'!$A:$E,4,0)=0, "",VLOOKUP(A104,'Aux - pivots1'!$A:$E,4,0)) -> 45495 | L104: =IF(VLOOKUP(A104,'Aux - pivots1'!$A:$E,5,0)=0, "",VLOOKUP(A104,'Aux - pivots1'!$A:$E,5,0)) -> 45495
A105: =E105&F105 -> PROPERTYCONSTRUCTION_COMPLETED_PCT | B105: Pilar III | C105: Bens Imóveis - Output | D105: 2. Campo | E105: PROPERTY | F105: CONSTRUCTION_COMPLETED_PCT | G105: =VLOOKUP(A105,Plano_V3!$A$26:$G$592,7,0) -> 1. Concluído | H105: 1. Concluído | I105: 22/07/2024: Entrega de campo para testes | J105: =IF(VLOOKUP(A105,'Aux - pivots1'!$A:$E,3,0)=0, "",VLOOKUP(A105,'Aux - pivots1'!$A:$E,3,0)) -> 45491 | K105: =IF(VLOOKUP(A105,'Aux - pivots1'!$A:$E,4,0)=0, "",VLOOKUP(A105,'Aux - pivots1'!$A:$E,4,0)) -> 45495 | L105: =IF(VLOOKUP(A105,'Aux - pivots1'!$A:$E,5,0)=0, "",VLOOKUP(A105,'Aux - pivots1'!$A:$E,5,0)) -> 45495
A106: =E106&F106 -> PROPERTYDATA_DATE_PART | B106: Pilar III | C106: Bens Imóveis - Output | D106: 2. Campo | E106: PROPERTY | F106: DATA_DATE_PART | G106: =VLOOKUP(A106,Plano_V3!$A$26:$G$592,7,0) -> 1. Concluído | H106: 1. Concluído | J106: =IF(VLOOKUP(A106,'Aux - pivots1'!$A:$E,3,0)=0, "",VLOOKUP(A106,'Aux - pivots1'!$A:$E,3,0)) | K106: =IF(VLOOKUP(A106,'Aux - pivots1'!$A:$E,4,0)=0, "",VLOOKUP(A106,'Aux - pivots1'!$A:$E,4,0)) | L106: =IF(VLOOKUP(A106,'Aux - pivots1'!$A:$E,5,0)=0, "",VLOOKUP(A106,'Aux - pivots1'!$A:$E,5,0))
A107: =E107&F107 -> PROPERTYCGARANT_BEM | B107: Pilar III | C107: Bens Imóveis - Output | D107: 2. Campo | E107: PROPERTY | F107: CGARANT_BEM | G107: =VLOOKUP(A107,Plano_V3!$A$26:$G$592,7,0) -> 6. Em implementação (re-especificação) | H107: 6. Em implementação (re-especificação) | J107: =IF(VLOOKUP(A107,'Aux - pivots1'!$A:$E,3,0)=0, "",VLOOKUP(A107,'Aux - pivots1'!$A:$E,3,0)) | K107: =IF(VLOOKUP(A107,'Aux - pivots1'!$A:$E,4,0)=0, "",VLOOKUP(A107,'Aux - pivots1'!$A:$E,4,0)) | L107: =IF(VLOOKUP(A107,'Aux - pivots1'!$A:$E,5,0)=0, "",VLOOKUP(A107,'Aux - pivots1'!$A:$E,5,0))
A108: =E108&F108 -> PROPERTYURBANIZATION | B108: Pilar III | C108: Bens Imóveis - Output | D108: 2. Campo | E108: PROPERTY | F108: URBANIZATION | G108: =VLOOKUP(A108,Plano_V3!$A$26:$G$592,7,0) -> 1. Concluído | H108: 1. Concluído | J108: =IF(VLOOKUP(A108,'Aux - pivots1'!$A:$E,3,0)=0, "",VLOOKUP(A108,'Aux - pivots1'!$A:$E,3,0)) | K108: =IF(VLOOKUP(A108,'Aux - pivots1'!$A:$E,4,0)=0, "",VLOOKUP(A108,'Aux - pivots1'!$A:$E,4,0)) | L108: =IF(VLOOKUP(A108,'Aux - pivots1'!$A:$E,5,0)=0, "",VLOOKUP(A108,'Aux - pivots1'!$A:$E,5,0))
A109: =E109&F109 -> PROPERTY_ENERGY_CERTIFICATEn.a. | B109: Pilar III | C109: Bens Imóveis - Output | D109: 1. Universo | E109: PROPERTY_ENERGY_CERTIFICATE | F109: n.a. | G109: =VLOOKUP(A109,Plano_V3!$A$26:$G$592,7,0) -> 1. Concluído | H109: 1. Concluído | J109: =IF(VLOOKUP(A109,'Aux - pivots1'!$A:$E,3,0)=0, "",VLOOKUP(A109,'Aux - pivots1'!$A:$E,3,0)) | K109: =IF(VLOOKUP(A109,'Aux - pivots1'!$A:$E,4,0)=0, "",VLOOKUP(A109,'Aux - pivots1'!$A:$E,4,0)) | L109: =IF(VLOOKUP(A109,'Aux - pivots1'!$A:$E,5,0)=0, "",VLOOKUP(A109,'Aux - pivots1'!$A:$E,5,0))
A110: =E110&F110 -> PROPERTY_ENERGY_CERTIFICATEPROPERTY_BANK_ID | B110: Pilar III | C110: Bens Imóveis - Output | D110: 2. Campo | E110: PROPERTY_ENERGY_CERTIFICATE | F110: PROPERTY_BANK_ID | G110: =VLOOKUP(A110,Plano_V3!$A$26:$G$592,7,0) -> 1. Concluído | H110: 1. Concluído | J110: =IF(VLOOKUP(A110,'Aux - pivots1'!$A:$E,3,0)=0, "",VLOOKUP(A110,'Aux - pivots1'!$A:$E,3,0)) | K110: =IF(VLOOKUP(A110,'Aux - pivots1'!$A:$E,4,0)=0, "",VLOOKUP(A110,'Aux - pivots1'!$A:$E,4,0)) | L110: =IF(VLOOKUP(A110,'Aux - pivots1'!$A:$E,5,0)=0, "",VLOOKUP(A110,'Aux - pivots1'!$A:$E,5,0))
A111: =E111&F111 -> PROPERTY_ENERGY_CERTIFICATEPROPERTY_BRANCH_CODE | B111: Pilar III | C111: Bens Imóveis - Output | D111: 2. Campo | E111: PROPERTY_ENERGY_CERTIFICATE | F111: PROPERTY_BRANCH_CODE | G111: =VLOOKUP(A111,Plano_V3!$A$26:$G$592,7,0) -> 1. Concluído | H111: 1. Concluído | J111: =IF(VLOOKUP(A111,'Aux - pivots1'!$A:$E,3,0)=0, "",VLOOKUP(A111,'Aux - pivots1'!$A:$E,3,0)) | K111: =IF(VLOOKUP(A111,'Aux - pivots1'!$A:$E,4,0)=0, "",VLOOKUP(A111,'Aux - pivots1'!$A:$E,4,0)) | L111: =IF(VLOOKUP(A111,'Aux - pivots1'!$A:$E,5,0)=0, "",VLOOKUP(A111,'Aux - pivots1'!$A:$E,5,0))
A112: =E112&F112 -> PROPERTY_ENERGY_CERTIFICATEPROPERTY_CONTRACT_ID | B112: Pilar III | C112: Bens Imóveis - Output | D112: 2. Campo | E112: PROPERTY_ENERGY_CERTIFICATE | F112: PROPERTY_CONTRACT_ID | G112: =VLOOKUP(A112,Plano_V3!$A$26:$G$592,7,0) -> 1. Concluído | H112: 1. Concluído | J112: =IF(VLOOKUP(A112,'Aux - pivots1'!$A:$E,3,0)=0, "",VLOOKUP(A112,'Aux - pivots1'!$A:$E,3,0)) | K112: =IF(VLOOKUP(A112,'Aux - pivots1'!$A:$E,4,0)=0, "",VLOOKUP(A112,'Aux - pivots1'!$A:$E,4,0)) | L112: =IF(VLOOKUP(A112,'Aux - pivots1'!$A:$E,5,0)=0, "",VLOOKUP(A112,'Aux - pivots1'!$A:$E,5,0))
...

Sheet Plano_V3
B6: Re-testes - input | D6: 0.2 | R6: =R7-R10 -> 3 | S6: =S7-S10 -> 3 | T6: =T7-T10 -> 3 | U6: =U7-U10 -> 3 | V6: =V7-V10 -> 3 | W6: =W7-W10 -> 0 | X6: =X7-X10 -> 0 | Y6: =Y7-Y10 -> 0 | ... ES6: =ES7-ES10 -> 0
B7: Re-testes - output | D7: =50%*25% -> 0.125 | Q7: =AVERAGE(R7:EQ7) -> 2.4923077 | R7: 3 | S7: 3 | T7: 3 | U7: 3 | V7: 3 | W7: 2 | X7: 2 | Y7: 2 | Z7: 2 | AA7: 2 | AB7: 2 | AC7: 2 | AD7: 2 | AE7: 2 | AF7: 2 | AG7: 2 | AH7: 2 | AI7: 1 | AJ7: 1 | AK7: 1 | AL7: 3 | AM7: 3 | AN7: 3 | AO7: 3 | AP7: 2 | AQ7: 3 | AR7: 3 | AS7: 3 | AT7: 3 | AU7: 3 | AV7: 2 | AW7: 2 | AX7: 2 | AY7: 0 | AZ7: 1 | BA7: 1 | BB7: 0 | BC7: 1 | BD7: 1 | BE7: 1 | BF7: 2 | BG7: 2 | BH7: 2 | BI7: 2 | BJ7: 2 | BK7: 2 | BL7: 2 | BM7: 2 | BN7: 2 | BO7: 2 | BP7: 2 | BQ7: 2 | BR7: 2 | BS7: 2 | BT7: 2 | BU7: 3 | BV7: 3 | BW7: 3 | BX7: 3 | BY7: 3 | BZ7: 3 | CA7: 3 | CB7: 3 | CC7: 3 | CD7: 3 | CE7: 3 | CF7: 3 | CG7: 3 | CH7: 3 | CI7: 3 | CJ7: 3 | CK7: 3 | CL7: 3 | CM7: 3 | CN7: 3 | CO7: 3 | CP7: 3 | CQ7: 3 | CR7: 3 | CS7: 3 | CT7: 3 | CU7: 3 | CV7: 3 | CW7: 3 | CX7: 3 | CY7: 3 | CZ7: 3 | DA7: 3 | DB7: 3 | DC7: 3 | DD7: 3 | DE7: 3 | DF7: 3 | DG7: 3 | DH7: 3 | DI7: 3 | DJ7: 3 | DK7: 3 | DL7: 3 | DM7: 3 | DN7: 3 | DO7: 3 | DP7: 3 | DQ7: 3 | DR7: 3 | DS7: 2 | DT7: 3 | DU7: 3 | DV7: 3 | DW7: 3 | DX7: 3 | DY7: 3 | DZ7: 3 | EA7: 3 | EB7: 3 | EC7: 3 | ED7: 3 | EE7: 3 | EF7: 3 | EG7: 3 | EH7: 3 | EI7: 3 | EJ7: 3 | EK7: 3 | EL7: 3 | EM7: 3 | EN7: 0 | EO7: 0 | EP7: 0 | EQ7: 0 | ER7: 0 | ES7: 0
Q9: 45595 | R9: =IF(R13<=$Q$9,"S","N") -> S | S9: =IF(S13<=$Q$9,"S","N") -> S | T9: =IF(T13<=$Q$9,"S","N") -> S | U9: =IF(U13<=$Q$9,"S","N") -> S | V9: =IF(V13<=$Q$9,"S","N") -> S | W9: =IF(W13<=$Q$9,"S","N") -> S | X9: =IF(X13<=$Q$9,"S","N") -> S | Y9: =IF(Y13<=$Q$9,"S","N") -> S | ... ES9: =IF(ES13<=$Q$9,"S","N") -> N
R10: =SUBTOTAL(9,R14:R592) -> 0 | S10: =SUBTOTAL(9,S14:S592) -> 0 | T10: =SUBTOTAL(9,T14:T592) -> 0 | U10: =SUBTOTAL(9,U14:U592) -> 0 | V10: =SUBTOTAL(9,V14:V592) -> 0 | W10: =SUBTOTAL(9,W14:W592) -> 2 | X10: =SUBTOTAL(9,X14:X592) -> 2 | Y10: =SUBTOTAL(9,Y14:Y592) -> 2 | ... ES10: =SUBTOTAL(9,ES14:ES592) -> 0
R11: Julho | AO11: Agosto | BK11: Setembro | CF11: Outubro | DC11: Novembro | DX11: Dezembro
R12: =R13 -> 45474 | S12: =S13 -> 45475 | T12: =T13 -> 45476 | U12: =U13 -> 45477 | V12: =V13 -> 45478 | W12: =W13 -> 45481 | X12: =X13 -> 45482 | Y12: =Y13 -> 45483 | ... ES12: =ES13 -> 45657
B13: Âmbito | C13: Sub-âmbito | D13: Tipo de teste | E13: Tabela | F13: Campo | G13: Status | H13: Status2 | I13: Horas previstas | J13: Dias | K13: Horas efetivas | L13: Dias efetivos | M13: Status Estimado | N13: Status Real | O13: Desvios | P13: Observações | Q13: Val | R13: 45474 | S13: =WORKDAY(R13,1) -> 45475 | T13: =WORKDAY(S13,1) -> 45476 | U13: =WORKDAY(T13,1) -> 45477 | V13: =WORKDAY(U13,1) -> 45478 | W13: =WORKDAY(V13,1) -> 45481 | X13: =WORKDAY(W13,1) -> 45482 | Y13: =WORKDAY(X13,1) -> 45483 | Z13: =WORKDAY(Y13,1) -> 45484 | ... ES13: =WORKDAY(ER13,1) -> 45657
B14: 1. Assessment | I14: =SUM(I15:I17) -> 160 | J14: =SUM(J15:J17) -> 20 | K14: =I14 -> 160 | L14: =J14 -> 20 | M14: =SUMPRODUCT(M15:M17,I15:I17)/I14 -> 1 | N14: =SUMPRODUCT(N15:N17,J15:J17)/J14 -> 1 | O14: =N14-M14 -> 0 | P14: N/A
B15: Pilar III | C15: Bens Imóveis | G15: 7. Por iniciar | I15: =J15*8 -> 40 | J15: 5 | M15: =100% -> 1 | N15: =100% -> 1 | O15: =N15-M15 -> 0 | P15: N/A | Q15: =J15-SUM(R15:ES15) -> 0 | AB15: 1 | AC15: 1 | AD15: 1 | AE15: 1 | AF15: 1
B16: Pilar III | C16: Modelo Verde | G16: 7. Por iniciar | I16: =J16*8 -> 80 | J16: 10 | M16: =100% -> 1 | N16: =100% -> 1 | O16: =N16-M16 -> 0 | P16: N/A | Q16: =J16-SUM(R16:ES16) -> 0 | W16: 2 | X16: 2 | Y16: 2 | Z16: 2 | AA16: 2
B17: Pilar III | C17: LT Pilar III | G17: 7. Por iniciar | I17: =J17*8 -> 40 | J17: 5 | M17: =100% -> 1 | N17: =100% -> 1 | O17: =N17-M17 -> 0 | P17: N/A | Q17: =J17-SUM(R17:ES17) -> 0 | AG17: 1 | AH17: 1 | AI17: 1 | AJ17: 1 | AK17: 0.5 | AL17: 0.5
B19: 2. Re-especificação | I19: =SUM(I20:I22) -> 120 | J19: =SUM(J20:J22) -> 15 | K19: =N19*I19 -> 118.8 | L19: =N19*J19 -> 14.85 | M19: =SUMPRODUCT(M20:M23,I20:I23)/I19 -> 0.93333333 | N19: =SUMPRODUCT(N20:N22,J20:J22)/J19 -> 0.99 | O19: =N19-M19 -> 0.056666667 | P19: N/A
B20: Pilar III | C20: Bens Imóveis | G20: 7. Por iniciar | I20: =J20*8 -> 40 | J20: 5 | M20: =SUMIFS(R20:ES20,$R$9:$ES$9,"S")/J20 -> 1 | N20: =100% -> 1 | O20: =N20-M20 -> 0 | P20: N/A | Q20: =J20-SUM(R20:ES20) -> 0 | AB20: 0.5 | AG20: 0.5 | AL20: 0.5 | AQ20: 0.5 | AV20: 0.5 | BA20: 0.5 | BF20: 0.5 | BK20: 0.5 | BP20: 0.5 | BU20: 0.5
B21: Pilar III | C21: Modelo Verde | G21: 7. Por iniciar | I21: =J21*8 -> 40 | J21: 5 | M21: =SUMIFS(R21:ES21,$R$9:$ES$9,"S")/J21 -> 1 | N21: 1 | O21: =N21-M21 -> 0 | P21: N/A | Q21: =J21-SUM(R21:ES21) -> 0 | AB21: 0.5 | AG21: 0.5 | AL21: 0.5 | AQ21: 0.5 | AV21: 0.5 | BA21: 0.5 | BF21: 0.5 | BK21: 0.5 | BP21: 0.5 | BU21: 0.5
B22: Pilar III | C22: LT Pilar III | G22: 7. Por iniciar | I22: =J22*8 -> 40 | J22: 5 | M22: =SUMIFS(R22:ES22,$R$9:$ES$9,"S")/J22 -> 0.8 | N22: 0.97 | O22: =N22-M22 -> 0.17 | P22: - Em falta a re-especificação de um campo do Pilar III dependente de reunião com o LCM | Q22: =J22-SUM(R22:ES22) -> 0.5 | BP22: 0.5 | BU22: 0.5 | BZ22: 0.5 | CE22: 0.5 | CJ22: 0.5 | CO22: 0.5 | CT22: 0.5 | CY22: 0.5 | DD22: 0.5
B24: 3. Testes / Re-testes | I24: =I25+I40+I204+I371+I456 -> 2209.015 | J24: =J25+J40+J204+J371+J456 -> 279 | K24: =K25+K40+K204+K371+K456 -> 1336.2444 | L24: =L25+L40+L204+L371+L456 -> 169 | M24: =((M25*J25)+(M40*J40)+(M204*J204)+(M371*J371)+(M456*J456))/J24 -> 0.57885305 | N24: =((N25*L25)+(N40*L40)+(N204*L204)+(N371*L371)+(N456*L456))/L24 -> 0.68749715 | O24: =N24-M24 -> 0.10864411 | P24: N/A
B25: Pilar III | C25: Bens Imóveis - Input | I25: =SUM(I26:I39) -> 18.24 | J25: =ROUNDUP(I25/8,0) -> 3 | K25: =SUM(K26:K39) -> 4.56 | L25: =ROUNDUP(K25/8,0) -> 1 | M25: =SUMIFS(R25:ES25,$R$9:$ES$9,"S")/J25 -> 1 | N25: =IFERROR(L25/J25,0) -> 0.33333333 | O25: =N25-M25 -> -0.66666667 | P25: - Pendência de desenvolvimentos de IT: Tabela da Gloval | Q25: =J25-SUM(R25:ES25) -> 0 | AC25: 0.5 | AD25: 0.5 | AH25: 0.5 | AO25: 0.5 | AP25: 0.5 | AQ25: 0.5
A26: =E26&F26 -> ENERGY_CERTIFICATE_EST_INPUTn.a. | B26: Pilar III | C26: Bens Imóveis - Input | D26: 1. Universo | E26: ENERGY_CERTIFICATE_EST_INPUT | F26: n.a. | G26: =INDEX(Auxiliar!$B$16:$B$24,MATCH(Plano_V3!H26,Auxiliar!$C$16:$C$24,0),1) -> 6. Em implementação (re-especificação) | H26: =VLOOKUP(A26,'Aux - pivots1'!$A:$B,2,0) -> 7 | I26: =SUMIFS(Table1[Estimação (horas)],Table1[Tabela],Plano_V3!E26,Table1[Campo],Plano_V3!F26) -> 8 | J26: =I26/8 -> 1 | K26: =SUMIFS(Table1[Horas efetivas],Table1[Tabela],Plano_V3!E26,Table1[Campo],Plano_V3!F26) -> 2 | L26: =K26/8 -> 0.25 | N26: =L26/J26 -> 0.25 | O26: =N26-M26 -> 0.25 | P26: sem pendencia | Q26: =J26-SUM(R26:ES26) -> 1
A27: =E27&F27 -> ENERGY_CERTIFICATE_EST_INPUTPROPERTY_BANK_ID | B27: Pilar III | C27: Bens Imóveis - Input | D27: 2. Campo | E27: ENERGY_CERTIFICATE_EST_INPUT | F27: PROPERTY_BANK_ID | G27: =INDEX(Auxiliar!$B$16:$B$24,MATCH(Plano_V3!H27,Auxiliar!$C$16:$C$24,0),1) -> 6. Em implementação (re-especificação) | H27: =VLOOKUP(A27,'Aux - pivots1'!$A:$B,2,0) -> 7 | I27: =SUMIFS(Table1[Estimação (horas)],Table1[Tabela],Plano_V3!E27,Table1[Campo],Plano_V3!F27) -> 0.6 | J27: =I27/8 -> 0.075 | K27: =SUMIFS(Table1[Horas efetivas],Table1[Tabela],Plano_V3!E27,Table1[Campo],Plano_V3!F27) -> 0.15 | L27: =K27/8 -> 0.01875 | N27: =L27/J27 -> 0.25 | O27: =N27-M27 -> 0.25 | P27: sem pendencia | Q27: =J27-SUM(R27:ES27) -> 0.075
A28: =E28&F28 -> ENERGY_CERTIFICATE_EST_INPUTENCRYPTED_KEY | B28: Pilar III | C28: Bens Imóveis - Input | D28: 2. Campo | E28: ENERGY_CERTIFICATE_EST_INPUT | F28: ENCRYPTED_KEY | G28: =INDEX(Auxiliar!$B$16:$B$24,MATCH(Plano_V3!H28,Auxiliar!$C$16:$C$24,0),1) -> 6. Em implementação (re-especificação) | H28: =VLOOKUP(A28,'Aux - pivots1'!$A:$B,2,0) -> 7 | I28: =SUMIFS(Table1[Estimação (horas)],Table1[Tabela],Plano_V3!E28,Table1[Campo],Plano_V3!F28) -> 0.6 | J28: =I28/8 -> 0.075 | K28: =SUMIFS(Table1[Horas efetivas],Table1[Tabela],Plano_V3!E28,Table1[Campo],Plano_V3!F28) -> 0.15 | L28: =K28/8 -> 0.01875 | N28: =L28/J28 -> 0.25 | O28: =N28-M28 -> 0.25 | P28: sem pendencia | Q28: =J28-SUM(R28:ES28) -> 0.075
A29: =E29&F29 -> ENERGY_CERTIFICATE_EST_INPUTPROPERTY_BRANCH_CODE | B29: Pilar III | C29: Bens Imóveis - Input | D29: 2. Campo | E29: ENERGY_CERTIFICATE_EST_INPUT | F29: PROPERTY_BRANCH_CODE | G29: =INDEX(Auxiliar!$B$16:$B$24,MATCH(Plano_V3!H29,Auxiliar!$C$16:$C$24,0),1) -> 6. Em implementação (re-especificação) | H29: =VLOOKUP(A29,'Aux - pivots1'!$A:$B,2,0) -> 7 | I29: =SUMIFS(Table1[Estimação (horas)],Table1[Tabela],Plano_V3!E29,Table1[Campo],Plano_V3!F29) -> 0.6 | J29: =I29/8 -> 0.075 | K29: =SUMIFS(Table1[Horas efetivas],Table1[Tabela],Plano_V3!E29,Table1[Campo],Plano_V3!F29) -> 0.15 | L29: =K29/8 -> 0.01875 | N29: =L29/J29 -> 0.25 | O29: =N29-M29 -> 0.25 | P29: sem pendencia | Q29: =J29-SUM(R29:ES29) -> 0.075
A30: =E30&F30 -> ENERGY_CERTIFICATE_EST_INPUTPROPERTY_CONTRACT_ID | B30: Pilar III | C30: Bens Imóveis - Input | D30: 2. Campo | E30: ENERGY_CERTIFICATE_EST_INPUT | F30: PROPERTY_CONTRACT_ID | G30: =INDEX(Auxiliar!$B$16:$B$24,MATCH(Plano_V3!H30,Auxiliar!$C$16:$C$24,0),1) -> 6. Em implementação (re-especificação) | H30: =VLOOKUP(A30,'Aux - pivots1'!$A:$B,2,0) -> 7 | I30: =SUMIFS(Table1[Estimação (horas)],Table1[Tabela],Plano_V3!E30,Table1[Campo],Plano_V3!F30) -> 0.6 | J30: =I30/8 -> 0.075 | K30: =SUMIFS(Table1[Horas efetivas],Table1[Tabela],Plano_V3!E30,Table1[Campo],Plano_V3!F30) -> 0.15 | L30: =K30/8 -> 0.01875 | N30: =L30/J30 -> 0.25 | O30: =N30-M30 -> 0.25 | P30: sem pendencia | Q30: =J30-SUM(R30:ES30) -> 0.075
A31: =E31&F31 -> ENERGY_CERTIFICATE_EST_INPUTPROPERTY_REFERENCE_CODE | B31: Pilar III | C31: Bens Imóveis - Input | D31: 2. Campo | E31: ENERGY_CERTIFICATE_EST_INPUT | F31: PROPERTY_REFERENCE_CODE | G31: =INDEX(Auxiliar!$B$16:$B$24,MATCH(Plano_V3!H31,Auxiliar!$C$16:$C$24,0),1) -> 6. Em implementação (re-especificação) | H31: =VLOOKUP(A31,'Aux - pivots1'!$A:$B,2,0) -> 7 | I31: =SUMIFS(Table1[Estimação (horas)],Table1[Tabela],Plano_V3!E31,Table1[Campo],Plano_V3!F31) -> 0.6 | J31: =I31/8 -> 0.075 | K31: =SUMIFS(Table1[Horas efetivas],Table1[Tabela],Plano_V3!E31,Table1[Campo],Plano_V3!F31) -> 0.15 | L31: =K31/8 -> 0.01875 | N31: =L31/J31 -> 0.25 | O31: =N31-M31 -> 0.25 | P31: sem pendencia | Q31: =J31-SUM(R31:ES31) -> 0.075
A32: =E32&F32 -> ENERGY_CERTIFICATE_EST_INPUTDATA_EXTRACTION_DATE | B32: Pilar III | C32: Bens Imóveis - Input | D32: 2. Campo | E32: ENERGY_CERTIFICATE_EST_INPUT | F32: DATA_EXTRACTION_DATE | G32: =INDEX(Auxiliar!$B$16:$B$24,MATCH(Plano_V3!H32,Auxiliar!$C$16:$C$24,0),1) -> 6. Em implementação (re-especificação) | H32: =VLOOKUP(A32,'Aux - pivots1'!$A:$B,2,0) -> 7 | I32: =SUMIFS(Table1[Estimação (horas)],Table1[Tabela],Plano_V3!E32,Table1[Campo],Plano_V3!F32) -> 0.6 | J32: =I32/8 -> 0.075 | K32: =SUMIFS(Table1[Horas efetivas],Table1[Tabela],Plano_V3!E32,Table1[Campo],Plano_V3!F32) -> 0.15 | L32: =K32/8 -> 0.01875 | N32: =L32/J32 -> 0.25 | O32: =N32-M32 -> 0.25 | P32: sem pendencia | Q32: =J32-SUM(R32:ES32) -> 0.075
A33: =E33&F33 -> ENERGY_CERTIFICATE_EST_INPUTEPC | B33: Pilar III | C33: Bens Imóveis - Input | D33: 2. Campo | E33: ENERGY_CERTIFICATE_EST_INPUT | F33: EPC | G33: =INDEX(Auxiliar!$B$16:$B$24,MATCH(Plano_V3!H33,Auxiliar!$C$16:$C$24,0),1) -> 6. Em implementação (re-especificação) | H33: =VLOOKUP(A33,'Aux - pivots1'!$A:$B,2,0) -> 7 | I33: =SUMIFS(Table1[Estimação (horas)],Table1[Tabela],Plano_V3!E33,Table1[Campo],Plano_V3!F33) -> 0.6 | J33: =I33/8 -> 0.075 | K33: =SUMIFS(Table1[Horas efetivas],Table1[Tabela],Plano_V3!E33,Table1[Campo],Plano_V3!F33) -> 0.15 | L33: =K33/8 -> 0.01875 | N33: =L33/J33 -> 0.25 | O33: =N33-M33 -> 0.25 | P33: sem pendencia | Q33: =J33-SUM(R33:ES33) -> 0.075
A34: =E34&F34 -> ENERGY_CERTIFICATE_EST_INPUTDATA_PROVIDER | B34: Pilar III | C34: Bens Imóveis - Input | D34: 2. Campo | E34: ENERGY_CERTIFICATE_EST_INPUT | F34: DATA_PROVIDER | G34: =INDEX(Auxiliar!$B$16:$B$24,MATCH(Plano_V3!H34,Auxiliar!$C$16:$C$24,0),1) -> 6. Em implementação (re-especificação) | H34: =VLOOKUP(A34,'Aux - pivots1'!$A:$B,2,0) -> 7 | I34: =SUMIFS(Table1[Estimação (horas)],Table1[Tabela],Plano_V3!E34,Table1[Campo],Plano_V3!F34) -> 0.6 | J34: =I34/8 -> 0.075 | K34: =SUMIFS(Table1[Horas efetivas],Table1[Tabela],Plano_V3!E34,Table1[Campo],Plano_V3!F34) -> 0.15 | L34: =K34/8 -> 0.01875 | N34: =L34/J34 -> 0.25 | O34: =N34-M34 -> 0.25 | P34: sem pendencia | Q34: =J34-SUM(R34:ES34) -> 0.075
A35: =E35&F35 -> ENERGY_CERTIFICATE_EST_INPUTACTUAL_VALUE_IND | B35: Pilar III | C35: Bens Imóveis - Input | D35: 2. Campo | E35: ENERGY_CERTIFICATE_EST_INPUT | F35: ACTUAL_VALUE_IND | G35: =INDEX(Auxiliar!$B$16:$B$24,MATCH(Plano_V3!H35,Auxiliar!$C$16:$C$24,0),1) -> 6. Em implementação (re-especificação) | H35: =VLOOKUP(A35,'Aux - pivots1'!$A:$B,2,0) -> 7 | I35: =SUMIFS(Table1[Estimação (horas)],Table1[Tabela],Plano_V3!E35,Table1[Campo],Plano_V3!F35) -> 0.6 | J35: =I35/8 -> 0.075 | K35: =SUMIFS(Table1[Horas efetivas],Table1[Tabela],Plano_V3!E35,Table1[Campo],Plano_V3!F35) -> 0.15 | L35: =K35/8 -> 0.01875 | N35: =L35/J35 -> 0.25 | O35: =N35-M35 -> 0.25 | P35: sem pendencia | Q35: =J35-SUM(R35:ES35) -> 0.075
A36: =E36&F36 -> ENERGY_CERTIFICATE_EST_INPUTQUALITY_SCORE | B36: Pilar III | C36: Bens Imóveis - Input | D36: 2. Campo | E36: ENERGY_CERTIFICATE_EST_INPUT | F36: QUALITY_SCORE | G36: =INDEX(Auxiliar!$B$16:$B$24,MATCH(Plano_V3!H36,Auxiliar!$C$16:$C$24,0),1) -> 6. Em implementação (re-especificação) | H36: =VLOOKUP(A36,'Aux - pivots1'!$A:$B,2,0) -> 7 | I36: =SUMIFS(Table1[Estimação (horas)],Table1[Tabela],Plano_V3!E36,Table1[Campo],Plano_V3!F36) -> 0.6 | J36: =I36/8 -> 0.075 | K36: =SUMIFS(Table1[Horas efetivas],Table1[Tabela],Plano_V3!E36,Table1[Campo],Plano_V3!F36) -> 0.15 | L36: =K36/8 -> 0.01875 | N36: =L36/J36 -> 0.25 | O36: =N36-M36 -> 0.25 | P36: sem pendencia | Q36: =J36-SUM(R36:ES36) -> 0.075
A37: =E37&F37 -> ENERGY_CERTIFICATE_EST_INPUTENERGY_CONSUMPTION_VALUE_YEAR | B37: Pilar III | C37: Bens Imóveis - Input | D37: 2. Campo | E37: ENERGY_CERTIFICATE_EST_INPUT | F37: ENERGY_CONSUMPTION_VALUE_YEAR | G37: =INDEX(Auxiliar!$B$16:$B$24,MATCH(Plano_V3!H37,Auxiliar!$C$16:$C$24,0),1) -> 6. Em implementação (re-especificação) | H37: =VLOOKUP(A37,'Aux - pivots1'!$A:$B,2,0) -> 7 | I37: =SUMIFS(Table1[Estimação (horas)],Table1[Tabela],Plano_V3!E37,Table1[Campo],Plano_V3!F37) -> 0.6 | J37: =I37/8 -> 0.075 | K37: =SUMIFS(Table1[Horas efetivas],Table1[Tabela],Plano_V3!E37,Table1[Campo],Plano_V3!F37) -> 0.15 | L37: =K37/8 -> 0.01875 | N37: =L37/J37 -> 0.25 | O37: =N37-M37 -> 0.25 | P37: sem pendencia | Q37: =J37-SUM(R37:ES37) -> 0.075
A38: =E38&F38 -> ENERGY_CERTIFICATE_EST_INPUTCARBON_EMISSION_VALUE_YEAR | B38: Pilar III | C38: Bens Imóveis - Input | D38: 2. Campo | E38: ENERGY_CERTIFICATE_EST_INPUT | F38: CARBON_EMISSION_VALUE_YEAR | G38: =INDEX(Auxiliar!$B$16:$B$24,MATCH(Plano_V3!H38,Auxiliar!$C$16:$C$24,0),1) -> 6. Em implementação (re-especificação) | H38: =VLOOKUP(A38,'Aux - pivots1'!$A:$B,2,0) -> 7 | I38: =SUMIFS(Table1[Estimação (horas)],Table1[Tabela],Plano_V3!E38,Table1[Campo],Plano_V3!F38) -> 0.6 | J38: =I38/8 -> 0.075 | K38: =SUMIFS(Table1[Horas efetivas],Table1[Tabela],Plano_V3!E38,Table1[Campo],Plano_V3!F38) -> 0.15 | L38: =K38/8 -> 0.01875 | N38: =L38/J38 -> 0.25 | O38: =N38-M38 -> 0.25 | P38: sem pendencia | Q38: =J38-SUM(R38:ES38) -> 0.075
A39: =E39&F39 -> Re-testesn.a. | B39: Pilar III | C39: Bens Imóveis - Input | D39: 2. Campo | E39: Re-testes | F39: n.a. | G39: 7. Por iniciar | I39: =SUM(I26:I38)*$D$6 -> 3.04 | J39: =I39/8 -> 0.38 | K39: =SUM(K26:K38)*$D$6 -> 0.76 | L39: =K39/8 -> 0.095 | N39: =L39/J39 -> 0.25 | O39: =N39-M39 -> 0.25 | P39: sem pendencia | Q39: =J39-SUM(R39:ES39) -> 0.38
A40: =E40&F40 | B40: Pilar III | C40: Bens Imóveis - Output | I40: =SUM(I41:I203) -> 835.65 | J40: =ROUNDUP(I40/8,0) -> 105 | K40: =SUM(K41:K203) -> 751.35938 | L40: =ROUNDUP(K40/8,0) -> 94 | M40: =SUMIFS(R40:ES40,$R$9:$ES$9,"S")/J40 -> 0.95238095 | N40: =IFERROR(L40/J40,0) -> 0.8952381 | O40: =N40-M40 -> -0.057142857 | P40: - Pendência de reprocessamento de IT: Tabela de certificados energéticos. | Q40: =J40-SUM(R40:ES40) -> 5 | AL40: 1 | AM40: 1 | AN40: 1 | AO40: 1 | AR40: 1 | AS40: 1 | AT40: 1 | AU40: 1 | AW40: 1 | AX40: 2 | AZ40: 1 | BC40: 1 | BD40: 1 | BE40: 1 | BF40: 1 | BG40: 2 | BH40: 2 | BI40: 2 | BJ40: 2 | BK40: 0.5 | BL40: 2 | BM40: 2 | BN40: 2 | BO40: 2 | BP40: 0.5 | BQ40: 2 | BR40: 2 | BS40: 2 | BT40: 2 | BU40: 1.5 | BV40: 2 | BW40: 2 | BX40: 2 | BY40: 2 | BZ40: 2 | CA40: 2 | CB40: 2 | CC40: 2 | CD40: 2 | CE40: 2 | CF40: 2 | CG40: 2 | CH40: 2 | CI40: 2 | CJ40: 2 | CK40: 2 | CL40: 2 | CM40: 2 | CN40: 2 | CO40: 2 | CP40: 2 | CQ40: 2 | CR40: 2 | CS40: 2 | CT40: 2 | CU40: 2 | CV40: 2 | CW40: 2 | CX40: 1.5
A41: =E41&F41 -> PROCESSn.a. | B41: Pilar III | C41: Bens Imóveis - Output | D41: 1. Universo | E41: PROCESS | F41: n.a. | G41: =INDEX(Auxiliar!$B$16:$B$24,MATCH(Plano_V3!H41,Auxiliar!$C$16:$C$24,0),1) -> 1. Concluído | H41: =VLOOKUP(A41,'Aux - pivots1'!$A:$B,2,0) -> 1 | I41: =SUMIFS(Table1[Estimação (horas)],Table1[Tabela],Plano_V3!E41,Table1[Campo],Plano_V3!F41) -> 8 | J41: =I41/8 -> 1 | K41: =SUMIFS(Table1[Horas efetivas],Table1[Tabela],Plano_V3!E41,Table1[Campo],Plano_V3!F41) -> 8 | L41: =K41/8 -> 1 | N41: =L41/J41 -> 1 | O41: =N41-M41 -> 1 | P41: cd_imv_out_trz_cred_prc | Q41: =J41-SUM(R41:ES41) -> 1
A42: =E42&F42 -> PROCESSPROCESS_BANK_ID | B42: Pilar III | C42: Bens Imóveis - Output | D42: 2. Campo | E42: PROCESS | F42: PROCESS_BANK_ID | G42: =INDEX(Auxiliar!$B$16:$B$24,MATCH(Plano_V3!H42,Auxiliar!$C$16:$C$24,0),1) -> 1. Concluído | H42: =VLOOKUP(A42,'Aux - pivots1'!$A:$B,2,0) -> 1 | I42: =SUMIFS(Table1[Estimação (horas)],Table1[Tabela],Plano_V3!E42,Table1[Campo],Plano_V3!F42) -> 4.1 | J42: =I42/8 -> 0.5125 | K42: =SUMIFS(Table1[Horas efetivas],Table1[Tabela],Plano_V3!E42,Table1[Campo],Plano_V3!F42) -> 4.1 | L42: =K42/8 -> 0.5125 | N42: =L42/J42 -> 1 | O42: =N42-M42 -> 1 | P42: cd_imv_out_trz_cred_prc | Q42: =J42-SUM(R42:ES42) -> 0.5125
A43: =E43&F43 -> PROCESSPROCESS_BRANCH_CODE | B43: Pilar III | C43: Bens Imóveis - Output | D43: 2. Campo | E43: PROCESS | F43: PROCESS_BRANCH_CODE | G43: =INDEX(Auxiliar!$B$16:$B$24,MATCH(Plano_V3!H43,Auxiliar!$C$16:$C$24,0),1) -> 1. Concluído | H43: =VLOOKUP(A43,'Aux - pivots1'!$A:$B,2,0) -> 1 | I43: =SUMIFS(Table1[Estimação (horas)],Table1[Tabela],Plano_V3!E43,Table1[Campo],Plano_V3!F43) -> 4.1 | J43: =I43/8 -> 0.5125 | K43: =SUMIFS(Table1[Horas efetivas],Table1[Tabela],Plano_V3!E43,Table1[Campo],Plano_V3!F43) -> 4.1 | L43: =K43/8 -> 0.5125 | N43: =L43/J43 -> 1 | O43: =N43-M43 -> 1 | P43: cd_imv_out_trz_cred_prc | Q43: =J43-SUM(R43:ES43) -> 0.5125
A44: =E44&F44 -> PROCESSPROCESS_ACCOUNT_ID | B44: Pilar III | C44: Bens Imóveis - Output | D44: 2. Campo | E44: PROCESS | F44: PROCESS_ACCOUNT_ID | G44: =INDEX(Auxiliar!$B$16:$B$24,MATCH(Plano_V3!H44,Auxiliar!$C$16:$C$24,0),1) -> 1. Concluído | H44: =VLOOKUP(A44,'Aux - pivots1'!$A:$B,2,0) -> 1 | I44: =SUMIFS(Table1[Estimação (horas)],Table1[Tabela],Plano_V3!E44,Table1[Campo],Plano_V3!F44) -> 4.1 | J44: =I44/8 -> 0.5125 | K44: =SUMIFS(Table1[Horas efetivas],Table1[Tabela],Plano_V3!E44,Table1[Campo],Plano_V3!F44) -> 4.1 | L44: =K44/8 -> 0.5125 | N44: =L44/J44 -> 1 | O44: =N44-M44 -> 1 | P44: cd_imv_out_trz_cred_prc | Q44: =J44-SUM(R44:ES44) -> 0.5125
A45: =E45&F45 -> PROCESScod_estd_prcs | B45: Pilar III | C45: Bens Imóveis - Output | D45: 2. Campo | E45: PROCESS | F45: cod_estd_prcs | G45: =INDEX(Auxiliar!$B$16:$B$24,MATCH(Plano_V3!H45,Auxiliar!$C$16:$C$24,0),1) -> 0. Cancelado | H45: =VLOOKUP(A45,'Aux - pivots1'!$A:$B,2,0) -> 0 | I45: 0 | J45: =I45/8 -> 0 | K45: =SUMIFS(Table1[Horas efetivas],Table1[Tabela],Plano_V3!E45,Table1[Campo],Plano_V3!F45) -> 0 | L45: =K45/8 -> 0 | N45: =L45/J45 -> #DIV/0! | O45: =N45-M45 -> #DIV/0! | P45: cd_imv_out_trz_cred_prc | Q45: =J45-SUM(R45:ES45) -> 0
A46: =E46&F46 -> PROCESSGUARANTEE_CODE | B46: Pilar III | C46: Bens Imóveis - Output | D46: 2. Campo | E46: PROCESS | F46: GUARANTEE_CODE | G46: =INDEX(Auxiliar!$B$16:$B$24,MATCH(Plano_V3!H46,Auxiliar!$C$16:$C$24,0),1) -> 1. Concluído | H46: =VLOOKUP(A46,'Aux - pivots1'!$A:$B,2,0) -> 1 | I46: =SUMIFS(Table1[Estimação (horas)],Table1[Tabela],Plano_V3!E46,Table1[Campo],Plano_V3!F46) -> 4.1 | J46: =I46/8 -> 0.5125 | K46: =SUMIFS(Table1[Horas efetivas],Table1[Tabela],Plano_V3!E46,Table1[Campo],Plano_V3!F46) -> 4.1 | L46: =K46/8 -> 0.5125 | N46: =L46/J46 -> 1 | O46: =N46-M46 -> 1 | P46: cd_imv_out_trz_cred_prc | Q46: =J46-SUM(R46:ES46) -> 0.5125
A47: =E47&F47 -> PROCESSCURRENCY_CODE | B47: Pilar III | C47: Bens Imóveis - Output | D47: 2. Campo | E47: PROCESS | F47: CURRENCY_CODE | G47: =INDEX(Auxiliar!$B$16:$B$24,MATCH(Plano_V3!H47,Auxiliar!$C$16:$C$24,0),1) -> 1. Concluído | H47: =VLOOKUP(A47,'Aux - pivots1'!$A:$B,2,0) -> 1 | I47: =SUMIFS(Table1[Estimação (horas)],Table1[Tabela],Plano_V3!E47,Table1[Campo],Plano_V3!F47) -> 4.1 | J47: =I47/8 -> 0.5125 | K47: =SUMIFS(Table1[Horas efetivas],Table1[Tabela],Plano_V3!E47,Table1[Campo],Plano_V3!F47) -> 4.1 | L47: =K47/8 -> 0.5125 | N47: =L47/J47 -> 1 | O47: =N47-M47 -> 1 | P47: cd_imv_out_trz_cred_prc | Q47: =J47-SUM(R47:ES47) -> 0.5125
A48: =E48&F48 -> PROCESSPROCESS_CAMPAIGN_CODE | B48: Pilar III | C48: Bens Imóveis - Output | D48: 2. Campo | E48: PROCESS | F48: PROCESS_CAMPAIGN_CODE | G48: =INDEX(Auxiliar!$B$16:$B$24,MATCH(Plano_V3!H48,Auxiliar!$C$16:$C$24,0),1) -> 1. Concluído | H48: =VLOOKUP(A48,'Aux - pivots1'!$A:$B,2,0) -> 1 | I48: =SUMIFS(Table1[Estimação (horas)],Table1[Tabela],Plano_V3!E48,Table1[Campo],Plano_V3!F48) -> 4.1 | J48: =I48/8 -> 0.5125 | K48: =SUMIFS(Table1[Horas efetivas],Table1[Tabela],Plano_V3!E48,Table1[Campo],Plano_V3!F48) -> 4.1 | L48: =K48/8 -> 0.5125 | N48: =L48/J48 -> 1 | O48: =N48-M48 -> 1 | P48: cd_imv_out_trz_cred_prc | Q48: =J48-SUM(R48:ES48) -> 0.5125
A49: =E49&F49 -> PROCESSPROCESS_PRODUCT_ID | B49: Pilar III | C49: Bens Imóveis - Output | D49: 2. Campo | E49: PROCESS | F49: PROCESS_PRODUCT_ID | G49: =INDEX(Auxiliar!$B$16:$B$24,MATCH(Plano_V3!H49,Auxiliar!$C$16:$C$24,0),1) -> 1. Concluído | H49: =VLOOKUP(A49,'Aux - pivots1'!$A:$B,2,0) -> 1 | I49: =SUMIFS(Table1[Estimação (horas)],Table1[Tabela],Plano_V3!E49,Table1[Campo],Plano_V3!F49) -> 4.1 | J49: =I49/8 -> 0.5125 | K49: =SUMIFS(Table1[Horas efetivas],Table1[Tabela],Plano_V3!E49,Table1[Campo],Plano_V3!F49) -> 4.1 | L49: =K49/8 -> 0.5125 | N49: =L49/J49 -> 1 | O49: =N49-M49 -> 1 | P49: cd_imv_out_trz_cred_prc | Q49: =J49-SUM(R49:ES49) -> 0.5125
A50: =E50&F50 -> PROCESSPROCESS_SUBPRODUCT_ID | B50: Pilar III | C50: Bens Imóveis - Output | D50: 2. Campo | E50: PROCESS | F50: PROCESS_SUBPRODUCT_ID | G50: =INDEX(Auxiliar!$B$16:$B$24,MATCH(Plano_V3!H50,Auxiliar!$C$16:$C$24,0),1) -> 1. Concluído | H50: =VLOOKUP(A50,'Aux - pivots1'!$A:$B,2,0) -> 1 | I50: =SUMIFS(Table1[Estimação (horas)],Table1[Tabela],Plano_V3!E50,Table1[Campo],Plano_V3!F50) -> 4.1 | J50: =I50/8 -> 0.5125 | K50: =SUMIFS(Table1[Horas efetivas],Table1[Tabela],Plano_V3!E50,Table1[Campo],Plano_V3!F50) -> 4.1 | L50: =K50/8 -> 0.5125 | N50: =L50/J50 -> 1 | O50: =N50-M50 -> 1 | P50: cd_imv_out_trz_cred_prc | Q50: =J50-SUM(R50:ES50) -> 0.5125
A51: =E51&F51 -> PROCESSGUARANTEE_TYPE_CODE | B51: Pilar III | C51: Bens Imóveis - Output | D51: 2. Campo | E51: PROCESS | F51: GUARANTEE_TYPE_CODE | G51: =INDEX(Auxiliar!$B$16:$B$24,MATCH(Plano_V3!H51,Auxiliar!$C$16:$C$24,0),1) -> 1. Concluído | H51: =VLOOKUP(A51,'Aux - pivots1'!$A:$B,2,0) -> 1 | I51: =SUMIFS(Table1[Estimação (horas)],Table1[Tabela],Plano_V3!E51,Table1[Campo],Plano_V3!F51) -> 4.1 | J51: =I51/8 -> 0.5125 | K51: =SUMIFS(Table1[Horas efetivas],Table1[Tabela],Plano_V3!E51,Table1[Campo],Plano_V3!F51) -> 4.1 | L51: =K51/8 -> 0.5125 | N51: =L51/J51 -> 1 | O51: =N51-M51 -> 1 | P51: cd_imv_out_trz_cred_prc | Q51: =J51-SUM(R51:ES51) -> 0.5125
A52: =E52&F52 -> PROCESSPROCESS_REFERENCE_CODE | B52: Pilar III | C52: Bens Imóveis - Output | D52: 2. Campo | E52: PROCESS | F52: PROCESS_REFERENCE_CODE | G52: =INDEX(Auxiliar!$B$16:$B$24,MATCH(Plano_V3!H52,Auxiliar!$C$16:$C$24,0),1) -> 1. Concluído | H52: =VLOOKUP(A52,'Aux - pivots1'!$A:$B,2,0) -> 1 | I52: =SUMIFS(Table1[Estimação (horas)],Table1[Tabela],Plano_V3!E52,Table1[Campo],Plano_V3!F52) -> 4.1 | J52: =I52/8 -> 0.5125 | K52: =SUMIFS(Table1[Horas efetivas],Table1[Tabela],Plano_V3!E52,Table1[Campo],Plano_V3!F52) -> 4.1 | L52: =K52/8 -> 0.5125 | N52: =L52/J52 -> 1 | O52: =N52-M52 -> 1 | P52: cd_imv_out_trz_cred_prc | Q52: =J52-SUM(R52:ES52) -> 0.5125
A53: =E53&F53 -> PROCESSPROCESS_START_DATE | B53: Pilar III | C53: Bens Imóveis - Output | D53: 2. Campo | E53: PROCESS | F53: PROCESS_START_DATE | G53: =INDEX(Auxiliar!$B$16:$B$24,MATCH(Plano_V3!H53,Auxiliar!$C$16:$C$24,0),1) -> 1. Concluído | H53: =VLOOKUP(A53,'Aux - pivots1'!$A:$B,2,0) -> 1 | I53: =SUMIFS(Table1[Estimação (horas)],Table1[Tabela],Plano_V3!E53,Table1[Campo],Plano_V3!F53) -> 4.1 | J53: =I53/8 -> 0.5125 | K53: =SUMIFS(Table1[Horas efetivas],Table1[Tabela],Plano_V3!E53,Table1[Campo],Plano_V3!F53) -> 4.1 | L53: =K53/8 -> 0.5125 | N53: =L53/J53 -> 1 | O53: =N53-M53 -> 1 | P53: cd_imv_out_trz_cred_prc | Q53: =J53-SUM(R53:ES53) -> 0.5125
A54: =E54&F54 -> PROCESSPROCESS_DUE_DATE | B54: Pilar III | C54: Bens Imóveis - Output | D54: 2. Campo | E54: PROCESS | F54: PROCESS_DUE_DATE | G54: =INDEX(Auxiliar!$B$16:$B$24,MATCH(Plano_V3!H54,Auxiliar!$C$16:$C$24,0),1) -> 1. Concluído | H54: =VLOOKUP(A54,'Aux - pivots1'!$A:$B,2,0) -> 1 | I54: =SUMIFS(Table1[Estimação (horas)],Table1[Tabela],Plano_V3!E54,Table1[Campo],Plano_V3!F54) -> 4.1 | J54: =I54/8 -> 0.5125 | K54: =SUMIFS(Table1[Horas efetivas],Table1[Tabela],Plano_V3!E54,Table1[Campo],Plano_V3!F54) -> 4.1 | L54: =K54/8 -> 0.5125 | N54: =L54/J54 -> 1 | O54: =N54-M54 -> 1 | P54: cd_imv_out_trz_cred_prc | Q54: =J54-SUM(R54:ES54) -> 0.5125
A55: =E55&F55 -> PROCESSmontante_eur | B55: Pilar III | C55: Bens Imóveis - Output | D55: 2. Campo | E55: PROCESS | F55: montante_eur | G55: =INDEX(Auxiliar!$B$16:$B$24,MATCH(Plano_V3!H55,Auxiliar!$C$16:$C$24,0),1) -> 0. Cancelado | H55: =VLOOKUP(A55,'Aux - pivots1'!$A:$B,2,0) -> 0 | I55: 0 | J55: =I55/8 -> 0 | K55: =SUMIFS(Table1[Horas efetivas],Table1[Tabela],Plano_V3!E55,Table1[Campo],Plano_V3!F55) -> 0 | L55: =K55/8 -> 0 | N55: =L55/J55 -> #DIV/0! | O55: =N55-M55 -> #DIV/0! | P55: cd_imv_out_trz_cred_prc | Q55: =J55-SUM(R55:ES55) -> 0
A56: =E56&F56 -> PROCESSmontante_org | B56: Pilar III | C56: Bens Imóveis - Output | D56: 2. Campo | E56: PROCESS | F56: montante_org | G56: =INDEX(Auxiliar!$B$16:$B$24,MATCH(Plano_V3!H56,Auxiliar!$C$16:$C$24,0),1) -> 0. Cancelado | H56: =VLOOKUP(A56,'Aux - pivots1'!$A:$B,2,0) -> 0 | I56: 0 | J56: =I56/8 -> 0 | K56: =SUMIFS(Table1[Horas efetivas],Table1[Tabela],Plano_V3!E56,Table1[Campo],Plano_V3!F56) -> 0 | L56: =K56/8 -> 0 | N56: =L56/J56 -> #DIV/0! | O56: =N56-M56 -> #DIV/0! | P56: cd_imv_out_trz_cred_prc | Q56: =J56-SUM(R56:ES56) -> 0
A57: =E57&F57 -> PROCESSorigem | B57: Pilar III | C57: Bens Imóveis - Output | D57: 2. Campo | E57: PROCESS | F57: origem | G57: =INDEX(Auxiliar!$B$16:$B$24,MATCH(Plano_V3!H57,Auxiliar!$C$16:$C$24,0),1) -> 0. Cancelado | H57: =VLOOKUP(A57,'Aux - pivots1'!$A:$B,2,0) -> 0 | I57: =SUMIFS(Table1[Estimação (horas)],Table1[Tabela],Plano_V3!E57,Table1[Campo],Plano_V3!F57) -> 4.1 | J57: =I57/8 -> 0.5125 | K57: =SUMIFS(Table1[Horas efetivas],Table1[Tabela],Plano_V3!E57,Table1[Campo],Plano_V3!F57) -> 0 | L57: =K57/8 -> 0 | N57: =L57/J57 -> 0 | O57: =N57-M57 -> 0 | P57: cd_imv_out_trz_cred_prc | Q57: =J57-SUM(R57:ES57) -> 0.5125
A58: =E58&F58 -> PROCESSDATA_DATE_PART | B58: Pilar III | C58: Bens Imóveis - Output | D58: 2. Campo | E58: PROCESS | F58: DATA_DATE_PART | G58: =INDEX(Auxiliar!$B$16:$B$24,MATCH(Plano_V3!H58,Auxiliar!$C$16:$C$24,0),1) -> 1. Concluído | H58: =VLOOKUP(A58,'Aux - pivots1'!$A:$B,2,0) -> 1 | I58: =SUMIFS(Table1[Estimação (horas)],Table1[Tabela],Plano_V3!E58,Table1[Campo],Plano_V3!F58) -> 4.1 | J58: =I58/8 -> 0.5125 | K58: =SUMIFS(Table1[Horas efetivas],Table1[Tabela],Plano_V3!E58,Table1[Campo],Plano_V3!F58) -> 4.1 | L58: =K58/8 -> 0.5125 | N58: =L58/J58 -> 1 | O58: =N58-M58 -> 1 | P58: cd_imv_out_trz_cred_prc | Q58: =J58-SUM(R58:ES58) -> 0.5125
A59: =E59&F59 -> RESPONSIBILITY_PROCESS_RELn.a. | B59: Pilar III | C59: Bens Imóveis - Output | D59: 1. Universo | E59: RESPONSIBILITY_PROCESS_REL | F59: n.a. | G59: =INDEX(Auxiliar!$B$16:$B$24,MATCH(Plano_V3!H59,Auxiliar!$C$16:$C$24,0),1) -> 1. Concluído | H59: =VLOOKUP(A59,'Aux - pivots1'!$A:$B,2,0) -> 1 | I59: =SUMIFS(Table1[Estimação (horas)],Table1[Tabela],Plano_V3!E59,Table1[Campo],Plano_V3!F59) -> 8 | J59: =I59/8 -> 1 | K59: =SUMIFS(Table1[Horas efetivas],Table1[Tabela],Plano_V3!E59,Table1[Campo],Plano_V3!F59) -> 8 | L59: =K59/8 -> 1 | N59: =L59/J59 -> 1 | O59: =N59-M59 -> 1 | P59: sem pendencia | Q59: =J59-SUM(R59:ES59) -> 1
A60: =E60&F60 -> RESPONSIBILITY_PROCESS_RELPROCESS_BANK_ID | B60: Pilar III | C60: Bens Imóveis - Output | D60: 2. Campo | E60: RESPONSIBILITY_PROCESS_REL | F60: PROCESS_BANK_ID | G60: =INDEX(Auxiliar!$B$16:$B$24,MATCH(Plano_V3!H60,Auxiliar!$C$16:$C$24,0),1) -> 1. Concluído | H60: =VLOOKUP(A60,'Aux - pivots1'!$A:$B,2,0) -> 1 | I60: =SUMIFS(Table1[Estimação (horas)],Table1[Tabela],Plano_V3!E60,Table1[Campo],Plano_V3!F60) -> 8.1 | J60: =I60/8 -> 1.0125 | K60: =SUMIFS(Table1[Horas efetivas],Table1[Tabela],Plano_V3!E60,Table1[Campo],Plano_V3!F60) -> 8.1 | L60: =K60/8 -> 1.0125 | N60: =L60/J60 -> 1 | O60: =N60-M60 -> 1 | P60: sem pendencia | Q60: =J60-SUM(R60:ES60) -> 1.0125
A61: =E61&F61 -> RESPONSIBILITY_PROCESS_RELBANK_ID | B61: Pilar III | C61: Bens Imóveis - Output | D61: 2. Campo | E61: RESPONSIBILITY_PROCESS_REL | F61: BANK_ID | G61: =INDEX(Auxiliar!$B$16:$B$24,MATCH(Plano_V3!H61,Auxiliar!$C$16:$C$24,0),1) -> 1. Concluído | H61: =VLOOKUP(A61,'Aux - pivots1'!$A:$B,2,0) -> 1 | I61: =SUMIFS(Table1[Estimação (horas)],Table1[Tabela],Plano_V3!E61,Table1[Campo],Plano_V3!F61) -> 8.1 | J61: =I61/8 -> 1.0125 | K61: =SUMIFS(Table1[Horas efetivas],Table1[Tabela],Plano_V3!E61,Table1[Campo],Plano_V3!F61) -> 8.1 | L61: =K61/8 -> 1.0125 | N61: =L61/J61 -> 1 | O61: =N61-M61 -> 1 | P61: sem pendencia | Q61: =J61-SUM(R61:ES61) -> 1.0125
A62: =E62&F62 -> RESPONSIBILITY_PROCESS_RELPROCESS_BRANCH_CODE | B62: Pilar III | C62: Bens Imóveis - Output | D62: 2. Campo | E62: RESPONSIBILITY_PROCESS_REL | F62: PROCESS_BRANCH_CODE | G62: =INDEX(Auxiliar!$B$16:$B$24,MATCH(Plano_V3!H62,Auxiliar!$C$16:$C$24,0),1) -> 1. Concluído | H62: =VLOOKUP(A62,'Aux - pivots1'!$A:$B,2,0) -> 1 | I62: =SUMIFS(Table1[Estimação (horas)],Table1[Tabela],Plano_V3!E62,Table1[Campo],Plano_V3!F62) -> 8.1 | J62: =I62/8 -> 1.0125 | K62: =SUMIFS(Table1[Horas efetivas],Table1[Tabela],Plano_V3!E62,Table1[Campo],Plano_V3!F62) -> 8.1 | L62: =K62/8 -> 1.0125 | N62: =L62/J62 -> 1 | O62: =N62-M62 -> 1 | P62: sem pendencia | Q62: =J62-SUM(R62:ES62) -> 1.0125
A63: =E63&F63 -> RESPONSIBILITY_PROCESS_RELBRANCH_CODE | B63: Pilar III | C63: Bens Imóveis - Output | D63: 2. Campo | E63: RESPONSIBILITY_PROCESS_REL | F63: BRANCH_CODE | G63: =INDEX(Auxiliar!$B$16:$B$24,MATCH(Plano_V3!H63,Auxiliar!$C$16:$C$24,0),1) -> 1. Concluído | H63: =VLOOKUP(A63,'Aux - pivots1'!$A:$B,2,0) -> 1 | I63: =SUMIFS(Table1[Estimação (horas)],Table1[Tabela],Plano_V3!E63,Table1[Campo],Plano_V3!F63) -> 8.1 | J63: =I63/8 -> 1.0125 | K63: =SUMIFS(Table1[Horas efetivas],Table1[Tabela],Plano_V3!E63,Table1[Campo],Plano_V3!F63) -> 8.1 | L63: =K63/8 -> 1.0125 | N63: =L63/J63 -> 1 | O63: =N63-M63 -> 1 | P63: sem pendencia | Q63: =J63-SUM(R63:ES63) -> 1.0125
A64: =E64&F64 -> RESPONSIBILITY_PROCESS_RELCONTRACT_ID | B64: Pilar III | C64: Bens Imóveis - Output | D64: 2. Campo | E64: RESPONSIBILITY_PROCESS_REL | F64: CONTRACT_ID | G64: =INDEX(Auxiliar!$B$16:$B$24,MATCH(Plano_V3!H64,Auxiliar!$C$16:$C$24,0),1) -> 1. Concluído | H64: =VLOOKUP(A64,'Aux - pivots1'!$A:$B,2,0) -> 1 | I64: =SUMIFS(Table1[Estimação (horas)],Table1[Tabela],Plano_V3!E64,Table1[Campo],Plano_V3!F64) -> 8.1 | J64: =I64/8 -> 1.0125 | K64: =SUMIFS(Table1[Horas efetivas],Table1[Tabela],Plano_V3!E64,Table1[Campo],Plano_V3!F64) -> 8.1 | L64: =K64/8 -> 1.0125 | N64: =L64/J64 -> 1 | O64: =N64-M64 -> 1 | P64: sem pendencia | Q64: =J64-SUM(R64:ES64) -> 1.0125
A65: =E65&F65 -> RESPONSIBILITY_PROCESS_RELPROCESS_ACCOUNT_ID | B65: Pilar III | C65: Bens Imóveis - Output | D65: 2. Campo | E65: RESPONSIBILITY_PROCESS_REL | F65: PROCESS_ACCOUNT_ID | G65: =INDEX(Auxiliar!$B$16:$B$24,MATCH(Plano_V3!H65,Auxiliar!$C$16:$C$24,0),1) -> 1. Concluído | H65: =VLOOKUP(A65,'Aux - pivots1'!$A:$B,2,0) -> 1 | I65: =SUMIFS(Table1[Estimação (horas)],Table1[Tabela],Plano_V3!E65,Table1[Campo],Plano_V3!F65) -> 8.1 | J65: =I65/8 -> 1.0125 | K65: =SUMIFS(Table1[Horas efetivas],Table1[Tabela],Plano_V3!E65,Table1[Campo],Plano_V3!F65) -> 8.1 | L65: =K65/8 -> 1.0125 | N65: =L65/J65 -> 1 | O65: =N65-M65 -> 1 | P65: sem pendencia | Q65: =J65-SUM(R65:ES65) -> 1.0125
A66: =E66&F66 -> RESPONSIBILITY_PROCESS_RELREFERENCE_CODE | B66: Pilar III | C66: Bens Imóveis - Output | D66: 2. Campo | E66: RESPONSIBILITY_PROCESS_REL | F66: REFERENCE_CODE | G66: =INDEX(Auxiliar!$B$16:$B$24,MATCH(Plano_V3!H66,Auxiliar!$C$16:$C$24,0),1) -> 1. Concluído | H66: =VLOOKUP(A66,'Aux - pivots1'!$A:$B,2,0) -> 1 | I66: =SUMIFS(Table1[Estimação (horas)],Table1[Tabela],Plano_V3!E66,Table1[Campo],Plano_V3!F66) -> 8.1 | J66: =I66/8 -> 1.0125 | K66: =SUMIFS(Table1[Horas efetivas],Table1[Tabela],Plano_V3!E66,Table1[Campo],Plano_V3!F66) -> 8.1 | L66: =K66/8 -> 1.0125 | N66: =L66/J66 -> 1 | O66: =N66-M66 -> 1 | P66: sem pendencia | Q66: =J66-SUM(R66:ES66) -> 1.0125
A67: =E67&F67 -> RESPONSIBILITY_PROCESS_RELPURPOSE_CODE | B67: Pilar III | C67: Bens Imóveis - Output | D67: 2. Campo | E67: RESPONSIBILITY_PROCESS_REL | F67: PURPOSE_CODE | G67: =INDEX(Auxiliar!$B$16:$B$24,MATCH(Plano_V3!H67,Auxiliar!$C$16:$C$24,0),1) -> 1. Concluído | H67: =VLOOKUP(A67,'Aux - pivots1'!$A:$B,2,0) -> 1 | I67: =SUMIFS(Table1[Estimação (horas)],Table1[Tabela],Plano_V3!E67,Table1[Campo],Plano_V3!F67) -> 8.1 | J67: =I67/8 -> 1.0125 | K67: =SUMIFS(Table1[Horas efetivas],Table1[Tabela],Plano_V3!E67,Table1[Campo],Plano_V3!F67) -> 8.1 | L67: =K67/8 -> 1.0125 | N67: =L67/J67 -> 1 | O67: =N67-M67 -> 1 | P67: sem pendencia | Q67: =J67-SUM(R67:ES67) -> 1.0125
A68: =E68&F68 -> RESPONSIBILITY_PROCESS_RELINDIVIDUAL_OCCUPATION_CODE | B68: Pilar III | C68: Bens Imóveis - Output | D68: 2. Campo | E68: RESPONSIBILITY_PROCESS_REL | F68: INDIVIDUAL_OCCUPATION_CODE | G68: =INDEX(Auxiliar!$B$16:$B$24,MATCH(Plano_V3!H68,Auxiliar!$C$16:$C$24,0),1) -> 1. Concluído | H68: =VLOOKUP(A68,'Aux - pivots1'!$A:$B,2,0) -> 1 | I68: =SUMIFS(Table1[Estimação (horas)],Table1[Tabela],Plano_V3!E68,Table1[Campo],Plano_V3!F68) -> 8.1 | J68: =I68/8 -> 1.0125 | K68: =SUMIFS(Table1[Horas efetivas],Table1[Tabela],Plano_V3!E68,Table1[Campo],Plano_V3!F68) -> 8.1 | L68: =K68/8 -> 1.0125 | N68: =L68/J68 -> 1 | O68: =N68-M68 -> 1 | P68: sem pendencia | Q68: =J68-SUM(R68:ES68) -> 1.0125
A69: =E69&F69 -> RESPONSIBILITY_PROCESS_RELPRODUCT_ID | B69: Pilar III | C69: Bens Imóveis - Output | D69: 2. Campo | E69: RESPONSIBILITY_PROCESS_REL | F69: PRODUCT_ID | G69: =INDEX(Auxiliar!$B$16:$B$24,MATCH(Plano_V3!H69,Auxiliar!$C$16:$C$24,0),1) -> 1. Concluído | H69: =VLOOKUP(A69,'Aux - pivots1'!$A:$B,2,0) -> 1 | I69: =SUMIFS(Table1[Estimação (horas)],Table1[Tabela],Plano_V3!E69,Table1[Campo],Plano_V3!F69) -> 8.1 | J69: =I69/8 -> 1.0125 | K69: =SUMIFS(Table1[Horas efetivas],Table1[Tabela],Plano_V3!E69,Table1[Campo],Plano_V3!F69) -> 8.1 | L69: =K69/8 -> 1.0125 | N69: =L69/J69 -> 1 | O69: =N69-M69 -> 1 | P69: sem pendencia | Q69: =J69-SUM(R69:ES69) -> 1.0125
A70: =E70&F70 -> RESPONSIBILITY_PROCESS_RELcod_sit | B70: Pilar III | C70: Bens Imóveis - Output | D70: 2. Campo | E70: RESPONSIBILITY_PROCESS_REL | F70: cod_sit | G70: =INDEX(Auxiliar!$B$16:$B$24,MATCH(Plano_V3!H70,Auxiliar!$C$16:$C$24,0),1) -> 0. Cancelado | H70: =VLOOKUP(A70,'Aux - pivots1'!$A:$B,2,0) -> 0 | I70: 0 | J70: =I70/8 -> 0 | K70: =SUMIFS(Table1[Horas efetivas],Table1[Tabela],Plano_V3!E70,Table1[Campo],Plano_V3!F70) -> 0 | L70: =K70/8 -> 0 | N70: =L70/J70 -> #DIV/0! | O70: =N70-M70 -> #DIV/0! | P70: sem pendencia | Q70: =J70-SUM(R70:ES70) -> 0
A71: =E71&F71 -> RESPONSIBILITY_PROCESS_RELSUBPRODUCT_ID | B71: Pilar III | C71: Bens Imóveis - Output | D71: 2. Campo | E71: RESPONSIBILITY_PROCESS_REL | F71: SUBPRODUCT_ID | G71: =INDEX(Auxiliar!$B$16:$B$24,MATCH(Plano_V3!H71,Auxiliar!$C$16:$C$24,0),1) -> 1. Concluído | H71: =VLOOKUP(A71,'Aux - pivots1'!$A:$B,2,0) -> 1 | I71: =SUMIFS(Table1[Estimação (horas)],Table1[Tabela],Plano_V3!E71,Table1[Campo],Plano_V3!F71) -> 8.1 | J71: =I71/8 -> 1.0125 | K71: =SUMIFS(Table1[Horas efetivas],Table1[Tabela],Plano_V3!E71,Table1[Campo],Plano_V3!F71) -> 8.1 | L71: =K71/8 -> 1.0125 | N71: =L71/J71 -> 1 | O71: =N71-M71 -> 1 | P71: sem pendencia | Q71: =J71-SUM(R71:ES71) -> 1.0125
A72: =E72&F72 -> RESPONSIBILITY_PROCESS_RELPROCESS_REFERENCE_CODE | B72: Pilar III | C72: Bens Imóveis - Output | D72: 2. Campo | E72: RESPONSIBILITY_PROCESS_REL | F72: PROCESS_REFERENCE_CODE | G72: =INDEX(Auxiliar!$B$16:$B$24,MATCH(Plano_V3!H72,Auxiliar!$C$16:$C$24,0),1) -> 1. Concluído | H72: =VLOOKUP(A72,'Aux - pivots1'!$A:$B,2,0) -> 1 | I72: =SUMIFS(Table1[Estimação (horas)],Table1[Tabela],Plano_V3!E72,Table1[Campo],Plano_V3!F72) -> 8.1 | J72: =I72/8 -> 1.0125 | K72: =SUMIFS(Table1[Horas efetivas],Table1[Tabela],Plano_V3!E72,Table1[Campo],Plano_V3!F72) -> 8.1 | L72: =K72/8 -> 1.0125 | N72: =L72/J72 -> 1 | O72: =N72-M72 -> 1 | P72: sem pendencia | Q72: =J72-SUM(R72:ES72) -> 1.0125
A73: =E73&F73 -> RESPONSIBILITY_PROCESS_RELEFFECTIVE_RELATION_END_DATE | B73: Pilar III | C73: Bens Imóveis - Output | D73: 2. Campo | E73: RESPONSIBILITY_PROCESS_REL | F73: EFFECTIVE_RELATION_END_DATE | G73: =INDEX(Auxiliar!$B$16:$B$24,MATCH(Plano_V3!H73,Auxiliar!$C$16:$C$24,0),1) -> 1. Concluído | H73: =VLOOKUP(A73,'Aux - pivots1'!$A:$B,2,0) -> 1 | I73: =SUMIFS(Table1[Estimação (horas)],Table1[Tabela],Plano_V3!E73,Table1[Campo],Plano_V3!F73) -> 8.1 | J73: =I73/8 -> 1.0125 | K73: =SUMIFS(Table1[Horas efetivas],Table1[Tabela],Plano_V3!E73,Table1[Campo],Plano_V3!F73) -> 8.1 | L73: =K73/8 -> 1.0125 | N73: =L73/J73 -> 1 | O73: =N73-M73 -> 1 | P73: sem pendencia | Q73: =J73-SUM(R73:ES73) -> 1.0125
A74: =E74&F74 -> RESPONSIBILITY_PROCESS_RELPROCESS_START_DATE | B74: Pilar III | C74: Bens Imóveis - Output | D74: 2. Campo | E74: RESPONSIBILITY_PROCESS_REL | F74: PROCESS_START_DATE | G74: =INDEX(Auxiliar!$B$16:$B$24,MATCH(Plano_V3!H74,Auxiliar!$C$16:$C$24,0),1) -> 1. Concluído | H74: =VLOOKUP(A74,'Aux - pivots1'!$A:$B,2,0) -> 1 | I74: =SUMIFS(Table1[Estimação (horas)],Table1[Tabela],Plano_V3!E74,Table1[Campo],Plano_V3!F74) -> 8.1 | J74: =I74/8 -> 1.0125 | K74: =SUMIFS(Table1[Horas efetivas],Table1[Tabela],Plano_V3!E74,Table1[Campo],Plano_V3!F74) -> 8.1 | L74: =K74/8 -> 1.0125 | N74: =L74/J74 -> 1 | O74: =N74-M74 -> 1 | P74: sem pendencia | Q74: =J74-SUM(R74:ES74) -> 1.0125
A75: =E75&F75 -> RESPONSIBILITY_PROCESS_RELPROCESS_DUE_DATE | B75: Pilar III | C75: Bens Imóveis - Output | D75: 2. Campo | E75: RESPONSIBILITY_PROCESS_REL | F75: PROCESS_DUE_DATE | G75: =INDEX(Auxiliar!$B$16:$B$24,MATCH(Plano_V3!H75,Auxiliar!$C$16:$C$24,0),1) -> 1. Concluído | H75: =VLOOKUP(A75,'Aux - pivots1'!$A:$B,2,0) -> 1 | I75: =SUMIFS(Table1[Estimação (horas)],Table1[Tabela],Plano_V3!E75,Table1[Campo],Plano_V3!F75) -> 8.1 | J75: =I75/8 -> 1.0125 | K75: =SUMIFS(Table1[Horas efetivas],Table1[Tabela],Plano_V3!E75,Table1[Campo],Plano_V3!F75) -> 8.1 | L75: =K75/8 -> 1.0125 | N75: =L75/J75 -> 1 | O75: =N75-M75 -> 1 | P75: sem pendencia | Q75: =J75-SUM(R75:ES75) -> 1.0125
A76: =E76&F76 -> RESPONSIBILITY_PROCESS_RELidetgar | B76: Pilar III | C76: Bens Imóveis - Output | D76: 2. Campo | E76: RESPONSIBILITY_PROCESS_REL | F76: idetgar | G76: =INDEX(Auxiliar!$B$16:$B$24,MATCH(Plano_V3!H76,Auxiliar!$C$16:$C$24,0),1) -> 0. Cancelado | H76: =VLOOKUP(A76,'Aux - pivots1'!$A:$B,2,0) -> 0 | I76: 0 | J76: =I76/8 -> 0 | K76: =SUMIFS(Table1[Horas efetivas],Table1[Tabela],Plano_V3!E76,Table1[Campo],Plano_V3!F76) -> 0 | L76: =K76/8 -> 0 | N76: =L76/J76 -> #DIV/0! | O76: =N76-M76 -> #DIV/0! | P76: sem pendencia | Q76: =J76-SUM(R76:ES76) -> 0
A77: =E77&F77 -> RESPONSIBILITY_PROCESS_RELnum_prop | B77: Pilar III | C77: Bens Imóveis - Output | D77: 2. Campo | E77: RESPONSIBILITY_PROCESS_REL | F77: num_prop | G77: =INDEX(Auxiliar!$B$16:$B$24,MATCH(Plano_V3!H77,Auxiliar!$C$16:$C$24,0),1) -> 0. Cancelado | H77: =VLOOKUP(A77,'Aux - pivots1'!$A:$B,2,0) -> 0 | I77: 0 | J77: =I77/8 -> 0 | K77: =SUMIFS(Table1[Horas efetivas],Table1[Tabela],Plano_V3!E77,Table1[Campo],Plano_V3!F77) -> 0 | L77: =K77/8 -> 0 | N77: =L77/J77 -> #DIV/0! | O77: =N77-M77 -> #DIV/0! | P77: sem pendencia | Q77: =J77-SUM(R77:ES77) -> 0
A78: =E78&F78 -> RESPONSIBILITY_PROCESS_RELSOURCE_CODE | B78: Pilar III | C78: Bens Imóveis - Output | D78: 2. Campo | E78: RESPONSIBILITY_PROCESS_REL | F78: SOURCE_CODE | G78: =INDEX(Auxiliar!$B$16:$B$24,MATCH(Plano_V3!H78,Auxiliar!$C$16:$C$24,0),1) -> 1. Concluído | H78: =VLOOKUP(A78,'Aux - pivots1'!$A:$B,2,0) -> 1 | I78: =SUMIFS(Table1[Estimação (horas)],Table1[Tabela],Plano_V3!E78,Table1[Campo],Plano_V3!F78) -> 4.1 | J78: =I78/8 -> 0.5125 | K78: =SUMIFS(Table1[Horas efetivas],Table1[Tabela],Plano_V3!E78,Table1[Campo],Plano_V3!F78) -> 4.1 | L78: =K78/8 -> 0.5125 | N78: =L78/J78 -> 1 | O78: =N78-M78 -> 1 | P78: sem pendencia | Q78: =J78-SUM(R78:ES78) -> 0.5125
A79: =E79&F79 -> RESPONSIBILITY_PROCESS_RELDATA_DATE_PART | B79: Pilar III | C79: Bens Imóveis - Output | D79: 2. Campo | E79: RESPONSIBILITY_PROCESS_REL | F79: DATA_DATE_PART | G79: =INDEX(Auxiliar!$B$16:$B$24,MATCH(Plano_V3!H79,Auxiliar!$C$16:$C$24,0),1) -> 1. Concluído | H79: =VLOOKUP(A79,'Aux - pivots1'!$A:$B,2,0) -> 1 | I79: =SUMIFS(Table1[Estimação (horas)],Table1[Tabela],Plano_V3!E79,Table1[Campo],Plano_V3!F79) -> 4.1 | J79: =I79/8 -> 0.5125 | K79: =SUMIFS(Table1[Horas efetivas],Table1[Tabela],Plano_V3!E79,Table1[Campo],Plano_V3!F79) -> 4.1 | L79: =K79/8 -> 0.5125 | N79: =L79/J79 -> 1 | O79: =N79-M79 -> 1 | P79: sem pendencia | Q79: =J79-SUM(R79:ES79) -> 0.5125
A80: =E80&F80 -> PROCESS_PROPERTY_RELn.a. | B80: Pilar III | C80: Bens Imóveis - Output | D80: 1. Universo | E80: PROCESS_PROPERTY_REL | F80: n.a. | G80: =INDEX(Auxiliar!$B$16:$B$24,MATCH(Plano_V3!H80,Auxiliar!$C$16:$C$24,0),1) -> 1. Concluído | H80: =VLOOKUP(A80,'Aux - pivots1'!$A:$B,2,0) -> 1 | I80: =SUMIFS(Table1[Estimação (horas)],Table1[Tabela],Plano_V3!E80,Table1[Campo],Plano_V3!F80) -> 8 | J80: =I80/8 -> 1 | K80: =SUMIFS(Table1[Horas efetivas],Table1[Tabela],Plano_V3!E80,Table1[Campo],Plano_V3!F80) -> 8 | L80: =K80/8 -> 1 | N80: =L80/J80 -> 1 | O80: =N80-M80 -> 1 | P80: cd_imv_out_trz_cred_prc | Q80: =J80-SUM(R80:ES80) -> 1
A81: =E81&F81 -> PROCESS_PROPERTY_RELPROPERTY_BANK_ID | B81: Pilar III | C81: Bens Imóveis - Output | D81: 2. Campo | E81: PROCESS_PROPERTY_REL | F81: PROPERTY_BANK_ID | G81: =INDEX(Auxiliar!$B$16:$B$24,MATCH(Plano_V3!H81,Auxiliar!$C$16:$C$24,0),1) -> 1. Concluído | H81: =VLOOKUP(A81,'Aux - pivots1'!$A:$B,2,0) -> 1 | I81: =SUMIFS(Table1[Estimação (horas)],Table1[Tabela],Plano_V3!E81,Table1[Campo],Plano_V3!F81) -> 4.1 | J81: =I81/8 -> 0.5125 | K81: =SUMIFS(Table1[Horas efetivas],Table1[Tabela],Plano_V3!E81,Table1[Campo],Plano_V3!F81) -> 4.1 | L81: =K81/8 -> 0.5125 | N81: =L81/J81 -> 1 | O81: =N81-M81 -> 1 | P81: cd_imv_out_trz_cred_prc | Q81: =J81-SUM(R81:ES81) -> 0.5125
A82: =E82&F82 -> PROCESS_PROPERTY_RELPROCESS_BANK_ID | B82: Pilar III | C82: Bens Imóveis - Output | D82: 2. Campo | E82: PROCESS_PROPERTY_REL | F82: PROCESS_BANK_ID | G82: =INDEX(Auxiliar!$B$16:$B$24,MATCH(Plano_V3!H82,Auxiliar!$C$16:$C$24,0),1) -> 1. Concluído | H82: =VLOOKUP(A82,'Aux - pivots1'!$A:$B,2,0) -> 1 | I82: =SUMIFS(Table1[Estimação (horas)],Table1[Tabela],Plano_V3!E82,Table1[Campo],Plano_V3!F82) -> 8.1 | J82: =I82/8 -> 1.0125 | K82: =SUMIFS(Table1[Horas efetivas],Table1[Tabela],Plano_V3!E82,Table1[Campo],Plano_V3!F82) -> 8.1 | L82: =K82/8 -> 1.0125 | N82: =L82/J82 -> 1 | O82: =N82-M82 -> 1 | P82: cd_imv_out_trz_cred_prc | Q82: =J82-SUM(R82:ES82) -> 1.0125
A83: =E83&F83 -> PROCESS_PROPERTY_RELPROPERTY_BRANCH_CODE | B83: Pilar III | C83: Bens Imóveis - Output | D83: 2. Campo | E83: PROCESS_PROPERTY_REL | F83: PROPERTY_BRANCH_CODE | G83: =INDEX(Auxiliar!$B$16:$B$24,MATCH(Plano_V3!H83,Auxiliar!$C$16:$C$24,0),1) -> 1. Concluído | H83: =VLOOKUP(A83,'Aux - pivots1'!$A:$B,2,0) -> 1 | I83: =SUMIFS(Table1[Estimação (horas)],Table1[Tabela],Plano_V3!E83,Table1[Campo],Plano_V3!F83) -> 8.1 | J83: =I83/8 -> 1.0125 | K83: =SUMIFS(Table1[Horas efetivas],Table1[Tabela],Plano_V3!E83,Table1[Campo],Plano_V3!F83) -> 8.1 | L83: =K83/8 -> 1.0125 | N83: =L83/J83 -> 1 | O83: =N83-M83 -> 1 | P83: cd_imv_out_trz_cred_prc | Q83: =J83-SUM(R83:ES83) -> 1.0125
A84: =E84&F84 -> PROCESS_PROPERTY_RELPROCESS_BRANCH_CODE | B84: Pilar III | C84: Bens Imóveis - Output | D84: 2. Campo | E84: PROCESS_PROPERTY_REL | F84: PROCESS_BRANCH_CODE | G84: =INDEX(Auxiliar!$B$16:$B$24,MATCH(Plano_V3!H84,Auxiliar!$C$16:$C$24,0),1) -> 1. Concluído | H84: =VLOOKUP(A84,'Aux - pivots1'!$A:$B,2,0) -> 1 | I84: =SUMIFS(Table1[Estimação (horas)],Table1[Tabela],Plano_V3!E84,Table1[Campo],Plano_V3!F84) -> 8.1 | J84: =I84/8 -> 1.0125 | K84: =SUMIFS(Table1[Horas efetivas],Table1[Tabela],Plano_V3!E84,Table1[Campo],Plano_V3!F84) -> 8.1 | L84: =K84/8 -> 1.0125 | N84: =L84/J84 -> 1 | O84: =N84-M84 -> 1 | P84: cd_imv_out_trz_cred_prc | Q84: =J84-SUM(R84:ES84) -> 1.0125
A85: =E85&F85 -> PROCESS_PROPERTY_RELPROPERTY_CONTRACT_ID | B85: Pilar III | C85: Bens Imóveis - Output | D85: 2. Campo | E85: PROCESS_PROPERTY_REL | F85: PROPERTY_CONTRACT_ID | G85: =INDEX(Auxiliar!$B$16:$B$24,MATCH(Plano_V3!H85,Auxiliar!$C$16:$C$24,0),1) -> 1. Concluído | H85: =VLOOKUP(A85,'Aux - pivots1'!$A:$B,2,0) -> 1 | I85: =SUMIFS(Table1[Estimação (horas)],Table1[Tabela],Plano_V3!E85,Table1[Campo],Plano_V3!F85) -> 8.1 | J85: =I85/8 -> 1.0125 | K85: =SUMIFS(Table1[Horas efetivas],Table1[Tabela],Plano_V3!E85,Table1[Campo],Plano_V3!F85) -> 8.1 | L85: =K85/8 -> 1.0125 | N85: =L85/J85 -> 1 | O85: =N85-M85 -> 1 | P85: cd_imv_out_trz_cred_prc | Q85: =J85-SUM(R85:ES85) -> 1.0125
A86: =E86&F86 -> PROCESS_PROPERTY_RELPROCESS_ACCOUNT_ID | B86: Pilar III | C86: Bens Imóveis - Output | D86: 2. Campo | E86: PROCESS_PROPERTY_REL | F86: PROCESS_ACCOUNT_ID | G86: =INDEX(Auxiliar!$B$16:$B$24,MATCH(Plano_V3!H86,Auxiliar!$C$16:$C$24,0),1) -> 1. Concluído | H86: =VLOOKUP(A86,'Aux - pivots1'!$A:$B,2,0) -> 1 | I86: =SUMIFS(Table1[Estimação (horas)],Table1[Tabela],Plano_V3!E86,Table1[Campo],Plano_V3!F86) -> 8.1 | J86: =I86/8 -> 1.0125 | K86: =SUMIFS(Table1[Horas efetivas],Table1[Tabela],Plano_V3!E86,Table1[Campo],Plano_V3!F86) -> 8.1 | L86: =K86/8 -> 1.0125 | N86: =L86/J86 -> 1 | O86: =N86-M86 -> 1 | P86: cd_imv_out_trz_cred_prc | Q86: =J86-SUM(R86:ES86) -> 1.0125
A87: =E87&F87 -> PROCESS_PROPERTY_RELPROPERTY_REFERENCE_CODE | B87: Pilar III | C87: Bens Imóveis - Output | D87: 2. Campo | E87: PROCESS_PROPERTY_REL | F87: PROPERTY_REFERENCE_CODE | G87: =INDEX(Auxiliar!$B$16:$B$24,MATCH(Plano_V3!H87,Auxiliar!$C$16:$C$24,0),1) -> 1. Concluído | H87: =VLOOKUP(A87,'Aux - pivots1'!$A:$B,2,0) -> 1 | I87: =SUMIFS(Table1[Estimação (horas)],Table1[Tabela],Plano_V3!E87,Table1[Campo],Plano_V3!F87) -> 4.1 | J87: =I87/8 -> 0.5125 | K87: =SUMIFS(Table1[Horas efetivas],Table1[Tabela],Plano_V3!E87,Table1[Campo],Plano_V3!F87) -> 4.1 | L87: =K87/8 -> 0.5125 | N87: =L87/J87 -> 1 | O87: =N87-M87 -> 1 | P87: cd_imv_out_trz_cred_prc | Q87: =J87-SUM(R87:ES87) -> 0.5125
A88: =E88&F88 -> PROCESS_PROPERTY_RELPROCESS_REFERENCE_CODE | B88: Pilar III | C88: Bens Imóveis - Output | D88: 2. Campo | E88: PROCESS_PROPERTY_REL | F88: PROCESS_REFERENCE_CODE | G88: =INDEX(Auxiliar!$B$16:$B$24,MATCH(Plano_V3!H88,Auxiliar!$C$16:$C$24,0),1) -> 1. Concluído | H88: =VLOOKUP(A88,'Aux - pivots1'!$A:$B,2,0) -> 1 | I88: =SUMIFS(Table1[Estimação (horas)],Table1[Tabela],Plano_V3!E88,Table1[Campo],Plano_V3!F88) -> 8.1 | J88: =I88/8 -> 1.0125 | K88: =SUMIFS(Table1[Horas efetivas],Table1[Tabela],Plano_V3!E88,Table1[Campo],Plano_V3!F88) -> 8.1 | L88: =K88/8 -> 1.0125 | N88: =L88/J88 -> 1 | O88: =N88-M88 -> 1 | P88: cd_imv_out_trz_cred_prc | Q88: =J88-SUM(R88:ES88) -> 1.0125
A89: =E89&F89 -> PROCESS_PROPERTY_RELdata_assc | B89: Pilar III | C89: Bens Imóveis - Output | D89: 2. Campo | E89: PROCESS_PROPERTY_REL | F89: data_assc | G89: =INDEX(Auxiliar!$B$16:$B$24,MATCH(Plano_V3!H89,Auxiliar!$C$16:$C$24,0),1) -> 0. Cancelado | H89: =VLOOKUP(A89,'Aux - pivots1'!$A:$B,2,0) -> 0 | I89: 0 | J89: =I89/8 -> 0 | K89: =SUMIFS(Table1[Horas efetivas],Table1[Tabela],Plano_V3!E89,Table1[Campo],Plano_V3!F89) -> 0 | L89: =K89/8 -> 0 | N89: =L89/J89 -> #DIV/0! | O89: =N89-M89 -> #DIV/0! | P89: cd_imv_out_trz_cred_prc | Q89: =J89-SUM(R89:ES89) -> 0
A90: =E90&F90 -> PROCESS_PROPERTY_RELSEIZED_PROPERTY_IND | B90: Pilar III | C90: Bens Imóveis - Output | D90: 2. Campo | E90: PROCESS_PROPERTY_REL | F90: SEIZED_PROPERTY_IND | G90: =INDEX(Auxiliar!$B$16:$B$24,MATCH(Plano_V3!H90,Auxiliar!$C$16:$C$24,0),1) -> 1. Concluído | H90: =VLOOKUP(A90,'Aux - pivots1'!$A:$B,2,0) -> 1 | I90: =SUMIFS(Table1[Estimação (horas)],Table1[Tabela],Plano_V3!E90,Table1[Campo],Plano_V3!F90) -> 4.1 | J90: =I90/8 -> 0.5125 | K90: =SUMIFS(Table1[Horas efetivas],Table1[Tabela],Plano_V3!E90,Table1[Campo],Plano_V3!F90) -> 4.1 | L90: =K90/8 -> 0.5125 | N90: =L90/J90 -> 1 | O90: =N90-M90 -> 1 | P90: cd_imv_out_trz_cred_prc | Q90: =J90-SUM(R90:ES90) -> 0.5125
A91: =E91&F91 -> PROCESS_PROPERTY_RELCOLLATERAL_PROPERTY_IND | B91: Pilar III | C91: Bens Imóveis - Output | D91: 2. Campo | E91: PROCESS_PROPERTY_REL | F91: COLLATERAL_PROPERTY_IND | G91: =INDEX(Auxiliar!$B$16:$B$24,MATCH(Plano_V3!H91,Auxiliar!$C$16:$C$24,0),1) -> 1. Concluído | H91: =VLOOKUP(A91,'Aux - pivots1'!$A:$B,2,0) -> 1 | I91: =SUMIFS(Table1[Estimação (horas)],Table1[Tabela],Plano_V3!E91,Table1[Campo],Plano_V3!F91) -> 4.1 | J91: =I91/8 -> 0.5125 | K91: =SUMIFS(Table1[Horas efetivas],Table1[Tabela],Plano_V3!E91,Table1[Campo],Plano_V3!F91) -> 4.1 | L91: =K91/8 -> 0.5125 | N91: =L91/J91 -> 1 | O91: =N91-M91 -> 1 | P91: cd_imv_out_trz_cred_prc | Q91: =J91-SUM(R91:ES91) -> 0.5125
A92: =E92&F92 -> PROCESS_PROPERTY_RELFINANCED_PROPERTY_IND | B92: Pilar III | C92: Bens Imóveis - Output | D92: 2. Campo | E92: PROCESS_PROPERTY_REL | F92: FINANCED_PROPERTY_IND | G92: =INDEX(Auxiliar!$B$16:$B$24,MATCH(Plano_V3!H92,Auxiliar!$C$16:$C$24,0),1) -> 1. Concluído | H92: =VLOOKUP(A92,'Aux - pivots1'!$A:$B,2,0) -> 1 | I92: =SUMIFS(Table1[Estimação (horas)],Table1[Tabela],Plano_V3!E92,Table1[Campo],Plano_V3!F92) -> 4.1 | J92: =I92/8 -> 0.5125 | K92: =SUMIFS(Table1[Horas efetivas],Table1[Tabela],Plano_V3!E92,Table1[Campo],Plano_V3!F92) -> 4.1 | L92: =K92/8 -> 0.5125 | N92: =L92/J92 -> 1 | O92: =N92-M92 -> 1 | P92: cd_imv_out_trz_cred_prc | Q92: =J92-SUM(R92:ES92) -> 0.5125
A93: =E93&F93 -> PROCESS_PROPERTY_RELOWNED_PROPERTY_IND | B93: Pilar III | C93: Bens Imóveis - Output | D93: 2. Campo | E93: PROCESS_PROPERTY_REL | F93: OWNED_PROPERTY_IND | G93: =INDEX(Auxiliar!$B$16:$B$24,MATCH(Plano_V3!H93,Auxiliar!$C$16:$C$24,0),1) -> 1. Concluído | H93: =VLOOKUP(A93,'Aux - pivots1'!$A:$B,2,0) -> 1 | I93: =SUMIFS(Table1[Estimação (horas)],Table1[Tabela],Plano_V3!E93,Table1[Campo],Plano_V3!F93) -> 4.1 | J93: =I93/8 -> 0.5125 | K93: =SUMIFS(Table1[Horas efetivas],Table1[Tabela],Plano_V3!E93,Table1[Campo],Plano_V3!F93) -> 4.1 | L93: =K93/8 -> 0.5125 | N93: =L93/J93 -> 1 | O93: =N93-M93 -> 1 | P93: cd_imv_out_trz_cred_prc | Q93: =J93-SUM(R93:ES93) -> 0.5125
A94: =E94&F94 -> PROCESS_PROPERTY_RELSOURCE_CODE | B94: Pilar III | C94: Bens Imóveis - Output | D94: 2. Campo | E94: PROCESS_PROPERTY_REL | F94: SOURCE_CODE | G94: =INDEX(Auxiliar!$B$16:$B$24,MATCH(Plano_V3!H94,Auxiliar!$C$16:$C$24,0),1) -> 1. Concluído | H94: =VLOOKUP(A94,'Aux - pivots1'!$A:$B,2,0) -> 1 | I94: =SUMIFS(Table1[Estimação (horas)],Table1[Tabela],Plano_V3!E94,Table1[Campo],Plano_V3!F94) -> 4.1 | J94: =I94/8 -> 0.5125 | K94: =SUMIFS(Table1[Horas efetivas],Table1[Tabela],Plano_V3!E94,Table1[Campo],Plano_V3!F94) -> 4.1 | L94: =K94/8 -> 0.5125 | N94: =L94/J94 -> 1 | O94: =N94-M94 -> 1 | P94: cd_imv_out_trz_cred_prc | Q94: =J94-SUM(R94:ES94) -> 0.5125
A95: =E95&F95 -> PROCESS_PROPERTY_RELDATA_DATE_PART | B95: Pilar III | C95: Bens Imóveis - Output | D95: 2. Campo | E95: PROCESS_PROPERTY_REL | F95: DATA_DATE_PART | G95: =INDEX(Auxiliar!$B$16:$B$24,MATCH(Plano_V3!H95,Auxiliar!$C$16:$C$24,0),1) -> 1. Concluído | H95: =VLOOKUP(A95,'Aux - pivots1'!$A:$B,2,0) -> 1 | I95: =SUMIFS(Table1[Estimação (horas)],Table1[Tabela],Plano_V3!E95,Table1[Campo],Plano_V3!F95) -> 4.1 | J95: =I95/8 -> 0.5125 | K95: =SUMIFS(Table1[Horas efetivas],Table1[Tabela],Plano_V3!E95,Table1[Campo],Plano_V3!F95) -> 4.1 | L95: =K95/8 -> 0.5125 | N95: =L95/J95 -> 1 | O95: =N95-M95 -> 1 | P95: cd_imv_out_trz_cred_prc | Q95: =J95-SUM(R95:ES95) -> 0.5125
A96: =E96&F96 -> PROPERTYn.a. | B96: Pilar III | C96: Bens Imóveis - Output | D96: 1. Universo | E96: PROPERTY | F96: n.a. | G96: =INDEX(Auxiliar!$B$16:$B$24,MATCH(Plano_V3!H96,Auxiliar!$C$16:$C$24,0),1) -> 1. Concluído | H96: =VLOOKUP(A96,'Aux - pivots1'!$A:$B,2,0) -> 1 | I96: =SUMIFS(Table1[Estimação (horas)],Table1[Tabela],Plano_V3!E96,Table1[Campo],Plano_V3!F96) -> 8 | J96: =I96/8 -> 1 | K96: =SUMIFS(Table1[Horas efetivas],Table1[Tabela],Plano_V3!E96,Table1[Campo],Plano_V3!F96) -> 8 | L96: =K96/8 -> 1 | N96: =L96/J96 -> 1 | O96: =N96-M96 -> 1 | P96: cd_imv_out_trz_prc_bens_imv ; cd_imv_out_prc ; cd_imv_out_trz_cred_prc | Q96: =J96-SUM(R96:ES96) -> 1
A97: =E97&F97 -> PROPERTYCONSTRUCTION_YEAR | B97: Pilar III | C97: Bens Imóveis - Output | D97: 2. Campo | E97: PROPERTY | F97: CONSTRUCTION_YEAR | G97: =INDEX(Auxiliar!$B$16:$B$24,MATCH(Plano_V3!H97,Auxiliar!$C$16:$C$24,0),1) -> 1. Concluído | H97: =VLOOKUP(A97,'Aux - pivots1'!$A:$B,2,0) -> 1 | I97: 0 | J97: =I97/8 -> 0 | K97: =SUMIFS(Table1[Horas efetivas],Table1[Tabela],Plano_V3!E97,Table1[Campo],Plano_V3!F97) -> 4 | L97: =K97/8 -> 0.5 | N97: =L97/J97 -> #DIV/0! | O97: =N97-M97 -> #DIV/0! | P97: cd_imv_out_trz_prc_bens_imv ; cd_imv_out_prc ; cd_imv_out_trz_cred_prc | Q97: =J97-SUM(R97:ES97) -> 0
A98: =E98&F98 -> PROPERTYNET_FLOOR_AREA | B98: Pilar III | C98: Bens Imóveis - Output | D98: 2. Campo | E98: PROPERTY | F98: NET_FLOOR_AREA | G98: =INDEX(Auxiliar!$B$16:$B$24,MATCH(Plano_V3!H98,Auxiliar!$C$16:$C$24,0),1) -> 1. Concluído | H98: =VLOOKUP(A98,'Aux - pivots1'!$A:$B,2,0) -> 1 | I98: =SUMIFS(Table1[Estimação (horas)],Table1[Tabela],Plano_V3!E98,Table1[Campo],Plano_V3!F98) -> 8.1 | J98: =I98/8 -> 1.0125 | K98: =SUMIFS(Table1[Horas efetivas],Table1[Tabela],Plano_V3!E98,Table1[Campo],Plano_V3!F98) -> 8.1 | L98: =K98/8 -> 1.0125 | N98: =L98/J98 -> 1 | O98: =N98-M98 -> 1 | P98: cd_imv_out_trz_prc_bens_imv ; cd_imv_out_prc ; cd_imv_out_trz_cred_prc | Q98: =J98-SUM(R98:ES98) -> 1.0125
A99: =E99&F99 -> PROPERTYPROPERTY_BANK_ID | B99: Pilar III | C99: Bens Imóveis - Output | D99: 2. Campo | E99: PROPERTY | F99: PROPERTY_BANK_ID | G99: =INDEX(Auxiliar!$B$16:$B$24,MATCH(Plano_V3!H99,Auxiliar!$C$16:$C$24,0),1) -> 1. Concluído | H99: =VLOOKUP(A99,'Aux - pivots1'!$A:$B,2,0) -> 1 | I99: =SUMIFS(Table1[Estimação (horas)],Table1[Tabela],Plano_V3!E99,Table1[Campo],Plano_V3!F99) -> 4.1 | J99: =I99/8 -> 0.5125 | K99: =SUMIFS(Table1[Horas efetivas],Table1[Tabela],Plano_V3!E99,Table1[Campo],Plano_V3!F99) -> 4.1 | L99: =K99/8 -> 0.5125 | N99: =L99/J99 -> 1 | O99: =N99-M99 -> 1 | P99: cd_imv_out_trz_prc_bens_imv ; cd_imv_out_prc ; cd_imv_out_trz_cred_prc | Q99: =J99-SUM(R99:ES99) -> 0.5125
A100: =E100&F100 -> PROPERTYPROPERTY_BRANCH_CODE | B100: Pilar III | C100: Bens Imóveis - Output | D100: 2. Campo | E100: PROPERTY | F100: PROPERTY_BRANCH_CODE | G100: =INDEX(Auxiliar!$B$16:$B$24,MATCH(Plano_V3!H100,Auxiliar!$C$16:$C$24,0),1) -> 1. Concluído | H100: =VLOOKUP(A100,'Aux - pivots1'!$A:$B,2,0) -> 1 | I100: =SUMIFS(Table1[Estimação (horas)],Table1[Tabela],Plano_V3!E100,Table1[Campo],Plano_V3!F100) -> 4.1 | J100: =I100/8 -> 0.5125 | K100: =SUMIFS(Table1[Horas efetivas],Table1[Tabela],Plano_V3!E100,Table1[Campo],Plano_V3!F100) -> 4.1 | L100: =K100/8 -> 0.5125 | N100: =L100/J100 -> 1 | O100: =N100-M100 -> 1 | P100: cd_imv_out_trz_prc_bens_imv ; cd_imv_out_prc ; cd_imv_out_trz_cred_prc | Q100: =J100-SUM(R100:ES100) -> 0.5125
A101: =E101&F101 -> PROPERTYPROPERTY_CONTRACT_ID | B101: Pilar III | C101: Bens Imóveis - Output | D101: 2. Campo | E101: PROPERTY | F101: PROPERTY_CONTRACT_ID | G101: =INDEX(Auxiliar!$B$16:$B$24,MATCH(Plano_V3!H101,Auxiliar!$C$16:$C$24,0),1) -> 1. Concluído | H101: =VLOOKUP(A101,'Aux - pivots1'!$A:$B,2,0) -> 1 | I101: =SUMIFS(Table1[Estimação (horas)],Table1[Tabela],Plano_V3!E101,Table1[Campo],Plano_V3!F101) -> 4.1 | J101: =I101/8 -> 0.5125 | K101: =SUMIFS(Table1[Horas efetivas],Table1[Tabela],Plano_V3!E101,Table1[Campo],Plano_V3!F101) -> 4.1 | L101: =K101/8 -> 0.5125 | N101: =L101/J101 -> 1 | O101: =N101-M101 -> 1 | P101: cd_imv_out_trz_prc_bens_imv ; cd_imv_out_prc ; cd_imv_out_trz_cred_prc | Q101: =J101-SUM(R101:ES101) -> 0.5125
A102: =E102&F102 -> PROPERTYPROPERTY_REFERENCE_CODE | B102: Pilar III | C102: Bens Imóveis - Output | D102: 2. Campo | E102: PROPERTY | F102: PROPERTY_REFERENCE_CODE | G102: =INDEX(Auxiliar!$B$16:$B$24,MATCH(Plano_V3!H102,Auxiliar!$C$16:$C$24,0),1) -> 1. Concluído | H102: =VLOOKUP(A102,'Aux - pivots1'!$A:$B,2,0) -> 1 | I102: =SUMIFS(Table1[Estimação (horas)],Table1[Tabela],Plano_V3!E102,Table1[Campo],Plano_V3!F102) -> 4.1 | J102: =I102/8 -> 0.5125 | K102: =SUMIFS(Table1[Horas efetivas],Table1[Tabela],Plano_V3!E102,Table1[Campo],Plano_V3!F102) -> 4.1 | L102: =K102/8 -> 0.5125 | N102: =L102/J102 -> 1 | O102: =N102-M102 -> 1 | P102: cd_imv_out_trz_prc_bens_imv ; cd_imv_out_prc ; cd_imv_out_trz_cred_prc | Q102: =J102-SUM(R102:ES102) -> 0.5125
A103: =E103&F103 -> PROPERTYCADASTRAL_REGISTER_CODE | B103: Pilar III | C103: Bens Imóveis - Output | D103: 2. Campo | E103: PROPERTY | F103: CADASTRAL_REGISTER_CODE | G103: =INDEX(Auxiliar!$B$16:$B$24,MATCH(Plano_V3!H103,Auxiliar!$C$16:$C$24,0),1) -> 1. Concluído | H103: =VLOOKUP(A103,'Aux - pivots1'!$A:$B,2,0) -> 1 | I103: =SUMIFS(Table1[Estimação (horas)],Table1[Tabela],Plano_V3!E103,Table1[Campo],Plano_V3!F103) -> 4.1 | J103: =I103/8 -> 0.5125 | K103: =SUMIFS(Table1[Horas efetivas],Table1[Tabela],Plano_V3!E103,Table1[Campo],Plano_V3!F103) -> 4.1 | L103: =K103/8 -> 0.5125 | N103: =L103/J103 -> 1 | O103: =N103-M103 -> 1 | P103: cd_imv_out_trz_prc_bens_imv ; cd_imv_out_prc ; cd_imv_out_trz_cred_prc | Q103: =J103-SUM(R103:ES103) -> 0.5125
A104: =E104&F104 -> PROPERTYAPPRAISAL_CODE | B104: Pilar III | C104: Bens Imóveis - Output | D104: 2. Campo | E104: PROPERTY | F104: APPRAISAL_CODE | G104: =INDEX(Auxiliar!$B$16:$B$24,MATCH(Plano_V3!H104,Auxiliar!$C$16:$C$24,0),1) -> 1. Concluído | H104: =VLOOKUP(A104,'Aux - pivots1'!$A:$B,2,0) -> 1 | I104: =SUMIFS(Table1[Estimação (horas)],Table1[Tabela],Plano_V3!E104,Table1[Campo],Plano_V3!F104) -> 4.1 | J104: =I104/8 -> 0.5125 | K104: =SUMIFS(Table1[Horas efetivas],Table1[Tabela],Plano_V3!E104,Table1[Campo],Plano_V3!F104) -> 4.1 | L104: =K104/8 -> 0.5125 | N104: =L104/J104 -> 1 | O104: =N104-M104 -> 1 | P104: cd_imv_out_trz_prc_bens_imv ; cd_imv_out_prc ; cd_imv_out_trz_cred_prc | Q104: =J104-SUM(R104:ES104) -> 0.5125
A105: =E105&F105 -> PROPERTYcod_bem | B105: Pilar III | C105: Bens Imóveis - Output | D105: 2. Campo | E105: PROPERTY | F105: cod_bem | G105: =INDEX(Auxiliar!$B$16:$B$24,MATCH(Plano_V3!H105,Auxiliar!$C$16:$C$24,0),1) -> 0. Cancelado | H105: =VLOOKUP(A105,'Aux - pivots1'!$A:$B,2,0) -> 0 | I105: 0 | J105: =I105/8 -> 0 | K105: =SUMIFS(Table1[Horas efetivas],Table1[Tabela],Plano_V3!E105,Table1[Campo],Plano_V3!F105) -> 0 | L105: =K105/8 -> 0 | N105: =L105/J105 -> #DIV/0! | O105: =N105-M105 -> #DIV/0! | P105: cd_imv_out_trz_prc_bens_imv ; cd_imv_out_prc ; cd_imv_out_trz_cred_prc | Q105: =J105-SUM(R105:ES105) -> 0
A106: =E106&F106 -> PROPERTYDISTRICT_MUNICIP_PARISH_CODE | B106: Pilar III | C106: Bens Imóveis - Output | D106: 2. Campo | E106: PROPERTY | F106: DISTRICT_MUNICIP_PARISH_CODE | G106: =INDEX(Auxiliar!$B$16:$B$24,MATCH(Plano_V3!H106,Auxiliar!$C$16:$C$24,0),1) -> 1. Concluído | H106: =VLOOKUP(A106,'Aux - pivots1'!$A:$B,2,0) -> 1 | I106: =SUMIFS(Table1[Estimação (horas)],Table1[Tabela],Plano_V3!E106,Table1[Campo],Plano_V3!F106) -> 4.1 | J106: =I106/8 -> 0.5125 | K106: =SUMIFS(Table1[Horas efetivas],Table1[Tabela],Plano_V3!E106,Table1[Campo],Plano_V3!F106) -> 4.1 | L106: =K106/8 -> 0.5125 | N106: =L106/J106 -> 1 | O106: =N106-M106 -> 1 | P106: cd_imv_out_trz_prc_bens_imv ; cd_imv_out_prc ; cd_imv_out_trz_cred_prc | Q106: =J106-SUM(R106:ES106) -> 0.5125
A107: =E107&F107 -> PROPERTYPROPERTY_PURPOSE_CODE | B107: Pilar III | C107: Bens Imóveis - Output | D107: 2. Campo | E107: PROPERTY | F107: PROPERTY_PURPOSE_CODE | G107: =INDEX(Auxiliar!$B$16:$B$24,MATCH(Plano_V3!H107,Auxiliar!$C$16:$C$24,0),1) -> 1. Concluído | H107: =VLOOKUP(A107,'Aux - pivots1'!$A:$B,2,0) -> 1 | I107: =SUMIFS(Table1[Estimação (horas)],Table1[Tabela],Plano_V3!E107,Table1[Campo],Plano_V3!F107) -> 4.1 | J107: =I107/8 -> 0.5125 | K107: =SUMIFS(Table1[Horas efetivas],Table1[Tabela],Plano_V3!E107,Table1[Campo],Plano_V3!F107) -> 4.1 | L107: =K107/8 -> 0.5125 | N107: =L107/J107 -> 1 | O107: =N107-M107 -> 1 | P107: cd_imv_out_trz_prc_bens_imv ; cd_imv_out_prc ; cd_imv_out_trz_cred_prc | Q107: =J107-SUM(R107:ES107) -> 0.5125
A108: =E108&F108 -> PROPERTYPROPERTY_LIFETIME_CODE | B108: Pilar III | C108: Bens Imóveis - Output | D108: 2. Campo | E108: PROPERTY | F108: PROPERTY_LIFETIME_CODE | G108: =INDEX(Auxiliar!$B$16:$B$24,MATCH(Plano_V3!H108,Auxiliar!$C$16:$C$24,0),1) -> 1. Concluído | H108: =VLOOKUP(A108,'Aux - pivots1'!$A:$B,2,0) -> 1 | I108: =SUMIFS(Table1[Estimação (horas)],Table1[Tabela],Plano_V3!E108,Table1[Campo],Plano_V3!F108) -> 4.1 | J108: =I108/8 -> 0.5125 | K108: =SUMIFS(Table1[Horas efetivas],Table1[Tabela],Plano_V3!E108,Table1[Campo],Plano_V3!F108) -> 4.1 | L108: =K108/8 -> 0.5125 | N108: =L108/J108 -> 1 | O108: =N108-M108 -> 1 | P108: cd_imv_out_trz_prc_bens_imv ; cd_imv_out_prc ; cd_imv_out_trz_cred_prc | Q108: =J108-SUM(R108:ES108) -> 0.5125
...

Sheet Aux - pivots1
A3: concat | B3: Max of Status2 | C3: Max of Data de incidência / pedido esclarecimento | D3: Max of Data de correção/resposta prevista | E3: Max of Data de correção/resposta efetiva
A4: ENERGY_CERTIFICATE_EST_INPUTACTUAL_VALUE_IND | B4: 7 | C4: 45510 | D4: 45624
A5: ENERGY_CERTIFICATE_EST_INPUTCARBON_EMISSION_VALUE_YEAR | B5: 7 | C5: 45510 | D5: 45624
A6: ENERGY_CERTIFICATE_EST_INPUTDATA_EXTRACTION_DATE | B6: 7 | C6: 45510 | D6: 45624
A7: ENERGY_CERTIFICATE_EST_INPUTDATA_PROVIDER | B7: 7 | C7: 45510 | D7: 45624
A8: ENERGY_CERTIFICATE_EST_INPUTENCRYPTED_KEY | B8: 7 | C8: 45510 | D8: 45624
A9: ENERGY_CERTIFICATE_EST_INPUTENERGY_CONSUMPTION_VALUE_YEAR | B9: 7 | C9: 45510 | D9: 45624
A10: ENERGY_CERTIFICATE_EST_INPUTEPC | B10: 7 | C10: 45510 | D10: 45624
A11: ENERGY_CERTIFICATE_EST_INPUTn.a. | B11: 7 | C11: 45510 | D11: 45624
A12: ENERGY_CERTIFICATE_EST_INPUTPROPERTY_BANK_ID | B12: 7 | C12: 45510 | D12: 45624
A13: ENERGY_CERTIFICATE_EST_INPUTPROPERTY_BRANCH_CODE | B13: 7 | C13: 45510 | D13: 45624
A14: ENERGY_CERTIFICATE_EST_INPUTPROPERTY_CONTRACT_ID | B14: 7 | C14: 45510 | D14: 45624
A15: ENERGY_CERTIFICATE_EST_INPUTPROPERTY_REFERENCE_CODE | B15: 7 | C15: 45510 | D15: 45624
A16: ENERGY_CERTIFICATE_EST_INPUTQUALITY_SCORE | B16: 7 | C16: 45510 | D16: 45624
A17: lt002_instrumentaccmltd_chngs_fv_cr_instrmnt | B17: 1
A18: lt002_instrumentaccmltd_imprmnt_instrmnt | B18: 1
A19: lt002_instrumentaccntng_clssfctn | B19: 1
A20: lt002_instrumentcod_soc | B20: 1
A21: lt002_instrumentdflt_stts_instrmnt | B21: 1
A22: lt002_instrumentdt_incptn | B22: 1
A23: lt002_instrumentdt_lgl_fnl_mtrty | B23: 1
A24: lt002_instrumentdt_rfrnc | B24: 1
A25: lt002_instrumentgrss_cmmssn_incm | B25: 2
A26: lt002_instrumentgrss_cmmssn_incm_off_blnc | B26: 2
A27: lt002_instrumentgrss_crryng_amnt_instrmnt | B27: 1
A28: lt002_instrumentgrss_intrst_incm | B28: 2
... A34: lt002_instrumentlcl_instmrnt_id | B34: 1
A35: lt002_instrumentlns_clltrlzd_clssfctn | B35: 1 | C35: 45583 | D35: 45589 | E35: 45589
A36: lt002_instrumentmthd_usd_instrmnt_scp_1 | B36: 7 | C36: 45593 | D36: 45611
A37: lt002_instrumentmthd_usd_instrmnt_scp_2 | B37: 7 | C37: 45593 | D37: 45611
A38: lt002_instrumentmthd_usd_instrmnt_scp_3 | B38: 7 | C38: 45593 | D38: 45611
A39: lt002_instrumentprfrmng_stts | B39: 1
A40: lt002_instrumentprjct_fnnc_ln | B40: 1
A41: lt002_instrumentprmry_asst_clssf | B41: 1
A42: lt002_instrumentrsk_mtgtd_ccp | B42: 7 | C42: 45595 | D42: 374342
A43: lt002_instrumentrsk_mtgtd_cct | B43: 7 | C43: 45595 | D43: 374329
A44: lt002_instrumentsstnbl_ctgry_txnmy | B44: 7 | C44: 45593 | D44: 45624
A45: lt002_instrumentsubportfolio_id | B45: 1
A46: lt002_instrumenttyp_instrmnt | B46: 1
A47: lt003_entityannl_trnvr_le | B47: 1
A48: lt003_entitycntrprty_emssns_scp1 | B48: 4 | D48: 45621 | E48: 45596
A49: lt003_entitycntrprty_emssns_scp2 | B49: 4 | D49: 45621 | E49: 45596
A50: lt003_entitycntrprty_emssns_scp3 | B50: 4 | D50: 45621 | E50: 45596
A51: lt003_entitycntry | B51: 1
A52: lt003_entitycod_soc | B52: 1
A53: lt003_entitydt_rfrnc | B53: 1
A54: lt003_entityecnmc_actvty | B54: 1
A55: lt003_entityenblng_capex_cca | B55: 4 | D55: 45614 | E55: 45596
A56: lt003_entityenblng_capex_ccm | B56: 4 | D56: 45614 | E56: 45596
A57: lt003_entityenblng_trnvr_cca | B57: 4 | D57: 45614 | E57: 45596
A58: lt003_entityenblng_trnvr_ccm | B58: 4 | D58: 45614 | E58: 45596
A59: lt003_entityentty_id | B59: 1
A60: lt003_entityeqty | B60: 1
A61: lt003_entityesg_sbsctr | B61: 7 | C61: 45583 | D61: 45611
A62: lt003_entityflg_act_physcl_rsk | B62: 4 | C62: 45589 | E62: 45596
A63: lt003_entityflg_chrnc_physcl_rsk | B63: 4 | C63: 45589 | E63: 45596
A64: lt003_entityflg_excldd_eu_prs_algnd_bnchmrk | B64: 4 | D64: 45614 | E64: 45596
A65: lt003_entityflg_grp_nfrd_applcblty | B65: 4 | C65: 45589 | E65: 45596
A66: lt003_entityflg_nfrd_applcblty | B66: 7 | C66: 45589 | D66: 45611
A67: lt003_entitygrp_annl_trnvr_le | B67: 7 | C67: 45593 | D67: 45611
A68: lt003_entitygrp_emssns_scp1 | B68: 4 | C68: 45589 | E68: 45596
A69: lt003_entitygrp_emssns_scp2 | B69: 4 | C69: 45589 | E69: 45596
A70: lt003_entitygrp_emssns_scp3 | B70: 4 | C70: 45589 | E70: 45596
A71: lt003_entitygrp_eqty | B71: 1
A72: lt003_entitygrp_ttl_dbt | B72: 1
A73: lt003_entitygrp_ttl_lblty | B73: 7 | C73: 45593 | D73: 45611
A74: lt003_entityisin | B74: 7 | C74: 45589
A75: lt003_entitylei | B75: 1
A76: lt003_entitynace_esg | B76: 4 | C76: 45583 | E76: 45596
A77: lt003_entitypst_cd | B77: 1 | C77: 45589 | D77: 45596 | E77: 45596
A78: lt003_entitypure_capex_cca | B78: 7 | D78: 45611
A79: lt003_entitypure_capex_ccm | B79: 4 | D79: 45614 | E79: 45596
A80: lt003_entitypure_trnvr_cca | B80: 4 | D80: 45614 | E80: 45596
A81: lt003_entitypure_trnvr_ccm | B81: 4 | D81: 45614 | E81: 45596
A82: lt003_entitytrnstnl_capex | B82: 4 | D82: 45614 | E82: 45596
A83: lt003_entitytrnstnl_trnvr | B83: 4 | D83: 45614 | E83: 45596
A84: lt003_entityttl_dbt | B84: 1
A85: lt003_entityttl_lblty | B85: 7 | C85: 45593 | D85: 45624
A86: lt003_entitytxnmy_elgbl_capex_cca | B86: 4 | D86: 45614 | E86: 45596
A87: lt003_entitytxnmy_elgbl_capex_ccm | B87: 4 | C87: 45583 | D87: 45614 | E87: 45596
A88: lt003_entitytxnmy_elgbl_trnvr_cca | B88: 4 | D88: 45614 | E88: 45596
A89: lt003_entitytxnmy_elgbl_trnvr_ccm | B89: 4 | D89: 45614 | E89: 45596
A90: lt004_protectioncod_soc | B90: 1
A91: lt004_protectiondt_rfrnc | B91: 1
A92: lt004_protectionemssns_scp1_prtctn | B92: 7 | C92: 45583 | D92: 45596 | E92: 45596
A93: lt004_protectionemssns_scp2_prtctn | B93: 7 | C93: 45583 | D93: 45596 | E93: 45596
A94: lt004_protectionemssns_scp3_prtctn | B94: 7 | C94: 45583 | D94: 45596 | E94: 45596
A95: lt004_protectionep_scr | B95: 2 | C95: 45583 | D95: 45596 | E95: 45596
A96: lt004_protectionepc_lbl | B96: 2 | C96: 45583 | D96: 45596 | E96: 45596
A97: lt004_protectionflg_act_physcl_rsk | B97: 4 | C97: 45583 | D97: 45596 | E97: 45596
A98: lt004_protectionflg_chrnc_physcl_rsk | B98: 4 | C98: 45583 | D98: 45596 | E98: 45596
A99: lt004_protectionflg_col | B99: 7 | C99: 45593 | D99: 45624
A100: lt004_protectionflg_exec | B100: 7 | C100: 45593 | D100: 45624
A101: lt004_protectionflg_fin | B101: 7 | C101: 45593 | D101: 45624
A102: lt004_protectionflg_pro | B102: 7 | C102: 45593 | D102: 45624
A103: lt004_protectionmthd_usd_prtctn_scp_1 | B103: 7 | C103: 45583 | D103: 45596 | E103: 45596
A104: lt004_protectionmthd_usd_prtctn_scp_2 | B104: 7 | C104: 45583 | D104: 45596 | E104: 45596
A105: lt004_protectionmthd_usd_prtctn_scp_3 | B105: 7 | C105: 45583 | D105: 45596 | E105: 45596
A106: lt004_protectionorgnl_prtctn_vl | B106: 7 | C106: 45595 | D106: 45611
A107: lt004_protectionprtctn_id | B107: 7 | C107: 45589 | D107: 45611
...

Sheet Aux - Pivots2
B2: 1. Modelo Bens imóveis
B5: Âmbito | C5: Pilar III
B6: Sub-âmbito | C6: (Multiple Items)
B7: Tipo de teste | C7: 2. Campo
B9: Count of Campo | C9: Column Labels
B10: Row Labels | C10: 0. Cancelado | D10: 1. Concluído | E10: 4. Validação EF | F10: 6. Em implementação (re-especificação) | G10: Grand Total
B11: RESPONSIBILITY_PROCESS_REL | C11: 3 | D11: 17 | G11: 20
B12: PROPERTY_ENERGY_CERTIFICATE | D12: 50 | E12: 22 | G12: 72
B13: PROPERTY | C13: 2 | D13: 30 | F13: 1 | G13: 33
B14: PROCESS_PROPERTY_REL | C14: 1 | D14: 14 | G14: 15
B15: PROCESS | C15: 4 | D15: 13 | G15: 17
B16: ENERGY_CERTIFICATE_EST_INPUT | F16: 12 | G16: 12
B17: Grand Total | C17: 10 | D17: 124 | E17: 22 | F17: 13 | G17: 169
B23: Âmbito | C23: Pilar III
B24: Sub-âmbito | C24: (Multiple Items)
B25: Tipo de teste | C25: 2. Campo
B27: Row Labels | C27: Count of Campo
B28: 0. Cancelado | C28: 10
B29: 1. Concluído | C29: 124
B30: 4. Validação EF | C30: 22
B31: 6. Em implementação (re-especificação) | C31: 13
B32: Grand Total | C32: 169
B42: 2. Modelo Verde
B44: Âmbito | C44: Pilar III
B45: Sub-âmbito | C45: (Multiple Items)
B46: Tipo de teste | C46: 2. Campo
B48: Count of Campo | C48: Column Labels
B49: Row Labels | C49: 0. Cancelado | D49: 1. Concluído | E49: 2.1 Em Teste | F49: 6. Em implementação (re-especificação) | G49: Grand Total
B50: modesg_param_sfcs_taxon_europeia | C50: 2 | D50: 12 | E50: 16 | G50: 30
B51: modesg_out_sfcs_taxon_europeia | C51: 1 | D51: 1 | F51: 12 | G51: 14
B52: modesg_out_emss_vcls | D52: 8 | F52: 7 | G52: 15
B53: modesg_out_empr_info_nfin | D53: 2 | F53: 30 | G53: 32
B54: modesg_out_bens_imoveis | D54: 8 | E54: 6 | F54: 4 | G54: 18
B55: modesg_inp_risco_fisico | D55: 6 | G55: 6
B56: modesg_inp_nfrd_alinhamento_tax | D56: 41 | G56: 41
B57: modesg_inp_km_medios_emss_vcls | C57: 3 | D57: 6 | G57: 9
B58: modesg_inp_emss_vcls | D58: 17 | G58: 17
B59: modesg_inp_emss_scib | D59: 17 | G59: 17
B60: modesg_inp_emss_nace | C60: 7 | D60: 14 | G60: 21
B61: modesg_inp_emss_bens_imoveis | C61: 1 | D61: 17 | G61: 18
B62: modesg_inp_empr_excl_paris | D62: 7 | G62: 7
B63: Grand Total | C63: 14 | D63: 156 | E63: 22 | F63: 53 | G63: 245
B68: Âmbito | C68: Pilar III
B69: Sub-âmbito | C69: (Multiple Items)
B70: Tipo de teste | C70: 2. Campo
B72: Row Labels | C72: Count of Campo
B73: 0. Cancelado | C73: 14
B74: 1. Concluído | C74: 156
B75: 2.1 Em Teste | C75: 22
B76: 6. Em implementação (re-especificação) | C76: 53
B77: Grand Total | C77: 245
B87: 3. Loan Tape | Pilar III
B90: Âmbito | C90: Pilar III
B91: Sub-âmbito | C91: Pilar III
B92: Tipo de teste | C92: 2. Campo
B94: Count of Campo | C94: Column Labels
B95: Row Labels | C95: 1. Concluído | D95: 2.1 Em Teste | E95: 3. Pendente de outros desenvolvimentos | F95: 6. Em implementação (re-especificação) | G95: Grand Total
B96: lt002_instrument | C96: 21 | D96: 3 | F96: 6 | G96: 30
B97: lt003_entity | C97: 12 | E97: 24 | F97: 7 | G97: 43
B98: lt004_protection | C98: 2 | D98: 3 | E98: 2 | F98: 17 | G98: 24
B99: lt005_instr_ent | C99: 5 | G99: 5
B100: lt006_instr_prot | C100: 5 | G100: 5
B101: lt007_instr_activity | F101: 4 | G101: 4
B102: lt826_esg_sbsctr | C102: 9 | G102: 9
B103: lt827_mthd_usd_instrmnt | F103: 15 | G103: 15
B104: Grand Total | C104: 54 | D104: 6 | E104: 26 | F104: 49 | G104: 135
B111: Âmbito | C111: Pilar III
B112: Sub-âmbito | C112: Pilar III
B113: Tipo de teste | C113: 2. Campo
B115: Row Labels | C115: Count of Campo
B116: 1. Concluído | C116: 54
B117: 6. Em implementação (re-especificação) | C117: 49
B118: 3. Pendente de outros desenvolvimentos | C118: 26
B119: 2.1 Em Teste | C119: 6
B120: Grand Total | C120: 135

Sheet Caderno Testes
N7: (alterar quando necessário) | R7: (data default - Dez2023)
B8: Âmbito | C8: Sub-âmbito | D8: Origem | E8: Campo Origem | F8: Tabela | G8: Campo | H8: concat | I8: Status | J8: Status2 | K8: Tipologia_Testes | L8: Necessidade de re-especificação? (campo) | M8: Complexidade | N8: Data de Alteração Status | O8: Estimação (horas) | P8: Notas | Q8: Owner | R8: Data alteração especificação | S8: Data de inicio testes | T8: Data de incidência / pedido esclarecimento | U8: Data de correção/resposta prevista | V8: Data de correção/resposta efetiva | W8: Horas efetivas | X8: Query
