Workbook

Sheet Plano_V1
B6: Re-testes - input | D6: 0.2 | M6: =M7-M10 -> 0 | N6: =N7-N10 -> 0 | O6: =O7-O10 -> 0 | P6: =P7-P10 -> 0 | Q6: =Q7-Q10 -> 0 | R6: =R7-R10 -> 0 | S6: =S7-S10 -> 0 | T6: =T7-T10 -> 0 | ... FK6: =FK7-FK10 -> 0
B7: Re-testes - output | D7: =50%*25% -> 0.125 | L7: =AVERAGE(M7:EL7) -> 2.4923077 | M7: 3 | N7: 3 | O7: 3 | P7: 3 | Q7: 3 | R7: 2 | S7: 2 | T7: 2 | U7: 2 | V7: 2 | W7: 2 | X7: 2 | Y7: 2 | Z7: 2 | AA7: 2 | AB7: 2 | AC7: 2 | AD7: 1 | AE7: 1 | AF7: 1 | AG7: 3 | AH7: 3 | AI7: 3 | AJ7: 3 | AK7: 2 | AL7: 3 | AM7: 3 | AN7: 3 | AO7: 3 | AP7: 3 | AQ7: 2 | AR7: 2 | AS7: 2 | AT7: 0 | AU7: 1 | AV7: 1 | AW7: 0 | AX7: 1 | AY7: 1 | AZ7: 1 | BA7: 2 | BB7: 2 | BC7: 2 | BD7: 2 | BE7: 2 | BF7: 2 | BG7: 2 | BH7: 2 | BI7: 2 | BJ7: 2 | BK7: 2 | BL7: 2 | BM7: 2 | BN7: 2 | BO7: 2 | BP7: 3 | BQ7: 3 | BR7: 3 | BS7: 3 | BT7: 3 | BU7: 3 | BV7: 3 | BW7: 3 | BX7: 3 | BY7: 3 | BZ7: 3 | CA7: 3 | CB7: 3 | CC7: 3 | CD7: 3 | CE7: 3 | CF7: 3 | CG7: 3 | CH7: 3 | CI7: 3 | CJ7: 3 | CK7: 3 | CL7: 3 | CM7: 3 | CN7: 3 | CO7: 3 | CP7: 3 | CQ7: 3 | CR7: 3 | CS7: 3 | CT7: 3 | CU7: 3 | CV7: 3 | CW7: 3 | CX7: 3 | CY7: 3 | CZ7: 3 | DA7: 3 | DB7: 3 | DC7: 3 | DD7: 3 | DE7: 3 | DF7: 3 | DG7: 3 | DH7: 3 | DI7: 3 | DJ7: 3 | DK7: 3 | DL7: 3 | DM7: 3 | DN7: 2 | DO7: 3 | DP7: 3 | DQ7: 3 | DR7: 3 | DS7: 3 | DT7: 3 | DU7: 3 | DV7: 3 | DW7: 3 | DX7: 3 | DY7: 3 | DZ7: 3 | EA7: 3 | EB7: 3 | EC7: 3 | ED7: 3 | EE7: 3 | EF7: 3 | EG7: 3 | EH7: 3 | EI7: 0 | EJ7: 0 | EK7: 0 | EL7: 0 | EM7: 0 | EN7: 0 | EO7: 0 | EP7: 3 | EQ7: 3 | ER7: 3 | ES7: 3 | ET7: 3 | EU7: 3 | EV7: 3 | EW7: 3 | EX7: 3 | EY7: 3 | EZ7: 3 | FA7: 3 | FB7: 3 | FC7: 3 | FD7: 3 | FE7: 3 | FF7: 3 | FG7: 3 | FH7: 3 | FI7: 3 | FJ7: 3 | FK7: 3
M10: =SUBTOTAL(9,M14:M636) -> 3 | N10: =SUBTOTAL(9,N14:N636) -> 3 | O10: =SUBTOTAL(9,O14:O636) -> 3 | P10: =SUBTOTAL(9,P14:P636) -> 3 | Q10: =SUBTOTAL(9,Q14:Q636) -> 3 | R10: =SUBTOTAL(9,R14:R636) -> 2 | S10: =SUBTOTAL(9,S14:S636) -> 2 | T10: =SUBTOTAL(9,T14:T636) -> 2 | ... FK10: =SUBTOTAL(9,FK14:FK636) -> 3
M11: Julho | W11: Julho | AJ11: Agosto | BF11: Setembro | CA11: Outubro | CX11: Novembro | DS11: Dezembro | EO11: Janeiro
M12: =M13 -> 45474 | N12: =N13 -> 45475 | O12: =O13 -> 45476 | P12: =P13 -> 45477 | Q12: =Q13 -> 45478 | R12: =R13 -> 45481 | S12: =S13 -> 45482 | T12: =T13 -> 45483 | ... FK12: =FK13 -> 45688
B13: Âmbito | C13: Sub-âmbito | D13: Tipo de teste | E13: Tabela | F13: Campo | G13: Status | H13: Status2 | I13: Horas | J13: Dias | K13: Pendências | L13: Val | M13: 45474 | N13: =WORKDAY(M13,1) -> 45475 | O13: =WORKDAY(N13,1) -> 45476 | P13: =WORKDAY(O13,1) -> 45477 | Q13: =WORKDAY(P13,1) -> 45478 | R13: =WORKDAY(Q13,1) -> 45481 | S13: =WORKDAY(R13,1) -> 45482 | T13: =WORKDAY(S13,1) -> 45483 | U13: =WORKDAY(T13,1) -> 45484 | ... FK13: =WORKDAY(FJ13,1) -> 45688
B14: 1. Assessment | I14: =SUM(I15:I18) -> 280 | J14: =SUM(J15:J18) -> 35
B15: Pilar III | C15: Bens Imóveis | G15: 7. Por iniciar | I15: =J15*8 -> 40 | J15: 5 | L15: =J15-SUM(M15:FK15) -> 0 | W15: 1 | X15: 1 | Y15: 1 | Z15: 1 | AA15: 1
B16: Pilar III | C16: Modelo Verde | G16: 7. Por iniciar | I16: =J16*8 -> 80 | J16: 10 | L16: =J16-SUM(M16:FK16) -> 0 | R16: 2 | S16: 2 | T16: 2 | U16: 2 | V16: 2
B17: Pilar III | C17: Pilar III | G17: 7. Por iniciar | I17: =J17*8 -> 40 | J17: 5 | L17: =J17-SUM(M17:FK17) -> 0 | AB17: 1 | AC17: 1 | AD17: 1 | AE17: 1 | AF17: 0.5 | AG17: 0.5
B18: GD | C18: GD | G18: 7. Por iniciar | I18: =J18*8 -> 120 | J18: 15 | L18: =J18-SUM(M18:FK18) -> 0 | M18: 3 | N18: 3 | O18: 3 | P18: 3 | Q18: 3
B20: 2. Re-especificação | I20: =SUM(I21:I23) -> 120 | J20: =SUM(J21:J23) -> 15
B21: Pilar III | C21: Bens Imóveis | G21: 7. Por iniciar | I21: =J21*8 -> 40 | J21: 5 | L21: =J21-SUM(M21:FK21) -> 0 | W21: 0.5 | AB21: 0.5 | AG21: 0.5 | AL21: 0.5 | AQ21: 0.5 | AV21: 0.5 | BA21: 0.5 | BF21: 0.5 | BK21: 0.5 | BP21: 0.5
B22: Pilar III | C22: Modelo Verde | G22: 7. Por iniciar | I22: =J22*8 -> 40 | J22: 5 | L22: =J22-SUM(M22:FK22) -> 0 | W22: 0.5 | AB22: 0.5 | AG22: 0.5 | AL22: 0.5 | AQ22: 0.5 | AV22: 0.5 | BA22: 0.5 | BF22: 0.5 | BK22: 0.5 | BP22: 0.5
B23: Pilar III | C23: Pilar III | G23: 7. Por iniciar | I23: =J23*8 -> 40 | J23: 5 | L23: =J23-SUM(M23:FK23) -> 0 | BF23: 0.5 | BK23: 0.5 | BP23: 0.5 | BU23: 0.5 | BZ23: 0.5 | CE23: 0.5 | CJ23: 0.5 | CO23: 0.5 | CT23: 0.5 | CY23: 0.5
B25: 3. Testes / Re-testes | I25: =I26+I27+I42+I198+I362+I447 -> 1192.8125 | J25: =J26+J27+J42+J198+J362+J447 -> 151
B26: Testes Regressivos | G26: 7. Por iniciar | I26: =4*22 -> 88 | J26: =I26/8 -> 11 | L26: =J26-SUM(M26:FK26) -> 0 | AA26: 0.5 | AF26: 0.5 | AK26: 0.5 | AP26: 0.5 | AU26: 0.5 | AZ26: 0.5 | BE26: 0.5 | BJ26: 0.5 | BO26: 0.5 | BT26: 0.5 | BY26: 0.5 | CD26: 0.5 | CI26: 0.5 | CN26: 0.5 | CS26: 0.5 | CX26: 0.5 | DC26: 0.5 | DH26: 0.5 | DM26: 0.5 | DR26: 0.5 | DW26: 0.5 | EB26: 0.5
B27: Pilar III | C27: Bens Imóveis - Input | I27: =SUM(I28:I41) -> 0 | J27: =ROUNDUP(I27/8,0) -> 0 | L27: =J27-SUM(M27:FK27) -> -3 | X27: 0.5 | Y27: 0.5 | AC27: 0.5 | AG27: 1 | AH27: 0.5
A28: =E28&F28 -> cd_imv_inp_certif_estimativan.a. | B28: Pilar III | C28: Bens Imóveis - Input | D28: 1. Universo | E28: cd_imv_inp_certif_estimativa | F28: n.a. | G28: =INDEX(Auxiliar!$B$16:$B$24,MATCH(Plano_V1!H28,Auxiliar!$C$16:$C$24,0),1) -> #N/A | H28: =VLOOKUP(A28,'Aux - pivots1'!$A:$B,2,0) -> #N/A | I28: =SUMIFS(Table1[Estimação (horas)],Table1[Tabela],Plano_V1!E28,Table1[Campo],Plano_V1!F28) -> 0 | J28: =I28/8 -> 0 | K28: sem pendencia | L28: =J28-SUM(M28:FK28) -> 0
A29: =E29&F29 -> cd_imv_inp_certif_estimativacempbem | B29: Pilar III | C29: Bens Imóveis - Input | D29: 2. Campo | E29: cd_imv_inp_certif_estimativa | F29: cempbem | G29: =INDEX(Auxiliar!$B$16:$B$24,MATCH(Plano_V1!H29,Auxiliar!$C$16:$C$24,0),1) -> #N/A | H29: =VLOOKUP(A29,'Aux - pivots1'!$A:$B,2,0) -> #N/A | I29: =SUMIFS(Table1[Estimação (horas)],Table1[Tabela],Plano_V1!E29,Table1[Campo],Plano_V1!F29) -> 0 | J29: =I29/8 -> 0 | K29: sem pendencia | L29: =J29-SUM(M29:FK29) -> 0
A30: =E30&F30 -> cd_imv_inp_certif_estimativachave_encriptada | B30: Pilar III | C30: Bens Imóveis - Input | D30: 2. Campo | E30: cd_imv_inp_certif_estimativa | F30: chave_encriptada | G30: =INDEX(Auxiliar!$B$16:$B$24,MATCH(Plano_V1!H30,Auxiliar!$C$16:$C$24,0),1) -> #N/A | H30: =VLOOKUP(A30,'Aux - pivots1'!$A:$B,2,0) -> #N/A | I30: =SUMIFS(Table1[Estimação (horas)],Table1[Tabela],Plano_V1!E30,Table1[Campo],Plano_V1!F30) -> 0 | J30: =I30/8 -> 0 | K30: sem pendencia | L30: =J30-SUM(M30:FK30) -> 0
A31: =E31&F31 -> cd_imv_inp_certif_estimativackbalbem | B31: Pilar III | C31: Bens Imóveis - Input | D31: 2. Campo | E31: cd_imv_inp_certif_estimativa | F31: ckbalbem | G31: =INDEX(Auxiliar!$B$16:$B$24,MATCH(Plano_V1!H31,Auxiliar!$C$16:$C$24,0),1) -> #N/A | H31: =VLOOKUP(A31,'Aux - pivots1'!$A:$B,2,0) -> #N/A | I31: =SUMIFS(Table1[Estimação (horas)],Table1[Tabela],Plano_V1!E31,Table1[Campo],Plano_V1!F31) -> 0 | J31: =I31/8 -> 0 | K31: sem pendencia | L31: =J31-SUM(M31:FK31) -> 0
A32: =E32&F32 -> cd_imv_inp_certif_estimativackctabem | B32: Pilar III | C32: Bens Imóveis - Input | D32: 2. Campo | E32: cd_imv_inp_certif_estimativa | F32: ckctabem | G32: =INDEX(Auxiliar!$B$16:$B$24,MATCH(Plano_V1!H32,Auxiliar!$C$16:$C$24,0),1) -> #N/A | H32: =VLOOKUP(A32,'Aux - pivots1'!$A:$B,2,0) -> #N/A | I32: =SUMIFS(Table1[Estimação (horas)],Table1[Tabela],Plano_V1!E32,Table1[Campo],Plano_V1!F32) -> 0 | J32: =I32/8 -> 0 | K32: sem pendencia | L32: =J32-SUM(M32:FK32) -> 0
A33: =E33&F33 -> cd_imv_inp_certif_estimativackrefbem | B33: Pilar III | C33: Bens Imóveis - Input | D33: 2. Campo | E33: cd_imv_inp_certif_estimativa | F33: ckrefbem | G33: =INDEX(Auxiliar!$B$16:$B$24,MATCH(Plano_V1!H33,Auxiliar!$C$16:$C$24,0),1) -> #N/A | H33: =VLOOKUP(A33,'Aux - pivots1'!$A:$B,2,0) -> #N/A | I33: =SUMIFS(Table1[Estimação (horas)],Table1[Tabela],Plano_V1!E33,Table1[Campo],Plano_V1!F33) -> 0 | J33: =I33/8 -> 0 | K33: sem pendencia | L33: =J33-SUM(M33:FK33) -> 0
A34: =E34&F34 -> cd_imv_inp_certif_estimativadata_extraccao_info | B34: Pilar III | C34: Bens Imóveis - Input | D34: 2. Campo | E34: cd_imv_inp_certif_estimativa | F34: data_extraccao_info | G34: =INDEX(Auxiliar!$B$16:$B$24,MATCH(Plano_V1!H34,Auxiliar!$C$16:$C$24,0),1) -> #N/A | H34: =VLOOKUP(A34,'Aux - pivots1'!$A:$B,2,0) -> #N/A | I34: =SUMIFS(Table1[Estimação (horas)],Table1[Tabela],Plano_V1!E34,Table1[Campo],Plano_V1!F34) -> 0 | J34: =I34/8 -> 0 | K34: sem pendencia | L34: =J34-SUM(M34:FK34) -> 0
A35: =E35&F35 -> cd_imv_inp_certif_estimativaepc | B35: Pilar III | C35: Bens Imóveis - Input | D35: 2. Campo | E35: cd_imv_inp_certif_estimativa | F35: epc | G35: =INDEX(Auxiliar!$B$16:$B$24,MATCH(Plano_V1!H35,Auxiliar!$C$16:$C$24,0),1) -> #N/A | H35: =VLOOKUP(A35,'Aux - pivots1'!$A:$B,2,0) -> #N/A | I35: =SUMIFS(Table1[Estimação (horas)],Table1[Tabela],Plano_V1!E35,Table1[Campo],Plano_V1!F35) -> 0 | J35: =I35/8 -> 0 | K35: sem pendencia | L35: =J35-SUM(M35:FK35) -> 0
A36: =E36&F36 -> cd_imv_inp_certif_estimativafornecedor | B36: Pilar III | C36: Bens Imóveis - Input | D36: 2. Campo | E36: cd_imv_inp_certif_estimativa | F36: fornecedor | G36: =INDEX(Auxiliar!$B$16:$B$24,MATCH(Plano_V1!H36,Auxiliar!$C$16:$C$24,0),1) -> #N/A | H36: =VLOOKUP(A36,'Aux - pivots1'!$A:$B,2,0) -> #N/A | I36: =SUMIFS(Table1[Estimação (horas)],Table1[Tabela],Plano_V1!E36,Table1[Campo],Plano_V1!F36) -> 0 | J36: =I36/8 -> 0 | K36: sem pendencia | L36: =J36-SUM(M36:FK36) -> 0
A37: =E37&F37 -> cd_imv_inp_certif_estimativametodo_info | B37: Pilar III | C37: Bens Imóveis - Input | D37: 2. Campo | E37: cd_imv_inp_certif_estimativa | F37: metodo_info | G37: =INDEX(Auxiliar!$B$16:$B$24,MATCH(Plano_V1!H37,Auxiliar!$C$16:$C$24,0),1) -> #N/A | H37: =VLOOKUP(A37,'Aux - pivots1'!$A:$B,2,0) -> #N/A | I37: =SUMIFS(Table1[Estimação (horas)],Table1[Tabela],Plano_V1!E37,Table1[Campo],Plano_V1!F37) -> 0 | J37: =I37/8 -> 0 | K37: sem pendencia | L37: =J37-SUM(M37:FK37) -> 0
A38: =E38&F38 -> cd_imv_inp_certif_estimativascore_qualidade | B38: Pilar III | C38: Bens Imóveis - Input | D38: 2. Campo | E38: cd_imv_inp_certif_estimativa | F38: score_qualidade | G38: =INDEX(Auxiliar!$B$16:$B$24,MATCH(Plano_V1!H38,Auxiliar!$C$16:$C$24,0),1) -> #N/A | H38: =VLOOKUP(A38,'Aux - pivots1'!$A:$B,2,0) -> #N/A | I38: =SUMIFS(Table1[Estimação (horas)],Table1[Tabela],Plano_V1!E38,Table1[Campo],Plano_V1!F38) -> 0 | J38: =I38/8 -> 0 | K38: sem pendencia | L38: =J38-SUM(M38:FK38) -> 0
A39: =E39&F39 -> cd_imv_inp_certif_estimativavlr_cnsm_ano | B39: Pilar III | C39: Bens Imóveis - Input | D39: 2. Campo | E39: cd_imv_inp_certif_estimativa | F39: vlr_cnsm_ano | G39: =INDEX(Auxiliar!$B$16:$B$24,MATCH(Plano_V1!H39,Auxiliar!$C$16:$C$24,0),1) -> #N/A | H39: =VLOOKUP(A39,'Aux - pivots1'!$A:$B,2,0) -> #N/A | I39: =SUMIFS(Table1[Estimação (horas)],Table1[Tabela],Plano_V1!E39,Table1[Campo],Plano_V1!F39) -> 0 | J39: =I39/8 -> 0 | K39: sem pendencia | L39: =J39-SUM(M39:FK39) -> 0
A40: =E40&F40 -> cd_imv_inp_certif_estimativavlr_emss_ano | B40: Pilar III | C40: Bens Imóveis - Input | D40: 2. Campo | E40: cd_imv_inp_certif_estimativa | F40: vlr_emss_ano | G40: =INDEX(Auxiliar!$B$16:$B$24,MATCH(Plano_V1!H40,Auxiliar!$C$16:$C$24,0),1) -> #N/A | H40: =VLOOKUP(A40,'Aux - pivots1'!$A:$B,2,0) -> #N/A | I40: =SUMIFS(Table1[Estimação (horas)],Table1[Tabela],Plano_V1!E40,Table1[Campo],Plano_V1!F40) -> 0 | J40: =I40/8 -> 0 | K40: sem pendencia | L40: =J40-SUM(M40:FK40) -> 0
A41: =E41&F41 -> Re-testesn.a. | B41: Pilar III | C41: Bens Imóveis - Input | D41: 2. Campo | E41: Re-testes | F41: n.a. | G41: 7. Por iniciar | I41: =SUM(I28:I40)*D6 -> 0 | J41: =I41/8 -> 0 | K41: sem pendencia | L41: =J41-SUM(M41:FK41) -> 0
A42: =E42&F42 | B42: Pilar III | C42: Bens Imóveis - Output | I42: =SUM(I43:I197) -> 0 | J42: =ROUNDUP(I42/8,0) -> 0 | L42: =J42-SUM(M42:FK42) -> -100 | AH42: 0.5 | AI42: 1 | AJ42: 1 | AM42: 1 | AN42: 1 | AO42: 1 | AP42: 0.5 | AR42: 1 | AS42: 2 | AU42: 0.5 | AX42: 1 | AY42: 1 | AZ42: 0.5 | BA42: 1 | BB42: 2 | BC42: 2 | BD42: 2 | BE42: 1.5 | BF42: 0.5 | BG42: 2 | BH42: 2 | BI42: 2 | BJ42: 1.5 | BK42: 0.5 | BL42: 2 | BM42: 2 | BN42: 2 | BO42: 1.5 | BP42: 1.5 | BQ42: 2 | BR42: 2 | BS42: 2 | BT42: 2 | BU42: 2 | BV42: 2 | BW42: 2 | BX42: 2 | BY42: 2 | BZ42: 2 | CA42: 2 | CB42: 2 | CC42: 2 | CD42: 2 | CE42: 2 | CF42: 2 | CG42: 2 | CH42: 2 | CI42: 2 | CJ42: 2 | CK42: 2 | CL42: 2 | CM42: 2 | CN42: 2 | CO42: 2 | CP42: 2 | CQ42: 2 | CR42: 2 | CS42: 2 | CT42: 2 | CU42: 2
A43: =E43&F43 -> cd_imv_out_prcn.a. | B43: Pilar III | C43: Bens Imóveis - Output | D43: 1. Universo | E43: cd_imv_out_prc | F43: n.a. | G43: =INDEX(Auxiliar!$B$16:$B$24,MATCH(Plano_V1!H43,Auxiliar!$C$16:$C$24,0),1) -> #N/A | H43: =VLOOKUP(A43,'Aux - pivots1'!$A:$B,2,0) -> #N/A | I43: =SUMIFS(Table1[Estimação (horas)],Table1[Tabela],Plano_V1!E43,Table1[Campo],Plano_V1!F43) -> 0 | J43: =I43/8 -> 0 | K43: cd_imv_out_trz_cred_prc | L43: =J43-SUM(M43:FK43) -> 0
A44: =E44&F44 -> cd_imv_out_prccempresa | B44: Pilar III | C44: Bens Imóveis - Output | D44: 2. Campo | E44: cd_imv_out_prc | F44: cempresa | G44: =INDEX(Auxiliar!$B$16:$B$24,MATCH(Plano_V1!H44,Auxiliar!$C$16:$C$24,0),1) -> #N/A | H44: =VLOOKUP(A44,'Aux - pivots1'!$A:$B,2,0) -> #N/A | I44: =SUMIFS(Table1[Estimação (horas)],Table1[Tabela],Plano_V1!E44,Table1[Campo],Plano_V1!F44) -> 0 | J44: =I44/8 -> 0 | K44: cd_imv_out_trz_cred_prc | L44: =J44-SUM(M44:FK44) -> 0
A45: =E45&F45 -> cd_imv_out_prcckbalcao | B45: Pilar III | C45: Bens Imóveis - Output | D45: 2. Campo | E45: cd_imv_out_prc | F45: ckbalcao | G45: =INDEX(Auxiliar!$B$16:$B$24,MATCH(Plano_V1!H45,Auxiliar!$C$16:$C$24,0),1) -> #N/A | H45: =VLOOKUP(A45,'Aux - pivots1'!$A:$B,2,0) -> #N/A | I45: =SUMIFS(Table1[Estimação (horas)],Table1[Tabela],Plano_V1!E45,Table1[Campo],Plano_V1!F45) -> 0 | J45: =I45/8 -> 0 | K45: cd_imv_out_trz_cred_prc | L45: =J45-SUM(M45:FK45) -> 0
A46: =E46&F46 -> cd_imv_out_prccknumcta | B46: Pilar III | C46: Bens Imóveis - Output | D46: 2. Campo | E46: cd_imv_out_prc | F46: cknumcta | G46: =INDEX(Auxiliar!$B$16:$B$24,MATCH(Plano_V1!H46,Auxiliar!$C$16:$C$24,0),1) -> #N/A | H46: =VLOOKUP(A46,'Aux - pivots1'!$A:$B,2,0) -> #N/A | I46: =SUMIFS(Table1[Estimação (horas)],Table1[Tabela],Plano_V1!E46,Table1[Campo],Plano_V1!F46) -> 0 | J46: =I46/8 -> 0 | K46: cd_imv_out_trz_cred_prc | L46: =J46-SUM(M46:FK46) -> 0
A47: =E47&F47 -> cd_imv_out_prccod_estd_prcs | B47: Pilar III | C47: Bens Imóveis - Output | D47: 2. Campo | E47: cd_imv_out_prc | F47: cod_estd_prcs | G47: =INDEX(Auxiliar!$B$16:$B$24,MATCH(Plano_V1!H47,Auxiliar!$C$16:$C$24,0),1) -> #N/A | H47: =VLOOKUP(A47,'Aux - pivots1'!$A:$B,2,0) -> #N/A | I47: 0 | J47: =I47/8 -> 0 | K47: cd_imv_out_trz_cred_prc | L47: =J47-SUM(M47:FK47) -> 0
A48: =E48&F48 -> cd_imv_out_prccod_grt | B48: Pilar III | C48: Bens Imóveis - Output | D48: 2. Campo | E48: cd_imv_out_prc | F48: cod_grt | G48: =INDEX(Auxiliar!$B$16:$B$24,MATCH(Plano_V1!H48,Auxiliar!$C$16:$C$24,0),1) -> #N/A | H48: =VLOOKUP(A48,'Aux - pivots1'!$A:$B,2,0) -> #N/A | I48: =SUMIFS(Table1[Estimação (horas)],Table1[Tabela],Plano_V1!E48,Table1[Campo],Plano_V1!F48) -> 0 | J48: =I48/8 -> 0 | K48: cd_imv_out_trz_cred_prc | L48: =J48-SUM(M48:FK48) -> 0
A49: =E49&F49 -> cd_imv_out_prccod_moeda | B49: Pilar III | C49: Bens Imóveis - Output | D49: 2. Campo | E49: cd_imv_out_prc | F49: cod_moeda | G49: =INDEX(Auxiliar!$B$16:$B$24,MATCH(Plano_V1!H49,Auxiliar!$C$16:$C$24,0),1) -> #N/A | H49: =VLOOKUP(A49,'Aux - pivots1'!$A:$B,2,0) -> #N/A | I49: =SUMIFS(Table1[Estimação (horas)],Table1[Tabela],Plano_V1!E49,Table1[Campo],Plano_V1!F49) -> 0 | J49: =I49/8 -> 0 | K49: cd_imv_out_trz_cred_prc | L49: =J49-SUM(M49:FK49) -> 0
A50: =E50&F50 -> cd_imv_out_prccod_observacao | B50: Pilar III | C50: Bens Imóveis - Output | D50: 2. Campo | E50: cd_imv_out_prc | F50: cod_observacao | G50: =INDEX(Auxiliar!$B$16:$B$24,MATCH(Plano_V1!H50,Auxiliar!$C$16:$C$24,0),1) -> #N/A | H50: =VLOOKUP(A50,'Aux - pivots1'!$A:$B,2,0) -> #N/A | I50: =SUMIFS(Table1[Estimação (horas)],Table1[Tabela],Plano_V1!E50,Table1[Campo],Plano_V1!F50) -> 0 | J50: =I50/8 -> 0 | K50: cd_imv_out_trz_cred_prc | L50: =J50-SUM(M50:FK50) -> 0
A51: =E51&F51 -> cd_imv_out_prccod_prd_grnt | B51: Pilar III | C51: Bens Imóveis - Output | D51: 2. Campo | E51: cd_imv_out_prc | F51: cod_prd_grnt | G51: =INDEX(Auxiliar!$B$16:$B$24,MATCH(Plano_V1!H51,Auxiliar!$C$16:$C$24,0),1) -> #N/A | H51: =VLOOKUP(A51,'Aux - pivots1'!$A:$B,2,0) -> #N/A | I51: =SUMIFS(Table1[Estimação (horas)],Table1[Tabela],Plano_V1!E51,Table1[Campo],Plano_V1!F51) -> 0 | J51: =I51/8 -> 0 | K51: cd_imv_out_trz_cred_prc | L51: =J51-SUM(M51:FK51) -> 0
A52: =E52&F52 -> cd_imv_out_prccod_sprd_grnt | B52: Pilar III | C52: Bens Imóveis - Output | D52: 2. Campo | E52: cd_imv_out_prc | F52: cod_sprd_grnt | G52: =INDEX(Auxiliar!$B$16:$B$24,MATCH(Plano_V1!H52,Auxiliar!$C$16:$C$24,0),1) -> #N/A | H52: =VLOOKUP(A52,'Aux - pivots1'!$A:$B,2,0) -> #N/A | I52: =SUMIFS(Table1[Estimação (horas)],Table1[Tabela],Plano_V1!E52,Table1[Campo],Plano_V1!F52) -> 0 | J52: =I52/8 -> 0 | K52: cd_imv_out_trz_cred_prc | L52: =J52-SUM(M52:FK52) -> 0
A53: =E53&F53 -> cd_imv_out_prccod_tipo | B53: Pilar III | C53: Bens Imóveis - Output | D53: 2. Campo | E53: cd_imv_out_prc | F53: cod_tipo | G53: =INDEX(Auxiliar!$B$16:$B$24,MATCH(Plano_V1!H53,Auxiliar!$C$16:$C$24,0),1) -> #N/A | H53: =VLOOKUP(A53,'Aux - pivots1'!$A:$B,2,0) -> #N/A | I53: =SUMIFS(Table1[Estimação (horas)],Table1[Tabela],Plano_V1!E53,Table1[Campo],Plano_V1!F53) -> 0 | J53: =I53/8 -> 0 | K53: cd_imv_out_trz_cred_prc | L53: =J53-SUM(M53:FK53) -> 0
A54: =E54&F54 -> cd_imv_out_prccomp_id_gar | B54: Pilar III | C54: Bens Imóveis - Output | D54: 2. Campo | E54: cd_imv_out_prc | F54: comp_id_gar | G54: =INDEX(Auxiliar!$B$16:$B$24,MATCH(Plano_V1!H54,Auxiliar!$C$16:$C$24,0),1) -> #N/A | H54: =VLOOKUP(A54,'Aux - pivots1'!$A:$B,2,0) -> #N/A | I54: =SUMIFS(Table1[Estimação (horas)],Table1[Tabela],Plano_V1!E54,Table1[Campo],Plano_V1!F54) -> 0 | J54: =I54/8 -> 0 | K54: cd_imv_out_trz_cred_prc | L54: =J54-SUM(M54:FK54) -> 0
A55: =E55&F55 -> cd_imv_out_prcdata_inicio | B55: Pilar III | C55: Bens Imóveis - Output | D55: 2. Campo | E55: cd_imv_out_prc | F55: data_inicio | G55: =INDEX(Auxiliar!$B$16:$B$24,MATCH(Plano_V1!H55,Auxiliar!$C$16:$C$24,0),1) -> #N/A | H55: =VLOOKUP(A55,'Aux - pivots1'!$A:$B,2,0) -> #N/A | I55: =SUMIFS(Table1[Estimação (horas)],Table1[Tabela],Plano_V1!E55,Table1[Campo],Plano_V1!F55) -> 0 | J55: =I55/8 -> 0 | K55: cd_imv_out_trz_cred_prc | L55: =J55-SUM(M55:FK55) -> 0
A56: =E56&F56 -> cd_imv_out_prcdata_vcmt | B56: Pilar III | C56: Bens Imóveis - Output | D56: 2. Campo | E56: cd_imv_out_prc | F56: data_vcmt | G56: =INDEX(Auxiliar!$B$16:$B$24,MATCH(Plano_V1!H56,Auxiliar!$C$16:$C$24,0),1) -> #N/A | H56: =VLOOKUP(A56,'Aux - pivots1'!$A:$B,2,0) -> #N/A | I56: =SUMIFS(Table1[Estimação (horas)],Table1[Tabela],Plano_V1!E56,Table1[Campo],Plano_V1!F56) -> 0 | J56: =I56/8 -> 0 | K56: cd_imv_out_trz_cred_prc | L56: =J56-SUM(M56:FK56) -> 0
A57: =E57&F57 -> cd_imv_out_prcmontante_eur | B57: Pilar III | C57: Bens Imóveis - Output | D57: 2. Campo | E57: cd_imv_out_prc | F57: montante_eur | G57: =INDEX(Auxiliar!$B$16:$B$24,MATCH(Plano_V1!H57,Auxiliar!$C$16:$C$24,0),1) -> #N/A | H57: =VLOOKUP(A57,'Aux - pivots1'!$A:$B,2,0) -> #N/A | I57: 0 | J57: =I57/8 -> 0 | K57: cd_imv_out_trz_cred_prc | L57: =J57-SUM(M57:FK57) -> 0
A58: =E58&F58 -> cd_imv_out_prcmontante_org | B58: Pilar III | C58: Bens Imóveis - Output | D58: 2. Campo | E58: cd_imv_out_prc | F58: montante_org | G58: =INDEX(Auxiliar!$B$16:$B$24,MATCH(Plano_V1!H58,Auxiliar!$C$16:$C$24,0),1) -> #N/A | H58: =VLOOKUP(A58,'Aux - pivots1'!$A:$B,2,0) -> #N/A | I58: 0 | J58: =I58/8 -> 0 | K58: cd_imv_out_trz_cred_prc | L58: =J58-SUM(M58:FK58) -> 0
A59: =E59&F59 -> cd_imv_out_prcorigem | B59: Pilar III | C59: Bens Imóveis - Output | D59: 2. Campo | E59: cd_imv_out_prc | F59: origem | G59: =INDEX(Auxiliar!$B$16:$B$24,MATCH(Plano_V1!H59,Auxiliar!$C$16:$C$24,0),1) -> #N/A | H59: =VLOOKUP(A59,'Aux - pivots1'!$A:$B,2,0) -> #N/A | I59: =SUMIFS(Table1[Estimação (horas)],Table1[Tabela],Plano_V1!E59,Table1[Campo],Plano_V1!F59) -> 0 | J59: =I59/8 -> 0 | K59: cd_imv_out_trz_cred_prc | L59: =J59-SUM(M59:FK59) -> 0
A60: =E60&F60 -> cd_imv_out_prcref_date | B60: Pilar III | C60: Bens Imóveis - Output | D60: 2. Campo | E60: cd_imv_out_prc | F60: ref_date | G60: =INDEX(Auxiliar!$B$16:$B$24,MATCH(Plano_V1!H60,Auxiliar!$C$16:$C$24,0),1) -> #N/A | H60: =VLOOKUP(A60,'Aux - pivots1'!$A:$B,2,0) -> #N/A | I60: =SUMIFS(Table1[Estimação (horas)],Table1[Tabela],Plano_V1!E60,Table1[Campo],Plano_V1!F60) -> 0 | J60: =I60/8 -> 0 | K60: cd_imv_out_trz_cred_prc | L60: =J60-SUM(M60:FK60) -> 0
A61: =E61&F61 -> cd_imv_out_trz_cred_prcn.a. | B61: Pilar III | C61: Bens Imóveis - Output | D61: 1. Universo | E61: cd_imv_out_trz_cred_prc | F61: n.a. | G61: =INDEX(Auxiliar!$B$16:$B$24,MATCH(Plano_V1!H61,Auxiliar!$C$16:$C$24,0),1) -> #N/A | H61: =VLOOKUP(A61,'Aux - pivots1'!$A:$B,2,0) -> #N/A | I61: =SUMIFS(Table1[Estimação (horas)],Table1[Tabela],Plano_V1!E61,Table1[Campo],Plano_V1!F61) -> 0 | J61: =I61/8 -> 0 | K61: sem pendencia | L61: =J61-SUM(M61:FK61) -> 0
A62: =E62&F62 -> cd_imv_out_trz_cred_prccempresa | B62: Pilar III | C62: Bens Imóveis - Output | D62: 2. Campo | E62: cd_imv_out_trz_cred_prc | F62: cempresa | G62: =INDEX(Auxiliar!$B$16:$B$24,MATCH(Plano_V1!H62,Auxiliar!$C$16:$C$24,0),1) -> #N/A | H62: =VLOOKUP(A62,'Aux - pivots1'!$A:$B,2,0) -> #N/A | I62: =SUMIFS(Table1[Estimação (horas)],Table1[Tabela],Plano_V1!E62,Table1[Campo],Plano_V1!F62) -> 0 | J62: =I62/8 -> 0 | K62: sem pendencia | L62: =J62-SUM(M62:FK62) -> 0
A63: =E63&F63 -> cd_imv_out_trz_cred_prccempresp | B63: Pilar III | C63: Bens Imóveis - Output | D63: 2. Campo | E63: cd_imv_out_trz_cred_prc | F63: cempresp | G63: =INDEX(Auxiliar!$B$16:$B$24,MATCH(Plano_V1!H63,Auxiliar!$C$16:$C$24,0),1) -> #N/A | H63: =VLOOKUP(A63,'Aux - pivots1'!$A:$B,2,0) -> #N/A | I63: =SUMIFS(Table1[Estimação (horas)],Table1[Tabela],Plano_V1!E63,Table1[Campo],Plano_V1!F63) -> 0 | J63: =I63/8 -> 0 | K63: sem pendencia | L63: =J63-SUM(M63:FK63) -> 0
A64: =E64&F64 -> cd_imv_out_trz_cred_prcckbalcao | B64: Pilar III | C64: Bens Imóveis - Output | D64: 2. Campo | E64: cd_imv_out_trz_cred_prc | F64: ckbalcao | G64: =INDEX(Auxiliar!$B$16:$B$24,MATCH(Plano_V1!H64,Auxiliar!$C$16:$C$24,0),1) -> #N/A | H64: =VLOOKUP(A64,'Aux - pivots1'!$A:$B,2,0) -> #N/A | I64: =SUMIFS(Table1[Estimação (horas)],Table1[Tabela],Plano_V1!E64,Table1[Campo],Plano_V1!F64) -> 0 | J64: =I64/8 -> 0 | K64: sem pendencia | L64: =J64-SUM(M64:FK64) -> 0
A65: =E65&F65 -> cd_imv_out_trz_cred_prcckbalres | B65: Pilar III | C65: Bens Imóveis - Output | D65: 2. Campo | E65: cd_imv_out_trz_cred_prc | F65: ckbalres | G65: =INDEX(Auxiliar!$B$16:$B$24,MATCH(Plano_V1!H65,Auxiliar!$C$16:$C$24,0),1) -> #N/A | H65: =VLOOKUP(A65,'Aux - pivots1'!$A:$B,2,0) -> #N/A | I65: =SUMIFS(Table1[Estimação (horas)],Table1[Tabela],Plano_V1!E65,Table1[Campo],Plano_V1!F65) -> 0 | J65: =I65/8 -> 0 | K65: sem pendencia | L65: =J65-SUM(M65:FK65) -> 0
A66: =E66&F66 -> cd_imv_out_trz_cred_prcckctares | B66: Pilar III | C66: Bens Imóveis - Output | D66: 2. Campo | E66: cd_imv_out_trz_cred_prc | F66: ckctares | G66: =INDEX(Auxiliar!$B$16:$B$24,MATCH(Plano_V1!H66,Auxiliar!$C$16:$C$24,0),1) -> #N/A | H66: =VLOOKUP(A66,'Aux - pivots1'!$A:$B,2,0) -> #N/A | I66: =SUMIFS(Table1[Estimação (horas)],Table1[Tabela],Plano_V1!E66,Table1[Campo],Plano_V1!F66) -> 0 | J66: =I66/8 -> 0 | K66: sem pendencia | L66: =J66-SUM(M66:FK66) -> 0
A67: =E67&F67 -> cd_imv_out_trz_cred_prccknumcta | B67: Pilar III | C67: Bens Imóveis - Output | D67: 2. Campo | E67: cd_imv_out_trz_cred_prc | F67: cknumcta | G67: =INDEX(Auxiliar!$B$16:$B$24,MATCH(Plano_V1!H67,Auxiliar!$C$16:$C$24,0),1) -> #N/A | H67: =VLOOKUP(A67,'Aux - pivots1'!$A:$B,2,0) -> #N/A | I67: =SUMIFS(Table1[Estimação (horas)],Table1[Tabela],Plano_V1!E67,Table1[Campo],Plano_V1!F67) -> 0 | J67: =I67/8 -> 0 | K67: sem pendencia | L67: =J67-SUM(M67:FK67) -> 0
A68: =E68&F68 -> cd_imv_out_trz_cred_prcckrefresp | B68: Pilar III | C68: Bens Imóveis - Output | D68: 2. Campo | E68: cd_imv_out_trz_cred_prc | F68: ckrefresp | G68: =INDEX(Auxiliar!$B$16:$B$24,MATCH(Plano_V1!H68,Auxiliar!$C$16:$C$24,0),1) -> #N/A | H68: =VLOOKUP(A68,'Aux - pivots1'!$A:$B,2,0) -> #N/A | I68: =SUMIFS(Table1[Estimação (horas)],Table1[Tabela],Plano_V1!E68,Table1[Campo],Plano_V1!F68) -> 0 | J68: =I68/8 -> 0 | K68: sem pendencia | L68: =J68-SUM(M68:FK68) -> 0
A69: =E69&F69 -> cd_imv_out_trz_cred_prccod_fnld | B69: Pilar III | C69: Bens Imóveis - Output | D69: 2. Campo | E69: cd_imv_out_trz_cred_prc | F69: cod_fnld | G69: =INDEX(Auxiliar!$B$16:$B$24,MATCH(Plano_V1!H69,Auxiliar!$C$16:$C$24,0),1) -> #N/A | H69: =VLOOKUP(A69,'Aux - pivots1'!$A:$B,2,0) -> #N/A | I69: =SUMIFS(Table1[Estimação (horas)],Table1[Tabela],Plano_V1!E69,Table1[Campo],Plano_V1!F69) -> 0 | J69: =I69/8 -> 0 | K69: sem pendencia | L69: =J69-SUM(M69:FK69) -> 0
A70: =E70&F70 -> cd_imv_out_trz_cred_prccod_ocupacao | B70: Pilar III | C70: Bens Imóveis - Output | D70: 2. Campo | E70: cd_imv_out_trz_cred_prc | F70: cod_ocupacao | G70: =INDEX(Auxiliar!$B$16:$B$24,MATCH(Plano_V1!H70,Auxiliar!$C$16:$C$24,0),1) -> #N/A | H70: =VLOOKUP(A70,'Aux - pivots1'!$A:$B,2,0) -> #N/A | I70: =SUMIFS(Table1[Estimação (horas)],Table1[Tabela],Plano_V1!E70,Table1[Campo],Plano_V1!F70) -> 0 | J70: =I70/8 -> 0 | K70: sem pendencia | L70: =J70-SUM(M70:FK70) -> 0
A71: =E71&F71 -> cd_imv_out_trz_cred_prccod_prd_resp | B71: Pilar III | C71: Bens Imóveis - Output | D71: 2. Campo | E71: cd_imv_out_trz_cred_prc | F71: cod_prd_resp | G71: =INDEX(Auxiliar!$B$16:$B$24,MATCH(Plano_V1!H71,Auxiliar!$C$16:$C$24,0),1) -> #N/A | H71: =VLOOKUP(A71,'Aux - pivots1'!$A:$B,2,0) -> #N/A | I71: =SUMIFS(Table1[Estimação (horas)],Table1[Tabela],Plano_V1!E71,Table1[Campo],Plano_V1!F71) -> 0 | J71: =I71/8 -> 0 | K71: sem pendencia | L71: =J71-SUM(M71:FK71) -> 0
A72: =E72&F72 -> cd_imv_out_trz_cred_prccod_sit | B72: Pilar III | C72: Bens Imóveis - Output | D72: 2. Campo | E72: cd_imv_out_trz_cred_prc | F72: cod_sit | G72: =INDEX(Auxiliar!$B$16:$B$24,MATCH(Plano_V1!H72,Auxiliar!$C$16:$C$24,0),1) -> #N/A | H72: =VLOOKUP(A72,'Aux - pivots1'!$A:$B,2,0) -> #N/A | I72: 0 | J72: =I72/8 -> 0 | K72: sem pendencia | L72: =J72-SUM(M72:FK72) -> 0
A73: =E73&F73 -> cd_imv_out_trz_cred_prccod_sprd_resp | B73: Pilar III | C73: Bens Imóveis - Output | D73: 2. Campo | E73: cd_imv_out_trz_cred_prc | F73: cod_sprd_resp | G73: =INDEX(Auxiliar!$B$16:$B$24,MATCH(Plano_V1!H73,Auxiliar!$C$16:$C$24,0),1) -> #N/A | H73: =VLOOKUP(A73,'Aux - pivots1'!$A:$B,2,0) -> #N/A | I73: =SUMIFS(Table1[Estimação (horas)],Table1[Tabela],Plano_V1!E73,Table1[Campo],Plano_V1!F73) -> 0 | J73: =I73/8 -> 0 | K73: sem pendencia | L73: =J73-SUM(M73:FK73) -> 0
A74: =E74&F74 -> cd_imv_out_trz_cred_prccomp_id_gar | B74: Pilar III | C74: Bens Imóveis - Output | D74: 2. Campo | E74: cd_imv_out_trz_cred_prc | F74: comp_id_gar | G74: =INDEX(Auxiliar!$B$16:$B$24,MATCH(Plano_V1!H74,Auxiliar!$C$16:$C$24,0),1) -> #N/A | H74: =VLOOKUP(A74,'Aux - pivots1'!$A:$B,2,0) -> #N/A | I74: =SUMIFS(Table1[Estimação (horas)],Table1[Tabela],Plano_V1!E74,Table1[Campo],Plano_V1!F74) -> 0 | J74: =I74/8 -> 0 | K74: sem pendencia | L74: =J74-SUM(M74:FK74) -> 0
A75: =E75&F75 -> cd_imv_out_trz_cred_prcdata_fim | B75: Pilar III | C75: Bens Imóveis - Output | D75: 2. Campo | E75: cd_imv_out_trz_cred_prc | F75: data_fim | G75: =INDEX(Auxiliar!$B$16:$B$24,MATCH(Plano_V1!H75,Auxiliar!$C$16:$C$24,0),1) -> #N/A | H75: =VLOOKUP(A75,'Aux - pivots1'!$A:$B,2,0) -> #N/A | I75: =SUMIFS(Table1[Estimação (horas)],Table1[Tabela],Plano_V1!E75,Table1[Campo],Plano_V1!F75) -> 0 | J75: =I75/8 -> 0 | K75: sem pendencia | L75: =J75-SUM(M75:FK75) -> 0
A76: =E76&F76 -> cd_imv_out_trz_cred_prcdata_inicio | B76: Pilar III | C76: Bens Imóveis - Output | D76: 2. Campo | E76: cd_imv_out_trz_cred_prc | F76: data_inicio | G76: =INDEX(Auxiliar!$B$16:$B$24,MATCH(Plano_V1!H76,Auxiliar!$C$16:$C$24,0),1) -> #N/A | H76: =VLOOKUP(A76,'Aux - pivots1'!$A:$B,2,0) -> #N/A | I76: =SUMIFS(Table1[Estimação (horas)],Table1[Tabela],Plano_V1!E76,Table1[Campo],Plano_V1!F76) -> 0 | J76: =I76/8 -> 0 | K76: sem pendencia | L76: =J76-SUM(M76:FK76) -> 0
A77: =E77&F77 -> cd_imv_out_trz_cred_prcdata_vcmt | B77: Pilar III | C77: Bens Imóveis - Output | D77: 2. Campo | E77: cd_imv_out_trz_cred_prc | F77: data_vcmt | G77: =INDEX(Auxiliar!$B$16:$B$24,MATCH(Plano_V1!H77,Auxiliar!$C$16:$C$24,0),1) -> #N/A | H77: =VLOOKUP(A77,'Aux - pivots1'!$A:$B,2,0) -> #N/A | I77: =SUMIFS(Table1[Estimação (horas)],Table1[Tabela],Plano_V1!E77,Table1[Campo],Plano_V1!F77) -> 0 | J77: =I77/8 -> 0 | K77: sem pendencia | L77: =J77-SUM(M77:FK77) -> 0
A78: =E78&F78 -> cd_imv_out_trz_cred_prcidetgar | B78: Pilar III | C78: Bens Imóveis - Output | D78: 2. Campo | E78: cd_imv_out_trz_cred_prc | F78: idetgar | G78: =INDEX(Auxiliar!$B$16:$B$24,MATCH(Plano_V1!H78,Auxiliar!$C$16:$C$24,0),1) -> #N/A | H78: =VLOOKUP(A78,'Aux - pivots1'!$A:$B,2,0) -> #N/A | I78: 0 | J78: =I78/8 -> 0 | K78: sem pendencia | L78: =J78-SUM(M78:FK78) -> 0
A79: =E79&F79 -> cd_imv_out_trz_cred_prcnum_prop | B79: Pilar III | C79: Bens Imóveis - Output | D79: 2. Campo | E79: cd_imv_out_trz_cred_prc | F79: num_prop | G79: =INDEX(Auxiliar!$B$16:$B$24,MATCH(Plano_V1!H79,Auxiliar!$C$16:$C$24,0),1) -> #N/A | H79: =VLOOKUP(A79,'Aux - pivots1'!$A:$B,2,0) -> #N/A | I79: 0 | J79: =I79/8 -> 0 | K79: sem pendencia | L79: =J79-SUM(M79:FK79) -> 0
A80: =E80&F80 -> cd_imv_out_trz_cred_prcorigem | B80: Pilar III | C80: Bens Imóveis - Output | D80: 2. Campo | E80: cd_imv_out_trz_cred_prc | F80: origem | G80: =INDEX(Auxiliar!$B$16:$B$24,MATCH(Plano_V1!H80,Auxiliar!$C$16:$C$24,0),1) -> #N/A | H80: =VLOOKUP(A80,'Aux - pivots1'!$A:$B,2,0) -> #N/A | I80: =SUMIFS(Table1[Estimação (horas)],Table1[Tabela],Plano_V1!E80,Table1[Campo],Plano_V1!F80) -> 0 | J80: =I80/8 -> 0 | K80: sem pendencia | L80: =J80-SUM(M80:FK80) -> 0
A81: =E81&F81 -> cd_imv_out_trz_cred_prcref_date | B81: Pilar III | C81: Bens Imóveis - Output | D81: 2. Campo | E81: cd_imv_out_trz_cred_prc | F81: ref_date | G81: =INDEX(Auxiliar!$B$16:$B$24,MATCH(Plano_V1!H81,Auxiliar!$C$16:$C$24,0),1) -> #N/A | H81: =VLOOKUP(A81,'Aux - pivots1'!$A:$B,2,0) -> #N/A | I81: =SUMIFS(Table1[Estimação (horas)],Table1[Tabela],Plano_V1!E81,Table1[Campo],Plano_V1!F81) -> 0 | J81: =I81/8 -> 0 | K81: sem pendencia | L81: =J81-SUM(M81:FK81) -> 0
A82: =E82&F82 -> cd_imv_out_trz_prc_bens_imvn.a. | B82: Pilar III | C82: Bens Imóveis - Output | D82: 1. Universo | E82: cd_imv_out_trz_prc_bens_imv | F82: n.a. | G82: =INDEX(Auxiliar!$B$16:$B$24,MATCH(Plano_V1!H82,Auxiliar!$C$16:$C$24,0),1) -> #N/A | H82: =VLOOKUP(A82,'Aux - pivots1'!$A:$B,2,0) -> #N/A | I82: =SUMIFS(Table1[Estimação (horas)],Table1[Tabela],Plano_V1!E82,Table1[Campo],Plano_V1!F82) -> 0 | J82: =I82/8 -> 0 | K82: cd_imv_out_trz_cred_prc | L82: =J82-SUM(M82:FK82) -> 0
A83: =E83&F83 -> cd_imv_out_trz_prc_bens_imvcempbem | B83: Pilar III | C83: Bens Imóveis - Output | D83: 2. Campo | E83: cd_imv_out_trz_prc_bens_imv | F83: cempbem | G83: =INDEX(Auxiliar!$B$16:$B$24,MATCH(Plano_V1!H83,Auxiliar!$C$16:$C$24,0),1) -> #N/A | H83: =VLOOKUP(A83,'Aux - pivots1'!$A:$B,2,0) -> #N/A | I83: =SUMIFS(Table1[Estimação (horas)],Table1[Tabela],Plano_V1!E83,Table1[Campo],Plano_V1!F83) -> 0 | J83: =I83/8 -> 0 | K83: cd_imv_out_trz_cred_prc | L83: =J83-SUM(M83:FK83) -> 0
A84: =E84&F84 -> cd_imv_out_trz_prc_bens_imvcempresa | B84: Pilar III | C84: Bens Imóveis - Output | D84: 2. Campo | E84: cd_imv_out_trz_prc_bens_imv | F84: cempresa | G84: =INDEX(Auxiliar!$B$16:$B$24,MATCH(Plano_V1!H84,Auxiliar!$C$16:$C$24,0),1) -> #N/A | H84: =VLOOKUP(A84,'Aux - pivots1'!$A:$B,2,0) -> #N/A | I84: =SUMIFS(Table1[Estimação (horas)],Table1[Tabela],Plano_V1!E84,Table1[Campo],Plano_V1!F84) -> 0 | J84: =I84/8 -> 0 | K84: cd_imv_out_trz_cred_prc | L84: =J84-SUM(M84:FK84) -> 0
A85: =E85&F85 -> cd_imv_out_trz_prc_bens_imvckbalbem | B85: Pilar III | C85: Bens Imóveis - Output | D85: 2. Campo | E85: cd_imv_out_trz_prc_bens_imv | F85: ckbalbem | G85: =INDEX(Auxiliar!$B$16:$B$24,MATCH(Plano_V1!H85,Auxiliar!$C$16:$C$24,0),1) -> #N/A | H85: =VLOOKUP(A85,'Aux - pivots1'!$A:$B,2,0) -> #N/A | I85: =SUMIFS(Table1[Estimação (horas)],Table1[Tabela],Plano_V1!E85,Table1[Campo],Plano_V1!F85) -> 0 | J85: =I85/8 -> 0 | K85: cd_imv_out_trz_cred_prc | L85: =J85-SUM(M85:FK85) -> 0
A86: =E86&F86 -> cd_imv_out_trz_prc_bens_imvckbalcao | B86: Pilar III | C86: Bens Imóveis - Output | D86: 2. Campo | E86: cd_imv_out_trz_prc_bens_imv | F86: ckbalcao | G86: =INDEX(Auxiliar!$B$16:$B$24,MATCH(Plano_V1!H86,Auxiliar!$C$16:$C$24,0),1) -> #N/A | H86: =VLOOKUP(A86,'Aux - pivots1'!$A:$B,2,0) -> #N/A | I86: =SUMIFS(Table1[Estimação (horas)],Table1[Tabela],Plano_V1!E86,Table1[Campo],Plano_V1!F86) -> 0 | J86: =I86/8 -> 0 | K86: cd_imv_out_trz_cred_prc | L86: =J86-SUM(M86:FK86) -> 0
A87: =E87&F87 -> cd_imv_out_trz_prc_bens_imvckctabem | B87: Pilar III | C87: Bens Imóveis - Output | D87: 2. Campo | E87: cd_imv_out_trz_prc_bens_imv | F87: ckctabem | G87: =INDEX(Auxiliar!$B$16:$B$24,MATCH(Plano_V1!H87,Auxiliar!$C$16:$C$24,0),1) -> #N/A | H87: =VLOOKUP(A87,'Aux - pivots1'!$A:$B,2,0) -> #N/A | I87: =SUMIFS(Table1[Estimação (horas)],Table1[Tabela],Plano_V1!E87,Table1[Campo],Plano_V1!F87) -> 0 | J87: =I87/8 -> 0 | K87: cd_imv_out_trz_cred_prc | L87: =J87-SUM(M87:FK87) -> 0
A88: =E88&F88 -> cd_imv_out_trz_prc_bens_imvcknumcta | B88: Pilar III | C88: Bens Imóveis - Output | D88: 2. Campo | E88: cd_imv_out_trz_prc_bens_imv | F88: cknumcta | G88: =INDEX(Auxiliar!$B$16:$B$24,MATCH(Plano_V1!H88,Auxiliar!$C$16:$C$24,0),1) -> #N/A | H88: =VLOOKUP(A88,'Aux - pivots1'!$A:$B,2,0) -> #N/A | I88: =SUMIFS(Table1[Estimação (horas)],Table1[Tabela],Plano_V1!E88,Table1[Campo],Plano_V1!F88) -> 0 | J88: =I88/8 -> 0 | K88: cd_imv_out_trz_cred_prc | L88: =J88-SUM(M88:FK88) -> 0
A89: =E89&F89 -> cd_imv_out_trz_prc_bens_imvckrefbem | B89: Pilar III | C89: Bens Imóveis - Output | D89: 2. Campo | E89: cd_imv_out_trz_prc_bens_imv | F89: ckrefbem | G89: =INDEX(Auxiliar!$B$16:$B$24,MATCH(Plano_V1!H89,Auxiliar!$C$16:$C$24,0),1) -> #N/A | H89: =VLOOKUP(A89,'Aux - pivots1'!$A:$B,2,0) -> #N/A | I89: =SUMIFS(Table1[Estimação (horas)],Table1[Tabela],Plano_V1!E89,Table1[Campo],Plano_V1!F89) -> 0 | J89: =I89/8 -> 0 | K89: cd_imv_out_trz_cred_prc | L89: =J89-SUM(M89:FK89) -> 0
A90: =E90&F90 -> cd_imv_out_trz_prc_bens_imvcomp_id_gar | B90: Pilar III | C90: Bens Imóveis - Output | D90: 2. Campo | E90: cd_imv_out_trz_prc_bens_imv | F90: comp_id_gar | G90: =INDEX(Auxiliar!$B$16:$B$24,MATCH(Plano_V1!H90,Auxiliar!$C$16:$C$24,0),1) -> #N/A | H90: =VLOOKUP(A90,'Aux - pivots1'!$A:$B,2,0) -> #N/A | I90: =SUMIFS(Table1[Estimação (horas)],Table1[Tabela],Plano_V1!E90,Table1[Campo],Plano_V1!F90) -> 0 | J90: =I90/8 -> 0 | K90: cd_imv_out_trz_cred_prc | L90: =J90-SUM(M90:FK90) -> 0
A91: =E91&F91 -> cd_imv_out_trz_prc_bens_imvdata_assc | B91: Pilar III | C91: Bens Imóveis - Output | D91: 2. Campo | E91: cd_imv_out_trz_prc_bens_imv | F91: data_assc | G91: =INDEX(Auxiliar!$B$16:$B$24,MATCH(Plano_V1!H91,Auxiliar!$C$16:$C$24,0),1) -> #N/A | H91: =VLOOKUP(A91,'Aux - pivots1'!$A:$B,2,0) -> #N/A | I91: 0 | J91: =I91/8 -> 0 | K91: cd_imv_out_trz_cred_prc | L91: =J91-SUM(M91:FK91) -> 0
A92: =E92&F92 -> cd_imv_out_trz_prc_bens_imvflg_adj | B92: Pilar III | C92: Bens Imóveis - Output | D92: 2. Campo | E92: cd_imv_out_trz_prc_bens_imv | F92: flg_adj | G92: =INDEX(Auxiliar!$B$16:$B$24,MATCH(Plano_V1!H92,Auxiliar!$C$16:$C$24,0),1) -> #N/A | H92: =VLOOKUP(A92,'Aux - pivots1'!$A:$B,2,0) -> #N/A | I92: =SUMIFS(Table1[Estimação (horas)],Table1[Tabela],Plano_V1!E92,Table1[Campo],Plano_V1!F92) -> 0 | J92: =I92/8 -> 0 | K92: cd_imv_out_trz_cred_prc | L92: =J92-SUM(M92:FK92) -> 0
A93: =E93&F93 -> cd_imv_out_trz_prc_bens_imvflg_col | B93: Pilar III | C93: Bens Imóveis - Output | D93: 2. Campo | E93: cd_imv_out_trz_prc_bens_imv | F93: flg_col | G93: =INDEX(Auxiliar!$B$16:$B$24,MATCH(Plano_V1!H93,Auxiliar!$C$16:$C$24,0),1) -> #N/A | H93: =VLOOKUP(A93,'Aux - pivots1'!$A:$B,2,0) -> #N/A | I93: =SUMIFS(Table1[Estimação (horas)],Table1[Tabela],Plano_V1!E93,Table1[Campo],Plano_V1!F93) -> 0 | J93: =I93/8 -> 0 | K93: cd_imv_out_trz_cred_prc | L93: =J93-SUM(M93:FK93) -> 0
A94: =E94&F94 -> cd_imv_out_trz_prc_bens_imvflg_fin | B94: Pilar III | C94: Bens Imóveis - Output | D94: 2. Campo | E94: cd_imv_out_trz_prc_bens_imv | F94: flg_fin | G94: =INDEX(Auxiliar!$B$16:$B$24,MATCH(Plano_V1!H94,Auxiliar!$C$16:$C$24,0),1) -> #N/A | H94: =VLOOKUP(A94,'Aux - pivots1'!$A:$B,2,0) -> #N/A | I94: =SUMIFS(Table1[Estimação (horas)],Table1[Tabela],Plano_V1!E94,Table1[Campo],Plano_V1!F94) -> 0 | J94: =I94/8 -> 0 | K94: cd_imv_out_trz_cred_prc | L94: =J94-SUM(M94:FK94) -> 0
A95: =E95&F95 -> cd_imv_out_trz_prc_bens_imvflg_pro | B95: Pilar III | C95: Bens Imóveis - Output | D95: 2. Campo | E95: cd_imv_out_trz_prc_bens_imv | F95: flg_pro | G95: =INDEX(Auxiliar!$B$16:$B$24,MATCH(Plano_V1!H95,Auxiliar!$C$16:$C$24,0),1) -> #N/A | H95: =VLOOKUP(A95,'Aux - pivots1'!$A:$B,2,0) -> #N/A | I95: =SUMIFS(Table1[Estimação (horas)],Table1[Tabela],Plano_V1!E95,Table1[Campo],Plano_V1!F95) -> 0 | J95: =I95/8 -> 0 | K95: cd_imv_out_trz_cred_prc | L95: =J95-SUM(M95:FK95) -> 0
A96: =E96&F96 -> cd_imv_out_trz_prc_bens_imvorigem | B96: Pilar III | C96: Bens Imóveis - Output | D96: 2. Campo | E96: cd_imv_out_trz_prc_bens_imv | F96: origem | G96: =INDEX(Auxiliar!$B$16:$B$24,MATCH(Plano_V1!H96,Auxiliar!$C$16:$C$24,0),1) -> #N/A | H96: =VLOOKUP(A96,'Aux - pivots1'!$A:$B,2,0) -> #N/A | I96: =SUMIFS(Table1[Estimação (horas)],Table1[Tabela],Plano_V1!E96,Table1[Campo],Plano_V1!F96) -> 0 | J96: =I96/8 -> 0 | K96: cd_imv_out_trz_cred_prc | L96: =J96-SUM(M96:FK96) -> 0
A97: =E97&F97 -> cd_imv_out_trz_prc_bens_imvref_date | B97: Pilar III | C97: Bens Imóveis - Output | D97: 2. Campo | E97: cd_imv_out_trz_prc_bens_imv | F97: ref_date | G97: =INDEX(Auxiliar!$B$16:$B$24,MATCH(Plano_V1!H97,Auxiliar!$C$16:$C$24,0),1) -> #N/A | H97: =VLOOKUP(A97,'Aux - pivots1'!$A:$B,2,0) -> #N/A | I97: =SUMIFS(Table1[Estimação (horas)],Table1[Tabela],Plano_V1!E97,Table1[Campo],Plano_V1!F97) -> 0 | J97: =I97/8 -> 0 | K97: cd_imv_out_trz_cred_prc | L97: =J97-SUM(M97:FK97) -> 0
A98: =E98&F98 -> cd_imv_out_bensn.a. | B98: Pilar III | C98: Bens Imóveis - Output | D98: 1. Universo | E98: cd_imv_out_bens | F98: n.a. | G98: =INDEX(Auxiliar!$B$16:$B$24,MATCH(Plano_V1!H98,Auxiliar!$C$16:$C$24,0),1) -> #N/A | H98: =VLOOKUP(A98,'Aux - pivots1'!$A:$B,2,0) -> #N/A | I98: =SUMIFS(Table1[Estimação (horas)],Table1[Tabela],Plano_V1!E98,Table1[Campo],Plano_V1!F98) -> 0 | J98: =I98/8 -> 0 | K98: cd_imv_out_trz_prc_bens_imv ; cd_imv_out_prc ; cd_imv_out_trz_cred_prc | L98: =J98-SUM(M98:FK98) -> 0
A99: =E99&F99 -> cd_imv_out_bensano_construcao | B99: Pilar III | C99: Bens Imóveis - Output | D99: 2. Campo | E99: cd_imv_out_bens | F99: ano_construcao | G99: =INDEX(Auxiliar!$B$16:$B$24,MATCH(Plano_V1!H99,Auxiliar!$C$16:$C$24,0),1) -> #N/A | H99: =VLOOKUP(A99,'Aux - pivots1'!$A:$B,2,0) -> #N/A | I99: 0 | J99: =I99/8 -> 0 | K99: cd_imv_out_trz_prc_bens_imv ; cd_imv_out_prc ; cd_imv_out_trz_cred_prc | L99: =J99-SUM(M99:FK99) -> 0
A100: =E100&F100 -> cd_imv_out_bensarea_util | B100: Pilar III | C100: Bens Imóveis - Output | D100: 2. Campo | E100: cd_imv_out_bens | F100: area_util | G100: =INDEX(Auxiliar!$B$16:$B$24,MATCH(Plano_V1!H100,Auxiliar!$C$16:$C$24,0),1) -> #N/A | H100: =VLOOKUP(A100,'Aux - pivots1'!$A:$B,2,0) -> #N/A | I100: =SUMIFS(Table1[Estimação (horas)],Table1[Tabela],Plano_V1!E100,Table1[Campo],Plano_V1!F100) -> 0 | J100: =I100/8 -> 0 | K100: cd_imv_out_trz_prc_bens_imv ; cd_imv_out_prc ; cd_imv_out_trz_cred_prc | L100: =J100-SUM(M100:FK100) -> 0
A101: =E101&F101 -> cd_imv_out_benscempbem | B101: Pilar III | C101: Bens Imóveis - Output | D101: 2. Campo | E101: cd_imv_out_bens | F101: cempbem | G101: =INDEX(Auxiliar!$B$16:$B$24,MATCH(Plano_V1!H101,Auxiliar!$C$16:$C$24,0),1) -> #N/A | H101: =VLOOKUP(A101,'Aux - pivots1'!$A:$B,2,0) -> #N/A | I101: =SUMIFS(Table1[Estimação (horas)],Table1[Tabela],Plano_V1!E101,Table1[Campo],Plano_V1!F101) -> 0 | J101: =I101/8 -> 0 | K101: cd_imv_out_trz_prc_bens_imv ; cd_imv_out_prc ; cd_imv_out_trz_cred_prc | L101: =J101-SUM(M101:FK101) -> 0
A102: =E102&F102 -> cd_imv_out_bensckbalbem | B102: Pilar III | C102: Bens Imóveis - Output | D102: 2. Campo | E102: cd_imv_out_bens | F102: ckbalbem | G102: =INDEX(Auxiliar!$B$16:$B$24,MATCH(Plano_V1!H102,Auxiliar!$C$16:$C$24,0),1) -> #N/A | H102: =VLOOKUP(A102,'Aux - pivots1'!$A:$B,2,0) -> #N/A | I102: =SUMIFS(Table1[Estimação (horas)],Table1[Tabela],Plano_V1!E102,Table1[Campo],Plano_V1!F102) -> 0 | J102: =I102/8 -> 0 | K102: cd_imv_out_trz_prc_bens_imv ; cd_imv_out_prc ; cd_imv_out_trz_cred_prc | L102: =J102-SUM(M102:FK102) -> 0
A103: =E103&F103 -> cd_imv_out_bensckctabem | B103: Pilar III | C103: Bens Imóveis - Output | D103: 2. Campo | E103: cd_imv_out_bens | F103: ckctabem | G103: =INDEX(Auxiliar!$B$16:$B$24,MATCH(Plano_V1!H103,Auxiliar!$C$16:$C$24,0),1) -> #N/A | H103: =VLOOKUP(A103,'Aux - pivots1'!$A:$B,2,0) -> #N/A | I103: =SUMIFS(Table1[Estimação (horas)],Table1[Tabela],Plano_V1!E103,Table1[Campo],Plano_V1!F103) -> 0 | J103: =I103/8 -> 0 | K103: cd_imv_out_trz_prc_bens_imv ; cd_imv_out_prc ; cd_imv_out_trz_cred_prc | L103: =J103-SUM(M103:FK103) -> 0
A104: =E104&F104 -> cd_imv_out_bensckrefbem | B104: Pilar III | C104: Bens Imóveis - Output | D104: 2. Campo | E104: cd_imv_out_bens | F104: ckrefbem | G104: =INDEX(Auxiliar!$B$16:$B$24,MATCH(Plano_V1!H104,Auxiliar!$C$16:$C$24,0),1) -> #N/A | H104: =VLOOKUP(A104,'Aux - pivots1'!$A:$B,2,0) -> #N/A | I104: =SUMIFS(Table1[Estimação (horas)],Table1[Tabela],Plano_V1!E104,Table1[Campo],Plano_V1!F104) -> 0 | J104: =I104/8 -> 0 | K104: cd_imv_out_trz_prc_bens_imv ; cd_imv_out_prc ; cd_imv_out_trz_cred_prc | L104: =J104-SUM(M104:FK104) -> 0
A105: =E105&F105 -> cd_imv_out_benscod_art_matr | B105: Pilar III | C105: Bens Imóveis - Output | D105: 2. Campo | E105: cd_imv_out_bens | F105: cod_art_matr | G105: =INDEX(Auxiliar!$B$16:$B$24,MATCH(Plano_V1!H105,Auxiliar!$C$16:$C$24,0),1) -> #N/A | H105: =VLOOKUP(A105,'Aux - pivots1'!$A:$B,2,0) -> #N/A | I105: =SUMIFS(Table1[Estimação (horas)],Table1[Tabela],Plano_V1!E105,Table1[Campo],Plano_V1!F105) -> 0 | J105: =I105/8 -> 0 | K105: cd_imv_out_trz_prc_bens_imv ; cd_imv_out_prc ; cd_imv_out_trz_cred_prc | L105: =J105-SUM(M105:FK105) -> 0
A106: =E106&F106 -> cd_imv_out_benscod_avl | B106: Pilar III | C106: Bens Imóveis - Output | D106: 2. Campo | E106: cd_imv_out_bens | F106: cod_avl | G106: =INDEX(Auxiliar!$B$16:$B$24,MATCH(Plano_V1!H106,Auxiliar!$C$16:$C$24,0),1) -> #N/A | H106: =VLOOKUP(A106,'Aux - pivots1'!$A:$B,2,0) -> #N/A | I106: =SUMIFS(Table1[Estimação (horas)],Table1[Tabela],Plano_V1!E106,Table1[Campo],Plano_V1!F106) -> 0 | J106: =I106/8 -> 0 | K106: cd_imv_out_trz_prc_bens_imv ; cd_imv_out_prc ; cd_imv_out_trz_cred_prc | L106: =J106-SUM(M106:FK106) -> 0
A107: =E107&F107 -> cd_imv_out_benscod_bem | B107: Pilar III | C107: Bens Imóveis - Output | D107: 2. Campo | E107: cd_imv_out_bens | F107: cod_bem | G107: =INDEX(Auxiliar!$B$16:$B$24,MATCH(Plano_V1!H107,Auxiliar!$C$16:$C$24,0),1) -> #N/A | H107: =VLOOKUP(A107,'Aux - pivots1'!$A:$B,2,0) -> #N/A | I107: 0 | J107: =I107/8 -> 0 | K107: cd_imv_out_trz_prc_bens_imv ; cd_imv_out_prc ; cd_imv_out_trz_cred_prc | L107: =J107-SUM(M107:FK107) -> 0
A108: =E108&F108 -> cd_imv_out_benscod_disconf | B108: Pilar III | C108: Bens Imóveis - Output | D108: 2. Campo | E108: cd_imv_out_bens | F108: cod_disconf | G108: =INDEX(Auxiliar!$B$16:$B$24,MATCH(Plano_V1!H108,Auxiliar!$C$16:$C$24,0),1) -> #N/A | H108: =VLOOKUP(A108,'Aux - pivots1'!$A:$B,2,0) -> #N/A | I108: =SUMIFS(Table1[Estimação (horas)],Table1[Tabela],Plano_V1!E108,Table1[Campo],Plano_V1!F108) -> 0 | J108: =I108/8 -> 0 | K108: cd_imv_out_trz_prc_bens_imv ; cd_imv_out_prc ; cd_imv_out_trz_cred_prc | L108: =J108-SUM(M108:FK108) -> 0
A109: =E109&F109 -> cd_imv_out_benscod_fin_bem | B109: Pilar III | C109: Bens Imóveis - Output | D109: 2. Campo | E109: cd_imv_out_bens | F109: cod_fin_bem | G109: =INDEX(Auxiliar!$B$16:$B$24,MATCH(Plano_V1!H109,Auxiliar!$C$16:$C$24,0),1) -> #N/A | H109: =VLOOKUP(A109,'Aux - pivots1'!$A:$B,2,0) -> #N/A | I109: =SUMIFS(Table1[Estimação (horas)],Table1[Tabela],Plano_V1!E109,Table1[Campo],Plano_V1!F109) -> 0 | J109: =I109/8 -> 0 | K109: cd_imv_out_trz_prc_bens_imv ; cd_imv_out_prc ; cd_imv_out_trz_cred_prc | L109: =J109-SUM(M109:FK109) -> 0
...

Sheet 1. Status Resumo FY24
B6: Sumário Executivo |10 de janeiro a 17 de janeiro
B8: - Concluídos 3 campos da tabela de Clientes do Modelo Verde; - Concluídos 8 campos do Pilar III
B13: 1. Visão Geral
C16: Resumo | H16: Detalhe por Tabela | P16: Status (campos) | T16: 45625 | U16: =T16+7 -> 45632 | V16: ∆ | X16: Highlights
P17: 0. Cancelado | T17: =COUNTIFS('2. Status Detalhe Campos FY24'!$H$7:$H$725,'1. Status Resumo FY24'!$P75,'2. Status Detalhe Campos FY24'!$C$7:$C$725,'1. Status Resumo FY24'!$G$71,'2. Status Detalhe Campos FY24'!$D$7:$D$725,"2. Campo")+COUNTIFS('2. Status Detalhe Campos FY24'!$H$7:$H$725,'1. Status Resumo FY24'!$P75,'2. Status Detalhe Campos FY24'!$C$7:$C$725,'1. Status Resumo FY24'!$H$71,'2. Status Detalhe Campos FY24'!$D$7:$D$725,"2. Campo")+COUNTIFS('2. Status Detalhe Campos FY24'!$H$7:$H$725,'1. Status Resumo FY24'!$P99,'2. Status Detalhe Campos FY24'!$C$7:$C$725,'1. Status Resumo FY24'!$G$95,'2. Status Detalhe Campos FY24'!$D$7:$D$725,"2. Campo")+COUNTIFS('2. Status Detalhe Campos FY24'!$H$7:$H$725,'1. Status Resumo FY24'!$P99,'2. Status Detalhe Campos FY24'!$C$7:$C$725,'1. Status Resumo FY24'!$H$95,'2. Status Detalhe Campos FY24'!$D$7:$D$725,"2. Campo")+COUNTIFS(Table4[Status Anterior],'1. Status Resumo FY24'!$P134,Table4[Sub-âmbito],'1. Status Resumo FY24'!$G$130,Table4[Tipo de teste],"2. Campo") -> 24 | U17: =COUNTIFS('2. Status Detalhe Campos FY24'!$G$7:$G$725,'1. Status Resumo FY24'!$P75,'2. Status Detalhe Campos FY24'!$C$7:$C$725,'1. Status Resumo FY24'!$G$71,'2. Status Detalhe Campos FY24'!$D$7:$D$725,"2. Campo")+COUNTIFS('2. Status Detalhe Campos FY24'!$G$7:$G$725,'1. Status Resumo FY24'!$P75,'2. Status Detalhe Campos FY24'!$C$7:$C$725,'1. Status Resumo FY24'!$H$71,'2. Status Detalhe Campos FY24'!$D$7:$D$725,"2. Campo")+COUNTIFS('2. Status Detalhe Campos FY24'!$G$7:$G$725,'1. Status Resumo FY24'!$P99,'2. Status Detalhe Campos FY24'!$C$7:$C$725,'1. Status Resumo FY24'!$G$95,'2. Status Detalhe Campos FY24'!$D$7:$D$725,"2. Campo")+COUNTIFS('2. Status Detalhe Campos FY24'!$G$7:$G$725,'1. Status Resumo FY24'!$P99,'2. Status Detalhe Campos FY24'!$C$7:$C$725,'1. Status Resumo FY24'!$H$95,'2. Status Detalhe Campos FY24'!$D$7:$D$725,"2. Campo")+COUNTIFS(Table4[Status Atual],'1. Status Resumo FY24'!$P134,Table4[Sub-âmbito],'1. Status Resumo FY24'!$G$130,Table4[Tipo de teste],"2. Campo") -> 26 | V17: =U17-T17 -> 2
P18: 1. Concluído | T18: =COUNTIFS('2. Status Detalhe Campos FY24'!$H$7:$H$725,'1. Status Resumo FY24'!$P76,'2. Status Detalhe Campos FY24'!$C$7:$C$725,'1. Status Resumo FY24'!$G$71,'2. Status Detalhe Campos FY24'!$D$7:$D$725,"2. Campo")+COUNTIFS('2. Status Detalhe Campos FY24'!$H$7:$H$725,'1. Status Resumo FY24'!$P76,'2. Status Detalhe Campos FY24'!$C$7:$C$725,'1. Status Resumo FY24'!$H$71,'2. Status Detalhe Campos FY24'!$D$7:$D$725,"2. Campo")+COUNTIFS('2. Status Detalhe Campos FY24'!$H$7:$H$725,'1. Status Resumo FY24'!$P100,'2. Status Detalhe Campos FY24'!$C$7:$C$725,'1. Status Resumo FY24'!$G$95,'2. Status Detalhe Campos FY24'!$D$7:$D$725,"2. Campo")+COUNTIFS('2. Status Detalhe Campos FY24'!$H$7:$H$725,'1. Status Resumo FY24'!$P100,'2. Status Detalhe Campos FY24'!$C$7:$C$725,'1. Status Resumo FY24'!$H$95,'2. Status Detalhe Campos FY24'!$D$7:$D$725,"2. Campo")+COUNTIFS(Table4[Status Anterior],'1. Status Resumo FY24'!$P135,Table4[Sub-âmbito],'1. Status Resumo FY24'!$G$130,Table4[Tipo de teste],"2. Campo") -> 471 | U18: =COUNTIFS('2. Status Detalhe Campos FY24'!$G$7:$G$725,'1. Status Resumo FY24'!$P76,'2. Status Detalhe Campos FY24'!$C$7:$C$725,'1. Status Resumo FY24'!$G$71,'2. Status Detalhe Campos FY24'!$D$7:$D$725,"2. Campo")+COUNTIFS('2. Status Detalhe Campos FY24'!$G$7:$G$725,'1. Status Resumo FY24'!$P76,'2. Status Detalhe Campos FY24'!$C$7:$C$725,'1. Status Resumo FY24'!$H$71,'2. Status Detalhe Campos FY24'!$D$7:$D$725,"2. Campo")+COUNTIFS('2. Status Detalhe Campos FY24'!$G$7:$G$725,'1. Status Resumo FY24'!$P100,'2. Status Detalhe Campos FY24'!$C$7:$C$725,'1. Status Resumo FY24'!$G$95,'2. Status Detalhe Campos FY24'!$D$7:$D$725,"2. Campo")+COUNTIFS('2. Status Detalhe Campos FY24'!$G$7:$G$725,'1. Status Resumo FY24'!$P100,'2. Status Detalhe Campos FY24'!$C$7:$C$725,'1. Status Resumo FY24'!$H$95,'2. Status Detalhe Campos FY24'!$D$7:$D$725,"2. Campo")+COUNTIFS(Table4[Status Atual],'1. Status Resumo FY24'!$P135,Table4[Sub-âmbito],'1. Status Resumo FY24'!$G$130,Table4[Tipo de teste],"2. Campo") -> 486 | V18: =U18-T18 -> 15
P19: 2.1 Em Teste | T19: =COUNTIFS('2. Status Detalhe Campos FY24'!$H$7:$H$725,'1. Status Resumo FY24'!$P77,'2. Status Detalhe Campos FY24'!$C$7:$C$725,'1. Status Resumo FY24'!$G$71,'2. Status Detalhe Campos FY24'!$D$7:$D$725,"2. Campo")+COUNTIFS('2. Status Detalhe Campos FY24'!$H$7:$H$725,'1. Status Resumo FY24'!$P77,'2. Status Detalhe Campos FY24'!$C$7:$C$725,'1. Status Resumo FY24'!$H$71,'2. Status Detalhe Campos FY24'!$D$7:$D$725,"2. Campo")+COUNTIFS('2. Status Detalhe Campos FY24'!$H$7:$H$725,'1. Status Resumo FY24'!$P101,'2. Status Detalhe Campos FY24'!$C$7:$C$725,'1. Status Resumo FY24'!$G$95,'2. Status Detalhe Campos FY24'!$D$7:$D$725,"2. Campo")+COUNTIFS('2. Status Detalhe Campos FY24'!$H$7:$H$725,'1. Status Resumo FY24'!$P101,'2. Status Detalhe Campos FY24'!$C$7:$C$725,'1. Status Resumo FY24'!$H$95,'2. Status Detalhe Campos FY24'!$D$7:$D$725,"2. Campo")+COUNTIFS(Table4[Status Anterior],'1. Status Resumo FY24'!$P136,Table4[Sub-âmbito],'1. Status Resumo FY24'!$G$130,Table4[Tipo de teste],"2. Campo") -> 6 | U19: =COUNTIFS('2. Status Detalhe Campos FY24'!$G$7:$G$725,'1. Status Resumo FY24'!$P77,'2. Status Detalhe Campos FY24'!$C$7:$C$725,'1. Status Resumo FY24'!$G$71,'2. Status Detalhe Campos FY24'!$D$7:$D$725,"2. Campo")+COUNTIFS('2. Status Detalhe Campos FY24'!$G$7:$G$725,'1. Status Resumo FY24'!$P77,'2. Status Detalhe Campos FY24'!$C$7:$C$725,'1. Status Resumo FY24'!$H$71,'2. Status Detalhe Campos FY24'!$D$7:$D$725,"2. Campo")+COUNTIFS('2. Status Detalhe Campos FY24'!$G$7:$G$725,'1. Status Resumo FY24'!$P101,'2. Status Detalhe Campos FY24'!$C$7:$C$725,'1. Status Resumo FY24'!$G$95,'2. Status Detalhe Campos FY24'!$D$7:$D$725,"2. Campo")+COUNTIFS('2. Status Detalhe Campos FY24'!$G$7:$G$725,'1. Status Resumo FY24'!$P101,'2. Status Detalhe Campos FY24'!$C$7:$C$725,'1. Status Resumo FY24'!$H$95,'2. Status Detalhe Campos FY24'!$D$7:$D$725,"2. Campo")+COUNTIFS(Table4[Status Atual],'1. Status Resumo FY24'!$P136,Table4[Sub-âmbito],'1. Status Resumo FY24'!$G$130,Table4[Tipo de teste],"2. Campo") -> 1 | V19: =U19-T19 -> -5
P20: 2.2 Em Re-especificação | T20: =COUNTIFS('2. Status Detalhe Campos FY24'!$H$7:$H$725,'1. Status Resumo FY24'!$P78,'2. Status Detalhe Campos FY24'!$C$7:$C$725,'1. Status Resumo FY24'!$G$71,'2. Status Detalhe Campos FY24'!$D$7:$D$725,"2. Campo")+COUNTIFS('2. Status Detalhe Campos FY24'!$H$7:$H$725,'1. Status Resumo FY24'!$P78,'2. Status Detalhe Campos FY24'!$C$7:$C$725,'1. Status Resumo FY24'!$H$71,'2. Status Detalhe Campos FY24'!$D$7:$D$725,"2. Campo")+COUNTIFS('2. Status Detalhe Campos FY24'!$H$7:$H$725,'1. Status Resumo FY24'!$P102,'2. Status Detalhe Campos FY24'!$C$7:$C$725,'1. Status Resumo FY24'!$G$95,'2. Status Detalhe Campos FY24'!$D$7:$D$725,"2. Campo")+COUNTIFS('2. Status Detalhe Campos FY24'!$H$7:$H$725,'1. Status Resumo FY24'!$P102,'2. Status Detalhe Campos FY24'!$C$7:$C$725,'1. Status Resumo FY24'!$H$95,'2. Status Detalhe Campos FY24'!$D$7:$D$725,"2. Campo")+COUNTIFS(Table4[Status Anterior],'1. Status Resumo FY24'!$P137,Table4[Sub-âmbito],'1. Status Resumo FY24'!$G$130,Table4[Tipo de teste],"2. Campo") -> 18 | U20: =COUNTIFS('2. Status Detalhe Campos FY24'!$G$7:$G$725,'1. Status Resumo FY24'!$P78,'2. Status Detalhe Campos FY24'!$C$7:$C$725,'1. Status Resumo FY24'!$G$71,'2. Status Detalhe Campos FY24'!$D$7:$D$725,"2. Campo")+COUNTIFS('2. Status Detalhe Campos FY24'!$G$7:$G$725,'1. Status Resumo FY24'!$P78,'2. Status Detalhe Campos FY24'!$C$7:$C$725,'1. Status Resumo FY24'!$H$71,'2. Status Detalhe Campos FY24'!$D$7:$D$725,"2. Campo")+COUNTIFS('2. Status Detalhe Campos FY24'!$G$7:$G$725,'1. Status Resumo FY24'!$P102,'2. Status Detalhe Campos FY24'!$C$7:$C$725,'1. Status Resumo FY24'!$G$95,'2. Status Detalhe Campos FY24'!$D$7:$D$725,"2. Campo")+COUNTIFS('2. Status Detalhe Campos FY24'!$G$7:$G$725,'1. Status Resumo FY24'!$P102,'2. Status Detalhe Campos FY24'!$C$7:$C$725,'1. Status Resumo FY24'!$H$95,'2. Status Detalhe Campos FY24'!$D$7:$D$725,"2. Campo")+COUNTIFS(Table4[Status Atual],'1. Status Resumo FY24'!$P137,Table4[Sub-âmbito],'1. Status Resumo FY24'!$G$130,Table4[Tipo de teste],"2. Campo") -> 8 | V20: =U20-T20 -> -10
P21: 3. Pendente de outros desenvolvimentos | T21: =COUNTIFS('2. Status Detalhe Campos FY24'!$H$7:$H$725,'1. Status Resumo FY24'!$P79,'2. Status Detalhe Campos FY24'!$C$7:$C$725,'1. Status Resumo FY24'!$G$71,'2. Status Detalhe Campos FY24'!$D$7:$D$725,"2. Campo")+COUNTIFS('2. Status Detalhe Campos FY24'!$H$7:$H$725,'1. Status Resumo FY24'!$P79,'2. Status Detalhe Campos FY24'!$C$7:$C$725,'1. Status Resumo FY24'!$H$71,'2. Status Detalhe Campos FY24'!$D$7:$D$725,"2. Campo")+COUNTIFS('2. Status Detalhe Campos FY24'!$H$7:$H$725,'1. Status Resumo FY24'!$P103,'2. Status Detalhe Campos FY24'!$C$7:$C$725,'1. Status Resumo FY24'!$G$95,'2. Status Detalhe Campos FY24'!$D$7:$D$725,"2. Campo")+COUNTIFS('2. Status Detalhe Campos FY24'!$H$7:$H$725,'1. Status Resumo FY24'!$P103,'2. Status Detalhe Campos FY24'!$C$7:$C$725,'1. Status Resumo FY24'!$H$95,'2. Status Detalhe Campos FY24'!$D$7:$D$725,"2. Campo")+COUNTIFS(Table4[Status Anterior],'1. Status Resumo FY24'!$P138,Table4[Sub-âmbito],'1. Status Resumo FY24'!$G$130,Table4[Tipo de teste],"2. Campo") -> 10 | U21: =COUNTIFS('2. Status Detalhe Campos FY24'!$G$7:$G$725,'1. Status Resumo FY24'!$P79,'2. Status Detalhe Campos FY24'!$C$7:$C$725,'1. Status Resumo FY24'!$G$71,'2. Status Detalhe Campos FY24'!$D$7:$D$725,"2. Campo")+COUNTIFS('2. Status Detalhe Campos FY24'!$G$7:$G$725,'1. Status Resumo FY24'!$P79,'2. Status Detalhe Campos FY24'!$C$7:$C$725,'1. Status Resumo FY24'!$H$71,'2. Status Detalhe Campos FY24'!$D$7:$D$725,"2. Campo")+COUNTIFS('2. Status Detalhe Campos FY24'!$G$7:$G$725,'1. Status Resumo FY24'!$P103,'2. Status Detalhe Campos FY24'!$C$7:$C$725,'1. Status Resumo FY24'!$G$95,'2. Status Detalhe Campos FY24'!$D$7:$D$725,"2. Campo")+COUNTIFS('2. Status Detalhe Campos FY24'!$G$7:$G$725,'1. Status Resumo FY24'!$P103,'2. Status Detalhe Campos FY24'!$C$7:$C$725,'1. Status Resumo FY24'!$H$95,'2. Status Detalhe Campos FY24'!$D$7:$D$725,"2. Campo")+COUNTIFS(Table4[Status Atual],'1. Status Resumo FY24'!$P138,Table4[Sub-âmbito],'1. Status Resumo FY24'!$G$130,Table4[Tipo de teste],"2. Campo") -> 15 | V21: =U21-T21 -> 5
P22: 4. Validação EF | T22: =COUNTIFS('2. Status Detalhe Campos FY24'!$H$7:$H$725,'1. Status Resumo FY24'!$P80,'2. Status Detalhe Campos FY24'!$C$7:$C$725,'1. Status Resumo FY24'!$G$71,'2. Status Detalhe Campos FY24'!$D$7:$D$725,"2. Campo")+COUNTIFS('2. Status Detalhe Campos FY24'!$H$7:$H$725,'1. Status Resumo FY24'!$P80,'2. Status Detalhe Campos FY24'!$C$7:$C$725,'1. Status Resumo FY24'!$H$71,'2. Status Detalhe Campos FY24'!$D$7:$D$725,"2. Campo")+COUNTIFS('2. Status Detalhe Campos FY24'!$H$7:$H$725,'1. Status Resumo FY24'!$P104,'2. Status Detalhe Campos FY24'!$C$7:$C$725,'1. Status Resumo FY24'!$G$95,'2. Status Detalhe Campos FY24'!$D$7:$D$725,"2. Campo")+COUNTIFS('2. Status Detalhe Campos FY24'!$H$7:$H$725,'1. Status Resumo FY24'!$P104,'2. Status Detalhe Campos FY24'!$C$7:$C$725,'1. Status Resumo FY24'!$H$95,'2. Status Detalhe Campos FY24'!$D$7:$D$725,"2. Campo")+COUNTIFS(Table4[Status Anterior],'1. Status Resumo FY24'!$P139,Table4[Sub-âmbito],'1. Status Resumo FY24'!$G$130,Table4[Tipo de teste],"2. Campo") -> 14 | U22: =COUNTIFS('2. Status Detalhe Campos FY24'!$G$7:$G$725,'1. Status Resumo FY24'!$P80,'2. Status Detalhe Campos FY24'!$C$7:$C$725,'1. Status Resumo FY24'!$G$71,'2. Status Detalhe Campos FY24'!$D$7:$D$725,"2. Campo")+COUNTIFS('2. Status Detalhe Campos FY24'!$G$7:$G$725,'1. Status Resumo FY24'!$P80,'2. Status Detalhe Campos FY24'!$C$7:$C$725,'1. Status Resumo FY24'!$H$71,'2. Status Detalhe Campos FY24'!$D$7:$D$725,"2. Campo")+COUNTIFS('2. Status Detalhe Campos FY24'!$G$7:$G$725,'1. Status Resumo FY24'!$P104,'2. Status Detalhe Campos FY24'!$C$7:$C$725,'1. Status Resumo FY24'!$G$95,'2. Status Detalhe Campos FY24'!$D$7:$D$725,"2. Campo")+COUNTIFS('2. Status Detalhe Campos FY24'!$G$7:$G$725,'1. Status Resumo FY24'!$P104,'2. Status Detalhe Campos FY24'!$C$7:$C$725,'1. Status Resumo FY24'!$H$95,'2. Status Detalhe Campos FY24'!$D$7:$D$725,"2. Campo")+COUNTIFS(Table4[Status Atual],'1. Status Resumo FY24'!$P139,Table4[Sub-âmbito],'1. Status Resumo FY24'!$G$130,Table4[Tipo de teste],"2. Campo") -> 56 | V22: =U22-T22 -> 42
P23: 5. Em Correção | R23: (incidências) | T23: =COUNTIFS('2. Status Detalhe Campos FY24'!$H$7:$H$725,'1. Status Resumo FY24'!$P81,'2. Status Detalhe Campos FY24'!$C$7:$C$725,'1. Status Resumo FY24'!$G$71,'2. Status Detalhe Campos FY24'!$D$7:$D$725,"2. Campo")+COUNTIFS('2. Status Detalhe Campos FY24'!$H$7:$H$725,'1. Status Resumo FY24'!$P81,'2. Status Detalhe Campos FY24'!$C$7:$C$725,'1. Status Resumo FY24'!$H$71,'2. Status Detalhe Campos FY24'!$D$7:$D$725,"2. Campo")+COUNTIFS('2. Status Detalhe Campos FY24'!$H$7:$H$725,'1. Status Resumo FY24'!$P105,'2. Status Detalhe Campos FY24'!$C$7:$C$725,'1. Status Resumo FY24'!$G$95,'2. Status Detalhe Campos FY24'!$D$7:$D$725,"2. Campo")+COUNTIFS('2. Status Detalhe Campos FY24'!$H$7:$H$725,'1. Status Resumo FY24'!$P105,'2. Status Detalhe Campos FY24'!$C$7:$C$725,'1. Status Resumo FY24'!$H$95,'2. Status Detalhe Campos FY24'!$D$7:$D$725,"2. Campo")+COUNTIFS(Table4[Status Anterior],'1. Status Resumo FY24'!$P140,Table4[Sub-âmbito],'1. Status Resumo FY24'!$G$130,Table4[Tipo de teste],"2. Campo") -> 1 | U23: =COUNTIFS('2. Status Detalhe Campos FY24'!$G$7:$G$725,'1. Status Resumo FY24'!$P81,'2. Status Detalhe Campos FY24'!$C$7:$C$725,'1. Status Resumo FY24'!$G$71,'2. Status Detalhe Campos FY24'!$D$7:$D$725,"2. Campo")+COUNTIFS('2. Status Detalhe Campos FY24'!$G$7:$G$725,'1. Status Resumo FY24'!$P81,'2. Status Detalhe Campos FY24'!$C$7:$C$725,'1. Status Resumo FY24'!$H$71,'2. Status Detalhe Campos FY24'!$D$7:$D$725,"2. Campo")+COUNTIFS('2. Status Detalhe Campos FY24'!$G$7:$G$725,'1. Status Resumo FY24'!$P105,'2. Status Detalhe Campos FY24'!$C$7:$C$725,'1. Status Resumo FY24'!$G$95,'2. Status Detalhe Campos FY24'!$D$7:$D$725,"2. Campo")+COUNTIFS('2. Status Detalhe Campos FY24'!$G$7:$G$725,'1. Status Resumo FY24'!$P105,'2. Status Detalhe Campos FY24'!$C$7:$C$725,'1. Status Resumo FY24'!$H$95,'2. Status Detalhe Campos FY24'!$D$7:$D$725,"2. Campo")+COUNTIFS(Table4[Status Atual],'1. Status Resumo FY24'!$P140,Table4[Sub-âmbito],'1. Status Resumo FY24'!$G$130,Table4[Tipo de teste],"2. Campo") -> 3 | V23: =U23-T23 -> 2
P24: 6. Em implementação (re-especificação) | T24: =COUNTIFS('2. Status Detalhe Campos FY24'!$H$7:$H$725,'1. Status Resumo FY24'!$P82,'2. Status Detalhe Campos FY24'!$C$7:$C$725,'1. Status Resumo FY24'!$G$71,'2. Status Detalhe Campos FY24'!$D$7:$D$725,"2. Campo")+COUNTIFS('2. Status Detalhe Campos FY24'!$H$7:$H$725,'1. Status Resumo FY24'!$P82,'2. Status Detalhe Campos FY24'!$C$7:$C$725,'1. Status Resumo FY24'!$H$71,'2. Status Detalhe Campos FY24'!$D$7:$D$725,"2. Campo")+COUNTIFS('2. Status Detalhe Campos FY24'!$H$7:$H$725,'1. Status Resumo FY24'!$P106,'2. Status Detalhe Campos FY24'!$C$7:$C$725,'1. Status Resumo FY24'!$G$95,'2. Status Detalhe Campos FY24'!$D$7:$D$725,"2. Campo")+COUNTIFS('2. Status Detalhe Campos FY24'!$H$7:$H$725,'1. Status Resumo FY24'!$P106,'2. Status Detalhe Campos FY24'!$C$7:$C$725,'1. Status Resumo FY24'!$H$95,'2. Status Detalhe Campos FY24'!$D$7:$D$725,"2. Campo")+COUNTIFS(Table4[Status Anterior],'1. Status Resumo FY24'!$P141,Table4[Sub-âmbito],'1. Status Resumo FY24'!$G$130,Table4[Tipo de teste],"2. Campo") -> 6 | U24: =COUNTIFS('2. Status Detalhe Campos FY24'!$G$7:$G$725,'1. Status Resumo FY24'!$P82,'2. Status Detalhe Campos FY24'!$C$7:$C$725,'1. Status Resumo FY24'!$G$71,'2. Status Detalhe Campos FY24'!$D$7:$D$725,"2. Campo")+COUNTIFS('2. Status Detalhe Campos FY24'!$G$7:$G$725,'1. Status Resumo FY24'!$P82,'2. Status Detalhe Campos FY24'!$C$7:$C$725,'1. Status Resumo FY24'!$H$71,'2. Status Detalhe Campos FY24'!$D$7:$D$725,"2. Campo")+COUNTIFS('2. Status Detalhe Campos FY24'!$G$7:$G$725,'1. Status Resumo FY24'!$P106,'2. Status Detalhe Campos FY24'!$C$7:$C$725,'1. Status Resumo FY24'!$G$95,'2. Status Detalhe Campos FY24'!$D$7:$D$725,"2. Campo")+COUNTIFS('2. Status Detalhe Campos FY24'!$G$7:$G$725,'1. Status Resumo FY24'!$P106,'2. Status Detalhe Campos FY24'!$C$7:$C$725,'1. Status Resumo FY24'!$H$95,'2. Status Detalhe Campos FY24'!$D$7:$D$725,"2. Campo")+COUNTIFS(Table4[Status Atual],'1. Status Resumo FY24'!$P141,Table4[Sub-âmbito],'1. Status Resumo FY24'!$G$130,Table4[Tipo de teste],"2. Campo") -> 48 | V24: =U24-T24 -> 42
P25: 7. Por iniciar | T25: =COUNTIFS('2. Status Detalhe Campos FY24'!$H$7:$H$725,'1. Status Resumo FY24'!$P83,'2. Status Detalhe Campos FY24'!$C$7:$C$725,'1. Status Resumo FY24'!$G$71,'2. Status Detalhe Campos FY24'!$D$7:$D$725,"2. Campo")+COUNTIFS('2. Status Detalhe Campos FY24'!$H$7:$H$725,'1. Status Resumo FY24'!$P83,'2. Status Detalhe Campos FY24'!$C$7:$C$725,'1. Status Resumo FY24'!$H$71,'2. Status Detalhe Campos FY24'!$D$7:$D$725,"2. Campo")+COUNTIFS('2. Status Detalhe Campos FY24'!$H$7:$H$725,'1. Status Resumo FY24'!$P107,'2. Status Detalhe Campos FY24'!$C$7:$C$725,'1. Status Resumo FY24'!$G$95,'2. Status Detalhe Campos FY24'!$D$7:$D$725,"2. Campo")+COUNTIFS('2. Status Detalhe Campos FY24'!$H$7:$H$725,'1. Status Resumo FY24'!$P107,'2. Status Detalhe Campos FY24'!$C$7:$C$725,'1. Status Resumo FY24'!$H$95,'2. Status Detalhe Campos FY24'!$D$7:$D$725,"2. Campo")+COUNTIFS(Table4[Status Anterior],'1. Status Resumo FY24'!$P142,Table4[Sub-âmbito],'1. Status Resumo FY24'!$G$130,Table4[Tipo de teste],"2. Campo") -> 0 | U25: =COUNTIFS('2. Status Detalhe Campos FY24'!$G$7:$G$725,'1. Status Resumo FY24'!$P83,'2. Status Detalhe Campos FY24'!$C$7:$C$725,'1. Status Resumo FY24'!$G$71,'2. Status Detalhe Campos FY24'!$D$7:$D$725,"2. Campo")+COUNTIFS('2. Status Detalhe Campos FY24'!$G$7:$G$725,'1. Status Resumo FY24'!$P83,'2. Status Detalhe Campos FY24'!$C$7:$C$725,'1. Status Resumo FY24'!$H$71,'2. Status Detalhe Campos FY24'!$D$7:$D$725,"2. Campo")+COUNTIFS('2. Status Detalhe Campos FY24'!$G$7:$G$725,'1. Status Resumo FY24'!$P107,'2. Status Detalhe Campos FY24'!$C$7:$C$725,'1. Status Resumo FY24'!$G$95,'2. Status Detalhe Campos FY24'!$D$7:$D$725,"2. Campo")+COUNTIFS('2. Status Detalhe Campos FY24'!$G$7:$G$725,'1. Status Resumo FY24'!$P107,'2. Status Detalhe Campos FY24'!$C$7:$C$725,'1. Status Resumo FY24'!$H$95,'2. Status Detalhe Campos FY24'!$D$7:$D$725,"2. Campo")+COUNTIFS(Table4[Status Atual],'1. Status Resumo FY24'!$P142,Table4[Sub-âmbito],'1. Status Resumo FY24'!$G$130,Table4[Tipo de teste],"2. Campo") -> 57 | V25: =U25-T25 -> 57
T26: =SUM(T17:T25) -> 550 | U26: =SUM(U17:U25) -> 700
B30: 1. Plano de Testes
C34: Planeado | X34: Highlights
D35: T. Campos | E35: T. Concluídos | F35: T. Cancelados | G35: Por testar | H35: 45674 | I35: 45674 | J35: 45678 | K35: Plano
C36: MBI | D36: =T84 -> 168 | E36: =T76 -> 147 | F36: =T75 -> 10 | G36: =D36-E36-F36 -> 11 | H36: 0 | I36: 0 | J36: 0 | K36: =SUM(H36:J36) -> 0 | X36: Testes 17 de janeiro: 1. Modelo Verde: - Foram concluídos 7 campos, sendo que estavam previstos testar 4 campos. Contudo, um dos campos planeados não foi testado uma vez que está pendente do alinhamento da especificação da tabela de parametrização com CdG e área de ESG Risk. 2. Pilar III: - Foram concluídos os 6 campos previstos no Pilar III , incluindo mais 2 campos. - Existem 2 campos pendentes do alinhamento da especificação da Tabela de Parametrização e de Output de Marcação Verde. Testes 21/Jan: 1. Modelo Bens Imóveis: - Atualização dos 12 campos do input Gloval; - Especificação Campo Novo tabela de Certificados - Re-especificação 4 campos reabertos da Tabela de Certificados [para incluir a lógica da tabela de acumulados gloval que já não será considerada] 2. Modelo Verde: - Re-especificação Parametrização Marcação Verde + Output Marcação Verde (12 campos) - Atualizar especificação com os novos códigos do campo Code_Nace 3. Pilar III: - Está previsto testar os 3 campos referentes a juros e comissões No próximo PdS já iremos partilhar a visão com o incremento dos novos campos do novo Projeto e com a reflexão das datas de entrega dos campos de Project Finance (6 campos MV + 3 campos Pilar III)
C37: MV | D37: =T108 -> 246 | E37: =T100 -> 204 | F37: =T99 -> 14 | G37: =D37-E37-F37 -> 28 | H37: 4 | I37: 7 | J37: 0 | K37: =SUM(I37:J37) -> 7
C38: Pilar III | D38: =T143 -> 136 | E38: =T135 -> 120 | F38: =T134 -> 0 | G38: =D38-E38-F38 -> 16 | H38: 6 | I38: 8 | J38: 3 | K38: =SUM(I38:J38) -> 11
C39: TOTAL | D39: =SUM(D36:D38) -> 550 | E39: =SUM(E36:E38) -> 471 | F39: =SUM(F36:F38) -> 24 | G39: =SUM(G36:G38) -> 55 | H39: =SUM(H36:H38) -> 10 | I39: =SUM(I36:I38) -> 15 | J39: 0 | K39: =SUM(K36:K38) -> 18
C40: Status | E40: =E39/$D$39 -> 0.85636364 | F40: =F39/$D$39 -> 0.043636364 | G40: =G39/$D$39 -> 0.1
C41: Satus s/ cancelados | E41: =E39/($D$39-$F$39) -> 0.89543726 | F41: - | G41: =G39/($D$39-$F$39) -> 0.10456274
C43: Real
D44: T. Campos | E44: T. Concluídos | F44: T. Cancelados | G44: Por testar | H44: 45674 | I44: 45678 | J44: Planeado | K44: Campos Em falta
C45: MBI | D45: =U84 -> 202 | E45: =U76 -> 143 | F45: =U75 -> 10 | G45: =D45-E45-F45 -> 49 | H45: 0 | I45: 0 | J45: =SUM(I45) -> 0 | K45: =G45-J45 -> 49 | L45: -> 12 campos Gloval + Campo Novo + 4 campos Tabela Certificados
C46: MV | D46: =U108 -> 292 | E46: =U100 -> 207 | F46: =U99 -> 12 | G46: =D46-E46-F46 -> 73 | H46: 7 | I46: 0 | J46: =SUM(I46) -> 0 | K46: =G46-J46 -> 73 | L46: -> 12 campos Marcação Verde + Campo Parametrização + Code Nace + 6 campos para incluir Projet Finance
C47: Pilar III | D47: =U143 -> 206 | E47: =U135 -> 136 | F47: =U134 -> 4 | G47: =D47-E47-F47 -> 66 | H47: 8 | I47: 3 | J47: =SUM(I47) -> 3 | K47: =G47-J47 -> 63 | L47: -> 3 campos para incluir Project Finance [Depende do MV] + 2 campos pendentes da Marcação Verde
C48: TOTAL | D48: =SUM(D45:D47) -> 700 | E48: =SUM(E45:E47) -> 486 | F48: =SUM(F45:F47) -> 26 | G48: =SUM(G45:G47) -> 188 | H48: =SUM(H45:H47) -> 15 | I48: 0 | J48: =SUM(J45:J47) -> 3 | K48: =SUM(K45:K47) -> 185
C49: Status | E49: =E48/$D$48 -> 0.69428571 | F49: =F48/$D$48 -> 0.037142857 | G49: =G48/$D$48 -> 0.26857143
C50: Satus s/ cancelados | E50: =E48/($D$48-F48) -> 0.72106825 | F50: - | G50: =G48/($D$48-F48) -> 0.27893175
C53: Visão de entregas de especificações
B71: 2. Modelo de Bens Imóveis | G71: Bens Imóveis - Input | H71: Bens Imóveis - Output | I71: Modelo Verde - Input | J71: Modelo Verde - Output | K71: Pilar III
C74: Resumo | G74: Detalhe por Tabela | P74: Status (campos) | T74: 45667 | U74: =T74+7 -> 45674 | V74: ∆ | X74: Highlights
P75: 0. Cancelado | T75: =COUNTIFS('2. Status Detalhe Campos FY24'!$H$7:$H$725,'1. Status Resumo FY24'!$P75,'2. Status Detalhe Campos FY24'!$C$7:$C$725,'1. Status Resumo FY24'!$G$71,'2. Status Detalhe Campos FY24'!$D$7:$D$725,"2. Campo")+COUNTIFS('2. Status Detalhe Campos FY24'!$H$7:$H$725,'1. Status Resumo FY24'!$P75,'2. Status Detalhe Campos FY24'!$C$7:$C$725,'1. Status Resumo FY24'!$H$71,'2. Status Detalhe Campos FY24'!$D$7:$D$725,"2. Campo") -> 10 | U75: =COUNTIFS('2. Status Detalhe Campos FY24'!$G$7:$G$725,'1. Status Resumo FY24'!$P75,'2. Status Detalhe Campos FY24'!$C$7:$C$725,'1. Status Resumo FY24'!$G$71,'2. Status Detalhe Campos FY24'!$D$7:$D$725,"2. Campo")+COUNTIFS('2. Status Detalhe Campos FY24'!$G$7:$G$725,'1. Status Resumo FY24'!$P75,'2. Status Detalhe Campos FY24'!$C$7:$C$725,'1. Status Resumo FY24'!$H$71,'2. Status Detalhe Campos FY24'!$D$7:$D$725,"2. Campo") -> 10 | V75: =U75-T75 -> 0 | X75: 1. Testes: Gloval: - Foram realizadas reuniões para alinhamento do processo da Gloval. Já foi alinhada a solução final e iremos avançar na re-especificação para posterior implementação. Tabela de Certificados: - Adicionalmente, já temos a validação de CDO para inclusão do novo campo na tabela de Certificados Energéticos. Iremos também re-especificar e enviar para tecnologia. - Foram reabertos 4 campos da tabela de certificados para incluir a lógica da escolha do registo da Gloval que estava na tabela acumulados da Gloval, uma vez que esta foi desconsiderada.
P76: 1. Concluído | T76: =COUNTIFS('2. Status Detalhe Campos FY24'!$H$7:$H$725,'1. Status Resumo FY24'!$P76,'2. Status Detalhe Campos FY24'!$C$7:$C$725,'1. Status Resumo FY24'!$G$71,'2. Status Detalhe Campos FY24'!$D$7:$D$725,"2. Campo")+COUNTIFS('2. Status Detalhe Campos FY24'!$H$7:$H$725,'1. Status Resumo FY24'!$P76,'2. Status Detalhe Campos FY24'!$C$7:$C$725,'1. Status Resumo FY24'!$H$71,'2. Status Detalhe Campos FY24'!$D$7:$D$725,"2. Campo") -> 147 | U76: =COUNTIFS('2. Status Detalhe Campos FY24'!$G$7:$G$725,'1. Status Resumo FY24'!$P76,'2. Status Detalhe Campos FY24'!$C$7:$C$725,'1. Status Resumo FY24'!$G$71,'2. Status Detalhe Campos FY24'!$D$7:$D$725,"2. Campo")+COUNTIFS('2. Status Detalhe Campos FY24'!$G$7:$G$725,'1. Status Resumo FY24'!$P76,'2. Status Detalhe Campos FY24'!$C$7:$C$725,'1. Status Resumo FY24'!$H$71,'2. Status Detalhe Campos FY24'!$D$7:$D$725,"2. Campo") -> 143 | V76: =U76-T76 -> -4
P77: 2.1 Em Teste | T77: =COUNTIFS('2. Status Detalhe Campos FY24'!$H$7:$H$725,'1. Status Resumo FY24'!$P77,'2. Status Detalhe Campos FY24'!$C$7:$C$725,'1. Status Resumo FY24'!$G$71,'2. Status Detalhe Campos FY24'!$D$7:$D$725,"2. Campo")+COUNTIFS('2. Status Detalhe Campos FY24'!$H$7:$H$725,'1. Status Resumo FY24'!$P77,'2. Status Detalhe Campos FY24'!$C$7:$C$725,'1. Status Resumo FY24'!$H$71,'2. Status Detalhe Campos FY24'!$D$7:$D$725,"2. Campo") -> 0 | U77: =COUNTIFS('2. Status Detalhe Campos FY24'!$G$7:$G$725,'1. Status Resumo FY24'!$P77,'2. Status Detalhe Campos FY24'!$C$7:$C$725,'1. Status Resumo FY24'!$G$71,'2. Status Detalhe Campos FY24'!$D$7:$D$725,"2. Campo")+COUNTIFS('2. Status Detalhe Campos FY24'!$G$7:$G$725,'1. Status Resumo FY24'!$P77,'2. Status Detalhe Campos FY24'!$C$7:$C$725,'1. Status Resumo FY24'!$H$71,'2. Status Detalhe Campos FY24'!$D$7:$D$725,"2. Campo") -> 1 | V77: =U77-T77 -> 1
D78: ="# "&U84 -> # 202 | P78: 2.2 Em Re-especificação | T78: =COUNTIFS('2. Status Detalhe Campos FY24'!$H$7:$H$725,'1. Status Resumo FY24'!$P78,'2. Status Detalhe Campos FY24'!$C$7:$C$725,'1. Status Resumo FY24'!$G$71,'2. Status Detalhe Campos FY24'!$D$7:$D$725,"2. Campo")+COUNTIFS('2. Status Detalhe Campos FY24'!$H$7:$H$725,'1. Status Resumo FY24'!$P78,'2. Status Detalhe Campos FY24'!$C$7:$C$725,'1. Status Resumo FY24'!$H$71,'2. Status Detalhe Campos FY24'!$D$7:$D$725,"2. Campo") -> 0 | U78: =COUNTIFS('2. Status Detalhe Campos FY24'!$G$7:$G$725,'1. Status Resumo FY24'!$P78,'2. Status Detalhe Campos FY24'!$C$7:$C$725,'1. Status Resumo FY24'!$G$71,'2. Status Detalhe Campos FY24'!$D$7:$D$725,"2. Campo")+COUNTIFS('2. Status Detalhe Campos FY24'!$G$7:$G$725,'1. Status Resumo FY24'!$P78,'2. Status Detalhe Campos FY24'!$C$7:$C$725,'1. Status Resumo FY24'!$H$71,'2. Status Detalhe Campos FY24'!$D$7:$D$725,"2. Campo") -> 0 | V78: =U78-T78 -> 0
P79: 3. Pendente de outros desenvolvimentos | T79: =COUNTIFS('2. Status Detalhe Campos FY24'!$H$7:$H$725,'1. Status Resumo FY24'!$P79,'2. Status Detalhe Campos FY24'!$C$7:$C$725,'1. Status Resumo FY24'!$G$71,'2. Status Detalhe Campos FY24'!$D$7:$D$725,"2. Campo")+COUNTIFS('2. Status Detalhe Campos FY24'!$H$7:$H$725,'1. Status Resumo FY24'!$P79,'2. Status Detalhe Campos FY24'!$C$7:$C$725,'1. Status Resumo FY24'!$H$71,'2. Status Detalhe Campos FY24'!$D$7:$D$725,"2. Campo") -> 0 | U79: =COUNTIFS('2. Status Detalhe Campos FY24'!$G$7:$G$725,'1. Status Resumo FY24'!$P79,'2. Status Detalhe Campos FY24'!$C$7:$C$725,'1. Status Resumo FY24'!$G$71,'2. Status Detalhe Campos FY24'!$D$7:$D$725,"2. Campo")+COUNTIFS('2. Status Detalhe Campos FY24'!$G$7:$G$725,'1. Status Resumo FY24'!$P79,'2. Status Detalhe Campos FY24'!$C$7:$C$725,'1. Status Resumo FY24'!$H$71,'2. Status Detalhe Campos FY24'!$D$7:$D$725,"2. Campo") -> 0 | V79: =U79-T79 -> 0
P80: 4. Validação EF | T80: =COUNTIFS('2. Status Detalhe Campos FY24'!$H$7:$H$725,'1. Status Resumo FY24'!$P80,'2. Status Detalhe Campos FY24'!$C$7:$C$725,'1. Status Resumo FY24'!$G$71,'2. Status Detalhe Campos FY24'!$D$7:$D$725,"2. Campo")+COUNTIFS('2. Status Detalhe Campos FY24'!$H$7:$H$725,'1. Status Resumo FY24'!$P80,'2. Status Detalhe Campos FY24'!$C$7:$C$725,'1. Status Resumo FY24'!$H$71,'2. Status Detalhe Campos FY24'!$D$7:$D$725,"2. Campo") -> 11 | U80: =COUNTIFS('2. Status Detalhe Campos FY24'!$G$7:$G$725,'1. Status Resumo FY24'!$P80,'2. Status Detalhe Campos FY24'!$C$7:$C$725,'1. Status Resumo FY24'!$G$71,'2. Status Detalhe Campos FY24'!$D$7:$D$725,"2. Campo")+COUNTIFS('2. Status Detalhe Campos FY24'!$G$7:$G$725,'1. Status Resumo FY24'!$P80,'2. Status Detalhe Campos FY24'!$C$7:$C$725,'1. Status Resumo FY24'!$H$71,'2. Status Detalhe Campos FY24'!$D$7:$D$725,"2. Campo") -> 0 | V80: =U80-T80 -> -11
P81: 5. Em Correção | R81: (incidências) | T81: =COUNTIFS('2. Status Detalhe Campos FY24'!$H$7:$H$725,'1. Status Resumo FY24'!$P81,'2. Status Detalhe Campos FY24'!$C$7:$C$725,'1. Status Resumo FY24'!$G$71,'2. Status Detalhe Campos FY24'!$D$7:$D$725,"2. Campo")+COUNTIFS('2. Status Detalhe Campos FY24'!$H$7:$H$725,'1. Status Resumo FY24'!$P81,'2. Status Detalhe Campos FY24'!$C$7:$C$725,'1. Status Resumo FY24'!$H$71,'2. Status Detalhe Campos FY24'!$D$7:$D$725,"2. Campo") -> 0 | U81: =COUNTIFS('2. Status Detalhe Campos FY24'!$G$7:$G$725,'1. Status Resumo FY24'!$P81,'2. Status Detalhe Campos FY24'!$C$7:$C$725,'1. Status Resumo FY24'!$G$71,'2. Status Detalhe Campos FY24'!$D$7:$D$725,"2. Campo")+COUNTIFS('2. Status Detalhe Campos FY24'!$G$7:$G$725,'1. Status Resumo FY24'!$P81,'2. Status Detalhe Campos FY24'!$C$7:$C$725,'1. Status Resumo FY24'!$H$71,'2. Status Detalhe Campos FY24'!$D$7:$D$725,"2. Campo") -> 0 | V81: =U81-T81 -> 0
P82: 6. Em implementação (re-especificação) | T82: =COUNTIFS('2. Status Detalhe Campos FY24'!$H$7:$H$725,'1. Status Resumo FY24'!$P82,'2. Status Detalhe Campos FY24'!$C$7:$C$725,'1. Status Resumo FY24'!$G$71,'2. Status Detalhe Campos FY24'!$D$7:$D$725,"2. Campo")+COUNTIFS('2. Status Detalhe Campos FY24'!$H$7:$H$725,'1. Status Resumo FY24'!$P82,'2. Status Detalhe Campos FY24'!$C$7:$C$725,'1. Status Resumo FY24'!$H$71,'2. Status Detalhe Campos FY24'!$D$7:$D$725,"2. Campo") -> 0 | U82: =COUNTIFS('2. Status Detalhe Campos FY24'!$G$7:$G$725,'1. Status Resumo FY24'!$P82,'2. Status Detalhe Campos FY24'!$C$7:$C$725,'1. Status Resumo FY24'!$G$71,'2. Status Detalhe Campos FY24'!$D$7:$D$725,"2. Campo")+COUNTIFS('2. Status Detalhe Campos FY24'!$G$7:$G$725,'1. Status Resumo FY24'!$P82,'2. Status Detalhe Campos FY24'!$C$7:$C$725,'1. Status Resumo FY24'!$H$71,'2. Status Detalhe Campos FY24'!$D$7:$D$725,"2. Campo") -> 48 | V82: =U82-T82 -> 48
P83: 7. Por iniciar | T83: =COUNTIFS('2. Status Detalhe Campos FY24'!$H$7:$H$725,'1. Status Resumo FY24'!$P83,'2. Status Detalhe Campos FY24'!$C$7:$C$725,'1. Status Resumo FY24'!$G$71,'2. Status Detalhe Campos FY24'!$D$7:$D$725,"2. Campo")+COUNTIFS('2. Status Detalhe Campos FY24'!$H$7:$H$725,'1. Status Resumo FY24'!$P83,'2. Status Detalhe Campos FY24'!$C$7:$C$725,'1. Status Resumo FY24'!$H$71,'2. Status Detalhe Campos FY24'!$D$7:$D$725,"2. Campo") -> 0 | U83: =COUNTIFS('2. Status Detalhe Campos FY24'!$G$7:$G$725,'1. Status Resumo FY24'!$P83,'2. Status Detalhe Campos FY24'!$C$7:$C$725,'1. Status Resumo FY24'!$G$71,'2. Status Detalhe Campos FY24'!$D$7:$D$725,"2. Campo")+COUNTIFS('2. Status Detalhe Campos FY24'!$G$7:$G$725,'1. Status Resumo FY24'!$P83,'2. Status Detalhe Campos FY24'!$C$7:$C$725,'1. Status Resumo FY24'!$H$71,'2. Status Detalhe Campos FY24'!$D$7:$D$725,"2. Campo") -> 0 | V83: =U83-T83 -> 0
T84: =SUM(T75:T83) -> 168 | U84: =SUM(U75:U83) -> 202
G85: Status (Tabelas) | P85: Status (Universos)
F86: > | G86: Tabela de Bens Imóveis | L86: OK | O86: > | P86: Universo Bens Colateralizados (MUG) | T86: OK
F87: > | G87: Tabelas de Processos Imobiliários | L87: OK | O87: > | P87: Universo Bens Não Colateralizados (GP) | T87: OK
F88: > | G88: Tabela de Traçabilidade Processo -Bem | L88: OK | O88: > | P88: Universo Bens Adjudicados | T88: Não serão testados neste projeto
F89: > | G89: Tabela de Traçabilidade Crédito - Processo | L89: OK
F90: > | G90: Tabela input de Cerificados Energéticos (Gloval) | L90: Em Re-especificação
F91: > | G91: Tabela Output de Cerificados Energéticos | L91: Em Re-especificação
B95: 3. Modelo Verde | G95: Modelo Verde - Input | H95: Modelo Verde - Output
C98: Resumo | G98: Detalhe por Tabela | P98: Status (campos) | T98: =T74 -> 45667 | U98: =U74 -> 45674 | V98: ∆ | X98: Highlights
P99: 0. Cancelado | T99: =COUNTIFS('2. Status Detalhe Campos FY24'!$H$7:$H$725,'1. Status Resumo FY24'!$P99,'2. Status Detalhe Campos FY24'!$C$7:$C$725,'1. Status Resumo FY24'!$G$95,'2. Status Detalhe Campos FY24'!$D$7:$D$725,"2. Campo")+COUNTIFS('2. Status Detalhe Campos FY24'!$H$7:$H$725,'1. Status Resumo FY24'!$P99,'2. Status Detalhe Campos FY24'!$C$7:$C$725,'1. Status Resumo FY24'!$H$95,'2. Status Detalhe Campos FY24'!$D$7:$D$725,"2. Campo") -> 14 | U99: =COUNTIFS('2. Status Detalhe Campos FY24'!$G$7:$G$725,'1. Status Resumo FY24'!$P99,'2. Status Detalhe Campos FY24'!$C$7:$C$725,'1. Status Resumo FY24'!$G$95,'2. Status Detalhe Campos FY24'!$D$7:$D$725,"2. Campo")+COUNTIFS('2. Status Detalhe Campos FY24'!$G$7:$G$725,'1. Status Resumo FY24'!$P99,'2. Status Detalhe Campos FY24'!$C$7:$C$725,'1. Status Resumo FY24'!$H$95,'2. Status Detalhe Campos FY24'!$D$7:$D$725,"2. Campo") -> 12 | V99: =U99-T99 -> -2 | X99: 1. Datas de entrega de Tecnologia: - Emissões Project Finance (Tabela de Clientes) (6 campos) -> 27/01 - Novo input Project Finance (Tabela de Clientes): 23/01 2. Testes: Tabela de Output de Clientes: - Foram concluídos os 3 campos previstos testar esta semana. - Partilhada a re-especificação de Project Finance. Adicionalmente foi realizada uma reunião com CDO para aprovação da nova tabela de Input necessária para o calculo de emissões de Project Finance. A mesma já foi validada e já enviamos a especifiação para Tecnologia. Tabela de Bens Imóveis: - Fechados 4 campos Tabela de Parametrização Marcação Verde: - Não foi possível testar a tabela de parametrização porque a especificação da mesma ainda não está concluída. A reunião de hoje servirá para concluir este tema. Tabela de Output Marcação Verde: - Foram realizadas várias sessões com a área de CdG e ESG Risk para alinhamento da especificação de Marcação Verde. Está agendada uma reunião para hoje para fecho do tema.
P100: 1. Concluído | T100: =COUNTIFS('2. Status Detalhe Campos FY24'!$H$7:$H$725,'1. Status Resumo FY24'!$P100,'2. Status Detalhe Campos FY24'!$C$7:$C$725,'1. Status Resumo FY24'!$G$95,'2. Status Detalhe Campos FY24'!$D$7:$D$725,"2. Campo")+COUNTIFS('2. Status Detalhe Campos FY24'!$H$7:$H$725,'1. Status Resumo FY24'!$P100,'2. Status Detalhe Campos FY24'!$C$7:$C$725,'1. Status Resumo FY24'!$H$95,'2. Status Detalhe Campos FY24'!$D$7:$D$725,"2. Campo") -> 204 | U100: =COUNTIFS('2. Status Detalhe Campos FY24'!$G$7:$G$725,'1. Status Resumo FY24'!$P100,'2. Status Detalhe Campos FY24'!$C$7:$C$725,'1. Status Resumo FY24'!$G$95,'2. Status Detalhe Campos FY24'!$D$7:$D$725,"2. Campo")+COUNTIFS('2. Status Detalhe Campos FY24'!$G$7:$G$725,'1. Status Resumo FY24'!$P100,'2. Status Detalhe Campos FY24'!$C$7:$C$725,'1. Status Resumo FY24'!$H$95,'2. Status Detalhe Campos FY24'!$D$7:$D$725,"2. Campo") -> 207 | V100: =U100-T100 -> 3
P101: 2.1 Em Teste | T101: =COUNTIFS('2. Status Detalhe Campos FY24'!$H$7:$H$725,'1. Status Resumo FY24'!$P101,'2. Status Detalhe Campos FY24'!$C$7:$C$725,'1. Status Resumo FY24'!$G$95,'2. Status Detalhe Campos FY24'!$D$7:$D$725,"2. Campo")+COUNTIFS('2. Status Detalhe Campos FY24'!$H$7:$H$725,'1. Status Resumo FY24'!$P101,'2. Status Detalhe Campos FY24'!$C$7:$C$725,'1. Status Resumo FY24'!$H$95,'2. Status Detalhe Campos FY24'!$D$7:$D$725,"2. Campo") -> 3 | U101: =COUNTIFS('2. Status Detalhe Campos FY24'!$G$7:$G$725,'1. Status Resumo FY24'!$P101,'2. Status Detalhe Campos FY24'!$C$7:$C$725,'1. Status Resumo FY24'!$G$95,'2. Status Detalhe Campos FY24'!$D$7:$D$725,"2. Campo")+COUNTIFS('2. Status Detalhe Campos FY24'!$G$7:$G$725,'1. Status Resumo FY24'!$P101,'2. Status Detalhe Campos FY24'!$C$7:$C$725,'1. Status Resumo FY24'!$H$95,'2. Status Detalhe Campos FY24'!$D$7:$D$725,"2. Campo") -> 0 | V101: =U101-T101 -> -3
D102: ="# "&U108 -> # 292 | P102: 2.2 Em Re-especificação | T102: =COUNTIFS('2. Status Detalhe Campos FY24'!$H$7:$H$725,'1. Status Resumo FY24'!$P102,'2. Status Detalhe Campos FY24'!$C$7:$C$725,'1. Status Resumo FY24'!$G$95,'2. Status Detalhe Campos FY24'!$D$7:$D$725,"2. Campo")+COUNTIFS('2. Status Detalhe Campos FY24'!$H$7:$H$725,'1. Status Resumo FY24'!$P102,'2. Status Detalhe Campos FY24'!$C$7:$C$725,'1. Status Resumo FY24'!$H$95,'2. Status Detalhe Campos FY24'!$D$7:$D$725,"2. Campo") -> 18 | U102: =COUNTIFS('2. Status Detalhe Campos FY24'!$G$7:$G$725,'1. Status Resumo FY24'!$P102,'2. Status Detalhe Campos FY24'!$C$7:$C$725,'1. Status Resumo FY24'!$G$95,'2. Status Detalhe Campos FY24'!$D$7:$D$725,"2. Campo")+COUNTIFS('2. Status Detalhe Campos FY24'!$G$7:$G$725,'1. Status Resumo FY24'!$P102,'2. Status Detalhe Campos FY24'!$C$7:$C$725,'1. Status Resumo FY24'!$H$95,'2. Status Detalhe Campos FY24'!$D$7:$D$725,"2. Campo") -> 7 | V102: =U102-T102 -> -11
P103: 3. Pendente de outros desenvolvimentos | T103: =COUNTIFS('2. Status Detalhe Campos FY24'!$H$7:$H$725,'1. Status Resumo FY24'!$P103,'2. Status Detalhe Campos FY24'!$C$7:$C$725,'1. Status Resumo FY24'!$G$95,'2. Status Detalhe Campos FY24'!$D$7:$D$725,"2. Campo")+COUNTIFS('2. Status Detalhe Campos FY24'!$H$7:$H$725,'1. Status Resumo FY24'!$P103,'2. Status Detalhe Campos FY24'!$C$7:$C$725,'1. Status Resumo FY24'!$H$95,'2. Status Detalhe Campos FY24'!$D$7:$D$725,"2. Campo") -> 0 | U103: =COUNTIFS('2. Status Detalhe Campos FY24'!$G$7:$G$725,'1. Status Resumo FY24'!$P103,'2. Status Detalhe Campos FY24'!$C$7:$C$725,'1. Status Resumo FY24'!$G$95,'2. Status Detalhe Campos FY24'!$D$7:$D$725,"2. Campo")+COUNTIFS('2. Status Detalhe Campos FY24'!$G$7:$G$725,'1. Status Resumo FY24'!$P103,'2. Status Detalhe Campos FY24'!$C$7:$C$725,'1. Status Resumo FY24'!$H$95,'2. Status Detalhe Campos FY24'!$D$7:$D$725,"2. Campo") -> 6 | V103: =U103-T103 -> 6
P104: 4. Validação EF | T104: =COUNTIFS('2. Status Detalhe Campos FY24'!$H$7:$H$725,'1. Status Resumo FY24'!$P104,'2. Status Detalhe Campos FY24'!$C$7:$C$725,'1. Status Resumo FY24'!$G$95,'2. Status Detalhe Campos FY24'!$D$7:$D$725,"2. Campo")+COUNTIFS('2. Status Detalhe Campos FY24'!$H$7:$H$725,'1. Status Resumo FY24'!$P104,'2. Status Detalhe Campos FY24'!$C$7:$C$725,'1. Status Resumo FY24'!$H$95,'2. Status Detalhe Campos FY24'!$D$7:$D$725,"2. Campo") -> 1 | U104: =COUNTIFS('2. Status Detalhe Campos FY24'!$G$7:$G$725,'1. Status Resumo FY24'!$P104,'2. Status Detalhe Campos FY24'!$C$7:$C$725,'1. Status Resumo FY24'!$G$95,'2. Status Detalhe Campos FY24'!$D$7:$D$725,"2. Campo")+COUNTIFS('2. Status Detalhe Campos FY24'!$G$7:$G$725,'1. Status Resumo FY24'!$P104,'2. Status Detalhe Campos FY24'!$C$7:$C$725,'1. Status Resumo FY24'!$H$95,'2. Status Detalhe Campos FY24'!$D$7:$D$725,"2. Campo") -> 55 | V104: =U104-T104 -> 54
P105: 5. Em Correção | R105: (incidências) | T105: =COUNTIFS('2. Status Detalhe Campos FY24'!$H$7:$H$725,'1. Status Resumo FY24'!$P105,'2. Status Detalhe Campos FY24'!$C$7:$C$725,'1. Status Resumo FY24'!$G$95,'2. Status Detalhe Campos FY24'!$D$7:$D$725,"2. Campo")+COUNTIFS('2. Status Detalhe Campos FY24'!$H$7:$H$725,'1. Status Resumo FY24'!$P105,'2. Status Detalhe Campos FY24'!$C$7:$C$725,'1. Status Resumo FY24'!$H$95,'2. Status Detalhe Campos FY24'!$D$7:$D$725,"2. Campo") -> 0 | U105: =COUNTIFS('2. Status Detalhe Campos FY24'!$G$7:$G$725,'1. Status Resumo FY24'!$P105,'2. Status Detalhe Campos FY24'!$C$7:$C$725,'1. Status Resumo FY24'!$G$95,'2. Status Detalhe Campos FY24'!$D$7:$D$725,"2. Campo")+COUNTIFS('2. Status Detalhe Campos FY24'!$G$7:$G$725,'1. Status Resumo FY24'!$P105,'2. Status Detalhe Campos FY24'!$C$7:$C$725,'1. Status Resumo FY24'!$H$95,'2. Status Detalhe Campos FY24'!$D$7:$D$725,"2. Campo") -> 0 | V105: =U105-T105 -> 0
P106: 6. Em implementação (re-especificação) | T106: =COUNTIFS('2. Status Detalhe Campos FY24'!$H$7:$H$725,'1. Status Resumo FY24'!$P106,'2. Status Detalhe Campos FY24'!$C$7:$C$725,'1. Status Resumo FY24'!$G$95,'2. Status Detalhe Campos FY24'!$D$7:$D$725,"2. Campo")+COUNTIFS('2. Status Detalhe Campos FY24'!$H$7:$H$725,'1. Status Resumo FY24'!$P106,'2. Status Detalhe Campos FY24'!$C$7:$C$725,'1. Status Resumo FY24'!$H$95,'2. Status Detalhe Campos FY24'!$D$7:$D$725,"2. Campo") -> 6 | U106: =COUNTIFS('2. Status Detalhe Campos FY24'!$G$7:$G$725,'1. Status Resumo FY24'!$P106,'2. Status Detalhe Campos FY24'!$C$7:$C$725,'1. Status Resumo FY24'!$G$95,'2. Status Detalhe Campos FY24'!$D$7:$D$725,"2. Campo")+COUNTIFS('2. Status Detalhe Campos FY24'!$G$7:$G$725,'1. Status Resumo FY24'!$P106,'2. Status Detalhe Campos FY24'!$C$7:$C$725,'1. Status Resumo FY24'!$H$95,'2. Status Detalhe Campos FY24'!$D$7:$D$725,"2. Campo") -> 0 | V106: =U106-T106 -> -6
P107: 7. Por iniciar | T107: =COUNTIFS('2. Status Detalhe Campos FY24'!$H$7:$H$725,'1. Status Resumo FY24'!$P107,'2. Status Detalhe Campos FY24'!$C$7:$C$725,'1. Status Resumo FY24'!$G$95,'2. Status Detalhe Campos FY24'!$D$7:$D$725,"2. Campo")+COUNTIFS('2. Status Detalhe Campos FY24'!$H$7:$H$725,'1. Status Resumo FY24'!$P107,'2. Status Detalhe Campos FY24'!$C$7:$C$725,'1. Status Resumo FY24'!$H$95,'2. Status Detalhe Campos FY24'!$D$7:$D$725,"2. Campo") -> 0 | U107: =COUNTIFS('2. Status Detalhe Campos FY24'!$G$7:$G$725,'1. Status Resumo FY24'!$P107,'2. Status Detalhe Campos FY24'!$C$7:$C$725,'1. Status Resumo FY24'!$G$95,'2. Status Detalhe Campos FY24'!$D$7:$D$725,"2. Campo")+COUNTIFS('2. Status Detalhe Campos FY24'!$G$7:$G$725,'1. Status Resumo FY24'!$P107,'2. Status Detalhe Campos FY24'!$C$7:$C$725,'1. Status Resumo FY24'!$H$95,'2. Status Detalhe Campos FY24'!$D$7:$D$725,"2. Campo") -> 5 | V107: =U107-T107 -> 5
T108: =SUM(T99:T107) -> 246 | U108: =SUM(U99:U107) -> 292
P110: Status (Universos - Inputs)
O111: > | P111: modesg_inp_risco_fisico | T111: OK
O112: > | P112: modesg_inp_nfrd_alinhamento_tax | T112: OK
O113: > | P113: modesg_inp_km_medios_emss_vcls | T113: OK
O114: > | P114: modesg_inp_emss_vcls | T114: OK
O115: > | P115: modesg_inp_emss_scib | T115: OK
O116: > | P116: modesg_inp_emss_nace | T116: OK
O117: > | P117: modesg_inp_emss_bens_imoveis | T117: OK
O118: > | P118: modesg_inp_empr_excl_paris | T118: OK
O119: > | P119: modesg_param_sfcs_taxon_europeia | T119: Validação EF
O120: > | P120: Input Munich Re | T120: Em Implementação
P122: Status (Universos - Outputs)
O123: > | P123: modesg_out_ems_vcls | T123: OK
O124: > | P124: modesg_out_bens_imoveis | T124: OK (coerente com Modelo de Bens Imóveis)
O125: > | P125: modesg_out_empr_info_nfin | T125: OK
O126: > | P126: modesg_out_sfcs_taxon_europeia | T126: Validação EF
B130: 4. Loan Tape | Pilar III | G130: Pilar III
C133: Resumo | G133: Detalhe por Tabela | P133: Status (campos) | T133: =T74 -> 45667 | U133: =U74 -> 45674 | V133: ∆ | X133: Highlights
P134: 0. Cancelado | T134: =COUNTIFS(Table4[Status Anterior],'1. Status Resumo FY24'!$P134,Table4[Sub-âmbito],'1. Status Resumo FY24'!$G$130,Table4[Tipo de teste],"2. Campo") -> 0 | U134: =COUNTIFS(Table4[Status Atual],'1. Status Resumo FY24'!$P134,Table4[Sub-âmbito],'1. Status Resumo FY24'!$G$130,Table4[Tipo de teste],"2. Campo") -> 4 | V134: =U134-T134 -> 4 | X134: 1. Testes: Tabela de Clientes (lt003_entity): - Foram fechados 7 campos, número superior ao previsto. Tabela de Contratos (lt002_instrument): - 1 não foi possível testar por dependência do alinhamento da especificação da tabela de parametrização e da output de Marcação Verde Tabela da relação do Contrato/Categoria (lt007_instr_activity): - 1 não foi possível testar por dependência do alinhamento da especificação da tabela de parametrização e da output de Marcação Verde Tabela de Garantias (lt004_protection): - Concluído 1 campo, conforme previsto.
P135: 1. Concluído | T135: =COUNTIFS(Table4[Status Anterior],'1. Status Resumo FY24'!$P135,Table4[Sub-âmbito],'1. Status Resumo FY24'!$G$130,Table4[Tipo de teste],"2. Campo") -> 120 | U135: =COUNTIFS(Table4[Status Atual],'1. Status Resumo FY24'!$P135,Table4[Sub-âmbito],'1. Status Resumo FY24'!$G$130,Table4[Tipo de teste],"2. Campo") -> 136 | V135: =U135-T135 -> 16
P136: 2.1 Em Teste | T136: =COUNTIFS(Table4[Status Anterior],'1. Status Resumo FY24'!$P136,Table4[Sub-âmbito],'1. Status Resumo FY24'!$G$130,Table4[Tipo de teste],"2. Campo") -> 3 | U136: =COUNTIFS(Table4[Status Atual],'1. Status Resumo FY24'!$P136,Table4[Sub-âmbito],'1. Status Resumo FY24'!$G$130,Table4[Tipo de teste],"2. Campo") -> 0 | V136: =U136-T136 -> -3
D137: ="# "&U143 -> # 206 | P137: 2.2 Em Re-especificação | T137: =COUNTIFS(Table4[Status Anterior],'1. Status Resumo FY24'!$P137,Table4[Sub-âmbito],'1. Status Resumo FY24'!$G$130,Table4[Tipo de teste],"2. Campo") -> 0 | U137: =COUNTIFS(Table4[Status Atual],'1. Status Resumo FY24'!$P137,Table4[Sub-âmbito],'1. Status Resumo FY24'!$G$130,Table4[Tipo de teste],"2. Campo") -> 1 | V137: =U137-T137 -> 1
P138: 3. Pendente de outros desenvolvimentos | T138: =COUNTIFS(Table4[Status Anterior],'1. Status Resumo FY24'!$P138,Table4[Sub-âmbito],'1. Status Resumo FY24'!$G$130,Table4[Tipo de teste],"2. Campo") -> 10 | U138: =COUNTIFS(Table4[Status Atual],'1. Status Resumo FY24'!$P138,Table4[Sub-âmbito],'1. Status Resumo FY24'!$G$130,Table4[Tipo de teste],"2. Campo") -> 9 | V138: =U138-T138 -> -1
P139: 4. Validação EF | T139: =COUNTIFS(Table4[Status Anterior],'1. Status Resumo FY24'!$P139,Table4[Sub-âmbito],'1. Status Resumo FY24'!$G$130,Table4[Tipo de teste],"2. Campo") -> 2 | U139: =COUNTIFS(Table4[Status Atual],'1. Status Resumo FY24'!$P139,Table4[Sub-âmbito],'1. Status Resumo FY24'!$G$130,Table4[Tipo de teste],"2. Campo") -> 1 | V139: =U139-T139 -> -1
P140: 5. Em Correção | R140: (incidências) | T140: =COUNTIFS(Table4[Status Anterior],'1. Status Resumo FY24'!$P140,Table4[Sub-âmbito],'1. Status Resumo FY24'!$G$130,Table4[Tipo de teste],"2. Campo") -> 1 | U140: =COUNTIFS(Table4[Status Atual],'1. Status Resumo FY24'!$P140,Table4[Sub-âmbito],'1. Status Resumo FY24'!$G$130,Table4[Tipo de teste],"2. Campo") -> 3 | V140: =U140-T140 -> 2
P141: 6. Em implementação (re-especificação) | T141: =COUNTIFS(Table4[Status Anterior],'1. Status Resumo FY24'!$P141,Table4[Sub-âmbito],'1. Status Resumo FY24'!$G$130,Table4[Tipo de teste],"2. Campo") -> 0 | U141: =COUNTIFS(Table4[Status Atual],'1. Status Resumo FY24'!$P141,Table4[Sub-âmbito],'1. Status Resumo FY24'!$G$130,Table4[Tipo de teste],"2. Campo") -> 0 | V141: =U141-T141 -> 0
P142: 7. Por iniciar | T142: =COUNTIFS(Table4[Status Anterior],'1. Status Resumo FY24'!$P142,Table4[Sub-âmbito],'1. Status Resumo FY24'!$G$130,Table4[Tipo de teste],"2. Campo") -> 0 | U142: =COUNTIFS(Table4[Status Atual],'1. Status Resumo FY24'!$P142,Table4[Sub-âmbito],'1. Status Resumo FY24'!$G$130,Table4[Tipo de teste],"2. Campo") -> 52 | V142: =U142-T142 -> 52
T143: =SUM(T134:T142) -> 136 | U143: =SUM(U134:U142) -> 206
P145: Status (Tabelas)
O146: > | P146: lt002_instrument | T146: Em Curso
O147: > | P147: lt003_entity | T147: OK (Em falta portfolio Project Finance)
O148: > | P148: lt004_protection | T148: OK
O149: > | P149: lt005_instr_ent | T149: OK
O150: > | P150: lt006_instr_prot | T150: OK
O151: > | P151: lt007_instr_activity | T151: Validação EF
O152: > | P152: lt827_mthd_usd_instrmnt | T152: OK
O153: > | P153: lt826_esg_sbsctr | T153: OK

Sheet 2. Status Detalhe Campos FY24
E2: Novos requisitos
B6: Âmbito | C6: Sub-âmbito | D6: Tipo de teste | E6: Tabela | F6: Campo | G6: Status Atual | H6: Status Anterior | I6: Observações | J6: Data de Pedido correção/esclarecimento | K6: Data de correção prevista | L6: Data de correção efetiva | M6: Data Prevista de Re-especificação | N6: Data Prevista de Teste | O6: Modelo | Q6: Owner
A7: =E7&F7 -> ENERGY_CERTIFICATE_EST_INPUTn.a. | B7: Pilar III | C7: Bens Imóveis - Input | D7: 1. Universo | E7: ENERGY_CERTIFICATE_EST_INPUT | F7: n.a. | G7: =VLOOKUP(A7,Plano_V3!$A$26:$G$753,7,0) -> 6. Em implementação (re-especificação) | H7: 4. Validação EF | J7: =IF(VLOOKUP(A7,'Aux - pivots1'!$A:$E,3,0)=0, "",VLOOKUP(A7,'Aux - pivots1'!$A:$E,3,0)) | K7: =IF(VLOOKUP(A7,'Aux - pivots1'!$A:$E,4,0)=0, "",VLOOKUP(A7,'Aux - pivots1'!$A:$E,4,0)) | L7: =IF(VLOOKUP(A7,'Aux - pivots1'!$A:$E,5,0)=0, "",VLOOKUP(A7,'Aux - pivots1'!$A:$E,5,0)) | O7: Bens Imóveis
A8: =E8&F8 -> ENERGY_CERTIFICATE_EST_INPUTCHAVE_GLOVAL | B8: Pilar III | C8: Bens Imóveis - Input | D8: 2. Campo | E8: ENERGY_CERTIFICATE_EST_INPUT | F8: CHAVE_GLOVAL | G8: =VLOOKUP(A8,Plano_V3!$A$26:$G$753,7,0) -> 6. Em implementação (re-especificação) | H8: 4. Validação EF | J8: =IF(VLOOKUP(A8,'Aux - pivots1'!$A:$E,3,0)=0, "",VLOOKUP(A8,'Aux - pivots1'!$A:$E,3,0)) | K8: =IF(VLOOKUP(A8,'Aux - pivots1'!$A:$E,4,0)=0, "",VLOOKUP(A8,'Aux - pivots1'!$A:$E,4,0)) | L8: =IF(VLOOKUP(A8,'Aux - pivots1'!$A:$E,5,0)=0, "",VLOOKUP(A8,'Aux - pivots1'!$A:$E,5,0)) | O8: Bens Imóveis
A9: =E9&F9 -> ENERGY_CERTIFICATE_EST_INPUTPROPERTY_BANK_ID | B9: Pilar III | C9: Bens Imóveis - Input | D9: 2. Campo | E9: ENERGY_CERTIFICATE_EST_INPUT | F9: PROPERTY_BANK_ID | G9: =VLOOKUP(A9,Plano_V3!$A$26:$G$753,7,0) -> 6. Em implementação (re-especificação) | H9: 4. Validação EF | J9: =IF(VLOOKUP(A9,'Aux - pivots1'!$A:$E,3,0)=0, "",VLOOKUP(A9,'Aux - pivots1'!$A:$E,3,0)) | K9: =IF(VLOOKUP(A9,'Aux - pivots1'!$A:$E,4,0)=0, "",VLOOKUP(A9,'Aux - pivots1'!$A:$E,4,0)) | L9: =IF(VLOOKUP(A9,'Aux - pivots1'!$A:$E,5,0)=0, "",VLOOKUP(A9,'Aux - pivots1'!$A:$E,5,0)) | O9: Bens Imóveis
A10: =E10&F10 -> ENERGY_CERTIFICATE_EST_INPUTPROPERTY_BRANCH_CODE | B10: Pilar III | C10: Bens Imóveis - Input | D10: 2. Campo | E10: ENERGY_CERTIFICATE_EST_INPUT | F10: PROPERTY_BRANCH_CODE | G10: =VLOOKUP(A10,Plano_V3!$A$26:$G$753,7,0) -> 6. Em implementação (re-especificação) | H10: 4. Validação EF | J10: =IF(VLOOKUP(A10,'Aux - pivots1'!$A:$E,3,0)=0, "",VLOOKUP(A10,'Aux - pivots1'!$A:$E,3,0)) | K10: =IF(VLOOKUP(A10,'Aux - pivots1'!$A:$E,4,0)=0, "",VLOOKUP(A10,'Aux - pivots1'!$A:$E,4,0)) | L10: =IF(VLOOKUP(A10,'Aux - pivots1'!$A:$E,5,0)=0, "",VLOOKUP(A10,'Aux - pivots1'!$A:$E,5,0)) | O10: Bens Imóveis
A11: =E11&F11 -> ENERGY_CERTIFICATE_EST_INPUTPROPERTY_CONTRACT_ID | B11: Pilar III | C11: Bens Imóveis - Input | D11: 2. Campo | E11: ENERGY_CERTIFICATE_EST_INPUT | F11: PROPERTY_CONTRACT_ID | G11: =VLOOKUP(A11,Plano_V3!$A$26:$G$753,7,0) -> 6. Em implementação (re-especificação) | H11: 4. Validação EF | J11: =IF(VLOOKUP(A11,'Aux - pivots1'!$A:$E,3,0)=0, "",VLOOKUP(A11,'Aux - pivots1'!$A:$E,3,0)) | K11: =IF(VLOOKUP(A11,'Aux - pivots1'!$A:$E,4,0)=0, "",VLOOKUP(A11,'Aux - pivots1'!$A:$E,4,0)) | L11: =IF(VLOOKUP(A11,'Aux - pivots1'!$A:$E,5,0)=0, "",VLOOKUP(A11,'Aux - pivots1'!$A:$E,5,0)) | O11: Bens Imóveis
A12: =E12&F12 -> ENERGY_CERTIFICATE_EST_INPUTPROPERTY_REFERENCE_CODE | B12: Pilar III | C12: Bens Imóveis - Input | D12: 2. Campo | E12: ENERGY_CERTIFICATE_EST_INPUT | F12: PROPERTY_REFERENCE_CODE | G12: =VLOOKUP(A12,Plano_V3!$A$26:$G$753,7,0) -> 6. Em implementação (re-especificação) | H12: 4. Validação EF | J12: =IF(VLOOKUP(A12,'Aux - pivots1'!$A:$E,3,0)=0, "",VLOOKUP(A12,'Aux - pivots1'!$A:$E,3,0)) | K12: =IF(VLOOKUP(A12,'Aux - pivots1'!$A:$E,4,0)=0, "",VLOOKUP(A12,'Aux - pivots1'!$A:$E,4,0)) | L12: =IF(VLOOKUP(A12,'Aux - pivots1'!$A:$E,5,0)=0, "",VLOOKUP(A12,'Aux - pivots1'!$A:$E,5,0)) | O12: Bens Imóveis
A13: =E13&F13 -> ENERGY_CERTIFICATE_EST_INPUTCÓDIGO_DISTRITO | B13: Pilar III | C13: Bens Imóveis - Input | D13: 2. Campo | E13: ENERGY_CERTIFICATE_EST_INPUT | F13: CÓDIGO_DISTRITO | G13: =VLOOKUP(A13,Plano_V3!$A$26:$G$753,7,0) -> 6. Em implementação (re-especificação) | H13: 4. Validação EF | J13: =IF(VLOOKUP(A13,'Aux - pivots1'!$A:$E,3,0)=0, "",VLOOKUP(A13,'Aux - pivots1'!$A:$E,3,0)) | K13: =IF(VLOOKUP(A13,'Aux - pivots1'!$A:$E,4,0)=0, "",VLOOKUP(A13,'Aux - pivots1'!$A:$E,4,0)) | L13: =IF(VLOOKUP(A13,'Aux - pivots1'!$A:$E,5,0)=0, "",VLOOKUP(A13,'Aux - pivots1'!$A:$E,5,0)) | O13: Bens Imóveis
A14: =E14&F14 -> ENERGY_CERTIFICATE_EST_INPUTNOMBRE_DISTRITO | B14: Pilar III | C14: Bens Imóveis - Input | D14: 2. Campo | E14: ENERGY_CERTIFICATE_EST_INPUT | F14: NOMBRE_DISTRITO | G14: =VLOOKUP(A14,Plano_V3!$A$26:$G$753,7,0) -> 6. Em implementação (re-especificação) | H14: 4. Validação EF | J14: =IF(VLOOKUP(A14,'Aux - pivots1'!$A:$E,3,0)=0, "",VLOOKUP(A14,'Aux - pivots1'!$A:$E,3,0)) | K14: =IF(VLOOKUP(A14,'Aux - pivots1'!$A:$E,4,0)=0, "",VLOOKUP(A14,'Aux - pivots1'!$A:$E,4,0)) | L14: =IF(VLOOKUP(A14,'Aux - pivots1'!$A:$E,5,0)=0, "",VLOOKUP(A14,'Aux - pivots1'!$A:$E,5,0)) | O14: Bens Imóveis
A15: =E15&F15 -> ENERGY_CERTIFICATE_EST_INPUTCÓDIGO_CONCEJO | B15: Pilar III | C15: Bens Imóveis - Input | D15: 2. Campo | E15: ENERGY_CERTIFICATE_EST_INPUT | F15: CÓDIGO_CONCEJO | G15: =VLOOKUP(A15,Plano_V3!$A$26:$G$753,7,0) -> 6. Em implementação (re-especificação) | H15: 4. Validação EF | J15: =IF(VLOOKUP(A15,'Aux - pivots1'!$A:$E,3,0)=0, "",VLOOKUP(A15,'Aux - pivots1'!$A:$E,3,0)) | K15: =IF(VLOOKUP(A15,'Aux - pivots1'!$A:$E,4,0)=0, "",VLOOKUP(A15,'Aux - pivots1'!$A:$E,4,0)) | L15: =IF(VLOOKUP(A15,'Aux - pivots1'!$A:$E,5,0)=0, "",VLOOKUP(A15,'Aux - pivots1'!$A:$E,5,0)) | O15: Bens Imóveis
A16: =E16&F16 -> ENERGY_CERTIFICATE_EST_INPUTNOMBRE_CONCEJO | B16: Pilar III | C16: Bens Imóveis - Input | D16: 2. Campo | E16: ENERGY_CERTIFICATE_EST_INPUT | F16: NOMBRE_CONCEJO | G16: =VLOOKUP(A16,Plano_V3!$A$26:$G$753,7,0) -> 6. Em implementação (re-especificação) | H16: 4. Validação EF | J16: =IF(VLOOKUP(A16,'Aux - pivots1'!$A:$E,3,0)=0, "",VLOOKUP(A16,'Aux - pivots1'!$A:$E,3,0)) | K16: =IF(VLOOKUP(A16,'Aux - pivots1'!$A:$E,4,0)=0, "",VLOOKUP(A16,'Aux - pivots1'!$A:$E,4,0)) | L16: =IF(VLOOKUP(A16,'Aux - pivots1'!$A:$E,5,0)=0, "",VLOOKUP(A16,'Aux - pivots1'!$A:$E,5,0)) | O16: Bens Imóveis
A17: =E17&F17 -> ENERGY_CERTIFICATE_EST_INPUTCÓDIGO_FREGUESIA | B17: Pilar III | C17: Bens Imóveis - Input | D17: 2. Campo | E17: ENERGY_CERTIFICATE_EST_INPUT | F17: CÓDIGO_FREGUESIA | G17: =VLOOKUP(A17,Plano_V3!$A$26:$G$753,7,0) -> 6. Em implementação (re-especificação) | H17: 4. Validação EF | J17: =IF(VLOOKUP(A17,'Aux - pivots1'!$A:$E,3,0)=0, "",VLOOKUP(A17,'Aux - pivots1'!$A:$E,3,0)) | K17: =IF(VLOOKUP(A17,'Aux - pivots1'!$A:$E,4,0)=0, "",VLOOKUP(A17,'Aux - pivots1'!$A:$E,4,0)) | L17: =IF(VLOOKUP(A17,'Aux - pivots1'!$A:$E,5,0)=0, "",VLOOKUP(A17,'Aux - pivots1'!$A:$E,5,0)) | O17: Bens Imóveis
A18: =E18&F18 -> ENERGY_CERTIFICATE_EST_INPUTNOMBRE_FREGUESIA | B18: Pilar III | C18: Bens Imóveis - Input | D18: 2. Campo | E18: ENERGY_CERTIFICATE_EST_INPUT | F18: NOMBRE_FREGUESIA | G18: =VLOOKUP(A18,Plano_V3!$A$26:$G$753,7,0) -> 6. Em implementação (re-especificação) | H18: 4. Validação EF | J18: =IF(VLOOKUP(A18,'Aux - pivots1'!$A:$E,3,0)=0, "",VLOOKUP(A18,'Aux - pivots1'!$A:$E,3,0)) | K18: =IF(VLOOKUP(A18,'Aux - pivots1'!$A:$E,4,0)=0, "",VLOOKUP(A18,'Aux - pivots1'!$A:$E,4,0)) | L18: =IF(VLOOKUP(A18,'Aux - pivots1'!$A:$E,5,0)=0, "",VLOOKUP(A18,'Aux - pivots1'!$A:$E,5,0)) | O18: Bens Imóveis
A19: =E19&F19 -> ENERGY_CERTIFICATE_EST_INPUTLOCALIDADE | B19: Pilar III | C19: Bens Imóveis - Input | D19: 2. Campo | E19: ENERGY_CERTIFICATE_EST_INPUT | F19: LOCALIDADE | G19: =VLOOKUP(A19,Plano_V3!$A$26:$G$753,7,0) -> 6. Em implementação (re-especificação) | J19: =IF(VLOOKUP(A19,'Aux - pivots1'!$A:$E,3,0)=0, "",VLOOKUP(A19,'Aux - pivots1'!$A:$E,3,0)) | K19: =IF(VLOOKUP(A19,'Aux - pivots1'!$A:$E,4,0)=0, "",VLOOKUP(A19,'Aux - pivots1'!$A:$E,4,0)) | L19: =IF(VLOOKUP(A19,'Aux - pivots1'!$A:$E,5,0)=0, "",VLOOKUP(A19,'Aux - pivots1'!$A:$E,5,0)) | O19: Bens Imóveis
A20: =E20&F20 -> ENERGY_CERTIFICATE_EST_INPUTTIPO_VIA | B20: Pilar III | C20: Bens Imóveis - Input | D20: 2. Campo | E20: ENERGY_CERTIFICATE_EST_INPUT | F20: TIPO_VIA | G20: =VLOOKUP(A20,Plano_V3!$A$26:$G$753,7,0) -> 6. Em implementação (re-especificação) | J20: =IF(VLOOKUP(A20,'Aux - pivots1'!$A:$E,3,0)=0, "",VLOOKUP(A20,'Aux - pivots1'!$A:$E,3,0)) | K20: =IF(VLOOKUP(A20,'Aux - pivots1'!$A:$E,4,0)=0, "",VLOOKUP(A20,'Aux - pivots1'!$A:$E,4,0)) | L20: =IF(VLOOKUP(A20,'Aux - pivots1'!$A:$E,5,0)=0, "",VLOOKUP(A20,'Aux - pivots1'!$A:$E,5,0)) | O20: Bens Imóveis
A21: =E21&F21 -> ENERGY_CERTIFICATE_EST_INPUTNOMBRE_TIPO_VIA | B21: Pilar III | C21: Bens Imóveis - Input | D21: 2. Campo | E21: ENERGY_CERTIFICATE_EST_INPUT | F21: NOMBRE_TIPO_VIA | G21: =VLOOKUP(A21,Plano_V3!$A$26:$G$753,7,0) -> 6. Em implementação (re-especificação) | J21: =IF(VLOOKUP(A21,'Aux - pivots1'!$A:$E,3,0)=0, "",VLOOKUP(A21,'Aux - pivots1'!$A:$E,3,0)) | K21: =IF(VLOOKUP(A21,'Aux - pivots1'!$A:$E,4,0)=0, "",VLOOKUP(A21,'Aux - pivots1'!$A:$E,4,0)) | L21: =IF(VLOOKUP(A21,'Aux - pivots1'!$A:$E,5,0)=0, "",VLOOKUP(A21,'Aux - pivots1'!$A:$E,5,0)) | O21: Bens Imóveis
A22: =E22&F22 -> ENERGY_CERTIFICATE_EST_INPUTNOMBRE_VIA | B22: Pilar III | C22: Bens Imóveis - Input | D22: 2. Campo | E22: ENERGY_CERTIFICATE_EST_INPUT | F22: NOMBRE_VIA | G22: =VLOOKUP(A22,Plano_V3!$A$26:$G$753,7,0) -> 6. Em implementação (re-especificação) | J22: =IF(VLOOKUP(A22,'Aux - pivots1'!$A:$E,3,0)=0, "",VLOOKUP(A22,'Aux - pivots1'!$A:$E,3,0)) | K22: =IF(VLOOKUP(A22,'Aux - pivots1'!$A:$E,4,0)=0, "",VLOOKUP(A22,'Aux - pivots1'!$A:$E,4,0)) | L22: =IF(VLOOKUP(A22,'Aux - pivots1'!$A:$E,5,0)=0, "",VLOOKUP(A22,'Aux - pivots1'!$A:$E,5,0)) | O22: Bens Imóveis
A23: =E23&F23 -> ENERGY_CERTIFICATE_EST_INPUTNUMERO_VIA | B23: Pilar III | C23: Bens Imóveis - Input | D23: 2. Campo | E23: ENERGY_CERTIFICATE_EST_INPUT | F23: NUMERO_VIA | G23: =VLOOKUP(A23,Plano_V3!$A$26:$G$753,7,0) -> 6. Em implementação (re-especificação) | J23: =IF(VLOOKUP(A23,'Aux - pivots1'!$A:$E,3,0)=0, "",VLOOKUP(A23,'Aux - pivots1'!$A:$E,3,0)) | K23: =IF(VLOOKUP(A23,'Aux - pivots1'!$A:$E,4,0)=0, "",VLOOKUP(A23,'Aux - pivots1'!$A:$E,4,0)) | L23: =IF(VLOOKUP(A23,'Aux - pivots1'!$A:$E,5,0)=0, "",VLOOKUP(A23,'Aux - pivots1'!$A:$E,5,0)) | O23: Bens Imóveis
A24: =E24&F24 -> ENERGY_CERTIFICATE_EST_INPUTLOTE | B24: Pilar III | C24: Bens Imóveis - Input | D24: 2. Campo | E24: ENERGY_CERTIFICATE_EST_INPUT | F24: LOTE | G24: =VLOOKUP(A24,Plano_V3!$A$26:$G$753,7,0) -> 6. Em implementação (re-especificação) | J24: =IF(VLOOKUP(A24,'Aux - pivots1'!$A:$E,3,0)=0, "",VLOOKUP(A24,'Aux - pivots1'!$A:$E,3,0)) | K24: =IF(VLOOKUP(A24,'Aux - pivots1'!$A:$E,4,0)=0, "",VLOOKUP(A24,'Aux - pivots1'!$A:$E,4,0)) | L24: =IF(VLOOKUP(A24,'Aux - pivots1'!$A:$E,5,0)=0, "",VLOOKUP(A24,'Aux - pivots1'!$A:$E,5,0)) | O24: Bens Imóveis
A25: =E25&F25 -> ENERGY_CERTIFICATE_EST_INPUTURBANIZACION | B25: Pilar III | C25: Bens Imóveis - Input | D25: 2. Campo | E25: ENERGY_CERTIFICATE_EST_INPUT | F25: URBANIZACION | G25: =VLOOKUP(A25,Plano_V3!$A$26:$G$753,7,0) -> 6. Em implementação (re-especificação) | J25: =IF(VLOOKUP(A25,'Aux - pivots1'!$A:$E,3,0)=0, "",VLOOKUP(A25,'Aux - pivots1'!$A:$E,3,0)) | K25: =IF(VLOOKUP(A25,'Aux - pivots1'!$A:$E,4,0)=0, "",VLOOKUP(A25,'Aux - pivots1'!$A:$E,4,0)) | L25: =IF(VLOOKUP(A25,'Aux - pivots1'!$A:$E,5,0)=0, "",VLOOKUP(A25,'Aux - pivots1'!$A:$E,5,0)) | O25: Bens Imóveis
A26: =E26&F26 -> ENERGY_CERTIFICATE_EST_INPUTCAGLURB | B26: Pilar III | C26: Bens Imóveis - Input | D26: 2. Campo | E26: ENERGY_CERTIFICATE_EST_INPUT | F26: CAGLURB | G26: =VLOOKUP(A26,Plano_V3!$A$26:$G$753,7,0) -> 6. Em implementação (re-especificação) | J26: =IF(VLOOKUP(A26,'Aux - pivots1'!$A:$E,3,0)=0, "",VLOOKUP(A26,'Aux - pivots1'!$A:$E,3,0)) | K26: =IF(VLOOKUP(A26,'Aux - pivots1'!$A:$E,4,0)=0, "",VLOOKUP(A26,'Aux - pivots1'!$A:$E,4,0)) | L26: =IF(VLOOKUP(A26,'Aux - pivots1'!$A:$E,5,0)=0, "",VLOOKUP(A26,'Aux - pivots1'!$A:$E,5,0)) | O26: Bens Imóveis
A27: =E27&F27 -> ENERGY_CERTIFICATE_EST_INPUTRESTO_DIRECCION | B27: Pilar III | C27: Bens Imóveis - Input | D27: 2. Campo | E27: ENERGY_CERTIFICATE_EST_INPUT | F27: RESTO_DIRECCION | G27: =VLOOKUP(A27,Plano_V3!$A$26:$G$753,7,0) -> 6. Em implementação (re-especificação) | J27: =IF(VLOOKUP(A27,'Aux - pivots1'!$A:$E,3,0)=0, "",VLOOKUP(A27,'Aux - pivots1'!$A:$E,3,0)) | K27: =IF(VLOOKUP(A27,'Aux - pivots1'!$A:$E,4,0)=0, "",VLOOKUP(A27,'Aux - pivots1'!$A:$E,4,0)) | L27: =IF(VLOOKUP(A27,'Aux - pivots1'!$A:$E,5,0)=0, "",VLOOKUP(A27,'Aux - pivots1'!$A:$E,5,0)) | O27: Bens Imóveis
A28: =E28&F28 -> ENERGY_CERTIFICATE_EST_INPUTLATITUDE | B28: Pilar III | C28: Bens Imóveis - Input | D28: 2. Campo | E28: ENERGY_CERTIFICATE_EST_INPUT | F28: LATITUDE | G28: =VLOOKUP(A28,Plano_V3!$A$26:$G$753,7,0) -> 6. Em implementação (re-especificação) | J28: =IF(VLOOKUP(A28,'Aux - pivots1'!$A:$E,3,0)=0, "",VLOOKUP(A28,'Aux - pivots1'!$A:$E,3,0)) | K28: =IF(VLOOKUP(A28,'Aux - pivots1'!$A:$E,4,0)=0, "",VLOOKUP(A28,'Aux - pivots1'!$A:$E,4,0)) | L28: =IF(VLOOKUP(A28,'Aux - pivots1'!$A:$E,5,0)=0, "",VLOOKUP(A28,'Aux - pivots1'!$A:$E,5,0)) | O28: Bens Imóveis
A29: =E29&F29 -> ENERGY_CERTIFICATE_EST_INPUTLONGITUDE | B29: Pilar III | C29: Bens Imóveis - Input | D29: 2. Campo | E29: ENERGY_CERTIFICATE_EST_INPUT | F29: LONGITUDE | G29: =VLOOKUP(A29,Plano_V3!$A$26:$G$753,7,0) -> 6. Em implementação (re-especificação) | J29: =IF(VLOOKUP(A29,'Aux - pivots1'!$A:$E,3,0)=0, "",VLOOKUP(A29,'Aux - pivots1'!$A:$E,3,0)) | K29: =IF(VLOOKUP(A29,'Aux - pivots1'!$A:$E,4,0)=0, "",VLOOKUP(A29,'Aux - pivots1'!$A:$E,4,0)) | L29: =IF(VLOOKUP(A29,'Aux - pivots1'!$A:$E,5,0)=0, "",VLOOKUP(A29,'Aux - pivots1'!$A:$E,5,0)) | O29: Bens Imóveis
A30: =E30&F30 -> ENERGY_CERTIFICATE_EST_INPUTCODIGO_POSTAL | B30: Pilar III | C30: Bens Imóveis - Input | D30: 2. Campo | E30: ENERGY_CERTIFICATE_EST_INPUT | F30: CODIGO_POSTAL | G30: =VLOOKUP(A30,Plano_V3!$A$26:$G$753,7,0) -> 6. Em implementação (re-especificação) | J30: =IF(VLOOKUP(A30,'Aux - pivots1'!$A:$E,3,0)=0, "",VLOOKUP(A30,'Aux - pivots1'!$A:$E,3,0)) | K30: =IF(VLOOKUP(A30,'Aux - pivots1'!$A:$E,4,0)=0, "",VLOOKUP(A30,'Aux - pivots1'!$A:$E,4,0)) | L30: =IF(VLOOKUP(A30,'Aux - pivots1'!$A:$E,5,0)=0, "",VLOOKUP(A30,'Aux - pivots1'!$A:$E,5,0)) | O30: Bens Imóveis
... A51: =E51&F51 -> ENERGY_CERTIFICATE_EST_INPUTDATA_ENVIO | B51: Pilar III | C51: Bens Imóveis - Input | D51: 2. Campo | E51: ENERGY_CERTIFICATE_EST_INPUT | F51: DATA_ENVIO | G51: =VLOOKUP(A51,Plano_V3!$A$26:$G$753,7,0) -> 6. Em implementação (re-especificação) | J51: =IF(VLOOKUP(A51,'Aux - pivots1'!$A:$E,3,0)=0, "",VLOOKUP(A51,'Aux - pivots1'!$A:$E,3,0)) | K51: =IF(VLOOKUP(A51,'Aux - pivots1'!$A:$E,4,0)=0, "",VLOOKUP(A51,'Aux - pivots1'!$A:$E,4,0)) | L51: =IF(VLOOKUP(A51,'Aux - pivots1'!$A:$E,5,0)=0, "",VLOOKUP(A51,'Aux - pivots1'!$A:$E,5,0)) | O51: Bens Imóveis
A52: =E52&F52 -> PROCESSn.a. | B52: Pilar III | C52: Bens Imóveis - Output | D52: 1. Universo | E52: PROCESS | F52: n.a. | G52: =VLOOKUP(A52,Plano_V3!$A$26:$G$753,7,0) -> 1. Concluído | H52: 1. Concluído | J52: =IF(VLOOKUP(A52,'Aux - pivots1'!$A:$E,3,0)=0, "",VLOOKUP(A52,'Aux - pivots1'!$A:$E,3,0)) | K52: =IF(VLOOKUP(A52,'Aux - pivots1'!$A:$E,4,0)=0, "",VLOOKUP(A52,'Aux - pivots1'!$A:$E,4,0)) | L52: =IF(VLOOKUP(A52,'Aux - pivots1'!$A:$E,5,0)=0, "",VLOOKUP(A52,'Aux - pivots1'!$A:$E,5,0)) | O52: Bens Imóveis
A53: =E53&F53 -> PROCESSPROCESS_BANK_ID | B53: Pilar III | C53: Bens Imóveis - Output | D53: 2. Campo | E53: PROCESS | F53: PROCESS_BANK_ID | G53: =VLOOKUP(A53,Plano_V3!$A$26:$G$753,7,0) -> 1. Concluído | H53: 1. Concluído | I53: 26/07/2024: Conclusão de testes ao universo MUG e GP. Adjudicados fora de âmbito deste projeto. | J53: =IF(VLOOKUP(A53,'Aux - pivots1'!$A:$E,3,0)=0, "",VLOOKUP(A53,'Aux - pivots1'!$A:$E,3,0)) | K53: =IF(VLOOKUP(A53,'Aux - pivots1'!$A:$E,4,0)=0, "",VLOOKUP(A53,'Aux - pivots1'!$A:$E,4,0)) | L53: =IF(VLOOKUP(A53,'Aux - pivots1'!$A:$E,5,0)=0, "",VLOOKUP(A53,'Aux - pivots1'!$A:$E,5,0)) | O53: Bens Imóveis
A54: =E54&F54 -> PROCESSPROCESS_BRANCH_CODE | B54: Pilar III | C54: Bens Imóveis - Output | D54: 2. Campo | E54: PROCESS | F54: PROCESS_BRANCH_CODE | G54: =VLOOKUP(A54,Plano_V3!$A$26:$G$753,7,0) -> 1. Concluído | H54: 1. Concluído | I54: 26/07/2024: Conclusão de testes ao universo MUG e GP. Adjudicados fora de âmbito deste projeto. | J54: =IF(VLOOKUP(A54,'Aux - pivots1'!$A:$E,3,0)=0, "",VLOOKUP(A54,'Aux - pivots1'!$A:$E,3,0)) | K54: =IF(VLOOKUP(A54,'Aux - pivots1'!$A:$E,4,0)=0, "",VLOOKUP(A54,'Aux - pivots1'!$A:$E,4,0)) | L54: =IF(VLOOKUP(A54,'Aux - pivots1'!$A:$E,5,0)=0, "",VLOOKUP(A54,'Aux - pivots1'!$A:$E,5,0)) | O54: Bens Imóveis
A55: =E55&F55 -> PROCESSPROCESS_ACCOUNT_ID | B55: Pilar III | C55: Bens Imóveis - Output | D55: 2. Campo | E55: PROCESS | F55: PROCESS_ACCOUNT_ID | G55: =VLOOKUP(A55,Plano_V3!$A$26:$G$753,7,0) -> 1. Concluído | H55: 1. Concluído | I55: 26/07/2024: Conclusão de testes ao universo MUG e GP. Adjudicados fora de âmbito deste projeto. | J55: =IF(VLOOKUP(A55,'Aux - pivots1'!$A:$E,3,0)=0, "",VLOOKUP(A55,'Aux - pivots1'!$A:$E,3,0)) | K55: =IF(VLOOKUP(A55,'Aux - pivots1'!$A:$E,4,0)=0, "",VLOOKUP(A55,'Aux - pivots1'!$A:$E,4,0)) | L55: =IF(VLOOKUP(A55,'Aux - pivots1'!$A:$E,5,0)=0, "",VLOOKUP(A55,'Aux - pivots1'!$A:$E,5,0)) | O55: Bens Imóveis
A56: =E56&F56 -> PROCESScod_estd_prcs | B56: Pilar III | C56: Bens Imóveis - Output | D56: 2. Campo | E56: PROCESS | F56: cod_estd_prcs | G56: =VLOOKUP(A56,Plano_V3!$A$26:$G$753,7,0) -> 0. Cancelado | H56: 0. Cancelado | I56: 19/07/2024: Campo eliminado do Modelo para garantir coerência com MUG | J56: =IF(VLOOKUP(A56,'Aux - pivots1'!$A:$E,3,0)=0, "",VLOOKUP(A56,'Aux - pivots1'!$A:$E,3,0)) | K56: =IF(VLOOKUP(A56,'Aux - pivots1'!$A:$E,4,0)=0, "",VLOOKUP(A56,'Aux - pivots1'!$A:$E,4,0)) | L56: =IF(VLOOKUP(A56,'Aux - pivots1'!$A:$E,5,0)=0, "",VLOOKUP(A56,'Aux - pivots1'!$A:$E,5,0)) | O56: Bens Imóveis
A57: =E57&F57 -> PROCESSGUARANTEE_CODE | B57: Pilar III | C57: Bens Imóveis - Output | D57: 2. Campo | E57: PROCESS | F57: GUARANTEE_CODE | G57: =VLOOKUP(A57,Plano_V3!$A$26:$G$753,7,0) -> 1. Concluído | H57: 1. Concluído | J57: =IF(VLOOKUP(A57,'Aux - pivots1'!$A:$E,3,0)=0, "",VLOOKUP(A57,'Aux - pivots1'!$A:$E,3,0)) | K57: =IF(VLOOKUP(A57,'Aux - pivots1'!$A:$E,4,0)=0, "",VLOOKUP(A57,'Aux - pivots1'!$A:$E,4,0)) | L57: =IF(VLOOKUP(A57,'Aux - pivots1'!$A:$E,5,0)=0, "",VLOOKUP(A57,'Aux - pivots1'!$A:$E,5,0)) | O57: Bens Imóveis
A58: =E58&F58 -> PROCESSCURRENCY_CODE | B58: Pilar III | C58: Bens Imóveis - Output | D58: 2. Campo | E58: PROCESS | F58: CURRENCY_CODE | G58: =VLOOKUP(A58,Plano_V3!$A$26:$G$753,7,0) -> 1. Concluído | H58: 1. Concluído | J58: =IF(VLOOKUP(A58,'Aux - pivots1'!$A:$E,3,0)=0, "",VLOOKUP(A58,'Aux - pivots1'!$A:$E,3,0)) | K58: =IF(VLOOKUP(A58,'Aux - pivots1'!$A:$E,4,0)=0, "",VLOOKUP(A58,'Aux - pivots1'!$A:$E,4,0)) | L58: =IF(VLOOKUP(A58,'Aux - pivots1'!$A:$E,5,0)=0, "",VLOOKUP(A58,'Aux - pivots1'!$A:$E,5,0)) | O58: Bens Imóveis
A59: =E59&F59 -> PROCESSPROCESS_CAMPAIGN_CODE | B59: Pilar III | C59: Bens Imóveis - Output | D59: 2. Campo | E59: PROCESS | F59: PROCESS_CAMPAIGN_CODE | G59: =VLOOKUP(A59,Plano_V3!$A$26:$G$753,7,0) -> 1. Concluído | H59: 1. Concluído | J59: =IF(VLOOKUP(A59,'Aux - pivots1'!$A:$E,3,0)=0, "",VLOOKUP(A59,'Aux - pivots1'!$A:$E,3,0)) | K59: =IF(VLOOKUP(A59,'Aux - pivots1'!$A:$E,4,0)=0, "",VLOOKUP(A59,'Aux - pivots1'!$A:$E,4,0)) | L59: =IF(VLOOKUP(A59,'Aux - pivots1'!$A:$E,5,0)=0, "",VLOOKUP(A59,'Aux - pivots1'!$A:$E,5,0)) | O59: Bens Imóveis
A60: =E60&F60 -> PROCESSPROCESS_PRODUCT_ID | B60: Pilar III | C60: Bens Imóveis - Output | D60: 2. Campo | E60: PROCESS | F60: PROCESS_PRODUCT_ID | G60: =VLOOKUP(A60,Plano_V3!$A$26:$G$753,7,0) -> 1. Concluído | H60: 1. Concluído | J60: =IF(VLOOKUP(A60,'Aux - pivots1'!$A:$E,3,0)=0, "",VLOOKUP(A60,'Aux - pivots1'!$A:$E,3,0)) | K60: =IF(VLOOKUP(A60,'Aux - pivots1'!$A:$E,4,0)=0, "",VLOOKUP(A60,'Aux - pivots1'!$A:$E,4,0)) | L60: =IF(VLOOKUP(A60,'Aux - pivots1'!$A:$E,5,0)=0, "",VLOOKUP(A60,'Aux - pivots1'!$A:$E,5,0)) | O60: Bens Imóveis
A61: =E61&F61 -> PROCESSPROCESS_SUBPRODUCT_ID | B61: Pilar III | C61: Bens Imóveis - Output | D61: 2. Campo | E61: PROCESS | F61: PROCESS_SUBPRODUCT_ID | G61: =VLOOKUP(A61,Plano_V3!$A$26:$G$753,7,0) -> 1. Concluído | H61: 1. Concluído | J61: =IF(VLOOKUP(A61,'Aux - pivots1'!$A:$E,3,0)=0, "",VLOOKUP(A61,'Aux - pivots1'!$A:$E,3,0)) | K61: =IF(VLOOKUP(A61,'Aux - pivots1'!$A:$E,4,0)=0, "",VLOOKUP(A61,'Aux - pivots1'!$A:$E,4,0)) | L61: =IF(VLOOKUP(A61,'Aux - pivots1'!$A:$E,5,0)=0, "",VLOOKUP(A61,'Aux - pivots1'!$A:$E,5,0)) | O61: Bens Imóveis
A62: =E62&F62 -> PROCESSGUARANTEE_TYPE_CODE | B62: Pilar III | C62: Bens Imóveis - Output | D62: 2. Campo | E62: PROCESS | F62: GUARANTEE_TYPE_CODE | G62: =VLOOKUP(A62,Plano_V3!$A$26:$G$753,7,0) -> 1. Concluído | H62: 1. Concluído | J62: =IF(VLOOKUP(A62,'Aux - pivots1'!$A:$E,3,0)=0, "",VLOOKUP(A62,'Aux - pivots1'!$A:$E,3,0)) | K62: =IF(VLOOKUP(A62,'Aux - pivots1'!$A:$E,4,0)=0, "",VLOOKUP(A62,'Aux - pivots1'!$A:$E,4,0)) | L62: =IF(VLOOKUP(A62,'Aux - pivots1'!$A:$E,5,0)=0, "",VLOOKUP(A62,'Aux - pivots1'!$A:$E,5,0)) | O62: Bens Imóveis
A63: =E63&F63 -> PROCESSPROCESS_REFERENCE_CODE | B63: Pilar III | C63: Bens Imóveis - Output | D63: 2. Campo | E63: PROCESS | F63: PROCESS_REFERENCE_CODE | G63: =VLOOKUP(A63,Plano_V3!$A$26:$G$753,7,0) -> 1. Concluído | H63: 1. Concluído | J63: =IF(VLOOKUP(A63,'Aux - pivots1'!$A:$E,3,0)=0, "",VLOOKUP(A63,'Aux - pivots1'!$A:$E,3,0)) | K63: =IF(VLOOKUP(A63,'Aux - pivots1'!$A:$E,4,0)=0, "",VLOOKUP(A63,'Aux - pivots1'!$A:$E,4,0)) | L63: =IF(VLOOKUP(A63,'Aux - pivots1'!$A:$E,5,0)=0, "",VLOOKUP(A63,'Aux - pivots1'!$A:$E,5,0)) | O63: Bens Imóveis
A64: =E64&F64 -> PROCESSPROCESS_START_DATE | B64: Pilar III | C64: Bens Imóveis - Output | D64: 2. Campo | E64: PROCESS | F64: PROCESS_START_DATE | G64: =VLOOKUP(A64,Plano_V3!$A$26:$G$753,7,0) -> 1. Concluído | H64: 1. Concluído | J64: =IF(VLOOKUP(A64,'Aux - pivots1'!$A:$E,3,0)=0, "",VLOOKUP(A64,'Aux - pivots1'!$A:$E,3,0)) | K64: =IF(VLOOKUP(A64,'Aux - pivots1'!$A:$E,4,0)=0, "",VLOOKUP(A64,'Aux - pivots1'!$A:$E,4,0)) | L64: =IF(VLOOKUP(A64,'Aux - pivots1'!$A:$E,5,0)=0, "",VLOOKUP(A64,'Aux - pivots1'!$A:$E,5,0)) | O64: Bens Imóveis
A65: =E65&F65 -> PROCESSPROCESS_DUE_DATE | B65: Pilar III | C65: Bens Imóveis - Output | D65: 2. Campo | E65: PROCESS | F65: PROCESS_DUE_DATE | G65: =VLOOKUP(A65,Plano_V3!$A$26:$G$753,7,0) -> 1. Concluído | H65: 1. Concluído | J65: =IF(VLOOKUP(A65,'Aux - pivots1'!$A:$E,3,0)=0, "",VLOOKUP(A65,'Aux - pivots1'!$A:$E,3,0)) | K65: =IF(VLOOKUP(A65,'Aux - pivots1'!$A:$E,4,0)=0, "",VLOOKUP(A65,'Aux - pivots1'!$A:$E,4,0)) | L65: =IF(VLOOKUP(A65,'Aux - pivots1'!$A:$E,5,0)=0, "",VLOOKUP(A65,'Aux - pivots1'!$A:$E,5,0)) | O65: Bens Imóveis
A66: =E66&F66 -> PROCESSmontante_eur | B66: Pilar III | C66: Bens Imóveis - Output | D66: 2. Campo | E66: PROCESS | F66: montante_eur | G66: =VLOOKUP(A66,Plano_V3!$A$26:$G$753,7,0) -> 0. Cancelado | H66: 0. Cancelado | I66: 19/07/2024: Campo eliminado do Modelo para garantir coerência com MUG | J66: =IF(VLOOKUP(A66,'Aux - pivots1'!$A:$E,3,0)=0, "",VLOOKUP(A66,'Aux - pivots1'!$A:$E,3,0)) | K66: =IF(VLOOKUP(A66,'Aux - pivots1'!$A:$E,4,0)=0, "",VLOOKUP(A66,'Aux - pivots1'!$A:$E,4,0)) | L66: =IF(VLOOKUP(A66,'Aux - pivots1'!$A:$E,5,0)=0, "",VLOOKUP(A66,'Aux - pivots1'!$A:$E,5,0)) | O66: Bens Imóveis
A67: =E67&F67 -> PROCESSmontante_org | B67: Pilar III | C67: Bens Imóveis - Output | D67: 2. Campo | E67: PROCESS | F67: montante_org | G67: =VLOOKUP(A67,Plano_V3!$A$26:$G$753,7,0) -> 0. Cancelado | H67: 0. Cancelado | I67: 19/07/2024: Campo eliminado do Modelo para garantir coerência com MUG | J67: =IF(VLOOKUP(A67,'Aux - pivots1'!$A:$E,3,0)=0, "",VLOOKUP(A67,'Aux - pivots1'!$A:$E,3,0)) | K67: =IF(VLOOKUP(A67,'Aux - pivots1'!$A:$E,4,0)=0, "",VLOOKUP(A67,'Aux - pivots1'!$A:$E,4,0)) | L67: =IF(VLOOKUP(A67,'Aux - pivots1'!$A:$E,5,0)=0, "",VLOOKUP(A67,'Aux - pivots1'!$A:$E,5,0)) | O67: Bens Imóveis
A68: =E68&F68 -> PROCESSorigem | B68: Pilar III | C68: Bens Imóveis - Output | D68: 2. Campo | E68: PROCESS | F68: origem | G68: =VLOOKUP(A68,Plano_V3!$A$26:$G$753,7,0) -> 0. Cancelado | H68: 0. Cancelado | I68: 08/08/2024: Campo eliminado de modo a garantir a coerência com o atualmente realizado no Modelo Único de Garantias. | J68: =IF(VLOOKUP(A68,'Aux - pivots1'!$A:$E,3,0)=0, "",VLOOKUP(A68,'Aux - pivots1'!$A:$E,3,0)) | K68: =IF(VLOOKUP(A68,'Aux - pivots1'!$A:$E,4,0)=0, "",VLOOKUP(A68,'Aux - pivots1'!$A:$E,4,0)) | L68: =IF(VLOOKUP(A68,'Aux - pivots1'!$A:$E,5,0)=0, "",VLOOKUP(A68,'Aux - pivots1'!$A:$E,5,0)) | O68: Bens Imóveis
A69: =E69&F69 -> PROCESSDATA_DATE_PART | B69: Pilar III | C69: Bens Imóveis - Output | D69: 2. Campo | E69: PROCESS | F69: DATA_DATE_PART | G69: =VLOOKUP(A69,Plano_V3!$A$26:$G$753,7,0) -> 1. Concluído | H69: 1. Concluído | J69: =IF(VLOOKUP(A69,'Aux - pivots1'!$A:$E,3,0)=0, "",VLOOKUP(A69,'Aux - pivots1'!$A:$E,3,0)) | K69: =IF(VLOOKUP(A69,'Aux - pivots1'!$A:$E,4,0)=0, "",VLOOKUP(A69,'Aux - pivots1'!$A:$E,4,0)) | L69: =IF(VLOOKUP(A69,'Aux - pivots1'!$A:$E,5,0)=0, "",VLOOKUP(A69,'Aux - pivots1'!$A:$E,5,0)) | O69: Bens Imóveis
A70: =E70&F70 -> RESPONSIBILITY_PROCESS_RELn.a. | B70: Pilar III | C70: Bens Imóveis - Output | D70: 1. Universo | E70: RESPONSIBILITY_PROCESS_REL | F70: n.a. | G70: =VLOOKUP(A70,Plano_V3!$A$26:$G$753,7,0) -> 1. Concluído | H70: 1. Concluído | J70: =IF(VLOOKUP(A70,'Aux - pivots1'!$A:$E,3,0)=0, "",VLOOKUP(A70,'Aux - pivots1'!$A:$E,3,0)) | K70: =IF(VLOOKUP(A70,'Aux - pivots1'!$A:$E,4,0)=0, "",VLOOKUP(A70,'Aux - pivots1'!$A:$E,4,0)) | L70: =IF(VLOOKUP(A70,'Aux - pivots1'!$A:$E,5,0)=0, "",VLOOKUP(A70,'Aux - pivots1'!$A:$E,5,0)) | O70: Bens Imóveis
A71: =E71&F71 -> RESPONSIBILITY_PROCESS_RELPROCESS_BANK_ID | B71: Pilar III | C71: Bens Imóveis - Output | D71: 2. Campo | E71: RESPONSIBILITY_PROCESS_REL | F71: PROCESS_BANK_ID | G71: =VLOOKUP(A71,Plano_V3!$A$26:$G$753,7,0) -> 1. Concluído | H71: 1. Concluído | I71: 26/07/2024: Conclusão de testes ao universo MUG e GP. Adjudicados fora de âmbito deste projeto. | J71: =IF(VLOOKUP(A71,'Aux - pivots1'!$A:$E,3,0)=0, "",VLOOKUP(A71,'Aux - pivots1'!$A:$E,3,0)) | K71: =IF(VLOOKUP(A71,'Aux - pivots1'!$A:$E,4,0)=0, "",VLOOKUP(A71,'Aux - pivots1'!$A:$E,4,0)) | L71: =IF(VLOOKUP(A71,'Aux - pivots1'!$A:$E,5,0)=0, "",VLOOKUP(A71,'Aux - pivots1'!$A:$E,5,0)) | O71: Bens Imóveis
A72: =E72&F72 -> RESPONSIBILITY_PROCESS_RELBANK_ID | B72: Pilar III | C72: Bens Imóveis - Output | D72: 2. Campo | E72: RESPONSIBILITY_PROCESS_REL | F72: BANK_ID | G72: =VLOOKUP(A72,Plano_V3!$A$26:$G$753,7,0) -> 1. Concluído | H72: 1. Concluído | I72: 26/07/2024: Conclusão de testes ao universo MUG e GP. Adjudicados fora de âmbito deste projeto. | J72: =IF(VLOOKUP(A72,'Aux - pivots1'!$A:$E,3,0)=0, "",VLOOKUP(A72,'Aux - pivots1'!$A:$E,3,0)) | K72: =IF(VLOOKUP(A72,'Aux - pivots1'!$A:$E,4,0)=0, "",VLOOKUP(A72,'Aux - pivots1'!$A:$E,4,0)) | L72: =IF(VLOOKUP(A72,'Aux - pivots1'!$A:$E,5,0)=0, "",VLOOKUP(A72,'Aux - pivots1'!$A:$E,5,0)) | O72: Bens Imóveis
A73: =E73&F73 -> RESPONSIBILITY_PROCESS_RELPROCESS_BRANCH_CODE | B73: Pilar III | C73: Bens Imóveis - Output | D73: 2. Campo | E73: RESPONSIBILITY_PROCESS_REL | F73: PROCESS_BRANCH_CODE | G73: =VLOOKUP(A73,Plano_V3!$A$26:$G$753,7,0) -> 1. Concluído | H73: 1. Concluído | I73: 26/07/2024: Conclusão de testes ao universo MUG e GP. Adjudicados fora de âmbito deste projeto. | J73: =IF(VLOOKUP(A73,'Aux - pivots1'!$A:$E,3,0)=0, "",VLOOKUP(A73,'Aux - pivots1'!$A:$E,3,0)) | K73: =IF(VLOOKUP(A73,'Aux - pivots1'!$A:$E,4,0)=0, "",VLOOKUP(A73,'Aux - pivots1'!$A:$E,4,0)) | L73: =IF(VLOOKUP(A73,'Aux - pivots1'!$A:$E,5,0)=0, "",VLOOKUP(A73,'Aux - pivots1'!$A:$E,5,0)) | O73: Bens Imóveis
A74: =E74&F74 -> RESPONSIBILITY_PROCESS_RELBRANCH_CODE | B74: Pilar III | C74: Bens Imóveis - Output | D74: 2. Campo | E74: RESPONSIBILITY_PROCESS_REL | F74: BRANCH_CODE | G74: =VLOOKUP(A74,Plano_V3!$A$26:$G$753,7,0) -> 1. Concluído | H74: 1. Concluído | I74: 26/07/2024: Conclusão de testes ao universo MUG e GP. Adjudicados fora de âmbito deste projeto. | J74: =IF(VLOOKUP(A74,'Aux - pivots1'!$A:$E,3,0)=0, "",VLOOKUP(A74,'Aux - pivots1'!$A:$E,3,0)) | K74: =IF(VLOOKUP(A74,'Aux - pivots1'!$A:$E,4,0)=0, "",VLOOKUP(A74,'Aux - pivots1'!$A:$E,4,0)) | L74: =IF(VLOOKUP(A74,'Aux - pivots1'!$A:$E,5,0)=0, "",VLOOKUP(A74,'Aux - pivots1'!$A:$E,5,0)) | O74: Bens Imóveis
A75: =E75&F75 -> RESPONSIBILITY_PROCESS_RELCONTRACT_ID | B75: Pilar III | C75: Bens Imóveis - Output | D75: 2. Campo | E75: RESPONSIBILITY_PROCESS_REL | F75: CONTRACT_ID | G75: =VLOOKUP(A75,Plano_V3!$A$26:$G$753,7,0) -> 1. Concluído | H75: 1. Concluído | I75: 26/07/2024: Conclusão de testes ao universo MUG e GP. Adjudicados fora de âmbito deste projeto. | J75: =IF(VLOOKUP(A75,'Aux - pivots1'!$A:$E,3,0)=0, "",VLOOKUP(A75,'Aux - pivots1'!$A:$E,3,0)) | K75: =IF(VLOOKUP(A75,'Aux - pivots1'!$A:$E,4,0)=0, "",VLOOKUP(A75,'Aux - pivots1'!$A:$E,4,0)) | L75: =IF(VLOOKUP(A75,'Aux - pivots1'!$A:$E,5,0)=0, "",VLOOKUP(A75,'Aux - pivots1'!$A:$E,5,0)) | O75: Bens Imóveis
A76: =E76&F76 -> RESPONSIBILITY_PROCESS_RELPROCESS_ACCOUNT_ID | B76: Pilar III | C76: Bens Imóveis - Output | D76: 2. Campo | E76: RESPONSIBILITY_PROCESS_REL | F76: PROCESS_ACCOUNT_ID | G76: =VLOOKUP(A76,Plano_V3!$A$26:$G$753,7,0) -> 1. Concluído | H76: 1. Concluído | I76: 26/07/2024: Conclusão de testes ao universo MUG e GP. Adjudicados fora de âmbito deste projeto. | J76: =IF(VLOOKUP(A76,'Aux - pivots1'!$A:$E,3,0)=0, "",VLOOKUP(A76,'Aux - pivots1'!$A:$E,3,0)) | K76: =IF(VLOOKUP(A76,'Aux - pivots1'!$A:$E,4,0)=0, "",VLOOKUP(A76,'Aux - pivots1'!$A:$E,4,0)) | L76: =IF(VLOOKUP(A76,'Aux - pivots1'!$A:$E,5,0)=0, "",VLOOKUP(A76,'Aux - pivots1'!$A:$E,5,0)) | O76: Bens Imóveis
A77: =E77&F77 -> RESPONSIBILITY_PROCESS_RELREFERENCE_CODE | B77: Pilar III | C77: Bens Imóveis - Output | D77: 2. Campo | E77: RESPONSIBILITY_PROCESS_REL | F77: REFERENCE_CODE | G77: =VLOOKUP(A77,Plano_V3!$A$26:$G$753,7,0) -> 1. Concluído | H77: 1. Concluído | I77: 26/07/2024: Conclusão de testes ao universo MUG e GP. Adjudicados fora de âmbito deste projeto. | J77: =IF(VLOOKUP(A77,'Aux - pivots1'!$A:$E,3,0)=0, "",VLOOKUP(A77,'Aux - pivots1'!$A:$E,3,0)) | K77: =IF(VLOOKUP(A77,'Aux - pivots1'!$A:$E,4,0)=0, "",VLOOKUP(A77,'Aux - pivots1'!$A:$E,4,0)) | L77: =IF(VLOOKUP(A77,'Aux - pivots1'!$A:$E,5,0)=0, "",VLOOKUP(A77,'Aux - pivots1'!$A:$E,5,0)) | O77: Bens Imóveis
A78: =E78&F78 -> RESPONSIBILITY_PROCESS_RELPURPOSE_CODE | B78: Pilar III | C78: Bens Imóveis - Output | D78: 2. Campo | E78: RESPONSIBILITY_PROCESS_REL | F78: PURPOSE_CODE | G78: =VLOOKUP(A78,Plano_V3!$A$26:$G$753,7,0) -> 1. Concluído | H78: 1. Concluído | J78: =IF(VLOOKUP(A78,'Aux - pivots1'!$A:$E,3,0)=0, "",VLOOKUP(A78,'Aux - pivots1'!$A:$E,3,0)) | K78: =IF(VLOOKUP(A78,'Aux - pivots1'!$A:$E,4,0)=0, "",VLOOKUP(A78,'Aux - pivots1'!$A:$E,4,0)) | L78: =IF(VLOOKUP(A78,'Aux - pivots1'!$A:$E,5,0)=0, "",VLOOKUP(A78,'Aux - pivots1'!$A:$E,5,0)) | O78: Bens Imóveis
A79: =E79&F79 -> RESPONSIBILITY_PROCESS_RELINDIVIDUAL_OCCUPATION_CODE | B79: Pilar III | C79: Bens Imóveis - Output | D79: 2. Campo | E79: RESPONSIBILITY_PROCESS_REL | F79: INDIVIDUAL_OCCUPATION_CODE | G79: =VLOOKUP(A79,Plano_V3!$A$26:$G$753,7,0) -> 1. Concluído | H79: 1. Concluído | J79: =IF(VLOOKUP(A79,'Aux - pivots1'!$A:$E,3,0)=0, "",VLOOKUP(A79,'Aux - pivots1'!$A:$E,3,0)) | K79: =IF(VLOOKUP(A79,'Aux - pivots1'!$A:$E,4,0)=0, "",VLOOKUP(A79,'Aux - pivots1'!$A:$E,4,0)) | L79: =IF(VLOOKUP(A79,'Aux - pivots1'!$A:$E,5,0)=0, "",VLOOKUP(A79,'Aux - pivots1'!$A:$E,5,0)) | O79: Bens Imóveis
A80: =E80&F80 -> RESPONSIBILITY_PROCESS_RELPRODUCT_ID | B80: Pilar III | C80: Bens Imóveis - Output | D80: 2. Campo | E80: RESPONSIBILITY_PROCESS_REL | F80: PRODUCT_ID | G80: =VLOOKUP(A80,Plano_V3!$A$26:$G$753,7,0) -> 1. Concluído | H80: 1. Concluído | J80: =IF(VLOOKUP(A80,'Aux - pivots1'!$A:$E,3,0)=0, "",VLOOKUP(A80,'Aux - pivots1'!$A:$E,3,0)) | K80: =IF(VLOOKUP(A80,'Aux - pivots1'!$A:$E,4,0)=0, "",VLOOKUP(A80,'Aux - pivots1'!$A:$E,4,0)) | L80: =IF(VLOOKUP(A80,'Aux - pivots1'!$A:$E,5,0)=0, "",VLOOKUP(A80,'Aux - pivots1'!$A:$E,5,0)) | O80: Bens Imóveis
A81: =E81&F81 -> RESPONSIBILITY_PROCESS_RELcod_sit | B81: Pilar III | C81: Bens Imóveis - Output | D81: 2. Campo | E81: RESPONSIBILITY_PROCESS_REL | F81: cod_sit | G81: =VLOOKUP(A81,Plano_V3!$A$26:$G$753,7,0) -> 0. Cancelado | H81: 0. Cancelado | I81: 19/07/2024: Campo eliminado do Modelo para garantir coerência com MUG | J81: =IF(VLOOKUP(A81,'Aux - pivots1'!$A:$E,3,0)=0, "",VLOOKUP(A81,'Aux - pivots1'!$A:$E,3,0)) | K81: =IF(VLOOKUP(A81,'Aux - pivots1'!$A:$E,4,0)=0, "",VLOOKUP(A81,'Aux - pivots1'!$A:$E,4,0)) | L81: =IF(VLOOKUP(A81,'Aux - pivots1'!$A:$E,5,0)=0, "",VLOOKUP(A81,'Aux - pivots1'!$A:$E,5,0)) | O81: Bens Imóveis
A82: =E82&F82 -> RESPONSIBILITY_PROCESS_RELSUBPRODUCT_ID | B82: Pilar III | C82: Bens Imóveis - Output | D82: 2. Campo | E82: RESPONSIBILITY_PROCESS_REL | F82: SUBPRODUCT_ID | G82: =VLOOKUP(A82,Plano_V3!$A$26:$G$753,7,0) -> 1. Concluído | H82: 1. Concluído | J82: =IF(VLOOKUP(A82,'Aux - pivots1'!$A:$E,3,0)=0, "",VLOOKUP(A82,'Aux - pivots1'!$A:$E,3,0)) | K82: =IF(VLOOKUP(A82,'Aux - pivots1'!$A:$E,4,0)=0, "",VLOOKUP(A82,'Aux - pivots1'!$A:$E,4,0)) | L82: =IF(VLOOKUP(A82,'Aux - pivots1'!$A:$E,5,0)=0, "",VLOOKUP(A82,'Aux - pivots1'!$A:$E,5,0)) | O82: Bens Imóveis
A83: =E83&F83 -> RESPONSIBILITY_PROCESS_RELPROCESS_REFERENCE_CODE | B83: Pilar III | C83: Bens Imóveis - Output | D83: 2. Campo | E83: RESPONSIBILITY_PROCESS_REL | F83: PROCESS_REFERENCE_CODE | G83: =VLOOKUP(A83,Plano_V3!$A$26:$G$753,7,0) -> 1. Concluído | H83: 1. Concluído | J83: =IF(VLOOKUP(A83,'Aux - pivots1'!$A:$E,3,0)=0, "",VLOOKUP(A83,'Aux - pivots1'!$A:$E,3,0)) | K83: =IF(VLOOKUP(A83,'Aux - pivots1'!$A:$E,4,0)=0, "",VLOOKUP(A83,'Aux - pivots1'!$A:$E,4,0)) | L83: =IF(VLOOKUP(A83,'Aux - pivots1'!$A:$E,5,0)=0, "",VLOOKUP(A83,'Aux - pivots1'!$A:$E,5,0)) | O83: Bens Imóveis
A84: =E84&F84 -> RESPONSIBILITY_PROCESS_RELEFFECTIVE_RELATION_END_DATE | B84: Pilar III | C84: Bens Imóveis - Output | D84: 2. Campo | E84: RESPONSIBILITY_PROCESS_REL | F84: EFFECTIVE_RELATION_END_DATE | G84: =VLOOKUP(A84,Plano_V3!$A$26:$G$753,7,0) -> 1. Concluído | H84: 1. Concluído | J84: =IF(VLOOKUP(A84,'Aux - pivots1'!$A:$E,3,0)=0, "",VLOOKUP(A84,'Aux - pivots1'!$A:$E,3,0)) | K84: =IF(VLOOKUP(A84,'Aux - pivots1'!$A:$E,4,0)=0, "",VLOOKUP(A84,'Aux - pivots1'!$A:$E,4,0)) | L84: =IF(VLOOKUP(A84,'Aux - pivots1'!$A:$E,5,0)=0, "",VLOOKUP(A84,'Aux - pivots1'!$A:$E,5,0)) | O84: Bens Imóveis
A85: =E85&F85 -> RESPONSIBILITY_PROCESS_RELPROCESS_START_DATE | B85: Pilar III | C85: Bens Imóveis - Output | D85: 2. Campo | E85: RESPONSIBILITY_PROCESS_REL | F85: PROCESS_START_DATE | G85: =VLOOKUP(A85,Plano_V3!$A$26:$G$753,7,0) -> 1. Concluído | H85: 1. Concluído | J85: =IF(VLOOKUP(A85,'Aux - pivots1'!$A:$E,3,0)=0, "",VLOOKUP(A85,'Aux - pivots1'!$A:$E,3,0)) | K85: =IF(VLOOKUP(A85,'Aux - pivots1'!$A:$E,4,0)=0, "",VLOOKUP(A85,'Aux - pivots1'!$A:$E,4,0)) | L85: =IF(VLOOKUP(A85,'Aux - pivots1'!$A:$E,5,0)=0, "",VLOOKUP(A85,'Aux - pivots1'!$A:$E,5,0)) | O85: Bens Imóveis
A86: =E86&F86 -> RESPONSIBILITY_PROCESS_RELPROCESS_DUE_DATE | B86: Pilar III | C86: Bens Imóveis - Output | D86: 2. Campo | E86: RESPONSIBILITY_PROCESS_REL | F86: PROCESS_DUE_DATE | G86: =VLOOKUP(A86,Plano_V3!$A$26:$G$753,7,0) -> 1. Concluído | H86: 1. Concluído | J86: =IF(VLOOKUP(A86,'Aux - pivots1'!$A:$E,3,0)=0, "",VLOOKUP(A86,'Aux - pivots1'!$A:$E,3,0)) | K86: =IF(VLOOKUP(A86,'Aux - pivots1'!$A:$E,4,0)=0, "",VLOOKUP(A86,'Aux - pivots1'!$A:$E,4,0)) | L86: =IF(VLOOKUP(A86,'Aux - pivots1'!$A:$E,5,0)=0, "",VLOOKUP(A86,'Aux - pivots1'!$A:$E,5,0)) | O86: Bens Imóveis
A87: =E87&F87 -> RESPONSIBILITY_PROCESS_RELidetgar | B87: Pilar III | C87: Bens Imóveis - Output | D87: 2. Campo | E87: RESPONSIBILITY_PROCESS_REL | F87: idetgar | G87: =VLOOKUP(A87,Plano_V3!$A$26:$G$753,7,0) -> 0. Cancelado | H87: 0. Cancelado | I87: 19/07/2024: Campo eliminado do Modelo para garantir coerência com MUG | J87: =IF(VLOOKUP(A87,'Aux - pivots1'!$A:$E,3,0)=0, "",VLOOKUP(A87,'Aux - pivots1'!$A:$E,3,0)) | K87: =IF(VLOOKUP(A87,'Aux - pivots1'!$A:$E,4,0)=0, "",VLOOKUP(A87,'Aux - pivots1'!$A:$E,4,0)) | L87: =IF(VLOOKUP(A87,'Aux - pivots1'!$A:$E,5,0)=0, "",VLOOKUP(A87,'Aux - pivots1'!$A:$E,5,0)) | O87: Bens Imóveis
A88: =E88&F88 -> RESPONSIBILITY_PROCESS_RELnum_prop | B88: Pilar III | C88: Bens Imóveis - Output | D88: 2. Campo | E88: RESPONSIBILITY_PROCESS_REL | F88: num_prop | G88: =VLOOKUP(A88,Plano_V3!$A$26:$G$753,7,0) -> 0. Cancelado | H88: 0. Cancelado | I88: 19/07/2024: Campo eliminado do Modelo para garantir coerência com MUG | J88: =IF(VLOOKUP(A88,'Aux - pivots1'!$A:$E,3,0)=0, "",VLOOKUP(A88,'Aux - pivots1'!$A:$E,3,0)) | K88: =IF(VLOOKUP(A88,'Aux - pivots1'!$A:$E,4,0)=0, "",VLOOKUP(A88,'Aux - pivots1'!$A:$E,4,0)) | L88: =IF(VLOOKUP(A88,'Aux - pivots1'!$A:$E,5,0)=0, "",VLOOKUP(A88,'Aux - pivots1'!$A:$E,5,0)) | O88: Bens Imóveis
A89: =E89&F89 -> RESPONSIBILITY_PROCESS_RELSOURCE_CODE | B89: Pilar III | C89: Bens Imóveis - Output | D89: 2. Campo | E89: RESPONSIBILITY_PROCESS_REL | F89: SOURCE_CODE | G89: =VLOOKUP(A89,Plano_V3!$A$26:$G$753,7,0) -> 1. Concluído | H89: 1. Concluído | J89: =IF(VLOOKUP(A89,'Aux - pivots1'!$A:$E,3,0)=0, "",VLOOKUP(A89,'Aux - pivots1'!$A:$E,3,0)) | K89: =IF(VLOOKUP(A89,'Aux - pivots1'!$A:$E,4,0)=0, "",VLOOKUP(A89,'Aux - pivots1'!$A:$E,4,0)) | L89: =IF(VLOOKUP(A89,'Aux - pivots1'!$A:$E,5,0)=0, "",VLOOKUP(A89,'Aux - pivots1'!$A:$E,5,0)) | O89: Bens Imóveis
A90: =E90&F90 -> RESPONSIBILITY_PROCESS_RELDATA_DATE_PART | B90: Pilar III | C90: Bens Imóveis - Output | D90: 2. Campo | E90: RESPONSIBILITY_PROCESS_REL | F90: DATA_DATE_PART | G90: =VLOOKUP(A90,Plano_V3!$A$26:$G$753,7,0) -> 1. Concluído | H90: 1. Concluído | J90: =IF(VLOOKUP(A90,'Aux - pivots1'!$A:$E,3,0)=0, "",VLOOKUP(A90,'Aux - pivots1'!$A:$E,3,0)) | K90: =IF(VLOOKUP(A90,'Aux - pivots1'!$A:$E,4,0)=0, "",VLOOKUP(A90,'Aux - pivots1'!$A:$E,4,0)) | L90: =IF(VLOOKUP(A90,'Aux - pivots1'!$A:$E,5,0)=0, "",VLOOKUP(A90,'Aux - pivots1'!$A:$E,5,0)) | O90: Bens Imóveis
A91: =E91&F91 -> PROCESS_PROPERTY_RELn.a. | B91: Pilar III | C91: Bens Imóveis - Output | D91: 1. Universo | E91: PROCESS_PROPERTY_REL | F91: n.a. | G91: =VLOOKUP(A91,Plano_V3!$A$26:$G$753,7,0) -> 1. Concluído | H91: 1. Concluído | J91: =IF(VLOOKUP(A91,'Aux - pivots1'!$A:$E,3,0)=0, "",VLOOKUP(A91,'Aux - pivots1'!$A:$E,3,0)) | K91: =IF(VLOOKUP(A91,'Aux - pivots1'!$A:$E,4,0)=0, "",VLOOKUP(A91,'Aux - pivots1'!$A:$E,4,0)) | L91: =IF(VLOOKUP(A91,'Aux - pivots1'!$A:$E,5,0)=0, "",VLOOKUP(A91,'Aux - pivots1'!$A:$E,5,0)) | O91: Bens Imóveis
A92: =E92&F92 -> PROCESS_PROPERTY_RELPROPERTY_BANK_ID | B92: Pilar III | C92: Bens Imóveis - Output | D92: 2. Campo | E92: PROCESS_PROPERTY_REL | F92: PROPERTY_BANK_ID | G92: =VLOOKUP(A92,Plano_V3!$A$26:$G$753,7,0) -> 1. Concluído | H92: 1. Concluído | J92: =IF(VLOOKUP(A92,'Aux - pivots1'!$A:$E,3,0)=0, "",VLOOKUP(A92,'Aux - pivots1'!$A:$E,3,0)) | K92: =IF(VLOOKUP(A92,'Aux - pivots1'!$A:$E,4,0)=0, "",VLOOKUP(A92,'Aux - pivots1'!$A:$E,4,0)) | L92: =IF(VLOOKUP(A92,'Aux - pivots1'!$A:$E,5,0)=0, "",VLOOKUP(A92,'Aux - pivots1'!$A:$E,5,0)) | O92: Bens Imóveis
A93: =E93&F93 -> PROCESS_PROPERTY_RELPROCESS_BANK_ID | B93: Pilar III | C93: Bens Imóveis - Output | D93: 2. Campo | E93: PROCESS_PROPERTY_REL | F93: PROCESS_BANK_ID | G93: =VLOOKUP(A93,Plano_V3!$A$26:$G$753,7,0) -> 1. Concluído | H93: 1. Concluído | I93: 26/07/2024: Conclusão de testes ao universo MUG e GP. Adjudicados fora de âmbito deste projeto. | J93: =IF(VLOOKUP(A93,'Aux - pivots1'!$A:$E,3,0)=0, "",VLOOKUP(A93,'Aux - pivots1'!$A:$E,3,0)) | K93: =IF(VLOOKUP(A93,'Aux - pivots1'!$A:$E,4,0)=0, "",VLOOKUP(A93,'Aux - pivots1'!$A:$E,4,0)) | L93: =IF(VLOOKUP(A93,'Aux - pivots1'!$A:$E,5,0)=0, "",VLOOKUP(A93,'Aux - pivots1'!$A:$E,5,0)) | O93: Bens Imóveis
A94: =E94&F94 -> PROCESS_PROPERTY_RELPROPERTY_BRANCH_CODE | B94: Pilar III | C94: Bens Imóveis - Output | D94: 2. Campo | E94: PROCESS_PROPERTY_REL | F94: PROPERTY_BRANCH_CODE | G94: =VLOOKUP(A94,Plano_V3!$A$26:$G$753,7,0) -> 1. Concluído | H94: 1. Concluído | I94: 26/07/2024: Conclusão de testes ao universo MUG e GP. Adjudicados fora de âmbito deste projeto. | J94: =IF(VLOOKUP(A94,'Aux - pivots1'!$A:$E,3,0)=0, "",VLOOKUP(A94,'Aux - pivots1'!$A:$E,3,0)) | K94: =IF(VLOOKUP(A94,'Aux - pivots1'!$A:$E,4,0)=0, "",VLOOKUP(A94,'Aux - pivots1'!$A:$E,4,0)) | L94: =IF(VLOOKUP(A94,'Aux - pivots1'!$A:$E,5,0)=0, "",VLOOKUP(A94,'Aux - pivots1'!$A:$E,5,0)) | O94: Bens Imóveis
A95: =E95&F95 -> PROCESS_PROPERTY_RELPROCESS_BRANCH_CODE | B95: Pilar III | C95: Bens Imóveis - Output | D95: 2. Campo | E95: PROCESS_PROPERTY_REL | F95: PROCESS_BRANCH_CODE | G95: =VLOOKUP(A95,Plano_V3!$A$26:$G$753,7,0) -> 1. Concluído | H95: 1. Concluído | I95: 26/07/2024: Conclusão de testes ao universo MUG e GP. Adjudicados fora de âmbito deste projeto. | J95: =IF(VLOOKUP(A95,'Aux - pivots1'!$A:$E,3,0)=0, "",VLOOKUP(A95,'Aux - pivots1'!$A:$E,3,0)) | K95: =IF(VLOOKUP(A95,'Aux - pivots1'!$A:$E,4,0)=0, "",VLOOKUP(A95,'Aux - pivots1'!$A:$E,4,0)) | L95: =IF(VLOOKUP(A95,'Aux - pivots1'!$A:$E,5,0)=0, "",VLOOKUP(A95,'Aux - pivots1'!$A:$E,5,0)) | O95: Bens Imóveis
A96: =E96&F96 -> PROCESS_PROPERTY_RELPROPERTY_CONTRACT_ID | B96: Pilar III | C96: Bens Imóveis - Output | D96: 2. Campo | E96: PROCESS_PROPERTY_REL | F96: PROPERTY_CONTRACT_ID | G96: =VLOOKUP(A96,Plano_V3!$A$26:$G$753,7,0) -> 1. Concluído | H96: 1. Concluído | I96: 26/07/2024: Conclusão de testes ao universo MUG e GP. Adjudicados fora de âmbito deste projeto. | J96: =IF(VLOOKUP(A96,'Aux - pivots1'!$A:$E,3,0)=0, "",VLOOKUP(A96,'Aux - pivots1'!$A:$E,3,0)) | K96: =IF(VLOOKUP(A96,'Aux - pivots1'!$A:$E,4,0)=0, "",VLOOKUP(A96,'Aux - pivots1'!$A:$E,4,0)) | L96: =IF(VLOOKUP(A96,'Aux - pivots1'!$A:$E,5,0)=0, "",VLOOKUP(A96,'Aux - pivots1'!$A:$E,5,0)) | O96: Bens Imóveis
A97: =E97&F97 -> PROCESS_PROPERTY_RELPROCESS_ACCOUNT_ID | B97: Pilar III | C97: Bens Imóveis - Output | D97: 2. Campo | E97: PROCESS_PROPERTY_REL | F97: PROCESS_ACCOUNT_ID | G97: =VLOOKUP(A97,Plano_V3!$A$26:$G$753,7,0) -> 1. Concluído | H97: 1. Concluído | I97: 26/07/2024: Conclusão de testes ao universo MUG e GP. Adjudicados fora de âmbito deste projeto. | J97: =IF(VLOOKUP(A97,'Aux - pivots1'!$A:$E,3,0)=0, "",VLOOKUP(A97,'Aux - pivots1'!$A:$E,3,0)) | K97: =IF(VLOOKUP(A97,'Aux - pivots1'!$A:$E,4,0)=0, "",VLOOKUP(A97,'Aux - pivots1'!$A:$E,4,0)) | L97: =IF(VLOOKUP(A97,'Aux - pivots1'!$A:$E,5,0)=0, "",VLOOKUP(A97,'Aux - pivots1'!$A:$E,5,0)) | O97: Bens Imóveis
A98: =E98&F98 -> PROCESS_PROPERTY_RELPROPERTY_REFERENCE_CODE | B98: Pilar III | C98: Bens Imóveis - Output | D98: 2. Campo | E98: PROCESS_PROPERTY_REL | F98: PROPERTY_REFERENCE_CODE | G98: =VLOOKUP(A98,Plano_V3!$A$26:$G$753,7,0) -> 1. Concluído | H98: 1. Concluído | J98: =IF(VLOOKUP(A98,'Aux - pivots1'!$A:$E,3,0)=0, "",VLOOKUP(A98,'Aux - pivots1'!$A:$E,3,0)) | K98: =IF(VLOOKUP(A98,'Aux - pivots1'!$A:$E,4,0)=0, "",VLOOKUP(A98,'Aux - pivots1'!$A:$E,4,0)) | L98: =IF(VLOOKUP(A98,'Aux - pivots1'!$A:$E,5,0)=0, "",VLOOKUP(A98,'Aux - pivots1'!$A:$E,5,0)) | O98: Bens Imóveis
A99: =E99&F99 -> PROCESS_PROPERTY_RELPROCESS_REFERENCE_CODE | B99: Pilar III | C99: Bens Imóveis - Output | D99: 2. Campo | E99: PROCESS_PROPERTY_REL | F99: PROCESS_REFERENCE_CODE | G99: =VLOOKUP(A99,Plano_V3!$A$26:$G$753,7,0) -> 1. Concluído | H99: 1. Concluído | J99: =IF(VLOOKUP(A99,'Aux - pivots1'!$A:$E,3,0)=0, "",VLOOKUP(A99,'Aux - pivots1'!$A:$E,3,0)) | K99: =IF(VLOOKUP(A99,'Aux - pivots1'!$A:$E,4,0)=0, "",VLOOKUP(A99,'Aux - pivots1'!$A:$E,4,0)) | L99: =IF(VLOOKUP(A99,'Aux - pivots1'!$A:$E,5,0)=0, "",VLOOKUP(A99,'Aux - pivots1'!$A:$E,5,0)) | O99: Bens Imóveis
A100: =E100&F100 -> PROCESS_PROPERTY_RELdata_assc | B100: Pilar III | C100: Bens Imóveis - Output | D100: 2. Campo | E100: PROCESS_PROPERTY_REL | F100: data_assc | G100: =VLOOKUP(A100,Plano_V3!$A$26:$G$753,7,0) -> 0. Cancelado | H100: 0. Cancelado | I100: 19/07/2024: Campo eliminado do Modelo para garantir coerência com MUG | J100: =IF(VLOOKUP(A100,'Aux - pivots1'!$A:$E,3,0)=0, "",VLOOKUP(A100,'Aux - pivots1'!$A:$E,3,0)) | K100: =IF(VLOOKUP(A100,'Aux - pivots1'!$A:$E,4,0)=0, "",VLOOKUP(A100,'Aux - pivots1'!$A:$E,4,0)) | L100: =IF(VLOOKUP(A100,'Aux - pivots1'!$A:$E,5,0)=0, "",VLOOKUP(A100,'Aux - pivots1'!$A:$E,5,0)) | O100: Bens Imóveis
A101: =E101&F101 -> PROCESS_PROPERTY_RELSEIZED_PROPERTY_IND | B101: Pilar III | C101: Bens Imóveis - Output | D101: 2. Campo | E101: PROCESS_PROPERTY_REL | F101: SEIZED_PROPERTY_IND | G101: =VLOOKUP(A101,Plano_V3!$A$26:$G$753,7,0) -> 1. Concluído | H101: 1. Concluído | J101: =IF(VLOOKUP(A101,'Aux - pivots1'!$A:$E,3,0)=0, "",VLOOKUP(A101,'Aux - pivots1'!$A:$E,3,0)) | K101: =IF(VLOOKUP(A101,'Aux - pivots1'!$A:$E,4,0)=0, "",VLOOKUP(A101,'Aux - pivots1'!$A:$E,4,0)) | L101: =IF(VLOOKUP(A101,'Aux - pivots1'!$A:$E,5,0)=0, "",VLOOKUP(A101,'Aux - pivots1'!$A:$E,5,0)) | O101: Bens Imóveis
A102: =E102&F102 -> PROCESS_PROPERTY_RELCOLLATERAL_PROPERTY_IND | B102: Pilar III | C102: Bens Imóveis - Output | D102: 2. Campo | E102: PROCESS_PROPERTY_REL | F102: COLLATERAL_PROPERTY_IND | G102: =VLOOKUP(A102,Plano_V3!$A$26:$G$753,7,0) -> 1. Concluído | H102: 1. Concluído | J102: =IF(VLOOKUP(A102,'Aux - pivots1'!$A:$E,3,0)=0, "",VLOOKUP(A102,'Aux - pivots1'!$A:$E,3,0)) | K102: =IF(VLOOKUP(A102,'Aux - pivots1'!$A:$E,4,0)=0, "",VLOOKUP(A102,'Aux - pivots1'!$A:$E,4,0)) | L102: =IF(VLOOKUP(A102,'Aux - pivots1'!$A:$E,5,0)=0, "",VLOOKUP(A102,'Aux - pivots1'!$A:$E,5,0)) | O102: Bens Imóveis
A103: =E103&F103 -> PROCESS_PROPERTY_RELFINANCED_PROPERTY_IND | B103: Pilar III | C103: Bens Imóveis - Output | D103: 2. Campo | E103: PROCESS_PROPERTY_REL | F103: FINANCED_PROPERTY_IND | G103: =VLOOKUP(A103,Plano_V3!$A$26:$G$753,7,0) -> 1. Concluído | H103: 1. Concluído | J103: =IF(VLOOKUP(A103,'Aux - pivots1'!$A:$E,3,0)=0, "",VLOOKUP(A103,'Aux - pivots1'!$A:$E,3,0)) | K103: =IF(VLOOKUP(A103,'Aux - pivots1'!$A:$E,4,0)=0, "",VLOOKUP(A103,'Aux - pivots1'!$A:$E,4,0)) | L103: =IF(VLOOKUP(A103,'Aux - pivots1'!$A:$E,5,0)=0, "",VLOOKUP(A103,'Aux - pivots1'!$A:$E,5,0)) | O103: Bens Imóveis
A104: =E104&F104 -> PROCESS_PROPERTY_RELOWNED_PROPERTY_IND | B104: Pilar III | C104: Bens Imóveis - Output | D104: 2. Campo | E104: PROCESS_PROPERTY_REL | F104: OWNED_PROPERTY_IND | G104: =VLOOKUP(A104,Plano_V3!$A$26:$G$753,7,0) -> 1. Concluído | H104: 1. Concluído | J104: =IF(VLOOKUP(A104,'Aux - pivots1'!$A:$E,3,0)=0, "",VLOOKUP(A104,'Aux - pivots1'!$A:$E,3,0)) | K104: =IF(VLOOKUP(A104,'Aux - pivots1'!$A:$E,4,0)=0, "",VLOOKUP(A104,'Aux - pivots1'!$A:$E,4,0)) | L104: =IF(VLOOKUP(A104,'Aux - pivots1'!$A:$E,5,0)=0, "",VLOOKUP(A104,'Aux - pivots1'!$A:$E,5,0)) | O104: Bens Imóveis
A105: =E105&F105 -> PROCESS_PROPERTY_RELSOURCE_CODE | B105: Pilar III | C105: Bens Imóveis - Output | D105: 2. Campo | E105: PROCESS_PROPERTY_REL | F105: SOURCE_CODE | G105: =VLOOKUP(A105,Plano_V3!$A$26:$G$753,7,0) -> 1. Concluído | H105: 1. Concluído | J105: =IF(VLOOKUP(A105,'Aux - pivots1'!$A:$E,3,0)=0, "",VLOOKUP(A105,'Aux - pivots1'!$A:$E,3,0)) | K105: =IF(VLOOKUP(A105,'Aux - pivots1'!$A:$E,4,0)=0, "",VLOOKUP(A105,'Aux - pivots1'!$A:$E,4,0)) | L105: =IF(VLOOKUP(A105,'Aux - pivots1'!$A:$E,5,0)=0, "",VLOOKUP(A105,'Aux - pivots1'!$A:$E,5,0)) | O105: Bens Imóveis
A106: =E106&F106 -> PROCESS_PROPERTY_RELDATA_DATE_PART | B106: Pilar III | C106: Bens Imóveis - Output | D106: 2. Campo | E106: PROCESS_PROPERTY_REL | F106: DATA_DATE_PART | G106: =VLOOKUP(A106,Plano_V3!$A$26:$G$753,7,0) -> 1. Concluído | H106: 1. Concluído | J106: =IF(VLOOKUP(A106,'Aux - pivots1'!$A:$E,3,0)=0, "",VLOOKUP(A106,'Aux - pivots1'!$A:$E,3,0)) | K106: =IF(VLOOKUP(A106,'Aux - pivots1'!$A:$E,4,0)=0, "",VLOOKUP(A106,'Aux - pivots1'!$A:$E,4,0)) | L106: =IF(VLOOKUP(A106,'Aux - pivots1'!$A:$E,5,0)=0, "",VLOOKUP(A106,'Aux - pivots1'!$A:$E,5,0)) | O106: Bens Imóveis
A107: =E107&F107 -> PROPERTYn.a. | B107: Pilar III | C107: Bens Imóveis - Output | D107: 1. Universo | E107: PROPERTY | F107: n.a. | G107: =VLOOKUP(A107,Plano_V3!$A$26:$G$753,7,0) -> 1. Concluído | H107: 1. Concluído | J107: =IF(VLOOKUP(A107,'Aux - pivots1'!$A:$E,3,0)=0, "",VLOOKUP(A107,'Aux - pivots1'!$A:$E,3,0)) | K107: =IF(VLOOKUP(A107,'Aux - pivots1'!$A:$E,4,0)=0, "",VLOOKUP(A107,'Aux - pivots1'!$A:$E,4,0)) | L107: =IF(VLOOKUP(A107,'Aux - pivots1'!$A:$E,5,0)=0, "",VLOOKUP(A107,'Aux - pivots1'!$A:$E,5,0)) | O107: Bens Imóveis
A108: =E108&F108 -> PROPERTYCONSTRUCTION_YEAR | B108: Pilar III | C108: Bens Imóveis - Output | D108: 2. Campo | E108: PROPERTY | F108: CONSTRUCTION_YEAR | G108: =VLOOKUP(A108,Plano_V3!$A$26:$G$753,7,0) -> 1. Concluído | H108: 1. Concluído | J108: =IF(VLOOKUP(A108,'Aux - pivots1'!$A:$E,3,0)=0, "",VLOOKUP(A108,'Aux - pivots1'!$A:$E,3,0)) | K108: =IF(VLOOKUP(A108,'Aux - pivots1'!$A:$E,4,0)=0, "",VLOOKUP(A108,'Aux - pivots1'!$A:$E,4,0)) | L108: =IF(VLOOKUP(A108,'Aux - pivots1'!$A:$E,5,0)=0, "",VLOOKUP(A108,'Aux - pivots1'!$A:$E,5,0)) | O108: Bens Imóveis
A109: =E109&F109 -> PROPERTYNET_FLOOR_AREA | B109: Pilar III | C109: Bens Imóveis - Output | D109: 2. Campo | E109: PROPERTY | F109: NET_FLOOR_AREA | G109: =VLOOKUP(A109,Plano_V3!$A$26:$G$753,7,0) -> 1. Concluído | H109: 1. Concluído | J109: =IF(VLOOKUP(A109,'Aux - pivots1'!$A:$E,3,0)=0, "",VLOOKUP(A109,'Aux - pivots1'!$A:$E,3,0)) | K109: =IF(VLOOKUP(A109,'Aux - pivots1'!$A:$E,4,0)=0, "",VLOOKUP(A109,'Aux - pivots1'!$A:$E,4,0)) | L109: =IF(VLOOKUP(A109,'Aux - pivots1'!$A:$E,5,0)=0, "",VLOOKUP(A109,'Aux - pivots1'!$A:$E,5,0)) | O109: Bens Imóveis
A110: =E110&F110 -> PROPERTYPROPERTY_BANK_ID | B110: Pilar III | C110: Bens Imóveis - Output | D110: 2. Campo | E110: PROPERTY | F110: PROPERTY_BANK_ID | G110: =VLOOKUP(A110,Plano_V3!$A$26:$G$753,7,0) -> 1. Concluído | H110: 1. Concluído | J110: =IF(VLOOKUP(A110,'Aux - pivots1'!$A:$E,3,0)=0, "",VLOOKUP(A110,'Aux - pivots1'!$A:$E,3,0)) | K110: =IF(VLOOKUP(A110,'Aux - pivots1'!$A:$E,4,0)=0, "",VLOOKUP(A110,'Aux - pivots1'!$A:$E,4,0)) | L110: =IF(VLOOKUP(A110,'Aux - pivots1'!$A:$E,5,0)=0, "",VLOOKUP(A110,'Aux - pivots1'!$A:$E,5,0)) | O110: Bens Imóveis
A111: =E111&F111 -> PROPERTYPROPERTY_BRANCH_CODE | B111: Pilar III | C111: Bens Imóveis - Output | D111: 2. Campo | E111: PROPERTY | F111: PROPERTY_BRANCH_CODE | G111: =VLOOKUP(A111,Plano_V3!$A$26:$G$753,7,0) -> 1. Concluído | H111: 1. Concluído | J111: =IF(VLOOKUP(A111,'Aux - pivots1'!$A:$E,3,0)=0, "",VLOOKUP(A111,'Aux - pivots1'!$A:$E,3,0)) | K111: =IF(VLOOKUP(A111,'Aux - pivots1'!$A:$E,4,0)=0, "",VLOOKUP(A111,'Aux - pivots1'!$A:$E,4,0)) | L111: =IF(VLOOKUP(A111,'Aux - pivots1'!$A:$E,5,0)=0, "",VLOOKUP(A111,'Aux - pivots1'!$A:$E,5,0)) | O111: Bens Imóveis
A112: =E112&F112 -> PROPERTYPROPERTY_CONTRACT_ID | B112: Pilar III | C112: Bens Imóveis - Output | D112: 2. Campo | E112: PROPERTY | F112: PROPERTY_CONTRACT_ID | G112: =VLOOKUP(A112,Plano_V3!$A$26:$G$753,7,0) -> 1. Concluído | H112: 1. Concluído | J112: =IF(VLOOKUP(A112,'Aux - pivots1'!$A:$E,3,0)=0, "",VLOOKUP(A112,'Aux - pivots1'!$A:$E,3,0)) | K112: =IF(VLOOKUP(A112,'Aux - pivots1'!$A:$E,4,0)=0, "",VLOOKUP(A112,'Aux - pivots1'!$A:$E,4,0)) | L112: =IF(VLOOKUP(A112,'Aux - pivots1'!$A:$E,5,0)=0, "",VLOOKUP(A112,'Aux - pivots1'!$A:$E,5,0)) | O112: Bens Imóveis
... A115: =E115&F115 -> PROPERTYAPPRAISAL_CODE | B115: Pilar III | C115: Bens Imóveis - Output | D115: 2. Campo | E115: PROPERTY | F115: APPRAISAL_CODE | G115: =VLOOKUP(A115,Plano_V3!$A$26:$G$753,7,0) -> 1. Concluído | H115: 1. Concluído | J115: =IF(VLOOKUP(A115,'Aux - pivots1'!$A:$E,3,0)=0, "",VLOOKUP(A115,'Aux - pivots1'!$A:$E,3,0)) | K115: =IF(VLOOKUP(A115,'Aux - pivots1'!$A:$E,4,0)=0, "",VLOOKUP(A115,'Aux - pivots1'!$A:$E,4,0)) | L115: =IF(VLOOKUP(A115,'Aux - pivots1'!$A:$E,5,0)=0, "",VLOOKUP(A115,'Aux - pivots1'!$A:$E,5,0)) | O115: Bens Imóveis
A116: =E116&F116 -> PROPERTYcod_bem | B116: Pilar III | C116: Bens Imóveis - Output | D116: 2. Campo | E116: PROPERTY | F116: cod_bem | G116: =VLOOKUP(A116,Plano_V3!$A$26:$G$753,7,0) -> 0. Cancelado | H116: 0. Cancelado | I116: 19/07/2024: Campo eliminado do Modelo para garantir coerência com MUG | J116: =IF(VLOOKUP(A116,'Aux - pivots1'!$A:$E,3,0)=0, "",VLOOKUP(A116,'Aux - pivots1'!$A:$E,3,0)) | K116: =IF(VLOOKUP(A116,'Aux - pivots1'!$A:$E,4,0)=0, "",VLOOKUP(A116,'Aux - pivots1'!$A:$E,4,0)) | L116: =IF(VLOOKUP(A116,'Aux - pivots1'!$A:$E,5,0)=0, "",VLOOKUP(A116,'Aux - pivots1'!$A:$E,5,0)) | O116: Bens Imóveis
A117: =E117&F117 -> PROPERTYDISTRICT_MUNICIP_PARISH_CODE | B117: Pilar III | C117: Bens Imóveis - Output | D117: 2. Campo | E117: PROPERTY | F117: DISTRICT_MUNICIP_PARISH_CODE | G117: =VLOOKUP(A117,Plano_V3!$A$26:$G$753,7,0) -> 1. Concluído | H117: 1. Concluído | J117: =IF(VLOOKUP(A117,'Aux - pivots1'!$A:$E,3,0)=0, "",VLOOKUP(A117,'Aux - pivots1'!$A:$E,3,0)) | K117: =IF(VLOOKUP(A117,'Aux - pivots1'!$A:$E,4,0)=0, "",VLOOKUP(A117,'Aux - pivots1'!$A:$E,4,0)) | L117: =IF(VLOOKUP(A117,'Aux - pivots1'!$A:$E,5,0)=0, "",VLOOKUP(A117,'Aux - pivots1'!$A:$E,5,0)) | O117: Bens Imóveis
A118: =E118&F118 -> PROPERTYPROPERTY_PURPOSE_CODE | B118: Pilar III | C118: Bens Imóveis - Output | D118: 2. Campo | E118: PROPERTY | F118: PROPERTY_PURPOSE_CODE | G118: =VLOOKUP(A118,Plano_V3!$A$26:$G$753,7,0) -> 1. Concluído | H118: 1. Concluído | J118: =IF(VLOOKUP(A118,'Aux - pivots1'!$A:$E,3,0)=0, "",VLOOKUP(A118,'Aux - pivots1'!$A:$E,3,0)) | K118: =IF(VLOOKUP(A118,'Aux - pivots1'!$A:$E,4,0)=0, "",VLOOKUP(A118,'Aux - pivots1'!$A:$E,4,0)) | L118: =IF(VLOOKUP(A118,'Aux - pivots1'!$A:$E,5,0)=0, "",VLOOKUP(A118,'Aux - pivots1'!$A:$E,5,0)) | O118: Bens Imóveis
A119: =E119&F119 -> PROPERTYPROPERTY_LIFETIME_CODE | B119: Pilar III | C119: Bens Imóveis - Output | D119: 2. Campo | E119: PROPERTY | F119: PROPERTY_LIFETIME_CODE | G119: =VLOOKUP(A119,Plano_V3!$A$26:$G$753,7,0) -> 1. Concluído | H119: 1. Concluído | J119: =IF(VLOOKUP(A119,'Aux - pivots1'!$A:$E,3,0)=0, "",VLOOKUP(A119,'Aux - pivots1'!$A:$E,3,0)) | K119: =IF(VLOOKUP(A119,'Aux - pivots1'!$A:$E,4,0)=0, "",VLOOKUP(A119,'Aux - pivots1'!$A:$E,4,0)) | L119: =IF(VLOOKUP(A119,'Aux - pivots1'!$A:$E,5,0)=0, "",VLOOKUP(A119,'Aux - pivots1'!$A:$E,5,0)) | O119: Bens Imóveis
A120: =E120&F120 -> PROPERTYADDRESS_CODE | B120: Pilar III | C120: Bens Imóveis - Output | D120: 2. Campo | E120: PROPERTY | F120: ADDRESS_CODE | G120: =VLOOKUP(A120,Plano_V3!$A$26:$G$753,7,0) -> 1. Concluído | H120: 1. Concluído | J120: =IF(VLOOKUP(A120,'Aux - pivots1'!$A:$E,3,0)=0, "",VLOOKUP(A120,'Aux - pivots1'!$A:$E,3,0)) | K120: =IF(VLOOKUP(A120,'Aux - pivots1'!$A:$E,4,0)=0, "",VLOOKUP(A120,'Aux - pivots1'!$A:$E,4,0)) | L120: =IF(VLOOKUP(A120,'Aux - pivots1'!$A:$E,5,0)=0, "",VLOOKUP(A120,'Aux - pivots1'!$A:$E,5,0)) | O120: Bens Imóveis
A121: =E121&F121 -> PROPERTYCOUNTRY_CODE | B121: Pilar III | C121: Bens Imóveis - Output | D121: 2. Campo | E121: PROPERTY | F121: COUNTRY_CODE | G121: =VLOOKUP(A121,Plano_V3!$A$26:$G$753,7,0) -> 1. Concluído | H121: 1. Concluído | J121: =IF(VLOOKUP(A121,'Aux - pivots1'!$A:$E,3,0)=0, "",VLOOKUP(A121,'Aux - pivots1'!$A:$E,3,0)) | K121: =IF(VLOOKUP(A121,'Aux - pivots1'!$A:$E,4,0)=0, "",VLOOKUP(A121,'Aux - pivots1'!$A:$E,4,0)) | L121: =IF(VLOOKUP(A121,'Aux - pivots1'!$A:$E,5,0)=0, "",VLOOKUP(A121,'Aux - pivots1'!$A:$E,5,0)) | O121: Bens Imóveis
A122: =E122&F122 -> PROPERTYPOSTAL_CODE | B122: Pilar III | C122: Bens Imóveis - Output | D122: 2. Campo | E122: PROPERTY | F122: POSTAL_CODE | G122: =VLOOKUP(A122,Plano_V3!$A$26:$G$753,7,0) -> 1. Concluído | H122: 1. Concluído | J122: =IF(VLOOKUP(A122,'Aux - pivots1'!$A:$E,3,0)=0, "",VLOOKUP(A122,'Aux - pivots1'!$A:$E,3,0)) | K122: =IF(VLOOKUP(A122,'Aux - pivots1'!$A:$E,4,0)=0, "",VLOOKUP(A122,'Aux - pivots1'!$A:$E,4,0)) | L122: =IF(VLOOKUP(A122,'Aux - pivots1'!$A:$E,5,0)=0, "",VLOOKUP(A122,'Aux - pivots1'!$A:$E,5,0)) | O122: Bens Imóveis
A123: =E123&F123 -> PROPERTYPROPERTY_TYPE_CODE | B123: Pilar III | C123: Bens Imóveis - Output | D123: 2. Campo | E123: PROPERTY | F123: PROPERTY_TYPE_CODE | G123: =VLOOKUP(A123,Plano_V3!$A$26:$G$753,7,0) -> 1. Concluído | H123: 1. Concluído | J123: =IF(VLOOKUP(A123,'Aux - pivots1'!$A:$E,3,0)=0, "",VLOOKUP(A123,'Aux - pivots1'!$A:$E,3,0)) | K123: =IF(VLOOKUP(A123,'Aux - pivots1'!$A:$E,4,0)=0, "",VLOOKUP(A123,'Aux - pivots1'!$A:$E,4,0)) | L123: =IF(VLOOKUP(A123,'Aux - pivots1'!$A:$E,5,0)=0, "",VLOOKUP(A123,'Aux - pivots1'!$A:$E,5,0)) | O123: Bens Imóveis
A124: =E124&F124 -> PROPERTYLAST_APPRAISAL_DATE | B124: Pilar III | C124: Bens Imóveis - Output | D124: 2. Campo | E124: PROPERTY | F124: LAST_APPRAISAL_DATE | G124: =VLOOKUP(A124,Plano_V3!$A$26:$G$753,7,0) -> 1. Concluído | H124: 1. Concluído | J124: =IF(VLOOKUP(A124,'Aux - pivots1'!$A:$E,3,0)=0, "",VLOOKUP(A124,'Aux - pivots1'!$A:$E,3,0)) | K124: =IF(VLOOKUP(A124,'Aux - pivots1'!$A:$E,4,0)=0, "",VLOOKUP(A124,'Aux - pivots1'!$A:$E,4,0)) | L124: =IF(VLOOKUP(A124,'Aux - pivots1'!$A:$E,5,0)=0, "",VLOOKUP(A124,'Aux - pivots1'!$A:$E,5,0)) | O124: Bens Imóveis
A125: =E125&F125 -> PROPERTYUSAGE_PERMIT_START_DATE | B125: Pilar III | C125: Bens Imóveis - Output | D125: 2. Campo | E125: PROPERTY | F125: USAGE_PERMIT_START_DATE | G125: =VLOOKUP(A125,Plano_V3!$A$26:$G$753,7,0) -> 1. Concluído | H125: 1. Concluído | J125: =IF(VLOOKUP(A125,'Aux - pivots1'!$A:$E,3,0)=0, "",VLOOKUP(A125,'Aux - pivots1'!$A:$E,3,0)) | K125: =IF(VLOOKUP(A125,'Aux - pivots1'!$A:$E,4,0)=0, "",VLOOKUP(A125,'Aux - pivots1'!$A:$E,4,0)) | L125: =IF(VLOOKUP(A125,'Aux - pivots1'!$A:$E,5,0)=0, "",VLOOKUP(A125,'Aux - pivots1'!$A:$E,5,0)) | O125: Bens Imóveis
A126: =E126&F126 -> PROPERTYCONSERVATORY_REG_FILE_ID | B126: Pilar III | C126: Bens Imóveis - Output | D126: 2. Campo | E126: PROPERTY | F126: CONSERVATORY_REG_FILE_ID | G126: =VLOOKUP(A126,Plano_V3!$A$26:$G$753,7,0) -> 1. Concluído | H126: 1. Concluído | J126: =IF(VLOOKUP(A126,'Aux - pivots1'!$A:$E,3,0)=0, "",VLOOKUP(A126,'Aux - pivots1'!$A:$E,3,0)) | K126: =IF(VLOOKUP(A126,'Aux - pivots1'!$A:$E,4,0)=0, "",VLOOKUP(A126,'Aux - pivots1'!$A:$E,4,0)) | L126: =IF(VLOOKUP(A126,'Aux - pivots1'!$A:$E,5,0)=0, "",VLOOKUP(A126,'Aux - pivots1'!$A:$E,5,0)) | O126: Bens Imóveis
...

Sheet Aux - pivots1
A3: concat | B3: Max of Status2
A4: ENERGY_CERTIFICATE_EST_INPUTANIO_CONSTRUCCION | B4: 7
A5: ENERGY_CERTIFICATE_EST_INPUTART_MATRICIAIS | B5: 7
A6: ENERGY_CERTIFICATE_EST_INPUTASSUPERFICIE_UTIL | B6: 7
A7: ENERGY_CERTIFICATE_EST_INPUTCAGLURB | B7: 7
A8: ENERGY_CERTIFICATE_EST_INPUTCASA_UNIFAMILIAR | B8: 7
A9: ENERGY_CERTIFICATE_EST_INPUTCHAVE_GLOVAL | B9: 7
A10: ENERGY_CERTIFICATE_EST_INPUTCLASS_GPT31 | B10: 7
A11: ENERGY_CERTIFICATE_EST_INPUTCLASS_STCLIM | B11: 7
A12: ENERGY_CERTIFICATE_EST_INPUTCLASSE_ENERGETICA | B12: 7
A13: ENERGY_CERTIFICATE_EST_INPUTCOD_CONSERVATORIA | B13: 7
A14: ENERGY_CERTIFICATE_EST_INPUTCÓDIGO_CONCEJO | B14: 7
A15: ENERGY_CERTIFICATE_EST_INPUTCÓDIGO_DISTRITO | B15: 7
... A723: Grand Total | B723: 8

Sheet Aux - Pivots2
B2: 1. Visão Geral
B6: Âmbito | C6: Pilar III
B7: Tipo de teste | C7: 2. Campo
B9: Count of Campo | C9: Column Labels
B10: Row Labels | C10: 0. Cancelado | D10: 1. Concluído | E10: 2.1 Em Teste | F10: 3. Pendente de outros desenvolvimentos | G10: 4. Validação EF | H10: 5. Em Correção | I10: 6. Em implementação (re-especificação) | J10: 2.2 Em Re-especificação | K10: 7. Por iniciar | L10: Grand Total
B11: Bens Imóveis | C11: 10 | D11: 143 | E11: 1 | I11: 48 | L11: 202
B12: Modelo Verde | C12: 12 | D12: 178 | F12: 6 | G12: 55 | J12: 7 | L12: 258
B13: Pilar III | C13: 4 | D13: 132 | F13: 9 | G13: 1 | H13: 3 | J13: 1 | K13: 3 | L13: 153
B14: (blank) | D14: 33 | K14: 54 | L14: 87
B15: Grand Total | C15: 26 | D15: 486 | E15: 1 | F15: 15 | G15: 56 | H15: 3 | I15: 48 | J15: 8 | K15: 57 | L15: 700
B19: Âmbito | C19: Pilar III
B20: Modelo | C20: (All)
B21: Tipo de teste | C21: 2. Campo
B23: Row Labels | C23: Count of Campo
B24: 0. Cancelado | C24: 26
B25: 1. Concluído | C25: 486
B26: 2.1 Em Teste | C26: 1
B27: 3. Pendente de outros desenvolvimentos | C27: 15
B28: 4. Validação EF | C28: 56
B29: 5. Em Correção | C29: 3
B30: 6. Em implementação (re-especificação) | C30: 48
B31: 2.2 Em Re-especificação | C31: 8
B32: 7. Por iniciar | C32: 57
B33: Grand Total | C33: 700
B42: 2. Modelo Bens imóveis
B45: Âmbito | C45: Pilar III
B46: Sub-âmbito | C46: (Multiple Items)
B47: Tipo de teste | C47: 2. Campo
B49: Count of Campo | C49: Column Labels
B50: Row Labels | C50: 0. Cancelado | D50: 1. Concluído | E50: 2.1 Em Teste | F50: 6. Em implementação (re-especificação) | G50: Grand Total
B51: RESPONSIBILITY_PROCESS_REL | C51: 3 | D51: 17 | G51: 20
B52: PROPERTY_ENERGY_CERTIFICATE | D52: 68 | E52: 1 | F52: 4 | G52: 73
B53: PROPERTY | C53: 2 | D53: 31 | G53: 33
B54: PROCESS_PROPERTY_REL | C54: 1 | D54: 14 | G54: 15
B55: PROCESS | C55: 4 | D55: 13 | G55: 17
B56: ENERGY_CERTIFICATE_EST_INPUT | F56: 44 | G56: 44
B57: Grand Total | C57: 10 | D57: 143 | E57: 1 | F57: 48 | G57: 202
B62: Âmbito | C62: Pilar III
B63: Sub-âmbito | C63: (Multiple Items)
B64: Tipo de teste | C64: 2. Campo
B66: Row Labels | C66: Count of Campo
B67: 0. Cancelado | C67: 10
B68: 1. Concluído | C68: 143
B69: 2.1 Em Teste | C69: 1
B70: 6. Em implementação (re-especificação) | C70: 48
B71: Grand Total | C71: 202
B81: 3. Modelo Verde
B83: Âmbito | C83: Pilar III
B84: Sub-âmbito | C84: (Multiple Items)
B85: Tipo de teste | C85: 2. Campo
B87: Count of Campo | C87: Column Labels
B88: Row Labels | C88: 0. Cancelado | D88: 1. Concluído | E88: 2.2 Em Re-especificação | F88: 3. Pendente de outros desenvolvimentos | G88: 4. Validação EF | H88: 7. Por iniciar | I88: Grand Total
B89: modesg_param_sfics_taxon_europeia | G89: 42 | I89: 42
B90: modesg_out_sfics_taxon_europeia | C90: 1 | D90: 1 | G90: 13 | I90: 15
B91: modesg_out_emss_vcls | D91: 15 | I91: 15
B92: modesg_out_empr_info_nfin | D92: 41 | E92: 5 | F92: 6 | I92: 52
B93: modesg_out_bens_imoveis | D93: 16 | E93: 2 | I93: 18
B94: modesg_inp_risco_fisico_zipcode | H94: 5 | I94: 5
B95: modesg_inp_risco_fisico | D95: 6 | I95: 6
B96: modesg_inp_project_finance | D96: 9 | I96: 9
B97: modesg_inp_nfrd_alinhamento_tax | D97: 41 | I97: 41
B98: modesg_inp_km_medios_emss_vcls | C98: 3 | D98: 6 | I98: 9
B99: modesg_inp_emss_vcls | D99: 17 | I99: 17
B100: modesg_inp_emss_scib | D100: 17 | I100: 17
B101: modesg_inp_emss_nace | C101: 7 | D101: 14 | I101: 21
B102: modesg_inp_emss_bens_imoveis | C102: 1 | D102: 17 | I102: 18
B103: modesg_inp_empr_excl_paris | D103: 7 | I103: 7
B104: Grand Total | C104: 12 | D104: 207 | E104: 7 | F104: 6 | G104: 55 | H104: 5 | I104: 292
B107: Âmbito | C107: Pilar III
B108: Sub-âmbito | C108: (Multiple Items)
B109: Tipo de teste | C109: 2. Campo
B111: Row Labels | C111: Count of Campo
B112: 0. Cancelado | C112: 12
B113: 1. Concluído | C113: 207
B114: 2.2 Em Re-especificação | C114: 7
B115: 3. Pendente de outros desenvolvimentos | C115: 6
B116: 4. Validação EF | C116: 55
B117: 7. Por iniciar | C117: 5
B118: Grand Total | C118: 292
B126: 4. Loan Tape | Pilar III
B129: Âmbito | C129: Pilar III
B130: Sub-âmbito | C130: Pilar III
B131: Tipo de teste | C131: 2. Campo
B133: Count of Campo | C133: Column Labels
B134: Row Labels | C134: 0. Cancelado | D134: 1. Concluído | E134: 2.2 Em Re-especificação | F134: 3. Pendente de outros desenvolvimentos | G134: 4. Validação EF | H134: 5. Em Correção | I134: 7. Por iniciar | J134: Grand Total
B135: lt002_instrument | D135: 23 | F135: 4 | H135: 3 | I135: 16 | J135: 46
B136: lt003_entity | D136: 59 | E136: 1 | F136: 3 | I136: 4 | J136: 67
B137: lt004_protection | C137: 4 | D137: 18 | F137: 2 | I137: 23 | J137: 47
B138: lt005_instr_ent | D138: 5 | J138: 5
B139: lt006_instr_prot | D139: 4 | I139: 2 | J139: 6
B140: lt007_instr_activity | D140: 3 | G140: 1 | I140: 7 | J140: 11
B141: lt826_esg_sbsctr | D141: 9 | J141: 9
B142: lt827_mthd_usd_instrmnt | D142: 15 | J142: 15
B143: Grand Total | C143: 4 | D143: 136 | E143: 1 | F143: 9 | G143: 1 | H143: 3 | I143: 52 | J143: 206
B150: Âmbito | C150: Pilar III
B151: Sub-âmbito | C151: Pilar III
B152: Tipo de teste | C152: 2. Campo
B154: Row Labels | C154: Count of Campo
B155: 1. Concluído | C155: 136
B156: 0. Cancelado | C156: 4
...

Sheet Caderno Testes FY24
N7: (alterar quando necessário) | R7: (data default - Dez2023)
B8: Âmbito | C8: Sub-âmbito | D8: Origem | E8: Campo Origem | F8: Tabela | G8: Campo | H8: concat | I8: Status | J8: Status2 | K8: Tipologia_Testes | L8: Necessidade de re-especificação? (campo) | M8: Complexidade | N8: Data de Alteração Status | O8: Estimação (horas) | P8: Notas | Q8: Owner | R8: Data alteração especificação | S8: Data de inicio testes | T8: Data de incidência / pedido esclarecimento | U8: Data de correção/resposta prevista | V8: Data de correção/resposta efetiva | W8: Horas efetivas | X8: Query
B9: Pilar III | C9: Bens Imóveis - Input | D9: bu_esg_work.kt_chave_gloval; bu_esg_work.gloval_clase_energetica_dez23 | E9: n.a. | F9: ENERGY_CERTIFICATE_EST_INPUT | G9: n.a. | H9: =Table1[[#This Row],[Tabela]]&Table1[[#This Row],[Campo]] -> ENERGY_CERTIFICATE_EST_INPUTn.a. | I9: 6. Em implementação (re-especificação) | J9: =VLOOKUP(Table1[[#This Row],[Status]],Auxiliar!$B$16:$C$24,2,0) -> 7 | K9: 1. Teste de universo | L9: Não | M9: Baixa | N9: 45688 | O9: =INDEX(Auxiliar!$D$5:$F$13,MATCH(Table1[[#This Row],[Tipologia_Testes]],Auxiliar!$B$5:$B$13,0),MATCH(Table1[[#This Row],[Complexidade]],Auxiliar!$D$4:$F$4,0)) -> 8 | R9: 45261 | T9: 45510 | U9: 45624 | W9: =VLOOKUP(Table1[[#This Row],[Status]],Auxiliar!$B$16:$D$24,3,0)*Table1[[#This Row],[Estimação (horas)]] -> 2
B10: Pilar III | C10: Bens Imóveis - Input | D10: bu_esg_work.kt_chave_gloval; bu_esg_work.gloval_clase_energetica_dez23 | E10: n.a. | F10: ENERGY_CERTIFICATE_EST_INPUT | G10: CHAVE_GLOVAL | H10: =Table1[[#This Row],[Tabela]]&Table1[[#This Row],[Campo]] -> ENERGY_CERTIFICATE_EST_INPUTCHAVE_GLOVAL | I10: 6. Em implementação (re-especificação) | J10: =VLOOKUP(Table1[[#This Row],[Status]],Auxiliar!$B$16:$C$24,2,0) -> 7 | K10: 6. Validação de formatos | L10: Sim | M10: Baixa | N10: 45688 | O10: =INDEX(Auxiliar!$D$5:$F$13,MATCH(Table1[[#This Row],[Tipologia_Testes]],Auxiliar!$B$5:$B$13,0),MATCH(Table1[[#This Row],[Complexidade]],Auxiliar!$D$4:$F$4,0)) -> 0.1 | R10: 45261 | T10: 45510 | U10: 45624 | W10: =VLOOKUP(Table1[[#This Row],[Status]],Auxiliar!$B$16:$D$24,3,0)*Table1[[#This Row],[Estimação (horas)]] -> 0.025
B11: Pilar III | C11: Bens Imóveis - Input | D11: bu_esg_work.kt_chave_gloval; bu_esg_work.gloval_clase_energetica_dez23 | E11: n.a. | F11: ENERGY_CERTIFICATE_EST_INPUT | G11: PROPERTY_BANK_ID | H11: =Table1[[#This Row],[Tabela]]&Table1[[#This Row],[Campo]] -> ENERGY_CERTIFICATE_EST_INPUTPROPERTY_BANK_ID | I11: 6. Em implementação (re-especificação) | J11: =VLOOKUP(Table1[[#This Row],[Status]],Auxiliar!$B$16:$C$24,2,0) -> 7 | K11: 6. Validação de formatos | L11: Sim | M11: Baixa | N11: 45688 | O11: =INDEX(Auxiliar!$D$5:$F$13,MATCH(Table1[[#This Row],[Tipologia_Testes]],Auxiliar!$B$5:$B$13,0),MATCH(Table1[[#This Row],[Complexidade]],Auxiliar!$D$4:$F$4,0)) -> 0.1 | P11: Comentário da Susana ao paralelo: Efetivamente recebemos informação da Gloval mas para este efeito devemos apenas tomar os dados reais (e não as estimativas); existe um campo que indica essa situação | R11: 45261 | T11: 45510 | U11: 45624 | W11: =VLOOKUP(Table1[[#This Row],[Status]],Auxiliar!$B$16:$D$24,3,0)*Table1[[#This Row],[Estimação (horas)]] -> 0.025
B12: Pilar III | C12: Bens Imóveis - Input | D12: bu_esg_work.kt_chave_gloval; bu_esg_work.gloval_clase_energetica_dez23 | E12: n.a. | F12: ENERGY_CERTIFICATE_EST_INPUT | G12: PROPERTY_BRANCH_CODE | H12: =Table1[[#This Row],[Tabela]]&Table1[[#This Row],[Campo]] -> ENERGY_CERTIFICATE_EST_INPUTPROPERTY_BRANCH_CODE | I12: 6. Em implementação (re-especificação) | J12: =VLOOKUP(Table1[[#This Row],[Status]],Auxiliar!$B$16:$C$24,2,0) -> 7 | K12: 6. Validação de formatos | L12: Sim | M12: Baixa | N12: 45688 | O12: =INDEX(Auxiliar!$D$5:$F$13,MATCH(Table1[[#This Row],[Tipologia_Testes]],Auxiliar!$B$5:$B$13,0),MATCH(Table1[[#This Row],[Complexidade]],Auxiliar!$D$4:$F$4,0)) -> 0.1 | P12: Cempresa não está incluída na chave - mas a especificação no excel diz: Chave encriptada do bem, gerada com base na concatenação das variáveis cempbem, ckbalbem, ckctabem e ckrefbem | R12: 45261 | T12: 45510 | U12: 45624 | W12: =VLOOKUP(Table1[[#This Row],[Status]],Auxiliar!$B$16:$D$24,3,0)*Table1[[#This Row],[Estimação (horas)]] -> 0.025
B13: Pilar III | C13: Bens Imóveis - Input | D13: bu_esg_work.kt_chave_gloval; bu_esg_work.gloval_clase_energetica_dez23 | E13: n.a. | F13: ENERGY_CERTIFICATE_EST_INPUT | G13: PROPERTY_CONTRACT_ID | H13: =Table1[[#This Row],[Tabela]]&Table1[[#This Row],[Campo]] -> ENERGY_CERTIFICATE_EST_INPUTPROPERTY_CONTRACT_ID | I13: 6. Em implementação (re-especificação) | J13: =VLOOKUP(Table1[[#This Row],[Status]],Auxiliar!$B$16:$C$24,2,0) -> 7 | K13: 6. Validação de formatos | L13: Sim | M13: Baixa | N13: 45688 | O13: =INDEX(Auxiliar!$D$5:$F$13,MATCH(Table1[[#This Row],[Tipologia_Testes]],Auxiliar!$B$5:$B$13,0),MATCH(Table1[[#This Row],[Complexidade]],Auxiliar!$D$4:$F$4,0)) -> 0.1 | P13: Cempresa não está incluída na chave - mas a especificação no excel diz: Chave encriptada do bem, gerada com base na concatenação das variáveis cempbem, ckbalbem, ckctabem e ckrefbem | R13: 45261 | T13: 45510 | U13: 45624 | W13: =VLOOKUP(Table1[[#This Row],[Status]],Auxiliar!$B$16:$D$24,3,0)*Table1[[#This Row],[Estimação (horas)]] -> 0.025
B14: Pilar III | C14: Bens Imóveis - Input | D14: bu_esg_work.kt_chave_gloval; bu_esg_work.gloval_clase_energetica_dez23 | E14: n.a. | F14: ENERGY_CERTIFICATE_EST_INPUT | G14: PROPERTY_REFERENCE_CODE | H14: =Table1[[#This Row],[Tabela]]&Table1[[#This Row],[Campo]] -> ENERGY_CERTIFICATE_EST_INPUTPROPERTY_REFERENCE_CODE | I14: 6. Em implementação (re-especificação) | J14: =VLOOKUP(Table1[[#This Row],[Status]],Auxiliar!$B$16:$C$24,2,0) -> 7 | K14: 6. Validação de formatos | L14: Sim | M14: Baixa | N14: 45688 | O14: =INDEX(Auxiliar!$D$5:$F$13,MATCH(Table1[[#This Row],[Tipologia_Testes]],Auxiliar!$B$5:$B$13,0),MATCH(Table1[[#This Row],[Complexidade]],Auxiliar!$D$4:$F$4,0)) -> 0.1 | R14: 45261 | T14: 45510 | U14: 45624 | W14: =VLOOKUP(Table1[[#This Row],[Status]],Auxiliar!$B$16:$D$24,3,0)*Table1[[#This Row],[Estimação (horas)]] -> 0.025
B15: Pilar III | C15: Bens Imóveis - Input | D15: bu_esg_work.kt_chave_gloval; bu_esg_work.gloval_clase_energetica_dez23 | E15: n.a. | F15: ENERGY_CERTIFICATE_EST_INPUT | G15: CÓDIGO_DISTRITO | H15: =Table1[[#This Row],[Tabela]]&Table1[[#This Row],[Campo]] -> ENERGY_CERTIFICATE_EST_INPUTCÓDIGO_DISTRITO | I15: 6. Em implementação (re-especificação) | J15: =VLOOKUP(Table1[[#This Row],[Status]],Auxiliar!$B$16:$C$24,2,0) -> 7 | K15: 6. Validação de formatos | L15: Sim | M15: Baixa | N15: 45688 | O15: =INDEX(Auxiliar!$D$5:$F$13,MATCH(Table1[[#This Row],[Tipologia_Testes]],Auxiliar!$B$5:$B$13,0),MATCH(Table1[[#This Row],[Complexidade]],Auxiliar!$D$4:$F$4,0)) -> 0.1 | R15: 45261 | T15: 45510 | U15: 45624 | W15: =VLOOKUP(Table1[[#This Row],[Status]],Auxiliar!$B$16:$D$24,3,0)*Table1[[#This Row],[Estimação (horas)]] -> 0.025
B16: Pilar III | C16: Bens Imóveis - Input | D16: bu_esg_work.kt_chave_gloval; bu_esg_work.gloval_clase_energetica_dez23 | E16: n.a. | F16: ENERGY_CERTIFICATE_EST_INPUT | G16: NOMBRE_DISTRITO | H16: =Table1[[#This Row],[Tabela]]&Table1[[#This Row],[Campo]] -> ENERGY_CERTIFICATE_EST_INPUTNOMBRE_DISTRITO | I16: 6. Em implementação (re-especificação) | J16: =VLOOKUP(Table1[[#This Row],[Status]],Auxiliar!$B$16:$C$24,2,0) -> 7 | K16: 6. Validação de formatos | L16: Sim | M16: Baixa | N16: 45688 | O16: =INDEX(Auxiliar!$D$5:$F$13,MATCH(Table1[[#This Row],[Tipologia_Testes]],Auxiliar!$B$5:$B$13,0),MATCH(Table1[[#This Row],[Complexidade]],Auxiliar!$D$4:$F$4,0)) -> 0.1 | R16: 45261 | T16: 45510 | U16: 45624 | W16: =VLOOKUP(Table1[[#This Row],[Status]],Auxiliar!$B$16:$D$24,3,0)*Table1[[#This Row],[Estimação (horas)]] -> 0.025
B17: Pilar III | C17: Bens Imóveis - Input | D17: bu_esg_work.kt_chave_gloval; bu_esg_work.gloval_clase_energetica_dez23 | E17: n.a. | F17: ENERGY_CERTIFICATE_EST_INPUT | G17: CÓDIGO_CONCEJO | H17: =Table1[[#This Row],[Tabela]]&Table1[[#This Row],[Campo]] -> ENERGY_CERTIFICATE_EST_INPUTCÓDIGO_CONCEJO | I17: 6. Em implementação (re-especificação) | J17: =VLOOKUP(Table1[[#This Row],[Status]],Auxiliar!$B$16:$C$24,2,0) -> 7 | K17: 6. Validação de formatos | L17: Sim | M17: Baixa | N17: 45688 | O17: =INDEX(Auxiliar!$D$5:$F$13,MATCH(Table1[[#This Row],[Tipologia_Testes]],Auxiliar!$B$5:$B$13,0),MATCH(Table1[[#This Row],[Complexidade]],Auxiliar!$D$4:$F$4,0)) -> 0.1 | R17: 45261 | T17: 45510 | U17: 45624 | W17: =VLOOKUP(Table1[[#This Row],[Status]],Auxiliar!$B$16:$D$24,3,0)*Table1[[#This Row],[Estimação (horas)]] -> 0.025
B18: Pilar III | C18: Bens Imóveis - Input | D18: bu_esg_work.kt_chave_gloval; bu_esg_work.gloval_clase_energetica_dez23 | E18: n.a. | F18: ENERGY_CERTIFICATE_EST_INPUT | G18: NOMBRE_CONCEJO | H18: =Table1[[#This Row],[Tabela]]&Table1[[#This Row],[Campo]] -> ENERGY_CERTIFICATE_EST_INPUTNOMBRE_CONCEJO | I18: 6. Em implementação (re-especificação) | J18: =VLOOKUP(Table1[[#This Row],[Status]],Auxiliar!$B$16:$C$24,2,0) -> 7 | K18: 6. Validação de formatos | L18: Sim | M18: Baixa | N18: 45688 | O18: =INDEX(Auxiliar!$D$5:$F$13,MATCH(Table1[[#This Row],[Tipologia_Testes]],Auxiliar!$B$5:$B$13,0),MATCH(Table1[[#This Row],[Complexidade]],Auxiliar!$D$4:$F$4,0)) -> 0.1 | R18: 45261 | T18: 45510 | U18: 45624 | W18: =VLOOKUP(Table1[[#This Row],[Status]],Auxiliar!$B$16:$D$24,3,0)*Table1[[#This Row],[Estimação (horas)]] -> 0.025
B19: Pilar III | C19: Bens Imóveis - Input | D19: bu_esg_work.kt_chave_gloval; bu_esg_work.gloval_clase_energetica_dez23 | E19: n.a. | F19: ENERGY_CERTIFICATE_EST_INPUT | G19: CÓDIGO_FREGUESIA | H19: =Table1[[#This Row],[Tabela]]&Table1[[#This Row],[Campo]] -> ENERGY_CERTIFICATE_EST_INPUTCÓDIGO_FREGUESIA | I19: 6. Em implementação (re-especificação) | J19: =VLOOKUP(Table1[[#This Row],[Status]],Auxiliar!$B$16:$C$24,2,0) -> 7 | K19: 6. Validação de formatos | L19: Sim | M19: Baixa | N19: 45688 | O19: =INDEX(Auxiliar!$D$5:$F$13,MATCH(Table1[[#This Row],[Tipologia_Testes]],Auxiliar!$B$5:$B$13,0),MATCH(Table1[[#This Row],[Complexidade]],Auxiliar!$D$4:$F$4,0)) -> 0.1 | R19: 45261 | T19: 45510 | U19: 45624 | W19: =VLOOKUP(Table1[[#This Row],[Status]],Auxiliar!$B$16:$D$24,3,0)*Table1[[#This Row],[Estimação (horas)]] -> 0.025
B20: Pilar III | C20: Bens Imóveis - Input | D20: bu_esg_work.kt_chave_gloval; bu_esg_work.gloval_clase_energetica_dez23 | E20: n.a. | F20: ENERGY_CERTIFICATE_EST_INPUT | G20: NOMBRE_FREGUESIA | H20: =Table1[[#This Row],[Tabela]]&Table1[[#This Row],[Campo]] -> ENERGY_CERTIFICATE_EST_INPUTNOMBRE_FREGUESIA | I20: 6. Em implementação (re-especificação) | J20: =VLOOKUP(Table1[[#This Row],[Status]],Auxiliar!$B$16:$C$24,2,0) -> 7 | K20: 6. Validação de formatos | L20: Sim | M20: Baixa | N20: 45688 | O20: =INDEX(Auxiliar!$D$5:$F$13,MATCH(Table1[[#This Row],[Tipologia_Testes]],Auxiliar!$B$5:$B$13,0),MATCH(Table1[[#This Row],[Complexidade]],Auxiliar!$D$4:$F$4,0)) -> 0.1 | R20: 45261 | T20: 45510 | U20: 45624 | W20: =VLOOKUP(Table1[[#This Row],[Status]],Auxiliar!$B$16:$D$24,3,0)*Table1[[#This Row],[Estimação (horas)]] -> 0.025
B21: Pilar III | C21: Bens Imóveis - Input | D21: bu_esg_work.kt_chave_gloval; bu_esg_work.gloval_clase_energetica_dez23 | E21: n.a. | F21: ENERGY_CERTIFICATE_EST_INPUT | G21: LOCALIDADE | H21: =Table1[[#This Row],[Tabela]]&Table1[[#This Row],[Campo]] -> ENERGY_CERTIFICATE_EST_INPUTLOCALIDADE | I21: 6. Em implementação (re-especificação) | J21: =VLOOKUP(Table1[[#This Row],[Status]],Auxiliar!$B$16:$C$24,2,0) -> 7 | K21: 6. Validação de formatos | L21: Sim | M21: Baixa | N21: 45688 | O21: =INDEX(Auxiliar!$D$5:$F$13,MATCH(Table1[[#This Row],[Tipologia_Testes]],Auxiliar!$B$5:$B$13,0),MATCH(Table1[[#This Row],[Complexidade]],Auxiliar!$D$4:$F$4,0)) -> 0.1 | R21: 45261 | T21: 45510 | U21: 45624 | W21: =VLOOKUP(Table1[[#This Row],[Status]],Auxiliar!$B$16:$D$24,3,0)*Table1[[#This Row],[Estimação (horas)]] -> 0.025
B22: Pilar III | C22: Bens Imóveis - Input | D22: bu_esg_work.kt_chave_gloval; bu_esg_work.gloval_clase_energetica_dez23 | E22: n.a. | F22: ENERGY_CERTIFICATE_EST_INPUT | G22: TIPO_VIA | H22: =Table1[[#This Row],[Tabela]]&Table1[[#This Row],[Campo]] -> ENERGY_CERTIFICATE_EST_INPUTTIPO_VIA | I22: 6. Em implementação (re-especificação) | J22: =VLOOKUP(Table1[[#This Row],[Status]],Auxiliar!$B$16:$C$24,2,0) -> 7 | K22: 6. Validação de formatos | L22: Sim | M22: Baixa | N22: 45688 | O22: =INDEX(Auxiliar!$D$5:$F$13,MATCH(Table1[[#This Row],[Tipologia_Testes]],Auxiliar!$B$5:$B$13,0),MATCH(Table1[[#This Row],[Complexidade]],Auxiliar!$D$4:$F$4,0)) -> 0.1 | P22: Chave primária na especificação não está de acordo com a especificação mas está bem implementado | R22: 45261 | T22: 45510 | U22: 45624 | W22: =VLOOKUP(Table1[[#This Row],[Status]],Auxiliar!$B$16:$D$24,3,0)*Table1[[#This Row],[Estimação (horas)]] -> 0.025
B23: Pilar III | C23: Bens Imóveis - Input | D23: bu_esg_work.kt_chave_gloval; bu_esg_work.gloval_clase_energetica_dez23 | E23: n.a. | F23: ENERGY_CERTIFICATE_EST_INPUT | G23: NOMBRE_TIPO_VIA | H23: =Table1[[#This Row],[Tabela]]&Table1[[#This Row],[Campo]] -> ENERGY_CERTIFICATE_EST_INPUTNOMBRE_TIPO_VIA | I23: 6. Em implementação (re-especificação) | J23: =VLOOKUP(Table1[[#This Row],[Status]],Auxiliar!$B$16:$C$24,2,0) -> 7 | K23: 6. Validação de formatos | L23: Sim | M23: Baixa | N23: 45688 | O23: =INDEX(Auxiliar!$D$5:$F$13,MATCH(Table1[[#This Row],[Tipologia_Testes]],Auxiliar!$B$5:$B$13,0),MATCH(Table1[[#This Row],[Complexidade]],Auxiliar!$D$4:$F$4,0)) -> 0.1 | P23: Chave primária na especificação não está de acordo com a especificação mas está bem implementado | R23: 45261 | T23: 45510 | U23: 45624 | W23: =VLOOKUP(Table1[[#This Row],[Status]],Auxiliar!$B$16:$D$24,3,0)*Table1[[#This Row],[Estimação (horas)]] -> 0.025
B24: Pilar III | C24: Bens Imóveis - Input | D24: bu_esg_work.kt_chave_gloval; bu_esg_work.gloval_clase_energetica_dez23 | E24: n.a. | F24: ENERGY_CERTIFICATE_EST_INPUT | G24: NOMBRE_VIA | H24: =Table1[[#This Row],[Tabela]]&Table1[[#This Row],[Campo]] -> ENERGY_CERTIFICATE_EST_INPUTNOMBRE_VIA | I24: 6. Em implementação (re-especificação) | J24: =VLOOKUP(Table1[[#This Row],[Status]],Auxiliar!$B$16:$C$24,2,0) -> 7 | K24: 6. Validação de formatos | L24: Sim | M24: Baixa | N24: 45688 | O24: =INDEX(Auxiliar!$D$5:$F$13,MATCH(Table1[[#This Row],[Tipologia_Testes]],Auxiliar!$B$5:$B$13,0),MATCH(Table1[[#This Row],[Complexidade]],Auxiliar!$D$4:$F$4,0)) -> 0.1 | P24: Controlos errados na EF | R24: 45261 | T24: 45510 | U24: 45624 | W24: =VLOOKUP(Table1[[#This Row],[Status]],Auxiliar!$B$16:$D$24,3,0)*Table1[[#This Row],[Estimação (horas)]] -> 0.025
B25: Pilar III | C25: Bens Imóveis - Input | D25: bu_esg_work.kt_chave_gloval; bu_esg_work.gloval_clase_energetica_dez23 | E25: n.a. | F25: ENERGY_CERTIFICATE_EST_INPUT | G25: NUMERO_VIA | H25: =Table1[[#This Row],[Tabela]]&Table1[[#This Row],[Campo]] -> ENERGY_CERTIFICATE_EST_INPUTNUMERO_VIA | I25: 6. Em implementação (re-especificação) | J25: =VLOOKUP(Table1[[#This Row],[Status]],Auxiliar!$B$16:$C$24,2,0) -> 7 | K25: 6. Validação de formatos | L25: Sim | M25: Baixa | N25: 45688 | O25: =INDEX(Auxiliar!$D$5:$F$13,MATCH(Table1[[#This Row],[Tipologia_Testes]],Auxiliar!$B$5:$B$13,0),MATCH(Table1[[#This Row],[Complexidade]],Auxiliar!$D$4:$F$4,0)) -> 0.1 | P25: Controlos errados na EF | R25: 45261 | T25: 45510 | U25: 45624 | W25: =VLOOKUP(Table1[[#This Row],[Status]],Auxiliar!$B$16:$D$24,3,0)*Table1[[#This Row],[Estimação (horas)]] -> 0.025
B26: Pilar III | C26: Bens Imóveis - Input | D26: bu_esg_work.kt_chave_gloval; bu_esg_work.gloval_clase_energetica_dez23 | E26: n.a. | F26: ENERGY_CERTIFICATE_EST_INPUT | G26: LOTE | H26: =Table1[[#This Row],[Tabela]]&Table1[[#This Row],[Campo]] -> ENERGY_CERTIFICATE_EST_INPUTLOTE | I26: 6. Em implementação (re-especificação) | J26: =VLOOKUP(Table1[[#This Row],[Status]],Auxiliar!$B$16:$C$24,2,0) -> 7 | K26: 6. Validação de formatos | L26: Sim | M26: Baixa | N26: 45688 | O26: =INDEX(Auxiliar!$D$5:$F$13,MATCH(Table1[[#This Row],[Tipologia_Testes]],Auxiliar!$B$5:$B$13,0),MATCH(Table1[[#This Row],[Complexidade]],Auxiliar!$D$4:$F$4,0)) -> 0.1 | R26: 45261 | T26: 45510 | U26: 45624 | W26: =VLOOKUP(Table1[[#This Row],[Status]],Auxiliar!$B$16:$D$24,3,0)*Table1[[#This Row],[Estimação (horas)]] -> 0.025
B27: Pilar III | C27: Bens Imóveis - Input | D27: bu_esg_work.kt_chave_gloval; bu_esg_work.gloval_clase_energetica_dez23 | E27: n.a. | F27: ENERGY_CERTIFICATE_EST_INPUT | G27: URBANIZACION | H27: =Table1[[#This Row],[Tabela]]&Table1[[#This Row],[Campo]] -> ENERGY_CERTIFICATE_EST_INPUTURBANIZACION | I27: 6. Em implementação (re-especificação) | J27: =VLOOKUP(Table1[[#This Row],[Status]],Auxiliar!$B$16:$C$24,2,0) -> 7 | K27: 6. Validação de formatos | L27: Sim | M27: Baixa | N27: 45688 | O27: =INDEX(Auxiliar!$D$5:$F$13,MATCH(Table1[[#This Row],[Tipologia_Testes]],Auxiliar!$B$5:$B$13,0),MATCH(Table1[[#This Row],[Complexidade]],Auxiliar!$D$4:$F$4,0)) -> 0.1 | R27: 45261 | T27: 45510 | U27: 45624 | W27: =VLOOKUP(Table1[[#This Row],[Status]],Auxiliar!$B$16:$D$24,3,0)*Table1[[#This Row],[Estimação (horas)]] -> 0.025
B28: Pilar III | C28: Bens Imóveis - Input | D28: bu_esg_work.kt_chave_gloval; bu_esg_work.gloval_clase_energetica_dez23 | E28: n.a. | F28: ENERGY_CERTIFICATE_EST_INPUT | G28: CAGLURB | H28: =Table1[[#This Row],[Tabela]]&Table1[[#This Row],[Campo]] -> ENERGY_CERTIFICATE_EST_INPUTCAGLURB | I28: 6. Em implementação (re-especificação) | J28: =VLOOKUP(Table1[[#This Row],[Status]],Auxiliar!$B$16:$C$24,2,0) -> 7 | K28: 6. Validação de formatos | L28: Sim | M28: Baixa | N28: 45688 | O28: =INDEX(Auxiliar!$D$5:$F$13,MATCH(Table1[[#This Row],[Tipologia_Testes]],Auxiliar!$B$5:$B$13,0),MATCH(Table1[[#This Row],[Complexidade]],Auxiliar!$D$4:$F$4,0)) -> 0.1 | R28: 45261 | T28: 45510 | U28: 45624 | W28: =VLOOKUP(Table1[[#This Row],[Status]],Auxiliar!$B$16:$D$24,3,0)*Table1[[#This Row],[Estimação (horas)]] -> 0.025
B29: Pilar III | C29: Bens Imóveis - Input | D29: bu_esg_work.kt_chave_gloval; bu_esg_work.gloval_clase_energetica_dez23 | E29: n.a. | F29: ENERGY_CERTIFICATE_EST_INPUT | G29: RESTO_DIRECCION | H29: =Table1[[#This Row],[Tabela]]&Table1[[#This Row],[Campo]] -> ENERGY_CERTIFICATE_EST_INPUTRESTO_DIRECCION | I29: 6. Em implementação (re-especificação) | J29: =VLOOKUP(Table1[[#This Row],[Status]],Auxiliar!$B$16:$C$24,2,0) -> 7 | K29: 6. Validação de formatos | L29: Sim | M29: Baixa | N29: 45688 | O29: =INDEX(Auxiliar!$D$5:$F$11,MATCH(Table1[[#This Row],[Tipologia_Testes]],Auxiliar!$B$5:$B$11,0),MATCH(Table1[[#This Row],[Complexidade]],Auxiliar!$D$4:$F$4,0)) -> 0.1 | W29: =VLOOKUP(Table1[[#This Row],[Status]],Auxiliar!$B$16:$D$24,3,0)*Table1[[#This Row],[Estimação (horas)]] -> 0.025
B30: Pilar III | C30: Bens Imóveis - Input | D30: bu_esg_work.kt_chave_gloval; bu_esg_work.gloval_clase_energetica_dez23 | E30: n.a. | F30: ENERGY_CERTIFICATE_EST_INPUT | G30: LATITUDE | H30: =Table1[[#This Row],[Tabela]]&Table1[[#This Row],[Campo]] -> ENERGY_CERTIFICATE_EST_INPUTLATITUDE | I30: 6. Em implementação (re-especificação) | J30: =VLOOKUP(Table1[[#This Row],[Status]],Auxiliar!$B$16:$C$24,2,0) -> 7 | K30: 6. Validação de formatos | L30: Sim | M30: Baixa | N30: 45688 | O30: =INDEX(Auxiliar!$D$5:$F$11,MATCH(Table1[[#This Row],[Tipologia_Testes]],Auxiliar!$B$5:$B$11,0),MATCH(Table1[[#This Row],[Complexidade]],Auxiliar!$D$4:$F$4,0)) -> 0.1 | W30: =VLOOKUP(Table1[[#This Row],[Status]],Auxiliar!$B$16:$D$24,3,0)*Table1[[#This Row],[Estimação (horas)]] -> 0.025
B31: Pilar III | C31: Bens Imóveis - Input | D31: bu_esg_work.kt_chave_gloval; bu_esg_work.gloval_clase_energetica_dez23 | E31: n.a. | F31: ENERGY_CERTIFICATE_EST_INPUT | G31: LONGITUDE | H31: =Table1[[#This Row],[Tabela]]&Table1[[#This Row],[Campo]] -> ENERGY_CERTIFICATE_EST_INPUTLONGITUDE | I31: 6. Em implementação (re-especificação) | J31: =VLOOKUP(Table1[[#This Row],[Status]],Auxiliar!$B$16:$C$24,2,0) -> 7 | K31: 6. Validação de formatos | L31: Sim | M31: Baixa | N31: 45688 | O31: =INDEX(Auxiliar!$D$5:$F$11,MATCH(Table1[[#This Row],[Tipologia_Testes]],Auxiliar!$B$5:$B$11,0),MATCH(Table1[[#This Row],[Complexidade]],Auxiliar!$D$4:$F$4,0)) -> 0.1 | W31: =VLOOKUP(Table1[[#This Row],[Status]],Auxiliar!$B$16:$D$24,3,0)*Table1[[#This Row],[Estimação (horas)]] -> 0.025
B32: Pilar III | C32: Bens Imóveis - Input | D32: bu_esg_work.kt_chave_gloval; bu_esg_work.gloval_clase_energetica_dez23 | E32: n.a. | F32: ENERGY_CERTIFICATE_EST_INPUT | G32: CODIGO_POSTAL | H32: =Table1[[#This Row],[Tabela]]&Table1[[#This Row],[Campo]] -> ENERGY_CERTIFICATE_EST_INPUTCODIGO_POSTAL | I32: 6. Em implementação (re-especificação) | J32: =VLOOKUP(Table1[[#This Row],[Status]],Auxiliar!$B$16:$C$24,2,0) -> 7 | K32: 6. Validação de formatos | L32: Sim | M32: Baixa | N32: 45688 | O32: =INDEX(Auxiliar!$D$5:$F$11,MATCH(Table1[[#This Row],[Tipologia_Testes]],Auxiliar!$B$5:$B$11,0),MATCH(Table1[[#This Row],[Complexidade]],Auxiliar!$D$4:$F$4,0)) -> 0.1 | W32: =VLOOKUP(Table1[[#This Row],[Status]],Auxiliar!$B$16:$D$24,3,0)*Table1[[#This Row],[Estimação (horas)]] -> 0.025
B33: Pilar III | C33: Bens Imóveis - Input | D33: bu_esg_work.kt_chave_gloval; bu_esg_work.gloval_clase_energetica_dez23 | E33: n.a. | F33: ENERGY_CERTIFICATE_EST_INPUT | G33: SUBCODIGO_POSTAL | H33: =Table1[[#This Row],[Tabela]]&Table1[[#This Row],[Campo]] -> ENERGY_CERTIFICATE_EST_INPUTSUBCODIGO_POSTAL | I33: 6. Em implementação (re-especificação) | J33: =VLOOKUP(Table1[[#This Row],[Status]],Auxiliar!$B$16:$C$24,2,0) -> 7 | K33: 6. Validação de formatos | L33: Sim | M33: Baixa | N33: 45688 | O33: =INDEX(Auxiliar!$D$5:$F$11,MATCH(Table1[[#This Row],[Tipologia_Testes]],Auxiliar!$B$5:$B$11,0),MATCH(Table1[[#This Row],[Complexidade]],Auxiliar!$D$4:$F$4,0)) -> 0.1 | W33: =VLOOKUP(Table1[[#This Row],[Status]],Auxiliar!$B$16:$D$24,3,0)*Table1[[#This Row],[Estimação (horas)]] -> 0.025
B34: Pilar III | C34: Bens Imóveis - Input | D34: bu_esg_work.kt_chave_gloval; bu_esg_work.gloval_clase_energetica_dez23 | E34: n.a. | F34: ENERGY_CERTIFICATE_EST_INPUT | G34: ASSUPERFICIE_UTIL | H34: =Table1[[#This Row],[Tabela]]&Table1[[#This Row],[Campo]] -> ENERGY_CERTIFICATE_EST_INPUTASSUPERFICIE_UTIL | I34: 6. Em implementação (re-especificação) | J34: =VLOOKUP(Table1[[#This Row],[Status]],Auxiliar!$B$16:$C$24,2,0) -> 7 | K34: 6. Validação de formatos | L34: Sim | M34: Baixa | N34: 45688 | O34: =INDEX(Auxiliar!$D$5:$F$11,MATCH(Table1[[#This Row],[Tipologia_Testes]],Auxiliar!$B$5:$B$11,0),MATCH(Table1[[#This Row],[Complexidade]],Auxiliar!$D$4:$F$4,0)) -> 0.1 | W34: =VLOOKUP(Table1[[#This Row],[Status]],Auxiliar!$B$16:$D$24,3,0)*Table1[[#This Row],[Estimação (horas)]] -> 0.025
B35: Pilar III | C35: Bens Imóveis - Input | D35: bu_esg_work.kt_chave_gloval; bu_esg_work.gloval_clase_energetica_dez23 | E35: n.a. | F35: ENERGY_CERTIFICATE_EST_INPUT | G35: ANIO_CONSTRUCCION | H35: =Table1[[#This Row],[Tabela]]&Table1[[#This Row],[Campo]] -> ENERGY_CERTIFICATE_EST_INPUTANIO_CONSTRUCCION | I35: 6. Em implementação (re-especificação) | J35: =VLOOKUP(Table1[[#This Row],[Status]],Auxiliar!$B$16:$C$24,2,0) -> 7 | K35: 6. Validação de formatos | L35: Sim | M35: Baixa | N35: 45688 | O35: =INDEX(Auxiliar!$D$5:$F$11,MATCH(Table1[[#This Row],[Tipologia_Testes]],Auxiliar!$B$5:$B$11,0),MATCH(Table1[[#This Row],[Complexidade]],Auxiliar!$D$4:$F$4,0)) -> 0.1 | W35: =VLOOKUP(Table1[[#This Row],[Status]],Auxiliar!$B$16:$D$24,3,0)*Table1[[#This Row],[Estimação (horas)]] -> 0.025
B36: Pilar III | C36: Bens Imóveis - Input | D36: bu_esg_work.kt_chave_gloval; bu_esg_work.gloval_clase_energetica_dez23 | E36: n.a. | F36: ENERGY_CERTIFICATE_EST_INPUT | G36: TIPO_INMUEBLE_HABITACAO | H36: =Table1[[#This Row],[Tabela]]&Table1[[#This Row],[Campo]] -> ENERGY_CERTIFICATE_EST_INPUTTIPO_INMUEBLE_HABITACAO | I36: 6. Em implementação (re-especificação) | J36: =VLOOKUP(Table1[[#This Row],[Status]],Auxiliar!$B$16:$C$24,2,0) -> 7 | K36: 6. Validação de formatos | L36: Sim | M36: Baixa | N36: 45688 | O36: =INDEX(Auxiliar!$D$5:$F$11,MATCH(Table1[[#This Row],[Tipologia_Testes]],Auxiliar!$B$5:$B$11,0),MATCH(Table1[[#This Row],[Complexidade]],Auxiliar!$D$4:$F$4,0)) -> 0.1 | W36: =VLOOKUP(Table1[[#This Row],[Status]],Auxiliar!$B$16:$D$24,3,0)*Table1[[#This Row],[Estimação (horas)]] -> 0.025
B37: Pilar III | C37: Bens Imóveis - Input | D37: bu_esg_work.kt_chave_gloval; bu_esg_work.gloval_clase_energetica_dez23 | E37: n.a. | F37: ENERGY_CERTIFICATE_EST_INPUT | G37: PISO_APARTAMENTO | H37: =Table1[[#This Row],[Tabela]]&Table1[[#This Row],[Campo]] -> ENERGY_CERTIFICATE_EST_INPUTPISO_APARTAMENTO | I37: 6. Em implementação (re-especificação) | J37: =VLOOKUP(Table1[[#This Row],[Status]],Auxiliar!$B$16:$C$24,2,0) -> 7 | K37: 6. Validação de formatos | L37: Sim | M37: Baixa | N37: 45688 | O37: =INDEX(Auxiliar!$D$5:$F$11,MATCH(Table1[[#This Row],[Tipologia_Testes]],Auxiliar!$B$5:$B$11,0),MATCH(Table1[[#This Row],[Complexidade]],Auxiliar!$D$4:$F$4,0)) -> 0.1 | W37: =VLOOKUP(Table1[[#This Row],[Status]],Auxiliar!$B$16:$D$24,3,0)*Table1[[#This Row],[Estimação (horas)]] -> 0.025
B38: Pilar III | C38: Bens Imóveis - Input | D38: bu_esg_work.kt_chave_gloval; bu_esg_work.gloval_clase_energetica_dez23 | E38: n.a. | F38: ENERGY_CERTIFICATE_EST_INPUT | G38: CASA_UNIFAMILIAR | H38: =Table1[[#This Row],[Tabela]]&Table1[[#This Row],[Campo]] -> ENERGY_CERTIFICATE_EST_INPUTCASA_UNIFAMILIAR | I38: 6. Em implementação (re-especificação) | J38: =VLOOKUP(Table1[[#This Row],[Status]],Auxiliar!$B$16:$C$24,2,0) -> 7 | K38: 6. Validação de formatos | L38: Sim | M38: Baixa | N38: 45688 | O38: =INDEX(Auxiliar!$D$5:$F$11,MATCH(Table1[[#This Row],[Tipologia_Testes]],Auxiliar!$B$5:$B$11,0),MATCH(Table1[[#This Row],[Complexidade]],Auxiliar!$D$4:$F$4,0)) -> 0.1 | W38: =VLOOKUP(Table1[[#This Row],[Status]],Auxiliar!$B$16:$D$24,3,0)*Table1[[#This Row],[Estimação (horas)]] -> 0.025
B39: Pilar III | C39: Bens Imóveis - Input | D39: bu_esg_work.kt_chave_gloval; bu_esg_work.gloval_clase_energetica_dez23 | E39: n.a. | F39: ENERGY_CERTIFICATE_EST_INPUT | G39: TIPO_INMUEBLE_COMERCIO_SERVICOS | H39: =Table1[[#This Row],[Tabela]]&Table1[[#This Row],[Campo]] -> ENERGY_CERTIFICATE_EST_INPUTTIPO_INMUEBLE_COMERCIO_SERVICOS | I39: 6. Em implementação (re-especificação) | J39: =VLOOKUP(Table1[[#This Row],[Status]],Auxiliar!$B$16:$C$24,2,0) -> 7 | K39: 6. Validação de formatos | L39: Sim | M39: Baixa | N39: 45688 | O39: =INDEX(Auxiliar!$D$5:$F$11,MATCH(Table1[[#This Row],[Tipologia_Testes]],Auxiliar!$B$5:$B$11,0),MATCH(Table1[[#This Row],[Complexidade]],Auxiliar!$D$4:$F$4,0)) -> 0.1 | W39: =VLOOKUP(Table1[[#This Row],[Status]],Auxiliar!$B$16:$D$24,3,0)*Table1[[#This Row],[Estimação (horas)]] -> 0.025
B40: Pilar III | C40: Bens Imóveis - Input | D40: bu_esg_work.kt_chave_gloval; bu_esg_work.gloval_clase_energetica_dez23 | E40: n.a. | F40: ENERGY_CERTIFICATE_EST_INPUT | G40: NOME_CONSERVATORIA | H40: =Table1[[#This Row],[Tabela]]&Table1[[#This Row],[Campo]] -> ENERGY_CERTIFICATE_EST_INPUTNOME_CONSERVATORIA | I40: 6. Em implementação (re-especificação) | J40: =VLOOKUP(Table1[[#This Row],[Status]],Auxiliar!$B$16:$C$24,2,0) -> 7 | K40: 6. Validação de formatos | L40: Sim | M40: Baixa | N40: 45688 | O40: =INDEX(Auxiliar!$D$5:$F$11,MATCH(Table1[[#This Row],[Tipologia_Testes]],Auxiliar!$B$5:$B$11,0),MATCH(Table1[[#This Row],[Complexidade]],Auxiliar!$D$4:$F$4,0)) -> 0.1 | W40: =VLOOKUP(Table1[[#This Row],[Status]],Auxiliar!$B$16:$D$24,3,0)*Table1[[#This Row],[Estimação (horas)]] -> 0.025
... B48: Pilar III | C48: Bens Imóveis - Input | D48: bu_esg_work.kt_chave_gloval; bu_esg_work.gloval_clase_energetica_dez23 | E48: n.a. | F48: ENERGY_CERTIFICATE_EST_INPUT | G48: CONF_STCLIM | H48: =Table1[[#This Row],[Tabela]]&Table1[[#This Row],[Campo]] -> ENERGY_CERTIFICATE_EST_INPUTCONF_STCLIM | I48: 6. Em implementação (re-especificação) | J48: =VLOOKUP(Table1[[#This Row],[Status]],Auxiliar!$B$16:$C$24,2,0) -> 7 | K48: 6. Validação de formatos | L48: Sim | M48: Baixa | N48: 45688 | O48: =INDEX(Auxiliar!$D$5:$F$11,MATCH(Table1[[#This Row],[Tipologia_Testes]],Auxiliar!$B$5:$B$11,0),MATCH(Table1[[#This Row],[Complexidade]],Auxiliar!$D$4:$F$4,0)) -> 0.1 | W48: =VLOOKUP(Table1[[#This Row],[Status]],Auxiliar!$B$16:$D$24,3,0)*Table1[[#This Row],[Estimação (horas)]] -> 0.025
B49: Pilar III | C49: Bens Imóveis - Input | D49: bu_esg_work.kt_chave_gloval; bu_esg_work.gloval_clase_energetica_dez23 | E49: n.a. | F49: ENERGY_CERTIFICATE_EST_INPUT | G49: CLASSE_ENERGETICA | H49: =Table1[[#This Row],[Tabela]]&Table1[[#This Row],[Campo]] -> ENERGY_CERTIFICATE_EST_INPUTCLASSE_ENERGETICA | I49: 6. Em implementação (re-especificação) | J49: =VLOOKUP(Table1[[#This Row],[Status]],Auxiliar!$B$16:$C$24,2,0) -> 7 | K49: 6. Validação de formatos | L49: Sim | M49: Baixa | N49: 45688 | O49: =INDEX(Auxiliar!$D$5:$F$13,MATCH(Table1[[#This Row],[Tipologia_Testes]],Auxiliar!$B$5:$B$13,0),MATCH(Table1[[#This Row],[Complexidade]],Auxiliar!$D$4:$F$4,0)) -> 0.1 | R49: 45261 | T49: 45510 | U49: 45624 | W49: =VLOOKUP(Table1[[#This Row],[Status]],Auxiliar!$B$16:$D$24,3,0)*Table1[[#This Row],[Estimação (horas)]] -> 0.025
B50: Pilar III | C50: Bens Imóveis - Input | D50: bu_esg_work.kt_chave_gloval; bu_esg_work.gloval_clase_energetica_dez23 | E50: n.a. | F50: ENERGY_CERTIFICATE_EST_INPUT | G50: FIABILIDAD | H50: =Table1[[#This Row],[Tabela]]&Table1[[#This Row],[Campo]] -> ENERGY_CERTIFICATE_EST_INPUTFIABILIDAD | I50: 6. Em implementação (re-especificação) | J50: =VLOOKUP(Table1[[#This Row],[Status]],Auxiliar!$B$16:$C$24,2,0) -> 7 | K50: 6. Validação de formatos | L50: Sim | M50: Baixa | N50: 45688 | O50: =INDEX(Auxiliar!$D$5:$F$13,MATCH(Table1[[#This Row],[Tipologia_Testes]],Auxiliar!$B$5:$B$13,0),MATCH(Table1[[#This Row],[Complexidade]],Auxiliar!$D$4:$F$4,0)) -> 0.1 | P50: Chave primária na especificação não está de acordo com a especificação mas está bem implementado | R50: 45261 | T50: 45510 | U50: 45624 | W50: =VLOOKUP(Table1[[#This Row],[Status]],Auxiliar!$B$16:$D$24,3,0)*Table1[[#This Row],[Estimação (horas)]] -> 0.025
B51: Pilar III | C51: Bens Imóveis - Input | D51: bu_esg_work.kt_chave_gloval; bu_esg_work.gloval_clase_energetica_dez23 | E51: n.a. | F51: ENERGY_CERTIFICATE_EST_INPUT | G51: EMISSIONES | H51: =Table1[[#This Row],[Tabela]]&Table1[[#This Row],[Campo]] -> ENERGY_CERTIFICATE_EST_INPUTEMISSIONES | I51: 6. Em implementação (re-especificação) | J51: =VLOOKUP(Table1[[#This Row],[Status]],Auxiliar!$B$16:$C$24,2,0) -> 7 | K51: 6. Validação de formatos | L51: Sim | M51: Baixa | N51: 45688 | O51: =INDEX(Auxiliar!$D$5:$F$13,MATCH(Table1[[#This Row],[Tipologia_Testes]],Auxiliar!$B$5:$B$13,0),MATCH(Table1[[#This Row],[Complexidade]],Auxiliar!$D$4:$F$4,0)) -> 0.1 | P51: Chave primária na especificação não está de acordo com a especificação mas está bem implementado | R51: 45261 | T51: 45510 | U51: 45624 | W51: =VLOOKUP(Table1[[#This Row],[Status]],Auxiliar!$B$16:$D$24,3,0)*Table1[[#This Row],[Estimação (horas)]] -> 0.025
B52: Pilar III | C52: Bens Imóveis - Input | D52: bu_esg_work.kt_chave_gloval; bu_esg_work.gloval_clase_energetica_dez23 | E52: n.a. | F52: ENERGY_CERTIFICATE_EST_INPUT | G52: CONSUMOS | H52: =Table1[[#This Row],[Tabela]]&Table1[[#This Row],[Campo]] -> ENERGY_CERTIFICATE_EST_INPUTCONSUMOS | I52: 6. Em implementação (re-especificação) | J52: =VLOOKUP(Table1[[#This Row],[Status]],Auxiliar!$B$16:$C$24,2,0) -> 7 | K52: 6. Validação de formatos | L52: Sim | M52: Baixa | N52: 45688 | O52: =INDEX(Auxiliar!$D$5:$F$13,MATCH(Table1[[#This Row],[Tipologia_Testes]],Auxiliar!$B$5:$B$13,0),MATCH(Table1[[#This Row],[Complexidade]],Auxiliar!$D$4:$F$4,0)) -> 0.1 | P52: Chave primária na especificação não está de acordo com a especificação mas está bem implementado | R52: 45261 | T52: 45510 | U52: 45624 | W52: =VLOOKUP(Table1[[#This Row],[Status]],Auxiliar!$B$16:$D$24,3,0)*Table1[[#This Row],[Estimação (horas)]] -> 0.025
B53: Pilar III | C53: Bens Imóveis - Input | D53: bu_esg_work.kt_chave_gloval; bu_esg_work.gloval_clase_energetica_dez23 | E53: n.a. | F53: ENERGY_CERTIFICATE_EST_INPUT | G53: DATA_ENVIO | H53: =Table1[[#This Row],[Tabela]]&Table1[[#This Row],[Campo]] -> ENERGY_CERTIFICATE_EST_INPUTDATA_ENVIO | I53: 6. Em implementação (re-especificação) | J53: =VLOOKUP(Table1[[#This Row],[Status]],Auxiliar!$B$16:$C$24,2,0) -> 7 | K53: 6. Validação de formatos | L53: Sim | M53: Baixa | N53: 45688 | O53: =INDEX(Auxiliar!$D$5:$F$13,MATCH(Table1[[#This Row],[Tipologia_Testes]],Auxiliar!$B$5:$B$13,0),MATCH(Table1[[#This Row],[Complexidade]],Auxiliar!$D$4:$F$4,0)) -> 0.1 | P53: Chave primária na especificação não está de acordo com a especificação mas está bem implementado | R53: 45261 | T53: 45510 | U53: 45624 | W53: =VLOOKUP(Table1[[#This Row],[Status]],Auxiliar!$B$16:$D$24,3,0)*Table1[[#This Row],[Estimação (horas)]] -> 0.025
B54: Pilar III | C54: Bens Imóveis - Input | D54: bu_esg_work.kt_chave_gloval; bu_esg_work.gloval_clase_energetica_dez23 | E54: n.a. | F54: ENERGY_CERTIFICATE_EST_INPUT | G54: CHAVE_GLOVAL | H54: =Table1[[#This Row],[Tabela]]&Table1[[#This Row],[Campo]] -> ENERGY_CERTIFICATE_EST_INPUTCHAVE_GLOVAL | I54: 6. Em implementação (re-especificação) | J54: =VLOOKUP(Table1[[#This Row],[Status]],Auxiliar!$B$16:$C$24,2,0) -> 7 | K54: 9. Teste de Integridade | L54: Sim | M54: Baixa | N54: 45688 | O54: =INDEX(Auxiliar!$D$5:$F$11,MATCH(Table1[[#This Row],[Tipologia_Testes]],Auxiliar!$B$5:$B$11,0),MATCH(Table1[[#This Row],[Complexidade]],Auxiliar!$D$4:$F$4,0)) -> #N/A | W54: =VLOOKUP(Table1[[#This Row],[Status]],Auxiliar!$B$16:$D$24,3,0)*Table1[[#This Row],[Estimação (horas)]] -> #N/A
B55: Pilar III | C55: Bens Imóveis - Input | D55: bu_esg_work.kt_chave_gloval; bu_esg_work.gloval_clase_energetica_dez23 | E55: n.a. | F55: ENERGY_CERTIFICATE_EST_INPUT | G55: PROPERTY_BANK_ID | H55: =Table1[[#This Row],[Tabela]]&Table1[[#This Row],[Campo]] -> ENERGY_CERTIFICATE_EST_INPUTPROPERTY_BANK_ID | I55: 6. Em implementação (re-especificação) | J55: =VLOOKUP(Table1[[#This Row],[Status]],Auxiliar!$B$16:$C$24,2,0) -> 7 | K55: 9. Teste de Integridade | L55: Sim | M55: Baixa | N55: 45688 | O55: =INDEX(Auxiliar!$D$5:$F$11,MATCH(Table1[[#This Row],[Tipologia_Testes]],Auxiliar!$B$5:$B$11,0),MATCH(Table1[[#This Row],[Complexidade]],Auxiliar!$D$4:$F$4,0)) -> #N/A | W55: =VLOOKUP(Table1[[#This Row],[Status]],Auxiliar!$B$16:$D$24,3,0)*Table1[[#This Row],[Estimação (horas)]] -> #N/A
B56: Pilar III | C56: Bens Imóveis - Input | D56: bu_esg_work.kt_chave_gloval; bu_esg_work.gloval_clase_energetica_dez23 | E56: n.a. | F56: ENERGY_CERTIFICATE_EST_INPUT | G56: PROPERTY_BRANCH_CODE | H56: =Table1[[#This Row],[Tabela]]&Table1[[#This Row],[Campo]] -> ENERGY_CERTIFICATE_EST_INPUTPROPERTY_BRANCH_CODE | I56: 6. Em implementação (re-especificação) | J56: =VLOOKUP(Table1[[#This Row],[Status]],Auxiliar!$B$16:$C$24,2,0) -> 7 | K56: 9. Teste de Integridade | L56: Sim | M56: Baixa | N56: 45688 | O56: =INDEX(Auxiliar!$D$5:$F$11,MATCH(Table1[[#This Row],[Tipologia_Testes]],Auxiliar!$B$5:$B$11,0),MATCH(Table1[[#This Row],[Complexidade]],Auxiliar!$D$4:$F$4,0)) -> #N/A | W56: =VLOOKUP(Table1[[#This Row],[Status]],Auxiliar!$B$16:$D$24,3,0)*Table1[[#This Row],[Estimação (horas)]] -> #N/A
B57: Pilar III | C57: Bens Imóveis - Input | D57: bu_esg_work.kt_chave_gloval; bu_esg_work.gloval_clase_energetica_dez23 | E57: n.a. | F57: ENERGY_CERTIFICATE_EST_INPUT | G57: PROPERTY_CONTRACT_ID | H57: =Table1[[#This Row],[Tabela]]&Table1[[#This Row],[Campo]] -> ENERGY_CERTIFICATE_EST_INPUTPROPERTY_CONTRACT_ID | I57: 6. Em implementação (re-especificação) | J57: =VLOOKUP(Table1[[#This Row],[Status]],Auxiliar!$B$16:$C$24,2,0) -> 7 | K57: 9. Teste de Integridade | L57: Sim | M57: Baixa | N57: 45688 | O57: =INDEX(Auxiliar!$D$5:$F$11,MATCH(Table1[[#This Row],[Tipologia_Testes]],Auxiliar!$B$5:$B$11,0),MATCH(Table1[[#This Row],[Complexidade]],Auxiliar!$D$4:$F$4,0)) -> #N/A | W57: =VLOOKUP(Table1[[#This Row],[Status]],Auxiliar!$B$16:$D$24,3,0)*Table1[[#This Row],[Estimação (horas)]] -> #N/A
B58: Pilar III | C58: Bens Imóveis - Input | D58: bu_esg_work.kt_chave_gloval; bu_esg_work.gloval_clase_energetica_dez23 | E58: n.a. | F58: ENERGY_CERTIFICATE_EST_INPUT | G58: PROPERTY_REFERENCE_CODE | H58: =Table1[[#This Row],[Tabela]]&Table1[[#This Row],[Campo]] -> ENERGY_CERTIFICATE_EST_INPUTPROPERTY_REFERENCE_CODE | I58: 6. Em implementação (re-especificação) | J58: =VLOOKUP(Table1[[#This Row],[Status]],Auxiliar!$B$16:$C$24,2,0) -> 7 | K58: 9. Teste de Integridade | L58: Sim | M58: Baixa | N58: 45688 | O58: =INDEX(Auxiliar!$D$5:$F$11,MATCH(Table1[[#This Row],[Tipologia_Testes]],Auxiliar!$B$5:$B$11,0),MATCH(Table1[[#This Row],[Complexidade]],Auxiliar!$D$4:$F$4,0)) -> #N/A | W58: =VLOOKUP(Table1[[#This Row],[Status]],Auxiliar!$B$16:$D$24,3,0)*Table1[[#This Row],[Estimação (horas)]] -> #N/A
B59: Pilar III | C59: Bens Imóveis - Input | D59: bu_esg_work.kt_chave_gloval; bu_esg_work.gloval_clase_energetica_dez23 | E59: n.a. | F59: ENERGY_CERTIFICATE_EST_INPUT | G59: CÓDIGO_DISTRITO | H59: =Table1[[#This Row],[Tabela]]&Table1[[#This Row],[Campo]] -> ENERGY_CERTIFICATE_EST_INPUTCÓDIGO_DISTRITO | I59: 6. Em implementação (re-especificação) | J59: =VLOOKUP(Table1[[#This Row],[Status]],Auxiliar!$B$16:$C$24,2,0) -> 7 | K59: 9. Teste de Integridade | L59: Sim | M59: Baixa | N59: 45688 | O59: =INDEX(Auxiliar!$D$5:$F$11,MATCH(Table1[[#This Row],[Tipologia_Testes]],Auxiliar!$B$5:$B$11,0),MATCH(Table1[[#This Row],[Complexidade]],Auxiliar!$D$4:$F$4,0)) -> #N/A | W59: =VLOOKUP(Table1[[#This Row],[Status]],Auxiliar!$B$16:$D$24,3,0)*Table1[[#This Row],[Estimação (horas)]] -> #N/A
B60: Pilar III | C60: Bens Imóveis - Input | D60: bu_esg_work.kt_chave_gloval; bu_esg_work.gloval_clase_energetica_dez23 | E60: n.a. | F60: ENERGY_CERTIFICATE_EST_INPUT | G60: NOMBRE_DISTRITO | H60: =Table1[[#This Row],[Tabela]]&Table1[[#This Row],[Campo]] -> ENERGY_CERTIFICATE_EST_INPUTNOMBRE_DISTRITO | I60: 6. Em implementação (re-especificação) | J60: =VLOOKUP(Table1[[#This Row],[Status]],Auxiliar!$B$16:$C$24,2,0) -> 7 | K60: 9. Teste de Integridade | L60: Sim | M60: Baixa | N60: 45688 | O60: =INDEX(Auxiliar!$D$5:$F$11,MATCH(Table1[[#This Row],[Tipologia_Testes]],Auxiliar!$B$5:$B$11,0),MATCH(Table1[[#This Row],[Complexidade]],Auxiliar!$D$4:$F$4,0)) -> #N/A | W60: =VLOOKUP(Table1[[#This Row],[Status]],Auxiliar!$B$16:$D$24,3,0)*Table1[[#This Row],[Estimação (horas)]] -> #N/A
B61: Pilar III | C61: Bens Imóveis - Input | D61: bu_esg_work.kt_chave_gloval; bu_esg_work.gloval_clase_energetica_dez23 | E61: n.a. | F61: ENERGY_CERTIFICATE_EST_INPUT | G61: CÓDIGO_CONCEJO | H61: =Table1[[#This Row],[Tabela]]&Table1[[#This Row],[Campo]] -> ENERGY_CERTIFICATE_EST_INPUTCÓDIGO_CONCEJO | I61: 6. Em implementação (re-especificação) | J61: =VLOOKUP(Table1[[#This Row],[Status]],Auxiliar!$B$16:$C$24,2,0) -> 7 | K61: 9. Teste de Integridade | L61: Sim | M61: Baixa | N61: 45688 | O61: =INDEX(Auxiliar!$D$5:$F$11,MATCH(Table1[[#This Row],[Tipologia_Testes]],Auxiliar!$B$5:$B$11,0),MATCH(Table1[[#This Row],[Complexidade]],Auxiliar!$D$4:$F$4,0)) -> #N/A | W61: =VLOOKUP(Table1[[#This Row],[Status]],Auxiliar!$B$16:$D$24,3,0)*Table1[[#This Row],[Estimação (horas)]] -> #N/A
B62: Pilar III | C62: Bens Imóveis - Input | D62: bu_esg_work.kt_chave_gloval; bu_esg_work.gloval_clase_energetica_dez23 | E62: n.a. | F62: ENERGY_CERTIFICATE_EST_INPUT | G62: NOMBRE_CONCEJO | H62: =Table1[[#This Row],[Tabela]]&Table1[[#This Row],[Campo]] -> ENERGY_CERTIFICATE_EST_INPUTNOMBRE_CONCEJO | I62: 6. Em implementação (re-especificação) | J62: =VLOOKUP(Table1[[#This Row],[Status]],Auxiliar!$B$16:$C$24,2,0) -> 7 | K62: 9. Teste de Integridade | L62: Sim | M62: Baixa | N62: 45688 | O62: =INDEX(Auxiliar!$D$5:$F$11,MATCH(Table1[[#This Row],[Tipologia_Testes]],Auxiliar!$B$5:$B$11,0),MATCH(Table1[[#This Row],[Complexidade]],Auxiliar!$D$4:$F$4,0)) -> #N/A | W62: =VLOOKUP(Table1[[#This Row],[Status]],Auxiliar!$B$16:$D$24,3,0)*Table1[[#This Row],[Estimação (horas)]] -> #N/A
B63: Pilar III | C63: Bens Imóveis - Input | D63: bu_esg_work.kt_chave_gloval; bu_esg_work.gloval_clase_energetica_dez23 | E63: n.a. | F63: ENERGY_CERTIFICATE_EST_INPUT | G63: CÓDIGO_FREGUESIA | H63: =Table1[[#This Row],[Tabela]]&Table1[[#This Row],[Campo]] -> ENERGY_CERTIFICATE_EST_INPUTCÓDIGO_FREGUESIA | I63: 6. Em implementação (re-especificação) | J63: =VLOOKUP(Table1[[#This Row],[Status]],Auxiliar!$B$16:$C$24,2,0) -> 7 | K63: 9. Teste de Integridade | L63: Sim | M63: Baixa | N63: 45688 | O63: =INDEX(Auxiliar!$D$5:$F$11,MATCH(Table1[[#This Row],[Tipologia_Testes]],Auxiliar!$B$5:$B$11,0),MATCH(Table1[[#This Row],[Complexidade]],Auxiliar!$D$4:$F$4,0)) -> #N/A | W63: =VLOOKUP(Table1[[#This Row],[Status]],Auxiliar!$B$16:$D$24,3,0)*Table1[[#This Row],[Estimação (horas)]] -> #N/A
B64: Pilar III | C64: Bens Imóveis - Input | D64: bu_esg_work.kt_chave_gloval; bu_esg_work.gloval_clase_energetica_dez23 | E64: n.a. | F64: ENERGY_CERTIFICATE_EST_INPUT | G64: NOMBRE_FREGUESIA | H64: =Table1[[#This Row],[Tabela]]&Table1[[#This Row],[Campo]] -> ENERGY_CERTIFICATE_EST_INPUTNOMBRE_FREGUESIA | I64: 6. Em implementação (re-especificação) | J64: =VLOOKUP(Table1[[#This Row],[Status]],Auxiliar!$B$16:$C$24,2,0) -> 7 | K64: 9. Teste de Integridade | L64: Sim | M64: Baixa | N64: 45688 | O64: =INDEX(Auxiliar!$D$5:$F$11,MATCH(Table1[[#This Row],[Tipologia_Testes]],Auxiliar!$B$5:$B$11,0),MATCH(Table1[[#This Row],[Complexidade]],Auxiliar!$D$4:$F$4,0)) -> #N/A | W64: =VLOOKUP(Table1[[#This Row],[Status]],Auxiliar!$B$16:$D$24,3,0)*Table1[[#This Row],[Estimação (horas)]] -> #N/A
B65: Pilar III | C65: Bens Imóveis - Input | D65: bu_esg_work.kt_chave_gloval; bu_esg_work.gloval_clase_energetica_dez23 | E65: n.a. | F65: ENERGY_CERTIFICATE_EST_INPUT | G65: LOCALIDADE | H65: =Table1[[#This Row],[Tabela]]&Table1[[#This Row],[Campo]] -> ENERGY_CERTIFICATE_EST_INPUTLOCALIDADE | I65: 6. Em implementação (re-especificação) | J65: =VLOOKUP(Table1[[#This Row],[Status]],Auxiliar!$B$16:$C$24,2,0) -> 7 | K65: 9. Teste de Integridade | L65: Sim | M65: Baixa | N65: 45688 | O65: =INDEX(Auxiliar!$D$5:$F$11,MATCH(Table1[[#This Row],[Tipologia_Testes]],Auxiliar!$B$5:$B$11,0),MATCH(Table1[[#This Row],[Complexidade]],Auxiliar!$D$4:$F$4,0)) -> #N/A | W65: =VLOOKUP(Table1[[#This Row],[Status]],Auxiliar!$B$16:$D$24,3,0)*Table1[[#This Row],[Estimação (horas)]] -> #N/A
... B97: Pilar III | C97: Bens Imóveis - Input | D97: bu_esg_work.kt_chave_gloval; bu_esg_work.gloval_clase_energetica_dez23 | E97: n.a. | F97: ENERGY_CERTIFICATE_EST_INPUT | G97: DATA_ENVIO | H97: =Table1[[#This Row],[Tabela]]&Table1[[#This Row],[Campo]] -> ENERGY_CERTIFICATE_EST_INPUTDATA_ENVIO | I97: 6. Em implementação (re-especificação) | J97: =VLOOKUP(Table1[[#This Row],[Status]],Auxiliar!$B$16:$C$24,2,0) -> 7 | K97: 9. Teste de Integridade | L97: Sim | M97: Baixa | N97: 45688 | O97: =INDEX(Auxiliar!$D$5:$F$11,MATCH(Table1[[#This Row],[Tipologia_Testes]],Auxiliar!$B$5:$B$11,0),MATCH(Table1[[#This Row],[Complexidade]],Auxiliar!$D$4:$F$4,0)) -> #N/A | W97: =VLOOKUP(Table1[[#This Row],[Status]],Auxiliar!$B$16:$D$24,3,0)*Table1[[#This Row],[Estimação (horas)]] -> #N/A
B98: Pilar III | C98: Bens Imóveis - Output | D98: cd_imv_out_trz_prc_bens_imv ; cd_imv_out_prc ; cd_imv_out_trz_cred_prc | E98: n.a. | F98: PROPERTY | G98: n.a. | H98: =Table1[[#This Row],[Tabela]]&Table1[[#This Row],[Campo]] -> PROPERTYn.a. | I98: 1. Concluído | J98: =VLOOKUP(Table1[[#This Row],[Status]],Auxiliar!$B$16:$C$24,2,0) -> 1 | K98: 1. Teste de universo | L98: Sim | M98: Alta | N98: 45505 | O98: =INDEX(Auxiliar!$D$5:$F$13,MATCH(Table1[[#This Row],[Tipologia_Testes]],Auxiliar!$B$5:$B$13,0),MATCH(Table1[[#This Row],[Complexidade]],Auxiliar!$D$4:$F$4,0)) -> 8 | P98: Gestão processual (validação igual à cd_imv_out_trz_prc_bens_imv) Modelo de Garantias Adjudicados (especificação igual à cd_imv_out_trz_prc_bens_imv) | Q98: HC | R98: 45261 | W98: =VLOOKUP(Table1[[#This Row],[Status]],Auxiliar!$B$16:$D$24,3,0)*Table1[[#This Row],[Estimação (horas)]] -> 8
