Workbook

Sheet Plano_V1
B6: Re-testes - input | D6: 0.2 | M6: =M7-M10 -> 0 | N6: =N7-N10 -> 0 | O6: =O7-O10 -> 0 | P6: =P7-P10 -> 0 | Q6: =Q7-Q10 -> 0 | R6: =R7-R10 -> 0 | S6: =S7-S10 -> 0 | T6: =T7-T10 -> 0 | ... FK6: =FK7-FK10 -> 0
B7: Re-testes - output | D7: =50%*25% -> 0.125 | L7: =AVERAGE(M7:EL7) -> 2.4923077 | M7: 3 | N7: 3 | O7: 3 | P7: 3 | Q7: 3 | R7: 2 | S7: 2 | T7: 2 | U7: 2 | V7: 2 | W7: 2 | X7: 2 | Y7: 2 | Z7: 2 | AA7: 2 | AB7: 2 | AC7: 2 | AD7: 1 | AE7: 1 | AF7: 1 | AG7: 3 | AH7: 3 | AI7: 3 | AJ7: 3 | AK7: 2 | AL7: 3 | AM7: 3 | AN7: 3 | AO7: 3 | AP7: 3 | AQ7: 2 | AR7: 2 | AS7: 2 | AT7: 0 | AU7: 1 | AV7: 1 | AW7: 0 | AX7: 1 | AY7: 1 | AZ7: 1 | BA7: 2 | BB7: 2 | BC7: 2 | BD7: 2 | BE7: 2 | BF7: 2 | BG7: 2 | BH7: 2 | BI7: 2 | BJ7: 2 | BK7: 2 | BL7: 2 | BM7: 2 | BN7: 2 | BO7: 2 | BP7: 3 | BQ7: 3 | BR7: 3 | BS7: 3 | BT7: 3 | BU7: 3 | BV7: 3 | BW7: 3 | BX7: 3 | BY7: 3 | BZ7: 3 | CA7: 3 | CB7: 3 | CC7: 3 | CD7: 3 | CE7: 3 | CF7: 3 | CG7: 3 | CH7: 3 | CI7: 3 | CJ7: 3 | CK7: 3 | CL7: 3 | CM7: 3 | CN7: 3 | CO7: 3 | CP7: 3 | CQ7: 3 | CR7: 3 | CS7: 3 | CT7: 3 | CU7: 3 | CV7: 3 | CW7: 3 | CX7: 3 | CY7: 3 | CZ7: 3 | DA7: 3 | DB7: 3 | DC7: 3 | DD7: 3 | DE7: 3 | DF7: 3 | DG7: 3 | DH7: 3 | DI7: 3 | DJ7: 3 | DK7: 3 | DL7: 3 | DM7: 3 | DN7: 2 | DO7: 3 | DP7: 3 | DQ7: 3 | DR7: 3 | DS7: 3 | DT7: 3 | DU7: 3 | DV7: 3 | DW7: 3 | DX7: 3 | DY7: 3 | DZ7: 3 | EA7: 3 | EB7: 3 | EC7: 3 | ED7: 3 | EE7: 3 | EF7: 3 | EG7: 3 | EH7: 3 | EI7: 0 | EJ7: 0 | EK7: 0 | EL7: 0 | EM7: 0 | EN7: 0 | EO7: 0 | EP7: 3 | EQ7: 3 | ER7: 3 | ES7: 3 | ET7: 3 | EU7: 3 | EV7: 3 | EW7: 3 | EX7: 3 | EY7: 3 | EZ7: 3 | FA7: 3 | FB7: 3 | FC7: 3 | FD7: 3 | FE7: 3 | FF7: 3 | FG7: 3 | FH7: 3 | FI7: 3 | FJ7: 3 | FK7: 3
M10: =SUBTOTAL(9,M14:M636) -> 3 | N10: =SUBTOTAL(9,N14:N636) -> 3 | O10: =SUBTOTAL(9,O14:O636) -> 3 | P10: =SUBTOTAL(9,P14:P636) -> 3 | Q10: =SUBTOTAL(9,Q14:Q636) -> 3 | R10: =SUBTOTAL(9,R14:R636) -> 2 | S10: =SUBTOTAL(9,S14:S636) -> 2 | T10: =SUBTOTAL(9,T14:T636) -> 2 | ... FK10: =SUBTOTAL(9,FK14:FK636) -> 3
M11: Julho | W11: Julho | AJ11: Agosto | BF11: Setembro | CA11: Outubro | CX11: Novembro | DS11: Dezembro | EO11: Janeiro
M12: =M13 -> 45474 | N12: =N13 -> 45475 | O12: =O13 -> 45476 | P12: =P13 -> 45477 | Q12: =Q13 -> 45478 | R12: =R13 -> 45481 | S12: =S13 -> 45482 | T12: =T13 -> 45483 | ... FK12: =FK13 -> 45688
B13: Âmbito | C13: Sub-âmbito | D13: Tipo de teste | E13: Tabela | F13: Campo | G13: Status | H13: Status2 | I13: Horas | J13: Dias | K13: Pendências | L13: Val | M13: 45474 | N13: =WORKDAY(M13,1) -> 45475 | O13: =WORKDAY(N13,1) -> 45476 | P13: =WORKDAY(O13,1) -> 45477 | Q13: =WORKDAY(P13,1) -> 45478 | R13: =WORKDAY(Q13,1) -> 45481 | S13: =WORKDAY(R13,1) -> 45482 | T13: =WORKDAY(S13,1) -> 45483 | U13: =WORKDAY(T13,1) -> 45484 | ... FK13: =WORKDAY(FJ13,1) -> 45688
B14: 1. Assessment | I14: =SUM(I15:I18) -> 280 | J14: =SUM(J15:J18) -> 35
B15: Pilar III | C15: Bens Imóveis | G15: 7. Por iniciar | I15: =J15*8 -> 40 | J15: 5 | L15: =J15-SUM(M15:FK15) -> 0 | W15: 1 | X15: 1 | Y15: 1 | Z15: 1 | AA15: 1
B16: Pilar III | C16: Modelo Verde | G16: 7. Por iniciar | I16: =J16*8 -> 80 | J16: 10 | L16: =J16-SUM(M16:FK16) -> 0 | R16: 2 | S16: 2 | T16: 2 | U16: 2 | V16: 2
B17: Pilar III | C17: Pilar III | G17: 7. Por iniciar | I17: =J17*8 -> 40 | J17: 5 | L17: =J17-SUM(M17:FK17) -> 0 | AB17: 1 | AC17: 1 | AD17: 1 | AE17: 1 | AF17: 0.5 | AG17: 0.5
B18: GD | C18: GD | G18: 7. Por iniciar | I18: =J18*8 -> 120 | J18: 15 | L18: =J18-SUM(M18:FK18) -> 0 | M18: 3 | N18: 3 | O18: 3 | P18: 3 | Q18: 3
B20: 2. Re-especificação | I20: =SUM(I21:I23) -> 120 | J20: =SUM(J21:J23) -> 15
B21: Pilar III | C21: Bens Imóveis | G21: 7. Por iniciar | I21: =J21*8 -> 40 | J21: 5 | L21: =J21-SUM(M21:FK21) -> 0 | W21: 0.5 | AB21: 0.5 | AG21: 0.5 | AL21: 0.5 | AQ21: 0.5 | AV21: 0.5 | BA21: 0.5 | BF21: 0.5 | BK21: 0.5 | BP21: 0.5
B22: Pilar III | C22: Modelo Verde | G22: 7. Por iniciar | I22: =J22*8 -> 40 | J22: 5 | L22: =J22-SUM(M22:FK22) -> 0 | W22: 0.5 | AB22: 0.5 | AG22: 0.5 | AL22: 0.5 | AQ22: 0.5 | AV22: 0.5 | BA22: 0.5 | BF22: 0.5 | BK22: 0.5 | BP22: 0.5
B23: Pilar III | C23: Pilar III | G23: 7. Por iniciar | I23: =J23*8 -> 40 | J23: 5 | L23: =J23-SUM(M23:FK23) -> 0 | BF23: 0.5 | BK23: 0.5 | BP23: 0.5 | BU23: 0.5 | BZ23: 0.5 | CE23: 0.5 | CJ23: 0.5 | CO23: 0.5 | CT23: 0.5 | CY23: 0.5
B25: 3. Testes / Re-testes | I25: =I26+I27+I42+I198+I362+I447 -> 1192.8125 | J25: =J26+J27+J42+J198+J362+J447 -> 151
B26: Testes Regressivos | G26: 7. Por iniciar | I26: =4*22 -> 88 | J26: =I26/8 -> 11 | L26: =J26-SUM(M26:FK26) -> 0 | AA26: 0.5 | AF26: 0.5 | AK26: 0.5 | AP26: 0.5 | AU26: 0.5 | AZ26: 0.5 | BE26: 0.5 | BJ26: 0.5 | BO26: 0.5 | BT26: 0.5 | BY26: 0.5 | CD26: 0.5 | CI26: 0.5 | CN26: 0.5 | CS26: 0.5 | CX26: 0.5 | DC26: 0.5 | DH26: 0.5 | DM26: 0.5 | DR26: 0.5 | DW26: 0.5 | EB26: 0.5
B27: Pilar III | C27: Bens Imóveis - Input | I27: =SUM(I28:I41) -> 0 | J27: =ROUNDUP(I27/8,0) -> 0 | L27: =J27-SUM(M27:FK27) -> -3 | X27: 0.5 | Y27: 0.5 | AC27: 0.5 | AG27: 1 | AH27: 0.5
A28: =E28&F28 -> cd_imv_inp_certif_estimativan.a. | B28: Pilar III | C28: Bens Imóveis - Input | D28: 1. Universo | E28: cd_imv_inp_certif_estimativa | F28: n.a. | G28: =INDEX(Auxiliar!$B$16:$B$24,MATCH(Plano_V1!H28,Auxiliar!$C$16:$C$24,0),1) -> #N/A | H28: =VLOOKUP(A28,'Aux - pivots1'!$A:$B,2,0) -> #N/A | I28: =SUMIFS(Table1[Estimação (horas)],Table1[Tabela],Plano_V1!E28,Table1[Campo],Plano_V1!F28) -> 0 | J28: =I28/8 -> 0 | K28: sem pendencia | L28: =J28-SUM(M28:FK28) -> 0
A29: =E29&F29 -> cd_imv_inp_certif_estimativacempbem | B29: Pilar III | C29: Bens Imóveis - Input | D29: 2. Campo | E29: cd_imv_inp_certif_estimativa | F29: cempbem | G29: =INDEX(Auxiliar!$B$16:$B$24,MATCH(Plano_V1!H29,Auxiliar!$C$16:$C$24,0),1) -> #N/A | H29: =VLOOKUP(A29,'Aux - pivots1'!$A:$B,2,0) -> #N/A | I29: =SUMIFS(Table1[Estimação (horas)],Table1[Tabela],Plano_V1!E29,Table1[Campo],Plano_V1!F29) -> 0 | J29: =I29/8 -> 0 | K29: sem pendencia | L29: =J29-SUM(M29:FK29) -> 0
A30: =E30&F30 -> cd_imv_inp_certif_estimativachave_encriptada | B30: Pilar III | C30: Bens Imóveis - Input | D30: 2. Campo | E30: cd_imv_inp_certif_estimativa | F30: chave_encriptada | G30: =INDEX(Auxiliar!$B$16:$B$24,MATCH(Plano_V1!H30,Auxiliar!$C$16:$C$24,0),1) -> #N/A | H30: =VLOOKUP(A30,'Aux - pivots1'!$A:$B,2,0) -> #N/A | I30: =SUMIFS(Table1[Estimação (horas)],Table1[Tabela],Plano_V1!E30,Table1[Campo],Plano_V1!F30) -> 0 | J30: =I30/8 -> 0 | K30: sem pendencia | L30: =J30-SUM(M30:FK30) -> 0
A31: =E31&F31 -> cd_imv_inp_certif_estimativackbalbem | B31: Pilar III | C31: Bens Imóveis - Input | D31: 2. Campo | E31: cd_imv_inp_certif_estimativa | F31: ckbalbem | G31: =INDEX(Auxiliar!$B$16:$B$24,MATCH(Plano_V1!H31,Auxiliar!$C$16:$C$24,0),1) -> #N/A | H31: =VLOOKUP(A31,'Aux - pivots1'!$A:$B,2,0) -> #N/A | I31: =SUMIFS(Table1[Estimação (horas)],Table1[Tabela],Plano_V1!E31,Table1[Campo],Plano_V1!F31) -> 0 | J31: =I31/8 -> 0 | K31: sem pendencia | L31: =J31-SUM(M31:FK31) -> 0
A32: =E32&F32 -> cd_imv_inp_certif_estimativackctabem | B32: Pilar III | C32: Bens Imóveis - Input | D32: 2. Campo | E32: cd_imv_inp_certif_estimativa | F32: ckctabem | G32: =INDEX(Auxiliar!$B$16:$B$24,MATCH(Plano_V1!H32,Auxiliar!$C$16:$C$24,0),1) -> #N/A | H32: =VLOOKUP(A32,'Aux - pivots1'!$A:$B,2,0) -> #N/A | I32: =SUMIFS(Table1[Estimação (horas)],Table1[Tabela],Plano_V1!E32,Table1[Campo],Plano_V1!F32) -> 0 | J32: =I32/8 -> 0 | K32: sem pendencia | L32: =J32-SUM(M32:FK32) -> 0
A33: =E33&F33 -> cd_imv_inp_certif_estimativackrefbem | B33: Pilar III | C33: Bens Imóveis - Input | D33: 2. Campo | E33: cd_imv_inp_certif_estimativa | F33: ckrefbem | G33: =INDEX(Auxiliar!$B$16:$B$24,MATCH(Plano_V1!H33,Auxiliar!$C$16:$C$24,0),1) -> #N/A | H33: =VLOOKUP(A33,'Aux - pivots1'!$A:$B,2,0) -> #N/A | I33: =SUMIFS(Table1[Estimação (horas)],Table1[Tabela],Plano_V1!E33,Table1[Campo],Plano_V1!F33) -> 0 | J33: =I33/8 -> 0 | K33: sem pendencia | L33: =J33-SUM(M33:FK33) -> 0
A34: =E34&F34 -> cd_imv_inp_certif_estimativadata_extraccao_info | B34: Pilar III | C34: Bens Imóveis - Input | D34: 2. Campo | E34: cd_imv_inp_certif_estimativa | F34: data_extraccao_info | G34: =INDEX(Auxiliar!$B$16:$B$24,MATCH(Plano_V1!H34,Auxiliar!$C$16:$C$24,0),1) -> #N/A | H34: =VLOOKUP(A34,'Aux - pivots1'!$A:$B,2,0) -> #N/A | I34: =SUMIFS(Table1[Estimação (horas)],Table1[Tabela],Plano_V1!E34,Table1[Campo],Plano_V1!F34) -> 0 | J34: =I34/8 -> 0 | K34: sem pendencia | L34: =J34-SUM(M34:FK34) -> 0
A35: =E35&F35 -> cd_imv_inp_certif_estimativaepc | B35: Pilar III | C35: Bens Imóveis - Input | D35: 2. Campo | E35: cd_imv_inp_certif_estimativa | F35: epc | G35: =INDEX(Auxiliar!$B$16:$B$24,MATCH(Plano_V1!H35,Auxiliar!$C$16:$C$24,0),1) -> #N/A | H35: =VLOOKUP(A35,'Aux - pivots1'!$A:$B,2,0) -> #N/A | I35: =SUMIFS(Table1[Estimação (horas)],Table1[Tabela],Plano_V1!E35,Table1[Campo],Plano_V1!F35) -> 0 | J35: =I35/8 -> 0 | K35: sem pendencia | L35: =J35-SUM(M35:FK35) -> 0
A36: =E36&F36 -> cd_imv_inp_certif_estimativafornecedor | B36: Pilar III | C36: Bens Imóveis - Input | D36: 2. Campo | E36: cd_imv_inp_certif_estimativa | F36: fornecedor | G36: =INDEX(Auxiliar!$B$16:$B$24,MATCH(Plano_V1!H36,Auxiliar!$C$16:$C$24,0),1) -> #N/A | H36: =VLOOKUP(A36,'Aux - pivots1'!$A:$B,2,0) -> #N/A | I36: =SUMIFS(Table1[Estimação (horas)],Table1[Tabela],Plano_V1!E36,Table1[Campo],Plano_V1!F36) -> 0 | J36: =I36/8 -> 0 | K36: sem pendencia | L36: =J36-SUM(M36:FK36) -> 0
A37: =E37&F37 -> cd_imv_inp_certif_estimativametodo_info | B37: Pilar III | C37: Bens Imóveis - Input | D37: 2. Campo | E37: cd_imv_inp_certif_estimativa | F37: metodo_info | G37: =INDEX(Auxiliar!$B$16:$B$24,MATCH(Plano_V1!H37,Auxiliar!$C$16:$C$24,0),1) -> #N/A | H37: =VLOOKUP(A37,'Aux - pivots1'!$A:$B,2,0) -> #N/A | I37: =SUMIFS(Table1[Estimação (horas)],Table1[Tabela],Plano_V1!E37,Table1[Campo],Plano_V1!F37) -> 0 | J37: =I37/8 -> 0 | K37: sem pendencia | L37: =J37-SUM(M37:FK37) -> 0
A38: =E38&F38 -> cd_imv_inp_certif_estimativascore_qualidade | B38: Pilar III | C38: Bens Imóveis - Input | D38: 2. Campo | E38: cd_imv_inp_certif_estimativa | F38: score_qualidade | G38: =INDEX(Auxiliar!$B$16:$B$24,MATCH(Plano_V1!H38,Auxiliar!$C$16:$C$24,0),1) -> #N/A | H38: =VLOOKUP(A38,'Aux - pivots1'!$A:$B,2,0) -> #N/A | I38: =SUMIFS(Table1[Estimação (horas)],Table1[Tabela],Plano_V1!E38,Table1[Campo],Plano_V1!F38) -> 0 | J38: =I38/8 -> 0 | K38: sem pendencia | L38: =J38-SUM(M38:FK38) -> 0
A39: =E39&F39 -> cd_imv_inp_certif_estimativavlr_cnsm_ano | B39: Pilar III | C39: Bens Imóveis - Input | D39: 2. Campo | E39: cd_imv_inp_certif_estimativa | F39: vlr_cnsm_ano | G39: =INDEX(Auxiliar!$B$16:$B$24,MATCH(Plano_V1!H39,Auxiliar!$C$16:$C$24,0),1) -> #N/A | H39: =VLOOKUP(A39,'Aux - pivots1'!$A:$B,2,0) -> #N/A | I39: =SUMIFS(Table1[Estimação (horas)],Table1[Tabela],Plano_V1!E39,Table1[Campo],Plano_V1!F39) -> 0 | J39: =I39/8 -> 0 | K39: sem pendencia | L39: =J39-SUM(M39:FK39) -> 0
A40: =E40&F40 -> cd_imv_inp_certif_estimativavlr_emss_ano | B40: Pilar III | C40: Bens Imóveis - Input | D40: 2. Campo | E40: cd_imv_inp_certif_estimativa | F40: vlr_emss_ano | G40: =INDEX(Auxiliar!$B$16:$B$24,MATCH(Plano_V1!H40,Auxiliar!$C$16:$C$24,0),1) -> #N/A | H40: =VLOOKUP(A40,'Aux - pivots1'!$A:$B,2,0) -> #N/A | I40: =SUMIFS(Table1[Estimação (horas)],Table1[Tabela],Plano_V1!E40,Table1[Campo],Plano_V1!F40) -> 0 | J40: =I40/8 -> 0 | K40: sem pendencia | L40: =J40-SUM(M40:FK40) -> 0
A41: =E41&F41 -> Re-testesn.a. | B41: Pilar III | C41: Bens Imóveis - Input | D41: 2. Campo | E41: Re-testes | F41: n.a. | G41: 7. Por iniciar | I41: =SUM(I28:I40)*D6 -> 0 | J41: =I41/8 -> 0 | K41: sem pendencia | L41: =J41-SUM(M41:FK41) -> 0
A42: =E42&F42 | B42: Pilar III | C42: Bens Imóveis - Output | I42: =SUM(I43:I197) -> 0 | J42: =ROUNDUP(I42/8,0) -> 0 | L42: =J42-SUM(M42:FK42) -> -100 | AH42: 0.5 | AI42: 1 | AJ42: 1 | AM42: 1 | AN42: 1 | AO42: 1 | AP42: 0.5 | AR42: 1 | AS42: 2 | AU42: 0.5 | AX42: 1 | AY42: 1 | AZ42: 0.5 | BA42: 1 | BB42: 2 | BC42: 2 | BD42: 2 | BE42: 1.5 | BF42: 0.5 | BG42: 2 | BH42: 2 | BI42: 2 | BJ42: 1.5 | BK42: 0.5 | BL42: 2 | BM42: 2 | BN42: 2 | BO42: 1.5 | BP42: 1.5 | BQ42: 2 | BR42: 2 | BS42: 2 | BT42: 2 | BU42: 2 | BV42: 2 | BW42: 2 | BX42: 2 | BY42: 2 | BZ42: 2 | CA42: 2 | CB42: 2 | CC42: 2 | CD42: 2 | CE42: 2 | CF42: 2 | CG42: 2 | CH42: 2 | CI42: 2 | CJ42: 2 | CK42: 2 | CL42: 2 | CM42: 2 | CN42: 2 | CO42: 2 | CP42: 2 | CQ42: 2 | CR42: 2 | CS42: 2 | CT42: 2 | CU42: 2
A43: =E43&F43 -> cd_imv_out_prcn.a. | B43: Pilar III | C43: Bens Imóveis - Output | D43: 1. Universo | E43: cd_imv_out_prc | F43: n.a. | G43: =INDEX(Auxiliar!$B$16:$B$24,MATCH(Plano_V1!H43,Auxiliar!$C$16:$C$24,0),1) -> #N/A | H43: =VLOOKUP(A43,'Aux - pivots1'!$A:$B,2,0) -> #N/A | I43: =SUMIFS(Table1[Estimação (horas)],Table1[Tabela],Plano_V1!E43,Table1[Campo],Plano_V1!F43) -> 0 | J43: =I43/8 -> 0 | K43: cd_imv_out_trz_cred_prc | L43: =J43-SUM(M43:FK43) -> 0
A44: =E44&F44 -> cd_imv_out_prccempresa | B44: Pilar III | C44: Bens Imóveis - Output | D44: 2. Campo | E44: cd_imv_out_prc | F44: cempresa | G44: =INDEX(Auxiliar!$B$16:$B$24,MATCH(Plano_V1!H44,Auxiliar!$C$16:$C$24,0),1) -> #N/A | H44: =VLOOKUP(A44,'Aux - pivots1'!$A:$B,2,0) -> #N/A | I44: =SUMIFS(Table1[Estimação (horas)],Table1[Tabela],Plano_V1!E44,Table1[Campo],Plano_V1!F44) -> 0 | J44: =I44/8 -> 0 | K44: cd_imv_out_trz_cred_prc | L44: =J44-SUM(M44:FK44) -> 0
A45: =E45&F45 -> cd_imv_out_prcckbalcao | B45: Pilar III | C45: Bens Imóveis - Output | D45: 2. Campo | E45: cd_imv_out_prc | F45: ckbalcao | G45: =INDEX(Auxiliar!$B$16:$B$24,MATCH(Plano_V1!H45,Auxiliar!$C$16:$C$24,0),1) -> #N/A | H45: =VLOOKUP(A45,'Aux - pivots1'!$A:$B,2,0) -> #N/A | I45: =SUMIFS(Table1[Estimação (horas)],Table1[Tabela],Plano_V1!E45,Table1[Campo],Plano_V1!F45) -> 0 | J45: =I45/8 -> 0 | K45: cd_imv_out_trz_cred_prc | L45: =J45-SUM(M45:FK45) -> 0
A46: =E46&F46 -> cd_imv_out_prccknumcta | B46: Pilar III | C46: Bens Imóveis - Output | D46: 2. Campo | E46: cd_imv_out_prc | F46: cknumcta | G46: =INDEX(Auxiliar!$B$16:$B$24,MATCH(Plano_V1!H46,Auxiliar!$C$16:$C$24,0),1) -> #N/A | H46: =VLOOKUP(A46,'Aux - pivots1'!$A:$B,2,0) -> #N/A | I46: =SUMIFS(Table1[Estimação (horas)],Table1[Tabela],Plano_V1!E46,Table1[Campo],Plano_V1!F46) -> 0 | J46: =I46/8 -> 0 | K46: cd_imv_out_trz_cred_prc | L46: =J46-SUM(M46:FK46) -> 0
A47: =E47&F47 -> cd_imv_out_prccod_estd_prcs | B47: Pilar III | C47: Bens Imóveis - Output | D47: 2. Campo | E47: cd_imv_out_prc | F47: cod_estd_prcs | G47: =INDEX(Auxiliar!$B$16:$B$24,MATCH(Plano_V1!H47,Auxiliar!$C$16:$C$24,0),1) -> #N/A | H47: =VLOOKUP(A47,'Aux - pivots1'!$A:$B,2,0) -> #N/A | I47: 0 | J47: =I47/8 -> 0 | K47: cd_imv_out_trz_cred_prc | L47: =J47-SUM(M47:FK47) -> 0
A48: =E48&F48 -> cd_imv_out_prccod_grt | B48: Pilar III | C48: Bens Imóveis - Output | D48: 2. Campo | E48: cd_imv_out_prc | F48: cod_grt | G48: =INDEX(Auxiliar!$B$16:$B$24,MATCH(Plano_V1!H48,Auxiliar!$C$16:$C$24,0),1) -> #N/A | H48: =VLOOKUP(A48,'Aux - pivots1'!$A:$B,2,0) -> #N/A | I48: =SUMIFS(Table1[Estimação (horas)],Table1[Tabela],Plano_V1!E48,Table1[Campo],Plano_V1!F48) -> 0 | J48: =I48/8 -> 0 | K48: cd_imv_out_trz_cred_prc | L48: =J48-SUM(M48:FK48) -> 0
A49: =E49&F49 -> cd_imv_out_prccod_moeda | B49: Pilar III | C49: Bens Imóveis - Output | D49: 2. Campo | E49: cd_imv_out_prc | F49: cod_moeda | G49: =INDEX(Auxiliar!$B$16:$B$24,MATCH(Plano_V1!H49,Auxiliar!$C$16:$C$24,0),1) -> #N/A | H49: =VLOOKUP(A49,'Aux - pivots1'!$A:$B,2,0) -> #N/A | I49: =SUMIFS(Table1[Estimação (horas)],Table1[Tabela],Plano_V1!E49,Table1[Campo],Plano_V1!F49) -> 0 | J49: =I49/8 -> 0 | K49: cd_imv_out_trz_cred_prc | L49: =J49-SUM(M49:FK49) -> 0
A50: =E50&F50 -> cd_imv_out_prccod_observacao | B50: Pilar III | C50: Bens Imóveis - Output | D50: 2. Campo | E50: cd_imv_out_prc | F50: cod_observacao | G50: =INDEX(Auxiliar!$B$16:$B$24,MATCH(Plano_V1!H50,Auxiliar!$C$16:$C$24,0),1) -> #N/A | H50: =VLOOKUP(A50,'Aux - pivots1'!$A:$B,2,0) -> #N/A | I50: =SUMIFS(Table1[Estimação (horas)],Table1[Tabela],Plano_V1!E50,Table1[Campo],Plano_V1!F50) -> 0 | J50: =I50/8 -> 0 | K50: cd_imv_out_trz_cred_prc | L50: =J50-SUM(M50:FK50) -> 0
A51: =E51&F51 -> cd_imv_out_prccod_prd_grnt | B51: Pilar III | C51: Bens Imóveis - Output | D51: 2. Campo | E51: cd_imv_out_prc | F51: cod_prd_grnt | G51: =INDEX(Auxiliar!$B$16:$B$24,MATCH(Plano_V1!H51,Auxiliar!$C$16:$C$24,0),1) -> #N/A | H51: =VLOOKUP(A51,'Aux - pivots1'!$A:$B,2,0) -> #N/A | I51: =SUMIFS(Table1[Estimação (horas)],Table1[Tabela],Plano_V1!E51,Table1[Campo],Plano_V1!F51) -> 0 | J51: =I51/8 -> 0 | K51: cd_imv_out_trz_cred_prc | L51: =J51-SUM(M51:FK51) -> 0
A52: =E52&F52 -> cd_imv_out_prccod_sprd_grnt | B52: Pilar III | C52: Bens Imóveis - Output | D52: 2. Campo | E52: cd_imv_out_prc | F52: cod_sprd_grnt | G52: =INDEX(Auxiliar!$B$16:$B$24,MATCH(Plano_V1!H52,Auxiliar!$C$16:$C$24,0),1) -> #N/A | H52: =VLOOKUP(A52,'Aux - pivots1'!$A:$B,2,0) -> #N/A | I52: =SUMIFS(Table1[Estimação (horas)],Table1[Tabela],Plano_V1!E52,Table1[Campo],Plano_V1!F52) -> 0 | J52: =I52/8 -> 0 | K52: cd_imv_out_trz_cred_prc | L52: =J52-SUM(M52:FK52) -> 0
A53: =E53&F53 -> cd_imv_out_prccod_tipo | B53: Pilar III | C53: Bens Imóveis - Output | D53: 2. Campo | E53: cd_imv_out_prc | F53: cod_tipo | G53: =INDEX(Auxiliar!$B$16:$B$24,MATCH(Plano_V1!H53,Auxiliar!$C$16:$C$24,0),1) -> #N/A | H53: =VLOOKUP(A53,'Aux - pivots1'!$A:$B,2,0) -> #N/A | I53: =SUMIFS(Table1[Estimação (horas)],Table1[Tabela],Plano_V1!E53,Table1[Campo],Plano_V1!F53) -> 0 | J53: =I53/8 -> 0 | K53: cd_imv_out_trz_cred_prc | L53: =J53-SUM(M53:FK53) -> 0
A54: =E54&F54 -> cd_imv_out_prccomp_id_gar | B54: Pilar III | C54: Bens Imóveis - Output | D54: 2. Campo | E54: cd_imv_out_prc | F54: comp_id_gar | G54: =INDEX(Auxiliar!$B$16:$B$24,MATCH(Plano_V1!H54,Auxiliar!$C$16:$C$24,0),1) -> #N/A | H54: =VLOOKUP(A54,'Aux - pivots1'!$A:$B,2,0) -> #N/A | I54: =SUMIFS(Table1[Estimação (horas)],Table1[Tabela],Plano_V1!E54,Table1[Campo],Plano_V1!F54) -> 0 | J54: =I54/8 -> 0 | K54: cd_imv_out_trz_cred_prc | L54: =J54-SUM(M54:FK54) -> 0
A55: =E55&F55 -> cd_imv_out_prcdata_inicio | B55: Pilar III | C55: Bens Imóveis - Output | D55: 2. Campo | E55: cd_imv_out_prc | F55: data_inicio | G55: =INDEX(Auxiliar!$B$16:$B$24,MATCH(Plano_V1!H55,Auxiliar!$C$16:$C$24,0),1) -> #N/A | H55: =VLOOKUP(A55,'Aux - pivots1'!$A:$B,2,0) -> #N/A | I55: =SUMIFS(Table1[Estimação (horas)],Table1[Tabela],Plano_V1!E55,Table1[Campo],Plano_V1!F55) -> 0 | J55: =I55/8 -> 0 | K55: cd_imv_out_trz_cred_prc | L55: =J55-SUM(M55:FK55) -> 0
A56: =E56&F56 -> cd_imv_out_prcdata_vcmt | B56: Pilar III | C56: Bens Imóveis - Output | D56: 2. Campo | E56: cd_imv_out_prc | F56: data_vcmt | G56: =INDEX(Auxiliar!$B$16:$B$24,MATCH(Plano_V1!H56,Auxiliar!$C$16:$C$24,0),1) -> #N/A | H56: =VLOOKUP(A56,'Aux - pivots1'!$A:$B,2,0) -> #N/A | I56: =SUMIFS(Table1[Estimação (horas)],Table1[Tabela],Plano_V1!E56,Table1[Campo],Plano_V1!F56) -> 0 | J56: =I56/8 -> 0 | K56: cd_imv_out_trz_cred_prc | L56: =J56-SUM(M56:FK56) -> 0
A57: =E57&F57 -> cd_imv_out_prcmontante_eur | B57: Pilar III | C57: Bens Imóveis - Output | D57: 2. Campo | E57: cd_imv_out_prc | F57: montante_eur | G57: =INDEX(Auxiliar!$B$16:$B$24,MATCH(Plano_V1!H57,Auxiliar!$C$16:$C$24,0),1) -> #N/A | H57: =VLOOKUP(A57,'Aux - pivots1'!$A:$B,2,0) -> #N/A | I57: 0 | J57: =I57/8 -> 0 | K57: cd_imv_out_trz_cred_prc | L57: =J57-SUM(M57:FK57) -> 0
A58: =E58&F58 -> cd_imv_out_prcmontante_org | B58: Pilar III | C58: Bens Imóveis - Output | D58: 2. Campo | E58: cd_imv_out_prc | F58: montante_org | G58: =INDEX(Auxiliar!$B$16:$B$24,MATCH(Plano_V1!H58,Auxiliar!$C$16:$C$24,0),1) -> #N/A | H58: =VLOOKUP(A58,'Aux - pivots1'!$A:$B,2,0) -> #N/A | I58: 0 | J58: =I58/8 -> 0 | K58: cd_imv_out_trz_cred_prc | L58: =J58-SUM(M58:FK58) -> 0
A59: =E59&F59 -> cd_imv_out_prcorigem | B59: Pilar III | C59: Bens Imóveis - Output | D59: 2. Campo | E59: cd_imv_out_prc | F59: origem | G59: =INDEX(Auxiliar!$B$16:$B$24,MATCH(Plano_V1!H59,Auxiliar!$C$16:$C$24,0),1) -> #N/A | H59: =VLOOKUP(A59,'Aux - pivots1'!$A:$B,2,0) -> #N/A | I59: =SUMIFS(Table1[Estimação (horas)],Table1[Tabela],Plano_V1!E59,Table1[Campo],Plano_V1!F59) -> 0 | J59: =I59/8 -> 0 | K59: cd_imv_out_trz_cred_prc | L59: =J59-SUM(M59:FK59) -> 0
A60: =E60&F60 -> cd_imv_out_prcref_date | B60: Pilar III | C60: Bens Imóveis - Output | D60: 2. Campo | E60: cd_imv_out_prc | F60: ref_date | G60: =INDEX(Auxiliar!$B$16:$B$24,MATCH(Plano_V1!H60,Auxiliar!$C$16:$C$24,0),1) -> #N/A | H60: =VLOOKUP(A60,'Aux - pivots1'!$A:$B,2,0) -> #N/A | I60: =SUMIFS(Table1[Estimação (horas)],Table1[Tabela],Plano_V1!E60,Table1[Campo],Plano_V1!F60) -> 0 | J60: =I60/8 -> 0 | K60: cd_imv_out_trz_cred_prc | L60: =J60-SUM(M60:FK60) -> 0
A61: =E61&F61 -> cd_imv_out_trz_cred_prcn.a. | B61: Pilar III | C61: Bens Imóveis - Output | D61: 1. Universo | E61: cd_imv_out_trz_cred_prc | F61: n.a. | G61: =INDEX(Auxiliar!$B$16:$B$24,MATCH(Plano_V1!H61,Auxiliar!$C$16:$C$24,0),1) -> #N/A | H61: =VLOOKUP(A61,'Aux - pivots1'!$A:$B,2,0) -> #N/A | I61: =SUMIFS(Table1[Estimação (horas)],Table1[Tabela],Plano_V1!E61,Table1[Campo],Plano_V1!F61) -> 0 | J61: =I61/8 -> 0 | K61: sem pendencia | L61: =J61-SUM(M61:FK61) -> 0
A62: =E62&F62 -> cd_imv_out_trz_cred_prccempresa | B62: Pilar III | C62: Bens Imóveis - Output | D62: 2. Campo | E62: cd_imv_out_trz_cred_prc | F62: cempresa | G62: =INDEX(Auxiliar!$B$16:$B$24,MATCH(Plano_V1!H62,Auxiliar!$C$16:$C$24,0),1) -> #N/A | H62: =VLOOKUP(A62,'Aux - pivots1'!$A:$B,2,0) -> #N/A | I62: =SUMIFS(Table1[Estimação (horas)],Table1[Tabela],Plano_V1!E62,Table1[Campo],Plano_V1!F62) -> 0 | J62: =I62/8 -> 0 | K62: sem pendencia | L62: =J62-SUM(M62:FK62) -> 0
A63: =E63&F63 -> cd_imv_out_trz_cred_prccempresp | B63: Pilar III | C63: Bens Imóveis - Output | D63: 2. Campo | E63: cd_imv_out_trz_cred_prc | F63: cempresp | G63: =INDEX(Auxiliar!$B$16:$B$24,MATCH(Plano_V1!H63,Auxiliar!$C$16:$C$24,0),1) -> #N/A | H63: =VLOOKUP(A63,'Aux - pivots1'!$A:$B,2,0) -> #N/A | I63: =SUMIFS(Table1[Estimação (horas)],Table1[Tabela],Plano_V1!E63,Table1[Campo],Plano_V1!F63) -> 0 | J63: =I63/8 -> 0 | K63: sem pendencia | L63: =J63-SUM(M63:FK63) -> 0
A64: =E64&F64 -> cd_imv_out_trz_cred_prcckbalcao | B64: Pilar III | C64: Bens Imóveis - Output | D64: 2. Campo | E64: cd_imv_out_trz_cred_prc | F64: ckbalcao | G64: =INDEX(Auxiliar!$B$16:$B$24,MATCH(Plano_V1!H64,Auxiliar!$C$16:$C$24,0),1) -> #N/A | H64: =VLOOKUP(A64,'Aux - pivots1'!$A:$B,2,0) -> #N/A | I64: =SUMIFS(Table1[Estimação (horas)],Table1[Tabela],Plano_V1!E64,Table1[Campo],Plano_V1!F64) -> 0 | J64: =I64/8 -> 0 | K64: sem pendencia | L64: =J64-SUM(M64:FK64) -> 0
A65: =E65&F65 -> cd_imv_out_trz_cred_prcckbalres | B65: Pilar III | C65: Bens Imóveis - Output | D65: 2. Campo | E65: cd_imv_out_trz_cred_prc | F65: ckbalres | G65: =INDEX(Auxiliar!$B$16:$B$24,MATCH(Plano_V1!H65,Auxiliar!$C$16:$C$24,0),1) -> #N/A | H65: =VLOOKUP(A65,'Aux - pivots1'!$A:$B,2,0) -> #N/A | I65: =SUMIFS(Table1[Estimação (horas)],Table1[Tabela],Plano_V1!E65,Table1[Campo],Plano_V1!F65) -> 0 | J65: =I65/8 -> 0 | K65: sem pendencia | L65: =J65-SUM(M65:FK65) -> 0
A66: =E66&F66 -> cd_imv_out_trz_cred_prcckctares | B66: Pilar III | C66: Bens Imóveis - Output | D66: 2. Campo | E66: cd_imv_out_trz_cred_prc | F66: ckctares | G66: =INDEX(Auxiliar!$B$16:$B$24,MATCH(Plano_V1!H66,Auxiliar!$C$16:$C$24,0),1) -> #N/A | H66: =VLOOKUP(A66,'Aux - pivots1'!$A:$B,2,0) -> #N/A | I66: =SUMIFS(Table1[Estimação (horas)],Table1[Tabela],Plano_V1!E66,Table1[Campo],Plano_V1!F66) -> 0 | J66: =I66/8 -> 0 | K66: sem pendencia | L66: =J66-SUM(M66:FK66) -> 0
A67: =E67&F67 -> cd_imv_out_trz_cred_prccknumcta | B67: Pilar III | C67: Bens Imóveis - Output | D67: 2. Campo | E67: cd_imv_out_trz_cred_prc | F67: cknumcta | G67: =INDEX(Auxiliar!$B$16:$B$24,MATCH(Plano_V1!H67,Auxiliar!$C$16:$C$24,0),1) -> #N/A | H67: =VLOOKUP(A67,'Aux - pivots1'!$A:$B,2,0) -> #N/A | I67: =SUMIFS(Table1[Estimação (horas)],Table1[Tabela],Plano_V1!E67,Table1[Campo],Plano_V1!F67) -> 0 | J67: =I67/8 -> 0 | K67: sem pendencia | L67: =J67-SUM(M67:FK67) -> 0
A68: =E68&F68 -> cd_imv_out_trz_cred_prcckrefresp | B68: Pilar III | C68: Bens Imóveis - Output | D68: 2. Campo | E68: cd_imv_out_trz_cred_prc | F68: ckrefresp | G68: =INDEX(Auxiliar!$B$16:$B$24,MATCH(Plano_V1!H68,Auxiliar!$C$16:$C$24,0),1) -> #N/A | H68: =VLOOKUP(A68,'Aux - pivots1'!$A:$B,2,0) -> #N/A | I68: =SUMIFS(Table1[Estimação (horas)],Table1[Tabela],Plano_V1!E68,Table1[Campo],Plano_V1!F68) -> 0 | J68: =I68/8 -> 0 | K68: sem pendencia | L68: =J68-SUM(M68:FK68) -> 0
A69: =E69&F69 -> cd_imv_out_trz_cred_prccod_fnld | B69: Pilar III | C69: Bens Imóveis - Output | D69: 2. Campo | E69: cd_imv_out_trz_cred_prc | F69: cod_fnld | G69: =INDEX(Auxiliar!$B$16:$B$24,MATCH(Plano_V1!H69,Auxiliar!$C$16:$C$24,0),1) -> #N/A | H69: =VLOOKUP(A69,'Aux - pivots1'!$A:$B,2,0) -> #N/A | I69: =SUMIFS(Table1[Estimação (horas)],Table1[Tabela],Plano_V1!E69,Table1[Campo],Plano_V1!F69) -> 0 | J69: =I69/8 -> 0 | K69: sem pendencia | L69: =J69-SUM(M69:FK69) -> 0
A70: =E70&F70 -> cd_imv_out_trz_cred_prccod_ocupacao | B70: Pilar III | C70: Bens Imóveis - Output | D70: 2. Campo | E70: cd_imv_out_trz_cred_prc | F70: cod_ocupacao | G70: =INDEX(Auxiliar!$B$16:$B$24,MATCH(Plano_V1!H70,Auxiliar!$C$16:$C$24,0),1) -> #N/A | H70: =VLOOKUP(A70,'Aux - pivots1'!$A:$B,2,0) -> #N/A | I70: =SUMIFS(Table1[Estimação (horas)],Table1[Tabela],Plano_V1!E70,Table1[Campo],Plano_V1!F70) -> 0 | J70: =I70/8 -> 0 | K70: sem pendencia | L70: =J70-SUM(M70:FK70) -> 0
A71: =E71&F71 -> cd_imv_out_trz_cred_prccod_prd_resp | B71: Pilar III | C71: Bens Imóveis - Output | D71: 2. Campo | E71: cd_imv_out_trz_cred_prc | F71: cod_prd_resp | G71: =INDEX(Auxiliar!$B$16:$B$24,MATCH(Plano_V1!H71,Auxiliar!$C$16:$C$24,0),1) -> #N/A | H71: =VLOOKUP(A71,'Aux - pivots1'!$A:$B,2,0) -> #N/A | I71: =SUMIFS(Table1[Estimação (horas)],Table1[Tabela],Plano_V1!E71,Table1[Campo],Plano_V1!F71) -> 0 | J71: =I71/8 -> 0 | K71: sem pendencia | L71: =J71-SUM(M71:FK71) -> 0
A72: =E72&F72 -> cd_imv_out_trz_cred_prccod_sit | B72: Pilar III | C72: Bens Imóveis - Output | D72: 2. Campo | E72: cd_imv_out_trz_cred_prc | F72: cod_sit | G72: =INDEX(Auxiliar!$B$16:$B$24,MATCH(Plano_V1!H72,Auxiliar!$C$16:$C$24,0),1) -> #N/A | H72: =VLOOKUP(A72,'Aux - pivots1'!$A:$B,2,0) -> #N/A | I72: 0 | J72: =I72/8 -> 0 | K72: sem pendencia | L72: =J72-SUM(M72:FK72) -> 0
A73: =E73&F73 -> cd_imv_out_trz_cred_prccod_sprd_resp | B73: Pilar III | C73: Bens Imóveis - Output | D73: 2. Campo | E73: cd_imv_out_trz_cred_prc | F73: cod_sprd_resp | G73: =INDEX(Auxiliar!$B$16:$B$24,MATCH(Plano_V1!H73,Auxiliar!$C$16:$C$24,0),1) -> #N/A | H73: =VLOOKUP(A73,'Aux - pivots1'!$A:$B,2,0) -> #N/A | I73: =SUMIFS(Table1[Estimação (horas)],Table1[Tabela],Plano_V1!E73,Table1[Campo],Plano_V1!F73) -> 0 | J73: =I73/8 -> 0 | K73: sem pendencia | L73: =J73-SUM(M73:FK73) -> 0
A74: =E74&F74 -> cd_imv_out_trz_cred_prccomp_id_gar | B74: Pilar III | C74: Bens Imóveis - Output | D74: 2. Campo | E74: cd_imv_out_trz_cred_prc | F74: comp_id_gar | G74: =INDEX(Auxiliar!$B$16:$B$24,MATCH(Plano_V1!H74,Auxiliar!$C$16:$C$24,0),1) -> #N/A | H74: =VLOOKUP(A74,'Aux - pivots1'!$A:$B,2,0) -> #N/A | I74: =SUMIFS(Table1[Estimação (horas)],Table1[Tabela],Plano_V1!E74,Table1[Campo],Plano_V1!F74) -> 0 | J74: =I74/8 -> 0 | K74: sem pendencia | L74: =J74-SUM(M74:FK74) -> 0
A75: =E75&F75 -> cd_imv_out_trz_cred_prcdata_fim | B75: Pilar III | C75: Bens Imóveis - Output | D75: 2. Campo | E75: cd_imv_out_trz_cred_prc | F75: data_fim | G75: =INDEX(Auxiliar!$B$16:$B$24,MATCH(Plano_V1!H75,Auxiliar!$C$16:$C$24,0),1) -> #N/A | H75: =VLOOKUP(A75,'Aux - pivots1'!$A:$B,2,0) -> #N/A | I75: =SUMIFS(Table1[Estimação (horas)],Table1[Tabela],Plano_V1!E75,Table1[Campo],Plano_V1!F75) -> 0 | J75: =I75/8 -> 0 | K75: sem pendencia | L75: =J75-SUM(M75:FK75) -> 0
A76: =E76&F76 -> cd_imv_out_trz_cred_prcdata_inicio | B76: Pilar III | C76: Bens Imóveis - Output | D76: 2. Campo | E76: cd_imv_out_trz_cred_prc | F76: data_inicio | G76: =INDEX(Auxiliar!$B$16:$B$24,MATCH(Plano_V1!H76,Auxiliar!$C$16:$C$24,0),1) -> #N/A | H76: =VLOOKUP(A76,'Aux - pivots1'!$A:$B,2,0) -> #N/A | I76: =SUMIFS(Table1[Estimação (horas)],Table1[Tabela],Plano_V1!E76,Table1[Campo],Plano_V1!F76) -> 0 | J76: =I76/8 -> 0 | K76: sem pendencia | L76: =J76-SUM(M76:FK76) -> 0
A77: =E77&F77 -> cd_imv_out_trz_cred_prcdata_vcmt | B77: Pilar III | C77: Bens Imóveis - Output | D77: 2. Campo | E77: cd_imv_out_trz_cred_prc | F77: data_vcmt | G77: =INDEX(Auxiliar!$B$16:$B$24,MATCH(Plano_V1!H77,Auxiliar!$C$16:$C$24,0),1) -> #N/A | H77: =VLOOKUP(A77,'Aux - pivots1'!$A:$B,2,0) -> #N/A | I77: =SUMIFS(Table1[Estimação (horas)],Table1[Tabela],Plano_V1!E77,Table1[Campo],Plano_V1!F77) -> 0 | J77: =I77/8 -> 0 | K77: sem pendencia | L77: =J77-SUM(M77:FK77) -> 0
A78: =E78&F78 -> cd_imv_out_trz_cred_prcidetgar | B78: Pilar III | C78: Bens Imóveis - Output | D78: 2. Campo | E78: cd_imv_out_trz_cred_prc | F78: idetgar | G78: =INDEX(Auxiliar!$B$16:$B$24,MATCH(Plano_V1!H78,Auxiliar!$C$16:$C$24,0),1) -> #N/A | H78: =VLOOKUP(A78,'Aux - pivots1'!$A:$B,2,0) -> #N/A | I78: 0 | J78: =I78/8 -> 0 | K78: sem pendencia | L78: =J78-SUM(M78:FK78) -> 0
A79: =E79&F79 -> cd_imv_out_trz_cred_prcnum_prop | B79: Pilar III | C79: Bens Imóveis - Output | D79: 2. Campo | E79: cd_imv_out_trz_cred_prc | F79: num_prop | G79: =INDEX(Auxiliar!$B$16:$B$24,MATCH(Plano_V1!H79,Auxiliar!$C$16:$C$24,0),1) -> #N/A | H79: =VLOOKUP(A79,'Aux - pivots1'!$A:$B,2,0) -> #N/A | I79: 0 | J79: =I79/8 -> 0 | K79: sem pendencia | L79: =J79-SUM(M79:FK79) -> 0
A80: =E80&F80 -> cd_imv_out_trz_cred_prcorigem | B80: Pilar III | C80: Bens Imóveis - Output | D80: 2. Campo | E80: cd_imv_out_trz_cred_prc | F80: origem | G80: =INDEX(Auxiliar!$B$16:$B$24,MATCH(Plano_V1!H80,Auxiliar!$C$16:$C$24,0),1) -> #N/A | H80: =VLOOKUP(A80,'Aux - pivots1'!$A:$B,2,0) -> #N/A | I80: =SUMIFS(Table1[Estimação (horas)],Table1[Tabela],Plano_V1!E80,Table1[Campo],Plano_V1!F80) -> 0 | J80: =I80/8 -> 0 | K80: sem pendencia | L80: =J80-SUM(M80:FK80) -> 0
A81: =E81&F81 -> cd_imv_out_trz_cred_prcref_date | B81: Pilar III | C81: Bens Imóveis - Output | D81: 2. Campo | E81: cd_imv_out_trz_cred_prc | F81: ref_date | G81: =INDEX(Auxiliar!$B$16:$B$24,MATCH(Plano_V1!H81,Auxiliar!$C$16:$C$24,0),1) -> #N/A | H81: =VLOOKUP(A81,'Aux - pivots1'!$A:$B,2,0) -> #N/A | I81: =SUMIFS(Table1[Estimação (horas)],Table1[Tabela],Plano_V1!E81,Table1[Campo],Plano_V1!F81) -> 0 | J81: =I81/8 -> 0 | K81: sem pendencia | L81: =J81-SUM(M81:FK81) -> 0
A82: =E82&F82 -> cd_imv_out_trz_prc_bens_imvn.a. | B82: Pilar III | C82: Bens Imóveis - Output | D82: 1. Universo | E82: cd_imv_out_trz_prc_bens_imv | F82: n.a. | G82: =INDEX(Auxiliar!$B$16:$B$24,MATCH(Plano_V1!H82,Auxiliar!$C$16:$C$24,0),1) -> #N/A | H82: =VLOOKUP(A82,'Aux - pivots1'!$A:$B,2,0) -> #N/A | I82: =SUMIFS(Table1[Estimação (horas)],Table1[Tabela],Plano_V1!E82,Table1[Campo],Plano_V1!F82) -> 0 | J82: =I82/8 -> 0 | K82: cd_imv_out_trz_cred_prc | L82: =J82-SUM(M82:FK82) -> 0
A83: =E83&F83 -> cd_imv_out_trz_prc_bens_imvcempbem | B83: Pilar III | C83: Bens Imóveis - Output | D83: 2. Campo | E83: cd_imv_out_trz_prc_bens_imv | F83: cempbem | G83: =INDEX(Auxiliar!$B$16:$B$24,MATCH(Plano_V1!H83,Auxiliar!$C$16:$C$24,0),1) -> #N/A | H83: =VLOOKUP(A83,'Aux - pivots1'!$A:$B,2,0) -> #N/A | I83: =SUMIFS(Table1[Estimação (horas)],Table1[Tabela],Plano_V1!E83,Table1[Campo],Plano_V1!F83) -> 0 | J83: =I83/8 -> 0 | K83: cd_imv_out_trz_cred_prc | L83: =J83-SUM(M83:FK83) -> 0
A84: =E84&F84 -> cd_imv_out_trz_prc_bens_imvcempresa | B84: Pilar III | C84: Bens Imóveis - Output | D84: 2. Campo | E84: cd_imv_out_trz_prc_bens_imv | F84: cempresa | G84: =INDEX(Auxiliar!$B$16:$B$24,MATCH(Plano_V1!H84,Auxiliar!$C$16:$C$24,0),1) -> #N/A | H84: =VLOOKUP(A84,'Aux - pivots1'!$A:$B,2,0) -> #N/A | I84: =SUMIFS(Table1[Estimação (horas)],Table1[Tabela],Plano_V1!E84,Table1[Campo],Plano_V1!F84) -> 0 | J84: =I84/8 -> 0 | K84: cd_imv_out_trz_cred_prc | L84: =J84-SUM(M84:FK84) -> 0
A85: =E85&F85 -> cd_imv_out_trz_prc_bens_imvckbalbem | B85: Pilar III | C85: Bens Imóveis - Output | D85: 2. Campo | E85: cd_imv_out_trz_prc_bens_imv | F85: ckbalbem | G85: =INDEX(Auxiliar!$B$16:$B$24,MATCH(Plano_V1!H85,Auxiliar!$C$16:$C$24,0),1) -> #N/A | H85: =VLOOKUP(A85,'Aux - pivots1'!$A:$B,2,0) -> #N/A | I85: =SUMIFS(Table1[Estimação (horas)],Table1[Tabela],Plano_V1!E85,Table1[Campo],Plano_V1!F85) -> 0 | J85: =I85/8 -> 0 | K85: cd_imv_out_trz_cred_prc | L85: =J85-SUM(M85:FK85) -> 0
A86: =E86&F86 -> cd_imv_out_trz_prc_bens_imvckbalcao | B86: Pilar III | C86: Bens Imóveis - Output | D86: 2. Campo | E86: cd_imv_out_trz_prc_bens_imv | F86: ckbalcao | G86: =INDEX(Auxiliar!$B$16:$B$24,MATCH(Plano_V1!H86,Auxiliar!$C$16:$C$24,0),1) -> #N/A | H86: =VLOOKUP(A86,'Aux - pivots1'!$A:$B,2,0) -> #N/A | I86: =SUMIFS(Table1[Estimação (horas)],Table1[Tabela],Plano_V1!E86,Table1[Campo],Plano_V1!F86) -> 0 | J86: =I86/8 -> 0 | K86: cd_imv_out_trz_cred_prc | L86: =J86-SUM(M86:FK86) -> 0
A87: =E87&F87 -> cd_imv_out_trz_prc_bens_imvckctabem | B87: Pilar III | C87: Bens Imóveis - Output | D87: 2. Campo | E87: cd_imv_out_trz_prc_bens_imv | F87: ckctabem | G87: =INDEX(Auxiliar!$B$16:$B$24,MATCH(Plano_V1!H87,Auxiliar!$C$16:$C$24,0),1) -> #N/A | H87: =VLOOKUP(A87,'Aux - pivots1'!$A:$B,2,0) -> #N/A | I87: =SUMIFS(Table1[Estimação (horas)],Table1[Tabela],Plano_V1!E87,Table1[Campo],Plano_V1!F87) -> 0 | J87: =I87/8 -> 0 | K87: cd_imv_out_trz_cred_prc | L87: =J87-SUM(M87:FK87) -> 0
A88: =E88&F88 -> cd_imv_out_trz_prc_bens_imvcknumcta | B88: Pilar III | C88: Bens Imóveis - Output | D88: 2. Campo | E88: cd_imv_out_trz_prc_bens_imv | F88: cknumcta | G88: =INDEX(Auxiliar!$B$16:$B$24,MATCH(Plano_V1!H88,Auxiliar!$C$16:$C$24,0),1) -> #N/A | H88: =VLOOKUP(A88,'Aux - pivots1'!$A:$B,2,0) -> #N/A | I88: =SUMIFS(Table1[Estimação (horas)],Table1[Tabela],Plano_V1!E88,Table1[Campo],Plano_V1!F88) -> 0 | J88: =I88/8 -> 0 | K88: cd_imv_out_trz_cred_prc | L88: =J88-SUM(M88:FK88) -> 0
A89: =E89&F89 -> cd_imv_out_trz_prc_bens_imvckrefbem | B89: Pilar III | C89: Bens Imóveis - Output | D89: 2. Campo | E89: cd_imv_out_trz_prc_bens_imv | F89: ckrefbem | G89: =INDEX(Auxiliar!$B$16:$B$24,MATCH(Plano_V1!H89,Auxiliar!$C$16:$C$24,0),1) -> #N/A | H89: =VLOOKUP(A89,'Aux - pivots1'!$A:$B,2,0) -> #N/A | I89: =SUMIFS(Table1[Estimação (horas)],Table1[Tabela],Plano_V1!E89,Table1[Campo],Plano_V1!F89) -> 0 | J89: =I89/8 -> 0 | K89: cd_imv_out_trz_cred_prc | L89: =J89-SUM(M89:FK89) -> 0
A90: =E90&F90 -> cd_imv_out_trz_prc_bens_imvcomp_id_gar | B90: Pilar III | C90: Bens Imóveis - Output | D90: 2. Campo | E90: cd_imv_out_trz_prc_bens_imv | F90: comp_id_gar | G90: =INDEX(Auxiliar!$B$16:$B$24,MATCH(Plano_V1!H90,Auxiliar!$C$16:$C$24,0),1) -> #N/A | H90: =VLOOKUP(A90,'Aux - pivots1'!$A:$B,2,0) -> #N/A | I90: =SUMIFS(Table1[Estimação (horas)],Table1[Tabela],Plano_V1!E90,Table1[Campo],Plano_V1!F90) -> 0 | J90: =I90/8 -> 0 | K90: cd_imv_out_trz_cred_prc | L90: =J90-SUM(M90:FK90) -> 0
A91: =E91&F91 -> cd_imv_out_trz_prc_bens_imvdata_assc | B91: Pilar III | C91: Bens Imóveis - Output | D91: 2. Campo | E91: cd_imv_out_trz_prc_bens_imv | F91: data_assc | G91: =INDEX(Auxiliar!$B$16:$B$24,MATCH(Plano_V1!H91,Auxiliar!$C$16:$C$24,0),1) -> #N/A | H91: =VLOOKUP(A91,'Aux - pivots1'!$A:$B,2,0) -> #N/A | I91: 0 | J91: =I91/8 -> 0 | K91: cd_imv_out_trz_cred_prc | L91: =J91-SUM(M91:FK91) -> 0
A92: =E92&F92 -> cd_imv_out_trz_prc_bens_imvflg_adj | B92: Pilar III | C92: Bens Imóveis - Output | D92: 2. Campo | E92: cd_imv_out_trz_prc_bens_imv | F92: flg_adj | G92: =INDEX(Auxiliar!$B$16:$B$24,MATCH(Plano_V1!H92,Auxiliar!$C$16:$C$24,0),1) -> #N/A | H92: =VLOOKUP(A92,'Aux - pivots1'!$A:$B,2,0) -> #N/A | I92: =SUMIFS(Table1[Estimação (horas)],Table1[Tabela],Plano_V1!E92,Table1[Campo],Plano_V1!F92) -> 0 | J92: =I92/8 -> 0 | K92: cd_imv_out_trz_cred_prc | L92: =J92-SUM(M92:FK92) -> 0
A93: =E93&F93 -> cd_imv_out_trz_prc_bens_imvflg_col | B93: Pilar III | C93: Bens Imóveis - Output | D93: 2. Campo | E93: cd_imv_out_trz_prc_bens_imv | F93: flg_col | G93: =INDEX(Auxiliar!$B$16:$B$24,MATCH(Plano_V1!H93,Auxiliar!$C$16:$C$24,0),1) -> #N/A | H93: =VLOOKUP(A93,'Aux - pivots1'!$A:$B,2,0) -> #N/A | I93: =SUMIFS(Table1[Estimação (horas)],Table1[Tabela],Plano_V1!E93,Table1[Campo],Plano_V1!F93) -> 0 | J93: =I93/8 -> 0 | K93: cd_imv_out_trz_cred_prc | L93: =J93-SUM(M93:FK93) -> 0
A94: =E94&F94 -> cd_imv_out_trz_prc_bens_imvflg_fin | B94: Pilar III | C94: Bens Imóveis - Output | D94: 2. Campo | E94: cd_imv_out_trz_prc_bens_imv | F94: flg_fin | G94: =INDEX(Auxiliar!$B$16:$B$24,MATCH(Plano_V1!H94,Auxiliar!$C$16:$C$24,0),1) -> #N/A | H94: =VLOOKUP(A94,'Aux - pivots1'!$A:$B,2,0) -> #N/A | I94: =SUMIFS(Table1[Estimação (horas)],Table1[Tabela],Plano_V1!E94,Table1[Campo],Plano_V1!F94) -> 0 | J94: =I94/8 -> 0 | K94: cd_imv_out_trz_cred_prc | L94: =J94-SUM(M94:FK94) -> 0
A95: =E95&F95 -> cd_imv_out_trz_prc_bens_imvflg_pro | B95: Pilar III | C95: Bens Imóveis - Output | D95: 2. Campo | E95: cd_imv_out_trz_prc_bens_imv | F95: flg_pro | G95: =INDEX(Auxiliar!$B$16:$B$24,MATCH(Plano_V1!H95,Auxiliar!$C$16:$C$24,0),1) -> #N/A | H95: =VLOOKUP(A95,'Aux - pivots1'!$A:$B,2,0) -> #N/A | I95: =SUMIFS(Table1[Estimação (horas)],Table1[Tabela],Plano_V1!E95,Table1[Campo],Plano_V1!F95) -> 0 | J95: =I95/8 -> 0 | K95: cd_imv_out_trz_cred_prc | L95: =J95-SUM(M95:FK95) -> 0
A96: =E96&F96 -> cd_imv_out_trz_prc_bens_imvorigem | B96: Pilar III | C96: Bens Imóveis - Output | D96: 2. Campo | E96: cd_imv_out_trz_prc_bens_imv | F96: origem | G96: =INDEX(Auxiliar!$B$16:$B$24,MATCH(Plano_V1!H96,Auxiliar!$C$16:$C$24,0),1) -> #N/A | H96: =VLOOKUP(A96,'Aux - pivots1'!$A:$B,2,0) -> #N/A | I96: =SUMIFS(Table1[Estimação (horas)],Table1[Tabela],Plano_V1!E96,Table1[Campo],Plano_V1!F96) -> 0 | J96: =I96/8 -> 0 | K96: cd_imv_out_trz_cred_prc | L96: =J96-SUM(M96:FK96) -> 0
A97: =E97&F97 -> cd_imv_out_trz_prc_bens_imvref_date | B97: Pilar III | C97: Bens Imóveis - Output | D97: 2. Campo | E97: cd_imv_out_trz_prc_bens_imv | F97: ref_date | G97: =INDEX(Auxiliar!$B$16:$B$24,MATCH(Plano_V1!H97,Auxiliar!$C$16:$C$24,0),1) -> #N/A | H97: =VLOOKUP(A97,'Aux - pivots1'!$A:$B,2,0) -> #N/A | I97: =SUMIFS(Table1[Estimação (horas)],Table1[Tabela],Plano_V1!E97,Table1[Campo],Plano_V1!F97) -> 0 | J97: =I97/8 -> 0 | K97: cd_imv_out_trz_cred_prc | L97: =J97-SUM(M97:FK97) -> 0
A98: =E98&F98 -> cd_imv_out_bensn.a. | B98: Pilar III | C98: Bens Imóveis - Output | D98: 1. Universo | E98: cd_imv_out_bens | F98: n.a. | G98: =INDEX(Auxiliar!$B$16:$B$24,MATCH(Plano_V1!H98,Auxiliar!$C$16:$C$24,0),1) -> #N/A | H98: =VLOOKUP(A98,'Aux - pivots1'!$A:$B,2,0) -> #N/A | I98: =SUMIFS(Table1[Estimação (horas)],Table1[Tabela],Plano_V1!E98,Table1[Campo],Plano_V1!F98) -> 0 | J98: =I98/8 -> 0 | K98: cd_imv_out_trz_prc_bens_imv ; cd_imv_out_prc ; cd_imv_out_trz_cred_prc | L98: =J98-SUM(M98:FK98) -> 0
A99: =E99&F99 -> cd_imv_out_bensano_construcao | B99: Pilar III | C99: Bens Imóveis - Output | D99: 2. Campo | E99: cd_imv_out_bens | F99: ano_construcao | G99: =INDEX(Auxiliar!$B$16:$B$24,MATCH(Plano_V1!H99,Auxiliar!$C$16:$C$24,0),1) -> #N/A | H99: =VLOOKUP(A99,'Aux - pivots1'!$A:$B,2,0) -> #N/A | I99: 0 | J99: =I99/8 -> 0 | K99: cd_imv_out_trz_prc_bens_imv ; cd_imv_out_prc ; cd_imv_out_trz_cred_prc | L99: =J99-SUM(M99:FK99) -> 0
A100: =E100&F100 -> cd_imv_out_bensarea_util | B100: Pilar III | C100: Bens Imóveis - Output | D100: 2. Campo | E100: cd_imv_out_bens | F100: area_util | G100: =INDEX(Auxiliar!$B$16:$B$24,MATCH(Plano_V1!H100,Auxiliar!$C$16:$C$24,0),1) -> #N/A | H100: =VLOOKUP(A100,'Aux - pivots1'!$A:$B,2,0) -> #N/A | I100: =SUMIFS(Table1[Estimação (horas)],Table1[Tabela],Plano_V1!E100,Table1[Campo],Plano_V1!F100) -> 0 | J100: =I100/8 -> 0 | K100: cd_imv_out_trz_prc_bens_imv ; cd_imv_out_prc ; cd_imv_out_trz_cred_prc | L100: =J100-SUM(M100:FK100) -> 0
A101: =E101&F101 -> cd_imv_out_benscempbem | B101: Pilar III | C101: Bens Imóveis - Output | D101: 2. Campo | E101: cd_imv_out_bens | F101: cempbem | G101: =INDEX(Auxiliar!$B$16:$B$24,MATCH(Plano_V1!H101,Auxiliar!$C$16:$C$24,0),1) -> #N/A | H101: =VLOOKUP(A101,'Aux - pivots1'!$A:$B,2,0) -> #N/A | I101: =SUMIFS(Table1[Estimação (horas)],Table1[Tabela],Plano_V1!E101,Table1[Campo],Plano_V1!F101) -> 0 | J101: =I101/8 -> 0 | K101: cd_imv_out_trz_prc_bens_imv ; cd_imv_out_prc ; cd_imv_out_trz_cred_prc | L101: =J101-SUM(M101:FK101) -> 0
A102: =E102&F102 -> cd_imv_out_bensckbalbem | B102: Pilar III | C102: Bens Imóveis - Output | D102: 2. Campo | E102: cd_imv_out_bens | F102: ckbalbem | G102: =INDEX(Auxiliar!$B$16:$B$24,MATCH(Plano_V1!H102,Auxiliar!$C$16:$C$24,0),1) -> #N/A | H102: =VLOOKUP(A102,'Aux - pivots1'!$A:$B,2,0) -> #N/A | I102: =SUMIFS(Table1[Estimação (horas)],Table1[Tabela],Plano_V1!E102,Table1[Campo],Plano_V1!F102) -> 0 | J102: =I102/8 -> 0 | K102: cd_imv_out_trz_prc_bens_imv ; cd_imv_out_prc ; cd_imv_out_trz_cred_prc | L102: =J102-SUM(M102:FK102) -> 0
A103: =E103&F103 -> cd_imv_out_bensckctabem | B103: Pilar III | C103: Bens Imóveis - Output | D103: 2. Campo | E103: cd_imv_out_bens | F103: ckctabem | G103: =INDEX(Auxiliar!$B$16:$B$24,MATCH(Plano_V1!H103,Auxiliar!$C$16:$C$24,0),1) -> #N/A | H103: =VLOOKUP(A103,'Aux - pivots1'!$A:$B,2,0) -> #N/A | I103: =SUMIFS(Table1[Estimação (horas)],Table1[Tabela],Plano_V1!E103,Table1[Campo],Plano_V1!F103) -> 0 | J103: =I103/8 -> 0 | K103: cd_imv_out_trz_prc_bens_imv ; cd_imv_out_prc ; cd_imv_out_trz_cred_prc | L103: =J103-SUM(M103:FK103) -> 0
A104: =E104&F104 -> cd_imv_out_bensckrefbem | B104: Pilar III | C104: Bens Imóveis - Output | D104: 2. Campo | E104: cd_imv_out_bens | F104: ckrefbem | G104: =INDEX(Auxiliar!$B$16:$B$24,MATCH(Plano_V1!H104,Auxiliar!$C$16:$C$24,0),1) -> #N/A | H104: =VLOOKUP(A104,'Aux - pivots1'!$A:$B,2,0) -> #N/A | I104: =SUMIFS(Table1[Estimação (horas)],Table1[Tabela],Plano_V1!E104,Table1[Campo],Plano_V1!F104) -> 0 | J104: =I104/8 -> 0 | K104: cd_imv_out_trz_prc_bens_imv ; cd_imv_out_prc ; cd_imv_out_trz_cred_prc | L104: =J104-SUM(M104:FK104) -> 0
A105: =E105&F105 -> cd_imv_out_benscod_art_matr | B105: Pilar III | C105: Bens Imóveis - Output | D105: 2. Campo | E105: cd_imv_out_bens | F105: cod_art_matr | G105: =INDEX(Auxiliar!$B$16:$B$24,MATCH(Plano_V1!H105,Auxiliar!$C$16:$C$24,0),1) -> #N/A | H105: =VLOOKUP(A105,'Aux - pivots1'!$A:$B,2,0) -> #N/A | I105: =SUMIFS(Table1[Estimação (horas)],Table1[Tabela],Plano_V1!E105,Table1[Campo],Plano_V1!F105) -> 0 | J105: =I105/8 -> 0 | K105: cd_imv_out_trz_prc_bens_imv ; cd_imv_out_prc ; cd_imv_out_trz_cred_prc | L105: =J105-SUM(M105:FK105) -> 0
A106: =E106&F106 -> cd_imv_out_benscod_avl | B106: Pilar III | C106: Bens Imóveis - Output | D106: 2. Campo | E106: cd_imv_out_bens | F106: cod_avl | G106: =INDEX(Auxiliar!$B$16:$B$24,MATCH(Plano_V1!H106,Auxiliar!$C$16:$C$24,0),1) -> #N/A | H106: =VLOOKUP(A106,'Aux - pivots1'!$A:$B,2,0) -> #N/A | I106: =SUMIFS(Table1[Estimação (horas)],Table1[Tabela],Plano_V1!E106,Table1[Campo],Plano_V1!F106) -> 0 | J106: =I106/8 -> 0 | K106: cd_imv_out_trz_prc_bens_imv ; cd_imv_out_prc ; cd_imv_out_trz_cred_prc | L106: =J106-SUM(M106:FK106) -> 0
A107: =E107&F107 -> cd_imv_out_benscod_bem | B107: Pilar III | C107: Bens Imóveis - Output | D107: 2. Campo | E107: cd_imv_out_bens | F107: cod_bem | G107: =INDEX(Auxiliar!$B$16:$B$24,MATCH(Plano_V1!H107,Auxiliar!$C$16:$C$24,0),1) -> #N/A | H107: =VLOOKUP(A107,'Aux - pivots1'!$A:$B,2,0) -> #N/A | I107: 0 | J107: =I107/8 -> 0 | K107: cd_imv_out_trz_prc_bens_imv ; cd_imv_out_prc ; cd_imv_out_trz_cred_prc | L107: =J107-SUM(M107:FK107) -> 0
A108: =E108&F108 -> cd_imv_out_benscod_disconf | B108: Pilar III | C108: Bens Imóveis - Output | D108: 2. Campo | E108: cd_imv_out_bens | F108: cod_disconf | G108: =INDEX(Auxiliar!$B$16:$B$24,MATCH(Plano_V1!H108,Auxiliar!$C$16:$C$24,0),1) -> #N/A | H108: =VLOOKUP(A108,'Aux - pivots1'!$A:$B,2,0) -> #N/A | I108: =SUMIFS(Table1[Estimação (horas)],Table1[Tabela],Plano_V1!E108,Table1[Campo],Plano_V1!F108) -> 0 | J108: =I108/8 -> 0 | K108: cd_imv_out_trz_prc_bens_imv ; cd_imv_out_prc ; cd_imv_out_trz_cred_prc | L108: =J108-SUM(M108:FK108) -> 0
A109: =E109&F109 -> cd_imv_out_benscod_fin_bem | B109: Pilar III | C109: Bens Imóveis - Output | D109: 2. Campo | E109: cd_imv_out_bens | F109: cod_fin_bem | G109: =INDEX(Auxiliar!$B$16:$B$24,MATCH(Plano_V1!H109,Auxiliar!$C$16:$C$24,0),1) -> #N/A | H109: =VLOOKUP(A109,'Aux - pivots1'!$A:$B,2,0) -> #N/A | I109: =SUMIFS(Table1[Estimação (horas)],Table1[Tabela],Plano_V1!E109,Table1[Campo],Plano_V1!F109) -> 0 | J109: =I109/8 -> 0 | K109: cd_imv_out_trz_prc_bens_imv ; cd_imv_out_prc ; cd_imv_out_trz_cred_prc | L109: =J109-SUM(M109:FK109) -> 0
...

Sheet 1. Status Resumo FY24
B6: 1. Sumário Executivo |31 de janeiro a 07 de fevereiro
B8: 1 | AG8: 1
C9: Resumo de entregas de Especificações | P9: Detalhe Packages planeados | X9: Highlights
E10: 0 | H10: 1 | L10: 4 | X10: 1. Resumo de especificações: Modelo de Bens Imóveis - Relativo aos requisitos de 2024, foi fechada e partilhada a especificação de 49 campos (conforme planeado), sendo 44 referentes a tabela de input da Gloval e 5 referentes à tabela de certificados. Modelo Verde - Relativo aos requisitos de 2024, foi fechada e partilhada a especificação de 1 campo referente à tabela de clientes (conforme planeado). - Relativo aos requisitos de 2025, foi fechada e partilhada a especificação de 20 campos referente à tabela de clientes (conforme planeado). Loan Tape - Relativo aos requisitos de 2025, foi fechada e partilhada a especificação de 20 campos referente à tabela de clientes (conforme planeado). Denote-se que relativo aos novos requisitos de FY 2025 estavam planeados a entrega de 68 campos ao longo das semanas. No entanto, na nova versão disponibilizada pela corporação verificámos que 2 campos dos partilhados na proposta tinham sido cancelados e foram adicionados 5 novos campos, que por sua vez, perfaz um total de 71 campos. O 1º package de campos foi especificado e partilhado como previsto. Na próxima semana será disponibilizado 30 campos (referentes aos packages 2 e 3). 2. Resumo de testes: Modelo de Bens Imóveis - Relativo aos requisitos de 2024, foi testado 1 campo (rácio NTC) na tabela de certificados (conforme planeado). Em virtude de terem sido verificadas incidências no mesmo, este será re-testado na próxima semana (após correção). Loan Tape - Relativo aos requisitos de 2024, foram testados 3 campos (conforme planeado) e não foram detetadas incidências. No entanto, é necessário re-especificar estes campos em virtude das alterações da nova versão do guia corporativo.
C11: Âmbito | E11: Entregas Semana Anterior | H11: Entregas Semana Atual | L11: Entregas Semana Seguinte | Q11: Dt. Prev. | R11: Req. FY25 | T11: Req. FY25 (atualiz.) | V11: Status
E12: Planeado | F12: Real | G12: ∆ | H12: Semana Ant. | I12: Planeado | J12: Real | K12: ∆ | L12: Semana Ant. | M12: Planeado | N12: Total | O12: 1 | P12: Package 1 | Q12: 27/jan | R12: 20 | T12: =+COUNTIFS('2. Status Detalhe Campos FY24'!$C:$C,"*Pilar*",'2. Status Detalhe Campos FY24'!$I:$I,"*"&O12&"*",'2. Status Detalhe Campos FY24'!T:T,"*Novo Plano*") -> 20 | V12: OK
C13: Modelo de Bens Imóveis | E13: 49 | F13: 49 | G13: =+F13-E13 -> 0 | H13: =+IF(G13<0,-G13,0) -> 0 | I13: 0 | J13: 0 | K13: =+J13-I13 -> 0 | L13: =+IF(K13<0,-K13,0) -> 0 | M13: =+COUNTIFS('2. Status Detalhe Campos FY24'!$C:$C,"*Bens Imóveis*",'2. Status Detalhe Campos FY24'!$I:$I,"*"&$L$10&"*") -> 0 | N13: =+M13+L13 -> 0 | O13: 2 | P13: Package 2 | Q13: 4/fev | R13: 15 | T13: =+COUNTIFS('2. Status Detalhe Campos FY24'!$C:$C,"*Pilar*",'2. Status Detalhe Campos FY24'!$I:$I,"*"&O13&"*",'2. Status Detalhe Campos FY24'!T:T,"*Novo Plano*") -> 14 | V13: OK
C14: Requisitos FY24 | E14: 49 | F14: 49 | G14: =+F14-E14 -> 0 | H14: =+IF(G14<0,-G14,0) -> 0 | I14: 0 | J14: 0 | K14: =+J14-I14 -> 0 | L14: =+IF(K14<0,-K14,0) -> 0 | M14: =+COUNTIFS('2. Status Detalhe Campos FY24'!$C:$C,"*Bens Imóveis*",'2. Status Detalhe Campos FY24'!$I:$I,"*"&$L$10&"*",'2. Status Detalhe Campos FY24'!T:T,"*anterior*") -> 0 | N14: =+M14+L14 -> 0 | O14: 3 | P14: Package 3 | Q14: 5/fev | R14: 14 | T14: =+COUNTIFS('2. Status Detalhe Campos FY24'!$C:$C,"*Pilar*",'2. Status Detalhe Campos FY24'!$I:$I,"*"&O14&"*",'2. Status Detalhe Campos FY24'!T:T,"*Novo Plano*") -> 16 | V14: OK
C15: Novos Requisitos FY25 | E15: 0 | F15: 0 | G15: =+F15-E15 -> 0 | H15: =+IF(G15<0,-G15,0) -> 0 | I15: 0 | J15: 0 | K15: =+J15-I15 -> 0 | L15: =+IF(K15<0,-K15,0) -> 0 | M15: =+COUNTIFS('2. Status Detalhe Campos FY24'!$C:$C,"*Bens Imóveis*",'2. Status Detalhe Campos FY24'!$I:$I,"*"&$L$10&"*",'2. Status Detalhe Campos FY24'!T:T,"*Novo Plano*") -> 0 | N15: =+M15+L15 -> 0 | O15: 4 | P15: Package 4 | Q15: 11/fev | R15: 13 | T15: =+COUNTIFS('2. Status Detalhe Campos FY24'!$C:$C,"*Pilar*",'2. Status Detalhe Campos FY24'!$I:$I,"*"&O15&"*",'2. Status Detalhe Campos FY24'!T:T,"*Novo Plano*") -> 14 | V15: Por Iniciar
C16: Modelo Verde | E16: 21 | F16: 21 | G16: =+F16-E16 -> 0 | H16: =+IF(G16<0,-G16,0) -> 0 | I16: 13 | J16: 13 | K16: =+J16-I16 -> 0 | L16: =+IF(K16<0,-K16,0) -> 0 | M16: =+COUNTIFS('2. Status Detalhe Campos FY24'!$C:$C,"*Verde*",'2. Status Detalhe Campos FY24'!$I:$I,"*"&$L$10&"*") -> 0 | N16: =+M16+L16 -> 0 | O16: 5 | P16: Package 5 | Q16: 17/fev | R16: 6 | T16: =+COUNTIFS('2. Status Detalhe Campos FY24'!$C:$C,"*Pilar*",'2. Status Detalhe Campos FY24'!$I:$I,"*"&O16&"*",'2. Status Detalhe Campos FY24'!T:T,"*Novo Plano*") -> 7 | V16: Por Iniciar
C17: Requisitos FY24 | E17: 1 | F17: 1 | G17: =+F17-E17 -> 0 | H17: =+IF(G17<0,-G17,0) -> 0 | I17: 8 | J17: 8 | K17: =+J17-I17 -> 0 | L17: =+IF(K17<0,-K17,0) -> 0 | M17: =+COUNTIFS('2. Status Detalhe Campos FY24'!$C:$C,"*Verde*",'2. Status Detalhe Campos FY24'!$I:$I,"*"&$L$10&"*",'2. Status Detalhe Campos FY24'!T:T,"*anterior*") -> 0 | N17: =+M17+L17 -> 0 | P17: Total | R17: =+SUM(R12:S16) -> 68 | T17: =+SUM(T12:T16) -> 71
C18: Novos Requisitos FY25 | E18: 20 | F18: 20 | G18: =+F18-E18 -> 0 | H18: =+IF(G18<0,-G18,0) -> 0 | I18: 5 | J18: 5 | K18: =+J18-I18 -> 0 | L18: =+IF(K18<0,-K18,0) -> 0 | M18: =+COUNTIFS('2. Status Detalhe Campos FY24'!$C:$C,"*Verde*",'2. Status Detalhe Campos FY24'!$I:$I,"*"&$L$10&"*",'2. Status Detalhe Campos FY24'!T:T,"*Novo Plano*") -> 0 | N18: =+M18+L18 -> 0
C19: Loan Tape | E19: 20 | F19: 20 | G19: =+F19-E19 -> 0 | H19: =+IF(G19<0,-G19,0) -> 0 | I19: 32 | J19: 32 | K19: =+J19-I19 -> 0 | L19: =+IF(K19<0,-K19,0) -> 0 | M19: =+COUNTIFS('2. Status Detalhe Campos FY24'!$C:$C,"*Pilar*",'2. Status Detalhe Campos FY24'!$I:$I,"*"&$L$10&"*") -> 14 | N19: =+M19+L19 -> 14
C20: Requisitos FY24 | E20: 0 | F20: 0 | G20: =+F20-E20 -> 0 | H20: =+IF(G20<0,-G20,0) -> 0 | I20: 2 | J20: 2 | K20: =+J20-I20 -> 0 | L20: =+IF(K20<0,-K20,0) -> 0 | M20: =+COUNTIFS('2. Status Detalhe Campos FY24'!$C:$C,"*Pilar*",'2. Status Detalhe Campos FY24'!$I:$I,"*"&$L$10&"*",'2. Status Detalhe Campos FY24'!T:T,"*anterior*") -> 0 | N20: =+M20+L20 -> 0
C21: Novos Requisitos FY25 | E21: 20 | F21: 20 | G21: =+F21-E21 -> 0 | H21: =+IF(G21<0,-G21,0) -> 0 | I21: 30 | J21: 30 | K21: =+J21-I21 -> 0 | L21: =+IF(K21<0,-K21,0) -> 0 | M21: =+COUNTIFS('2. Status Detalhe Campos FY24'!$C:$C,"*Pilar*",'2. Status Detalhe Campos FY24'!$I:$I,"*"&$L$10&"*",'2. Status Detalhe Campos FY24'!T:T,"*Novo Plano*") -> 14 | N21: =+M21+L21 -> 14
C22: Total | E22: 90 | F22: 90 | G22: 0 | H22: =+SUM(H13,H16,H19) -> 0 | I22: 45 | J22: 45 | K22: =+SUM(K13,K16,K19) -> 0 | L22: =+SUM(L13,L16,L19) -> 0 | M22: =+SUM(M13,M16,M19) -> 14 | N22: =+SUM(N13,N16,N19) -> 14
C24: Resumo de Testes
E25: 1 | I25: 1 | P25: 2
C26: Âmbito | E26: Semana Anterior | J26: Semana Atual | P26: Semana Seguinte
E27: Planeado | F27: Com Incidên. | G27: Sem Incidên. | H27: Re- Especif. | I27: ∆ | J27: Semana Ant. | K27: Planeado | L27: Com Incidên. | M27: Sem Incidên. | N27: Re- Especif. | O27: ∆ | P27: Semana Ant. | Q27: Planeado | R27: Total
C28: Modelo de Bens Imóveis | E28: 1 | F28: 1 | G28: 0 | H28: 0 | I28: 0 | J28: 1 | K28: 0 | L28: 0 | M28: 1 | N28: 0 | O28: =+SUM(J28:K28)-SUM(L28:N28) -> 0 | P28: 0 | Q28: =+COUNTIFS('2. Status Detalhe Campos FY24'!$C:$C,"*Bens Imóveis*",'2. Status Detalhe Campos FY24'!$J:$J,"*"&$P$25&"*") -> 0 | R28: =+Q28+P28 -> 0
C29: RequisItos FY24 | E29: 1 | F29: 1 | G29: 0 | H29: 0 | I29: 0 | J29: 1 | K29: 0 | L29: 0 | M29: 1 | N29: 0 | O29: =+SUM(J29:K29)-SUM(L29:N29) -> 0 | P29: =+IF(O29<0,-O29,0) -> 0 | Q29: =+COUNTIFS('2. Status Detalhe Campos FY24'!$C:$C,"*Bens Imóveis*",'2. Status Detalhe Campos FY24'!$J:$J,"*"&$P$25&"*",'2. Status Detalhe Campos FY24'!T:T,"*anterior*") -> 0 | R29: =+Q29+P29 -> 0
C30: Novos Requisitos FY25 | E30: 0 | F30: 0 | G30: 0 | H30: 0 | I30: 0 | J30: 0 | K30: 0 | L30: 0 | M30: 0 | N30: 0 | O30: =+SUM(J30:K30)-SUM(L30:N30) -> 0 | P30: =+IF(O30<0,-O30,0) -> 0 | Q30: =+COUNTIFS('2. Status Detalhe Campos FY24'!$C:$C,"*Bens Imóveis*",'2. Status Detalhe Campos FY24'!$J:$J,"*"&$P$25&"*",'2. Status Detalhe Campos FY24'!T:T,"*Novo Plano*") -> 0 | R30: =+Q30+P30 -> 0
C31: Modelo Verde | E31: 0 | F31: 0 | G31: 0 | H31: 0 | I31: 0 | J31: 0 | K31: 0 | L31: 0 | M31: 0 | N31: 0 | O31: =+SUM(J31:K31)-SUM(L31:N31) -> 0 | P31: =+IF(O31<0,-O31,0) -> 0 | Q31: =+COUNTIFS('2. Status Detalhe Campos FY24'!$C:$C,"*Verde*",'2. Status Detalhe Campos FY24'!$J:$J,"*"&$P$25&"*") -> 20 | R31: =+Q31+P31 -> 20
C32: RequisItos FY24 | E32: 0 | F32: 0 | G32: 0 | H32: 0 | I32: 0 | J32: 0 | K32: 0 | L32: 0 | M32: 0 | N32: 0 | O32: =+SUM(J32:K32)-SUM(L32:N32) -> 0 | P32: =+IF(O32<0,-O32,0) -> 0 | Q32: =+COUNTIFS('2. Status Detalhe Campos FY24'!$C:$C,"*Verde*",'2. Status Detalhe Campos FY24'!$J:$J,"*"&$P$25&"*",'2. Status Detalhe Campos FY24'!T:T,"*anterior*") -> 0 | R32: =+Q32+P32 -> 0
C33: Novos Requisitos FY25 | E33: 0 | F33: 0 | G33: 0 | H33: 0 | I33: 0 | J33: 0 | K33: 0 | L33: 0 | M33: 0 | N33: 0 | O33: =+SUM(J33:K33)-SUM(L33:N33) -> 0 | P33: =+IF(O33<0,-O33,0) -> 0 | Q33: =+COUNTIFS('2. Status Detalhe Campos FY24'!$C:$C,"*Verde*",'2. Status Detalhe Campos FY24'!$J:$J,"*"&$P$25&"*",'2. Status Detalhe Campos FY24'!T:T,"*Novo Plano*") -> 20 | R33: =+Q33+P33 -> 20
C34: Loan Tape | E34: 3 | F34: 0 | G34: 0 | H34: 3 | I34: 0 | J34: 0 | K34: 0 | L34: 0 | M34: 0 | N34: 0 | O34: =+SUM(J34:K34)-SUM(L34:N34) -> 0 | P34: =+IF(O34<0,-O34,0) -> 0 | Q34: =+COUNTIFS('2. Status Detalhe Campos FY24'!$C:$C,"*Pilar*",'2. Status Detalhe Campos FY24'!$J:$J,"*"&$P$25&"*") -> 0 | R34: =+Q34+P34 -> 0
C35: RequisItos FY24 | E35: 3 | F35: 0 | G35: 0 | H35: 3 | I35: 0 | J35: 0 | K35: 0 | L35: 0 | M35: 0 | N35: 0 | O35: =+SUM(J35:K35)-SUM(L35:N35) -> 0 | P35: =+IF(O35<0,-O35,0) -> 0 | Q35: =+COUNTIFS('2. Status Detalhe Campos FY24'!$C:$C,"*Pilar*",'2. Status Detalhe Campos FY24'!$J:$J,"*"&$P$25&"*",'2. Status Detalhe Campos FY24'!T:T,"*anterior*") -> 0 | R35: =+Q35+P35 -> 0
C36: Novos Requisitos FY25 | E36: 0 | F36: 0 | G36: 0 | H36: 0 | I36: 0 | J36: 0 | K36: 0 | L36: 0 | M36: 0 | N36: 0 | O36: =+SUM(J36:K36)-SUM(L36:N36) -> 0 | P36: =+IF(O36<0,-O36,0) -> 0 | Q36: =+COUNTIFS('2. Status Detalhe Campos FY24'!$C:$C,"*Pilar*",'2. Status Detalhe Campos FY24'!$J:$J,"*"&$P$25&"*",'2. Status Detalhe Campos FY24'!T:T,"*Novo Plano*") -> 0 | R36: =+Q36+P36 -> 0
C37: Total | E37: 4 | F37: 1 | G37: 0 | H37: 3 | I37: 0 | J37: 1 | K37: 0 | L37: =+SUM(L28,L31,L34) -> 0 | M37: =+SUM(M28,M31,M34) -> 1 | N37: =+SUM(N28,N31,N34) -> 0 | O37: =+SUM(O28,O31,O34) -> 0 | P37: =+SUM(P28,P31,P34) -> 0 | Q37: =+SUM(Q28,Q31,Q34) -> 20 | R37: =+SUM(R28,R31,R34) -> 20
B41: 1 | AG41: 1
B43: 1. Modelo de Bens Imóveis | G43: Bens Imóveis - Input | H43: Bens Imóveis - Output | I43: Modelo Verde - Input | J43: Modelo Verde - Output | K43: Pilar III
C46: Resumo | G46: Detalhe por Tabela | P46: Status (campos) | T46: 45688 | U46: =T46+7 -> 45695 | V46: ∆ | X46: Highlights
P47: 0. Cancelado | T47: =COUNTIFS('2. Status Detalhe Campos FY24'!$H$7:$H$731,'1. Status Resumo FY24'!$P47,'2. Status Detalhe Campos FY24'!$C$7:$C$731,'1. Status Resumo FY24'!$G$43,'2. Status Detalhe Campos FY24'!$D$7:$D$731,"2. Campo")+COUNTIFS('2. Status Detalhe Campos FY24'!$H$7:$H$731,'1. Status Resumo FY24'!$P47,'2. Status Detalhe Campos FY24'!$C$7:$C$731,'1. Status Resumo FY24'!$H$43,'2. Status Detalhe Campos FY24'!$D$7:$D$731,"2. Campo") -> 12 | U47: =COUNTIFS('2. Status Detalhe Campos FY24'!$G$7:$G$731,'1. Status Resumo FY24'!$P47,'2. Status Detalhe Campos FY24'!$C$7:$C$731,'1. Status Resumo FY24'!$G$43,'2. Status Detalhe Campos FY24'!$D$7:$D$731,"2. Campo")+COUNTIFS('2. Status Detalhe Campos FY24'!$G$7:$G$731,'1. Status Resumo FY24'!$P47,'2. Status Detalhe Campos FY24'!$C$7:$C$731,'1. Status Resumo FY24'!$H$43,'2. Status Detalhe Campos FY24'!$D$7:$D$731,"2. Campo") -> 12 | V47: =U47-T47 -> 0 | X47: 1. Gloval: - Os desenvolvimentos referente à Gloval serão entregues pela equipa de Tecnologia no dia 10/02. - Encontrámos uma solução com a equipa de IT que permite avançar com os testes dos campos da tabela de Certificados que são aprovisionados pela tabela de Input da Gloval (4 campos). Contudo, para testar o front e a tabela de Input será necessário obter os acessos ao mesmo. 2. Tabela de Certificados: - Adicionalmente, foi retestado e concluído o novo campo da tabela de certificados (rácio NTC).
P48: RequisItos FY24 | T48: =COUNTIFS('2. Status Detalhe Campos FY24'!$H$7:$H$731,'1. Status Resumo FY24'!$P47,'2. Status Detalhe Campos FY24'!$C$7:$C$731,'1. Status Resumo FY24'!$G$43,'2. Status Detalhe Campos FY24'!$D$7:$D$731,"2. Campo",'2. Status Detalhe Campos FY24'!$T$7:$T$731,"*Plano anterior*") +COUNTIFS('2. Status Detalhe Campos FY24'!$H$7:$H$731,'1. Status Resumo FY24'!$P47,'2. Status Detalhe Campos FY24'!$C$7:$C$731,'1. Status Resumo FY24'!$H$43,'2. Status Detalhe Campos FY24'!$D$7:$D$731,"2. Campo",'2. Status Detalhe Campos FY24'!$T$7:$T$731,"*Plano anterior*") -> 12 | U48: =COUNTIFS('2. Status Detalhe Campos FY24'!$G$7:$G$731,'1. Status Resumo FY24'!$P47,'2. Status Detalhe Campos FY24'!$C$7:$C$731,'1. Status Resumo FY24'!$G$43,'2. Status Detalhe Campos FY24'!$D$7:$D$731,"2. Campo",'2. Status Detalhe Campos FY24'!$T$7:$T$731,"*Plano anterior*") +COUNTIFS('2. Status Detalhe Campos FY24'!$G$7:$G$731,'1. Status Resumo FY24'!$P47,'2. Status Detalhe Campos FY24'!$C$7:$C$731,'1. Status Resumo FY24'!$H$43,'2. Status Detalhe Campos FY24'!$D$7:$D$731,"2. Campo",'2. Status Detalhe Campos FY24'!$T$7:$T$731,"*Plano anterior*") -> 12 | V48: =U48-T48 -> 0
P49: Novos Requisitos FY25 | T49: =COUNTIFS('2. Status Detalhe Campos FY24'!$H$7:$H$731,'1. Status Resumo FY24'!$P48,'2. Status Detalhe Campos FY24'!$C$7:$C$731,'1. Status Resumo FY24'!$G$43,'2. Status Detalhe Campos FY24'!$D$7:$D$731,"2. Campo",'2. Status Detalhe Campos FY24'!$T$7:$T$731,"*Novo Plano*") +COUNTIFS('2. Status Detalhe Campos FY24'!$H$7:$H$731,'1. Status Resumo FY24'!$P48,'2. Status Detalhe Campos FY24'!$C$7:$C$731,'1. Status Resumo FY24'!$H$43,'2. Status Detalhe Campos FY24'!$D$7:$D$731,"2. Campo",'2. Status Detalhe Campos FY24'!$T$7:$T$731,"*Novo Plano*") -> 0 | U49: =COUNTIFS('2. Status Detalhe Campos FY24'!$G$7:$G$731,'1. Status Resumo FY24'!$P47,'2. Status Detalhe Campos FY24'!$C$7:$C$731,'1. Status Resumo FY24'!$G$43,'2. Status Detalhe Campos FY24'!$D$7:$D$731,"2. Campo",'2. Status Detalhe Campos FY24'!$T$7:$T$731,"*Novo Plano*") +COUNTIFS('2. Status Detalhe Campos FY24'!$G$7:$G$731,'1. Status Resumo FY24'!$P47,'2. Status Detalhe Campos FY24'!$C$7:$C$731,'1. Status Resumo FY24'!$H$43,'2. Status Detalhe Campos FY24'!$D$7:$D$731,"2. Campo",'2. Status Detalhe Campos FY24'!$T$7:$T$731,"*Novo Plano*") -> 0 | V49: =U49-T49 -> 0
P50: 1. Concluído | T50: =COUNTIFS('2. Status Detalhe Campos FY24'!$H$7:$H$731,'1. Status Resumo FY24'!$P50,'2. Status Detalhe Campos FY24'!$C$7:$C$731,'1. Status Resumo FY24'!$G$43,'2. Status Detalhe Campos FY24'!$D$7:$D$731,"2. Campo")+COUNTIFS('2. Status Detalhe Campos FY24'!$H$7:$H$731,'1. Status Resumo FY24'!$P50,'2. Status Detalhe Campos FY24'!$C$7:$C$731,'1. Status Resumo FY24'!$H$43,'2. Status Detalhe Campos FY24'!$D$7:$D$731,"2. Campo") -> 143 | U50: =COUNTIFS('2. Status Detalhe Campos FY24'!$G$7:$G$731,'1. Status Resumo FY24'!$P50,'2. Status Detalhe Campos FY24'!$C$7:$C$731,'1. Status Resumo FY24'!$G$43,'2. Status Detalhe Campos FY24'!$D$7:$D$731,"2. Campo")+COUNTIFS('2. Status Detalhe Campos FY24'!$G$7:$G$731,'1. Status Resumo FY24'!$P50,'2. Status Detalhe Campos FY24'!$C$7:$C$731,'1. Status Resumo FY24'!$H$43,'2. Status Detalhe Campos FY24'!$D$7:$D$731,"2. Campo") -> 144 | V50: =U50-T50 -> 1
P51: RequisItos FY24 | T51: =COUNTIFS('2. Status Detalhe Campos FY24'!$H$7:$H$731,'1. Status Resumo FY24'!$P50,'2. Status Detalhe Campos FY24'!$C$7:$C$731,'1. Status Resumo FY24'!$G$43,'2. Status Detalhe Campos FY24'!$D$7:$D$731,"2. Campo",'2. Status Detalhe Campos FY24'!$T$7:$T$731,"*Plano anterior*") +COUNTIFS('2. Status Detalhe Campos FY24'!$H$7:$H$731,'1. Status Resumo FY24'!$P50,'2. Status Detalhe Campos FY24'!$C$7:$C$731,'1. Status Resumo FY24'!$H$43,'2. Status Detalhe Campos FY24'!$D$7:$D$731,"2. Campo",'2. Status Detalhe Campos FY24'!$T$7:$T$731,"*Plano anterior*") -> 143 | U51: =COUNTIFS('2. Status Detalhe Campos FY24'!$G$7:$G$731,'1. Status Resumo FY24'!$P50,'2. Status Detalhe Campos FY24'!$C$7:$C$731,'1. Status Resumo FY24'!$G$43,'2. Status Detalhe Campos FY24'!$D$7:$D$731,"2. Campo",'2. Status Detalhe Campos FY24'!$T$7:$T$731,"*Plano anterior*") +COUNTIFS('2. Status Detalhe Campos FY24'!$G$7:$G$731,'1. Status Resumo FY24'!$P50,'2. Status Detalhe Campos FY24'!$C$7:$C$731,'1. Status Resumo FY24'!$H$43,'2. Status Detalhe Campos FY24'!$D$7:$D$731,"2. Campo",'2. Status Detalhe Campos FY24'!$T$7:$T$731,"*Plano anterior*") -> 144 | V51: =U51-T51 -> 1
P52: Novos Requisitos FY25 | T52: =COUNTIFS('2. Status Detalhe Campos FY24'!$H$7:$H$731,'1. Status Resumo FY24'!$P51,'2. Status Detalhe Campos FY24'!$C$7:$C$731,'1. Status Resumo FY24'!$G$43,'2. Status Detalhe Campos FY24'!$D$7:$D$731,"2. Campo",'2. Status Detalhe Campos FY24'!$T$7:$T$731,"*Novo Plano*") +COUNTIFS('2. Status Detalhe Campos FY24'!$H$7:$H$731,'1. Status Resumo FY24'!$P51,'2. Status Detalhe Campos FY24'!$C$7:$C$731,'1. Status Resumo FY24'!$H$43,'2. Status Detalhe Campos FY24'!$D$7:$D$731,"2. Campo",'2. Status Detalhe Campos FY24'!$T$7:$T$731,"*Novo Plano*") -> 0 | U52: =COUNTIFS('2. Status Detalhe Campos FY24'!$G$7:$G$731,'1. Status Resumo FY24'!$P50,'2. Status Detalhe Campos FY24'!$C$7:$C$731,'1. Status Resumo FY24'!$G$43,'2. Status Detalhe Campos FY24'!$D$7:$D$731,"2. Campo",'2. Status Detalhe Campos FY24'!$T$7:$T$731,"*Novo Plano*") +COUNTIFS('2. Status Detalhe Campos FY24'!$G$7:$G$731,'1. Status Resumo FY24'!$P50,'2. Status Detalhe Campos FY24'!$C$7:$C$731,'1. Status Resumo FY24'!$H$43,'2. Status Detalhe Campos FY24'!$D$7:$D$731,"2. Campo",'2. Status Detalhe Campos FY24'!$T$7:$T$731,"*Novo Plano*") -> 0 | V52: =U52-T52 -> 0
P53: 2.1 Em Teste | T53: =COUNTIFS('2. Status Detalhe Campos FY24'!$H$7:$H$731,'1. Status Resumo FY24'!$P53,'2. Status Detalhe Campos FY24'!$C$7:$C$731,'1. Status Resumo FY24'!$G$43,'2. Status Detalhe Campos FY24'!$D$7:$D$731,"2. Campo")+COUNTIFS('2. Status Detalhe Campos FY24'!$H$7:$H$731,'1. Status Resumo FY24'!$P53,'2. Status Detalhe Campos FY24'!$C$7:$C$731,'1. Status Resumo FY24'!$H$43,'2. Status Detalhe Campos FY24'!$D$7:$D$731,"2. Campo") -> 0 | U53: =COUNTIFS('2. Status Detalhe Campos FY24'!$G$7:$G$731,'1. Status Resumo FY24'!$P53,'2. Status Detalhe Campos FY24'!$C$7:$C$731,'1. Status Resumo FY24'!$G$43,'2. Status Detalhe Campos FY24'!$D$7:$D$731,"2. Campo")+COUNTIFS('2. Status Detalhe Campos FY24'!$G$7:$G$731,'1. Status Resumo FY24'!$P53,'2. Status Detalhe Campos FY24'!$C$7:$C$731,'1. Status Resumo FY24'!$H$43,'2. Status Detalhe Campos FY24'!$D$7:$D$731,"2. Campo") -> 0 | V53: =U53-T53 -> 0
P54: RequisItos FY24 | T54: =COUNTIFS('2. Status Detalhe Campos FY24'!$H$7:$H$731,'1. Status Resumo FY24'!$P53,'2. Status Detalhe Campos FY24'!$C$7:$C$731,'1. Status Resumo FY24'!$G$43,'2. Status Detalhe Campos FY24'!$D$7:$D$731,"2. Campo",'2. Status Detalhe Campos FY24'!$T$7:$T$731,"*Plano anterior*") +COUNTIFS('2. Status Detalhe Campos FY24'!$H$7:$H$731,'1. Status Resumo FY24'!$P53,'2. Status Detalhe Campos FY24'!$C$7:$C$731,'1. Status Resumo FY24'!$H$43,'2. Status Detalhe Campos FY24'!$D$7:$D$731,"2. Campo",'2. Status Detalhe Campos FY24'!$T$7:$T$731,"*Plano anterior*") -> 0 | U54: =COUNTIFS('2. Status Detalhe Campos FY24'!$G$7:$G$731,'1. Status Resumo FY24'!$P53,'2. Status Detalhe Campos FY24'!$C$7:$C$731,'1. Status Resumo FY24'!$G$43,'2. Status Detalhe Campos FY24'!$D$7:$D$731,"2. Campo",'2. Status Detalhe Campos FY24'!$T$7:$T$731,"*Plano anterior*") +COUNTIFS('2. Status Detalhe Campos FY24'!$G$7:$G$731,'1. Status Resumo FY24'!$P53,'2. Status Detalhe Campos FY24'!$C$7:$C$731,'1. Status Resumo FY24'!$H$43,'2. Status Detalhe Campos FY24'!$D$7:$D$731,"2. Campo",'2. Status Detalhe Campos FY24'!$T$7:$T$731,"*Plano anterior*") -> 0 | V54: =U54-T54 -> 0
P55: Novos Requisitos FY25 | T55: =COUNTIFS('2. Status Detalhe Campos FY24'!$H$7:$H$731,'1. Status Resumo FY24'!$P54,'2. Status Detalhe Campos FY24'!$C$7:$C$731,'1. Status Resumo FY24'!$G$43,'2. Status Detalhe Campos FY24'!$D$7:$D$731,"2. Campo",'2. Status Detalhe Campos FY24'!$T$7:$T$731,"*Novo Plano*") +COUNTIFS('2. Status Detalhe Campos FY24'!$H$7:$H$731,'1. Status Resumo FY24'!$P54,'2. Status Detalhe Campos FY24'!$C$7:$C$731,'1. Status Resumo FY24'!$H$43,'2. Status Detalhe Campos FY24'!$D$7:$D$731,"2. Campo",'2. Status Detalhe Campos FY24'!$T$7:$T$731,"*Novo Plano*") -> 0 | U55: =COUNTIFS('2. Status Detalhe Campos FY24'!$G$7:$G$731,'1. Status Resumo FY24'!$P53,'2. Status Detalhe Campos FY24'!$C$7:$C$731,'1. Status Resumo FY24'!$G$43,'2. Status Detalhe Campos FY24'!$D$7:$D$731,"2. Campo",'2. Status Detalhe Campos FY24'!$T$7:$T$731,"*Novo Plano*") +COUNTIFS('2. Status Detalhe Campos FY24'!$G$7:$G$731,'1. Status Resumo FY24'!$P53,'2. Status Detalhe Campos FY24'!$C$7:$C$731,'1. Status Resumo FY24'!$H$43,'2. Status Detalhe Campos FY24'!$D$7:$D$731,"2. Campo",'2. Status Detalhe Campos FY24'!$T$7:$T$731,"*Novo Plano*") -> 0 | V55: =U55-T55 -> 0
D56: ="# "&U74 -> # 204 | P56: 2.2 Em especificação | T56: =COUNTIFS('2. Status Detalhe Campos FY24'!$H$7:$H$731,'1. Status Resumo FY24'!$P56,'2. Status Detalhe Campos FY24'!$C$7:$C$731,'1. Status Resumo FY24'!$G$43,'2. Status Detalhe Campos FY24'!$D$7:$D$731,"2. Campo")+COUNTIFS('2. Status Detalhe Campos FY24'!$H$7:$H$731,'1. Status Resumo FY24'!$P56,'2. Status Detalhe Campos FY24'!$C$7:$C$731,'1. Status Resumo FY24'!$H$43,'2. Status Detalhe Campos FY24'!$D$7:$D$731,"2. Campo") -> 0 | U56: =COUNTIFS('2. Status Detalhe Campos FY24'!$G$7:$G$731,'1. Status Resumo FY24'!$P56,'2. Status Detalhe Campos FY24'!$C$7:$C$731,'1. Status Resumo FY24'!$G$43,'2. Status Detalhe Campos FY24'!$D$7:$D$731,"2. Campo")+COUNTIFS('2. Status Detalhe Campos FY24'!$G$7:$G$731,'1. Status Resumo FY24'!$P56,'2. Status Detalhe Campos FY24'!$C$7:$C$731,'1. Status Resumo FY24'!$H$43,'2. Status Detalhe Campos FY24'!$D$7:$D$731,"2. Campo") -> 0 | V56: =U56-T56 -> 0
P57: RequisItos FY24 | T57: =COUNTIFS('2. Status Detalhe Campos FY24'!$H$7:$H$731,'1. Status Resumo FY24'!$P56,'2. Status Detalhe Campos FY24'!$C$7:$C$731,'1. Status Resumo FY24'!$G$43,'2. Status Detalhe Campos FY24'!$D$7:$D$731,"2. Campo",'2. Status Detalhe Campos FY24'!$T$7:$T$731,"*Plano anterior*") +COUNTIFS('2. Status Detalhe Campos FY24'!$H$7:$H$731,'1. Status Resumo FY24'!$P56,'2. Status Detalhe Campos FY24'!$C$7:$C$731,'1. Status Resumo FY24'!$H$43,'2. Status Detalhe Campos FY24'!$D$7:$D$731,"2. Campo",'2. Status Detalhe Campos FY24'!$T$7:$T$731,"*Plano anterior*") -> 0 | U57: =COUNTIFS('2. Status Detalhe Campos FY24'!$G$7:$G$731,'1. Status Resumo FY24'!$P56,'2. Status Detalhe Campos FY24'!$C$7:$C$731,'1. Status Resumo FY24'!$G$43,'2. Status Detalhe Campos FY24'!$D$7:$D$731,"2. Campo",'2. Status Detalhe Campos FY24'!$T$7:$T$731,"*Plano anterior*") +COUNTIFS('2. Status Detalhe Campos FY24'!$G$7:$G$731,'1. Status Resumo FY24'!$P56,'2. Status Detalhe Campos FY24'!$C$7:$C$731,'1. Status Resumo FY24'!$H$43,'2. Status Detalhe Campos FY24'!$D$7:$D$731,"2. Campo",'2. Status Detalhe Campos FY24'!$T$7:$T$731,"*Plano anterior*") -> 0 | V57: =U57-T57 -> 0
P58: Novos Requisitos FY25 | T58: =COUNTIFS('2. Status Detalhe Campos FY24'!$H$7:$H$731,'1. Status Resumo FY24'!$P57,'2. Status Detalhe Campos FY24'!$C$7:$C$731,'1. Status Resumo FY24'!$G$43,'2. Status Detalhe Campos FY24'!$D$7:$D$731,"2. Campo",'2. Status Detalhe Campos FY24'!$T$7:$T$731,"*Novo Plano*") +COUNTIFS('2. Status Detalhe Campos FY24'!$H$7:$H$731,'1. Status Resumo FY24'!$P57,'2. Status Detalhe Campos FY24'!$C$7:$C$731,'1. Status Resumo FY24'!$H$43,'2. Status Detalhe Campos FY24'!$D$7:$D$731,"2. Campo",'2. Status Detalhe Campos FY24'!$T$7:$T$731,"*Novo Plano*") -> 0 | U58: =COUNTIFS('2. Status Detalhe Campos FY24'!$G$7:$G$731,'1. Status Resumo FY24'!$P56,'2. Status Detalhe Campos FY24'!$C$7:$C$731,'1. Status Resumo FY24'!$G$43,'2. Status Detalhe Campos FY24'!$D$7:$D$731,"2. Campo",'2. Status Detalhe Campos FY24'!$T$7:$T$731,"*Novo Plano*") +COUNTIFS('2. Status Detalhe Campos FY24'!$G$7:$G$731,'1. Status Resumo FY24'!$P56,'2. Status Detalhe Campos FY24'!$C$7:$C$731,'1. Status Resumo FY24'!$H$43,'2. Status Detalhe Campos FY24'!$D$7:$D$731,"2. Campo",'2. Status Detalhe Campos FY24'!$T$7:$T$731,"*Novo Plano*") -> 0 | V58: =U58-T58 -> 0
P59: 3. Pendente de outros desenvolvimentos | T59: =COUNTIFS('2. Status Detalhe Campos FY24'!$H$7:$H$731,'1. Status Resumo FY24'!$P59,'2. Status Detalhe Campos FY24'!$C$7:$C$731,'1. Status Resumo FY24'!$G$43,'2. Status Detalhe Campos FY24'!$D$7:$D$731,"2. Campo")+COUNTIFS('2. Status Detalhe Campos FY24'!$H$7:$H$731,'1. Status Resumo FY24'!$P59,'2. Status Detalhe Campos FY24'!$C$7:$C$731,'1. Status Resumo FY24'!$H$43,'2. Status Detalhe Campos FY24'!$D$7:$D$731,"2. Campo") -> 0 | U59: =COUNTIFS('2. Status Detalhe Campos FY24'!$G$7:$G$731,'1. Status Resumo FY24'!$P59,'2. Status Detalhe Campos FY24'!$C$7:$C$731,'1. Status Resumo FY24'!$G$43,'2. Status Detalhe Campos FY24'!$D$7:$D$731,"2. Campo")+COUNTIFS('2. Status Detalhe Campos FY24'!$G$7:$G$731,'1. Status Resumo FY24'!$P59,'2. Status Detalhe Campos FY24'!$C$7:$C$731,'1. Status Resumo FY24'!$H$43,'2. Status Detalhe Campos FY24'!$D$7:$D$731,"2. Campo") -> 0 | V59: =U59-T59 -> 0
P60: RequisItos FY24 | T60: =COUNTIFS('2. Status Detalhe Campos FY24'!$H$7:$H$731,'1. Status Resumo FY24'!$P59,'2. Status Detalhe Campos FY24'!$C$7:$C$731,'1. Status Resumo FY24'!$G$43,'2. Status Detalhe Campos FY24'!$D$7:$D$731,"2. Campo",'2. Status Detalhe Campos FY24'!$T$7:$T$731,"*Plano anterior*") +COUNTIFS('2. Status Detalhe Campos FY24'!$H$7:$H$731,'1. Status Resumo FY24'!$P59,'2. Status Detalhe Campos FY24'!$C$7:$C$731,'1. Status Resumo FY24'!$H$43,'2. Status Detalhe Campos FY24'!$D$7:$D$731,"2. Campo",'2. Status Detalhe Campos FY24'!$T$7:$T$731,"*Plano anterior*") -> 0 | U60: =COUNTIFS('2. Status Detalhe Campos FY24'!$G$7:$G$731,'1. Status Resumo FY24'!$P59,'2. Status Detalhe Campos FY24'!$C$7:$C$731,'1. Status Resumo FY24'!$G$43,'2. Status Detalhe Campos FY24'!$D$7:$D$731,"2. Campo",'2. Status Detalhe Campos FY24'!$T$7:$T$731,"*Plano anterior*") +COUNTIFS('2. Status Detalhe Campos FY24'!$G$7:$G$731,'1. Status Resumo FY24'!$P59,'2. Status Detalhe Campos FY24'!$C$7:$C$731,'1. Status Resumo FY24'!$H$43,'2. Status Detalhe Campos FY24'!$D$7:$D$731,"2. Campo",'2. Status Detalhe Campos FY24'!$T$7:$T$731,"*Plano anterior*") -> 0 | V60: =U60-T60 -> 0
P61: Novos Requisitos FY25 | T61: =COUNTIFS('2. Status Detalhe Campos FY24'!$H$7:$H$731,'1. Status Resumo FY24'!$P60,'2. Status Detalhe Campos FY24'!$C$7:$C$731,'1. Status Resumo FY24'!$G$43,'2. Status Detalhe Campos FY24'!$D$7:$D$731,"2. Campo",'2. Status Detalhe Campos FY24'!$T$7:$T$731,"*Novo Plano*") +COUNTIFS('2. Status Detalhe Campos FY24'!$H$7:$H$731,'1. Status Resumo FY24'!$P60,'2. Status Detalhe Campos FY24'!$C$7:$C$731,'1. Status Resumo FY24'!$H$43,'2. Status Detalhe Campos FY24'!$D$7:$D$731,"2. Campo",'2. Status Detalhe Campos FY24'!$T$7:$T$731,"*Novo Plano*") -> 0 | U61: =COUNTIFS('2. Status Detalhe Campos FY24'!$G$7:$G$731,'1. Status Resumo FY24'!$P59,'2. Status Detalhe Campos FY24'!$C$7:$C$731,'1. Status Resumo FY24'!$G$43,'2. Status Detalhe Campos FY24'!$D$7:$D$731,"2. Campo",'2. Status Detalhe Campos FY24'!$T$7:$T$731,"*Novo Plano*") +COUNTIFS('2. Status Detalhe Campos FY24'!$G$7:$G$731,'1. Status Resumo FY24'!$P59,'2. Status Detalhe Campos FY24'!$C$7:$C$731,'1. Status Resumo FY24'!$H$43,'2. Status Detalhe Campos FY24'!$D$7:$D$731,"2. Campo",'2. Status Detalhe Campos FY24'!$T$7:$T$731,"*Novo Plano*") -> 0 | V61: =U61-T61 -> 0
P62: 4. Validação EF | T62: =COUNTIFS('2. Status Detalhe Campos FY24'!$H$7:$H$731,'1. Status Resumo FY24'!$P62,'2. Status Detalhe Campos FY24'!$C$7:$C$731,'1. Status Resumo FY24'!$G$43,'2. Status Detalhe Campos FY24'!$D$7:$D$731,"2. Campo")+COUNTIFS('2. Status Detalhe Campos FY24'!$H$7:$H$731,'1. Status Resumo FY24'!$P62,'2. Status Detalhe Campos FY24'!$C$7:$C$731,'1. Status Resumo FY24'!$H$43,'2. Status Detalhe Campos FY24'!$D$7:$D$731,"2. Campo") -> 0 | U62: =COUNTIFS('2. Status Detalhe Campos FY24'!$G$7:$G$731,'1. Status Resumo FY24'!$P62,'2. Status Detalhe Campos FY24'!$C$7:$C$731,'1. Status Resumo FY24'!$G$43,'2. Status Detalhe Campos FY24'!$D$7:$D$731,"2. Campo")+COUNTIFS('2. Status Detalhe Campos FY24'!$G$7:$G$731,'1. Status Resumo FY24'!$P62,'2. Status Detalhe Campos FY24'!$C$7:$C$731,'1. Status Resumo FY24'!$H$43,'2. Status Detalhe Campos FY24'!$D$7:$D$731,"2. Campo") -> 0 | V62: =U62-T62 -> 0
P63: RequisItos FY24 | T63: =COUNTIFS('2. Status Detalhe Campos FY24'!$H$7:$H$731,'1. Status Resumo FY24'!$P62,'2. Status Detalhe Campos FY24'!$C$7:$C$731,'1. Status Resumo FY24'!$G$43,'2. Status Detalhe Campos FY24'!$D$7:$D$731,"2. Campo",'2. Status Detalhe Campos FY24'!$T$7:$T$731,"*Plano anterior*") +COUNTIFS('2. Status Detalhe Campos FY24'!$H$7:$H$731,'1. Status Resumo FY24'!$P62,'2. Status Detalhe Campos FY24'!$C$7:$C$731,'1. Status Resumo FY24'!$H$43,'2. Status Detalhe Campos FY24'!$D$7:$D$731,"2. Campo",'2. Status Detalhe Campos FY24'!$T$7:$T$731,"*Plano anterior*") -> 0 | U63: =COUNTIFS('2. Status Detalhe Campos FY24'!$G$7:$G$731,'1. Status Resumo FY24'!$P62,'2. Status Detalhe Campos FY24'!$C$7:$C$731,'1. Status Resumo FY24'!$G$43,'2. Status Detalhe Campos FY24'!$D$7:$D$731,"2. Campo",'2. Status Detalhe Campos FY24'!$T$7:$T$731,"*Plano anterior*") +COUNTIFS('2. Status Detalhe Campos FY24'!$G$7:$G$731,'1. Status Resumo FY24'!$P62,'2. Status Detalhe Campos FY24'!$C$7:$C$731,'1. Status Resumo FY24'!$H$43,'2. Status Detalhe Campos FY24'!$D$7:$D$731,"2. Campo",'2. Status Detalhe Campos FY24'!$T$7:$T$731,"*Plano anterior*") -> 0 | V63: =U63-T63 -> 0
P64: Novos Requisitos FY25 | T64: =COUNTIFS('2. Status Detalhe Campos FY24'!$H$7:$H$731,'1. Status Resumo FY24'!$P63,'2. Status Detalhe Campos FY24'!$C$7:$C$731,'1. Status Resumo FY24'!$G$43,'2. Status Detalhe Campos FY24'!$D$7:$D$731,"2. Campo",'2. Status Detalhe Campos FY24'!$T$7:$T$731,"*Novo Plano*") +COUNTIFS('2. Status Detalhe Campos FY24'!$H$7:$H$731,'1. Status Resumo FY24'!$P63,'2. Status Detalhe Campos FY24'!$C$7:$C$731,'1. Status Resumo FY24'!$H$43,'2. Status Detalhe Campos FY24'!$D$7:$D$731,"2. Campo",'2. Status Detalhe Campos FY24'!$T$7:$T$731,"*Novo Plano*") -> 0 | U64: =COUNTIFS('2. Status Detalhe Campos FY24'!$G$7:$G$731,'1. Status Resumo FY24'!$P62,'2. Status Detalhe Campos FY24'!$C$7:$C$731,'1. Status Resumo FY24'!$G$43,'2. Status Detalhe Campos FY24'!$D$7:$D$731,"2. Campo",'2. Status Detalhe Campos FY24'!$T$7:$T$731,"*Novo Plano*") +COUNTIFS('2. Status Detalhe Campos FY24'!$G$7:$G$731,'1. Status Resumo FY24'!$P62,'2. Status Detalhe Campos FY24'!$C$7:$C$731,'1. Status Resumo FY24'!$H$43,'2. Status Detalhe Campos FY24'!$D$7:$D$731,"2. Campo",'2. Status Detalhe Campos FY24'!$T$7:$T$731,"*Novo Plano*") -> 0 | V64: =U64-T64 -> 0
P65: 5. Em Correção | R65: (incidências) | T65: =COUNTIFS('2. Status Detalhe Campos FY24'!$H$7:$H$731,'1. Status Resumo FY24'!$P65,'2. Status Detalhe Campos FY24'!$C$7:$C$731,'1. Status Resumo FY24'!$G$43,'2. Status Detalhe Campos FY24'!$D$7:$D$731,"2. Campo")+COUNTIFS('2. Status Detalhe Campos FY24'!$H$7:$H$731,'1. Status Resumo FY24'!$P65,'2. Status Detalhe Campos FY24'!$C$7:$C$731,'1. Status Resumo FY24'!$H$43,'2. Status Detalhe Campos FY24'!$D$7:$D$731,"2. Campo") -> 1 | U65: =COUNTIFS('2. Status Detalhe Campos FY24'!$G$7:$G$731,'1. Status Resumo FY24'!$P65,'2. Status Detalhe Campos FY24'!$C$7:$C$731,'1. Status Resumo FY24'!$G$43,'2. Status Detalhe Campos FY24'!$D$7:$D$731,"2. Campo")+COUNTIFS('2. Status Detalhe Campos FY24'!$G$7:$G$731,'1. Status Resumo FY24'!$P65,'2. Status Detalhe Campos FY24'!$C$7:$C$731,'1. Status Resumo FY24'!$H$43,'2. Status Detalhe Campos FY24'!$D$7:$D$731,"2. Campo") -> 0 | V65: =U65-T65 -> -1
P66: RequisItos FY24 | T66: =COUNTIFS('2. Status Detalhe Campos FY24'!$H$7:$H$731,'1. Status Resumo FY24'!$P65,'2. Status Detalhe Campos FY24'!$C$7:$C$731,'1. Status Resumo FY24'!$G$43,'2. Status Detalhe Campos FY24'!$D$7:$D$731,"2. Campo",'2. Status Detalhe Campos FY24'!$T$7:$T$731,"*Plano anterior*") +COUNTIFS('2. Status Detalhe Campos FY24'!$H$7:$H$731,'1. Status Resumo FY24'!$P65,'2. Status Detalhe Campos FY24'!$C$7:$C$731,'1. Status Resumo FY24'!$H$43,'2. Status Detalhe Campos FY24'!$D$7:$D$731,"2. Campo",'2. Status Detalhe Campos FY24'!$T$7:$T$731,"*Plano anterior*") -> 1 | U66: =COUNTIFS('2. Status Detalhe Campos FY24'!$G$7:$G$731,'1. Status Resumo FY24'!$P65,'2. Status Detalhe Campos FY24'!$C$7:$C$731,'1. Status Resumo FY24'!$G$43,'2. Status Detalhe Campos FY24'!$D$7:$D$731,"2. Campo",'2. Status Detalhe Campos FY24'!$T$7:$T$731,"*Plano anterior*") +COUNTIFS('2. Status Detalhe Campos FY24'!$G$7:$G$731,'1. Status Resumo FY24'!$P65,'2. Status Detalhe Campos FY24'!$C$7:$C$731,'1. Status Resumo FY24'!$H$43,'2. Status Detalhe Campos FY24'!$D$7:$D$731,"2. Campo",'2. Status Detalhe Campos FY24'!$T$7:$T$731,"*Plano anterior*") -> 0 | V66: =U66-T66 -> -1
P67: Novos Requisitos FY25 | T67: =COUNTIFS('2. Status Detalhe Campos FY24'!$H$7:$H$731,'1. Status Resumo FY24'!$P66,'2. Status Detalhe Campos FY24'!$C$7:$C$731,'1. Status Resumo FY24'!$G$43,'2. Status Detalhe Campos FY24'!$D$7:$D$731,"2. Campo",'2. Status Detalhe Campos FY24'!$T$7:$T$731,"*Novo Plano*") +COUNTIFS('2. Status Detalhe Campos FY24'!$H$7:$H$731,'1. Status Resumo FY24'!$P66,'2. Status Detalhe Campos FY24'!$C$7:$C$731,'1. Status Resumo FY24'!$H$43,'2. Status Detalhe Campos FY24'!$D$7:$D$731,"2. Campo",'2. Status Detalhe Campos FY24'!$T$7:$T$731,"*Novo Plano*") -> 0 | U67: =COUNTIFS('2. Status Detalhe Campos FY24'!$G$7:$G$731,'1. Status Resumo FY24'!$P65,'2. Status Detalhe Campos FY24'!$C$7:$C$731,'1. Status Resumo FY24'!$G$43,'2. Status Detalhe Campos FY24'!$D$7:$D$731,"2. Campo",'2. Status Detalhe Campos FY24'!$T$7:$T$731,"*Novo Plano*") +COUNTIFS('2. Status Detalhe Campos FY24'!$G$7:$G$731,'1. Status Resumo FY24'!$P65,'2. Status Detalhe Campos FY24'!$C$7:$C$731,'1. Status Resumo FY24'!$H$43,'2. Status Detalhe Campos FY24'!$D$7:$D$731,"2. Campo",'2. Status Detalhe Campos FY24'!$T$7:$T$731,"*Novo Plano*") -> 0 | V67: =U67-T67 -> 0
P68: 6. Em implementação | T68: =COUNTIFS('2. Status Detalhe Campos FY24'!$H$7:$H$731,'1. Status Resumo FY24'!$P68,'2. Status Detalhe Campos FY24'!$C$7:$C$731,'1. Status Resumo FY24'!$G$43,'2. Status Detalhe Campos FY24'!$D$7:$D$731,"2. Campo")+COUNTIFS('2. Status Detalhe Campos FY24'!$H$7:$H$731,'1. Status Resumo FY24'!$P68,'2. Status Detalhe Campos FY24'!$C$7:$C$731,'1. Status Resumo FY24'!$H$43,'2. Status Detalhe Campos FY24'!$D$7:$D$731,"2. Campo") -> 48 | U68: =COUNTIFS('2. Status Detalhe Campos FY24'!$G$7:$G$731,'1. Status Resumo FY24'!$P68,'2. Status Detalhe Campos FY24'!$C$7:$C$731,'1. Status Resumo FY24'!$G$43,'2. Status Detalhe Campos FY24'!$D$7:$D$731,"2. Campo")+COUNTIFS('2. Status Detalhe Campos FY24'!$G$7:$G$731,'1. Status Resumo FY24'!$P68,'2. Status Detalhe Campos FY24'!$C$7:$C$731,'1. Status Resumo FY24'!$H$43,'2. Status Detalhe Campos FY24'!$D$7:$D$731,"2. Campo") -> 48 | V68: =U68-T68 -> 0
P69: RequisItos FY24 | T69: =COUNTIFS('2. Status Detalhe Campos FY24'!$H$7:$H$731,'1. Status Resumo FY24'!$P68,'2. Status Detalhe Campos FY24'!$C$7:$C$731,'1. Status Resumo FY24'!$G$43,'2. Status Detalhe Campos FY24'!$D$7:$D$731,"2. Campo",'2. Status Detalhe Campos FY24'!$T$7:$T$731,"*Plano anterior*") +COUNTIFS('2. Status Detalhe Campos FY24'!$H$7:$H$731,'1. Status Resumo FY24'!$P68,'2. Status Detalhe Campos FY24'!$C$7:$C$731,'1. Status Resumo FY24'!$H$43,'2. Status Detalhe Campos FY24'!$D$7:$D$731,"2. Campo",'2. Status Detalhe Campos FY24'!$T$7:$T$731,"*Plano anterior*") -> 48 | U69: =COUNTIFS('2. Status Detalhe Campos FY24'!$G$7:$G$731,'1. Status Resumo FY24'!$P68,'2. Status Detalhe Campos FY24'!$C$7:$C$731,'1. Status Resumo FY24'!$G$43,'2. Status Detalhe Campos FY24'!$D$7:$D$731,"2. Campo",'2. Status Detalhe Campos FY24'!$T$7:$T$731,"*Plano anterior*") +COUNTIFS('2. Status Detalhe Campos FY24'!$G$7:$G$731,'1. Status Resumo FY24'!$P68,'2. Status Detalhe Campos FY24'!$C$7:$C$731,'1. Status Resumo FY24'!$H$43,'2. Status Detalhe Campos FY24'!$D$7:$D$731,"2. Campo",'2. Status Detalhe Campos FY24'!$T$7:$T$731,"*Plano anterior*") -> 48 | V69: =U69-T69 -> 0
P70: Novos Requisitos FY25 | T70: =COUNTIFS('2. Status Detalhe Campos FY24'!$H$7:$H$731,'1. Status Resumo FY24'!$P69,'2. Status Detalhe Campos FY24'!$C$7:$C$731,'1. Status Resumo FY24'!$G$43,'2. Status Detalhe Campos FY24'!$D$7:$D$731,"2. Campo",'2. Status Detalhe Campos FY24'!$T$7:$T$731,"*Novo Plano*") +COUNTIFS('2. Status Detalhe Campos FY24'!$H$7:$H$731,'1. Status Resumo FY24'!$P69,'2. Status Detalhe Campos FY24'!$C$7:$C$731,'1. Status Resumo FY24'!$H$43,'2. Status Detalhe Campos FY24'!$D$7:$D$731,"2. Campo",'2. Status Detalhe Campos FY24'!$T$7:$T$731,"*Novo Plano*") -> 0 | U70: =COUNTIFS('2. Status Detalhe Campos FY24'!$G$7:$G$731,'1. Status Resumo FY24'!$P68,'2. Status Detalhe Campos FY24'!$C$7:$C$731,'1. Status Resumo FY24'!$G$43,'2. Status Detalhe Campos FY24'!$D$7:$D$731,"2. Campo",'2. Status Detalhe Campos FY24'!$T$7:$T$731,"*Novo Plano*") +COUNTIFS('2. Status Detalhe Campos FY24'!$G$7:$G$731,'1. Status Resumo FY24'!$P68,'2. Status Detalhe Campos FY24'!$C$7:$C$731,'1. Status Resumo FY24'!$H$43,'2. Status Detalhe Campos FY24'!$D$7:$D$731,"2. Campo",'2. Status Detalhe Campos FY24'!$T$7:$T$731,"*Novo Plano*") -> 0 | V70: =U70-T70 -> 0
P71: 7. Por iniciar | T71: =COUNTIFS('2. Status Detalhe Campos FY24'!$H$7:$H$731,'1. Status Resumo FY24'!$P71,'2. Status Detalhe Campos FY24'!$C$7:$C$731,'1. Status Resumo FY24'!$G$43,'2. Status Detalhe Campos FY24'!$D$7:$D$731,"2. Campo")+COUNTIFS('2. Status Detalhe Campos FY24'!$H$7:$H$731,'1. Status Resumo FY24'!$P71,'2. Status Detalhe Campos FY24'!$C$7:$C$731,'1. Status Resumo FY24'!$H$43,'2. Status Detalhe Campos FY24'!$D$7:$D$731,"2. Campo") -> 0 | U71: =COUNTIFS('2. Status Detalhe Campos FY24'!$G$7:$G$731,'1. Status Resumo FY24'!$P71,'2. Status Detalhe Campos FY24'!$C$7:$C$731,'1. Status Resumo FY24'!$G$43,'2. Status Detalhe Campos FY24'!$D$7:$D$731,"2. Campo")+COUNTIFS('2. Status Detalhe Campos FY24'!$G$7:$G$731,'1. Status Resumo FY24'!$P71,'2. Status Detalhe Campos FY24'!$C$7:$C$731,'1. Status Resumo FY24'!$H$43,'2. Status Detalhe Campos FY24'!$D$7:$D$731,"2. Campo") -> 0 | V71: =U71-T71 -> 0
P72: RequisItos FY24 | T72: =COUNTIFS('2. Status Detalhe Campos FY24'!$H$7:$H$731,'1. Status Resumo FY24'!$P71,'2. Status Detalhe Campos FY24'!$C$7:$C$731,'1. Status Resumo FY24'!$G$43,'2. Status Detalhe Campos FY24'!$D$7:$D$731,"2. Campo",'2. Status Detalhe Campos FY24'!$T$7:$T$731,"*Plano anterior*") +COUNTIFS('2. Status Detalhe Campos FY24'!$H$7:$H$731,'1. Status Resumo FY24'!$P71,'2. Status Detalhe Campos FY24'!$C$7:$C$731,'1. Status Resumo FY24'!$H$43,'2. Status Detalhe Campos FY24'!$D$7:$D$731,"2. Campo",'2. Status Detalhe Campos FY24'!$T$7:$T$731,"*Plano anterior*") -> 0 | U72: =COUNTIFS('2. Status Detalhe Campos FY24'!$G$7:$G$731,'1. Status Resumo FY24'!$P71,'2. Status Detalhe Campos FY24'!$C$7:$C$731,'1. Status Resumo FY24'!$G$43,'2. Status Detalhe Campos FY24'!$D$7:$D$731,"2. Campo",'2. Status Detalhe Campos FY24'!$T$7:$T$731,"*Plano anterior*") +COUNTIFS('2. Status Detalhe Campos FY24'!$G$7:$G$731,'1. Status Resumo FY24'!$P71,'2. Status Detalhe Campos FY24'!$C$7:$C$731,'1. Status Resumo FY24'!$H$43,'2. Status Detalhe Campos FY24'!$D$7:$D$731,"2. Campo",'2. Status Detalhe Campos FY24'!$T$7:$T$731,"*Plano anterior*") -> 0 | V72: =U72-T72 -> 0
P73: Novos Requisitos FY25 | T73: =COUNTIFS('2. Status Detalhe Campos FY24'!$H$7:$H$731,'1. Status Resumo FY24'!$P72,'2. Status Detalhe Campos FY24'!$C$7:$C$731,'1. Status Resumo FY24'!$G$43,'2. Status Detalhe Campos FY24'!$D$7:$D$731,"2. Campo",'2. Status Detalhe Campos FY24'!$T$7:$T$731,"*Novo Plano*") +COUNTIFS('2. Status Detalhe Campos FY24'!$H$7:$H$731,'1. Status Resumo FY24'!$P72,'2. Status Detalhe Campos FY24'!$C$7:$C$731,'1. Status Resumo FY24'!$H$43,'2. Status Detalhe Campos FY24'!$D$7:$D$731,"2. Campo",'2. Status Detalhe Campos FY24'!$T$7:$T$731,"*Novo Plano*") -> 0 | U73: =COUNTIFS('2. Status Detalhe Campos FY24'!$G$7:$G$731,'1. Status Resumo FY24'!$P71,'2. Status Detalhe Campos FY24'!$C$7:$C$731,'1. Status Resumo FY24'!$G$43,'2. Status Detalhe Campos FY24'!$D$7:$D$731,"2. Campo",'2. Status Detalhe Campos FY24'!$T$7:$T$731,"*Novo Plano*") +COUNTIFS('2. Status Detalhe Campos FY24'!$G$7:$G$731,'1. Status Resumo FY24'!$P71,'2. Status Detalhe Campos FY24'!$C$7:$C$731,'1. Status Resumo FY24'!$H$43,'2. Status Detalhe Campos FY24'!$D$7:$D$731,"2. Campo",'2. Status Detalhe Campos FY24'!$T$7:$T$731,"*Novo Plano*") -> 0 | V73: =U73-T73 -> 0
P74: Total | T74: =+SUM(T47,T50,T53,T59,T62,T65,T68,T71,T56) -> 204 | U74: =+SUM(U47,U50,U53,U59,U62,U65,U68,U71,U56) -> 204 | V74: =+U74-T74 -> 0
P75: RequisItos FY24 | T75: =+SUM(T48,T51,T54,T57,T60,T63,T66,T69,T72) -> 204 | U75: =+SUM(U48,U51,U54,U57,U60,U63,U66,U69,U72) -> 204 | V75: =+U75-T75 -> 0
P76: Novos Requisitos FY25 | T76: =+SUM(T49,T52,T55,T58,T61,T64,T67,T70,T73) -> 0 | U76: =+SUM(U49,U52,U55,U58,U61,U64,U67,U70,U73) -> 0 | V76: =+U76-T76 -> 0
G78: Status (Tabelas) | P78: Status (Universos)
F79: > | G79: Tabela de Bens Imóveis | L79: OK | O79: > | P79: Universo Bens Colateralizados (MUG) | T79: OK
F80: > | G80: Tabelas de Processos Imobiliários | L80: OK | O80: > | P80: Universo Bens Não Colateralizados (GP) | T80: OK
F81: > | G81: Tabela de Traçabilidade Processo -Bem | L81: OK | O81: > | P81: Universo Bens Adjudicados | T81: Não serão testados neste projeto
F82: > | G82: Tabela de Traçabilidade Crédito - Processo | L82: OK
F83: > | G83: Tabela input de Cerificados Energéticos (Gloval) | L83: Em Implementação
F84: > | G84: Tabela Output de Cerificados Energéticos | L84: Em Implementação
B88: 2. Modelo Verde | G88: Modelo Verde - Input | H88: Modelo Verde - Output
C91: Resumo | G91: Detalhe por Tabela | P91: Status (campos) | T91: =T46 -> 45688 | U91: =U46 -> 45695 | V91: ∆ | X91: Highlights
P92: 0. Cancelado | T92: =COUNTIFS('2. Status Detalhe Campos FY24'!$H$7:$H$731,'1. Status Resumo FY24'!$P92,'2. Status Detalhe Campos FY24'!$C$7:$C$731,'1. Status Resumo FY24'!$G$88,'2. Status Detalhe Campos FY24'!$D$7:$D$731,"2. Campo")+COUNTIFS('2. Status Detalhe Campos FY24'!$H$7:$H$731,'1. Status Resumo FY24'!$P92,'2. Status Detalhe Campos FY24'!$C$7:$C$731,'1. Status Resumo FY24'!$H$88,'2. Status Detalhe Campos FY24'!$D$7:$D$731,"2. Campo") -> 16 | U92: =COUNTIFS('2. Status Detalhe Campos FY24'!$G$7:$G$731,'1. Status Resumo FY24'!$P92,'2. Status Detalhe Campos FY24'!$C$7:$C$731,'1. Status Resumo FY24'!$G$88,'2. Status Detalhe Campos FY24'!$D$7:$D$731,"2. Campo")+COUNTIFS('2. Status Detalhe Campos FY24'!$G$7:$G$731,'1. Status Resumo FY24'!$P92,'2. Status Detalhe Campos FY24'!$C$7:$C$731,'1. Status Resumo FY24'!$H$88,'2. Status Detalhe Campos FY24'!$D$7:$D$731,"2. Campo") -> 16 | V92: =U92-T92 -> 0 | X92: 1. Tabela de Input Corporativo de Risco Físico por ZipCode: - Foi concluída e partilhada a especificação dos novos 5 campos (FY25) da tabela de Input Corporativo de Risco Físico por Zip Code. Os mesmos encontram-se agora em implementação pela equipa de Tecnologia. - Estamos a finalizar a especificação do campo Code_Nace devido à alteração dos códigos e iremos partilhar ao final do dia de hoje com a equipa de tecnologia. 2. Tabela de Output de Clientes e Bens Imóveis: - Foi concluída e partilhada a especificação dos 4 campos de Risco Físico da Tabela de Clientes e dos 4 campos de Risco Físico da Tabela de Bens Imóveis, devido ao impacto da introdução do novo Input Corporativo de Risco Físico por Zip Code. 3. Tabela de Input Marcação Verde: - Foram realizadas reunioes com CdG para definir ownership de requisitos da tabela. Adicionalmente, foi disponibilizada a tecnologia a estrutura da tabela inicio das implementações.
P93: Requisitos FY24 | T93: =COUNTIFS('2. Status Detalhe Campos FY24'!$H$7:$H$731,'1. Status Resumo FY24'!$P92,'2. Status Detalhe Campos FY24'!$C$7:$C$731,'1. Status Resumo FY24'!$G$88,'2. Status Detalhe Campos FY24'!$D$7:$D$731,"2. Campo",'2. Status Detalhe Campos FY24'!$T$7:$T$731,"*Plano anterior*") +COUNTIFS('2. Status Detalhe Campos FY24'!$H$7:$H$731,'1. Status Resumo FY24'!$P92,'2. Status Detalhe Campos FY24'!$C$7:$C$731,'1. Status Resumo FY24'!$H$88,'2. Status Detalhe Campos FY24'!$D$7:$D$731,"2. Campo",'2. Status Detalhe Campos FY24'!$T$7:$T$731,"*Plano anterior*") -> 16 | U93: =COUNTIFS('2. Status Detalhe Campos FY24'!$G$7:$G$731,'1. Status Resumo FY24'!$P92,'2. Status Detalhe Campos FY24'!$C$7:$C$731,'1. Status Resumo FY24'!$G$88,'2. Status Detalhe Campos FY24'!$D$7:$D$731,"2. Campo",'2. Status Detalhe Campos FY24'!$T$7:$T$731,"*Plano anterior*") +COUNTIFS('2. Status Detalhe Campos FY24'!$G$7:$G$731,'1. Status Resumo FY24'!$P92,'2. Status Detalhe Campos FY24'!$C$7:$C$731,'1. Status Resumo FY24'!$H$88,'2. Status Detalhe Campos FY24'!$D$7:$D$731,"2. Campo",'2. Status Detalhe Campos FY24'!$T$7:$T$731,"*Plano anterior*") -> 16 | V93: =U93-T93 -> 0
P94: Novos Requisitos FY25 | T94: =COUNTIFS('2. Status Detalhe Campos FY24'!$H$7:$H$731,'1. Status Resumo FY24'!$P92,'2. Status Detalhe Campos FY24'!$C$7:$C$731,'1. Status Resumo FY24'!$G$88,'2. Status Detalhe Campos FY24'!$D$7:$D$731,"2. Campo",'2. Status Detalhe Campos FY24'!$T$7:$T$731,"*Novo Plano*") +COUNTIFS('2. Status Detalhe Campos FY24'!$H$7:$H$731,'1. Status Resumo FY24'!$P92,'2. Status Detalhe Campos FY24'!$C$7:$C$731,'1. Status Resumo FY24'!$H$88,'2. Status Detalhe Campos FY24'!$D$7:$D$731,"2. Campo",'2. Status Detalhe Campos FY24'!$T$7:$T$731,"*Novo Plano*") -> 0 | U94: =COUNTIFS('2. Status Detalhe Campos FY24'!$G$7:$G$731,'1. Status Resumo FY24'!$P92,'2. Status Detalhe Campos FY24'!$C$7:$C$731,'1. Status Resumo FY24'!$G$88,'2. Status Detalhe Campos FY24'!$D$7:$D$731,"2. Campo",'2. Status Detalhe Campos FY24'!$T$7:$T$731,"*Novo Plano*") +COUNTIFS('2. Status Detalhe Campos FY24'!$G$7:$G$731,'1. Status Resumo FY24'!$P92,'2. Status Detalhe Campos FY24'!$C$7:$C$731,'1. Status Resumo FY24'!$H$88,'2. Status Detalhe Campos FY24'!$D$7:$D$731,"2. Campo",'2. Status Detalhe Campos FY24'!$T$7:$T$731,"*Novo Plano*") -> 0 | V94: =U94-T94 -> 0
P95: 1. Concluído | T95: =COUNTIFS('2. Status Detalhe Campos FY24'!$H$7:$H$731,'1. Status Resumo FY24'!$P95,'2. Status Detalhe Campos FY24'!$C$7:$C$731,'1. Status Resumo FY24'!$G$88,'2. Status Detalhe Campos FY24'!$D$7:$D$731,"2. Campo")+COUNTIFS('2. Status Detalhe Campos FY24'!$H$7:$H$731,'1. Status Resumo FY24'!$P95,'2. Status Detalhe Campos FY24'!$C$7:$C$731,'1. Status Resumo FY24'!$H$88,'2. Status Detalhe Campos FY24'!$D$7:$D$731,"2. Campo") -> 185 | U95: =COUNTIFS('2. Status Detalhe Campos FY24'!$G$7:$G$731,'1. Status Resumo FY24'!$P95,'2. Status Detalhe Campos FY24'!$C$7:$C$731,'1. Status Resumo FY24'!$G$88,'2. Status Detalhe Campos FY24'!$D$7:$D$731,"2. Campo")+COUNTIFS('2. Status Detalhe Campos FY24'!$G$7:$G$731,'1. Status Resumo FY24'!$P95,'2. Status Detalhe Campos FY24'!$C$7:$C$731,'1. Status Resumo FY24'!$H$88,'2. Status Detalhe Campos FY24'!$D$7:$D$731,"2. Campo") -> 185 | V95: =U95-T95 -> 0
P96: Requisitos FY24 | T96: =COUNTIFS('2. Status Detalhe Campos FY24'!$H$7:$H$731,'1. Status Resumo FY24'!$P95,'2. Status Detalhe Campos FY24'!$C$7:$C$731,'1. Status Resumo FY24'!$G$88,'2. Status Detalhe Campos FY24'!$D$7:$D$731,"2. Campo",'2. Status Detalhe Campos FY24'!$T$7:$T$731,"*Plano anterior*") +COUNTIFS('2. Status Detalhe Campos FY24'!$H$7:$H$731,'1. Status Resumo FY24'!$P95,'2. Status Detalhe Campos FY24'!$C$7:$C$731,'1. Status Resumo FY24'!$H$88,'2. Status Detalhe Campos FY24'!$D$7:$D$731,"2. Campo",'2. Status Detalhe Campos FY24'!$T$7:$T$731,"*Plano anterior*") -> 185 | U96: =COUNTIFS('2. Status Detalhe Campos FY24'!$G$7:$G$731,'1. Status Resumo FY24'!$P95,'2. Status Detalhe Campos FY24'!$C$7:$C$731,'1. Status Resumo FY24'!$G$88,'2. Status Detalhe Campos FY24'!$D$7:$D$731,"2. Campo",'2. Status Detalhe Campos FY24'!$T$7:$T$731,"*Plano anterior*") +COUNTIFS('2. Status Detalhe Campos FY24'!$G$7:$G$731,'1. Status Resumo FY24'!$P95,'2. Status Detalhe Campos FY24'!$C$7:$C$731,'1. Status Resumo FY24'!$H$88,'2. Status Detalhe Campos FY24'!$D$7:$D$731,"2. Campo",'2. Status Detalhe Campos FY24'!$T$7:$T$731,"*Plano anterior*") -> 185 | V96: =U96-T96 -> 0
P97: Novos Requisitos FY25 | T97: =COUNTIFS('2. Status Detalhe Campos FY24'!$H$7:$H$731,'1. Status Resumo FY24'!$P95,'2. Status Detalhe Campos FY24'!$C$7:$C$731,'1. Status Resumo FY24'!$G$88,'2. Status Detalhe Campos FY24'!$D$7:$D$731,"2. Campo",'2. Status Detalhe Campos FY24'!$T$7:$T$731,"*Novo Plano*") +COUNTIFS('2. Status Detalhe Campos FY24'!$H$7:$H$731,'1. Status Resumo FY24'!$P95,'2. Status Detalhe Campos FY24'!$C$7:$C$731,'1. Status Resumo FY24'!$H$88,'2. Status Detalhe Campos FY24'!$D$7:$D$731,"2. Campo",'2. Status Detalhe Campos FY24'!$T$7:$T$731,"*Novo Plano*") -> 0 | U97: =COUNTIFS('2. Status Detalhe Campos FY24'!$G$7:$G$731,'1. Status Resumo FY24'!$P95,'2. Status Detalhe Campos FY24'!$C$7:$C$731,'1. Status Resumo FY24'!$G$88,'2. Status Detalhe Campos FY24'!$D$7:$D$731,"2. Campo",'2. Status Detalhe Campos FY24'!$T$7:$T$731,"*Novo Plano*") +COUNTIFS('2. Status Detalhe Campos FY24'!$G$7:$G$731,'1. Status Resumo FY24'!$P95,'2. Status Detalhe Campos FY24'!$C$7:$C$731,'1. Status Resumo FY24'!$H$88,'2. Status Detalhe Campos FY24'!$D$7:$D$731,"2. Campo",'2. Status Detalhe Campos FY24'!$T$7:$T$731,"*Novo Plano*") -> 0 | V97: =U97-T97 -> 0
P98: 2.1 Em Teste | T98: =COUNTIFS('2. Status Detalhe Campos FY24'!$H$7:$H$731,'1. Status Resumo FY24'!$P98,'2. Status Detalhe Campos FY24'!$C$7:$C$731,'1. Status Resumo FY24'!$G$88,'2. Status Detalhe Campos FY24'!$D$7:$D$731,"2. Campo")+COUNTIFS('2. Status Detalhe Campos FY24'!$H$7:$H$731,'1. Status Resumo FY24'!$P98,'2. Status Detalhe Campos FY24'!$C$7:$C$731,'1. Status Resumo FY24'!$H$88,'2. Status Detalhe Campos FY24'!$D$7:$D$731,"2. Campo") -> 0 | U98: =COUNTIFS('2. Status Detalhe Campos FY24'!$G$7:$G$731,'1. Status Resumo FY24'!$P98,'2. Status Detalhe Campos FY24'!$C$7:$C$731,'1. Status Resumo FY24'!$G$88,'2. Status Detalhe Campos FY24'!$D$7:$D$731,"2. Campo")+COUNTIFS('2. Status Detalhe Campos FY24'!$G$7:$G$731,'1. Status Resumo FY24'!$P98,'2. Status Detalhe Campos FY24'!$C$7:$C$731,'1. Status Resumo FY24'!$H$88,'2. Status Detalhe Campos FY24'!$D$7:$D$731,"2. Campo") -> 26 | V98: =U98-T98 -> 26
P99: Requisitos FY24 | T99: =COUNTIFS('2. Status Detalhe Campos FY24'!$H$7:$H$731,'1. Status Resumo FY24'!$P98,'2. Status Detalhe Campos FY24'!$C$7:$C$731,'1. Status Resumo FY24'!$G$88,'2. Status Detalhe Campos FY24'!$D$7:$D$731,"2. Campo",'2. Status Detalhe Campos FY24'!$T$7:$T$731,"*Plano anterior*") +COUNTIFS('2. Status Detalhe Campos FY24'!$H$7:$H$731,'1. Status Resumo FY24'!$P98,'2. Status Detalhe Campos FY24'!$C$7:$C$731,'1. Status Resumo FY24'!$H$88,'2. Status Detalhe Campos FY24'!$D$7:$D$731,"2. Campo",'2. Status Detalhe Campos FY24'!$T$7:$T$731,"*Plano anterior*") -> 0 | U99: =COUNTIFS('2. Status Detalhe Campos FY24'!$G$7:$G$731,'1. Status Resumo FY24'!$P98,'2. Status Detalhe Campos FY24'!$C$7:$C$731,'1. Status Resumo FY24'!$G$88,'2. Status Detalhe Campos FY24'!$D$7:$D$731,"2. Campo",'2. Status Detalhe Campos FY24'!$T$7:$T$731,"*Plano anterior*") +COUNTIFS('2. Status Detalhe Campos FY24'!$G$7:$G$731,'1. Status Resumo FY24'!$P98,'2. Status Detalhe Campos FY24'!$C$7:$C$731,'1. Status Resumo FY24'!$H$88,'2. Status Detalhe Campos FY24'!$D$7:$D$731,"2. Campo",'2. Status Detalhe Campos FY24'!$T$7:$T$731,"*Plano anterior*") -> 6 | V99: =U99-T99 -> 6
P100: Novos Requisitos FY25 | T100: =COUNTIFS('2. Status Detalhe Campos FY24'!$H$7:$H$731,'1. Status Resumo FY24'!$P98,'2. Status Detalhe Campos FY24'!$C$7:$C$731,'1. Status Resumo FY24'!$G$88,'2. Status Detalhe Campos FY24'!$D$7:$D$731,"2. Campo",'2. Status Detalhe Campos FY24'!$T$7:$T$731,"*Novo Plano*") +COUNTIFS('2. Status Detalhe Campos FY24'!$H$7:$H$731,'1. Status Resumo FY24'!$P98,'2. Status Detalhe Campos FY24'!$C$7:$C$731,'1. Status Resumo FY24'!$H$88,'2. Status Detalhe Campos FY24'!$D$7:$D$731,"2. Campo",'2. Status Detalhe Campos FY24'!$T$7:$T$731,"*Novo Plano*") -> 0 | U100: =COUNTIFS('2. Status Detalhe Campos FY24'!$G$7:$G$731,'1. Status Resumo FY24'!$P98,'2. Status Detalhe Campos FY24'!$C$7:$C$731,'1. Status Resumo FY24'!$G$88,'2. Status Detalhe Campos FY24'!$D$7:$D$731,"2. Campo",'2. Status Detalhe Campos FY24'!$T$7:$T$731,"*Novo Plano*") +COUNTIFS('2. Status Detalhe Campos FY24'!$G$7:$G$731,'1. Status Resumo FY24'!$P98,'2. Status Detalhe Campos FY24'!$C$7:$C$731,'1. Status Resumo FY24'!$H$88,'2. Status Detalhe Campos FY24'!$D$7:$D$731,"2. Campo",'2. Status Detalhe Campos FY24'!$T$7:$T$731,"*Novo Plano*") -> 20 | V100: =U100-T100 -> 20
P101: 2.2 Em especificação | T101: =COUNTIFS('2. Status Detalhe Campos FY24'!$H$7:$H$731,'1. Status Resumo FY24'!$P101,'2. Status Detalhe Campos FY24'!$C$7:$C$731,'1. Status Resumo FY24'!$G$88,'2. Status Detalhe Campos FY24'!$D$7:$D$731,"2. Campo")+COUNTIFS('2. Status Detalhe Campos FY24'!$H$7:$H$731,'1. Status Resumo FY24'!$P101,'2. Status Detalhe Campos FY24'!$C$7:$C$731,'1. Status Resumo FY24'!$H$88,'2. Status Detalhe Campos FY24'!$D$7:$D$731,"2. Campo") -> 8 | U101: =COUNTIFS('2. Status Detalhe Campos FY24'!$G$7:$G$731,'1. Status Resumo FY24'!$P101,'2. Status Detalhe Campos FY24'!$C$7:$C$731,'1. Status Resumo FY24'!$G$88,'2. Status Detalhe Campos FY24'!$D$7:$D$731,"2. Campo")+COUNTIFS('2. Status Detalhe Campos FY24'!$G$7:$G$731,'1. Status Resumo FY24'!$P101,'2. Status Detalhe Campos FY24'!$C$7:$C$731,'1. Status Resumo FY24'!$H$88,'2. Status Detalhe Campos FY24'!$D$7:$D$731,"2. Campo") -> 55 | V101: =U101-T101 -> 47
P102: Requisitos FY24 | T102: =COUNTIFS('2. Status Detalhe Campos FY24'!$H$7:$H$731,'1. Status Resumo FY24'!$P101,'2. Status Detalhe Campos FY24'!$C$7:$C$731,'1. Status Resumo FY24'!$G$88,'2. Status Detalhe Campos FY24'!$D$7:$D$731,"2. Campo",'2. Status Detalhe Campos FY24'!$T$7:$T$731,"*Plano anterior*") +COUNTIFS('2. Status Detalhe Campos FY24'!$H$7:$H$731,'1. Status Resumo FY24'!$P101,'2. Status Detalhe Campos FY24'!$C$7:$C$731,'1. Status Resumo FY24'!$H$88,'2. Status Detalhe Campos FY24'!$D$7:$D$731,"2. Campo",'2. Status Detalhe Campos FY24'!$T$7:$T$731,"*Plano anterior*") -> 8 | U102: =COUNTIFS('2. Status Detalhe Campos FY24'!$G$7:$G$731,'1. Status Resumo FY24'!$P101,'2. Status Detalhe Campos FY24'!$C$7:$C$731,'1. Status Resumo FY24'!$G$88,'2. Status Detalhe Campos FY24'!$D$7:$D$731,"2. Campo",'2. Status Detalhe Campos FY24'!$T$7:$T$731,"*Plano anterior*") +COUNTIFS('2. Status Detalhe Campos FY24'!$G$7:$G$731,'1. Status Resumo FY24'!$P101,'2. Status Detalhe Campos FY24'!$C$7:$C$731,'1. Status Resumo FY24'!$H$88,'2. Status Detalhe Campos FY24'!$D$7:$D$731,"2. Campo",'2. Status Detalhe Campos FY24'!$T$7:$T$731,"*Plano anterior*") -> 55 | V102: =U102-T102 -> 47
P103: Novos Requisitos FY25 | T103: =COUNTIFS('2. Status Detalhe Campos FY24'!$H$7:$H$731,'1. Status Resumo FY24'!$P101,'2. Status Detalhe Campos FY24'!$C$7:$C$731,'1. Status Resumo FY24'!$G$88,'2. Status Detalhe Campos FY24'!$D$7:$D$731,"2. Campo",'2. Status Detalhe Campos FY24'!$T$7:$T$731,"*Novo Plano*") +COUNTIFS('2. Status Detalhe Campos FY24'!$H$7:$H$731,'1. Status Resumo FY24'!$P101,'2. Status Detalhe Campos FY24'!$C$7:$C$731,'1. Status Resumo FY24'!$H$88,'2. Status Detalhe Campos FY24'!$D$7:$D$731,"2. Campo",'2. Status Detalhe Campos FY24'!$T$7:$T$731,"*Novo Plano*") -> 0 | U103: =COUNTIFS('2. Status Detalhe Campos FY24'!$G$7:$G$731,'1. Status Resumo FY24'!$P101,'2. Status Detalhe Campos FY24'!$C$7:$C$731,'1. Status Resumo FY24'!$G$88,'2. Status Detalhe Campos FY24'!$D$7:$D$731,"2. Campo",'2. Status Detalhe Campos FY24'!$T$7:$T$731,"*Novo Plano*") +COUNTIFS('2. Status Detalhe Campos FY24'!$G$7:$G$731,'1. Status Resumo FY24'!$P101,'2. Status Detalhe Campos FY24'!$C$7:$C$731,'1. Status Resumo FY24'!$H$88,'2. Status Detalhe Campos FY24'!$D$7:$D$731,"2. Campo",'2. Status Detalhe Campos FY24'!$T$7:$T$731,"*Novo Plano*") -> 0 | V103: =U103-T103 -> 0
P104: 3. Pendente de outros desenvolvimentos | T104: =COUNTIFS('2. Status Detalhe Campos FY24'!$H$7:$H$731,'1. Status Resumo FY24'!$P104,'2. Status Detalhe Campos FY24'!$C$7:$C$731,'1. Status Resumo FY24'!$G$88,'2. Status Detalhe Campos FY24'!$D$7:$D$731,"2. Campo")+COUNTIFS('2. Status Detalhe Campos FY24'!$H$7:$H$731,'1. Status Resumo FY24'!$P104,'2. Status Detalhe Campos FY24'!$C$7:$C$731,'1. Status Resumo FY24'!$H$88,'2. Status Detalhe Campos FY24'!$D$7:$D$731,"2. Campo") -> 6 | U104: =COUNTIFS('2. Status Detalhe Campos FY24'!$G$7:$G$731,'1. Status Resumo FY24'!$P104,'2. Status Detalhe Campos FY24'!$C$7:$C$731,'1. Status Resumo FY24'!$G$88,'2. Status Detalhe Campos FY24'!$D$7:$D$731,"2. Campo")+COUNTIFS('2. Status Detalhe Campos FY24'!$G$7:$G$731,'1. Status Resumo FY24'!$P104,'2. Status Detalhe Campos FY24'!$C$7:$C$731,'1. Status Resumo FY24'!$H$88,'2. Status Detalhe Campos FY24'!$D$7:$D$731,"2. Campo") -> 0 | V104: =U104-T104 -> -6
E105: =+"#"&$U$119 -> #296 | P105: Requisitos FY24 | T105: =COUNTIFS('2. Status Detalhe Campos FY24'!$H$7:$H$731,'1. Status Resumo FY24'!$P104,'2. Status Detalhe Campos FY24'!$C$7:$C$731,'1. Status Resumo FY24'!$G$88,'2. Status Detalhe Campos FY24'!$D$7:$D$731,"2. Campo",'2. Status Detalhe Campos FY24'!$T$7:$T$731,"*Plano anterior*") +COUNTIFS('2. Status Detalhe Campos FY24'!$H$7:$H$731,'1. Status Resumo FY24'!$P104,'2. Status Detalhe Campos FY24'!$C$7:$C$731,'1. Status Resumo FY24'!$H$88,'2. Status Detalhe Campos FY24'!$D$7:$D$731,"2. Campo",'2. Status Detalhe Campos FY24'!$T$7:$T$731,"*Plano anterior*") -> 6 | U105: =COUNTIFS('2. Status Detalhe Campos FY24'!$G$7:$G$731,'1. Status Resumo FY24'!$P104,'2. Status Detalhe Campos FY24'!$C$7:$C$731,'1. Status Resumo FY24'!$G$88,'2. Status Detalhe Campos FY24'!$D$7:$D$731,"2. Campo",'2. Status Detalhe Campos FY24'!$T$7:$T$731,"*Plano anterior*") +COUNTIFS('2. Status Detalhe Campos FY24'!$G$7:$G$731,'1. Status Resumo FY24'!$P104,'2. Status Detalhe Campos FY24'!$C$7:$C$731,'1. Status Resumo FY24'!$H$88,'2. Status Detalhe Campos FY24'!$D$7:$D$731,"2. Campo",'2. Status Detalhe Campos FY24'!$T$7:$T$731,"*Plano anterior*") -> 0 | V105: =U105-T105 -> -6
P106: Novos Requisitos FY25 | T106: =COUNTIFS('2. Status Detalhe Campos FY24'!$H$7:$H$731,'1. Status Resumo FY24'!$P104,'2. Status Detalhe Campos FY24'!$C$7:$C$731,'1. Status Resumo FY24'!$G$88,'2. Status Detalhe Campos FY24'!$D$7:$D$731,"2. Campo",'2. Status Detalhe Campos FY24'!$T$7:$T$731,"*Novo Plano*") +COUNTIFS('2. Status Detalhe Campos FY24'!$H$7:$H$731,'1. Status Resumo FY24'!$P104,'2. Status Detalhe Campos FY24'!$C$7:$C$731,'1. Status Resumo FY24'!$H$88,'2. Status Detalhe Campos FY24'!$D$7:$D$731,"2. Campo",'2. Status Detalhe Campos FY24'!$T$7:$T$731,"*Novo Plano*") -> 0 | U106: =COUNTIFS('2. Status Detalhe Campos FY24'!$G$7:$G$731,'1. Status Resumo FY24'!$P104,'2. Status Detalhe Campos FY24'!$C$7:$C$731,'1. Status Resumo FY24'!$G$88,'2. Status Detalhe Campos FY24'!$D$7:$D$731,"2. Campo",'2. Status Detalhe Campos FY24'!$T$7:$T$731,"*Novo Plano*") +COUNTIFS('2. Status Detalhe Campos FY24'!$G$7:$G$731,'1. Status Resumo FY24'!$P104,'2. Status Detalhe Campos FY24'!$C$7:$C$731,'1. Status Resumo FY24'!$H$88,'2. Status Detalhe Campos FY24'!$D$7:$D$731,"2. Campo",'2. Status Detalhe Campos FY24'!$T$7:$T$731,"*Novo Plano*") -> 0 | V106: =U106-T106 -> 0
P107: 4. Validação EF | T107: =COUNTIFS('2. Status Detalhe Campos FY24'!$H$7:$H$731,'1. Status Resumo FY24'!$P107,'2. Status Detalhe Campos FY24'!$C$7:$C$731,'1. Status Resumo FY24'!$G$88,'2. Status Detalhe Campos FY24'!$D$7:$D$731,"2. Campo")+COUNTIFS('2. Status Detalhe Campos FY24'!$H$7:$H$731,'1. Status Resumo FY24'!$P107,'2. Status Detalhe Campos FY24'!$C$7:$C$731,'1. Status Resumo FY24'!$H$88,'2. Status Detalhe Campos FY24'!$D$7:$D$731,"2. Campo") -> 55 | U107: =COUNTIFS('2. Status Detalhe Campos FY24'!$G$7:$G$731,'1. Status Resumo FY24'!$P107,'2. Status Detalhe Campos FY24'!$C$7:$C$731,'1. Status Resumo FY24'!$G$88,'2. Status Detalhe Campos FY24'!$D$7:$D$731,"2. Campo")+COUNTIFS('2. Status Detalhe Campos FY24'!$G$7:$G$731,'1. Status Resumo FY24'!$P107,'2. Status Detalhe Campos FY24'!$C$7:$C$731,'1. Status Resumo FY24'!$H$88,'2. Status Detalhe Campos FY24'!$D$7:$D$731,"2. Campo") -> 0 | V107: =U107-T107 -> -55
P108: Requisitos FY24 | T108: =COUNTIFS('2. Status Detalhe Campos FY24'!$H$7:$H$731,'1. Status Resumo FY24'!$P107,'2. Status Detalhe Campos FY24'!$C$7:$C$731,'1. Status Resumo FY24'!$G$88,'2. Status Detalhe Campos FY24'!$D$7:$D$731,"2. Campo",'2. Status Detalhe Campos FY24'!$T$7:$T$731,"*Plano anterior*") +COUNTIFS('2. Status Detalhe Campos FY24'!$H$7:$H$731,'1. Status Resumo FY24'!$P107,'2. Status Detalhe Campos FY24'!$C$7:$C$731,'1. Status Resumo FY24'!$H$88,'2. Status Detalhe Campos FY24'!$D$7:$D$731,"2. Campo",'2. Status Detalhe Campos FY24'!$T$7:$T$731,"*Plano anterior*") -> 55 | U108: =COUNTIFS('2. Status Detalhe Campos FY24'!$G$7:$G$731,'1. Status Resumo FY24'!$P107,'2. Status Detalhe Campos FY24'!$C$7:$C$731,'1. Status Resumo FY24'!$G$88,'2. Status Detalhe Campos FY24'!$D$7:$D$731,"2. Campo",'2. Status Detalhe Campos FY24'!$T$7:$T$731,"*Plano anterior*") +COUNTIFS('2. Status Detalhe Campos FY24'!$G$7:$G$731,'1. Status Resumo FY24'!$P107,'2. Status Detalhe Campos FY24'!$C$7:$C$731,'1. Status Resumo FY24'!$H$88,'2. Status Detalhe Campos FY24'!$D$7:$D$731,"2. Campo",'2. Status Detalhe Campos FY24'!$T$7:$T$731,"*Plano anterior*") -> 0 | V108: =U108-T108 -> -55
P109: Novos Requisitos FY25 | T109: =COUNTIFS('2. Status Detalhe Campos FY24'!$H$7:$H$731,'1. Status Resumo FY24'!$P107,'2. Status Detalhe Campos FY24'!$C$7:$C$731,'1. Status Resumo FY24'!$G$88,'2. Status Detalhe Campos FY24'!$D$7:$D$731,"2. Campo",'2. Status Detalhe Campos FY24'!$T$7:$T$731,"*Novo Plano*") +COUNTIFS('2. Status Detalhe Campos FY24'!$H$7:$H$731,'1. Status Resumo FY24'!$P107,'2. Status Detalhe Campos FY24'!$C$7:$C$731,'1. Status Resumo FY24'!$H$88,'2. Status Detalhe Campos FY24'!$D$7:$D$731,"2. Campo",'2. Status Detalhe Campos FY24'!$T$7:$T$731,"*Novo Plano*") -> 0 | U109: =COUNTIFS('2. Status Detalhe Campos FY24'!$G$7:$G$731,'1. Status Resumo FY24'!$P107,'2. Status Detalhe Campos FY24'!$C$7:$C$731,'1. Status Resumo FY24'!$G$88,'2. Status Detalhe Campos FY24'!$D$7:$D$731,"2. Campo",'2. Status Detalhe Campos FY24'!$T$7:$T$731,"*Novo Plano*") +COUNTIFS('2. Status Detalhe Campos FY24'!$G$7:$G$731,'1. Status Resumo FY24'!$P107,'2. Status Detalhe Campos FY24'!$C$7:$C$731,'1. Status Resumo FY24'!$H$88,'2. Status Detalhe Campos FY24'!$D$7:$D$731,"2. Campo",'2. Status Detalhe Campos FY24'!$T$7:$T$731,"*Novo Plano*") -> 0 | V109: =U109-T109 -> 0
P110: 5. Em Correção | R110: (incidências) | T110: =COUNTIFS('2. Status Detalhe Campos FY24'!$H$7:$H$731,'1. Status Resumo FY24'!$P110,'2. Status Detalhe Campos FY24'!$C$7:$C$731,'1. Status Resumo FY24'!$G$88,'2. Status Detalhe Campos FY24'!$D$7:$D$731,"2. Campo")+COUNTIFS('2. Status Detalhe Campos FY24'!$H$7:$H$731,'1. Status Resumo FY24'!$P110,'2. Status Detalhe Campos FY24'!$C$7:$C$731,'1. Status Resumo FY24'!$H$88,'2. Status Detalhe Campos FY24'!$D$7:$D$731,"2. Campo") -> 0 | U110: =COUNTIFS('2. Status Detalhe Campos FY24'!$G$7:$G$731,'1. Status Resumo FY24'!$P110,'2. Status Detalhe Campos FY24'!$C$7:$C$731,'1. Status Resumo FY24'!$G$88,'2. Status Detalhe Campos FY24'!$D$7:$D$731,"2. Campo")+COUNTIFS('2. Status Detalhe Campos FY24'!$G$7:$G$731,'1. Status Resumo FY24'!$P110,'2. Status Detalhe Campos FY24'!$C$7:$C$731,'1. Status Resumo FY24'!$H$88,'2. Status Detalhe Campos FY24'!$D$7:$D$731,"2. Campo") -> 0 | V110: =U110-T110 -> 0
P111: Requisitos FY24 | T111: =COUNTIFS('2. Status Detalhe Campos FY24'!$H$7:$H$731,'1. Status Resumo FY24'!$P110,'2. Status Detalhe Campos FY24'!$C$7:$C$731,'1. Status Resumo FY24'!$G$88,'2. Status Detalhe Campos FY24'!$D$7:$D$731,"2. Campo",'2. Status Detalhe Campos FY24'!$T$7:$T$731,"*Plano anterior*") +COUNTIFS('2. Status Detalhe Campos FY24'!$H$7:$H$731,'1. Status Resumo FY24'!$P110,'2. Status Detalhe Campos FY24'!$C$7:$C$731,'1. Status Resumo FY24'!$H$88,'2. Status Detalhe Campos FY24'!$D$7:$D$731,"2. Campo",'2. Status Detalhe Campos FY24'!$T$7:$T$731,"*Plano anterior*") -> 0 | U111: =COUNTIFS('2. Status Detalhe Campos FY24'!$G$7:$G$731,'1. Status Resumo FY24'!$P110,'2. Status Detalhe Campos FY24'!$C$7:$C$731,'1. Status Resumo FY24'!$G$88,'2. Status Detalhe Campos FY24'!$D$7:$D$731,"2. Campo",'2. Status Detalhe Campos FY24'!$T$7:$T$731,"*Plano anterior*") +COUNTIFS('2. Status Detalhe Campos FY24'!$G$7:$G$731,'1. Status Resumo FY24'!$P110,'2. Status Detalhe Campos FY24'!$C$7:$C$731,'1. Status Resumo FY24'!$H$88,'2. Status Detalhe Campos FY24'!$D$7:$D$731,"2. Campo",'2. Status Detalhe Campos FY24'!$T$7:$T$731,"*Plano anterior*") -> 0 | V111: =U111-T111 -> 0
P112: Novos Requisitos FY25 | T112: =COUNTIFS('2. Status Detalhe Campos FY24'!$H$7:$H$731,'1. Status Resumo FY24'!$P110,'2. Status Detalhe Campos FY24'!$C$7:$C$731,'1. Status Resumo FY24'!$G$88,'2. Status Detalhe Campos FY24'!$D$7:$D$731,"2. Campo",'2. Status Detalhe Campos FY24'!$T$7:$T$731,"*Novo Plano*") +COUNTIFS('2. Status Detalhe Campos FY24'!$H$7:$H$731,'1. Status Resumo FY24'!$P110,'2. Status Detalhe Campos FY24'!$C$7:$C$731,'1. Status Resumo FY24'!$H$88,'2. Status Detalhe Campos FY24'!$D$7:$D$731,"2. Campo",'2. Status Detalhe Campos FY24'!$T$7:$T$731,"*Novo Plano*") -> 0 | U112: =COUNTIFS('2. Status Detalhe Campos FY24'!$G$7:$G$731,'1. Status Resumo FY24'!$P110,'2. Status Detalhe Campos FY24'!$C$7:$C$731,'1. Status Resumo FY24'!$G$88,'2. Status Detalhe Campos FY24'!$D$7:$D$731,"2. Campo",'2. Status Detalhe Campos FY24'!$T$7:$T$731,"*Novo Plano*") +COUNTIFS('2. Status Detalhe Campos FY24'!$G$7:$G$731,'1. Status Resumo FY24'!$P110,'2. Status Detalhe Campos FY24'!$C$7:$C$731,'1. Status Resumo FY24'!$H$88,'2. Status Detalhe Campos FY24'!$D$7:$D$731,"2. Campo",'2. Status Detalhe Campos FY24'!$T$7:$T$731,"*Novo Plano*") -> 0 | V112: =U112-T112 -> 0
P113: 6. Em implementação | T113: =COUNTIFS('2. Status Detalhe Campos FY24'!$H$7:$H$731,'1. Status Resumo FY24'!$P113,'2. Status Detalhe Campos FY24'!$C$7:$C$731,'1. Status Resumo FY24'!$G$88,'2. Status Detalhe Campos FY24'!$D$7:$D$731,"2. Campo")+COUNTIFS('2. Status Detalhe Campos FY24'!$H$7:$H$731,'1. Status Resumo FY24'!$P113,'2. Status Detalhe Campos FY24'!$C$7:$C$731,'1. Status Resumo FY24'!$H$88,'2. Status Detalhe Campos FY24'!$D$7:$D$731,"2. Campo") -> 21 | U113: =COUNTIFS('2. Status Detalhe Campos FY24'!$G$7:$G$731,'1. Status Resumo FY24'!$P113,'2. Status Detalhe Campos FY24'!$C$7:$C$731,'1. Status Resumo FY24'!$G$88,'2. Status Detalhe Campos FY24'!$D$7:$D$731,"2. Campo")+COUNTIFS('2. Status Detalhe Campos FY24'!$G$7:$G$731,'1. Status Resumo FY24'!$P113,'2. Status Detalhe Campos FY24'!$C$7:$C$731,'1. Status Resumo FY24'!$H$88,'2. Status Detalhe Campos FY24'!$D$7:$D$731,"2. Campo") -> 14 | V113: =U113-T113 -> -7
P114: Requisitos FY24 | T114: =COUNTIFS('2. Status Detalhe Campos FY24'!$H$7:$H$731,'1. Status Resumo FY24'!$P113,'2. Status Detalhe Campos FY24'!$C$7:$C$731,'1. Status Resumo FY24'!$G$88,'2. Status Detalhe Campos FY24'!$D$7:$D$731,"2. Campo",'2. Status Detalhe Campos FY24'!$T$7:$T$731,"*Plano anterior*") +COUNTIFS('2. Status Detalhe Campos FY24'!$H$7:$H$731,'1. Status Resumo FY24'!$P113,'2. Status Detalhe Campos FY24'!$C$7:$C$731,'1. Status Resumo FY24'!$H$88,'2. Status Detalhe Campos FY24'!$D$7:$D$731,"2. Campo",'2. Status Detalhe Campos FY24'!$T$7:$T$731,"*Plano anterior*") -> 1 | U114: =COUNTIFS('2. Status Detalhe Campos FY24'!$G$7:$G$731,'1. Status Resumo FY24'!$P113,'2. Status Detalhe Campos FY24'!$C$7:$C$731,'1. Status Resumo FY24'!$G$88,'2. Status Detalhe Campos FY24'!$D$7:$D$731,"2. Campo",'2. Status Detalhe Campos FY24'!$T$7:$T$731,"*Plano anterior*") +COUNTIFS('2. Status Detalhe Campos FY24'!$G$7:$G$731,'1. Status Resumo FY24'!$P113,'2. Status Detalhe Campos FY24'!$C$7:$C$731,'1. Status Resumo FY24'!$H$88,'2. Status Detalhe Campos FY24'!$D$7:$D$731,"2. Campo",'2. Status Detalhe Campos FY24'!$T$7:$T$731,"*Plano anterior*") -> 9 | V114: =U114-T114 -> 8
P115: Novos Requisitos FY25 | T115: =COUNTIFS('2. Status Detalhe Campos FY24'!$H$7:$H$731,'1. Status Resumo FY24'!$P113,'2. Status Detalhe Campos FY24'!$C$7:$C$731,'1. Status Resumo FY24'!$G$88,'2. Status Detalhe Campos FY24'!$D$7:$D$731,"2. Campo",'2. Status Detalhe Campos FY24'!$T$7:$T$731,"*Novo Plano*") +COUNTIFS('2. Status Detalhe Campos FY24'!$H$7:$H$731,'1. Status Resumo FY24'!$P113,'2. Status Detalhe Campos FY24'!$C$7:$C$731,'1. Status Resumo FY24'!$H$88,'2. Status Detalhe Campos FY24'!$D$7:$D$731,"2. Campo",'2. Status Detalhe Campos FY24'!$T$7:$T$731,"*Novo Plano*") -> 20 | U115: =COUNTIFS('2. Status Detalhe Campos FY24'!$G$7:$G$731,'1. Status Resumo FY24'!$P113,'2. Status Detalhe Campos FY24'!$C$7:$C$731,'1. Status Resumo FY24'!$G$88,'2. Status Detalhe Campos FY24'!$D$7:$D$731,"2. Campo",'2. Status Detalhe Campos FY24'!$T$7:$T$731,"*Novo Plano*") +COUNTIFS('2. Status Detalhe Campos FY24'!$G$7:$G$731,'1. Status Resumo FY24'!$P113,'2. Status Detalhe Campos FY24'!$C$7:$C$731,'1. Status Resumo FY24'!$H$88,'2. Status Detalhe Campos FY24'!$D$7:$D$731,"2. Campo",'2. Status Detalhe Campos FY24'!$T$7:$T$731,"*Novo Plano*") -> 5 | V115: =U115-T115 -> -15
P116: 7. Por iniciar | T116: =COUNTIFS('2. Status Detalhe Campos FY24'!$H$7:$H$731,'1. Status Resumo FY24'!$P116,'2. Status Detalhe Campos FY24'!$C$7:$C$731,'1. Status Resumo FY24'!$G$88,'2. Status Detalhe Campos FY24'!$D$7:$D$731,"2. Campo")+COUNTIFS('2. Status Detalhe Campos FY24'!$H$7:$H$731,'1. Status Resumo FY24'!$P116,'2. Status Detalhe Campos FY24'!$C$7:$C$731,'1. Status Resumo FY24'!$H$88,'2. Status Detalhe Campos FY24'!$D$7:$D$731,"2. Campo") -> 5 | U116: =COUNTIFS('2. Status Detalhe Campos FY24'!$G$7:$G$731,'1. Status Resumo FY24'!$P116,'2. Status Detalhe Campos FY24'!$C$7:$C$731,'1. Status Resumo FY24'!$G$88,'2. Status Detalhe Campos FY24'!$D$7:$D$731,"2. Campo")+COUNTIFS('2. Status Detalhe Campos FY24'!$G$7:$G$731,'1. Status Resumo FY24'!$P116,'2. Status Detalhe Campos FY24'!$C$7:$C$731,'1. Status Resumo FY24'!$H$88,'2. Status Detalhe Campos FY24'!$D$7:$D$731,"2. Campo") -> 0 | V116: =U116-T116 -> -5
P117: Requisitos FY24 | T117: =COUNTIFS('2. Status Detalhe Campos FY24'!$H$7:$H$731,'1. Status Resumo FY24'!$P116,'2. Status Detalhe Campos FY24'!$C$7:$C$731,'1. Status Resumo FY24'!$G$88,'2. Status Detalhe Campos FY24'!$D$7:$D$731,"2. Campo",'2. Status Detalhe Campos FY24'!$T$7:$T$731,"*Plano anterior*") +COUNTIFS('2. Status Detalhe Campos FY24'!$H$7:$H$731,'1. Status Resumo FY24'!$P116,'2. Status Detalhe Campos FY24'!$C$7:$C$731,'1. Status Resumo FY24'!$H$88,'2. Status Detalhe Campos FY24'!$D$7:$D$731,"2. Campo",'2. Status Detalhe Campos FY24'!$T$7:$T$731,"*Plano anterior*") -> 0 | U117: =COUNTIFS('2. Status Detalhe Campos FY24'!$G$7:$G$731,'1. Status Resumo FY24'!$P116,'2. Status Detalhe Campos FY24'!$C$7:$C$731,'1. Status Resumo FY24'!$G$88,'2. Status Detalhe Campos FY24'!$D$7:$D$731,"2. Campo",'2. Status Detalhe Campos FY24'!$T$7:$T$731,"*Plano anterior*") +COUNTIFS('2. Status Detalhe Campos FY24'!$G$7:$G$731,'1. Status Resumo FY24'!$P116,'2. Status Detalhe Campos FY24'!$C$7:$C$731,'1. Status Resumo FY24'!$H$88,'2. Status Detalhe Campos FY24'!$D$7:$D$731,"2. Campo",'2. Status Detalhe Campos FY24'!$T$7:$T$731,"*Plano anterior*") -> 0 | V117: =U117-T117 -> 0
P118: Novos Requisitos FY25 | T118: =COUNTIFS('2. Status Detalhe Campos FY24'!$H$7:$H$731,'1. Status Resumo FY24'!$P116,'2. Status Detalhe Campos FY24'!$C$7:$C$731,'1. Status Resumo FY24'!$G$88,'2. Status Detalhe Campos FY24'!$D$7:$D$731,"2. Campo",'2. Status Detalhe Campos FY24'!$T$7:$T$731,"*Novo Plano*") +COUNTIFS('2. Status Detalhe Campos FY24'!$H$7:$H$731,'1. Status Resumo FY24'!$P116,'2. Status Detalhe Campos FY24'!$C$7:$C$731,'1. Status Resumo FY24'!$H$88,'2. Status Detalhe Campos FY24'!$D$7:$D$731,"2. Campo",'2. Status Detalhe Campos FY24'!$T$7:$T$731,"*Novo Plano*") -> 5 | U118: =COUNTIFS('2. Status Detalhe Campos FY24'!$G$7:$G$731,'1. Status Resumo FY24'!$P116,'2. Status Detalhe Campos FY24'!$C$7:$C$731,'1. Status Resumo FY24'!$G$88,'2. Status Detalhe Campos FY24'!$D$7:$D$731,"2. Campo",'2. Status Detalhe Campos FY24'!$T$7:$T$731,"*Novo Plano*") +COUNTIFS('2. Status Detalhe Campos FY24'!$G$7:$G$731,'1. Status Resumo FY24'!$P116,'2. Status Detalhe Campos FY24'!$C$7:$C$731,'1. Status Resumo FY24'!$H$88,'2. Status Detalhe Campos FY24'!$D$7:$D$731,"2. Campo",'2. Status Detalhe Campos FY24'!$T$7:$T$731,"*Novo Plano*") -> 0 | V118: =U118-T118 -> -5
P119: Total | T119: =+SUM(T92,T95,T98,T104,T107,T110,T113,T116,T101) -> 296 | U119: =+SUM(U92,U95,U98,U104,U107,U110,U113,U116,U101) -> 296 | V119: =+U119-T119 -> 0
...

Sheet Auxiliar
D2: Estimação Horas
B3: Tipologia de testes | D3: Complexidade
B4: Categorização de Testes | C4: Descrição | D4: Baixa | E4: Média | F4: Alta | H4: Baixa | I4: Média | J4: Alta
B5: 1. Teste de universo | C5: 1. Validação de universo de contratos (quando comparado âmbito "CDG" e "PM", e numero de registos) 2. Controlos sobre o desdobramento de chaves nas relações FR-MIS | D5: 8 | E5: 8 | F5: 8 | H5: 1 | I5: 3 | J5: 8
B6: 2. Simulação | C6: Simulação da especificação funcional. Suplementarmente, realizar reuniões de validações e esclarecimentos funcionais junto do negócio/owner. | D6: 2 | E6: 4 | F6: 8 | H6: 1 | I6: 3 | J6: 4
B7: 3. Testes comparativos (Espec. VS Impl.) | C7: A partir da simulação realizada, comparar resultados com a implementação de IT. | D7: 2 | E7: 4 | F7: 8 | H7: 1 | I7: 1 | J7: 2
B8: 4. Validação de parametrizações | C8: A partir da simulação realizada, comparar com as parametrizações implementadas por IT. | D8: 2 | E8: 4 | F8: 8 | H8: 2 | I8: 4 | J8: 4
B9: 5. Teste comparativos com LT | C9: Garantir que a informação do campo da LT-ESTR âmbito 'PM' está espelhado no âmbito 'CDG'. | D9: 1 | E9: 1 | F9: 1
B10: 6. Validação de formatos | C10: Validação de formato de acordo com o que é esperado pela Corporação (incluindo validação de codelists, missing e default values) Validar especificação e controlos da especificação vs o que está implementado | D10: 0.1 | E10: 0.1 | F10: 0.1 | H10: 0.1 | I10: 0.5 | J10: 0.5
B11: 7. Validação de controlos corporativos | C11: Validar controlos corporativos e se a especificação cumpre os requisitos. | D11: 1 | E11: 2 | F11: 2
B12: 8. Teste de Carregamento | C12: Garantir que o carregamento do ficheiro é realizado com sucesso no Front. | D12: 0.5 | E12: 0.5 | F12: 0.5 | H12: 0.5 | I12: 0.5 | J12: 0.5
B13: 9. Teste de Integridade | C13: Garantir integridade entre o ficheiro importado pela equipa de testes e o ficheiro de tecnologia (Ex: Garantir que a informação de todos os campos está correta de acordo com os dados corporativos) | D13: 0.5 | E13: 0.5 | F13: 0.5 | H13: 0.5 | I13: 0.5 | J13: 0.5
B15: Status
B16: 1. Concluído | C16: =_xlfn.NUMBERVALUE(LEFT(B16,1)) -> 1 | D16: 1 | E16: 1
A17: Pendente de outros campos/tabelas | B17: 3. Pendente de outros desenvolvimentos | C17: 4 | D17: 0.25 | E17: 0
B18: 7. Por iniciar | C18: 8 | D18: 0 | E18: 0
B19: 2.1 Em Teste | C19: =_xlfn.NUMBERVALUE(LEFT(B19,1)) -> 2 | D19: 0.5 | E19: 0.25
B20: 2.2 Em especificação | C20: 3 | D20: 0.5 | E20: 0
A21: Validação da Susana/LCM/Corp/conceito/alterações | B21: 4. Validação EF | C21: 5 | D21: 0.25 | E21: 0.25
A22: Por IT | B22: 5. Em Correção | C22: 6 | D22: 0.25 | E22: 0
A23: Por IT | B23: 6. Em implementação | C23: 7 | D23: 0.25 | E23: 0
A24: Campo eliminado | B24: 0. Cancelado | C24: =_xlfn.NUMBERVALUE(LEFT(B24,1)) -> 0 | D24: 0 | E24: 0

Sheet Aux - Pivots2
B2: 1. Visão Geral
B6: Âmbito | C6: Pilar III
B7: Tipo de teste | C7: 2. Campo
C9: Column Labels
C10: 0. Cancelado | D10: 1. Concluído | E10: 2.1 Em Teste | F10: 3. Pendente de outros desenvolvimentos | G10: 4. Validação EF | H10: 7. Por iniciar | I10: 6. Em implementação | J10: 2.2 Em especificação | K10: Grand Total
B11: Count of Campo | C11: 32 | D11: 444 | E11: 26 | F11: 10 | G11: 2 | H11: 21 | I11: 113 | J11: 58 | K11: 706
B20: Âmbito | C20: Pilar III
B21: Tipo de teste | C21: 2. Campo
B23: Row Labels | C23: Count of Campo
B24: 0. Cancelado | C24: 32
B25: 1. Concluído | C25: 444
B26: 2.1 Em Teste | C26: 26
B27: 3. Pendente de outros desenvolvimentos | C27: 10
B28: 4. Validação EF | C28: 2
B29: 7. Por iniciar | C29: 21
B30: 6. Em implementação | C30: 113
B31: 2.2 Em especificação | C31: 58
B32: Grand Total | C32: 706
B42: 2. Modelo Bens imóveis
B45: Âmbito | C45: Pilar III
B46: Sub-âmbito | C46: (Multiple Items)
B47: Tipo de teste | C47: 2. Campo
B49: Count of Campo | C49: Column Labels
B50: Row Labels | C50: 0. Cancelado | D50: 1. Concluído | E50: 6. Em implementação | F50: Grand Total
B51: RESPONSIBILITY_PROCESS_REL | C51: 3 | D51: 17 | F51: 20
B52: PROPERTY_ENERGY_CERTIFICATE | D52: 69 | E52: 4 | F52: 73
B53: PROPERTY | C53: 2 | D53: 31 | F53: 33
B54: PROCESS_PROPERTY_REL | C54: 1 | D54: 14 | F54: 15
B55: PROCESS | C55: 4 | D55: 13 | F55: 17
B56: ENERGY_CERTIFICATE_EST_INPUT | C56: 2 | E56: 44 | F56: 46
B57: Grand Total | C57: 12 | D57: 144 | E57: 48 | F57: 204
B62: Âmbito | C62: Pilar III
B63: Sub-âmbito | C63: (Multiple Items)
B64: Tipo de teste | C64: 2. Campo
B66: Row Labels | C66: Count of Campo
B67: 0. Cancelado | C67: 12
B68: 1. Concluído | C68: 144
B69: 6. Em implementação | C69: 48
B70: Grand Total | C70: 204
B81: 3. Modelo Verde
B83: Âmbito | C83: Pilar III
B84: Sub-âmbito | C84: (Multiple Items)
B85: Tipo de teste | C85: 2. Campo
B87: Count of Campo | C87: Column Labels
B88: Row Labels | C88: 0. Cancelado | D88: 1. Concluído | E88: 2.1 Em Teste | F88: 2.2 Em especificação | G88: 6. Em implementação | H88: Grand Total
B89: modesg_param_sfics_taxon_europeia | C89: 4 | F89: 42 | H89: 46
B90: modesg_out_sfics_taxon_europeia | C90: 1 | D90: 1 | F90: 13 | H90: 15
B91: modesg_out_emss_vcls | D91: 15 | H91: 15
B92: modesg_out_empr_info_nfin | D92: 21 | E92: 26 | G92: 5 | H92: 52
B93: modesg_out_bens_imoveis | D93: 14 | G93: 4 | H93: 18
B94: modesg_inp_risco_fisico_zipcode | G94: 5 | H94: 5
B95: modesg_inp_risco_fisico | D95: 6 | H95: 6
B96: modesg_inp_project_finance | D96: 9 | H96: 9
B97: modesg_inp_nfrd_alinhamento_tax | D97: 41 | H97: 41
B98: modesg_inp_km_medios_emss_vcls | C98: 3 | D98: 6 | H98: 9
B99: modesg_inp_emss_vcls | D99: 17 | H99: 17
B100: modesg_inp_emss_scib | D100: 17 | H100: 17
B101: modesg_inp_emss_nace | C101: 7 | D101: 14 | H101: 21
B102: modesg_inp_emss_bens_imoveis | C102: 1 | D102: 17 | H102: 18
B103: modesg_inp_empr_excl_paris | D103: 7 | H103: 7
B104: Grand Total | C104: 16 | D104: 185 | E104: 26 | F104: 55 | G104: 14 | H104: 296
B107: Âmbito | C107: All
B108: Sub-âmbito | C108: Pilar III
B109: Tipo de teste | C109: 2. Campo
B111: Row Labels | C111: Count of Campo
B112: 0. Cancelado | C112: 4
B113: 1. Concluído | C113: 115
B114: 2.2 Em especificação | C114: 3
B115: 3. Pendente de outros desenvolvimentos | C115: 10
B116: 4. Validação EF | C116: 2
B117: 6. Em implementação | C117: 51
B118: 7. Por iniciar | C118: 21
B119: Grand Total | C119: 206
B126: 4. Loan Tape | Pilar III
B129: Âmbito | C129: Pilar III
B130: Sub-âmbito | C130: Pilar III
B131: Tipo de teste | C131: 2. Campo
B133: Count of Campo | C133: Column Labels
B134: Row Labels | C134: 0. Cancelado | D134: 1. Concluído | E134: 2.2 Em especificação | F134: 3. Pendente de outros desenvolvimentos | G134: 4. Validação EF | H134: 6. Em implementação | I134: 7. Por iniciar | J134: Grand Total
B135: lt002_instrument | D135: 23 | E135: 3 | F135: 4 | H135: 12 | I135: 4 | J135: 46
B136: lt003_entity | D136: 39 | F136: 4 | H136: 21 | I136: 3 | J136: 67
B137: lt004_protection | C137: 4 | D137: 18 | F137: 2 | H137: 14 | I137: 9 | J137: 47
B138: lt005_instr_ent | D138: 5 | J138: 5
B139: lt006_instr_prot | D139: 4 | H139: 1 | I139: 1 | J139: 6
B140: lt007_instr_activity | D140: 2 | G140: 2 | H140: 3 | I140: 4 | J140: 11
B141: lt826_esg_sbsctr | D141: 9 | J141: 9
B142: lt827_mthd_usd_instrmnt | D142: 15 | J142: 15
B143: Grand Total | C143: 4 | D143: 115 | E143: 3 | F143: 10 | G143: 2 | H143: 51 | I143: 21 | J143: 206
B150: Âmbito | C150: Pilar III
B151: Sub-âmbito | C151: Pilar III
B152: Tipo de teste | C152: 2. Campo
B154: Row Labels | C154: Count of Campo
B155: 1. Concluído | C155: 115
B156: 0. Cancelado | C156: 4
B157: 4. Validação EF | C157: 2
B158: 3. Pendente de outros desenvolvimentos | C158: 10
B159: 7. Por iniciar | C159: 21
B160: 2.2 Em especificação | C160: 3
B161: 6. Em implementação | C161: 51
B162: Grand Total | C162: 206
...

Sheet 2. Status Detalhe Campos FY24
E2: Novos requisitos
I5: APAGAR | J5: APAGAR | K5: APAGAR | Q5: APAGAR | R5: APAGAR | S5: APAGAR | T5: APAGAR | U5: APAGAR
B6: Âmbito | C6: Sub-âmbito | D6: Tipo de teste | E6: Tabela | F6: Campo | G6: Status Atual | H6: Status Anterior | I6: Observações - Especificações | J6: Observações - Testes | K6: Observações - Testes sem visibilidade | L6: Data de Pedido correção/esclarecimento | M6: Data de correção prevista | N6: Data de correção efetiva | O6: Data Prevista de Re-especificação | P6: Data Prevista de Teste | Q6: Projeto (Aux JB) | R6: LT Âmbito | S6: LT Âmbito- Aux | T6: Plano | U6: Owner
A7: =E7&F7 -> ENERGY_CERTIFICATE_EST_INPUTn.a. | B7: Pilar III | C7: Bens Imóveis - Input | D7: 1. Universo | E7: ENERGY_CERTIFICATE_EST_INPUT | F7: n.a. | G7: =VLOOKUP(A7,Plano_V3!$A$26:$G$759,7,0) -> 6. Em implementação | H7: 6. Em implementação | L7: =IF(VLOOKUP(A7,'Aux - pivots1'!$A:$E,3,0)=0, "",VLOOKUP(A7,'Aux - pivots1'!$A:$E,3,0)) | M7: =IF(VLOOKUP(A7,'Aux - pivots1'!$A:$E,4,0)=0, "",VLOOKUP(A7,'Aux - pivots1'!$A:$E,4,0)) | N7: =IF(VLOOKUP(A7,'Aux - pivots1'!$A:$E,5,0)=0, "",VLOOKUP(A7,'Aux - pivots1'!$A:$E,5,0)) | T7: Plano anterior
A8: =E8&F8 -> ENERGY_CERTIFICATE_EST_INPUTCHAVE_GLOVAL | B8: Pilar III | C8: Bens Imóveis - Input | D8: 2. Campo | E8: ENERGY_CERTIFICATE_EST_INPUT | F8: CHAVE_GLOVAL | G8: =VLOOKUP(A8,Plano_V3!$A$26:$G$759,7,0) -> 6. Em implementação | H8: 6. Em implementação | I8: Package 1 | J8: Package X | L8: =IF(VLOOKUP(A8,'Aux - pivots1'!$A:$E,3,0)=0, "",VLOOKUP(A8,'Aux - pivots1'!$A:$E,3,0)) | M8: =IF(VLOOKUP(A8,'Aux - pivots1'!$A:$E,4,0)=0, "",VLOOKUP(A8,'Aux - pivots1'!$A:$E,4,0)) | N8: =IF(VLOOKUP(A8,'Aux - pivots1'!$A:$E,5,0)=0, "",VLOOKUP(A8,'Aux - pivots1'!$A:$E,5,0)) | T8: Plano anterior (alteração nome)
A9: =E9&F9 -> ENERGY_CERTIFICATE_EST_INPUTPROPERTY_BANK_ID | B9: Pilar III | C9: Bens Imóveis - Input | D9: 2. Campo | E9: ENERGY_CERTIFICATE_EST_INPUT | F9: PROPERTY_BANK_ID | G9: =VLOOKUP(A9,Plano_V3!$A$26:$G$759,7,0) -> 6. Em implementação | H9: 6. Em implementação | I9: Package 1 | J9: Package X | L9: =IF(VLOOKUP(A9,'Aux - pivots1'!$A:$E,3,0)=0, "",VLOOKUP(A9,'Aux - pivots1'!$A:$E,3,0)) | M9: =IF(VLOOKUP(A9,'Aux - pivots1'!$A:$E,4,0)=0, "",VLOOKUP(A9,'Aux - pivots1'!$A:$E,4,0)) | N9: =IF(VLOOKUP(A9,'Aux - pivots1'!$A:$E,5,0)=0, "",VLOOKUP(A9,'Aux - pivots1'!$A:$E,5,0)) | T9: Plano anterior
A10: =E10&F10 -> ENERGY_CERTIFICATE_EST_INPUTPROPERTY_BRANCH_CODE | B10: Pilar III | C10: Bens Imóveis - Input | D10: 2. Campo | E10: ENERGY_CERTIFICATE_EST_INPUT | F10: PROPERTY_BRANCH_CODE | G10: =VLOOKUP(A10,Plano_V3!$A$26:$G$759,7,0) -> 6. Em implementação | H10: 6. Em implementação | I10: Package 1 | J10: Package X | L10: =IF(VLOOKUP(A10,'Aux - pivots1'!$A:$E,3,0)=0, "",VLOOKUP(A10,'Aux - pivots1'!$A:$E,3,0)) | M10: =IF(VLOOKUP(A10,'Aux - pivots1'!$A:$E,4,0)=0, "",VLOOKUP(A10,'Aux - pivots1'!$A:$E,4,0)) | N10: =IF(VLOOKUP(A10,'Aux - pivots1'!$A:$E,5,0)=0, "",VLOOKUP(A10,'Aux - pivots1'!$A:$E,5,0)) | T10: Plano anterior
A11: =E11&F11 -> ENERGY_CERTIFICATE_EST_INPUTPROPERTY_CONTRACT_ID | B11: Pilar III | C11: Bens Imóveis - Input | D11: 2. Campo | E11: ENERGY_CERTIFICATE_EST_INPUT | F11: PROPERTY_CONTRACT_ID | G11: =VLOOKUP(A11,Plano_V3!$A$26:$G$759,7,0) -> 6. Em implementação | H11: 6. Em implementação | I11: Package 1 | J11: Package X | L11: =IF(VLOOKUP(A11,'Aux - pivots1'!$A:$E,3,0)=0, "",VLOOKUP(A11,'Aux - pivots1'!$A:$E,3,0)) | M11: =IF(VLOOKUP(A11,'Aux - pivots1'!$A:$E,4,0)=0, "",VLOOKUP(A11,'Aux - pivots1'!$A:$E,4,0)) | N11: =IF(VLOOKUP(A11,'Aux - pivots1'!$A:$E,5,0)=0, "",VLOOKUP(A11,'Aux - pivots1'!$A:$E,5,0)) | T11: Plano anterior
A12: =E12&F12 -> ENERGY_CERTIFICATE_EST_INPUTPROPERTY_REFERENCE_CODE | B12: Pilar III | C12: Bens Imóveis - Input | D12: 2. Campo | E12: ENERGY_CERTIFICATE_EST_INPUT | F12: PROPERTY_REFERENCE_CODE | G12: =VLOOKUP(A12,Plano_V3!$A$26:$G$759,7,0) -> 6. Em implementação | H12: 6. Em implementação | I12: Package 1 | J12: Package X | L12: =IF(VLOOKUP(A12,'Aux - pivots1'!$A:$E,3,0)=0, "",VLOOKUP(A12,'Aux - pivots1'!$A:$E,3,0)) | M12: =IF(VLOOKUP(A12,'Aux - pivots1'!$A:$E,4,0)=0, "",VLOOKUP(A12,'Aux - pivots1'!$A:$E,4,0)) | N12: =IF(VLOOKUP(A12,'Aux - pivots1'!$A:$E,5,0)=0, "",VLOOKUP(A12,'Aux - pivots1'!$A:$E,5,0)) | T12: Plano anterior
A13: =E13&F13 -> ENERGY_CERTIFICATE_EST_INPUTCÓDIGO_DISTRITO | B13: Pilar III | C13: Bens Imóveis - Input | D13: 2. Campo | E13: ENERGY_CERTIFICATE_EST_INPUT | F13: CÓDIGO_DISTRITO | G13: =VLOOKUP(A13,Plano_V3!$A$26:$G$759,7,0) -> 6. Em implementação | H13: 6. Em implementação | I13: Package 1 | J13: Package X | L13: =IF(VLOOKUP(A13,'Aux - pivots1'!$A:$E,3,0)=0, "",VLOOKUP(A13,'Aux - pivots1'!$A:$E,3,0)) | M13: =IF(VLOOKUP(A13,'Aux - pivots1'!$A:$E,4,0)=0, "",VLOOKUP(A13,'Aux - pivots1'!$A:$E,4,0)) | N13: =IF(VLOOKUP(A13,'Aux - pivots1'!$A:$E,5,0)=0, "",VLOOKUP(A13,'Aux - pivots1'!$A:$E,5,0)) | T13: Plano anterior (sem visibilidade no PdS enviado 17/01)
A14: =E14&F14 -> ENERGY_CERTIFICATE_EST_INPUTNOMBRE_DISTRITO | B14: Pilar III | C14: Bens Imóveis - Input | D14: 2. Campo | E14: ENERGY_CERTIFICATE_EST_INPUT | F14: NOMBRE_DISTRITO | G14: =VLOOKUP(A14,Plano_V3!$A$26:$G$759,7,0) -> 6. Em implementação | H14: 6. Em implementação | I14: Package 1 | J14: Package X | L14: =IF(VLOOKUP(A14,'Aux - pivots1'!$A:$E,3,0)=0, "",VLOOKUP(A14,'Aux - pivots1'!$A:$E,3,0)) | M14: =IF(VLOOKUP(A14,'Aux - pivots1'!$A:$E,4,0)=0, "",VLOOKUP(A14,'Aux - pivots1'!$A:$E,4,0)) | N14: =IF(VLOOKUP(A14,'Aux - pivots1'!$A:$E,5,0)=0, "",VLOOKUP(A14,'Aux - pivots1'!$A:$E,5,0)) | T14: Plano anterior (sem visibilidade no PdS enviado 17/01)
A15: =E15&F15 -> ENERGY_CERTIFICATE_EST_INPUTCÓDIGO_CONCEJO | B15: Pilar III | C15: Bens Imóveis - Input | D15: 2. Campo | E15: ENERGY_CERTIFICATE_EST_INPUT | F15: CÓDIGO_CONCEJO | G15: =VLOOKUP(A15,Plano_V3!$A$26:$G$759,7,0) -> 6. Em implementação | H15: 6. Em implementação | I15: Package 1 | J15: Package X | L15: =IF(VLOOKUP(A15,'Aux - pivots1'!$A:$E,3,0)=0, "",VLOOKUP(A15,'Aux - pivots1'!$A:$E,3,0)) | M15: =IF(VLOOKUP(A15,'Aux - pivots1'!$A:$E,4,0)=0, "",VLOOKUP(A15,'Aux - pivots1'!$A:$E,4,0)) | N15: =IF(VLOOKUP(A15,'Aux - pivots1'!$A:$E,5,0)=0, "",VLOOKUP(A15,'Aux - pivots1'!$A:$E,5,0)) | T15: Plano anterior (sem visibilidade no PdS enviado 17/01)
A16: =E16&F16 -> ENERGY_CERTIFICATE_EST_INPUTNOMBRE_CONCEJO | B16: Pilar III | C16: Bens Imóveis - Input | D16: 2. Campo | E16: ENERGY_CERTIFICATE_EST_INPUT | F16: NOMBRE_CONCEJO | G16: =VLOOKUP(A16,Plano_V3!$A$26:$G$759,7,0) -> 6. Em implementação | H16: 6. Em implementação | I16: Package 1 | J16: Package X | L16: =IF(VLOOKUP(A16,'Aux - pivots1'!$A:$E,3,0)=0, "",VLOOKUP(A16,'Aux - pivots1'!$A:$E,3,0)) | M16: =IF(VLOOKUP(A16,'Aux - pivots1'!$A:$E,4,0)=0, "",VLOOKUP(A16,'Aux - pivots1'!$A:$E,4,0)) | N16: =IF(VLOOKUP(A16,'Aux - pivots1'!$A:$E,5,0)=0, "",VLOOKUP(A16,'Aux - pivots1'!$A:$E,5,0)) | T16: Plano anterior (sem visibilidade no PdS enviado 17/01)
A17: =E17&F17 -> ENERGY_CERTIFICATE_EST_INPUTCÓDIGO_FREGUESIA | B17: Pilar III | C17: Bens Imóveis - Input | D17: 2. Campo | E17: ENERGY_CERTIFICATE_EST_INPUT | F17: CÓDIGO_FREGUESIA | G17: =VLOOKUP(A17,Plano_V3!$A$26:$G$759,7,0) -> 6. Em implementação | H17: 6. Em implementação | I17: Package 1 | J17: Package X | L17: =IF(VLOOKUP(A17,'Aux - pivots1'!$A:$E,3,0)=0, "",VLOOKUP(A17,'Aux - pivots1'!$A:$E,3,0)) | M17: =IF(VLOOKUP(A17,'Aux - pivots1'!$A:$E,4,0)=0, "",VLOOKUP(A17,'Aux - pivots1'!$A:$E,4,0)) | N17: =IF(VLOOKUP(A17,'Aux - pivots1'!$A:$E,5,0)=0, "",VLOOKUP(A17,'Aux - pivots1'!$A:$E,5,0)) | T17: Plano anterior (sem visibilidade no PdS enviado 17/01)
A18: =E18&F18 -> ENERGY_CERTIFICATE_EST_INPUTNOMBRE_FREGUESIA | B18: Pilar III | C18: Bens Imóveis - Input | D18: 2. Campo | E18: ENERGY_CERTIFICATE_EST_INPUT | F18: NOMBRE_FREGUESIA | G18: =VLOOKUP(A18,Plano_V3!$A$26:$G$759,7,0) -> 6. Em implementação | H18: 6. Em implementação | I18: Package 1 | J18: Package X | L18: =IF(VLOOKUP(A18,'Aux - pivots1'!$A:$E,3,0)=0, "",VLOOKUP(A18,'Aux - pivots1'!$A:$E,3,0)) | M18: =IF(VLOOKUP(A18,'Aux - pivots1'!$A:$E,4,0)=0, "",VLOOKUP(A18,'Aux - pivots1'!$A:$E,4,0)) | N18: =IF(VLOOKUP(A18,'Aux - pivots1'!$A:$E,5,0)=0, "",VLOOKUP(A18,'Aux - pivots1'!$A:$E,5,0)) | T18: Plano anterior (sem visibilidade no PdS enviado 17/01)
A19: =E19&F19 -> ENERGY_CERTIFICATE_EST_INPUTLOCALIDADE | B19: Pilar III | C19: Bens Imóveis - Input | D19: 2. Campo | E19: ENERGY_CERTIFICATE_EST_INPUT | F19: LOCALIDADE | G19: =VLOOKUP(A19,Plano_V3!$A$26:$G$759,7,0) -> 6. Em implementação | H19: 6. Em implementação | I19: Package 1 | J19: Package X | L19: =IF(VLOOKUP(A19,'Aux - pivots1'!$A:$E,3,0)=0, "",VLOOKUP(A19,'Aux - pivots1'!$A:$E,3,0)) | M19: =IF(VLOOKUP(A19,'Aux - pivots1'!$A:$E,4,0)=0, "",VLOOKUP(A19,'Aux - pivots1'!$A:$E,4,0)) | N19: =IF(VLOOKUP(A19,'Aux - pivots1'!$A:$E,5,0)=0, "",VLOOKUP(A19,'Aux - pivots1'!$A:$E,5,0)) | T19: Plano anterior (sem visibilidade no PdS enviado 17/01)
... A41: =E41&F41 -> ENERGY_CERTIFICATE_EST_INPUTART_MATRICIAIS | B41: Pilar III | C41: Bens Imóveis - Input | D41: 2. Campo | E41: ENERGY_CERTIFICATE_EST_INPUT | F41: ART_MATRICIAIS | G41: =VLOOKUP(A41,Plano_V3!$A$26:$G$759,7,0) -> 6. Em implementação | H41: 6. Em implementação | I41: Package 1 | J41: Package X | L41: =IF(VLOOKUP(A41,'Aux - pivots1'!$A:$E,3,0)=0, "",VLOOKUP(A41,'Aux - pivots1'!$A:$E,3,0)) | M41: =IF(VLOOKUP(A41,'Aux - pivots1'!$A:$E,4,0)=0, "",VLOOKUP(A41,'Aux - pivots1'!$A:$E,4,0)) | N41: =IF(VLOOKUP(A41,'Aux - pivots1'!$A:$E,5,0)=0, "",VLOOKUP(A41,'Aux - pivots1'!$A:$E,5,0)) | T41: Plano anterior (sem visibilidade no PdS enviado 17/01)
A42: =E42&F42 -> ENERGY_CERTIFICATE_EST_INPUTDATA_PROVIDER | B42: Pilar III | C42: Bens Imóveis - Input | D42: 2. Campo | E42: ENERGY_CERTIFICATE_EST_INPUT | F42: DATA_PROVIDER | G42: =VLOOKUP(A42,Plano_V3!$A$26:$G$759,7,0) -> 0. Cancelado | H42: 0. Cancelado | L42: =IF(VLOOKUP(A42,'Aux - pivots1'!$A:$E,3,0)=0, "",VLOOKUP(A42,'Aux - pivots1'!$A:$E,3,0)) | M42: =IF(VLOOKUP(A42,'Aux - pivots1'!$A:$E,4,0)=0, "",VLOOKUP(A42,'Aux - pivots1'!$A:$E,4,0)) | N42: =IF(VLOOKUP(A42,'Aux - pivots1'!$A:$E,5,0)=0, "",VLOOKUP(A42,'Aux - pivots1'!$A:$E,5,0)) | T42: Plano anterior
A43: =E43&F43 -> ENERGY_CERTIFICATE_EST_INPUTACTUAL_VALUE_IND | B43: Pilar III | C43: Bens Imóveis - Input | D43: 2. Campo | E43: ENERGY_CERTIFICATE_EST_INPUT | F43: ACTUAL_VALUE_IND | G43: =VLOOKUP(A43,Plano_V3!$A$26:$G$759,7,0) -> 0. Cancelado | H43: 0. Cancelado | L43: =IF(VLOOKUP(A43,'Aux - pivots1'!$A:$E,3,0)=0, "",VLOOKUP(A43,'Aux - pivots1'!$A:$E,3,0)) | M43: =IF(VLOOKUP(A43,'Aux - pivots1'!$A:$E,4,0)=0, "",VLOOKUP(A43,'Aux - pivots1'!$A:$E,4,0)) | N43: =IF(VLOOKUP(A43,'Aux - pivots1'!$A:$E,5,0)=0, "",VLOOKUP(A43,'Aux - pivots1'!$A:$E,5,0)) | T43: Plano anterior
A44: =E44&F44 -> ENERGY_CERTIFICATE_EST_INPUTFRACCAO_AUTONOMA | B44: Pilar III | C44: Bens Imóveis - Input | D44: 2. Campo | E44: ENERGY_CERTIFICATE_EST_INPUT | F44: FRACCAO_AUTONOMA | G44: =VLOOKUP(A44,Plano_V3!$A$26:$G$759,7,0) -> 6. Em implementação | H44: 6. Em implementação | I44: Package 1 | J44: Package X | L44: =IF(VLOOKUP(A44,'Aux - pivots1'!$A:$E,3,0)=0, "",VLOOKUP(A44,'Aux - pivots1'!$A:$E,3,0)) | M44: =IF(VLOOKUP(A44,'Aux - pivots1'!$A:$E,4,0)=0, "",VLOOKUP(A44,'Aux - pivots1'!$A:$E,4,0)) | N44: =IF(VLOOKUP(A44,'Aux - pivots1'!$A:$E,5,0)=0, "",VLOOKUP(A44,'Aux - pivots1'!$A:$E,5,0)) | T44: Plano anterior (sem visibilidade no PdS enviado 17/01)
A45: =E45&F45 -> ENERGY_CERTIFICATE_EST_INPUTFINALIDADE_BEM | B45: Pilar III | C45: Bens Imóveis - Input | D45: 2. Campo | E45: ENERGY_CERTIFICATE_EST_INPUT | F45: FINALIDADE_BEM | G45: =VLOOKUP(A45,Plano_V3!$A$26:$G$759,7,0) -> 6. Em implementação | H45: 6. Em implementação | I45: Package 1 | J45: Package X | L45: =IF(VLOOKUP(A45,'Aux - pivots1'!$A:$E,3,0)=0, "",VLOOKUP(A45,'Aux - pivots1'!$A:$E,3,0)) | M45: =IF(VLOOKUP(A45,'Aux - pivots1'!$A:$E,4,0)=0, "",VLOOKUP(A45,'Aux - pivots1'!$A:$E,4,0)) | N45: =IF(VLOOKUP(A45,'Aux - pivots1'!$A:$E,5,0)=0, "",VLOOKUP(A45,'Aux - pivots1'!$A:$E,5,0)) | T45: Plano anterior (sem visibilidade no PdS enviado 17/01)
A46: =E46&F46 -> ENERGY_CERTIFICATE_EST_INPUTCLASS_GPT31 | B46: Pilar III | C46: Bens Imóveis - Input | D46: 2. Campo | E46: ENERGY_CERTIFICATE_EST_INPUT | F46: CLASS_GPT31 | G46: =VLOOKUP(A46,Plano_V3!$A$26:$G$759,7,0) -> 6. Em implementação | H46: 6. Em implementação | I46: Package 1 | J46: Package X | L46: =IF(VLOOKUP(A46,'Aux - pivots1'!$A:$E,3,0)=0, "",VLOOKUP(A46,'Aux - pivots1'!$A:$E,3,0)) | M46: =IF(VLOOKUP(A46,'Aux - pivots1'!$A:$E,4,0)=0, "",VLOOKUP(A46,'Aux - pivots1'!$A:$E,4,0)) | N46: =IF(VLOOKUP(A46,'Aux - pivots1'!$A:$E,5,0)=0, "",VLOOKUP(A46,'Aux - pivots1'!$A:$E,5,0)) | T46: Plano anterior (sem visibilidade no PdS enviado 17/01)
A47: =E47&F47 -> ENERGY_CERTIFICATE_EST_INPUTCLASS_STCLIM | B47: Pilar III | C47: Bens Imóveis - Input | D47: 2. Campo | E47: ENERGY_CERTIFICATE_EST_INPUT | F47: CLASS_STCLIM | G47: =VLOOKUP(A47,Plano_V3!$A$26:$G$759,7,0) -> 6. Em implementação | H47: 6. Em implementação | I47: Package 1 | J47: Package X | L47: =IF(VLOOKUP(A47,'Aux - pivots1'!$A:$E,3,0)=0, "",VLOOKUP(A47,'Aux - pivots1'!$A:$E,3,0)) | M47: =IF(VLOOKUP(A47,'Aux - pivots1'!$A:$E,4,0)=0, "",VLOOKUP(A47,'Aux - pivots1'!$A:$E,4,0)) | N47: =IF(VLOOKUP(A47,'Aux - pivots1'!$A:$E,5,0)=0, "",VLOOKUP(A47,'Aux - pivots1'!$A:$E,5,0)) | T47: Plano anterior (sem visibilidade no PdS enviado 17/01)
A48: =E48&F48 -> ENERGY_CERTIFICATE_EST_INPUTCONF_STCLIM | B48: Pilar III | C48: Bens Imóveis - Input | D48: 2. Campo | E48: ENERGY_CERTIFICATE_EST_INPUT | F48: CONF_STCLIM | G48: =VLOOKUP(A48,Plano_V3!$A$26:$G$759,7,0) -> 6. Em implementação | H48: 6. Em implementação | I48: Package 1 | J48: Package X | L48: =IF(VLOOKUP(A48,'Aux - pivots1'!$A:$E,3,0)=0, "",VLOOKUP(A48,'Aux - pivots1'!$A:$E,3,0)) | M48: =IF(VLOOKUP(A48,'Aux - pivots1'!$A:$E,4,0)=0, "",VLOOKUP(A48,'Aux - pivots1'!$A:$E,4,0)) | N48: =IF(VLOOKUP(A48,'Aux - pivots1'!$A:$E,5,0)=0, "",VLOOKUP(A48,'Aux - pivots1'!$A:$E,5,0)) | T48: Plano anterior (sem visibilidade no PdS enviado 17/01)
A49: =E49&F49 -> ENERGY_CERTIFICATE_EST_INPUTCLASSE_ENERGETICA | B49: Pilar III | C49: Bens Imóveis - Input | D49: 2. Campo | E49: ENERGY_CERTIFICATE_EST_INPUT | F49: CLASSE_ENERGETICA | G49: =VLOOKUP(A49,Plano_V3!$A$26:$G$759,7,0) -> 6. Em implementação | H49: 6. Em implementação | I49: Package 1 | J49: Package X | L49: =IF(VLOOKUP(A49,'Aux - pivots1'!$A:$E,3,0)=0, "",VLOOKUP(A49,'Aux - pivots1'!$A:$E,3,0)) | M49: =IF(VLOOKUP(A49,'Aux - pivots1'!$A:$E,4,0)=0, "",VLOOKUP(A49,'Aux - pivots1'!$A:$E,4,0)) | N49: =IF(VLOOKUP(A49,'Aux - pivots1'!$A:$E,5,0)=0, "",VLOOKUP(A49,'Aux - pivots1'!$A:$E,5,0)) | T49: Plano anterior (alteração nome)
A50: =E50&F50 -> ENERGY_CERTIFICATE_EST_INPUTFIABILIDAD | B50: Pilar III | C50: Bens Imóveis - Input | D50: 2. Campo | E50: ENERGY_CERTIFICATE_EST_INPUT | F50: FIABILIDAD | G50: =VLOOKUP(A50,Plano_V3!$A$26:$G$759,7,0) -> 6. Em implementação | H50: 6. Em implementação | I50: Package 1 | J50: Package X | L50: =IF(VLOOKUP(A50,'Aux - pivots1'!$A:$E,3,0)=0, "",VLOOKUP(A50,'Aux - pivots1'!$A:$E,3,0)) | M50: =IF(VLOOKUP(A50,'Aux - pivots1'!$A:$E,4,0)=0, "",VLOOKUP(A50,'Aux - pivots1'!$A:$E,4,0)) | N50: =IF(VLOOKUP(A50,'Aux - pivots1'!$A:$E,5,0)=0, "",VLOOKUP(A50,'Aux - pivots1'!$A:$E,5,0)) | T50: Plano anterior (alteração nome)
A51: =E51&F51 -> ENERGY_CERTIFICATE_EST_INPUTEMISSIONES | B51: Pilar III | C51: Bens Imóveis - Input | D51: 2. Campo | E51: ENERGY_CERTIFICATE_EST_INPUT | F51: EMISSIONES | G51: =VLOOKUP(A51,Plano_V3!$A$26:$G$759,7,0) -> 6. Em implementação | H51: 6. Em implementação | I51: Package 1 | J51: Package X | L51: =IF(VLOOKUP(A51,'Aux - pivots1'!$A:$E,3,0)=0, "",VLOOKUP(A51,'Aux - pivots1'!$A:$E,3,0)) | M51: =IF(VLOOKUP(A51,'Aux - pivots1'!$A:$E,4,0)=0, "",VLOOKUP(A51,'Aux - pivots1'!$A:$E,4,0)) | N51: =IF(VLOOKUP(A51,'Aux - pivots1'!$A:$E,5,0)=0, "",VLOOKUP(A51,'Aux - pivots1'!$A:$E,5,0)) | T51: Plano anterior (alteração nome)
A52: =E52&F52 -> ENERGY_CERTIFICATE_EST_INPUTCONSUMOS | B52: Pilar III | C52: Bens Imóveis - Input | D52: 2. Campo | E52: ENERGY_CERTIFICATE_EST_INPUT | F52: CONSUMOS | G52: =VLOOKUP(A52,Plano_V3!$A$26:$G$759,7,0) -> 6. Em implementação | H52: 6. Em implementação | I52: Package 1 | J52: Package X | L52: =IF(VLOOKUP(A52,'Aux - pivots1'!$A:$E,3,0)=0, "",VLOOKUP(A52,'Aux - pivots1'!$A:$E,3,0)) | M52: =IF(VLOOKUP(A52,'Aux - pivots1'!$A:$E,4,0)=0, "",VLOOKUP(A52,'Aux - pivots1'!$A:$E,4,0)) | N52: =IF(VLOOKUP(A52,'Aux - pivots1'!$A:$E,5,0)=0, "",VLOOKUP(A52,'Aux - pivots1'!$A:$E,5,0)) | T52: Plano anterior (alteração nome)
A53: =E53&F53 -> ENERGY_CERTIFICATE_EST_INPUTDATA_ENVIO | B53: Pilar III | C53: Bens Imóveis - Input | D53: 2. Campo | E53: ENERGY_CERTIFICATE_EST_INPUT | F53: DATA_ENVIO | G53: =VLOOKUP(A53,Plano_V3!$A$26:$G$759,7,0) -> 6. Em implementação | H53: 6. Em implementação | I53: Package 1 | J53: Package X | L53: =IF(VLOOKUP(A53,'Aux - pivots1'!$A:$E,3,0)=0, "",VLOOKUP(A53,'Aux - pivots1'!$A:$E,3,0)) | M53: =IF(VLOOKUP(A53,'Aux - pivots1'!$A:$E,4,0)=0, "",VLOOKUP(A53,'Aux - pivots1'!$A:$E,4,0)) | N53: =IF(VLOOKUP(A53,'Aux - pivots1'!$A:$E,5,0)=0, "",VLOOKUP(A53,'Aux - pivots1'!$A:$E,5,0)) | T53: Plano anterior (alteração nome)
A54: =E54&F54 -> PROCESSn.a. | B54: Pilar III | C54: Bens Imóveis - Output | D54: 1. Universo | E54: PROCESS | F54: n.a. | G54: =VLOOKUP(A54,Plano_V3!$A$26:$G$759,7,0) -> 1. Concluído | H54: 1. Concluído | L54: =IF(VLOOKUP(A54,'Aux - pivots1'!$A:$E,3,0)=0, "",VLOOKUP(A54,'Aux - pivots1'!$A:$E,3,0)) | M54: =IF(VLOOKUP(A54,'Aux - pivots1'!$A:$E,4,0)=0, "",VLOOKUP(A54,'Aux - pivots1'!$A:$E,4,0)) | N54: =IF(VLOOKUP(A54,'Aux - pivots1'!$A:$E,5,0)=0, "",VLOOKUP(A54,'Aux - pivots1'!$A:$E,5,0)) | T54: Plano anterior
A55: =E55&F55 -> PROCESSPROCESS_BANK_ID | B55: Pilar III | C55: Bens Imóveis - Output | D55: 2. Campo | E55: PROCESS | F55: PROCESS_BANK_ID | G55: =VLOOKUP(A55,Plano_V3!$A$26:$G$759,7,0) -> 1. Concluído | H55: 1. Concluído | L55: =IF(VLOOKUP(A55,'Aux - pivots1'!$A:$E,3,0)=0, "",VLOOKUP(A55,'Aux - pivots1'!$A:$E,3,0)) | M55: =IF(VLOOKUP(A55,'Aux - pivots1'!$A:$E,4,0)=0, "",VLOOKUP(A55,'Aux - pivots1'!$A:$E,4,0)) | N55: =IF(VLOOKUP(A55,'Aux - pivots1'!$A:$E,5,0)=0, "",VLOOKUP(A55,'Aux - pivots1'!$A:$E,5,0)) | T55: Plano anterior
A56: =E56&F56 -> PROCESSPROCESS_BRANCH_CODE | B56: Pilar III | C56: Bens Imóveis - Output | D56: 2. Campo | E56: PROCESS | F56: PROCESS_BRANCH_CODE | G56: =VLOOKUP(A56,Plano_V3!$A$26:$G$759,7,0) -> 1. Concluído | H56: 1. Concluído | L56: =IF(VLOOKUP(A56,'Aux - pivots1'!$A:$E,3,0)=0, "",VLOOKUP(A56,'Aux - pivots1'!$A:$E,3,0)) | M56: =IF(VLOOKUP(A56,'Aux - pivots1'!$A:$E,4,0)=0, "",VLOOKUP(A56,'Aux - pivots1'!$A:$E,4,0)) | N56: =IF(VLOOKUP(A56,'Aux - pivots1'!$A:$E,5,0)=0, "",VLOOKUP(A56,'Aux - pivots1'!$A:$E,5,0)) | T56: Plano anterior
A57: =E57&F57 -> PROCESSPROCESS_ACCOUNT_ID | B57: Pilar III | C57: Bens Imóveis - Output | D57: 2. Campo | E57: PROCESS | F57: PROCESS_ACCOUNT_ID | G57: =VLOOKUP(A57,Plano_V3!$A$26:$G$759,7,0) -> 1. Concluído | H57: 1. Concluído | L57: =IF(VLOOKUP(A57,'Aux - pivots1'!$A:$E,3,0)=0, "",VLOOKUP(A57,'Aux - pivots1'!$A:$E,3,0)) | M57: =IF(VLOOKUP(A57,'Aux - pivots1'!$A:$E,4,0)=0, "",VLOOKUP(A57,'Aux - pivots1'!$A:$E,4,0)) | N57: =IF(VLOOKUP(A57,'Aux - pivots1'!$A:$E,5,0)=0, "",VLOOKUP(A57,'Aux - pivots1'!$A:$E,5,0)) | T57: Plano anterior
A58: =E58&F58 -> PROCESScod_estd_prcs | B58: Pilar III | C58: Bens Imóveis - Output | D58: 2. Campo | E58: PROCESS | F58: cod_estd_prcs | G58: =VLOOKUP(A58,Plano_V3!$A$26:$G$759,7,0) -> 0. Cancelado | H58: 0. Cancelado | L58: =IF(VLOOKUP(A58,'Aux - pivots1'!$A:$E,3,0)=0, "",VLOOKUP(A58,'Aux - pivots1'!$A:$E,3,0)) | M58: =IF(VLOOKUP(A58,'Aux - pivots1'!$A:$E,4,0)=0, "",VLOOKUP(A58,'Aux - pivots1'!$A:$E,4,0)) | N58: =IF(VLOOKUP(A58,'Aux - pivots1'!$A:$E,5,0)=0, "",VLOOKUP(A58,'Aux - pivots1'!$A:$E,5,0)) | T58: Plano anterior
A59: =E59&F59 -> PROCESSGUARANTEE_CODE | B59: Pilar III | C59: Bens Imóveis - Output | D59: 2. Campo | E59: PROCESS | F59: GUARANTEE_CODE | G59: =VLOOKUP(A59,Plano_V3!$A$26:$G$759,7,0) -> 1. Concluído | H59: 1. Concluído | L59: =IF(VLOOKUP(A59,'Aux - pivots1'!$A:$E,3,0)=0, "",VLOOKUP(A59,'Aux - pivots1'!$A:$E,3,0)) | M59: =IF(VLOOKUP(A59,'Aux - pivots1'!$A:$E,4,0)=0, "",VLOOKUP(A59,'Aux - pivots1'!$A:$E,4,0)) | N59: =IF(VLOOKUP(A59,'Aux - pivots1'!$A:$E,5,0)=0, "",VLOOKUP(A59,'Aux - pivots1'!$A:$E,5,0)) | T59: Plano anterior
A60: =E60&F60 -> PROCESSCURRENCY_CODE | B60: Pilar III | C60: Bens Imóveis - Output | D60: 2. Campo | E60: PROCESS | F60: CURRENCY_CODE | G60: =VLOOKUP(A60,Plano_V3!$A$26:$G$759,7,0) -> 1. Concluído | H60: 1. Concluído | L60: =IF(VLOOKUP(A60,'Aux - pivots1'!$A:$E,3,0)=0, "",VLOOKUP(A60,'Aux - pivots1'!$A:$E,3,0)) | M60: =IF(VLOOKUP(A60,'Aux - pivots1'!$A:$E,4,0)=0, "",VLOOKUP(A60,'Aux - pivots1'!$A:$E,4,0)) | N60: =IF(VLOOKUP(A60,'Aux - pivots1'!$A:$E,5,0)=0, "",VLOOKUP(A60,'Aux - pivots1'!$A:$E,5,0)) | T60: Plano anterior
A61: =E61&F61 -> PROCESSPROCESS_CAMPAIGN_CODE | B61: Pilar III | C61: Bens Imóveis - Output | D61: 2. Campo | E61: PROCESS | F61: PROCESS_CAMPAIGN_CODE | G61: =VLOOKUP(A61,Plano_V3!$A$26:$G$759,7,0) -> 1. Concluído | H61: 1. Concluído | L61: =IF(VLOOKUP(A61,'Aux - pivots1'!$A:$E,3,0)=0, "",VLOOKUP(A61,'Aux - pivots1'!$A:$E,3,0)) | M61: =IF(VLOOKUP(A61,'Aux - pivots1'!$A:$E,4,0)=0, "",VLOOKUP(A61,'Aux - pivots1'!$A:$E,4,0)) | N61: =IF(VLOOKUP(A61,'Aux - pivots1'!$A:$E,5,0)=0, "",VLOOKUP(A61,'Aux - pivots1'!$A:$E,5,0)) | T61: Plano anterior
A62: =E62&F62 -> PROCESSPROCESS_PRODUCT_ID | B62: Pilar III | C62: Bens Imóveis - Output | D62: 2. Campo | E62: PROCESS | F62: PROCESS_PRODUCT_ID | G62: =VLOOKUP(A62,Plano_V3!$A$26:$G$759,7,0) -> 1. Concluído | H62: 1. Concluído | L62: =IF(VLOOKUP(A62,'Aux - pivots1'!$A:$E,3,0)=0, "",VLOOKUP(A62,'Aux - pivots1'!$A:$E,3,0)) | M62: =IF(VLOOKUP(A62,'Aux - pivots1'!$A:$E,4,0)=0, "",VLOOKUP(A62,'Aux - pivots1'!$A:$E,4,0)) | N62: =IF(VLOOKUP(A62,'Aux - pivots1'!$A:$E,5,0)=0, "",VLOOKUP(A62,'Aux - pivots1'!$A:$E,5,0)) | T62: Plano anterior
A63: =E63&F63 -> PROCESSPROCESS_SUBPRODUCT_ID | B63: Pilar III | C63: Bens Imóveis - Output | D63: 2. Campo | E63: PROCESS | F63: PROCESS_SUBPRODUCT_ID | G63: =VLOOKUP(A63,Plano_V3!$A$26:$G$759,7,0) -> 1. Concluído | H63: 1. Concluído | L63: =IF(VLOOKUP(A63,'Aux - pivots1'!$A:$E,3,0)=0, "",VLOOKUP(A63,'Aux - pivots1'!$A:$E,3,0)) | M63: =IF(VLOOKUP(A63,'Aux - pivots1'!$A:$E,4,0)=0, "",VLOOKUP(A63,'Aux - pivots1'!$A:$E,4,0)) | N63: =IF(VLOOKUP(A63,'Aux - pivots1'!$A:$E,5,0)=0, "",VLOOKUP(A63,'Aux - pivots1'!$A:$E,5,0)) | T63: Plano anterior
A64: =E64&F64 -> PROCESSGUARANTEE_TYPE_CODE | B64: Pilar III | C64: Bens Imóveis - Output | D64: 2. Campo | E64: PROCESS | F64: GUARANTEE_TYPE_CODE | G64: =VLOOKUP(A64,Plano_V3!$A$26:$G$759,7,0) -> 1. Concluído | H64: 1. Concluído | L64: =IF(VLOOKUP(A64,'Aux - pivots1'!$A:$E,3,0)=0, "",VLOOKUP(A64,'Aux - pivots1'!$A:$E,3,0)) | M64: =IF(VLOOKUP(A64,'Aux - pivots1'!$A:$E,4,0)=0, "",VLOOKUP(A64,'Aux - pivots1'!$A:$E,4,0)) | N64: =IF(VLOOKUP(A64,'Aux - pivots1'!$A:$E,5,0)=0, "",VLOOKUP(A64,'Aux - pivots1'!$A:$E,5,0)) | T64: Plano anterior
A65: =E65&F65 -> PROCESSPROCESS_REFERENCE_CODE | B65: Pilar III | C65: Bens Imóveis - Output | D65: 2. Campo | E65: PROCESS | F65: PROCESS_REFERENCE_CODE | G65: =VLOOKUP(A65,Plano_V3!$A$26:$G$759,7,0) -> 1. Concluído | H65: 1. Concluído | L65: =IF(VLOOKUP(A65,'Aux - pivots1'!$A:$E,3,0)=0, "",VLOOKUP(A65,'Aux - pivots1'!$A:$E,3,0)) | M65: =IF(VLOOKUP(A65,'Aux - pivots1'!$A:$E,4,0)=0, "",VLOOKUP(A65,'Aux - pivots1'!$A:$E,4,0)) | N65: =IF(VLOOKUP(A65,'Aux - pivots1'!$A:$E,5,0)=0, "",VLOOKUP(A65,'Aux - pivots1'!$A:$E,5,0)) | T65: Plano anterior
... A142: =E142&F142 -> PROPERTYURBANIZATION | B142: Pilar III | C142: Bens Imóveis - Output | D142: 2. Campo | E142: PROPERTY | F142: URBANIZATION | G142: =VLOOKUP(A142,Plano_V3!$A$26:$G$759,7,0) -> 1. Concluído | H142: 1. Concluído | L142: =IF(VLOOKUP(A142,'Aux - pivots1'!$A:$E,3,0)=0, "",VLOOKUP(A142,'Aux - pivots1'!$A:$E,3,0)) | M142: =IF(VLOOKUP(A142,'Aux - pivots1'!$A:$E,4,0)=0, "",VLOOKUP(A142,'Aux - pivots1'!$A:$E,4,0)) | N142: =IF(VLOOKUP(A142,'Aux - pivots1'!$A:$E,5,0)=0, "",VLOOKUP(A142,'Aux - pivots1'!$A:$E,5,0)) | T142: Plano anterior
A143: =E143&F143 -> PROPERTY_ENERGY_CERTIFICATEn.a. | B143: Pilar III | C143: Bens Imóveis - Output | D143: 1. Universo | E143: PROPERTY_ENERGY_CERTIFICATE | F143: n.a. | G143: =VLOOKUP(A143,Plano_V3!$A$26:$G$759,7,0) -> 1. Concluído | H143: 1. Concluído | K143: Package X | L143: =IF(VLOOKUP(A143,'Aux - pivots1'!$A:$E,3,0)=0, "",VLOOKUP(A143,'Aux - pivots1'!$A:$E,3,0)) | M143: =IF(VLOOKUP(A143,'Aux - pivots1'!$A:$E,4,0)=0, "",VLOOKUP(A143,'Aux - pivots1'!$A:$E,4,0)) | N143: =IF(VLOOKUP(A143,'Aux - pivots1'!$A:$E,5,0)=0, "",VLOOKUP(A143,'Aux - pivots1'!$A:$E,5,0)) | T143: Plano anterior
A144: =E144&F144 -> PROPERTY_ENERGY_CERTIFICATEPROPERTY_BANK_ID | B144: Pilar III | C144: Bens Imóveis - Output | D144: 2. Campo | E144: PROPERTY_ENERGY_CERTIFICATE | F144: PROPERTY_BANK_ID | G144: =VLOOKUP(A144,Plano_V3!$A$26:$G$759,7,0) -> 1. Concluído | H144: 1. Concluído | K144: Package X | L144: =IF(VLOOKUP(A144,'Aux - pivots1'!$A:$E,3,0)=0, "",VLOOKUP(A144,'Aux - pivots1'!$A:$E,3,0)) | M144: =IF(VLOOKUP(A144,'Aux - pivots1'!$A:$E,4,0)=0, "",VLOOKUP(A144,'Aux - pivots1'!$A:$E,4,0)) | N144: =IF(VLOOKUP(A144,'Aux - pivots1'!$A:$E,5,0)=0, "",VLOOKUP(A144,'Aux - pivots1'!$A:$E,5,0)) | T144: Plano anterior
A145: =E145&F145 -> PROPERTY_ENERGY_CERTIFICATEPROPERTY_BRANCH_CODE | B145: Pilar III | C145: Bens Imóveis - Output | D145: 2. Campo | E145: PROPERTY_ENERGY_CERTIFICATE | F145: PROPERTY_BRANCH_CODE | G145: =VLOOKUP(A145,Plano_V3!$A$26:$G$759,7,0) -> 1. Concluído | H145: 1. Concluído | K145: Package X | L145: =IF(VLOOKUP(A145,'Aux - pivots1'!$A:$E,3,0)=0, "",VLOOKUP(A145,'Aux - pivots1'!$A:$E,3,0)) | M145: =IF(VLOOKUP(A145,'Aux - pivots1'!$A:$E,4,0)=0, "",VLOOKUP(A145,'Aux - pivots1'!$A:$E,4,0)) | N145: =IF(VLOOKUP(A145,'Aux - pivots1'!$A:$E,5,0)=0, "",VLOOKUP(A145,'Aux - pivots1'!$A:$E,5,0)) | T145: Plano anterior
A146: =E146&F146 -> PROPERTY_ENERGY_CERTIFICATEPROPERTY_CONTRACT_ID | B146: Pilar III | C146: Bens Imóveis - Output | D146: 2. Campo | E146: PROPERTY_ENERGY_CERTIFICATE | F146: PROPERTY_CONTRACT_ID | G146: =VLOOKUP(A146,Plano_V3!$A$26:$G$759,7,0) -> 1. Concluído | H146: 1. Concluído | K146: Package X | L146: =IF(VLOOKUP(A146,'Aux - pivots1'!$A:$E,3,0)=0, "",VLOOKUP(A146,'Aux - pivots1'!$A:$E,3,0)) | M146: =IF(VLOOKUP(A146,'Aux - pivots1'!$A:$E,4,0)=0, "",VLOOKUP(A146,'Aux - pivots1'!$A:$E,4,0)) | N146: =IF(VLOOKUP(A146,'Aux - pivots1'!$A:$E,5,0)=0, "",VLOOKUP(A146,'Aux - pivots1'!$A:$E,5,0)) | T146: Plano anterior
A147: =E147&F147 -> PROPERTY_ENERGY_CERTIFICATEPROPERTY_REFERENCE_CODE | B147: Pilar III | C147: Bens Imóveis - Output | D147: 2. Campo | E147: PROPERTY_ENERGY_CERTIFICATE | F147: PROPERTY_REFERENCE_CODE | G147: =VLOOKUP(A147,Plano_V3!$A$26:$G$759,7,0) -> 1. Concluído | H147: 1. Concluído | K147: Package X | L147: =IF(VLOOKUP(A147,'Aux - pivots1'!$A:$E,3,0)=0, "",VLOOKUP(A147,'Aux - pivots1'!$A:$E,3,0)) | M147: =IF(VLOOKUP(A147,'Aux - pivots1'!$A:$E,4,0)=0, "",VLOOKUP(A147,'Aux - pivots1'!$A:$E,4,0)) | N147: =IF(VLOOKUP(A147,'Aux - pivots1'!$A:$E,5,0)=0, "",VLOOKUP(A147,'Aux - pivots1'!$A:$E,5,0)) | T147: Plano anterior
A148: =E148&F148 -> PROPERTY_ENERGY_CERTIFICATELAND_REGISTRY_OFFICE_CODE | B148: Pilar III | C148: Bens Imóveis - Output | D148: 2. Campo | E148: PROPERTY_ENERGY_CERTIFICATE | F148: LAND_REGISTRY_OFFICE_CODE | G148: =VLOOKUP(A148,Plano_V3!$A$26:$G$759,7,0) -> 1. Concluído | H148: 1. Concluído | K148: Package X | L148: =IF(VLOOKUP(A148,'Aux - pivots1'!$A:$E,3,0)=0, "",VLOOKUP(A148,'Aux - pivots1'!$A:$E,3,0)) | M148: =IF(VLOOKUP(A148,'Aux - pivots1'!$A:$E,4,0)=0, "",VLOOKUP(A148,'Aux - pivots1'!$A:$E,4,0)) | N148: =IF(VLOOKUP(A148,'Aux - pivots1'!$A:$E,5,0)=0, "",VLOOKUP(A148,'Aux - pivots1'!$A:$E,5,0)) | T148: Plano anterior
A149: =E149&F149 -> PROPERTY_ENERGY_CERTIFICATEPROPERTY_IDENTIFICATION_CODE | B149: Pilar III | C149: Bens Imóveis - Output | D149: 2. Campo | E149: PROPERTY_ENERGY_CERTIFICATE | F149: PROPERTY_IDENTIFICATION_CODE | G149: =VLOOKUP(A149,Plano_V3!$A$26:$G$759,7,0) -> 1. Concluído | H149: 1. Concluído | K149: Package X | L149: =IF(VLOOKUP(A149,'Aux - pivots1'!$A:$E,3,0)=0, "",VLOOKUP(A149,'Aux - pivots1'!$A:$E,3,0)) | M149: =IF(VLOOKUP(A149,'Aux - pivots1'!$A:$E,4,0)=0, "",VLOOKUP(A149,'Aux - pivots1'!$A:$E,4,0)) | N149: =IF(VLOOKUP(A149,'Aux - pivots1'!$A:$E,5,0)=0, "",VLOOKUP(A149,'Aux - pivots1'!$A:$E,5,0)) | T149: Plano anterior
A150: =E150&F150 -> PROPERTY_ENERGY_CERTIFICATEENERGY_CERTIFICATION_SYSTEM_CODE | B150: Pilar III | C150: Bens Imóveis - Output | D150: 2. Campo | E150: PROPERTY_ENERGY_CERTIFICATE | F150: ENERGY_CERTIFICATION_SYSTEM_CODE | G150: =VLOOKUP(A150,Plano_V3!$A$26:$G$759,7,0) -> 1. Concluído | H150: 1. Concluído | K150: Package X | L150: =IF(VLOOKUP(A150,'Aux - pivots1'!$A:$E,3,0)=0, "",VLOOKUP(A150,'Aux - pivots1'!$A:$E,3,0)) | M150: =IF(VLOOKUP(A150,'Aux - pivots1'!$A:$E,4,0)=0, "",VLOOKUP(A150,'Aux - pivots1'!$A:$E,4,0)) | N150: =IF(VLOOKUP(A150,'Aux - pivots1'!$A:$E,5,0)=0, "",VLOOKUP(A150,'Aux - pivots1'!$A:$E,5,0)) | T150: Plano anterior
A151: =E151&F151 -> PROPERTY_ENERGY_CERTIFICATEEPC_ISSUING_DATE | B151: Pilar III | C151: Bens Imóveis - Output | D151: 2. Campo | E151: PROPERTY_ENERGY_CERTIFICATE | F151: EPC_ISSUING_DATE | G151: =VLOOKUP(A151,Plano_V3!$A$26:$G$759,7,0) -> 1. Concluído | H151: 1. Concluído | K151: Package X | L151: =IF(VLOOKUP(A151,'Aux - pivots1'!$A:$E,3,0)=0, "",VLOOKUP(A151,'Aux - pivots1'!$A:$E,3,0)) | M151: =IF(VLOOKUP(A151,'Aux - pivots1'!$A:$E,4,0)=0, "",VLOOKUP(A151,'Aux - pivots1'!$A:$E,4,0)) | N151: =IF(VLOOKUP(A151,'Aux - pivots1'!$A:$E,5,0)=0, "",VLOOKUP(A151,'Aux - pivots1'!$A:$E,5,0)) | T151: Plano anterior
A152: =E152&F152 -> PROPERTY_ENERGY_CERTIFICATEEPC_EXPIRATION_DATE | B152: Pilar III | C152: Bens Imóveis - Output | D152: 2. Campo | E152: PROPERTY_ENERGY_CERTIFICATE | F152: EPC_EXPIRATION_DATE | G152: =VLOOKUP(A152,Plano_V3!$A$26:$G$759,7,0) -> 1. Concluído | H152: 1. Concluído | K152: Package X | L152: =IF(VLOOKUP(A152,'Aux - pivots1'!$A:$E,3,0)=0, "",VLOOKUP(A152,'Aux - pivots1'!$A:$E,3,0)) | M152: =IF(VLOOKUP(A152,'Aux - pivots1'!$A:$E,4,0)=0, "",VLOOKUP(A152,'Aux - pivots1'!$A:$E,4,0)) | N152: =IF(VLOOKUP(A152,'Aux - pivots1'!$A:$E,5,0)=0, "",VLOOKUP(A152,'Aux - pivots1'!$A:$E,5,0)) | T152: Plano anterior
A153: =E153&F153 -> PROPERTY_ENERGY_CERTIFICATEEPC | B153: Pilar III | C153: Bens Imóveis - Output | D153: 2. Campo | E153: PROPERTY_ENERGY_CERTIFICATE | F153: EPC | G153: =VLOOKUP(A153,Plano_V3!$A$26:$G$759,7,0) -> 6. Em implementação | H153: 6. Em implementação | I153: Package 1 | J153: Package X | L153: =IF(VLOOKUP(A153,'Aux - pivots1'!$A:$E,3,0)=0, "",VLOOKUP(A153,'Aux - pivots1'!$A:$E,3,0)) | M153: =IF(VLOOKUP(A153,'Aux - pivots1'!$A:$E,4,0)=0, "",VLOOKUP(A153,'Aux - pivots1'!$A:$E,4,0)) | N153: =IF(VLOOKUP(A153,'Aux - pivots1'!$A:$E,5,0)=0, "",VLOOKUP(A153,'Aux - pivots1'!$A:$E,5,0)) | T153: Plano anterior
A154: =E154&F154 -> PROPERTY_ENERGY_CERTIFICATEENERGY_CONSUMPTION_TYPE_S_IND | B154: Pilar III | C154: Bens Imóveis - Output | D154: 2. Campo | E154: PROPERTY_ENERGY_CERTIFICATE | F154: ENERGY_CONSUMPTION_TYPE_S_IND | G154: =VLOOKUP(A154,Plano_V3!$A$26:$G$759,7,0) -> 1. Concluído | H154: 1. Concluído | K154: Package X | L154: =IF(VLOOKUP(A154,'Aux - pivots1'!$A:$E,3,0)=0, "",VLOOKUP(A154,'Aux - pivots1'!$A:$E,3,0)) | M154: =IF(VLOOKUP(A154,'Aux - pivots1'!$A:$E,4,0)=0, "",VLOOKUP(A154,'Aux - pivots1'!$A:$E,4,0)) | N154: =IF(VLOOKUP(A154,'Aux - pivots1'!$A:$E,5,0)=0, "",VLOOKUP(A154,'Aux - pivots1'!$A:$E,5,0)) | T154: Plano anterior
A155: =E155&F155 -> PROPERTY_ENERGY_CERTIFICATEENERGY_CONSUMPTION_TYPE_T_IND | B155: Pilar III | C155: Bens Imóveis - Output | D155: 2. Campo | E155: PROPERTY_ENERGY_CERTIFICATE | F155: ENERGY_CONSUMPTION_TYPE_T_IND | G155: =VLOOKUP(A155,Plano_V3!$A$26:$G$759,7,0) -> 1. Concluído | H155: 1. Concluído | K155: Package X | L155: =IF(VLOOKUP(A155,'Aux - pivots1'!$A:$E,3,0)=0, "",VLOOKUP(A155,'Aux - pivots1'!$A:$E,3,0)) | M155: =IF(VLOOKUP(A155,'Aux - pivots1'!$A:$E,4,0)=0, "",VLOOKUP(A155,'Aux - pivots1'!$A:$E,4,0)) | N155: =IF(VLOOKUP(A155,'Aux - pivots1'!$A:$E,5,0)=0, "",VLOOKUP(A155,'Aux - pivots1'!$A:$E,5,0)) | T155: Plano anterior
A156: =E156&F156 -> PROPERTY_ENERGY_CERTIFICATEENERGY_EFFICIENCY_IND | B156: Pilar III | C156: Bens Imóveis - Output | D156: 2. Campo | E156: PROPERTY_ENERGY_CERTIFICATE | F156: ENERGY_EFFICIENCY_IND | G156: =VLOOKUP(A156,Plano_V3!$A$26:$G$759,7,0) -> 1. Concluído | H156: 1. Concluído | K156: Package X | L156: =IF(VLOOKUP(A156,'Aux - pivots1'!$A:$E,3,0)=0, "",VLOOKUP(A156,'Aux - pivots1'!$A:$E,3,0)) | M156: =IF(VLOOKUP(A156,'Aux - pivots1'!$A:$E,4,0)=0, "",VLOOKUP(A156,'Aux - pivots1'!$A:$E,4,0)) | N156: =IF(VLOOKUP(A156,'Aux - pivots1'!$A:$E,5,0)=0, "",VLOOKUP(A156,'Aux - pivots1'!$A:$E,5,0)) | T156: Plano anterior
A157: =E157&F157 -> PROPERTY_ENERGY_CERTIFICATEREN_ENERGY_EFFICIENCY_IND | B157: Pilar III | C157: Bens Imóveis - Output | D157: 2. Campo | E157: PROPERTY_ENERGY_CERTIFICATE | F157: REN_ENERGY_EFFICIENCY_IND | G157: =VLOOKUP(A157,Plano_V3!$A$26:$G$759,7,0) -> 1. Concluído | H157: 1. Concluído | K157: Package X | L157: =IF(VLOOKUP(A157,'Aux - pivots1'!$A:$E,3,0)=0, "",VLOOKUP(A157,'Aux - pivots1'!$A:$E,3,0)) | M157: =IF(VLOOKUP(A157,'Aux - pivots1'!$A:$E,4,0)=0, "",VLOOKUP(A157,'Aux - pivots1'!$A:$E,4,0)) | N157: =IF(VLOOKUP(A157,'Aux - pivots1'!$A:$E,5,0)=0, "",VLOOKUP(A157,'Aux - pivots1'!$A:$E,5,0)) | T157: Plano anterior
A158: =E158&F158 -> PROPERTY_ENERGY_CERTIFICATENZEB_IND | B158: Pilar III | C158: Bens Imóveis - Output | D158: 2. Campo | E158: PROPERTY_ENERGY_CERTIFICATE | F158: NZEB_IND | G158: =VLOOKUP(A158,Plano_V3!$A$26:$G$759,7,0) -> 1. Concluído | H158: 1. Concluído | K158: Package X | L158: =IF(VLOOKUP(A158,'Aux - pivots1'!$A:$E,3,0)=0, "",VLOOKUP(A158,'Aux - pivots1'!$A:$E,3,0)) | M158: =IF(VLOOKUP(A158,'Aux - pivots1'!$A:$E,4,0)=0, "",VLOOKUP(A158,'Aux - pivots1'!$A:$E,4,0)) | N158: =IF(VLOOKUP(A158,'Aux - pivots1'!$A:$E,5,0)=0, "",VLOOKUP(A158,'Aux - pivots1'!$A:$E,5,0)) | T158: Plano anterior
A159: =E159&F159 -> PROPERTY_ENERGY_CERTIFICATEACTUAL_VALUE_IND | B159: Pilar III | C159: Bens Imóveis - Output | D159: 2. Campo | E159: PROPERTY_ENERGY_CERTIFICATE | F159: ACTUAL_VALUE_IND | G159: =VLOOKUP(A159,Plano_V3!$A$26:$G$759,7,0) -> 1. Concluído | H159: 1. Concluído | K159: Package X | L159: =IF(VLOOKUP(A159,'Aux - pivots1'!$A:$E,3,0)=0, "",VLOOKUP(A159,'Aux - pivots1'!$A:$E,3,0)) | M159: =IF(VLOOKUP(A159,'Aux - pivots1'!$A:$E,4,0)=0, "",VLOOKUP(A159,'Aux - pivots1'!$A:$E,4,0)) | N159: =IF(VLOOKUP(A159,'Aux - pivots1'!$A:$E,5,0)=0, "",VLOOKUP(A159,'Aux - pivots1'!$A:$E,5,0)) | T159: Plano anterior
A160: =E160&F160 -> PROPERTY_ENERGY_CERTIFICATEEP_SCORE | B160: Pilar III | C160: Bens Imóveis - Output | D160: 2. Campo | E160: PROPERTY_ENERGY_CERTIFICATE | F160: EP_SCORE | G160: =VLOOKUP(A160,Plano_V3!$A$26:$G$759,7,0) -> 6. Em implementação | H160: 6. Em implementação | I160: Package 1 | J160: Package X | L160: =IF(VLOOKUP(A160,'Aux - pivots1'!$A:$E,3,0)=0, "",VLOOKUP(A160,'Aux - pivots1'!$A:$E,3,0)) | M160: =IF(VLOOKUP(A160,'Aux - pivots1'!$A:$E,4,0)=0, "",VLOOKUP(A160,'Aux - pivots1'!$A:$E,4,0)) | N160: =IF(VLOOKUP(A160,'Aux - pivots1'!$A:$E,5,0)=0, "",VLOOKUP(A160,'Aux - pivots1'!$A:$E,5,0)) | T160: Plano anterior
A161: =E161&F161 -> PROPERTY_ENERGY_CERTIFICATESOURCE_CODE | B161: Pilar III | C161: Bens Imóveis - Output | D161: 2. Campo | E161: PROPERTY_ENERGY_CERTIFICATE | F161: SOURCE_CODE | G161: =VLOOKUP(A161,Plano_V3!$A$26:$G$759,7,0) -> 1. Concluído | H161: 1. Concluído | K161: Package X | L161: =IF(VLOOKUP(A161,'Aux - pivots1'!$A:$E,3,0)=0, "",VLOOKUP(A161,'Aux - pivots1'!$A:$E,3,0)) | M161: =IF(VLOOKUP(A161,'Aux - pivots1'!$A:$E,4,0)=0, "",VLOOKUP(A161,'Aux - pivots1'!$A:$E,4,0)) | N161: =IF(VLOOKUP(A161,'Aux - pivots1'!$A:$E,5,0)=0, "",VLOOKUP(A161,'Aux - pivots1'!$A:$E,5,0)) | T161: Plano anterior
A162: =E162&F162 -> PROPERTY_ENERGY_CERTIFICATEDATA_DATE_PART | B162: Pilar III | C162: Bens Imóveis - Output | D162: 2. Campo | E162: PROPERTY_ENERGY_CERTIFICATE | F162: DATA_DATE_PART | G162: =VLOOKUP(A162,Plano_V3!$A$26:$G$759,7,0) -> 1. Concluído | H162: 1. Concluído | K162: Package X | L162: =IF(VLOOKUP(A162,'Aux - pivots1'!$A:$E,3,0)=0, "",VLOOKUP(A162,'Aux - pivots1'!$A:$E,3,0)) | M162: =IF(VLOOKUP(A162,'Aux - pivots1'!$A:$E,4,0)=0, "",VLOOKUP(A162,'Aux - pivots1'!$A:$E,4,0)) | N162: =IF(VLOOKUP(A162,'Aux - pivots1'!$A:$E,5,0)=0, "",VLOOKUP(A162,'Aux - pivots1'!$A:$E,5,0)) | T162: Plano anterior
A163: =E163&F163 -> PROPERTY_ENERGY_CERTIFICATECERTIFICATE_TYPE | B163: Pilar III | C163: Bens Imóveis - Output | D163: 2. Campo | E163: PROPERTY_ENERGY_CERTIFICATE | F163: CERTIFICATE_TYPE | G163: =VLOOKUP(A163,Plano_V3!$A$26:$G$759,7,0) -> 1. Concluído | H163: 1. Concluído | K163: Package X | L163: =IF(VLOOKUP(A163,'Aux - pivots1'!$A:$E,3,0)=0, "",VLOOKUP(A163,'Aux - pivots1'!$A:$E,3,0)) | M163: =IF(VLOOKUP(A163,'Aux - pivots1'!$A:$E,4,0)=0, "",VLOOKUP(A163,'Aux - pivots1'!$A:$E,4,0)) | N163: =IF(VLOOKUP(A163,'Aux - pivots1'!$A:$E,5,0)=0, "",VLOOKUP(A163,'Aux - pivots1'!$A:$E,5,0)) | T163: Plano anterior
A164: =E164&F164 -> PROPERTY_ENERGY_CERTIFICATEBUILDING_DOMEST_HOTWATER_VALUE | B164: Pilar III | C164: Bens Imóveis - Output | D164: 2. Campo | E164: PROPERTY_ENERGY_CERTIFICATE | F164: BUILDING_DOMEST_HOTWATER_VALUE | G164: =VLOOKUP(A164,Plano_V3!$A$26:$G$759,7,0) -> 1. Concluído | H164: 1. Concluído | K164: Package X | L164: =IF(VLOOKUP(A164,'Aux - pivots1'!$A:$E,3,0)=0, "",VLOOKUP(A164,'Aux - pivots1'!$A:$E,3,0)) | M164: =IF(VLOOKUP(A164,'Aux - pivots1'!$A:$E,4,0)=0, "",VLOOKUP(A164,'Aux - pivots1'!$A:$E,4,0)) | N164: =IF(VLOOKUP(A164,'Aux - pivots1'!$A:$E,5,0)=0, "",VLOOKUP(A164,'Aux - pivots1'!$A:$E,5,0)) | T164: Plano anterior
A165: =E165&F165 -> PROPERTY_ENERGY_CERTIFICATERENEWABLE_DOMEST_HOTWATER_VALUE | B165: Pilar III | C165: Bens Imóveis - Output | D165: 2. Campo | E165: PROPERTY_ENERGY_CERTIFICATE | F165: RENEWABLE_DOMEST_HOTWATER_VALUE | G165: =VLOOKUP(A165,Plano_V3!$A$26:$G$759,7,0) -> 1. Concluído | H165: 1. Concluído | K165: Package X | L165: =IF(VLOOKUP(A165,'Aux - pivots1'!$A:$E,3,0)=0, "",VLOOKUP(A165,'Aux - pivots1'!$A:$E,3,0)) | M165: =IF(VLOOKUP(A165,'Aux - pivots1'!$A:$E,4,0)=0, "",VLOOKUP(A165,'Aux - pivots1'!$A:$E,4,0)) | N165: =IF(VLOOKUP(A165,'Aux - pivots1'!$A:$E,5,0)=0, "",VLOOKUP(A165,'Aux - pivots1'!$A:$E,5,0)) | T165: Plano anterior
A166: =E166&F166 -> PROPERTY_ENERGY_CERTIFICATEDOMEST_HOTWATER_REF_VALUE | B166: Pilar III | C166: Bens Imóveis - Output | D166: 2. Campo | E166: PROPERTY_ENERGY_CERTIFICATE | F166: DOMEST_HOTWATER_REF_VALUE | G166: =VLOOKUP(A166,Plano_V3!$A$26:$G$759,7,0) -> 1. Concluído | H166: 1. Concluído | K166: Package X | L166: =IF(VLOOKUP(A166,'Aux - pivots1'!$A:$E,3,0)=0, "",VLOOKUP(A166,'Aux - pivots1'!$A:$E,3,0)) | M166: =IF(VLOOKUP(A166,'Aux - pivots1'!$A:$E,4,0)=0, "",VLOOKUP(A166,'Aux - pivots1'!$A:$E,4,0)) | N166: =IF(VLOOKUP(A166,'Aux - pivots1'!$A:$E,5,0)=0, "",VLOOKUP(A166,'Aux - pivots1'!$A:$E,5,0)) | T166: Plano anterior
A167: =E167&F167 -> PROPERTY_ENERGY_CERTIFICATEHEIGHT | B167: Pilar III | C167: Bens Imóveis - Output | D167: 2. Campo | E167: PROPERTY_ENERGY_CERTIFICATE | F167: HEIGHT | G167: =VLOOKUP(A167,Plano_V3!$A$26:$G$759,7,0) -> 1. Concluído | H167: 1. Concluído | K167: Package X | L167: =IF(VLOOKUP(A167,'Aux - pivots1'!$A:$E,3,0)=0, "",VLOOKUP(A167,'Aux - pivots1'!$A:$E,3,0)) | M167: =IF(VLOOKUP(A167,'Aux - pivots1'!$A:$E,4,0)=0, "",VLOOKUP(A167,'Aux - pivots1'!$A:$E,4,0)) | N167: =IF(VLOOKUP(A167,'Aux - pivots1'!$A:$E,5,0)=0, "",VLOOKUP(A167,'Aux - pivots1'!$A:$E,5,0)) | T167: Plano anterior
A168: =E168&F168 -> PROPERTY_ENERGY_CERTIFICATEBUILDING_SPACE_HEATING_VALUE | B168: Pilar III | C168: Bens Imóveis - Output | D168: 2. Campo | E168: PROPERTY_ENERGY_CERTIFICATE | F168: BUILDING_SPACE_HEATING_VALUE | G168: =VLOOKUP(A168,Plano_V3!$A$26:$G$759,7,0) -> 1. Concluído | H168: 1. Concluído | K168: Package X | L168: =IF(VLOOKUP(A168,'Aux - pivots1'!$A:$E,3,0)=0, "",VLOOKUP(A168,'Aux - pivots1'!$A:$E,3,0)) | M168: =IF(VLOOKUP(A168,'Aux - pivots1'!$A:$E,4,0)=0, "",VLOOKUP(A168,'Aux - pivots1'!$A:$E,4,0)) | N168: =IF(VLOOKUP(A168,'Aux - pivots1'!$A:$E,5,0)=0, "",VLOOKUP(A168,'Aux - pivots1'!$A:$E,5,0)) | T168: Plano anterior
A169: =E169&F169 -> PROPERTY_ENERGY_CERTIFICATESPACE_HEATING_REF_VALUE | B169: Pilar III | C169: Bens Imóveis - Output | D169: 2. Campo | E169: PROPERTY_ENERGY_CERTIFICATE | F169: SPACE_HEATING_REF_VALUE | G169: =VLOOKUP(A169,Plano_V3!$A$26:$G$759,7,0) -> 1. Concluído | H169: 1. Concluído | K169: Package X | L169: =IF(VLOOKUP(A169,'Aux - pivots1'!$A:$E,3,0)=0, "",VLOOKUP(A169,'Aux - pivots1'!$A:$E,3,0)) | M169: =IF(VLOOKUP(A169,'Aux - pivots1'!$A:$E,4,0)=0, "",VLOOKUP(A169,'Aux - pivots1'!$A:$E,4,0)) | N169: =IF(VLOOKUP(A169,'Aux - pivots1'!$A:$E,5,0)=0, "",VLOOKUP(A169,'Aux - pivots1'!$A:$E,5,0)) | T169: Plano anterior
A170: =E170&F170 -> PROPERTY_ENERGY_CERTIFICATERENEWABLE_SPACE_HEATING_VALUE | B170: Pilar III | C170: Bens Imóveis - Output | D170: 2. Campo | E170: PROPERTY_ENERGY_CERTIFICATE | F170: RENEWABLE_SPACE_HEATING_VALUE | G170: =VLOOKUP(A170,Plano_V3!$A$26:$G$759,7,0) -> 1. Concluído | H170: 1. Concluído | K170: Package X | L170: =IF(VLOOKUP(A170,'Aux - pivots1'!$A:$E,3,0)=0, "",VLOOKUP(A170,'Aux - pivots1'!$A:$E,3,0)) | M170: =IF(VLOOKUP(A170,'Aux - pivots1'!$A:$E,4,0)=0, "",VLOOKUP(A170,'Aux - pivots1'!$A:$E,4,0)) | N170: =IF(VLOOKUP(A170,'Aux - pivots1'!$A:$E,5,0)=0, "",VLOOKUP(A170,'Aux - pivots1'!$A:$E,5,0)) | T170: Plano anterior
A171: =E171&F171 -> PROPERTY_ENERGY_CERTIFICATEBUILDING_SPACE_COOLING_VALUE | B171: Pilar III | C171: Bens Imóveis - Output | D171: 2. Campo | E171: PROPERTY_ENERGY_CERTIFICATE | F171: BUILDING_SPACE_COOLING_VALUE | G171: =VLOOKUP(A171,Plano_V3!$A$26:$G$759,7,0) -> 1. Concluído | H171: 1. Concluído | K171: Package X | L171: =IF(VLOOKUP(A171,'Aux - pivots1'!$A:$E,3,0)=0, "",VLOOKUP(A171,'Aux - pivots1'!$A:$E,3,0)) | M171: =IF(VLOOKUP(A171,'Aux - pivots1'!$A:$E,4,0)=0, "",VLOOKUP(A171,'Aux - pivots1'!$A:$E,4,0)) | N171: =IF(VLOOKUP(A171,'Aux - pivots1'!$A:$E,5,0)=0, "",VLOOKUP(A171,'Aux - pivots1'!$A:$E,5,0)) | T171: Plano anterior
A172: =E172&F172 -> PROPERTY_ENERGY_CERTIFICATERENEWABLE_SPACE_COOLING_VALUE | B172: Pilar III | C172: Bens Imóveis - Output | D172: 2. Campo | E172: PROPERTY_ENERGY_CERTIFICATE | F172: RENEWABLE_SPACE_COOLING_VALUE | G172: =VLOOKUP(A172,Plano_V3!$A$26:$G$759,7,0) -> 1. Concluído | H172: 1. Concluído | K172: Package X | L172: =IF(VLOOKUP(A172,'Aux - pivots1'!$A:$E,3,0)=0, "",VLOOKUP(A172,'Aux - pivots1'!$A:$E,3,0)) | M172: =IF(VLOOKUP(A172,'Aux - pivots1'!$A:$E,4,0)=0, "",VLOOKUP(A172,'Aux - pivots1'!$A:$E,4,0)) | N172: =IF(VLOOKUP(A172,'Aux - pivots1'!$A:$E,5,0)=0, "",VLOOKUP(A172,'Aux - pivots1'!$A:$E,5,0)) | T172: Plano anterior
... A174: =E174&F174 -> PROPERTY_ENERGY_CERTIFICATEENERGY_CLASS_AFTER_MEASUREMENT | B174: Pilar III | C174: Bens Imóveis - Output | D174: 2. Campo | E174: PROPERTY_ENERGY_CERTIFICATE | F174: ENERGY_CLASS_AFTER_MEASUREMENT | G174: =VLOOKUP(A174,Plano_V3!$A$26:$G$759,7,0) -> 1. Concluído | H174: 1. Concluído | K174: Package X | L174: =IF(VLOOKUP(A174,'Aux - pivots1'!$A:$E,3,0)=0, "",VLOOKUP(A174,'Aux - pivots1'!$A:$E,3,0)) | M174: =IF(VLOOKUP(A174,'Aux - pivots1'!$A:$E,4,0)=0, "",VLOOKUP(A174,'Aux - pivots1'!$A:$E,4,0)) | N174: =IF(VLOOKUP(A174,'Aux - pivots1'!$A:$E,5,0)=0, "",VLOOKUP(A174,'Aux - pivots1'!$A:$E,5,0)) | T174: Plano anterior
A175: =E175&F175 -> PROPERTY_ENERGY_CERTIFICATEENERGY_CONSUMPTION_VALUE_YEAR | B175: Pilar III | C175: Bens Imóveis - Output | D175: 2. Campo | E175: PROPERTY_ENERGY_CERTIFICATE | F175: ENERGY_CONSUMPTION_VALUE_YEAR | G175: =VLOOKUP(A175,Plano_V3!$A$26:$G$759,7,0) -> 6. Em implementação | H175: 6. Em implementação | I175: Package 1 | J175: Package X | L175: =IF(VLOOKUP(A175,'Aux - pivots1'!$A:$E,3,0)=0, "",VLOOKUP(A175,'Aux - pivots1'!$A:$E,3,0)) | M175: =IF(VLOOKUP(A175,'Aux - pivots1'!$A:$E,4,0)=0, "",VLOOKUP(A175,'Aux - pivots1'!$A:$E,4,0)) | N175: =IF(VLOOKUP(A175,'Aux - pivots1'!$A:$E,5,0)=0, "",VLOOKUP(A175,'Aux - pivots1'!$A:$E,5,0)) | T175: Plano anterior
A176: =E176&F176 -> PROPERTY_ENERGY_CERTIFICATETHERMAL_BEHAVIOUR_ROOF | B176: Pilar III | C176: Bens Imóveis - Output | D176: 2. Campo | E176: PROPERTY_ENERGY_CERTIFICATE | F176: THERMAL_BEHAVIOUR_ROOF | G176: =VLOOKUP(A176,Plano_V3!$A$26:$G$759,7,0) -> 1. Concluído | H176: 1. Concluído | K176: Package X | L176: =IF(VLOOKUP(A176,'Aux - pivots1'!$A:$E,3,0)=0, "",VLOOKUP(A176,'Aux - pivots1'!$A:$E,3,0)) | M176: =IF(VLOOKUP(A176,'Aux - pivots1'!$A:$E,4,0)=0, "",VLOOKUP(A176,'Aux - pivots1'!$A:$E,4,0)) | N176: =IF(VLOOKUP(A176,'Aux - pivots1'!$A:$E,5,0)=0, "",VLOOKUP(A176,'Aux - pivots1'!$A:$E,5,0)) | T176: Plano anterior
A177: =E177&F177 -> PROPERTY_ENERGY_CERTIFICATETHERMAL_BEHAVIOUR_WINDOWS | B177: Pilar III | C177: Bens Imóveis - Output | D177: 2. Campo | E177: PROPERTY_ENERGY_CERTIFICATE | F177: THERMAL_BEHAVIOUR_WINDOWS | G177: =VLOOKUP(A177,Plano_V3!$A$26:$G$759,7,0) -> 1. Concluído | H177: 1. Concluído | K177: Package X | L177: =IF(VLOOKUP(A177,'Aux - pivots1'!$A:$E,3,0)=0, "",VLOOKUP(A177,'Aux - pivots1'!$A:$E,3,0)) | M177: =IF(VLOOKUP(A177,'Aux - pivots1'!$A:$E,4,0)=0, "",VLOOKUP(A177,'Aux - pivots1'!$A:$E,4,0)) | N177: =IF(VLOOKUP(A177,'Aux - pivots1'!$A:$E,5,0)=0, "",VLOOKUP(A177,'Aux - pivots1'!$A:$E,5,0)) | T177: Plano anterior
A178: =E178&F178 -> PROPERTY_ENERGY_CERTIFICATETHERMAL_BEHAVIOUR_WALL | B178: Pilar III | C178: Bens Imóveis - Output | D178: 2. Campo | E178: PROPERTY_ENERGY_CERTIFICATE | F178: THERMAL_BEHAVIOUR_WALL | G178: =VLOOKUP(A178,Plano_V3!$A$26:$G$759,7,0) -> 1. Concluído | H178: 1. Concluído | K178: Package X | L178: =IF(VLOOKUP(A178,'Aux - pivots1'!$A:$E,3,0)=0, "",VLOOKUP(A178,'Aux - pivots1'!$A:$E,3,0)) | M178: =IF(VLOOKUP(A178,'Aux - pivots1'!$A:$E,4,0)=0, "",VLOOKUP(A178,'Aux - pivots1'!$A:$E,4,0)) | N178: =IF(VLOOKUP(A178,'Aux - pivots1'!$A:$E,5,0)=0, "",VLOOKUP(A178,'Aux - pivots1'!$A:$E,5,0)) | T178: Plano anterior
A179: =E179&F179 -> PROPERTY_ENERGY_CERTIFICATETHERMAL_BEHAVIOUR_FLOORS | B179: Pilar III | C179: Bens Imóveis - Output | D179: 2. Campo | E179: PROPERTY_ENERGY_CERTIFICATE | F179: THERMAL_BEHAVIOUR_FLOORS | G179: =VLOOKUP(A179,Plano_V3!$A$26:$G$759,7,0) -> 1. Concluído | H179: 1. Concluído | K179: Package X | L179: =IF(VLOOKUP(A179,'Aux - pivots1'!$A:$E,3,0)=0, "",VLOOKUP(A179,'Aux - pivots1'!$A:$E,3,0)) | M179: =IF(VLOOKUP(A179,'Aux - pivots1'!$A:$E,4,0)=0, "",VLOOKUP(A179,'Aux - pivots1'!$A:$E,4,0)) | N179: =IF(VLOOKUP(A179,'Aux - pivots1'!$A:$E,5,0)=0, "",VLOOKUP(A179,'Aux - pivots1'!$A:$E,5,0)) | T179: Plano anterior
A180: =E180&F180 -> PROPERTY_ENERGY_CERTIFICATETHERMAL_BEHAVIOUR_TECH_SYS_VENT | B180: Pilar III | C180: Bens Imóveis - Output | D180: 2. Campo | E180: PROPERTY_ENERGY_CERTIFICATE | F180: THERMAL_BEHAVIOUR_TECH_SYS_VENT | G180: =VLOOKUP(A180,Plano_V3!$A$26:$G$759,7,0) -> 1. Concluído | H180: 1. Concluído | K180: Package X | L180: =IF(VLOOKUP(A180,'Aux - pivots1'!$A:$E,3,0)=0, "",VLOOKUP(A180,'Aux - pivots1'!$A:$E,3,0)) | M180: =IF(VLOOKUP(A180,'Aux - pivots1'!$A:$E,4,0)=0, "",VLOOKUP(A180,'Aux - pivots1'!$A:$E,4,0)) | N180: =IF(VLOOKUP(A180,'Aux - pivots1'!$A:$E,5,0)=0, "",VLOOKUP(A180,'Aux - pivots1'!$A:$E,5,0)) | T180: Plano anterior
A181: =E181&F181 -> PROPERTY_ENERGY_CERTIFICATETOTAL_INVSTMNT_ESTMTD_VALUE | B181: Pilar III | C181: Bens Imóveis - Output | D181: 2. Campo | E181: PROPERTY_ENERGY_CERTIFICATE | F181: TOTAL_INVSTMNT_ESTMTD_VALUE | G181: =VLOOKUP(A181,Plano_V3!$A$26:$G$759,7,0) -> 1. Concluído | H181: 1. Concluído | K181: Package X | L181: =IF(VLOOKUP(A181,'Aux - pivots1'!$A:$E,3,0)=0, "",VLOOKUP(A181,'Aux - pivots1'!$A:$E,3,0)) | M181: =IF(VLOOKUP(A181,'Aux - pivots1'!$A:$E,4,0)=0, "",VLOOKUP(A181,'Aux - pivots1'!$A:$E,4,0)) | N181: =IF(VLOOKUP(A181,'Aux - pivots1'!$A:$E,5,0)=0, "",VLOOKUP(A181,'Aux - pivots1'!$A:$E,5,0)) | T181: Plano anterior
A182: =E182&F182 -> PROPERTY_ENERGY_CERTIFICATEDURATION_SUMMER | B182: Pilar III | C182: Bens Imóveis - Output | D182: 2. Campo | E182: PROPERTY_ENERGY_CERTIFICATE | F182: DURATION_SUMMER | G182: =VLOOKUP(A182,Plano_V3!$A$26:$G$759,7,0) -> 1. Concluído | H182: 1. Concluído | K182: Package X | L182: =IF(VLOOKUP(A182,'Aux - pivots1'!$A:$E,3,0)=0, "",VLOOKUP(A182,'Aux - pivots1'!$A:$E,3,0)) | M182: =IF(VLOOKUP(A182,'Aux - pivots1'!$A:$E,4,0)=0, "",VLOOKUP(A182,'Aux - pivots1'!$A:$E,4,0)) | N182: =IF(VLOOKUP(A182,'Aux - pivots1'!$A:$E,5,0)=0, "",VLOOKUP(A182,'Aux - pivots1'!$A:$E,5,0)) | T182: Plano anterior
A183: =E183&F183 -> PROPERTY_ENERGY_CERTIFICATEDURATION_WINTER | B183: Pilar III | C183: Bens Imóveis - Output | D183: 2. Campo | E183: PROPERTY_ENERGY_CERTIFICATE | F183: DURATION_WINTER | G183: =VLOOKUP(A183,Plano_V3!$A$26:$G$759,7,0) -> 1. Concluído | H183: 1. Concluído | K183: Package X | L183: =IF(VLOOKUP(A183,'Aux - pivots1'!$A:$E,3,0)=0, "",VLOOKUP(A183,'Aux - pivots1'!$A:$E,3,0)) | M183: =IF(VLOOKUP(A183,'Aux - pivots1'!$A:$E,4,0)=0, "",VLOOKUP(A183,'Aux - pivots1'!$A:$E,4,0)) | N183: =IF(VLOOKUP(A183,'Aux - pivots1'!$A:$E,5,0)=0, "",VLOOKUP(A183,'Aux - pivots1'!$A:$E,5,0)) | T183: Plano anterior
A184: =E184&F184 -> PROPERTY_ENERGY_CERTIFICATECARBON_EMISSION_VALUE_YEAR | B184: Pilar III | C184: Bens Imóveis - Output | D184: 2. Campo | E184: PROPERTY_ENERGY_CERTIFICATE | F184: CARBON_EMISSION_VALUE_YEAR | G184: =VLOOKUP(A184,Plano_V3!$A$26:$G$759,7,0) -> 6. Em implementação | H184: 6. Em implementação | I184: Package 1 | J184: Package X | L184: =IF(VLOOKUP(A184,'Aux - pivots1'!$A:$E,3,0)=0, "",VLOOKUP(A184,'Aux - pivots1'!$A:$E,3,0)) | M184: =IF(VLOOKUP(A184,'Aux - pivots1'!$A:$E,4,0)=0, "",VLOOKUP(A184,'Aux - pivots1'!$A:$E,4,0)) | N184: =IF(VLOOKUP(A184,'Aux - pivots1'!$A:$E,5,0)=0, "",VLOOKUP(A184,'Aux - pivots1'!$A:$E,5,0)) | T184: Plano anterior
A185: =E185&F185 -> PROPERTY_ENERGY_CERTIFICATECARBON_EMISSION_VALUE | B185: Pilar III | C185: Bens Imóveis - Output | D185: 2. Campo | E185: PROPERTY_ENERGY_CERTIFICATE | F185: CARBON_EMISSION_VALUE | G185: =VLOOKUP(A185,Plano_V3!$A$26:$G$759,7,0) -> 1. Concluído | H185: 1. Concluído | K185: Package X | L185: =IF(VLOOKUP(A185,'Aux - pivots1'!$A:$E,3,0)=0, "",VLOOKUP(A185,'Aux - pivots1'!$A:$E,3,0)) | M185: =IF(VLOOKUP(A185,'Aux - pivots1'!$A:$E,4,0)=0, "",VLOOKUP(A185,'Aux - pivots1'!$A:$E,4,0)) | N185: =IF(VLOOKUP(A185,'Aux - pivots1'!$A:$E,5,0)=0, "",VLOOKUP(A185,'Aux - pivots1'!$A:$E,5,0)) | T185: Plano anterior
A186: =E186&F186 -> PROPERTY_ENERGY_CERTIFICATEUSEFUL_ENERGY_FANS_REQ_VALUE | B186: Pilar III | C186: Bens Imóveis - Output | D186: 2. Campo | E186: PROPERTY_ENERGY_CERTIFICATE | F186: USEFUL_ENERGY_FANS_REQ_VALUE | G186: =VLOOKUP(A186,Plano_V3!$A$26:$G$759,7,0) -> 1. Concluído | H186: 1. Concluído | K186: Package X | L186: =IF(VLOOKUP(A186,'Aux - pivots1'!$A:$E,3,0)=0, "",VLOOKUP(A186,'Aux - pivots1'!$A:$E,3,0)) | M186: =IF(VLOOKUP(A186,'Aux - pivots1'!$A:$E,4,0)=0, "",VLOOKUP(A186,'Aux - pivots1'!$A:$E,4,0)) | N186: =IF(VLOOKUP(A186,'Aux - pivots1'!$A:$E,5,0)=0, "",VLOOKUP(A186,'Aux - pivots1'!$A:$E,5,0)) | T186: Plano anterior
A187: =E187&F187 -> PROPERTY_ENERGY_CERTIFICATEREN_ENERGY_PRODUCED_OTHER_VALUE | B187: Pilar III | C187: Bens Imóveis - Output | D187: 2. Campo | E187: PROPERTY_ENERGY_CERTIFICATE | F187: REN_ENERGY_PRODUCED_OTHER_VALUE | G187: =VLOOKUP(A187,Plano_V3!$A$26:$G$759,7,0) -> 1. Concluído | H187: 1. Concluído | K187: Package X | L187: =IF(VLOOKUP(A187,'Aux - pivots1'!$A:$E,3,0)=0, "",VLOOKUP(A187,'Aux - pivots1'!$A:$E,3,0)) | M187: =IF(VLOOKUP(A187,'Aux - pivots1'!$A:$E,4,0)=0, "",VLOOKUP(A187,'Aux - pivots1'!$A:$E,4,0)) | N187: =IF(VLOOKUP(A187,'Aux - pivots1'!$A:$E,5,0)=0, "",VLOOKUP(A187,'Aux - pivots1'!$A:$E,5,0)) | T187: Plano anterior
A188: =E188&F188 -> PROPERTY_ENERGY_CERTIFICATEREN_ENERGY_PRODUCED_REG_VALUE | B188: Pilar III | C188: Bens Imóveis - Output | D188: 2. Campo | E188: PROPERTY_ENERGY_CERTIFICATE | F188: REN_ENERGY_PRODUCED_REG_VALUE | G188: =VLOOKUP(A188,Plano_V3!$A$26:$G$759,7,0) -> 1. Concluído | H188: 1. Concluído | K188: Package X | L188: =IF(VLOOKUP(A188,'Aux - pivots1'!$A:$E,3,0)=0, "",VLOOKUP(A188,'Aux - pivots1'!$A:$E,3,0)) | M188: =IF(VLOOKUP(A188,'Aux - pivots1'!$A:$E,4,0)=0, "",VLOOKUP(A188,'Aux - pivots1'!$A:$E,4,0)) | N188: =IF(VLOOKUP(A188,'Aux - pivots1'!$A:$E,5,0)=0, "",VLOOKUP(A188,'Aux - pivots1'!$A:$E,5,0)) | T188: Plano anterior
A189: =E189&F189 -> PROPERTY_ENERGY_CERTIFICATEREN_ENERGY_PRODUCED_VALUE | B189: Pilar III | C189: Bens Imóveis - Output | D189: 2. Campo | E189: PROPERTY_ENERGY_CERTIFICATE | F189: REN_ENERGY_PRODUCED_VALUE | G189: =VLOOKUP(A189,Plano_V3!$A$26:$G$759,7,0) -> 1. Concluído | H189: 1. Concluído | K189: Package X | L189: =IF(VLOOKUP(A189,'Aux - pivots1'!$A:$E,3,0)=0, "",VLOOKUP(A189,'Aux - pivots1'!$A:$E,3,0)) | M189: =IF(VLOOKUP(A189,'Aux - pivots1'!$A:$E,4,0)=0, "",VLOOKUP(A189,'Aux - pivots1'!$A:$E,4,0)) | N189: =IF(VLOOKUP(A189,'Aux - pivots1'!$A:$E,5,0)=0, "",VLOOKUP(A189,'Aux - pivots1'!$A:$E,5,0)) | T189: Plano anterior
A190: =E190&F190 -> PROPERTY_ENERGY_CERTIFICATEUSEFUL_ENERGY_DOM_HOTWATER_VALUE | B190: Pilar III | C190: Bens Imóveis - Output | D190: 2. Campo | E190: PROPERTY_ENERGY_CERTIFICATE | F190: USEFUL_ENERGY_DOM_HOTWATER_VALUE | G190: =VLOOKUP(A190,Plano_V3!$A$26:$G$759,7,0) -> 1. Concluído | H190: 1. Concluído | K190: Package X | L190: =IF(VLOOKUP(A190,'Aux - pivots1'!$A:$E,3,0)=0, "",VLOOKUP(A190,'Aux - pivots1'!$A:$E,3,0)) | M190: =IF(VLOOKUP(A190,'Aux - pivots1'!$A:$E,4,0)=0, "",VLOOKUP(A190,'Aux - pivots1'!$A:$E,4,0)) | N190: =IF(VLOOKUP(A190,'Aux - pivots1'!$A:$E,5,0)=0, "",VLOOKUP(A190,'Aux - pivots1'!$A:$E,5,0)) | T190: Plano anterior
A191: =E191&F191 -> PROPERTY_ENERGY_CERTIFICATEUSEFUL_ENERGY_COOLING_VALUE | B191: Pilar III | C191: Bens Imóveis - Output | D191: 2. Campo | E191: PROPERTY_ENERGY_CERTIFICATE | F191: USEFUL_ENERGY_COOLING_VALUE | G191: =VLOOKUP(A191,Plano_V3!$A$26:$G$759,7,0) -> 1. Concluído | H191: 1. Concluído | K191: Package X | L191: =IF(VLOOKUP(A191,'Aux - pivots1'!$A:$E,3,0)=0, "",VLOOKUP(A191,'Aux - pivots1'!$A:$E,3,0)) | M191: =IF(VLOOKUP(A191,'Aux - pivots1'!$A:$E,4,0)=0, "",VLOOKUP(A191,'Aux - pivots1'!$A:$E,4,0)) | N191: =IF(VLOOKUP(A191,'Aux - pivots1'!$A:$E,5,0)=0, "",VLOOKUP(A191,'Aux - pivots1'!$A:$E,5,0)) | T191: Plano anterior
A192: =E192&F192 -> PROPERTY_ENERGY_CERTIFICATETEMPERATURE_DAY_VALUE | B192: Pilar III | C192: Bens Imóveis - Output | D192: 2. Campo | E192: PROPERTY_ENERGY_CERTIFICATE | F192: TEMPERATURE_DAY_VALUE | G192: =VLOOKUP(A192,Plano_V3!$A$26:$G$759,7,0) -> 1. Concluído | H192: 1. Concluído | K192: Package X | L192: =IF(VLOOKUP(A192,'Aux - pivots1'!$A:$E,3,0)=0, "",VLOOKUP(A192,'Aux - pivots1'!$A:$E,3,0)) | M192: =IF(VLOOKUP(A192,'Aux - pivots1'!$A:$E,4,0)=0, "",VLOOKUP(A192,'Aux - pivots1'!$A:$E,4,0)) | N192: =IF(VLOOKUP(A192,'Aux - pivots1'!$A:$E,5,0)=0, "",VLOOKUP(A192,'Aux - pivots1'!$A:$E,5,0)) | T192: Plano anterior
A193: =E193&F193 -> PROPERTY_ENERGY_CERTIFICATEPRIMARY_ENERGY_REQ_VALUE | B193: Pilar III | C193: Bens Imóveis - Output | D193: 2. Campo | E193: PROPERTY_ENERGY_CERTIFICATE | F193: PRIMARY_ENERGY_REQ_VALUE | G193: =VLOOKUP(A193,Plano_V3!$A$26:$G$759,7,0) -> 1. Concluído | H193: 1. Concluído | K193: Package X | L193: =IF(VLOOKUP(A193,'Aux - pivots1'!$A:$E,3,0)=0, "",VLOOKUP(A193,'Aux - pivots1'!$A:$E,3,0)) | M193: =IF(VLOOKUP(A193,'Aux - pivots1'!$A:$E,4,0)=0, "",VLOOKUP(A193,'Aux - pivots1'!$A:$E,4,0)) | N193: =IF(VLOOKUP(A193,'Aux - pivots1'!$A:$E,5,0)=0, "",VLOOKUP(A193,'Aux - pivots1'!$A:$E,5,0)) | T193: Plano anterior
A194: =E194&F194 -> PROPERTY_ENERGY_CERTIFICATEUSEFUL_ENERGY_HEATING_REQ_VALUE | B194: Pilar III | C194: Bens Imóveis - Output | D194: 2. Campo | E194: PROPERTY_ENERGY_CERTIFICATE | F194: USEFUL_ENERGY_HEATING_REQ_VALUE | G194: =VLOOKUP(A194,Plano_V3!$A$26:$G$759,7,0) -> 1. Concluído | H194: 1. Concluído | K194: Package X | L194: =IF(VLOOKUP(A194,'Aux - pivots1'!$A:$E,3,0)=0, "",VLOOKUP(A194,'Aux - pivots1'!$A:$E,3,0)) | M194: =IF(VLOOKUP(A194,'Aux - pivots1'!$A:$E,4,0)=0, "",VLOOKUP(A194,'Aux - pivots1'!$A:$E,4,0)) | N194: =IF(VLOOKUP(A194,'Aux - pivots1'!$A:$E,5,0)=0, "",VLOOKUP(A194,'Aux - pivots1'!$A:$E,5,0)) | T194: Plano anterior
A195: =E195&F195 -> PROPERTY_ENERGY_CERTIFICATEPNL_WINTER_WALLS_DOORS_VALUE | B195: Pilar III | C195: Bens Imóveis - Output | D195: 2. Campo | E195: PROPERTY_ENERGY_CERTIFICATE | F195: PNL_WINTER_WALLS_DOORS_VALUE | G195: =VLOOKUP(A195,Plano_V3!$A$26:$G$759,7,0) -> 1. Concluído | H195: 1. Concluído | K195: Package X | L195: =IF(VLOOKUP(A195,'Aux - pivots1'!$A:$E,3,0)=0, "",VLOOKUP(A195,'Aux - pivots1'!$A:$E,3,0)) | M195: =IF(VLOOKUP(A195,'Aux - pivots1'!$A:$E,4,0)=0, "",VLOOKUP(A195,'Aux - pivots1'!$A:$E,4,0)) | N195: =IF(VLOOKUP(A195,'Aux - pivots1'!$A:$E,5,0)=0, "",VLOOKUP(A195,'Aux - pivots1'!$A:$E,5,0)) | T195: Plano anterior
A196: =E196&F196 -> PROPERTY_ENERGY_CERTIFICATEPNL_WINTER_FLOORS_VALUE | B196: Pilar III | C196: Bens Imóveis - Output | D196: 2. Campo | E196: PROPERTY_ENERGY_CERTIFICATE | F196: PNL_WINTER_FLOORS_VALUE | G196: =VLOOKUP(A196,Plano_V3!$A$26:$G$759,7,0) -> 1. Concluído | H196: 1. Concluído | K196: Package X | L196: =IF(VLOOKUP(A196,'Aux - pivots1'!$A:$E,3,0)=0, "",VLOOKUP(A196,'Aux - pivots1'!$A:$E,3,0)) | M196: =IF(VLOOKUP(A196,'Aux - pivots1'!$A:$E,4,0)=0, "",VLOOKUP(A196,'Aux - pivots1'!$A:$E,4,0)) | N196: =IF(VLOOKUP(A196,'Aux - pivots1'!$A:$E,5,0)=0, "",VLOOKUP(A196,'Aux - pivots1'!$A:$E,5,0)) | T196: Plano anterior
... A215: =E215&F215 -> PROPERTY_ENERGY_CERTIFICATECLIMATE_ZONE_SUMMER | B215: Pilar III | C215: Bens Imóveis - Output | D215: 2. Campo | E215: PROPERTY_ENERGY_CERTIFICATE | F215: CLIMATE_ZONE_SUMMER | G215: =VLOOKUP(A215,Plano_V3!$A$26:$G$759,7,0) -> 1. Concluído | H215: 1. Concluído | K215: Package X | L215: =IF(VLOOKUP(A215,'Aux - pivots1'!$A:$E,3,0)=0, "",VLOOKUP(A215,'Aux - pivots1'!$A:$E,3,0)) | M215: =IF(VLOOKUP(A215,'Aux - pivots1'!$A:$E,4,0)=0, "",VLOOKUP(A215,'Aux - pivots1'!$A:$E,4,0)) | N215: =IF(VLOOKUP(A215,'Aux - pivots1'!$A:$E,5,0)=0, "",VLOOKUP(A215,'Aux - pivots1'!$A:$E,5,0)) | T215: Plano anterior
A216: =E216&F216 -> PROPERTY_ENERGY_CERTIFICATECURRENT_ENERGY_RATING_PERCENTAGE | B216: Pilar III | C216: Bens Imóveis - Output | D216: 2. Campo | E216: PROPERTY_ENERGY_CERTIFICATE | F216: CURRENT_ENERGY_RATING_PERCENTAGE | G216: =VLOOKUP(A216,Plano_V3!$A$26:$G$759,7,0) -> 1. Concluído | H216: 5. Em Correção | I216: Package 1 | J216: Package 1 | L216: =IF(VLOOKUP(A216,'Aux - pivots1'!$A:$E,3,0)=0, "",VLOOKUP(A216,'Aux - pivots1'!$A:$E,3,0)) | M216: =IF(VLOOKUP(A216,'Aux - pivots1'!$A:$E,4,0)=0, "",VLOOKUP(A216,'Aux - pivots1'!$A:$E,4,0)) | N216: =IF(VLOOKUP(A216,'Aux - pivots1'!$A:$E,5,0)=0, "",VLOOKUP(A216,'Aux - pivots1'!$A:$E,5,0)) | T216: Plano anterior | U216: HF
A217: =E217&F217 -> modesg_param_sfics_taxon_europeian.a. | B217: Pilar III | C217: Modelo Verde - Input | D217: 1. Universo | E217: modesg_param_sfics_taxon_europeia | F217: n.a. | G217: =VLOOKUP(A217,Plano_V3!$A$26:$G$759,7,0) -> 2.2 Em especificação | H217: 4. Validação EF | I217: Package X | J217: Package X | L217: =IF(VLOOKUP(A217,'Aux - pivots1'!$A:$E,3,0)=0, "",VLOOKUP(A217,'Aux - pivots1'!$A:$E,3,0)) | M217: =IF(VLOOKUP(A217,'Aux - pivots1'!$A:$E,4,0)=0, "",VLOOKUP(A217,'Aux - pivots1'!$A:$E,4,0)) | N217: =IF(VLOOKUP(A217,'Aux - pivots1'!$A:$E,5,0)=0, "",VLOOKUP(A217,'Aux - pivots1'!$A:$E,5,0)) | T217: Plano anterior | U217: RC
A218: =E218&F218 -> modesg_param_sfics_taxon_europeiaref_date | B218: Pilar III | C218: Modelo Verde - Input | D218: 2. Campo | E218: modesg_param_sfics_taxon_europeia | F218: ref_date | G218: =VLOOKUP(A218,Plano_V3!$A$26:$G$759,7,0) -> 2.2 Em especificação | H218: 4. Validação EF | I218: Package X | J218: Package X | L218: =IF(VLOOKUP(A218,'Aux - pivots1'!$A:$E,3,0)=0, "",VLOOKUP(A218,'Aux - pivots1'!$A:$E,3,0)) | M218: =IF(VLOOKUP(A218,'Aux - pivots1'!$A:$E,4,0)=0, "",VLOOKUP(A218,'Aux - pivots1'!$A:$E,4,0)) | N218: =IF(VLOOKUP(A218,'Aux - pivots1'!$A:$E,5,0)=0, "",VLOOKUP(A218,'Aux - pivots1'!$A:$E,5,0)) | T218: Plano anterior | U218: RC
A219: =E219&F219 -> modesg_param_sfics_taxon_europeiacod_regra | B219: Pilar III | C219: Modelo Verde - Input | D219: 2. Campo | E219: modesg_param_sfics_taxon_europeia | F219: cod_regra | G219: =VLOOKUP(A219,Plano_V3!$A$26:$G$759,7,0) -> 2.2 Em especificação | H219: 4. Validação EF | I219: Package X | J219: Package X | L219: =IF(VLOOKUP(A219,'Aux - pivots1'!$A:$E,3,0)=0, "",VLOOKUP(A219,'Aux - pivots1'!$A:$E,3,0)) | M219: =IF(VLOOKUP(A219,'Aux - pivots1'!$A:$E,4,0)=0, "",VLOOKUP(A219,'Aux - pivots1'!$A:$E,4,0)) | N219: =IF(VLOOKUP(A219,'Aux - pivots1'!$A:$E,5,0)=0, "",VLOOKUP(A219,'Aux - pivots1'!$A:$E,5,0)) | T219: Plano anterior | U219: RC
...

Sheet Aux - pivots1
A3: concat | B3: Max of Status2
A4: ENERGY_CERTIFICATE_EST_INPUTACTUAL_VALUE_IND | B4: 0
A5: ENERGY_CERTIFICATE_EST_INPUTANIO_CONSTRUCCION | B5: 7
A6: ENERGY_CERTIFICATE_EST_INPUTART_MATRICIAIS | B6: 7
A7: ENERGY_CERTIFICATE_EST_INPUTASSUPERFICIE_UTIL | B7: 7
A8: ENERGY_CERTIFICATE_EST_INPUTCAGLURB | B8: 7
A9: ENERGY_CERTIFICATE_EST_INPUTCASA_UNIFAMILIAR | B9: 7
A10: ENERGY_CERTIFICATE_EST_INPUTCHAVE_GLOVAL | B10: 7
A11: ENERGY_CERTIFICATE_EST_INPUTCLASS_GPT31 | B11: 7
A12: ENERGY_CERTIFICATE_EST_INPUTCLASS_STCLIM | B12: 7
A13: ENERGY_CERTIFICATE_EST_INPUTCLASSE_ENERGETICA | B13: 7
A14: ENERGY_CERTIFICATE_EST_INPUTCOD_CONSERVATORIA | B14: 7
A15: ENERGY_CERTIFICATE_EST_INPUTCÓDIGO_CONCEJO | B15: 7
... A729: Grand Total | B729: 8

Sheet Caderno Testes FY24
N7: (alterar quando necessário) | R7: (data default - Dez2023)
B8: Âmbito | C8: Sub-âmbito | D8: Origem | E8: Campo Origem | F8: Tabela | G8: Campo | H8: concat | I8: Status | J8: Status2 | K8: Tipologia_Testes | L8: Necessidade de re-especificação? (campo) | M8: Complexidade | N8: Data de Alteração Status | O8: Estimação (horas) | P8: Notas | Q8: Owner | R8: Data alteração especificação | S8: Data de inicio testes | T8: Data de incidência / pedido esclarecimento | U8: Data de correção/resposta prevista | V8: Data de correção/resposta efetiva | W8: Horas efetivas | X8: Query
B9: Pilar III | C9: Bens Imóveis - Input | D9: bu_esg_work.kt_chave_gloval; bu_esg_work.gloval_clase_energetica_dez23 | E9: n.a. | F9: ENERGY_CERTIFICATE_EST_INPUT | G9: n.a. | H9: =Table1[[#This Row],[Tabela]]&Table1[[#This Row],[Campo]] -> ENERGY_CERTIFICATE_EST_INPUTn.a. | I9: 6. Em implementação | J9: =VLOOKUP(Table1[[#This Row],[Status]],Auxiliar!$B$16:$C$24,2,0) -> 7 | K9: 1. Teste de universo | L9: Não | M9: Baixa | N9: 45688 | O9: =INDEX(Auxiliar!$D$5:$F$13,MATCH(Table1[[#This Row],[Tipologia_Testes]],Auxiliar!$B$5:$B$13,0),MATCH(Table1[[#This Row],[Complexidade]],Auxiliar!$D$4:$F$4,0)) -> 8 | R9: 45261 | T9: 45510 | U9: 45624 | W9: =VLOOKUP(Table1[[#This Row],[Status]],Auxiliar!$B$16:$D$24,3,0)*Table1[[#This Row],[Estimação (horas)]] -> 2
B10: Pilar III | C10: Bens Imóveis - Input | D10: bu_esg_work.kt_chave_gloval; bu_esg_work.gloval_clase_energetica_dez23 | E10: n.a. | F10: ENERGY_CERTIFICATE_EST_INPUT | G10: DATA_PROVIDER | H10: =Table1[[#This Row],[Tabela]]&Table1[[#This Row],[Campo]] -> ENERGY_CERTIFICATE_EST_INPUTDATA_PROVIDER | I10: 0. Cancelado | J10: =VLOOKUP(Table1[[#This Row],[Status]],Auxiliar!$B$16:$C$24,2,0) -> 0 | N10: 45688 | O10: =INDEX(Auxiliar!$D$5:$F$11,MATCH(Table1[[#This Row],[Tipologia_Testes]],Auxiliar!$B$5:$B$11,0),MATCH(Table1[[#This Row],[Complexidade]],Auxiliar!$D$4:$F$4,0)) -> #N/A | W10: =VLOOKUP(Table1[[#This Row],[Status]],Auxiliar!$B$16:$D$24,3,0)*Table1[[#This Row],[Estimação (horas)]] -> #N/A
B11: Pilar III | C11: Bens Imóveis - Input | D11: bu_esg_work.kt_chave_gloval; bu_esg_work.gloval_clase_energetica_dez23 | E11: n.a. | F11: ENERGY_CERTIFICATE_EST_INPUT | G11: ACTUAL_VALUE_IND | H11: =Table1[[#This Row],[Tabela]]&Table1[[#This Row],[Campo]] -> ENERGY_CERTIFICATE_EST_INPUTACTUAL_VALUE_IND | I11: 0. Cancelado | J11: =VLOOKUP(Table1[[#This Row],[Status]],Auxiliar!$B$16:$C$24,2,0) -> 0 | N11: 45688 | O11: =INDEX(Auxiliar!$D$5:$F$11,MATCH(Table1[[#This Row],[Tipologia_Testes]],Auxiliar!$B$5:$B$11,0),MATCH(Table1[[#This Row],[Complexidade]],Auxiliar!$D$4:$F$4,0)) -> #N/A | W11: =VLOOKUP(Table1[[#This Row],[Status]],Auxiliar!$B$16:$D$24,3,0)*Table1[[#This Row],[Estimação (horas)]] -> #N/A
B12: Pilar III | C12: Bens Imóveis - Input | D12: bu_esg_work.kt_chave_gloval; bu_esg_work.gloval_clase_energetica_dez23 | E12: n.a. | F12: ENERGY_CERTIFICATE_EST_INPUT | G12: CHAVE_GLOVAL | H12: =Table1[[#This Row],[Tabela]]&Table1[[#This Row],[Campo]] -> ENERGY_CERTIFICATE_EST_INPUTCHAVE_GLOVAL | I12: 6. Em implementação | J12: =VLOOKUP(Table1[[#This Row],[Status]],Auxiliar!$B$16:$C$24,2,0) -> 7 | K12: 6. Validação de formatos | L12: Sim | M12: Baixa | N12: 45688 | O12: =INDEX(Auxiliar!$D$5:$F$13,MATCH(Table1[[#This Row],[Tipologia_Testes]],Auxiliar!$B$5:$B$13,0),MATCH(Table1[[#This Row],[Complexidade]],Auxiliar!$D$4:$F$4,0)) -> 0.1 | R12: 45261 | T12: 45510 | U12: 45624 | W12: =VLOOKUP(Table1[[#This Row],[Status]],Auxiliar!$B$16:$D$24,3,0)*Table1[[#This Row],[Estimação (horas)]] -> 0.025
B13: Pilar III | C13: Bens Imóveis - Input | D13: bu_esg_work.kt_chave_gloval; bu_esg_work.gloval_clase_energetica_dez23 | E13: n.a. | F13: ENERGY_CERTIFICATE_EST_INPUT | G13: PROPERTY_BANK_ID | H13: =Table1[[#This Row],[Tabela]]&Table1[[#This Row],[Campo]] -> ENERGY_CERTIFICATE_EST_INPUTPROPERTY_BANK_ID | I13: 6. Em implementação | J13: =VLOOKUP(Table1[[#This Row],[Status]],Auxiliar!$B$16:$C$24,2,0) -> 7 | K13: 6. Validação de formatos | L13: Sim | M13: Baixa | N13: 45688 | O13: =INDEX(Auxiliar!$D$5:$F$13,MATCH(Table1[[#This Row],[Tipologia_Testes]],Auxiliar!$B$5:$B$13,0),MATCH(Table1[[#This Row],[Complexidade]],Auxiliar!$D$4:$F$4,0)) -> 0.1 | P13: Comentário da Susana ao paralelo: Efetivamente recebemos informação da Gloval mas para este efeito devemos apenas tomar os dados reais (e não as estimativas); existe um campo que indica essa situação | R13: 45261 | T13: 45510 | U13: 45624 | W13: =VLOOKUP(Table1[[#This Row],[Status]],Auxiliar!$B$16:$D$24,3,0)*Table1[[#This Row],[Estimação (horas)]] -> 0.025
B14: Pilar III | C14: Bens Imóveis - Input | D14: bu_esg_work.kt_chave_gloval; bu_esg_work.gloval_clase_energetica_dez23 | E14: n.a. | F14: ENERGY_CERTIFICATE_EST_INPUT | G14: PROPERTY_BRANCH_CODE | H14: =Table1[[#This Row],[Tabela]]&Table1[[#This Row],[Campo]] -> ENERGY_CERTIFICATE_EST_INPUTPROPERTY_BRANCH_CODE | I14: 6. Em implementação | J14: =VLOOKUP(Table1[[#This Row],[Status]],Auxiliar!$B$16:$C$24,2,0) -> 7 | K14: 6. Validação de formatos | L14: Sim | M14: Baixa | N14: 45688 | O14: =INDEX(Auxiliar!$D$5:$F$13,MATCH(Table1[[#This Row],[Tipologia_Testes]],Auxiliar!$B$5:$B$13,0),MATCH(Table1[[#This Row],[Complexidade]],Auxiliar!$D$4:$F$4,0)) -> 0.1 | P14: Cempresa não está incluída na chave - mas a especificação no excel diz: Chave encriptada do bem, gerada com base na concatenação das variáveis cempbem, ckbalbem, ckctabem e ckrefbem | R14: 45261 | T14: 45510 | U14: 45624 | W14: =VLOOKUP(Table1[[#This Row],[Status]],Auxiliar!$B$16:$D$24,3,0)*Table1[[#This Row],[Estimação (horas)]] -> 0.025
B15: Pilar III | C15: Bens Imóveis - Input | D15: bu_esg_work.kt_chave_gloval; bu_esg_work.gloval_clase_energetica_dez23 | E15: n.a. | F15: ENERGY_CERTIFICATE_EST_INPUT | G15: PROPERTY_CONTRACT_ID | H15: =Table1[[#This Row],[Tabela]]&Table1[[#This Row],[Campo]] -> ENERGY_CERTIFICATE_EST_INPUTPROPERTY_CONTRACT_ID | I15: 6. Em implementação | J15: =VLOOKUP(Table1[[#This Row],[Status]],Auxiliar!$B$16:$C$24,2,0) -> 7 | K15: 6. Validação de formatos | L15: Sim | M15: Baixa | N15: 45688 | O15: =INDEX(Auxiliar!$D$5:$F$13,MATCH(Table1[[#This Row],[Tipologia_Testes]],Auxiliar!$B$5:$B$13,0),MATCH(Table1[[#This Row],[Complexidade]],Auxiliar!$D$4:$F$4,0)) -> 0.1 | P15: Cempresa não está incluída na chave - mas a especificação no excel diz: Chave encriptada do bem, gerada com base na concatenação das variáveis cempbem, ckbalbem, ckctabem e ckrefbem | R15: 45261 | T15: 45510 | U15: 45624 | W15: =VLOOKUP(Table1[[#This Row],[Status]],Auxiliar!$B$16:$D$24,3,0)*Table1[[#This Row],[Estimação (horas)]] -> 0.025
B16: Pilar III | C16: Bens Imóveis - Input | D16: bu_esg_work.kt_chave_gloval; bu_esg_work.gloval_clase_energetica_dez23 | E16: n.a. | F16: ENERGY_CERTIFICATE_EST_INPUT | G16: PROPERTY_REFERENCE_CODE | H16: =Table1[[#This Row],[Tabela]]&Table1[[#This Row],[Campo]] -> ENERGY_CERTIFICATE_EST_INPUTPROPERTY_REFERENCE_CODE | I16: 6. Em implementação | J16: =VLOOKUP(Table1[[#This Row],[Status]],Auxiliar!$B$16:$C$24,2,0) -> 7 | K16: 6. Validação de formatos | L16: Sim | M16: Baixa | N16: 45688 | O16: =INDEX(Auxiliar!$D$5:$F$13,MATCH(Table1[[#This Row],[Tipologia_Testes]],Auxiliar!$B$5:$B$13,0),MATCH(Table1[[#This Row],[Complexidade]],Auxiliar!$D$4:$F$4,0)) -> 0.1 | R16: 45261 | T16: 45510 | U16: 45624 | W16: =VLOOKUP(Table1[[#This Row],[Status]],Auxiliar!$B$16:$D$24,3,0)*Table1[[#This Row],[Estimação (horas)]] -> 0.025
B17: Pilar III | C17: Bens Imóveis - Input | D17: bu_esg_work.kt_chave_gloval; bu_esg_work.gloval_clase_energetica_dez23 | E17: n.a. | F17: ENERGY_CERTIFICATE_EST_INPUT | G17: CÓDIGO_DISTRITO | H17: =Table1[[#This Row],[Tabela]]&Table1[[#This Row],[Campo]] -> ENERGY_CERTIFICATE_EST_INPUTCÓDIGO_DISTRITO | I17: 6. Em implementação | J17: =VLOOKUP(Table1[[#This Row],[Status]],Auxiliar!$B$16:$C$24,2,0) -> 7 | K17: 6. Validação de formatos | L17: Sim | M17: Baixa | N17: 45688 | O17: =INDEX(Auxiliar!$D$5:$F$13,MATCH(Table1[[#This Row],[Tipologia_Testes]],Auxiliar!$B$5:$B$13,0),MATCH(Table1[[#This Row],[Complexidade]],Auxiliar!$D$4:$F$4,0)) -> 0.1 | R17: 45261 | T17: 45510 | U17: 45624 | W17: =VLOOKUP(Table1[[#This Row],[Status]],Auxiliar!$B$16:$D$24,3,0)*Table1[[#This Row],[Estimação (horas)]] -> 0.025
B18: Pilar III | C18: Bens Imóveis - Input | D18: bu_esg_work.kt_chave_gloval; bu_esg_work.gloval_clase_energetica_dez23 | E18: n.a. | F18: ENERGY_CERTIFICATE_EST_INPUT | G18: NOMBRE_DISTRITO | H18: =Table1[[#This Row],[Tabela]]&Table1[[#This Row],[Campo]] -> ENERGY_CERTIFICATE_EST_INPUTNOMBRE_DISTRITO | I18: 6. Em implementação | J18: =VLOOKUP(Table1[[#This Row],[Status]],Auxiliar!$B$16:$C$24,2,0) -> 7 | K18: 6. Validação de formatos | L18: Sim | M18: Baixa | N18: 45688 | O18: =INDEX(Auxiliar!$D$5:$F$13,MATCH(Table1[[#This Row],[Tipologia_Testes]],Auxiliar!$B$5:$B$13,0),MATCH(Table1[[#This Row],[Complexidade]],Auxiliar!$D$4:$F$4,0)) -> 0.1 | R18: 45261 | T18: 45510 | U18: 45624 | W18: =VLOOKUP(Table1[[#This Row],[Status]],Auxiliar!$B$16:$D$24,3,0)*Table1[[#This Row],[Estimação (horas)]] -> 0.025
B19: Pilar III | C19: Bens Imóveis - Input | D19: bu_esg_work.kt_chave_gloval; bu_esg_work.gloval_clase_energetica_dez23 | E19: n.a. | F19: ENERGY_CERTIFICATE_EST_INPUT | G19: CÓDIGO_CONCEJO | H19: =Table1[[#This Row],[Tabela]]&Table1[[#This Row],[Campo]] -> ENERGY_CERTIFICATE_EST_INPUTCÓDIGO_CONCEJO | I19: 6. Em implementação | J19: =VLOOKUP(Table1[[#This Row],[Status]],Auxiliar!$B$16:$C$24,2,0) -> 7 | K19: 6. Validação de formatos | L19: Sim | M19: Baixa | N19: 45688 | O19: =INDEX(Auxiliar!$D$5:$F$13,MATCH(Table1[[#This Row],[Tipologia_Testes]],Auxiliar!$B$5:$B$13,0),MATCH(Table1[[#This Row],[Complexidade]],Auxiliar!$D$4:$F$4,0)) -> 0.1 | R19: 45261 | T19: 45510 | U19: 45624 | W19: =VLOOKUP(Table1[[#This Row],[Status]],Auxiliar!$B$16:$D$24,3,0)*Table1[[#This Row],[Estimação (horas)]] -> 0.025
B20: Pilar III | C20: Bens Imóveis - Input | D20: bu_esg_work.kt_chave_gloval; bu_esg_work.gloval_clase_energetica_dez23 | E20: n.a. | F20: ENERGY_CERTIFICATE_EST_INPUT | G20: NOMBRE_CONCEJO | H20: =Table1[[#This Row],[Tabela]]&Table1[[#This Row],[Campo]] -> ENERGY_CERTIFICATE_EST_INPUTNOMBRE_CONCEJO | I20: 6. Em implementação | J20: =VLOOKUP(Table1[[#This Row],[Status]],Auxiliar!$B$16:$C$24,2,0) -> 7 | K20: 6. Validação de formatos | L20: Sim | M20: Baixa | N20: 45688 | O20: =INDEX(Auxiliar!$D$5:$F$13,MATCH(Table1[[#This Row],[Tipologia_Testes]],Auxiliar!$B$5:$B$13,0),MATCH(Table1[[#This Row],[Complexidade]],Auxiliar!$D$4:$F$4,0)) -> 0.1 | R20: 45261 | T20: 45510 | U20: 45624 | W20: =VLOOKUP(Table1[[#This Row],[Status]],Auxiliar!$B$16:$D$24,3,0)*Table1[[#This Row],[Estimação (horas)]] -> 0.025
B21: Pilar III | C21: Bens Imóveis - Input | D21: bu_esg_work.kt_chave_gloval; bu_esg_work.gloval_clase_energetica_dez23 | E21: n.a. | F21: ENERGY_CERTIFICATE_EST_INPUT | G21: CÓDIGO_FREGUESIA | H21: =Table1[[#This Row],[Tabela]]&Table1[[#This Row],[Campo]] -> ENERGY_CERTIFICATE_EST_INPUTCÓDIGO_FREGUESIA | I21: 6. Em implementação | J21: =VLOOKUP(Table1[[#This Row],[Status]],Auxiliar!$B$16:$C$24,2,0) -> 7 | K21: 6. Validação de formatos | L21: Sim | M21: Baixa | N21: 45688 | O21: =INDEX(Auxiliar!$D$5:$F$13,MATCH(Table1[[#This Row],[Tipologia_Testes]],Auxiliar!$B$5:$B$13,0),MATCH(Table1[[#This Row],[Complexidade]],Auxiliar!$D$4:$F$4,0)) -> 0.1 | R21: 45261 | T21: 45510 | U21: 45624 | W21: =VLOOKUP(Table1[[#This Row],[Status]],Auxiliar!$B$16:$D$24,3,0)*Table1[[#This Row],[Estimação (horas)]] -> 0.025
B22: Pilar III | C22: Bens Imóveis - Input | D22: bu_esg_work.kt_chave_gloval; bu_esg_work.gloval_clase_energetica_dez23 | E22: n.a. | F22: ENERGY_CERTIFICATE_EST_INPUT | G22: NOMBRE_FREGUESIA | H22: =Table1[[#This Row],[Tabela]]&Table1[[#This Row],[Campo]] -> ENERGY_CERTIFICATE_EST_INPUTNOMBRE_FREGUESIA | I22: 6. Em implementação | J22: =VLOOKUP(Table1[[#This Row],[Status]],Auxiliar!$B$16:$C$24,2,0) -> 7 | K22: 6. Validação de formatos | L22: Sim | M22: Baixa | N22: 45688 | O22: =INDEX(Auxiliar!$D$5:$F$13,MATCH(Table1[[#This Row],[Tipologia_Testes]],Auxiliar!$B$5:$B$13,0),MATCH(Table1[[#This Row],[Complexidade]],Auxiliar!$D$4:$F$4,0)) -> 0.1 | R22: 45261 | T22: 45510 | U22: 45624 | W22: =VLOOKUP(Table1[[#This Row],[Status]],Auxiliar!$B$16:$D$24,3,0)*Table1[[#This Row],[Estimação (horas)]] -> 0.025
B23: Pilar III | C23: Bens Imóveis - Input | D23: bu_esg_work.kt_chave_gloval; bu_esg_work.gloval_clase_energetica_dez23 | E23: n.a. | F23: ENERGY_CERTIFICATE_EST_INPUT | G23: LOCALIDADE | H23: =Table1[[#This Row],[Tabela]]&Table1[[#This Row],[Campo]] -> ENERGY_CERTIFICATE_EST_INPUTLOCALIDADE | I23: 6. Em implementação | J23: =VLOOKUP(Table1[[#This Row],[Status]],Auxiliar!$B$16:$C$24,2,0) -> 7 | K23: 6. Validação de formatos | L23: Sim | M23: Baixa | N23: 45688 | O23: =INDEX(Auxiliar!$D$5:$F$13,MATCH(Table1[[#This Row],[Tipologia_Testes]],Auxiliar!$B$5:$B$13,0),MATCH(Table1[[#This Row],[Complexidade]],Auxiliar!$D$4:$F$4,0)) -> 0.1 | R23: 45261 | T23: 45510 | U23: 45624 | W23: =VLOOKUP(Table1[[#This Row],[Status]],Auxiliar!$B$16:$D$24,3,0)*Table1[[#This Row],[Estimação (horas)]] -> 0.025
