Workbook

Sheet Plano_V1
B6: Re-testes - input | D6: 0.2 | M6: =M7-M10 -> 0 | N6: =N7-N10 -> 0 | O6: =O7-O10 -> 0 | P6: =P7-P10 -> 0 | Q6: =Q7-Q10 -> 0 | R6: =R7-R10 -> 0 | S6: =S7-S10 -> 0 | T6: =T7-T10 -> 0 | ... FK6: =FK7-FK10 -> 0
B7: Re-testes - output | D7: =50%*25% -> 0.125 | L7: =AVERAGE(M7:EL7) -> 2.4923077 | M7: 3 | N7: 3 | O7: 3 | P7: 3 | Q7: 3 | R7: 2 | S7: 2 | T7: 2 | U7: 2 | V7: 2 | W7: 2 | X7: 2 | Y7: 2 | Z7: 2 | AA7: 2 | AB7: 2 | AC7: 2 | AD7: 1 | AE7: 1 | AF7: 1 | AG7: 3 | AH7: 3 | AI7: 3 | AJ7: 3 | AK7: 2 | AL7: 3 | AM7: 3 | AN7: 3 | AO7: 3 | AP7: 3 | AQ7: 2 | AR7: 2 | AS7: 2 | AT7: 0 | AU7: 1 | AV7: 1 | AW7: 0 | AX7: 1 | AY7: 1 | AZ7: 1 | BA7: 2 | BB7: 2 | BC7: 2 | BD7: 2 | BE7: 2 | BF7: 2 | BG7: 2 | BH7: 2 | BI7: 2 | BJ7: 2 | BK7: 2 | BL7: 2 | BM7: 2 | BN7: 2 | BO7: 2 | BP7: 3 | BQ7: 3 | BR7: 3 | BS7: 3 | BT7: 3 | BU7: 3 | BV7: 3 | BW7: 3 | BX7: 3 | BY7: 3 | BZ7: 3 | CA7: 3 | CB7: 3 | CC7: 3 | CD7: 3 | CE7: 3 | CF7: 3 | CG7: 3 | CH7: 3 | CI7: 3 | CJ7: 3 | CK7: 3 | CL7: 3 | CM7: 3 | CN7: 3 | CO7: 3 | CP7: 3 | CQ7: 3 | CR7: 3 | CS7: 3 | CT7: 3 | CU7: 3 | CV7: 3 | CW7: 3 | CX7: 3 | CY7: 3 | CZ7: 3 | DA7: 3 | DB7: 3 | DC7: 3 | DD7: 3 | DE7: 3 | DF7: 3 | DG7: 3 | DH7: 3 | DI7: 3 | DJ7: 3 | DK7: 3 | DL7: 3 | DM7: 3 | DN7: 2 | DO7: 3 | DP7: 3 | DQ7: 3 | DR7: 3 | DS7: 3 | DT7: 3 | DU7: 3 | DV7: 3 | DW7: 3 | DX7: 3 | DY7: 3 | DZ7: 3 | EA7: 3 | EB7: 3 | EC7: 3 | ED7: 3 | EE7: 3 | EF7: 3 | EG7: 3 | EH7: 3 | EI7: 0 | EJ7: 0 | EK7: 0 | EL7: 0 | EM7: 0 | EN7: 0 | EO7: 0 | EP7: 3 | EQ7: 3 | ER7: 3 | ES7: 3 | ET7: 3 | EU7: 3 | EV7: 3 | EW7: 3 | EX7: 3 | EY7: 3 | EZ7: 3 | FA7: 3 | FB7: 3 | FC7: 3 | FD7: 3 | FE7: 3 | FF7: 3 | FG7: 3 | FH7: 3 | FI7: 3 | FJ7: 3 | FK7: 3
M10: =SUBTOTAL(9,M14:M636) -> 3 | N10: =SUBTOTAL(9,N14:N636) -> 3 | O10: =SUBTOTAL(9,O14:O636) -> 3 | P10: =SUBTOTAL(9,P14:P636) -> 3 | Q10: =SUBTOTAL(9,Q14:Q636) -> 3 | R10: =SUBTOTAL(9,R14:R636) -> 2 | S10: =SUBTOTAL(9,S14:S636) -> 2 | T10: =SUBTOTAL(9,T14:T636) -> 2 | ... FK10: =SUBTOTAL(9,FK14:FK636) -> 3
M11: Julho | W11: Julho | AJ11: Agosto | BF11: Setembro | CA11: Outubro | CX11: Novembro | DS11: Dezembro | EO11: Janeiro
M12: =M13 -> 45474 | N12: =N13 -> 45475 | O12: =O13 -> 45476 | P12: =P13 -> 45477 | Q12: =Q13 -> 45478 | R12: =R13 -> 45481 | S12: =S13 -> 45482 | T12: =T13 -> 45483 | ... FK12: =FK13 -> 45688
B13: Âmbito | C13: Sub-âmbito | D13: Tipo de teste | E13: Tabela | F13: Campo | G13: Status | H13: Status2 | I13: Horas | J13: Dias | K13: Pendências | L13: Val | M13: 45474 | N13: =WORKDAY(M13,1) -> 45475 | O13: =WORKDAY(N13,1) -> 45476 | P13: =WORKDAY(O13,1) -> 45477 | Q13: =WORKDAY(P13,1) -> 45478 | R13: =WORKDAY(Q13,1) -> 45481 | S13: =WORKDAY(R13,1) -> 45482 | T13: =WORKDAY(S13,1) -> 45483 | U13: =WORKDAY(T13,1) -> 45484 | ... FK13: =WORKDAY(FJ13,1) -> 45688
B14: 1. Assessment | I14: =SUM(I15:I18) -> 280 | J14: =SUM(J15:J18) -> 35
B15: Pilar III | C15: Bens Imóveis | G15: 7. Por iniciar | I15: =J15*8 -> 40 | J15: 5 | L15: =J15-SUM(M15:FK15) -> 0 | W15: 1 | X15: 1 | Y15: 1 | Z15: 1 | AA15: 1
B16: Pilar III | C16: Modelo Verde | G16: 7. Por iniciar | I16: =J16*8 -> 80 | J16: 10 | L16: =J16-SUM(M16:FK16) -> 0 | R16: 2 | S16: 2 | T16: 2 | U16: 2 | V16: 2
B17: Pilar III | C17: Pilar III | G17: 7. Por iniciar | I17: =J17*8 -> 40 | J17: 5 | L17: =J17-SUM(M17:FK17) -> 0 | AB17: 1 | AC17: 1 | AD17: 1 | AE17: 1 | AF17: 0.5 | AG17: 0.5
B18: GD | C18: GD | G18: 7. Por iniciar | I18: =J18*8 -> 120 | J18: 15 | L18: =J18-SUM(M18:FK18) -> 0 | M18: 3 | N18: 3 | O18: 3 | P18: 3 | Q18: 3
B20: 2. Re-especificação | I20: =SUM(I21:I23) -> 120 | J20: =SUM(J21:J23) -> 15
B21: Pilar III | C21: Bens Imóveis | G21: 7. Por iniciar | I21: =J21*8 -> 40 | J21: 5 | L21: =J21-SUM(M21:FK21) -> 0 | W21: 0.5 | AB21: 0.5 | AG21: 0.5 | AL21: 0.5 | AQ21: 0.5 | AV21: 0.5 | BA21: 0.5 | BF21: 0.5 | BK21: 0.5 | BP21: 0.5
B22: Pilar III | C22: Modelo Verde | G22: 7. Por iniciar | I22: =J22*8 -> 40 | J22: 5 | L22: =J22-SUM(M22:FK22) -> 0 | W22: 0.5 | AB22: 0.5 | AG22: 0.5 | AL22: 0.5 | AQ22: 0.5 | AV22: 0.5 | BA22: 0.5 | BF22: 0.5 | BK22: 0.5 | BP22: 0.5
B23: Pilar III | C23: Pilar III | G23: 7. Por iniciar | I23: =J23*8 -> 40 | J23: 5 | L23: =J23-SUM(M23:FK23) -> 0 | BF23: 0.5 | BK23: 0.5 | BP23: 0.5 | BU23: 0.5 | BZ23: 0.5 | CE23: 0.5 | CJ23: 0.5 | CO23: 0.5 | CT23: 0.5 | CY23: 0.5
B25: 3. Testes / Re-testes | I25: =I26+I27+I42+I198+I362+I447 -> 1192.8125 | J25: =J26+J27+J42+J198+J362+J447 -> 151
B26: Testes Regressivos | G26: 7. Por iniciar | I26: =4*22 -> 88 | J26: =I26/8 -> 11 | L26: =J26-SUM(M26:FK26) -> 0 | AA26: 0.5 | AF26: 0.5 | AK26: 0.5 | AP26: 0.5 | AU26: 0.5 | AZ26: 0.5 | BE26: 0.5 | BJ26: 0.5 | BO26: 0.5 | BT26: 0.5 | BY26: 0.5 | CD26: 0.5 | CI26: 0.5 | CN26: 0.5 | CS26: 0.5 | CX26: 0.5 | DC26: 0.5 | DH26: 0.5 | DM26: 0.5 | DR26: 0.5 | DW26: 0.5 | EB26: 0.5
B27: Pilar III | C27: Bens Imóveis - Input | I27: =SUM(I28:I41) -> 0 | J27: =ROUNDUP(I27/8,0) -> 0 | L27: =J27-SUM(M27:FK27) -> -3 | X27: 0.5 | Y27: 0.5 | AC27: 0.5 | AG27: 1 | AH27: 0.5
A28: =E28&F28 -> cd_imv_inp_certif_estimativan.a. | B28: Pilar III | C28: Bens Imóveis - Input | D28: 1. Universo | E28: cd_imv_inp_certif_estimativa | F28: n.a. | G28: =INDEX(Auxiliar!$B$16:$B$24,MATCH(Plano_V1!H28,Auxiliar!$C$16:$C$24,0),1) -> #N/A | H28: =VLOOKUP(A28,'Aux - pivots1'!$A:$B,2,0) -> #N/A | I28: =SUMIFS(Table1[Estimação (horas)],Table1[Tabela],Plano_V1!E28,Table1[Campo],Plano_V1!F28) -> 0 | J28: =I28/8 -> 0 | K28: sem pendencia | L28: =J28-SUM(M28:FK28) -> 0
A29: =E29&F29 -> cd_imv_inp_certif_estimativacempbem | B29: Pilar III | C29: Bens Imóveis - Input | D29: 2. Campo | E29: cd_imv_inp_certif_estimativa | F29: cempbem | G29: =INDEX(Auxiliar!$B$16:$B$24,MATCH(Plano_V1!H29,Auxiliar!$C$16:$C$24,0),1) -> #N/A | H29: =VLOOKUP(A29,'Aux - pivots1'!$A:$B,2,0) -> #N/A | I29: =SUMIFS(Table1[Estimação (horas)],Table1[Tabela],Plano_V1!E29,Table1[Campo],Plano_V1!F29) -> 0 | J29: =I29/8 -> 0 | K29: sem pendencia | L29: =J29-SUM(M29:FK29) -> 0
A30: =E30&F30 -> cd_imv_inp_certif_estimativachave_encriptada | B30: Pilar III | C30: Bens Imóveis - Input | D30: 2. Campo | E30: cd_imv_inp_certif_estimativa | F30: chave_encriptada | G30: =INDEX(Auxiliar!$B$16:$B$24,MATCH(Plano_V1!H30,Auxiliar!$C$16:$C$24,0),1) -> #N/A | H30: =VLOOKUP(A30,'Aux - pivots1'!$A:$B,2,0) -> #N/A | I30: =SUMIFS(Table1[Estimação (horas)],Table1[Tabela],Plano_V1!E30,Table1[Campo],Plano_V1!F30) -> 0 | J30: =I30/8 -> 0 | K30: sem pendencia | L30: =J30-SUM(M30:FK30) -> 0
A31: =E31&F31 -> cd_imv_inp_certif_estimativackbalbem | B31: Pilar III | C31: Bens Imóveis - Input | D31: 2. Campo | E31: cd_imv_inp_certif_estimativa | F31: ckbalbem | G31: =INDEX(Auxiliar!$B$16:$B$24,MATCH(Plano_V1!H31,Auxiliar!$C$16:$C$24,0),1) -> #N/A | H31: =VLOOKUP(A31,'Aux - pivots1'!$A:$B,2,0) -> #N/A | I31: =SUMIFS(Table1[Estimação (horas)],Table1[Tabela],Plano_V1!E31,Table1[Campo],Plano_V1!F31) -> 0 | J31: =I31/8 -> 0 | K31: sem pendencia | L31: =J31-SUM(M31:FK31) -> 0
A32: =E32&F32 -> cd_imv_inp_certif_estimativackctabem | B32: Pilar III | C32: Bens Imóveis - Input | D32: 2. Campo | E32: cd_imv_inp_certif_estimativa | F32: ckctabem | G32: =INDEX(Auxiliar!$B$16:$B$24,MATCH(Plano_V1!H32,Auxiliar!$C$16:$C$24,0),1) -> #N/A | H32: =VLOOKUP(A32,'Aux - pivots1'!$A:$B,2,0) -> #N/A | I32: =SUMIFS(Table1[Estimação (horas)],Table1[Tabela],Plano_V1!E32,Table1[Campo],Plano_V1!F32) -> 0 | J32: =I32/8 -> 0 | K32: sem pendencia | L32: =J32-SUM(M32:FK32) -> 0
A33: =E33&F33 -> cd_imv_inp_certif_estimativackrefbem | B33: Pilar III | C33: Bens Imóveis - Input | D33: 2. Campo | E33: cd_imv_inp_certif_estimativa | F33: ckrefbem | G33: =INDEX(Auxiliar!$B$16:$B$24,MATCH(Plano_V1!H33,Auxiliar!$C$16:$C$24,0),1) -> #N/A | H33: =VLOOKUP(A33,'Aux - pivots1'!$A:$B,2,0) -> #N/A | I33: =SUMIFS(Table1[Estimação (horas)],Table1[Tabela],Plano_V1!E33,Table1[Campo],Plano_V1!F33) -> 0 | J33: =I33/8 -> 0 | K33: sem pendencia | L33: =J33-SUM(M33:FK33) -> 0
A34: =E34&F34 -> cd_imv_inp_certif_estimativadata_extraccao_info | B34: Pilar III | C34: Bens Imóveis - Input | D34: 2. Campo | E34: cd_imv_inp_certif_estimativa | F34: data_extraccao_info | G34: =INDEX(Auxiliar!$B$16:$B$24,MATCH(Plano_V1!H34,Auxiliar!$C$16:$C$24,0),1) -> #N/A | H34: =VLOOKUP(A34,'Aux - pivots1'!$A:$B,2,0) -> #N/A | I34: =SUMIFS(Table1[Estimação (horas)],Table1[Tabela],Plano_V1!E34,Table1[Campo],Plano_V1!F34) -> 0 | J34: =I34/8 -> 0 | K34: sem pendencia | L34: =J34-SUM(M34:FK34) -> 0
A35: =E35&F35 -> cd_imv_inp_certif_estimativaepc | B35: Pilar III | C35: Bens Imóveis - Input | D35: 2. Campo | E35: cd_imv_inp_certif_estimativa | F35: epc | G35: =INDEX(Auxiliar!$B$16:$B$24,MATCH(Plano_V1!H35,Auxiliar!$C$16:$C$24,0),1) -> #N/A | H35: =VLOOKUP(A35,'Aux - pivots1'!$A:$B,2,0) -> #N/A | I35: =SUMIFS(Table1[Estimação (horas)],Table1[Tabela],Plano_V1!E35,Table1[Campo],Plano_V1!F35) -> 0 | J35: =I35/8 -> 0 | K35: sem pendencia | L35: =J35-SUM(M35:FK35) -> 0
A36: =E36&F36 -> cd_imv_inp_certif_estimativafornecedor | B36: Pilar III | C36: Bens Imóveis - Input | D36: 2. Campo | E36: cd_imv_inp_certif_estimativa | F36: fornecedor | G36: =INDEX(Auxiliar!$B$16:$B$24,MATCH(Plano_V1!H36,Auxiliar!$C$16:$C$24,0),1) -> #N/A | H36: =VLOOKUP(A36,'Aux - pivots1'!$A:$B,2,0) -> #N/A | I36: =SUMIFS(Table1[Estimação (horas)],Table1[Tabela],Plano_V1!E36,Table1[Campo],Plano_V1!F36) -> 0 | J36: =I36/8 -> 0 | K36: sem pendencia | L36: =J36-SUM(M36:FK36) -> 0
A37: =E37&F37 -> cd_imv_inp_certif_estimativametodo_info | B37: Pilar III | C37: Bens Imóveis - Input | D37: 2. Campo | E37: cd_imv_inp_certif_estimativa | F37: metodo_info | G37: =INDEX(Auxiliar!$B$16:$B$24,MATCH(Plano_V1!H37,Auxiliar!$C$16:$C$24,0),1) -> #N/A | H37: =VLOOKUP(A37,'Aux - pivots1'!$A:$B,2,0) -> #N/A | I37: =SUMIFS(Table1[Estimação (horas)],Table1[Tabela],Plano_V1!E37,Table1[Campo],Plano_V1!F37) -> 0 | J37: =I37/8 -> 0 | K37: sem pendencia | L37: =J37-SUM(M37:FK37) -> 0
A38: =E38&F38 -> cd_imv_inp_certif_estimativascore_qualidade | B38: Pilar III | C38: Bens Imóveis - Input | D38: 2. Campo | E38: cd_imv_inp_certif_estimativa | F38: score_qualidade | G38: =INDEX(Auxiliar!$B$16:$B$24,MATCH(Plano_V1!H38,Auxiliar!$C$16:$C$24,0),1) -> #N/A | H38: =VLOOKUP(A38,'Aux - pivots1'!$A:$B,2,0) -> #N/A | I38: =SUMIFS(Table1[Estimação (horas)],Table1[Tabela],Plano_V1!E38,Table1[Campo],Plano_V1!F38) -> 0 | J38: =I38/8 -> 0 | K38: sem pendencia | L38: =J38-SUM(M38:FK38) -> 0
A39: =E39&F39 -> cd_imv_inp_certif_estimativavlr_cnsm_ano | B39: Pilar III | C39: Bens Imóveis - Input | D39: 2. Campo | E39: cd_imv_inp_certif_estimativa | F39: vlr_cnsm_ano | G39: =INDEX(Auxiliar!$B$16:$B$24,MATCH(Plano_V1!H39,Auxiliar!$C$16:$C$24,0),1) -> #N/A | H39: =VLOOKUP(A39,'Aux - pivots1'!$A:$B,2,0) -> #N/A | I39: =SUMIFS(Table1[Estimação (horas)],Table1[Tabela],Plano_V1!E39,Table1[Campo],Plano_V1!F39) -> 0 | J39: =I39/8 -> 0 | K39: sem pendencia | L39: =J39-SUM(M39:FK39) -> 0
A40: =E40&F40 -> cd_imv_inp_certif_estimativavlr_emss_ano | B40: Pilar III | C40: Bens Imóveis - Input | D40: 2. Campo | E40: cd_imv_inp_certif_estimativa | F40: vlr_emss_ano | G40: =INDEX(Auxiliar!$B$16:$B$24,MATCH(Plano_V1!H40,Auxiliar!$C$16:$C$24,0),1) -> #N/A | H40: =VLOOKUP(A40,'Aux - pivots1'!$A:$B,2,0) -> #N/A | I40: =SUMIFS(Table1[Estimação (horas)],Table1[Tabela],Plano_V1!E40,Table1[Campo],Plano_V1!F40) -> 0 | J40: =I40/8 -> 0 | K40: sem pendencia | L40: =J40-SUM(M40:FK40) -> 0
A41: =E41&F41 -> Re-testesn.a. | B41: Pilar III | C41: Bens Imóveis - Input | D41: 2. Campo | E41: Re-testes | F41: n.a. | G41: 7. Por iniciar | I41: =SUM(I28:I40)*D6 -> 0 | J41: =I41/8 -> 0 | K41: sem pendencia | L41: =J41-SUM(M41:FK41) -> 0
A42: =E42&F42 | B42: Pilar III | C42: Bens Imóveis - Output | I42: =SUM(I43:I197) -> 0 | J42: =ROUNDUP(I42/8,0) -> 0 | L42: =J42-SUM(M42:FK42) -> -100 | AH42: 0.5 | AI42: 1 | AJ42: 1 | AM42: 1 | AN42: 1 | AO42: 1 | AP42: 0.5 | AR42: 1 | AS42: 2 | AU42: 0.5 | AX42: 1 | AY42: 1 | AZ42: 0.5 | BA42: 1 | BB42: 2 | BC42: 2 | BD42: 2 | BE42: 1.5 | BF42: 0.5 | BG42: 2 | BH42: 2 | BI42: 2 | BJ42: 1.5 | BK42: 0.5 | BL42: 2 | BM42: 2 | BN42: 2 | BO42: 1.5 | BP42: 1.5 | BQ42: 2 | BR42: 2 | BS42: 2 | BT42: 2 | BU42: 2 | BV42: 2 | BW42: 2 | BX42: 2 | BY42: 2 | BZ42: 2 | CA42: 2 | CB42: 2 | CC42: 2 | CD42: 2 | CE42: 2 | CF42: 2 | CG42: 2 | CH42: 2 | CI42: 2 | CJ42: 2 | CK42: 2 | CL42: 2 | CM42: 2 | CN42: 2 | CO42: 2 | CP42: 2 | CQ42: 2 | CR42: 2 | CS42: 2 | CT42: 2 | CU42: 2
A43: =E43&F43 -> cd_imv_out_prcn.a. | B43: Pilar III | C43: Bens Imóveis - Output | D43: 1. Universo | E43: cd_imv_out_prc | F43: n.a. | G43: =INDEX(Auxiliar!$B$16:$B$24,MATCH(Plano_V1!H43,Auxiliar!$C$16:$C$24,0),1) -> #N/A | H43: =VLOOKUP(A43,'Aux - pivots1'!$A:$B,2,0) -> #N/A | I43: =SUMIFS(Table1[Estimação (horas)],Table1[Tabela],Plano_V1!E43,Table1[Campo],Plano_V1!F43) -> 0 | J43: =I43/8 -> 0 | K43: cd_imv_out_trz_cred_prc | L43: =J43-SUM(M43:FK43) -> 0
A44: =E44&F44 -> cd_imv_out_prccempresa | B44: Pilar III | C44: Bens Imóveis - Output | D44: 2. Campo | E44: cd_imv_out_prc | F44: cempresa | G44: =INDEX(Auxiliar!$B$16:$B$24,MATCH(Plano_V1!H44,Auxiliar!$C$16:$C$24,0),1) -> #N/A | H44: =VLOOKUP(A44,'Aux - pivots1'!$A:$B,2,0) -> #N/A | I44: =SUMIFS(Table1[Estimação (horas)],Table1[Tabela],Plano_V1!E44,Table1[Campo],Plano_V1!F44) -> 0 | J44: =I44/8 -> 0 | K44: cd_imv_out_trz_cred_prc | L44: =J44-SUM(M44:FK44) -> 0
A45: =E45&F45 -> cd_imv_out_prcckbalcao | B45: Pilar III | C45: Bens Imóveis - Output | D45: 2. Campo | E45: cd_imv_out_prc | F45: ckbalcao | G45: =INDEX(Auxiliar!$B$16:$B$24,MATCH(Plano_V1!H45,Auxiliar!$C$16:$C$24,0),1) -> #N/A | H45: =VLOOKUP(A45,'Aux - pivots1'!$A:$B,2,0) -> #N/A | I45: =SUMIFS(Table1[Estimação (horas)],Table1[Tabela],Plano_V1!E45,Table1[Campo],Plano_V1!F45) -> 0 | J45: =I45/8 -> 0 | K45: cd_imv_out_trz_cred_prc | L45: =J45-SUM(M45:FK45) -> 0
A46: =E46&F46 -> cd_imv_out_prccknumcta | B46: Pilar III | C46: Bens Imóveis - Output | D46: 2. Campo | E46: cd_imv_out_prc | F46: cknumcta | G46: =INDEX(Auxiliar!$B$16:$B$24,MATCH(Plano_V1!H46,Auxiliar!$C$16:$C$24,0),1) -> #N/A | H46: =VLOOKUP(A46,'Aux - pivots1'!$A:$B,2,0) -> #N/A | I46: =SUMIFS(Table1[Estimação (horas)],Table1[Tabela],Plano_V1!E46,Table1[Campo],Plano_V1!F46) -> 0 | J46: =I46/8 -> 0 | K46: cd_imv_out_trz_cred_prc | L46: =J46-SUM(M46:FK46) -> 0
A47: =E47&F47 -> cd_imv_out_prccod_estd_prcs | B47: Pilar III | C47: Bens Imóveis - Output | D47: 2. Campo | E47: cd_imv_out_prc | F47: cod_estd_prcs | G47: =INDEX(Auxiliar!$B$16:$B$24,MATCH(Plano_V1!H47,Auxiliar!$C$16:$C$24,0),1) -> #N/A | H47: =VLOOKUP(A47,'Aux - pivots1'!$A:$B,2,0) -> #N/A | I47: 0 | J47: =I47/8 -> 0 | K47: cd_imv_out_trz_cred_prc | L47: =J47-SUM(M47:FK47) -> 0
A48: =E48&F48 -> cd_imv_out_prccod_grt | B48: Pilar III | C48: Bens Imóveis - Output | D48: 2. Campo | E48: cd_imv_out_prc | F48: cod_grt | G48: =INDEX(Auxiliar!$B$16:$B$24,MATCH(Plano_V1!H48,Auxiliar!$C$16:$C$24,0),1) -> #N/A | H48: =VLOOKUP(A48,'Aux - pivots1'!$A:$B,2,0) -> #N/A | I48: =SUMIFS(Table1[Estimação (horas)],Table1[Tabela],Plano_V1!E48,Table1[Campo],Plano_V1!F48) -> 0 | J48: =I48/8 -> 0 | K48: cd_imv_out_trz_cred_prc | L48: =J48-SUM(M48:FK48) -> 0
A49: =E49&F49 -> cd_imv_out_prccod_moeda | B49: Pilar III | C49: Bens Imóveis - Output | D49: 2. Campo | E49: cd_imv_out_prc | F49: cod_moeda | G49: =INDEX(Auxiliar!$B$16:$B$24,MATCH(Plano_V1!H49,Auxiliar!$C$16:$C$24,0),1) -> #N/A | H49: =VLOOKUP(A49,'Aux - pivots1'!$A:$B,2,0) -> #N/A | I49: =SUMIFS(Table1[Estimação (horas)],Table1[Tabela],Plano_V1!E49,Table1[Campo],Plano_V1!F49) -> 0 | J49: =I49/8 -> 0 | K49: cd_imv_out_trz_cred_prc | L49: =J49-SUM(M49:FK49) -> 0
A50: =E50&F50 -> cd_imv_out_prccod_observacao | B50: Pilar III | C50: Bens Imóveis - Output | D50: 2. Campo | E50: cd_imv_out_prc | F50: cod_observacao | G50: =INDEX(Auxiliar!$B$16:$B$24,MATCH(Plano_V1!H50,Auxiliar!$C$16:$C$24,0),1) -> #N/A | H50: =VLOOKUP(A50,'Aux - pivots1'!$A:$B,2,0) -> #N/A | I50: =SUMIFS(Table1[Estimação (horas)],Table1[Tabela],Plano_V1!E50,Table1[Campo],Plano_V1!F50) -> 0 | J50: =I50/8 -> 0 | K50: cd_imv_out_trz_cred_prc | L50: =J50-SUM(M50:FK50) -> 0
A51: =E51&F51 -> cd_imv_out_prccod_prd_grnt | B51: Pilar III | C51: Bens Imóveis - Output | D51: 2. Campo | E51: cd_imv_out_prc | F51: cod_prd_grnt | G51: =INDEX(Auxiliar!$B$16:$B$24,MATCH(Plano_V1!H51,Auxiliar!$C$16:$C$24,0),1) -> #N/A | H51: =VLOOKUP(A51,'Aux - pivots1'!$A:$B,2,0) -> #N/A | I51: =SUMIFS(Table1[Estimação (horas)],Table1[Tabela],Plano_V1!E51,Table1[Campo],Plano_V1!F51) -> 0 | J51: =I51/8 -> 0 | K51: cd_imv_out_trz_cred_prc | L51: =J51-SUM(M51:FK51) -> 0
A52: =E52&F52 -> cd_imv_out_prccod_sprd_grnt | B52: Pilar III | C52: Bens Imóveis - Output | D52: 2. Campo | E52: cd_imv_out_prc | F52: cod_sprd_grnt | G52: =INDEX(Auxiliar!$B$16:$B$24,MATCH(Plano_V1!H52,Auxiliar!$C$16:$C$24,0),1) -> #N/A | H52: =VLOOKUP(A52,'Aux - pivots1'!$A:$B,2,0) -> #N/A | I52: =SUMIFS(Table1[Estimação (horas)],Table1[Tabela],Plano_V1!E52,Table1[Campo],Plano_V1!F52) -> 0 | J52: =I52/8 -> 0 | K52: cd_imv_out_trz_cred_prc | L52: =J52-SUM(M52:FK52) -> 0
A53: =E53&F53 -> cd_imv_out_prccod_tipo | B53: Pilar III | C53: Bens Imóveis - Output | D53: 2. Campo | E53: cd_imv_out_prc | F53: cod_tipo | G53: =INDEX(Auxiliar!$B$16:$B$24,MATCH(Plano_V1!H53,Auxiliar!$C$16:$C$24,0),1) -> #N/A | H53: =VLOOKUP(A53,'Aux - pivots1'!$A:$B,2,0) -> #N/A | I53: =SUMIFS(Table1[Estimação (horas)],Table1[Tabela],Plano_V1!E53,Table1[Campo],Plano_V1!F53) -> 0 | J53: =I53/8 -> 0 | K53: cd_imv_out_trz_cred_prc | L53: =J53-SUM(M53:FK53) -> 0
A54: =E54&F54 -> cd_imv_out_prccomp_id_gar | B54: Pilar III | C54: Bens Imóveis - Output | D54: 2. Campo | E54: cd_imv_out_prc | F54: comp_id_gar | G54: =INDEX(Auxiliar!$B$16:$B$24,MATCH(Plano_V1!H54,Auxiliar!$C$16:$C$24,0),1) -> #N/A | H54: =VLOOKUP(A54,'Aux - pivots1'!$A:$B,2,0) -> #N/A | I54: =SUMIFS(Table1[Estimação (horas)],Table1[Tabela],Plano_V1!E54,Table1[Campo],Plano_V1!F54) -> 0 | J54: =I54/8 -> 0 | K54: cd_imv_out_trz_cred_prc | L54: =J54-SUM(M54:FK54) -> 0
A55: =E55&F55 -> cd_imv_out_prcdata_inicio | B55: Pilar III | C55: Bens Imóveis - Output | D55: 2. Campo | E55: cd_imv_out_prc | F55: data_inicio | G55: =INDEX(Auxiliar!$B$16:$B$24,MATCH(Plano_V1!H55,Auxiliar!$C$16:$C$24,0),1) -> #N/A | H55: =VLOOKUP(A55,'Aux - pivots1'!$A:$B,2,0) -> #N/A | I55: =SUMIFS(Table1[Estimação (horas)],Table1[Tabela],Plano_V1!E55,Table1[Campo],Plano_V1!F55) -> 0 | J55: =I55/8 -> 0 | K55: cd_imv_out_trz_cred_prc | L55: =J55-SUM(M55:FK55) -> 0
A56: =E56&F56 -> cd_imv_out_prcdata_vcmt | B56: Pilar III | C56: Bens Imóveis - Output | D56: 2. Campo | E56: cd_imv_out_prc | F56: data_vcmt | G56: =INDEX(Auxiliar!$B$16:$B$24,MATCH(Plano_V1!H56,Auxiliar!$C$16:$C$24,0),1) -> #N/A | H56: =VLOOKUP(A56,'Aux - pivots1'!$A:$B,2,0) -> #N/A | I56: =SUMIFS(Table1[Estimação (horas)],Table1[Tabela],Plano_V1!E56,Table1[Campo],Plano_V1!F56) -> 0 | J56: =I56/8 -> 0 | K56: cd_imv_out_trz_cred_prc | L56: =J56-SUM(M56:FK56) -> 0
A57: =E57&F57 -> cd_imv_out_prcmontante_eur | B57: Pilar III | C57: Bens Imóveis - Output | D57: 2. Campo | E57: cd_imv_out_prc | F57: montante_eur | G57: =INDEX(Auxiliar!$B$16:$B$24,MATCH(Plano_V1!H57,Auxiliar!$C$16:$C$24,0),1) -> #N/A | H57: =VLOOKUP(A57,'Aux - pivots1'!$A:$B,2,0) -> #N/A | I57: 0 | J57: =I57/8 -> 0 | K57: cd_imv_out_trz_cred_prc | L57: =J57-SUM(M57:FK57) -> 0
A58: =E58&F58 -> cd_imv_out_prcmontante_org | B58: Pilar III | C58: Bens Imóveis - Output | D58: 2. Campo | E58: cd_imv_out_prc | F58: montante_org | G58: =INDEX(Auxiliar!$B$16:$B$24,MATCH(Plano_V1!H58,Auxiliar!$C$16:$C$24,0),1) -> #N/A | H58: =VLOOKUP(A58,'Aux - pivots1'!$A:$B,2,0) -> #N/A | I58: 0 | J58: =I58/8 -> 0 | K58: cd_imv_out_trz_cred_prc | L58: =J58-SUM(M58:FK58) -> 0
A59: =E59&F59 -> cd_imv_out_prcorigem | B59: Pilar III | C59: Bens Imóveis - Output | D59: 2. Campo | E59: cd_imv_out_prc | F59: origem | G59: =INDEX(Auxiliar!$B$16:$B$24,MATCH(Plano_V1!H59,Auxiliar!$C$16:$C$24,0),1) -> #N/A | H59: =VLOOKUP(A59,'Aux - pivots1'!$A:$B,2,0) -> #N/A | I59: =SUMIFS(Table1[Estimação (horas)],Table1[Tabela],Plano_V1!E59,Table1[Campo],Plano_V1!F59) -> 0 | J59: =I59/8 -> 0 | K59: cd_imv_out_trz_cred_prc | L59: =J59-SUM(M59:FK59) -> 0
A60: =E60&F60 -> cd_imv_out_prcref_date | B60: Pilar III | C60: Bens Imóveis - Output | D60: 2. Campo | E60: cd_imv_out_prc | F60: ref_date | G60: =INDEX(Auxiliar!$B$16:$B$24,MATCH(Plano_V1!H60,Auxiliar!$C$16:$C$24,0),1) -> #N/A | H60: =VLOOKUP(A60,'Aux - pivots1'!$A:$B,2,0) -> #N/A | I60: =SUMIFS(Table1[Estimação (horas)],Table1[Tabela],Plano_V1!E60,Table1[Campo],Plano_V1!F60) -> 0 | J60: =I60/8 -> 0 | K60: cd_imv_out_trz_cred_prc | L60: =J60-SUM(M60:FK60) -> 0
A61: =E61&F61 -> cd_imv_out_trz_cred_prcn.a. | B61: Pilar III | C61: Bens Imóveis - Output | D61: 1. Universo | E61: cd_imv_out_trz_cred_prc | F61: n.a. | G61: =INDEX(Auxiliar!$B$16:$B$24,MATCH(Plano_V1!H61,Auxiliar!$C$16:$C$24,0),1) -> #N/A | H61: =VLOOKUP(A61,'Aux - pivots1'!$A:$B,2,0) -> #N/A | I61: =SUMIFS(Table1[Estimação (horas)],Table1[Tabela],Plano_V1!E61,Table1[Campo],Plano_V1!F61) -> 0 | J61: =I61/8 -> 0 | K61: sem pendencia | L61: =J61-SUM(M61:FK61) -> 0
A62: =E62&F62 -> cd_imv_out_trz_cred_prccempresa | B62: Pilar III | C62: Bens Imóveis - Output | D62: 2. Campo | E62: cd_imv_out_trz_cred_prc | F62: cempresa | G62: =INDEX(Auxiliar!$B$16:$B$24,MATCH(Plano_V1!H62,Auxiliar!$C$16:$C$24,0),1) -> #N/A | H62: =VLOOKUP(A62,'Aux - pivots1'!$A:$B,2,0) -> #N/A | I62: =SUMIFS(Table1[Estimação (horas)],Table1[Tabela],Plano_V1!E62,Table1[Campo],Plano_V1!F62) -> 0 | J62: =I62/8 -> 0 | K62: sem pendencia | L62: =J62-SUM(M62:FK62) -> 0
A63: =E63&F63 -> cd_imv_out_trz_cred_prccempresp | B63: Pilar III | C63: Bens Imóveis - Output | D63: 2. Campo | E63: cd_imv_out_trz_cred_prc | F63: cempresp | G63: =INDEX(Auxiliar!$B$16:$B$24,MATCH(Plano_V1!H63,Auxiliar!$C$16:$C$24,0),1) -> #N/A | H63: =VLOOKUP(A63,'Aux - pivots1'!$A:$B,2,0) -> #N/A | I63: =SUMIFS(Table1[Estimação (horas)],Table1[Tabela],Plano_V1!E63,Table1[Campo],Plano_V1!F63) -> 0 | J63: =I63/8 -> 0 | K63: sem pendencia | L63: =J63-SUM(M63:FK63) -> 0
A64: =E64&F64 -> cd_imv_out_trz_cred_prcckbalcao | B64: Pilar III | C64: Bens Imóveis - Output | D64: 2. Campo | E64: cd_imv_out_trz_cred_prc | F64: ckbalcao | G64: =INDEX(Auxiliar!$B$16:$B$24,MATCH(Plano_V1!H64,Auxiliar!$C$16:$C$24,0),1) -> #N/A | H64: =VLOOKUP(A64,'Aux - pivots1'!$A:$B,2,0) -> #N/A | I64: =SUMIFS(Table1[Estimação (horas)],Table1[Tabela],Plano_V1!E64,Table1[Campo],Plano_V1!F64) -> 0 | J64: =I64/8 -> 0 | K64: sem pendencia | L64: =J64-SUM(M64:FK64) -> 0
A65: =E65&F65 -> cd_imv_out_trz_cred_prcckbalres | B65: Pilar III | C65: Bens Imóveis - Output | D65: 2. Campo | E65: cd_imv_out_trz_cred_prc | F65: ckbalres | G65: =INDEX(Auxiliar!$B$16:$B$24,MATCH(Plano_V1!H65,Auxiliar!$C$16:$C$24,0),1) -> #N/A | H65: =VLOOKUP(A65,'Aux - pivots1'!$A:$B,2,0) -> #N/A | I65: =SUMIFS(Table1[Estimação (horas)],Table1[Tabela],Plano_V1!E65,Table1[Campo],Plano_V1!F65) -> 0 | J65: =I65/8 -> 0 | K65: sem pendencia | L65: =J65-SUM(M65:FK65) -> 0
A66: =E66&F66 -> cd_imv_out_trz_cred_prcckctares | B66: Pilar III | C66: Bens Imóveis - Output | D66: 2. Campo | E66: cd_imv_out_trz_cred_prc | F66: ckctares | G66: =INDEX(Auxiliar!$B$16:$B$24,MATCH(Plano_V1!H66,Auxiliar!$C$16:$C$24,0),1) -> #N/A | H66: =VLOOKUP(A66,'Aux - pivots1'!$A:$B,2,0) -> #N/A | I66: =SUMIFS(Table1[Estimação (horas)],Table1[Tabela],Plano_V1!E66,Table1[Campo],Plano_V1!F66) -> 0 | J66: =I66/8 -> 0 | K66: sem pendencia | L66: =J66-SUM(M66:FK66) -> 0
A67: =E67&F67 -> cd_imv_out_trz_cred_prccknumcta | B67: Pilar III | C67: Bens Imóveis - Output | D67: 2. Campo | E67: cd_imv_out_trz_cred_prc | F67: cknumcta | G67: =INDEX(Auxiliar!$B$16:$B$24,MATCH(Plano_V1!H67,Auxiliar!$C$16:$C$24,0),1) -> #N/A | H67: =VLOOKUP(A67,'Aux - pivots1'!$A:$B,2,0) -> #N/A | I67: =SUMIFS(Table1[Estimação (horas)],Table1[Tabela],Plano_V1!E67,Table1[Campo],Plano_V1!F67) -> 0 | J67: =I67/8 -> 0 | K67: sem pendencia | L67: =J67-SUM(M67:FK67) -> 0
A68: =E68&F68 -> cd_imv_out_trz_cred_prcckrefresp | B68: Pilar III | C68: Bens Imóveis - Output | D68: 2. Campo | E68: cd_imv_out_trz_cred_prc | F68: ckrefresp | G68: =INDEX(Auxiliar!$B$16:$B$24,MATCH(Plano_V1!H68,Auxiliar!$C$16:$C$24,0),1) -> #N/A | H68: =VLOOKUP(A68,'Aux - pivots1'!$A:$B,2,0) -> #N/A | I68: =SUMIFS(Table1[Estimação (horas)],Table1[Tabela],Plano_V1!E68,Table1[Campo],Plano_V1!F68) -> 0 | J68: =I68/8 -> 0 | K68: sem pendencia | L68: =J68-SUM(M68:FK68) -> 0
A69: =E69&F69 -> cd_imv_out_trz_cred_prccod_fnld | B69: Pilar III | C69: Bens Imóveis - Output | D69: 2. Campo | E69: cd_imv_out_trz_cred_prc | F69: cod_fnld | G69: =INDEX(Auxiliar!$B$16:$B$24,MATCH(Plano_V1!H69,Auxiliar!$C$16:$C$24,0),1) -> #N/A | H69: =VLOOKUP(A69,'Aux - pivots1'!$A:$B,2,0) -> #N/A | I69: =SUMIFS(Table1[Estimação (horas)],Table1[Tabela],Plano_V1!E69,Table1[Campo],Plano_V1!F69) -> 0 | J69: =I69/8 -> 0 | K69: sem pendencia | L69: =J69-SUM(M69:FK69) -> 0
A70: =E70&F70 -> cd_imv_out_trz_cred_prccod_ocupacao | B70: Pilar III | C70: Bens Imóveis - Output | D70: 2. Campo | E70: cd_imv_out_trz_cred_prc | F70: cod_ocupacao | G70: =INDEX(Auxiliar!$B$16:$B$24,MATCH(Plano_V1!H70,Auxiliar!$C$16:$C$24,0),1) -> #N/A | H70: =VLOOKUP(A70,'Aux - pivots1'!$A:$B,2,0) -> #N/A | I70: =SUMIFS(Table1[Estimação (horas)],Table1[Tabela],Plano_V1!E70,Table1[Campo],Plano_V1!F70) -> 0 | J70: =I70/8 -> 0 | K70: sem pendencia | L70: =J70-SUM(M70:FK70) -> 0
A71: =E71&F71 -> cd_imv_out_trz_cred_prccod_prd_resp | B71: Pilar III | C71: Bens Imóveis - Output | D71: 2. Campo | E71: cd_imv_out_trz_cred_prc | F71: cod_prd_resp | G71: =INDEX(Auxiliar!$B$16:$B$24,MATCH(Plano_V1!H71,Auxiliar!$C$16:$C$24,0),1) -> #N/A | H71: =VLOOKUP(A71,'Aux - pivots1'!$A:$B,2,0) -> #N/A | I71: =SUMIFS(Table1[Estimação (horas)],Table1[Tabela],Plano_V1!E71,Table1[Campo],Plano_V1!F71) -> 0 | J71: =I71/8 -> 0 | K71: sem pendencia | L71: =J71-SUM(M71:FK71) -> 0
A72: =E72&F72 -> cd_imv_out_trz_cred_prccod_sit | B72: Pilar III | C72: Bens Imóveis - Output | D72: 2. Campo | E72: cd_imv_out_trz_cred_prc | F72: cod_sit | G72: =INDEX(Auxiliar!$B$16:$B$24,MATCH(Plano_V1!H72,Auxiliar!$C$16:$C$24,0),1) -> #N/A | H72: =VLOOKUP(A72,'Aux - pivots1'!$A:$B,2,0) -> #N/A | I72: 0 | J72: =I72/8 -> 0 | K72: sem pendencia | L72: =J72-SUM(M72:FK72) -> 0
A73: =E73&F73 -> cd_imv_out_trz_cred_prccod_sprd_resp | B73: Pilar III | C73: Bens Imóveis - Output | D73: 2. Campo | E73: cd_imv_out_trz_cred_prc | F73: cod_sprd_resp | G73: =INDEX(Auxiliar!$B$16:$B$24,MATCH(Plano_V1!H73,Auxiliar!$C$16:$C$24,0),1) -> #N/A | H73: =VLOOKUP(A73,'Aux - pivots1'!$A:$B,2,0) -> #N/A | I73: =SUMIFS(Table1[Estimação (horas)],Table1[Tabela],Plano_V1!E73,Table1[Campo],Plano_V1!F73) -> 0 | J73: =I73/8 -> 0 | K73: sem pendencia | L73: =J73-SUM(M73:FK73) -> 0
A74: =E74&F74 -> cd_imv_out_trz_cred_prccomp_id_gar | B74: Pilar III | C74: Bens Imóveis - Output | D74: 2. Campo | E74: cd_imv_out_trz_cred_prc | F74: comp_id_gar | G74: =INDEX(Auxiliar!$B$16:$B$24,MATCH(Plano_V1!H74,Auxiliar!$C$16:$C$24,0),1) -> #N/A | H74: =VLOOKUP(A74,'Aux - pivots1'!$A:$B,2,0) -> #N/A | I74: =SUMIFS(Table1[Estimação (horas)],Table1[Tabela],Plano_V1!E74,Table1[Campo],Plano_V1!F74) -> 0 | J74: =I74/8 -> 0 | K74: sem pendencia | L74: =J74-SUM(M74:FK74) -> 0
A75: =E75&F75 -> cd_imv_out_trz_cred_prcdata_fim | B75: Pilar III | C75: Bens Imóveis - Output | D75: 2. Campo | E75: cd_imv_out_trz_cred_prc | F75: data_fim | G75: =INDEX(Auxiliar!$B$16:$B$24,MATCH(Plano_V1!H75,Auxiliar!$C$16:$C$24,0),1) -> #N/A | H75: =VLOOKUP(A75,'Aux - pivots1'!$A:$B,2,0) -> #N/A | I75: =SUMIFS(Table1[Estimação (horas)],Table1[Tabela],Plano_V1!E75,Table1[Campo],Plano_V1!F75) -> 0 | J75: =I75/8 -> 0 | K75: sem pendencia | L75: =J75-SUM(M75:FK75) -> 0
A76: =E76&F76 -> cd_imv_out_trz_cred_prcdata_inicio | B76: Pilar III | C76: Bens Imóveis - Output | D76: 2. Campo | E76: cd_imv_out_trz_cred_prc | F76: data_inicio | G76: =INDEX(Auxiliar!$B$16:$B$24,MATCH(Plano_V1!H76,Auxiliar!$C$16:$C$24,0),1) -> #N/A | H76: =VLOOKUP(A76,'Aux - pivots1'!$A:$B,2,0) -> #N/A | I76: =SUMIFS(Table1[Estimação (horas)],Table1[Tabela],Plano_V1!E76,Table1[Campo],Plano_V1!F76) -> 0 | J76: =I76/8 -> 0 | K76: sem pendencia | L76: =J76-SUM(M76:FK76) -> 0
A77: =E77&F77 -> cd_imv_out_trz_cred_prcdata_vcmt | B77: Pilar III | C77: Bens Imóveis - Output | D77: 2. Campo | E77: cd_imv_out_trz_cred_prc | F77: data_vcmt | G77: =INDEX(Auxiliar!$B$16:$B$24,MATCH(Plano_V1!H77,Auxiliar!$C$16:$C$24,0),1) -> #N/A | H77: =VLOOKUP(A77,'Aux - pivots1'!$A:$B,2,0) -> #N/A | I77: =SUMIFS(Table1[Estimação (horas)],Table1[Tabela],Plano_V1!E77,Table1[Campo],Plano_V1!F77) -> 0 | J77: =I77/8 -> 0 | K77: sem pendencia | L77: =J77-SUM(M77:FK77) -> 0
A78: =E78&F78 -> cd_imv_out_trz_cred_prcidetgar | B78: Pilar III | C78: Bens Imóveis - Output | D78: 2. Campo | E78: cd_imv_out_trz_cred_prc | F78: idetgar | G78: =INDEX(Auxiliar!$B$16:$B$24,MATCH(Plano_V1!H78,Auxiliar!$C$16:$C$24,0),1) -> #N/A | H78: =VLOOKUP(A78,'Aux - pivots1'!$A:$B,2,0) -> #N/A | I78: 0 | J78: =I78/8 -> 0 | K78: sem pendencia | L78: =J78-SUM(M78:FK78) -> 0
A79: =E79&F79 -> cd_imv_out_trz_cred_prcnum_prop | B79: Pilar III | C79: Bens Imóveis - Output | D79: 2. Campo | E79: cd_imv_out_trz_cred_prc | F79: num_prop | G79: =INDEX(Auxiliar!$B$16:$B$24,MATCH(Plano_V1!H79,Auxiliar!$C$16:$C$24,0),1) -> #N/A | H79: =VLOOKUP(A79,'Aux - pivots1'!$A:$B,2,0) -> #N/A | I79: 0 | J79: =I79/8 -> 0 | K79: sem pendencia | L79: =J79-SUM(M79:FK79) -> 0
A80: =E80&F80 -> cd_imv_out_trz_cred_prcorigem | B80: Pilar III | C80: Bens Imóveis - Output | D80: 2. Campo | E80: cd_imv_out_trz_cred_prc | F80: origem | G80: =INDEX(Auxiliar!$B$16:$B$24,MATCH(Plano_V1!H80,Auxiliar!$C$16:$C$24,0),1) -> #N/A | H80: =VLOOKUP(A80,'Aux - pivots1'!$A:$B,2,0) -> #N/A | I80: =SUMIFS(Table1[Estimação (horas)],Table1[Tabela],Plano_V1!E80,Table1[Campo],Plano_V1!F80) -> 0 | J80: =I80/8 -> 0 | K80: sem pendencia | L80: =J80-SUM(M80:FK80) -> 0
A81: =E81&F81 -> cd_imv_out_trz_cred_prcref_date | B81: Pilar III | C81: Bens Imóveis - Output | D81: 2. Campo | E81: cd_imv_out_trz_cred_prc | F81: ref_date | G81: =INDEX(Auxiliar!$B$16:$B$24,MATCH(Plano_V1!H81,Auxiliar!$C$16:$C$24,0),1) -> #N/A | H81: =VLOOKUP(A81,'Aux - pivots1'!$A:$B,2,0) -> #N/A | I81: =SUMIFS(Table1[Estimação (horas)],Table1[Tabela],Plano_V1!E81,Table1[Campo],Plano_V1!F81) -> 0 | J81: =I81/8 -> 0 | K81: sem pendencia | L81: =J81-SUM(M81:FK81) -> 0
A82: =E82&F82 -> cd_imv_out_trz_prc_bens_imvn.a. | B82: Pilar III | C82: Bens Imóveis - Output | D82: 1. Universo | E82: cd_imv_out_trz_prc_bens_imv | F82: n.a. | G82: =INDEX(Auxiliar!$B$16:$B$24,MATCH(Plano_V1!H82,Auxiliar!$C$16:$C$24,0),1) -> #N/A | H82: =VLOOKUP(A82,'Aux - pivots1'!$A:$B,2,0) -> #N/A | I82: =SUMIFS(Table1[Estimação (horas)],Table1[Tabela],Plano_V1!E82,Table1[Campo],Plano_V1!F82) -> 0 | J82: =I82/8 -> 0 | K82: cd_imv_out_trz_cred_prc | L82: =J82-SUM(M82:FK82) -> 0
A83: =E83&F83 -> cd_imv_out_trz_prc_bens_imvcempbem | B83: Pilar III | C83: Bens Imóveis - Output | D83: 2. Campo | E83: cd_imv_out_trz_prc_bens_imv | F83: cempbem | G83: =INDEX(Auxiliar!$B$16:$B$24,MATCH(Plano_V1!H83,Auxiliar!$C$16:$C$24,0),1) -> #N/A | H83: =VLOOKUP(A83,'Aux - pivots1'!$A:$B,2,0) -> #N/A | I83: =SUMIFS(Table1[Estimação (horas)],Table1[Tabela],Plano_V1!E83,Table1[Campo],Plano_V1!F83) -> 0 | J83: =I83/8 -> 0 | K83: cd_imv_out_trz_cred_prc | L83: =J83-SUM(M83:FK83) -> 0
A84: =E84&F84 -> cd_imv_out_trz_prc_bens_imvcempresa | B84: Pilar III | C84: Bens Imóveis - Output | D84: 2. Campo | E84: cd_imv_out_trz_prc_bens_imv | F84: cempresa | G84: =INDEX(Auxiliar!$B$16:$B$24,MATCH(Plano_V1!H84,Auxiliar!$C$16:$C$24,0),1) -> #N/A | H84: =VLOOKUP(A84,'Aux - pivots1'!$A:$B,2,0) -> #N/A | I84: =SUMIFS(Table1[Estimação (horas)],Table1[Tabela],Plano_V1!E84,Table1[Campo],Plano_V1!F84) -> 0 | J84: =I84/8 -> 0 | K84: cd_imv_out_trz_cred_prc | L84: =J84-SUM(M84:FK84) -> 0
A85: =E85&F85 -> cd_imv_out_trz_prc_bens_imvckbalbem | B85: Pilar III | C85: Bens Imóveis - Output | D85: 2. Campo | E85: cd_imv_out_trz_prc_bens_imv | F85: ckbalbem | G85: =INDEX(Auxiliar!$B$16:$B$24,MATCH(Plano_V1!H85,Auxiliar!$C$16:$C$24,0),1) -> #N/A | H85: =VLOOKUP(A85,'Aux - pivots1'!$A:$B,2,0) -> #N/A | I85: =SUMIFS(Table1[Estimação (horas)],Table1[Tabela],Plano_V1!E85,Table1[Campo],Plano_V1!F85) -> 0 | J85: =I85/8 -> 0 | K85: cd_imv_out_trz_cred_prc | L85: =J85-SUM(M85:FK85) -> 0
A86: =E86&F86 -> cd_imv_out_trz_prc_bens_imvckbalcao | B86: Pilar III | C86: Bens Imóveis - Output | D86: 2. Campo | E86: cd_imv_out_trz_prc_bens_imv | F86: ckbalcao | G86: =INDEX(Auxiliar!$B$16:$B$24,MATCH(Plano_V1!H86,Auxiliar!$C$16:$C$24,0),1) -> #N/A | H86: =VLOOKUP(A86,'Aux - pivots1'!$A:$B,2,0) -> #N/A | I86: =SUMIFS(Table1[Estimação (horas)],Table1[Tabela],Plano_V1!E86,Table1[Campo],Plano_V1!F86) -> 0 | J86: =I86/8 -> 0 | K86: cd_imv_out_trz_cred_prc | L86: =J86-SUM(M86:FK86) -> 0
A87: =E87&F87 -> cd_imv_out_trz_prc_bens_imvckctabem | B87: Pilar III | C87: Bens Imóveis - Output | D87: 2. Campo | E87: cd_imv_out_trz_prc_bens_imv | F87: ckctabem | G87: =INDEX(Auxiliar!$B$16:$B$24,MATCH(Plano_V1!H87,Auxiliar!$C$16:$C$24,0),1) -> #N/A | H87: =VLOOKUP(A87,'Aux - pivots1'!$A:$B,2,0) -> #N/A | I87: =SUMIFS(Table1[Estimação (horas)],Table1[Tabela],Plano_V1!E87,Table1[Campo],Plano_V1!F87) -> 0 | J87: =I87/8 -> 0 | K87: cd_imv_out_trz_cred_prc | L87: =J87-SUM(M87:FK87) -> 0
A88: =E88&F88 -> cd_imv_out_trz_prc_bens_imvcknumcta | B88: Pilar III | C88: Bens Imóveis - Output | D88: 2. Campo | E88: cd_imv_out_trz_prc_bens_imv | F88: cknumcta | G88: =INDEX(Auxiliar!$B$16:$B$24,MATCH(Plano_V1!H88,Auxiliar!$C$16:$C$24,0),1) -> #N/A | H88: =VLOOKUP(A88,'Aux - pivots1'!$A:$B,2,0) -> #N/A | I88: =SUMIFS(Table1[Estimação (horas)],Table1[Tabela],Plano_V1!E88,Table1[Campo],Plano_V1!F88) -> 0 | J88: =I88/8 -> 0 | K88: cd_imv_out_trz_cred_prc | L88: =J88-SUM(M88:FK88) -> 0
A89: =E89&F89 -> cd_imv_out_trz_prc_bens_imvckrefbem | B89: Pilar III | C89: Bens Imóveis - Output | D89: 2. Campo | E89: cd_imv_out_trz_prc_bens_imv | F89: ckrefbem | G89: =INDEX(Auxiliar!$B$16:$B$24,MATCH(Plano_V1!H89,Auxiliar!$C$16:$C$24,0),1) -> #N/A | H89: =VLOOKUP(A89,'Aux - pivots1'!$A:$B,2,0) -> #N/A | I89: =SUMIFS(Table1[Estimação (horas)],Table1[Tabela],Plano_V1!E89,Table1[Campo],Plano_V1!F89) -> 0 | J89: =I89/8 -> 0 | K89: cd_imv_out_trz_cred_prc | L89: =J89-SUM(M89:FK89) -> 0
A90: =E90&F90 -> cd_imv_out_trz_prc_bens_imvcomp_id_gar | B90: Pilar III | C90: Bens Imóveis - Output | D90: 2. Campo | E90: cd_imv_out_trz_prc_bens_imv | F90: comp_id_gar | G90: =INDEX(Auxiliar!$B$16:$B$24,MATCH(Plano_V1!H90,Auxiliar!$C$16:$C$24,0),1) -> #N/A | H90: =VLOOKUP(A90,'Aux - pivots1'!$A:$B,2,0) -> #N/A | I90: =SUMIFS(Table1[Estimação (horas)],Table1[Tabela],Plano_V1!E90,Table1[Campo],Plano_V1!F90) -> 0 | J90: =I90/8 -> 0 | K90: cd_imv_out_trz_cred_prc | L90: =J90-SUM(M90:FK90) -> 0
A91: =E91&F91 -> cd_imv_out_trz_prc_bens_imvdata_assc | B91: Pilar III | C91: Bens Imóveis - Output | D91: 2. Campo | E91: cd_imv_out_trz_prc_bens_imv | F91: data_assc | G91: =INDEX(Auxiliar!$B$16:$B$24,MATCH(Plano_V1!H91,Auxiliar!$C$16:$C$24,0),1) -> #N/A | H91: =VLOOKUP(A91,'Aux - pivots1'!$A:$B,2,0) -> #N/A | I91: 0 | J91: =I91/8 -> 0 | K91: cd_imv_out_trz_cred_prc | L91: =J91-SUM(M91:FK91) -> 0
A92: =E92&F92 -> cd_imv_out_trz_prc_bens_imvflg_adj | B92: Pilar III | C92: Bens Imóveis - Output | D92: 2. Campo | E92: cd_imv_out_trz_prc_bens_imv | F92: flg_adj | G92: =INDEX(Auxiliar!$B$16:$B$24,MATCH(Plano_V1!H92,Auxiliar!$C$16:$C$24,0),1) -> #N/A | H92: =VLOOKUP(A92,'Aux - pivots1'!$A:$B,2,0) -> #N/A | I92: =SUMIFS(Table1[Estimação (horas)],Table1[Tabela],Plano_V1!E92,Table1[Campo],Plano_V1!F92) -> 0 | J92: =I92/8 -> 0 | K92: cd_imv_out_trz_cred_prc | L92: =J92-SUM(M92:FK92) -> 0
A93: =E93&F93 -> cd_imv_out_trz_prc_bens_imvflg_col | B93: Pilar III | C93: Bens Imóveis - Output | D93: 2. Campo | E93: cd_imv_out_trz_prc_bens_imv | F93: flg_col | G93: =INDEX(Auxiliar!$B$16:$B$24,MATCH(Plano_V1!H93,Auxiliar!$C$16:$C$24,0),1) -> #N/A | H93: =VLOOKUP(A93,'Aux - pivots1'!$A:$B,2,0) -> #N/A | I93: =SUMIFS(Table1[Estimação (horas)],Table1[Tabela],Plano_V1!E93,Table1[Campo],Plano_V1!F93) -> 0 | J93: =I93/8 -> 0 | K93: cd_imv_out_trz_cred_prc | L93: =J93-SUM(M93:FK93) -> 0
A94: =E94&F94 -> cd_imv_out_trz_prc_bens_imvflg_fin | B94: Pilar III | C94: Bens Imóveis - Output | D94: 2. Campo | E94: cd_imv_out_trz_prc_bens_imv | F94: flg_fin | G94: =INDEX(Auxiliar!$B$16:$B$24,MATCH(Plano_V1!H94,Auxiliar!$C$16:$C$24,0),1) -> #N/A | H94: =VLOOKUP(A94,'Aux - pivots1'!$A:$B,2,0) -> #N/A | I94: =SUMIFS(Table1[Estimação (horas)],Table1[Tabela],Plano_V1!E94,Table1[Campo],Plano_V1!F94) -> 0 | J94: =I94/8 -> 0 | K94: cd_imv_out_trz_cred_prc | L94: =J94-SUM(M94:FK94) -> 0
A95: =E95&F95 -> cd_imv_out_trz_prc_bens_imvflg_pro | B95: Pilar III | C95: Bens Imóveis - Output | D95: 2. Campo | E95: cd_imv_out_trz_prc_bens_imv | F95: flg_pro | G95: =INDEX(Auxiliar!$B$16:$B$24,MATCH(Plano_V1!H95,Auxiliar!$C$16:$C$24,0),1) -> #N/A | H95: =VLOOKUP(A95,'Aux - pivots1'!$A:$B,2,0) -> #N/A | I95: =SUMIFS(Table1[Estimação (horas)],Table1[Tabela],Plano_V1!E95,Table1[Campo],Plano_V1!F95) -> 0 | J95: =I95/8 -> 0 | K95: cd_imv_out_trz_cred_prc | L95: =J95-SUM(M95:FK95) -> 0
A96: =E96&F96 -> cd_imv_out_trz_prc_bens_imvorigem | B96: Pilar III | C96: Bens Imóveis - Output | D96: 2. Campo | E96: cd_imv_out_trz_prc_bens_imv | F96: origem | G96: =INDEX(Auxiliar!$B$16:$B$24,MATCH(Plano_V1!H96,Auxiliar!$C$16:$C$24,0),1) -> #N/A | H96: =VLOOKUP(A96,'Aux - pivots1'!$A:$B,2,0) -> #N/A | I96: =SUMIFS(Table1[Estimação (horas)],Table1[Tabela],Plano_V1!E96,Table1[Campo],Plano_V1!F96) -> 0 | J96: =I96/8 -> 0 | K96: cd_imv_out_trz_cred_prc | L96: =J96-SUM(M96:FK96) -> 0
A97: =E97&F97 -> cd_imv_out_trz_prc_bens_imvref_date | B97: Pilar III | C97: Bens Imóveis - Output | D97: 2. Campo | E97: cd_imv_out_trz_prc_bens_imv | F97: ref_date | G97: =INDEX(Auxiliar!$B$16:$B$24,MATCH(Plano_V1!H97,Auxiliar!$C$16:$C$24,0),1) -> #N/A | H97: =VLOOKUP(A97,'Aux - pivots1'!$A:$B,2,0) -> #N/A | I97: =SUMIFS(Table1[Estimação (horas)],Table1[Tabela],Plano_V1!E97,Table1[Campo],Plano_V1!F97) -> 0 | J97: =I97/8 -> 0 | K97: cd_imv_out_trz_cred_prc | L97: =J97-SUM(M97:FK97) -> 0
A98: =E98&F98 -> cd_imv_out_bensn.a. | B98: Pilar III | C98: Bens Imóveis - Output | D98: 1. Universo | E98: cd_imv_out_bens | F98: n.a. | G98: =INDEX(Auxiliar!$B$16:$B$24,MATCH(Plano_V1!H98,Auxiliar!$C$16:$C$24,0),1) -> #N/A | H98: =VLOOKUP(A98,'Aux - pivots1'!$A:$B,2,0) -> #N/A | I98: =SUMIFS(Table1[Estimação (horas)],Table1[Tabela],Plano_V1!E98,Table1[Campo],Plano_V1!F98) -> 0 | J98: =I98/8 -> 0 | K98: cd_imv_out_trz_prc_bens_imv ; cd_imv_out_prc ; cd_imv_out_trz_cred_prc | L98: =J98-SUM(M98:FK98) -> 0
A99: =E99&F99 -> cd_imv_out_bensano_construcao | B99: Pilar III | C99: Bens Imóveis - Output | D99: 2. Campo | E99: cd_imv_out_bens | F99: ano_construcao | G99: =INDEX(Auxiliar!$B$16:$B$24,MATCH(Plano_V1!H99,Auxiliar!$C$16:$C$24,0),1) -> #N/A | H99: =VLOOKUP(A99,'Aux - pivots1'!$A:$B,2,0) -> #N/A | I99: 0 | J99: =I99/8 -> 0 | K99: cd_imv_out_trz_prc_bens_imv ; cd_imv_out_prc ; cd_imv_out_trz_cred_prc | L99: =J99-SUM(M99:FK99) -> 0
A100: =E100&F100 -> cd_imv_out_bensarea_util | B100: Pilar III | C100: Bens Imóveis - Output | D100: 2. Campo | E100: cd_imv_out_bens | F100: area_util | G100: =INDEX(Auxiliar!$B$16:$B$24,MATCH(Plano_V1!H100,Auxiliar!$C$16:$C$24,0),1) -> #N/A | H100: =VLOOKUP(A100,'Aux - pivots1'!$A:$B,2,0) -> #N/A | I100: =SUMIFS(Table1[Estimação (horas)],Table1[Tabela],Plano_V1!E100,Table1[Campo],Plano_V1!F100) -> 0 | J100: =I100/8 -> 0 | K100: cd_imv_out_trz_prc_bens_imv ; cd_imv_out_prc ; cd_imv_out_trz_cred_prc | L100: =J100-SUM(M100:FK100) -> 0
A101: =E101&F101 -> cd_imv_out_benscempbem | B101: Pilar III | C101: Bens Imóveis - Output | D101: 2. Campo | E101: cd_imv_out_bens | F101: cempbem | G101: =INDEX(Auxiliar!$B$16:$B$24,MATCH(Plano_V1!H101,Auxiliar!$C$16:$C$24,0),1) -> #N/A | H101: =VLOOKUP(A101,'Aux - pivots1'!$A:$B,2,0) -> #N/A | I101: =SUMIFS(Table1[Estimação (horas)],Table1[Tabela],Plano_V1!E101,Table1[Campo],Plano_V1!F101) -> 0 | J101: =I101/8 -> 0 | K101: cd_imv_out_trz_prc_bens_imv ; cd_imv_out_prc ; cd_imv_out_trz_cred_prc | L101: =J101-SUM(M101:FK101) -> 0
A102: =E102&F102 -> cd_imv_out_bensckbalbem | B102: Pilar III | C102: Bens Imóveis - Output | D102: 2. Campo | E102: cd_imv_out_bens | F102: ckbalbem | G102: =INDEX(Auxiliar!$B$16:$B$24,MATCH(Plano_V1!H102,Auxiliar!$C$16:$C$24,0),1) -> #N/A | H102: =VLOOKUP(A102,'Aux - pivots1'!$A:$B,2,0) -> #N/A | I102: =SUMIFS(Table1[Estimação (horas)],Table1[Tabela],Plano_V1!E102,Table1[Campo],Plano_V1!F102) -> 0 | J102: =I102/8 -> 0 | K102: cd_imv_out_trz_prc_bens_imv ; cd_imv_out_prc ; cd_imv_out_trz_cred_prc | L102: =J102-SUM(M102:FK102) -> 0
A103: =E103&F103 -> cd_imv_out_bensckctabem | B103: Pilar III | C103: Bens Imóveis - Output | D103: 2. Campo | E103: cd_imv_out_bens | F103: ckctabem | G103: =INDEX(Auxiliar!$B$16:$B$24,MATCH(Plano_V1!H103,Auxiliar!$C$16:$C$24,0),1) -> #N/A | H103: =VLOOKUP(A103,'Aux - pivots1'!$A:$B,2,0) -> #N/A | I103: =SUMIFS(Table1[Estimação (horas)],Table1[Tabela],Plano_V1!E103,Table1[Campo],Plano_V1!F103) -> 0 | J103: =I103/8 -> 0 | K103: cd_imv_out_trz_prc_bens_imv ; cd_imv_out_prc ; cd_imv_out_trz_cred_prc | L103: =J103-SUM(M103:FK103) -> 0
A104: =E104&F104 -> cd_imv_out_bensckrefbem | B104: Pilar III | C104: Bens Imóveis - Output | D104: 2. Campo | E104: cd_imv_out_bens | F104: ckrefbem | G104: =INDEX(Auxiliar!$B$16:$B$24,MATCH(Plano_V1!H104,Auxiliar!$C$16:$C$24,0),1) -> #N/A | H104: =VLOOKUP(A104,'Aux - pivots1'!$A:$B,2,0) -> #N/A | I104: =SUMIFS(Table1[Estimação (horas)],Table1[Tabela],Plano_V1!E104,Table1[Campo],Plano_V1!F104) -> 0 | J104: =I104/8 -> 0 | K104: cd_imv_out_trz_prc_bens_imv ; cd_imv_out_prc ; cd_imv_out_trz_cred_prc | L104: =J104-SUM(M104:FK104) -> 0
A105: =E105&F105 -> cd_imv_out_benscod_art_matr | B105: Pilar III | C105: Bens Imóveis - Output | D105: 2. Campo | E105: cd_imv_out_bens | F105: cod_art_matr | G105: =INDEX(Auxiliar!$B$16:$B$24,MATCH(Plano_V1!H105,Auxiliar!$C$16:$C$24,0),1) -> #N/A | H105: =VLOOKUP(A105,'Aux - pivots1'!$A:$B,2,0) -> #N/A | I105: =SUMIFS(Table1[Estimação (horas)],Table1[Tabela],Plano_V1!E105,Table1[Campo],Plano_V1!F105) -> 0 | J105: =I105/8 -> 0 | K105: cd_imv_out_trz_prc_bens_imv ; cd_imv_out_prc ; cd_imv_out_trz_cred_prc | L105: =J105-SUM(M105:FK105) -> 0
A106: =E106&F106 -> cd_imv_out_benscod_avl | B106: Pilar III | C106: Bens Imóveis - Output | D106: 2. Campo | E106: cd_imv_out_bens | F106: cod_avl | G106: =INDEX(Auxiliar!$B$16:$B$24,MATCH(Plano_V1!H106,Auxiliar!$C$16:$C$24,0),1) -> #N/A | H106: =VLOOKUP(A106,'Aux - pivots1'!$A:$B,2,0) -> #N/A | I106: =SUMIFS(Table1[Estimação (horas)],Table1[Tabela],Plano_V1!E106,Table1[Campo],Plano_V1!F106) -> 0 | J106: =I106/8 -> 0 | K106: cd_imv_out_trz_prc_bens_imv ; cd_imv_out_prc ; cd_imv_out_trz_cred_prc | L106: =J106-SUM(M106:FK106) -> 0
A107: =E107&F107 -> cd_imv_out_benscod_bem | B107: Pilar III | C107: Bens Imóveis - Output | D107: 2. Campo | E107: cd_imv_out_bens | F107: cod_bem | G107: =INDEX(Auxiliar!$B$16:$B$24,MATCH(Plano_V1!H107,Auxiliar!$C$16:$C$24,0),1) -> #N/A | H107: =VLOOKUP(A107,'Aux - pivots1'!$A:$B,2,0) -> #N/A | I107: 0 | J107: =I107/8 -> 0 | K107: cd_imv_out_trz_prc_bens_imv ; cd_imv_out_prc ; cd_imv_out_trz_cred_prc | L107: =J107-SUM(M107:FK107) -> 0
A108: =E108&F108 -> cd_imv_out_benscod_disconf | B108: Pilar III | C108: Bens Imóveis - Output | D108: 2. Campo | E108: cd_imv_out_bens | F108: cod_disconf | G108: =INDEX(Auxiliar!$B$16:$B$24,MATCH(Plano_V1!H108,Auxiliar!$C$16:$C$24,0),1) -> #N/A | H108: =VLOOKUP(A108,'Aux - pivots1'!$A:$B,2,0) -> #N/A | I108: =SUMIFS(Table1[Estimação (horas)],Table1[Tabela],Plano_V1!E108,Table1[Campo],Plano_V1!F108) -> 0 | J108: =I108/8 -> 0 | K108: cd_imv_out_trz_prc_bens_imv ; cd_imv_out_prc ; cd_imv_out_trz_cred_prc | L108: =J108-SUM(M108:FK108) -> 0
A109: =E109&F109 -> cd_imv_out_benscod_fin_bem | B109: Pilar III | C109: Bens Imóveis - Output | D109: 2. Campo | E109: cd_imv_out_bens | F109: cod_fin_bem | G109: =INDEX(Auxiliar!$B$16:$B$24,MATCH(Plano_V1!H109,Auxiliar!$C$16:$C$24,0),1) -> #N/A | H109: =VLOOKUP(A109,'Aux - pivots1'!$A:$B,2,0) -> #N/A | I109: =SUMIFS(Table1[Estimação (horas)],Table1[Tabela],Plano_V1!E109,Table1[Campo],Plano_V1!F109) -> 0 | J109: =I109/8 -> 0 | K109: cd_imv_out_trz_prc_bens_imv ; cd_imv_out_prc ; cd_imv_out_trz_cred_prc | L109: =J109-SUM(M109:FK109) -> 0
...

Sheet 1. Status Resumo FY24
B6: 1. Sumário Executivo |07 de fevereiro a 14 de fevereiro
B8: 1 | AG8: 1
C9: Resumo de entregas de Especificações | P9: Detalhe Packages planeados | X9: Highlights
E10: 0 | H10: 1 | L10: 5 | X10: Resumo semana atual: 1. Modelo de Bens Imóveis: Conforme planeado, foram tratados e preparados os 6 ficheiros relativos a cada rácio de receção de informação de consumo e eficiência energética da Gloval.Contudo, para testar o front e a tabela de Input será necessário obter os acessos ao mesmo. 2. Modelo Verde: Conforme planeado, foram testados e concluídos sem incidências 20 campos referentes aos rácios dos clientes. 3. Loan Tape: Conforme planeado foram concluídas e partilhas com a equipa de Tecnologia as especificações de 10 campos referentes ao packages 4. Destes 10 campos, 5 são do âmbito estrutural e 5 não são comuns com o âmbito estrutural. Adicionalmente, existem 4 campos com pendências, sendo que: - 1 campo está pendente da validação do mapeamento das viaturas pela área de Leasing - 3 campos estão pendentes da validação da corporação Semana Seguinte: 1. Loan Tape - FY25: Na próxima semana, está previsto fechar a especificação dos campos pendentes do package 4 (4 campos). - FY25: Na próxima semana, está previsto fechar a especificação do package 5 (7 campos). - FY24: Na próxima semana, está previsto fechar a especificação de 2 campos. - Adicionalmente, serão realizados testes regressivos entre os dados em produção e desenvolvimente referente aos âmbitos estrutural e pilar3. 2. Modelo Bens Imóveis - FY24: Testar 4 campos da tabela de certificados relativos aos dados do fornecedor externo Gloval.
C11: Âmbito | E11: Entregas Semana Anterior | H11: Entregas Semana Atual | L11: Entregas Semana Seguinte | Q11: Dt. Prev. | R11: Req. FY25 | T11: Req. FY25 (atualiz.) | V11: Status
E12: Planeado | F12: Real | G12: ∆ | H12: Semana Ant. | I12: Planeado | J12: Real | K12: ∆ | L12: Semana Ant. | M12: Planeado | N12: Total | O12: 1 | P12: Package 1 | Q12: 27/jan | R12: 20 | T12: =+COUNTIFS('2. Status Detalhe Campos FY24'!$C:$C,"*Pilar*",'2. Status Detalhe Campos FY24'!$J:$J,"*"&O12&"*",'2. Status Detalhe Campos FY24'!U:U,"*Novo Plano*") -> 20 | V12: OK
C13: Modelo de Bens Imóveis | E13: 0 | F13: 0 | G13: =E13-F13 -> 0 | H13: 0 | I13: 0 | J13: 0 | K13: =J13-(I13+H13) -> 0 | L13: =+IF(K13<0,-K13,0) -> 0 | M13: =+COUNTIFS('2. Status Detalhe Campos FY24'!$C:$C,"*Bens Imóveis*",'2. Status Detalhe Campos FY24'!$J:$J,"*"&$L$10&"*") -> 0 | N13: =+M13+L13 -> 0 | O13: 2 | P13: Package 2 | Q13: 4/fev | R13: 15 | T13: =+COUNTIFS('2. Status Detalhe Campos FY24'!$C:$C,"*Pilar*",'2. Status Detalhe Campos FY24'!$J:$J,"*"&O13&"*",'2. Status Detalhe Campos FY24'!U:U,"*Novo Plano*") -> 14 | V13: OK
C14: Requisitos FY24 | E14: 0 | F14: 0 | G14: =E14-F14 -> 0 | H14: 0 | I14: 0 | J14: 0 | K14: =J14-(I14+H14) -> 0 | L14: =+IF(K14<0,-K14,0) -> 0 | M14: =+COUNTIFS('2. Status Detalhe Campos FY24'!$C:$C,"*Bens Imóveis*",'2. Status Detalhe Campos FY24'!$J:$J,"*"&$L$10&"*",'2. Status Detalhe Campos FY24'!U:U,"*anterior*") -> 0 | N14: =+M14+L14 -> 0 | O14: 3 | P14: Package 3 | Q14: 5/fev | R14: 14 | T14: =+COUNTIFS('2. Status Detalhe Campos FY24'!$C:$C,"*Pilar*",'2. Status Detalhe Campos FY24'!$J:$J,"*"&O14&"*",'2. Status Detalhe Campos FY24'!U:U,"*Novo Plano*") -> 16 | V14: OK
C15: Novos Requisitos FY25 | E15: 0 | F15: 0 | G15: =E15-F15 -> 0 | H15: 0 | I15: 0 | J15: 0 | K15: =J15-(I15+H15) -> 0 | L15: =+IF(K15<0,-K15,0) -> 0 | M15: =+COUNTIFS('2. Status Detalhe Campos FY24'!$C:$C,"*Bens Imóveis*",'2. Status Detalhe Campos FY24'!$J:$J,"*"&$L$10&"*",'2. Status Detalhe Campos FY24'!U:U,"*Novo Plano*") -> 0 | N15: =+M15+L15 -> 0 | O15: 4 | P15: Package 4 | Q15: 11/fev | R15: 13 | T15: =+COUNTIFS('2. Status Detalhe Campos FY24'!$C:$C,"*Pilar*",'2. Status Detalhe Campos FY24'!$J:$J,"*"&O15&"*",'2. Status Detalhe Campos FY24'!U:U,"*Novo Plano*") -> 14 | V15: OK (11 campos)
C16: Modelo Verde | E16: 0 | F16: 0 | G16: =E16-F16 -> 0 | H16: 0 | I16: 0 | J16: 0 | K16: =J16-(I16+H16) -> 0 | L16: =+IF(K16<0,-K16,0) -> 0 | M16: =+COUNTIFS('2. Status Detalhe Campos FY24'!$C:$C,"*Verde*",'2. Status Detalhe Campos FY24'!$J:$J,"*"&$L$10&"*") -> 0 | N16: =+M16+L16 -> 0 | O16: 5 | P16: Package 5 | Q16: 17/fev | R16: 6 | T16: =+COUNTIFS('2. Status Detalhe Campos FY24'!$C:$C,"*Pilar*",'2. Status Detalhe Campos FY24'!$J:$J,"*"&O16&"*",'2. Status Detalhe Campos FY24'!U:U,"*Novo Plano*") -> 7 | V16: OK (6 campos)
C17: Requisitos FY24 | E17: 0 | F17: 0 | G17: =E17-F17 -> 0 | H17: 0 | I17: 0 | J17: 0 | K17: =J17-(I17+H17) -> 0 | L17: =+IF(K17<0,-K17,0) -> 0 | M17: =+COUNTIFS('2. Status Detalhe Campos FY24'!$C:$C,"*Verde*",'2. Status Detalhe Campos FY24'!$J:$J,"*"&$L$10&"*",'2. Status Detalhe Campos FY24'!U:U,"*anterior*") -> 0 | N17: =+M17+L17 -> 0 | P17: Total | R17: =+SUM(R12:S16) -> 68 | T17: =+SUM(T12:T16) -> 71
C18: Novos Requisitos FY25 | E18: 0 | F18: 0 | G18: =E18-F18 -> 0 | H18: 0 | I18: 0 | J18: 0 | K18: =J18-(I18+H18) -> 0 | L18: =+IF(K18<0,-K18,0) -> 0 | M18: =+COUNTIFS('2. Status Detalhe Campos FY24'!$C:$C,"*Verde*",'2. Status Detalhe Campos FY24'!$J:$J,"*"&$L$10&"*",'2. Status Detalhe Campos FY24'!U:U,"*Novo Plano*") -> 0 | N18: =+M18+L18 -> 0
C19: Loan Tape | E19: 14 | F19: 10 | G19: =E19-F19 -> 4 | H19: 4 | I19: 9 | J19: 8 | K19: =J19-(I19+H19) -> -5 | L19: =+IF(K19<0,-K19,0) -> 5 | M19: 3 | N19: =+M19+L19 -> 8
C20: Requisitos FY24 | E20: 0 | F20: 0 | G20: =E20-F20 -> 0 | H20: 0 | I20: 2 | J20: 1 | K20: =J20-(I20+H20) -> -1 | L20: =+IF(K20<0,-K20,0) -> 1 | M20: 3 | N20: =+M20+L20 -> 4
C21: Novos Requisitos FY25 | E21: 14 | F21: 10 | G21: =E21-F21 -> 4 | H21: 4 | I21: 7 | J21: 7 | K21: =J21-(I21+H21) -> -4 | L21: =+IF(K21<0,-K21,0) -> 4 | M21: 0 | N21: =+M21+L21 -> 4
C22: Total | E22: 14 | F22: 10 | G22: =E22-F22 -> 4 | H22: 4 | I22: 9 | J22: 8 | K22: =J22-(I22+H22) -> -5 | L22: =+SUM(L13,L16,L19) -> 5 | M22: =+SUM(M13,M16,M19) -> 3 | N22: =+SUM(N13,N16,N19) -> 8
C24: Resumo de Testes
E25: 1 | I25: 1 | P25: 4
C26: Âmbito | E26: Semana Anterior | J26: Semana Atual | P26: Semana Seguinte
E27: Planeado | F27: Com Incidên. | G27: Sem Incidên. | H27: Re- Especif. | I27: ∆ | J27: Semana Ant. | K27: Planeado | L27: Com Incidên. | M27: Sem Incidên. | N27: Re- Especif. | O27: ∆ | P27: Semana Ant. | Q27: Planeado | R27: Total
C28: Modelo de Bens Imóveis | E28: 0 | F28: 0 | G28: 0 | H28: 0 | I28: 0 | J28: 0 | K28: 4 | L28: 0 | M28: 0 | N28: 0 | O28: =+SUM(J28:K28)-SUM(L28:N28) -> 4 | P28: 4 | Q28: =+COUNTIFS('2. Status Detalhe Campos FY24'!$C:$C,"*Bens Imóveis*",'2. Status Detalhe Campos FY24'!$K:$K,"*"&$P$25&"*") -> 44 | R28: =+Q28+P28 -> 48
C29: RequisItos FY24 | E29: 0 | F29: 0 | G29: 0 | H29: 0 | I29: 0 | J29: 0 | K29: 4 | L29: 0 | M29: 0 | N29: 0 | O29: =+SUM(J29:K29)-SUM(L29:N29) -> 4 | P29: 4 | Q29: =+COUNTIFS('2. Status Detalhe Campos FY24'!$C:$C,"*Bens Imóveis*",'2. Status Detalhe Campos FY24'!$K:$K,"*"&$P$25&"*",'2. Status Detalhe Campos FY24'!U:U,"*anterior*") -> 44 | R29: =+Q29+P29 -> 48
C30: Novos Requisitos FY25 | E30: 0 | F30: 0 | G30: 0 | H30: 0 | I30: 0 | J30: 0 | K30: 0 | L30: 0 | M30: 0 | N30: 0 | O30: =+SUM(J30:K30)-SUM(L30:N30) -> 0 | P30: 0 | Q30: =+COUNTIFS('2. Status Detalhe Campos FY24'!$C:$C,"*Bens Imóveis*",'2. Status Detalhe Campos FY24'!$K:$K,"*"&$P$25&"*",'2. Status Detalhe Campos FY24'!U:U,"*Novo Plano*") -> 0 | R30: =+Q30+P30 -> 0
C31: Modelo Verde | E31: 20 | F31: 0 | G31: 20 | H31: 0 | I31: 0 | J31: 0 | K31: 0 | L31: 0 | M31: 0 | N31: 0 | O31: =+SUM(J31:K31)-SUM(L31:N31) -> 0 | P31: 0 | Q31: =+COUNTIFS('2. Status Detalhe Campos FY24'!$C:$C,"*Verde*",'2. Status Detalhe Campos FY24'!$K:$K,"*"&$P$25&"*") -> 0 | R31: =+Q31+P31 -> 0
C32: RequisItos FY24 | E32: 0 | F32: 0 | G32: 0 | H32: 0 | I32: 0 | J32: 0 | K32: 0 | L32: 0 | M32: 0 | N32: 0 | O32: =+SUM(J32:K32)-SUM(L32:N32) -> 0 | P32: 0 | Q32: =+COUNTIFS('2. Status Detalhe Campos FY24'!$C:$C,"*Verde*",'2. Status Detalhe Campos FY24'!$K:$K,"*"&$P$25&"*",'2. Status Detalhe Campos FY24'!U:U,"*anterior*") -> 0 | R32: =+Q32+P32 -> 0
C33: Novos Requisitos FY25 | E33: 20 | F33: 0 | G33: 20 | H33: 0 | I33: 0 | J33: 0 | K33: 0 | L33: 0 | M33: 0 | N33: 0 | O33: =+SUM(J33:K33)-SUM(L33:N33) -> 0 | P33: 0 | Q33: =+COUNTIFS('2. Status Detalhe Campos FY24'!$C:$C,"*Verde*",'2. Status Detalhe Campos FY24'!$K:$K,"*"&$P$25&"*",'2. Status Detalhe Campos FY24'!U:U,"*Novo Plano*") -> 0 | R33: =+Q33+P33 -> 0
C34: Loan Tape | E34: 0 | F34: 0 | G34: 0 | H34: 0 | I34: 0 | J34: 0 | K34: 0 | L34: 0 | M34: 0 | N34: 0 | O34: =+SUM(J34:K34)-SUM(L34:N34) -> 0 | P34: 0 | Q34: =+COUNTIFS('2. Status Detalhe Campos FY24'!$C:$C,"*Pilar*",'2. Status Detalhe Campos FY24'!$K:$K,"*"&$P$25&"*") -> 0 | R34: =+Q34+P34 -> 0
C35: RequisItos FY24 | E35: 0 | F35: 0 | G35: 0 | H35: 0 | I35: 0 | J35: 0 | K35: 0 | L35: 0 | M35: 0 | N35: 0 | O35: =+SUM(J35:K35)-SUM(L35:N35) -> 0 | P35: 0 | Q35: =+COUNTIFS('2. Status Detalhe Campos FY24'!$C:$C,"*Pilar*",'2. Status Detalhe Campos FY24'!$K:$K,"*"&$P$25&"*",'2. Status Detalhe Campos FY24'!U:U,"*anterior*") -> 0 | R35: =+Q35+P35 -> 0
C36: Novos Requisitos FY25 | E36: 0 | F36: 0 | G36: 0 | H36: 0 | I36: 0 | J36: 0 | K36: 0 | L36: 0 | M36: 0 | N36: 0 | O36: =+SUM(J36:K36)-SUM(L36:N36) -> 0 | P36: 0 | Q36: =+COUNTIFS('2. Status Detalhe Campos FY24'!$C:$C,"*Pilar*",'2. Status Detalhe Campos FY24'!$K:$K,"*"&$P$25&"*",'2. Status Detalhe Campos FY24'!U:U,"*Novo Plano*") -> 0 | R36: =+Q36+P36 -> 0
C37: Total | E37: 20 | F37: 0 | G37: 20 | H37: 0 | I37: 0 | J37: 0 | K37: 4 | L37: =+SUM(L28,L31,L34) -> 0 | M37: =+SUM(M28,M31,M34) -> 0 | N37: =+SUM(N28,N31,N34) -> 0 | O37: =+SUM(O28,O31,O34) -> 4 | P37: 4 | Q37: =+SUM(Q28,Q31,Q34) -> 44 | R37: =+SUM(R28,R31,R34) -> 48
B41: 1 | AG41: 1
B43: 1. Modelo de Bens Imóveis | G43: Bens Imóveis - Input | H43: Bens Imóveis - Output | I43: Modelo Verde - Input | J43: Modelo Verde - Output | K43: Pilar III
C46: Resumo | G46: Detalhe por Tabela | P46: Status (campos) | T46: 45695 | U46: =T46+7 -> 45702 | V46: ∆ | X46: Highlights
P47: 0. Cancelado | T47: =COUNTIFS('2. Status Detalhe Campos FY24'!$H$7:$H$736,'1. Status Resumo FY24'!$P47,'2. Status Detalhe Campos FY24'!$C$7:$C$736,'1. Status Resumo FY24'!$G$43,'2. Status Detalhe Campos FY24'!$D$7:$D$736,"2. Campo")+COUNTIFS('2. Status Detalhe Campos FY24'!$H$7:$H$736,'1. Status Resumo FY24'!$P47,'2. Status Detalhe Campos FY24'!$C$7:$C$736,'1. Status Resumo FY24'!$H$43,'2. Status Detalhe Campos FY24'!$D$7:$D$736,"2. Campo") -> 12 | U47: =COUNTIFS('2. Status Detalhe Campos FY24'!$G$7:$G$736,'1. Status Resumo FY24'!$P47,'2. Status Detalhe Campos FY24'!$C$7:$C$736,'1. Status Resumo FY24'!$G$43,'2. Status Detalhe Campos FY24'!$D$7:$D$736,"2. Campo")+COUNTIFS('2. Status Detalhe Campos FY24'!$G$7:$G$736,'1. Status Resumo FY24'!$P47,'2. Status Detalhe Campos FY24'!$C$7:$C$736,'1. Status Resumo FY24'!$H$43,'2. Status Detalhe Campos FY24'!$D$7:$D$736,"2. Campo") -> 12 | V47: =U47-T47 -> 0 | X47: 1. Gloval: - Tratamento e preparação de 6 ficheiros relativos a cada rácio de receção de informação de consumo e eficiência energética da Gloval. Denote-se que para testar o front e a tabela de Input será necessário obter os acessos ao mesmo.
P48: RequisItos FY24 | T48: =COUNTIFS('2. Status Detalhe Campos FY24'!$H$7:$H$736,'1. Status Resumo FY24'!$P47,'2. Status Detalhe Campos FY24'!$C$7:$C$736,'1. Status Resumo FY24'!$G$43,'2. Status Detalhe Campos FY24'!$D$7:$D$736,"2. Campo",'2. Status Detalhe Campos FY24'!$U$7:$U$736,"*Plano anterior*") +COUNTIFS('2. Status Detalhe Campos FY24'!$H$7:$H$736,'1. Status Resumo FY24'!$P47,'2. Status Detalhe Campos FY24'!$C$7:$C$736,'1. Status Resumo FY24'!$H$43,'2. Status Detalhe Campos FY24'!$D$7:$D$736,"2. Campo",'2. Status Detalhe Campos FY24'!$U$7:$U$736,"*Plano anterior*") -> 12 | U48: =COUNTIFS('2. Status Detalhe Campos FY24'!$G$7:$G$736,'1. Status Resumo FY24'!$P47,'2. Status Detalhe Campos FY24'!$C$7:$C$736,'1. Status Resumo FY24'!$G$43,'2. Status Detalhe Campos FY24'!$D$7:$D$736,"2. Campo",'2. Status Detalhe Campos FY24'!$U$7:$U$736,"*Plano anterior*") +COUNTIFS('2. Status Detalhe Campos FY24'!$G$7:$G$736,'1. Status Resumo FY24'!$P47,'2. Status Detalhe Campos FY24'!$C$7:$C$736,'1. Status Resumo FY24'!$H$43,'2. Status Detalhe Campos FY24'!$D$7:$D$736,"2. Campo",'2. Status Detalhe Campos FY24'!$U$7:$U$736,"*Plano anterior*") -> 12 | V48: =U48-T48 -> 0
P49: Novos Requisitos FY25 | T49: =COUNTIFS('2. Status Detalhe Campos FY24'!$H$7:$H$736,'1. Status Resumo FY24'!$P48,'2. Status Detalhe Campos FY24'!$C$7:$C$736,'1. Status Resumo FY24'!$G$43,'2. Status Detalhe Campos FY24'!$D$7:$D$736,"2. Campo",'2. Status Detalhe Campos FY24'!$U$7:$U$736,"*Novo Plano*") +COUNTIFS('2. Status Detalhe Campos FY24'!$H$7:$H$736,'1. Status Resumo FY24'!$P48,'2. Status Detalhe Campos FY24'!$C$7:$C$736,'1. Status Resumo FY24'!$H$43,'2. Status Detalhe Campos FY24'!$D$7:$D$736,"2. Campo",'2. Status Detalhe Campos FY24'!$U$7:$U$736,"*Novo Plano*") -> 0 | U49: =COUNTIFS('2. Status Detalhe Campos FY24'!$G$7:$G$736,'1. Status Resumo FY24'!$P47,'2. Status Detalhe Campos FY24'!$C$7:$C$736,'1. Status Resumo FY24'!$G$43,'2. Status Detalhe Campos FY24'!$D$7:$D$736,"2. Campo",'2. Status Detalhe Campos FY24'!$U$7:$U$736,"*Novo Plano*") +COUNTIFS('2. Status Detalhe Campos FY24'!$G$7:$G$736,'1. Status Resumo FY24'!$P47,'2. Status Detalhe Campos FY24'!$C$7:$C$736,'1. Status Resumo FY24'!$H$43,'2. Status Detalhe Campos FY24'!$D$7:$D$736,"2. Campo",'2. Status Detalhe Campos FY24'!$U$7:$U$736,"*Novo Plano*") -> 0 | V49: =U49-T49 -> 0
P50: 1. Concluído | T50: =COUNTIFS('2. Status Detalhe Campos FY24'!$H$7:$H$736,'1. Status Resumo FY24'!$P50,'2. Status Detalhe Campos FY24'!$C$7:$C$736,'1. Status Resumo FY24'!$G$43,'2. Status Detalhe Campos FY24'!$D$7:$D$736,"2. Campo")+COUNTIFS('2. Status Detalhe Campos FY24'!$H$7:$H$736,'1. Status Resumo FY24'!$P50,'2. Status Detalhe Campos FY24'!$C$7:$C$736,'1. Status Resumo FY24'!$H$43,'2. Status Detalhe Campos FY24'!$D$7:$D$736,"2. Campo") -> 144 | U50: =COUNTIFS('2. Status Detalhe Campos FY24'!$G$7:$G$736,'1. Status Resumo FY24'!$P50,'2. Status Detalhe Campos FY24'!$C$7:$C$736,'1. Status Resumo FY24'!$G$43,'2. Status Detalhe Campos FY24'!$D$7:$D$736,"2. Campo")+COUNTIFS('2. Status Detalhe Campos FY24'!$G$7:$G$736,'1. Status Resumo FY24'!$P50,'2. Status Detalhe Campos FY24'!$C$7:$C$736,'1. Status Resumo FY24'!$H$43,'2. Status Detalhe Campos FY24'!$D$7:$D$736,"2. Campo") -> 144 | V50: =U50-T50 -> 0
P51: RequisItos FY24 | T51: =COUNTIFS('2. Status Detalhe Campos FY24'!$H$7:$H$736,'1. Status Resumo FY24'!$P50,'2. Status Detalhe Campos FY24'!$C$7:$C$736,'1. Status Resumo FY24'!$G$43,'2. Status Detalhe Campos FY24'!$D$7:$D$736,"2. Campo",'2. Status Detalhe Campos FY24'!$U$7:$U$736,"*Plano anterior*") +COUNTIFS('2. Status Detalhe Campos FY24'!$H$7:$H$736,'1. Status Resumo FY24'!$P50,'2. Status Detalhe Campos FY24'!$C$7:$C$736,'1. Status Resumo FY24'!$H$43,'2. Status Detalhe Campos FY24'!$D$7:$D$736,"2. Campo",'2. Status Detalhe Campos FY24'!$U$7:$U$736,"*Plano anterior*") -> 144 | U51: =COUNTIFS('2. Status Detalhe Campos FY24'!$G$7:$G$736,'1. Status Resumo FY24'!$P50,'2. Status Detalhe Campos FY24'!$C$7:$C$736,'1. Status Resumo FY24'!$G$43,'2. Status Detalhe Campos FY24'!$D$7:$D$736,"2. Campo",'2. Status Detalhe Campos FY24'!$U$7:$U$736,"*Plano anterior*") +COUNTIFS('2. Status Detalhe Campos FY24'!$G$7:$G$736,'1. Status Resumo FY24'!$P50,'2. Status Detalhe Campos FY24'!$C$7:$C$736,'1. Status Resumo FY24'!$H$43,'2. Status Detalhe Campos FY24'!$D$7:$D$736,"2. Campo",'2. Status Detalhe Campos FY24'!$U$7:$U$736,"*Plano anterior*") -> 144 | V51: =U51-T51 -> 0
P52: Novos Requisitos FY25 | T52: =COUNTIFS('2. Status Detalhe Campos FY24'!$H$7:$H$736,'1. Status Resumo FY24'!$P51,'2. Status Detalhe Campos FY24'!$C$7:$C$736,'1. Status Resumo FY24'!$G$43,'2. Status Detalhe Campos FY24'!$D$7:$D$736,"2. Campo",'2. Status Detalhe Campos FY24'!$U$7:$U$736,"*Novo Plano*") +COUNTIFS('2. Status Detalhe Campos FY24'!$H$7:$H$736,'1. Status Resumo FY24'!$P51,'2. Status Detalhe Campos FY24'!$C$7:$C$736,'1. Status Resumo FY24'!$H$43,'2. Status Detalhe Campos FY24'!$D$7:$D$736,"2. Campo",'2. Status Detalhe Campos FY24'!$U$7:$U$736,"*Novo Plano*") -> 0 | U52: =COUNTIFS('2. Status Detalhe Campos FY24'!$G$7:$G$736,'1. Status Resumo FY24'!$P50,'2. Status Detalhe Campos FY24'!$C$7:$C$736,'1. Status Resumo FY24'!$G$43,'2. Status Detalhe Campos FY24'!$D$7:$D$736,"2. Campo",'2. Status Detalhe Campos FY24'!$U$7:$U$736,"*Novo Plano*") +COUNTIFS('2. Status Detalhe Campos FY24'!$G$7:$G$736,'1. Status Resumo FY24'!$P50,'2. Status Detalhe Campos FY24'!$C$7:$C$736,'1. Status Resumo FY24'!$H$43,'2. Status Detalhe Campos FY24'!$D$7:$D$736,"2. Campo",'2. Status Detalhe Campos FY24'!$U$7:$U$736,"*Novo Plano*") -> 0 | V52: =U52-T52 -> 0
P53: 2.1 Em Teste | T53: =COUNTIFS('2. Status Detalhe Campos FY24'!$H$7:$H$736,'1. Status Resumo FY24'!$P53,'2. Status Detalhe Campos FY24'!$C$7:$C$736,'1. Status Resumo FY24'!$G$43,'2. Status Detalhe Campos FY24'!$D$7:$D$736,"2. Campo")+COUNTIFS('2. Status Detalhe Campos FY24'!$H$7:$H$736,'1. Status Resumo FY24'!$P53,'2. Status Detalhe Campos FY24'!$C$7:$C$736,'1. Status Resumo FY24'!$H$43,'2. Status Detalhe Campos FY24'!$D$7:$D$736,"2. Campo") -> 0 | U53: =COUNTIFS('2. Status Detalhe Campos FY24'!$G$7:$G$736,'1. Status Resumo FY24'!$P53,'2. Status Detalhe Campos FY24'!$C$7:$C$736,'1. Status Resumo FY24'!$G$43,'2. Status Detalhe Campos FY24'!$D$7:$D$736,"2. Campo")+COUNTIFS('2. Status Detalhe Campos FY24'!$G$7:$G$736,'1. Status Resumo FY24'!$P53,'2. Status Detalhe Campos FY24'!$C$7:$C$736,'1. Status Resumo FY24'!$H$43,'2. Status Detalhe Campos FY24'!$D$7:$D$736,"2. Campo") -> 2 | V53: =U53-T53 -> 2
P54: RequisItos FY24 | T54: =COUNTIFS('2. Status Detalhe Campos FY24'!$H$7:$H$736,'1. Status Resumo FY24'!$P53,'2. Status Detalhe Campos FY24'!$C$7:$C$736,'1. Status Resumo FY24'!$G$43,'2. Status Detalhe Campos FY24'!$D$7:$D$736,"2. Campo",'2. Status Detalhe Campos FY24'!$U$7:$U$736,"*Plano anterior*") +COUNTIFS('2. Status Detalhe Campos FY24'!$H$7:$H$736,'1. Status Resumo FY24'!$P53,'2. Status Detalhe Campos FY24'!$C$7:$C$736,'1. Status Resumo FY24'!$H$43,'2. Status Detalhe Campos FY24'!$D$7:$D$736,"2. Campo",'2. Status Detalhe Campos FY24'!$U$7:$U$736,"*Plano anterior*") -> 0 | U54: =COUNTIFS('2. Status Detalhe Campos FY24'!$G$7:$G$736,'1. Status Resumo FY24'!$P53,'2. Status Detalhe Campos FY24'!$C$7:$C$736,'1. Status Resumo FY24'!$G$43,'2. Status Detalhe Campos FY24'!$D$7:$D$736,"2. Campo",'2. Status Detalhe Campos FY24'!$U$7:$U$736,"*Plano anterior*") +COUNTIFS('2. Status Detalhe Campos FY24'!$G$7:$G$736,'1. Status Resumo FY24'!$P53,'2. Status Detalhe Campos FY24'!$C$7:$C$736,'1. Status Resumo FY24'!$H$43,'2. Status Detalhe Campos FY24'!$D$7:$D$736,"2. Campo",'2. Status Detalhe Campos FY24'!$U$7:$U$736,"*Plano anterior*") -> 2 | V54: =U54-T54 -> 2
P55: Novos Requisitos FY25 | T55: =COUNTIFS('2. Status Detalhe Campos FY24'!$H$7:$H$736,'1. Status Resumo FY24'!$P54,'2. Status Detalhe Campos FY24'!$C$7:$C$736,'1. Status Resumo FY24'!$G$43,'2. Status Detalhe Campos FY24'!$D$7:$D$736,"2. Campo",'2. Status Detalhe Campos FY24'!$U$7:$U$736,"*Novo Plano*") +COUNTIFS('2. Status Detalhe Campos FY24'!$H$7:$H$736,'1. Status Resumo FY24'!$P54,'2. Status Detalhe Campos FY24'!$C$7:$C$736,'1. Status Resumo FY24'!$H$43,'2. Status Detalhe Campos FY24'!$D$7:$D$736,"2. Campo",'2. Status Detalhe Campos FY24'!$U$7:$U$736,"*Novo Plano*") -> 0 | U55: =COUNTIFS('2. Status Detalhe Campos FY24'!$G$7:$G$736,'1. Status Resumo FY24'!$P53,'2. Status Detalhe Campos FY24'!$C$7:$C$736,'1. Status Resumo FY24'!$G$43,'2. Status Detalhe Campos FY24'!$D$7:$D$736,"2. Campo",'2. Status Detalhe Campos FY24'!$U$7:$U$736,"*Novo Plano*") +COUNTIFS('2. Status Detalhe Campos FY24'!$G$7:$G$736,'1. Status Resumo FY24'!$P53,'2. Status Detalhe Campos FY24'!$C$7:$C$736,'1. Status Resumo FY24'!$H$43,'2. Status Detalhe Campos FY24'!$D$7:$D$736,"2. Campo",'2. Status Detalhe Campos FY24'!$U$7:$U$736,"*Novo Plano*") -> 0 | V55: =U55-T55 -> 0
D56: ="# "&U74 -> # 161 | P56: 2.2 Em especificação | T56: =COUNTIFS('2. Status Detalhe Campos FY24'!$H$7:$H$736,'1. Status Resumo FY24'!$P56,'2. Status Detalhe Campos FY24'!$C$7:$C$736,'1. Status Resumo FY24'!$G$43,'2. Status Detalhe Campos FY24'!$D$7:$D$736,"2. Campo")+COUNTIFS('2. Status Detalhe Campos FY24'!$H$7:$H$736,'1. Status Resumo FY24'!$P56,'2. Status Detalhe Campos FY24'!$C$7:$C$736,'1. Status Resumo FY24'!$H$43,'2. Status Detalhe Campos FY24'!$D$7:$D$736,"2. Campo") -> 0 | U56: =COUNTIFS('2. Status Detalhe Campos FY24'!$G$7:$G$736,'1. Status Resumo FY24'!$P56,'2. Status Detalhe Campos FY24'!$C$7:$C$736,'1. Status Resumo FY24'!$G$43,'2. Status Detalhe Campos FY24'!$D$7:$D$736,"2. Campo")+COUNTIFS('2. Status Detalhe Campos FY24'!$G$7:$G$736,'1. Status Resumo FY24'!$P56,'2. Status Detalhe Campos FY24'!$C$7:$C$736,'1. Status Resumo FY24'!$H$43,'2. Status Detalhe Campos FY24'!$D$7:$D$736,"2. Campo") -> 0 | V56: =U56-T56 -> 0
P57: RequisItos FY24 | T57: =COUNTIFS('2. Status Detalhe Campos FY24'!$H$7:$H$736,'1. Status Resumo FY24'!$P56,'2. Status Detalhe Campos FY24'!$C$7:$C$736,'1. Status Resumo FY24'!$G$43,'2. Status Detalhe Campos FY24'!$D$7:$D$736,"2. Campo",'2. Status Detalhe Campos FY24'!$U$7:$U$736,"*Plano anterior*") +COUNTIFS('2. Status Detalhe Campos FY24'!$H$7:$H$736,'1. Status Resumo FY24'!$P56,'2. Status Detalhe Campos FY24'!$C$7:$C$736,'1. Status Resumo FY24'!$H$43,'2. Status Detalhe Campos FY24'!$D$7:$D$736,"2. Campo",'2. Status Detalhe Campos FY24'!$U$7:$U$736,"*Plano anterior*") -> 0 | U57: =COUNTIFS('2. Status Detalhe Campos FY24'!$G$7:$G$736,'1. Status Resumo FY24'!$P56,'2. Status Detalhe Campos FY24'!$C$7:$C$736,'1. Status Resumo FY24'!$G$43,'2. Status Detalhe Campos FY24'!$D$7:$D$736,"2. Campo",'2. Status Detalhe Campos FY24'!$U$7:$U$736,"*Plano anterior*") +COUNTIFS('2. Status Detalhe Campos FY24'!$G$7:$G$736,'1. Status Resumo FY24'!$P56,'2. Status Detalhe Campos FY24'!$C$7:$C$736,'1. Status Resumo FY24'!$H$43,'2. Status Detalhe Campos FY24'!$D$7:$D$736,"2. Campo",'2. Status Detalhe Campos FY24'!$U$7:$U$736,"*Plano anterior*") -> 0 | V57: =U57-T57 -> 0
P58: Novos Requisitos FY25 | T58: =COUNTIFS('2. Status Detalhe Campos FY24'!$H$7:$H$736,'1. Status Resumo FY24'!$P57,'2. Status Detalhe Campos FY24'!$C$7:$C$736,'1. Status Resumo FY24'!$G$43,'2. Status Detalhe Campos FY24'!$D$7:$D$736,"2. Campo",'2. Status Detalhe Campos FY24'!$U$7:$U$736,"*Novo Plano*") +COUNTIFS('2. Status Detalhe Campos FY24'!$H$7:$H$736,'1. Status Resumo FY24'!$P57,'2. Status Detalhe Campos FY24'!$C$7:$C$736,'1. Status Resumo FY24'!$H$43,'2. Status Detalhe Campos FY24'!$D$7:$D$736,"2. Campo",'2. Status Detalhe Campos FY24'!$U$7:$U$736,"*Novo Plano*") -> 0 | U58: =COUNTIFS('2. Status Detalhe Campos FY24'!$G$7:$G$736,'1. Status Resumo FY24'!$P56,'2. Status Detalhe Campos FY24'!$C$7:$C$736,'1. Status Resumo FY24'!$G$43,'2. Status Detalhe Campos FY24'!$D$7:$D$736,"2. Campo",'2. Status Detalhe Campos FY24'!$U$7:$U$736,"*Novo Plano*") +COUNTIFS('2. Status Detalhe Campos FY24'!$G$7:$G$736,'1. Status Resumo FY24'!$P56,'2. Status Detalhe Campos FY24'!$C$7:$C$736,'1. Status Resumo FY24'!$H$43,'2. Status Detalhe Campos FY24'!$D$7:$D$736,"2. Campo",'2. Status Detalhe Campos FY24'!$U$7:$U$736,"*Novo Plano*") -> 0 | V58: =U58-T58 -> 0
P59: 3. Pendente de outros desenvolvimentos | T59: =COUNTIFS('2. Status Detalhe Campos FY24'!$H$7:$H$736,'1. Status Resumo FY24'!$P59,'2. Status Detalhe Campos FY24'!$C$7:$C$736,'1. Status Resumo FY24'!$G$43,'2. Status Detalhe Campos FY24'!$D$7:$D$736,"2. Campo")+COUNTIFS('2. Status Detalhe Campos FY24'!$H$7:$H$736,'1. Status Resumo FY24'!$P59,'2. Status Detalhe Campos FY24'!$C$7:$C$736,'1. Status Resumo FY24'!$H$43,'2. Status Detalhe Campos FY24'!$D$7:$D$736,"2. Campo") -> 0 | U59: =COUNTIFS('2. Status Detalhe Campos FY24'!$G$7:$G$736,'1. Status Resumo FY24'!$P59,'2. Status Detalhe Campos FY24'!$C$7:$C$736,'1. Status Resumo FY24'!$G$43,'2. Status Detalhe Campos FY24'!$D$7:$D$736,"2. Campo")+COUNTIFS('2. Status Detalhe Campos FY24'!$G$7:$G$736,'1. Status Resumo FY24'!$P59,'2. Status Detalhe Campos FY24'!$C$7:$C$736,'1. Status Resumo FY24'!$H$43,'2. Status Detalhe Campos FY24'!$D$7:$D$736,"2. Campo") -> 0 | V59: =U59-T59 -> 0
P60: RequisItos FY24 | T60: =COUNTIFS('2. Status Detalhe Campos FY24'!$H$7:$H$736,'1. Status Resumo FY24'!$P59,'2. Status Detalhe Campos FY24'!$C$7:$C$736,'1. Status Resumo FY24'!$G$43,'2. Status Detalhe Campos FY24'!$D$7:$D$736,"2. Campo",'2. Status Detalhe Campos FY24'!$U$7:$U$736,"*Plano anterior*") +COUNTIFS('2. Status Detalhe Campos FY24'!$H$7:$H$736,'1. Status Resumo FY24'!$P59,'2. Status Detalhe Campos FY24'!$C$7:$C$736,'1. Status Resumo FY24'!$H$43,'2. Status Detalhe Campos FY24'!$D$7:$D$736,"2. Campo",'2. Status Detalhe Campos FY24'!$U$7:$U$736,"*Plano anterior*") -> 0 | U60: =COUNTIFS('2. Status Detalhe Campos FY24'!$G$7:$G$736,'1. Status Resumo FY24'!$P59,'2. Status Detalhe Campos FY24'!$C$7:$C$736,'1. Status Resumo FY24'!$G$43,'2. Status Detalhe Campos FY24'!$D$7:$D$736,"2. Campo",'2. Status Detalhe Campos FY24'!$U$7:$U$736,"*Plano anterior*") +COUNTIFS('2. Status Detalhe Campos FY24'!$G$7:$G$736,'1. Status Resumo FY24'!$P59,'2. Status Detalhe Campos FY24'!$C$7:$C$736,'1. Status Resumo FY24'!$H$43,'2. Status Detalhe Campos FY24'!$D$7:$D$736,"2. Campo",'2. Status Detalhe Campos FY24'!$U$7:$U$736,"*Plano anterior*") -> 0 | V60: =U60-T60 -> 0
P61: Novos Requisitos FY25 | T61: =COUNTIFS('2. Status Detalhe Campos FY24'!$H$7:$H$736,'1. Status Resumo FY24'!$P60,'2. Status Detalhe Campos FY24'!$C$7:$C$736,'1. Status Resumo FY24'!$G$43,'2. Status Detalhe Campos FY24'!$D$7:$D$736,"2. Campo",'2. Status Detalhe Campos FY24'!$U$7:$U$736,"*Novo Plano*") +COUNTIFS('2. Status Detalhe Campos FY24'!$H$7:$H$736,'1. Status Resumo FY24'!$P60,'2. Status Detalhe Campos FY24'!$C$7:$C$736,'1. Status Resumo FY24'!$H$43,'2. Status Detalhe Campos FY24'!$D$7:$D$736,"2. Campo",'2. Status Detalhe Campos FY24'!$U$7:$U$736,"*Novo Plano*") -> 0 | U61: =COUNTIFS('2. Status Detalhe Campos FY24'!$G$7:$G$736,'1. Status Resumo FY24'!$P59,'2. Status Detalhe Campos FY24'!$C$7:$C$736,'1. Status Resumo FY24'!$G$43,'2. Status Detalhe Campos FY24'!$D$7:$D$736,"2. Campo",'2. Status Detalhe Campos FY24'!$U$7:$U$736,"*Novo Plano*") +COUNTIFS('2. Status Detalhe Campos FY24'!$G$7:$G$736,'1. Status Resumo FY24'!$P59,'2. Status Detalhe Campos FY24'!$C$7:$C$736,'1. Status Resumo FY24'!$H$43,'2. Status Detalhe Campos FY24'!$D$7:$D$736,"2. Campo",'2. Status Detalhe Campos FY24'!$U$7:$U$736,"*Novo Plano*") -> 0 | V61: =U61-T61 -> 0
P62: 4. Validação EF | T62: =COUNTIFS('2. Status Detalhe Campos FY24'!$H$7:$H$736,'1. Status Resumo FY24'!$P62,'2. Status Detalhe Campos FY24'!$C$7:$C$736,'1. Status Resumo FY24'!$G$43,'2. Status Detalhe Campos FY24'!$D$7:$D$736,"2. Campo")+COUNTIFS('2. Status Detalhe Campos FY24'!$H$7:$H$736,'1. Status Resumo FY24'!$P62,'2. Status Detalhe Campos FY24'!$C$7:$C$736,'1. Status Resumo FY24'!$H$43,'2. Status Detalhe Campos FY24'!$D$7:$D$736,"2. Campo") -> 0 | U62: =COUNTIFS('2. Status Detalhe Campos FY24'!$G$7:$G$736,'1. Status Resumo FY24'!$P62,'2. Status Detalhe Campos FY24'!$C$7:$C$736,'1. Status Resumo FY24'!$G$43,'2. Status Detalhe Campos FY24'!$D$7:$D$736,"2. Campo")+COUNTIFS('2. Status Detalhe Campos FY24'!$G$7:$G$736,'1. Status Resumo FY24'!$P62,'2. Status Detalhe Campos FY24'!$C$7:$C$736,'1. Status Resumo FY24'!$H$43,'2. Status Detalhe Campos FY24'!$D$7:$D$736,"2. Campo") -> 2 | V62: =U62-T62 -> 2
P63: RequisItos FY24 | T63: =COUNTIFS('2. Status Detalhe Campos FY24'!$H$7:$H$736,'1. Status Resumo FY24'!$P62,'2. Status Detalhe Campos FY24'!$C$7:$C$736,'1. Status Resumo FY24'!$G$43,'2. Status Detalhe Campos FY24'!$D$7:$D$736,"2. Campo",'2. Status Detalhe Campos FY24'!$U$7:$U$736,"*Plano anterior*") +COUNTIFS('2. Status Detalhe Campos FY24'!$H$7:$H$736,'1. Status Resumo FY24'!$P62,'2. Status Detalhe Campos FY24'!$C$7:$C$736,'1. Status Resumo FY24'!$H$43,'2. Status Detalhe Campos FY24'!$D$7:$D$736,"2. Campo",'2. Status Detalhe Campos FY24'!$U$7:$U$736,"*Plano anterior*") -> 0 | U63: =COUNTIFS('2. Status Detalhe Campos FY24'!$G$7:$G$736,'1. Status Resumo FY24'!$P62,'2. Status Detalhe Campos FY24'!$C$7:$C$736,'1. Status Resumo FY24'!$G$43,'2. Status Detalhe Campos FY24'!$D$7:$D$736,"2. Campo",'2. Status Detalhe Campos FY24'!$U$7:$U$736,"*Plano anterior*") +COUNTIFS('2. Status Detalhe Campos FY24'!$G$7:$G$736,'1. Status Resumo FY24'!$P62,'2. Status Detalhe Campos FY24'!$C$7:$C$736,'1. Status Resumo FY24'!$H$43,'2. Status Detalhe Campos FY24'!$D$7:$D$736,"2. Campo",'2. Status Detalhe Campos FY24'!$U$7:$U$736,"*Plano anterior*") -> 2 | V63: =U63-T63 -> 2
P64: Novos Requisitos FY25 | T64: =COUNTIFS('2. Status Detalhe Campos FY24'!$H$7:$H$736,'1. Status Resumo FY24'!$P63,'2. Status Detalhe Campos FY24'!$C$7:$C$736,'1. Status Resumo FY24'!$G$43,'2. Status Detalhe Campos FY24'!$D$7:$D$736,"2. Campo",'2. Status Detalhe Campos FY24'!$U$7:$U$736,"*Novo Plano*") +COUNTIFS('2. Status Detalhe Campos FY24'!$H$7:$H$736,'1. Status Resumo FY24'!$P63,'2. Status Detalhe Campos FY24'!$C$7:$C$736,'1. Status Resumo FY24'!$H$43,'2. Status Detalhe Campos FY24'!$D$7:$D$736,"2. Campo",'2. Status Detalhe Campos FY24'!$U$7:$U$736,"*Novo Plano*") -> 0 | U64: =COUNTIFS('2. Status Detalhe Campos FY24'!$G$7:$G$736,'1. Status Resumo FY24'!$P62,'2. Status Detalhe Campos FY24'!$C$7:$C$736,'1. Status Resumo FY24'!$G$43,'2. Status Detalhe Campos FY24'!$D$7:$D$736,"2. Campo",'2. Status Detalhe Campos FY24'!$U$7:$U$736,"*Novo Plano*") +COUNTIFS('2. Status Detalhe Campos FY24'!$G$7:$G$736,'1. Status Resumo FY24'!$P62,'2. Status Detalhe Campos FY24'!$C$7:$C$736,'1. Status Resumo FY24'!$H$43,'2. Status Detalhe Campos FY24'!$D$7:$D$736,"2. Campo",'2. Status Detalhe Campos FY24'!$U$7:$U$736,"*Novo Plano*") -> 0 | V64: =U64-T64 -> 0
P65: 5. Em Correção | R65: (incidências) | T65: =COUNTIFS('2. Status Detalhe Campos FY24'!$H$7:$H$736,'1. Status Resumo FY24'!$P65,'2. Status Detalhe Campos FY24'!$C$7:$C$736,'1. Status Resumo FY24'!$G$43,'2. Status Detalhe Campos FY24'!$D$7:$D$736,"2. Campo")+COUNTIFS('2. Status Detalhe Campos FY24'!$H$7:$H$736,'1. Status Resumo FY24'!$P65,'2. Status Detalhe Campos FY24'!$C$7:$C$736,'1. Status Resumo FY24'!$H$43,'2. Status Detalhe Campos FY24'!$D$7:$D$736,"2. Campo") -> 0 | U65: =COUNTIFS('2. Status Detalhe Campos FY24'!$G$7:$G$736,'1. Status Resumo FY24'!$P65,'2. Status Detalhe Campos FY24'!$C$7:$C$736,'1. Status Resumo FY24'!$G$43,'2. Status Detalhe Campos FY24'!$D$7:$D$736,"2. Campo")+COUNTIFS('2. Status Detalhe Campos FY24'!$G$7:$G$736,'1. Status Resumo FY24'!$P65,'2. Status Detalhe Campos FY24'!$C$7:$C$736,'1. Status Resumo FY24'!$H$43,'2. Status Detalhe Campos FY24'!$D$7:$D$736,"2. Campo") -> 0 | V65: =U65-T65 -> 0
P66: RequisItos FY24 | T66: =COUNTIFS('2. Status Detalhe Campos FY24'!$H$7:$H$736,'1. Status Resumo FY24'!$P65,'2. Status Detalhe Campos FY24'!$C$7:$C$736,'1. Status Resumo FY24'!$G$43,'2. Status Detalhe Campos FY24'!$D$7:$D$736,"2. Campo",'2. Status Detalhe Campos FY24'!$U$7:$U$736,"*Plano anterior*") +COUNTIFS('2. Status Detalhe Campos FY24'!$H$7:$H$736,'1. Status Resumo FY24'!$P65,'2. Status Detalhe Campos FY24'!$C$7:$C$736,'1. Status Resumo FY24'!$H$43,'2. Status Detalhe Campos FY24'!$D$7:$D$736,"2. Campo",'2. Status Detalhe Campos FY24'!$U$7:$U$736,"*Plano anterior*") -> 0 | U66: =COUNTIFS('2. Status Detalhe Campos FY24'!$G$7:$G$736,'1. Status Resumo FY24'!$P65,'2. Status Detalhe Campos FY24'!$C$7:$C$736,'1. Status Resumo FY24'!$G$43,'2. Status Detalhe Campos FY24'!$D$7:$D$736,"2. Campo",'2. Status Detalhe Campos FY24'!$U$7:$U$736,"*Plano anterior*") +COUNTIFS('2. Status Detalhe Campos FY24'!$G$7:$G$736,'1. Status Resumo FY24'!$P65,'2. Status Detalhe Campos FY24'!$C$7:$C$736,'1. Status Resumo FY24'!$H$43,'2. Status Detalhe Campos FY24'!$D$7:$D$736,"2. Campo",'2. Status Detalhe Campos FY24'!$U$7:$U$736,"*Plano anterior*") -> 0 | V66: =U66-T66 -> 0
P67: Novos Requisitos FY25 | T67: =COUNTIFS('2. Status Detalhe Campos FY24'!$H$7:$H$736,'1. Status Resumo FY24'!$P66,'2. Status Detalhe Campos FY24'!$C$7:$C$736,'1. Status Resumo FY24'!$G$43,'2. Status Detalhe Campos FY24'!$D$7:$D$736,"2. Campo",'2. Status Detalhe Campos FY24'!$U$7:$U$736,"*Novo Plano*") +COUNTIFS('2. Status Detalhe Campos FY24'!$H$7:$H$736,'1. Status Resumo FY24'!$P66,'2. Status Detalhe Campos FY24'!$C$7:$C$736,'1. Status Resumo FY24'!$H$43,'2. Status Detalhe Campos FY24'!$D$7:$D$736,"2. Campo",'2. Status Detalhe Campos FY24'!$U$7:$U$736,"*Novo Plano*") -> 0 | U67: =COUNTIFS('2. Status Detalhe Campos FY24'!$G$7:$G$736,'1. Status Resumo FY24'!$P65,'2. Status Detalhe Campos FY24'!$C$7:$C$736,'1. Status Resumo FY24'!$G$43,'2. Status Detalhe Campos FY24'!$D$7:$D$736,"2. Campo",'2. Status Detalhe Campos FY24'!$U$7:$U$736,"*Novo Plano*") +COUNTIFS('2. Status Detalhe Campos FY24'!$G$7:$G$736,'1. Status Resumo FY24'!$P65,'2. Status Detalhe Campos FY24'!$C$7:$C$736,'1. Status Resumo FY24'!$H$43,'2. Status Detalhe Campos FY24'!$D$7:$D$736,"2. Campo",'2. Status Detalhe Campos FY24'!$U$7:$U$736,"*Novo Plano*") -> 0 | V67: =U67-T67 -> 0
P68: 6. Em implementação | T68: =COUNTIFS('2. Status Detalhe Campos FY24'!$H$7:$H$736,'1. Status Resumo FY24'!$P68,'2. Status Detalhe Campos FY24'!$C$7:$C$736,'1. Status Resumo FY24'!$G$43,'2. Status Detalhe Campos FY24'!$D$7:$D$736,"2. Campo")+COUNTIFS('2. Status Detalhe Campos FY24'!$H$7:$H$736,'1. Status Resumo FY24'!$P68,'2. Status Detalhe Campos FY24'!$C$7:$C$736,'1. Status Resumo FY24'!$H$43,'2. Status Detalhe Campos FY24'!$D$7:$D$736,"2. Campo") -> 48 | U68: =COUNTIFS('2. Status Detalhe Campos FY24'!$G$7:$G$736,'1. Status Resumo FY24'!$P68,'2. Status Detalhe Campos FY24'!$C$7:$C$736,'1. Status Resumo FY24'!$G$43,'2. Status Detalhe Campos FY24'!$D$7:$D$736,"2. Campo")+COUNTIFS('2. Status Detalhe Campos FY24'!$G$7:$G$736,'1. Status Resumo FY24'!$P68,'2. Status Detalhe Campos FY24'!$C$7:$C$736,'1. Status Resumo FY24'!$H$43,'2. Status Detalhe Campos FY24'!$D$7:$D$736,"2. Campo") -> 1 | V68: =U68-T68 -> -47
P69: RequisItos FY24 | T69: =COUNTIFS('2. Status Detalhe Campos FY24'!$H$7:$H$736,'1. Status Resumo FY24'!$P68,'2. Status Detalhe Campos FY24'!$C$7:$C$736,'1. Status Resumo FY24'!$G$43,'2. Status Detalhe Campos FY24'!$D$7:$D$736,"2. Campo",'2. Status Detalhe Campos FY24'!$U$7:$U$736,"*Plano anterior*") +COUNTIFS('2. Status Detalhe Campos FY24'!$H$7:$H$736,'1. Status Resumo FY24'!$P68,'2. Status Detalhe Campos FY24'!$C$7:$C$736,'1. Status Resumo FY24'!$H$43,'2. Status Detalhe Campos FY24'!$D$7:$D$736,"2. Campo",'2. Status Detalhe Campos FY24'!$U$7:$U$736,"*Plano anterior*") -> 48 | U69: =COUNTIFS('2. Status Detalhe Campos FY24'!$G$7:$G$736,'1. Status Resumo FY24'!$P68,'2. Status Detalhe Campos FY24'!$C$7:$C$736,'1. Status Resumo FY24'!$G$43,'2. Status Detalhe Campos FY24'!$D$7:$D$736,"2. Campo",'2. Status Detalhe Campos FY24'!$U$7:$U$736,"*Plano anterior*") +COUNTIFS('2. Status Detalhe Campos FY24'!$G$7:$G$736,'1. Status Resumo FY24'!$P68,'2. Status Detalhe Campos FY24'!$C$7:$C$736,'1. Status Resumo FY24'!$H$43,'2. Status Detalhe Campos FY24'!$D$7:$D$736,"2. Campo",'2. Status Detalhe Campos FY24'!$U$7:$U$736,"*Plano anterior*") -> 0 | V69: =U69-T69 -> -48
P70: Novos Requisitos FY25 | T70: =COUNTIFS('2. Status Detalhe Campos FY24'!$H$7:$H$736,'1. Status Resumo FY24'!$P69,'2. Status Detalhe Campos FY24'!$C$7:$C$736,'1. Status Resumo FY24'!$G$43,'2. Status Detalhe Campos FY24'!$D$7:$D$736,"2. Campo",'2. Status Detalhe Campos FY24'!$U$7:$U$736,"*Novo Plano*") +COUNTIFS('2. Status Detalhe Campos FY24'!$H$7:$H$736,'1. Status Resumo FY24'!$P69,'2. Status Detalhe Campos FY24'!$C$7:$C$736,'1. Status Resumo FY24'!$H$43,'2. Status Detalhe Campos FY24'!$D$7:$D$736,"2. Campo",'2. Status Detalhe Campos FY24'!$U$7:$U$736,"*Novo Plano*") -> 0 | U70: =COUNTIFS('2. Status Detalhe Campos FY24'!$G$7:$G$736,'1. Status Resumo FY24'!$P68,'2. Status Detalhe Campos FY24'!$C$7:$C$736,'1. Status Resumo FY24'!$G$43,'2. Status Detalhe Campos FY24'!$D$7:$D$736,"2. Campo",'2. Status Detalhe Campos FY24'!$U$7:$U$736,"*Novo Plano*") +COUNTIFS('2. Status Detalhe Campos FY24'!$G$7:$G$736,'1. Status Resumo FY24'!$P68,'2. Status Detalhe Campos FY24'!$C$7:$C$736,'1. Status Resumo FY24'!$H$43,'2. Status Detalhe Campos FY24'!$D$7:$D$736,"2. Campo",'2. Status Detalhe Campos FY24'!$U$7:$U$736,"*Novo Plano*") -> 0 | V70: =U70-T70 -> 0
P71: 7. Por iniciar | T71: =COUNTIFS('2. Status Detalhe Campos FY24'!$H$7:$H$736,'1. Status Resumo FY24'!$P71,'2. Status Detalhe Campos FY24'!$C$7:$C$736,'1. Status Resumo FY24'!$G$43,'2. Status Detalhe Campos FY24'!$D$7:$D$736,"2. Campo")+COUNTIFS('2. Status Detalhe Campos FY24'!$H$7:$H$736,'1. Status Resumo FY24'!$P71,'2. Status Detalhe Campos FY24'!$C$7:$C$736,'1. Status Resumo FY24'!$H$43,'2. Status Detalhe Campos FY24'!$D$7:$D$736,"2. Campo") -> 0 | U71: =COUNTIFS('2. Status Detalhe Campos FY24'!$G$7:$G$736,'1. Status Resumo FY24'!$P71,'2. Status Detalhe Campos FY24'!$C$7:$C$736,'1. Status Resumo FY24'!$G$43,'2. Status Detalhe Campos FY24'!$D$7:$D$736,"2. Campo")+COUNTIFS('2. Status Detalhe Campos FY24'!$G$7:$G$736,'1. Status Resumo FY24'!$P71,'2. Status Detalhe Campos FY24'!$C$7:$C$736,'1. Status Resumo FY24'!$H$43,'2. Status Detalhe Campos FY24'!$D$7:$D$736,"2. Campo") -> 0 | V71: =U71-T71 -> 0
P72: RequisItos FY24 | T72: =COUNTIFS('2. Status Detalhe Campos FY24'!$H$7:$H$736,'1. Status Resumo FY24'!$P71,'2. Status Detalhe Campos FY24'!$C$7:$C$736,'1. Status Resumo FY24'!$G$43,'2. Status Detalhe Campos FY24'!$D$7:$D$736,"2. Campo",'2. Status Detalhe Campos FY24'!$U$7:$U$736,"*Plano anterior*") +COUNTIFS('2. Status Detalhe Campos FY24'!$H$7:$H$736,'1. Status Resumo FY24'!$P71,'2. Status Detalhe Campos FY24'!$C$7:$C$736,'1. Status Resumo FY24'!$H$43,'2. Status Detalhe Campos FY24'!$D$7:$D$736,"2. Campo",'2. Status Detalhe Campos FY24'!$U$7:$U$736,"*Plano anterior*") -> 0 | U72: =COUNTIFS('2. Status Detalhe Campos FY24'!$G$7:$G$736,'1. Status Resumo FY24'!$P71,'2. Status Detalhe Campos FY24'!$C$7:$C$736,'1. Status Resumo FY24'!$G$43,'2. Status Detalhe Campos FY24'!$D$7:$D$736,"2. Campo",'2. Status Detalhe Campos FY24'!$U$7:$U$736,"*Plano anterior*") +COUNTIFS('2. Status Detalhe Campos FY24'!$G$7:$G$736,'1. Status Resumo FY24'!$P71,'2. Status Detalhe Campos FY24'!$C$7:$C$736,'1. Status Resumo FY24'!$H$43,'2. Status Detalhe Campos FY24'!$D$7:$D$736,"2. Campo",'2. Status Detalhe Campos FY24'!$U$7:$U$736,"*Plano anterior*") -> 0 | V72: =U72-T72 -> 0
P73: Novos Requisitos FY25 | T73: =COUNTIFS('2. Status Detalhe Campos FY24'!$H$7:$H$736,'1. Status Resumo FY24'!$P72,'2. Status Detalhe Campos FY24'!$C$7:$C$736,'1. Status Resumo FY24'!$G$43,'2. Status Detalhe Campos FY24'!$D$7:$D$736,"2. Campo",'2. Status Detalhe Campos FY24'!$U$7:$U$736,"*Novo Plano*") +COUNTIFS('2. Status Detalhe Campos FY24'!$H$7:$H$736,'1. Status Resumo FY24'!$P72,'2. Status Detalhe Campos FY24'!$C$7:$C$736,'1. Status Resumo FY24'!$H$43,'2. Status Detalhe Campos FY24'!$D$7:$D$736,"2. Campo",'2. Status Detalhe Campos FY24'!$U$7:$U$736,"*Novo Plano*") -> 0 | U73: =COUNTIFS('2. Status Detalhe Campos FY24'!$G$7:$G$736,'1. Status Resumo FY24'!$P71,'2. Status Detalhe Campos FY24'!$C$7:$C$736,'1. Status Resumo FY24'!$G$43,'2. Status Detalhe Campos FY24'!$D$7:$D$736,"2. Campo",'2. Status Detalhe Campos FY24'!$U$7:$U$736,"*Novo Plano*") +COUNTIFS('2. Status Detalhe Campos FY24'!$G$7:$G$736,'1. Status Resumo FY24'!$P71,'2. Status Detalhe Campos FY24'!$C$7:$C$736,'1. Status Resumo FY24'!$H$43,'2. Status Detalhe Campos FY24'!$D$7:$D$736,"2. Campo",'2. Status Detalhe Campos FY24'!$U$7:$U$736,"*Novo Plano*") -> 0 | V73: =U73-T73 -> 0
P74: Total | T74: =+SUM(T47,T50,T53,T59,T62,T65,T68,T71,T56) -> 204 | U74: =+SUM(U47,U50,U53,U59,U62,U65,U68,U71,U56) -> 161 | V74: =+U74-T74 -> -43
P75: RequisItos FY24 | T75: =+SUM(T48,T51,T54,T57,T60,T63,T66,T69,T72) -> 204 | U75: =+SUM(U48,U51,U54,U57,U60,U63,U66,U69,U72) -> 160 | V75: =+U75-T75 -> -44
P76: Novos Requisitos FY25 | T76: =+SUM(T49,T52,T55,T58,T61,T64,T67,T70,T73) -> 0 | U76: =+SUM(U49,U52,U55,U58,U61,U64,U67,U70,U73) -> 0 | V76: =+U76-T76 -> 0
G78: Status (Tabelas) | P78: Status (Universos)
F79: > | G79: Tabela de Bens Imóveis | L79: OK | O79: > | P79: Universo Bens Colateralizados (MUG) | T79: OK
F80: > | G80: Tabelas de Processos Imobiliários | L80: OK | O80: > | P80: Universo Bens Não Colateralizados (GP) | T80: OK
F81: > | G81: Tabela de Traçabilidade Processo -Bem | L81: OK | O81: > | P81: Universo Bens Adjudicados | T81: Não serão testados neste projeto
F82: > | G82: Tabela de Traçabilidade Crédito - Processo | L82: OK
F83: > | G83: Tabela input de Cerificados Energéticos (Gloval) | L83: Em Implementação
F84: > | G84: Tabela Output de Cerificados Energéticos | L84: Em Implementação
B88: 2. Modelo Verde | G88: Modelo Verde - Input | H88: Modelo Verde - Output
C91: Resumo | G91: Detalhe por Tabela | P91: Status (campos) | T91: =T46 -> 45695 | U91: =U46 -> 45702 | V91: ∆ | X91: Highlights
P92: 0. Cancelado | T92: =COUNTIFS('2. Status Detalhe Campos FY24'!$H$7:$H$736,'1. Status Resumo FY24'!$P92,'2. Status Detalhe Campos FY24'!$C$7:$C$736,'1. Status Resumo FY24'!$G$88,'2. Status Detalhe Campos FY24'!$D$7:$D$736,"2. Campo")+COUNTIFS('2. Status Detalhe Campos FY24'!$H$7:$H$736,'1. Status Resumo FY24'!$P92,'2. Status Detalhe Campos FY24'!$C$7:$C$736,'1. Status Resumo FY24'!$H$88,'2. Status Detalhe Campos FY24'!$D$7:$D$736,"2. Campo") -> 16 | U92: =COUNTIFS('2. Status Detalhe Campos FY24'!$G$7:$G$736,'1. Status Resumo FY24'!$P92,'2. Status Detalhe Campos FY24'!$C$7:$C$736,'1. Status Resumo FY24'!$G$88,'2. Status Detalhe Campos FY24'!$D$7:$D$736,"2. Campo")+COUNTIFS('2. Status Detalhe Campos FY24'!$G$7:$G$736,'1. Status Resumo FY24'!$P92,'2. Status Detalhe Campos FY24'!$C$7:$C$736,'1. Status Resumo FY24'!$H$88,'2. Status Detalhe Campos FY24'!$D$7:$D$736,"2. Campo") -> 16 | V92: =U92-T92 -> 0 | X92: 1. Tabela de Input Marcação Verde: - Foi concluída e partilhada a especificação de todos campos (FY25) da tabela de Input de marcação verde. Os mesmos encontram-se agora em implementação pela equipa de Tecnologia. - Adicionalmente, foram realizadas reuniões com CdG de modo a ser alinhado a marcação verde. 2. Tabela de Output Marcação Verde: - Foram realizadas reuniões de modo a clarificar o mapeamento de 2 campos. Denote-se que estes 2 campos estão pendentes de validação por parte da corporação.
P93: Requisitos FY24 | T93: =COUNTIFS('2. Status Detalhe Campos FY24'!$H$7:$H$736,'1. Status Resumo FY24'!$P92,'2. Status Detalhe Campos FY24'!$C$7:$C$736,'1. Status Resumo FY24'!$G$88,'2. Status Detalhe Campos FY24'!$D$7:$D$736,"2. Campo",'2. Status Detalhe Campos FY24'!$U$7:$U$736,"*Plano anterior*") +COUNTIFS('2. Status Detalhe Campos FY24'!$H$7:$H$736,'1. Status Resumo FY24'!$P92,'2. Status Detalhe Campos FY24'!$C$7:$C$736,'1. Status Resumo FY24'!$H$88,'2. Status Detalhe Campos FY24'!$D$7:$D$736,"2. Campo",'2. Status Detalhe Campos FY24'!$U$7:$U$736,"*Plano anterior*") -> 16 | U93: =COUNTIFS('2. Status Detalhe Campos FY24'!$G$7:$G$736,'1. Status Resumo FY24'!$P92,'2. Status Detalhe Campos FY24'!$C$7:$C$736,'1. Status Resumo FY24'!$G$88,'2. Status Detalhe Campos FY24'!$D$7:$D$736,"2. Campo",'2. Status Detalhe Campos FY24'!$U$7:$U$736,"*Plano anterior*") +COUNTIFS('2. Status Detalhe Campos FY24'!$G$7:$G$736,'1. Status Resumo FY24'!$P92,'2. Status Detalhe Campos FY24'!$C$7:$C$736,'1. Status Resumo FY24'!$H$88,'2. Status Detalhe Campos FY24'!$D$7:$D$736,"2. Campo",'2. Status Detalhe Campos FY24'!$U$7:$U$736,"*Plano anterior*") -> 16 | V93: =U93-T93 -> 0
P94: Novos Requisitos FY25 | T94: =COUNTIFS('2. Status Detalhe Campos FY24'!$H$7:$H$736,'1. Status Resumo FY24'!$P92,'2. Status Detalhe Campos FY24'!$C$7:$C$736,'1. Status Resumo FY24'!$G$88,'2. Status Detalhe Campos FY24'!$D$7:$D$736,"2. Campo",'2. Status Detalhe Campos FY24'!$U$7:$U$736,"*Novo Plano*") +COUNTIFS('2. Status Detalhe Campos FY24'!$H$7:$H$736,'1. Status Resumo FY24'!$P92,'2. Status Detalhe Campos FY24'!$C$7:$C$736,'1. Status Resumo FY24'!$H$88,'2. Status Detalhe Campos FY24'!$D$7:$D$736,"2. Campo",'2. Status Detalhe Campos FY24'!$U$7:$U$736,"*Novo Plano*") -> 0 | U94: =COUNTIFS('2. Status Detalhe Campos FY24'!$G$7:$G$736,'1. Status Resumo FY24'!$P92,'2. Status Detalhe Campos FY24'!$C$7:$C$736,'1. Status Resumo FY24'!$G$88,'2. Status Detalhe Campos FY24'!$D$7:$D$736,"2. Campo",'2. Status Detalhe Campos FY24'!$U$7:$U$736,"*Novo Plano*") +COUNTIFS('2. Status Detalhe Campos FY24'!$G$7:$G$736,'1. Status Resumo FY24'!$P92,'2. Status Detalhe Campos FY24'!$C$7:$C$736,'1. Status Resumo FY24'!$H$88,'2. Status Detalhe Campos FY24'!$D$7:$D$736,"2. Campo",'2. Status Detalhe Campos FY24'!$U$7:$U$736,"*Novo Plano*") -> 0 | V94: =U94-T94 -> 0
P95: 1. Concluído | T95: =COUNTIFS('2. Status Detalhe Campos FY24'!$H$7:$H$736,'1. Status Resumo FY24'!$P95,'2. Status Detalhe Campos FY24'!$C$7:$C$736,'1. Status Resumo FY24'!$G$88,'2. Status Detalhe Campos FY24'!$D$7:$D$736,"2. Campo")+COUNTIFS('2. Status Detalhe Campos FY24'!$H$7:$H$736,'1. Status Resumo FY24'!$P95,'2. Status Detalhe Campos FY24'!$C$7:$C$736,'1. Status Resumo FY24'!$H$88,'2. Status Detalhe Campos FY24'!$D$7:$D$736,"2. Campo") -> 185 | U95: =COUNTIFS('2. Status Detalhe Campos FY24'!$G$7:$G$736,'1. Status Resumo FY24'!$P95,'2. Status Detalhe Campos FY24'!$C$7:$C$736,'1. Status Resumo FY24'!$G$88,'2. Status Detalhe Campos FY24'!$D$7:$D$736,"2. Campo")+COUNTIFS('2. Status Detalhe Campos FY24'!$G$7:$G$736,'1. Status Resumo FY24'!$P95,'2. Status Detalhe Campos FY24'!$C$7:$C$736,'1. Status Resumo FY24'!$H$88,'2. Status Detalhe Campos FY24'!$D$7:$D$736,"2. Campo") -> 204 | V95: =U95-T95 -> 19
P96: Requisitos FY24 | T96: =COUNTIFS('2. Status Detalhe Campos FY24'!$H$7:$H$736,'1. Status Resumo FY24'!$P95,'2. Status Detalhe Campos FY24'!$C$7:$C$736,'1. Status Resumo FY24'!$G$88,'2. Status Detalhe Campos FY24'!$D$7:$D$736,"2. Campo",'2. Status Detalhe Campos FY24'!$U$7:$U$736,"*Plano anterior*") +COUNTIFS('2. Status Detalhe Campos FY24'!$H$7:$H$736,'1. Status Resumo FY24'!$P95,'2. Status Detalhe Campos FY24'!$C$7:$C$736,'1. Status Resumo FY24'!$H$88,'2. Status Detalhe Campos FY24'!$D$7:$D$736,"2. Campo",'2. Status Detalhe Campos FY24'!$U$7:$U$736,"*Plano anterior*") -> 185 | U96: =COUNTIFS('2. Status Detalhe Campos FY24'!$G$7:$G$736,'1. Status Resumo FY24'!$P95,'2. Status Detalhe Campos FY24'!$C$7:$C$736,'1. Status Resumo FY24'!$G$88,'2. Status Detalhe Campos FY24'!$D$7:$D$736,"2. Campo",'2. Status Detalhe Campos FY24'!$U$7:$U$736,"*Plano anterior*") +COUNTIFS('2. Status Detalhe Campos FY24'!$G$7:$G$736,'1. Status Resumo FY24'!$P95,'2. Status Detalhe Campos FY24'!$C$7:$C$736,'1. Status Resumo FY24'!$H$88,'2. Status Detalhe Campos FY24'!$D$7:$D$736,"2. Campo",'2. Status Detalhe Campos FY24'!$U$7:$U$736,"*Plano anterior*") -> 184 | V96: =U96-T96 -> -1
P97: Novos Requisitos FY25 | T97: =COUNTIFS('2. Status Detalhe Campos FY24'!$H$7:$H$736,'1. Status Resumo FY24'!$P95,'2. Status Detalhe Campos FY24'!$C$7:$C$736,'1. Status Resumo FY24'!$G$88,'2. Status Detalhe Campos FY24'!$D$7:$D$736,"2. Campo",'2. Status Detalhe Campos FY24'!$U$7:$U$736,"*Novo Plano*") +COUNTIFS('2. Status Detalhe Campos FY24'!$H$7:$H$736,'1. Status Resumo FY24'!$P95,'2. Status Detalhe Campos FY24'!$C$7:$C$736,'1. Status Resumo FY24'!$H$88,'2. Status Detalhe Campos FY24'!$D$7:$D$736,"2. Campo",'2. Status Detalhe Campos FY24'!$U$7:$U$736,"*Novo Plano*") -> 0 | U97: =COUNTIFS('2. Status Detalhe Campos FY24'!$G$7:$G$736,'1. Status Resumo FY24'!$P95,'2. Status Detalhe Campos FY24'!$C$7:$C$736,'1. Status Resumo FY24'!$G$88,'2. Status Detalhe Campos FY24'!$D$7:$D$736,"2. Campo",'2. Status Detalhe Campos FY24'!$U$7:$U$736,"*Novo Plano*") +COUNTIFS('2. Status Detalhe Campos FY24'!$G$7:$G$736,'1. Status Resumo FY24'!$P95,'2. Status Detalhe Campos FY24'!$C$7:$C$736,'1. Status Resumo FY24'!$H$88,'2. Status Detalhe Campos FY24'!$D$7:$D$736,"2. Campo",'2. Status Detalhe Campos FY24'!$U$7:$U$736,"*Novo Plano*") -> 20 | V97: =U97-T97 -> 20
P98: 2.1 Em Teste | T98: =COUNTIFS('2. Status Detalhe Campos FY24'!$H$7:$H$736,'1. Status Resumo FY24'!$P98,'2. Status Detalhe Campos FY24'!$C$7:$C$736,'1. Status Resumo FY24'!$G$88,'2. Status Detalhe Campos FY24'!$D$7:$D$736,"2. Campo")+COUNTIFS('2. Status Detalhe Campos FY24'!$H$7:$H$736,'1. Status Resumo FY24'!$P98,'2. Status Detalhe Campos FY24'!$C$7:$C$736,'1. Status Resumo FY24'!$H$88,'2. Status Detalhe Campos FY24'!$D$7:$D$736,"2. Campo") -> 26 | U98: =COUNTIFS('2. Status Detalhe Campos FY24'!$G$7:$G$736,'1. Status Resumo FY24'!$P98,'2. Status Detalhe Campos FY24'!$C$7:$C$736,'1. Status Resumo FY24'!$G$88,'2. Status Detalhe Campos FY24'!$D$7:$D$736,"2. Campo")+COUNTIFS('2. Status Detalhe Campos FY24'!$G$7:$G$736,'1. Status Resumo FY24'!$P98,'2. Status Detalhe Campos FY24'!$C$7:$C$736,'1. Status Resumo FY24'!$H$88,'2. Status Detalhe Campos FY24'!$D$7:$D$736,"2. Campo") -> 6 | V98: =U98-T98 -> -20
P99: Requisitos FY24 | T99: =COUNTIFS('2. Status Detalhe Campos FY24'!$H$7:$H$736,'1. Status Resumo FY24'!$P98,'2. Status Detalhe Campos FY24'!$C$7:$C$736,'1. Status Resumo FY24'!$G$88,'2. Status Detalhe Campos FY24'!$D$7:$D$736,"2. Campo",'2. Status Detalhe Campos FY24'!$U$7:$U$736,"*Plano anterior*") +COUNTIFS('2. Status Detalhe Campos FY24'!$H$7:$H$736,'1. Status Resumo FY24'!$P98,'2. Status Detalhe Campos FY24'!$C$7:$C$736,'1. Status Resumo FY24'!$H$88,'2. Status Detalhe Campos FY24'!$D$7:$D$736,"2. Campo",'2. Status Detalhe Campos FY24'!$U$7:$U$736,"*Plano anterior*") -> 6 | U99: =COUNTIFS('2. Status Detalhe Campos FY24'!$G$7:$G$736,'1. Status Resumo FY24'!$P98,'2. Status Detalhe Campos FY24'!$C$7:$C$736,'1. Status Resumo FY24'!$G$88,'2. Status Detalhe Campos FY24'!$D$7:$D$736,"2. Campo",'2. Status Detalhe Campos FY24'!$U$7:$U$736,"*Plano anterior*") +COUNTIFS('2. Status Detalhe Campos FY24'!$G$7:$G$736,'1. Status Resumo FY24'!$P98,'2. Status Detalhe Campos FY24'!$C$7:$C$736,'1. Status Resumo FY24'!$H$88,'2. Status Detalhe Campos FY24'!$D$7:$D$736,"2. Campo",'2. Status Detalhe Campos FY24'!$U$7:$U$736,"*Plano anterior*") -> 6 | V99: =U99-T99 -> 0
P100: Novos Requisitos FY25 | T100: =COUNTIFS('2. Status Detalhe Campos FY24'!$H$7:$H$736,'1. Status Resumo FY24'!$P98,'2. Status Detalhe Campos FY24'!$C$7:$C$736,'1. Status Resumo FY24'!$G$88,'2. Status Detalhe Campos FY24'!$D$7:$D$736,"2. Campo",'2. Status Detalhe Campos FY24'!$U$7:$U$736,"*Novo Plano*") +COUNTIFS('2. Status Detalhe Campos FY24'!$H$7:$H$736,'1. Status Resumo FY24'!$P98,'2. Status Detalhe Campos FY24'!$C$7:$C$736,'1. Status Resumo FY24'!$H$88,'2. Status Detalhe Campos FY24'!$D$7:$D$736,"2. Campo",'2. Status Detalhe Campos FY24'!$U$7:$U$736,"*Novo Plano*") -> 20 | U100: =COUNTIFS('2. Status Detalhe Campos FY24'!$G$7:$G$736,'1. Status Resumo FY24'!$P98,'2. Status Detalhe Campos FY24'!$C$7:$C$736,'1. Status Resumo FY24'!$G$88,'2. Status Detalhe Campos FY24'!$D$7:$D$736,"2. Campo",'2. Status Detalhe Campos FY24'!$U$7:$U$736,"*Novo Plano*") +COUNTIFS('2. Status Detalhe Campos FY24'!$G$7:$G$736,'1. Status Resumo FY24'!$P98,'2. Status Detalhe Campos FY24'!$C$7:$C$736,'1. Status Resumo FY24'!$H$88,'2. Status Detalhe Campos FY24'!$D$7:$D$736,"2. Campo",'2. Status Detalhe Campos FY24'!$U$7:$U$736,"*Novo Plano*") -> 0 | V100: =U100-T100 -> -20
P101: 2.2 Em especificação | T101: =COUNTIFS('2. Status Detalhe Campos FY24'!$H$7:$H$736,'1. Status Resumo FY24'!$P101,'2. Status Detalhe Campos FY24'!$C$7:$C$736,'1. Status Resumo FY24'!$G$88,'2. Status Detalhe Campos FY24'!$D$7:$D$736,"2. Campo")+COUNTIFS('2. Status Detalhe Campos FY24'!$H$7:$H$736,'1. Status Resumo FY24'!$P101,'2. Status Detalhe Campos FY24'!$C$7:$C$736,'1. Status Resumo FY24'!$H$88,'2. Status Detalhe Campos FY24'!$D$7:$D$736,"2. Campo") -> 56 | U101: =COUNTIFS('2. Status Detalhe Campos FY24'!$G$7:$G$736,'1. Status Resumo FY24'!$P101,'2. Status Detalhe Campos FY24'!$C$7:$C$736,'1. Status Resumo FY24'!$G$88,'2. Status Detalhe Campos FY24'!$D$7:$D$736,"2. Campo")+COUNTIFS('2. Status Detalhe Campos FY24'!$G$7:$G$736,'1. Status Resumo FY24'!$P101,'2. Status Detalhe Campos FY24'!$C$7:$C$736,'1. Status Resumo FY24'!$H$88,'2. Status Detalhe Campos FY24'!$D$7:$D$736,"2. Campo") -> 1 | V101: =U101-T101 -> -55
P102: Requisitos FY24 | T102: =COUNTIFS('2. Status Detalhe Campos FY24'!$H$7:$H$736,'1. Status Resumo FY24'!$P101,'2. Status Detalhe Campos FY24'!$C$7:$C$736,'1. Status Resumo FY24'!$G$88,'2. Status Detalhe Campos FY24'!$D$7:$D$736,"2. Campo",'2. Status Detalhe Campos FY24'!$U$7:$U$736,"*Plano anterior*") +COUNTIFS('2. Status Detalhe Campos FY24'!$H$7:$H$736,'1. Status Resumo FY24'!$P101,'2. Status Detalhe Campos FY24'!$C$7:$C$736,'1. Status Resumo FY24'!$H$88,'2. Status Detalhe Campos FY24'!$D$7:$D$736,"2. Campo",'2. Status Detalhe Campos FY24'!$U$7:$U$736,"*Plano anterior*") -> 55 | U102: =COUNTIFS('2. Status Detalhe Campos FY24'!$G$7:$G$736,'1. Status Resumo FY24'!$P101,'2. Status Detalhe Campos FY24'!$C$7:$C$736,'1. Status Resumo FY24'!$G$88,'2. Status Detalhe Campos FY24'!$D$7:$D$736,"2. Campo",'2. Status Detalhe Campos FY24'!$U$7:$U$736,"*Plano anterior*") +COUNTIFS('2. Status Detalhe Campos FY24'!$G$7:$G$736,'1. Status Resumo FY24'!$P101,'2. Status Detalhe Campos FY24'!$C$7:$C$736,'1. Status Resumo FY24'!$H$88,'2. Status Detalhe Campos FY24'!$D$7:$D$736,"2. Campo",'2. Status Detalhe Campos FY24'!$U$7:$U$736,"*Plano anterior*") -> 0 | V102: =U102-T102 -> -55
P103: Novos Requisitos FY25 | T103: =COUNTIFS('2. Status Detalhe Campos FY24'!$H$7:$H$736,'1. Status Resumo FY24'!$P101,'2. Status Detalhe Campos FY24'!$C$7:$C$736,'1. Status Resumo FY24'!$G$88,'2. Status Detalhe Campos FY24'!$D$7:$D$736,"2. Campo",'2. Status Detalhe Campos FY24'!$U$7:$U$736,"*Novo Plano*") +COUNTIFS('2. Status Detalhe Campos FY24'!$H$7:$H$736,'1. Status Resumo FY24'!$P101,'2. Status Detalhe Campos FY24'!$C$7:$C$736,'1. Status Resumo FY24'!$H$88,'2. Status Detalhe Campos FY24'!$D$7:$D$736,"2. Campo",'2. Status Detalhe Campos FY24'!$U$7:$U$736,"*Novo Plano*") -> 0 | U103: =COUNTIFS('2. Status Detalhe Campos FY24'!$G$7:$G$736,'1. Status Resumo FY24'!$P101,'2. Status Detalhe Campos FY24'!$C$7:$C$736,'1. Status Resumo FY24'!$G$88,'2. Status Detalhe Campos FY24'!$D$7:$D$736,"2. Campo",'2. Status Detalhe Campos FY24'!$U$7:$U$736,"*Novo Plano*") +COUNTIFS('2. Status Detalhe Campos FY24'!$G$7:$G$736,'1. Status Resumo FY24'!$P101,'2. Status Detalhe Campos FY24'!$C$7:$C$736,'1. Status Resumo FY24'!$H$88,'2. Status Detalhe Campos FY24'!$D$7:$D$736,"2. Campo",'2. Status Detalhe Campos FY24'!$U$7:$U$736,"*Novo Plano*") -> 0 | V103: =U103-T103 -> 0
P104: 3. Pendente de outros desenvolvimentos | T104: =COUNTIFS('2. Status Detalhe Campos FY24'!$H$7:$H$736,'1. Status Resumo FY24'!$P104,'2. Status Detalhe Campos FY24'!$C$7:$C$736,'1. Status Resumo FY24'!$G$88,'2. Status Detalhe Campos FY24'!$D$7:$D$736,"2. Campo")+COUNTIFS('2. Status Detalhe Campos FY24'!$H$7:$H$736,'1. Status Resumo FY24'!$P104,'2. Status Detalhe Campos FY24'!$C$7:$C$736,'1. Status Resumo FY24'!$H$88,'2. Status Detalhe Campos FY24'!$D$7:$D$736,"2. Campo") -> 0 | U104: =COUNTIFS('2. Status Detalhe Campos FY24'!$G$7:$G$736,'1. Status Resumo FY24'!$P104,'2. Status Detalhe Campos FY24'!$C$7:$C$736,'1. Status Resumo FY24'!$G$88,'2. Status Detalhe Campos FY24'!$D$7:$D$736,"2. Campo")+COUNTIFS('2. Status Detalhe Campos FY24'!$G$7:$G$736,'1. Status Resumo FY24'!$P104,'2. Status Detalhe Campos FY24'!$C$7:$C$736,'1. Status Resumo FY24'!$H$88,'2. Status Detalhe Campos FY24'!$D$7:$D$736,"2. Campo") -> 0 | V104: =U104-T104 -> 0
E105: =+"#"&$U$119 -> #300 | P105: Requisitos FY24 | T105: =COUNTIFS('2. Status Detalhe Campos FY24'!$H$7:$H$736,'1. Status Resumo FY24'!$P104,'2. Status Detalhe Campos FY24'!$C$7:$C$736,'1. Status Resumo FY24'!$G$88,'2. Status Detalhe Campos FY24'!$D$7:$D$736,"2. Campo",'2. Status Detalhe Campos FY24'!$U$7:$U$736,"*Plano anterior*") +COUNTIFS('2. Status Detalhe Campos FY24'!$H$7:$H$736,'1. Status Resumo FY24'!$P104,'2. Status Detalhe Campos FY24'!$C$7:$C$736,'1. Status Resumo FY24'!$H$88,'2. Status Detalhe Campos FY24'!$D$7:$D$736,"2. Campo",'2. Status Detalhe Campos FY24'!$U$7:$U$736,"*Plano anterior*") -> 0 | U105: =COUNTIFS('2. Status Detalhe Campos FY24'!$G$7:$G$736,'1. Status Resumo FY24'!$P104,'2. Status Detalhe Campos FY24'!$C$7:$C$736,'1. Status Resumo FY24'!$G$88,'2. Status Detalhe Campos FY24'!$D$7:$D$736,"2. Campo",'2. Status Detalhe Campos FY24'!$U$7:$U$736,"*Plano anterior*") +COUNTIFS('2. Status Detalhe Campos FY24'!$G$7:$G$736,'1. Status Resumo FY24'!$P104,'2. Status Detalhe Campos FY24'!$C$7:$C$736,'1. Status Resumo FY24'!$H$88,'2. Status Detalhe Campos FY24'!$D$7:$D$736,"2. Campo",'2. Status Detalhe Campos FY24'!$U$7:$U$736,"*Plano anterior*") -> 0 | V105: =U105-T105 -> 0
P106: Novos Requisitos FY25 | T106: =COUNTIFS('2. Status Detalhe Campos FY24'!$H$7:$H$736,'1. Status Resumo FY24'!$P104,'2. Status Detalhe Campos FY24'!$C$7:$C$736,'1. Status Resumo FY24'!$G$88,'2. Status Detalhe Campos FY24'!$D$7:$D$736,"2. Campo",'2. Status Detalhe Campos FY24'!$U$7:$U$736,"*Novo Plano*") +COUNTIFS('2. Status Detalhe Campos FY24'!$H$7:$H$736,'1. Status Resumo FY24'!$P104,'2. Status Detalhe Campos FY24'!$C$7:$C$736,'1. Status Resumo FY24'!$H$88,'2. Status Detalhe Campos FY24'!$D$7:$D$736,"2. Campo",'2. Status Detalhe Campos FY24'!$U$7:$U$736,"*Novo Plano*") -> 0 | U106: =COUNTIFS('2. Status Detalhe Campos FY24'!$G$7:$G$736,'1. Status Resumo FY24'!$P104,'2. Status Detalhe Campos FY24'!$C$7:$C$736,'1. Status Resumo FY24'!$G$88,'2. Status Detalhe Campos FY24'!$D$7:$D$736,"2. Campo",'2. Status Detalhe Campos FY24'!$U$7:$U$736,"*Novo Plano*") +COUNTIFS('2. Status Detalhe Campos FY24'!$G$7:$G$736,'1. Status Resumo FY24'!$P104,'2. Status Detalhe Campos FY24'!$C$7:$C$736,'1. Status Resumo FY24'!$H$88,'2. Status Detalhe Campos FY24'!$D$7:$D$736,"2. Campo",'2. Status Detalhe Campos FY24'!$U$7:$U$736,"*Novo Plano*") -> 0 | V106: =U106-T106 -> 0
P107: 4. Validação EF | T107: =COUNTIFS('2. Status Detalhe Campos FY24'!$H$7:$H$736,'1. Status Resumo FY24'!$P107,'2. Status Detalhe Campos FY24'!$C$7:$C$736,'1. Status Resumo FY24'!$G$88,'2. Status Detalhe Campos FY24'!$D$7:$D$736,"2. Campo")+COUNTIFS('2. Status Detalhe Campos FY24'!$H$7:$H$736,'1. Status Resumo FY24'!$P107,'2. Status Detalhe Campos FY24'!$C$7:$C$736,'1. Status Resumo FY24'!$H$88,'2. Status Detalhe Campos FY24'!$D$7:$D$736,"2. Campo") -> 0 | U107: =COUNTIFS('2. Status Detalhe Campos FY24'!$G$7:$G$736,'1. Status Resumo FY24'!$P107,'2. Status Detalhe Campos FY24'!$C$7:$C$736,'1. Status Resumo FY24'!$G$88,'2. Status Detalhe Campos FY24'!$D$7:$D$736,"2. Campo")+COUNTIFS('2. Status Detalhe Campos FY24'!$G$7:$G$736,'1. Status Resumo FY24'!$P107,'2. Status Detalhe Campos FY24'!$C$7:$C$736,'1. Status Resumo FY24'!$H$88,'2. Status Detalhe Campos FY24'!$D$7:$D$736,"2. Campo") -> 0 | V107: =U107-T107 -> 0
P108: Requisitos FY24 | T108: =COUNTIFS('2. Status Detalhe Campos FY24'!$H$7:$H$736,'1. Status Resumo FY24'!$P107,'2. Status Detalhe Campos FY24'!$C$7:$C$736,'1. Status Resumo FY24'!$G$88,'2. Status Detalhe Campos FY24'!$D$7:$D$736,"2. Campo",'2. Status Detalhe Campos FY24'!$U$7:$U$736,"*Plano anterior*") +COUNTIFS('2. Status Detalhe Campos FY24'!$H$7:$H$736,'1. Status Resumo FY24'!$P107,'2. Status Detalhe Campos FY24'!$C$7:$C$736,'1. Status Resumo FY24'!$H$88,'2. Status Detalhe Campos FY24'!$D$7:$D$736,"2. Campo",'2. Status Detalhe Campos FY24'!$U$7:$U$736,"*Plano anterior*") -> 0 | U108: =COUNTIFS('2. Status Detalhe Campos FY24'!$G$7:$G$736,'1. Status Resumo FY24'!$P107,'2. Status Detalhe Campos FY24'!$C$7:$C$736,'1. Status Resumo FY24'!$G$88,'2. Status Detalhe Campos FY24'!$D$7:$D$736,"2. Campo",'2. Status Detalhe Campos FY24'!$U$7:$U$736,"*Plano anterior*") +COUNTIFS('2. Status Detalhe Campos FY24'!$G$7:$G$736,'1. Status Resumo FY24'!$P107,'2. Status Detalhe Campos FY24'!$C$7:$C$736,'1. Status Resumo FY24'!$H$88,'2. Status Detalhe Campos FY24'!$D$7:$D$736,"2. Campo",'2. Status Detalhe Campos FY24'!$U$7:$U$736,"*Plano anterior*") -> 0 | V108: =U108-T108 -> 0
P109: Novos Requisitos FY25 | T109: =COUNTIFS('2. Status Detalhe Campos FY24'!$H$7:$H$736,'1. Status Resumo FY24'!$P107,'2. Status Detalhe Campos FY24'!$C$7:$C$736,'1. Status Resumo FY24'!$G$88,'2. Status Detalhe Campos FY24'!$D$7:$D$736,"2. Campo",'2. Status Detalhe Campos FY24'!$U$7:$U$736,"*Novo Plano*") +COUNTIFS('2. Status Detalhe Campos FY24'!$H$7:$H$736,'1. Status Resumo FY24'!$P107,'2. Status Detalhe Campos FY24'!$C$7:$C$736,'1. Status Resumo FY24'!$H$88,'2. Status Detalhe Campos FY24'!$D$7:$D$736,"2. Campo",'2. Status Detalhe Campos FY24'!$U$7:$U$736,"*Novo Plano*") -> 0 | U109: =COUNTIFS('2. Status Detalhe Campos FY24'!$G$7:$G$736,'1. Status Resumo FY24'!$P107,'2. Status Detalhe Campos FY24'!$C$7:$C$736,'1. Status Resumo FY24'!$G$88,'2. Status Detalhe Campos FY24'!$D$7:$D$736,"2. Campo",'2. Status Detalhe Campos FY24'!$U$7:$U$736,"*Novo Plano*") +COUNTIFS('2. Status Detalhe Campos FY24'!$G$7:$G$736,'1. Status Resumo FY24'!$P107,'2. Status Detalhe Campos FY24'!$C$7:$C$736,'1. Status Resumo FY24'!$H$88,'2. Status Detalhe Campos FY24'!$D$7:$D$736,"2. Campo",'2. Status Detalhe Campos FY24'!$U$7:$U$736,"*Novo Plano*") -> 0 | V109: =U109-T109 -> 0
P110: 5. Em Correção | R110: (incidências) | T110: =COUNTIFS('2. Status Detalhe Campos FY24'!$H$7:$H$736,'1. Status Resumo FY24'!$P110,'2. Status Detalhe Campos FY24'!$C$7:$C$736,'1. Status Resumo FY24'!$G$88,'2. Status Detalhe Campos FY24'!$D$7:$D$736,"2. Campo")+COUNTIFS('2. Status Detalhe Campos FY24'!$H$7:$H$736,'1. Status Resumo FY24'!$P110,'2. Status Detalhe Campos FY24'!$C$7:$C$736,'1. Status Resumo FY24'!$H$88,'2. Status Detalhe Campos FY24'!$D$7:$D$736,"2. Campo") -> 0 | U110: =COUNTIFS('2. Status Detalhe Campos FY24'!$G$7:$G$736,'1. Status Resumo FY24'!$P110,'2. Status Detalhe Campos FY24'!$C$7:$C$736,'1. Status Resumo FY24'!$G$88,'2. Status Detalhe Campos FY24'!$D$7:$D$736,"2. Campo")+COUNTIFS('2. Status Detalhe Campos FY24'!$G$7:$G$736,'1. Status Resumo FY24'!$P110,'2. Status Detalhe Campos FY24'!$C$7:$C$736,'1. Status Resumo FY24'!$H$88,'2. Status Detalhe Campos FY24'!$D$7:$D$736,"2. Campo") -> 0 | V110: =U110-T110 -> 0
P111: Requisitos FY24 | T111: =COUNTIFS('2. Status Detalhe Campos FY24'!$H$7:$H$736,'1. Status Resumo FY24'!$P110,'2. Status Detalhe Campos FY24'!$C$7:$C$736,'1. Status Resumo FY24'!$G$88,'2. Status Detalhe Campos FY24'!$D$7:$D$736,"2. Campo",'2. Status Detalhe Campos FY24'!$U$7:$U$736,"*Plano anterior*") +COUNTIFS('2. Status Detalhe Campos FY24'!$H$7:$H$736,'1. Status Resumo FY24'!$P110,'2. Status Detalhe Campos FY24'!$C$7:$C$736,'1. Status Resumo FY24'!$H$88,'2. Status Detalhe Campos FY24'!$D$7:$D$736,"2. Campo",'2. Status Detalhe Campos FY24'!$U$7:$U$736,"*Plano anterior*") -> 0 | U111: =COUNTIFS('2. Status Detalhe Campos FY24'!$G$7:$G$736,'1. Status Resumo FY24'!$P110,'2. Status Detalhe Campos FY24'!$C$7:$C$736,'1. Status Resumo FY24'!$G$88,'2. Status Detalhe Campos FY24'!$D$7:$D$736,"2. Campo",'2. Status Detalhe Campos FY24'!$U$7:$U$736,"*Plano anterior*") +COUNTIFS('2. Status Detalhe Campos FY24'!$G$7:$G$736,'1. Status Resumo FY24'!$P110,'2. Status Detalhe Campos FY24'!$C$7:$C$736,'1. Status Resumo FY24'!$H$88,'2. Status Detalhe Campos FY24'!$D$7:$D$736,"2. Campo",'2. Status Detalhe Campos FY24'!$U$7:$U$736,"*Plano anterior*") -> 0 | V111: =U111-T111 -> 0
P112: Novos Requisitos FY25 | T112: =COUNTIFS('2. Status Detalhe Campos FY24'!$H$7:$H$736,'1. Status Resumo FY24'!$P110,'2. Status Detalhe Campos FY24'!$C$7:$C$736,'1. Status Resumo FY24'!$G$88,'2. Status Detalhe Campos FY24'!$D$7:$D$736,"2. Campo",'2. Status Detalhe Campos FY24'!$U$7:$U$736,"*Novo Plano*") +COUNTIFS('2. Status Detalhe Campos FY24'!$H$7:$H$736,'1. Status Resumo FY24'!$P110,'2. Status Detalhe Campos FY24'!$C$7:$C$736,'1. Status Resumo FY24'!$H$88,'2. Status Detalhe Campos FY24'!$D$7:$D$736,"2. Campo",'2. Status Detalhe Campos FY24'!$U$7:$U$736,"*Novo Plano*") -> 0 | U112: =COUNTIFS('2. Status Detalhe Campos FY24'!$G$7:$G$736,'1. Status Resumo FY24'!$P110,'2. Status Detalhe Campos FY24'!$C$7:$C$736,'1. Status Resumo FY24'!$G$88,'2. Status Detalhe Campos FY24'!$D$7:$D$736,"2. Campo",'2. Status Detalhe Campos FY24'!$U$7:$U$736,"*Novo Plano*") +COUNTIFS('2. Status Detalhe Campos FY24'!$G$7:$G$736,'1. Status Resumo FY24'!$P110,'2. Status Detalhe Campos FY24'!$C$7:$C$736,'1. Status Resumo FY24'!$H$88,'2. Status Detalhe Campos FY24'!$D$7:$D$736,"2. Campo",'2. Status Detalhe Campos FY24'!$U$7:$U$736,"*Novo Plano*") -> 0 | V112: =U112-T112 -> 0
P113: 6. Em implementação | T113: =COUNTIFS('2. Status Detalhe Campos FY24'!$H$7:$H$736,'1. Status Resumo FY24'!$P113,'2. Status Detalhe Campos FY24'!$C$7:$C$736,'1. Status Resumo FY24'!$G$88,'2. Status Detalhe Campos FY24'!$D$7:$D$736,"2. Campo")+COUNTIFS('2. Status Detalhe Campos FY24'!$H$7:$H$736,'1. Status Resumo FY24'!$P113,'2. Status Detalhe Campos FY24'!$C$7:$C$736,'1. Status Resumo FY24'!$H$88,'2. Status Detalhe Campos FY24'!$D$7:$D$736,"2. Campo") -> 14 | U113: =COUNTIFS('2. Status Detalhe Campos FY24'!$G$7:$G$736,'1. Status Resumo FY24'!$P113,'2. Status Detalhe Campos FY24'!$C$7:$C$736,'1. Status Resumo FY24'!$G$88,'2. Status Detalhe Campos FY24'!$D$7:$D$736,"2. Campo")+COUNTIFS('2. Status Detalhe Campos FY24'!$G$7:$G$736,'1. Status Resumo FY24'!$P113,'2. Status Detalhe Campos FY24'!$C$7:$C$736,'1. Status Resumo FY24'!$H$88,'2. Status Detalhe Campos FY24'!$D$7:$D$736,"2. Campo") -> 73 | V113: =U113-T113 -> 59
P114: Requisitos FY24 | T114: =COUNTIFS('2. Status Detalhe Campos FY24'!$H$7:$H$736,'1. Status Resumo FY24'!$P113,'2. Status Detalhe Campos FY24'!$C$7:$C$736,'1. Status Resumo FY24'!$G$88,'2. Status Detalhe Campos FY24'!$D$7:$D$736,"2. Campo",'2. Status Detalhe Campos FY24'!$U$7:$U$736,"*Plano anterior*") +COUNTIFS('2. Status Detalhe Campos FY24'!$H$7:$H$736,'1. Status Resumo FY24'!$P113,'2. Status Detalhe Campos FY24'!$C$7:$C$736,'1. Status Resumo FY24'!$H$88,'2. Status Detalhe Campos FY24'!$D$7:$D$736,"2. Campo",'2. Status Detalhe Campos FY24'!$U$7:$U$736,"*Plano anterior*") -> 9 | U114: =COUNTIFS('2. Status Detalhe Campos FY24'!$G$7:$G$736,'1. Status Resumo FY24'!$P113,'2. Status Detalhe Campos FY24'!$C$7:$C$736,'1. Status Resumo FY24'!$G$88,'2. Status Detalhe Campos FY24'!$D$7:$D$736,"2. Campo",'2. Status Detalhe Campos FY24'!$U$7:$U$736,"*Plano anterior*") +COUNTIFS('2. Status Detalhe Campos FY24'!$G$7:$G$736,'1. Status Resumo FY24'!$P113,'2. Status Detalhe Campos FY24'!$C$7:$C$736,'1. Status Resumo FY24'!$H$88,'2. Status Detalhe Campos FY24'!$D$7:$D$736,"2. Campo",'2. Status Detalhe Campos FY24'!$U$7:$U$736,"*Plano anterior*") -> 65 | V114: =U114-T114 -> 56
P115: Novos Requisitos FY25 | T115: =COUNTIFS('2. Status Detalhe Campos FY24'!$H$7:$H$736,'1. Status Resumo FY24'!$P113,'2. Status Detalhe Campos FY24'!$C$7:$C$736,'1. Status Resumo FY24'!$G$88,'2. Status Detalhe Campos FY24'!$D$7:$D$736,"2. Campo",'2. Status Detalhe Campos FY24'!$U$7:$U$736,"*Novo Plano*") +COUNTIFS('2. Status Detalhe Campos FY24'!$H$7:$H$736,'1. Status Resumo FY24'!$P113,'2. Status Detalhe Campos FY24'!$C$7:$C$736,'1. Status Resumo FY24'!$H$88,'2. Status Detalhe Campos FY24'!$D$7:$D$736,"2. Campo",'2. Status Detalhe Campos FY24'!$U$7:$U$736,"*Novo Plano*") -> 5 | U115: =COUNTIFS('2. Status Detalhe Campos FY24'!$G$7:$G$736,'1. Status Resumo FY24'!$P113,'2. Status Detalhe Campos FY24'!$C$7:$C$736,'1. Status Resumo FY24'!$G$88,'2. Status Detalhe Campos FY24'!$D$7:$D$736,"2. Campo",'2. Status Detalhe Campos FY24'!$U$7:$U$736,"*Novo Plano*") +COUNTIFS('2. Status Detalhe Campos FY24'!$G$7:$G$736,'1. Status Resumo FY24'!$P113,'2. Status Detalhe Campos FY24'!$C$7:$C$736,'1. Status Resumo FY24'!$H$88,'2. Status Detalhe Campos FY24'!$D$7:$D$736,"2. Campo",'2. Status Detalhe Campos FY24'!$U$7:$U$736,"*Novo Plano*") -> 5 | V115: =U115-T115 -> 0
P116: 7. Por iniciar | T116: =COUNTIFS('2. Status Detalhe Campos FY24'!$H$7:$H$736,'1. Status Resumo FY24'!$P116,'2. Status Detalhe Campos FY24'!$C$7:$C$736,'1. Status Resumo FY24'!$G$88,'2. Status Detalhe Campos FY24'!$D$7:$D$736,"2. Campo")+COUNTIFS('2. Status Detalhe Campos FY24'!$H$7:$H$736,'1. Status Resumo FY24'!$P116,'2. Status Detalhe Campos FY24'!$C$7:$C$736,'1. Status Resumo FY24'!$H$88,'2. Status Detalhe Campos FY24'!$D$7:$D$736,"2. Campo") -> 0 | U116: =COUNTIFS('2. Status Detalhe Campos FY24'!$G$7:$G$736,'1. Status Resumo FY24'!$P116,'2. Status Detalhe Campos FY24'!$C$7:$C$736,'1. Status Resumo FY24'!$G$88,'2. Status Detalhe Campos FY24'!$D$7:$D$736,"2. Campo")+COUNTIFS('2. Status Detalhe Campos FY24'!$G$7:$G$736,'1. Status Resumo FY24'!$P116,'2. Status Detalhe Campos FY24'!$C$7:$C$736,'1. Status Resumo FY24'!$H$88,'2. Status Detalhe Campos FY24'!$D$7:$D$736,"2. Campo") -> 0 | V116: =U116-T116 -> 0
P117: Requisitos FY24 | T117: =COUNTIFS('2. Status Detalhe Campos FY24'!$H$7:$H$736,'1. Status Resumo FY24'!$P116,'2. Status Detalhe Campos FY24'!$C$7:$C$736,'1. Status Resumo FY24'!$G$88,'2. Status Detalhe Campos FY24'!$D$7:$D$736,"2. Campo",'2. Status Detalhe Campos FY24'!$U$7:$U$736,"*Plano anterior*") +COUNTIFS('2. Status Detalhe Campos FY24'!$H$7:$H$736,'1. Status Resumo FY24'!$P116,'2. Status Detalhe Campos FY24'!$C$7:$C$736,'1. Status Resumo FY24'!$H$88,'2. Status Detalhe Campos FY24'!$D$7:$D$736,"2. Campo",'2. Status Detalhe Campos FY24'!$U$7:$U$736,"*Plano anterior*") -> 0 | U117: =COUNTIFS('2. Status Detalhe Campos FY24'!$G$7:$G$736,'1. Status Resumo FY24'!$P116,'2. Status Detalhe Campos FY24'!$C$7:$C$736,'1. Status Resumo FY24'!$G$88,'2. Status Detalhe Campos FY24'!$D$7:$D$736,"2. Campo",'2. Status Detalhe Campos FY24'!$U$7:$U$736,"*Plano anterior*") +COUNTIFS('2. Status Detalhe Campos FY24'!$G$7:$G$736,'1. Status Resumo FY24'!$P116,'2. Status Detalhe Campos FY24'!$C$7:$C$736,'1. Status Resumo FY24'!$H$88,'2. Status Detalhe Campos FY24'!$D$7:$D$736,"2. Campo",'2. Status Detalhe Campos FY24'!$U$7:$U$736,"*Plano anterior*") -> 0 | V117: =U117-T117 -> 0
P118: Novos Requisitos FY25 | T118: =COUNTIFS('2. Status Detalhe Campos FY24'!$H$7:$H$736,'1. Status Resumo FY24'!$P116,'2. Status Detalhe Campos FY24'!$C$7:$C$736,'1. Status Resumo FY24'!$G$88,'2. Status Detalhe Campos FY24'!$D$7:$D$736,"2. Campo",'2. Status Detalhe Campos FY24'!$U$7:$U$736,"*Novo Plano*") +COUNTIFS('2. Status Detalhe Campos FY24'!$H$7:$H$736,'1. Status Resumo FY24'!$P116,'2. Status Detalhe Campos FY24'!$C$7:$C$736,'1. Status Resumo FY24'!$H$88,'2. Status Detalhe Campos FY24'!$D$7:$D$736,"2. Campo",'2. Status Detalhe Campos FY24'!$U$7:$U$736,"*Novo Plano*") -> 0 | U118: =COUNTIFS('2. Status Detalhe Campos FY24'!$G$7:$G$736,'1. Status Resumo FY24'!$P116,'2. Status Detalhe Campos FY24'!$C$7:$C$736,'1. Status Resumo FY24'!$G$88,'2. Status Detalhe Campos FY24'!$D$7:$D$736,"2. Campo",'2. Status Detalhe Campos FY24'!$U$7:$U$736,"*Novo Plano*") +COUNTIFS('2. Status Detalhe Campos FY24'!$G$7:$G$736,'1. Status Resumo FY24'!$P116,'2. Status Detalhe Campos FY24'!$C$7:$C$736,'1. Status Resumo FY24'!$H$88,'2. Status Detalhe Campos FY24'!$D$7:$D$736,"2. Campo",'2. Status Detalhe Campos FY24'!$U$7:$U$736,"*Novo Plano*") -> 0 | V118: =U118-T118 -> 0
P119: Total | T119: =+SUM(T92,T95,T98,T104,T107,T110,T113,T116,T101) -> 297 | U119: =+SUM(U92,U95,U98,U104,U107,U110,U113,U116,U101) -> 300 | V119: =+U119-T119 -> 3
...

Sheet Auxiliar
D2: Estimação Horas
B3: Tipologia de testes | D3: Complexidade
B4: Categorização de Testes | C4: Descrição | D4: Baixa | E4: Média | F4: Alta | H4: Baixa | I4: Média | J4: Alta
B5: 1. Teste de universo | C5: 1. Validação de universo de contratos (quando comparado âmbito "CDG" e "PM", e numero de registos) 2. Controlos sobre o desdobramento de chaves nas relações FR-MIS | D5: 8 | E5: 8 | F5: 8 | H5: 1 | I5: 3 | J5: 8
B6: 2. Simulação | C6: Simulação da especificação funcional. Suplementarmente, realizar reuniões de validações e esclarecimentos funcionais junto do negócio/owner. | D6: 2 | E6: 4 | F6: 8 | H6: 1 | I6: 3 | J6: 4
B7: 3. Testes comparativos (Espec. VS Impl.) | C7: A partir da simulação realizada, comparar resultados com a implementação de IT. | D7: 2 | E7: 4 | F7: 8 | H7: 1 | I7: 1 | J7: 2
B8: 4. Validação de parametrizações | C8: A partir da simulação realizada, comparar com as parametrizações implementadas por IT. | D8: 2 | E8: 4 | F8: 8 | H8: 2 | I8: 4 | J8: 4
B9: 5. Teste comparativos com LT | C9: Garantir que a informação do campo da LT-ESTR âmbito 'PM' está espelhado no âmbito 'CDG'. | D9: 1 | E9: 1 | F9: 1
B10: 6. Validação de formatos | C10: Validação de formato de acordo com o que é esperado pela Corporação (incluindo validação de codelists, missing e default values) Validar especificação e controlos da especificação vs o que está implementado | D10: 0.1 | E10: 0.1 | F10: 0.1 | H10: 0.1 | I10: 0.5 | J10: 0.5
B11: 7. Validação de controlos corporativos | C11: Validar controlos corporativos e se a especificação cumpre os requisitos. | D11: 1 | E11: 2 | F11: 2
B12: 8. Teste de Carregamento | C12: Garantir que o carregamento do ficheiro é realizado com sucesso no Front. | D12: 0.5 | E12: 0.5 | F12: 0.5 | H12: 0.5 | I12: 0.5 | J12: 0.5
B13: 9. Teste de Integridade | C13: Garantir integridade entre o ficheiro importado pela equipa de testes e o ficheiro de tecnologia (Ex: Garantir que a informação de todos os campos está correta de acordo com os dados corporativos) | D13: 0.5 | E13: 0.5 | F13: 0.5 | H13: 0.5 | I13: 0.5 | J13: 0.5
B15: Status
B16: 1. Concluído | C16: =_xlfn.NUMBERVALUE(LEFT(B16,1)) -> 1 | D16: 1 | E16: 1
A17: Pendente de outros campos/tabelas | B17: 3. Pendente de outros desenvolvimentos | C17: 4 | D17: 0.25 | E17: 0
B18: 7. Por iniciar | C18: 8 | D18: 0 | E18: 0
B19: 2.1 Em Teste | C19: =_xlfn.NUMBERVALUE(LEFT(B19,1)) -> 2 | D19: 0.5 | E19: 0.25
B20: 2.2 Em especificação | C20: 3 | D20: 0.5 | E20: 0
A21: Validação da Susana/LCM/Corp/conceito/alterações | B21: 4. Validação EF | C21: 5 | D21: 0.25 | E21: 0.25
A22: Por IT | B22: 5. Em Correção | C22: 6 | D22: 0.25 | E22: 0
A23: Por IT | B23: 6. Em implementação | C23: 7 | D23: 0.25 | E23: 0
A24: Campo eliminado | B24: 0. Cancelado | C24: =_xlfn.NUMBERVALUE(LEFT(B24,1)) -> 0 | D24: 0 | E24: 0

Sheet Aux - Pivots2
B2: 1. Visão Geral
B6: Âmbito | C6: Pilar III
B7: Tipo de teste | C7: 2. Campo
C9: Column Labels
C10: 0. Cancelado | D10: 1. Concluído | E10: 2.1 Em Teste | F10: 3. Pendente de outros desenvolvimentos | G10: 4. Validação EF | H10: 6. Em implementação | I10: 2.2 Em especificação | J10: 2. Em Teste | K10: Grand Total
B11: Count of Campo | C11: 32 | D11: 463 | E11: 8 | F11: 9 | G11: 4 | H11: 143 | I11: 7 | J11: 44 | K11: 710
B20: Âmbito | C20: Pilar III
B21: Tipo de teste | C21: 2. Campo
B23: Row Labels | C23: Count of Campo
B24: 0. Cancelado | C24: 32
B25: 1. Concluído | C25: 463
B26: 2.1 Em Teste | C26: 8
B27: 3. Pendente de outros desenvolvimentos | C27: 9
B28: 4. Validação EF | C28: 4
B29: 6. Em implementação | C29: 143
B30: 2.2 Em especificação | C30: 7
B31: 2. Em Teste | C31: 44
B32: Grand Total | C32: 710
B42: 2. Modelo Bens imóveis
B45: Âmbito | C45: Pilar III
B46: Sub-âmbito | C46: (Multiple Items)
B47: Tipo de teste | C47: 2. Campo
B49: Count of Campo | C49: Column Labels
B50: Row Labels | C50: 0. Cancelado | D50: 1. Concluído | E50: 2. Em Teste | F50: 2.1 Em Teste | G50: 4. Validação EF | H50: Grand Total
B51: RESPONSIBILITY_PROCESS_REL | C51: 3 | D51: 17 | H51: 20
B52: PROPERTY_ENERGY_CERTIFICATE | D52: 69 | F52: 2 | G52: 2 | H52: 73
B53: PROPERTY | C53: 2 | D53: 31 | H53: 33
B54: PROCESS_PROPERTY_REL | C54: 1 | D54: 14 | H54: 15
B55: PROCESS | C55: 4 | D55: 13 | H55: 17
B56: ENERGY_CERTIFICATE_EST_INPUT | C56: 2 | E56: 44 | H56: 46
B57: Grand Total | C57: 12 | D57: 144 | E57: 44 | F57: 2 | G57: 2 | H57: 204
B62: Âmbito | C62: Pilar III
B63: Sub-âmbito | C63: (Multiple Items)
B64: Tipo de teste | C64: 2. Campo
B66: Row Labels | C66: Count of Campo
B67: 0. Cancelado | C67: 12
B68: 1. Concluído | C68: 144
B69: 2.1 Em Teste | C69: 2
B70: 4. Validação EF | C70: 2
B71: 2. Em Teste | C71: 44
B72: Grand Total | C72: 204
B81: 3. Modelo Verde
B83: Âmbito | C83: Pilar III
B84: Sub-âmbito | C84: (Multiple Items)
B85: Tipo de teste | C85: 2. Campo
B87: Count of Campo | C87: Column Labels
B88: Row Labels | C88: 0. Cancelado | D88: 1. Concluído | E88: 2.1 Em Teste | F88: 2.2 Em especificação | G88: 6. Em implementação | H88: Grand Total
B89: modesg_param_sfics_taxon_europeia | C89: 3 | G89: 45 | H89: 48
B90: modesg_out_sfics_taxon_europeia | C90: 2 | F90: 1 | G90: 14 | H90: 17
B91: modesg_out_emss_vcls | D91: 15 | H91: 15
B92: modesg_out_empr_info_nfin | D92: 41 | E92: 6 | G92: 5 | H92: 52
B93: modesg_out_bens_imoveis | D93: 14 | G93: 4 | H93: 18
B94: modesg_inp_risco_fisico_zipcode | G94: 5 | H94: 5
B95: modesg_inp_risco_fisico | D95: 6 | H95: 6
B96: modesg_inp_project_finance | D96: 9 | H96: 9
B97: modesg_inp_nfrd_alinhamento_tax | D97: 41 | H97: 41
B98: modesg_inp_km_medios_emss_vcls | C98: 3 | D98: 6 | H98: 9
B99: modesg_inp_emss_vcls | D99: 17 | H99: 17
B100: modesg_inp_emss_scib | D100: 17 | H100: 17
B101: modesg_inp_emss_nace | C101: 7 | D101: 14 | H101: 21
B102: modesg_inp_emss_bens_imoveis | C102: 1 | D102: 17 | H102: 18
B103: modesg_inp_empr_excl_paris | D103: 7 | H103: 7
B104: Grand Total | C104: 16 | D104: 204 | E104: 6 | F104: 1 | G104: 73 | H104: 300
B107: Âmbito | C107: All
B108: Sub-âmbito | C108: Pilar III
B109: Tipo de teste | C109: 2. Campo
B111: Row Labels | C111: Count of Campo
B112: 0. Cancelado | C112: 4
B113: 1. Concluído | C113: 115
B114: 2.2 Em especificação | C114: 6
B115: 3. Pendente de outros desenvolvimentos | C115: 9
B116: 4. Validação EF | C116: 2
B117: 6. Em implementação | C117: 70
B118: Grand Total | C118: 206
B126: 4. Loan Tape | Pilar III
B129: Âmbito | C129: Pilar III
B130: Sub-âmbito | C130: Pilar III
B131: Tipo de teste | C131: 2. Campo
B133: Count of Campo | C133: Column Labels
B134: Row Labels | C134: 0. Cancelado | D134: 1. Concluído | E134: 2.2 Em especificação | F134: 3. Pendente de outros desenvolvimentos | G134: 4. Validação EF | H134: 6. Em implementação | I134: Grand Total
B135: lt002_instrument | D135: 23 | E135: 3 | F135: 4 | G135: 1 | H135: 15 | I135: 46
B136: lt003_entity | D136: 39 | F136: 3 | H136: 25 | I136: 67
B137: lt004_protection | C137: 4 | D137: 18 | E137: 3 | F137: 2 | H137: 20 | I137: 47
B138: lt005_instr_ent | D138: 5 | I138: 5
B139: lt006_instr_prot | D139: 4 | H139: 2 | I139: 6
B140: lt007_instr_activity | D140: 2 | G140: 1 | H140: 8 | I140: 11
B141: lt826_esg_sbsctr | D141: 9 | I141: 9
B142: lt827_mthd_usd_instrmnt | D142: 15 | I142: 15
B143: Grand Total | C143: 4 | D143: 115 | E143: 6 | F143: 9 | G143: 2 | H143: 70 | I143: 206
B150: Âmbito | C150: Pilar III
B151: Sub-âmbito | C151: Pilar III
B152: Tipo de teste | C152: 2. Campo
B154: Row Labels | C154: Count of Campo
B155: 1. Concluído | C155: 115
B156: 0. Cancelado | C156: 4
B157: 4. Validação EF | C157: 2
B158: 3. Pendente de outros desenvolvimentos | C158: 9
B159: 2.2 Em especificação | C159: 6
B160: 6. Em implementação | C160: 70
B161: Grand Total | C161: 206
...

Sheet 2. Status Detalhe Campos FY24
E2: Novos requisitos
J5: APAGAR | K5: APAGAR | L5: APAGAR | R5: APAGAR | S5: APAGAR | T5: APAGAR | U5: APAGAR | V5: APAGAR
B6: Âmbito | C6: Sub-âmbito | D6: Tipo de teste | E6: Tabela | F6: Campo | G6: Status Atual | H6: Status Anterior | I6: Fase | J6: Observações - Especificações | K6: Observações - Testes | L6: Observações - Testes sem visibilidade | M6: Data de Pedido correção/esclarecimento | N6: Data de correção prevista | O6: Data de correção efetiva | P6: Data Prevista de Re-especificação | Q6: Data Prevista de Teste | R6: Projeto (Aux JB) | S6: LT Âmbito | T6: LT Âmbito- Aux | U6: Plano | V6: Owner
A7: =E7&F7 -> ENERGY_CERTIFICATE_EST_INPUTn.a. | B7: Pilar III | C7: Bens Imóveis - Input | D7: 1. Universo | E7: ENERGY_CERTIFICATE_EST_INPUT | F7: n.a. | G7: =VLOOKUP(A7,Plano_V3!$A$26:$G$764,7,0) -> 2. Em Teste | H7: 6. Em implementação | I7: Fase I | M7: =IF(VLOOKUP(A7,'Aux - pivots1'!$A:$E,3,0)=0, "",VLOOKUP(A7,'Aux - pivots1'!$A:$E,3,0)) | N7: =IF(VLOOKUP(A7,'Aux - pivots1'!$A:$E,4,0)=0, "",VLOOKUP(A7,'Aux - pivots1'!$A:$E,4,0)) | O7: =IF(VLOOKUP(A7,'Aux - pivots1'!$A:$E,5,0)=0, "",VLOOKUP(A7,'Aux - pivots1'!$A:$E,5,0)) | U7: Plano anterior
A8: =E8&F8 -> ENERGY_CERTIFICATE_EST_INPUTCHAVE_GLOVAL | B8: Pilar III | C8: Bens Imóveis - Input | D8: 2. Campo | E8: ENERGY_CERTIFICATE_EST_INPUT | F8: CHAVE_GLOVAL | G8: =VLOOKUP(A8,Plano_V3!$A$26:$G$764,7,0) -> 2. Em Teste | H8: 6. Em implementação | I8: Fase I | J8: Package 1 | K8: Package 4 | M8: =IF(VLOOKUP(A8,'Aux - pivots1'!$A:$E,3,0)=0, "",VLOOKUP(A8,'Aux - pivots1'!$A:$E,3,0)) | N8: =IF(VLOOKUP(A8,'Aux - pivots1'!$A:$E,4,0)=0, "",VLOOKUP(A8,'Aux - pivots1'!$A:$E,4,0)) | O8: =IF(VLOOKUP(A8,'Aux - pivots1'!$A:$E,5,0)=0, "",VLOOKUP(A8,'Aux - pivots1'!$A:$E,5,0)) | U8: Plano anterior (alteração nome)
A9: =E9&F9 -> ENERGY_CERTIFICATE_EST_INPUTPROPERTY_BANK_ID | B9: Pilar III | C9: Bens Imóveis - Input | D9: 2. Campo | E9: ENERGY_CERTIFICATE_EST_INPUT | F9: PROPERTY_BANK_ID | G9: =VLOOKUP(A9,Plano_V3!$A$26:$G$764,7,0) -> 2. Em Teste | H9: 6. Em implementação | I9: Fase I | J9: Package 1 | K9: Package 4 | M9: =IF(VLOOKUP(A9,'Aux - pivots1'!$A:$E,3,0)=0, "",VLOOKUP(A9,'Aux - pivots1'!$A:$E,3,0)) | N9: =IF(VLOOKUP(A9,'Aux - pivots1'!$A:$E,4,0)=0, "",VLOOKUP(A9,'Aux - pivots1'!$A:$E,4,0)) | O9: =IF(VLOOKUP(A9,'Aux - pivots1'!$A:$E,5,0)=0, "",VLOOKUP(A9,'Aux - pivots1'!$A:$E,5,0)) | U9: Plano anterior
A10: =E10&F10 -> ENERGY_CERTIFICATE_EST_INPUTPROPERTY_BRANCH_CODE | B10: Pilar III | C10: Bens Imóveis - Input | D10: 2. Campo | E10: ENERGY_CERTIFICATE_EST_INPUT | F10: PROPERTY_BRANCH_CODE | G10: =VLOOKUP(A10,Plano_V3!$A$26:$G$764,7,0) -> 2. Em Teste | H10: 6. Em implementação | I10: Fase I | J10: Package 1 | K10: Package 4 | M10: =IF(VLOOKUP(A10,'Aux - pivots1'!$A:$E,3,0)=0, "",VLOOKUP(A10,'Aux - pivots1'!$A:$E,3,0)) | N10: =IF(VLOOKUP(A10,'Aux - pivots1'!$A:$E,4,0)=0, "",VLOOKUP(A10,'Aux - pivots1'!$A:$E,4,0)) | O10: =IF(VLOOKUP(A10,'Aux - pivots1'!$A:$E,5,0)=0, "",VLOOKUP(A10,'Aux - pivots1'!$A:$E,5,0)) | U10: Plano anterior
A11: =E11&F11 -> ENERGY_CERTIFICATE_EST_INPUTPROPERTY_CONTRACT_ID | B11: Pilar III | C11: Bens Imóveis - Input | D11: 2. Campo | E11: ENERGY_CERTIFICATE_EST_INPUT | F11: PROPERTY_CONTRACT_ID | G11: =VLOOKUP(A11,Plano_V3!$A$26:$G$764,7,0) -> 2. Em Teste | H11: 6. Em implementação | I11: Fase I | J11: Package 1 | K11: Package 4 | M11: =IF(VLOOKUP(A11,'Aux - pivots1'!$A:$E,3,0)=0, "",VLOOKUP(A11,'Aux - pivots1'!$A:$E,3,0)) | N11: =IF(VLOOKUP(A11,'Aux - pivots1'!$A:$E,4,0)=0, "",VLOOKUP(A11,'Aux - pivots1'!$A:$E,4,0)) | O11: =IF(VLOOKUP(A11,'Aux - pivots1'!$A:$E,5,0)=0, "",VLOOKUP(A11,'Aux - pivots1'!$A:$E,5,0)) | U11: Plano anterior
A12: =E12&F12 -> ENERGY_CERTIFICATE_EST_INPUTPROPERTY_REFERENCE_CODE | B12: Pilar III | C12: Bens Imóveis - Input | D12: 2. Campo | E12: ENERGY_CERTIFICATE_EST_INPUT | F12: PROPERTY_REFERENCE_CODE | G12: =VLOOKUP(A12,Plano_V3!$A$26:$G$764,7,0) -> 2. Em Teste | H12: 6. Em implementação | I12: Fase I | J12: Package 1 | K12: Package 4 | M12: =IF(VLOOKUP(A12,'Aux - pivots1'!$A:$E,3,0)=0, "",VLOOKUP(A12,'Aux - pivots1'!$A:$E,3,0)) | N12: =IF(VLOOKUP(A12,'Aux - pivots1'!$A:$E,4,0)=0, "",VLOOKUP(A12,'Aux - pivots1'!$A:$E,4,0)) | O12: =IF(VLOOKUP(A12,'Aux - pivots1'!$A:$E,5,0)=0, "",VLOOKUP(A12,'Aux - pivots1'!$A:$E,5,0)) | U12: Plano anterior
A13: =E13&F13 -> ENERGY_CERTIFICATE_EST_INPUTCÓDIGO_DISTRITO | B13: Pilar III | C13: Bens Imóveis - Input | D13: 2. Campo | E13: ENERGY_CERTIFICATE_EST_INPUT | F13: CÓDIGO_DISTRITO | G13: =VLOOKUP(A13,Plano_V3!$A$26:$G$764,7,0) -> 2. Em Teste | H13: 6. Em implementação | I13: Fase I | J13: Package 1 | K13: Package 4 | M13: =IF(VLOOKUP(A13,'Aux - pivots1'!$A:$E,3,0)=0, "",VLOOKUP(A13,'Aux - pivots1'!$A:$E,3,0)) | N13: =IF(VLOOKUP(A13,'Aux - pivots1'!$A:$E,4,0)=0, "",VLOOKUP(A13,'Aux - pivots1'!$A:$E,4,0)) | O13: =IF(VLOOKUP(A13,'Aux - pivots1'!$A:$E,5,0)=0, "",VLOOKUP(A13,'Aux - pivots1'!$A:$E,5,0)) | U13: Plano anterior (sem visibilidade no PdS enviado 17/01)
A14: =E14&F14 -> ENERGY_CERTIFICATE_EST_INPUTNOMBRE_DISTRITO | B14: Pilar III | C14: Bens Imóveis - Input | D14: 2. Campo | E14: ENERGY_CERTIFICATE_EST_INPUT | F14: NOMBRE_DISTRITO | G14: =VLOOKUP(A14,Plano_V3!$A$26:$G$764,7,0) -> 2. Em Teste | H14: 6. Em implementação | I14: Fase I | J14: Package 1 | K14: Package 4 | M14: =IF(VLOOKUP(A14,'Aux - pivots1'!$A:$E,3,0)=0, "",VLOOKUP(A14,'Aux - pivots1'!$A:$E,3,0)) | N14: =IF(VLOOKUP(A14,'Aux - pivots1'!$A:$E,4,0)=0, "",VLOOKUP(A14,'Aux - pivots1'!$A:$E,4,0)) | O14: =IF(VLOOKUP(A14,'Aux - pivots1'!$A:$E,5,0)=0, "",VLOOKUP(A14,'Aux - pivots1'!$A:$E,5,0)) | U14: Plano anterior (sem visibilidade no PdS enviado 17/01)
A15: =E15&F15 -> ENERGY_CERTIFICATE_EST_INPUTCÓDIGO_CONCEJO | B15: Pilar III | C15: Bens Imóveis - Input | D15: 2. Campo | E15: ENERGY_CERTIFICATE_EST_INPUT | F15: CÓDIGO_CONCEJO | G15: =VLOOKUP(A15,Plano_V3!$A$26:$G$764,7,0) -> 2. Em Teste | H15: 6. Em implementação | I15: Fase I | J15: Package 1 | K15: Package 4 | M15: =IF(VLOOKUP(A15,'Aux - pivots1'!$A:$E,3,0)=0, "",VLOOKUP(A15,'Aux - pivots1'!$A:$E,3,0)) | N15: =IF(VLOOKUP(A15,'Aux - pivots1'!$A:$E,4,0)=0, "",VLOOKUP(A15,'Aux - pivots1'!$A:$E,4,0)) | O15: =IF(VLOOKUP(A15,'Aux - pivots1'!$A:$E,5,0)=0, "",VLOOKUP(A15,'Aux - pivots1'!$A:$E,5,0)) | U15: Plano anterior (sem visibilidade no PdS enviado 17/01)
A16: =E16&F16 -> ENERGY_CERTIFICATE_EST_INPUTNOMBRE_CONCEJO | B16: Pilar III | C16: Bens Imóveis - Input | D16: 2. Campo | E16: ENERGY_CERTIFICATE_EST_INPUT | F16: NOMBRE_CONCEJO | G16: =VLOOKUP(A16,Plano_V3!$A$26:$G$764,7,0) -> 2. Em Teste | H16: 6. Em implementação | I16: Fase I | J16: Package 1 | K16: Package 4 | M16: =IF(VLOOKUP(A16,'Aux - pivots1'!$A:$E,3,0)=0, "",VLOOKUP(A16,'Aux - pivots1'!$A:$E,3,0)) | N16: =IF(VLOOKUP(A16,'Aux - pivots1'!$A:$E,4,0)=0, "",VLOOKUP(A16,'Aux - pivots1'!$A:$E,4,0)) | O16: =IF(VLOOKUP(A16,'Aux - pivots1'!$A:$E,5,0)=0, "",VLOOKUP(A16,'Aux - pivots1'!$A:$E,5,0)) | U16: Plano anterior (sem visibilidade no PdS enviado 17/01)
A17: =E17&F17 -> ENERGY_CERTIFICATE_EST_INPUTCÓDIGO_FREGUESIA | B17: Pilar III | C17: Bens Imóveis - Input | D17: 2. Campo | E17: ENERGY_CERTIFICATE_EST_INPUT | F17: CÓDIGO_FREGUESIA | G17: =VLOOKUP(A17,Plano_V3!$A$26:$G$764,7,0) -> 2. Em Teste | H17: 6. Em implementação | I17: Fase I | J17: Package 1 | K17: Package 4 | M17: =IF(VLOOKUP(A17,'Aux - pivots1'!$A:$E,3,0)=0, "",VLOOKUP(A17,'Aux - pivots1'!$A:$E,3,0)) | N17: =IF(VLOOKUP(A17,'Aux - pivots1'!$A:$E,4,0)=0, "",VLOOKUP(A17,'Aux - pivots1'!$A:$E,4,0)) | O17: =IF(VLOOKUP(A17,'Aux - pivots1'!$A:$E,5,0)=0, "",VLOOKUP(A17,'Aux - pivots1'!$A:$E,5,0)) | U17: Plano anterior (sem visibilidade no PdS enviado 17/01)
A18: =E18&F18 -> ENERGY_CERTIFICATE_EST_INPUTNOMBRE_FREGUESIA | B18: Pilar III | C18: Bens Imóveis - Input | D18: 2. Campo | E18: ENERGY_CERTIFICATE_EST_INPUT | F18: NOMBRE_FREGUESIA | G18: =VLOOKUP(A18,Plano_V3!$A$26:$G$764,7,0) -> 2. Em Teste | H18: 6. Em implementação | I18: Fase I | J18: Package 1 | K18: Package 4 | M18: =IF(VLOOKUP(A18,'Aux - pivots1'!$A:$E,3,0)=0, "",VLOOKUP(A18,'Aux - pivots1'!$A:$E,3,0)) | N18: =IF(VLOOKUP(A18,'Aux - pivots1'!$A:$E,4,0)=0, "",VLOOKUP(A18,'Aux - pivots1'!$A:$E,4,0)) | O18: =IF(VLOOKUP(A18,'Aux - pivots1'!$A:$E,5,0)=0, "",VLOOKUP(A18,'Aux - pivots1'!$A:$E,5,0)) | U18: Plano anterior (sem visibilidade no PdS enviado 17/01)
A19: =E19&F19 -> ENERGY_CERTIFICATE_EST_INPUTLOCALIDADE | B19: Pilar III | C19: Bens Imóveis - Input | D19: 2. Campo | E19: ENERGY_CERTIFICATE_EST_INPUT | F19: LOCALIDADE | G19: =VLOOKUP(A19,Plano_V3!$A$26:$G$764,7,0) -> 2. Em Teste | H19: 6. Em implementação | I19: Fase I | J19: Package 1 | K19: Package 4 | M19: =IF(VLOOKUP(A19,'Aux - pivots1'!$A:$E,3,0)=0, "",VLOOKUP(A19,'Aux - pivots1'!$A:$E,3,0)) | N19: =IF(VLOOKUP(A19,'Aux - pivots1'!$A:$E,4,0)=0, "",VLOOKUP(A19,'Aux - pivots1'!$A:$E,4,0)) | O19: =IF(VLOOKUP(A19,'Aux - pivots1'!$A:$E,5,0)=0, "",VLOOKUP(A19,'Aux - pivots1'!$A:$E,5,0)) | U19: Plano anterior (sem visibilidade no PdS enviado 17/01)
... A41: =E41&F41 -> ENERGY_CERTIFICATE_EST_INPUTART_MATRICIAIS | B41: Pilar III | C41: Bens Imóveis - Input | D41: 2. Campo | E41: ENERGY_CERTIFICATE_EST_INPUT | F41: ART_MATRICIAIS | G41: =VLOOKUP(A41,Plano_V3!$A$26:$G$764,7,0) -> 2. Em Teste | H41: 6. Em implementação | I41: Fase I | J41: Package 1 | K41: Package 4 | M41: =IF(VLOOKUP(A41,'Aux - pivots1'!$A:$E,3,0)=0, "",VLOOKUP(A41,'Aux - pivots1'!$A:$E,3,0)) | N41: =IF(VLOOKUP(A41,'Aux - pivots1'!$A:$E,4,0)=0, "",VLOOKUP(A41,'Aux - pivots1'!$A:$E,4,0)) | O41: =IF(VLOOKUP(A41,'Aux - pivots1'!$A:$E,5,0)=0, "",VLOOKUP(A41,'Aux - pivots1'!$A:$E,5,0)) | U41: Plano anterior (sem visibilidade no PdS enviado 17/01)
A42: =E42&F42 -> ENERGY_CERTIFICATE_EST_INPUTDATA_PROVIDER | B42: Pilar III | C42: Bens Imóveis - Input | D42: 2. Campo | E42: ENERGY_CERTIFICATE_EST_INPUT | F42: DATA_PROVIDER | G42: =VLOOKUP(A42,Plano_V3!$A$26:$G$764,7,0) -> 0. Cancelado | H42: 0. Cancelado | I42: Fase I | M42: =IF(VLOOKUP(A42,'Aux - pivots1'!$A:$E,3,0)=0, "",VLOOKUP(A42,'Aux - pivots1'!$A:$E,3,0)) | N42: =IF(VLOOKUP(A42,'Aux - pivots1'!$A:$E,4,0)=0, "",VLOOKUP(A42,'Aux - pivots1'!$A:$E,4,0)) | O42: =IF(VLOOKUP(A42,'Aux - pivots1'!$A:$E,5,0)=0, "",VLOOKUP(A42,'Aux - pivots1'!$A:$E,5,0)) | U42: Plano anterior
A43: =E43&F43 -> ENERGY_CERTIFICATE_EST_INPUTACTUAL_VALUE_IND | B43: Pilar III | C43: Bens Imóveis - Input | D43: 2. Campo | E43: ENERGY_CERTIFICATE_EST_INPUT | F43: ACTUAL_VALUE_IND | G43: =VLOOKUP(A43,Plano_V3!$A$26:$G$764,7,0) -> 0. Cancelado | H43: 0. Cancelado | I43: Fase I | M43: =IF(VLOOKUP(A43,'Aux - pivots1'!$A:$E,3,0)=0, "",VLOOKUP(A43,'Aux - pivots1'!$A:$E,3,0)) | N43: =IF(VLOOKUP(A43,'Aux - pivots1'!$A:$E,4,0)=0, "",VLOOKUP(A43,'Aux - pivots1'!$A:$E,4,0)) | O43: =IF(VLOOKUP(A43,'Aux - pivots1'!$A:$E,5,0)=0, "",VLOOKUP(A43,'Aux - pivots1'!$A:$E,5,0)) | U43: Plano anterior
A44: =E44&F44 -> ENERGY_CERTIFICATE_EST_INPUTFRACCAO_AUTONOMA | B44: Pilar III | C44: Bens Imóveis - Input | D44: 2. Campo | E44: ENERGY_CERTIFICATE_EST_INPUT | F44: FRACCAO_AUTONOMA | G44: =VLOOKUP(A44,Plano_V3!$A$26:$G$764,7,0) -> 2. Em Teste | H44: 6. Em implementação | I44: Fase I | J44: Package 1 | K44: Package 4 | M44: =IF(VLOOKUP(A44,'Aux - pivots1'!$A:$E,3,0)=0, "",VLOOKUP(A44,'Aux - pivots1'!$A:$E,3,0)) | N44: =IF(VLOOKUP(A44,'Aux - pivots1'!$A:$E,4,0)=0, "",VLOOKUP(A44,'Aux - pivots1'!$A:$E,4,0)) | O44: =IF(VLOOKUP(A44,'Aux - pivots1'!$A:$E,5,0)=0, "",VLOOKUP(A44,'Aux - pivots1'!$A:$E,5,0)) | U44: Plano anterior (sem visibilidade no PdS enviado 17/01)
A45: =E45&F45 -> ENERGY_CERTIFICATE_EST_INPUTFINALIDADE_BEM | B45: Pilar III | C45: Bens Imóveis - Input | D45: 2. Campo | E45: ENERGY_CERTIFICATE_EST_INPUT | F45: FINALIDADE_BEM | G45: =VLOOKUP(A45,Plano_V3!$A$26:$G$764,7,0) -> 2. Em Teste | H45: 6. Em implementação | I45: Fase I | J45: Package 1 | K45: Package 4 | M45: =IF(VLOOKUP(A45,'Aux - pivots1'!$A:$E,3,0)=0, "",VLOOKUP(A45,'Aux - pivots1'!$A:$E,3,0)) | N45: =IF(VLOOKUP(A45,'Aux - pivots1'!$A:$E,4,0)=0, "",VLOOKUP(A45,'Aux - pivots1'!$A:$E,4,0)) | O45: =IF(VLOOKUP(A45,'Aux - pivots1'!$A:$E,5,0)=0, "",VLOOKUP(A45,'Aux - pivots1'!$A:$E,5,0)) | U45: Plano anterior (sem visibilidade no PdS enviado 17/01)
A46: =E46&F46 -> ENERGY_CERTIFICATE_EST_INPUTCLASS_GPT31 | B46: Pilar III | C46: Bens Imóveis - Input | D46: 2. Campo | E46: ENERGY_CERTIFICATE_EST_INPUT | F46: CLASS_GPT31 | G46: =VLOOKUP(A46,Plano_V3!$A$26:$G$764,7,0) -> 2. Em Teste | H46: 6. Em implementação | I46: Fase I | J46: Package 1 | K46: Package 4 | M46: =IF(VLOOKUP(A46,'Aux - pivots1'!$A:$E,3,0)=0, "",VLOOKUP(A46,'Aux - pivots1'!$A:$E,3,0)) | N46: =IF(VLOOKUP(A46,'Aux - pivots1'!$A:$E,4,0)=0, "",VLOOKUP(A46,'Aux - pivots1'!$A:$E,4,0)) | O46: =IF(VLOOKUP(A46,'Aux - pivots1'!$A:$E,5,0)=0, "",VLOOKUP(A46,'Aux - pivots1'!$A:$E,5,0)) | U46: Plano anterior (sem visibilidade no PdS enviado 17/01)
A47: =E47&F47 -> ENERGY_CERTIFICATE_EST_INPUTCLASS_STCLIM | B47: Pilar III | C47: Bens Imóveis - Input | D47: 2. Campo | E47: ENERGY_CERTIFICATE_EST_INPUT | F47: CLASS_STCLIM | G47: =VLOOKUP(A47,Plano_V3!$A$26:$G$764,7,0) -> 2. Em Teste | H47: 6. Em implementação | I47: Fase I | J47: Package 1 | K47: Package 4 | M47: =IF(VLOOKUP(A47,'Aux - pivots1'!$A:$E,3,0)=0, "",VLOOKUP(A47,'Aux - pivots1'!$A:$E,3,0)) | N47: =IF(VLOOKUP(A47,'Aux - pivots1'!$A:$E,4,0)=0, "",VLOOKUP(A47,'Aux - pivots1'!$A:$E,4,0)) | O47: =IF(VLOOKUP(A47,'Aux - pivots1'!$A:$E,5,0)=0, "",VLOOKUP(A47,'Aux - pivots1'!$A:$E,5,0)) | U47: Plano anterior (sem visibilidade no PdS enviado 17/01)
A48: =E48&F48 -> ENERGY_CERTIFICATE_EST_INPUTCONF_STCLIM | B48: Pilar III | C48: Bens Imóveis - Input | D48: 2. Campo | E48: ENERGY_CERTIFICATE_EST_INPUT | F48: CONF_STCLIM | G48: =VLOOKUP(A48,Plano_V3!$A$26:$G$764,7,0) -> 2. Em Teste | H48: 6. Em implementação | I48: Fase I | J48: Package 1 | K48: Package 4 | M48: =IF(VLOOKUP(A48,'Aux - pivots1'!$A:$E,3,0)=0, "",VLOOKUP(A48,'Aux - pivots1'!$A:$E,3,0)) | N48: =IF(VLOOKUP(A48,'Aux - pivots1'!$A:$E,4,0)=0, "",VLOOKUP(A48,'Aux - pivots1'!$A:$E,4,0)) | O48: =IF(VLOOKUP(A48,'Aux - pivots1'!$A:$E,5,0)=0, "",VLOOKUP(A48,'Aux - pivots1'!$A:$E,5,0)) | U48: Plano anterior (sem visibilidade no PdS enviado 17/01)
A49: =E49&F49 -> ENERGY_CERTIFICATE_EST_INPUTCLASSE_ENERGETICA | B49: Pilar III | C49: Bens Imóveis - Input | D49: 2. Campo | E49: ENERGY_CERTIFICATE_EST_INPUT | F49: CLASSE_ENERGETICA | G49: =VLOOKUP(A49,Plano_V3!$A$26:$G$764,7,0) -> 2. Em Teste | H49: 6. Em implementação | I49: Fase I | J49: Package 1 | K49: Package 4 | M49: =IF(VLOOKUP(A49,'Aux - pivots1'!$A:$E,3,0)=0, "",VLOOKUP(A49,'Aux - pivots1'!$A:$E,3,0)) | N49: =IF(VLOOKUP(A49,'Aux - pivots1'!$A:$E,4,0)=0, "",VLOOKUP(A49,'Aux - pivots1'!$A:$E,4,0)) | O49: =IF(VLOOKUP(A49,'Aux - pivots1'!$A:$E,5,0)=0, "",VLOOKUP(A49,'Aux - pivots1'!$A:$E,5,0)) | U49: Plano anterior (alteração nome)
A50: =E50&F50 -> ENERGY_CERTIFICATE_EST_INPUTFIABILIDAD | B50: Pilar III | C50: Bens Imóveis - Input | D50: 2. Campo | E50: ENERGY_CERTIFICATE_EST_INPUT | F50: FIABILIDAD | G50: =VLOOKUP(A50,Plano_V3!$A$26:$G$764,7,0) -> 2. Em Teste | H50: 6. Em implementação | I50: Fase I | J50: Package 1 | K50: Package 4 | M50: =IF(VLOOKUP(A50,'Aux - pivots1'!$A:$E,3,0)=0, "",VLOOKUP(A50,'Aux - pivots1'!$A:$E,3,0)) | N50: =IF(VLOOKUP(A50,'Aux - pivots1'!$A:$E,4,0)=0, "",VLOOKUP(A50,'Aux - pivots1'!$A:$E,4,0)) | O50: =IF(VLOOKUP(A50,'Aux - pivots1'!$A:$E,5,0)=0, "",VLOOKUP(A50,'Aux - pivots1'!$A:$E,5,0)) | U50: Plano anterior (alteração nome)
A51: =E51&F51 -> ENERGY_CERTIFICATE_EST_INPUTEMISSIONES | B51: Pilar III | C51: Bens Imóveis - Input | D51: 2. Campo | E51: ENERGY_CERTIFICATE_EST_INPUT | F51: EMISSIONES | G51: =VLOOKUP(A51,Plano_V3!$A$26:$G$764,7,0) -> 2. Em Teste | H51: 6. Em implementação | I51: Fase I | J51: Package 1 | K51: Package 4 | M51: =IF(VLOOKUP(A51,'Aux - pivots1'!$A:$E,3,0)=0, "",VLOOKUP(A51,'Aux - pivots1'!$A:$E,3,0)) | N51: =IF(VLOOKUP(A51,'Aux - pivots1'!$A:$E,4,0)=0, "",VLOOKUP(A51,'Aux - pivots1'!$A:$E,4,0)) | O51: =IF(VLOOKUP(A51,'Aux - pivots1'!$A:$E,5,0)=0, "",VLOOKUP(A51,'Aux - pivots1'!$A:$E,5,0)) | U51: Plano anterior (alteração nome)
A52: =E52&F52 -> ENERGY_CERTIFICATE_EST_INPUTCONSUMOS | B52: Pilar III | C52: Bens Imóveis - Input | D52: 2. Campo | E52: ENERGY_CERTIFICATE_EST_INPUT | F52: CONSUMOS | G52: =VLOOKUP(A52,Plano_V3!$A$26:$G$764,7,0) -> 2. Em Teste | H52: 6. Em implementação | I52: Fase I | J52: Package 1 | K52: Package 4 | M52: =IF(VLOOKUP(A52,'Aux - pivots1'!$A:$E,3,0)=0, "",VLOOKUP(A52,'Aux - pivots1'!$A:$E,3,0)) | N52: =IF(VLOOKUP(A52,'Aux - pivots1'!$A:$E,4,0)=0, "",VLOOKUP(A52,'Aux - pivots1'!$A:$E,4,0)) | O52: =IF(VLOOKUP(A52,'Aux - pivots1'!$A:$E,5,0)=0, "",VLOOKUP(A52,'Aux - pivots1'!$A:$E,5,0)) | U52: Plano anterior (alteração nome)
A53: =E53&F53 -> ENERGY_CERTIFICATE_EST_INPUTDATA_ENVIO | B53: Pilar III | C53: Bens Imóveis - Input | D53: 2. Campo | E53: ENERGY_CERTIFICATE_EST_INPUT | F53: DATA_ENVIO | G53: =VLOOKUP(A53,Plano_V3!$A$26:$G$764,7,0) -> 2. Em Teste | H53: 6. Em implementação | I53: Fase I | J53: Package 1 | K53: Package 4 | M53: =IF(VLOOKUP(A53,'Aux - pivots1'!$A:$E,3,0)=0, "",VLOOKUP(A53,'Aux - pivots1'!$A:$E,3,0)) | N53: =IF(VLOOKUP(A53,'Aux - pivots1'!$A:$E,4,0)=0, "",VLOOKUP(A53,'Aux - pivots1'!$A:$E,4,0)) | O53: =IF(VLOOKUP(A53,'Aux - pivots1'!$A:$E,5,0)=0, "",VLOOKUP(A53,'Aux - pivots1'!$A:$E,5,0)) | U53: Plano anterior (alteração nome)
A54: =E54&F54 -> PROCESSn.a. | B54: Pilar III | C54: Bens Imóveis - Output | D54: 1. Universo | E54: PROCESS | F54: n.a. | G54: =VLOOKUP(A54,Plano_V3!$A$26:$G$764,7,0) -> 1. Concluído | H54: 1. Concluído | M54: =IF(VLOOKUP(A54,'Aux - pivots1'!$A:$E,3,0)=0, "",VLOOKUP(A54,'Aux - pivots1'!$A:$E,3,0)) | N54: =IF(VLOOKUP(A54,'Aux - pivots1'!$A:$E,4,0)=0, "",VLOOKUP(A54,'Aux - pivots1'!$A:$E,4,0)) | O54: =IF(VLOOKUP(A54,'Aux - pivots1'!$A:$E,5,0)=0, "",VLOOKUP(A54,'Aux - pivots1'!$A:$E,5,0)) | U54: Plano anterior
A55: =E55&F55 -> PROCESSPROCESS_BANK_ID | B55: Pilar III | C55: Bens Imóveis - Output | D55: 2. Campo | E55: PROCESS | F55: PROCESS_BANK_ID | G55: =VLOOKUP(A55,Plano_V3!$A$26:$G$764,7,0) -> 1. Concluído | H55: 1. Concluído | M55: =IF(VLOOKUP(A55,'Aux - pivots1'!$A:$E,3,0)=0, "",VLOOKUP(A55,'Aux - pivots1'!$A:$E,3,0)) | N55: =IF(VLOOKUP(A55,'Aux - pivots1'!$A:$E,4,0)=0, "",VLOOKUP(A55,'Aux - pivots1'!$A:$E,4,0)) | O55: =IF(VLOOKUP(A55,'Aux - pivots1'!$A:$E,5,0)=0, "",VLOOKUP(A55,'Aux - pivots1'!$A:$E,5,0)) | U55: Plano anterior
A56: =E56&F56 -> PROCESSPROCESS_BRANCH_CODE | B56: Pilar III | C56: Bens Imóveis - Output | D56: 2. Campo | E56: PROCESS | F56: PROCESS_BRANCH_CODE | G56: =VLOOKUP(A56,Plano_V3!$A$26:$G$764,7,0) -> 1. Concluído | H56: 1. Concluído | M56: =IF(VLOOKUP(A56,'Aux - pivots1'!$A:$E,3,0)=0, "",VLOOKUP(A56,'Aux - pivots1'!$A:$E,3,0)) | N56: =IF(VLOOKUP(A56,'Aux - pivots1'!$A:$E,4,0)=0, "",VLOOKUP(A56,'Aux - pivots1'!$A:$E,4,0)) | O56: =IF(VLOOKUP(A56,'Aux - pivots1'!$A:$E,5,0)=0, "",VLOOKUP(A56,'Aux - pivots1'!$A:$E,5,0)) | U56: Plano anterior
A57: =E57&F57 -> PROCESSPROCESS_ACCOUNT_ID | B57: Pilar III | C57: Bens Imóveis - Output | D57: 2. Campo | E57: PROCESS | F57: PROCESS_ACCOUNT_ID | G57: =VLOOKUP(A57,Plano_V3!$A$26:$G$764,7,0) -> 1. Concluído | H57: 1. Concluído | M57: =IF(VLOOKUP(A57,'Aux - pivots1'!$A:$E,3,0)=0, "",VLOOKUP(A57,'Aux - pivots1'!$A:$E,3,0)) | N57: =IF(VLOOKUP(A57,'Aux - pivots1'!$A:$E,4,0)=0, "",VLOOKUP(A57,'Aux - pivots1'!$A:$E,4,0)) | O57: =IF(VLOOKUP(A57,'Aux - pivots1'!$A:$E,5,0)=0, "",VLOOKUP(A57,'Aux - pivots1'!$A:$E,5,0)) | U57: Plano anterior
A58: =E58&F58 -> PROCESScod_estd_prcs | B58: Pilar III | C58: Bens Imóveis - Output | D58: 2. Campo | E58: PROCESS | F58: cod_estd_prcs | G58: =VLOOKUP(A58,Plano_V3!$A$26:$G$764,7,0) -> 0. Cancelado | H58: 0. Cancelado | M58: =IF(VLOOKUP(A58,'Aux - pivots1'!$A:$E,3,0)=0, "",VLOOKUP(A58,'Aux - pivots1'!$A:$E,3,0)) | N58: =IF(VLOOKUP(A58,'Aux - pivots1'!$A:$E,4,0)=0, "",VLOOKUP(A58,'Aux - pivots1'!$A:$E,4,0)) | O58: =IF(VLOOKUP(A58,'Aux - pivots1'!$A:$E,5,0)=0, "",VLOOKUP(A58,'Aux - pivots1'!$A:$E,5,0)) | U58: Plano anterior
A59: =E59&F59 -> PROCESSGUARANTEE_CODE | B59: Pilar III | C59: Bens Imóveis - Output | D59: 2. Campo | E59: PROCESS | F59: GUARANTEE_CODE | G59: =VLOOKUP(A59,Plano_V3!$A$26:$G$764,7,0) -> 1. Concluído | H59: 1. Concluído | M59: =IF(VLOOKUP(A59,'Aux - pivots1'!$A:$E,3,0)=0, "",VLOOKUP(A59,'Aux - pivots1'!$A:$E,3,0)) | N59: =IF(VLOOKUP(A59,'Aux - pivots1'!$A:$E,4,0)=0, "",VLOOKUP(A59,'Aux - pivots1'!$A:$E,4,0)) | O59: =IF(VLOOKUP(A59,'Aux - pivots1'!$A:$E,5,0)=0, "",VLOOKUP(A59,'Aux - pivots1'!$A:$E,5,0)) | U59: Plano anterior
A60: =E60&F60 -> PROCESSCURRENCY_CODE | B60: Pilar III | C60: Bens Imóveis - Output | D60: 2. Campo | E60: PROCESS | F60: CURRENCY_CODE | G60: =VLOOKUP(A60,Plano_V3!$A$26:$G$764,7,0) -> 1. Concluído | H60: 1. Concluído | M60: =IF(VLOOKUP(A60,'Aux - pivots1'!$A:$E,3,0)=0, "",VLOOKUP(A60,'Aux - pivots1'!$A:$E,3,0)) | N60: =IF(VLOOKUP(A60,'Aux - pivots1'!$A:$E,4,0)=0, "",VLOOKUP(A60,'Aux - pivots1'!$A:$E,4,0)) | O60: =IF(VLOOKUP(A60,'Aux - pivots1'!$A:$E,5,0)=0, "",VLOOKUP(A60,'Aux - pivots1'!$A:$E,5,0)) | U60: Plano anterior
A61: =E61&F61 -> PROCESSPROCESS_CAMPAIGN_CODE | B61: Pilar III | C61: Bens Imóveis - Output | D61: 2. Campo | E61: PROCESS | F61: PROCESS_CAMPAIGN_CODE | G61: =VLOOKUP(A61,Plano_V3!$A$26:$G$764,7,0) -> 1. Concluído | H61: 1. Concluído | M61: =IF(VLOOKUP(A61,'Aux - pivots1'!$A:$E,3,0)=0, "",VLOOKUP(A61,'Aux - pivots1'!$A:$E,3,0)) | N61: =IF(VLOOKUP(A61,'Aux - pivots1'!$A:$E,4,0)=0, "",VLOOKUP(A61,'Aux - pivots1'!$A:$E,4,0)) | O61: =IF(VLOOKUP(A61,'Aux - pivots1'!$A:$E,5,0)=0, "",VLOOKUP(A61,'Aux - pivots1'!$A:$E,5,0)) | U61: Plano anterior
A62: =E62&F62 -> PROCESSPROCESS_PRODUCT_ID | B62: Pilar III | C62: Bens Imóveis - Output | D62: 2. Campo | E62: PROCESS | F62: PROCESS_PRODUCT_ID | G62: =VLOOKUP(A62,Plano_V3!$A$26:$G$764,7,0) -> 1. Concluído | H62: 1. Concluído | M62: =IF(VLOOKUP(A62,'Aux - pivots1'!$A:$E,3,0)=0, "",VLOOKUP(A62,'Aux - pivots1'!$A:$E,3,0)) | N62: =IF(VLOOKUP(A62,'Aux - pivots1'!$A:$E,4,0)=0, "",VLOOKUP(A62,'Aux - pivots1'!$A:$E,4,0)) | O62: =IF(VLOOKUP(A62,'Aux - pivots1'!$A:$E,5,0)=0, "",VLOOKUP(A62,'Aux - pivots1'!$A:$E,5,0)) | U62: Plano anterior
A63: =E63&F63 -> PROCESSPROCESS_SUBPRODUCT_ID | B63: Pilar III | C63: Bens Imóveis - Output | D63: 2. Campo | E63: PROCESS | F63: PROCESS_SUBPRODUCT_ID | G63: =VLOOKUP(A63,Plano_V3!$A$26:$G$764,7,0) -> 1. Concluído | H63: 1. Concluído | M63: =IF(VLOOKUP(A63,'Aux - pivots1'!$A:$E,3,0)=0, "",VLOOKUP(A63,'Aux - pivots1'!$A:$E,3,0)) | N63: =IF(VLOOKUP(A63,'Aux - pivots1'!$A:$E,4,0)=0, "",VLOOKUP(A63,'Aux - pivots1'!$A:$E,4,0)) | O63: =IF(VLOOKUP(A63,'Aux - pivots1'!$A:$E,5,0)=0, "",VLOOKUP(A63,'Aux - pivots1'!$A:$E,5,0)) | U63: Plano anterior
A64: =E64&F64 -> PROCESSGUARANTEE_TYPE_CODE | B64: Pilar III | C64: Bens Imóveis - Output | D64: 2. Campo | E64: PROCESS | F64: GUARANTEE_TYPE_CODE | G64: =VLOOKUP(A64,Plano_V3!$A$26:$G$764,7,0) -> 1. Concluído | H64: 1. Concluído | M64: =IF(VLOOKUP(A64,'Aux - pivots1'!$A:$E,3,0)=0, "",VLOOKUP(A64,'Aux - pivots1'!$A:$E,3,0)) | N64: =IF(VLOOKUP(A64,'Aux - pivots1'!$A:$E,4,0)=0, "",VLOOKUP(A64,'Aux - pivots1'!$A:$E,4,0)) | O64: =IF(VLOOKUP(A64,'Aux - pivots1'!$A:$E,5,0)=0, "",VLOOKUP(A64,'Aux - pivots1'!$A:$E,5,0)) | U64: Plano anterior
A65: =E65&F65 -> PROCESSPROCESS_REFERENCE_CODE | B65: Pilar III | C65: Bens Imóveis - Output | D65: 2. Campo | E65: PROCESS | F65: PROCESS_REFERENCE_CODE | G65: =VLOOKUP(A65,Plano_V3!$A$26:$G$764,7,0) -> 1. Concluído | H65: 1. Concluído | M65: =IF(VLOOKUP(A65,'Aux - pivots1'!$A:$E,3,0)=0, "",VLOOKUP(A65,'Aux - pivots1'!$A:$E,3,0)) | N65: =IF(VLOOKUP(A65,'Aux - pivots1'!$A:$E,4,0)=0, "",VLOOKUP(A65,'Aux - pivots1'!$A:$E,4,0)) | O65: =IF(VLOOKUP(A65,'Aux - pivots1'!$A:$E,5,0)=0, "",VLOOKUP(A65,'Aux - pivots1'!$A:$E,5,0)) | U65: Plano anterior
... A152: =E152&F152 -> PROPERTY_ENERGY_CERTIFICATEEPC_EXPIRATION_DATE | B152: Pilar III | C152: Bens Imóveis - Output | D152: 2. Campo | E152: PROPERTY_ENERGY_CERTIFICATE | F152: EPC_EXPIRATION_DATE | G152: =VLOOKUP(A152,Plano_V3!$A$26:$G$764,7,0) -> 1. Concluído | H152: 1. Concluído | M152: =IF(VLOOKUP(A152,'Aux - pivots1'!$A:$E,3,0)=0, "",VLOOKUP(A152,'Aux - pivots1'!$A:$E,3,0)) | N152: =IF(VLOOKUP(A152,'Aux - pivots1'!$A:$E,4,0)=0, "",VLOOKUP(A152,'Aux - pivots1'!$A:$E,4,0)) | O152: =IF(VLOOKUP(A152,'Aux - pivots1'!$A:$E,5,0)=0, "",VLOOKUP(A152,'Aux - pivots1'!$A:$E,5,0)) | U152: Plano anterior
A153: =E153&F153 -> PROPERTY_ENERGY_CERTIFICATEEPC | B153: Pilar III | C153: Bens Imóveis - Output | D153: 2. Campo | E153: PROPERTY_ENERGY_CERTIFICATE | F153: EPC | G153: =VLOOKUP(A153,Plano_V3!$A$26:$G$764,7,0) -> 2.1 Em Teste | H153: 6. Em implementação | J153: Package 1 | K153: Package 3 | M153: =IF(VLOOKUP(A153,'Aux - pivots1'!$A:$E,3,0)=0, "",VLOOKUP(A153,'Aux - pivots1'!$A:$E,3,0)) | N153: =IF(VLOOKUP(A153,'Aux - pivots1'!$A:$E,4,0)=0, "",VLOOKUP(A153,'Aux - pivots1'!$A:$E,4,0)) | O153: =IF(VLOOKUP(A153,'Aux - pivots1'!$A:$E,5,0)=0, "",VLOOKUP(A153,'Aux - pivots1'!$A:$E,5,0)) | U153: Plano anterior
A154: =E154&F154 -> PROPERTY_ENERGY_CERTIFICATEENERGY_CONSUMPTION_TYPE_S_IND | B154: Pilar III | C154: Bens Imóveis - Output | D154: 2. Campo | E154: PROPERTY_ENERGY_CERTIFICATE | F154: ENERGY_CONSUMPTION_TYPE_S_IND | G154: =VLOOKUP(A154,Plano_V3!$A$26:$G$764,7,0) -> 1. Concluído | H154: 1. Concluído | M154: =IF(VLOOKUP(A154,'Aux - pivots1'!$A:$E,3,0)=0, "",VLOOKUP(A154,'Aux - pivots1'!$A:$E,3,0)) | N154: =IF(VLOOKUP(A154,'Aux - pivots1'!$A:$E,4,0)=0, "",VLOOKUP(A154,'Aux - pivots1'!$A:$E,4,0)) | O154: =IF(VLOOKUP(A154,'Aux - pivots1'!$A:$E,5,0)=0, "",VLOOKUP(A154,'Aux - pivots1'!$A:$E,5,0)) | U154: Plano anterior
A155: =E155&F155 -> PROPERTY_ENERGY_CERTIFICATEENERGY_CONSUMPTION_TYPE_T_IND | B155: Pilar III | C155: Bens Imóveis - Output | D155: 2. Campo | E155: PROPERTY_ENERGY_CERTIFICATE | F155: ENERGY_CONSUMPTION_TYPE_T_IND | G155: =VLOOKUP(A155,Plano_V3!$A$26:$G$764,7,0) -> 1. Concluído | H155: 1. Concluído | M155: =IF(VLOOKUP(A155,'Aux - pivots1'!$A:$E,3,0)=0, "",VLOOKUP(A155,'Aux - pivots1'!$A:$E,3,0)) | N155: =IF(VLOOKUP(A155,'Aux - pivots1'!$A:$E,4,0)=0, "",VLOOKUP(A155,'Aux - pivots1'!$A:$E,4,0)) | O155: =IF(VLOOKUP(A155,'Aux - pivots1'!$A:$E,5,0)=0, "",VLOOKUP(A155,'Aux - pivots1'!$A:$E,5,0)) | U155: Plano anterior
A156: =E156&F156 -> PROPERTY_ENERGY_CERTIFICATEENERGY_EFFICIENCY_IND | B156: Pilar III | C156: Bens Imóveis - Output | D156: 2. Campo | E156: PROPERTY_ENERGY_CERTIFICATE | F156: ENERGY_EFFICIENCY_IND | G156: =VLOOKUP(A156,Plano_V3!$A$26:$G$764,7,0) -> 1. Concluído | H156: 1. Concluído | M156: =IF(VLOOKUP(A156,'Aux - pivots1'!$A:$E,3,0)=0, "",VLOOKUP(A156,'Aux - pivots1'!$A:$E,3,0)) | N156: =IF(VLOOKUP(A156,'Aux - pivots1'!$A:$E,4,0)=0, "",VLOOKUP(A156,'Aux - pivots1'!$A:$E,4,0)) | O156: =IF(VLOOKUP(A156,'Aux - pivots1'!$A:$E,5,0)=0, "",VLOOKUP(A156,'Aux - pivots1'!$A:$E,5,0)) | U156: Plano anterior
A157: =E157&F157 -> PROPERTY_ENERGY_CERTIFICATEREN_ENERGY_EFFICIENCY_IND | B157: Pilar III | C157: Bens Imóveis - Output | D157: 2. Campo | E157: PROPERTY_ENERGY_CERTIFICATE | F157: REN_ENERGY_EFFICIENCY_IND | G157: =VLOOKUP(A157,Plano_V3!$A$26:$G$764,7,0) -> 1. Concluído | H157: 1. Concluído | M157: =IF(VLOOKUP(A157,'Aux - pivots1'!$A:$E,3,0)=0, "",VLOOKUP(A157,'Aux - pivots1'!$A:$E,3,0)) | N157: =IF(VLOOKUP(A157,'Aux - pivots1'!$A:$E,4,0)=0, "",VLOOKUP(A157,'Aux - pivots1'!$A:$E,4,0)) | O157: =IF(VLOOKUP(A157,'Aux - pivots1'!$A:$E,5,0)=0, "",VLOOKUP(A157,'Aux - pivots1'!$A:$E,5,0)) | U157: Plano anterior
A158: =E158&F158 -> PROPERTY_ENERGY_CERTIFICATENZEB_IND | B158: Pilar III | C158: Bens Imóveis - Output | D158: 2. Campo | E158: PROPERTY_ENERGY_CERTIFICATE | F158: NZEB_IND | G158: =VLOOKUP(A158,Plano_V3!$A$26:$G$764,7,0) -> 1. Concluído | H158: 1. Concluído | M158: =IF(VLOOKUP(A158,'Aux - pivots1'!$A:$E,3,0)=0, "",VLOOKUP(A158,'Aux - pivots1'!$A:$E,3,0)) | N158: =IF(VLOOKUP(A158,'Aux - pivots1'!$A:$E,4,0)=0, "",VLOOKUP(A158,'Aux - pivots1'!$A:$E,4,0)) | O158: =IF(VLOOKUP(A158,'Aux - pivots1'!$A:$E,5,0)=0, "",VLOOKUP(A158,'Aux - pivots1'!$A:$E,5,0)) | U158: Plano anterior
A159: =E159&F159 -> PROPERTY_ENERGY_CERTIFICATEACTUAL_VALUE_IND | B159: Pilar III | C159: Bens Imóveis - Output | D159: 2. Campo | E159: PROPERTY_ENERGY_CERTIFICATE | F159: ACTUAL_VALUE_IND | G159: =VLOOKUP(A159,Plano_V3!$A$26:$G$764,7,0) -> 1. Concluído | H159: 1. Concluído | M159: =IF(VLOOKUP(A159,'Aux - pivots1'!$A:$E,3,0)=0, "",VLOOKUP(A159,'Aux - pivots1'!$A:$E,3,0)) | N159: =IF(VLOOKUP(A159,'Aux - pivots1'!$A:$E,4,0)=0, "",VLOOKUP(A159,'Aux - pivots1'!$A:$E,4,0)) | O159: =IF(VLOOKUP(A159,'Aux - pivots1'!$A:$E,5,0)=0, "",VLOOKUP(A159,'Aux - pivots1'!$A:$E,5,0)) | U159: Plano anterior
A160: =E160&F160 -> PROPERTY_ENERGY_CERTIFICATEEP_SCORE | B160: Pilar III | C160: Bens Imóveis - Output | D160: 2. Campo | E160: PROPERTY_ENERGY_CERTIFICATE | F160: EP_SCORE | G160: 4. Validação EF | H160: 6. Em implementação | J160: Package 1 | K160: Package 3 | M160: =IF(VLOOKUP(A160,'Aux - pivots1'!$A:$E,3,0)=0, "",VLOOKUP(A160,'Aux - pivots1'!$A:$E,3,0)) | N160: =IF(VLOOKUP(A160,'Aux - pivots1'!$A:$E,4,0)=0, "",VLOOKUP(A160,'Aux - pivots1'!$A:$E,4,0)) | O160: =IF(VLOOKUP(A160,'Aux - pivots1'!$A:$E,5,0)=0, "",VLOOKUP(A160,'Aux - pivots1'!$A:$E,5,0)) | U160: Plano anterior
A161: =E161&F161 -> PROPERTY_ENERGY_CERTIFICATEPRMRY_ENRGY_DMND_RFRNC_VL | B161: Pilar III | C161: Bens Imóveis - Output | D161: 2. Campo | E161: PROPERTY_ENERGY_CERTIFICATE | F161: PRMRY_ENRGY_DMND_RFRNC_VL | G161: =VLOOKUP(A161,Plano_V3!$A$26:$G$764,7,0) -> 6. Em implementação | M161: =IF(VLOOKUP(A161,'Aux - pivots1'!$A:$E,3,0)=0, "",VLOOKUP(A161,'Aux - pivots1'!$A:$E,3,0)) -> #N/A | N161: =IF(VLOOKUP(A161,'Aux - pivots1'!$A:$E,4,0)=0, "",VLOOKUP(A161,'Aux - pivots1'!$A:$E,4,0)) -> #N/A | O161: =IF(VLOOKUP(A161,'Aux - pivots1'!$A:$E,5,0)=0, "",VLOOKUP(A161,'Aux - pivots1'!$A:$E,5,0)) -> #N/A
A162: =E162&F162 -> PROPERTY_ENERGY_CERTIFICATESOURCE_CODE | B162: Pilar III | C162: Bens Imóveis - Output | D162: 2. Campo | E162: PROPERTY_ENERGY_CERTIFICATE | F162: SOURCE_CODE | G162: =VLOOKUP(A162,Plano_V3!$A$26:$G$764,7,0) -> 1. Concluído | H162: 1. Concluído | M162: =IF(VLOOKUP(A162,'Aux - pivots1'!$A:$E,3,0)=0, "",VLOOKUP(A162,'Aux - pivots1'!$A:$E,3,0)) | N162: =IF(VLOOKUP(A162,'Aux - pivots1'!$A:$E,4,0)=0, "",VLOOKUP(A162,'Aux - pivots1'!$A:$E,4,0)) | O162: =IF(VLOOKUP(A162,'Aux - pivots1'!$A:$E,5,0)=0, "",VLOOKUP(A162,'Aux - pivots1'!$A:$E,5,0)) | U162: Plano anterior
A163: =E163&F163 -> PROPERTY_ENERGY_CERTIFICATEDATA_DATE_PART | B163: Pilar III | C163: Bens Imóveis - Output | D163: 2. Campo | E163: PROPERTY_ENERGY_CERTIFICATE | F163: DATA_DATE_PART | G163: =VLOOKUP(A163,Plano_V3!$A$26:$G$764,7,0) -> 1. Concluído | H163: 1. Concluído | M163: =IF(VLOOKUP(A163,'Aux - pivots1'!$A:$E,3,0)=0, "",VLOOKUP(A163,'Aux - pivots1'!$A:$E,3,0)) | N163: =IF(VLOOKUP(A163,'Aux - pivots1'!$A:$E,4,0)=0, "",VLOOKUP(A163,'Aux - pivots1'!$A:$E,4,0)) | O163: =IF(VLOOKUP(A163,'Aux - pivots1'!$A:$E,5,0)=0, "",VLOOKUP(A163,'Aux - pivots1'!$A:$E,5,0)) | U163: Plano anterior
A164: =E164&F164 -> PROPERTY_ENERGY_CERTIFICATECERTIFICATE_TYPE | B164: Pilar III | C164: Bens Imóveis - Output | D164: 2. Campo | E164: PROPERTY_ENERGY_CERTIFICATE | F164: CERTIFICATE_TYPE | G164: =VLOOKUP(A164,Plano_V3!$A$26:$G$764,7,0) -> 1. Concluído | H164: 1. Concluído | M164: =IF(VLOOKUP(A164,'Aux - pivots1'!$A:$E,3,0)=0, "",VLOOKUP(A164,'Aux - pivots1'!$A:$E,3,0)) | N164: =IF(VLOOKUP(A164,'Aux - pivots1'!$A:$E,4,0)=0, "",VLOOKUP(A164,'Aux - pivots1'!$A:$E,4,0)) | O164: =IF(VLOOKUP(A164,'Aux - pivots1'!$A:$E,5,0)=0, "",VLOOKUP(A164,'Aux - pivots1'!$A:$E,5,0)) | U164: Plano anterior
A165: =E165&F165 -> PROPERTY_ENERGY_CERTIFICATEBUILDING_DOMEST_HOTWATER_VALUE | B165: Pilar III | C165: Bens Imóveis - Output | D165: 2. Campo | E165: PROPERTY_ENERGY_CERTIFICATE | F165: BUILDING_DOMEST_HOTWATER_VALUE | G165: =VLOOKUP(A165,Plano_V3!$A$26:$G$764,7,0) -> 1. Concluído | H165: 1. Concluído | M165: =IF(VLOOKUP(A165,'Aux - pivots1'!$A:$E,3,0)=0, "",VLOOKUP(A165,'Aux - pivots1'!$A:$E,3,0)) | N165: =IF(VLOOKUP(A165,'Aux - pivots1'!$A:$E,4,0)=0, "",VLOOKUP(A165,'Aux - pivots1'!$A:$E,4,0)) | O165: =IF(VLOOKUP(A165,'Aux - pivots1'!$A:$E,5,0)=0, "",VLOOKUP(A165,'Aux - pivots1'!$A:$E,5,0)) | U165: Plano anterior
A166: =E166&F166 -> PROPERTY_ENERGY_CERTIFICATERENEWABLE_DOMEST_HOTWATER_VALUE | B166: Pilar III | C166: Bens Imóveis - Output | D166: 2. Campo | E166: PROPERTY_ENERGY_CERTIFICATE | F166: RENEWABLE_DOMEST_HOTWATER_VALUE | G166: =VLOOKUP(A166,Plano_V3!$A$26:$G$764,7,0) -> 1. Concluído | H166: 1. Concluído | M166: =IF(VLOOKUP(A166,'Aux - pivots1'!$A:$E,3,0)=0, "",VLOOKUP(A166,'Aux - pivots1'!$A:$E,3,0)) | N166: =IF(VLOOKUP(A166,'Aux - pivots1'!$A:$E,4,0)=0, "",VLOOKUP(A166,'Aux - pivots1'!$A:$E,4,0)) | O166: =IF(VLOOKUP(A166,'Aux - pivots1'!$A:$E,5,0)=0, "",VLOOKUP(A166,'Aux - pivots1'!$A:$E,5,0)) | U166: Plano anterior
A167: =E167&F167 -> PROPERTY_ENERGY_CERTIFICATEDOMEST_HOTWATER_REF_VALUE | B167: Pilar III | C167: Bens Imóveis - Output | D167: 2. Campo | E167: PROPERTY_ENERGY_CERTIFICATE | F167: DOMEST_HOTWATER_REF_VALUE | G167: =VLOOKUP(A167,Plano_V3!$A$26:$G$764,7,0) -> 1. Concluído | H167: 1. Concluído | M167: =IF(VLOOKUP(A167,'Aux - pivots1'!$A:$E,3,0)=0, "",VLOOKUP(A167,'Aux - pivots1'!$A:$E,3,0)) | N167: =IF(VLOOKUP(A167,'Aux - pivots1'!$A:$E,4,0)=0, "",VLOOKUP(A167,'Aux - pivots1'!$A:$E,4,0)) | O167: =IF(VLOOKUP(A167,'Aux - pivots1'!$A:$E,5,0)=0, "",VLOOKUP(A167,'Aux - pivots1'!$A:$E,5,0)) | U167: Plano anterior
A168: =E168&F168 -> PROPERTY_ENERGY_CERTIFICATEHEIGHT | B168: Pilar III | C168: Bens Imóveis - Output | D168: 2. Campo | E168: PROPERTY_ENERGY_CERTIFICATE | F168: HEIGHT | G168: =VLOOKUP(A168,Plano_V3!$A$26:$G$764,7,0) -> 1. Concluído | H168: 1. Concluído | M168: =IF(VLOOKUP(A168,'Aux - pivots1'!$A:$E,3,0)=0, "",VLOOKUP(A168,'Aux - pivots1'!$A:$E,3,0)) | N168: =IF(VLOOKUP(A168,'Aux - pivots1'!$A:$E,4,0)=0, "",VLOOKUP(A168,'Aux - pivots1'!$A:$E,4,0)) | O168: =IF(VLOOKUP(A168,'Aux - pivots1'!$A:$E,5,0)=0, "",VLOOKUP(A168,'Aux - pivots1'!$A:$E,5,0)) | U168: Plano anterior
A169: =E169&F169 -> PROPERTY_ENERGY_CERTIFICATEBUILDING_SPACE_HEATING_VALUE | B169: Pilar III | C169: Bens Imóveis - Output | D169: 2. Campo | E169: PROPERTY_ENERGY_CERTIFICATE | F169: BUILDING_SPACE_HEATING_VALUE | G169: =VLOOKUP(A169,Plano_V3!$A$26:$G$764,7,0) -> 1. Concluído | H169: 1. Concluído | M169: =IF(VLOOKUP(A169,'Aux - pivots1'!$A:$E,3,0)=0, "",VLOOKUP(A169,'Aux - pivots1'!$A:$E,3,0)) | N169: =IF(VLOOKUP(A169,'Aux - pivots1'!$A:$E,4,0)=0, "",VLOOKUP(A169,'Aux - pivots1'!$A:$E,4,0)) | O169: =IF(VLOOKUP(A169,'Aux - pivots1'!$A:$E,5,0)=0, "",VLOOKUP(A169,'Aux - pivots1'!$A:$E,5,0)) | U169: Plano anterior
A170: =E170&F170 -> PROPERTY_ENERGY_CERTIFICATESPACE_HEATING_REF_VALUE | B170: Pilar III | C170: Bens Imóveis - Output | D170: 2. Campo | E170: PROPERTY_ENERGY_CERTIFICATE | F170: SPACE_HEATING_REF_VALUE | G170: =VLOOKUP(A170,Plano_V3!$A$26:$G$764,7,0) -> 1. Concluído | H170: 1. Concluído | M170: =IF(VLOOKUP(A170,'Aux - pivots1'!$A:$E,3,0)=0, "",VLOOKUP(A170,'Aux - pivots1'!$A:$E,3,0)) | N170: =IF(VLOOKUP(A170,'Aux - pivots1'!$A:$E,4,0)=0, "",VLOOKUP(A170,'Aux - pivots1'!$A:$E,4,0)) | O170: =IF(VLOOKUP(A170,'Aux - pivots1'!$A:$E,5,0)=0, "",VLOOKUP(A170,'Aux - pivots1'!$A:$E,5,0)) | U170: Plano anterior
A171: =E171&F171 -> PROPERTY_ENERGY_CERTIFICATERENEWABLE_SPACE_HEATING_VALUE | B171: Pilar III | C171: Bens Imóveis - Output | D171: 2. Campo | E171: PROPERTY_ENERGY_CERTIFICATE | F171: RENEWABLE_SPACE_HEATING_VALUE | G171: =VLOOKUP(A171,Plano_V3!$A$26:$G$764,7,0) -> 1. Concluído | H171: 1. Concluído | M171: =IF(VLOOKUP(A171,'Aux - pivots1'!$A:$E,3,0)=0, "",VLOOKUP(A171,'Aux - pivots1'!$A:$E,3,0)) | N171: =IF(VLOOKUP(A171,'Aux - pivots1'!$A:$E,4,0)=0, "",VLOOKUP(A171,'Aux - pivots1'!$A:$E,4,0)) | O171: =IF(VLOOKUP(A171,'Aux - pivots1'!$A:$E,5,0)=0, "",VLOOKUP(A171,'Aux - pivots1'!$A:$E,5,0)) | U171: Plano anterior
A172: =E172&F172 -> PROPERTY_ENERGY_CERTIFICATEBUILDING_SPACE_COOLING_VALUE | B172: Pilar III | C172: Bens Imóveis - Output | D172: 2. Campo | E172: PROPERTY_ENERGY_CERTIFICATE | F172: BUILDING_SPACE_COOLING_VALUE | G172: =VLOOKUP(A172,Plano_V3!$A$26:$G$764,7,0) -> 1. Concluído | H172: 1. Concluído | M172: =IF(VLOOKUP(A172,'Aux - pivots1'!$A:$E,3,0)=0, "",VLOOKUP(A172,'Aux - pivots1'!$A:$E,3,0)) | N172: =IF(VLOOKUP(A172,'Aux - pivots1'!$A:$E,4,0)=0, "",VLOOKUP(A172,'Aux - pivots1'!$A:$E,4,0)) | O172: =IF(VLOOKUP(A172,'Aux - pivots1'!$A:$E,5,0)=0, "",VLOOKUP(A172,'Aux - pivots1'!$A:$E,5,0)) | U172: Plano anterior
A173: =E173&F173 -> PROPERTY_ENERGY_CERTIFICATERENEWABLE_SPACE_COOLING_VALUE | B173: Pilar III | C173: Bens Imóveis - Output | D173: 2. Campo | E173: PROPERTY_ENERGY_CERTIFICATE | F173: RENEWABLE_SPACE_COOLING_VALUE | G173: =VLOOKUP(A173,Plano_V3!$A$26:$G$764,7,0) -> 1. Concluído | H173: 1. Concluído | M173: =IF(VLOOKUP(A173,'Aux - pivots1'!$A:$E,3,0)=0, "",VLOOKUP(A173,'Aux - pivots1'!$A:$E,3,0)) | N173: =IF(VLOOKUP(A173,'Aux - pivots1'!$A:$E,4,0)=0, "",VLOOKUP(A173,'Aux - pivots1'!$A:$E,4,0)) | O173: =IF(VLOOKUP(A173,'Aux - pivots1'!$A:$E,5,0)=0, "",VLOOKUP(A173,'Aux - pivots1'!$A:$E,5,0)) | U173: Plano anterior
... A175: =E175&F175 -> PROPERTY_ENERGY_CERTIFICATEENERGY_CLASS_AFTER_MEASUREMENT | B175: Pilar III | C175: Bens Imóveis - Output | D175: 2. Campo | E175: PROPERTY_ENERGY_CERTIFICATE | F175: ENERGY_CLASS_AFTER_MEASUREMENT | G175: =VLOOKUP(A175,Plano_V3!$A$26:$G$764,7,0) -> 1. Concluído | H175: 1. Concluído | M175: =IF(VLOOKUP(A175,'Aux - pivots1'!$A:$E,3,0)=0, "",VLOOKUP(A175,'Aux - pivots1'!$A:$E,3,0)) | N175: =IF(VLOOKUP(A175,'Aux - pivots1'!$A:$E,4,0)=0, "",VLOOKUP(A175,'Aux - pivots1'!$A:$E,4,0)) | O175: =IF(VLOOKUP(A175,'Aux - pivots1'!$A:$E,5,0)=0, "",VLOOKUP(A175,'Aux - pivots1'!$A:$E,5,0)) | U175: Plano anterior
A176: =E176&F176 -> PROPERTY_ENERGY_CERTIFICATEENERGY_CONSUMPTION_VALUE_YEAR | B176: Pilar III | C176: Bens Imóveis - Output | D176: 2. Campo | E176: PROPERTY_ENERGY_CERTIFICATE | F176: ENERGY_CONSUMPTION_VALUE_YEAR | G176: =VLOOKUP(A176,Plano_V3!$A$26:$G$764,7,0) -> 4. Validação EF | H176: 6. Em implementação | J176: Package 1 | K176: Package 3 | M176: =IF(VLOOKUP(A176,'Aux - pivots1'!$A:$E,3,0)=0, "",VLOOKUP(A176,'Aux - pivots1'!$A:$E,3,0)) | N176: =IF(VLOOKUP(A176,'Aux - pivots1'!$A:$E,4,0)=0, "",VLOOKUP(A176,'Aux - pivots1'!$A:$E,4,0)) | O176: =IF(VLOOKUP(A176,'Aux - pivots1'!$A:$E,5,0)=0, "",VLOOKUP(A176,'Aux - pivots1'!$A:$E,5,0)) | U176: Plano anterior
A177: =E177&F177 -> PROPERTY_ENERGY_CERTIFICATETHERMAL_BEHAVIOUR_ROOF | B177: Pilar III | C177: Bens Imóveis - Output | D177: 2. Campo | E177: PROPERTY_ENERGY_CERTIFICATE | F177: THERMAL_BEHAVIOUR_ROOF | G177: =VLOOKUP(A177,Plano_V3!$A$26:$G$764,7,0) -> 1. Concluído | H177: 1. Concluído | M177: =IF(VLOOKUP(A177,'Aux - pivots1'!$A:$E,3,0)=0, "",VLOOKUP(A177,'Aux - pivots1'!$A:$E,3,0)) | N177: =IF(VLOOKUP(A177,'Aux - pivots1'!$A:$E,4,0)=0, "",VLOOKUP(A177,'Aux - pivots1'!$A:$E,4,0)) | O177: =IF(VLOOKUP(A177,'Aux - pivots1'!$A:$E,5,0)=0, "",VLOOKUP(A177,'Aux - pivots1'!$A:$E,5,0)) | U177: Plano anterior
A178: =E178&F178 -> PROPERTY_ENERGY_CERTIFICATETHERMAL_BEHAVIOUR_WINDOWS | B178: Pilar III | C178: Bens Imóveis - Output | D178: 2. Campo | E178: PROPERTY_ENERGY_CERTIFICATE | F178: THERMAL_BEHAVIOUR_WINDOWS | G178: =VLOOKUP(A178,Plano_V3!$A$26:$G$764,7,0) -> 1. Concluído | H178: 1. Concluído | M178: =IF(VLOOKUP(A178,'Aux - pivots1'!$A:$E,3,0)=0, "",VLOOKUP(A178,'Aux - pivots1'!$A:$E,3,0)) | N178: =IF(VLOOKUP(A178,'Aux - pivots1'!$A:$E,4,0)=0, "",VLOOKUP(A178,'Aux - pivots1'!$A:$E,4,0)) | O178: =IF(VLOOKUP(A178,'Aux - pivots1'!$A:$E,5,0)=0, "",VLOOKUP(A178,'Aux - pivots1'!$A:$E,5,0)) | U178: Plano anterior
A179: =E179&F179 -> PROPERTY_ENERGY_CERTIFICATETHERMAL_BEHAVIOUR_WALL | B179: Pilar III | C179: Bens Imóveis - Output | D179: 2. Campo | E179: PROPERTY_ENERGY_CERTIFICATE | F179: THERMAL_BEHAVIOUR_WALL | G179: =VLOOKUP(A179,Plano_V3!$A$26:$G$764,7,0) -> 1. Concluído | H179: 1. Concluído | M179: =IF(VLOOKUP(A179,'Aux - pivots1'!$A:$E,3,0)=0, "",VLOOKUP(A179,'Aux - pivots1'!$A:$E,3,0)) | N179: =IF(VLOOKUP(A179,'Aux - pivots1'!$A:$E,4,0)=0, "",VLOOKUP(A179,'Aux - pivots1'!$A:$E,4,0)) | O179: =IF(VLOOKUP(A179,'Aux - pivots1'!$A:$E,5,0)=0, "",VLOOKUP(A179,'Aux - pivots1'!$A:$E,5,0)) | U179: Plano anterior
A180: =E180&F180 -> PROPERTY_ENERGY_CERTIFICATETHERMAL_BEHAVIOUR_FLOORS | B180: Pilar III | C180: Bens Imóveis - Output | D180: 2. Campo | E180: PROPERTY_ENERGY_CERTIFICATE | F180: THERMAL_BEHAVIOUR_FLOORS | G180: =VLOOKUP(A180,Plano_V3!$A$26:$G$764,7,0) -> 1. Concluído | H180: 1. Concluído | M180: =IF(VLOOKUP(A180,'Aux - pivots1'!$A:$E,3,0)=0, "",VLOOKUP(A180,'Aux - pivots1'!$A:$E,3,0)) | N180: =IF(VLOOKUP(A180,'Aux - pivots1'!$A:$E,4,0)=0, "",VLOOKUP(A180,'Aux - pivots1'!$A:$E,4,0)) | O180: =IF(VLOOKUP(A180,'Aux - pivots1'!$A:$E,5,0)=0, "",VLOOKUP(A180,'Aux - pivots1'!$A:$E,5,0)) | U180: Plano anterior
A181: =E181&F181 -> PROPERTY_ENERGY_CERTIFICATETHERMAL_BEHAVIOUR_TECH_SYS_VENT | B181: Pilar III | C181: Bens Imóveis - Output | D181: 2. Campo | E181: PROPERTY_ENERGY_CERTIFICATE | F181: THERMAL_BEHAVIOUR_TECH_SYS_VENT | G181: =VLOOKUP(A181,Plano_V3!$A$26:$G$764,7,0) -> 1. Concluído | H181: 1. Concluído | M181: =IF(VLOOKUP(A181,'Aux - pivots1'!$A:$E,3,0)=0, "",VLOOKUP(A181,'Aux - pivots1'!$A:$E,3,0)) | N181: =IF(VLOOKUP(A181,'Aux - pivots1'!$A:$E,4,0)=0, "",VLOOKUP(A181,'Aux - pivots1'!$A:$E,4,0)) | O181: =IF(VLOOKUP(A181,'Aux - pivots1'!$A:$E,5,0)=0, "",VLOOKUP(A181,'Aux - pivots1'!$A:$E,5,0)) | U181: Plano anterior
A182: =E182&F182 -> PROPERTY_ENERGY_CERTIFICATETOTAL_INVSTMNT_ESTMTD_VALUE | B182: Pilar III | C182: Bens Imóveis - Output | D182: 2. Campo | E182: PROPERTY_ENERGY_CERTIFICATE | F182: TOTAL_INVSTMNT_ESTMTD_VALUE | G182: =VLOOKUP(A182,Plano_V3!$A$26:$G$764,7,0) -> 1. Concluído | H182: 1. Concluído | M182: =IF(VLOOKUP(A182,'Aux - pivots1'!$A:$E,3,0)=0, "",VLOOKUP(A182,'Aux - pivots1'!$A:$E,3,0)) | N182: =IF(VLOOKUP(A182,'Aux - pivots1'!$A:$E,4,0)=0, "",VLOOKUP(A182,'Aux - pivots1'!$A:$E,4,0)) | O182: =IF(VLOOKUP(A182,'Aux - pivots1'!$A:$E,5,0)=0, "",VLOOKUP(A182,'Aux - pivots1'!$A:$E,5,0)) | U182: Plano anterior
A183: =E183&F183 -> PROPERTY_ENERGY_CERTIFICATEDURATION_SUMMER | B183: Pilar III | C183: Bens Imóveis - Output | D183: 2. Campo | E183: PROPERTY_ENERGY_CERTIFICATE | F183: DURATION_SUMMER | G183: =VLOOKUP(A183,Plano_V3!$A$26:$G$764,7,0) -> 1. Concluído | H183: 1. Concluído | M183: =IF(VLOOKUP(A183,'Aux - pivots1'!$A:$E,3,0)=0, "",VLOOKUP(A183,'Aux - pivots1'!$A:$E,3,0)) | N183: =IF(VLOOKUP(A183,'Aux - pivots1'!$A:$E,4,0)=0, "",VLOOKUP(A183,'Aux - pivots1'!$A:$E,4,0)) | O183: =IF(VLOOKUP(A183,'Aux - pivots1'!$A:$E,5,0)=0, "",VLOOKUP(A183,'Aux - pivots1'!$A:$E,5,0)) | U183: Plano anterior
A184: =E184&F184 -> PROPERTY_ENERGY_CERTIFICATEDURATION_WINTER | B184: Pilar III | C184: Bens Imóveis - Output | D184: 2. Campo | E184: PROPERTY_ENERGY_CERTIFICATE | F184: DURATION_WINTER | G184: =VLOOKUP(A184,Plano_V3!$A$26:$G$764,7,0) -> 1. Concluído | H184: 1. Concluído | M184: =IF(VLOOKUP(A184,'Aux - pivots1'!$A:$E,3,0)=0, "",VLOOKUP(A184,'Aux - pivots1'!$A:$E,3,0)) | N184: =IF(VLOOKUP(A184,'Aux - pivots1'!$A:$E,4,0)=0, "",VLOOKUP(A184,'Aux - pivots1'!$A:$E,4,0)) | O184: =IF(VLOOKUP(A184,'Aux - pivots1'!$A:$E,5,0)=0, "",VLOOKUP(A184,'Aux - pivots1'!$A:$E,5,0)) | U184: Plano anterior
A185: =E185&F185 -> PROPERTY_ENERGY_CERTIFICATECARBON_EMISSION_VALUE_YEAR | B185: Pilar III | C185: Bens Imóveis - Output | D185: 2. Campo | E185: PROPERTY_ENERGY_CERTIFICATE | F185: CARBON_EMISSION_VALUE_YEAR | G185: =VLOOKUP(A185,Plano_V3!$A$26:$G$764,7,0) -> 2.1 Em Teste | H185: 6. Em implementação | J185: Package 1 | K185: Package 3 | M185: =IF(VLOOKUP(A185,'Aux - pivots1'!$A:$E,3,0)=0, "",VLOOKUP(A185,'Aux - pivots1'!$A:$E,3,0)) | N185: =IF(VLOOKUP(A185,'Aux - pivots1'!$A:$E,4,0)=0, "",VLOOKUP(A185,'Aux - pivots1'!$A:$E,4,0)) | O185: =IF(VLOOKUP(A185,'Aux - pivots1'!$A:$E,5,0)=0, "",VLOOKUP(A185,'Aux - pivots1'!$A:$E,5,0)) | U185: Plano anterior
A186: =E186&F186 -> PROPERTY_ENERGY_CERTIFICATECARBON_EMISSION_VALUE | B186: Pilar III | C186: Bens Imóveis - Output | D186: 2. Campo | E186: PROPERTY_ENERGY_CERTIFICATE | F186: CARBON_EMISSION_VALUE | G186: =VLOOKUP(A186,Plano_V3!$A$26:$G$764,7,0) -> 1. Concluído | H186: 1. Concluído | M186: =IF(VLOOKUP(A186,'Aux - pivots1'!$A:$E,3,0)=0, "",VLOOKUP(A186,'Aux - pivots1'!$A:$E,3,0)) | N186: =IF(VLOOKUP(A186,'Aux - pivots1'!$A:$E,4,0)=0, "",VLOOKUP(A186,'Aux - pivots1'!$A:$E,4,0)) | O186: =IF(VLOOKUP(A186,'Aux - pivots1'!$A:$E,5,0)=0, "",VLOOKUP(A186,'Aux - pivots1'!$A:$E,5,0)) | U186: Plano anterior
A187: =E187&F187 -> PROPERTY_ENERGY_CERTIFICATEUSEFUL_ENERGY_FANS_REQ_VALUE | B187: Pilar III | C187: Bens Imóveis - Output | D187: 2. Campo | E187: PROPERTY_ENERGY_CERTIFICATE | F187: USEFUL_ENERGY_FANS_REQ_VALUE | G187: =VLOOKUP(A187,Plano_V3!$A$26:$G$764,7,0) -> 1. Concluído | H187: 1. Concluído | M187: =IF(VLOOKUP(A187,'Aux - pivots1'!$A:$E,3,0)=0, "",VLOOKUP(A187,'Aux - pivots1'!$A:$E,3,0)) | N187: =IF(VLOOKUP(A187,'Aux - pivots1'!$A:$E,4,0)=0, "",VLOOKUP(A187,'Aux - pivots1'!$A:$E,4,0)) | O187: =IF(VLOOKUP(A187,'Aux - pivots1'!$A:$E,5,0)=0, "",VLOOKUP(A187,'Aux - pivots1'!$A:$E,5,0)) | U187: Plano anterior
A188: =E188&F188 -> PROPERTY_ENERGY_CERTIFICATEREN_ENERGY_PRODUCED_OTHER_VALUE | B188: Pilar III | C188: Bens Imóveis - Output | D188: 2. Campo | E188: PROPERTY_ENERGY_CERTIFICATE | F188: REN_ENERGY_PRODUCED_OTHER_VALUE | G188: =VLOOKUP(A188,Plano_V3!$A$26:$G$764,7,0) -> 1. Concluído | H188: 1. Concluído | M188: =IF(VLOOKUP(A188,'Aux - pivots1'!$A:$E,3,0)=0, "",VLOOKUP(A188,'Aux - pivots1'!$A:$E,3,0)) | N188: =IF(VLOOKUP(A188,'Aux - pivots1'!$A:$E,4,0)=0, "",VLOOKUP(A188,'Aux - pivots1'!$A:$E,4,0)) | O188: =IF(VLOOKUP(A188,'Aux - pivots1'!$A:$E,5,0)=0, "",VLOOKUP(A188,'Aux - pivots1'!$A:$E,5,0)) | U188: Plano anterior
A189: =E189&F189 -> PROPERTY_ENERGY_CERTIFICATEREN_ENERGY_PRODUCED_REG_VALUE | B189: Pilar III | C189: Bens Imóveis - Output | D189: 2. Campo | E189: PROPERTY_ENERGY_CERTIFICATE | F189: REN_ENERGY_PRODUCED_REG_VALUE | G189: =VLOOKUP(A189,Plano_V3!$A$26:$G$764,7,0) -> 1. Concluído | H189: 1. Concluído | M189: =IF(VLOOKUP(A189,'Aux - pivots1'!$A:$E,3,0)=0, "",VLOOKUP(A189,'Aux - pivots1'!$A:$E,3,0)) | N189: =IF(VLOOKUP(A189,'Aux - pivots1'!$A:$E,4,0)=0, "",VLOOKUP(A189,'Aux - pivots1'!$A:$E,4,0)) | O189: =IF(VLOOKUP(A189,'Aux - pivots1'!$A:$E,5,0)=0, "",VLOOKUP(A189,'Aux - pivots1'!$A:$E,5,0)) | U189: Plano anterior
A190: =E190&F190 -> PROPERTY_ENERGY_CERTIFICATEREN_ENERGY_PRODUCED_VALUE | B190: Pilar III | C190: Bens Imóveis - Output | D190: 2. Campo | E190: PROPERTY_ENERGY_CERTIFICATE | F190: REN_ENERGY_PRODUCED_VALUE | G190: =VLOOKUP(A190,Plano_V3!$A$26:$G$764,7,0) -> 1. Concluído | H190: 1. Concluído | M190: =IF(VLOOKUP(A190,'Aux - pivots1'!$A:$E,3,0)=0, "",VLOOKUP(A190,'Aux - pivots1'!$A:$E,3,0)) | N190: =IF(VLOOKUP(A190,'Aux - pivots1'!$A:$E,4,0)=0, "",VLOOKUP(A190,'Aux - pivots1'!$A:$E,4,0)) | O190: =IF(VLOOKUP(A190,'Aux - pivots1'!$A:$E,5,0)=0, "",VLOOKUP(A190,'Aux - pivots1'!$A:$E,5,0)) | U190: Plano anterior
A191: =E191&F191 -> PROPERTY_ENERGY_CERTIFICATEUSEFUL_ENERGY_DOM_HOTWATER_VALUE | B191: Pilar III | C191: Bens Imóveis - Output | D191: 2. Campo | E191: PROPERTY_ENERGY_CERTIFICATE | F191: USEFUL_ENERGY_DOM_HOTWATER_VALUE | G191: =VLOOKUP(A191,Plano_V3!$A$26:$G$764,7,0) -> 1. Concluído | H191: 1. Concluído | M191: =IF(VLOOKUP(A191,'Aux - pivots1'!$A:$E,3,0)=0, "",VLOOKUP(A191,'Aux - pivots1'!$A:$E,3,0)) | N191: =IF(VLOOKUP(A191,'Aux - pivots1'!$A:$E,4,0)=0, "",VLOOKUP(A191,'Aux - pivots1'!$A:$E,4,0)) | O191: =IF(VLOOKUP(A191,'Aux - pivots1'!$A:$E,5,0)=0, "",VLOOKUP(A191,'Aux - pivots1'!$A:$E,5,0)) | U191: Plano anterior
A192: =E192&F192 -> PROPERTY_ENERGY_CERTIFICATEUSEFUL_ENERGY_COOLING_VALUE | B192: Pilar III | C192: Bens Imóveis - Output | D192: 2. Campo | E192: PROPERTY_ENERGY_CERTIFICATE | F192: USEFUL_ENERGY_COOLING_VALUE | G192: =VLOOKUP(A192,Plano_V3!$A$26:$G$764,7,0) -> 1. Concluído | H192: 1. Concluído | M192: =IF(VLOOKUP(A192,'Aux - pivots1'!$A:$E,3,0)=0, "",VLOOKUP(A192,'Aux - pivots1'!$A:$E,3,0)) | N192: =IF(VLOOKUP(A192,'Aux - pivots1'!$A:$E,4,0)=0, "",VLOOKUP(A192,'Aux - pivots1'!$A:$E,4,0)) | O192: =IF(VLOOKUP(A192,'Aux - pivots1'!$A:$E,5,0)=0, "",VLOOKUP(A192,'Aux - pivots1'!$A:$E,5,0)) | U192: Plano anterior
A193: =E193&F193 -> PROPERTY_ENERGY_CERTIFICATETEMPERATURE_DAY_VALUE | B193: Pilar III | C193: Bens Imóveis - Output | D193: 2. Campo | E193: PROPERTY_ENERGY_CERTIFICATE | F193: TEMPERATURE_DAY_VALUE | G193: =VLOOKUP(A193,Plano_V3!$A$26:$G$764,7,0) -> 1. Concluído | H193: 1. Concluído | M193: =IF(VLOOKUP(A193,'Aux - pivots1'!$A:$E,3,0)=0, "",VLOOKUP(A193,'Aux - pivots1'!$A:$E,3,0)) | N193: =IF(VLOOKUP(A193,'Aux - pivots1'!$A:$E,4,0)=0, "",VLOOKUP(A193,'Aux - pivots1'!$A:$E,4,0)) | O193: =IF(VLOOKUP(A193,'Aux - pivots1'!$A:$E,5,0)=0, "",VLOOKUP(A193,'Aux - pivots1'!$A:$E,5,0)) | U193: Plano anterior
A194: =E194&F194 -> PROPERTY_ENERGY_CERTIFICATEPRIMARY_ENERGY_REQ_VALUE | B194: Pilar III | C194: Bens Imóveis - Output | D194: 2. Campo | E194: PROPERTY_ENERGY_CERTIFICATE | F194: PRIMARY_ENERGY_REQ_VALUE | G194: =VLOOKUP(A194,Plano_V3!$A$26:$G$764,7,0) -> 1. Concluído | H194: 1. Concluído | M194: =IF(VLOOKUP(A194,'Aux - pivots1'!$A:$E,3,0)=0, "",VLOOKUP(A194,'Aux - pivots1'!$A:$E,3,0)) | N194: =IF(VLOOKUP(A194,'Aux - pivots1'!$A:$E,4,0)=0, "",VLOOKUP(A194,'Aux - pivots1'!$A:$E,4,0)) | O194: =IF(VLOOKUP(A194,'Aux - pivots1'!$A:$E,5,0)=0, "",VLOOKUP(A194,'Aux - pivots1'!$A:$E,5,0)) | U194: Plano anterior
A195: =E195&F195 -> PROPERTY_ENERGY_CERTIFICATEUSEFUL_ENERGY_HEATING_REQ_VALUE | B195: Pilar III | C195: Bens Imóveis - Output | D195: 2. Campo | E195: PROPERTY_ENERGY_CERTIFICATE | F195: USEFUL_ENERGY_HEATING_REQ_VALUE | G195: =VLOOKUP(A195,Plano_V3!$A$26:$G$764,7,0) -> 1. Concluído | H195: 1. Concluído | M195: =IF(VLOOKUP(A195,'Aux - pivots1'!$A:$E,3,0)=0, "",VLOOKUP(A195,'Aux - pivots1'!$A:$E,3,0)) | N195: =IF(VLOOKUP(A195,'Aux - pivots1'!$A:$E,4,0)=0, "",VLOOKUP(A195,'Aux - pivots1'!$A:$E,4,0)) | O195: =IF(VLOOKUP(A195,'Aux - pivots1'!$A:$E,5,0)=0, "",VLOOKUP(A195,'Aux - pivots1'!$A:$E,5,0)) | U195: Plano anterior
A196: =E196&F196 -> PROPERTY_ENERGY_CERTIFICATEPNL_WINTER_WALLS_DOORS_VALUE | B196: Pilar III | C196: Bens Imóveis - Output | D196: 2. Campo | E196: PROPERTY_ENERGY_CERTIFICATE | F196: PNL_WINTER_WALLS_DOORS_VALUE | G196: =VLOOKUP(A196,Plano_V3!$A$26:$G$764,7,0) -> 1. Concluído | H196: 1. Concluído | M196: =IF(VLOOKUP(A196,'Aux - pivots1'!$A:$E,3,0)=0, "",VLOOKUP(A196,'Aux - pivots1'!$A:$E,3,0)) | N196: =IF(VLOOKUP(A196,'Aux - pivots1'!$A:$E,4,0)=0, "",VLOOKUP(A196,'Aux - pivots1'!$A:$E,4,0)) | O196: =IF(VLOOKUP(A196,'Aux - pivots1'!$A:$E,5,0)=0, "",VLOOKUP(A196,'Aux - pivots1'!$A:$E,5,0)) | U196: Plano anterior
A197: =E197&F197 -> PROPERTY_ENERGY_CERTIFICATEPNL_WINTER_FLOORS_VALUE | B197: Pilar III | C197: Bens Imóveis - Output | D197: 2. Campo | E197: PROPERTY_ENERGY_CERTIFICATE | F197: PNL_WINTER_FLOORS_VALUE | G197: =VLOOKUP(A197,Plano_V3!$A$26:$G$764,7,0) -> 1. Concluído | H197: 1. Concluído | M197: =IF(VLOOKUP(A197,'Aux - pivots1'!$A:$E,3,0)=0, "",VLOOKUP(A197,'Aux - pivots1'!$A:$E,3,0)) | N197: =IF(VLOOKUP(A197,'Aux - pivots1'!$A:$E,4,0)=0, "",VLOOKUP(A197,'Aux - pivots1'!$A:$E,4,0)) | O197: =IF(VLOOKUP(A197,'Aux - pivots1'!$A:$E,5,0)=0, "",VLOOKUP(A197,'Aux - pivots1'!$A:$E,5,0)) | U197: Plano anterior
... A216: =E216&F216 -> PROPERTY_ENERGY_CERTIFICATECLIMATE_ZONE_SUMMER | B216: Pilar III | C216: Bens Imóveis - Output | D216: 2. Campo | E216: PROPERTY_ENERGY_CERTIFICATE | F216: CLIMATE_ZONE_SUMMER | G216: =VLOOKUP(A216,Plano_V3!$A$26:$G$764,7,0) -> 1. Concluído | H216: 1. Concluído | M216: =IF(VLOOKUP(A216,'Aux - pivots1'!$A:$E,3,0)=0, "",VLOOKUP(A216,'Aux - pivots1'!$A:$E,3,0)) | N216: =IF(VLOOKUP(A216,'Aux - pivots1'!$A:$E,4,0)=0, "",VLOOKUP(A216,'Aux - pivots1'!$A:$E,4,0)) | O216: =IF(VLOOKUP(A216,'Aux - pivots1'!$A:$E,5,0)=0, "",VLOOKUP(A216,'Aux - pivots1'!$A:$E,5,0)) | U216: Plano anterior
A217: =E217&F217 -> PROPERTY_ENERGY_CERTIFICATECURRENT_ENERGY_RATING_PERCENTAGE | B217: Pilar III | C217: Bens Imóveis - Output | D217: 2. Campo | E217: PROPERTY_ENERGY_CERTIFICATE | F217: CURRENT_ENERGY_RATING_PERCENTAGE | G217: =VLOOKUP(A217,Plano_V3!$A$26:$G$764,7,0) -> 1. Concluído | H217: 1. Concluído | J217: Package 1 | K217: Package 1 | M217: =IF(VLOOKUP(A217,'Aux - pivots1'!$A:$E,3,0)=0, "",VLOOKUP(A217,'Aux - pivots1'!$A:$E,3,0)) | N217: =IF(VLOOKUP(A217,'Aux - pivots1'!$A:$E,4,0)=0, "",VLOOKUP(A217,'Aux - pivots1'!$A:$E,4,0)) | O217: =IF(VLOOKUP(A217,'Aux - pivots1'!$A:$E,5,0)=0, "",VLOOKUP(A217,'Aux - pivots1'!$A:$E,5,0)) | U217: Plano anterior | V217: HF
A218: =E218&F218 -> modesg_param_sfics_taxon_europeian.a. | B218: Pilar III | C218: Modelo Verde - Input | D218: 1. Universo | E218: modesg_param_sfics_taxon_europeia | F218: n.a. | G218: =VLOOKUP(A218,Plano_V3!$A$26:$G$764,7,0) -> 6. Em implementação | H218: 2.2 Em especificação | J218: Package X | K218: Package X | M218: =IF(VLOOKUP(A218,'Aux - pivots1'!$A:$E,3,0)=0, "",VLOOKUP(A218,'Aux - pivots1'!$A:$E,3,0)) | N218: =IF(VLOOKUP(A218,'Aux - pivots1'!$A:$E,4,0)=0, "",VLOOKUP(A218,'Aux - pivots1'!$A:$E,4,0)) | O218: =IF(VLOOKUP(A218,'Aux - pivots1'!$A:$E,5,0)=0, "",VLOOKUP(A218,'Aux - pivots1'!$A:$E,5,0)) | U218: Plano anterior | V218: RC
A219: =E219&F219 -> modesg_param_sfics_taxon_europeiacod_regra | B219: Pilar III | C219: Modelo Verde - Input | D219: 2. Campo | E219: modesg_param_sfics_taxon_europeia | F219: cod_regra | G219: =VLOOKUP(A219,Plano_V3!$A$26:$G$764,7,0) -> 6. Em implementação | H219: 2.2 Em especificação | J219: Package X | K219: Package X | M219: =IF(VLOOKUP(A219,'Aux - pivots1'!$A:$E,3,0)=0, "",VLOOKUP(A219,'Aux - pivots1'!$A:$E,3,0)) | N219: =IF(VLOOKUP(A219,'Aux - pivots1'!$A:$E,4,0)=0, "",VLOOKUP(A219,'Aux - pivots1'!$A:$E,4,0)) | O219: =IF(VLOOKUP(A219,'Aux - pivots1'!$A:$E,5,0)=0, "",VLOOKUP(A219,'Aux - pivots1'!$A:$E,5,0)) | U219: Plano anterior | V219: RC
A220: =E220&F220 -> modesg_param_sfics_taxon_europeianivel | B220: Pilar III | C220: Modelo Verde - Input | D220: 2. Campo | E220: modesg_param_sfics_taxon_europeia | F220: nivel | G220: =VLOOKUP(A220,Plano_V3!$A$26:$G$764,7,0) -> 6. Em implementação | H220: 0. Cancelado | J220: Package X | K220: Package X | M220: =IF(VLOOKUP(A220,'Aux - pivots1'!$A:$E,3,0)=0, "",VLOOKUP(A220,'Aux - pivots1'!$A:$E,3,0)) | N220: =IF(VLOOKUP(A220,'Aux - pivots1'!$A:$E,4,0)=0, "",VLOOKUP(A220,'Aux - pivots1'!$A:$E,4,0)) | O220: =IF(VLOOKUP(A220,'Aux - pivots1'!$A:$E,5,0)=0, "",VLOOKUP(A220,'Aux - pivots1'!$A:$E,5,0)) | U220: Plano anterior | V220: RC
A221: =E221&F221 -> modesg_param_sfics_taxon_europeiagrupo_regra | B221: Pilar III | C221: Modelo Verde - Input | D221: 2. Campo | E221: modesg_param_sfics_taxon_europeia | F221: grupo_regra | G221: =VLOOKUP(A221,Plano_V3!$A$26:$G$764,7,0) -> 6. Em implementação | M221: =IF(VLOOKUP(A221,'Aux - pivots1'!$A:$E,3,0)=0, "",VLOOKUP(A221,'Aux - pivots1'!$A:$E,3,0)) | N221: =IF(VLOOKUP(A221,'Aux - pivots1'!$A:$E,4,0)=0, "",VLOOKUP(A221,'Aux - pivots1'!$A:$E,4,0)) | O221: =IF(VLOOKUP(A221,'Aux - pivots1'!$A:$E,5,0)=0, "",VLOOKUP(A221,'Aux - pivots1'!$A:$E,5,0))
A222: =E222&F222 -> modesg_param_sfics_taxon_europeiadscrc | B222: Pilar III | C222: Modelo Verde - Input | D222: 2. Campo | E222: modesg_param_sfics_taxon_europeia | F222: dscrc | G222: =VLOOKUP(A222,Plano_V3!$A$26:$G$764,7,0) -> 6. Em implementação | H222: 2.2 Em especificação | J222: Package X | K222: Package X | M222: =IF(VLOOKUP(A222,'Aux - pivots1'!$A:$E,3,0)=0, "",VLOOKUP(A222,'Aux - pivots1'!$A:$E,3,0)) | N222: =IF(VLOOKUP(A222,'Aux - pivots1'!$A:$E,4,0)=0, "",VLOOKUP(A222,'Aux - pivots1'!$A:$E,4,0)) | O222: =IF(VLOOKUP(A222,'Aux - pivots1'!$A:$E,5,0)=0, "",VLOOKUP(A222,'Aux - pivots1'!$A:$E,5,0)) | U222: Plano anterior | V222: RC
A223: =E223&F223 -> modesg_param_sfics_taxon_europeiacomite | B223: Pilar III | C223: Modelo Verde - Input | D223: 2. Campo | E223: modesg_param_sfics_taxon_europeia | F223: comite | G223: =VLOOKUP(A223,Plano_V3!$A$26:$G$764,7,0) -> 6. Em implementação | H223: 2.2 Em especificação | J223: Package X | K223: Package X | M223: =IF(VLOOKUP(A223,'Aux - pivots1'!$A:$E,3,0)=0, "",VLOOKUP(A223,'Aux - pivots1'!$A:$E,3,0)) | N223: =IF(VLOOKUP(A223,'Aux - pivots1'!$A:$E,4,0)=0, "",VLOOKUP(A223,'Aux - pivots1'!$A:$E,4,0)) | O223: =IF(VLOOKUP(A223,'Aux - pivots1'!$A:$E,5,0)=0, "",VLOOKUP(A223,'Aux - pivots1'!$A:$E,5,0)) | U223: Plano anterior | V223: RC
A224: =E224&F224 -> modesg_param_sfics_taxon_europeiadata_aprvc | B224: Pilar III | C224: Modelo Verde - Input | D224: 2. Campo | E224: modesg_param_sfics_taxon_europeia | F224: data_aprvc | G224: =VLOOKUP(A224,Plano_V3!$A$26:$G$764,7,0) -> 6. Em implementação | H224: 2.2 Em especificação | J224: Package X | K224: Package X | M224: =IF(VLOOKUP(A224,'Aux - pivots1'!$A:$E,3,0)=0, "",VLOOKUP(A224,'Aux - pivots1'!$A:$E,3,0)) | N224: =IF(VLOOKUP(A224,'Aux - pivots1'!$A:$E,4,0)=0, "",VLOOKUP(A224,'Aux - pivots1'!$A:$E,4,0)) | O224: =IF(VLOOKUP(A224,'Aux - pivots1'!$A:$E,5,0)=0, "",VLOOKUP(A224,'Aux - pivots1'!$A:$E,5,0)) | U224: Plano anterior | V224: RC
A225: =E225&F225 -> modesg_param_sfics_taxon_europeiadata_inicial | B225: Pilar III | C225: Modelo Verde - Input | D225: 2. Campo | E225: modesg_param_sfics_taxon_europeia | F225: data_inicial | G225: =VLOOKUP(A225,Plano_V3!$A$26:$G$764,7,0) -> 6. Em implementação | H225: 2.2 Em especificação | J225: Package X | K225: Package X | M225: =IF(VLOOKUP(A225,'Aux - pivots1'!$A:$E,3,0)=0, "",VLOOKUP(A225,'Aux - pivots1'!$A:$E,3,0)) | N225: =IF(VLOOKUP(A225,'Aux - pivots1'!$A:$E,4,0)=0, "",VLOOKUP(A225,'Aux - pivots1'!$A:$E,4,0)) | O225: =IF(VLOOKUP(A225,'Aux - pivots1'!$A:$E,5,0)=0, "",VLOOKUP(A225,'Aux - pivots1'!$A:$E,5,0)) | U225: Plano anterior | V225: RC
A226: =E226&F226 -> modesg_param_sfics_taxon_europeiadata_final | B226: Pilar III | C226: Modelo Verde - Input | D226: 2. Campo | E226: modesg_param_sfics_taxon_europeia | F226: data_final | G226: =VLOOKUP(A226,Plano_V3!$A$26:$G$764,7,0) -> 6. Em implementação | H226: 2.2 Em especificação | J226: Package X | K226: Package X | M226: =IF(VLOOKUP(A226,'Aux - pivots1'!$A:$E,3,0)=0, "",VLOOKUP(A226,'Aux - pivots1'!$A:$E,3,0)) | N226: =IF(VLOOKUP(A226,'Aux - pivots1'!$A:$E,4,0)=0, "",VLOOKUP(A226,'Aux - pivots1'!$A:$E,4,0)) | O226: =IF(VLOOKUP(A226,'Aux - pivots1'!$A:$E,5,0)=0, "",VLOOKUP(A226,'Aux - pivots1'!$A:$E,5,0)) | U226: Plano anterior | V226: RC
A227: =E227&F227 -> modesg_param_sfics_taxon_europeiazcliente | B227: Pilar III | C227: Modelo Verde - Input | D227: 2. Campo | E227: modesg_param_sfics_taxon_europeia | F227: zcliente | G227: =VLOOKUP(A227,Plano_V3!$A$26:$G$764,7,0) -> 6. Em implementação | H227: 2.2 Em especificação | J227: Package X | K227: Package X | M227: =IF(VLOOKUP(A227,'Aux - pivots1'!$A:$E,3,0)=0, "",VLOOKUP(A227,'Aux - pivots1'!$A:$E,3,0)) | N227: =IF(VLOOKUP(A227,'Aux - pivots1'!$A:$E,4,0)=0, "",VLOOKUP(A227,'Aux - pivots1'!$A:$E,4,0)) | O227: =IF(VLOOKUP(A227,'Aux - pivots1'!$A:$E,5,0)=0, "",VLOOKUP(A227,'Aux - pivots1'!$A:$E,5,0)) | U227: Plano anterior | V227: RC
A228: =E228&F228 -> modesg_param_sfics_taxon_europeiacempcta | B228: Pilar III | C228: Modelo Verde - Input | D228: 2. Campo | E228: modesg_param_sfics_taxon_europeia | F228: cempcta | G228: =VLOOKUP(A228,Plano_V3!$A$26:$G$764,7,0) -> 6. Em implementação | H228: 2.2 Em especificação | J228: Package X | K228: Package X | M228: =IF(VLOOKUP(A228,'Aux - pivots1'!$A:$E,3,0)=0, "",VLOOKUP(A228,'Aux - pivots1'!$A:$E,3,0)) | N228: =IF(VLOOKUP(A228,'Aux - pivots1'!$A:$E,4,0)=0, "",VLOOKUP(A228,'Aux - pivots1'!$A:$E,4,0)) | O228: =IF(VLOOKUP(A228,'Aux - pivots1'!$A:$E,5,0)=0, "",VLOOKUP(A228,'Aux - pivots1'!$A:$E,5,0)) | U228: Plano anterior (sem visibilidade no PdS enviado 17/01) | V228: RC
A229: =E229&F229 -> modesg_param_sfics_taxon_europeiackbalcao | B229: Pilar III | C229: Modelo Verde - Input | D229: 2. Campo | E229: modesg_param_sfics_taxon_europeia | F229: ckbalcao | G229: =VLOOKUP(A229,Plano_V3!$A$26:$G$764,7,0) -> 6. Em implementação | H229: 2.2 Em especificação | J229: Package X | K229: Package X | M229: =IF(VLOOKUP(A229,'Aux - pivots1'!$A:$E,3,0)=0, "",VLOOKUP(A229,'Aux - pivots1'!$A:$E,3,0)) | N229: =IF(VLOOKUP(A229,'Aux - pivots1'!$A:$E,4,0)=0, "",VLOOKUP(A229,'Aux - pivots1'!$A:$E,4,0)) | O229: =IF(VLOOKUP(A229,'Aux - pivots1'!$A:$E,5,0)=0, "",VLOOKUP(A229,'Aux - pivots1'!$A:$E,5,0)) | U229: Plano anterior | V229: RC
...

Sheet Sheet1
B1: Âmbito | C1: Sub-âmbito | D1: Tipo de teste | E1: Tabela | F1: Campo | G1: Status Atual | H1: Status Anterior | I1: Fase | J1: Observações - Especificações | K1: Observações - Testes | L1: Observações - Testes sem visibilidade | M1: Projeto (Aux JB) | N1: LT Âmbito | O1: LT Âmbito- Aux | P1: Plano | Q1: Owner
A2: =C2&E2&F2 -> Pilar IIIlt003_entityesg_sbsctr | B2: Pilar III | C2: Pilar III | D2: 2. Campo | E2: lt003_entity | F2: esg_sbsctr | G2: 6. Em implementação | H2: 3. Pendente de outros desenvolvimentos | J2: Package 2 | K2: Package X | N2: ESTR & P3 | P2: Plano anterior | Q2: JB/RC
A3: =C3&E3&F3 -> Pilar IIIlt007_instr_activitysstnbl_indctr | B3: Pilar III | C3: Pilar III | D3: 2. Campo | E3: lt007_instr_activity | F3: sstnbl_indctr | G3: 4. Validação EF | H3: 4. Validação EF | J3: Package 5 | K3: Package X | M3: Projeto Anterior - Especificação | P3: Plano anterior | Q3: RC
A4: =C4&E4&F4 -> Pilar IIIlt007_instr_activityCOD_SOC | B4: Pilar III | C4: Pilar III | D4: 2. Campo | E4: lt007_instr_activity | F4: COD_SOC | G4: 6. Em implementação | H4: 7. Por iniciar | J4: Package 4 | K4: Package X | M4: Novo Projeto - Em especificação | N4: GD, P3 e GF | O4: Novos Requisitos FY25 - Outros | P4: Novo Plano | Q4: RC
A5: =C5&E5&F5 -> Pilar IIIlt007_instr_activityDT_RFRNC | B5: Pilar III | C5: Pilar III | D5: 2. Campo | E5: lt007_instr_activity | F5: DT_RFRNC | G5: 6. Em implementação | H5: 6. Em implementação | J5: Package 3 | K5: Package X | M5: Novo Projeto - Em especificação | N5: GD, P3 e GF | O5: Novos Requisitos FY25 - Outros | P5: Novo Plano | Q5: RC
A6: =C6&E6&F6 -> Pilar IIIlt007_instr_activityINSTRMNT_ID | B6: Pilar III | C6: Pilar III | D6: 2. Campo | E6: lt007_instr_activity | F6: INSTRMNT_ID | G6: 6. Em implementação | H6: 7. Por iniciar | J6: Package 4 | K6: Package X | M6: Novo Projeto - Em especificação | N6: GD, P3 e GF | O6: Novos Requisitos FY25 - Outros | P6: Novo Plano | Q6: RC
A7: =C7&E7&F7 -> Pilar IIIlt007_instr_activityPRCNTG_ACTVTY | B7: Pilar III | C7: Pilar III | D7: 2. Campo | E7: lt007_instr_activity | F7: PRCNTG_ACTVTY | G7: 6. Em implementação | H7: 7. Por iniciar | J7: Package 5 | K7: Package X | M7: Novo Projeto - Em especificação | N7: GD, P3 e GF | O7: Novos Requisitos FY25 - Outros | P7: Novo Plano | Q7: RC
A8: =C8&E8&F8 -> Pilar IIIlt007_instr_activityFLG_SBSTNTL_CNTRBTN | B8: Pilar III | C8: Pilar III | D8: 2. Campo | E8: lt007_instr_activity | F8: FLG_SBSTNTL_CNTRBTN | G8: 6. Em implementação | H8: 7. Por iniciar | J8: Package 5 | K8: Package X | M8: Novo Projeto - Em especificação | N8: P3 | O8: Novos Requisitos FY25 - Outros | P8: Novo Plano | Q8: RC
A9: =C9&E9&F9 -> Pilar IIIlt007_instr_activityFLG_DNSH_CMPLNC | B9: Pilar III | C9: Pilar III | D9: 2. Campo | E9: lt007_instr_activity | F9: FLG_DNSH_CMPLNC | G9: 6. Em implementação | H9: 6. Em implementação | J9: Package 2 | K9: Package X | M9: Novo Projeto - Em especificação | N9: P3 | O9: Novos Requisitos FY25 - Outros | P9: Novo Plano | Q9: JB/RC
A10: =C10&E10&F10 -> Pilar IIIlt007_instr_activityDNSH_DTL | B10: Pilar III | C10: Pilar III | D10: 2. Campo | E10: lt007_instr_activity | F10: DNSH_DTL | G10: 6. Em implementação | H10: 6. Em implementação | J10: Package 2 | K10: Package X | M10: Novo Projeto - Em especificação | N10: P3 | O10: Novos Requisitos FY25 - Outros | P10: Novo Plano | Q10: JB/RC
A11: =C11&E11&F11 -> Pilar IIIlt007_instr_activitysstnbl_ctgry | B11: Pilar III | C11: Pilar III | D11: 2. Campo | E11: lt007_instr_activity | F11: sstnbl_ctgry | G11: 6. Em implementação | H11: 4. Validação EF | J11: Package 5 | K11: Package X | M11: Projeto Anterior - Especificação | P11: Plano anterior | Q11: RC
A12: =C12&E12&F12 -> Pilar IIIlt002_instrumentFRBRNC_STTS_INSTRMNT | B12: Pilar III | C12: Pilar III | D12: 2. Campo | E12: lt002_instrument | F12: FRBRNC_STTS_INSTRMNT | G12: 6. Em implementação | H12: 6. Em implementação | J12: Package 2 | K12: Package X | M12: Novo Projeto - Em especificação | N12: ESTR, P3 e LF | O12: Novos Requisitos FY25 - Âmbito ESTR e (ou) LF | P12: Novo Plano | Q12: JB
A13: =C13&E13&F13 -> Pilar IIIlt002_instrumentINTRNL_SGMNT | B13: Pilar III | C13: Pilar III | D13: 2. Campo | E13: lt002_instrument | F13: INTRNL_SGMNT | G13: 6. Em implementação | H13: 6. Em implementação | J13: Package 3 | K13: Package X | M13: Novo Projeto - Em especificação | N13: ESTR, ESG e LF | O13: Novos Requisitos FY25 - Âmbito ESTR e (ou) LF | P13: Novo Plano | Q13: HF
A14: =C14&E14&F14 -> Pilar IIIlt002_instrumentDT_ORGNL_MTRTY | B14: Pilar III | C14: Pilar III | D14: 2. Campo | E14: lt002_instrument | F14: DT_ORGNL_MTRTY | G14: 6. Em implementação | H14: 6. Em implementação | J14: Package 3 | K14: Package X | M14: Novo Projeto - Em especificação | N14: ESTR, P3, GF e LF | O14: Novos Requisitos FY25 - Âmbito ESTR e (ou) LF | P14: Novo Plano | Q14: HF
A15: =C15&E15&F15 -> Pilar IIIlt002_instrumentEAD | B15: Pilar III | C15: Pilar III | D15: 2. Campo | E15: lt002_instrument | F15: EAD | G15: 6. Em implementação | H15: 6. Em implementação | J15: Package 3 | K15: Package X | M15: Novo Projeto - Em especificação | N15: ESTR, GD, ESG e LF | O15: Novos Requisitos FY25 - Âmbito ESTR e (ou) LF | P15: Novo Plano | Q15: HF
A16: =C16&E16&F16 -> Pilar IIIlt002_instrumentOFF_BLNC_SHT_AMNT_INSTRMNT | B16: Pilar III | C16: Pilar III | D16: 2. Campo | E16: lt002_instrument | F16: OFF_BLNC_SHT_AMNT_INSTRMNT | G16: 6. Em implementação | H16: 7. Por iniciar | J16: Package 4 | K16: Package X | M16: Novo Projeto - Em especificação | N16: ESTR, GD, GF, ESG e LF | O16: Novos Requisitos FY25 - Âmbito ESTR e (ou) LF | P16: Novo Plano | Q16: HF
A17: =C17&E17&F17 -> Pilar IIIlt002_instrumentRWA | B17: Pilar III | C17: Pilar III | D17: 2. Campo | E17: lt002_instrument | F17: RWA | G17: 6. Em implementação | H17: 6. Em implementação | J17: Package 3 | K17: Package X | M17: Novo Projeto - Em especificação | N17: ESTR, GD, P3, GF e LF | O17: Novos Requisitos FY25 - Âmbito ESTR e (ou) LF | P17: Novo Plano | Q17: HF
A18: =C18&E18&F18 -> Pilar IIIlt002_instrumentLTV | B18: Pilar III | C18: Pilar III | D18: 2. Campo | E18: lt002_instrument | F18: LTV | G18: 6. Em implementação | H18: 6. Em implementação | J18: Package 3 | K18: Package X | M18: Novo Projeto - Em especificação | N18: ESTR e P3 | O18: Novos Requisitos FY25 - Âmbito ESTR e (ou) LF | P18: Novo Plano | Q18: HF
A19: =C19&E19&F19 -> Pilar IIIlt002_instrumentLTV_INCPTN | B19: Pilar III | C19: Pilar III | D19: 2. Campo | E19: lt002_instrument | F19: LTV_INCPTN | G19: 6. Em implementação | H19: 6. Em implementação | J19: Package 3 | K19: Package X | M19: Novo Projeto - Em especificação | N19: ESTR e P3 | O19: Novos Requisitos FY25 - Âmbito ESTR e (ou) LF | P19: Novo Plano | Q19: JB
A20: =C20&E20&F20 -> Pilar IIIlt002_instrumentEIR | B20: Pilar III | C20: Pilar III | D20: 2. Campo | E20: lt002_instrument | F20: EIR | G20: 6. Em implementação | H20: 6. Em implementação | J20: Package 3 | K20: Package X | M20: Novo Projeto - Em especificação | N20: ESTR, P3 e LF | O20: Novos Requisitos FY25 - Âmbito ESTR e (ou) LF | P20: Novo Plano | Q20: JB
A21: =C21&E21&F21 -> Pilar IIIlt002_instrumentEIR_INCPTN | B21: Pilar III | C21: Pilar III | D21: 2. Campo | E21: lt002_instrument | F21: EIR_INCPTN | G21: 6. Em implementação | H21: 6. Em implementação | J21: Package 3 | K21: Package X | M21: Novo Projeto - Em especificação | N21: ESTR e P3 | O21: Novos Requisitos FY25 - Âmbito ESTR e (ou) LF | P21: Novo Plano | Q21: JB
A22: =C22&E22&F22 -> Pilar IIIlt002_instrumentINTRNL_SGMNT_CAT_MSTA | B22: Pilar III | C22: Pilar III | D22: 2. Campo | E22: lt002_instrument | F22: INTRNL_SGMNT_CAT_MSTA | G22: 6. Em implementação | H22: 6. Em implementação | J22: Package 3 | K22: Package X | M22: Novo Projeto - Em especificação | N22: ESTR e ESG | O22: Novos Requisitos FY25 - Âmbito ESTR e (ou) LF | P22: Novo Plano | Q22: JB
A23: =C23&E23&F23 -> Pilar IIIlt002_instrumentINTRNL_SGMNT_CATGSUB | B23: Pilar III | C23: Pilar III | D23: 2. Campo | E23: lt002_instrument | F23: INTRNL_SGMNT_CATGSUB | G23: 6. Em implementação | H23: 6. Em implementação | J23: Package 3 | K23: Package X | M23: Novo Projeto - Em especificação | N23: ESTR e ESG | O23: Novos Requisitos FY25 - Âmbito ESTR e (ou) LF | P23: Novo Plano | Q23: JB
... A51: =C51&E51&F51 -> Pilar IIIlt003_entityenblng_trnvr_ce | B51: Pilar III | C51: Pilar III | D51: 2. Campo | E51: lt003_entity | F51: enblng_trnvr_ce | G51: 6. Em implementação | H51: 6. Em implementação | J51: Package 1 | K51: Package x | M51: Novo Projeto - Em especificação | N51: P3 | O51: Novos Requisitos FY25 - Outros | P51: Novo Plano | Q51: JB
A52: =C52&E52&F52 -> Pilar IIIlt006_instr_protprtctn_allctd_vl | B52: Pilar III | C52: Pilar III | D52: 2. Campo | E52: lt006_instr_prot | F52: prtctn_allctd_vl | G52: 6. Em implementação | H52: 6. Em implementação | J52: Package 2 | K52: Package X | M52: Novo Projeto - Em especificação | P52: Plano anterior | Q52: JB - Falar com SB
A53: =C53&E53&F53 -> Pilar IIIlt006_instr_protTYP_RLTN | B53: Pilar III | C53: Pilar III | D53: 2. Campo | E53: lt006_instr_prot | F53: TYP_RLTN | G53: 6. Em implementação | H53: 7. Por iniciar | J53: Package 5 | K53: Package X | M53: Novo Projeto - Em especificação | N53: GD e P3 | O53: Novos Requisitos FY25 - Outros | P53: Novo Plano | Q53: JB
A54: =C54&E54&F54 -> Pilar IIIlt004_protectionRL_ESTT_ADDRSS | B54: Pilar III | C54: Pilar III | D54: 2. Campo | E54: lt004_protection | F54: RL_ESTT_ADDRSS | G54: 6. Em implementação | H54: 7. Por iniciar | J54: Package 4 | K54: Package X | M54: Novo Projeto - Em especificação | N54: ESTR e ESG | O54: Novos Requisitos FY25 - Âmbito ESTR e (ou) LF | P54: Novo Plano | Q54: JB
A55: =C55&E55&F55 -> Pilar IIIlt004_protectionRL_ESTT_CLLTRL_LCTN_INT | B55: Pilar III | C55: Pilar III | D55: 2. Campo | E55: lt004_protection | F55: RL_ESTT_CLLTRL_LCTN_INT | G55: 6. Em implementação | H55: 7. Por iniciar | J55: Package 5 | K55: Package X | M55: Novo Projeto - Em especificação | N55: ESTR e ESG | O55: Novos Requisitos FY25 - Âmbito ESTR e (ou) LF | P55: Novo Plano | Q55: JB
A56: =C56&E56&F56 -> Pilar IIIlt004_protectionRL_ESTT_CTY | B56: Pilar III | C56: Pilar III | D56: 2. Campo | E56: lt004_protection | F56: RL_ESTT_CTY | G56: 6. Em implementação | H56: 6. Em implementação | J56: Package 3 | K56: Package X | M56: Novo Projeto - Em especificação | N56: ESTR e ESG | O56: Novos Requisitos FY25 - Âmbito ESTR e (ou) LF | P56: Novo Plano | Q56: JB
A57: =C57&E57&F57 -> Pilar IIIlt004_protectionTYP_EMSSNS_LBL | B57: Pilar III | C57: Pilar III | D57: 2. Campo | E57: lt004_protection | F57: TYP_EMSSNS_LBL | G57: 6. Em implementação | H57: 6. Em implementação | J57: Package 2 | K57: Package X | M57: Novo Projeto - Em especificação | N57: ESG | O57: Novos Requisitos FY25 - Outros | P57: Novo Plano | Q57: JB
A58: =C58&E58&F58 -> Pilar IIIlt004_protectionEPC_EMSSNS_LBL | B58: Pilar III | C58: Pilar III | D58: 2. Campo | E58: lt004_protection | F58: EPC_EMSSNS_LBL | G58: 2.2 Em especificação | H58: 7. Por iniciar | J58: Package 4 | K58: Package X | M58: Novo Projeto - Em especificação | N58: ESG | O58: Novos Requisitos FY25 - Outros | P58: Novo Plano | Q58: JB
A59: =C59&E59&F59 -> Pilar IIIlt004_protectionVHCL_EMSSNS_LBL | B59: Pilar III | C59: Pilar III | D59: 2. Campo | E59: lt004_protection | F59: VHCL_EMSSNS_LBL | G59: 6. Em implementação | H59: 6. Em implementação | J59: Package 2 | K59: Package X | M59: Novo Projeto - Em especificação | N59: ESG | O59: Novos Requisitos FY25 - Outros | P59: Novo Plano | Q59: JB
A60: =C60&E60&F60 -> Pilar IIIlt004_protectionTYP_EMSSNS_SCR | B60: Pilar III | C60: Pilar III | D60: 2. Campo | E60: lt004_protection | F60: TYP_EMSSNS_SCR | G60: 2.2 Em especificação | H60: 7. Por iniciar | J60: Package 4 | K60: Package X | M60: Novo Projeto - Em especificação | N60: ESG | O60: Novos Requisitos FY25 - Outros | P60: Novo Plano | Q60: JB
A61: =C61&E61&F61 -> Pilar IIIlt004_protectionEPC_EMSSNS_SCR | B61: Pilar III | C61: Pilar III | D61: 2. Campo | E61: lt004_protection | F61: EPC_EMSSNS_SCR | G61: 2.2 Em especificação | H61: 7. Por iniciar | J61: Package 4 | K61: Package X | M61: Novo Projeto - Em especificação | N61: ESG | O61: Novos Requisitos FY25 - Outros | P61: Novo Plano | Q61: JB
A62: =C62&E62&F62 -> Pilar IIIlt004_protectionVHCL_EMSSNS_SCR | B62: Pilar III | C62: Pilar III | D62: 2. Campo | E62: lt004_protection | F62: VHCL_EMSSNS_SCR | G62: 6. Em implementação | H62: 6. Em implementação | J62: Package 2 | K62: Package X | M62: Novo Projeto - Em especificação | N62: ESG | O62: Novos Requisitos FY25 - Outros | P62: Novo Plano | Q62: JB
A63: =C63&E63&F63 -> Pilar IIIlt004_protectionINSRNC_ID | B63: Pilar III | C63: Pilar III | D63: 2. Campo | E63: lt004_protection | F63: INSRNC_ID | G63: 6. Em implementação | H63: 6. Em implementação | J63: Package 2 | K63: Package X | M63: Novo Projeto - Em especificação | N63: ESG | O63: Novos Requisitos FY25 - Outros | P63: Novo Plano | Q63: JB
A64: =C64&E64&F64 -> Pilar IIIlt004_protectionTYP_HZRDS_INSRD | B64: Pilar III | C64: Pilar III | D64: 2. Campo | E64: lt004_protection | F64: TYP_HZRDS_INSRD | G64: 6. Em implementação | H64: 6. Em implementação | J64: Package 2 | K64: Package X | M64: Novo Projeto - Em especificação | N64: ESG | O64: Novos Requisitos FY25 - Outros | P64: Novo Plano | Q64: JB
... A76: =C76&E76&F76 -> Pilar IIIlt004_protectionRL_ESTT_CLMT_ZN | B76: Pilar III | C76: Pilar III | D76: 2. Campo | E76: lt004_protection | F76: RL_ESTT_CLMT_ZN | G76: 6. Em implementação | H76: 7. Por iniciar | J76: Package 4 | K76: Package X | M76: Novo Projeto - Em especificação | N76: P3 e ESG | O76: Novos Requisitos FY25 - Outros | P76: Novo Plano | Q76: JB

Sheet Aux - pivots1
A3: concat | B3: Max of Status2
A4: ENERGY_CERTIFICATE_EST_INPUTACTUAL_VALUE_IND | B4: 0
A5: ENERGY_CERTIFICATE_EST_INPUTANIO_CONSTRUCCION | B5: 2
A6: ENERGY_CERTIFICATE_EST_INPUTART_MATRICIAIS | B6: 2
A7: ENERGY_CERTIFICATE_EST_INPUTASSUPERFICIE_UTIL | B7: 2
A8: ENERGY_CERTIFICATE_EST_INPUTCAGLURB | B8: 2
A9: ENERGY_CERTIFICATE_EST_INPUTCASA_UNIFAMILIAR | B9: 2
A10: ENERGY_CERTIFICATE_EST_INPUTCHAVE_GLOVAL | B10: 2
A11: ENERGY_CERTIFICATE_EST_INPUTCLASS_GPT31 | B11: 2
A12: ENERGY_CERTIFICATE_EST_INPUTCLASS_STCLIM | B12: 2
A13: ENERGY_CERTIFICATE_EST_INPUTCLASSE_ENERGETICA | B13: 2
A14: ENERGY_CERTIFICATE_EST_INPUTCOD_CONSERVATORIA | B14: 2
A15: ENERGY_CERTIFICATE_EST_INPUTCÓDIGO_CONCEJO | B15: 2
... A734: Grand Total | B734: 7

Sheet Caderno Testes FY24
N7: (alterar quando necessário) | R7: (data default - Dez2023)
B8: Âmbito | C8: Sub-âmbito | D8: Origem | E8: Campo Origem | F8: Tabela | G8: Campo | H8: concat | I8: Status | J8: Status2 | K8: Tipologia_Testes | L8: Necessidade de re-especificação? (campo) | M8: Complexidade | N8: Data de Alteração Status | O8: Estimação (horas) | P8: Notas | Q8: Owner | R8: Data alteração especificação | S8: Data de inicio testes | T8: Data de incidência / pedido esclarecimento | U8: Data de correção/resposta prevista | V8: Data de correção/resposta efetiva | W8: Horas efetivas | X8: Query
B9: Pilar III | C9: Bens Imóveis - Input | D9: bu_esg_work.kt_chave_gloval; bu_esg_work.gloval_clase_energetica_dez23 | E9: n.a. | F9: ENERGY_CERTIFICATE_EST_INPUT | G9: n.a. | H9: =Table1[[#This Row],[Tabela]]&Table1[[#This Row],[Campo]] -> ENERGY_CERTIFICATE_EST_INPUTn.a. | I9: 2.1 Em Teste | J9: =VLOOKUP(Table1[[#This Row],[Status]],Auxiliar!$B$16:$C$24,2,0) -> 2 | K9: 1. Teste de universo | L9: Não | M9: Baixa | N9: 45688 | O9: =INDEX(Auxiliar!$D$5:$F$13,MATCH(Table1[[#This Row],[Tipologia_Testes]],Auxiliar!$B$5:$B$13,0),MATCH(Table1[[#This Row],[Complexidade]],Auxiliar!$D$4:$F$4,0)) -> 8 | R9: 45261 | T9: 45510 | U9: 45624 | W9: =VLOOKUP(Table1[[#This Row],[Status]],Auxiliar!$B$16:$D$24,3,0)*Table1[[#This Row],[Estimação (horas)]] -> 4 | X9: =+VLOOKUP(CONCATENATE(Table1[[#This Row],[Tabela]],Table1[[#This Row],[Campo]]),'2. Status Detalhe Campos FY24'!A:J,9,FALSE) -> Fase I
