Workbook

Sheet Âmbito de atuação
B6: Âmbito de atuação
C9: Modelo Relacional - Modelo Verde | V9: Modelo Relacional - Bens Imóveis
C39: Legenda:
D40: Tabelas âmbito de atuação

Sheet Plano_V3
B6: Re-testes - input | D6: 0.2 | P6: =P7-P10 -> 0 | Q6: =Q7-Q10 -> 0 | R6: =R7-R10 -> 0 | S6: =S7-S10 -> 0 | T6: =T7-T10 -> 0 | U6: =U7-U10 -> 0 | V6: =V7-V10 -> 0 | W6: =W7-W10 -> 0 | ... EQ6: =EQ7-EQ10 -> 0
B7: Re-testes - output | D7: =50%*25% -> 0.125 | O7: =AVERAGE(P7:EO7) -> 2.4923077 | P7: 3 | Q7: 3 | R7: 3 | S7: 3 | T7: 3 | U7: 2 | V7: 2 | W7: 2 | X7: 2 | Y7: 2 | Z7: 2 | AA7: 2 | AB7: 2 | AC7: 2 | AD7: 2 | AE7: 2 | AF7: 2 | AG7: 1 | AH7: 1 | AI7: 1 | AJ7: 3 | AK7: 3 | AL7: 3 | AM7: 3 | AN7: 2 | AO7: 3 | AP7: 3 | AQ7: 3 | AR7: 3 | AS7: 3 | AT7: 2 | AU7: 2 | AV7: 2 | AW7: 0 | AX7: 1 | AY7: 1 | AZ7: 0 | BA7: 1 | BB7: 1 | BC7: 1 | BD7: 2 | BE7: 2 | BF7: 2 | BG7: 2 | BH7: 2 | BI7: 2 | BJ7: 2 | BK7: 2 | BL7: 2 | BM7: 2 | BN7: 2 | BO7: 2 | BP7: 2 | BQ7: 2 | BR7: 2 | BS7: 3 | BT7: 3 | BU7: 3 | BV7: 3 | BW7: 3 | BX7: 3 | BY7: 3 | BZ7: 3 | CA7: 3 | CB7: 3 | CC7: 3 | CD7: 3 | CE7: 3 | CF7: 3 | CG7: 3 | CH7: 3 | CI7: 3 | CJ7: 3 | CK7: 3 | CL7: 3 | CM7: 3 | CN7: 3 | CO7: 3 | CP7: 3 | CQ7: 3 | CR7: 3 | CS7: 3 | CT7: 3 | CU7: 3 | CV7: 3 | CW7: 3 | CX7: 3 | CY7: 3 | CZ7: 3 | DA7: 3 | DB7: 3 | DC7: 3 | DD7: 3 | DE7: 3 | DF7: 3 | DG7: 3 | DH7: 3 | DI7: 3 | DJ7: 3 | DK7: 3 | DL7: 3 | DM7: 3 | DN7: 3 | DO7: 3 | DP7: 3 | DQ7: 2 | DR7: 3 | DS7: 3 | DT7: 3 | DU7: 3 | DV7: 3 | DW7: 3 | DX7: 3 | DY7: 3 | DZ7: 3 | EA7: 3 | EB7: 3 | EC7: 3 | ED7: 3 | EE7: 3 | EF7: 3 | EG7: 3 | EH7: 3 | EI7: 3 | EJ7: 3 | EK7: 3 | EL7: 0 | EM7: 0 | EN7: 0 | EO7: 0 | EP7: 0 | EQ7: 0
P10: =SUBTOTAL(9,P14:P583) -> 3 | Q10: =SUBTOTAL(9,Q14:Q583) -> 3 | R10: =SUBTOTAL(9,R14:R583) -> 3 | S10: =SUBTOTAL(9,S14:S583) -> 3 | T10: =SUBTOTAL(9,T14:T583) -> 3 | U10: =SUBTOTAL(9,U14:U583) -> 2 | V10: =SUBTOTAL(9,V14:V583) -> 2 | W10: =SUBTOTAL(9,W14:W583) -> 2 | ... EQ10: =SUBTOTAL(9,EQ14:EQ583) -> 0
P11: Julho | Z11: Julho | AM11: Agosto | BI11: Setembro | CD11: Outubro | DA11: Novembro | DV11: Dezembro
P12: =P13 -> 45474 | Q12: =Q13 -> 45475 | R12: =R13 -> 45476 | S12: =S13 -> 45477 | T12: =T13 -> 45478 | U12: =U13 -> 45481 | V12: =V13 -> 45482 | W12: =W13 -> 45483 | ... EQ12: =EQ13 -> 45657
B13: Âmbito | C13: Sub-âmbito | D13: Tipo de teste | E13: Tabela | F13: Campo | G13: Status | H13: Status2 | I13: Horas previstas | J13: Dias | K13: Horas efetivas | L13: Dias efetivos | M13: % Status | N13: Pendências | O13: Val | P13: 45474 | Q13: =WORKDAY(P13,1) -> 45475 | R13: =WORKDAY(Q13,1) -> 45476 | S13: =WORKDAY(R13,1) -> 45477 | T13: =WORKDAY(S13,1) -> 45478 | U13: =WORKDAY(T13,1) -> 45481 | V13: =WORKDAY(U13,1) -> 45482 | W13: =WORKDAY(V13,1) -> 45483 | X13: =WORKDAY(W13,1) -> 45484 | ... EQ13: =WORKDAY(EP13,1) -> 45657
B14: 1. Assessment | I14: =SUM(I15:I18) -> 280 | J14: =SUM(J15:J18) -> 35 | M14: =SUMPRODUCT(M15:M18,J15:J18)/J14 -> 0.71428571
B15: Pilar III | C15: Bens Imóveis | G15: 7. Por iniciar | I15: =J15*8 -> 40 | J15: 5 | M15: 0.5 | O15: =J15-SUM(P15:EQ15) -> 0 | Z15: 1 | AA15: 1 | AB15: 1 | AC15: 1 | AD15: 1
B16: Pilar III | C16: Modelo Verde | G16: 7. Por iniciar | I16: =J16*8 -> 80 | J16: 10 | M16: 0.5 | O16: =J16-SUM(P16:EQ16) -> 0 | U16: 2 | V16: 2 | W16: 2 | X16: 2 | Y16: 2
B17: Pilar III | C17: Pilar III | G17: 7. Por iniciar | I17: =J17*8 -> 40 | J17: 5 | M17: 0.5 | O17: =J17-SUM(P17:EQ17) -> 0 | AE17: 1 | AF17: 1 | AG17: 1 | AH17: 1 | AI17: 0.5 | AJ17: 0.5
B18: GD | C18: GD | G18: 7. Por iniciar | I18: =J18*8 -> 120 | J18: 15 | M18: 1 | O18: =J18-SUM(P18:EQ18) -> 0 | P18: 3 | Q18: 3 | R18: 3 | S18: 3 | T18: 3
B20: 2. Re-especificação | I20: =SUM(I21:I23) -> 120 | J20: =SUM(J21:J23) -> 15
B21: Pilar III | C21: Bens Imóveis | G21: 7. Por iniciar | I21: =J21*8 -> 40 | J21: 5 | O21: =J21-SUM(P21:EQ21) -> 0 | Z21: 0.5 | AE21: 0.5 | AJ21: 0.5 | AO21: 0.5 | AT21: 0.5 | AY21: 0.5 | BD21: 0.5 | BI21: 0.5 | BN21: 0.5 | BS21: 0.5
B22: Pilar III | C22: Modelo Verde | G22: 7. Por iniciar | I22: =J22*8 -> 40 | J22: 5 | O22: =J22-SUM(P22:EQ22) -> 0 | Z22: 0.5 | AE22: 0.5 | AJ22: 0.5 | AO22: 0.5 | AT22: 0.5 | AY22: 0.5 | BD22: 0.5 | BI22: 0.5 | BN22: 0.5 | BS22: 0.5
B23: Pilar III | C23: Pilar III | G23: 7. Por iniciar | I23: =J23*8 -> 40 | J23: 5 | O23: =J23-SUM(P23:EQ23) -> 0 | BI23: 0.5 | BN23: 0.5 | BS23: 0.5 | BX23: 0.5 | CC23: 0.5 | CH23: 0.5 | CM23: 0.5 | CR23: 0.5 | CW23: 0.5 | DB23: 0.5
B25: 3. Testes / Re-testes | I25: =I26+I41+I204+I371+I456 -> 2164.94 | J25: =J26+J41+J204+J371+J456 -> 273
B26: Pilar III | C26: Bens Imóveis - Input | I26: =SUM(I27:I40) -> 18.24 | J26: =ROUNDUP(I26/8,0) -> 3 | K26: =SUM(K27:K40) -> 4.56 | L26: =ROUNDUP(K26/8,0) -> 1 | O26: =J26-SUM(P26:EQ26) -> 0 | AA26: 0.5 | AB26: 0.5 | AF26: 0.5 | AM26: 0.5 | AN26: 0.5 | AO26: 0.5
A27: =E27&F27 -> cd_imv_inp_certif_estimativan.a. | B27: Pilar III | C27: Bens Imóveis - Input | D27: 1. Universo | E27: cd_imv_inp_certif_estimativa | F27: n.a. | G27: =INDEX(Auxiliar!$B$16:$B$23,MATCH(Plano_V3!H27,Auxiliar!$C$16:$C$23,0),1) -> 6. Em implementação (re-especificação) | H27: =VLOOKUP(A27,'Aux - pivots1'!$A:$B,2,0) -> 6 | I27: =SUMIFS(Table1[Estimação (horas)],Table1[Tabela],Plano_V3!E27,Table1[Campo],Plano_V3!F27) -> 8 | J27: =I27/8 -> 1 | K27: =SUMIFS(Table1[Horas efetivas],Table1[Tabela],Plano_V3!E27,Table1[Campo],Plano_V3!F27) -> 2 | L27: =K27/8 -> 0.25 | M27: =L27/J27 -> 0.25 | N27: sem pendencia | O27: =J27-SUM(P27:EQ27) -> 1
A28: =E28&F28 -> cd_imv_inp_certif_estimativacempbem | B28: Pilar III | C28: Bens Imóveis - Input | D28: 2. Campo | E28: cd_imv_inp_certif_estimativa | F28: cempbem | G28: =INDEX(Auxiliar!$B$16:$B$23,MATCH(Plano_V3!H28,Auxiliar!$C$16:$C$23,0),1) -> 6. Em implementação (re-especificação) | H28: =VLOOKUP(A28,'Aux - pivots1'!$A:$B,2,0) -> 6 | I28: =SUMIFS(Table1[Estimação (horas)],Table1[Tabela],Plano_V3!E28,Table1[Campo],Plano_V3!F28) -> 0.6 | J28: =I28/8 -> 0.075 | K28: =SUMIFS(Table1[Horas efetivas],Table1[Tabela],Plano_V3!E28,Table1[Campo],Plano_V3!F28) -> 0.15 | L28: =K28/8 -> 0.01875 | M28: =L28/J28 -> 0.25 | N28: sem pendencia | O28: =J28-SUM(P28:EQ28) -> 0.075
A29: =E29&F29 -> cd_imv_inp_certif_estimativachave_encriptada | B29: Pilar III | C29: Bens Imóveis - Input | D29: 2. Campo | E29: cd_imv_inp_certif_estimativa | F29: chave_encriptada | G29: =INDEX(Auxiliar!$B$16:$B$23,MATCH(Plano_V3!H29,Auxiliar!$C$16:$C$23,0),1) -> 6. Em implementação (re-especificação) | H29: =VLOOKUP(A29,'Aux - pivots1'!$A:$B,2,0) -> 6 | I29: =SUMIFS(Table1[Estimação (horas)],Table1[Tabela],Plano_V3!E29,Table1[Campo],Plano_V3!F29) -> 0.6 | J29: =I29/8 -> 0.075 | K29: =SUMIFS(Table1[Horas efetivas],Table1[Tabela],Plano_V3!E29,Table1[Campo],Plano_V3!F29) -> 0.15 | L29: =K29/8 -> 0.01875 | M29: =L29/J29 -> 0.25 | N29: sem pendencia | O29: =J29-SUM(P29:EQ29) -> 0.075
A30: =E30&F30 -> cd_imv_inp_certif_estimativackbalbem | B30: Pilar III | C30: Bens Imóveis - Input | D30: 2. Campo | E30: cd_imv_inp_certif_estimativa | F30: ckbalbem | G30: =INDEX(Auxiliar!$B$16:$B$23,MATCH(Plano_V3!H30,Auxiliar!$C$16:$C$23,0),1) -> 6. Em implementação (re-especificação) | H30: =VLOOKUP(A30,'Aux - pivots1'!$A:$B,2,0) -> 6 | I30: =SUMIFS(Table1[Estimação (horas)],Table1[Tabela],Plano_V3!E30,Table1[Campo],Plano_V3!F30) -> 0.6 | J30: =I30/8 -> 0.075 | K30: =SUMIFS(Table1[Horas efetivas],Table1[Tabela],Plano_V3!E30,Table1[Campo],Plano_V3!F30) -> 0.15 | L30: =K30/8 -> 0.01875 | M30: =L30/J30 -> 0.25 | N30: sem pendencia | O30: =J30-SUM(P30:EQ30) -> 0.075
A31: =E31&F31 -> cd_imv_inp_certif_estimativackctabem | B31: Pilar III | C31: Bens Imóveis - Input | D31: 2. Campo | E31: cd_imv_inp_certif_estimativa | F31: ckctabem | G31: =INDEX(Auxiliar!$B$16:$B$23,MATCH(Plano_V3!H31,Auxiliar!$C$16:$C$23,0),1) -> 6. Em implementação (re-especificação) | H31: =VLOOKUP(A31,'Aux - pivots1'!$A:$B,2,0) -> 6 | I31: =SUMIFS(Table1[Estimação (horas)],Table1[Tabela],Plano_V3!E31,Table1[Campo],Plano_V3!F31) -> 0.6 | J31: =I31/8 -> 0.075 | K31: =SUMIFS(Table1[Horas efetivas],Table1[Tabela],Plano_V3!E31,Table1[Campo],Plano_V3!F31) -> 0.15 | L31: =K31/8 -> 0.01875 | M31: =L31/J31 -> 0.25 | N31: sem pendencia | O31: =J31-SUM(P31:EQ31) -> 0.075
A32: =E32&F32 -> cd_imv_inp_certif_estimativackrefbem | B32: Pilar III | C32: Bens Imóveis - Input | D32: 2. Campo | E32: cd_imv_inp_certif_estimativa | F32: ckrefbem | G32: =INDEX(Auxiliar!$B$16:$B$23,MATCH(Plano_V3!H32,Auxiliar!$C$16:$C$23,0),1) -> 6. Em implementação (re-especificação) | H32: =VLOOKUP(A32,'Aux - pivots1'!$A:$B,2,0) -> 6 | I32: =SUMIFS(Table1[Estimação (horas)],Table1[Tabela],Plano_V3!E32,Table1[Campo],Plano_V3!F32) -> 0.6 | J32: =I32/8 -> 0.075 | K32: =SUMIFS(Table1[Horas efetivas],Table1[Tabela],Plano_V3!E32,Table1[Campo],Plano_V3!F32) -> 0.15 | L32: =K32/8 -> 0.01875 | M32: =L32/J32 -> 0.25 | N32: sem pendencia | O32: =J32-SUM(P32:EQ32) -> 0.075
A33: =E33&F33 -> cd_imv_inp_certif_estimativadata_extraccao_info | B33: Pilar III | C33: Bens Imóveis - Input | D33: 2. Campo | E33: cd_imv_inp_certif_estimativa | F33: data_extraccao_info | G33: =INDEX(Auxiliar!$B$16:$B$23,MATCH(Plano_V3!H33,Auxiliar!$C$16:$C$23,0),1) -> 6. Em implementação (re-especificação) | H33: =VLOOKUP(A33,'Aux - pivots1'!$A:$B,2,0) -> 6 | I33: =SUMIFS(Table1[Estimação (horas)],Table1[Tabela],Plano_V3!E33,Table1[Campo],Plano_V3!F33) -> 0.6 | J33: =I33/8 -> 0.075 | K33: =SUMIFS(Table1[Horas efetivas],Table1[Tabela],Plano_V3!E33,Table1[Campo],Plano_V3!F33) -> 0.15 | L33: =K33/8 -> 0.01875 | M33: =L33/J33 -> 0.25 | N33: sem pendencia | O33: =J33-SUM(P33:EQ33) -> 0.075
A34: =E34&F34 -> cd_imv_inp_certif_estimativaepc | B34: Pilar III | C34: Bens Imóveis - Input | D34: 2. Campo | E34: cd_imv_inp_certif_estimativa | F34: epc | G34: =INDEX(Auxiliar!$B$16:$B$23,MATCH(Plano_V3!H34,Auxiliar!$C$16:$C$23,0),1) -> 6. Em implementação (re-especificação) | H34: =VLOOKUP(A34,'Aux - pivots1'!$A:$B,2,0) -> 6 | I34: =SUMIFS(Table1[Estimação (horas)],Table1[Tabela],Plano_V3!E34,Table1[Campo],Plano_V3!F34) -> 0.6 | J34: =I34/8 -> 0.075 | K34: =SUMIFS(Table1[Horas efetivas],Table1[Tabela],Plano_V3!E34,Table1[Campo],Plano_V3!F34) -> 0.15 | L34: =K34/8 -> 0.01875 | M34: =L34/J34 -> 0.25 | N34: sem pendencia | O34: =J34-SUM(P34:EQ34) -> 0.075
A35: =E35&F35 -> cd_imv_inp_certif_estimativafornecedor | B35: Pilar III | C35: Bens Imóveis - Input | D35: 2. Campo | E35: cd_imv_inp_certif_estimativa | F35: fornecedor | G35: =INDEX(Auxiliar!$B$16:$B$23,MATCH(Plano_V3!H35,Auxiliar!$C$16:$C$23,0),1) -> 6. Em implementação (re-especificação) | H35: =VLOOKUP(A35,'Aux - pivots1'!$A:$B,2,0) -> 6 | I35: =SUMIFS(Table1[Estimação (horas)],Table1[Tabela],Plano_V3!E35,Table1[Campo],Plano_V3!F35) -> 0.6 | J35: =I35/8 -> 0.075 | K35: =SUMIFS(Table1[Horas efetivas],Table1[Tabela],Plano_V3!E35,Table1[Campo],Plano_V3!F35) -> 0.15 | L35: =K35/8 -> 0.01875 | M35: =L35/J35 -> 0.25 | N35: sem pendencia | O35: =J35-SUM(P35:EQ35) -> 0.075
A36: =E36&F36 -> cd_imv_inp_certif_estimativametodo_info | B36: Pilar III | C36: Bens Imóveis - Input | D36: 2. Campo | E36: cd_imv_inp_certif_estimativa | F36: metodo_info | G36: =INDEX(Auxiliar!$B$16:$B$23,MATCH(Plano_V3!H36,Auxiliar!$C$16:$C$23,0),1) -> 6. Em implementação (re-especificação) | H36: =VLOOKUP(A36,'Aux - pivots1'!$A:$B,2,0) -> 6 | I36: =SUMIFS(Table1[Estimação (horas)],Table1[Tabela],Plano_V3!E36,Table1[Campo],Plano_V3!F36) -> 0.6 | J36: =I36/8 -> 0.075 | K36: =SUMIFS(Table1[Horas efetivas],Table1[Tabela],Plano_V3!E36,Table1[Campo],Plano_V3!F36) -> 0.15 | L36: =K36/8 -> 0.01875 | M36: =L36/J36 -> 0.25 | N36: sem pendencia | O36: =J36-SUM(P36:EQ36) -> 0.075
A37: =E37&F37 -> cd_imv_inp_certif_estimativascore_qualidade | B37: Pilar III | C37: Bens Imóveis - Input | D37: 2. Campo | E37: cd_imv_inp_certif_estimativa | F37: score_qualidade | G37: =INDEX(Auxiliar!$B$16:$B$23,MATCH(Plano_V3!H37,Auxiliar!$C$16:$C$23,0),1) -> 6. Em implementação (re-especificação) | H37: =VLOOKUP(A37,'Aux - pivots1'!$A:$B,2,0) -> 6 | I37: =SUMIFS(Table1[Estimação (horas)],Table1[Tabela],Plano_V3!E37,Table1[Campo],Plano_V3!F37) -> 0.6 | J37: =I37/8 -> 0.075 | K37: =SUMIFS(Table1[Horas efetivas],Table1[Tabela],Plano_V3!E37,Table1[Campo],Plano_V3!F37) -> 0.15 | L37: =K37/8 -> 0.01875 | M37: =L37/J37 -> 0.25 | N37: sem pendencia | O37: =J37-SUM(P37:EQ37) -> 0.075
A38: =E38&F38 -> cd_imv_inp_certif_estimativavlr_cnsm_ano | B38: Pilar III | C38: Bens Imóveis - Input | D38: 2. Campo | E38: cd_imv_inp_certif_estimativa | F38: vlr_cnsm_ano | G38: =INDEX(Auxiliar!$B$16:$B$23,MATCH(Plano_V3!H38,Auxiliar!$C$16:$C$23,0),1) -> 6. Em implementação (re-especificação) | H38: =VLOOKUP(A38,'Aux - pivots1'!$A:$B,2,0) -> 6 | I38: =SUMIFS(Table1[Estimação (horas)],Table1[Tabela],Plano_V3!E38,Table1[Campo],Plano_V3!F38) -> 0.6 | J38: =I38/8 -> 0.075 | K38: =SUMIFS(Table1[Horas efetivas],Table1[Tabela],Plano_V3!E38,Table1[Campo],Plano_V3!F38) -> 0.15 | L38: =K38/8 -> 0.01875 | M38: =L38/J38 -> 0.25 | N38: sem pendencia | O38: =J38-SUM(P38:EQ38) -> 0.075
A39: =E39&F39 -> cd_imv_inp_certif_estimativavlr_emss_ano | B39: Pilar III | C39: Bens Imóveis - Input | D39: 2. Campo | E39: cd_imv_inp_certif_estimativa | F39: vlr_emss_ano | G39: =INDEX(Auxiliar!$B$16:$B$23,MATCH(Plano_V3!H39,Auxiliar!$C$16:$C$23,0),1) -> 6. Em implementação (re-especificação) | H39: =VLOOKUP(A39,'Aux - pivots1'!$A:$B,2,0) -> 6 | I39: =SUMIFS(Table1[Estimação (horas)],Table1[Tabela],Plano_V3!E39,Table1[Campo],Plano_V3!F39) -> 0.6 | J39: =I39/8 -> 0.075 | K39: =SUMIFS(Table1[Horas efetivas],Table1[Tabela],Plano_V3!E39,Table1[Campo],Plano_V3!F39) -> 0.15 | L39: =K39/8 -> 0.01875 | M39: =L39/J39 -> 0.25 | N39: sem pendencia | O39: =J39-SUM(P39:EQ39) -> 0.075
A40: =E40&F40 -> Re-testesn.a. | B40: Pilar III | C40: Bens Imóveis - Input | D40: 2. Campo | E40: Re-testes | F40: n.a. | G40: 7. Por iniciar | I40: =SUM(I27:I39)*$D$6 -> 3.04 | J40: =I40/8 -> 0.38 | K40: =SUM(K27:K39)*$D$6 -> 0.76 | L40: =K40/8 -> 0.095 | M40: =L40/J40 -> 0.25 | N40: sem pendencia | O40: =J40-SUM(P40:EQ40) -> 0.38
A41: =E41&F41 | B41: Pilar III | C41: Bens Imóveis - Output | I41: =SUM(I42:I203) -> 831.0375 | J41: =ROUNDUP(I41/8,0) -> 104 | O41: =J41-SUM(P41:EQ41) -> 4 | AJ41: 1 | AK41: 1 | AL41: 1 | AM41: 1 | AP41: 1 | AQ41: 1 | AR41: 1 | AS41: 1 | AU41: 1 | AV41: 2 | AX41: 1 | BA41: 1 | BB41: 1 | BC41: 1 | BD41: 1 | BE41: 2 | BF41: 2 | BG41: 2 | BH41: 2 | BI41: 0.5 | BJ41: 2 | BK41: 2 | BL41: 2 | BM41: 2 | BN41: 0.5 | BO41: 2 | BP41: 2 | BQ41: 2 | BR41: 2 | BS41: 1.5 | BT41: 2 | BU41: 2 | BV41: 2 | BW41: 2 | BX41: 2 | BY41: 2 | BZ41: 2 | CA41: 2 | CB41: 2 | CC41: 2 | CD41: 2 | CE41: 2 | CF41: 2 | CG41: 2 | CH41: 2 | CI41: 2 | CJ41: 2 | CK41: 2 | CL41: 2 | CM41: 2 | CN41: 2 | CO41: 2 | CP41: 2 | CQ41: 2 | CR41: 2 | CS41: 2 | CT41: 2 | CU41: 2 | CV41: 1.5
A42: =E42&F42 -> cd_imv_out_prcn.a. | B42: Pilar III | C42: Bens Imóveis - Output | D42: 1. Universo | E42: cd_imv_out_prc | F42: n.a. | G42: =INDEX(Auxiliar!$B$16:$B$23,MATCH(Plano_V3!H42,Auxiliar!$C$16:$C$23,0),1) -> 1. Concluído | H42: =VLOOKUP(A42,'Aux - pivots1'!$A:$B,2,0) -> 1 | I42: =SUMIFS(Table1[Estimação (horas)],Table1[Tabela],Plano_V3!E42,Table1[Campo],Plano_V3!F42) -> 8 | J42: =I42/8 -> 1 | K42: =SUMIFS(Table1[Horas efetivas],Table1[Tabela],Plano_V3!E42,Table1[Campo],Plano_V3!F42) -> 8 | L42: =K42/8 -> 1 | M42: =L42/J42 -> 1 | N42: cd_imv_out_trz_cred_prc | O42: =J42-SUM(P42:EQ42) -> 1
A43: =E43&F43 -> cd_imv_out_prccempresa | B43: Pilar III | C43: Bens Imóveis - Output | D43: 2. Campo | E43: cd_imv_out_prc | F43: cempresa | G43: =INDEX(Auxiliar!$B$16:$B$23,MATCH(Plano_V3!H43,Auxiliar!$C$16:$C$23,0),1) -> 1. Concluído | H43: =VLOOKUP(A43,'Aux - pivots1'!$A:$B,2,0) -> 1 | I43: =SUMIFS(Table1[Estimação (horas)],Table1[Tabela],Plano_V3!E43,Table1[Campo],Plano_V3!F43) -> 4.1 | J43: =I43/8 -> 0.5125 | K43: =SUMIFS(Table1[Horas efetivas],Table1[Tabela],Plano_V3!E43,Table1[Campo],Plano_V3!F43) -> 4.1 | L43: =K43/8 -> 0.5125 | M43: =L43/J43 -> 1 | N43: cd_imv_out_trz_cred_prc | O43: =J43-SUM(P43:EQ43) -> 0.5125
A44: =E44&F44 -> cd_imv_out_prcckbalcao | B44: Pilar III | C44: Bens Imóveis - Output | D44: 2. Campo | E44: cd_imv_out_prc | F44: ckbalcao | G44: =INDEX(Auxiliar!$B$16:$B$23,MATCH(Plano_V3!H44,Auxiliar!$C$16:$C$23,0),1) -> 1. Concluído | H44: =VLOOKUP(A44,'Aux - pivots1'!$A:$B,2,0) -> 1 | I44: =SUMIFS(Table1[Estimação (horas)],Table1[Tabela],Plano_V3!E44,Table1[Campo],Plano_V3!F44) -> 4.1 | J44: =I44/8 -> 0.5125 | K44: =SUMIFS(Table1[Horas efetivas],Table1[Tabela],Plano_V3!E44,Table1[Campo],Plano_V3!F44) -> 4.1 | L44: =K44/8 -> 0.5125 | M44: =L44/J44 -> 1 | N44: cd_imv_out_trz_cred_prc | O44: =J44-SUM(P44:EQ44) -> 0.5125
A45: =E45&F45 -> cd_imv_out_prccknumcta | B45: Pilar III | C45: Bens Imóveis - Output | D45: 2. Campo | E45: cd_imv_out_prc | F45: cknumcta | G45: =INDEX(Auxiliar!$B$16:$B$23,MATCH(Plano_V3!H45,Auxiliar!$C$16:$C$23,0),1) -> 1. Concluído | H45: =VLOOKUP(A45,'Aux - pivots1'!$A:$B,2,0) -> 1 | I45: =SUMIFS(Table1[Estimação (horas)],Table1[Tabela],Plano_V3!E45,Table1[Campo],Plano_V3!F45) -> 4.1 | J45: =I45/8 -> 0.5125 | K45: =SUMIFS(Table1[Horas efetivas],Table1[Tabela],Plano_V3!E45,Table1[Campo],Plano_V3!F45) -> 4.1 | L45: =K45/8 -> 0.5125 | M45: =L45/J45 -> 1 | N45: cd_imv_out_trz_cred_prc | O45: =J45-SUM(P45:EQ45) -> 0.5125
A46: =E46&F46 -> cd_imv_out_prccod_estd_prcs | B46: Pilar III | C46: Bens Imóveis - Output | D46: 2. Campo | E46: cd_imv_out_prc | F46: cod_estd_prcs | G46: =INDEX(Auxiliar!$B$16:$B$23,MATCH(Plano_V3!H46,Auxiliar!$C$16:$C$23,0),1) -> 0. Cancelado | H46: =VLOOKUP(A46,'Aux - pivots1'!$A:$B,2,0) -> 0 | I46: 0 | J46: =I46/8 -> 0 | K46: =SUMIFS(Table1[Horas efetivas],Table1[Tabela],Plano_V3!E46,Table1[Campo],Plano_V3!F46) -> 0 | L46: =K46/8 -> 0 | M46: =L46/J46 -> #DIV/0! | N46: cd_imv_out_trz_cred_prc | O46: =J46-SUM(P46:EQ46) -> 0
A47: =E47&F47 -> cd_imv_out_prccod_grt | B47: Pilar III | C47: Bens Imóveis - Output | D47: 2. Campo | E47: cd_imv_out_prc | F47: cod_grt | G47: =INDEX(Auxiliar!$B$16:$B$23,MATCH(Plano_V3!H47,Auxiliar!$C$16:$C$23,0),1) -> 1. Concluído | H47: =VLOOKUP(A47,'Aux - pivots1'!$A:$B,2,0) -> 1 | I47: =SUMIFS(Table1[Estimação (horas)],Table1[Tabela],Plano_V3!E47,Table1[Campo],Plano_V3!F47) -> 4.1 | J47: =I47/8 -> 0.5125 | K47: =SUMIFS(Table1[Horas efetivas],Table1[Tabela],Plano_V3!E47,Table1[Campo],Plano_V3!F47) -> 4.1 | L47: =K47/8 -> 0.5125 | M47: =L47/J47 -> 1 | N47: cd_imv_out_trz_cred_prc | O47: =J47-SUM(P47:EQ47) -> 0.5125
A48: =E48&F48 -> cd_imv_out_prccod_moeda | B48: Pilar III | C48: Bens Imóveis - Output | D48: 2. Campo | E48: cd_imv_out_prc | F48: cod_moeda | G48: =INDEX(Auxiliar!$B$16:$B$23,MATCH(Plano_V3!H48,Auxiliar!$C$16:$C$23,0),1) -> 1. Concluído | H48: =VLOOKUP(A48,'Aux - pivots1'!$A:$B,2,0) -> 1 | I48: =SUMIFS(Table1[Estimação (horas)],Table1[Tabela],Plano_V3!E48,Table1[Campo],Plano_V3!F48) -> 4.1 | J48: =I48/8 -> 0.5125 | K48: =SUMIFS(Table1[Horas efetivas],Table1[Tabela],Plano_V3!E48,Table1[Campo],Plano_V3!F48) -> 4.1 | L48: =K48/8 -> 0.5125 | M48: =L48/J48 -> 1 | N48: cd_imv_out_trz_cred_prc | O48: =J48-SUM(P48:EQ48) -> 0.5125
A49: =E49&F49 -> cd_imv_out_prccod_observacao | B49: Pilar III | C49: Bens Imóveis - Output | D49: 2. Campo | E49: cd_imv_out_prc | F49: cod_observacao | G49: =INDEX(Auxiliar!$B$16:$B$23,MATCH(Plano_V3!H49,Auxiliar!$C$16:$C$23,0),1) -> 1. Concluído | H49: =VLOOKUP(A49,'Aux - pivots1'!$A:$B,2,0) -> 1 | I49: =SUMIFS(Table1[Estimação (horas)],Table1[Tabela],Plano_V3!E49,Table1[Campo],Plano_V3!F49) -> 4.1 | J49: =I49/8 -> 0.5125 | K49: =SUMIFS(Table1[Horas efetivas],Table1[Tabela],Plano_V3!E49,Table1[Campo],Plano_V3!F49) -> 4.1 | L49: =K49/8 -> 0.5125 | M49: =L49/J49 -> 1 | N49: cd_imv_out_trz_cred_prc | O49: =J49-SUM(P49:EQ49) -> 0.5125
A50: =E50&F50 -> cd_imv_out_prccod_prd_grnt | B50: Pilar III | C50: Bens Imóveis - Output | D50: 2. Campo | E50: cd_imv_out_prc | F50: cod_prd_grnt | G50: =INDEX(Auxiliar!$B$16:$B$23,MATCH(Plano_V3!H50,Auxiliar!$C$16:$C$23,0),1) -> 1. Concluído | H50: =VLOOKUP(A50,'Aux - pivots1'!$A:$B,2,0) -> 1 | I50: =SUMIFS(Table1[Estimação (horas)],Table1[Tabela],Plano_V3!E50,Table1[Campo],Plano_V3!F50) -> 4.1 | J50: =I50/8 -> 0.5125 | K50: =SUMIFS(Table1[Horas efetivas],Table1[Tabela],Plano_V3!E50,Table1[Campo],Plano_V3!F50) -> 4.1 | L50: =K50/8 -> 0.5125 | M50: =L50/J50 -> 1 | N50: cd_imv_out_trz_cred_prc | O50: =J50-SUM(P50:EQ50) -> 0.5125
A51: =E51&F51 -> cd_imv_out_prccod_sprd_grnt | B51: Pilar III | C51: Bens Imóveis - Output | D51: 2. Campo | E51: cd_imv_out_prc | F51: cod_sprd_grnt | G51: =INDEX(Auxiliar!$B$16:$B$23,MATCH(Plano_V3!H51,Auxiliar!$C$16:$C$23,0),1) -> 1. Concluído | H51: =VLOOKUP(A51,'Aux - pivots1'!$A:$B,2,0) -> 1 | I51: =SUMIFS(Table1[Estimação (horas)],Table1[Tabela],Plano_V3!E51,Table1[Campo],Plano_V3!F51) -> 4.1 | J51: =I51/8 -> 0.5125 | K51: =SUMIFS(Table1[Horas efetivas],Table1[Tabela],Plano_V3!E51,Table1[Campo],Plano_V3!F51) -> 4.1 | L51: =K51/8 -> 0.5125 | M51: =L51/J51 -> 1 | N51: cd_imv_out_trz_cred_prc | O51: =J51-SUM(P51:EQ51) -> 0.5125
A52: =E52&F52 -> cd_imv_out_prccod_tipo | B52: Pilar III | C52: Bens Imóveis - Output | D52: 2. Campo | E52: cd_imv_out_prc | F52: cod_tipo | G52: =INDEX(Auxiliar!$B$16:$B$23,MATCH(Plano_V3!H52,Auxiliar!$C$16:$C$23,0),1) -> 1. Concluído | H52: =VLOOKUP(A52,'Aux - pivots1'!$A:$B,2,0) -> 1 | I52: =SUMIFS(Table1[Estimação (horas)],Table1[Tabela],Plano_V3!E52,Table1[Campo],Plano_V3!F52) -> 4.1 | J52: =I52/8 -> 0.5125 | K52: =SUMIFS(Table1[Horas efetivas],Table1[Tabela],Plano_V3!E52,Table1[Campo],Plano_V3!F52) -> 4.1 | L52: =K52/8 -> 0.5125 | M52: =L52/J52 -> 1 | N52: cd_imv_out_trz_cred_prc | O52: =J52-SUM(P52:EQ52) -> 0.5125
A53: =E53&F53 -> cd_imv_out_prccomp_id_gar | B53: Pilar III | C53: Bens Imóveis - Output | D53: 2. Campo | E53: cd_imv_out_prc | F53: comp_id_gar | G53: =INDEX(Auxiliar!$B$16:$B$23,MATCH(Plano_V3!H53,Auxiliar!$C$16:$C$23,0),1) -> 1. Concluído | H53: =VLOOKUP(A53,'Aux - pivots1'!$A:$B,2,0) -> 1 | I53: =SUMIFS(Table1[Estimação (horas)],Table1[Tabela],Plano_V3!E53,Table1[Campo],Plano_V3!F53) -> 4.1 | J53: =I53/8 -> 0.5125 | K53: =SUMIFS(Table1[Horas efetivas],Table1[Tabela],Plano_V3!E53,Table1[Campo],Plano_V3!F53) -> 4.1 | L53: =K53/8 -> 0.5125 | M53: =L53/J53 -> 1 | N53: cd_imv_out_trz_cred_prc | O53: =J53-SUM(P53:EQ53) -> 0.5125
A54: =E54&F54 -> cd_imv_out_prcdata_inicio | B54: Pilar III | C54: Bens Imóveis - Output | D54: 2. Campo | E54: cd_imv_out_prc | F54: data_inicio | G54: =INDEX(Auxiliar!$B$16:$B$23,MATCH(Plano_V3!H54,Auxiliar!$C$16:$C$23,0),1) -> 1. Concluído | H54: =VLOOKUP(A54,'Aux - pivots1'!$A:$B,2,0) -> 1 | I54: =SUMIFS(Table1[Estimação (horas)],Table1[Tabela],Plano_V3!E54,Table1[Campo],Plano_V3!F54) -> 4.1 | J54: =I54/8 -> 0.5125 | K54: =SUMIFS(Table1[Horas efetivas],Table1[Tabela],Plano_V3!E54,Table1[Campo],Plano_V3!F54) -> 4.1 | L54: =K54/8 -> 0.5125 | M54: =L54/J54 -> 1 | N54: cd_imv_out_trz_cred_prc | O54: =J54-SUM(P54:EQ54) -> 0.5125
A55: =E55&F55 -> cd_imv_out_prcdata_vcmt | B55: Pilar III | C55: Bens Imóveis - Output | D55: 2. Campo | E55: cd_imv_out_prc | F55: data_vcmt | G55: =INDEX(Auxiliar!$B$16:$B$23,MATCH(Plano_V3!H55,Auxiliar!$C$16:$C$23,0),1) -> 1. Concluído | H55: =VLOOKUP(A55,'Aux - pivots1'!$A:$B,2,0) -> 1 | I55: =SUMIFS(Table1[Estimação (horas)],Table1[Tabela],Plano_V3!E55,Table1[Campo],Plano_V3!F55) -> 4.1 | J55: =I55/8 -> 0.5125 | K55: =SUMIFS(Table1[Horas efetivas],Table1[Tabela],Plano_V3!E55,Table1[Campo],Plano_V3!F55) -> 4.1 | L55: =K55/8 -> 0.5125 | M55: =L55/J55 -> 1 | N55: cd_imv_out_trz_cred_prc | O55: =J55-SUM(P55:EQ55) -> 0.5125
A56: =E56&F56 -> cd_imv_out_prcmontante_eur | B56: Pilar III | C56: Bens Imóveis - Output | D56: 2. Campo | E56: cd_imv_out_prc | F56: montante_eur | G56: =INDEX(Auxiliar!$B$16:$B$23,MATCH(Plano_V3!H56,Auxiliar!$C$16:$C$23,0),1) -> 0. Cancelado | H56: =VLOOKUP(A56,'Aux - pivots1'!$A:$B,2,0) -> 0 | I56: 0 | J56: =I56/8 -> 0 | K56: =SUMIFS(Table1[Horas efetivas],Table1[Tabela],Plano_V3!E56,Table1[Campo],Plano_V3!F56) -> 0 | L56: =K56/8 -> 0 | M56: =L56/J56 -> #DIV/0! | N56: cd_imv_out_trz_cred_prc | O56: =J56-SUM(P56:EQ56) -> 0
A57: =E57&F57 -> cd_imv_out_prcmontante_org | B57: Pilar III | C57: Bens Imóveis - Output | D57: 2. Campo | E57: cd_imv_out_prc | F57: montante_org | G57: =INDEX(Auxiliar!$B$16:$B$23,MATCH(Plano_V3!H57,Auxiliar!$C$16:$C$23,0),1) -> 0. Cancelado | H57: =VLOOKUP(A57,'Aux - pivots1'!$A:$B,2,0) -> 0 | I57: 0 | J57: =I57/8 -> 0 | K57: =SUMIFS(Table1[Horas efetivas],Table1[Tabela],Plano_V3!E57,Table1[Campo],Plano_V3!F57) -> 0 | L57: =K57/8 -> 0 | M57: =L57/J57 -> #DIV/0! | N57: cd_imv_out_trz_cred_prc | O57: =J57-SUM(P57:EQ57) -> 0
A58: =E58&F58 -> cd_imv_out_prcorigem | B58: Pilar III | C58: Bens Imóveis - Output | D58: 2. Campo | E58: cd_imv_out_prc | F58: origem | G58: =INDEX(Auxiliar!$B$16:$B$23,MATCH(Plano_V3!H58,Auxiliar!$C$16:$C$23,0),1) -> 0. Cancelado | H58: =VLOOKUP(A58,'Aux - pivots1'!$A:$B,2,0) -> 0 | I58: =SUMIFS(Table1[Estimação (horas)],Table1[Tabela],Plano_V3!E58,Table1[Campo],Plano_V3!F58) -> 4.1 | J58: =I58/8 -> 0.5125 | K58: =SUMIFS(Table1[Horas efetivas],Table1[Tabela],Plano_V3!E58,Table1[Campo],Plano_V3!F58) -> 0 | L58: =K58/8 -> 0 | M58: =L58/J58 -> 0 | N58: cd_imv_out_trz_cred_prc | O58: =J58-SUM(P58:EQ58) -> 0.5125
A59: =E59&F59 -> cd_imv_out_prcref_date | B59: Pilar III | C59: Bens Imóveis - Output | D59: 2. Campo | E59: cd_imv_out_prc | F59: ref_date | G59: =INDEX(Auxiliar!$B$16:$B$23,MATCH(Plano_V3!H59,Auxiliar!$C$16:$C$23,0),1) -> 1. Concluído | H59: =VLOOKUP(A59,'Aux - pivots1'!$A:$B,2,0) -> 1 | I59: =SUMIFS(Table1[Estimação (horas)],Table1[Tabela],Plano_V3!E59,Table1[Campo],Plano_V3!F59) -> 4.1 | J59: =I59/8 -> 0.5125 | K59: =SUMIFS(Table1[Horas efetivas],Table1[Tabela],Plano_V3!E59,Table1[Campo],Plano_V3!F59) -> 4.1 | L59: =K59/8 -> 0.5125 | M59: =L59/J59 -> 1 | N59: cd_imv_out_trz_cred_prc | O59: =J59-SUM(P59:EQ59) -> 0.5125
A60: =E60&F60 -> cd_imv_out_trz_cred_prcn.a. | B60: Pilar III | C60: Bens Imóveis - Output | D60: 1. Universo | E60: cd_imv_out_trz_cred_prc | F60: n.a. | G60: =INDEX(Auxiliar!$B$16:$B$23,MATCH(Plano_V3!H60,Auxiliar!$C$16:$C$23,0),1) -> 1. Concluído | H60: =VLOOKUP(A60,'Aux - pivots1'!$A:$B,2,0) -> 1 | I60: =SUMIFS(Table1[Estimação (horas)],Table1[Tabela],Plano_V3!E60,Table1[Campo],Plano_V3!F60) -> 8 | J60: =I60/8 -> 1 | K60: =SUMIFS(Table1[Horas efetivas],Table1[Tabela],Plano_V3!E60,Table1[Campo],Plano_V3!F60) -> 8 | L60: =K60/8 -> 1 | M60: =L60/J60 -> 1 | N60: sem pendencia | O60: =J60-SUM(P60:EQ60) -> 1
A61: =E61&F61 -> cd_imv_out_trz_cred_prccempresa | B61: Pilar III | C61: Bens Imóveis - Output | D61: 2. Campo | E61: cd_imv_out_trz_cred_prc | F61: cempresa | G61: =INDEX(Auxiliar!$B$16:$B$23,MATCH(Plano_V3!H61,Auxiliar!$C$16:$C$23,0),1) -> 1. Concluído | H61: =VLOOKUP(A61,'Aux - pivots1'!$A:$B,2,0) -> 1 | I61: =SUMIFS(Table1[Estimação (horas)],Table1[Tabela],Plano_V3!E61,Table1[Campo],Plano_V3!F61) -> 8.1 | J61: =I61/8 -> 1.0125 | K61: =SUMIFS(Table1[Horas efetivas],Table1[Tabela],Plano_V3!E61,Table1[Campo],Plano_V3!F61) -> 8.1 | L61: =K61/8 -> 1.0125 | M61: =L61/J61 -> 1 | N61: sem pendencia | O61: =J61-SUM(P61:EQ61) -> 1.0125
A62: =E62&F62 -> cd_imv_out_trz_cred_prccempresp | B62: Pilar III | C62: Bens Imóveis - Output | D62: 2. Campo | E62: cd_imv_out_trz_cred_prc | F62: cempresp | G62: =INDEX(Auxiliar!$B$16:$B$23,MATCH(Plano_V3!H62,Auxiliar!$C$16:$C$23,0),1) -> 1. Concluído | H62: =VLOOKUP(A62,'Aux - pivots1'!$A:$B,2,0) -> 1 | I62: =SUMIFS(Table1[Estimação (horas)],Table1[Tabela],Plano_V3!E62,Table1[Campo],Plano_V3!F62) -> 8.1 | J62: =I62/8 -> 1.0125 | K62: =SUMIFS(Table1[Horas efetivas],Table1[Tabela],Plano_V3!E62,Table1[Campo],Plano_V3!F62) -> 8.1 | L62: =K62/8 -> 1.0125 | M62: =L62/J62 -> 1 | N62: sem pendencia | O62: =J62-SUM(P62:EQ62) -> 1.0125
A63: =E63&F63 -> cd_imv_out_trz_cred_prcckbalcao | B63: Pilar III | C63: Bens Imóveis - Output | D63: 2. Campo | E63: cd_imv_out_trz_cred_prc | F63: ckbalcao | G63: =INDEX(Auxiliar!$B$16:$B$23,MATCH(Plano_V3!H63,Auxiliar!$C$16:$C$23,0),1) -> 1. Concluído | H63: =VLOOKUP(A63,'Aux - pivots1'!$A:$B,2,0) -> 1 | I63: =SUMIFS(Table1[Estimação (horas)],Table1[Tabela],Plano_V3!E63,Table1[Campo],Plano_V3!F63) -> 8.1 | J63: =I63/8 -> 1.0125 | K63: =SUMIFS(Table1[Horas efetivas],Table1[Tabela],Plano_V3!E63,Table1[Campo],Plano_V3!F63) -> 8.1 | L63: =K63/8 -> 1.0125 | M63: =L63/J63 -> 1 | N63: sem pendencia | O63: =J63-SUM(P63:EQ63) -> 1.0125
A64: =E64&F64 -> cd_imv_out_trz_cred_prcckbalres | B64: Pilar III | C64: Bens Imóveis - Output | D64: 2. Campo | E64: cd_imv_out_trz_cred_prc | F64: ckbalres | G64: =INDEX(Auxiliar!$B$16:$B$23,MATCH(Plano_V3!H64,Auxiliar!$C$16:$C$23,0),1) -> 1. Concluído | H64: =VLOOKUP(A64,'Aux - pivots1'!$A:$B,2,0) -> 1 | I64: =SUMIFS(Table1[Estimação (horas)],Table1[Tabela],Plano_V3!E64,Table1[Campo],Plano_V3!F64) -> 8.1 | J64: =I64/8 -> 1.0125 | K64: =SUMIFS(Table1[Horas efetivas],Table1[Tabela],Plano_V3!E64,Table1[Campo],Plano_V3!F64) -> 8.1 | L64: =K64/8 -> 1.0125 | M64: =L64/J64 -> 1 | N64: sem pendencia | O64: =J64-SUM(P64:EQ64) -> 1.0125
A65: =E65&F65 -> cd_imv_out_trz_cred_prcckctares | B65: Pilar III | C65: Bens Imóveis - Output | D65: 2. Campo | E65: cd_imv_out_trz_cred_prc | F65: ckctares | G65: =INDEX(Auxiliar!$B$16:$B$23,MATCH(Plano_V3!H65,Auxiliar!$C$16:$C$23,0),1) -> 1. Concluído | H65: =VLOOKUP(A65,'Aux - pivots1'!$A:$B,2,0) -> 1 | I65: =SUMIFS(Table1[Estimação (horas)],Table1[Tabela],Plano_V3!E65,Table1[Campo],Plano_V3!F65) -> 8.1 | J65: =I65/8 -> 1.0125 | K65: =SUMIFS(Table1[Horas efetivas],Table1[Tabela],Plano_V3!E65,Table1[Campo],Plano_V3!F65) -> 8.1 | L65: =K65/8 -> 1.0125 | M65: =L65/J65 -> 1 | N65: sem pendencia | O65: =J65-SUM(P65:EQ65) -> 1.0125
A66: =E66&F66 -> cd_imv_out_trz_cred_prccknumcta | B66: Pilar III | C66: Bens Imóveis - Output | D66: 2. Campo | E66: cd_imv_out_trz_cred_prc | F66: cknumcta | G66: =INDEX(Auxiliar!$B$16:$B$23,MATCH(Plano_V3!H66,Auxiliar!$C$16:$C$23,0),1) -> 1. Concluído | H66: =VLOOKUP(A66,'Aux - pivots1'!$A:$B,2,0) -> 1 | I66: =SUMIFS(Table1[Estimação (horas)],Table1[Tabela],Plano_V3!E66,Table1[Campo],Plano_V3!F66) -> 8.1 | J66: =I66/8 -> 1.0125 | K66: =SUMIFS(Table1[Horas efetivas],Table1[Tabela],Plano_V3!E66,Table1[Campo],Plano_V3!F66) -> 8.1 | L66: =K66/8 -> 1.0125 | M66: =L66/J66 -> 1 | N66: sem pendencia | O66: =J66-SUM(P66:EQ66) -> 1.0125
A67: =E67&F67 -> cd_imv_out_trz_cred_prcckrefresp | B67: Pilar III | C67: Bens Imóveis - Output | D67: 2. Campo | E67: cd_imv_out_trz_cred_prc | F67: ckrefresp | G67: =INDEX(Auxiliar!$B$16:$B$23,MATCH(Plano_V3!H67,Auxiliar!$C$16:$C$23,0),1) -> 1. Concluído | H67: =VLOOKUP(A67,'Aux - pivots1'!$A:$B,2,0) -> 1 | I67: =SUMIFS(Table1[Estimação (horas)],Table1[Tabela],Plano_V3!E67,Table1[Campo],Plano_V3!F67) -> 8.1 | J67: =I67/8 -> 1.0125 | K67: =SUMIFS(Table1[Horas efetivas],Table1[Tabela],Plano_V3!E67,Table1[Campo],Plano_V3!F67) -> 8.1 | L67: =K67/8 -> 1.0125 | M67: =L67/J67 -> 1 | N67: sem pendencia | O67: =J67-SUM(P67:EQ67) -> 1.0125
A68: =E68&F68 -> cd_imv_out_trz_cred_prccod_fnld | B68: Pilar III | C68: Bens Imóveis - Output | D68: 2. Campo | E68: cd_imv_out_trz_cred_prc | F68: cod_fnld | G68: =INDEX(Auxiliar!$B$16:$B$23,MATCH(Plano_V3!H68,Auxiliar!$C$16:$C$23,0),1) -> 1. Concluído | H68: =VLOOKUP(A68,'Aux - pivots1'!$A:$B,2,0) -> 1 | I68: =SUMIFS(Table1[Estimação (horas)],Table1[Tabela],Plano_V3!E68,Table1[Campo],Plano_V3!F68) -> 8.1 | J68: =I68/8 -> 1.0125 | K68: =SUMIFS(Table1[Horas efetivas],Table1[Tabela],Plano_V3!E68,Table1[Campo],Plano_V3!F68) -> 8.1 | L68: =K68/8 -> 1.0125 | M68: =L68/J68 -> 1 | N68: sem pendencia | O68: =J68-SUM(P68:EQ68) -> 1.0125
A69: =E69&F69 -> cd_imv_out_trz_cred_prccod_ocupacao | B69: Pilar III | C69: Bens Imóveis - Output | D69: 2. Campo | E69: cd_imv_out_trz_cred_prc | F69: cod_ocupacao | G69: =INDEX(Auxiliar!$B$16:$B$23,MATCH(Plano_V3!H69,Auxiliar!$C$16:$C$23,0),1) -> 1. Concluído | H69: =VLOOKUP(A69,'Aux - pivots1'!$A:$B,2,0) -> 1 | I69: =SUMIFS(Table1[Estimação (horas)],Table1[Tabela],Plano_V3!E69,Table1[Campo],Plano_V3!F69) -> 8.1 | J69: =I69/8 -> 1.0125 | K69: =SUMIFS(Table1[Horas efetivas],Table1[Tabela],Plano_V3!E69,Table1[Campo],Plano_V3!F69) -> 8.1 | L69: =K69/8 -> 1.0125 | M69: =L69/J69 -> 1 | N69: sem pendencia | O69: =J69-SUM(P69:EQ69) -> 1.0125
A70: =E70&F70 -> cd_imv_out_trz_cred_prccod_prd_resp | B70: Pilar III | C70: Bens Imóveis - Output | D70: 2. Campo | E70: cd_imv_out_trz_cred_prc | F70: cod_prd_resp | G70: =INDEX(Auxiliar!$B$16:$B$23,MATCH(Plano_V3!H70,Auxiliar!$C$16:$C$23,0),1) -> 1. Concluído | H70: =VLOOKUP(A70,'Aux - pivots1'!$A:$B,2,0) -> 1 | I70: =SUMIFS(Table1[Estimação (horas)],Table1[Tabela],Plano_V3!E70,Table1[Campo],Plano_V3!F70) -> 8.1 | J70: =I70/8 -> 1.0125 | K70: =SUMIFS(Table1[Horas efetivas],Table1[Tabela],Plano_V3!E70,Table1[Campo],Plano_V3!F70) -> 8.1 | L70: =K70/8 -> 1.0125 | M70: =L70/J70 -> 1 | N70: sem pendencia | O70: =J70-SUM(P70:EQ70) -> 1.0125
A71: =E71&F71 -> cd_imv_out_trz_cred_prccod_sit | B71: Pilar III | C71: Bens Imóveis - Output | D71: 2. Campo | E71: cd_imv_out_trz_cred_prc | F71: cod_sit | G71: =INDEX(Auxiliar!$B$16:$B$23,MATCH(Plano_V3!H71,Auxiliar!$C$16:$C$23,0),1) -> 0. Cancelado | H71: =VLOOKUP(A71,'Aux - pivots1'!$A:$B,2,0) -> 0 | I71: 0 | J71: =I71/8 -> 0 | K71: =SUMIFS(Table1[Horas efetivas],Table1[Tabela],Plano_V3!E71,Table1[Campo],Plano_V3!F71) -> 0 | L71: =K71/8 -> 0 | M71: =L71/J71 -> #DIV/0! | N71: sem pendencia | O71: =J71-SUM(P71:EQ71) -> 0
A72: =E72&F72 -> cd_imv_out_trz_cred_prccod_sprd_resp | B72: Pilar III | C72: Bens Imóveis - Output | D72: 2. Campo | E72: cd_imv_out_trz_cred_prc | F72: cod_sprd_resp | G72: =INDEX(Auxiliar!$B$16:$B$23,MATCH(Plano_V3!H72,Auxiliar!$C$16:$C$23,0),1) -> 1. Concluído | H72: =VLOOKUP(A72,'Aux - pivots1'!$A:$B,2,0) -> 1 | I72: =SUMIFS(Table1[Estimação (horas)],Table1[Tabela],Plano_V3!E72,Table1[Campo],Plano_V3!F72) -> 8.1 | J72: =I72/8 -> 1.0125 | K72: =SUMIFS(Table1[Horas efetivas],Table1[Tabela],Plano_V3!E72,Table1[Campo],Plano_V3!F72) -> 8.1 | L72: =K72/8 -> 1.0125 | M72: =L72/J72 -> 1 | N72: sem pendencia | O72: =J72-SUM(P72:EQ72) -> 1.0125
A73: =E73&F73 -> cd_imv_out_trz_cred_prccomp_id_gar | B73: Pilar III | C73: Bens Imóveis - Output | D73: 2. Campo | E73: cd_imv_out_trz_cred_prc | F73: comp_id_gar | G73: =INDEX(Auxiliar!$B$16:$B$23,MATCH(Plano_V3!H73,Auxiliar!$C$16:$C$23,0),1) -> 1. Concluído | H73: =VLOOKUP(A73,'Aux - pivots1'!$A:$B,2,0) -> 1 | I73: =SUMIFS(Table1[Estimação (horas)],Table1[Tabela],Plano_V3!E73,Table1[Campo],Plano_V3!F73) -> 8.1 | J73: =I73/8 -> 1.0125 | K73: =SUMIFS(Table1[Horas efetivas],Table1[Tabela],Plano_V3!E73,Table1[Campo],Plano_V3!F73) -> 8.1 | L73: =K73/8 -> 1.0125 | M73: =L73/J73 -> 1 | N73: sem pendencia | O73: =J73-SUM(P73:EQ73) -> 1.0125
A74: =E74&F74 -> cd_imv_out_trz_cred_prcdata_fim | B74: Pilar III | C74: Bens Imóveis - Output | D74: 2. Campo | E74: cd_imv_out_trz_cred_prc | F74: data_fim | G74: =INDEX(Auxiliar!$B$16:$B$23,MATCH(Plano_V3!H74,Auxiliar!$C$16:$C$23,0),1) -> 1. Concluído | H74: =VLOOKUP(A74,'Aux - pivots1'!$A:$B,2,0) -> 1 | I74: =SUMIFS(Table1[Estimação (horas)],Table1[Tabela],Plano_V3!E74,Table1[Campo],Plano_V3!F74) -> 8.1 | J74: =I74/8 -> 1.0125 | K74: =SUMIFS(Table1[Horas efetivas],Table1[Tabela],Plano_V3!E74,Table1[Campo],Plano_V3!F74) -> 8.1 | L74: =K74/8 -> 1.0125 | M74: =L74/J74 -> 1 | N74: sem pendencia | O74: =J74-SUM(P74:EQ74) -> 1.0125
A75: =E75&F75 -> cd_imv_out_trz_cred_prcdata_inicio | B75: Pilar III | C75: Bens Imóveis - Output | D75: 2. Campo | E75: cd_imv_out_trz_cred_prc | F75: data_inicio | G75: =INDEX(Auxiliar!$B$16:$B$23,MATCH(Plano_V3!H75,Auxiliar!$C$16:$C$23,0),1) -> 1. Concluído | H75: =VLOOKUP(A75,'Aux - pivots1'!$A:$B,2,0) -> 1 | I75: =SUMIFS(Table1[Estimação (horas)],Table1[Tabela],Plano_V3!E75,Table1[Campo],Plano_V3!F75) -> 8.1 | J75: =I75/8 -> 1.0125 | K75: =SUMIFS(Table1[Horas efetivas],Table1[Tabela],Plano_V3!E75,Table1[Campo],Plano_V3!F75) -> 8.1 | L75: =K75/8 -> 1.0125 | M75: =L75/J75 -> 1 | N75: sem pendencia | O75: =J75-SUM(P75:EQ75) -> 1.0125
A76: =E76&F76 -> cd_imv_out_trz_cred_prcdata_vcmt | B76: Pilar III | C76: Bens Imóveis - Output | D76: 2. Campo | E76: cd_imv_out_trz_cred_prc | F76: data_vcmt | G76: =INDEX(Auxiliar!$B$16:$B$23,MATCH(Plano_V3!H76,Auxiliar!$C$16:$C$23,0),1) -> 1. Concluído | H76: =VLOOKUP(A76,'Aux - pivots1'!$A:$B,2,0) -> 1 | I76: =SUMIFS(Table1[Estimação (horas)],Table1[Tabela],Plano_V3!E76,Table1[Campo],Plano_V3!F76) -> 8.1 | J76: =I76/8 -> 1.0125 | K76: =SUMIFS(Table1[Horas efetivas],Table1[Tabela],Plano_V3!E76,Table1[Campo],Plano_V3!F76) -> 8.1 | L76: =K76/8 -> 1.0125 | M76: =L76/J76 -> 1 | N76: sem pendencia | O76: =J76-SUM(P76:EQ76) -> 1.0125
A77: =E77&F77 -> cd_imv_out_trz_cred_prcidetgar | B77: Pilar III | C77: Bens Imóveis - Output | D77: 2. Campo | E77: cd_imv_out_trz_cred_prc | F77: idetgar | G77: =INDEX(Auxiliar!$B$16:$B$23,MATCH(Plano_V3!H77,Auxiliar!$C$16:$C$23,0),1) -> 0. Cancelado | H77: =VLOOKUP(A77,'Aux - pivots1'!$A:$B,2,0) -> 0 | I77: 0 | J77: =I77/8 -> 0 | K77: =SUMIFS(Table1[Horas efetivas],Table1[Tabela],Plano_V3!E77,Table1[Campo],Plano_V3!F77) -> 0 | L77: =K77/8 -> 0 | M77: =L77/J77 -> #DIV/0! | N77: sem pendencia | O77: =J77-SUM(P77:EQ77) -> 0
A78: =E78&F78 -> cd_imv_out_trz_cred_prcnum_prop | B78: Pilar III | C78: Bens Imóveis - Output | D78: 2. Campo | E78: cd_imv_out_trz_cred_prc | F78: num_prop | G78: =INDEX(Auxiliar!$B$16:$B$23,MATCH(Plano_V3!H78,Auxiliar!$C$16:$C$23,0),1) -> 0. Cancelado | H78: =VLOOKUP(A78,'Aux - pivots1'!$A:$B,2,0) -> 0 | I78: 0 | J78: =I78/8 -> 0 | K78: =SUMIFS(Table1[Horas efetivas],Table1[Tabela],Plano_V3!E78,Table1[Campo],Plano_V3!F78) -> 0 | L78: =K78/8 -> 0 | M78: =L78/J78 -> #DIV/0! | N78: sem pendencia | O78: =J78-SUM(P78:EQ78) -> 0
A79: =E79&F79 -> cd_imv_out_trz_cred_prcorigem | B79: Pilar III | C79: Bens Imóveis - Output | D79: 2. Campo | E79: cd_imv_out_trz_cred_prc | F79: origem | G79: =INDEX(Auxiliar!$B$16:$B$23,MATCH(Plano_V3!H79,Auxiliar!$C$16:$C$23,0),1) -> 1. Concluído | H79: =VLOOKUP(A79,'Aux - pivots1'!$A:$B,2,0) -> 1 | I79: =SUMIFS(Table1[Estimação (horas)],Table1[Tabela],Plano_V3!E79,Table1[Campo],Plano_V3!F79) -> 4.1 | J79: =I79/8 -> 0.5125 | K79: =SUMIFS(Table1[Horas efetivas],Table1[Tabela],Plano_V3!E79,Table1[Campo],Plano_V3!F79) -> 4.1 | L79: =K79/8 -> 0.5125 | M79: =L79/J79 -> 1 | N79: sem pendencia | O79: =J79-SUM(P79:EQ79) -> 0.5125
A80: =E80&F80 -> cd_imv_out_trz_cred_prcref_date | B80: Pilar III | C80: Bens Imóveis - Output | D80: 2. Campo | E80: cd_imv_out_trz_cred_prc | F80: ref_date | G80: =INDEX(Auxiliar!$B$16:$B$23,MATCH(Plano_V3!H80,Auxiliar!$C$16:$C$23,0),1) -> 1. Concluído | H80: =VLOOKUP(A80,'Aux - pivots1'!$A:$B,2,0) -> 1 | I80: =SUMIFS(Table1[Estimação (horas)],Table1[Tabela],Plano_V3!E80,Table1[Campo],Plano_V3!F80) -> 4.1 | J80: =I80/8 -> 0.5125 | K80: =SUMIFS(Table1[Horas efetivas],Table1[Tabela],Plano_V3!E80,Table1[Campo],Plano_V3!F80) -> 4.1 | L80: =K80/8 -> 0.5125 | M80: =L80/J80 -> 1 | N80: sem pendencia | O80: =J80-SUM(P80:EQ80) -> 0.5125
A81: =E81&F81 -> cd_imv_out_trz_prc_bens_imvn.a. | B81: Pilar III | C81: Bens Imóveis - Output | D81: 1. Universo | E81: cd_imv_out_trz_prc_bens_imv | F81: n.a. | G81: =INDEX(Auxiliar!$B$16:$B$23,MATCH(Plano_V3!H81,Auxiliar!$C$16:$C$23,0),1) -> 1. Concluído | H81: =VLOOKUP(A81,'Aux - pivots1'!$A:$B,2,0) -> 1 | I81: =SUMIFS(Table1[Estimação (horas)],Table1[Tabela],Plano_V3!E81,Table1[Campo],Plano_V3!F81) -> 8 | J81: =I81/8 -> 1 | K81: =SUMIFS(Table1[Horas efetivas],Table1[Tabela],Plano_V3!E81,Table1[Campo],Plano_V3!F81) -> 8 | L81: =K81/8 -> 1 | M81: =L81/J81 -> 1 | N81: cd_imv_out_trz_cred_prc | O81: =J81-SUM(P81:EQ81) -> 1
A82: =E82&F82 -> cd_imv_out_trz_prc_bens_imvcempbem | B82: Pilar III | C82: Bens Imóveis - Output | D82: 2. Campo | E82: cd_imv_out_trz_prc_bens_imv | F82: cempbem | G82: =INDEX(Auxiliar!$B$16:$B$23,MATCH(Plano_V3!H82,Auxiliar!$C$16:$C$23,0),1) -> 1. Concluído | H82: =VLOOKUP(A82,'Aux - pivots1'!$A:$B,2,0) -> 1 | I82: =SUMIFS(Table1[Estimação (horas)],Table1[Tabela],Plano_V3!E82,Table1[Campo],Plano_V3!F82) -> 4.1 | J82: =I82/8 -> 0.5125 | K82: =SUMIFS(Table1[Horas efetivas],Table1[Tabela],Plano_V3!E82,Table1[Campo],Plano_V3!F82) -> 4.1 | L82: =K82/8 -> 0.5125 | M82: =L82/J82 -> 1 | N82: cd_imv_out_trz_cred_prc | O82: =J82-SUM(P82:EQ82) -> 0.5125
A83: =E83&F83 -> cd_imv_out_trz_prc_bens_imvcempresa | B83: Pilar III | C83: Bens Imóveis - Output | D83: 2. Campo | E83: cd_imv_out_trz_prc_bens_imv | F83: cempresa | G83: =INDEX(Auxiliar!$B$16:$B$23,MATCH(Plano_V3!H83,Auxiliar!$C$16:$C$23,0),1) -> 1. Concluído | H83: =VLOOKUP(A83,'Aux - pivots1'!$A:$B,2,0) -> 1 | I83: =SUMIFS(Table1[Estimação (horas)],Table1[Tabela],Plano_V3!E83,Table1[Campo],Plano_V3!F83) -> 8.1 | J83: =I83/8 -> 1.0125 | K83: =SUMIFS(Table1[Horas efetivas],Table1[Tabela],Plano_V3!E83,Table1[Campo],Plano_V3!F83) -> 8.1 | L83: =K83/8 -> 1.0125 | M83: =L83/J83 -> 1 | N83: cd_imv_out_trz_cred_prc | O83: =J83-SUM(P83:EQ83) -> 1.0125
A84: =E84&F84 -> cd_imv_out_trz_prc_bens_imvckbalbem | B84: Pilar III | C84: Bens Imóveis - Output | D84: 2. Campo | E84: cd_imv_out_trz_prc_bens_imv | F84: ckbalbem | G84: =INDEX(Auxiliar!$B$16:$B$23,MATCH(Plano_V3!H84,Auxiliar!$C$16:$C$23,0),1) -> 1. Concluído | H84: =VLOOKUP(A84,'Aux - pivots1'!$A:$B,2,0) -> 1 | I84: =SUMIFS(Table1[Estimação (horas)],Table1[Tabela],Plano_V3!E84,Table1[Campo],Plano_V3!F84) -> 8.1 | J84: =I84/8 -> 1.0125 | K84: =SUMIFS(Table1[Horas efetivas],Table1[Tabela],Plano_V3!E84,Table1[Campo],Plano_V3!F84) -> 8.1 | L84: =K84/8 -> 1.0125 | M84: =L84/J84 -> 1 | N84: cd_imv_out_trz_cred_prc | O84: =J84-SUM(P84:EQ84) -> 1.0125
A85: =E85&F85 -> cd_imv_out_trz_prc_bens_imvckbalcao | B85: Pilar III | C85: Bens Imóveis - Output | D85: 2. Campo | E85: cd_imv_out_trz_prc_bens_imv | F85: ckbalcao | G85: =INDEX(Auxiliar!$B$16:$B$23,MATCH(Plano_V3!H85,Auxiliar!$C$16:$C$23,0),1) -> 1. Concluído | H85: =VLOOKUP(A85,'Aux - pivots1'!$A:$B,2,0) -> 1 | I85: =SUMIFS(Table1[Estimação (horas)],Table1[Tabela],Plano_V3!E85,Table1[Campo],Plano_V3!F85) -> 8.1 | J85: =I85/8 -> 1.0125 | K85: =SUMIFS(Table1[Horas efetivas],Table1[Tabela],Plano_V3!E85,Table1[Campo],Plano_V3!F85) -> 8.1 | L85: =K85/8 -> 1.0125 | M85: =L85/J85 -> 1 | N85: cd_imv_out_trz_cred_prc | O85: =J85-SUM(P85:EQ85) -> 1.0125
A86: =E86&F86 -> cd_imv_out_trz_prc_bens_imvckctabem | B86: Pilar III | C86: Bens Imóveis - Output | D86: 2. Campo | E86: cd_imv_out_trz_prc_bens_imv | F86: ckctabem | G86: =INDEX(Auxiliar!$B$16:$B$23,MATCH(Plano_V3!H86,Auxiliar!$C$16:$C$23,0),1) -> 1. Concluído | H86: =VLOOKUP(A86,'Aux - pivots1'!$A:$B,2,0) -> 1 | I86: =SUMIFS(Table1[Estimação (horas)],Table1[Tabela],Plano_V3!E86,Table1[Campo],Plano_V3!F86) -> 8.1 | J86: =I86/8 -> 1.0125 | K86: =SUMIFS(Table1[Horas efetivas],Table1[Tabela],Plano_V3!E86,Table1[Campo],Plano_V3!F86) -> 8.1 | L86: =K86/8 -> 1.0125 | M86: =L86/J86 -> 1 | N86: cd_imv_out_trz_cred_prc | O86: =J86-SUM(P86:EQ86) -> 1.0125
A87: =E87&F87 -> cd_imv_out_trz_prc_bens_imvcknumcta | B87: Pilar III | C87: Bens Imóveis - Output | D87: 2. Campo | E87: cd_imv_out_trz_prc_bens_imv | F87: cknumcta | G87: =INDEX(Auxiliar!$B$16:$B$23,MATCH(Plano_V3!H87,Auxiliar!$C$16:$C$23,0),1) -> 1. Concluído | H87: =VLOOKUP(A87,'Aux - pivots1'!$A:$B,2,0) -> 1 | I87: =SUMIFS(Table1[Estimação (horas)],Table1[Tabela],Plano_V3!E87,Table1[Campo],Plano_V3!F87) -> 8.1 | J87: =I87/8 -> 1.0125 | K87: =SUMIFS(Table1[Horas efetivas],Table1[Tabela],Plano_V3!E87,Table1[Campo],Plano_V3!F87) -> 8.1 | L87: =K87/8 -> 1.0125 | M87: =L87/J87 -> 1 | N87: cd_imv_out_trz_cred_prc | O87: =J87-SUM(P87:EQ87) -> 1.0125
A88: =E88&F88 -> cd_imv_out_trz_prc_bens_imvckrefbem | B88: Pilar III | C88: Bens Imóveis - Output | D88: 2. Campo | E88: cd_imv_out_trz_prc_bens_imv | F88: ckrefbem | G88: =INDEX(Auxiliar!$B$16:$B$23,MATCH(Plano_V3!H88,Auxiliar!$C$16:$C$23,0),1) -> 1. Concluído | H88: =VLOOKUP(A88,'Aux - pivots1'!$A:$B,2,0) -> 1 | I88: =SUMIFS(Table1[Estimação (horas)],Table1[Tabela],Plano_V3!E88,Table1[Campo],Plano_V3!F88) -> 4.1 | J88: =I88/8 -> 0.5125 | K88: =SUMIFS(Table1[Horas efetivas],Table1[Tabela],Plano_V3!E88,Table1[Campo],Plano_V3!F88) -> 4.1 | L88: =K88/8 -> 0.5125 | M88: =L88/J88 -> 1 | N88: cd_imv_out_trz_cred_prc | O88: =J88-SUM(P88:EQ88) -> 0.5125
A89: =E89&F89 -> cd_imv_out_trz_prc_bens_imvcomp_id_gar | B89: Pilar III | C89: Bens Imóveis - Output | D89: 2. Campo | E89: cd_imv_out_trz_prc_bens_imv | F89: comp_id_gar | G89: =INDEX(Auxiliar!$B$16:$B$23,MATCH(Plano_V3!H89,Auxiliar!$C$16:$C$23,0),1) -> 1. Concluído | H89: =VLOOKUP(A89,'Aux - pivots1'!$A:$B,2,0) -> 1 | I89: =SUMIFS(Table1[Estimação (horas)],Table1[Tabela],Plano_V3!E89,Table1[Campo],Plano_V3!F89) -> 8.1 | J89: =I89/8 -> 1.0125 | K89: =SUMIFS(Table1[Horas efetivas],Table1[Tabela],Plano_V3!E89,Table1[Campo],Plano_V3!F89) -> 8.1 | L89: =K89/8 -> 1.0125 | M89: =L89/J89 -> 1 | N89: cd_imv_out_trz_cred_prc | O89: =J89-SUM(P89:EQ89) -> 1.0125
A90: =E90&F90 -> cd_imv_out_trz_prc_bens_imvdata_assc | B90: Pilar III | C90: Bens Imóveis - Output | D90: 2. Campo | E90: cd_imv_out_trz_prc_bens_imv | F90: data_assc | G90: =INDEX(Auxiliar!$B$16:$B$23,MATCH(Plano_V3!H90,Auxiliar!$C$16:$C$23,0),1) -> 0. Cancelado | H90: =VLOOKUP(A90,'Aux - pivots1'!$A:$B,2,0) -> 0 | I90: 0 | J90: =I90/8 -> 0 | K90: =SUMIFS(Table1[Horas efetivas],Table1[Tabela],Plano_V3!E90,Table1[Campo],Plano_V3!F90) -> 0 | L90: =K90/8 -> 0 | M90: =L90/J90 -> #DIV/0! | N90: cd_imv_out_trz_cred_prc | O90: =J90-SUM(P90:EQ90) -> 0
A91: =E91&F91 -> cd_imv_out_trz_prc_bens_imvflg_adj | B91: Pilar III | C91: Bens Imóveis - Output | D91: 2. Campo | E91: cd_imv_out_trz_prc_bens_imv | F91: flg_adj | G91: =INDEX(Auxiliar!$B$16:$B$23,MATCH(Plano_V3!H91,Auxiliar!$C$16:$C$23,0),1) -> 1. Concluído | H91: =VLOOKUP(A91,'Aux - pivots1'!$A:$B,2,0) -> 1 | I91: =SUMIFS(Table1[Estimação (horas)],Table1[Tabela],Plano_V3!E91,Table1[Campo],Plano_V3!F91) -> 4.1 | J91: =I91/8 -> 0.5125 | K91: =SUMIFS(Table1[Horas efetivas],Table1[Tabela],Plano_V3!E91,Table1[Campo],Plano_V3!F91) -> 4.1 | L91: =K91/8 -> 0.5125 | M91: =L91/J91 -> 1 | N91: cd_imv_out_trz_cred_prc | O91: =J91-SUM(P91:EQ91) -> 0.5125
A92: =E92&F92 -> cd_imv_out_trz_prc_bens_imvflg_col | B92: Pilar III | C92: Bens Imóveis - Output | D92: 2. Campo | E92: cd_imv_out_trz_prc_bens_imv | F92: flg_col | G92: =INDEX(Auxiliar!$B$16:$B$23,MATCH(Plano_V3!H92,Auxiliar!$C$16:$C$23,0),1) -> 1. Concluído | H92: =VLOOKUP(A92,'Aux - pivots1'!$A:$B,2,0) -> 1 | I92: =SUMIFS(Table1[Estimação (horas)],Table1[Tabela],Plano_V3!E92,Table1[Campo],Plano_V3!F92) -> 4.1 | J92: =I92/8 -> 0.5125 | K92: =SUMIFS(Table1[Horas efetivas],Table1[Tabela],Plano_V3!E92,Table1[Campo],Plano_V3!F92) -> 4.1 | L92: =K92/8 -> 0.5125 | M92: =L92/J92 -> 1 | N92: cd_imv_out_trz_cred_prc | O92: =J92-SUM(P92:EQ92) -> 0.5125
A93: =E93&F93 -> cd_imv_out_trz_prc_bens_imvflg_fin | B93: Pilar III | C93: Bens Imóveis - Output | D93: 2. Campo | E93: cd_imv_out_trz_prc_bens_imv | F93: flg_fin | G93: =INDEX(Auxiliar!$B$16:$B$23,MATCH(Plano_V3!H93,Auxiliar!$C$16:$C$23,0),1) -> 1. Concluído | H93: =VLOOKUP(A93,'Aux - pivots1'!$A:$B,2,0) -> 1 | I93: =SUMIFS(Table1[Estimação (horas)],Table1[Tabela],Plano_V3!E93,Table1[Campo],Plano_V3!F93) -> 4.1 | J93: =I93/8 -> 0.5125 | K93: =SUMIFS(Table1[Horas efetivas],Table1[Tabela],Plano_V3!E93,Table1[Campo],Plano_V3!F93) -> 4.1 | L93: =K93/8 -> 0.5125 | M93: =L93/J93 -> 1 | N93: cd_imv_out_trz_cred_prc | O93: =J93-SUM(P93:EQ93) -> 0.5125
A94: =E94&F94 -> cd_imv_out_trz_prc_bens_imvflg_pro | B94: Pilar III | C94: Bens Imóveis - Output | D94: 2. Campo | E94: cd_imv_out_trz_prc_bens_imv | F94: flg_pro | G94: =INDEX(Auxiliar!$B$16:$B$23,MATCH(Plano_V3!H94,Auxiliar!$C$16:$C$23,0),1) -> 1. Concluído | H94: =VLOOKUP(A94,'Aux - pivots1'!$A:$B,2,0) -> 1 | I94: =SUMIFS(Table1[Estimação (horas)],Table1[Tabela],Plano_V3!E94,Table1[Campo],Plano_V3!F94) -> 4.1 | J94: =I94/8 -> 0.5125 | K94: =SUMIFS(Table1[Horas efetivas],Table1[Tabela],Plano_V3!E94,Table1[Campo],Plano_V3!F94) -> 4.1 | L94: =K94/8 -> 0.5125 | M94: =L94/J94 -> 1 | N94: cd_imv_out_trz_cred_prc | O94: =J94-SUM(P94:EQ94) -> 0.5125
A95: =E95&F95 -> cd_imv_out_trz_prc_bens_imvorigem | B95: Pilar III | C95: Bens Imóveis - Output | D95: 2. Campo | E95: cd_imv_out_trz_prc_bens_imv | F95: origem | G95: =INDEX(Auxiliar!$B$16:$B$23,MATCH(Plano_V3!H95,Auxiliar!$C$16:$C$23,0),1) -> 1. Concluído | H95: =VLOOKUP(A95,'Aux - pivots1'!$A:$B,2,0) -> 1 | I95: =SUMIFS(Table1[Estimação (horas)],Table1[Tabela],Plano_V3!E95,Table1[Campo],Plano_V3!F95) -> 4.1 | J95: =I95/8 -> 0.5125 | K95: =SUMIFS(Table1[Horas efetivas],Table1[Tabela],Plano_V3!E95,Table1[Campo],Plano_V3!F95) -> 4.1 | L95: =K95/8 -> 0.5125 | M95: =L95/J95 -> 1 | N95: cd_imv_out_trz_cred_prc | O95: =J95-SUM(P95:EQ95) -> 0.5125
A96: =E96&F96 -> cd_imv_out_trz_prc_bens_imvref_date | B96: Pilar III | C96: Bens Imóveis - Output | D96: 2. Campo | E96: cd_imv_out_trz_prc_bens_imv | F96: ref_date | G96: =INDEX(Auxiliar!$B$16:$B$23,MATCH(Plano_V3!H96,Auxiliar!$C$16:$C$23,0),1) -> 1. Concluído | H96: =VLOOKUP(A96,'Aux - pivots1'!$A:$B,2,0) -> 1 | I96: =SUMIFS(Table1[Estimação (horas)],Table1[Tabela],Plano_V3!E96,Table1[Campo],Plano_V3!F96) -> 4.1 | J96: =I96/8 -> 0.5125 | K96: =SUMIFS(Table1[Horas efetivas],Table1[Tabela],Plano_V3!E96,Table1[Campo],Plano_V3!F96) -> 4.1 | L96: =K96/8 -> 0.5125 | M96: =L96/J96 -> 1 | N96: cd_imv_out_trz_cred_prc | O96: =J96-SUM(P96:EQ96) -> 0.5125
A97: =E97&F97 -> cd_imv_out_bensn.a. | B97: Pilar III | C97: Bens Imóveis - Output | D97: 1. Universo | E97: cd_imv_out_bens | F97: n.a. | G97: =INDEX(Auxiliar!$B$16:$B$23,MATCH(Plano_V3!H97,Auxiliar!$C$16:$C$23,0),1) -> 1. Concluído | H97: =VLOOKUP(A97,'Aux - pivots1'!$A:$B,2,0) -> 1 | I97: =SUMIFS(Table1[Estimação (horas)],Table1[Tabela],Plano_V3!E97,Table1[Campo],Plano_V3!F97) -> 8 | J97: =I97/8 -> 1 | K97: =SUMIFS(Table1[Horas efetivas],Table1[Tabela],Plano_V3!E97,Table1[Campo],Plano_V3!F97) -> 8 | L97: =K97/8 -> 1 | M97: =L97/J97 -> 1 | N97: cd_imv_out_trz_prc_bens_imv ; cd_imv_out_prc ; cd_imv_out_trz_cred_prc | O97: =J97-SUM(P97:EQ97) -> 1
A98: =E98&F98 -> cd_imv_out_bensano_construcao | B98: Pilar III | C98: Bens Imóveis - Output | D98: 2. Campo | E98: cd_imv_out_bens | F98: ano_construcao | G98: =INDEX(Auxiliar!$B$16:$B$23,MATCH(Plano_V3!H98,Auxiliar!$C$16:$C$23,0),1) -> 1. Concluído | H98: =VLOOKUP(A98,'Aux - pivots1'!$A:$B,2,0) -> 1 | I98: 0 | J98: =I98/8 -> 0 | K98: =SUMIFS(Table1[Horas efetivas],Table1[Tabela],Plano_V3!E98,Table1[Campo],Plano_V3!F98) -> 4 | L98: =K98/8 -> 0.5 | M98: =L98/J98 -> #DIV/0! | N98: cd_imv_out_trz_prc_bens_imv ; cd_imv_out_prc ; cd_imv_out_trz_cred_prc | O98: =J98-SUM(P98:EQ98) -> 0
A99: =E99&F99 -> cd_imv_out_bensarea_util | B99: Pilar III | C99: Bens Imóveis - Output | D99: 2. Campo | E99: cd_imv_out_bens | F99: area_util | G99: =INDEX(Auxiliar!$B$16:$B$23,MATCH(Plano_V3!H99,Auxiliar!$C$16:$C$23,0),1) -> 1. Concluído | H99: =VLOOKUP(A99,'Aux - pivots1'!$A:$B,2,0) -> 1 | I99: =SUMIFS(Table1[Estimação (horas)],Table1[Tabela],Plano_V3!E99,Table1[Campo],Plano_V3!F99) -> 8.1 | J99: =I99/8 -> 1.0125 | K99: =SUMIFS(Table1[Horas efetivas],Table1[Tabela],Plano_V3!E99,Table1[Campo],Plano_V3!F99) -> 8.1 | L99: =K99/8 -> 1.0125 | M99: =L99/J99 -> 1 | N99: cd_imv_out_trz_prc_bens_imv ; cd_imv_out_prc ; cd_imv_out_trz_cred_prc | O99: =J99-SUM(P99:EQ99) -> 1.0125
A100: =E100&F100 -> cd_imv_out_benscempbem | B100: Pilar III | C100: Bens Imóveis - Output | D100: 2. Campo | E100: cd_imv_out_bens | F100: cempbem | G100: =INDEX(Auxiliar!$B$16:$B$23,MATCH(Plano_V3!H100,Auxiliar!$C$16:$C$23,0),1) -> 1. Concluído | H100: =VLOOKUP(A100,'Aux - pivots1'!$A:$B,2,0) -> 1 | I100: =SUMIFS(Table1[Estimação (horas)],Table1[Tabela],Plano_V3!E100,Table1[Campo],Plano_V3!F100) -> 4.1 | J100: =I100/8 -> 0.5125 | K100: =SUMIFS(Table1[Horas efetivas],Table1[Tabela],Plano_V3!E100,Table1[Campo],Plano_V3!F100) -> 4.1 | L100: =K100/8 -> 0.5125 | M100: =L100/J100 -> 1 | N100: cd_imv_out_trz_prc_bens_imv ; cd_imv_out_prc ; cd_imv_out_trz_cred_prc | O100: =J100-SUM(P100:EQ100) -> 0.5125
A101: =E101&F101 -> cd_imv_out_bensckbalbem | B101: Pilar III | C101: Bens Imóveis - Output | D101: 2. Campo | E101: cd_imv_out_bens | F101: ckbalbem | G101: =INDEX(Auxiliar!$B$16:$B$23,MATCH(Plano_V3!H101,Auxiliar!$C$16:$C$23,0),1) -> 1. Concluído | H101: =VLOOKUP(A101,'Aux - pivots1'!$A:$B,2,0) -> 1 | I101: =SUMIFS(Table1[Estimação (horas)],Table1[Tabela],Plano_V3!E101,Table1[Campo],Plano_V3!F101) -> 4.1 | J101: =I101/8 -> 0.5125 | K101: =SUMIFS(Table1[Horas efetivas],Table1[Tabela],Plano_V3!E101,Table1[Campo],Plano_V3!F101) -> 4.1 | L101: =K101/8 -> 0.5125 | M101: =L101/J101 -> 1 | N101: cd_imv_out_trz_prc_bens_imv ; cd_imv_out_prc ; cd_imv_out_trz_cred_prc | O101: =J101-SUM(P101:EQ101) -> 0.5125
A102: =E102&F102 -> cd_imv_out_bensckctabem | B102: Pilar III | C102: Bens Imóveis - Output | D102: 2. Campo | E102: cd_imv_out_bens | F102: ckctabem | G102: =INDEX(Auxiliar!$B$16:$B$23,MATCH(Plano_V3!H102,Auxiliar!$C$16:$C$23,0),1) -> 1. Concluído | H102: =VLOOKUP(A102,'Aux - pivots1'!$A:$B,2,0) -> 1 | I102: =SUMIFS(Table1[Estimação (horas)],Table1[Tabela],Plano_V3!E102,Table1[Campo],Plano_V3!F102) -> 4.1 | J102: =I102/8 -> 0.5125 | K102: =SUMIFS(Table1[Horas efetivas],Table1[Tabela],Plano_V3!E102,Table1[Campo],Plano_V3!F102) -> 4.1 | L102: =K102/8 -> 0.5125 | M102: =L102/J102 -> 1 | N102: cd_imv_out_trz_prc_bens_imv ; cd_imv_out_prc ; cd_imv_out_trz_cred_prc | O102: =J102-SUM(P102:EQ102) -> 0.5125
A103: =E103&F103 -> cd_imv_out_bensckrefbem | B103: Pilar III | C103: Bens Imóveis - Output | D103: 2. Campo | E103: cd_imv_out_bens | F103: ckrefbem | G103: =INDEX(Auxiliar!$B$16:$B$23,MATCH(Plano_V3!H103,Auxiliar!$C$16:$C$23,0),1) -> 1. Concluído | H103: =VLOOKUP(A103,'Aux - pivots1'!$A:$B,2,0) -> 1 | I103: =SUMIFS(Table1[Estimação (horas)],Table1[Tabela],Plano_V3!E103,Table1[Campo],Plano_V3!F103) -> 4.1 | J103: =I103/8 -> 0.5125 | K103: =SUMIFS(Table1[Horas efetivas],Table1[Tabela],Plano_V3!E103,Table1[Campo],Plano_V3!F103) -> 4.1 | L103: =K103/8 -> 0.5125 | M103: =L103/J103 -> 1 | N103: cd_imv_out_trz_prc_bens_imv ; cd_imv_out_prc ; cd_imv_out_trz_cred_prc | O103: =J103-SUM(P103:EQ103) -> 0.5125
A104: =E104&F104 -> cd_imv_out_benscod_art_matr | B104: Pilar III | C104: Bens Imóveis - Output | D104: 2. Campo | E104: cd_imv_out_bens | F104: cod_art_matr | G104: =INDEX(Auxiliar!$B$16:$B$23,MATCH(Plano_V3!H104,Auxiliar!$C$16:$C$23,0),1) -> 1. Concluído | H104: =VLOOKUP(A104,'Aux - pivots1'!$A:$B,2,0) -> 1 | I104: =SUMIFS(Table1[Estimação (horas)],Table1[Tabela],Plano_V3!E104,Table1[Campo],Plano_V3!F104) -> 4.1 | J104: =I104/8 -> 0.5125 | K104: =SUMIFS(Table1[Horas efetivas],Table1[Tabela],Plano_V3!E104,Table1[Campo],Plano_V3!F104) -> 4.1 | L104: =K104/8 -> 0.5125 | M104: =L104/J104 -> 1 | N104: cd_imv_out_trz_prc_bens_imv ; cd_imv_out_prc ; cd_imv_out_trz_cred_prc | O104: =J104-SUM(P104:EQ104) -> 0.5125
A105: =E105&F105 -> cd_imv_out_benscod_avl | B105: Pilar III | C105: Bens Imóveis - Output | D105: 2. Campo | E105: cd_imv_out_bens | F105: cod_avl | G105: =INDEX(Auxiliar!$B$16:$B$23,MATCH(Plano_V3!H105,Auxiliar!$C$16:$C$23,0),1) -> 1. Concluído | H105: =VLOOKUP(A105,'Aux - pivots1'!$A:$B,2,0) -> 1 | I105: =SUMIFS(Table1[Estimação (horas)],Table1[Tabela],Plano_V3!E105,Table1[Campo],Plano_V3!F105) -> 4.1 | J105: =I105/8 -> 0.5125 | K105: =SUMIFS(Table1[Horas efetivas],Table1[Tabela],Plano_V3!E105,Table1[Campo],Plano_V3!F105) -> 4.1 | L105: =K105/8 -> 0.5125 | M105: =L105/J105 -> 1 | N105: cd_imv_out_trz_prc_bens_imv ; cd_imv_out_prc ; cd_imv_out_trz_cred_prc | O105: =J105-SUM(P105:EQ105) -> 0.5125
A106: =E106&F106 -> cd_imv_out_benscod_bem | B106: Pilar III | C106: Bens Imóveis - Output | D106: 2. Campo | E106: cd_imv_out_bens | F106: cod_bem | G106: =INDEX(Auxiliar!$B$16:$B$23,MATCH(Plano_V3!H106,Auxiliar!$C$16:$C$23,0),1) -> 0. Cancelado | H106: =VLOOKUP(A106,'Aux - pivots1'!$A:$B,2,0) -> 0 | I106: 0 | J106: =I106/8 -> 0 | K106: =SUMIFS(Table1[Horas efetivas],Table1[Tabela],Plano_V3!E106,Table1[Campo],Plano_V3!F106) -> 0 | L106: =K106/8 -> 0 | M106: =L106/J106 -> #DIV/0! | N106: cd_imv_out_trz_prc_bens_imv ; cd_imv_out_prc ; cd_imv_out_trz_cred_prc | O106: =J106-SUM(P106:EQ106) -> 0
A107: =E107&F107 -> cd_imv_out_benscod_disconf | B107: Pilar III | C107: Bens Imóveis - Output | D107: 2. Campo | E107: cd_imv_out_bens | F107: cod_disconf | G107: =INDEX(Auxiliar!$B$16:$B$23,MATCH(Plano_V3!H107,Auxiliar!$C$16:$C$23,0),1) -> 1. Concluído | H107: =VLOOKUP(A107,'Aux - pivots1'!$A:$B,2,0) -> 1 | I107: =SUMIFS(Table1[Estimação (horas)],Table1[Tabela],Plano_V3!E107,Table1[Campo],Plano_V3!F107) -> 4.1 | J107: =I107/8 -> 0.5125 | K107: =SUMIFS(Table1[Horas efetivas],Table1[Tabela],Plano_V3!E107,Table1[Campo],Plano_V3!F107) -> 4.1 | L107: =K107/8 -> 0.5125 | M107: =L107/J107 -> 1 | N107: cd_imv_out_trz_prc_bens_imv ; cd_imv_out_prc ; cd_imv_out_trz_cred_prc | O107: =J107-SUM(P107:EQ107) -> 0.5125
A108: =E108&F108 -> cd_imv_out_benscod_fin_bem | B108: Pilar III | C108: Bens Imóveis - Output | D108: 2. Campo | E108: cd_imv_out_bens | F108: cod_fin_bem | G108: =INDEX(Auxiliar!$B$16:$B$23,MATCH(Plano_V3!H108,Auxiliar!$C$16:$C$23,0),1) -> 1. Concluído | H108: =VLOOKUP(A108,'Aux - pivots1'!$A:$B,2,0) -> 1 | I108: =SUMIFS(Table1[Estimação (horas)],Table1[Tabela],Plano_V3!E108,Table1[Campo],Plano_V3!F108) -> 4.1 | J108: =I108/8 -> 0.5125 | K108: =SUMIFS(Table1[Horas efetivas],Table1[Tabela],Plano_V3!E108,Table1[Campo],Plano_V3!F108) -> 4.1 | L108: =K108/8 -> 0.5125 | M108: =L108/J108 -> 1 | N108: cd_imv_out_trz_prc_bens_imv ; cd_imv_out_prc ; cd_imv_out_trz_cred_prc | O108: =J108-SUM(P108:EQ108) -> 0.5125
A109: =E109&F109 -> cd_imv_out_benscod_idd_pred | B109: Pilar III | C109: Bens Imóveis - Output | D109: 2. Campo | E109: cd_imv_out_bens | F109: cod_idd_pred | G109: =INDEX(Auxiliar!$B$16:$B$23,MATCH(Plano_V3!H109,Auxiliar!$C$16:$C$23,0),1) -> 1. Concluído | H109: =VLOOKUP(A109,'Aux - pivots1'!$A:$B,2,0) -> 1 | I109: =SUMIFS(Table1[Estimação (horas)],Table1[Tabela],Plano_V3!E109,Table1[Campo],Plano_V3!F109) -> 4.1 | J109: =I109/8 -> 0.5125 | K109: =SUMIFS(Table1[Horas efetivas],Table1[Tabela],Plano_V3!E109,Table1[Campo],Plano_V3!F109) -> 4.1 | L109: =K109/8 -> 0.5125 | M109: =L109/J109 -> 1 | N109: cd_imv_out_trz_prc_bens_imv ; cd_imv_out_prc ; cd_imv_out_trz_cred_prc | O109: =J109-SUM(P109:EQ109) -> 0.5125
...

Sheet Plano_V1
B6: Re-testes - input | D6: 0.2 | M6: =M7-M10 -> 0 | N6: =N7-N10 -> 0 | O6: =O7-O10 -> 0 | P6: =P7-P10 -> 0 | Q6: =Q7-Q10 -> 0 | R6: =R7-R10 -> 0 | S6: =S7-S10 -> 0 | T6: =T7-T10 -> 0 | ... FK6: =FK7-FK10 -> 0
B7: Re-testes - output | D7: =50%*25% -> 0.125 | L7: =AVERAGE(M7:EL7) -> 2.4923077 | M7: 3 | N7: 3 | O7: 3 | P7: 3 | Q7: 3 | R7: 2 | S7: 2 | T7: 2 | U7: 2 | V7: 2 | W7: 2 | X7: 2 | Y7: 2 | Z7: 2 | AA7: 2 | AB7: 2 | AC7: 2 | AD7: 1 | AE7: 1 | AF7: 1 | AG7: 3 | AH7: 3 | AI7: 3 | AJ7: 3 | AK7: 2 | AL7: 3 | AM7: 3 | AN7: 3 | AO7: 3 | AP7: 3 | AQ7: 2 | AR7: 2 | AS7: 2 | AT7: 0 | AU7: 1 | AV7: 1 | AW7: 0 | AX7: 1 | AY7: 1 | AZ7: 1 | BA7: 2 | BB7: 2 | BC7: 2 | BD7: 2 | BE7: 2 | BF7: 2 | BG7: 2 | BH7: 2 | BI7: 2 | BJ7: 2 | BK7: 2 | BL7: 2 | BM7: 2 | BN7: 2 | BO7: 2 | BP7: 3 | BQ7: 3 | BR7: 3 | BS7: 3 | BT7: 3 | BU7: 3 | BV7: 3 | BW7: 3 | BX7: 3 | BY7: 3 | BZ7: 3 | CA7: 3 | CB7: 3 | CC7: 3 | CD7: 3 | CE7: 3 | CF7: 3 | CG7: 3 | CH7: 3 | CI7: 3 | CJ7: 3 | CK7: 3 | CL7: 3 | CM7: 3 | CN7: 3 | CO7: 3 | CP7: 3 | CQ7: 3 | CR7: 3 | CS7: 3 | CT7: 3 | CU7: 3 | CV7: 3 | CW7: 3 | CX7: 3 | CY7: 3 | CZ7: 3 | DA7: 3 | DB7: 3 | DC7: 3 | DD7: 3 | DE7: 3 | DF7: 3 | DG7: 3 | DH7: 3 | DI7: 3 | DJ7: 3 | DK7: 3 | DL7: 3 | DM7: 3 | DN7: 2 | DO7: 3 | DP7: 3 | DQ7: 3 | DR7: 3 | DS7: 3 | DT7: 3 | DU7: 3 | DV7: 3 | DW7: 3 | DX7: 3 | DY7: 3 | DZ7: 3 | EA7: 3 | EB7: 3 | EC7: 3 | ED7: 3 | EE7: 3 | EF7: 3 | EG7: 3 | EH7: 3 | EI7: 0 | EJ7: 0 | EK7: 0 | EL7: 0 | EM7: 0 | EN7: 0 | EO7: 0 | EP7: 3 | EQ7: 3 | ER7: 3 | ES7: 3 | ET7: 3 | EU7: 3 | EV7: 3 | EW7: 3 | EX7: 3 | EY7: 3 | EZ7: 3 | FA7: 3 | FB7: 3 | FC7: 3 | FD7: 3 | FE7: 3 | FF7: 3 | FG7: 3 | FH7: 3 | FI7: 3 | FJ7: 3 | FK7: 3
M10: =SUBTOTAL(9,M14:M636) -> 3 | N10: =SUBTOTAL(9,N14:N636) -> 3 | O10: =SUBTOTAL(9,O14:O636) -> 3 | P10: =SUBTOTAL(9,P14:P636) -> 3 | Q10: =SUBTOTAL(9,Q14:Q636) -> 3 | R10: =SUBTOTAL(9,R14:R636) -> 2 | S10: =SUBTOTAL(9,S14:S636) -> 2 | T10: =SUBTOTAL(9,T14:T636) -> 2 | ... FK10: =SUBTOTAL(9,FK14:FK636) -> 3
M11: Julho | W11: Julho | AJ11: Agosto | BF11: Setembro | CA11: Outubro | CX11: Novembro | DS11: Dezembro | EO11: Janeiro
M12: =M13 -> 45474 | N12: =N13 -> 45475 | O12: =O13 -> 45476 | P12: =P13 -> 45477 | Q12: =Q13 -> 45478 | R12: =R13 -> 45481 | S12: =S13 -> 45482 | T12: =T13 -> 45483 | ... FK12: =FK13 -> 45688
B13: Âmbito | C13: Sub-âmbito | D13: Tipo de teste | E13: Tabela | F13: Campo | G13: Status | H13: Status2 | I13: Horas | J13: Dias | K13: Pendências | L13: Val | M13: 45474 | N13: =WORKDAY(M13,1) -> 45475 | O13: =WORKDAY(N13,1) -> 45476 | P13: =WORKDAY(O13,1) -> 45477 | Q13: =WORKDAY(P13,1) -> 45478 | R13: =WORKDAY(Q13,1) -> 45481 | S13: =WORKDAY(R13,1) -> 45482 | T13: =WORKDAY(S13,1) -> 45483 | U13: =WORKDAY(T13,1) -> 45484 | ... FK13: =WORKDAY(FJ13,1) -> 45688
B14: 1. Assessment | I14: =SUM(I15:I18) -> 280 | J14: =SUM(J15:J18) -> 35
B15: Pilar III | C15: Bens Imóveis | G15: 7. Por iniciar | I15: =J15*8 -> 40 | J15: 5 | L15: =J15-SUM(M15:FK15) -> 0 | W15: 1 | X15: 1 | Y15: 1 | Z15: 1 | AA15: 1
B16: Pilar III | C16: Modelo Verde | G16: 7. Por iniciar | I16: =J16*8 -> 80 | J16: 10 | L16: =J16-SUM(M16:FK16) -> 0 | R16: 2 | S16: 2 | T16: 2 | U16: 2 | V16: 2
B17: Pilar III | C17: Pilar III | G17: 7. Por iniciar | I17: =J17*8 -> 40 | J17: 5 | L17: =J17-SUM(M17:FK17) -> 0 | AB17: 1 | AC17: 1 | AD17: 1 | AE17: 1 | AF17: 0.5 | AG17: 0.5
B18: GD | C18: GD | G18: 7. Por iniciar | I18: =J18*8 -> 120 | J18: 15 | L18: =J18-SUM(M18:FK18) -> 0 | M18: 3 | N18: 3 | O18: 3 | P18: 3 | Q18: 3
B20: 2. Re-especificação | I20: =SUM(I21:I23) -> 120 | J20: =SUM(J21:J23) -> 15
B21: Pilar III | C21: Bens Imóveis | G21: 7. Por iniciar | I21: =J21*8 -> 40 | J21: 5 | L21: =J21-SUM(M21:FK21) -> 0 | W21: 0.5 | AB21: 0.5 | AG21: 0.5 | AL21: 0.5 | AQ21: 0.5 | AV21: 0.5 | BA21: 0.5 | BF21: 0.5 | BK21: 0.5 | BP21: 0.5
B22: Pilar III | C22: Modelo Verde | G22: 7. Por iniciar | I22: =J22*8 -> 40 | J22: 5 | L22: =J22-SUM(M22:FK22) -> 0 | W22: 0.5 | AB22: 0.5 | AG22: 0.5 | AL22: 0.5 | AQ22: 0.5 | AV22: 0.5 | BA22: 0.5 | BF22: 0.5 | BK22: 0.5 | BP22: 0.5
B23: Pilar III | C23: Pilar III | G23: 7. Por iniciar | I23: =J23*8 -> 40 | J23: 5 | L23: =J23-SUM(M23:FK23) -> 0 | BF23: 0.5 | BK23: 0.5 | BP23: 0.5 | BU23: 0.5 | BZ23: 0.5 | CE23: 0.5 | CJ23: 0.5 | CO23: 0.5 | CT23: 0.5 | CY23: 0.5
B25: 3. Testes / Re-testes | I25: =I26+I27+I42+I198+I362+I447 -> 2213.7525 | J25: =J26+J27+J42+J198+J362+J447 -> 279
B26: Testes Regressivos | G26: 7. Por iniciar | I26: =4*22 -> 88 | J26: =I26/8 -> 11 | L26: =J26-SUM(M26:FK26) -> 0 | AA26: 0.5 | AF26: 0.5 | AK26: 0.5 | AP26: 0.5 | AU26: 0.5 | AZ26: 0.5 | BE26: 0.5 | BJ26: 0.5 | BO26: 0.5 | BT26: 0.5 | BY26: 0.5 | CD26: 0.5 | CI26: 0.5 | CN26: 0.5 | CS26: 0.5 | CX26: 0.5 | DC26: 0.5 | DH26: 0.5 | DM26: 0.5 | DR26: 0.5 | DW26: 0.5 | EB26: 0.5
B27: Pilar III | C27: Bens Imóveis - Input | I27: =SUM(I28:I41) -> 18.24 | J27: =ROUNDUP(I27/8,0) -> 3 | L27: =J27-SUM(M27:FK27) -> 0 | X27: 0.5 | Y27: 0.5 | AC27: 0.5 | AG27: 1 | AH27: 0.5
A28: =E28&F28 -> cd_imv_inp_certif_estimativan.a. | B28: Pilar III | C28: Bens Imóveis - Input | D28: 1. Universo | E28: cd_imv_inp_certif_estimativa | F28: n.a. | G28: =INDEX(Auxiliar!$B$16:$B$23,MATCH(Plano_V1!H28,Auxiliar!$C$16:$C$23,0),1) -> 6. Em implementação (re-especificação) | H28: =VLOOKUP(A28,'Aux - pivots1'!$A:$B,2,0) -> 6 | I28: =SUMIFS(Table1[Estimação (horas)],Table1[Tabela],Plano_V1!E28,Table1[Campo],Plano_V1!F28) -> 8 | J28: =I28/8 -> 1 | K28: sem pendencia | L28: =J28-SUM(M28:FK28) -> 1
A29: =E29&F29 -> cd_imv_inp_certif_estimativacempbem | B29: Pilar III | C29: Bens Imóveis - Input | D29: 2. Campo | E29: cd_imv_inp_certif_estimativa | F29: cempbem | G29: =INDEX(Auxiliar!$B$16:$B$23,MATCH(Plano_V1!H29,Auxiliar!$C$16:$C$23,0),1) -> 6. Em implementação (re-especificação) | H29: =VLOOKUP(A29,'Aux - pivots1'!$A:$B,2,0) -> 6 | I29: =SUMIFS(Table1[Estimação (horas)],Table1[Tabela],Plano_V1!E29,Table1[Campo],Plano_V1!F29) -> 0.6 | J29: =I29/8 -> 0.075 | K29: sem pendencia | L29: =J29-SUM(M29:FK29) -> 0.075
A30: =E30&F30 -> cd_imv_inp_certif_estimativachave_encriptada | B30: Pilar III | C30: Bens Imóveis - Input | D30: 2. Campo | E30: cd_imv_inp_certif_estimativa | F30: chave_encriptada | G30: =INDEX(Auxiliar!$B$16:$B$23,MATCH(Plano_V1!H30,Auxiliar!$C$16:$C$23,0),1) -> 6. Em implementação (re-especificação) | H30: =VLOOKUP(A30,'Aux - pivots1'!$A:$B,2,0) -> 6 | I30: =SUMIFS(Table1[Estimação (horas)],Table1[Tabela],Plano_V1!E30,Table1[Campo],Plano_V1!F30) -> 0.6 | J30: =I30/8 -> 0.075 | K30: sem pendencia | L30: =J30-SUM(M30:FK30) -> 0.075
A31: =E31&F31 -> cd_imv_inp_certif_estimativackbalbem | B31: Pilar III | C31: Bens Imóveis - Input | D31: 2. Campo | E31: cd_imv_inp_certif_estimativa | F31: ckbalbem | G31: =INDEX(Auxiliar!$B$16:$B$23,MATCH(Plano_V1!H31,Auxiliar!$C$16:$C$23,0),1) -> 6. Em implementação (re-especificação) | H31: =VLOOKUP(A31,'Aux - pivots1'!$A:$B,2,0) -> 6 | I31: =SUMIFS(Table1[Estimação (horas)],Table1[Tabela],Plano_V1!E31,Table1[Campo],Plano_V1!F31) -> 0.6 | J31: =I31/8 -> 0.075 | K31: sem pendencia | L31: =J31-SUM(M31:FK31) -> 0.075
A32: =E32&F32 -> cd_imv_inp_certif_estimativackctabem | B32: Pilar III | C32: Bens Imóveis - Input | D32: 2. Campo | E32: cd_imv_inp_certif_estimativa | F32: ckctabem | G32: =INDEX(Auxiliar!$B$16:$B$23,MATCH(Plano_V1!H32,Auxiliar!$C$16:$C$23,0),1) -> 6. Em implementação (re-especificação) | H32: =VLOOKUP(A32,'Aux - pivots1'!$A:$B,2,0) -> 6 | I32: =SUMIFS(Table1[Estimação (horas)],Table1[Tabela],Plano_V1!E32,Table1[Campo],Plano_V1!F32) -> 0.6 | J32: =I32/8 -> 0.075 | K32: sem pendencia | L32: =J32-SUM(M32:FK32) -> 0.075
A33: =E33&F33 -> cd_imv_inp_certif_estimativackrefbem | B33: Pilar III | C33: Bens Imóveis - Input | D33: 2. Campo | E33: cd_imv_inp_certif_estimativa | F33: ckrefbem | G33: =INDEX(Auxiliar!$B$16:$B$23,MATCH(Plano_V1!H33,Auxiliar!$C$16:$C$23,0),1) -> 6. Em implementação (re-especificação) | H33: =VLOOKUP(A33,'Aux - pivots1'!$A:$B,2,0) -> 6 | I33: =SUMIFS(Table1[Estimação (horas)],Table1[Tabela],Plano_V1!E33,Table1[Campo],Plano_V1!F33) -> 0.6 | J33: =I33/8 -> 0.075 | K33: sem pendencia | L33: =J33-SUM(M33:FK33) -> 0.075
A34: =E34&F34 -> cd_imv_inp_certif_estimativadata_extraccao_info | B34: Pilar III | C34: Bens Imóveis - Input | D34: 2. Campo | E34: cd_imv_inp_certif_estimativa | F34: data_extraccao_info | G34: =INDEX(Auxiliar!$B$16:$B$23,MATCH(Plano_V1!H34,Auxiliar!$C$16:$C$23,0),1) -> 6. Em implementação (re-especificação) | H34: =VLOOKUP(A34,'Aux - pivots1'!$A:$B,2,0) -> 6 | I34: =SUMIFS(Table1[Estimação (horas)],Table1[Tabela],Plano_V1!E34,Table1[Campo],Plano_V1!F34) -> 0.6 | J34: =I34/8 -> 0.075 | K34: sem pendencia | L34: =J34-SUM(M34:FK34) -> 0.075
A35: =E35&F35 -> cd_imv_inp_certif_estimativaepc | B35: Pilar III | C35: Bens Imóveis - Input | D35: 2. Campo | E35: cd_imv_inp_certif_estimativa | F35: epc | G35: =INDEX(Auxiliar!$B$16:$B$23,MATCH(Plano_V1!H35,Auxiliar!$C$16:$C$23,0),1) -> 6. Em implementação (re-especificação) | H35: =VLOOKUP(A35,'Aux - pivots1'!$A:$B,2,0) -> 6 | I35: =SUMIFS(Table1[Estimação (horas)],Table1[Tabela],Plano_V1!E35,Table1[Campo],Plano_V1!F35) -> 0.6 | J35: =I35/8 -> 0.075 | K35: sem pendencia | L35: =J35-SUM(M35:FK35) -> 0.075
A36: =E36&F36 -> cd_imv_inp_certif_estimativafornecedor | B36: Pilar III | C36: Bens Imóveis - Input | D36: 2. Campo | E36: cd_imv_inp_certif_estimativa | F36: fornecedor | G36: =INDEX(Auxiliar!$B$16:$B$23,MATCH(Plano_V1!H36,Auxiliar!$C$16:$C$23,0),1) -> 6. Em implementação (re-especificação) | H36: =VLOOKUP(A36,'Aux - pivots1'!$A:$B,2,0) -> 6 | I36: =SUMIFS(Table1[Estimação (horas)],Table1[Tabela],Plano_V1!E36,Table1[Campo],Plano_V1!F36) -> 0.6 | J36: =I36/8 -> 0.075 | K36: sem pendencia | L36: =J36-SUM(M36:FK36) -> 0.075
A37: =E37&F37 -> cd_imv_inp_certif_estimativametodo_info | B37: Pilar III | C37: Bens Imóveis - Input | D37: 2. Campo | E37: cd_imv_inp_certif_estimativa | F37: metodo_info | G37: =INDEX(Auxiliar!$B$16:$B$23,MATCH(Plano_V1!H37,Auxiliar!$C$16:$C$23,0),1) -> 6. Em implementação (re-especificação) | H37: =VLOOKUP(A37,'Aux - pivots1'!$A:$B,2,0) -> 6 | I37: =SUMIFS(Table1[Estimação (horas)],Table1[Tabela],Plano_V1!E37,Table1[Campo],Plano_V1!F37) -> 0.6 | J37: =I37/8 -> 0.075 | K37: sem pendencia | L37: =J37-SUM(M37:FK37) -> 0.075
A38: =E38&F38 -> cd_imv_inp_certif_estimativascore_qualidade | B38: Pilar III | C38: Bens Imóveis - Input | D38: 2. Campo | E38: cd_imv_inp_certif_estimativa | F38: score_qualidade | G38: =INDEX(Auxiliar!$B$16:$B$23,MATCH(Plano_V1!H38,Auxiliar!$C$16:$C$23,0),1) -> 6. Em implementação (re-especificação) | H38: =VLOOKUP(A38,'Aux - pivots1'!$A:$B,2,0) -> 6 | I38: =SUMIFS(Table1[Estimação (horas)],Table1[Tabela],Plano_V1!E38,Table1[Campo],Plano_V1!F38) -> 0.6 | J38: =I38/8 -> 0.075 | K38: sem pendencia | L38: =J38-SUM(M38:FK38) -> 0.075
A39: =E39&F39 -> cd_imv_inp_certif_estimativavlr_cnsm_ano | B39: Pilar III | C39: Bens Imóveis - Input | D39: 2. Campo | E39: cd_imv_inp_certif_estimativa | F39: vlr_cnsm_ano | G39: =INDEX(Auxiliar!$B$16:$B$23,MATCH(Plano_V1!H39,Auxiliar!$C$16:$C$23,0),1) -> 6. Em implementação (re-especificação) | H39: =VLOOKUP(A39,'Aux - pivots1'!$A:$B,2,0) -> 6 | I39: =SUMIFS(Table1[Estimação (horas)],Table1[Tabela],Plano_V1!E39,Table1[Campo],Plano_V1!F39) -> 0.6 | J39: =I39/8 -> 0.075 | K39: sem pendencia | L39: =J39-SUM(M39:FK39) -> 0.075
A40: =E40&F40 -> cd_imv_inp_certif_estimativavlr_emss_ano | B40: Pilar III | C40: Bens Imóveis - Input | D40: 2. Campo | E40: cd_imv_inp_certif_estimativa | F40: vlr_emss_ano | G40: =INDEX(Auxiliar!$B$16:$B$23,MATCH(Plano_V1!H40,Auxiliar!$C$16:$C$23,0),1) -> 6. Em implementação (re-especificação) | H40: =VLOOKUP(A40,'Aux - pivots1'!$A:$B,2,0) -> 6 | I40: =SUMIFS(Table1[Estimação (horas)],Table1[Tabela],Plano_V1!E40,Table1[Campo],Plano_V1!F40) -> 0.6 | J40: =I40/8 -> 0.075 | K40: sem pendencia | L40: =J40-SUM(M40:FK40) -> 0.075
A41: =E41&F41 -> Re-testesn.a. | B41: Pilar III | C41: Bens Imóveis - Input | D41: 2. Campo | E41: Re-testes | F41: n.a. | G41: 7. Por iniciar | I41: =SUM(I28:I40)*D6 -> 3.04 | J41: =I41/8 -> 0.38 | K41: sem pendencia | L41: =J41-SUM(M41:FK41) -> 0.38
A42: =E42&F42 | B42: Pilar III | C42: Bens Imóveis - Output | I42: =SUM(I43:I197) -> 798.75 | J42: =ROUNDUP(I42/8,0) -> 100 | L42: =J42-SUM(M42:FK42) -> 0 | AH42: 0.5 | AI42: 1 | AJ42: 1 | AM42: 1 | AN42: 1 | AO42: 1 | AP42: 0.5 | AR42: 1 | AS42: 2 | AU42: 0.5 | AX42: 1 | AY42: 1 | AZ42: 0.5 | BA42: 1 | BB42: 2 | BC42: 2 | BD42: 2 | BE42: 1.5 | BF42: 0.5 | BG42: 2 | BH42: 2 | BI42: 2 | BJ42: 1.5 | BK42: 0.5 | BL42: 2 | BM42: 2 | BN42: 2 | BO42: 1.5 | BP42: 1.5 | BQ42: 2 | BR42: 2 | BS42: 2 | BT42: 2 | BU42: 2 | BV42: 2 | BW42: 2 | BX42: 2 | BY42: 2 | BZ42: 2 | CA42: 2 | CB42: 2 | CC42: 2 | CD42: 2 | CE42: 2 | CF42: 2 | CG42: 2 | CH42: 2 | CI42: 2 | CJ42: 2 | CK42: 2 | CL42: 2 | CM42: 2 | CN42: 2 | CO42: 2 | CP42: 2 | CQ42: 2 | CR42: 2 | CS42: 2 | CT42: 2 | CU42: 2
A43: =E43&F43 -> cd_imv_out_prcn.a. | B43: Pilar III | C43: Bens Imóveis - Output | D43: 1. Universo | E43: cd_imv_out_prc | F43: n.a. | G43: =INDEX(Auxiliar!$B$16:$B$23,MATCH(Plano_V1!H43,Auxiliar!$C$16:$C$23,0),1) -> 1. Concluído | H43: =VLOOKUP(A43,'Aux - pivots1'!$A:$B,2,0) -> 1 | I43: =SUMIFS(Table1[Estimação (horas)],Table1[Tabela],Plano_V1!E43,Table1[Campo],Plano_V1!F43) -> 8 | J43: =I43/8 -> 1 | K43: cd_imv_out_trz_cred_prc | L43: =J43-SUM(M43:FK43) -> 1
A44: =E44&F44 -> cd_imv_out_prccempresa | B44: Pilar III | C44: Bens Imóveis - Output | D44: 2. Campo | E44: cd_imv_out_prc | F44: cempresa | G44: =INDEX(Auxiliar!$B$16:$B$23,MATCH(Plano_V1!H44,Auxiliar!$C$16:$C$23,0),1) -> 1. Concluído | H44: =VLOOKUP(A44,'Aux - pivots1'!$A:$B,2,0) -> 1 | I44: =SUMIFS(Table1[Estimação (horas)],Table1[Tabela],Plano_V1!E44,Table1[Campo],Plano_V1!F44) -> 4.1 | J44: =I44/8 -> 0.5125 | K44: cd_imv_out_trz_cred_prc | L44: =J44-SUM(M44:FK44) -> 0.5125
A45: =E45&F45 -> cd_imv_out_prcckbalcao | B45: Pilar III | C45: Bens Imóveis - Output | D45: 2. Campo | E45: cd_imv_out_prc | F45: ckbalcao | G45: =INDEX(Auxiliar!$B$16:$B$23,MATCH(Plano_V1!H45,Auxiliar!$C$16:$C$23,0),1) -> 1. Concluído | H45: =VLOOKUP(A45,'Aux - pivots1'!$A:$B,2,0) -> 1 | I45: =SUMIFS(Table1[Estimação (horas)],Table1[Tabela],Plano_V1!E45,Table1[Campo],Plano_V1!F45) -> 4.1 | J45: =I45/8 -> 0.5125 | K45: cd_imv_out_trz_cred_prc | L45: =J45-SUM(M45:FK45) -> 0.5125
A46: =E46&F46 -> cd_imv_out_prccknumcta | B46: Pilar III | C46: Bens Imóveis - Output | D46: 2. Campo | E46: cd_imv_out_prc | F46: cknumcta | G46: =INDEX(Auxiliar!$B$16:$B$23,MATCH(Plano_V1!H46,Auxiliar!$C$16:$C$23,0),1) -> 1. Concluído | H46: =VLOOKUP(A46,'Aux - pivots1'!$A:$B,2,0) -> 1 | I46: =SUMIFS(Table1[Estimação (horas)],Table1[Tabela],Plano_V1!E46,Table1[Campo],Plano_V1!F46) -> 4.1 | J46: =I46/8 -> 0.5125 | K46: cd_imv_out_trz_cred_prc | L46: =J46-SUM(M46:FK46) -> 0.5125
A47: =E47&F47 -> cd_imv_out_prccod_estd_prcs | B47: Pilar III | C47: Bens Imóveis - Output | D47: 2. Campo | E47: cd_imv_out_prc | F47: cod_estd_prcs | G47: =INDEX(Auxiliar!$B$16:$B$23,MATCH(Plano_V1!H47,Auxiliar!$C$16:$C$23,0),1) -> 0. Cancelado | H47: =VLOOKUP(A47,'Aux - pivots1'!$A:$B,2,0) -> 0 | I47: 0 | J47: =I47/8 -> 0 | K47: cd_imv_out_trz_cred_prc | L47: =J47-SUM(M47:FK47) -> 0
A48: =E48&F48 -> cd_imv_out_prccod_grt | B48: Pilar III | C48: Bens Imóveis - Output | D48: 2. Campo | E48: cd_imv_out_prc | F48: cod_grt | G48: =INDEX(Auxiliar!$B$16:$B$23,MATCH(Plano_V1!H48,Auxiliar!$C$16:$C$23,0),1) -> 1. Concluído | H48: =VLOOKUP(A48,'Aux - pivots1'!$A:$B,2,0) -> 1 | I48: =SUMIFS(Table1[Estimação (horas)],Table1[Tabela],Plano_V1!E48,Table1[Campo],Plano_V1!F48) -> 4.1 | J48: =I48/8 -> 0.5125 | K48: cd_imv_out_trz_cred_prc | L48: =J48-SUM(M48:FK48) -> 0.5125
A49: =E49&F49 -> cd_imv_out_prccod_moeda | B49: Pilar III | C49: Bens Imóveis - Output | D49: 2. Campo | E49: cd_imv_out_prc | F49: cod_moeda | G49: =INDEX(Auxiliar!$B$16:$B$23,MATCH(Plano_V1!H49,Auxiliar!$C$16:$C$23,0),1) -> 1. Concluído | H49: =VLOOKUP(A49,'Aux - pivots1'!$A:$B,2,0) -> 1 | I49: =SUMIFS(Table1[Estimação (horas)],Table1[Tabela],Plano_V1!E49,Table1[Campo],Plano_V1!F49) -> 4.1 | J49: =I49/8 -> 0.5125 | K49: cd_imv_out_trz_cred_prc | L49: =J49-SUM(M49:FK49) -> 0.5125
A50: =E50&F50 -> cd_imv_out_prccod_observacao | B50: Pilar III | C50: Bens Imóveis - Output | D50: 2. Campo | E50: cd_imv_out_prc | F50: cod_observacao | G50: =INDEX(Auxiliar!$B$16:$B$23,MATCH(Plano_V1!H50,Auxiliar!$C$16:$C$23,0),1) -> 1. Concluído | H50: =VLOOKUP(A50,'Aux - pivots1'!$A:$B,2,0) -> 1 | I50: =SUMIFS(Table1[Estimação (horas)],Table1[Tabela],Plano_V1!E50,Table1[Campo],Plano_V1!F50) -> 4.1 | J50: =I50/8 -> 0.5125 | K50: cd_imv_out_trz_cred_prc | L50: =J50-SUM(M50:FK50) -> 0.5125
A51: =E51&F51 -> cd_imv_out_prccod_prd_grnt | B51: Pilar III | C51: Bens Imóveis - Output | D51: 2. Campo | E51: cd_imv_out_prc | F51: cod_prd_grnt | G51: =INDEX(Auxiliar!$B$16:$B$23,MATCH(Plano_V1!H51,Auxiliar!$C$16:$C$23,0),1) -> 1. Concluído | H51: =VLOOKUP(A51,'Aux - pivots1'!$A:$B,2,0) -> 1 | I51: =SUMIFS(Table1[Estimação (horas)],Table1[Tabela],Plano_V1!E51,Table1[Campo],Plano_V1!F51) -> 4.1 | J51: =I51/8 -> 0.5125 | K51: cd_imv_out_trz_cred_prc | L51: =J51-SUM(M51:FK51) -> 0.5125
A52: =E52&F52 -> cd_imv_out_prccod_sprd_grnt | B52: Pilar III | C52: Bens Imóveis - Output | D52: 2. Campo | E52: cd_imv_out_prc | F52: cod_sprd_grnt | G52: =INDEX(Auxiliar!$B$16:$B$23,MATCH(Plano_V1!H52,Auxiliar!$C$16:$C$23,0),1) -> 1. Concluído | H52: =VLOOKUP(A52,'Aux - pivots1'!$A:$B,2,0) -> 1 | I52: =SUMIFS(Table1[Estimação (horas)],Table1[Tabela],Plano_V1!E52,Table1[Campo],Plano_V1!F52) -> 4.1 | J52: =I52/8 -> 0.5125 | K52: cd_imv_out_trz_cred_prc | L52: =J52-SUM(M52:FK52) -> 0.5125
A53: =E53&F53 -> cd_imv_out_prccod_tipo | B53: Pilar III | C53: Bens Imóveis - Output | D53: 2. Campo | E53: cd_imv_out_prc | F53: cod_tipo | G53: =INDEX(Auxiliar!$B$16:$B$23,MATCH(Plano_V1!H53,Auxiliar!$C$16:$C$23,0),1) -> 1. Concluído | H53: =VLOOKUP(A53,'Aux - pivots1'!$A:$B,2,0) -> 1 | I53: =SUMIFS(Table1[Estimação (horas)],Table1[Tabela],Plano_V1!E53,Table1[Campo],Plano_V1!F53) -> 4.1 | J53: =I53/8 -> 0.5125 | K53: cd_imv_out_trz_cred_prc | L53: =J53-SUM(M53:FK53) -> 0.5125
A54: =E54&F54 -> cd_imv_out_prccomp_id_gar | B54: Pilar III | C54: Bens Imóveis - Output | D54: 2. Campo | E54: cd_imv_out_prc | F54: comp_id_gar | G54: =INDEX(Auxiliar!$B$16:$B$23,MATCH(Plano_V1!H54,Auxiliar!$C$16:$C$23,0),1) -> 1. Concluído | H54: =VLOOKUP(A54,'Aux - pivots1'!$A:$B,2,0) -> 1 | I54: =SUMIFS(Table1[Estimação (horas)],Table1[Tabela],Plano_V1!E54,Table1[Campo],Plano_V1!F54) -> 4.1 | J54: =I54/8 -> 0.5125 | K54: cd_imv_out_trz_cred_prc | L54: =J54-SUM(M54:FK54) -> 0.5125
A55: =E55&F55 -> cd_imv_out_prcdata_inicio | B55: Pilar III | C55: Bens Imóveis - Output | D55: 2. Campo | E55: cd_imv_out_prc | F55: data_inicio | G55: =INDEX(Auxiliar!$B$16:$B$23,MATCH(Plano_V1!H55,Auxiliar!$C$16:$C$23,0),1) -> 1. Concluído | H55: =VLOOKUP(A55,'Aux - pivots1'!$A:$B,2,0) -> 1 | I55: =SUMIFS(Table1[Estimação (horas)],Table1[Tabela],Plano_V1!E55,Table1[Campo],Plano_V1!F55) -> 4.1 | J55: =I55/8 -> 0.5125 | K55: cd_imv_out_trz_cred_prc | L55: =J55-SUM(M55:FK55) -> 0.5125
A56: =E56&F56 -> cd_imv_out_prcdata_vcmt | B56: Pilar III | C56: Bens Imóveis - Output | D56: 2. Campo | E56: cd_imv_out_prc | F56: data_vcmt | G56: =INDEX(Auxiliar!$B$16:$B$23,MATCH(Plano_V1!H56,Auxiliar!$C$16:$C$23,0),1) -> 1. Concluído | H56: =VLOOKUP(A56,'Aux - pivots1'!$A:$B,2,0) -> 1 | I56: =SUMIFS(Table1[Estimação (horas)],Table1[Tabela],Plano_V1!E56,Table1[Campo],Plano_V1!F56) -> 4.1 | J56: =I56/8 -> 0.5125 | K56: cd_imv_out_trz_cred_prc | L56: =J56-SUM(M56:FK56) -> 0.5125
A57: =E57&F57 -> cd_imv_out_prcmontante_eur | B57: Pilar III | C57: Bens Imóveis - Output | D57: 2. Campo | E57: cd_imv_out_prc | F57: montante_eur | G57: =INDEX(Auxiliar!$B$16:$B$23,MATCH(Plano_V1!H57,Auxiliar!$C$16:$C$23,0),1) -> 0. Cancelado | H57: =VLOOKUP(A57,'Aux - pivots1'!$A:$B,2,0) -> 0 | I57: 0 | J57: =I57/8 -> 0 | K57: cd_imv_out_trz_cred_prc | L57: =J57-SUM(M57:FK57) -> 0
A58: =E58&F58 -> cd_imv_out_prcmontante_org | B58: Pilar III | C58: Bens Imóveis - Output | D58: 2. Campo | E58: cd_imv_out_prc | F58: montante_org | G58: =INDEX(Auxiliar!$B$16:$B$23,MATCH(Plano_V1!H58,Auxiliar!$C$16:$C$23,0),1) -> 0. Cancelado | H58: =VLOOKUP(A58,'Aux - pivots1'!$A:$B,2,0) -> 0 | I58: 0 | J58: =I58/8 -> 0 | K58: cd_imv_out_trz_cred_prc | L58: =J58-SUM(M58:FK58) -> 0
A59: =E59&F59 -> cd_imv_out_prcorigem | B59: Pilar III | C59: Bens Imóveis - Output | D59: 2. Campo | E59: cd_imv_out_prc | F59: origem | G59: =INDEX(Auxiliar!$B$16:$B$23,MATCH(Plano_V1!H59,Auxiliar!$C$16:$C$23,0),1) -> 0. Cancelado | H59: =VLOOKUP(A59,'Aux - pivots1'!$A:$B,2,0) -> 0 | I59: =SUMIFS(Table1[Estimação (horas)],Table1[Tabela],Plano_V1!E59,Table1[Campo],Plano_V1!F59) -> 4.1 | J59: =I59/8 -> 0.5125 | K59: cd_imv_out_trz_cred_prc | L59: =J59-SUM(M59:FK59) -> 0.5125
A60: =E60&F60 -> cd_imv_out_prcref_date | B60: Pilar III | C60: Bens Imóveis - Output | D60: 2. Campo | E60: cd_imv_out_prc | F60: ref_date | G60: =INDEX(Auxiliar!$B$16:$B$23,MATCH(Plano_V1!H60,Auxiliar!$C$16:$C$23,0),1) -> 1. Concluído | H60: =VLOOKUP(A60,'Aux - pivots1'!$A:$B,2,0) -> 1 | I60: =SUMIFS(Table1[Estimação (horas)],Table1[Tabela],Plano_V1!E60,Table1[Campo],Plano_V1!F60) -> 4.1 | J60: =I60/8 -> 0.5125 | K60: cd_imv_out_trz_cred_prc | L60: =J60-SUM(M60:FK60) -> 0.5125
A61: =E61&F61 -> cd_imv_out_trz_cred_prcn.a. | B61: Pilar III | C61: Bens Imóveis - Output | D61: 1. Universo | E61: cd_imv_out_trz_cred_prc | F61: n.a. | G61: =INDEX(Auxiliar!$B$16:$B$23,MATCH(Plano_V1!H61,Auxiliar!$C$16:$C$23,0),1) -> 1. Concluído | H61: =VLOOKUP(A61,'Aux - pivots1'!$A:$B,2,0) -> 1 | I61: =SUMIFS(Table1[Estimação (horas)],Table1[Tabela],Plano_V1!E61,Table1[Campo],Plano_V1!F61) -> 8 | J61: =I61/8 -> 1 | K61: sem pendencia | L61: =J61-SUM(M61:FK61) -> 1
A62: =E62&F62 -> cd_imv_out_trz_cred_prccempresa | B62: Pilar III | C62: Bens Imóveis - Output | D62: 2. Campo | E62: cd_imv_out_trz_cred_prc | F62: cempresa | G62: =INDEX(Auxiliar!$B$16:$B$23,MATCH(Plano_V1!H62,Auxiliar!$C$16:$C$23,0),1) -> 1. Concluído | H62: =VLOOKUP(A62,'Aux - pivots1'!$A:$B,2,0) -> 1 | I62: =SUMIFS(Table1[Estimação (horas)],Table1[Tabela],Plano_V1!E62,Table1[Campo],Plano_V1!F62) -> 8.1 | J62: =I62/8 -> 1.0125 | K62: sem pendencia | L62: =J62-SUM(M62:FK62) -> 1.0125
A63: =E63&F63 -> cd_imv_out_trz_cred_prccempresp | B63: Pilar III | C63: Bens Imóveis - Output | D63: 2. Campo | E63: cd_imv_out_trz_cred_prc | F63: cempresp | G63: =INDEX(Auxiliar!$B$16:$B$23,MATCH(Plano_V1!H63,Auxiliar!$C$16:$C$23,0),1) -> 1. Concluído | H63: =VLOOKUP(A63,'Aux - pivots1'!$A:$B,2,0) -> 1 | I63: =SUMIFS(Table1[Estimação (horas)],Table1[Tabela],Plano_V1!E63,Table1[Campo],Plano_V1!F63) -> 8.1 | J63: =I63/8 -> 1.0125 | K63: sem pendencia | L63: =J63-SUM(M63:FK63) -> 1.0125
A64: =E64&F64 -> cd_imv_out_trz_cred_prcckbalcao | B64: Pilar III | C64: Bens Imóveis - Output | D64: 2. Campo | E64: cd_imv_out_trz_cred_prc | F64: ckbalcao | G64: =INDEX(Auxiliar!$B$16:$B$23,MATCH(Plano_V1!H64,Auxiliar!$C$16:$C$23,0),1) -> 1. Concluído | H64: =VLOOKUP(A64,'Aux - pivots1'!$A:$B,2,0) -> 1 | I64: =SUMIFS(Table1[Estimação (horas)],Table1[Tabela],Plano_V1!E64,Table1[Campo],Plano_V1!F64) -> 8.1 | J64: =I64/8 -> 1.0125 | K64: sem pendencia | L64: =J64-SUM(M64:FK64) -> 1.0125
A65: =E65&F65 -> cd_imv_out_trz_cred_prcckbalres | B65: Pilar III | C65: Bens Imóveis - Output | D65: 2. Campo | E65: cd_imv_out_trz_cred_prc | F65: ckbalres | G65: =INDEX(Auxiliar!$B$16:$B$23,MATCH(Plano_V1!H65,Auxiliar!$C$16:$C$23,0),1) -> 1. Concluído | H65: =VLOOKUP(A65,'Aux - pivots1'!$A:$B,2,0) -> 1 | I65: =SUMIFS(Table1[Estimação (horas)],Table1[Tabela],Plano_V1!E65,Table1[Campo],Plano_V1!F65) -> 8.1 | J65: =I65/8 -> 1.0125 | K65: sem pendencia | L65: =J65-SUM(M65:FK65) -> 1.0125
A66: =E66&F66 -> cd_imv_out_trz_cred_prcckctares | B66: Pilar III | C66: Bens Imóveis - Output | D66: 2. Campo | E66: cd_imv_out_trz_cred_prc | F66: ckctares | G66: =INDEX(Auxiliar!$B$16:$B$23,MATCH(Plano_V1!H66,Auxiliar!$C$16:$C$23,0),1) -> 1. Concluído | H66: =VLOOKUP(A66,'Aux - pivots1'!$A:$B,2,0) -> 1 | I66: =SUMIFS(Table1[Estimação (horas)],Table1[Tabela],Plano_V1!E66,Table1[Campo],Plano_V1!F66) -> 8.1 | J66: =I66/8 -> 1.0125 | K66: sem pendencia | L66: =J66-SUM(M66:FK66) -> 1.0125
A67: =E67&F67 -> cd_imv_out_trz_cred_prccknumcta | B67: Pilar III | C67: Bens Imóveis - Output | D67: 2. Campo | E67: cd_imv_out_trz_cred_prc | F67: cknumcta | G67: =INDEX(Auxiliar!$B$16:$B$23,MATCH(Plano_V1!H67,Auxiliar!$C$16:$C$23,0),1) -> 1. Concluído | H67: =VLOOKUP(A67,'Aux - pivots1'!$A:$B,2,0) -> 1 | I67: =SUMIFS(Table1[Estimação (horas)],Table1[Tabela],Plano_V1!E67,Table1[Campo],Plano_V1!F67) -> 8.1 | J67: =I67/8 -> 1.0125 | K67: sem pendencia | L67: =J67-SUM(M67:FK67) -> 1.0125
A68: =E68&F68 -> cd_imv_out_trz_cred_prcckrefresp | B68: Pilar III | C68: Bens Imóveis - Output | D68: 2. Campo | E68: cd_imv_out_trz_cred_prc | F68: ckrefresp | G68: =INDEX(Auxiliar!$B$16:$B$23,MATCH(Plano_V1!H68,Auxiliar!$C$16:$C$23,0),1) -> 1. Concluído | H68: =VLOOKUP(A68,'Aux - pivots1'!$A:$B,2,0) -> 1 | I68: =SUMIFS(Table1[Estimação (horas)],Table1[Tabela],Plano_V1!E68,Table1[Campo],Plano_V1!F68) -> 8.1 | J68: =I68/8 -> 1.0125 | K68: sem pendencia | L68: =J68-SUM(M68:FK68) -> 1.0125
A69: =E69&F69 -> cd_imv_out_trz_cred_prccod_fnld | B69: Pilar III | C69: Bens Imóveis - Output | D69: 2. Campo | E69: cd_imv_out_trz_cred_prc | F69: cod_fnld | G69: =INDEX(Auxiliar!$B$16:$B$23,MATCH(Plano_V1!H69,Auxiliar!$C$16:$C$23,0),1) -> 1. Concluído | H69: =VLOOKUP(A69,'Aux - pivots1'!$A:$B,2,0) -> 1 | I69: =SUMIFS(Table1[Estimação (horas)],Table1[Tabela],Plano_V1!E69,Table1[Campo],Plano_V1!F69) -> 8.1 | J69: =I69/8 -> 1.0125 | K69: sem pendencia | L69: =J69-SUM(M69:FK69) -> 1.0125
A70: =E70&F70 -> cd_imv_out_trz_cred_prccod_ocupacao | B70: Pilar III | C70: Bens Imóveis - Output | D70: 2. Campo | E70: cd_imv_out_trz_cred_prc | F70: cod_ocupacao | G70: =INDEX(Auxiliar!$B$16:$B$23,MATCH(Plano_V1!H70,Auxiliar!$C$16:$C$23,0),1) -> 1. Concluído | H70: =VLOOKUP(A70,'Aux - pivots1'!$A:$B,2,0) -> 1 | I70: =SUMIFS(Table1[Estimação (horas)],Table1[Tabela],Plano_V1!E70,Table1[Campo],Plano_V1!F70) -> 8.1 | J70: =I70/8 -> 1.0125 | K70: sem pendencia | L70: =J70-SUM(M70:FK70) -> 1.0125
A71: =E71&F71 -> cd_imv_out_trz_cred_prccod_prd_resp | B71: Pilar III | C71: Bens Imóveis - Output | D71: 2. Campo | E71: cd_imv_out_trz_cred_prc | F71: cod_prd_resp | G71: =INDEX(Auxiliar!$B$16:$B$23,MATCH(Plano_V1!H71,Auxiliar!$C$16:$C$23,0),1) -> 1. Concluído | H71: =VLOOKUP(A71,'Aux - pivots1'!$A:$B,2,0) -> 1 | I71: =SUMIFS(Table1[Estimação (horas)],Table1[Tabela],Plano_V1!E71,Table1[Campo],Plano_V1!F71) -> 8.1 | J71: =I71/8 -> 1.0125 | K71: sem pendencia | L71: =J71-SUM(M71:FK71) -> 1.0125
A72: =E72&F72 -> cd_imv_out_trz_cred_prccod_sit | B72: Pilar III | C72: Bens Imóveis - Output | D72: 2. Campo | E72: cd_imv_out_trz_cred_prc | F72: cod_sit | G72: =INDEX(Auxiliar!$B$16:$B$23,MATCH(Plano_V1!H72,Auxiliar!$C$16:$C$23,0),1) -> 0. Cancelado | H72: =VLOOKUP(A72,'Aux - pivots1'!$A:$B,2,0) -> 0 | I72: 0 | J72: =I72/8 -> 0 | K72: sem pendencia | L72: =J72-SUM(M72:FK72) -> 0
A73: =E73&F73 -> cd_imv_out_trz_cred_prccod_sprd_resp | B73: Pilar III | C73: Bens Imóveis - Output | D73: 2. Campo | E73: cd_imv_out_trz_cred_prc | F73: cod_sprd_resp | G73: =INDEX(Auxiliar!$B$16:$B$23,MATCH(Plano_V1!H73,Auxiliar!$C$16:$C$23,0),1) -> 1. Concluído | H73: =VLOOKUP(A73,'Aux - pivots1'!$A:$B,2,0) -> 1 | I73: =SUMIFS(Table1[Estimação (horas)],Table1[Tabela],Plano_V1!E73,Table1[Campo],Plano_V1!F73) -> 8.1 | J73: =I73/8 -> 1.0125 | K73: sem pendencia | L73: =J73-SUM(M73:FK73) -> 1.0125
A74: =E74&F74 -> cd_imv_out_trz_cred_prccomp_id_gar | B74: Pilar III | C74: Bens Imóveis - Output | D74: 2. Campo | E74: cd_imv_out_trz_cred_prc | F74: comp_id_gar | G74: =INDEX(Auxiliar!$B$16:$B$23,MATCH(Plano_V1!H74,Auxiliar!$C$16:$C$23,0),1) -> 1. Concluído | H74: =VLOOKUP(A74,'Aux - pivots1'!$A:$B,2,0) -> 1 | I74: =SUMIFS(Table1[Estimação (horas)],Table1[Tabela],Plano_V1!E74,Table1[Campo],Plano_V1!F74) -> 8.1 | J74: =I74/8 -> 1.0125 | K74: sem pendencia | L74: =J74-SUM(M74:FK74) -> 1.0125
A75: =E75&F75 -> cd_imv_out_trz_cred_prcdata_fim | B75: Pilar III | C75: Bens Imóveis - Output | D75: 2. Campo | E75: cd_imv_out_trz_cred_prc | F75: data_fim | G75: =INDEX(Auxiliar!$B$16:$B$23,MATCH(Plano_V1!H75,Auxiliar!$C$16:$C$23,0),1) -> 1. Concluído | H75: =VLOOKUP(A75,'Aux - pivots1'!$A:$B,2,0) -> 1 | I75: =SUMIFS(Table1[Estimação (horas)],Table1[Tabela],Plano_V1!E75,Table1[Campo],Plano_V1!F75) -> 8.1 | J75: =I75/8 -> 1.0125 | K75: sem pendencia | L75: =J75-SUM(M75:FK75) -> 1.0125
A76: =E76&F76 -> cd_imv_out_trz_cred_prcdata_inicio | B76: Pilar III | C76: Bens Imóveis - Output | D76: 2. Campo | E76: cd_imv_out_trz_cred_prc | F76: data_inicio | G76: =INDEX(Auxiliar!$B$16:$B$23,MATCH(Plano_V1!H76,Auxiliar!$C$16:$C$23,0),1) -> 1. Concluído | H76: =VLOOKUP(A76,'Aux - pivots1'!$A:$B,2,0) -> 1 | I76: =SUMIFS(Table1[Estimação (horas)],Table1[Tabela],Plano_V1!E76,Table1[Campo],Plano_V1!F76) -> 8.1 | J76: =I76/8 -> 1.0125 | K76: sem pendencia | L76: =J76-SUM(M76:FK76) -> 1.0125
A77: =E77&F77 -> cd_imv_out_trz_cred_prcdata_vcmt | B77: Pilar III | C77: Bens Imóveis - Output | D77: 2. Campo | E77: cd_imv_out_trz_cred_prc | F77: data_vcmt | G77: =INDEX(Auxiliar!$B$16:$B$23,MATCH(Plano_V1!H77,Auxiliar!$C$16:$C$23,0),1) -> 1. Concluído | H77: =VLOOKUP(A77,'Aux - pivots1'!$A:$B,2,0) -> 1 | I77: =SUMIFS(Table1[Estimação (horas)],Table1[Tabela],Plano_V1!E77,Table1[Campo],Plano_V1!F77) -> 8.1 | J77: =I77/8 -> 1.0125 | K77: sem pendencia | L77: =J77-SUM(M77:FK77) -> 1.0125
A78: =E78&F78 -> cd_imv_out_trz_cred_prcidetgar | B78: Pilar III | C78: Bens Imóveis - Output | D78: 2. Campo | E78: cd_imv_out_trz_cred_prc | F78: idetgar | G78: =INDEX(Auxiliar!$B$16:$B$23,MATCH(Plano_V1!H78,Auxiliar!$C$16:$C$23,0),1) -> 0. Cancelado | H78: =VLOOKUP(A78,'Aux - pivots1'!$A:$B,2,0) -> 0 | I78: 0 | J78: =I78/8 -> 0 | K78: sem pendencia | L78: =J78-SUM(M78:FK78) -> 0
A79: =E79&F79 -> cd_imv_out_trz_cred_prcnum_prop | B79: Pilar III | C79: Bens Imóveis - Output | D79: 2. Campo | E79: cd_imv_out_trz_cred_prc | F79: num_prop | G79: =INDEX(Auxiliar!$B$16:$B$23,MATCH(Plano_V1!H79,Auxiliar!$C$16:$C$23,0),1) -> 0. Cancelado | H79: =VLOOKUP(A79,'Aux - pivots1'!$A:$B,2,0) -> 0 | I79: 0 | J79: =I79/8 -> 0 | K79: sem pendencia | L79: =J79-SUM(M79:FK79) -> 0
A80: =E80&F80 -> cd_imv_out_trz_cred_prcorigem | B80: Pilar III | C80: Bens Imóveis - Output | D80: 2. Campo | E80: cd_imv_out_trz_cred_prc | F80: origem | G80: =INDEX(Auxiliar!$B$16:$B$23,MATCH(Plano_V1!H80,Auxiliar!$C$16:$C$23,0),1) -> 1. Concluído | H80: =VLOOKUP(A80,'Aux - pivots1'!$A:$B,2,0) -> 1 | I80: =SUMIFS(Table1[Estimação (horas)],Table1[Tabela],Plano_V1!E80,Table1[Campo],Plano_V1!F80) -> 4.1 | J80: =I80/8 -> 0.5125 | K80: sem pendencia | L80: =J80-SUM(M80:FK80) -> 0.5125
A81: =E81&F81 -> cd_imv_out_trz_cred_prcref_date | B81: Pilar III | C81: Bens Imóveis - Output | D81: 2. Campo | E81: cd_imv_out_trz_cred_prc | F81: ref_date | G81: =INDEX(Auxiliar!$B$16:$B$23,MATCH(Plano_V1!H81,Auxiliar!$C$16:$C$23,0),1) -> 1. Concluído | H81: =VLOOKUP(A81,'Aux - pivots1'!$A:$B,2,0) -> 1 | I81: =SUMIFS(Table1[Estimação (horas)],Table1[Tabela],Plano_V1!E81,Table1[Campo],Plano_V1!F81) -> 4.1 | J81: =I81/8 -> 0.5125 | K81: sem pendencia | L81: =J81-SUM(M81:FK81) -> 0.5125
A82: =E82&F82 -> cd_imv_out_trz_prc_bens_imvn.a. | B82: Pilar III | C82: Bens Imóveis - Output | D82: 1. Universo | E82: cd_imv_out_trz_prc_bens_imv | F82: n.a. | G82: =INDEX(Auxiliar!$B$16:$B$23,MATCH(Plano_V1!H82,Auxiliar!$C$16:$C$23,0),1) -> 1. Concluído | H82: =VLOOKUP(A82,'Aux - pivots1'!$A:$B,2,0) -> 1 | I82: =SUMIFS(Table1[Estimação (horas)],Table1[Tabela],Plano_V1!E82,Table1[Campo],Plano_V1!F82) -> 8 | J82: =I82/8 -> 1 | K82: cd_imv_out_trz_cred_prc | L82: =J82-SUM(M82:FK82) -> 1
A83: =E83&F83 -> cd_imv_out_trz_prc_bens_imvcempbem | B83: Pilar III | C83: Bens Imóveis - Output | D83: 2. Campo | E83: cd_imv_out_trz_prc_bens_imv | F83: cempbem | G83: =INDEX(Auxiliar!$B$16:$B$23,MATCH(Plano_V1!H83,Auxiliar!$C$16:$C$23,0),1) -> 1. Concluído | H83: =VLOOKUP(A83,'Aux - pivots1'!$A:$B,2,0) -> 1 | I83: =SUMIFS(Table1[Estimação (horas)],Table1[Tabela],Plano_V1!E83,Table1[Campo],Plano_V1!F83) -> 4.1 | J83: =I83/8 -> 0.5125 | K83: cd_imv_out_trz_cred_prc | L83: =J83-SUM(M83:FK83) -> 0.5125
A84: =E84&F84 -> cd_imv_out_trz_prc_bens_imvcempresa | B84: Pilar III | C84: Bens Imóveis - Output | D84: 2. Campo | E84: cd_imv_out_trz_prc_bens_imv | F84: cempresa | G84: =INDEX(Auxiliar!$B$16:$B$23,MATCH(Plano_V1!H84,Auxiliar!$C$16:$C$23,0),1) -> 1. Concluído | H84: =VLOOKUP(A84,'Aux - pivots1'!$A:$B,2,0) -> 1 | I84: =SUMIFS(Table1[Estimação (horas)],Table1[Tabela],Plano_V1!E84,Table1[Campo],Plano_V1!F84) -> 8.1 | J84: =I84/8 -> 1.0125 | K84: cd_imv_out_trz_cred_prc | L84: =J84-SUM(M84:FK84) -> 1.0125
A85: =E85&F85 -> cd_imv_out_trz_prc_bens_imvckbalbem | B85: Pilar III | C85: Bens Imóveis - Output | D85: 2. Campo | E85: cd_imv_out_trz_prc_bens_imv | F85: ckbalbem | G85: =INDEX(Auxiliar!$B$16:$B$23,MATCH(Plano_V1!H85,Auxiliar!$C$16:$C$23,0),1) -> 1. Concluído | H85: =VLOOKUP(A85,'Aux - pivots1'!$A:$B,2,0) -> 1 | I85: =SUMIFS(Table1[Estimação (horas)],Table1[Tabela],Plano_V1!E85,Table1[Campo],Plano_V1!F85) -> 8.1 | J85: =I85/8 -> 1.0125 | K85: cd_imv_out_trz_cred_prc | L85: =J85-SUM(M85:FK85) -> 1.0125
A86: =E86&F86 -> cd_imv_out_trz_prc_bens_imvckbalcao | B86: Pilar III | C86: Bens Imóveis - Output | D86: 2. Campo | E86: cd_imv_out_trz_prc_bens_imv | F86: ckbalcao | G86: =INDEX(Auxiliar!$B$16:$B$23,MATCH(Plano_V1!H86,Auxiliar!$C$16:$C$23,0),1) -> 1. Concluído | H86: =VLOOKUP(A86,'Aux - pivots1'!$A:$B,2,0) -> 1 | I86: =SUMIFS(Table1[Estimação (horas)],Table1[Tabela],Plano_V1!E86,Table1[Campo],Plano_V1!F86) -> 8.1 | J86: =I86/8 -> 1.0125 | K86: cd_imv_out_trz_cred_prc | L86: =J86-SUM(M86:FK86) -> 1.0125
A87: =E87&F87 -> cd_imv_out_trz_prc_bens_imvckctabem | B87: Pilar III | C87: Bens Imóveis - Output | D87: 2. Campo | E87: cd_imv_out_trz_prc_bens_imv | F87: ckctabem | G87: =INDEX(Auxiliar!$B$16:$B$23,MATCH(Plano_V1!H87,Auxiliar!$C$16:$C$23,0),1) -> 1. Concluído | H87: =VLOOKUP(A87,'Aux - pivots1'!$A:$B,2,0) -> 1 | I87: =SUMIFS(Table1[Estimação (horas)],Table1[Tabela],Plano_V1!E87,Table1[Campo],Plano_V1!F87) -> 8.1 | J87: =I87/8 -> 1.0125 | K87: cd_imv_out_trz_cred_prc | L87: =J87-SUM(M87:FK87) -> 1.0125
A88: =E88&F88 -> cd_imv_out_trz_prc_bens_imvcknumcta | B88: Pilar III | C88: Bens Imóveis - Output | D88: 2. Campo | E88: cd_imv_out_trz_prc_bens_imv | F88: cknumcta | G88: =INDEX(Auxiliar!$B$16:$B$23,MATCH(Plano_V1!H88,Auxiliar!$C$16:$C$23,0),1) -> 1. Concluído | H88: =VLOOKUP(A88,'Aux - pivots1'!$A:$B,2,0) -> 1 | I88: =SUMIFS(Table1[Estimação (horas)],Table1[Tabela],Plano_V1!E88,Table1[Campo],Plano_V1!F88) -> 8.1 | J88: =I88/8 -> 1.0125 | K88: cd_imv_out_trz_cred_prc | L88: =J88-SUM(M88:FK88) -> 1.0125
A89: =E89&F89 -> cd_imv_out_trz_prc_bens_imvckrefbem | B89: Pilar III | C89: Bens Imóveis - Output | D89: 2. Campo | E89: cd_imv_out_trz_prc_bens_imv | F89: ckrefbem | G89: =INDEX(Auxiliar!$B$16:$B$23,MATCH(Plano_V1!H89,Auxiliar!$C$16:$C$23,0),1) -> 1. Concluído | H89: =VLOOKUP(A89,'Aux - pivots1'!$A:$B,2,0) -> 1 | I89: =SUMIFS(Table1[Estimação (horas)],Table1[Tabela],Plano_V1!E89,Table1[Campo],Plano_V1!F89) -> 4.1 | J89: =I89/8 -> 0.5125 | K89: cd_imv_out_trz_cred_prc | L89: =J89-SUM(M89:FK89) -> 0.5125
A90: =E90&F90 -> cd_imv_out_trz_prc_bens_imvcomp_id_gar | B90: Pilar III | C90: Bens Imóveis - Output | D90: 2. Campo | E90: cd_imv_out_trz_prc_bens_imv | F90: comp_id_gar | G90: =INDEX(Auxiliar!$B$16:$B$23,MATCH(Plano_V1!H90,Auxiliar!$C$16:$C$23,0),1) -> 1. Concluído | H90: =VLOOKUP(A90,'Aux - pivots1'!$A:$B,2,0) -> 1 | I90: =SUMIFS(Table1[Estimação (horas)],Table1[Tabela],Plano_V1!E90,Table1[Campo],Plano_V1!F90) -> 8.1 | J90: =I90/8 -> 1.0125 | K90: cd_imv_out_trz_cred_prc | L90: =J90-SUM(M90:FK90) -> 1.0125
A91: =E91&F91 -> cd_imv_out_trz_prc_bens_imvdata_assc | B91: Pilar III | C91: Bens Imóveis - Output | D91: 2. Campo | E91: cd_imv_out_trz_prc_bens_imv | F91: data_assc | G91: =INDEX(Auxiliar!$B$16:$B$23,MATCH(Plano_V1!H91,Auxiliar!$C$16:$C$23,0),1) -> 0. Cancelado | H91: =VLOOKUP(A91,'Aux - pivots1'!$A:$B,2,0) -> 0 | I91: 0 | J91: =I91/8 -> 0 | K91: cd_imv_out_trz_cred_prc | L91: =J91-SUM(M91:FK91) -> 0
A92: =E92&F92 -> cd_imv_out_trz_prc_bens_imvflg_adj | B92: Pilar III | C92: Bens Imóveis - Output | D92: 2. Campo | E92: cd_imv_out_trz_prc_bens_imv | F92: flg_adj | G92: =INDEX(Auxiliar!$B$16:$B$23,MATCH(Plano_V1!H92,Auxiliar!$C$16:$C$23,0),1) -> 1. Concluído | H92: =VLOOKUP(A92,'Aux - pivots1'!$A:$B,2,0) -> 1 | I92: =SUMIFS(Table1[Estimação (horas)],Table1[Tabela],Plano_V1!E92,Table1[Campo],Plano_V1!F92) -> 4.1 | J92: =I92/8 -> 0.5125 | K92: cd_imv_out_trz_cred_prc | L92: =J92-SUM(M92:FK92) -> 0.5125
A93: =E93&F93 -> cd_imv_out_trz_prc_bens_imvflg_col | B93: Pilar III | C93: Bens Imóveis - Output | D93: 2. Campo | E93: cd_imv_out_trz_prc_bens_imv | F93: flg_col | G93: =INDEX(Auxiliar!$B$16:$B$23,MATCH(Plano_V1!H93,Auxiliar!$C$16:$C$23,0),1) -> 1. Concluído | H93: =VLOOKUP(A93,'Aux - pivots1'!$A:$B,2,0) -> 1 | I93: =SUMIFS(Table1[Estimação (horas)],Table1[Tabela],Plano_V1!E93,Table1[Campo],Plano_V1!F93) -> 4.1 | J93: =I93/8 -> 0.5125 | K93: cd_imv_out_trz_cred_prc | L93: =J93-SUM(M93:FK93) -> 0.5125
A94: =E94&F94 -> cd_imv_out_trz_prc_bens_imvflg_fin | B94: Pilar III | C94: Bens Imóveis - Output | D94: 2. Campo | E94: cd_imv_out_trz_prc_bens_imv | F94: flg_fin | G94: =INDEX(Auxiliar!$B$16:$B$23,MATCH(Plano_V1!H94,Auxiliar!$C$16:$C$23,0),1) -> 1. Concluído | H94: =VLOOKUP(A94,'Aux - pivots1'!$A:$B,2,0) -> 1 | I94: =SUMIFS(Table1[Estimação (horas)],Table1[Tabela],Plano_V1!E94,Table1[Campo],Plano_V1!F94) -> 4.1 | J94: =I94/8 -> 0.5125 | K94: cd_imv_out_trz_cred_prc | L94: =J94-SUM(M94:FK94) -> 0.5125
A95: =E95&F95 -> cd_imv_out_trz_prc_bens_imvflg_pro | B95: Pilar III | C95: Bens Imóveis - Output | D95: 2. Campo | E95: cd_imv_out_trz_prc_bens_imv | F95: flg_pro | G95: =INDEX(Auxiliar!$B$16:$B$23,MATCH(Plano_V1!H95,Auxiliar!$C$16:$C$23,0),1) -> 1. Concluído | H95: =VLOOKUP(A95,'Aux - pivots1'!$A:$B,2,0) -> 1 | I95: =SUMIFS(Table1[Estimação (horas)],Table1[Tabela],Plano_V1!E95,Table1[Campo],Plano_V1!F95) -> 4.1 | J95: =I95/8 -> 0.5125 | K95: cd_imv_out_trz_cred_prc | L95: =J95-SUM(M95:FK95) -> 0.5125
A96: =E96&F96 -> cd_imv_out_trz_prc_bens_imvorigem | B96: Pilar III | C96: Bens Imóveis - Output | D96: 2. Campo | E96: cd_imv_out_trz_prc_bens_imv | F96: origem | G96: =INDEX(Auxiliar!$B$16:$B$23,MATCH(Plano_V1!H96,Auxiliar!$C$16:$C$23,0),1) -> 1. Concluído | H96: =VLOOKUP(A96,'Aux - pivots1'!$A:$B,2,0) -> 1 | I96: =SUMIFS(Table1[Estimação (horas)],Table1[Tabela],Plano_V1!E96,Table1[Campo],Plano_V1!F96) -> 4.1 | J96: =I96/8 -> 0.5125 | K96: cd_imv_out_trz_cred_prc | L96: =J96-SUM(M96:FK96) -> 0.5125
A97: =E97&F97 -> cd_imv_out_trz_prc_bens_imvref_date | B97: Pilar III | C97: Bens Imóveis - Output | D97: 2. Campo | E97: cd_imv_out_trz_prc_bens_imv | F97: ref_date | G97: =INDEX(Auxiliar!$B$16:$B$23,MATCH(Plano_V1!H97,Auxiliar!$C$16:$C$23,0),1) -> 1. Concluído | H97: =VLOOKUP(A97,'Aux - pivots1'!$A:$B,2,0) -> 1 | I97: =SUMIFS(Table1[Estimação (horas)],Table1[Tabela],Plano_V1!E97,Table1[Campo],Plano_V1!F97) -> 4.1 | J97: =I97/8 -> 0.5125 | K97: cd_imv_out_trz_cred_prc | L97: =J97-SUM(M97:FK97) -> 0.5125
A98: =E98&F98 -> cd_imv_out_bensn.a. | B98: Pilar III | C98: Bens Imóveis - Output | D98: 1. Universo | E98: cd_imv_out_bens | F98: n.a. | G98: =INDEX(Auxiliar!$B$16:$B$23,MATCH(Plano_V1!H98,Auxiliar!$C$16:$C$23,0),1) -> 1. Concluído | H98: =VLOOKUP(A98,'Aux - pivots1'!$A:$B,2,0) -> 1 | I98: =SUMIFS(Table1[Estimação (horas)],Table1[Tabela],Plano_V1!E98,Table1[Campo],Plano_V1!F98) -> 8 | J98: =I98/8 -> 1 | K98: cd_imv_out_trz_prc_bens_imv ; cd_imv_out_prc ; cd_imv_out_trz_cred_prc | L98: =J98-SUM(M98:FK98) -> 1
A99: =E99&F99 -> cd_imv_out_bensano_construcao | B99: Pilar III | C99: Bens Imóveis - Output | D99: 2. Campo | E99: cd_imv_out_bens | F99: ano_construcao | G99: =INDEX(Auxiliar!$B$16:$B$23,MATCH(Plano_V1!H99,Auxiliar!$C$16:$C$23,0),1) -> 1. Concluído | H99: =VLOOKUP(A99,'Aux - pivots1'!$A:$B,2,0) -> 1 | I99: 0 | J99: =I99/8 -> 0 | K99: cd_imv_out_trz_prc_bens_imv ; cd_imv_out_prc ; cd_imv_out_trz_cred_prc | L99: =J99-SUM(M99:FK99) -> 0
A100: =E100&F100 -> cd_imv_out_bensarea_util | B100: Pilar III | C100: Bens Imóveis - Output | D100: 2. Campo | E100: cd_imv_out_bens | F100: area_util | G100: =INDEX(Auxiliar!$B$16:$B$23,MATCH(Plano_V1!H100,Auxiliar!$C$16:$C$23,0),1) -> 1. Concluído | H100: =VLOOKUP(A100,'Aux - pivots1'!$A:$B,2,0) -> 1 | I100: =SUMIFS(Table1[Estimação (horas)],Table1[Tabela],Plano_V1!E100,Table1[Campo],Plano_V1!F100) -> 8.1 | J100: =I100/8 -> 1.0125 | K100: cd_imv_out_trz_prc_bens_imv ; cd_imv_out_prc ; cd_imv_out_trz_cred_prc | L100: =J100-SUM(M100:FK100) -> 1.0125
A101: =E101&F101 -> cd_imv_out_benscempbem | B101: Pilar III | C101: Bens Imóveis - Output | D101: 2. Campo | E101: cd_imv_out_bens | F101: cempbem | G101: =INDEX(Auxiliar!$B$16:$B$23,MATCH(Plano_V1!H101,Auxiliar!$C$16:$C$23,0),1) -> 1. Concluído | H101: =VLOOKUP(A101,'Aux - pivots1'!$A:$B,2,0) -> 1 | I101: =SUMIFS(Table1[Estimação (horas)],Table1[Tabela],Plano_V1!E101,Table1[Campo],Plano_V1!F101) -> 4.1 | J101: =I101/8 -> 0.5125 | K101: cd_imv_out_trz_prc_bens_imv ; cd_imv_out_prc ; cd_imv_out_trz_cred_prc | L101: =J101-SUM(M101:FK101) -> 0.5125
A102: =E102&F102 -> cd_imv_out_bensckbalbem | B102: Pilar III | C102: Bens Imóveis - Output | D102: 2. Campo | E102: cd_imv_out_bens | F102: ckbalbem | G102: =INDEX(Auxiliar!$B$16:$B$23,MATCH(Plano_V1!H102,Auxiliar!$C$16:$C$23,0),1) -> 1. Concluído | H102: =VLOOKUP(A102,'Aux - pivots1'!$A:$B,2,0) -> 1 | I102: =SUMIFS(Table1[Estimação (horas)],Table1[Tabela],Plano_V1!E102,Table1[Campo],Plano_V1!F102) -> 4.1 | J102: =I102/8 -> 0.5125 | K102: cd_imv_out_trz_prc_bens_imv ; cd_imv_out_prc ; cd_imv_out_trz_cred_prc | L102: =J102-SUM(M102:FK102) -> 0.5125
A103: =E103&F103 -> cd_imv_out_bensckctabem | B103: Pilar III | C103: Bens Imóveis - Output | D103: 2. Campo | E103: cd_imv_out_bens | F103: ckctabem | G103: =INDEX(Auxiliar!$B$16:$B$23,MATCH(Plano_V1!H103,Auxiliar!$C$16:$C$23,0),1) -> 1. Concluído | H103: =VLOOKUP(A103,'Aux - pivots1'!$A:$B,2,0) -> 1 | I103: =SUMIFS(Table1[Estimação (horas)],Table1[Tabela],Plano_V1!E103,Table1[Campo],Plano_V1!F103) -> 4.1 | J103: =I103/8 -> 0.5125 | K103: cd_imv_out_trz_prc_bens_imv ; cd_imv_out_prc ; cd_imv_out_trz_cred_prc | L103: =J103-SUM(M103:FK103) -> 0.5125
A104: =E104&F104 -> cd_imv_out_bensckrefbem | B104: Pilar III | C104: Bens Imóveis - Output | D104: 2. Campo | E104: cd_imv_out_bens | F104: ckrefbem | G104: =INDEX(Auxiliar!$B$16:$B$23,MATCH(Plano_V1!H104,Auxiliar!$C$16:$C$23,0),1) -> 1. Concluído | H104: =VLOOKUP(A104,'Aux - pivots1'!$A:$B,2,0) -> 1 | I104: =SUMIFS(Table1[Estimação (horas)],Table1[Tabela],Plano_V1!E104,Table1[Campo],Plano_V1!F104) -> 4.1 | J104: =I104/8 -> 0.5125 | K104: cd_imv_out_trz_prc_bens_imv ; cd_imv_out_prc ; cd_imv_out_trz_cred_prc | L104: =J104-SUM(M104:FK104) -> 0.5125
A105: =E105&F105 -> cd_imv_out_benscod_art_matr | B105: Pilar III | C105: Bens Imóveis - Output | D105: 2. Campo | E105: cd_imv_out_bens | F105: cod_art_matr | G105: =INDEX(Auxiliar!$B$16:$B$23,MATCH(Plano_V1!H105,Auxiliar!$C$16:$C$23,0),1) -> 1. Concluído | H105: =VLOOKUP(A105,'Aux - pivots1'!$A:$B,2,0) -> 1 | I105: =SUMIFS(Table1[Estimação (horas)],Table1[Tabela],Plano_V1!E105,Table1[Campo],Plano_V1!F105) -> 4.1 | J105: =I105/8 -> 0.5125 | K105: cd_imv_out_trz_prc_bens_imv ; cd_imv_out_prc ; cd_imv_out_trz_cred_prc | L105: =J105-SUM(M105:FK105) -> 0.5125
A106: =E106&F106 -> cd_imv_out_benscod_avl | B106: Pilar III | C106: Bens Imóveis - Output | D106: 2. Campo | E106: cd_imv_out_bens | F106: cod_avl | G106: =INDEX(Auxiliar!$B$16:$B$23,MATCH(Plano_V1!H106,Auxiliar!$C$16:$C$23,0),1) -> 1. Concluído | H106: =VLOOKUP(A106,'Aux - pivots1'!$A:$B,2,0) -> 1 | I106: =SUMIFS(Table1[Estimação (horas)],Table1[Tabela],Plano_V1!E106,Table1[Campo],Plano_V1!F106) -> 4.1 | J106: =I106/8 -> 0.5125 | K106: cd_imv_out_trz_prc_bens_imv ; cd_imv_out_prc ; cd_imv_out_trz_cred_prc | L106: =J106-SUM(M106:FK106) -> 0.5125
A107: =E107&F107 -> cd_imv_out_benscod_bem | B107: Pilar III | C107: Bens Imóveis - Output | D107: 2. Campo | E107: cd_imv_out_bens | F107: cod_bem | G107: =INDEX(Auxiliar!$B$16:$B$23,MATCH(Plano_V1!H107,Auxiliar!$C$16:$C$23,0),1) -> 0. Cancelado | H107: =VLOOKUP(A107,'Aux - pivots1'!$A:$B,2,0) -> 0 | I107: 0 | J107: =I107/8 -> 0 | K107: cd_imv_out_trz_prc_bens_imv ; cd_imv_out_prc ; cd_imv_out_trz_cred_prc | L107: =J107-SUM(M107:FK107) -> 0
A108: =E108&F108 -> cd_imv_out_benscod_disconf | B108: Pilar III | C108: Bens Imóveis - Output | D108: 2. Campo | E108: cd_imv_out_bens | F108: cod_disconf | G108: =INDEX(Auxiliar!$B$16:$B$23,MATCH(Plano_V1!H108,Auxiliar!$C$16:$C$23,0),1) -> 1. Concluído | H108: =VLOOKUP(A108,'Aux - pivots1'!$A:$B,2,0) -> 1 | I108: =SUMIFS(Table1[Estimação (horas)],Table1[Tabela],Plano_V1!E108,Table1[Campo],Plano_V1!F108) -> 4.1 | J108: =I108/8 -> 0.5125 | K108: cd_imv_out_trz_prc_bens_imv ; cd_imv_out_prc ; cd_imv_out_trz_cred_prc | L108: =J108-SUM(M108:FK108) -> 0.5125
A109: =E109&F109 -> cd_imv_out_benscod_fin_bem | B109: Pilar III | C109: Bens Imóveis - Output | D109: 2. Campo | E109: cd_imv_out_bens | F109: cod_fin_bem | G109: =INDEX(Auxiliar!$B$16:$B$23,MATCH(Plano_V1!H109,Auxiliar!$C$16:$C$23,0),1) -> 1. Concluído | H109: =VLOOKUP(A109,'Aux - pivots1'!$A:$B,2,0) -> 1 | I109: =SUMIFS(Table1[Estimação (horas)],Table1[Tabela],Plano_V1!E109,Table1[Campo],Plano_V1!F109) -> 4.1 | J109: =I109/8 -> 0.5125 | K109: cd_imv_out_trz_prc_bens_imv ; cd_imv_out_prc ; cd_imv_out_trz_cred_prc | L109: =J109-SUM(M109:FK109) -> 0.5125
...

Sheet 1. Status Resumo
B6: Sumário Executivo |16 de Setembro a 27 de setembro
B8: 1. Foram realizadas reuniões de esclarecimento relativas à informação proveniente de Gestão de Empreendimentos, tendo sido as especificações dos campos esclarecidos sido enviados para implementação de tecnologia. Concluiram-se as simulações de 2 tabelas do MBI em inglês. Atualmente, encontram-se fechadas 4 tabelas, totalizando 77% de campos concluídos no Modelo de Bens Imóveis. 2. No âmbito do Modelo Verde, foram realizadas várias reuniões que permitiram fechar re-especificações, que neste momento se encontram em validação ou em implementação do lado do IT. 3. Foram concluidos os testes às tabelas de inputs corporativos.
B22: 1. Modelo de Bens Imóveis | G22: Bens Imóveis - Input | H22: Bens Imóveis - Output
C25: Resumo | G25: Detalhe por Tabela | P25: Status (campos) | T25: 45551 | U25: =T25+11 -> 45562 | V25: ∆ | X25: Highlights
P26: 0. Cancelado | T26: =COUNTIFS('2. Status Detalhe Campos'!$H$7:$H$608,'1. Status Resumo'!$P26,'2. Status Detalhe Campos'!$C$7:$C$608,'1. Status Resumo'!$G$22,'2. Status Detalhe Campos'!$D$7:$D$608,"2. Campo")+COUNTIFS('2. Status Detalhe Campos'!$H$7:$H$608,'1. Status Resumo'!$P26,'2. Status Detalhe Campos'!$C$7:$C$608,'1. Status Resumo'!$H$22,'2. Status Detalhe Campos'!$D$7:$D$608,"2. Campo") -> 10 | U26: =COUNTIFS('2. Status Detalhe Campos'!$G$7:$G$608,'1. Status Resumo'!$P26,'2. Status Detalhe Campos'!$C$7:$C$608,'1. Status Resumo'!$G$22,'2. Status Detalhe Campos'!$D$7:$D$608,"2. Campo")+COUNTIFS('2. Status Detalhe Campos'!$G$7:$G$608,'1. Status Resumo'!$P26,'2. Status Detalhe Campos'!$C$7:$C$608,'1. Status Resumo'!$H$22,'2. Status Detalhe Campos'!$D$7:$D$608,"2. Campo") -> 10 | V26: =U26-T26 -> 0 | X26: 1. Realizaram-se reuniões de esclarecimento dos ficheiros da OCR da aplicação de Gestão de Empreendimentos de forma a compreender o Modelo de Dados e garantir coerência na informação. 2. A equipa enviou a especificação dos campos esclarecidos da tabela de certificados energéticos para implementação do IT. 3. Atualmente, existem apenas temas de certificados, 4 tabelas concluídas no Modelo de Bens Imóveis e 77% dos campos fechados, com 15% dos campos em Implementação e 3 campos Em Validação EF. 4. Continuação das simulações do MBI em inglês. Concluíram-se as simulações de 2 tabelas: PROCESS e RESPONSIBILITY_PROCESS_REL.
P27: 1. Concluído | T27: =COUNTIFS('2. Status Detalhe Campos'!$H$7:$H$608,'1. Status Resumo'!$P27,'2. Status Detalhe Campos'!$C$7:$C$608,'1. Status Resumo'!$G$22,'2. Status Detalhe Campos'!$D$7:$D$608,"2. Campo")+COUNTIFS('2. Status Detalhe Campos'!$H$7:$H$608,'1. Status Resumo'!$P27,'2. Status Detalhe Campos'!$C$7:$C$608,'1. Status Resumo'!$H$22,'2. Status Detalhe Campos'!$D$7:$D$608,"2. Campo") -> 132 | U27: =COUNTIFS('2. Status Detalhe Campos'!$G$7:$G$608,'1. Status Resumo'!$P27,'2. Status Detalhe Campos'!$C$7:$C$608,'1. Status Resumo'!$G$22,'2. Status Detalhe Campos'!$D$7:$D$608,"2. Campo")+COUNTIFS('2. Status Detalhe Campos'!$G$7:$G$608,'1. Status Resumo'!$P27,'2. Status Detalhe Campos'!$C$7:$C$608,'1. Status Resumo'!$H$22,'2. Status Detalhe Campos'!$D$7:$D$608,"2. Campo") -> 124 | V27: =U27-T27 -> -8
P28: 2. Em Teste | T28: =COUNTIFS('2. Status Detalhe Campos'!$H$7:$H$608,'1. Status Resumo'!$P28,'2. Status Detalhe Campos'!$C$7:$C$608,'1. Status Resumo'!$G$22,'2. Status Detalhe Campos'!$D$7:$D$608,"2. Campo")+COUNTIFS('2. Status Detalhe Campos'!$H$7:$H$608,'1. Status Resumo'!$P28,'2. Status Detalhe Campos'!$C$7:$C$608,'1. Status Resumo'!$H$22,'2. Status Detalhe Campos'!$D$7:$D$608,"2. Campo") -> 0 | U28: =COUNTIFS('2. Status Detalhe Campos'!$G$7:$G$608,'1. Status Resumo'!$P28,'2. Status Detalhe Campos'!$C$7:$C$608,'1. Status Resumo'!$G$22,'2. Status Detalhe Campos'!$D$7:$D$608,"2. Campo")+COUNTIFS('2. Status Detalhe Campos'!$G$7:$G$608,'1. Status Resumo'!$P28,'2. Status Detalhe Campos'!$C$7:$C$608,'1. Status Resumo'!$H$22,'2. Status Detalhe Campos'!$D$7:$D$608,"2. Campo") -> 0 | V28: =U28-T28 -> 0
D29: ="# "&U34 -> # 161 | P29: 3. Pendente de outros desenvolvimentos | T29: =COUNTIFS('2. Status Detalhe Campos'!$H$7:$H$608,'1. Status Resumo'!$P29,'2. Status Detalhe Campos'!$C$7:$C$608,'1. Status Resumo'!$G$22,'2. Status Detalhe Campos'!$D$7:$D$608,"2. Campo")+COUNTIFS('2. Status Detalhe Campos'!$H$7:$H$608,'1. Status Resumo'!$P29,'2. Status Detalhe Campos'!$C$7:$C$608,'1. Status Resumo'!$H$22,'2. Status Detalhe Campos'!$D$7:$D$608,"2. Campo") -> 0 | U29: =COUNTIFS('2. Status Detalhe Campos'!$G$7:$G$608,'1. Status Resumo'!$P29,'2. Status Detalhe Campos'!$C$7:$C$608,'1. Status Resumo'!$G$22,'2. Status Detalhe Campos'!$D$7:$D$608,"2. Campo")+COUNTIFS('2. Status Detalhe Campos'!$G$7:$G$608,'1. Status Resumo'!$P29,'2. Status Detalhe Campos'!$C$7:$C$608,'1. Status Resumo'!$H$22,'2. Status Detalhe Campos'!$D$7:$D$608,"2. Campo") -> 0 | V29: =U29-T29 -> 0
P30: 4. Validação EF | T30: =COUNTIFS('2. Status Detalhe Campos'!$H$7:$H$608,'1. Status Resumo'!$P30,'2. Status Detalhe Campos'!$C$7:$C$608,'1. Status Resumo'!$G$22,'2. Status Detalhe Campos'!$D$7:$D$608,"2. Campo")+COUNTIFS('2. Status Detalhe Campos'!$H$7:$H$608,'1. Status Resumo'!$P30,'2. Status Detalhe Campos'!$C$7:$C$608,'1. Status Resumo'!$H$22,'2. Status Detalhe Campos'!$D$7:$D$608,"2. Campo") -> 7 | U30: =COUNTIFS('2. Status Detalhe Campos'!$G$7:$G$608,'1. Status Resumo'!$P30,'2. Status Detalhe Campos'!$C$7:$C$608,'1. Status Resumo'!$G$22,'2. Status Detalhe Campos'!$D$7:$D$608,"2. Campo")+COUNTIFS('2. Status Detalhe Campos'!$G$7:$G$608,'1. Status Resumo'!$P30,'2. Status Detalhe Campos'!$C$7:$C$608,'1. Status Resumo'!$H$22,'2. Status Detalhe Campos'!$D$7:$D$608,"2. Campo") -> 3 | V30: =U30-T30 -> -4
P31: 5. Em Correção | R31: (incidências) | T31: =COUNTIFS('2. Status Detalhe Campos'!$H$7:$H$608,'1. Status Resumo'!$P31,'2. Status Detalhe Campos'!$C$7:$C$608,'1. Status Resumo'!$G$22,'2. Status Detalhe Campos'!$D$7:$D$608,"2. Campo")+COUNTIFS('2. Status Detalhe Campos'!$H$7:$H$608,'1. Status Resumo'!$P31,'2. Status Detalhe Campos'!$C$7:$C$608,'1. Status Resumo'!$H$22,'2. Status Detalhe Campos'!$D$7:$D$608,"2. Campo") -> 0 | U31: =COUNTIFS('2. Status Detalhe Campos'!$G$7:$G$608,'1. Status Resumo'!$P31,'2. Status Detalhe Campos'!$C$7:$C$608,'1. Status Resumo'!$G$22,'2. Status Detalhe Campos'!$D$7:$D$608,"2. Campo")+COUNTIFS('2. Status Detalhe Campos'!$G$7:$G$608,'1. Status Resumo'!$P31,'2. Status Detalhe Campos'!$C$7:$C$608,'1. Status Resumo'!$H$22,'2. Status Detalhe Campos'!$D$7:$D$608,"2. Campo") -> 0 | V31: =U31-T31 -> 0
P32: 6. Em implementação (re-especificação) | T32: =COUNTIFS('2. Status Detalhe Campos'!$H$7:$H$608,'1. Status Resumo'!$P32,'2. Status Detalhe Campos'!$C$7:$C$608,'1. Status Resumo'!$G$22,'2. Status Detalhe Campos'!$D$7:$D$608,"2. Campo")+COUNTIFS('2. Status Detalhe Campos'!$H$7:$H$608,'1. Status Resumo'!$P32,'2. Status Detalhe Campos'!$C$7:$C$608,'1. Status Resumo'!$H$22,'2. Status Detalhe Campos'!$D$7:$D$608,"2. Campo") -> 12 | U32: =COUNTIFS('2. Status Detalhe Campos'!$G$7:$G$608,'1. Status Resumo'!$P32,'2. Status Detalhe Campos'!$C$7:$C$608,'1. Status Resumo'!$G$22,'2. Status Detalhe Campos'!$D$7:$D$608,"2. Campo")+COUNTIFS('2. Status Detalhe Campos'!$G$7:$G$608,'1. Status Resumo'!$P32,'2. Status Detalhe Campos'!$C$7:$C$608,'1. Status Resumo'!$H$22,'2. Status Detalhe Campos'!$D$7:$D$608,"2. Campo") -> 24 | V32: =U32-T32 -> 12
P33: 7. Por iniciar | T33: =COUNTIFS('2. Status Detalhe Campos'!$H$7:$H$608,'1. Status Resumo'!$P33,'2. Status Detalhe Campos'!$C$7:$C$608,'1. Status Resumo'!$G$22,'2. Status Detalhe Campos'!$D$7:$D$608,"2. Campo")+COUNTIFS('2. Status Detalhe Campos'!$H$7:$H$608,'1. Status Resumo'!$P33,'2. Status Detalhe Campos'!$C$7:$C$608,'1. Status Resumo'!$H$22,'2. Status Detalhe Campos'!$D$7:$D$608,"2. Campo") -> 0 | U33: =COUNTIFS('2. Status Detalhe Campos'!$G$7:$G$608,'1. Status Resumo'!$P33,'2. Status Detalhe Campos'!$C$7:$C$608,'1. Status Resumo'!$G$22,'2. Status Detalhe Campos'!$D$7:$D$608,"2. Campo")+COUNTIFS('2. Status Detalhe Campos'!$G$7:$G$608,'1. Status Resumo'!$P33,'2. Status Detalhe Campos'!$C$7:$C$608,'1. Status Resumo'!$H$22,'2. Status Detalhe Campos'!$D$7:$D$608,"2. Campo") -> 0 | V33: =U33-T33 -> 0
T34: =SUM(T26:T33) -> 161 | U34: =SUM(U26:U33) -> 161
G35: Status (Tabelas) | P35: Status (Universos)
F36: > | G36: Tabela de Bens Imóveis | L36: OK | O36: > | P36: Universo Bens Colateralizados (MUG) | T36: OK
F37: > | G37: Tabelas de Processos Imobiliários | L37: OK | O37: > | P37: Universo Bens Não Colateralizados (GP) | T37: OK
F38: > | G38: Tabela de Traçabilidade Processo -Bem | L38: OK | O38: > | P38: Universo Bens Adjudicados | T38: Não serão testados neste projeto
F39: > | G39: Tabela de Traçabilidade Crédito - Processo | L39: OK
F40: > | G40: Tabela input de Cerificados Energéticos (Gloval) | L40: Em Implementação
F41: > | G41: Tabela Output de Cerificados Energéticos | L41: Validação Especificação Funcional
B48: 2. Modelo Verde | G48: Modelo Verde - Input | H48: Modelo Verde - Output
C51: Resumo | G51: Detalhe por Tabela | P51: Status (campos) | T51: =T25 -> 45551 | U51: =$U$25 -> 45562 | V51: ∆ | X51: Highlights
P52: 0. Cancelado | T52: =COUNTIFS('2. Status Detalhe Campos'!$H$7:$H$608,'1. Status Resumo'!$P52,'2. Status Detalhe Campos'!$C$7:$C$608,'1. Status Resumo'!$G$48,'2. Status Detalhe Campos'!$D$7:$D$608,"2. Campo")+COUNTIFS('2. Status Detalhe Campos'!$H$7:$H$608,'1. Status Resumo'!$P52,'2. Status Detalhe Campos'!$C$7:$C$608,'1. Status Resumo'!$H$48,'2. Status Detalhe Campos'!$D$7:$D$608,"2. Campo") -> 13 | U52: =COUNTIFS('2. Status Detalhe Campos'!$G$7:$G$608,'1. Status Resumo'!$P52,'2. Status Detalhe Campos'!$C$7:$C$608,'1. Status Resumo'!$G$48,'2. Status Detalhe Campos'!$D$7:$D$608,"2. Campo")+COUNTIFS('2. Status Detalhe Campos'!$G$7:$G$608,'1. Status Resumo'!$P52,'2. Status Detalhe Campos'!$C$7:$C$608,'1. Status Resumo'!$H$48,'2. Status Detalhe Campos'!$D$7:$D$608,"2. Campo") -> 14 | V52: =U52-T52 -> 1 | X52: 1. Continua em curso o assessment ao Modelo Verde. 2. Temas endereçados: 2.1 Inputs Corporativos: Foi carregado e testado o input nace (modesg_inp_emss_nace), após alteração manual ao campo do cod nace. 2.2. Universo de Veiculos (Modesg_out_ems_vcls): - Já foi partilhada a re-especificação do novo universo com IT para implementação - Adicionalmente, a especificação da nova tat já foi também partilhada com o IT do MUG para implementação - Após reunião com CDO relativamente à tabela de parametrização, a mesma foi aprovada e estamos a fechar a especificação (dependente de resposta do lease). - Estamos a terminar a re-especificação dos campos das scopes. 2.3. Tabela de Clientes (modesg_out_empr_info_nfin) - O universo de clientes foi testado e está ok - Foram partilhados 4 re-especificações relativamente aos campos cod nace, flag exclusão de paris, flg nfrd e rácios de eligibilidade e flags de risco físico para aprovação. - Estamos a terminar a re-especificação dos campos das scopes. 2.4. Tabela de Marcação Verde (output e parametrização) Foi realizada uma sessão de validação com o CDO e já foi partilhado o e-mail de re-especificação para desenvolvimento por parte do IT. Aguardamos o envio da tabela de parametrização com os códigos das categorias atualizados pelo Controlo de Gestão. 2.5. Tabela de Bens Imóveis -Após reunião com CDO relativamente à tabela de parametrização, a mesma foi aprovada e estamos a fechar a especificação (dependente de resposta do lease) - Foi partilhada a re-especificações relativa aos campos das flags de risco físico para aprovação. -O término da re-especificação dos campos de scopes desta tabela está dependente de uma dúvida de uma metodologia colocada à corporação e da tabela de parametrização. Contudo, parte da re-especificação já foi partilhada com o IT.
P53: 1. Concluído | T53: =COUNTIFS('2. Status Detalhe Campos'!$H$7:$H$608,'1. Status Resumo'!$P53,'2. Status Detalhe Campos'!$C$7:$C$608,'1. Status Resumo'!$G$48,'2. Status Detalhe Campos'!$D$7:$D$608,"2. Campo")+COUNTIFS('2. Status Detalhe Campos'!$H$7:$H$608,'1. Status Resumo'!$P53,'2. Status Detalhe Campos'!$C$7:$C$608,'1. Status Resumo'!$H$48,'2. Status Detalhe Campos'!$D$7:$D$608,"2. Campo") -> 148 | U53: =COUNTIFS('2. Status Detalhe Campos'!$G$7:$G$608,'1. Status Resumo'!$P53,'2. Status Detalhe Campos'!$C$7:$C$608,'1. Status Resumo'!$G$48,'2. Status Detalhe Campos'!$D$7:$D$608,"2. Campo")+COUNTIFS('2. Status Detalhe Campos'!$G$7:$G$608,'1. Status Resumo'!$P53,'2. Status Detalhe Campos'!$C$7:$C$608,'1. Status Resumo'!$H$48,'2. Status Detalhe Campos'!$D$7:$D$608,"2. Campo") -> 150 | V53: =U53-T53 -> 2
P54: 2. Em Teste | T54: =COUNTIFS('2. Status Detalhe Campos'!$H$7:$H$608,'1. Status Resumo'!$P54,'2. Status Detalhe Campos'!$C$7:$C$608,'1. Status Resumo'!$G$48,'2. Status Detalhe Campos'!$D$7:$D$608,"2. Campo")+COUNTIFS('2. Status Detalhe Campos'!$H$7:$H$608,'1. Status Resumo'!$P54,'2. Status Detalhe Campos'!$C$7:$C$608,'1. Status Resumo'!$H$48,'2. Status Detalhe Campos'!$D$7:$D$608,"2. Campo") -> 11 | U54: =COUNTIFS('2. Status Detalhe Campos'!$G$7:$G$608,'1. Status Resumo'!$P54,'2. Status Detalhe Campos'!$C$7:$C$608,'1. Status Resumo'!$G$48,'2. Status Detalhe Campos'!$D$7:$D$608,"2. Campo")+COUNTIFS('2. Status Detalhe Campos'!$G$7:$G$608,'1. Status Resumo'!$P54,'2. Status Detalhe Campos'!$C$7:$C$608,'1. Status Resumo'!$H$48,'2. Status Detalhe Campos'!$D$7:$D$608,"2. Campo") -> 15 | V54: =U54-T54 -> 4
D55: ="# "&U60 -> # 245 | P55: 3. Pendente de outros desenvolvimentos | T55: =COUNTIFS('2. Status Detalhe Campos'!$H$7:$H$608,'1. Status Resumo'!$P55,'2. Status Detalhe Campos'!$C$7:$C$608,'1. Status Resumo'!$G$48,'2. Status Detalhe Campos'!$D$7:$D$608,"2. Campo")+COUNTIFS('2. Status Detalhe Campos'!$H$7:$H$608,'1. Status Resumo'!$P55,'2. Status Detalhe Campos'!$C$7:$C$608,'1. Status Resumo'!$H$48,'2. Status Detalhe Campos'!$D$7:$D$608,"2. Campo") -> 0 | U55: =COUNTIFS('2. Status Detalhe Campos'!$G$7:$G$608,'1. Status Resumo'!$P55,'2. Status Detalhe Campos'!$C$7:$C$608,'1. Status Resumo'!$G$48,'2. Status Detalhe Campos'!$D$7:$D$608,"2. Campo")+COUNTIFS('2. Status Detalhe Campos'!$G$7:$G$608,'1. Status Resumo'!$P55,'2. Status Detalhe Campos'!$C$7:$C$608,'1. Status Resumo'!$H$48,'2. Status Detalhe Campos'!$D$7:$D$608,"2. Campo") -> 0 | V55: =U55-T55 -> 0
P56: 4. Validação EF | T56: =COUNTIFS('2. Status Detalhe Campos'!$H$7:$H$608,'1. Status Resumo'!$P56,'2. Status Detalhe Campos'!$C$7:$C$608,'1. Status Resumo'!$G$48,'2. Status Detalhe Campos'!$D$7:$D$608,"2. Campo")+COUNTIFS('2. Status Detalhe Campos'!$H$7:$H$608,'1. Status Resumo'!$P56,'2. Status Detalhe Campos'!$C$7:$C$608,'1. Status Resumo'!$H$48,'2. Status Detalhe Campos'!$D$7:$D$608,"2. Campo") -> 43 | U56: =COUNTIFS('2. Status Detalhe Campos'!$G$7:$G$608,'1. Status Resumo'!$P56,'2. Status Detalhe Campos'!$C$7:$C$608,'1. Status Resumo'!$G$48,'2. Status Detalhe Campos'!$D$7:$D$608,"2. Campo")+COUNTIFS('2. Status Detalhe Campos'!$G$7:$G$608,'1. Status Resumo'!$P56,'2. Status Detalhe Campos'!$C$7:$C$608,'1. Status Resumo'!$H$48,'2. Status Detalhe Campos'!$D$7:$D$608,"2. Campo") -> 36 | V56: =U56-T56 -> -7
P57: 5. Em Correção | R57: (incidências) | T57: =COUNTIFS('2. Status Detalhe Campos'!$H$7:$H$608,'1. Status Resumo'!$P57,'2. Status Detalhe Campos'!$C$7:$C$608,'1. Status Resumo'!$G$48,'2. Status Detalhe Campos'!$D$7:$D$608,"2. Campo")+COUNTIFS('2. Status Detalhe Campos'!$H$7:$H$608,'1. Status Resumo'!$P57,'2. Status Detalhe Campos'!$C$7:$C$608,'1. Status Resumo'!$H$48,'2. Status Detalhe Campos'!$D$7:$D$608,"2. Campo") -> 0 | U57: =COUNTIFS('2. Status Detalhe Campos'!$G$7:$G$608,'1. Status Resumo'!$P57,'2. Status Detalhe Campos'!$C$7:$C$608,'1. Status Resumo'!$G$48,'2. Status Detalhe Campos'!$D$7:$D$608,"2. Campo")+COUNTIFS('2. Status Detalhe Campos'!$G$7:$G$608,'1. Status Resumo'!$P57,'2. Status Detalhe Campos'!$C$7:$C$608,'1. Status Resumo'!$H$48,'2. Status Detalhe Campos'!$D$7:$D$608,"2. Campo") -> 0 | V57: =U57-T57 -> 0
P58: 6. Em implementação (re-especificação) | T58: =COUNTIFS('2. Status Detalhe Campos'!$H$7:$H$608,'1. Status Resumo'!$P58,'2. Status Detalhe Campos'!$C$7:$C$608,'1. Status Resumo'!$G$48,'2. Status Detalhe Campos'!$D$7:$D$608,"2. Campo")+COUNTIFS('2. Status Detalhe Campos'!$H$7:$H$608,'1. Status Resumo'!$P58,'2. Status Detalhe Campos'!$C$7:$C$608,'1. Status Resumo'!$H$48,'2. Status Detalhe Campos'!$D$7:$D$608,"2. Campo") -> 30 | U58: =COUNTIFS('2. Status Detalhe Campos'!$G$7:$G$608,'1. Status Resumo'!$P58,'2. Status Detalhe Campos'!$C$7:$C$608,'1. Status Resumo'!$G$48,'2. Status Detalhe Campos'!$D$7:$D$608,"2. Campo")+COUNTIFS('2. Status Detalhe Campos'!$G$7:$G$608,'1. Status Resumo'!$P58,'2. Status Detalhe Campos'!$C$7:$C$608,'1. Status Resumo'!$H$48,'2. Status Detalhe Campos'!$D$7:$D$608,"2. Campo") -> 30 | V58: =U58-T58 -> 0
P59: 7. Por iniciar | T59: =COUNTIFS('2. Status Detalhe Campos'!$H$7:$H$608,'1. Status Resumo'!$P59,'2. Status Detalhe Campos'!$C$7:$C$608,'1. Status Resumo'!$G$48,'2. Status Detalhe Campos'!$D$7:$D$608,"2. Campo")+COUNTIFS('2. Status Detalhe Campos'!$H$7:$H$608,'1. Status Resumo'!$P59,'2. Status Detalhe Campos'!$C$7:$C$608,'1. Status Resumo'!$H$48,'2. Status Detalhe Campos'!$D$7:$D$608,"2. Campo") -> 0 | U59: =COUNTIFS('2. Status Detalhe Campos'!$G$7:$G$608,'1. Status Resumo'!$P59,'2. Status Detalhe Campos'!$C$7:$C$608,'1. Status Resumo'!$G$48,'2. Status Detalhe Campos'!$D$7:$D$608,"2. Campo")+COUNTIFS('2. Status Detalhe Campos'!$G$7:$G$608,'1. Status Resumo'!$P59,'2. Status Detalhe Campos'!$C$7:$C$608,'1. Status Resumo'!$H$48,'2. Status Detalhe Campos'!$D$7:$D$608,"2. Campo") -> 0 | V59: =U59-T59 -> 0
T60: =SUM(T52:T59) -> 245 | U60: =SUM(U52:U59) -> 245
P62: Status (Universos - Inputs)
O63: > | P63: modesg_inp_risco_fisico | T63: OK
O64: > | P64: modesg_inp_nfrd_alinhamento_tax | T64: OK
O65: > | P65: modesg_inp_km_medios_emss_vcls | T65: OK
O66: > | P66: modesg_inp_emss_vcls | T66: OK
O67: > | P67: modesg_inp_emss_scib | T67: OK
O68: > | P68: modesg_inp_emss_nace | T68: OK
O69: > | P69: modesg_inp_emss_bens_imoveis | T69: OK
O70: > | P70: modesg_inp_empr_excl_paris | T70: OK
O71: > | P71: modesg_param_sfcs_taxon_europeia | T71: Em Implementação (re-especificação)
P73: Status (Universos - Outputs)
O74: > | P74: modesg_out_ems_vcls | T74: Em Implementação (re-especificação)
O75: > | P75: modesg_out_bens_imoveis | T75: OK (coerente com Modelo de Bens Imóveis)
O76: > | P76: modesg_out_empr_info_nfin | T76: OK
O77: > | P77: modesg_out_sfcs_taxon_europeia | T77: Em Implementação (re-especificação)
B89: 3. Loan Tape | Pilar III | G89: Pilar III
C92: Resumo | G92: Detalhe por Tabela | P92: Status (campos) | T92: =T25 -> 45551 | U92: =$U$25 -> 45562 | V92: ∆ | X92: Highlights
P93: 0. Cancelado | T93: =COUNTIFS(Table4[Status Anterior],'1. Status Resumo'!$P93,Table4[Sub-âmbito],'1. Status Resumo'!$G$89,Table4[Tipo de teste],"2. Campo") -> 0 | U93: =COUNTIFS(Table4[Status Atual],'1. Status Resumo'!$P93,Table4[Sub-âmbito],'1. Status Resumo'!$G$89,Table4[Tipo de teste],"2. Campo") -> 0 | V93: =U93-T93 -> 0 | X93: 1. Não foram realizados avanços devido à dependência dos desenvolvimentos no Modelo de Bens Imóveis e Modelo Verde. 2. Atualmente existem 42 campos concluídos. 3. Encontra-se atualmente 9 campos em validação EF. Notas: 1. Universo de contratos deve corresponder ao da Loan Tape Estrutural. 2. Na tabela da Protection apenas serão testados os imóveis colateralizados.
P94: 1. Concluído | T94: =COUNTIFS(Table4[Status Anterior],'1. Status Resumo'!$P94,Table4[Sub-âmbito],'1. Status Resumo'!$G$89,Table4[Tipo de teste],"2. Campo") -> 42 | U94: =COUNTIFS(Table4[Status Atual],'1. Status Resumo'!$P94,Table4[Sub-âmbito],'1. Status Resumo'!$G$89,Table4[Tipo de teste],"2. Campo") -> 42 | V94: =U94-T94 -> 0
P95: 2. Em Teste | T95: =COUNTIFS(Table4[Status Anterior],'1. Status Resumo'!$P95,Table4[Sub-âmbito],'1. Status Resumo'!$G$89,Table4[Tipo de teste],"2. Campo") -> 0 | U95: =COUNTIFS(Table4[Status Atual],'1. Status Resumo'!$P95,Table4[Sub-âmbito],'1. Status Resumo'!$G$89,Table4[Tipo de teste],"2. Campo") -> 0 | V95: =U95-T95 -> 0
D96: ="# "&U101 -> # 126 | P96: 3. Pendente de outros desenvolvimentos | T96: =COUNTIFS(Table4[Status Anterior],'1. Status Resumo'!$P96,Table4[Sub-âmbito],'1. Status Resumo'!$G$89,Table4[Tipo de teste],"2. Campo") -> 0 | U96: =COUNTIFS(Table4[Status Atual],'1. Status Resumo'!$P96,Table4[Sub-âmbito],'1. Status Resumo'!$G$89,Table4[Tipo de teste],"2. Campo") -> 0 | V96: =U96-T96 -> 0
P97: 4. Validação EF | T97: =COUNTIFS(Table4[Status Anterior],'1. Status Resumo'!$P97,Table4[Sub-âmbito],'1. Status Resumo'!$G$89,Table4[Tipo de teste],"2. Campo") -> 9 | U97: =COUNTIFS(Table4[Status Atual],'1. Status Resumo'!$P97,Table4[Sub-âmbito],'1. Status Resumo'!$G$89,Table4[Tipo de teste],"2. Campo") -> 9 | V97: =U97-T97 -> 0
P98: 5. Em Correção | R98: (incidências) | T98: =COUNTIFS(Table4[Status Anterior],'1. Status Resumo'!$P98,Table4[Sub-âmbito],'1. Status Resumo'!$G$89,Table4[Tipo de teste],"2. Campo") -> 0 | U98: =COUNTIFS(Table4[Status Atual],'1. Status Resumo'!$P98,Table4[Sub-âmbito],'1. Status Resumo'!$G$89,Table4[Tipo de teste],"2. Campo") -> 0 | V98: =U98-T98 -> 0
P99: 6. Em implementação (re-especificação) | T99: =COUNTIFS(Table4[Status Anterior],'1. Status Resumo'!$P99,Table4[Sub-âmbito],'1. Status Resumo'!$G$89,Table4[Tipo de teste],"2. Campo") -> 0 | U99: =COUNTIFS(Table4[Status Atual],'1. Status Resumo'!$P99,Table4[Sub-âmbito],'1. Status Resumo'!$G$89,Table4[Tipo de teste],"2. Campo") -> 0 | V99: =U99-T99 -> 0
P100: 7. Por iniciar | T100: =COUNTIFS(Table4[Status Anterior],'1. Status Resumo'!$P100,Table4[Sub-âmbito],'1. Status Resumo'!$G$89,Table4[Tipo de teste],"2. Campo") -> 75 | U100: =COUNTIFS(Table4[Status Atual],'1. Status Resumo'!$P100,Table4[Sub-âmbito],'1. Status Resumo'!$G$89,Table4[Tipo de teste],"2. Campo") -> 75 | V100: =U100-T100 -> 0
T101: =SUM(T93:T100) -> 126 | U101: =SUM(U93:U100) -> 126
B107: 4. Loan Tape | Green Dashboard | G107: GD
C110: Resumo | G110: Detalhe por Tabela | P110: Status (campos) | T110: =T51 -> 45551 | U110: =$U$25 -> 45562 | V110: ∆ | X110: Highlights
P111: 0. Cancelado | T111: =COUNTIFS('2. Status Detalhe Campos'!$H$7:$H$598,'1. Status Resumo'!$P111,'2. Status Detalhe Campos'!$C$7:$C$598,'1. Status Resumo'!$G$107,'2. Status Detalhe Campos'!$D$7:$D$598,"2. Campo") -> 0 | U111: =COUNTIFS('2. Status Detalhe Campos'!$G$7:$G$598,'1. Status Resumo'!$P111,'2. Status Detalhe Campos'!$C$7:$C$598,'1. Status Resumo'!$G$107,'2. Status Detalhe Campos'!$D$7:$D$598,"2. Campo") -> 0 | V111: =U111-T111 -> 0 | X111: 1. Foi realizada uma reunião de esclarecimento/dúvida relativamente à especificação as-is e to-be dos campos e desagregação da chave do contrato com as equipas envolvidas. Este bloco encontra-se em stand by pela equipa de testes.
P112: 1. Concluído | T112: =COUNTIFS('2. Status Detalhe Campos'!$H$7:$H$598,'1. Status Resumo'!$P112,'2. Status Detalhe Campos'!$C$7:$C$598,'1. Status Resumo'!$G$107,'2. Status Detalhe Campos'!$D$7:$D$598,"2. Campo") -> 23 | U112: =COUNTIFS('2. Status Detalhe Campos'!$G$7:$G$598,'1. Status Resumo'!$P112,'2. Status Detalhe Campos'!$C$7:$C$598,'1. Status Resumo'!$G$107,'2. Status Detalhe Campos'!$D$7:$D$598,"2. Campo") -> 23 | V112: =U112-T112 -> 0
P113: 2. Em Teste | T113: =COUNTIFS('2. Status Detalhe Campos'!$H$7:$H$598,'1. Status Resumo'!$P113,'2. Status Detalhe Campos'!$C$7:$C$598,'1. Status Resumo'!$G$107,'2. Status Detalhe Campos'!$D$7:$D$598,"2. Campo") -> 26 | U113: =COUNTIFS('2. Status Detalhe Campos'!$G$7:$G$598,'1. Status Resumo'!$P113,'2. Status Detalhe Campos'!$C$7:$C$598,'1. Status Resumo'!$G$107,'2. Status Detalhe Campos'!$D$7:$D$598,"2. Campo") -> 26 | V113: =U113-T113 -> 0
D114: ="# "&U119 -> # 50 | P114: 3. Pendente de outros desenvolvimentos | T114: =COUNTIFS('2. Status Detalhe Campos'!$H$7:$H$598,'1. Status Resumo'!$P114,'2. Status Detalhe Campos'!$C$7:$C$598,'1. Status Resumo'!$G$107,'2. Status Detalhe Campos'!$D$7:$D$598,"2. Campo") -> 1 | U114: =COUNTIFS('2. Status Detalhe Campos'!$G$7:$G$598,'1. Status Resumo'!$P114,'2. Status Detalhe Campos'!$C$7:$C$598,'1. Status Resumo'!$G$107,'2. Status Detalhe Campos'!$D$7:$D$598,"2. Campo") -> 1 | V114: =U114-T114 -> 0
P115: 4. Validação EF | T115: =COUNTIFS('2. Status Detalhe Campos'!$H$7:$H$598,'1. Status Resumo'!$P115,'2. Status Detalhe Campos'!$C$7:$C$598,'1. Status Resumo'!$G$107,'2. Status Detalhe Campos'!$D$7:$D$598,"2. Campo") -> 0 | U115: =COUNTIFS('2. Status Detalhe Campos'!$G$7:$G$598,'1. Status Resumo'!$P115,'2. Status Detalhe Campos'!$C$7:$C$598,'1. Status Resumo'!$G$107,'2. Status Detalhe Campos'!$D$7:$D$598,"2. Campo") -> 0 | V115: =U115-T115 -> 0
P116: 5. Em Correção | R116: (incidências) | T116: =COUNTIFS('2. Status Detalhe Campos'!$H$7:$H$598,'1. Status Resumo'!$P116,'2. Status Detalhe Campos'!$C$7:$C$598,'1. Status Resumo'!$G$107,'2. Status Detalhe Campos'!$D$7:$D$598,"2. Campo") -> 0 | U116: =COUNTIFS('2. Status Detalhe Campos'!$G$7:$G$598,'1. Status Resumo'!$P116,'2. Status Detalhe Campos'!$C$7:$C$598,'1. Status Resumo'!$G$107,'2. Status Detalhe Campos'!$D$7:$D$598,"2. Campo") -> 0 | V116: =U116-T116 -> 0
P117: 6. Em implementação (re-especificação) | T117: =COUNTIFS('2. Status Detalhe Campos'!$H$7:$H$598,'1. Status Resumo'!$P117,'2. Status Detalhe Campos'!$C$7:$C$598,'1. Status Resumo'!$G$107,'2. Status Detalhe Campos'!$D$7:$D$598,"2. Campo") -> 0 | U117: =COUNTIFS('2. Status Detalhe Campos'!$G$7:$G$598,'1. Status Resumo'!$P117,'2. Status Detalhe Campos'!$C$7:$C$598,'1. Status Resumo'!$G$107,'2. Status Detalhe Campos'!$D$7:$D$598,"2. Campo") -> 0 | V117: =U117-T117 -> 0
P118: 7. Por iniciar | T118: =COUNTIFS('2. Status Detalhe Campos'!$H$7:$H$598,'1. Status Resumo'!$P118,'2. Status Detalhe Campos'!$C$7:$C$598,'1. Status Resumo'!$G$107,'2. Status Detalhe Campos'!$D$7:$D$598,"2. Campo") -> 0 | U118: =COUNTIFS('2. Status Detalhe Campos'!$G$7:$G$598,'1. Status Resumo'!$P118,'2. Status Detalhe Campos'!$C$7:$C$598,'1. Status Resumo'!$G$107,'2. Status Detalhe Campos'!$D$7:$D$598,"2. Campo") -> 0 | V118: =U118-T118 -> 0
T119: =SUM(T111:T118) -> 50 | U119: =SUM(U111:U118) -> 50
A134: <

Sheet 2. Status Detalhe Campos
B6: Âmbito | C6: Sub-âmbito | D6: Tipo de teste | E6: Tabela | F6: Campo | G6: Status Atual | H6: Status Anterior | I6: Observações | J6: Data de Pedido correção/esclarecimento | K6: Data de correção prevista | L6: Data de correção efetiva | M6: Data Reunião
A7: =E7&F7 -> cd_imv_inp_certif_estimativan.a. | B7: Pilar III | C7: Bens Imóveis - Input | D7: 1. Universo | E7: cd_imv_inp_certif_estimativa | F7: n.a. | G7: =VLOOKUP(A7,Plano_V3!$A$27:$G$583,7,0) -> 6. Em implementação (re-especificação) | H7: 6. Em implementação (re-especificação) | J7: =IF(VLOOKUP(A7,'Aux - pivots1'!$A:$E,3,0)=0, "",VLOOKUP(A7,'Aux - pivots1'!$A:$E,3,0)) | K7: =IF(VLOOKUP(A7,'Aux - pivots1'!$A:$E,4,0)=0, "",VLOOKUP(A7,'Aux - pivots1'!$A:$E,4,0)) | L7: =IF(VLOOKUP(A7,'Aux - pivots1'!$A:$E,5,0)=0, "",VLOOKUP(A7,'Aux - pivots1'!$A:$E,5,0))
A8: =E8&F8 -> cd_imv_inp_certif_estimativacempbem | B8: Pilar III | C8: Bens Imóveis - Input | D8: 2. Campo | E8: cd_imv_inp_certif_estimativa | F8: cempbem | G8: =VLOOKUP(A8,Plano_V3!$A$27:$G$583,7,0) -> 6. Em implementação (re-especificação) | H8: 6. Em implementação (re-especificação) | J8: =IF(VLOOKUP(A8,'Aux - pivots1'!$A:$E,3,0)=0, "",VLOOKUP(A8,'Aux - pivots1'!$A:$E,3,0)) | K8: =IF(VLOOKUP(A8,'Aux - pivots1'!$A:$E,4,0)=0, "",VLOOKUP(A8,'Aux - pivots1'!$A:$E,4,0)) | L8: =IF(VLOOKUP(A8,'Aux - pivots1'!$A:$E,5,0)=0, "",VLOOKUP(A8,'Aux - pivots1'!$A:$E,5,0))
A9: =E9&F9 -> cd_imv_inp_certif_estimativachave_encriptada | B9: Pilar III | C9: Bens Imóveis - Input | D9: 2. Campo | E9: cd_imv_inp_certif_estimativa | F9: chave_encriptada | G9: =VLOOKUP(A9,Plano_V3!$A$27:$G$583,7,0) -> 6. Em implementação (re-especificação) | H9: 6. Em implementação (re-especificação) | J9: =IF(VLOOKUP(A9,'Aux - pivots1'!$A:$E,3,0)=0, "",VLOOKUP(A9,'Aux - pivots1'!$A:$E,3,0)) | K9: =IF(VLOOKUP(A9,'Aux - pivots1'!$A:$E,4,0)=0, "",VLOOKUP(A9,'Aux - pivots1'!$A:$E,4,0)) | L9: =IF(VLOOKUP(A9,'Aux - pivots1'!$A:$E,5,0)=0, "",VLOOKUP(A9,'Aux - pivots1'!$A:$E,5,0))
A10: =E10&F10 -> cd_imv_inp_certif_estimativackbalbem | B10: Pilar III | C10: Bens Imóveis - Input | D10: 2. Campo | E10: cd_imv_inp_certif_estimativa | F10: ckbalbem | G10: =VLOOKUP(A10,Plano_V3!$A$27:$G$583,7,0) -> 6. Em implementação (re-especificação) | H10: 6. Em implementação (re-especificação) | J10: =IF(VLOOKUP(A10,'Aux - pivots1'!$A:$E,3,0)=0, "",VLOOKUP(A10,'Aux - pivots1'!$A:$E,3,0)) | K10: =IF(VLOOKUP(A10,'Aux - pivots1'!$A:$E,4,0)=0, "",VLOOKUP(A10,'Aux - pivots1'!$A:$E,4,0)) | L10: =IF(VLOOKUP(A10,'Aux - pivots1'!$A:$E,5,0)=0, "",VLOOKUP(A10,'Aux - pivots1'!$A:$E,5,0))
A11: =E11&F11 -> cd_imv_inp_certif_estimativackctabem | B11: Pilar III | C11: Bens Imóveis - Input | D11: 2. Campo | E11: cd_imv_inp_certif_estimativa | F11: ckctabem | G11: =VLOOKUP(A11,Plano_V3!$A$27:$G$583,7,0) -> 6. Em implementação (re-especificação) | H11: 6. Em implementação (re-especificação) | J11: =IF(VLOOKUP(A11,'Aux - pivots1'!$A:$E,3,0)=0, "",VLOOKUP(A11,'Aux - pivots1'!$A:$E,3,0)) | K11: =IF(VLOOKUP(A11,'Aux - pivots1'!$A:$E,4,0)=0, "",VLOOKUP(A11,'Aux - pivots1'!$A:$E,4,0)) | L11: =IF(VLOOKUP(A11,'Aux - pivots1'!$A:$E,5,0)=0, "",VLOOKUP(A11,'Aux - pivots1'!$A:$E,5,0))
A12: =E12&F12 -> cd_imv_inp_certif_estimativackrefbem | B12: Pilar III | C12: Bens Imóveis - Input | D12: 2. Campo | E12: cd_imv_inp_certif_estimativa | F12: ckrefbem | G12: =VLOOKUP(A12,Plano_V3!$A$27:$G$583,7,0) -> 6. Em implementação (re-especificação) | H12: 6. Em implementação (re-especificação) | J12: =IF(VLOOKUP(A12,'Aux - pivots1'!$A:$E,3,0)=0, "",VLOOKUP(A12,'Aux - pivots1'!$A:$E,3,0)) | K12: =IF(VLOOKUP(A12,'Aux - pivots1'!$A:$E,4,0)=0, "",VLOOKUP(A12,'Aux - pivots1'!$A:$E,4,0)) | L12: =IF(VLOOKUP(A12,'Aux - pivots1'!$A:$E,5,0)=0, "",VLOOKUP(A12,'Aux - pivots1'!$A:$E,5,0))
A13: =E13&F13 -> cd_imv_inp_certif_estimativadata_extraccao_info | B13: Pilar III | C13: Bens Imóveis - Input | D13: 2. Campo | E13: cd_imv_inp_certif_estimativa | F13: data_extraccao_info | G13: =VLOOKUP(A13,Plano_V3!$A$27:$G$583,7,0) -> 6. Em implementação (re-especificação) | H13: 6. Em implementação (re-especificação) | J13: =IF(VLOOKUP(A13,'Aux - pivots1'!$A:$E,3,0)=0, "",VLOOKUP(A13,'Aux - pivots1'!$A:$E,3,0)) | K13: =IF(VLOOKUP(A13,'Aux - pivots1'!$A:$E,4,0)=0, "",VLOOKUP(A13,'Aux - pivots1'!$A:$E,4,0)) | L13: =IF(VLOOKUP(A13,'Aux - pivots1'!$A:$E,5,0)=0, "",VLOOKUP(A13,'Aux - pivots1'!$A:$E,5,0))
A14: =E14&F14 -> cd_imv_inp_certif_estimativaepc | B14: Pilar III | C14: Bens Imóveis - Input | D14: 2. Campo | E14: cd_imv_inp_certif_estimativa | F14: epc | G14: =VLOOKUP(A14,Plano_V3!$A$27:$G$583,7,0) -> 6. Em implementação (re-especificação) | H14: 6. Em implementação (re-especificação) | J14: =IF(VLOOKUP(A14,'Aux - pivots1'!$A:$E,3,0)=0, "",VLOOKUP(A14,'Aux - pivots1'!$A:$E,3,0)) | K14: =IF(VLOOKUP(A14,'Aux - pivots1'!$A:$E,4,0)=0, "",VLOOKUP(A14,'Aux - pivots1'!$A:$E,4,0)) | L14: =IF(VLOOKUP(A14,'Aux - pivots1'!$A:$E,5,0)=0, "",VLOOKUP(A14,'Aux - pivots1'!$A:$E,5,0))
A15: =E15&F15 -> cd_imv_inp_certif_estimativafornecedor | B15: Pilar III | C15: Bens Imóveis - Input | D15: 2. Campo | E15: cd_imv_inp_certif_estimativa | F15: fornecedor | G15: =VLOOKUP(A15,Plano_V3!$A$27:$G$583,7,0) -> 6. Em implementação (re-especificação) | H15: 6. Em implementação (re-especificação) | J15: =IF(VLOOKUP(A15,'Aux - pivots1'!$A:$E,3,0)=0, "",VLOOKUP(A15,'Aux - pivots1'!$A:$E,3,0)) | K15: =IF(VLOOKUP(A15,'Aux - pivots1'!$A:$E,4,0)=0, "",VLOOKUP(A15,'Aux - pivots1'!$A:$E,4,0)) | L15: =IF(VLOOKUP(A15,'Aux - pivots1'!$A:$E,5,0)=0, "",VLOOKUP(A15,'Aux - pivots1'!$A:$E,5,0))
A16: =E16&F16 -> cd_imv_inp_certif_estimativametodo_info | B16: Pilar III | C16: Bens Imóveis - Input | D16: 2. Campo | E16: cd_imv_inp_certif_estimativa | F16: metodo_info | G16: =VLOOKUP(A16,Plano_V3!$A$27:$G$583,7,0) -> 6. Em implementação (re-especificação) | H16: 6. Em implementação (re-especificação) | J16: =IF(VLOOKUP(A16,'Aux - pivots1'!$A:$E,3,0)=0, "",VLOOKUP(A16,'Aux - pivots1'!$A:$E,3,0)) | K16: =IF(VLOOKUP(A16,'Aux - pivots1'!$A:$E,4,0)=0, "",VLOOKUP(A16,'Aux - pivots1'!$A:$E,4,0)) | L16: =IF(VLOOKUP(A16,'Aux - pivots1'!$A:$E,5,0)=0, "",VLOOKUP(A16,'Aux - pivots1'!$A:$E,5,0))
A17: =E17&F17 -> cd_imv_inp_certif_estimativascore_qualidade | B17: Pilar III | C17: Bens Imóveis - Input | D17: 2. Campo | E17: cd_imv_inp_certif_estimativa | F17: score_qualidade | G17: =VLOOKUP(A17,Plano_V3!$A$27:$G$583,7,0) -> 6. Em implementação (re-especificação) | H17: 6. Em implementação (re-especificação) | J17: =IF(VLOOKUP(A17,'Aux - pivots1'!$A:$E,3,0)=0, "",VLOOKUP(A17,'Aux - pivots1'!$A:$E,3,0)) | K17: =IF(VLOOKUP(A17,'Aux - pivots1'!$A:$E,4,0)=0, "",VLOOKUP(A17,'Aux - pivots1'!$A:$E,4,0)) | L17: =IF(VLOOKUP(A17,'Aux - pivots1'!$A:$E,5,0)=0, "",VLOOKUP(A17,'Aux - pivots1'!$A:$E,5,0))
A18: =E18&F18 -> cd_imv_inp_certif_estimativavlr_cnsm_ano | B18: Pilar III | C18: Bens Imóveis - Input | D18: 2. Campo | E18: cd_imv_inp_certif_estimativa | F18: vlr_cnsm_ano | G18: =VLOOKUP(A18,Plano_V3!$A$27:$G$583,7,0) -> 6. Em implementação (re-especificação) | H18: 6. Em implementação (re-especificação) | J18: =IF(VLOOKUP(A18,'Aux - pivots1'!$A:$E,3,0)=0, "",VLOOKUP(A18,'Aux - pivots1'!$A:$E,3,0)) | K18: =IF(VLOOKUP(A18,'Aux - pivots1'!$A:$E,4,0)=0, "",VLOOKUP(A18,'Aux - pivots1'!$A:$E,4,0)) | L18: =IF(VLOOKUP(A18,'Aux - pivots1'!$A:$E,5,0)=0, "",VLOOKUP(A18,'Aux - pivots1'!$A:$E,5,0))
... A20: =E20&F20 -> cd_imv_out_prcn.a. | B20: Pilar III | C20: Bens Imóveis - Output | D20: 1. Universo | E20: cd_imv_out_prc | F20: n.a. | G20: =VLOOKUP(A20,Plano_V3!$A$27:$G$583,7,0) -> 1. Concluído | H20: 1. Concluído | J20: =IF(VLOOKUP(A20,'Aux - pivots1'!$A:$E,3,0)=0, "",VLOOKUP(A20,'Aux - pivots1'!$A:$E,3,0)) | K20: =IF(VLOOKUP(A20,'Aux - pivots1'!$A:$E,4,0)=0, "",VLOOKUP(A20,'Aux - pivots1'!$A:$E,4,0)) | L20: =IF(VLOOKUP(A20,'Aux - pivots1'!$A:$E,5,0)=0, "",VLOOKUP(A20,'Aux - pivots1'!$A:$E,5,0))
A21: =E21&F21 -> cd_imv_out_prccempresa | B21: Pilar III | C21: Bens Imóveis - Output | D21: 2. Campo | E21: cd_imv_out_prc | F21: cempresa | G21: =VLOOKUP(A21,Plano_V3!$A$27:$G$583,7,0) -> 1. Concluído | H21: 1. Concluído | I21: 26/07/2024: Conclusão de testes ao universo MUG e GP. Adjudicados fora de âmbito deste projeto. | J21: =IF(VLOOKUP(A21,'Aux - pivots1'!$A:$E,3,0)=0, "",VLOOKUP(A21,'Aux - pivots1'!$A:$E,3,0)) | K21: =IF(VLOOKUP(A21,'Aux - pivots1'!$A:$E,4,0)=0, "",VLOOKUP(A21,'Aux - pivots1'!$A:$E,4,0)) | L21: =IF(VLOOKUP(A21,'Aux - pivots1'!$A:$E,5,0)=0, "",VLOOKUP(A21,'Aux - pivots1'!$A:$E,5,0))
A22: =E22&F22 -> cd_imv_out_prcckbalcao | B22: Pilar III | C22: Bens Imóveis - Output | D22: 2. Campo | E22: cd_imv_out_prc | F22: ckbalcao | G22: =VLOOKUP(A22,Plano_V3!$A$27:$G$583,7,0) -> 1. Concluído | H22: 1. Concluído | I22: 26/07/2024: Conclusão de testes ao universo MUG e GP. Adjudicados fora de âmbito deste projeto. | J22: =IF(VLOOKUP(A22,'Aux - pivots1'!$A:$E,3,0)=0, "",VLOOKUP(A22,'Aux - pivots1'!$A:$E,3,0)) | K22: =IF(VLOOKUP(A22,'Aux - pivots1'!$A:$E,4,0)=0, "",VLOOKUP(A22,'Aux - pivots1'!$A:$E,4,0)) | L22: =IF(VLOOKUP(A22,'Aux - pivots1'!$A:$E,5,0)=0, "",VLOOKUP(A22,'Aux - pivots1'!$A:$E,5,0))
A23: =E23&F23 -> cd_imv_out_prccknumcta | B23: Pilar III | C23: Bens Imóveis - Output | D23: 2. Campo | E23: cd_imv_out_prc | F23: cknumcta | G23: =VLOOKUP(A23,Plano_V3!$A$27:$G$583,7,0) -> 1. Concluído | H23: 1. Concluído | I23: 26/07/2024: Conclusão de testes ao universo MUG e GP. Adjudicados fora de âmbito deste projeto. | J23: =IF(VLOOKUP(A23,'Aux - pivots1'!$A:$E,3,0)=0, "",VLOOKUP(A23,'Aux - pivots1'!$A:$E,3,0)) | K23: =IF(VLOOKUP(A23,'Aux - pivots1'!$A:$E,4,0)=0, "",VLOOKUP(A23,'Aux - pivots1'!$A:$E,4,0)) | L23: =IF(VLOOKUP(A23,'Aux - pivots1'!$A:$E,5,0)=0, "",VLOOKUP(A23,'Aux - pivots1'!$A:$E,5,0))
A24: =E24&F24 -> cd_imv_out_prccod_estd_prcs | B24: Pilar III | C24: Bens Imóveis - Output | D24: 2. Campo | E24: cd_imv_out_prc | F24: cod_estd_prcs | G24: =VLOOKUP(A24,Plano_V3!$A$27:$G$583,7,0) -> 0. Cancelado | H24: 0. Cancelado | I24: 19/07/2024: Campo eliminado do Modelo para garantir coerência com MUG | J24: =IF(VLOOKUP(A24,'Aux - pivots1'!$A:$E,3,0)=0, "",VLOOKUP(A24,'Aux - pivots1'!$A:$E,3,0)) | K24: =IF(VLOOKUP(A24,'Aux - pivots1'!$A:$E,4,0)=0, "",VLOOKUP(A24,'Aux - pivots1'!$A:$E,4,0)) | L24: =IF(VLOOKUP(A24,'Aux - pivots1'!$A:$E,5,0)=0, "",VLOOKUP(A24,'Aux - pivots1'!$A:$E,5,0))
A25: =E25&F25 -> cd_imv_out_prccod_grt | B25: Pilar III | C25: Bens Imóveis - Output | D25: 2. Campo | E25: cd_imv_out_prc | F25: cod_grt | G25: =VLOOKUP(A25,Plano_V3!$A$27:$G$583,7,0) -> 1. Concluído | H25: 1. Concluído | J25: =IF(VLOOKUP(A25,'Aux - pivots1'!$A:$E,3,0)=0, "",VLOOKUP(A25,'Aux - pivots1'!$A:$E,3,0)) | K25: =IF(VLOOKUP(A25,'Aux - pivots1'!$A:$E,4,0)=0, "",VLOOKUP(A25,'Aux - pivots1'!$A:$E,4,0)) | L25: =IF(VLOOKUP(A25,'Aux - pivots1'!$A:$E,5,0)=0, "",VLOOKUP(A25,'Aux - pivots1'!$A:$E,5,0))
A26: =E26&F26 -> cd_imv_out_prccod_moeda | B26: Pilar III | C26: Bens Imóveis - Output | D26: 2. Campo | E26: cd_imv_out_prc | F26: cod_moeda | G26: =VLOOKUP(A26,Plano_V3!$A$27:$G$583,7,0) -> 1. Concluído | H26: 1. Concluído | J26: =IF(VLOOKUP(A26,'Aux - pivots1'!$A:$E,3,0)=0, "",VLOOKUP(A26,'Aux - pivots1'!$A:$E,3,0)) -> 45512 | K26: =IF(VLOOKUP(A26,'Aux - pivots1'!$A:$E,4,0)=0, "",VLOOKUP(A26,'Aux - pivots1'!$A:$E,4,0)) -> 45526 | L26: =IF(VLOOKUP(A26,'Aux - pivots1'!$A:$E,5,0)=0, "",VLOOKUP(A26,'Aux - pivots1'!$A:$E,5,0))
A27: =E27&F27 -> cd_imv_out_prccod_observacao | B27: Pilar III | C27: Bens Imóveis - Output | D27: 2. Campo | E27: cd_imv_out_prc | F27: cod_observacao | G27: =VLOOKUP(A27,Plano_V3!$A$27:$G$583,7,0) -> 1. Concluído | H27: 1. Concluído | J27: =IF(VLOOKUP(A27,'Aux - pivots1'!$A:$E,3,0)=0, "",VLOOKUP(A27,'Aux - pivots1'!$A:$E,3,0)) | K27: =IF(VLOOKUP(A27,'Aux - pivots1'!$A:$E,4,0)=0, "",VLOOKUP(A27,'Aux - pivots1'!$A:$E,4,0)) | L27: =IF(VLOOKUP(A27,'Aux - pivots1'!$A:$E,5,0)=0, "",VLOOKUP(A27,'Aux - pivots1'!$A:$E,5,0))
A28: =E28&F28 -> cd_imv_out_prccod_prd_grnt | B28: Pilar III | C28: Bens Imóveis - Output | D28: 2. Campo | E28: cd_imv_out_prc | F28: cod_prd_grnt | G28: =VLOOKUP(A28,Plano_V3!$A$27:$G$583,7,0) -> 1. Concluído | H28: 1. Concluído | J28: =IF(VLOOKUP(A28,'Aux - pivots1'!$A:$E,3,0)=0, "",VLOOKUP(A28,'Aux - pivots1'!$A:$E,3,0)) | K28: =IF(VLOOKUP(A28,'Aux - pivots1'!$A:$E,4,0)=0, "",VLOOKUP(A28,'Aux - pivots1'!$A:$E,4,0)) | L28: =IF(VLOOKUP(A28,'Aux - pivots1'!$A:$E,5,0)=0, "",VLOOKUP(A28,'Aux - pivots1'!$A:$E,5,0))
A29: =E29&F29 -> cd_imv_out_prccod_sprd_grnt | B29: Pilar III | C29: Bens Imóveis - Output | D29: 2. Campo | E29: cd_imv_out_prc | F29: cod_sprd_grnt | G29: =VLOOKUP(A29,Plano_V3!$A$27:$G$583,7,0) -> 1. Concluído | H29: 1. Concluído | J29: =IF(VLOOKUP(A29,'Aux - pivots1'!$A:$E,3,0)=0, "",VLOOKUP(A29,'Aux - pivots1'!$A:$E,3,0)) | K29: =IF(VLOOKUP(A29,'Aux - pivots1'!$A:$E,4,0)=0, "",VLOOKUP(A29,'Aux - pivots1'!$A:$E,4,0)) | L29: =IF(VLOOKUP(A29,'Aux - pivots1'!$A:$E,5,0)=0, "",VLOOKUP(A29,'Aux - pivots1'!$A:$E,5,0))
A30: =E30&F30 -> cd_imv_out_prccod_tipo | B30: Pilar III | C30: Bens Imóveis - Output | D30: 2. Campo | E30: cd_imv_out_prc | F30: cod_tipo | G30: =VLOOKUP(A30,Plano_V3!$A$27:$G$583,7,0) -> 1. Concluído | H30: 1. Concluído | J30: =IF(VLOOKUP(A30,'Aux - pivots1'!$A:$E,3,0)=0, "",VLOOKUP(A30,'Aux - pivots1'!$A:$E,3,0)) | K30: =IF(VLOOKUP(A30,'Aux - pivots1'!$A:$E,4,0)=0, "",VLOOKUP(A30,'Aux - pivots1'!$A:$E,4,0)) | L30: =IF(VLOOKUP(A30,'Aux - pivots1'!$A:$E,5,0)=0, "",VLOOKUP(A30,'Aux - pivots1'!$A:$E,5,0))
A31: =E31&F31 -> cd_imv_out_prccomp_id_gar | B31: Pilar III | C31: Bens Imóveis - Output | D31: 2. Campo | E31: cd_imv_out_prc | F31: comp_id_gar | G31: =VLOOKUP(A31,Plano_V3!$A$27:$G$583,7,0) -> 1. Concluído | H31: 1. Concluído | J31: =IF(VLOOKUP(A31,'Aux - pivots1'!$A:$E,3,0)=0, "",VLOOKUP(A31,'Aux - pivots1'!$A:$E,3,0)) | K31: =IF(VLOOKUP(A31,'Aux - pivots1'!$A:$E,4,0)=0, "",VLOOKUP(A31,'Aux - pivots1'!$A:$E,4,0)) | L31: =IF(VLOOKUP(A31,'Aux - pivots1'!$A:$E,5,0)=0, "",VLOOKUP(A31,'Aux - pivots1'!$A:$E,5,0))
A32: =E32&F32 -> cd_imv_out_prcdata_inicio | B32: Pilar III | C32: Bens Imóveis - Output | D32: 2. Campo | E32: cd_imv_out_prc | F32: data_inicio | G32: =VLOOKUP(A32,Plano_V3!$A$27:$G$583,7,0) -> 1. Concluído | H32: 1. Concluído | J32: =IF(VLOOKUP(A32,'Aux - pivots1'!$A:$E,3,0)=0, "",VLOOKUP(A32,'Aux - pivots1'!$A:$E,3,0)) | K32: =IF(VLOOKUP(A32,'Aux - pivots1'!$A:$E,4,0)=0, "",VLOOKUP(A32,'Aux - pivots1'!$A:$E,4,0)) | L32: =IF(VLOOKUP(A32,'Aux - pivots1'!$A:$E,5,0)=0, "",VLOOKUP(A32,'Aux - pivots1'!$A:$E,5,0))
A33: =E33&F33 -> cd_imv_out_prcdata_vcmt | B33: Pilar III | C33: Bens Imóveis - Output | D33: 2. Campo | E33: cd_imv_out_prc | F33: data_vcmt | G33: =VLOOKUP(A33,Plano_V3!$A$27:$G$583,7,0) -> 1. Concluído | H33: 1. Concluído | J33: =IF(VLOOKUP(A33,'Aux - pivots1'!$A:$E,3,0)=0, "",VLOOKUP(A33,'Aux - pivots1'!$A:$E,3,0)) | K33: =IF(VLOOKUP(A33,'Aux - pivots1'!$A:$E,4,0)=0, "",VLOOKUP(A33,'Aux - pivots1'!$A:$E,4,0)) | L33: =IF(VLOOKUP(A33,'Aux - pivots1'!$A:$E,5,0)=0, "",VLOOKUP(A33,'Aux - pivots1'!$A:$E,5,0))
A34: =E34&F34 -> cd_imv_out_prcmontante_eur | B34: Pilar III | C34: Bens Imóveis - Output | D34: 2. Campo | E34: cd_imv_out_prc | F34: montante_eur | G34: =VLOOKUP(A34,Plano_V3!$A$27:$G$583,7,0) -> 0. Cancelado | H34: 0. Cancelado | I34: 19/07/2024: Campo eliminado do Modelo para garantir coerência com MUG | J34: =IF(VLOOKUP(A34,'Aux - pivots1'!$A:$E,3,0)=0, "",VLOOKUP(A34,'Aux - pivots1'!$A:$E,3,0)) | K34: =IF(VLOOKUP(A34,'Aux - pivots1'!$A:$E,4,0)=0, "",VLOOKUP(A34,'Aux - pivots1'!$A:$E,4,0)) | L34: =IF(VLOOKUP(A34,'Aux - pivots1'!$A:$E,5,0)=0, "",VLOOKUP(A34,'Aux - pivots1'!$A:$E,5,0))
A35: =E35&F35 -> cd_imv_out_prcmontante_org | B35: Pilar III | C35: Bens Imóveis - Output | D35: 2. Campo | E35: cd_imv_out_prc | F35: montante_org | G35: =VLOOKUP(A35,Plano_V3!$A$27:$G$583,7,0) -> 0. Cancelado | H35: 0. Cancelado | I35: 19/07/2024: Campo eliminado do Modelo para garantir coerência com MUG | J35: =IF(VLOOKUP(A35,'Aux - pivots1'!$A:$E,3,0)=0, "",VLOOKUP(A35,'Aux - pivots1'!$A:$E,3,0)) | K35: =IF(VLOOKUP(A35,'Aux - pivots1'!$A:$E,4,0)=0, "",VLOOKUP(A35,'Aux - pivots1'!$A:$E,4,0)) | L35: =IF(VLOOKUP(A35,'Aux - pivots1'!$A:$E,5,0)=0, "",VLOOKUP(A35,'Aux - pivots1'!$A:$E,5,0))
A36: =E36&F36 -> cd_imv_out_prcorigem | B36: Pilar III | C36: Bens Imóveis - Output | D36: 2. Campo | E36: cd_imv_out_prc | F36: origem | G36: =VLOOKUP(A36,Plano_V3!$A$27:$G$583,7,0) -> 0. Cancelado | H36: 0. Cancelado | I36: 08/08/2024: Campo eliminado de modo a garantir a coerência com o atualmente realizado no Modelo Único de Garantias. | J36: =IF(VLOOKUP(A36,'Aux - pivots1'!$A:$E,3,0)=0, "",VLOOKUP(A36,'Aux - pivots1'!$A:$E,3,0)) | K36: =IF(VLOOKUP(A36,'Aux - pivots1'!$A:$E,4,0)=0, "",VLOOKUP(A36,'Aux - pivots1'!$A:$E,4,0)) | L36: =IF(VLOOKUP(A36,'Aux - pivots1'!$A:$E,5,0)=0, "",VLOOKUP(A36,'Aux - pivots1'!$A:$E,5,0))
A37: =E37&F37 -> cd_imv_out_prcref_date | B37: Pilar III | C37: Bens Imóveis - Output | D37: 2. Campo | E37: cd_imv_out_prc | F37: ref_date | G37: =VLOOKUP(A37,Plano_V3!$A$27:$G$583,7,0) -> 1. Concluído | H37: 1. Concluído | J37: =IF(VLOOKUP(A37,'Aux - pivots1'!$A:$E,3,0)=0, "",VLOOKUP(A37,'Aux - pivots1'!$A:$E,3,0)) | K37: =IF(VLOOKUP(A37,'Aux - pivots1'!$A:$E,4,0)=0, "",VLOOKUP(A37,'Aux - pivots1'!$A:$E,4,0)) | L37: =IF(VLOOKUP(A37,'Aux - pivots1'!$A:$E,5,0)=0, "",VLOOKUP(A37,'Aux - pivots1'!$A:$E,5,0))
A38: =E38&F38 -> cd_imv_out_trz_cred_prcn.a. | B38: Pilar III | C38: Bens Imóveis - Output | D38: 1. Universo | E38: cd_imv_out_trz_cred_prc | F38: n.a. | G38: =VLOOKUP(A38,Plano_V3!$A$27:$G$583,7,0) -> 1. Concluído | H38: 1. Concluído | J38: =IF(VLOOKUP(A38,'Aux - pivots1'!$A:$E,3,0)=0, "",VLOOKUP(A38,'Aux - pivots1'!$A:$E,3,0)) | K38: =IF(VLOOKUP(A38,'Aux - pivots1'!$A:$E,4,0)=0, "",VLOOKUP(A38,'Aux - pivots1'!$A:$E,4,0)) | L38: =IF(VLOOKUP(A38,'Aux - pivots1'!$A:$E,5,0)=0, "",VLOOKUP(A38,'Aux - pivots1'!$A:$E,5,0))
A39: =E39&F39 -> cd_imv_out_trz_cred_prccempresa | B39: Pilar III | C39: Bens Imóveis - Output | D39: 2. Campo | E39: cd_imv_out_trz_cred_prc | F39: cempresa | G39: =VLOOKUP(A39,Plano_V3!$A$27:$G$583,7,0) -> 1. Concluído | H39: 1. Concluído | I39: 26/07/2024: Conclusão de testes ao universo MUG e GP. Adjudicados fora de âmbito deste projeto. | J39: =IF(VLOOKUP(A39,'Aux - pivots1'!$A:$E,3,0)=0, "",VLOOKUP(A39,'Aux - pivots1'!$A:$E,3,0)) | K39: =IF(VLOOKUP(A39,'Aux - pivots1'!$A:$E,4,0)=0, "",VLOOKUP(A39,'Aux - pivots1'!$A:$E,4,0)) | L39: =IF(VLOOKUP(A39,'Aux - pivots1'!$A:$E,5,0)=0, "",VLOOKUP(A39,'Aux - pivots1'!$A:$E,5,0))
A40: =E40&F40 -> cd_imv_out_trz_cred_prccempresp | B40: Pilar III | C40: Bens Imóveis - Output | D40: 2. Campo | E40: cd_imv_out_trz_cred_prc | F40: cempresp | G40: =VLOOKUP(A40,Plano_V3!$A$27:$G$583,7,0) -> 1. Concluído | H40: 1. Concluído | I40: 26/07/2024: Conclusão de testes ao universo MUG e GP. Adjudicados fora de âmbito deste projeto. | J40: =IF(VLOOKUP(A40,'Aux - pivots1'!$A:$E,3,0)=0, "",VLOOKUP(A40,'Aux - pivots1'!$A:$E,3,0)) | K40: =IF(VLOOKUP(A40,'Aux - pivots1'!$A:$E,4,0)=0, "",VLOOKUP(A40,'Aux - pivots1'!$A:$E,4,0)) | L40: =IF(VLOOKUP(A40,'Aux - pivots1'!$A:$E,5,0)=0, "",VLOOKUP(A40,'Aux - pivots1'!$A:$E,5,0))
A41: =E41&F41 -> cd_imv_out_trz_cred_prcckbalcao | B41: Pilar III | C41: Bens Imóveis - Output | D41: 2. Campo | E41: cd_imv_out_trz_cred_prc | F41: ckbalcao | G41: =VLOOKUP(A41,Plano_V3!$A$27:$G$583,7,0) -> 1. Concluído | H41: 1. Concluído | I41: 26/07/2024: Conclusão de testes ao universo MUG e GP. Adjudicados fora de âmbito deste projeto. | J41: =IF(VLOOKUP(A41,'Aux - pivots1'!$A:$E,3,0)=0, "",VLOOKUP(A41,'Aux - pivots1'!$A:$E,3,0)) | K41: =IF(VLOOKUP(A41,'Aux - pivots1'!$A:$E,4,0)=0, "",VLOOKUP(A41,'Aux - pivots1'!$A:$E,4,0)) | L41: =IF(VLOOKUP(A41,'Aux - pivots1'!$A:$E,5,0)=0, "",VLOOKUP(A41,'Aux - pivots1'!$A:$E,5,0))
A42: =E42&F42 -> cd_imv_out_trz_cred_prcckbalres | B42: Pilar III | C42: Bens Imóveis - Output | D42: 2. Campo | E42: cd_imv_out_trz_cred_prc | F42: ckbalres | G42: =VLOOKUP(A42,Plano_V3!$A$27:$G$583,7,0) -> 1. Concluído | H42: 1. Concluído | I42: 26/07/2024: Conclusão de testes ao universo MUG e GP. Adjudicados fora de âmbito deste projeto. | J42: =IF(VLOOKUP(A42,'Aux - pivots1'!$A:$E,3,0)=0, "",VLOOKUP(A42,'Aux - pivots1'!$A:$E,3,0)) | K42: =IF(VLOOKUP(A42,'Aux - pivots1'!$A:$E,4,0)=0, "",VLOOKUP(A42,'Aux - pivots1'!$A:$E,4,0)) | L42: =IF(VLOOKUP(A42,'Aux - pivots1'!$A:$E,5,0)=0, "",VLOOKUP(A42,'Aux - pivots1'!$A:$E,5,0))
A43: =E43&F43 -> cd_imv_out_trz_cred_prcckctares | B43: Pilar III | C43: Bens Imóveis - Output | D43: 2. Campo | E43: cd_imv_out_trz_cred_prc | F43: ckctares | G43: =VLOOKUP(A43,Plano_V3!$A$27:$G$583,7,0) -> 1. Concluído | H43: 1. Concluído | I43: 26/07/2024: Conclusão de testes ao universo MUG e GP. Adjudicados fora de âmbito deste projeto. | J43: =IF(VLOOKUP(A43,'Aux - pivots1'!$A:$E,3,0)=0, "",VLOOKUP(A43,'Aux - pivots1'!$A:$E,3,0)) | K43: =IF(VLOOKUP(A43,'Aux - pivots1'!$A:$E,4,0)=0, "",VLOOKUP(A43,'Aux - pivots1'!$A:$E,4,0)) | L43: =IF(VLOOKUP(A43,'Aux - pivots1'!$A:$E,5,0)=0, "",VLOOKUP(A43,'Aux - pivots1'!$A:$E,5,0))
A44: =E44&F44 -> cd_imv_out_trz_cred_prccknumcta | B44: Pilar III | C44: Bens Imóveis - Output | D44: 2. Campo | E44: cd_imv_out_trz_cred_prc | F44: cknumcta | G44: =VLOOKUP(A44,Plano_V3!$A$27:$G$583,7,0) -> 1. Concluído | H44: 1. Concluído | I44: 26/07/2024: Conclusão de testes ao universo MUG e GP. Adjudicados fora de âmbito deste projeto. | J44: =IF(VLOOKUP(A44,'Aux - pivots1'!$A:$E,3,0)=0, "",VLOOKUP(A44,'Aux - pivots1'!$A:$E,3,0)) | K44: =IF(VLOOKUP(A44,'Aux - pivots1'!$A:$E,4,0)=0, "",VLOOKUP(A44,'Aux - pivots1'!$A:$E,4,0)) | L44: =IF(VLOOKUP(A44,'Aux - pivots1'!$A:$E,5,0)=0, "",VLOOKUP(A44,'Aux - pivots1'!$A:$E,5,0))
A45: =E45&F45 -> cd_imv_out_trz_cred_prcckrefresp | B45: Pilar III | C45: Bens Imóveis - Output | D45: 2. Campo | E45: cd_imv_out_trz_cred_prc | F45: ckrefresp | G45: =VLOOKUP(A45,Plano_V3!$A$27:$G$583,7,0) -> 1. Concluído | H45: 1. Concluído | I45: 26/07/2024: Conclusão de testes ao universo MUG e GP. Adjudicados fora de âmbito deste projeto. | J45: =IF(VLOOKUP(A45,'Aux - pivots1'!$A:$E,3,0)=0, "",VLOOKUP(A45,'Aux - pivots1'!$A:$E,3,0)) | K45: =IF(VLOOKUP(A45,'Aux - pivots1'!$A:$E,4,0)=0, "",VLOOKUP(A45,'Aux - pivots1'!$A:$E,4,0)) | L45: =IF(VLOOKUP(A45,'Aux - pivots1'!$A:$E,5,0)=0, "",VLOOKUP(A45,'Aux - pivots1'!$A:$E,5,0))
A46: =E46&F46 -> cd_imv_out_trz_cred_prccod_fnld | B46: Pilar III | C46: Bens Imóveis - Output | D46: 2. Campo | E46: cd_imv_out_trz_cred_prc | F46: cod_fnld | G46: =VLOOKUP(A46,Plano_V3!$A$27:$G$583,7,0) -> 1. Concluído | H46: 1. Concluído | J46: =IF(VLOOKUP(A46,'Aux - pivots1'!$A:$E,3,0)=0, "",VLOOKUP(A46,'Aux - pivots1'!$A:$E,3,0)) | K46: =IF(VLOOKUP(A46,'Aux - pivots1'!$A:$E,4,0)=0, "",VLOOKUP(A46,'Aux - pivots1'!$A:$E,4,0)) | L46: =IF(VLOOKUP(A46,'Aux - pivots1'!$A:$E,5,0)=0, "",VLOOKUP(A46,'Aux - pivots1'!$A:$E,5,0))
A47: =E47&F47 -> cd_imv_out_trz_cred_prccod_ocupacao | B47: Pilar III | C47: Bens Imóveis - Output | D47: 2. Campo | E47: cd_imv_out_trz_cred_prc | F47: cod_ocupacao | G47: =VLOOKUP(A47,Plano_V3!$A$27:$G$583,7,0) -> 1. Concluído | H47: 1. Concluído | J47: =IF(VLOOKUP(A47,'Aux - pivots1'!$A:$E,3,0)=0, "",VLOOKUP(A47,'Aux - pivots1'!$A:$E,3,0)) | K47: =IF(VLOOKUP(A47,'Aux - pivots1'!$A:$E,4,0)=0, "",VLOOKUP(A47,'Aux - pivots1'!$A:$E,4,0)) | L47: =IF(VLOOKUP(A47,'Aux - pivots1'!$A:$E,5,0)=0, "",VLOOKUP(A47,'Aux - pivots1'!$A:$E,5,0))
A48: =E48&F48 -> cd_imv_out_trz_cred_prccod_prd_resp | B48: Pilar III | C48: Bens Imóveis - Output | D48: 2. Campo | E48: cd_imv_out_trz_cred_prc | F48: cod_prd_resp | G48: =VLOOKUP(A48,Plano_V3!$A$27:$G$583,7,0) -> 1. Concluído | H48: 1. Concluído | J48: =IF(VLOOKUP(A48,'Aux - pivots1'!$A:$E,3,0)=0, "",VLOOKUP(A48,'Aux - pivots1'!$A:$E,3,0)) | K48: =IF(VLOOKUP(A48,'Aux - pivots1'!$A:$E,4,0)=0, "",VLOOKUP(A48,'Aux - pivots1'!$A:$E,4,0)) | L48: =IF(VLOOKUP(A48,'Aux - pivots1'!$A:$E,5,0)=0, "",VLOOKUP(A48,'Aux - pivots1'!$A:$E,5,0))
A49: =E49&F49 -> cd_imv_out_trz_cred_prccod_sit | B49: Pilar III | C49: Bens Imóveis - Output | D49: 2. Campo | E49: cd_imv_out_trz_cred_prc | F49: cod_sit | G49: =VLOOKUP(A49,Plano_V3!$A$27:$G$583,7,0) -> 0. Cancelado | H49: 0. Cancelado | I49: 19/07/2024: Campo eliminado do Modelo para garantir coerência com MUG | J49: =IF(VLOOKUP(A49,'Aux - pivots1'!$A:$E,3,0)=0, "",VLOOKUP(A49,'Aux - pivots1'!$A:$E,3,0)) | K49: =IF(VLOOKUP(A49,'Aux - pivots1'!$A:$E,4,0)=0, "",VLOOKUP(A49,'Aux - pivots1'!$A:$E,4,0)) | L49: =IF(VLOOKUP(A49,'Aux - pivots1'!$A:$E,5,0)=0, "",VLOOKUP(A49,'Aux - pivots1'!$A:$E,5,0))
A50: =E50&F50 -> cd_imv_out_trz_cred_prccod_sprd_resp | B50: Pilar III | C50: Bens Imóveis - Output | D50: 2. Campo | E50: cd_imv_out_trz_cred_prc | F50: cod_sprd_resp | G50: =VLOOKUP(A50,Plano_V3!$A$27:$G$583,7,0) -> 1. Concluído | H50: 1. Concluído | J50: =IF(VLOOKUP(A50,'Aux - pivots1'!$A:$E,3,0)=0, "",VLOOKUP(A50,'Aux - pivots1'!$A:$E,3,0)) | K50: =IF(VLOOKUP(A50,'Aux - pivots1'!$A:$E,4,0)=0, "",VLOOKUP(A50,'Aux - pivots1'!$A:$E,4,0)) | L50: =IF(VLOOKUP(A50,'Aux - pivots1'!$A:$E,5,0)=0, "",VLOOKUP(A50,'Aux - pivots1'!$A:$E,5,0))
A51: =E51&F51 -> cd_imv_out_trz_cred_prccomp_id_gar | B51: Pilar III | C51: Bens Imóveis - Output | D51: 2. Campo | E51: cd_imv_out_trz_cred_prc | F51: comp_id_gar | G51: =VLOOKUP(A51,Plano_V3!$A$27:$G$583,7,0) -> 1. Concluído | H51: 1. Concluído | J51: =IF(VLOOKUP(A51,'Aux - pivots1'!$A:$E,3,0)=0, "",VLOOKUP(A51,'Aux - pivots1'!$A:$E,3,0)) | K51: =IF(VLOOKUP(A51,'Aux - pivots1'!$A:$E,4,0)=0, "",VLOOKUP(A51,'Aux - pivots1'!$A:$E,4,0)) | L51: =IF(VLOOKUP(A51,'Aux - pivots1'!$A:$E,5,0)=0, "",VLOOKUP(A51,'Aux - pivots1'!$A:$E,5,0))
A52: =E52&F52 -> cd_imv_out_trz_cred_prcdata_fim | B52: Pilar III | C52: Bens Imóveis - Output | D52: 2. Campo | E52: cd_imv_out_trz_cred_prc | F52: data_fim | G52: =VLOOKUP(A52,Plano_V3!$A$27:$G$583,7,0) -> 1. Concluído | H52: 1. Concluído | J52: =IF(VLOOKUP(A52,'Aux - pivots1'!$A:$E,3,0)=0, "",VLOOKUP(A52,'Aux - pivots1'!$A:$E,3,0)) | K52: =IF(VLOOKUP(A52,'Aux - pivots1'!$A:$E,4,0)=0, "",VLOOKUP(A52,'Aux - pivots1'!$A:$E,4,0)) | L52: =IF(VLOOKUP(A52,'Aux - pivots1'!$A:$E,5,0)=0, "",VLOOKUP(A52,'Aux - pivots1'!$A:$E,5,0))
A53: =E53&F53 -> cd_imv_out_trz_cred_prcdata_inicio | B53: Pilar III | C53: Bens Imóveis - Output | D53: 2. Campo | E53: cd_imv_out_trz_cred_prc | F53: data_inicio | G53: =VLOOKUP(A53,Plano_V3!$A$27:$G$583,7,0) -> 1. Concluído | H53: 1. Concluído | J53: =IF(VLOOKUP(A53,'Aux - pivots1'!$A:$E,3,0)=0, "",VLOOKUP(A53,'Aux - pivots1'!$A:$E,3,0)) | K53: =IF(VLOOKUP(A53,'Aux - pivots1'!$A:$E,4,0)=0, "",VLOOKUP(A53,'Aux - pivots1'!$A:$E,4,0)) | L53: =IF(VLOOKUP(A53,'Aux - pivots1'!$A:$E,5,0)=0, "",VLOOKUP(A53,'Aux - pivots1'!$A:$E,5,0))
A54: =E54&F54 -> cd_imv_out_trz_cred_prcdata_vcmt | B54: Pilar III | C54: Bens Imóveis - Output | D54: 2. Campo | E54: cd_imv_out_trz_cred_prc | F54: data_vcmt | G54: =VLOOKUP(A54,Plano_V3!$A$27:$G$583,7,0) -> 1. Concluído | H54: 1. Concluído | J54: =IF(VLOOKUP(A54,'Aux - pivots1'!$A:$E,3,0)=0, "",VLOOKUP(A54,'Aux - pivots1'!$A:$E,3,0)) | K54: =IF(VLOOKUP(A54,'Aux - pivots1'!$A:$E,4,0)=0, "",VLOOKUP(A54,'Aux - pivots1'!$A:$E,4,0)) | L54: =IF(VLOOKUP(A54,'Aux - pivots1'!$A:$E,5,0)=0, "",VLOOKUP(A54,'Aux - pivots1'!$A:$E,5,0))
A55: =E55&F55 -> cd_imv_out_trz_cred_prcidetgar | B55: Pilar III | C55: Bens Imóveis - Output | D55: 2. Campo | E55: cd_imv_out_trz_cred_prc | F55: idetgar | G55: =VLOOKUP(A55,Plano_V3!$A$27:$G$583,7,0) -> 0. Cancelado | H55: 0. Cancelado | I55: 19/07/2024: Campo eliminado do Modelo para garantir coerência com MUG | J55: =IF(VLOOKUP(A55,'Aux - pivots1'!$A:$E,3,0)=0, "",VLOOKUP(A55,'Aux - pivots1'!$A:$E,3,0)) | K55: =IF(VLOOKUP(A55,'Aux - pivots1'!$A:$E,4,0)=0, "",VLOOKUP(A55,'Aux - pivots1'!$A:$E,4,0)) | L55: =IF(VLOOKUP(A55,'Aux - pivots1'!$A:$E,5,0)=0, "",VLOOKUP(A55,'Aux - pivots1'!$A:$E,5,0))
A56: =E56&F56 -> cd_imv_out_trz_cred_prcnum_prop | B56: Pilar III | C56: Bens Imóveis - Output | D56: 2. Campo | E56: cd_imv_out_trz_cred_prc | F56: num_prop | G56: =VLOOKUP(A56,Plano_V3!$A$27:$G$583,7,0) -> 0. Cancelado | H56: 0. Cancelado | I56: 19/07/2024: Campo eliminado do Modelo para garantir coerência com MUG | J56: =IF(VLOOKUP(A56,'Aux - pivots1'!$A:$E,3,0)=0, "",VLOOKUP(A56,'Aux - pivots1'!$A:$E,3,0)) | K56: =IF(VLOOKUP(A56,'Aux - pivots1'!$A:$E,4,0)=0, "",VLOOKUP(A56,'Aux - pivots1'!$A:$E,4,0)) | L56: =IF(VLOOKUP(A56,'Aux - pivots1'!$A:$E,5,0)=0, "",VLOOKUP(A56,'Aux - pivots1'!$A:$E,5,0))
A57: =E57&F57 -> cd_imv_out_trz_cred_prcorigem | B57: Pilar III | C57: Bens Imóveis - Output | D57: 2. Campo | E57: cd_imv_out_trz_cred_prc | F57: origem | G57: =VLOOKUP(A57,Plano_V3!$A$27:$G$583,7,0) -> 1. Concluído | H57: 1. Concluído | J57: =IF(VLOOKUP(A57,'Aux - pivots1'!$A:$E,3,0)=0, "",VLOOKUP(A57,'Aux - pivots1'!$A:$E,3,0)) | K57: =IF(VLOOKUP(A57,'Aux - pivots1'!$A:$E,4,0)=0, "",VLOOKUP(A57,'Aux - pivots1'!$A:$E,4,0)) | L57: =IF(VLOOKUP(A57,'Aux - pivots1'!$A:$E,5,0)=0, "",VLOOKUP(A57,'Aux - pivots1'!$A:$E,5,0))
A58: =E58&F58 -> cd_imv_out_trz_cred_prcref_date | B58: Pilar III | C58: Bens Imóveis - Output | D58: 2. Campo | E58: cd_imv_out_trz_cred_prc | F58: ref_date | G58: =VLOOKUP(A58,Plano_V3!$A$27:$G$583,7,0) -> 1. Concluído | H58: 1. Concluído | J58: =IF(VLOOKUP(A58,'Aux - pivots1'!$A:$E,3,0)=0, "",VLOOKUP(A58,'Aux - pivots1'!$A:$E,3,0)) | K58: =IF(VLOOKUP(A58,'Aux - pivots1'!$A:$E,4,0)=0, "",VLOOKUP(A58,'Aux - pivots1'!$A:$E,4,0)) | L58: =IF(VLOOKUP(A58,'Aux - pivots1'!$A:$E,5,0)=0, "",VLOOKUP(A58,'Aux - pivots1'!$A:$E,5,0))
A59: =E59&F59 -> cd_imv_out_trz_prc_bens_imvn.a. | B59: Pilar III | C59: Bens Imóveis - Output | D59: 1. Universo | E59: cd_imv_out_trz_prc_bens_imv | F59: n.a. | G59: =VLOOKUP(A59,Plano_V3!$A$27:$G$583,7,0) -> 1. Concluído | H59: 1. Concluído | J59: =IF(VLOOKUP(A59,'Aux - pivots1'!$A:$E,3,0)=0, "",VLOOKUP(A59,'Aux - pivots1'!$A:$E,3,0)) | K59: =IF(VLOOKUP(A59,'Aux - pivots1'!$A:$E,4,0)=0, "",VLOOKUP(A59,'Aux - pivots1'!$A:$E,4,0)) | L59: =IF(VLOOKUP(A59,'Aux - pivots1'!$A:$E,5,0)=0, "",VLOOKUP(A59,'Aux - pivots1'!$A:$E,5,0))
A60: =E60&F60 -> cd_imv_out_trz_prc_bens_imvcempbem | B60: Pilar III | C60: Bens Imóveis - Output | D60: 2. Campo | E60: cd_imv_out_trz_prc_bens_imv | F60: cempbem | G60: =VLOOKUP(A60,Plano_V3!$A$27:$G$583,7,0) -> 1. Concluído | H60: 1. Concluído | J60: =IF(VLOOKUP(A60,'Aux - pivots1'!$A:$E,3,0)=0, "",VLOOKUP(A60,'Aux - pivots1'!$A:$E,3,0)) | K60: =IF(VLOOKUP(A60,'Aux - pivots1'!$A:$E,4,0)=0, "",VLOOKUP(A60,'Aux - pivots1'!$A:$E,4,0)) | L60: =IF(VLOOKUP(A60,'Aux - pivots1'!$A:$E,5,0)=0, "",VLOOKUP(A60,'Aux - pivots1'!$A:$E,5,0))
A61: =E61&F61 -> cd_imv_out_trz_prc_bens_imvcempresa | B61: Pilar III | C61: Bens Imóveis - Output | D61: 2. Campo | E61: cd_imv_out_trz_prc_bens_imv | F61: cempresa | G61: =VLOOKUP(A61,Plano_V3!$A$27:$G$583,7,0) -> 1. Concluído | H61: 1. Concluído | I61: 26/07/2024: Conclusão de testes ao universo MUG e GP. Adjudicados fora de âmbito deste projeto. | J61: =IF(VLOOKUP(A61,'Aux - pivots1'!$A:$E,3,0)=0, "",VLOOKUP(A61,'Aux - pivots1'!$A:$E,3,0)) | K61: =IF(VLOOKUP(A61,'Aux - pivots1'!$A:$E,4,0)=0, "",VLOOKUP(A61,'Aux - pivots1'!$A:$E,4,0)) | L61: =IF(VLOOKUP(A61,'Aux - pivots1'!$A:$E,5,0)=0, "",VLOOKUP(A61,'Aux - pivots1'!$A:$E,5,0))
A62: =E62&F62 -> cd_imv_out_trz_prc_bens_imvckbalbem | B62: Pilar III | C62: Bens Imóveis - Output | D62: 2. Campo | E62: cd_imv_out_trz_prc_bens_imv | F62: ckbalbem | G62: =VLOOKUP(A62,Plano_V3!$A$27:$G$583,7,0) -> 1. Concluído | H62: 1. Concluído | I62: 26/07/2024: Conclusão de testes ao universo MUG e GP. Adjudicados fora de âmbito deste projeto. | J62: =IF(VLOOKUP(A62,'Aux - pivots1'!$A:$E,3,0)=0, "",VLOOKUP(A62,'Aux - pivots1'!$A:$E,3,0)) | K62: =IF(VLOOKUP(A62,'Aux - pivots1'!$A:$E,4,0)=0, "",VLOOKUP(A62,'Aux - pivots1'!$A:$E,4,0)) | L62: =IF(VLOOKUP(A62,'Aux - pivots1'!$A:$E,5,0)=0, "",VLOOKUP(A62,'Aux - pivots1'!$A:$E,5,0))
A63: =E63&F63 -> cd_imv_out_trz_prc_bens_imvckbalcao | B63: Pilar III | C63: Bens Imóveis - Output | D63: 2. Campo | E63: cd_imv_out_trz_prc_bens_imv | F63: ckbalcao | G63: =VLOOKUP(A63,Plano_V3!$A$27:$G$583,7,0) -> 1. Concluído | H63: 1. Concluído | I63: 26/07/2024: Conclusão de testes ao universo MUG e GP. Adjudicados fora de âmbito deste projeto. | J63: =IF(VLOOKUP(A63,'Aux - pivots1'!$A:$E,3,0)=0, "",VLOOKUP(A63,'Aux - pivots1'!$A:$E,3,0)) | K63: =IF(VLOOKUP(A63,'Aux - pivots1'!$A:$E,4,0)=0, "",VLOOKUP(A63,'Aux - pivots1'!$A:$E,4,0)) | L63: =IF(VLOOKUP(A63,'Aux - pivots1'!$A:$E,5,0)=0, "",VLOOKUP(A63,'Aux - pivots1'!$A:$E,5,0))
A64: =E64&F64 -> cd_imv_out_trz_prc_bens_imvckctabem | B64: Pilar III | C64: Bens Imóveis - Output | D64: 2. Campo | E64: cd_imv_out_trz_prc_bens_imv | F64: ckctabem | G64: =VLOOKUP(A64,Plano_V3!$A$27:$G$583,7,0) -> 1. Concluído | H64: 1. Concluído | I64: 26/07/2024: Conclusão de testes ao universo MUG e GP. Adjudicados fora de âmbito deste projeto. | J64: =IF(VLOOKUP(A64,'Aux - pivots1'!$A:$E,3,0)=0, "",VLOOKUP(A64,'Aux - pivots1'!$A:$E,3,0)) | K64: =IF(VLOOKUP(A64,'Aux - pivots1'!$A:$E,4,0)=0, "",VLOOKUP(A64,'Aux - pivots1'!$A:$E,4,0)) | L64: =IF(VLOOKUP(A64,'Aux - pivots1'!$A:$E,5,0)=0, "",VLOOKUP(A64,'Aux - pivots1'!$A:$E,5,0))
A65: =E65&F65 -> cd_imv_out_trz_prc_bens_imvcknumcta | B65: Pilar III | C65: Bens Imóveis - Output | D65: 2. Campo | E65: cd_imv_out_trz_prc_bens_imv | F65: cknumcta | G65: =VLOOKUP(A65,Plano_V3!$A$27:$G$583,7,0) -> 1. Concluído | H65: 1. Concluído | I65: 26/07/2024: Conclusão de testes ao universo MUG e GP. Adjudicados fora de âmbito deste projeto. | J65: =IF(VLOOKUP(A65,'Aux - pivots1'!$A:$E,3,0)=0, "",VLOOKUP(A65,'Aux - pivots1'!$A:$E,3,0)) | K65: =IF(VLOOKUP(A65,'Aux - pivots1'!$A:$E,4,0)=0, "",VLOOKUP(A65,'Aux - pivots1'!$A:$E,4,0)) | L65: =IF(VLOOKUP(A65,'Aux - pivots1'!$A:$E,5,0)=0, "",VLOOKUP(A65,'Aux - pivots1'!$A:$E,5,0))
A66: =E66&F66 -> cd_imv_out_trz_prc_bens_imvckrefbem | B66: Pilar III | C66: Bens Imóveis - Output | D66: 2. Campo | E66: cd_imv_out_trz_prc_bens_imv | F66: ckrefbem | G66: =VLOOKUP(A66,Plano_V3!$A$27:$G$583,7,0) -> 1. Concluído | H66: 1. Concluído | J66: =IF(VLOOKUP(A66,'Aux - pivots1'!$A:$E,3,0)=0, "",VLOOKUP(A66,'Aux - pivots1'!$A:$E,3,0)) | K66: =IF(VLOOKUP(A66,'Aux - pivots1'!$A:$E,4,0)=0, "",VLOOKUP(A66,'Aux - pivots1'!$A:$E,4,0)) | L66: =IF(VLOOKUP(A66,'Aux - pivots1'!$A:$E,5,0)=0, "",VLOOKUP(A66,'Aux - pivots1'!$A:$E,5,0))
A67: =E67&F67 -> cd_imv_out_trz_prc_bens_imvcomp_id_gar | B67: Pilar III | C67: Bens Imóveis - Output | D67: 2. Campo | E67: cd_imv_out_trz_prc_bens_imv | F67: comp_id_gar | G67: =VLOOKUP(A67,Plano_V3!$A$27:$G$583,7,0) -> 1. Concluído | H67: 1. Concluído | J67: =IF(VLOOKUP(A67,'Aux - pivots1'!$A:$E,3,0)=0, "",VLOOKUP(A67,'Aux - pivots1'!$A:$E,3,0)) | K67: =IF(VLOOKUP(A67,'Aux - pivots1'!$A:$E,4,0)=0, "",VLOOKUP(A67,'Aux - pivots1'!$A:$E,4,0)) | L67: =IF(VLOOKUP(A67,'Aux - pivots1'!$A:$E,5,0)=0, "",VLOOKUP(A67,'Aux - pivots1'!$A:$E,5,0))
A68: =E68&F68 -> cd_imv_out_trz_prc_bens_imvdata_assc | B68: Pilar III | C68: Bens Imóveis - Output | D68: 2. Campo | E68: cd_imv_out_trz_prc_bens_imv | F68: data_assc | G68: =VLOOKUP(A68,Plano_V3!$A$27:$G$583,7,0) -> 0. Cancelado | H68: 0. Cancelado | I68: 19/07/2024: Campo eliminado do Modelo para garantir coerência com MUG | J68: =IF(VLOOKUP(A68,'Aux - pivots1'!$A:$E,3,0)=0, "",VLOOKUP(A68,'Aux - pivots1'!$A:$E,3,0)) | K68: =IF(VLOOKUP(A68,'Aux - pivots1'!$A:$E,4,0)=0, "",VLOOKUP(A68,'Aux - pivots1'!$A:$E,4,0)) | L68: =IF(VLOOKUP(A68,'Aux - pivots1'!$A:$E,5,0)=0, "",VLOOKUP(A68,'Aux - pivots1'!$A:$E,5,0))
A69: =E69&F69 -> cd_imv_out_trz_prc_bens_imvflg_adj | B69: Pilar III | C69: Bens Imóveis - Output | D69: 2. Campo | E69: cd_imv_out_trz_prc_bens_imv | F69: flg_adj | G69: =VLOOKUP(A69,Plano_V3!$A$27:$G$583,7,0) -> 1. Concluído | H69: 1. Concluído | J69: =IF(VLOOKUP(A69,'Aux - pivots1'!$A:$E,3,0)=0, "",VLOOKUP(A69,'Aux - pivots1'!$A:$E,3,0)) | K69: =IF(VLOOKUP(A69,'Aux - pivots1'!$A:$E,4,0)=0, "",VLOOKUP(A69,'Aux - pivots1'!$A:$E,4,0)) | L69: =IF(VLOOKUP(A69,'Aux - pivots1'!$A:$E,5,0)=0, "",VLOOKUP(A69,'Aux - pivots1'!$A:$E,5,0))
A70: =E70&F70 -> cd_imv_out_trz_prc_bens_imvflg_col | B70: Pilar III | C70: Bens Imóveis - Output | D70: 2. Campo | E70: cd_imv_out_trz_prc_bens_imv | F70: flg_col | G70: =VLOOKUP(A70,Plano_V3!$A$27:$G$583,7,0) -> 1. Concluído | H70: 1. Concluído | J70: =IF(VLOOKUP(A70,'Aux - pivots1'!$A:$E,3,0)=0, "",VLOOKUP(A70,'Aux - pivots1'!$A:$E,3,0)) | K70: =IF(VLOOKUP(A70,'Aux - pivots1'!$A:$E,4,0)=0, "",VLOOKUP(A70,'Aux - pivots1'!$A:$E,4,0)) | L70: =IF(VLOOKUP(A70,'Aux - pivots1'!$A:$E,5,0)=0, "",VLOOKUP(A70,'Aux - pivots1'!$A:$E,5,0))
A71: =E71&F71 -> cd_imv_out_trz_prc_bens_imvflg_fin | B71: Pilar III | C71: Bens Imóveis - Output | D71: 2. Campo | E71: cd_imv_out_trz_prc_bens_imv | F71: flg_fin | G71: =VLOOKUP(A71,Plano_V3!$A$27:$G$583,7,0) -> 1. Concluído | H71: 1. Concluído | J71: =IF(VLOOKUP(A71,'Aux - pivots1'!$A:$E,3,0)=0, "",VLOOKUP(A71,'Aux - pivots1'!$A:$E,3,0)) | K71: =IF(VLOOKUP(A71,'Aux - pivots1'!$A:$E,4,0)=0, "",VLOOKUP(A71,'Aux - pivots1'!$A:$E,4,0)) | L71: =IF(VLOOKUP(A71,'Aux - pivots1'!$A:$E,5,0)=0, "",VLOOKUP(A71,'Aux - pivots1'!$A:$E,5,0))
A72: =E72&F72 -> cd_imv_out_trz_prc_bens_imvflg_pro | B72: Pilar III | C72: Bens Imóveis - Output | D72: 2. Campo | E72: cd_imv_out_trz_prc_bens_imv | F72: flg_pro | G72: =VLOOKUP(A72,Plano_V3!$A$27:$G$583,7,0) -> 1. Concluído | H72: 1. Concluído | J72: =IF(VLOOKUP(A72,'Aux - pivots1'!$A:$E,3,0)=0, "",VLOOKUP(A72,'Aux - pivots1'!$A:$E,3,0)) | K72: =IF(VLOOKUP(A72,'Aux - pivots1'!$A:$E,4,0)=0, "",VLOOKUP(A72,'Aux - pivots1'!$A:$E,4,0)) | L72: =IF(VLOOKUP(A72,'Aux - pivots1'!$A:$E,5,0)=0, "",VLOOKUP(A72,'Aux - pivots1'!$A:$E,5,0))
A73: =E73&F73 -> cd_imv_out_trz_prc_bens_imvorigem | B73: Pilar III | C73: Bens Imóveis - Output | D73: 2. Campo | E73: cd_imv_out_trz_prc_bens_imv | F73: origem | G73: =VLOOKUP(A73,Plano_V3!$A$27:$G$583,7,0) -> 1. Concluído | H73: 1. Concluído | J73: =IF(VLOOKUP(A73,'Aux - pivots1'!$A:$E,3,0)=0, "",VLOOKUP(A73,'Aux - pivots1'!$A:$E,3,0)) | K73: =IF(VLOOKUP(A73,'Aux - pivots1'!$A:$E,4,0)=0, "",VLOOKUP(A73,'Aux - pivots1'!$A:$E,4,0)) | L73: =IF(VLOOKUP(A73,'Aux - pivots1'!$A:$E,5,0)=0, "",VLOOKUP(A73,'Aux - pivots1'!$A:$E,5,0))
A74: =E74&F74 -> cd_imv_out_trz_prc_bens_imvref_date | B74: Pilar III | C74: Bens Imóveis - Output | D74: 2. Campo | E74: cd_imv_out_trz_prc_bens_imv | F74: ref_date | G74: =VLOOKUP(A74,Plano_V3!$A$27:$G$583,7,0) -> 1. Concluído | H74: 1. Concluído | J74: =IF(VLOOKUP(A74,'Aux - pivots1'!$A:$E,3,0)=0, "",VLOOKUP(A74,'Aux - pivots1'!$A:$E,3,0)) | K74: =IF(VLOOKUP(A74,'Aux - pivots1'!$A:$E,4,0)=0, "",VLOOKUP(A74,'Aux - pivots1'!$A:$E,4,0)) | L74: =IF(VLOOKUP(A74,'Aux - pivots1'!$A:$E,5,0)=0, "",VLOOKUP(A74,'Aux - pivots1'!$A:$E,5,0))
A75: =E75&F75 -> cd_imv_out_bensn.a. | B75: Pilar III | C75: Bens Imóveis - Output | D75: 1. Universo | E75: cd_imv_out_bens | F75: n.a. | G75: =VLOOKUP(A75,Plano_V3!$A$27:$G$583,7,0) -> 1. Concluído | H75: 1. Concluído | J75: =IF(VLOOKUP(A75,'Aux - pivots1'!$A:$E,3,0)=0, "",VLOOKUP(A75,'Aux - pivots1'!$A:$E,3,0)) | K75: =IF(VLOOKUP(A75,'Aux - pivots1'!$A:$E,4,0)=0, "",VLOOKUP(A75,'Aux - pivots1'!$A:$E,4,0)) | L75: =IF(VLOOKUP(A75,'Aux - pivots1'!$A:$E,5,0)=0, "",VLOOKUP(A75,'Aux - pivots1'!$A:$E,5,0))
A76: =E76&F76 -> cd_imv_out_bensano_construcao | B76: Pilar III | C76: Bens Imóveis - Output | D76: 2. Campo | E76: cd_imv_out_bens | F76: ano_construcao | G76: =VLOOKUP(A76,Plano_V3!$A$27:$G$583,7,0) -> 1. Concluído | H76: 1. Concluído | J76: =IF(VLOOKUP(A76,'Aux - pivots1'!$A:$E,3,0)=0, "",VLOOKUP(A76,'Aux - pivots1'!$A:$E,3,0)) | K76: =IF(VLOOKUP(A76,'Aux - pivots1'!$A:$E,4,0)=0, "",VLOOKUP(A76,'Aux - pivots1'!$A:$E,4,0)) | L76: =IF(VLOOKUP(A76,'Aux - pivots1'!$A:$E,5,0)=0, "",VLOOKUP(A76,'Aux - pivots1'!$A:$E,5,0))
A77: =E77&F77 -> cd_imv_out_bensarea_util | B77: Pilar III | C77: Bens Imóveis - Output | D77: 2. Campo | E77: cd_imv_out_bens | F77: area_util | G77: =VLOOKUP(A77,Plano_V3!$A$27:$G$583,7,0) -> 1. Concluído | H77: 1. Concluído | J77: =IF(VLOOKUP(A77,'Aux - pivots1'!$A:$E,3,0)=0, "",VLOOKUP(A77,'Aux - pivots1'!$A:$E,3,0)) | K77: =IF(VLOOKUP(A77,'Aux - pivots1'!$A:$E,4,0)=0, "",VLOOKUP(A77,'Aux - pivots1'!$A:$E,4,0)) | L77: =IF(VLOOKUP(A77,'Aux - pivots1'!$A:$E,5,0)=0, "",VLOOKUP(A77,'Aux - pivots1'!$A:$E,5,0))
A78: =E78&F78 -> cd_imv_out_benscempbem | B78: Pilar III | C78: Bens Imóveis - Output | D78: 2. Campo | E78: cd_imv_out_bens | F78: cempbem | G78: =VLOOKUP(A78,Plano_V3!$A$27:$G$583,7,0) -> 1. Concluído | H78: 1. Concluído | J78: =IF(VLOOKUP(A78,'Aux - pivots1'!$A:$E,3,0)=0, "",VLOOKUP(A78,'Aux - pivots1'!$A:$E,3,0)) | K78: =IF(VLOOKUP(A78,'Aux - pivots1'!$A:$E,4,0)=0, "",VLOOKUP(A78,'Aux - pivots1'!$A:$E,4,0)) | L78: =IF(VLOOKUP(A78,'Aux - pivots1'!$A:$E,5,0)=0, "",VLOOKUP(A78,'Aux - pivots1'!$A:$E,5,0))
A79: =E79&F79 -> cd_imv_out_bensckbalbem | B79: Pilar III | C79: Bens Imóveis - Output | D79: 2. Campo | E79: cd_imv_out_bens | F79: ckbalbem | G79: =VLOOKUP(A79,Plano_V3!$A$27:$G$583,7,0) -> 1. Concluído | H79: 1. Concluído | J79: =IF(VLOOKUP(A79,'Aux - pivots1'!$A:$E,3,0)=0, "",VLOOKUP(A79,'Aux - pivots1'!$A:$E,3,0)) | K79: =IF(VLOOKUP(A79,'Aux - pivots1'!$A:$E,4,0)=0, "",VLOOKUP(A79,'Aux - pivots1'!$A:$E,4,0)) | L79: =IF(VLOOKUP(A79,'Aux - pivots1'!$A:$E,5,0)=0, "",VLOOKUP(A79,'Aux - pivots1'!$A:$E,5,0))
A80: =E80&F80 -> cd_imv_out_bensckctabem | B80: Pilar III | C80: Bens Imóveis - Output | D80: 2. Campo | E80: cd_imv_out_bens | F80: ckctabem | G80: =VLOOKUP(A80,Plano_V3!$A$27:$G$583,7,0) -> 1. Concluído | H80: 1. Concluído | J80: =IF(VLOOKUP(A80,'Aux - pivots1'!$A:$E,3,0)=0, "",VLOOKUP(A80,'Aux - pivots1'!$A:$E,3,0)) | K80: =IF(VLOOKUP(A80,'Aux - pivots1'!$A:$E,4,0)=0, "",VLOOKUP(A80,'Aux - pivots1'!$A:$E,4,0)) | L80: =IF(VLOOKUP(A80,'Aux - pivots1'!$A:$E,5,0)=0, "",VLOOKUP(A80,'Aux - pivots1'!$A:$E,5,0))
... A83: =E83&F83 -> cd_imv_out_benscod_avl | B83: Pilar III | C83: Bens Imóveis - Output | D83: 2. Campo | E83: cd_imv_out_bens | F83: cod_avl | G83: =VLOOKUP(A83,Plano_V3!$A$27:$G$583,7,0) -> 1. Concluído | H83: 1. Concluído | J83: =IF(VLOOKUP(A83,'Aux - pivots1'!$A:$E,3,0)=0, "",VLOOKUP(A83,'Aux - pivots1'!$A:$E,3,0)) | K83: =IF(VLOOKUP(A83,'Aux - pivots1'!$A:$E,4,0)=0, "",VLOOKUP(A83,'Aux - pivots1'!$A:$E,4,0)) | L83: =IF(VLOOKUP(A83,'Aux - pivots1'!$A:$E,5,0)=0, "",VLOOKUP(A83,'Aux - pivots1'!$A:$E,5,0))
A84: =E84&F84 -> cd_imv_out_benscod_bem | B84: Pilar III | C84: Bens Imóveis - Output | D84: 2. Campo | E84: cd_imv_out_bens | F84: cod_bem | G84: =VLOOKUP(A84,Plano_V3!$A$27:$G$583,7,0) -> 0. Cancelado | H84: 0. Cancelado | I84: 19/07/2024: Campo eliminado do Modelo para garantir coerência com MUG | J84: =IF(VLOOKUP(A84,'Aux - pivots1'!$A:$E,3,0)=0, "",VLOOKUP(A84,'Aux - pivots1'!$A:$E,3,0)) | K84: =IF(VLOOKUP(A84,'Aux - pivots1'!$A:$E,4,0)=0, "",VLOOKUP(A84,'Aux - pivots1'!$A:$E,4,0)) | L84: =IF(VLOOKUP(A84,'Aux - pivots1'!$A:$E,5,0)=0, "",VLOOKUP(A84,'Aux - pivots1'!$A:$E,5,0))
A85: =E85&F85 -> cd_imv_out_benscod_disconf | B85: Pilar III | C85: Bens Imóveis - Output | D85: 2. Campo | E85: cd_imv_out_bens | F85: cod_disconf | G85: =VLOOKUP(A85,Plano_V3!$A$27:$G$583,7,0) -> 1. Concluído | H85: 1. Concluído | J85: =IF(VLOOKUP(A85,'Aux - pivots1'!$A:$E,3,0)=0, "",VLOOKUP(A85,'Aux - pivots1'!$A:$E,3,0)) | K85: =IF(VLOOKUP(A85,'Aux - pivots1'!$A:$E,4,0)=0, "",VLOOKUP(A85,'Aux - pivots1'!$A:$E,4,0)) | L85: =IF(VLOOKUP(A85,'Aux - pivots1'!$A:$E,5,0)=0, "",VLOOKUP(A85,'Aux - pivots1'!$A:$E,5,0))
A86: =E86&F86 -> cd_imv_out_benscod_fin_bem | B86: Pilar III | C86: Bens Imóveis - Output | D86: 2. Campo | E86: cd_imv_out_bens | F86: cod_fin_bem | G86: =VLOOKUP(A86,Plano_V3!$A$27:$G$583,7,0) -> 1. Concluído | H86: 1. Concluído | J86: =IF(VLOOKUP(A86,'Aux - pivots1'!$A:$E,3,0)=0, "",VLOOKUP(A86,'Aux - pivots1'!$A:$E,3,0)) | K86: =IF(VLOOKUP(A86,'Aux - pivots1'!$A:$E,4,0)=0, "",VLOOKUP(A86,'Aux - pivots1'!$A:$E,4,0)) | L86: =IF(VLOOKUP(A86,'Aux - pivots1'!$A:$E,5,0)=0, "",VLOOKUP(A86,'Aux - pivots1'!$A:$E,5,0))
A87: =E87&F87 -> cd_imv_out_benscod_idd_pred | B87: Pilar III | C87: Bens Imóveis - Output | D87: 2. Campo | E87: cd_imv_out_bens | F87: cod_idd_pred | G87: =VLOOKUP(A87,Plano_V3!$A$27:$G$583,7,0) -> 1. Concluído | H87: 1. Concluído | J87: =IF(VLOOKUP(A87,'Aux - pivots1'!$A:$E,3,0)=0, "",VLOOKUP(A87,'Aux - pivots1'!$A:$E,3,0)) | K87: =IF(VLOOKUP(A87,'Aux - pivots1'!$A:$E,4,0)=0, "",VLOOKUP(A87,'Aux - pivots1'!$A:$E,4,0)) | L87: =IF(VLOOKUP(A87,'Aux - pivots1'!$A:$E,5,0)=0, "",VLOOKUP(A87,'Aux - pivots1'!$A:$E,5,0))
A88: =E88&F88 -> cd_imv_out_benscod_morada | B88: Pilar III | C88: Bens Imóveis - Output | D88: 2. Campo | E88: cd_imv_out_bens | F88: cod_morada | G88: =VLOOKUP(A88,Plano_V3!$A$27:$G$583,7,0) -> 1. Concluído | H88: 1. Concluído | J88: =IF(VLOOKUP(A88,'Aux - pivots1'!$A:$E,3,0)=0, "",VLOOKUP(A88,'Aux - pivots1'!$A:$E,3,0)) | K88: =IF(VLOOKUP(A88,'Aux - pivots1'!$A:$E,4,0)=0, "",VLOOKUP(A88,'Aux - pivots1'!$A:$E,4,0)) | L88: =IF(VLOOKUP(A88,'Aux - pivots1'!$A:$E,5,0)=0, "",VLOOKUP(A88,'Aux - pivots1'!$A:$E,5,0))
A89: =E89&F89 -> cd_imv_out_benscod_pais | B89: Pilar III | C89: Bens Imóveis - Output | D89: 2. Campo | E89: cd_imv_out_bens | F89: cod_pais | G89: =VLOOKUP(A89,Plano_V3!$A$27:$G$583,7,0) -> 1. Concluído | H89: 1. Concluído | J89: =IF(VLOOKUP(A89,'Aux - pivots1'!$A:$E,3,0)=0, "",VLOOKUP(A89,'Aux - pivots1'!$A:$E,3,0)) | K89: =IF(VLOOKUP(A89,'Aux - pivots1'!$A:$E,4,0)=0, "",VLOOKUP(A89,'Aux - pivots1'!$A:$E,4,0)) | L89: =IF(VLOOKUP(A89,'Aux - pivots1'!$A:$E,5,0)=0, "",VLOOKUP(A89,'Aux - pivots1'!$A:$E,5,0))
A90: =E90&F90 -> cd_imv_out_benscod_post | B90: Pilar III | C90: Bens Imóveis - Output | D90: 2. Campo | E90: cd_imv_out_bens | F90: cod_post | G90: =VLOOKUP(A90,Plano_V3!$A$27:$G$583,7,0) -> 1. Concluído | H90: 1. Concluído | J90: =IF(VLOOKUP(A90,'Aux - pivots1'!$A:$E,3,0)=0, "",VLOOKUP(A90,'Aux - pivots1'!$A:$E,3,0)) | K90: =IF(VLOOKUP(A90,'Aux - pivots1'!$A:$E,4,0)=0, "",VLOOKUP(A90,'Aux - pivots1'!$A:$E,4,0)) | L90: =IF(VLOOKUP(A90,'Aux - pivots1'!$A:$E,5,0)=0, "",VLOOKUP(A90,'Aux - pivots1'!$A:$E,5,0))
A91: =E91&F91 -> cd_imv_out_benscod_tp_bem | B91: Pilar III | C91: Bens Imóveis - Output | D91: 2. Campo | E91: cd_imv_out_bens | F91: cod_tp_bem | G91: =VLOOKUP(A91,Plano_V3!$A$27:$G$583,7,0) -> 1. Concluído | H91: 1. Concluído | J91: =IF(VLOOKUP(A91,'Aux - pivots1'!$A:$E,3,0)=0, "",VLOOKUP(A91,'Aux - pivots1'!$A:$E,3,0)) | K91: =IF(VLOOKUP(A91,'Aux - pivots1'!$A:$E,4,0)=0, "",VLOOKUP(A91,'Aux - pivots1'!$A:$E,4,0)) | L91: =IF(VLOOKUP(A91,'Aux - pivots1'!$A:$E,5,0)=0, "",VLOOKUP(A91,'Aux - pivots1'!$A:$E,5,0))
A92: =E92&F92 -> cd_imv_out_bensdata_avl | B92: Pilar III | C92: Bens Imóveis - Output | D92: 2. Campo | E92: cd_imv_out_bens | F92: data_avl | G92: =VLOOKUP(A92,Plano_V3!$A$27:$G$583,7,0) -> 1. Concluído | H92: 1. Concluído | J92: =IF(VLOOKUP(A92,'Aux - pivots1'!$A:$E,3,0)=0, "",VLOOKUP(A92,'Aux - pivots1'!$A:$E,3,0)) | K92: =IF(VLOOKUP(A92,'Aux - pivots1'!$A:$E,4,0)=0, "",VLOOKUP(A92,'Aux - pivots1'!$A:$E,4,0)) | L92: =IF(VLOOKUP(A92,'Aux - pivots1'!$A:$E,5,0)=0, "",VLOOKUP(A92,'Aux - pivots1'!$A:$E,5,0))
A93: =E93&F93 -> cd_imv_out_bensdata_lic_util | B93: Pilar III | C93: Bens Imóveis - Output | D93: 2. Campo | E93: cd_imv_out_bens | F93: data_lic_util | G93: =VLOOKUP(A93,Plano_V3!$A$27:$G$583,7,0) -> 1. Concluído | H93: 1. Concluído | J93: =IF(VLOOKUP(A93,'Aux - pivots1'!$A:$E,3,0)=0, "",VLOOKUP(A93,'Aux - pivots1'!$A:$E,3,0)) | K93: =IF(VLOOKUP(A93,'Aux - pivots1'!$A:$E,4,0)=0, "",VLOOKUP(A93,'Aux - pivots1'!$A:$E,4,0)) | L93: =IF(VLOOKUP(A93,'Aux - pivots1'!$A:$E,5,0)=0, "",VLOOKUP(A93,'Aux - pivots1'!$A:$E,5,0))
A94: =E94&F94 -> cd_imv_out_bensficha | B94: Pilar III | C94: Bens Imóveis - Output | D94: 2. Campo | E94: cd_imv_out_bens | F94: ficha | G94: =VLOOKUP(A94,Plano_V3!$A$27:$G$583,7,0) -> 1. Concluído | H94: 1. Concluído | J94: =IF(VLOOKUP(A94,'Aux - pivots1'!$A:$E,3,0)=0, "",VLOOKUP(A94,'Aux - pivots1'!$A:$E,3,0)) | K94: =IF(VLOOKUP(A94,'Aux - pivots1'!$A:$E,4,0)=0, "",VLOOKUP(A94,'Aux - pivots1'!$A:$E,4,0)) | L94: =IF(VLOOKUP(A94,'Aux - pivots1'!$A:$E,5,0)=0, "",VLOOKUP(A94,'Aux - pivots1'!$A:$E,5,0))
A95: =E95&F95 -> cd_imv_out_bensid_frac | B95: Pilar III | C95: Bens Imóveis - Output | D95: 2. Campo | E95: cd_imv_out_bens | F95: id_frac | G95: =VLOOKUP(A95,Plano_V3!$A$27:$G$583,7,0) -> 1. Concluído | H95: 1. Concluído | J95: =IF(VLOOKUP(A95,'Aux - pivots1'!$A:$E,3,0)=0, "",VLOOKUP(A95,'Aux - pivots1'!$A:$E,3,0)) | K95: =IF(VLOOKUP(A95,'Aux - pivots1'!$A:$E,4,0)=0, "",VLOOKUP(A95,'Aux - pivots1'!$A:$E,4,0)) | L95: =IF(VLOOKUP(A95,'Aux - pivots1'!$A:$E,5,0)=0, "",VLOOKUP(A95,'Aux - pivots1'!$A:$E,5,0))
A96: =E96&F96 -> cd_imv_out_benslocalid | B96: Pilar III | C96: Bens Imóveis - Output | D96: 2. Campo | E96: cd_imv_out_bens | F96: localid | G96: =VLOOKUP(A96,Plano_V3!$A$27:$G$583,7,0) -> 1. Concluído | H96: 1. Concluído | J96: =IF(VLOOKUP(A96,'Aux - pivots1'!$A:$E,3,0)=0, "",VLOOKUP(A96,'Aux - pivots1'!$A:$E,3,0)) | K96: =IF(VLOOKUP(A96,'Aux - pivots1'!$A:$E,4,0)=0, "",VLOOKUP(A96,'Aux - pivots1'!$A:$E,4,0)) | L96: =IF(VLOOKUP(A96,'Aux - pivots1'!$A:$E,5,0)=0, "",VLOOKUP(A96,'Aux - pivots1'!$A:$E,5,0))
... A102: =E102&F102 -> cd_imv_out_bensnum | B102: Pilar III | C102: Bens Imóveis - Output | D102: 2. Campo | E102: cd_imv_out_bens | F102: num | G102: =VLOOKUP(A102,Plano_V3!$A$27:$G$583,7,0) -> 1. Concluído | H102: 1. Concluído | J102: =IF(VLOOKUP(A102,'Aux - pivots1'!$A:$E,3,0)=0, "",VLOOKUP(A102,'Aux - pivots1'!$A:$E,3,0)) | K102: =IF(VLOOKUP(A102,'Aux - pivots1'!$A:$E,4,0)=0, "",VLOOKUP(A102,'Aux - pivots1'!$A:$E,4,0)) | L102: =IF(VLOOKUP(A102,'Aux - pivots1'!$A:$E,5,0)=0, "",VLOOKUP(A102,'Aux - pivots1'!$A:$E,5,0))
A103: =E103&F103 -> cd_imv_out_bensorigem | B103: Pilar III | C103: Bens Imóveis - Output | D103: 2. Campo | E103: cd_imv_out_bens | F103: origem | G103: =VLOOKUP(A103,Plano_V3!$A$27:$G$583,7,0) -> 0. Cancelado | H103: 0. Cancelado | I103: 08/08/2024: Campo eliminado de modo a garantir a coerência com o atualmente realizado no Modelo Único de Garantias. | J103: =IF(VLOOKUP(A103,'Aux - pivots1'!$A:$E,3,0)=0, "",VLOOKUP(A103,'Aux - pivots1'!$A:$E,3,0)) | K103: =IF(VLOOKUP(A103,'Aux - pivots1'!$A:$E,4,0)=0, "",VLOOKUP(A103,'Aux - pivots1'!$A:$E,4,0)) | L103: =IF(VLOOKUP(A103,'Aux - pivots1'!$A:$E,5,0)=0, "",VLOOKUP(A103,'Aux - pivots1'!$A:$E,5,0))
A104: =E104&F104 -> cd_imv_out_bensperc_obra | B104: Pilar III | C104: Bens Imóveis - Output | D104: 2. Campo | E104: cd_imv_out_bens | F104: perc_obra | G104: =VLOOKUP(A104,Plano_V3!$A$27:$G$583,7,0) -> 1. Concluído | H104: 1. Concluído | I104: 22/07/2024: Entrega de campo para testes | J104: =IF(VLOOKUP(A104,'Aux - pivots1'!$A:$E,3,0)=0, "",VLOOKUP(A104,'Aux - pivots1'!$A:$E,3,0)) -> 45491 | K104: =IF(VLOOKUP(A104,'Aux - pivots1'!$A:$E,4,0)=0, "",VLOOKUP(A104,'Aux - pivots1'!$A:$E,4,0)) -> 45495 | L104: =IF(VLOOKUP(A104,'Aux - pivots1'!$A:$E,5,0)=0, "",VLOOKUP(A104,'Aux - pivots1'!$A:$E,5,0)) -> 45495
A105: =E105&F105 -> cd_imv_out_bensprealcons | B105: Pilar III | C105: Bens Imóveis - Output | D105: 2. Campo | E105: cd_imv_out_bens | F105: prealcons | G105: =VLOOKUP(A105,Plano_V3!$A$27:$G$583,7,0) -> 1. Concluído | H105: 1. Concluído | I105: 22/07/2024: Entrega de campo para testes | J105: =IF(VLOOKUP(A105,'Aux - pivots1'!$A:$E,3,0)=0, "",VLOOKUP(A105,'Aux - pivots1'!$A:$E,3,0)) -> 45491 | K105: =IF(VLOOKUP(A105,'Aux - pivots1'!$A:$E,4,0)=0, "",VLOOKUP(A105,'Aux - pivots1'!$A:$E,4,0)) -> 45495 | L105: =IF(VLOOKUP(A105,'Aux - pivots1'!$A:$E,5,0)=0, "",VLOOKUP(A105,'Aux - pivots1'!$A:$E,5,0)) -> 45495
A106: =E106&F106 -> cd_imv_out_bensref_date | B106: Pilar III | C106: Bens Imóveis - Output | D106: 2. Campo | E106: cd_imv_out_bens | F106: ref_date | G106: =VLOOKUP(A106,Plano_V3!$A$27:$G$583,7,0) -> 1. Concluído | H106: 1. Concluído | J106: =IF(VLOOKUP(A106,'Aux - pivots1'!$A:$E,3,0)=0, "",VLOOKUP(A106,'Aux - pivots1'!$A:$E,3,0)) | K106: =IF(VLOOKUP(A106,'Aux - pivots1'!$A:$E,4,0)=0, "",VLOOKUP(A106,'Aux - pivots1'!$A:$E,4,0)) | L106: =IF(VLOOKUP(A106,'Aux - pivots1'!$A:$E,5,0)=0, "",VLOOKUP(A106,'Aux - pivots1'!$A:$E,5,0))
A107: =E107&F107 -> cd_imv_out_bensurbaniz | B107: Pilar III | C107: Bens Imóveis - Output | D107: 2. Campo | E107: cd_imv_out_bens | F107: urbaniz | G107: =VLOOKUP(A107,Plano_V3!$A$27:$G$583,7,0) -> 1. Concluído | H107: 1. Concluído | J107: =IF(VLOOKUP(A107,'Aux - pivots1'!$A:$E,3,0)=0, "",VLOOKUP(A107,'Aux - pivots1'!$A:$E,3,0)) | K107: =IF(VLOOKUP(A107,'Aux - pivots1'!$A:$E,4,0)=0, "",VLOOKUP(A107,'Aux - pivots1'!$A:$E,4,0)) | L107: =IF(VLOOKUP(A107,'Aux - pivots1'!$A:$E,5,0)=0, "",VLOOKUP(A107,'Aux - pivots1'!$A:$E,5,0))
A108: =E108&F108 -> cd_imv_out_certifn.a. | B108: Pilar III | C108: Bens Imóveis - Output | D108: 1. Universo | E108: cd_imv_out_certif | F108: n.a. | G108: =VLOOKUP(A108,Plano_V3!$A$27:$G$583,7,0) -> 1. Concluído | H108: 1. Concluído | J108: =IF(VLOOKUP(A108,'Aux - pivots1'!$A:$E,3,0)=0, "",VLOOKUP(A108,'Aux - pivots1'!$A:$E,3,0)) | K108: =IF(VLOOKUP(A108,'Aux - pivots1'!$A:$E,4,0)=0, "",VLOOKUP(A108,'Aux - pivots1'!$A:$E,4,0)) | L108: =IF(VLOOKUP(A108,'Aux - pivots1'!$A:$E,5,0)=0, "",VLOOKUP(A108,'Aux - pivots1'!$A:$E,5,0))
A109: =E109&F109 -> cd_imv_out_certifcempbem | B109: Pilar III | C109: Bens Imóveis - Output | D109: 2. Campo | E109: cd_imv_out_certif | F109: cempbem | G109: =VLOOKUP(A109,Plano_V3!$A$27:$G$583,7,0) -> 1. Concluído | H109: 1. Concluído | J109: =IF(VLOOKUP(A109,'Aux - pivots1'!$A:$E,3,0)=0, "",VLOOKUP(A109,'Aux - pivots1'!$A:$E,3,0)) | K109: =IF(VLOOKUP(A109,'Aux - pivots1'!$A:$E,4,0)=0, "",VLOOKUP(A109,'Aux - pivots1'!$A:$E,4,0)) | L109: =IF(VLOOKUP(A109,'Aux - pivots1'!$A:$E,5,0)=0, "",VLOOKUP(A109,'Aux - pivots1'!$A:$E,5,0))
A110: =E110&F110 -> cd_imv_out_certifckbalbem | B110: Pilar III | C110: Bens Imóveis - Output | D110: 2. Campo | E110: cd_imv_out_certif | F110: ckbalbem | G110: =VLOOKUP(A110,Plano_V3!$A$27:$G$583,7,0) -> 1. Concluído | H110: 1. Concluído | J110: =IF(VLOOKUP(A110,'Aux - pivots1'!$A:$E,3,0)=0, "",VLOOKUP(A110,'Aux - pivots1'!$A:$E,3,0)) | K110: =IF(VLOOKUP(A110,'Aux - pivots1'!$A:$E,4,0)=0, "",VLOOKUP(A110,'Aux - pivots1'!$A:$E,4,0)) | L110: =IF(VLOOKUP(A110,'Aux - pivots1'!$A:$E,5,0)=0, "",VLOOKUP(A110,'Aux - pivots1'!$A:$E,5,0))
A111: =E111&F111 -> cd_imv_out_certifckctabem | B111: Pilar III | C111: Bens Imóveis - Output | D111: 2. Campo | E111: cd_imv_out_certif | F111: ckctabem | G111: =VLOOKUP(A111,Plano_V3!$A$27:$G$583,7,0) -> 1. Concluído | H111: 1. Concluído | J111: =IF(VLOOKUP(A111,'Aux - pivots1'!$A:$E,3,0)=0, "",VLOOKUP(A111,'Aux - pivots1'!$A:$E,3,0)) | K111: =IF(VLOOKUP(A111,'Aux - pivots1'!$A:$E,4,0)=0, "",VLOOKUP(A111,'Aux - pivots1'!$A:$E,4,0)) | L111: =IF(VLOOKUP(A111,'Aux - pivots1'!$A:$E,5,0)=0, "",VLOOKUP(A111,'Aux - pivots1'!$A:$E,5,0))
A112: =E112&F112 -> cd_imv_out_certifckrefbem | B112: Pilar III | C112: Bens Imóveis - Output | D112: 2. Campo | E112: cd_imv_out_certif | F112: ckrefbem | G112: =VLOOKUP(A112,Plano_V3!$A$27:$G$583,7,0) -> 1. Concluído | H112: 1. Concluído | J112: =IF(VLOOKUP(A112,'Aux - pivots1'!$A:$E,3,0)=0, "",VLOOKUP(A112,'Aux - pivots1'!$A:$E,3,0)) | K112: =IF(VLOOKUP(A112,'Aux - pivots1'!$A:$E,4,0)=0, "",VLOOKUP(A112,'Aux - pivots1'!$A:$E,4,0)) | L112: =IF(VLOOKUP(A112,'Aux - pivots1'!$A:$E,5,0)=0, "",VLOOKUP(A112,'Aux - pivots1'!$A:$E,5,0))
A113: =E113&F113 -> cd_imv_out_certifcod_cnsrvtr_rgst_prdl | B113: Pilar III | C113: Bens Imóveis - Output | D113: 2. Campo | E113: cd_imv_out_certif | F113: cod_cnsrvtr_rgst_prdl | G113: =VLOOKUP(A113,Plano_V3!$A$27:$G$583,7,0) -> 6. Em implementação (re-especificação) | H113: 4. Validação EF | J113: =IF(VLOOKUP(A113,'Aux - pivots1'!$A:$E,3,0)=0, "",VLOOKUP(A113,'Aux - pivots1'!$A:$E,3,0)) | K113: =IF(VLOOKUP(A113,'Aux - pivots1'!$A:$E,4,0)=0, "",VLOOKUP(A113,'Aux - pivots1'!$A:$E,4,0)) | L113: =IF(VLOOKUP(A113,'Aux - pivots1'!$A:$E,5,0)=0, "",VLOOKUP(A113,'Aux - pivots1'!$A:$E,5,0))
...

Sheet Aux - pivots1
A3: concat | B3: Max of Status2 | C3: Max of Data de incidência / pedido esclarecimento | D3: Max of Data de correção/resposta prevista | E3: Max of Data de correção/resposta efetiva
A4: cd_imv_inp_certif_estimativacempbem | B4: 6
A5: cd_imv_inp_certif_estimativachave_encriptada | B5: 6
A6: cd_imv_inp_certif_estimativackbalbem | B6: 6
A7: cd_imv_inp_certif_estimativackctabem | B7: 6
A8: cd_imv_inp_certif_estimativackrefbem | B8: 6
A9: cd_imv_inp_certif_estimativadata_extraccao_info | B9: 6
A10: cd_imv_inp_certif_estimativaepc | B10: 6
A11: cd_imv_inp_certif_estimativafornecedor | B11: 6
A12: cd_imv_inp_certif_estimativametodo_info | B12: 6
A13: cd_imv_inp_certif_estimativan.a. | B13: 6
A14: cd_imv_inp_certif_estimativascore_qualidade | B14: 6
A15: cd_imv_inp_certif_estimativavlr_cnsm_ano | B15: 6
... A45: cd_imv_out_bensorigem | B45: 0
A46: cd_imv_out_bensperc_obra | B46: 1 | C46: 45491 | D46: 45495 | E46: 45495
A47: cd_imv_out_bensprealcons | B47: 1 | C47: 45491 | D47: 45495 | E47: 45495
A48: cd_imv_out_bensref_date | B48: 1
A49: cd_imv_out_bensurbaniz | B49: 1
A50: cd_imv_out_certifarea_util | B50: 6
A51: cd_imv_out_certifcempbem | B51: 1
A52: cd_imv_out_certifckbalbem | B52: 1
A53: cd_imv_out_certifckctabem | B53: 1
A54: cd_imv_out_certifckrefbem | B54: 1
A55: cd_imv_out_certifcod_art_matr | B55: 6
A56: cd_imv_out_certifcod_cnsrvtr_rgst_prdl | B56: 6
A57: cd_imv_out_certifcod_disconf | B57: 6
A58: cd_imv_out_certifcod_fin_bem | B58: 6
A59: cd_imv_out_certifcod_inscrc | B59: 6
... A127: cd_imv_out_prccod_grt | B127: 1
A128: cd_imv_out_prccod_moeda | B128: 1 | C128: 45512 | D128: 45526
A129: cd_imv_out_prccod_observacao | B129: 1
A130: cd_imv_out_prccod_prd_grnt | B130: 1
A131: cd_imv_out_prccod_sprd_grnt | B131: 1
A132: cd_imv_out_prccod_tipo | B132: 1
A133: cd_imv_out_prccomp_id_gar | B133: 1
A134: cd_imv_out_prcdata_inicio | B134: 1
A135: cd_imv_out_prcdata_vcmt | B135: 1
A136: cd_imv_out_prcmontante_eur | B136: 0
A137: cd_imv_out_prcmontante_org | B137: 0
A138: cd_imv_out_prcn.a. | B138: 1
A139: cd_imv_out_prcorigem | B139: 0
A140: cd_imv_out_prcref_date | B140: 1
... A185: lt002_insrmntbsnss_area_dstntn | B185: 1
A186: lt002_insrmntcnclld_instrmnt_stts | B186: 2 | C186: 45471 | D186: 45481 | E186: 45481
A187: lt002_insrmntcod_soc | B187: 1
A188: lt002_insrmntcod_soc_dstntn | B188: 1
A189: lt002_insrmntcod_soc_intrgrp | B189: 1
A190: lt002_insrmntdflt_stts_instrmnt | B190: 1
A191: lt002_insrmntdt_rfrnc | B191: 1
A192: lt002_insrmntflg_intrbsnss | B192: 1
A193: lt002_insrmntgns_fnncl_trnsctn_exchng_ccrr | B193: 2
A194: lt002_insrmntgns_fnncl_trnsctn_exchng_dffrncs | B194: 2
A195: lt002_insrmntgrss_cmmssn_expns | B195: 2
A196: lt002_insrmntgrss_cmmssn_expns_ccrr | B196: 2
A197: lt002_insrmntgrss_cmmssn_expns_off_blnc | B197: 2
A198: lt002_insrmntgrss_cmmssn_expns_off_blnc_ccrr | B198: 2
... A225: lt002_insrmntsstnbl_ctgry | B225: 3
A226: lt002_insrmntsstnbl_indctr | B226: 2 | C226: 45471 | D226: 45481 | E226: 45481
A227: lt002_insrmntsubportfolio_id | B227: 1
A228: lt002_insrmnttyp_instrmnt | B228: 1
A229: lt002_instrumentaccmltd_chngs_fv_cr_instrmnt | B229: 1
A230: lt002_instrumentaccmltd_imprmnt_instrmnt | B230: 1
A231: lt002_instrumentaccntng_clssfctn | B231: 1
A232: lt002_instrumentcod_soc | B232: 1
A233: lt002_instrumentdflt_stts_instrmnt | B233: 1
A234: lt002_instrumentdt_incptn | B234: 1
A235: lt002_instrumentdt_lgl_fnl_mtrty | B235: 1
A236: lt002_instrumentdt_rfrnc | B236: 1
A237: lt002_instrumentenvrnmntl_objctv | B237: 7
A238: lt002_instrumentgrss_cmmssn_incm | B238: 7
... A366: modesg_inp_empr_excl_parisref_date | B366: 1
A367: modesg_inp_emss_bens_imoveisano_fator_emissao | B367: 1 | D367: 45534 | E367: 45534
A368: modesg_inp_emss_bens_imoveisclasse_ativo | B368: 1 | D368: 45534 | E368: 45534
A369: modesg_inp_emss_bens_imoveisepc | B369: 1 | D369: 45534 | E369: 45534
A370: modesg_inp_emss_bens_imoveisflg_ftr_emss_area | B370: 0 | D370: 45534 | E370: 45534
A371: modesg_inp_emss_bens_imoveisn.a. | B371: 1 | D371: 45534 | E371: 45534
A372: modesg_inp_emss_bens_imoveisnome_estado | B372: 1 | D372: 45534 | E372: 45534
A373: modesg_inp_emss_bens_imoveisnome_fator_emissao | B373: 1 | D373: 45534 | E373: 45534
A374: modesg_inp_emss_bens_imoveisnome_pais | B374: 1 | D374: 45534 | E374: 45534
A375: modesg_inp_emss_bens_imoveisnome_unidade_funcional | B375: 1 | D375: 45534 | E375: 45534
A376: modesg_inp_emss_bens_imoveisref_date | B376: 1 | D376: 45534 | E376: 45534
A377: modesg_inp_emss_bens_imoveisregiao | B377: 1 | D377: 45534 | E377: 45534
A378: modesg_inp_emss_bens_imoveisscore_qualidade | B378: 1 | D378: 45534 | E378: 45534
... A386: modesg_inp_emss_naceano | B386: 1 | D386: 45534 | E386: 45534
A387: modesg_inp_emss_nacearea_atividade | B387: 0
A388: modesg_inp_emss_naceclasse_ativo | B388: 1 | D388: 45534 | E388: 45534
A389: modesg_inp_emss_nacecod_class_indust | B389: 1 | D389: 45534 | E389: 45534
A390: modesg_inp_emss_nacecod_nace_esg | B390: 1 | D390: 45534 | E390: 45534
A391: modesg_inp_emss_nacefator_emissao | B391: 0
A392: modesg_inp_emss_nacen.a. | B392: 1 | D392: 45534 | E392: 45534
A393: modesg_inp_emss_nacenivel_classificacao_1 | B393: 1 | D393: 45534 | E393: 45534
A394: modesg_inp_emss_nacenome_pais | B394: 1 | D394: 45534 | E394: 45534
A395: modesg_inp_emss_nacenome_regiao | B395: 0
A396: modesg_inp_emss_naceopcao_metodologia | B396: 1 | D396: 45534 | E396: 45534
A397: modesg_inp_emss_naceref_date | B397: 1 | D397: 45534 | E397: 45534
A398: modesg_inp_emss_nacescore_qualidade | B398: 1 | D398: 45534 | E398: 45534
A399: modesg_inp_emss_nacescp1_ftr_emss | B399: 6 | D399: 45534 | E399: 45534
A400: modesg_inp_emss_nacescp2_ftr_emss | B400: 6 | D400: 45534 | E400: 45534
A401: modesg_inp_emss_nacescp3_ftr_emss | B401: 6 | D401: 45534 | E401: 45534
A402: modesg_inp_emss_nacesub_tipo_atividade_1 | B402: 0
...

Sheet Aux - Pivots2
B2: 1. Modelo Bens imóveis
B5: Âmbito | C5: Pilar III
B6: Sub-âmbito | C6: (Multiple Items)
B7: Tipo de teste | C7: 2. Campo
B9: Count of Campo | C9: Column Labels
B10: Row Labels | C10: 0. Cancelado | D10: 1. Concluído | E10: 4. Validação EF | F10: 6. Em implementação (re-especificação) | G10: Grand Total
B11: cd_imv_out_trz_prc_bens_imv | C11: 1 | D11: 14 | G11: 15
B12: cd_imv_out_trz_cred_prc | C12: 3 | D12: 17 | G12: 20
B13: cd_imv_out_prc | C13: 4 | D13: 13 | G13: 17
B14: cd_imv_out_certif | D14: 50 | E14: 3 | F14: 12 | G14: 65
B15: cd_imv_out_bens | C15: 2 | D15: 30 | G15: 32
B16: cd_imv_inp_certif_estimativa | F16: 12 | G16: 12
B17: Grand Total | C17: 10 | D17: 124 | E17: 3 | F17: 24 | G17: 161
B23: Âmbito | C23: Pilar III
B24: Sub-âmbito | C24: (Multiple Items)
B25: Tipo de teste | C25: 2. Campo
B27: Row Labels | C27: Count of Campo
B28: 0. Cancelado | C28: 10
B29: 1. Concluído | C29: 124
B30: 4. Validação EF | C30: 3
B31: 6. Em implementação (re-especificação) | C31: 24
B32: Grand Total | C32: 161
B42: 2. Modelo Verde
B44: Âmbito | C44: Pilar III
B45: Sub-âmbito | C45: (Multiple Items)
B46: Tipo de teste | C46: 2. Campo
B48: Count of Campo | C48: Column Labels
B49: Row Labels | C49: 0. Cancelado | D49: 1. Concluído | E49: 2. Em Teste | F49: 4. Validação EF | G49: 6. Em implementação (re-especificação) | H49: Grand Total
B50: modesg_param_sfcs_taxon_europeia | C50: 2 | D50: 12 | F50: 1 | G50: 15 | H50: 30
B51: modesg_out_sfcs_taxon_europeia | C51: 1 | D51: 1 | F51: 12 | H51: 14
B52: modesg_out_emss_vcls | D52: 8 | G52: 7 | H52: 15
B53: modesg_out_empr_info_nfin | D53: 1 | E53: 7 | F53: 19 | G53: 5 | H53: 32
B54: modesg_out_bens_imoveis | D54: 6 | E54: 8 | F54: 4 | H54: 18
B55: modesg_inp_risco_fisico | D55: 6 | H55: 6
B56: modesg_inp_nfrd_alinhamento_tax | D56: 41 | H56: 41
B57: modesg_inp_km_medios_emss_vcls | C57: 3 | D57: 6 | H57: 9
B58: modesg_inp_emss_vcls | D58: 17 | H58: 17
B59: modesg_inp_emss_scib | D59: 17 | H59: 17
B60: modesg_inp_emss_nace | C60: 7 | D60: 11 | G60: 3 | H60: 21
B61: modesg_inp_emss_bens_imoveis | C61: 1 | D61: 17 | H61: 18
B62: modesg_inp_empr_excl_paris | D62: 7 | H62: 7
B63: Grand Total | C63: 14 | D63: 150 | E63: 15 | F63: 36 | G63: 30 | H63: 245
B68: Âmbito | C68: Pilar III
B69: Sub-âmbito | C69: (Multiple Items)
B70: Tipo de teste | C70: 2. Campo
B72: Row Labels | C72: Count of Campo
B73: 0. Cancelado | C73: 14
B74: 1. Concluído | C74: 150
B75: 2. Em Teste | C75: 15
B76: 4. Validação EF | C76: 36
B77: 6. Em implementação (re-especificação) | C77: 30
B78: Grand Total | C78: 245
B87: 3. Loan Tape | Pilar III
B90: Âmbito | C90: Pilar III
B91: Sub-âmbito | C91: Pilar III
B92: Tipo de teste | C92: 2. Campo
B94: Count of Campo | C94: Column Labels
B95: Row Labels | C95: 1. Concluído | D95: 4. Validação EF | E95: 7. Por iniciar | F95: Grand Total
B96: lt002_instrument | C96: 20 | E96: 14 | F96: 34
B97: lt003_entity | C97: 11 | E97: 32 | F97: 43
B98: lt004_protection | C98: 1 | D98: 9 | E98: 10 | F98: 20
B99: lt005_instr_ent | C99: 5 | F99: 5
B100: lt006_instr_prot | C100: 5 | F100: 5
B101: lt825_mthd_usd_instrmnt | E101: 10 | F101: 10
B102: lt826_esg_sbsctr | E102: 9 | F102: 9
B103: Grand Total | C103: 42 | D103: 9 | E103: 75 | F103: 126
B111: Âmbito | C111: Pilar III
B112: Sub-âmbito | C112: Pilar III
B113: Tipo de teste | C113: 2. Campo
B115: Row Labels | C115: Count of Campo
B116: 7. Por iniciar | C116: 75
B117: 1. Concluído | C117: 42
B118: 4. Validação EF | C118: 9
B119: Grand Total | C119: 126
B129: 4. Loan Tape | Green Dashboard
B132: Âmbito | C132: GD
B133: Tipo de teste | C133: 2. Campo
B135: Count of Campo | C135: Column Labels
B136: Row Labels | C136: 1. Concluído | D136: 2. Em Teste | E136: 3. Pendente de outros desenvolvimentos | F136: Grand Total
B137: lt002_insrmnt | C137: 23 | D137: 26 | E137: 1 | F137: 50
B138: Grand Total | C138: 23 | D138: 26 | E138: 1 | F138: 50
B141: Âmbito | C141: GD
B142: Tipo de teste | C142: 2. Campo
B144: Row Labels | C144: Count of Campo
B145: 1. Concluído | C145: 23
B146: 2. Em Teste | C146: 26
B147: 3. Pendente de outros desenvolvimentos | C147: 1
B148: Grand Total | C148: 50

Sheet Caderno Testes
N7: (alterar quando necessário) | R7: (data default - Dez2023)
B8: Âmbito | C8: Sub-âmbito | D8: Origem | E8: Campo Origem | F8: Tabela | G8: Campo | H8: concat | I8: Status | J8: Status2 | K8: Tipologia_Testes | L8: Necessidade de re-especificação? (campo) | M8: Complexidade | N8: Data de Alteração Status | O8: Estimação (horas) | P8: Notas | Q8: Owner | R8: Data alteração especificação | S8: Data de inicio testes | T8: Data de incidência / pedido esclarecimento | U8: Data de correção/resposta prevista | V8: Data de correção/resposta efetiva | W8: Horas efetivas | X8: Query
B9: GD | C9: GD | D9: n.a. | E9: n.a. | F9: lt002_insrmnt | G9: n.a. | H9: =Table1[[#This Row],[Tabela]]&Table1[[#This Row],[Campo]] -> lt002_insrmntn.a. | I9: 2. Em Teste | J9: =VLOOKUP(Table1[[#This Row],[Status]],Auxiliar!$B$16:$C$23,2,0) -> 2 | K9: 1. Teste de universo | L9: Sim | M9: Alta | N9: 45485 | O9: =INDEX(Auxiliar!$D$5:$F$13,MATCH(Table1[[#This Row],[Tipologia_Testes]],Auxiliar!$B$5:$B$13,0),MATCH(Table1[[#This Row],[Complexidade]],Auxiliar!$D$4:$F$4,0)) -> 8 | R9: 45261 | W9: =VLOOKUP(Table1[[#This Row],[Status]],Auxiliar!$B$16:$D$23,3,0)*Table1[[#This Row],[Estimação (horas)]] -> 4
B10: GD | C10: GD | D10: Modelo Verde | E10: n.a. | F10: lt002_insrmnt | G10: sstnbl_ctgry | H10: =Table1[[#This Row],[Tabela]]&Table1[[#This Row],[Campo]] -> lt002_insrmntsstnbl_ctgry | I10: 3. Pendente de outros desenvolvimentos | J10: =VLOOKUP(Table1[[#This Row],[Status]],Auxiliar!$B$16:$C$23,2,0) -> 3 | K10: 2. Simulação | L10: Sim | M10: Alta | N10: 45485 | O10: =INDEX(Auxiliar!$D$5:$F$13,MATCH(Table1[[#This Row],[Tipologia_Testes]],Auxiliar!$B$5:$B$13,0),MATCH(Table1[[#This Row],[Complexidade]],Auxiliar!$D$4:$F$4,0)) -> 8 | R10: 45261 | W10: =VLOOKUP(Table1[[#This Row],[Status]],Auxiliar!$B$16:$D$23,3,0)*Table1[[#This Row],[Estimação (horas)]] -> 2
B11: GD | C11: GD | D11: Modelo Verde | E11: n.a. | F11: lt002_insrmnt | G11: sstnbl_ctgry | H11: =Table1[[#This Row],[Tabela]]&Table1[[#This Row],[Campo]] -> lt002_insrmntsstnbl_ctgry | I11: 3. Pendente de outros desenvolvimentos | J11: =VLOOKUP(Table1[[#This Row],[Status]],Auxiliar!$B$16:$C$23,2,0) -> 3 | K11: 3. Testes comparativos (Espec. VS Impl.) | L11: Sim | M11: Alta | N11: 45485 | O11: =INDEX(Auxiliar!$D$5:$F$13,MATCH(Table1[[#This Row],[Tipologia_Testes]],Auxiliar!$B$5:$B$13,0),MATCH(Table1[[#This Row],[Complexidade]],Auxiliar!$D$4:$F$4,0)) -> 8 | R11: 45261 | W11: =VLOOKUP(Table1[[#This Row],[Status]],Auxiliar!$B$16:$D$23,3,0)*Table1[[#This Row],[Estimação (horas)]] -> 2
B12: GD | C12: GD | D12: Modelo Verde | E12: n.a. | F12: lt002_insrmnt | G12: sstnbl_ctgry | H12: =Table1[[#This Row],[Tabela]]&Table1[[#This Row],[Campo]] -> lt002_insrmntsstnbl_ctgry | I12: 3. Pendente de outros desenvolvimentos | J12: =VLOOKUP(Table1[[#This Row],[Status]],Auxiliar!$B$16:$C$23,2,0) -> 3 | K12: 4. Validação de parametrizações | L12: Sim | M12: Alta | N12: 45485 | O12: =INDEX(Auxiliar!$D$5:$F$13,MATCH(Table1[[#This Row],[Tipologia_Testes]],Auxiliar!$B$5:$B$13,0),MATCH(Table1[[#This Row],[Complexidade]],Auxiliar!$D$4:$F$4,0)) -> 8 | P12: Parametrização a ser implementada: lt803 | R12: 45261 | W12: =VLOOKUP(Table1[[#This Row],[Status]],Auxiliar!$B$16:$D$23,3,0)*Table1[[#This Row],[Estimação (horas)]] -> 2
B13: GD | C13: GD | D13: Modelo Verde | E13: n.a. | F13: lt002_insrmnt | G13: sstnbl_ctgry | H13: =Table1[[#This Row],[Tabela]]&Table1[[#This Row],[Campo]] -> lt002_insrmntsstnbl_ctgry | I13: 3. Pendente de outros desenvolvimentos | J13: =VLOOKUP(Table1[[#This Row],[Status]],Auxiliar!$B$16:$C$23,2,0) -> 3 | K13: 6. Validação de formatos | L13: Sim | M13: Alta | N13: 45485 | O13: =INDEX(Auxiliar!$D$5:$F$13,MATCH(Table1[[#This Row],[Tipologia_Testes]],Auxiliar!$B$5:$B$13,0),MATCH(Table1[[#This Row],[Complexidade]],Auxiliar!$D$4:$F$4,0)) -> 0.1 | R13: 45261 | W13: =VLOOKUP(Table1[[#This Row],[Status]],Auxiliar!$B$16:$D$23,3,0)*Table1[[#This Row],[Estimação (horas)]] -> 0.025
