Workbook
Name _ftnref1_50: '[1]Table 39_'!#REF!
Name _ftnref1_51: '[1]Table 39_'!#REF!
Name _ftref1_50: '[1]Table 39_'!#REF!
Name Carlos: #REF!
Name DataPointIDs: #REF!
Name DataPointTooltips: #REF!
Name DBName: #REF!
Name dsa: #REF!
Name F20.04: #REF!
Name F20.04ES: #REF!
Name F20.06: #REF!
Name F20.061: #REF!
Name F20.062: #REF!
Name fdsg: '[1]Table 39_'!#REF!
Name ho: #REF!
Name JedenRadekPodSestavou: #REF!
Name JedenRadekPodSestavou_11: #REF!
Name JedenRadekPodSestavou_2: #REF!
Name JedenRadekPodSestavou_28: #REF!
Name JedenRadekVedleSestavy: #REF!
Name JedenRadekVedleSestavy_11: #REF!
Name JedenRadekVedleSestavy_2: #REF!
Name JedenRadekVedleSestavy_28: #REF!
Name MaxOblastTabulky: #REF!
Name MaxOblastTabulky_11: #REF!
Name MaxOblastTabulky_2: #REF!
Name MaxOblastTabulky_28: #REF!
Name myData: OFFSET(#REF!,0,0,MATCH("*",#REF!,-1),6)
Name myFilterSelection: #REF!
Name myPivotTable: #REF!
Name myPivotTableStart: #REF!
Name OblastDat2: #REF!
Name OblastDat2_11: #REF!
Name OblastDat2_2: #REF!
Name OblastDat2_28: #REF!
Name OblastNadpisuRadku: #REF!
Name OblastNadpisuRadku_11: #REF!
Name OblastNadpisuRadku_2: #REF!
Name OblastNadpisuRadku_28: #REF!
Name OblastNadpisuSloupcu: #REF!
Name OblastNadpisuSloupcu_11: #REF!
Name OblastNadpisuSloupcu_2: #REF!
Name OblastNadpisuSloupcu_28: #REF!
Name OLE_LINK11: 'BST individual BS Oct25'!#REF!
Name Print_Area_MI: #REF!
Name Print_Area_MI_11: #REF!
Name Print_Area_MI_2: #REF!
Name Print_Area_MI_28: #REF!
Name Print_Titles_MI: #REF!
Name Print_Titles_MI_11: #REF!
Name Print_Titles_MI_2: #REF!
Name Print_Titles_MI_28: #REF!
Name rfgf: '[1]Table 39_'!#REF!
Name Templates: #REF!

Sheet Accounting Check
B2: Accounting
B4: Bucket | C4: # | D4: Instruments | F4: 30Oct24 | G4: 15Nov24 | I4: Δ Abs | J4: Δ % | K4: Status | L4: Justificacion
B5: 1 | C5: 1 | D5: Common Equity Tier 1 | F5: =SUMIF(Inventory!AF:AF,C5,Inventory!AB:AB) -> 1566022662 | G5: =SUMIF('B0200'!Q:Q,B5,'B0200'!BX:BX) -> 1566022662 | I5: =+G5-F5 -> 0 | J5: =(G5-F5)/F5 -> 0 | K5: =IF(ABS(J5)<0.05,"OK",IF(ABS(J5)<0.1,"Warning","KO")) -> OK
B6: 2 | C6: 2 | D6: Additional Tier 1 Instruments | F6: =SUMIF(Inventory!AF:AF,C6,Inventory!AB:AB) -> 1200000000 | G6: =SUMIF('B0200'!Q:Q,B6,'B0200'!BX:BX) -> 1200000000 | I6: =+G6-F6 -> 0 | J6: =(G6-F6)/F6 -> 0 | K6: =IF(ABS(J6)<0.05,"OK",IF(ABS(J6)<0.1,"Warning","KO")) -> OK
B7: 3 | C7: 3 | D7: Subordinated debt (Tier 2) | F7: =SUMIF(Inventory!AF:AF,C7,Inventory!AB:AB) -> 2.1138497e+08 | G7: =SUMIF('B0200'!Q:Q,B7,'B0200'!BX:BX) -> 2.1176845e+08 | I7: =+G7-F7 -> 383482.05 | J7: =(G7-F7)/F7 -> 0.0018141406 | K7: =IF(ABS(J7)<0.05,"OK",IF(ABS(J7)<0.1,"Warning","KO")) -> OK | L7: Accrued interest
B8: 8 | C8: 8 | D8: Senior Non-preferred debt | F8: =SUMIF(Inventory!AF:AF,C8,Inventory!AB:AB) -> 1.112872e+09 | G8: =SUMIF('B0200'!Q:Q,B8,'B0200'!BX:BX) -> 1.1143596e+09 | I8: =+G8-F8 -> 1487567.1 | J8: =(G8-F8)/F8 -> 0.001336692 | K8: =IF(ABS(J8)<0.05,"OK",IF(ABS(J8)<0.1,"Warning","KO")) -> OK | L8: Accrued interest

Sheet Summary SRB
B2: Summary of controls
D4: Total # Controls | E4: Controls KO > 1% | H4: Comments
B5: Level 1 | D5: =COUNT('V_Level 1'!L5:L44) -> 40 | E5: =COUNTIF('V_Level 1'!N5:N44,">1%") -> 0 | F5: =E5/D5 -> 0
B6: B0200 | D6: =COUNT('V_Level 1'!L5:L43) -> 39 | E6: =COUNTIF('V_Level 1'!N5:N43,">1%") -> 0 | F6: =E6/D6 -> 0
B7: B9000 | D7: =COUNT('V_Level 1'!L44) -> 1 | E7: =COUNTIF('V_Level 1'!N44,">1%") -> 0 | F7: =E7/D7 -> 0
B8: Level 2 | D8: =COUNT('V_Level 2'!L4:L43) -> 40 | E8: =COUNTIF('V_Level 2'!N4:N43,">1%") -> 2 | F8: =E8/D8 -> 0.05
B9: B0200 | D9: =COUNT('V_Level 2'!L4:L39) -> 36 | E9: =COUNTIF('V_Level 2'!N4:N39,">1%") -> 0 | F9: =E9/D9 -> 0
B10: B9000 | D10: =COUNT('V_Level 2'!L40:L43) -> 4 | E10: =COUNTIF('V_Level 2'!N40:N43,">1%") -> 2 | F10: =E10/D10 -> 0.5 | H10: Controls not designed for Non resolution entities?

Sheet B9900
A2: Name of Legal Entity | B2: LEI of Legal Entity | C2: Country of incorporation | D2: Name of the ultimate parent entity | E2: LEI of the ultimate parent entity | F2: Name of the Resolution Entity | G2: LEI of the Resolution Entity | H2: Reporting entity type | I2: Reference date | J2: Reported currency | K2: EUR exchange rate
A3: c0010 | B3: c0020 | C3: c0030 | D3: c0040 | E3: c0041 | F3: c0050 | G3: c0051 | H3: c0060 | I3: c0070 | J3: c0080 | K3: c0090
A4: Banco Santander Totta, SA | B4: 549300URJH9VSI58CS32 | C4: PT | D4: Banco Santander, S.A. | E4: 5493006QMFDDMYWIAM13 | F4: Banco Santander, S.A. | G4: 5493006QMFDDMYWIAM13 | H4: Non-Resolution Entity | I4: 45976 | J4: EUR | K4: 1

Sheet B0200
CB1: Requirements for Non-Resolution Entities | CD1: Validations
A2: Row number | B2: Unique internal identification number | C2: Unique identification number (known to the counterparty) | D2: Type of the unique identifier (known to the counterparty) | E2: Original amount issued in EUR | F2: Original amount issued in foreign currency | G2: Contract currency | H2: Outstanding principal amount | I2: Portion of instrument or liability held by the reporting entity | J2: Accrued interest | K2: Applicable fees and charges | L2: Outstanding amount | M2: Relevant amount for Bail-in/WDC | N2: Nature of the liability | O2: Nature of the liability (if other) | P2: Structurally subordinated | Q2: Insolvency ranking | R2: Contractual subordination | S2: Bail-in cascade | T2: Date of issuance | U2: Date of the next interest payment | V2: Date of the next (partial) redemption payment | W2: Earliest redemption date | X2: Legal maturity | Y2: Governing law | Z2: Bail-in recognition clause | AA2: Zero-Coupon | AB2: Structured product | AC2: Guaranteed minimum repayment amount of the structured product | AD2: Fair value of the structured product | AE2: Not covered and not preferential deposit | AF2: Not covered but preferential deposit | AG2: Covered portion of eligible deposits | AH2: Secured/Unsecured | AI2: Amount of pledge, lien or collateral | AJ2: Amount of the uncollateralized part | AK2: Internal identification number of the pledge, lien or collateral/collateral pool | AL2: Type of the collateral | AM2: Type of the collateral (if other) | AN2: Trading method | AO2: Denomination / Nominal value per security in EUR | AP2: Denomination / Nominal value per security in original currency | AQ2: Number of securities outstanding not held by the reporting entity | AR2: Number of securities outstanding held by the reporting entity | AS2: Accrued interest per security | AT2: Fees and charges per security | AU2: Fair value per security | AV2: Principal amount of the global note in EUR | AW2: Principal amount of the global note in original currency | AX2: Nature of the global note | AY2: Current pool factor | AZ2: Central securities depository | BA2: Central securities depository (LEI) | BB2: Central securities depository name (if other) | BC2: (Mandated) paying agent | BD2: (Mandated) paying agent (LEI) | BE2: Trading venue | BF2: Trading venue (LEI) | BG2: Registrar for information about creditors/holders | BH2: Registrar for information about creditors/holders (LEI) | BI2: National Numbering Agency | BJ2: National Numbering Agency (LEI) | BK2: Common Depository | BL2: Common Depository (LEI) | BM2: Common Service Provider | BN2: Common Service Provider (LEI) | BO2: Type of own funds at individual level | BP2: Eligible amount for own funds at individual level | BQ2: Type of own funds at consolidated level | BR2: Eligible amount for own funds at consolidated level | BS2: Amount of the security interest provided | BT2: Security interest provider (Name) | BU2: Security interest provider (LEI) | BV2: Type of security interest provided by a third party | BW2: Collateral for an asset position | BX2: Carrying amount IFRS | BY2: Balance sheet item according to IFRS | BZ2: Carrying amount national GAAP | CA2: Balance sheet item at Resolution entity level according to national GAAP | CB2: Instrument/liability is issued to or bought by an existing shareholder that is not part of the same resolution group | CC2: Instrument/liability meets the requirements of Art. 21(7a) SRMR | CD2: Level 1 | DQ2: Level 2
CD3: =COUNTIF(CD5:CD1048576,"KO") -> 0 | CE3: =COUNTIF(CE5:CE1048576,"KO") -> 0 | CF3: =COUNTIF(CF5:CF1048576,"KO") -> 0 | CG3: =COUNTIF(CG5:CG1048576,"KO") -> 0 | CH3: =COUNTIF(CH5:CH1048576,"KO") -> 0 | CI3: =COUNTIF(CI5:CI1048576,"KO") -> 0 | CJ3: =COUNTIF(CJ5:CJ1048576,"KO") -> 0 | CK3: =COUNTIF(CK5:CK1048576,"KO") -> 0 | ... EZ3: =COUNTIF(EZ5:EZ1048576,"KO") -> 0
A4: c0010 | B4: c0020 | C4: c0030 | D4: c0040 | E4: c0050 | F4: c0060 | G4: c0070 | H4: c0080 | I4: c0090 | J4: c0100 | K4: c0110 | L4: c0120 | M4: c0130 | N4: c0140 | O4: c0141 | P4: c0150 | Q4: c0160 | R4: c0161 | S4: c0162 | T4: c0170 | U4: c0180 | V4: c0190 | W4: c0200 | X4: c0210 | Y4: c0220 | Z4: c0230 | AA4: c0240 | AB4: c0250 | AC4: c0260 | AD4: c0270 | AE4: c0280 | AF4: c0290 | AG4: c0300 | AH4: c0310 | AI4: c0320 | AJ4: c0330 | AK4: c0340 | AL4: c0350 | AM4: c0351 | AN4: c0360 | AO4: c0370 | AP4: c0380 | AQ4: c0390 | AR4: c0391 | AS4: c0400 | AT4: c0410 | AU4: c0420 | AV4: c0430 | AW4: c0431 | AX4: c0440 | AY4: c0450 | AZ4: c0460 | BA4: c0461 | BB4: c0462 | BC4: c0470 | BD4: c0471 | BE4: c0480 | BF4: c0481 | BG4: c0490 | BH4: c0491 | BI4: c0500 | BJ4: c0501 | BK4: c0510 | BL4: c0511 | BM4: c0520 | BN4: c0521 | BO4: c0530 | BP4: c0540 | BQ4: c0550 | BR4: c0560 | BS4: c0570 | BT4: c0580 | BU4: c0581 | BV4: c0590 | BW4: c0600 | BX4: c0610 | BY4: c0620 | BZ4: c0630 | CA4: c0640 | CB4: c5000 | CC4: c5010 | CD4: v_1_0001 | CE4: v_1_0002 | CF4: v_1_0003 | CG4: v_1_0004 | CH4: v_1_0005 | CI4: v_1_0006 | CJ4: v_1_0007 | CK4: v_1_0008 | CL4: v_1_0009 | CM4: v_1_0010 | CN4: v_1_0011 | CO4: v_1_0012 | CP4: v_1_0013 | CQ4: v_1_0014 | CR4: v_1_0015 | CS4: v_1_0016 | CT4: v_1_0017 | CU4: v_1_0018 | CV4: v_1_0019 | CW4: v_1_0020 | CX4: v_1_0021 | CY4: v_1_0022 | CZ4: v_1_0023 | DA4: v_1_0024 | DB4: v_1_0025 | DC4: v_1_0026 | DD4: v_1_0027 | DE4: v_1_0028 | DF4: v_1_0029 | DG4: v_1_0030 | DH4: v_1_0031 | DI4: v_1_0032 | DJ4: v_1_0033 | DK4: v_1_0034 | DL4: v_1_0035 | DM4: v_1_0036 | DN4: v_1_0037 | DO4: v_1_0038 | DP4: v_1_0039 | DQ4: v_2_0001 | DR4: v_2_0003 | DS4: v_2_0004 | DT4: v_2_0005 | DU4: v_2_0006 | DV4: v_2_0007 | DW4: v_2_0008 | DX4: v_2_0009 | DY4: v_2_0011 | DZ4: v_2_0012 | EA4: v_2_0013 | EB4: v_2_0014 | EC4: v_2_0015 | ED4: v_2_0016 | EE4: v_2_0017 | EF4: v_2_0018 | EG4: v_2_0019 | EH4: v_2_0020 | EI4: v_2_0021 | EJ4: v_2_0022 | EK4: v_2_0023 | EL4: v_2_0024 | EM4: v_2_0025 | EN4: v_2_0026 | EO4: v_2_0027 | EP4: v_2_0028 | EQ4: v_2_0029 | ER4: v_2_0030 | ES4: v_2_0031 | ET4: v_2_0032 | EU4: v_2_0033 | EV4: v_2_0034 | EW4: v_2_0035 | EX4: v_2_0036 | EY4: v_2_0037 | EZ4: v_2_0038
A5: 1 | B5: 31641600000000000PTBSREOM0028000 | C5: PTBSREOM0028 | D5: ISIN | E5: 7599000 | F5: 999999999999999 | G5: EUR | H5: 7599000 | I5: 0 | J5: 62457.537 | K5: 0 | L5: 7661457.5 | M5: 7661457.5 | N5: Registered Bond | O5: Not applicable | P5: Not applicable | Q5: 3 | R5: 999999999999999 | S5: 3 | T5: 2016-09-28 | U5: 2026-10-06 | V5: 2026-10-06 | W5: 2026-10-06 | X5: 2026-10-06 | Y5: PT | Z5: Yes, supported by Legal Opinion | AA5: No ZCB | AB5: Non-structured/Vanilla | AC5: 999999999999999 | AD5: 999999999999999 | AE5: FALSE | AF5: FALSE | AG5: 999999999999999 | AH5: Unsecured | AI5: 999999999999999 | AJ5: 999999999999999 | AK5: Not applicable | AL5: Not applicable | AM5: Not applicable | AN5: Nominal | AO5: 1000 | AP5: 1000 | AQ5: 7599 | AR5: 0 | AS5: =+B02.00[[#This Row],[c0100]]/B02.00[[#This Row],[c0390]] -> 8.2191784 | AT5: 0 | AU5: 999999999999999 | AV5: 999999999999999 | AW5: 999999999999999 | AX5: Not applicable | AY5: -10000 | AZ5: INTERBOLSA_PT | BA5: 529900LG70TCAGWCXT47 | BB5: Not applicable | BC5: BANCO SANTANDER TOTTA S,A, | BD5: 549300URJH9VSI58CS32 | BE5: Not applicable | BF5: Not applicable | BG5: INTERBOLSA_PT | BH5: 529900LG70TCAGWCXT47 | BI5: INTERBOLSA_PT | BJ5: 529900LG70TCAGWCXT47 | BK5: Not applicable | BL5: Not applicable | BM5: Not applicable | BN5: Not applicable | BO5: Fully Compliant T2 | BP5: 382215.35 | BQ5: Fully Compliant T2 | BR5: 382215.35 | BS5: 0 | BT5: Not applicable | BU5: Not applicable | BV5: Not applicable | BW5: FALSE | BX5: 7661457.5 | BY5: 110 Financial liabilities at amortized cost | BZ5: 999999999999999 | CA5: Not applicable | CB5: FALSE | CC5: TRUE | CD5: =IF(B02.00[[#This Row],[c0010]]="","KO","OK") -> OK | CE5: =IF(B02.00[[#This Row],[c0030]]="","KO","OK") -> OK | CF5: =IF(B02.00[[#This Row],[c0040]]="","KO","OK") -> OK | CG5: =IF(B02.00[[#This Row],[c0070]]="","KO","OK") -> OK | CH5: =IF(OR(B02.00[[#This Row],[c0250]]= "Non-Structured/Vanilla",B02.00[[#This Row],[c0250]]="Other non-standard terms"),(IF(B02.00[[#This Row],[c0080]]="","KO","OK")),"OK") -> OK | CI5: =IF(OR(B02.00[[#This Row],[c0250]]= "Structured",B02.00[[#This Row],[c0250]]="Only structured coupon"),(IF(B02.00[[#This Row],[c0080]]="","KO","OK")),"OK") -> OK | CJ5: =IF(B02.00[[#This Row],[c0040]]="ISIN",(IF(B02.00[[#This Row],[c0090]]="","KO","OK")),"OK") -> OK | CK5: =IF(AND(OR(B02.00[[#This Row],[c0250]]="Non-Structured/Vanilla",B02.00[[#This Row],[c0250]]="Other non-standard terms"),B02.00[[#This Row],[c0240]]<>"ZCB issued at discount"),(IF(B02.00[[#This Row],[c0100]]="","KO","OK")),"OK") -> OK | CL5: =IF(OR(B02.00[[#This Row],[c0250]]<> "Non-Structured/Vanilla",B02.00[[#This Row],[c0460]]<>"Other non-standard terms"),(IF(B02.00[[#This Row],[c0100]]="","KO","OK")),"OK") -> OK | CM5: =IF(OR(B02.00[[#This Row],[c0250]]= "Non-Structured/Vanilla",B02.00[[#This Row],[c0460]]="Other non-standard terms"),(IF(B02.00[[#This Row],[c0120]]="","KO","OK")),"OK") -> OK | CN5: =IF(OR(B02.00[[#This Row],[c0250]]<> "Structured",B02.00[[#This Row],[c0250]]<>"Only structured coupon"),(IF(B02.00[[#This Row],[c0120]]="","KO","OK")),"OK") -> OK | CO5: =IF(B02.00[[#This Row],[c0130]]="","KO","OK") -> OK | CP5: =IF(B02.00[[#This Row],[c0140]]="","KO","OK") -> OK | CQ5: =IF(B02.00[[#This Row],[c0140]]="Other",(IF(B02.00[[#This Row],[c0141]]="","KO","OK")),"OK") -> OK | CR5: =IF(B02.00[[#This Row],[c0160]]="","KO","OK") -> OK | CS5: =IF(B02.00[[#This Row],[c0162]]="","KO","OK") -> OK | CT5: =IF(AND(OR(B02.00[[#This Row],[c0250]]= "Non-Structured/Vanilla",B02.00[[#This Row],[c0250]]="Other non-standard terms"),B02.00[[#This Row],[c0240]]<>"ZCB issued at discount"),(IF(B02.00[[#This Row],[c0180]]="","KO","OK")),"OK") -> OK | CU5: =IF(AND(B02.00[[#This Row],[c0250]]<> "Structured",B02.00[[#This Row],[c0250]]<>"Only structured coupon"),(IF(B02.00[[#This Row],[c0180]]="","KO","OK")),"OK") -> OK | CV5: =IF(B02.00[[#This Row],[c0200]]="","KO","OK") -> OK | CW5: =IF(B02.00[[#This Row],[c0140]]<>"Cash account/saving account",(IF(B02.00[[#This Row],[c0210]]="","KO","OK")),"OK") -> OK | CX5: =IF(B02.00[[#This Row],[c0220]]="","KO","OK") -> OK | CY5: =IF(B02.00[[#This Row],[c0250]]="","KO","OK") -> OK | CZ5: =IF(OR(B02.00[[#This Row],[c0250]]="Structured",B02.00[[#This Row],[c0250]]="Only structured coupon"),(IF(B02.00[[#This Row],[c0260]]="","KO","OK")),"OK") -> OK | DA5: =IF(OR(B02.00[[#This Row],[c0250]]="Structured",B02.00[[#This Row],[c0250]]="Only structured coupon"),(IF(B02.00[[#This Row],[c0270]]="","KO","OK")),"OK") -> OK | DB5: =IF(OR(B02.00[[#This Row],[c0280]]="TRUE",B02.00[[#This Row],[c0290]]="TRUE"),(IF(B02.00[[#This Row],[c0300]]="","KO","OK")),"OK") -> OK | DC5: =IF(B02.00[[#This Row],[c0310]]="","KO","OK") -> OK | DD5: =IF(B02.00[[#This Row],[c0310]]="Secured",(IF(B02.00[[#This Row],[c0320]]="","KO","OK")),"OK") -> OK | DE5: =IF(B02.00[[#This Row],[c0310]]="Secured",(IF(B02.00[[#This Row],[c0330]]="","KO","OK")),"OK") -> OK | DF5: =IF(B02.00[[#This Row],[c0310]]="Secured",(IF(B02.00[[#This Row],[c0350]]="","KO","OK")),"OK") -> OK | DG5: =IF(B02.00[[#This Row],[c0350]]="Other",(IF(B02.00[[#This Row],[c0351]]="","KO","OK")),"OK") -> OK | DH5: =IF(AND(B02.00[[#This Row],[c0040]]="ISIN",B02.00[[#This Row],[c0360]]="Nominal "),(IF(B02.00[[#This Row],[c0370]]="","KO","OK")),"OK") -> OK | DI5: =IF(AND(B02.00[[#This Row],[c0040]]="ISIN",B02.00[[#This Row],[c0360]]="Unit "),(IF(B02.00[[#This Row],[c0370]]="","KO","OK")),"OK") -> OK | DJ5: =IF(B02.00[[#This Row],[c0040]]="ISIN",(IF(B02.00[[#This Row],[c0390]]="","KO","OK")),"OK") -> OK | DK5: =IF(B02.00[[#This Row],[c0040]]="ISIN",(IF(B02.00[[#This Row],[c0391]]="","KO","OK")),"OK") -> OK | DL5: =IF(AND(B02.00[[#This Row],[c0040]]="ISIN",OR(B02.00[[#This Row],[c0250]]= "Non-Structured/Vanilla",B02.00[[#This Row],[c0250]]="Other non-standard terms"),B02.00[[#This Row],[c0240]]<>"ZCB issued at discount"),(IF(B02.00[[#This Row],[c0400]]="","KO","OK")),"OK") -> OK | DM5: =IF(AND(B02.00[[#This Row],[c0040]]="ISIN",AND(B02.00[[#This Row],[c0250]]<>"Structured",B02.00[[#This Row],[c0250]]<>"Only structured coupon")),(IF(B02.00[[#This Row],[c0400]]="","KO","OK")),"OK") -> OK | DN5: =IF(B02.00[[#This Row],[c0610]]="","KO","OK") -> OK | DO5: =IF('B9900'!$H$4="Non-Resolution Entity",(IF(B02.00[[#This Row],[c5000]]="","KO","OK")),"OK") -> OK | DP5: =IF('B9900'!$H$4="Non-Resolution Entity",(IF(B02.00[[#This Row],[c5010]]="","KO","OK")),"OK") -> OK | DQ5: =IF(B02.00[[#This Row],[c0040]]="ISIN",(IF(AND(LEN(B02.00[[#This Row],[c0030]]=12),NOT(ISNUMBER(LEFT(B02.00[[#This Row],[c0030]],2)))),"OK","KO")),"OK") -> OK | DR5: =IF(AND(B02.00[[#This Row],[c0020]]<>"NCNP",B02.00[[#This Row],[c0020]]<>"NCBP"),(IF(AND(LEN(B02.00[[#This Row],[c0070]])=3,NOT(ISERROR(MATCH(UPPER(B02.00[[#This Row],[c0070]]),Tabelle1[Alphabetic Code],0)))),"OK","KO")),"OK") -> OK | DS5: =IF(B02.00[[#This Row],[c0080]]>0,"OK","KO") -> OK | DT5: =IF(B02.00[[#This Row],[c0040]]="ISIN",(IF(B02.00[[#This Row],[c0090]]>=0,"OK","KO")),"OK") -> OK | DU5: =IF(B02.00[[#This Row],[c0100]]>=0,"OK","KO") -> OK | DV5: =IF(B02.00[[#This Row],[c0110]]>=0,"OK","KO") -> OK | DW5: =IF(B02.00[[#This Row],[c0120]]>=0,"OK","KO") -> OK | DX5: =IF(B02.00[[#This Row],[c0120]]=(H5+J5+K5),"OK","KO") -> OK | DY5: =IF(OR(B02.00[[#This Row],[c0250]]="Non-structured /Vanilla",B02.00[[#This Row],[c0250]]="Other non-standard terms"),(IF(B02.00[[#This Row],[c0130]]=MAX(0,B02.00[[#This Row],[c0120]],B02.00[[#This Row],[c0300]],B02.00[[#This Row],[c0320]]),"OK","KO")),"OK") -> OK | DZ5: =IF(OR(B02.00[[#This Row],[c0250]]="Structured",B02.00[[#This Row],[c0250]]="Only structured coupon"),(IF(OR(B02.00[[#This Row],[c0130]]=MAX(0,B02.00[[#This Row],[c0270]],B02.00[[#This Row],[c0300]],B02.00[[#This Row],[c0320]]),B02.00[[#This Row],[c0130]]=MAX(0,B02.00[[#This Row],[c0120]],B02.00[[#This Row],[c0300]],B02.00[[#This Row],[c0320]])),"OK","KO")),"OK") -> OK | EA5: =IF(OR(B02.00[[#This Row],[c0140]]="Registered Bond",B02.00[[#This Row],[c0140]]="Bearrer Bond",B02.00[[#This Row],[c0140]]="Borrower Note Loan",B02.00[[#This Row],[c0140]]="Certificate of Deposit / Commercial Paper",B02.00[[#This Row],[c0140]]="Title of ownership",B02.00[[#This Row],[c0140]]="Cash account/saving account",B02.00[[#This Row],[c0140]]="Term deposit",B02.00[[#This Row],[c0140]]="Loan",B02.00[[#This Row],[c0140]]="Bill of exchange",B02.00[[#This Row],[c0140]]="Other"),"OK","KO") -> OK | EB5: =IF(B02.00[[#This Row],[c0160]]>=1,"OK","KO") -> OK | EC5: =IF(AND(B02.00[[#This Row],[c0020]]<>"NCNP",B02.00[[#This Row],[c0020]]<>"NCBP"),(IF(B02.00[[#This Row],[c0170]]>DATE(1900,1,1),"OK","KO")),"OK") -> OK | ED5: =IF(AND(OR(B02.00[[#This Row],[c0190]]<>"",B02.00[[#This Row],[c0200]]<>""),AND(B02.00[[#This Row],[c0020]]<>"NCNP",B02.00[[#This Row],[c0020]]<>"NCBP")),(IF(AND(B02.00[[#This Row],[c0170]]<B02.00[[#This Row],[c0190]],B02.00[[#This Row],[c0170]]<B02.00[[#This Row],[c0200]]),"OK","KO")),"OK") -> OK | EE5: =IF(AND(B02.00[[#This Row],[c0020]]<>"NCNP",B02.00[[#This Row],[c0020]]<>"NCBP"),IF(B02.00[[#This Row],[c0180]]="","KO",IF(B02.00[[#This Row],[c0180]]>DATE(1900,1,1),"OK","KO")),"OK") -> OK | EF5: =IF(AND('B9900'!$I$4<>"",B02.00[[#This Row],[c0020]]<>"NCNP",B02.00[[#This Row],[c0020]]<>"NCBP"),IF(B02.00[[#This Row],[c0180]]="","KO",IF(B02.00[[#This Row],[c0180]]>'B9900'!$I$4,"OK","KO")),"OK") -> OK | EG5: =IF(AND(B02.00[[#This Row],[c0020]]<>"NCNP",B02.00[[#This Row],[c0020]]<>"NCBP"),(IF(B02.00[[#This Row],[c0200]]>DATE(1900,1,1),"OK","KO")),"OK") -> OK | EH5: =IF(AND('B9900'!$I$4<>"",AND(B02.00[[#This Row],[c0020]]<>"NCNP",B02.00[[#This Row],[c0020]]<>"NCBP")),(IF(B02.00[[#This Row],[c0200]]>'B9900'!$I$4,"OK","KO")),"OK") -> OK | EI5: =IF(AND(B02.00[[#This Row],[c0020]]<>"NCNP",B02.00[[#This Row],[c0020]]<>"NCBP"),(IF(B02.00[[#This Row],[c0210]]>DATE(1900,1,1),"OK","KO")),"OK") -> OK | EJ5: =IF(AND('B9900'!$I$4<>"",AND(B02.00[[#This Row],[c0020]]<>"NCNP",B02.00[[#This Row],[c0020]]<>"NCBP")),(IF(B02.00[[#This Row],[c0210]]>'B9900'!$I$4,"OK","KO")),"OK") -> OK | EK5: =IF(AND(B02.00[[#This Row],[c0020]]<>"NCNP",B02.00[[#This Row],[c0020]]<>"NCBP"),(IF(OR(NOT(ISERROR(MATCH(B02.00[[#This Row],[c0220]],'ISO 3166'!B:B,0))),NOT(ISERROR(MATCH(B02.00[[#This Row],[c0220]],'ISO 3166'!E:E,0)))),"OK","KO")),"OK") -> OK | EL5: =IF(AND(B02.00[[#This Row],[c0020]]<>"NCNP",B02.00[[#This Row],[c0020]]<>"NCBP"),(IF(OR(B02.00[[#This Row],[c0230]]="Yes, supported by Legal Opinion",B02.00[[#This Row],[c0230]]="Yes, not supported by Legal Opinion",B02.00[[#This Row],[c0230]]="No",B02.00[[#This Row],[c0230]]="Not applicable",B02.00[[#This Row],[c0230]]="Aggregated"),"OK","KO")),"OK") -> OK | EM5: =IF(OR(B02.00[[#This Row],[c0250]]="Non-structured/Vanilla",B02.00[[#This Row],[c0250]]="Structured",B02.00[[#This Row],[c0250]]="Other non-standard terms",B02.00[[#This Row],[c0250]]="Only structured coupon",B02.00[[#This Row],[c0250]]="Aggregated"),"OK","KO") -> OK | EN5: =IF(OR(B02.00[[#This Row],[c0310]]="Secured",B02.00[[#This Row],[c0310]]="Unsecured"),"OK","KO") -> OK | EO5: =IF(AND(B02.00[[#This Row],[c0310]]="Secured",OR(B02.00[[#This Row],[c0250]]="Non-structured/Vanilla",B02.00[[#This Row],[c0250]]="Other non-standard terms"),B02.00[[#This Row],[c0240]]<>"ZCB issued at discount"),(IF(B02.00[[#This Row],[c0330]]=MAX(0,B02.00[[#This Row],[c0120]],B02.00[[#This Row],[c0320]]),"OK","KO")),"OK") -> OK | EP5: =IF(AND(B02.00[[#This Row],[c0310]]="Secured",OR(B02.00[[#This Row],[c0250]]="Structured",B02.00[[#This Row],[c0250]]="Only structured coupon")),(IF(OR(B02.00[[#This Row],[c0330]]=MAX(0,B02.00[[#This Row],[c0270]],B02.00[[#This Row],[c0320]]),B02.00[[#This Row],[c0330]]=MAX(0,B02.00[[#This Row],[c0120]],B02.00[[#This Row],[c0320]])),"OK","KO")),"OK") -> OK | EQ5: =IF(OR(B02.00[[#This Row],[c0350]]="Real estate",B02.00[[#This Row],[c0350]]="Ships",B02.00[[#This Row],[c0350]]="Aircraft",B02.00[[#This Row],[c0350]]="Financial",B02.00[[#This Row],[c0350]]="Other",B02.00[[#This Row],[c0350]]="Not applicable"),"OK","KO") -> OK | ER5: =IF(B02.00[[#This Row],[c0310]]="Unsecured",(IF(B02.00[[#This Row],[c0350]]="Not applicable","OK","KO")),"OK") -> OK | ES5: =IF(OR(B02.00[[#This Row],[c0440]]="NGN",B02.00[[#This Row],[c0440]]="CGN",B02.00[[#This Row],[c0440]]="Not applicable"),"OK","KO") -> OK | ET5: =IF(OR(B02.00[[#This Row],[c0530]]="T2 in phase-out",B02.00[[#This Row],[c0530]]="Grandfathered T2",B02.00[[#This Row],[c0530]]="Fully Compliant T2",B02.00[[#This Row],[c0530]]="Partially (A)T1 and T2",B02.00[[#This Row],[c0530]]="Grandfathered AT1",B02.00[[#This Row],[c0530]]="Fully Compliant AT1",B02.00[[#This Row],[c0530]]="CET1",B02.00[[#This Row],[c0530]]="No"),"OK","KO") -> OK | EU5: =IF(B02.00[[#This Row],[c0540]] ="","KO",IF(B02.00[[#This Row],[c0540]]>=0,"OK","KO")) -> OK | EV5: =IF(OR(B02.00[[#This Row],[c0550]]="T2 in phase-out",B02.00[[#This Row],[c0550]]="Grandfathered T2",B02.00[[#This Row],[c0550]]="Fully Compliant T2",B02.00[[#This Row],[c0550]]="Partially (A)T1 and T2",B02.00[[#This Row],[c0550]]="Grandfathered AT1",B02.00[[#This Row],[c0550]]="Fully Compliant AT1",B02.00[[#This Row],[c0550]]="CET1",B02.00[[#This Row],[c0550]]="No"),"OK","KO") -> OK | EW5: =IF(B02.00[[#This Row],[c0560]]="","KO",IF(B02.00[[#This Row],[c0560]]>=0,"OK","KO")) -> OK | EX5: =IF(OR(B02.00[[#This Row],[c0590]]="Lien",B02.00[[#This Row],[c0590]]="Guarantee",B02.00[[#This Row],[c0590]]="Surety",B02.00[[#This Row],[c0590]]="Guarantee obligation",B02.00[[#This Row],[c0590]]="Other",B02.00[[#This Row],[c0590]]="Not applicable",B02.00[[#This Row],[c0590]]="Aggregated"),"OK","KO") -> OK | EY5: =IF(B02.00[[#This Row],[c0610]]="","KO",IF(B02.00[[#This Row],[c0610]]>=0,"OK","KO")) -> OK | EZ5: =IF(OR(B02.00[[#This Row],[c0620]]="010 Financial liabilities held for trading",B02.00[[#This Row],[c0620]]="070 Financial liabilities at fair value through profit or loss",B02.00[[#This Row],[c0620]]="110 Financial liabilities at amortized cost",B02.00[[#This Row],[c0620]]="280 Other liabilities",B02.00[[#This Row],[c0620]]="300 Total equity",),"OK","KO") -> OK
A6: 2 | B6: 31641600000000000PTSTOEOM0021000 | C6: PTSTOEOM0021 | D6: ISIN | E6: 600000000 | F6: 999999999999999 | G6: EUR | H6: 600000000 | I6: 0 | J6: 8348547.9 | K6: 0 | L6: 6.0834855e+08 | M6: 6.0834855e+08 | N6: Registered Bond | O6: Not applicable | P6: Not applicable | Q6: 8 | R6: 999999999999999 | S6: 8 | T6: 2022-06-01 | U6: 2026-06-03 | V6: 2027-06-03 | W6: 2026-06-03 | X6: 2027-06-03 | Y6: PT | Z6: Yes, supported by Legal Opinion | AA6: No ZCB | AB6: Non-structured/Vanilla | AC6: 999999999999999 | AD6: 999999999999999 | AE6: FALSE | AF6: FALSE | AG6: 999999999999999 | AH6: Unsecured | AI6: 999999999999999 | AJ6: 999999999999999 | AK6: Not applicable | AL6: Not applicable | AM6: Not applicable | AN6: Nominal | AO6: 100000 | AP6: 100000 | AQ6: 6000 | AR6: 0 | AS6: =+B02.00[[#This Row],[c0100]]/B02.00[[#This Row],[c0390]] -> 1391.4247 | AT6: 0 | AU6: 999999999999999 | AV6: 999999999999999 | AW6: 999999999999999 | AX6: Not applicable | AY6: -10000 | AZ6: INTERBOLSA_PT | BA6: 529900LG70TCAGWCXT47 | BB6: Not applicable | BC6: BANCO SANTANDER TOTTA S,A, | BD6: 549300URJH9VSI58CS32 | BE6: Not applicable | BF6: Not applicable | BG6: INTERBOLSA_PT | BH6: 529900LG70TCAGWCXT47 | BI6: INTERBOLSA_PT | BJ6: 529900LG70TCAGWCXT47 | BK6: Not applicable | BL6: Not applicable | BM6: Not applicable | BN6: Not applicable | BO6: No | BP6: 0 | BQ6: No | BR6: 0 | BS6: 0 | BT6: Not applicable | BU6: Not applicable | BV6: Not applicable | BW6: FALSE | BX6: 6.0834855e+08 | BY6: 110 Financial liabilities at amortized cost | BZ6: 999999999999999 | CA6: Not applicable | CB6: FALSE | CC6: TRUE | CD6: =IF(B02.00[[#This Row],[c0010]]="","KO","OK") -> OK | CE6: =IF(B02.00[[#This Row],[c0030]]="","KO","OK") -> OK | CF6: =IF(B02.00[[#This Row],[c0040]]="","KO","OK") -> OK | CG6: =IF(B02.00[[#This Row],[c0070]]="","KO","OK") -> OK | CH6: =IF(OR(B02.00[[#This Row],[c0250]]= "Non-Structured/Vanilla",B02.00[[#This Row],[c0250]]="Other non-standard terms"),(IF(B02.00[[#This Row],[c0080]]="","KO","OK")),"OK") -> OK | CI6: =IF(OR(B02.00[[#This Row],[c0250]]= "Structured",B02.00[[#This Row],[c0250]]="Only structured coupon"),(IF(B02.00[[#This Row],[c0080]]="","KO","OK")),"OK") -> OK | CJ6: =IF(B02.00[[#This Row],[c0040]]="ISIN",(IF(B02.00[[#This Row],[c0090]]="","KO","OK")),"OK") -> OK | CK6: =IF(AND(OR(B02.00[[#This Row],[c0250]]="Non-Structured/Vanilla",B02.00[[#This Row],[c0250]]="Other non-standard terms"),B02.00[[#This Row],[c0240]]<>"ZCB issued at discount"),(IF(B02.00[[#This Row],[c0100]]="","KO","OK")),"OK") -> OK | CL6: =IF(OR(B02.00[[#This Row],[c0250]]<> "Non-Structured/Vanilla",B02.00[[#This Row],[c0460]]<>"Other non-standard terms"),IF(B02.00[[#This Row],[c0100]]="","KO","OK")) -> OK | CM6: =IF(OR(B02.00[[#This Row],[c0250]]= "Non-Structured/Vanilla",B02.00[[#This Row],[c0460]]="Other non-standard terms"),(IF(B02.00[[#This Row],[c0120]]="","KO","OK")),"OK") -> OK | CN6: =IF(OR(B02.00[[#This Row],[c0250]]<> "Structured",B02.00[[#This Row],[c0250]]<>"Only structured coupon"),(IF(B02.00[[#This Row],[c0120]]="","KO","OK")),"OK") -> OK | CO6: =IF(B02.00[[#This Row],[c0130]]="","KO","OK") -> OK | CP6: =IF(B02.00[[#This Row],[c0140]]="","KO","OK") -> OK | CQ6: =IF(B02.00[[#This Row],[c0140]]="Other",(IF(B02.00[[#This Row],[c0141]]="","KO","OK")),"OK") -> OK | CR6: =IF(B02.00[[#This Row],[c0160]]="","KO","OK") -> OK | CS6: =IF(B02.00[[#This Row],[c0162]]="","KO","OK") -> OK | CT6: =IF(AND(OR(B02.00[[#This Row],[c0250]]= "Non-Structured/Vanilla",B02.00[[#This Row],[c0250]]="Other non-standard terms"),B02.00[[#This Row],[c0240]]<>"ZCB issued at discount"),(IF(B02.00[[#This Row],[c0180]]="","KO","OK")),"OK") -> OK | CU6: =IF(AND(B02.00[[#This Row],[c0250]]<> "Structured",B02.00[[#This Row],[c0250]]<>"Only structured coupon"),(IF(B02.00[[#This Row],[c0180]]="","KO","OK")),"OK") -> OK | CV6: =IF(B02.00[[#This Row],[c0200]]="","KO","OK") -> OK | CW6: =IF(B02.00[[#This Row],[c0140]]<>"Cash account/saving account",(IF(B02.00[[#This Row],[c0210]]="","KO","OK")),"OK") -> OK | CX6: =IF(B02.00[[#This Row],[c0220]]="","KO","OK") -> OK | CY6: =IF(B02.00[[#This Row],[c0250]]="","KO","OK") -> OK | CZ6: =IF(OR(B02.00[[#This Row],[c0250]]="Structured",B02.00[[#This Row],[c0250]]="Only structured coupon"),(IF(B02.00[[#This Row],[c0260]]="","KO","OK")),"OK") -> OK | DA6: =IF(OR(B02.00[[#This Row],[c0250]]="Structured",B02.00[[#This Row],[c0250]]="Only structured coupon"),(IF(B02.00[[#This Row],[c0270]]="","KO","OK")),"OK") -> OK | DB6: =IF(OR(B02.00[[#This Row],[c0280]]="TRUE",B02.00[[#This Row],[c0290]]="TRUE"),(IF(B02.00[[#This Row],[c0300]]="","KO","OK")),"OK") -> OK | DC6: =IF(B02.00[[#This Row],[c0310]]="","KO","OK") -> OK | DD6: =IF(B02.00[[#This Row],[c0310]]="Secured",(IF(B02.00[[#This Row],[c0320]]="","KO","OK")),"OK") -> OK | DE6: =IF(B02.00[[#This Row],[c0310]]="Secured",(IF(B02.00[[#This Row],[c0330]]="","KO","OK")),"OK") -> OK | DF6: =IF(B02.00[[#This Row],[c0310]]="Secured",(IF(B02.00[[#This Row],[c0350]]="","KO","OK")),"OK") -> OK | DG6: =IF(B02.00[[#This Row],[c0350]]="Other",(IF(B02.00[[#This Row],[c0351]]="","KO","OK")),"OK") -> OK | DH6: =IF(AND(B02.00[[#This Row],[c0040]]="ISIN",B02.00[[#This Row],[c0360]]="Nominal "),(IF(B02.00[[#This Row],[c0370]]="","KO","OK")),"OK") -> OK | DI6: =IF(AND(B02.00[[#This Row],[c0040]]="ISIN",B02.00[[#This Row],[c0360]]="Unit "),(IF(B02.00[[#This Row],[c0370]]="","KO","OK")),"OK") -> OK | DJ6: =IF(B02.00[[#This Row],[c0040]]="ISIN",(IF(B02.00[[#This Row],[c0390]]="","KO","OK")),"OK") -> OK | DK6: =IF(B02.00[[#This Row],[c0040]]="ISIN",(IF(B02.00[[#This Row],[c0391]]="","KO","OK")),"OK") -> OK | DL6: =IF(AND(B02.00[[#This Row],[c0040]]="ISIN",OR(B02.00[[#This Row],[c0250]]= "Non-Structured/Vanilla",B02.00[[#This Row],[c0250]]="Other non-standard terms"),B02.00[[#This Row],[c0240]]<>"ZCB issued at discount"),(IF(B02.00[[#This Row],[c0400]]="","KO","OK")),"OK") -> OK | DM6: =IF(AND(B02.00[[#This Row],[c0040]]="ISIN",AND(B02.00[[#This Row],[c0250]]<>"Structured",B02.00[[#This Row],[c0250]]<>"Only structured coupon")),(IF(B02.00[[#This Row],[c0400]]="","KO","OK")),"OK") -> OK | DN6: =IF(B02.00[[#This Row],[c0610]]="","KO","OK") -> OK | DO6: =IF('B9900'!$H$4="Non-Resolution Entity",(IF(B02.00[[#This Row],[c5000]]="","KO","OK")),"OK") -> OK | DP6: =IF('B9900'!$H$4="Non-Resolution Entity",(IF(B02.00[[#This Row],[c5010]]="","KO","OK")),"OK") -> OK | DQ6: =IF(B02.00[[#This Row],[c0040]]="ISIN",(IF(AND(LEN(B02.00[[#This Row],[c0030]]=12),NOT(ISNUMBER(LEFT(B02.00[[#This Row],[c0030]],2)))),"OK","KO")),"OK") -> OK | DR6: =IF(AND(B02.00[[#This Row],[c0020]]<>"NCNP",B02.00[[#This Row],[c0020]]<>"NCBP"),(IF(AND(LEN(B02.00[[#This Row],[c0070]])=3,NOT(ISERROR(MATCH(UPPER(B02.00[[#This Row],[c0070]]),Tabelle1[Alphabetic Code],0)))),"OK","KO")),"OK") -> OK | DS6: =IF(B02.00[[#This Row],[c0080]]>0,"OK","KO") -> OK | DT6: =IF(B02.00[[#This Row],[c0040]]="ISIN",(IF(B02.00[[#This Row],[c0090]]>=0,"OK","KO")),"OK") -> OK | DU6: =IF(B02.00[[#This Row],[c0100]]>=0,"OK","KO") -> OK | DV6: =IF(B02.00[[#This Row],[c0110]]>=0,"OK","KO") -> OK | DW6: =IF(B02.00[[#This Row],[c0120]]>=0,"OK","KO") -> OK | DX6: =IF(B02.00[[#This Row],[c0120]]=(H6+J6+K6),"OK","KO") -> OK | DY6: =IF(OR(B02.00[[#This Row],[c0250]]="Non-structured /Vanilla",B02.00[[#This Row],[c0250]]="Other non-standard terms"),(IF(B02.00[[#This Row],[c0130]]=MAX(0,B02.00[[#This Row],[c0120]],B02.00[[#This Row],[c0300]],B02.00[[#This Row],[c0320]]),"OK","KO")),"OK") -> OK | DZ6: =IF(OR(B02.00[[#This Row],[c0250]]="Structured",B02.00[[#This Row],[c0250]]="Only structured coupon"),(IF(OR(B02.00[[#This Row],[c0130]]=MAX(0,B02.00[[#This Row],[c0270]],B02.00[[#This Row],[c0300]],B02.00[[#This Row],[c0320]]),B02.00[[#This Row],[c0130]]=MAX(0,B02.00[[#This Row],[c0120]],B02.00[[#This Row],[c0300]],B02.00[[#This Row],[c0320]])),"OK","KO")),"OK") -> OK | EA6: =IF(OR(B02.00[[#This Row],[c0140]]="Registered Bond",B02.00[[#This Row],[c0140]]="Bearrer Bond",B02.00[[#This Row],[c0140]]="Borrower Note Loan",B02.00[[#This Row],[c0140]]="Certificate of Deposit / Commercial Paper",B02.00[[#This Row],[c0140]]="Title of ownership",B02.00[[#This Row],[c0140]]="Cash account/saving account",B02.00[[#This Row],[c0140]]="Term deposit",B02.00[[#This Row],[c0140]]="Loan",B02.00[[#This Row],[c0140]]="Bill of exchange",B02.00[[#This Row],[c0140]]="Other"),"OK","KO") -> OK | EB6: =IF(B02.00[[#This Row],[c0160]]>=1,"OK","KO") -> OK | EC6: =IF(AND(B02.00[[#This Row],[c0020]]<>"NCNP",B02.00[[#This Row],[c0020]]<>"NCBP"),(IF(B02.00[[#This Row],[c0170]]>DATE(1900,1,1),"OK","KO")),"OK") -> OK | ED6: =IF(AND(OR(B02.00[[#This Row],[c0190]]<>"",B02.00[[#This Row],[c0200]]<>""),AND(B02.00[[#This Row],[c0020]]<>"NCNP",B02.00[[#This Row],[c0020]]<>"NCBP")),(IF(AND(B02.00[[#This Row],[c0170]]<B02.00[[#This Row],[c0190]],B02.00[[#This Row],[c0170]]<B02.00[[#This Row],[c0200]]),"OK","KO")),"OK") -> OK | EE6: =IF(AND(B02.00[[#This Row],[c0020]]<>"NCNP",B02.00[[#This Row],[c0020]]<>"NCBP"),IF(B02.00[[#This Row],[c0180]]="","KO",IF(B02.00[[#This Row],[c0180]]>DATE(1900,1,1),"OK","KO")),"OK") -> OK | EF6: =IF(AND('B9900'!$I$4<>"",B02.00[[#This Row],[c0020]]<>"NCNP",B02.00[[#This Row],[c0020]]<>"NCBP"),IF(B02.00[[#This Row],[c0180]]="","KO",IF(B02.00[[#This Row],[c0180]]>'B9900'!$I$4,"OK","KO")),"OK") -> OK | EG6: =IF(AND(B02.00[[#This Row],[c0020]]<>"NCNP",B02.00[[#This Row],[c0020]]<>"NCBP"),(IF(B02.00[[#This Row],[c0200]]>DATE(1900,1,1),"OK","KO")),"OK") -> OK | EH6: =IF(AND('B9900'!$I$4<>"",AND(B02.00[[#This Row],[c0020]]<>"NCNP",B02.00[[#This Row],[c0020]]<>"NCBP")),(IF(B02.00[[#This Row],[c0200]]>'B9900'!$I$4,"OK","KO")),"OK") -> OK | EI6: =IF(AND(B02.00[[#This Row],[c0020]]<>"NCNP",B02.00[[#This Row],[c0020]]<>"NCBP"),(IF(B02.00[[#This Row],[c0210]]>DATE(1900,1,1),"OK","KO")),"OK") -> OK | EJ6: =IF(AND('B9900'!$I$4<>"",AND(B02.00[[#This Row],[c0020]]<>"NCNP",B02.00[[#This Row],[c0020]]<>"NCBP")),(IF(B02.00[[#This Row],[c0210]]>'B9900'!$I$4,"OK","KO")),"OK") -> OK | EK6: =IF(AND(B02.00[[#This Row],[c0020]]<>"NCNP",B02.00[[#This Row],[c0020]]<>"NCBP"),(IF(OR(NOT(ISERROR(MATCH(B02.00[[#This Row],[c0220]],'ISO 3166'!B:B,0))),NOT(ISERROR(MATCH(B02.00[[#This Row],[c0220]],'ISO 3166'!E:E,0)))),"OK","KO")),"OK") -> OK | EL6: =IF(AND(B02.00[[#This Row],[c0020]]<>"NCNP",B02.00[[#This Row],[c0020]]<>"NCBP"),(IF(OR(B02.00[[#This Row],[c0230]]="Yes, supported by Legal Opinion",B02.00[[#This Row],[c0230]]="Yes, not supported by Legal Opinion",B02.00[[#This Row],[c0230]]="No",B02.00[[#This Row],[c0230]]="Not applicable",B02.00[[#This Row],[c0230]]="Aggregated"),"OK","KO")),"OK") -> OK | EM6: =IF(OR(B02.00[[#This Row],[c0250]]="Non-structured/Vanilla",B02.00[[#This Row],[c0250]]="Structured",B02.00[[#This Row],[c0250]]="Other non-standard terms",B02.00[[#This Row],[c0250]]="Only structured coupon",B02.00[[#This Row],[c0250]]="Aggregated"),"OK","KO") -> OK | EN6: =IF(OR(B02.00[[#This Row],[c0310]]="Secured",B02.00[[#This Row],[c0310]]="Unsecured"),"OK","KO") -> OK | EO6: =IF(AND(B02.00[[#This Row],[c0310]]="Secured",OR(B02.00[[#This Row],[c0250]]="Non-structured/Vanilla",B02.00[[#This Row],[c0250]]="Other non-standard terms"),B02.00[[#This Row],[c0240]]<>"ZCB issued at discount"),(IF(B02.00[[#This Row],[c0330]]=MAX(0,B02.00[[#This Row],[c0120]],B02.00[[#This Row],[c0320]]),"OK","KO")),"OK") -> OK | EP6: =IF(AND(B02.00[[#This Row],[c0310]]="Secured",OR(B02.00[[#This Row],[c0250]]="Structured",B02.00[[#This Row],[c0250]]="Only structured coupon")),(IF(OR(B02.00[[#This Row],[c0330]]=MAX(0,B02.00[[#This Row],[c0270]],B02.00[[#This Row],[c0320]]),B02.00[[#This Row],[c0330]]=MAX(0,B02.00[[#This Row],[c0120]],B02.00[[#This Row],[c0320]])),"OK","KO")),"OK") -> OK | EQ6: =IF(OR(B02.00[[#This Row],[c0350]]="Real estate",B02.00[[#This Row],[c0350]]="Ships",B02.00[[#This Row],[c0350]]="Aircraft",B02.00[[#This Row],[c0350]]="Financial",B02.00[[#This Row],[c0350]]="Other",B02.00[[#This Row],[c0350]]="Not applicable"),"OK","KO") -> OK | ER6: =IF(B02.00[[#This Row],[c0310]]="Unsecured",(IF(B02.00[[#This Row],[c0350]]="Not applicable","OK","KO")),"OK") -> OK | ES6: =IF(OR(B02.00[[#This Row],[c0440]]="NGN",B02.00[[#This Row],[c0440]]="CGN",B02.00[[#This Row],[c0440]]="Not applicable"),"OK","KO") -> OK | ET6: =IF(OR(B02.00[[#This Row],[c0530]]="T2 in phase-out",B02.00[[#This Row],[c0530]]="Grandfathered T2",B02.00[[#This Row],[c0530]]="Fully Compliant T2",B02.00[[#This Row],[c0530]]="Partially (A)T1 and T2",B02.00[[#This Row],[c0530]]="Grandfathered AT1",B02.00[[#This Row],[c0530]]="Fully Compliant AT1",B02.00[[#This Row],[c0530]]="CET1",B02.00[[#This Row],[c0530]]="No"),"OK","KO") -> OK | EU6: =IF(B02.00[[#This Row],[c0540]] ="","KO",IF(B02.00[[#This Row],[c0540]]>=0,"OK","KO")) -> OK | EV6: =IF(OR(B02.00[[#This Row],[c0550]]="T2 in phase-out",B02.00[[#This Row],[c0550]]="Grandfathered T2",B02.00[[#This Row],[c0550]]="Fully Compliant T2",B02.00[[#This Row],[c0550]]="Partially (A)T1 and T2",B02.00[[#This Row],[c0550]]="Grandfathered AT1",B02.00[[#This Row],[c0550]]="Fully Compliant AT1",B02.00[[#This Row],[c0550]]="CET1",B02.00[[#This Row],[c0550]]="No"),"OK","KO") -> OK | EW6: =IF(B02.00[[#This Row],[c0560]]="","KO",IF(B02.00[[#This Row],[c0560]]>=0,"OK","KO")) -> OK | EX6: =IF(OR(B02.00[[#This Row],[c0590]]="Lien",B02.00[[#This Row],[c0590]]="Guarantee",B02.00[[#This Row],[c0590]]="Surety",B02.00[[#This Row],[c0590]]="Guarantee obligation",B02.00[[#This Row],[c0590]]="Other",B02.00[[#This Row],[c0590]]="Not applicable",B02.00[[#This Row],[c0590]]="Aggregated"),"OK","KO") -> OK | EY6: =IF(B02.00[[#This Row],[c0610]]="","KO",IF(B02.00[[#This Row],[c0610]]>=0,"OK","KO")) -> OK | EZ6: =IF(OR(B02.00[[#This Row],[c0620]]="010 Financial liabilities held for trading",B02.00[[#This Row],[c0620]]="070 Financial liabilities at fair value through profit or loss",B02.00[[#This Row],[c0620]]="110 Financial liabilities at amortized cost",B02.00[[#This Row],[c0620]]="280 Other liabilities",B02.00[[#This Row],[c0620]]="300 Total equity",),"OK","KO") -> OK
A7: 3 | B7: 31641600000000000PTSTOFOM0004000 | C7: PTSTOFOM0004 | D7: ISIN | E7: 200000000 | F7: 999999999999999 | G7: EUR | H7: 200000000 | I7: 0 | J7: 4106991.8 | K7: 0 | L7: 2.0410699e+08 | M7: 2.0410699e+08 | N7: Registered Bond | O7: Not applicable | P7: Not applicable | Q7: 3 | R7: 999999999999999 | S7: 3 | T7: 2022-06-07 | U7: 2026-06-09 | V7: 2027-06-09 | W7: 2027-06-09 | X7: 2027-06-09 | Y7: PT | Z7: Yes, supported by Legal Opinion | AA7: No ZCB | AB7: Non-structured/Vanilla | AC7: 999999999999999 | AD7: 999999999999999 | AE7: FALSE | AF7: FALSE | AG7: 999999999999999 | AH7: Unsecured | AI7: 999999999999999 | AJ7: 999999999999999 | AK7: Not applicable | AL7: Not applicable | AM7: Not applicable | AN7: Nominal | AO7: 100000 | AP7: 100000 | AQ7: 2000 | AR7: 0 | AS7: =+B02.00[[#This Row],[c0100]]/B02.00[[#This Row],[c0390]] -> 2053.4959 | AT7: 0 | AU7: 999999999999999 | AV7: 999999999999999 | AW7: 999999999999999 | AX7: Not applicable | AY7: -10000 | AZ7: INTERBOLSA_PT | BA7: 529900LG70TCAGWCXT47 | BB7: Not applicable | BC7: BANCO SANTANDER TOTTA S,A, | BD7: 549300URJH9VSI58CS32 | BE7: Not applicable | BF7: Not applicable | BG7: INTERBOLSA_PT | BH7: 529900LG70TCAGWCXT47 | BI7: INTERBOLSA_PT | BJ7: 529900LG70TCAGWCXT47 | BK7: Not applicable | BL7: Not applicable | BM7: Not applicable | BN7: Not applicable | BO7: Fully Compliant T2 | BP7: 2.0410699e+08 | BQ7: Fully Compliant T2 | BR7: 2.0410699e+08 | BS7: 0 | BT7: Not applicable | BU7: Not applicable | BV7: Not applicable | BW7: FALSE | BX7: 2.0410699e+08 | BY7: 110 Financial liabilities at amortized cost | BZ7: 999999999999999 | CA7: Not applicable | CB7: FALSE | CC7: TRUE | CD7: =IF(B02.00[[#This Row],[c0010]]="","KO","OK") -> OK | CE7: =IF(B02.00[[#This Row],[c0030]]="","KO","OK") -> OK | CF7: =IF(B02.00[[#This Row],[c0040]]="","KO","OK") -> OK | CG7: =IF(B02.00[[#This Row],[c0070]]="","KO","OK") -> OK | CH7: =IF(OR(B02.00[[#This Row],[c0250]]= "Non-Structured/Vanilla",B02.00[[#This Row],[c0250]]="Other non-standard terms"),(IF(B02.00[[#This Row],[c0080]]="","KO","OK")),"OK") -> OK | CI7: =IF(OR(B02.00[[#This Row],[c0250]]= "Structured",B02.00[[#This Row],[c0250]]="Only structured coupon"),(IF(B02.00[[#This Row],[c0080]]="","KO","OK")),"OK") -> OK | CJ7: =IF(B02.00[[#This Row],[c0040]]="ISIN",(IF(B02.00[[#This Row],[c0090]]="","KO","OK")),"OK") -> OK | CK7: =IF(AND(OR(B02.00[[#This Row],[c0250]]="Non-Structured/Vanilla",B02.00[[#This Row],[c0250]]="Other non-standard terms"),B02.00[[#This Row],[c0240]]<>"ZCB issued at discount"),(IF(B02.00[[#This Row],[c0100]]="","KO","OK")),"OK") -> OK | CL7: =IF(OR(B02.00[[#This Row],[c0250]]<> "Non-Structured/Vanilla",B02.00[[#This Row],[c0460]]<>"Other non-standard terms"),IF(B02.00[[#This Row],[c0100]]="","KO","OK")) -> OK | CM7: =IF(OR(B02.00[[#This Row],[c0250]]= "Non-Structured/Vanilla",B02.00[[#This Row],[c0460]]="Other non-standard terms"),(IF(B02.00[[#This Row],[c0120]]="","KO","OK")),"OK") -> OK | CN7: =IF(OR(B02.00[[#This Row],[c0250]]<> "Structured",B02.00[[#This Row],[c0250]]<>"Only structured coupon"),(IF(B02.00[[#This Row],[c0120]]="","KO","OK")),"OK") -> OK | CO7: =IF(B02.00[[#This Row],[c0130]]="","KO","OK") -> OK | CP7: =IF(B02.00[[#This Row],[c0140]]="","KO","OK") -> OK | CQ7: =IF(B02.00[[#This Row],[c0140]]="Other",(IF(B02.00[[#This Row],[c0141]]="","KO","OK")),"OK") -> OK | CR7: =IF(B02.00[[#This Row],[c0160]]="","KO","OK") -> OK | CS7: =IF(B02.00[[#This Row],[c0162]]="","KO","OK") -> OK | CT7: =IF(AND(OR(B02.00[[#This Row],[c0250]]= "Non-Structured/Vanilla",B02.00[[#This Row],[c0250]]="Other non-standard terms"),B02.00[[#This Row],[c0240]]<>"ZCB issued at discount"),(IF(B02.00[[#This Row],[c0180]]="","KO","OK")),"OK") -> OK | CU7: =IF(AND(B02.00[[#This Row],[c0250]]<> "Structured",B02.00[[#This Row],[c0250]]<>"Only structured coupon"),(IF(B02.00[[#This Row],[c0180]]="","KO","OK")),"OK") -> OK | CV7: =IF(B02.00[[#This Row],[c0200]]="","KO","OK") -> OK | CW7: =IF(B02.00[[#This Row],[c0140]]<>"Cash account/saving account",(IF(B02.00[[#This Row],[c0210]]="","KO","OK")),"OK") -> OK | CX7: =IF(B02.00[[#This Row],[c0220]]="","KO","OK") -> OK | CY7: =IF(B02.00[[#This Row],[c0250]]="","KO","OK") -> OK | CZ7: =IF(OR(B02.00[[#This Row],[c0250]]="Structured",B02.00[[#This Row],[c0250]]="Only structured coupon"),(IF(B02.00[[#This Row],[c0260]]="","KO","OK")),"OK") -> OK | DA7: =IF(OR(B02.00[[#This Row],[c0250]]="Structured",B02.00[[#This Row],[c0250]]="Only structured coupon"),(IF(B02.00[[#This Row],[c0270]]="","KO","OK")),"OK") -> OK | DB7: =IF(OR(B02.00[[#This Row],[c0280]]="TRUE",B02.00[[#This Row],[c0290]]="TRUE"),(IF(B02.00[[#This Row],[c0300]]="","KO","OK")),"OK") -> OK | DC7: =IF(B02.00[[#This Row],[c0310]]="","KO","OK") -> OK | DD7: =IF(B02.00[[#This Row],[c0310]]="Secured",(IF(B02.00[[#This Row],[c0320]]="","KO","OK")),"OK") -> OK | DE7: =IF(B02.00[[#This Row],[c0310]]="Secured",(IF(B02.00[[#This Row],[c0330]]="","KO","OK")),"OK") -> OK | DF7: =IF(B02.00[[#This Row],[c0310]]="Secured",(IF(B02.00[[#This Row],[c0350]]="","KO","OK")),"OK") -> OK | DG7: =IF(B02.00[[#This Row],[c0350]]="Other",(IF(B02.00[[#This Row],[c0351]]="","KO","OK")),"OK") -> OK | DH7: =IF(AND(B02.00[[#This Row],[c0040]]="ISIN",B02.00[[#This Row],[c0360]]="Nominal "),(IF(B02.00[[#This Row],[c0370]]="","KO","OK")),"OK") -> OK | DI7: =IF(AND(B02.00[[#This Row],[c0040]]="ISIN",B02.00[[#This Row],[c0360]]="Unit "),(IF(B02.00[[#This Row],[c0370]]="","KO","OK")),"OK") -> OK | DJ7: =IF(B02.00[[#This Row],[c0040]]="ISIN",(IF(B02.00[[#This Row],[c0390]]="","KO","OK")),"OK") -> OK | DK7: =IF(B02.00[[#This Row],[c0040]]="ISIN",(IF(B02.00[[#This Row],[c0391]]="","KO","OK")),"OK") -> OK | DL7: =IF(AND(B02.00[[#This Row],[c0040]]="ISIN",OR(B02.00[[#This Row],[c0250]]= "Non-Structured/Vanilla",B02.00[[#This Row],[c0250]]="Other non-standard terms"),B02.00[[#This Row],[c0240]]<>"ZCB issued at discount"),(IF(B02.00[[#This Row],[c0400]]="","KO","OK")),"OK") -> OK | DM7: =IF(AND(B02.00[[#This Row],[c0040]]="ISIN",AND(B02.00[[#This Row],[c0250]]<>"Structured",B02.00[[#This Row],[c0250]]<>"Only structured coupon")),(IF(B02.00[[#This Row],[c0400]]="","KO","OK")),"OK") -> OK | DN7: =IF(B02.00[[#This Row],[c0610]]="","KO","OK") -> OK | DO7: =IF('B9900'!$H$4="Non-Resolution Entity",(IF(B02.00[[#This Row],[c5000]]="","KO","OK")),"OK") -> OK | DP7: =IF('B9900'!$H$4="Non-Resolution Entity",(IF(B02.00[[#This Row],[c5010]]="","KO","OK")),"OK") -> OK | DQ7: =IF(B02.00[[#This Row],[c0040]]="ISIN",(IF(AND(LEN(B02.00[[#This Row],[c0030]]=12),NOT(ISNUMBER(LEFT(B02.00[[#This Row],[c0030]],2)))),"OK","KO")),"OK") -> OK | DR7: =IF(AND(B02.00[[#This Row],[c0020]]<>"NCNP",B02.00[[#This Row],[c0020]]<>"NCBP"),(IF(AND(LEN(B02.00[[#This Row],[c0070]])=3,NOT(ISERROR(MATCH(UPPER(B02.00[[#This Row],[c0070]]),Tabelle1[Alphabetic Code],0)))),"OK","KO")),"OK") -> OK | DS7: =IF(B02.00[[#This Row],[c0080]]>0,"OK","KO") -> OK | DT7: =IF(B02.00[[#This Row],[c0040]]="ISIN",(IF(B02.00[[#This Row],[c0090]]>=0,"OK","KO")),"OK") -> OK | DU7: =IF(B02.00[[#This Row],[c0100]]>=0,"OK","KO") -> OK | DV7: =IF(B02.00[[#This Row],[c0110]]>=0,"OK","KO") -> OK | DW7: =IF(B02.00[[#This Row],[c0120]]>=0,"OK","KO") -> OK | DX7: =IF(B02.00[[#This Row],[c0120]]=(H7+J7+K7),"OK","KO") -> OK | DY7: =IF(OR(B02.00[[#This Row],[c0250]]="Non-structured /Vanilla",B02.00[[#This Row],[c0250]]="Other non-standard terms"),(IF(B02.00[[#This Row],[c0130]]=MAX(0,B02.00[[#This Row],[c0120]],B02.00[[#This Row],[c0300]],B02.00[[#This Row],[c0320]]),"OK","KO")),"OK") -> OK | DZ7: =IF(OR(B02.00[[#This Row],[c0250]]="Structured",B02.00[[#This Row],[c0250]]="Only structured coupon"),(IF(OR(B02.00[[#This Row],[c0130]]=MAX(0,B02.00[[#This Row],[c0270]],B02.00[[#This Row],[c0300]],B02.00[[#This Row],[c0320]]),B02.00[[#This Row],[c0130]]=MAX(0,B02.00[[#This Row],[c0120]],B02.00[[#This Row],[c0300]],B02.00[[#This Row],[c0320]])),"OK","KO")),"OK") -> OK | EA7: =IF(OR(B02.00[[#This Row],[c0140]]="Registered Bond",B02.00[[#This Row],[c0140]]="Bearrer Bond",B02.00[[#This Row],[c0140]]="Borrower Note Loan",B02.00[[#This Row],[c0140]]="Certificate of Deposit / Commercial Paper",B02.00[[#This Row],[c0140]]="Title of ownership",B02.00[[#This Row],[c0140]]="Cash account/saving account",B02.00[[#This Row],[c0140]]="Term deposit",B02.00[[#This Row],[c0140]]="Loan",B02.00[[#This Row],[c0140]]="Bill of exchange",B02.00[[#This Row],[c0140]]="Other"),"OK","KO") -> OK | EB7: =IF(B02.00[[#This Row],[c0160]]>=1,"OK","KO") -> OK | EC7: =IF(AND(B02.00[[#This Row],[c0020]]<>"NCNP",B02.00[[#This Row],[c0020]]<>"NCBP"),(IF(B02.00[[#This Row],[c0170]]>DATE(1900,1,1),"OK","KO")),"OK") -> OK | ED7: =IF(AND(OR(B02.00[[#This Row],[c0190]]<>"",B02.00[[#This Row],[c0200]]<>""),AND(B02.00[[#This Row],[c0020]]<>"NCNP",B02.00[[#This Row],[c0020]]<>"NCBP")),(IF(AND(B02.00[[#This Row],[c0170]]<B02.00[[#This Row],[c0190]],B02.00[[#This Row],[c0170]]<B02.00[[#This Row],[c0200]]),"OK","KO")),"OK") -> OK | EE7: =IF(AND(B02.00[[#This Row],[c0020]]<>"NCNP",B02.00[[#This Row],[c0020]]<>"NCBP"),IF(B02.00[[#This Row],[c0180]]="","KO",IF(B02.00[[#This Row],[c0180]]>DATE(1900,1,1),"OK","KO")),"OK") -> OK | EF7: =IF(AND('B9900'!$I$4<>"",B02.00[[#This Row],[c0020]]<>"NCNP",B02.00[[#This Row],[c0020]]<>"NCBP"),IF(B02.00[[#This Row],[c0180]]="","KO",IF(B02.00[[#This Row],[c0180]]>'B9900'!$I$4,"OK","KO")),"OK") -> OK | EG7: =IF(AND(B02.00[[#This Row],[c0020]]<>"NCNP",B02.00[[#This Row],[c0020]]<>"NCBP"),(IF(B02.00[[#This Row],[c0200]]>DATE(1900,1,1),"OK","KO")),"OK") -> OK | EH7: =IF(AND('B9900'!$I$4<>"",AND(B02.00[[#This Row],[c0020]]<>"NCNP",B02.00[[#This Row],[c0020]]<>"NCBP")),(IF(B02.00[[#This Row],[c0200]]>'B9900'!$I$4,"OK","KO")),"OK") -> OK | EI7: =IF(AND(B02.00[[#This Row],[c0020]]<>"NCNP",B02.00[[#This Row],[c0020]]<>"NCBP"),(IF(B02.00[[#This Row],[c0210]]>DATE(1900,1,1),"OK","KO")),"OK") -> OK | EJ7: =IF(AND('B9900'!$I$4<>"",AND(B02.00[[#This Row],[c0020]]<>"NCNP",B02.00[[#This Row],[c0020]]<>"NCBP")),(IF(B02.00[[#This Row],[c0210]]>'B9900'!$I$4,"OK","KO")),"OK") -> OK | EK7: =IF(AND(B02.00[[#This Row],[c0020]]<>"NCNP",B02.00[[#This Row],[c0020]]<>"NCBP"),(IF(OR(NOT(ISERROR(MATCH(B02.00[[#This Row],[c0220]],'ISO 3166'!B:B,0))),NOT(ISERROR(MATCH(B02.00[[#This Row],[c0220]],'ISO 3166'!E:E,0)))),"OK","KO")),"OK") -> OK | EL7: =IF(AND(B02.00[[#This Row],[c0020]]<>"NCNP",B02.00[[#This Row],[c0020]]<>"NCBP"),(IF(OR(B02.00[[#This Row],[c0230]]="Yes, supported by Legal Opinion",B02.00[[#This Row],[c0230]]="Yes, not supported by Legal Opinion",B02.00[[#This Row],[c0230]]="No",B02.00[[#This Row],[c0230]]="Not applicable",B02.00[[#This Row],[c0230]]="Aggregated"),"OK","KO")),"OK") -> OK | EM7: =IF(OR(B02.00[[#This Row],[c0250]]="Non-structured/Vanilla",B02.00[[#This Row],[c0250]]="Structured",B02.00[[#This Row],[c0250]]="Other non-standard terms",B02.00[[#This Row],[c0250]]="Only structured coupon",B02.00[[#This Row],[c0250]]="Aggregated"),"OK","KO") -> OK | EN7: =IF(OR(B02.00[[#This Row],[c0310]]="Secured",B02.00[[#This Row],[c0310]]="Unsecured"),"OK","KO") -> OK | EO7: =IF(AND(B02.00[[#This Row],[c0310]]="Secured",OR(B02.00[[#This Row],[c0250]]="Non-structured/Vanilla",B02.00[[#This Row],[c0250]]="Other non-standard terms"),B02.00[[#This Row],[c0240]]<>"ZCB issued at discount"),(IF(B02.00[[#This Row],[c0330]]=MAX(0,B02.00[[#This Row],[c0120]],B02.00[[#This Row],[c0320]]),"OK","KO")),"OK") -> OK | EP7: =IF(AND(B02.00[[#This Row],[c0310]]="Secured",OR(B02.00[[#This Row],[c0250]]="Structured",B02.00[[#This Row],[c0250]]="Only structured coupon")),(IF(OR(B02.00[[#This Row],[c0330]]=MAX(0,B02.00[[#This Row],[c0270]],B02.00[[#This Row],[c0320]]),B02.00[[#This Row],[c0330]]=MAX(0,B02.00[[#This Row],[c0120]],B02.00[[#This Row],[c0320]])),"OK","KO")),"OK") -> OK | EQ7: =IF(OR(B02.00[[#This Row],[c0350]]="Real estate",B02.00[[#This Row],[c0350]]="Ships",B02.00[[#This Row],[c0350]]="Aircraft",B02.00[[#This Row],[c0350]]="Financial",B02.00[[#This Row],[c0350]]="Other",B02.00[[#This Row],[c0350]]="Not applicable"),"OK","KO") -> OK | ER7: =IF(B02.00[[#This Row],[c0310]]="Unsecured",(IF(B02.00[[#This Row],[c0350]]="Not applicable","OK","KO")),"OK") -> OK | ES7: =IF(OR(B02.00[[#This Row],[c0440]]="NGN",B02.00[[#This Row],[c0440]]="CGN",B02.00[[#This Row],[c0440]]="Not applicable"),"OK","KO") -> OK | ET7: =IF(OR(B02.00[[#This Row],[c0530]]="T2 in phase-out",B02.00[[#This Row],[c0530]]="Grandfathered T2",B02.00[[#This Row],[c0530]]="Fully Compliant T2",B02.00[[#This Row],[c0530]]="Partially (A)T1 and T2",B02.00[[#This Row],[c0530]]="Grandfathered AT1",B02.00[[#This Row],[c0530]]="Fully Compliant AT1",B02.00[[#This Row],[c0530]]="CET1",B02.00[[#This Row],[c0530]]="No"),"OK","KO") -> OK | EU7: =IF(B02.00[[#This Row],[c0540]] ="","KO",IF(B02.00[[#This Row],[c0540]]>=0,"OK","KO")) -> OK | EV7: =IF(OR(B02.00[[#This Row],[c0550]]="T2 in phase-out",B02.00[[#This Row],[c0550]]="Grandfathered T2",B02.00[[#This Row],[c0550]]="Fully Compliant T2",B02.00[[#This Row],[c0550]]="Partially (A)T1 and T2",B02.00[[#This Row],[c0550]]="Grandfathered AT1",B02.00[[#This Row],[c0550]]="Fully Compliant AT1",B02.00[[#This Row],[c0550]]="CET1",B02.00[[#This Row],[c0550]]="No"),"OK","KO") -> OK | EW7: =IF(B02.00[[#This Row],[c0560]]="","KO",IF(B02.00[[#This Row],[c0560]]>=0,"OK","KO")) -> OK | EX7: =IF(OR(B02.00[[#This Row],[c0590]]="Lien",B02.00[[#This Row],[c0590]]="Guarantee",B02.00[[#This Row],[c0590]]="Surety",B02.00[[#This Row],[c0590]]="Guarantee obligation",B02.00[[#This Row],[c0590]]="Other",B02.00[[#This Row],[c0590]]="Not applicable",B02.00[[#This Row],[c0590]]="Aggregated"),"OK","KO") -> OK | EY7: =IF(B02.00[[#This Row],[c0610]]="","KO",IF(B02.00[[#This Row],[c0610]]>=0,"OK","KO")) -> OK | EZ7: =IF(OR(B02.00[[#This Row],[c0620]]="010 Financial liabilities held for trading",B02.00[[#This Row],[c0620]]="070 Financial liabilities at fair value through profit or loss",B02.00[[#This Row],[c0620]]="110 Financial liabilities at amortized cost",B02.00[[#This Row],[c0620]]="280 Other liabilities",B02.00[[#This Row],[c0620]]="300 Total equity",),"OK","KO") -> OK
A8: 4 | B8: 31641600000000000PTSTOGOM0003000 | C8: PTSTOGOM0003 | D8: ISIN | E8: 300000000 | F8: 999999999999999 | G8: EUR | H8: 300000000 | I8: 0 | J8: 0 | K8: 0 | L8: 300000000 | M8: 300000000 | N8: Title of ownership | O8: Not applicable | P8: Not applicable | Q8: 2 | R8: 999999999999999 | S8: 2 | T8: 2024-02-22 | U8: 0001-01-01 | V8: 2099-01-31 | W8: 2099-01-31 | X8: 2099-01-31 | Y8: PT | Z8: Yes, supported by Legal Opinion | AA8: No ZCB | AB8: Non-structured/Vanilla | AC8: 999999999999999 | AD8: 999999999999999 | AE8: FALSE | AF8: FALSE | AG8: 999999999999999 | AH8: Unsecured | AI8: 999999999999999 | AJ8: 999999999999999 | AK8: Not applicable | AL8: Not applicable | AM8: Not applicable | AN8: Nominal | AO8: 100000 | AP8: 100000 | AQ8: 3000 | AR8: 0 | AS8: 0 | AT8: 0 | AU8: 999999999999999 | AV8: 999999999999999 | AW8: 999999999999999 | AX8: Not applicable | AY8: -10000 | AZ8: INTERBOLSA_PT | BA8: 529900LG70TCAGWCXT47 | BB8: Not applicable | BC8: BANCO SANTANDER TOTTA S,A, | BD8: 549300URJH9VSI58CS32 | BE8: Not applicable | BF8: Not applicable | BG8: INTERBOLSA_PT | BH8: 529900LG70TCAGWCXT47 | BI8: INTERBOLSA_PT | BJ8: 529900LG70TCAGWCXT47 | BK8: Not applicable | BL8: Not applicable | BM8: Not applicable | BN8: Not applicable | BO8: Fully Compliant AT1 | BP8: 300000000 | BQ8: Fully Compliant AT1 | BR8: 300000000 | BS8: 0 | BT8: Not applicable | BU8: Not applicable | BV8: Not applicable | BW8: FALSE | BX8: 300000000 | BY8: 300 Total equity | BZ8: 999999999999999 | CA8: Not applicable | CB8: FALSE | CC8: TRUE | CD8: =IF(B02.00[[#This Row],[c0010]]="","KO","OK") -> OK | CE8: =IF(B02.00[[#This Row],[c0030]]="","KO","OK") -> OK | CF8: =IF(B02.00[[#This Row],[c0040]]="","KO","OK") -> OK | CG8: =IF(B02.00[[#This Row],[c0070]]="","KO","OK") -> OK | CH8: =IF(OR(B02.00[[#This Row],[c0250]]= "Non-Structured/Vanilla",B02.00[[#This Row],[c0250]]="Other non-standard terms"),(IF(B02.00[[#This Row],[c0080]]="","KO","OK")),"OK") -> OK | CI8: =IF(OR(B02.00[[#This Row],[c0250]]= "Structured",B02.00[[#This Row],[c0250]]="Only structured coupon"),(IF(B02.00[[#This Row],[c0080]]="","KO","OK")),"OK") -> OK | CJ8: =IF(B02.00[[#This Row],[c0040]]="ISIN",(IF(B02.00[[#This Row],[c0090]]="","KO","OK")),"OK") -> OK | CK8: =IF(AND(OR(B02.00[[#This Row],[c0250]]="Non-Structured/Vanilla",B02.00[[#This Row],[c0250]]="Other non-standard terms"),B02.00[[#This Row],[c0240]]<>"ZCB issued at discount"),(IF(B02.00[[#This Row],[c0100]]="","KO","OK")),"OK") -> OK | CL8: =IF(OR(B02.00[[#This Row],[c0250]]<> "Non-Structured/Vanilla",B02.00[[#This Row],[c0460]]<>"Other non-standard terms"),IF(B02.00[[#This Row],[c0100]]="","KO","OK")) -> OK | CM8: =IF(OR(B02.00[[#This Row],[c0250]]= "Non-Structured/Vanilla",B02.00[[#This Row],[c0460]]="Other non-standard terms"),(IF(B02.00[[#This Row],[c0120]]="","KO","OK")),"OK") -> OK | CN8: =IF(OR(B02.00[[#This Row],[c0250]]<> "Structured",B02.00[[#This Row],[c0250]]<>"Only structured coupon"),(IF(B02.00[[#This Row],[c0120]]="","KO","OK")),"OK") -> OK | CO8: =IF(B02.00[[#This Row],[c0130]]="","KO","OK") -> OK | CP8: =IF(B02.00[[#This Row],[c0140]]="","KO","OK") -> OK | CQ8: =IF(B02.00[[#This Row],[c0140]]="Other",(IF(B02.00[[#This Row],[c0141]]="","KO","OK")),"OK") -> OK | CR8: =IF(B02.00[[#This Row],[c0160]]="","KO","OK") -> OK | CS8: =IF(B02.00[[#This Row],[c0162]]="","KO","OK") -> OK | CT8: =IF(AND(OR(B02.00[[#This Row],[c0250]]= "Non-Structured/Vanilla",B02.00[[#This Row],[c0250]]="Other non-standard terms"),B02.00[[#This Row],[c0240]]<>"ZCB issued at discount"),(IF(B02.00[[#This Row],[c0180]]="","KO","OK")),"OK") -> OK | CU8: =IF(AND(B02.00[[#This Row],[c0250]]<> "Structured",B02.00[[#This Row],[c0250]]<>"Only structured coupon"),(IF(B02.00[[#This Row],[c0180]]="","KO","OK")),"OK") -> OK | CV8: =IF(B02.00[[#This Row],[c0200]]="","KO","OK") -> OK | CW8: =IF(B02.00[[#This Row],[c0140]]<>"Cash account/saving account",(IF(B02.00[[#This Row],[c0210]]="","KO","OK")),"OK") -> OK | CX8: =IF(B02.00[[#This Row],[c0220]]="","KO","OK") -> OK | CY8: =IF(B02.00[[#This Row],[c0250]]="","KO","OK") -> OK | CZ8: =IF(OR(B02.00[[#This Row],[c0250]]="Structured",B02.00[[#This Row],[c0250]]="Only structured coupon"),(IF(B02.00[[#This Row],[c0260]]="","KO","OK")),"OK") -> OK | DA8: =IF(OR(B02.00[[#This Row],[c0250]]="Structured",B02.00[[#This Row],[c0250]]="Only structured coupon"),(IF(B02.00[[#This Row],[c0270]]="","KO","OK")),"OK") -> OK | DB8: =IF(OR(B02.00[[#This Row],[c0280]]="TRUE",B02.00[[#This Row],[c0290]]="TRUE"),(IF(B02.00[[#This Row],[c0300]]="","KO","OK")),"OK") -> OK | DC8: =IF(B02.00[[#This Row],[c0310]]="","KO","OK") -> OK | DD8: =IF(B02.00[[#This Row],[c0310]]="Secured",(IF(B02.00[[#This Row],[c0320]]="","KO","OK")),"OK") -> OK | DE8: =IF(B02.00[[#This Row],[c0310]]="Secured",(IF(B02.00[[#This Row],[c0330]]="","KO","OK")),"OK") -> OK | DF8: =IF(B02.00[[#This Row],[c0310]]="Secured",(IF(B02.00[[#This Row],[c0350]]="","KO","OK")),"OK") -> OK | DG8: =IF(B02.00[[#This Row],[c0350]]="Other",(IF(B02.00[[#This Row],[c0351]]="","KO","OK")),"OK") -> OK | DH8: =IF(AND(B02.00[[#This Row],[c0040]]="ISIN",B02.00[[#This Row],[c0360]]="Nominal "),(IF(B02.00[[#This Row],[c0370]]="","KO","OK")),"OK") -> OK | DI8: =IF(AND(B02.00[[#This Row],[c0040]]="ISIN",B02.00[[#This Row],[c0360]]="Unit "),(IF(B02.00[[#This Row],[c0370]]="","KO","OK")),"OK") -> OK | DJ8: =IF(B02.00[[#This Row],[c0040]]="ISIN",(IF(B02.00[[#This Row],[c0390]]="","KO","OK")),"OK") -> OK | DK8: =IF(B02.00[[#This Row],[c0040]]="ISIN",(IF(B02.00[[#This Row],[c0391]]="","KO","OK")),"OK") -> OK | DL8: =IF(AND(B02.00[[#This Row],[c0040]]="ISIN",OR(B02.00[[#This Row],[c0250]]= "Non-Structured/Vanilla",B02.00[[#This Row],[c0250]]="Other non-standard terms"),B02.00[[#This Row],[c0240]]<>"ZCB issued at discount"),(IF(B02.00[[#This Row],[c0400]]="","KO","OK")),"OK") -> OK | DM8: =IF(AND(B02.00[[#This Row],[c0040]]="ISIN",AND(B02.00[[#This Row],[c0250]]<>"Structured",B02.00[[#This Row],[c0250]]<>"Only structured coupon")),(IF(B02.00[[#This Row],[c0400]]="","KO","OK")),"OK") -> OK | DN8: =IF(B02.00[[#This Row],[c0610]]="","KO","OK") -> OK | DO8: =IF('B9900'!$H$4="Non-Resolution Entity",(IF(B02.00[[#This Row],[c5000]]="","KO","OK")),"OK") -> OK | DP8: =IF('B9900'!$H$4="Non-Resolution Entity",(IF(B02.00[[#This Row],[c5010]]="","KO","OK")),"OK") -> OK | DQ8: =IF(B02.00[[#This Row],[c0040]]="ISIN",(IF(AND(LEN(B02.00[[#This Row],[c0030]]=12),NOT(ISNUMBER(LEFT(B02.00[[#This Row],[c0030]],2)))),"OK","KO")),"OK") -> OK | DR8: =IF(AND(B02.00[[#This Row],[c0020]]<>"NCNP",B02.00[[#This Row],[c0020]]<>"NCBP"),(IF(AND(LEN(B02.00[[#This Row],[c0070]])=3,NOT(ISERROR(MATCH(UPPER(B02.00[[#This Row],[c0070]]),Tabelle1[Alphabetic Code],0)))),"OK","KO")),"OK") -> OK | DS8: =IF(B02.00[[#This Row],[c0080]]>0,"OK","KO") -> OK | DT8: =IF(B02.00[[#This Row],[c0040]]="ISIN",(IF(B02.00[[#This Row],[c0090]]>=0,"OK","KO")),"OK") -> OK | DU8: =IF(B02.00[[#This Row],[c0100]]>=0,"OK","KO") -> OK | DV8: =IF(B02.00[[#This Row],[c0110]]>=0,"OK","KO") -> OK | DW8: =IF(B02.00[[#This Row],[c0120]]>=0,"OK","KO") -> OK | DX8: =IF(B02.00[[#This Row],[c0120]]=(H8+J8+K8),"OK","KO") -> OK | DY8: =IF(OR(B02.00[[#This Row],[c0250]]="Non-structured /Vanilla",B02.00[[#This Row],[c0250]]="Other non-standard terms"),(IF(B02.00[[#This Row],[c0130]]=MAX(0,B02.00[[#This Row],[c0120]],B02.00[[#This Row],[c0300]],B02.00[[#This Row],[c0320]]),"OK","KO")),"OK") -> OK | DZ8: =IF(OR(B02.00[[#This Row],[c0250]]="Structured",B02.00[[#This Row],[c0250]]="Only structured coupon"),(IF(OR(B02.00[[#This Row],[c0130]]=MAX(0,B02.00[[#This Row],[c0270]],B02.00[[#This Row],[c0300]],B02.00[[#This Row],[c0320]]),B02.00[[#This Row],[c0130]]=MAX(0,B02.00[[#This Row],[c0120]],B02.00[[#This Row],[c0300]],B02.00[[#This Row],[c0320]])),"OK","KO")),"OK") -> OK | EA8: =IF(OR(B02.00[[#This Row],[c0140]]="Registered Bond",B02.00[[#This Row],[c0140]]="Bearrer Bond",B02.00[[#This Row],[c0140]]="Borrower Note Loan",B02.00[[#This Row],[c0140]]="Certificate of Deposit / Commercial Paper",B02.00[[#This Row],[c0140]]="Title of ownership",B02.00[[#This Row],[c0140]]="Cash account/saving account",B02.00[[#This Row],[c0140]]="Term deposit",B02.00[[#This Row],[c0140]]="Loan",B02.00[[#This Row],[c0140]]="Bill of exchange",B02.00[[#This Row],[c0140]]="Other"),"OK","KO") -> OK | EB8: =IF(B02.00[[#This Row],[c0160]]>=1,"OK","KO") -> OK | EC8: =IF(AND(B02.00[[#This Row],[c0020]]<>"NCNP",B02.00[[#This Row],[c0020]]<>"NCBP"),(IF(B02.00[[#This Row],[c0170]]>DATE(1900,1,1),"OK","KO")),"OK") -> OK | ED8: =IF(AND(OR(B02.00[[#This Row],[c0190]]<>"",B02.00[[#This Row],[c0200]]<>""),AND(B02.00[[#This Row],[c0020]]<>"NCNP",B02.00[[#This Row],[c0020]]<>"NCBP")),(IF(AND(B02.00[[#This Row],[c0170]]<B02.00[[#This Row],[c0190]],B02.00[[#This Row],[c0170]]<B02.00[[#This Row],[c0200]]),"OK","KO")),"OK") -> OK | EE8: =IF(AND(B02.00[[#This Row],[c0020]]<>"NCNP",B02.00[[#This Row],[c0020]]<>"NCBP"),IF(B02.00[[#This Row],[c0180]]="","KO",IF(B02.00[[#This Row],[c0180]]>DATE(1900,1,1),"OK","KO")),"OK") -> OK | EF8: =IF(AND('B9900'!$I$4<>"",B02.00[[#This Row],[c0020]]<>"NCNP",B02.00[[#This Row],[c0020]]<>"NCBP"),IF(B02.00[[#This Row],[c0180]]="","KO",IF(B02.00[[#This Row],[c0180]]>'B9900'!$I$4,"OK","KO")),"OK") -> OK | EG8: =IF(AND(B02.00[[#This Row],[c0020]]<>"NCNP",B02.00[[#This Row],[c0020]]<>"NCBP"),(IF(B02.00[[#This Row],[c0200]]>DATE(1900,1,1),"OK","KO")),"OK") -> OK | EH8: =IF(AND('B9900'!$I$4<>"",AND(B02.00[[#This Row],[c0020]]<>"NCNP",B02.00[[#This Row],[c0020]]<>"NCBP")),(IF(B02.00[[#This Row],[c0200]]>'B9900'!$I$4,"OK","KO")),"OK") -> OK | EI8: =IF(AND(B02.00[[#This Row],[c0020]]<>"NCNP",B02.00[[#This Row],[c0020]]<>"NCBP"),(IF(B02.00[[#This Row],[c0210]]>DATE(1900,1,1),"OK","KO")),"OK") -> OK | EJ8: =IF(AND('B9900'!$I$4<>"",AND(B02.00[[#This Row],[c0020]]<>"NCNP",B02.00[[#This Row],[c0020]]<>"NCBP")),(IF(B02.00[[#This Row],[c0210]]>'B9900'!$I$4,"OK","KO")),"OK") -> OK | EK8: =IF(AND(B02.00[[#This Row],[c0020]]<>"NCNP",B02.00[[#This Row],[c0020]]<>"NCBP"),(IF(OR(NOT(ISERROR(MATCH(B02.00[[#This Row],[c0220]],'ISO 3166'!B:B,0))),NOT(ISERROR(MATCH(B02.00[[#This Row],[c0220]],'ISO 3166'!E:E,0)))),"OK","KO")),"OK") -> OK | EL8: =IF(AND(B02.00[[#This Row],[c0020]]<>"NCNP",B02.00[[#This Row],[c0020]]<>"NCBP"),(IF(OR(B02.00[[#This Row],[c0230]]="Yes, supported by Legal Opinion",B02.00[[#This Row],[c0230]]="Yes, not supported by Legal Opinion",B02.00[[#This Row],[c0230]]="No",B02.00[[#This Row],[c0230]]="Not applicable",B02.00[[#This Row],[c0230]]="Aggregated"),"OK","KO")),"OK") -> OK | EM8: =IF(OR(B02.00[[#This Row],[c0250]]="Non-structured/Vanilla",B02.00[[#This Row],[c0250]]="Structured",B02.00[[#This Row],[c0250]]="Other non-standard terms",B02.00[[#This Row],[c0250]]="Only structured coupon",B02.00[[#This Row],[c0250]]="Aggregated"),"OK","KO") -> OK | EN8: =IF(OR(B02.00[[#This Row],[c0310]]="Secured",B02.00[[#This Row],[c0310]]="Unsecured"),"OK","KO") -> OK | EO8: =IF(AND(B02.00[[#This Row],[c0310]]="Secured",OR(B02.00[[#This Row],[c0250]]="Non-structured/Vanilla",B02.00[[#This Row],[c0250]]="Other non-standard terms"),B02.00[[#This Row],[c0240]]<>"ZCB issued at discount"),(IF(B02.00[[#This Row],[c0330]]=MAX(0,B02.00[[#This Row],[c0120]],B02.00[[#This Row],[c0320]]),"OK","KO")),"OK") -> OK | EP8: =IF(AND(B02.00[[#This Row],[c0310]]="Secured",OR(B02.00[[#This Row],[c0250]]="Structured",B02.00[[#This Row],[c0250]]="Only structured coupon")),(IF(OR(B02.00[[#This Row],[c0330]]=MAX(0,B02.00[[#This Row],[c0270]],B02.00[[#This Row],[c0320]]),B02.00[[#This Row],[c0330]]=MAX(0,B02.00[[#This Row],[c0120]],B02.00[[#This Row],[c0320]])),"OK","KO")),"OK") -> OK | EQ8: =IF(OR(B02.00[[#This Row],[c0350]]="Real estate",B02.00[[#This Row],[c0350]]="Ships",B02.00[[#This Row],[c0350]]="Aircraft",B02.00[[#This Row],[c0350]]="Financial",B02.00[[#This Row],[c0350]]="Other",B02.00[[#This Row],[c0350]]="Not applicable"),"OK","KO") -> OK | ER8: =IF(B02.00[[#This Row],[c0310]]="Unsecured",(IF(B02.00[[#This Row],[c0350]]="Not applicable","OK","KO")),"OK") -> OK | ES8: =IF(OR(B02.00[[#This Row],[c0440]]="NGN",B02.00[[#This Row],[c0440]]="CGN",B02.00[[#This Row],[c0440]]="Not applicable"),"OK","KO") -> OK | ET8: =IF(OR(B02.00[[#This Row],[c0530]]="T2 in phase-out",B02.00[[#This Row],[c0530]]="Grandfathered T2",B02.00[[#This Row],[c0530]]="Fully Compliant T2",B02.00[[#This Row],[c0530]]="Partially (A)T1 and T2",B02.00[[#This Row],[c0530]]="Grandfathered AT1",B02.00[[#This Row],[c0530]]="Fully Compliant AT1",B02.00[[#This Row],[c0530]]="CET1",B02.00[[#This Row],[c0530]]="No"),"OK","KO") -> OK | EU8: =IF(B02.00[[#This Row],[c0540]] ="","KO",IF(B02.00[[#This Row],[c0540]]>=0,"OK","KO")) -> OK | EV8: =IF(OR(B02.00[[#This Row],[c0550]]="T2 in phase-out",B02.00[[#This Row],[c0550]]="Grandfathered T2",B02.00[[#This Row],[c0550]]="Fully Compliant T2",B02.00[[#This Row],[c0550]]="Partially (A)T1 and T2",B02.00[[#This Row],[c0550]]="Grandfathered AT1",B02.00[[#This Row],[c0550]]="Fully Compliant AT1",B02.00[[#This Row],[c0550]]="CET1",B02.00[[#This Row],[c0550]]="No"),"OK","KO") -> OK | EW8: =IF(B02.00[[#This Row],[c0560]]="","KO",IF(B02.00[[#This Row],[c0560]]>=0,"OK","KO")) -> OK | EX8: =IF(OR(B02.00[[#This Row],[c0590]]="Lien",B02.00[[#This Row],[c0590]]="Guarantee",B02.00[[#This Row],[c0590]]="Surety",B02.00[[#This Row],[c0590]]="Guarantee obligation",B02.00[[#This Row],[c0590]]="Other",B02.00[[#This Row],[c0590]]="Not applicable",B02.00[[#This Row],[c0590]]="Aggregated"),"OK","KO") -> OK | EY8: =IF(B02.00[[#This Row],[c0610]]="","KO",IF(B02.00[[#This Row],[c0610]]>=0,"OK","KO")) -> OK | EZ8: =IF(OR(B02.00[[#This Row],[c0620]]="010 Financial liabilities held for trading",B02.00[[#This Row],[c0620]]="070 Financial liabilities at fair value through profit or loss",B02.00[[#This Row],[c0620]]="110 Financial liabilities at amortized cost",B02.00[[#This Row],[c0620]]="280 Other liabilities",B02.00[[#This Row],[c0620]]="300 Total equity",),"OK","KO") -> OK
A9: 5 | B9: 31641600000000000PTSTOHOM0002000 | C9: PTSTOHOM0002 | D9: ISIN | E9: 500000000 | F9: 999999999999999 | G9: EUR | H9: 500000000 | I9: 0 | J9: 6011013.7 | K9: 0 | L9: 5.0601101e+08 | M9: 5.0601101e+08 | N9: Registered Bond | O9: Not applicable | P9: Not applicable | Q9: 8 | R9: 999999999999999 | S9: 8 | T9: 2024-07-30 | U9: 2026-07-30 | V9: 2030-07-30 | W9: 2029-07-30 | X9: 2030-07-30 | Y9: PT | Z9: Yes, supported by Legal Opinion | AA9: No ZCB | AB9: Non-structured/Vanilla | AC9: 999999999999999 | AD9: 999999999999999 | AE9: FALSE | AF9: FALSE | AG9: 999999999999999 | AH9: Unsecured | AI9: 999999999999999 | AJ9: 999999999999999 | AK9: Not applicable | AL9: Not applicable | AM9: Not applicable | AN9: Nominal | AO9: 100000 | AP9: 100000 | AQ9: 5000 | AR9: 0 | AS9: =+B02.00[[#This Row],[c0100]]/B02.00[[#This Row],[c0390]] -> 1202.2027 | AT9: 0 | AU9: 999999999999999 | AV9: 999999999999999 | AW9: 999999999999999 | AX9: Not applicable | AY9: -10000 | AZ9: INTERBOLSA_PT | BA9: 529900LG70TCAGWCXT47 | BB9: Not applicable | BC9: BANCO SANTANDER TOTTA S,A, | BD9: 549300URJH9VSI58CS32 | BE9: Not applicable | BF9: Not applicable | BG9: INTERBOLSA_PT | BH9: 529900LG70TCAGWCXT47 | BI9: INTERBOLSA_PT | BJ9: 529900LG70TCAGWCXT47 | BK9: Not applicable | BL9: Not applicable | BM9: Not applicable | BN9: Not applicable | BO9: No | BP9: 0 | BQ9: No | BR9: 0 | BS9: 0 | BT9: Not applicable | BU9: Not applicable | BV9: Not applicable | BW9: FALSE | BX9: 5.0601101e+08 | BY9: 110 Financial liabilities at amortized cost | BZ9: 999999999999999 | CA9: Not applicable | CB9: FALSE | CC9: TRUE | CD9: =IF(B02.00[[#This Row],[c0010]]="","KO","OK") -> OK | CE9: =IF(B02.00[[#This Row],[c0030]]="","KO","OK") -> OK | CF9: =IF(B02.00[[#This Row],[c0040]]="","KO","OK") -> OK | CG9: =IF(B02.00[[#This Row],[c0070]]="","KO","OK") -> OK | CH9: =IF(OR(B02.00[[#This Row],[c0250]]= "Non-Structured/Vanilla",B02.00[[#This Row],[c0250]]="Other non-standard terms"),(IF(B02.00[[#This Row],[c0080]]="","KO","OK")),"OK") -> OK | CI9: =IF(OR(B02.00[[#This Row],[c0250]]= "Structured",B02.00[[#This Row],[c0250]]="Only structured coupon"),(IF(B02.00[[#This Row],[c0080]]="","KO","OK")),"OK") -> OK | CJ9: =IF(B02.00[[#This Row],[c0040]]="ISIN",(IF(B02.00[[#This Row],[c0090]]="","KO","OK")),"OK") -> OK | CK9: =IF(AND(OR(B02.00[[#This Row],[c0250]]="Non-Structured/Vanilla",B02.00[[#This Row],[c0250]]="Other non-standard terms"),B02.00[[#This Row],[c0240]]<>"ZCB issued at discount"),(IF(B02.00[[#This Row],[c0100]]="","KO","OK")),"OK") -> OK | CL9: =IF(OR(B02.00[[#This Row],[c0250]]<> "Non-Structured/Vanilla",B02.00[[#This Row],[c0460]]<>"Other non-standard terms"),IF(B02.00[[#This Row],[c0100]]="","KO","OK")) -> OK | CM9: =IF(OR(B02.00[[#This Row],[c0250]]= "Non-Structured/Vanilla",B02.00[[#This Row],[c0460]]="Other non-standard terms"),(IF(B02.00[[#This Row],[c0120]]="","KO","OK")),"OK") -> OK | CN9: =IF(OR(B02.00[[#This Row],[c0250]]<> "Structured",B02.00[[#This Row],[c0250]]<>"Only structured coupon"),(IF(B02.00[[#This Row],[c0120]]="","KO","OK")),"OK") -> OK | CO9: =IF(B02.00[[#This Row],[c0130]]="","KO","OK") -> OK | CP9: =IF(B02.00[[#This Row],[c0140]]="","KO","OK") -> OK | CQ9: =IF(B02.00[[#This Row],[c0140]]="Other",(IF(B02.00[[#This Row],[c0141]]="","KO","OK")),"OK") -> OK | CR9: =IF(B02.00[[#This Row],[c0160]]="","KO","OK") -> OK | CS9: =IF(B02.00[[#This Row],[c0162]]="","KO","OK") -> OK | CT9: =IF(AND(OR(B02.00[[#This Row],[c0250]]= "Non-Structured/Vanilla",B02.00[[#This Row],[c0250]]="Other non-standard terms"),B02.00[[#This Row],[c0240]]<>"ZCB issued at discount"),(IF(B02.00[[#This Row],[c0180]]="","KO","OK")),"OK") -> OK | CU9: =IF(AND(B02.00[[#This Row],[c0250]]<> "Structured",B02.00[[#This Row],[c0250]]<>"Only structured coupon"),(IF(B02.00[[#This Row],[c0180]]="","KO","OK")),"OK") -> OK | CV9: =IF(B02.00[[#This Row],[c0200]]="","KO","OK") -> OK | CW9: =IF(B02.00[[#This Row],[c0140]]<>"Cash account/saving account",(IF(B02.00[[#This Row],[c0210]]="","KO","OK")),"OK") -> OK | CX9: =IF(B02.00[[#This Row],[c0220]]="","KO","OK") -> OK | CY9: =IF(B02.00[[#This Row],[c0250]]="","KO","OK") -> OK | CZ9: =IF(OR(B02.00[[#This Row],[c0250]]="Structured",B02.00[[#This Row],[c0250]]="Only structured coupon"),(IF(B02.00[[#This Row],[c0260]]="","KO","OK")),"OK") -> OK | DA9: =IF(OR(B02.00[[#This Row],[c0250]]="Structured",B02.00[[#This Row],[c0250]]="Only structured coupon"),(IF(B02.00[[#This Row],[c0270]]="","KO","OK")),"OK") -> OK | DB9: =IF(OR(B02.00[[#This Row],[c0280]]="TRUE",B02.00[[#This Row],[c0290]]="TRUE"),(IF(B02.00[[#This Row],[c0300]]="","KO","OK")),"OK") -> OK | DC9: =IF(B02.00[[#This Row],[c0310]]="","KO","OK") -> OK | DD9: =IF(B02.00[[#This Row],[c0310]]="Secured",(IF(B02.00[[#This Row],[c0320]]="","KO","OK")),"OK") -> OK | DE9: =IF(B02.00[[#This Row],[c0310]]="Secured",(IF(B02.00[[#This Row],[c0330]]="","KO","OK")),"OK") -> OK | DF9: =IF(B02.00[[#This Row],[c0310]]="Secured",(IF(B02.00[[#This Row],[c0350]]="","KO","OK")),"OK") -> OK | DG9: =IF(B02.00[[#This Row],[c0350]]="Other",(IF(B02.00[[#This Row],[c0351]]="","KO","OK")),"OK") -> OK | DH9: =IF(AND(B02.00[[#This Row],[c0040]]="ISIN",B02.00[[#This Row],[c0360]]="Nominal "),(IF(B02.00[[#This Row],[c0370]]="","KO","OK")),"OK") -> OK | DI9: =IF(AND(B02.00[[#This Row],[c0040]]="ISIN",B02.00[[#This Row],[c0360]]="Unit "),(IF(B02.00[[#This Row],[c0370]]="","KO","OK")),"OK") -> OK | DJ9: =IF(B02.00[[#This Row],[c0040]]="ISIN",(IF(B02.00[[#This Row],[c0390]]="","KO","OK")),"OK") -> OK | DK9: =IF(B02.00[[#This Row],[c0040]]="ISIN",(IF(B02.00[[#This Row],[c0391]]="","KO","OK")),"OK") -> OK | DL9: =IF(AND(B02.00[[#This Row],[c0040]]="ISIN",OR(B02.00[[#This Row],[c0250]]= "Non-Structured/Vanilla",B02.00[[#This Row],[c0250]]="Other non-standard terms"),B02.00[[#This Row],[c0240]]<>"ZCB issued at discount"),(IF(B02.00[[#This Row],[c0400]]="","KO","OK")),"OK") -> OK | DM9: =IF(AND(B02.00[[#This Row],[c0040]]="ISIN",AND(B02.00[[#This Row],[c0250]]<>"Structured",B02.00[[#This Row],[c0250]]<>"Only structured coupon")),(IF(B02.00[[#This Row],[c0400]]="","KO","OK")),"OK") -> OK | DN9: =IF(B02.00[[#This Row],[c0610]]="","KO","OK") -> OK | DO9: =IF('B9900'!$H$4="Non-Resolution Entity",(IF(B02.00[[#This Row],[c5000]]="","KO","OK")),"OK") -> OK | DP9: =IF('B9900'!$H$4="Non-Resolution Entity",(IF(B02.00[[#This Row],[c5010]]="","KO","OK")),"OK") -> OK | DQ9: =IF(B02.00[[#This Row],[c0040]]="ISIN",(IF(AND(LEN(B02.00[[#This Row],[c0030]]=12),NOT(ISNUMBER(LEFT(B02.00[[#This Row],[c0030]],2)))),"OK","KO")),"OK") -> OK | DR9: =IF(AND(B02.00[[#This Row],[c0020]]<>"NCNP",B02.00[[#This Row],[c0020]]<>"NCBP"),(IF(AND(LEN(B02.00[[#This Row],[c0070]])=3,NOT(ISERROR(MATCH(UPPER(B02.00[[#This Row],[c0070]]),Tabelle1[Alphabetic Code],0)))),"OK","KO")),"OK") -> OK | DS9: =IF(B02.00[[#This Row],[c0080]]>0,"OK","KO") -> OK | DT9: =IF(B02.00[[#This Row],[c0040]]="ISIN",(IF(B02.00[[#This Row],[c0090]]>=0,"OK","KO")),"OK") -> OK | DU9: =IF(B02.00[[#This Row],[c0100]]>=0,"OK","KO") -> OK | DV9: =IF(B02.00[[#This Row],[c0110]]>=0,"OK","KO") -> OK | DW9: =IF(B02.00[[#This Row],[c0120]]>=0,"OK","KO") -> OK | DX9: =IF(B02.00[[#This Row],[c0120]]=(H9+J9+K9),"OK","KO") -> OK | DY9: =IF(OR(B02.00[[#This Row],[c0250]]="Non-structured /Vanilla",B02.00[[#This Row],[c0250]]="Other non-standard terms"),(IF(B02.00[[#This Row],[c0130]]=MAX(0,B02.00[[#This Row],[c0120]],B02.00[[#This Row],[c0300]],B02.00[[#This Row],[c0320]]),"OK","KO")),"OK") -> OK | DZ9: =IF(OR(B02.00[[#This Row],[c0250]]="Structured",B02.00[[#This Row],[c0250]]="Only structured coupon"),(IF(OR(B02.00[[#This Row],[c0130]]=MAX(0,B02.00[[#This Row],[c0270]],B02.00[[#This Row],[c0300]],B02.00[[#This Row],[c0320]]),B02.00[[#This Row],[c0130]]=MAX(0,B02.00[[#This Row],[c0120]],B02.00[[#This Row],[c0300]],B02.00[[#This Row],[c0320]])),"OK","KO")),"OK") -> OK | EA9: =IF(OR(B02.00[[#This Row],[c0140]]="Registered Bond",B02.00[[#This Row],[c0140]]="Bearrer Bond",B02.00[[#This Row],[c0140]]="Borrower Note Loan",B02.00[[#This Row],[c0140]]="Certificate of Deposit / Commercial Paper",B02.00[[#This Row],[c0140]]="Title of ownership",B02.00[[#This Row],[c0140]]="Cash account/saving account",B02.00[[#This Row],[c0140]]="Term deposit",B02.00[[#This Row],[c0140]]="Loan",B02.00[[#This Row],[c0140]]="Bill of exchange",B02.00[[#This Row],[c0140]]="Other"),"OK","KO") -> OK | EB9: =IF(B02.00[[#This Row],[c0160]]>=1,"OK","KO") -> OK | EC9: =IF(AND(B02.00[[#This Row],[c0020]]<>"NCNP",B02.00[[#This Row],[c0020]]<>"NCBP"),(IF(B02.00[[#This Row],[c0170]]>DATE(1900,1,1),"OK","KO")),"OK") -> OK | ED9: =IF(AND(OR(B02.00[[#This Row],[c0190]]<>"",B02.00[[#This Row],[c0200]]<>""),AND(B02.00[[#This Row],[c0020]]<>"NCNP",B02.00[[#This Row],[c0020]]<>"NCBP")),(IF(AND(B02.00[[#This Row],[c0170]]<B02.00[[#This Row],[c0190]],B02.00[[#This Row],[c0170]]<B02.00[[#This Row],[c0200]]),"OK","KO")),"OK") -> OK | EE9: =IF(AND(B02.00[[#This Row],[c0020]]<>"NCNP",B02.00[[#This Row],[c0020]]<>"NCBP"),IF(B02.00[[#This Row],[c0180]]="","KO",IF(B02.00[[#This Row],[c0180]]>DATE(1900,1,1),"OK","KO")),"OK") -> OK | EF9: =IF(AND('B9900'!$I$4<>"",B02.00[[#This Row],[c0020]]<>"NCNP",B02.00[[#This Row],[c0020]]<>"NCBP"),IF(B02.00[[#This Row],[c0180]]="","KO",IF(B02.00[[#This Row],[c0180]]>'B9900'!$I$4,"OK","KO")),"OK") -> OK | EG9: =IF(AND(B02.00[[#This Row],[c0020]]<>"NCNP",B02.00[[#This Row],[c0020]]<>"NCBP"),(IF(B02.00[[#This Row],[c0200]]>DATE(1900,1,1),"OK","KO")),"OK") -> OK | EH9: =IF(AND('B9900'!$I$4<>"",AND(B02.00[[#This Row],[c0020]]<>"NCNP",B02.00[[#This Row],[c0020]]<>"NCBP")),(IF(B02.00[[#This Row],[c0200]]>'B9900'!$I$4,"OK","KO")),"OK") -> OK | EI9: =IF(AND(B02.00[[#This Row],[c0020]]<>"NCNP",B02.00[[#This Row],[c0020]]<>"NCBP"),(IF(B02.00[[#This Row],[c0210]]>DATE(1900,1,1),"OK","KO")),"OK") -> OK | EJ9: =IF(AND('B9900'!$I$4<>"",AND(B02.00[[#This Row],[c0020]]<>"NCNP",B02.00[[#This Row],[c0020]]<>"NCBP")),(IF(B02.00[[#This Row],[c0210]]>'B9900'!$I$4,"OK","KO")),"OK") -> OK | EK9: =IF(AND(B02.00[[#This Row],[c0020]]<>"NCNP",B02.00[[#This Row],[c0020]]<>"NCBP"),(IF(OR(NOT(ISERROR(MATCH(B02.00[[#This Row],[c0220]],'ISO 3166'!B:B,0))),NOT(ISERROR(MATCH(B02.00[[#This Row],[c0220]],'ISO 3166'!E:E,0)))),"OK","KO")),"OK") -> OK | EL9: =IF(AND(B02.00[[#This Row],[c0020]]<>"NCNP",B02.00[[#This Row],[c0020]]<>"NCBP"),(IF(OR(B02.00[[#This Row],[c0230]]="Yes, supported by Legal Opinion",B02.00[[#This Row],[c0230]]="Yes, not supported by Legal Opinion",B02.00[[#This Row],[c0230]]="No",B02.00[[#This Row],[c0230]]="Not applicable",B02.00[[#This Row],[c0230]]="Aggregated"),"OK","KO")),"OK") -> OK | EM9: =IF(OR(B02.00[[#This Row],[c0250]]="Non-structured/Vanilla",B02.00[[#This Row],[c0250]]="Structured",B02.00[[#This Row],[c0250]]="Other non-standard terms",B02.00[[#This Row],[c0250]]="Only structured coupon",B02.00[[#This Row],[c0250]]="Aggregated"),"OK","KO") -> OK | EN9: =IF(OR(B02.00[[#This Row],[c0310]]="Secured",B02.00[[#This Row],[c0310]]="Unsecured"),"OK","KO") -> OK | EO9: =IF(AND(B02.00[[#This Row],[c0310]]="Secured",OR(B02.00[[#This Row],[c0250]]="Non-structured/Vanilla",B02.00[[#This Row],[c0250]]="Other non-standard terms"),B02.00[[#This Row],[c0240]]<>"ZCB issued at discount"),(IF(B02.00[[#This Row],[c0330]]=MAX(0,B02.00[[#This Row],[c0120]],B02.00[[#This Row],[c0320]]),"OK","KO")),"OK") -> OK | EP9: =IF(AND(B02.00[[#This Row],[c0310]]="Secured",OR(B02.00[[#This Row],[c0250]]="Structured",B02.00[[#This Row],[c0250]]="Only structured coupon")),(IF(OR(B02.00[[#This Row],[c0330]]=MAX(0,B02.00[[#This Row],[c0270]],B02.00[[#This Row],[c0320]]),B02.00[[#This Row],[c0330]]=MAX(0,B02.00[[#This Row],[c0120]],B02.00[[#This Row],[c0320]])),"OK","KO")),"OK") -> OK | EQ9: =IF(OR(B02.00[[#This Row],[c0350]]="Real estate",B02.00[[#This Row],[c0350]]="Ships",B02.00[[#This Row],[c0350]]="Aircraft",B02.00[[#This Row],[c0350]]="Financial",B02.00[[#This Row],[c0350]]="Other",B02.00[[#This Row],[c0350]]="Not applicable"),"OK","KO") -> OK | ER9: =IF(B02.00[[#This Row],[c0310]]="Unsecured",(IF(B02.00[[#This Row],[c0350]]="Not applicable","OK","KO")),"OK") -> OK | ES9: =IF(OR(B02.00[[#This Row],[c0440]]="NGN",B02.00[[#This Row],[c0440]]="CGN",B02.00[[#This Row],[c0440]]="Not applicable"),"OK","KO") -> OK | ET9: =IF(OR(B02.00[[#This Row],[c0530]]="T2 in phase-out",B02.00[[#This Row],[c0530]]="Grandfathered T2",B02.00[[#This Row],[c0530]]="Fully Compliant T2",B02.00[[#This Row],[c0530]]="Partially (A)T1 and T2",B02.00[[#This Row],[c0530]]="Grandfathered AT1",B02.00[[#This Row],[c0530]]="Fully Compliant AT1",B02.00[[#This Row],[c0530]]="CET1",B02.00[[#This Row],[c0530]]="No"),"OK","KO") -> OK | EU9: =IF(B02.00[[#This Row],[c0540]] ="","KO",IF(B02.00[[#This Row],[c0540]]>=0,"OK","KO")) -> OK | EV9: =IF(OR(B02.00[[#This Row],[c0550]]="T2 in phase-out",B02.00[[#This Row],[c0550]]="Grandfathered T2",B02.00[[#This Row],[c0550]]="Fully Compliant T2",B02.00[[#This Row],[c0550]]="Partially (A)T1 and T2",B02.00[[#This Row],[c0550]]="Grandfathered AT1",B02.00[[#This Row],[c0550]]="Fully Compliant AT1",B02.00[[#This Row],[c0550]]="CET1",B02.00[[#This Row],[c0550]]="No"),"OK","KO") -> OK | EW9: =IF(B02.00[[#This Row],[c0560]]="","KO",IF(B02.00[[#This Row],[c0560]]>=0,"OK","KO")) -> OK | EX9: =IF(OR(B02.00[[#This Row],[c0590]]="Lien",B02.00[[#This Row],[c0590]]="Guarantee",B02.00[[#This Row],[c0590]]="Surety",B02.00[[#This Row],[c0590]]="Guarantee obligation",B02.00[[#This Row],[c0590]]="Other",B02.00[[#This Row],[c0590]]="Not applicable",B02.00[[#This Row],[c0590]]="Aggregated"),"OK","KO") -> OK | EY9: =IF(B02.00[[#This Row],[c0610]]="","KO",IF(B02.00[[#This Row],[c0610]]>=0,"OK","KO")) -> OK | EZ9: =IF(OR(B02.00[[#This Row],[c0620]]="010 Financial liabilities held for trading",B02.00[[#This Row],[c0620]]="070 Financial liabilities at fair value through profit or loss",B02.00[[#This Row],[c0620]]="110 Financial liabilities at amortized cost",B02.00[[#This Row],[c0620]]="280 Other liabilities",B02.00[[#This Row],[c0620]]="300 Total equity",),"OK","KO") -> OK
A10: 6 | B10: 31641600005800007PTBSRDOM0037000 | C10: PTBSRDOM0037 | D10: ISIN | E10: 500000000 | F10: 999999999999999 | G10: EUR | H10: 500000000 | I10: 0 | J10: 0 | K10: 0 | L10: 500000000 | M10: 500000000 | N10: Title of ownership | O10: Not applicable | P10: Not applicable | Q10: 2 | R10: 999999999999999 | S10: 2 | T10: 2025-05-29 | U10: 0001-01-01 | V10: 2099-01-31 | W10: 2099-01-31 | X10: 2099-01-31 | Y10: PT | Z10: Yes, supported by Legal Opinion | AA10: No ZCB | AB10: Non-structured/Vanilla | AC10: 999999999999999 | AD10: 999999999999999 | AE10: FALSE | AF10: FALSE | AG10: 999999999999999 | AH10: Unsecured | AI10: 999999999999999 | AJ10: 999999999999999 | AK10: Not applicable | AL10: Not applicable | AM10: Not applicable | AN10: Nominal | AO10: 100000 | AP10: 100000 | AQ10: 5000 | AR10: 0 | AS10: 0 | AT10: 0 | AU10: 999999999999999 | AV10: 999999999999999 | AW10: 999999999999999 | AX10: Not applicable | AY10: -10000 | AZ10: INTERBOLSA_PT | BA10: 529900LG70TCAGWCXT47 | BB10: Not applicable | BC10: BANCO SANTANDER TOTTA S,A, | BD10: 549300URJH9VSI58CS32 | BE10: Not applicable | BF10: Not applicable | BG10: INTERBOLSA_PT | BH10: 529900LG70TCAGWCXT47 | BI10: INTERBOLSA_PT | BJ10: 529900LG70TCAGWCXT47 | BK10: Not applicable | BL10: Not applicable | BM10: Not applicable | BN10: Not applicable | BO10: Fully Compliant AT1 | BP10: 500000000 | BQ10: Fully Compliant AT1 | BR10: 500000000 | BS10: 0 | BT10: Not applicable | BU10: Not applicable | BV10: Not applicable | BW10: FALSE | BX10: 500000000 | BY10: 300 Total equity | BZ10: 999999999999999 | CA10: Not applicable | CB10: FALSE | CC10: TRUE | CD10: =IF(B02.00[[#This Row],[c0010]]="","KO","OK") -> OK | CE10: =IF(B02.00[[#This Row],[c0030]]="","KO","OK") -> OK | CF10: =IF(B02.00[[#This Row],[c0040]]="","KO","OK") -> OK | CG10: =IF(B02.00[[#This Row],[c0070]]="","KO","OK") -> OK | CH10: =IF(OR(B02.00[[#This Row],[c0250]]= "Non-Structured/Vanilla",B02.00[[#This Row],[c0250]]="Other non-standard terms"),(IF(B02.00[[#This Row],[c0080]]="","KO","OK")),"OK") -> OK | CI10: =IF(OR(B02.00[[#This Row],[c0250]]= "Structured",B02.00[[#This Row],[c0250]]="Only structured coupon"),(IF(B02.00[[#This Row],[c0080]]="","KO","OK")),"OK") -> OK | CJ10: =IF(B02.00[[#This Row],[c0040]]="ISIN",(IF(B02.00[[#This Row],[c0090]]="","KO","OK")),"OK") -> OK | CK10: =IF(AND(OR(B02.00[[#This Row],[c0250]]="Non-Structured/Vanilla",B02.00[[#This Row],[c0250]]="Other non-standard terms"),B02.00[[#This Row],[c0240]]<>"ZCB issued at discount"),(IF(B02.00[[#This Row],[c0100]]="","KO","OK")),"OK") -> OK | CL10: =IF(OR(B02.00[[#This Row],[c0250]]<> "Non-Structured/Vanilla",B02.00[[#This Row],[c0460]]<>"Other non-standard terms"),IF(B02.00[[#This Row],[c0100]]="","KO","OK")) -> OK | CM10: =IF(OR(B02.00[[#This Row],[c0250]]= "Non-Structured/Vanilla",B02.00[[#This Row],[c0460]]="Other non-standard terms"),(IF(B02.00[[#This Row],[c0120]]="","KO","OK")),"OK") -> OK | CN10: =IF(OR(B02.00[[#This Row],[c0250]]<> "Structured",B02.00[[#This Row],[c0250]]<>"Only structured coupon"),(IF(B02.00[[#This Row],[c0120]]="","KO","OK")),"OK") -> OK | CO10: =IF(B02.00[[#This Row],[c0130]]="","KO","OK") -> OK | CP10: =IF(B02.00[[#This Row],[c0140]]="","KO","OK") -> OK | CQ10: =IF(B02.00[[#This Row],[c0140]]="Other",(IF(B02.00[[#This Row],[c0141]]="","KO","OK")),"OK") -> OK | CR10: =IF(B02.00[[#This Row],[c0160]]="","KO","OK") -> OK | CS10: =IF(B02.00[[#This Row],[c0162]]="","KO","OK") -> OK | CT10: =IF(AND(OR(B02.00[[#This Row],[c0250]]= "Non-Structured/Vanilla",B02.00[[#This Row],[c0250]]="Other non-standard terms"),B02.00[[#This Row],[c0240]]<>"ZCB issued at discount"),(IF(B02.00[[#This Row],[c0180]]="","KO","OK")),"OK") -> OK | CU10: =IF(AND(B02.00[[#This Row],[c0250]]<> "Structured",B02.00[[#This Row],[c0250]]<>"Only structured coupon"),(IF(B02.00[[#This Row],[c0180]]="","KO","OK")),"OK") -> OK | CV10: =IF(B02.00[[#This Row],[c0200]]="","KO","OK") -> OK | CW10: =IF(B02.00[[#This Row],[c0140]]<>"Cash account/saving account",(IF(B02.00[[#This Row],[c0210]]="","KO","OK")),"OK") -> OK | CX10: =IF(B02.00[[#This Row],[c0220]]="","KO","OK") -> OK | CY10: =IF(B02.00[[#This Row],[c0250]]="","KO","OK") -> OK | CZ10: =IF(OR(B02.00[[#This Row],[c0250]]="Structured",B02.00[[#This Row],[c0250]]="Only structured coupon"),(IF(B02.00[[#This Row],[c0260]]="","KO","OK")),"OK") -> OK | DA10: =IF(OR(B02.00[[#This Row],[c0250]]="Structured",B02.00[[#This Row],[c0250]]="Only structured coupon"),(IF(B02.00[[#This Row],[c0270]]="","KO","OK")),"OK") -> OK | DB10: =IF(OR(B02.00[[#This Row],[c0280]]="TRUE",B02.00[[#This Row],[c0290]]="TRUE"),(IF(B02.00[[#This Row],[c0300]]="","KO","OK")),"OK") -> OK | DC10: =IF(B02.00[[#This Row],[c0310]]="","KO","OK") -> OK | DD10: =IF(B02.00[[#This Row],[c0310]]="Secured",(IF(B02.00[[#This Row],[c0320]]="","KO","OK")),"OK") -> OK | DE10: =IF(B02.00[[#This Row],[c0310]]="Secured",(IF(B02.00[[#This Row],[c0330]]="","KO","OK")),"OK") -> OK | DF10: =IF(B02.00[[#This Row],[c0310]]="Secured",(IF(B02.00[[#This Row],[c0350]]="","KO","OK")),"OK") -> OK | DG10: =IF(B02.00[[#This Row],[c0350]]="Other",(IF(B02.00[[#This Row],[c0351]]="","KO","OK")),"OK") -> OK | DH10: =IF(AND(B02.00[[#This Row],[c0040]]="ISIN",B02.00[[#This Row],[c0360]]="Nominal "),(IF(B02.00[[#This Row],[c0370]]="","KO","OK")),"OK") -> OK | DI10: =IF(AND(B02.00[[#This Row],[c0040]]="ISIN",B02.00[[#This Row],[c0360]]="Unit "),(IF(B02.00[[#This Row],[c0370]]="","KO","OK")),"OK") -> OK | DJ10: =IF(B02.00[[#This Row],[c0040]]="ISIN",(IF(B02.00[[#This Row],[c0390]]="","KO","OK")),"OK") -> OK | DK10: =IF(B02.00[[#This Row],[c0040]]="ISIN",(IF(B02.00[[#This Row],[c0391]]="","KO","OK")),"OK") -> OK | DL10: =IF(AND(B02.00[[#This Row],[c0040]]="ISIN",OR(B02.00[[#This Row],[c0250]]= "Non-Structured/Vanilla",B02.00[[#This Row],[c0250]]="Other non-standard terms"),B02.00[[#This Row],[c0240]]<>"ZCB issued at discount"),(IF(B02.00[[#This Row],[c0400]]="","KO","OK")),"OK") -> OK | DM10: =IF(AND(B02.00[[#This Row],[c0040]]="ISIN",AND(B02.00[[#This Row],[c0250]]<>"Structured",B02.00[[#This Row],[c0250]]<>"Only structured coupon")),(IF(B02.00[[#This Row],[c0400]]="","KO","OK")),"OK") -> OK | DN10: =IF(B02.00[[#This Row],[c0610]]="","KO","OK") -> OK | DO10: =IF('B9900'!$H$4="Non-Resolution Entity",(IF(B02.00[[#This Row],[c5000]]="","KO","OK")),"OK") -> OK | DP10: =IF('B9900'!$H$4="Non-Resolution Entity",(IF(B02.00[[#This Row],[c5010]]="","KO","OK")),"OK") -> OK | DQ10: =IF(B02.00[[#This Row],[c0040]]="ISIN",(IF(AND(LEN(B02.00[[#This Row],[c0030]]=12),NOT(ISNUMBER(LEFT(B02.00[[#This Row],[c0030]],2)))),"OK","KO")),"OK") -> OK | DR10: =IF(AND(B02.00[[#This Row],[c0020]]<>"NCNP",B02.00[[#This Row],[c0020]]<>"NCBP"),(IF(AND(LEN(B02.00[[#This Row],[c0070]])=3,NOT(ISERROR(MATCH(UPPER(B02.00[[#This Row],[c0070]]),Tabelle1[Alphabetic Code],0)))),"OK","KO")),"OK") -> OK | DS10: =IF(B02.00[[#This Row],[c0080]]>0,"OK","KO") -> OK | DT10: =IF(B02.00[[#This Row],[c0040]]="ISIN",(IF(B02.00[[#This Row],[c0090]]>=0,"OK","KO")),"OK") -> OK | DU10: =IF(B02.00[[#This Row],[c0100]]>=0,"OK","KO") -> OK | DV10: =IF(B02.00[[#This Row],[c0110]]>=0,"OK","KO") -> OK | DW10: =IF(B02.00[[#This Row],[c0120]]>=0,"OK","KO") -> OK | DX10: =IF(B02.00[[#This Row],[c0120]]=(H10+J10+K10),"OK","KO") -> OK | DY10: =IF(OR(B02.00[[#This Row],[c0250]]="Non-structured /Vanilla",B02.00[[#This Row],[c0250]]="Other non-standard terms"),(IF(B02.00[[#This Row],[c0130]]=MAX(0,B02.00[[#This Row],[c0120]],B02.00[[#This Row],[c0300]],B02.00[[#This Row],[c0320]]),"OK","KO")),"OK") -> OK | DZ10: =IF(OR(B02.00[[#This Row],[c0250]]="Structured",B02.00[[#This Row],[c0250]]="Only structured coupon"),(IF(OR(B02.00[[#This Row],[c0130]]=MAX(0,B02.00[[#This Row],[c0270]],B02.00[[#This Row],[c0300]],B02.00[[#This Row],[c0320]]),B02.00[[#This Row],[c0130]]=MAX(0,B02.00[[#This Row],[c0120]],B02.00[[#This Row],[c0300]],B02.00[[#This Row],[c0320]])),"OK","KO")),"OK") -> OK | EA10: =IF(OR(B02.00[[#This Row],[c0140]]="Registered Bond",B02.00[[#This Row],[c0140]]="Bearrer Bond",B02.00[[#This Row],[c0140]]="Borrower Note Loan",B02.00[[#This Row],[c0140]]="Certificate of Deposit / Commercial Paper",B02.00[[#This Row],[c0140]]="Title of ownership",B02.00[[#This Row],[c0140]]="Cash account/saving account",B02.00[[#This Row],[c0140]]="Term deposit",B02.00[[#This Row],[c0140]]="Loan",B02.00[[#This Row],[c0140]]="Bill of exchange",B02.00[[#This Row],[c0140]]="Other"),"OK","KO") -> OK | EB10: =IF(B02.00[[#This Row],[c0160]]>=1,"OK","KO") -> OK | EC10: =IF(AND(B02.00[[#This Row],[c0020]]<>"NCNP",B02.00[[#This Row],[c0020]]<>"NCBP"),(IF(B02.00[[#This Row],[c0170]]>DATE(1900,1,1),"OK","KO")),"OK") -> OK | ED10: =IF(AND(OR(B02.00[[#This Row],[c0190]]<>"",B02.00[[#This Row],[c0200]]<>""),AND(B02.00[[#This Row],[c0020]]<>"NCNP",B02.00[[#This Row],[c0020]]<>"NCBP")),(IF(AND(B02.00[[#This Row],[c0170]]<B02.00[[#This Row],[c0190]],B02.00[[#This Row],[c0170]]<B02.00[[#This Row],[c0200]]),"OK","KO")),"OK") -> OK | EE10: =IF(AND(B02.00[[#This Row],[c0020]]<>"NCNP",B02.00[[#This Row],[c0020]]<>"NCBP"),IF(B02.00[[#This Row],[c0180]]="","KO",IF(B02.00[[#This Row],[c0180]]>DATE(1900,1,1),"OK","KO")),"OK") -> OK | EF10: =IF(AND('B9900'!$I$4<>"",B02.00[[#This Row],[c0020]]<>"NCNP",B02.00[[#This Row],[c0020]]<>"NCBP"),IF(B02.00[[#This Row],[c0180]]="","KO",IF(B02.00[[#This Row],[c0180]]>'B9900'!$I$4,"OK","KO")),"OK") -> OK | EG10: =IF(AND(B02.00[[#This Row],[c0020]]<>"NCNP",B02.00[[#This Row],[c0020]]<>"NCBP"),(IF(B02.00[[#This Row],[c0200]]>DATE(1900,1,1),"OK","KO")),"OK") -> OK | EH10: =IF(AND('B9900'!$I$4<>"",AND(B02.00[[#This Row],[c0020]]<>"NCNP",B02.00[[#This Row],[c0020]]<>"NCBP")),(IF(B02.00[[#This Row],[c0200]]>'B9900'!$I$4,"OK","KO")),"OK") -> OK | EI10: =IF(AND(B02.00[[#This Row],[c0020]]<>"NCNP",B02.00[[#This Row],[c0020]]<>"NCBP"),(IF(B02.00[[#This Row],[c0210]]>DATE(1900,1,1),"OK","KO")),"OK") -> OK | EJ10: =IF(AND('B9900'!$I$4<>"",AND(B02.00[[#This Row],[c0020]]<>"NCNP",B02.00[[#This Row],[c0020]]<>"NCBP")),(IF(B02.00[[#This Row],[c0210]]>'B9900'!$I$4,"OK","KO")),"OK") -> OK | EK10: =IF(AND(B02.00[[#This Row],[c0020]]<>"NCNP",B02.00[[#This Row],[c0020]]<>"NCBP"),(IF(OR(NOT(ISERROR(MATCH(B02.00[[#This Row],[c0220]],'ISO 3166'!B:B,0))),NOT(ISERROR(MATCH(B02.00[[#This Row],[c0220]],'ISO 3166'!E:E,0)))),"OK","KO")),"OK") -> OK | EL10: =IF(AND(B02.00[[#This Row],[c0020]]<>"NCNP",B02.00[[#This Row],[c0020]]<>"NCBP"),(IF(OR(B02.00[[#This Row],[c0230]]="Yes, supported by Legal Opinion",B02.00[[#This Row],[c0230]]="Yes, not supported by Legal Opinion",B02.00[[#This Row],[c0230]]="No",B02.00[[#This Row],[c0230]]="Not applicable",B02.00[[#This Row],[c0230]]="Aggregated"),"OK","KO")),"OK") -> OK | EM10: =IF(OR(B02.00[[#This Row],[c0250]]="Non-structured/Vanilla",B02.00[[#This Row],[c0250]]="Structured",B02.00[[#This Row],[c0250]]="Other non-standard terms",B02.00[[#This Row],[c0250]]="Only structured coupon",B02.00[[#This Row],[c0250]]="Aggregated"),"OK","KO") -> OK | EN10: =IF(OR(B02.00[[#This Row],[c0310]]="Secured",B02.00[[#This Row],[c0310]]="Unsecured"),"OK","KO") -> OK | EO10: =IF(AND(B02.00[[#This Row],[c0310]]="Secured",OR(B02.00[[#This Row],[c0250]]="Non-structured/Vanilla",B02.00[[#This Row],[c0250]]="Other non-standard terms"),B02.00[[#This Row],[c0240]]<>"ZCB issued at discount"),(IF(B02.00[[#This Row],[c0330]]=MAX(0,B02.00[[#This Row],[c0120]],B02.00[[#This Row],[c0320]]),"OK","KO")),"OK") -> OK | EP10: =IF(AND(B02.00[[#This Row],[c0310]]="Secured",OR(B02.00[[#This Row],[c0250]]="Structured",B02.00[[#This Row],[c0250]]="Only structured coupon")),(IF(OR(B02.00[[#This Row],[c0330]]=MAX(0,B02.00[[#This Row],[c0270]],B02.00[[#This Row],[c0320]]),B02.00[[#This Row],[c0330]]=MAX(0,B02.00[[#This Row],[c0120]],B02.00[[#This Row],[c0320]])),"OK","KO")),"OK") -> OK | EQ10: =IF(OR(B02.00[[#This Row],[c0350]]="Real estate",B02.00[[#This Row],[c0350]]="Ships",B02.00[[#This Row],[c0350]]="Aircraft",B02.00[[#This Row],[c0350]]="Financial",B02.00[[#This Row],[c0350]]="Other",B02.00[[#This Row],[c0350]]="Not applicable"),"OK","KO") -> OK | ER10: =IF(B02.00[[#This Row],[c0310]]="Unsecured",(IF(B02.00[[#This Row],[c0350]]="Not applicable","OK","KO")),"OK") -> OK | ES10: =IF(OR(B02.00[[#This Row],[c0440]]="NGN",B02.00[[#This Row],[c0440]]="CGN",B02.00[[#This Row],[c0440]]="Not applicable"),"OK","KO") -> OK | ET10: =IF(OR(B02.00[[#This Row],[c0530]]="T2 in phase-out",B02.00[[#This Row],[c0530]]="Grandfathered T2",B02.00[[#This Row],[c0530]]="Fully Compliant T2",B02.00[[#This Row],[c0530]]="Partially (A)T1 and T2",B02.00[[#This Row],[c0530]]="Grandfathered AT1",B02.00[[#This Row],[c0530]]="Fully Compliant AT1",B02.00[[#This Row],[c0530]]="CET1",B02.00[[#This Row],[c0530]]="No"),"OK","KO") -> OK | EU10: =IF(B02.00[[#This Row],[c0540]] ="","KO",IF(B02.00[[#This Row],[c0540]]>=0,"OK","KO")) -> OK | EV10: =IF(OR(B02.00[[#This Row],[c0550]]="T2 in phase-out",B02.00[[#This Row],[c0550]]="Grandfathered T2",B02.00[[#This Row],[c0550]]="Fully Compliant T2",B02.00[[#This Row],[c0550]]="Partially (A)T1 and T2",B02.00[[#This Row],[c0550]]="Grandfathered AT1",B02.00[[#This Row],[c0550]]="Fully Compliant AT1",B02.00[[#This Row],[c0550]]="CET1",B02.00[[#This Row],[c0550]]="No"),"OK","KO") -> OK | EW10: =IF(B02.00[[#This Row],[c0560]]="","KO",IF(B02.00[[#This Row],[c0560]]>=0,"OK","KO")) -> OK | EX10: =IF(OR(B02.00[[#This Row],[c0590]]="Lien",B02.00[[#This Row],[c0590]]="Guarantee",B02.00[[#This Row],[c0590]]="Surety",B02.00[[#This Row],[c0590]]="Guarantee obligation",B02.00[[#This Row],[c0590]]="Other",B02.00[[#This Row],[c0590]]="Not applicable",B02.00[[#This Row],[c0590]]="Aggregated"),"OK","KO") -> OK | EY10: =IF(B02.00[[#This Row],[c0610]]="","KO",IF(B02.00[[#This Row],[c0610]]>=0,"OK","KO")) -> OK | EZ10: =IF(OR(B02.00[[#This Row],[c0620]]="010 Financial liabilities held for trading",B02.00[[#This Row],[c0620]]="070 Financial liabilities at fair value through profit or loss",B02.00[[#This Row],[c0620]]="110 Financial liabilities at amortized cost",B02.00[[#This Row],[c0620]]="280 Other liabilities",B02.00[[#This Row],[c0620]]="300 Total equity",),"OK","KO") -> OK
A11: 7 | B11: 31641600005800007PTCPP0AM0007000 | C11: PTCPP0AM0007 | D11: ISIN | E11: 1391779674 | F11: 999999999999999 | G11: EUR | H11: 1566022662 | I11: 6326736 | J11: 0 | K11: 0 | L11: 1566022662 | M11: 1566022662 | N11: Title of ownership | O11: Not applicable | P11: Not applicable | Q11: 1 | R11: 999999999999999 | S11: 1 | T11: 1992-01-05 | U11: 0001-01-01 | V11: 2099-01-31 | W11: 2099-01-31 | X11: 2099-01-31 | Y11: PT | Z11: Yes, supported by Legal Opinion | AA11: No ZCB | AB11: Non-structured/Vanilla | AC11: 999999999999999 | AD11: 999999999999999 | AE11: FALSE | AF11: FALSE | AG11: 999999999999999 | AH11: Unsecured | AI11: 999999999999999 | AJ11: 999999999999999 | AK11: Not applicable | AL11: Not applicable | AM11: Not applicable | AN11: Unit | AO11: 1 | AP11: 1 | AQ11: =+B02.00[[#This Row],[c0050]] -> 1391779674 | AR11: 6326736 | AS11: 0 | AT11: 0 | AU11: 999999999999999 | AV11: 999999999999999 | AW11: 999999999999999 | AX11: Not applicable | AY11: -10000 | AZ11: INTERBOLSA_PT | BA11: 529900LG70TCAGWCXT47 | BB11: Not applicable | BC11: BANCO SANTANDER TOTTA S,A, | BD11: 549300URJH9VSI58CS32 | BE11: Not applicable | BF11: Not applicable | BG11: INTERBOLSA_PT | BH11: 529900LG70TCAGWCXT47 | BI11: INTERBOLSA_PT | BJ11: 529900LG70TCAGWCXT47 | BK11: Not applicable | BL11: Not applicable | BM11: Not applicable | BN11: Not applicable | BO11: CET1 | BP11: 1566022662 | BQ11: CET1 | BR11: 1566022662 | BS11: 0 | BT11: Not applicable | BU11: Not applicable | BV11: Not applicable | BW11: FALSE | BX11: 1566022662 | BY11: 300 Total equity | BZ11: 999999999999999 | CA11: Not applicable | CB11: FALSE | CC11: TRUE | CD11: =IF(B02.00[[#This Row],[c0010]]="","KO","OK") -> OK | CE11: =IF(B02.00[[#This Row],[c0030]]="","KO","OK") -> OK | CF11: =IF(B02.00[[#This Row],[c0040]]="","KO","OK") -> OK | CG11: =IF(B02.00[[#This Row],[c0070]]="","KO","OK") -> OK | CH11: =IF(OR(B02.00[[#This Row],[c0250]]= "Non-Structured/Vanilla",B02.00[[#This Row],[c0250]]="Other non-standard terms"),(IF(B02.00[[#This Row],[c0080]]="","KO","OK")),"OK") -> OK | CI11: =IF(OR(B02.00[[#This Row],[c0250]]= "Structured",B02.00[[#This Row],[c0250]]="Only structured coupon"),(IF(B02.00[[#This Row],[c0080]]="","KO","OK")),"OK") -> OK | CJ11: =IF(B02.00[[#This Row],[c0040]]="ISIN",(IF(B02.00[[#This Row],[c0090]]="","KO","OK")),"OK") -> OK | CK11: =IF(AND(OR(B02.00[[#This Row],[c0250]]="Non-Structured/Vanilla",B02.00[[#This Row],[c0250]]="Other non-standard terms"),B02.00[[#This Row],[c0240]]<>"ZCB issued at discount"),(IF(B02.00[[#This Row],[c0100]]="","KO","OK")),"OK") -> OK | CL11: =IF(OR(B02.00[[#This Row],[c0250]]<> "Non-Structured/Vanilla",B02.00[[#This Row],[c0460]]<>"Other non-standard terms"),IF(B02.00[[#This Row],[c0100]]="","KO","OK")) -> OK | CM11: =IF(OR(B02.00[[#This Row],[c0250]]= "Non-Structured/Vanilla",B02.00[[#This Row],[c0460]]="Other non-standard terms"),(IF(B02.00[[#This Row],[c0120]]="","KO","OK")),"OK") -> OK | CN11: =IF(OR(B02.00[[#This Row],[c0250]]<> "Structured",B02.00[[#This Row],[c0250]]<>"Only structured coupon"),(IF(B02.00[[#This Row],[c0120]]="","KO","OK")),"OK") -> OK | CO11: =IF(B02.00[[#This Row],[c0130]]="","KO","OK") -> OK | CP11: =IF(B02.00[[#This Row],[c0140]]="","KO","OK") -> OK | CQ11: =IF(B02.00[[#This Row],[c0140]]="Other",(IF(B02.00[[#This Row],[c0141]]="","KO","OK")),"OK") -> OK | CR11: =IF(B02.00[[#This Row],[c0160]]="","KO","OK") -> OK | CS11: =IF(B02.00[[#This Row],[c0162]]="","KO","OK") -> OK | CT11: =IF(AND(OR(B02.00[[#This Row],[c0250]]= "Non-Structured/Vanilla",B02.00[[#This Row],[c0250]]="Other non-standard terms"),B02.00[[#This Row],[c0240]]<>"ZCB issued at discount"),(IF(B02.00[[#This Row],[c0180]]="","KO","OK")),"OK") -> OK | CU11: =IF(AND(B02.00[[#This Row],[c0250]]<> "Structured",B02.00[[#This Row],[c0250]]<>"Only structured coupon"),(IF(B02.00[[#This Row],[c0180]]="","KO","OK")),"OK") -> OK | CV11: =IF(B02.00[[#This Row],[c0200]]="","KO","OK") -> OK | CW11: =IF(B02.00[[#This Row],[c0140]]<>"Cash account/saving account",(IF(B02.00[[#This Row],[c0210]]="","KO","OK")),"OK") -> OK | CX11: =IF(B02.00[[#This Row],[c0220]]="","KO","OK") -> OK | CY11: =IF(B02.00[[#This Row],[c0250]]="","KO","OK") -> OK | CZ11: =IF(OR(B02.00[[#This Row],[c0250]]="Structured",B02.00[[#This Row],[c0250]]="Only structured coupon"),(IF(B02.00[[#This Row],[c0260]]="","KO","OK")),"OK") -> OK | DA11: =IF(OR(B02.00[[#This Row],[c0250]]="Structured",B02.00[[#This Row],[c0250]]="Only structured coupon"),(IF(B02.00[[#This Row],[c0270]]="","KO","OK")),"OK") -> OK | DB11: =IF(OR(B02.00[[#This Row],[c0280]]="TRUE",B02.00[[#This Row],[c0290]]="TRUE"),(IF(B02.00[[#This Row],[c0300]]="","KO","OK")),"OK") -> OK | DC11: =IF(B02.00[[#This Row],[c0310]]="","KO","OK") -> OK | DD11: =IF(B02.00[[#This Row],[c0310]]="Secured",(IF(B02.00[[#This Row],[c0320]]="","KO","OK")),"OK") -> OK | DE11: =IF(B02.00[[#This Row],[c0310]]="Secured",(IF(B02.00[[#This Row],[c0330]]="","KO","OK")),"OK") -> OK | DF11: =IF(B02.00[[#This Row],[c0310]]="Secured",(IF(B02.00[[#This Row],[c0350]]="","KO","OK")),"OK") -> OK | DG11: =IF(B02.00[[#This Row],[c0350]]="Other",(IF(B02.00[[#This Row],[c0351]]="","KO","OK")),"OK") -> OK | DH11: =IF(AND(B02.00[[#This Row],[c0040]]="ISIN",B02.00[[#This Row],[c0360]]="Nominal "),(IF(B02.00[[#This Row],[c0370]]="","KO","OK")),"OK") -> OK | DI11: =IF(AND(B02.00[[#This Row],[c0040]]="ISIN",B02.00[[#This Row],[c0360]]="Unit "),(IF(B02.00[[#This Row],[c0370]]="","KO","OK")),"OK") -> OK | DJ11: =IF(B02.00[[#This Row],[c0040]]="ISIN",(IF(B02.00[[#This Row],[c0390]]="","KO","OK")),"OK") -> OK | DK11: =IF(B02.00[[#This Row],[c0040]]="ISIN",(IF(B02.00[[#This Row],[c0391]]="","KO","OK")),"OK") -> OK | DL11: =IF(AND(B02.00[[#This Row],[c0040]]="ISIN",OR(B02.00[[#This Row],[c0250]]= "Non-Structured/Vanilla",B02.00[[#This Row],[c0250]]="Other non-standard terms"),B02.00[[#This Row],[c0240]]<>"ZCB issued at discount"),(IF(B02.00[[#This Row],[c0400]]="","KO","OK")),"OK") -> OK | DM11: =IF(AND(B02.00[[#This Row],[c0040]]="ISIN",AND(B02.00[[#This Row],[c0250]]<>"Structured",B02.00[[#This Row],[c0250]]<>"Only structured coupon")),(IF(B02.00[[#This Row],[c0400]]="","KO","OK")),"OK") -> OK | DN11: =IF(B02.00[[#This Row],[c0610]]="","KO","OK") -> OK | DO11: =IF('B9900'!$H$4="Non-Resolution Entity",(IF(B02.00[[#This Row],[c5000]]="","KO","OK")),"OK") -> OK | DP11: =IF('B9900'!$H$4="Non-Resolution Entity",(IF(B02.00[[#This Row],[c5010]]="","KO","OK")),"OK") -> OK | DQ11: =IF(B02.00[[#This Row],[c0040]]="ISIN",(IF(AND(LEN(B02.00[[#This Row],[c0030]]=12),NOT(ISNUMBER(LEFT(B02.00[[#This Row],[c0030]],2)))),"OK","KO")),"OK") -> OK | DR11: =IF(AND(B02.00[[#This Row],[c0020]]<>"NCNP",B02.00[[#This Row],[c0020]]<>"NCBP"),(IF(AND(LEN(B02.00[[#This Row],[c0070]])=3,NOT(ISERROR(MATCH(UPPER(B02.00[[#This Row],[c0070]]),Tabelle1[Alphabetic Code],0)))),"OK","KO")),"OK") -> OK | DS11: =IF(B02.00[[#This Row],[c0080]]>0,"OK","KO") -> OK | DT11: =IF(B02.00[[#This Row],[c0040]]="ISIN",(IF(B02.00[[#This Row],[c0090]]>=0,"OK","KO")),"OK") -> OK | DU11: =IF(B02.00[[#This Row],[c0100]]>=0,"OK","KO") -> OK | DV11: =IF(B02.00[[#This Row],[c0110]]>=0,"OK","KO") -> OK | DW11: =IF(B02.00[[#This Row],[c0120]]>=0,"OK","KO") -> OK | DX11: =IF(B02.00[[#This Row],[c0120]]=(H11+J11+K11),"OK","KO") -> OK | DY11: =IF(OR(B02.00[[#This Row],[c0250]]="Non-structured /Vanilla",B02.00[[#This Row],[c0250]]="Other non-standard terms"),(IF(B02.00[[#This Row],[c0130]]=MAX(0,B02.00[[#This Row],[c0120]],B02.00[[#This Row],[c0300]],B02.00[[#This Row],[c0320]]),"OK","KO")),"OK") -> OK | DZ11: =IF(OR(B02.00[[#This Row],[c0250]]="Structured",B02.00[[#This Row],[c0250]]="Only structured coupon"),(IF(OR(B02.00[[#This Row],[c0130]]=MAX(0,B02.00[[#This Row],[c0270]],B02.00[[#This Row],[c0300]],B02.00[[#This Row],[c0320]]),B02.00[[#This Row],[c0130]]=MAX(0,B02.00[[#This Row],[c0120]],B02.00[[#This Row],[c0300]],B02.00[[#This Row],[c0320]])),"OK","KO")),"OK") -> OK | EA11: =IF(OR(B02.00[[#This Row],[c0140]]="Registered Bond",B02.00[[#This Row],[c0140]]="Bearrer Bond",B02.00[[#This Row],[c0140]]="Borrower Note Loan",B02.00[[#This Row],[c0140]]="Certificate of Deposit / Commercial Paper",B02.00[[#This Row],[c0140]]="Title of ownership",B02.00[[#This Row],[c0140]]="Cash account/saving account",B02.00[[#This Row],[c0140]]="Term deposit",B02.00[[#This Row],[c0140]]="Loan",B02.00[[#This Row],[c0140]]="Bill of exchange",B02.00[[#This Row],[c0140]]="Other"),"OK","KO") -> OK | EB11: =IF(B02.00[[#This Row],[c0160]]>=1,"OK","KO") -> OK | EC11: =IF(AND(B02.00[[#This Row],[c0020]]<>"NCNP",B02.00[[#This Row],[c0020]]<>"NCBP"),(IF(B02.00[[#This Row],[c0170]]>DATE(1900,1,1),"OK","KO")),"OK") -> OK | ED11: =IF(AND(OR(B02.00[[#This Row],[c0190]]<>"",B02.00[[#This Row],[c0200]]<>""),AND(B02.00[[#This Row],[c0020]]<>"NCNP",B02.00[[#This Row],[c0020]]<>"NCBP")),(IF(AND(B02.00[[#This Row],[c0170]]<B02.00[[#This Row],[c0190]],B02.00[[#This Row],[c0170]]<B02.00[[#This Row],[c0200]]),"OK","KO")),"OK") -> OK | EE11: =IF(AND(B02.00[[#This Row],[c0020]]<>"NCNP",B02.00[[#This Row],[c0020]]<>"NCBP"),IF(B02.00[[#This Row],[c0180]]="","KO",IF(B02.00[[#This Row],[c0180]]>DATE(1900,1,1),"OK","KO")),"OK") -> OK | EF11: =IF(AND('B9900'!$I$4<>"",B02.00[[#This Row],[c0020]]<>"NCNP",B02.00[[#This Row],[c0020]]<>"NCBP"),IF(B02.00[[#This Row],[c0180]]="","KO",IF(B02.00[[#This Row],[c0180]]>'B9900'!$I$4,"OK","KO")),"OK") -> OK | EG11: =IF(AND(B02.00[[#This Row],[c0020]]<>"NCNP",B02.00[[#This Row],[c0020]]<>"NCBP"),(IF(B02.00[[#This Row],[c0200]]>DATE(1900,1,1),"OK","KO")),"OK") -> OK | EH11: =IF(AND('B9900'!$I$4<>"",AND(B02.00[[#This Row],[c0020]]<>"NCNP",B02.00[[#This Row],[c0020]]<>"NCBP")),(IF(B02.00[[#This Row],[c0200]]>'B9900'!$I$4,"OK","KO")),"OK") -> OK | EI11: =IF(AND(B02.00[[#This Row],[c0020]]<>"NCNP",B02.00[[#This Row],[c0020]]<>"NCBP"),(IF(B02.00[[#This Row],[c0210]]>DATE(1900,1,1),"OK","KO")),"OK") -> OK | EJ11: =IF(AND('B9900'!$I$4<>"",AND(B02.00[[#This Row],[c0020]]<>"NCNP",B02.00[[#This Row],[c0020]]<>"NCBP")),(IF(B02.00[[#This Row],[c0210]]>'B9900'!$I$4,"OK","KO")),"OK") -> OK | EK11: =IF(AND(B02.00[[#This Row],[c0020]]<>"NCNP",B02.00[[#This Row],[c0020]]<>"NCBP"),(IF(OR(NOT(ISERROR(MATCH(B02.00[[#This Row],[c0220]],'ISO 3166'!B:B,0))),NOT(ISERROR(MATCH(B02.00[[#This Row],[c0220]],'ISO 3166'!E:E,0)))),"OK","KO")),"OK") -> OK | EL11: =IF(AND(B02.00[[#This Row],[c0020]]<>"NCNP",B02.00[[#This Row],[c0020]]<>"NCBP"),(IF(OR(B02.00[[#This Row],[c0230]]="Yes, supported by Legal Opinion",B02.00[[#This Row],[c0230]]="Yes, not supported by Legal Opinion",B02.00[[#This Row],[c0230]]="No",B02.00[[#This Row],[c0230]]="Not applicable",B02.00[[#This Row],[c0230]]="Aggregated"),"OK","KO")),"OK") -> OK | EM11: =IF(OR(B02.00[[#This Row],[c0250]]="Non-structured/Vanilla",B02.00[[#This Row],[c0250]]="Structured",B02.00[[#This Row],[c0250]]="Other non-standard terms",B02.00[[#This Row],[c0250]]="Only structured coupon",B02.00[[#This Row],[c0250]]="Aggregated"),"OK","KO") -> OK | EN11: =IF(OR(B02.00[[#This Row],[c0310]]="Secured",B02.00[[#This Row],[c0310]]="Unsecured"),"OK","KO") -> OK | EO11: =IF(AND(B02.00[[#This Row],[c0310]]="Secured",OR(B02.00[[#This Row],[c0250]]="Non-structured/Vanilla",B02.00[[#This Row],[c0250]]="Other non-standard terms"),B02.00[[#This Row],[c0240]]<>"ZCB issued at discount"),(IF(B02.00[[#This Row],[c0330]]=MAX(0,B02.00[[#This Row],[c0120]],B02.00[[#This Row],[c0320]]),"OK","KO")),"OK") -> OK | EP11: =IF(AND(B02.00[[#This Row],[c0310]]="Secured",OR(B02.00[[#This Row],[c0250]]="Structured",B02.00[[#This Row],[c0250]]="Only structured coupon")),(IF(OR(B02.00[[#This Row],[c0330]]=MAX(0,B02.00[[#This Row],[c0270]],B02.00[[#This Row],[c0320]]),B02.00[[#This Row],[c0330]]=MAX(0,B02.00[[#This Row],[c0120]],B02.00[[#This Row],[c0320]])),"OK","KO")),"OK") -> OK | EQ11: =IF(OR(B02.00[[#This Row],[c0350]]="Real estate",B02.00[[#This Row],[c0350]]="Ships",B02.00[[#This Row],[c0350]]="Aircraft",B02.00[[#This Row],[c0350]]="Financial",B02.00[[#This Row],[c0350]]="Other",B02.00[[#This Row],[c0350]]="Not applicable"),"OK","KO") -> OK | ER11: =IF(B02.00[[#This Row],[c0310]]="Unsecured",(IF(B02.00[[#This Row],[c0350]]="Not applicable","OK","KO")),"OK") -> OK | ES11: =IF(OR(B02.00[[#This Row],[c0440]]="NGN",B02.00[[#This Row],[c0440]]="CGN",B02.00[[#This Row],[c0440]]="Not applicable"),"OK","KO") -> OK | ET11: =IF(OR(B02.00[[#This Row],[c0530]]="T2 in phase-out",B02.00[[#This Row],[c0530]]="Grandfathered T2",B02.00[[#This Row],[c0530]]="Fully Compliant T2",B02.00[[#This Row],[c0530]]="Partially (A)T1 and T2",B02.00[[#This Row],[c0530]]="Grandfathered AT1",B02.00[[#This Row],[c0530]]="Fully Compliant AT1",B02.00[[#This Row],[c0530]]="CET1",B02.00[[#This Row],[c0530]]="No"),"OK","KO") -> OK | EU11: =IF(B02.00[[#This Row],[c0540]] ="","KO",IF(B02.00[[#This Row],[c0540]]>=0,"OK","KO")) -> OK | EV11: =IF(OR(B02.00[[#This Row],[c0550]]="T2 in phase-out",B02.00[[#This Row],[c0550]]="Grandfathered T2",B02.00[[#This Row],[c0550]]="Fully Compliant T2",B02.00[[#This Row],[c0550]]="Partially (A)T1 and T2",B02.00[[#This Row],[c0550]]="Grandfathered AT1",B02.00[[#This Row],[c0550]]="Fully Compliant AT1",B02.00[[#This Row],[c0550]]="CET1",B02.00[[#This Row],[c0550]]="No"),"OK","KO") -> OK | EW11: =IF(B02.00[[#This Row],[c0560]]="","KO",IF(B02.00[[#This Row],[c0560]]>=0,"OK","KO")) -> OK | EX11: =IF(OR(B02.00[[#This Row],[c0590]]="Lien",B02.00[[#This Row],[c0590]]="Guarantee",B02.00[[#This Row],[c0590]]="Surety",B02.00[[#This Row],[c0590]]="Guarantee obligation",B02.00[[#This Row],[c0590]]="Other",B02.00[[#This Row],[c0590]]="Not applicable",B02.00[[#This Row],[c0590]]="Aggregated"),"OK","KO") -> OK | EY11: =IF(B02.00[[#This Row],[c0610]]="","KO",IF(B02.00[[#This Row],[c0610]]>=0,"OK","KO")) -> OK | EZ11: =IF(OR(B02.00[[#This Row],[c0620]]="010 Financial liabilities held for trading",B02.00[[#This Row],[c0620]]="070 Financial liabilities at fair value through profit or loss",B02.00[[#This Row],[c0620]]="110 Financial liabilities at amortized cost",B02.00[[#This Row],[c0620]]="280 Other liabilities",B02.00[[#This Row],[c0620]]="300 Total equity",),"OK","KO") -> OK
A12: 8 | B12: 31641600005800007PTSTOCOM0007000 | C12: PTSTOCOM0007 | D12: ISIN | E12: 400000000 | F12: 999999999999999 | G12: EUR | H12: 400000000 | I12: 0 | J12: 0 | K12: 0 | L12: 400000000 | M12: 400000000 | N12: Title of ownership | O12: Not applicable | P12: Not applicable | Q12: 2 | R12: 999999999999999 | S12: 2 | T12: 2021-01-14 | U12: 0001-01-01 | V12: 2099-01-31 | W12: 2099-01-31 | X12: 2099-01-31 | Y12: PT | Z12: Yes, supported by Legal Opinion | AA12: No ZCB | AB12: Non-structured/Vanilla | AC12: 999999999999999 | AD12: 999999999999999 | AE12: FALSE | AF12: FALSE | AG12: 999999999999999 | AH12: Unsecured | AI12: 999999999999999 | AJ12: 999999999999999 | AK12: Not applicable | AL12: Not applicable | AM12: Not applicable | AN12: Nominal | AO12: 100000 | AP12: 100000 | AQ12: 4000 | AR12: 0 | AS12: 0 | AT12: 0 | AU12: 999999999999999 | AV12: 999999999999999 | AW12: 999999999999999 | AX12: Not applicable | AY12: -10000 | AZ12: INTERBOLSA_PT | BA12: 529900LG70TCAGWCXT47 | BB12: Not applicable | BC12: BANCO SANTANDER TOTTA S,A, | BD12: 549300URJH9VSI58CS32 | BE12: Not applicable | BF12: Not applicable | BG12: INTERBOLSA_PT | BH12: 529900LG70TCAGWCXT47 | BI12: INTERBOLSA_PT | BJ12: 529900LG70TCAGWCXT47 | BK12: Not applicable | BL12: Not applicable | BM12: Not applicable | BN12: Not applicable | BO12: Fully Compliant AT1 | BP12: 400000000 | BQ12: Fully Compliant AT1 | BR12: 400000000 | BS12: 0 | BT12: Not applicable | BU12: Not applicable | BV12: Not applicable | BW12: FALSE | BX12: 400000000 | BY12: 300 Total equity | BZ12: 999999999999999 | CA12: Not applicable | CB12: FALSE | CC12: TRUE | CD12: =IF(B02.00[[#This Row],[c0010]]="","KO","OK") -> OK | CE12: =IF(B02.00[[#This Row],[c0030]]="","KO","OK") -> OK | CF12: =IF(B02.00[[#This Row],[c0040]]="","KO","OK") -> OK | CG12: =IF(B02.00[[#This Row],[c0070]]="","KO","OK") -> OK | CH12: =IF(OR(B02.00[[#This Row],[c0250]]= "Non-Structured/Vanilla",B02.00[[#This Row],[c0250]]="Other non-standard terms"),(IF(B02.00[[#This Row],[c0080]]="","KO","OK")),"OK") -> OK | CI12: =IF(OR(B02.00[[#This Row],[c0250]]= "Structured",B02.00[[#This Row],[c0250]]="Only structured coupon"),(IF(B02.00[[#This Row],[c0080]]="","KO","OK")),"OK") -> OK | CJ12: =IF(B02.00[[#This Row],[c0040]]="ISIN",(IF(B02.00[[#This Row],[c0090]]="","KO","OK")),"OK") -> OK | CK12: =IF(AND(OR(B02.00[[#This Row],[c0250]]="Non-Structured/Vanilla",B02.00[[#This Row],[c0250]]="Other non-standard terms"),B02.00[[#This Row],[c0240]]<>"ZCB issued at discount"),(IF(B02.00[[#This Row],[c0100]]="","KO","OK")),"OK") -> OK | CL12: =IF(OR(B02.00[[#This Row],[c0250]]<> "Non-Structured/Vanilla",B02.00[[#This Row],[c0460]]<>"Other non-standard terms"),IF(B02.00[[#This Row],[c0100]]="","KO","OK")) -> OK | CM12: =IF(OR(B02.00[[#This Row],[c0250]]= "Non-Structured/Vanilla",B02.00[[#This Row],[c0460]]="Other non-standard terms"),(IF(B02.00[[#This Row],[c0120]]="","KO","OK")),"OK") -> OK | CN12: =IF(OR(B02.00[[#This Row],[c0250]]<> "Structured",B02.00[[#This Row],[c0250]]<>"Only structured coupon"),(IF(B02.00[[#This Row],[c0120]]="","KO","OK")),"OK") -> OK | CO12: =IF(B02.00[[#This Row],[c0130]]="","KO","OK") -> OK | CP12: =IF(B02.00[[#This Row],[c0140]]="","KO","OK") -> OK | CQ12: =IF(B02.00[[#This Row],[c0140]]="Other",(IF(B02.00[[#This Row],[c0141]]="","KO","OK")),"OK") -> OK | CR12: =IF(B02.00[[#This Row],[c0160]]="","KO","OK") -> OK | CS12: =IF(B02.00[[#This Row],[c0162]]="","KO","OK") -> OK | CT12: =IF(AND(OR(B02.00[[#This Row],[c0250]]= "Non-Structured/Vanilla",B02.00[[#This Row],[c0250]]="Other non-standard terms"),B02.00[[#This Row],[c0240]]<>"ZCB issued at discount"),(IF(B02.00[[#This Row],[c0180]]="","KO","OK")),"OK") -> OK | CU12: =IF(AND(B02.00[[#This Row],[c0250]]<> "Structured",B02.00[[#This Row],[c0250]]<>"Only structured coupon"),(IF(B02.00[[#This Row],[c0180]]="","KO","OK")),"OK") -> OK | CV12: =IF(B02.00[[#This Row],[c0200]]="","KO","OK") -> OK | CW12: =IF(B02.00[[#This Row],[c0140]]<>"Cash account/saving account",(IF(B02.00[[#This Row],[c0210]]="","KO","OK")),"OK") -> OK | CX12: =IF(B02.00[[#This Row],[c0220]]="","KO","OK") -> OK | CY12: =IF(B02.00[[#This Row],[c0250]]="","KO","OK") -> OK | CZ12: =IF(OR(B02.00[[#This Row],[c0250]]="Structured",B02.00[[#This Row],[c0250]]="Only structured coupon"),(IF(B02.00[[#This Row],[c0260]]="","KO","OK")),"OK") -> OK | DA12: =IF(OR(B02.00[[#This Row],[c0250]]="Structured",B02.00[[#This Row],[c0250]]="Only structured coupon"),(IF(B02.00[[#This Row],[c0270]]="","KO","OK")),"OK") -> OK | DB12: =IF(OR(B02.00[[#This Row],[c0280]]="TRUE",B02.00[[#This Row],[c0290]]="TRUE"),(IF(B02.00[[#This Row],[c0300]]="","KO","OK")),"OK") -> OK | DC12: =IF(B02.00[[#This Row],[c0310]]="","KO","OK") -> OK | DD12: =IF(B02.00[[#This Row],[c0310]]="Secured",(IF(B02.00[[#This Row],[c0320]]="","KO","OK")),"OK") -> OK | DE12: =IF(B02.00[[#This Row],[c0310]]="Secured",(IF(B02.00[[#This Row],[c0330]]="","KO","OK")),"OK") -> OK | DF12: =IF(B02.00[[#This Row],[c0310]]="Secured",(IF(B02.00[[#This Row],[c0350]]="","KO","OK")),"OK") -> OK | DG12: =IF(B02.00[[#This Row],[c0350]]="Other",(IF(B02.00[[#This Row],[c0351]]="","KO","OK")),"OK") -> OK | DH12: =IF(AND(B02.00[[#This Row],[c0040]]="ISIN",B02.00[[#This Row],[c0360]]="Nominal "),(IF(B02.00[[#This Row],[c0370]]="","KO","OK")),"OK") -> OK | DI12: =IF(AND(B02.00[[#This Row],[c0040]]="ISIN",B02.00[[#This Row],[c0360]]="Unit "),(IF(B02.00[[#This Row],[c0370]]="","KO","OK")),"OK") -> OK | DJ12: =IF(B02.00[[#This Row],[c0040]]="ISIN",(IF(B02.00[[#This Row],[c0390]]="","KO","OK")),"OK") -> OK | DK12: =IF(B02.00[[#This Row],[c0040]]="ISIN",(IF(B02.00[[#This Row],[c0391]]="","KO","OK")),"OK") -> OK | DL12: =IF(AND(B02.00[[#This Row],[c0040]]="ISIN",OR(B02.00[[#This Row],[c0250]]= "Non-Structured/Vanilla",B02.00[[#This Row],[c0250]]="Other non-standard terms"),B02.00[[#This Row],[c0240]]<>"ZCB issued at discount"),(IF(B02.00[[#This Row],[c0400]]="","KO","OK")),"OK") -> OK | DM12: =IF(AND(B02.00[[#This Row],[c0040]]="ISIN",AND(B02.00[[#This Row],[c0250]]<>"Structured",B02.00[[#This Row],[c0250]]<>"Only structured coupon")),(IF(B02.00[[#This Row],[c0400]]="","KO","OK")),"OK") -> OK | DN12: =IF(B02.00[[#This Row],[c0610]]="","KO","OK") -> OK | DO12: =IF('B9900'!$H$4="Non-Resolution Entity",(IF(B02.00[[#This Row],[c5000]]="","KO","OK")),"OK") -> OK | DP12: =IF('B9900'!$H$4="Non-Resolution Entity",(IF(B02.00[[#This Row],[c5010]]="","KO","OK")),"OK") -> OK | DQ12: =IF(B02.00[[#This Row],[c0040]]="ISIN",(IF(AND(LEN(B02.00[[#This Row],[c0030]]=12),NOT(ISNUMBER(LEFT(B02.00[[#This Row],[c0030]],2)))),"OK","KO")),"OK") -> OK | DR12: =IF(AND(B02.00[[#This Row],[c0020]]<>"NCNP",B02.00[[#This Row],[c0020]]<>"NCBP"),(IF(AND(LEN(B02.00[[#This Row],[c0070]])=3,NOT(ISERROR(MATCH(UPPER(B02.00[[#This Row],[c0070]]),Tabelle1[Alphabetic Code],0)))),"OK","KO")),"OK") -> OK | DS12: =IF(B02.00[[#This Row],[c0080]]>0,"OK","KO") -> OK | DT12: =IF(B02.00[[#This Row],[c0040]]="ISIN",(IF(B02.00[[#This Row],[c0090]]>=0,"OK","KO")),"OK") -> OK | DU12: =IF(B02.00[[#This Row],[c0100]]>=0,"OK","KO") -> OK | DV12: =IF(B02.00[[#This Row],[c0110]]>=0,"OK","KO") -> OK | DW12: =IF(B02.00[[#This Row],[c0120]]>=0,"OK","KO") -> OK | DX12: =IF(B02.00[[#This Row],[c0120]]=(H12+J12+K12),"OK","KO") -> OK | DY12: =IF(OR(B02.00[[#This Row],[c0250]]="Non-structured /Vanilla",B02.00[[#This Row],[c0250]]="Other non-standard terms"),(IF(B02.00[[#This Row],[c0130]]=MAX(0,B02.00[[#This Row],[c0120]],B02.00[[#This Row],[c0300]],B02.00[[#This Row],[c0320]]),"OK","KO")),"OK") -> OK | DZ12: =IF(OR(B02.00[[#This Row],[c0250]]="Structured",B02.00[[#This Row],[c0250]]="Only structured coupon"),(IF(OR(B02.00[[#This Row],[c0130]]=MAX(0,B02.00[[#This Row],[c0270]],B02.00[[#This Row],[c0300]],B02.00[[#This Row],[c0320]]),B02.00[[#This Row],[c0130]]=MAX(0,B02.00[[#This Row],[c0120]],B02.00[[#This Row],[c0300]],B02.00[[#This Row],[c0320]])),"OK","KO")),"OK") -> OK | EA12: =IF(OR(B02.00[[#This Row],[c0140]]="Registered Bond",B02.00[[#This Row],[c0140]]="Bearrer Bond",B02.00[[#This Row],[c0140]]="Borrower Note Loan",B02.00[[#This Row],[c0140]]="Certificate of Deposit / Commercial Paper",B02.00[[#This Row],[c0140]]="Title of ownership",B02.00[[#This Row],[c0140]]="Cash account/saving account",B02.00[[#This Row],[c0140]]="Term deposit",B02.00[[#This Row],[c0140]]="Loan",B02.00[[#This Row],[c0140]]="Bill of exchange",B02.00[[#This Row],[c0140]]="Other"),"OK","KO") -> OK | EB12: =IF(B02.00[[#This Row],[c0160]]>=1,"OK","KO") -> OK | EC12: =IF(AND(B02.00[[#This Row],[c0020]]<>"NCNP",B02.00[[#This Row],[c0020]]<>"NCBP"),(IF(B02.00[[#This Row],[c0170]]>DATE(1900,1,1),"OK","KO")),"OK") -> OK | ED12: =IF(AND(OR(B02.00[[#This Row],[c0190]]<>"",B02.00[[#This Row],[c0200]]<>""),AND(B02.00[[#This Row],[c0020]]<>"NCNP",B02.00[[#This Row],[c0020]]<>"NCBP")),(IF(AND(B02.00[[#This Row],[c0170]]<B02.00[[#This Row],[c0190]],B02.00[[#This Row],[c0170]]<B02.00[[#This Row],[c0200]]),"OK","KO")),"OK") -> OK | EE12: =IF(AND(B02.00[[#This Row],[c0020]]<>"NCNP",B02.00[[#This Row],[c0020]]<>"NCBP"),IF(B02.00[[#This Row],[c0180]]="","KO",IF(B02.00[[#This Row],[c0180]]>DATE(1900,1,1),"OK","KO")),"OK") -> OK | EF12: =IF(AND('B9900'!$I$4<>"",B02.00[[#This Row],[c0020]]<>"NCNP",B02.00[[#This Row],[c0020]]<>"NCBP"),IF(B02.00[[#This Row],[c0180]]="","KO",IF(B02.00[[#This Row],[c0180]]>'B9900'!$I$4,"OK","KO")),"OK") -> OK | EG12: =IF(AND(B02.00[[#This Row],[c0020]]<>"NCNP",B02.00[[#This Row],[c0020]]<>"NCBP"),(IF(B02.00[[#This Row],[c0200]]>DATE(1900,1,1),"OK","KO")),"OK") -> OK | EH12: =IF(AND('B9900'!$I$4<>"",AND(B02.00[[#This Row],[c0020]]<>"NCNP",B02.00[[#This Row],[c0020]]<>"NCBP")),(IF(B02.00[[#This Row],[c0200]]>'B9900'!$I$4,"OK","KO")),"OK") -> OK | EI12: =IF(AND(B02.00[[#This Row],[c0020]]<>"NCNP",B02.00[[#This Row],[c0020]]<>"NCBP"),(IF(B02.00[[#This Row],[c0210]]>DATE(1900,1,1),"OK","KO")),"OK") -> OK | EJ12: =IF(AND('B9900'!$I$4<>"",AND(B02.00[[#This Row],[c0020]]<>"NCNP",B02.00[[#This Row],[c0020]]<>"NCBP")),(IF(B02.00[[#This Row],[c0210]]>'B9900'!$I$4,"OK","KO")),"OK") -> OK | EK12: =IF(AND(B02.00[[#This Row],[c0020]]<>"NCNP",B02.00[[#This Row],[c0020]]<>"NCBP"),(IF(OR(NOT(ISERROR(MATCH(B02.00[[#This Row],[c0220]],'ISO 3166'!B:B,0))),NOT(ISERROR(MATCH(B02.00[[#This Row],[c0220]],'ISO 3166'!E:E,0)))),"OK","KO")),"OK") -> OK | EL12: =IF(AND(B02.00[[#This Row],[c0020]]<>"NCNP",B02.00[[#This Row],[c0020]]<>"NCBP"),(IF(OR(B02.00[[#This Row],[c0230]]="Yes, supported by Legal Opinion",B02.00[[#This Row],[c0230]]="Yes, not supported by Legal Opinion",B02.00[[#This Row],[c0230]]="No",B02.00[[#This Row],[c0230]]="Not applicable",B02.00[[#This Row],[c0230]]="Aggregated"),"OK","KO")),"OK") -> OK | EM12: =IF(OR(B02.00[[#This Row],[c0250]]="Non-structured/Vanilla",B02.00[[#This Row],[c0250]]="Structured",B02.00[[#This Row],[c0250]]="Other non-standard terms",B02.00[[#This Row],[c0250]]="Only structured coupon",B02.00[[#This Row],[c0250]]="Aggregated"),"OK","KO") -> OK | EN12: =IF(OR(B02.00[[#This Row],[c0310]]="Secured",B02.00[[#This Row],[c0310]]="Unsecured"),"OK","KO") -> OK | EO12: =IF(AND(B02.00[[#This Row],[c0310]]="Secured",OR(B02.00[[#This Row],[c0250]]="Non-structured/Vanilla",B02.00[[#This Row],[c0250]]="Other non-standard terms"),B02.00[[#This Row],[c0240]]<>"ZCB issued at discount"),(IF(B02.00[[#This Row],[c0330]]=MAX(0,B02.00[[#This Row],[c0120]],B02.00[[#This Row],[c0320]]),"OK","KO")),"OK") -> OK | EP12: =IF(AND(B02.00[[#This Row],[c0310]]="Secured",OR(B02.00[[#This Row],[c0250]]="Structured",B02.00[[#This Row],[c0250]]="Only structured coupon")),(IF(OR(B02.00[[#This Row],[c0330]]=MAX(0,B02.00[[#This Row],[c0270]],B02.00[[#This Row],[c0320]]),B02.00[[#This Row],[c0330]]=MAX(0,B02.00[[#This Row],[c0120]],B02.00[[#This Row],[c0320]])),"OK","KO")),"OK") -> OK | EQ12: =IF(OR(B02.00[[#This Row],[c0350]]="Real estate",B02.00[[#This Row],[c0350]]="Ships",B02.00[[#This Row],[c0350]]="Aircraft",B02.00[[#This Row],[c0350]]="Financial",B02.00[[#This Row],[c0350]]="Other",B02.00[[#This Row],[c0350]]="Not applicable"),"OK","KO") -> OK | ER12: =IF(B02.00[[#This Row],[c0310]]="Unsecured",(IF(B02.00[[#This Row],[c0350]]="Not applicable","OK","KO")),"OK") -> OK | ES12: =IF(OR(B02.00[[#This Row],[c0440]]="NGN",B02.00[[#This Row],[c0440]]="CGN",B02.00[[#This Row],[c0440]]="Not applicable"),"OK","KO") -> OK | ET12: =IF(OR(B02.00[[#This Row],[c0530]]="T2 in phase-out",B02.00[[#This Row],[c0530]]="Grandfathered T2",B02.00[[#This Row],[c0530]]="Fully Compliant T2",B02.00[[#This Row],[c0530]]="Partially (A)T1 and T2",B02.00[[#This Row],[c0530]]="Grandfathered AT1",B02.00[[#This Row],[c0530]]="Fully Compliant AT1",B02.00[[#This Row],[c0530]]="CET1",B02.00[[#This Row],[c0530]]="No"),"OK","KO") -> OK | EU12: =IF(B02.00[[#This Row],[c0540]] ="","KO",IF(B02.00[[#This Row],[c0540]]>=0,"OK","KO")) -> OK | EV12: =IF(OR(B02.00[[#This Row],[c0550]]="T2 in phase-out",B02.00[[#This Row],[c0550]]="Grandfathered T2",B02.00[[#This Row],[c0550]]="Fully Compliant T2",B02.00[[#This Row],[c0550]]="Partially (A)T1 and T2",B02.00[[#This Row],[c0550]]="Grandfathered AT1",B02.00[[#This Row],[c0550]]="Fully Compliant AT1",B02.00[[#This Row],[c0550]]="CET1",B02.00[[#This Row],[c0550]]="No"),"OK","KO") -> OK | EW12: =IF(B02.00[[#This Row],[c0560]]="","KO",IF(B02.00[[#This Row],[c0560]]>=0,"OK","KO")) -> OK | EX12: =IF(OR(B02.00[[#This Row],[c0590]]="Lien",B02.00[[#This Row],[c0590]]="Guarantee",B02.00[[#This Row],[c0590]]="Surety",B02.00[[#This Row],[c0590]]="Guarantee obligation",B02.00[[#This Row],[c0590]]="Other",B02.00[[#This Row],[c0590]]="Not applicable",B02.00[[#This Row],[c0590]]="Aggregated"),"OK","KO") -> OK | EY12: =IF(B02.00[[#This Row],[c0610]]="","KO",IF(B02.00[[#This Row],[c0610]]>=0,"OK","KO")) -> OK | EZ12: =IF(OR(B02.00[[#This Row],[c0620]]="010 Financial liabilities held for trading",B02.00[[#This Row],[c0620]]="070 Financial liabilities at fair value through profit or loss",B02.00[[#This Row],[c0620]]="110 Financial liabilities at amortized cost",B02.00[[#This Row],[c0620]]="280 Other liabilities",B02.00[[#This Row],[c0620]]="300 Total equity",),"OK","KO") -> OK

Sheet B9000
L1: Validations
A2: Row number | B2: Tab of origin | C2: Unique identification number (known to the counterparty) | D2: Counterparty within the resolution group | E2: Counterparty name | F2: Counterparty identifier (preferably LEI) | G2: Type of counterparty identifier | H2: Internal identifier of the counterparty | I2: Counterparty type | J2: Country of the counterparty | K2: Relevant amount for Bail-in/WDC | L2: Level 1 | M2: Level 2
L3: =COUNTIF(L5:L1048576,"KO") -> 0 | M3: =COUNTIF(M5:M1048576,"KO") -> 0 | N3: =COUNTIF(N5:N1048576,"KO") -> 0 | O3: =COUNTIF(O5:O1048576,"KO") -> 2 | P3: =COUNTIF(P5:P1048576,"KO") -> 7
A4: c0010 | B4: c0011 | C4: c0020 | D4: c0030 | E4: c0040 | F4: c0050 | G4: c0060 | H4: c0070 | I4: c0080 | J4: c0090 | K4: c0100 | L4: v_1_0056 | M4: v_2_0058 | N4: v_2_0059 | O4: v_2_0060 | P4: v_2_0061
A5: 1 | B5: B0200 | C5: PTBSRDOM0037 | D5: Intragroup and intra-resolution group | E5: BANCO SANTANDER SA | F5: 5493006QMFDDMYWIAM13 | G5: LEI | H5: 0000003686 | I5: Institutions | J5: ES | K5: 500000000 | L5: =IF(B90.00[[#This Row],[c0030]]="","KO","OK") -> OK | M5: =IF(OR(B90.00[[#This Row],[c0030]]="Intragroup and intra-resolution group",B90.00[[#This Row],[c0030]]="Intragroup but not intra-resolution group",B90.00[[#This Row],[c0030]]="No"),"OK","KO") -> OK | N5: =IF(OR(B90.00[[#This Row],[c0080]]="Households",B90.00[[#This Row],[c0080]]="Micro & SME",B90.00[[#This Row],[c0080]]="Corporates",B90.00[[#This Row],[c0080]]="Institutions",B90.00[[#This Row],[c0080]]="Other financial corporations",B90.00[[#This Row],[c0080]]="Insurance firms & pension funds",B90.00[[#This Row],[c0080]]="Government, central banks & supranationals",B90.00[[#This Row],[c0080]]="Non identified, listed on an exchange platform",B90.00[[#This Row],[c0080]]="Non identified, not listed on an exchange platform"),"OK","KO") -> OK | O5: =IF(AND(B90.00[[#This Row],[c0080]]<>"XX",B90.00[[#This Row],[c0080]]<>"99"),(IF(OR(NOT(ISERROR(MATCH(B90.00[[#This Row],[c0090]],'ISO 3166'!B:B,0))),NOT(ISERROR(MATCH(B90.00[[#This Row],[c0090]],'ISO 3166'!E:E,0)))),"OK","KO")),"OK") -> OK | P5: =IF(B90.00[[#This Row],[c0030]]<>"No",(IF(B90.00[[#This Row],[c0100]]="","KO",IF(B90.00[[#This Row],[c0100]]=0,"OK","KO"))),"OK") -> KO
A6: 2 | B6: B0200 | C6: PTBSREOM0028 | D6: No | E6: Not applicable | F6: Not applicable | G6: Not applicable | H6: Not applicable | I6: Non identified, not listed on an exchange platform | J6: 99 | K6: 7661457.5 | L6: =IF(B90.00[[#This Row],[c0030]]="","KO","OK") -> OK | M6: =IF(OR(B90.00[[#This Row],[c0030]]="Intragroup and intra-resolution group",B90.00[[#This Row],[c0030]]="Intragroup but not intra-resolution group",B90.00[[#This Row],[c0030]]="No"),"OK","KO") -> OK | N6: =IF(OR(B90.00[[#This Row],[c0080]]="Households",B90.00[[#This Row],[c0080]]="Micro & SME",B90.00[[#This Row],[c0080]]="Corporates",B90.00[[#This Row],[c0080]]="Institutions",B90.00[[#This Row],[c0080]]="Other financial corporations",B90.00[[#This Row],[c0080]]="Insurance firms & pension funds",B90.00[[#This Row],[c0080]]="Government, central banks & supranationals",B90.00[[#This Row],[c0080]]="Non identified, listed on an exchange platform",B90.00[[#This Row],[c0080]]="Non identified, not listed on an exchange platform"),"OK","KO") -> OK | O6: =IF(AND(B90.00[[#This Row],[c0080]]<>"XX",B90.00[[#This Row],[c0080]]<>"99"),(IF(OR(NOT(ISERROR(MATCH(B90.00[[#This Row],[c0090]],'ISO 3166'!B:B,0))),NOT(ISERROR(MATCH(B90.00[[#This Row],[c0090]],'ISO 3166'!E:E,0)))),"OK","KO")),"OK") -> KO | P6: =IF(B90.00[[#This Row],[c0030]]<>"No",(IF(B90.00[[#This Row],[c0100]]="","KO",IF(B90.00[[#This Row],[c0100]]=0,"OK","KO"))),"OK") -> OK
A7: 3 | B7: B0200 | C7: PTCPP0AM0007 | D7: No | E7: Not applicable | F7: Not applicable | G7: Not applicable | H7: Not applicable | I7: Non identified, not listed on an exchange platform | J7: 99 | K7: 1762761 | L7: =IF(B90.00[[#This Row],[c0030]]="","KO","OK") -> OK | M7: =IF(OR(B90.00[[#This Row],[c0030]]="Intragroup and intra-resolution group",B90.00[[#This Row],[c0030]]="Intragroup but not intra-resolution group",B90.00[[#This Row],[c0030]]="No"),"OK","KO") -> OK | N7: =IF(OR(B90.00[[#This Row],[c0080]]="Households",B90.00[[#This Row],[c0080]]="Micro & SME",B90.00[[#This Row],[c0080]]="Corporates",B90.00[[#This Row],[c0080]]="Institutions",B90.00[[#This Row],[c0080]]="Other financial corporations",B90.00[[#This Row],[c0080]]="Insurance firms & pension funds",B90.00[[#This Row],[c0080]]="Government, central banks & supranationals",B90.00[[#This Row],[c0080]]="Non identified, listed on an exchange platform",B90.00[[#This Row],[c0080]]="Non identified, not listed on an exchange platform"),"OK","KO") -> OK | O7: =IF(AND(B90.00[[#This Row],[c0080]]<>"XX",B90.00[[#This Row],[c0080]]<>"99"),(IF(OR(NOT(ISERROR(MATCH(B90.00[[#This Row],[c0090]],'ISO 3166'!B:B,0))),NOT(ISERROR(MATCH(B90.00[[#This Row],[c0090]],'ISO 3166'!E:E,0)))),"OK","KO")),"OK") -> KO | P7: =IF(B90.00[[#This Row],[c0030]]<>"No",(IF(B90.00[[#This Row],[c0100]]="","KO",IF(B90.00[[#This Row],[c0100]]=0,"OK","KO"))),"OK") -> OK
A8: 4 | B8: B0200 | C8: PTCPP0AM0007 | D8: Intragroup and intra-resolution group | E8: BANCO SANTANDER SA | F8: 5493006QMFDDMYWIAM13 | G8: LEI | H8: 0000003686 | I8: Institutions | J8: ES | K8: 1559695926 | L8: =IF(B90.00[[#This Row],[c0030]]="","KO","OK") -> OK | M8: =IF(OR(B90.00[[#This Row],[c0030]]="Intragroup and intra-resolution group",B90.00[[#This Row],[c0030]]="Intragroup but not intra-resolution group",B90.00[[#This Row],[c0030]]="No"),"OK","KO") -> OK | N8: =IF(OR(B90.00[[#This Row],[c0080]]="Households",B90.00[[#This Row],[c0080]]="Micro & SME",B90.00[[#This Row],[c0080]]="Corporates",B90.00[[#This Row],[c0080]]="Institutions",B90.00[[#This Row],[c0080]]="Other financial corporations",B90.00[[#This Row],[c0080]]="Insurance firms & pension funds",B90.00[[#This Row],[c0080]]="Government, central banks & supranationals",B90.00[[#This Row],[c0080]]="Non identified, listed on an exchange platform",B90.00[[#This Row],[c0080]]="Non identified, not listed on an exchange platform"),"OK","KO") -> OK | O8: =IF(AND(B90.00[[#This Row],[c0080]]<>"XX",B90.00[[#This Row],[c0080]]<>"99"),(IF(OR(NOT(ISERROR(MATCH(B90.00[[#This Row],[c0090]],'ISO 3166'!B:B,0))),NOT(ISERROR(MATCH(B90.00[[#This Row],[c0090]],'ISO 3166'!E:E,0)))),"OK","KO")),"OK") -> OK | P8: =IF(B90.00[[#This Row],[c0030]]<>"No",(IF(B90.00[[#This Row],[c0100]]="","KO",IF(B90.00[[#This Row],[c0100]]=0,"OK","KO"))),"OK") -> KO
A9: 5 | B9: B0200 | C9: PTSTOCOM0007 | D9: Intragroup and intra-resolution group | E9: BANCO SANTANDER SA | F9: 5493006QMFDDMYWIAM13 | G9: LEI | H9: 0000003686 | I9: Institutions | J9: ES | K9: 400000000 | L9: =IF(B90.00[[#This Row],[c0030]]="","KO","OK") -> OK | M9: =IF(OR(B90.00[[#This Row],[c0030]]="Intragroup and intra-resolution group",B90.00[[#This Row],[c0030]]="Intragroup but not intra-resolution group",B90.00[[#This Row],[c0030]]="No"),"OK","KO") -> OK | N9: =IF(OR(B90.00[[#This Row],[c0080]]="Households",B90.00[[#This Row],[c0080]]="Micro & SME",B90.00[[#This Row],[c0080]]="Corporates",B90.00[[#This Row],[c0080]]="Institutions",B90.00[[#This Row],[c0080]]="Other financial corporations",B90.00[[#This Row],[c0080]]="Insurance firms & pension funds",B90.00[[#This Row],[c0080]]="Government, central banks & supranationals",B90.00[[#This Row],[c0080]]="Non identified, listed on an exchange platform",B90.00[[#This Row],[c0080]]="Non identified, not listed on an exchange platform"),"OK","KO") -> OK | O9: =IF(AND(B90.00[[#This Row],[c0080]]<>"XX",B90.00[[#This Row],[c0080]]<>"99"),(IF(OR(NOT(ISERROR(MATCH(B90.00[[#This Row],[c0090]],'ISO 3166'!B:B,0))),NOT(ISERROR(MATCH(B90.00[[#This Row],[c0090]],'ISO 3166'!E:E,0)))),"OK","KO")),"OK") -> OK | P9: =IF(B90.00[[#This Row],[c0030]]<>"No",(IF(B90.00[[#This Row],[c0100]]="","KO",IF(B90.00[[#This Row],[c0100]]=0,"OK","KO"))),"OK") -> KO
A10: 6 | B10: B0200 | C10: PTSTOEOM0021 | D10: Intragroup and intra-resolution group | E10: BANCO SANTANDER SA | F10: 5493006QMFDDMYWIAM13 | G10: LEI | H10: 0000003686 | I10: Institutions | J10: ES | K10: 6.0834855e+08 | L10: =IF(B90.00[[#This Row],[c0030]]="","KO","OK") -> OK | M10: =IF(OR(B90.00[[#This Row],[c0030]]="Intragroup and intra-resolution group",B90.00[[#This Row],[c0030]]="Intragroup but not intra-resolution group",B90.00[[#This Row],[c0030]]="No"),"OK","KO") -> OK | N10: =IF(OR(B90.00[[#This Row],[c0080]]="Households",B90.00[[#This Row],[c0080]]="Micro & SME",B90.00[[#This Row],[c0080]]="Corporates",B90.00[[#This Row],[c0080]]="Institutions",B90.00[[#This Row],[c0080]]="Other financial corporations",B90.00[[#This Row],[c0080]]="Insurance firms & pension funds",B90.00[[#This Row],[c0080]]="Government, central banks & supranationals",B90.00[[#This Row],[c0080]]="Non identified, listed on an exchange platform",B90.00[[#This Row],[c0080]]="Non identified, not listed on an exchange platform"),"OK","KO") -> OK | O10: =IF(AND(B90.00[[#This Row],[c0080]]<>"XX",B90.00[[#This Row],[c0080]]<>"99"),(IF(OR(NOT(ISERROR(MATCH(B90.00[[#This Row],[c0090]],'ISO 3166'!B:B,0))),NOT(ISERROR(MATCH(B90.00[[#This Row],[c0090]],'ISO 3166'!E:E,0)))),"OK","KO")),"OK") -> OK | P10: =IF(B90.00[[#This Row],[c0030]]<>"No",(IF(B90.00[[#This Row],[c0100]]="","KO",IF(B90.00[[#This Row],[c0100]]=0,"OK","KO"))),"OK") -> KO
A11: 7 | B11: B0200 | C11: PTSTOFOM0004 | D11: Intragroup and intra-resolution group | E11: BANCO SANTANDER SA | F11: 5493006QMFDDMYWIAM13 | G11: LEI | H11: 0000003686 | I11: Institutions | J11: ES | K11: 2.0410699e+08 | L11: =IF(B90.00[[#This Row],[c0030]]="","KO","OK") -> OK | M11: =IF(OR(B90.00[[#This Row],[c0030]]="Intragroup and intra-resolution group",B90.00[[#This Row],[c0030]]="Intragroup but not intra-resolution group",B90.00[[#This Row],[c0030]]="No"),"OK","KO") -> OK | N11: =IF(OR(B90.00[[#This Row],[c0080]]="Households",B90.00[[#This Row],[c0080]]="Micro & SME",B90.00[[#This Row],[c0080]]="Corporates",B90.00[[#This Row],[c0080]]="Institutions",B90.00[[#This Row],[c0080]]="Other financial corporations",B90.00[[#This Row],[c0080]]="Insurance firms & pension funds",B90.00[[#This Row],[c0080]]="Government, central banks & supranationals",B90.00[[#This Row],[c0080]]="Non identified, listed on an exchange platform",B90.00[[#This Row],[c0080]]="Non identified, not listed on an exchange platform"),"OK","KO") -> OK | O11: =IF(AND(B90.00[[#This Row],[c0080]]<>"XX",B90.00[[#This Row],[c0080]]<>"99"),(IF(OR(NOT(ISERROR(MATCH(B90.00[[#This Row],[c0090]],'ISO 3166'!B:B,0))),NOT(ISERROR(MATCH(B90.00[[#This Row],[c0090]],'ISO 3166'!E:E,0)))),"OK","KO")),"OK") -> OK | P11: =IF(B90.00[[#This Row],[c0030]]<>"No",(IF(B90.00[[#This Row],[c0100]]="","KO",IF(B90.00[[#This Row],[c0100]]=0,"OK","KO"))),"OK") -> KO
A12: 8 | B12: B0200 | C12: PTSTOGOM0003 | D12: Intragroup and intra-resolution group | E12: BANCO SANTANDER SA | F12: 5493006QMFDDMYWIAM13 | G12: LEI | H12: 0000003686 | I12: Institutions | J12: ES | K12: 300000000 | L12: =IF(B90.00[[#This Row],[c0030]]="","KO","OK") -> OK | M12: =IF(OR(B90.00[[#This Row],[c0030]]="Intragroup and intra-resolution group",B90.00[[#This Row],[c0030]]="Intragroup but not intra-resolution group",B90.00[[#This Row],[c0030]]="No"),"OK","KO") -> OK | N12: =IF(OR(B90.00[[#This Row],[c0080]]="Households",B90.00[[#This Row],[c0080]]="Micro & SME",B90.00[[#This Row],[c0080]]="Corporates",B90.00[[#This Row],[c0080]]="Institutions",B90.00[[#This Row],[c0080]]="Other financial corporations",B90.00[[#This Row],[c0080]]="Insurance firms & pension funds",B90.00[[#This Row],[c0080]]="Government, central banks & supranationals",B90.00[[#This Row],[c0080]]="Non identified, listed on an exchange platform",B90.00[[#This Row],[c0080]]="Non identified, not listed on an exchange platform"),"OK","KO") -> OK | O12: =IF(AND(B90.00[[#This Row],[c0080]]<>"XX",B90.00[[#This Row],[c0080]]<>"99"),(IF(OR(NOT(ISERROR(MATCH(B90.00[[#This Row],[c0090]],'ISO 3166'!B:B,0))),NOT(ISERROR(MATCH(B90.00[[#This Row],[c0090]],'ISO 3166'!E:E,0)))),"OK","KO")),"OK") -> OK | P12: =IF(B90.00[[#This Row],[c0030]]<>"No",(IF(B90.00[[#This Row],[c0100]]="","KO",IF(B90.00[[#This Row],[c0100]]=0,"OK","KO"))),"OK") -> KO
A13: 9 | B13: B0200 | C13: PTSTOHOM0002 | D13: Intragroup and intra-resolution group | E13: BANCO SANTANDER SA | F13: 5493006QMFDDMYWIAM13 | G13: LEI | H13: 0000003686 | I13: Institutions | J13: ES | K13: 5.0601101e+08 | L13: =IF(B90.00[[#This Row],[c0030]]="","KO","OK") -> OK | M13: =IF(OR(B90.00[[#This Row],[c0030]]="Intragroup and intra-resolution group",B90.00[[#This Row],[c0030]]="Intragroup but not intra-resolution group",B90.00[[#This Row],[c0030]]="No"),"OK","KO") -> OK | N13: =IF(OR(B90.00[[#This Row],[c0080]]="Households",B90.00[[#This Row],[c0080]]="Micro & SME",B90.00[[#This Row],[c0080]]="Corporates",B90.00[[#This Row],[c0080]]="Institutions",B90.00[[#This Row],[c0080]]="Other financial corporations",B90.00[[#This Row],[c0080]]="Insurance firms & pension funds",B90.00[[#This Row],[c0080]]="Government, central banks & supranationals",B90.00[[#This Row],[c0080]]="Non identified, listed on an exchange platform",B90.00[[#This Row],[c0080]]="Non identified, not listed on an exchange platform"),"OK","KO") -> OK | O13: =IF(AND(B90.00[[#This Row],[c0080]]<>"XX",B90.00[[#This Row],[c0080]]<>"99"),(IF(OR(NOT(ISERROR(MATCH(B90.00[[#This Row],[c0090]],'ISO 3166'!B:B,0))),NOT(ISERROR(MATCH(B90.00[[#This Row],[c0090]],'ISO 3166'!E:E,0)))),"OK","KO")),"OK") -> OK | P13: =IF(B90.00[[#This Row],[c0030]]<>"No",(IF(B90.00[[#This Row],[c0100]]="","KO",IF(B90.00[[#This Row],[c0100]]=0,"OK","KO"))),"OK") -> KO

Sheet V_Level 1
B2: MBDT - Level 1 Validation Rules: completeness checks.
M3: KO | O3: OK | R3: KO | T3: OK
B4: Check ID | C4: Tab | D4: Data point (Row/Column) | E4: Data point (Label) | F4: Data point type | G4: High severity (i.e the validation rule should in general not be breached) | H4: Warning only (i.e. the validation rule can be breached in certain cases) | I4: Type of test (missing values means "not applicable" or "not available") | J4: Prerequisite / Dependency | K4: Explanation | L4: Total registros | M4: Registros | N4: Porcentaje | O4: Registros | P4: Porcentaje | Q4: Amount | R4: Total | S4: Porcentaje | T4: Total | U4: Porcentaje
B5: v_1_0001 | C5: B02.00 | D5: 0010 | E5: Row number | F5: Numeric: Integer | G5: X | I5: Test for missing values. | K5: Missing value. The field must be reported. | L5: =SUM(M5,O5) -> 8 | M5: =COUNTIF('B0200'!CD:CD,"KO") -> 0 | N5: =M5/L5 -> 0 | O5: =COUNTIF('B0200'!CD:CD,"OK") -> 8 | P5: =O5/L5 -> 1 | Q5: =SUM(R5,T5) -> 4.0921507e+09 | R5: =SUMIFS('B0200'!L:L,'B0200'!CD:CD,"KO") -> 0 | S5: =R5/Q5 -> 0 | T5: =SUMIFS('B0200'!L:L,'B0200'!CD:CD,"OK") -> 4.0921507e+09 | U5: =T5/Q5 -> 1
B6: v_1_0002 | C6: B02.00 | D6: 0030 | E6: Unique identification number (known to the counterparty) | F6: String: Free text | G6: X | I6: Test for missing values. | K6: Missing value. The field must be reported. | L6: =SUM(M6,O6) -> 8 | M6: =COUNTIF('B0200'!CE:CE,"KO") -> 0 | N6: =M6/L6 -> 0 | O6: =COUNTIF('B0200'!CE:CE,"OK") -> 8 | P6: =O6/L6 -> 1 | Q6: =SUM(R6,T6) -> 4.0921507e+09 | R6: =SUMIFS('B0200'!L:L,'B0200'!CE:CE,"KO") -> 0 | S6: =R6/Q6 -> 0 | T6: =SUMIFS('B0200'!L:L,'B0200'!CE:CE,"OK") -> 4.0921507e+09 | U6: =T6/Q6 -> 1
B7: v_1_0003 | C7: B02.00 | D7: 0040 | E7: Type of the unique identifier (known to the counterparty) | F7: String: Free text, but fixed values for specific items | G7: X | I7: Test for missing values. | K7: Missing value. The field must be reported. | L7: =SUM(M7,O7) -> 8 | M7: =COUNTIF('B0200'!CF:CF,"KO") -> 0 | N7: =M7/L7 -> 0 | O7: =COUNTIF('B0200'!CF:CF,"OK") -> 8 | P7: =O7/L7 -> 1 | Q7: =SUM(R7,T7) -> 4.0921507e+09 | R7: =SUMIFS('B0200'!L:L,'B0200'!CF:CF,"KO") -> 0 | S7: =R7/Q7 -> 0 | T7: =SUMIFS('B0200'!L:L,'B0200'!CF:CF,"OK") -> 4.0921507e+09 | U7: =T7/Q7 -> 1
B8: v_1_0004 | C8: B02.00 | D8: 0070 | E8: Contract Currency | F8: String: 3-letters ISO 4217 | G8: X | I8: Test for missing values. | K8: Missing value. The field must be reported. | L8: =SUM(M8,O8) -> 8 | M8: =COUNTIF('B0200'!CG:CG,"KO") -> 0 | N8: =M8/L8 -> 0 | O8: =COUNTIF('B0200'!CG:CG,"OK") -> 8 | P8: =O8/L8 -> 1 | Q8: =SUM(R8,T8) -> 4.0921507e+09 | R8: =SUMIFS('B0200'!L:L,'B0200'!CG:CG,"KO") -> 0 | S8: =R8/Q8 -> 0 | T8: =SUMIFS('B0200'!L:L,'B0200'!CG:CG,"OK") -> 4.0921507e+09 | U8: =T8/Q8 -> 1
B9: v_1_0005 | C9: B02.00 | D9: 0080 | E9: Outstanding principal amount | F9: Numeric: 2 decimals | G9: X | I9: Test for missing values. | J9: Rule applicable if c0250 = ("Non-Structured/Vanilla" OR "Other non-standard terms") | K9: Missing value. The field must be reported for non-structured liabilities. | L9: =SUM(M9,O9) -> 8 | M9: =COUNTIF('B0200'!CH:CH,"KO") -> 0 | N9: =M9/L9 -> 0 | O9: =COUNTIF('B0200'!CH:CH,"OK") -> 8 | P9: =O9/L9 -> 1 | Q9: =SUM(R9,T9) -> 4.0921507e+09 | R9: =SUMIFS('B0200'!L:L,'B0200'!CH:CH,"KO") -> 0 | S9: =R9/Q9 -> 0 | T9: =SUMIFS('B0200'!L:L,'B0200'!CH:CH,"OK") -> 4.0921507e+09 | U9: =T9/Q9 -> 1
B10: v_1_0006 | C10: B02.00 | D10: 0080 | E10: Outstanding principal amount | F10: Numeric: 2 decimals | H10: X | I10: Test for missing values. | J10: Rule applicable if c0250 = ("Structured" OR "Only structured coupon") | K10: Missing value (warning only). For structured liabilities, the field has to be reported if the information exists. | L10: =SUM(M10,O10) -> 8 | M10: =COUNTIF('B0200'!CI:CI,"KO") -> 0 | N10: =M10/L10 -> 0 | O10: =COUNTIF('B0200'!CI:CI,"OK") -> 8 | P10: =O10/L10 -> 1 | Q10: =SUM(R10,T10) -> 4.0921507e+09 | R10: =SUMIFS('B0200'!L:L,'B0200'!CI:CI,"KO") -> 0 | S10: =R10/Q10 -> 0 | T10: =SUMIFS('B0200'!L:L,'B0200'!CI:CI,"OK") -> 4.0921507e+09 | U10: =T10/Q10 -> 1
B11: v_1_0007 | C11: B02.00 | D11: 0090 | E11: Portion of instrument or liability held by the reporting entity | F11: Numeric: 2 decimals | G11: X | I11: Test for missing values. | J11: Rule applicable only if c0040 = "ISIN" | K11: Missing value. The field must be reported for securities. | L11: =SUM(M11,O11) -> 8 | M11: =COUNTIF('B0200'!CJ:CJ,"KO") -> 0 | N11: =M11/L11 -> 0 | O11: =COUNTIF('B0200'!CJ:CJ,"OK") -> 8 | P11: =O11/L11 -> 1 | Q11: =SUM(R11,T11) -> 4.0921507e+09 | R11: =SUMIFS('B0200'!L:L,'B0200'!CJ:CJ,"KO") -> 0 | S11: =R11/Q11 -> 0 | T11: =SUMIFS('B0200'!L:L,'B0200'!CJ:CJ,"OK") -> 4.0921507e+09 | U11: =T11/Q11 -> 1
B12: v_1_0008 | C12: B02.00 | D12: 0100 | E12: Accrued interest | F12: Numeric: 2 decimals | G12: X | I12: Test for missing values. | J12: Rule applicable if c0250 = ("Non-Structured" OR "Other non-standard terms") AND c0240 != "ZCB issued at discount" | K12: Missing value. For non-structured liabilities that are not zero coupon bonds issued at discount, this field must be reported. | L12: =SUM(M12,O12) -> 8 | M12: =COUNTIF('B0200'!CK:CK,"KO") -> 0 | N12: =M12/L12 -> 0 | O12: =COUNTIF('B0200'!CK:CK,"OK") -> 8 | P12: =O12/L12 -> 1 | Q12: =SUM(R12,T12) -> 4.0921507e+09 | R12: =SUMIFS('B0200'!L:L,'B0200'!CK:CK,"KO") -> 0 | S12: =R12/Q12 -> 0 | T12: =SUMIFS('B0200'!L:L,'B0200'!CK:CK,"OK") -> 4.0921507e+09 | U12: =T12/Q12 -> 1
B13: v_1_0009 | C13: B02.00 | D13: 0100 | E13: Accrued interest | F13: Numeric: 2 decimals | H13: X | I13: Test for missing values. | J13: Rule applicable only if c0250 != ("Structured" OR "Only structured coupon") | K13: Missing value (warning only). For structured liabilities, the field has to be reported if the information exists. | L13: =SUM(M13,O13) -> 8 | M13: =COUNTIF('B0200'!CL:CL,"KO") -> 0 | N13: =M13/L13 -> 0 | O13: =COUNTIF('B0200'!CL:CL,"OK") -> 8 | P13: =O13/L13 -> 1 | Q13: =SUM(R13,T13) -> 4.0921507e+09 | R13: =SUMIFS('B0200'!L:L,'B0200'!CL:CL,"KO") -> 0 | S13: =R13/Q13 -> 0 | T13: =SUMIFS('B0200'!L:L,'B0200'!CL:CL,"OK") -> 4.0921507e+09 | U13: =T13/Q13 -> 1
B14: v_1_0010 | C14: B02.00 | D14: 0120 | E14: Outstanding amount | F14: Numeric: 2 decimals | G14: X | I14: Test for missing values. | J14: Rule applicable if c0250 = ("Non-Structured/Vanilla" OR "Other non-standard terms") | K14: Missing value. For non-structured liabilities, this field must be reported. | L14: =SUM(M14,O14) -> 8 | M14: =COUNTIF('B0200'!CM:CM,"KO") -> 0 | N14: =M14/L14 -> 0 | O14: =COUNTIF('B0200'!CM:CM,"OK") -> 8 | P14: =O14/L14 -> 1 | Q14: =SUM(R14,T14) -> 4.0921507e+09 | R14: =SUMIFS('B0200'!L:L,'B0200'!CM:CM,"KO") -> 0 | S14: =R14/Q14 -> 0 | T14: =SUMIFS('B0200'!L:L,'B0200'!CM:CM,"OK") -> 4.0921507e+09 | U14: =T14/Q14 -> 1
B15: v_1_0011 | C15: B02.00 | D15: 0120 | E15: Outstanding amount | F15: Numeric: 2 decimals | H15: X | I15: Test for missing values. | J15: Rule applicable only if c0250 != ("Structured" OR "Only structured coupon") | K15: Missing value (warning only). For structured liabilities, the field has to be reported if the information exists. | L15: =SUM(M15,O15) -> 8 | M15: =COUNTIF('B0200'!CN:CN,"KO") -> 0 | N15: =M15/L15 -> 0 | O15: =COUNTIF('B0200'!CN:CN,"OK") -> 8 | P15: =O15/L15 -> 1 | Q15: =SUM(R15,T15) -> 4.0921507e+09 | R15: =SUMIFS('B0200'!L:L,'B0200'!CN:CN,"KO") -> 0 | S15: =R15/Q15 -> 0 | T15: =SUMIFS('B0200'!L:L,'B0200'!CN:CN,"OK") -> 4.0921507e+09 | U15: =T15/Q15 -> 1
B16: v_1_0012 | C16: B02.00 | D16: 0130 | E16: Relevant amount for Bail-in/WDC | F16: Numeric: 2 decimals | G16: X | I16: Test for missing values. | K16: Missing value. The field must be reported. | L16: =SUM(M16,O16) -> 8 | M16: =COUNTIF('B0200'!CO:CO,"KO") -> 0 | N16: =M16/L16 -> 0 | O16: =COUNTIF('B0200'!CO:CO,"OK") -> 8 | P16: =O16/L16 -> 1 | Q16: =SUM(R16,T16) -> 4.0921507e+09 | R16: =SUMIFS('B0200'!L:L,'B0200'!CO:CO,"KO") -> 0 | S16: =R16/Q16 -> 0 | T16: =SUMIFS('B0200'!L:L,'B0200'!CO:CO,"OK") -> 4.0921507e+09 | U16: =T16/Q16 -> 1
B17: v_1_0013 | C17: B02.00 | D17: 0140 | E17: Nature of the liability | F17: String: Drop-down | G17: X | I17: Test for missing values. | K17: Missing value. The field must be reported. | L17: =SUM(M17,O17) -> 8 | M17: =COUNTIF('B0200'!CP:CP,"KO") -> 0 | N17: =M17/L17 -> 0 | O17: =COUNTIF('B0200'!CP:CP,"OK") -> 8 | P17: =O17/L17 -> 1 | Q17: =SUM(R17,T17) -> 4.0921507e+09 | R17: =SUMIFS('B0200'!L:L,'B0200'!CP:CP,"KO") -> 0 | S17: =R17/Q17 -> 0 | T17: =SUMIFS('B0200'!L:L,'B0200'!CP:CP,"OK") -> 4.0921507e+09 | U17: =T17/Q17 -> 1
B18: v_1_0014 | C18: B02.00 | D18: 0141 | E18: Nature of the liability (if other) | F18: String: Free text | G18: X | I18: Test for missing values. | J18: Rule applicable only if c0140 = "Other". | K18: Missing value. The field must be reported if option "Other" has been selected in c0140. | L18: =SUM(M18,O18) -> 8 | M18: =COUNTIF('B0200'!CQ:CQ,"KO") -> 0 | N18: =M18/L18 -> 0 | O18: =COUNTIF('B0200'!CQ:CQ,"OK") -> 8 | P18: =O18/L18 -> 1 | Q18: =SUM(R18,T18) -> 4.0921507e+09 | R18: =SUMIFS('B0200'!L:L,'B0200'!CQ:CQ,"KO") -> 0 | S18: =R18/Q18 -> 0 | T18: =SUMIFS('B0200'!L:L,'B0200'!CQ:CQ,"OK") -> 4.0921507e+09 | U18: =T18/Q18 -> 1
B19: v_1_0015 | C19: B02.00 | D19: 0160 | E19: Insolvency ranking | F19: Numeric: Integer | G19: X | I19: Test for missing values. | K19: Missing value. The field must be reported. | L19: =SUM(M19,O19) -> 8 | M19: =COUNTIF('B0200'!CR:CR,"KO") -> 0 | N19: =M19/L19 -> 0 | O19: =COUNTIF('B0200'!CR:CR,"OK") -> 8 | P19: =O19/L19 -> 1 | Q19: =SUM(R19,T19) -> 4.0921507e+09 | R19: =SUMIFS('B0200'!L:L,'B0200'!CR:CR,"KO") -> 0 | S19: =R19/Q19 -> 0 | T19: =SUMIFS('B0200'!L:L,'B0200'!CR:CR,"OK") -> 4.0921507e+09 | U19: =T19/Q19 -> 1
B20: v_1_0016 | C20: B02.00 | D20: 0162 | E20: Bail-in cascade | F20: String: Fixed values | G20: X | I20: Test for missing values. | K20: Missing value. The field must be reported. | L20: =SUM(M20,O20) -> 8 | M20: =COUNTIF('B0200'!CS:CS,"KO") -> 0 | N20: =M20/L20 -> 0 | O20: =COUNTIF('B0200'!CS:CS,"OK") -> 8 | P20: =O20/L20 -> 1 | Q20: =SUM(R20,T20) -> 4.0921507e+09 | R20: =SUMIFS('B0200'!L:L,'B0200'!CS:CS,"KO") -> 0 | S20: =R20/Q20 -> 0 | T20: =SUMIFS('B0200'!L:L,'B0200'!CS:CS,"OK") -> 4.0921507e+09 | U20: =T20/Q20 -> 1
B21: v_1_0017 | C21: B02.00 | D21: 0180 | E21: Date of the next interest payment | F21: Date: yyyy-mm-dd | G21: X | I21: Test for missing values. | J21: Rule applicable if c0250 = ("Non-Structured/Vanilla" OR "Other non-standard terms") AND c0240 != "ZCB issued at discount" | K21: Missing value. For non-structured liabilities that are not zero coupon bonds issued at discount, this field is must be reported. | L21: =SUM(M21,O21) -> 8 | M21: =COUNTIF('B0200'!CT:CT,"KO") -> 0 | N21: =M21/L21 -> 0 | O21: =COUNTIF('B0200'!CT:CT,"OK") -> 8 | P21: =O21/L21 -> 1 | Q21: =SUM(R21,T21) -> 4.0921507e+09 | R21: =SUMIFS('B0200'!L:L,'B0200'!CT:CT,"KO") -> 0 | S21: =R21/Q21 -> 0 | T21: =SUMIFS('B0200'!L:L,'B0200'!CT:CT,"OK") -> 4.0921507e+09 | U21: =T21/Q21 -> 1
B22: v_1_0018 | C22: B02.00 | D22: 0180 | E22: Date of the next interest payment | F22: Date: yyyy-mm-dd | H22: X | I22: Test for missing values. | J22: Rule applicable only if c0250 != ("Structured" OR "Only structured coupon") | K22: Missing value (warning only). For structured liabilities, this field should be reported only if the information exists.. | L22: =SUM(M22,O22) -> 8 | M22: =COUNTIF('B0200'!CU:CU,"KO") -> 0 | N22: =M22/L22 -> 0 | O22: =COUNTIF('B0200'!CU:CU,"OK") -> 8 | P22: =O22/L22 -> 1 | Q22: =SUM(R22,T22) -> 4.0921507e+09 | R22: =SUMIFS('B0200'!L:L,'B0200'!CU:CU,"KO") -> 0 | S22: =R22/Q22 -> 0 | T22: =SUMIFS('B0200'!L:L,'B0200'!CU:CU,"OK") -> 4.0921507e+09 | U22: =T22/Q22 -> 1
B23: v_1_0019 | C23: B02.00 | D23: 0200 | E23: Earliest redemption date | F23: Date: yyyy-mm-dd | H23: X | I23: Test for missing values. | K23: Missing value (warning only). This field needs to be reported if the information exists. | L23: =SUM(M23,O23) -> 8 | M23: =COUNTIF('B0200'!CV:CV,"KO") -> 0 | N23: =M23/L23 -> 0 | O23: =COUNTIF('B0200'!CV:CV,"OK") -> 8 | P23: =O23/L23 -> 1 | Q23: =SUM(R23,T23) -> 4.0921507e+09 | R23: =SUMIFS('B0200'!L:L,'B0200'!CV:CV,"KO") -> 0 | S23: =R23/Q23 -> 0 | T23: =SUMIFS('B0200'!L:L,'B0200'!CV:CV,"OK") -> 4.0921507e+09 | U23: =T23/Q23 -> 1
B24: v_1_0020 | C24: B02.00 | D24: 0210 | E24: Legal maturity | F24: Date: yyyy-mm-dd | G24: X | I24: Test for missing values. | J24: Rule applicable if c0140 != "Cash account/saving account". | K24: Missing value.For liabilities other than of the type "Cash account/savings account, the field must be reported. | L24: =SUM(M24,O24) -> 8 | M24: =COUNTIF('B0200'!CW:CW,"KO") -> 0 | N24: =M24/L24 -> 0 | O24: =COUNTIF('B0200'!CW:CW,"OK") -> 8 | P24: =O24/L24 -> 1 | Q24: =SUM(R24,T24) -> 4.0921507e+09 | R24: =SUMIFS('B0200'!L:L,'B0200'!CW:CW,"KO") -> 0 | S24: =R24/Q24 -> 0 | T24: =SUMIFS('B0200'!L:L,'B0200'!CW:CW,"OK") -> 4.0921507e+09 | U24: =T24/Q24 -> 1
B25: v_1_0021 | C25: B02.00 | D25: 0220 | E25: Governing law | F25: String: ISO 3166-1 alpha 2 / ISO 3166-2 | G25: X | I25: Test for missing values. | K25: Missing value. The field must be reported. | L25: =SUM(M25,O25) -> 8 | M25: =COUNTIF('B0200'!CX:CX,"KO") -> 0 | N25: =M25/L25 -> 0 | O25: =COUNTIF('B0200'!CX:CX,"OK") -> 8 | P25: =O25/L25 -> 1 | Q25: =SUM(R25,T25) -> 4.0921507e+09 | R25: =SUMIFS('B0200'!L:L,'B0200'!CX:CX,"KO") -> 0 | S25: =R25/Q25 -> 0 | T25: =SUMIFS('B0200'!L:L,'B0200'!CX:CX,"OK") -> 4.0921507e+09 | U25: =T25/Q25 -> 1
B26: v_1_0022 | C26: B02.00 | D26: 0250 | E26: Structured product | F26: String: Drop-down | G26: X | I26: Test for missing values. | K26: Missing value. The field must be reported. | L26: =SUM(M26,O26) -> 8 | M26: =COUNTIF('B0200'!CY:CY,"KO") -> 0 | N26: =M26/L26 -> 0 | O26: =COUNTIF('B0200'!CY:CY,"OK") -> 8 | P26: =O26/L26 -> 1 | Q26: =SUM(R26,T26) -> 4.0921507e+09 | R26: =SUMIFS('B0200'!L:L,'B0200'!CY:CY,"KO") -> 0 | S26: =R26/Q26 -> 0 | T26: =SUMIFS('B0200'!L:L,'B0200'!CY:CY,"OK") -> 4.0921507e+09 | U26: =T26/Q26 -> 1
B27: v_1_0023 | C27: B02.00 | D27: 0260 | E27: Guaranteed minimum repayment amount of the structured product | F27: Numeric: 2 decimals | H27: X | I27: Test for missing values. | J27: Rule applicable only if c0250 = ("Structured" OR "Structured coupon only") | K27: Missing value (warning only). For structured liabilities, this field should be reported if the information exists.. | L27: =SUM(M27,O27) -> 8 | M27: =COUNTIF('B0200'!CZ:CZ,"KO") -> 0 | N27: =M27/L27 -> 0 | O27: =COUNTIF('B0200'!CZ:CZ,"OK") -> 8 | P27: =O27/L27 -> 1 | Q27: =SUM(R27,T27) -> 4.0921507e+09 | R27: =SUMIFS('B0200'!L:L,'B0200'!CZ:CZ,"KO") -> 0 | S27: =R27/Q27 -> 0 | T27: =SUMIFS('B0200'!L:L,'B0200'!CZ:CZ,"OK") -> 4.0921507e+09 | U27: =T27/Q27 -> 1
B28: v_1_0024 | C28: B02.00 | D28: 0270 | E28: Fair value of the structured product | F28: Numeric: 2 decimals | G28: X | I28: Test for missing values. | J28: Rule applicable only if c0250 = ("Structured" OR "Structured coupon only") | K28: Missing value. The field must be reported for structured products. | L28: =SUM(M28,O28) -> 8 | M28: =COUNTIF('B0200'!DA:DA,"KO") -> 0 | N28: =M28/L28 -> 0 | O28: =COUNTIF('B0200'!DA:DA,"OK") -> 8 | P28: =O28/L28 -> 1 | Q28: =SUM(R28,T28) -> 4.0921507e+09 | R28: =SUMIFS('B0200'!L:L,'B0200'!DA:DA,"KO") -> 0 | S28: =R28/Q28 -> 0 | T28: =SUMIFS('B0200'!L:L,'B0200'!DA:DA,"OK") -> 4.0921507e+09 | U28: =T28/Q28 -> 1
B29: v_1_0025 | C29: B02.00 | D29: 0300 | E29: Covered portion of eligible deposits | F29: Numeric: 2 decimals | G29: X | I29: Test for missing values. | J29: Rule applicable only if c0280 = "TRUE" or c0290 = "TRUE". | K29: Missing value. The field must be reported for eligible deposits. If the value is zero, "0" should be entered. | L29: =SUM(M29,O29) -> 8 | M29: =COUNTIF('B0200'!DB:DB,"KO") -> 0 | N29: =M29/L29 -> 0 | O29: =COUNTIF('B0200'!DB:DB,"OK") -> 8 | P29: =O29/L29 -> 1 | Q29: =SUM(R29,T29) -> 4.0921507e+09 | R29: =SUMIFS('B0200'!L:L,'B0200'!DB:DB,"KO") -> 0 | S29: =R29/Q29 -> 0 | T29: =SUMIFS('B0200'!L:L,'B0200'!DB:DB,"OK") -> 4.0921507e+09 | U29: =T29/Q29 -> 1
B30: v_1_0026 | C30: B02.00 | D30: 0310 | E30: Secured/Unsecured | F30: String: Drop-down | G30: X | I30: Test for missing values. | K30: Missing value. The field must be reported. | L30: =SUM(M30,O30) -> 8 | M30: =COUNTIF('B0200'!DC:DC,"KO") -> 0 | N30: =M30/L30 -> 0 | O30: =COUNTIF('B0200'!DC:DC,"OK") -> 8 | P30: =O30/L30 -> 1 | Q30: =SUM(R30,T30) -> 4.0921507e+09 | R30: =SUMIFS('B0200'!L:L,'B0200'!DC:DC,"KO") -> 0 | S30: =R30/Q30 -> 0 | T30: =SUMIFS('B0200'!L:L,'B0200'!DC:DC,"OK") -> 4.0921507e+09 | U30: =T30/Q30 -> 1
B31: v_1_0027 | C31: B02.00 | D31: 0320 | E31: Amount of pledge, lien or collateral based on the current internal valuation | F31: Numeric: 2 decimals | G31: X | I31: Test for missing values. | J31: Rule applicable only if c0310 = "Secured" | K31: Missing value. The field must be reported for secured products. If the value is zero, "0" should be entered. | L31: =SUM(M31,O31) -> 8 | M31: =COUNTIF('B0200'!DD:DD,"KO") -> 0 | N31: =M31/L31 -> 0 | O31: =COUNTIF('B0200'!DD:DD,"OK") -> 8 | P31: =O31/L31 -> 1 | Q31: =SUM(R31,T31) -> 4.0921507e+09 | R31: =SUMIFS('B0200'!L:L,'B0200'!DD:DD,"KO") -> 0 | S31: =R31/Q31 -> 0 | T31: =SUMIFS('B0200'!L:L,'B0200'!DD:DD,"OK") -> 4.0921507e+09 | U31: =T31/Q31 -> 1
B32: v_1_0028 | C32: B02.00 | D32: 0330 | E32: Amount of the uncollateralized part | F32: Numeric: 2 decimals | G32: X | I32: Test for missing values. | J32: Rule applicable only if c0310 = "Secured" | K32: Missing value. The field must be reported for secured products. | L32: =SUM(M32,O32) -> 8 | M32: =COUNTIF('B0200'!DE:DE,"KO") -> 0 | N32: =M32/L32 -> 0 | O32: =COUNTIF('B0200'!DE:DE,"OK") -> 8 | P32: =O32/L32 -> 1 | Q32: =SUM(R32,T32) -> 4.0921507e+09 | R32: =SUMIFS('B0200'!L:L,'B0200'!DE:DE,"KO") -> 0 | S32: =R32/Q32 -> 0 | T32: =SUMIFS('B0200'!L:L,'B0200'!DE:DE,"OK") -> 4.0921507e+09 | U32: =T32/Q32 -> 1
B33: v_1_0029 | C33: B02.00 | D33: 0350 | E33: Type of the collateral | F33: String: Drop-down | G33: X | I33: Test for missing values. | J33: Rule applicable only if c0310 = "Secured" | K33: Missing value. The field must be reported for secured products. | L33: =SUM(M33,O33) -> 8 | M33: =COUNTIF('B0200'!DF:DF,"KO") -> 0 | N33: =M33/L33 -> 0 | O33: =COUNTIF('B0200'!DF:DF,"OK") -> 8 | P33: =O33/L33 -> 1 | Q33: =SUM(R33,T33) -> 4.0921507e+09 | R33: =SUMIFS('B0200'!L:L,'B0200'!DF:DF,"KO") -> 0 | S33: =R33/Q33 -> 0 | T33: =SUMIFS('B0200'!L:L,'B0200'!DF:DF,"OK") -> 4.0921507e+09 | U33: =T33/Q33 -> 1
B34: v_1_0030 | C34: B02.00 | D34: 0351 | E34: Type of the collateral (if other) | F34: String: Free text | G34: X | I34: Test for missing values. | J34: Rule applicable only if c0350 = "Other" | K34: Missing value (warning). The field should be reported if c0350 = "Other". | L34: =SUM(M34,O34) -> 8 | M34: =COUNTIF('B0200'!DG:DG,"KO") -> 0 | N34: =M34/L34 -> 0 | O34: =COUNTIF('B0200'!DG:DG,"OK") -> 8 | P34: =O34/L34 -> 1 | Q34: =SUM(R34,T34) -> 4.0921507e+09 | R34: =SUMIFS('B0200'!L:L,'B0200'!DG:DG,"KO") -> 0 | S34: =R34/Q34 -> 0 | T34: =SUMIFS('B0200'!L:L,'B0200'!DG:DG,"OK") -> 4.0921507e+09 | U34: =T34/Q34 -> 1
B35: v_1_0031 | C35: B02.00 | D35: 0370 | E35: Denomination / Nominal value per security in EUR | F35: Numeric: 2 decimals | G35: X | I35: Test for missing values. | J35: Rule applicable only if c0040 = "ISIN" and c0360 = "Nominal" | K35: Missing value. The field must be reported for securities with trading-method = "Nominal". | L35: =SUM(M35,O35) -> 8 | M35: =COUNTIF('B0200'!DH:DH,"KO") -> 0 | N35: =M35/L35 -> 0 | O35: =COUNTIF('B0200'!DH:DH,"OK") -> 8 | P35: =O35/L35 -> 1 | Q35: =SUM(R35,T35) -> 4.0921507e+09 | R35: =SUMIFS('B0200'!L:L,'B0200'!DH:DH,"KO") -> 0 | S35: =R35/Q35 -> 0 | T35: =SUMIFS('B0200'!L:L,'B0200'!DH:DH,"OK") -> 4.0921507e+09 | U35: =T35/Q35 -> 1
B36: v_1_0032 | C36: B02.00 | D36: 0370 | E36: Denomination / Nominal value per security in EUR | F36: Numeric: 2 decimals | H36: X | I36: Test for missing values. | J36: Rule applicable only if c0040 = "ISIN" and c0360 = "Unit" | K36: Missing value (warning only). The field should be reported for securities with trading-method = "Unit" if the information exists. | L36: =SUM(M36,O36) -> 8 | M36: =COUNTIF('B0200'!DI:DI,"KO") -> 0 | N36: =M36/L36 -> 0 | O36: =COUNTIF('B0200'!DI:DI,"OK") -> 8 | P36: =O36/L36 -> 1 | Q36: =SUM(R36,T36) -> 4.0921507e+09 | R36: =SUMIFS('B0200'!L:L,'B0200'!DI:DI,"KO") -> 0 | S36: =R36/Q36 -> 0 | T36: =SUMIFS('B0200'!L:L,'B0200'!DI:DI,"OK") -> 4.0921507e+09 | U36: =T36/Q36 -> 1
B37: v_1_0033 | C37: B02.00 | D37: 0390 | E37: Number of securities outstanding not held by the reporting entity | F37: Numeric: Integer | G37: X | I37: Test for missing values. | J37: Rule applicable only if c0040 = "ISIN". | K37: Missing value. The field must be reported when c0040 = "ISIN". If the value is zero, "0" must be entered. | L37: =SUM(M37,O37) -> 8 | M37: =COUNTIF('B0200'!DJ:DJ,"KO") -> 0 | N37: =M37/L37 -> 0 | O37: =COUNTIF('B0200'!DJ:DJ,"OK") -> 8 | P37: =O37/L37 -> 1 | Q37: =SUM(R37,T37) -> 4.0921507e+09 | R37: =SUMIFS('B0200'!L:L,'B0200'!DJ:DJ,"KO") -> 0 | S37: =R37/Q37 -> 0 | T37: =SUMIFS('B0200'!L:L,'B0200'!DJ:DJ,"OK") -> 4.0921507e+09 | U37: =T37/Q37 -> 1
B38: v_1_0034 | C38: B02.00 | D38: 0391 | E38: Number of securities outstanding held by the reporting entity | F38: Numeric: Integer | G38: X | I38: Test for missing values. | J38: Rule applicable only if c0040 = "ISIN". | K38: Missing value. The field must be reported for securities. If the value is zero, "0" must be entered. | L38: =SUM(M38,O38) -> 8 | M38: =COUNTIF('B0200'!DK:DK,"KO") -> 0 | N38: =M38/L38 -> 0 | O38: =COUNTIF('B0200'!DK:DK,"OK") -> 8 | P38: =O38/L38 -> 1 | Q38: =SUM(R38,T38) -> 4.0921507e+09 | R38: =SUMIFS('B0200'!L:L,'B0200'!DK:DK,"KO") -> 0 | S38: =R38/Q38 -> 0 | T38: =SUMIFS('B0200'!L:L,'B0200'!DK:DK,"OK") -> 4.0921507e+09 | U38: =T38/Q38 -> 1
B39: v_1_0035 | C39: B02.00 | D39: 0400 | E39: Accrued interest per security | F39: Numeric: 4 decimals | G39: X | I39: Test for missing values. | J39: Rule applicable if c0040 = "ISIN", c0250 = ("Non-Structured/Vanilla" OR "Other non-standard terms) AND c0240 != "ZCB issued at discount" | K39: Missing value. The field must be reported for non-structured securities that are not zero coupon bonds issued at discount. | L39: =SUM(M39,O39) -> 8 | M39: =COUNTIF('B0200'!DL:DL,"KO") -> 0 | N39: =M39/L39 -> 0 | O39: =COUNTIF('B0200'!DL:DL,"OK") -> 8 | P39: =O39/L39 -> 1 | Q39: =SUM(R39,T39) -> 4.0921507e+09 | R39: =SUMIFS('B0200'!L:L,'B0200'!DL:DL,"KO") -> 0 | S39: =R39/Q39 -> 0 | T39: =SUMIFS('B0200'!L:L,'B0200'!DL:DL,"OK") -> 4.0921507e+09 | U39: =T39/Q39 -> 1
B40: v_1_0036 | C40: B02.00 | D40: 0400 | E40: Accrued interest per security | F40: Numeric: 4 decimals | H40: X | I40: Test for missing values. | J40: Rule applicable if c0040 = "ISIN", c0250 != ("Structured" OR "Only structured coupon") | K40: Missing value (warning only). This field must be reported for structured securities if the information exists. | L40: =SUM(M40,O40) -> 8 | M40: =COUNTIF('B0200'!DM:DM,"KO") -> 0 | N40: =M40/L40 -> 0 | O40: =COUNTIF('B0200'!DM:DM,"OK") -> 8 | P40: =O40/L40 -> 1 | Q40: =SUM(R40,T40) -> 4.0921507e+09 | R40: =SUMIFS('B0200'!L:L,'B0200'!DM:DM,"KO") -> 0 | S40: =R40/Q40 -> 0 | T40: =SUMIFS('B0200'!L:L,'B0200'!DM:DM,"OK") -> 4.0921507e+09 | U40: =T40/Q40 -> 1
B41: v_1_0037 | C41: B02.00 | D41: 0610 | E41: Carrying amount IFRS | F41: Numeric: 2 decimals | H41: X | I41: Test for missing values. | K41: Missing value (warning only). The field must be reported if the information exists, i.e. the entity reports in IFRS. | L41: =SUM(M41,O41) -> 8 | M41: =COUNTIF('B0200'!DN:DN,"KO") -> 0 | N41: =M41/L41 -> 0 | O41: =COUNTIF('B0200'!DN:DN,"OK") -> 8 | P41: =O41/L41 -> 1 | Q41: =SUM(R41,T41) -> 4.0921507e+09 | R41: =SUMIFS('B0200'!L:L,'B0200'!DN:DN,"KO") -> 0 | S41: =R41/Q41 -> 0 | T41: =SUMIFS('B0200'!L:L,'B0200'!DN:DN,"OK") -> 4.0921507e+09 | U41: =T41/Q41 -> 1
B42: v_1_0038 | C42: B02.00 | D42: 5000 | E42: Instrument/liability is issued to or bought by an existing shareholder that is not part of the same resolution group | F42: String: TRUE / FALSE boolean | G42: X | I42: Test for missing values. | J42: if {B99.00;c0060} = "Non-Resolution Entity" | K42: Missing value. The field must be reported for Non-Resolution Entities. | L42: =SUM(M42,O42) -> 8 | M42: =COUNTIF('B0200'!DO:DO,"KO") -> 0 | N42: =M42/L42 -> 0 | O42: =COUNTIF('B0200'!DO:DO,"OK") -> 8 | P42: =O42/L42 -> 1 | Q42: =SUM(R42,T42) -> 4.0921507e+09 | R42: =SUMIFS('B0200'!L:L,'B0200'!DO:DO,"KO") -> 0 | S42: =R42/Q42 -> 0 | T42: =SUMIFS('B0200'!L:L,'B0200'!DO:DO,"OK") -> 4.0921507e+09 | U42: =T42/Q42 -> 1
B43: v_1_0039 | C43: B02.00 | D43: 5010 | E43: Instrument/liability meets the requirements of Art. 21(7a) SRMR | F43: String: TRUE / FALSE boolean | G43: X | I43: Test for missing values. | J43: if {B99.00;c0060} = "Non-Resolution Entity" | K43: Missing value. The field must be reported for Non-Resolution Entities. | L43: =SUM(M43,O43) -> 8 | M43: =COUNTIF('B0200'!DP:DP,"KO") -> 0 | N43: =M43/L43 -> 0 | O43: =COUNTIF('B0200'!DP:DP,"OK") -> 8 | P43: =O43/L43 -> 1 | Q43: =SUM(R43,T43) -> 4.0921507e+09 | R43: =SUMIFS('B0200'!L:L,'B0200'!DP:DP,"KO") -> 0 | S43: =R43/Q43 -> 0 | T43: =SUMIFS('B0200'!L:L,'B0200'!DP:DP,"OK") -> 4.0921507e+09 | U43: =T43/Q43 -> 1
B44: v_1_0056 | C44: B90.00 | D44: 0030 | E44: Counterparty within the resolution group | F44: String: Drop-down | G44: X | I44: Test for missing values. | K44: Missing value. The field must be reported. | L44: =SUM(M44,O44) -> 9 | M44: =COUNTIF('B9000'!L:L,"KO") -> 0 | N44: =M44/L44 -> 0 | O44: =COUNTIF('B9000'!L:L,"OK") -> 9 | P44: =O44/L44 -> 1 | Q44: =SUM(R44,T44) -> 4.0875867e+09 | R44: =SUMIFS('B9000'!K:K,'B9000'!L:L,"KO") -> 0 | S44: =R44/Q44 -> 0 | T44: =SUMIFS('B9000'!K:K,'B9000'!L:L,"OK") -> 4.0875867e+09 | U44: =T44/Q44 -> 1

Sheet V_Level 2
B1: Level 2 Validation Rules: internal consistency checks.
M2: KO | O2: OK | R2: KO | T2: OK
A3: 0001 | B3: Check ID | C3: Tab | D3: Data point (Row/Column) | E3: Data point (Label) | F3: Data point type | G3: High severity (i.e the validation rule should in general not be breached) | H3: Warning only (i.e. the validation rule can be breached in certain cases) | I3: Type of test | J3: Prerequisites | K3: Explanation | L3: Total Registros | M3: Registros | N3: Porcentaje | O3: Registros | P3: Porcentaje | Q3: Amount | R3: Total | S3: Porcentaje | T3: Total | U3: Porcentaje
A4: 0003 | B4: =CONCATENATE("v_2_",A3) -> v_2_0001 | C4: B02.00 | D4: 0030 | E4: Unique identification number (known to the counterparty) | F4: String: Free text | G4: X | I4: The field must have the characteristics of an ISIN, e.g., max. 12 characters and start with 2 letters signifying the ISO country code. | J4: c0040 = "ISIN" | K4: If the ID is an ISIN (c0030 = "ISIN"), then the ID reported in c0020 must have the characteristics of an ISIN, e.g. 12 characters and start with 2 letters signifying the ISO country code. | L4: =SUM(M4,O4) -> 8 | M4: =COUNTIF('B0200'!DQ:DQ,"KO") -> 0 | N4: =M4/L4 -> 0 | O4: =COUNTIF('B0200'!DQ:DQ,"OK") -> 8 | P4: =O4/L4 -> 1 | Q4: =SUM(R4,T4) -> 4.0921507e+09 | R4: =SUMIFS('B0200'!L:L,'B0200'!DQ:DQ,"KO") -> 0 | S4: =R4/Q4 -> 0 | T4: =SUMIFS('B0200'!L:L,'B0200'!DQ:DQ,"OK") -> 4.0921507e+09 | U4: =T4/Q4 -> 1
A5: 0004 | B5: =CONCATENATE("v_2_",A4) -> v_2_0003 | C5: B02.00 | D5: 0070 | E5: Contract Currency | F5: String: 3-letters ISO 4217 | G5: X | I5: Check if the reported field respect the 3-letters ISO 4217 code. | J5: c0020 ≠ (NCNP OR NCBP) | K5: Currencies must be reported using the 3-letters ISO 4217 code. | L5: =SUM(M5,O5) -> 8 | M5: =COUNTIF('B0200'!DR:DR,"KO") -> 0 | N5: =M5/L5 -> 0 | O5: =COUNTIF('B0200'!DR:DR,"OK") -> 8 | P5: =O5/L5 -> 1 | Q5: =SUM(R5,T5) -> 4.0921507e+09 | R5: =SUMIFS('B0200'!L:L,'B0200'!DR:DR,"KO") -> 0 | S5: =R5/Q5 -> 0 | T5: =SUMIFS('B0200'!L:L,'B0200'!DR:DR,"OK") -> 4.0921507e+09 | U5: =T5/Q5 -> 1
A6: 0005 | B6: =CONCATENATE("v_2_",A5) -> v_2_0004 | C6: B02.00 | D6: 0080 | E6: Outstanding principal amount | F6: Numeric: 2 decimals | H6: X | I6: Check if the reported field is higher than 0. | K6: The reported amount must in general be positive. | L6: =SUM(M6,O6) -> 8 | M6: =COUNTIF('B0200'!DS:DS,"KO") -> 0 | N6: =M6/L6 -> 0 | O6: =COUNTIF('B0200'!DS:DS,"OK") -> 8 | P6: =O6/L6 -> 1 | Q6: =SUM(R6,T6) -> 4.0921507e+09 | R6: =SUMIFS('B0200'!L:L,'B0200'!DS:DS,"KO") -> 0 | S6: =R6/Q6 -> 0 | T6: =SUMIFS('B0200'!L:L,'B0200'!DS:DS,"OK") -> 4.0921507e+09 | U6: =T6/Q6 -> 1
A7: 0006 | B7: =CONCATENATE("v_2_",A6) -> v_2_0005 | C7: B02.00 | D7: 0090 | E7: Portion of instrument or liability held by the reporting entity | F7: Numeric: 2 decimals | G7: X | I7: Check if the reported field is higher than or equal 0. | J7: c0040 = "ISIN" | K7: The reported amount must be positive or zero. | L7: =SUM(M7,O7) -> 8 | M7: =COUNTIF('B0200'!DT:DT,"KO") -> 0 | N7: =M7/L7 -> 0 | O7: =COUNTIF('B0200'!DT:DT,"OK") -> 8 | P7: =O7/L7 -> 1 | Q7: =SUM(R7,T7) -> 4.0921507e+09 | R7: =SUMIFS('B0200'!L:L,'B0200'!DT:DT,"KO") -> 0 | S7: =R7/Q7 -> 0 | T7: =SUMIFS('B0200'!L:L,'B0200'!DT:DT,"OK") -> 4.0921507e+09 | U7: =T7/Q7 -> 1
A8: 0007 | B8: =CONCATENATE("v_2_",A7) -> v_2_0006 | C8: B02.00 | D8: 0100 | E8: Accrued interest | F8: Numeric: 2 decimals | H8: X | I8: Check if the reported field is higher than or equal 0. | K8: The reported amount should be positive or zero. However, negative accrued interests are in principle allowed, if duly justified by the reporting entity. | L8: =SUM(M8,O8) -> 8 | M8: =COUNTIF('B0200'!DU:DU,"KO") -> 0 | N8: =M8/L8 -> 0 | O8: =COUNTIF('B0200'!DU:DU,"OK") -> 8 | P8: =O8/L8 -> 1 | Q8: =SUM(R8,T8) -> 4.0921507e+09 | R8: =SUMIFS('B0200'!L:L,'B0200'!DU:DU,"KO") -> 0 | S8: =R8/Q8 -> 0 | T8: =SUMIFS('B0200'!L:L,'B0200'!DU:DU,"OK") -> 4.0921507e+09 | U8: =T8/Q8 -> 1
A9: 0008 | B9: =CONCATENATE("v_2_",A8) -> v_2_0007 | C9: B02.00 | D9: 0110 | E9: Applicable fees and charges | F9: Numeric: 2 decimals | H9: X | I9: Check if the reported field is higher than or equal 0. | K9: The reported amount should be in general positive or zero. | L9: =SUM(M9,O9) -> 8 | M9: =COUNTIF('B0200'!DV:DV,"KO") -> 0 | N9: =M9/L9 -> 0 | O9: =COUNTIF('B0200'!DV:DV,"OK") -> 8 | P9: =O9/L9 -> 1 | Q9: =SUM(R9,T9) -> 4.0921507e+09 | R9: =SUMIFS('B0200'!L:L,'B0200'!DV:DV,"KO") -> 0 | S9: =R9/Q9 -> 0 | T9: =SUMIFS('B0200'!L:L,'B0200'!DV:DV,"OK") -> 4.0921507e+09 | U9: =T9/Q9 -> 1
A10: 0009 | B10: =CONCATENATE("v_2_",A9) -> v_2_0008 | C10: B02.00 | D10: 0120 | E10: Outstanding amount | F10: Numeric: 2 decimals | G10: X | I10: Check if the reported field is higher than 0. | K10: The reported amount should be positive. | L10: =SUM(M10,O10) -> 8 | M10: =COUNTIF('B0200'!DW:DW,"KO") -> 0 | N10: =M10/L10 -> 0 | O10: =COUNTIF('B0200'!DW:DW,"OK") -> 8 | P10: =O10/L10 -> 1 | Q10: =SUM(R10,T10) -> 4.0921507e+09 | R10: =SUMIFS('B0200'!L:L,'B0200'!DW:DW,"KO") -> 0 | S10: =R10/Q10 -> 0 | T10: =SUMIFS('B0200'!L:L,'B0200'!DW:DW,"OK") -> 4.0921507e+09 | U10: =T10/Q10 -> 1
A11: 0011 | B11: =CONCATENATE("v_2_",A10) -> v_2_0009 | C11: B02.00 | D11: 0120 | E11: Outstanding amount | F11: Numeric: 2 decimals | G11: X | I11: Check if the reported field is equal to c0080 + c0100 + c0110. | K11: The reported amount should be equal to: c0080 + c0100 + c0110. | L11: =SUM(M11,O11) -> 8 | M11: =COUNTIF('B0200'!DX:DX,"KO") -> 0 | N11: =M11/L11 -> 0 | O11: =COUNTIF('B0200'!DX:DX,"OK") -> 8 | P11: =O11/L11 -> 1 | Q11: =SUM(R11,T11) -> 4.0921507e+09 | R11: =SUMIFS('B0200'!L:L,'B0200'!DX:DX,"KO") -> 0 | S11: =R11/Q11 -> 0 | T11: =SUMIFS('B0200'!L:L,'B0200'!DX:DX,"OK") -> 4.0921507e+09 | U11: =T11/Q11 -> 1
A12: 0012 | B12: =CONCATENATE("v_2_",A11) -> v_2_0011 | C12: B02.00 | D12: 0130 | E12: Relevant amount for Bail-in/WDC | F12: Numeric: 2 decimals | G12: X | I12: Check if the reported field is equal to of: max{0, c0120 - c0300 - c0320}. | J12: c0250 = ("Non-structured/Vanilla" OR "Other non-standard terms") & c0240 != "ZCB issued at discount" | K12: The reported amount should be equal to: c0120 - c0300 - c0320, besides for Zero Coupon Bonds for which specific provisions may apply. | L12: =SUM(M12,O12) -> 8 | M12: =COUNTIF('B0200'!DY:DY,"KO") -> 0 | N12: =M12/L12 -> 0 | O12: =COUNTIF('B0200'!DY:DY,"OK") -> 8 | P12: =O12/L12 -> 1 | Q12: =SUM(R12,T12) -> 4.0921507e+09 | R12: =SUMIFS('B0200'!L:L,'B0200'!DY:DY,"KO") -> 0 | S12: =R12/Q12 -> 0 | T12: =SUMIFS('B0200'!L:L,'B0200'!DY:DY,"OK") -> 4.0921507e+09 | U12: =T12/Q12 -> 1
A13: 0013 | B13: =CONCATENATE("v_2_",A12) -> v_2_0012 | C13: B02.00 | D13: 0130 | E13: Relevant amount for Bail-in/WDC | F13: Numeric: 2 decimals | G13: X | I13: Check if the reported field is either equal to max(0, c0270 - c0300 - c0320) OR equal to max(0, c0120 - c0300 - c0320) | J13: c0250 = ( "Structured" OR "Structured coupon only") | K13: For structured products, the reported amount should be equal to: (c0270 - c0300 - c0320) if the fair value is used to support the determination of the relevant amount for bail-in, OR (c0120 - c0300 - c0320) if not. | L13: =SUM(M13,O13) -> 8 | M13: =COUNTIF('B0200'!DZ:DZ,"KO") -> 0 | N13: =M13/L13 -> 0 | O13: =COUNTIF('B0200'!DZ:DZ,"OK") -> 8 | P13: =O13/L13 -> 1 | Q13: =SUM(R13,T13) -> 4.0921507e+09 | R13: =SUMIFS('B0200'!L:L,'B0200'!DZ:DZ,"KO") -> 0 | S13: =R13/Q13 -> 0 | T13: =SUMIFS('B0200'!L:L,'B0200'!DZ:DZ,"OK") -> 4.0921507e+09 | U13: =T13/Q13 -> 1
A14: 0014 | B14: =CONCATENATE("v_2_",A13) -> v_2_0013 | C14: B02.00 | D14: 0140 | E14: Nature of the liability | F14: String: Drop-down | G14: X | I14: Drop down values must be respected. | K14: The drop down values must be respected. | L14: =SUM(M14,O14) -> 8 | M14: =COUNTIF('B0200'!EA:EA,"KO") -> 0 | N14: =M14/L14 -> 0 | O14: =COUNTIF('B0200'!EA:EA,"OK") -> 8 | P14: =O14/L14 -> 1 | Q14: =SUM(R14,T14) -> 4.0921507e+09 | R14: =SUMIFS('B0200'!L:L,'B0200'!EA:EA,"KO") -> 0 | S14: =R14/Q14 -> 0 | T14: =SUMIFS('B0200'!L:L,'B0200'!EA:EA,"OK") -> 4.0921507e+09 | U14: =T14/Q14 -> 1
A15: 0015 | B15: =CONCATENATE("v_2_",A14) -> v_2_0014 | C15: B02.00 | D15: 0160 | E15: Insolvency ranking | F15: Numeric: Integer | G15: X | I15: Numeric integer values from 1 onwards must be reported. | K15: Numeric values from 1 onwards must be reported. | L15: =SUM(M15,O15) -> 8 | M15: =COUNTIF('B0200'!EB:EB,"KO") -> 0 | N15: =M15/L15 -> 0 | O15: =COUNTIF('B0200'!EB:EB,"OK") -> 8 | P15: =O15/L15 -> 1 | Q15: =SUM(R15,T15) -> 4.0921507e+09 | R15: =SUMIFS('B0200'!L:L,'B0200'!EB:EB,"KO") -> 0 | S15: =R15/Q15 -> 0 | T15: =SUMIFS('B0200'!L:L,'B0200'!EB:EB,"OK") -> 4.0921507e+09 | U15: =T15/Q15 -> 1
A16: 0016 | B16: =CONCATENATE("v_2_",A15) -> v_2_0015 | C16: B02.00 | D16: 0170 | E16: Date of issuance | F16: Date: yyyy-mm-dd | G16: X | I16: The reported value must be a date (yyyy-mm-gg). | J16: (c0020 ≠ "NCNP" OR "NCBP") | K16: The reported value must be a date (yyyy-mm-gg). | L16: =SUM(M16,O16) -> 8 | M16: =COUNTIF('B0200'!EC:EC,"KO") -> 0 | N16: =M16/L16 -> 0 | O16: =COUNTIF('B0200'!EC:EC,"OK") -> 8 | P16: =O16/L16 -> 1 | Q16: =SUM(R16,T16) -> 4.0921507e+09 | R16: =SUMIFS('B0200'!L:L,'B0200'!EC:EC,"KO") -> 0 | S16: =R16/Q16 -> 0 | T16: =SUMIFS('B0200'!L:L,'B0200'!EC:EC,"OK") -> 4.0921507e+09 | U16: =T16/Q16 -> 1
A17: 0017 | B17: =CONCATENATE("v_2_",A16) -> v_2_0016 | C17: B02.00 | D17: 0170 | E17: Date of issuance | F17: Date: yyyy-mm-dd | G17: X | I17: The reported value must be before the Date of the next (partial) redemption payment (c0190) and the earliest redemption date (c0200). | J17: (c0190 or c0200) are reported & (c0020 ≠ "NCNP" OR "NCBP") | K17: The reported value must be before the Date of the next (partial) redemption payment (c0190) and the earliest redemption date (c0200). | L17: =SUM(M17,O17) -> 8 | M17: =COUNTIF('B0200'!ED:ED,"KO") -> 0 | N17: =M17/L17 -> 0 | O17: =COUNTIF('B0200'!ED:ED,"OK") -> 8 | P17: =O17/L17 -> 1 | Q17: =SUM(R17,T17) -> 4.0921507e+09 | R17: =SUMIFS('B0200'!L:L,'B0200'!ED:ED,"KO") -> 0 | S17: =R17/Q17 -> 0 | T17: =SUMIFS('B0200'!L:L,'B0200'!ED:ED,"OK") -> 4.0921507e+09 | U17: =T17/Q17 -> 1
A18: 0018 | B18: =CONCATENATE("v_2_",A17) -> v_2_0017 | C18: B02.00 | D18: 0180 | E18: Date of the next interest payment | F18: Date: yyyy-mm-dd | G18: X | I18: The reported value must be a date (yyyy-mm-gg). | J18: (c0020 ≠ "NCNP" OR "NCBP") | K18: The reported value must be a date (yyyy-mm-gg). | L18: =SUM(M18,O18) -> 8 | M18: =COUNTIF('B0200'!EE:EE,"KO") -> 0 | N18: =M18/L18 -> 0 | O18: =COUNTIF('B0200'!EE:EE,"OK") -> 8 | P18: =O18/L18 -> 1 | Q18: =SUM(R18,T18) -> 4.0921507e+09 | R18: =SUMIFS('B0200'!L:L,'B0200'!EE:EE,"KO") -> 0 | S18: =R18/Q18 -> 0 | T18: =SUMIFS('B0200'!L:L,'B0200'!EE:EE,"OK") -> 4.0921507e+09 | U18: =T18/Q18 -> 1
A19: 0019 | B19: =CONCATENATE("v_2_",A18) -> v_2_0018 | C19: B02.00 | D19: 0180 | E19: Date of the next interest payment | F19: Date: yyyy-mm-dd | G19: X | I19: The reported value must be after the reference date reported in B99.00 (c0070). | J19: {B99.00;c0070} is reported & (c0020 ≠ "NCNP" OR "NCBP") | K19: The reported value must be after the reference date reported in B99.00 (c0070). | L19: =SUM(M19,O19) -> 8 | M19: =COUNTIF('B0200'!EF:EF,"KO") -> 0 | N19: =M19/L19 -> 0 | O19: =COUNTIF('B0200'!EF:EF,"OK") -> 8 | P19: =O19/L19 -> 1 | Q19: =SUM(R19,T19) -> 4.0921507e+09 | R19: =SUMIFS('B0200'!L:L,'B0200'!EF:EF,"KO") -> 0 | S19: =R19/Q19 -> 0 | T19: =SUMIFS('B0200'!L:L,'B0200'!EF:EF,"OK") -> 4.0921507e+09 | U19: =T19/Q19 -> 1
A20: 0020 | B20: =CONCATENATE("v_2_",A19) -> v_2_0019 | C20: B02.00 | D20: 0200 | E20: Earliest redemption date | F20: Date: yyyy-mm-dd | G20: X | I20: The reported value must be a date (yyyy-mm-gg). | J20: (c0020 ≠ "NCNP" OR "NCBP") | K20: The reported value must be a date (yyyy-mm-gg). | L20: =SUM(M20,O20) -> 8 | M20: =COUNTIF('B0200'!EG:EG,"KO") -> 0 | N20: =M20/L20 -> 0 | O20: =COUNTIF('B0200'!EG:EG,"OK") -> 8 | P20: =O20/L20 -> 1 | Q20: =SUM(R20,T20) -> 4.0921507e+09 | R20: =SUMIFS('B0200'!L:L,'B0200'!EG:EG,"KO") -> 0 | S20: =R20/Q20 -> 0 | T20: =SUMIFS('B0200'!L:L,'B0200'!EG:EG,"OK") -> 4.0921507e+09 | U20: =T20/Q20 -> 1
A21: 0021 | B21: =CONCATENATE("v_2_",A20) -> v_2_0020 | C21: B02.00 | D21: 0200 | E21: Earliest redemption date | F21: Date: yyyy-mm-dd | G21: X | I21: The reported value must be after the reference date reported in B99.00 (c0070). | J21: {B99.00;c0070} is reported & (c0020 ≠ "NCNP" OR "NCBP") | K21: The reported value must be after the reference date reported in B99.00 (c0070). | L21: =SUM(M21,O21) -> 8 | M21: =COUNTIF('B0200'!EH:EH,"KO") -> 0 | N21: =M21/L21 -> 0 | O21: =COUNTIF('B0200'!EH:EH,"OK") -> 8 | P21: =O21/L21 -> 1 | Q21: =SUM(R21,T21) -> 4.0921507e+09 | R21: =SUMIFS('B0200'!L:L,'B0200'!EH:EH,"KO") -> 0 | S21: =R21/Q21 -> 0 | T21: =SUMIFS('B0200'!L:L,'B0200'!EH:EH,"OK") -> 4.0921507e+09 | U21: =T21/Q21 -> 1
A22: 0022 | B22: =CONCATENATE("v_2_",A21) -> v_2_0021 | C22: B02.00 | D22: 0210 | E22: Legal maturity | F22: Date: yyyy-mm-dd | G22: X | I22: The reported value must be a date (yyyy-mm-gg). | J22: (c0020 ≠ "NCNP" OR "NCBP") | K22: The reported value must be a date (yyyy-mm-gg). | L22: =SUM(M22,O22) -> 8 | M22: =COUNTIF('B0200'!EI:EI,"KO") -> 0 | N22: =M22/L22 -> 0 | O22: =COUNTIF('B0200'!EI:EI,"OK") -> 8 | P22: =O22/L22 -> 1 | Q22: =SUM(R22,T22) -> 4.0921507e+09 | R22: =SUMIFS('B0200'!L:L,'B0200'!EI:EI,"KO") -> 0 | S22: =R22/Q22 -> 0 | T22: =SUMIFS('B0200'!L:L,'B0200'!EI:EI,"OK") -> 4.0921507e+09 | U22: =T22/Q22 -> 1
A23: 0023 | B23: =CONCATENATE("v_2_",A22) -> v_2_0022 | C23: B02.00 | D23: 0210 | E23: Legal maturity | F23: Date: yyyy-mm-dd | G23: X | I23: The reported value must be after the reference date reported in B99.00 (c0070). | J23: {B99.00;c0070} is reported & (c0020 ≠ "NCNP" OR "NCBP") | K23: The reported value must be after the reference date reported in B99.00 (c0070). | L23: =SUM(M23,O23) -> 8 | M23: =COUNTIF('B0200'!EJ:EJ,"KO") -> 0 | N23: =M23/L23 -> 0 | O23: =COUNTIF('B0200'!EJ:EJ,"OK") -> 8 | P23: =O23/L23 -> 1 | Q23: =SUM(R23,T23) -> 4.0921507e+09 | R23: =SUMIFS('B0200'!L:L,'B0200'!EJ:EJ,"KO") -> 0 | S23: =R23/Q23 -> 0 | T23: =SUMIFS('B0200'!L:L,'B0200'!EJ:EJ,"OK") -> 4.0921507e+09 | U23: =T23/Q23 -> 1
A24: 0024 | B24: =CONCATENATE("v_2_",A23) -> v_2_0023 | C24: B02.00 | D24: 0220 | E24: Governing law | F24: String: ISO 3166-1 alpha 2 / ISO 3166-2 | G24: X | I24: Check if the reported field respects the ISO 3166-1 alpha-2 code or 3166-2 | J24: (c0020 ≠ "NCNP" OR "NCBP") | K24: Governing law must be reported using the ISO 3166-1 alpha-2 code. | L24: =SUM(M24,O24) -> 8 | M24: =COUNTIF('B0200'!EK:EK,"KO") -> 0 | N24: =M24/L24 -> 0 | O24: =COUNTIF('B0200'!EK:EK,"OK") -> 8 | P24: =O24/L24 -> 1 | Q24: =SUM(R24,T24) -> 4.0921507e+09 | R24: =SUMIFS('B0200'!L:L,'B0200'!EK:EK,"KO") -> 0 | S24: =R24/Q24 -> 0 | T24: =SUMIFS('B0200'!L:L,'B0200'!EK:EK,"OK") -> 4.0921507e+09 | U24: =T24/Q24 -> 1
A25: 0025 | B25: =CONCATENATE("v_2_",A24) -> v_2_0024 | C25: B02.00 | D25: 0230 | E25: Bail-in recognition clause | F25: String: Drop-down | G25: X | I25: Drop down values must be respected. | J25: (c0020 ≠ "NCNP" OR "NCBP") | K25: The drop down values must be respected. | L25: =SUM(M25,O25) -> 8 | M25: =COUNTIF('B0200'!EL:EL,"KO") -> 0 | N25: =M25/L25 -> 0 | O25: =COUNTIF('B0200'!EL:EL,"OK") -> 8 | P25: =O25/L25 -> 1 | Q25: =SUM(R25,T25) -> 4.0921507e+09 | R25: =SUMIFS('B0200'!L:L,'B0200'!EL:EL,"KO") -> 0 | S25: =R25/Q25 -> 0 | T25: =SUMIFS('B0200'!L:L,'B0200'!EL:EL,"OK") -> 4.0921507e+09 | U25: =T25/Q25 -> 1
A26: 0026 | B26: =CONCATENATE("v_2_",A25) -> v_2_0025 | C26: B02.00 | D26: 0250 | E26: Structured product | F26: String: Drop-down | G26: X | I26: Drop down values must be respected. | K26: The drop down values must be respected. | L26: =SUM(M26,O26) -> 8 | M26: =COUNTIF('B0200'!EM:EM,"KO") -> 0 | N26: =M26/L26 -> 0 | O26: =COUNTIF('B0200'!EM:EM,"OK") -> 8 | P26: =O26/L26 -> 1 | Q26: =SUM(R26,T26) -> 4.0921507e+09 | R26: =SUMIFS('B0200'!L:L,'B0200'!EM:EM,"KO") -> 0 | S26: =R26/Q26 -> 0 | T26: =SUMIFS('B0200'!L:L,'B0200'!EM:EM,"OK") -> 4.0921507e+09 | U26: =T26/Q26 -> 1
A27: 0027 | B27: =CONCATENATE("v_2_",A26) -> v_2_0026 | C27: B02.00 | D27: 0310 | E27: Secured/Unsecured | F27: String: Drop-down | G27: X | I27: Drop down values must be respected. | K27: The drop down values must be respected. | L27: =SUM(M27,O27) -> 8 | M27: =COUNTIF('B0200'!EN:EN,"KO") -> 0 | N27: =M27/L27 -> 0 | O27: =COUNTIF('B0200'!EN:EN,"OK") -> 8 | P27: =O27/L27 -> 1 | Q27: =SUM(R27,T27) -> 4.0921507e+09 | R27: =SUMIFS('B0200'!L:L,'B0200'!EN:EN,"KO") -> 0 | S27: =R27/Q27 -> 0 | T27: =SUMIFS('B0200'!L:L,'B0200'!EN:EN,"OK") -> 4.0921507e+09 | U27: =T27/Q27 -> 1
A28: 0028 | B28: =CONCATENATE("v_2_",A27) -> v_2_0027 | C28: B02.00 | D28: 0330 | E28: Amount of the uncollateralized part | F28: Numeric: 2 decimals | G28: X | I28: Check if the reported field is equal to: max(0,c0120 - c0320.) | J28: c0310 = "Secured" & c0250 = ( "Non-structured/Vanilla"OR "Other non-standard terms") AND c0240 !="ZCB issued at discount" | K28: The reported field should be equal to: c0120 - c0320. | L28: =SUM(M28,O28) -> 8 | M28: =COUNTIF('B0200'!EO:EO,"KO") -> 0 | N28: =M28/L28 -> 0 | O28: =COUNTIF('B0200'!EO:EO,"OK") -> 8 | P28: =O28/L28 -> 1 | Q28: =SUM(R28,T28) -> 4.0921507e+09 | R28: =SUMIFS('B0200'!L:L,'B0200'!EO:EO,"KO") -> 0 | S28: =R28/Q28 -> 0 | T28: =SUMIFS('B0200'!L:L,'B0200'!EO:EO,"OK") -> 4.0921507e+09 | U28: =T28/Q28 -> 1
A29: 0029 | B29: =CONCATENATE("v_2_",A28) -> v_2_0028 | C29: B02.00 | D29: 0330 | E29: Amount of the uncollateralized part | F29: Numeric: 2 decimals | G29: X | I29: Check if the reported field is either max(0, c0270 - c0320) or max (0, c0120 - c0320) | J29: c0310 = "Secured" & c0250 = ("Structured" OR "Only structured coupon") | K29: The reported field should be equal to (c0270 - c0320) if the fair value is used, or equal to (c0120 - c0320) otherwise | L29: =SUM(M29,O29) -> 8 | M29: =COUNTIF('B0200'!EP:EP,"KO") -> 0 | N29: =M29/L29 -> 0 | O29: =COUNTIF('B0200'!EP:EP,"OK") -> 8 | P29: =O29/L29 -> 1 | Q29: =SUM(R29,T29) -> 4.0921507e+09 | R29: =SUMIFS('B0200'!L:L,'B0200'!EP:EP,"KO") -> 0 | S29: =R29/Q29 -> 0 | T29: =SUMIFS('B0200'!L:L,'B0200'!EP:EP,"OK") -> 4.0921507e+09 | U29: =T29/Q29 -> 1
A30: 0030 | B30: =CONCATENATE("v_2_",A29) -> v_2_0029 | C30: B02.00 | D30: 0350 | E30: Type of the collateral | F30: String: Drop-down | G30: X | I30: Drop down values must be respected. | K30: The drop down values must be respected. | L30: =SUM(M30,O30) -> 8 | M30: =COUNTIF('B0200'!EQ:EQ,"KO") -> 0 | N30: =M30/L30 -> 0 | O30: =COUNTIF('B0200'!EQ:EQ,"OK") -> 8 | P30: =O30/L30 -> 1 | Q30: =SUM(R30,T30) -> 4.0921507e+09 | R30: =SUMIFS('B0200'!L:L,'B0200'!EQ:EQ,"KO") -> 0 | S30: =R30/Q30 -> 0 | T30: =SUMIFS('B0200'!L:L,'B0200'!EQ:EQ,"OK") -> 4.0921507e+09 | U30: =T30/Q30 -> 1
A31: 0031 | B31: =CONCATENATE("v_2_",A30) -> v_2_0030 | C31: B02.00 | D31: 0350 | E31: Type of the collateral | F31: String: Drop-down | G31: X | I31: "Not applicable" must be reported. | J31: c0310 = "Unsecured" | K31: The field must be "Not applicable" if c0310 is unsecured. | L31: =SUM(M31,O31) -> 8 | M31: =COUNTIF('B0200'!ER:ER,"KO") -> 0 | N31: =M31/L31 -> 0 | O31: =COUNTIF('B0200'!ER:ER,"OK") -> 8 | P31: =O31/L31 -> 1 | Q31: =SUM(R31,T31) -> 4.0921507e+09 | R31: =SUMIFS('B0200'!L:L,'B0200'!ER:ER,"KO") -> 0 | S31: =R31/Q31 -> 0 | T31: =SUMIFS('B0200'!L:L,'B0200'!ER:ER,"OK") -> 4.0921507e+09 | U31: =T31/Q31 -> 1
A32: 0032 | B32: =CONCATENATE("v_2_",A31) -> v_2_0031 | C32: B02.00 | D32: 0440 | E32: Nature of the global note | F32: String: Drop-down | G32: X | I32: Drop down values must be respected. | K32: The drop down values must be respected. | L32: =SUM(M32,O32) -> 8 | M32: =COUNTIF('B0200'!ES:ES,"KO") -> 0 | N32: =M32/L32 -> 0 | O32: =COUNTIF('B0200'!ES:ES,"OK") -> 8 | P32: =O32/L32 -> 1 | Q32: =SUM(R32,T32) -> 4.0921507e+09 | R32: =SUMIFS('B0200'!L:L,'B0200'!ES:ES,"KO") -> 0 | S32: =R32/Q32 -> 0 | T32: =SUMIFS('B0200'!L:L,'B0200'!ES:ES,"OK") -> 4.0921507e+09 | U32: =T32/Q32 -> 1
A33: 0033 | B33: =CONCATENATE("v_2_",A32) -> v_2_0032 | C33: B02.00 | D33: 0530 | E33: Type of own funds at individual level | F33: String: Drop-down | G33: X | I33: Drop down values must be respected. | K33: The drop down values must be respected. | L33: =SUM(M33,O33) -> 8 | M33: =COUNTIF('B0200'!ET:ET,"KO") -> 0 | N33: =M33/L33 -> 0 | O33: =COUNTIF('B0200'!ET:ET,"OK") -> 8 | P33: =O33/L33 -> 1 | Q33: =SUM(R33,T33) -> 4.0921507e+09 | R33: =SUMIFS('B0200'!L:L,'B0200'!ET:ET,"KO") -> 0 | S33: =R33/Q33 -> 0 | T33: =SUMIFS('B0200'!L:L,'B0200'!ET:ET,"OK") -> 4.0921507e+09 | U33: =T33/Q33 -> 1
A34: 0034 | B34: =CONCATENATE("v_2_",A33) -> v_2_0033 | C34: B02.00 | D34: 0540 | E34: Eligible amount for own funds at individual level | F34: Numeric: 2 decimals | G34: X | I34: Check if the reported field is higher than or equal 0. | K34: The reported amount should be positive or zero. | L34: =SUM(M34,O34) -> 8 | M34: =COUNTIF('B0200'!EU:EU,"KO") -> 0 | N34: =M34/L34 -> 0 | O34: =COUNTIF('B0200'!EU:EU,"OK") -> 8 | P34: =O34/L34 -> 1 | Q34: =SUM(R34,T34) -> 4.0921507e+09 | R34: =SUMIFS('B0200'!L:L,'B0200'!EU:EU,"KO") -> 0 | S34: =R34/Q34 -> 0 | T34: =SUMIFS('B0200'!L:L,'B0200'!EU:EU,"OK") -> 4.0921507e+09 | U34: =T34/Q34 -> 1
A35: 0035 | B35: =CONCATENATE("v_2_",A34) -> v_2_0034 | C35: B02.00 | D35: 0550 | E35: Type of own funds at consolidated level | F35: String: Drop-down | G35: X | I35: Drop down values must be respected. | K35: The drop down values must be respected. | L35: =SUM(M35,O35) -> 8 | M35: =COUNTIF('B0200'!EV:EV,"KO") -> 0 | N35: =M35/L35 -> 0 | O35: =COUNTIF('B0200'!EV:EV,"OK") -> 8 | P35: =O35/L35 -> 1 | Q35: =SUM(R35,T35) -> 4.0921507e+09 | R35: =SUMIFS('B0200'!L:L,'B0200'!EV:EV,"KO") -> 0 | S35: =R35/Q35 -> 0 | T35: =SUMIFS('B0200'!L:L,'B0200'!EV:EV,"OK") -> 4.0921507e+09 | U35: =T35/Q35 -> 1
A36: 0036 | B36: =CONCATENATE("v_2_",A35) -> v_2_0035 | C36: B02.00 | D36: 0560 | E36: Eligible amount for own funds at consolidated level | F36: Numeric: 2 decimals | G36: X | I36: Check if the reported field is higher than or equal 0. | K36: The reported amount should be positive or zero. | L36: =SUM(M36,O36) -> 8 | M36: =COUNTIF('B0200'!EW:EW,"KO") -> 0 | N36: =M36/L36 -> 0 | O36: =COUNTIF('B0200'!EW:EW,"OK") -> 8 | P36: =O36/L36 -> 1 | Q36: =SUM(R36,T36) -> 4.0921507e+09 | R36: =SUMIFS('B0200'!L:L,'B0200'!EW:EW,"KO") -> 0 | S36: =R36/Q36 -> 0 | T36: =SUMIFS('B0200'!L:L,'B0200'!EW:EW,"OK") -> 4.0921507e+09 | U36: =T36/Q36 -> 1
A37: 0037 | B37: =CONCATENATE("v_2_",A36) -> v_2_0036 | C37: B02.00 | D37: 0590 | E37: Type of security interest provided by a third party | F37: String: Drop-down | G37: X | I37: Drop down values must be respected. | K37: The drop down values must be respected. | L37: =SUM(M37,O37) -> 8 | M37: =COUNTIF('B0200'!EX:EX,"KO") -> 0 | N37: =M37/L37 -> 0 | O37: =COUNTIF('B0200'!EX:EX,"OK") -> 8 | P37: =O37/L37 -> 1 | Q37: =SUM(R37,T37) -> 4.0921507e+09 | R37: =SUMIFS('B0200'!L:L,'B0200'!EX:EX,"KO") -> 0 | S37: =R37/Q37 -> 0 | T37: =SUMIFS('B0200'!L:L,'B0200'!EX:EX,"OK") -> 4.0921507e+09 | U37: =T37/Q37 -> 1
A38: 0038 | B38: =CONCATENATE("v_2_",A37) -> v_2_0037 | C38: B02.00 | D38: 0610 | E38: Carrying amount IFRS | F38: Numeric: 2 decimals | G38: X | I38: Check if the reported field is higher than or equal 0. | K38: The reported amount should be positive or zero. | L38: =SUM(M38,O38) -> 8 | M38: =COUNTIF('B0200'!EY:EY,"KO") -> 0 | N38: =M38/L38 -> 0 | O38: =COUNTIF('B0200'!EY:EY,"OK") -> 8 | P38: =O38/L38 -> 1 | Q38: =SUM(R38,T38) -> 4.0921507e+09 | R38: =SUMIFS('B0200'!L:L,'B0200'!EY:EY,"KO") -> 0 | S38: =R38/Q38 -> 0 | T38: =SUMIFS('B0200'!L:L,'B0200'!EY:EY,"OK") -> 4.0921507e+09 | U38: =T38/Q38 -> 1
A39: 0040 | B39: =CONCATENATE("v_2_",A38) -> v_2_0038 | C39: B02.00 | D39: 0620 | E39: Balance sheet item according to IFRS | F39: String: Drop-down | G39: x | I39: Drop down values must be respected. | K39: The drop down values must be respected. | L39: =SUM(M39,O39) -> 8 | M39: =COUNTIF('B0200'!EZ:EZ,"KO") -> 0 | N39: =M39/L39 -> 0 | O39: =COUNTIF('B0200'!EZ:EZ,"OK") -> 8 | P39: =O39/L39 -> 1 | Q39: =SUM(R39,T39) -> 4.0921507e+09 | R39: =SUMIFS('B0200'!L:L,'B0200'!EZ:EZ,"KO") -> 0 | S39: =R39/Q39 -> 0 | T39: =SUMIFS('B0200'!L:L,'B0200'!EZ:EZ,"OK") -> 4.0921507e+09 | U39: =T39/Q39 -> 1
A40: 0059 | B40: =CONCATENATE("v_2_",A39) -> v_2_0040 | C40: B90.00 | D40: 0030 | E40: Counterparty within the resolution group | F40: String: Drop-down | G40: X | I40: Drop down values must be respected. | K40: The drop down values must be respected. | L40: =SUM(M40,O40) -> 9 | M40: =COUNTIF('B9000'!M:M,"KO") -> 0 | N40: =M40/L40 -> 0 | O40: =COUNTIF('B9000'!M:M,"OK") -> 9 | P40: =O40/L40 -> 1 | Q40: =SUM(R40,T40) -> 4.0875867e+09 | R40: =SUMIFS('B9000'!K:K,'B9000'!M:M,"KO") -> 0 | S40: =R40/Q40 -> 0 | T40: =SUMIFS('B9000'!K:K,'B9000'!M:M,"OK") -> 4.0875867e+09 | U40: =T40/Q40 -> 1
A41: 0060 | B41: =CONCATENATE("v_2_",A40) -> v_2_0059 | C41: B90.00 | D41: 0080 | E41: Counterparty Type | F41: String: Drop-down | G41: X | I41: Drop down values must be respected. | K41: The drop down values must be respected. | L41: =SUM(M41,O41) -> 9 | M41: =COUNTIF('B9000'!N:N,"KO") -> 0 | N41: =M41/L41 -> 0 | O41: =COUNTIF('B9000'!N:N,"OK") -> 9 | P41: =O41/L41 -> 1 | Q41: =SUM(R41,T41) -> 4.0875867e+09 | R41: =SUMIFS('B9000'!K:K,'B9000'!N:N,"KO") -> 0 | S41: =R41/Q41 -> 0 | T41: =SUMIFS('B9000'!K:K,'B9000'!N:N,"OK") -> 4.0875867e+09 | U41: =T41/Q41 -> 1
A42: 0061 | B42: =CONCATENATE("v_2_",A41) -> v_2_0060 | C42: B90.00 | D42: 0090 | E42: Country of the counterparty | F42: String: ISO 3166-1 | G42: X | I42: Check if the reported field respects the ISO 3166-1 alpha-2 code. | J42: c0080 ≠ "XX" OR "99" | K42: The field must be reported using the ISO 3166-1 alpha-2 code. | L42: =SUM(M42,O42) -> 9 | M42: =COUNTIF('B9000'!O:O,"KO") -> 2 | N42: =M42/L42 -> 0.22222222 | O42: =COUNTIF('B9000'!O:O,"OK") -> 7 | P42: =O42/L42 -> 0.77777778 | Q42: =SUM(R42,T42) -> 4.0875867e+09 | R42: =SUMIFS('B9000'!K:K,'B9000'!O:O,"KO") -> 9424218.5 | S42: =R42/Q42 -> 0.0023055703 | T42: =SUMIFS('B9000'!K:K,'B9000'!O:O,"OK") -> 4.0781625e+09 | U42: =T42/Q42 -> 0.99769443
B43: =CONCATENATE("v_2_",A42) -> v_2_0061 | C43: B90.00 | D43: 0100 | E43: Relevant amount for Bail-in/WDC | F43: Numeric: 2 decimals | H43: X | I43: Check if the reported field is equal 0. | J43: c0030 ≠ "No" | K43: Positive values are allowed in case intragroup liabilities do not meet the conditions set forth in article 44(2)h BRRD and should be duly justified by the reporting entity | L43: =SUM(M43,O43) -> 9 | M43: =COUNTIF('B9000'!P:P,"KO") -> 7 | N43: =M43/L43 -> 0.77777778 | O43: =COUNTIF('B9000'!P:P,"OK") -> 2 | P43: =O43/L43 -> 0.22222222 | Q43: =SUM(R43,T43) -> 4.0875867e+09 | R43: =SUMIFS('B9000'!K:K,'B9000'!P:P,"KO") -> 4.0781625e+09 | S43: =R43/Q43 -> 0.99769443 | T43: =SUMIFS('B9000'!K:K,'B9000'!P:P,"OK") -> 9424218.5 | U43: =T43/Q43 -> 0.0023055703

Sheet BST individual BS Oct25
A1: BANCO SANTANDER TOTTA, S.A.
A3: BALANÇO INDIVIDUAL EM 31 DE OUTUBRO DE 2025
A5: (Montantes expressos em Euros)
E9: 31-10-2025 | I9: 45596
C10: Valor antes de
C11: imparidade e | E11: Imparidade | G11: Valor | I11: Valor
A12: ATIVO | C12: amortizações | E12: e amortizações | G12: líquido | I12: líquido | K12: PASSIVO E CAPITAL PRÓPRIO | M12: 31-10-2025 | O12: 45596
A14: Caixa e disponibilidades em bancos centrais | C14: 2464681486 | E14: 0 | G14: 2464681486 | I14: 2291880753
A15: Disponibilidades em outras instituições de crédito | C15: 132511791 | E15: 1 | G15: 132511790 | I15: 129398229 | K15: Passivos financeiros detidos para negociação | M15: 797902389 | O15: 1628982350
A16: Ativos financeiros detidos para negociação | C16: 793969431 | E16: 0 | G16: 793969431 | I16: 1616240841 | K16: Passivos financeiros obrigatóriamente ao justo valor através de resultados | M16: 0 | O16: 0
A17: Outros ativos financeiros obrigatoriamente ao justo valor através de resultados | C17: 1351291494 | E17: 0 | G17: 1351291494 | I17: 921174772 | K17: Passivos financeiros ao custo amortizado
A18: Ativos financeiros contabilizados pelo justo valor através dos resultados | C18: 0 | E18: 0 | G18: 0 | I18: 0 | K18: Recursos de bancos centrais | M18: 0 | O18: 0
A19: Outros ativos financeiros ao justo valor através de outro rendimento integral | K19: Recursos de outras instituições de crédito | M19: 4542411639 | O19: 4796730694
A20: Aplicações em instituições de crédito | C20: 0 | E20: 0 | G20: 0 | I20: 0 | K20: Recursos de clientes e outros empréstimos | M20: 39616278335 | O20: 38306381418
A21: Instrumentos de capital | C21: 170042707 | E21: 0 | G21: 170042707 | I21: 174317798 | K21: Responsabilidades representadas por títulos | M21: 6803435718 | O21: 5181981776
A22: Títulos de dívida | C22: 1191129741 | E22: 0 | G22: 1191129741 | I22: 1231017822 | K22: Passivos financeiros associados a ativos transferidos | M22: 3950994377 | O22: 2157823137
A23: Crédito concedido | C23: 2396463194 | E23: 0 | G23: 2396463194 | I23: 2408216706 | K23: Outros passivos financeiros | M23: 342888024 | O23: 309613524
A24: Outros saldos a receber | C24: 0 | E24: 0 | G24: 0 | I24: 0 | K24: Derivados de cobertura | M24: 41505612 | O24: 17418310
A25: Ativos financeiros ao custo amortizado | K25: Correções de valor em passivos inseridos em operações de cobertura | M25: 0 | O25: 0
A26: Aplicações em instituições de crédito | C26: 63200423 | E26: 135935 | G26: 63064488 | I26: 2660003 | K26: Provisões | M26: 118546163 | O26: 112731557
A27: Títulos de dívida | C27: 13340853358 | E27: 5409546 | G27: 13335443812 | I27: 12016075814 | K27: Passivos por impostos | M27: 149834187 | O27: 482563249
A28: Crédito concedido | C28: 37867923771 | E28: 719305621 | G28: 37148618150 | I28: 34886927751 | K28: Instrumentos representativos de capital reembolsáveis | M28: 0 | O28: 0
A29: Outros saldos a receber | C29: 486315247 | E29: 6400170 | G29: 479915077 | I29: 481828991 | K29: Outros passivos | M29: 424932419 | O29: 597435147
A30: Investimentos detidos até à maturidade | C30: 0 | E30: 0 | G30: 0 | I30: 0 | K30: Total do Passivo | M30: 56788728863 | O30: 53591661162
A31: Derivados de cobertura | C31: 95794790 | E31: 0 | G31: 95794790 | I31: 148737590
A32: Correções de valor em ativos inseridos em operações de cobertura | C32: 0 | E32: 0 | G32: 0 | I32: 0 | K32: Capital Próprio
A33: Investimentos em associadas | C33: 558558076 | E33: 11000000 | G33: 547558076 | I33: 548607576 | K33: Capital | M33: 1391779674 | O33: 1391779674
A34: Propriedades de investimento | C34: 0 | E34: 0 | G34: 0 | I34: 0 | K34: Prémios de emissão | M34: 193389954 | O34: 193389954
A35: Outros ativos tangíveis | C35: 497930833 | E35: 243807053 | G35: 254123780 | I35: 253126572 | K35: Outros instrumentos de capital | M35: 1200000000 | O35: 400000000
A36: Ativos intangíveis | C36: 150392138 | E36: 107658508 | G36: 42733630 | I36: 31439522 | K36: Reservas por rendimento integral acumulado | M36: -277867488 | O36: -207348334
A37: Ativos por impostos | C37: 103195299 | E37: 0 | G37: 103195299 | I37: 112966973 | K37: Outras reservas e resultados transitados | M37: 1127393007 | O37: 1346161683
A38: Outros ativos | C38: 340132870 | E38: 23696609 | G38: 316436261 | I38: 300751949 | K38: (Ações próprias) | M38: -19146966 | O38: -2239096
A39: Ativos não correntes detidos para venda | C39: 30301661 | E39: 9304585 | G39: 20997076 | I39: 30565264 | K39: Resultado Individual do periodo | M39: 782420417 | O39: 872529883
K40: Dividendos antecipados | M40: -278727179 | O40: 0
K41: Total Capital Próprio | M41: 4119241419 | O41: 3994273764
A42: Total do Ativo | C42: 62034688310 | E42: 1126718028 | G42: 60907970282 | I42: 57585934926 | K42: Total Passivo + Capital Próprio | M42: 60907970282 | O42: 57585934926

Sheet Lists
A1: Reporting entity type | B1: Boolean | C1: Category | D1: Instrument or liability within the resolution group | E1: Nature of the liability | F1: Bail-in recognition clause | G1: Zero coupon bond | H1: Structured product | I1: Secured/Unsecured | J1: Type of the collateral | K1: Trading method | L1: Nature of the global note | M1: Counterparty Type | N1: Type of own funds | O1: Type of security interest provided by a third party | P1: Balance sheet item according to IFRS | Q1: ISDA Protocol Resolution Stay – reporting entity | R1: Recognition Resolution Stay of the counterparty | S1: Type of guarantee | T1: Type of protection value | U1: Protection valuation approach | V1: MBDT tab
A2: Resolution Entity | B2: TRUE | C2: Covered deposits (BRRD art. 44/2/a) | D2: Intragroup and intra-resolution group | E2: Registered Bond | F2: Yes, supported by Legal Opinion | G2: ZCB issued at discount | H2: Non-structured/Vanilla | I2: Secured | J2: Real estate | K2: Nominal | L2: NGN | M2: Households | N2: T2 in phase-out | O2: Lien | P2: 010 Financial liabilities held for trading | Q2: Yes - ISDA Universal Protocol | R2: Yes - ISDA Universal Protocol | S2: Issuance | T2: Notional amount | U2: Mark-to-market valuation | V2: B0200
A3: Non-Resolution Entity | B3: FALSE | C3: Secured liabilities - collateralized part (BRRD art. 44/2/b) | D3: Intragroup but not intra-resolution group | E3: Bearer Bond | F3: Yes, not supported by Legal Opinion | G3: ZCB not issued at discount | H3: Structured | I3: Unsecured | J3: Ships | K3: Unit | L3: CGN | M3: Micro & SME | N3: Grandfathered T2 | O3: Guarantee | P3: 070 Financial liabilities at fair value through profit or loss | Q3: Yes - ISDA JMP Module | R3: Yes - ISDA JMP Module | S3: Counterparty | T3: Fair value | U3: Counterparty estimation | V3: B0300
C4: Client liabilities, if protected in insolvency (BRRD art. 44/2/c) | D4: No | E4: Borrower Note Loan | F4: No | G4: No ZCB | H4: Other non-standard terms | J4: Aircraft | K4: Not applicable | L4: Not applicable | M4: Corporates | N4: Fully Compliant T2 | O4: Surety | P4: 110 Financial liabilities at amortized cost | Q4: Yes - Other | R4: Yes - Other Agreement for resolution stay recognition | S4: Unlimited | T4: Market value | U4: Creditor valuation | V4: B0400
C5: Fiduciary liabilities, if protected in insolvency (BRRD art. 44/2/d) | E5: Certificate of Deposit / Commercial paper | F5: Not applicable | G5: Aggregated | H5: Only structured coupon | J5: Financial | M5: Institutions | N5: Partially (A)T1 and T2 | O5: Guarantee obligation | P5: 280 Other liabilities | Q5: Not applicable | R5: Not applicable | S5: Other types of guarantee than issuance guarantees, counterparty guarantees and unlimited guarantees | T5: Long-term sustainable value | U5: Third party valuation | V5: B0500
C6: Institution liabilities < 7 days (BRRD art. 44/2/e) | E6: Title of ownership | F6: Aggregated | H6: Aggregated | J6: Other | M6: Other financial corporations | N6: Grandfathered AT1 | O6: Other | P6: 300 Total equity | Q6: No resolution stay recognition | R6: No resolution stay recognition | T6: Other protection value
C7: System (operator) and CCP liabilities < 7 days (BRRD art. 44/2/f) | E7: Cash account/saving account | J7: Not applicable | M7: Insurance firms & pension funds | N7: Fully Compliant AT1 | O7: Not applicable
C8: Employee liabilities (BRRD art. 44/2/g/i) | E8: Term deposit | M8: Government, central banks & supranationals | N8: CET1 | O8: Aggregated
C9: Critical service liabilities (BRRD art. 44/2/g/ii) | E9: Loan | M9: Non identified, listed on an exchange platform | N9: No
C10: Tax and social security authorities liabilities, if preferred (BRRD art. 44/2/g/iii) | E10: Bill of exchange | M10: Non identified, not listed on an exchange platform
C11: DGS liabilities (BRRD art. 44/2/g/iv) | E11: Other
C12: Liabilities towards other entities of the resolution group (BRRD art. 44/2/h)
C13: Liabilities eligible for bail-in
C14: Other equity items
C15: Title of ownership

Sheet ISO 4217
A1: List one: Currency, fund and precious metal codes
A2: Published:
A3: 45789
A4: ENTITY | B4: Currency | C4: Alphabetic Code | D4: Numeric Code | E4: Minor unit | F4: Fund
A5: AFGHANISTAN | B5: Afghani | C5: AFN | D5: 971 | E5: 2
A6: ÅLAND ISLANDS | B6: Euro | C6: EUR | D6: 978 | E6: 2
A7: ALBANIA | B7: Lek | C7: ALL | D7: 008 | E7: 2
A8: ALGERIA | B8: Algerian Dinar | C8: DZD | D8: 012 | E8: 2
A9: AMERICAN SAMOA | B9: US Dollar | C9: USD | D9: 840 | E9: 2
A10: ANDORRA | B10: Euro | C10: EUR | D10: 978 | E10: 2
A11: ANGOLA | B11: Kwanza | C11: AOA | D11: 973 | E11: 2
A12: ANGUILLA | B12: East Caribbean Dollar | C12: XCD | D12: 951 | E12: 2
A13: ANTARCTICA | B13: No universal currency
A14: ANTIGUA AND BARBUDA | B14: East Caribbean Dollar | C14: XCD | D14: 951 | E14: 2
A15: ARAB MONETARY FUND | B15: Arab Accounting Dinar | C15: XAD | D15: 396 | E15: 2
A16: ARGENTINA | B16: Argentine Peso | C16: ARS | D16: 032 | E16: 2
A17: ARMENIA | B17: Armenian Dram | C17: AMD | D17: 051 | E17: 2
A18: ARUBA | B18: Aruban Florin | C18: AWG | D18: 533 | E18: 2
A19: AUSTRALIA | B19: Australian Dollar | C19: AUD | D19: 036 | E19: 2
A20: AUSTRIA | B20: Euro | C20: EUR | D20: 978 | E20: 2
A21: AZERBAIJAN | B21: Azerbaijan Manat | C21: AZN | D21: 944 | E21: 2
A22: BAHAMAS (THE) | B22: Bahamian Dollar | C22: BSD | D22: 044 | E22: 2
A23: BAHRAIN | B23: Bahraini Dinar | C23: BHD | D23: 048 | E23: 3
A24: BANGLADESH | B24: Taka | C24: BDT | D24: 050 | E24: 2
A25: BARBADOS | B25: Barbados Dollar | C25: BBD | D25: 052 | E25: 2
A26: BELARUS | B26: Belarusian Ruble | C26: BYN | D26: 933 | E26: 2
A27: BELGIUM | B27: Euro | C27: EUR | D27: 978 | E27: 2
... A33: BOLIVIA (PLURINATIONAL STATE OF) | B33: Boliviano | C33: BOB | D33: 068 | E33: 2
A34: BOLIVIA (PLURINATIONAL STATE OF) | B34: Mvdol | C34: BOV | D34: 984 | E34: 2 | F34: TRUE
A35: BONAIRE, SINT EUSTATIUS AND SABA | B35: US Dollar | C35: USD | D35: 840 | E35: 2
