Workbook

Sheet Mapeamento as-is vs to-be
B2: 1. Proposta de mapeamento para os códigos do Management Product | Tabela CT875
B4: Mapeamento as-is | L4: Proposta to-be
B5: campo | C5: valor_campo | D5: Descritivo Guia Corporativo | E5: cnmetanseg | F5: ccentro_gestor | G5: ckmetamis | H5: cmetacom | I5: ckarea | J5: ordem | K5: Descritivo ckarea | L5: ckmetamis | M5: ckarea | N5: ckarea (para implementar) | O5: Descritivo ckarea
B6: MNGMNT_PRDCT | C6: PRDCT0304 | D6: =TRIM(VLOOKUP(C6,codelist!$B:$C,2,FALSE)) -> Securitization | E6: NULL | F6: NULL | G6: in (S,UGP000,A,P) | H6: NULL | I6: GB0530 | J6: 1 | K6: =+VLOOKUP(I6,'Códigos antigos'!$A$2:$B$102,2,FALSE) -> Debt Capital Markets & Securitization | L6: NULL | M6: AN02040300 | N6: in (AN02040300, AN02040400) | O6: =+VLOOKUP(M6,'Novos códigos'!A1:B87,2,FALSE) -> Securitization Products
L7: NULL | M7: AN02040400 | O7: =+VLOOKUP(M7,'Novos códigos'!A2:B88,2,FALSE) -> Securitization Finance
B8: MNGMNT_PRDCT | C8: PRDCT0303 | D8: =TRIM(VLOOKUP(C8,codelist!$B:$C,2,FALSE)) -> Debt Capital Markets (DCM) | E8: NULL | F8: NULL | G8: not in (S,UGP000,A,P) | H8: NULL | I8: GB0530 | J8: 2 | K8: =+VLOOKUP(I8,'Códigos antigos'!$A$2:$B$102,2,FALSE) -> Debt Capital Markets & Securitization | L8: NULL | M8: AN02030200 | N8: AN02030200 | O8: =+VLOOKUP(M8,'Novos códigos'!A3:B89,2,FALSE) -> DCM
B9: MNGMNT_PRDCT | C9: PRDCT01010201 | D9: =TRIM(VLOOKUP(C9,codelist!$B:$C,2,FALSE)) -> Project & Acquisition Finance | E9: NULL | F9: NULL | G9: NULL | H9: NULL | I9: GB0525 | J9: 3 | K9: =+VLOOKUP(I9,'Códigos antigos'!$A$2:$B$102,2,FALSE) -> Project and Acquisition Finance | L9: NULL | M9: AN02030300 | N9: AN02030300 | O9: =+VLOOKUP(M9,'Novos códigos'!A4:B90,2,FALSE) -> Project and Acquisition Finance.
B10: MNGMNT_PRDCT | C10: PRDCT01010202 | D10: =TRIM(VLOOKUP(C10,codelist!$B:$C,2,FALSE)) -> Syndicated Loans | E10: NULL | F10: NULL | G10: NULL | H10: NULL | I10: GB0540 | J10: 4 | K10: =+VLOOKUP(I10,'Códigos antigos'!$A$2:$B$102,2,FALSE) -> Sindicados | L10: NULL | M10: AN02030400 | N10: AN02030400 | O10: =+VLOOKUP(M10,'Novos códigos'!A5:B91,2,FALSE) -> Syndicated Loans
B11: MNGMNT_PRDCT | C11: PRDCT01010204 | D11: =TRIM(VLOOKUP(C11,codelist!$B:$C,2,FALSE)) -> Asset Based Finance (ABF) | E11: NULL | F11: NULL | G11: NULL | H11: NULL | I11: GB0535 | J11: 5 | K11: =+VLOOKUP(I11,'Códigos antigos'!$A$2:$B$102,2,FALSE) -> ACS - Asset & Capital Structuring | L11: NULL | M11: AN02010200 | N11: AN02010200 | O11: =+VLOOKUP(M11,'Novos códigos'!A6:B92,2,FALSE) -> ABF
B12: MNGMNT_PRDCT | C12: PRDCT01010205 | D12: =TRIM(VLOOKUP(C12,codelist!$B:$C,2,FALSE)) -> Leveraged Finance | E12: NULL | F12: NULL | G12: NULL | H12: NULL | I12: GB0545 | J12: 6 | K12: =+VLOOKUP(I12,'Códigos antigos'!$A$2:$B$102,2,FALSE) -> Leveraged Finance | L12: NULL | M12: AN02030600 | N12: AN02030600 | O12: =+VLOOKUP(M12,'Novos códigos'!A7:B93,2,FALSE) -> Leveraged Finance
B13: MNGMNT_PRDCT | C13: PRDCT01010206 | D13: =TRIM(VLOOKUP(C13,codelist!$B:$C,2,FALSE)) -> Export & Agency Finance | E13: NULL | F13: NULL | G13: NULL | H13: NULL | I13: GB1025 | J13: 7 | K13: =+VLOOKUP(I13,'Códigos antigos'!$A$2:$B$102,2,FALSE) -> Export & Agency Finance | L13: NULL | M13: AN02020400 | N13: AN02020400 | O13: =+VLOOKUP(M13,'Novos códigos'!A8:B94,2,FALSE) -> Export & Agency Finance
B14: MNGMNT_PRDCT | C14: PRDCT01010207 | D14: =TRIM(VLOOKUP(C14,codelist!$B:$C,2,FALSE)) -> Trade & Working Capital Solutions | E14: NULL | F14: NULL | G14: NULL | H14: NULL | I14: GB1015 | J14: 8 | K14: =+VLOOKUP(I14,'Códigos antigos'!$A$2:$B$102,2,FALSE) -> Trade & WCS | L14: NULL | M14: AN02020200 | N14: AN02020200 | O14: =+VLOOKUP(M14,'Novos códigos'!A9:B95,2,FALSE) -> Trade & WCS
B15: MNGMNT_PRDCT | C15: PRDCT0203 | D15: =TRIM(VLOOKUP(C15,codelist!$B:$C,2,FALSE)) -> Derivatives | E15: NULL | F15: NULL | G15: NULL | H15: NULL | I15: GB2005 | J15: 9 | K15: =+VLOOKUP(I15,'Códigos antigos'!$A$2:$B$102,2,FALSE) -> Sales Mercados | L15: NULL | M15: AN02040100 | N15: in (AN02040100, AN02040200, GB2001, AN02050100, AN02040700) | O15: =+VLOOKUP(M15,'Novos códigos'!A10:B96,2,FALSE) -> FX
L16: NULL | M16: AN02040200 | O16: =+VLOOKUP(M16,'Novos códigos'!A11:B97,2,FALSE) -> Rates
L17: NULL | M17: GB2001 | O17: =+VLOOKUP(M17,'Novos códigos'!A12:B98,2,FALSE) -> Credit | P17: Inclui as áreas AN02040500 e AN02040600.
L18: NULL | M18: AN02050100 | O18: =+VLOOKUP(M18,'Novos códigos'!A15:B101,2,FALSE) -> Equity Derivatives
L19: NULL | M19: AN02040700 | O19: =+VLOOKUP(M19,'Novos códigos'!A16:B102,2,FALSE) -> Commodities
B20: MNGMNT_PRDCT | C20: PRDCT0301 | D20: =TRIM(VLOOKUP(C20,codelist!$B:$C,2,FALSE)) -> Mergers & Acquisitions (M&A) | E20: NULL | F20: NULL | G20: NULL | H20: NULL | I20: GB0505 | J20: 10 | K20: =+VLOOKUP(I20,'Códigos antigos'!$A$2:$B$102,2,FALSE) -> M & A - Mergers and Acquisitions | L20: NULL | M20: AN02050600 | N20: AN02050600 | O20: =+VLOOKUP(M20,'Novos códigos'!A11:B97,2,FALSE) -> M & A - Mergers and Acquisitions
B21: MNGMNT_PRDCT | C21: PRDCT0302 | D21: =TRIM(VLOOKUP(C21,codelist!$B:$C,2,FALSE)) -> Equity Capital Markets (ECM) | E21: NULL | F21: NULL | G21: NULL | H21: NULL | I21: GB0510 | J21: 11 | K21: =+VLOOKUP(I21,'Códigos antigos'!$A$2:$B$102,2,FALSE) -> ECM - Equity Capital Markets | L21: NULL | M21: GB0510 | N21: GB0510 | O21: =+VLOOKUP(M21,'Novos códigos'!A12:B98,2,FALSE) -> ECM - Equity Capital Markets & Others
B22: MNGMNT_PRDCT | C22: PRDCT010101 | D22: =TRIM(VLOOKUP(C22,codelist!$B:$C,2,FALSE)) -> Mortgages | E22: NULL | F22: NULL | G22: in (AI02,AI03) | H22: NULL | I22: NULL | J22: 12 | L22: in (AI02,AI03) | M22: NULL | N22: NULL
B23: MNGMNT_PRDCT | C23: PRDCT0103 | D23: =TRIM(VLOOKUP(C23,codelist!$B:$C,2,FALSE)) -> Bonds Portfolio | E23: NULL | F23: NULL | G23: in (AI0490) | H23: NULL | I23: NULL | J23: 13 | L23: in (AI0490) | M23: NULL | N23: NULL
B24: MNGMNT_PRDCT | C24: PRDCT0201 | D24: =TRIM(VLOOKUP(C24,codelist!$B:$C,2,FALSE)) -> Contingent risks | E24: NULL | F24: NULL | G24: in (AI10) | H24: NULL | I24: NULL | J24: 14 | L24: in (AI10) | M24: NULL | N24: NULL
B25: MNGMNT_PRDCT | C25: PRDCT010103 | D25: =TRIM(VLOOKUP(C25,codelist!$B:$C,2,FALSE)) -> Other Loans & Advances | E25: NULL | F25: NULL | G25: NULL | H25: NULL | I25: NULL | J25: 15 | L25: NULL | M25: NULL | N25: NULL

Sheet Emai CdG
B3: campo | C3: valor_campo | D3: cnmetanseg | E3: ccentro_gestor | F3: ckmetamis | G3: cmetacom | H3: ckarea | I3: ordem
B4: MNGMNT_PRDCT | C4: PRDCT0304 | D4: NULL | E4: NULL | F4: NULL | G4: NULL | H4: in (AN02040300, AN02040400) | I4: 1
B5: MNGMNT_PRDCT | C5: PRDCT0303 | D5: NULL | E5: NULL | F5: NULL | G5: NULL | H5: AN02030200 | I5: 2
B6: MNGMNT_PRDCT | C6: PRDCT01010201 | D6: NULL | E6: NULL | F6: NULL | G6: NULL | H6: AN02030300 | I6: 3
B7: MNGMNT_PRDCT | C7: PRDCT01010202 | D7: NULL | E7: NULL | F7: NULL | G7: NULL | H7: AN02030400 | I7: 4
B8: MNGMNT_PRDCT | C8: PRDCT01010204 | D8: NULL | E8: NULL | F8: NULL | G8: NULL | H8: AN02010200 | I8: 5
B9: MNGMNT_PRDCT | C9: PRDCT01010205 | D9: NULL | E9: NULL | F9: NULL | G9: NULL | H9: AN02030600 | I9: 6
B10: MNGMNT_PRDCT | C10: PRDCT01010206 | D10: NULL | E10: NULL | F10: NULL | G10: NULL | H10: AN02020400 | I10: 7
B11: MNGMNT_PRDCT | C11: PRDCT01010207 | D11: NULL | E11: NULL | F11: NULL | G11: NULL | H11: AN02020200 | I11: 8
B12: MNGMNT_PRDCT | C12: PRDCT0203 | D12: NULL | E12: NULL | F12: NULL | G12: NULL | H12: in (AN02040100, AN02040200, GB2001, AN02050100, AN02040700) | I12: 9
B13: MNGMNT_PRDCT | C13: PRDCT0301 | D13: NULL | E13: NULL | F13: NULL | G13: NULL | H13: AN02050600 | I13: 10
B14: MNGMNT_PRDCT | C14: PRDCT0302 | D14: NULL | E14: NULL | F14: NULL | G14: NULL | H14: GB0510 | I14: 11
B15: MNGMNT_PRDCT | C15: PRDCT010101 | D15: NULL | E15: NULL | F15: in (AI02,AI03) | G15: NULL | H15: NULL | I15: 12
... B18: MNGMNT_PRDCT | C18: PRDCT010103 | D18: NULL | E18: NULL | F18: NULL | G18: NULL | H18: NULL | I18: 15

Sheet Novos códigos
A1: Código | B1: English Description
A2: AN | B2: Total Business Area
A3: WM | B3: Wealth Management and Insurance
A4: BP | B4: Private Banking
A5: AN01010100 | B5: Private Wealth
A6: AN01050000 | B6: Private Banking Rest
A7: GA | B7: Asset Management
A8: AN03010000 | B8: Investment Funds
A9: AN03020000 | B9: Pension Funds
A10: SE | B10: Insurance
A11: AN03030000 | B11: Insurance.
A12: PIW | B12: Investment Platforms Wealth
... A88: EL | B88: Intra-Group Reassignment

Sheet Códigos antigos
A1: cod_atributo_dim | B1: nome_atributo_dim | C1: desc_atributo_dim
A2: AN | B2: Total Área de Negocio | C2: Total Área de Negocio
A3: AC | B3: Actividades Corporativas | C3: Actividades Corporativas
A4: AC05 | B4: Gestión Financiera | C4: Gestión Financiera
A5: AN04010500 | B5: Financiación | C5: Financiación
A6: AN04010600 | B6: Coberturas estratégicas | C6: Coberturas estratégicas
A7: AN04010400 | B7: Coberturas de balance | C7: Coberturas de balance
A8: AN04010100 | B8: ALCO | C8: ALCO
A9: AN04010700 | B9: Financiación intragrupo | C9: Financiación intragrupo
A10: AC10 | B10: Resto | C10: Resto
A11: AC1010 | B11: Otros | C11: Otros
A12: AN04030000 | B12: Resto Actividades Corporativas | C12: Resto Actividades Corporativas
... A102: AN21010100 | B102: Promemoria. | C102: Promemoria.

Sheet codelist
B3: Code | C3: Description
C4: On Balance (excluding HfT)
C5: Loans & advances (customers and credit institutions)
B6: PRDCT010101 | C6: Mortgages
C7: Products Added value CIB
B8: PRDCT01010201 | C8: Project & Acquisition Finance
B9: PRDCT01010202 | C9: Syndicated Loans
B10: PRDCT01010203 | C10: Capital Finance
B11: PRDCT01010204 | C11: Asset Based Finance (ABF)
B12: PRDCT01010205 | C12: Leveraged Finance
B13: PRDCT01010206 | C13: Export & Agency Finance
B14: PRDCT01010207 | C14: Trade & Working Capital Solutions
B15: PRDCT010103 | C15: Other Loans & Advances
B16: PRDCT0102 | C16: Renting / Operating Leasing
B17: PRDCT0103 | C17: Bonds Portfolio
C18: Off Balance
B19: PRDCT0201 | C19: Contingent risks
B20: PRDCT0202 | C20: Undrawn balances Committed
B21: PRDCT0203 | C21: Derivatives
C22: Advisory & Facilitation services
B23: PRDCT0301 | C23: Mergers & Acquisitions (M&A)
B24: PRDCT0302 | C24: Equity Capital Markets (ECM)
B25: PRDCT0303 | C25: Debt Capital Markets (DCM)
B26: PRDCT0304 | C26: Securitization
B27: PRDCT0305 | C27: Project & Acquisition Finance (Advisory)
C28: Liabilities
B29: PRDCT0401 | C29: Financing instruments issued
B30: PRDCT0402 | C30: Deposits
B31: PRDCT0403 | C31: Other Liabilities

Sheet Email cátia&irina
A1: campo | B1: valor_campo | C1: Descritivo valor_campo | D1: ckmetamis | E1: ckarea | F1: Descritivo antigo ckarea | G1: Novo código | H1: Descritivo Novo
A2: MNGMNT_PRDCT | B2: PRDCT0304 | C2: =+VLOOKUP(B2,codelist!$B$4:$C$31,2,FALSE) -> Securitization | D2: in (S,UGP000,A,P) | E2: GB0530 | F2: Debt Capital Markets & Securitization | G2: AN02030200 | H2: DCM
A3: MNGMNT_PRDCT | B3: PRDCT0303 | C3: =+VLOOKUP(B3,codelist!$B$4:$C$31,2,FALSE) -> Debt Capital Markets (DCM) | D3: not in (S,UGP000,A,P) | E3: GB0530 | F3: Debt Capital Markets & Securitization | G3: AN02030200 | H3: DCM
A4: MNGMNT_PRDCT | B4: PRDCT01010201 | C4: =+VLOOKUP(B4,codelist!$B$4:$C$31,2,FALSE) -> Project & Acquisition Finance | D4: NULL | E4: GB0525 | F4: Project and Acquisition Finance | G4: AN02030300 | H4: Project and Acquisition Finance.
A5: MNGMNT_PRDCT | B5: PRDCT01010202 | C5: =+VLOOKUP(B5,codelist!$B$4:$C$31,2,FALSE) -> Syndicated Loans | D5: NULL | E5: GB0540 | F5: Sindicados | G5: AN02030400 | H5: Syndicated Loans
A6: MNGMNT_PRDCT | B6: PRDCT01010204 | C6: =+VLOOKUP(B6,codelist!$B$4:$C$31,2,FALSE) -> Asset Based Finance (ABF) | D6: NULL | E6: GB0535 | F6: ACS - Asset & Capital Structuring
A7: MNGMNT_PRDCT | B7: PRDCT01010205 | C7: =+VLOOKUP(B7,codelist!$B$4:$C$31,2,FALSE) -> Leveraged Finance | D7: NULL | E7: GB0545 | F7: Leveraged Finance | G7: AN02030600 | H7: Leveraged Finance
A8: MNGMNT_PRDCT | B8: PRDCT01010206 | C8: =+VLOOKUP(B8,codelist!$B$4:$C$31,2,FALSE) -> Export & Agency Finance | D8: NULL | E8: GB1025 | F8: Export & Agency Finance | G8: AN02020400 | H8: Export & Agency Finance
A9: MNGMNT_PRDCT | B9: PRDCT01010207 | C9: =+VLOOKUP(B9,codelist!$B$4:$C$31,2,FALSE) -> Trade & Working Capital Solutions | D9: NULL | E9: GB1015 | F9: Trade & WCS | G9: AN02020200 | H9: Trade & WCS
A10: MNGMNT_PRDCT | B10: PRDCT0203 | C10: =+VLOOKUP(B10,codelist!$B$4:$C$31,2,FALSE) -> Derivatives | D10: NULL | E10: GB2005 | F10: Sales Mercados
A11: MNGMNT_PRDCT | B11: PRDCT0301 | C11: =+VLOOKUP(B11,codelist!$B$4:$C$31,2,FALSE) -> Mergers & Acquisitions (M&A) | D11: NULL | E11: GB0505 | F11: M & A - Mergers and Acquisitions | G11: AN02050600 | H11: M & A - Mergers and Acquisitions
A12: MNGMNT_PRDCT | B12: PRDCT0302 | C12: =+VLOOKUP(B12,codelist!$B$4:$C$31,2,FALSE) -> Equity Capital Markets (ECM) | D12: NULL | E12: GB0510 | F12: ECM - Equity Capital Markets | G12: GB0510 | H12: ECM - Equity Capital Markets & Others
A13: MNGMNT_PRDCT | B13: PRDCT010101 | C13: =+VLOOKUP(B13,codelist!$B$4:$C$31,2,FALSE) -> Mortgages | D13: in (AI02,AI03) | E13: NULL
A14: MNGMNT_PRDCT | B14: PRDCT0103 | C14: =+VLOOKUP(B14,codelist!$B$4:$C$31,2,FALSE) -> Bonds Portfolio | D14: in (AI0490) | E14: NULL
A15: MNGMNT_PRDCT | B15: PRDCT0201 | C15: =+VLOOKUP(B15,codelist!$B$4:$C$31,2,FALSE) -> Contingent risks | D15: in (AI10) | E15: NULL
A16: MNGMNT_PRDCT | B16: PRDCT010103 | C16: =+VLOOKUP(B16,codelist!$B$4:$C$31,2,FALSE) -> Other Loans & Advances | D16: NULL | E16: NULL

Sheet Email cátia&irina_
B2: 1) Situações detetadas após a alteração das ckareas
B4: Situação 1: Deixamos de ter o conceito de Sales Mercados. Do lado da Corporação o descritivo seria Derivatives e temos esse conceito a desagregar em 2 códigos de ckarea, mas o Luis Silva sugeriu a proposta entre um dos dois códigos
B6: As-Is | G6: Proposta | J6: Código old | L6: Código new
B7: campo | C7: valor_campo | D7: Descritivo valor_campo | E7: ckarea | F7: Descritivo antigo ckarea | G7: Novo código | H7: Descritivo Novo | J7: ckarea | K7: Descritivo | L7: ckarea | M7: Descritivo
B8: MNGMNT_PRDCT | C8: PRDCT0203 | D8: =+VLOOKUP(C8,codelist!$B$4:$C$31,2,FALSE) -> Derivatives | E8: GB2005 | F8: Sales Mercados | G8: AN02040100 | H8: FX | J8: GB2005 | K8: Sales Mercados | L8: AN02040100 | M8: FX
G9: AN02040200 | H9: Rates | L9: AN02040200 | M9: Rates
B11: Situação 2: Descritivo era mais agregador e agora passamos a ter o conceito menos agregado.
B12: Proposta 2.1:
B13: As-Is | G13: Proposta | J13: Código old | L13: Código new
B14: campo | C14: valor_campo | D14: Descritivo valor_campo | E14: ckarea | F14: Descritivo antigo ckarea | G14: Novo código | H14: Descritivo Novo | J14: ckarea | K14: Descritivo | L14: ckarea | M14: Descritivo
B15: MNGMNT_PRDCT | C15: PRDCT0304 | D15: Securitization | E15: GB0530 | F15: Debt Capital Markets & Securitization | G15: AN02030200 | H15: DCM | J15: GB0530 | K15: Debt Capital Markets & Securitization | L15: AN02030200 | M15: DCM
B16: MNGMNT_PRDCT | C16: PRDCT0303 | D16: Debt Capital Markets (DCM) | E16: GB0530 | F16: Debt Capital Markets & Securitization | G16: AN02030200 | H16: DCM | L16: AN02040300 | M16: Securitization Products
L17: AN02040400 | M17: Securitization Finance
B18: Proposta 2.2:
B19: As-Is | G19: Proposta
B20: campo | C20: valor_campo | D20: Descritivo valor_campo | E20: ckarea | F20: Descritivo antigo ckarea | G20: Novo código | H20: Descritivo Novo
B21: MNGMNT_PRDCT | C21: PRDCT0304 | D21: Securitization | E21: GB0530 | F21: Debt Capital Markets & Securitization | G21: AN02040300 | H21: Securitization Products
G22: AN02040400 | H22: Securitization Finance
B23: MNGMNT_PRDCT | C23: PRDCT0303 | D23: Debt Capital Markets (DCM) | E23: GB0530 | F23: Debt Capital Markets & Securitization | G23: AN02030200 | H23: DCM
