Workbook

Sheet QUERY BUILDER
A1: COD_KPI | B1: CAMPO | C1: THEN | D1: DESCRIÇÃO | E1: REFDATE | F1: TIPOLOGIA_TESTE | G1: TABELA | H1: CASE WHEN | I1: ELSE | J1: DIF | K1: QUERY | L1: Comentar
A2: v_1_0001 | B2: 0010_row_nmbr | C2: 1 | D2: =+VLOOKUP(A2,Descrição!A:K,11,FALSE) -> Testar se o campo está a missing. O campo tem de ser reportado. | E2: "& RefDate &" | F2: REGULAMENTAR | G2: BU_LOANTAPE_WORK.OUT_B0200_MAIN_LIABILITIES | H2: `0010_row_nmbr` IS NULL or cast(`0010_row_nmbr` as string)='' | I2: =+IF(C2=1,0,1) -> 0 | J2: =+IF(C2=0,"THEN NULL ELSE X.CHAVE_IT END","THEN X.CHAVE_IT ELSE NULL END") -> THEN X.CHAVE_IT ELSE NULL END | K2: ="UNION ALL SELECT '"&E2&"' AS REF_DATE, '"&A2&"' AS COD_KPI, '"&F2&"' AS TIPOLOGIA_TESTE, '"&D2&"' AS DESCRIÇÃO, '"&G2&"' AS TABELA, '"&B2&"' AS CAMPO, COUNT(*) AS NUM_REG, SUM(IF("&H2&","&C2&" ,"&I2&")) AS NUM_REG_DIF, GROUP_CONCAT(CASE WHEN "&H2&" "&J2&", '; ') AS DETALHE FROM (SELECT *, 0020_UNIQ_ID AS CHAVE_IT, "&B2&" AS CAMPO_IT FROM "&G2&" WHERE REF_DATE='"&E2&"')X GROUP BY 1" -> UNION ALL SELECT '"& RefDate &"' AS REF_DATE, 'v_1_0001' AS COD_KPI, 'REGULAMENTAR' AS TIPOLOGIA_TESTE, 'Testar se o campo está a missing. O campo tem de ser reportado.' AS DESCRIÇÃO, 'BU_LOANTAPE_WORK.OUT_B0200_MAIN_LIABILITIES' AS TABELA, '0010_row_nmbr' AS CAMPO, COUNT(*) AS NUM_REG, SUM(IF(`0010_row_nmbr` IS NULL or cast(`0010_row_nmbr` as string)='',1 ,0)) AS NUM_REG_DIF, GROUP_CONCAT(CASE WHEN `0010_row_nmbr` IS NULL or cast(`0010_row_nmbr` as string)='' THEN X.CHAVE_IT ELSE NULL END, '; ') AS DETALHE FROM (SELECT *, 0020_UNIQ_ID AS CHAVE_IT, 0010_row_nmbr AS CAMPO_IT FROM BU_LOANTAPE_WORK.OUT_B0200_MAIN_LIABILITIES WHERE REF_DATE='"& RefDate &"')X GROUP BY 1
A3: v_1_0002 | B3: 0030_uniq_id_knwn_cntrprty | C3: 1 | D3: =+VLOOKUP(A3,Descrição!A:K,11,FALSE) -> Testar se o campo está a missing. O campo tem de ser reportado. | E3: "& RefDate &" | F3: REGULAMENTAR | G3: BU_LOANTAPE_WORK.OUT_B0200_MAIN_LIABILITIES | H3: `0030_uniq_id_knwn_cntrprty` = '' | I3: =+IF(C3=1,0,1) -> 0 | J3: =+IF(C3=0,"THEN NULL ELSE X.CHAVE_IT END","THEN X.CHAVE_IT ELSE NULL END") -> THEN X.CHAVE_IT ELSE NULL END | K3: ="UNION ALL SELECT '"&E3&"' AS REF_DATE, '"&A3&"' AS COD_KPI, '"&F3&"' AS TIPOLOGIA_TESTE, '"&D3&"' AS DESCRIÇÃO, '"&G3&"' AS TABELA, '"&B3&"' AS CAMPO, COUNT(*) AS NUM_REG, SUM(IF("&H3&","&C3&" ,"&I3&")) AS NUM_REG_DIF, GROUP_CONCAT(CASE WHEN "&H3&" "&J3&", '; ') AS DETALHE FROM (SELECT *, 0020_UNIQ_ID AS CHAVE_IT, "&B3&" AS CAMPO_IT FROM "&G3&" WHERE REF_DATE='"&E3&"')X GROUP BY 1" -> UNION ALL SELECT '"& RefDate &"' AS REF_DATE, 'v_1_0002' AS COD_KPI, 'REGULAMENTAR' AS TIPOLOGIA_TESTE, 'Testar se o campo está a missing. O campo tem de ser reportado.' AS DESCRIÇÃO, 'BU_LOANTAPE_WORK.OUT_B0200_MAIN_LIABILITIES' AS TABELA, '0030_uniq_id_knwn_cntrprty' AS CAMPO, COUNT(*) AS NUM_REG, SUM(IF(`0030_uniq_id_knwn_cntrprty` = '',1 ,0)) AS NUM_REG_DIF, GROUP_CONCAT(CASE WHEN `0030_uniq_id_knwn_cntrprty` = '' THEN X.CHAVE_IT ELSE NULL END, '; ') AS DETALHE FROM (SELECT *, 0020_UNIQ_ID AS CHAVE_IT, 0030_uniq_id_knwn_cntrprty AS CAMPO_IT FROM BU_LOANTAPE_WORK.OUT_B0200_MAIN_LIABILITIES WHERE REF_DATE='"& RefDate &"')X GROUP BY 1
A4: v_1_0003 | B4: 0040_typ_uniq_id_knwn_cntrprty | C4: 1 | D4: =+VLOOKUP(A4,Descrição!A:K,11,FALSE) -> Testar se o campo está a missing. O campo tem de ser reportado. | E4: "& RefDate &" | F4: REGULAMENTAR | G4: BU_LOANTAPE_WORK.OUT_B0200_MAIN_LIABILITIES | H4: `0040_typ_uniq_id_knwn_cntrprty` = '' | I4: =+IF(C4=1,0,1) -> 0 | J4: =+IF(C4=0,"THEN NULL ELSE X.CHAVE_IT END","THEN X.CHAVE_IT ELSE NULL END") -> THEN X.CHAVE_IT ELSE NULL END | K4: ="UNION ALL SELECT '"&E4&"' AS REF_DATE, '"&A4&"' AS COD_KPI, '"&F4&"' AS TIPOLOGIA_TESTE, '"&D4&"' AS DESCRIÇÃO, '"&G4&"' AS TABELA, '"&B4&"' AS CAMPO, COUNT(*) AS NUM_REG, SUM(IF("&H4&","&C4&" ,"&I4&")) AS NUM_REG_DIF, GROUP_CONCAT(CASE WHEN "&H4&" "&J4&", '; ') AS DETALHE FROM (SELECT *, 0020_UNIQ_ID AS CHAVE_IT, "&B4&" AS CAMPO_IT FROM "&G4&" WHERE REF_DATE='"&E4&"')X GROUP BY 1" -> UNION ALL SELECT '"& RefDate &"' AS REF_DATE, 'v_1_0003' AS COD_KPI, 'REGULAMENTAR' AS TIPOLOGIA_TESTE, 'Testar se o campo está a missing. O campo tem de ser reportado.' AS DESCRIÇÃO, 'BU_LOANTAPE_WORK.OUT_B0200_MAIN_LIABILITIES' AS TABELA, '0040_typ_uniq_id_knwn_cntrprty' AS CAMPO, COUNT(*) AS NUM_REG, SUM(IF(`0040_typ_uniq_id_knwn_cntrprty` = '' ,1 ,0)) AS NUM_REG_DIF, GROUP_CONCAT(CASE WHEN `0040_typ_uniq_id_knwn_cntrprty` = '' THEN X.CHAVE_IT ELSE NULL END, '; ') AS DETALHE FROM (SELECT *, 0020_UNIQ_ID AS CHAVE_IT, 0040_typ_uniq_id_knwn_cntrprty AS CAMPO_IT FROM BU_LOANTAPE_WORK.OUT_B0200_MAIN_LIABILITIES WHERE REF_DATE='"& RefDate &"')X GROUP BY 1
A5: v_1_0004 | B5: 0070_cntrct_crrncy | C5: 1 | D5: =+VLOOKUP(A5,Descrição!A:K,11,FALSE) -> Testar se o campo está a missing. O campo tem de ser reportado. | E5: "& RefDate &" | F5: REGULAMENTAR | G5: BU_LOANTAPE_WORK.OUT_B0200_MAIN_LIABILITIES | H5: `0070_cntrct_crrncy` = '' | I5: =+IF(C5=1,0,1) -> 0 | J5: =+IF(C5=0,"THEN NULL ELSE X.CHAVE_IT END","THEN X.CHAVE_IT ELSE NULL END") -> THEN X.CHAVE_IT ELSE NULL END | K5: ="UNION ALL SELECT '"&E5&"' AS REF_DATE, '"&A5&"' AS COD_KPI, '"&F5&"' AS TIPOLOGIA_TESTE, '"&D5&"' AS DESCRIÇÃO, '"&G5&"' AS TABELA, '"&B5&"' AS CAMPO, COUNT(*) AS NUM_REG, SUM(IF("&H5&","&C5&" ,"&I5&")) AS NUM_REG_DIF, GROUP_CONCAT(CASE WHEN "&H5&" "&J5&", '; ') AS DETALHE FROM (SELECT *, 0020_UNIQ_ID AS CHAVE_IT, "&B5&" AS CAMPO_IT FROM "&G5&" WHERE REF_DATE='"&E5&"')X GROUP BY 1" -> UNION ALL SELECT '"& RefDate &"' AS REF_DATE, 'v_1_0004' AS COD_KPI, 'REGULAMENTAR' AS TIPOLOGIA_TESTE, 'Testar se o campo está a missing. O campo tem de ser reportado.' AS DESCRIÇÃO, 'BU_LOANTAPE_WORK.OUT_B0200_MAIN_LIABILITIES' AS TABELA, '0070_cntrct_crrncy' AS CAMPO, COUNT(*) AS NUM_REG, SUM(IF(`0070_cntrct_crrncy` = '',1 ,0)) AS NUM_REG_DIF, GROUP_CONCAT(CASE WHEN `0070_cntrct_crrncy` = '' THEN X.CHAVE_IT ELSE NULL END, '; ') AS DETALHE FROM (SELECT *, 0020_UNIQ_ID AS CHAVE_IT, 0070_cntrct_crrncy AS CAMPO_IT FROM BU_LOANTAPE_WORK.OUT_B0200_MAIN_LIABILITIES WHERE REF_DATE='"& RefDate &"')X GROUP BY 1
A6: v_1_0005 | B6: 0080_otstndng_prncpl_amnt | C6: 1 | D6: =+VLOOKUP(A6,Descrição!A:K,11,FALSE) -> Testar se o campo está a missing. O campo deve ser reportado para passivos não estruturados. | E6: "& RefDate &" | F6: REGULAMENTAR | G6: BU_LOANTAPE_WORK.OUT_B0200_MAIN_LIABILITIES | H6: (`0080_otstndng_prncpl_amnt` IS NULL OR CAST(`0080_otstndng_prncpl_amnt` AS STRING) = '') AND `0250_strctrd_prdct` IN ('Non-Structured/Vanilla', 'Other non-standard terms') | I6: =+IF(C6=1,0,1) -> 0 | J6: =+IF(C6=0,"THEN NULL ELSE X.CHAVE_IT END","THEN X.CHAVE_IT ELSE NULL END") -> THEN X.CHAVE_IT ELSE NULL END | K6: ="UNION ALL SELECT '"&E6&"' AS REF_DATE, '"&A6&"' AS COD_KPI, '"&F6&"' AS TIPOLOGIA_TESTE, '"&D6&"' AS DESCRIÇÃO, '"&G6&"' AS TABELA, '"&B6&"' AS CAMPO, COUNT(*) AS NUM_REG, SUM(IF("&H6&","&C6&" ,"&I6&")) AS NUM_REG_DIF, GROUP_CONCAT(CASE WHEN "&H6&" "&J6&", '; ') AS DETALHE FROM (SELECT *, 0020_UNIQ_ID AS CHAVE_IT, "&B6&" AS CAMPO_IT FROM "&G6&" WHERE REF_DATE='"&E6&"')X GROUP BY 1" -> UNION ALL SELECT '"& RefDate &"' AS REF_DATE, 'v_1_0005' AS COD_KPI, 'REGULAMENTAR' AS TIPOLOGIA_TESTE, 'Testar se o campo está a missing. O campo deve ser reportado para passivos não estruturados.' AS DESCRIÇÃO, 'BU_LOANTAPE_WORK.OUT_B0200_MAIN_LIABILITIES' AS TABELA, '0080_otstndng_prncpl_amnt' AS CAMPO, COUNT(*) AS NUM_REG, SUM(IF((`0080_otstndng_prncpl_amnt` IS NULL OR CAST(`0080_otstndng_prncpl_amnt` AS STRING) = '') AND `0250_strctrd_prdct` IN ('Non-Structured/Vanilla', 'Other non-standard terms'),1 ,0)) AS NUM_REG_DIF, GROUP_CONCAT(CASE WHEN (`0080_otstndng_prncpl_amnt` IS NULL OR CAST(`0080_otstndng_prncpl_amnt` AS STRING) = '') AND `0250_strctrd_prdct` IN ('Non-Structured/Vanilla', 'Other non-standard terms') THEN X.CHAVE_IT ELSE NULL END, '; ') AS DETALHE FROM (SELECT *, 0020_UNIQ_ID AS CHAVE_IT, 0080_otstndng_prncpl_amnt AS CAMPO_IT FROM BU_LOANTAPE_WORK.OUT_B0200_MAIN_LIABILITIES WHERE REF_DATE='"& RefDate &"')X GROUP BY 1
A7: v_1_0006 | B7: 0080_otstndng_prncpl_amnt | C7: 1 | D7: =+VLOOKUP(A7,Descrição!A:K,11,FALSE) -> Alerta: Testar se o campo está a missing. Para passivos estruturados, o campo tem de ser reportado se a informação existir. | E7: "& RefDate &" | F7: REGULAMENTAR | G7: BU_LOANTAPE_WORK.OUT_B0200_MAIN_LIABILITIES | H7: (`0080_otstndng_prncpl_amnt` IS NULL OR CAST(`0080_otstndng_prncpl_amnt` AS STRING) = '') AND `0250_strctrd_prdct` IN ('Structured', 'Only structured coupon') | I7: =+IF(C7=1,0,1) -> 0 | J7: =+IF(C7=0,"THEN NULL ELSE X.CHAVE_IT END","THEN X.CHAVE_IT ELSE NULL END") -> THEN X.CHAVE_IT ELSE NULL END | K7: ="UNION ALL SELECT '"&E7&"' AS REF_DATE, '"&A7&"' AS COD_KPI, '"&F7&"' AS TIPOLOGIA_TESTE, '"&D7&"' AS DESCRIÇÃO, '"&G7&"' AS TABELA, '"&B7&"' AS CAMPO, COUNT(*) AS NUM_REG, SUM(IF("&H7&","&C7&" ,"&I7&")) AS NUM_REG_DIF, GROUP_CONCAT(CASE WHEN "&H7&" "&J7&", '; ') AS DETALHE FROM (SELECT *, 0020_UNIQ_ID AS CHAVE_IT, "&B7&" AS CAMPO_IT FROM "&G7&" WHERE REF_DATE='"&E7&"')X GROUP BY 1" -> UNION ALL SELECT '"& RefDate &"' AS REF_DATE, 'v_1_0006' AS COD_KPI, 'REGULAMENTAR' AS TIPOLOGIA_TESTE, 'Alerta: Testar se o campo está a missing. Para passivos estruturados, o campo tem de ser reportado se a informação existir.' AS DESCRIÇÃO, 'BU_LOANTAPE_WORK.OUT_B0200_MAIN_LIABILITIES' AS TABELA, '0080_otstndng_prncpl_amnt' AS CAMPO, COUNT(*) AS NUM_REG, SUM(IF((`0080_otstndng_prncpl_amnt` IS NULL OR CAST(`0080_otstndng_prncpl_amnt` AS STRING) = '') AND `0250_strctrd_prdct` IN ('Structured', 'Only structured coupon'),1 ,0)) AS NUM_REG_DIF, GROUP_CONCAT(CASE WHEN (`0080_otstndng_prncpl_amnt` IS NULL OR CAST(`0080_otstndng_prncpl_amnt` AS STRING) = '') AND `0250_strctrd_prdct` IN ('Structured', 'Only structured coupon') THEN X.CHAVE_IT ELSE NULL END, '; ') AS DETALHE FROM (SELECT *, 0020_UNIQ_ID AS CHAVE_IT, 0080_otstndng_prncpl_amnt AS CAMPO_IT FROM BU_LOANTAPE_WORK.OUT_B0200_MAIN_LIABILITIES WHERE REF_DATE='"& RefDate &"')X GROUP BY 1
A8: v_1_0007 | B8: 0090_prtn_amnt_rprtng_entty | C8: 1 | D8: =+VLOOKUP(A8,Descrição!A:K,11,FALSE) -> Testar se o campo está a missing. O campo deve ser reportado para valores mobiliários. | E8: "& RefDate &" | F8: REGULAMENTAR | G8: BU_LOANTAPE_WORK.OUT_B0200_MAIN_LIABILITIES | H8: (`0090_prtn_amnt_rprtng_entty` IS NULL OR CAST(`0090_prtn_amnt_rprtng_entty` AS STRING) = '') AND `0040_typ_uniq_id_knwn_cntrprty` = 'ISIN' | I8: =+IF(C8=1,0,1) -> 0 | J8: =+IF(C8=0,"THEN NULL ELSE X.CHAVE_IT END","THEN X.CHAVE_IT ELSE NULL END") -> THEN X.CHAVE_IT ELSE NULL END | K8: ="UNION ALL SELECT '"&E8&"' AS REF_DATE, '"&A8&"' AS COD_KPI, '"&F8&"' AS TIPOLOGIA_TESTE, '"&D8&"' AS DESCRIÇÃO, '"&G8&"' AS TABELA, '"&B8&"' AS CAMPO, COUNT(*) AS NUM_REG, SUM(IF("&H8&","&C8&" ,"&I8&")) AS NUM_REG_DIF, GROUP_CONCAT(CASE WHEN "&H8&" "&J8&", '; ') AS DETALHE FROM (SELECT *, 0020_UNIQ_ID AS CHAVE_IT, "&B8&" AS CAMPO_IT FROM "&G8&" WHERE REF_DATE='"&E8&"')X GROUP BY 1" -> UNION ALL SELECT '"& RefDate &"' AS REF_DATE, 'v_1_0007' AS COD_KPI, 'REGULAMENTAR' AS TIPOLOGIA_TESTE, 'Testar se o campo está a missing. O campo deve ser reportado para valores mobiliários.' AS DESCRIÇÃO, 'BU_LOANTAPE_WORK.OUT_B0200_MAIN_LIABILITIES' AS TABELA, '0090_prtn_amnt_rprtng_entty' AS CAMPO, COUNT(*) AS NUM_REG, SUM(IF((`0090_prtn_amnt_rprtng_entty` IS NULL OR CAST(`0090_prtn_amnt_rprtng_entty` AS STRING) = '') AND `0040_typ_uniq_id_knwn_cntrprty` = 'ISIN',1 ,0)) AS NUM_REG_DIF, GROUP_CONCAT(CASE WHEN (`0090_prtn_amnt_rprtng_entty` IS NULL OR CAST(`0090_prtn_amnt_rprtng_entty` AS STRING) = '') AND `0040_typ_uniq_id_knwn_cntrprty` = 'ISIN' THEN X.CHAVE_IT ELSE NULL END, '; ') AS DETALHE FROM (SELECT *, 0020_UNIQ_ID AS CHAVE_IT, 0090_prtn_amnt_rprtng_entty AS CAMPO_IT FROM BU_LOANTAPE_WORK.OUT_B0200_MAIN_LIABILITIES WHERE REF_DATE='"& RefDate &"')X GROUP BY 1
A9: v_1_0008 | B9: 0100_accrd_intrst_instrmnt | C9: 1 | D9: =+VLOOKUP(A9,Descrição!A:K,11,FALSE) -> Testar se o campo está a missing. Para passivos não estruturados que não sejam zero coupon bonds emitidas com desconto, este campo deve ser reportado. | E9: "& RefDate &" | F9: REGULAMENTAR | G9: BU_LOANTAPE_WORK.OUT_B0200_MAIN_LIABILITIES | H9: (`0100_accrd_intrst_instrmnt` IS NULL OR CAST(`0100_accrd_intrst_instrmnt` AS STRING) = '') AND `0250_strctrd_prdct` IN ('Non-Structured', 'Other non-standard terms') AND `0240_zero_coupon` != 'ZCB issued at discount' | I9: =+IF(C9=1,0,1) -> 0 | J9: =+IF(C9=0,"THEN NULL ELSE X.CHAVE_IT END","THEN X.CHAVE_IT ELSE NULL END") -> THEN X.CHAVE_IT ELSE NULL END | K9: ="UNION ALL SELECT '"&E9&"' AS REF_DATE, '"&A9&"' AS COD_KPI, '"&F9&"' AS TIPOLOGIA_TESTE, '"&D9&"' AS DESCRIÇÃO, '"&G9&"' AS TABELA, '"&B9&"' AS CAMPO, COUNT(*) AS NUM_REG, SUM(IF("&H9&","&C9&" ,"&I9&")) AS NUM_REG_DIF, GROUP_CONCAT(CASE WHEN "&H9&" "&J9&", '; ') AS DETALHE FROM (SELECT *, 0020_UNIQ_ID AS CHAVE_IT, "&B9&" AS CAMPO_IT FROM "&G9&" WHERE REF_DATE='"&E9&"')X GROUP BY 1" -> UNION ALL SELECT '"& RefDate &"' AS REF_DATE, 'v_1_0008' AS COD_KPI, 'REGULAMENTAR' AS TIPOLOGIA_TESTE, 'Testar se o campo está a missing. Para passivos não estruturados que não sejam zero coupon bonds emitidas com desconto, este campo deve ser reportado.' AS DESCRIÇÃO, 'BU_LOANTAPE_WORK.OUT_B0200_MAIN_LIABILITIES' AS TABELA, '0100_accrd_intrst_instrmnt' AS CAMPO, COUNT(*) AS NUM_REG, SUM(IF((`0100_accrd_intrst_instrmnt` IS NULL OR CAST(`0100_accrd_intrst_instrmnt` AS STRING) = '') AND `0250_strctrd_prdct` IN ('Non-Structured', 'Other non-standard terms') AND `0240_zero_coupon` != 'ZCB issued at discount',1 ,0)) AS NUM_REG_DIF, GROUP_CONCAT(CASE WHEN (`0100_accrd_intrst_instrmnt` IS NULL OR CAST(`0100_accrd_intrst_instrmnt` AS STRING) = '') AND `0250_strctrd_prdct` IN ('Non-Structured', 'Other non-standard terms') AND `0240_zero_coupon` != 'ZCB issued at discount' THEN X.CHAVE_IT ELSE NULL END, '; ') AS DETALHE FROM (SELECT *, 0020_UNIQ_ID AS CHAVE_IT, 0100_accrd_intrst_instrmnt AS CAMPO_IT FROM BU_LOANTAPE_WORK.OUT_B0200_MAIN_LIABILITIES WHERE REF_DATE='"& RefDate &"')X GROUP BY 1
A10: v_1_0009 | B10: 0100_accrd_intrst_instrmnt | C10: 1 | D10: =+VLOOKUP(A10,Descrição!A:K,11,FALSE) -> Alerta: Testar se o campo está a missing. Para passivos estruturados, o campo tem de ser reportado se a informação existir. | E10: "& RefDate &" | F10: REGULAMENTAR | G10: BU_LOANTAPE_WORK.OUT_B0200_MAIN_LIABILITIES | H10: (`0100_accrd_intrst_instrmnt` IS NULL OR CAST(`0100_accrd_intrst_instrmnt` AS STRING) = '') AND `0250_strctrd_prdct` IN ('Structured', 'Only structured coupon') | I10: =+IF(C10=1,0,1) -> 0 | J10: =+IF(C10=0,"THEN NULL ELSE X.CHAVE_IT END","THEN X.CHAVE_IT ELSE NULL END") -> THEN X.CHAVE_IT ELSE NULL END | K10: ="UNION ALL SELECT '"&E10&"' AS REF_DATE, '"&A10&"' AS COD_KPI, '"&F10&"' AS TIPOLOGIA_TESTE, '"&D10&"' AS DESCRIÇÃO, '"&G10&"' AS TABELA, '"&B10&"' AS CAMPO, COUNT(*) AS NUM_REG, SUM(IF("&H10&","&C10&" ,"&I10&")) AS NUM_REG_DIF, GROUP_CONCAT(CASE WHEN "&H10&" "&J10&", '; ') AS DETALHE FROM (SELECT *, 0020_UNIQ_ID AS CHAVE_IT, "&B10&" AS CAMPO_IT FROM "&G10&" WHERE REF_DATE='"&E10&"')X GROUP BY 1" -> UNION ALL SELECT '"& RefDate &"' AS REF_DATE, 'v_1_0009' AS COD_KPI, 'REGULAMENTAR' AS TIPOLOGIA_TESTE, 'Alerta: Testar se o campo está a missing. Para passivos estruturados, o campo tem de ser reportado se a informação existir.' AS DESCRIÇÃO, 'BU_LOANTAPE_WORK.OUT_B0200_MAIN_LIABILITIES' AS TABELA, '0100_accrd_intrst_instrmnt' AS CAMPO, COUNT(*) AS NUM_REG, SUM(IF((`0100_accrd_intrst_instrmnt` IS NULL OR CAST(`0100_accrd_intrst_instrmnt` AS STRING) = '') AND `0250_strctrd_prdct` IN ('Structured', 'Only structured coupon') ,1 ,0)) AS NUM_REG_DIF, GROUP_CONCAT(CASE WHEN (`0100_accrd_intrst_instrmnt` IS NULL OR CAST(`0100_accrd_intrst_instrmnt` AS STRING) = '') AND `0250_strctrd_prdct` IN ('Structured', 'Only structured coupon') THEN X.CHAVE_IT ELSE NULL END, '; ') AS DETALHE FROM (SELECT *, 0020_UNIQ_ID AS CHAVE_IT, 0100_accrd_intrst_instrmnt AS CAMPO_IT FROM BU_LOANTAPE_WORK.OUT_B0200_MAIN_LIABILITIES WHERE REF_DATE='"& RefDate &"')X GROUP BY 1
A11: v_1_0010 | B11: 0120_otstndng_amnt | C11: 1 | D11: =+VLOOKUP(A11,Descrição!A:K,11,FALSE) -> Testar se o campo está a missing. Para passivos não estruturados, este campo deve ser declarado. | E11: "& RefDate &" | F11: REGULAMENTAR | G11: BU_LOANTAPE_WORK.OUT_B0200_MAIN_LIABILITIES | H11: (`0120_otstndng_amnt` IS NULL OR CAST(`0120_otstndng_amnt` AS STRING) = '') AND `0250_strctrd_prdct` IN ('Non-Structured/Vanilla', 'Other non-standard terms') | I11: =+IF(C11=1,0,1) -> 0 | J11: =+IF(C11=0,"THEN NULL ELSE X.CHAVE_IT END","THEN X.CHAVE_IT ELSE NULL END") -> THEN X.CHAVE_IT ELSE NULL END | K11: ="UNION ALL SELECT '"&E11&"' AS REF_DATE, '"&A11&"' AS COD_KPI, '"&F11&"' AS TIPOLOGIA_TESTE, '"&D11&"' AS DESCRIÇÃO, '"&G11&"' AS TABELA, '"&B11&"' AS CAMPO, COUNT(*) AS NUM_REG, SUM(IF("&H11&","&C11&" ,"&I11&")) AS NUM_REG_DIF, GROUP_CONCAT(CASE WHEN "&H11&" "&J11&", '; ') AS DETALHE FROM (SELECT *, 0020_UNIQ_ID AS CHAVE_IT, "&B11&" AS CAMPO_IT FROM "&G11&" WHERE REF_DATE='"&E11&"')X GROUP BY 1" -> UNION ALL SELECT '"& RefDate &"' AS REF_DATE, 'v_1_0010' AS COD_KPI, 'REGULAMENTAR' AS TIPOLOGIA_TESTE, 'Testar se o campo está a missing. Para passivos não estruturados, este campo deve ser declarado.' AS DESCRIÇÃO, 'BU_LOANTAPE_WORK.OUT_B0200_MAIN_LIABILITIES' AS TABELA, '0120_otstndng_amnt' AS CAMPO, COUNT(*) AS NUM_REG, SUM(IF((`0120_otstndng_amnt` IS NULL OR CAST(`0120_otstndng_amnt` AS STRING) = '') AND `0250_strctrd_prdct` IN ('Non-Structured/Vanilla', 'Other non-standard terms'),1 ,0)) AS NUM_REG_DIF, GROUP_CONCAT(CASE WHEN (`0120_otstndng_amnt` IS NULL OR CAST(`0120_otstndng_amnt` AS STRING) = '') AND `0250_strctrd_prdct` IN ('Non-Structured/Vanilla', 'Other non-standard terms') THEN X.CHAVE_IT ELSE NULL END, '; ') AS DETALHE FROM (SELECT *, 0020_UNIQ_ID AS CHAVE_IT, 0120_otstndng_amnt AS CAMPO_IT FROM BU_LOANTAPE_WORK.OUT_B0200_MAIN_LIABILITIES WHERE REF_DATE='"& RefDate &"')X GROUP BY 1
A12: v_1_0011 | B12: 0120_otstndng_amnt | C12: 1 | D12: =+VLOOKUP(A12,Descrição!A:K,11,FALSE) -> Alerta: Testar se o campo está a missing. Para passivos estruturados, o campo tem de ser reportado se a informação existir. | E12: "& RefDate &" | F12: REGULAMENTAR | G12: BU_LOANTAPE_WORK.OUT_B0200_MAIN_LIABILITIES | H12: (`0120_otstndng_amnt` IS NULL OR CAST(`0120_otstndng_amnt` AS STRING) = '') AND `0250_strctrd_prdct` NOT IN ('Structured', 'Only structured coupon') | I12: =+IF(C12=1,0,1) -> 0 | J12: =+IF(C12=0,"THEN NULL ELSE X.CHAVE_IT END","THEN X.CHAVE_IT ELSE NULL END") -> THEN X.CHAVE_IT ELSE NULL END | K12: ="UNION ALL SELECT '"&E12&"' AS REF_DATE, '"&A12&"' AS COD_KPI, '"&F12&"' AS TIPOLOGIA_TESTE, '"&D12&"' AS DESCRIÇÃO, '"&G12&"' AS TABELA, '"&B12&"' AS CAMPO, COUNT(*) AS NUM_REG, SUM(IF("&H12&","&C12&" ,"&I12&")) AS NUM_REG_DIF, GROUP_CONCAT(CASE WHEN "&H12&" "&J12&", '; ') AS DETALHE FROM (SELECT *, 0020_UNIQ_ID AS CHAVE_IT, "&B12&" AS CAMPO_IT FROM "&G12&" WHERE REF_DATE='"&E12&"')X GROUP BY 1" -> UNION ALL SELECT '"& RefDate &"' AS REF_DATE, 'v_1_0011' AS COD_KPI, 'REGULAMENTAR' AS TIPOLOGIA_TESTE, 'Alerta: Testar se o campo está a missing. Para passivos estruturados, o campo tem de ser reportado se a informação existir.' AS DESCRIÇÃO, 'BU_LOANTAPE_WORK.OUT_B0200_MAIN_LIABILITIES' AS TABELA, '0120_otstndng_amnt' AS CAMPO, COUNT(*) AS NUM_REG, SUM(IF((`0120_otstndng_amnt` IS NULL OR CAST(`0120_otstndng_amnt` AS STRING) = '') AND `0250_strctrd_prdct` NOT IN ('Structured', 'Only structured coupon'),1 ,0)) AS NUM_REG_DIF, GROUP_CONCAT(CASE WHEN (`0120_otstndng_amnt` IS NULL OR CAST(`0120_otstndng_amnt` AS STRING) = '') AND `0250_strctrd_prdct` NOT IN ('Structured', 'Only structured coupon') THEN X.CHAVE_IT ELSE NULL END, '; ') AS DETALHE FROM (SELECT *, 0020_UNIQ_ID AS CHAVE_IT, 0120_otstndng_amnt AS CAMPO_IT FROM BU_LOANTAPE_WORK.OUT_B0200_MAIN_LIABILITIES WHERE REF_DATE='"& RefDate &"')X GROUP BY 1
A13: v_1_0012 | B13: 0130_rlvnt_amnt_wdc | C13: 1 | D13: =+VLOOKUP(A13,Descrição!A:K,11,FALSE) -> Testar se o campo está a missing. O campo tem de ser reportado. | E13: "& RefDate &" | F13: REGULAMENTAR | G13: BU_LOANTAPE_WORK.OUT_B0200_MAIN_LIABILITIES | H13: `0130_rlvnt_amnt_wdc` IS NULL OR CAST(`0130_rlvnt_amnt_wdc` AS STRING) = '' | I13: =+IF(C13=1,0,1) -> 0 | J13: =+IF(C13=0,"THEN NULL ELSE X.CHAVE_IT END","THEN X.CHAVE_IT ELSE NULL END") -> THEN X.CHAVE_IT ELSE NULL END | K13: ="UNION ALL SELECT '"&E13&"' AS REF_DATE, '"&A13&"' AS COD_KPI, '"&F13&"' AS TIPOLOGIA_TESTE, '"&D13&"' AS DESCRIÇÃO, '"&G13&"' AS TABELA, '"&B13&"' AS CAMPO, COUNT(*) AS NUM_REG, SUM(IF("&H13&","&C13&" ,"&I13&")) AS NUM_REG_DIF, GROUP_CONCAT(CASE WHEN "&H13&" "&J13&", '; ') AS DETALHE FROM (SELECT *, 0020_UNIQ_ID AS CHAVE_IT, "&B13&" AS CAMPO_IT FROM "&G13&" WHERE REF_DATE='"&E13&"')X GROUP BY 1" -> UNION ALL SELECT '"& RefDate &"' AS REF_DATE, 'v_1_0012' AS COD_KPI, 'REGULAMENTAR' AS TIPOLOGIA_TESTE, 'Testar se o campo está a missing. O campo tem de ser reportado.' AS DESCRIÇÃO, 'BU_LOANTAPE_WORK.OUT_B0200_MAIN_LIABILITIES' AS TABELA, '0130_rlvnt_amnt_wdc' AS CAMPO, COUNT(*) AS NUM_REG, SUM(IF(`0130_rlvnt_amnt_wdc` IS NULL OR CAST(`0130_rlvnt_amnt_wdc` AS STRING) = '',1 ,0)) AS NUM_REG_DIF, GROUP_CONCAT(CASE WHEN `0130_rlvnt_amnt_wdc` IS NULL OR CAST(`0130_rlvnt_amnt_wdc` AS STRING) = '' THEN X.CHAVE_IT ELSE NULL END, '; ') AS DETALHE FROM (SELECT *, 0020_UNIQ_ID AS CHAVE_IT, 0130_rlvnt_amnt_wdc AS CAMPO_IT FROM BU_LOANTAPE_WORK.OUT_B0200_MAIN_LIABILITIES WHERE REF_DATE='"& RefDate &"')X GROUP BY 1
... A38: v_1_0037 | B38: 0610_crryng_amnt_ifrs | C38: 1 | D38: =+VLOOKUP(A38,Descrição!A:K,11,FALSE) -> Alerta: Testar se o campo está a missing. O campo deve ser reportado se a informação existir, ou seja, se a entidade reportar em IFRS. | E38: "& RefDate &" | F38: REGULAMENTAR | G38: BU_LOANTAPE_WORK.OUT_B0200_MAIN_LIABILITIES | H38: (`0610_crryng_amnt_ifrs` IS NULL or cast(`0610_crryng_amnt_ifrs` as string)='') | I38: =+IF(C38=1,0,1) -> 0 | J38: =+IF(C38=0,"THEN NULL ELSE X.CHAVE_IT END","THEN X.CHAVE_IT ELSE NULL END") -> THEN X.CHAVE_IT ELSE NULL END | K38: ="UNION ALL SELECT '"&E38&"' AS REF_DATE, '"&A38&"' AS COD_KPI, '"&F38&"' AS TIPOLOGIA_TESTE, '"&D38&"' AS DESCRIÇÃO, '"&G38&"' AS TABELA, '"&B38&"' AS CAMPO, COUNT(*) AS NUM_REG, SUM(IF("&H38&","&C38&" ,"&I38&")) AS NUM_REG_DIF, GROUP_CONCAT(CASE WHEN "&H38&" "&J38&", '; ') AS DETALHE FROM (SELECT *, 0020_UNIQ_ID AS CHAVE_IT, "&B38&" AS CAMPO_IT FROM "&G38&" WHERE REF_DATE='"&E38&"')X GROUP BY 1" -> UNION ALL SELECT '"& RefDate &"' AS REF_DATE, 'v_1_0037' AS COD_KPI, 'REGULAMENTAR' AS TIPOLOGIA_TESTE, 'Alerta: Testar se o campo está a missing. O campo deve ser reportado se a informação existir, ou seja, se a entidade reportar em IFRS.' AS DESCRIÇÃO, 'BU_LOANTAPE_WORK.OUT_B0200_MAIN_LIABILITIES' AS TABELA, '0610_crryng_amnt_ifrs' AS CAMPO, COUNT(*) AS NUM_REG, SUM(IF((`0610_crryng_amnt_ifrs` IS NULL or cast(`0610_crryng_amnt_ifrs` as string)=''),1 ,0)) AS NUM_REG_DIF, GROUP_CONCAT(CASE WHEN (`0610_crryng_amnt_ifrs` IS NULL or cast(`0610_crryng_amnt_ifrs` as string)='') THEN X.CHAVE_IT ELSE NULL END, '; ') AS DETALHE FROM (SELECT *, 0020_UNIQ_ID AS CHAVE_IT, 0610_crryng_amnt_ifrs AS CAMPO_IT FROM BU_LOANTAPE_WORK.OUT_B0200_MAIN_LIABILITIES WHERE REF_DATE='"& RefDate &"')X GROUP BY 1
A39: v_1_0038 | B39: 5000_flg_shrhldr_not_rsltn_grp | C39: 1 | D39: =+VLOOKUP(A39,Descrição!A:K,11,FALSE) -> Testar se o campo está a missing. O campo deve ser reportado para Non-Resolution Entities. | E39: "& RefDate &" | F39: REGULAMENTAR | G39: BU_LOANTAPE_WORK.OUT_B0200_MAIN_LIABILITIES | H39: (`5000_flg_shrhldr_not_rsltn_grp` IS MISSING or cast(`5000_flg_shrhldr_not_rsltn_grp` as string) = '') AND B99.`0060_orgnl_amnt_fx` = 'Non-Resolution Entity' | I39: =+IF(C39=1,0,1) -> 0 | J39: =+IF(C39=0,"THEN NULL ELSE X.CHAVE_IT END","THEN X.CHAVE_IT ELSE NULL END") -> THEN X.CHAVE_IT ELSE NULL END | K39: ="--UNION ALL SELECT '"&E39&"' AS REF_DATE, '"&A39&"' AS COD_KPI, '"&F39&"' AS TIPOLOGIA_TESTE, '"&D39&"' AS DESCRIÇÃO, '"&G39&"' AS TABELA, '"&B39&"' AS CAMPO, COUNT(*) AS NUM_REG, SUM(IF("&H39&","&C39&" ,"&I39&")) AS NUM_REG_DIF, GROUP_CONCAT(CASE WHEN "&H39&" "&J39&", '; ') AS DETALHE FROM (SELECT *, 0020_UNIQ_ID AS CHAVE_IT, "&B39&" AS CAMPO_IT FROM "&G39&" WHERE REF_DATE='"&E39&"')X GROUP BY 1" -> --UNION ALL SELECT '"& RefDate &"' AS REF_DATE, 'v_1_0038' AS COD_KPI, 'REGULAMENTAR' AS TIPOLOGIA_TESTE, 'Testar se o campo está a missing. O campo deve ser reportado para Non-Resolution Entities.' AS DESCRIÇÃO, 'BU_LOANTAPE_WORK.OUT_B0200_MAIN_LIABILITIES' AS TABELA, '5000_flg_shrhldr_not_rsltn_grp' AS CAMPO, COUNT(*) AS NUM_REG, SUM(IF((`5000_flg_shrhldr_not_rsltn_grp` IS MISSING or cast(`5000_flg_shrhldr_not_rsltn_grp` as string) = '') AND B99.`0060_orgnl_amnt_fx` = 'Non-Resolution Entity',1 ,0)) AS NUM_REG_DIF, GROUP_CONCAT(CASE WHEN (`5000_flg_shrhldr_not_rsltn_grp` IS MISSING or cast(`5000_flg_shrhldr_not_rsltn_grp` as string) = '') AND B99.`0060_orgnl_amnt_fx` = 'Non-Resolution Entity' THEN X.CHAVE_IT ELSE NULL END, '; ') AS DETALHE FROM (SELECT *, 0020_UNIQ_ID AS CHAVE_IT, 5000_flg_shrhldr_not_rsltn_grp AS CAMPO_IT FROM BU_LOANTAPE_WORK.OUT_B0200_MAIN_LIABILITIES WHERE REF_DATE='"& RefDate &"')X GROUP BY 1
A40: v_1_0039 | B40: 5010_flg_art21_7a_srmr | C40: 1 | D40: =+VLOOKUP(A40,Descrição!A:K,11,FALSE) -> Testar se o campo está a missing. O campo deve ser reportado para Non-Resolution Entities. | E40: "& RefDate &" | F40: REGULAMENTAR | G40: BU_LOANTAPE_WORK.OUT_B0200_MAIN_LIABILITIES | H40: (`5010_flg_art21_7a_srmr` IS MISSING or cast(`5010_flg_art21_7a_srmr` as string) = '') AND B99.`0060_orgnl_amnt_fx` = 'Non-Resolution Entity' | I40: =+IF(C40=1,0,1) -> 0 | J40: =+IF(C40=0,"THEN NULL ELSE X.CHAVE_IT END","THEN X.CHAVE_IT ELSE NULL END") -> THEN X.CHAVE_IT ELSE NULL END | K40: ="--UNION ALL SELECT '"&E40&"' AS REF_DATE, '"&A40&"' AS COD_KPI, '"&F40&"' AS TIPOLOGIA_TESTE, '"&D40&"' AS DESCRIÇÃO, '"&G40&"' AS TABELA, '"&B40&"' AS CAMPO, COUNT(*) AS NUM_REG, SUM(IF("&H40&","&C40&" ,"&I40&")) AS NUM_REG_DIF, GROUP_CONCAT(CASE WHEN "&H40&" "&J40&", '; ') AS DETALHE FROM (SELECT *, 0020_UNIQ_ID AS CHAVE_IT, "&B40&" AS CAMPO_IT FROM "&G40&" WHERE REF_DATE='"&E40&"')X GROUP BY 1" -> --UNION ALL SELECT '"& RefDate &"' AS REF_DATE, 'v_1_0039' AS COD_KPI, 'REGULAMENTAR' AS TIPOLOGIA_TESTE, 'Testar se o campo está a missing. O campo deve ser reportado para Non-Resolution Entities.' AS DESCRIÇÃO, 'BU_LOANTAPE_WORK.OUT_B0200_MAIN_LIABILITIES' AS TABELA, '5010_flg_art21_7a_srmr' AS CAMPO, COUNT(*) AS NUM_REG, SUM(IF((`5010_flg_art21_7a_srmr` IS MISSING or cast(`5010_flg_art21_7a_srmr` as string) = '') AND B99.`0060_orgnl_amnt_fx` = 'Non-Resolution Entity',1 ,0)) AS NUM_REG_DIF, GROUP_CONCAT(CASE WHEN (`5010_flg_art21_7a_srmr` IS MISSING or cast(`5010_flg_art21_7a_srmr` as string) = '') AND B99.`0060_orgnl_amnt_fx` = 'Non-Resolution Entity' THEN X.CHAVE_IT ELSE NULL END, '; ') AS DETALHE FROM (SELECT *, 0020_UNIQ_ID AS CHAVE_IT, 5010_flg_art21_7a_srmr AS CAMPO_IT FROM BU_LOANTAPE_WORK.OUT_B0200_MAIN_LIABILITIES WHERE REF_DATE='"& RefDate &"')X GROUP BY 1
A41: v_2_0001 | B41: 0030_uniq_id_knwn_cntrprty | C41: 0 | D41: =+VLOOKUP(A41,Descrição!A:K,11,FALSE) -> Se o ID for um ISIN (c0030 = ISIN), então o ID reportado em c0020 deve ter as características de um ISIN, por exemplo, 12 caracteres e começar com 2 letras que significam o código de país ISO. | E41: "& RefDate &" | F41: REGULAMENTAR | G41: BU_LOANTAPE_WORK.OUT_B0200_MAIN_LIABILITIES | H41: `0040_typ_uniq_id_knwn_cntrprty` = 'ISIN' AND LENGTH(`0030_uniq_id_knwn_cntrprty`) <= 12 AND SUBSTR(`0030_uniq_id_knwn_cntrprty`, 1, 2) RLIKE '[A-Za-z]$' | I41: =+IF(C41=1,0,1) -> 1 | J41: =+IF(C41=0,"THEN NULL ELSE X.CHAVE_IT END","THEN X.CHAVE_IT ELSE NULL END") -> THEN NULL ELSE X.CHAVE_IT END | K41: ="UNION ALL SELECT '"&E41&"' AS REF_DATE, '"&A41&"' AS COD_KPI, '"&F41&"' AS TIPOLOGIA_TESTE, '"&D41&"' AS DESCRIÇÃO, '"&G41&"' AS TABELA, '"&B41&"' AS CAMPO, COUNT(*) AS NUM_REG, SUM(IF("&H41&","&C41&" ,"&I41&")) AS NUM_REG_DIF, GROUP_CONCAT(CASE WHEN "&H41&" "&J41&", '; ') AS DETALHE FROM (SELECT *, 0020_UNIQ_ID AS CHAVE_IT, "&B41&" AS CAMPO_IT FROM "&G41&" WHERE REF_DATE='"&E41&"')X GROUP BY 1" -> UNION ALL SELECT '"& RefDate &"' AS REF_DATE, 'v_2_0001' AS COD_KPI, 'REGULAMENTAR' AS TIPOLOGIA_TESTE, 'Se o ID for um ISIN (c0030 = ISIN), então o ID reportado em c0020 deve ter as características de um ISIN, por exemplo, 12 caracteres e começar com 2 letras que significam o código de país ISO.' AS DESCRIÇÃO, 'BU_LOANTAPE_WORK.OUT_B0200_MAIN_LIABILITIES' AS TABELA, '0030_uniq_id_knwn_cntrprty' AS CAMPO, COUNT(*) AS NUM_REG, SUM(IF(`0040_typ_uniq_id_knwn_cntrprty` = 'ISIN' AND LENGTH(`0030_uniq_id_knwn_cntrprty`) <= 12 AND SUBSTR(`0030_uniq_id_knwn_cntrprty`, 1, 2) RLIKE '[A-Za-z]$',0 ,1)) AS NUM_REG_DIF, GROUP_CONCAT(CASE WHEN `0040_typ_uniq_id_knwn_cntrprty` = 'ISIN' AND LENGTH(`0030_uniq_id_knwn_cntrprty`) <= 12 AND SUBSTR(`0030_uniq_id_knwn_cntrprty`, 1, 2) RLIKE '[A-Za-z]$' THEN NULL ELSE X.CHAVE_IT END, '; ') AS DETALHE FROM (SELECT *, 0020_UNIQ_ID AS CHAVE_IT, 0030_uniq_id_knwn_cntrprty AS CAMPO_IT FROM BU_LOANTAPE_WORK.OUT_B0200_MAIN_LIABILITIES WHERE REF_DATE='"& RefDate &"')X GROUP BY 1
A42: v_2_0003 | B42: 0070_cntrct_crrncy | C42: 1 | D42: =+VLOOKUP(A42,Descrição!A:K,11,FALSE) -> As moedas devem ser reportadas usando o código ISO 4217 de 3 letras. | E42: "& RefDate &" | F42: REGULAMENTAR | G42: BU_LOANTAPE_WORK.OUT_B0200_MAIN_LIABILITIES | H42: `0020_uniq_id` NOT IN ('NCNP', 'NCBP') AND `0070_cntrct_crrncy` NOT IN ('AFN', 'EUR', 'ALL', 'DZD', 'USD', 'EUR', 'AOA', 'XCD', 'XCD', 'XAD', 'ARS', 'AMD', 'AWG', 'AUD', 'EUR', 'AZN', 'BSD', 'BHD', 'BDT', 'BBD', 'BYN', 'EUR', 'BZD', 'XOF', 'BMD', 'INR', 'BTN', 'BOB', 'BOV', 'USD', 'BAM', 'BWP', 'NOK', 'BRL', 'USD', 'BND', 'BGN', 'XOF', 'BIF', 'CVE', 'KHR', 'XAF', 'CAD', 'KYD', 'XAF', 'XAF', 'CLP', 'CLF', 'CNY', 'CNH', 'AUD', 'AUD', 'COP', 'COU', 'KMF', 'CDF', 'XAF', 'NZD', 'CRC', 'XOF', 'EUR', 'CUP', 'XCG', 'EUR', 'CZK', 'DKK', 'DJF', 'XCD', 'DOP', 'USD', 'EGP', 'SVC', 'USD', 'XAF', 'ERN', 'EUR', 'SZL', 'ETB', 'EUR', 'FKP', 'DKK', 'FJD', 'EUR', 'EUR', 'EUR', 'XPF', 'EUR', 'XAF', 'GMD', 'GEL', 'EUR', 'GHS', 'GIP', 'EUR', 'DKK', 'XCD', 'EUR', 'USD', 'GTQ', 'GBP', 'GNF', 'XOF', 'GYD', 'HTG', 'USD', 'AUD', 'EUR', 'HNL', 'HKD', 'HUF', 'ISK', 'INR', 'IDR', 'XDR', 'IRR', 'IQD', 'EUR', 'GBP', 'ILS', 'EUR', 'JMD', 'JPY', 'GBP', 'JOD', 'KZT', 'KES', 'AUD', 'KPW', 'KRW', 'KWD', 'KGS', 'LAK', 'EUR', 'LBP', 'LSL', 'ZAR', 'LRD', 'LYD', 'CHF', 'EUR', 'EUR', 'MOP', 'MGA', 'MWK', 'MYR', 'MVR', 'XOF', 'EUR', 'USD', 'EUR', 'MRU', 'MUR', 'EUR', 'XUA', 'MXN', 'MXV', 'USD', 'MDL', 'EUR', 'MNT', 'EUR', 'XCD', 'MAD', 'MZN', 'MMK', 'NAD', 'ZAR', 'AUD', 'NPR', 'EUR', 'XPF', 'NZD', 'NIO', 'XOF', 'NGN', 'NZD', 'AUD', 'MKD', 'USD', 'NOK', 'OMR', 'PKR', 'USD', 'PAB', 'USD', 'PGK', 'PYG', 'PEN', 'PHP', 'NZD', 'PLN', 'EUR', 'USD', 'QAR', 'EUR', 'RON', 'RUB', 'RWF', 'EUR', 'SHP', 'XCD', 'XCD', 'EUR', 'EUR', 'XCD', 'WST', 'EUR', 'STN', 'SAR', 'XOF', 'RSD', 'SCR', 'SLE', 'SGD', 'XCG', 'XSU', 'EUR', 'EUR', 'SBD', 'SOS', 'ZAR', 'SSP', 'EUR', 'LKR', 'SDG', 'SRD', 'NOK', 'SEK', 'CHF', 'CHE', 'CHW', 'SYP', 'TWD', 'TJS', 'TZS', 'THB', 'USD', 'XOF', 'NZD', 'TOP', 'TTD', 'TND', 'TRY', 'TMT', 'USD', 'AUD', 'UGX', 'UAH', 'AED', 'GBP', 'USD', 'USD', 'USN', 'UYU', 'UYI', 'UYW', 'UZS', 'VUV', 'VES', 'VED', 'VND', 'USD', 'USD', 'XPF', 'MAD', 'YER', 'ZMW', 'ZWG', 'XBA', 'XBB', 'XBC', 'XBD', 'XTS', 'XXX', 'XAU', 'XPD', 'XPT', 'XAG') | I42: =+IF(C42=1,0,1) -> 0 | J42: =+IF(C42=0,"THEN NULL ELSE X.CHAVE_IT END","THEN X.CHAVE_IT ELSE NULL END") -> THEN X.CHAVE_IT ELSE NULL END | K42: ="UNION ALL SELECT '"&E42&"' AS REF_DATE, '"&A42&"' AS COD_KPI, '"&F42&"' AS TIPOLOGIA_TESTE, '"&D42&"' AS DESCRIÇÃO, '"&G42&"' AS TABELA, '"&B42&"' AS CAMPO, COUNT(*) AS NUM_REG, SUM(IF("&H42&","&C42&" ,"&I42&")) AS NUM_REG_DIF, GROUP_CONCAT(CASE WHEN "&H42&" "&J42&", '; ') AS DETALHE FROM (SELECT *, 0020_UNIQ_ID AS CHAVE_IT, "&B42&" AS CAMPO_IT FROM "&G42&" WHERE REF_DATE='"&E42&"')X GROUP BY 1" -> UNION ALL SELECT '"& RefDate &"' AS REF_DATE, 'v_2_0003' AS COD_KPI, 'REGULAMENTAR' AS TIPOLOGIA_TESTE, 'As moedas devem ser reportadas usando o código ISO 4217 de 3 letras.' AS DESCRIÇÃO, 'BU_LOANTAPE_WORK.OUT_B0200_MAIN_LIABILITIES' AS TABELA, '0070_cntrct_crrncy' AS CAMPO, COUNT(*) AS NUM_REG, SUM(IF(`0020_uniq_id` NOT IN ('NCNP', 'NCBP') AND `0070_cntrct_crrncy` NOT IN ('AFN', 'EUR', 'ALL', 'DZD', 'USD', 'EUR', 'AOA', 'XCD', 'XCD', 'XAD', 'ARS', 'AMD', 'AWG', 'AUD', 'EUR', 'AZN', 'BSD', 'BHD', 'BDT', 'BBD', 'BYN', 'EUR', 'BZD', 'XOF', 'BMD', 'INR', 'BTN', 'BOB', 'BOV', 'USD', 'BAM', 'BWP', 'NOK', 'BRL', 'USD', 'BND', 'BGN', 'XOF', 'BIF', 'CVE', 'KHR', 'XAF', 'CAD', 'KYD', 'XAF', 'XAF', 'CLP', 'CLF', 'CNY', 'CNH', 'AUD', 'AUD', 'COP', 'COU', 'KMF', 'CDF', 'XAF', 'NZD', 'CRC', 'XOF', 'EUR', 'CUP', 'XCG', 'EUR', 'CZK', 'DKK', 'DJF', 'XCD', 'DOP', 'USD', 'EGP', 'SVC', 'USD', 'XAF', 'ERN', 'EUR', 'SZL', 'ETB', 'EUR', 'FKP', 'DKK', 'FJD', 'EUR', 'EUR', 'EUR', 'XPF', 'EUR', 'XAF', 'GMD', 'GEL', 'EUR', 'GHS', 'GIP', 'EUR', 'DKK', 'XCD', 'EUR', 'USD', 'GTQ', 'GBP', 'GNF', 'XOF', 'GYD', 'HTG', 'USD', 'AUD', 'EUR', 'HNL', 'HKD', 'HUF', 'ISK', 'INR', 'IDR', 'XDR', 'IRR', 'IQD', 'EUR', 'GBP', 'ILS', 'EUR', 'JMD', 'JPY', 'GBP', 'JOD', 'KZT', 'KES', 'AUD', 'KPW', 'KRW', 'KWD', 'KGS', 'LAK', 'EUR', 'LBP', 'LSL', 'ZAR', 'LRD', 'LYD', 'CHF', 'EUR', 'EUR', 'MOP', 'MGA', 'MWK', 'MYR', 'MVR', 'XOF', 'EUR', 'USD', 'EUR', 'MRU', 'MUR', 'EUR', 'XUA', 'MXN', 'MXV', 'USD', 'MDL', 'EUR', 'MNT', 'EUR', 'XCD', 'MAD', 'MZN', 'MMK', 'NAD', 'ZAR', 'AUD', 'NPR', 'EUR', 'XPF', 'NZD', 'NIO', 'XOF', 'NGN', 'NZD', 'AUD', 'MKD', 'USD', 'NOK', 'OMR', 'PKR', 'USD', 'PAB', 'USD', 'PGK', 'PYG', 'PEN', 'PHP', 'NZD', 'PLN', 'EUR', 'USD', 'QAR', 'EUR', 'RON', 'RUB', 'RWF', 'EUR', 'SHP', 'XCD', 'XCD', 'EUR', 'EUR', 'XCD', 'WST', 'EUR', 'STN', 'SAR', 'XOF', 'RSD', 'SCR', 'SLE', 'SGD', 'XCG', 'XSU', 'EUR', 'EUR', 'SBD', 'SOS', 'ZAR', 'SSP', 'EUR', 'LKR', 'SDG', 'SRD', 'NOK', 'SEK', 'CHF', 'CHE', 'CHW', 'SYP', 'TWD', 'TJS', 'TZS', 'THB', 'USD', 'XOF', 'NZD', 'TOP', 'TTD', 'TND', 'TRY', 'TMT', 'USD', 'AUD', 'UGX', 'UAH', 'AED', 'GBP', 'USD', 'USD', 'USN', 'UYU', 'UYI', 'UYW', 'UZS', 'VUV', 'VES', 'VED', 'VND', 'USD', 'USD', 'XPF', 'MAD', 'YER', 'ZMW', 'ZWG', 'XBA', 'XBB', 'XBC', 'XBD', 'XTS', 'XXX', 'XAU', 'XPD', 'XPT', 'XAG'),1 ,0)) AS NUM_REG_DIF, GROUP_CONCAT(CASE WHEN `0020_uniq_id` NOT IN ('NCNP', 'NCBP') AND `0070_cntrct_crrncy` NOT IN ('AFN', 'EUR', 'ALL', 'DZD', 'USD', 'EUR', 'AOA', 'XCD', 'XCD', 'XAD', 'ARS', 'AMD', 'AWG', 'AUD', 'EUR', 'AZN', 'BSD', 'BHD', 'BDT', 'BBD', 'BYN', 'EUR', 'BZD', 'XOF', 'BMD', 'INR', 'BTN', 'BOB', 'BOV', 'USD', 'BAM', 'BWP', 'NOK', 'BRL', 'USD', 'BND', 'BGN', 'XOF', 'BIF', 'CVE', 'KHR', 'XAF', 'CAD', 'KYD', 'XAF', 'XAF', 'CLP', 'CLF', 'CNY', 'CNH', 'AUD', 'AUD', 'COP', 'COU', 'KMF', 'CDF', 'XAF', 'NZD', 'CRC', 'XOF', 'EUR', 'CUP', 'XCG', 'EUR', 'CZK', 'DKK', 'DJF', 'XCD', 'DOP', 'USD', 'EGP', 'SVC', 'USD', 'XAF', 'ERN', 'EUR', 'SZL', 'ETB', 'EUR', 'FKP', 'DKK', 'FJD', 'EUR', 'EUR', 'EUR', 'XPF', 'EUR', 'XAF', 'GMD', 'GEL', 'EUR', 'GHS', 'GIP', 'EUR', 'DKK', 'XCD', 'EUR', 'USD', 'GTQ', 'GBP', 'GNF', 'XOF', 'GYD', 'HTG', 'USD', 'AUD', 'EUR', 'HNL', 'HKD', 'HUF', 'ISK', 'INR', 'IDR', 'XDR', 'IRR', 'IQD', 'EUR', 'GBP', 'ILS', 'EUR', 'JMD', 'JPY', 'GBP', 'JOD', 'KZT', 'KES', 'AUD', 'KPW', 'KRW', 'KWD', 'KGS', 'LAK', 'EUR', 'LBP', 'LSL', 'ZAR', 'LRD', 'LYD', 'CHF', 'EUR', 'EUR', 'MOP', 'MGA', 'MWK', 'MYR', 'MVR', 'XOF', 'EUR', 'USD', 'EUR', 'MRU', 'MUR', 'EUR', 'XUA', 'MXN', 'MXV', 'USD', 'MDL', 'EUR', 'MNT', 'EUR', 'XCD', 'MAD', 'MZN', 'MMK', 'NAD', 'ZAR', 'AUD', 'NPR', 'EUR', 'XPF', 'NZD', 'NIO', 'XOF', 'NGN', 'NZD', 'AUD', 'MKD', 'USD', 'NOK', 'OMR', 'PKR', 'USD', 'PAB', 'USD', 'PGK', 'PYG', 'PEN', 'PHP', 'NZD', 'PLN', 'EUR', 'USD', 'QAR', 'EUR', 'RON', 'RUB', 'RWF', 'EUR', 'SHP', 'XCD', 'XCD', 'EUR', 'EUR', 'XCD', 'WST', 'EUR', 'STN', 'SAR', 'XOF', 'RSD', 'SCR', 'SLE', 'SGD', 'XCG', 'XSU', 'EUR', 'EUR', 'SBD', 'SOS', 'ZAR', 'SSP', 'EUR', 'LKR', 'SDG', 'SRD', 'NOK', 'SEK', 'CHF', 'CHE', 'CHW', 'SYP', 'TWD', 'TJS', 'TZS', 'THB', 'USD', 'XOF', 'NZD', 'TOP', 'TTD', 'TND', 'TRY', 'TMT', 'USD', 'AUD', 'UGX', 'UAH', 'AED', 'GBP', 'USD', 'USD', 'USN', 'UYU', 'UYI', 'UYW', 'UZS', 'VUV', 'VES', 'VED', 'VND', 'USD', 'USD', 'XPF', 'MAD', 'YER', 'ZMW', 'ZWG', 'XBA', 'XBB', 'XBC', 'XBD', 'XTS', 'XXX', 'XAU', 'XPD', 'XPT', 'XAG') THEN X.CHAVE_IT ELSE NULL END, '; ') AS DETALHE FROM (SELECT *, 0020_UNIQ_ID AS CHAVE_IT, 0070_cntrct_crrncy AS CAMPO_IT FROM BU_LOANTAPE_WORK.OUT_B0200_MAIN_LIABILITIES WHERE REF_DATE='"& RefDate &"')X GROUP BY 1
A43: v_2_0004 | B43: 0080_otstndng_prncpl_amnt | C43: 1 | D43: =+VLOOKUP(A43,Descrição!A:K,11,FALSE) -> Alerta: o valor declarado deve, em geral, ser positivo. | E43: "& RefDate &" | F43: REGULAMENTAR | G43: BU_LOANTAPE_WORK.OUT_B0200_MAIN_LIABILITIES | H43: `0080_otstndng_prncpl_amnt` <= 0 | I43: =+IF(C43=1,0,1) -> 0 | J43: =+IF(C43=0,"THEN NULL ELSE X.CHAVE_IT END","THEN X.CHAVE_IT ELSE NULL END") -> THEN X.CHAVE_IT ELSE NULL END | K43: ="UNION ALL SELECT '"&E43&"' AS REF_DATE, '"&A43&"' AS COD_KPI, '"&F43&"' AS TIPOLOGIA_TESTE, '"&D43&"' AS DESCRIÇÃO, '"&G43&"' AS TABELA, '"&B43&"' AS CAMPO, COUNT(*) AS NUM_REG, SUM(IF("&H43&","&C43&" ,"&I43&")) AS NUM_REG_DIF, GROUP_CONCAT(CASE WHEN "&H43&" "&J43&", '; ') AS DETALHE FROM (SELECT *, 0020_UNIQ_ID AS CHAVE_IT, "&B43&" AS CAMPO_IT FROM "&G43&" WHERE REF_DATE='"&E43&"')X GROUP BY 1" -> UNION ALL SELECT '"& RefDate &"' AS REF_DATE, 'v_2_0004' AS COD_KPI, 'REGULAMENTAR' AS TIPOLOGIA_TESTE, 'Alerta: o valor declarado deve, em geral, ser positivo.' AS DESCRIÇÃO, 'BU_LOANTAPE_WORK.OUT_B0200_MAIN_LIABILITIES' AS TABELA, '0080_otstndng_prncpl_amnt' AS CAMPO, COUNT(*) AS NUM_REG, SUM(IF(`0080_otstndng_prncpl_amnt` <= 0,1 ,0)) AS NUM_REG_DIF, GROUP_CONCAT(CASE WHEN `0080_otstndng_prncpl_amnt` <= 0 THEN X.CHAVE_IT ELSE NULL END, '; ') AS DETALHE FROM (SELECT *, 0020_UNIQ_ID AS CHAVE_IT, 0080_otstndng_prncpl_amnt AS CAMPO_IT FROM BU_LOANTAPE_WORK.OUT_B0200_MAIN_LIABILITIES WHERE REF_DATE='"& RefDate &"')X GROUP BY 1
A44: v_2_0005 | B44: 0090_prtn_amnt_rprtng_entty | C44: 1 | D44: =+VLOOKUP(A44,Descrição!A:K,11,FALSE) -> O valor declarado deve ser positivo ou zero. | E44: "& RefDate &" | F44: REGULAMENTAR | G44: BU_LOANTAPE_WORK.OUT_B0200_MAIN_LIABILITIES | H44: `0090_prtn_amnt_rprtng_entty` <0 AND `0040_typ_uniq_id_knwn_cntrprty` = 'ISIN' | I44: =+IF(C44=1,0,1) -> 0 | J44: =+IF(C44=0,"THEN NULL ELSE X.CHAVE_IT END","THEN X.CHAVE_IT ELSE NULL END") -> THEN X.CHAVE_IT ELSE NULL END | K44: ="UNION ALL SELECT '"&E44&"' AS REF_DATE, '"&A44&"' AS COD_KPI, '"&F44&"' AS TIPOLOGIA_TESTE, '"&D44&"' AS DESCRIÇÃO, '"&G44&"' AS TABELA, '"&B44&"' AS CAMPO, COUNT(*) AS NUM_REG, SUM(IF("&H44&","&C44&" ,"&I44&")) AS NUM_REG_DIF, GROUP_CONCAT(CASE WHEN "&H44&" "&J44&", '; ') AS DETALHE FROM (SELECT *, 0020_UNIQ_ID AS CHAVE_IT, "&B44&" AS CAMPO_IT FROM "&G44&" WHERE REF_DATE='"&E44&"')X GROUP BY 1" -> UNION ALL SELECT '"& RefDate &"' AS REF_DATE, 'v_2_0005' AS COD_KPI, 'REGULAMENTAR' AS TIPOLOGIA_TESTE, 'O valor declarado deve ser positivo ou zero.' AS DESCRIÇÃO, 'BU_LOANTAPE_WORK.OUT_B0200_MAIN_LIABILITIES' AS TABELA, '0090_prtn_amnt_rprtng_entty' AS CAMPO, COUNT(*) AS NUM_REG, SUM(IF(`0090_prtn_amnt_rprtng_entty` <0 AND `0040_typ_uniq_id_knwn_cntrprty` = 'ISIN',1 ,0)) AS NUM_REG_DIF, GROUP_CONCAT(CASE WHEN `0090_prtn_amnt_rprtng_entty` <0 AND `0040_typ_uniq_id_knwn_cntrprty` = 'ISIN' THEN X.CHAVE_IT ELSE NULL END, '; ') AS DETALHE FROM (SELECT *, 0020_UNIQ_ID AS CHAVE_IT, 0090_prtn_amnt_rprtng_entty AS CAMPO_IT FROM BU_LOANTAPE_WORK.OUT_B0200_MAIN_LIABILITIES WHERE REF_DATE='"& RefDate &"')X GROUP BY 1
A45: v_2_0006 | B45: 0100_accrd_intrst_instrmnt | C45: 1 | D45: =+VLOOKUP(A45,Descrição!A:K,11,FALSE) -> Alerta: o valor declarado deve ser positivo ou zero. No entanto, juros acumulados negativos são, em princípio, permitidos, se devidamente justificados pela entidade reportante. | E45: "& RefDate &" | F45: REGULAMENTAR | G45: BU_LOANTAPE_WORK.OUT_B0200_MAIN_LIABILITIES | H45: `0100_accrd_intrst_instrmnt` <0 | I45: =+IF(C45=1,0,1) -> 0 | J45: =+IF(C45=0,"THEN NULL ELSE X.CHAVE_IT END","THEN X.CHAVE_IT ELSE NULL END") -> THEN X.CHAVE_IT ELSE NULL END | K45: ="UNION ALL SELECT '"&E45&"' AS REF_DATE, '"&A45&"' AS COD_KPI, '"&F45&"' AS TIPOLOGIA_TESTE, '"&D45&"' AS DESCRIÇÃO, '"&G45&"' AS TABELA, '"&B45&"' AS CAMPO, COUNT(*) AS NUM_REG, SUM(IF("&H45&","&C45&" ,"&I45&")) AS NUM_REG_DIF, GROUP_CONCAT(CASE WHEN "&H45&" "&J45&", '; ') AS DETALHE FROM (SELECT *, 0020_UNIQ_ID AS CHAVE_IT, "&B45&" AS CAMPO_IT FROM "&G45&" WHERE REF_DATE='"&E45&"')X GROUP BY 1" -> UNION ALL SELECT '"& RefDate &"' AS REF_DATE, 'v_2_0006' AS COD_KPI, 'REGULAMENTAR' AS TIPOLOGIA_TESTE, 'Alerta: o valor declarado deve ser positivo ou zero. No entanto, juros acumulados negativos são, em princípio, permitidos, se devidamente justificados pela entidade reportante.' AS DESCRIÇÃO, 'BU_LOANTAPE_WORK.OUT_B0200_MAIN_LIABILITIES' AS TABELA, '0100_accrd_intrst_instrmnt' AS CAMPO, COUNT(*) AS NUM_REG, SUM(IF(`0100_accrd_intrst_instrmnt` <0,1 ,0)) AS NUM_REG_DIF, GROUP_CONCAT(CASE WHEN `0100_accrd_intrst_instrmnt` <0 THEN X.CHAVE_IT ELSE NULL END, '; ') AS DETALHE FROM (SELECT *, 0020_UNIQ_ID AS CHAVE_IT, 0100_accrd_intrst_instrmnt AS CAMPO_IT FROM BU_LOANTAPE_WORK.OUT_B0200_MAIN_LIABILITIES WHERE REF_DATE='"& RefDate &"')X GROUP BY 1
A46: v_2_0007 | B46: 0110_applcbl_fees_charges | C46: 1 | D46: =+VLOOKUP(A46,Descrição!A:K,11,FALSE) -> Alerta: o valor declarado deve ser, em geral, positivo ou zero. | E46: "& RefDate &" | F46: REGULAMENTAR | G46: BU_LOANTAPE_WORK.OUT_B0200_MAIN_LIABILITIES | H46: `0110_applcbl_fees_charges` < 0 | I46: =+IF(C46=1,0,1) -> 0 | J46: =+IF(C46=0,"THEN NULL ELSE X.CHAVE_IT END","THEN X.CHAVE_IT ELSE NULL END") -> THEN X.CHAVE_IT ELSE NULL END | K46: ="UNION ALL SELECT '"&E46&"' AS REF_DATE, '"&A46&"' AS COD_KPI, '"&F46&"' AS TIPOLOGIA_TESTE, '"&D46&"' AS DESCRIÇÃO, '"&G46&"' AS TABELA, '"&B46&"' AS CAMPO, COUNT(*) AS NUM_REG, SUM(IF("&H46&","&C46&" ,"&I46&")) AS NUM_REG_DIF, GROUP_CONCAT(CASE WHEN "&H46&" "&J46&", '; ') AS DETALHE FROM (SELECT *, 0020_UNIQ_ID AS CHAVE_IT, "&B46&" AS CAMPO_IT FROM "&G46&" WHERE REF_DATE='"&E46&"')X GROUP BY 1" -> UNION ALL SELECT '"& RefDate &"' AS REF_DATE, 'v_2_0007' AS COD_KPI, 'REGULAMENTAR' AS TIPOLOGIA_TESTE, 'Alerta: o valor declarado deve ser, em geral, positivo ou zero.' AS DESCRIÇÃO, 'BU_LOANTAPE_WORK.OUT_B0200_MAIN_LIABILITIES' AS TABELA, '0110_applcbl_fees_charges' AS CAMPO, COUNT(*) AS NUM_REG, SUM(IF(`0110_applcbl_fees_charges` < 0,1 ,0)) AS NUM_REG_DIF, GROUP_CONCAT(CASE WHEN `0110_applcbl_fees_charges` < 0 THEN X.CHAVE_IT ELSE NULL END, '; ') AS DETALHE FROM (SELECT *, 0020_UNIQ_ID AS CHAVE_IT, 0110_applcbl_fees_charges AS CAMPO_IT FROM BU_LOANTAPE_WORK.OUT_B0200_MAIN_LIABILITIES WHERE REF_DATE='"& RefDate &"')X GROUP BY 1
A47: v_2_0008 | B47: 0120_otstndng_amnt | C47: 1 | D47: =+VLOOKUP(A47,Descrição!A:K,11,FALSE) -> O valor reportado deve ser positivo. | E47: "& RefDate &" | F47: REGULAMENTAR | G47: BU_LOANTAPE_WORK.OUT_B0200_MAIN_LIABILITIES | H47: `0120_otstndng_amnt` >=0 | I47: =+IF(C47=1,0,1) -> 0 | J47: =+IF(C47=0,"THEN NULL ELSE X.CHAVE_IT END","THEN X.CHAVE_IT ELSE NULL END") -> THEN X.CHAVE_IT ELSE NULL END | K47: ="UNION ALL SELECT '"&E47&"' AS REF_DATE, '"&A47&"' AS COD_KPI, '"&F47&"' AS TIPOLOGIA_TESTE, '"&D47&"' AS DESCRIÇÃO, '"&G47&"' AS TABELA, '"&B47&"' AS CAMPO, COUNT(*) AS NUM_REG, SUM(IF("&H47&","&C47&" ,"&I47&")) AS NUM_REG_DIF, GROUP_CONCAT(CASE WHEN "&H47&" "&J47&", '; ') AS DETALHE FROM (SELECT *, 0020_UNIQ_ID AS CHAVE_IT, "&B47&" AS CAMPO_IT FROM "&G47&" WHERE REF_DATE='"&E47&"')X GROUP BY 1" -> UNION ALL SELECT '"& RefDate &"' AS REF_DATE, 'v_2_0008' AS COD_KPI, 'REGULAMENTAR' AS TIPOLOGIA_TESTE, 'O valor reportado deve ser positivo.' AS DESCRIÇÃO, 'BU_LOANTAPE_WORK.OUT_B0200_MAIN_LIABILITIES' AS TABELA, '0120_otstndng_amnt' AS CAMPO, COUNT(*) AS NUM_REG, SUM(IF(`0120_otstndng_amnt` >=0,1 ,0)) AS NUM_REG_DIF, GROUP_CONCAT(CASE WHEN `0120_otstndng_amnt` >=0 THEN X.CHAVE_IT ELSE NULL END, '; ') AS DETALHE FROM (SELECT *, 0020_UNIQ_ID AS CHAVE_IT, 0120_otstndng_amnt AS CAMPO_IT FROM BU_LOANTAPE_WORK.OUT_B0200_MAIN_LIABILITIES WHERE REF_DATE='"& RefDate &"')X GROUP BY 1
A48: v_2_0009 | B48: 0120_otstndng_amnt | C48: 1 | D48: =+VLOOKUP(A48,Descrição!A:K,11,FALSE) -> O valor declarado deve ser igual a: c0080 + c0100 + c0110. | E48: "& RefDate &" | F48: REGULAMENTAR | G48: BU_LOANTAPE_WORK.OUT_B0200_MAIN_LIABILITIES | H48: `0120_otstndng_amnt` != (`0080_otstndng_prncpl_amnt`+`0100_accrd_intrst_instrmnt`+`0110_applcbl_fees_charges`) | I48: =+IF(C48=1,0,1) -> 0 | J48: =+IF(C48=0,"THEN NULL ELSE X.CHAVE_IT END","THEN X.CHAVE_IT ELSE NULL END") -> THEN X.CHAVE_IT ELSE NULL END | K48: ="UNION ALL SELECT '"&E48&"' AS REF_DATE, '"&A48&"' AS COD_KPI, '"&F48&"' AS TIPOLOGIA_TESTE, '"&D48&"' AS DESCRIÇÃO, '"&G48&"' AS TABELA, '"&B48&"' AS CAMPO, COUNT(*) AS NUM_REG, SUM(IF("&H48&","&C48&" ,"&I48&")) AS NUM_REG_DIF, GROUP_CONCAT(CASE WHEN "&H48&" "&J48&", '; ') AS DETALHE FROM (SELECT *, 0020_UNIQ_ID AS CHAVE_IT, "&B48&" AS CAMPO_IT FROM "&G48&" WHERE REF_DATE='"&E48&"')X GROUP BY 1" -> UNION ALL SELECT '"& RefDate &"' AS REF_DATE, 'v_2_0009' AS COD_KPI, 'REGULAMENTAR' AS TIPOLOGIA_TESTE, 'O valor declarado deve ser igual a: c0080 + c0100 + c0110.' AS DESCRIÇÃO, 'BU_LOANTAPE_WORK.OUT_B0200_MAIN_LIABILITIES' AS TABELA, '0120_otstndng_amnt' AS CAMPO, COUNT(*) AS NUM_REG, SUM(IF(`0120_otstndng_amnt` != (`0080_otstndng_prncpl_amnt`+`0100_accrd_intrst_instrmnt`+`0110_applcbl_fees_charges`),1 ,0)) AS NUM_REG_DIF, GROUP_CONCAT(CASE WHEN `0120_otstndng_amnt` != (`0080_otstndng_prncpl_amnt`+`0100_accrd_intrst_instrmnt`+`0110_applcbl_fees_charges`) THEN X.CHAVE_IT ELSE NULL END, '; ') AS DETALHE FROM (SELECT *, 0020_UNIQ_ID AS CHAVE_IT, 0120_otstndng_amnt AS CAMPO_IT FROM BU_LOANTAPE_WORK.OUT_B0200_MAIN_LIABILITIES WHERE REF_DATE='"& RefDate &"')X GROUP BY 1
A49: v_2_0011 | B49: 0130_rlvnt_amnt_wdc | C49: 1 | D49: =+VLOOKUP(A49,Descrição!A:K,11,FALSE) -> O montante declarado deve ser igual a: c0120 - c0300 - c0320, exceto para Zero Coupon Bonds para as quais se possam aplicar disposições específicas. | E49: "& RefDate &" | F49: REGULAMENTAR | G49: BU_LOANTAPE_WORK.OUT_B0200_MAIN_LIABILITIES | H49: `0130_rlvnt_amnt_wdc` != GREATEST(0, `0120_otstndng_amnt`-`0300_amnt_cvrd_elgbl_dpsts`-`0320_amnt_clltrl`) AND `0250_strctrd_prdct` IN ('Non-structured/Vanilla', 'Other non-standard terms') AND `0240_zero_coupon` != 'ZCB issued at discount' | I49: =+IF(C49=1,0,1) -> 0 | J49: =+IF(C49=0,"THEN NULL ELSE X.CHAVE_IT END","THEN X.CHAVE_IT ELSE NULL END") -> THEN X.CHAVE_IT ELSE NULL END | K49: ="UNION ALL SELECT '"&E49&"' AS REF_DATE, '"&A49&"' AS COD_KPI, '"&F49&"' AS TIPOLOGIA_TESTE, '"&D49&"' AS DESCRIÇÃO, '"&G49&"' AS TABELA, '"&B49&"' AS CAMPO, COUNT(*) AS NUM_REG, SUM(IF("&H49&","&C49&" ,"&I49&")) AS NUM_REG_DIF, GROUP_CONCAT(CASE WHEN "&H49&" "&J49&", '; ') AS DETALHE FROM (SELECT *, 0020_UNIQ_ID AS CHAVE_IT, "&B49&" AS CAMPO_IT FROM "&G49&" WHERE REF_DATE='"&E49&"')X GROUP BY 1" -> UNION ALL SELECT '"& RefDate &"' AS REF_DATE, 'v_2_0011' AS COD_KPI, 'REGULAMENTAR' AS TIPOLOGIA_TESTE, 'O montante declarado deve ser igual a: c0120 - c0300 - c0320, exceto para Zero Coupon Bonds para as quais se possam aplicar disposições específicas.' AS DESCRIÇÃO, 'BU_LOANTAPE_WORK.OUT_B0200_MAIN_LIABILITIES' AS TABELA, '0130_rlvnt_amnt_wdc' AS CAMPO, COUNT(*) AS NUM_REG, SUM(IF(`0130_rlvnt_amnt_wdc` != GREATEST(0, `0120_otstndng_amnt`-`0300_amnt_cvrd_elgbl_dpsts`-`0320_amnt_clltrl`) AND `0250_strctrd_prdct` IN ('Non-structured/Vanilla', 'Other non-standard terms') AND `0240_zero_coupon` != 'ZCB issued at discount',1 ,0)) AS NUM_REG_DIF, GROUP_CONCAT(CASE WHEN `0130_rlvnt_amnt_wdc` != GREATEST(0, `0120_otstndng_amnt`-`0300_amnt_cvrd_elgbl_dpsts`-`0320_amnt_clltrl`) AND `0250_strctrd_prdct` IN ('Non-structured/Vanilla', 'Other non-standard terms') AND `0240_zero_coupon` != 'ZCB issued at discount' THEN X.CHAVE_IT ELSE NULL END, '; ') AS DETALHE FROM (SELECT *, 0020_UNIQ_ID AS CHAVE_IT, 0130_rlvnt_amnt_wdc AS CAMPO_IT FROM BU_LOANTAPE_WORK.OUT_B0200_MAIN_LIABILITIES WHERE REF_DATE='"& RefDate &"')X GROUP BY 1
A50: v_2_0012 | B50: 0130_rlvnt_amnt_wdc | C50: 1 | D50: =+VLOOKUP(A50,Descrição!A:K,11,FALSE) -> Para produtos estruturados, o montante declarado deve ser igual a: (c0270 - c0300 - c0320) se o valor justo for utilizado para apoiar a determinação do montante relevante para o bail-in, OU (c0120 - c0300 - c0320) caso contrário. | E50: "& RefDate &" | F50: REGULAMENTAR | G50: BU_LOANTAPE_WORK.OUT_B0200_MAIN_LIABILITIES | H50: `0130_rlvnt_amnt_wdc` != GREATEST(0, `0270_fv_amnt_strctrd_prdct`-`0300_amnt_cvrd_elgbl_dpsts`-`0320_amnt_clltrl`) AND `0130_rlvnt_amnt_wdc` != GREATEST(0, `0120_otstndng_amnt`-`0300_amnt_cvrd_elgbl_dpsts`-`0320_amnt_clltrl`) AND `0250_strctrd_prdct` IN ('Structured', 'Structured coupon only') | I50: =+IF(C50=1,0,1) -> 0 | J50: =+IF(C50=0,"THEN NULL ELSE X.CHAVE_IT END","THEN X.CHAVE_IT ELSE NULL END") -> THEN X.CHAVE_IT ELSE NULL END | K50: ="UNION ALL SELECT '"&E50&"' AS REF_DATE, '"&A50&"' AS COD_KPI, '"&F50&"' AS TIPOLOGIA_TESTE, '"&D50&"' AS DESCRIÇÃO, '"&G50&"' AS TABELA, '"&B50&"' AS CAMPO, COUNT(*) AS NUM_REG, SUM(IF("&H50&","&C50&" ,"&I50&")) AS NUM_REG_DIF, GROUP_CONCAT(CASE WHEN "&H50&" "&J50&", '; ') AS DETALHE FROM (SELECT *, 0020_UNIQ_ID AS CHAVE_IT, "&B50&" AS CAMPO_IT FROM "&G50&" WHERE REF_DATE='"&E50&"')X GROUP BY 1" -> UNION ALL SELECT '"& RefDate &"' AS REF_DATE, 'v_2_0012' AS COD_KPI, 'REGULAMENTAR' AS TIPOLOGIA_TESTE, 'Para produtos estruturados, o montante declarado deve ser igual a: (c0270 - c0300 - c0320) se o valor justo for utilizado para apoiar a determinação do montante relevante para o bail-in, OU (c0120 - c0300 - c0320) caso contrário.' AS DESCRIÇÃO, 'BU_LOANTAPE_WORK.OUT_B0200_MAIN_LIABILITIES' AS TABELA, '0130_rlvnt_amnt_wdc' AS CAMPO, COUNT(*) AS NUM_REG, SUM(IF(`0130_rlvnt_amnt_wdc` != GREATEST(0, `0270_fv_amnt_strctrd_prdct`-`0300_amnt_cvrd_elgbl_dpsts`-`0320_amnt_clltrl`) AND `0130_rlvnt_amnt_wdc` != GREATEST(0, `0120_otstndng_amnt`-`0300_amnt_cvrd_elgbl_dpsts`-`0320_amnt_clltrl`) AND `0250_strctrd_prdct` IN ('Structured', 'Structured coupon only'),1 ,0)) AS NUM_REG_DIF, GROUP_CONCAT(CASE WHEN `0130_rlvnt_amnt_wdc` != GREATEST(0, `0270_fv_amnt_strctrd_prdct`-`0300_amnt_cvrd_elgbl_dpsts`-`0320_amnt_clltrl`) AND `0130_rlvnt_amnt_wdc` != GREATEST(0, `0120_otstndng_amnt`-`0300_amnt_cvrd_elgbl_dpsts`-`0320_amnt_clltrl`) AND `0250_strctrd_prdct` IN ('Structured', 'Structured coupon only') THEN X.CHAVE_IT ELSE NULL END, '; ') AS DETALHE FROM (SELECT *, 0020_UNIQ_ID AS CHAVE_IT, 0130_rlvnt_amnt_wdc AS CAMPO_IT FROM BU_LOANTAPE_WORK.OUT_B0200_MAIN_LIABILITIES WHERE REF_DATE='"& RefDate &"')X GROUP BY 1
A51: v_2_0013 | B51: 0140_ntr_lblty | C51: 1 | D51: =+VLOOKUP(A51,Descrição!A:K,11,FALSE) -> Os valores dos dropdowns devem ser respeitados. | E51: "& RefDate &" | F51: REGULAMENTAR | G51: BU_LOANTAPE_WORK.OUT_B0200_MAIN_LIABILITIES | H51: `0140_ntr_lblty` NOT IN ('Registered Bond', 'Bearer Bond', 'Borrower Note Loan', 'Certificate of Deposit / Commercial paper', 'Title of ownership', 'Cash account/saving account', 'Term deposit', 'Loan', 'Bill of exchange ', 'Other') | I51: =+IF(C51=1,0,1) -> 0 | J51: =+IF(C51=0,"THEN NULL ELSE X.CHAVE_IT END","THEN X.CHAVE_IT ELSE NULL END") -> THEN X.CHAVE_IT ELSE NULL END | K51: ="UNION ALL SELECT '"&E51&"' AS REF_DATE, '"&A51&"' AS COD_KPI, '"&F51&"' AS TIPOLOGIA_TESTE, '"&D51&"' AS DESCRIÇÃO, '"&G51&"' AS TABELA, '"&B51&"' AS CAMPO, COUNT(*) AS NUM_REG, SUM(IF("&H51&","&C51&" ,"&I51&")) AS NUM_REG_DIF, GROUP_CONCAT(CASE WHEN "&H51&" "&J51&", '; ') AS DETALHE FROM (SELECT *, 0020_UNIQ_ID AS CHAVE_IT, "&B51&" AS CAMPO_IT FROM "&G51&" WHERE REF_DATE='"&E51&"')X GROUP BY 1" -> UNION ALL SELECT '"& RefDate &"' AS REF_DATE, 'v_2_0013' AS COD_KPI, 'REGULAMENTAR' AS TIPOLOGIA_TESTE, 'Os valores dos dropdowns devem ser respeitados.' AS DESCRIÇÃO, 'BU_LOANTAPE_WORK.OUT_B0200_MAIN_LIABILITIES' AS TABELA, '0140_ntr_lblty' AS CAMPO, COUNT(*) AS NUM_REG, SUM(IF(`0140_ntr_lblty` NOT IN ('Registered Bond', 'Bearer Bond', 'Borrower Note Loan', 'Certificate of Deposit / Commercial paper', 'Title of ownership', 'Cash account/saving account', 'Term deposit', 'Loan', 'Bill of exchange ', 'Other'),1 ,0)) AS NUM_REG_DIF, GROUP_CONCAT(CASE WHEN `0140_ntr_lblty` NOT IN ('Registered Bond', 'Bearer Bond', 'Borrower Note Loan', 'Certificate of Deposit / Commercial paper', 'Title of ownership', 'Cash account/saving account', 'Term deposit', 'Loan', 'Bill of exchange ', 'Other') THEN X.CHAVE_IT ELSE NULL END, '; ') AS DETALHE FROM (SELECT *, 0020_UNIQ_ID AS CHAVE_IT, 0140_ntr_lblty AS CAMPO_IT FROM BU_LOANTAPE_WORK.OUT_B0200_MAIN_LIABILITIES WHERE REF_DATE='"& RefDate &"')X GROUP BY 1
A52: v_2_0014 | B52: 0160_rank_insolv | C52: 1 | D52: =+VLOOKUP(A52,Descrição!A:K,11,FALSE) -> Os valores numéricos a partir de 1 devem ser reportados. | E52: "& RefDate &" | F52: REGULAMENTAR | G52: BU_LOANTAPE_WORK.OUT_B0200_MAIN_LIABILITIES | H52: CAST(`0160_rank_insolv` AS STRING) NOT REGEXP '^-?[0-9]+$' | I52: =+IF(C52=1,0,1) -> 0 | J52: =+IF(C52=0,"THEN NULL ELSE X.CHAVE_IT END","THEN X.CHAVE_IT ELSE NULL END") -> THEN X.CHAVE_IT ELSE NULL END | K52: ="UNION ALL SELECT '"&E52&"' AS REF_DATE, '"&A52&"' AS COD_KPI, '"&F52&"' AS TIPOLOGIA_TESTE, '"&D52&"' AS DESCRIÇÃO, '"&G52&"' AS TABELA, '"&B52&"' AS CAMPO, COUNT(*) AS NUM_REG, SUM(IF("&H52&","&C52&" ,"&I52&")) AS NUM_REG_DIF, GROUP_CONCAT(CASE WHEN "&H52&" "&J52&", '; ') AS DETALHE FROM (SELECT *, 0020_UNIQ_ID AS CHAVE_IT, "&B52&" AS CAMPO_IT FROM "&G52&" WHERE REF_DATE='"&E52&"')X GROUP BY 1" -> UNION ALL SELECT '"& RefDate &"' AS REF_DATE, 'v_2_0014' AS COD_KPI, 'REGULAMENTAR' AS TIPOLOGIA_TESTE, 'Os valores numéricos a partir de 1 devem ser reportados.' AS DESCRIÇÃO, 'BU_LOANTAPE_WORK.OUT_B0200_MAIN_LIABILITIES' AS TABELA, '0160_rank_insolv' AS CAMPO, COUNT(*) AS NUM_REG, SUM(IF(CAST(`0160_rank_insolv` AS STRING) NOT REGEXP '^-?[0-9]+$',1 ,0)) AS NUM_REG_DIF, GROUP_CONCAT(CASE WHEN CAST(`0160_rank_insolv` AS STRING) NOT REGEXP '^-?[0-9]+$' THEN X.CHAVE_IT ELSE NULL END, '; ') AS DETALHE FROM (SELECT *, 0020_UNIQ_ID AS CHAVE_IT, 0160_rank_insolv AS CAMPO_IT FROM BU_LOANTAPE_WORK.OUT_B0200_MAIN_LIABILITIES WHERE REF_DATE='"& RefDate &"')X GROUP BY 1
... A55: v_2_0017 | B55: 0180_dt_nxt_intrst_pymnt | C55: 1 | D55: =+VLOOKUP(A55,Descrição!A:K,11,FALSE) -> O valor reportado deve ser uma data (yyy-mm-dd). | E55: "& RefDate &" | F55: REGULAMENTAR | G55: BU_LOANTAPE_WORK.OUT_B0200_MAIN_LIABILITIES | H55: `0180_dt_nxt_intrst_pymnt` NOT REGEXP '^[0-9]{4}-[0-9]{2}-[0-9]{2}$' AND `0020_uniq_id` NOT IN ('NCNP', 'NCBP') | I55: =+IF(C55=1,0,1) -> 0 | J55: =+IF(C55=0,"THEN NULL ELSE X.CHAVE_IT END","THEN X.CHAVE_IT ELSE NULL END") -> THEN X.CHAVE_IT ELSE NULL END | K55: ="UNION ALL SELECT '"&E55&"' AS REF_DATE, '"&A55&"' AS COD_KPI, '"&F55&"' AS TIPOLOGIA_TESTE, '"&D55&"' AS DESCRIÇÃO, '"&G55&"' AS TABELA, '"&B55&"' AS CAMPO, COUNT(*) AS NUM_REG, SUM(IF("&H55&","&C55&" ,"&I55&")) AS NUM_REG_DIF, GROUP_CONCAT(CASE WHEN "&H55&" "&J55&", '; ') AS DETALHE FROM (SELECT *, 0020_UNIQ_ID AS CHAVE_IT, "&B55&" AS CAMPO_IT FROM "&G55&" WHERE REF_DATE='"&E55&"')X GROUP BY 1" -> UNION ALL SELECT '"& RefDate &"' AS REF_DATE, 'v_2_0017' AS COD_KPI, 'REGULAMENTAR' AS TIPOLOGIA_TESTE, 'O valor reportado deve ser uma data (yyy-mm-dd).' AS DESCRIÇÃO, 'BU_LOANTAPE_WORK.OUT_B0200_MAIN_LIABILITIES' AS TABELA, '0180_dt_nxt_intrst_pymnt' AS CAMPO, COUNT(*) AS NUM_REG, SUM(IF(`0180_dt_nxt_intrst_pymnt` NOT REGEXP '^[0-9]{4}-[0-9]{2}-[0-9]{2}$' AND `0020_uniq_id` NOT IN ('NCNP', 'NCBP'),1 ,0)) AS NUM_REG_DIF, GROUP_CONCAT(CASE WHEN `0180_dt_nxt_intrst_pymnt` NOT REGEXP '^[0-9]{4}-[0-9]{2}-[0-9]{2}$' AND `0020_uniq_id` NOT IN ('NCNP', 'NCBP') THEN X.CHAVE_IT ELSE NULL END, '; ') AS DETALHE FROM (SELECT *, 0020_UNIQ_ID AS CHAVE_IT, 0180_dt_nxt_intrst_pymnt AS CAMPO_IT FROM BU_LOANTAPE_WORK.OUT_B0200_MAIN_LIABILITIES WHERE REF_DATE='"& RefDate &"')X GROUP BY 1
A56: v_2_0018 | B56: 0180_dt_nxt_intrst_pymnt | C56: 0 | D56: =+VLOOKUP(A56,Descrição!A:K,11,FALSE) -> O valor declarado deve ser posterior à data de referência reportada em B99.00 (c0070). | E56: "& RefDate &" | F56: REGULAMENTAR | G56: BU_LOANTAPE_WORK.OUT_B0200_MAIN_LIABILITIES | H56: (`0180_dt_nxt_intrst_pymnt` > `0070_cntrct_crrncy` AND `0070_cntrct_crrncy` != '' AND `0020_uniq_id` NOT IN ('NCNP', 'NCBP')) OR `0180_dt_nxt_intrst_pymnt` IN ('0001-01-01', '') | I56: =+IF(C56=1,0,1) -> 1 | J56: =+IF(C56=0,"THEN NULL ELSE X.CHAVE_IT END","THEN X.CHAVE_IT ELSE NULL END") -> THEN NULL ELSE X.CHAVE_IT END | K56: ="--UNION ALL SELECT '"&E56&"' AS REF_DATE, '"&A56&"' AS COD_KPI, '"&F56&"' AS TIPOLOGIA_TESTE, '"&D56&"' AS DESCRIÇÃO, '"&G56&"' AS TABELA, '"&B56&"' AS CAMPO, COUNT(*) AS NUM_REG, SUM(IF("&H56&","&C56&" ,"&I56&")) AS NUM_REG_DIF, GROUP_CONCAT(CASE WHEN "&H56&" "&J56&", '; ') AS DETALHE FROM (SELECT *, 0020_UNIQ_ID AS CHAVE_IT, "&B56&" AS CAMPO_IT FROM "&G56&" WHERE REF_DATE='"&E56&"')X GROUP BY 1" -> --UNION ALL SELECT '"& RefDate &"' AS REF_DATE, 'v_2_0018' AS COD_KPI, 'REGULAMENTAR' AS TIPOLOGIA_TESTE, 'O valor declarado deve ser posterior à data de referência reportada em B99.00 (c0070).' AS DESCRIÇÃO, 'BU_LOANTAPE_WORK.OUT_B0200_MAIN_LIABILITIES' AS TABELA, '0180_dt_nxt_intrst_pymnt' AS CAMPO, COUNT(*) AS NUM_REG, SUM(IF((`0180_dt_nxt_intrst_pymnt` > `0070_cntrct_crrncy` AND `0070_cntrct_crrncy` != '' AND `0020_uniq_id` NOT IN ('NCNP', 'NCBP')) OR `0180_dt_nxt_intrst_pymnt` IN ('0001-01-01', ''),0 ,1)) AS NUM_REG_DIF, GROUP_CONCAT(CASE WHEN (`0180_dt_nxt_intrst_pymnt` > `0070_cntrct_crrncy` AND `0070_cntrct_crrncy` != '' AND `0020_uniq_id` NOT IN ('NCNP', 'NCBP')) OR `0180_dt_nxt_intrst_pymnt` IN ('0001-01-01', '') THEN NULL ELSE X.CHAVE_IT END, '; ') AS DETALHE FROM (SELECT *, 0020_UNIQ_ID AS CHAVE_IT, 0180_dt_nxt_intrst_pymnt AS CAMPO_IT FROM BU_LOANTAPE_WORK.OUT_B0200_MAIN_LIABILITIES WHERE REF_DATE='"& RefDate &"')X GROUP BY 1
A57: v_2_0019 | B57: 0200_dt_erlst_rdmptn | C57: 1 | D57: =+VLOOKUP(A57,Descrição!A:K,11,FALSE) -> O valor reportado deve ser uma data (yyy-mm-dd). | E57: "& RefDate &" | F57: REGULAMENTAR | G57: BU_LOANTAPE_WORK.OUT_B0200_MAIN_LIABILITIES | H57: `0200_dt_erlst_rdmptn` NOT REGEXP '^[0-9]{4}-[0-9]{2}-[0-9]{2}$' AND `0020_uniq_id` NOT IN ('NCNP', 'NCBP') | I57: =+IF(C57=1,0,1) -> 0 | J57: =+IF(C57=0,"THEN NULL ELSE X.CHAVE_IT END","THEN X.CHAVE_IT ELSE NULL END") -> THEN X.CHAVE_IT ELSE NULL END | K57: ="UNION ALL SELECT '"&E57&"' AS REF_DATE, '"&A57&"' AS COD_KPI, '"&F57&"' AS TIPOLOGIA_TESTE, '"&D57&"' AS DESCRIÇÃO, '"&G57&"' AS TABELA, '"&B57&"' AS CAMPO, COUNT(*) AS NUM_REG, SUM(IF("&H57&","&C57&" ,"&I57&")) AS NUM_REG_DIF, GROUP_CONCAT(CASE WHEN "&H57&" "&J57&", '; ') AS DETALHE FROM (SELECT *, 0020_UNIQ_ID AS CHAVE_IT, "&B57&" AS CAMPO_IT FROM "&G57&" WHERE REF_DATE='"&E57&"')X GROUP BY 1" -> UNION ALL SELECT '"& RefDate &"' AS REF_DATE, 'v_2_0019' AS COD_KPI, 'REGULAMENTAR' AS TIPOLOGIA_TESTE, 'O valor reportado deve ser uma data (yyy-mm-dd).' AS DESCRIÇÃO, 'BU_LOANTAPE_WORK.OUT_B0200_MAIN_LIABILITIES' AS TABELA, '0200_dt_erlst_rdmptn' AS CAMPO, COUNT(*) AS NUM_REG, SUM(IF(`0200_dt_erlst_rdmptn` NOT REGEXP '^[0-9]{4}-[0-9]{2}-[0-9]{2}$' AND `0020_uniq_id` NOT IN ('NCNP', 'NCBP'),1 ,0)) AS NUM_REG_DIF, GROUP_CONCAT(CASE WHEN `0200_dt_erlst_rdmptn` NOT REGEXP '^[0-9]{4}-[0-9]{2}-[0-9]{2}$' AND `0020_uniq_id` NOT IN ('NCNP', 'NCBP') THEN X.CHAVE_IT ELSE NULL END, '; ') AS DETALHE FROM (SELECT *, 0020_UNIQ_ID AS CHAVE_IT, 0200_dt_erlst_rdmptn AS CAMPO_IT FROM BU_LOANTAPE_WORK.OUT_B0200_MAIN_LIABILITIES WHERE REF_DATE='"& RefDate &"')X GROUP BY 1
A58: v_2_0020 | B58: 0200_dt_erlst_rdmptn | C58: 0 | D58: =+VLOOKUP(A58,Descrição!A:K,11,FALSE) -> O valor declarado deve ser posterior à data de referência reportada em B99.00 (c0070). | E58: "& RefDate &" | F58: REGULAMENTAR | G58: BU_LOANTAPE_WORK.OUT_B0200_MAIN_LIABILITIES | H58: (`0200_dt_erlst_rdmptn` > `0070_cntrct_crrncy` AND `0070_cntrct_crrncy` != '' AND `0020_uniq_id` NOT IN ('NCNP', 'NCBP')) OR `0200_dt_erlst_rdmptn` IN ('0001-01-01') | I58: =+IF(C58=1,0,1) -> 1 | J58: =+IF(C58=0,"THEN NULL ELSE X.CHAVE_IT END","THEN X.CHAVE_IT ELSE NULL END") -> THEN NULL ELSE X.CHAVE_IT END | K58: ="--UNION ALL SELECT '"&E58&"' AS REF_DATE, '"&A58&"' AS COD_KPI, '"&F58&"' AS TIPOLOGIA_TESTE, '"&D58&"' AS DESCRIÇÃO, '"&G58&"' AS TABELA, '"&B58&"' AS CAMPO, COUNT(*) AS NUM_REG, SUM(IF("&H58&","&C58&" ,"&I58&")) AS NUM_REG_DIF, GROUP_CONCAT(CASE WHEN "&H58&" "&J58&", '; ') AS DETALHE FROM (SELECT *, 0020_UNIQ_ID AS CHAVE_IT, "&B58&" AS CAMPO_IT FROM "&G58&" WHERE REF_DATE='"&E58&"')X GROUP BY 1" -> --UNION ALL SELECT '"& RefDate &"' AS REF_DATE, 'v_2_0020' AS COD_KPI, 'REGULAMENTAR' AS TIPOLOGIA_TESTE, 'O valor declarado deve ser posterior à data de referência reportada em B99.00 (c0070).' AS DESCRIÇÃO, 'BU_LOANTAPE_WORK.OUT_B0200_MAIN_LIABILITIES' AS TABELA, '0200_dt_erlst_rdmptn' AS CAMPO, COUNT(*) AS NUM_REG, SUM(IF((`0200_dt_erlst_rdmptn` > `0070_cntrct_crrncy` AND `0070_cntrct_crrncy` != '' AND `0020_uniq_id` NOT IN ('NCNP', 'NCBP')) OR `0200_dt_erlst_rdmptn` IN ('0001-01-01'),0 ,1)) AS NUM_REG_DIF, GROUP_CONCAT(CASE WHEN (`0200_dt_erlst_rdmptn` > `0070_cntrct_crrncy` AND `0070_cntrct_crrncy` != '' AND `0020_uniq_id` NOT IN ('NCNP', 'NCBP')) OR `0200_dt_erlst_rdmptn` IN ('0001-01-01') THEN NULL ELSE X.CHAVE_IT END, '; ') AS DETALHE FROM (SELECT *, 0020_UNIQ_ID AS CHAVE_IT, 0200_dt_erlst_rdmptn AS CAMPO_IT FROM BU_LOANTAPE_WORK.OUT_B0200_MAIN_LIABILITIES WHERE REF_DATE='"& RefDate &"')X GROUP BY 1
A59: v_2_0021 | B59: 0210_dt_lgl_fnl_mtrty | C59: 1 | D59: =+VLOOKUP(A59,Descrição!A:K,11,FALSE) -> O valor reportado deve ser uma data (yyy-mm-dd). | E59: "& RefDate &" | F59: REGULAMENTAR | G59: BU_LOANTAPE_WORK.OUT_B0200_MAIN_LIABILITIES | H59: `0210_dt_lgl_fnl_mtrty` NOT REGEXP '^[0-9]{4}-[0-9]{2}-[0-9]{2}$' AND `0020_uniq_id` NOT IN ('NCNP', 'NCBP') | I59: =+IF(C59=1,0,1) -> 0 | J59: =+IF(C59=0,"THEN NULL ELSE X.CHAVE_IT END","THEN X.CHAVE_IT ELSE NULL END") -> THEN X.CHAVE_IT ELSE NULL END | K59: ="UNION ALL SELECT '"&E59&"' AS REF_DATE, '"&A59&"' AS COD_KPI, '"&F59&"' AS TIPOLOGIA_TESTE, '"&D59&"' AS DESCRIÇÃO, '"&G59&"' AS TABELA, '"&B59&"' AS CAMPO, COUNT(*) AS NUM_REG, SUM(IF("&H59&","&C59&" ,"&I59&")) AS NUM_REG_DIF, GROUP_CONCAT(CASE WHEN "&H59&" "&J59&", '; ') AS DETALHE FROM (SELECT *, 0020_UNIQ_ID AS CHAVE_IT, "&B59&" AS CAMPO_IT FROM "&G59&" WHERE REF_DATE='"&E59&"')X GROUP BY 1" -> UNION ALL SELECT '"& RefDate &"' AS REF_DATE, 'v_2_0021' AS COD_KPI, 'REGULAMENTAR' AS TIPOLOGIA_TESTE, 'O valor reportado deve ser uma data (yyy-mm-dd).' AS DESCRIÇÃO, 'BU_LOANTAPE_WORK.OUT_B0200_MAIN_LIABILITIES' AS TABELA, '0210_dt_lgl_fnl_mtrty' AS CAMPO, COUNT(*) AS NUM_REG, SUM(IF(`0210_dt_lgl_fnl_mtrty` NOT REGEXP '^[0-9]{4}-[0-9]{2}-[0-9]{2}$' AND `0020_uniq_id` NOT IN ('NCNP', 'NCBP'),1 ,0)) AS NUM_REG_DIF, GROUP_CONCAT(CASE WHEN `0210_dt_lgl_fnl_mtrty` NOT REGEXP '^[0-9]{4}-[0-9]{2}-[0-9]{2}$' AND `0020_uniq_id` NOT IN ('NCNP', 'NCBP') THEN X.CHAVE_IT ELSE NULL END, '; ') AS DETALHE FROM (SELECT *, 0020_UNIQ_ID AS CHAVE_IT, 0210_dt_lgl_fnl_mtrty AS CAMPO_IT FROM BU_LOANTAPE_WORK.OUT_B0200_MAIN_LIABILITIES WHERE REF_DATE='"& RefDate &"')X GROUP BY 1
A60: v_2_0022 | B60: 0210_dt_lgl_fnl_mtrty | C60: 0 | D60: =+VLOOKUP(A60,Descrição!A:K,11,FALSE) -> O valor declarado deve ser posterior à data de referência reportada em B99.00 (c0070). | E60: "& RefDate &" | F60: REGULAMENTAR | G60: BU_LOANTAPE_WORK.OUT_B0200_MAIN_LIABILITIES | H60: `0210_dt_lgl_fnl_mtrty` > `0070_cntrct_crrncy` AND `0070_cntrct_crrncy` != '' AND `0020_uniq_id` NOT IN ('NCNP', 'NCBP') | I60: =+IF(C60=1,0,1) -> 1 | J60: =+IF(C60=0,"THEN NULL ELSE X.CHAVE_IT END","THEN X.CHAVE_IT ELSE NULL END") -> THEN NULL ELSE X.CHAVE_IT END | K60: ="--UNION ALL SELECT '"&E60&"' AS REF_DATE, '"&A60&"' AS COD_KPI, '"&F60&"' AS TIPOLOGIA_TESTE, '"&D60&"' AS DESCRIÇÃO, '"&G60&"' AS TABELA, '"&B60&"' AS CAMPO, COUNT(*) AS NUM_REG, SUM(IF("&H60&","&C60&" ,"&I60&")) AS NUM_REG_DIF, GROUP_CONCAT(CASE WHEN "&H60&" "&J60&", '; ') AS DETALHE FROM (SELECT *, 0020_UNIQ_ID AS CHAVE_IT, "&B60&" AS CAMPO_IT FROM "&G60&" WHERE REF_DATE='"&E60&"')X GROUP BY 1" -> --UNION ALL SELECT '"& RefDate &"' AS REF_DATE, 'v_2_0022' AS COD_KPI, 'REGULAMENTAR' AS TIPOLOGIA_TESTE, 'O valor declarado deve ser posterior à data de referência reportada em B99.00 (c0070).' AS DESCRIÇÃO, 'BU_LOANTAPE_WORK.OUT_B0200_MAIN_LIABILITIES' AS TABELA, '0210_dt_lgl_fnl_mtrty' AS CAMPO, COUNT(*) AS NUM_REG, SUM(IF(`0210_dt_lgl_fnl_mtrty` > `0070_cntrct_crrncy` AND `0070_cntrct_crrncy` != '' AND `0020_uniq_id` NOT IN ('NCNP', 'NCBP'),0 ,1)) AS NUM_REG_DIF, GROUP_CONCAT(CASE WHEN `0210_dt_lgl_fnl_mtrty` > `0070_cntrct_crrncy` AND `0070_cntrct_crrncy` != '' AND `0020_uniq_id` NOT IN ('NCNP', 'NCBP') THEN NULL ELSE X.CHAVE_IT END, '; ') AS DETALHE FROM (SELECT *, 0020_UNIQ_ID AS CHAVE_IT, 0210_dt_lgl_fnl_mtrty AS CAMPO_IT FROM BU_LOANTAPE_WORK.OUT_B0200_MAIN_LIABILITIES WHERE REF_DATE='"& RefDate &"')X GROUP BY 1
A61: v_2_0023 | B61: 0220_governing_law | C61: 1 | D61: =+VLOOKUP(A61,Descrição!A:K,11,FALSE) -> A legislação aplicável deve ser reportada utilizando o código ISO 3166-1 alpha-2. | E61: "& RefDate &" | F61: REGULAMENTAR | G61: BU_LOANTAPE_WORK.OUT_B0200_MAIN_LIABILITIES | H61: `0020_uniq_id` NOT IN ('NCNP', 'NCBP') AND `0220_governing_law` NOT IN ('AF','AX','AL','DZ','AS','AD','AO','AI','AQ','AG','AR','AM','AW','AU','AT','AZ','BS','BH','BD','BB','BY','BE','BZ','BJ','BM','BT','BO','BQ','BA','BW','BV','BR','IO','BN','BG','BF','BI','CV','KH','CM','CA','KY','CF','TD','CL','CN','CX','CC','CO','KM','CG','CD','CK','CR','CI','HR','CU','CW','CY','CZ','DK','DJ','DM','DO','EC','EG','SV','GQ','ER','EE','SZ','ET','FK','FO','FJ','FI','FR','GF','PF','TF','GA','GM','GE','DE','GH','GI','GR','GL','GD','GP','GU','GT','GG','GN','GW','GY','HT','HM','VA','HN','HK','HU','IS','IN','ID','IR','IQ','IE','IM','IL','IT','JM','JP','JE','JO','KZ','KE','KI','KP','KR','KW','KG','LA','LV','LB','LS','LR','LY','LI','LT','LU','MO','MG','MW','MY','MV','ML','MT','MH','MQ','MR','MU','YT','MX','FM','MD','MC','MN','ME','MS','MA','MZ','MM','NA','NR','NP','NL','NC','NZ','NI','NE','NG','NU','NF','MK','MP','NO','OM','PK','PW','PS','PA','PG','PY','PE','PH','PN','PL','PT','PR','QA','RE','RO','RU','RW','BL','SH','KN','LC','MF','PM','VC','WS','SM','ST','SA','SN','RS','SC','SL','SG','SX','SK','SI','SB','SO','ZA','GS','SS','ES','LK','SD','SR','SJ','SE','CH','SY','TW','TJ','TZ','TH','TL','TG','TK','TO','TT','TN','TR','TM','TC','TV','UG','UA','AE','GB','US','UM','UY','UZ','VU','VE','VN','VG','VI','WF','EH','YE','ZM','ZW') | I61: =+IF(C61=1,0,1) -> 0 | J61: =+IF(C61=0,"THEN NULL ELSE X.CHAVE_IT END","THEN X.CHAVE_IT ELSE NULL END") -> THEN X.CHAVE_IT ELSE NULL END | K61: ="UNION ALL SELECT '"&E61&"' AS REF_DATE, '"&A61&"' AS COD_KPI, '"&F61&"' AS TIPOLOGIA_TESTE, '"&D61&"' AS DESCRIÇÃO, '"&G61&"' AS TABELA, '"&B61&"' AS CAMPO, COUNT(*) AS NUM_REG, SUM(IF("&H61&","&C61&" ,"&I61&")) AS NUM_REG_DIF, GROUP_CONCAT(CASE WHEN "&H61&" "&J61&", '; ') AS DETALHE FROM (SELECT *, 0020_UNIQ_ID AS CHAVE_IT, "&B61&" AS CAMPO_IT FROM "&G61&" WHERE REF_DATE='"&E61&"')X GROUP BY 1" -> UNION ALL SELECT '"& RefDate &"' AS REF_DATE, 'v_2_0023' AS COD_KPI, 'REGULAMENTAR' AS TIPOLOGIA_TESTE, 'A legislação aplicável deve ser reportada utilizando o código ISO 3166-1 alpha-2.' AS DESCRIÇÃO, 'BU_LOANTAPE_WORK.OUT_B0200_MAIN_LIABILITIES' AS TABELA, '0220_governing_law' AS CAMPO, COUNT(*) AS NUM_REG, SUM(IF(`0020_uniq_id` NOT IN ('NCNP', 'NCBP') AND `0220_governing_law` NOT IN ('AF','AX','AL','DZ','AS','AD','AO','AI','AQ','AG','AR','AM','AW','AU','AT','AZ','BS','BH','BD','BB','BY','BE','BZ','BJ','BM','BT','BO','BQ','BA','BW','BV','BR','IO','BN','BG','BF','BI','CV','KH','CM','CA','KY','CF','TD','CL','CN','CX','CC','CO','KM','CG','CD','CK','CR','CI','HR','CU','CW','CY','CZ','DK','DJ','DM','DO','EC','EG','SV','GQ','ER','EE','SZ','ET','FK','FO','FJ','FI','FR','GF','PF','TF','GA','GM','GE','DE','GH','GI','GR','GL','GD','GP','GU','GT','GG','GN','GW','GY','HT','HM','VA','HN','HK','HU','IS','IN','ID','IR','IQ','IE','IM','IL','IT','JM','JP','JE','JO','KZ','KE','KI','KP','KR','KW','KG','LA','LV','LB','LS','LR','LY','LI','LT','LU','MO','MG','MW','MY','MV','ML','MT','MH','MQ','MR','MU','YT','MX','FM','MD','MC','MN','ME','MS','MA','MZ','MM','NA','NR','NP','NL','NC','NZ','NI','NE','NG','NU','NF','MK','MP','NO','OM','PK','PW','PS','PA','PG','PY','PE','PH','PN','PL','PT','PR','QA','RE','RO','RU','RW','BL','SH','KN','LC','MF','PM','VC','WS','SM','ST','SA','SN','RS','SC','SL','SG','SX','SK','SI','SB','SO','ZA','GS','SS','ES','LK','SD','SR','SJ','SE','CH','SY','TW','TJ','TZ','TH','TL','TG','TK','TO','TT','TN','TR','TM','TC','TV','UG','UA','AE','GB','US','UM','UY','UZ','VU','VE','VN','VG','VI','WF','EH','YE','ZM','ZW'),1 ,0)) AS NUM_REG_DIF, GROUP_CONCAT(CASE WHEN `0020_uniq_id` NOT IN ('NCNP', 'NCBP') AND `0220_governing_law` NOT IN ('AF','AX','AL','DZ','AS','AD','AO','AI','AQ','AG','AR','AM','AW','AU','AT','AZ','BS','BH','BD','BB','BY','BE','BZ','BJ','BM','BT','BO','BQ','BA','BW','BV','BR','IO','BN','BG','BF','BI','CV','KH','CM','CA','KY','CF','TD','CL','CN','CX','CC','CO','KM','CG','CD','CK','CR','CI','HR','CU','CW','CY','CZ','DK','DJ','DM','DO','EC','EG','SV','GQ','ER','EE','SZ','ET','FK','FO','FJ','FI','FR','GF','PF','TF','GA','GM','GE','DE','GH','GI','GR','GL','GD','GP','GU','GT','GG','GN','GW','GY','HT','HM','VA','HN','HK','HU','IS','IN','ID','IR','IQ','IE','IM','IL','IT','JM','JP','JE','JO','KZ','KE','KI','KP','KR','KW','KG','LA','LV','LB','LS','LR','LY','LI','LT','LU','MO','MG','MW','MY','MV','ML','MT','MH','MQ','MR','MU','YT','MX','FM','MD','MC','MN','ME','MS','MA','MZ','MM','NA','NR','NP','NL','NC','NZ','NI','NE','NG','NU','NF','MK','MP','NO','OM','PK','PW','PS','PA','PG','PY','PE','PH','PN','PL','PT','PR','QA','RE','RO','RU','RW','BL','SH','KN','LC','MF','PM','VC','WS','SM','ST','SA','SN','RS','SC','SL','SG','SX','SK','SI','SB','SO','ZA','GS','SS','ES','LK','SD','SR','SJ','SE','CH','SY','TW','TJ','TZ','TH','TL','TG','TK','TO','TT','TN','TR','TM','TC','TV','UG','UA','AE','GB','US','UM','UY','UZ','VU','VE','VN','VG','VI','WF','EH','YE','ZM','ZW') THEN X.CHAVE_IT ELSE NULL END, '; ') AS DETALHE FROM (SELECT *, 0020_UNIQ_ID AS CHAVE_IT, 0220_governing_law AS CAMPO_IT FROM BU_LOANTAPE_WORK.OUT_B0200_MAIN_LIABILITIES WHERE REF_DATE='"& RefDate &"')X GROUP BY 1
A62: v_2_0024 | B62: 0230_bail_in_rcgntn_cls | C62: 1 | D62: =+VLOOKUP(A62,Descrição!A:K,11,FALSE) -> Os valores dos dropdowns devem ser respeitados. | E62: "& RefDate &" | F62: REGULAMENTAR | G62: BU_LOANTAPE_WORK.OUT_B0200_MAIN_LIABILITIES | H62: `0230_bail_in_rcgntn_cls` NOT IN ('Yes, supported by Legal Opinion', 'Yes, not supported by Legal Opinion', 'No', 'Not applicable', 'Aggregated') AND `0020_uniq_id` NOT IN ('NCNP', 'NCBP') | I62: =+IF(C62=1,0,1) -> 0 | J62: =+IF(C62=0,"THEN NULL ELSE X.CHAVE_IT END","THEN X.CHAVE_IT ELSE NULL END") -> THEN X.CHAVE_IT ELSE NULL END | K62: ="UNION ALL SELECT '"&E62&"' AS REF_DATE, '"&A62&"' AS COD_KPI, '"&F62&"' AS TIPOLOGIA_TESTE, '"&D62&"' AS DESCRIÇÃO, '"&G62&"' AS TABELA, '"&B62&"' AS CAMPO, COUNT(*) AS NUM_REG, SUM(IF("&H62&","&C62&" ,"&I62&")) AS NUM_REG_DIF, GROUP_CONCAT(CASE WHEN "&H62&" "&J62&", '; ') AS DETALHE FROM (SELECT *, 0020_UNIQ_ID AS CHAVE_IT, "&B62&" AS CAMPO_IT FROM "&G62&" WHERE REF_DATE='"&E62&"')X GROUP BY 1" -> UNION ALL SELECT '"& RefDate &"' AS REF_DATE, 'v_2_0024' AS COD_KPI, 'REGULAMENTAR' AS TIPOLOGIA_TESTE, 'Os valores dos dropdowns devem ser respeitados.' AS DESCRIÇÃO, 'BU_LOANTAPE_WORK.OUT_B0200_MAIN_LIABILITIES' AS TABELA, '0230_bail_in_rcgntn_cls' AS CAMPO, COUNT(*) AS NUM_REG, SUM(IF(`0230_bail_in_rcgntn_cls` NOT IN ('Yes, supported by Legal Opinion', 'Yes, not supported by Legal Opinion', 'No', 'Not applicable', 'Aggregated') AND `0020_uniq_id` NOT IN ('NCNP', 'NCBP'),1 ,0)) AS NUM_REG_DIF, GROUP_CONCAT(CASE WHEN `0230_bail_in_rcgntn_cls` NOT IN ('Yes, supported by Legal Opinion', 'Yes, not supported by Legal Opinion', 'No', 'Not applicable', 'Aggregated') AND `0020_uniq_id` NOT IN ('NCNP', 'NCBP') THEN X.CHAVE_IT ELSE NULL END, '; ') AS DETALHE FROM (SELECT *, 0020_UNIQ_ID AS CHAVE_IT, 0230_bail_in_rcgntn_cls AS CAMPO_IT FROM BU_LOANTAPE_WORK.OUT_B0200_MAIN_LIABILITIES WHERE REF_DATE='"& RefDate &"')X GROUP BY 1
A63: v_2_0025 | B63: 0250_strctrd_prdct | C63: 1 | D63: =+VLOOKUP(A63,Descrição!A:K,11,FALSE) -> Os valores dos dropdowns devem ser respeitados. | E63: "& RefDate &" | F63: REGULAMENTAR | G63: BU_LOANTAPE_WORK.OUT_B0200_MAIN_LIABILITIES | H63: `0250_strctrd_prdct` NOT IN ('Non-structured/Vanilla', 'Structured', 'Other non-standard terms', 'Only structured coupon', 'Aggregated') | I63: =+IF(C63=1,0,1) -> 0 | J63: =+IF(C63=0,"THEN NULL ELSE X.CHAVE_IT END","THEN X.CHAVE_IT ELSE NULL END") -> THEN X.CHAVE_IT ELSE NULL END | K63: ="UNION ALL SELECT '"&E63&"' AS REF_DATE, '"&A63&"' AS COD_KPI, '"&F63&"' AS TIPOLOGIA_TESTE, '"&D63&"' AS DESCRIÇÃO, '"&G63&"' AS TABELA, '"&B63&"' AS CAMPO, COUNT(*) AS NUM_REG, SUM(IF("&H63&","&C63&" ,"&I63&")) AS NUM_REG_DIF, GROUP_CONCAT(CASE WHEN "&H63&" "&J63&", '; ') AS DETALHE FROM (SELECT *, 0020_UNIQ_ID AS CHAVE_IT, "&B63&" AS CAMPO_IT FROM "&G63&" WHERE REF_DATE='"&E63&"')X GROUP BY 1" -> UNION ALL SELECT '"& RefDate &"' AS REF_DATE, 'v_2_0025' AS COD_KPI, 'REGULAMENTAR' AS TIPOLOGIA_TESTE, 'Os valores dos dropdowns devem ser respeitados.' AS DESCRIÇÃO, 'BU_LOANTAPE_WORK.OUT_B0200_MAIN_LIABILITIES' AS TABELA, '0250_strctrd_prdct' AS CAMPO, COUNT(*) AS NUM_REG, SUM(IF(`0250_strctrd_prdct` NOT IN ('Non-structured/Vanilla', 'Structured', 'Other non-standard terms', 'Only structured coupon', 'Aggregated'),1 ,0)) AS NUM_REG_DIF, GROUP_CONCAT(CASE WHEN `0250_strctrd_prdct` NOT IN ('Non-structured/Vanilla', 'Structured', 'Other non-standard terms', 'Only structured coupon', 'Aggregated') THEN X.CHAVE_IT ELSE NULL END, '; ') AS DETALHE FROM (SELECT *, 0020_UNIQ_ID AS CHAVE_IT, 0250_strctrd_prdct AS CAMPO_IT FROM BU_LOANTAPE_WORK.OUT_B0200_MAIN_LIABILITIES WHERE REF_DATE='"& RefDate &"')X GROUP BY 1
A64: v_2_0026 | B64: 0310_flg_clltrl_agrmnts | C64: 1 | D64: =+VLOOKUP(A64,Descrição!A:K,11,FALSE) -> Os valores dos dropdowns devem ser respeitados. | E64: "& RefDate &" | F64: REGULAMENTAR | G64: BU_LOANTAPE_WORK.OUT_B0200_MAIN_LIABILITIES | H64: `0310_flg_clltrl_agrmnts` NOT IN ('Secured', 'Unsecured') | I64: =+IF(C64=1,0,1) -> 0 | J64: =+IF(C64=0,"THEN NULL ELSE X.CHAVE_IT END","THEN X.CHAVE_IT ELSE NULL END") -> THEN X.CHAVE_IT ELSE NULL END | K64: ="UNION ALL SELECT '"&E64&"' AS REF_DATE, '"&A64&"' AS COD_KPI, '"&F64&"' AS TIPOLOGIA_TESTE, '"&D64&"' AS DESCRIÇÃO, '"&G64&"' AS TABELA, '"&B64&"' AS CAMPO, COUNT(*) AS NUM_REG, SUM(IF("&H64&","&C64&" ,"&I64&")) AS NUM_REG_DIF, GROUP_CONCAT(CASE WHEN "&H64&" "&J64&", '; ') AS DETALHE FROM (SELECT *, 0020_UNIQ_ID AS CHAVE_IT, "&B64&" AS CAMPO_IT FROM "&G64&" WHERE REF_DATE='"&E64&"')X GROUP BY 1" -> UNION ALL SELECT '"& RefDate &"' AS REF_DATE, 'v_2_0026' AS COD_KPI, 'REGULAMENTAR' AS TIPOLOGIA_TESTE, 'Os valores dos dropdowns devem ser respeitados.' AS DESCRIÇÃO, 'BU_LOANTAPE_WORK.OUT_B0200_MAIN_LIABILITIES' AS TABELA, '0310_flg_clltrl_agrmnts' AS CAMPO, COUNT(*) AS NUM_REG, SUM(IF(`0310_flg_clltrl_agrmnts` NOT IN ('Secured', 'Unsecured'),1 ,0)) AS NUM_REG_DIF, GROUP_CONCAT(CASE WHEN `0310_flg_clltrl_agrmnts` NOT IN ('Secured', 'Unsecured') THEN X.CHAVE_IT ELSE NULL END, '; ') AS DETALHE FROM (SELECT *, 0020_UNIQ_ID AS CHAVE_IT, 0310_flg_clltrl_agrmnts AS CAMPO_IT FROM BU_LOANTAPE_WORK.OUT_B0200_MAIN_LIABILITIES WHERE REF_DATE='"& RefDate &"')X GROUP BY 1
A65: v_2_0027 | B65: 0330_amnt_unclltrlzd | C65: 1 | D65: =+VLOOKUP(A65,Descrição!A:K,11,FALSE) -> O campo reportado deve ser igual a: c0120 - c0320. | E65: "& RefDate &" | F65: REGULAMENTAR | G65: BU_LOANTAPE_WORK.OUT_B0200_MAIN_LIABILITIES | H65: `0330_amnt_unclltrlzd` != GREATEST(0, `0120_otstndng_amnt`-`0320_amnt_clltrl`) AND `0310_flg_clltrl_agrmnts` = 'Secured' AND `0250_strctrd_prdct` IN ('Non-structured/Vanilla', 'Other non-standard terms') AND `0240_zero_coupon` != 'ZCB issued at discount' | I65: =+IF(C65=1,0,1) -> 0 | J65: =+IF(C65=0,"THEN NULL ELSE X.CHAVE_IT END","THEN X.CHAVE_IT ELSE NULL END") -> THEN X.CHAVE_IT ELSE NULL END | K65: ="UNION ALL SELECT '"&E65&"' AS REF_DATE, '"&A65&"' AS COD_KPI, '"&F65&"' AS TIPOLOGIA_TESTE, '"&D65&"' AS DESCRIÇÃO, '"&G65&"' AS TABELA, '"&B65&"' AS CAMPO, COUNT(*) AS NUM_REG, SUM(IF("&H65&","&C65&" ,"&I65&")) AS NUM_REG_DIF, GROUP_CONCAT(CASE WHEN "&H65&" "&J65&", '; ') AS DETALHE FROM (SELECT *, 0020_UNIQ_ID AS CHAVE_IT, "&B65&" AS CAMPO_IT FROM "&G65&" WHERE REF_DATE='"&E65&"')X GROUP BY 1" -> UNION ALL SELECT '"& RefDate &"' AS REF_DATE, 'v_2_0027' AS COD_KPI, 'REGULAMENTAR' AS TIPOLOGIA_TESTE, 'O campo reportado deve ser igual a: c0120 - c0320.' AS DESCRIÇÃO, 'BU_LOANTAPE_WORK.OUT_B0200_MAIN_LIABILITIES' AS TABELA, '0330_amnt_unclltrlzd' AS CAMPO, COUNT(*) AS NUM_REG, SUM(IF(`0330_amnt_unclltrlzd` != GREATEST(0, `0120_otstndng_amnt`-`0320_amnt_clltrl`) AND `0310_flg_clltrl_agrmnts` = 'Secured' AND `0250_strctrd_prdct` IN ('Non-structured/Vanilla', 'Other non-standard terms') AND `0240_zero_coupon` != 'ZCB issued at discount' ,1 ,0)) AS NUM_REG_DIF, GROUP_CONCAT(CASE WHEN `0330_amnt_unclltrlzd` != GREATEST(0, `0120_otstndng_amnt`-`0320_amnt_clltrl`) AND `0310_flg_clltrl_agrmnts` = 'Secured' AND `0250_strctrd_prdct` IN ('Non-structured/Vanilla', 'Other non-standard terms') AND `0240_zero_coupon` != 'ZCB issued at discount' THEN X.CHAVE_IT ELSE NULL END, '; ') AS DETALHE FROM (SELECT *, 0020_UNIQ_ID AS CHAVE_IT, 0330_amnt_unclltrlzd AS CAMPO_IT FROM BU_LOANTAPE_WORK.OUT_B0200_MAIN_LIABILITIES WHERE REF_DATE='"& RefDate &"')X GROUP BY 1
A66: v_2_0028 | B66: 0330_amnt_unclltrlzd | C66: 1 | D66: =+VLOOKUP(A66,Descrição!A:K,11,FALSE) -> O campo reportado deve ser igual a (c0270 - c0320) se for utilizado o valor justo, ou igual a (c0120 - c0320) caso contrário. | E66: "& RefDate &" | F66: REGULAMENTAR | G66: BU_LOANTAPE_WORK.OUT_B0200_MAIN_LIABILITIES | H66: (`0330_amnt_unclltrlzd` != GREATEST(0, `0270_fv_amnt_strctrd_prdct`-`0320_amnt_clltrl`) AND `0330_amnt_unclltrlzd` != GREATEST(0, `0120_otstndng_amnt`-`0320_amnt_clltrl`)) AND `0310_flg_clltrl_agrmnts` = 'Secured' AND `0250_strctrd_prdct` IN ('Structured', 'Only structured coupon') AND `0240_zero_coupon` != 'ZCB issued at discount' | I66: =+IF(C66=1,0,1) -> 0 | J66: =+IF(C66=0,"THEN NULL ELSE X.CHAVE_IT END","THEN X.CHAVE_IT ELSE NULL END") -> THEN X.CHAVE_IT ELSE NULL END | K66: ="UNION ALL SELECT '"&E66&"' AS REF_DATE, '"&A66&"' AS COD_KPI, '"&F66&"' AS TIPOLOGIA_TESTE, '"&D66&"' AS DESCRIÇÃO, '"&G66&"' AS TABELA, '"&B66&"' AS CAMPO, COUNT(*) AS NUM_REG, SUM(IF("&H66&","&C66&" ,"&I66&")) AS NUM_REG_DIF, GROUP_CONCAT(CASE WHEN "&H66&" "&J66&", '; ') AS DETALHE FROM (SELECT *, 0020_UNIQ_ID AS CHAVE_IT, "&B66&" AS CAMPO_IT FROM "&G66&" WHERE REF_DATE='"&E66&"')X GROUP BY 1" -> UNION ALL SELECT '"& RefDate &"' AS REF_DATE, 'v_2_0028' AS COD_KPI, 'REGULAMENTAR' AS TIPOLOGIA_TESTE, 'O campo reportado deve ser igual a (c0270 - c0320) se for utilizado o valor justo, ou igual a (c0120 - c0320) caso contrário.' AS DESCRIÇÃO, 'BU_LOANTAPE_WORK.OUT_B0200_MAIN_LIABILITIES' AS TABELA, '0330_amnt_unclltrlzd' AS CAMPO, COUNT(*) AS NUM_REG, SUM(IF((`0330_amnt_unclltrlzd` != GREATEST(0, `0270_fv_amnt_strctrd_prdct`-`0320_amnt_clltrl`) AND `0330_amnt_unclltrlzd` != GREATEST(0, `0120_otstndng_amnt`-`0320_amnt_clltrl`)) AND `0310_flg_clltrl_agrmnts` = 'Secured' AND `0250_strctrd_prdct` IN ('Structured', 'Only structured coupon') AND `0240_zero_coupon` != 'ZCB issued at discount',1 ,0)) AS NUM_REG_DIF, GROUP_CONCAT(CASE WHEN (`0330_amnt_unclltrlzd` != GREATEST(0, `0270_fv_amnt_strctrd_prdct`-`0320_amnt_clltrl`) AND `0330_amnt_unclltrlzd` != GREATEST(0, `0120_otstndng_amnt`-`0320_amnt_clltrl`)) AND `0310_flg_clltrl_agrmnts` = 'Secured' AND `0250_strctrd_prdct` IN ('Structured', 'Only structured coupon') AND `0240_zero_coupon` != 'ZCB issued at discount' THEN X.CHAVE_IT ELSE NULL END, '; ') AS DETALHE FROM (SELECT *, 0020_UNIQ_ID AS CHAVE_IT, 0330_amnt_unclltrlzd AS CAMPO_IT FROM BU_LOANTAPE_WORK.OUT_B0200_MAIN_LIABILITIES WHERE REF_DATE='"& RefDate &"')X GROUP BY 1
A67: v_2_0029 | B67: 0350_typ_clltrl | C67: 1 | D67: =+VLOOKUP(A67,Descrição!A:K,11,FALSE) -> Os valores dos dropdowns devem ser respeitados. | E67: "& RefDate &" | F67: REGULAMENTAR | G67: BU_LOANTAPE_WORK.OUT_B0200_MAIN_LIABILITIES | H67: `0350_typ_clltrl` NOT IN ('Real estate', 'Ships', 'Aircraft', 'Financial', 'Other', 'Not applicable') | I67: =+IF(C67=1,0,1) -> 0 | J67: =+IF(C67=0,"THEN NULL ELSE X.CHAVE_IT END","THEN X.CHAVE_IT ELSE NULL END") -> THEN X.CHAVE_IT ELSE NULL END | K67: ="UNION ALL SELECT '"&E67&"' AS REF_DATE, '"&A67&"' AS COD_KPI, '"&F67&"' AS TIPOLOGIA_TESTE, '"&D67&"' AS DESCRIÇÃO, '"&G67&"' AS TABELA, '"&B67&"' AS CAMPO, COUNT(*) AS NUM_REG, SUM(IF("&H67&","&C67&" ,"&I67&")) AS NUM_REG_DIF, GROUP_CONCAT(CASE WHEN "&H67&" "&J67&", '; ') AS DETALHE FROM (SELECT *, 0020_UNIQ_ID AS CHAVE_IT, "&B67&" AS CAMPO_IT FROM "&G67&" WHERE REF_DATE='"&E67&"')X GROUP BY 1" -> UNION ALL SELECT '"& RefDate &"' AS REF_DATE, 'v_2_0029' AS COD_KPI, 'REGULAMENTAR' AS TIPOLOGIA_TESTE, 'Os valores dos dropdowns devem ser respeitados.' AS DESCRIÇÃO, 'BU_LOANTAPE_WORK.OUT_B0200_MAIN_LIABILITIES' AS TABELA, '0350_typ_clltrl' AS CAMPO, COUNT(*) AS NUM_REG, SUM(IF(`0350_typ_clltrl` NOT IN ('Real estate', 'Ships', 'Aircraft', 'Financial', 'Other', 'Not applicable'),1 ,0)) AS NUM_REG_DIF, GROUP_CONCAT(CASE WHEN `0350_typ_clltrl` NOT IN ('Real estate', 'Ships', 'Aircraft', 'Financial', 'Other', 'Not applicable') THEN X.CHAVE_IT ELSE NULL END, '; ') AS DETALHE FROM (SELECT *, 0020_UNIQ_ID AS CHAVE_IT, 0350_typ_clltrl AS CAMPO_IT FROM BU_LOANTAPE_WORK.OUT_B0200_MAIN_LIABILITIES WHERE REF_DATE='"& RefDate &"')X GROUP BY 1
A68: v_2_0030 | B68: 0350_typ_clltrl | C68: 1 | D68: =+VLOOKUP(A68,Descrição!A:K,11,FALSE) -> O campo deve ser Not applicable se o c0310 não estiver seguro. | E68: "& RefDate &" | F68: REGULAMENTAR | G68: BU_LOANTAPE_WORK.OUT_B0200_MAIN_LIABILITIES | H68: `0350_typ_clltrl` != 'Not applicable' AND `0310_flg_clltrl_agrmnts` = 'Unsecured' | I68: =+IF(C68=1,0,1) -> 0 | J68: =+IF(C68=0,"THEN NULL ELSE X.CHAVE_IT END","THEN X.CHAVE_IT ELSE NULL END") -> THEN X.CHAVE_IT ELSE NULL END | K68: ="UNION ALL SELECT '"&E68&"' AS REF_DATE, '"&A68&"' AS COD_KPI, '"&F68&"' AS TIPOLOGIA_TESTE, '"&D68&"' AS DESCRIÇÃO, '"&G68&"' AS TABELA, '"&B68&"' AS CAMPO, COUNT(*) AS NUM_REG, SUM(IF("&H68&","&C68&" ,"&I68&")) AS NUM_REG_DIF, GROUP_CONCAT(CASE WHEN "&H68&" "&J68&", '; ') AS DETALHE FROM (SELECT *, 0020_UNIQ_ID AS CHAVE_IT, "&B68&" AS CAMPO_IT FROM "&G68&" WHERE REF_DATE='"&E68&"')X GROUP BY 1" -> UNION ALL SELECT '"& RefDate &"' AS REF_DATE, 'v_2_0030' AS COD_KPI, 'REGULAMENTAR' AS TIPOLOGIA_TESTE, 'O campo deve ser Not applicable se o c0310 não estiver seguro.' AS DESCRIÇÃO, 'BU_LOANTAPE_WORK.OUT_B0200_MAIN_LIABILITIES' AS TABELA, '0350_typ_clltrl' AS CAMPO, COUNT(*) AS NUM_REG, SUM(IF(`0350_typ_clltrl` != 'Not applicable' AND `0310_flg_clltrl_agrmnts` = 'Unsecured',1 ,0)) AS NUM_REG_DIF, GROUP_CONCAT(CASE WHEN `0350_typ_clltrl` != 'Not applicable' AND `0310_flg_clltrl_agrmnts` = 'Unsecured' THEN X.CHAVE_IT ELSE NULL END, '; ') AS DETALHE FROM (SELECT *, 0020_UNIQ_ID AS CHAVE_IT, 0350_typ_clltrl AS CAMPO_IT FROM BU_LOANTAPE_WORK.OUT_B0200_MAIN_LIABILITIES WHERE REF_DATE='"& RefDate &"')X GROUP BY 1
A69: v_2_0031 | B69: 0440_ntr_glbl_nt | C69: 1 | D69: =+VLOOKUP(A69,Descrição!A:K,11,FALSE) -> Os valores dos dropdowns devem ser respeitados. | E69: "& RefDate &" | F69: REGULAMENTAR | G69: BU_LOANTAPE_WORK.OUT_B0200_MAIN_LIABILITIES | H69: `0440_ntr_glbl_nt` NOT IN ('NGN', 'CGN', 'Not applicable') | I69: =+IF(C69=1,0,1) -> 0 | J69: =+IF(C69=0,"THEN NULL ELSE X.CHAVE_IT END","THEN X.CHAVE_IT ELSE NULL END") -> THEN X.CHAVE_IT ELSE NULL END | K69: ="UNION ALL SELECT '"&E69&"' AS REF_DATE, '"&A69&"' AS COD_KPI, '"&F69&"' AS TIPOLOGIA_TESTE, '"&D69&"' AS DESCRIÇÃO, '"&G69&"' AS TABELA, '"&B69&"' AS CAMPO, COUNT(*) AS NUM_REG, SUM(IF("&H69&","&C69&" ,"&I69&")) AS NUM_REG_DIF, GROUP_CONCAT(CASE WHEN "&H69&" "&J69&", '; ') AS DETALHE FROM (SELECT *, 0020_UNIQ_ID AS CHAVE_IT, "&B69&" AS CAMPO_IT FROM "&G69&" WHERE REF_DATE='"&E69&"')X GROUP BY 1" -> UNION ALL SELECT '"& RefDate &"' AS REF_DATE, 'v_2_0031' AS COD_KPI, 'REGULAMENTAR' AS TIPOLOGIA_TESTE, 'Os valores dos dropdowns devem ser respeitados.' AS DESCRIÇÃO, 'BU_LOANTAPE_WORK.OUT_B0200_MAIN_LIABILITIES' AS TABELA, '0440_ntr_glbl_nt' AS CAMPO, COUNT(*) AS NUM_REG, SUM(IF(`0440_ntr_glbl_nt` NOT IN ('NGN', 'CGN', 'Not applicable'),1 ,0)) AS NUM_REG_DIF, GROUP_CONCAT(CASE WHEN `0440_ntr_glbl_nt` NOT IN ('NGN', 'CGN', 'Not applicable') THEN X.CHAVE_IT ELSE NULL END, '; ') AS DETALHE FROM (SELECT *, 0020_UNIQ_ID AS CHAVE_IT, 0440_ntr_glbl_nt AS CAMPO_IT FROM BU_LOANTAPE_WORK.OUT_B0200_MAIN_LIABILITIES WHERE REF_DATE='"& RefDate &"')X GROUP BY 1
A70: v_2_0032 | B70: 0530_typ_own_fnds_ind_lvl | C70: 1 | D70: =+VLOOKUP(A70,Descrição!A:K,11,FALSE) -> Os valores dos dropdowns devem ser respeitados. | E70: "& RefDate &" | F70: REGULAMENTAR | G70: BU_LOANTAPE_WORK.OUT_B0200_MAIN_LIABILITIES | H70: `0530_typ_own_fnds_ind_lvl` NOT IN ('T2 in phase-out', 'Grandfathered T2', 'Fully Compliant T2', 'Partially (A)T1 and T2', 'Grandfathered AT1', 'Fully Compliant AT1', 'CET1', 'No') | I70: =+IF(C70=1,0,1) -> 0 | J70: =+IF(C70=0,"THEN NULL ELSE X.CHAVE_IT END","THEN X.CHAVE_IT ELSE NULL END") -> THEN X.CHAVE_IT ELSE NULL END | K70: ="UNION ALL SELECT '"&E70&"' AS REF_DATE, '"&A70&"' AS COD_KPI, '"&F70&"' AS TIPOLOGIA_TESTE, '"&D70&"' AS DESCRIÇÃO, '"&G70&"' AS TABELA, '"&B70&"' AS CAMPO, COUNT(*) AS NUM_REG, SUM(IF("&H70&","&C70&" ,"&I70&")) AS NUM_REG_DIF, GROUP_CONCAT(CASE WHEN "&H70&" "&J70&", '; ') AS DETALHE FROM (SELECT *, 0020_UNIQ_ID AS CHAVE_IT, "&B70&" AS CAMPO_IT FROM "&G70&" WHERE REF_DATE='"&E70&"')X GROUP BY 1" -> UNION ALL SELECT '"& RefDate &"' AS REF_DATE, 'v_2_0032' AS COD_KPI, 'REGULAMENTAR' AS TIPOLOGIA_TESTE, 'Os valores dos dropdowns devem ser respeitados.' AS DESCRIÇÃO, 'BU_LOANTAPE_WORK.OUT_B0200_MAIN_LIABILITIES' AS TABELA, '0530_typ_own_fnds_ind_lvl' AS CAMPO, COUNT(*) AS NUM_REG, SUM(IF(`0530_typ_own_fnds_ind_lvl` NOT IN ('T2 in phase-out', 'Grandfathered T2', 'Fully Compliant T2', 'Partially (A)T1 and T2', 'Grandfathered AT1', 'Fully Compliant AT1', 'CET1', 'No'),1 ,0)) AS NUM_REG_DIF, GROUP_CONCAT(CASE WHEN `0530_typ_own_fnds_ind_lvl` NOT IN ('T2 in phase-out', 'Grandfathered T2', 'Fully Compliant T2', 'Partially (A)T1 and T2', 'Grandfathered AT1', 'Fully Compliant AT1', 'CET1', 'No') THEN X.CHAVE_IT ELSE NULL END, '; ') AS DETALHE FROM (SELECT *, 0020_UNIQ_ID AS CHAVE_IT, 0530_typ_own_fnds_ind_lvl AS CAMPO_IT FROM BU_LOANTAPE_WORK.OUT_B0200_MAIN_LIABILITIES WHERE REF_DATE='"& RefDate &"')X GROUP BY 1
A71: v_2_0033 | B71: 0540_elgbl_amnt_own_fnds_ind_lvl | C71: 1 | D71: =+VLOOKUP(A71,Descrição!A:K,11,FALSE) -> O valor declarado deve ser positivo ou zero. | E71: "& RefDate &" | F71: REGULAMENTAR | G71: BU_LOANTAPE_WORK.OUT_B0200_MAIN_LIABILITIES | H71: `0540_elgbl_amnt_own_fnds_ind_lvl` < 0 | I71: =+IF(C71=1,0,1) -> 0 | J71: =+IF(C71=0,"THEN NULL ELSE X.CHAVE_IT END","THEN X.CHAVE_IT ELSE NULL END") -> THEN X.CHAVE_IT ELSE NULL END | K71: ="UNION ALL SELECT '"&E71&"' AS REF_DATE, '"&A71&"' AS COD_KPI, '"&F71&"' AS TIPOLOGIA_TESTE, '"&D71&"' AS DESCRIÇÃO, '"&G71&"' AS TABELA, '"&B71&"' AS CAMPO, COUNT(*) AS NUM_REG, SUM(IF("&H71&","&C71&" ,"&I71&")) AS NUM_REG_DIF, GROUP_CONCAT(CASE WHEN "&H71&" "&J71&", '; ') AS DETALHE FROM (SELECT *, 0020_UNIQ_ID AS CHAVE_IT, "&B71&" AS CAMPO_IT FROM "&G71&" WHERE REF_DATE='"&E71&"')X GROUP BY 1" -> UNION ALL SELECT '"& RefDate &"' AS REF_DATE, 'v_2_0033' AS COD_KPI, 'REGULAMENTAR' AS TIPOLOGIA_TESTE, 'O valor declarado deve ser positivo ou zero.' AS DESCRIÇÃO, 'BU_LOANTAPE_WORK.OUT_B0200_MAIN_LIABILITIES' AS TABELA, '0540_elgbl_amnt_own_fnds_ind_lvl' AS CAMPO, COUNT(*) AS NUM_REG, SUM(IF(`0540_elgbl_amnt_own_fnds_ind_lvl` < 0,1 ,0)) AS NUM_REG_DIF, GROUP_CONCAT(CASE WHEN `0540_elgbl_amnt_own_fnds_ind_lvl` < 0 THEN X.CHAVE_IT ELSE NULL END, '; ') AS DETALHE FROM (SELECT *, 0020_UNIQ_ID AS CHAVE_IT, 0540_elgbl_amnt_own_fnds_ind_lvl AS CAMPO_IT FROM BU_LOANTAPE_WORK.OUT_B0200_MAIN_LIABILITIES WHERE REF_DATE='"& RefDate &"')X GROUP BY 1
A72: v_2_0034 | B72: 0550_typ_own_fnds_cnsldtd_lvl | C72: 1 | D72: =+VLOOKUP(A72,Descrição!A:K,11,FALSE) -> Os valores dos dropdowns devem ser respeitados. | E72: "& RefDate &" | F72: REGULAMENTAR | G72: BU_LOANTAPE_WORK.OUT_B0200_MAIN_LIABILITIES | H72: `0550_typ_own_fnds_cnsldtd_lvl` NOT IN ('T2 in phase-out', 'Grandfathered T2', 'Fully Compliant T2', 'Partially (A)T1 and T2', 'Grandfathered AT1', 'Fully Compliant AT1', 'CET1', 'No') | I72: =+IF(C72=1,0,1) -> 0 | J72: =+IF(C72=0,"THEN NULL ELSE X.CHAVE_IT END","THEN X.CHAVE_IT ELSE NULL END") -> THEN X.CHAVE_IT ELSE NULL END | K72: ="UNION ALL SELECT '"&E72&"' AS REF_DATE, '"&A72&"' AS COD_KPI, '"&F72&"' AS TIPOLOGIA_TESTE, '"&D72&"' AS DESCRIÇÃO, '"&G72&"' AS TABELA, '"&B72&"' AS CAMPO, COUNT(*) AS NUM_REG, SUM(IF("&H72&","&C72&" ,"&I72&")) AS NUM_REG_DIF, GROUP_CONCAT(CASE WHEN "&H72&" "&J72&", '; ') AS DETALHE FROM (SELECT *, 0020_UNIQ_ID AS CHAVE_IT, "&B72&" AS CAMPO_IT FROM "&G72&" WHERE REF_DATE='"&E72&"')X GROUP BY 1" -> UNION ALL SELECT '"& RefDate &"' AS REF_DATE, 'v_2_0034' AS COD_KPI, 'REGULAMENTAR' AS TIPOLOGIA_TESTE, 'Os valores dos dropdowns devem ser respeitados.' AS DESCRIÇÃO, 'BU_LOANTAPE_WORK.OUT_B0200_MAIN_LIABILITIES' AS TABELA, '0550_typ_own_fnds_cnsldtd_lvl' AS CAMPO, COUNT(*) AS NUM_REG, SUM(IF(`0550_typ_own_fnds_cnsldtd_lvl` NOT IN ('T2 in phase-out', 'Grandfathered T2', 'Fully Compliant T2', 'Partially (A)T1 and T2', 'Grandfathered AT1', 'Fully Compliant AT1', 'CET1', 'No'),1 ,0)) AS NUM_REG_DIF, GROUP_CONCAT(CASE WHEN `0550_typ_own_fnds_cnsldtd_lvl` NOT IN ('T2 in phase-out', 'Grandfathered T2', 'Fully Compliant T2', 'Partially (A)T1 and T2', 'Grandfathered AT1', 'Fully Compliant AT1', 'CET1', 'No') THEN X.CHAVE_IT ELSE NULL END, '; ') AS DETALHE FROM (SELECT *, 0020_UNIQ_ID AS CHAVE_IT, 0550_typ_own_fnds_cnsldtd_lvl AS CAMPO_IT FROM BU_LOANTAPE_WORK.OUT_B0200_MAIN_LIABILITIES WHERE REF_DATE='"& RefDate &"')X GROUP BY 1
A73: v_2_0035 | B73: 0560_elgbl_amnt_own_fnds_cnsldtd_lvl | C73: 1 | D73: =+VLOOKUP(A73,Descrição!A:K,11,FALSE) -> O valor declarado deve ser positivo ou zero. | E73: "& RefDate &" | F73: REGULAMENTAR | G73: BU_LOANTAPE_WORK.OUT_B0200_MAIN_LIABILITIES | H73: `0560_elgbl_amnt_own_fnds_cnsldtd_lvl` < 0 | I73: =+IF(C73=1,0,1) -> 0 | J73: =+IF(C73=0,"THEN NULL ELSE X.CHAVE_IT END","THEN X.CHAVE_IT ELSE NULL END") -> THEN X.CHAVE_IT ELSE NULL END | K73: ="UNION ALL SELECT '"&E73&"' AS REF_DATE, '"&A73&"' AS COD_KPI, '"&F73&"' AS TIPOLOGIA_TESTE, '"&D73&"' AS DESCRIÇÃO, '"&G73&"' AS TABELA, '"&B73&"' AS CAMPO, COUNT(*) AS NUM_REG, SUM(IF("&H73&","&C73&" ,"&I73&")) AS NUM_REG_DIF, GROUP_CONCAT(CASE WHEN "&H73&" "&J73&", '; ') AS DETALHE FROM (SELECT *, 0020_UNIQ_ID AS CHAVE_IT, "&B73&" AS CAMPO_IT FROM "&G73&" WHERE REF_DATE='"&E73&"')X GROUP BY 1" -> UNION ALL SELECT '"& RefDate &"' AS REF_DATE, 'v_2_0035' AS COD_KPI, 'REGULAMENTAR' AS TIPOLOGIA_TESTE, 'O valor declarado deve ser positivo ou zero.' AS DESCRIÇÃO, 'BU_LOANTAPE_WORK.OUT_B0200_MAIN_LIABILITIES' AS TABELA, '0560_elgbl_amnt_own_fnds_cnsldtd_lvl' AS CAMPO, COUNT(*) AS NUM_REG, SUM(IF(`0560_elgbl_amnt_own_fnds_cnsldtd_lvl` < 0,1 ,0)) AS NUM_REG_DIF, GROUP_CONCAT(CASE WHEN `0560_elgbl_amnt_own_fnds_cnsldtd_lvl` < 0 THEN X.CHAVE_IT ELSE NULL END, '; ') AS DETALHE FROM (SELECT *, 0020_UNIQ_ID AS CHAVE_IT, 0560_elgbl_amnt_own_fnds_cnsldtd_lvl AS CAMPO_IT FROM BU_LOANTAPE_WORK.OUT_B0200_MAIN_LIABILITIES WHERE REF_DATE='"& RefDate &"')X GROUP BY 1
A74: v_2_0036 | B74: 0590_typ_scrty_intrst_prvdd | C74: 1 | D74: =+VLOOKUP(A74,Descrição!A:K,11,FALSE) -> Os valores dos dropdowns devem ser respeitados. | E74: "& RefDate &" | F74: REGULAMENTAR | G74: BU_LOANTAPE_WORK.OUT_B0200_MAIN_LIABILITIES | H74: `0590_typ_scrty_intrst_prvdd` NOT IN ('T2 in phase-out', 'Grandfathered T2', 'Fully Compliant T2', 'Partially (A)T1 and T2', 'Grandfathered AT1', 'Fully Compliant AT1', 'CET1', 'No', 'Not applicable') | I74: =+IF(C74=1,0,1) -> 0 | J74: =+IF(C74=0,"THEN NULL ELSE X.CHAVE_IT END","THEN X.CHAVE_IT ELSE NULL END") -> THEN X.CHAVE_IT ELSE NULL END | K74: ="UNION ALL SELECT '"&E74&"' AS REF_DATE, '"&A74&"' AS COD_KPI, '"&F74&"' AS TIPOLOGIA_TESTE, '"&D74&"' AS DESCRIÇÃO, '"&G74&"' AS TABELA, '"&B74&"' AS CAMPO, COUNT(*) AS NUM_REG, SUM(IF("&H74&","&C74&" ,"&I74&")) AS NUM_REG_DIF, GROUP_CONCAT(CASE WHEN "&H74&" "&J74&", '; ') AS DETALHE FROM (SELECT *, 0020_UNIQ_ID AS CHAVE_IT, "&B74&" AS CAMPO_IT FROM "&G74&" WHERE REF_DATE='"&E74&"')X GROUP BY 1" -> UNION ALL SELECT '"& RefDate &"' AS REF_DATE, 'v_2_0036' AS COD_KPI, 'REGULAMENTAR' AS TIPOLOGIA_TESTE, 'Os valores dos dropdowns devem ser respeitados.' AS DESCRIÇÃO, 'BU_LOANTAPE_WORK.OUT_B0200_MAIN_LIABILITIES' AS TABELA, '0590_typ_scrty_intrst_prvdd' AS CAMPO, COUNT(*) AS NUM_REG, SUM(IF(`0590_typ_scrty_intrst_prvdd` NOT IN ('T2 in phase-out', 'Grandfathered T2', 'Fully Compliant T2', 'Partially (A)T1 and T2', 'Grandfathered AT1', 'Fully Compliant AT1', 'CET1', 'No', 'Not applicable'),1 ,0)) AS NUM_REG_DIF, GROUP_CONCAT(CASE WHEN `0590_typ_scrty_intrst_prvdd` NOT IN ('T2 in phase-out', 'Grandfathered T2', 'Fully Compliant T2', 'Partially (A)T1 and T2', 'Grandfathered AT1', 'Fully Compliant AT1', 'CET1', 'No', 'Not applicable') THEN X.CHAVE_IT ELSE NULL END, '; ') AS DETALHE FROM (SELECT *, 0020_UNIQ_ID AS CHAVE_IT, 0590_typ_scrty_intrst_prvdd AS CAMPO_IT FROM BU_LOANTAPE_WORK.OUT_B0200_MAIN_LIABILITIES WHERE REF_DATE='"& RefDate &"')X GROUP BY 1 | L74: x
A75: v_2_0037 | B75: 0610_crryng_amnt_ifrs | C75: 1 | D75: =+VLOOKUP(A75,Descrição!A:K,11,FALSE) -> O valor declarado deve ser positivo ou zero. | E75: "& RefDate &" | F75: REGULAMENTAR | G75: BU_LOANTAPE_WORK.OUT_B0200_MAIN_LIABILITIES | H75: `0610_crryng_amnt_ifrs` < 0 | I75: =+IF(C75=1,0,1) -> 0 | J75: =+IF(C75=0,"THEN NULL ELSE X.CHAVE_IT END","THEN X.CHAVE_IT ELSE NULL END") -> THEN X.CHAVE_IT ELSE NULL END | K75: ="UNION ALL SELECT '"&E75&"' AS REF_DATE, '"&A75&"' AS COD_KPI, '"&F75&"' AS TIPOLOGIA_TESTE, '"&D75&"' AS DESCRIÇÃO, '"&G75&"' AS TABELA, '"&B75&"' AS CAMPO, COUNT(*) AS NUM_REG, SUM(IF("&H75&","&C75&" ,"&I75&")) AS NUM_REG_DIF, GROUP_CONCAT(CASE WHEN "&H75&" "&J75&", '; ') AS DETALHE FROM (SELECT *, 0020_UNIQ_ID AS CHAVE_IT, "&B75&" AS CAMPO_IT FROM "&G75&" WHERE REF_DATE='"&E75&"')X GROUP BY 1" -> UNION ALL SELECT '"& RefDate &"' AS REF_DATE, 'v_2_0037' AS COD_KPI, 'REGULAMENTAR' AS TIPOLOGIA_TESTE, 'O valor declarado deve ser positivo ou zero.' AS DESCRIÇÃO, 'BU_LOANTAPE_WORK.OUT_B0200_MAIN_LIABILITIES' AS TABELA, '0610_crryng_amnt_ifrs' AS CAMPO, COUNT(*) AS NUM_REG, SUM(IF(`0610_crryng_amnt_ifrs` < 0,1 ,0)) AS NUM_REG_DIF, GROUP_CONCAT(CASE WHEN `0610_crryng_amnt_ifrs` < 0 THEN X.CHAVE_IT ELSE NULL END, '; ') AS DETALHE FROM (SELECT *, 0020_UNIQ_ID AS CHAVE_IT, 0610_crryng_amnt_ifrs AS CAMPO_IT FROM BU_LOANTAPE_WORK.OUT_B0200_MAIN_LIABILITIES WHERE REF_DATE='"& RefDate &"')X GROUP BY 1 | L75: x
A76: v_2_0038 | B76: 0620_blnc_sht_ifrs | C76: 1 | D76: =+VLOOKUP(A76,Descrição!A:K,11,FALSE) -> Os valores dos dropdowns devem ser respeitados. | E76: "& RefDate &" | F76: REGULAMENTAR | G76: BU_LOANTAPE_WORK.OUT_B0200_MAIN_LIABILITIES | H76: `0620_blnc_sht_ifrs` NOT IN ('010 Financial liabilities held for trading', '070 Financial liabilities at fair value through profit or loss', '110 Financial liabilities at amortized cost', '280 Other liabilities', '300 Total equity') | I76: =+IF(C76=1,0,1) -> 0 | J76: =+IF(C76=0,"THEN NULL ELSE X.CHAVE_IT END","THEN X.CHAVE_IT ELSE NULL END") -> THEN X.CHAVE_IT ELSE NULL END | K76: ="UNION ALL SELECT '"&E76&"' AS REF_DATE, '"&A76&"' AS COD_KPI, '"&F76&"' AS TIPOLOGIA_TESTE, '"&D76&"' AS DESCRIÇÃO, '"&G76&"' AS TABELA, '"&B76&"' AS CAMPO, COUNT(*) AS NUM_REG, SUM(IF("&H76&","&C76&" ,"&I76&")) AS NUM_REG_DIF, GROUP_CONCAT(CASE WHEN "&H76&" "&J76&", '; ') AS DETALHE FROM (SELECT *, 0020_UNIQ_ID AS CHAVE_IT, "&B76&" AS CAMPO_IT FROM "&G76&" WHERE REF_DATE='"&E76&"')X GROUP BY 1" -> UNION ALL SELECT '"& RefDate &"' AS REF_DATE, 'v_2_0038' AS COD_KPI, 'REGULAMENTAR' AS TIPOLOGIA_TESTE, 'Os valores dos dropdowns devem ser respeitados.' AS DESCRIÇÃO, 'BU_LOANTAPE_WORK.OUT_B0200_MAIN_LIABILITIES' AS TABELA, '0620_blnc_sht_ifrs' AS CAMPO, COUNT(*) AS NUM_REG, SUM(IF(`0620_blnc_sht_ifrs` NOT IN ('010 Financial liabilities held for trading', '070 Financial liabilities at fair value through profit or loss', '110 Financial liabilities at amortized cost', '280 Other liabilities', '300 Total equity'),1 ,0)) AS NUM_REG_DIF, GROUP_CONCAT(CASE WHEN `0620_blnc_sht_ifrs` NOT IN ('010 Financial liabilities held for trading', '070 Financial liabilities at fair value through profit or loss', '110 Financial liabilities at amortized cost', '280 Other liabilities', '300 Total equity') THEN X.CHAVE_IT ELSE NULL END, '; ') AS DETALHE FROM (SELECT *, 0020_UNIQ_ID AS CHAVE_IT, 0620_blnc_sht_ifrs AS CAMPO_IT FROM BU_LOANTAPE_WORK.OUT_B0200_MAIN_LIABILITIES WHERE REF_DATE='"& RefDate &"')X GROUP BY 1
A77: ="FRMT_"&MID(G77,22,5)&"_C"&LEFT(B77,4) -> FRMT_B0200_C0010 | B77: 0010_row_nmbr | C77: 0 | D77: O campo deve ser reportado com formato numérico inteiro. | E77: "& RefDate &" | F77: REGULAMENTAR | G77: BU_LOANTAPE_WORK.OUT_B0200_MAIN_LIABILITIES | H77: cast(`0010_row_nmbr` as string) RLIKE '^[0-9]+$' AND CAST(`0010_row_nmbr` AS STRING) NOT IN ('N/A','11111111111','11111111111.00','11111111111.000000','1111-11-11','0000-00-00','0001-01-01','9999-12-31','MISS','00000','99999999999.00','99999999999.000000','-9999.9999','','Not applicable','XXX') | I77: =+IF(C77=1,0,1) -> 1 | J77: =+IF(C77=0,"THEN NULL ELSE X.CHAVE_IT END","THEN X.CHAVE_IT ELSE NULL END") -> THEN NULL ELSE X.CHAVE_IT END | K77: ="UNION ALL SELECT '"&E77&"' AS REF_DATE, '"&A77&"' AS COD_KPI, '"&F77&"' AS TIPOLOGIA_TESTE, '"&D77&"' AS DESCRIÇÃO, '"&G77&"' AS TABELA, '"&B77&"' AS CAMPO, COUNT(*) AS NUM_REG, SUM(IF("&H77&","&C77&" ,"&I77&")) AS NUM_REG_DIF, GROUP_CONCAT(CASE WHEN "&H77&" "&J77&", '; ') AS DETALHE FROM (SELECT *, 0020_UNIQ_ID AS CHAVE_IT, "&B77&" AS CAMPO_IT FROM "&G77&" WHERE REF_DATE='"&E77&"')X GROUP BY 1" -> UNION ALL SELECT '"& RefDate &"' AS REF_DATE, 'FRMT_B0200_C0010' AS COD_KPI, 'REGULAMENTAR' AS TIPOLOGIA_TESTE, 'O campo deve ser reportado com formato numérico inteiro.' AS DESCRIÇÃO, 'BU_LOANTAPE_WORK.OUT_B0200_MAIN_LIABILITIES' AS TABELA, '0010_row_nmbr' AS CAMPO, COUNT(*) AS NUM_REG, SUM(IF(cast(`0010_row_nmbr` as string) RLIKE '^[0-9]+$' AND CAST(`0010_row_nmbr` AS STRING) NOT IN ('N/A','11111111111','11111111111.00','11111111111.000000','1111-11-11','0000-00-00','0001-01-01','9999-12-31','MISS','00000','99999999999.00','99999999999.000000','-9999.9999','','Not applicable','XXX'),0 ,1)) AS NUM_REG_DIF, GROUP_CONCAT(CASE WHEN cast(`0010_row_nmbr` as string) RLIKE '^[0-9]+$' AND CAST(`0010_row_nmbr` AS STRING) NOT IN ('N/A','11111111111','11111111111.00','11111111111.000000','1111-11-11','0000-00-00','0001-01-01','9999-12-31','MISS','00000','99999999999.00','99999999999.000000','-9999.9999','','Not applicable','XXX') THEN NULL ELSE X.CHAVE_IT END, '; ') AS DETALHE FROM (SELECT *, 0020_UNIQ_ID AS CHAVE_IT, 0010_row_nmbr AS CAMPO_IT FROM BU_LOANTAPE_WORK.OUT_B0200_MAIN_LIABILITIES WHERE REF_DATE='"& RefDate &"')X GROUP BY 1
A78: ="FRMT_"&MID(G78,22,5)&"_C"&LEFT(B78,4) -> FRMT_B0200_C0020 | B78: 0020_uniq_id | C78: 0 | D78: O campo deve ser reportado com formato texto livre. | E78: "& RefDate &" | F78: REGULAMENTAR | G78: BU_LOANTAPE_WORK.OUT_B0200_MAIN_LIABILITIES | H78: `0020_uniq_id` RLIKE '[A-Za-z]' and `0020_uniq_id` NOT IN ('N/A','11111111111','11111111111.00','11111111111.000000','1111-11-11','0000-00-00','0001-01-01','9999-12-31','MISS','00000','99999999999','999999999999999','99999999999.00','99999999999.000000','-9999.9999','','Not applicable','XXX') | I78: =+IF(C78=1,0,1) -> 1 | J78: =+IF(C78=0,"THEN NULL ELSE X.CHAVE_IT END","THEN X.CHAVE_IT ELSE NULL END") -> THEN NULL ELSE X.CHAVE_IT END | K78: ="UNION ALL SELECT '"&E78&"' AS REF_DATE, '"&A78&"' AS COD_KPI, '"&F78&"' AS TIPOLOGIA_TESTE, '"&D78&"' AS DESCRIÇÃO, '"&G78&"' AS TABELA, '"&B78&"' AS CAMPO, COUNT(*) AS NUM_REG, SUM(IF("&H78&","&C78&" ,"&I78&")) AS NUM_REG_DIF, GROUP_CONCAT(CASE WHEN "&H78&" "&J78&", '; ') AS DETALHE FROM (SELECT *, 0020_UNIQ_ID AS CHAVE_IT, "&B78&" AS CAMPO_IT FROM "&G78&" WHERE REF_DATE='"&E78&"')X GROUP BY 1" -> UNION ALL SELECT '"& RefDate &"' AS REF_DATE, 'FRMT_B0200_C0020' AS COD_KPI, 'REGULAMENTAR' AS TIPOLOGIA_TESTE, 'O campo deve ser reportado com formato texto livre.' AS DESCRIÇÃO, 'BU_LOANTAPE_WORK.OUT_B0200_MAIN_LIABILITIES' AS TABELA, '0020_uniq_id' AS CAMPO, COUNT(*) AS NUM_REG, SUM(IF(`0020_uniq_id` RLIKE '[A-Za-z]' and `0020_uniq_id` NOT IN ('N/A','11111111111','11111111111.00','11111111111.000000','1111-11-11','0000-00-00','0001-01-01','9999-12-31','MISS','00000','99999999999','999999999999999','99999999999.00','99999999999.000000','-9999.9999','','Not applicable','XXX'),0 ,1)) AS NUM_REG_DIF, GROUP_CONCAT(CASE WHEN `0020_uniq_id` RLIKE '[A-Za-z]' and `0020_uniq_id` NOT IN ('N/A','11111111111','11111111111.00','11111111111.000000','1111-11-11','0000-00-00','0001-01-01','9999-12-31','MISS','00000','99999999999','999999999999999','99999999999.00','99999999999.000000','-9999.9999','','Not applicable','XXX') THEN NULL ELSE X.CHAVE_IT END, '; ') AS DETALHE FROM (SELECT *, 0020_UNIQ_ID AS CHAVE_IT, 0020_uniq_id AS CAMPO_IT FROM BU_LOANTAPE_WORK.OUT_B0200_MAIN_LIABILITIES WHERE REF_DATE='"& RefDate &"')X GROUP BY 1
A79: ="FRMT_"&MID(G79,22,5)&"_C"&LEFT(B79,4) -> FRMT_B0200_C0030 | B79: 0030_uniq_id_knwn_cntrprty | C79: 0 | D79: O campo deve ser reportado com formato texto livre. | E79: "& RefDate &" | F79: REGULAMENTAR | G79: BU_LOANTAPE_WORK.OUT_B0200_MAIN_LIABILITIES | H79: `0030_uniq_id_knwn_cntrprty` RLIKE '[A-Za-z]' and `0030_uniq_id_knwn_cntrprty` NOT IN ('N/A','11111111111','11111111111.00','11111111111.000000','1111-11-11','0000-00-00','0001-01-01','9999-12-31','MISS','00000','99999999999','999999999999999','99999999999.00','99999999999.000000','-9999.9999','','Not applicable','XXX') | I79: =+IF(C79=1,0,1) -> 1 | J79: =+IF(C79=0,"THEN NULL ELSE X.CHAVE_IT END","THEN X.CHAVE_IT ELSE NULL END") -> THEN NULL ELSE X.CHAVE_IT END | K79: ="UNION ALL SELECT '"&E79&"' AS REF_DATE, '"&A79&"' AS COD_KPI, '"&F79&"' AS TIPOLOGIA_TESTE, '"&D79&"' AS DESCRIÇÃO, '"&G79&"' AS TABELA, '"&B79&"' AS CAMPO, COUNT(*) AS NUM_REG, SUM(IF("&H79&","&C79&" ,"&I79&")) AS NUM_REG_DIF, GROUP_CONCAT(CASE WHEN "&H79&" "&J79&", '; ') AS DETALHE FROM (SELECT *, 0020_UNIQ_ID AS CHAVE_IT, "&B79&" AS CAMPO_IT FROM "&G79&" WHERE REF_DATE='"&E79&"')X GROUP BY 1" -> UNION ALL SELECT '"& RefDate &"' AS REF_DATE, 'FRMT_B0200_C0030' AS COD_KPI, 'REGULAMENTAR' AS TIPOLOGIA_TESTE, 'O campo deve ser reportado com formato texto livre.' AS DESCRIÇÃO, 'BU_LOANTAPE_WORK.OUT_B0200_MAIN_LIABILITIES' AS TABELA, '0030_uniq_id_knwn_cntrprty' AS CAMPO, COUNT(*) AS NUM_REG, SUM(IF(`0030_uniq_id_knwn_cntrprty` RLIKE '[A-Za-z]' and `0030_uniq_id_knwn_cntrprty` NOT IN ('N/A','11111111111','11111111111.00','11111111111.000000','1111-11-11','0000-00-00','0001-01-01','9999-12-31','MISS','00000','99999999999','999999999999999','99999999999.00','99999999999.000000','-9999.9999','','Not applicable','XXX'),0 ,1)) AS NUM_REG_DIF, GROUP_CONCAT(CASE WHEN `0030_uniq_id_knwn_cntrprty` RLIKE '[A-Za-z]' and `0030_uniq_id_knwn_cntrprty` NOT IN ('N/A','11111111111','11111111111.00','11111111111.000000','1111-11-11','0000-00-00','0001-01-01','9999-12-31','MISS','00000','99999999999','999999999999999','99999999999.00','99999999999.000000','-9999.9999','','Not applicable','XXX') THEN NULL ELSE X.CHAVE_IT END, '; ') AS DETALHE FROM (SELECT *, 0020_UNIQ_ID AS CHAVE_IT, 0030_uniq_id_knwn_cntrprty AS CAMPO_IT FROM BU_LOANTAPE_WORK.OUT_B0200_MAIN_LIABILITIES WHERE REF_DATE='"& RefDate &"')X GROUP BY 1
A80: ="FRMT_"&MID(G80,22,5)&"_C"&LEFT(B80,4) -> FRMT_B0200_C0040 | B80: 0040_typ_uniq_id_knwn_cntrprty | C80: 0 | D80: O campo deve ser reportado com formato texto livre. | E80: "& RefDate &" | F80: REGULAMENTAR | G80: BU_LOANTAPE_WORK.OUT_B0200_MAIN_LIABILITIES | H80: `0040_typ_uniq_id_knwn_cntrprty` RLIKE '[A-Za-z]' AND `0040_typ_uniq_id_knwn_cntrprty` NOT IN ('N/A','11111111111','11111111111.00','11111111111.000000','1111-11-11','0000-00-00','0001-01-01','9999-12-31','MISS','00000','99999999999','999999999999999','99999999999.00','99999999999.000000','-9999.9999','','Not applicable','XXX') | I80: =+IF(C80=1,0,1) -> 1 | J80: =+IF(C80=0,"THEN NULL ELSE X.CHAVE_IT END","THEN X.CHAVE_IT ELSE NULL END") -> THEN NULL ELSE X.CHAVE_IT END | K80: ="UNION ALL SELECT '"&E80&"' AS REF_DATE, '"&A80&"' AS COD_KPI, '"&F80&"' AS TIPOLOGIA_TESTE, '"&D80&"' AS DESCRIÇÃO, '"&G80&"' AS TABELA, '"&B80&"' AS CAMPO, COUNT(*) AS NUM_REG, SUM(IF("&H80&","&C80&" ,"&I80&")) AS NUM_REG_DIF, GROUP_CONCAT(CASE WHEN "&H80&" "&J80&", '; ') AS DETALHE FROM (SELECT *, 0020_UNIQ_ID AS CHAVE_IT, "&B80&" AS CAMPO_IT FROM "&G80&" WHERE REF_DATE='"&E80&"')X GROUP BY 1" -> UNION ALL SELECT '"& RefDate &"' AS REF_DATE, 'FRMT_B0200_C0040' AS COD_KPI, 'REGULAMENTAR' AS TIPOLOGIA_TESTE, 'O campo deve ser reportado com formato texto livre.' AS DESCRIÇÃO, 'BU_LOANTAPE_WORK.OUT_B0200_MAIN_LIABILITIES' AS TABELA, '0040_typ_uniq_id_knwn_cntrprty' AS CAMPO, COUNT(*) AS NUM_REG, SUM(IF(`0040_typ_uniq_id_knwn_cntrprty` RLIKE '[A-Za-z]' AND `0040_typ_uniq_id_knwn_cntrprty` NOT IN ('N/A','11111111111','11111111111.00','11111111111.000000','1111-11-11','0000-00-00','0001-01-01','9999-12-31','MISS','00000','99999999999','999999999999999','99999999999.00','99999999999.000000','-9999.9999','','Not applicable','XXX'),0 ,1)) AS NUM_REG_DIF, GROUP_CONCAT(CASE WHEN `0040_typ_uniq_id_knwn_cntrprty` RLIKE '[A-Za-z]' AND `0040_typ_uniq_id_knwn_cntrprty` NOT IN ('N/A','11111111111','11111111111.00','11111111111.000000','1111-11-11','0000-00-00','0001-01-01','9999-12-31','MISS','00000','99999999999','999999999999999','99999999999.00','99999999999.000000','-9999.9999','','Not applicable','XXX') THEN NULL ELSE X.CHAVE_IT END, '; ') AS DETALHE FROM (SELECT *, 0020_UNIQ_ID AS CHAVE_IT, 0040_typ_uniq_id_knwn_cntrprty AS CAMPO_IT FROM BU_LOANTAPE_WORK.OUT_B0200_MAIN_LIABILITIES WHERE REF_DATE='"& RefDate &"')X GROUP BY 1
A81: ="FRMT_"&MID(G81,22,5)&"_C"&LEFT(B81,4) -> FRMT_B0200_C0050 | B81: 0050_orgnl_amnt_eur | C81: 0 | D81: O campo deve ser reportado com formato numérico com 2 casas decimais. | E81: "& RefDate &" | F81: REGULAMENTAR | G81: BU_LOANTAPE_WORK.OUT_B0200_MAIN_LIABILITIES | H81: (CAST(ROUND(`0050_orgnl_amnt_eur`, 2) AS STRING) = CAST(`0050_orgnl_amnt_eur` AS STRING) AND CAST(`0050_orgnl_amnt_eur` AS STRING) NOT IN ('N/A','11111111111','11111111111.00','11111111111.000000','1111-11-11','0000-00-00','0001-01-01','9999-12-31','MISS','00000','99999999999','99999999999.00','99999999999.000000','-9999.9999','','Not applicable','XXX')) OR `0050_orgnl_amnt_eur`= 999999999999999.00 | I81: =+IF(C81=1,0,1) -> 1 | J81: =+IF(C81=0,"THEN NULL ELSE X.CHAVE_IT END","THEN X.CHAVE_IT ELSE NULL END") -> THEN NULL ELSE X.CHAVE_IT END | K81: ="UNION ALL SELECT '"&E81&"' AS REF_DATE, '"&A81&"' AS COD_KPI, '"&F81&"' AS TIPOLOGIA_TESTE, '"&D81&"' AS DESCRIÇÃO, '"&G81&"' AS TABELA, '"&B81&"' AS CAMPO, COUNT(*) AS NUM_REG, SUM(IF("&H81&","&C81&" ,"&I81&")) AS NUM_REG_DIF, GROUP_CONCAT(CASE WHEN "&H81&" "&J81&", '; ') AS DETALHE FROM (SELECT *, 0020_UNIQ_ID AS CHAVE_IT, "&B81&" AS CAMPO_IT FROM "&G81&" WHERE REF_DATE='"&E81&"')X GROUP BY 1" -> UNION ALL SELECT '"& RefDate &"' AS REF_DATE, 'FRMT_B0200_C0050' AS COD_KPI, 'REGULAMENTAR' AS TIPOLOGIA_TESTE, 'O campo deve ser reportado com formato numérico com 2 casas decimais.' AS DESCRIÇÃO, 'BU_LOANTAPE_WORK.OUT_B0200_MAIN_LIABILITIES' AS TABELA, '0050_orgnl_amnt_eur' AS CAMPO, COUNT(*) AS NUM_REG, SUM(IF((CAST(ROUND(`0050_orgnl_amnt_eur`, 2) AS STRING) = CAST(`0050_orgnl_amnt_eur` AS STRING) AND CAST(`0050_orgnl_amnt_eur` AS STRING) NOT IN ('N/A','11111111111','11111111111.00','11111111111.000000','1111-11-11','0000-00-00','0001-01-01','9999-12-31','MISS','00000','99999999999','99999999999.00','99999999999.000000','-9999.9999','','Not applicable','XXX')) OR `0050_orgnl_amnt_eur`= 999999999999999.00 ,0 ,1)) AS NUM_REG_DIF, GROUP_CONCAT(CASE WHEN (CAST(ROUND(`0050_orgnl_amnt_eur`, 2) AS STRING) = CAST(`0050_orgnl_amnt_eur` AS STRING) AND CAST(`0050_orgnl_amnt_eur` AS STRING) NOT IN ('N/A','11111111111','11111111111.00','11111111111.000000','1111-11-11','0000-00-00','0001-01-01','9999-12-31','MISS','00000','99999999999','99999999999.00','99999999999.000000','-9999.9999','','Not applicable','XXX')) OR `0050_orgnl_amnt_eur`= 999999999999999.00 THEN NULL ELSE X.CHAVE_IT END, '; ') AS DETALHE FROM (SELECT *, 0020_UNIQ_ID AS CHAVE_IT, 0050_orgnl_amnt_eur AS CAMPO_IT FROM BU_LOANTAPE_WORK.OUT_B0200_MAIN_LIABILITIES WHERE REF_DATE='"& RefDate &"')X GROUP BY 1
A82: ="FRMT_"&MID(G82,22,5)&"_C"&LEFT(B82,4) -> FRMT_B0200_C0060 | B82: 0060_orgnl_amnt_fx | C82: 0 | D82: O campo deve ser reportado com formato numérico com 2 casas decimais. | E82: "& RefDate &" | F82: REGULAMENTAR | G82: BU_LOANTAPE_WORK.OUT_B0200_MAIN_LIABILITIES | H82: (CAST(ROUND(`0060_orgnl_amnt_fx`, 2) AS STRING) = CAST(`0060_orgnl_amnt_fx` AS STRING) AND CAST(`0060_orgnl_amnt_fx` AS STRING) NOT IN ('N/A','11111111111','11111111111.00','11111111111.000000','1111-11-11','0000-00-00','0001-01-01','9999-12-31','MISS','00000','99999999999','99999999999.00','99999999999.000000','-9999.9999','','Not applicable','XXX')) OR `0060_orgnl_amnt_fx`= 999999999999999.00 | I82: =+IF(C82=1,0,1) -> 1 | J82: =+IF(C82=0,"THEN NULL ELSE X.CHAVE_IT END","THEN X.CHAVE_IT ELSE NULL END") -> THEN NULL ELSE X.CHAVE_IT END | K82: ="UNION ALL SELECT '"&E82&"' AS REF_DATE, '"&A82&"' AS COD_KPI, '"&F82&"' AS TIPOLOGIA_TESTE, '"&D82&"' AS DESCRIÇÃO, '"&G82&"' AS TABELA, '"&B82&"' AS CAMPO, COUNT(*) AS NUM_REG, SUM(IF("&H82&","&C82&" ,"&I82&")) AS NUM_REG_DIF, GROUP_CONCAT(CASE WHEN "&H82&" "&J82&", '; ') AS DETALHE FROM (SELECT *, 0020_UNIQ_ID AS CHAVE_IT, "&B82&" AS CAMPO_IT FROM "&G82&" WHERE REF_DATE='"&E82&"')X GROUP BY 1" -> UNION ALL SELECT '"& RefDate &"' AS REF_DATE, 'FRMT_B0200_C0060' AS COD_KPI, 'REGULAMENTAR' AS TIPOLOGIA_TESTE, 'O campo deve ser reportado com formato numérico com 2 casas decimais.' AS DESCRIÇÃO, 'BU_LOANTAPE_WORK.OUT_B0200_MAIN_LIABILITIES' AS TABELA, '0060_orgnl_amnt_fx' AS CAMPO, COUNT(*) AS NUM_REG, SUM(IF((CAST(ROUND(`0060_orgnl_amnt_fx`, 2) AS STRING) = CAST(`0060_orgnl_amnt_fx` AS STRING) AND CAST(`0060_orgnl_amnt_fx` AS STRING) NOT IN ('N/A','11111111111','11111111111.00','11111111111.000000','1111-11-11','0000-00-00','0001-01-01','9999-12-31','MISS','00000','99999999999','99999999999.00','99999999999.000000','-9999.9999','','Not applicable','XXX')) OR `0060_orgnl_amnt_fx`= 999999999999999.00 ,0 ,1)) AS NUM_REG_DIF, GROUP_CONCAT(CASE WHEN (CAST(ROUND(`0060_orgnl_amnt_fx`, 2) AS STRING) = CAST(`0060_orgnl_amnt_fx` AS STRING) AND CAST(`0060_orgnl_amnt_fx` AS STRING) NOT IN ('N/A','11111111111','11111111111.00','11111111111.000000','1111-11-11','0000-00-00','0001-01-01','9999-12-31','MISS','00000','99999999999','99999999999.00','99999999999.000000','-9999.9999','','Not applicable','XXX')) OR `0060_orgnl_amnt_fx`= 999999999999999.00 THEN NULL ELSE X.CHAVE_IT END, '; ') AS DETALHE FROM (SELECT *, 0020_UNIQ_ID AS CHAVE_IT, 0060_orgnl_amnt_fx AS CAMPO_IT FROM BU_LOANTAPE_WORK.OUT_B0200_MAIN_LIABILITIES WHERE REF_DATE='"& RefDate &"')X GROUP BY 1
A83: ="FRMT_"&MID(G83,22,5)&"_C"&LEFT(B83,4) -> FRMT_B0200_C0070 | B83: 0070_cntrct_crrncy | C83: 0 | D83: O campo deve ser reportado usando o código 3-letra ISO 4217. | E83: "& RefDate &" | F83: REGULAMENTAR | G83: BU_LOANTAPE_WORK.OUT_B0200_MAIN_LIABILITIES | H83: (LENGTH(`0070_cntrct_crrncy`) = 3 AND `0070_cntrct_crrncy` NOT IN ('N/A','11111111111','11111111111.00','11111111111.000000','1111-11-11','0000-00-00','0001-01-01','9999-12-31','MISS','00000','99999999999','99999999999.00','99999999999.000000','-9999.9999','','Not applicable')) OR `0070_cntrct_crrncy`='XXX' | I83: =+IF(C83=1,0,1) -> 1 | J83: =+IF(C83=0,"THEN NULL ELSE X.CHAVE_IT END","THEN X.CHAVE_IT ELSE NULL END") -> THEN NULL ELSE X.CHAVE_IT END | K83: ="UNION ALL SELECT '"&E83&"' AS REF_DATE, '"&A83&"' AS COD_KPI, '"&F83&"' AS TIPOLOGIA_TESTE, '"&D83&"' AS DESCRIÇÃO, '"&G83&"' AS TABELA, '"&B83&"' AS CAMPO, COUNT(*) AS NUM_REG, SUM(IF("&H83&","&C83&" ,"&I83&")) AS NUM_REG_DIF, GROUP_CONCAT(CASE WHEN "&H83&" "&J83&", '; ') AS DETALHE FROM (SELECT *, 0020_UNIQ_ID AS CHAVE_IT, "&B83&" AS CAMPO_IT FROM "&G83&" WHERE REF_DATE='"&E83&"')X GROUP BY 1" -> UNION ALL SELECT '"& RefDate &"' AS REF_DATE, 'FRMT_B0200_C0070' AS COD_KPI, 'REGULAMENTAR' AS TIPOLOGIA_TESTE, 'O campo deve ser reportado usando o código 3-letra ISO 4217.' AS DESCRIÇÃO, 'BU_LOANTAPE_WORK.OUT_B0200_MAIN_LIABILITIES' AS TABELA, '0070_cntrct_crrncy' AS CAMPO, COUNT(*) AS NUM_REG, SUM(IF((LENGTH(`0070_cntrct_crrncy`) = 3 AND `0070_cntrct_crrncy` NOT IN ('N/A','11111111111','11111111111.00','11111111111.000000','1111-11-11','0000-00-00','0001-01-01','9999-12-31','MISS','00000','99999999999','99999999999.00','99999999999.000000','-9999.9999','','Not applicable')) OR `0070_cntrct_crrncy`='XXX',0 ,1)) AS NUM_REG_DIF, GROUP_CONCAT(CASE WHEN (LENGTH(`0070_cntrct_crrncy`) = 3 AND `0070_cntrct_crrncy` NOT IN ('N/A','11111111111','11111111111.00','11111111111.000000','1111-11-11','0000-00-00','0001-01-01','9999-12-31','MISS','00000','99999999999','99999999999.00','99999999999.000000','-9999.9999','','Not applicable')) OR `0070_cntrct_crrncy`='XXX' THEN NULL ELSE X.CHAVE_IT END, '; ') AS DETALHE FROM (SELECT *, 0020_UNIQ_ID AS CHAVE_IT, 0070_cntrct_crrncy AS CAMPO_IT FROM BU_LOANTAPE_WORK.OUT_B0200_MAIN_LIABILITIES WHERE REF_DATE='"& RefDate &"')X GROUP BY 1
A84: ="FRMT_"&MID(G84,22,5)&"_C"&LEFT(B84,4) -> FRMT_B0200_C0080 | B84: 0080_otstndng_prncpl_amnt | C84: 0 | D84: O campo deve ser reportado com formato numérico com 2 casas decimais. | E84: "& RefDate &" | F84: REGULAMENTAR | G84: BU_LOANTAPE_WORK.OUT_B0200_MAIN_LIABILITIES | H84: CAST(ROUND(`0080_otstndng_prncpl_amnt`, 2) AS STRING) = CAST(`0080_otstndng_prncpl_amnt` AS STRING) AND CAST(`0080_otstndng_prncpl_amnt` AS STRING) NOT IN ('N/A','11111111111','11111111111.00','11111111111.000000','1111-11-11','0000-00-00','0001-01-01','9999-12-31','MISS','00000','99999999999','99999999999.00','99999999999.000000','-9999.9999','','Not applicable','XXX') | I84: =+IF(C84=1,0,1) -> 1 | J84: =+IF(C84=0,"THEN NULL ELSE X.CHAVE_IT END","THEN X.CHAVE_IT ELSE NULL END") -> THEN NULL ELSE X.CHAVE_IT END | K84: ="UNION ALL SELECT '"&E84&"' AS REF_DATE, '"&A84&"' AS COD_KPI, '"&F84&"' AS TIPOLOGIA_TESTE, '"&D84&"' AS DESCRIÇÃO, '"&G84&"' AS TABELA, '"&B84&"' AS CAMPO, COUNT(*) AS NUM_REG, SUM(IF("&H84&","&C84&" ,"&I84&")) AS NUM_REG_DIF, GROUP_CONCAT(CASE WHEN "&H84&" "&J84&", '; ') AS DETALHE FROM (SELECT *, 0020_UNIQ_ID AS CHAVE_IT, "&B84&" AS CAMPO_IT FROM "&G84&" WHERE REF_DATE='"&E84&"')X GROUP BY 1" -> UNION ALL SELECT '"& RefDate &"' AS REF_DATE, 'FRMT_B0200_C0080' AS COD_KPI, 'REGULAMENTAR' AS TIPOLOGIA_TESTE, 'O campo deve ser reportado com formato numérico com 2 casas decimais.' AS DESCRIÇÃO, 'BU_LOANTAPE_WORK.OUT_B0200_MAIN_LIABILITIES' AS TABELA, '0080_otstndng_prncpl_amnt' AS CAMPO, COUNT(*) AS NUM_REG, SUM(IF(CAST(ROUND(`0080_otstndng_prncpl_amnt`, 2) AS STRING) = CAST(`0080_otstndng_prncpl_amnt` AS STRING) AND CAST(`0080_otstndng_prncpl_amnt` AS STRING) NOT IN ('N/A','11111111111','11111111111.00','11111111111.000000','1111-11-11','0000-00-00','0001-01-01','9999-12-31','MISS','00000','99999999999','99999999999.00','99999999999.000000','-9999.9999','','Not applicable','XXX'),0 ,1)) AS NUM_REG_DIF, GROUP_CONCAT(CASE WHEN CAST(ROUND(`0080_otstndng_prncpl_amnt`, 2) AS STRING) = CAST(`0080_otstndng_prncpl_amnt` AS STRING) AND CAST(`0080_otstndng_prncpl_amnt` AS STRING) NOT IN ('N/A','11111111111','11111111111.00','11111111111.000000','1111-11-11','0000-00-00','0001-01-01','9999-12-31','MISS','00000','99999999999','99999999999.00','99999999999.000000','-9999.9999','','Not applicable','XXX') THEN NULL ELSE X.CHAVE_IT END, '; ') AS DETALHE FROM (SELECT *, 0020_UNIQ_ID AS CHAVE_IT, 0080_otstndng_prncpl_amnt AS CAMPO_IT FROM BU_LOANTAPE_WORK.OUT_B0200_MAIN_LIABILITIES WHERE REF_DATE='"& RefDate &"')X GROUP BY 1
A85: ="FRMT_"&MID(G85,22,5)&"_C"&LEFT(B85,4) -> FRMT_B0200_C0090 | B85: 0090_prtn_amnt_rprtng_entty | C85: 0 | D85: O campo deve ser reportado com formato numérico com 2 casas decimais. | E85: "& RefDate &" | F85: REGULAMENTAR | G85: BU_LOANTAPE_WORK.OUT_B0200_MAIN_LIABILITIES | H85: (CAST(ROUND(`0090_prtn_amnt_rprtng_entty`, 2) AS STRING) = CAST(`0090_prtn_amnt_rprtng_entty` AS STRING) AND CAST(`0090_prtn_amnt_rprtng_entty` AS STRING) NOT IN ('N/A','11111111111','11111111111.00','11111111111.000000','1111-11-11','0000-00-00','0001-01-01','9999-12-31','MISS','00000','99999999999','99999999999.00','99999999999.000000','-9999.9999','','Not applicable','XXX')) OR `0090_prtn_amnt_rprtng_entty`= 999999999999999.00 | I85: =+IF(C85=1,0,1) -> 1 | J85: =+IF(C85=0,"THEN NULL ELSE X.CHAVE_IT END","THEN X.CHAVE_IT ELSE NULL END") -> THEN NULL ELSE X.CHAVE_IT END | K85: ="UNION ALL SELECT '"&E85&"' AS REF_DATE, '"&A85&"' AS COD_KPI, '"&F85&"' AS TIPOLOGIA_TESTE, '"&D85&"' AS DESCRIÇÃO, '"&G85&"' AS TABELA, '"&B85&"' AS CAMPO, COUNT(*) AS NUM_REG, SUM(IF("&H85&","&C85&" ,"&I85&")) AS NUM_REG_DIF, GROUP_CONCAT(CASE WHEN "&H85&" "&J85&", '; ') AS DETALHE FROM (SELECT *, 0020_UNIQ_ID AS CHAVE_IT, "&B85&" AS CAMPO_IT FROM "&G85&" WHERE REF_DATE='"&E85&"')X GROUP BY 1" -> UNION ALL SELECT '"& RefDate &"' AS REF_DATE, 'FRMT_B0200_C0090' AS COD_KPI, 'REGULAMENTAR' AS TIPOLOGIA_TESTE, 'O campo deve ser reportado com formato numérico com 2 casas decimais.' AS DESCRIÇÃO, 'BU_LOANTAPE_WORK.OUT_B0200_MAIN_LIABILITIES' AS TABELA, '0090_prtn_amnt_rprtng_entty' AS CAMPO, COUNT(*) AS NUM_REG, SUM(IF((CAST(ROUND(`0090_prtn_amnt_rprtng_entty`, 2) AS STRING) = CAST(`0090_prtn_amnt_rprtng_entty` AS STRING) AND CAST(`0090_prtn_amnt_rprtng_entty` AS STRING) NOT IN ('N/A','11111111111','11111111111.00','11111111111.000000','1111-11-11','0000-00-00','0001-01-01','9999-12-31','MISS','00000','99999999999','99999999999.00','99999999999.000000','-9999.9999','','Not applicable','XXX')) OR `0090_prtn_amnt_rprtng_entty`= 999999999999999.00 ,0 ,1)) AS NUM_REG_DIF, GROUP_CONCAT(CASE WHEN (CAST(ROUND(`0090_prtn_amnt_rprtng_entty`, 2) AS STRING) = CAST(`0090_prtn_amnt_rprtng_entty` AS STRING) AND CAST(`0090_prtn_amnt_rprtng_entty` AS STRING) NOT IN ('N/A','11111111111','11111111111.00','11111111111.000000','1111-11-11','0000-00-00','0001-01-01','9999-12-31','MISS','00000','99999999999','99999999999.00','99999999999.000000','-9999.9999','','Not applicable','XXX')) OR `0090_prtn_amnt_rprtng_entty`= 999999999999999.00 THEN NULL ELSE X.CHAVE_IT END, '; ') AS DETALHE FROM (SELECT *, 0020_UNIQ_ID AS CHAVE_IT, 0090_prtn_amnt_rprtng_entty AS CAMPO_IT FROM BU_LOANTAPE_WORK.OUT_B0200_MAIN_LIABILITIES WHERE REF_DATE='"& RefDate &"')X GROUP BY 1
A86: ="FRMT_"&MID(G86,22,5)&"_C"&LEFT(B86,4) -> FRMT_B0200_C0100 | B86: 0100_accrd_intrst_instrmnt | C86: 0 | D86: O campo deve ser reportado com formato numérico com 2 casas decimais. | E86: "& RefDate &" | F86: REGULAMENTAR | G86: BU_LOANTAPE_WORK.OUT_B0200_MAIN_LIABILITIES | H86: (CAST(ROUND(`0100_accrd_intrst_instrmnt`, 2) AS STRING) = CAST(`0100_accrd_intrst_instrmnt` AS STRING) AND CAST(`0100_accrd_intrst_instrmnt` AS STRING) NOT IN ('N/A','11111111111','11111111111.00','11111111111.000000','1111-11-11','0000-00-00','0001-01-01','9999-12-31','MISS','00000','99999999999','99999999999.00','99999999999.000000','-9999.9999','Not applicable','XXX')) OR `0100_accrd_intrst_instrmnt` = 999999999999999 OR CAST(`0100_accrd_intrst_instrmnt` AS STRING) = '' | I86: =+IF(C86=1,0,1) -> 1 | J86: =+IF(C86=0,"THEN NULL ELSE X.CHAVE_IT END","THEN X.CHAVE_IT ELSE NULL END") -> THEN NULL ELSE X.CHAVE_IT END | K86: ="UNION ALL SELECT '"&E86&"' AS REF_DATE, '"&A86&"' AS COD_KPI, '"&F86&"' AS TIPOLOGIA_TESTE, '"&D86&"' AS DESCRIÇÃO, '"&G86&"' AS TABELA, '"&B86&"' AS CAMPO, COUNT(*) AS NUM_REG, SUM(IF("&H86&","&C86&" ,"&I86&")) AS NUM_REG_DIF, GROUP_CONCAT(CASE WHEN "&H86&" "&J86&", '; ') AS DETALHE FROM (SELECT *, 0020_UNIQ_ID AS CHAVE_IT, "&B86&" AS CAMPO_IT FROM "&G86&" WHERE REF_DATE='"&E86&"')X GROUP BY 1" -> UNION ALL SELECT '"& RefDate &"' AS REF_DATE, 'FRMT_B0200_C0100' AS COD_KPI, 'REGULAMENTAR' AS TIPOLOGIA_TESTE, 'O campo deve ser reportado com formato numérico com 2 casas decimais.' AS DESCRIÇÃO, 'BU_LOANTAPE_WORK.OUT_B0200_MAIN_LIABILITIES' AS TABELA, '0100_accrd_intrst_instrmnt' AS CAMPO, COUNT(*) AS NUM_REG, SUM(IF((CAST(ROUND(`0100_accrd_intrst_instrmnt`, 2) AS STRING) = CAST(`0100_accrd_intrst_instrmnt` AS STRING) AND CAST(`0100_accrd_intrst_instrmnt` AS STRING) NOT IN ('N/A','11111111111','11111111111.00','11111111111.000000','1111-11-11','0000-00-00','0001-01-01','9999-12-31','MISS','00000','99999999999','99999999999.00','99999999999.000000','-9999.9999','Not applicable','XXX')) OR `0100_accrd_intrst_instrmnt` = 999999999999999 OR CAST(`0100_accrd_intrst_instrmnt` AS STRING) = '',0 ,1)) AS NUM_REG_DIF, GROUP_CONCAT(CASE WHEN (CAST(ROUND(`0100_accrd_intrst_instrmnt`, 2) AS STRING) = CAST(`0100_accrd_intrst_instrmnt` AS STRING) AND CAST(`0100_accrd_intrst_instrmnt` AS STRING) NOT IN ('N/A','11111111111','11111111111.00','11111111111.000000','1111-11-11','0000-00-00','0001-01-01','9999-12-31','MISS','00000','99999999999','99999999999.00','99999999999.000000','-9999.9999','Not applicable','XXX')) OR `0100_accrd_intrst_instrmnt` = 999999999999999 OR CAST(`0100_accrd_intrst_instrmnt` AS STRING) = '' THEN NULL ELSE X.CHAVE_IT END, '; ') AS DETALHE FROM (SELECT *, 0020_UNIQ_ID AS CHAVE_IT, 0100_accrd_intrst_instrmnt AS CAMPO_IT FROM BU_LOANTAPE_WORK.OUT_B0200_MAIN_LIABILITIES WHERE REF_DATE='"& RefDate &"')X GROUP BY 1
A87: ="FRMT_"&MID(G87,22,5)&"_C"&LEFT(B87,4) -> FRMT_B0200_C0110 | B87: 0110_applcbl_fees_charges | C87: 0 | D87: O campo deve ser reportado com formato numérico com 2 casas decimais. | E87: "& RefDate &" | F87: REGULAMENTAR | G87: BU_LOANTAPE_WORK.OUT_B0200_MAIN_LIABILITIES | H87: (CAST(ROUND(`0110_applcbl_fees_charges`, 2) AS STRING) = CAST(`0110_applcbl_fees_charges` AS STRING) AND CAST(`0110_applcbl_fees_charges` AS STRING) NOT IN ('N/A','11111111111','11111111111.00','11111111111.000000','1111-11-11','0000-00-00','0001-01-01','9999-12-31','MISS','00000','99999999999','99999999999.00','99999999999.000000','-9999.9999','Not applicable','XXX')) OR `0110_applcbl_fees_charges` = 999999999999999 OR CAST(`0110_applcbl_fees_charges` AS STRING) = '' | I87: =+IF(C87=1,0,1) -> 1 | J87: =+IF(C87=0,"THEN NULL ELSE X.CHAVE_IT END","THEN X.CHAVE_IT ELSE NULL END") -> THEN NULL ELSE X.CHAVE_IT END | K87: ="UNION ALL SELECT '"&E87&"' AS REF_DATE, '"&A87&"' AS COD_KPI, '"&F87&"' AS TIPOLOGIA_TESTE, '"&D87&"' AS DESCRIÇÃO, '"&G87&"' AS TABELA, '"&B87&"' AS CAMPO, COUNT(*) AS NUM_REG, SUM(IF("&H87&","&C87&" ,"&I87&")) AS NUM_REG_DIF, GROUP_CONCAT(CASE WHEN "&H87&" "&J87&", '; ') AS DETALHE FROM (SELECT *, 0020_UNIQ_ID AS CHAVE_IT, "&B87&" AS CAMPO_IT FROM "&G87&" WHERE REF_DATE='"&E87&"')X GROUP BY 1" -> UNION ALL SELECT '"& RefDate &"' AS REF_DATE, 'FRMT_B0200_C0110' AS COD_KPI, 'REGULAMENTAR' AS TIPOLOGIA_TESTE, 'O campo deve ser reportado com formato numérico com 2 casas decimais.' AS DESCRIÇÃO, 'BU_LOANTAPE_WORK.OUT_B0200_MAIN_LIABILITIES' AS TABELA, '0110_applcbl_fees_charges' AS CAMPO, COUNT(*) AS NUM_REG, SUM(IF((CAST(ROUND(`0110_applcbl_fees_charges`, 2) AS STRING) = CAST(`0110_applcbl_fees_charges` AS STRING) AND CAST(`0110_applcbl_fees_charges` AS STRING) NOT IN ('N/A','11111111111','11111111111.00','11111111111.000000','1111-11-11','0000-00-00','0001-01-01','9999-12-31','MISS','00000','99999999999','99999999999.00','99999999999.000000','-9999.9999','Not applicable','XXX')) OR `0110_applcbl_fees_charges` = 999999999999999 OR CAST(`0110_applcbl_fees_charges` AS STRING) = '',0 ,1)) AS NUM_REG_DIF, GROUP_CONCAT(CASE WHEN (CAST(ROUND(`0110_applcbl_fees_charges`, 2) AS STRING) = CAST(`0110_applcbl_fees_charges` AS STRING) AND CAST(`0110_applcbl_fees_charges` AS STRING) NOT IN ('N/A','11111111111','11111111111.00','11111111111.000000','1111-11-11','0000-00-00','0001-01-01','9999-12-31','MISS','00000','99999999999','99999999999.00','99999999999.000000','-9999.9999','Not applicable','XXX')) OR `0110_applcbl_fees_charges` = 999999999999999 OR CAST(`0110_applcbl_fees_charges` AS STRING) = '' THEN NULL ELSE X.CHAVE_IT END, '; ') AS DETALHE FROM (SELECT *, 0020_UNIQ_ID AS CHAVE_IT, 0110_applcbl_fees_charges AS CAMPO_IT FROM BU_LOANTAPE_WORK.OUT_B0200_MAIN_LIABILITIES WHERE REF_DATE='"& RefDate &"')X GROUP BY 1
A88: ="FRMT_"&MID(G88,22,5)&"_C"&LEFT(B88,4) -> FRMT_B0200_C0120 | B88: 0120_otstndng_amnt | C88: 0 | D88: O campo deve ser reportado com formato numérico com 2 casas decimais. | E88: "& RefDate &" | F88: REGULAMENTAR | G88: BU_LOANTAPE_WORK.OUT_B0200_MAIN_LIABILITIES | H88: (CAST(ROUND(`0120_otstndng_amnt`, 2) AS STRING) = CAST(`0120_otstndng_amnt` AS STRING) AND CAST(`0120_otstndng_amnt` AS STRING) NOT IN ('N/A','11111111111','11111111111.00','11111111111.000000','1111-11-11','0000-00-00','0001-01-01','9999-12-31','MISS','00000','99999999999','99999999999.00','99999999999.000000','-9999.9999','','Not applicable','XXX')) OR `0120_otstndng_amnt`= 999999999999999.00 | I88: =+IF(C88=1,0,1) -> 1 | J88: =+IF(C88=0,"THEN NULL ELSE X.CHAVE_IT END","THEN X.CHAVE_IT ELSE NULL END") -> THEN NULL ELSE X.CHAVE_IT END | K88: ="UNION ALL SELECT '"&E88&"' AS REF_DATE, '"&A88&"' AS COD_KPI, '"&F88&"' AS TIPOLOGIA_TESTE, '"&D88&"' AS DESCRIÇÃO, '"&G88&"' AS TABELA, '"&B88&"' AS CAMPO, COUNT(*) AS NUM_REG, SUM(IF("&H88&","&C88&" ,"&I88&")) AS NUM_REG_DIF, GROUP_CONCAT(CASE WHEN "&H88&" "&J88&", '; ') AS DETALHE FROM (SELECT *, 0020_UNIQ_ID AS CHAVE_IT, "&B88&" AS CAMPO_IT FROM "&G88&" WHERE REF_DATE='"&E88&"')X GROUP BY 1" -> UNION ALL SELECT '"& RefDate &"' AS REF_DATE, 'FRMT_B0200_C0120' AS COD_KPI, 'REGULAMENTAR' AS TIPOLOGIA_TESTE, 'O campo deve ser reportado com formato numérico com 2 casas decimais.' AS DESCRIÇÃO, 'BU_LOANTAPE_WORK.OUT_B0200_MAIN_LIABILITIES' AS TABELA, '0120_otstndng_amnt' AS CAMPO, COUNT(*) AS NUM_REG, SUM(IF((CAST(ROUND(`0120_otstndng_amnt`, 2) AS STRING) = CAST(`0120_otstndng_amnt` AS STRING) AND CAST(`0120_otstndng_amnt` AS STRING) NOT IN ('N/A','11111111111','11111111111.00','11111111111.000000','1111-11-11','0000-00-00','0001-01-01','9999-12-31','MISS','00000','99999999999','99999999999.00','99999999999.000000','-9999.9999','','Not applicable','XXX')) OR `0120_otstndng_amnt`= 999999999999999.00,0 ,1)) AS NUM_REG_DIF, GROUP_CONCAT(CASE WHEN (CAST(ROUND(`0120_otstndng_amnt`, 2) AS STRING) = CAST(`0120_otstndng_amnt` AS STRING) AND CAST(`0120_otstndng_amnt` AS STRING) NOT IN ('N/A','11111111111','11111111111.00','11111111111.000000','1111-11-11','0000-00-00','0001-01-01','9999-12-31','MISS','00000','99999999999','99999999999.00','99999999999.000000','-9999.9999','','Not applicable','XXX')) OR `0120_otstndng_amnt`= 999999999999999.00 THEN NULL ELSE X.CHAVE_IT END, '; ') AS DETALHE FROM (SELECT *, 0020_UNIQ_ID AS CHAVE_IT, 0120_otstndng_amnt AS CAMPO_IT FROM BU_LOANTAPE_WORK.OUT_B0200_MAIN_LIABILITIES WHERE REF_DATE='"& RefDate &"')X GROUP BY 1
... A90: ="FRMT_"&MID(G90,22,5)&"_C"&LEFT(B90,4) -> FRMT_B0200_C0140 | B90: 0140_ntr_lblty | C90: 0 | D90: Os valores dos dropdowns devem ser respeitados. | E90: "& RefDate &" | F90: REGULAMENTAR | G90: BU_LOANTAPE_WORK.OUT_B0200_MAIN_LIABILITIES | H90: `0140_ntr_lblty` IN ('Registered Bond', 'Bearer Bond', 'Borrower Note Loan', 'Certificate of Deposit / Commercial paper', 'Title of ownership', 'Cash account/saving account', 'Term deposit', 'Loan', 'Bill of exchange ', 'Other') | I90: =+IF(C90=1,0,1) -> 1 | J90: =+IF(C90=0,"THEN NULL ELSE X.CHAVE_IT END","THEN X.CHAVE_IT ELSE NULL END") -> THEN NULL ELSE X.CHAVE_IT END | K90: ="UNION ALL SELECT '"&E90&"' AS REF_DATE, '"&A90&"' AS COD_KPI, '"&F90&"' AS TIPOLOGIA_TESTE, '"&D90&"' AS DESCRIÇÃO, '"&G90&"' AS TABELA, '"&B90&"' AS CAMPO, COUNT(*) AS NUM_REG, SUM(IF("&H90&","&C90&" ,"&I90&")) AS NUM_REG_DIF, GROUP_CONCAT(CASE WHEN "&H90&" "&J90&", '; ') AS DETALHE FROM (SELECT *, 0020_UNIQ_ID AS CHAVE_IT, "&B90&" AS CAMPO_IT FROM "&G90&" WHERE REF_DATE='"&E90&"')X GROUP BY 1" -> UNION ALL SELECT '"& RefDate &"' AS REF_DATE, 'FRMT_B0200_C0140' AS COD_KPI, 'REGULAMENTAR' AS TIPOLOGIA_TESTE, 'Os valores dos dropdowns devem ser respeitados.' AS DESCRIÇÃO, 'BU_LOANTAPE_WORK.OUT_B0200_MAIN_LIABILITIES' AS TABELA, '0140_ntr_lblty' AS CAMPO, COUNT(*) AS NUM_REG, SUM(IF(`0140_ntr_lblty` IN ('Registered Bond', 'Bearer Bond', 'Borrower Note Loan', 'Certificate of Deposit / Commercial paper', 'Title of ownership', 'Cash account/saving account', 'Term deposit', 'Loan', 'Bill of exchange ', 'Other'),0 ,1)) AS NUM_REG_DIF, GROUP_CONCAT(CASE WHEN `0140_ntr_lblty` IN ('Registered Bond', 'Bearer Bond', 'Borrower Note Loan', 'Certificate of Deposit / Commercial paper', 'Title of ownership', 'Cash account/saving account', 'Term deposit', 'Loan', 'Bill of exchange ', 'Other') THEN NULL ELSE X.CHAVE_IT END, '; ') AS DETALHE FROM (SELECT *, 0020_UNIQ_ID AS CHAVE_IT, 0140_ntr_lblty AS CAMPO_IT FROM BU_LOANTAPE_WORK.OUT_B0200_MAIN_LIABILITIES WHERE REF_DATE='"& RefDate &"')X GROUP BY 1
A91: ="FRMT_"&MID(G91,22,5)&"_C"&LEFT(B91,4) -> FRMT_B0200_C0141 | B91: 0141_ntr_lblty_othr | C91: 0 | D91: O campo deve ser reportado com formato texto livre. | E91: "& RefDate &" | F91: REGULAMENTAR | G91: BU_LOANTAPE_WORK.OUT_B0200_MAIN_LIABILITIES | H91: `0141_ntr_lblty_othr` RLIKE '[A-Za-z]' AND `0141_ntr_lblty_othr` NOT IN ('N/A','11111111111','11111111111.00','11111111111.000000','1111-11-11','0000-00-00','0001-01-01','9999-12-31','MISS','00000','99999999999','999999999999999','99999999999.00','99999999999.000000','-9999.9999','','Not applicable','XXX') | I91: =+IF(C91=1,0,1) -> 1 | J91: =+IF(C91=0,"THEN NULL ELSE X.CHAVE_IT END","THEN X.CHAVE_IT ELSE NULL END") -> THEN NULL ELSE X.CHAVE_IT END | K91: ="UNION ALL SELECT '"&E91&"' AS REF_DATE, '"&A91&"' AS COD_KPI, '"&F91&"' AS TIPOLOGIA_TESTE, '"&D91&"' AS DESCRIÇÃO, '"&G91&"' AS TABELA, '"&B91&"' AS CAMPO, COUNT(*) AS NUM_REG, SUM(IF("&H91&","&C91&" ,"&I91&")) AS NUM_REG_DIF, GROUP_CONCAT(CASE WHEN "&H91&" "&J91&", '; ') AS DETALHE FROM (SELECT *, 0020_UNIQ_ID AS CHAVE_IT, "&B91&" AS CAMPO_IT FROM "&G91&" WHERE REF_DATE='"&E91&"')X GROUP BY 1" -> UNION ALL SELECT '"& RefDate &"' AS REF_DATE, 'FRMT_B0200_C0141' AS COD_KPI, 'REGULAMENTAR' AS TIPOLOGIA_TESTE, 'O campo deve ser reportado com formato texto livre.' AS DESCRIÇÃO, 'BU_LOANTAPE_WORK.OUT_B0200_MAIN_LIABILITIES' AS TABELA, '0141_ntr_lblty_othr' AS CAMPO, COUNT(*) AS NUM_REG, SUM(IF(`0141_ntr_lblty_othr` RLIKE '[A-Za-z]' AND `0141_ntr_lblty_othr` NOT IN ('N/A','11111111111','11111111111.00','11111111111.000000','1111-11-11','0000-00-00','0001-01-01','9999-12-31','MISS','00000','99999999999','999999999999999','99999999999.00','99999999999.000000','-9999.9999','','Not applicable','XXX'),0 ,1)) AS NUM_REG_DIF, GROUP_CONCAT(CASE WHEN `0141_ntr_lblty_othr` RLIKE '[A-Za-z]' AND `0141_ntr_lblty_othr` NOT IN ('N/A','11111111111','11111111111.00','11111111111.000000','1111-11-11','0000-00-00','0001-01-01','9999-12-31','MISS','00000','99999999999','999999999999999','99999999999.00','99999999999.000000','-9999.9999','','Not applicable','XXX') THEN NULL ELSE X.CHAVE_IT END, '; ') AS DETALHE FROM (SELECT *, 0020_UNIQ_ID AS CHAVE_IT, 0141_ntr_lblty_othr AS CAMPO_IT FROM BU_LOANTAPE_WORK.OUT_B0200_MAIN_LIABILITIES WHERE REF_DATE='"& RefDate &"')X GROUP BY 1 | L91: x
A92: ="FRMT_"&MID(G92,22,5)&"_C"&LEFT(B92,4) -> FRMT_B0200_C0150 | B92: 0150_flg_strctrlly_sbrdntd | C92: 0 | D92: O campo deve ser reportado usando TRUE ou FALSE. | E92: "& RefDate &" | F92: REGULAMENTAR | G92: BU_LOANTAPE_WORK.OUT_B0200_MAIN_LIABILITIES | H92: `0150_flg_strctrlly_sbrdntd` IN ('TRUE', 'FALSE') | I92: =+IF(C92=1,0,1) -> 1 | J92: =+IF(C92=0,"THEN NULL ELSE X.CHAVE_IT END","THEN X.CHAVE_IT ELSE NULL END") -> THEN NULL ELSE X.CHAVE_IT END | K92: ="UNION ALL SELECT '"&E92&"' AS REF_DATE, '"&A92&"' AS COD_KPI, '"&F92&"' AS TIPOLOGIA_TESTE, '"&D92&"' AS DESCRIÇÃO, '"&G92&"' AS TABELA, '"&B92&"' AS CAMPO, COUNT(*) AS NUM_REG, SUM(IF("&H92&","&C92&" ,"&I92&")) AS NUM_REG_DIF, GROUP_CONCAT(CASE WHEN "&H92&" "&J92&", '; ') AS DETALHE FROM (SELECT *, 0020_UNIQ_ID AS CHAVE_IT, "&B92&" AS CAMPO_IT FROM "&G92&" WHERE REF_DATE='"&E92&"')X GROUP BY 1" -> UNION ALL SELECT '"& RefDate &"' AS REF_DATE, 'FRMT_B0200_C0150' AS COD_KPI, 'REGULAMENTAR' AS TIPOLOGIA_TESTE, 'O campo deve ser reportado usando TRUE ou FALSE.' AS DESCRIÇÃO, 'BU_LOANTAPE_WORK.OUT_B0200_MAIN_LIABILITIES' AS TABELA, '0150_flg_strctrlly_sbrdntd' AS CAMPO, COUNT(*) AS NUM_REG, SUM(IF(`0150_flg_strctrlly_sbrdntd` IN ('TRUE', 'FALSE'),0 ,1)) AS NUM_REG_DIF, GROUP_CONCAT(CASE WHEN `0150_flg_strctrlly_sbrdntd` IN ('TRUE', 'FALSE') THEN NULL ELSE X.CHAVE_IT END, '; ') AS DETALHE FROM (SELECT *, 0020_UNIQ_ID AS CHAVE_IT, 0150_flg_strctrlly_sbrdntd AS CAMPO_IT FROM BU_LOANTAPE_WORK.OUT_B0200_MAIN_LIABILITIES WHERE REF_DATE='"& RefDate &"')X GROUP BY 1
A93: ="FRMT_"&MID(G93,22,5)&"_C"&LEFT(B93,4) -> FRMT_B0200_C0160 | B93: 0160_rank_insolv | C93: 0 | D93: O campo deve ser reportado com formato numérico inteiro. | E93: "& RefDate &" | F93: REGULAMENTAR | G93: BU_LOANTAPE_WORK.OUT_B0200_MAIN_LIABILITIES | H93: CAST(`0160_rank_insolv` AS STRING) RLIKE '^[0-9]+$' AND CAST(`0160_rank_insolv` AS STRING) NOT IN ('N/A','11111111111','11111111111.00','11111111111.000000','1111-11-11','0000-00-00','0001-01-01','9999-12-31','MISS','00000','99999999999','999999999999999','99999999999.00','99999999999.000000','-9999.9999','','Not applicable','XXX') | I93: =+IF(C93=1,0,1) -> 1 | J93: =+IF(C93=0,"THEN NULL ELSE X.CHAVE_IT END","THEN X.CHAVE_IT ELSE NULL END") -> THEN NULL ELSE X.CHAVE_IT END | K93: ="UNION ALL SELECT '"&E93&"' AS REF_DATE, '"&A93&"' AS COD_KPI, '"&F93&"' AS TIPOLOGIA_TESTE, '"&D93&"' AS DESCRIÇÃO, '"&G93&"' AS TABELA, '"&B93&"' AS CAMPO, COUNT(*) AS NUM_REG, SUM(IF("&H93&","&C93&" ,"&I93&")) AS NUM_REG_DIF, GROUP_CONCAT(CASE WHEN "&H93&" "&J93&", '; ') AS DETALHE FROM (SELECT *, 0020_UNIQ_ID AS CHAVE_IT, "&B93&" AS CAMPO_IT FROM "&G93&" WHERE REF_DATE='"&E93&"')X GROUP BY 1" -> UNION ALL SELECT '"& RefDate &"' AS REF_DATE, 'FRMT_B0200_C0160' AS COD_KPI, 'REGULAMENTAR' AS TIPOLOGIA_TESTE, 'O campo deve ser reportado com formato numérico inteiro.' AS DESCRIÇÃO, 'BU_LOANTAPE_WORK.OUT_B0200_MAIN_LIABILITIES' AS TABELA, '0160_rank_insolv' AS CAMPO, COUNT(*) AS NUM_REG, SUM(IF(CAST(`0160_rank_insolv` AS STRING) RLIKE '^[0-9]+$' AND CAST(`0160_rank_insolv` AS STRING) NOT IN ('N/A','11111111111','11111111111.00','11111111111.000000','1111-11-11','0000-00-00','0001-01-01','9999-12-31','MISS','00000','99999999999','999999999999999','99999999999.00','99999999999.000000','-9999.9999','','Not applicable','XXX'),0 ,1)) AS NUM_REG_DIF, GROUP_CONCAT(CASE WHEN CAST(`0160_rank_insolv` AS STRING) RLIKE '^[0-9]+$' AND CAST(`0160_rank_insolv` AS STRING) NOT IN ('N/A','11111111111','11111111111.00','11111111111.000000','1111-11-11','0000-00-00','0001-01-01','9999-12-31','MISS','00000','99999999999','999999999999999','99999999999.00','99999999999.000000','-9999.9999','','Not applicable','XXX') THEN NULL ELSE X.CHAVE_IT END, '; ') AS DETALHE FROM (SELECT *, 0020_UNIQ_ID AS CHAVE_IT, 0160_rank_insolv AS CAMPO_IT FROM BU_LOANTAPE_WORK.OUT_B0200_MAIN_LIABILITIES WHERE REF_DATE='"& RefDate &"')X GROUP BY 1 | L93: x
A94: ="FRMT_"&MID(G94,22,5)&"_C"&LEFT(B94,4) -> FRMT_B0200_C0161 | B94: 0161_cntrctl_sbrdntn | C94: 0 | D94: O campo deve ser reportado com formato numérico com 2 casas decimais. | E94: "& RefDate &" | F94: REGULAMENTAR | G94: BU_LOANTAPE_WORK.OUT_B0200_MAIN_LIABILITIES | H94: (CAST(ROUND(`0161_cntrctl_sbrdntn`, 2) AS STRING) = CAST(`0161_cntrctl_sbrdntn` AS STRING) AND CAST(`0161_cntrctl_sbrdntn` AS STRING) NOT IN ('N/A','11111111111','11111111111.00','11111111111.000000','1111-11-11','0000-00-00','0001-01-01','9999-12-31','MISS','00000','99999999999','99999999999.00','99999999999.000000','-9999.9999','','Not applicable','XXX')) OR `0161_cntrctl_sbrdntn`= 999999999999999.00 | I94: =+IF(C94=1,0,1) -> 1 | J94: =+IF(C94=0,"THEN NULL ELSE X.CHAVE_IT END","THEN X.CHAVE_IT ELSE NULL END") -> THEN NULL ELSE X.CHAVE_IT END | K94: ="UNION ALL SELECT '"&E94&"' AS REF_DATE, '"&A94&"' AS COD_KPI, '"&F94&"' AS TIPOLOGIA_TESTE, '"&D94&"' AS DESCRIÇÃO, '"&G94&"' AS TABELA, '"&B94&"' AS CAMPO, COUNT(*) AS NUM_REG, SUM(IF("&H94&","&C94&" ,"&I94&")) AS NUM_REG_DIF, GROUP_CONCAT(CASE WHEN "&H94&" "&J94&", '; ') AS DETALHE FROM (SELECT *, 0020_UNIQ_ID AS CHAVE_IT, "&B94&" AS CAMPO_IT FROM "&G94&" WHERE REF_DATE='"&E94&"')X GROUP BY 1" -> UNION ALL SELECT '"& RefDate &"' AS REF_DATE, 'FRMT_B0200_C0161' AS COD_KPI, 'REGULAMENTAR' AS TIPOLOGIA_TESTE, 'O campo deve ser reportado com formato numérico com 2 casas decimais.' AS DESCRIÇÃO, 'BU_LOANTAPE_WORK.OUT_B0200_MAIN_LIABILITIES' AS TABELA, '0161_cntrctl_sbrdntn' AS CAMPO, COUNT(*) AS NUM_REG, SUM(IF((CAST(ROUND(`0161_cntrctl_sbrdntn`, 2) AS STRING) = CAST(`0161_cntrctl_sbrdntn` AS STRING) AND CAST(`0161_cntrctl_sbrdntn` AS STRING) NOT IN ('N/A','11111111111','11111111111.00','11111111111.000000','1111-11-11','0000-00-00','0001-01-01','9999-12-31','MISS','00000','99999999999','99999999999.00','99999999999.000000','-9999.9999','','Not applicable','XXX')) OR `0161_cntrctl_sbrdntn`= 999999999999999.00,0 ,1)) AS NUM_REG_DIF, GROUP_CONCAT(CASE WHEN (CAST(ROUND(`0161_cntrctl_sbrdntn`, 2) AS STRING) = CAST(`0161_cntrctl_sbrdntn` AS STRING) AND CAST(`0161_cntrctl_sbrdntn` AS STRING) NOT IN ('N/A','11111111111','11111111111.00','11111111111.000000','1111-11-11','0000-00-00','0001-01-01','9999-12-31','MISS','00000','99999999999','99999999999.00','99999999999.000000','-9999.9999','','Not applicable','XXX')) OR `0161_cntrctl_sbrdntn`= 999999999999999.00 THEN NULL ELSE X.CHAVE_IT END, '; ') AS DETALHE FROM (SELECT *, 0020_UNIQ_ID AS CHAVE_IT, 0161_cntrctl_sbrdntn AS CAMPO_IT FROM BU_LOANTAPE_WORK.OUT_B0200_MAIN_LIABILITIES WHERE REF_DATE='"& RefDate &"')X GROUP BY 1
A95: ="FRMT_"&MID(G95,22,5)&"_C"&LEFT(B95,4) -> FRMT_B0200_C0162 | B95: 0162_bail_in_cascade | C95: 0 | D95: O campo deve ser reportado usando os valores fixos. | E95: "& RefDate &" | F95: REGULAMENTAR | G95: BU_LOANTAPE_WORK.OUT_B0200_MAIN_LIABILITIES | H95: `0162_bail_in_cascade` in ('1','2','3','4','5','6','7','8','9','10','11','12','13','14','14','15','16','17','18','19','20') | I95: =+IF(C95=1,0,1) -> 1 | J95: =+IF(C95=0,"THEN NULL ELSE X.CHAVE_IT END","THEN X.CHAVE_IT ELSE NULL END") -> THEN NULL ELSE X.CHAVE_IT END | K95: ="UNION ALL SELECT '"&E95&"' AS REF_DATE, '"&A95&"' AS COD_KPI, '"&F95&"' AS TIPOLOGIA_TESTE, '"&D95&"' AS DESCRIÇÃO, '"&G95&"' AS TABELA, '"&B95&"' AS CAMPO, COUNT(*) AS NUM_REG, SUM(IF("&H95&","&C95&" ,"&I95&")) AS NUM_REG_DIF, GROUP_CONCAT(CASE WHEN "&H95&" "&J95&", '; ') AS DETALHE FROM (SELECT *, 0020_UNIQ_ID AS CHAVE_IT, "&B95&" AS CAMPO_IT FROM "&G95&" WHERE REF_DATE='"&E95&"')X GROUP BY 1" -> UNION ALL SELECT '"& RefDate &"' AS REF_DATE, 'FRMT_B0200_C0162' AS COD_KPI, 'REGULAMENTAR' AS TIPOLOGIA_TESTE, 'O campo deve ser reportado usando os valores fixos.' AS DESCRIÇÃO, 'BU_LOANTAPE_WORK.OUT_B0200_MAIN_LIABILITIES' AS TABELA, '0162_bail_in_cascade' AS CAMPO, COUNT(*) AS NUM_REG, SUM(IF(`0162_bail_in_cascade` in ('1','2','3','4','5','6','7','8','9','10','11','12','13','14','14','15','16','17','18','19','20'),0 ,1)) AS NUM_REG_DIF, GROUP_CONCAT(CASE WHEN `0162_bail_in_cascade` in ('1','2','3','4','5','6','7','8','9','10','11','12','13','14','14','15','16','17','18','19','20') THEN NULL ELSE X.CHAVE_IT END, '; ') AS DETALHE FROM (SELECT *, 0020_UNIQ_ID AS CHAVE_IT, 0162_bail_in_cascade AS CAMPO_IT FROM BU_LOANTAPE_WORK.OUT_B0200_MAIN_LIABILITIES WHERE REF_DATE='"& RefDate &"')X GROUP BY 1 | L95: x
A96: ="FRMT_"&MID(G96,22,5)&"_C"&LEFT(B96,4) -> FRMT_B0200_C0170 | B96: 0170_dt_incptn | C96: 0 | D96: O campo deve ser reportado com formato yyyy-mm-dd. | E96: "& RefDate &" | F96: REGULAMENTAR | G96: BU_LOANTAPE_WORK.OUT_B0200_MAIN_LIABILITIES | H96: `0170_dt_incptn` REGEXP '^[0-9]{4}-[0-9]{2}-[0-9]{2}$' and `0170_dt_incptn` NOT IN ('N/A','11111111111','11111111111.00','11111111111.000000','1111-11-11','0000-00-00','0001-01-01','9999-12-31','MISS','00000','99999999999','999999999999999','99999999999.00','99999999999.000000','-9999.9999','','Not applicable','XXX') | I96: =+IF(C96=1,0,1) -> 1 | J96: =+IF(C96=0,"THEN NULL ELSE X.CHAVE_IT END","THEN X.CHAVE_IT ELSE NULL END") -> THEN NULL ELSE X.CHAVE_IT END | K96: ="UNION ALL SELECT '"&E96&"' AS REF_DATE, '"&A96&"' AS COD_KPI, '"&F96&"' AS TIPOLOGIA_TESTE, '"&D96&"' AS DESCRIÇÃO, '"&G96&"' AS TABELA, '"&B96&"' AS CAMPO, COUNT(*) AS NUM_REG, SUM(IF("&H96&","&C96&" ,"&I96&")) AS NUM_REG_DIF, GROUP_CONCAT(CASE WHEN "&H96&" "&J96&", '; ') AS DETALHE FROM (SELECT *, 0020_UNIQ_ID AS CHAVE_IT, "&B96&" AS CAMPO_IT FROM "&G96&" WHERE REF_DATE='"&E96&"')X GROUP BY 1" -> UNION ALL SELECT '"& RefDate &"' AS REF_DATE, 'FRMT_B0200_C0170' AS COD_KPI, 'REGULAMENTAR' AS TIPOLOGIA_TESTE, 'O campo deve ser reportado com formato yyyy-mm-dd.' AS DESCRIÇÃO, 'BU_LOANTAPE_WORK.OUT_B0200_MAIN_LIABILITIES' AS TABELA, '0170_dt_incptn' AS CAMPO, COUNT(*) AS NUM_REG, SUM(IF(`0170_dt_incptn` REGEXP '^[0-9]{4}-[0-9]{2}-[0-9]{2}$' and `0170_dt_incptn` NOT IN ('N/A','11111111111','11111111111.00','11111111111.000000','1111-11-11','0000-00-00','0001-01-01','9999-12-31','MISS','00000','99999999999','999999999999999','99999999999.00','99999999999.000000','-9999.9999','','Not applicable','XXX'),0 ,1)) AS NUM_REG_DIF, GROUP_CONCAT(CASE WHEN `0170_dt_incptn` REGEXP '^[0-9]{4}-[0-9]{2}-[0-9]{2}$' and `0170_dt_incptn` NOT IN ('N/A','11111111111','11111111111.00','11111111111.000000','1111-11-11','0000-00-00','0001-01-01','9999-12-31','MISS','00000','99999999999','999999999999999','99999999999.00','99999999999.000000','-9999.9999','','Not applicable','XXX') THEN NULL ELSE X.CHAVE_IT END, '; ') AS DETALHE FROM (SELECT *, 0020_UNIQ_ID AS CHAVE_IT, 0170_dt_incptn AS CAMPO_IT FROM BU_LOANTAPE_WORK.OUT_B0200_MAIN_LIABILITIES WHERE REF_DATE='"& RefDate &"')X GROUP BY 1
A97: ="FRMT_"&MID(G97,22,5)&"_C"&LEFT(B97,4) -> FRMT_B0200_C0180 | B97: 0180_dt_nxt_intrst_pymnt | C97: 0 | D97: O campo deve ser reportado com formato yyyy-mm-dd. | E97: "& RefDate &" | F97: REGULAMENTAR | G97: BU_LOANTAPE_WORK.OUT_B0200_MAIN_LIABILITIES | H97: (`0180_dt_nxt_intrst_pymnt` REGEXP '^[0-9]{4}-[0-9]{2}-[0-9]{2}$' and `0180_dt_nxt_intrst_pymnt` NOT IN ('N/A','11111111111','11111111111.00','11111111111.000000','1111-11-11','0000-00-00','9999-12-31','MISS','00000','99999999999','999999999999999','99999999999.00','99999999999.000000','-9999.9999','Not applicable','XXX')) OR `0180_dt_nxt_intrst_pymnt` IN ('0001-01-01', '') | I97: =+IF(C97=1,0,1) -> 1 | J97: =+IF(C97=0,"THEN NULL ELSE X.CHAVE_IT END","THEN X.CHAVE_IT ELSE NULL END") -> THEN NULL ELSE X.CHAVE_IT END | K97: ="UNION ALL SELECT '"&E97&"' AS REF_DATE, '"&A97&"' AS COD_KPI, '"&F97&"' AS TIPOLOGIA_TESTE, '"&D97&"' AS DESCRIÇÃO, '"&G97&"' AS TABELA, '"&B97&"' AS CAMPO, COUNT(*) AS NUM_REG, SUM(IF("&H97&","&C97&" ,"&I97&")) AS NUM_REG_DIF, GROUP_CONCAT(CASE WHEN "&H97&" "&J97&", '; ') AS DETALHE FROM (SELECT *, 0020_UNIQ_ID AS CHAVE_IT, "&B97&" AS CAMPO_IT FROM "&G97&" WHERE REF_DATE='"&E97&"')X GROUP BY 1" -> UNION ALL SELECT '"& RefDate &"' AS REF_DATE, 'FRMT_B0200_C0180' AS COD_KPI, 'REGULAMENTAR' AS TIPOLOGIA_TESTE, 'O campo deve ser reportado com formato yyyy-mm-dd.' AS DESCRIÇÃO, 'BU_LOANTAPE_WORK.OUT_B0200_MAIN_LIABILITIES' AS TABELA, '0180_dt_nxt_intrst_pymnt' AS CAMPO, COUNT(*) AS NUM_REG, SUM(IF((`0180_dt_nxt_intrst_pymnt` REGEXP '^[0-9]{4}-[0-9]{2}-[0-9]{2}$' and `0180_dt_nxt_intrst_pymnt` NOT IN ('N/A','11111111111','11111111111.00','11111111111.000000','1111-11-11','0000-00-00','9999-12-31','MISS','00000','99999999999','999999999999999','99999999999.00','99999999999.000000','-9999.9999','Not applicable','XXX')) OR `0180_dt_nxt_intrst_pymnt` IN ('0001-01-01', ''),0 ,1)) AS NUM_REG_DIF, GROUP_CONCAT(CASE WHEN (`0180_dt_nxt_intrst_pymnt` REGEXP '^[0-9]{4}-[0-9]{2}-[0-9]{2}$' and `0180_dt_nxt_intrst_pymnt` NOT IN ('N/A','11111111111','11111111111.00','11111111111.000000','1111-11-11','0000-00-00','9999-12-31','MISS','00000','99999999999','999999999999999','99999999999.00','99999999999.000000','-9999.9999','Not applicable','XXX')) OR `0180_dt_nxt_intrst_pymnt` IN ('0001-01-01', '') THEN NULL ELSE X.CHAVE_IT END, '; ') AS DETALHE FROM (SELECT *, 0020_UNIQ_ID AS CHAVE_IT, 0180_dt_nxt_intrst_pymnt AS CAMPO_IT FROM BU_LOANTAPE_WORK.OUT_B0200_MAIN_LIABILITIES WHERE REF_DATE='"& RefDate &"')X GROUP BY 1
A98: ="FRMT_"&MID(G98,22,5)&"_C"&LEFT(B98,4) -> FRMT_B0200_C0190 | B98: 0190_dt_nxt_rdmptn_pymnt | C98: 0 | D98: O campo deve ser reportado com formato yyyy-mm-dd. | E98: "& RefDate &" | F98: REGULAMENTAR | G98: BU_LOANTAPE_WORK.OUT_B0200_MAIN_LIABILITIES | H98: (`0190_dt_nxt_rdmptn_pymnt` REGEXP '^[0-9]{4}-[0-9]{2}-[0-9]{2}$' AND `0190_dt_nxt_rdmptn_pymnt` NOT IN ('N/A','11111111111','11111111111.00','11111111111.000000','1111-11-11','0000-00-00','0001-01-01','9999-12-31','MISS','00000','99999999999','999999999999999','99999999999.00','99999999999.000000','-9999.9999','','Not applicable','XXX')) OR `0190_dt_nxt_rdmptn_pymnt` = `0210_dt_lgl_fnl_mtrty` | I98: =+IF(C98=1,0,1) -> 1 | J98: =+IF(C98=0,"THEN NULL ELSE X.CHAVE_IT END","THEN X.CHAVE_IT ELSE NULL END") -> THEN NULL ELSE X.CHAVE_IT END | K98: ="UNION ALL SELECT '"&E98&"' AS REF_DATE, '"&A98&"' AS COD_KPI, '"&F98&"' AS TIPOLOGIA_TESTE, '"&D98&"' AS DESCRIÇÃO, '"&G98&"' AS TABELA, '"&B98&"' AS CAMPO, COUNT(*) AS NUM_REG, SUM(IF("&H98&","&C98&" ,"&I98&")) AS NUM_REG_DIF, GROUP_CONCAT(CASE WHEN "&H98&" "&J98&", '; ') AS DETALHE FROM (SELECT *, 0020_UNIQ_ID AS CHAVE_IT, "&B98&" AS CAMPO_IT FROM "&G98&" WHERE REF_DATE='"&E98&"')X GROUP BY 1" -> UNION ALL SELECT '"& RefDate &"' AS REF_DATE, 'FRMT_B0200_C0190' AS COD_KPI, 'REGULAMENTAR' AS TIPOLOGIA_TESTE, 'O campo deve ser reportado com formato yyyy-mm-dd.' AS DESCRIÇÃO, 'BU_LOANTAPE_WORK.OUT_B0200_MAIN_LIABILITIES' AS TABELA, '0190_dt_nxt_rdmptn_pymnt' AS CAMPO, COUNT(*) AS NUM_REG, SUM(IF((`0190_dt_nxt_rdmptn_pymnt` REGEXP '^[0-9]{4}-[0-9]{2}-[0-9]{2}$' AND `0190_dt_nxt_rdmptn_pymnt` NOT IN ('N/A','11111111111','11111111111.00','11111111111.000000','1111-11-11','0000-00-00','0001-01-01','9999-12-31','MISS','00000','99999999999','999999999999999','99999999999.00','99999999999.000000','-9999.9999','','Not applicable','XXX')) OR `0190_dt_nxt_rdmptn_pymnt` = `0210_dt_lgl_fnl_mtrty`,0 ,1)) AS NUM_REG_DIF, GROUP_CONCAT(CASE WHEN (`0190_dt_nxt_rdmptn_pymnt` REGEXP '^[0-9]{4}-[0-9]{2}-[0-9]{2}$' AND `0190_dt_nxt_rdmptn_pymnt` NOT IN ('N/A','11111111111','11111111111.00','11111111111.000000','1111-11-11','0000-00-00','0001-01-01','9999-12-31','MISS','00000','99999999999','999999999999999','99999999999.00','99999999999.000000','-9999.9999','','Not applicable','XXX')) OR `0190_dt_nxt_rdmptn_pymnt` = `0210_dt_lgl_fnl_mtrty` THEN NULL ELSE X.CHAVE_IT END, '; ') AS DETALHE FROM (SELECT *, 0020_UNIQ_ID AS CHAVE_IT, 0190_dt_nxt_rdmptn_pymnt AS CAMPO_IT FROM BU_LOANTAPE_WORK.OUT_B0200_MAIN_LIABILITIES WHERE REF_DATE='"& RefDate &"')X GROUP BY 1
A99: ="FRMT_"&MID(G99,22,5)&"_C"&LEFT(B99,4) -> FRMT_B0200_C0200 | B99: 0200_dt_erlst_rdmptn | C99: 0 | D99: O campo deve ser reportado com formato yyyy-mm-dd. | E99: "& RefDate &" | F99: REGULAMENTAR | G99: BU_LOANTAPE_WORK.OUT_B0200_MAIN_LIABILITIES | H99: (`0200_dt_erlst_rdmptn` REGEXP '^[0-9]{4}-[0-9]{2}-[0-9]{2}$' and `0200_dt_erlst_rdmptn` NOT IN ('N/A','11111111111','11111111111.00','11111111111.000000','1111-11-11','0000-00-00','9999-12-31','MISS','00000','99999999999','999999999999999','99999999999.00','99999999999.000000','-9999.9999','Not applicable','XXX')) OR `0200_dt_erlst_rdmptn` IN ('0001-01-01', '') | I99: =+IF(C99=1,0,1) -> 1 | J99: =+IF(C99=0,"THEN NULL ELSE X.CHAVE_IT END","THEN X.CHAVE_IT ELSE NULL END") -> THEN NULL ELSE X.CHAVE_IT END | K99: ="UNION ALL SELECT '"&E99&"' AS REF_DATE, '"&A99&"' AS COD_KPI, '"&F99&"' AS TIPOLOGIA_TESTE, '"&D99&"' AS DESCRIÇÃO, '"&G99&"' AS TABELA, '"&B99&"' AS CAMPO, COUNT(*) AS NUM_REG, SUM(IF("&H99&","&C99&" ,"&I99&")) AS NUM_REG_DIF, GROUP_CONCAT(CASE WHEN "&H99&" "&J99&", '; ') AS DETALHE FROM (SELECT *, 0020_UNIQ_ID AS CHAVE_IT, "&B99&" AS CAMPO_IT FROM "&G99&" WHERE REF_DATE='"&E99&"')X GROUP BY 1" -> UNION ALL SELECT '"& RefDate &"' AS REF_DATE, 'FRMT_B0200_C0200' AS COD_KPI, 'REGULAMENTAR' AS TIPOLOGIA_TESTE, 'O campo deve ser reportado com formato yyyy-mm-dd.' AS DESCRIÇÃO, 'BU_LOANTAPE_WORK.OUT_B0200_MAIN_LIABILITIES' AS TABELA, '0200_dt_erlst_rdmptn' AS CAMPO, COUNT(*) AS NUM_REG, SUM(IF((`0200_dt_erlst_rdmptn` REGEXP '^[0-9]{4}-[0-9]{2}-[0-9]{2}$' and `0200_dt_erlst_rdmptn` NOT IN ('N/A','11111111111','11111111111.00','11111111111.000000','1111-11-11','0000-00-00','9999-12-31','MISS','00000','99999999999','999999999999999','99999999999.00','99999999999.000000','-9999.9999','Not applicable','XXX')) OR `0200_dt_erlst_rdmptn` IN ('0001-01-01', ''),0 ,1)) AS NUM_REG_DIF, GROUP_CONCAT(CASE WHEN (`0200_dt_erlst_rdmptn` REGEXP '^[0-9]{4}-[0-9]{2}-[0-9]{2}$' and `0200_dt_erlst_rdmptn` NOT IN ('N/A','11111111111','11111111111.00','11111111111.000000','1111-11-11','0000-00-00','9999-12-31','MISS','00000','99999999999','999999999999999','99999999999.00','99999999999.000000','-9999.9999','Not applicable','XXX')) OR `0200_dt_erlst_rdmptn` IN ('0001-01-01', '') THEN NULL ELSE X.CHAVE_IT END, '; ') AS DETALHE FROM (SELECT *, 0020_UNIQ_ID AS CHAVE_IT, 0200_dt_erlst_rdmptn AS CAMPO_IT FROM BU_LOANTAPE_WORK.OUT_B0200_MAIN_LIABILITIES WHERE REF_DATE='"& RefDate &"')X GROUP BY 1
A100: ="FRMT_"&MID(G100,22,5)&"_C"&LEFT(B100,4) -> FRMT_B0200_C0210 | B100: 0210_dt_lgl_fnl_mtrty | C100: 0 | D100: O campo deve ser reportado com formato yyyy-mm-dd. | E100: "& RefDate &" | F100: REGULAMENTAR | G100: BU_LOANTAPE_WORK.OUT_B0200_MAIN_LIABILITIES | H100: (`0210_dt_lgl_fnl_mtrty` REGEXP '^[0-9]{4}-[0-9]{2}-[0-9]{2}$' and `0210_dt_lgl_fnl_mtrty` NOT IN ('N/A','11111111111','11111111111.00','11111111111.000000','1111-11-11','0000-00-00','9999-12-31','MISS','00000','99999999999','999999999999999','99999999999.00','99999999999.000000','-9999.9999','Not applicable','XXX')) OR `0210_dt_lgl_fnl_mtrty` IN ('0001-01-01', '') | I100: =+IF(C100=1,0,1) -> 1 | J100: =+IF(C100=0,"THEN NULL ELSE X.CHAVE_IT END","THEN X.CHAVE_IT ELSE NULL END") -> THEN NULL ELSE X.CHAVE_IT END | K100: ="UNION ALL SELECT '"&E100&"' AS REF_DATE, '"&A100&"' AS COD_KPI, '"&F100&"' AS TIPOLOGIA_TESTE, '"&D100&"' AS DESCRIÇÃO, '"&G100&"' AS TABELA, '"&B100&"' AS CAMPO, COUNT(*) AS NUM_REG, SUM(IF("&H100&","&C100&" ,"&I100&")) AS NUM_REG_DIF, GROUP_CONCAT(CASE WHEN "&H100&" "&J100&", '; ') AS DETALHE FROM (SELECT *, 0020_UNIQ_ID AS CHAVE_IT, "&B100&" AS CAMPO_IT FROM "&G100&" WHERE REF_DATE='"&E100&"')X GROUP BY 1" -> UNION ALL SELECT '"& RefDate &"' AS REF_DATE, 'FRMT_B0200_C0210' AS COD_KPI, 'REGULAMENTAR' AS TIPOLOGIA_TESTE, 'O campo deve ser reportado com formato yyyy-mm-dd.' AS DESCRIÇÃO, 'BU_LOANTAPE_WORK.OUT_B0200_MAIN_LIABILITIES' AS TABELA, '0210_dt_lgl_fnl_mtrty' AS CAMPO, COUNT(*) AS NUM_REG, SUM(IF((`0210_dt_lgl_fnl_mtrty` REGEXP '^[0-9]{4}-[0-9]{2}-[0-9]{2}$' and `0210_dt_lgl_fnl_mtrty` NOT IN ('N/A','11111111111','11111111111.00','11111111111.000000','1111-11-11','0000-00-00','9999-12-31','MISS','00000','99999999999','999999999999999','99999999999.00','99999999999.000000','-9999.9999','Not applicable','XXX')) OR `0210_dt_lgl_fnl_mtrty` IN ('0001-01-01', ''),0 ,1)) AS NUM_REG_DIF, GROUP_CONCAT(CASE WHEN (`0210_dt_lgl_fnl_mtrty` REGEXP '^[0-9]{4}-[0-9]{2}-[0-9]{2}$' and `0210_dt_lgl_fnl_mtrty` NOT IN ('N/A','11111111111','11111111111.00','11111111111.000000','1111-11-11','0000-00-00','9999-12-31','MISS','00000','99999999999','999999999999999','99999999999.00','99999999999.000000','-9999.9999','Not applicable','XXX')) OR `0210_dt_lgl_fnl_mtrty` IN ('0001-01-01', '') THEN NULL ELSE X.CHAVE_IT END, '; ') AS DETALHE FROM (SELECT *, 0020_UNIQ_ID AS CHAVE_IT, 0210_dt_lgl_fnl_mtrty AS CAMPO_IT FROM BU_LOANTAPE_WORK.OUT_B0200_MAIN_LIABILITIES WHERE REF_DATE='"& RefDate &"')X GROUP BY 1
A101: ="FRMT_"&MID(G101,22,5)&"_C"&LEFT(B101,4) -> FRMT_B0200_C0220 | B101: 0220_governing_law | C101: 0 | D101: O campo deve ser reportado usando o código ISO 3166-1 alpha-2. | E101: "& RefDate &" | F101: REGULAMENTAR | G101: BU_LOANTAPE_WORK.OUT_B0200_MAIN_LIABILITIES | H101: LENGTH(`0220_governing_law`) = 2 OR `0220_governing_law` = 'XX' | I101: =+IF(C101=1,0,1) -> 1 | J101: =+IF(C101=0,"THEN NULL ELSE X.CHAVE_IT END","THEN X.CHAVE_IT ELSE NULL END") -> THEN NULL ELSE X.CHAVE_IT END | K101: ="UNION ALL SELECT '"&E101&"' AS REF_DATE, '"&A101&"' AS COD_KPI, '"&F101&"' AS TIPOLOGIA_TESTE, '"&D101&"' AS DESCRIÇÃO, '"&G101&"' AS TABELA, '"&B101&"' AS CAMPO, COUNT(*) AS NUM_REG, SUM(IF("&H101&","&C101&" ,"&I101&")) AS NUM_REG_DIF, GROUP_CONCAT(CASE WHEN "&H101&" "&J101&", '; ') AS DETALHE FROM (SELECT *, 0020_UNIQ_ID AS CHAVE_IT, "&B101&" AS CAMPO_IT FROM "&G101&" WHERE REF_DATE='"&E101&"')X GROUP BY 1" -> UNION ALL SELECT '"& RefDate &"' AS REF_DATE, 'FRMT_B0200_C0220' AS COD_KPI, 'REGULAMENTAR' AS TIPOLOGIA_TESTE, 'O campo deve ser reportado usando o código ISO 3166-1 alpha-2.' AS DESCRIÇÃO, 'BU_LOANTAPE_WORK.OUT_B0200_MAIN_LIABILITIES' AS TABELA, '0220_governing_law' AS CAMPO, COUNT(*) AS NUM_REG, SUM(IF(LENGTH(`0220_governing_law`) = 2 OR `0220_governing_law` = 'XX',0 ,1)) AS NUM_REG_DIF, GROUP_CONCAT(CASE WHEN LENGTH(`0220_governing_law`) = 2 OR `0220_governing_law` = 'XX' THEN NULL ELSE X.CHAVE_IT END, '; ') AS DETALHE FROM (SELECT *, 0020_UNIQ_ID AS CHAVE_IT, 0220_governing_law AS CAMPO_IT FROM BU_LOANTAPE_WORK.OUT_B0200_MAIN_LIABILITIES WHERE REF_DATE='"& RefDate &"')X GROUP BY 1
A102: ="FRMT_"&MID(G102,22,5)&"_C"&LEFT(B102,4) -> FRMT_B0200_C0230 | B102: 0230_bail_in_rcgntn_cls | C102: 0 | D102: Os valores dos dropdowns devem ser respeitados. | E102: "& RefDate &" | F102: REGULAMENTAR | G102: BU_LOANTAPE_WORK.OUT_B0200_MAIN_LIABILITIES | H102: `0230_bail_in_rcgntn_cls` IN ('Yes, supported by Legal Opinion', 'Yes, not supported by Legal Opinion', 'No', 'Not applicable', 'Aggregated', 'Not applicable') | I102: =+IF(C102=1,0,1) -> 1 | J102: =+IF(C102=0,"THEN NULL ELSE X.CHAVE_IT END","THEN X.CHAVE_IT ELSE NULL END") -> THEN NULL ELSE X.CHAVE_IT END | K102: ="UNION ALL SELECT '"&E102&"' AS REF_DATE, '"&A102&"' AS COD_KPI, '"&F102&"' AS TIPOLOGIA_TESTE, '"&D102&"' AS DESCRIÇÃO, '"&G102&"' AS TABELA, '"&B102&"' AS CAMPO, COUNT(*) AS NUM_REG, SUM(IF("&H102&","&C102&" ,"&I102&")) AS NUM_REG_DIF, GROUP_CONCAT(CASE WHEN "&H102&" "&J102&", '; ') AS DETALHE FROM (SELECT *, 0020_UNIQ_ID AS CHAVE_IT, "&B102&" AS CAMPO_IT FROM "&G102&" WHERE REF_DATE='"&E102&"')X GROUP BY 1" -> UNION ALL SELECT '"& RefDate &"' AS REF_DATE, 'FRMT_B0200_C0230' AS COD_KPI, 'REGULAMENTAR' AS TIPOLOGIA_TESTE, 'Os valores dos dropdowns devem ser respeitados.' AS DESCRIÇÃO, 'BU_LOANTAPE_WORK.OUT_B0200_MAIN_LIABILITIES' AS TABELA, '0230_bail_in_rcgntn_cls' AS CAMPO, COUNT(*) AS NUM_REG, SUM(IF(`0230_bail_in_rcgntn_cls` IN ('Yes, supported by Legal Opinion', 'Yes, not supported by Legal Opinion', 'No', 'Not applicable', 'Aggregated', 'Not applicable'),0 ,1)) AS NUM_REG_DIF, GROUP_CONCAT(CASE WHEN `0230_bail_in_rcgntn_cls` IN ('Yes, supported by Legal Opinion', 'Yes, not supported by Legal Opinion', 'No', 'Not applicable', 'Aggregated', 'Not applicable') THEN NULL ELSE X.CHAVE_IT END, '; ') AS DETALHE FROM (SELECT *, 0020_UNIQ_ID AS CHAVE_IT, 0230_bail_in_rcgntn_cls AS CAMPO_IT FROM BU_LOANTAPE_WORK.OUT_B0200_MAIN_LIABILITIES WHERE REF_DATE='"& RefDate &"')X GROUP BY 1
A103: ="FRMT_"&MID(G103,22,5)&"_C"&LEFT(B103,4) -> FRMT_B0200_C0240 | B103: 0240_zero_coupon | C103: 0 | D103: Os valores dos dropdowns devem ser respeitados. | E103: "& RefDate &" | F103: REGULAMENTAR | G103: BU_LOANTAPE_WORK.OUT_B0200_MAIN_LIABILITIES | H103: `0240_zero_coupon` IN ('ZCB issued at discount', 'ZCB not issued at discount', 'No ZCB', 'Aggregated') | I103: =+IF(C103=1,0,1) -> 1 | J103: =+IF(C103=0,"THEN NULL ELSE X.CHAVE_IT END","THEN X.CHAVE_IT ELSE NULL END") -> THEN NULL ELSE X.CHAVE_IT END | K103: ="UNION ALL SELECT '"&E103&"' AS REF_DATE, '"&A103&"' AS COD_KPI, '"&F103&"' AS TIPOLOGIA_TESTE, '"&D103&"' AS DESCRIÇÃO, '"&G103&"' AS TABELA, '"&B103&"' AS CAMPO, COUNT(*) AS NUM_REG, SUM(IF("&H103&","&C103&" ,"&I103&")) AS NUM_REG_DIF, GROUP_CONCAT(CASE WHEN "&H103&" "&J103&", '; ') AS DETALHE FROM (SELECT *, 0020_UNIQ_ID AS CHAVE_IT, "&B103&" AS CAMPO_IT FROM "&G103&" WHERE REF_DATE='"&E103&"')X GROUP BY 1" -> UNION ALL SELECT '"& RefDate &"' AS REF_DATE, 'FRMT_B0200_C0240' AS COD_KPI, 'REGULAMENTAR' AS TIPOLOGIA_TESTE, 'Os valores dos dropdowns devem ser respeitados.' AS DESCRIÇÃO, 'BU_LOANTAPE_WORK.OUT_B0200_MAIN_LIABILITIES' AS TABELA, '0240_zero_coupon' AS CAMPO, COUNT(*) AS NUM_REG, SUM(IF(`0240_zero_coupon` IN ('ZCB issued at discount', 'ZCB not issued at discount', 'No ZCB', 'Aggregated'),0 ,1)) AS NUM_REG_DIF, GROUP_CONCAT(CASE WHEN `0240_zero_coupon` IN ('ZCB issued at discount', 'ZCB not issued at discount', 'No ZCB', 'Aggregated') THEN NULL ELSE X.CHAVE_IT END, '; ') AS DETALHE FROM (SELECT *, 0020_UNIQ_ID AS CHAVE_IT, 0240_zero_coupon AS CAMPO_IT FROM BU_LOANTAPE_WORK.OUT_B0200_MAIN_LIABILITIES WHERE REF_DATE='"& RefDate &"')X GROUP BY 1
A104: ="FRMT_"&MID(G104,22,5)&"_C"&LEFT(B104,4) -> FRMT_B0200_C0250 | B104: 0250_strctrd_prdct | C104: 0 | D104: Os valores dos dropdowns devem ser respeitados. | E104: "& RefDate &" | F104: REGULAMENTAR | G104: BU_LOANTAPE_WORK.OUT_B0200_MAIN_LIABILITIES | H104: `0250_strctrd_prdct` IN ('Non-structured/Vanilla', 'Structured', 'Other non-standard terms', 'Only structured coupon', 'Aggregated') | I104: =+IF(C104=1,0,1) -> 1 | J104: =+IF(C104=0,"THEN NULL ELSE X.CHAVE_IT END","THEN X.CHAVE_IT ELSE NULL END") -> THEN NULL ELSE X.CHAVE_IT END | K104: ="UNION ALL SELECT '"&E104&"' AS REF_DATE, '"&A104&"' AS COD_KPI, '"&F104&"' AS TIPOLOGIA_TESTE, '"&D104&"' AS DESCRIÇÃO, '"&G104&"' AS TABELA, '"&B104&"' AS CAMPO, COUNT(*) AS NUM_REG, SUM(IF("&H104&","&C104&" ,"&I104&")) AS NUM_REG_DIF, GROUP_CONCAT(CASE WHEN "&H104&" "&J104&", '; ') AS DETALHE FROM (SELECT *, 0020_UNIQ_ID AS CHAVE_IT, "&B104&" AS CAMPO_IT FROM "&G104&" WHERE REF_DATE='"&E104&"')X GROUP BY 1" -> UNION ALL SELECT '"& RefDate &"' AS REF_DATE, 'FRMT_B0200_C0250' AS COD_KPI, 'REGULAMENTAR' AS TIPOLOGIA_TESTE, 'Os valores dos dropdowns devem ser respeitados.' AS DESCRIÇÃO, 'BU_LOANTAPE_WORK.OUT_B0200_MAIN_LIABILITIES' AS TABELA, '0250_strctrd_prdct' AS CAMPO, COUNT(*) AS NUM_REG, SUM(IF(`0250_strctrd_prdct` IN ('Non-structured/Vanilla', 'Structured', 'Other non-standard terms', 'Only structured coupon', 'Aggregated'),0 ,1)) AS NUM_REG_DIF, GROUP_CONCAT(CASE WHEN `0250_strctrd_prdct` IN ('Non-structured/Vanilla', 'Structured', 'Other non-standard terms', 'Only structured coupon', 'Aggregated') THEN NULL ELSE X.CHAVE_IT END, '; ') AS DETALHE FROM (SELECT *, 0020_UNIQ_ID AS CHAVE_IT, 0250_strctrd_prdct AS CAMPO_IT FROM BU_LOANTAPE_WORK.OUT_B0200_MAIN_LIABILITIES WHERE REF_DATE='"& RefDate &"')X GROUP BY 1
A105: ="FRMT_"&MID(G105,22,5)&"_C"&LEFT(B105,4) -> FRMT_B0200_C0260 | B105: 0260_grntd_min_amnt_strctrd_prdct | C105: 0 | D105: O campo deve ser reportado com formato numérico com 2 casas decimais. | E105: "& RefDate &" | F105: REGULAMENTAR | G105: BU_LOANTAPE_WORK.OUT_B0200_MAIN_LIABILITIES | H105: CAST(ROUND(`0260_grntd_min_amnt_strctrd_prdct`, 2) AS STRING) = CAST(`0260_grntd_min_amnt_strctrd_prdct` AS STRING) AND CAST(`0260_grntd_min_amnt_strctrd_prdct` AS STRING) NOT IN ('N/A','11111111111','11111111111.00','11111111111.000000','1111-11-11','0000-00-00','0001-01-01','9999-12-31','MISS','00000','99999999999','99999999999.00','99999999999.000000','-9999.9999','','Not applicable','XXX') | I105: =+IF(C105=1,0,1) -> 1 | J105: =+IF(C105=0,"THEN NULL ELSE X.CHAVE_IT END","THEN X.CHAVE_IT ELSE NULL END") -> THEN NULL ELSE X.CHAVE_IT END | K105: ="UNION ALL SELECT '"&E105&"' AS REF_DATE, '"&A105&"' AS COD_KPI, '"&F105&"' AS TIPOLOGIA_TESTE, '"&D105&"' AS DESCRIÇÃO, '"&G105&"' AS TABELA, '"&B105&"' AS CAMPO, COUNT(*) AS NUM_REG, SUM(IF("&H105&","&C105&" ,"&I105&")) AS NUM_REG_DIF, GROUP_CONCAT(CASE WHEN "&H105&" "&J105&", '; ') AS DETALHE FROM (SELECT *, 0020_UNIQ_ID AS CHAVE_IT, "&B105&" AS CAMPO_IT FROM "&G105&" WHERE REF_DATE='"&E105&"')X GROUP BY 1" -> UNION ALL SELECT '"& RefDate &"' AS REF_DATE, 'FRMT_B0200_C0260' AS COD_KPI, 'REGULAMENTAR' AS TIPOLOGIA_TESTE, 'O campo deve ser reportado com formato numérico com 2 casas decimais.' AS DESCRIÇÃO, 'BU_LOANTAPE_WORK.OUT_B0200_MAIN_LIABILITIES' AS TABELA, '0260_grntd_min_amnt_strctrd_prdct' AS CAMPO, COUNT(*) AS NUM_REG, SUM(IF(CAST(ROUND(`0260_grntd_min_amnt_strctrd_prdct`, 2) AS STRING) = CAST(`0260_grntd_min_amnt_strctrd_prdct` AS STRING) AND CAST(`0260_grntd_min_amnt_strctrd_prdct` AS STRING) NOT IN ('N/A','11111111111','11111111111.00','11111111111.000000','1111-11-11','0000-00-00','0001-01-01','9999-12-31','MISS','00000','99999999999','99999999999.00','99999999999.000000','-9999.9999','','Not applicable','XXX'),0 ,1)) AS NUM_REG_DIF, GROUP_CONCAT(CASE WHEN CAST(ROUND(`0260_grntd_min_amnt_strctrd_prdct`, 2) AS STRING) = CAST(`0260_grntd_min_amnt_strctrd_prdct` AS STRING) AND CAST(`0260_grntd_min_amnt_strctrd_prdct` AS STRING) NOT IN ('N/A','11111111111','11111111111.00','11111111111.000000','1111-11-11','0000-00-00','0001-01-01','9999-12-31','MISS','00000','99999999999','99999999999.00','99999999999.000000','-9999.9999','','Not applicable','XXX') THEN NULL ELSE X.CHAVE_IT END, '; ') AS DETALHE FROM (SELECT *, 0020_UNIQ_ID AS CHAVE_IT, 0260_grntd_min_amnt_strctrd_prdct AS CAMPO_IT FROM BU_LOANTAPE_WORK.OUT_B0200_MAIN_LIABILITIES WHERE REF_DATE='"& RefDate &"')X GROUP BY 1
A106: ="FRMT_"&MID(G106,22,5)&"_C"&LEFT(B106,4) -> FRMT_B0200_C0270 | B106: 0270_fv_amnt_strctrd_prdct | C106: 0 | D106: O campo deve ser reportado com formato numérico com 2 casas decimais. | E106: "& RefDate &" | F106: REGULAMENTAR | G106: BU_LOANTAPE_WORK.OUT_B0200_MAIN_LIABILITIES | H106: CAST(ROUND(`0270_fv_amnt_strctrd_prdct`, 2) AS STRING) = CAST(`0270_fv_amnt_strctrd_prdct` AS STRING) AND CAST(`0270_fv_amnt_strctrd_prdct` AS STRING) NOT IN ('N/A','11111111111','11111111111.00','11111111111.000000','1111-11-11','0000-00-00','0001-01-01','9999-12-31','MISS','00000','99999999999','99999999999.00','99999999999.000000','-9999.9999','','Not applicable','XXX') | I106: =+IF(C106=1,0,1) -> 1 | J106: =+IF(C106=0,"THEN NULL ELSE X.CHAVE_IT END","THEN X.CHAVE_IT ELSE NULL END") -> THEN NULL ELSE X.CHAVE_IT END | K106: ="UNION ALL SELECT '"&E106&"' AS REF_DATE, '"&A106&"' AS COD_KPI, '"&F106&"' AS TIPOLOGIA_TESTE, '"&D106&"' AS DESCRIÇÃO, '"&G106&"' AS TABELA, '"&B106&"' AS CAMPO, COUNT(*) AS NUM_REG, SUM(IF("&H106&","&C106&" ,"&I106&")) AS NUM_REG_DIF, GROUP_CONCAT(CASE WHEN "&H106&" "&J106&", '; ') AS DETALHE FROM (SELECT *, 0020_UNIQ_ID AS CHAVE_IT, "&B106&" AS CAMPO_IT FROM "&G106&" WHERE REF_DATE='"&E106&"')X GROUP BY 1" -> UNION ALL SELECT '"& RefDate &"' AS REF_DATE, 'FRMT_B0200_C0270' AS COD_KPI, 'REGULAMENTAR' AS TIPOLOGIA_TESTE, 'O campo deve ser reportado com formato numérico com 2 casas decimais.' AS DESCRIÇÃO, 'BU_LOANTAPE_WORK.OUT_B0200_MAIN_LIABILITIES' AS TABELA, '0270_fv_amnt_strctrd_prdct' AS CAMPO, COUNT(*) AS NUM_REG, SUM(IF(CAST(ROUND(`0270_fv_amnt_strctrd_prdct`, 2) AS STRING) = CAST(`0270_fv_amnt_strctrd_prdct` AS STRING) AND CAST(`0270_fv_amnt_strctrd_prdct` AS STRING) NOT IN ('N/A','11111111111','11111111111.00','11111111111.000000','1111-11-11','0000-00-00','0001-01-01','9999-12-31','MISS','00000','99999999999','99999999999.00','99999999999.000000','-9999.9999','','Not applicable','XXX'),0 ,1)) AS NUM_REG_DIF, GROUP_CONCAT(CASE WHEN CAST(ROUND(`0270_fv_amnt_strctrd_prdct`, 2) AS STRING) = CAST(`0270_fv_amnt_strctrd_prdct` AS STRING) AND CAST(`0270_fv_amnt_strctrd_prdct` AS STRING) NOT IN ('N/A','11111111111','11111111111.00','11111111111.000000','1111-11-11','0000-00-00','0001-01-01','9999-12-31','MISS','00000','99999999999','99999999999.00','99999999999.000000','-9999.9999','','Not applicable','XXX') THEN NULL ELSE X.CHAVE_IT END, '; ') AS DETALHE FROM (SELECT *, 0020_UNIQ_ID AS CHAVE_IT, 0270_fv_amnt_strctrd_prdct AS CAMPO_IT FROM BU_LOANTAPE_WORK.OUT_B0200_MAIN_LIABILITIES WHERE REF_DATE='"& RefDate &"')X GROUP BY 1
A107: ="FRMT_"&MID(G107,22,5)&"_C"&LEFT(B107,4) -> FRMT_B0200_C0280 | B107: 0280_flg_ncnp_dpsts | C107: 0 | D107: O campo deve ser reportado usando TRUE ou FALSE. | E107: "& RefDate &" | F107: REGULAMENTAR | G107: BU_LOANTAPE_WORK.OUT_B0200_MAIN_LIABILITIES | H107: `0280_flg_ncnp_dpsts` IN ('TRUE', 'FALSE') | I107: =+IF(C107=1,0,1) -> 1 | J107: =+IF(C107=0,"THEN NULL ELSE X.CHAVE_IT END","THEN X.CHAVE_IT ELSE NULL END") -> THEN NULL ELSE X.CHAVE_IT END | K107: ="UNION ALL SELECT '"&E107&"' AS REF_DATE, '"&A107&"' AS COD_KPI, '"&F107&"' AS TIPOLOGIA_TESTE, '"&D107&"' AS DESCRIÇÃO, '"&G107&"' AS TABELA, '"&B107&"' AS CAMPO, COUNT(*) AS NUM_REG, SUM(IF("&H107&","&C107&" ,"&I107&")) AS NUM_REG_DIF, GROUP_CONCAT(CASE WHEN "&H107&" "&J107&", '; ') AS DETALHE FROM (SELECT *, 0020_UNIQ_ID AS CHAVE_IT, "&B107&" AS CAMPO_IT FROM "&G107&" WHERE REF_DATE='"&E107&"')X GROUP BY 1" -> UNION ALL SELECT '"& RefDate &"' AS REF_DATE, 'FRMT_B0200_C0280' AS COD_KPI, 'REGULAMENTAR' AS TIPOLOGIA_TESTE, 'O campo deve ser reportado usando TRUE ou FALSE.' AS DESCRIÇÃO, 'BU_LOANTAPE_WORK.OUT_B0200_MAIN_LIABILITIES' AS TABELA, '0280_flg_ncnp_dpsts' AS CAMPO, COUNT(*) AS NUM_REG, SUM(IF(`0280_flg_ncnp_dpsts` IN ('TRUE', 'FALSE'),0 ,1)) AS NUM_REG_DIF, GROUP_CONCAT(CASE WHEN `0280_flg_ncnp_dpsts` IN ('TRUE', 'FALSE') THEN NULL ELSE X.CHAVE_IT END, '; ') AS DETALHE FROM (SELECT *, 0020_UNIQ_ID AS CHAVE_IT, 0280_flg_ncnp_dpsts AS CAMPO_IT FROM BU_LOANTAPE_WORK.OUT_B0200_MAIN_LIABILITIES WHERE REF_DATE='"& RefDate &"')X GROUP BY 1
... A157: ="FRMT_"&MID(G157,22,5)&"_C"&LEFT(B157,4) -> FRMT_B0200_C5010 | B157: 5010_flg_art21_7a_srmr | C157: 0 | D157: O campo deve ser reportado usando TRUE ou FALSE. | E157: "& RefDate &" | F157: REGULAMENTAR | G157: BU_LOANTAPE_WORK.OUT_B0200_MAIN_LIABILITIES | H157: `5010_flg_art21_7a_srmr` IN ('TRUE', 'FALSE') | I157: =+IF(C157=1,0,1) -> 1 | J157: =+IF(C157=0,"THEN NULL ELSE X.CHAVE_IT END","THEN X.CHAVE_IT ELSE NULL END") -> THEN NULL ELSE X.CHAVE_IT END | K157: ="UNION ALL SELECT '"&E157&"' AS REF_DATE, '"&A157&"' AS COD_KPI, '"&F157&"' AS TIPOLOGIA_TESTE, '"&D157&"' AS DESCRIÇÃO, '"&G157&"' AS TABELA, '"&B157&"' AS CAMPO, COUNT(*) AS NUM_REG, SUM(IF("&H157&","&C157&" ,"&I157&")) AS NUM_REG_DIF, GROUP_CONCAT(CASE WHEN "&H157&" "&J157&", '; ') AS DETALHE FROM (SELECT *, 0020_UNIQ_ID AS CHAVE_IT, "&B157&" AS CAMPO_IT FROM "&G157&" WHERE REF_DATE='"&E157&"')X GROUP BY 1" -> UNION ALL SELECT '"& RefDate &"' AS REF_DATE, 'FRMT_B0200_C5010' AS COD_KPI, 'REGULAMENTAR' AS TIPOLOGIA_TESTE, 'O campo deve ser reportado usando TRUE ou FALSE.' AS DESCRIÇÃO, 'BU_LOANTAPE_WORK.OUT_B0200_MAIN_LIABILITIES' AS TABELA, '5010_flg_art21_7a_srmr' AS CAMPO, COUNT(*) AS NUM_REG, SUM(IF(`5010_flg_art21_7a_srmr` IN ('TRUE', 'FALSE'),0 ,1)) AS NUM_REG_DIF, GROUP_CONCAT(CASE WHEN `5010_flg_art21_7a_srmr` IN ('TRUE', 'FALSE') THEN NULL ELSE X.CHAVE_IT END, '; ') AS DETALHE FROM (SELECT *, 0020_UNIQ_ID AS CHAVE_IT, 5010_flg_art21_7a_srmr AS CAMPO_IT FROM BU_LOANTAPE_WORK.OUT_B0200_MAIN_LIABILITIES WHERE REF_DATE='"& RefDate &"')X GROUP BY 1
A158: v_2_0053 | B158: 0030_governing_law | C158: 1 | D158: =+VLOOKUP(A158,Descrição!A:K,11,FALSE) -> O campo deve ser reportado usando o código ISO 3166-1 alfa-2 ou 3166-2. | E158: "& RefDate &" | F158: REGULAMENTAR | G158: BU_LOANTAPE_WORK.OUT_B0500_GUARANTEES | H158: `0030_governing_law` NOT IN ('AF','AX','AL','DZ','AS','AD','AO','AI','AQ','AG','AR','AM','AW','AU','AT','AZ','BS','BH','BD','BB','BY','BE','BZ','BJ','BM','BT','BO','BQ','BA','BW','BV','BR','IO','BN','BG','BF','BI','CV','KH','CM','CA','KY','CF','TD','CL','CN','CX','CC','CO','KM','CG','CD','CK','CR','CI','HR','CU','CW','CY','CZ','DK','DJ','DM','DO','EC','EG','SV','GQ','ER','EE','SZ','ET','FK','FO','FJ','FI','FR','GF','PF','TF','GA','GM','GE','DE','GH','GI','GR','GL','GD','GP','GU','GT','GG','GN','GW','GY','HT','HM','VA','HN','HK','HU','IS','IN','ID','IR','IQ','IE','IM','IL','IT','JM','JP','JE','JO','KZ','KE','KI','KP','KR','KW','KG','LA','LV','LB','LS','LR','LY','LI','LT','LU','MO','MG','MW','MY','MV','ML','MT','MH','MQ','MR','MU','YT','MX','FM','MD','MC','MN','ME','MS','MA','MZ','MM','NA','NR','NP','NL','NC','NZ','NI','NE','NG','NU','NF','MK','MP','NO','OM','PK','PW','PS','PA','PG','PY','PE','PH','PN','PL','PT','PR','QA','RE','RO','RU','RW','BL','SH','KN','LC','MF','PM','VC','WS','SM','ST','SA','SN','RS','SC','SL','SG','SX','SK','SI','SB','SO','ZA','GS','SS','ES','LK','SD','SR','SJ','SE','CH','SY','TW','TJ','TZ','TH','TL','TG','TK','TO','TT','TN','TR','TM','TC','TV','UG','UA','AE','GB','US','UM','UY','UZ','VU','VE','VN','VG','VI','WF','EH','YE','ZM','ZW') | I158: =+IF(C158=1,0,1) -> 0 | J158: =+IF(C158=0,"THEN NULL ELSE X.CHAVE_IT END","THEN X.CHAVE_IT ELSE NULL END") -> THEN X.CHAVE_IT ELSE NULL END | K158: ="UNION ALL SELECT '"&E158&"' AS REF_DATE, '"&A158&"' AS COD_KPI, '"&F158&"' AS TIPOLOGIA_TESTE, '"&D158&"' AS DESCRIÇÃO, '"&G158&"' AS TABELA, '"&B158&"' AS CAMPO, COUNT(*) AS NUM_REG, SUM(IF("&H158&","&C158&" ,"&I158&")) AS NUM_REG_DIF, GROUP_CONCAT(CASE WHEN "&H158&" "&J158&", '; ') AS DETALHE FROM (SELECT *, 0020_UNIQ_ID_GUARANTEE AS CHAVE_IT, "&B158&" AS CAMPO_IT FROM "&G158&" WHERE REF_DATE='"&E158&"')X GROUP BY 1" -> UNION ALL SELECT '"& RefDate &"' AS REF_DATE, 'v_2_0053' AS COD_KPI, 'REGULAMENTAR' AS TIPOLOGIA_TESTE, 'O campo deve ser reportado usando o código ISO 3166-1 alfa-2 ou 3166-2.' AS DESCRIÇÃO, 'BU_LOANTAPE_WORK.OUT_B0500_GUARANTEES' AS TABELA, '0030_governing_law' AS CAMPO, COUNT(*) AS NUM_REG, SUM(IF(`0030_governing_law` NOT IN ('AF','AX','AL','DZ','AS','AD','AO','AI','AQ','AG','AR','AM','AW','AU','AT','AZ','BS','BH','BD','BB','BY','BE','BZ','BJ','BM','BT','BO','BQ','BA','BW','BV','BR','IO','BN','BG','BF','BI','CV','KH','CM','CA','KY','CF','TD','CL','CN','CX','CC','CO','KM','CG','CD','CK','CR','CI','HR','CU','CW','CY','CZ','DK','DJ','DM','DO','EC','EG','SV','GQ','ER','EE','SZ','ET','FK','FO','FJ','FI','FR','GF','PF','TF','GA','GM','GE','DE','GH','GI','GR','GL','GD','GP','GU','GT','GG','GN','GW','GY','HT','HM','VA','HN','HK','HU','IS','IN','ID','IR','IQ','IE','IM','IL','IT','JM','JP','JE','JO','KZ','KE','KI','KP','KR','KW','KG','LA','LV','LB','LS','LR','LY','LI','LT','LU','MO','MG','MW','MY','MV','ML','MT','MH','MQ','MR','MU','YT','MX','FM','MD','MC','MN','ME','MS','MA','MZ','MM','NA','NR','NP','NL','NC','NZ','NI','NE','NG','NU','NF','MK','MP','NO','OM','PK','PW','PS','PA','PG','PY','PE','PH','PN','PL','PT','PR','QA','RE','RO','RU','RW','BL','SH','KN','LC','MF','PM','VC','WS','SM','ST','SA','SN','RS','SC','SL','SG','SX','SK','SI','SB','SO','ZA','GS','SS','ES','LK','SD','SR','SJ','SE','CH','SY','TW','TJ','TZ','TH','TL','TG','TK','TO','TT','TN','TR','TM','TC','TV','UG','UA','AE','GB','US','UM','UY','UZ','VU','VE','VN','VG','VI','WF','EH','YE','ZM','ZW'),1 ,0)) AS NUM_REG_DIF, GROUP_CONCAT(CASE WHEN `0030_governing_law` NOT IN ('AF','AX','AL','DZ','AS','AD','AO','AI','AQ','AG','AR','AM','AW','AU','AT','AZ','BS','BH','BD','BB','BY','BE','BZ','BJ','BM','BT','BO','BQ','BA','BW','BV','BR','IO','BN','BG','BF','BI','CV','KH','CM','CA','KY','CF','TD','CL','CN','CX','CC','CO','KM','CG','CD','CK','CR','CI','HR','CU','CW','CY','CZ','DK','DJ','DM','DO','EC','EG','SV','GQ','ER','EE','SZ','ET','FK','FO','FJ','FI','FR','GF','PF','TF','GA','GM','GE','DE','GH','GI','GR','GL','GD','GP','GU','GT','GG','GN','GW','GY','HT','HM','VA','HN','HK','HU','IS','IN','ID','IR','IQ','IE','IM','IL','IT','JM','JP','JE','JO','KZ','KE','KI','KP','KR','KW','KG','LA','LV','LB','LS','LR','LY','LI','LT','LU','MO','MG','MW','MY','MV','ML','MT','MH','MQ','MR','MU','YT','MX','FM','MD','MC','MN','ME','MS','MA','MZ','MM','NA','NR','NP','NL','NC','NZ','NI','NE','NG','NU','NF','MK','MP','NO','OM','PK','PW','PS','PA','PG','PY','PE','PH','PN','PL','PT','PR','QA','RE','RO','RU','RW','BL','SH','KN','LC','MF','PM','VC','WS','SM','ST','SA','SN','RS','SC','SL','SG','SX','SK','SI','SB','SO','ZA','GS','SS','ES','LK','SD','SR','SJ','SE','CH','SY','TW','TJ','TZ','TH','TL','TG','TK','TO','TT','TN','TR','TM','TC','TV','UG','UA','AE','GB','US','UM','UY','UZ','VU','VE','VN','VG','VI','WF','EH','YE','ZM','ZW') THEN X.CHAVE_IT ELSE NULL END, '; ') AS DETALHE FROM (SELECT *, 0020_UNIQ_ID_GUARANTEE AS CHAVE_IT, 0030_governing_law AS CAMPO_IT FROM BU_LOANTAPE_WORK.OUT_B0500_GUARANTEES WHERE REF_DATE='"& RefDate &"')X GROUP BY 1
A159: v_2_0054 | B159: 0050_typ_guarantee | C159: 1 | D159: =+VLOOKUP(A159,Descrição!A:K,11,FALSE) -> Os valores dos dropdowns devem ser respeitados. | E159: "& RefDate &" | F159: REGULAMENTAR | G159: BU_LOANTAPE_WORK.OUT_B0500_GUARANTEES | H159: `0050_typ_guarantee` NOT IN ('Issuance', 'Counterparty', 'Unlimited', 'Other types of guarantee than issuance guarantees, counterparty guarantees and unlimited guarantees') | I159: =+IF(C159=1,0,1) -> 0 | J159: =+IF(C159=0,"THEN NULL ELSE X.CHAVE_IT END","THEN X.CHAVE_IT ELSE NULL END") -> THEN X.CHAVE_IT ELSE NULL END | K159: ="UNION ALL SELECT '"&E159&"' AS REF_DATE, '"&A159&"' AS COD_KPI, '"&F159&"' AS TIPOLOGIA_TESTE, '"&D159&"' AS DESCRIÇÃO, '"&G159&"' AS TABELA, '"&B159&"' AS CAMPO, COUNT(*) AS NUM_REG, SUM(IF("&H159&","&C159&" ,"&I159&")) AS NUM_REG_DIF, GROUP_CONCAT(CASE WHEN "&H159&" "&J159&", '; ') AS DETALHE FROM (SELECT *, 0020_UNIQ_ID_GUARANTEE AS CHAVE_IT, "&B159&" AS CAMPO_IT FROM "&G159&" WHERE REF_DATE='"&E159&"')X GROUP BY 1" -> UNION ALL SELECT '"& RefDate &"' AS REF_DATE, 'v_2_0054' AS COD_KPI, 'REGULAMENTAR' AS TIPOLOGIA_TESTE, 'Os valores dos dropdowns devem ser respeitados.' AS DESCRIÇÃO, 'BU_LOANTAPE_WORK.OUT_B0500_GUARANTEES' AS TABELA, '0050_typ_guarantee' AS CAMPO, COUNT(*) AS NUM_REG, SUM(IF(`0050_typ_guarantee` NOT IN ('Issuance', 'Counterparty', 'Unlimited', 'Other types of guarantee than issuance guarantees, counterparty guarantees and unlimited guarantees'),1 ,0)) AS NUM_REG_DIF, GROUP_CONCAT(CASE WHEN `0050_typ_guarantee` NOT IN ('Issuance', 'Counterparty', 'Unlimited', 'Other types of guarantee than issuance guarantees, counterparty guarantees and unlimited guarantees') THEN X.CHAVE_IT ELSE NULL END, '; ') AS DETALHE FROM (SELECT *, 0020_UNIQ_ID_GUARANTEE AS CHAVE_IT, 0050_typ_guarantee AS CAMPO_IT FROM BU_LOANTAPE_WORK.OUT_B0500_GUARANTEES WHERE REF_DATE='"& RefDate &"')X GROUP BY 1
A160: v_2_0055 | B160: 0060_max_amnt_guarantee | C160: 1 | D160: =+VLOOKUP(A160,Descrição!A:K,11,FALSE) -> O valor declarado deve ser positivo ou zero. | E160: "& RefDate &" | F160: REGULAMENTAR | G160: BU_LOANTAPE_WORK.OUT_B0500_GUARANTEES | H160: `0060_max_amnt_guarantee` < 0 | I160: =+IF(C160=1,0,1) -> 0 | J160: =+IF(C160=0,"THEN NULL ELSE X.CHAVE_IT END","THEN X.CHAVE_IT ELSE NULL END") -> THEN X.CHAVE_IT ELSE NULL END | K160: ="UNION ALL SELECT '"&E160&"' AS REF_DATE, '"&A160&"' AS COD_KPI, '"&F160&"' AS TIPOLOGIA_TESTE, '"&D160&"' AS DESCRIÇÃO, '"&G160&"' AS TABELA, '"&B160&"' AS CAMPO, COUNT(*) AS NUM_REG, SUM(IF("&H160&","&C160&" ,"&I160&")) AS NUM_REG_DIF, GROUP_CONCAT(CASE WHEN "&H160&" "&J160&", '; ') AS DETALHE FROM (SELECT *, 0020_UNIQ_ID_GUARANTEE AS CHAVE_IT, "&B160&" AS CAMPO_IT FROM "&G160&" WHERE REF_DATE='"&E160&"')X GROUP BY 1" -> UNION ALL SELECT '"& RefDate &"' AS REF_DATE, 'v_2_0055' AS COD_KPI, 'REGULAMENTAR' AS TIPOLOGIA_TESTE, 'O valor declarado deve ser positivo ou zero.' AS DESCRIÇÃO, 'BU_LOANTAPE_WORK.OUT_B0500_GUARANTEES' AS TABELA, '0060_max_amnt_guarantee' AS CAMPO, COUNT(*) AS NUM_REG, SUM(IF(`0060_max_amnt_guarantee` < 0,1 ,0)) AS NUM_REG_DIF, GROUP_CONCAT(CASE WHEN `0060_max_amnt_guarantee` < 0 THEN X.CHAVE_IT ELSE NULL END, '; ') AS DETALHE FROM (SELECT *, 0020_UNIQ_ID_GUARANTEE AS CHAVE_IT, 0060_max_amnt_guarantee AS CAMPO_IT FROM BU_LOANTAPE_WORK.OUT_B0500_GUARANTEES WHERE REF_DATE='"& RefDate &"')X GROUP BY 1
A161: v_2_0056 | B161: 0070_flg_scrd | C161: 0 | D161: =+VLOOKUP(A161,Descrição!A:K,11,FALSE) -> Os valores dos dropdowns devem ser respeitados. | E161: "& RefDate &" | F161: REGULAMENTAR | G161: BU_LOANTAPE_WORK.OUT_B0500_GUARANTEES | H161: `0070_flg_scrd` IN ('Issuance', 'Counterparty', 'Unlimited', 'Other types of guarantee than issuance guarantees, counterparty guarantees and unlimited guarantees') | I161: =+IF(C161=1,0,1) -> 1 | J161: =+IF(C161=0,"THEN NULL ELSE X.CHAVE_IT END","THEN X.CHAVE_IT ELSE NULL END") -> THEN NULL ELSE X.CHAVE_IT END | K161: ="UNION ALL SELECT '"&E161&"' AS REF_DATE, '"&A161&"' AS COD_KPI, '"&F161&"' AS TIPOLOGIA_TESTE, '"&D161&"' AS DESCRIÇÃO, '"&G161&"' AS TABELA, '"&B161&"' AS CAMPO, COUNT(*) AS NUM_REG, SUM(IF("&H161&","&C161&" ,"&I161&")) AS NUM_REG_DIF, GROUP_CONCAT(CASE WHEN "&H161&" "&J161&", '; ') AS DETALHE FROM (SELECT *, 0020_UNIQ_ID_GUARANTEE AS CHAVE_IT, "&B161&" AS CAMPO_IT FROM "&G161&" WHERE REF_DATE='"&E161&"')X GROUP BY 1" -> UNION ALL SELECT '"& RefDate &"' AS REF_DATE, 'v_2_0056' AS COD_KPI, 'REGULAMENTAR' AS TIPOLOGIA_TESTE, 'Os valores dos dropdowns devem ser respeitados.' AS DESCRIÇÃO, 'BU_LOANTAPE_WORK.OUT_B0500_GUARANTEES' AS TABELA, '0070_flg_scrd' AS CAMPO, COUNT(*) AS NUM_REG, SUM(IF(`0070_flg_scrd` IN ('Issuance', 'Counterparty', 'Unlimited', 'Other types of guarantee than issuance guarantees, counterparty guarantees and unlimited guarantees'),0 ,1)) AS NUM_REG_DIF, GROUP_CONCAT(CASE WHEN `0070_flg_scrd` IN ('Issuance', 'Counterparty', 'Unlimited', 'Other types of guarantee than issuance guarantees, counterparty guarantees and unlimited guarantees') THEN NULL ELSE X.CHAVE_IT END, '; ') AS DETALHE FROM (SELECT *, 0020_UNIQ_ID_GUARANTEE AS CHAVE_IT, 0070_flg_scrd AS CAMPO_IT FROM BU_LOANTAPE_WORK.OUT_B0500_GUARANTEES WHERE REF_DATE='"& RefDate &"')X GROUP BY 1
A162: v_2_0057 | B162: 0080_amnt_clltrl | C162: 1 | D162: =+VLOOKUP(A162,Descrição!A:K,11,FALSE) -> O valor declarado deve ser positivo ou zero. | E162: "& RefDate &" | F162: REGULAMENTAR | G162: BU_LOANTAPE_WORK.OUT_B0500_GUARANTEES | H162: `0080_amnt_clltrl` < 0 AND `0070_flg_scrd` = 'Secured' | I162: =+IF(C162=1,0,1) -> 0 | J162: =+IF(C162=0,"THEN NULL ELSE X.CHAVE_IT END","THEN X.CHAVE_IT ELSE NULL END") -> THEN X.CHAVE_IT ELSE NULL END | K162: ="UNION ALL SELECT '"&E162&"' AS REF_DATE, '"&A162&"' AS COD_KPI, '"&F162&"' AS TIPOLOGIA_TESTE, '"&D162&"' AS DESCRIÇÃO, '"&G162&"' AS TABELA, '"&B162&"' AS CAMPO, COUNT(*) AS NUM_REG, SUM(IF("&H162&","&C162&" ,"&I162&")) AS NUM_REG_DIF, GROUP_CONCAT(CASE WHEN "&H162&" "&J162&", '; ') AS DETALHE FROM (SELECT *, 0020_UNIQ_ID_GUARANTEE AS CHAVE_IT, "&B162&" AS CAMPO_IT FROM "&G162&" WHERE REF_DATE='"&E162&"')X GROUP BY 1" -> UNION ALL SELECT '"& RefDate &"' AS REF_DATE, 'v_2_0057' AS COD_KPI, 'REGULAMENTAR' AS TIPOLOGIA_TESTE, 'O valor declarado deve ser positivo ou zero.' AS DESCRIÇÃO, 'BU_LOANTAPE_WORK.OUT_B0500_GUARANTEES' AS TABELA, '0080_amnt_clltrl' AS CAMPO, COUNT(*) AS NUM_REG, SUM(IF(`0080_amnt_clltrl` < 0 AND `0070_flg_scrd` = 'Secured',1 ,0)) AS NUM_REG_DIF, GROUP_CONCAT(CASE WHEN `0080_amnt_clltrl` < 0 AND `0070_flg_scrd` = 'Secured' THEN X.CHAVE_IT ELSE NULL END, '; ') AS DETALHE FROM (SELECT *, 0020_UNIQ_ID_GUARANTEE AS CHAVE_IT, 0080_amnt_clltrl AS CAMPO_IT FROM BU_LOANTAPE_WORK.OUT_B0500_GUARANTEES WHERE REF_DATE='"& RefDate &"')X GROUP BY 1
A163: ="FRMT_"&MID(G163,22,5)&"_C"&LEFT(B163,4) -> FRMT_B0500_C0010 | B163: 0010_row_nmbr | C163: 1 | D163: O campo deve ser reportado com formato numérico inteiro. | E163: "& RefDate &" | F163: REGULAMENTAR | G163: BU_LOANTAPE_WORK.OUT_B0500_GUARANTEES | H163: CAST(`0010_row_nmbr` AS STRING) NOT RLIKE '^[0-9]+$' | I163: =+IF(C163=1,0,1) -> 0 | J163: =+IF(C163=0,"THEN NULL ELSE X.CHAVE_IT END","THEN X.CHAVE_IT ELSE NULL END") -> THEN X.CHAVE_IT ELSE NULL END | K163: ="UNION ALL SELECT '"&E163&"' AS REF_DATE, '"&A163&"' AS COD_KPI, '"&F163&"' AS TIPOLOGIA_TESTE, '"&D163&"' AS DESCRIÇÃO, '"&G163&"' AS TABELA, '"&B163&"' AS CAMPO, COUNT(*) AS NUM_REG, SUM(IF("&H163&","&C163&" ,"&I163&")) AS NUM_REG_DIF, GROUP_CONCAT(CASE WHEN "&H163&" "&J163&", '; ') AS DETALHE FROM (SELECT *, 0020_UNIQ_ID_GUARANTEE AS CHAVE_IT, "&B163&" AS CAMPO_IT FROM "&G163&" WHERE REF_DATE='"&E163&"')X GROUP BY 1" -> UNION ALL SELECT '"& RefDate &"' AS REF_DATE, 'FRMT_B0500_C0010' AS COD_KPI, 'REGULAMENTAR' AS TIPOLOGIA_TESTE, 'O campo deve ser reportado com formato numérico inteiro.' AS DESCRIÇÃO, 'BU_LOANTAPE_WORK.OUT_B0500_GUARANTEES' AS TABELA, '0010_row_nmbr' AS CAMPO, COUNT(*) AS NUM_REG, SUM(IF(CAST(`0010_row_nmbr` AS STRING) NOT RLIKE '^[0-9]+$',1 ,0)) AS NUM_REG_DIF, GROUP_CONCAT(CASE WHEN CAST(`0010_row_nmbr` AS STRING) NOT RLIKE '^[0-9]+$' THEN X.CHAVE_IT ELSE NULL END, '; ') AS DETALHE FROM (SELECT *, 0020_UNIQ_ID_GUARANTEE AS CHAVE_IT, 0010_row_nmbr AS CAMPO_IT FROM BU_LOANTAPE_WORK.OUT_B0500_GUARANTEES WHERE REF_DATE='"& RefDate &"')X GROUP BY 1
A164: ="FRMT_"&MID(G164,22,5)&"_C"&LEFT(B164,4) -> FRMT_B0500_C0020 | B164: 0020_uniq_id_guarantee | C164: 1 | D164: O campo deve ser reportado com formato texto livre. | E164: "& RefDate &" | F164: REGULAMENTAR | G164: BU_LOANTAPE_WORK.OUT_B0500_GUARANTEES | H164: `0020_uniq_id_guarantee` NOT RLIKE '[A-Za-z]' | I164: =+IF(C164=1,0,1) -> 0 | J164: =+IF(C164=0,"THEN NULL ELSE X.CHAVE_IT END","THEN X.CHAVE_IT ELSE NULL END") -> THEN X.CHAVE_IT ELSE NULL END | K164: ="UNION ALL SELECT '"&E164&"' AS REF_DATE, '"&A164&"' AS COD_KPI, '"&F164&"' AS TIPOLOGIA_TESTE, '"&D164&"' AS DESCRIÇÃO, '"&G164&"' AS TABELA, '"&B164&"' AS CAMPO, COUNT(*) AS NUM_REG, SUM(IF("&H164&","&C164&" ,"&I164&")) AS NUM_REG_DIF, GROUP_CONCAT(CASE WHEN "&H164&" "&J164&", '; ') AS DETALHE FROM (SELECT *, 0020_UNIQ_ID_GUARANTEE AS CHAVE_IT, "&B164&" AS CAMPO_IT FROM "&G164&" WHERE REF_DATE='"&E164&"')X GROUP BY 1" -> UNION ALL SELECT '"& RefDate &"' AS REF_DATE, 'FRMT_B0500_C0020' AS COD_KPI, 'REGULAMENTAR' AS TIPOLOGIA_TESTE, 'O campo deve ser reportado com formato texto livre.' AS DESCRIÇÃO, 'BU_LOANTAPE_WORK.OUT_B0500_GUARANTEES' AS TABELA, '0020_uniq_id_guarantee' AS CAMPO, COUNT(*) AS NUM_REG, SUM(IF(`0020_uniq_id_guarantee` NOT RLIKE '[A-Za-z]',1 ,0)) AS NUM_REG_DIF, GROUP_CONCAT(CASE WHEN `0020_uniq_id_guarantee` NOT RLIKE '[A-Za-z]' THEN X.CHAVE_IT ELSE NULL END, '; ') AS DETALHE FROM (SELECT *, 0020_UNIQ_ID_GUARANTEE AS CHAVE_IT, 0020_uniq_id_guarantee AS CAMPO_IT FROM BU_LOANTAPE_WORK.OUT_B0500_GUARANTEES WHERE REF_DATE='"& RefDate &"')X GROUP BY 1
A165: ="FRMT_"&MID(G165,22,5)&"_C"&LEFT(B165,4) -> FRMT_B0500_C0030 | B165: 0030_governing_law | C165: 1 | D165: O campo deve ser reportado usando o código ISO 3166-1 alpha-2. | E165: "& RefDate &" | F165: REGULAMENTAR | G165: BU_LOANTAPE_WORK.OUT_B0500_GUARANTEES | H165: LENGTH(`0030_governing_law`) != 2 | I165: =+IF(C165=1,0,1) -> 0 | J165: =+IF(C165=0,"THEN NULL ELSE X.CHAVE_IT END","THEN X.CHAVE_IT ELSE NULL END") -> THEN X.CHAVE_IT ELSE NULL END | K165: ="UNION ALL SELECT '"&E165&"' AS REF_DATE, '"&A165&"' AS COD_KPI, '"&F165&"' AS TIPOLOGIA_TESTE, '"&D165&"' AS DESCRIÇÃO, '"&G165&"' AS TABELA, '"&B165&"' AS CAMPO, COUNT(*) AS NUM_REG, SUM(IF("&H165&","&C165&" ,"&I165&")) AS NUM_REG_DIF, GROUP_CONCAT(CASE WHEN "&H165&" "&J165&", '; ') AS DETALHE FROM (SELECT *, 0020_UNIQ_ID_GUARANTEE AS CHAVE_IT, "&B165&" AS CAMPO_IT FROM "&G165&" WHERE REF_DATE='"&E165&"')X GROUP BY 1" -> UNION ALL SELECT '"& RefDate &"' AS REF_DATE, 'FRMT_B0500_C0030' AS COD_KPI, 'REGULAMENTAR' AS TIPOLOGIA_TESTE, 'O campo deve ser reportado usando o código ISO 3166-1 alpha-2.' AS DESCRIÇÃO, 'BU_LOANTAPE_WORK.OUT_B0500_GUARANTEES' AS TABELA, '0030_governing_law' AS CAMPO, COUNT(*) AS NUM_REG, SUM(IF(LENGTH(`0030_governing_law`) != 2,1 ,0)) AS NUM_REG_DIF, GROUP_CONCAT(CASE WHEN LENGTH(`0030_governing_law`) != 2 THEN X.CHAVE_IT ELSE NULL END, '; ') AS DETALHE FROM (SELECT *, 0020_UNIQ_ID_GUARANTEE AS CHAVE_IT, 0030_governing_law AS CAMPO_IT FROM BU_LOANTAPE_WORK.OUT_B0500_GUARANTEES WHERE REF_DATE='"& RefDate &"')X GROUP BY 1
A166: ="FRMT_"&MID(G166,22,5)&"_C"&LEFT(B166,4) -> FRMT_B0500_C0040 | B166: 0040_flg_art12g_3_srmr | C166: 1 | D166: O campo deve ser reportado usando TRUE ou FALSE. | E166: "& RefDate &" | F166: REGULAMENTAR | G166: BU_LOANTAPE_WORK.OUT_B0500_GUARANTEES | H166: `0040_flg_art12g_3_srmr` NOT IN ('TRUE', 'FALSE') | I166: =+IF(C166=1,0,1) -> 0 | J166: =+IF(C166=0,"THEN NULL ELSE X.CHAVE_IT END","THEN X.CHAVE_IT ELSE NULL END") -> THEN X.CHAVE_IT ELSE NULL END | K166: ="UNION ALL SELECT '"&E166&"' AS REF_DATE, '"&A166&"' AS COD_KPI, '"&F166&"' AS TIPOLOGIA_TESTE, '"&D166&"' AS DESCRIÇÃO, '"&G166&"' AS TABELA, '"&B166&"' AS CAMPO, COUNT(*) AS NUM_REG, SUM(IF("&H166&","&C166&" ,"&I166&")) AS NUM_REG_DIF, GROUP_CONCAT(CASE WHEN "&H166&" "&J166&", '; ') AS DETALHE FROM (SELECT *, 0020_UNIQ_ID_GUARANTEE AS CHAVE_IT, "&B166&" AS CAMPO_IT FROM "&G166&" WHERE REF_DATE='"&E166&"')X GROUP BY 1" -> UNION ALL SELECT '"& RefDate &"' AS REF_DATE, 'FRMT_B0500_C0040' AS COD_KPI, 'REGULAMENTAR' AS TIPOLOGIA_TESTE, 'O campo deve ser reportado usando TRUE ou FALSE.' AS DESCRIÇÃO, 'BU_LOANTAPE_WORK.OUT_B0500_GUARANTEES' AS TABELA, '0040_flg_art12g_3_srmr' AS CAMPO, COUNT(*) AS NUM_REG, SUM(IF(`0040_flg_art12g_3_srmr` NOT IN ('TRUE', 'FALSE'),1 ,0)) AS NUM_REG_DIF, GROUP_CONCAT(CASE WHEN `0040_flg_art12g_3_srmr` NOT IN ('TRUE', 'FALSE') THEN X.CHAVE_IT ELSE NULL END, '; ') AS DETALHE FROM (SELECT *, 0020_UNIQ_ID_GUARANTEE AS CHAVE_IT, 0040_flg_art12g_3_srmr AS CAMPO_IT FROM BU_LOANTAPE_WORK.OUT_B0500_GUARANTEES WHERE REF_DATE='"& RefDate &"')X GROUP BY 1
A167: ="FRMT_"&MID(G167,22,5)&"_C"&LEFT(B167,4) -> FRMT_B0500_C0050 | B167: 0050_typ_guarantee | C167: 1 | D167: Os valores dos dropdowns devem ser respeitados. | E167: "& RefDate &" | F167: REGULAMENTAR | G167: BU_LOANTAPE_WORK.OUT_B0500_GUARANTEES | H167: `0050_typ_guarantee` NOT IN ('Issuance', 'Counterparty', 'Unlimited', 'Other types of guarantee than issuance guarantees, counterparty guarantees and unlimited guarantees') | I167: =+IF(C167=1,0,1) -> 0 | J167: =+IF(C167=0,"THEN NULL ELSE X.CHAVE_IT END","THEN X.CHAVE_IT ELSE NULL END") -> THEN X.CHAVE_IT ELSE NULL END | K167: ="UNION ALL SELECT '"&E167&"' AS REF_DATE, '"&A167&"' AS COD_KPI, '"&F167&"' AS TIPOLOGIA_TESTE, '"&D167&"' AS DESCRIÇÃO, '"&G167&"' AS TABELA, '"&B167&"' AS CAMPO, COUNT(*) AS NUM_REG, SUM(IF("&H167&","&C167&" ,"&I167&")) AS NUM_REG_DIF, GROUP_CONCAT(CASE WHEN "&H167&" "&J167&", '; ') AS DETALHE FROM (SELECT *, 0020_UNIQ_ID_GUARANTEE AS CHAVE_IT, "&B167&" AS CAMPO_IT FROM "&G167&" WHERE REF_DATE='"&E167&"')X GROUP BY 1" -> UNION ALL SELECT '"& RefDate &"' AS REF_DATE, 'FRMT_B0500_C0050' AS COD_KPI, 'REGULAMENTAR' AS TIPOLOGIA_TESTE, 'Os valores dos dropdowns devem ser respeitados.' AS DESCRIÇÃO, 'BU_LOANTAPE_WORK.OUT_B0500_GUARANTEES' AS TABELA, '0050_typ_guarantee' AS CAMPO, COUNT(*) AS NUM_REG, SUM(IF(`0050_typ_guarantee` NOT IN ('Issuance', 'Counterparty', 'Unlimited', 'Other types of guarantee than issuance guarantees, counterparty guarantees and unlimited guarantees'),1 ,0)) AS NUM_REG_DIF, GROUP_CONCAT(CASE WHEN `0050_typ_guarantee` NOT IN ('Issuance', 'Counterparty', 'Unlimited', 'Other types of guarantee than issuance guarantees, counterparty guarantees and unlimited guarantees') THEN X.CHAVE_IT ELSE NULL END, '; ') AS DETALHE FROM (SELECT *, 0020_UNIQ_ID_GUARANTEE AS CHAVE_IT, 0050_typ_guarantee AS CAMPO_IT FROM BU_LOANTAPE_WORK.OUT_B0500_GUARANTEES WHERE REF_DATE='"& RefDate &"')X GROUP BY 1
A168: ="FRMT_"&MID(G168,22,5)&"_C"&LEFT(B168,4) -> FRMT_B0500_C0060 | B168: 0060_max_amnt_guarantee | C168: 1 | D168: O campo deve ser reportado com formato numérico com 2 casas decimais. | E168: "& RefDate &" | F168: REGULAMENTAR | G168: BU_LOANTAPE_WORK.OUT_B0500_GUARANTEES | H168: CAST(ROUND(`0060_max_amnt_guarantee`, 2) AS STRING) != CAST(`0060_max_amnt_guarantee` AS STRING) | I168: =+IF(C168=1,0,1) -> 0 | J168: =+IF(C168=0,"THEN NULL ELSE X.CHAVE_IT END","THEN X.CHAVE_IT ELSE NULL END") -> THEN X.CHAVE_IT ELSE NULL END | K168: ="UNION ALL SELECT '"&E168&"' AS REF_DATE, '"&A168&"' AS COD_KPI, '"&F168&"' AS TIPOLOGIA_TESTE, '"&D168&"' AS DESCRIÇÃO, '"&G168&"' AS TABELA, '"&B168&"' AS CAMPO, COUNT(*) AS NUM_REG, SUM(IF("&H168&","&C168&" ,"&I168&")) AS NUM_REG_DIF, GROUP_CONCAT(CASE WHEN "&H168&" "&J168&", '; ') AS DETALHE FROM (SELECT *, 0020_UNIQ_ID_GUARANTEE AS CHAVE_IT, "&B168&" AS CAMPO_IT FROM "&G168&" WHERE REF_DATE='"&E168&"')X GROUP BY 1" -> UNION ALL SELECT '"& RefDate &"' AS REF_DATE, 'FRMT_B0500_C0060' AS COD_KPI, 'REGULAMENTAR' AS TIPOLOGIA_TESTE, 'O campo deve ser reportado com formato numérico com 2 casas decimais.' AS DESCRIÇÃO, 'BU_LOANTAPE_WORK.OUT_B0500_GUARANTEES' AS TABELA, '0060_max_amnt_guarantee' AS CAMPO, COUNT(*) AS NUM_REG, SUM(IF( CAST(ROUND(`0060_max_amnt_guarantee`, 2) AS STRING) != CAST(`0060_max_amnt_guarantee` AS STRING),1 ,0)) AS NUM_REG_DIF, GROUP_CONCAT(CASE WHEN CAST(ROUND(`0060_max_amnt_guarantee`, 2) AS STRING) != CAST(`0060_max_amnt_guarantee` AS STRING) THEN X.CHAVE_IT ELSE NULL END, '; ') AS DETALHE FROM (SELECT *, 0020_UNIQ_ID_GUARANTEE AS CHAVE_IT, 0060_max_amnt_guarantee AS CAMPO_IT FROM BU_LOANTAPE_WORK.OUT_B0500_GUARANTEES WHERE REF_DATE='"& RefDate &"')X GROUP BY 1
A169: ="FRMT_"&MID(G169,22,5)&"_C"&LEFT(B169,4) -> FRMT_B0500_C0070 | B169: 0070_flg_scrd | C169: 1 | D169: Os valores dos dropdowns devem ser respeitados. | E169: "& RefDate &" | F169: REGULAMENTAR | G169: BU_LOANTAPE_WORK.OUT_B0500_GUARANTEES | H169: `0070_flg_scrd` NOT IN ('Secured', 'Unsecured') | I169: =+IF(C169=1,0,1) -> 0 | J169: =+IF(C169=0,"THEN NULL ELSE X.CHAVE_IT END","THEN X.CHAVE_IT ELSE NULL END") -> THEN X.CHAVE_IT ELSE NULL END | K169: ="UNION ALL SELECT '"&E169&"' AS REF_DATE, '"&A169&"' AS COD_KPI, '"&F169&"' AS TIPOLOGIA_TESTE, '"&D169&"' AS DESCRIÇÃO, '"&G169&"' AS TABELA, '"&B169&"' AS CAMPO, COUNT(*) AS NUM_REG, SUM(IF("&H169&","&C169&" ,"&I169&")) AS NUM_REG_DIF, GROUP_CONCAT(CASE WHEN "&H169&" "&J169&", '; ') AS DETALHE FROM (SELECT *, 0020_UNIQ_ID_GUARANTEE AS CHAVE_IT, "&B169&" AS CAMPO_IT FROM "&G169&" WHERE REF_DATE='"&E169&"')X GROUP BY 1" -> UNION ALL SELECT '"& RefDate &"' AS REF_DATE, 'FRMT_B0500_C0070' AS COD_KPI, 'REGULAMENTAR' AS TIPOLOGIA_TESTE, 'Os valores dos dropdowns devem ser respeitados.' AS DESCRIÇÃO, 'BU_LOANTAPE_WORK.OUT_B0500_GUARANTEES' AS TABELA, '0070_flg_scrd' AS CAMPO, COUNT(*) AS NUM_REG, SUM(IF(`0070_flg_scrd` NOT IN ('Secured', 'Unsecured'),1 ,0)) AS NUM_REG_DIF, GROUP_CONCAT(CASE WHEN `0070_flg_scrd` NOT IN ('Secured', 'Unsecured') THEN X.CHAVE_IT ELSE NULL END, '; ') AS DETALHE FROM (SELECT *, 0020_UNIQ_ID_GUARANTEE AS CHAVE_IT, 0070_flg_scrd AS CAMPO_IT FROM BU_LOANTAPE_WORK.OUT_B0500_GUARANTEES WHERE REF_DATE='"& RefDate &"')X GROUP BY 1
A170: ="FRMT_"&MID(G170,22,5)&"_C"&LEFT(B170,4) -> FRMT_B0500_C0080 | B170: 0080_amnt_clltrl | C170: 1 | D170: O campo deve ser reportado com formato numérico com 2 casas decimais. | E170: "& RefDate &" | F170: REGULAMENTAR | G170: BU_LOANTAPE_WORK.OUT_B0500_GUARANTEES | H170: CAST(ROUND(`0080_amnt_clltrl`, 2) AS STRING) != CAST(`0080_amnt_clltrl` AS STRING) | I170: =+IF(C170=1,0,1) -> 0 | J170: =+IF(C170=0,"THEN NULL ELSE X.CHAVE_IT END","THEN X.CHAVE_IT ELSE NULL END") -> THEN X.CHAVE_IT ELSE NULL END | K170: ="UNION ALL SELECT '"&E170&"' AS REF_DATE, '"&A170&"' AS COD_KPI, '"&F170&"' AS TIPOLOGIA_TESTE, '"&D170&"' AS DESCRIÇÃO, '"&G170&"' AS TABELA, '"&B170&"' AS CAMPO, COUNT(*) AS NUM_REG, SUM(IF("&H170&","&C170&" ,"&I170&")) AS NUM_REG_DIF, GROUP_CONCAT(CASE WHEN "&H170&" "&J170&", '; ') AS DETALHE FROM (SELECT *, 0020_UNIQ_ID_GUARANTEE AS CHAVE_IT, "&B170&" AS CAMPO_IT FROM "&G170&" WHERE REF_DATE='"&E170&"')X GROUP BY 1" -> UNION ALL SELECT '"& RefDate &"' AS REF_DATE, 'FRMT_B0500_C0080' AS COD_KPI, 'REGULAMENTAR' AS TIPOLOGIA_TESTE, 'O campo deve ser reportado com formato numérico com 2 casas decimais.' AS DESCRIÇÃO, 'BU_LOANTAPE_WORK.OUT_B0500_GUARANTEES' AS TABELA, '0080_amnt_clltrl' AS CAMPO, COUNT(*) AS NUM_REG, SUM(IF(CAST(ROUND(`0080_amnt_clltrl`, 2) AS STRING) != CAST(`0080_amnt_clltrl` AS STRING),1 ,0)) AS NUM_REG_DIF, GROUP_CONCAT(CASE WHEN CAST(ROUND(`0080_amnt_clltrl`, 2) AS STRING) != CAST(`0080_amnt_clltrl` AS STRING) THEN X.CHAVE_IT ELSE NULL END, '; ') AS DETALHE FROM (SELECT *, 0020_UNIQ_ID_GUARANTEE AS CHAVE_IT, 0080_amnt_clltrl AS CAMPO_IT FROM BU_LOANTAPE_WORK.OUT_B0500_GUARANTEES WHERE REF_DATE='"& RefDate &"')X GROUP BY 1
A171: ="FRMT_"&MID(G171,22,5)&"_C"&LEFT(B171,4) -> FRMT_B0500_C0090 | B171: 0090_guarantee_trggr | C171: 1 | D171: O campo deve ser reportado usando o valor fixo Default. | E171: "& RefDate &" | F171: REGULAMENTAR | G171: BU_LOANTAPE_WORK.OUT_B0500_GUARANTEES | H171: `0090_guarantee_trggr` != 'Default' | I171: =+IF(C171=1,0,1) -> 0 | J171: =+IF(C171=0,"THEN NULL ELSE X.CHAVE_IT END","THEN X.CHAVE_IT ELSE NULL END") -> THEN X.CHAVE_IT ELSE NULL END | K171: ="UNION ALL SELECT '"&E171&"' AS REF_DATE, '"&A171&"' AS COD_KPI, '"&F171&"' AS TIPOLOGIA_TESTE, '"&D171&"' AS DESCRIÇÃO, '"&G171&"' AS TABELA, '"&B171&"' AS CAMPO, COUNT(*) AS NUM_REG, SUM(IF("&H171&","&C171&" ,"&I171&")) AS NUM_REG_DIF, GROUP_CONCAT(CASE WHEN "&H171&" "&J171&", '; ') AS DETALHE FROM (SELECT *, 0020_UNIQ_ID_GUARANTEE AS CHAVE_IT, "&B171&" AS CAMPO_IT FROM "&G171&" WHERE REF_DATE='"&E171&"')X GROUP BY 1" -> UNION ALL SELECT '"& RefDate &"' AS REF_DATE, 'FRMT_B0500_C0090' AS COD_KPI, 'REGULAMENTAR' AS TIPOLOGIA_TESTE, 'O campo deve ser reportado usando o valor fixo Default.' AS DESCRIÇÃO, 'BU_LOANTAPE_WORK.OUT_B0500_GUARANTEES' AS TABELA, '0090_guarantee_trggr' AS CAMPO, COUNT(*) AS NUM_REG, SUM(IF(`0090_guarantee_trggr` != 'Default',1 ,0)) AS NUM_REG_DIF, GROUP_CONCAT(CASE WHEN `0090_guarantee_trggr` != 'Default' THEN X.CHAVE_IT ELSE NULL END, '; ') AS DETALHE FROM (SELECT *, 0020_UNIQ_ID_GUARANTEE AS CHAVE_IT, 0090_guarantee_trggr AS CAMPO_IT FROM BU_LOANTAPE_WORK.OUT_B0500_GUARANTEES WHERE REF_DATE='"& RefDate &"')X GROUP BY 1
A172: ="FRMT_"&MID(G172,22,5)&"_C"&LEFT(B172,4) -> FRMT_B0500_C0100 | B172: 0100_dt_mtrty_clltrl | C172: 1 | D172: O campo deve ser reportado com formato yyyy-mm-dd. | E172: "& RefDate &" | F172: REGULAMENTAR | G172: BU_LOANTAPE_WORK.OUT_B0500_GUARANTEES | H172: `0100_dt_mtrty_clltrl` NOT REGEXP '^[0-9]{4}-[0-9]{2}-[0-9]{2}$' | I172: =+IF(C172=1,0,1) -> 0 | J172: =+IF(C172=0,"THEN NULL ELSE X.CHAVE_IT END","THEN X.CHAVE_IT ELSE NULL END") -> THEN X.CHAVE_IT ELSE NULL END | K172: ="UNION ALL SELECT '"&E172&"' AS REF_DATE, '"&A172&"' AS COD_KPI, '"&F172&"' AS TIPOLOGIA_TESTE, '"&D172&"' AS DESCRIÇÃO, '"&G172&"' AS TABELA, '"&B172&"' AS CAMPO, COUNT(*) AS NUM_REG, SUM(IF("&H172&","&C172&" ,"&I172&")) AS NUM_REG_DIF, GROUP_CONCAT(CASE WHEN "&H172&" "&J172&", '; ') AS DETALHE FROM (SELECT *, 0020_UNIQ_ID_GUARANTEE AS CHAVE_IT, "&B172&" AS CAMPO_IT FROM "&G172&" WHERE REF_DATE='"&E172&"')X GROUP BY 1" -> UNION ALL SELECT '"& RefDate &"' AS REF_DATE, 'FRMT_B0500_C0100' AS COD_KPI, 'REGULAMENTAR' AS TIPOLOGIA_TESTE, 'O campo deve ser reportado com formato yyyy-mm-dd.' AS DESCRIÇÃO, 'BU_LOANTAPE_WORK.OUT_B0500_GUARANTEES' AS TABELA, '0100_dt_mtrty_clltrl' AS CAMPO, COUNT(*) AS NUM_REG, SUM(IF(`0100_dt_mtrty_clltrl` NOT REGEXP '^[0-9]{4}-[0-9]{2}-[0-9]{2}$' ,1 ,0)) AS NUM_REG_DIF, GROUP_CONCAT(CASE WHEN `0100_dt_mtrty_clltrl` NOT REGEXP '^[0-9]{4}-[0-9]{2}-[0-9]{2}$' THEN X.CHAVE_IT ELSE NULL END, '; ') AS DETALHE FROM (SELECT *, 0020_UNIQ_ID_GUARANTEE AS CHAVE_IT, 0100_dt_mtrty_clltrl AS CAMPO_IT FROM BU_LOANTAPE_WORK.OUT_B0500_GUARANTEES WHERE REF_DATE='"& RefDate &"')X GROUP BY 1
A173: ="FRMT_"&MID(G173,22,5)&"_C"&LEFT(B173,4) -> FRMT_B0500_C0110 | B173: 0110_scrts_clltrl_id | C173: 1 | D173: O campo deve ser reportado com formato texto livre. | E173: "& RefDate &" | F173: REGULAMENTAR | G173: BU_LOANTAPE_WORK.OUT_B0500_GUARANTEES | H173: `0110_scrts_clltrl_id` NOT RLIKE '[A-Za-z]' | I173: =+IF(C173=1,0,1) -> 0 | J173: =+IF(C173=0,"THEN NULL ELSE X.CHAVE_IT END","THEN X.CHAVE_IT ELSE NULL END") -> THEN X.CHAVE_IT ELSE NULL END | K173: ="UNION ALL SELECT '"&E173&"' AS REF_DATE, '"&A173&"' AS COD_KPI, '"&F173&"' AS TIPOLOGIA_TESTE, '"&D173&"' AS DESCRIÇÃO, '"&G173&"' AS TABELA, '"&B173&"' AS CAMPO, COUNT(*) AS NUM_REG, SUM(IF("&H173&","&C173&" ,"&I173&")) AS NUM_REG_DIF, GROUP_CONCAT(CASE WHEN "&H173&" "&J173&", '; ') AS DETALHE FROM (SELECT *, 0020_UNIQ_ID_GUARANTEE AS CHAVE_IT, "&B173&" AS CAMPO_IT FROM "&G173&" WHERE REF_DATE='"&E173&"')X GROUP BY 1" -> UNION ALL SELECT '"& RefDate &"' AS REF_DATE, 'FRMT_B0500_C0110' AS COD_KPI, 'REGULAMENTAR' AS TIPOLOGIA_TESTE, 'O campo deve ser reportado com formato texto livre.' AS DESCRIÇÃO, 'BU_LOANTAPE_WORK.OUT_B0500_GUARANTEES' AS TABELA, '0110_scrts_clltrl_id' AS CAMPO, COUNT(*) AS NUM_REG, SUM(IF(`0110_scrts_clltrl_id` NOT RLIKE '[A-Za-z]',1 ,0)) AS NUM_REG_DIF, GROUP_CONCAT(CASE WHEN `0110_scrts_clltrl_id` NOT RLIKE '[A-Za-z]' THEN X.CHAVE_IT ELSE NULL END, '; ') AS DETALHE FROM (SELECT *, 0020_UNIQ_ID_GUARANTEE AS CHAVE_IT, 0110_scrts_clltrl_id AS CAMPO_IT FROM BU_LOANTAPE_WORK.OUT_B0500_GUARANTEES WHERE REF_DATE='"& RefDate &"')X GROUP BY 1
A174: ="FRMT_"&MID(G174,22,5)&"_C"&LEFT(B174,4) -> FRMT_B0500_C0120 | B174: 0120_typ_clltrlztn | C174: 1 | D174: O campo deve ser reportado com formato texto livre. | E174: "& RefDate &" | F174: REGULAMENTAR | G174: BU_LOANTAPE_WORK.OUT_B0500_GUARANTEES | H174: `0120_typ_clltrlztn` NOT RLIKE '[A-Za-z]' | I174: =+IF(C174=1,0,1) -> 0 | J174: =+IF(C174=0,"THEN NULL ELSE X.CHAVE_IT END","THEN X.CHAVE_IT ELSE NULL END") -> THEN X.CHAVE_IT ELSE NULL END | K174: ="UNION ALL SELECT '"&E174&"' AS REF_DATE, '"&A174&"' AS COD_KPI, '"&F174&"' AS TIPOLOGIA_TESTE, '"&D174&"' AS DESCRIÇÃO, '"&G174&"' AS TABELA, '"&B174&"' AS CAMPO, COUNT(*) AS NUM_REG, SUM(IF("&H174&","&C174&" ,"&I174&")) AS NUM_REG_DIF, GROUP_CONCAT(CASE WHEN "&H174&" "&J174&", '; ') AS DETALHE FROM (SELECT *, 0020_UNIQ_ID_GUARANTEE AS CHAVE_IT, "&B174&" AS CAMPO_IT FROM "&G174&" WHERE REF_DATE='"&E174&"')X GROUP BY 1" -> UNION ALL SELECT '"& RefDate &"' AS REF_DATE, 'FRMT_B0500_C0120' AS COD_KPI, 'REGULAMENTAR' AS TIPOLOGIA_TESTE, 'O campo deve ser reportado com formato texto livre.' AS DESCRIÇÃO, 'BU_LOANTAPE_WORK.OUT_B0500_GUARANTEES' AS TABELA, '0120_typ_clltrlztn' AS CAMPO, COUNT(*) AS NUM_REG, SUM(IF(`0120_typ_clltrlztn` NOT RLIKE '[A-Za-z]',1 ,0)) AS NUM_REG_DIF, GROUP_CONCAT(CASE WHEN `0120_typ_clltrlztn` NOT RLIKE '[A-Za-z]' THEN X.CHAVE_IT ELSE NULL END, '; ') AS DETALHE FROM (SELECT *, 0020_UNIQ_ID_GUARANTEE AS CHAVE_IT, 0120_typ_clltrlztn AS CAMPO_IT FROM BU_LOANTAPE_WORK.OUT_B0500_GUARANTEES WHERE REF_DATE='"& RefDate &"')X GROUP BY 1
