Workbook

Sheet Level 1
A1: v_1_0001 | B1: MBDT - Level 1 Validation Rules: completeness checks. | U1: utilizar union all's (HF) | V1: utilizar case when's
B2: Check ID | C2: Tab | D2: Data point (Row/Column) | E2: Data point (Label) | F2: Data point type | G2: High severity (i.e the validation rule should in general not be breached) | H2: Warning only (i.e. the validation rule can be breached in certain cases) | I2: Type of test (missing values means "not applicable" or "not available") | J2: Prerequisite / Dependency | K2: Explanation | L2: AUX_ALERT | M2: AUX_TAB | N2: AUX_FIELD1 | O2: FIELD2 | P2: AUX_FIELD2 | Q2: FIELD3 | R2: AUX_FIELD3 | S2: FIELD4 | T2: AUX_FIELD4 | U2: OPTION 1 | V2: OPTION 2
A3: 0001 | B3: =CONCATENATE("v_1_",A3) -> v_1_0001 | C3: B02.00 | D3: =VLOOKUP(CONCATENATE(C3,"_",E3),'Data types'!A:E,4,FALSE) -> 0010 | E3: Row number | F3: =VLOOKUP(CONCATENATE(C3,"_",E3),'Data types'!A:F,6,FALSE) -> Numeric: Integer | G3: X | I3: Test for missing values. | K3: Missing value. The field must be reported. | L3: =+IF(G3="X","HIGH","WARNING") -> HIGH | M3: =+LEFT(C3,3) -> B02 | N3: ="`"&VLOOKUP(D3,'B02_Mapping fields'!B:C,2,FALSE)&"`" -> `0010_row_nmbr` | U3: =+",SELECT '"&M3&"' AS TAB, '"&L3&"' AS ALERT_TYPE, '"&B3&"' AS CHECK_ID, ROW_NUMBER, CASE WHEN A.ISSUES >0 THEN 1 ELSE 0 END AS "&B3&" FROM (SELECT COUNT(*) AS ISSUES FROM "&M3&" WHERE "&M3&"."&D3&" IS MISSING) AS A;" -> ,SELECT 'B02' AS TAB, 'HIGH' AS ALERT_TYPE, 'v_1_0001' AS CHECK_ID, ROW_NUMBER, CASE WHEN A.ISSUES >0 THEN 1 ELSE 0 END AS v_1_0001 FROM (SELECT COUNT(*) AS ISSUES FROM B02 WHERE B02.0010 IS MISSING) AS A; | V3: =+",CASE WHEN "&N3&" IS MISSING THEN 1 ELSE 0 END AS "&B3 -> ,CASE WHEN `0010_row_nmbr` IS MISSING THEN 1 ELSE 0 END AS v_1_0001 | W3: =+"SUM("&B3&") AS LVL1_H_"&MID(N3,2,LEN(N3)-2)&"," -> SUM(v_1_0001) AS LVL1_H_0010_row_nmbr,
A4: 0002 | B4: =CONCATENATE("v_1_",A4) -> v_1_0002 | C4: B02.00 | D4: =VLOOKUP(CONCATENATE(C4,"_",E4),'Data types'!A:E,4,FALSE) -> 0030 | E4: Unique identification number (known to the counterparty) | F4: =VLOOKUP(CONCATENATE(C4,"_",E4),'Data types'!A:F,6,FALSE) -> String: Free text | G4: X | I4: Test for missing values. | K4: Missing value. The field must be reported. | L4: =+IF(G4="X","HIGH","WARNING") -> HIGH | M4: =+LEFT(C4,3) -> B02 | N4: ="`"&VLOOKUP(D4,'B02_Mapping fields'!B:C,2,FALSE)&"`" -> `0030_uniq_id_knwn_cntrprty` | U4: =+",SELECT '"&M4&"' AS TAB, '"&L4&"' AS ALERT_TYPE, '"&B4&"' AS CHECK_ID, ROW_NUMBER, CASE WHEN A.ISSUES >0 THEN 1 ELSE 0 END AS "&B4&" FROM (SELECT COUNT(*) AS ISSUES FROM "&M4&" WHERE "&M4&"."&D4&" IS MISSING) AS A;" -> ,SELECT 'B02' AS TAB, 'HIGH' AS ALERT_TYPE, 'v_1_0002' AS CHECK_ID, ROW_NUMBER, CASE WHEN A.ISSUES >0 THEN 1 ELSE 0 END AS v_1_0002 FROM (SELECT COUNT(*) AS ISSUES FROM B02 WHERE B02.0030 IS MISSING) AS A; | V4: =+",CASE WHEN "&N4&" IS MISSING THEN 1 ELSE 0 END AS "&B4 -> ,CASE WHEN `0030_uniq_id_knwn_cntrprty` IS MISSING THEN 1 ELSE 0 END AS v_1_0002 | W4: =+"SUM("&B4&") AS LVL1_H_"&MID(N4,2,LEN(N4)-2)&"," -> SUM(v_1_0002) AS LVL1_H_0030_uniq_id_knwn_cntrprty,
A5: 0003 | B5: =CONCATENATE("v_1_",A5) -> v_1_0003 | C5: B02.00 | D5: =VLOOKUP(CONCATENATE(C5,"_",E5),'Data types'!A:E,4,FALSE) -> 0040 | E5: Type of the unique identifier (known to the counterparty) | F5: =VLOOKUP(CONCATENATE(C5,"_",E5),'Data types'!A:F,6,FALSE) -> String: Free text, but fixed values for specific items | G5: X | I5: Test for missing values. | K5: Missing value. The field must be reported. | L5: =+IF(G5="X","HIGH","WARNING") -> HIGH | M5: =+LEFT(C5,3) -> B02 | N5: ="`"&VLOOKUP(D5,'B02_Mapping fields'!B:C,2,FALSE)&"`" -> `0040_typ_uniq_id_knwn_cntrprty` | U5: =+",SELECT '"&M5&"' AS TAB, '"&L5&"' AS ALERT_TYPE, '"&B5&"' AS CHECK_ID, ROW_NUMBER, CASE WHEN A.ISSUES >0 THEN 1 ELSE 0 END AS "&B5&" FROM (SELECT COUNT(*) AS ISSUES FROM "&M5&" WHERE "&M5&"."&D5&" IS MISSING) AS A;" -> ,SELECT 'B02' AS TAB, 'HIGH' AS ALERT_TYPE, 'v_1_0003' AS CHECK_ID, ROW_NUMBER, CASE WHEN A.ISSUES >0 THEN 1 ELSE 0 END AS v_1_0003 FROM (SELECT COUNT(*) AS ISSUES FROM B02 WHERE B02.0040 IS MISSING) AS A; | V5: =+",CASE WHEN "&N5&" IS MISSING THEN 1 ELSE 0 END AS "&B5 -> ,CASE WHEN `0040_typ_uniq_id_knwn_cntrprty` IS MISSING THEN 1 ELSE 0 END AS v_1_0003 | W5: =+"SUM("&B5&") AS LVL1_H_"&MID(N5,2,LEN(N5)-2)&"," -> SUM(v_1_0003) AS LVL1_H_0040_typ_uniq_id_knwn_cntrprty,
A6: 0004 | B6: =CONCATENATE("v_1_",A6) -> v_1_0004 | C6: B02.00 | D6: =VLOOKUP(CONCATENATE(C6,"_",E6),'Data types'!A:E,4,FALSE) -> 0070 | E6: Contract Currency | F6: =VLOOKUP(CONCATENATE(C6,"_",E6),'Data types'!A:F,6,FALSE) -> String: 3-letters ISO 4217 | G6: X | I6: Test for missing values. | K6: Missing value. The field must be reported. | L6: =+IF(G6="X","HIGH","WARNING") -> HIGH | M6: =+LEFT(C6,3) -> B02 | N6: ="`"&VLOOKUP(D6,'B02_Mapping fields'!B:C,2,FALSE)&"`" -> `0070_cntrct_crrncy` | U6: =+",SELECT '"&M6&"' AS TAB, '"&L6&"' AS ALERT_TYPE, '"&B6&"' AS CHECK_ID, ROW_NUMBER, CASE WHEN A.ISSUES >0 THEN 1 ELSE 0 END AS "&B6&" FROM (SELECT COUNT(*) AS ISSUES FROM "&M6&" WHERE "&M6&"."&D6&" IS MISSING) AS A;" -> ,SELECT 'B02' AS TAB, 'HIGH' AS ALERT_TYPE, 'v_1_0004' AS CHECK_ID, ROW_NUMBER, CASE WHEN A.ISSUES >0 THEN 1 ELSE 0 END AS v_1_0004 FROM (SELECT COUNT(*) AS ISSUES FROM B02 WHERE B02.0070 IS MISSING) AS A; | V6: =+",CASE WHEN "&N6&" IS MISSING THEN 1 ELSE 0 END AS "&B6 -> ,CASE WHEN `0070_cntrct_crrncy` IS MISSING THEN 1 ELSE 0 END AS v_1_0004 | W6: =+"SUM("&B6&") AS LVL1_H_"&MID(N6,2,LEN(N6)-2)&"," -> SUM(v_1_0004) AS LVL1_H_0070_cntrct_crrncy,
A7: 0005 | B7: =CONCATENATE("v_1_",A7) -> v_1_0005 | C7: B02.00 | D7: =VLOOKUP(CONCATENATE(C7,"_",E7),'Data types'!A:E,4,FALSE) -> 0080 | E7: Outstanding principal amount | F7: =VLOOKUP(CONCATENATE(C7,"_",E7),'Data types'!A:F,6,FALSE) -> Numeric: 2 decimals | G7: X | I7: Test for missing values. | J7: Rule applicable if c0250 = ("Non-Structured/Vanilla" OR "Other non-standard terms") | K7: Missing value. The field must be reported for non-structured liabilities. | L7: =+IF(G7="X","HIGH","WARNING") -> HIGH | M7: =+LEFT(C7,3) -> B02 | N7: ="`"&VLOOKUP(D7,'B02_Mapping fields'!B:C,2,FALSE)&"`" -> `0080_otstndng_prncpl_amnt` | O7: 0250 | P7: ="`"&VLOOKUP(O7,'B02_Mapping fields'!B:C,2,FALSE)&"`" -> `0250_strctrd_prdct` | U7: =+",SELECT '"&M7&"' AS TAB, '"&L7&"' AS ALERT_TYPE, '"&B7&"' AS CHECK_ID, ROW_NUMBER, CASE WHEN A.ISSUES >0 THEN 1 ELSE 0 END AS "&B7&" FROM (SELECT COUNT(*) AS ISSUES FROM "&M7&" WHERE "&M7&"."&D7&" IS MISSING AND c0250 IN ('Non-Structured/Vanilla', 'Other non-standard terms')) AS A;" -> ,SELECT 'B02' AS TAB, 'HIGH' AS ALERT_TYPE, 'v_1_0005' AS CHECK_ID, ROW_NUMBER, CASE WHEN A.ISSUES >0 THEN 1 ELSE 0 END AS v_1_0005 FROM (SELECT COUNT(*) AS ISSUES FROM B02 WHERE B02.0080 IS MISSING AND c0250 IN ('Non-Structured/Vanilla', 'Other non-standard terms')) AS A; | V7: =+",CASE WHEN "&N7&" IS MISSING AND "&P7&" IN ('Non-Structured/Vanilla', 'Other non-standard terms') THEN 1 ELSE 0 END AS "&B7 -> ,CASE WHEN `0080_otstndng_prncpl_amnt` IS MISSING AND `0250_strctrd_prdct` IN ('Non-Structured/Vanilla', 'Other non-standard terms') THEN 1 ELSE 0 END AS v_1_0005 | W7: =+"SUM("&B7&") AS LVL1_H_"&MID(N7,2,LEN(N7)-2)&"," -> SUM(v_1_0005) AS LVL1_H_0080_otstndng_prncpl_amnt,
A8: 0006 | B8: =CONCATENATE("v_1_",A8) -> v_1_0006 | C8: B02.00 | D8: =VLOOKUP(CONCATENATE(C8,"_",E8),'Data types'!A:E,4,FALSE) -> 0080 | E8: Outstanding principal amount | F8: =VLOOKUP(CONCATENATE(C8,"_",E8),'Data types'!A:F,6,FALSE) -> Numeric: 2 decimals | H8: X | I8: Test for missing values. | J8: Rule applicable if c0250 = ("Structured" OR "Only structured coupon") | K8: Missing value (warning only). For structured liabilities, the field has to be reported if the information exists. | L8: =+IF(G8="X","HIGH","WARNING") -> WARNING | M8: =+LEFT(C8,3) -> B02 | N8: ="`"&VLOOKUP(D8,'B02_Mapping fields'!B:C,2,FALSE)&"`" -> `0080_otstndng_prncpl_amnt` | O8: 0250 | P8: ="`"&VLOOKUP(O8,'B02_Mapping fields'!B:C,2,FALSE)&"`" -> `0250_strctrd_prdct` | U8: =+",SELECT '"&M8&"' AS TAB, '"&L8&"' AS ALERT_TYPE, '"&B8&"' AS CHECK_ID, ROW_NUMBER, CASE WHEN A.ISSUES >0 THEN 1 ELSE 0 END AS "&B8&" FROM (SELECT COUNT(*) AS ISSUES FROM "&M8&" WHERE "&M8&"."&D8&" IS MISSING AND c0250 IN ('Structured', 'Only structured coupon')) AS A;" -> ,SELECT 'B02' AS TAB, 'WARNING' AS ALERT_TYPE, 'v_1_0006' AS CHECK_ID, ROW_NUMBER, CASE WHEN A.ISSUES >0 THEN 1 ELSE 0 END AS v_1_0006 FROM (SELECT COUNT(*) AS ISSUES FROM B02 WHERE B02.0080 IS MISSING AND c0250 IN ('Structured', 'Only structured coupon')) AS A; | V8: =+",CASE WHEN "&N8&" IS MISSING AND "&P8&" IN ('Structured', 'Only structured coupon') THEN 1 ELSE 0 END AS "&B8 -> ,CASE WHEN `0080_otstndng_prncpl_amnt` IS MISSING AND `0250_strctrd_prdct` IN ('Structured', 'Only structured coupon') THEN 1 ELSE 0 END AS v_1_0006 | W8: =+"SUM("&B8&") AS LVL1_W_"&MID(N8,2,LEN(N8)-2)&"," -> SUM(v_1_0006) AS LVL1_W_0080_otstndng_prncpl_amnt,
A9: 0007 | B9: =CONCATENATE("v_1_",A9) -> v_1_0007 | C9: B02.00 | D9: =VLOOKUP(CONCATENATE(C9,"_",E9),'Data types'!A:E,4,FALSE) -> 0090 | E9: Portion of instrument or liability held by the reporting entity | F9: =VLOOKUP(CONCATENATE(C9,"_",E9),'Data types'!A:F,6,FALSE) -> Numeric: 2 decimals | G9: X | I9: Test for missing values. | J9: Rule applicable only if c0040 = "ISIN" | K9: Missing value. The field must be reported for securities. | L9: =+IF(G9="X","HIGH","WARNING") -> HIGH | M9: =+LEFT(C9,3) -> B02 | N9: ="`"&VLOOKUP(D9,'B02_Mapping fields'!B:C,2,FALSE)&"`" -> `0090_prtn_amnt_rprtng_entty` | O9: 0040 | P9: ="`"&VLOOKUP(O9,'B02_Mapping fields'!B:C,2,FALSE)&"`" -> `0040_typ_uniq_id_knwn_cntrprty` | U9: =+",SELECT '"&M9&"' AS TAB, '"&L9&"' AS ALERT_TYPE, '"&B9&"' AS CHECK_ID, ROW_NUMBER, CASE WHEN A.ISSUES >0 THEN 1 ELSE 0 END AS "&B9&" FROM (SELECT COUNT(*) AS ISSUES FROM "&M9&" WHERE "&M9&"."&D9&" IS MISSING AND c0040 = 'ISIN') AS A;" -> ,SELECT 'B02' AS TAB, 'HIGH' AS ALERT_TYPE, 'v_1_0007' AS CHECK_ID, ROW_NUMBER, CASE WHEN A.ISSUES >0 THEN 1 ELSE 0 END AS v_1_0007 FROM (SELECT COUNT(*) AS ISSUES FROM B02 WHERE B02.0090 IS MISSING AND c0040 = 'ISIN') AS A; | V9: =+",CASE WHEN "&N9&" IS MISSING AND "&P9&" = 'ISIN' THEN 1 ELSE 0 END AS "&B9 -> ,CASE WHEN `0090_prtn_amnt_rprtng_entty` IS MISSING AND `0040_typ_uniq_id_knwn_cntrprty` = 'ISIN' THEN 1 ELSE 0 END AS v_1_0007 | W9: =+"SUM("&B9&") AS LVL1_H_"&MID(N9,2,LEN(N9)-2)&"," -> SUM(v_1_0007) AS LVL1_H_0090_prtn_amnt_rprtng_entty,
A10: 0008 | B10: =CONCATENATE("v_1_",A10) -> v_1_0008 | C10: B02.00 | D10: =VLOOKUP(CONCATENATE(C10,"_",E10),'Data types'!A:E,4,FALSE) -> 0100 | E10: Accrued interest | F10: =VLOOKUP(CONCATENATE(C10,"_",E10),'Data types'!A:F,6,FALSE) -> Numeric: 2 decimals | G10: X | I10: Test for missing values. | J10: Rule applicable if c0250 = ("Non-Structured" OR "Other non-standard terms") AND c0240 != "ZCB issued at discount" | K10: Missing value. For non-structured liabilities that are not zero coupon bonds issued at discount, this field must be reported. | L10: =+IF(G10="X","HIGH","WARNING") -> HIGH | M10: =+LEFT(C10,3) -> B02 | N10: ="`"&VLOOKUP(D10,'B02_Mapping fields'!B:C,2,FALSE)&"`" -> `0100_accrd_intrst_instrmnt` | O10: 0250 | P10: ="`"&VLOOKUP(O10,'B02_Mapping fields'!B:C,2,FALSE)&"`" -> `0250_strctrd_prdct` | Q10: 0240 | R10: ="`"&VLOOKUP(Q10,'B02_Mapping fields'!B:C,2,FALSE)&"`" -> `0240_zero_coupon` | U10: =+",SELECT '"&M10&"' AS TAB, '"&L10&"' AS ALERT_TYPE, '"&B10&"' AS CHECK_ID, ROW_NUMBER, CASE WHEN A.ISSUES >0 THEN 1 ELSE 0 END AS "&B10&" FROM (SELECT COUNT(*) AS ISSUES FROM "&M10&" WHERE "&M10&"."&D10&" IS MISSING AND c0250 IN ('Non-Structured', 'Other non-standard terms') AND c0240 != 'ZCB issued at discount') AS A;" -> ,SELECT 'B02' AS TAB, 'HIGH' AS ALERT_TYPE, 'v_1_0008' AS CHECK_ID, ROW_NUMBER, CASE WHEN A.ISSUES >0 THEN 1 ELSE 0 END AS v_1_0008 FROM (SELECT COUNT(*) AS ISSUES FROM B02 WHERE B02.0100 IS MISSING AND c0250 IN ('Non-Structured', 'Other non-standard terms') AND c0240 != 'ZCB issued at discount') AS A; | V10: =+",CASE WHEN "&N10&" IS MISSING AND "&P10&" IN ('Non-Structured', 'Other non-standard terms') AND "&R10&" != 'ZCB issued at discount' THEN 1 ELSE 0 END AS "&B10 -> ,CASE WHEN `0100_accrd_intrst_instrmnt` IS MISSING AND `0250_strctrd_prdct` IN ('Non-Structured', 'Other non-standard terms') AND `0240_zero_coupon` != 'ZCB issued at discount' THEN 1 ELSE 0 END AS v_1_0008 | W10: =+"SUM("&B10&") AS LVL1_H_"&MID(N10,2,LEN(N10)-2)&"," -> SUM(v_1_0008) AS LVL1_H_0100_accrd_intrst_instrmnt,
A11: 0009 | B11: =CONCATENATE("v_1_",A11) -> v_1_0009 | C11: B02.00 | D11: =VLOOKUP(CONCATENATE(C11,"_",E11),'Data types'!A:E,4,FALSE) -> 0100 | E11: Accrued interest | F11: =VLOOKUP(CONCATENATE(C11,"_",E11),'Data types'!A:F,6,FALSE) -> Numeric: 2 decimals | H11: X | I11: Test for missing values. | J11: Rule applicable only if c0250 != ("Structured" OR "Only structured coupon") | K11: Missing value (warning only). For structured liabilities, the field has to be reported if the information exists. | L11: =+IF(G11="X","HIGH","WARNING") -> WARNING | M11: =+LEFT(C11,3) -> B02 | N11: ="`"&VLOOKUP(D11,'B02_Mapping fields'!B:C,2,FALSE)&"`" -> `0100_accrd_intrst_instrmnt` | O11: 0250 | P11: ="`"&VLOOKUP(O11,'B02_Mapping fields'!B:C,2,FALSE)&"`" -> `0250_strctrd_prdct` | U11: =+",SELECT '"&M11&"' AS TAB, '"&L11&"' AS ALERT_TYPE, '"&B11&"' AS CHECK_ID, ROW_NUMBER, CASE WHEN A.ISSUES >0 THEN 1 ELSE 0 END AS "&B11&" FROM (SELECT COUNT(*) AS ISSUES FROM "&M11&" WHERE "&M11&"."&D11&" IS MISSING AND c0250 IN ('Structured', 'Only structured coupon')) AS A;" -> ,SELECT 'B02' AS TAB, 'WARNING' AS ALERT_TYPE, 'v_1_0009' AS CHECK_ID, ROW_NUMBER, CASE WHEN A.ISSUES >0 THEN 1 ELSE 0 END AS v_1_0009 FROM (SELECT COUNT(*) AS ISSUES FROM B02 WHERE B02.0100 IS MISSING AND c0250 IN ('Structured', 'Only structured coupon')) AS A; | V11: =+",CASE WHEN "&N11&" IS MISSING AND "&P11&" IN ('Structured', 'Only structured coupon') THEN 1 ELSE 0 END AS "&B11 -> ,CASE WHEN `0100_accrd_intrst_instrmnt` IS MISSING AND `0250_strctrd_prdct` IN ('Structured', 'Only structured coupon') THEN 1 ELSE 0 END AS v_1_0009 | W11: =+"SUM("&B11&") AS LVL1_W_"&MID(N11,2,LEN(N11)-2)&"," -> SUM(v_1_0009) AS LVL1_W_0100_accrd_intrst_instrmnt,
A12: 0010 | B12: =CONCATENATE("v_1_",A12) -> v_1_0010 | C12: B02.00 | D12: =VLOOKUP(CONCATENATE(C12,"_",E12),'Data types'!A:E,4,FALSE) -> 0120 | E12: Outstanding amount | F12: =VLOOKUP(CONCATENATE(C12,"_",E12),'Data types'!A:F,6,FALSE) -> Numeric: 2 decimals | G12: X | I12: Test for missing values. | J12: Rule applicable if c0250 = ("Non-Structured/Vanilla" OR "Other non-standard terms") | K12: Missing value. For non-structured liabilities, this field must be reported. | L12: =+IF(G12="X","HIGH","WARNING") -> HIGH | M12: =+LEFT(C12,3) -> B02 | N12: ="`"&VLOOKUP(D12,'B02_Mapping fields'!B:C,2,FALSE)&"`" -> `0120_otstndng_amnt` | O12: 0250 | P12: ="`"&VLOOKUP(O12,'B02_Mapping fields'!B:C,2,FALSE)&"`" -> `0250_strctrd_prdct` | U12: =+",SELECT '"&M12&"' AS TAB, '"&L12&"' AS ALERT_TYPE, '"&B12&"' AS CHECK_ID, ROW_NUMBER, CASE WHEN A.ISSUES >0 THEN 1 ELSE 0 END AS "&B12&" FROM (SELECT COUNT(*) AS ISSUES FROM "&M12&" WHERE "&M12&"."&D12&" IS MISSING AND c0250 IN ('Non-Structured/Vanilla', 'Other non-standard terms')) AS A;" -> ,SELECT 'B02' AS TAB, 'HIGH' AS ALERT_TYPE, 'v_1_0010' AS CHECK_ID, ROW_NUMBER, CASE WHEN A.ISSUES >0 THEN 1 ELSE 0 END AS v_1_0010 FROM (SELECT COUNT(*) AS ISSUES FROM B02 WHERE B02.0120 IS MISSING AND c0250 IN ('Non-Structured/Vanilla', 'Other non-standard terms')) AS A; | V12: =+",CASE WHEN "&N12&" IS MISSING AND "&P12&" IN ('Non-Structured/Vanilla', 'Other non-standard terms') THEN 1 ELSE 0 END AS "&B12 -> ,CASE WHEN `0120_otstndng_amnt` IS MISSING AND `0250_strctrd_prdct` IN ('Non-Structured/Vanilla', 'Other non-standard terms') THEN 1 ELSE 0 END AS v_1_0010 | W12: =+"SUM("&B12&") AS LVL1_H_"&MID(N12,2,LEN(N12)-2)&"," -> SUM(v_1_0010) AS LVL1_H_0120_otstndng_amnt,
A13: 0011 | B13: =CONCATENATE("v_1_",A13) -> v_1_0011 | C13: B02.00 | D13: =VLOOKUP(CONCATENATE(C13,"_",E13),'Data types'!A:E,4,FALSE) -> 0120 | E13: Outstanding amount | F13: =VLOOKUP(CONCATENATE(C13,"_",E13),'Data types'!A:F,6,FALSE) -> Numeric: 2 decimals | H13: X | I13: Test for missing values. | J13: Rule applicable only if c0250 != ("Structured" OR "Only structured coupon") | K13: Missing value (warning only). For structured liabilities, the field has to be reported if the information exists. | L13: =+IF(G13="X","HIGH","WARNING") -> WARNING | M13: =+LEFT(C13,3) -> B02 | N13: ="`"&VLOOKUP(D13,'B02_Mapping fields'!B:C,2,FALSE)&"`" -> `0120_otstndng_amnt` | O13: 0250 | P13: ="`"&VLOOKUP(O13,'B02_Mapping fields'!B:C,2,FALSE)&"`" -> `0250_strctrd_prdct` | U13: =+",SELECT '"&M13&"' AS TAB, '"&L13&"' AS ALERT_TYPE, '"&B13&"' AS CHECK_ID, ROW_NUMBER, CASE WHEN A.ISSUES >0 THEN 1 ELSE 0 END AS "&B13&" FROM (SELECT COUNT(*) AS ISSUES FROM "&M13&" WHERE "&M13&"."&D13&" IS MISSING AND c0250 NOT IN ('Structured', 'Only structured coupon')) AS A;" -> ,SELECT 'B02' AS TAB, 'WARNING' AS ALERT_TYPE, 'v_1_0011' AS CHECK_ID, ROW_NUMBER, CASE WHEN A.ISSUES >0 THEN 1 ELSE 0 END AS v_1_0011 FROM (SELECT COUNT(*) AS ISSUES FROM B02 WHERE B02.0120 IS MISSING AND c0250 NOT IN ('Structured', 'Only structured coupon')) AS A; | V13: =+",CASE WHEN "&N13&" IS MISSING AND "&P13&" NOT IN ('Structured', 'Only structured coupon') THEN 1 ELSE 0 END AS "&B13 -> ,CASE WHEN `0120_otstndng_amnt` IS MISSING AND `0250_strctrd_prdct` NOT IN ('Structured', 'Only structured coupon') THEN 1 ELSE 0 END AS v_1_0011 | W13: =+"SUM("&B13&") AS LVL1_W_"&MID(N13,2,LEN(N13)-2)&"," -> SUM(v_1_0011) AS LVL1_W_0120_otstndng_amnt,
A14: 0012 | B14: =CONCATENATE("v_1_",A14) -> v_1_0012 | C14: B02.00 | D14: =VLOOKUP(CONCATENATE(C14,"_",E14),'Data types'!A:E,4,FALSE) -> 0130 | E14: Relevant amount for Bail-in/WDC | F14: =VLOOKUP(CONCATENATE(C14,"_",E14),'Data types'!A:F,6,FALSE) -> Numeric: 2 decimals | G14: X | I14: Test for missing values. | K14: Missing value. The field must be reported. | L14: =+IF(G14="X","HIGH","WARNING") -> HIGH | M14: =+LEFT(C14,3) -> B02 | N14: ="`"&VLOOKUP(D14,'B02_Mapping fields'!B:C,2,FALSE)&"`" -> `0130_rlvnt_amnt_wdc` | U14: =+",SELECT '"&M14&"' AS TAB, '"&L14&"' AS ALERT_TYPE, '"&B14&"' AS CHECK_ID, ROW_NUMBER, CASE WHEN A.ISSUES >0 THEN 1 ELSE 0 END AS "&B14&" FROM (SELECT COUNT(*) AS ISSUES FROM "&M14&" WHERE "&M14&"."&D14&" IS MISSING) AS A;" -> ,SELECT 'B02' AS TAB, 'HIGH' AS ALERT_TYPE, 'v_1_0012' AS CHECK_ID, ROW_NUMBER, CASE WHEN A.ISSUES >0 THEN 1 ELSE 0 END AS v_1_0012 FROM (SELECT COUNT(*) AS ISSUES FROM B02 WHERE B02.0130 IS MISSING) AS A; | V14: =+",CASE WHEN "&N14&" IS MISSING THEN 1 ELSE 0 END AS "&B14 -> ,CASE WHEN `0130_rlvnt_amnt_wdc` IS MISSING THEN 1 ELSE 0 END AS v_1_0012 | W14: =+"SUM("&B14&") AS LVL1_H_"&MID(N14,2,LEN(N14)-2)&"," -> SUM(v_1_0012) AS LVL1_H_0130_rlvnt_amnt_wdc,
A15: 0013 | B15: =CONCATENATE("v_1_",A15) -> v_1_0013 | C15: B02.00 | D15: =VLOOKUP(CONCATENATE(C15,"_",E15),'Data types'!A:E,4,FALSE) -> 0140 | E15: Nature of the liability | F15: =VLOOKUP(CONCATENATE(C15,"_",E15),'Data types'!A:F,6,FALSE) -> String: Drop-down | G15: X | I15: Test for missing values. | K15: Missing value. The field must be reported. | L15: =+IF(G15="X","HIGH","WARNING") -> HIGH | M15: =+LEFT(C15,3) -> B02 | N15: ="`"&VLOOKUP(D15,'B02_Mapping fields'!B:C,2,FALSE)&"`" -> `0140_ntr_lblty` | U15: =+",SELECT '"&M15&"' AS TAB, '"&L15&"' AS ALERT_TYPE, '"&B15&"' AS CHECK_ID, ROW_NUMBER, CASE WHEN A.ISSUES >0 THEN 1 ELSE 0 END AS "&B15&" FROM (SELECT COUNT(*) AS ISSUES FROM "&M15&" WHERE "&M15&"."&D15&" IS MISSING) AS A;" -> ,SELECT 'B02' AS TAB, 'HIGH' AS ALERT_TYPE, 'v_1_0013' AS CHECK_ID, ROW_NUMBER, CASE WHEN A.ISSUES >0 THEN 1 ELSE 0 END AS v_1_0013 FROM (SELECT COUNT(*) AS ISSUES FROM B02 WHERE B02.0140 IS MISSING) AS A; | V15: =+",CASE WHEN "&N15&" IS MISSING THEN 1 ELSE 0 END AS "&B15 -> ,CASE WHEN `0140_ntr_lblty` IS MISSING THEN 1 ELSE 0 END AS v_1_0013 | W15: =+"SUM("&B15&") AS LVL1_H_"&MID(N15,2,LEN(N15)-2)&"," -> SUM(v_1_0013) AS LVL1_H_0140_ntr_lblty,
A16: 0014 | B16: =CONCATENATE("v_1_",A16) -> v_1_0014 | C16: B02.00 | D16: =VLOOKUP(CONCATENATE(C16,"_",E16),'Data types'!A:E,4,FALSE) -> 0141 | E16: Nature of the liability (if other) | F16: =VLOOKUP(CONCATENATE(C16,"_",E16),'Data types'!A:F,6,FALSE) -> String: Free text | G16: X | I16: Test for missing values. | J16: Rule applicable only if c0140 = "Other". | K16: Missing value. The field must be reported if option "Other" has been selected in c0140. | L16: =+IF(G16="X","HIGH","WARNING") -> HIGH | M16: =+LEFT(C16,3) -> B02 | N16: ="`"&VLOOKUP(D16,'B02_Mapping fields'!B:C,2,FALSE)&"`" -> `0141_ntr_lblty_othr` | O16: 0140 | P16: ="`"&VLOOKUP(O16,'B02_Mapping fields'!B:C,2,FALSE)&"`" -> `0140_ntr_lblty` | U16: =+",SELECT '"&M16&"' AS TAB, '"&L16&"' AS ALERT_TYPE, '"&B16&"' AS CHECK_ID, ROW_NUMBER, CASE WHEN A.ISSUES >0 THEN 1 ELSE 0 END AS "&B16&" FROM (SELECT COUNT(*) AS ISSUES FROM "&M16&" WHERE "&M16&"."&D16&" IS MISSING AND c0140 = 'Other') AS A;" -> ,SELECT 'B02' AS TAB, 'HIGH' AS ALERT_TYPE, 'v_1_0014' AS CHECK_ID, ROW_NUMBER, CASE WHEN A.ISSUES >0 THEN 1 ELSE 0 END AS v_1_0014 FROM (SELECT COUNT(*) AS ISSUES FROM B02 WHERE B02.0141 IS MISSING AND c0140 = 'Other') AS A; | V16: =+",CASE WHEN "&N16&" IS MISSING AND "&P16&" = 'Other' THEN 1 ELSE 0 END AS "&B16 -> ,CASE WHEN `0141_ntr_lblty_othr` IS MISSING AND `0140_ntr_lblty` = 'Other' THEN 1 ELSE 0 END AS v_1_0014 | W16: =+"SUM("&B16&") AS LVL1_H_"&MID(N16,2,LEN(N16)-2)&"," -> SUM(v_1_0014) AS LVL1_H_0141_ntr_lblty_othr,
A17: 0015 | B17: =CONCATENATE("v_1_",A17) -> v_1_0015 | C17: B02.00 | D17: =VLOOKUP(CONCATENATE(C17,"_",E17),'Data types'!A:E,4,FALSE) -> 0160 | E17: Insolvency ranking | F17: =VLOOKUP(CONCATENATE(C17,"_",E17),'Data types'!A:F,6,FALSE) -> Numeric: Integer | G17: X | I17: Test for missing values. | K17: Missing value. The field must be reported. | L17: =+IF(G17="X","HIGH","WARNING") -> HIGH | M17: =+LEFT(C17,3) -> B02 | N17: ="`"&VLOOKUP(D17,'B02_Mapping fields'!B:C,2,FALSE)&"`" -> `0160_rank_insolv` | U17: =+",SELECT '"&M17&"' AS TAB, '"&L17&"' AS ALERT_TYPE, '"&B17&"' AS CHECK_ID, ROW_NUMBER, CASE WHEN A.ISSUES >0 THEN 1 ELSE 0 END AS "&B17&" FROM (SELECT COUNT(*) AS ISSUES FROM "&M17&" WHERE "&M17&"."&D17&" IS MISSING) AS A;" -> ,SELECT 'B02' AS TAB, 'HIGH' AS ALERT_TYPE, 'v_1_0015' AS CHECK_ID, ROW_NUMBER, CASE WHEN A.ISSUES >0 THEN 1 ELSE 0 END AS v_1_0015 FROM (SELECT COUNT(*) AS ISSUES FROM B02 WHERE B02.0160 IS MISSING) AS A; | V17: =+",CASE WHEN "&N17&" IS MISSING THEN 1 ELSE 0 END AS "&B17 -> ,CASE WHEN `0160_rank_insolv` IS MISSING THEN 1 ELSE 0 END AS v_1_0015 | W17: =+"SUM("&B17&") AS LVL1_H_"&MID(N17,2,LEN(N17)-2)&"," -> SUM(v_1_0015) AS LVL1_H_0160_rank_insolv,
A18: 0016 | B18: =CONCATENATE("v_1_",A18) -> v_1_0016 | C18: B02.00 | D18: =VLOOKUP(CONCATENATE(C18,"_",E18),'Data types'!A:E,4,FALSE) -> 0162 | E18: Bail-in cascade | F18: =VLOOKUP(CONCATENATE(C18,"_",E18),'Data types'!A:F,6,FALSE) -> String: Fixed values | G18: X | I18: Test for missing values. | K18: Missing value. The field must be reported. | L18: =+IF(G18="X","HIGH","WARNING") -> HIGH | M18: =+LEFT(C18,3) -> B02 | N18: ="`"&VLOOKUP(D18,'B02_Mapping fields'!B:C,2,FALSE)&"`" -> `0162_bail_in_cascade` | U18: =+",SELECT '"&M18&"' AS TAB, '"&L18&"' AS ALERT_TYPE, '"&B18&"' AS CHECK_ID, ROW_NUMBER, CASE WHEN A.ISSUES >0 THEN 1 ELSE 0 END AS "&B18&" FROM (SELECT COUNT(*) AS ISSUES FROM "&M18&" WHERE "&M18&"."&D18&" IS MISSING) AS A;" -> ,SELECT 'B02' AS TAB, 'HIGH' AS ALERT_TYPE, 'v_1_0016' AS CHECK_ID, ROW_NUMBER, CASE WHEN A.ISSUES >0 THEN 1 ELSE 0 END AS v_1_0016 FROM (SELECT COUNT(*) AS ISSUES FROM B02 WHERE B02.0162 IS MISSING) AS A; | V18: =+",CASE WHEN "&N18&" IS MISSING THEN 1 ELSE 0 END AS "&B18 -> ,CASE WHEN `0162_bail_in_cascade` IS MISSING THEN 1 ELSE 0 END AS v_1_0016 | W18: =+"SUM("&B18&") AS LVL1_H_"&MID(N18,2,LEN(N18)-2)&"," -> SUM(v_1_0016) AS LVL1_H_0162_bail_in_cascade,
A19: 0017 | B19: =CONCATENATE("v_1_",A19) -> v_1_0017 | C19: B02.00 | D19: =VLOOKUP(CONCATENATE(C19,"_",E19),'Data types'!A:E,4,FALSE) -> 0180 | E19: Date of the next interest payment | F19: =VLOOKUP(CONCATENATE(C19,"_",E19),'Data types'!A:F,6,FALSE) -> Date: yyyy-mm-dd | G19: X | I19: Test for missing values. | J19: Rule applicable if c0250 = ("Non-Structured/Vanilla" OR "Other non-standard terms") AND c0240 != "ZCB issued at discount" | K19: Missing value. For non-structured liabilities that are not zero coupon bonds issued at discount, this field is must be reported. | L19: =+IF(G19="X","HIGH","WARNING") -> HIGH | M19: =+LEFT(C19,3) -> B02 | N19: ="`"&VLOOKUP(D19,'B02_Mapping fields'!B:C,2,FALSE)&"`" -> `0180_dt_nxt_intrst_pymnt` | O19: 0250 | P19: ="`"&VLOOKUP(O19,'B02_Mapping fields'!B:C,2,FALSE)&"`" -> `0250_strctrd_prdct` | Q19: 0240 | R19: ="`"&VLOOKUP(Q19,'B02_Mapping fields'!B:C,2,FALSE)&"`" -> `0240_zero_coupon` | U19: =+",SELECT '"&M19&"' AS TAB, '"&L19&"' AS ALERT_TYPE, '"&B19&"' AS CHECK_ID, ROW_NUMBER, CASE WHEN A.ISSUES >0 THEN 1 ELSE 0 END AS "&B19&" FROM (SELECT COUNT(*) AS ISSUES FROM "&M19&" WHERE "&M19&"."&D19&" IS MISSING AND c0250 IN ('Non-Structured/Vanilla', 'Other non-standard terms') AND c0240 != 'ZCB issued at discount') AS A;" -> ,SELECT 'B02' AS TAB, 'HIGH' AS ALERT_TYPE, 'v_1_0017' AS CHECK_ID, ROW_NUMBER, CASE WHEN A.ISSUES >0 THEN 1 ELSE 0 END AS v_1_0017 FROM (SELECT COUNT(*) AS ISSUES FROM B02 WHERE B02.0180 IS MISSING AND c0250 IN ('Non-Structured/Vanilla', 'Other non-standard terms') AND c0240 != 'ZCB issued at discount') AS A; | V19: =+",CASE WHEN "&N19&" IS MISSING AND "&P19&" IN ('Non-Structured/Vanilla', 'Other non-standard terms') AND "&R19&" != 'ZCB issued at discount' THEN 1 ELSE 0 END AS "&B19 -> ,CASE WHEN `0180_dt_nxt_intrst_pymnt` IS MISSING AND `0250_strctrd_prdct` IN ('Non-Structured/Vanilla', 'Other non-standard terms') AND `0240_zero_coupon` != 'ZCB issued at discount' THEN 1 ELSE 0 END AS v_1_0017 | W19: =+"SUM("&B19&") AS LVL1_H_"&MID(N19,2,LEN(N19)-2)&"," -> SUM(v_1_0017) AS LVL1_H_0180_dt_nxt_intrst_pymnt,
A20: 0018 | B20: =CONCATENATE("v_1_",A20) -> v_1_0018 | C20: B02.00 | D20: =VLOOKUP(CONCATENATE(C20,"_",E20),'Data types'!A:E,4,FALSE) -> 0180 | E20: Date of the next interest payment | F20: =VLOOKUP(CONCATENATE(C20,"_",E20),'Data types'!A:F,6,FALSE) -> Date: yyyy-mm-dd | H20: X | I20: Test for missing values. | J20: Rule applicable only if c0250 != ("Structured" OR "Only structured coupon") | K20: Missing value (warning only). For structured liabilities, this field should be reported only if the information exists.. | L20: =+IF(G20="X","HIGH","WARNING") -> WARNING | M20: =+LEFT(C20,3) -> B02 | N20: ="`"&VLOOKUP(D20,'B02_Mapping fields'!B:C,2,FALSE)&"`" -> `0180_dt_nxt_intrst_pymnt` | O20: 0250 | P20: ="`"&VLOOKUP(O20,'B02_Mapping fields'!B:C,2,FALSE)&"`" -> `0250_strctrd_prdct` | U20: =+",SELECT '"&M20&"' AS TAB, '"&L20&"' AS ALERT_TYPE, '"&B20&"' AS CHECK_ID, ROW_NUMBER, CASE WHEN A.ISSUES >0 THEN 1 ELSE 0 END AS "&B20&" FROM (SELECT COUNT(*) AS ISSUES FROM "&M20&" WHERE "&M20&"."&D20&" IS MISSING AND c0250 NOT IN ('Structured', 'Only structured coupon')) AS A;" -> ,SELECT 'B02' AS TAB, 'WARNING' AS ALERT_TYPE, 'v_1_0018' AS CHECK_ID, ROW_NUMBER, CASE WHEN A.ISSUES >0 THEN 1 ELSE 0 END AS v_1_0018 FROM (SELECT COUNT(*) AS ISSUES FROM B02 WHERE B02.0180 IS MISSING AND c0250 NOT IN ('Structured', 'Only structured coupon')) AS A; | V20: =+",CASE WHEN "&N20&" IS MISSING AND "&P20&" NOT IN ('Structured', 'Only structured coupon') THEN 1 ELSE 0 END AS "&B20 -> ,CASE WHEN `0180_dt_nxt_intrst_pymnt` IS MISSING AND `0250_strctrd_prdct` NOT IN ('Structured', 'Only structured coupon') THEN 1 ELSE 0 END AS v_1_0018 | W20: =+"SUM("&B20&") AS LVL1_W_"&MID(N20,2,LEN(N20)-2)&"," -> SUM(v_1_0018) AS LVL1_W_0180_dt_nxt_intrst_pymnt,
A21: 0019 | B21: =CONCATENATE("v_1_",A21) -> v_1_0019 | C21: B02.00 | D21: =VLOOKUP(CONCATENATE(C21,"_",E21),'Data types'!A:E,4,FALSE) -> 0200 | E21: Earliest redemption date | F21: =VLOOKUP(CONCATENATE(C21,"_",E21),'Data types'!A:F,6,FALSE) -> Date: yyyy-mm-dd | H21: X | I21: Test for missing values. | K21: Missing value (warning only). This field needs to be reported if the information exists. | L21: =+IF(G21="X","HIGH","WARNING") -> WARNING | M21: =+LEFT(C21,3) -> B02 | N21: ="`"&VLOOKUP(D21,'B02_Mapping fields'!B:C,2,FALSE)&"`" -> `0200_dt_erlst_rdmptn` | U21: =+",SELECT '"&M21&"' AS TAB, '"&L21&"' AS ALERT_TYPE, '"&B21&"' AS CHECK_ID, ROW_NUMBER, CASE WHEN A.ISSUES >0 THEN 1 ELSE 0 END AS "&B21&" FROM (SELECT COUNT(*) AS ISSUES FROM "&M21&" WHERE "&M21&"."&D21&" IS MISSING) AS A;" -> ,SELECT 'B02' AS TAB, 'WARNING' AS ALERT_TYPE, 'v_1_0019' AS CHECK_ID, ROW_NUMBER, CASE WHEN A.ISSUES >0 THEN 1 ELSE 0 END AS v_1_0019 FROM (SELECT COUNT(*) AS ISSUES FROM B02 WHERE B02.0200 IS MISSING) AS A; | V21: =+",CASE WHEN "&N21&" IS MISSING THEN 1 ELSE 0 END AS "&B21 -> ,CASE WHEN `0200_dt_erlst_rdmptn` IS MISSING THEN 1 ELSE 0 END AS v_1_0019 | W21: =+"SUM("&B21&") AS LVL1_W_"&MID(N21,2,LEN(N21)-2)&"," -> SUM(v_1_0019) AS LVL1_W_0200_dt_erlst_rdmptn,
A22: 0020 | B22: =CONCATENATE("v_1_",A22) -> v_1_0020 | C22: B02.00 | D22: =VLOOKUP(CONCATENATE(C22,"_",E22),'Data types'!A:E,4,FALSE) -> 0210 | E22: Legal maturity | F22: =VLOOKUP(CONCATENATE(C22,"_",E22),'Data types'!A:F,6,FALSE) -> Date: yyyy-mm-dd | G22: X | I22: Test for missing values. | J22: Rule applicable if c0140 != "Cash account/saving account". | K22: Missing value.For liabilities other than of the type "Cash account/savings account, the field must be reported. | L22: =+IF(G22="X","HIGH","WARNING") -> HIGH | M22: =+LEFT(C22,3) -> B02 | N22: ="`"&VLOOKUP(D22,'B02_Mapping fields'!B:C,2,FALSE)&"`" -> `0210_dt_lgl_fnl_mtrty` | O22: 0140 | P22: ="`"&VLOOKUP(O22,'B02_Mapping fields'!B:C,2,FALSE)&"`" -> `0140_ntr_lblty` | U22: =+",SELECT '"&M22&"' AS TAB, '"&L22&"' AS ALERT_TYPE, '"&B22&"' AS CHECK_ID, ROW_NUMBER, CASE WHEN A.ISSUES >0 THEN 1 ELSE 0 END AS "&B22&" FROM (SELECT COUNT(*) AS ISSUES FROM "&M22&" WHERE "&M22&"."&D22&" IS MISSING AND c0240 != 'Cash account/saving account') AS A;" -> ,SELECT 'B02' AS TAB, 'HIGH' AS ALERT_TYPE, 'v_1_0020' AS CHECK_ID, ROW_NUMBER, CASE WHEN A.ISSUES >0 THEN 1 ELSE 0 END AS v_1_0020 FROM (SELECT COUNT(*) AS ISSUES FROM B02 WHERE B02.0210 IS MISSING AND c0240 != 'Cash account/saving account') AS A; | V22: =+",CASE WHEN "&N22&" IS MISSING AND "&P22&" != 'Cash account/saving account' THEN 1 ELSE 0 END AS "&B22 -> ,CASE WHEN `0210_dt_lgl_fnl_mtrty` IS MISSING AND `0140_ntr_lblty` != 'Cash account/saving account' THEN 1 ELSE 0 END AS v_1_0020 | W22: =+"SUM("&B22&") AS LVL1_H_"&MID(N22,2,LEN(N22)-2)&"," -> SUM(v_1_0020) AS LVL1_H_0210_dt_lgl_fnl_mtrty,
A23: 0021 | B23: =CONCATENATE("v_1_",A23) -> v_1_0021 | C23: B02.00 | D23: =VLOOKUP(CONCATENATE(C23,"_",E23),'Data types'!A:E,4,FALSE) -> 0220 | E23: Governing law | F23: =VLOOKUP(CONCATENATE(C23,"_",E23),'Data types'!A:F,6,FALSE) -> String: ISO 3166-1 alpha 2 / ISO 3166-2 | G23: X | I23: Test for missing values. | K23: Missing value. The field must be reported. | L23: =+IF(G23="X","HIGH","WARNING") -> HIGH | M23: =+LEFT(C23,3) -> B02 | N23: ="`"&VLOOKUP(D23,'B02_Mapping fields'!B:C,2,FALSE)&"`" -> `0220_governing_law` | U23: =+",SELECT '"&M23&"' AS TAB, '"&L23&"' AS ALERT_TYPE, '"&B23&"' AS CHECK_ID, ROW_NUMBER, CASE WHEN A.ISSUES >0 THEN 1 ELSE 0 END AS "&B23&" FROM (SELECT COUNT(*) AS ISSUES FROM "&M23&" WHERE "&M23&"."&D23&" IS MISSING) AS A;" -> ,SELECT 'B02' AS TAB, 'HIGH' AS ALERT_TYPE, 'v_1_0021' AS CHECK_ID, ROW_NUMBER, CASE WHEN A.ISSUES >0 THEN 1 ELSE 0 END AS v_1_0021 FROM (SELECT COUNT(*) AS ISSUES FROM B02 WHERE B02.0220 IS MISSING) AS A; | V23: =+",CASE WHEN "&N23&" IS MISSING THEN 1 ELSE 0 END AS "&B23 -> ,CASE WHEN `0220_governing_law` IS MISSING THEN 1 ELSE 0 END AS v_1_0021 | W23: =+"SUM("&B23&") AS LVL1_H_"&MID(N23,2,LEN(N23)-2)&"," -> SUM(v_1_0021) AS LVL1_H_0220_governing_law,
A24: 0022 | B24: =CONCATENATE("v_1_",A24) -> v_1_0022 | C24: B02.00 | D24: =VLOOKUP(CONCATENATE(C24,"_",E24),'Data types'!A:E,4,FALSE) -> 0250 | E24: Structured product | F24: =VLOOKUP(CONCATENATE(C24,"_",E24),'Data types'!A:F,6,FALSE) -> String: Drop-down | G24: X | I24: Test for missing values. | K24: Missing value. The field must be reported. | L24: =+IF(G24="X","HIGH","WARNING") -> HIGH | M24: =+LEFT(C24,3) -> B02 | N24: ="`"&VLOOKUP(D24,'B02_Mapping fields'!B:C,2,FALSE)&"`" -> `0250_strctrd_prdct` | U24: =+",SELECT '"&M24&"' AS TAB, '"&L24&"' AS ALERT_TYPE, '"&B24&"' AS CHECK_ID, ROW_NUMBER, CASE WHEN A.ISSUES >0 THEN 1 ELSE 0 END AS "&B24&" FROM (SELECT COUNT(*) AS ISSUES FROM "&M24&" WHERE "&M24&"."&D24&" IS MISSING) AS A;" -> ,SELECT 'B02' AS TAB, 'HIGH' AS ALERT_TYPE, 'v_1_0022' AS CHECK_ID, ROW_NUMBER, CASE WHEN A.ISSUES >0 THEN 1 ELSE 0 END AS v_1_0022 FROM (SELECT COUNT(*) AS ISSUES FROM B02 WHERE B02.0250 IS MISSING) AS A; | V24: =+",CASE WHEN "&N24&" IS MISSING THEN 1 ELSE 0 END AS "&B24 -> ,CASE WHEN `0250_strctrd_prdct` IS MISSING THEN 1 ELSE 0 END AS v_1_0022 | W24: =+"SUM("&B24&") AS LVL1_H_"&MID(N24,2,LEN(N24)-2)&"," -> SUM(v_1_0022) AS LVL1_H_0250_strctrd_prdct,
A25: 0023 | B25: =CONCATENATE("v_1_",A25) -> v_1_0023 | C25: B02.00 | D25: =VLOOKUP(CONCATENATE(C25,"_",E25),'Data types'!A:E,4,FALSE) -> 0260 | E25: Guaranteed minimum repayment amount of the structured product | F25: =VLOOKUP(CONCATENATE(C25,"_",E25),'Data types'!A:F,6,FALSE) -> Numeric: 2 decimals | H25: X | I25: Test for missing values. | J25: Rule applicable only if c0250 = ("Structured" OR "Structured coupon only") | K25: Missing value (warning only). For structured liabilities, this field should be reported if the information exists.. | L25: =+IF(G25="X","HIGH","WARNING") -> WARNING | M25: =+LEFT(C25,3) -> B02 | N25: ="`"&VLOOKUP(D25,'B02_Mapping fields'!B:C,2,FALSE)&"`" -> `0260_grntd_min_amnt_strctrd_prdct` | O25: 0250 | P25: ="`"&VLOOKUP(O25,'B02_Mapping fields'!B:C,2,FALSE)&"`" -> `0250_strctrd_prdct` | U25: =+",SELECT '"&M25&"' AS TAB, '"&L25&"' AS ALERT_TYPE, '"&B25&"' AS CHECK_ID, ROW_NUMBER, CASE WHEN A.ISSUES >0 THEN 1 ELSE 0 END AS "&B25&" FROM (SELECT COUNT(*) AS ISSUES FROM "&M25&" WHERE "&M25&"."&D25&" IS MISSING AND c0250 IN ('Structured', 'Only structured coupon')) AS A;" -> ,SELECT 'B02' AS TAB, 'WARNING' AS ALERT_TYPE, 'v_1_0023' AS CHECK_ID, ROW_NUMBER, CASE WHEN A.ISSUES >0 THEN 1 ELSE 0 END AS v_1_0023 FROM (SELECT COUNT(*) AS ISSUES FROM B02 WHERE B02.0260 IS MISSING AND c0250 IN ('Structured', 'Only structured coupon')) AS A; | V25: =+",CASE WHEN "&N25&" IS MISSING AND "&P25&" IN ('Structured', 'Only structured coupon') THEN 1 ELSE 0 END AS "&B25 -> ,CASE WHEN `0260_grntd_min_amnt_strctrd_prdct` IS MISSING AND `0250_strctrd_prdct` IN ('Structured', 'Only structured coupon') THEN 1 ELSE 0 END AS v_1_0023 | W25: =+"SUM("&B25&") AS LVL1_W_"&MID(N25,2,LEN(N25)-2)&"," -> SUM(v_1_0023) AS LVL1_W_0260_grntd_min_amnt_strctrd_prdct,
A26: 0024 | B26: =CONCATENATE("v_1_",A26) -> v_1_0024 | C26: B02.00 | D26: =VLOOKUP(CONCATENATE(C26,"_",E26),'Data types'!A:E,4,FALSE) -> 0270 | E26: Fair value of the structured product | F26: =VLOOKUP(CONCATENATE(C26,"_",E26),'Data types'!A:F,6,FALSE) -> Numeric: 2 decimals | G26: X | I26: Test for missing values. | J26: Rule applicable only if c0250 = ("Structured" OR "Structured coupon only") | K26: Missing value. The field must be reported for structured products. | L26: =+IF(G26="X","HIGH","WARNING") -> HIGH | M26: =+LEFT(C26,3) -> B02 | N26: ="`"&VLOOKUP(D26,'B02_Mapping fields'!B:C,2,FALSE)&"`" -> `0270_fv_amnt_strctrd_prdct` | O26: 0250 | P26: ="`"&VLOOKUP(O26,'B02_Mapping fields'!B:C,2,FALSE)&"`" -> `0250_strctrd_prdct` | U26: =+",SELECT '"&M26&"' AS TAB, '"&L26&"' AS ALERT_TYPE, '"&B26&"' AS CHECK_ID, ROW_NUMBER, CASE WHEN A.ISSUES >0 THEN 1 ELSE 0 END AS "&B26&" FROM (SELECT COUNT(*) AS ISSUES FROM "&M26&" WHERE "&M26&"."&D26&" IS MISSING AND c0250 IN ('Structured', 'Only structured coupon')) AS A;" -> ,SELECT 'B02' AS TAB, 'HIGH' AS ALERT_TYPE, 'v_1_0024' AS CHECK_ID, ROW_NUMBER, CASE WHEN A.ISSUES >0 THEN 1 ELSE 0 END AS v_1_0024 FROM (SELECT COUNT(*) AS ISSUES FROM B02 WHERE B02.0270 IS MISSING AND c0250 IN ('Structured', 'Only structured coupon')) AS A; | V26: =+",CASE WHEN "&N26&" IS MISSING AND "&P26&" IN ('Structured', 'Only structured coupon') THEN 1 ELSE 0 END AS "&B26 -> ,CASE WHEN `0270_fv_amnt_strctrd_prdct` IS MISSING AND `0250_strctrd_prdct` IN ('Structured', 'Only structured coupon') THEN 1 ELSE 0 END AS v_1_0024 | W26: =+"SUM("&B26&") AS LVL1_H_"&MID(N26,2,LEN(N26)-2)&"," -> SUM(v_1_0024) AS LVL1_H_0270_fv_amnt_strctrd_prdct,
A27: 0025 | B27: =CONCATENATE("v_1_",A27) -> v_1_0025 | C27: B02.00 | D27: =VLOOKUP(CONCATENATE(C27,"_",E27),'Data types'!A:E,4,FALSE) -> 0300 | E27: Covered portion of eligible deposits | F27: =VLOOKUP(CONCATENATE(C27,"_",E27),'Data types'!A:F,6,FALSE) -> Numeric: 2 decimals | G27: X | I27: Test for missing values. | J27: Rule applicable only if c0280 = "TRUE" or c0290 = "TRUE". | K27: Missing value. The field must be reported for eligible deposits. If the value is zero, "0" should be entered. | L27: =+IF(G27="X","HIGH","WARNING") -> HIGH | M27: =+LEFT(C27,3) -> B02 | N27: ="`"&VLOOKUP(D27,'B02_Mapping fields'!B:C,2,FALSE)&"`" -> `0300_amnt_cvrd_elgbl_dpsts` | O27: 0280 | P27: ="`"&VLOOKUP(O27,'B02_Mapping fields'!B:C,2,FALSE)&"`" -> `0280_flg_ncnp_dpsts` | Q27: 0290 | R27: ="`"&VLOOKUP(Q27,'B02_Mapping fields'!B:C,2,FALSE)&"`" -> `0290_flg_ncbp_dpsts` | U27: =+",SELECT '"&M27&"' AS TAB, '"&L27&"' AS ALERT_TYPE, '"&B27&"' AS CHECK_ID, ROW_NUMBER, CASE WHEN A.ISSUES >0 THEN 1 ELSE 0 END AS "&B27&" FROM (SELECT COUNT(*) AS ISSUES FROM "&M27&" WHERE "&M27&"."&D27&" IS MISSING AND (c0280 = 'TRUE' or c0290 = 'TRUE')) AS A;" -> ,SELECT 'B02' AS TAB, 'HIGH' AS ALERT_TYPE, 'v_1_0025' AS CHECK_ID, ROW_NUMBER, CASE WHEN A.ISSUES >0 THEN 1 ELSE 0 END AS v_1_0025 FROM (SELECT COUNT(*) AS ISSUES FROM B02 WHERE B02.0300 IS MISSING AND (c0280 = 'TRUE' or c0290 = 'TRUE')) AS A; | V27: =+",CASE WHEN "&N27&" IS MISSING AND ("&P27&" = 'TRUE' or "&R27&" = 'TRUE') THEN 1 ELSE 0 END AS "&B27 -> ,CASE WHEN `0300_amnt_cvrd_elgbl_dpsts` IS MISSING AND (`0280_flg_ncnp_dpsts` = 'TRUE' or `0290_flg_ncbp_dpsts` = 'TRUE') THEN 1 ELSE 0 END AS v_1_0025 | W27: =+"SUM("&B27&") AS LVL1_H_"&MID(N27,2,LEN(N27)-2)&"," -> SUM(v_1_0025) AS LVL1_H_0300_amnt_cvrd_elgbl_dpsts,
A28: 0026 | B28: =CONCATENATE("v_1_",A28) -> v_1_0026 | C28: B02.00 | D28: =VLOOKUP(CONCATENATE(C28,"_",E28),'Data types'!A:E,4,FALSE) -> 0310 | E28: Secured/Unsecured | F28: =VLOOKUP(CONCATENATE(C28,"_",E28),'Data types'!A:F,6,FALSE) -> String: Drop-down | G28: X | I28: Test for missing values. | K28: Missing value. The field must be reported. | L28: =+IF(G28="X","HIGH","WARNING") -> HIGH | M28: =+LEFT(C28,3) -> B02 | N28: ="`"&VLOOKUP(D28,'B02_Mapping fields'!B:C,2,FALSE)&"`" -> `0310_flg_clltrl_agrmnts` | U28: =+",SELECT '"&M28&"' AS TAB, '"&L28&"' AS ALERT_TYPE, '"&B28&"' AS CHECK_ID, ROW_NUMBER, CASE WHEN A.ISSUES >0 THEN 1 ELSE 0 END AS "&B28&" FROM (SELECT COUNT(*) AS ISSUES FROM "&M28&" WHERE "&M28&"."&D28&" IS MISSING) AS A;" -> ,SELECT 'B02' AS TAB, 'HIGH' AS ALERT_TYPE, 'v_1_0026' AS CHECK_ID, ROW_NUMBER, CASE WHEN A.ISSUES >0 THEN 1 ELSE 0 END AS v_1_0026 FROM (SELECT COUNT(*) AS ISSUES FROM B02 WHERE B02.0310 IS MISSING) AS A; | V28: =+",CASE WHEN "&N28&" IS MISSING THEN 1 ELSE 0 END AS "&B28 -> ,CASE WHEN `0310_flg_clltrl_agrmnts` IS MISSING THEN 1 ELSE 0 END AS v_1_0026 | W28: =+"SUM("&B28&") AS LVL1_H_"&MID(N28,2,LEN(N28)-2)&"," -> SUM(v_1_0026) AS LVL1_H_0310_flg_clltrl_agrmnts,
A29: 0027 | B29: =CONCATENATE("v_1_",A29) -> v_1_0027 | C29: B02.00 | D29: =VLOOKUP(CONCATENATE(C29,"_",E29),'Data types'!A:E,4,FALSE) -> 0320 | E29: Amount of pledge, lien or collateral based on the current internal valuation | F29: =VLOOKUP(CONCATENATE(C29,"_",E29),'Data types'!A:F,6,FALSE) -> Numeric: 2 decimals | G29: X | I29: Test for missing values. | J29: Rule applicable only if c0310 = "Secured" | K29: Missing value. The field must be reported for secured products. If the value is zero, "0" should be entered. | L29: =+IF(G29="X","HIGH","WARNING") -> HIGH | M29: =+LEFT(C29,3) -> B02 | N29: ="`"&VLOOKUP(D29,'B02_Mapping fields'!B:C,2,FALSE)&"`" -> `0320_amnt_clltrl` | O29: 0310 | P29: ="`"&VLOOKUP(O29,'B02_Mapping fields'!B:C,2,FALSE)&"`" -> `0310_flg_clltrl_agrmnts` | U29: =+",SELECT '"&M29&"' AS TAB, '"&L29&"' AS ALERT_TYPE, '"&B29&"' AS CHECK_ID, ROW_NUMBER, CASE WHEN A.ISSUES >0 THEN 1 ELSE 0 END AS "&B29&" FROM (SELECT COUNT(*) AS ISSUES FROM "&M29&" WHERE "&M29&"."&D29&" IS MISSING AND c0310 = 'Secured') AS A;" -> ,SELECT 'B02' AS TAB, 'HIGH' AS ALERT_TYPE, 'v_1_0027' AS CHECK_ID, ROW_NUMBER, CASE WHEN A.ISSUES >0 THEN 1 ELSE 0 END AS v_1_0027 FROM (SELECT COUNT(*) AS ISSUES FROM B02 WHERE B02.0320 IS MISSING AND c0310 = 'Secured') AS A; | V29: =+",CASE WHEN "&N29&" IS MISSING AND "&P29&" = 'Secured' THEN 1 ELSE 0 END AS "&B29 -> ,CASE WHEN `0320_amnt_clltrl` IS MISSING AND `0310_flg_clltrl_agrmnts` = 'Secured' THEN 1 ELSE 0 END AS v_1_0027 | W29: =+"SUM("&B29&") AS LVL1_H_"&MID(N29,2,LEN(N29)-2)&"," -> SUM(v_1_0027) AS LVL1_H_0320_amnt_clltrl,
A30: 0028 | B30: =CONCATENATE("v_1_",A30) -> v_1_0028 | C30: B02.00 | D30: =VLOOKUP(CONCATENATE(C30,"_",E30),'Data types'!A:E,4,FALSE) -> 0330 | E30: Amount of the uncollateralized part | F30: =VLOOKUP(CONCATENATE(C30,"_",E30),'Data types'!A:F,6,FALSE) -> Numeric: 2 decimals | G30: X | I30: Test for missing values. | J30: Rule applicable only if c0310 = "Secured" | K30: Missing value. The field must be reported for secured products. | L30: =+IF(G30="X","HIGH","WARNING") -> HIGH | M30: =+LEFT(C30,3) -> B02 | N30: ="`"&VLOOKUP(D30,'B02_Mapping fields'!B:C,2,FALSE)&"`" -> `0330_amnt_unclltrlzd` | O30: 0310 | P30: ="`"&VLOOKUP(O30,'B02_Mapping fields'!B:C,2,FALSE)&"`" -> `0310_flg_clltrl_agrmnts` | U30: =+",SELECT '"&M30&"' AS TAB, '"&L30&"' AS ALERT_TYPE, '"&B30&"' AS CHECK_ID, ROW_NUMBER, CASE WHEN A.ISSUES >0 THEN 1 ELSE 0 END AS "&B30&" FROM (SELECT COUNT(*) AS ISSUES FROM "&M30&" WHERE "&M30&"."&D30&" IS MISSING AND c0310 = 'Secured') AS A;" -> ,SELECT 'B02' AS TAB, 'HIGH' AS ALERT_TYPE, 'v_1_0028' AS CHECK_ID, ROW_NUMBER, CASE WHEN A.ISSUES >0 THEN 1 ELSE 0 END AS v_1_0028 FROM (SELECT COUNT(*) AS ISSUES FROM B02 WHERE B02.0330 IS MISSING AND c0310 = 'Secured') AS A; | V30: =+",CASE WHEN "&N30&" IS MISSING AND "&P30&" = 'Secured' THEN 1 ELSE 0 END AS "&B30 -> ,CASE WHEN `0330_amnt_unclltrlzd` IS MISSING AND `0310_flg_clltrl_agrmnts` = 'Secured' THEN 1 ELSE 0 END AS v_1_0028 | W30: =+"SUM("&B30&") AS LVL1_H_"&MID(N30,2,LEN(N30)-2)&"," -> SUM(v_1_0028) AS LVL1_H_0330_amnt_unclltrlzd,
A31: 0029 | B31: =CONCATENATE("v_1_",A31) -> v_1_0029 | C31: B02.00 | D31: =VLOOKUP(CONCATENATE(C31,"_",E31),'Data types'!A:E,4,FALSE) -> 0350 | E31: Type of the collateral | F31: =VLOOKUP(CONCATENATE(C31,"_",E31),'Data types'!A:F,6,FALSE) -> String: Drop-down | G31: X | I31: Test for missing values. | J31: Rule applicable only if c0310 = "Secured" | K31: Missing value. The field must be reported for secured products. | L31: =+IF(G31="X","HIGH","WARNING") -> HIGH | M31: =+LEFT(C31,3) -> B02 | N31: ="`"&VLOOKUP(D31,'B02_Mapping fields'!B:C,2,FALSE)&"`" -> `0350_typ_clltrl` | O31: 0310 | P31: ="`"&VLOOKUP(O31,'B02_Mapping fields'!B:C,2,FALSE)&"`" -> `0310_flg_clltrl_agrmnts` | U31: =+",SELECT '"&M31&"' AS TAB, '"&L31&"' AS ALERT_TYPE, '"&B31&"' AS CHECK_ID, ROW_NUMBER, CASE WHEN A.ISSUES >0 THEN 1 ELSE 0 END AS "&B31&" FROM (SELECT COUNT(*) AS ISSUES FROM "&M31&" WHERE "&M31&"."&D31&" IS MISSING AND c0310 = 'Secured') AS A;" -> ,SELECT 'B02' AS TAB, 'HIGH' AS ALERT_TYPE, 'v_1_0029' AS CHECK_ID, ROW_NUMBER, CASE WHEN A.ISSUES >0 THEN 1 ELSE 0 END AS v_1_0029 FROM (SELECT COUNT(*) AS ISSUES FROM B02 WHERE B02.0350 IS MISSING AND c0310 = 'Secured') AS A; | V31: =+",CASE WHEN "&N31&" IS MISSING AND "&P31&" = 'Secured' THEN 1 ELSE 0 END AS "&B31 -> ,CASE WHEN `0350_typ_clltrl` IS MISSING AND `0310_flg_clltrl_agrmnts` = 'Secured' THEN 1 ELSE 0 END AS v_1_0029 | W31: =+"SUM("&B31&") AS LVL1_H_"&MID(N31,2,LEN(N31)-2)&"," -> SUM(v_1_0029) AS LVL1_H_0350_typ_clltrl,
A32: 0030 | B32: =CONCATENATE("v_1_",A32) -> v_1_0030 | C32: B02.00 | D32: =VLOOKUP(CONCATENATE(C32,"_",E32),'Data types'!A:E,4,FALSE) -> 0351 | E32: Type of the collateral (if other) | F32: =VLOOKUP(CONCATENATE(C32,"_",E32),'Data types'!A:F,6,FALSE) -> String: Free text | G32: X | I32: Test for missing values. | J32: Rule applicable only if c0350 = "Other" | K32: Missing value (warning). The field should be reported if c0350 = "Other". | L32: =+IF(G32="X","HIGH","WARNING") -> HIGH | M32: =+LEFT(C32,3) -> B02 | N32: ="`"&VLOOKUP(D32,'B02_Mapping fields'!B:C,2,FALSE)&"`" -> `0351_typ_clltrl_othr` | O32: 0350 | P32: ="`"&VLOOKUP(O32,'B02_Mapping fields'!B:C,2,FALSE)&"`" -> `0350_typ_clltrl` | U32: =+",SELECT '"&M32&"' AS TAB, '"&L32&"' AS ALERT_TYPE, '"&B32&"' AS CHECK_ID, ROW_NUMBER, CASE WHEN A.ISSUES >0 THEN 1 ELSE 0 END AS "&B32&" FROM (SELECT COUNT(*) AS ISSUES FROM "&M32&" WHERE "&M32&"."&D32&" IS MISSING AND c0350 = 'Other') AS A;" -> ,SELECT 'B02' AS TAB, 'HIGH' AS ALERT_TYPE, 'v_1_0030' AS CHECK_ID, ROW_NUMBER, CASE WHEN A.ISSUES >0 THEN 1 ELSE 0 END AS v_1_0030 FROM (SELECT COUNT(*) AS ISSUES FROM B02 WHERE B02.0351 IS MISSING AND c0350 = 'Other') AS A; | V32: =+",CASE WHEN "&N32&" IS MISSING AND "&P32&" = 'Other' THEN 1 ELSE 0 END AS "&B32 -> ,CASE WHEN `0351_typ_clltrl_othr` IS MISSING AND `0350_typ_clltrl` = 'Other' THEN 1 ELSE 0 END AS v_1_0030 | W32: =+"SUM("&B32&") AS LVL1_H_"&MID(N32,2,LEN(N32)-2)&"," -> SUM(v_1_0030) AS LVL1_H_0351_typ_clltrl_othr,
A33: 0031 | B33: =CONCATENATE("v_1_",A33) -> v_1_0031 | C33: B02.00 | D33: =VLOOKUP(CONCATENATE(C33,"_",E33),'Data types'!A:E,4,FALSE) -> 0370 | E33: Denomination / Nominal value per security in EUR | F33: =VLOOKUP(CONCATENATE(C33,"_",E33),'Data types'!A:F,6,FALSE) -> Numeric: 2 decimals | G33: X | I33: Test for missing values. | J33: Rule applicable only if c0040 = "ISIN" and c0360 = "Nominal" | K33: Missing value. The field must be reported for securities with trading-method = "Nominal". | L33: =+IF(G33="X","HIGH","WARNING") -> HIGH | M33: =+LEFT(C33,3) -> B02 | N33: ="`"&VLOOKUP(D33,'B02_Mapping fields'!B:C,2,FALSE)&"`" -> `0370_amnt_scrty_eur` | O33: 0040 | P33: ="`"&VLOOKUP(O33,'B02_Mapping fields'!B:C,2,FALSE)&"`" -> `0040_typ_uniq_id_knwn_cntrprty` | Q33: 0360 | R33: ="`"&VLOOKUP(Q33,'B02_Mapping fields'!B:C,2,FALSE)&"`" -> `0360_trdng_mthd` | U33: =+",SELECT '"&M33&"' AS TAB, '"&L33&"' AS ALERT_TYPE, '"&B33&"' AS CHECK_ID, ROW_NUMBER, CASE WHEN A.ISSUES >0 THEN 1 ELSE 0 END AS "&B33&" FROM (SELECT COUNT(*) AS ISSUES FROM "&M33&" WHERE "&M33&"."&D33&" IS MISSING AND c0040 = 'ISIN' AND c0360 = 'Nominal') AS A;" -> ,SELECT 'B02' AS TAB, 'HIGH' AS ALERT_TYPE, 'v_1_0031' AS CHECK_ID, ROW_NUMBER, CASE WHEN A.ISSUES >0 THEN 1 ELSE 0 END AS v_1_0031 FROM (SELECT COUNT(*) AS ISSUES FROM B02 WHERE B02.0370 IS MISSING AND c0040 = 'ISIN' AND c0360 = 'Nominal') AS A; | V33: =+",CASE WHEN "&N33&" IS MISSING AND "&P33&" = 'ISIN' AND "&R33&" = 'Nominal' THEN 1 ELSE 0 END AS "&B33 -> ,CASE WHEN `0370_amnt_scrty_eur` IS MISSING AND `0040_typ_uniq_id_knwn_cntrprty` = 'ISIN' AND `0360_trdng_mthd` = 'Nominal' THEN 1 ELSE 0 END AS v_1_0031 | W33: =+"SUM("&B33&") AS LVL1_H_"&MID(N33,2,LEN(N33)-2)&"," -> SUM(v_1_0031) AS LVL1_H_0370_amnt_scrty_eur,
A34: 0032 | B34: =CONCATENATE("v_1_",A34) -> v_1_0032 | C34: B02.00 | D34: =VLOOKUP(CONCATENATE(C34,"_",E34),'Data types'!A:E,4,FALSE) -> 0370 | E34: Denomination / Nominal value per security in EUR | F34: =VLOOKUP(CONCATENATE(C34,"_",E34),'Data types'!A:F,6,FALSE) -> Numeric: 2 decimals | H34: X | J34: Rule applicable only if c0040 = "ISIN" and c0360 = "Unit" | K34: Missing value (warning only). The field should be reported for securities with trading-method = "Unit" if the information exists. | L34: =+IF(G34="X","HIGH","WARNING") -> WARNING | M34: =+LEFT(C34,3) -> B02 | N34: ="`"&VLOOKUP(D34,'B02_Mapping fields'!B:C,2,FALSE)&"`" -> `0370_amnt_scrty_eur` | O34: 0040 | P34: ="`"&VLOOKUP(O34,'B02_Mapping fields'!B:C,2,FALSE)&"`" -> `0040_typ_uniq_id_knwn_cntrprty` | Q34: 0360 | R34: ="`"&VLOOKUP(Q34,'B02_Mapping fields'!B:C,2,FALSE)&"`" -> `0360_trdng_mthd` | U34: =+",SELECT '"&M34&"' AS TAB, '"&L34&"' AS ALERT_TYPE, '"&B34&"' AS CHECK_ID, ROW_NUMBER, CASE WHEN A.ISSUES >0 THEN 1 ELSE 0 END AS "&B34&" FROM (SELECT COUNT(*) AS ISSUES FROM "&M34&" WHERE "&M34&"."&D34&" IS MISSING AND c0040 = 'ISIN' AND c0360 = 'Unit') AS A;" -> ,SELECT 'B02' AS TAB, 'WARNING' AS ALERT_TYPE, 'v_1_0032' AS CHECK_ID, ROW_NUMBER, CASE WHEN A.ISSUES >0 THEN 1 ELSE 0 END AS v_1_0032 FROM (SELECT COUNT(*) AS ISSUES FROM B02 WHERE B02.0370 IS MISSING AND c0040 = 'ISIN' AND c0360 = 'Unit') AS A; | V34: =+",CASE WHEN "&N34&" IS MISSING AND "&P34&" = 'ISIN' AND "&R34&" = 'Unit' THEN 1 ELSE 0 END AS "&B34 -> ,CASE WHEN `0370_amnt_scrty_eur` IS MISSING AND `0040_typ_uniq_id_knwn_cntrprty` = 'ISIN' AND `0360_trdng_mthd` = 'Unit' THEN 1 ELSE 0 END AS v_1_0032 | W34: =+"SUM("&B34&") AS LVL1_W_"&MID(N34,2,LEN(N34)-2)&"," -> SUM(v_1_0032) AS LVL1_W_0370_amnt_scrty_eur,
A35: 0033 | B35: =CONCATENATE("v_1_",A35) -> v_1_0033 | C35: B02.00 | D35: =VLOOKUP(CONCATENATE(C35,"_",E35),'Data types'!A:E,4,FALSE) -> 0390 | E35: Number of securities outstanding not held by the reporting entity | F35: =VLOOKUP(CONCATENATE(C35,"_",E35),'Data types'!A:F,6,FALSE) -> Numeric: Integer | G35: X | I35: Test for missing values. | J35: Rule applicable only if c0040 = "ISIN". | K35: Missing value. The field must be reported when c0040 = "ISIN". If the value is zero, "0" must be entered. | L35: =+IF(G35="X","HIGH","WARNING") -> HIGH | M35: =+LEFT(C35,3) -> B02 | N35: ="`"&VLOOKUP(D35,'B02_Mapping fields'!B:C,2,FALSE)&"`" -> `0390_nmbr_scrts_not_rprtng_entty` | O35: 0040 | P35: ="`"&VLOOKUP(O35,'B02_Mapping fields'!B:C,2,FALSE)&"`" -> `0040_typ_uniq_id_knwn_cntrprty` | U35: =+",SELECT '"&M35&"' AS TAB, '"&L35&"' AS ALERT_TYPE, '"&B35&"' AS CHECK_ID, ROW_NUMBER, CASE WHEN A.ISSUES >0 THEN 1 ELSE 0 END AS "&B35&" FROM (SELECT COUNT(*) AS ISSUES FROM "&M35&" WHERE "&M35&"."&D35&" IS MISSING AND c0040 = 'ISIN') AS A;" -> ,SELECT 'B02' AS TAB, 'HIGH' AS ALERT_TYPE, 'v_1_0033' AS CHECK_ID, ROW_NUMBER, CASE WHEN A.ISSUES >0 THEN 1 ELSE 0 END AS v_1_0033 FROM (SELECT COUNT(*) AS ISSUES FROM B02 WHERE B02.0390 IS MISSING AND c0040 = 'ISIN') AS A; | V35: =+",CASE WHEN "&N35&" IS MISSING AND "&P35&" = 'ISIN' THEN 1 ELSE 0 END AS "&B35 -> ,CASE WHEN `0390_nmbr_scrts_not_rprtng_entty` IS MISSING AND `0040_typ_uniq_id_knwn_cntrprty` = 'ISIN' THEN 1 ELSE 0 END AS v_1_0033 | W35: =+"SUM("&B35&") AS LVL1_H_"&MID(N35,2,LEN(N35)-2)&"," -> SUM(v_1_0033) AS LVL1_H_0390_nmbr_scrts_not_rprtng_entty,
A36: 0034 | B36: =CONCATENATE("v_1_",A36) -> v_1_0034 | C36: B02.00 | D36: =VLOOKUP(CONCATENATE(C36,"_",E36),'Data types'!A:E,4,FALSE) -> 0391 | E36: Number of securities outstanding held by the reporting entity | F36: =VLOOKUP(CONCATENATE(C36,"_",E36),'Data types'!A:F,6,FALSE) -> Numeric: Integer | G36: X | I36: Test for missing values. | J36: Rule applicable only if c0040 = "ISIN". | K36: Missing value. The field must be reported for securities. If the value is zero, "0" must be entered. | L36: =+IF(G36="X","HIGH","WARNING") -> HIGH | M36: =+LEFT(C36,3) -> B02 | N36: ="`"&VLOOKUP(D36,'B02_Mapping fields'!B:C,2,FALSE)&"`" -> `0391_nmbr_scrts_rprtng_entty` | O36: 0040 | P36: ="`"&VLOOKUP(O36,'B02_Mapping fields'!B:C,2,FALSE)&"`" -> `0040_typ_uniq_id_knwn_cntrprty` | U36: =+",SELECT '"&M36&"' AS TAB, '"&L36&"' AS ALERT_TYPE, '"&B36&"' AS CHECK_ID, ROW_NUMBER, CASE WHEN A.ISSUES >0 THEN 1 ELSE 0 END AS "&B36&" FROM (SELECT COUNT(*) AS ISSUES FROM "&M36&" WHERE "&M36&"."&D36&" IS MISSING AND c0040 = 'ISIN') AS A;" -> ,SELECT 'B02' AS TAB, 'HIGH' AS ALERT_TYPE, 'v_1_0034' AS CHECK_ID, ROW_NUMBER, CASE WHEN A.ISSUES >0 THEN 1 ELSE 0 END AS v_1_0034 FROM (SELECT COUNT(*) AS ISSUES FROM B02 WHERE B02.0391 IS MISSING AND c0040 = 'ISIN') AS A; | V36: =+",CASE WHEN "&N36&" IS MISSING AND "&P36&" = 'ISIN' THEN 1 ELSE 0 END AS "&B36 -> ,CASE WHEN `0391_nmbr_scrts_rprtng_entty` IS MISSING AND `0040_typ_uniq_id_knwn_cntrprty` = 'ISIN' THEN 1 ELSE 0 END AS v_1_0034 | W36: =+"SUM("&B36&") AS LVL1_H_"&MID(N36,2,LEN(N36)-2)&"," -> SUM(v_1_0034) AS LVL1_H_0391_nmbr_scrts_rprtng_entty,
A37: 0035 | B37: =CONCATENATE("v_1_",A37) -> v_1_0035 | C37: B02.00 | D37: =VLOOKUP(CONCATENATE(C37,"_",E37),'Data types'!A:E,4,FALSE) -> 0400 | E37: Accrued interest per security | F37: =VLOOKUP(CONCATENATE(C37,"_",E37),'Data types'!A:F,6,FALSE) -> Numeric: 4 decimals | G37: X | I37: Test for missing values. | J37: Rule applicable if c0040 = "ISIN", c0250 = ("Non-Structured/Vanilla" OR "Other non-standard terms) AND c0240 != "ZCB issued at discount" | K37: Missing value. The field must be reported for non-structured securities that are not zero coupon bonds issued at discount. | L37: =+IF(G37="X","HIGH","WARNING") -> HIGH | M37: =+LEFT(C37,3) -> B02 | N37: ="`"&VLOOKUP(D37,'B02_Mapping fields'!B:C,2,FALSE)&"`" -> `0400_accrd_intrst_scrty` | O37: 0040 | P37: ="`"&VLOOKUP(O37,'B02_Mapping fields'!B:C,2,FALSE)&"`" -> `0040_typ_uniq_id_knwn_cntrprty` | Q37: 0250 | R37: ="`"&VLOOKUP(Q37,'B02_Mapping fields'!B:C,2,FALSE)&"`" -> `0250_strctrd_prdct` | S37: 0240 | T37: ="`"&VLOOKUP(S37,'B02_Mapping fields'!B:C,2,FALSE)&"`" -> `0240_zero_coupon` | U37: =+",SELECT '"&M37&"' AS TAB, '"&L37&"' AS ALERT_TYPE, '"&B37&"' AS CHECK_ID, ROW_NUMBER, CASE WHEN A.ISSUES >0 THEN 1 ELSE 0 END AS "&B37&" FROM (SELECT COUNT(*) AS ISSUES FROM "&M37&" WHERE "&M37&"."&D37&" IS MISSING AND c0250 IN ('Non-Structured/Vanilla', 'Other non-standard terms') AND c0240 != 'ZCB issued at discount') AS A;" -> ,SELECT 'B02' AS TAB, 'HIGH' AS ALERT_TYPE, 'v_1_0035' AS CHECK_ID, ROW_NUMBER, CASE WHEN A.ISSUES >0 THEN 1 ELSE 0 END AS v_1_0035 FROM (SELECT COUNT(*) AS ISSUES FROM B02 WHERE B02.0400 IS MISSING AND c0250 IN ('Non-Structured/Vanilla', 'Other non-standard terms') AND c0240 != 'ZCB issued at discount') AS A; | V37: =+",CASE WHEN "&N37&" IS MISSING AND "&P37&" = 'ISIN' AND "&R37&" IN ('Non-Structured/Vanilla', 'Other non-standard terms') AND "&T37&" != 'ZCB issued at discount' THEN 1 ELSE 0 END AS "&B37 -> ,CASE WHEN `0400_accrd_intrst_scrty` IS MISSING AND `0040_typ_uniq_id_knwn_cntrprty` = 'ISIN' AND `0250_strctrd_prdct` IN ('Non-Structured/Vanilla', 'Other non-standard terms') AND `0240_zero_coupon` != 'ZCB issued at discount' THEN 1 ELSE 0 END AS v_1_0035 | W37: =+"SUM("&B37&") AS LVL1_H_"&MID(N37,2,LEN(N37)-2)&"," -> SUM(v_1_0035) AS LVL1_H_0400_accrd_intrst_scrty,
A38: 0036 | B38: =CONCATENATE("v_1_",A38) -> v_1_0036 | C38: B02.00 | D38: =VLOOKUP(CONCATENATE(C38,"_",E38),'Data types'!A:E,4,FALSE) -> 0400 | E38: Accrued interest per security | F38: =VLOOKUP(CONCATENATE(C38,"_",E38),'Data types'!A:F,6,FALSE) -> Numeric: 4 decimals | H38: X | I38: Test for missing values. | J38: Rule applicable if c0040 = "ISIN", c0250 != ("Structured" OR "Only structured coupon") | K38: Missing value (warning only). This field must be reported for structured securities if the information exists. | L38: =+IF(G38="X","HIGH","WARNING") -> WARNING | M38: =+LEFT(C38,3) -> B02 | N38: ="`"&VLOOKUP(D38,'B02_Mapping fields'!B:C,2,FALSE)&"`" -> `0400_accrd_intrst_scrty` | O38: 0040 | P38: ="`"&VLOOKUP(O38,'B02_Mapping fields'!B:C,2,FALSE)&"`" -> `0040_typ_uniq_id_knwn_cntrprty` | Q38: 0250 | R38: ="`"&VLOOKUP(Q38,'B02_Mapping fields'!B:C,2,FALSE)&"`" -> `0250_strctrd_prdct` | U38: =+",SELECT '"&M38&"' AS TAB, '"&L38&"' AS ALERT_TYPE, '"&B38&"' AS CHECK_ID, ROW_NUMBER, CASE WHEN A.ISSUES >0 THEN 1 ELSE 0 END AS "&B38&" FROM (SELECT COUNT(*) AS ISSUES FROM "&M38&" WHERE "&M38&"."&D38&" IS MISSING AND c0040 = 'ISIN' AND c0250 NOT IN ('Structured', 'Only structured coupon')) AS A;" -> ,SELECT 'B02' AS TAB, 'WARNING' AS ALERT_TYPE, 'v_1_0036' AS CHECK_ID, ROW_NUMBER, CASE WHEN A.ISSUES >0 THEN 1 ELSE 0 END AS v_1_0036 FROM (SELECT COUNT(*) AS ISSUES FROM B02 WHERE B02.0400 IS MISSING AND c0040 = 'ISIN' AND c0250 NOT IN ('Structured', 'Only structured coupon')) AS A; | V38: =+",CASE WHEN "&N38&" IS MISSING AND "&P38&" = 'ISIN' AND "&R38&" NOT IN ('Structured', 'Only structured coupon') THEN 1 ELSE 0 END AS "&B38 -> ,CASE WHEN `0400_accrd_intrst_scrty` IS MISSING AND `0040_typ_uniq_id_knwn_cntrprty` = 'ISIN' AND `0250_strctrd_prdct` NOT IN ('Structured', 'Only structured coupon') THEN 1 ELSE 0 END AS v_1_0036 | W38: =+"SUM("&B38&") AS LVL1_W_"&MID(N38,2,LEN(N38)-2)&"," -> SUM(v_1_0036) AS LVL1_W_0400_accrd_intrst_scrty,
A39: 0037 | B39: =CONCATENATE("v_1_",A39) -> v_1_0037 | C39: B02.00 | D39: =VLOOKUP(CONCATENATE(C39,"_",E39),'Data types'!A:E,4,FALSE) -> 0610 | E39: Carrying amount IFRS | F39: =VLOOKUP(CONCATENATE(C39,"_",E39),'Data types'!A:F,6,FALSE) -> Numeric: 2 decimals | H39: X | I39: Test for missing values. | K39: Missing value (warning only). The field must be reported if the information exists, i.e. the entity reports in IFRS. | L39: =+IF(G39="X","HIGH","WARNING") -> WARNING | M39: =+LEFT(C39,3) -> B02 | N39: ="`"&VLOOKUP(D39,'B02_Mapping fields'!B:C,2,FALSE)&"`" -> `0610_crryng_amnt_ifrs` | U39: =+",SELECT '"&M39&"' AS TAB, '"&L39&"' AS ALERT_TYPE, '"&B39&"' AS CHECK_ID, ROW_NUMBER, CASE WHEN A.ISSUES >0 THEN 1 ELSE 0 END AS "&B39&" FROM (SELECT COUNT(*) AS ISSUES FROM "&M39&" WHERE "&M39&"."&D39&" IS MISSING) AS A;" -> ,SELECT 'B02' AS TAB, 'WARNING' AS ALERT_TYPE, 'v_1_0037' AS CHECK_ID, ROW_NUMBER, CASE WHEN A.ISSUES >0 THEN 1 ELSE 0 END AS v_1_0037 FROM (SELECT COUNT(*) AS ISSUES FROM B02 WHERE B02.0610 IS MISSING) AS A; | V39: =+",CASE WHEN "&N39&" IS MISSING THEN 1 ELSE 0 END AS "&B39 -> ,CASE WHEN `0610_crryng_amnt_ifrs` IS MISSING THEN 1 ELSE 0 END AS v_1_0037 | W39: =+"SUM("&B39&") AS LVL1_W_"&MID(N39,2,LEN(N39)-2)&"," -> SUM(v_1_0037) AS LVL1_W_0610_crryng_amnt_ifrs,
A40: 0038 | B40: =CONCATENATE("v_1_",A40) -> v_1_0038 | C40: B02.00 | D40: =VLOOKUP(CONCATENATE(C40,"_",E40),'Data types'!A:E,4,FALSE) -> 5000 | E40: Instrument/liability is issued to or bought by an existing shareholder that is not part of the same resolution group | F40: =VLOOKUP(CONCATENATE(C40,"_",E40),'Data types'!A:F,6,FALSE) -> String: TRUE / FALSE boolean | G40: X | I40: Test for missing values. | J40: if {B99.00;c0060} = "Non-Resolution Entity" | K40: Missing value. The field must be reported for Non-Resolution Entities. | L40: =+IF(G40="X","HIGH","WARNING") -> HIGH | M40: =+LEFT(C40,3) -> B02 | N40: ="`"&VLOOKUP(D40,'B02_Mapping fields'!B:C,2,FALSE)&"`" -> `5000_flg_shrhldr_not_rsltn_grp` | O40: 0060 | P40: ="`"&VLOOKUP(O40,'B02_Mapping fields'!B:C,2,FALSE)&"`" -> `0060_orgnl_amnt_fx` | V40: =+",CASE WHEN "&N40&" IS MISSING AND B99."&P40&" = 'Non-Resolution Entity' THEN 1 ELSE 0 END AS "&B40 -> ,CASE WHEN `5000_flg_shrhldr_not_rsltn_grp` IS MISSING AND B99.`0060_orgnl_amnt_fx` = 'Non-Resolution Entity' THEN 1 ELSE 0 END AS v_1_0038 | W40: =+"SUM("&B40&") AS LVL1_H_"&MID(N40,2,LEN(N40)-2)&"," -> SUM(v_1_0038) AS LVL1_H_5000_flg_shrhldr_not_rsltn_grp, | X40: --> Requer left join com B99 filtrado por c0011 por B02.00 e usando c0020 como chave
A41: 0039 | B41: =CONCATENATE("v_1_",A41) -> v_1_0039 | C41: B02.00 | D41: =VLOOKUP(CONCATENATE(C41,"_",E41),'Data types'!A:E,4,FALSE) -> 5010 | E41: Instrument/liability meets the requirements of Art. 21(7a) SRMR | F41: =VLOOKUP(CONCATENATE(C41,"_",E41),'Data types'!A:F,6,FALSE) -> String: TRUE / FALSE boolean | G41: X | I41: Test for missing values. | J41: if {B99.00;c0060} = "Non-Resolution Entity" | K41: Missing value. The field must be reported for Non-Resolution Entities. | L41: =+IF(G41="X","HIGH","WARNING") -> HIGH | M41: =+LEFT(C41,3) -> B02 | N41: ="`"&VLOOKUP(D41,'B02_Mapping fields'!B:C,2,FALSE)&"`" -> `5010_flg_art21_7a_srmr` | O41: 0060 | P41: ="`"&VLOOKUP(O41,'B02_Mapping fields'!B:C,2,FALSE)&"`" -> `0060_orgnl_amnt_fx` | V41: =+",CASE WHEN "&N41&" IS MISSING AND B99."&P41&" = 'Non-Resolution Entity' THEN 1 ELSE 0 END AS "&B41 -> ,CASE WHEN `5010_flg_art21_7a_srmr` IS MISSING AND B99.`0060_orgnl_amnt_fx` = 'Non-Resolution Entity' THEN 1 ELSE 0 END AS v_1_0039 | W41: =+"SUM("&B41&") AS LVL1_H_"&MID(N41,2,LEN(N41)-2)&"," -> SUM(v_1_0039) AS LVL1_H_5010_flg_art21_7a_srmr, | X41: --> Requer left join com B99 filtrado por c0011 por B02.00 e usando c0020 como chave
A42: 0040 | B42: =CONCATENATE("v_1_",A42) -> v_1_0040 | C42: B03.00 | D42: =VLOOKUP(CONCATENATE(C42,"_",E42),'Data types'!A:E,4,FALSE) -> 0010 | E42: Row number | F42: =VLOOKUP(CONCATENATE(C42,"_",E42),'Data types'!A:F,6,FALSE) -> Numeric: Integer | G42: X | I42: Test for missing values. | K42: Missing value. The field must be reported. | L42: =+IF(G42="X","HIGH","WARNING") -> HIGH | M42: =+LEFT(C42,3) -> B03 | W42: =+"SUM("&B42&") AS "&N42&"," -> SUM(v_1_0040) AS ,
A43: 0042 | B43: =CONCATENATE("v_1_",A43) -> v_1_0042 | C43: B03.00 | D43: =VLOOKUP(CONCATENATE(C43,"_",E43),'Data types'!A:E,4,FALSE) -> 0020 | E43: Unique identification number of the netting set known to the counterparty | F43: =VLOOKUP(CONCATENATE(C43,"_",E43),'Data types'!A:F,6,FALSE) -> String: Free text | G43: X | I43: Test for missing values. | K43: Missing value. The field must be reported. | L43: =+IF(G43="X","HIGH","WARNING") -> HIGH | M43: =+LEFT(C43,3) -> B03 | W43: =+"SUM("&B43&") AS "&N43&"," -> SUM(v_1_0042) AS ,
A44: 0043 | B44: =CONCATENATE("v_1_",A44) -> v_1_0043 | C44: B03.00 | D44: =VLOOKUP(CONCATENATE(C44,"_",E44),'Data types'!A:E,4,FALSE) -> 0030 | E44: Insolvency ranking | F44: =VLOOKUP(CONCATENATE(C44,"_",E44),'Data types'!A:F,6,FALSE) -> Numeric: Integer | G44: X | I44: Test for missing values. | K44: Missing value. The field must be reported. | L44: =+IF(G44="X","HIGH","WARNING") -> HIGH | M44: =+LEFT(C44,3) -> B03 | W44: =+"SUM("&B44&") AS "&N44&"," -> SUM(v_1_0043) AS ,
A45: 0044 | B45: =CONCATENATE("v_1_",A45) -> v_1_0044 | C45: B03.00 | D45: =VLOOKUP(CONCATENATE(C45,"_",E45),'Data types'!A:E,4,FALSE) -> 0060 | E45: Master agreement ID | F45: =VLOOKUP(CONCATENATE(C45,"_",E45),'Data types'!A:F,6,FALSE) -> String: Free text | G45: X | I45: Test for missing values. | K45: Missing value. The field must be reported. | L45: =+IF(G45="X","HIGH","WARNING") -> HIGH | M45: =+LEFT(C45,3) -> B03 | W45: =+"SUM("&B45&") AS "&N45&"," -> SUM(v_1_0044) AS ,
A46: 0045 | B46: =CONCATENATE("v_1_",A46) -> v_1_0045 | C46: B03.00 | D46: =VLOOKUP(CONCATENATE(C46,"_",E46),'Data types'!A:E,4,FALSE) -> 0070 | E46: Governing law of the Master agreement | F46: =VLOOKUP(CONCATENATE(C46,"_",E46),'Data types'!A:F,6,FALSE) -> String: ISO 3166-1 alpha 2 / ISO 3166-2 | G46: X | I46: Test for missing values. | K46: Missing value. The field must be reported. | L46: =+IF(G46="X","HIGH","WARNING") -> HIGH | M46: =+LEFT(C46,3) -> B03 | W46: =+"SUM("&B46&") AS "&N46&"," -> SUM(v_1_0045) AS ,
A47: 0046 | B47: =CONCATENATE("v_1_",A47) -> v_1_0046 | C47: B03.00 | D47: =VLOOKUP(CONCATENATE(C47,"_",E47),'Data types'!A:E,4,FALSE) -> 0080 | E47: Net mark-to-market value | F47: =VLOOKUP(CONCATENATE(C47,"_",E47),'Data types'!A:F,6,FALSE) -> Numeric: 2 decimals | G47: X | I47: Test for missing values. | K47: Missing value. The field must be reported. | L47: =+IF(G47="X","HIGH","WARNING") -> HIGH | M47: =+LEFT(C47,3) -> B03 | W47: =+"SUM("&B47&") AS "&N47&"," -> SUM(v_1_0046) AS ,
A48: 0047 | B48: =CONCATENATE("v_1_",A48) -> v_1_0047 | C48: B03.00 | D48: =VLOOKUP(CONCATENATE(C48,"_",E48),'Data types'!A:E,4,FALSE) -> 0110 | E48: Estimated early termination amount | F48: =VLOOKUP(CONCATENATE(C48,"_",E48),'Data types'!A:F,6,FALSE) -> Numeric: 2 decimals | G48: X | I48: Test for missing values. | K48: Missing value. The field must be reported. | L48: =+IF(G48="X","HIGH","WARNING") -> HIGH | M48: =+LEFT(C48,3) -> B03 | W48: =+"SUM("&B48&") AS "&N48&"," -> SUM(v_1_0047) AS ,
A49: 0048 | B49: =CONCATENATE("v_1_",A49) -> v_1_0048 | C49: B03.00 | D49: =VLOOKUP(CONCATENATE(C49,"_",E49),'Data types'!A:E,4,FALSE) -> 0120 | E49: CCP cleared | F49: =VLOOKUP(CONCATENATE(C49,"_",E49),'Data types'!A:F,6,FALSE) -> String: TRUE / FALSE boolean | G49: X | I49: Test for missing values. | K49: Missing value. The field must be reported. | L49: =+IF(G49="X","HIGH","WARNING") -> HIGH | M49: =+LEFT(C49,3) -> B03 | W49: =+"SUM("&B49&") AS "&N49&"," -> SUM(v_1_0048) AS ,
A50: 0049 | B50: =CONCATENATE("v_1_",A50) -> v_1_0049 | C50: B04.00 | D50: =VLOOKUP(CONCATENATE(C50,"_",E50),'Data types'!A:E,4,FALSE) -> 0010 | E50: Row number | F50: =VLOOKUP(CONCATENATE(C50,"_",E50),'Data types'!A:F,6,FALSE) -> Numeric: Integer | G50: X | I50: Test for missing values. | K50: Missing value. The field must be reported. | L50: =+IF(G50="X","HIGH","WARNING") -> HIGH | M50: =+LEFT(C50,3) -> B04 | W50: =+"SUM("&B50&") AS "&N50&"," -> SUM(v_1_0049) AS ,
A51: 0051 | B51: =CONCATENATE("v_1_",A51) -> v_1_0051 | C51: B04.00 | D51: =VLOOKUP(CONCATENATE(C51,"_",E51),'Data types'!A:E,4,FALSE) -> 0020 | E51: Unique identification number of the netting set known to the counterparty | F51: =VLOOKUP(CONCATENATE(C51,"_",E51),'Data types'!A:F,6,FALSE) -> String: Free text | G51: X | I51: Test for missing values. | K51: Missing value. The field must be reported. | L51: =+IF(G51="X","HIGH","WARNING") -> HIGH | M51: =+LEFT(C51,3) -> B04 | W51: =+"SUM("&B51&") AS "&N51&"," -> SUM(v_1_0051) AS ,
A52: 0052 | B52: =CONCATENATE("v_1_",A52) -> v_1_0052 | C52: B04.00 | D52: =VLOOKUP(CONCATENATE(C52,"_",E52),'Data types'!A:E,4,FALSE) -> 0030 | E52: Insolvency ranking | F52: =VLOOKUP(CONCATENATE(C52,"_",E52),'Data types'!A:F,6,FALSE) -> Numeric: Integer | G52: X | I52: Test for missing values. | K52: Missing value. The field must be reported. | L52: =+IF(G52="X","HIGH","WARNING") -> HIGH | M52: =+LEFT(C52,3) -> B04 | W52: =+"SUM("&B52&") AS "&N52&"," -> SUM(v_1_0052) AS ,
A53: 0053 | B53: =CONCATENATE("v_1_",A53) -> v_1_0053 | C53: B04.00 | D53: =VLOOKUP(CONCATENATE(C53,"_",E53),'Data types'!A:E,4,FALSE) -> 0040 | E53: Master agreement ID | F53: =VLOOKUP(CONCATENATE(C53,"_",E53),'Data types'!A:F,6,FALSE) -> String: Free text | G53: X | I53: Test for missing values. | K53: Missing value. The field must be reported. | L53: =+IF(G53="X","HIGH","WARNING") -> HIGH | M53: =+LEFT(C53,3) -> B04 | W53: =+"SUM("&B53&") AS "&N53&"," -> SUM(v_1_0053) AS ,
... A55: 0055 | B55: =CONCATENATE("v_1_",A55) -> v_1_0055 | C55: B04.00 | D55: =VLOOKUP(CONCATENATE(C55,"_",E55),'Data types'!A:E,4,FALSE) -> 0060 | E55: Net mark-to-market value | F55: =VLOOKUP(CONCATENATE(C55,"_",E55),'Data types'!A:F,6,FALSE) -> Numeric: 2 decimals | G55: X | I55: Test for missing values. | K55: Missing value. The field must be reported. | L55: =+IF(G55="X","HIGH","WARNING") -> HIGH | M55: =+LEFT(C55,3) -> B04 | W55: =+"SUM("&B55&") AS "&N55&"," -> SUM(v_1_0055) AS ,
A56: 0056 | B56: =CONCATENATE("v_1_",A56) -> v_1_0056 | C56: B90.00 | D56: =VLOOKUP(CONCATENATE(C56,"_",E56),'Data types'!A:E,4,FALSE) -> 0030 | E56: Counterparty within the resolution group | F56: =VLOOKUP(CONCATENATE(C56,"_",E56),'Data types'!A:F,6,FALSE) -> String: Drop-down | G56: X | I56: Test for missing values. | K56: Missing value. The field must be reported. | L56: =+IF(G56="X","HIGH","WARNING") -> HIGH | M56: =+LEFT(C56,3) -> B90 | N56: ="`"&VLOOKUP(D56,'B90_Maping fields'!B:C,2,FALSE)&"`" -> `0030_cntrprty_rsltn_grp` | U56: =+",SELECT '"&M56&"' AS TAB, '"&L56&"' AS ALERT_TYPE, '"&B56&"' AS CHECK_ID, ROW_NUMBER, CASE WHEN A.ISSUES >0 THEN 1 ELSE 0 END AS "&B56&" FROM (SELECT COUNT(*) AS ISSUES FROM "&M56&" WHERE "&M56&"."&D56&" IS MISSING) AS A;" -> ,SELECT 'B90' AS TAB, 'HIGH' AS ALERT_TYPE, 'v_1_0056' AS CHECK_ID, ROW_NUMBER, CASE WHEN A.ISSUES >0 THEN 1 ELSE 0 END AS v_1_0056 FROM (SELECT COUNT(*) AS ISSUES FROM B90 WHERE B90.0030 IS MISSING) AS A; | V56: =+",CASE WHEN "&N56&" IS MISSING OR "&N56&"='' THEN 1 ELSE 0 END AS "&B56 -> ,CASE WHEN `0030_cntrprty_rsltn_grp` IS MISSING OR `0030_cntrprty_rsltn_grp`='' THEN 1 ELSE 0 END AS v_1_0056 | W56: =+"SUM("&B56&") AS LVL1_H_"&MID(N56,2,LEN(N56)-2)&"," -> SUM(v_1_0056) AS LVL1_H_0030_cntrprty_rsltn_grp,

Sheet Level 2
B1: Level 2 Validation Rules: internal consistency checks. | Y1: utilizar case when's
B2: Check ID | C2: Tab | D2: Data point (Row/Column) | E2: Data point (Label) | F2: Data point type | G2: High severity (i.e the validation rule should in general not be breached) | H2: Warning only (i.e. the validation rule can be breached in certain cases) | I2: Type of test | J2: Prerequisites | K2: Explanation | L2: AUX_ALERT | M2: AUX_TAB | N2: AUX_FIELD1 | O2: FIELD2 | P2: AUX_FIELD2 | Q2: FIELD3 | R2: AUX_FIELD3 | S2: FIELD4 | T2: AUX_FIELD4 | U2: FIELD5 | V2: AUX_FIELD5 | W2: FIELD6 | X2: AUX_FIELD6 | Y2: OPTION 2
A3: 0001 | B3: =CONCATENATE("v_2_",A3) -> v_2_0001 | C3: B02.00 | D3: =VLOOKUP(CONCATENATE(C3,"_",E3),'Data types'!A:E,4,FALSE) -> 0030 | E3: Unique identification number (known to the counterparty) | F3: =VLOOKUP(CONCATENATE(C3,"_",E3),'Data types'!A:F,6,FALSE) -> String: Free text | G3: X | I3: The field must have the characteristics of an ISIN, e.g., max. 12 characters and start with 2 letters signifying the ISO country code. | J3: c0040 = "ISIN" | K3: If the ID is an ISIN (c0030 = "ISIN"), then the ID reported in c0020 must have the characteristics of an ISIN, e.g. 12 characters and start with 2 letters signifying the ISO country code. | L3: =+IF(G3="X","HIGH","WARNING") -> HIGH | M3: =+LEFT(C3,3) -> B02 | N3: ="`"&VLOOKUP(D3,'B02_Mapping fields'!B:C,2,FALSE)&"`" -> `0030_uniq_id_knwn_cntrprty` | O3: 0040 | P3: ="`"&VLOOKUP(O3,'B02_Mapping fields'!B:C,2,FALSE)&"`" -> `0040_typ_uniq_id_knwn_cntrprty` | Y3: =+",CASE WHEN "&P3&" = 'ISIN' AND LENGTH("&N3&") = 12 AND SUBSTR("&N3&", 1, 1) RLIKE '^[A-Za-z]$' AND SUBSTR("&N3&", 2, 1) RLIKE '^[A-Za-z]$' THEN 0 ELSE 1 END AS "&B3 -> ,CASE WHEN `0040_typ_uniq_id_knwn_cntrprty` = 'ISIN' AND LENGTH(`0030_uniq_id_knwn_cntrprty`) = 12 AND SUBSTR(`0030_uniq_id_knwn_cntrprty`, 1, 1) RLIKE '^[A-Za-z]$' AND SUBSTR(`0030_uniq_id_knwn_cntrprty`, 2, 1) RLIKE '^[A-Za-z]$' THEN 0 ELSE 1 END AS v_2_0001 | Z3: =+"SUM("&B3&") AS LVL2_H_"&MID(N3,2,LEN(N3)-2)&"," -> SUM(v_2_0001) AS LVL2_H_0030_uniq_id_knwn_cntrprty,
A4: 0003 | B4: =CONCATENATE("v_2_",A4) -> v_2_0003 | C4: B02.00 | D4: =VLOOKUP(CONCATENATE(C4,"_",E4),'Data types'!A:E,4,FALSE) -> 0070 | E4: Contract Currency | F4: =VLOOKUP(CONCATENATE(C4,"_",E4),'Data types'!A:F,6,FALSE) -> String: 3-letters ISO 4217 | G4: X | I4: Check if the reported field respect the 3-letters ISO 4217 code. | J4: c0020 ≠ (NCNP OR NCBP) | K4: Currencies must be reported using the 3-letters ISO 4217 code. | L4: =+IF(G4="X","HIGH","WARNING") -> HIGH | M4: =+LEFT(C4,3) -> B02 | N4: ="`"&VLOOKUP(D4,'B02_Mapping fields'!B:C,2,FALSE)&"`" -> `0070_cntrct_crrncy` | O4: 0020 | P4: ="`"&VLOOKUP(O4,'B02_Mapping fields'!B:C,2,FALSE)&"`" -> `0020_uniq_id` | Y4: =+",CASE WHEN "&P4&" NOT IN ('NCNP', 'NCBP') AND LENGTH("&N4&") = 3 THEN 0 ELSE 1 END AS "&B4 -> ,CASE WHEN `0020_uniq_id` NOT IN ('NCNP', 'NCBP') AND LENGTH(`0070_cntrct_crrncy`) = 3 THEN 0 ELSE 1 END AS v_2_0003 | Z4: =+"SUM("&B4&") AS LVL2_H_"&MID(N4,2,LEN(N4)-2)&"," -> SUM(v_2_0003) AS LVL2_H_0070_cntrct_crrncy,
A5: 0004 | B5: =CONCATENATE("v_2_",A5) -> v_2_0004 | C5: B02.00 | D5: =VLOOKUP(CONCATENATE(C5,"_",E5),'Data types'!A:E,4,FALSE) -> 0080 | E5: Outstanding principal amount | F5: =VLOOKUP(CONCATENATE(C5,"_",E5),'Data types'!A:F,6,FALSE) -> Numeric: 2 decimals | H5: X | I5: Check if the reported field is higher than 0. | K5: The reported amount must in general be positive. | L5: =+IF(G5="X","HIGH","WARNING") -> WARNING | M5: =+LEFT(C5,3) -> B02 | N5: ="`"&VLOOKUP(D5,'B02_Mapping fields'!B:C,2,FALSE)&"`" -> `0080_otstndng_prncpl_amnt` | Y5: =+",CASE WHEN "&N5&" <=0 THEN 1 ELSE 0 END AS "&B5 -> ,CASE WHEN `0080_otstndng_prncpl_amnt` <=0 THEN 1 ELSE 0 END AS v_2_0004 | Z5: =+"SUM("&B5&") AS LVL2_W_"&MID(N5,2,LEN(N5)-2)&"," -> SUM(v_2_0004) AS LVL2_W_0080_otstndng_prncpl_amnt,
A6: 0005 | B6: =CONCATENATE("v_2_",A6) -> v_2_0005 | C6: B02.00 | D6: =VLOOKUP(CONCATENATE(C6,"_",E6),'Data types'!A:E,4,FALSE) -> 0090 | E6: Portion of instrument or liability held by the reporting entity | F6: =VLOOKUP(CONCATENATE(C6,"_",E6),'Data types'!A:F,6,FALSE) -> Numeric: 2 decimals | G6: X | I6: Check if the reported field is higher than or equal 0. | J6: c0040 = "ISIN" | K6: The reported amount must be positive or zero. | L6: =+IF(G6="X","HIGH","WARNING") -> HIGH | M6: =+LEFT(C6,3) -> B02 | N6: ="`"&VLOOKUP(D6,'B02_Mapping fields'!B:C,2,FALSE)&"`" -> `0090_prtn_amnt_rprtng_entty` | O6: 0040 | P6: ="`"&VLOOKUP(O6,'B02_Mapping fields'!B:C,2,FALSE)&"`" -> `0040_typ_uniq_id_knwn_cntrprty` | Y6: =+",CASE WHEN "&N6&" >=0 AND "&P6&" = 'ISIN' THEN 0 ELSE 1 END AS "&B6 -> ,CASE WHEN `0090_prtn_amnt_rprtng_entty` >=0 AND `0040_typ_uniq_id_knwn_cntrprty` = 'ISIN' THEN 0 ELSE 1 END AS v_2_0005 | Z6: =+"SUM("&B6&") AS LVL2_H_"&MID(N6,2,LEN(N6)-2)&"," -> SUM(v_2_0005) AS LVL2_H_0090_prtn_amnt_rprtng_entty,
A7: 0006 | B7: =CONCATENATE("v_2_",A7) -> v_2_0006 | C7: B02.00 | D7: =VLOOKUP(CONCATENATE(C7,"_",E7),'Data types'!A:E,4,FALSE) -> 0100 | E7: Accrued interest | F7: =VLOOKUP(CONCATENATE(C7,"_",E7),'Data types'!A:F,6,FALSE) -> Numeric: 2 decimals | H7: X | I7: Check if the reported field is higher than or equal 0. | K7: The reported amount should be positive or zero. However, negative accrued interests are in principle allowed, if duly justified by the reporting entity. | L7: =+IF(G7="X","HIGH","WARNING") -> WARNING | M7: =+LEFT(C7,3) -> B02 | N7: ="`"&VLOOKUP(D7,'B02_Mapping fields'!B:C,2,FALSE)&"`" -> `0100_accrd_intrst_instrmnt` | Y7: =+",CASE WHEN "&N7&" >=0 THEN 0 ELSE 1 END AS "&B7 -> ,CASE WHEN `0100_accrd_intrst_instrmnt` >=0 THEN 0 ELSE 1 END AS v_2_0006 | Z7: =+"SUM("&B7&") AS LVL2_W_"&MID(N7,2,LEN(N7)-2)&"," -> SUM(v_2_0006) AS LVL2_W_0100_accrd_intrst_instrmnt,
A8: 0007 | B8: =CONCATENATE("v_2_",A8) -> v_2_0007 | C8: B02.00 | D8: =VLOOKUP(CONCATENATE(C8,"_",E8),'Data types'!A:E,4,FALSE) -> 0110 | E8: Applicable fees and charges | F8: =VLOOKUP(CONCATENATE(C8,"_",E8),'Data types'!A:F,6,FALSE) -> Numeric: 2 decimals | H8: X | I8: Check if the reported field is higher than or equal 0. | K8: The reported amount should be in general positive or zero. | L8: =+IF(G8="X","HIGH","WARNING") -> WARNING | M8: =+LEFT(C8,3) -> B02 | N8: ="`"&VLOOKUP(D8,'B02_Mapping fields'!B:C,2,FALSE)&"`" -> `0110_applcbl_fees_charges` | Y8: =+",CASE WHEN "&N8&" >=0 THEN 0 ELSE 1 END AS "&B8 -> ,CASE WHEN `0110_applcbl_fees_charges` >=0 THEN 0 ELSE 1 END AS v_2_0007 | Z8: =+"SUM("&B8&") AS LVL2_W_"&MID(N8,2,LEN(N8)-2)&"," -> SUM(v_2_0007) AS LVL2_W_0110_applcbl_fees_charges,
A9: 0008 | B9: =CONCATENATE("v_2_",A9) -> v_2_0008 | C9: B02.00 | D9: =VLOOKUP(CONCATENATE(C9,"_",E9),'Data types'!A:E,4,FALSE) -> 0120 | E9: Outstanding amount | F9: =VLOOKUP(CONCATENATE(C9,"_",E9),'Data types'!A:F,6,FALSE) -> Numeric: 2 decimals | G9: X | I9: Check if the reported field is higher than 0. | K9: The reported amount should be positive. | L9: =+IF(G9="X","HIGH","WARNING") -> HIGH | M9: =+LEFT(C9,3) -> B02 | N9: ="`"&VLOOKUP(D9,'B02_Mapping fields'!B:C,2,FALSE)&"`" -> `0120_otstndng_amnt` | Y9: =+",CASE WHEN "&N9&" >=0 THEN 0 ELSE 1 END AS "&B9 -> ,CASE WHEN `0120_otstndng_amnt` >=0 THEN 0 ELSE 1 END AS v_2_0008 | Z9: =+"SUM("&B9&") AS LVL2_H_"&MID(N9,2,LEN(N9)-2)&"," -> SUM(v_2_0008) AS LVL2_H_0120_otstndng_amnt,
A10: 0009 | B10: =CONCATENATE("v_2_",A10) -> v_2_0009 | C10: B02.00 | D10: =VLOOKUP(CONCATENATE(C10,"_",E10),'Data types'!A:E,4,FALSE) -> 0120 | E10: Outstanding amount | F10: =VLOOKUP(CONCATENATE(C10,"_",E10),'Data types'!A:F,6,FALSE) -> Numeric: 2 decimals | G10: X | I10: Check if the reported field is equal to c0080 + c0100 + c0110. | K10: The reported amount should be equal to: c0080 + c0100 + c0110. | L10: =+IF(G10="X","HIGH","WARNING") -> HIGH | M10: =+LEFT(C10,3) -> B02 | N10: ="`"&VLOOKUP(D10,'B02_Mapping fields'!B:C,2,FALSE)&"`" -> `0120_otstndng_amnt` | O10: 0080 | P10: ="`"&VLOOKUP(O10,'B02_Mapping fields'!B:C,2,FALSE)&"`" -> `0080_otstndng_prncpl_amnt` | Q10: 0100 | R10: ="`"&VLOOKUP(Q10,'B02_Mapping fields'!B:C,2,FALSE)&"`" -> `0100_accrd_intrst_instrmnt` | S10: 0110 | T10: ="`"&VLOOKUP(S10,'B02_Mapping fields'!B:C,2,FALSE)&"`" -> `0110_applcbl_fees_charges` | Y10: =+",CASE WHEN "&N10&" = ("&P10&"+"&R10&"+"&T10&") THEN 0 ELSE 1 END AS "&B10 -> ,CASE WHEN `0120_otstndng_amnt` = (`0080_otstndng_prncpl_amnt`+`0100_accrd_intrst_instrmnt`+`0110_applcbl_fees_charges`) THEN 0 ELSE 1 END AS v_2_0009 | Z10: =+"SUM("&B10&") AS LVL2_H_"&MID(N10,2,LEN(N10)-2)&"," -> SUM(v_2_0009) AS LVL2_H_0120_otstndng_amnt,
A11: 0011 | B11: =CONCATENATE("v_2_",A11) -> v_2_0011 | C11: B02.00 | D11: =VLOOKUP(CONCATENATE(C11,"_",E11),'Data types'!A:E,4,FALSE) -> 0130 | E11: Relevant amount for Bail-in/WDC | F11: =VLOOKUP(CONCATENATE(C11,"_",E11),'Data types'!A:F,6,FALSE) -> Numeric: 2 decimals | G11: X | I11: Check if the reported field is equal to of: max{0, c0120 - c0300 - c0320}. | J11: c0250 = ("Non-structured/Vanilla" OR "Other non-standard terms") & c0240 != "ZCB issued at discount" | K11: The reported amount should be equal to: c0120 - c0300 - c0320, besides for Zero Coupon Bonds for which specific provisions may apply. | L11: =+IF(G11="X","HIGH","WARNING") -> HIGH | M11: =+LEFT(C11,3) -> B02 | N11: ="`"&VLOOKUP(D11,'B02_Mapping fields'!B:C,2,FALSE)&"`" -> `0130_rlvnt_amnt_wdc` | O11: 0250 | P11: ="`"&VLOOKUP(O11,'B02_Mapping fields'!B:C,2,FALSE)&"`" -> `0250_strctrd_prdct` | Q11: 0240 | R11: ="`"&VLOOKUP(Q11,'B02_Mapping fields'!B:C,2,FALSE)&"`" -> `0240_zero_coupon` | S11: 0120 | T11: ="`"&VLOOKUP(S11,'B02_Mapping fields'!B:C,2,FALSE)&"`" -> `0120_otstndng_amnt` | U11: 0300 | V11: ="`"&VLOOKUP(U11,'B02_Mapping fields'!B:C,2,FALSE)&"`" -> `0300_amnt_cvrd_elgbl_dpsts` | W11: 0320 | X11: ="`"&VLOOKUP(W11,'B02_Mapping fields'!B:C,2,FALSE)&"`" -> `0320_amnt_clltrl` | Y11: =+",CASE WHEN "&N11&" = MAX(0, "&T11&"-"&V11&"-"&X11&") AND "&P11&" IN ('Non-structured/Vanilla', 'Other non-standard terms') AND "&R11&" != 'ZCB issued at discount' THEN 0 ELSE 1 END AS "&B11 -> ,CASE WHEN `0130_rlvnt_amnt_wdc` = MAX(0, `0120_otstndng_amnt`-`0300_amnt_cvrd_elgbl_dpsts`-`0320_amnt_clltrl`) AND `0250_strctrd_prdct` IN ('Non-structured/Vanilla', 'Other non-standard terms') AND `0240_zero_coupon` != 'ZCB issued at discount' THEN 0 ELSE 1 END AS v_2_0011 | Z11: =+"SUM("&B11&") AS LVL2_H_"&MID(N11,2,LEN(N11)-2)&"," -> SUM(v_2_0011) AS LVL2_H_0130_rlvnt_amnt_wdc,
A12: 0012 | B12: =CONCATENATE("v_2_",A12) -> v_2_0012 | C12: B02.00 | D12: =VLOOKUP(CONCATENATE(C12,"_",E12),'Data types'!A:E,4,FALSE) -> 0130 | E12: Relevant amount for Bail-in/WDC | F12: =VLOOKUP(CONCATENATE(C12,"_",E12),'Data types'!A:F,6,FALSE) -> Numeric: 2 decimals | G12: X | I12: Check if the reported field is either equal to max(0, c0270 - c0300 - c0320) OR equal to max(0, c0120 - c0300 - c0320) | J12: c0250 = ( "Structured" OR "Structured coupon only") | K12: For structured products, the reported amount should be equal to: (c0270 - c0300 - c0320) if the fair value is used to support the determination of the relevant amount for bail-in, OR (c0120 - c0300 - c0320) if not. | L12: =+IF(G12="X","HIGH","WARNING") -> HIGH | M12: =+LEFT(C12,3) -> B02 | N12: ="`"&VLOOKUP(D12,'B02_Mapping fields'!B:C,2,FALSE)&"`" -> `0130_rlvnt_amnt_wdc` | O12: 0250 | P12: ="`"&VLOOKUP(O12,'B02_Mapping fields'!B:C,2,FALSE)&"`" -> `0250_strctrd_prdct` | Q12: 0270 | R12: ="`"&VLOOKUP(Q12,'B02_Mapping fields'!B:C,2,FALSE)&"`" -> `0270_fv_amnt_strctrd_prdct` | S12: 0300 | T12: ="`"&VLOOKUP(S12,'B02_Mapping fields'!B:C,2,FALSE)&"`" -> `0300_amnt_cvrd_elgbl_dpsts` | U12: 0320 | V12: ="`"&VLOOKUP(U12,'B02_Mapping fields'!B:C,2,FALSE)&"`" -> `0320_amnt_clltrl` | W12: 0120 | X12: ="`"&VLOOKUP(W12,'B02_Mapping fields'!B:C,2,FALSE)&"`" -> `0120_otstndng_amnt` | Y12: =+",CASE WHEN ("&N12&" = MAX(0, "&R12&"-"&T12&"-"&V12&") OR "&N12&" = MAX(0, "&X12&"-"&T12&"-"&V12&")) AND "&P12&" IN ('Structured', 'Structured coupon only') THEN 0 ELSE 1 END AS "&B12 -> ,CASE WHEN (`0130_rlvnt_amnt_wdc` = MAX(0, `0270_fv_amnt_strctrd_prdct`-`0300_amnt_cvrd_elgbl_dpsts`-`0320_amnt_clltrl`) OR `0130_rlvnt_amnt_wdc` = MAX(0, `0120_otstndng_amnt`-`0300_amnt_cvrd_elgbl_dpsts`-`0320_amnt_clltrl`)) AND `0250_strctrd_prdct` IN ('Structured', 'Structured coupon only') THEN 0 ELSE 1 END AS v_2_0012 | Z12: =+"SUM("&B12&") AS LVL2_H_"&MID(N12,2,LEN(N12)-2)&"," -> SUM(v_2_0012) AS LVL2_H_0130_rlvnt_amnt_wdc,
A13: 0013 | B13: =CONCATENATE("v_2_",A13) -> v_2_0013 | C13: B02.00 | D13: =VLOOKUP(CONCATENATE(C13,"_",E13),'Data types'!A:E,4,FALSE) -> 0140 | E13: Nature of the liability | F13: =VLOOKUP(CONCATENATE(C13,"_",E13),'Data types'!A:F,6,FALSE) -> String: Drop-down | G13: X | I13: Drop down values must be respected. | K13: The drop down values must be respected. | L13: =+IF(G13="X","HIGH","WARNING") -> HIGH | M13: =+LEFT(C13,3) -> B02 | N13: ="`"&VLOOKUP(D13,'B02_Mapping fields'!B:C,2,FALSE)&"`" -> `0140_ntr_lblty` | Y13: =+",CASE WHEN "&N13&" IN ('Registered Bond', 'Bearer Bond', 'Borrower Note Loan', 'Certificate of Deposit / Commercial paper', 'Title of ownership', 'Cash account/saving account', 'Term deposit', 'Loan', 'Bill of exchange ', 'Other') THEN 0 ELSE 1 END AS "&B13 -> ,CASE WHEN `0140_ntr_lblty` IN ('Registered Bond', 'Bearer Bond', 'Borrower Note Loan', 'Certificate of Deposit / Commercial paper', 'Title of ownership', 'Cash account/saving account', 'Term deposit', 'Loan', 'Bill of exchange ', 'Other') THEN 0 ELSE 1 END AS v_2_0013 | Z13: =+"SUM("&B13&") AS LVL2_H_"&MID(N13,2,LEN(N13)-2)&"," -> SUM(v_2_0013) AS LVL2_H_0140_ntr_lblty,
A14: 0014 | B14: =CONCATENATE("v_2_",A14) -> v_2_0014 | C14: B02.00 | D14: =VLOOKUP(CONCATENATE(C14,"_",E14),'Data types'!A:E,4,FALSE) -> 0160 | E14: Insolvency ranking | F14: =VLOOKUP(CONCATENATE(C14,"_",E14),'Data types'!A:F,6,FALSE) -> Numeric: Integer | G14: X | I14: Numeric integer values from 1 onwards must be reported. | K14: Numeric values from 1 onwards must be reported. | L14: =+IF(G14="X","HIGH","WARNING") -> HIGH | M14: =+LEFT(C14,3) -> B02 | N14: ="`"&VLOOKUP(D14,'B02_Mapping fields'!B:C,2,FALSE)&"`" -> `0160_rank_insolv` | Y14: =+",CASE WHEN "&N14&" REGEXP '^-?[0-9]+$' THEN 0 ELSE 1 END AS "&B14 -> ,CASE WHEN `0160_rank_insolv` REGEXP '^-?[0-9]+$' THEN 0 ELSE 1 END AS v_2_0014 | Z14: =+"SUM("&B14&") AS LVL2_H_"&MID(N14,2,LEN(N14)-2)&"," -> SUM(v_2_0014) AS LVL2_H_0160_rank_insolv,
A15: 0015 | B15: =CONCATENATE("v_2_",A15) -> v_2_0015 | C15: B02.00 | D15: =VLOOKUP(CONCATENATE(C15,"_",E15),'Data types'!A:E,4,FALSE) -> 0170 | E15: Date of issuance | F15: =VLOOKUP(CONCATENATE(C15,"_",E15),'Data types'!A:F,6,FALSE) -> Date: yyyy-mm-dd | G15: X | I15: The reported value must be a date (yyyy-mm-gg). | J15: (c0020 ≠ "NCNP" OR "NCBP") | K15: The reported value must be a date (yyyy-mm-gg). | L15: =+IF(G15="X","HIGH","WARNING") -> HIGH | M15: =+LEFT(C15,3) -> B02 | N15: ="`"&VLOOKUP(D15,'B02_Mapping fields'!B:C,2,FALSE)&"`" -> `0170_dt_incptn` | O15: 0020 | P15: ="`"&VLOOKUP(O15,'B02_Mapping fields'!B:C,2,FALSE)&"`" -> `0020_uniq_id` | Y15: =+",CASE WHEN "&N15&" REGEXP '^[0-9]{4}-[0-9]{2}-[0-9]{2}$' AND "&P15&" NOT IN ('NCNP', 'NCBP') THEN 0 ELSE 1 END AS "&B15 -> ,CASE WHEN `0170_dt_incptn` REGEXP '^[0-9]{4}-[0-9]{2}-[0-9]{2}$' AND `0020_uniq_id` NOT IN ('NCNP', 'NCBP') THEN 0 ELSE 1 END AS v_2_0015 | Z15: =+"SUM("&B15&") AS LVL2_H_"&MID(N15,2,LEN(N15)-2)&"," -> SUM(v_2_0015) AS LVL2_H_0170_dt_incptn,
A16: 0016 | B16: =CONCATENATE("v_2_",A16) -> v_2_0016 | C16: B02.00 | D16: =VLOOKUP(CONCATENATE(C16,"_",E16),'Data types'!A:E,4,FALSE) -> 0170 | E16: Date of issuance | F16: =VLOOKUP(CONCATENATE(C16,"_",E16),'Data types'!A:F,6,FALSE) -> Date: yyyy-mm-dd | G16: X | I16: The reported value must be before the Date of the next (partial) redemption payment (c0190) and the earliest redemption date (c0200). | J16: (c0190 or c0200) are reported & (c0020 ≠ "NCNP" OR "NCBP") | K16: The reported value must be before the Date of the next (partial) redemption payment (c0190) and the earliest redemption date (c0200). | L16: =+IF(G16="X","HIGH","WARNING") -> HIGH | M16: =+LEFT(C16,3) -> B02 | N16: ="`"&VLOOKUP(D16,'B02_Mapping fields'!B:C,2,FALSE)&"`" -> `0170_dt_incptn` | O16: 0190 | P16: ="`"&VLOOKUP(O16,'B02_Mapping fields'!B:C,2,FALSE)&"`" -> `0190_dt_nxt_rdmptn_pymnt` | Q16: 0200 | R16: ="`"&VLOOKUP(Q16,'B02_Mapping fields'!B:C,2,FALSE)&"`" -> `0200_dt_erlst_rdmptn` | S16: 0020 | T16: ="`"&VLOOKUP(S16,'B02_Mapping fields'!B:C,2,FALSE)&"`" -> `0020_uniq_id` | Y16: =+",CASE WHEN "&N16&" < "&P16&" AND "&N16&" < "&R16&" AND "&P16&" IS NOT MISSING AND ("&R16&" IS NOT MISSING OR "&R16&" = '0001-01-01') AND "&T16&" NOT IN ('NCNP', 'NCBP') THEN 0 ELSE 1 END AS "&B16 -> ,CASE WHEN `0170_dt_incptn` < `0190_dt_nxt_rdmptn_pymnt` AND `0170_dt_incptn` < `0200_dt_erlst_rdmptn` AND `0190_dt_nxt_rdmptn_pymnt` IS NOT MISSING AND (`0200_dt_erlst_rdmptn` IS NOT MISSING OR `0200_dt_erlst_rdmptn` = '0001-01-01') AND `0020_uniq_id` NOT IN ('NCNP', 'NCBP') THEN 0 ELSE 1 END AS v_2_0016 | Z16: =+"SUM("&B16&") AS LVL2_H_"&MID(N16,2,LEN(N16)-2)&"," -> SUM(v_2_0016) AS LVL2_H_0170_dt_incptn,
A17: 0017 | B17: =CONCATENATE("v_2_",A17) -> v_2_0017 | C17: B02.00 | D17: =VLOOKUP(CONCATENATE(C17,"_",E17),'Data types'!A:E,4,FALSE) -> 0180 | E17: Date of the next interest payment | F17: =VLOOKUP(CONCATENATE(C17,"_",E17),'Data types'!A:F,6,FALSE) -> Date: yyyy-mm-dd | G17: X | I17: The reported value must be a date (yyyy-mm-gg). | J17: (c0020 ≠ "NCNP" OR "NCBP") | K17: The reported value must be a date (yyyy-mm-gg). | L17: =+IF(G17="X","HIGH","WARNING") -> HIGH | M17: =+LEFT(C17,3) -> B02 | N17: ="`"&VLOOKUP(D17,'B02_Mapping fields'!B:C,2,FALSE)&"`" -> `0180_dt_nxt_intrst_pymnt` | O17: 0020 | P17: ="`"&VLOOKUP(O17,'B02_Mapping fields'!B:C,2,FALSE)&"`" -> `0020_uniq_id` | Y17: =+",CASE WHEN "&N17&" REGEXP '^[0-9]{4}-[0-9]{2}-[0-9]{2}$' AND "&P17&" NOT IN ('NCNP', 'NCBP') THEN 0 ELSE 1 END AS "&B17 -> ,CASE WHEN `0180_dt_nxt_intrst_pymnt` REGEXP '^[0-9]{4}-[0-9]{2}-[0-9]{2}$' AND `0020_uniq_id` NOT IN ('NCNP', 'NCBP') THEN 0 ELSE 1 END AS v_2_0017 | Z17: =+"SUM("&B17&") AS LVL2_H_"&MID(N17,2,LEN(N17)-2)&"," -> SUM(v_2_0017) AS LVL2_H_0180_dt_nxt_intrst_pymnt,
A18: 0018 | B18: =CONCATENATE("v_2_",A18) -> v_2_0018 | C18: B02.00 | D18: =VLOOKUP(CONCATENATE(C18,"_",E18),'Data types'!A:E,4,FALSE) -> 0180 | E18: Date of the next interest payment | F18: =VLOOKUP(CONCATENATE(C18,"_",E18),'Data types'!A:F,6,FALSE) -> Date: yyyy-mm-dd | G18: X | I18: The reported value must be after the reference date reported in B99.00 (c0070). | J18: {B99.00;c0070} is reported & (c0020 ≠ "NCNP" OR "NCBP") | K18: The reported value must be after the reference date reported in B99.00 (c0070). | L18: =+IF(G18="X","HIGH","WARNING") -> HIGH | M18: =+LEFT(C18,3) -> B02 | N18: ="`"&VLOOKUP(D18,'B02_Mapping fields'!B:C,2,FALSE)&"`" -> `0180_dt_nxt_intrst_pymnt` | O18: 0070 | P18: ="`"&VLOOKUP(O18,'B02_Mapping fields'!B:C,2,FALSE)&"`" -> `0070_cntrct_crrncy` | Q18: 0020 | R18: ="`"&VLOOKUP(Q18,'B02_Mapping fields'!B:C,2,FALSE)&"`" -> `0020_uniq_id` | Y18: =+",CASE WHEN "&N18&" > "&P18&" AND "&P18&" IS NOT MISSING AND "&R18&" NOT IN ('NCNP', 'NCBP') THEN 0 ELSE 1 END AS "&B18 -> ,CASE WHEN `0180_dt_nxt_intrst_pymnt` > `0070_cntrct_crrncy` AND `0070_cntrct_crrncy` IS NOT MISSING AND `0020_uniq_id` NOT IN ('NCNP', 'NCBP') THEN 0 ELSE 1 END AS v_2_0018 | Z18: =+"SUM("&B18&") AS LVL2_H_"&MID(N18,2,LEN(N18)-2)&"," -> SUM(v_2_0018) AS LVL2_H_0180_dt_nxt_intrst_pymnt,
A19: 0019 | B19: =CONCATENATE("v_2_",A19) -> v_2_0019 | C19: B02.00 | D19: =VLOOKUP(CONCATENATE(C19,"_",E19),'Data types'!A:E,4,FALSE) -> 0200 | E19: Earliest redemption date | F19: =VLOOKUP(CONCATENATE(C19,"_",E19),'Data types'!A:F,6,FALSE) -> Date: yyyy-mm-dd | G19: X | I19: The reported value must be a date (yyyy-mm-gg). | J19: (c0020 ≠ "NCNP" OR "NCBP") | K19: The reported value must be a date (yyyy-mm-gg). | L19: =+IF(G19="X","HIGH","WARNING") -> HIGH | M19: =+LEFT(C19,3) -> B02 | N19: ="`"&VLOOKUP(D19,'B02_Mapping fields'!B:C,2,FALSE)&"`" -> `0200_dt_erlst_rdmptn` | O19: 0020 | P19: ="`"&VLOOKUP(O19,'B02_Mapping fields'!B:C,2,FALSE)&"`" -> `0020_uniq_id` | Y19: =+",CASE WHEN "&N19&" REGEXP '^[0-9]{4}-[0-9]{2}-[0-9]{2}$' AND "&P19&" NOT IN ('NCNP', 'NCBP') THEN 0 ELSE 1 END AS "&B19 -> ,CASE WHEN `0200_dt_erlst_rdmptn` REGEXP '^[0-9]{4}-[0-9]{2}-[0-9]{2}$' AND `0020_uniq_id` NOT IN ('NCNP', 'NCBP') THEN 0 ELSE 1 END AS v_2_0019 | Z19: =+"SUM("&B19&") AS LVL2_H_"&MID(N19,2,LEN(N19)-2)&"," -> SUM(v_2_0019) AS LVL2_H_0200_dt_erlst_rdmptn,
A20: 0020 | B20: =CONCATENATE("v_2_",A20) -> v_2_0020 | C20: B02.00 | D20: =VLOOKUP(CONCATENATE(C20,"_",E20),'Data types'!A:E,4,FALSE) -> 0200 | E20: Earliest redemption date | F20: =VLOOKUP(CONCATENATE(C20,"_",E20),'Data types'!A:F,6,FALSE) -> Date: yyyy-mm-dd | G20: X | I20: The reported value must be after the reference date reported in B99.00 (c0070). | J20: {B99.00;c0070} is reported & (c0020 ≠ "NCNP" OR "NCBP") | K20: The reported value must be after the reference date reported in B99.00 (c0070). | L20: =+IF(G20="X","HIGH","WARNING") -> HIGH | M20: =+LEFT(C20,3) -> B02 | N20: ="`"&VLOOKUP(D20,'B02_Mapping fields'!B:C,2,FALSE)&"`" -> `0200_dt_erlst_rdmptn` | O20: 0070 | P20: ="`"&VLOOKUP(O20,'B02_Mapping fields'!B:C,2,FALSE)&"`" -> `0070_cntrct_crrncy` | Q20: 0020 | R20: ="`"&VLOOKUP(Q20,'B02_Mapping fields'!B:C,2,FALSE)&"`" -> `0020_uniq_id` | Y20: =+",CASE WHEN "&N20&" > "&P20&" AND "&P20&" IS NOT MISSING AND "&R20&" NOT IN ('NCNP', 'NCBP') THEN 0 ELSE 1 END AS "&B20 -> ,CASE WHEN `0200_dt_erlst_rdmptn` > `0070_cntrct_crrncy` AND `0070_cntrct_crrncy` IS NOT MISSING AND `0020_uniq_id` NOT IN ('NCNP', 'NCBP') THEN 0 ELSE 1 END AS v_2_0020 | Z20: =+"SUM("&B20&") AS LVL2_H_"&MID(N20,2,LEN(N20)-2)&"," -> SUM(v_2_0020) AS LVL2_H_0200_dt_erlst_rdmptn,
A21: 0021 | B21: =CONCATENATE("v_2_",A21) -> v_2_0021 | C21: B02.00 | D21: =VLOOKUP(CONCATENATE(C21,"_",E21),'Data types'!A:E,4,FALSE) -> 0210 | E21: Legal maturity | F21: =VLOOKUP(CONCATENATE(C21,"_",E21),'Data types'!A:F,6,FALSE) -> Date: yyyy-mm-dd | G21: X | I21: The reported value must be a date (yyyy-mm-gg). | J21: (c0020 ≠ "NCNP" OR "NCBP") | K21: The reported value must be a date (yyyy-mm-gg). | L21: =+IF(G21="X","HIGH","WARNING") -> HIGH | M21: =+LEFT(C21,3) -> B02 | N21: ="`"&VLOOKUP(D21,'B02_Mapping fields'!B:C,2,FALSE)&"`" -> `0210_dt_lgl_fnl_mtrty` | O21: 0020 | P21: ="`"&VLOOKUP(O21,'B02_Mapping fields'!B:C,2,FALSE)&"`" -> `0020_uniq_id` | Y21: =+",CASE WHEN "&N21&" REGEXP '^[0-9]{4}-[0-9]{2}-[0-9]{2}$' AND "&P21&" NOT IN ('NCNP', 'NCBP') THEN 0 ELSE 1 END AS "&B21 -> ,CASE WHEN `0210_dt_lgl_fnl_mtrty` REGEXP '^[0-9]{4}-[0-9]{2}-[0-9]{2}$' AND `0020_uniq_id` NOT IN ('NCNP', 'NCBP') THEN 0 ELSE 1 END AS v_2_0021 | Z21: =+"SUM("&B21&") AS LVL2_H_"&MID(N21,2,LEN(N21)-2)&"," -> SUM(v_2_0021) AS LVL2_H_0210_dt_lgl_fnl_mtrty,
A22: 0022 | B22: =CONCATENATE("v_2_",A22) -> v_2_0022 | C22: B02.00 | D22: =VLOOKUP(CONCATENATE(C22,"_",E22),'Data types'!A:E,4,FALSE) -> 0210 | E22: Legal maturity | F22: =VLOOKUP(CONCATENATE(C22,"_",E22),'Data types'!A:F,6,FALSE) -> Date: yyyy-mm-dd | G22: X | I22: The reported value must be after the reference date reported in B99.00 (c0070). | J22: {B99.00;c0070} is reported & (c0020 ≠ "NCNP" OR "NCBP") | K22: The reported value must be after the reference date reported in B99.00 (c0070). | L22: =+IF(G22="X","HIGH","WARNING") -> HIGH | M22: =+LEFT(C22,3) -> B02 | N22: ="`"&VLOOKUP(D22,'B02_Mapping fields'!B:C,2,FALSE)&"`" -> `0210_dt_lgl_fnl_mtrty` | O22: 0070 | P22: ="`"&VLOOKUP(O22,'B02_Mapping fields'!B:C,2,FALSE)&"`" -> `0070_cntrct_crrncy` | Q22: 0020 | R22: ="`"&VLOOKUP(Q22,'B02_Mapping fields'!B:C,2,FALSE)&"`" -> `0020_uniq_id` | Y22: =+",CASE WHEN "&N22&" > "&P22&" AND "&P22&" IS NOT MISSING AND "&R22&" NOT IN ('NCNP', 'NCBP') THEN 0 ELSE 1 END AS "&B22 -> ,CASE WHEN `0210_dt_lgl_fnl_mtrty` > `0070_cntrct_crrncy` AND `0070_cntrct_crrncy` IS NOT MISSING AND `0020_uniq_id` NOT IN ('NCNP', 'NCBP') THEN 0 ELSE 1 END AS v_2_0022 | Z22: =+"SUM("&B22&") AS LVL2_H_"&MID(N22,2,LEN(N22)-2)&"," -> SUM(v_2_0022) AS LVL2_H_0210_dt_lgl_fnl_mtrty,
A23: 0023 | B23: =CONCATENATE("v_2_",A23) -> v_2_0023 | C23: B02.00 | D23: =VLOOKUP(CONCATENATE(C23,"_",E23),'Data types'!A:E,4,FALSE) -> 0220 | E23: Governing law | F23: =VLOOKUP(CONCATENATE(C23,"_",E23),'Data types'!A:F,6,FALSE) -> String: ISO 3166-1 alpha 2 / ISO 3166-2 | G23: X | I23: Check if the reported field respects the ISO 3166-1 alpha-2 code or 3166-2 | J23: (c0020 ≠ "NCNP" OR "NCBP") | K23: Governing law must be reported using the ISO 3166-1 alpha-2 code. | L23: =+IF(G23="X","HIGH","WARNING") -> HIGH | M23: =+LEFT(C23,3) -> B02 | N23: ="`"&VLOOKUP(D23,'B02_Mapping fields'!B:C,2,FALSE)&"`" -> `0220_governing_law` | O23: 0020 | P23: ="`"&VLOOKUP(O23,'B02_Mapping fields'!B:C,2,FALSE)&"`" -> `0020_uniq_id` | Y23: =+",CASE WHEN ("&N23&" REGEXP '^[A-Z]{2}$' OR "&N23&" REGEXP '^[A-Z]{2}-[A-Z0-9]{1,3}$') AND "&N23&" IS NOT MISSING AND "&P23&" NOT IN ('NCNP', 'NCBP') THEN 0 ELSE 1 END AS "&B23 -> ,CASE WHEN (`0220_governing_law` REGEXP '^[A-Z]{2}$' OR `0220_governing_law` REGEXP '^[A-Z]{2}-[A-Z0-9]{1,3}$') AND `0220_governing_law` IS NOT MISSING AND `0020_uniq_id` NOT IN ('NCNP', 'NCBP') THEN 0 ELSE 1 END AS v_2_0023 | Z23: =+"SUM("&B23&") AS LVL2_H_"&MID(N23,2,LEN(N23)-2)&"," -> SUM(v_2_0023) AS LVL2_H_0220_governing_law,
A24: 0024 | B24: =CONCATENATE("v_2_",A24) -> v_2_0024 | C24: B02.00 | D24: =VLOOKUP(CONCATENATE(C24,"_",E24),'Data types'!A:E,4,FALSE) -> 0230 | E24: Bail-in recognition clause | F24: =VLOOKUP(CONCATENATE(C24,"_",E24),'Data types'!A:F,6,FALSE) -> String: Drop-down | G24: X | I24: Drop down values must be respected. | J24: (c0020 ≠ "NCNP" OR "NCBP") | K24: The drop down values must be respected. | L24: =+IF(G24="X","HIGH","WARNING") -> HIGH | M24: =+LEFT(C24,3) -> B02 | N24: ="`"&VLOOKUP(D24,'B02_Mapping fields'!B:C,2,FALSE)&"`" -> `0230_bail_in_rcgntn_cls` | O24: 0020 | P24: ="`"&VLOOKUP(O24,'B02_Mapping fields'!B:C,2,FALSE)&"`" -> `0020_uniq_id` | Y24: =+",CASE WHEN "&N24&" IN ('Yes, supported by Legal Opinion', 'Yes, not supported by Legal Opinion', 'No', 'Not applicable', 'Aggregated') AND "&P24&" NOT IN ('NCNP', 'NCBP') THEN 0 ELSE 1 END AS "&B24 -> ,CASE WHEN `0230_bail_in_rcgntn_cls` IN ('Yes, supported by Legal Opinion', 'Yes, not supported by Legal Opinion', 'No', 'Not applicable', 'Aggregated') AND `0020_uniq_id` NOT IN ('NCNP', 'NCBP') THEN 0 ELSE 1 END AS v_2_0024 | Z24: =+"SUM("&B24&") AS LVL2_H_"&MID(N24,2,LEN(N24)-2)&"," -> SUM(v_2_0024) AS LVL2_H_0230_bail_in_rcgntn_cls,
A25: 0025 | B25: =CONCATENATE("v_2_",A25) -> v_2_0025 | C25: B02.00 | D25: =VLOOKUP(CONCATENATE(C25,"_",E25),'Data types'!A:E,4,FALSE) -> 0250 | E25: Structured product | F25: =VLOOKUP(CONCATENATE(C25,"_",E25),'Data types'!A:F,6,FALSE) -> String: Drop-down | G25: X | I25: Drop down values must be respected. | K25: The drop down values must be respected. | L25: =+IF(G25="X","HIGH","WARNING") -> HIGH | M25: =+LEFT(C25,3) -> B02 | N25: ="`"&VLOOKUP(D25,'B02_Mapping fields'!B:C,2,FALSE)&"`" -> `0250_strctrd_prdct` | Y25: =+",CASE WHEN "&N25&" IN ('Non-structured/Vanilla', 'Structured', 'Other non-standard terms', 'Only structured coupon', 'Aggregated') THEN 0 ELSE 1 END AS "&B25 -> ,CASE WHEN `0250_strctrd_prdct` IN ('Non-structured/Vanilla', 'Structured', 'Other non-standard terms', 'Only structured coupon', 'Aggregated') THEN 0 ELSE 1 END AS v_2_0025 | Z25: =+"SUM("&B25&") AS LVL2_H_"&MID(N25,2,LEN(N25)-2)&"," -> SUM(v_2_0025) AS LVL2_H_0250_strctrd_prdct,
A26: 0026 | B26: =CONCATENATE("v_2_",A26) -> v_2_0026 | C26: B02.00 | D26: =VLOOKUP(CONCATENATE(C26,"_",E26),'Data types'!A:E,4,FALSE) -> 0310 | E26: Secured/Unsecured | F26: =VLOOKUP(CONCATENATE(C26,"_",E26),'Data types'!A:F,6,FALSE) -> String: Drop-down | G26: X | I26: Drop down values must be respected. | K26: The drop down values must be respected. | L26: =+IF(G26="X","HIGH","WARNING") -> HIGH | M26: =+LEFT(C26,3) -> B02 | N26: ="`"&VLOOKUP(D26,'B02_Mapping fields'!B:C,2,FALSE)&"`" -> `0310_flg_clltrl_agrmnts` | Y26: =+",CASE WHEN "&N26&" IN ('Secured', 'Unsecured') THEN 0 ELSE 1 END AS "&B26 -> ,CASE WHEN `0310_flg_clltrl_agrmnts` IN ('Secured', 'Unsecured') THEN 0 ELSE 1 END AS v_2_0026 | Z26: =+"SUM("&B26&") AS LVL2_H_"&MID(N26,2,LEN(N26)-2)&"," -> SUM(v_2_0026) AS LVL2_H_0310_flg_clltrl_agrmnts,
A27: 0027 | B27: =CONCATENATE("v_2_",A27) -> v_2_0027 | C27: B02.00 | D27: =VLOOKUP(CONCATENATE(C27,"_",E27),'Data types'!A:E,4,FALSE) -> 0330 | E27: Amount of the uncollateralized part | F27: =VLOOKUP(CONCATENATE(C27,"_",E27),'Data types'!A:F,6,FALSE) -> Numeric: 2 decimals | G27: X | I27: Check if the reported field is equal to: max(0,c0120 - c0320.) | J27: c0310 = "Secured" & c0250 = ( "Non-structured/Vanilla"OR "Other non-standard terms") AND c0240 !="ZCB issued at discount" | K27: The reported field should be equal to: c0120 - c0320. | L27: =+IF(G27="X","HIGH","WARNING") -> HIGH | M27: =+LEFT(C27,3) -> B02 | N27: ="`"&VLOOKUP(D27,'B02_Mapping fields'!B:C,2,FALSE)&"`" -> `0330_amnt_unclltrlzd` | O27: 0310 | P27: ="`"&VLOOKUP(O27,'B02_Mapping fields'!B:C,2,FALSE)&"`" -> `0310_flg_clltrl_agrmnts` | Q27: 0250 | R27: ="`"&VLOOKUP(Q27,'B02_Mapping fields'!B:C,2,FALSE)&"`" -> `0250_strctrd_prdct` | S27: 0240 | T27: ="`"&VLOOKUP(S27,'B02_Mapping fields'!B:C,2,FALSE)&"`" -> `0240_zero_coupon` | U27: 0120 | V27: ="`"&VLOOKUP(U27,'B02_Mapping fields'!B:C,2,FALSE)&"`" -> `0120_otstndng_amnt` | W27: 0320 | X27: ="`"&VLOOKUP(W27,'B02_Mapping fields'!B:C,2,FALSE)&"`" -> `0320_amnt_clltrl` | Y27: =+",CASE WHEN "&N27&" = MAX(0, "&V27&"-"&X27&") AND "&P27&" = 'Secured' AND "&R27&" IN ('Non-structured/Vanilla', 'Other non-standard terms') AND "&T27&" != 'ZCB issued at discount' THEN 0 ELSE 1 END AS "&B27 -> ,CASE WHEN `0330_amnt_unclltrlzd` = MAX(0, `0120_otstndng_amnt`-`0320_amnt_clltrl`) AND `0310_flg_clltrl_agrmnts` = 'Secured' AND `0250_strctrd_prdct` IN ('Non-structured/Vanilla', 'Other non-standard terms') AND `0240_zero_coupon` != 'ZCB issued at discount' THEN 0 ELSE 1 END AS v_2_0027 | Z27: =+"SUM("&B27&") AS LVL2_H_"&MID(N27,2,LEN(N27)-2)&"," -> SUM(v_2_0027) AS LVL2_H_0330_amnt_unclltrlzd,
A28: 0028 | B28: =CONCATENATE("v_2_",A28) -> v_2_0028 | C28: B02.00 | D28: =VLOOKUP(CONCATENATE(C28,"_",E28),'Data types'!A:E,4,FALSE) -> 0330 | E28: Amount of the uncollateralized part | F28: =VLOOKUP(CONCATENATE(C28,"_",E28),'Data types'!A:F,6,FALSE) -> Numeric: 2 decimals | G28: X | I28: Check if the reported field is either max(0, c0270 - c0320) or max (0, c0120 - c0320) | J28: c0310 = "Secured" & c0250 = ("Structured" OR "Only structured coupon") | K28: The reported field should be equal to (c0270 - c0320) if the fair value is used, or equal to (c0120 - c0320) otherwise | L28: =+IF(G28="X","HIGH","WARNING") -> HIGH | M28: =+LEFT(C28,3) -> B02 | N28: ="`"&VLOOKUP(D28,'B02_Mapping fields'!B:C,2,FALSE)&"`" -> `0330_amnt_unclltrlzd` | O28: 0310 | P28: ="`"&VLOOKUP(O28,'B02_Mapping fields'!B:C,2,FALSE)&"`" -> `0310_flg_clltrl_agrmnts` | Q28: 0250 | R28: ="`"&VLOOKUP(Q28,'B02_Mapping fields'!B:C,2,FALSE)&"`" -> `0250_strctrd_prdct` | S28: 0270 | T28: ="`"&VLOOKUP(S28,'B02_Mapping fields'!B:C,2,FALSE)&"`" -> `0270_fv_amnt_strctrd_prdct` | U28: 0320 | V28: ="`"&VLOOKUP(U28,'B02_Mapping fields'!B:C,2,FALSE)&"`" -> `0320_amnt_clltrl` | W28: 0120 | X28: ="`"&VLOOKUP(W28,'B02_Mapping fields'!B:C,2,FALSE)&"`" -> `0120_otstndng_amnt` | Y28: =+",CASE WHEN ("&N28&" = MAX(0, "&T28&"-"&V28&") OR "&N28&" = MAX(0, "&X28&"-"&V28&")) AND "&P28&" = 'Secured' AND "&R28&" IN ('Structured', 'Only structured coupon') AND c0240 != 'ZCB issued at discount' THEN 0 ELSE 1 END AS "&B28 -> ,CASE WHEN (`0330_amnt_unclltrlzd` = MAX(0, `0270_fv_amnt_strctrd_prdct`-`0320_amnt_clltrl`) OR `0330_amnt_unclltrlzd` = MAX(0, `0120_otstndng_amnt`-`0320_amnt_clltrl`)) AND `0310_flg_clltrl_agrmnts` = 'Secured' AND `0250_strctrd_prdct` IN ('Structured', 'Only structured coupon') AND c0240 != 'ZCB issued at discount' THEN 0 ELSE 1 END AS v_2_0028 | Z28: =+"SUM("&B28&") AS LVL2_H_"&MID(N28,2,LEN(N28)-2)&"," -> SUM(v_2_0028) AS LVL2_H_0330_amnt_unclltrlzd,
A29: 0029 | B29: =CONCATENATE("v_2_",A29) -> v_2_0029 | C29: B02.00 | D29: =VLOOKUP(CONCATENATE(C29,"_",E29),'Data types'!A:E,4,FALSE) -> 0350 | E29: Type of the collateral | F29: =VLOOKUP(CONCATENATE(C29,"_",E29),'Data types'!A:F,6,FALSE) -> String: Drop-down | G29: X | I29: Drop down values must be respected. | K29: The drop down values must be respected. | L29: =+IF(G29="X","HIGH","WARNING") -> HIGH | M29: =+LEFT(C29,3) -> B02 | N29: ="`"&VLOOKUP(D29,'B02_Mapping fields'!B:C,2,FALSE)&"`" -> `0350_typ_clltrl` | Y29: =+",CASE WHEN "&N29&" IN ('Real estate', 'Ships', 'Aircraft', 'Financial', 'Other', 'Not applicable') THEN 0 ELSE 1 END AS "&B29 -> ,CASE WHEN `0350_typ_clltrl` IN ('Real estate', 'Ships', 'Aircraft', 'Financial', 'Other', 'Not applicable') THEN 0 ELSE 1 END AS v_2_0029 | Z29: =+"SUM("&B29&") AS LVL2_H_"&MID(N29,2,LEN(N29)-2)&"," -> SUM(v_2_0029) AS LVL2_H_0350_typ_clltrl,
A30: 0030 | B30: =CONCATENATE("v_2_",A30) -> v_2_0030 | C30: B02.00 | D30: =VLOOKUP(CONCATENATE(C30,"_",E30),'Data types'!A:E,4,FALSE) -> 0350 | E30: Type of the collateral | F30: =VLOOKUP(CONCATENATE(C30,"_",E30),'Data types'!A:F,6,FALSE) -> String: Drop-down | G30: X | I30: "Not applicable" must be reported. | J30: c0310 = "Unsecured" | K30: The field must be "Not applicable" if c0310 is unsecured. | L30: =+IF(G30="X","HIGH","WARNING") -> HIGH | M30: =+LEFT(C30,3) -> B02 | N30: ="`"&VLOOKUP(D30,'B02_Mapping fields'!B:C,2,FALSE)&"`" -> `0350_typ_clltrl` | O30: 0310 | P30: ="`"&VLOOKUP(O30,'B02_Mapping fields'!B:C,2,FALSE)&"`" -> `0310_flg_clltrl_agrmnts` | Y30: =+",CASE WHEN "&N30&" = 'Not applicable' AND "&P30&" = 'Unsecured' THEN 0 ELSE 1 END AS "&B30 -> ,CASE WHEN `0350_typ_clltrl` = 'Not applicable' AND `0310_flg_clltrl_agrmnts` = 'Unsecured' THEN 0 ELSE 1 END AS v_2_0030 | Z30: =+"SUM("&B30&") AS LVL2_H_"&MID(N30,2,LEN(N30)-2)&"," -> SUM(v_2_0030) AS LVL2_H_0350_typ_clltrl,
A31: 0031 | B31: =CONCATENATE("v_2_",A31) -> v_2_0031 | C31: B02.00 | D31: =VLOOKUP(CONCATENATE(C31,"_",E31),'Data types'!A:E,4,FALSE) -> 0440 | E31: Nature of the global note | F31: =VLOOKUP(CONCATENATE(C31,"_",E31),'Data types'!A:F,6,FALSE) -> String: Drop-down | G31: X | I31: Drop down values must be respected. | K31: The drop down values must be respected. | L31: =+IF(G31="X","HIGH","WARNING") -> HIGH | M31: =+LEFT(C31,3) -> B02 | N31: ="`"&VLOOKUP(D31,'B02_Mapping fields'!B:C,2,FALSE)&"`" -> `0440_ntr_glbl_nt` | Y31: =+",CASE WHEN "&N31&" IN ('NGN', 'CGN', 'Not applicable') THEN 0 ELSE 1 END AS "&B31 -> ,CASE WHEN `0440_ntr_glbl_nt` IN ('NGN', 'CGN', 'Not applicable') THEN 0 ELSE 1 END AS v_2_0031 | Z31: =+"SUM("&B31&") AS LVL2_H_"&MID(N31,2,LEN(N31)-2)&"," -> SUM(v_2_0031) AS LVL2_H_0440_ntr_glbl_nt,
A32: 0032 | B32: =CONCATENATE("v_2_",A32) -> v_2_0032 | C32: B02.00 | D32: =VLOOKUP(CONCATENATE(C32,"_",E32),'Data types'!A:E,4,FALSE) -> 0530 | E32: Type of own funds at individual level | F32: =VLOOKUP(CONCATENATE(C32,"_",E32),'Data types'!A:F,6,FALSE) -> String: Drop-down | G32: X | I32: Drop down values must be respected. | K32: The drop down values must be respected. | L32: =+IF(G32="X","HIGH","WARNING") -> HIGH | M32: =+LEFT(C32,3) -> B02 | N32: ="`"&VLOOKUP(D32,'B02_Mapping fields'!B:C,2,FALSE)&"`" -> `0530_typ_own_fnds_ind_lvl` | Y32: =+",CASE WHEN "&N32&" IN ('T2 in phase-out', 'Grandfathered T2', 'Fully Compliant T2', 'Partially (A)T1 and T2', 'Grandfathered AT1', 'Fully Compliant AT1', 'CET1', 'No') THEN 0 ELSE 1 END AS "&B32 -> ,CASE WHEN `0530_typ_own_fnds_ind_lvl` IN ('T2 in phase-out', 'Grandfathered T2', 'Fully Compliant T2', 'Partially (A)T1 and T2', 'Grandfathered AT1', 'Fully Compliant AT1', 'CET1', 'No') THEN 0 ELSE 1 END AS v_2_0032 | Z32: =+"SUM("&B32&") AS LVL2_H_"&MID(N32,2,LEN(N32)-2)&"," -> SUM(v_2_0032) AS LVL2_H_0530_typ_own_fnds_ind_lvl,
A33: 0033 | B33: =CONCATENATE("v_2_",A33) -> v_2_0033 | C33: B02.00 | D33: =VLOOKUP(CONCATENATE(C33,"_",E33),'Data types'!A:E,4,FALSE) -> 0540 | E33: Eligible amount for own funds at individual level | F33: =VLOOKUP(CONCATENATE(C33,"_",E33),'Data types'!A:F,6,FALSE) -> Numeric: 2 decimals | G33: X | I33: Check if the reported field is higher than or equal 0. | K33: The reported amount should be positive or zero. | L33: =+IF(G33="X","HIGH","WARNING") -> HIGH | M33: =+LEFT(C33,3) -> B02 | N33: ="`"&VLOOKUP(D33,'B02_Mapping fields'!B:C,2,FALSE)&"`" -> `0540_elgbl_amnt_own_fnds_ind_lvl` | Y33: =+",CASE WHEN "&N33&" >= 0 THEN 0 ELSE 1 END AS "&B33 -> ,CASE WHEN `0540_elgbl_amnt_own_fnds_ind_lvl` >= 0 THEN 0 ELSE 1 END AS v_2_0033 | Z33: =+"SUM("&B33&") AS LVL2_H_"&MID(N33,2,LEN(N33)-2)&"," -> SUM(v_2_0033) AS LVL2_H_0540_elgbl_amnt_own_fnds_ind_lvl,
A34: 0034 | B34: =CONCATENATE("v_2_",A34) -> v_2_0034 | C34: B02.00 | D34: =VLOOKUP(CONCATENATE(C34,"_",E34),'Data types'!A:E,4,FALSE) -> 0550 | E34: Type of own funds at consolidated level | F34: =VLOOKUP(CONCATENATE(C34,"_",E34),'Data types'!A:F,6,FALSE) -> String: Drop-down | G34: X | I34: Drop down values must be respected. | K34: The drop down values must be respected. | L34: =+IF(G34="X","HIGH","WARNING") -> HIGH | M34: =+LEFT(C34,3) -> B02 | N34: ="`"&VLOOKUP(D34,'B02_Mapping fields'!B:C,2,FALSE)&"`" -> `0550_typ_own_fnds_cnsldtd_lvl` | Y34: =+",CASE WHEN "&N34&" IN ('T2 in phase-out', 'Grandfathered T2', 'Fully Compliant T2', 'Partially (A)T1 and T2', 'Grandfathered AT1', 'Fully Compliant AT1', 'CET1', 'No') THEN 0 ELSE 1 END AS "&B34 -> ,CASE WHEN `0550_typ_own_fnds_cnsldtd_lvl` IN ('T2 in phase-out', 'Grandfathered T2', 'Fully Compliant T2', 'Partially (A)T1 and T2', 'Grandfathered AT1', 'Fully Compliant AT1', 'CET1', 'No') THEN 0 ELSE 1 END AS v_2_0034 | Z34: =+"SUM("&B34&") AS LVL2_H_"&MID(N34,2,LEN(N34)-2)&"," -> SUM(v_2_0034) AS LVL2_H_0550_typ_own_fnds_cnsldtd_lvl,
A35: 0035 | B35: =CONCATENATE("v_2_",A35) -> v_2_0035 | C35: B02.00 | D35: =VLOOKUP(CONCATENATE(C35,"_",E35),'Data types'!A:E,4,FALSE) -> 0560 | E35: Eligible amount for own funds at consolidated level | F35: =VLOOKUP(CONCATENATE(C35,"_",E35),'Data types'!A:F,6,FALSE) -> Numeric: 2 decimals | G35: X | I35: Check if the reported field is higher than or equal 0. | K35: The reported amount should be positive or zero. | L35: =+IF(G35="X","HIGH","WARNING") -> HIGH | M35: =+LEFT(C35,3) -> B02 | N35: ="`"&VLOOKUP(D35,'B02_Mapping fields'!B:C,2,FALSE)&"`" -> `0560_elgbl_amnt_own_fnds_cnsldtd_lvl` | Y35: =+",CASE WHEN "&N35&" >= 0 THEN 0 ELSE 1 END AS "&B35 -> ,CASE WHEN `0560_elgbl_amnt_own_fnds_cnsldtd_lvl` >= 0 THEN 0 ELSE 1 END AS v_2_0035 | Z35: =+"SUM("&B35&") AS LVL2_H_"&MID(N35,2,LEN(N35)-2)&"," -> SUM(v_2_0035) AS LVL2_H_0560_elgbl_amnt_own_fnds_cnsldtd_lvl,
A36: 0036 | B36: =CONCATENATE("v_2_",A36) -> v_2_0036 | C36: B02.00 | D36: =VLOOKUP(CONCATENATE(C36,"_",E36),'Data types'!A:E,4,FALSE) -> 0590 | E36: Type of security interest provided by a third party | F36: =VLOOKUP(CONCATENATE(C36,"_",E36),'Data types'!A:F,6,FALSE) -> String: Drop-down | G36: X | I36: Drop down values must be respected. | K36: The drop down values must be respected. | L36: =+IF(G36="X","HIGH","WARNING") -> HIGH | M36: =+LEFT(C36,3) -> B02 | N36: ="`"&VLOOKUP(D36,'B02_Mapping fields'!B:C,2,FALSE)&"`" -> `0590_typ_scrty_intrst_prvdd` | Y36: =+",CASE WHEN "&N36&" IN ('T2 in phase-out', 'Grandfathered T2', 'Fully Compliant T2', 'Partially (A)T1 and T2', 'Grandfathered AT1', 'Fully Compliant AT1', 'CET1', 'No') THEN 0 ELSE 1 END AS "&B36 -> ,CASE WHEN `0590_typ_scrty_intrst_prvdd` IN ('T2 in phase-out', 'Grandfathered T2', 'Fully Compliant T2', 'Partially (A)T1 and T2', 'Grandfathered AT1', 'Fully Compliant AT1', 'CET1', 'No') THEN 0 ELSE 1 END AS v_2_0036 | Z36: =+"SUM("&B36&") AS LVL2_H_"&MID(N36,2,LEN(N36)-2)&"," -> SUM(v_2_0036) AS LVL2_H_0590_typ_scrty_intrst_prvdd,
A37: 0037 | B37: =CONCATENATE("v_2_",A37) -> v_2_0037 | C37: B02.00 | D37: =VLOOKUP(CONCATENATE(C37,"_",E37),'Data types'!A:E,4,FALSE) -> 0610 | E37: Carrying amount IFRS | F37: =VLOOKUP(CONCATENATE(C37,"_",E37),'Data types'!A:F,6,FALSE) -> Numeric: 2 decimals | G37: X | I37: Check if the reported field is higher than or equal 0. | K37: The reported amount should be positive or zero. | L37: =+IF(G37="X","HIGH","WARNING") -> HIGH | M37: =+LEFT(C37,3) -> B02 | N37: ="`"&VLOOKUP(D37,'B02_Mapping fields'!B:C,2,FALSE)&"`" -> `0610_crryng_amnt_ifrs` | Y37: =+",CASE WHEN "&N37&" >= 0 THEN 0 ELSE 1 END AS "&B37 -> ,CASE WHEN `0610_crryng_amnt_ifrs` >= 0 THEN 0 ELSE 1 END AS v_2_0037 | Z37: =+"SUM("&B37&") AS LVL2_H_"&MID(N37,2,LEN(N37)-2)&"," -> SUM(v_2_0037) AS LVL2_H_0610_crryng_amnt_ifrs,
A38: 0038 | B38: =CONCATENATE("v_2_",A38) -> v_2_0038 | C38: B02.00 | D38: =VLOOKUP(CONCATENATE(C38,"_",E38),'Data types'!A:E,4,FALSE) -> 0620 | E38: Balance sheet item according to IFRS | F38: =VLOOKUP(CONCATENATE(C38,"_",E38),'Data types'!A:F,6,FALSE) -> String: Drop-down | G38: x | I38: Drop down values must be respected. | K38: The drop down values must be respected. | L38: =+IF(G38="X","HIGH","WARNING") -> HIGH | M38: =+LEFT(C38,3) -> B02 | N38: ="`"&VLOOKUP(D38,'B02_Mapping fields'!B:C,2,FALSE)&"`" -> `0620_blnc_sht_ifrs` | Y38: =+",CASE WHEN "&N38&" IN ('010 Financial liabilities held for trading', '070 Financial liabilities at fair value through profit or loss', '110 Financial liabilities at amortized cost', '280 Other liabilities', '300 Total equity') THEN 0 ELSE 1 END AS "&B38 -> ,CASE WHEN `0620_blnc_sht_ifrs` IN ('010 Financial liabilities held for trading', '070 Financial liabilities at fair value through profit or loss', '110 Financial liabilities at amortized cost', '280 Other liabilities', '300 Total equity') THEN 0 ELSE 1 END AS v_2_0038 | Z38: =+"SUM("&B38&") AS LVL2_H_"&MID(N38,2,LEN(N38)-2)&"," -> SUM(v_2_0038) AS LVL2_H_0620_blnc_sht_ifrs,
A39: 0040 | B39: =CONCATENATE("v_2_",A39) -> v_2_0040 | C39: B03.00 | D39: =VLOOKUP(CONCATENATE(C39,"_",E39),'Data types'!A:E,4,FALSE) -> 0030 | E39: Insolvency ranking | F39: =VLOOKUP(CONCATENATE(C39,"_",E39),'Data types'!A:F,6,FALSE) -> Numeric: Integer | G39: X | I39: Numeric values from 1 onwards must be reported. | K39: Numeric values from 1 onwards must be reported. | L39: =+IF(G39="X","HIGH","WARNING") -> HIGH | M39: =+LEFT(C39,3) -> B03 | Z39: =+"SUM("&B39&") AS LVL1_"&MID(N39,2,LEN(N39)-2)&"," -> #VALUE!
A40: 0041 | B40: =CONCATENATE("v_2_",A40) -> v_2_0041 | C40: B03.00 | D40: =VLOOKUP(CONCATENATE(C40,"_",E40),'Data types'!A:E,4,FALSE) -> 0040 | E40: ISDA Protocol Resolution Stay of the reporting entity | F40: =VLOOKUP(CONCATENATE(C40,"_",E40),'Data types'!A:F,6,FALSE) -> String: Drop down | G40: X | I40: Drop down values must be respected. | K40: The drop down values must be respected. | L40: =+IF(G40="X","HIGH","WARNING") -> HIGH | M40: =+LEFT(C40,3) -> B03 | Z40: =+"SUM("&B40&") AS LVL1_"&MID(N40,2,LEN(N40)-2)&"," -> #VALUE!
A41: 0042 | B41: =CONCATENATE("v_2_",A41) -> v_2_0042 | C41: B03.00 | D41: =VLOOKUP(CONCATENATE(C41,"_",E41),'Data types'!A:E,4,FALSE) -> 0050 | E41: Recognition Resolution Stay of counterparty | F41: =VLOOKUP(CONCATENATE(C41,"_",E41),'Data types'!A:F,6,FALSE) -> String: Drop down | G41: X | I41: Drop down values must be respected. | K41: The drop down values must be respected. | L41: =+IF(G41="X","HIGH","WARNING") -> HIGH | M41: =+LEFT(C41,3) -> B03 | Z41: =+"SUM("&B41&") AS LVL1_"&MID(N41,2,LEN(N41)-2)&"," -> #VALUE!
A42: 0043 | B42: =CONCATENATE("v_2_",A42) -> v_2_0043 | C42: B03.00 | D42: =VLOOKUP(CONCATENATE(C42,"_",E42),'Data types'!A:E,4,FALSE) -> 0070 | E42: Governing law of the Master agreement | F42: =VLOOKUP(CONCATENATE(C42,"_",E42),'Data types'!A:F,6,FALSE) -> String: ISO 3166-1 alpha 2 / ISO 3166-2 | G42: X | I42: Check if the reported field respects the ISO 3166-1 alpha-2 code or 3166-2. | K42: The field must be reported using the ISO 3166-1 alpha-2 code or 3166-2. | L42: =+IF(G42="X","HIGH","WARNING") -> HIGH | M42: =+LEFT(C42,3) -> B03 | Z42: =+"SUM("&B42&") AS LVL1_"&MID(N42,2,LEN(N42)-2)&"," -> #VALUE!
A43: 0044 | B43: =CONCATENATE("v_2_",A43) -> v_2_0044 | C43: B03.00 | D43: =VLOOKUP(CONCATENATE(C43,"_",E43),'Data types'!A:E,4,FALSE) -> 0080 | E43: Net mark-to-market value | F43: =VLOOKUP(CONCATENATE(C43,"_",E43),'Data types'!A:F,6,FALSE) -> Numeric: 2 decimals | G43: X | I43: Check if the reported field is higher than 0. | K43: The reported amount should be positive. | L43: =+IF(G43="X","HIGH","WARNING") -> HIGH | M43: =+LEFT(C43,3) -> B03 | Z43: =+"SUM("&B43&") AS LVL1_"&MID(N43,2,LEN(N43)-2)&"," -> #VALUE!
A44: 0045 | B44: =CONCATENATE("v_2_",A44) -> v_2_0045 | C44: B03.00 | D44: =VLOOKUP(CONCATENATE(C44,"_",E44),'Data types'!A:E,4,FALSE) -> 0100 | E44: Estimated close-out amount | F44: =VLOOKUP(CONCATENATE(C44,"_",E44),'Data types'!A:F,6,FALSE) -> Numeric: 2 decimals | H44: X | I44: Check if the reported field is higher than or equal 0. | K44: The reported amount should be positive or zero. Negative amounts should be duly justified by the reporting entity. | L44: =+IF(G44="X","HIGH","WARNING") -> WARNING | M44: =+LEFT(C44,3) -> B03 | Z44: =+"SUM("&B44&") AS LVL1_"&MID(N44,2,LEN(N44)-2)&"," -> #VALUE!
A45: 0046 | B45: =CONCATENATE("v_2_",A45) -> v_2_0046 | C45: B03.00 | D45: =VLOOKUP(CONCATENATE(C45,"_",E45),'Data types'!A:E,4,FALSE) -> 0110 | E45: Estimated early termination amount | F45: =VLOOKUP(CONCATENATE(C45,"_",E45),'Data types'!A:F,6,FALSE) -> Numeric: 2 decimals | G45: X | I45: Check if the reported field is equal or higher than 0. | K45: The reported amount should be equal or higher than zero. | L45: =+IF(G45="X","HIGH","WARNING") -> HIGH | M45: =+LEFT(C45,3) -> B03 | Z45: =+"SUM("&B45&") AS LVL1_"&MID(N45,2,LEN(N45)-2)&"," -> #VALUE!
A46: 0047 | B46: =CONCATENATE("v_2_",A46) -> v_2_0047 | C46: B03.00 | D46: =VLOOKUP(CONCATENATE(C46,"_",E46),'Data types'!A:E,4,FALSE) -> 0110 | E46: Estimated early termination amount | F46: =VLOOKUP(CONCATENATE(C46,"_",E46),'Data types'!A:F,6,FALSE) -> Numeric: 2 decimals | G46: X | I46: Check if the reported field is equal to: c0080 - c0090 + c0100. | J46: c0080 > c0090 | K46: The reported field should be equal to: c0080 - c0090 + c0100 for derivatives that are not fully collateralised. | L46: =+IF(G46="X","HIGH","WARNING") -> HIGH | M46: =+LEFT(C46,3) -> B03 | Z46: =+"SUM("&B46&") AS LVL1_"&MID(N46,2,LEN(N46)-2)&"," -> #VALUE!
A47: 0048 | B47: =CONCATENATE("v_2_",A47) -> v_2_0048 | C47: B03.00 | D47: =VLOOKUP(CONCATENATE(C47,"_",E47),'Data types'!A:E,4,FALSE) -> 0110 | E47: Estimated early termination amount | F47: =VLOOKUP(CONCATENATE(C47,"_",E47),'Data types'!A:F,6,FALSE) -> Numeric: 2 decimals | G47: X | I47: Check if the reported field is equal to zero | J47: c0080 <= c0090 | K47: The reported field should be equal to zero for fully collateralised derivatives. | L47: =+IF(G47="X","HIGH","WARNING") -> HIGH | M47: =+LEFT(C47,3) -> B03 | Z47: =+"SUM("&B47&") AS LVL1_"&MID(N47,2,LEN(N47)-2)&"," -> #VALUE!
A48: 0050 | B48: =CONCATENATE("v_2_",A48) -> v_2_0050 | C48: B04.00 | D48: =VLOOKUP(CONCATENATE(C48,"_",E48),'Data types'!A:E,4,FALSE) -> 0030 | E48: Insolvency ranking | F48: =VLOOKUP(CONCATENATE(C48,"_",E48),'Data types'!A:F,6,FALSE) -> Numeric: Integer | G48: X | I48: Numeric values from 1 onwards must be reported. | K48: Numeric values from 1 onwards must be reported. | L48: =+IF(G48="X","HIGH","WARNING") -> HIGH | M48: =+LEFT(C48,3) -> B04 | Z48: =+"SUM("&B48&") AS LVL1_"&MID(N48,2,LEN(N48)-2)&"," -> #VALUE!
A49: 0051 | B49: =CONCATENATE("v_2_",A49) -> v_2_0051 | C49: B04.00 | D49: =VLOOKUP(CONCATENATE(C49,"_",E49),'Data types'!A:E,4,FALSE) -> 0050 | E49: Governing law of the Master agreement | F49: =VLOOKUP(CONCATENATE(C49,"_",E49),'Data types'!A:F,6,FALSE) -> String: ISO 3166-1 alpha 2 / ISO 3166-2 | G49: X | I49: Check if the reported field respects the ISO 3166-1 alpha-2 code or 3166-2. | K49: The field must be reported using the ISO 3166-1 alpha-2 or 3166-2 code. | L49: =+IF(G49="X","HIGH","WARNING") -> HIGH | M49: =+LEFT(C49,3) -> B04 | Z49: =+"SUM("&B49&") AS LVL1_"&MID(N49,2,LEN(N49)-2)&"," -> #VALUE!
A50: 0052 | B50: =CONCATENATE("v_2_",A50) -> v_2_0052 | C50: B04.00 | D50: =VLOOKUP(CONCATENATE(C50,"_",E50),'Data types'!A:E,4,FALSE) -> 0060 | E50: Net mark-to-market value | F50: =VLOOKUP(CONCATENATE(C50,"_",E50),'Data types'!A:F,6,FALSE) -> Numeric: 2 decimals | G50: X | I50: Check if the reported field is higher than 0. | K50: The reported amount should be positive. | L50: =+IF(G50="X","HIGH","WARNING") -> HIGH | M50: =+LEFT(C50,3) -> B04 | Z50: =+"SUM("&B50&") AS LVL1_"&MID(N50,2,LEN(N50)-2)&"," -> #VALUE!
A51: 0053 | B51: =CONCATENATE("v_2_",A51) -> v_2_0053 | C51: B05.00 | D51: =VLOOKUP(CONCATENATE(C51,"_",E51),'Data types'!A:E,4,FALSE) -> 0030 | E51: Governing law | F51: =VLOOKUP(CONCATENATE(C51,"_",E51),'Data types'!A:F,6,FALSE) -> String: ISO 3166-1 alpha 2 / ISO 3166-2 | G51: X | I51: Check if the reported field respects the ISO 3166-1 alpha-2 code or 3166-2 | K51: The field must be reported using the ISO 3166-1 alpha-2 or 3166-2 code. | L51: =+IF(G51="X","HIGH","WARNING") -> HIGH | M51: =+LEFT(C51,3) -> B05 | N51: ="`"&VLOOKUP(D51,'B05_Mapping fields'!B:C,2,FALSE)&"`" -> `0030_governing_law` | Y51: =+",CASE WHEN ("&N51&" REGEXP '^[A-Z]{2}$' OR "&N51&" REGEXP '^[A-Z]{2}-[A-Z0-9]{1,3}$') AND "&N51&" IS NOT MISSING THEN 0 ELSE 1 END AS "&B51 -> ,CASE WHEN (`0030_governing_law` REGEXP '^[A-Z]{2}$' OR `0030_governing_law` REGEXP '^[A-Z]{2}-[A-Z0-9]{1,3}$') AND `0030_governing_law` IS NOT MISSING THEN 0 ELSE 1 END AS v_2_0053 | Z51: =+"SUM("&B51&") AS LVL2_H_"&MID(N51,2,LEN(N51)-2)&"," -> SUM(v_2_0053) AS LVL2_H_0030_governing_law,
A52: 0054 | B52: =CONCATENATE("v_2_",A52) -> v_2_0054 | C52: B05.00 | D52: =VLOOKUP(CONCATENATE(C52,"_",E52),'Data types'!A:E,4,FALSE) -> 0050 | E52: Type of guarantee | F52: =VLOOKUP(CONCATENATE(C52,"_",E52),'Data types'!A:F,6,FALSE) -> String: Drop down | G52: X | I52: Drop down values must be respected. | K52: The drop down values must be respected. | L52: =+IF(G52="X","HIGH","WARNING") -> HIGH | M52: =+LEFT(C52,3) -> B05 | N52: ="`"&VLOOKUP(D52,'B05_Mapping fields'!B:C,2,FALSE)&"`" -> `0050_typ_guarantee` | Y52: =+",CASE WHEN "&N52&" IN ('Issuance', 'Counterparty', 'Unlimited', 'Other types of guarantee than issuance guarantees, counterparty guarantees and unlimited guarantees') THEN 0 ELSE 1 END AS "&B52 -> ,CASE WHEN `0050_typ_guarantee` IN ('Issuance', 'Counterparty', 'Unlimited', 'Other types of guarantee than issuance guarantees, counterparty guarantees and unlimited guarantees') THEN 0 ELSE 1 END AS v_2_0054 | Z52: =+"SUM("&B52&") AS LVL2_H_"&MID(N52,2,LEN(N52)-2)&"," -> SUM(v_2_0054) AS LVL2_H_0050_typ_guarantee,
A53: 0055 | B53: =CONCATENATE("v_2_",A53) -> v_2_0055 | C53: B05.00 | D53: =VLOOKUP(CONCATENATE(C53,"_",E53),'Data types'!A:E,4,FALSE) -> 0060 | E53: Maximum amount of the guarantee | F53: =VLOOKUP(CONCATENATE(C53,"_",E53),'Data types'!A:F,6,FALSE) -> Numeric: 2 decimals | G53: X | I53: Check if the reported field is higher than or equal 0. | K53: The reported amount should be positive or zero. | L53: =+IF(G53="X","HIGH","WARNING") -> HIGH | M53: =+LEFT(C53,3) -> B05 | N53: ="`"&VLOOKUP(D53,'B05_Mapping fields'!B:C,2,FALSE)&"`" -> `0060_max_amnt_guarantee` | Y53: =+",CASE WHEN "&N53&" >= 0 THEN 0 ELSE 1 END AS "&B53 -> ,CASE WHEN `0060_max_amnt_guarantee` >= 0 THEN 0 ELSE 1 END AS v_2_0055 | Z53: =+"SUM("&B53&") AS LVL2_H_"&MID(N53,2,LEN(N53)-2)&"," -> SUM(v_2_0055) AS LVL2_H_0060_max_amnt_guarantee,
A54: 0056 | B54: =CONCATENATE("v_2_",A54) -> v_2_0056 | C54: B05.00 | D54: =VLOOKUP(CONCATENATE(C54,"_",E54),'Data types'!A:E,4,FALSE) -> 0070 | E54: Guarantee is secured | F54: =VLOOKUP(CONCATENATE(C54,"_",E54),'Data types'!A:F,6,FALSE) -> String: Drop down | G54: X | I54: Drop down values must be respected. | K54: The drop down values must be respected. | L54: =+IF(G54="X","HIGH","WARNING") -> HIGH | M54: =+LEFT(C54,3) -> B05 | N54: ="`"&VLOOKUP(D54,'B05_Mapping fields'!B:C,2,FALSE)&"`" -> `0070_flg_scrd` | Y54: =+",CASE WHEN "&N54&" IN ('Secured', 'Unsecured') THEN 0 ELSE 1 END AS "&B54 -> ,CASE WHEN `0070_flg_scrd` IN ('Secured', 'Unsecured') THEN 0 ELSE 1 END AS v_2_0056 | Z54: =+"SUM("&B54&") AS LVL2_H_"&MID(N54,2,LEN(N54)-2)&"," -> SUM(v_2_0056) AS LVL2_H_0070_flg_scrd,
A55: 0057 | B55: =CONCATENATE("v_2_",A55) -> v_2_0057 | C55: B05.00 | D55: =VLOOKUP(CONCATENATE(C55,"_",E55),'Data types'!A:E,4,FALSE) -> 0080 | E55: Current value of the collateral | F55: =VLOOKUP(CONCATENATE(C55,"_",E55),'Data types'!A:F,6,FALSE) -> Numeric: 2 decimals | G55: X | I55: Check if the reported field is higher than or equal 0. | J55: c0070 = "Secured" | K55: The reported amount should be positive or zero. | L55: =+IF(G55="X","HIGH","WARNING") -> HIGH | M55: =+LEFT(C55,3) -> B05 | N55: ="`"&VLOOKUP(D55,'B05_Mapping fields'!B:C,2,FALSE)&"`" -> `0080_amnt_clltrl` | O55: 0070 | P55: ="`"&VLOOKUP(O55,'B05_Mapping fields'!B:C,2,FALSE)&"`" -> `0070_flg_scrd` | Y55: =+",CASE WHEN "&N55&" >= 0 AND "&P55&" = 'Secured' THEN 0 ELSE 1 END AS "&B55 -> ,CASE WHEN `0080_amnt_clltrl` >= 0 AND `0070_flg_scrd` = 'Secured' THEN 0 ELSE 1 END AS v_2_0057 | Z55: =+"SUM("&B55&") AS LVL2_H_"&MID(N55,2,LEN(N55)-2)&"," -> SUM(v_2_0057) AS LVL2_H_0080_amnt_clltrl,
A56: 0058 | B56: =CONCATENATE("v_2_",A56) -> v_2_0058 | C56: B90.00 | D56: =VLOOKUP(CONCATENATE(C56,"_",E56),'Data types'!A:E,4,FALSE) -> 0030 | E56: Counterparty within the resolution group | F56: =VLOOKUP(CONCATENATE(C56,"_",E56),'Data types'!A:F,6,FALSE) -> String: Drop-down | G56: X | I56: Drop down values must be respected. | K56: The drop down values must be respected. | L56: =+IF(G56="X","HIGH","WARNING") -> HIGH | M56: =+LEFT(C56,3) -> B90 | N56: ="`"&VLOOKUP(D56,'B90_Maping fields'!B:C,2,FALSE)&"`" -> `0030_cntrprty_rsltn_grp` | Y56: =+",CASE WHEN "&N56&" IN ('Intragroup and intra-resolution group', 'Intragroup but not intra-resolution group', 'No') THEN 0 ELSE 1 END AS "&B56 -> ,CASE WHEN `0030_cntrprty_rsltn_grp` IN ('Intragroup and intra-resolution group', 'Intragroup but not intra-resolution group', 'No') THEN 0 ELSE 1 END AS v_2_0058 | Z56: =+"SUM("&B56&") AS LVL2_H_"&MID(N56,2,LEN(N56)-2)&"," -> SUM(v_2_0058) AS LVL2_H_0030_cntrprty_rsltn_grp,
A57: 0059 | B57: =CONCATENATE("v_2_",A57) -> v_2_0059 | C57: B90.00 | D57: =VLOOKUP(CONCATENATE(C57,"_",E57),'Data types'!A:E,4,FALSE) -> 0080 | E57: Counterparty Type | F57: =VLOOKUP(CONCATENATE(C57,"_",E57),'Data types'!A:F,6,FALSE) -> String: Drop-down | G57: X | I57: Drop down values must be respected. | K57: The drop down values must be respected. | L57: =+IF(G57="X","HIGH","WARNING") -> HIGH | M57: =+LEFT(C57,3) -> B90 | N57: ="`"&VLOOKUP(D57,'B90_Maping fields'!B:C,2,FALSE)&"`" -> `0080_cntrprty_typ` | Y57: =+",CASE WHEN "&N57&" IN ('"&Z57&") THEN 0 ELSE 1 END AS "&B57 -> ,CASE WHEN `0080_cntrprty_typ` IN ('SUM(v_2_0059) AS LVL2_H_0080_cntrprty_typ,) THEN 0 ELSE 1 END AS v_2_0059 | Z57: =+"SUM("&B57&") AS LVL2_H_"&MID(N57,2,LEN(N57)-2)&"," -> SUM(v_2_0059) AS LVL2_H_0080_cntrprty_typ,
A58: 0060 | B58: =CONCATENATE("v_2_",A58) -> v_2_0060 | C58: B90.00 | D58: =VLOOKUP(CONCATENATE(C58,"_",E58),'Data types'!A:E,4,FALSE) -> 0090 | E58: Country of the counterparty | F58: =VLOOKUP(CONCATENATE(C58,"_",E58),'Data types'!A:F,6,FALSE) -> String: ISO 3166-1 | G58: X | I58: Check if the reported field respects the ISO 3166-1 alpha-2 code. | J58: c0080 ≠ "XX" OR "99" | K58: The field must be reported using the ISO 3166-1 alpha-2 code. | L58: =+IF(G58="X","HIGH","WARNING") -> HIGH | M58: =+LEFT(C58,3) -> B90 | N58: ="`"&VLOOKUP(D58,'B90_Maping fields'!B:C,2,FALSE)&"`" -> `0090_cntry_cntrprty` | O58: 0080 | P58: ="`"&VLOOKUP(O58,'B90_Maping fields'!B:C,2,FALSE)&"`" -> `0080_cntrprty_typ` | Y58: =+",CASE WHEN ("&N58&" REGEXP '^[A-Z]{2}$' OR "&N58&" REGEXP '^[A-Z]{2}-[A-Z0-9]{1,3}$') AND "&N58&" IS NOT MISSING AND "&P58&" NOT IN ('XX', '99') THEN 0 ELSE 1 END AS "&B58 -> ,CASE WHEN (`0090_cntry_cntrprty` REGEXP '^[A-Z]{2}$' OR `0090_cntry_cntrprty` REGEXP '^[A-Z]{2}-[A-Z0-9]{1,3}$') AND `0090_cntry_cntrprty` IS NOT MISSING AND `0080_cntrprty_typ` NOT IN ('XX', '99') THEN 0 ELSE 1 END AS v_2_0060 | Z58: =+"SUM("&B58&") AS LVL2_H_"&MID(N58,2,LEN(N58)-2)&"," -> SUM(v_2_0060) AS LVL2_H_0090_cntry_cntrprty,
A59: 0061 | B59: =CONCATENATE("v_2_",A59) -> v_2_0061 | C59: B90.00 | D59: =VLOOKUP(CONCATENATE(C59,"_",E59),'Data types'!A:E,4,FALSE) -> 0100 | E59: Relevant amount for Bail-in/WDC | F59: =VLOOKUP(CONCATENATE(C59,"_",E59),'Data types'!A:F,6,FALSE) -> Numeric: 2 decimals | H59: X | I59: Check if the reported field is equal 0. | J59: c0030 ≠ "No" | K59: Positive values are allowed in case intragroup liabilities do not meet the conditions set forth in article 44(2)h BRRD and should be duly justified by the reporting entity | L59: =+IF(G59="X","HIGH","WARNING") -> WARNING | M59: =+LEFT(C59,3) -> B90 | N59: ="`"&VLOOKUP(D59,'B90_Maping fields'!B:C,2,FALSE)&"`" -> `0100_rlvnt_amnt_wdc` | O59: 0030 | P59: ="`"&VLOOKUP(O59,'B90_Maping fields'!B:C,2,FALSE)&"`" -> `0030_cntrprty_rsltn_grp` | Y59: =+",CASE WHEN "&N59&" = 0 AND "&P59&" != 'No' THEN 0 ELSE 1 END AS "&B59 -> ,CASE WHEN `0100_rlvnt_amnt_wdc` = 0 AND `0030_cntrprty_rsltn_grp` != 'No' THEN 0 ELSE 1 END AS v_2_0061 | Z59: =+"SUM("&B59&") AS LVL2_W_"&MID(N59,2,LEN(N59)-2)&"," -> SUM(v_2_0061) AS LVL2_W_0100_rlvnt_amnt_wdc,

Sheet Data types
A1: Tech | B1: Tab | C1: DP | D1: Column | E1: Label | F1: Data type label | G1: Data type | H1: Type of constrain | I1: Treatment of "Not applicable" (if cell is grey out, input is not expected) | J1: Treatment of "Not available" (if cell is grey out, input is not expected) | K1: FORMATS control | L1: aux_1 | M1: CASE WHEN | N1: QUERY
A2: =CONCATENATE(B2,"_",E2) -> B99.00_Name of Legal Entity | B2: B99.00 | C2: =CONCATENATE(B2,";c",D2) -> B99.00;c0010 | D2: 0010 | E2: Name of Legal Entity | F2: =CONCATENATE(G2,": ",H2) -> String: Free text | G2: String | H2: Free text
A3: =CONCATENATE(B3,"_",E3) -> B99.00_LEI of Legal Entity | B3: B99.00 | C3: =CONCATENATE(B3,";c",D3) -> B99.00;c0020 | D3: 0020 | E3: LEI of Legal Entity | F3: =CONCATENATE(G3,": ",H3) -> String: Free text | G3: String | H3: Free text
A4: =CONCATENATE(B4,"_",E4) -> B99.00_Country of incorporation | B4: B99.00 | C4: =CONCATENATE(B4,";c",D4) -> B99.00;c0030 | D4: 0030 | E4: Country of incorporation | F4: =CONCATENATE(G4,": ",H4) -> String: ISO 3166-1 | G4: String | H4: ISO 3166-1
A5: =CONCATENATE(B5,"_",E5) -> B99.00_Name of the ultimate parent entity | B5: B99.00 | C5: =CONCATENATE(B5,";c",D5) -> B99.00;c0040 | D5: 0040 | E5: Name of the ultimate parent entity | F5: =CONCATENATE(G5,": ",H5) -> String: Free text | G5: String | H5: Free text
A6: =CONCATENATE(B6,"_",E6) -> B99.00_LEI of the ultimate parent entity | B6: B99.00 | C6: =CONCATENATE(B6,";c",D6) -> B99.00;c0041 | D6: 0041 | E6: LEI of the ultimate parent entity | F6: =CONCATENATE(G6,": ",H6) -> String: Free text | G6: String | H6: Free text
A7: =CONCATENATE(B7,"_",E7) -> B99.00_Name of the Resolution Entity | B7: B99.00 | C7: =CONCATENATE(B7,";c",D7) -> B99.00;c0050 | D7: 0050 | E7: Name of the Resolution Entity | F7: =CONCATENATE(G7,": ",H7) -> String: Free text | G7: String | H7: Free text
A8: =CONCATENATE(B8,"_",E8) -> B99.00_LEI of the Resolution Entity | B8: B99.00 | C8: =CONCATENATE(B8,";c",D8) -> B99.00;c0051 | D8: 0051 | E8: LEI of the Resolution Entity | F8: =CONCATENATE(G8,": ",H8) -> String: Free text | G8: String | H8: Free text
A9: =CONCATENATE(B9,"_",E9) -> B99.00_Reporting entity type | B9: B99.00 | C9: =CONCATENATE(B9,";c",D9) -> B99.00;c0060 | D9: 0060 | E9: Reporting entity type | F9: =CONCATENATE(G9,": ",H9) -> String: Drop-down | G9: String | H9: Drop-down
A10: =CONCATENATE(B10,"_",E10) -> B99.00_Reference date | B10: B99.00 | C10: =CONCATENATE(B10,";c",D10) -> B99.00;c0070 | D10: 0070 | E10: Reference date | F10: =CONCATENATE(G10,": ",H10) -> Date: yyyy-mm-dd hh:mm:ss | G10: Date | H10: yyyy-mm-dd hh:mm:ss
A11: =CONCATENATE(B11,"_",E11) -> B99.00_Reported currency | B11: B99.00 | C11: =CONCATENATE(B11,";c",D11) -> B99.00;c0080 | D11: 0080 | E11: Reported currency | F11: =CONCATENATE(G11,": ",H11) -> String: 3-letters ISO 4217 | G11: String | H11: 3-letters ISO 4217
A12: =CONCATENATE(B12,"_",E12) -> B99.00_EUR exchange rate | B12: B99.00 | C12: =CONCATENATE(B12,";c",D12) -> B99.00;c0090 | D12: 0090 | E12: EUR exchange rate | F12: =CONCATENATE(G12,": ",H12) -> Numeric: 4 decimals | G12: Numeric | H12: 4 decimals
A13: =CONCATENATE(B13,"_",E13) -> B01.00_Row number | B13: B01.00 | C13: =CONCATENATE(B13,";c",D13) -> B01.00;c0010 | D13: 0010 | E13: Row number | F13: =CONCATENATE(G13,": ",H13) -> Numeric: Integer | G13: Numeric | H13: Integer
... A16: =CONCATENATE(B16,"_",E16) -> B01.00_Counterparty type | B16: B01.00 | C16: =CONCATENATE(B16,";c",D16) -> B01.00;c0040 | D16: 0040 | E16: Counterparty type | F16: =CONCATENATE(G16,": ",H16) -> String: Drop-down | G16: String | H16: Drop-down
A17: =CONCATENATE(B17,"_",E17) -> B01.00_Relevant amount for Bail-in/WDC | B17: B01.00 | C17: =CONCATENATE(B17,";c",D17) -> B01.00;c0050 | D17: 0050 | E17: Relevant amount for Bail-in/WDC | F17: =CONCATENATE(G17,": ",H17) -> Numeric: 2 decimals | G17: Numeric | H17: 2 decimals | I17: Input "Not applicable"
A18: =CONCATENATE(B18,"_",E18) -> B01.00_Amount excluded from Bail-in/WDC | B18: B01.00 | C18: =CONCATENATE(B18,";c",D18) -> B01.00;c0060 | D18: 0060 | E18: Amount excluded from Bail-in/WDC | F18: =CONCATENATE(G18,": ",H18) -> Numeric: 2 decimals | G18: Numeric | H18: 2 decimals
A19: =CONCATENATE(B19,"_",E19) -> B02.00_Row number | B19: B02.00 | C19: =CONCATENATE(B19,";c",D19) -> B02.00;c0010 | D19: 0010 | E19: Row number | F19: =CONCATENATE(G19,": ",H19) -> Numeric: Integer | G19: Numeric | H19: Integer | K19: =+"FRMT_"&L19 -> FRMT_0010_row_nmbr | L19: =+VLOOKUP(D19,'B02_Mapping fields'!B:C,2,FALSE) -> 0010_row_nmbr | M19: =+",CASE WHEN cast(`"&L19&"` as string) RLIKE '^[0-9]+$' AND CAST(`"&L19&_xlfn._LONGTEXT("` AS STRING) NOT IN ('N/A','11111111111','11111111111.00','11111111111.000000','1111-11-11','0000-00-00','0001-01-01','9999-12-31','MISS','00000','99999999999','999999999999999','99999999999.00','99999999999.000000','-9999.9999','','Not applicable','XXX')"," THEN 0 ELSE 1 END AS ")&K19 -> ,CASE WHEN cast(`0010_row_nmbr` as string) RLIKE '^[0-9]+$' AND CAST(`0010_row_nmbr` AS STRING) NOT IN ('N/A','11111111111','11111111111.00','11111111111.000000','1111-11-11','0000-00-00','0001-01-01','9999-12-31','MISS','00000','99999999999','999999999999999','99999999999.00','99999999999.000000','-9999.9999','','Not applicable','XXX') THEN 0 ELSE 1 END AS FRMT_0010_row_nmbr | N19: =+"SUM("&K19&") AS `"&K19&"`," -> SUM(FRMT_0010_row_nmbr) AS `FRMT_0010_row_nmbr`,
A20: =CONCATENATE(B20,"_",E20) -> B02.00_Unique internal identification number | B20: B02.00 | C20: =CONCATENATE(B20,";c",D20) -> B02.00;c0020 | D20: 0020 | E20: Unique internal identification number | F20: =CONCATENATE(G20,": ",H20) -> String: Free text | G20: String | H20: Free text | K20: =+"FRMT_"&L20 -> FRMT_0020_uniq_id | L20: =+VLOOKUP(D20,'B02_Mapping fields'!B:C,2,FALSE) -> 0020_uniq_id | M20: =+",CASE WHEN `"&L20&"` RLIKE '[A-Za-z]' and `"&L20&_xlfn._LONGTEXT("` NOT IN ('N/A','11111111111','11111111111.00','11111111111.000000','1111-11-11','0000-00-00','0001-01-01','9999-12-31','MISS','00000','99999999999','999999999999999','99999999999.00','99999999999.000000','-9999.9999','','Not applicable','XXX') THEN 0 ELS","E 1 END AS ")&K20 -> ,CASE WHEN `0020_uniq_id` RLIKE '[A-Za-z]' and `0020_uniq_id` NOT IN ('N/A','11111111111','11111111111.00','11111111111.000000','1111-11-11','0000-00-00','0001-01-01','9999-12-31','MISS','00000','99999999999','999999999999999','99999999999.00','99999999999.000000','-9999.9999','','Not applicable','XXX') THEN 0 ELSE 1 END AS FRMT_0020_uniq_id | N20: =+"SUM("&K20&") AS `"&K20&"`," -> SUM(FRMT_0020_uniq_id) AS `FRMT_0020_uniq_id`,
A21: =CONCATENATE(B21,"_",E21) -> B02.00_Unique identification number (known to the counterparty) | B21: B02.00 | C21: =CONCATENATE(B21,";c",D21) -> B02.00;c0030 | D21: 0030 | E21: Unique identification number (known to the counterparty) | F21: =CONCATENATE(G21,": ",H21) -> String: Free text | G21: String | H21: Free text | K21: =+"FRMT_"&L21 -> FRMT_0030_uniq_id_knwn_cntrprty | L21: =+VLOOKUP(D21,'B02_Mapping fields'!B:C,2,FALSE) -> 0030_uniq_id_knwn_cntrprty | M21: =+",CASE WHEN `"&L21&"` RLIKE '[A-Za-z]' and `"&L21&_xlfn._LONGTEXT("` NOT IN ('N/A','11111111111','11111111111.00','11111111111.000000','1111-11-11','0000-00-00','0001-01-01','9999-12-31','MISS','00000','99999999999','999999999999999','99999999999.00','99999999999.000000','-9999.9999','','Not applicable','XXX') THEN 0 ELS","E 1 END AS ")&K21 -> ,CASE WHEN `0030_uniq_id_knwn_cntrprty` RLIKE '[A-Za-z]' and `0030_uniq_id_knwn_cntrprty` NOT IN ('N/A','11111111111','11111111111.00','11111111111.000000','1111-11-11','0000-00-00','0001-01-01','9999-12-31','MISS','00000','99999999999','999999999999999','99999999999.00','99999999999.000000','-9999.9999','','Not applicable','XXX') THEN 0 ELSE 1 END AS FRMT_0030_uniq_id_knwn_cntrprty | N21: =+"SUM("&K21&") AS `"&K21&"`," -> SUM(FRMT_0030_uniq_id_knwn_cntrprty) AS `FRMT_0030_uniq_id_knwn_cntrprty`,
A22: =CONCATENATE(B22,"_",E22) -> B02.00_Type of the unique identifier (known to the counterparty) | B22: B02.00 | C22: =CONCATENATE(B22,";c",D22) -> B02.00;c0040 | D22: 0040 | E22: Type of the unique identifier (known to the counterparty) | F22: =CONCATENATE(G22,": ",H22) -> String: Free text, but fixed values for specific items | G22: String | H22: Free text, but fixed values for specific items | K22: =+"FRMT_"&L22 -> FRMT_0040_typ_uniq_id_knwn_cntrprty | L22: =+VLOOKUP(D22,'B02_Mapping fields'!B:C,2,FALSE) -> 0040_typ_uniq_id_knwn_cntrprty | M22: =+",CASE WHEN `"&L22&"` RLIKE '[A-Za-z]' AND `"&L22&_xlfn._LONGTEXT("` NOT IN ('N/A','11111111111','11111111111.00','11111111111.000000','1111-11-11','0000-00-00','0001-01-01','9999-12-31','MISS','00000','99999999999','999999999999999','99999999999.00','99999999999.000000','-9999.9999','','Not applicable','XXX') THEN 0 ELS","E 1 END AS ")&K22 -> ,CASE WHEN `0040_typ_uniq_id_knwn_cntrprty` RLIKE '[A-Za-z]' AND `0040_typ_uniq_id_knwn_cntrprty` NOT IN ('N/A','11111111111','11111111111.00','11111111111.000000','1111-11-11','0000-00-00','0001-01-01','9999-12-31','MISS','00000','99999999999','999999999999999','99999999999.00','99999999999.000000','-9999.9999','','Not applicable','XXX') THEN 0 ELSE 1 END AS FRMT_0040_typ_uniq_id_knwn_cntrprty | N22: =+"SUM("&K22&") AS `"&K22&"`," -> SUM(FRMT_0040_typ_uniq_id_knwn_cntrprty) AS `FRMT_0040_typ_uniq_id_knwn_cntrprty`,
A23: =CONCATENATE(B23,"_",E23) -> B02.00_Original amount issued in EUR | B23: B02.00 | C23: =CONCATENATE(B23,";c",D23) -> B02.00;c0050 | D23: 0050 | E23: Original amount issued in EUR | F23: =CONCATENATE(G23,": ",H23) -> Numeric: 2 decimals | G23: Numeric | H23: 2 decimals | I23: Input 999999999999999 | K23: =+"FRMT_"&L23 -> FRMT_0050_orgnl_amnt_eur | L23: =+VLOOKUP(D23,'B02_Mapping fields'!B:C,2,FALSE) -> 0050_orgnl_amnt_eur | M23: =+",CASE WHEN (CAST(ROUND(`"&L23&"`, 2) AS STRING) = CAST(`"&L23&"` AS STRING) AND CAST(`"&L23&"` AS STRING) NOT IN ('N/A','11111111111','11111111111.00','11111111111.000000','1111-11-11','0000-00-00','0001-01-01','9999-12-31','MISS','00000','99999999999','99999999999.00','99999999999.000000','-9999.9999','','Not applicable','XXX')) OR `"&L23&"`= 999999999999999.00 THEN 0 ELSE 1 END AS "&K23 -> ,CASE WHEN (CAST(ROUND(`0050_orgnl_amnt_eur`, 2) AS STRING) = CAST(`0050_orgnl_amnt_eur` AS STRING) AND CAST(`0050_orgnl_amnt_eur` AS STRING) NOT IN ('N/A','11111111111','11111111111.00','11111111111.000000','1111-11-11','0000-00-00','0001-01-01','9999-12-31','MISS','00000','99999999999','99999999999.00','99999999999.000000','-9999.9999','','Not applicable','XXX')) OR `0050_orgnl_amnt_eur`= 999999999999999.00 THEN 0 ELSE 1 END AS FRMT_0050_orgnl_amnt_eur | N23: =+"SUM("&K23&") AS `"&K23&"`," -> SUM(FRMT_0050_orgnl_amnt_eur) AS `FRMT_0050_orgnl_amnt_eur`,
A24: =CONCATENATE(B24,"_",E24) -> B02.00_Original amount issued in original currency | B24: B02.00 | C24: =CONCATENATE(B24,";c",D24) -> B02.00;c0060 | D24: 0060 | E24: Original amount issued in original currency | F24: =CONCATENATE(G24,": ",H24) -> Numeric: 2 decimals | G24: Numeric | H24: 2 decimals | I24: Input 999999999999999 | K24: =+"FRMT_"&L24 -> FRMT_0060_orgnl_amnt_fx | L24: =+VLOOKUP(D24,'B02_Mapping fields'!B:C,2,FALSE) -> 0060_orgnl_amnt_fx | M24: =+",CASE WHEN (CAST(ROUND(`"&L24&"`, 2) AS STRING) = CAST(`"&L24&"` AS STRING) AND CAST(`"&L24&"` AS STRING) NOT IN ('N/A','11111111111','11111111111.00','11111111111.000000','1111-11-11','0000-00-00','0001-01-01','9999-12-31','MISS','00000','99999999999','99999999999.00','99999999999.000000','-9999.9999','','Not applicable','XXX')) OR `"&L24&"`= 999999999999999.00 THEN 0 ELSE 1 END AS "&K24 -> ,CASE WHEN (CAST(ROUND(`0060_orgnl_amnt_fx`, 2) AS STRING) = CAST(`0060_orgnl_amnt_fx` AS STRING) AND CAST(`0060_orgnl_amnt_fx` AS STRING) NOT IN ('N/A','11111111111','11111111111.00','11111111111.000000','1111-11-11','0000-00-00','0001-01-01','9999-12-31','MISS','00000','99999999999','99999999999.00','99999999999.000000','-9999.9999','','Not applicable','XXX')) OR `0060_orgnl_amnt_fx`= 999999999999999.00 THEN 0 ELSE 1 END AS FRMT_0060_orgnl_amnt_fx | N24: =+"SUM("&K24&") AS `"&K24&"`," -> SUM(FRMT_0060_orgnl_amnt_fx) AS `FRMT_0060_orgnl_amnt_fx`,
A25: =CONCATENATE(B25,"_",E25) -> B02.00_Contract currency | B25: B02.00 | C25: =CONCATENATE(B25,";c",D25) -> B02.00;c0070 | D25: 0070 | E25: Contract currency | F25: =CONCATENATE(G25,": ",H25) -> String: 3-letters ISO 4217 | G25: String | H25: 3-letters ISO 4217 | I25: Input "XXX" | K25: =+"FRMT_"&L25 -> FRMT_0070_cntrct_crrncy | L25: =+VLOOKUP(D25,'B02_Mapping fields'!B:C,2,FALSE) -> 0070_cntrct_crrncy | M25: =+",CASE WHEN (LENGTH(`"&L25&"`) = 3 AND `"&L25&"` NOT IN ('N/A','11111111111','11111111111.00','11111111111.000000','1111-11-11','0000-00-00','0001-01-01','9999-12-31','MISS','00000','99999999999','99999999999.00','99999999999.000000','-9999.9999','','Not applicable')) OR `"&L25&"`='XXX' THEN 0 ELSE 1 END AS "&K25 -> ,CASE WHEN (LENGTH(`0070_cntrct_crrncy`) = 3 AND `0070_cntrct_crrncy` NOT IN ('N/A','11111111111','11111111111.00','11111111111.000000','1111-11-11','0000-00-00','0001-01-01','9999-12-31','MISS','00000','99999999999','99999999999.00','99999999999.000000','-9999.9999','','Not applicable')) OR `0070_cntrct_crrncy`='XXX' THEN 0 ELSE 1 END AS FRMT_0070_cntrct_crrncy | N25: =+"SUM("&K25&") AS `"&K25&"`," -> SUM(FRMT_0070_cntrct_crrncy) AS `FRMT_0070_cntrct_crrncy`,
A26: =CONCATENATE(B26,"_",E26) -> B02.00_Outstanding principal amount | B26: B02.00 | C26: =CONCATENATE(B26,";c",D26) -> B02.00;c0080 | D26: 0080 | E26: Outstanding principal amount | F26: =CONCATENATE(G26,": ",H26) -> Numeric: 2 decimals | G26: Numeric | H26: 2 decimals | K26: =+"FRMT_"&L26 -> FRMT_0080_otstndng_prncpl_amnt | L26: =+VLOOKUP(D26,'B02_Mapping fields'!B:C,2,FALSE) -> 0080_otstndng_prncpl_amnt | M26: =+",CASE WHEN CAST(ROUND(`"&L26&"`, 2) AS STRING) = CAST(`"&L26&"` AS STRING) AND CAST(`"&L26&_xlfn._LONGTEXT("` AS STRING) NOT IN ('N/A','11111111111','11111111111.00','11111111111.000000','1111-11-11','0000-00-00','0001-01-01','9999-12-31','MISS','00000','99999999999','99999999999.00','99999999999.000000','-9999.9999','','Not applicable','XXX') THEN 0 ELSE 1 END"," AS ")&K26 -> ,CASE WHEN CAST(ROUND(`0080_otstndng_prncpl_amnt`, 2) AS STRING) = CAST(`0080_otstndng_prncpl_amnt` AS STRING) AND CAST(`0080_otstndng_prncpl_amnt` AS STRING) NOT IN ('N/A','11111111111','11111111111.00','11111111111.000000','1111-11-11','0000-00-00','0001-01-01','9999-12-31','MISS','00000','99999999999','99999999999.00','99999999999.000000','-9999.9999','','Not applicable','XXX') THEN 0 ELSE 1 END AS FRMT_0080_otstndng_prncpl_amnt | N26: =+"SUM("&K26&") AS `"&K26&"`," -> SUM(FRMT_0080_otstndng_prncpl_amnt) AS `FRMT_0080_otstndng_prncpl_amnt`,
A27: =CONCATENATE(B27,"_",E27) -> B02.00_Portion of instrument or liability held by the reporting entity | B27: B02.00 | C27: =CONCATENATE(B27,";c",D27) -> B02.00;c0090 | D27: 0090 | E27: Portion of instrument or liability held by the reporting entity | F27: =CONCATENATE(G27,": ",H27) -> Numeric: 2 decimals | G27: Numeric | H27: 2 decimals | I27: Input 999999999999999 | K27: =+"FRMT_"&L27 -> FRMT_0090_prtn_amnt_rprtng_entty | L27: =+VLOOKUP(D27,'B02_Mapping fields'!B:C,2,FALSE) -> 0090_prtn_amnt_rprtng_entty | M27: =+",CASE WHEN (CAST(ROUND(`"&L27&"`, 2) AS STRING) = CAST(`"&L27&"` AS STRING) AND CAST(`"&L27&"` AS STRING) NOT IN ('N/A','11111111111','11111111111.00','11111111111.000000','1111-11-11','0000-00-00','0001-01-01','9999-12-31','MISS','00000','99999999999','99999999999.00','99999999999.000000','-9999.9999','','Not applicable','XXX')) OR `"&L27&"`= 999999999999999.00 THEN 0 ELSE 1 END AS "&K27 -> ,CASE WHEN (CAST(ROUND(`0090_prtn_amnt_rprtng_entty`, 2) AS STRING) = CAST(`0090_prtn_amnt_rprtng_entty` AS STRING) AND CAST(`0090_prtn_amnt_rprtng_entty` AS STRING) NOT IN ('N/A','11111111111','11111111111.00','11111111111.000000','1111-11-11','0000-00-00','0001-01-01','9999-12-31','MISS','00000','99999999999','99999999999.00','99999999999.000000','-9999.9999','','Not applicable','XXX')) OR `0090_prtn_amnt_rprtng_entty`= 999999999999999.00 THEN 0 ELSE 1 END AS FRMT_0090_prtn_amnt_rprtng_entty | N27: =+"SUM("&K27&") AS `"&K27&"`," -> SUM(FRMT_0090_prtn_amnt_rprtng_entty) AS `FRMT_0090_prtn_amnt_rprtng_entty`,
A28: =CONCATENATE(B28,"_",E28) -> B02.00_Accrued interest | B28: B02.00 | C28: =CONCATENATE(B28,";c",D28) -> B02.00;c0100 | D28: 0100 | E28: Accrued interest | F28: =CONCATENATE(G28,": ",H28) -> Numeric: 2 decimals | G28: Numeric | H28: 2 decimals | I28: Input 999999999999999 | J28: Leave blank | K28: =+"FRMT_"&L28 -> FRMT_0100_accrd_intrst_instrmnt | L28: =+VLOOKUP(D28,'B02_Mapping fields'!B:C,2,FALSE) -> 0100_accrd_intrst_instrmnt | M28: =+",CASE WHEN (CAST(ROUND(`"&L28&"`, 2) AS STRING) = CAST(`"&L28&"` AS STRING) AND CAST(`"&L28&"` AS STRING) NOT IN ('N/A','11111111111','11111111111.00','11111111111.000000','1111-11-11','0000-00-00','0001-01-01','9999-12-31','MISS','00000','99999999999','99999999999.00','99999999999.000000','-9999.9999','Not applicable','XXX')) OR `"&L28&"` = 999999999999999 OR CAST(`"&L28&"` AS STRING) = '' THEN 0 ELSE 1 END AS "&K28 -> ,CASE WHEN (CAST(ROUND(`0100_accrd_intrst_instrmnt`, 2) AS STRING) = CAST(`0100_accrd_intrst_instrmnt` AS STRING) AND CAST(`0100_accrd_intrst_instrmnt` AS STRING) NOT IN ('N/A','11111111111','11111111111.00','11111111111.000000','1111-11-11','0000-00-00','0001-01-01','9999-12-31','MISS','00000','99999999999','99999999999.00','99999999999.000000','-9999.9999','Not applicable','XXX')) OR `0100_accrd_intrst_instrmnt` = 999999999999999 OR CAST(`0100_accrd_intrst_instrmnt` AS STRING) = '' THEN 0 ELSE 1 END AS FRMT_0100_accrd_intrst_instrmnt | N28: =+"SUM("&K28&") AS `"&K28&"`," -> SUM(FRMT_0100_accrd_intrst_instrmnt) AS `FRMT_0100_accrd_intrst_instrmnt`,
A29: =CONCATENATE(B29,"_",E29) -> B02.00_Applicable fees and charges | B29: B02.00 | C29: =CONCATENATE(B29,";c",D29) -> B02.00;c0110 | D29: 0110 | E29: Applicable fees and charges | F29: =CONCATENATE(G29,": ",H29) -> Numeric: 2 decimals | G29: Numeric | H29: 2 decimals | I29: Input 999999999999999 | J29: Leave blank | K29: =+"FRMT_"&L29 -> FRMT_0110_applcbl_fees_charges | L29: =+VLOOKUP(D29,'B02_Mapping fields'!B:C,2,FALSE) -> 0110_applcbl_fees_charges | M29: =+",CASE WHEN (CAST(ROUND(`"&L29&"`, 2) AS STRING) = CAST(`"&L29&"` AS STRING) AND CAST(`"&L29&"` AS STRING) NOT IN ('N/A','11111111111','11111111111.00','11111111111.000000','1111-11-11','0000-00-00','0001-01-01','9999-12-31','MISS','00000','99999999999','99999999999.00','99999999999.000000','-9999.9999','Not applicable','XXX')) OR `"&L29&"` = 999999999999999 OR CAST(`"&L29&"` AS STRING) = '' THEN 0 ELSE 1 END AS "&K29 -> ,CASE WHEN (CAST(ROUND(`0110_applcbl_fees_charges`, 2) AS STRING) = CAST(`0110_applcbl_fees_charges` AS STRING) AND CAST(`0110_applcbl_fees_charges` AS STRING) NOT IN ('N/A','11111111111','11111111111.00','11111111111.000000','1111-11-11','0000-00-00','0001-01-01','9999-12-31','MISS','00000','99999999999','99999999999.00','99999999999.000000','-9999.9999','Not applicable','XXX')) OR `0110_applcbl_fees_charges` = 999999999999999 OR CAST(`0110_applcbl_fees_charges` AS STRING) = '' THEN 0 ELSE 1 END AS FRMT_0110_applcbl_fees_charges | N29: =+"SUM("&K29&") AS `"&K29&"`," -> SUM(FRMT_0110_applcbl_fees_charges) AS `FRMT_0110_applcbl_fees_charges`,
A30: =CONCATENATE(B30,"_",E30) -> B02.00_Outstanding amount | B30: B02.00 | C30: =CONCATENATE(B30,";c",D30) -> B02.00;c0120 | D30: 0120 | E30: Outstanding amount | F30: =CONCATENATE(G30,": ",H30) -> Numeric: 2 decimals | G30: Numeric | H30: 2 decimals | I30: Input 999999999999999 | K30: =+"FRMT_"&L30 -> FRMT_0120_otstndng_amnt | L30: =+VLOOKUP(D30,'B02_Mapping fields'!B:C,2,FALSE) -> 0120_otstndng_amnt | M30: =+",CASE WHEN (CAST(ROUND(`"&L30&"`, 2) AS STRING) = CAST(`"&L30&"` AS STRING) AND CAST(`"&L30&"` AS STRING) NOT IN ('N/A','11111111111','11111111111.00','11111111111.000000','1111-11-11','0000-00-00','0001-01-01','9999-12-31','MISS','00000','99999999999','99999999999.00','99999999999.000000','-9999.9999','','Not applicable','XXX')) OR `"&L30&"`= 999999999999999.00 THEN 0 ELSE 1 END AS "&K30 -> ,CASE WHEN (CAST(ROUND(`0120_otstndng_amnt`, 2) AS STRING) = CAST(`0120_otstndng_amnt` AS STRING) AND CAST(`0120_otstndng_amnt` AS STRING) NOT IN ('N/A','11111111111','11111111111.00','11111111111.000000','1111-11-11','0000-00-00','0001-01-01','9999-12-31','MISS','00000','99999999999','99999999999.00','99999999999.000000','-9999.9999','','Not applicable','XXX')) OR `0120_otstndng_amnt`= 999999999999999.00 THEN 0 ELSE 1 END AS FRMT_0120_otstndng_amnt | N30: =+"SUM("&K30&") AS `"&K30&"`," -> SUM(FRMT_0120_otstndng_amnt) AS `FRMT_0120_otstndng_amnt`,
A31: =CONCATENATE(B31,"_",E31) -> B02.00_Relevant amount for Bail-in/WDC | B31: B02.00 | C31: =CONCATENATE(B31,";c",D31) -> B02.00;c0130 | D31: 0130 | E31: Relevant amount for Bail-in/WDC | F31: =CONCATENATE(G31,": ",H31) -> Numeric: 2 decimals | G31: Numeric | H31: 2 decimals | K31: =+"FRMT_"&L31 -> FRMT_0130_rlvnt_amnt_wdc | L31: =+VLOOKUP(D31,'B02_Mapping fields'!B:C,2,FALSE) -> 0130_rlvnt_amnt_wdc | M31: =+",CASE WHEN CAST(ROUND(`"&L31&"`, 2) AS STRING) = CAST(`"&L31&"` AS STRING) AND CAST(`"&L31&_xlfn._LONGTEXT("` AS STRING) NOT IN ('N/A','11111111111','11111111111.00','11111111111.000000','1111-11-11','0000-00-00','0001-01-01','9999-12-31','MISS','00000','99999999999','99999999999.00','99999999999.000000','-9999.9999','','Not applicable','XXX') THEN 0 ELSE 1 END"," AS ")&K31 -> ,CASE WHEN CAST(ROUND(`0130_rlvnt_amnt_wdc`, 2) AS STRING) = CAST(`0130_rlvnt_amnt_wdc` AS STRING) AND CAST(`0130_rlvnt_amnt_wdc` AS STRING) NOT IN ('N/A','11111111111','11111111111.00','11111111111.000000','1111-11-11','0000-00-00','0001-01-01','9999-12-31','MISS','00000','99999999999','99999999999.00','99999999999.000000','-9999.9999','','Not applicable','XXX') THEN 0 ELSE 1 END AS FRMT_0130_rlvnt_amnt_wdc | N31: =+"SUM("&K31&") AS `"&K31&"`," -> SUM(FRMT_0130_rlvnt_amnt_wdc) AS `FRMT_0130_rlvnt_amnt_wdc`,
A32: =CONCATENATE(B32,"_",E32) -> B02.00_Nature of the liability | B32: B02.00 | C32: =CONCATENATE(B32,";c",D32) -> B02.00;c0140 | D32: 0140 | E32: Nature of the liability | F32: =CONCATENATE(G32,": ",H32) -> String: Drop-down | G32: String | H32: Drop-down | K32: =+"FRMT_"&L32 -> FRMT_0140_ntr_lblty | L32: =+VLOOKUP(D32,'B02_Mapping fields'!B:C,2,FALSE) -> 0140_ntr_lblty | M32: =+",CASE WHEN `"&L32&"` IN ('Registered Bond', 'Bearer Bond', 'Borrower Note Loan', 'Certificate of Deposit / Commercial paper', 'Title of ownership', 'Cash account/saving account', 'Term deposit', 'Loan', 'Bill of exchange ', 'Other') THEN 0 ELSE 1 END AS "&K32 -> ,CASE WHEN `0140_ntr_lblty` IN ('Registered Bond', 'Bearer Bond', 'Borrower Note Loan', 'Certificate of Deposit / Commercial paper', 'Title of ownership', 'Cash account/saving account', 'Term deposit', 'Loan', 'Bill of exchange ', 'Other') THEN 0 ELSE 1 END AS FRMT_0140_ntr_lblty | N32: =+"SUM("&K32&") AS `"&K32&"`," -> SUM(FRMT_0140_ntr_lblty) AS `FRMT_0140_ntr_lblty`,
A33: =CONCATENATE(B33,"_",E33) -> B02.00_Nature of the liability (if other) | B33: B02.00 | C33: =CONCATENATE(B33,";c",D33) -> B02.00;c0141 | D33: 0141 | E33: Nature of the liability (if other) | F33: =CONCATENATE(G33,": ",H33) -> String: Free text | G33: String | H33: Free text | K33: =+"FRMT_"&L33 -> FRMT_0141_ntr_lblty_othr | L33: =+VLOOKUP(D33,'B02_Mapping fields'!B:C,2,FALSE) -> 0141_ntr_lblty_othr | M33: =+",CASE WHEN `"&L33&"` RLIKE '[A-Za-z]' AND `"&L33&_xlfn._LONGTEXT("` NOT IN ('N/A','11111111111','11111111111.00','11111111111.000000','1111-11-11','0000-00-00','0001-01-01','9999-12-31','MISS','00000','99999999999','999999999999999','99999999999.00','99999999999.000000','-9999.9999','','Not applicable','XXX') THEN 0 ELS","E 1 END AS ")&K33 -> ,CASE WHEN `0141_ntr_lblty_othr` RLIKE '[A-Za-z]' AND `0141_ntr_lblty_othr` NOT IN ('N/A','11111111111','11111111111.00','11111111111.000000','1111-11-11','0000-00-00','0001-01-01','9999-12-31','MISS','00000','99999999999','999999999999999','99999999999.00','99999999999.000000','-9999.9999','','Not applicable','XXX') THEN 0 ELSE 1 END AS FRMT_0141_ntr_lblty_othr | N33: =+"SUM("&K33&") AS `"&K33&"`," -> SUM(FRMT_0141_ntr_lblty_othr) AS `FRMT_0141_ntr_lblty_othr`,
A34: =CONCATENATE(B34,"_",E34) -> B02.00_Structurally subordinated | B34: B02.00 | C34: =CONCATENATE(B34,";c",D34) -> B02.00;c0150 | D34: 0150 | E34: Structurally subordinated | F34: =CONCATENATE(G34,": ",H34) -> String: Drop-down | G34: String | H34: Drop-down | K34: =+"FRMT_"&L34 -> FRMT_0150_flg_strctrlly_sbrdntd | L34: =+VLOOKUP(D34,'B02_Mapping fields'!B:C,2,FALSE) -> 0150_flg_strctrlly_sbrdntd | M34: =+",CASE WHEN `"&L34&"` IN ('TRUE', 'FALSE') THEN 0 ELSE 1 END AS "&K34 -> ,CASE WHEN `0150_flg_strctrlly_sbrdntd` IN ('TRUE', 'FALSE') THEN 0 ELSE 1 END AS FRMT_0150_flg_strctrlly_sbrdntd | N34: =+"SUM("&K34&") AS `"&K34&"`," -> SUM(FRMT_0150_flg_strctrlly_sbrdntd) AS `FRMT_0150_flg_strctrlly_sbrdntd`,
A35: =CONCATENATE(B35,"_",E35) -> B02.00_Insolvency ranking | B35: B02.00 | C35: =CONCATENATE(B35,";c",D35) -> B02.00;c0160 | D35: 0160 | E35: Insolvency ranking | F35: =CONCATENATE(G35,": ",H35) -> Numeric: Integer | G35: Numeric | H35: Integer | K35: =+"FRMT_"&L35 -> FRMT_0160_rank_insolv | L35: =+VLOOKUP(D35,'B02_Mapping fields'!B:C,2,FALSE) -> 0160_rank_insolv | M35: =+",CASE WHEN CAST(`"&L35&"` AS STRING) RLIKE '^[0-9]+$' AND CAST(`"&L35&_xlfn._LONGTEXT("` AS STRING) NOT IN ('N/A','11111111111','11111111111.00','11111111111.000000','1111-11-11','0000-00-00','0001-01-01','9999-12-31','MISS','00000','99999999999','999999999999999','99999999999.00','99999999999.000000','-9999.9999','','Not applicable','XXX')"," THEN 0 ELSE 1 END AS ")&K35 -> ,CASE WHEN CAST(`0160_rank_insolv` AS STRING) RLIKE '^[0-9]+$' AND CAST(`0160_rank_insolv` AS STRING) NOT IN ('N/A','11111111111','11111111111.00','11111111111.000000','1111-11-11','0000-00-00','0001-01-01','9999-12-31','MISS','00000','99999999999','999999999999999','99999999999.00','99999999999.000000','-9999.9999','','Not applicable','XXX') THEN 0 ELSE 1 END AS FRMT_0160_rank_insolv | N35: =+"SUM("&K35&") AS `"&K35&"`," -> SUM(FRMT_0160_rank_insolv) AS `FRMT_0160_rank_insolv`,
A36: =CONCATENATE(B36,"_",E36) -> B02.00_Contractual subordination | B36: B02.00 | C36: =CONCATENATE(B36,";c",D36) -> B02.00;c0161 | D36: 0161 | E36: Contractual subordination | F36: =CONCATENATE(G36,": ",H36) -> Numeric: 2 decimals | G36: Numeric | H36: 2 decimals | I36: Input 999999999999999 | K36: =+"FRMT_"&L36 -> FRMT_0161_cntrctl_sbrdntn | L36: =+VLOOKUP(D36,'B02_Mapping fields'!B:C,2,FALSE) -> 0161_cntrctl_sbrdntn | M36: =+",CASE WHEN (CAST(ROUND(`"&L36&"`, 2) AS STRING) = CAST(`"&L36&"` AS STRING) AND CAST(`"&L36&"` AS STRING) NOT IN ('N/A','11111111111','11111111111.00','11111111111.000000','1111-11-11','0000-00-00','0001-01-01','9999-12-31','MISS','00000','99999999999','99999999999.00','99999999999.000000','-9999.9999','','Not applicable','XXX')) OR `"&L36&"`= 999999999999999.00 THEN 0 ELSE 1 END AS "&K36 -> ,CASE WHEN (CAST(ROUND(`0161_cntrctl_sbrdntn`, 2) AS STRING) = CAST(`0161_cntrctl_sbrdntn` AS STRING) AND CAST(`0161_cntrctl_sbrdntn` AS STRING) NOT IN ('N/A','11111111111','11111111111.00','11111111111.000000','1111-11-11','0000-00-00','0001-01-01','9999-12-31','MISS','00000','99999999999','99999999999.00','99999999999.000000','-9999.9999','','Not applicable','XXX')) OR `0161_cntrctl_sbrdntn`= 999999999999999.00 THEN 0 ELSE 1 END AS FRMT_0161_cntrctl_sbrdntn | N36: =+"SUM("&K36&") AS `"&K36&"`," -> SUM(FRMT_0161_cntrctl_sbrdntn) AS `FRMT_0161_cntrctl_sbrdntn`,
A37: =CONCATENATE(B37,"_",E37) -> B02.00_Bail-in cascade | B37: B02.00 | C37: =CONCATENATE(B37,";c",D37) -> B02.00;c0162 | D37: 0162 | E37: Bail-in cascade | F37: =CONCATENATE(G37,": ",H37) -> String: Fixed values | G37: String | H37: Fixed values | K37: =+"FRMT_"&L37 -> FRMT_0162_bail_in_cascade | L37: =+VLOOKUP(D37,'B02_Mapping fields'!B:C,2,FALSE) -> 0162_bail_in_cascade | M37: =+",CASE WHEN `"&L37&"` in ('1','2','3','4','5','6','7','8','9','10','11','12','13','14','14','15','16','17','18','19','20') THEN 0 ELSE 1 END AS "&K37 -> ,CASE WHEN `0162_bail_in_cascade` in ('1','2','3','4','5','6','7','8','9','10','11','12','13','14','14','15','16','17','18','19','20') THEN 0 ELSE 1 END AS FRMT_0162_bail_in_cascade | N37: =+"SUM("&K37&") AS `"&K37&"`," -> SUM(FRMT_0162_bail_in_cascade) AS `FRMT_0162_bail_in_cascade`,
A38: =CONCATENATE(B38,"_",E38) -> B02.00_Date of issuance | B38: B02.00 | C38: =CONCATENATE(B38,";c",D38) -> B02.00;c0170 | D38: 0170 | E38: Date of issuance | F38: =CONCATENATE(G38,": ",H38) -> Date: yyyy-mm-dd | G38: Date | H38: yyyy-mm-dd | K38: =+"FRMT_"&L38 -> FRMT_0170_dt_incptn | L38: =+VLOOKUP(D38,'B02_Mapping fields'!B:C,2,FALSE) -> 0170_dt_incptn | M38: =+",CASE WHEN `"&L38&"` REGEXP '^[0-9]{4}-[0-9]{2}-[0-9]{2}$' and `"&L38&_xlfn._LONGTEXT("` NOT IN ('N/A','11111111111','11111111111.00','11111111111.000000','1111-11-11','0000-00-00','0001-01-01','9999-12-31','MISS','00000','99999999999','999999999999999','99999999999.00','99999999999.000000','-9999.9999','','Not applicable','XXX') THEN 0 ELS","E 1 END AS ")&K38 -> ,CASE WHEN `0170_dt_incptn` REGEXP '^[0-9]{4}-[0-9]{2}-[0-9]{2}$' and `0170_dt_incptn` NOT IN ('N/A','11111111111','11111111111.00','11111111111.000000','1111-11-11','0000-00-00','0001-01-01','9999-12-31','MISS','00000','99999999999','999999999999999','99999999999.00','99999999999.000000','-9999.9999','','Not applicable','XXX') THEN 0 ELSE 1 END AS FRMT_0170_dt_incptn | N38: =+"SUM("&K38&") AS `"&K38&"`," -> SUM(FRMT_0170_dt_incptn) AS `FRMT_0170_dt_incptn`,
A39: =CONCATENATE(B39,"_",E39) -> B02.00_Date of the next interest payment | B39: B02.00 | C39: =CONCATENATE(B39,";c",D39) -> B02.00;c0180 | D39: 0180 | E39: Date of the next interest payment | F39: =CONCATENATE(G39,": ",H39) -> Date: yyyy-mm-dd | G39: Date | H39: yyyy-mm-dd | I39: Input "0001-01-01" | J39: Leave blank | K39: =+"FRMT_"&L39 -> FRMT_0180_dt_nxt_intrst_pymnt | L39: =+VLOOKUP(D39,'B02_Mapping fields'!B:C,2,FALSE) -> 0180_dt_nxt_intrst_pymnt | M39: =+",CASE WHEN (`"&L39&"` REGEXP '^[0-9]{4}-[0-9]{2}-[0-9]{2}$' and `"&L39&"` NOT IN ('N/A','11111111111','11111111111.00','11111111111.000000','1111-11-11','0000-00-00','9999-12-31','MISS','00000','99999999999','999999999999999','99999999999.00','99999999999.000000','-9999.9999','Not applicable','XXX')) OR `"&L39&"` IN ('0001-01-01', ' ') THEN 0 ELSE 1 END AS "&K39 -> ,CASE WHEN (`0180_dt_nxt_intrst_pymnt` REGEXP '^[0-9]{4}-[0-9]{2}-[0-9]{2}$' and `0180_dt_nxt_intrst_pymnt` NOT IN ('N/A','11111111111','11111111111.00','11111111111.000000','1111-11-11','0000-00-00','9999-12-31','MISS','00000','99999999999','999999999999999','99999999999.00','99999999999.000000','-9999.9999','Not applicable','XXX')) OR `0180_dt_nxt_intrst_pymnt` IN ('0001-01-01', ' ') THEN 0 ELSE 1 END AS FRMT_0180_dt_nxt_intrst_pymnt | N39: =+"SUM("&K39&") AS `"&K39&"`," -> SUM(FRMT_0180_dt_nxt_intrst_pymnt) AS `FRMT_0180_dt_nxt_intrst_pymnt`,
A40: =CONCATENATE(B40,"_",E40) -> B02.00_Date of the next (partial) redemption payment | B40: B02.00 | C40: =CONCATENATE(B40,";c",D40) -> B02.00;c0190 | D40: 0190 | E40: Date of the next (partial) redemption payment | F40: =CONCATENATE(G40,": ",H40) -> Date: yyyy-mm-dd | G40: Date | H40: yyyy-mm-dd | I40: Input the final legal maturity of the liability (c0210) | K40: =+"FRMT_"&L40 -> FRMT_0190_dt_nxt_rdmptn_pymnt | L40: =+VLOOKUP(D40,'B02_Mapping fields'!B:C,2,FALSE) -> 0190_dt_nxt_rdmptn_pymnt | M40: =+",CASE WHEN (`"&L40&"` REGEXP '^[0-9]{4}-[0-9]{2}-[0-9]{2}$' AND `"&L40&"` NOT IN ('N/A','11111111111','11111111111.00','11111111111.000000','1111-11-11','0000-00-00','0001-01-01','9999-12-31','MISS','00000','99999999999','999999999999999','99999999999.00','99999999999.000000','-9999.9999','','Not applicable','XXX')) OR `"&L40&"` = `0210_dt_lgl_fnl_mtrty` THEN 0 ELSE 1 END AS "&K40 -> ,CASE WHEN (`0190_dt_nxt_rdmptn_pymnt` REGEXP '^[0-9]{4}-[0-9]{2}-[0-9]{2}$' AND `0190_dt_nxt_rdmptn_pymnt` NOT IN ('N/A','11111111111','11111111111.00','11111111111.000000','1111-11-11','0000-00-00','0001-01-01','9999-12-31','MISS','00000','99999999999','999999999999999','99999999999.00','99999999999.000000','-9999.9999','','Not applicable','XXX')) OR `0190_dt_nxt_rdmptn_pymnt` = `0210_dt_lgl_fnl_mtrty` THEN 0 ELSE 1 END AS FRMT_0190_dt_nxt_rdmptn_pymnt | N40: =+"SUM("&K40&") AS `"&K40&"`," -> SUM(FRMT_0190_dt_nxt_rdmptn_pymnt) AS `FRMT_0190_dt_nxt_rdmptn_pymnt`,
A41: =CONCATENATE(B41,"_",E41) -> B02.00_Earliest redemption date | B41: B02.00 | C41: =CONCATENATE(B41,";c",D41) -> B02.00;c0200 | D41: 0200 | E41: Earliest redemption date | F41: =CONCATENATE(G41,": ",H41) -> Date: yyyy-mm-dd | G41: Date | H41: yyyy-mm-dd | I41: Input "0001-01-01" | K41: =+"FRMT_"&L41 -> FRMT_0200_dt_erlst_rdmptn | L41: =+VLOOKUP(D41,'B02_Mapping fields'!B:C,2,FALSE) -> 0200_dt_erlst_rdmptn | M41: =+",CASE WHEN (`"&L41&"` REGEXP '^[0-9]{4}-[0-9]{2}-[0-9]{2}$' and `"&L41&"` NOT IN ('N/A','11111111111','11111111111.00','11111111111.000000','1111-11-11','0000-00-00','9999-12-31','MISS','00000','99999999999','999999999999999','99999999999.00','99999999999.000000','-9999.9999','Not applicable','XXX')) OR `"&L41&"` IN ('0001-01-01', '') THEN 0 ELSE 1 END AS "&K41 -> ,CASE WHEN (`0200_dt_erlst_rdmptn` REGEXP '^[0-9]{4}-[0-9]{2}-[0-9]{2}$' and `0200_dt_erlst_rdmptn` NOT IN ('N/A','11111111111','11111111111.00','11111111111.000000','1111-11-11','0000-00-00','9999-12-31','MISS','00000','99999999999','999999999999999','99999999999.00','99999999999.000000','-9999.9999','Not applicable','XXX')) OR `0200_dt_erlst_rdmptn` IN ('0001-01-01', '') THEN 0 ELSE 1 END AS FRMT_0200_dt_erlst_rdmptn | N41: =+"SUM("&K41&") AS `"&K41&"`," -> SUM(FRMT_0200_dt_erlst_rdmptn) AS `FRMT_0200_dt_erlst_rdmptn`,
A42: =CONCATENATE(B42,"_",E42) -> B02.00_Legal maturity | B42: B02.00 | C42: =CONCATENATE(B42,";c",D42) -> B02.00;c0210 | D42: 0210 | E42: Legal maturity | F42: =CONCATENATE(G42,": ",H42) -> Date: yyyy-mm-dd | G42: Date | H42: yyyy-mm-dd | I42: Input "0001-01-01" | K42: =+"FRMT_"&L42 -> FRMT_0210_dt_lgl_fnl_mtrty | L42: =+VLOOKUP(D42,'B02_Mapping fields'!B:C,2,FALSE) -> 0210_dt_lgl_fnl_mtrty | M42: =+",CASE WHEN (`"&L42&"` REGEXP '^[0-9]{4}-[0-9]{2}-[0-9]{2}$' and `"&L42&"` NOT IN ('N/A','11111111111','11111111111.00','11111111111.000000','1111-11-11','0000-00-00','9999-12-31','MISS','00000','99999999999','999999999999999','99999999999.00','99999999999.000000','-9999.9999','Not applicable','XXX')) OR `"&L42&"` IN ('0001-01-01', '') THEN 0 ELSE 1 END AS "&K42 -> ,CASE WHEN (`0210_dt_lgl_fnl_mtrty` REGEXP '^[0-9]{4}-[0-9]{2}-[0-9]{2}$' and `0210_dt_lgl_fnl_mtrty` NOT IN ('N/A','11111111111','11111111111.00','11111111111.000000','1111-11-11','0000-00-00','9999-12-31','MISS','00000','99999999999','999999999999999','99999999999.00','99999999999.000000','-9999.9999','Not applicable','XXX')) OR `0210_dt_lgl_fnl_mtrty` IN ('0001-01-01', '') THEN 0 ELSE 1 END AS FRMT_0210_dt_lgl_fnl_mtrty | N42: =+"SUM("&K42&") AS `"&K42&"`," -> SUM(FRMT_0210_dt_lgl_fnl_mtrty) AS `FRMT_0210_dt_lgl_fnl_mtrty`,
A43: =CONCATENATE(B43,"_",E43) -> B02.00_Governing law | B43: B02.00 | C43: =CONCATENATE(B43,";c",D43) -> B02.00;c0220 | D43: 0220 | E43: Governing law | F43: =CONCATENATE(G43,": ",H43) -> String: ISO 3166-1 alpha 2 / ISO 3166-2 | G43: String | H43: ISO 3166-1 alpha 2 / ISO 3166-2 | I43: Input "XX" | K43: =+"FRMT_"&L43 -> FRMT_0220_governing_law | L43: =+VLOOKUP(D43,'B02_Mapping fields'!B:C,2,FALSE) -> 0220_governing_law | M43: =+",CASE WHEN LENGTH(`"&L43&"`) = 2 OR `"&L43&"` = 'XX' THEN 0 ELSE 1 END AS "&K43 -> ,CASE WHEN LENGTH(`0220_governing_law`) = 2 OR `0220_governing_law` = 'XX' THEN 0 ELSE 1 END AS FRMT_0220_governing_law | N43: =+"SUM("&K43&") AS `"&K43&"`," -> SUM(FRMT_0220_governing_law) AS `FRMT_0220_governing_law`,
A44: =CONCATENATE(B44,"_",E44) -> B02.00_Bail-in recognition clause | B44: B02.00 | C44: =CONCATENATE(B44,";c",D44) -> B02.00;c0230 | D44: 0230 | E44: Bail-in recognition clause | F44: =CONCATENATE(G44,": ",H44) -> String: Drop-down | G44: String | H44: Drop-down | I44: Input "Not applicable" | K44: =+"FRMT_"&L44 -> FRMT_0230_bail_in_rcgntn_cls | L44: =+VLOOKUP(D44,'B02_Mapping fields'!B:C,2,FALSE) -> 0230_bail_in_rcgntn_cls | M44: =+",CASE WHEN `"&L44&"` IN ('Yes, supported by Legal Opinion', 'Yes, not supported by Legal Opinion', 'No', 'Not applicable', 'Aggregated', 'Not applicable') THEN 0 ELSE 1 END AS "&K44 -> ,CASE WHEN `0230_bail_in_rcgntn_cls` IN ('Yes, supported by Legal Opinion', 'Yes, not supported by Legal Opinion', 'No', 'Not applicable', 'Aggregated', 'Not applicable') THEN 0 ELSE 1 END AS FRMT_0230_bail_in_rcgntn_cls | N44: =+"SUM("&K44&") AS `"&K44&"`," -> SUM(FRMT_0230_bail_in_rcgntn_cls) AS `FRMT_0230_bail_in_rcgntn_cls`,
A45: =CONCATENATE(B45,"_",E45) -> B02.00_Zero-Coupon | B45: B02.00 | C45: =CONCATENATE(B45,";c",D45) -> B02.00;c0240 | D45: 0240 | E45: Zero-Coupon | F45: =CONCATENATE(G45,": ",H45) -> String: Drop-down | G45: String | H45: Drop-down | K45: =+"FRMT_"&L45 -> FRMT_0240_zero_coupon | L45: =+VLOOKUP(D45,'B02_Mapping fields'!B:C,2,FALSE) -> 0240_zero_coupon | M45: =+",CASE WHEN `"&L45&"` IN ('ZCB issued at discount', 'ZCB not issued at discount', 'No ZCB', 'Aggregated') THEN 0 ELSE 1 END AS "&K45 -> ,CASE WHEN `0240_zero_coupon` IN ('ZCB issued at discount', 'ZCB not issued at discount', 'No ZCB', 'Aggregated') THEN 0 ELSE 1 END AS FRMT_0240_zero_coupon | N45: =+"SUM("&K45&") AS `"&K45&"`," -> SUM(FRMT_0240_zero_coupon) AS `FRMT_0240_zero_coupon`,
A46: =CONCATENATE(B46,"_",E46) -> B02.00_Structured product | B46: B02.00 | C46: =CONCATENATE(B46,";c",D46) -> B02.00;c0250 | D46: 0250 | E46: Structured product | F46: =CONCATENATE(G46,": ",H46) -> String: Drop-down | G46: String | H46: Drop-down | K46: =+"FRMT_"&L46 -> FRMT_0250_strctrd_prdct | L46: =+VLOOKUP(D46,'B02_Mapping fields'!B:C,2,FALSE) -> 0250_strctrd_prdct | M46: =+",CASE WHEN `"&L46&"` IN ('Non-structured/Vanilla', 'Structured', 'Other non-standard terms', 'Only structured coupon', 'Aggregated') THEN 0 ELSE 1 END AS "&K46 -> ,CASE WHEN `0250_strctrd_prdct` IN ('Non-structured/Vanilla', 'Structured', 'Other non-standard terms', 'Only structured coupon', 'Aggregated') THEN 0 ELSE 1 END AS FRMT_0250_strctrd_prdct | N46: =+"SUM("&K46&") AS `"&K46&"`," -> SUM(FRMT_0250_strctrd_prdct) AS `FRMT_0250_strctrd_prdct`,
A47: =CONCATENATE(B47,"_",E47) -> B02.00_Guaranteed minimum repayment amount of the structured product | B47: B02.00 | C47: =CONCATENATE(B47,";c",D47) -> B02.00;c0260 | D47: 0260 | E47: Guaranteed minimum repayment amount of the structured product | F47: =CONCATENATE(G47,": ",H47) -> Numeric: 2 decimals | G47: Numeric | H47: 2 decimals | K47: =+"FRMT_"&L47 -> FRMT_0260_grntd_min_amnt_strctrd_prdct | L47: =+VLOOKUP(D47,'B02_Mapping fields'!B:C,2,FALSE) -> 0260_grntd_min_amnt_strctrd_prdct | M47: =+",CASE WHEN CAST(ROUND(`"&L47&"`, 2) AS STRING) = CAST(`"&L47&"` AS STRING) AND CAST(`"&L47&_xlfn._LONGTEXT("` AS STRING) NOT IN ('N/A','11111111111','11111111111.00','11111111111.000000','1111-11-11','0000-00-00','0001-01-01','9999-12-31','MISS','00000','99999999999','99999999999.00','99999999999.000000','-9999.9999','','Not applicable','XXX') THEN 0 ELSE 1 END"," AS ")&K47 -> ,CASE WHEN CAST(ROUND(`0260_grntd_min_amnt_strctrd_prdct`, 2) AS STRING) = CAST(`0260_grntd_min_amnt_strctrd_prdct` AS STRING) AND CAST(`0260_grntd_min_amnt_strctrd_prdct` AS STRING) NOT IN ('N/A','11111111111','11111111111.00','11111111111.000000','1111-11-11','0000-00-00','0001-01-01','9999-12-31','MISS','00000','99999999999','99999999999.00','99999999999.000000','-9999.9999','','Not applicable','XXX') THEN 0 ELSE 1 END AS FRMT_0260_grntd_min_amnt_strctrd_prdct | N47: =+"SUM("&K47&") AS `"&K47&"`," -> SUM(FRMT_0260_grntd_min_amnt_strctrd_prdct) AS `FRMT_0260_grntd_min_amnt_strctrd_prdct`,
A48: =CONCATENATE(B48,"_",E48) -> B02.00_Fair value of the structured product | B48: B02.00 | C48: =CONCATENATE(B48,";c",D48) -> B02.00;c0270 | D48: 0270 | E48: Fair value of the structured product | F48: =CONCATENATE(G48,": ",H48) -> Numeric: 2 decimals | G48: Numeric | H48: 2 decimals | K48: =+"FRMT_"&L48 -> FRMT_0270_fv_amnt_strctrd_prdct | L48: =+VLOOKUP(D48,'B02_Mapping fields'!B:C,2,FALSE) -> 0270_fv_amnt_strctrd_prdct | M48: =+",CASE WHEN CAST(ROUND(`"&L48&"`, 2) AS STRING) = CAST(`"&L48&"` AS STRING) AND CAST(`"&L48&_xlfn._LONGTEXT("` AS STRING) NOT IN ('N/A','11111111111','11111111111.00','11111111111.000000','1111-11-11','0000-00-00','0001-01-01','9999-12-31','MISS','00000','99999999999','99999999999.00','99999999999.000000','-9999.9999','','Not applicable','XXX') THEN 0 ELSE 1 END"," AS ")&K48 -> ,CASE WHEN CAST(ROUND(`0270_fv_amnt_strctrd_prdct`, 2) AS STRING) = CAST(`0270_fv_amnt_strctrd_prdct` AS STRING) AND CAST(`0270_fv_amnt_strctrd_prdct` AS STRING) NOT IN ('N/A','11111111111','11111111111.00','11111111111.000000','1111-11-11','0000-00-00','0001-01-01','9999-12-31','MISS','00000','99999999999','99999999999.00','99999999999.000000','-9999.9999','','Not applicable','XXX') THEN 0 ELSE 1 END AS FRMT_0270_fv_amnt_strctrd_prdct | N48: =+"SUM("&K48&") AS `"&K48&"`," -> SUM(FRMT_0270_fv_amnt_strctrd_prdct) AS `FRMT_0270_fv_amnt_strctrd_prdct`,
A49: =CONCATENATE(B49,"_",E49) -> B02.00_Not covered and not preferential deposit | B49: B02.00 | C49: =CONCATENATE(B49,";c",D49) -> B02.00;c0280 | D49: 0280 | E49: Not covered and not preferential deposit | F49: =CONCATENATE(G49,": ",H49) -> String: TRUE / FALSE boolean | G49: String | H49: TRUE / FALSE boolean | K49: =+"FRMT_"&L49 -> FRMT_0280_flg_ncnp_dpsts | L49: =+VLOOKUP(D49,'B02_Mapping fields'!B:C,2,FALSE) -> 0280_flg_ncnp_dpsts | M49: =+",CASE WHEN `"&L49&"` IN ('TRUE', 'FALSE') THEN 0 ELSE 1 END AS "&K49 -> ,CASE WHEN `0280_flg_ncnp_dpsts` IN ('TRUE', 'FALSE') THEN 0 ELSE 1 END AS FRMT_0280_flg_ncnp_dpsts | N49: =+"SUM("&K49&") AS `"&K49&"`," -> SUM(FRMT_0280_flg_ncnp_dpsts) AS `FRMT_0280_flg_ncnp_dpsts`,
A50: =CONCATENATE(B50,"_",E50) -> B02.00_Not covered but preferential deposit | B50: B02.00 | C50: =CONCATENATE(B50,";c",D50) -> B02.00;c0290 | D50: 0290 | E50: Not covered but preferential deposit | F50: =CONCATENATE(G50,": ",H50) -> String: TRUE / FALSE boolean | G50: String | H50: TRUE / FALSE boolean | K50: =+"FRMT_"&L50 -> FRMT_0290_flg_ncbp_dpsts | L50: =+VLOOKUP(D50,'B02_Mapping fields'!B:C,2,FALSE) -> 0290_flg_ncbp_dpsts | M50: =+",CASE WHEN `"&L50&"` IN ('TRUE', 'FALSE') THEN 0 ELSE 1 END AS "&K50 -> ,CASE WHEN `0290_flg_ncbp_dpsts` IN ('TRUE', 'FALSE') THEN 0 ELSE 1 END AS FRMT_0290_flg_ncbp_dpsts | N50: =+"SUM("&K50&") AS `"&K50&"`," -> SUM(FRMT_0290_flg_ncbp_dpsts) AS `FRMT_0290_flg_ncbp_dpsts`,
A51: =CONCATENATE(B51,"_",E51) -> B02.00_Covered portion of eligible deposits | B51: B02.00 | C51: =CONCATENATE(B51,";c",D51) -> B02.00;c0300 | D51: 0300 | E51: Covered portion of eligible deposits | F51: =CONCATENATE(G51,": ",H51) -> Numeric: 2 decimals | G51: Numeric | H51: 2 decimals | K51: =+"FRMT_"&L51 -> FRMT_0300_amnt_cvrd_elgbl_dpsts | L51: =+VLOOKUP(D51,'B02_Mapping fields'!B:C,2,FALSE) -> 0300_amnt_cvrd_elgbl_dpsts | M51: =+",CASE WHEN CAST(ROUND(`"&L51&"`, 2) AS STRING) = CAST(`"&L51&"` AS STRING) AND CAST(`"&L51&_xlfn._LONGTEXT("` AS STRING) NOT IN ('N/A','11111111111','11111111111.00','11111111111.000000','1111-11-11','0000-00-00','0001-01-01','9999-12-31','MISS','00000','99999999999','99999999999.00','99999999999.000000','-9999.9999','','Not applicable','XXX') THEN 0 ELSE 1 END"," AS ")&K51 -> ,CASE WHEN CAST(ROUND(`0300_amnt_cvrd_elgbl_dpsts`, 2) AS STRING) = CAST(`0300_amnt_cvrd_elgbl_dpsts` AS STRING) AND CAST(`0300_amnt_cvrd_elgbl_dpsts` AS STRING) NOT IN ('N/A','11111111111','11111111111.00','11111111111.000000','1111-11-11','0000-00-00','0001-01-01','9999-12-31','MISS','00000','99999999999','99999999999.00','99999999999.000000','-9999.9999','','Not applicable','XXX') THEN 0 ELSE 1 END AS FRMT_0300_amnt_cvrd_elgbl_dpsts | N51: =+"SUM("&K51&") AS `"&K51&"`," -> SUM(FRMT_0300_amnt_cvrd_elgbl_dpsts) AS `FRMT_0300_amnt_cvrd_elgbl_dpsts`,
A52: =CONCATENATE(B52,"_",E52) -> B02.00_Secured/Unsecured | B52: B02.00 | C52: =CONCATENATE(B52,";c",D52) -> B02.00;c0310 | D52: 0310 | E52: Secured/Unsecured | F52: =CONCATENATE(G52,": ",H52) -> String: Drop-down | G52: String | H52: Drop-down | K52: =+"FRMT_"&L52 -> FRMT_0310_flg_clltrl_agrmnts | L52: =+VLOOKUP(D52,'B02_Mapping fields'!B:C,2,FALSE) -> 0310_flg_clltrl_agrmnts | M52: =+",CASE WHEN `"&L52&"` IN ('Secured', 'Unsecured') THEN 0 ELSE 1 END AS "&K52 -> ,CASE WHEN `0310_flg_clltrl_agrmnts` IN ('Secured', 'Unsecured') THEN 0 ELSE 1 END AS FRMT_0310_flg_clltrl_agrmnts | N52: =+"SUM("&K52&") AS `"&K52&"`," -> SUM(FRMT_0310_flg_clltrl_agrmnts) AS `FRMT_0310_flg_clltrl_agrmnts`,
A53: =CONCATENATE(B53,"_",E53) -> B02.00_Amount of pledge, lien or collateral based on the current internal valuation | B53: B02.00 | C53: =CONCATENATE(B53,";c",D53) -> B02.00;c0320 | D53: 0320 | E53: Amount of pledge, lien or collateral based on the current internal valuation | F53: =CONCATENATE(G53,": ",H53) -> Numeric: 2 decimals | G53: Numeric | H53: 2 decimals | K53: =+"FRMT_"&L53 -> FRMT_0320_amnt_clltrl | L53: =+VLOOKUP(D53,'B02_Mapping fields'!B:C,2,FALSE) -> 0320_amnt_clltrl | M53: =+",CASE WHEN CAST(ROUND(`"&L53&"`, 2) AS STRING) = CAST(`"&L53&"` AS STRING) AND CAST(`"&L53&_xlfn._LONGTEXT("` AS STRING) NOT IN ('N/A','11111111111','11111111111.00','11111111111.000000','1111-11-11','0000-00-00','0001-01-01','9999-12-31','MISS','00000','99999999999','99999999999.00','99999999999.000000','-9999.9999','','Not applicable','XXX') THEN 0 ELSE 1 END"," AS ")&K53 -> ,CASE WHEN CAST(ROUND(`0320_amnt_clltrl`, 2) AS STRING) = CAST(`0320_amnt_clltrl` AS STRING) AND CAST(`0320_amnt_clltrl` AS STRING) NOT IN ('N/A','11111111111','11111111111.00','11111111111.000000','1111-11-11','0000-00-00','0001-01-01','9999-12-31','MISS','00000','99999999999','99999999999.00','99999999999.000000','-9999.9999','','Not applicable','XXX') THEN 0 ELSE 1 END AS FRMT_0320_amnt_clltrl | N53: =+"SUM("&K53&") AS `"&K53&"`," -> SUM(FRMT_0320_amnt_clltrl) AS `FRMT_0320_amnt_clltrl`,
A54: =CONCATENATE(B54,"_",E54) -> B02.00_Amount of the uncollateralized part | B54: B02.00 | C54: =CONCATENATE(B54,";c",D54) -> B02.00;c0330 | D54: 0330 | E54: Amount of the uncollateralized part | F54: =CONCATENATE(G54,": ",H54) -> Numeric: 2 decimals | G54: Numeric | H54: 2 decimals | J54: Leave blank | K54: =+"FRMT_"&L54 -> FRMT_0330_amnt_unclltrlzd | L54: =+VLOOKUP(D54,'B02_Mapping fields'!B:C,2,FALSE) -> 0330_amnt_unclltrlzd | M54: =+",CASE WHEN (CAST(ROUND(`"&L54&"`, 2) AS STRING) = CAST(`"&L54&"` AS STRING) and cast(`"&L38&_xlfn._LONGTEXT("` as string) NOT IN ('N/A','11111111111','11111111111.00','11111111111.000000','1111-11-11','0000-00-00','0001-01-01','9999-12-31','MISS','00000','99999999999','999999999999999','99999999999.00','99999999999.000000','-9999.9999','Not applicable','XXX')) o","r CAST(`")&L54&"` AS STRING) = '' THEN 0 ELSE 1 END AS "&K54 -> ,CASE WHEN (CAST(ROUND(`0330_amnt_unclltrlzd`, 2) AS STRING) = CAST(`0330_amnt_unclltrlzd` AS STRING) and cast(`0170_dt_incptn` as string) NOT IN ('N/A','11111111111','11111111111.00','11111111111.000000','1111-11-11','0000-00-00','0001-01-01','9999-12-31','MISS','00000','99999999999','999999999999999','99999999999.00','99999999999.000000','-9999.9999','Not applicable','XXX')) or CAST(`0330_amnt_unclltrlzd` AS STRING) = '' THEN 0 ELSE 1 END AS FRMT_0330_amnt_unclltrlzd | N54: =+"SUM("&K54&") AS `"&K54&"`," -> SUM(FRMT_0330_amnt_unclltrlzd) AS `FRMT_0330_amnt_unclltrlzd`,
A55: =CONCATENATE(B55,"_",E55) -> B02.00_Internal identification number of the pledge, lien or collateral/collateral pool | B55: B02.00 | C55: =CONCATENATE(B55,";c",D55) -> B02.00;c0340 | D55: 0340 | E55: Internal identification number of the pledge, lien or collateral/collateral pool | F55: =CONCATENATE(G55,": ",H55) -> String: Free text | G55: String | H55: Free text | K55: =+"FRMT_"&L55 -> FRMT_0340_id_clltrl | L55: =+VLOOKUP(D55,'B02_Mapping fields'!B:C,2,FALSE) -> 0340_id_clltrl | M55: =+",CASE WHEN `"&L55&"` RLIKE '[A-Za-z]' AND `"&L55&_xlfn._LONGTEXT("` NOT IN ('N/A','11111111111','11111111111.00','11111111111.000000','1111-11-11','0000-00-00','0001-01-01','9999-12-31','MISS','00000','99999999999','999999999999999','99999999999.00','99999999999.000000','-9999.9999','','Not applicable','XXX') THEN 0 ELS","E 1 END AS ")&K55 -> ,CASE WHEN `0340_id_clltrl` RLIKE '[A-Za-z]' AND `0340_id_clltrl` NOT IN ('N/A','11111111111','11111111111.00','11111111111.000000','1111-11-11','0000-00-00','0001-01-01','9999-12-31','MISS','00000','99999999999','999999999999999','99999999999.00','99999999999.000000','-9999.9999','','Not applicable','XXX') THEN 0 ELSE 1 END AS FRMT_0340_id_clltrl | N55: =+"SUM("&K55&") AS `"&K55&"`," -> SUM(FRMT_0340_id_clltrl) AS `FRMT_0340_id_clltrl`,
A56: =CONCATENATE(B56,"_",E56) -> B02.00_Type of the collateral | B56: B02.00 | C56: =CONCATENATE(B56,";c",D56) -> B02.00;c0350 | D56: 0350 | E56: Type of the collateral | F56: =CONCATENATE(G56,": ",H56) -> String: Drop-down | G56: String | H56: Drop-down | I56: Input "Not applicable" | J56: Leave blank | K56: =+"FRMT_"&L56 -> FRMT_0350_typ_clltrl | L56: =+VLOOKUP(D56,'B02_Mapping fields'!B:C,2,FALSE) -> 0350_typ_clltrl | M56: =+",CASE WHEN `"&L56&"` IN ('Real estate', 'Ships', 'Aircraft', 'Financial', 'Other', 'Not applicable', '') THEN 0 ELSE 1 END AS "&K56 -> ,CASE WHEN `0350_typ_clltrl` IN ('Real estate', 'Ships', 'Aircraft', 'Financial', 'Other', 'Not applicable', '') THEN 0 ELSE 1 END AS FRMT_0350_typ_clltrl | N56: =+"SUM("&K56&") AS `"&K56&"`," -> SUM(FRMT_0350_typ_clltrl) AS `FRMT_0350_typ_clltrl`,
A57: =CONCATENATE(B57,"_",E57) -> B02.00_Type of the collateral (if other) | B57: B02.00 | C57: =CONCATENATE(B57,";c",D57) -> B02.00;c0351 | D57: 0351 | E57: Type of the collateral (if other) | F57: =CONCATENATE(G57,": ",H57) -> String: Free text | G57: String | H57: Free text | K57: =+"FRMT_"&L57 -> FRMT_0351_typ_clltrl_othr | L57: =+VLOOKUP(D57,'B02_Mapping fields'!B:C,2,FALSE) -> 0351_typ_clltrl_othr | M57: =+",CASE WHEN `"&L57&"` RLIKE '[A-Za-z]' AND `"&L57&_xlfn._LONGTEXT("` NOT IN ('N/A','11111111111','11111111111.00','11111111111.000000','1111-11-11','0000-00-00','0001-01-01','9999-12-31','MISS','00000','99999999999','999999999999999','99999999999.00','99999999999.000000','-9999.9999','','Not applicable','XXX') THEN 0 ELS","E 1 END AS ")&K57 -> ,CASE WHEN `0351_typ_clltrl_othr` RLIKE '[A-Za-z]' AND `0351_typ_clltrl_othr` NOT IN ('N/A','11111111111','11111111111.00','11111111111.000000','1111-11-11','0000-00-00','0001-01-01','9999-12-31','MISS','00000','99999999999','999999999999999','99999999999.00','99999999999.000000','-9999.9999','','Not applicable','XXX') THEN 0 ELSE 1 END AS FRMT_0351_typ_clltrl_othr | N57: =+"SUM("&K57&") AS `"&K57&"`," -> SUM(FRMT_0351_typ_clltrl_othr) AS `FRMT_0351_typ_clltrl_othr`,
A58: =CONCATENATE(B58,"_",E58) -> B02.00_Trading method | B58: B02.00 | C58: =CONCATENATE(B58,";c",D58) -> B02.00;c0360 | D58: 0360 | E58: Trading method | F58: =CONCATENATE(G58,": ",H58) -> String: Drop-down | G58: String | H58: Drop-down | K58: =+"FRMT_"&L58 -> FRMT_0360_trdng_mthd | L58: =+VLOOKUP(D58,'B02_Mapping fields'!B:C,2,FALSE) -> 0360_trdng_mthd | M58: =+",CASE WHEN `"&L58&"` IN ('Nominal', 'Unit', 'Not applicable') THEN 0 ELSE 1 END AS "&K58 -> ,CASE WHEN `0360_trdng_mthd` IN ('Nominal', 'Unit', 'Not applicable') THEN 0 ELSE 1 END AS FRMT_0360_trdng_mthd | N58: =+"SUM("&K58&") AS `"&K58&"`," -> SUM(FRMT_0360_trdng_mthd) AS `FRMT_0360_trdng_mthd`,
A59: =CONCATENATE(B59,"_",E59) -> B02.00_Denomination / Nominal value per security in EUR | B59: B02.00 | C59: =CONCATENATE(B59,";c",D59) -> B02.00;c0370 | D59: 0370 | E59: Denomination / Nominal value per security in EUR | F59: =CONCATENATE(G59,": ",H59) -> Numeric: 2 decimals | G59: Numeric | H59: 2 decimals | K59: =+"FRMT_"&L59 -> FRMT_0370_amnt_scrty_eur | L59: =+VLOOKUP(D59,'B02_Mapping fields'!B:C,2,FALSE) -> 0370_amnt_scrty_eur | M59: =+",CASE WHEN CAST(ROUND(`"&L59&"`, 2) AS STRING) = CAST(`"&L59&"` AS STRING) AND CAST(`"&L59&_xlfn._LONGTEXT("` AS STRING) NOT IN ('N/A','11111111111','11111111111.00','11111111111.000000','1111-11-11','0000-00-00','0001-01-01','9999-12-31','MISS','00000','99999999999','99999999999.00','99999999999.000000','-9999.9999','','Not applicable','XXX') THEN 0 ELSE 1 END"," AS ")&K59 -> ,CASE WHEN CAST(ROUND(`0370_amnt_scrty_eur`, 2) AS STRING) = CAST(`0370_amnt_scrty_eur` AS STRING) AND CAST(`0370_amnt_scrty_eur` AS STRING) NOT IN ('N/A','11111111111','11111111111.00','11111111111.000000','1111-11-11','0000-00-00','0001-01-01','9999-12-31','MISS','00000','99999999999','99999999999.00','99999999999.000000','-9999.9999','','Not applicable','XXX') THEN 0 ELSE 1 END AS FRMT_0370_amnt_scrty_eur | N59: =+"SUM("&K59&") AS `"&K59&"`," -> SUM(FRMT_0370_amnt_scrty_eur) AS `FRMT_0370_amnt_scrty_eur`,
A60: =CONCATENATE(B60,"_",E60) -> B02.00_Denomination / Nominal value per security in original currency | B60: B02.00 | C60: =CONCATENATE(B60,";c",D60) -> B02.00;c0380 | D60: 0380 | E60: Denomination / Nominal value per security in original currency | F60: =CONCATENATE(G60,": ",H60) -> Numeric: 2 decimals | G60: Numeric | H60: 2 decimals | K60: =+"FRMT_"&L60 -> FRMT_0380_amnt_scrty_fx | L60: =+VLOOKUP(D60,'B02_Mapping fields'!B:C,2,FALSE) -> 0380_amnt_scrty_fx | M60: =+",CASE WHEN CAST(ROUND(`"&L60&"`, 2) AS STRING) = CAST(`"&L60&"` AS STRING) AND CAST(`"&L60&_xlfn._LONGTEXT("` AS STRING) NOT IN ('N/A','11111111111','11111111111.00','11111111111.000000','1111-11-11','0000-00-00','0001-01-01','9999-12-31','MISS','00000','99999999999','99999999999.00','99999999999.000000','-9999.9999','','Not applicable','XXX') THEN 0 ELSE 1 END"," AS ")&K60 -> ,CASE WHEN CAST(ROUND(`0380_amnt_scrty_fx`, 2) AS STRING) = CAST(`0380_amnt_scrty_fx` AS STRING) AND CAST(`0380_amnt_scrty_fx` AS STRING) NOT IN ('N/A','11111111111','11111111111.00','11111111111.000000','1111-11-11','0000-00-00','0001-01-01','9999-12-31','MISS','00000','99999999999','99999999999.00','99999999999.000000','-9999.9999','','Not applicable','XXX') THEN 0 ELSE 1 END AS FRMT_0380_amnt_scrty_fx | N60: =+"SUM("&K60&") AS `"&K60&"`," -> SUM(FRMT_0380_amnt_scrty_fx) AS `FRMT_0380_amnt_scrty_fx`,
A61: =CONCATENATE(B61,"_",E61) -> B02.00_Number of securities outstanding not held by the reporting entity | B61: B02.00 | C61: =CONCATENATE(B61,";c",D61) -> B02.00;c0390 | D61: 0390 | E61: Number of securities outstanding not held by the reporting entity | F61: =CONCATENATE(G61,": ",H61) -> Numeric: Integer | G61: Numeric | H61: Integer | K61: =+"FRMT_"&L61 -> FRMT_0390_nmbr_scrts_not_rprtng_entty | L61: =+VLOOKUP(D61,'B02_Mapping fields'!B:C,2,FALSE) -> 0390_nmbr_scrts_not_rprtng_entty | M61: =+",CASE WHEN CAST(`"&L61&"` AS STRING) RLIKE '^[0-9]+$' AND CAST(`"&L61&_xlfn._LONGTEXT("` AS STRING) NOT IN ('N/A','11111111111','11111111111.00','11111111111.000000','1111-11-11','0000-00-00','0001-01-01','9999-12-31','MISS','00000','99999999999','999999999999999','99999999999.00','99999999999.000000','-9999.9999','','Not applicable','XXX')"," THEN 0 ELSE 1 END AS ")&K61 -> ,CASE WHEN CAST(`0390_nmbr_scrts_not_rprtng_entty` AS STRING) RLIKE '^[0-9]+$' AND CAST(`0390_nmbr_scrts_not_rprtng_entty` AS STRING) NOT IN ('N/A','11111111111','11111111111.00','11111111111.000000','1111-11-11','0000-00-00','0001-01-01','9999-12-31','MISS','00000','99999999999','999999999999999','99999999999.00','99999999999.000000','-9999.9999','','Not applicable','XXX') THEN 0 ELSE 1 END AS FRMT_0390_nmbr_scrts_not_rprtng_entty | N61: =+"SUM("&K61&") AS `"&K61&"`," -> SUM(FRMT_0390_nmbr_scrts_not_rprtng_entty) AS `FRMT_0390_nmbr_scrts_not_rprtng_entty`,
A62: =CONCATENATE(B62,"_",E62) -> B02.00_Number of securities outstanding held by the reporting entity | B62: B02.00 | C62: =CONCATENATE(B62,";c",D62) -> B02.00;c0391 | D62: 0391 | E62: Number of securities outstanding held by the reporting entity | F62: =CONCATENATE(G62,": ",H62) -> Numeric: Integer | G62: Numeric | H62: Integer | K62: =+"FRMT_"&L62 -> FRMT_0391_nmbr_scrts_rprtng_entty | L62: =+VLOOKUP(D62,'B02_Mapping fields'!B:C,2,FALSE) -> 0391_nmbr_scrts_rprtng_entty | M62: =+",CASE WHEN CAST(`"&L62&"` AS STRING) RLIKE '^[0-9]+$' AND CAST(`"&L62&_xlfn._LONGTEXT("` AS STRING) NOT IN ('N/A','11111111111','11111111111.00','11111111111.000000','1111-11-11','0000-00-00','0001-01-01','9999-12-31','MISS','00000','99999999999','999999999999999','99999999999.00','99999999999.000000','-9999.9999','','Not applicable','XXX')"," THEN 0 ELSE 1 END AS ")&K62 -> ,CASE WHEN CAST(`0391_nmbr_scrts_rprtng_entty` AS STRING) RLIKE '^[0-9]+$' AND CAST(`0391_nmbr_scrts_rprtng_entty` AS STRING) NOT IN ('N/A','11111111111','11111111111.00','11111111111.000000','1111-11-11','0000-00-00','0001-01-01','9999-12-31','MISS','00000','99999999999','999999999999999','99999999999.00','99999999999.000000','-9999.9999','','Not applicable','XXX') THEN 0 ELSE 1 END AS FRMT_0391_nmbr_scrts_rprtng_entty | N62: =+"SUM("&K62&") AS `"&K62&"`," -> SUM(FRMT_0391_nmbr_scrts_rprtng_entty) AS `FRMT_0391_nmbr_scrts_rprtng_entty`,
A63: =CONCATENATE(B63,"_",E63) -> B02.00_Accrued interest per security | B63: B02.00 | C63: =CONCATENATE(B63,";c",D63) -> B02.00;c0400 | D63: 0400 | E63: Accrued interest per security | F63: =CONCATENATE(G63,": ",H63) -> Numeric: 4 decimals | G63: Numeric | H63: 4 decimals | K63: =+"FRMT_"&L63 -> FRMT_0400_accrd_intrst_scrty | L63: =+VLOOKUP(D63,'B02_Mapping fields'!B:C,2,FALSE) -> 0400_accrd_intrst_scrty | M63: =+",CASE WHEN CAST(ROUND(`"&L63&"`, 4) AS STRING) = CAST(`"&L63&"` AS STRING) and cast(`"&L63&_xlfn._LONGTEXT("` as string) NOT IN ('N/A','11111111111','11111111111.00','11111111111.000000','1111-11-11','0000-00-00','0001-01-01','9999-12-31','MISS','00000','99999999999','999999999999999','99999999999.00','99999999999.000000','-9999.9999','','Not applicable','XXX')"," THEN 0 ELSE 1 END AS ")&K63 -> ,CASE WHEN CAST(ROUND(`0400_accrd_intrst_scrty`, 4) AS STRING) = CAST(`0400_accrd_intrst_scrty` AS STRING) and cast(`0400_accrd_intrst_scrty` as string) NOT IN ('N/A','11111111111','11111111111.00','11111111111.000000','1111-11-11','0000-00-00','0001-01-01','9999-12-31','MISS','00000','99999999999','999999999999999','99999999999.00','99999999999.000000','-9999.9999','','Not applicable','XXX') THEN 0 ELSE 1 END AS FRMT_0400_accrd_intrst_scrty | N63: =+"SUM("&K63&") AS `"&K63&"`," -> SUM(FRMT_0400_accrd_intrst_scrty) AS `FRMT_0400_accrd_intrst_scrty`,
A64: =CONCATENATE(B64,"_",E64) -> B02.00_Fees and charges per security | B64: B02.00 | C64: =CONCATENATE(B64,";c",D64) -> B02.00;c0410 | D64: 0410 | E64: Fees and charges per security | F64: =CONCATENATE(G64,": ",H64) -> Numeric: 4 decimals | G64: Numeric | H64: 4 decimals | K64: =+"FRMT_"&L64 -> FRMT_0410_fees_charges_scrty | L64: =+VLOOKUP(D64,'B02_Mapping fields'!B:C,2,FALSE) -> 0410_fees_charges_scrty | M64: =+",CASE WHEN CAST(ROUND(`"&L64&"`, 4) AS STRING) = CAST(`"&L64&"` AS STRING) and cast(`"&L64&_xlfn._LONGTEXT("` as string) NOT IN ('N/A','11111111111','11111111111.00','11111111111.000000','1111-11-11','0000-00-00','0001-01-01','9999-12-31','MISS','00000','99999999999','999999999999999','99999999999.00','99999999999.000000','-9999.9999','','Not applicable','XXX')"," THEN 0 ELSE 1 END AS ")&K64 -> ,CASE WHEN CAST(ROUND(`0410_fees_charges_scrty`, 4) AS STRING) = CAST(`0410_fees_charges_scrty` AS STRING) and cast(`0410_fees_charges_scrty` as string) NOT IN ('N/A','11111111111','11111111111.00','11111111111.000000','1111-11-11','0000-00-00','0001-01-01','9999-12-31','MISS','00000','99999999999','999999999999999','99999999999.00','99999999999.000000','-9999.9999','','Not applicable','XXX') THEN 0 ELSE 1 END AS FRMT_0410_fees_charges_scrty | N64: =+"SUM("&K64&") AS `"&K64&"`," -> SUM(FRMT_0410_fees_charges_scrty) AS `FRMT_0410_fees_charges_scrty`,
A65: =CONCATENATE(B65,"_",E65) -> B02.00_Fair value per security | B65: B02.00 | C65: =CONCATENATE(B65,";c",D65) -> B02.00;c0420 | D65: 0420 | E65: Fair value per security | F65: =CONCATENATE(G65,": ",H65) -> Numeric: 4 decimals | G65: Numeric | H65: 4 decimals | K65: =+"FRMT_"&L65 -> FRMT_0420_fv_amnt_scrty | L65: =+VLOOKUP(D65,'B02_Mapping fields'!B:C,2,FALSE) -> 0420_fv_amnt_scrty | M65: =+",CASE WHEN CAST(ROUND(`"&L65&"`, 4) AS STRING) = CAST(`"&L65&"` AS STRING) and cast(`"&L65&_xlfn._LONGTEXT("` as string) NOT IN ('N/A','11111111111','11111111111.00','11111111111.000000','1111-11-11','0000-00-00','0001-01-01','9999-12-31','MISS','00000','99999999999','999999999999999','99999999999.00','99999999999.000000','-9999.9999','','Not applicable','XXX')"," THEN 0 ELSE 1 END AS ")&K65 -> ,CASE WHEN CAST(ROUND(`0420_fv_amnt_scrty`, 4) AS STRING) = CAST(`0420_fv_amnt_scrty` AS STRING) and cast(`0420_fv_amnt_scrty` as string) NOT IN ('N/A','11111111111','11111111111.00','11111111111.000000','1111-11-11','0000-00-00','0001-01-01','9999-12-31','MISS','00000','99999999999','999999999999999','99999999999.00','99999999999.000000','-9999.9999','','Not applicable','XXX') THEN 0 ELSE 1 END AS FRMT_0420_fv_amnt_scrty | N65: =+"SUM("&K65&") AS `"&K65&"`," -> SUM(FRMT_0420_fv_amnt_scrty) AS `FRMT_0420_fv_amnt_scrty`,
A66: =CONCATENATE(B66,"_",E66) -> B02.00_Principal amount of the global note in EUR | B66: B02.00 | C66: =CONCATENATE(B66,";c",D66) -> B02.00;c0430 | D66: 0430 | E66: Principal amount of the global note in EUR | F66: =CONCATENATE(G66,": ",H66) -> Numeric: 2 decimals | G66: Numeric | H66: 2 decimals | I66: Input 999999999999999 | K66: =+"FRMT_"&L66 -> FRMT_0430_prncpl_amnt_glbl_nt_eur | L66: =+VLOOKUP(D66,'B02_Mapping fields'!B:C,2,FALSE) -> 0430_prncpl_amnt_glbl_nt_eur | M66: =+",CASE WHEN (CAST(ROUND(`"&L66&"`, 2) AS STRING) = CAST(`"&L66&"` AS STRING) AND CAST(`"&L66&"` AS STRING) NOT IN ('N/A','11111111111','11111111111.00','11111111111.000000','1111-11-11','0000-00-00','0001-01-01','9999-12-31','MISS','00000','99999999999','99999999999.00','99999999999.000000','-9999.9999','','Not applicable','XXX')) OR `"&L66&"`= 999999999999999.00 THEN 0 ELSE 1 END AS "&K66 -> ,CASE WHEN (CAST(ROUND(`0430_prncpl_amnt_glbl_nt_eur`, 2) AS STRING) = CAST(`0430_prncpl_amnt_glbl_nt_eur` AS STRING) AND CAST(`0430_prncpl_amnt_glbl_nt_eur` AS STRING) NOT IN ('N/A','11111111111','11111111111.00','11111111111.000000','1111-11-11','0000-00-00','0001-01-01','9999-12-31','MISS','00000','99999999999','99999999999.00','99999999999.000000','-9999.9999','','Not applicable','XXX')) OR `0430_prncpl_amnt_glbl_nt_eur`= 999999999999999.00 THEN 0 ELSE 1 END AS FRMT_0430_prncpl_amnt_glbl_nt_eur | N66: =+"SUM("&K66&") AS `"&K66&"`," -> SUM(FRMT_0430_prncpl_amnt_glbl_nt_eur) AS `FRMT_0430_prncpl_amnt_glbl_nt_eur`,
A67: =CONCATENATE(B67,"_",E67) -> B02.00_Principal amount of the global note in original currency | B67: B02.00 | C67: =CONCATENATE(B67,";c",D67) -> B02.00;c0431 | D67: 0431 | E67: Principal amount of the global note in original currency | F67: =CONCATENATE(G67,": ",H67) -> Numeric: 2 decimals | G67: Numeric | H67: 2 decimals | I67: Input 999999999999999 | K67: =+"FRMT_"&L67 -> FRMT_0431_prncpl_amnt_glbl_nt_fx | L67: =+VLOOKUP(D67,'B02_Mapping fields'!B:C,2,FALSE) -> 0431_prncpl_amnt_glbl_nt_fx | M67: =+",CASE WHEN (CAST(ROUND(`"&L67&"`, 2) AS STRING) = CAST(`"&L67&"` AS STRING) AND CAST(`"&L67&"` AS STRING) NOT IN ('N/A','11111111111','11111111111.00','11111111111.000000','1111-11-11','0000-00-00','0001-01-01','9999-12-31','MISS','00000','99999999999','99999999999.00','99999999999.000000','-9999.9999','','Not applicable','XXX')) OR `"&L67&"`= 999999999999999.00 THEN 0 ELSE 1 END AS "&K67 -> ,CASE WHEN (CAST(ROUND(`0431_prncpl_amnt_glbl_nt_fx`, 2) AS STRING) = CAST(`0431_prncpl_amnt_glbl_nt_fx` AS STRING) AND CAST(`0431_prncpl_amnt_glbl_nt_fx` AS STRING) NOT IN ('N/A','11111111111','11111111111.00','11111111111.000000','1111-11-11','0000-00-00','0001-01-01','9999-12-31','MISS','00000','99999999999','99999999999.00','99999999999.000000','-9999.9999','','Not applicable','XXX')) OR `0431_prncpl_amnt_glbl_nt_fx`= 999999999999999.00 THEN 0 ELSE 1 END AS FRMT_0431_prncpl_amnt_glbl_nt_fx | N67: =+"SUM("&K67&") AS `"&K67&"`," -> SUM(FRMT_0431_prncpl_amnt_glbl_nt_fx) AS `FRMT_0431_prncpl_amnt_glbl_nt_fx`,
A68: =CONCATENATE(B68,"_",E68) -> B02.00_Nature of the global note | B68: B02.00 | C68: =CONCATENATE(B68,";c",D68) -> B02.00;c0440 | D68: 0440 | E68: Nature of the global note | F68: =CONCATENATE(G68,": ",H68) -> String: Drop-down | G68: String | H68: Drop-down | I68: Input "Not applicable" | K68: =+"FRMT_"&L68 -> FRMT_0440_ntr_glbl_nt | L68: =+VLOOKUP(D68,'B02_Mapping fields'!B:C,2,FALSE) -> 0440_ntr_glbl_nt | M68: =+",CASE WHEN `"&L68&"` IN ('NGN', 'CGN', 'Not applicable') THEN 0 ELSE 1 END AS "&K68 -> ,CASE WHEN `0440_ntr_glbl_nt` IN ('NGN', 'CGN', 'Not applicable') THEN 0 ELSE 1 END AS FRMT_0440_ntr_glbl_nt | N68: =+"SUM("&K68&") AS `"&K68&"`," -> SUM(FRMT_0440_ntr_glbl_nt) AS `FRMT_0440_ntr_glbl_nt`,
A69: =CONCATENATE(B69,"_",E69) -> B02.00_Current pool factor | B69: B02.00 | C69: =CONCATENATE(B69,";c",D69) -> B02.00;c0450 | D69: 0450 | E69: Current pool factor | F69: =CONCATENATE(G69,": ",H69) -> Numeric: Values between 0 and 1, with 9 decimals | G69: Numeric | H69: Values between 0 and 1, with 9 decimals | I69: Input -9999.999999999 | K69: =+"FRMT_"&L69 -> FRMT_0450_crrnt_pool_fctr | L69: =+VLOOKUP(D69,'B02_Mapping fields'!B:C,2,FALSE) -> 0450_crrnt_pool_fctr | M69: =+",CASE WHEN (CAST(`"&L69&"` AS STRING) RLIKE '^0\\.[0-9]{1,9}$' AND (`"&L69&"` >=0 AND `"&L69&"`<=1) and cast(`"&L69&_xlfn._LONGTEXT("` as string) NOT IN ('N/A','11111111111','11111111111.00','11111111111.000000','1111-11-11','0000-00-00','0001-01-01','9999-12-31','MISS','00000','99999999999','999999999999999','99999999999.00','99999999999.000000','-9999.9999','','Not applicable','XXX')",") OR `")&L69&"`=-9999.999999999 THEN 0 ELSE 1 END AS "&K69 -> ,CASE WHEN (CAST(`0450_crrnt_pool_fctr` AS STRING) RLIKE '^0\\.[0-9]{1,9}$' AND (`0450_crrnt_pool_fctr` >=0 AND `0450_crrnt_pool_fctr`<=1) and cast(`0450_crrnt_pool_fctr` as string) NOT IN ('N/A','11111111111','11111111111.00','11111111111.000000','1111-11-11','0000-00-00','0001-01-01','9999-12-31','MISS','00000','99999999999','999999999999999','99999999999.00','99999999999.000000','-9999.9999','','Not applicable','XXX')) OR `0450_crrnt_pool_fctr`=-9999.999999999 THEN 0 ELSE 1 END AS FRMT_0450_crrnt_pool_fctr | N69: =+"SUM("&K69&") AS `"&K69&"`," -> SUM(FRMT_0450_crrnt_pool_fctr) AS `FRMT_0450_crrnt_pool_fctr`,
A70: =CONCATENATE(B70,"_",E70) -> B02.00_Central securities depository | B70: B02.00 | C70: =CONCATENATE(B70,";c",D70) -> B02.00;c0460 | D70: 0460 | E70: Central securities depository | F70: =CONCATENATE(G70,": ",H70) -> String: Fixed values | G70: String | H70: Fixed values | K70: =+"FRMT_"&L70 -> FRMT_0460_csd | L70: =+VLOOKUP(D70,'B02_Mapping fields'!B:C,2,FALSE) -> 0460_csd | M70: =+",CASE WHEN `"&L70&"` = 'INTERBOLSA_PT' THEN 0 ELSE 1 END AS "&K70 -> ,CASE WHEN `0460_csd` = 'INTERBOLSA_PT' THEN 0 ELSE 1 END AS FRMT_0460_csd | N70: =+"SUM("&K70&") AS `"&K70&"`," -> SUM(FRMT_0460_csd) AS `FRMT_0460_csd`,
A71: =CONCATENATE(B71,"_",E71) -> B02.00_Central securities depository (LEI) | B71: B02.00 | C71: =CONCATENATE(B71,";c",D71) -> B02.00;c0461 | D71: 0461 | E71: Central securities depository (LEI) | F71: =CONCATENATE(G71,": ",H71) -> String: Free text | G71: String | H71: Free text | K71: =+"FRMT_"&L71 -> FRMT_0461_csd_lei | L71: =+VLOOKUP(D71,'B02_Mapping fields'!B:C,2,FALSE) -> 0461_csd_lei | M71: =+",CASE WHEN `"&L71&"` RLIKE '[A-Za-z]' and `"&L71&_xlfn._LONGTEXT("` NOT IN ('N/A','11111111111','11111111111.00','11111111111.000000','1111-11-11','0000-00-00','0001-01-01','9999-12-31','MISS','00000','99999999999','999999999999999','99999999999.00','99999999999.000000','-9999.9999','','Not applicable','XXX') THEN 0 ELS","E 1 END AS ")&K71 -> ,CASE WHEN `0461_csd_lei` RLIKE '[A-Za-z]' and `0461_csd_lei` NOT IN ('N/A','11111111111','11111111111.00','11111111111.000000','1111-11-11','0000-00-00','0001-01-01','9999-12-31','MISS','00000','99999999999','999999999999999','99999999999.00','99999999999.000000','-9999.9999','','Not applicable','XXX') THEN 0 ELSE 1 END AS FRMT_0461_csd_lei | N71: =+"SUM("&K71&") AS `"&K71&"`," -> SUM(FRMT_0461_csd_lei) AS `FRMT_0461_csd_lei`,
A72: =CONCATENATE(B72,"_",E72) -> B02.00_Central securities depository name (if other) | B72: B02.00 | C72: =CONCATENATE(B72,";c",D72) -> B02.00;c0462 | D72: 0462 | E72: Central securities depository name (if other) | F72: =CONCATENATE(G72,": ",H72) -> String: Free text | G72: String | H72: Free text | K72: =+"FRMT_"&L72 -> FRMT_0462_csd_othr | L72: =+VLOOKUP(D72,'B02_Mapping fields'!B:C,2,FALSE) -> 0462_csd_othr | M72: =+",CASE WHEN `"&L72&"` RLIKE '[A-Za-z]' and `"&L72&_xlfn._LONGTEXT("` NOT IN ('N/A','11111111111','11111111111.00','11111111111.000000','1111-11-11','0000-00-00','0001-01-01','9999-12-31','MISS','00000','99999999999','999999999999999','99999999999.00','99999999999.000000','-9999.9999','','Not applicable','XXX') THEN 0 ELS","E 1 END AS ")&K72 -> ,CASE WHEN `0462_csd_othr` RLIKE '[A-Za-z]' and `0462_csd_othr` NOT IN ('N/A','11111111111','11111111111.00','11111111111.000000','1111-11-11','0000-00-00','0001-01-01','9999-12-31','MISS','00000','99999999999','999999999999999','99999999999.00','99999999999.000000','-9999.9999','','Not applicable','XXX') THEN 0 ELSE 1 END AS FRMT_0462_csd_othr | N72: =+"SUM("&K72&") AS `"&K72&"`," -> SUM(FRMT_0462_csd_othr) AS `FRMT_0462_csd_othr`,
A73: =CONCATENATE(B73,"_",E73) -> B02.00_(Mandated) paying agent | B73: B02.00 | C73: =CONCATENATE(B73,";c",D73) -> B02.00;c0470 | D73: 0470 | E73: (Mandated) paying agent | F73: =CONCATENATE(G73,": ",H73) -> String: Free text | G73: String | H73: Free text | I73: Input "Not applicable" | K73: =+"FRMT_"&L73 -> FRMT_0470_pyng_agnt | L73: =+VLOOKUP(D73,'B02_Mapping fields'!B:C,2,FALSE) -> 0470_pyng_agnt | M73: =+",CASE WHEN (`"&L73&"` RLIKE '[A-Za-z]' and `"&L73&"` NOT IN ('N/A','11111111111','11111111111.00','11111111111.000000','1111-11-11','0000-00-00','0001-01-01','9999-12-31','MISS','00000','99999999999','999999999999999','99999999999.00','99999999999.000000','-9999.9999','','XXX')) OR `"&L73&"` = 'Not applicable' THEN 0 ELSE 1 END AS "&K73 -> ,CASE WHEN (`0470_pyng_agnt` RLIKE '[A-Za-z]' and `0470_pyng_agnt` NOT IN ('N/A','11111111111','11111111111.00','11111111111.000000','1111-11-11','0000-00-00','0001-01-01','9999-12-31','MISS','00000','99999999999','999999999999999','99999999999.00','99999999999.000000','-9999.9999','','XXX')) OR `0470_pyng_agnt` = 'Not applicable' THEN 0 ELSE 1 END AS FRMT_0470_pyng_agnt | N73: =+"SUM("&K73&") AS `"&K73&"`," -> SUM(FRMT_0470_pyng_agnt) AS `FRMT_0470_pyng_agnt`,
A74: =CONCATENATE(B74,"_",E74) -> B02.00_(Mandated) paying agent (LEI) | B74: B02.00 | C74: =CONCATENATE(B74,";c",D74) -> B02.00;c0471 | D74: 0471 | E74: (Mandated) paying agent (LEI) | F74: =CONCATENATE(G74,": ",H74) -> String: Free text | G74: String | H74: Free text | I74: Input "Not applicable" | K74: =+"FRMT_"&L74 -> FRMT_0471_pyng_agnt_lei | L74: =+VLOOKUP(D74,'B02_Mapping fields'!B:C,2,FALSE) -> 0471_pyng_agnt_lei | M74: =+",CASE WHEN (`"&L74&"` RLIKE '[A-Za-z]' and `"&L74&"` NOT IN ('N/A','11111111111','11111111111.00','11111111111.000000','1111-11-11','0000-00-00','0001-01-01','9999-12-31','MISS','00000','99999999999','999999999999999','99999999999.00','99999999999.000000','-9999.9999','','XXX')) OR `"&L74&"` = 'Not applicable' THEN 0 ELSE 1 END AS "&K74 -> ,CASE WHEN (`0471_pyng_agnt_lei` RLIKE '[A-Za-z]' and `0471_pyng_agnt_lei` NOT IN ('N/A','11111111111','11111111111.00','11111111111.000000','1111-11-11','0000-00-00','0001-01-01','9999-12-31','MISS','00000','99999999999','999999999999999','99999999999.00','99999999999.000000','-9999.9999','','XXX')) OR `0471_pyng_agnt_lei` = 'Not applicable' THEN 0 ELSE 1 END AS FRMT_0471_pyng_agnt_lei | N74: =+"SUM("&K74&") AS `"&K74&"`," -> SUM(FRMT_0471_pyng_agnt_lei) AS `FRMT_0471_pyng_agnt_lei`,
A75: =CONCATENATE(B75,"_",E75) -> B02.00_Trading venue | B75: B02.00 | C75: =CONCATENATE(B75,";c",D75) -> B02.00;c0480 | D75: 0480 | E75: Trading venue | F75: =CONCATENATE(G75,": ",H75) -> String: Free text | G75: String | H75: Free text | I75: Input "Not applicable" | K75: =+"FRMT_"&L75 -> FRMT_0480_trdng_vn | L75: =+VLOOKUP(D75,'B02_Mapping fields'!B:C,2,FALSE) -> 0480_trdng_vn | M75: =+",CASE WHEN (`"&L75&"` RLIKE '[A-Za-z]' and `"&L75&"` NOT IN ('N/A','11111111111','11111111111.00','11111111111.000000','1111-11-11','0000-00-00','0001-01-01','9999-12-31','MISS','00000','99999999999','999999999999999','99999999999.00','99999999999.000000','-9999.9999','','XXX')) OR `"&L75&"` = 'Not applicable' THEN 0 ELSE 1 END AS "&K75 -> ,CASE WHEN (`0480_trdng_vn` RLIKE '[A-Za-z]' and `0480_trdng_vn` NOT IN ('N/A','11111111111','11111111111.00','11111111111.000000','1111-11-11','0000-00-00','0001-01-01','9999-12-31','MISS','00000','99999999999','999999999999999','99999999999.00','99999999999.000000','-9999.9999','','XXX')) OR `0480_trdng_vn` = 'Not applicable' THEN 0 ELSE 1 END AS FRMT_0480_trdng_vn | N75: =+"SUM("&K75&") AS `"&K75&"`," -> SUM(FRMT_0480_trdng_vn) AS `FRMT_0480_trdng_vn`,
A76: =CONCATENATE(B76,"_",E76) -> B02.00_Trading venue (LEI) | B76: B02.00 | C76: =CONCATENATE(B76,";c",D76) -> B02.00;c0481 | D76: 0481 | E76: Trading venue (LEI) | F76: =CONCATENATE(G76,": ",H76) -> String: Free text | G76: String | H76: Free text | I76: Input "Not applicable" | K76: =+"FRMT_"&L76 -> FRMT_0481_trdng_vn_lei | L76: =+VLOOKUP(D76,'B02_Mapping fields'!B:C,2,FALSE) -> 0481_trdng_vn_lei | M76: =+",CASE WHEN (`"&L76&"` RLIKE '[A-Za-z]' and `"&L76&"` NOT IN ('N/A','11111111111','11111111111.00','11111111111.000000','1111-11-11','0000-00-00','0001-01-01','9999-12-31','MISS','00000','99999999999','999999999999999','99999999999.00','99999999999.000000','-9999.9999','','XXX')) OR `"&L76&"` = 'Not applicable' THEN 0 ELSE 1 END AS "&K76 -> ,CASE WHEN (`0481_trdng_vn_lei` RLIKE '[A-Za-z]' and `0481_trdng_vn_lei` NOT IN ('N/A','11111111111','11111111111.00','11111111111.000000','1111-11-11','0000-00-00','0001-01-01','9999-12-31','MISS','00000','99999999999','999999999999999','99999999999.00','99999999999.000000','-9999.9999','','XXX')) OR `0481_trdng_vn_lei` = 'Not applicable' THEN 0 ELSE 1 END AS FRMT_0481_trdng_vn_lei | N76: =+"SUM("&K76&") AS `"&K76&"`," -> SUM(FRMT_0481_trdng_vn_lei) AS `FRMT_0481_trdng_vn_lei`,
