Workbook
Name asefadf: #REF!
Name bn: #REF!

Sheet 1. Campos
G2: Campos adicionados ao âmbito na nova versão da Corporação
G3: Campos fora de âmbito na nova versão da Corporação
G4: Campos por especificar do plano anterior (colunas AM/AN - Novo projeto martelado com não)
G5: Campos por testar do plano anterior (colunas AM/AN - Novo projeto martelado com não)
C6: Obs:. É necessário filtrar tudo o que não esta fora de âmbito, tudo o que não esta no PDS e excluir os verdes que são para testes e os vermelhos que foram excluidos.
B8: ID Data field / Field order | C8: Table | D8: Category | E8: Anacredit | G8: Data field | H8: Efectivo y otros depósitos a la vista / Cash balances and other deposits | I8: Bancos Centrales / Central Banks | J8: Administraciones públicas / General governments | K8: Entidades de crédito / Credit institutions | L8: Otras sociedades financieras / Other financial corporations | M8: Sociedades no financieras / Non financial corporations | N8: Hogares / Households | O8: DEBT SECURITIES (this column only applies to report the instrument table) | P8: Non-contractual balances and Accounting adjustments (this column only applies to report the instrument table) | Q8: Instrument cancelled (this column only applies to report the instrument and instrument activity tables) | R8: Data Types | S8: Guidance on data types | T8: Default value for missing data | U8: Default value for not applicable fields to be used WHEN the field is applicable for the corresponding segment (F to L columns ) | V8: Default value for not applicable fields to be used WHEN: (1) Non-contractual balances and accounting adjustments (2) If the field is not applicable for the corresponding segment (F to L columns) | W8: Field name | X8: Field Definition / Additional Guidance | Y8: BDR Status (*) Not applicable = not identified as available in BDR | Z8: BDR Definition | AA8: BDR Comments | AB8: Structural ECB Loan Tape | AC8: Green Dashboard | AD8: Pillar III ESG & CSRD | AE8: Green Finance | AF8: ESG Risks | AG8: Leveraged Finance | AH8: D + 15 [Green Dashboard] | AI8: D + 18 [+ Pillar III ESG] | AJ8: > D + 18 [+ ECB Loan Tape] | AK8: Âmbito | AL8: ESPEC PM | AM8: ESPEC PILAR 3 V12 | AN8: PdS 5.12 | AO8: Novo Projeto | AP8: PROJ GF | AQ8: STATUS PdS | AR8: STATUS GF | AT8: Especificação | AU8: Teste | AV8: Package | AW8: Status Entregas | AX8: Comentários
A9: =+C9&G9 -> ENTITYCOD_SOC | B9: EN.001 | C9: ENTITY | D9: Cargabal entity | E9: N | F9: COD_SOC | G9: COD_SOC | H9: Y | I9: Y | J9: Y | K9: Y | L9: Y | M9: Y | N9: Y | R9: VARCHAR2(5) | S9: Free (latin) text without special characters (semicolon, quotes, …) | T9: Default value not allowed | U9: Default value not allowed | V9: Default value not allowed | W9: Entity code of the informing society. | X9: Cargabal code or internal identifier of the informing society. | Y9: Not applicable | Z9: N/A | AA9: - | AB9: Y | AC9: N | AD9: Y | AE9: Y | AF9: Y | AG9: Y | AH9: N | AI9: Y | AJ9: Y | AK9: =+IF(AND(AD9="N",AF9="N"),"Fora de âmbito", IF(AND(AD9="N",AF9="Y"),"Apenas ESG Risk", IF(AND(AD9="Y",AF9="N"),"Apenas Pilar 3", IF(AND(AD9="Y",AF9="Y"),"Comum","")))) -> Comum | AL9: =+IF(IFERROR(VLOOKUP(A9,Ficheiros!I:I,1,FALSE),"")=A9,"Sim","Não") -> Sim | AM9: =+IF(IFERROR(VLOOKUP(A9,Ficheiros!E:E,1,FALSE),"")=A9,"Sim","Não") -> Não | AN9: =+IF(IFERROR(VLOOKUP(A9,Ficheiros!O:O,1,FALSE),"")=A9,"Sim","Não") -> Sim | AO9: =+IF(IFERROR(VLOOKUP(A9,'Especificação Novos Req. LT (2'!A:A,1,FALSE),"")=A9,"Sim","Não") -> Não | AP9: =+IF(IFERROR(VLOOKUP(A9,Ficheiros!T:T,1,FALSE),"")=A9,"Sim","Não") -> Sim | AQ9: =+VLOOKUP(A9,Ficheiros!O:P,2,FALSE) -> 1. Concluído | AR9: =+VLOOKUP(A9,Ficheiros!T:U,2,FALSE) -> 9. Concluído | AS9: =+VLOOKUP(A9,Ficheiros!T:V,3,FALSE) -> PM
A10: =+C10&G10 -> ENTITYCNTRY | B10: EN.002 | C10: ENTITY | D10: General | E10: Y | F10: CNTRY | G10: CNTRY | H10: Y | I10: Y | J10: Y | K10: Y | L10: Y | M10: Y | N10: Y | R10: Code list | S10: Use codes from the code list sheet | T10: MISS | U10: Default value not allowed | V10: N/A | W10: Country of counterparty residence | X10: Country of counterparty residence. | Y10: Yes - Mapping | Z10: BDR - Code List | AA10: - | AB10: Y | AC10: N | AD10: Y | AE10: Y | AF10: Y | AG10: Y | AH10: N | AI10: Y | AJ10: Y | AK10: =+IF(AND(AD10="N",AF10="N"),"Fora de âmbito", IF(AND(AD10="N",AF10="Y"),"Apenas ESG Risk", IF(AND(AD10="Y",AF10="N"),"Apenas Pilar 3", IF(AND(AD10="Y",AF10="Y"),"Comum","")))) -> Comum | AL10: =+IF(IFERROR(VLOOKUP(A10,Ficheiros!I:I,1,FALSE),"")=A10,"Sim","Não") -> Sim | AM10: =+IF(IFERROR(VLOOKUP(A10,Ficheiros!E:E,1,FALSE),"")=A10,"Sim","Não") -> Não | AN10: =+IF(IFERROR(VLOOKUP(A10,Ficheiros!O:O,1,FALSE),"")=A10,"Sim","Não") -> Sim | AO10: =+IF(IFERROR(VLOOKUP(A10,'Especificação Novos Req. LT (2'!A:A,1,FALSE),"")=A10,"Sim","Não") -> Não | AP10: =+IF(IFERROR(VLOOKUP(A10,Ficheiros!T:T,1,FALSE),"")=A10,"Sim","Não") -> Sim | AQ10: =+VLOOKUP(A10,Ficheiros!O:P,2,FALSE) -> 1. Concluído | AR10: =+VLOOKUP(A10,Ficheiros!T:U,2,FALSE) -> 9. Concluído | AS10: =+VLOOKUP(A10,Ficheiros!T:V,3,FALSE) -> PM
A11: =+C11&G11 -> ENTITYDT_BRTH | B11: EN.003 | C11: ENTITY | D11: General | E11: Y | F11: DT_BRTH | G11: DT_BRTH | H11: N | I11: N | J11: N | K11: N | L11: N | M11: Y | N11: Y | R11: DATE | S11: YYYY-MM-DD | T11: 0000-00-00 | U11: Default value not allowed | V11: 1111-11-11 | W11: Birth date counterparty | X11: Date when the entity was born / registered. | Y11: Yes - Equivalent | Z11: JM_CLIENT_BII - G4093_FECNACIM | AA11: - | AB11: Y | AC11: N | AD11: N | AE11: N | AF11: N | AG11: N | AH11: N | AI11: N | AJ11: Y | AK11: =+IF(AND(AD11="N",AF11="N"),"Fora de âmbito", IF(AND(AD11="N",AF11="Y"),"Apenas ESG Risk", IF(AND(AD11="Y",AF11="N"),"Apenas Pilar 3", IF(AND(AD11="Y",AF11="Y"),"Comum","")))) -> Fora de âmbito | AL11: =+IF(IFERROR(VLOOKUP(A11,Ficheiros!I:I,1,FALSE),"")=A11,"Sim","Não") -> Sim | AM11: =+IF(IFERROR(VLOOKUP(A11,Ficheiros!E:E,1,FALSE),"")=A11,"Sim","Não") -> Não | AN11: =+IF(IFERROR(VLOOKUP(A11,Ficheiros!O:O,1,FALSE),"")=A11,"Sim","Não") -> Não | AO11: =+IF(IFERROR(VLOOKUP(A11,'Especificação Novos Req. LT (2'!A:A,1,FALSE),"")=A11,"Sim","Não") -> Não | AP11: =+IF(IFERROR(VLOOKUP(A11,Ficheiros!T:T,1,FALSE),"")=A11,"Sim","Não") -> Sim | AQ11: =+VLOOKUP(A11,Ficheiros!O:P,2,FALSE) -> #N/A | AR11: =+VLOOKUP(A11,Ficheiros!T:U,2,FALSE) -> 7. Analisar controlos e completude | AS11: =+VLOOKUP(A11,Ficheiros!T:V,3,FALSE) -> PM
A12: =+C12&G12 -> ENTITYDT_DFLT_STTS | B12: EN.004 | C12: ENTITY | D12: General | E12: Y | F12: DT_DFLT_STTS | G12: DT_DFLT_STTS | H12: Y | I12: Y | J12: Y | K12: Y | L12: Y | M12: Y | N12: Y | R12: DATE | S12: YYYY-MM-DD | T12: 0000-00-00 | U12: 1111-11-11 | V12: 1111-11-11 | W12: Date of default status | X12: The date on which the default status, as reported in the data attribute “Default status”, is considered to have arisen. If "Not in default" since inception then this attribute is to be reported equally to the inception date. If default classification performed on instrument level then Entity is classified as defaulted when at least one instrument is classified as defaulted. If more than one Instrument is classified as defaulted then the earliest date has to be provided. The definition of default is aligned with Art 178 of Regulation (EU) No 575/2013. | Y12: Not applicable | Z12: N/A | AA12: - | AB12: Y | AC12: N | AD12: N | AE12: N | AF12: N | AG12: Y | AH12: N | AI12: N | AJ12: Y | AK12: =+IF(AND(AD12="N",AF12="N"),"Fora de âmbito", IF(AND(AD12="N",AF12="Y"),"Apenas ESG Risk", IF(AND(AD12="Y",AF12="N"),"Apenas Pilar 3", IF(AND(AD12="Y",AF12="Y"),"Comum","")))) -> Fora de âmbito | AL12: =+IF(IFERROR(VLOOKUP(A12,Ficheiros!I:I,1,FALSE),"")=A12,"Sim","Não") -> Sim | AM12: =+IF(IFERROR(VLOOKUP(A12,Ficheiros!E:E,1,FALSE),"")=A12,"Sim","Não") -> Não | AN12: =+IF(IFERROR(VLOOKUP(A12,Ficheiros!O:O,1,FALSE),"")=A12,"Sim","Não") -> Não | AO12: =+IF(IFERROR(VLOOKUP(A12,'Especificação Novos Req. LT (2'!A:A,1,FALSE),"")=A12,"Sim","Não") -> Não | AP12: =+IF(IFERROR(VLOOKUP(A12,Ficheiros!T:T,1,FALSE),"")=A12,"Sim","Não") -> Sim | AQ12: =+VLOOKUP(A12,Ficheiros!O:P,2,FALSE) -> #N/A | AR12: =+VLOOKUP(A12,Ficheiros!T:U,2,FALSE) -> 3. Pendente de decisão | AS12: =+VLOOKUP(A12,Ficheiros!T:V,3,FALSE) -> LF
A13: =+C13&G13 -> ENTITYDT_FNNCL_STTMTS | B13: EN.005 | C13: ENTITY | D13: General | E13: N | F13: DT_FNNCL_STTMTS | G13: DT_FNNCL_STTMTS | H13: Y | I13: Y | J13: Y | K13: Y | L13: Y | M13: Y | N13: N | R13: DATE | S13: YYYY-MM-DD | T13: 0000-00-00 | U13: 1111-11-11 | V13: 1111-11-11 | W13: Date of financial statements | X13: Date of financial statements. Please report on solo entity level unless advised otherwise. | Y13: Not applicable | Z13: N/A | AA13: - | AB13: Y | AC13: N | AD13: N | AE13: N | AF13: N | AG13: Y | AH13: N | AI13: N | AJ13: Y | AK13: =+IF(AND(AD13="N",AF13="N"),"Fora de âmbito", IF(AND(AD13="N",AF13="Y"),"Apenas ESG Risk", IF(AND(AD13="Y",AF13="N"),"Apenas Pilar 3", IF(AND(AD13="Y",AF13="Y"),"Comum","")))) -> Fora de âmbito | AL13: =+IF(IFERROR(VLOOKUP(A13,Ficheiros!I:I,1,FALSE),"")=A13,"Sim","Não") -> Sim | AM13: =+IF(IFERROR(VLOOKUP(A13,Ficheiros!E:E,1,FALSE),"")=A13,"Sim","Não") -> Não | AN13: =+IF(IFERROR(VLOOKUP(A13,Ficheiros!O:O,1,FALSE),"")=A13,"Sim","Não") -> Não | AO13: =+IF(IFERROR(VLOOKUP(A13,'Especificação Novos Req. LT (2'!A:A,1,FALSE),"")=A13,"Sim","Não") -> Não | AP13: =+IF(IFERROR(VLOOKUP(A13,Ficheiros!T:T,1,FALSE),"")=A13,"Sim","Não") -> Sim | AQ13: =+VLOOKUP(A13,Ficheiros!O:P,2,FALSE) -> #N/A | AR13: =+VLOOKUP(A13,Ficheiros!T:U,2,FALSE) -> 2. Alterar especificação | AS13: =+VLOOKUP(A13,Ficheiros!T:V,3,FALSE) -> PM & LF
A14: =+C14&G14 -> ENTITYDT_FNNCL_STTMTS_PRVS | B14: EN.006 | C14: ENTITY | D14: General | E14: N | F14: DT_FNNCL_STTMTS_PRVS | G14: DT_FNNCL_STTMTS_PRVS | H14: Y | I14: Y | J14: Y | K14: Y | L14: Y | M14: Y | N14: N | R14: DATE | S14: YYYY-MM-DD | T14: 0000-00-00 | U14: 1111-11-11 | V14: 1111-11-11 | W14: Date of previous fiscal year financial statements | X14: Date of previous fiscal year financial statements. Please report on solo entity level unless advised otherwise. | Y14: Not applicable | Z14: N/A | AA14: - | AB14: Y | AC14: N | AD14: N | AE14: N | AF14: N | AG14: Y | AH14: N | AI14: N | AJ14: Y | AK14: =+IF(AND(AD14="N",AF14="N"),"Fora de âmbito", IF(AND(AD14="N",AF14="Y"),"Apenas ESG Risk", IF(AND(AD14="Y",AF14="N"),"Apenas Pilar 3", IF(AND(AD14="Y",AF14="Y"),"Comum","")))) -> Fora de âmbito | AL14: =+IF(IFERROR(VLOOKUP(A14,Ficheiros!I:I,1,FALSE),"")=A14,"Sim","Não") -> Sim | AM14: =+IF(IFERROR(VLOOKUP(A14,Ficheiros!E:E,1,FALSE),"")=A14,"Sim","Não") -> Não | AN14: =+IF(IFERROR(VLOOKUP(A14,Ficheiros!O:O,1,FALSE),"")=A14,"Sim","Não") -> Não | AO14: =+IF(IFERROR(VLOOKUP(A14,'Especificação Novos Req. LT (2'!A:A,1,FALSE),"")=A14,"Sim","Não") -> Não | AP14: =+IF(IFERROR(VLOOKUP(A14,Ficheiros!T:T,1,FALSE),"")=A14,"Sim","Não") -> Sim | AQ14: =+VLOOKUP(A14,Ficheiros!O:P,2,FALSE) -> #N/A | AR14: =+VLOOKUP(A14,Ficheiros!T:U,2,FALSE) -> 2. Alterar especificação | AS14: =+VLOOKUP(A14,Ficheiros!T:V,3,FALSE) -> PM & LF
A15: =+C15&G15 -> ENTITYDT_INTTN_LGL_PRCDNGS_LE | B15: EN.007 | C15: ENTITY | D15: General | E15: Y | F15: DT_INTTN_LGL_PRCDNGS_LE | G15: DT_INTTN_LGL_PRCDNGS_LE | H15: Y | I15: Y | J15: Y | K15: Y | L15: Y | M15: Y | N15: Y | R15: DATE | S15: YYYY-MM-DD | T15: 0000-00-00 | U15: 1111-11-11 | V15: 1111-11-11 | W15: Date of initiation of legal proceedings counterparty (LE) | X15: Date of initiation of legal proceedings counterparty (LE). Only for Retail portfolios: The date when the hard collection process was initiated for given entity. If the hard collection process is defined on the level of instrument or protection and more instruments or protections with status "Other legal measures" are linked to the same entity the oldest date is reported. | Y15: Yes - Computed | Z15: IF E0623_GEST_SIT in (8;9) THEN E0623_FECULTMO | AA15: - | AB15: Y | AC15: N | AD15: N | AE15: N | AF15: N | AG15: Y | AH15: N | AI15: N | AJ15: Y | AK15: =+IF(AND(AD15="N",AF15="N"),"Fora de âmbito", IF(AND(AD15="N",AF15="Y"),"Apenas ESG Risk", IF(AND(AD15="Y",AF15="N"),"Apenas Pilar 3", IF(AND(AD15="Y",AF15="Y"),"Comum","")))) -> Fora de âmbito | AL15: =+IF(IFERROR(VLOOKUP(A15,Ficheiros!I:I,1,FALSE),"")=A15,"Sim","Não") -> Sim | AM15: =+IF(IFERROR(VLOOKUP(A15,Ficheiros!E:E,1,FALSE),"")=A15,"Sim","Não") -> Não | AN15: =+IF(IFERROR(VLOOKUP(A15,Ficheiros!O:O,1,FALSE),"")=A15,"Sim","Não") -> Não | AO15: =+IF(IFERROR(VLOOKUP(A15,'Especificação Novos Req. LT (2'!A:A,1,FALSE),"")=A15,"Sim","Não") -> Não | AP15: =+IF(IFERROR(VLOOKUP(A15,Ficheiros!T:T,1,FALSE),"")=A15,"Sim","Não") -> Sim | AQ15: =+VLOOKUP(A15,Ficheiros!O:P,2,FALSE) -> #N/A | AR15: =+VLOOKUP(A15,Ficheiros!T:U,2,FALSE) -> 9. Concluído | AS15: =+VLOOKUP(A15,Ficheiros!T:V,3,FALSE) -> PM
A16: =+C16&G16 -> ENTITYDT_PRFRMNG_STTS_LE | B16: EN.008 | C16: ENTITY | D16: General | E16: N | F16: DT_PRFRMNG_STTS_LE | G16: DT_PRFRMNG_STTS_LE | H16: Y | I16: Y | J16: Y | K16: Y | L16: Y | M16: Y | N16: Y | R16: DATE | S16: YYYY-MM-DD | T16: 0000-00-00 | U16: 1111-11-11 | V16: 1111-11-11 | W16: Date of performing status | X16: The date at which the latest change of the performing status according to Part 17 of Annex V to Implementing Regulation (EU) No 680/2014 occurred. For entities performing from inception this date should be equal to inception date. | Y16: Not applicable | Z16: N/A | AA16: - | AB16: Y | AC16: N | AD16: N | AE16: N | AF16: N | AG16: Y | AH16: N | AI16: N | AJ16: Y | AK16: =+IF(AND(AD16="N",AF16="N"),"Fora de âmbito", IF(AND(AD16="N",AF16="Y"),"Apenas ESG Risk", IF(AND(AD16="Y",AF16="N"),"Apenas Pilar 3", IF(AND(AD16="Y",AF16="Y"),"Comum","")))) -> Fora de âmbito | AL16: =+IF(IFERROR(VLOOKUP(A16,Ficheiros!I:I,1,FALSE),"")=A16,"Sim","Não") -> Sim | AM16: =+IF(IFERROR(VLOOKUP(A16,Ficheiros!E:E,1,FALSE),"")=A16,"Sim","Não") -> Não | AN16: =+IF(IFERROR(VLOOKUP(A16,Ficheiros!O:O,1,FALSE),"")=A16,"Sim","Não") -> Não | AO16: =+IF(IFERROR(VLOOKUP(A16,'Especificação Novos Req. LT (2'!A:A,1,FALSE),"")=A16,"Sim","Não") -> Não | AP16: =+IF(IFERROR(VLOOKUP(A16,Ficheiros!T:T,1,FALSE),"")=A16,"Sim","Não") -> Sim | AQ16: =+VLOOKUP(A16,Ficheiros!O:P,2,FALSE) -> #N/A | AR16: =+VLOOKUP(A16,Ficheiros!T:U,2,FALSE) -> 3. Pendente de decisão | AS16: =+VLOOKUP(A16,Ficheiros!T:V,3,FALSE) -> LF
A17: =+C17&G17 -> ENTITYDT_RFRNC | B17: EN.009 | C17: ENTITY | D17: General | E17: Y | F17: DT_RFRNC | G17: DT_RFRNC | H17: Y | I17: Y | J17: Y | K17: Y | L17: Y | M17: Y | N17: Y | R17: DATE | S17: YYYY-MM-DD | T17: Default value not allowed | U17: Default value not allowed | V17: Default value not allowed | W17: Reference date. | X17: Reference date. The reference date can refer to end-of-month, end-of-quarter or end-of-year. The value is fixed for the entire loan tape and will be defined and communicated by the Head of Mission. | Y17: Not applicable | Z17: N/A | AA17: - | AB17: Y | AC17: N | AD17: Y | AE17: Y | AF17: N | AG17: Y | AH17: N | AI17: Y | AJ17: Y | AK17: =+IF(AND(AD17="N",AF17="N"),"Fora de âmbito", IF(AND(AD17="N",AF17="Y"),"Apenas ESG Risk", IF(AND(AD17="Y",AF17="N"),"Apenas Pilar 3", IF(AND(AD17="Y",AF17="Y"),"Comum","")))) -> Apenas Pilar 3 | AL17: =+IF(IFERROR(VLOOKUP(A17,Ficheiros!I:I,1,FALSE),"")=A17,"Sim","Não") -> Sim | AM17: =+IF(IFERROR(VLOOKUP(A17,Ficheiros!E:E,1,FALSE),"")=A17,"Sim","Não") -> Não | AN17: =+IF(IFERROR(VLOOKUP(A17,Ficheiros!O:O,1,FALSE),"")=A17,"Sim","Não") -> Sim | AO17: =+IF(IFERROR(VLOOKUP(A17,'Especificação Novos Req. LT (2'!A:A,1,FALSE),"")=A17,"Sim","Não") -> Não | AP17: =+IF(IFERROR(VLOOKUP(A17,Ficheiros!T:T,1,FALSE),"")=A17,"Sim","Não") -> Sim | AQ17: =+VLOOKUP(A17,Ficheiros!O:P,2,FALSE) -> 1. Concluído | AR17: =+VLOOKUP(A17,Ficheiros!T:U,2,FALSE) -> 9. Concluído | AS17: =+VLOOKUP(A17,Ficheiros!T:V,3,FALSE) -> PM
A18: =+C18&G18 -> ENTITYENTTY_ID | B18: EN.010 | C18: ENTITY | D18: General | E18: Y | F18: ENTTY_ID | G18: ENTTY_ID | H18: Y | I18: Y | J18: Y | K18: Y | L18: Y | M18: Y | N18: Y | R18: VARCHAR2(255) | S18: Free (latin) text without special characters (semicolon, quotes, …) | T18: Default value not allowed | U18: Default value not allowed | V18: Default value not allowed | W18: Entity ID | X18: An identifier applied by the reporting agent to uniquely identify each counterparty. Each counterparty has a unique and exclusive counterparty identifier. This means that this value will not change over time and can never be used as the counterparty identifier for any other counterparty. | Y18: Not applicable | Z18: N/A | AA18: - | AB18: Y | AC18: N | AD18: Y | AE18: Y | AF18: Y | AG18: Y | AH18: N | AI18: Y | AJ18: Y | AK18: =+IF(AND(AD18="N",AF18="N"),"Fora de âmbito", IF(AND(AD18="N",AF18="Y"),"Apenas ESG Risk", IF(AND(AD18="Y",AF18="N"),"Apenas Pilar 3", IF(AND(AD18="Y",AF18="Y"),"Comum","")))) -> Comum | AL18: =+IF(IFERROR(VLOOKUP(A18,Ficheiros!I:I,1,FALSE),"")=A18,"Sim","Não") -> Sim | AM18: =+IF(IFERROR(VLOOKUP(A18,Ficheiros!E:E,1,FALSE),"")=A18,"Sim","Não") -> Não | AN18: =+IF(IFERROR(VLOOKUP(A18,Ficheiros!O:O,1,FALSE),"")=A18,"Sim","Não") -> Sim | AO18: =+IF(IFERROR(VLOOKUP(A18,'Especificação Novos Req. LT (2'!A:A,1,FALSE),"")=A18,"Sim","Não") -> Não | AP18: =+IF(IFERROR(VLOOKUP(A18,Ficheiros!T:T,1,FALSE),"")=A18,"Sim","Não") -> Sim | AQ18: =+VLOOKUP(A18,Ficheiros!O:P,2,FALSE) -> 1. Concluído | AR18: =+VLOOKUP(A18,Ficheiros!T:U,2,FALSE) -> 7. Analisar controlos e completude | AS18: =+VLOOKUP(A18,Ficheiros!T:V,3,FALSE) -> LF
A19: =+C19&G19 -> ENTITYGCC_PRNT_ID | B19: EN.011 | C19: ENTITY | D19: General | E19: N | F19: GCC_PRNT_ID | G19: GCC_PRNT_ID | H19: Y | I19: Y | J19: Y | K19: Y | L19: Y | M19: Y | N19: N | R19: VARCHAR2(255) | S19: Free (latin) text without special characters (semicolon, quotes, …) | T19: MISS | U19: N/A | V19: N/A | W19: Identifier for the parent entity of a group of connected clients | X19: The unique identifier of the group of connected clients according to Art 4 para. 39 of Regulation (EU) No 575/2013. If an entity is part of more than one group of connected clients please report the identifier for the most relevant. | Y19: Yes - Equivalent | Z19: JM_GRUP_ECONO - G5512_GRUP_ECO | AA19: - | AB19: Y | AC19: N | AD19: N | AE19: N | AF19: N | AG19: Y | AH19: N | AI19: N | AJ19: Y | AK19: =+IF(AND(AD19="N",AF19="N"),"Fora de âmbito", IF(AND(AD19="N",AF19="Y"),"Apenas ESG Risk", IF(AND(AD19="Y",AF19="N"),"Apenas Pilar 3", IF(AND(AD19="Y",AF19="Y"),"Comum","")))) -> Fora de âmbito | AL19: =+IF(IFERROR(VLOOKUP(A19,Ficheiros!I:I,1,FALSE),"")=A19,"Sim","Não") -> Sim | AM19: =+IF(IFERROR(VLOOKUP(A19,Ficheiros!E:E,1,FALSE),"")=A19,"Sim","Não") -> Não | AN19: =+IF(IFERROR(VLOOKUP(A19,Ficheiros!O:O,1,FALSE),"")=A19,"Sim","Não") -> Não | AO19: =+IF(IFERROR(VLOOKUP(A19,'Especificação Novos Req. LT (2'!A:A,1,FALSE),"")=A19,"Sim","Não") -> Não | AP19: =+IF(IFERROR(VLOOKUP(A19,Ficheiros!T:T,1,FALSE),"")=A19,"Sim","Não") -> Sim | AQ19: =+VLOOKUP(A19,Ficheiros!O:P,2,FALSE) -> #N/A | AR19: =+VLOOKUP(A19,Ficheiros!T:U,2,FALSE) -> 9. Concluído | AS19: =+VLOOKUP(A19,Ficheiros!T:V,3,FALSE) -> PM
A20: =+C20&G20 -> ENTITYGCC_PRNT_NM | B20: EN.012 | C20: ENTITY | D20: General | E20: N | F20: GCC_PRNT_NM | G20: GCC_PRNT_NM | H20: Y | I20: Y | J20: Y | K20: Y | L20: Y | M20: Y | N20: N | R20: VARCHAR2(255) | S20: Free (latin) text without special characters (semicolon, quotes, …) | T20: MISS | U20: N/A | V20: N/A | W20: Name of the parent entity of a group of connected clients | X20: The name of the group of connected clients according to Art 4 para. 39 of Regulation (EU) No 575/2013. If an entity is part of more than one group of connected clients please report the name for the most relevant. | Y20: Yes - Equivalent | Z20: JM_GRUP_ECONO - G5512_DGRUPO | AA20: Report Name of the entity reported in EN.011 | AB20: Y | AC20: N | AD20: N | AE20: N | AF20: N | AG20: Y | AH20: N | AI20: N | AJ20: Y | AK20: =+IF(AND(AD20="N",AF20="N"),"Fora de âmbito", IF(AND(AD20="N",AF20="Y"),"Apenas ESG Risk", IF(AND(AD20="Y",AF20="N"),"Apenas Pilar 3", IF(AND(AD20="Y",AF20="Y"),"Comum","")))) -> Fora de âmbito | AL20: =+IF(IFERROR(VLOOKUP(A20,Ficheiros!I:I,1,FALSE),"")=A20,"Sim","Não") -> Sim | AM20: =+IF(IFERROR(VLOOKUP(A20,Ficheiros!E:E,1,FALSE),"")=A20,"Sim","Não") -> Não | AN20: =+IF(IFERROR(VLOOKUP(A20,Ficheiros!O:O,1,FALSE),"")=A20,"Sim","Não") -> Não | AO20: =+IF(IFERROR(VLOOKUP(A20,'Especificação Novos Req. LT (2'!A:A,1,FALSE),"")=A20,"Sim","Não") -> Não | AP20: =+IF(IFERROR(VLOOKUP(A20,Ficheiros!T:T,1,FALSE),"")=A20,"Sim","Não") -> Sim | AQ20: =+VLOOKUP(A20,Ficheiros!O:P,2,FALSE) -> #N/A | AR20: =+VLOOKUP(A20,Ficheiros!T:U,2,FALSE) -> 9. Concluído | AS20: =+VLOOKUP(A20,Ficheiros!T:V,3,FALSE) -> PM
... A23: =+C23&G23 -> ENTITYLEI | B23: EN.015 | C23: ENTITY | D23: General | E23: Y | F23: LEI | G23: LEI | H23: Y | I23: Y | J23: Y | K23: Y | L23: Y | M23: Y | N23: N | R23: VARCHAR2(20) | S23: Free (latin) text without special characters (semicolon, quotes, …) | T23: MISS | U23: N/A | V23: N/A | W23: Legal entity identifier Counterparty | X23: Legal entity identifier counterparty. | Y23: Not applicable | Z23: N/A | AA23: - | AB23: Y | AC23: N | AD23: Y | AE23: N | AF23: N | AG23: Y | AH23: N | AI23: Y | AJ23: Y | AK23: =+IF(AND(AD23="N",AF23="N"),"Fora de âmbito", IF(AND(AD23="N",AF23="Y"),"Apenas ESG Risk", IF(AND(AD23="Y",AF23="N"),"Apenas Pilar 3", IF(AND(AD23="Y",AF23="Y"),"Comum","")))) -> Apenas Pilar 3 | AL23: =+IF(IFERROR(VLOOKUP(A23,Ficheiros!I:I,1,FALSE),"")=A23,"Sim","Não") -> Sim | AM23: =+IF(IFERROR(VLOOKUP(A23,Ficheiros!E:E,1,FALSE),"")=A23,"Sim","Não") -> Não | AN23: =+IF(IFERROR(VLOOKUP(A23,Ficheiros!O:O,1,FALSE),"")=A23,"Sim","Não") -> Sim | AO23: =+IF(IFERROR(VLOOKUP(A23,'Especificação Novos Req. LT (2'!A:A,1,FALSE),"")=A23,"Sim","Não") -> Não | AP23: =+IF(IFERROR(VLOOKUP(A23,Ficheiros!T:T,1,FALSE),"")=A23,"Sim","Não") -> Sim | AQ23: =+VLOOKUP(A23,Ficheiros!O:P,2,FALSE) -> 1. Concluído | AR23: =+VLOOKUP(A23,Ficheiros!T:U,2,FALSE) -> 9. Concluído | AS23: =+VLOOKUP(A23,Ficheiros!T:V,3,FALSE) -> PM
A24: =+C24&G24 -> ENTITYENTTY_NM | B24: EN.016 | C24: ENTITY | D24: General | E24: Y | F24: ENTTY_NM | G24: ENTTY_NM | H24: Y | I24: Y | J24: Y | K24: Y | L24: Y | M24: Y | N24: Y | R24: VARCHAR2(255) | S24: Free (latin) text without special characters (semicolon, quotes, …) | T24: MISS | U24: Default value not allowed | V24: Default value not allowed | W24: Name Counterparty | X24: Name counterparty. | Y24: Not applicable | Z24: N/A | AA24: - | AB24: Y | AC24: N | AD24: Y | AE24: Y | AF24: N | AG24: Y | AH24: N | AI24: Y | AJ24: Y | AK24: =+IF(AND(AD24="N",AF24="N"),"Fora de âmbito", IF(AND(AD24="N",AF24="Y"),"Apenas ESG Risk", IF(AND(AD24="Y",AF24="N"),"Apenas Pilar 3", IF(AND(AD24="Y",AF24="Y"),"Comum","")))) -> Apenas Pilar 3 | AL24: =+IF(IFERROR(VLOOKUP(A24,Ficheiros!I:I,1,FALSE),"")=A24,"Sim","Não") -> Sim | AM24: =+IF(IFERROR(VLOOKUP(A24,Ficheiros!E:E,1,FALSE),"")=A24,"Sim","Não") -> Não | AN24: =+IF(IFERROR(VLOOKUP(A24,Ficheiros!O:O,1,FALSE),"")=A24,"Sim","Não") -> Não | AO24: =+IF(IFERROR(VLOOKUP(A24,'Especificação Novos Req. LT (2'!A:A,1,FALSE),"")=A24,"Sim","Não") -> Sim | AP24: =+IF(IFERROR(VLOOKUP(A24,Ficheiros!T:T,1,FALSE),"")=A24,"Sim","Não") -> Sim | AQ24: =+VLOOKUP(A24,Ficheiros!O:P,2,FALSE) -> #N/A | AR24: =+VLOOKUP(A24,Ficheiros!T:U,2,FALSE) -> 9. Concluído | AS24: =+VLOOKUP(A24,Ficheiros!T:V,3,FALSE) -> PM | AV24: Package 3
A25: =+C25&G25 -> ENTITYEXTRNL_RTNG_NM | B25: EN.017 | C25: ENTITY | D25: General | E25: N | F25: EXTRNL_RTNG_NM | G25: EXTRNL_RTNG_NM | H25: Y | I25: Y | J25: Y | K25: Y | L25: Y | M25: Y | N25: N | R25: VARCHAR2(255) | S25: Free (latin) text without special characters (semicolon, quotes, …) | T25: MISS | U25: N/A | V25: N/A | W25: Name of external rating agency | X25: Name of external rating agency for the external rating at the reference date. | Y25: Yes - Equivalent | Z25: JM_CAL_EXT_CL - R9415_COD_AGEN | AA25: - | AB25: Y | AC25: N | AD25: N | AE25: N | AF25: N | AG25: Y | AH25: N | AI25: N | AJ25: Y | AK25: =+IF(AND(AD25="N",AF25="N"),"Fora de âmbito", IF(AND(AD25="N",AF25="Y"),"Apenas ESG Risk", IF(AND(AD25="Y",AF25="N"),"Apenas Pilar 3", IF(AND(AD25="Y",AF25="Y"),"Comum","")))) -> Fora de âmbito | AL25: =+IF(IFERROR(VLOOKUP(A25,Ficheiros!I:I,1,FALSE),"")=A25,"Sim","Não") -> Sim | AM25: =+IF(IFERROR(VLOOKUP(A25,Ficheiros!E:E,1,FALSE),"")=A25,"Sim","Não") -> Não | AN25: =+IF(IFERROR(VLOOKUP(A25,Ficheiros!O:O,1,FALSE),"")=A25,"Sim","Não") -> Não | AO25: =+IF(IFERROR(VLOOKUP(A25,'Especificação Novos Req. LT (2'!A:A,1,FALSE),"")=A25,"Sim","Não") -> Não | AP25: =+IF(IFERROR(VLOOKUP(A25,Ficheiros!T:T,1,FALSE),"")=A25,"Sim","Não") -> Sim | AQ25: =+VLOOKUP(A25,Ficheiros!O:P,2,FALSE) -> #N/A | AR25: =+VLOOKUP(A25,Ficheiros!T:U,2,FALSE) -> 2. Alterar especificação | AS25: =+VLOOKUP(A25,Ficheiros!T:V,3,FALSE) -> LF
A26: =+C26&G26 -> ENTITYACCNTNG_FRMWRK_SL | B26: EN.018 | C26: ENTITY | D26: Classification | E26: Y | F26: ACCNTNG_FRMWRK_SL | G26: ACCNTNG_FRMWRK_SL | H26: Y | I26: Y | J26: Y | K26: Y | L26: Y | M26: Y | N26: N | R26: Code List | S26: Use codes from the code list sheet | T26: 99999999999 | U26: 11111111111 | V26: 11111111111 | W26: Accounting standard counterparty | X26: Accounting standard counterparty. | Y26: Not applicable | Z26: N/A | AA26: - | AB26: Y | AC26: N | AD26: N | AE26: N | AF26: N | AG26: Y | AH26: N | AI26: N | AJ26: Y | AK26: =+IF(AND(AD26="N",AF26="N"),"Fora de âmbito", IF(AND(AD26="N",AF26="Y"),"Apenas ESG Risk", IF(AND(AD26="Y",AF26="N"),"Apenas Pilar 3", IF(AND(AD26="Y",AF26="Y"),"Comum","")))) -> Fora de âmbito | AL26: =+IF(IFERROR(VLOOKUP(A26,Ficheiros!I:I,1,FALSE),"")=A26,"Sim","Não") -> Sim | AM26: =+IF(IFERROR(VLOOKUP(A26,Ficheiros!E:E,1,FALSE),"")=A26,"Sim","Não") -> Não | AN26: =+IF(IFERROR(VLOOKUP(A26,Ficheiros!O:O,1,FALSE),"")=A26,"Sim","Não") -> Não | AO26: =+IF(IFERROR(VLOOKUP(A26,'Especificação Novos Req. LT (2'!A:A,1,FALSE),"")=A26,"Sim","Não") -> Não | AP26: =+IF(IFERROR(VLOOKUP(A26,Ficheiros!T:T,1,FALSE),"")=A26,"Sim","Não") -> Sim | AQ26: =+VLOOKUP(A26,Ficheiros!O:P,2,FALSE) -> #N/A | AR26: =+VLOOKUP(A26,Ficheiros!T:U,2,FALSE) -> 2. Alterar especificação | AS26: =+VLOOKUP(A26,Ficheiros!T:V,3,FALSE) -> PM & LF
A27: =+C27&G27 -> ENTITYCR_FLG | B27: EN.019 | C27: ENTITY | D27: Classification | E27: N | F27: CR_FLG | G27: CR_FLG | H27: Y | I27: Y | J27: Y | K27: Y | L27: Y | M27: Y | N27: Y | R27: Y, N | S27: Boolean: Y/N | T27: MISS | U27: N/A | V27: N/A | W27: Cure flag for entity which was classified as non-performing in the last 1.5 years and is classified as performing at the reference date | X27: The entity is to be classified on the reference date under one of the following categories: performing or non-performing, in accordance with Annex V to Implementing Regulation (EU) No 680/2014. | Y27: Yes - Computed | Z27: IF H0883_IND_CURA = 1 THEN T; ELSE IF H0883_IND_CURA = 0 THEN F; THEN N/A | AA27: - | AB27: Y | AC27: N | AD27: N | AE27: N | AF27: N | AG27: N | AH27: N | AI27: N | AJ27: Y | AK27: =+IF(AND(AD27="N",AF27="N"),"Fora de âmbito", IF(AND(AD27="N",AF27="Y"),"Apenas ESG Risk", IF(AND(AD27="Y",AF27="N"),"Apenas Pilar 3", IF(AND(AD27="Y",AF27="Y"),"Comum","")))) -> Fora de âmbito | AL27: =+IF(IFERROR(VLOOKUP(A27,Ficheiros!I:I,1,FALSE),"")=A27,"Sim","Não") -> Sim | AM27: =+IF(IFERROR(VLOOKUP(A27,Ficheiros!E:E,1,FALSE),"")=A27,"Sim","Não") -> Não | AN27: =+IF(IFERROR(VLOOKUP(A27,Ficheiros!O:O,1,FALSE),"")=A27,"Sim","Não") -> Não | AO27: =+IF(IFERROR(VLOOKUP(A27,'Especificação Novos Req. LT (2'!A:A,1,FALSE),"")=A27,"Sim","Não") -> Não | AP27: =+IF(IFERROR(VLOOKUP(A27,Ficheiros!T:T,1,FALSE),"")=A27,"Sim","Não") -> Sim | AQ27: =+VLOOKUP(A27,Ficheiros!O:P,2,FALSE) -> #N/A | AR27: =+VLOOKUP(A27,Ficheiros!T:U,2,FALSE) -> 7. Analisar controlos e completude | AS27: =+VLOOKUP(A27,Ficheiros!T:V,3,FALSE) -> PM
A28: =+C28&G28 -> ENTITYDCSD | B28: EN.020 | C28: ENTITY | D28: Classification | E28: N | F28: DCSD | G28: DCSD | H28: N | I28: N | J28: N | K28: N | L28: N | M28: N | N28: Y | R28: Y, N | S28: Boolean: Y/N | T28: MISS | U28: N/A | V28: N/A | W28: Entity deceased | X28: Indicator as to whether the Entity has passed away. The data attribute is applicable to natural persons only. | Y28: Not applicable | Z28: N/A | AA28: - | AB28: Y | AC28: N | AD28: N | AE28: N | AF28: N | AG28: N | AH28: N | AI28: N | AJ28: Y | AK28: =+IF(AND(AD28="N",AF28="N"),"Fora de âmbito", IF(AND(AD28="N",AF28="Y"),"Apenas ESG Risk", IF(AND(AD28="Y",AF28="N"),"Apenas Pilar 3", IF(AND(AD28="Y",AF28="Y"),"Comum","")))) -> Fora de âmbito | AL28: =+IF(IFERROR(VLOOKUP(A28,Ficheiros!I:I,1,FALSE),"")=A28,"Sim","Não") -> Sim | AM28: =+IF(IFERROR(VLOOKUP(A28,Ficheiros!E:E,1,FALSE),"")=A28,"Sim","Não") -> Não | AN28: =+IF(IFERROR(VLOOKUP(A28,Ficheiros!O:O,1,FALSE),"")=A28,"Sim","Não") -> Não | AO28: =+IF(IFERROR(VLOOKUP(A28,'Especificação Novos Req. LT (2'!A:A,1,FALSE),"")=A28,"Sim","Não") -> Não | AP28: =+IF(IFERROR(VLOOKUP(A28,Ficheiros!T:T,1,FALSE),"")=A28,"Sim","Não") -> Sim | AQ28: =+VLOOKUP(A28,Ficheiros!O:P,2,FALSE) -> #N/A | AR28: =+VLOOKUP(A28,Ficheiros!T:U,2,FALSE) -> 9. Concluído | AS28: =+VLOOKUP(A28,Ficheiros!T:V,3,FALSE) -> PM
A29: =+C29&G29 -> ENTITYDFLT_STTS | B29: EN.021 | C29: ENTITY | D29: Classification | E29: Y | F29: DFLT_STTS | G29: DFLT_STTS | H29: Y | I29: Y | J29: Y | K29: Y | L29: Y | M29: Y | N29: Y | R29: Code List | S29: Use codes from the code list sheet | T29: 99999999999 | U29: 11111111111 | V29: 11111111111 | W29: Default status of the entity | X29: Identification of the default status of the counterparty. Categories describing the motives for which the counterparty can be in default in accordance with Article 178 of Regulation (EU) No 575/2013. For retail only: If default classification performed on instrument level then Entity is classified as defaulted when at least one instrument is classified as defaulted. For corporate, SME, CRE and LF: if default classification performed on instrument level then entity level is "not applicable". | Y29: Not applicable | Z29: N/A | AA29: - | AB29: Y | AC29: N | AD29: N | AE29: N | AF29: N | AG29: Y | AH29: N | AI29: N | AJ29: Y | AK29: =+IF(AND(AD29="N",AF29="N"),"Fora de âmbito", IF(AND(AD29="N",AF29="Y"),"Apenas ESG Risk", IF(AND(AD29="Y",AF29="N"),"Apenas Pilar 3", IF(AND(AD29="Y",AF29="Y"),"Comum","")))) -> Fora de âmbito | AL29: =+IF(IFERROR(VLOOKUP(A29,Ficheiros!I:I,1,FALSE),"")=A29,"Sim","Não") -> Sim | AM29: =+IF(IFERROR(VLOOKUP(A29,Ficheiros!E:E,1,FALSE),"")=A29,"Sim","Não") -> Não | AN29: =+IF(IFERROR(VLOOKUP(A29,Ficheiros!O:O,1,FALSE),"")=A29,"Sim","Não") -> Não | AO29: =+IF(IFERROR(VLOOKUP(A29,'Especificação Novos Req. LT (2'!A:A,1,FALSE),"")=A29,"Sim","Não") -> Não | AP29: =+IF(IFERROR(VLOOKUP(A29,Ficheiros!T:T,1,FALSE),"")=A29,"Sim","Não") -> Sim | AQ29: =+VLOOKUP(A29,Ficheiros!O:P,2,FALSE) -> #N/A | AR29: =+VLOOKUP(A29,Ficheiros!T:U,2,FALSE) -> 3. Pendente de decisão | AS29: =+VLOOKUP(A29,Ficheiros!T:V,3,FALSE) -> LF
A30: =+C30&G30 -> ENTITYDT_EXTRNL_RTNG | B30: EN.022 | C30: ENTITY | D30: Classification | E30: N | F30: DT_EXTRNL_RTNG | G30: DT_EXTRNL_RTNG | H30: Y | I30: Y | J30: Y | K30: Y | L30: Y | M30: Y | N30: N | R30: DATE | S30: YYYY-MM-DD | T30: 0000-00-00 | U30: 1111-11-11 | V30: 1111-11-11 | W30: Date of external rating | X30: Date of the most recent external rating, i.e. applicable at the reference date. | Y30: Yes - Equivalent | Z30: JM_CAL_EXT_CL - R9415_FECCALIF | AA30: - | AB30: Y | AC30: N | AD30: N | AE30: N | AF30: N | AG30: Y | AH30: N | AI30: N | AJ30: Y | AK30: =+IF(AND(AD30="N",AF30="N"),"Fora de âmbito", IF(AND(AD30="N",AF30="Y"),"Apenas ESG Risk", IF(AND(AD30="Y",AF30="N"),"Apenas Pilar 3", IF(AND(AD30="Y",AF30="Y"),"Comum","")))) -> Fora de âmbito | AL30: =+IF(IFERROR(VLOOKUP(A30,Ficheiros!I:I,1,FALSE),"")=A30,"Sim","Não") -> Sim | AM30: =+IF(IFERROR(VLOOKUP(A30,Ficheiros!E:E,1,FALSE),"")=A30,"Sim","Não") -> Não | AN30: =+IF(IFERROR(VLOOKUP(A30,Ficheiros!O:O,1,FALSE),"")=A30,"Sim","Não") -> Não | AO30: =+IF(IFERROR(VLOOKUP(A30,'Especificação Novos Req. LT (2'!A:A,1,FALSE),"")=A30,"Sim","Não") -> Não | AP30: =+IF(IFERROR(VLOOKUP(A30,Ficheiros!T:T,1,FALSE),"")=A30,"Sim","Não") -> Sim | AQ30: =+VLOOKUP(A30,Ficheiros!O:P,2,FALSE) -> #N/A | AR30: =+VLOOKUP(A30,Ficheiros!T:U,2,FALSE) -> 2. Alterar especificação | AS30: =+VLOOKUP(A30,Ficheiros!T:V,3,FALSE) -> LF
A31: =+C31&G31 -> ENTITYDT_INTRNL_RTNG | B31: EN.023 | C31: ENTITY | D31: Classification | E31: N | F31: DT_INTRNL_RTNG | G31: DT_INTRNL_RTNG | H31: Y | I31: Y | J31: Y | K31: Y | L31: Y | M31: Y | N31: Y | R31: DATE | S31: YYYY-MM-DD | T31: 0000-00-00 | U31: 1111-11-11 | V31: 1111-11-11 | W31: Date of internal rating | X31: Date of the most recent internal rating according to Regulation (EU) No 575/2013, i.e. applicable rating as at the reference date. If the rating is assigned on instrument level then provide the rating for the instrument with the highest EAD. | Y31: Yes - Equivalent | Z31: JM_CAL_IN_CL - E9954_FECCALI | AA31: - | AB31: Y | AC31: N | AD31: N | AE31: N | AF31: N | AG31: Y | AH31: N | AI31: N | AJ31: Y | AK31: =+IF(AND(AD31="N",AF31="N"),"Fora de âmbito", IF(AND(AD31="N",AF31="Y"),"Apenas ESG Risk", IF(AND(AD31="Y",AF31="N"),"Apenas Pilar 3", IF(AND(AD31="Y",AF31="Y"),"Comum","")))) -> Fora de âmbito | AL31: =+IF(IFERROR(VLOOKUP(A31,Ficheiros!I:I,1,FALSE),"")=A31,"Sim","Não") -> Sim | AM31: =+IF(IFERROR(VLOOKUP(A31,Ficheiros!E:E,1,FALSE),"")=A31,"Sim","Não") -> Não | AN31: =+IF(IFERROR(VLOOKUP(A31,Ficheiros!O:O,1,FALSE),"")=A31,"Sim","Não") -> Não | AO31: =+IF(IFERROR(VLOOKUP(A31,'Especificação Novos Req. LT (2'!A:A,1,FALSE),"")=A31,"Sim","Não") -> Não | AP31: =+IF(IFERROR(VLOOKUP(A31,Ficheiros!T:T,1,FALSE),"")=A31,"Sim","Não") -> Sim | AQ31: =+VLOOKUP(A31,Ficheiros!O:P,2,FALSE) -> #N/A | AR31: =+VLOOKUP(A31,Ficheiros!T:U,2,FALSE) -> 5.1 Em testes - Re-especificação | AS31: =+VLOOKUP(A31,Ficheiros!T:V,3,FALSE) -> LF
A32: =+C32&G32 -> ENTITYECNMC_ACTVTY | B32: EN.024 | C32: ENTITY | D32: Classification | E32: Y | F32: ECNMC_ACTVTY | G32: ECNMC_ACTVTY | H32: N | I32: Y | J32: Y | K32: Y | L32: Y | M32: Y | N32: N | R32: Code list | S32: Use codes from the code list sheet | T32: MISS | U32: N/A | V32: N/A | W32: Economic activity counterparty | X32: The level four NACE code in accordance with Regulation (EC) No 1893/2006 is generally reported. If the level four NACE code is not available it may be allowed to report a level three or level two NACE code. | Y32: Not applicable | Z32: N/A | AA32: - | AB32: Y | AC32: N | AD32: Y | AE32: Y | AF32: Y | AG32: Y | AH32: N | AI32: Y | AJ32: Y | AK32: =+IF(AND(AD32="N",AF32="N"),"Fora de âmbito", IF(AND(AD32="N",AF32="Y"),"Apenas ESG Risk", IF(AND(AD32="Y",AF32="N"),"Apenas Pilar 3", IF(AND(AD32="Y",AF32="Y"),"Comum","")))) -> Comum | AL32: =+IF(IFERROR(VLOOKUP(A32,Ficheiros!I:I,1,FALSE),"")=A32,"Sim","Não") -> Sim | AM32: =+IF(IFERROR(VLOOKUP(A32,Ficheiros!E:E,1,FALSE),"")=A32,"Sim","Não") -> Não | AN32: =+IF(IFERROR(VLOOKUP(A32,Ficheiros!O:O,1,FALSE),"")=A32,"Sim","Não") -> Sim | AO32: =+IF(IFERROR(VLOOKUP(A32,'Especificação Novos Req. LT (2'!A:A,1,FALSE),"")=A32,"Sim","Não") -> Não | AP32: =+IF(IFERROR(VLOOKUP(A32,Ficheiros!T:T,1,FALSE),"")=A32,"Sim","Não") -> Sim | AQ32: =+VLOOKUP(A32,Ficheiros!O:P,2,FALSE) -> 1. Concluído | AR32: =+VLOOKUP(A32,Ficheiros!T:U,2,FALSE) -> 9. Concluído | AS32: =+VLOOKUP(A32,Ficheiros!T:V,3,FALSE) -> PM
A33: =+C33&G33 -> ENTITYEMPLYMNT_STTS_INTRNL | B33: EN.025 | C33: ENTITY | D33: Classification | E33: N | F33: EMPLYMNT_STTS_INTRNL | G33: EMPLYMNT_STTS_INTRNL | H33: N | I33: N | J33: N | K33: N | L33: N | M33: N | N33: Y | R33: VARCHAR2(255) | S33: Free (latin) text without special characters (semicolon, quotes, …) | T33: MISS | U33: N/A | V33: N/A | W33: Employment status according to bank-internal classification | X33: Employment status according to bank-internal classification. | Y33: Not applicable | Z33: N/A | AA33: - | AB33: Y | AC33: N | AD33: N | AE33: N | AF33: N | AG33: N | AH33: N | AI33: N | AJ33: Y | AK33: =+IF(AND(AD33="N",AF33="N"),"Fora de âmbito", IF(AND(AD33="N",AF33="Y"),"Apenas ESG Risk", IF(AND(AD33="Y",AF33="N"),"Apenas Pilar 3", IF(AND(AD33="Y",AF33="Y"),"Comum","")))) -> Fora de âmbito | AL33: =+IF(IFERROR(VLOOKUP(A33,Ficheiros!I:I,1,FALSE),"")=A33,"Sim","Não") -> Sim | AM33: =+IF(IFERROR(VLOOKUP(A33,Ficheiros!E:E,1,FALSE),"")=A33,"Sim","Não") -> Não | AN33: =+IF(IFERROR(VLOOKUP(A33,Ficheiros!O:O,1,FALSE),"")=A33,"Sim","Não") -> Não | AO33: =+IF(IFERROR(VLOOKUP(A33,'Especificação Novos Req. LT (2'!A:A,1,FALSE),"")=A33,"Sim","Não") -> Não | AP33: =+IF(IFERROR(VLOOKUP(A33,Ficheiros!T:T,1,FALSE),"")=A33,"Sim","Não") -> Sim | AQ33: =+VLOOKUP(A33,Ficheiros!O:P,2,FALSE) -> #N/A | AR33: =+VLOOKUP(A33,Ficheiros!T:U,2,FALSE) -> 9. Concluído | AS33: =+VLOOKUP(A33,Ficheiros!T:V,3,FALSE) -> PM
A34: =+C34&G34 -> ENTITYEMPLYMNT_STTS | B34: EN.026 | C34: ENTITY | D34: Classification | E34: N | F34: EMPLYMNT_STTS | G34: EMPLYMNT_STTS | H34: N | I34: N | J34: N | K34: N | L34: N | M34: N | N34: Y | R34: Code List | S34: Use codes from the code list sheet | T34: 99999999999 | U34: 11111111111 | V34: 11111111111 | W34: Employment status (Code List) | X34: Employment status. | Y34: Not applicable | Z34: N/A | AA34: - | AB34: Y | AC34: N | AD34: N | AE34: N | AF34: N | AG34: N | AH34: N | AI34: N | AJ34: Y | AK34: =+IF(AND(AD34="N",AF34="N"),"Fora de âmbito", IF(AND(AD34="N",AF34="Y"),"Apenas ESG Risk", IF(AND(AD34="Y",AF34="N"),"Apenas Pilar 3", IF(AND(AD34="Y",AF34="Y"),"Comum","")))) -> Fora de âmbito | AL34: =+IF(IFERROR(VLOOKUP(A34,Ficheiros!I:I,1,FALSE),"")=A34,"Sim","Não") -> Sim | AM34: =+IF(IFERROR(VLOOKUP(A34,Ficheiros!E:E,1,FALSE),"")=A34,"Sim","Não") -> Não | AN34: =+IF(IFERROR(VLOOKUP(A34,Ficheiros!O:O,1,FALSE),"")=A34,"Sim","Não") -> Não | AO34: =+IF(IFERROR(VLOOKUP(A34,'Especificação Novos Req. LT (2'!A:A,1,FALSE),"")=A34,"Sim","Não") -> Não | AP34: =+IF(IFERROR(VLOOKUP(A34,Ficheiros!T:T,1,FALSE),"")=A34,"Sim","Não") -> Sim | AQ34: =+VLOOKUP(A34,Ficheiros!O:P,2,FALSE) -> #N/A | AR34: =+VLOOKUP(A34,Ficheiros!T:U,2,FALSE) -> 9. Concluído | AS34: =+VLOOKUP(A34,Ficheiros!T:V,3,FALSE) -> PM
A35: =+C35&G35 -> ENTITYENTRPRS_SZ_LE | B35: EN.027 | C35: ENTITY | D35: Classification | E35: Y | F35: ENTRPRS_SZ_LE | G35: ENTRPRS_SZ_LE | H35: N | I35: N | J35: N | K35: N | L35: N | M35: Y | N35: N | R35: Code List | S35: Use codes from the code list sheet | T35: 99999999999 | U35: 11111111111 | V35: 11111111111 | W35: Enterprise size Counterparty (LE) | X35: Enterprise size counterparty (LE). Classification of enterprises by size, in accordance with the Annex to Commission Recommendation 2003/361/EC. However, if the local NCB decides not to request this attribute as part of the AnaC reporting data set then please report "Not applicable". | Y35: Yes - Computed | Z35: IF ((G5508_NUM_EMPL IS <250 AND >=50) AND ((G5508_IMPFACTM <=50MM) OR (G5508_TOT_ACTI<=43MM))) THEN 2; ELSE IF ((G5508_NUM_EMPL IS <50 AND >=10) AND ((G5508_IMPFACTM <=10MM) OR (G5508_TOT_ACTI<=10MM))) THEN 3; ELSE IF ((G5508_NUM_EMPL IS <10) AND ((G5508_IMPFACTM <=2MM) OR (G5508_TOT_ACTI<=2MM))) THEN 4; ELSE 1 | AA35: - | AB35: Y | AC35: N | AD35: N | AE35: N | AF35: N | AG35: N | AH35: N | AI35: N | AJ35: Y | AK35: =+IF(AND(AD35="N",AF35="N"),"Fora de âmbito", IF(AND(AD35="N",AF35="Y"),"Apenas ESG Risk", IF(AND(AD35="Y",AF35="N"),"Apenas Pilar 3", IF(AND(AD35="Y",AF35="Y"),"Comum","")))) -> Fora de âmbito | AL35: =+IF(IFERROR(VLOOKUP(A35,Ficheiros!I:I,1,FALSE),"")=A35,"Sim","Não") -> Sim | AM35: =+IF(IFERROR(VLOOKUP(A35,Ficheiros!E:E,1,FALSE),"")=A35,"Sim","Não") -> Não | AN35: =+IF(IFERROR(VLOOKUP(A35,Ficheiros!O:O,1,FALSE),"")=A35,"Sim","Não") -> Não | AO35: =+IF(IFERROR(VLOOKUP(A35,'Especificação Novos Req. LT (2'!A:A,1,FALSE),"")=A35,"Sim","Não") -> Não | AP35: =+IF(IFERROR(VLOOKUP(A35,Ficheiros!T:T,1,FALSE),"")=A35,"Sim","Não") -> Sim | AQ35: =+VLOOKUP(A35,Ficheiros!O:P,2,FALSE) -> #N/A | AR35: =+VLOOKUP(A35,Ficheiros!T:U,2,FALSE) -> 7. Analisar controlos e completude | AS35: =+VLOOKUP(A35,Ficheiros!T:V,3,FALSE) -> PM
A36: =+C36&G36 -> ENTITYEXTRNL_RTNG | B36: EN.028 | C36: ENTITY | D36: Classification | E36: N | F36: EXTRNL_RTNG | G36: EXTRNL_RTNG | H36: Y | I36: Y | J36: Y | K36: Y | L36: Y | M36: Y | N36: N | R36: Code List | S36: Use codes from the code list sheet | T36: 99999999999 | U36: 11111111111 | V36: 11111111111 | W36: External rating | X36: External rating at the reference date. | Y36: Yes - Computed | Z36: R9415_CALIFMAE following the conditions: 1) In those cases in which more than one ECAI provides an external rating: - Where two credit assessments are available from nominated ECAIs and the two correspond to different risk weights for a rated item, the higher risk weight shall be assigned - Where more than two credit assessments are available from nominated ECAIs for a rated item, the two assessments generating the two lowest risk weights shall be referred to. If the two lowest risk weights are different, the higher risk weight shall be assigned. If the two lowest risk weights are the same, that risk weight shall be assigned 2) If the rating is not available, the unit should report “99999999999” in the Loan Tape. In case, for example, of exposures calculated under the IRB approach, where the external rating does not apply, the expected value is “11111111111” 3) If the client was not part of any applicable portfolio in the prior year, the value informed should be “11111111111”, as not applicable | AA36: - | AB36: Y | AC36: N | AD36: N | AE36: N | AF36: N | AG36: Y | AH36: N | AI36: N | AJ36: Y | AK36: =+IF(AND(AD36="N",AF36="N"),"Fora de âmbito", IF(AND(AD36="N",AF36="Y"),"Apenas ESG Risk", IF(AND(AD36="Y",AF36="N"),"Apenas Pilar 3", IF(AND(AD36="Y",AF36="Y"),"Comum","")))) -> Fora de âmbito | AL36: =+IF(IFERROR(VLOOKUP(A36,Ficheiros!I:I,1,FALSE),"")=A36,"Sim","Não") -> Sim | AM36: =+IF(IFERROR(VLOOKUP(A36,Ficheiros!E:E,1,FALSE),"")=A36,"Sim","Não") -> Não | AN36: =+IF(IFERROR(VLOOKUP(A36,Ficheiros!O:O,1,FALSE),"")=A36,"Sim","Não") -> Não | AO36: =+IF(IFERROR(VLOOKUP(A36,'Especificação Novos Req. LT (2'!A:A,1,FALSE),"")=A36,"Sim","Não") -> Não | AP36: =+IF(IFERROR(VLOOKUP(A36,Ficheiros!T:T,1,FALSE),"")=A36,"Sim","Não") -> Sim | AQ36: =+VLOOKUP(A36,Ficheiros!O:P,2,FALSE) -> #N/A | AR36: =+VLOOKUP(A36,Ficheiros!T:U,2,FALSE) -> 2. Alterar especificação | AS36: =+VLOOKUP(A36,Ficheiros!T:V,3,FALSE) -> LF
A37: =+C37&G37 -> ENTITYEXTRNL_RTNG_PRVS | B37: EN.029 | C37: ENTITY | D37: Classification | E37: N | F37: EXTRNL_RTNG_PRVS | G37: EXTRNL_RTNG_PRVS | H37: Y | I37: Y | J37: Y | K37: Y | L37: Y | M37: Y | N37: N | R37: Code List | S37: Use codes from the code list sheet | T37: 99999999999 | U37: 11111111111 | V37: 11111111111 | W37: External rating T-1 | X37: External rating one year prior to the reference date. | Y37: Yes - Computed | Z37: R9415_CALIFMAE having R9415_CALIFMAE one year prior to the reference date and following the conditions: 1) In those cases in which more than one ECAI provides an external rating: - Where two credit assessments are available from nominated ECAIs and the two correspond to different risk weights for a rated item, the higher risk weight shall be assigned - Where more than two credit assessments are available from nominated ECAIs for a rated item, the two assessments generating the two lowest risk weights shall be referred to. If the two lowest risk weights are different, the higher risk weight shall be assigned. If the two lowest risk weights are the same, that risk weight shall be assigned 2) If the rating is not available, the unit should report “99999999999” in the Loan Tape. In case, for example, of exposures calculated under the IRB approach, where the external rating does not apply, the expected value is “11111111111” 3) If the client was not part of any applicable portfolio in the prior year, the value informed should be “11111111111”, as not applicable | AA37: - | AB37: Y | AC37: N | AD37: N | AE37: N | AF37: N | AG37: Y | AH37: N | AI37: N | AJ37: Y | AK37: =+IF(AND(AD37="N",AF37="N"),"Fora de âmbito", IF(AND(AD37="N",AF37="Y"),"Apenas ESG Risk", IF(AND(AD37="Y",AF37="N"),"Apenas Pilar 3", IF(AND(AD37="Y",AF37="Y"),"Comum","")))) -> Fora de âmbito | AL37: =+IF(IFERROR(VLOOKUP(A37,Ficheiros!I:I,1,FALSE),"")=A37,"Sim","Não") -> Sim | AM37: =+IF(IFERROR(VLOOKUP(A37,Ficheiros!E:E,1,FALSE),"")=A37,"Sim","Não") -> Não | AN37: =+IF(IFERROR(VLOOKUP(A37,Ficheiros!O:O,1,FALSE),"")=A37,"Sim","Não") -> Não | AO37: =+IF(IFERROR(VLOOKUP(A37,'Especificação Novos Req. LT (2'!A:A,1,FALSE),"")=A37,"Sim","Não") -> Não | AP37: =+IF(IFERROR(VLOOKUP(A37,Ficheiros!T:T,1,FALSE),"")=A37,"Sim","Não") -> Sim | AQ37: =+VLOOKUP(A37,Ficheiros!O:P,2,FALSE) -> #N/A | AR37: =+VLOOKUP(A37,Ficheiros!T:U,2,FALSE) -> 2. Alterar especificação | AS37: =+VLOOKUP(A37,Ficheiros!T:V,3,FALSE) -> LF
A38: =+C38&G38 -> ENTITYFLG_BNKRPTCY_IN_GRP | B38: EN.030 | C38: ENTITY | D38: Classification | E38: N | F38: FLG_BNKRPTCY_IN_GRP | G38: FLG_BNKRPTCY_IN_GRP | H38: N | I38: Y | J38: Y | K38: Y | L38: Y | M38: Y | N38: N | R38: Y, N | S38: Boolean: Y/N | T38: MISS | U38: N/A | V38: N/A | W38: Any legal entity within the group of connected clients of the debtor (incl. subsidiaries of the debtor) has filed bankruptcy application | X38: Report "Y' if any legal entity within the group of connected clients of the debtor (incl. subsidiaries of the debtor) has filed bankruptcy application according to local insolvency law. | Y38: Yes - Computed | Z38: IF G4093_UTP_CLI = 00001 for any of the related clientes (necessary to identify the Group of the cliente (E1963_GRUP_ECO) and then all the connected clients (E1963_IDNUMCLI) for this Group) THEN Y; ELSE N | AA38: - | AB38: Y | AC38: N | AD38: N | AE38: N | AF38: N | AG38: N | AH38: N | AI38: N | AJ38: Y | AK38: =+IF(AND(AD38="N",AF38="N"),"Fora de âmbito", IF(AND(AD38="N",AF38="Y"),"Apenas ESG Risk", IF(AND(AD38="Y",AF38="N"),"Apenas Pilar 3", IF(AND(AD38="Y",AF38="Y"),"Comum","")))) -> Fora de âmbito | AL38: =+IF(IFERROR(VLOOKUP(A38,Ficheiros!I:I,1,FALSE),"")=A38,"Sim","Não") -> Sim | AM38: =+IF(IFERROR(VLOOKUP(A38,Ficheiros!E:E,1,FALSE),"")=A38,"Sim","Não") -> Não | AN38: =+IF(IFERROR(VLOOKUP(A38,Ficheiros!O:O,1,FALSE),"")=A38,"Sim","Não") -> Não | AO38: =+IF(IFERROR(VLOOKUP(A38,'Especificação Novos Req. LT (2'!A:A,1,FALSE),"")=A38,"Sim","Não") -> Não | AP38: =+IF(IFERROR(VLOOKUP(A38,Ficheiros!T:T,1,FALSE),"")=A38,"Sim","Não") -> Sim | AQ38: =+VLOOKUP(A38,Ficheiros!O:P,2,FALSE) -> #N/A | AR38: =+VLOOKUP(A38,Ficheiros!T:U,2,FALSE) -> 9. Concluído | AS38: =+VLOOKUP(A38,Ficheiros!T:V,3,FALSE) -> PM
A39: =+C39&G39 -> ENTITYFLG_HGH_CDS | B39: EN.031 | C39: ENTITY | D39: Classification | E39: N | F39: FLG_HGH_CDS | G39: FLG_HGH_CDS | H39: Y | I39: Y | J39: Y | K39: Y | L39: Y | M39: Y | N39: N | R39: Y, N | S39: Boolean: Y/N | T39: MISS | U39: N/A | V39: N/A | W39: 5Y CDS > 1,000bps over the last 12 months | X39: Report "Y" if 5Y CDS > 1,000bps over the last 12 months. The flag would be required to be reported "Y" if the 5y CDS spread of a debtor is at least once greater or equal 1000bps within the last 12 months. | Y39: Not applicable | Z39: N/A | AA39: - | AB39: Y | AC39: N | AD39: N | AE39: N | AF39: N | AG39: N | AH39: N | AI39: N | AJ39: Y | AK39: =+IF(AND(AD39="N",AF39="N"),"Fora de âmbito", IF(AND(AD39="N",AF39="Y"),"Apenas ESG Risk", IF(AND(AD39="Y",AF39="N"),"Apenas Pilar 3", IF(AND(AD39="Y",AF39="Y"),"Comum","")))) -> Fora de âmbito | AL39: =+IF(IFERROR(VLOOKUP(A39,Ficheiros!I:I,1,FALSE),"")=A39,"Sim","Não") -> Sim | AM39: =+IF(IFERROR(VLOOKUP(A39,Ficheiros!E:E,1,FALSE),"")=A39,"Sim","Não") -> Não | AN39: =+IF(IFERROR(VLOOKUP(A39,Ficheiros!O:O,1,FALSE),"")=A39,"Sim","Não") -> Não | AO39: =+IF(IFERROR(VLOOKUP(A39,'Especificação Novos Req. LT (2'!A:A,1,FALSE),"")=A39,"Sim","Não") -> Não | AP39: =+IF(IFERROR(VLOOKUP(A39,Ficheiros!T:T,1,FALSE),"")=A39,"Sim","Não") -> Sim | AQ39: =+VLOOKUP(A39,Ficheiros!O:P,2,FALSE) -> #N/A | AR39: =+VLOOKUP(A39,Ficheiros!T:U,2,FALSE) -> 9. Concluído | AS39: =+VLOOKUP(A39,Ficheiros!T:V,3,FALSE) -> PM
A40: =+C40&G40 -> ENTITYFLG_ISDA_CRDT_EVNT | B40: EN.032 | C40: ENTITY | D40: Classification | E40: N | F40: FLG_ISDA_CRDT_EVNT | G40: FLG_ISDA_CRDT_EVNT | H40: Y | I40: Y | J40: Y | K40: Y | L40: Y | M40: Y | N40: N | R40: Y, N | S40: Boolean: Y/N | T40: MISS | U40: N/A | V40: N/A | W40: ISDA credit event declared | X40: The flag would be required to be reported "Y" if a credit event occurred under any ISDA master agreement associated with this debtor. | Y40: Not applicable | Z40: N/A | AA40: - | AB40: Y | AC40: N | AD40: N | AE40: N | AF40: N | AG40: N | AH40: N | AI40: N | AJ40: Y | AK40: =+IF(AND(AD40="N",AF40="N"),"Fora de âmbito", IF(AND(AD40="N",AF40="Y"),"Apenas ESG Risk", IF(AND(AD40="Y",AF40="N"),"Apenas Pilar 3", IF(AND(AD40="Y",AF40="Y"),"Comum","")))) -> Fora de âmbito | AL40: =+IF(IFERROR(VLOOKUP(A40,Ficheiros!I:I,1,FALSE),"")=A40,"Sim","Não") -> Sim | AM40: =+IF(IFERROR(VLOOKUP(A40,Ficheiros!E:E,1,FALSE),"")=A40,"Sim","Não") -> Não | AN40: =+IF(IFERROR(VLOOKUP(A40,Ficheiros!O:O,1,FALSE),"")=A40,"Sim","Não") -> Não | AO40: =+IF(IFERROR(VLOOKUP(A40,'Especificação Novos Req. LT (2'!A:A,1,FALSE),"")=A40,"Sim","Não") -> Não | AP40: =+IF(IFERROR(VLOOKUP(A40,Ficheiros!T:T,1,FALSE),"")=A40,"Sim","Não") -> Sim | AQ40: =+VLOOKUP(A40,Ficheiros!O:P,2,FALSE) -> #N/A | AR40: =+VLOOKUP(A40,Ficheiros!T:U,2,FALSE) -> 9. Concluído | AS40: =+VLOOKUP(A40,Ficheiros!T:V,3,FALSE) -> PM
A41: =+C41&G41 -> ENTITYFLG_NN_ACCRL | B41: EN.033 | C41: ENTITY | D41: Classification | E41: N | F41: FLG_NN_ACCRL | G41: FLG_NN_ACCRL | H41: N | I41: N | J41: N | K41: N | L41: N | M41: Y | N41: Y | R41: Y, N | S41: Boolean: Y/N | T41: MISS | U41: N/A | V41: N/A | W41: Credit obligation on non-accrual status | X41: Report "Y" if any credit obligation associated to this debtor is set on non-accrual status. | Y41: Not applicable | Z41: N/A | AA41: - | AB41: Y | AC41: N | AD41: N | AE41: N | AF41: N | AG41: N | AH41: N | AI41: N | AJ41: Y | AK41: =+IF(AND(AD41="N",AF41="N"),"Fora de âmbito", IF(AND(AD41="N",AF41="Y"),"Apenas ESG Risk", IF(AND(AD41="Y",AF41="N"),"Apenas Pilar 3", IF(AND(AD41="Y",AF41="Y"),"Comum","")))) -> Fora de âmbito | AL41: =+IF(IFERROR(VLOOKUP(A41,Ficheiros!I:I,1,FALSE),"")=A41,"Sim","Não") -> Sim | AM41: =+IF(IFERROR(VLOOKUP(A41,Ficheiros!E:E,1,FALSE),"")=A41,"Sim","Não") -> Não | AN41: =+IF(IFERROR(VLOOKUP(A41,Ficheiros!O:O,1,FALSE),"")=A41,"Sim","Não") -> Não | AO41: =+IF(IFERROR(VLOOKUP(A41,'Especificação Novos Req. LT (2'!A:A,1,FALSE),"")=A41,"Sim","Não") -> Não | AP41: =+IF(IFERROR(VLOOKUP(A41,Ficheiros!T:T,1,FALSE),"")=A41,"Sim","Não") -> Sim | AQ41: =+VLOOKUP(A41,Ficheiros!O:P,2,FALSE) -> #N/A | AR41: =+VLOOKUP(A41,Ficheiros!T:U,2,FALSE) -> 9. Concluído | AS41: =+VLOOKUP(A41,Ficheiros!T:V,3,FALSE) -> PM
A42: =+C42&G42 -> ENTITYFLG_RQST_BNKRPTCY | B42: EN.034 | C42: ENTITY | D42: Classification | E42: N | F42: FLG_RQST_BNKRPTCY | G42: FLG_RQST_BNKRPTCY | H42: N | I42: Y | J42: Y | K42: Y | L42: Y | M42: Y | N42: N | R42: Y, N | S42: Boolean: Y/N | T42: MISS | U42: N/A | V42: N/A | W42: Request by the institution for the obligor's bankruptcy | X42: Flag "Y" if bankruptcy proceedings have been initiated by the bank according to local insolvency law, e.g. due to illiquidity, over-indebtedness. | Y42: Not applicable | Z42: N/A | AA42: - | AB42: Y | AC42: N | AD42: N | AE42: N | AF42: N | AG42: N | AH42: N | AI42: N | AJ42: Y | AK42: =+IF(AND(AD42="N",AF42="N"),"Fora de âmbito", IF(AND(AD42="N",AF42="Y"),"Apenas ESG Risk", IF(AND(AD42="Y",AF42="N"),"Apenas Pilar 3", IF(AND(AD42="Y",AF42="Y"),"Comum","")))) -> Fora de âmbito | AL42: =+IF(IFERROR(VLOOKUP(A42,Ficheiros!I:I,1,FALSE),"")=A42,"Sim","Não") -> Sim | AM42: =+IF(IFERROR(VLOOKUP(A42,Ficheiros!E:E,1,FALSE),"")=A42,"Sim","Não") -> Não | AN42: =+IF(IFERROR(VLOOKUP(A42,Ficheiros!O:O,1,FALSE),"")=A42,"Sim","Não") -> Não | AO42: =+IF(IFERROR(VLOOKUP(A42,'Especificação Novos Req. LT (2'!A:A,1,FALSE),"")=A42,"Sim","Não") -> Não | AP42: =+IF(IFERROR(VLOOKUP(A42,Ficheiros!T:T,1,FALSE),"")=A42,"Sim","Não") -> Sim | AQ42: =+VLOOKUP(A42,Ficheiros!O:P,2,FALSE) -> #N/A | AR42: =+VLOOKUP(A42,Ficheiros!T:U,2,FALSE) -> 9. Concluído | AS42: =+VLOOKUP(A42,Ficheiros!T:V,3,FALSE) -> PM
A43: =+C43&G43 -> ENTITYFLG_RQST_DSTRSSD_RSTRCTRNG | B43: EN.035 | C43: ENTITY | D43: Classification | E43: N | F43: FLG_RQST_DSTRSSD_RSTRCTRNG | G43: FLG_RQST_DSTRSSD_RSTRCTRNG | H43: N | I43: N | J43: N | K43: N | L43: N | M43: Y | N43: Y | R43: Y, N | S43: Boolean: Y/N | T43: MISS | U43: N/A | V43: N/A | W43: Request for current concession of forbearance measures as defined in EBA/ITS/2013/03 resulting in distressed restructuring of the credit obligation | X43: Report "Y" if there is a request for current concession of forbearance measures as defined in EBA/ITS/2013/03 resulting in distressed restructuring of the credit obligation. | Y43: Not applicable | Z43: N/A | AA43: - | AB43: Y | AC43: N | AD43: N | AE43: N | AF43: N | AG43: N | AH43: N | AI43: N | AJ43: Y | AK43: =+IF(AND(AD43="N",AF43="N"),"Fora de âmbito", IF(AND(AD43="N",AF43="Y"),"Apenas ESG Risk", IF(AND(AD43="Y",AF43="N"),"Apenas Pilar 3", IF(AND(AD43="Y",AF43="Y"),"Comum","")))) -> Fora de âmbito | AL43: =+IF(IFERROR(VLOOKUP(A43,Ficheiros!I:I,1,FALSE),"")=A43,"Sim","Não") -> Sim | AM43: =+IF(IFERROR(VLOOKUP(A43,Ficheiros!E:E,1,FALSE),"")=A43,"Sim","Não") -> Não | AN43: =+IF(IFERROR(VLOOKUP(A43,Ficheiros!O:O,1,FALSE),"")=A43,"Sim","Não") -> Não | AO43: =+IF(IFERROR(VLOOKUP(A43,'Especificação Novos Req. LT (2'!A:A,1,FALSE),"")=A43,"Sim","Não") -> Não | AP43: =+IF(IFERROR(VLOOKUP(A43,Ficheiros!T:T,1,FALSE),"")=A43,"Sim","Não") -> Sim | AQ43: =+VLOOKUP(A43,Ficheiros!O:P,2,FALSE) -> #N/A | AR43: =+VLOOKUP(A43,Ficheiros!T:U,2,FALSE) -> 1. Especificar | AS43: =+VLOOKUP(A43,Ficheiros!T:V,3,FALSE) -> PM
A44: =+C44&G44 -> ENTITYFLG_RQST_EMRGNCY_FNDNG | B44: EN.036 | C44: ENTITY | D44: Classification | E44: N | F44: FLG_RQST_EMRGNCY_FNDNG | G44: FLG_RQST_EMRGNCY_FNDNG | H44: N | I44: N | J44: N | K44: N | L44: Y | M44: Y | N44: Y | R44: Y, N | S44: Boolean: Y/N | T44: MISS | U44: Default value not allowed | V44: N/A | W44: Request by the debtor for emergency funding from the bank | X44: Report "Y" if there is a request by the debtor for emergency funding from the bank. | Y44: Not applicable | Z44: N/A | AA44: - | AB44: Y | AC44: N | AD44: N | AE44: N | AF44: N | AG44: Y | AH44: N | AI44: N | AJ44: Y | AK44: =+IF(AND(AD44="N",AF44="N"),"Fora de âmbito", IF(AND(AD44="N",AF44="Y"),"Apenas ESG Risk", IF(AND(AD44="Y",AF44="N"),"Apenas Pilar 3", IF(AND(AD44="Y",AF44="Y"),"Comum","")))) -> Fora de âmbito | AL44: =+IF(IFERROR(VLOOKUP(A44,Ficheiros!I:I,1,FALSE),"")=A44,"Sim","Não") -> Sim | AM44: =+IF(IFERROR(VLOOKUP(A44,Ficheiros!E:E,1,FALSE),"")=A44,"Sim","Não") -> Não | AN44: =+IF(IFERROR(VLOOKUP(A44,Ficheiros!O:O,1,FALSE),"")=A44,"Sim","Não") -> Não | AO44: =+IF(IFERROR(VLOOKUP(A44,'Especificação Novos Req. LT (2'!A:A,1,FALSE),"")=A44,"Sim","Não") -> Não | AP44: =+IF(IFERROR(VLOOKUP(A44,Ficheiros!T:T,1,FALSE),"")=A44,"Sim","Não") -> Sim | AQ44: =+VLOOKUP(A44,Ficheiros!O:P,2,FALSE) -> #N/A | AR44: =+VLOOKUP(A44,Ficheiros!T:U,2,FALSE) -> 9. Concluído | AS44: =+VLOOKUP(A44,Ficheiros!T:V,3,FALSE) -> PM
A45: =+C45&G45 -> ENTITYFLG_SLL_WTH_LSS | B45: EN.037 | C45: ENTITY | D45: Classification | E45: N | F45: FLG_SLL_WTH_LSS | G45: FLG_SLL_WTH_LSS | H45: N | I45: Y | J45: Y | K45: Y | L45: Y | M45: Y | N45: N | R45: Y, N | S45: Boolean: Y/N | T45: MISS | U45: N/A | V45: N/A | W45: Sell of a credit obligation with material credit related economic loss (>= 5%) | X45: Report "Y" if there is a sell of a credit obligation with material credit related economic loss (>= 5%) according to EBA/GL/2016/07 para 44. | Y45: Yes - Computed | Z45: IF T2437_SITGESND = 23 THEN Y; ELSE N | AA45: - | AB45: Y | AC45: N | AD45: N | AE45: N | AF45: N | AG45: N | AH45: N | AI45: N | AJ45: Y | AK45: =+IF(AND(AD45="N",AF45="N"),"Fora de âmbito", IF(AND(AD45="N",AF45="Y"),"Apenas ESG Risk", IF(AND(AD45="Y",AF45="N"),"Apenas Pilar 3", IF(AND(AD45="Y",AF45="Y"),"Comum","")))) -> Fora de âmbito | AL45: =+IF(IFERROR(VLOOKUP(A45,Ficheiros!I:I,1,FALSE),"")=A45,"Sim","Não") -> Sim | AM45: =+IF(IFERROR(VLOOKUP(A45,Ficheiros!E:E,1,FALSE),"")=A45,"Sim","Não") -> Não | AN45: =+IF(IFERROR(VLOOKUP(A45,Ficheiros!O:O,1,FALSE),"")=A45,"Sim","Não") -> Não | AO45: =+IF(IFERROR(VLOOKUP(A45,'Especificação Novos Req. LT (2'!A:A,1,FALSE),"")=A45,"Sim","Não") -> Não | AP45: =+IF(IFERROR(VLOOKUP(A45,Ficheiros!T:T,1,FALSE),"")=A45,"Sim","Não") -> Sim | AQ45: =+VLOOKUP(A45,Ficheiros!O:P,2,FALSE) -> #N/A | AR45: =+VLOOKUP(A45,Ficheiros!T:U,2,FALSE) -> 9. Concluído | AS45: =+VLOOKUP(A45,Ficheiros!T:V,3,FALSE) -> PM
A46: =+C46&G46 -> ENTITYINCM_SC | B46: EN.038 | C46: ENTITY | D46: Classification | E46: N | F46: INCM_SC | G46: INCM_SC | H46: N | I46: N | J46: N | K46: N | L46: N | M46: N | N46: Y | R46: Y, N | S46: Boolean: Y/N | T46: MISS | U46: N/A | V46: N/A | W46: Income self-certified | X46: The data field applicable to natural persons only should be flagged "Y" if the counterpart has no other source of income certification than its own personal declaration, e.g. absence of payroll or tax declaration forms. | Y46: Yes - Computed | Z46: IF H0780_INGCLIEN is informed and H0780_FLGACSLD = 1 THEN Y; ELSE N | AA46: - | AB46: Y | AC46: N | AD46: N | AE46: N | AF46: N | AG46: N | AH46: N | AI46: N | AJ46: Y | AK46: =+IF(AND(AD46="N",AF46="N"),"Fora de âmbito", IF(AND(AD46="N",AF46="Y"),"Apenas ESG Risk", IF(AND(AD46="Y",AF46="N"),"Apenas Pilar 3", IF(AND(AD46="Y",AF46="Y"),"Comum","")))) -> Fora de âmbito | AL46: =+IF(IFERROR(VLOOKUP(A46,Ficheiros!I:I,1,FALSE),"")=A46,"Sim","Não") -> Sim | AM46: =+IF(IFERROR(VLOOKUP(A46,Ficheiros!E:E,1,FALSE),"")=A46,"Sim","Não") -> Não | AN46: =+IF(IFERROR(VLOOKUP(A46,Ficheiros!O:O,1,FALSE),"")=A46,"Sim","Não") -> Não | AO46: =+IF(IFERROR(VLOOKUP(A46,'Especificação Novos Req. LT (2'!A:A,1,FALSE),"")=A46,"Sim","Não") -> Não | AP46: =+IF(IFERROR(VLOOKUP(A46,Ficheiros!T:T,1,FALSE),"")=A46,"Sim","Não") -> Sim | AQ46: =+VLOOKUP(A46,Ficheiros!O:P,2,FALSE) -> #N/A | AR46: =+VLOOKUP(A46,Ficheiros!T:U,2,FALSE) -> 1. Especificar | AS46: =+VLOOKUP(A46,Ficheiros!T:V,3,FALSE) -> PM
A47: =+C47&G47 -> ENTITYINTRNL_RTNG | B47: EN.039 | C47: ENTITY | D47: Classification | E47: N | F47: INTRNL_RTNG | G47: INTRNL_RTNG | H47: Y | I47: Y | J47: Y | K47: Y | L47: Y | M47: Y | N47: Y | R47: Code List | S47: Use codes from the code list sheet | T47: MISS | U47: N/A | V47: N/A | W47: Internal rating at reference date | X47: Internal rating at the reference date according to Regulation (EU) No 575/2013. Please also add in sheet "Code List" the list of values used, i.e. bank-internal masterscale. | Y47: Not applicable | Z47: N/A | AA47: - | AB47: Y | AC47: N | AD47: N | AE47: N | AF47: N | AG47: Y | AH47: N | AI47: N | AJ47: Y | AK47: =+IF(AND(AD47="N",AF47="N"),"Fora de âmbito", IF(AND(AD47="N",AF47="Y"),"Apenas ESG Risk", IF(AND(AD47="Y",AF47="N"),"Apenas Pilar 3", IF(AND(AD47="Y",AF47="Y"),"Comum","")))) -> Fora de âmbito | AL47: =+IF(IFERROR(VLOOKUP(A47,Ficheiros!I:I,1,FALSE),"")=A47,"Sim","Não") -> Sim | AM47: =+IF(IFERROR(VLOOKUP(A47,Ficheiros!E:E,1,FALSE),"")=A47,"Sim","Não") -> Não | AN47: =+IF(IFERROR(VLOOKUP(A47,Ficheiros!O:O,1,FALSE),"")=A47,"Sim","Não") -> Não | AO47: =+IF(IFERROR(VLOOKUP(A47,'Especificação Novos Req. LT (2'!A:A,1,FALSE),"")=A47,"Sim","Não") -> Não | AP47: =+IF(IFERROR(VLOOKUP(A47,Ficheiros!T:T,1,FALSE),"")=A47,"Sim","Não") -> Sim | AQ47: =+VLOOKUP(A47,Ficheiros!O:P,2,FALSE) -> #N/A | AR47: =+VLOOKUP(A47,Ficheiros!T:U,2,FALSE) -> 5.1 Em testes - Re-especificação | AS47: =+VLOOKUP(A47,Ficheiros!T:V,3,FALSE) -> LF
A48: =+C48&G48 -> ENTITYINTRNL_RTNG_PRVS | B48: EN.040 | C48: ENTITY | D48: Classification | E48: N | F48: INTRNL_RTNG_PRVS | G48: INTRNL_RTNG_PRVS | H48: Y | I48: Y | J48: Y | K48: Y | L48: Y | M48: Y | N48: Y | R48: Code List | S48: Use codes from the code list sheet | T48: MISS | U48: N/A | V48: N/A | W48: Previous internal rating | X48: Internal rating according to Regulation (EU) No 575/2013 one year prior to the reference date. | Y48: Not applicable | Z48: N/A | AA48: - | AB48: Y | AC48: N | AD48: N | AE48: N | AF48: N | AG48: Y | AH48: N | AI48: N | AJ48: Y | AK48: =+IF(AND(AD48="N",AF48="N"),"Fora de âmbito", IF(AND(AD48="N",AF48="Y"),"Apenas ESG Risk", IF(AND(AD48="Y",AF48="N"),"Apenas Pilar 3", IF(AND(AD48="Y",AF48="Y"),"Comum","")))) -> Fora de âmbito | AL48: =+IF(IFERROR(VLOOKUP(A48,Ficheiros!I:I,1,FALSE),"")=A48,"Sim","Não") -> Sim | AM48: =+IF(IFERROR(VLOOKUP(A48,Ficheiros!E:E,1,FALSE),"")=A48,"Sim","Não") -> Não | AN48: =+IF(IFERROR(VLOOKUP(A48,Ficheiros!O:O,1,FALSE),"")=A48,"Sim","Não") -> Não | AO48: =+IF(IFERROR(VLOOKUP(A48,'Especificação Novos Req. LT (2'!A:A,1,FALSE),"")=A48,"Sim","Não") -> Não | AP48: =+IF(IFERROR(VLOOKUP(A48,Ficheiros!T:T,1,FALSE),"")=A48,"Sim","Não") -> Sim | AQ48: =+VLOOKUP(A48,Ficheiros!O:P,2,FALSE) -> #N/A | AR48: =+VLOOKUP(A48,Ficheiros!T:U,2,FALSE) -> 5.1 Em testes - Re-especificação | AS48: =+VLOOKUP(A48,Ficheiros!T:V,3,FALSE) -> LF
A49: =+C49&G49 -> ENTITYLGL_PRCDNG_STTS_LE | B49: EN.041 | C49: ENTITY | D49: Classification | E49: Y | F49: LGL_PRCDNG_STTS_LE | G49: LGL_PRCDNG_STTS_LE | H49: Y | I49: Y | J49: Y | K49: Y | L49: Y | M49: Y | N49: Y | R49: Code List | S49: Use codes from the code list sheet | T49: 99999999999 | U49: Default value not allowed | V49: Default value not allowed | W49: Legal proceedings status Counterparty (LE) | X49: Legal proceedings status Counterparty (LE). Only for Retail portfolios: Status "No legal action taken" or "Other legal measures" are possible. Status "Other legal measures" is reported when the hard collection process was initiated at the level of a given entity or at the level of any associated instrument or protection of this entity. | Y49: Yes - Computed | Z49: IF T1824_GEST_SIT in (8) THEN LGL_PRCDNG_STTS = 2; ELSE IF G4093_UTP_CLI = 00001 THEN 3; ELSE 1 | AA49: - | AB49: Y | AC49: N | AD49: N | AE49: N | AF49: N | AG49: Y | AH49: N | AI49: N | AJ49: Y | AK49: =+IF(AND(AD49="N",AF49="N"),"Fora de âmbito", IF(AND(AD49="N",AF49="Y"),"Apenas ESG Risk", IF(AND(AD49="Y",AF49="N"),"Apenas Pilar 3", IF(AND(AD49="Y",AF49="Y"),"Comum","")))) -> Fora de âmbito | AL49: =+IF(IFERROR(VLOOKUP(A49,Ficheiros!I:I,1,FALSE),"")=A49,"Sim","Não") -> Sim | AM49: =+IF(IFERROR(VLOOKUP(A49,Ficheiros!E:E,1,FALSE),"")=A49,"Sim","Não") -> Não | AN49: =+IF(IFERROR(VLOOKUP(A49,Ficheiros!O:O,1,FALSE),"")=A49,"Sim","Não") -> Não | AO49: =+IF(IFERROR(VLOOKUP(A49,'Especificação Novos Req. LT (2'!A:A,1,FALSE),"")=A49,"Sim","Não") -> Não | AP49: =+IF(IFERROR(VLOOKUP(A49,Ficheiros!T:T,1,FALSE),"")=A49,"Sim","Não") -> Sim | AQ49: =+VLOOKUP(A49,Ficheiros!O:P,2,FALSE) -> #N/A | AR49: =+VLOOKUP(A49,Ficheiros!T:U,2,FALSE) -> 7. Analisar controlos e completude | AS49: =+VLOOKUP(A49,Ficheiros!T:V,3,FALSE) -> LF
A50: =+C50&G50 -> ENTITYOWND_BY_SPNSR | B50: EN.042 | C50: ENTITY | D50: Classification | E50: N | F50: OWND_BY_SPNSR | G50: OWND_BY_SPNSR | H50: N | I50: N | J50: N | K50: N | L50: Y | M50: Y | N50: N | R50: Y, N | S50: Boolean: Y/N | T50: MISS | U50: N/A | V50: N/A | W50: >50% owned by a sponsor as per ECB Guidance on leveraged transactions | X50: In accordance the ECB Guidance on Leveraged Transactions. As per point (37) of Article 4(1) of Regulation (EU) No 575/2013, a financial sponsor is deemed to be the owner if it controls or owns more than 50% of the borrower’s equity. The term “financial sponsor” refers to an investment firm that undertakes private equity investments in and/or leveraged buyouts of companies with the intention of exiting those investments on a mediumterm basis | Y50: Not applicable | Z50: N/A | AA50: - | AB50: Y | AC50: N | AD50: N | AE50: N | AF50: N | AG50: Y | AH50: N | AI50: N | AJ50: Y | AK50: =+IF(AND(AD50="N",AF50="N"),"Fora de âmbito", IF(AND(AD50="N",AF50="Y"),"Apenas ESG Risk", IF(AND(AD50="Y",AF50="N"),"Apenas Pilar 3", IF(AND(AD50="Y",AF50="Y"),"Comum","")))) -> Fora de âmbito | AL50: =+IF(IFERROR(VLOOKUP(A50,Ficheiros!I:I,1,FALSE),"")=A50,"Sim","Não") -> Sim | AM50: =+IF(IFERROR(VLOOKUP(A50,Ficheiros!E:E,1,FALSE),"")=A50,"Sim","Não") -> Não | AN50: =+IF(IFERROR(VLOOKUP(A50,Ficheiros!O:O,1,FALSE),"")=A50,"Sim","Não") -> Não | AO50: =+IF(IFERROR(VLOOKUP(A50,'Especificação Novos Req. LT (2'!A:A,1,FALSE),"")=A50,"Sim","Não") -> Não | AP50: =+IF(IFERROR(VLOOKUP(A50,Ficheiros!T:T,1,FALSE),"")=A50,"Sim","Não") -> Sim | AQ50: =+VLOOKUP(A50,Ficheiros!O:P,2,FALSE) -> #N/A | AR50: =+VLOOKUP(A50,Ficheiros!T:U,2,FALSE) -> 9. Concluído | AS50: =+VLOOKUP(A50,Ficheiros!T:V,3,FALSE) -> PM & LF
A51: =+C51&G51 -> ENTITYPRFRMNG_STTS_LE | B51: EN.043 | C51: ENTITY | D51: Classification | E51: N | F51: PRFRMNG_STTS_LE | G51: PRFRMNG_STTS_LE | H51: Y | I51: Y | J51: Y | K51: Y | L51: Y | M51: Y | N51: Y | R51: Code List | S51: Use codes from the code list sheet | T51: 99999999999 | U51: 11111111111 | V51: 11111111111 | W51: Performing status | X51: Performing status. Identification of the performing status of the counterparty. Categories describing the motives for which the counterparty can be non-performing in accordance with Implementing Technical Standard (ITS) on Supervisory Reporting (Forbearance and non-performing exposures). For retail only: If performing classification performed on instrument level then Entity is classified as non-performing when at least one instrument is classified as non-performing For corporate, SME, CRE and LF: if default classification performed on instrument level then entity level is "not applicable". | Y51: Not applicable | Z51: N/A | AA51: - | AB51: Y | AC51: N | AD51: N | AE51: N | AF51: N | AG51: Y | AH51: N | AI51: N | AJ51: Y | AK51: =+IF(AND(AD51="N",AF51="N"),"Fora de âmbito", IF(AND(AD51="N",AF51="Y"),"Apenas ESG Risk", IF(AND(AD51="Y",AF51="N"),"Apenas Pilar 3", IF(AND(AD51="Y",AF51="Y"),"Comum","")))) -> Fora de âmbito | AL51: =+IF(IFERROR(VLOOKUP(A51,Ficheiros!I:I,1,FALSE),"")=A51,"Sim","Não") -> Sim | AM51: =+IF(IFERROR(VLOOKUP(A51,Ficheiros!E:E,1,FALSE),"")=A51,"Sim","Não") -> Não | AN51: =+IF(IFERROR(VLOOKUP(A51,Ficheiros!O:O,1,FALSE),"")=A51,"Sim","Não") -> Não | AO51: =+IF(IFERROR(VLOOKUP(A51,'Especificação Novos Req. LT (2'!A:A,1,FALSE),"")=A51,"Sim","Não") -> Não | AP51: =+IF(IFERROR(VLOOKUP(A51,Ficheiros!T:T,1,FALSE),"")=A51,"Sim","Não") -> Sim | AQ51: =+VLOOKUP(A51,Ficheiros!O:P,2,FALSE) -> #N/A | AR51: =+VLOOKUP(A51,Ficheiros!T:U,2,FALSE) -> 9. Concluído | AS51: =+VLOOKUP(A51,Ficheiros!T:V,3,FALSE) -> PM
A52: =+C52&G52 -> ENTITYRTNG_MTHD | B52: EN.044 | C52: ENTITY | D52: Classification | E52: N | F52: RTNG_MTHD | G52: RTNG_MTHD | H52: Y | I52: Y | J52: Y | K52: Y | L52: Y | M52: Y | N52: Y | R52: Code List | S52: Use codes from the code list sheet | T52: 99999999999 | U52: 11111111111 | V52: 11111111111 | W52: Rating method | X52: Internal definition and name of the rating/scoring model. | Y52: Yes - Equivalent | Z52: JM_CAL_IN_CL - E9954_TIPMODEL | AA52: - | AB52: Y | AC52: N | AD52: N | AE52: N | AF52: N | AG52: Y | AH52: N | AI52: N | AJ52: Y | AK52: =+IF(AND(AD52="N",AF52="N"),"Fora de âmbito", IF(AND(AD52="N",AF52="Y"),"Apenas ESG Risk", IF(AND(AD52="Y",AF52="N"),"Apenas Pilar 3", IF(AND(AD52="Y",AF52="Y"),"Comum","")))) -> Fora de âmbito | AL52: =+IF(IFERROR(VLOOKUP(A52,Ficheiros!I:I,1,FALSE),"")=A52,"Sim","Não") -> Sim | AM52: =+IF(IFERROR(VLOOKUP(A52,Ficheiros!E:E,1,FALSE),"")=A52,"Sim","Não") -> Não | AN52: =+IF(IFERROR(VLOOKUP(A52,Ficheiros!O:O,1,FALSE),"")=A52,"Sim","Não") -> Não | AO52: =+IF(IFERROR(VLOOKUP(A52,'Especificação Novos Req. LT (2'!A:A,1,FALSE),"")=A52,"Sim","Não") -> Não | AP52: =+IF(IFERROR(VLOOKUP(A52,Ficheiros!T:T,1,FALSE),"")=A52,"Sim","Não") -> Sim | AQ52: =+VLOOKUP(A52,Ficheiros!O:P,2,FALSE) -> #N/A | AR52: =+VLOOKUP(A52,Ficheiros!T:U,2,FALSE) -> 5.1 Em testes - Re-especificação | AS52: =+VLOOKUP(A52,Ficheiros!T:V,3,FALSE) -> LF
A53: =+C53&G53 -> ENTITYRTNG_SCL | B53: EN.045 | C53: ENTITY | D53: Classification | E53: N | F53: RTNG_SCL | G53: RTNG_SCL | H53: Corporation | I53: Corporation | J53: Corporation | K53: Corporation | L53: Corporation | M53: Corporation | N53: Corporation | R53: Code List | S53: Use codes from the code list sheet | T53: 99999999999 | U53: 11111111111 | V53: 11111111111 | W53: Rating scale | X53: Internal name and definition of the rating master scale. It should be mapped to the assigned rating, i.e. INTRNL_RTNG. | Y53: Not applicable | Z53: N/A | AA53: - | AB53: Y | AC53: N | AD53: N | AE53: N | AF53: N | AG53: Y | AH53: N | AI53: N | AJ53: Y | AK53: =+IF(AND(AD53="N",AF53="N"),"Fora de âmbito", IF(AND(AD53="N",AF53="Y"),"Apenas ESG Risk", IF(AND(AD53="Y",AF53="N"),"Apenas Pilar 3", IF(AND(AD53="Y",AF53="Y"),"Comum","")))) -> Fora de âmbito | AL53: =+IF(IFERROR(VLOOKUP(A53,Ficheiros!I:I,1,FALSE),"")=A53,"Sim","Não") -> Sim | AM53: =+IF(IFERROR(VLOOKUP(A53,Ficheiros!E:E,1,FALSE),"")=A53,"Sim","Não") -> Não | AN53: =+IF(IFERROR(VLOOKUP(A53,Ficheiros!O:O,1,FALSE),"")=A53,"Sim","Não") -> Não | AO53: =+IF(IFERROR(VLOOKUP(A53,'Especificação Novos Req. LT (2'!A:A,1,FALSE),"")=A53,"Sim","Não") -> Não | AP53: =+IF(IFERROR(VLOOKUP(A53,Ficheiros!T:T,1,FALSE),"")=A53,"Sim","Não") -> Sim | AQ53: =+VLOOKUP(A53,Ficheiros!O:P,2,FALSE) -> #N/A | AR53: =+VLOOKUP(A53,Ficheiros!T:U,2,FALSE) -> 9. Concluído | AS53: =+VLOOKUP(A53,Ficheiros!T:V,3,FALSE) -> PM
A54: =+C54&G54 -> ENTITYWTCH_LST | B54: EN.046 | C54: ENTITY | D54: Classification | E54: N | F54: WTCH_LST | G54: WTCH_LST | H54: N | I54: Y | J54: Y | K54: Y | L54: Y | M54: Y | N54: Y | R54: Y, N | S54: Boolean: Y/N | T54: MISS | U54: N/A | V54: N/A | W54: Debtor on watch-list (Y/N) | X54: Report "Y" when the debtor has been added to an internal watch list. | Y54: Yes - Computed | Z54: IF R8182_EST_FEVE in (02;03;04;05;06;08) THEN Y; ELSE N | AA54: - | AB54: Y | AC54: N | AD54: N | AE54: N | AF54: N | AG54: Y | AH54: N | AI54: N | AJ54: Y | AK54: =+IF(AND(AD54="N",AF54="N"),"Fora de âmbito", IF(AND(AD54="N",AF54="Y"),"Apenas ESG Risk", IF(AND(AD54="Y",AF54="N"),"Apenas Pilar 3", IF(AND(AD54="Y",AF54="Y"),"Comum","")))) -> Fora de âmbito | AL54: =+IF(IFERROR(VLOOKUP(A54,Ficheiros!I:I,1,FALSE),"")=A54,"Sim","Não") -> Sim | AM54: =+IF(IFERROR(VLOOKUP(A54,Ficheiros!E:E,1,FALSE),"")=A54,"Sim","Não") -> Não | AN54: =+IF(IFERROR(VLOOKUP(A54,Ficheiros!O:O,1,FALSE),"")=A54,"Sim","Não") -> Não | AO54: =+IF(IFERROR(VLOOKUP(A54,'Especificação Novos Req. LT (2'!A:A,1,FALSE),"")=A54,"Sim","Não") -> Não | AP54: =+IF(IFERROR(VLOOKUP(A54,Ficheiros!T:T,1,FALSE),"")=A54,"Sim","Não") -> Sim | AQ54: =+VLOOKUP(A54,Ficheiros!O:P,2,FALSE) -> #N/A | AR54: =+VLOOKUP(A54,Ficheiros!T:U,2,FALSE) -> 9. Concluído | AS54: =+VLOOKUP(A54,Ficheiros!T:V,3,FALSE) -> PM
A55: =+C55&G55 -> ENTITYSNGL_PRPS_VHCL | B55: EN.047 | C55: ENTITY | D55: Classification | E55: N | F55: SNGL_PRPS_VHCL | G55: SNGL_PRPS_VHCL | H55: N | I55: N | J55: N | K55: N | L55: N | M55: Y | N55: N | R55: Code List | S55: Use codes from the code list sheet | T55: 99999999999 | U55: 11111111111 | V55: 11111111111 | W55: Type of SPV debtor | X55: In the CRE development business the debtor can be either a 'SPV with recourse' or a 'SPV without recourse' or an 'Other type of entity'. | Y55: Not applicable | Z55: N/A | AA55: - | AB55: Y | AC55: N | AD55: N | AE55: N | AF55: N | AG55: N | AH55: N | AI55: N | AJ55: Y | AK55: =+IF(AND(AD55="N",AF55="N"),"Fora de âmbito", IF(AND(AD55="N",AF55="Y"),"Apenas ESG Risk", IF(AND(AD55="Y",AF55="N"),"Apenas Pilar 3", IF(AND(AD55="Y",AF55="Y"),"Comum","")))) -> Fora de âmbito | AL55: =+IF(IFERROR(VLOOKUP(A55,Ficheiros!I:I,1,FALSE),"")=A55,"Sim","Não") -> Sim | AM55: =+IF(IFERROR(VLOOKUP(A55,Ficheiros!E:E,1,FALSE),"")=A55,"Sim","Não") -> Não | AN55: =+IF(IFERROR(VLOOKUP(A55,Ficheiros!O:O,1,FALSE),"")=A55,"Sim","Não") -> Não | AO55: =+IF(IFERROR(VLOOKUP(A55,'Especificação Novos Req. LT (2'!A:A,1,FALSE),"")=A55,"Sim","Não") -> Não | AP55: =+IF(IFERROR(VLOOKUP(A55,Ficheiros!T:T,1,FALSE),"")=A55,"Sim","Não") -> Sim | AQ55: =+VLOOKUP(A55,Ficheiros!O:P,2,FALSE) -> #N/A | AR55: =+VLOOKUP(A55,Ficheiros!T:U,2,FALSE) -> 9. Concluído | AS55: =+VLOOKUP(A55,Ficheiros!T:V,3,FALSE) -> PM
A56: =+C56&G56 -> ENTITYGRP_EBITDA | B56: EN.048 | C56: ENTITY | D56: Financial Information | E56: N | F56: GRP_EBITDA | G56: GRP_EBITDA | H56: Y | I56: Y | J56: Y | K56: Y | L56: Y | M56: Y | N56: N | R56: FLOAT 2 decimal places | S56: Use decimal point, no thousands seperator | T56: 99999999999 | U56: 11111111111 | V56: 11111111111 | W56: Group's EBITDA at most recent reported figures | X56: EBITDA at latest reported figures. Please report level of the consolidated financial statement of the group accoding to the applicable accounting standard. | Y56: Not applicable | Z56: N/A | AA56: - | AB56: Y | AC56: N | AD56: N | AE56: N | AF56: N | AG56: Y | AH56: N | AI56: N | AJ56: Y | AK56: =+IF(AND(AD56="N",AF56="N"),"Fora de âmbito", IF(AND(AD56="N",AF56="Y"),"Apenas ESG Risk", IF(AND(AD56="Y",AF56="N"),"Apenas Pilar 3", IF(AND(AD56="Y",AF56="Y"),"Comum","")))) -> Fora de âmbito | AL56: =+IF(IFERROR(VLOOKUP(A56,Ficheiros!I:I,1,FALSE),"")=A56,"Sim","Não") -> Sim | AM56: =+IF(IFERROR(VLOOKUP(A56,Ficheiros!E:E,1,FALSE),"")=A56,"Sim","Não") -> Não | AN56: =+IF(IFERROR(VLOOKUP(A56,Ficheiros!O:O,1,FALSE),"")=A56,"Sim","Não") -> Não | AO56: =+IF(IFERROR(VLOOKUP(A56,'Especificação Novos Req. LT (2'!A:A,1,FALSE),"")=A56,"Sim","Não") -> Não | AP56: =+IF(IFERROR(VLOOKUP(A56,Ficheiros!T:T,1,FALSE),"")=A56,"Sim","Não") -> Sim | AQ56: =+VLOOKUP(A56,Ficheiros!O:P,2,FALSE) -> #N/A | AR56: =+VLOOKUP(A56,Ficheiros!T:U,2,FALSE) -> 9. Concluído | AS56: =+VLOOKUP(A56,Ficheiros!T:V,3,FALSE) -> PM
A57: =+C57&G57 -> ENTITYGRP_EQTY | B57: EN.049 | C57: ENTITY | D57: Financial Information | E57: N | F57: GRP_EQTY | G57: GRP_EQTY | H57: Y | I57: Y | J57: Y | K57: Y | L57: Y | M57: Y | N57: N | R57: FLOAT 2 decimal places | S57: Use decimal point, no thousands seperator | T57: 99999999999 | U57: 11111111111 | V57: 11111111111 | W57: Group's equity at most recent reported figures | X57: Equity at most recent reported figures. Please report level of the consolidated financial statement of the group accoding to the applicable accounting standard. | Y57: Not applicable | Z57: N/A | AA57: - | AB57: Y | AC57: N | AD57: Y | AE57: N | AF57: N | AG57: Y | AH57: N | AI57: Y | AJ57: Y | AK57: =+IF(AND(AD57="N",AF57="N"),"Fora de âmbito", IF(AND(AD57="N",AF57="Y"),"Apenas ESG Risk", IF(AND(AD57="Y",AF57="N"),"Apenas Pilar 3", IF(AND(AD57="Y",AF57="Y"),"Comum","")))) -> Apenas Pilar 3 | AL57: =+IF(IFERROR(VLOOKUP(A57,Ficheiros!I:I,1,FALSE),"")=A57,"Sim","Não") -> Sim | AM57: =+IF(IFERROR(VLOOKUP(A57,Ficheiros!E:E,1,FALSE),"")=A57,"Sim","Não") -> Não | AN57: =+IF(IFERROR(VLOOKUP(A57,Ficheiros!O:O,1,FALSE),"")=A57,"Sim","Não") -> Sim | AO57: =+IF(IFERROR(VLOOKUP(A57,'Especificação Novos Req. LT (2'!A:A,1,FALSE),"")=A57,"Sim","Não") -> Não | AP57: =+IF(IFERROR(VLOOKUP(A57,Ficheiros!T:T,1,FALSE),"")=A57,"Sim","Não") -> Sim | AQ57: =+VLOOKUP(A57,Ficheiros!O:P,2,FALSE) -> 1. Concluído | AR57: =+VLOOKUP(A57,Ficheiros!T:U,2,FALSE) -> 9. Concluído | AS57: =+VLOOKUP(A57,Ficheiros!T:V,3,FALSE) -> PM
A58: =+C58&G58 -> ENTITYGRP_NT_DBT | B58: EN.050 | C58: ENTITY | D58: Financial Information | E58: N | F58: GRP_NT_DBT | G58: GRP_NT_DBT | H58: Y | I58: Y | J58: Y | K58: Y | L58: Y | M58: Y | N58: N | R58: FLOAT 2 decimal places | S58: Use decimal point, no thousands seperator | T58: 99999999999 | U58: 11111111111 | V58: 11111111111 | W58: Total net debt at most recent reported figures | X58: Total net debt at most recent reported figures. Please report level of the consolidated financial statement of the group accoding to the applicable accounting standard. | Y58: Not applicable | Z58: N/A | AA58: - | AB58: Y | AC58: N | AD58: N | AE58: N | AF58: N | AG58: Y | AH58: N | AI58: N | AJ58: Y | AK58: =+IF(AND(AD58="N",AF58="N"),"Fora de âmbito", IF(AND(AD58="N",AF58="Y"),"Apenas ESG Risk", IF(AND(AD58="Y",AF58="N"),"Apenas Pilar 3", IF(AND(AD58="Y",AF58="Y"),"Comum","")))) -> Fora de âmbito | AL58: =+IF(IFERROR(VLOOKUP(A58,Ficheiros!I:I,1,FALSE),"")=A58,"Sim","Não") -> Sim | AM58: =+IF(IFERROR(VLOOKUP(A58,Ficheiros!E:E,1,FALSE),"")=A58,"Sim","Não") -> Não | AN58: =+IF(IFERROR(VLOOKUP(A58,Ficheiros!O:O,1,FALSE),"")=A58,"Sim","Não") -> Não | AO58: =+IF(IFERROR(VLOOKUP(A58,'Especificação Novos Req. LT (2'!A:A,1,FALSE),"")=A58,"Sim","Não") -> Não | AP58: =+IF(IFERROR(VLOOKUP(A58,Ficheiros!T:T,1,FALSE),"")=A58,"Sim","Não") -> Sim | AQ58: =+VLOOKUP(A58,Ficheiros!O:P,2,FALSE) -> #N/A | AR58: =+VLOOKUP(A58,Ficheiros!T:U,2,FALSE) -> 9. Concluído | AS58: =+VLOOKUP(A58,Ficheiros!T:V,3,FALSE) -> PM
A59: =+C59&G59 -> ENTITYANNL_TRNVR_LE | B59: EN.051 | C59: ENTITY | D59: Financial Information | E59: Y | F59: ANNL_TRNVR_LE | G59: ANNL_TRNVR_LE | H59: Y | I59: Y | J59: Y | K59: Y | L59: Y | M59: Y | N59: N | R59: FLOAT 2 decimal places | S59: Use decimal point, no thousands seperator | T59: 99999999999 | U59: 11111111111 | V59: 11111111111 | W59: Annual turnover counterparty (LE) | X59: Annual sales volume net of all discounts and sales taxes in accordance with Recommendation 2003/361/EC. Equivalent to the concept of 'total annual sales' in Article 153(4) of Regulation (EU) No 575/2013. Please report on solo entity level unless advised otherwise. | Y59: Not applicable | Z59: N/A | AA59: - | AB59: Y | AC59: N | AD59: Y | AE59: N | AF59: N | AG59: Y | AH59: N | AI59: Y | AJ59: Y | AK59: =+IF(AND(AD59="N",AF59="N"),"Fora de âmbito", IF(AND(AD59="N",AF59="Y"),"Apenas ESG Risk", IF(AND(AD59="Y",AF59="N"),"Apenas Pilar 3", IF(AND(AD59="Y",AF59="Y"),"Comum","")))) -> Apenas Pilar 3 | AL59: =+IF(IFERROR(VLOOKUP(A59,Ficheiros!I:I,1,FALSE),"")=A59,"Sim","Não") -> Sim | AM59: =+IF(IFERROR(VLOOKUP(A59,Ficheiros!E:E,1,FALSE),"")=A59,"Sim","Não") -> Não | AN59: =+IF(IFERROR(VLOOKUP(A59,Ficheiros!O:O,1,FALSE),"")=A59,"Sim","Não") -> Sim | AO59: =+IF(IFERROR(VLOOKUP(A59,'Especificação Novos Req. LT (2'!A:A,1,FALSE),"")=A59,"Sim","Não") -> Não | AP59: =+IF(IFERROR(VLOOKUP(A59,Ficheiros!T:T,1,FALSE),"")=A59,"Sim","Não") -> Sim | AQ59: =+VLOOKUP(A59,Ficheiros!O:P,2,FALSE) -> 1. Concluído | AR59: =+VLOOKUP(A59,Ficheiros!T:U,2,FALSE) -> 2. Alterar especificação | AS59: =+VLOOKUP(A59,Ficheiros!T:V,3,FALSE) -> PM & LF
A60: =+C60&G60 -> ENTITYANNL_TRNVR_PRVS | B60: EN.052 | C60: ENTITY | D60: Financial Information | E60: N | F60: ANNL_TRNVR_PRVS | G60: ANNL_TRNVR_PRVS | H60: Y | I60: Y | J60: Y | K60: Y | L60: Y | M60: Y | N60: N | R60: FLOAT 2 decimal places | S60: Use decimal point, no thousands seperator | T60: 99999999999 | U60: 11111111111 | V60: 11111111111 | W60: Annual turnover counterparty (LE) at previous reporting | X60: Annual sales volume net of all discounts and sales taxes in accordance with Recommendation 2003/361/EC. Equivalent to the concept of 'total annual sales' in Article 153(4) of Regulation (EU) No 575/2013. Please report on solo entity level unless advised otherwise. | Y60: Not applicable | Z60: N/A | AA60: - | AB60: Y | AC60: N | AD60: N | AE60: N | AF60: N | AG60: Y | AH60: N | AI60: N | AJ60: Y | AK60: =+IF(AND(AD60="N",AF60="N"),"Fora de âmbito", IF(AND(AD60="N",AF60="Y"),"Apenas ESG Risk", IF(AND(AD60="Y",AF60="N"),"Apenas Pilar 3", IF(AND(AD60="Y",AF60="Y"),"Comum","")))) -> Fora de âmbito | AL60: =+IF(IFERROR(VLOOKUP(A60,Ficheiros!I:I,1,FALSE),"")=A60,"Sim","Não") -> Sim | AM60: =+IF(IFERROR(VLOOKUP(A60,Ficheiros!E:E,1,FALSE),"")=A60,"Sim","Não") -> Não | AN60: =+IF(IFERROR(VLOOKUP(A60,Ficheiros!O:O,1,FALSE),"")=A60,"Sim","Não") -> Não | AO60: =+IF(IFERROR(VLOOKUP(A60,'Especificação Novos Req. LT (2'!A:A,1,FALSE),"")=A60,"Sim","Não") -> Não | AP60: =+IF(IFERROR(VLOOKUP(A60,Ficheiros!T:T,1,FALSE),"")=A60,"Sim","Não") -> Sim | AQ60: =+VLOOKUP(A60,Ficheiros!O:P,2,FALSE) -> #N/A | AR60: =+VLOOKUP(A60,Ficheiros!T:U,2,FALSE) -> 2. Alterar especificação | AS60: =+VLOOKUP(A60,Ficheiros!T:V,3,FALSE) -> PM & LF
A61: =+C61&G61 -> ENTITYCAPEX | B61: EN.053 | C61: ENTITY | D61: Financial Information | E61: N | F61: CAPEX | G61: CAPEX | H61: Y | I61: Y | J61: Y | K61: Y | L61: Y | M61: Y | N61: N | R61: FLOAT 2 decimal places | S61: Use decimal point, no thousands seperator | T61: 99999999999 | U61: 11111111111 | V61: 11111111111 | W61: Capital expenditures at most recent reported figures | X61: Capital expenditures at most recent reported figures. Please report on solo entity level unless advised otherwise. | Y61: Not applicable | Z61: N/A | AA61: - | AB61: Y | AC61: N | AD61: N | AE61: N | AF61: N | AG61: N | AH61: N | AI61: N | AJ61: Y | AK61: =+IF(AND(AD61="N",AF61="N"),"Fora de âmbito", IF(AND(AD61="N",AF61="Y"),"Apenas ESG Risk", IF(AND(AD61="Y",AF61="N"),"Apenas Pilar 3", IF(AND(AD61="Y",AF61="Y"),"Comum","")))) -> Fora de âmbito | AL61: =+IF(IFERROR(VLOOKUP(A61,Ficheiros!I:I,1,FALSE),"")=A61,"Sim","Não") -> Sim | AM61: =+IF(IFERROR(VLOOKUP(A61,Ficheiros!E:E,1,FALSE),"")=A61,"Sim","Não") -> Não | AN61: =+IF(IFERROR(VLOOKUP(A61,Ficheiros!O:O,1,FALSE),"")=A61,"Sim","Não") -> Não | AO61: =+IF(IFERROR(VLOOKUP(A61,'Especificação Novos Req. LT (2'!A:A,1,FALSE),"")=A61,"Sim","Não") -> Não | AP61: =+IF(IFERROR(VLOOKUP(A61,Ficheiros!T:T,1,FALSE),"")=A61,"Sim","Não") -> Sim | AQ61: =+VLOOKUP(A61,Ficheiros!O:P,2,FALSE) -> #N/A | AR61: =+VLOOKUP(A61,Ficheiros!T:U,2,FALSE) -> 2. Alterar especificação | AS61: =+VLOOKUP(A61,Ficheiros!T:V,3,FALSE) -> PM
A62: =+C62&G62 -> ENTITYCAPEX_PRVS | B62: EN.054 | C62: ENTITY | D62: Financial Information | E62: N | F62: CAPEX_PRVS | G62: CAPEX_PRVS | H62: Y | I62: Y | J62: Y | K62: Y | L62: Y | M62: Y | N62: N | R62: FLOAT 2 decimal places | S62: Use decimal point, no thousands seperator | T62: 99999999999 | U62: 11111111111 | V62: 11111111111 | W62: Capital expenditures at previous reported figures | X62: Capital expenditures at previous reported figures. Please report on solo entity level unless advised otherwise. | Y62: Not applicable | Z62: N/A | AA62: - | AB62: Y | AC62: N | AD62: N | AE62: N | AF62: N | AG62: N | AH62: N | AI62: N | AJ62: Y | AK62: =+IF(AND(AD62="N",AF62="N"),"Fora de âmbito", IF(AND(AD62="N",AF62="Y"),"Apenas ESG Risk", IF(AND(AD62="Y",AF62="N"),"Apenas Pilar 3", IF(AND(AD62="Y",AF62="Y"),"Comum","")))) -> Fora de âmbito | AL62: =+IF(IFERROR(VLOOKUP(A62,Ficheiros!I:I,1,FALSE),"")=A62,"Sim","Não") -> Sim | AM62: =+IF(IFERROR(VLOOKUP(A62,Ficheiros!E:E,1,FALSE),"")=A62,"Sim","Não") -> Não | AN62: =+IF(IFERROR(VLOOKUP(A62,Ficheiros!O:O,1,FALSE),"")=A62,"Sim","Não") -> Não | AO62: =+IF(IFERROR(VLOOKUP(A62,'Especificação Novos Req. LT (2'!A:A,1,FALSE),"")=A62,"Sim","Não") -> Não | AP62: =+IF(IFERROR(VLOOKUP(A62,Ficheiros!T:T,1,FALSE),"")=A62,"Sim","Não") -> Sim | AQ62: =+VLOOKUP(A62,Ficheiros!O:P,2,FALSE) -> #N/A | AR62: =+VLOOKUP(A62,Ficheiros!T:U,2,FALSE) -> 2. Alterar especificação | AS62: =+VLOOKUP(A62,Ficheiros!T:V,3,FALSE) -> PM
A63: =+C63&G63 -> ENTITYCLLCTN_MD | B63: EN.055 | C63: ENTITY | D63: Financial Information | E63: N | F63: CLLCTN_MD | G63: CLLCTN_MD | H63: N | I63: Y | J63: Y | K63: Y | L63: Y | M63: Y | N63: Y | R63: Code List | S63: Use codes from the code list sheet | T63: 99999999999 | U63: 11111111111 | V63: 11111111111 | W63: Collection mode | X63: Collection mode. Hard collection would be similar to foreclosure proceedings while soft collection means to call the collateral without any legal proceedings. | Y63: Not applicable | Z63: N/A | AA63: - | AB63: Y | AC63: N | AD63: N | AE63: N | AF63: N | AG63: N | AH63: N | AI63: N | AJ63: Y | AK63: =+IF(AND(AD63="N",AF63="N"),"Fora de âmbito", IF(AND(AD63="N",AF63="Y"),"Apenas ESG Risk", IF(AND(AD63="Y",AF63="N"),"Apenas Pilar 3", IF(AND(AD63="Y",AF63="Y"),"Comum","")))) -> Fora de âmbito | AL63: =+IF(IFERROR(VLOOKUP(A63,Ficheiros!I:I,1,FALSE),"")=A63,"Sim","Não") -> Sim | AM63: =+IF(IFERROR(VLOOKUP(A63,Ficheiros!E:E,1,FALSE),"")=A63,"Sim","Não") -> Não | AN63: =+IF(IFERROR(VLOOKUP(A63,Ficheiros!O:O,1,FALSE),"")=A63,"Sim","Não") -> Não | AO63: =+IF(IFERROR(VLOOKUP(A63,'Especificação Novos Req. LT (2'!A:A,1,FALSE),"")=A63,"Sim","Não") -> Não | AP63: =+IF(IFERROR(VLOOKUP(A63,Ficheiros!T:T,1,FALSE),"")=A63,"Sim","Não") -> Sim | AQ63: =+VLOOKUP(A63,Ficheiros!O:P,2,FALSE) -> #N/A | AR63: =+VLOOKUP(A63,Ficheiros!T:U,2,FALSE) -> 9. Concluído | AS63: =+VLOOKUP(A63,Ficheiros!T:V,3,FALSE) -> PM
A64: =+C64&G64 -> ENTITYCSH | B64: EN.056 | C64: ENTITY | D64: Financial Information | E64: N | F64: CSH | G64: CSH | H64: Y | I64: Y | J64: Y | K64: Y | L64: Y | M64: Y | N64: N | R64: FLOAT 2 decimal places | S64: Use decimal point, no thousands seperator | T64: 99999999999 | U64: 11111111111 | V64: 11111111111 | W64: Cash and cash equivalents at most recent reported figures | X64: Cash and cash equivalents at most recent reported figures. Please report on solo entity level unless advised otherwise. | Y64: Not applicable | Z64: N/A | AA64: - | AB64: Y | AC64: N | AD64: N | AE64: N | AF64: N | AG64: N | AH64: N | AI64: N | AJ64: Y | AK64: =+IF(AND(AD64="N",AF64="N"),"Fora de âmbito", IF(AND(AD64="N",AF64="Y"),"Apenas ESG Risk", IF(AND(AD64="Y",AF64="N"),"Apenas Pilar 3", IF(AND(AD64="Y",AF64="Y"),"Comum","")))) -> Fora de âmbito | AL64: =+IF(IFERROR(VLOOKUP(A64,Ficheiros!I:I,1,FALSE),"")=A64,"Sim","Não") -> Sim | AM64: =+IF(IFERROR(VLOOKUP(A64,Ficheiros!E:E,1,FALSE),"")=A64,"Sim","Não") -> Não | AN64: =+IF(IFERROR(VLOOKUP(A64,Ficheiros!O:O,1,FALSE),"")=A64,"Sim","Não") -> Não | AO64: =+IF(IFERROR(VLOOKUP(A64,'Especificação Novos Req. LT (2'!A:A,1,FALSE),"")=A64,"Sim","Não") -> Não | AP64: =+IF(IFERROR(VLOOKUP(A64,Ficheiros!T:T,1,FALSE),"")=A64,"Sim","Não") -> Sim | AQ64: =+VLOOKUP(A64,Ficheiros!O:P,2,FALSE) -> #N/A | AR64: =+VLOOKUP(A64,Ficheiros!T:U,2,FALSE) -> 2. Alterar especificação | AS64: =+VLOOKUP(A64,Ficheiros!T:V,3,FALSE) -> PM
A65: =+C65&G65 -> ENTITYCSH_PRVS | B65: EN.057 | C65: ENTITY | D65: Financial Information | E65: N | F65: CSH_PRVS | G65: CSH_PRVS | H65: Y | I65: Y | J65: Y | K65: Y | L65: Y | M65: Y | N65: N | R65: FLOAT 2 decimal places | S65: Use decimal point, no thousands seperator | T65: 99999999999 | U65: 11111111111 | V65: 11111111111 | W65: Cash and cash equivalents at previous reported figures | X65: Cash and cash equivalents at previous reported figures. Please report on solo entity level unless advised otherwise. | Y65: Not applicable | Z65: N/A | AA65: - | AB65: Y | AC65: N | AD65: N | AE65: N | AF65: N | AG65: N | AH65: N | AI65: N | AJ65: Y | AK65: =+IF(AND(AD65="N",AF65="N"),"Fora de âmbito", IF(AND(AD65="N",AF65="Y"),"Apenas ESG Risk", IF(AND(AD65="Y",AF65="N"),"Apenas Pilar 3", IF(AND(AD65="Y",AF65="Y"),"Comum","")))) -> Fora de âmbito | AL65: =+IF(IFERROR(VLOOKUP(A65,Ficheiros!I:I,1,FALSE),"")=A65,"Sim","Não") -> Sim | AM65: =+IF(IFERROR(VLOOKUP(A65,Ficheiros!E:E,1,FALSE),"")=A65,"Sim","Não") -> Não | AN65: =+IF(IFERROR(VLOOKUP(A65,Ficheiros!O:O,1,FALSE),"")=A65,"Sim","Não") -> Não | AO65: =+IF(IFERROR(VLOOKUP(A65,'Especificação Novos Req. LT (2'!A:A,1,FALSE),"")=A65,"Sim","Não") -> Não | AP65: =+IF(IFERROR(VLOOKUP(A65,Ficheiros!T:T,1,FALSE),"")=A65,"Sim","Não") -> Sim | AQ65: =+VLOOKUP(A65,Ficheiros!O:P,2,FALSE) -> #N/A | AR65: =+VLOOKUP(A65,Ficheiros!T:U,2,FALSE) -> 2. Alterar especificação | AS65: =+VLOOKUP(A65,Ficheiros!T:V,3,FALSE) -> PM
A66: =+C66&G66 -> ENTITYEBITDA | B66: EN.058 | C66: ENTITY | D66: Financial Information | E66: N | F66: EBITDA | G66: EBITDA | H66: Y | I66: Y | J66: Y | K66: Y | L66: Y | M66: Y | N66: N | R66: FLOAT 2 decimal places | S66: Use decimal point, no thousands seperator | T66: 99999999999 | U66: 11111111111 | V66: 11111111111 | W66: EBITDA at latest reported figures | X66: EBITDA at latest reported figures. Please report on solo entity level unless advised otherwise. | Y66: Not applicable | Z66: N/A | AA66: - | AB66: Y | AC66: N | AD66: N | AE66: N | AF66: N | AG66: Y | AH66: N | AI66: N | AJ66: Y | AK66: =+IF(AND(AD66="N",AF66="N"),"Fora de âmbito", IF(AND(AD66="N",AF66="Y"),"Apenas ESG Risk", IF(AND(AD66="Y",AF66="N"),"Apenas Pilar 3", IF(AND(AD66="Y",AF66="Y"),"Comum","")))) -> Fora de âmbito | AL66: =+IF(IFERROR(VLOOKUP(A66,Ficheiros!I:I,1,FALSE),"")=A66,"Sim","Não") -> Sim | AM66: =+IF(IFERROR(VLOOKUP(A66,Ficheiros!E:E,1,FALSE),"")=A66,"Sim","Não") -> Não | AN66: =+IF(IFERROR(VLOOKUP(A66,Ficheiros!O:O,1,FALSE),"")=A66,"Sim","Não") -> Não | AO66: =+IF(IFERROR(VLOOKUP(A66,'Especificação Novos Req. LT (2'!A:A,1,FALSE),"")=A66,"Sim","Não") -> Não | AP66: =+IF(IFERROR(VLOOKUP(A66,Ficheiros!T:T,1,FALSE),"")=A66,"Sim","Não") -> Sim | AQ66: =+VLOOKUP(A66,Ficheiros!O:P,2,FALSE) -> #N/A | AR66: =+VLOOKUP(A66,Ficheiros!T:U,2,FALSE) -> 2. Alterar especificação | AS66: =+VLOOKUP(A66,Ficheiros!T:V,3,FALSE) -> PM & LF
... A92: =+C92&G92 -> ENTITYPD_IFRS9_12M_RD_T1 | B92: EN.084 | C92: ENTITY | D92: Indicators | E92: N | F92: PD_IFRS9_12M_RD_T1 | G92: PD_IFRS9_12M_RD_T1 | H92: Y | I92: Y | J92: Y | K92: Y | L92: Y | M92: Y | N92: Y | R92: FLOAT 6 decimal places | S92: Use decimal point, no thousands seperator | T92: 99999999999 | U92: 11111111111 | V92: 11111111111 | W92: 12-month PD one year prior to the reporting date according to IFRS 9 | X92: 12-month PD one year prior to the reference date which is used by the bank for the computation of stage 1 ECL or for SICR assessment if the bank uses a 12 month proxy for staging. If the PD is calculated on instruments level please provide an EAD weighted average. | Y92: Yes - Computed | Z92: SUM for all of client's contracts (T2417_P12IFRS9 * T2417_EADIFRS9) / Total Client T2417_EADIFRS9 | AA92: To be computed using one year previous to the reference date information. (for example, if Reference date: 03/30/2022, information as of 03/30/2021 is used to compute this field) | AB92: Y | AC92: N | AD92: N | AE92: N | AF92: N | AG92: N | AH92: N | AI92: N | AJ92: Y | AK92: =+IF(AND(AD92="N",AF92="N"),"Fora de âmbito", IF(AND(AD92="N",AF92="Y"),"Apenas ESG Risk", IF(AND(AD92="Y",AF92="N"),"Apenas Pilar 3", IF(AND(AD92="Y",AF92="Y"),"Comum","")))) -> Fora de âmbito | AL92: =+IF(IFERROR(VLOOKUP(A92,Ficheiros!I:I,1,FALSE),"")=A92,"Sim","Não") -> Sim | AM92: =+IF(IFERROR(VLOOKUP(A92,Ficheiros!E:E,1,FALSE),"")=A92,"Sim","Não") -> Não | AN92: =+IF(IFERROR(VLOOKUP(A92,Ficheiros!O:O,1,FALSE),"")=A92,"Sim","Não") -> Não | AO92: =+IF(IFERROR(VLOOKUP(A92,'Especificação Novos Req. LT (2'!A:A,1,FALSE),"")=A92,"Sim","Não") -> Não | AP92: =+IF(IFERROR(VLOOKUP(A92,Ficheiros!T:T,1,FALSE),"")=A92,"Sim","Não") -> Sim | AQ92: =+VLOOKUP(A92,Ficheiros!O:P,2,FALSE) -> #N/A | AR92: =+VLOOKUP(A92,Ficheiros!T:U,2,FALSE) -> 7. Analisar controlos e completude | AS92: =+VLOOKUP(A92,Ficheiros!T:V,3,FALSE) -> PM
A93: =+C93&G93 -> ENTITYTAX_ID | B93: EN.085 | C93: ENTITY | D93: General | E93: N | F93: TAX_ID | G93: TAX_ID | H93: Y | I93: Y | J93: Y | K93: Y | L93: Y | M93: Y | N93: Y | R93: VARCHAR2(255) | S93: Free (latin) text without special characters (semicolon, quotes, …) | T93: MISS | U93: N/A | V93: N/A | W93: Fiscal ID | X93: Fiscal ID (CIF, NIF, Tax number, etc). | Y93: Yes - Equivalent | Z93: JM_CLIENT_BII - G4093_CODIDPER | AA93: - | AB93: Y | AC93: N | AD93: N | AE93: N | AF93: N | AG93: N | AH93: N | AI93: N | AJ93: Y | AK93: =+IF(AND(AD93="N",AF93="N"),"Fora de âmbito", IF(AND(AD93="N",AF93="Y"),"Apenas ESG Risk", IF(AND(AD93="Y",AF93="N"),"Apenas Pilar 3", IF(AND(AD93="Y",AF93="Y"),"Comum","")))) -> Fora de âmbito | AL93: =+IF(IFERROR(VLOOKUP(A93,Ficheiros!I:I,1,FALSE),"")=A93,"Sim","Não") -> Sim | AM93: =+IF(IFERROR(VLOOKUP(A93,Ficheiros!E:E,1,FALSE),"")=A93,"Sim","Não") -> Não | AN93: =+IF(IFERROR(VLOOKUP(A93,Ficheiros!O:O,1,FALSE),"")=A93,"Sim","Não") -> Não | AO93: =+IF(IFERROR(VLOOKUP(A93,'Especificação Novos Req. LT (2'!A:A,1,FALSE),"")=A93,"Sim","Não") -> Não | AP93: =+IF(IFERROR(VLOOKUP(A93,Ficheiros!T:T,1,FALSE),"")=A93,"Sim","Não") -> Sim | AQ93: =+VLOOKUP(A93,Ficheiros!O:P,2,FALSE) -> #N/A | AR93: =+VLOOKUP(A93,Ficheiros!T:U,2,FALSE) -> 7. Analisar controlos e completude | AS93: =+VLOOKUP(A93,Ficheiros!T:V,3,FALSE) -> PM
A94: =+C94&G94 -> ENTITYANNL_TRNVR_LE_BDR | B94: EN.086 | C94: ENTITY | D94: Financial Information | E94: N | F94: ANNL_TRNVR_LE_BDR | G94: ANNL_TRNVR_LE_BDR | H94: Y | I94: Y | J94: Y | K94: Y | L94: Y | M94: Y | N94: N | R94: FLOAT 2 decimal places | S94: Use decimal point, no thousands seperator | T94: 99999999999 | U94: 11111111111 | V94: 11111111111 | W94: BDR Annual turnover counterparty (LE) | X94: BDR Annual sales volume net of all discounts and sales taxes in accordance with Recommendation 2003/361/EC. Equivalent to the concept of 'total annual sales' in Article 153(4) of Regulation (EU) No 575/2013. Please report on solo entity level unless advised otherwise. | Y94: Yes - Equivalent | Z94: JM_CLIEN_JURI - G5508_IMPFACTM | AA94: - | AB94: Y | AC94: N | AD94: N | AE94: N | AF94: N | AG94: N | AH94: N | AI94: N | AJ94: Y | AK94: =+IF(AND(AD94="N",AF94="N"),"Fora de âmbito", IF(AND(AD94="N",AF94="Y"),"Apenas ESG Risk", IF(AND(AD94="Y",AF94="N"),"Apenas Pilar 3", IF(AND(AD94="Y",AF94="Y"),"Comum","")))) -> Fora de âmbito | AL94: =+IF(IFERROR(VLOOKUP(A94,Ficheiros!I:I,1,FALSE),"")=A94,"Sim","Não") -> Sim | AM94: =+IF(IFERROR(VLOOKUP(A94,Ficheiros!E:E,1,FALSE),"")=A94,"Sim","Não") -> Não | AN94: =+IF(IFERROR(VLOOKUP(A94,Ficheiros!O:O,1,FALSE),"")=A94,"Sim","Não") -> Não | AO94: =+IF(IFERROR(VLOOKUP(A94,'Especificação Novos Req. LT (2'!A:A,1,FALSE),"")=A94,"Sim","Não") -> Não | AP94: =+IF(IFERROR(VLOOKUP(A94,Ficheiros!T:T,1,FALSE),"")=A94,"Sim","Não") -> Sim | AQ94: =+VLOOKUP(A94,Ficheiros!O:P,2,FALSE) -> #N/A | AR94: =+VLOOKUP(A94,Ficheiros!T:U,2,FALSE) -> 9. Concluído | AS94: =+VLOOKUP(A94,Ficheiros!T:V,3,FALSE) -> PM
A95: =+C95&G95 -> ENTITYANNL_TRNVR_PRVS_BDR | B95: EN.087 | C95: ENTITY | D95: Financial Information | E95: N | F95: ANNL_TRNVR_PRVS_BDR | G95: ANNL_TRNVR_PRVS_BDR | H95: Y | I95: Y | J95: Y | K95: Y | L95: Y | M95: Y | N95: N | R95: FLOAT 2 decimal places | S95: Use decimal point, no thousands seperator | T95: 99999999999 | U95: 11111111111 | V95: 11111111111 | W95: BDR Annual turnover counterparty (LE) at previous reporting | X95: BDR Annual sales volume net of all discounts and sales taxes in accordance with Recommendation 2003/361/EC. Equivalent to the concept of 'total annual sales' in Article 153(4) of Regulation (EU) No 575/2013. Please report on solo entity level unless advised otherwise. | Y95: Yes - Equivalent | Z95: JM_CLIEN_JURI - G5508_IMPFACTM | AA95: To be computed using the one at previous reporting | AB95: Y | AC95: N | AD95: N | AE95: N | AF95: N | AG95: N | AH95: N | AI95: N | AJ95: Y | AK95: =+IF(AND(AD95="N",AF95="N"),"Fora de âmbito", IF(AND(AD95="N",AF95="Y"),"Apenas ESG Risk", IF(AND(AD95="Y",AF95="N"),"Apenas Pilar 3", IF(AND(AD95="Y",AF95="Y"),"Comum","")))) -> Fora de âmbito | AL95: =+IF(IFERROR(VLOOKUP(A95,Ficheiros!I:I,1,FALSE),"")=A95,"Sim","Não") -> Sim | AM95: =+IF(IFERROR(VLOOKUP(A95,Ficheiros!E:E,1,FALSE),"")=A95,"Sim","Não") -> Não | AN95: =+IF(IFERROR(VLOOKUP(A95,Ficheiros!O:O,1,FALSE),"")=A95,"Sim","Não") -> Não | AO95: =+IF(IFERROR(VLOOKUP(A95,'Especificação Novos Req. LT (2'!A:A,1,FALSE),"")=A95,"Sim","Não") -> Não | AP95: =+IF(IFERROR(VLOOKUP(A95,Ficheiros!T:T,1,FALSE),"")=A95,"Sim","Não") -> Sim | AQ95: =+VLOOKUP(A95,Ficheiros!O:P,2,FALSE) -> #N/A | AR95: =+VLOOKUP(A95,Ficheiros!T:U,2,FALSE) -> 9. Concluído | AS95: =+VLOOKUP(A95,Ficheiros!T:V,3,FALSE) -> PM
A96: =+C96&G96 -> ENTITYOSI_ID | B96: EN.088 | C96: ENTITY | D96: General | E96: N | F96: OSI_ID | G96: OSI_ID | H96: Corporation | I96: Corporation | J96: Corporation | K96: Corporation | L96: Corporation | M96: Corporation | N96: Corporation | R96: VARCHAR2(255) | S96: Free (latin) text without special characters (semicolon, quotes, …) | T96: MISS | U96: N/A | V96: N/A | W96: On-site inspection identifier | X96: The identifier that is used to identify an on-site inspection as is referenced in the on-site inspection notification letter head. The value typically follows the convention: "OSI-YYYY-JSTCD-01234". | Y96: Not applicable | Z96: N/A | AA96: - | AB96: Y | AC96: N | AD96: N | AE96: N | AF96: N | AG96: Y | AH96: N | AI96: N | AJ96: Y | AK96: =+IF(AND(AD96="N",AF96="N"),"Fora de âmbito", IF(AND(AD96="N",AF96="Y"),"Apenas ESG Risk", IF(AND(AD96="Y",AF96="N"),"Apenas Pilar 3", IF(AND(AD96="Y",AF96="Y"),"Comum","")))) -> Fora de âmbito | AL96: =+IF(IFERROR(VLOOKUP(A96,Ficheiros!I:I,1,FALSE),"")=A96,"Sim","Não") -> Sim | AM96: =+IF(IFERROR(VLOOKUP(A96,Ficheiros!E:E,1,FALSE),"")=A96,"Sim","Não") -> Não | AN96: =+IF(IFERROR(VLOOKUP(A96,Ficheiros!O:O,1,FALSE),"")=A96,"Sim","Não") -> Não | AO96: =+IF(IFERROR(VLOOKUP(A96,'Especificação Novos Req. LT (2'!A:A,1,FALSE),"")=A96,"Sim","Não") -> Não | AP96: =+IF(IFERROR(VLOOKUP(A96,Ficheiros!T:T,1,FALSE),"")=A96,"Sim","Não") -> Sim | AQ96: =+VLOOKUP(A96,Ficheiros!O:P,2,FALSE) -> #N/A | AR96: =+VLOOKUP(A96,Ficheiros!T:U,2,FALSE) -> 9. Concluído | AS96: =+VLOOKUP(A96,Ficheiros!T:V,3,FALSE) -> PM
A97: =+C97&G97 -> ENTITYPD_CRR_RD_T1 | B97: EN.089 | C97: ENTITY | D97: Indicators | E97: N | F97: PD_CRR_RD_T1 | G97: PD_CRR_RD_T1 | H97: Y | I97: Y | J97: Y | K97: Y | L97: Y | M97: Y | N97: Y | R97: FLOAT 6 decimal places | S97: Use decimal point, no thousands seperator | T97: 99999999999 | U97: 11111111111 | V97: 11111111111 | W97: Probability of default according to CRR one year prior to the reference date | X97: The PD over one year, determined in accordance with Articles 160, 163, 179 and 180 of Regulation (EU) No 575/2013. If the PD is calculated on obligor level then provide the obligor PD. If the PD is calculated on instruments level please provide an EAD weighted average. | Y97: Yes - Computed | Z97: SUM for all of client's contracts (G7162_IN_PDINI * EAD) / Total Client EAD | AA97: EAD refers to the LT data field IN.074 Report PD one year previous to the reference date. (for example, if Reference date: 03/30/2022, the PD as of 03/30/2021 is reported in this field) | AB97: Y | AC97: N | AD97: N | AE97: N | AF97: N | AG97: N | AH97: N | AI97: N | AJ97: Y | AK97: =+IF(AND(AD97="N",AF97="N"),"Fora de âmbito", IF(AND(AD97="N",AF97="Y"),"Apenas ESG Risk", IF(AND(AD97="Y",AF97="N"),"Apenas Pilar 3", IF(AND(AD97="Y",AF97="Y"),"Comum","")))) -> Fora de âmbito | AL97: =+IF(IFERROR(VLOOKUP(A97,Ficheiros!I:I,1,FALSE),"")=A97,"Sim","Não") -> Sim | AM97: =+IF(IFERROR(VLOOKUP(A97,Ficheiros!E:E,1,FALSE),"")=A97,"Sim","Não") -> Não | AN97: =+IF(IFERROR(VLOOKUP(A97,Ficheiros!O:O,1,FALSE),"")=A97,"Sim","Não") -> Não | AO97: =+IF(IFERROR(VLOOKUP(A97,'Especificação Novos Req. LT (2'!A:A,1,FALSE),"")=A97,"Sim","Não") -> Não | AP97: =+IF(IFERROR(VLOOKUP(A97,Ficheiros!T:T,1,FALSE),"")=A97,"Sim","Não") -> Sim | AQ97: =+VLOOKUP(A97,Ficheiros!O:P,2,FALSE) -> #N/A | AR97: =+VLOOKUP(A97,Ficheiros!T:U,2,FALSE) -> 5.1 Em testes - Re-especificação | AS97: =+VLOOKUP(A97,Ficheiros!T:V,3,FALSE) -> PM
A98: =+C98&G98 -> ENTITYEC_GRP_ID | B98: EN.090 | C98: ENTITY | D98: General | E98: N | F98: EC_GRP_ID | G98: EC_GRP_ID | H98: Y | I98: Y | J98: Y | K98: Y | L98: Y | M98: Y | N98: N | R98: VARCHAR2(255) | S98: Free (latin) text without special characters (semicolon, quotes, …) | T98: MISS | U98: N/A | V98: N/A | W98: Economic (financial) Group ID | X98: The unit should report the unique identifier of the economic group (ultimate parent entity) of the counterparty. | Y98: Yes - Equivalent | Z98: JM_GRUP_ECONO - G5512_GRUP_ECO | AB98: Y | AC98: N | AD98: Y | AE98: Y | AF98: N | AG98: Y | AH98: N | AI98: Y | AJ98: Y | AK98: =+IF(AND(AD98="N",AF98="N"),"Fora de âmbito", IF(AND(AD98="N",AF98="Y"),"Apenas ESG Risk", IF(AND(AD98="Y",AF98="N"),"Apenas Pilar 3", IF(AND(AD98="Y",AF98="Y"),"Comum","")))) -> Apenas Pilar 3 | AL98: =+IF(IFERROR(VLOOKUP(A98,Ficheiros!I:I,1,FALSE),"")=A98,"Sim","Não") -> Sim | AM98: =+IF(IFERROR(VLOOKUP(A98,Ficheiros!E:E,1,FALSE),"")=A98,"Sim","Não") -> Não | AN98: =+IF(IFERROR(VLOOKUP(A98,Ficheiros!O:O,1,FALSE),"")=A98,"Sim","Não") -> Não | AO98: =+IF(IFERROR(VLOOKUP(A98,'Especificação Novos Req. LT (2'!A:A,1,FALSE),"")=A98,"Sim","Não") -> Não | AP98: =+IF(IFERROR(VLOOKUP(A98,Ficheiros!T:T,1,FALSE),"")=A98,"Sim","Não") -> Sim | AQ98: =+VLOOKUP(A98,Ficheiros!O:P,2,FALSE) -> #N/A | AR98: =+VLOOKUP(A98,Ficheiros!T:U,2,FALSE) -> 1. Especificar | AS98: =+VLOOKUP(A98,Ficheiros!T:V,3,FALSE) -> LF | AT98: Sim | AU98: Sim | AV98: Package 4 | AX98: Especificar o campo
A99: =+C99&G99 -> ENTITYEC_GRP_NM | B99: EN.091 | C99: ENTITY | D99: General | E99: N | F99: EC_GRP_NM | G99: EC_GRP_NM | H99: Y | I99: Y | J99: Y | K99: Y | L99: Y | M99: Y | N99: N | R99: VARCHAR2(255) | S99: Free (latin) text without special characters (semicolon, quotes, …) | T99: MISS | U99: N/A | V99: N/A | W99: Economic (Financial) Group Name | X99: The unit should report the legal/official name of the ultimate parent entity of the counterparty’s economic group | Y99: Yes - Equivalent | Z99: JM_GRUP_ECONO - G5512_DGRUPO | AA99: Report Name of the entity reported in EN.011 | AB99: Y | AC99: N | AD99: Y | AE99: Y | AF99: N | AG99: Y | AH99: N | AI99: Y | AJ99: Y | AK99: =+IF(AND(AD99="N",AF99="N"),"Fora de âmbito", IF(AND(AD99="N",AF99="Y"),"Apenas ESG Risk", IF(AND(AD99="Y",AF99="N"),"Apenas Pilar 3", IF(AND(AD99="Y",AF99="Y"),"Comum","")))) -> Apenas Pilar 3 | AL99: =+IF(IFERROR(VLOOKUP(A99,Ficheiros!I:I,1,FALSE),"")=A99,"Sim","Não") -> Sim | AM99: =+IF(IFERROR(VLOOKUP(A99,Ficheiros!E:E,1,FALSE),"")=A99,"Sim","Não") -> Não | AN99: =+IF(IFERROR(VLOOKUP(A99,Ficheiros!O:O,1,FALSE),"")=A99,"Sim","Não") -> Não | AO99: =+IF(IFERROR(VLOOKUP(A99,'Especificação Novos Req. LT (2'!A:A,1,FALSE),"")=A99,"Sim","Não") -> Sim | AP99: =+IF(IFERROR(VLOOKUP(A99,Ficheiros!T:T,1,FALSE),"")=A99,"Sim","Não") -> Sim | AQ99: =+VLOOKUP(A99,Ficheiros!O:P,2,FALSE) -> #N/A | AR99: =+VLOOKUP(A99,Ficheiros!T:U,2,FALSE) -> 1. Especificar | AS99: =+VLOOKUP(A99,Ficheiros!T:V,3,FALSE) -> LF | AV99: Package 5
A100: =+C100&G100 -> ENTITYPST_CD | B100: EN.092 | C100: ENTITY | D100: General | E100: N | F100: PST_CD | G100: PST_CD | H100: N | I100: Y | J100: Y | K100: Y | L100: Y | M100: Y | N100: Y | R100: VARCHAR2(255) | S100: Free (latin) text without special characters (semicolon, quotes, …) | T100: MISS | U100: N/A | V100: N/A | W100: Post code / ZIP | X100: Post code / ZIP. | Y100: Not applicable | Z100: N/A | AA100: - | AB100: N | AC100: N | AD100: Y | AE100: N | AF100: Y | AG100: N | AH100: N | AI100: Y | AJ100: Y | AK100: =+IF(AND(AD100="N",AF100="N"),"Fora de âmbito", IF(AND(AD100="N",AF100="Y"),"Apenas ESG Risk", IF(AND(AD100="Y",AF100="N"),"Apenas Pilar 3", IF(AND(AD100="Y",AF100="Y"),"Comum","")))) -> Comum | AL100: =+IF(IFERROR(VLOOKUP(A100,Ficheiros!I:I,1,FALSE),"")=A100,"Sim","Não") -> Não | AM100: =+IF(IFERROR(VLOOKUP(A100,Ficheiros!E:E,1,FALSE),"")=A100,"Sim","Não") -> Sim | AN100: =+IF(IFERROR(VLOOKUP(A100,Ficheiros!O:O,1,FALSE),"")=A100,"Sim","Não") -> Sim | AO100: =+IF(IFERROR(VLOOKUP(A100,'Especificação Novos Req. LT (2'!A:A,1,FALSE),"")=A100,"Sim","Não") -> Não | AP100: =+IF(IFERROR(VLOOKUP(A100,Ficheiros!T:T,1,FALSE),"")=A100,"Sim","Não") -> Não | AQ100: =+VLOOKUP(A100,Ficheiros!O:P,2,FALSE) -> 1. Concluído | AR100: =+VLOOKUP(A100,Ficheiros!R:S,3,FALSE) -> #N/A | AS100: =+VLOOKUP(A100,Ficheiros!T:V,3,FALSE) -> #N/A
A101: =+C101&G101 -> ENTITYESG_SBSCTR | B101: EN.093 | C101: ENTITY | D101: General | E101: N | F101: ESG_SBSCTR | G101: ESG_SBSCTR | H101: N | I101: N | J101: Y | K101: N | L101: Y | M101: N | N101: N | R101: Code List | S101: Use codes from the code list sheet | T101: MISS | U101: N/A | V101: N/A | W101: ESG Subsector | X101: ESG Subsector is a breakdown of NOPER Annex Segments (General governments and Other Financial Corporation) | Y101: Not applicable | Z101: N/A | AA101: - | AB101: N | AC101: N | AD101: Y | AE101: N | AF101: N | AG101: N | AH101: N | AI101: Y | AJ101: Y | AK101: =+IF(AND(AD101="N",AF101="N"),"Fora de âmbito", IF(AND(AD101="N",AF101="Y"),"Apenas ESG Risk", IF(AND(AD101="Y",AF101="N"),"Apenas Pilar 3", IF(AND(AD101="Y",AF101="Y"),"Comum","")))) -> Apenas Pilar 3 | AL101: =+IF(IFERROR(VLOOKUP(A101,Ficheiros!I:I,1,FALSE),"")=A101,"Sim","Não") -> Não | AM101: Não | AN101: Não | AO101: =+IF(IFERROR(VLOOKUP(A101,'Especificação Novos Req. LT (2'!A:A,1,FALSE),"")=A101,"Sim","Não") -> Não | AP101: =+IF(IFERROR(VLOOKUP(A101,Ficheiros!T:T,1,FALSE),"")=A101,"Sim","Não") -> Não | AQ101: =+VLOOKUP(A101,Ficheiros!O:P,2,FALSE) -> 1. Concluído | AR101: =+VLOOKUP(A101,Ficheiros!R:S,3,FALSE) -> #N/A | AS101: =+VLOOKUP(A101,Ficheiros!T:V,3,FALSE) -> #N/A | AV101: Package 5 | AW101: Concluído | AX101: Quando o campo for testado é necessário testar a LT826
A102: =+C102&G102 -> ENTITYNACE_ESG | B102: EN.094 | C102: ENTITY | D102: Classification | E102: N | F102: NACE_ESG | G102: NACE_ESG | H102: N | I102: Y | J102: Y | K102: Y | L102: Y | M102: Y | N102: N | R102: Code list | S102: Use codes from the code list sheet | T102: MISS | U102: N/A | V102: N/A | W102: Economic activity counterparty ESG | X102: The level four NACE code in accordance with Regulation (EC) No 1893/2006 is generally reported but following the Pilar 3 ESG EBA Guidelines criteria for the NACE allocation. | Y102: Not applicable | Z102: N/A | AA102: - | AB102: N | AC102: N | AD102: Y | AE102: N | AF102: Y | AG102: N | AH102: N | AI102: Y | AJ102: Y | AK102: =+IF(AND(AD102="N",AF102="N"),"Fora de âmbito", IF(AND(AD102="N",AF102="Y"),"Apenas ESG Risk", IF(AND(AD102="Y",AF102="N"),"Apenas Pilar 3", IF(AND(AD102="Y",AF102="Y"),"Comum","")))) -> Comum | AL102: =+IF(IFERROR(VLOOKUP(A102,Ficheiros!I:I,1,FALSE),"")=A102,"Sim","Não") -> Não | AM102: =+IF(IFERROR(VLOOKUP(A102,Ficheiros!E:E,1,FALSE),"")=A102,"Sim","Não") -> Sim | AN102: =+IF(IFERROR(VLOOKUP(A102,Ficheiros!O:O,1,FALSE),"")=A102,"Sim","Não") -> Sim | AO102: =+IF(IFERROR(VLOOKUP(A102,'Especificação Novos Req. LT (2'!A:A,1,FALSE),"")=A102,"Sim","Não") -> Não | AP102: =+IF(IFERROR(VLOOKUP(A102,Ficheiros!T:T,1,FALSE),"")=A102,"Sim","Não") -> Não | AQ102: =+VLOOKUP(A102,Ficheiros!O:P,2,FALSE) -> 1. Concluído | AR102: =+VLOOKUP(A102,Ficheiros!R:S,3,FALSE) -> #N/A | AS102: =+VLOOKUP(A102,Ficheiros!T:V,3,FALSE) -> #N/A
A103: =+C103&G103 -> ENTITYTTL_LBLTY | B103: EN.095 | C103: ENTITY | D103: Financial Information | E103: N | F103: TTL_LBLTY | G103: TTL_LBLTY | H103: Y | I103: N | J103: Y | K103: Y | L103: Y | M103: Y | N103: N | R103: FLOAT 2 decimal places | S103: Use decimal point, no thousands seperator | T103: 99999999999 | U103: 11111111111 | V103: 11111111111 | W103: Total Liabilities at latest most recent reported figures | X103: Counterparty’s total liabilities according to its annual financial statements at most recent reported figures | Y103: Not applicable | Z103: N/A | AA103: - | AB103: N | AC103: N | AD103: Y | AE103: N | AF103: N | AG103: N | AH103: N | AI103: Y | AJ103: Y | AK103: =+IF(AND(AD103="N",AF103="N"),"Fora de âmbito", IF(AND(AD103="N",AF103="Y"),"Apenas ESG Risk", IF(AND(AD103="Y",AF103="N"),"Apenas Pilar 3", IF(AND(AD103="Y",AF103="Y"),"Comum","")))) -> Apenas Pilar 3 | AL103: =+IF(IFERROR(VLOOKUP(A103,Ficheiros!I:I,1,FALSE),"")=A103,"Sim","Não") -> Não | AM103: =+IF(IFERROR(VLOOKUP(A103,Ficheiros!E:E,1,FALSE),"")=A103,"Sim","Não") -> Sim | AN103: =+IF(IFERROR(VLOOKUP(A103,Ficheiros!O:O,1,FALSE),"")=A103,"Sim","Não") -> Sim | AO103: =+IF(IFERROR(VLOOKUP(A103,'Especificação Novos Req. LT (2'!A:A,1,FALSE),"")=A103,"Sim","Não") -> Não | AP103: =+IF(IFERROR(VLOOKUP(A103,Ficheiros!T:T,1,FALSE),"")=A103,"Sim","Não") -> Não | AQ103: =+VLOOKUP(A103,Ficheiros!O:P,2,FALSE) -> 1. Concluído | AR103: =+VLOOKUP(A103,Ficheiros!R:S,3,FALSE) -> #N/A | AS103: =+VLOOKUP(A103,Ficheiros!T:V,3,FALSE) -> #N/A
A104: =+C104&G104 -> ENTITYTXNMY_ELGBL_CAPEX_CCM | B104: EN.096 | C104: ENTITY | D104: General | E104: N | F104: TXNMY_ELGBL_CAPEX_CCM | G104: TXNMY_ELGBL_CAPEX_CCM | H104: N | I104: N | J104: N | K104: Y | L104: Y | M104: Y | N104: N | R104: FLOAT 6 decimal places | S104: Use decimal point, no thousands seperator | T104: 99999999999 | U104: 11111111111 | V104: 11111111111 | W104: Taxonomy-eligible CAPEX (CCM) Ratio | X104: Counterparty’s reported proportion of CAPEX eligible according to European Taxonomy and that might make a substantial contribution to an environmental objective of ‘Climate Change Mitigation’. | Y104: Not applicable | Z104: N/A | AA104: - | AB104: N | AC104: N | AD104: Y | AE104: N | AF104: N | AG104: N | AH104: N | AI104: Y | AJ104: Y | AK104: =+IF(AND(AD104="N",AF104="N"),"Fora de âmbito", IF(AND(AD104="N",AF104="Y"),"Apenas ESG Risk", IF(AND(AD104="Y",AF104="N"),"Apenas Pilar 3", IF(AND(AD104="Y",AF104="Y"),"Comum","")))) -> Apenas Pilar 3 | AL104: =+IF(IFERROR(VLOOKUP(A104,Ficheiros!I:I,1,FALSE),"")=A104,"Sim","Não") -> Não | AM104: =+IF(IFERROR(VLOOKUP(A104,Ficheiros!E:E,1,FALSE),"")=A104,"Sim","Não") -> Sim | AN104: =+IF(IFERROR(VLOOKUP(A104,Ficheiros!O:O,1,FALSE),"")=A104,"Sim","Não") -> Sim | AO104: =+IF(IFERROR(VLOOKUP(A104,'Especificação Novos Req. LT (2'!A:A,1,FALSE),"")=A104,"Sim","Não") -> Não | AP104: =+IF(IFERROR(VLOOKUP(A104,Ficheiros!T:T,1,FALSE),"")=A104,"Sim","Não") -> Não | AQ104: =+VLOOKUP(A104,Ficheiros!O:P,2,FALSE) -> 1. Concluído | AR104: =+VLOOKUP(A104,Ficheiros!R:S,3,FALSE) -> #N/A | AS104: =+VLOOKUP(A104,Ficheiros!T:V,3,FALSE) -> #N/A
A105: =+C105&G105 -> ENTITYTXNMY_ELGBL_TRNVR_CCM | B105: EN.097 | C105: ENTITY | D105: General | E105: N | F105: TXNMY_ELGBL_TRNVR_CCM | G105: TXNMY_ELGBL_TRNVR_CCM | H105: N | I105: N | J105: N | K105: Y | L105: Y | M105: Y | N105: N | R105: FLOAT 6 decimal places | S105: Use decimal point, no thousands seperator | T105: 99999999999 | U105: 11111111111 | V105: 11111111111 | W105: Taxonomy-eligible Turnover (CCM) Ratio | X105: Counterparty’s reported proportion of Turnover eligible according to European Taxonomy and that might make a substantial contribution to an environmental objective of ‘Climate Change Mitigation’. | Y105: Not applicable | Z105: N/A | AA105: - | AB105: N | AC105: N | AD105: Y | AE105: N | AF105: N | AG105: N | AH105: N | AI105: Y | AJ105: Y | AK105: =+IF(AND(AD105="N",AF105="N"),"Fora de âmbito", IF(AND(AD105="N",AF105="Y"),"Apenas ESG Risk", IF(AND(AD105="Y",AF105="N"),"Apenas Pilar 3", IF(AND(AD105="Y",AF105="Y"),"Comum","")))) -> Apenas Pilar 3 | AL105: =+IF(IFERROR(VLOOKUP(A105,Ficheiros!I:I,1,FALSE),"")=A105,"Sim","Não") -> Não | AM105: =+IF(IFERROR(VLOOKUP(A105,Ficheiros!E:E,1,FALSE),"")=A105,"Sim","Não") -> Sim | AN105: =+IF(IFERROR(VLOOKUP(A105,Ficheiros!O:O,1,FALSE),"")=A105,"Sim","Não") -> Sim | AO105: =+IF(IFERROR(VLOOKUP(A105,'Especificação Novos Req. LT (2'!A:A,1,FALSE),"")=A105,"Sim","Não") -> Não | AP105: =+IF(IFERROR(VLOOKUP(A105,Ficheiros!T:T,1,FALSE),"")=A105,"Sim","Não") -> Não | AQ105: =+VLOOKUP(A105,Ficheiros!O:P,2,FALSE) -> 1. Concluído | AR105: =+VLOOKUP(A105,Ficheiros!R:S,3,FALSE) -> #N/A | AS105: =+VLOOKUP(A105,Ficheiros!T:V,3,FALSE) -> #N/A
A106: =+C106&G106 -> ENTITYTXNMY_ELGBL_CAPEX_CCA | B106: EN.098 | C106: ENTITY | D106: General | E106: N | F106: TXNMY_ELGBL_CAPEX_CCA | G106: TXNMY_ELGBL_CAPEX_CCA | H106: N | I106: N | J106: N | K106: Y | L106: Y | M106: Y | N106: N | R106: FLOAT 6 decimal places | S106: Use decimal point, no thousands seperator | T106: 99999999999 | U106: 11111111111 | V106: 11111111111 | W106: Taxonomy-eligible CAPEX (CCA) Ratio | X106: Counterparty’s reported proportion of CAPEX eligible according to European Taxonomy and that might make a substantial contribution to an environmental objective of ‘Climate Change Adaptation’. | Y106: Not applicable | Z106: N/A | AA106: - | AB106: N | AC106: N | AD106: Y | AE106: N | AF106: N | AG106: N | AH106: N | AI106: Y | AJ106: Y | AK106: =+IF(AND(AD106="N",AF106="N"),"Fora de âmbito", IF(AND(AD106="N",AF106="Y"),"Apenas ESG Risk", IF(AND(AD106="Y",AF106="N"),"Apenas Pilar 3", IF(AND(AD106="Y",AF106="Y"),"Comum","")))) -> Apenas Pilar 3 | AL106: =+IF(IFERROR(VLOOKUP(A106,Ficheiros!I:I,1,FALSE),"")=A106,"Sim","Não") -> Não | AM106: =+IF(IFERROR(VLOOKUP(A106,Ficheiros!E:E,1,FALSE),"")=A106,"Sim","Não") -> Sim | AN106: =+IF(IFERROR(VLOOKUP(A106,Ficheiros!O:O,1,FALSE),"")=A106,"Sim","Não") -> Sim | AO106: =+IF(IFERROR(VLOOKUP(A106,'Especificação Novos Req. LT (2'!A:A,1,FALSE),"")=A106,"Sim","Não") -> Não | AP106: =+IF(IFERROR(VLOOKUP(A106,Ficheiros!T:T,1,FALSE),"")=A106,"Sim","Não") -> Não | AQ106: =+VLOOKUP(A106,Ficheiros!O:P,2,FALSE) -> 1. Concluído | AR106: =+VLOOKUP(A106,Ficheiros!R:S,3,FALSE) -> #N/A | AS106: =+VLOOKUP(A106,Ficheiros!T:V,3,FALSE) -> #N/A
A107: =+C107&G107 -> ENTITYTXNMY_ELGBL_TRNVR_CCA | B107: EN.099 | C107: ENTITY | D107: General | E107: N | F107: TXNMY_ELGBL_TRNVR_CCA | G107: TXNMY_ELGBL_TRNVR_CCA | H107: N | I107: N | J107: N | K107: Y | L107: Y | M107: Y | N107: N | R107: FLOAT 6 decimal places | S107: Use decimal point, no thousands seperator | T107: 99999999999 | U107: 11111111111 | V107: 11111111111 | W107: Taxonomy-eligible Turnover (CCA) Ratio | X107: Counterparty’s reported proportion of Turnover eligible according to European Taxonomy and that might make a substantial contribution to an environmental objective of ‘Climate Change Adaptation’ | Y107: Not applicable | Z107: N/A | AA107: - | AB107: N | AC107: N | AD107: Y | AE107: N | AF107: N | AG107: N | AH107: N | AI107: Y | AJ107: Y | AK107: =+IF(AND(AD107="N",AF107="N"),"Fora de âmbito", IF(AND(AD107="N",AF107="Y"),"Apenas ESG Risk", IF(AND(AD107="Y",AF107="N"),"Apenas Pilar 3", IF(AND(AD107="Y",AF107="Y"),"Comum","")))) -> Apenas Pilar 3 | AL107: =+IF(IFERROR(VLOOKUP(A107,Ficheiros!I:I,1,FALSE),"")=A107,"Sim","Não") -> Não | AM107: =+IF(IFERROR(VLOOKUP(A107,Ficheiros!E:E,1,FALSE),"")=A107,"Sim","Não") -> Sim | AN107: =+IF(IFERROR(VLOOKUP(A107,Ficheiros!O:O,1,FALSE),"")=A107,"Sim","Não") -> Sim | AO107: =+IF(IFERROR(VLOOKUP(A107,'Especificação Novos Req. LT (2'!A:A,1,FALSE),"")=A107,"Sim","Não") -> Não | AP107: =+IF(IFERROR(VLOOKUP(A107,Ficheiros!T:T,1,FALSE),"")=A107,"Sim","Não") -> Não | AQ107: =+VLOOKUP(A107,Ficheiros!O:P,2,FALSE) -> 1. Concluído | AR107: =+VLOOKUP(A107,Ficheiros!R:S,3,FALSE) -> #N/A | AS107: =+VLOOKUP(A107,Ficheiros!T:V,3,FALSE) -> #N/A
A108: =+C108&G108 -> ENTITYENBLNG_CAPEX_CCM | B108: EN.100 | C108: ENTITY | D108: General | E108: N | F108: ENBLNG_CAPEX_CCM | G108: ENBLNG_CAPEX_CCM | H108: N | I108: N | J108: N | K108: Y | L108: Y | M108: Y | N108: N | R108: FLOAT 6 decimal places | S108: Use decimal point, no thousands seperator | T108: 99999999999 | U108: 11111111111 | V108: 11111111111 | W108: Taxonomy-aligned CAPEX (CCM) - Enabling Ratio | X108: Counterparty’s proportion of CAPEX that is Taxonomy-aligned under CCM objective and that enables other activities to make a substantial contribution to one or more of these objectives. | Y108: Not applicable | Z108: N/A | AA108: - | AB108: N | AC108: N | AD108: Y | AE108: N | AF108: N | AG108: N | AH108: N | AI108: Y | AJ108: Y | AK108: =+IF(AND(AD108="N",AF108="N"),"Fora de âmbito", IF(AND(AD108="N",AF108="Y"),"Apenas ESG Risk", IF(AND(AD108="Y",AF108="N"),"Apenas Pilar 3", IF(AND(AD108="Y",AF108="Y"),"Comum","")))) -> Apenas Pilar 3 | AL108: =+IF(IFERROR(VLOOKUP(A108,Ficheiros!I:I,1,FALSE),"")=A108,"Sim","Não") -> Não | AM108: =+IF(IFERROR(VLOOKUP(A108,Ficheiros!E:E,1,FALSE),"")=A108,"Sim","Não") -> Sim | AN108: =+IF(IFERROR(VLOOKUP(A108,Ficheiros!O:O,1,FALSE),"")=A108,"Sim","Não") -> Sim | AO108: =+IF(IFERROR(VLOOKUP(A108,'Especificação Novos Req. LT (2'!A:A,1,FALSE),"")=A108,"Sim","Não") -> Não | AP108: =+IF(IFERROR(VLOOKUP(A108,Ficheiros!T:T,1,FALSE),"")=A108,"Sim","Não") -> Não | AQ108: =+VLOOKUP(A108,Ficheiros!O:P,2,FALSE) -> 1. Concluído | AR108: =+VLOOKUP(A108,Ficheiros!R:S,3,FALSE) -> #N/A | AS108: =+VLOOKUP(A108,Ficheiros!T:V,3,FALSE) -> #N/A
A109: =+C109&G109 -> ENTITYENBLNG_CAPEX_CCA | B109: EN.101 | C109: ENTITY | D109: General | E109: N | F109: ENBLNG_CAPEX_CCA | G109: ENBLNG_CAPEX_CCA | H109: N | I109: N | J109: N | K109: Y | L109: Y | M109: Y | N109: N | R109: FLOAT 6 decimal places | S109: Use decimal point, no thousands seperator | T109: 99999999999 | U109: 11111111111 | V109: 11111111111 | W109: Taxonomy-aligned CAPEX (CCA) - Enabling Ratio | X109: Counterparty’s proportion of CAPEX that is Taxonomy-aligned under CCA objective and that enables other activities to make a substantial contribution to one or more of these objectives. | Y109: Not applicable | Z109: N/A | AA109: - | AB109: N | AC109: N | AD109: Y | AE109: N | AF109: N | AG109: N | AH109: N | AI109: Y | AJ109: Y | AK109: =+IF(AND(AD109="N",AF109="N"),"Fora de âmbito", IF(AND(AD109="N",AF109="Y"),"Apenas ESG Risk", IF(AND(AD109="Y",AF109="N"),"Apenas Pilar 3", IF(AND(AD109="Y",AF109="Y"),"Comum","")))) -> Apenas Pilar 3 | AL109: =+IF(IFERROR(VLOOKUP(A109,Ficheiros!I:I,1,FALSE),"")=A109,"Sim","Não") -> Não | AM109: =+IF(IFERROR(VLOOKUP(A109,Ficheiros!E:E,1,FALSE),"")=A109,"Sim","Não") -> Sim | AN109: =+IF(IFERROR(VLOOKUP(A109,Ficheiros!O:O,1,FALSE),"")=A109,"Sim","Não") -> Sim | AO109: =+IF(IFERROR(VLOOKUP(A109,'Especificação Novos Req. LT (2'!A:A,1,FALSE),"")=A109,"Sim","Não") -> Não | AP109: =+IF(IFERROR(VLOOKUP(A109,Ficheiros!T:T,1,FALSE),"")=A109,"Sim","Não") -> Não | AQ109: =+VLOOKUP(A109,Ficheiros!O:P,2,FALSE) -> 1. Concluído | AR109: =+VLOOKUP(A109,Ficheiros!R:S,3,FALSE) -> #N/A | AS109: =+VLOOKUP(A109,Ficheiros!T:V,3,FALSE) -> #N/A
A110: =+C110&G110 -> ENTITYTRNSTNL_CAPEX | B110: EN.102 | C110: ENTITY | D110: General | E110: N | F110: TRNSTNL_CAPEX | G110: TRNSTNL_CAPEX | H110: N | I110: N | J110: N | K110: Y | L110: Y | M110: Y | N110: N | R110: FLOAT 6 decimal places | S110: Use decimal point, no thousands seperator | T110: 99999999999 | U110: 11111111111 | V110: 11111111111 | W110: Taxonomy-aligned CAPEX (CCM) - Transitional Ratio | X110: Counterparty’s proportion of CAPEX that is Taxonomy-aligned under CCM objective and dedicated to transition activities. | Y110: Not applicable | Z110: N/A | AA110: - | AB110: N | AC110: N | AD110: Y | AE110: N | AF110: N | AG110: N | AH110: N | AI110: Y | AJ110: Y | AK110: =+IF(AND(AD110="N",AF110="N"),"Fora de âmbito", IF(AND(AD110="N",AF110="Y"),"Apenas ESG Risk", IF(AND(AD110="Y",AF110="N"),"Apenas Pilar 3", IF(AND(AD110="Y",AF110="Y"),"Comum","")))) -> Apenas Pilar 3 | AL110: =+IF(IFERROR(VLOOKUP(A110,Ficheiros!I:I,1,FALSE),"")=A110,"Sim","Não") -> Não | AM110: =+IF(IFERROR(VLOOKUP(A110,Ficheiros!E:E,1,FALSE),"")=A110,"Sim","Não") -> Sim | AN110: =+IF(IFERROR(VLOOKUP(A110,Ficheiros!O:O,1,FALSE),"")=A110,"Sim","Não") -> Sim | AO110: =+IF(IFERROR(VLOOKUP(A110,'Especificação Novos Req. LT (2'!A:A,1,FALSE),"")=A110,"Sim","Não") -> Não | AP110: =+IF(IFERROR(VLOOKUP(A110,Ficheiros!T:T,1,FALSE),"")=A110,"Sim","Não") -> Não | AQ110: =+VLOOKUP(A110,Ficheiros!O:P,2,FALSE) -> 1. Concluído | AR110: =+VLOOKUP(A110,Ficheiros!R:S,3,FALSE) -> #N/A | AS110: =+VLOOKUP(A110,Ficheiros!T:V,3,FALSE) -> #N/A
A111: =+C111&G111 -> ENTITYPURE_CAPEX_CCM | B111: EN.103 | C111: ENTITY | D111: General | E111: N | F111: PURE_CAPEX_CCM | G111: PURE_CAPEX_CCM | H111: N | I111: N | J111: N | K111: Y | L111: Y | M111: Y | N111: N | R111: FLOAT 6 decimal places | S111: Use decimal point, no thousands seperator | T111: 99999999999 | U111: 11111111111 | V111: 11111111111 | W111: Taxonomy-aligned CAPEX (CCM) - Pure Ratio | X111: Counterparty’s proportion of CAPEX that is Taxonomy-aligned under CCM objective and contributes substantially to the objective of climate change mitigation | Y111: Not applicable | Z111: N/A | AA111: - | AB111: N | AC111: N | AD111: Y | AE111: N | AF111: N | AG111: N | AH111: N | AI111: Y | AJ111: Y | AK111: =+IF(AND(AD111="N",AF111="N"),"Fora de âmbito", IF(AND(AD111="N",AF111="Y"),"Apenas ESG Risk", IF(AND(AD111="Y",AF111="N"),"Apenas Pilar 3", IF(AND(AD111="Y",AF111="Y"),"Comum","")))) -> Apenas Pilar 3 | AL111: =+IF(IFERROR(VLOOKUP(A111,Ficheiros!I:I,1,FALSE),"")=A111,"Sim","Não") -> Não | AM111: =+IF(IFERROR(VLOOKUP(A111,Ficheiros!E:E,1,FALSE),"")=A111,"Sim","Não") -> Sim | AN111: =+IF(IFERROR(VLOOKUP(A111,Ficheiros!O:O,1,FALSE),"")=A111,"Sim","Não") -> Sim | AO111: =+IF(IFERROR(VLOOKUP(A111,'Especificação Novos Req. LT (2'!A:A,1,FALSE),"")=A111,"Sim","Não") -> Não | AP111: =+IF(IFERROR(VLOOKUP(A111,Ficheiros!T:T,1,FALSE),"")=A111,"Sim","Não") -> Não | AQ111: =+VLOOKUP(A111,Ficheiros!O:P,2,FALSE) -> 1. Concluído | AR111: =+VLOOKUP(A111,Ficheiros!R:S,3,FALSE) -> #N/A | AS111: =+VLOOKUP(A111,Ficheiros!T:V,3,FALSE) -> #N/A
A112: =+C112&G112 -> ENTITYPURE_CAPEX_CCA | B112: EN.104 | C112: ENTITY | D112: General | E112: N | F112: PURE_CAPEX_CCA | G112: PURE_CAPEX_CCA | H112: N | I112: N | J112: N | K112: Y | L112: Y | M112: Y | N112: N | R112: FLOAT 6 decimal places | S112: Use decimal point, no thousands seperator | T112: 99999999999 | U112: 11111111111 | V112: 11111111111 | W112: Taxonomy-aligned CAPEX (CCA) - Pure Ratio | X112: Counterparty’s proportion of CAPEX that is Taxonomy-aligned under CCA objective and contributes substantially to the objective of climate change adaptation | Y112: Not applicable | Z112: N/A | AA112: - | AB112: N | AC112: N | AD112: Y | AE112: N | AF112: N | AG112: N | AH112: N | AI112: Y | AJ112: Y | AK112: =+IF(AND(AD112="N",AF112="N"),"Fora de âmbito", IF(AND(AD112="N",AF112="Y"),"Apenas ESG Risk", IF(AND(AD112="Y",AF112="N"),"Apenas Pilar 3", IF(AND(AD112="Y",AF112="Y"),"Comum","")))) -> Apenas Pilar 3 | AL112: =+IF(IFERROR(VLOOKUP(A112,Ficheiros!I:I,1,FALSE),"")=A112,"Sim","Não") -> Não | AM112: =+IF(IFERROR(VLOOKUP(A112,Ficheiros!E:E,1,FALSE),"")=A112,"Sim","Não") -> Sim | AN112: =+IF(IFERROR(VLOOKUP(A112,Ficheiros!O:O,1,FALSE),"")=A112,"Sim","Não") -> Sim | AO112: =+IF(IFERROR(VLOOKUP(A112,'Especificação Novos Req. LT (2'!A:A,1,FALSE),"")=A112,"Sim","Não") -> Não | AP112: =+IF(IFERROR(VLOOKUP(A112,Ficheiros!T:T,1,FALSE),"")=A112,"Sim","Não") -> Não | AQ112: =+VLOOKUP(A112,Ficheiros!O:P,2,FALSE) -> 1. Concluído | AR112: =+VLOOKUP(A112,Ficheiros!R:S,3,FALSE) -> #N/A | AS112: =+VLOOKUP(A112,Ficheiros!T:V,3,FALSE) -> #N/A
A113: =+C113&G113 -> ENTITYENBLNG_TRNVR_CCM | B113: EN.105 | C113: ENTITY | D113: General | E113: N | F113: ENBLNG_TRNVR_CCM | G113: ENBLNG_TRNVR_CCM | H113: N | I113: N | J113: N | K113: Y | L113: Y | M113: Y | N113: N | R113: FLOAT 6 decimal places | S113: Use decimal point, no thousands seperator | T113: 99999999999 | U113: 11111111111 | V113: 11111111111 | W113: Taxonomy-aligned Turnover (CCM) - Enabling Ratio | X113: Counterparty’s proportion of Turnover that is Taxonomy-aligned under CCM objective and that enables other activities to make a substantial contribution to one or more of these objectives. | Y113: Not applicable | Z113: N/A | AA113: - | AB113: N | AC113: N | AD113: Y | AE113: N | AF113: N | AG113: N | AH113: N | AI113: Y | AJ113: Y | AK113: =+IF(AND(AD113="N",AF113="N"),"Fora de âmbito", IF(AND(AD113="N",AF113="Y"),"Apenas ESG Risk", IF(AND(AD113="Y",AF113="N"),"Apenas Pilar 3", IF(AND(AD113="Y",AF113="Y"),"Comum","")))) -> Apenas Pilar 3 | AL113: =+IF(IFERROR(VLOOKUP(A113,Ficheiros!I:I,1,FALSE),"")=A113,"Sim","Não") -> Não | AM113: =+IF(IFERROR(VLOOKUP(A113,Ficheiros!E:E,1,FALSE),"")=A113,"Sim","Não") -> Sim | AN113: =+IF(IFERROR(VLOOKUP(A113,Ficheiros!O:O,1,FALSE),"")=A113,"Sim","Não") -> Sim | AO113: =+IF(IFERROR(VLOOKUP(A113,'Especificação Novos Req. LT (2'!A:A,1,FALSE),"")=A113,"Sim","Não") -> Não | AP113: =+IF(IFERROR(VLOOKUP(A113,Ficheiros!T:T,1,FALSE),"")=A113,"Sim","Não") -> Não | AQ113: =+VLOOKUP(A113,Ficheiros!O:P,2,FALSE) -> 1. Concluído | AR113: =+VLOOKUP(A113,Ficheiros!R:S,3,FALSE) -> #N/A | AS113: =+VLOOKUP(A113,Ficheiros!T:V,3,FALSE) -> #N/A
A114: =+C114&G114 -> ENTITYENBLNG_TRNVR_CCA | B114: EN.106 | C114: ENTITY | D114: General | E114: N | F114: ENBLNG_TRNVR_CCA | G114: ENBLNG_TRNVR_CCA | H114: N | I114: N | J114: N | K114: Y | L114: Y | M114: Y | N114: N | R114: FLOAT 6 decimal places | S114: Use decimal point, no thousands seperator | T114: 99999999999 | U114: 11111111111 | V114: 11111111111 | W114: Taxonomy-aligned Turnover (CCA) - Enabling Ratio | X114: Counterparty’s proportion of Turnover that is Taxonomy-aligned under CCA objective and that enables other activities to make a substantial contribution to one or more of these objectives. | Y114: Not applicable | Z114: N/A | AA114: - | AB114: N | AC114: N | AD114: Y | AE114: N | AF114: N | AG114: N | AH114: N | AI114: Y | AJ114: Y | AK114: =+IF(AND(AD114="N",AF114="N"),"Fora de âmbito", IF(AND(AD114="N",AF114="Y"),"Apenas ESG Risk", IF(AND(AD114="Y",AF114="N"),"Apenas Pilar 3", IF(AND(AD114="Y",AF114="Y"),"Comum","")))) -> Apenas Pilar 3 | AL114: =+IF(IFERROR(VLOOKUP(A114,Ficheiros!I:I,1,FALSE),"")=A114,"Sim","Não") -> Não | AM114: =+IF(IFERROR(VLOOKUP(A114,Ficheiros!E:E,1,FALSE),"")=A114,"Sim","Não") -> Sim | AN114: =+IF(IFERROR(VLOOKUP(A114,Ficheiros!O:O,1,FALSE),"")=A114,"Sim","Não") -> Sim | AO114: =+IF(IFERROR(VLOOKUP(A114,'Especificação Novos Req. LT (2'!A:A,1,FALSE),"")=A114,"Sim","Não") -> Não | AP114: =+IF(IFERROR(VLOOKUP(A114,Ficheiros!T:T,1,FALSE),"")=A114,"Sim","Não") -> Não | AQ114: =+VLOOKUP(A114,Ficheiros!O:P,2,FALSE) -> 1. Concluído | AR114: =+VLOOKUP(A114,Ficheiros!R:S,3,FALSE) -> #N/A | AS114: =+VLOOKUP(A114,Ficheiros!T:V,3,FALSE) -> #N/A
... A117: =+C117&G117 -> ENTITYPURE_TRNVR_CCA | B117: EN.109 | C117: ENTITY | D117: General | E117: N | F117: PURE_TRNVR_CCA | G117: PURE_TRNVR_CCA | H117: N | I117: N | J117: N | K117: Y | L117: Y | M117: Y | N117: N | R117: FLOAT 6 decimal places | S117: Use decimal point, no thousands seperator | T117: 99999999999 | U117: 11111111111 | V117: 11111111111 | W117: Taxonomy-aligned turnover (CCA) - Pure Ratio | X117: Counterparty’s proportion of turnover that is Taxonomy-aligned under CCA objective and contributes substantially to the objective of climate change adaptation | Y117: Not applicable | Z117: N/A | AA117: - | AB117: N | AC117: N | AD117: Y | AE117: N | AF117: N | AG117: N | AH117: N | AI117: Y | AJ117: Y | AK117: =+IF(AND(AD117="N",AF117="N"),"Fora de âmbito", IF(AND(AD117="N",AF117="Y"),"Apenas ESG Risk", IF(AND(AD117="Y",AF117="N"),"Apenas Pilar 3", IF(AND(AD117="Y",AF117="Y"),"Comum","")))) -> Apenas Pilar 3 | AL117: =+IF(IFERROR(VLOOKUP(A117,Ficheiros!I:I,1,FALSE),"")=A117,"Sim","Não") -> Não | AM117: =+IF(IFERROR(VLOOKUP(A117,Ficheiros!E:E,1,FALSE),"")=A117,"Sim","Não") -> Sim | AN117: =+IF(IFERROR(VLOOKUP(A117,Ficheiros!O:O,1,FALSE),"")=A117,"Sim","Não") -> Sim | AO117: =+IF(IFERROR(VLOOKUP(A117,'Especificação Novos Req. LT (2'!A:A,1,FALSE),"")=A117,"Sim","Não") -> Não | AP117: =+IF(IFERROR(VLOOKUP(A117,Ficheiros!T:T,1,FALSE),"")=A117,"Sim","Não") -> Não | AQ117: =+VLOOKUP(A117,Ficheiros!O:P,2,FALSE) -> 1. Concluído | AR117: =+VLOOKUP(A117,Ficheiros!R:S,3,FALSE) -> #N/A | AS117: =+VLOOKUP(A117,Ficheiros!T:V,3,FALSE) -> #N/A
A118: =+C118&G118 -> ENTITYFLG_NFRD_APPLCBLTY | B118: EN.110 | C118: ENTITY | D118: Classification | E118: N | F118: FLG_CSRD_APPLCBLTY | G118: FLG_NFRD_APPLCBLTY | H118: N | I118: N | J118: N | K118: Y | L118: Y | M118: Y | N118: N | R118: Y, N | S118: Boolean: Y/N | T118: MISS | U118: Default value not allowed | V118: N/A | W118: Flag of CSRD applicability at counterparty level | X118: The Corporate Sustainability Reporting Directive (CSRD) requires a progressive certain amount of companies to disclose information on the way they operate and manage social and environmental challenges. The purpose of the “flag of CSRD applicability at counterparty level” is to identify which counterparties qualify to be subject to disclose a Non-Financial Report. | Y118: Not applicable | Z118: N/A | AA118: - | AB118: N | AC118: N | AD118: Y | AE118: N | AF118: Y | AG118: N | AH118: N | AI118: Y | AJ118: Y | AK118: =+IF(AND(AD118="N",AF118="N"),"Fora de âmbito", IF(AND(AD118="N",AF118="Y"),"Apenas ESG Risk", IF(AND(AD118="Y",AF118="N"),"Apenas Pilar 3", IF(AND(AD118="Y",AF118="Y"),"Comum","")))) -> Comum | AL118: =+IF(IFERROR(VLOOKUP(A118,Ficheiros!I:I,1,FALSE),"")=A118,"Sim","Não") -> Não | AM118: =+IF(IFERROR(VLOOKUP(A118,Ficheiros!E:E,1,FALSE),"")=A118,"Sim","Não") -> Sim | AN118: =+IF(IFERROR(VLOOKUP(A118,Ficheiros!O:O,1,FALSE),"")=A118,"Sim","Não") -> Sim | AO118: =+IF(IFERROR(VLOOKUP(A118,'Especificação Novos Req. LT (2'!A:A,1,FALSE),"")=A118,"Sim","Não") -> Não | AP118: =+IF(IFERROR(VLOOKUP(A118,Ficheiros!T:T,1,FALSE),"")=A118,"Sim","Não") -> Não | AQ118: =+VLOOKUP(A118,Ficheiros!O:P,2,FALSE) -> 1. Concluído | AR118: =+VLOOKUP(A118,Ficheiros!R:S,3,FALSE) -> #N/A | AS118: =+VLOOKUP(A118,Ficheiros!T:V,3,FALSE) -> #N/A
A119: =+C119&G119 -> ENTITYFLG_GRP_NFRD_APPLCBLTY | B119: EN.111 | C119: ENTITY | D119: Classification | E119: N | F119: FLG_GRP_CSRD_APPLCBLTY | G119: FLG_GRP_NFRD_APPLCBLTY | H119: N | I119: N | J119: N | K119: Y | L119: Y | M119: Y | N119: N | R119: Y, N | S119: Boolean: Y/N | T119: MISS | U119: Default value not allowed | V119: N/A | W119: Flag of CSRD applicability at Group Level | X119: The Corporate Sustainability Reporting Directive (CSRD) requires a progressive certain amount of companies to disclose information on the way they operate and manage social and environmental challenges. The purpose of the “flag of CSRD applicability at group level” is to identify which Groups qualify to be subject to disclose a Non-Financial Report. | Y119: Not applicable | Z119: N/A | AA119: - | AB119: N | AC119: N | AD119: Y | AE119: N | AF119: Y | AG119: N | AH119: N | AI119: Y | AJ119: Y | AK119: =+IF(AND(AD119="N",AF119="N"),"Fora de âmbito", IF(AND(AD119="N",AF119="Y"),"Apenas ESG Risk", IF(AND(AD119="Y",AF119="N"),"Apenas Pilar 3", IF(AND(AD119="Y",AF119="Y"),"Comum","")))) -> Comum | AL119: =+IF(IFERROR(VLOOKUP(A119,Ficheiros!I:I,1,FALSE),"")=A119,"Sim","Não") -> Não | AM119: =+IF(IFERROR(VLOOKUP(A119,Ficheiros!E:E,1,FALSE),"")=A119,"Sim","Não") -> Sim | AN119: =+IF(IFERROR(VLOOKUP(A119,Ficheiros!O:O,1,FALSE),"")=A119,"Sim","Não") -> Sim | AO119: =+IF(IFERROR(VLOOKUP(A119,'Especificação Novos Req. LT (2'!A:A,1,FALSE),"")=A119,"Sim","Não") -> Não | AP119: =+IF(IFERROR(VLOOKUP(A119,Ficheiros!T:T,1,FALSE),"")=A119,"Sim","Não") -> Não | AQ119: =+VLOOKUP(A119,Ficheiros!O:P,2,FALSE) -> 1. Concluído | AR119: =+VLOOKUP(A119,Ficheiros!R:S,3,FALSE) -> #N/A | AS119: =+VLOOKUP(A119,Ficheiros!T:V,3,FALSE) -> #N/A
A120: =+C120&G120 -> ENTITYISIN | B120: EN.112 | C120: ENTITY | D120: Issuer identification | E120: N | F120: ISIN | G120: ISIN | H120: N | I120: Y | J120: N | K120: Y | L120: N | M120: Y | N120: N | R120: VARCHAR(12) | S120: Free (latin) text without special characters (semicolon, quotes, …) | T120: MISS | U120: N/A | V120: N/A | W120: ISIN | X120: International Securities Identification Number (ISIN) at entity level. | Y120: Not applicable | Z120: N/A | AA120: - | AB120: N | AC120: N | AD120: Y | AE120: N | AF120: N | AG120: N | AH120: N | AI120: Y | AJ120: Y | AK120: =+IF(AND(AD120="N",AF120="N"),"Fora de âmbito", IF(AND(AD120="N",AF120="Y"),"Apenas ESG Risk", IF(AND(AD120="Y",AF120="N"),"Apenas Pilar 3", IF(AND(AD120="Y",AF120="Y"),"Comum","")))) -> Apenas Pilar 3 | AL120: =+IF(IFERROR(VLOOKUP(A120,Ficheiros!I:I,1,FALSE),"")=A120,"Sim","Não") -> Não | AM120: =+IF(IFERROR(VLOOKUP(A120,Ficheiros!E:E,1,FALSE),"")=A120,"Sim","Não") -> Sim | AN120: =+IF(IFERROR(VLOOKUP(A120,Ficheiros!O:O,1,FALSE),"")=A120,"Sim","Não") -> Sim | AO120: =+IF(IFERROR(VLOOKUP(A120,'Especificação Novos Req. LT (2'!A:A,1,FALSE),"")=A120,"Sim","Não") -> Não | AP120: =+IF(IFERROR(VLOOKUP(A120,Ficheiros!T:T,1,FALSE),"")=A120,"Sim","Não") -> Não | AQ120: =+VLOOKUP(A120,Ficheiros!O:P,2,FALSE) -> 1. Concluído | AR120: =+VLOOKUP(A120,Ficheiros!R:S,3,FALSE) -> #N/A | AS120: =+VLOOKUP(A120,Ficheiros!T:V,3,FALSE) -> #N/A
A121: =+C121&G121 -> ENTITYGRP_ANNL_TRNVR_LE | B121: EN.113 | C121: ENTITY | D121: Financial Information | E121: N | F121: GRP_ANNL_TRNVR_LE | G121: GRP_ANNL_TRNVR_LE | H121: Y | I121: Y | J121: Y | K121: Y | L121: Y | M121: Y | N121: N | R121: FLOAT 2 decimal places | S121: Use decimal point, no thousands seperator | T121: 99999999999 | U121: 11111111111 | V121: 11111111111 | W121: Group's annual turnover (LE) | X121: Annual sales volume net of all discounts and sales taxes in accordance with Recommendation 2003/361/EC. Equivalent to the concept of 'total annual sales' in Article 153(4) of Regulation (EU) No 575/2013. Please report at group level | Y121: Not applicable | Z121: N/A | AA121: - | AB121: N | AC121: N | AD121: Y | AE121: N | AF121: N | AG121: N | AH121: N | AI121: Y | AJ121: Y | AK121: =+IF(AND(AD121="N",AF121="N"),"Fora de âmbito", IF(AND(AD121="N",AF121="Y"),"Apenas ESG Risk", IF(AND(AD121="Y",AF121="N"),"Apenas Pilar 3", IF(AND(AD121="Y",AF121="Y"),"Comum","")))) -> Apenas Pilar 3 | AL121: =+IF(IFERROR(VLOOKUP(A121,Ficheiros!I:I,1,FALSE),"")=A121,"Sim","Não") -> Não | AM121: =+IF(IFERROR(VLOOKUP(A121,Ficheiros!E:E,1,FALSE),"")=A121,"Sim","Não") -> Sim | AN121: =+IF(IFERROR(VLOOKUP(A121,Ficheiros!O:O,1,FALSE),"")=A121,"Sim","Não") -> Sim | AO121: =+IF(IFERROR(VLOOKUP(A121,'Especificação Novos Req. LT (2'!A:A,1,FALSE),"")=A121,"Sim","Não") -> Não | AP121: =+IF(IFERROR(VLOOKUP(A121,Ficheiros!T:T,1,FALSE),"")=A121,"Sim","Não") -> Não | AQ121: =+VLOOKUP(A121,Ficheiros!O:P,2,FALSE) -> 1. Concluído | AR121: =+VLOOKUP(A121,Ficheiros!R:S,3,FALSE) -> #N/A | AS121: =+VLOOKUP(A121,Ficheiros!T:V,3,FALSE) -> #N/A
A122: =+C122&G122 -> ENTITYGRP_TTL_LBLTY | B122: EN.114 | C122: ENTITY | D122: Financial Information | E122: N | F122: GRP_TTL_LBLTY | G122: GRP_TTL_LBLTY | H122: Y | I122: Y | J122: Y | K122: Y | L122: Y | M122: Y | N122: N | R122: FLOAT 2 decimal places | S122: Use decimal point, no thousands seperator | T122: 99999999999 | U122: 11111111111 | V122: 11111111111 | W122: Group's total liability at most recent reported figures | X122: Total liability at most recent reported figures. Please report level of the consolidated financial statement of the group accoding to the applicable accounting standard. | Y122: Not applicable | Z122: N/A | AA122: - | AB122: N | AC122: N | AD122: Y | AE122: N | AF122: N | AG122: N | AH122: N | AI122: Y | AJ122: Y | AK122: =+IF(AND(AD122="N",AF122="N"),"Fora de âmbito", IF(AND(AD122="N",AF122="Y"),"Apenas ESG Risk", IF(AND(AD122="Y",AF122="N"),"Apenas Pilar 3", IF(AND(AD122="Y",AF122="Y"),"Comum","")))) -> Apenas Pilar 3 | AL122: =+IF(IFERROR(VLOOKUP(A122,Ficheiros!I:I,1,FALSE),"")=A122,"Sim","Não") -> Não | AM122: =+IF(IFERROR(VLOOKUP(A122,Ficheiros!E:E,1,FALSE),"")=A122,"Sim","Não") -> Sim | AN122: =+IF(IFERROR(VLOOKUP(A122,Ficheiros!O:O,1,FALSE),"")=A122,"Sim","Não") -> Sim | AO122: =+IF(IFERROR(VLOOKUP(A122,'Especificação Novos Req. LT (2'!A:A,1,FALSE),"")=A122,"Sim","Não") -> Não | AP122: =+IF(IFERROR(VLOOKUP(A122,Ficheiros!T:T,1,FALSE),"")=A122,"Sim","Não") -> Não | AQ122: =+VLOOKUP(A122,Ficheiros!O:P,2,FALSE) -> 1. Concluído | AR122: =+VLOOKUP(A122,Ficheiros!R:S,3,FALSE) -> #N/A | AS122: =+VLOOKUP(A122,Ficheiros!T:V,3,FALSE) -> #N/A
A123: =+C123&G123 -> ENTITYCNTRPRTY_EMSSNS_SCP1 | B123: EN.115 | C123: ENTITY | D123: General | E123: N | F123: CNTRPRTY_EMSSNS_SCP1 | G123: CNTRPRTY_EMSSNS_SCP1 | H123: N | I123: N | J123: N | K123: N | L123: N | M123: Y | N123: N | R123: FLOAT 6 decimal places | S123: Use decimal point, no thousands seperator | T123: 99999999999 | U123: 11111111111 | V123: 11111111111 | W123: Counterparty's emissions scope 1 | X123: Scope 1 emissions corresponding to the Counterparty | Y123: Not applicable | Z123: N/A | AA123: - | AB123: N | AC123: N | AD123: Y | AE123: N | AF123: Y | AG123: N | AH123: N | AI123: Y | AJ123: Y | AK123: =+IF(AND(AD123="N",AF123="N"),"Fora de âmbito", IF(AND(AD123="N",AF123="Y"),"Apenas ESG Risk", IF(AND(AD123="Y",AF123="N"),"Apenas Pilar 3", IF(AND(AD123="Y",AF123="Y"),"Comum","")))) -> Comum | AL123: =+IF(IFERROR(VLOOKUP(A123,Ficheiros!I:I,1,FALSE),"")=A123,"Sim","Não") -> Não | AM123: =+IF(IFERROR(VLOOKUP(A123,Ficheiros!E:E,1,FALSE),"")=A123,"Sim","Não") -> Sim | AN123: =+IF(IFERROR(VLOOKUP(A123,Ficheiros!O:O,1,FALSE),"")=A123,"Sim","Não") -> Sim | AO123: =+IF(IFERROR(VLOOKUP(A123,'Especificação Novos Req. LT (2'!A:A,1,FALSE),"")=A123,"Sim","Não") -> Não | AP123: =+IF(IFERROR(VLOOKUP(A123,Ficheiros!T:T,1,FALSE),"")=A123,"Sim","Não") -> Não | AQ123: =+VLOOKUP(A123,Ficheiros!O:P,2,FALSE) -> 1. Concluído | AR123: =+VLOOKUP(A123,Ficheiros!R:S,3,FALSE) -> #N/A | AS123: =+VLOOKUP(A123,Ficheiros!T:V,3,FALSE) -> #N/A
A124: =+C124&G124 -> ENTITYCNTRPRTY_EMSSNS_SCP2 | B124: EN.116 | C124: ENTITY | D124: General | E124: N | F124: CNTRPRTY_EMSSNS_SCP2 | G124: CNTRPRTY_EMSSNS_SCP2 | H124: N | I124: N | J124: N | K124: N | L124: N | M124: Y | N124: N | R124: FLOAT 6 decimal places | S124: Use decimal point, no thousands seperator | T124: 99999999999 | U124: 11111111111 | V124: 11111111111 | W124: Counterparty's emissions scope 2 | X124: Scope 2 emissions corresponding to the Counterparty | Y124: Not applicable | Z124: N/A | AA124: - | AB124: N | AC124: N | AD124: Y | AE124: N | AF124: Y | AG124: N | AH124: N | AI124: Y | AJ124: Y | AK124: =+IF(AND(AD124="N",AF124="N"),"Fora de âmbito", IF(AND(AD124="N",AF124="Y"),"Apenas ESG Risk", IF(AND(AD124="Y",AF124="N"),"Apenas Pilar 3", IF(AND(AD124="Y",AF124="Y"),"Comum","")))) -> Comum | AL124: =+IF(IFERROR(VLOOKUP(A124,Ficheiros!I:I,1,FALSE),"")=A124,"Sim","Não") -> Não | AM124: =+IF(IFERROR(VLOOKUP(A124,Ficheiros!E:E,1,FALSE),"")=A124,"Sim","Não") -> Sim | AN124: =+IF(IFERROR(VLOOKUP(A124,Ficheiros!O:O,1,FALSE),"")=A124,"Sim","Não") -> Sim | AO124: =+IF(IFERROR(VLOOKUP(A124,'Especificação Novos Req. LT (2'!A:A,1,FALSE),"")=A124,"Sim","Não") -> Não | AP124: =+IF(IFERROR(VLOOKUP(A124,Ficheiros!T:T,1,FALSE),"")=A124,"Sim","Não") -> Não | AQ124: =+VLOOKUP(A124,Ficheiros!O:P,2,FALSE) -> 1. Concluído | AR124: =+VLOOKUP(A124,Ficheiros!R:S,3,FALSE) -> #N/A | AS124: =+VLOOKUP(A124,Ficheiros!T:V,3,FALSE) -> #N/A
A125: =+C125&G125 -> ENTITYCNTRPRTY_EMSSNS_SCP3 | B125: EN.117 | C125: ENTITY | D125: General | E125: N | F125: CNTRPRTY_EMSSNS_SCP3 | G125: CNTRPRTY_EMSSNS_SCP3 | H125: N | I125: N | J125: N | K125: N | L125: N | M125: Y | N125: N | R125: FLOAT 6 decimal places | S125: Use decimal point, no thousands seperator | T125: 99999999999 | U125: 11111111111 | V125: 11111111111 | W125: Counterparty's emissions scope 3 | X125: Scope 3 emissions corresponding to the Counterparty | Y125: Not applicable | Z125: N/A | AA125: - | AB125: N | AC125: N | AD125: Y | AE125: N | AF125: Y | AG125: N | AH125: N | AI125: Y | AJ125: Y | AK125: =+IF(AND(AD125="N",AF125="N"),"Fora de âmbito", IF(AND(AD125="N",AF125="Y"),"Apenas ESG Risk", IF(AND(AD125="Y",AF125="N"),"Apenas Pilar 3", IF(AND(AD125="Y",AF125="Y"),"Comum","")))) -> Comum | AL125: =+IF(IFERROR(VLOOKUP(A125,Ficheiros!I:I,1,FALSE),"")=A125,"Sim","Não") -> Não | AM125: =+IF(IFERROR(VLOOKUP(A125,Ficheiros!E:E,1,FALSE),"")=A125,"Sim","Não") -> Sim | AN125: =+IF(IFERROR(VLOOKUP(A125,Ficheiros!O:O,1,FALSE),"")=A125,"Sim","Não") -> Sim | AO125: =+IF(IFERROR(VLOOKUP(A125,'Especificação Novos Req. LT (2'!A:A,1,FALSE),"")=A125,"Sim","Não") -> Não | AP125: =+IF(IFERROR(VLOOKUP(A125,Ficheiros!T:T,1,FALSE),"")=A125,"Sim","Não") -> Não | AQ125: =+VLOOKUP(A125,Ficheiros!O:P,2,FALSE) -> 1. Concluído | AR125: =+VLOOKUP(A125,Ficheiros!R:S,3,FALSE) -> #N/A | AS125: =+VLOOKUP(A125,Ficheiros!T:V,3,FALSE) -> #N/A
A126: =+C126&G126 -> ENTITYFLG_EXCLDD_EU_PRS_ALGND_BNCHMRK | B126: EN.118 | C126: ENTITY | D126: General | E126: N | F126: FLG_EXCLDD_EU_PRS_ALGND_BNCHMRK | G126: FLG_EXCLDD_EU_PRS_ALGND_BNCHMRK | H126: N | I126: N | J126: N | K126: N | L126: N | M126: Y | N126: N | R126: Y, N | S126: Boolean: Y/N | T126: MISS | U126: Default value not allowed | V126: N/A | W126: Flag Excluded from EU Paris-aligned benchmark | X126: This flag allows to identify whether the entity is excluded from the EU Paris-aligned benchmark | Y126: Not applicable | Z126: N/A | AA126: - | AB126: N | AC126: N | AD126: Y | AE126: N | AF126: N | AG126: N | AH126: N | AI126: Y | AJ126: Y | AK126: =+IF(AND(AD126="N",AF126="N"),"Fora de âmbito", IF(AND(AD126="N",AF126="Y"),"Apenas ESG Risk", IF(AND(AD126="Y",AF126="N"),"Apenas Pilar 3", IF(AND(AD126="Y",AF126="Y"),"Comum","")))) -> Apenas Pilar 3 | AL126: =+IF(IFERROR(VLOOKUP(A126,Ficheiros!I:I,1,FALSE),"")=A126,"Sim","Não") -> Não | AM126: =+IF(IFERROR(VLOOKUP(A126,Ficheiros!E:E,1,FALSE),"")=A126,"Sim","Não") -> Sim | AN126: =+IF(IFERROR(VLOOKUP(A126,Ficheiros!O:O,1,FALSE),"")=A126,"Sim","Não") -> Sim | AO126: =+IF(IFERROR(VLOOKUP(A126,'Especificação Novos Req. LT (2'!A:A,1,FALSE),"")=A126,"Sim","Não") -> Não | AP126: =+IF(IFERROR(VLOOKUP(A126,Ficheiros!T:T,1,FALSE),"")=A126,"Sim","Não") -> Não | AQ126: =+VLOOKUP(A126,Ficheiros!O:P,2,FALSE) -> 1. Concluído | AR126: =+VLOOKUP(A126,Ficheiros!R:S,3,FALSE) -> #N/A | AS126: =+VLOOKUP(A126,Ficheiros!T:V,3,FALSE) -> #N/A
A127: =+C127&G127 -> ENTITYGRP_EMSSNS_SCP1 | B127: EN.119 | C127: ENTITY | D127: General | E127: N | F127: GRP_EMSSNS_SCP1 | G127: GRP_EMSSNS_SCP1 | H127: N | I127: N | J127: N | K127: N | L127: N | M127: Y | N127: N | R127: FLOAT 6 decimal places | S127: Use decimal point, no thousands seperator | T127: 99999999999 | U127: 11111111111 | V127: 11111111111 | W127: Group's emissions scope 1 | X127: Scope 1 emissions corresponding to the Group | Y127: Not applicable | Z127: N/A | AA127: - | AB127: N | AC127: N | AD127: Y | AE127: N | AF127: Y | AG127: N | AH127: N | AI127: Y | AJ127: Y | AK127: =+IF(AND(AD127="N",AF127="N"),"Fora de âmbito", IF(AND(AD127="N",AF127="Y"),"Apenas ESG Risk", IF(AND(AD127="Y",AF127="N"),"Apenas Pilar 3", IF(AND(AD127="Y",AF127="Y"),"Comum","")))) -> Comum | AL127: =+IF(IFERROR(VLOOKUP(A127,Ficheiros!I:I,1,FALSE),"")=A127,"Sim","Não") -> Não | AM127: =+IF(IFERROR(VLOOKUP(A127,Ficheiros!E:E,1,FALSE),"")=A127,"Sim","Não") -> Sim | AN127: =+IF(IFERROR(VLOOKUP(A127,Ficheiros!O:O,1,FALSE),"")=A127,"Sim","Não") -> Sim | AO127: =+IF(IFERROR(VLOOKUP(A127,'Especificação Novos Req. LT (2'!A:A,1,FALSE),"")=A127,"Sim","Não") -> Não | AP127: =+IF(IFERROR(VLOOKUP(A127,Ficheiros!T:T,1,FALSE),"")=A127,"Sim","Não") -> Não | AQ127: =+VLOOKUP(A127,Ficheiros!O:P,2,FALSE) -> 1. Concluído | AR127: =+VLOOKUP(A127,Ficheiros!R:S,3,FALSE) -> #N/A | AS127: =+VLOOKUP(A127,Ficheiros!T:V,3,FALSE) -> #N/A
A128: =+C128&G128 -> ENTITYGRP_EMSSNS_SCP2 | B128: EN.120 | C128: ENTITY | D128: General | E128: N | F128: GRP_EMSSNS_SCP2 | G128: GRP_EMSSNS_SCP2 | H128: N | I128: N | J128: N | K128: N | L128: N | M128: Y | N128: N | R128: FLOAT 6 decimal places | S128: Use decimal point, no thousands seperator | T128: 99999999999 | U128: 11111111111 | V128: 11111111111 | W128: Group's emissions scope 2 | X128: Scope 2 emissions corresponding to the Group | Y128: Not applicable | Z128: N/A | AA128: - | AB128: N | AC128: N | AD128: Y | AE128: N | AF128: Y | AG128: N | AH128: N | AI128: Y | AJ128: Y | AK128: =+IF(AND(AD128="N",AF128="N"),"Fora de âmbito", IF(AND(AD128="N",AF128="Y"),"Apenas ESG Risk", IF(AND(AD128="Y",AF128="N"),"Apenas Pilar 3", IF(AND(AD128="Y",AF128="Y"),"Comum","")))) -> Comum | AL128: =+IF(IFERROR(VLOOKUP(A128,Ficheiros!I:I,1,FALSE),"")=A128,"Sim","Não") -> Não | AM128: =+IF(IFERROR(VLOOKUP(A128,Ficheiros!E:E,1,FALSE),"")=A128,"Sim","Não") -> Sim | AN128: =+IF(IFERROR(VLOOKUP(A128,Ficheiros!O:O,1,FALSE),"")=A128,"Sim","Não") -> Sim | AO128: =+IF(IFERROR(VLOOKUP(A128,'Especificação Novos Req. LT (2'!A:A,1,FALSE),"")=A128,"Sim","Não") -> Não | AP128: =+IF(IFERROR(VLOOKUP(A128,Ficheiros!T:T,1,FALSE),"")=A128,"Sim","Não") -> Não | AQ128: =+VLOOKUP(A128,Ficheiros!O:P,2,FALSE) -> 1. Concluído | AR128: =+VLOOKUP(A128,Ficheiros!R:S,3,FALSE) -> #N/A | AS128: =+VLOOKUP(A128,Ficheiros!T:V,3,FALSE) -> #N/A
A129: =+C129&G129 -> ENTITYGRP_EMSSNS_SCP3 | B129: EN.121 | C129: ENTITY | D129: General | E129: N | F129: GRP_EMSSNS_SCP3 | G129: GRP_EMSSNS_SCP3 | H129: N | I129: N | J129: N | K129: N | L129: N | M129: Y | N129: N | R129: FLOAT 6 decimal places | S129: Use decimal point, no thousands seperator | T129: 99999999999 | U129: 11111111111 | V129: 11111111111 | W129: Group's emissions scope 3 | X129: Scope 3 emissions corresponding to the Group | Y129: Not applicable | Z129: N/A | AA129: - | AB129: N | AC129: N | AD129: Y | AE129: N | AF129: Y | AG129: N | AH129: N | AI129: Y | AJ129: Y | AK129: =+IF(AND(AD129="N",AF129="N"),"Fora de âmbito", IF(AND(AD129="N",AF129="Y"),"Apenas ESG Risk", IF(AND(AD129="Y",AF129="N"),"Apenas Pilar 3", IF(AND(AD129="Y",AF129="Y"),"Comum","")))) -> Comum | AL129: =+IF(IFERROR(VLOOKUP(A129,Ficheiros!I:I,1,FALSE),"")=A129,"Sim","Não") -> Não | AM129: =+IF(IFERROR(VLOOKUP(A129,Ficheiros!E:E,1,FALSE),"")=A129,"Sim","Não") -> Sim | AN129: =+IF(IFERROR(VLOOKUP(A129,Ficheiros!O:O,1,FALSE),"")=A129,"Sim","Não") -> Sim | AO129: =+IF(IFERROR(VLOOKUP(A129,'Especificação Novos Req. LT (2'!A:A,1,FALSE),"")=A129,"Sim","Não") -> Não | AP129: =+IF(IFERROR(VLOOKUP(A129,Ficheiros!T:T,1,FALSE),"")=A129,"Sim","Não") -> Não | AQ129: =+VLOOKUP(A129,Ficheiros!O:P,2,FALSE) -> 1. Concluído | AR129: =+VLOOKUP(A129,Ficheiros!R:S,3,FALSE) -> #N/A | AS129: =+VLOOKUP(A129,Ficheiros!T:V,3,FALSE) -> #N/A
A130: =+C130&G130 -> ENTITYFLG_ACT_PHYSCL_RSK | B130: EN.122 | C130: ENTITY | D130: General | E130: N | F130: FLG_ACT_PHYSCL_RSK | G130: FLG_ACT_PHYSCL_RSK | H130: N | I130: Y | J130: Y | K130: Y | L130: Y | M130: Y | N130: Y | R130: Y, N | S130: Boolean: Y/N | T130: Default value not allowed | U130: Default value not allowed | V130: N/A | W130: Flag Acute Physical Risk at entity level | X130: This flag allows to identify whether the informing society has Acute physical risk or not (Acute physical risks refer to those that are event-driven, including increased severity of extreme weather events, such as cyclones, hurricanes, or floods.) | Y130: Not applicable | Z130: N/A | AA130: - | AB130: N | AC130: N | AD130: Y | AE130: N | AF130: N | AG130: N | AH130: N | AI130: Y | AJ130: Y | AK130: =+IF(AND(AD130="N",AF130="N"),"Fora de âmbito", IF(AND(AD130="N",AF130="Y"),"Apenas ESG Risk", IF(AND(AD130="Y",AF130="N"),"Apenas Pilar 3", IF(AND(AD130="Y",AF130="Y"),"Comum","")))) -> Apenas Pilar 3 | AL130: =+IF(IFERROR(VLOOKUP(A130,Ficheiros!I:I,1,FALSE),"")=A130,"Sim","Não") -> Não | AM130: Não | AN130: Não | AO130: =+IF(IFERROR(VLOOKUP(A130,'Especificação Novos Req. LT (2'!A:A,1,FALSE),"")=A130,"Sim","Não") -> Não | AP130: =+IF(IFERROR(VLOOKUP(A130,Ficheiros!T:T,1,FALSE),"")=A130,"Sim","Não") -> Não | AQ130: =+VLOOKUP(A130,Ficheiros!O:P,2,FALSE) -> 1. Concluído | AR130: =+VLOOKUP(A130,Ficheiros!R:S,3,FALSE) -> #N/A | AS130: =+VLOOKUP(A130,Ficheiros!T:V,3,FALSE) -> #N/A
A131: =+C131&G131 -> ENTITYFLG_CHRNC_PHYSCL_RSK | B131: EN.123 | C131: ENTITY | D131: General | E131: N | F131: FLG_CHRNC_PHYSCL_RSK | G131: FLG_CHRNC_PHYSCL_RSK | H131: N | I131: Y | J131: Y | K131: Y | L131: Y | M131: Y | N131: Y | R131: Y, N | S131: Boolean: Y/N | T131: Default value not allowed | U131: Default value not allowed | V131: N/A | W131: Flag Chronic Physical Risk at entity level | X131: This flag allows to identify whether the informing society has Chronic physical risk or not (Chronic physical risks refer to longer-term shifts in climate patterns (e.g., sustained higher temperatures) that may cause sea level rise or chronic heat waves.) | Y131: Not applicable | Z131: N/A | AA131: - | AB131: N | AC131: N | AD131: Y | AE131: N | AF131: N | AG131: N | AH131: N | AI131: Y | AJ131: Y | AK131: =+IF(AND(AD131="N",AF131="N"),"Fora de âmbito", IF(AND(AD131="N",AF131="Y"),"Apenas ESG Risk", IF(AND(AD131="Y",AF131="N"),"Apenas Pilar 3", IF(AND(AD131="Y",AF131="Y"),"Comum","")))) -> Apenas Pilar 3 | AL131: =+IF(IFERROR(VLOOKUP(A131,Ficheiros!I:I,1,FALSE),"")=A131,"Sim","Não") -> Não | AM131: Não | AN131: Não | AO131: =+IF(IFERROR(VLOOKUP(A131,'Especificação Novos Req. LT (2'!A:A,1,FALSE),"")=A131,"Sim","Não") -> Não | AP131: =+IF(IFERROR(VLOOKUP(A131,Ficheiros!T:T,1,FALSE),"")=A131,"Sim","Não") -> Não | AQ131: =+VLOOKUP(A131,Ficheiros!O:P,2,FALSE) -> 1. Concluído | AR131: =+VLOOKUP(A131,Ficheiros!R:S,3,FALSE) -> #N/A | AS131: =+VLOOKUP(A131,Ficheiros!T:V,3,FALSE) -> #N/A
...

Sheet 2. Entregas 31Jan
B2: Âmbito | C2: Tabela | D2: Campo | E2: Visibilidade em Plano | F2: Status
B3: Modelo de Bens Imóveis | C3: Certificados | D3: Especificação: Gloval + Novo Campo | E3: Sim | F3: Concluido
B4: Modelo de Bens Imóveis | C4: Input Gloval | D4: Especificação: Input Gloval | E4: Sim | F4: Concluido
B5: Modelo de Bens Imóveis | C5: Certificados | D5: Teste: Campo Rácio NTC | E5: Sim | F5: WIP
B6: Modelo de Bens Imóveis | C6: Certificados | D6: Teste: Restantes Campos (exceto Gloval) | E6: Não | F6: WIP
B8: Modelo Verde | C8: Veiculos | D8: Especificação: Scopes & Origens & Unid | E8: Não | F8: WIP
B9: Modelo Verde | C9: Imóveis | D9: Especificação: Scopes & Origens & Unid | E9: Não | F9: WIP
B10: Modelo Verde | C10: Clientes | D10: Especificação: Code Nace (TAT) no Risco Físico + SPV + Campo Code Nace | E10: Sim | F10: WIP
B11: Modelo Verde | C11: Imóveis | D11: Especificação: Code Nace (TAT) no Risco Físico | E11: Sim | F11: WIP
B13: Pilar III | C13: Protection | D13: Especificação: TYP_EPC_LBL & EPC_LBL | E13: Não | F13: Concluido
B14: Pilar III | C14: Protection | D14: Especificação: 6 campos (emissões e origens --> as emissões dependem das origens do MV (ex: eletricos) | E14: Não | F14: WIP
B15: Pilar III | C15: Instrument | D15: Especificação: Métodos obtenção das scopes na LT827 (móveis e imóveis) | E15: Não | F15: WIP
... B19: Novo Projeto | C19: Modelo Verde | D19: Especificação: 20 campos de rácio de elegi | E19: Sim | F19: Concluido
B21: Marcação Verde | D21: Tempo perdido em reuniões
B23: Restantes To Do's
B24: - Confirmar com a MR campos da LT006
B25: - Enviar e-mail a Zneida acerca do universo de ESG RISK
B26: - Confirmar se a LT007 vai ter os contratos todos

Sheet Input >>

Sheet Ficheiros
B2: Pilar 3 - V12 | G2: LOAN TAPE | K2: Plano 5.12 | R2: Projeto GF
B3: TABELA | C3: NOME COLUNA | D3: AUX_TABELA | E3: AUX_COMBINAÇÃO | G3: TABELA | H3: NOME COLUNA | I3: AUX_COMBINAÇÃO | K3: TABELA | L3: NOME COLUNA | M3: STATUS | N3: AUX_TABELA | O3: AUX_COMBINAÇÃO | P3: STATUS | R3: TABELA | S3: NOME COLUNA | T3: AUX_COMBINAÇÃO | U3: STATUS
B4: lt004_protection | C4: orgnl_prtctn_vl | D4: =+UPPER(MID(B4,FIND("_",B4,1)+1,LEN(B4))) -> PROTECTION | E4: =+D4&UPPER(C4) -> PROTECTIONORGNL_PRTCTN_VL | G4: INSTRUMENT | H4: ACCMLTD_CHNGS_FV_CR_INSTRMNT | I4: =+G4&H4 -> INSTRUMENTACCMLTD_CHNGS_FV_CR_INSTRMNT | K4: lt003_entity | L4: nace_esg | M4: 1. Concluído | N4: =+UPPER(MID(K4,FIND("_",K4,1)+1,LEN(K4))) -> ENTITY | O4: =+N4&UPPER(L4) -> ENTITYNACE_ESG | P4: 1. Concluído | R4: INSTRUMENT | S4: ACCMLTD_CHNGS_FV_CR_INSTRMNT | T4: =+R4&S4 -> INSTRUMENTACCMLTD_CHNGS_FV_CR_INSTRMNT | U4: 9. Concluído | V4: PM
B5: lt004_protection | C5: typ_prtctn | D5: =+UPPER(MID(B5,FIND("_",B5,1)+1,LEN(B5))) -> PROTECTION | E5: =+D5&UPPER(C5) -> PROTECTIONTYP_PRTCTN | G5: INSTRUMENT | H5: ACCMLTD_IMPRMNT_INSTRMNT | I5: =+G5&H5 -> INSTRUMENTACCMLTD_IMPRMNT_INSTRMNT | K5: lt003_entity | L5: txnmy_elgbl_capex_ccm | M5: 1. Concluído | N5: =+UPPER(MID(K5,FIND("_",K5,1)+1,LEN(K5))) -> ENTITY | O5: =+N5&UPPER(L5) -> ENTITYTXNMY_ELGBL_CAPEX_CCM | P5: 1. Concluído | R5: INSTRUMENT | S5: ACCMLTD_IMPRMNT_INSTRMNT | T5: =+R5&S5 -> INSTRUMENTACCMLTD_IMPRMNT_INSTRMNT | U5: 9. Concluído | V5: PM
B6: lt003_entity | C6: nace_esg | D6: =+UPPER(MID(B6,FIND("_",B6,1)+1,LEN(B6))) -> ENTITY | E6: =+D6&UPPER(C6) -> ENTITYNACE_ESG | G6: INSTRUMENT | H6: ACCMLTD_IMPRMNT_INSTRMNT_PRVS | I6: =+G6&H6 -> INSTRUMENTACCMLTD_IMPRMNT_INSTRMNT_PRVS | K6: lt003_entity | L6: txnmy_elgbl_trnvr_ccm | M6: 1. Concluído | N6: =+UPPER(MID(K6,FIND("_",K6,1)+1,LEN(K6))) -> ENTITY | O6: =+N6&UPPER(L6) -> ENTITYTXNMY_ELGBL_TRNVR_CCM | P6: 1. Concluído | R6: INSTRUMENT | S6: ACCMLTD_IMPRMNT_INSTRMNT_PRVS | T6: =+R6&S6 -> INSTRUMENTACCMLTD_IMPRMNT_INSTRMNT_PRVS | U6: 5.2 Em testes - Incidência | V6: LF
B7: lt003_entity | C7: txnmy_elgbl_capex_ccm | D7: =+UPPER(MID(B7,FIND("_",B7,1)+1,LEN(B7))) -> ENTITY | E7: =+D7&UPPER(C7) -> ENTITYTXNMY_ELGBL_CAPEX_CCM | G7: INSTRUMENT | H7: ACCMLTD_WRTFFS_INSTRMNT | I7: =+G7&H7 -> INSTRUMENTACCMLTD_WRTFFS_INSTRMNT | K7: lt003_entity | L7: txnmy_elgbl_capex_cca | M7: 1. Concluído | N7: =+UPPER(MID(K7,FIND("_",K7,1)+1,LEN(K7))) -> ENTITY | O7: =+N7&UPPER(L7) -> ENTITYTXNMY_ELGBL_CAPEX_CCA | P7: 1. Concluído | R7: INSTRUMENT | S7: ACCMLTD_WRTFFS_INSTRMNT | T7: =+R7&S7 -> INSTRUMENTACCMLTD_WRTFFS_INSTRMNT | U7: 9. Concluído | V7: PM
B8: lt003_entity | C8: txnmy_elgbl_trnvr_ccm | D8: =+UPPER(MID(B8,FIND("_",B8,1)+1,LEN(B8))) -> ENTITY | E8: =+D8&UPPER(C8) -> ENTITYTXNMY_ELGBL_TRNVR_CCM | G8: INSTRUMENT | H8: ACCNTNG_CLSSFCTN | I8: =+G8&H8 -> INSTRUMENTACCNTNG_CLSSFCTN | K8: lt003_entity | L8: txnmy_elgbl_trnvr_cca | M8: 1. Concluído | N8: =+UPPER(MID(K8,FIND("_",K8,1)+1,LEN(K8))) -> ENTITY | O8: =+N8&UPPER(L8) -> ENTITYTXNMY_ELGBL_TRNVR_CCA | P8: 1. Concluído | R8: INSTRUMENT | S8: ACCNTNG_CLSSFCTN | T8: =+R8&S8 -> INSTRUMENTACCNTNG_CLSSFCTN | U8: 9. Concluído | V8: PM
B9: lt003_entity | C9: txnmy_elgbl_capex_cca | D9: =+UPPER(MID(B9,FIND("_",B9,1)+1,LEN(B9))) -> ENTITY | E9: =+D9&UPPER(C9) -> ENTITYTXNMY_ELGBL_CAPEX_CCA | G9: INSTRUMENT | H9: ACCRD_INTRST_INSTRMNT | I9: =+G9&H9 -> INSTRUMENTACCRD_INTRST_INSTRMNT | K9: lt003_entity | L9: enblng_capex_ccm | M9: 1. Concluído | N9: =+UPPER(MID(K9,FIND("_",K9,1)+1,LEN(K9))) -> ENTITY | O9: =+N9&UPPER(L9) -> ENTITYENBLNG_CAPEX_CCM | P9: 1. Concluído | R9: ENTITY | S9: ACCNTNG_FRMWRK_SL | T9: =+R9&S9 -> ENTITYACCNTNG_FRMWRK_SL | U9: 2. Alterar especificação | V9: PM & LF
B10: lt003_entity | C10: txnmy_elgbl_trnvr_cca | D10: =+UPPER(MID(B10,FIND("_",B10,1)+1,LEN(B10))) -> ENTITY | E10: =+D10&UPPER(C10) -> ENTITYTXNMY_ELGBL_TRNVR_CCA | G10: INSTRUMENT | H10: AMNT_D_AT_MTRTY | I10: =+G10&H10 -> INSTRUMENTAMNT_D_AT_MTRTY | K10: lt003_entity | L10: enblng_capex_cca | M10: 1. Concluído | N10: =+UPPER(MID(K10,FIND("_",K10,1)+1,LEN(K10))) -> ENTITY | O10: =+N10&UPPER(L10) -> ENTITYENBLNG_CAPEX_CCA | P10: 1. Concluído | R10: INSTRUMENT | S10: TYP_MRTGG | T10: =+R10&S10 -> INSTRUMENTTYP_MRTGG | U10: 2. Alterar especificação | V10: PM
B11: lt003_entity | C11: enblng_capex_ccm | D11: =+UPPER(MID(B11,FIND("_",B11,1)+1,LEN(B11))) -> ENTITY | E11: =+D11&UPPER(C11) -> ENTITYENBLNG_CAPEX_CCM | G11: INSTRUMENT | H11: ANNLSD_AGRD_RT | I11: =+G11&H11 -> INSTRUMENTANNLSD_AGRD_RT | K11: lt003_entity | L11: trnstnl_capex | M11: 1. Concluído | N11: =+UPPER(MID(K11,FIND("_",K11,1)+1,LEN(K11))) -> ENTITY | O11: =+N11&UPPER(L11) -> ENTITYTRNSTNL_CAPEX | P11: 1. Concluído | R11: INSTRUMENT | S11: AMNT_D_AT_MTRTY | T11: =+R11&S11 -> INSTRUMENTAMNT_D_AT_MTRTY | U11: 1. Especificar | V11: LF
B12: lt003_entity | C12: enblng_capex_cca | D12: =+UPPER(MID(B12,FIND("_",B12,1)+1,LEN(B12))) -> ENTITY | E12: =+D12&UPPER(C12) -> ENTITYENBLNG_CAPEX_CCA | G12: INSTRUMENT | H12: ARRRS_INSTRMNT | I12: =+G12&H12 -> INSTRUMENTARRRS_INSTRMNT | K12: lt003_entity | L12: pure_capex_ccm | M12: 1. Concluído | N12: =+UPPER(MID(K12,FIND("_",K12,1)+1,LEN(K12))) -> ENTITY | O12: =+N12&UPPER(L12) -> ENTITYPURE_CAPEX_CCM | P12: 1. Concluído | R12: ENTITY | S12: ANNL_TRNVR_LE | T12: =+R12&S12 -> ENTITYANNL_TRNVR_LE | U12: 2. Alterar especificação | V12: PM & LF
B13: lt003_entity | C13: trnstnl_capex | D13: =+UPPER(MID(B13,FIND("_",B13,1)+1,LEN(B13))) -> ENTITY | E13: =+D13&UPPER(C13) -> ENTITYTRNSTNL_CAPEX | G13: INSTRUMENT | H13: ARRRS_INSTRMNT_12M | I13: =+G13&H13 -> INSTRUMENTARRRS_INSTRMNT_12M | K13: lt003_entity | L13: pure_capex_cca | M13: 1. Concluído | N13: =+UPPER(MID(K13,FIND("_",K13,1)+1,LEN(K13))) -> ENTITY | O13: =+N13&UPPER(L13) -> ENTITYPURE_CAPEX_CCA | P13: 1. Concluído | R13: ENTITY | S13: ANNL_TRNVR_LE_BDR | T13: =+R13&S13 -> ENTITYANNL_TRNVR_LE_BDR | U13: 9. Concluído | V13: PM
B14: lt003_entity | C14: pure_capex_ccm | D14: =+UPPER(MID(B14,FIND("_",B14,1)+1,LEN(B14))) -> ENTITY | E14: =+D14&UPPER(C14) -> ENTITYPURE_CAPEX_CCM | G14: INSTRUMENT | H14: ASST_SCRT_CLSS | I14: =+G14&H14 -> INSTRUMENTASST_SCRT_CLSS | K14: lt003_entity | L14: enblng_trnvr_ccm | M14: 1. Concluído | N14: =+UPPER(MID(K14,FIND("_",K14,1)+1,LEN(K14))) -> ENTITY | O14: =+N14&UPPER(L14) -> ENTITYENBLNG_TRNVR_CCM | P14: 1. Concluído | R14: ENTITY | S14: ANNL_TRNVR_PRVS | T14: =+R14&S14 -> ENTITYANNL_TRNVR_PRVS | U14: 2. Alterar especificação | V14: PM & LF
B15: lt003_entity | C15: pure_capex_cca | D15: =+UPPER(MID(B15,FIND("_",B15,1)+1,LEN(B15))) -> ENTITY | E15: =+D15&UPPER(C15) -> ENTITYPURE_CAPEX_CCA | G15: INSTRUMENT | H15: BRCHD_CVNNTS | I15: =+G15&H15 -> INSTRUMENTBRCHD_CVNNTS | K15: lt003_entity | L15: enblng_trnvr_cca | M15: 1. Concluído | N15: =+UPPER(MID(K15,FIND("_",K15,1)+1,LEN(K15))) -> ENTITY | O15: =+N15&UPPER(L15) -> ENTITYENBLNG_TRNVR_CCA | P15: 1. Concluído | R15: ENTITY | S15: ANNL_TRNVR_PRVS_BDR | T15: =+R15&S15 -> ENTITYANNL_TRNVR_PRVS_BDR | U15: 9. Concluído | V15: PM
... B91: lt007_instr_activity | C91: sstnbl_ctgry | D91: =+UPPER(MID(B91,FIND("_",B91,1)+1,LEN(B91))) -> INSTR_ACTIVITY | E91: =+D91&UPPER(C91) -> INSTR_ACTIVITYSSTNBL_CTGRY | G91: INSTRUMENT | H91: IFRS9_EAD | I91: =+G91&H91 -> INSTRUMENTIFRS9_EAD | K91: lt002_instrument | L91: accntng_clssfctn | M91: 1. Concluído | N91: =+UPPER(MID(K91,FIND("_",K91,1)+1,LEN(K91))) -> INSTRUMENT | O91: =+N91&UPPER(L91) -> INSTRUMENTACCNTNG_CLSSFCTN | P91: 1. Concluído | R91: INSTRUMENT | S91: RCVD_INTRST_12M | T91: =+R91&S91 -> INSTRUMENTRCVD_INTRST_12M | U91: 2. Alterar especificação | V91: LF
G92: INSTRUMENT | H92: IFRS9_LGD | I92: =+G92&H92 -> INSTRUMENTIFRS9_LGD | K92: lt002_instrument | L92: dt_lgl_fnl_mtrty | M92: 1. Concluído | N92: =+UPPER(MID(K92,FIND("_",K92,1)+1,LEN(K92))) -> INSTRUMENT | O92: =+N92&UPPER(L92) -> INSTRUMENTDT_LGL_FNL_MTRTY | P92: 1. Concluído | R92: INSTRUMENT | S92: DT_FRBRNC_STTS_PRVS_C19 | T92: =+R92&S92 -> INSTRUMENTDT_FRBRNC_STTS_PRVS_C19 | U92: 9. Concluído | V92: PM
G93: INSTRUMENT | H93: IMPRMNT_ASSSSMNT_MTHD | I93: =+G93&H93 -> INSTRUMENTIMPRMNT_ASSSSMNT_MTHD | K93: lt002_instrument | L93: accmltd_imprmnt_instrmnt | M93: 1. Concluído | N93: =+UPPER(MID(K93,FIND("_",K93,1)+1,LEN(K93))) -> INSTRUMENT | O93: =+N93&UPPER(L93) -> INSTRUMENTACCMLTD_IMPRMNT_INSTRMNT | P93: 1. Concluído | R93: PROTECTION | S93: DT_FRST_USG | T93: =+R93&S93 -> PROTECTIONDT_FRST_USG | U93: 7. Analisar controlos e completude | V93: PM
G94: INSTRUMENT | H94: IMPRMNT_CLCLTN_MTHD | I94: =+G94&H94 -> INSTRUMENTIMPRMNT_CLCLTN_MTHD | K94: lt002_instrument | L94: issr_cntry | M94: 1. Concluído | N94: =+UPPER(MID(K94,FIND("_",K94,1)+1,LEN(K94))) -> INSTRUMENT | O94: =+N94&UPPER(L94) -> INSTRUMENTISSR_CNTRY | P94: 1. Concluído | R94: INSTRUMENT | S94: DT_IMPRMNT_STTS | T94: =+R94&S94 -> INSTRUMENTDT_IMPRMNT_STTS | U94: 5.1 Em testes - Re-especificação | V94: PM
G95: INSTRUMENT | H95: IMPRMNT_STTS | I95: =+G95&H95 -> INSTRUMENTIMPRMNT_STTS | K95: lt002_instrument | L95: issr_nace_sctr | M95: 1. Concluído | N95: =+UPPER(MID(K95,FIND("_",K95,1)+1,LEN(K95))) -> INSTRUMENT | O95: =+N95&UPPER(L95) -> INSTRUMENTISSR_NACE_SCTR | P95: 1. Concluído | R95: INSTRUMENT | S95: DT_IMPRMNT_STTS_PRVS | T95: =+R95&S95 -> INSTRUMENTDT_IMPRMNT_STTS_PRVS | U95: 5.1 Em testes - Re-especificação | V95: PM
G96: INSTRUMENT | H96: IMPRMNT_STTS_PRVS | I96: =+G96&H96 -> INSTRUMENTIMPRMNT_STTS_PRVS | K96: lt002_instrument | L96: prmry_asst_clssf | M96: 1. Concluído | N96: =+UPPER(MID(K96,FIND("_",K96,1)+1,LEN(K96))) -> INSTRUMENT | O96: =+N96&UPPER(L96) -> INSTRUMENTPRMRY_ASST_CLSSF | P96: 1. Concluído | R96: INSTRUMENT | S96: DT_INCPTN | T96: =+R96&S96 -> INSTRUMENTDT_INCPTN | U96: 7. Analisar controlos e completude | V96: LF
G97: INSTRUMENT | H97: INSTLMNT_PAY | I97: =+G97&H97 -> INSTRUMENTINSTLMNT_PAY | K97: lt002_instrument | L97: subportfolio_id | M97: 1. Concluído | N97: =+UPPER(MID(K97,FIND("_",K97,1)+1,LEN(K97))) -> INSTRUMENT | O97: =+N97&UPPER(L97) -> INSTRUMENTSUBPORTFOLIO_ID | P97: 1. Concluído | R97: ENTITY | S97: DT_INTRNL_RTNG | T97: =+R97&S97 -> ENTITYDT_INTRNL_RTNG | U97: 5.1 Em testes - Re-especificação | V97: LF
G98: INSTRUMENT | H98: INSTR_SNRTY_CLSS | I98: =+G98&H98 -> INSTRUMENTINSTR_SNRTY_CLSS | K98: lt002_instrument | L98: cod_soc | M98: 1. Concluído | N98: =+UPPER(MID(K98,FIND("_",K98,1)+1,LEN(K98))) -> INSTRUMENT | O98: =+N98&UPPER(L98) -> INSTRUMENTCOD_SOC | P98: 1. Concluído | R98: INSTRUMENT | S98: DT_INTRNL_RTNG | T98: =+R98&S98 -> INSTRUMENTDT_INTRNL_RTNG | U98: 5.1 Em testes - Re-especificação | V98: LF
G99: INSTRUMENT | H99: INSTRMNT_CLSS | I99: =+G99&H99 -> INSTRUMENTINSTRMNT_CLSS | K99: lt002_instrument | L99: lcl_instmrnt_id | M99: 1. Concluído | N99: =+UPPER(MID(K99,FIND("_",K99,1)+1,LEN(K99))) -> INSTRUMENT | O99: =+N99&UPPER(L99) -> INSTRUMENTLCL_INSTMRNT_ID | P99: 1. Concluído | R99: ENTITY | S99: DT_INTTN_LGL_PRCDNGS_LE | T99: =+R99&S99 -> ENTITYDT_INTTN_LGL_PRCDNGS_LE | U99: 9. Concluído | V99: PM
G100: INSTRUMENT | H100: INSTRMNT_ID | I100: =+G100&H100 -> INSTRUMENTINSTRMNT_ID | K100: lt007_instr_activity | L100: sstnbl_indctr | M100: 1. Concluído | N100: =+UPPER(MID(K100,FIND("_",K100,1)+1,LEN(K100))) -> INSTR_ACTIVITY | O100: =+N100&UPPER(L100) -> INSTR_ACTIVITYSSTNBL_INDCTR | P100: 1. Concluído | R100: PROTECTION | S100: DVLPMNT_STTS | T100: =+R100&S100 -> PROTECTIONDVLPMNT_STTS | U100: 9. Concluído | V100: PM
G101: INSTRUMENT | H101: INTRNL_RTNG | I101: =+G101&H101 -> INSTRUMENTINTRNL_RTNG | K101: lt007_instr_activity | L101: sstnbl_ctgry | M101: 4. Validação EF | N101: =+UPPER(MID(K101,FIND("_",K101,1)+1,LEN(K101))) -> INSTR_ACTIVITY | O101: =+N101&UPPER(L101) -> INSTR_ACTIVITYSSTNBL_CTGRY | P101: 4. Validação EF | R101: PROTECTION | S101: DT_LST_FLL_APPRSL | T101: =+R101&S101 -> PROTECTIONDT_LST_FLL_APPRSL | U101: 9. Concluído | V101: PM
G102: INSTRUMENT | H102: INTRNL_RTNG_INCPTN | I102: =+G102&H102 -> INSTRUMENTINTRNL_RTNG_INCPTN | K102: lt002_instrument | L102: grss_intrst_incm | M102: 2.1 Em Teste | N102: =+UPPER(MID(K102,FIND("_",K102,1)+1,LEN(K102))) -> INSTRUMENT | O102: =+N102&UPPER(L102) -> INSTRUMENTGRSS_INTRST_INCM | P102: 2.1 Em Teste | R102: PROTECTION | S102: DT_MTRTY_PRTCTN | T102: =+R102&S102 -> PROTECTIONDT_MTRTY_PRTCTN | U102: 7. Analisar controlos e completude | V102: PM
G103: INSTRUMENT | H103: INTRNL_SGMNT | I103: =+G103&H103 -> INSTRUMENTINTRNL_SGMNT | K103: lt002_instrument | L103: grss_cmmssn_incm | M103: 2.1 Em Teste | N103: =+UPPER(MID(K103,FIND("_",K103,1)+1,LEN(K103))) -> INSTRUMENT | O103: =+N103&UPPER(L103) -> INSTRUMENTGRSS_CMMSSN_INCM | P103: 2.1 Em Teste | R103: INSTRUMENT | S103: SICR_ASSSSMNT_MTHD | T103: =+R103&S103 -> INSTRUMENTSICR_ASSSSMNT_MTHD | U103: 9. Concluído | V103: PM
... G124: INSTRUMENT | H124: LND_DRGTN | I124: =+G124&H124 -> INSTRUMENTLND_DRGTN | K124: lt004_protection | L124: cod_soc | M124: 1. Concluído | N124: =+UPPER(MID(K124,FIND("_",K124,1)+1,LEN(K124))) -> PROTECTION | O124: =+N124&UPPER(L124) -> PROTECTIONCOD_SOC | P124: 1. Concluído | R124: ENTITY | S124: EC_GRP_ID | T124: =+R124&S124 -> ENTITYEC_GRP_ID | U124: 1. Especificar | V124: LF
G125: INSTRUMENT | H125: LSTI | I125: =+G125&H125 -> INSTRUMENTLSTI | K125: lt005_instr_ent | L125: dt_rfrnc | M125: 1. Concluído | N125: INSTR_ENTITY | O125: =+N125&UPPER(L125) -> INSTR_ENTITYDT_RFRNC | P125: 1. Concluído | R125: ENTITY | S125: EC_GRP_NM | T125: =+R125&S125 -> ENTITYEC_GRP_NM | U125: 1. Especificar | V125: LF
G126: INSTRUMENT | H126: LTI_INSTRMNT | I126: =+G126&H126 -> INSTRUMENTLTI_INSTRMNT | K126: lt005_instr_ent | L126: entty_id | M126: 1. Concluído | N126: INSTR_ENTITY | O126: =+N126&UPPER(L126) -> INSTR_ENTITYENTTY_ID | P126: 1. Concluído | R126: ENTITY | S126: ECNMC_ACTVTY | T126: =+R126&S126 -> ENTITYECNMC_ACTVTY | U126: 9. Concluído | V126: PM
G127: INSTRUMENT | H127: LTV | I127: =+G127&H127 -> INSTRUMENTLTV | K127: lt005_instr_ent | L127: instrmnt_id | M127: 1. Concluído | N127: INSTR_ENTITY | O127: =+N127&UPPER(L127) -> INSTR_ENTITYINSTRMNT_ID | P127: 1. Concluído | R127: INSTRUMENT | S127: EIR | T127: =+R127&S127 -> INSTRUMENTEIR | U127: 7. Analisar controlos e completude | V127: LF
G128: INSTRUMENT | H128: LTV_INCPTN | I128: =+G128&H128 -> INSTRUMENTLTV_INCPTN | K128: lt005_instr_ent | L128: cod_soc | M128: 1. Concluído | N128: INSTR_ENTITY | O128: =+N128&UPPER(L128) -> INSTR_ENTITYCOD_SOC | P128: 1. Concluído | R128: INSTRUMENT | S128: EIR_INCPTN | T128: =+R128&S128 -> INSTRUMENTEIR_INCPTN | U128: 7. Analisar controlos e completude | V128: PM
G129: INSTRUMENT | H129: LTV_NPE | I129: =+G129&H129 -> INSTRUMENTLTV_NPE | K129: lt005_instr_ent | L129: mn_entty_id | M129: 1. Concluído | N129: INSTR_ENTITY | O129: =+N129&UPPER(L129) -> INSTR_ENTITYMN_ENTTY_ID | P129: 1. Concluído | R129: INSTRUMENT | S129: ELGBLTY_ECB | T129: =+R129&S129 -> INSTRUMENTELGBLTY_ECB | U129: 9. Concluído | V129: PM
G130: INSTRUMENT | H130: LVRG_FNNC_FLG | I130: =+G130&H130 -> INSTRUMENTLVRG_FNNC_FLG | K130: lt006_instr_prot | L130: dt_rfrnc | M130: 1. Concluído | N130: INSTR_PROTECTION | O130: =+N130&UPPER(L130) -> INSTR_PROTECTIONDT_RFRNC | P130: 1. Concluído | R130: ENTITY | S130: EMPLYMNT_STTS | T130: =+R130&S130 -> ENTITYEMPLYMNT_STTS | U130: 9. Concluído | V130: PM
G131: INSTRUMENT | H131: MTRTY_LTST_FRBRNC_MSR_C19 | I131: =+G131&H131 -> INSTRUMENTMTRTY_LTST_FRBRNC_MSR_C19 | K131: lt006_instr_prot | L131: instrmnt_id | M131: 1. Concluído | N131: INSTR_PROTECTION | O131: =+N131&UPPER(L131) -> INSTR_PROTECTIONINSTRMNT_ID | P131: 1. Concluído | R131: ENTITY | S131: EMPLYMNT_STTS_INTRNL | T131: =+R131&S131 -> ENTITYEMPLYMNT_STTS_INTRNL | U131: 9. Concluído | V131: PM
G132: INSTRUMENT | H132: MTRTY_LTST_MRTR_C19 | I132: =+G132&H132 -> INSTRUMENTMTRTY_LTST_MRTR_C19 | K132: lt006_instr_prot | L132: prtctn_id | M132: 1. Concluído | N132: INSTR_PROTECTION | O132: =+N132&UPPER(L132) -> INSTR_PROTECTIONPRTCTN_ID | P132: 1. Concluído | R132: ENTITY | S132: ENTRPRS_SZ_LE | T132: =+R132&S132 -> ENTITYENTRPRS_SZ_LE | U132: 7. Analisar controlos e completude | V132: PM
G133: INSTRUMENT | H133: NMBR_FRBRNC_MSRS | I133: =+G133&H133 -> INSTRUMENTNMBR_FRBRNC_MSRS | K133: lt006_instr_prot | L133: prtctn_allctd_vl | M133: 1. Concluído | N133: INSTR_PROTECTION | O133: =+N133&UPPER(L133) -> INSTR_PROTECTIONPRTCTN_ALLCTD_VL | P133: 1. Concluído | R133: ENTITY | S133: ENTTY_ID | T133: =+R133&S133 -> ENTITYENTTY_ID | U133: 7. Analisar controlos e completude | V133: LF
G134: INSTRUMENT | H134: OBSRVD_AGNT_ID | I134: =+G134&H134 -> INSTRUMENTOBSRVD_AGNT_ID | K134: lt006_instr_prot | L134: cod_soc | M134: 1. Concluído | N134: INSTR_PROTECTION | O134: =+N134&UPPER(L134) -> INSTR_PROTECTIONCOD_SOC | P134: 1. Concluído | R134: INSTR_ENTITY | S134: ENTTY_ID | T134: =+R134&S134 -> INSTR_ENTITYENTTY_ID | U134: 7. Analisar controlos e completude | V134: LF
G135: INSTRUMENT | H135: OBSRVD_AGNT_NM | I135: =+G135&H135 -> INSTRUMENTOBSRVD_AGNT_NM | K135: lt004_protection | L135: flg_fin | M135: 0. Cancelado | N135: =+UPPER(MID(K135,FIND("_",K135,1)+1,LEN(K135))) -> PROTECTION | O135: =+N135&UPPER(L135) -> PROTECTIONFLG_FIN | P135: 0. Cancelado | R135: ENTITY | S135: ENTTY_NM | T135: =+R135&S135 -> ENTITYENTTY_NM | U135: 9. Concluído | V135: PM
G136: INSTRUMENT | H136: OFF_BLNC_SHT_AMNT_INSTRMNT | I136: =+G136&H136 -> INSTRUMENTOFF_BLNC_SHT_AMNT_INSTRMNT | K136: lt004_protection | L136: flg_exec | M136: 0. Cancelado | N136: =+UPPER(MID(K136,FIND("_",K136,1)+1,LEN(K136))) -> PROTECTION | O136: =+N136&UPPER(L136) -> PROTECTIONFLG_EXEC | P136: 0. Cancelado | R136: ENTITY | S136: EQTY | T136: =+R136&S136 -> ENTITYEQTY | U136: 2. Alterar especificação | V136: PM & LF
G137: INSTRUMENT | H137: OFF_BLNC_SHT_AMNT_INSTRMNT_PRVS | I137: =+G137&H137 -> INSTRUMENTOFF_BLNC_SHT_AMNT_INSTRMNT_PRVS | K137: lt004_protection | L137: flg_col | M137: 0. Cancelado | N137: =+UPPER(MID(K137,FIND("_",K137,1)+1,LEN(K137))) -> PROTECTION | O137: =+N137&UPPER(L137) -> PROTECTIONFLG_COL | P137: 0. Cancelado | R137: ENTITY | S137: EQTY_PRVS | T137: =+R137&S137 -> ENTITYEQTY_PRVS | U137: 2. Alterar especificação | V137: PM & LF
G138: INSTRUMENT | H138: OTSTNDNG_NMNL_AMNT_INSTRMNT | I138: =+G138&H138 -> INSTRUMENTOTSTNDNG_NMNL_AMNT_INSTRMNT | K138: lt004_protection | L138: flg_pro | M138: 0. Cancelado | N138: =+UPPER(MID(K138,FIND("_",K138,1)+1,LEN(K138))) -> PROTECTION | O138: =+N138&UPPER(L138) -> PROTECTIONFLG_PRO | P138: 0. Cancelado | R138: INSTRUMENT | S138: EXPCTD_LSS_CRR | T138: =+R138&S138 -> INSTRUMENTEXPCTD_LSS_CRR | U138: 5.1 Em testes - Re-especificação | V138: PM
G139: INSTRUMENT | H139: OTSTNDNG_NMNL_AMNT_INSTRMNT_PRVS | I139: =+G139&H139 -> INSTRUMENTOTSTNDNG_NMNL_AMNT_INSTRMNT_PRVS | R139: INSTRUMENT | S139: EXPSR_IN_SCP | T139: =+R139&S139 -> INSTRUMENTEXPSR_IN_SCP | U139: 9. Concluído | V139: PM
G140: INSTRUMENT | H140: PBLC_GRNT_SCHM_C19_NM | I140: =+G140&H140 -> INSTRUMENTPBLC_GRNT_SCHM_C19_NM | R140: INSTRUMENT | S140: FRBRNC_STTS_INSTRMNT | T140: =+R140&S140 -> INSTRUMENTFRBRNC_STTS_INSTRMNT | U140: 2. Alterar especificação | V140: LF
G141: INSTRUMENT | H141: PD_CRR_INCPTN | I141: =+G141&H141 -> INSTRUMENTPD_CRR_INCPTN | R141: ENTITY | S141: EXTRNL_RTNG_PRVS | T141: =+R141&S141 -> ENTITYEXTRNL_RTNG_PRVS | U141: 2. Alterar especificação | V141: LF
G142: INSTRUMENT | H142: PD_CRR_RD | I142: =+G142&H142 -> INSTRUMENTPD_CRR_RD | R142: ENTITY | S142: EXTRNL_RTNG_NM | T142: =+R142&S142 -> ENTITYEXTRNL_RTNG_NM | U142: 2. Alterar especificação | V142: LF
G143: INSTRUMENT | H143: PD_CRR_RD_T1 | I143: =+G143&H143 -> INSTRUMENTPD_CRR_RD_T1 | R143: INSTRUMENT | S143: FLD_SYNDCTN | T143: =+R143&S143 -> INSTRUMENTFLD_SYNDCTN | U143: 6. Outros Desenvolvimentos | V143: LF
G144: INSTRUMENT | H144: PD_IFRS9_12M_INCPTN | I144: =+G144&H144 -> INSTRUMENTPD_IFRS9_12M_INCPTN | R144: ENTITY | S144: FLG_BNKRPTCY_IN_GRP | T144: =+R144&S144 -> ENTITYFLG_BNKRPTCY_IN_GRP | U144: 9. Concluído | V144: PM
G145: INSTRUMENT | H145: PD_IFRS9_12M_RD | I145: =+G145&H145 -> INSTRUMENTPD_IFRS9_12M_RD | R145: ENTITY | S145: FLG_HGH_CDS | T145: =+R145&S145 -> ENTITYFLG_HGH_CDS | U145: 9. Concluído | V145: PM
G146: INSTRUMENT | H146: PD_IFRS9_12M_RD_T1 | I146: =+G146&H146 -> INSTRUMENTPD_IFRS9_12M_RD_T1 | R146: ENTITY | S146: FLG_ISDA_CRDT_EVNT | T146: =+R146&S146 -> ENTITYFLG_ISDA_CRDT_EVNT | U146: 9. Concluído | V146: PM
G147: INSTRUMENT | H147: PD_IFRS9_LFTM_INCPTN | I147: =+G147&H147 -> INSTRUMENTPD_IFRS9_LFTM_INCPTN | R147: INSTRUMENT | S147: FLG_LBO | T147: =+R147&S147 -> INSTRUMENTFLG_LBO | U147: 9. Concluído | V147: PM & LF
G148: INSTRUMENT | H148: PD_IFRS9_RMNNG_LFTM_INCPTN | I148: =+G148&H148 -> INSTRUMENTPD_IFRS9_RMNNG_LFTM_INCPTN | R148: ENTITY | S148: FLG_NN_ACCRL | T148: =+R148&S148 -> ENTITYFLG_NN_ACCRL | U148: 9. Concluído | V148: PM
G149: INSTRUMENT | H149: PD_IFRS9_RMNNG_LFTM_RD | I149: =+G149&H149 -> INSTRUMENTPD_IFRS9_RMNNG_LFTM_RD | R149: ENTITY | S149: FLG_RQST_BNKRPTCY | T149: =+R149&S149 -> ENTITYFLG_RQST_BNKRPTCY | U149: 9. Concluído | V149: PM
G150: INSTRUMENT | H150: PMNT_PBLC_GRNT_SCHM_C19 | I150: =+G150&H150 -> INSTRUMENTPMNT_PBLC_GRNT_SCHM_C19 | R150: ENTITY | S150: FLG_RQST_DSTRSSD_RSTRCTRNG | T150: =+R150&S150 -> ENTITYFLG_RQST_DSTRSSD_RSTRCTRNG | U150: 1. Especificar | V150: PM
... G349: INSTR_PROTECTION | H349: COD_SOC | I349: =+G349&H349 -> INSTR_PROTECTIONCOD_SOC | R349: PROTECTION | S349: YR_CNSTRCTN | T349: =+R349&S349 -> PROTECTIONYR_CNSTRCTN | U349: 1. Especificar | V349: PM
R350: ENTITY | S350: ADDRSS_CTY | T350: =+R350&S350 -> ENTITYADDRSS_CTY | U350: 1. Especificar | V350: PM - Novos Campos
R351: ENTITY | S351: ADDRSS_STRT | T351: =+R351&S351 -> ENTITYADDRSS_STRT | U351: 1. Especificar | V351: PM - Novos Campos
R352: ENTITY | S352: DT_ENTRPRS_SZ | T352: =+R352&S352 -> ENTITYDT_ENTRPRS_SZ | U352: 1. Especificar | V352: PM - Novos Campos
R353: ENTITY | S353: NMBR_EMPLYS | T353: =+R353&S353 -> ENTITYNMBR_EMPLYS | U353: 1. Especificar | V353: PM - Novos Campos
R354: ENTITY | S354: LGL_FRM | T354: =+R354&S354 -> ENTITYLGL_FRM | U354: 1. Especificar | V354: PM - Novos Campos
R355: ENTITY | S355: HD_OFFC_UNDRTKNG_ID | T355: =+R355&S355 -> ENTITYHD_OFFC_UNDRTKNG_ID | U355: 1. Especificar | V355: PM - Novos Campos
R356: ENTITY | S356: IMMDT_PRNT_UNDRTKNG_ID | T356: =+R356&S356 -> ENTITYIMMDT_PRNT_UNDRTKNG_ID | U356: 1. Especificar | V356: PM - Novos Campos
R357: ENTITY | S357: ULTMT_PRNT_UNDRTKNG_ID | T357: =+R357&S357 -> ENTITYULTMT_PRNT_UNDRTKNG_ID | U357: 1. Especificar | V357: PM - Novos Campos
R358: ENTITY | S358: TTL_ASSTS | T358: =+R358&S358 -> ENTITYTTL_ASSTS | U358: 1. Especificar | V358: PM - Novos Campos
R359: ENTITY | S359: ENTTY_ID_BDR | T359: =+R359&S359 -> ENTITYENTTY_ID_BDR | U359: 1. Especificar | V359: PM - Novos Campos
R360: INSTRUMENT | S360: CPN_RT_FLTNG | T360: =+R360&S360 -> INSTRUMENTCPN_RT_FLTNG | U360: 1. Especificar | V360: PM - Novos Campos
R361: INSTRUMENT | S361: INTRST_RT_CP | T361: =+R361&S361 -> INSTRUMENTINTRST_RT_CP | U361: 1. Especificar | V361: PM - Novos Campos
... R382: INSTR_ACTIVITY | S382: PRCNTG_ACTVTY | T382: =+R382&S382 -> INSTR_ACTIVITYPRCNTG_ACTVTY | U382: 1. Especificar | V382: PM - Novos Campos

Sheet Especificação Novos Req. LT (2
C2: Datas de entrega de especificação novos requisitos Loan Tape - Pilar III
C4: 1º package de especificação (20 campos) – 27 janeiro 2025 | D4: Tabela | E4: Ambito
A6: =+D6&C6 -> ENTITYTXNMY_ELGBL_CAPEX_W | C6: TXNMY_ELGBL_CAPEX_W | D6: ENTITY | E6: PILAR III
A7: =+D7&C7 -> ENTITYTXNMY_ELGBL_TRNVR_W | C7: TXNMY_ELGBL_TRNVR_W | D7: ENTITY | E7: PILAR III
A8: =+D8&C8 -> ENTITYTXNMY_ELGBL_CAPEX_P | C8: TXNMY_ELGBL_CAPEX_P | D8: ENTITY | E8: PILAR III
A9: =+D9&C9 -> ENTITYTXNMY_ELGBL_TRNVR_P | C9: TXNMY_ELGBL_TRNVR_P | D9: ENTITY | E9: PILAR III
A10: =+D10&C10 -> ENTITYTXNMY_ELGBL_CAPEX_B | C10: TXNMY_ELGBL_CAPEX_B | D10: ENTITY | E10: PILAR III
A11: =+D11&C11 -> ENTITYTXNMY_ELGBL_TRNVR_B | C11: TXNMY_ELGBL_TRNVR_B | D11: ENTITY | E11: PILAR III
A12: =+D12&C12 -> ENTITYTXNMY_ELGBL_CAPEX_CE | C12: TXNMY_ELGBL_CAPEX_CE | D12: ENTITY | E12: PILAR III
A13: =+D13&C13 -> ENTITYTXNMY_ELGBL_TRNVR_CE | C13: TXNMY_ELGBL_TRNVR_CE | D13: ENTITY | E13: PILAR III
A14: =+D14&C14 -> ENTITYPURE_CAPEX_P | C14: PURE_CAPEX_P | D14: ENTITY | E14: PILAR III
A15: =+D15&C15 -> ENTITYPURE_TRNVR_P | C15: PURE_TRNVR_P | D15: ENTITY | E15: PILAR III
A16: =+D16&C16 -> ENTITYPURE_CAPEX_B | C16: PURE_CAPEX_B | D16: ENTITY | E16: PILAR III
A17: =+D17&C17 -> ENTITYPURE_TRNVR_B | C17: PURE_TRNVR_B | D17: ENTITY | E17: PILAR III
... A25: =+D25&C25 -> ENTITYENBLNG_TRNVR_CE | C25: ENBLNG_TRNVR_CE | D25: ENTITY | E25: PILAR III
C27: 2º package de especificação (15 campos) – 4 fevereiro 2025 | D27: Tabela | E27: Ambito
A29: =+D29&C29 -> PROTECTIONBLDNG_AR | C29: BLDNG_AR | D29: PROTECTION | E29: PILAR III + ESG Risk | I29: area util
A30: =+D30&C30 -> INSTR_ACTIVITYFLG_SBSTNTL_CNTRBTN | C30: FLG_SBSTNTL_CNTRBTN | D30: INSTR_ACTIVITY | E30: PILAR III
A31: =+D31&C31 -> INSTRUMENTIFRS9_BHVRL_MTRTY | C31: IFRS9_BHVRL_MTRTY | D31: INSTRUMENT | E31: PILAR III | F31: Já há especificação (LT) e não tem incidências - É só passar para produção
A32: =+D32&C32 -> INSTRUMENTLTV | C32: LTV | D32: INSTRUMENT | E32: PILAR III
A33: =+D33&C33 -> INSTRUMENTLTV_INCPTN | C33: LTV_INCPTN | D33: INSTRUMENT | E33: PILAR III
A34: =+D34&C34 -> INSTRUMENTANNLSD_AGRD_RT | C34: ANNLSD_AGRD_RT | D34: INSTRUMENT | E34: PILAR III
A35: =+D35&C35 -> INSTRUMENTEIR_INCPTN | C35: EIR_INCPTN | D35: INSTRUMENT | E35: PILAR III
A36: =+D36&C36 -> PROTECTIONYR_CNSTRCTN | C36: YR_CNSTRCTN | D36: PROTECTION | E36: PILAR III + ESG Risk
A37: =+D37&C37 -> INSTR_ACTIVITYCOD_SOC | C37: COD_SOC | D37: INSTR_ACTIVITY | E37: PILAR III
A38: =+D38&C38 -> INSTR_ACTIVITYDT_RFRNC | C38: DT_RFRNC | D38: INSTR_ACTIVITY | E38: PILAR III
A39: =+D39&C39 -> INSTR_ACTIVITYINSTRMNT_ID | C39: INSTRMNT_ID | D39: INSTR_ACTIVITY | E39: PILAR III
A40: =+D40&C40 -> INSTR_ACTIVITYPRCNTG_ACTVTY | C40: PRCNTG_ACTVTY | D40: INSTR_ACTIVITY | E40: PILAR III
A41: =+D41&C41 -> ENTITYENTTY_NM | C41: ENTTY_NM | D41: ENTITY | E41: PILAR III | F41: Campo fechado (LT) (testes e especificação)
A42: =+D42&C42 -> ENTITYEC_GRP_NM | C42: EC_GRP_NM | D42: ENTITY | E42: PILAR III | F42: Por especificar (LT) e está no outro projeto
A43: =+D43&C43 -> INSTRUMENTFRBRNC_STTS_INSTRMNT | C43: FRBRNC_STTS_INSTRMNT | D43: INSTRUMENT | E43: PILAR III
C45: 3º package de especificação (14 campos) – 5 fevereiro 2025 | D45: Tabela | E45: Ambito
A47: =+D47&C47 -> INSTRUMENTFLG_MNMM_SFGRDS | C47: FLG_MNMM_SFGRDS | D47: INSTRUMENT | E47: PILAR III + ESG Risk | F47: =VLOOKUP(C47,[1]Sheet1!$D$5:$E$18,2,0) -> MISS
A48: =+D48&C48 -> PROTECTIONRL_ESTT_CRTFCTN | C48: RL_ESTT_CRTFCTN | D48: PROTECTION | E48: PILAR III + ESG Risk | F48: =VLOOKUP(C48,[1]Sheet1!$D$5:$E$18,2,0) -> MISS
A49: =+D49&C49 -> PROTECTIONTYP_VHCL | C49: TYP_VHCL | D49: PROTECTION | E49: PILAR III + ESG Risk + GD
A50: =+D50&C50 -> PROTECTIONDT_RGSTRTN | C50: DT_RGSTRTN | D50: PROTECTION | E50: PILAR III + ESG Risk | F50: 0000-00-00
A51: =+D51&C51 -> INSTR_ACTIVITYFLG_DNSH_CMPLNC | C51: FLG_DNSH_CMPLNC | D51: INSTR_ACTIVITY | E51: PILAR III | F51: =VLOOKUP(C51,[1]Sheet1!$D$5:$E$18,2,0) -> MISS
A52: =+D52&C52 -> INSTR_ACTIVITYDNSH_DTL | C52: DNSH_DTL | D52: INSTR_ACTIVITY | E52: PILAR III | F52: =VLOOKUP(C52,[1]Sheet1!$D$5:$E$18,2,0) -> MISS
A53: =+D53&C53 -> PROTECTIONTYP_EMSSNS_LBL | C53: TYP_EMSSNS_LBL | D53: PROTECTION | E53: ESG Risk | F53: =VLOOKUP(C53,[1]Sheet1!$D$5:$E$18,2,0) -> MISS
A54: =+D54&C54 -> PROTECTIONVHCL_EMSSNS_LBL | C54: VHCL_EMSSNS_LBL | D54: PROTECTION | E54: ESG Risk | F54: =VLOOKUP(C54,[1]Sheet1!$D$5:$E$18,2,0) -> MISS
A55: =+D55&C55 -> PROTECTIONVHCL_EMSSNS_SCR | C55: VHCL_EMSSNS_SCR | D55: PROTECTION | E55: ESG Risk | F55: =VLOOKUP(C55,[1]Sheet1!$D$5:$E$18,2,0) -> 99999999999
A56: =+D56&C56 -> PROTECTIONINSRNC_ID | C56: INSRNC_ID | D56: PROTECTION | E56: ESG Risk | F56: =VLOOKUP(C56,[1]Sheet1!$D$5:$E$18,2,0) -> MISS
A57: =+D57&C57 -> PROTECTIONTYP_HZRDS_INSRD | C57: TYP_HZRDS_INSRD | D57: PROTECTION | E57: ESG Risk | F57: =VLOOKUP(C57,[1]Sheet1!$D$5:$E$18,2,0) -> MISS
A58: =+D58&C58 -> PROTECTIONAMNT_CVRD_INSRNC | C58: AMNT_CVRD_INSRNC | D58: PROTECTION | E58: ESG Risk | F58: =VLOOKUP(C58,[1]Sheet1!$D$5:$E$18,2,0) -> 99999999999
A59: =+D59&C59 -> PROTECTIONDT_MTRTY_INSRNC | C59: DT_MTRTY_INSRNC | D59: PROTECTION | E59: ESG Risk | F59: =VLOOKUP(C59,[1]Sheet1!$D$5:$E$18,2,0) -> 0000-00-00
A60: =+D60&C60 -> PROTECTIONFLG_FRST_HM | C60: FLG_FRST_HM | D60: PROTECTION | E60: ESG Risk | F60: =VLOOKUP(C60,[1]Sheet1!$D$5:$E$18,2,0) -> MISS
C62: 4º package de especificação (13 campos) – 11 fevereiro 2025
A64: =+D64&C64 -> PROTECTIONPRMRY_ENRGY_DMND_NN_RNWBL | C64: PRMRY_ENRGY_DMND_NN_RNWBL | D64: PROTECTION | E64: PILAR III + ESG Risk
A65: =+D65&C65 -> PROTECTIONPRMRY_ENRGY_DMND_TTL | C65: PRMRY_ENRGY_DMND_TTL | D65: PROTECTION | E65: PILAR III + ESG Risk
A66: =+D66&C66 -> PROTECTIONPRMRY_ENRGY_DMND_RFRNC_VL | C66: PRMRY_ENRGY_DMND_RFRNC_VL | D66: PROTECTION | E66: PILAR III + ESG Risk
A67: =+D67&C67 -> INSTRUMENTTYP_OFF_BLNC_PRDCT | C67: TYP_OFF_BLNC_PRDCT | D67: INSTRUMENT | E67: PILAR III
A68: =+D68&C68 -> PROTECTIONEPC_EMSSNS_LBL | C68: EPC_EMSSNS_LBL | D68: PROTECTION | E68: ESG Risk
A69: =+D69&C69 -> PROTECTIONTYP_EMSSNS_SCR | C69: TYP_EMSSNS_SCR | D69: PROTECTION | E69: ESG Risk
A70: =+D70&C70 -> PROTECTIONEPC_EMSSNS_SCR | C70: EPC_EMSSNS_SCR | D70: PROTECTION | E70: ESG Risk
A71: =+D71&C71 -> INSTRUMENTINTRNL_SGMNT | C71: INTRNL_SGMNT | D71: INSTRUMENT | E71: ESG Risk
A72: =+D72&C72 -> INSTRUMENTEAD | C72: EAD | D72: INSTRUMENT | E72: ESG Risk
A73: =+D73&C73 -> INSTRUMENTOFF_BLNC_SHT_AMNT_INSTRMNT | C73: OFF_BLNC_SHT_AMNT_INSTRMNT | D73: INSTRUMENT | E73: ESG Risk
A74: =+D74&C74 -> PROTECTIONRL_ESTT_ADDRSS | C74: RL_ESTT_ADDRSS | D74: PROTECTION | E74: ESG Risk
A75: =+D75&C75 -> PROTECTIONRL_ESTT_CLLTRL_LCTN_INT | C75: RL_ESTT_CLLTRL_LCTN_INT | D75: PROTECTION | E75: ESG Risk
A76: =+D76&C76 -> PROTECTIONRL_ESTT_CTY | C76: RL_ESTT_CTY | D76: PROTECTION | E76: ESG Risk
C79: 5º package de especificação (6 campos) – 17 fevereiro 2025
A81: =+D81&C81 -> PROTECTIONRL_ESTT_CLMT_ZN | C81: RL_ESTT_CLMT_ZN | D81: PROTECTION | E81: PILAR III + ESG Risk
A82: =+D82&C82 -> INSTRUMENTNW_BSNSS | C82: NW_BSNSS | D82: INSTRUMENT | E82: PILAR III
A83: =+D83&C83 -> INSTR_PROTECTIONTYP_RLTN | C83: TYP_RLTN | D83: INSTR_PROTECTION | E83: PILAR III
A84: =+D84&C84 -> ENTITYGRP_ECNMC_ACTVTY | C84: GRP_ECNMC_ACTVTY | D84: ENTITY | E84: ESG Risk
A85: =+D85&C85 -> INSTRUMENTINTRNL_SGMNT_CAT_MSTA | C85: INTRNL_SGMNT_CAT_MSTA | D85: INSTRUMENT | E85: ESG Risk
A86: =+D86&C86 -> INSTRUMENTINTRNL_SGMNT_CATGSUB | C86: INTRNL_SGMNT_CATGSUB | D86: INSTRUMENT | E86: ESG Risk
C89: 6º package - não vinha na proposta
C90: EC_GRP_ID | D90: ENTITY | E90: PILAR III
