Workbook

Sheet Instruções
B2: Instruções:
B3: 1. Alterar apenas o que está a amarelo (nota: no campo ref_date, colocar a plica no início da data para manter como texto)
C5: Schema AS IS (prod) | D5: cd_loan_tapes_bce | F5: TABLE_NAME | G5: Tabela LT_AS_IS | H5: Tabela LT_TO_BE | I5: Chave1 | J5: Chave2
C6: Schema TO BE (testes) | D6: bu_loantape_work | F6: ENTTY | G6: lt003_entity | H6: lt003_entity | I6: entty_id
C7: ref_date | D7: 2025-06-30 | F7: INSTR_ENTTY | G7: lt005_instr_ent | H7: lt005_instr_ent | I7: instrmnt_id | J7: entty_id
C8: nome_perimetro | D8: Individual IDComb | F8: INSTR_PRTCTN | G8: lt006_instr_prot | H8: lt006_instr_prot | I8: instrmnt_id | J8: prtctn_id
C9: segmento | D9: ESTR | F9: INSTRMNT | G9: lt002_instrument | H9: lt002_instrument | I9: instrmnt_id
C10: ambito | D10: PM | F10: PRTCTN | G10: lt004_protection | H10: lt004_protection | I10: prtctn_id
C11: filtro final | D11: ="ref_date='"&$D$7&"' AND nome_perimetro= '"&$D$8&"' AND segmento= '"&$D$9&"' AND ambito= '"&$D$10&"' AND entidade='00100' AND cod_visao = 1" -> ref_date='2025-06-30' AND nome_perimetro= 'Individual IDComb' AND segmento= 'ESTR' AND ambito= 'PM' AND entidade='00100' AND cod_visao = 1
B13: 2. Criar tabelas AS-IS no schema BU_CAPTOOLS_WORK (executar código infra a verde)
B15: ="DROP TABLE IF EXISTS "&$D$5&"."&G6&"; CREATE TABLE "&$D$5&"."&G6&" as SELECT * FROM "&$D$6&"."&H6&" WHERE "&$D$11&";" -> DROP TABLE IF EXISTS cd_loan_tapes_bce.lt003_entity; CREATE TABLE cd_loan_tapes_bce.lt003_entity as SELECT * FROM bu_loantape_work.lt003_entity WHERE ref_date='2025-06-30' AND nome_perimetro= 'Individual IDComb' AND segmento= 'ESTR' AND ambito= 'PM' AND entidade='00100' AND cod_visao = 1;
B16: ="DROP TABLE IF EXISTS "&$D$5&"."&G7&"; CREATE TABLE "&$D$5&"."&G7&" as SELECT * FROM "&$D$6&"."&H7&" WHERE "&$D$11&";" -> DROP TABLE IF EXISTS cd_loan_tapes_bce.lt005_instr_ent; CREATE TABLE cd_loan_tapes_bce.lt005_instr_ent as SELECT * FROM bu_loantape_work.lt005_instr_ent WHERE ref_date='2025-06-30' AND nome_perimetro= 'Individual IDComb' AND segmento= 'ESTR' AND ambito= 'PM' AND entidade='00100' AND cod_visao = 1;
B17: ="DROP TABLE IF EXISTS "&$D$5&"."&G8&"; CREATE TABLE "&$D$5&"."&G8&" as SELECT * FROM "&$D$6&"."&H8&" WHERE "&$D$11&";" -> DROP TABLE IF EXISTS cd_loan_tapes_bce.lt006_instr_prot; CREATE TABLE cd_loan_tapes_bce.lt006_instr_prot as SELECT * FROM bu_loantape_work.lt006_instr_prot WHERE ref_date='2025-06-30' AND nome_perimetro= 'Individual IDComb' AND segmento= 'ESTR' AND ambito= 'PM' AND entidade='00100' AND cod_visao = 1;
B18: ="DROP TABLE IF EXISTS "&$D$5&"."&G9&"; CREATE TABLE "&$D$5&"."&G9&" as SELECT * FROM "&$D$6&"."&H9&" WHERE "&$D$11&";" -> DROP TABLE IF EXISTS cd_loan_tapes_bce.lt002_instrument; CREATE TABLE cd_loan_tapes_bce.lt002_instrument as SELECT * FROM bu_loantape_work.lt002_instrument WHERE ref_date='2025-06-30' AND nome_perimetro= 'Individual IDComb' AND segmento= 'ESTR' AND ambito= 'PM' AND entidade='00100' AND cod_visao = 1;
B19: ="DROP TABLE IF EXISTS "&$D$5&"."&G10&"; CREATE TABLE "&$D$5&"."&G10&" as SELECT * FROM "&$D$6&"."&H10&" WHERE "&$D$11&";" -> DROP TABLE IF EXISTS cd_loan_tapes_bce.lt004_protection; CREATE TABLE cd_loan_tapes_bce.lt004_protection as SELECT * FROM bu_loantape_work.lt004_protection WHERE ref_date='2025-06-30' AND nome_perimetro= 'Individual IDComb' AND segmento= 'ESTR' AND ambito= 'PM' AND entidade='00100' AND cod_visao = 1;
B21: 3. Executar no HUE as linhas da coluna UNION ALL por blocos na sheet testes resgressivos > correr cada bloco de cada (de 30 em 30)

Sheet Teste Regressivo
B3: TABLE_NAME | C3: TABELA_LT_AS_IS | D3: TABELA_LT_AS_TO_BE | E3: COLUMN_NAME | F3: COLUMN_NAME_AS_IS | G3: COLUMN_NAME_TO_BE | H3: UNIVERSO AS IS | I3: UNIVERSO TO BE | J3: CRUZAMENTO | K3: CONDIÇÃO | L3: QUERY 1 | M3: Tipologia testes | N3: QUERY 2 | O3: UNION ALL | P3: contagem
B4: ENTTY | C4: =_xlfn.CONCAT(Instruções!$D$5,".",VLOOKUP(B4,Instruções!$F$5:$H$10,2,0)) -> cd_loan_tapes_bce.lt003_entity | D4: =_xlfn.CONCAT(Instruções!$D$6,".",VLOOKUP(B4,Instruções!$F$5:$H$10,3,0)) -> bu_loantape_work.lt003_entity | E4: accntng_frmwrk_sl | F4: =E4&"_as_is" -> accntng_frmwrk_sl_as_is | G4: =E4&"_to_be" -> accntng_frmwrk_sl_to_be | H4: =IF(VLOOKUP(B4,Instruções!$F$6:$J$10,5,0)="", "(SELECT "&VLOOKUP(B4,Instruções!$F$6:$J$10,4,0)&" as "&VLOOKUP(B4,Instruções!$F$6:$J$10,4,0)&"_as_is, "&E4&" as "&F4&" FROM "&C4&" WHERE "&Instruções!$D$11&") A ", "(SELECT "&VLOOKUP(B4,Instruções!$F$6:$J$10,4,0)&" as "&VLOOKUP(B4,Instruções!$F$6:$J$10,4,0)&"_as_is, "&VLOOKUP(B4,Instruções!$F$6:$J$10,5,0)&" as "&VLOOKUP(B4,Instruções!$F$6:$J$10,5,0)&"_as_is,"&E4&" as "&F4&" FROM "&C4&" WHERE "&Instruções!$D$11&") A ") -> (SELECT entty_id as entty_id_as_is, accntng_frmwrk_sl as accntng_frmwrk_sl_as_is FROM cd_loan_tapes_bce.lt003_entity WHERE ref_date='2025-06-30' AND nome_perimetro= 'Individual IDComb' AND segmento= 'ESTR' AND ambito= 'PM' AND entidade='00100' AND cod_visao = 1) A | I4: =IF(VLOOKUP(B4,Instruções!$F$6:$J$10,5,0)="", "(SELECT "&VLOOKUP(B4,Instruções!$F$6:$J$10,4,0)&" as "&VLOOKUP(B4,Instruções!$F$6:$J$10,4,0)&"_to_be, "&E4&" as "&G4&" FROM "&D4&" WHERE "&Instruções!$D$11&") B ", "(SELECT "&VLOOKUP(B4,Instruções!$F$6:$J$10,4,0)&" as "&VLOOKUP(B4,Instruções!$F$6:$J$10,4,0)&"_to_be, "&VLOOKUP(B4,Instruções!$F$6:$J$10,5,0)&" as "&VLOOKUP(B4,Instruções!$F$6:$J$10,5,0)&"_to_be,"&E4&" as "&G4&" FROM "&D4&" WHERE "&Instruções!$D$11&") B ") -> (SELECT entty_id as entty_id_to_be, accntng_frmwrk_sl as accntng_frmwrk_sl_to_be FROM bu_loantape_work.lt003_entity WHERE ref_date='2025-06-30' AND nome_perimetro= 'Individual IDComb' AND segmento= 'ESTR' AND ambito= 'PM' AND entidade='00100' AND cod_visao = 1) B | J4: =IF(VLOOKUP(B4,Instruções!$F$6:$J$10,5,0)="", "ON "&VLOOKUP(B4,Instruções!$F$6:$J$10,4,0)&"_as_is = "&VLOOKUP(B4,Instruções!$F$6:$J$10,4,0)&"_to_be ", "ON "&VLOOKUP(B4,Instruções!$F$6:$J$10,4,0)&"_as_is = "&VLOOKUP(B4,Instruções!$F$6:$J$10,4,0)&"_to_be AND "&VLOOKUP(B4,Instruções!$F$6:$J$10,5,0)&"_as_is = "&VLOOKUP(B4,Instruções!$F$6:$J$10,5,0)&"_to_be ") -> ON entty_id_as_is = entty_id_to_be | K4: ="WHERE coalesce(cast("&F4&" as string), '') <> coalesce(cast("&G4&" as string), '') " -> WHERE coalesce(cast(accntng_frmwrk_sl_as_is as string), '') <> coalesce(cast(accntng_frmwrk_sl_to_be as string), '') | L4: ="SELECT count(*) AS NUM_REG_DIF FROM "&H4&" Inner join "&I4&J4&K4 -> SELECT count(*) AS NUM_REG_DIF FROM (SELECT entty_id as entty_id_as_is, accntng_frmwrk_sl as accntng_frmwrk_sl_as_is FROM cd_loan_tapes_bce.lt003_entity WHERE ref_date='2025-06-30' AND nome_perimetro= 'Individual IDComb' AND segmento= 'ESTR' AND ambito= 'PM' AND entidade='00100' AND cod_visao = 1) A Inner join (SELECT entty_id as entty_id_to_be, accntng_frmwrk_sl as accntng_frmwrk_sl_to_be FROM bu_loantape_work.lt003_entity WHERE ref_date='2025-06-30' AND nome_perimetro= 'Individual IDComb' AND segmento= 'ESTR' AND ambito= 'PM' AND entidade='00100' AND cod_visao = 1) B ON entty_id_as_is = entty_id_to_be WHERE coalesce(cast(accntng_frmwrk_sl_as_is as string), '') <> coalesce(cast(accntng_frmwrk_sl_to_be as string), '') | M4: Validação de campos | N4: ="SELECT 'Validação de campos' as tipologia_teste, '"&VLOOKUP(B4,Instruções!$F$6:$J$10,3,0)&"' AS TABELA, '"&E4&"' AS CAMPO, '"&Instruções!$D$7&"' as ref_date, coalesce(NUM_REG_DIF, 0) AS NUM_REG_DIF FROM ("&L4&") A " -> SELECT 'Validação de campos' as tipologia_teste, 'lt003_entity' AS TABELA, 'accntng_frmwrk_sl' AS CAMPO, '2025-06-30' as ref_date, coalesce(NUM_REG_DIF, 0) AS NUM_REG_DIF FROM (SELECT count(*) AS NUM_REG_DIF FROM (SELECT entty_id as entty_id_as_is, accntng_frmwrk_sl as accntng_frmwrk_sl_as_is FROM cd_loan_tapes_bce.lt003_entity WHERE ref_date='2025-06-30' AND nome_perimetro= 'Individual IDComb' AND segmento= 'ESTR' AND ambito= 'PM' AND entidade='00100' AND cod_visao = 1) A Inner join (SELECT entty_id as entty_id_to_be, accntng_frmwrk_sl as accntng_frmwrk_sl_to_be FROM bu_loantape_work.lt003_entity WHERE ref_date='2025-06-30' AND nome_perimetro= 'Individual IDComb' AND segmento= 'ESTR' AND ambito= 'PM' AND entidade='00100' AND cod_visao = 1) B ON entty_id_as_is = entty_id_to_be WHERE coalesce(cast(accntng_frmwrk_sl_as_is as string), '') <> coalesce(cast(accntng_frmwrk_sl_to_be as string), '') ) A | O4: =IF(O5="",N4,N4&$O$3) -> SELECT 'Validação de campos' as tipologia_teste, 'lt003_entity' AS TABELA, 'accntng_frmwrk_sl' AS CAMPO, '2025-06-30' as ref_date, coalesce(NUM_REG_DIF, 0) AS NUM_REG_DIF FROM (SELECT count(*) AS NUM_REG_DIF FROM (SELECT entty_id as entty_id_as_is, accntng_frmwrk_sl as accntng_frmwrk_sl_as_is FROM cd_loan_tapes_bce.lt003_entity WHERE ref_date='2025-06-30' AND nome_perimetro= 'Individual IDComb' AND segmento= 'ESTR' AND ambito= 'PM' AND entidade='00100' AND cod_visao = 1) A Inner join (SELECT entty_id as entty_id_to_be, accntng_frmwrk_sl as accntng_frmwrk_sl_to_be FROM bu_loantape_work.lt003_entity WHERE ref_date='2025-06-30' AND nome_perimetro= 'Individual IDComb' AND segmento= 'ESTR' AND ambito= 'PM' AND entidade='00100' AND cod_visao = 1) B ON entty_id_as_is = entty_id_to_be WHERE coalesce(cast(accntng_frmwrk_sl_as_is as string), '') <> coalesce(cast(accntng_frmwrk_sl_to_be as string), '') ) A UNION ALL | P4: =1 -> 1
B5: ENTTY | C5: =_xlfn.CONCAT(Instruções!$D$5,".",VLOOKUP(B5,Instruções!$F$5:$H$10,2,0)) -> cd_loan_tapes_bce.lt003_entity | D5: =_xlfn.CONCAT(Instruções!$D$6,".",VLOOKUP(B5,Instruções!$F$5:$H$10,3,0)) -> bu_loantape_work.lt003_entity | E5: annl_trnvr_le | F5: =E5&"_as_is" -> annl_trnvr_le_as_is | G5: =E5&"_to_be" -> annl_trnvr_le_to_be | H5: =IF(VLOOKUP(B5,Instruções!$F$6:$J$10,5,0)="", "(SELECT "&VLOOKUP(B5,Instruções!$F$6:$J$10,4,0)&" as "&VLOOKUP(B5,Instruções!$F$6:$J$10,4,0)&"_as_is, "&E5&" as "&F5&" FROM "&C5&" WHERE "&Instruções!$D$11&") A ", "(SELECT "&VLOOKUP(B5,Instruções!$F$6:$J$10,4,0)&" as "&VLOOKUP(B5,Instruções!$F$6:$J$10,4,0)&"_as_is, "&VLOOKUP(B5,Instruções!$F$6:$J$10,5,0)&" as "&VLOOKUP(B5,Instruções!$F$6:$J$10,5,0)&"_as_is,"&E5&" as "&F5&" FROM "&C5&" WHERE "&Instruções!$D$11&") A ") -> (SELECT entty_id as entty_id_as_is, annl_trnvr_le as annl_trnvr_le_as_is FROM cd_loan_tapes_bce.lt003_entity WHERE ref_date='2025-06-30' AND nome_perimetro= 'Individual IDComb' AND segmento= 'ESTR' AND ambito= 'PM' AND entidade='00100' AND cod_visao = 1) A | I5: =IF(VLOOKUP(B5,Instruções!$F$6:$J$10,5,0)="", "(SELECT "&VLOOKUP(B5,Instruções!$F$6:$J$10,4,0)&" as "&VLOOKUP(B5,Instruções!$F$6:$J$10,4,0)&"_to_be, "&E5&" as "&G5&" FROM "&D5&" WHERE "&Instruções!$D$11&") B ", "(SELECT "&VLOOKUP(B5,Instruções!$F$6:$J$10,4,0)&" as "&VLOOKUP(B5,Instruções!$F$6:$J$10,4,0)&"_to_be, "&VLOOKUP(B5,Instruções!$F$6:$J$10,5,0)&" as "&VLOOKUP(B5,Instruções!$F$6:$J$10,5,0)&"_to_be,"&E5&" as "&G5&" FROM "&D5&" WHERE "&Instruções!$D$11&") B ") -> (SELECT entty_id as entty_id_to_be, annl_trnvr_le as annl_trnvr_le_to_be FROM bu_loantape_work.lt003_entity WHERE ref_date='2025-06-30' AND nome_perimetro= 'Individual IDComb' AND segmento= 'ESTR' AND ambito= 'PM' AND entidade='00100' AND cod_visao = 1) B | J5: =IF(VLOOKUP(B5,Instruções!$F$6:$J$10,5,0)="", "ON "&VLOOKUP(B5,Instruções!$F$6:$J$10,4,0)&"_as_is = "&VLOOKUP(B5,Instruções!$F$6:$J$10,4,0)&"_to_be ", "ON "&VLOOKUP(B5,Instruções!$F$6:$J$10,4,0)&"_as_is = "&VLOOKUP(B5,Instruções!$F$6:$J$10,4,0)&"_to_be AND "&VLOOKUP(B5,Instruções!$F$6:$J$10,5,0)&"_as_is = "&VLOOKUP(B5,Instruções!$F$6:$J$10,5,0)&"_to_be ") -> ON entty_id_as_is = entty_id_to_be | K5: ="WHERE coalesce(cast("&F5&" as string), '') <> coalesce(cast("&G5&" as string), '') " -> WHERE coalesce(cast(annl_trnvr_le_as_is as string), '') <> coalesce(cast(annl_trnvr_le_to_be as string), '') | L5: ="SELECT count(*) AS NUM_REG_DIF FROM "&H5&" Inner join "&I5&J5&K5 -> SELECT count(*) AS NUM_REG_DIF FROM (SELECT entty_id as entty_id_as_is, annl_trnvr_le as annl_trnvr_le_as_is FROM cd_loan_tapes_bce.lt003_entity WHERE ref_date='2025-06-30' AND nome_perimetro= 'Individual IDComb' AND segmento= 'ESTR' AND ambito= 'PM' AND entidade='00100' AND cod_visao = 1) A Inner join (SELECT entty_id as entty_id_to_be, annl_trnvr_le as annl_trnvr_le_to_be FROM bu_loantape_work.lt003_entity WHERE ref_date='2025-06-30' AND nome_perimetro= 'Individual IDComb' AND segmento= 'ESTR' AND ambito= 'PM' AND entidade='00100' AND cod_visao = 1) B ON entty_id_as_is = entty_id_to_be WHERE coalesce(cast(annl_trnvr_le_as_is as string), '') <> coalesce(cast(annl_trnvr_le_to_be as string), '') | M5: Validação de campos | N5: ="SELECT 'Validação de campos' as tipologia_teste, '"&VLOOKUP(B5,Instruções!$F$6:$J$10,3,0)&"' AS TABELA, '"&E5&"' AS CAMPO, '"&Instruções!$D$7&"' as ref_date, coalesce(NUM_REG_DIF, 0) AS NUM_REG_DIF FROM ("&L5&") A " -> SELECT 'Validação de campos' as tipologia_teste, 'lt003_entity' AS TABELA, 'annl_trnvr_le' AS CAMPO, '2025-06-30' as ref_date, coalesce(NUM_REG_DIF, 0) AS NUM_REG_DIF FROM (SELECT count(*) AS NUM_REG_DIF FROM (SELECT entty_id as entty_id_as_is, annl_trnvr_le as annl_trnvr_le_as_is FROM cd_loan_tapes_bce.lt003_entity WHERE ref_date='2025-06-30' AND nome_perimetro= 'Individual IDComb' AND segmento= 'ESTR' AND ambito= 'PM' AND entidade='00100' AND cod_visao = 1) A Inner join (SELECT entty_id as entty_id_to_be, annl_trnvr_le as annl_trnvr_le_to_be FROM bu_loantape_work.lt003_entity WHERE ref_date='2025-06-30' AND nome_perimetro= 'Individual IDComb' AND segmento= 'ESTR' AND ambito= 'PM' AND entidade='00100' AND cod_visao = 1) B ON entty_id_as_is = entty_id_to_be WHERE coalesce(cast(annl_trnvr_le_as_is as string), '') <> coalesce(cast(annl_trnvr_le_to_be as string), '') ) A | O5: =IF(O6="",N5,N5&$O$3) -> SELECT 'Validação de campos' as tipologia_teste, 'lt003_entity' AS TABELA, 'annl_trnvr_le' AS CAMPO, '2025-06-30' as ref_date, coalesce(NUM_REG_DIF, 0) AS NUM_REG_DIF FROM (SELECT count(*) AS NUM_REG_DIF FROM (SELECT entty_id as entty_id_as_is, annl_trnvr_le as annl_trnvr_le_as_is FROM cd_loan_tapes_bce.lt003_entity WHERE ref_date='2025-06-30' AND nome_perimetro= 'Individual IDComb' AND segmento= 'ESTR' AND ambito= 'PM' AND entidade='00100' AND cod_visao = 1) A Inner join (SELECT entty_id as entty_id_to_be, annl_trnvr_le as annl_trnvr_le_to_be FROM bu_loantape_work.lt003_entity WHERE ref_date='2025-06-30' AND nome_perimetro= 'Individual IDComb' AND segmento= 'ESTR' AND ambito= 'PM' AND entidade='00100' AND cod_visao = 1) B ON entty_id_as_is = entty_id_to_be WHERE coalesce(cast(annl_trnvr_le_as_is as string), '') <> coalesce(cast(annl_trnvr_le_to_be as string), '') ) A UNION ALL | P5: =P4+1 -> 2
B6: ENTTY | C6: =_xlfn.CONCAT(Instruções!$D$5,".",VLOOKUP(B6,Instruções!$F$5:$H$10,2,0)) -> cd_loan_tapes_bce.lt003_entity | D6: =_xlfn.CONCAT(Instruções!$D$6,".",VLOOKUP(B6,Instruções!$F$5:$H$10,3,0)) -> bu_loantape_work.lt003_entity | E6: annl_trnvr_le_bdr | F6: =E6&"_as_is" -> annl_trnvr_le_bdr_as_is | G6: =E6&"_to_be" -> annl_trnvr_le_bdr_to_be | H6: =IF(VLOOKUP(B6,Instruções!$F$6:$J$10,5,0)="", "(SELECT "&VLOOKUP(B6,Instruções!$F$6:$J$10,4,0)&" as "&VLOOKUP(B6,Instruções!$F$6:$J$10,4,0)&"_as_is, "&E6&" as "&F6&" FROM "&C6&" WHERE "&Instruções!$D$11&") A ", "(SELECT "&VLOOKUP(B6,Instruções!$F$6:$J$10,4,0)&" as "&VLOOKUP(B6,Instruções!$F$6:$J$10,4,0)&"_as_is, "&VLOOKUP(B6,Instruções!$F$6:$J$10,5,0)&" as "&VLOOKUP(B6,Instruções!$F$6:$J$10,5,0)&"_as_is,"&E6&" as "&F6&" FROM "&C6&" WHERE "&Instruções!$D$11&") A ") -> (SELECT entty_id as entty_id_as_is, annl_trnvr_le_bdr as annl_trnvr_le_bdr_as_is FROM cd_loan_tapes_bce.lt003_entity WHERE ref_date='2025-06-30' AND nome_perimetro= 'Individual IDComb' AND segmento= 'ESTR' AND ambito= 'PM' AND entidade='00100' AND cod_visao = 1) A | I6: =IF(VLOOKUP(B6,Instruções!$F$6:$J$10,5,0)="", "(SELECT "&VLOOKUP(B6,Instruções!$F$6:$J$10,4,0)&" as "&VLOOKUP(B6,Instruções!$F$6:$J$10,4,0)&"_to_be, "&E6&" as "&G6&" FROM "&D6&" WHERE "&Instruções!$D$11&") B ", "(SELECT "&VLOOKUP(B6,Instruções!$F$6:$J$10,4,0)&" as "&VLOOKUP(B6,Instruções!$F$6:$J$10,4,0)&"_to_be, "&VLOOKUP(B6,Instruções!$F$6:$J$10,5,0)&" as "&VLOOKUP(B6,Instruções!$F$6:$J$10,5,0)&"_to_be,"&E6&" as "&G6&" FROM "&D6&" WHERE "&Instruções!$D$11&") B ") -> (SELECT entty_id as entty_id_to_be, annl_trnvr_le_bdr as annl_trnvr_le_bdr_to_be FROM bu_loantape_work.lt003_entity WHERE ref_date='2025-06-30' AND nome_perimetro= 'Individual IDComb' AND segmento= 'ESTR' AND ambito= 'PM' AND entidade='00100' AND cod_visao = 1) B | J6: =IF(VLOOKUP(B6,Instruções!$F$6:$J$10,5,0)="", "ON "&VLOOKUP(B6,Instruções!$F$6:$J$10,4,0)&"_as_is = "&VLOOKUP(B6,Instruções!$F$6:$J$10,4,0)&"_to_be ", "ON "&VLOOKUP(B6,Instruções!$F$6:$J$10,4,0)&"_as_is = "&VLOOKUP(B6,Instruções!$F$6:$J$10,4,0)&"_to_be AND "&VLOOKUP(B6,Instruções!$F$6:$J$10,5,0)&"_as_is = "&VLOOKUP(B6,Instruções!$F$6:$J$10,5,0)&"_to_be ") -> ON entty_id_as_is = entty_id_to_be | K6: ="WHERE coalesce(cast("&F6&" as string), '') <> coalesce(cast("&G6&" as string), '') " -> WHERE coalesce(cast(annl_trnvr_le_bdr_as_is as string), '') <> coalesce(cast(annl_trnvr_le_bdr_to_be as string), '') | L6: ="SELECT count(*) AS NUM_REG_DIF FROM "&H6&" Inner join "&I6&J6&K6 -> SELECT count(*) AS NUM_REG_DIF FROM (SELECT entty_id as entty_id_as_is, annl_trnvr_le_bdr as annl_trnvr_le_bdr_as_is FROM cd_loan_tapes_bce.lt003_entity WHERE ref_date='2025-06-30' AND nome_perimetro= 'Individual IDComb' AND segmento= 'ESTR' AND ambito= 'PM' AND entidade='00100' AND cod_visao = 1) A Inner join (SELECT entty_id as entty_id_to_be, annl_trnvr_le_bdr as annl_trnvr_le_bdr_to_be FROM bu_loantape_work.lt003_entity WHERE ref_date='2025-06-30' AND nome_perimetro= 'Individual IDComb' AND segmento= 'ESTR' AND ambito= 'PM' AND entidade='00100' AND cod_visao = 1) B ON entty_id_as_is = entty_id_to_be WHERE coalesce(cast(annl_trnvr_le_bdr_as_is as string), '') <> coalesce(cast(annl_trnvr_le_bdr_to_be as string), '') | M6: Validação de campos | N6: ="SELECT 'Validação de campos' as tipologia_teste, '"&VLOOKUP(B6,Instruções!$F$6:$J$10,3,0)&"' AS TABELA, '"&E6&"' AS CAMPO, '"&Instruções!$D$7&"' as ref_date, coalesce(NUM_REG_DIF, 0) AS NUM_REG_DIF FROM ("&L6&") A " -> SELECT 'Validação de campos' as tipologia_teste, 'lt003_entity' AS TABELA, 'annl_trnvr_le_bdr' AS CAMPO, '2025-06-30' as ref_date, coalesce(NUM_REG_DIF, 0) AS NUM_REG_DIF FROM (SELECT count(*) AS NUM_REG_DIF FROM (SELECT entty_id as entty_id_as_is, annl_trnvr_le_bdr as annl_trnvr_le_bdr_as_is FROM cd_loan_tapes_bce.lt003_entity WHERE ref_date='2025-06-30' AND nome_perimetro= 'Individual IDComb' AND segmento= 'ESTR' AND ambito= 'PM' AND entidade='00100' AND cod_visao = 1) A Inner join (SELECT entty_id as entty_id_to_be, annl_trnvr_le_bdr as annl_trnvr_le_bdr_to_be FROM bu_loantape_work.lt003_entity WHERE ref_date='2025-06-30' AND nome_perimetro= 'Individual IDComb' AND segmento= 'ESTR' AND ambito= 'PM' AND entidade='00100' AND cod_visao = 1) B ON entty_id_as_is = entty_id_to_be WHERE coalesce(cast(annl_trnvr_le_bdr_as_is as string), '') <> coalesce(cast(annl_trnvr_le_bdr_to_be as string), '') ) A | O6: =IF(O7="",N6,N6&$O$3) -> SELECT 'Validação de campos' as tipologia_teste, 'lt003_entity' AS TABELA, 'annl_trnvr_le_bdr' AS CAMPO, '2025-06-30' as ref_date, coalesce(NUM_REG_DIF, 0) AS NUM_REG_DIF FROM (SELECT count(*) AS NUM_REG_DIF FROM (SELECT entty_id as entty_id_as_is, annl_trnvr_le_bdr as annl_trnvr_le_bdr_as_is FROM cd_loan_tapes_bce.lt003_entity WHERE ref_date='2025-06-30' AND nome_perimetro= 'Individual IDComb' AND segmento= 'ESTR' AND ambito= 'PM' AND entidade='00100' AND cod_visao = 1) A Inner join (SELECT entty_id as entty_id_to_be, annl_trnvr_le_bdr as annl_trnvr_le_bdr_to_be FROM bu_loantape_work.lt003_entity WHERE ref_date='2025-06-30' AND nome_perimetro= 'Individual IDComb' AND segmento= 'ESTR' AND ambito= 'PM' AND entidade='00100' AND cod_visao = 1) B ON entty_id_as_is = entty_id_to_be WHERE coalesce(cast(annl_trnvr_le_bdr_as_is as string), '') <> coalesce(cast(annl_trnvr_le_bdr_to_be as string), '') ) A UNION ALL | P6: =P5+1 -> 3
B7: ENTTY | C7: =_xlfn.CONCAT(Instruções!$D$5,".",VLOOKUP(B7,Instruções!$F$5:$H$10,2,0)) -> cd_loan_tapes_bce.lt003_entity | D7: =_xlfn.CONCAT(Instruções!$D$6,".",VLOOKUP(B7,Instruções!$F$5:$H$10,3,0)) -> bu_loantape_work.lt003_entity | E7: annl_trnvr_prvs | F7: =E7&"_as_is" -> annl_trnvr_prvs_as_is | G7: =E7&"_to_be" -> annl_trnvr_prvs_to_be | H7: =IF(VLOOKUP(B7,Instruções!$F$6:$J$10,5,0)="", "(SELECT "&VLOOKUP(B7,Instruções!$F$6:$J$10,4,0)&" as "&VLOOKUP(B7,Instruções!$F$6:$J$10,4,0)&"_as_is, "&E7&" as "&F7&" FROM "&C7&" WHERE "&Instruções!$D$11&") A ", "(SELECT "&VLOOKUP(B7,Instruções!$F$6:$J$10,4,0)&" as "&VLOOKUP(B7,Instruções!$F$6:$J$10,4,0)&"_as_is, "&VLOOKUP(B7,Instruções!$F$6:$J$10,5,0)&" as "&VLOOKUP(B7,Instruções!$F$6:$J$10,5,0)&"_as_is,"&E7&" as "&F7&" FROM "&C7&" WHERE "&Instruções!$D$11&") A ") -> (SELECT entty_id as entty_id_as_is, annl_trnvr_prvs as annl_trnvr_prvs_as_is FROM cd_loan_tapes_bce.lt003_entity WHERE ref_date='2025-06-30' AND nome_perimetro= 'Individual IDComb' AND segmento= 'ESTR' AND ambito= 'PM' AND entidade='00100' AND cod_visao = 1) A | I7: =IF(VLOOKUP(B7,Instruções!$F$6:$J$10,5,0)="", "(SELECT "&VLOOKUP(B7,Instruções!$F$6:$J$10,4,0)&" as "&VLOOKUP(B7,Instruções!$F$6:$J$10,4,0)&"_to_be, "&E7&" as "&G7&" FROM "&D7&" WHERE "&Instruções!$D$11&") B ", "(SELECT "&VLOOKUP(B7,Instruções!$F$6:$J$10,4,0)&" as "&VLOOKUP(B7,Instruções!$F$6:$J$10,4,0)&"_to_be, "&VLOOKUP(B7,Instruções!$F$6:$J$10,5,0)&" as "&VLOOKUP(B7,Instruções!$F$6:$J$10,5,0)&"_to_be,"&E7&" as "&G7&" FROM "&D7&" WHERE "&Instruções!$D$11&") B ") -> (SELECT entty_id as entty_id_to_be, annl_trnvr_prvs as annl_trnvr_prvs_to_be FROM bu_loantape_work.lt003_entity WHERE ref_date='2025-06-30' AND nome_perimetro= 'Individual IDComb' AND segmento= 'ESTR' AND ambito= 'PM' AND entidade='00100' AND cod_visao = 1) B | J7: =IF(VLOOKUP(B7,Instruções!$F$6:$J$10,5,0)="", "ON "&VLOOKUP(B7,Instruções!$F$6:$J$10,4,0)&"_as_is = "&VLOOKUP(B7,Instruções!$F$6:$J$10,4,0)&"_to_be ", "ON "&VLOOKUP(B7,Instruções!$F$6:$J$10,4,0)&"_as_is = "&VLOOKUP(B7,Instruções!$F$6:$J$10,4,0)&"_to_be AND "&VLOOKUP(B7,Instruções!$F$6:$J$10,5,0)&"_as_is = "&VLOOKUP(B7,Instruções!$F$6:$J$10,5,0)&"_to_be ") -> ON entty_id_as_is = entty_id_to_be | K7: ="WHERE coalesce(cast("&F7&" as string), '') <> coalesce(cast("&G7&" as string), '') " -> WHERE coalesce(cast(annl_trnvr_prvs_as_is as string), '') <> coalesce(cast(annl_trnvr_prvs_to_be as string), '') | L7: ="SELECT count(*) AS NUM_REG_DIF FROM "&H7&" Inner join "&I7&J7&K7 -> SELECT count(*) AS NUM_REG_DIF FROM (SELECT entty_id as entty_id_as_is, annl_trnvr_prvs as annl_trnvr_prvs_as_is FROM cd_loan_tapes_bce.lt003_entity WHERE ref_date='2025-06-30' AND nome_perimetro= 'Individual IDComb' AND segmento= 'ESTR' AND ambito= 'PM' AND entidade='00100' AND cod_visao = 1) A Inner join (SELECT entty_id as entty_id_to_be, annl_trnvr_prvs as annl_trnvr_prvs_to_be FROM bu_loantape_work.lt003_entity WHERE ref_date='2025-06-30' AND nome_perimetro= 'Individual IDComb' AND segmento= 'ESTR' AND ambito= 'PM' AND entidade='00100' AND cod_visao = 1) B ON entty_id_as_is = entty_id_to_be WHERE coalesce(cast(annl_trnvr_prvs_as_is as string), '') <> coalesce(cast(annl_trnvr_prvs_to_be as string), '') | M7: Validação de campos | N7: ="SELECT 'Validação de campos' as tipologia_teste, '"&VLOOKUP(B7,Instruções!$F$6:$J$10,3,0)&"' AS TABELA, '"&E7&"' AS CAMPO, '"&Instruções!$D$7&"' as ref_date, coalesce(NUM_REG_DIF, 0) AS NUM_REG_DIF FROM ("&L7&") A " -> SELECT 'Validação de campos' as tipologia_teste, 'lt003_entity' AS TABELA, 'annl_trnvr_prvs' AS CAMPO, '2025-06-30' as ref_date, coalesce(NUM_REG_DIF, 0) AS NUM_REG_DIF FROM (SELECT count(*) AS NUM_REG_DIF FROM (SELECT entty_id as entty_id_as_is, annl_trnvr_prvs as annl_trnvr_prvs_as_is FROM cd_loan_tapes_bce.lt003_entity WHERE ref_date='2025-06-30' AND nome_perimetro= 'Individual IDComb' AND segmento= 'ESTR' AND ambito= 'PM' AND entidade='00100' AND cod_visao = 1) A Inner join (SELECT entty_id as entty_id_to_be, annl_trnvr_prvs as annl_trnvr_prvs_to_be FROM bu_loantape_work.lt003_entity WHERE ref_date='2025-06-30' AND nome_perimetro= 'Individual IDComb' AND segmento= 'ESTR' AND ambito= 'PM' AND entidade='00100' AND cod_visao = 1) B ON entty_id_as_is = entty_id_to_be WHERE coalesce(cast(annl_trnvr_prvs_as_is as string), '') <> coalesce(cast(annl_trnvr_prvs_to_be as string), '') ) A | O7: =IF(O8="",N7,N7&$O$3) -> SELECT 'Validação de campos' as tipologia_teste, 'lt003_entity' AS TABELA, 'annl_trnvr_prvs' AS CAMPO, '2025-06-30' as ref_date, coalesce(NUM_REG_DIF, 0) AS NUM_REG_DIF FROM (SELECT count(*) AS NUM_REG_DIF FROM (SELECT entty_id as entty_id_as_is, annl_trnvr_prvs as annl_trnvr_prvs_as_is FROM cd_loan_tapes_bce.lt003_entity WHERE ref_date='2025-06-30' AND nome_perimetro= 'Individual IDComb' AND segmento= 'ESTR' AND ambito= 'PM' AND entidade='00100' AND cod_visao = 1) A Inner join (SELECT entty_id as entty_id_to_be, annl_trnvr_prvs as annl_trnvr_prvs_to_be FROM bu_loantape_work.lt003_entity WHERE ref_date='2025-06-30' AND nome_perimetro= 'Individual IDComb' AND segmento= 'ESTR' AND ambito= 'PM' AND entidade='00100' AND cod_visao = 1) B ON entty_id_as_is = entty_id_to_be WHERE coalesce(cast(annl_trnvr_prvs_as_is as string), '') <> coalesce(cast(annl_trnvr_prvs_to_be as string), '') ) A UNION ALL | P7: =P6+1 -> 4
B8: ENTTY | C8: =_xlfn.CONCAT(Instruções!$D$5,".",VLOOKUP(B8,Instruções!$F$5:$H$10,2,0)) -> cd_loan_tapes_bce.lt003_entity | D8: =_xlfn.CONCAT(Instruções!$D$6,".",VLOOKUP(B8,Instruções!$F$5:$H$10,3,0)) -> bu_loantape_work.lt003_entity | E8: annl_trnvr_prvs_bdr | F8: =E8&"_as_is" -> annl_trnvr_prvs_bdr_as_is | G8: =E8&"_to_be" -> annl_trnvr_prvs_bdr_to_be | H8: =IF(VLOOKUP(B8,Instruções!$F$6:$J$10,5,0)="", "(SELECT "&VLOOKUP(B8,Instruções!$F$6:$J$10,4,0)&" as "&VLOOKUP(B8,Instruções!$F$6:$J$10,4,0)&"_as_is, "&E8&" as "&F8&" FROM "&C8&" WHERE "&Instruções!$D$11&") A ", "(SELECT "&VLOOKUP(B8,Instruções!$F$6:$J$10,4,0)&" as "&VLOOKUP(B8,Instruções!$F$6:$J$10,4,0)&"_as_is, "&VLOOKUP(B8,Instruções!$F$6:$J$10,5,0)&" as "&VLOOKUP(B8,Instruções!$F$6:$J$10,5,0)&"_as_is,"&E8&" as "&F8&" FROM "&C8&" WHERE "&Instruções!$D$11&") A ") -> (SELECT entty_id as entty_id_as_is, annl_trnvr_prvs_bdr as annl_trnvr_prvs_bdr_as_is FROM cd_loan_tapes_bce.lt003_entity WHERE ref_date='2025-06-30' AND nome_perimetro= 'Individual IDComb' AND segmento= 'ESTR' AND ambito= 'PM' AND entidade='00100' AND cod_visao = 1) A | I8: =IF(VLOOKUP(B8,Instruções!$F$6:$J$10,5,0)="", "(SELECT "&VLOOKUP(B8,Instruções!$F$6:$J$10,4,0)&" as "&VLOOKUP(B8,Instruções!$F$6:$J$10,4,0)&"_to_be, "&E8&" as "&G8&" FROM "&D8&" WHERE "&Instruções!$D$11&") B ", "(SELECT "&VLOOKUP(B8,Instruções!$F$6:$J$10,4,0)&" as "&VLOOKUP(B8,Instruções!$F$6:$J$10,4,0)&"_to_be, "&VLOOKUP(B8,Instruções!$F$6:$J$10,5,0)&" as "&VLOOKUP(B8,Instruções!$F$6:$J$10,5,0)&"_to_be,"&E8&" as "&G8&" FROM "&D8&" WHERE "&Instruções!$D$11&") B ") -> (SELECT entty_id as entty_id_to_be, annl_trnvr_prvs_bdr as annl_trnvr_prvs_bdr_to_be FROM bu_loantape_work.lt003_entity WHERE ref_date='2025-06-30' AND nome_perimetro= 'Individual IDComb' AND segmento= 'ESTR' AND ambito= 'PM' AND entidade='00100' AND cod_visao = 1) B | J8: =IF(VLOOKUP(B8,Instruções!$F$6:$J$10,5,0)="", "ON "&VLOOKUP(B8,Instruções!$F$6:$J$10,4,0)&"_as_is = "&VLOOKUP(B8,Instruções!$F$6:$J$10,4,0)&"_to_be ", "ON "&VLOOKUP(B8,Instruções!$F$6:$J$10,4,0)&"_as_is = "&VLOOKUP(B8,Instruções!$F$6:$J$10,4,0)&"_to_be AND "&VLOOKUP(B8,Instruções!$F$6:$J$10,5,0)&"_as_is = "&VLOOKUP(B8,Instruções!$F$6:$J$10,5,0)&"_to_be ") -> ON entty_id_as_is = entty_id_to_be | K8: ="WHERE coalesce(cast("&F8&" as string), '') <> coalesce(cast("&G8&" as string), '') " -> WHERE coalesce(cast(annl_trnvr_prvs_bdr_as_is as string), '') <> coalesce(cast(annl_trnvr_prvs_bdr_to_be as string), '') | L8: ="SELECT count(*) AS NUM_REG_DIF FROM "&H8&" Inner join "&I8&J8&K8 -> SELECT count(*) AS NUM_REG_DIF FROM (SELECT entty_id as entty_id_as_is, annl_trnvr_prvs_bdr as annl_trnvr_prvs_bdr_as_is FROM cd_loan_tapes_bce.lt003_entity WHERE ref_date='2025-06-30' AND nome_perimetro= 'Individual IDComb' AND segmento= 'ESTR' AND ambito= 'PM' AND entidade='00100' AND cod_visao = 1) A Inner join (SELECT entty_id as entty_id_to_be, annl_trnvr_prvs_bdr as annl_trnvr_prvs_bdr_to_be FROM bu_loantape_work.lt003_entity WHERE ref_date='2025-06-30' AND nome_perimetro= 'Individual IDComb' AND segmento= 'ESTR' AND ambito= 'PM' AND entidade='00100' AND cod_visao = 1) B ON entty_id_as_is = entty_id_to_be WHERE coalesce(cast(annl_trnvr_prvs_bdr_as_is as string), '') <> coalesce(cast(annl_trnvr_prvs_bdr_to_be as string), '') | M8: Validação de campos | N8: ="SELECT 'Validação de campos' as tipologia_teste, '"&VLOOKUP(B8,Instruções!$F$6:$J$10,3,0)&"' AS TABELA, '"&E8&"' AS CAMPO, '"&Instruções!$D$7&"' as ref_date, coalesce(NUM_REG_DIF, 0) AS NUM_REG_DIF FROM ("&L8&") A " -> SELECT 'Validação de campos' as tipologia_teste, 'lt003_entity' AS TABELA, 'annl_trnvr_prvs_bdr' AS CAMPO, '2025-06-30' as ref_date, coalesce(NUM_REG_DIF, 0) AS NUM_REG_DIF FROM (SELECT count(*) AS NUM_REG_DIF FROM (SELECT entty_id as entty_id_as_is, annl_trnvr_prvs_bdr as annl_trnvr_prvs_bdr_as_is FROM cd_loan_tapes_bce.lt003_entity WHERE ref_date='2025-06-30' AND nome_perimetro= 'Individual IDComb' AND segmento= 'ESTR' AND ambito= 'PM' AND entidade='00100' AND cod_visao = 1) A Inner join (SELECT entty_id as entty_id_to_be, annl_trnvr_prvs_bdr as annl_trnvr_prvs_bdr_to_be FROM bu_loantape_work.lt003_entity WHERE ref_date='2025-06-30' AND nome_perimetro= 'Individual IDComb' AND segmento= 'ESTR' AND ambito= 'PM' AND entidade='00100' AND cod_visao = 1) B ON entty_id_as_is = entty_id_to_be WHERE coalesce(cast(annl_trnvr_prvs_bdr_as_is as string), '') <> coalesce(cast(annl_trnvr_prvs_bdr_to_be as string), '') ) A | O8: =IF(O9="",N8,N8&$O$3) -> SELECT 'Validação de campos' as tipologia_teste, 'lt003_entity' AS TABELA, 'annl_trnvr_prvs_bdr' AS CAMPO, '2025-06-30' as ref_date, coalesce(NUM_REG_DIF, 0) AS NUM_REG_DIF FROM (SELECT count(*) AS NUM_REG_DIF FROM (SELECT entty_id as entty_id_as_is, annl_trnvr_prvs_bdr as annl_trnvr_prvs_bdr_as_is FROM cd_loan_tapes_bce.lt003_entity WHERE ref_date='2025-06-30' AND nome_perimetro= 'Individual IDComb' AND segmento= 'ESTR' AND ambito= 'PM' AND entidade='00100' AND cod_visao = 1) A Inner join (SELECT entty_id as entty_id_to_be, annl_trnvr_prvs_bdr as annl_trnvr_prvs_bdr_to_be FROM bu_loantape_work.lt003_entity WHERE ref_date='2025-06-30' AND nome_perimetro= 'Individual IDComb' AND segmento= 'ESTR' AND ambito= 'PM' AND entidade='00100' AND cod_visao = 1) B ON entty_id_as_is = entty_id_to_be WHERE coalesce(cast(annl_trnvr_prvs_bdr_as_is as string), '') <> coalesce(cast(annl_trnvr_prvs_bdr_to_be as string), '') ) A UNION ALL | P8: =P7+1 -> 5
B9: ENTTY | C9: =_xlfn.CONCAT(Instruções!$D$5,".",VLOOKUP(B9,Instruções!$F$5:$H$10,2,0)) -> cd_loan_tapes_bce.lt003_entity | D9: =_xlfn.CONCAT(Instruções!$D$6,".",VLOOKUP(B9,Instruções!$F$5:$H$10,3,0)) -> bu_loantape_work.lt003_entity | E9: capex | F9: =E9&"_as_is" -> capex_as_is | G9: =E9&"_to_be" -> capex_to_be | H9: =IF(VLOOKUP(B9,Instruções!$F$6:$J$10,5,0)="", "(SELECT "&VLOOKUP(B9,Instruções!$F$6:$J$10,4,0)&" as "&VLOOKUP(B9,Instruções!$F$6:$J$10,4,0)&"_as_is, "&E9&" as "&F9&" FROM "&C9&" WHERE "&Instruções!$D$11&") A ", "(SELECT "&VLOOKUP(B9,Instruções!$F$6:$J$10,4,0)&" as "&VLOOKUP(B9,Instruções!$F$6:$J$10,4,0)&"_as_is, "&VLOOKUP(B9,Instruções!$F$6:$J$10,5,0)&" as "&VLOOKUP(B9,Instruções!$F$6:$J$10,5,0)&"_as_is,"&E9&" as "&F9&" FROM "&C9&" WHERE "&Instruções!$D$11&") A ") -> (SELECT entty_id as entty_id_as_is, capex as capex_as_is FROM cd_loan_tapes_bce.lt003_entity WHERE ref_date='2025-06-30' AND nome_perimetro= 'Individual IDComb' AND segmento= 'ESTR' AND ambito= 'PM' AND entidade='00100' AND cod_visao = 1) A | I9: =IF(VLOOKUP(B9,Instruções!$F$6:$J$10,5,0)="", "(SELECT "&VLOOKUP(B9,Instruções!$F$6:$J$10,4,0)&" as "&VLOOKUP(B9,Instruções!$F$6:$J$10,4,0)&"_to_be, "&E9&" as "&G9&" FROM "&D9&" WHERE "&Instruções!$D$11&") B ", "(SELECT "&VLOOKUP(B9,Instruções!$F$6:$J$10,4,0)&" as "&VLOOKUP(B9,Instruções!$F$6:$J$10,4,0)&"_to_be, "&VLOOKUP(B9,Instruções!$F$6:$J$10,5,0)&" as "&VLOOKUP(B9,Instruções!$F$6:$J$10,5,0)&"_to_be,"&E9&" as "&G9&" FROM "&D9&" WHERE "&Instruções!$D$11&") B ") -> (SELECT entty_id as entty_id_to_be, capex as capex_to_be FROM bu_loantape_work.lt003_entity WHERE ref_date='2025-06-30' AND nome_perimetro= 'Individual IDComb' AND segmento= 'ESTR' AND ambito= 'PM' AND entidade='00100' AND cod_visao = 1) B | J9: =IF(VLOOKUP(B9,Instruções!$F$6:$J$10,5,0)="", "ON "&VLOOKUP(B9,Instruções!$F$6:$J$10,4,0)&"_as_is = "&VLOOKUP(B9,Instruções!$F$6:$J$10,4,0)&"_to_be ", "ON "&VLOOKUP(B9,Instruções!$F$6:$J$10,4,0)&"_as_is = "&VLOOKUP(B9,Instruções!$F$6:$J$10,4,0)&"_to_be AND "&VLOOKUP(B9,Instruções!$F$6:$J$10,5,0)&"_as_is = "&VLOOKUP(B9,Instruções!$F$6:$J$10,5,0)&"_to_be ") -> ON entty_id_as_is = entty_id_to_be | K9: ="WHERE coalesce(cast("&F9&" as string), '') <> coalesce(cast("&G9&" as string), '') " -> WHERE coalesce(cast(capex_as_is as string), '') <> coalesce(cast(capex_to_be as string), '') | L9: ="SELECT count(*) AS NUM_REG_DIF FROM "&H9&" Inner join "&I9&J9&K9 -> SELECT count(*) AS NUM_REG_DIF FROM (SELECT entty_id as entty_id_as_is, capex as capex_as_is FROM cd_loan_tapes_bce.lt003_entity WHERE ref_date='2025-06-30' AND nome_perimetro= 'Individual IDComb' AND segmento= 'ESTR' AND ambito= 'PM' AND entidade='00100' AND cod_visao = 1) A Inner join (SELECT entty_id as entty_id_to_be, capex as capex_to_be FROM bu_loantape_work.lt003_entity WHERE ref_date='2025-06-30' AND nome_perimetro= 'Individual IDComb' AND segmento= 'ESTR' AND ambito= 'PM' AND entidade='00100' AND cod_visao = 1) B ON entty_id_as_is = entty_id_to_be WHERE coalesce(cast(capex_as_is as string), '') <> coalesce(cast(capex_to_be as string), '') | M9: Validação de campos | N9: ="SELECT 'Validação de campos' as tipologia_teste, '"&VLOOKUP(B9,Instruções!$F$6:$J$10,3,0)&"' AS TABELA, '"&E9&"' AS CAMPO, '"&Instruções!$D$7&"' as ref_date, coalesce(NUM_REG_DIF, 0) AS NUM_REG_DIF FROM ("&L9&") A " -> SELECT 'Validação de campos' as tipologia_teste, 'lt003_entity' AS TABELA, 'capex' AS CAMPO, '2025-06-30' as ref_date, coalesce(NUM_REG_DIF, 0) AS NUM_REG_DIF FROM (SELECT count(*) AS NUM_REG_DIF FROM (SELECT entty_id as entty_id_as_is, capex as capex_as_is FROM cd_loan_tapes_bce.lt003_entity WHERE ref_date='2025-06-30' AND nome_perimetro= 'Individual IDComb' AND segmento= 'ESTR' AND ambito= 'PM' AND entidade='00100' AND cod_visao = 1) A Inner join (SELECT entty_id as entty_id_to_be, capex as capex_to_be FROM bu_loantape_work.lt003_entity WHERE ref_date='2025-06-30' AND nome_perimetro= 'Individual IDComb' AND segmento= 'ESTR' AND ambito= 'PM' AND entidade='00100' AND cod_visao = 1) B ON entty_id_as_is = entty_id_to_be WHERE coalesce(cast(capex_as_is as string), '') <> coalesce(cast(capex_to_be as string), '') ) A | O9: =IF(O10="",N9,N9&$O$3) -> SELECT 'Validação de campos' as tipologia_teste, 'lt003_entity' AS TABELA, 'capex' AS CAMPO, '2025-06-30' as ref_date, coalesce(NUM_REG_DIF, 0) AS NUM_REG_DIF FROM (SELECT count(*) AS NUM_REG_DIF FROM (SELECT entty_id as entty_id_as_is, capex as capex_as_is FROM cd_loan_tapes_bce.lt003_entity WHERE ref_date='2025-06-30' AND nome_perimetro= 'Individual IDComb' AND segmento= 'ESTR' AND ambito= 'PM' AND entidade='00100' AND cod_visao = 1) A Inner join (SELECT entty_id as entty_id_to_be, capex as capex_to_be FROM bu_loantape_work.lt003_entity WHERE ref_date='2025-06-30' AND nome_perimetro= 'Individual IDComb' AND segmento= 'ESTR' AND ambito= 'PM' AND entidade='00100' AND cod_visao = 1) B ON entty_id_as_is = entty_id_to_be WHERE coalesce(cast(capex_as_is as string), '') <> coalesce(cast(capex_to_be as string), '') ) A UNION ALL | P9: =P8+1 -> 6
B10: ENTTY | C10: =_xlfn.CONCAT(Instruções!$D$5,".",VLOOKUP(B10,Instruções!$F$5:$H$10,2,0)) -> cd_loan_tapes_bce.lt003_entity | D10: =_xlfn.CONCAT(Instruções!$D$6,".",VLOOKUP(B10,Instruções!$F$5:$H$10,3,0)) -> bu_loantape_work.lt003_entity | E10: capex_prvs | F10: =E10&"_as_is" -> capex_prvs_as_is | G10: =E10&"_to_be" -> capex_prvs_to_be | H10: =IF(VLOOKUP(B10,Instruções!$F$6:$J$10,5,0)="", "(SELECT "&VLOOKUP(B10,Instruções!$F$6:$J$10,4,0)&" as "&VLOOKUP(B10,Instruções!$F$6:$J$10,4,0)&"_as_is, "&E10&" as "&F10&" FROM "&C10&" WHERE "&Instruções!$D$11&") A ", "(SELECT "&VLOOKUP(B10,Instruções!$F$6:$J$10,4,0)&" as "&VLOOKUP(B10,Instruções!$F$6:$J$10,4,0)&"_as_is, "&VLOOKUP(B10,Instruções!$F$6:$J$10,5,0)&" as "&VLOOKUP(B10,Instruções!$F$6:$J$10,5,0)&"_as_is,"&E10&" as "&F10&" FROM "&C10&" WHERE "&Instruções!$D$11&") A ") -> (SELECT entty_id as entty_id_as_is, capex_prvs as capex_prvs_as_is FROM cd_loan_tapes_bce.lt003_entity WHERE ref_date='2025-06-30' AND nome_perimetro= 'Individual IDComb' AND segmento= 'ESTR' AND ambito= 'PM' AND entidade='00100' AND cod_visao = 1) A | I10: =IF(VLOOKUP(B10,Instruções!$F$6:$J$10,5,0)="", "(SELECT "&VLOOKUP(B10,Instruções!$F$6:$J$10,4,0)&" as "&VLOOKUP(B10,Instruções!$F$6:$J$10,4,0)&"_to_be, "&E10&" as "&G10&" FROM "&D10&" WHERE "&Instruções!$D$11&") B ", "(SELECT "&VLOOKUP(B10,Instruções!$F$6:$J$10,4,0)&" as "&VLOOKUP(B10,Instruções!$F$6:$J$10,4,0)&"_to_be, "&VLOOKUP(B10,Instruções!$F$6:$J$10,5,0)&" as "&VLOOKUP(B10,Instruções!$F$6:$J$10,5,0)&"_to_be,"&E10&" as "&G10&" FROM "&D10&" WHERE "&Instruções!$D$11&") B ") -> (SELECT entty_id as entty_id_to_be, capex_prvs as capex_prvs_to_be FROM bu_loantape_work.lt003_entity WHERE ref_date='2025-06-30' AND nome_perimetro= 'Individual IDComb' AND segmento= 'ESTR' AND ambito= 'PM' AND entidade='00100' AND cod_visao = 1) B | J10: =IF(VLOOKUP(B10,Instruções!$F$6:$J$10,5,0)="", "ON "&VLOOKUP(B10,Instruções!$F$6:$J$10,4,0)&"_as_is = "&VLOOKUP(B10,Instruções!$F$6:$J$10,4,0)&"_to_be ", "ON "&VLOOKUP(B10,Instruções!$F$6:$J$10,4,0)&"_as_is = "&VLOOKUP(B10,Instruções!$F$6:$J$10,4,0)&"_to_be AND "&VLOOKUP(B10,Instruções!$F$6:$J$10,5,0)&"_as_is = "&VLOOKUP(B10,Instruções!$F$6:$J$10,5,0)&"_to_be ") -> ON entty_id_as_is = entty_id_to_be | K10: ="WHERE coalesce(cast("&F10&" as string), '') <> coalesce(cast("&G10&" as string), '') " -> WHERE coalesce(cast(capex_prvs_as_is as string), '') <> coalesce(cast(capex_prvs_to_be as string), '') | L10: ="SELECT count(*) AS NUM_REG_DIF FROM "&H10&" Inner join "&I10&J10&K10 -> SELECT count(*) AS NUM_REG_DIF FROM (SELECT entty_id as entty_id_as_is, capex_prvs as capex_prvs_as_is FROM cd_loan_tapes_bce.lt003_entity WHERE ref_date='2025-06-30' AND nome_perimetro= 'Individual IDComb' AND segmento= 'ESTR' AND ambito= 'PM' AND entidade='00100' AND cod_visao = 1) A Inner join (SELECT entty_id as entty_id_to_be, capex_prvs as capex_prvs_to_be FROM bu_loantape_work.lt003_entity WHERE ref_date='2025-06-30' AND nome_perimetro= 'Individual IDComb' AND segmento= 'ESTR' AND ambito= 'PM' AND entidade='00100' AND cod_visao = 1) B ON entty_id_as_is = entty_id_to_be WHERE coalesce(cast(capex_prvs_as_is as string), '') <> coalesce(cast(capex_prvs_to_be as string), '') | M10: Validação de campos | N10: ="SELECT 'Validação de campos' as tipologia_teste, '"&VLOOKUP(B10,Instruções!$F$6:$J$10,3,0)&"' AS TABELA, '"&E10&"' AS CAMPO, '"&Instruções!$D$7&"' as ref_date, coalesce(NUM_REG_DIF, 0) AS NUM_REG_DIF FROM ("&L10&") A " -> SELECT 'Validação de campos' as tipologia_teste, 'lt003_entity' AS TABELA, 'capex_prvs' AS CAMPO, '2025-06-30' as ref_date, coalesce(NUM_REG_DIF, 0) AS NUM_REG_DIF FROM (SELECT count(*) AS NUM_REG_DIF FROM (SELECT entty_id as entty_id_as_is, capex_prvs as capex_prvs_as_is FROM cd_loan_tapes_bce.lt003_entity WHERE ref_date='2025-06-30' AND nome_perimetro= 'Individual IDComb' AND segmento= 'ESTR' AND ambito= 'PM' AND entidade='00100' AND cod_visao = 1) A Inner join (SELECT entty_id as entty_id_to_be, capex_prvs as capex_prvs_to_be FROM bu_loantape_work.lt003_entity WHERE ref_date='2025-06-30' AND nome_perimetro= 'Individual IDComb' AND segmento= 'ESTR' AND ambito= 'PM' AND entidade='00100' AND cod_visao = 1) B ON entty_id_as_is = entty_id_to_be WHERE coalesce(cast(capex_prvs_as_is as string), '') <> coalesce(cast(capex_prvs_to_be as string), '') ) A | O10: =IF(O11="",N10,N10&$O$3) -> SELECT 'Validação de campos' as tipologia_teste, 'lt003_entity' AS TABELA, 'capex_prvs' AS CAMPO, '2025-06-30' as ref_date, coalesce(NUM_REG_DIF, 0) AS NUM_REG_DIF FROM (SELECT count(*) AS NUM_REG_DIF FROM (SELECT entty_id as entty_id_as_is, capex_prvs as capex_prvs_as_is FROM cd_loan_tapes_bce.lt003_entity WHERE ref_date='2025-06-30' AND nome_perimetro= 'Individual IDComb' AND segmento= 'ESTR' AND ambito= 'PM' AND entidade='00100' AND cod_visao = 1) A Inner join (SELECT entty_id as entty_id_to_be, capex_prvs as capex_prvs_to_be FROM bu_loantape_work.lt003_entity WHERE ref_date='2025-06-30' AND nome_perimetro= 'Individual IDComb' AND segmento= 'ESTR' AND ambito= 'PM' AND entidade='00100' AND cod_visao = 1) B ON entty_id_as_is = entty_id_to_be WHERE coalesce(cast(capex_prvs_as_is as string), '') <> coalesce(cast(capex_prvs_to_be as string), '') ) A UNION ALL | P10: =P9+1 -> 7
B11: ENTTY | C11: =_xlfn.CONCAT(Instruções!$D$5,".",VLOOKUP(B11,Instruções!$F$5:$H$10,2,0)) -> cd_loan_tapes_bce.lt003_entity | D11: =_xlfn.CONCAT(Instruções!$D$6,".",VLOOKUP(B11,Instruções!$F$5:$H$10,3,0)) -> bu_loantape_work.lt003_entity | E11: cllctn_md | F11: =E11&"_as_is" -> cllctn_md_as_is | G11: =E11&"_to_be" -> cllctn_md_to_be | H11: =IF(VLOOKUP(B11,Instruções!$F$6:$J$10,5,0)="", "(SELECT "&VLOOKUP(B11,Instruções!$F$6:$J$10,4,0)&" as "&VLOOKUP(B11,Instruções!$F$6:$J$10,4,0)&"_as_is, "&E11&" as "&F11&" FROM "&C11&" WHERE "&Instruções!$D$11&") A ", "(SELECT "&VLOOKUP(B11,Instruções!$F$6:$J$10,4,0)&" as "&VLOOKUP(B11,Instruções!$F$6:$J$10,4,0)&"_as_is, "&VLOOKUP(B11,Instruções!$F$6:$J$10,5,0)&" as "&VLOOKUP(B11,Instruções!$F$6:$J$10,5,0)&"_as_is,"&E11&" as "&F11&" FROM "&C11&" WHERE "&Instruções!$D$11&") A ") -> (SELECT entty_id as entty_id_as_is, cllctn_md as cllctn_md_as_is FROM cd_loan_tapes_bce.lt003_entity WHERE ref_date='2025-06-30' AND nome_perimetro= 'Individual IDComb' AND segmento= 'ESTR' AND ambito= 'PM' AND entidade='00100' AND cod_visao = 1) A | I11: =IF(VLOOKUP(B11,Instruções!$F$6:$J$10,5,0)="", "(SELECT "&VLOOKUP(B11,Instruções!$F$6:$J$10,4,0)&" as "&VLOOKUP(B11,Instruções!$F$6:$J$10,4,0)&"_to_be, "&E11&" as "&G11&" FROM "&D11&" WHERE "&Instruções!$D$11&") B ", "(SELECT "&VLOOKUP(B11,Instruções!$F$6:$J$10,4,0)&" as "&VLOOKUP(B11,Instruções!$F$6:$J$10,4,0)&"_to_be, "&VLOOKUP(B11,Instruções!$F$6:$J$10,5,0)&" as "&VLOOKUP(B11,Instruções!$F$6:$J$10,5,0)&"_to_be,"&E11&" as "&G11&" FROM "&D11&" WHERE "&Instruções!$D$11&") B ") -> (SELECT entty_id as entty_id_to_be, cllctn_md as cllctn_md_to_be FROM bu_loantape_work.lt003_entity WHERE ref_date='2025-06-30' AND nome_perimetro= 'Individual IDComb' AND segmento= 'ESTR' AND ambito= 'PM' AND entidade='00100' AND cod_visao = 1) B | J11: =IF(VLOOKUP(B11,Instruções!$F$6:$J$10,5,0)="", "ON "&VLOOKUP(B11,Instruções!$F$6:$J$10,4,0)&"_as_is = "&VLOOKUP(B11,Instruções!$F$6:$J$10,4,0)&"_to_be ", "ON "&VLOOKUP(B11,Instruções!$F$6:$J$10,4,0)&"_as_is = "&VLOOKUP(B11,Instruções!$F$6:$J$10,4,0)&"_to_be AND "&VLOOKUP(B11,Instruções!$F$6:$J$10,5,0)&"_as_is = "&VLOOKUP(B11,Instruções!$F$6:$J$10,5,0)&"_to_be ") -> ON entty_id_as_is = entty_id_to_be | K11: ="WHERE coalesce(cast("&F11&" as string), '') <> coalesce(cast("&G11&" as string), '') " -> WHERE coalesce(cast(cllctn_md_as_is as string), '') <> coalesce(cast(cllctn_md_to_be as string), '') | L11: ="SELECT count(*) AS NUM_REG_DIF FROM "&H11&" Inner join "&I11&J11&K11 -> SELECT count(*) AS NUM_REG_DIF FROM (SELECT entty_id as entty_id_as_is, cllctn_md as cllctn_md_as_is FROM cd_loan_tapes_bce.lt003_entity WHERE ref_date='2025-06-30' AND nome_perimetro= 'Individual IDComb' AND segmento= 'ESTR' AND ambito= 'PM' AND entidade='00100' AND cod_visao = 1) A Inner join (SELECT entty_id as entty_id_to_be, cllctn_md as cllctn_md_to_be FROM bu_loantape_work.lt003_entity WHERE ref_date='2025-06-30' AND nome_perimetro= 'Individual IDComb' AND segmento= 'ESTR' AND ambito= 'PM' AND entidade='00100' AND cod_visao = 1) B ON entty_id_as_is = entty_id_to_be WHERE coalesce(cast(cllctn_md_as_is as string), '') <> coalesce(cast(cllctn_md_to_be as string), '') | M11: Validação de campos | N11: ="SELECT 'Validação de campos' as tipologia_teste, '"&VLOOKUP(B11,Instruções!$F$6:$J$10,3,0)&"' AS TABELA, '"&E11&"' AS CAMPO, '"&Instruções!$D$7&"' as ref_date, coalesce(NUM_REG_DIF, 0) AS NUM_REG_DIF FROM ("&L11&") A " -> SELECT 'Validação de campos' as tipologia_teste, 'lt003_entity' AS TABELA, 'cllctn_md' AS CAMPO, '2025-06-30' as ref_date, coalesce(NUM_REG_DIF, 0) AS NUM_REG_DIF FROM (SELECT count(*) AS NUM_REG_DIF FROM (SELECT entty_id as entty_id_as_is, cllctn_md as cllctn_md_as_is FROM cd_loan_tapes_bce.lt003_entity WHERE ref_date='2025-06-30' AND nome_perimetro= 'Individual IDComb' AND segmento= 'ESTR' AND ambito= 'PM' AND entidade='00100' AND cod_visao = 1) A Inner join (SELECT entty_id as entty_id_to_be, cllctn_md as cllctn_md_to_be FROM bu_loantape_work.lt003_entity WHERE ref_date='2025-06-30' AND nome_perimetro= 'Individual IDComb' AND segmento= 'ESTR' AND ambito= 'PM' AND entidade='00100' AND cod_visao = 1) B ON entty_id_as_is = entty_id_to_be WHERE coalesce(cast(cllctn_md_as_is as string), '') <> coalesce(cast(cllctn_md_to_be as string), '') ) A | O11: =IF(O12="",N11,N11&$O$3) -> SELECT 'Validação de campos' as tipologia_teste, 'lt003_entity' AS TABELA, 'cllctn_md' AS CAMPO, '2025-06-30' as ref_date, coalesce(NUM_REG_DIF, 0) AS NUM_REG_DIF FROM (SELECT count(*) AS NUM_REG_DIF FROM (SELECT entty_id as entty_id_as_is, cllctn_md as cllctn_md_as_is FROM cd_loan_tapes_bce.lt003_entity WHERE ref_date='2025-06-30' AND nome_perimetro= 'Individual IDComb' AND segmento= 'ESTR' AND ambito= 'PM' AND entidade='00100' AND cod_visao = 1) A Inner join (SELECT entty_id as entty_id_to_be, cllctn_md as cllctn_md_to_be FROM bu_loantape_work.lt003_entity WHERE ref_date='2025-06-30' AND nome_perimetro= 'Individual IDComb' AND segmento= 'ESTR' AND ambito= 'PM' AND entidade='00100' AND cod_visao = 1) B ON entty_id_as_is = entty_id_to_be WHERE coalesce(cast(cllctn_md_as_is as string), '') <> coalesce(cast(cllctn_md_to_be as string), '') ) A UNION ALL | P11: =P10+1 -> 8
B12: ENTTY | C12: =_xlfn.CONCAT(Instruções!$D$5,".",VLOOKUP(B12,Instruções!$F$5:$H$10,2,0)) -> cd_loan_tapes_bce.lt003_entity | D12: =_xlfn.CONCAT(Instruções!$D$6,".",VLOOKUP(B12,Instruções!$F$5:$H$10,3,0)) -> bu_loantape_work.lt003_entity | E12: cntry | F12: =E12&"_as_is" -> cntry_as_is | G12: =E12&"_to_be" -> cntry_to_be | H12: =IF(VLOOKUP(B12,Instruções!$F$6:$J$10,5,0)="", "(SELECT "&VLOOKUP(B12,Instruções!$F$6:$J$10,4,0)&" as "&VLOOKUP(B12,Instruções!$F$6:$J$10,4,0)&"_as_is, "&E12&" as "&F12&" FROM "&C12&" WHERE "&Instruções!$D$11&") A ", "(SELECT "&VLOOKUP(B12,Instruções!$F$6:$J$10,4,0)&" as "&VLOOKUP(B12,Instruções!$F$6:$J$10,4,0)&"_as_is, "&VLOOKUP(B12,Instruções!$F$6:$J$10,5,0)&" as "&VLOOKUP(B12,Instruções!$F$6:$J$10,5,0)&"_as_is,"&E12&" as "&F12&" FROM "&C12&" WHERE "&Instruções!$D$11&") A ") -> (SELECT entty_id as entty_id_as_is, cntry as cntry_as_is FROM cd_loan_tapes_bce.lt003_entity WHERE ref_date='2025-06-30' AND nome_perimetro= 'Individual IDComb' AND segmento= 'ESTR' AND ambito= 'PM' AND entidade='00100' AND cod_visao = 1) A | I12: =IF(VLOOKUP(B12,Instruções!$F$6:$J$10,5,0)="", "(SELECT "&VLOOKUP(B12,Instruções!$F$6:$J$10,4,0)&" as "&VLOOKUP(B12,Instruções!$F$6:$J$10,4,0)&"_to_be, "&E12&" as "&G12&" FROM "&D12&" WHERE "&Instruções!$D$11&") B ", "(SELECT "&VLOOKUP(B12,Instruções!$F$6:$J$10,4,0)&" as "&VLOOKUP(B12,Instruções!$F$6:$J$10,4,0)&"_to_be, "&VLOOKUP(B12,Instruções!$F$6:$J$10,5,0)&" as "&VLOOKUP(B12,Instruções!$F$6:$J$10,5,0)&"_to_be,"&E12&" as "&G12&" FROM "&D12&" WHERE "&Instruções!$D$11&") B ") -> (SELECT entty_id as entty_id_to_be, cntry as cntry_to_be FROM bu_loantape_work.lt003_entity WHERE ref_date='2025-06-30' AND nome_perimetro= 'Individual IDComb' AND segmento= 'ESTR' AND ambito= 'PM' AND entidade='00100' AND cod_visao = 1) B | J12: =IF(VLOOKUP(B12,Instruções!$F$6:$J$10,5,0)="", "ON "&VLOOKUP(B12,Instruções!$F$6:$J$10,4,0)&"_as_is = "&VLOOKUP(B12,Instruções!$F$6:$J$10,4,0)&"_to_be ", "ON "&VLOOKUP(B12,Instruções!$F$6:$J$10,4,0)&"_as_is = "&VLOOKUP(B12,Instruções!$F$6:$J$10,4,0)&"_to_be AND "&VLOOKUP(B12,Instruções!$F$6:$J$10,5,0)&"_as_is = "&VLOOKUP(B12,Instruções!$F$6:$J$10,5,0)&"_to_be ") -> ON entty_id_as_is = entty_id_to_be | K12: ="WHERE coalesce(cast("&F12&" as string), '') <> coalesce(cast("&G12&" as string), '') " -> WHERE coalesce(cast(cntry_as_is as string), '') <> coalesce(cast(cntry_to_be as string), '') | L12: ="SELECT count(*) AS NUM_REG_DIF FROM "&H12&" Inner join "&I12&J12&K12 -> SELECT count(*) AS NUM_REG_DIF FROM (SELECT entty_id as entty_id_as_is, cntry as cntry_as_is FROM cd_loan_tapes_bce.lt003_entity WHERE ref_date='2025-06-30' AND nome_perimetro= 'Individual IDComb' AND segmento= 'ESTR' AND ambito= 'PM' AND entidade='00100' AND cod_visao = 1) A Inner join (SELECT entty_id as entty_id_to_be, cntry as cntry_to_be FROM bu_loantape_work.lt003_entity WHERE ref_date='2025-06-30' AND nome_perimetro= 'Individual IDComb' AND segmento= 'ESTR' AND ambito= 'PM' AND entidade='00100' AND cod_visao = 1) B ON entty_id_as_is = entty_id_to_be WHERE coalesce(cast(cntry_as_is as string), '') <> coalesce(cast(cntry_to_be as string), '') | M12: Validação de campos | N12: ="SELECT 'Validação de campos' as tipologia_teste, '"&VLOOKUP(B12,Instruções!$F$6:$J$10,3,0)&"' AS TABELA, '"&E12&"' AS CAMPO, '"&Instruções!$D$7&"' as ref_date, coalesce(NUM_REG_DIF, 0) AS NUM_REG_DIF FROM ("&L12&") A " -> SELECT 'Validação de campos' as tipologia_teste, 'lt003_entity' AS TABELA, 'cntry' AS CAMPO, '2025-06-30' as ref_date, coalesce(NUM_REG_DIF, 0) AS NUM_REG_DIF FROM (SELECT count(*) AS NUM_REG_DIF FROM (SELECT entty_id as entty_id_as_is, cntry as cntry_as_is FROM cd_loan_tapes_bce.lt003_entity WHERE ref_date='2025-06-30' AND nome_perimetro= 'Individual IDComb' AND segmento= 'ESTR' AND ambito= 'PM' AND entidade='00100' AND cod_visao = 1) A Inner join (SELECT entty_id as entty_id_to_be, cntry as cntry_to_be FROM bu_loantape_work.lt003_entity WHERE ref_date='2025-06-30' AND nome_perimetro= 'Individual IDComb' AND segmento= 'ESTR' AND ambito= 'PM' AND entidade='00100' AND cod_visao = 1) B ON entty_id_as_is = entty_id_to_be WHERE coalesce(cast(cntry_as_is as string), '') <> coalesce(cast(cntry_to_be as string), '') ) A | O12: =IF(O13="",N12,N12&$O$3) -> SELECT 'Validação de campos' as tipologia_teste, 'lt003_entity' AS TABELA, 'cntry' AS CAMPO, '2025-06-30' as ref_date, coalesce(NUM_REG_DIF, 0) AS NUM_REG_DIF FROM (SELECT count(*) AS NUM_REG_DIF FROM (SELECT entty_id as entty_id_as_is, cntry as cntry_as_is FROM cd_loan_tapes_bce.lt003_entity WHERE ref_date='2025-06-30' AND nome_perimetro= 'Individual IDComb' AND segmento= 'ESTR' AND ambito= 'PM' AND entidade='00100' AND cod_visao = 1) A Inner join (SELECT entty_id as entty_id_to_be, cntry as cntry_to_be FROM bu_loantape_work.lt003_entity WHERE ref_date='2025-06-30' AND nome_perimetro= 'Individual IDComb' AND segmento= 'ESTR' AND ambito= 'PM' AND entidade='00100' AND cod_visao = 1) B ON entty_id_as_is = entty_id_to_be WHERE coalesce(cast(cntry_as_is as string), '') <> coalesce(cast(cntry_to_be as string), '') ) A UNION ALL | P12: =P11+1 -> 9
B13: ENTTY | C13: =_xlfn.CONCAT(Instruções!$D$5,".",VLOOKUP(B13,Instruções!$F$5:$H$10,2,0)) -> cd_loan_tapes_bce.lt003_entity | D13: =_xlfn.CONCAT(Instruções!$D$6,".",VLOOKUP(B13,Instruções!$F$5:$H$10,3,0)) -> bu_loantape_work.lt003_entity | E13: cod_soc | F13: =E13&"_as_is" -> cod_soc_as_is | G13: =E13&"_to_be" -> cod_soc_to_be | H13: =IF(VLOOKUP(B13,Instruções!$F$6:$J$10,5,0)="", "(SELECT "&VLOOKUP(B13,Instruções!$F$6:$J$10,4,0)&" as "&VLOOKUP(B13,Instruções!$F$6:$J$10,4,0)&"_as_is, "&E13&" as "&F13&" FROM "&C13&" WHERE "&Instruções!$D$11&") A ", "(SELECT "&VLOOKUP(B13,Instruções!$F$6:$J$10,4,0)&" as "&VLOOKUP(B13,Instruções!$F$6:$J$10,4,0)&"_as_is, "&VLOOKUP(B13,Instruções!$F$6:$J$10,5,0)&" as "&VLOOKUP(B13,Instruções!$F$6:$J$10,5,0)&"_as_is,"&E13&" as "&F13&" FROM "&C13&" WHERE "&Instruções!$D$11&") A ") -> (SELECT entty_id as entty_id_as_is, cod_soc as cod_soc_as_is FROM cd_loan_tapes_bce.lt003_entity WHERE ref_date='2025-06-30' AND nome_perimetro= 'Individual IDComb' AND segmento= 'ESTR' AND ambito= 'PM' AND entidade='00100' AND cod_visao = 1) A | I13: =IF(VLOOKUP(B13,Instruções!$F$6:$J$10,5,0)="", "(SELECT "&VLOOKUP(B13,Instruções!$F$6:$J$10,4,0)&" as "&VLOOKUP(B13,Instruções!$F$6:$J$10,4,0)&"_to_be, "&E13&" as "&G13&" FROM "&D13&" WHERE "&Instruções!$D$11&") B ", "(SELECT "&VLOOKUP(B13,Instruções!$F$6:$J$10,4,0)&" as "&VLOOKUP(B13,Instruções!$F$6:$J$10,4,0)&"_to_be, "&VLOOKUP(B13,Instruções!$F$6:$J$10,5,0)&" as "&VLOOKUP(B13,Instruções!$F$6:$J$10,5,0)&"_to_be,"&E13&" as "&G13&" FROM "&D13&" WHERE "&Instruções!$D$11&") B ") -> (SELECT entty_id as entty_id_to_be, cod_soc as cod_soc_to_be FROM bu_loantape_work.lt003_entity WHERE ref_date='2025-06-30' AND nome_perimetro= 'Individual IDComb' AND segmento= 'ESTR' AND ambito= 'PM' AND entidade='00100' AND cod_visao = 1) B | J13: =IF(VLOOKUP(B13,Instruções!$F$6:$J$10,5,0)="", "ON "&VLOOKUP(B13,Instruções!$F$6:$J$10,4,0)&"_as_is = "&VLOOKUP(B13,Instruções!$F$6:$J$10,4,0)&"_to_be ", "ON "&VLOOKUP(B13,Instruções!$F$6:$J$10,4,0)&"_as_is = "&VLOOKUP(B13,Instruções!$F$6:$J$10,4,0)&"_to_be AND "&VLOOKUP(B13,Instruções!$F$6:$J$10,5,0)&"_as_is = "&VLOOKUP(B13,Instruções!$F$6:$J$10,5,0)&"_to_be ") -> ON entty_id_as_is = entty_id_to_be | K13: ="WHERE coalesce(cast("&F13&" as string), '') <> coalesce(cast("&G13&" as string), '') " -> WHERE coalesce(cast(cod_soc_as_is as string), '') <> coalesce(cast(cod_soc_to_be as string), '') | L13: ="SELECT count(*) AS NUM_REG_DIF FROM "&H13&" Inner join "&I13&J13&K13 -> SELECT count(*) AS NUM_REG_DIF FROM (SELECT entty_id as entty_id_as_is, cod_soc as cod_soc_as_is FROM cd_loan_tapes_bce.lt003_entity WHERE ref_date='2025-06-30' AND nome_perimetro= 'Individual IDComb' AND segmento= 'ESTR' AND ambito= 'PM' AND entidade='00100' AND cod_visao = 1) A Inner join (SELECT entty_id as entty_id_to_be, cod_soc as cod_soc_to_be FROM bu_loantape_work.lt003_entity WHERE ref_date='2025-06-30' AND nome_perimetro= 'Individual IDComb' AND segmento= 'ESTR' AND ambito= 'PM' AND entidade='00100' AND cod_visao = 1) B ON entty_id_as_is = entty_id_to_be WHERE coalesce(cast(cod_soc_as_is as string), '') <> coalesce(cast(cod_soc_to_be as string), '') | M13: Validação de campos | N13: ="SELECT 'Validação de campos' as tipologia_teste, '"&VLOOKUP(B13,Instruções!$F$6:$J$10,3,0)&"' AS TABELA, '"&E13&"' AS CAMPO, '"&Instruções!$D$7&"' as ref_date, coalesce(NUM_REG_DIF, 0) AS NUM_REG_DIF FROM ("&L13&") A " -> SELECT 'Validação de campos' as tipologia_teste, 'lt003_entity' AS TABELA, 'cod_soc' AS CAMPO, '2025-06-30' as ref_date, coalesce(NUM_REG_DIF, 0) AS NUM_REG_DIF FROM (SELECT count(*) AS NUM_REG_DIF FROM (SELECT entty_id as entty_id_as_is, cod_soc as cod_soc_as_is FROM cd_loan_tapes_bce.lt003_entity WHERE ref_date='2025-06-30' AND nome_perimetro= 'Individual IDComb' AND segmento= 'ESTR' AND ambito= 'PM' AND entidade='00100' AND cod_visao = 1) A Inner join (SELECT entty_id as entty_id_to_be, cod_soc as cod_soc_to_be FROM bu_loantape_work.lt003_entity WHERE ref_date='2025-06-30' AND nome_perimetro= 'Individual IDComb' AND segmento= 'ESTR' AND ambito= 'PM' AND entidade='00100' AND cod_visao = 1) B ON entty_id_as_is = entty_id_to_be WHERE coalesce(cast(cod_soc_as_is as string), '') <> coalesce(cast(cod_soc_to_be as string), '') ) A | O13: =IF(O14="",N13,N13&$O$3) -> SELECT 'Validação de campos' as tipologia_teste, 'lt003_entity' AS TABELA, 'cod_soc' AS CAMPO, '2025-06-30' as ref_date, coalesce(NUM_REG_DIF, 0) AS NUM_REG_DIF FROM (SELECT count(*) AS NUM_REG_DIF FROM (SELECT entty_id as entty_id_as_is, cod_soc as cod_soc_as_is FROM cd_loan_tapes_bce.lt003_entity WHERE ref_date='2025-06-30' AND nome_perimetro= 'Individual IDComb' AND segmento= 'ESTR' AND ambito= 'PM' AND entidade='00100' AND cod_visao = 1) A Inner join (SELECT entty_id as entty_id_to_be, cod_soc as cod_soc_to_be FROM bu_loantape_work.lt003_entity WHERE ref_date='2025-06-30' AND nome_perimetro= 'Individual IDComb' AND segmento= 'ESTR' AND ambito= 'PM' AND entidade='00100' AND cod_visao = 1) B ON entty_id_as_is = entty_id_to_be WHERE coalesce(cast(cod_soc_as_is as string), '') <> coalesce(cast(cod_soc_to_be as string), '') ) A UNION ALL | P13: =P12+1 -> 10
B14: ENTTY | C14: =_xlfn.CONCAT(Instruções!$D$5,".",VLOOKUP(B14,Instruções!$F$5:$H$10,2,0)) -> cd_loan_tapes_bce.lt003_entity | D14: =_xlfn.CONCAT(Instruções!$D$6,".",VLOOKUP(B14,Instruções!$F$5:$H$10,3,0)) -> bu_loantape_work.lt003_entity | E14: cr_flg | F14: =E14&"_as_is" -> cr_flg_as_is | G14: =E14&"_to_be" -> cr_flg_to_be | H14: =IF(VLOOKUP(B14,Instruções!$F$6:$J$10,5,0)="", "(SELECT "&VLOOKUP(B14,Instruções!$F$6:$J$10,4,0)&" as "&VLOOKUP(B14,Instruções!$F$6:$J$10,4,0)&"_as_is, "&E14&" as "&F14&" FROM "&C14&" WHERE "&Instruções!$D$11&") A ", "(SELECT "&VLOOKUP(B14,Instruções!$F$6:$J$10,4,0)&" as "&VLOOKUP(B14,Instruções!$F$6:$J$10,4,0)&"_as_is, "&VLOOKUP(B14,Instruções!$F$6:$J$10,5,0)&" as "&VLOOKUP(B14,Instruções!$F$6:$J$10,5,0)&"_as_is,"&E14&" as "&F14&" FROM "&C14&" WHERE "&Instruções!$D$11&") A ") -> (SELECT entty_id as entty_id_as_is, cr_flg as cr_flg_as_is FROM cd_loan_tapes_bce.lt003_entity WHERE ref_date='2025-06-30' AND nome_perimetro= 'Individual IDComb' AND segmento= 'ESTR' AND ambito= 'PM' AND entidade='00100' AND cod_visao = 1) A | I14: =IF(VLOOKUP(B14,Instruções!$F$6:$J$10,5,0)="", "(SELECT "&VLOOKUP(B14,Instruções!$F$6:$J$10,4,0)&" as "&VLOOKUP(B14,Instruções!$F$6:$J$10,4,0)&"_to_be, "&E14&" as "&G14&" FROM "&D14&" WHERE "&Instruções!$D$11&") B ", "(SELECT "&VLOOKUP(B14,Instruções!$F$6:$J$10,4,0)&" as "&VLOOKUP(B14,Instruções!$F$6:$J$10,4,0)&"_to_be, "&VLOOKUP(B14,Instruções!$F$6:$J$10,5,0)&" as "&VLOOKUP(B14,Instruções!$F$6:$J$10,5,0)&"_to_be,"&E14&" as "&G14&" FROM "&D14&" WHERE "&Instruções!$D$11&") B ") -> (SELECT entty_id as entty_id_to_be, cr_flg as cr_flg_to_be FROM bu_loantape_work.lt003_entity WHERE ref_date='2025-06-30' AND nome_perimetro= 'Individual IDComb' AND segmento= 'ESTR' AND ambito= 'PM' AND entidade='00100' AND cod_visao = 1) B | J14: =IF(VLOOKUP(B14,Instruções!$F$6:$J$10,5,0)="", "ON "&VLOOKUP(B14,Instruções!$F$6:$J$10,4,0)&"_as_is = "&VLOOKUP(B14,Instruções!$F$6:$J$10,4,0)&"_to_be ", "ON "&VLOOKUP(B14,Instruções!$F$6:$J$10,4,0)&"_as_is = "&VLOOKUP(B14,Instruções!$F$6:$J$10,4,0)&"_to_be AND "&VLOOKUP(B14,Instruções!$F$6:$J$10,5,0)&"_as_is = "&VLOOKUP(B14,Instruções!$F$6:$J$10,5,0)&"_to_be ") -> ON entty_id_as_is = entty_id_to_be | K14: ="WHERE coalesce(cast("&F14&" as string), '') <> coalesce(cast("&G14&" as string), '') " -> WHERE coalesce(cast(cr_flg_as_is as string), '') <> coalesce(cast(cr_flg_to_be as string), '') | L14: ="SELECT count(*) AS NUM_REG_DIF FROM "&H14&" Inner join "&I14&J14&K14 -> SELECT count(*) AS NUM_REG_DIF FROM (SELECT entty_id as entty_id_as_is, cr_flg as cr_flg_as_is FROM cd_loan_tapes_bce.lt003_entity WHERE ref_date='2025-06-30' AND nome_perimetro= 'Individual IDComb' AND segmento= 'ESTR' AND ambito= 'PM' AND entidade='00100' AND cod_visao = 1) A Inner join (SELECT entty_id as entty_id_to_be, cr_flg as cr_flg_to_be FROM bu_loantape_work.lt003_entity WHERE ref_date='2025-06-30' AND nome_perimetro= 'Individual IDComb' AND segmento= 'ESTR' AND ambito= 'PM' AND entidade='00100' AND cod_visao = 1) B ON entty_id_as_is = entty_id_to_be WHERE coalesce(cast(cr_flg_as_is as string), '') <> coalesce(cast(cr_flg_to_be as string), '') | M14: Validação de campos | N14: ="SELECT 'Validação de campos' as tipologia_teste, '"&VLOOKUP(B14,Instruções!$F$6:$J$10,3,0)&"' AS TABELA, '"&E14&"' AS CAMPO, '"&Instruções!$D$7&"' as ref_date, coalesce(NUM_REG_DIF, 0) AS NUM_REG_DIF FROM ("&L14&") A " -> SELECT 'Validação de campos' as tipologia_teste, 'lt003_entity' AS TABELA, 'cr_flg' AS CAMPO, '2025-06-30' as ref_date, coalesce(NUM_REG_DIF, 0) AS NUM_REG_DIF FROM (SELECT count(*) AS NUM_REG_DIF FROM (SELECT entty_id as entty_id_as_is, cr_flg as cr_flg_as_is FROM cd_loan_tapes_bce.lt003_entity WHERE ref_date='2025-06-30' AND nome_perimetro= 'Individual IDComb' AND segmento= 'ESTR' AND ambito= 'PM' AND entidade='00100' AND cod_visao = 1) A Inner join (SELECT entty_id as entty_id_to_be, cr_flg as cr_flg_to_be FROM bu_loantape_work.lt003_entity WHERE ref_date='2025-06-30' AND nome_perimetro= 'Individual IDComb' AND segmento= 'ESTR' AND ambito= 'PM' AND entidade='00100' AND cod_visao = 1) B ON entty_id_as_is = entty_id_to_be WHERE coalesce(cast(cr_flg_as_is as string), '') <> coalesce(cast(cr_flg_to_be as string), '') ) A | O14: =IF(O15="",N14,N14&$O$3) -> SELECT 'Validação de campos' as tipologia_teste, 'lt003_entity' AS TABELA, 'cr_flg' AS CAMPO, '2025-06-30' as ref_date, coalesce(NUM_REG_DIF, 0) AS NUM_REG_DIF FROM (SELECT count(*) AS NUM_REG_DIF FROM (SELECT entty_id as entty_id_as_is, cr_flg as cr_flg_as_is FROM cd_loan_tapes_bce.lt003_entity WHERE ref_date='2025-06-30' AND nome_perimetro= 'Individual IDComb' AND segmento= 'ESTR' AND ambito= 'PM' AND entidade='00100' AND cod_visao = 1) A Inner join (SELECT entty_id as entty_id_to_be, cr_flg as cr_flg_to_be FROM bu_loantape_work.lt003_entity WHERE ref_date='2025-06-30' AND nome_perimetro= 'Individual IDComb' AND segmento= 'ESTR' AND ambito= 'PM' AND entidade='00100' AND cod_visao = 1) B ON entty_id_as_is = entty_id_to_be WHERE coalesce(cast(cr_flg_as_is as string), '') <> coalesce(cast(cr_flg_to_be as string), '') ) A UNION ALL | P14: =P13+1 -> 11
B15: ENTTY | C15: =_xlfn.CONCAT(Instruções!$D$5,".",VLOOKUP(B15,Instruções!$F$5:$H$10,2,0)) -> cd_loan_tapes_bce.lt003_entity | D15: =_xlfn.CONCAT(Instruções!$D$6,".",VLOOKUP(B15,Instruções!$F$5:$H$10,3,0)) -> bu_loantape_work.lt003_entity | E15: csh | F15: =E15&"_as_is" -> csh_as_is | G15: =E15&"_to_be" -> csh_to_be | H15: =IF(VLOOKUP(B15,Instruções!$F$6:$J$10,5,0)="", "(SELECT "&VLOOKUP(B15,Instruções!$F$6:$J$10,4,0)&" as "&VLOOKUP(B15,Instruções!$F$6:$J$10,4,0)&"_as_is, "&E15&" as "&F15&" FROM "&C15&" WHERE "&Instruções!$D$11&") A ", "(SELECT "&VLOOKUP(B15,Instruções!$F$6:$J$10,4,0)&" as "&VLOOKUP(B15,Instruções!$F$6:$J$10,4,0)&"_as_is, "&VLOOKUP(B15,Instruções!$F$6:$J$10,5,0)&" as "&VLOOKUP(B15,Instruções!$F$6:$J$10,5,0)&"_as_is,"&E15&" as "&F15&" FROM "&C15&" WHERE "&Instruções!$D$11&") A ") -> (SELECT entty_id as entty_id_as_is, csh as csh_as_is FROM cd_loan_tapes_bce.lt003_entity WHERE ref_date='2025-06-30' AND nome_perimetro= 'Individual IDComb' AND segmento= 'ESTR' AND ambito= 'PM' AND entidade='00100' AND cod_visao = 1) A | I15: =IF(VLOOKUP(B15,Instruções!$F$6:$J$10,5,0)="", "(SELECT "&VLOOKUP(B15,Instruções!$F$6:$J$10,4,0)&" as "&VLOOKUP(B15,Instruções!$F$6:$J$10,4,0)&"_to_be, "&E15&" as "&G15&" FROM "&D15&" WHERE "&Instruções!$D$11&") B ", "(SELECT "&VLOOKUP(B15,Instruções!$F$6:$J$10,4,0)&" as "&VLOOKUP(B15,Instruções!$F$6:$J$10,4,0)&"_to_be, "&VLOOKUP(B15,Instruções!$F$6:$J$10,5,0)&" as "&VLOOKUP(B15,Instruções!$F$6:$J$10,5,0)&"_to_be,"&E15&" as "&G15&" FROM "&D15&" WHERE "&Instruções!$D$11&") B ") -> (SELECT entty_id as entty_id_to_be, csh as csh_to_be FROM bu_loantape_work.lt003_entity WHERE ref_date='2025-06-30' AND nome_perimetro= 'Individual IDComb' AND segmento= 'ESTR' AND ambito= 'PM' AND entidade='00100' AND cod_visao = 1) B | J15: =IF(VLOOKUP(B15,Instruções!$F$6:$J$10,5,0)="", "ON "&VLOOKUP(B15,Instruções!$F$6:$J$10,4,0)&"_as_is = "&VLOOKUP(B15,Instruções!$F$6:$J$10,4,0)&"_to_be ", "ON "&VLOOKUP(B15,Instruções!$F$6:$J$10,4,0)&"_as_is = "&VLOOKUP(B15,Instruções!$F$6:$J$10,4,0)&"_to_be AND "&VLOOKUP(B15,Instruções!$F$6:$J$10,5,0)&"_as_is = "&VLOOKUP(B15,Instruções!$F$6:$J$10,5,0)&"_to_be ") -> ON entty_id_as_is = entty_id_to_be | K15: ="WHERE coalesce(cast("&F15&" as string), '') <> coalesce(cast("&G15&" as string), '') " -> WHERE coalesce(cast(csh_as_is as string), '') <> coalesce(cast(csh_to_be as string), '') | L15: ="SELECT count(*) AS NUM_REG_DIF FROM "&H15&" Inner join "&I15&J15&K15 -> SELECT count(*) AS NUM_REG_DIF FROM (SELECT entty_id as entty_id_as_is, csh as csh_as_is FROM cd_loan_tapes_bce.lt003_entity WHERE ref_date='2025-06-30' AND nome_perimetro= 'Individual IDComb' AND segmento= 'ESTR' AND ambito= 'PM' AND entidade='00100' AND cod_visao = 1) A Inner join (SELECT entty_id as entty_id_to_be, csh as csh_to_be FROM bu_loantape_work.lt003_entity WHERE ref_date='2025-06-30' AND nome_perimetro= 'Individual IDComb' AND segmento= 'ESTR' AND ambito= 'PM' AND entidade='00100' AND cod_visao = 1) B ON entty_id_as_is = entty_id_to_be WHERE coalesce(cast(csh_as_is as string), '') <> coalesce(cast(csh_to_be as string), '') | M15: Validação de campos | N15: ="SELECT 'Validação de campos' as tipologia_teste, '"&VLOOKUP(B15,Instruções!$F$6:$J$10,3,0)&"' AS TABELA, '"&E15&"' AS CAMPO, '"&Instruções!$D$7&"' as ref_date, coalesce(NUM_REG_DIF, 0) AS NUM_REG_DIF FROM ("&L15&") A " -> SELECT 'Validação de campos' as tipologia_teste, 'lt003_entity' AS TABELA, 'csh' AS CAMPO, '2025-06-30' as ref_date, coalesce(NUM_REG_DIF, 0) AS NUM_REG_DIF FROM (SELECT count(*) AS NUM_REG_DIF FROM (SELECT entty_id as entty_id_as_is, csh as csh_as_is FROM cd_loan_tapes_bce.lt003_entity WHERE ref_date='2025-06-30' AND nome_perimetro= 'Individual IDComb' AND segmento= 'ESTR' AND ambito= 'PM' AND entidade='00100' AND cod_visao = 1) A Inner join (SELECT entty_id as entty_id_to_be, csh as csh_to_be FROM bu_loantape_work.lt003_entity WHERE ref_date='2025-06-30' AND nome_perimetro= 'Individual IDComb' AND segmento= 'ESTR' AND ambito= 'PM' AND entidade='00100' AND cod_visao = 1) B ON entty_id_as_is = entty_id_to_be WHERE coalesce(cast(csh_as_is as string), '') <> coalesce(cast(csh_to_be as string), '') ) A | O15: =IF(O16="",N15,N15&$O$3) -> SELECT 'Validação de campos' as tipologia_teste, 'lt003_entity' AS TABELA, 'csh' AS CAMPO, '2025-06-30' as ref_date, coalesce(NUM_REG_DIF, 0) AS NUM_REG_DIF FROM (SELECT count(*) AS NUM_REG_DIF FROM (SELECT entty_id as entty_id_as_is, csh as csh_as_is FROM cd_loan_tapes_bce.lt003_entity WHERE ref_date='2025-06-30' AND nome_perimetro= 'Individual IDComb' AND segmento= 'ESTR' AND ambito= 'PM' AND entidade='00100' AND cod_visao = 1) A Inner join (SELECT entty_id as entty_id_to_be, csh as csh_to_be FROM bu_loantape_work.lt003_entity WHERE ref_date='2025-06-30' AND nome_perimetro= 'Individual IDComb' AND segmento= 'ESTR' AND ambito= 'PM' AND entidade='00100' AND cod_visao = 1) B ON entty_id_as_is = entty_id_to_be WHERE coalesce(cast(csh_as_is as string), '') <> coalesce(cast(csh_to_be as string), '') ) A UNION ALL | P15: =P14+1 -> 12
B16: ENTTY | C16: =_xlfn.CONCAT(Instruções!$D$5,".",VLOOKUP(B16,Instruções!$F$5:$H$10,2,0)) -> cd_loan_tapes_bce.lt003_entity | D16: =_xlfn.CONCAT(Instruções!$D$6,".",VLOOKUP(B16,Instruções!$F$5:$H$10,3,0)) -> bu_loantape_work.lt003_entity | E16: csh_prvs | F16: =E16&"_as_is" -> csh_prvs_as_is | G16: =E16&"_to_be" -> csh_prvs_to_be | H16: =IF(VLOOKUP(B16,Instruções!$F$6:$J$10,5,0)="", "(SELECT "&VLOOKUP(B16,Instruções!$F$6:$J$10,4,0)&" as "&VLOOKUP(B16,Instruções!$F$6:$J$10,4,0)&"_as_is, "&E16&" as "&F16&" FROM "&C16&" WHERE "&Instruções!$D$11&") A ", "(SELECT "&VLOOKUP(B16,Instruções!$F$6:$J$10,4,0)&" as "&VLOOKUP(B16,Instruções!$F$6:$J$10,4,0)&"_as_is, "&VLOOKUP(B16,Instruções!$F$6:$J$10,5,0)&" as "&VLOOKUP(B16,Instruções!$F$6:$J$10,5,0)&"_as_is,"&E16&" as "&F16&" FROM "&C16&" WHERE "&Instruções!$D$11&") A ") -> (SELECT entty_id as entty_id_as_is, csh_prvs as csh_prvs_as_is FROM cd_loan_tapes_bce.lt003_entity WHERE ref_date='2025-06-30' AND nome_perimetro= 'Individual IDComb' AND segmento= 'ESTR' AND ambito= 'PM' AND entidade='00100' AND cod_visao = 1) A | I16: =IF(VLOOKUP(B16,Instruções!$F$6:$J$10,5,0)="", "(SELECT "&VLOOKUP(B16,Instruções!$F$6:$J$10,4,0)&" as "&VLOOKUP(B16,Instruções!$F$6:$J$10,4,0)&"_to_be, "&E16&" as "&G16&" FROM "&D16&" WHERE "&Instruções!$D$11&") B ", "(SELECT "&VLOOKUP(B16,Instruções!$F$6:$J$10,4,0)&" as "&VLOOKUP(B16,Instruções!$F$6:$J$10,4,0)&"_to_be, "&VLOOKUP(B16,Instruções!$F$6:$J$10,5,0)&" as "&VLOOKUP(B16,Instruções!$F$6:$J$10,5,0)&"_to_be,"&E16&" as "&G16&" FROM "&D16&" WHERE "&Instruções!$D$11&") B ") -> (SELECT entty_id as entty_id_to_be, csh_prvs as csh_prvs_to_be FROM bu_loantape_work.lt003_entity WHERE ref_date='2025-06-30' AND nome_perimetro= 'Individual IDComb' AND segmento= 'ESTR' AND ambito= 'PM' AND entidade='00100' AND cod_visao = 1) B | J16: =IF(VLOOKUP(B16,Instruções!$F$6:$J$10,5,0)="", "ON "&VLOOKUP(B16,Instruções!$F$6:$J$10,4,0)&"_as_is = "&VLOOKUP(B16,Instruções!$F$6:$J$10,4,0)&"_to_be ", "ON "&VLOOKUP(B16,Instruções!$F$6:$J$10,4,0)&"_as_is = "&VLOOKUP(B16,Instruções!$F$6:$J$10,4,0)&"_to_be AND "&VLOOKUP(B16,Instruções!$F$6:$J$10,5,0)&"_as_is = "&VLOOKUP(B16,Instruções!$F$6:$J$10,5,0)&"_to_be ") -> ON entty_id_as_is = entty_id_to_be | K16: ="WHERE coalesce(cast("&F16&" as string), '') <> coalesce(cast("&G16&" as string), '') " -> WHERE coalesce(cast(csh_prvs_as_is as string), '') <> coalesce(cast(csh_prvs_to_be as string), '') | L16: ="SELECT count(*) AS NUM_REG_DIF FROM "&H16&" Inner join "&I16&J16&K16 -> SELECT count(*) AS NUM_REG_DIF FROM (SELECT entty_id as entty_id_as_is, csh_prvs as csh_prvs_as_is FROM cd_loan_tapes_bce.lt003_entity WHERE ref_date='2025-06-30' AND nome_perimetro= 'Individual IDComb' AND segmento= 'ESTR' AND ambito= 'PM' AND entidade='00100' AND cod_visao = 1) A Inner join (SELECT entty_id as entty_id_to_be, csh_prvs as csh_prvs_to_be FROM bu_loantape_work.lt003_entity WHERE ref_date='2025-06-30' AND nome_perimetro= 'Individual IDComb' AND segmento= 'ESTR' AND ambito= 'PM' AND entidade='00100' AND cod_visao = 1) B ON entty_id_as_is = entty_id_to_be WHERE coalesce(cast(csh_prvs_as_is as string), '') <> coalesce(cast(csh_prvs_to_be as string), '') | M16: Validação de campos | N16: ="SELECT 'Validação de campos' as tipologia_teste, '"&VLOOKUP(B16,Instruções!$F$6:$J$10,3,0)&"' AS TABELA, '"&E16&"' AS CAMPO, '"&Instruções!$D$7&"' as ref_date, coalesce(NUM_REG_DIF, 0) AS NUM_REG_DIF FROM ("&L16&") A " -> SELECT 'Validação de campos' as tipologia_teste, 'lt003_entity' AS TABELA, 'csh_prvs' AS CAMPO, '2025-06-30' as ref_date, coalesce(NUM_REG_DIF, 0) AS NUM_REG_DIF FROM (SELECT count(*) AS NUM_REG_DIF FROM (SELECT entty_id as entty_id_as_is, csh_prvs as csh_prvs_as_is FROM cd_loan_tapes_bce.lt003_entity WHERE ref_date='2025-06-30' AND nome_perimetro= 'Individual IDComb' AND segmento= 'ESTR' AND ambito= 'PM' AND entidade='00100' AND cod_visao = 1) A Inner join (SELECT entty_id as entty_id_to_be, csh_prvs as csh_prvs_to_be FROM bu_loantape_work.lt003_entity WHERE ref_date='2025-06-30' AND nome_perimetro= 'Individual IDComb' AND segmento= 'ESTR' AND ambito= 'PM' AND entidade='00100' AND cod_visao = 1) B ON entty_id_as_is = entty_id_to_be WHERE coalesce(cast(csh_prvs_as_is as string), '') <> coalesce(cast(csh_prvs_to_be as string), '') ) A | O16: =IF(O17="",N16,N16&$O$3) -> SELECT 'Validação de campos' as tipologia_teste, 'lt003_entity' AS TABELA, 'csh_prvs' AS CAMPO, '2025-06-30' as ref_date, coalesce(NUM_REG_DIF, 0) AS NUM_REG_DIF FROM (SELECT count(*) AS NUM_REG_DIF FROM (SELECT entty_id as entty_id_as_is, csh_prvs as csh_prvs_as_is FROM cd_loan_tapes_bce.lt003_entity WHERE ref_date='2025-06-30' AND nome_perimetro= 'Individual IDComb' AND segmento= 'ESTR' AND ambito= 'PM' AND entidade='00100' AND cod_visao = 1) A Inner join (SELECT entty_id as entty_id_to_be, csh_prvs as csh_prvs_to_be FROM bu_loantape_work.lt003_entity WHERE ref_date='2025-06-30' AND nome_perimetro= 'Individual IDComb' AND segmento= 'ESTR' AND ambito= 'PM' AND entidade='00100' AND cod_visao = 1) B ON entty_id_as_is = entty_id_to_be WHERE coalesce(cast(csh_prvs_as_is as string), '') <> coalesce(cast(csh_prvs_to_be as string), '') ) A UNION ALL | P16: =P15+1 -> 13
... B111: INSTR_PRTCTN | C111: =_xlfn.CONCAT(Instruções!$D$5,".",VLOOKUP(B111,Instruções!$F$5:$H$10,2,0)) -> cd_loan_tapes_bce.lt006_instr_prot | D111: =_xlfn.CONCAT(Instruções!$D$6,".",VLOOKUP(B111,Instruções!$F$5:$H$10,3,0)) -> bu_loantape_work.lt006_instr_prot | E111: prtctn_allctd_vl | F111: =E111&"_as_is" -> prtctn_allctd_vl_as_is | G111: =E111&"_to_be" -> prtctn_allctd_vl_to_be | H111: =IF(VLOOKUP(B111,Instruções!$F$6:$J$10,5,0)="", "(SELECT "&VLOOKUP(B111,Instruções!$F$6:$J$10,4,0)&" as "&VLOOKUP(B111,Instruções!$F$6:$J$10,4,0)&"_as_is, "&E111&" as "&F111&" FROM "&C111&" WHERE "&Instruções!$D$11&") A ", "(SELECT "&VLOOKUP(B111,Instruções!$F$6:$J$10,4,0)&" as "&VLOOKUP(B111,Instruções!$F$6:$J$10,4,0)&"_as_is, "&VLOOKUP(B111,Instruções!$F$6:$J$10,5,0)&" as "&VLOOKUP(B111,Instruções!$F$6:$J$10,5,0)&"_as_is,"&E111&" as "&F111&" FROM "&C111&" WHERE "&Instruções!$D$11&") A ") -> (SELECT instrmnt_id as instrmnt_id_as_is, prtctn_id as prtctn_id_as_is,prtctn_allctd_vl as prtctn_allctd_vl_as_is FROM cd_loan_tapes_bce.lt006_instr_prot WHERE ref_date='2025-06-30' AND nome_perimetro= 'Individual IDComb' AND segmento= 'ESTR' AND ambito= 'PM' AND entidade='00100' AND cod_visao = 1) A | I111: =IF(VLOOKUP(B111,Instruções!$F$6:$J$10,5,0)="", "(SELECT "&VLOOKUP(B111,Instruções!$F$6:$J$10,4,0)&" as "&VLOOKUP(B111,Instruções!$F$6:$J$10,4,0)&"_to_be, "&E111&" as "&G111&" FROM "&D111&" WHERE "&Instruções!$D$11&") B ", "(SELECT "&VLOOKUP(B111,Instruções!$F$6:$J$10,4,0)&" as "&VLOOKUP(B111,Instruções!$F$6:$J$10,4,0)&"_to_be, "&VLOOKUP(B111,Instruções!$F$6:$J$10,5,0)&" as "&VLOOKUP(B111,Instruções!$F$6:$J$10,5,0)&"_to_be,"&E111&" as "&G111&" FROM "&D111&" WHERE "&Instruções!$D$11&") B ") -> (SELECT instrmnt_id as instrmnt_id_to_be, prtctn_id as prtctn_id_to_be,prtctn_allctd_vl as prtctn_allctd_vl_to_be FROM bu_loantape_work.lt006_instr_prot WHERE ref_date='2025-06-30' AND nome_perimetro= 'Individual IDComb' AND segmento= 'ESTR' AND ambito= 'PM' AND entidade='00100' AND cod_visao = 1) B | J111: =IF(VLOOKUP(B111,Instruções!$F$6:$J$10,5,0)="", "ON "&VLOOKUP(B111,Instruções!$F$6:$J$10,4,0)&"_as_is = "&VLOOKUP(B111,Instruções!$F$6:$J$10,4,0)&"_to_be ", "ON "&VLOOKUP(B111,Instruções!$F$6:$J$10,4,0)&"_as_is = "&VLOOKUP(B111,Instruções!$F$6:$J$10,4,0)&"_to_be AND "&VLOOKUP(B111,Instruções!$F$6:$J$10,5,0)&"_as_is = "&VLOOKUP(B111,Instruções!$F$6:$J$10,5,0)&"_to_be ") -> ON instrmnt_id_as_is = instrmnt_id_to_be AND prtctn_id_as_is = prtctn_id_to_be | K111: ="WHERE coalesce(cast("&F111&" as string), '') <> coalesce(cast("&G111&" as string), '') " -> WHERE coalesce(cast(prtctn_allctd_vl_as_is as string), '') <> coalesce(cast(prtctn_allctd_vl_to_be as string), '') | L111: ="SELECT count(*) AS NUM_REG_DIF FROM "&H111&" Inner join "&I111&J111&K111 -> SELECT count(*) AS NUM_REG_DIF FROM (SELECT instrmnt_id as instrmnt_id_as_is, prtctn_id as prtctn_id_as_is,prtctn_allctd_vl as prtctn_allctd_vl_as_is FROM cd_loan_tapes_bce.lt006_instr_prot WHERE ref_date='2025-06-30' AND nome_perimetro= 'Individual IDComb' AND segmento= 'ESTR' AND ambito= 'PM' AND entidade='00100' AND cod_visao = 1) A Inner join (SELECT instrmnt_id as instrmnt_id_to_be, prtctn_id as prtctn_id_to_be,prtctn_allctd_vl as prtctn_allctd_vl_to_be FROM bu_loantape_work.lt006_instr_prot WHERE ref_date='2025-06-30' AND nome_perimetro= 'Individual IDComb' AND segmento= 'ESTR' AND ambito= 'PM' AND entidade='00100' AND cod_visao = 1) B ON instrmnt_id_as_is = instrmnt_id_to_be AND prtctn_id_as_is = prtctn_id_to_be WHERE coalesce(cast(prtctn_allctd_vl_as_is as string), '') <> coalesce(cast(prtctn_allctd_vl_to_be as string), '') | M111: Validação de campos | N111: ="SELECT 'Validação de campos' as tipologia_teste, '"&VLOOKUP(B111,Instruções!$F$6:$J$10,3,0)&"' AS TABELA, '"&E111&"' AS CAMPO, '"&Instruções!$D$7&"' as ref_date, coalesce(NUM_REG_DIF, 0) AS NUM_REG_DIF FROM ("&L111&") A " -> SELECT 'Validação de campos' as tipologia_teste, 'lt006_instr_prot' AS TABELA, 'prtctn_allctd_vl' AS CAMPO, '2025-06-30' as ref_date, coalesce(NUM_REG_DIF, 0) AS NUM_REG_DIF FROM (SELECT count(*) AS NUM_REG_DIF FROM (SELECT instrmnt_id as instrmnt_id_as_is, prtctn_id as prtctn_id_as_is,prtctn_allctd_vl as prtctn_allctd_vl_as_is FROM cd_loan_tapes_bce.lt006_instr_prot WHERE ref_date='2025-06-30' AND nome_perimetro= 'Individual IDComb' AND segmento= 'ESTR' AND ambito= 'PM' AND entidade='00100' AND cod_visao = 1) A Inner join (SELECT instrmnt_id as instrmnt_id_to_be, prtctn_id as prtctn_id_to_be,prtctn_allctd_vl as prtctn_allctd_vl_to_be FROM bu_loantape_work.lt006_instr_prot WHERE ref_date='2025-06-30' AND nome_perimetro= 'Individual IDComb' AND segmento= 'ESTR' AND ambito= 'PM' AND entidade='00100' AND cod_visao = 1) B ON instrmnt_id_as_is = instrmnt_id_to_be AND prtctn_id_as_is = prtctn_id_to_be WHERE coalesce(cast(prtctn_allctd_vl_as_is as string), '') <> coalesce(cast(prtctn_allctd_vl_to_be as string), '') ) A | O111: =IF(O112="",N111,N111&$O$3) -> SELECT 'Validação de campos' as tipologia_teste, 'lt006_instr_prot' AS TABELA, 'prtctn_allctd_vl' AS CAMPO, '2025-06-30' as ref_date, coalesce(NUM_REG_DIF, 0) AS NUM_REG_DIF FROM (SELECT count(*) AS NUM_REG_DIF FROM (SELECT instrmnt_id as instrmnt_id_as_is, prtctn_id as prtctn_id_as_is,prtctn_allctd_vl as prtctn_allctd_vl_as_is FROM cd_loan_tapes_bce.lt006_instr_prot WHERE ref_date='2025-06-30' AND nome_perimetro= 'Individual IDComb' AND segmento= 'ESTR' AND ambito= 'PM' AND entidade='00100' AND cod_visao = 1) A Inner join (SELECT instrmnt_id as instrmnt_id_to_be, prtctn_id as prtctn_id_to_be,prtctn_allctd_vl as prtctn_allctd_vl_to_be FROM bu_loantape_work.lt006_instr_prot WHERE ref_date='2025-06-30' AND nome_perimetro= 'Individual IDComb' AND segmento= 'ESTR' AND ambito= 'PM' AND entidade='00100' AND cod_visao = 1) B ON instrmnt_id_as_is = instrmnt_id_to_be AND prtctn_id_as_is = prtctn_id_to_be WHERE coalesce(cast(prtctn_allctd_vl_as_is as string), '') <> coalesce(cast(prtctn_allctd_vl_to_be as string), '') ) A | P111: =P110+1 -> 57
B113: INSTR_PRTCTN | C113: =_xlfn.CONCAT(Instruções!$D$5,".",VLOOKUP(B113,Instruções!$F$5:$H$10,2,0)) -> cd_loan_tapes_bce.lt006_instr_prot | D113: =_xlfn.CONCAT(Instruções!$D$6,".",VLOOKUP(B113,Instruções!$F$5:$H$10,3,0)) -> bu_loantape_work.lt006_instr_prot | E113: thrd_prty_prrty_clms | F113: =E113&"_as_is" -> thrd_prty_prrty_clms_as_is | G113: =E113&"_to_be" -> thrd_prty_prrty_clms_to_be | H113: =IF(VLOOKUP(B113,Instruções!$F$6:$J$10,5,0)="", "(SELECT "&VLOOKUP(B113,Instruções!$F$6:$J$10,4,0)&" as "&VLOOKUP(B113,Instruções!$F$6:$J$10,4,0)&"_as_is, "&E113&" as "&F113&" FROM "&C113&" WHERE "&Instruções!$D$11&") A ", "(SELECT "&VLOOKUP(B113,Instruções!$F$6:$J$10,4,0)&" as "&VLOOKUP(B113,Instruções!$F$6:$J$10,4,0)&"_as_is, "&VLOOKUP(B113,Instruções!$F$6:$J$10,5,0)&" as "&VLOOKUP(B113,Instruções!$F$6:$J$10,5,0)&"_as_is,"&E113&" as "&F113&" FROM "&C113&" WHERE "&Instruções!$D$11&") A ") -> (SELECT instrmnt_id as instrmnt_id_as_is, prtctn_id as prtctn_id_as_is,thrd_prty_prrty_clms as thrd_prty_prrty_clms_as_is FROM cd_loan_tapes_bce.lt006_instr_prot WHERE ref_date='2025-06-30' AND nome_perimetro= 'Individual IDComb' AND segmento= 'ESTR' AND ambito= 'PM' AND entidade='00100' AND cod_visao = 1) A | I113: =IF(VLOOKUP(B113,Instruções!$F$6:$J$10,5,0)="", "(SELECT "&VLOOKUP(B113,Instruções!$F$6:$J$10,4,0)&" as "&VLOOKUP(B113,Instruções!$F$6:$J$10,4,0)&"_to_be, "&E113&" as "&G113&" FROM "&D113&" WHERE "&Instruções!$D$11&") B ", "(SELECT "&VLOOKUP(B113,Instruções!$F$6:$J$10,4,0)&" as "&VLOOKUP(B113,Instruções!$F$6:$J$10,4,0)&"_to_be, "&VLOOKUP(B113,Instruções!$F$6:$J$10,5,0)&" as "&VLOOKUP(B113,Instruções!$F$6:$J$10,5,0)&"_to_be,"&E113&" as "&G113&" FROM "&D113&" WHERE "&Instruções!$D$11&") B ") -> (SELECT instrmnt_id as instrmnt_id_to_be, prtctn_id as prtctn_id_to_be,thrd_prty_prrty_clms as thrd_prty_prrty_clms_to_be FROM bu_loantape_work.lt006_instr_prot WHERE ref_date='2025-06-30' AND nome_perimetro= 'Individual IDComb' AND segmento= 'ESTR' AND ambito= 'PM' AND entidade='00100' AND cod_visao = 1) B | J113: =IF(VLOOKUP(B113,Instruções!$F$6:$J$10,5,0)="", "ON "&VLOOKUP(B113,Instruções!$F$6:$J$10,4,0)&"_as_is = "&VLOOKUP(B113,Instruções!$F$6:$J$10,4,0)&"_to_be ", "ON "&VLOOKUP(B113,Instruções!$F$6:$J$10,4,0)&"_as_is = "&VLOOKUP(B113,Instruções!$F$6:$J$10,4,0)&"_to_be AND "&VLOOKUP(B113,Instruções!$F$6:$J$10,5,0)&"_as_is = "&VLOOKUP(B113,Instruções!$F$6:$J$10,5,0)&"_to_be ") -> ON instrmnt_id_as_is = instrmnt_id_to_be AND prtctn_id_as_is = prtctn_id_to_be | K113: ="WHERE coalesce(cast("&F113&" as string), '') <> coalesce(cast("&G113&" as string), '') " -> WHERE coalesce(cast(thrd_prty_prrty_clms_as_is as string), '') <> coalesce(cast(thrd_prty_prrty_clms_to_be as string), '') | L113: ="SELECT count(*) AS NUM_REG_DIF FROM "&H113&" Inner join "&I113&J113&K113 -> SELECT count(*) AS NUM_REG_DIF FROM (SELECT instrmnt_id as instrmnt_id_as_is, prtctn_id as prtctn_id_as_is,thrd_prty_prrty_clms as thrd_prty_prrty_clms_as_is FROM cd_loan_tapes_bce.lt006_instr_prot WHERE ref_date='2025-06-30' AND nome_perimetro= 'Individual IDComb' AND segmento= 'ESTR' AND ambito= 'PM' AND entidade='00100' AND cod_visao = 1) A Inner join (SELECT instrmnt_id as instrmnt_id_to_be, prtctn_id as prtctn_id_to_be,thrd_prty_prrty_clms as thrd_prty_prrty_clms_to_be FROM bu_loantape_work.lt006_instr_prot WHERE ref_date='2025-06-30' AND nome_perimetro= 'Individual IDComb' AND segmento= 'ESTR' AND ambito= 'PM' AND entidade='00100' AND cod_visao = 1) B ON instrmnt_id_as_is = instrmnt_id_to_be AND prtctn_id_as_is = prtctn_id_to_be WHERE coalesce(cast(thrd_prty_prrty_clms_as_is as string), '') <> coalesce(cast(thrd_prty_prrty_clms_to_be as string), '') | M113: Validação de campos | N113: ="SELECT 'Validação de campos' as tipologia_teste, '"&VLOOKUP(B113,Instruções!$F$6:$J$10,3,0)&"' AS TABELA, '"&E113&"' AS CAMPO, '"&Instruções!$D$7&"' as ref_date, coalesce(NUM_REG_DIF, 0) AS NUM_REG_DIF FROM ("&L113&") A " -> SELECT 'Validação de campos' as tipologia_teste, 'lt006_instr_prot' AS TABELA, 'thrd_prty_prrty_clms' AS CAMPO, '2025-06-30' as ref_date, coalesce(NUM_REG_DIF, 0) AS NUM_REG_DIF FROM (SELECT count(*) AS NUM_REG_DIF FROM (SELECT instrmnt_id as instrmnt_id_as_is, prtctn_id as prtctn_id_as_is,thrd_prty_prrty_clms as thrd_prty_prrty_clms_as_is FROM cd_loan_tapes_bce.lt006_instr_prot WHERE ref_date='2025-06-30' AND nome_perimetro= 'Individual IDComb' AND segmento= 'ESTR' AND ambito= 'PM' AND entidade='00100' AND cod_visao = 1) A Inner join (SELECT instrmnt_id as instrmnt_id_to_be, prtctn_id as prtctn_id_to_be,thrd_prty_prrty_clms as thrd_prty_prrty_clms_to_be FROM bu_loantape_work.lt006_instr_prot WHERE ref_date='2025-06-30' AND nome_perimetro= 'Individual IDComb' AND segmento= 'ESTR' AND ambito= 'PM' AND entidade='00100' AND cod_visao = 1) B ON instrmnt_id_as_is = instrmnt_id_to_be AND prtctn_id_as_is = prtctn_id_to_be WHERE coalesce(cast(thrd_prty_prrty_clms_as_is as string), '') <> coalesce(cast(thrd_prty_prrty_clms_to_be as string), '') ) A | O113: =IF(O115="",N113,N113&$O$3) -> SELECT 'Validação de campos' as tipologia_teste, 'lt006_instr_prot' AS TABELA, 'thrd_prty_prrty_clms' AS CAMPO, '2025-06-30' as ref_date, coalesce(NUM_REG_DIF, 0) AS NUM_REG_DIF FROM (SELECT count(*) AS NUM_REG_DIF FROM (SELECT instrmnt_id as instrmnt_id_as_is, prtctn_id as prtctn_id_as_is,thrd_prty_prrty_clms as thrd_prty_prrty_clms_as_is FROM cd_loan_tapes_bce.lt006_instr_prot WHERE ref_date='2025-06-30' AND nome_perimetro= 'Individual IDComb' AND segmento= 'ESTR' AND ambito= 'PM' AND entidade='00100' AND cod_visao = 1) A Inner join (SELECT instrmnt_id as instrmnt_id_to_be, prtctn_id as prtctn_id_to_be,thrd_prty_prrty_clms as thrd_prty_prrty_clms_to_be FROM bu_loantape_work.lt006_instr_prot WHERE ref_date='2025-06-30' AND nome_perimetro= 'Individual IDComb' AND segmento= 'ESTR' AND ambito= 'PM' AND entidade='00100' AND cod_visao = 1) B ON instrmnt_id_as_is = instrmnt_id_to_be AND prtctn_id_as_is = prtctn_id_to_be WHERE coalesce(cast(thrd_prty_prrty_clms_as_is as string), '') <> coalesce(cast(thrd_prty_prrty_clms_to_be as string), '') ) A UNION ALL | P113: =P112+1 -> 1
B114: INSTR_PRTCTN | C114: =_xlfn.CONCAT(Instruções!$D$5,".",VLOOKUP(B114,Instruções!$F$5:$H$10,2,0)) -> cd_loan_tapes_bce.lt006_instr_prot | D114: =_xlfn.CONCAT(Instruções!$D$6,".",VLOOKUP(B114,Instruções!$F$5:$H$10,3,0)) -> bu_loantape_work.lt006_instr_prot | E114: grp_spprt | F114: =E114&"_as_is" -> grp_spprt_as_is | G114: =E114&"_to_be" -> grp_spprt_to_be | H114: =IF(VLOOKUP(B114,Instruções!$F$6:$J$10,5,0)="", "(SELECT "&VLOOKUP(B114,Instruções!$F$6:$J$10,4,0)&" as "&VLOOKUP(B114,Instruções!$F$6:$J$10,4,0)&"_as_is, "&E114&" as "&F114&" FROM "&C114&" WHERE "&Instruções!$D$11&") A ", "(SELECT "&VLOOKUP(B114,Instruções!$F$6:$J$10,4,0)&" as "&VLOOKUP(B114,Instruções!$F$6:$J$10,4,0)&"_as_is, "&VLOOKUP(B114,Instruções!$F$6:$J$10,5,0)&" as "&VLOOKUP(B114,Instruções!$F$6:$J$10,5,0)&"_as_is,"&E114&" as "&F114&" FROM "&C114&" WHERE "&Instruções!$D$11&") A ") -> (SELECT instrmnt_id as instrmnt_id_as_is, prtctn_id as prtctn_id_as_is,grp_spprt as grp_spprt_as_is FROM cd_loan_tapes_bce.lt006_instr_prot WHERE ref_date='2025-06-30' AND nome_perimetro= 'Individual IDComb' AND segmento= 'ESTR' AND ambito= 'PM' AND entidade='00100' AND cod_visao = 1) A | I114: =IF(VLOOKUP(B114,Instruções!$F$6:$J$10,5,0)="", "(SELECT "&VLOOKUP(B114,Instruções!$F$6:$J$10,4,0)&" as "&VLOOKUP(B114,Instruções!$F$6:$J$10,4,0)&"_to_be, "&E114&" as "&G114&" FROM "&D114&" WHERE "&Instruções!$D$11&") B ", "(SELECT "&VLOOKUP(B114,Instruções!$F$6:$J$10,4,0)&" as "&VLOOKUP(B114,Instruções!$F$6:$J$10,4,0)&"_to_be, "&VLOOKUP(B114,Instruções!$F$6:$J$10,5,0)&" as "&VLOOKUP(B114,Instruções!$F$6:$J$10,5,0)&"_to_be,"&E114&" as "&G114&" FROM "&D114&" WHERE "&Instruções!$D$11&") B ") -> (SELECT instrmnt_id as instrmnt_id_to_be, prtctn_id as prtctn_id_to_be,grp_spprt as grp_spprt_to_be FROM bu_loantape_work.lt006_instr_prot WHERE ref_date='2025-06-30' AND nome_perimetro= 'Individual IDComb' AND segmento= 'ESTR' AND ambito= 'PM' AND entidade='00100' AND cod_visao = 1) B | J114: =IF(VLOOKUP(B114,Instruções!$F$6:$J$10,5,0)="", "ON "&VLOOKUP(B114,Instruções!$F$6:$J$10,4,0)&"_as_is = "&VLOOKUP(B114,Instruções!$F$6:$J$10,4,0)&"_to_be ", "ON "&VLOOKUP(B114,Instruções!$F$6:$J$10,4,0)&"_as_is = "&VLOOKUP(B114,Instruções!$F$6:$J$10,4,0)&"_to_be AND "&VLOOKUP(B114,Instruções!$F$6:$J$10,5,0)&"_as_is = "&VLOOKUP(B114,Instruções!$F$6:$J$10,5,0)&"_to_be ") -> ON instrmnt_id_as_is = instrmnt_id_to_be AND prtctn_id_as_is = prtctn_id_to_be | K114: ="WHERE coalesce(cast("&F114&" as string), '') <> coalesce(cast("&G114&" as string), '') " -> WHERE coalesce(cast(grp_spprt_as_is as string), '') <> coalesce(cast(grp_spprt_to_be as string), '') | L114: ="SELECT count(*) AS NUM_REG_DIF FROM "&H114&" Inner join "&I114&J114&K114 -> SELECT count(*) AS NUM_REG_DIF FROM (SELECT instrmnt_id as instrmnt_id_as_is, prtctn_id as prtctn_id_as_is,grp_spprt as grp_spprt_as_is FROM cd_loan_tapes_bce.lt006_instr_prot WHERE ref_date='2025-06-30' AND nome_perimetro= 'Individual IDComb' AND segmento= 'ESTR' AND ambito= 'PM' AND entidade='00100' AND cod_visao = 1) A Inner join (SELECT instrmnt_id as instrmnt_id_to_be, prtctn_id as prtctn_id_to_be,grp_spprt as grp_spprt_to_be FROM bu_loantape_work.lt006_instr_prot WHERE ref_date='2025-06-30' AND nome_perimetro= 'Individual IDComb' AND segmento= 'ESTR' AND ambito= 'PM' AND entidade='00100' AND cod_visao = 1) B ON instrmnt_id_as_is = instrmnt_id_to_be AND prtctn_id_as_is = prtctn_id_to_be WHERE coalesce(cast(grp_spprt_as_is as string), '') <> coalesce(cast(grp_spprt_to_be as string), '') | M114: Validação de campos | N114: ="SELECT 'Validação de campos' as tipologia_teste, '"&VLOOKUP(B114,Instruções!$F$6:$J$10,3,0)&"' AS TABELA, '"&E114&"' AS CAMPO, '"&Instruções!$D$7&"' as ref_date, coalesce(NUM_REG_DIF, 0) AS NUM_REG_DIF FROM ("&L114&") A " -> SELECT 'Validação de campos' as tipologia_teste, 'lt006_instr_prot' AS TABELA, 'grp_spprt' AS CAMPO, '2025-06-30' as ref_date, coalesce(NUM_REG_DIF, 0) AS NUM_REG_DIF FROM (SELECT count(*) AS NUM_REG_DIF FROM (SELECT instrmnt_id as instrmnt_id_as_is, prtctn_id as prtctn_id_as_is,grp_spprt as grp_spprt_as_is FROM cd_loan_tapes_bce.lt006_instr_prot WHERE ref_date='2025-06-30' AND nome_perimetro= 'Individual IDComb' AND segmento= 'ESTR' AND ambito= 'PM' AND entidade='00100' AND cod_visao = 1) A Inner join (SELECT instrmnt_id as instrmnt_id_to_be, prtctn_id as prtctn_id_to_be,grp_spprt as grp_spprt_to_be FROM bu_loantape_work.lt006_instr_prot WHERE ref_date='2025-06-30' AND nome_perimetro= 'Individual IDComb' AND segmento= 'ESTR' AND ambito= 'PM' AND entidade='00100' AND cod_visao = 1) B ON instrmnt_id_as_is = instrmnt_id_to_be AND prtctn_id_as_is = prtctn_id_to_be WHERE coalesce(cast(grp_spprt_as_is as string), '') <> coalesce(cast(grp_spprt_to_be as string), '') ) A | O114: =IF(O116="",N114,N114&$O$3) -> SELECT 'Validação de campos' as tipologia_teste, 'lt006_instr_prot' AS TABELA, 'grp_spprt' AS CAMPO, '2025-06-30' as ref_date, coalesce(NUM_REG_DIF, 0) AS NUM_REG_DIF FROM (SELECT count(*) AS NUM_REG_DIF FROM (SELECT instrmnt_id as instrmnt_id_as_is, prtctn_id as prtctn_id_as_is,grp_spprt as grp_spprt_as_is FROM cd_loan_tapes_bce.lt006_instr_prot WHERE ref_date='2025-06-30' AND nome_perimetro= 'Individual IDComb' AND segmento= 'ESTR' AND ambito= 'PM' AND entidade='00100' AND cod_visao = 1) A Inner join (SELECT instrmnt_id as instrmnt_id_to_be, prtctn_id as prtctn_id_to_be,grp_spprt as grp_spprt_to_be FROM bu_loantape_work.lt006_instr_prot WHERE ref_date='2025-06-30' AND nome_perimetro= 'Individual IDComb' AND segmento= 'ESTR' AND ambito= 'PM' AND entidade='00100' AND cod_visao = 1) B ON instrmnt_id_as_is = instrmnt_id_to_be AND prtctn_id_as_is = prtctn_id_to_be WHERE coalesce(cast(grp_spprt_as_is as string), '') <> coalesce(cast(grp_spprt_to_be as string), '') ) A UNION ALL | P114: =P113+1 -> 2
B115: INSTRMNT | C115: =_xlfn.CONCAT(Instruções!$D$5,".",VLOOKUP(B115,Instruções!$F$5:$H$10,2,0)) -> cd_loan_tapes_bce.lt002_instrument | D115: =_xlfn.CONCAT(Instruções!$D$6,".",VLOOKUP(B115,Instruções!$F$5:$H$10,3,0)) -> bu_loantape_work.lt002_instrument | E115: accmltd_chngs_fv_cr_instrmnt | F115: =E115&"_as_is" -> accmltd_chngs_fv_cr_instrmnt_as_is | G115: =E115&"_to_be" -> accmltd_chngs_fv_cr_instrmnt_to_be | H115: =IF(VLOOKUP(B115,Instruções!$F$6:$J$10,5,0)="", "(SELECT "&VLOOKUP(B115,Instruções!$F$6:$J$10,4,0)&" as "&VLOOKUP(B115,Instruções!$F$6:$J$10,4,0)&"_as_is, "&E115&" as "&F115&" FROM "&C115&" WHERE "&Instruções!$D$11&") A ", "(SELECT "&VLOOKUP(B115,Instruções!$F$6:$J$10,4,0)&" as "&VLOOKUP(B115,Instruções!$F$6:$J$10,4,0)&"_as_is, "&VLOOKUP(B115,Instruções!$F$6:$J$10,5,0)&" as "&VLOOKUP(B115,Instruções!$F$6:$J$10,5,0)&"_as_is,"&E115&" as "&F115&" FROM "&C115&" WHERE "&Instruções!$D$11&") A ") -> (SELECT instrmnt_id as instrmnt_id_as_is, accmltd_chngs_fv_cr_instrmnt as accmltd_chngs_fv_cr_instrmnt_as_is FROM cd_loan_tapes_bce.lt002_instrument WHERE ref_date='2025-06-30' AND nome_perimetro= 'Individual IDComb' AND segmento= 'ESTR' AND ambito= 'PM' AND entidade='00100' AND cod_visao = 1) A | I115: =IF(VLOOKUP(B115,Instruções!$F$6:$J$10,5,0)="", "(SELECT "&VLOOKUP(B115,Instruções!$F$6:$J$10,4,0)&" as "&VLOOKUP(B115,Instruções!$F$6:$J$10,4,0)&"_to_be, "&E115&" as "&G115&" FROM "&D115&" WHERE "&Instruções!$D$11&") B ", "(SELECT "&VLOOKUP(B115,Instruções!$F$6:$J$10,4,0)&" as "&VLOOKUP(B115,Instruções!$F$6:$J$10,4,0)&"_to_be, "&VLOOKUP(B115,Instruções!$F$6:$J$10,5,0)&" as "&VLOOKUP(B115,Instruções!$F$6:$J$10,5,0)&"_to_be,"&E115&" as "&G115&" FROM "&D115&" WHERE "&Instruções!$D$11&") B ") -> (SELECT instrmnt_id as instrmnt_id_to_be, accmltd_chngs_fv_cr_instrmnt as accmltd_chngs_fv_cr_instrmnt_to_be FROM bu_loantape_work.lt002_instrument WHERE ref_date='2025-06-30' AND nome_perimetro= 'Individual IDComb' AND segmento= 'ESTR' AND ambito= 'PM' AND entidade='00100' AND cod_visao = 1) B | J115: =IF(VLOOKUP(B115,Instruções!$F$6:$J$10,5,0)="", "ON "&VLOOKUP(B115,Instruções!$F$6:$J$10,4,0)&"_as_is = "&VLOOKUP(B115,Instruções!$F$6:$J$10,4,0)&"_to_be ", "ON "&VLOOKUP(B115,Instruções!$F$6:$J$10,4,0)&"_as_is = "&VLOOKUP(B115,Instruções!$F$6:$J$10,4,0)&"_to_be AND "&VLOOKUP(B115,Instruções!$F$6:$J$10,5,0)&"_as_is = "&VLOOKUP(B115,Instruções!$F$6:$J$10,5,0)&"_to_be ") -> ON instrmnt_id_as_is = instrmnt_id_to_be | K115: ="WHERE coalesce(cast("&F115&" as string), '') <> coalesce(cast("&G115&" as string), '') " -> WHERE coalesce(cast(accmltd_chngs_fv_cr_instrmnt_as_is as string), '') <> coalesce(cast(accmltd_chngs_fv_cr_instrmnt_to_be as string), '') | L115: ="SELECT count(*) AS NUM_REG_DIF FROM "&H115&" Inner join "&I115&J115&K115 -> SELECT count(*) AS NUM_REG_DIF FROM (SELECT instrmnt_id as instrmnt_id_as_is, accmltd_chngs_fv_cr_instrmnt as accmltd_chngs_fv_cr_instrmnt_as_is FROM cd_loan_tapes_bce.lt002_instrument WHERE ref_date='2025-06-30' AND nome_perimetro= 'Individual IDComb' AND segmento= 'ESTR' AND ambito= 'PM' AND entidade='00100' AND cod_visao = 1) A Inner join (SELECT instrmnt_id as instrmnt_id_to_be, accmltd_chngs_fv_cr_instrmnt as accmltd_chngs_fv_cr_instrmnt_to_be FROM bu_loantape_work.lt002_instrument WHERE ref_date='2025-06-30' AND nome_perimetro= 'Individual IDComb' AND segmento= 'ESTR' AND ambito= 'PM' AND entidade='00100' AND cod_visao = 1) B ON instrmnt_id_as_is = instrmnt_id_to_be WHERE coalesce(cast(accmltd_chngs_fv_cr_instrmnt_as_is as string), '') <> coalesce(cast(accmltd_chngs_fv_cr_instrmnt_to_be as string), '') | M115: Validação de campos | N115: ="SELECT 'Validação de campos' as tipologia_teste, '"&VLOOKUP(B115,Instruções!$F$6:$J$10,3,0)&"' AS TABELA, '"&E115&"' AS CAMPO, '"&Instruções!$D$7&"' as ref_date, coalesce(NUM_REG_DIF, 0) AS NUM_REG_DIF FROM ("&L115&") A " -> SELECT 'Validação de campos' as tipologia_teste, 'lt002_instrument' AS TABELA, 'accmltd_chngs_fv_cr_instrmnt' AS CAMPO, '2025-06-30' as ref_date, coalesce(NUM_REG_DIF, 0) AS NUM_REG_DIF FROM (SELECT count(*) AS NUM_REG_DIF FROM (SELECT instrmnt_id as instrmnt_id_as_is, accmltd_chngs_fv_cr_instrmnt as accmltd_chngs_fv_cr_instrmnt_as_is FROM cd_loan_tapes_bce.lt002_instrument WHERE ref_date='2025-06-30' AND nome_perimetro= 'Individual IDComb' AND segmento= 'ESTR' AND ambito= 'PM' AND entidade='00100' AND cod_visao = 1) A Inner join (SELECT instrmnt_id as instrmnt_id_to_be, accmltd_chngs_fv_cr_instrmnt as accmltd_chngs_fv_cr_instrmnt_to_be FROM bu_loantape_work.lt002_instrument WHERE ref_date='2025-06-30' AND nome_perimetro= 'Individual IDComb' AND segmento= 'ESTR' AND ambito= 'PM' AND entidade='00100' AND cod_visao = 1) B ON instrmnt_id_as_is = instrmnt_id_to_be WHERE coalesce(cast(accmltd_chngs_fv_cr_instrmnt_as_is as string), '') <> coalesce(cast(accmltd_chngs_fv_cr_instrmnt_to_be as string), '') ) A | O115: =IF(O116="",N115,N115&$O$3) -> SELECT 'Validação de campos' as tipologia_teste, 'lt002_instrument' AS TABELA, 'accmltd_chngs_fv_cr_instrmnt' AS CAMPO, '2025-06-30' as ref_date, coalesce(NUM_REG_DIF, 0) AS NUM_REG_DIF FROM (SELECT count(*) AS NUM_REG_DIF FROM (SELECT instrmnt_id as instrmnt_id_as_is, accmltd_chngs_fv_cr_instrmnt as accmltd_chngs_fv_cr_instrmnt_as_is FROM cd_loan_tapes_bce.lt002_instrument WHERE ref_date='2025-06-30' AND nome_perimetro= 'Individual IDComb' AND segmento= 'ESTR' AND ambito= 'PM' AND entidade='00100' AND cod_visao = 1) A Inner join (SELECT instrmnt_id as instrmnt_id_to_be, accmltd_chngs_fv_cr_instrmnt as accmltd_chngs_fv_cr_instrmnt_to_be FROM bu_loantape_work.lt002_instrument WHERE ref_date='2025-06-30' AND nome_perimetro= 'Individual IDComb' AND segmento= 'ESTR' AND ambito= 'PM' AND entidade='00100' AND cod_visao = 1) B ON instrmnt_id_as_is = instrmnt_id_to_be WHERE coalesce(cast(accmltd_chngs_fv_cr_instrmnt_as_is as string), '') <> coalesce(cast(accmltd_chngs_fv_cr_instrmnt_to_be as string), '') ) A UNION ALL | P115: =P114+1 -> 3
B116: INSTRMNT | C116: =_xlfn.CONCAT(Instruções!$D$5,".",VLOOKUP(B116,Instruções!$F$5:$H$10,2,0)) -> cd_loan_tapes_bce.lt002_instrument | D116: =_xlfn.CONCAT(Instruções!$D$6,".",VLOOKUP(B116,Instruções!$F$5:$H$10,3,0)) -> bu_loantape_work.lt002_instrument | E116: accmltd_imprmnt_instrmnt | F116: =E116&"_as_is" -> accmltd_imprmnt_instrmnt_as_is | G116: =E116&"_to_be" -> accmltd_imprmnt_instrmnt_to_be | H116: =IF(VLOOKUP(B116,Instruções!$F$6:$J$10,5,0)="", "(SELECT "&VLOOKUP(B116,Instruções!$F$6:$J$10,4,0)&" as "&VLOOKUP(B116,Instruções!$F$6:$J$10,4,0)&"_as_is, "&E116&" as "&F116&" FROM "&C116&" WHERE "&Instruções!$D$11&") A ", "(SELECT "&VLOOKUP(B116,Instruções!$F$6:$J$10,4,0)&" as "&VLOOKUP(B116,Instruções!$F$6:$J$10,4,0)&"_as_is, "&VLOOKUP(B116,Instruções!$F$6:$J$10,5,0)&" as "&VLOOKUP(B116,Instruções!$F$6:$J$10,5,0)&"_as_is,"&E116&" as "&F116&" FROM "&C116&" WHERE "&Instruções!$D$11&") A ") -> (SELECT instrmnt_id as instrmnt_id_as_is, accmltd_imprmnt_instrmnt as accmltd_imprmnt_instrmnt_as_is FROM cd_loan_tapes_bce.lt002_instrument WHERE ref_date='2025-06-30' AND nome_perimetro= 'Individual IDComb' AND segmento= 'ESTR' AND ambito= 'PM' AND entidade='00100' AND cod_visao = 1) A | I116: =IF(VLOOKUP(B116,Instruções!$F$6:$J$10,5,0)="", "(SELECT "&VLOOKUP(B116,Instruções!$F$6:$J$10,4,0)&" as "&VLOOKUP(B116,Instruções!$F$6:$J$10,4,0)&"_to_be, "&E116&" as "&G116&" FROM "&D116&" WHERE "&Instruções!$D$11&") B ", "(SELECT "&VLOOKUP(B116,Instruções!$F$6:$J$10,4,0)&" as "&VLOOKUP(B116,Instruções!$F$6:$J$10,4,0)&"_to_be, "&VLOOKUP(B116,Instruções!$F$6:$J$10,5,0)&" as "&VLOOKUP(B116,Instruções!$F$6:$J$10,5,0)&"_to_be,"&E116&" as "&G116&" FROM "&D116&" WHERE "&Instruções!$D$11&") B ") -> (SELECT instrmnt_id as instrmnt_id_to_be, accmltd_imprmnt_instrmnt as accmltd_imprmnt_instrmnt_to_be FROM bu_loantape_work.lt002_instrument WHERE ref_date='2025-06-30' AND nome_perimetro= 'Individual IDComb' AND segmento= 'ESTR' AND ambito= 'PM' AND entidade='00100' AND cod_visao = 1) B | J116: =IF(VLOOKUP(B116,Instruções!$F$6:$J$10,5,0)="", "ON "&VLOOKUP(B116,Instruções!$F$6:$J$10,4,0)&"_as_is = "&VLOOKUP(B116,Instruções!$F$6:$J$10,4,0)&"_to_be ", "ON "&VLOOKUP(B116,Instruções!$F$6:$J$10,4,0)&"_as_is = "&VLOOKUP(B116,Instruções!$F$6:$J$10,4,0)&"_to_be AND "&VLOOKUP(B116,Instruções!$F$6:$J$10,5,0)&"_as_is = "&VLOOKUP(B116,Instruções!$F$6:$J$10,5,0)&"_to_be ") -> ON instrmnt_id_as_is = instrmnt_id_to_be | K116: ="WHERE coalesce(cast("&F116&" as string), '') <> coalesce(cast("&G116&" as string), '') " -> WHERE coalesce(cast(accmltd_imprmnt_instrmnt_as_is as string), '') <> coalesce(cast(accmltd_imprmnt_instrmnt_to_be as string), '') | L116: ="SELECT count(*) AS NUM_REG_DIF FROM "&H116&" Inner join "&I116&J116&K116 -> SELECT count(*) AS NUM_REG_DIF FROM (SELECT instrmnt_id as instrmnt_id_as_is, accmltd_imprmnt_instrmnt as accmltd_imprmnt_instrmnt_as_is FROM cd_loan_tapes_bce.lt002_instrument WHERE ref_date='2025-06-30' AND nome_perimetro= 'Individual IDComb' AND segmento= 'ESTR' AND ambito= 'PM' AND entidade='00100' AND cod_visao = 1) A Inner join (SELECT instrmnt_id as instrmnt_id_to_be, accmltd_imprmnt_instrmnt as accmltd_imprmnt_instrmnt_to_be FROM bu_loantape_work.lt002_instrument WHERE ref_date='2025-06-30' AND nome_perimetro= 'Individual IDComb' AND segmento= 'ESTR' AND ambito= 'PM' AND entidade='00100' AND cod_visao = 1) B ON instrmnt_id_as_is = instrmnt_id_to_be WHERE coalesce(cast(accmltd_imprmnt_instrmnt_as_is as string), '') <> coalesce(cast(accmltd_imprmnt_instrmnt_to_be as string), '') | M116: Validação de campos | N116: ="SELECT 'Validação de campos' as tipologia_teste, '"&VLOOKUP(B116,Instruções!$F$6:$J$10,3,0)&"' AS TABELA, '"&E116&"' AS CAMPO, '"&Instruções!$D$7&"' as ref_date, coalesce(NUM_REG_DIF, 0) AS NUM_REG_DIF FROM ("&L116&") A " -> SELECT 'Validação de campos' as tipologia_teste, 'lt002_instrument' AS TABELA, 'accmltd_imprmnt_instrmnt' AS CAMPO, '2025-06-30' as ref_date, coalesce(NUM_REG_DIF, 0) AS NUM_REG_DIF FROM (SELECT count(*) AS NUM_REG_DIF FROM (SELECT instrmnt_id as instrmnt_id_as_is, accmltd_imprmnt_instrmnt as accmltd_imprmnt_instrmnt_as_is FROM cd_loan_tapes_bce.lt002_instrument WHERE ref_date='2025-06-30' AND nome_perimetro= 'Individual IDComb' AND segmento= 'ESTR' AND ambito= 'PM' AND entidade='00100' AND cod_visao = 1) A Inner join (SELECT instrmnt_id as instrmnt_id_to_be, accmltd_imprmnt_instrmnt as accmltd_imprmnt_instrmnt_to_be FROM bu_loantape_work.lt002_instrument WHERE ref_date='2025-06-30' AND nome_perimetro= 'Individual IDComb' AND segmento= 'ESTR' AND ambito= 'PM' AND entidade='00100' AND cod_visao = 1) B ON instrmnt_id_as_is = instrmnt_id_to_be WHERE coalesce(cast(accmltd_imprmnt_instrmnt_as_is as string), '') <> coalesce(cast(accmltd_imprmnt_instrmnt_to_be as string), '') ) A | O116: =IF(O117="",N116,N116&$O$3) -> SELECT 'Validação de campos' as tipologia_teste, 'lt002_instrument' AS TABELA, 'accmltd_imprmnt_instrmnt' AS CAMPO, '2025-06-30' as ref_date, coalesce(NUM_REG_DIF, 0) AS NUM_REG_DIF FROM (SELECT count(*) AS NUM_REG_DIF FROM (SELECT instrmnt_id as instrmnt_id_as_is, accmltd_imprmnt_instrmnt as accmltd_imprmnt_instrmnt_as_is FROM cd_loan_tapes_bce.lt002_instrument WHERE ref_date='2025-06-30' AND nome_perimetro= 'Individual IDComb' AND segmento= 'ESTR' AND ambito= 'PM' AND entidade='00100' AND cod_visao = 1) A Inner join (SELECT instrmnt_id as instrmnt_id_to_be, accmltd_imprmnt_instrmnt as accmltd_imprmnt_instrmnt_to_be FROM bu_loantape_work.lt002_instrument WHERE ref_date='2025-06-30' AND nome_perimetro= 'Individual IDComb' AND segmento= 'ESTR' AND ambito= 'PM' AND entidade='00100' AND cod_visao = 1) B ON instrmnt_id_as_is = instrmnt_id_to_be WHERE coalesce(cast(accmltd_imprmnt_instrmnt_as_is as string), '') <> coalesce(cast(accmltd_imprmnt_instrmnt_to_be as string), '') ) A UNION ALL | P116: =P115+1 -> 4
B117: INSTRMNT | C117: =_xlfn.CONCAT(Instruções!$D$5,".",VLOOKUP(B117,Instruções!$F$5:$H$10,2,0)) -> cd_loan_tapes_bce.lt002_instrument | D117: =_xlfn.CONCAT(Instruções!$D$6,".",VLOOKUP(B117,Instruções!$F$5:$H$10,3,0)) -> bu_loantape_work.lt002_instrument | E117: accmltd_imprmnt_instrmnt_prvs | F117: =E117&"_as_is" -> accmltd_imprmnt_instrmnt_prvs_as_is | G117: =E117&"_to_be" -> accmltd_imprmnt_instrmnt_prvs_to_be | H117: =IF(VLOOKUP(B117,Instruções!$F$6:$J$10,5,0)="", "(SELECT "&VLOOKUP(B117,Instruções!$F$6:$J$10,4,0)&" as "&VLOOKUP(B117,Instruções!$F$6:$J$10,4,0)&"_as_is, "&E117&" as "&F117&" FROM "&C117&" WHERE "&Instruções!$D$11&") A ", "(SELECT "&VLOOKUP(B117,Instruções!$F$6:$J$10,4,0)&" as "&VLOOKUP(B117,Instruções!$F$6:$J$10,4,0)&"_as_is, "&VLOOKUP(B117,Instruções!$F$6:$J$10,5,0)&" as "&VLOOKUP(B117,Instruções!$F$6:$J$10,5,0)&"_as_is,"&E117&" as "&F117&" FROM "&C117&" WHERE "&Instruções!$D$11&") A ") -> (SELECT instrmnt_id as instrmnt_id_as_is, accmltd_imprmnt_instrmnt_prvs as accmltd_imprmnt_instrmnt_prvs_as_is FROM cd_loan_tapes_bce.lt002_instrument WHERE ref_date='2025-06-30' AND nome_perimetro= 'Individual IDComb' AND segmento= 'ESTR' AND ambito= 'PM' AND entidade='00100' AND cod_visao = 1) A | I117: =IF(VLOOKUP(B117,Instruções!$F$6:$J$10,5,0)="", "(SELECT "&VLOOKUP(B117,Instruções!$F$6:$J$10,4,0)&" as "&VLOOKUP(B117,Instruções!$F$6:$J$10,4,0)&"_to_be, "&E117&" as "&G117&" FROM "&D117&" WHERE "&Instruções!$D$11&") B ", "(SELECT "&VLOOKUP(B117,Instruções!$F$6:$J$10,4,0)&" as "&VLOOKUP(B117,Instruções!$F$6:$J$10,4,0)&"_to_be, "&VLOOKUP(B117,Instruções!$F$6:$J$10,5,0)&" as "&VLOOKUP(B117,Instruções!$F$6:$J$10,5,0)&"_to_be,"&E117&" as "&G117&" FROM "&D117&" WHERE "&Instruções!$D$11&") B ") -> (SELECT instrmnt_id as instrmnt_id_to_be, accmltd_imprmnt_instrmnt_prvs as accmltd_imprmnt_instrmnt_prvs_to_be FROM bu_loantape_work.lt002_instrument WHERE ref_date='2025-06-30' AND nome_perimetro= 'Individual IDComb' AND segmento= 'ESTR' AND ambito= 'PM' AND entidade='00100' AND cod_visao = 1) B | J117: =IF(VLOOKUP(B117,Instruções!$F$6:$J$10,5,0)="", "ON "&VLOOKUP(B117,Instruções!$F$6:$J$10,4,0)&"_as_is = "&VLOOKUP(B117,Instruções!$F$6:$J$10,4,0)&"_to_be ", "ON "&VLOOKUP(B117,Instruções!$F$6:$J$10,4,0)&"_as_is = "&VLOOKUP(B117,Instruções!$F$6:$J$10,4,0)&"_to_be AND "&VLOOKUP(B117,Instruções!$F$6:$J$10,5,0)&"_as_is = "&VLOOKUP(B117,Instruções!$F$6:$J$10,5,0)&"_to_be ") -> ON instrmnt_id_as_is = instrmnt_id_to_be | K117: ="WHERE coalesce(cast("&F117&" as string), '') <> coalesce(cast("&G117&" as string), '') " -> WHERE coalesce(cast(accmltd_imprmnt_instrmnt_prvs_as_is as string), '') <> coalesce(cast(accmltd_imprmnt_instrmnt_prvs_to_be as string), '') | L117: ="SELECT count(*) AS NUM_REG_DIF FROM "&H117&" Inner join "&I117&J117&K117 -> SELECT count(*) AS NUM_REG_DIF FROM (SELECT instrmnt_id as instrmnt_id_as_is, accmltd_imprmnt_instrmnt_prvs as accmltd_imprmnt_instrmnt_prvs_as_is FROM cd_loan_tapes_bce.lt002_instrument WHERE ref_date='2025-06-30' AND nome_perimetro= 'Individual IDComb' AND segmento= 'ESTR' AND ambito= 'PM' AND entidade='00100' AND cod_visao = 1) A Inner join (SELECT instrmnt_id as instrmnt_id_to_be, accmltd_imprmnt_instrmnt_prvs as accmltd_imprmnt_instrmnt_prvs_to_be FROM bu_loantape_work.lt002_instrument WHERE ref_date='2025-06-30' AND nome_perimetro= 'Individual IDComb' AND segmento= 'ESTR' AND ambito= 'PM' AND entidade='00100' AND cod_visao = 1) B ON instrmnt_id_as_is = instrmnt_id_to_be WHERE coalesce(cast(accmltd_imprmnt_instrmnt_prvs_as_is as string), '') <> coalesce(cast(accmltd_imprmnt_instrmnt_prvs_to_be as string), '') | M117: Validação de campos | N117: ="SELECT 'Validação de campos' as tipologia_teste, '"&VLOOKUP(B117,Instruções!$F$6:$J$10,3,0)&"' AS TABELA, '"&E117&"' AS CAMPO, '"&Instruções!$D$7&"' as ref_date, coalesce(NUM_REG_DIF, 0) AS NUM_REG_DIF FROM ("&L117&") A " -> SELECT 'Validação de campos' as tipologia_teste, 'lt002_instrument' AS TABELA, 'accmltd_imprmnt_instrmnt_prvs' AS CAMPO, '2025-06-30' as ref_date, coalesce(NUM_REG_DIF, 0) AS NUM_REG_DIF FROM (SELECT count(*) AS NUM_REG_DIF FROM (SELECT instrmnt_id as instrmnt_id_as_is, accmltd_imprmnt_instrmnt_prvs as accmltd_imprmnt_instrmnt_prvs_as_is FROM cd_loan_tapes_bce.lt002_instrument WHERE ref_date='2025-06-30' AND nome_perimetro= 'Individual IDComb' AND segmento= 'ESTR' AND ambito= 'PM' AND entidade='00100' AND cod_visao = 1) A Inner join (SELECT instrmnt_id as instrmnt_id_to_be, accmltd_imprmnt_instrmnt_prvs as accmltd_imprmnt_instrmnt_prvs_to_be FROM bu_loantape_work.lt002_instrument WHERE ref_date='2025-06-30' AND nome_perimetro= 'Individual IDComb' AND segmento= 'ESTR' AND ambito= 'PM' AND entidade='00100' AND cod_visao = 1) B ON instrmnt_id_as_is = instrmnt_id_to_be WHERE coalesce(cast(accmltd_imprmnt_instrmnt_prvs_as_is as string), '') <> coalesce(cast(accmltd_imprmnt_instrmnt_prvs_to_be as string), '') ) A | O117: =IF(O118="",N117,N117&$O$3) -> SELECT 'Validação de campos' as tipologia_teste, 'lt002_instrument' AS TABELA, 'accmltd_imprmnt_instrmnt_prvs' AS CAMPO, '2025-06-30' as ref_date, coalesce(NUM_REG_DIF, 0) AS NUM_REG_DIF FROM (SELECT count(*) AS NUM_REG_DIF FROM (SELECT instrmnt_id as instrmnt_id_as_is, accmltd_imprmnt_instrmnt_prvs as accmltd_imprmnt_instrmnt_prvs_as_is FROM cd_loan_tapes_bce.lt002_instrument WHERE ref_date='2025-06-30' AND nome_perimetro= 'Individual IDComb' AND segmento= 'ESTR' AND ambito= 'PM' AND entidade='00100' AND cod_visao = 1) A Inner join (SELECT instrmnt_id as instrmnt_id_to_be, accmltd_imprmnt_instrmnt_prvs as accmltd_imprmnt_instrmnt_prvs_to_be FROM bu_loantape_work.lt002_instrument WHERE ref_date='2025-06-30' AND nome_perimetro= 'Individual IDComb' AND segmento= 'ESTR' AND ambito= 'PM' AND entidade='00100' AND cod_visao = 1) B ON instrmnt_id_as_is = instrmnt_id_to_be WHERE coalesce(cast(accmltd_imprmnt_instrmnt_prvs_as_is as string), '') <> coalesce(cast(accmltd_imprmnt_instrmnt_prvs_to_be as string), '') ) A UNION ALL | P117: =P116+1 -> 5
B118: INSTRMNT | C118: =_xlfn.CONCAT(Instruções!$D$5,".",VLOOKUP(B118,Instruções!$F$5:$H$10,2,0)) -> cd_loan_tapes_bce.lt002_instrument | D118: =_xlfn.CONCAT(Instruções!$D$6,".",VLOOKUP(B118,Instruções!$F$5:$H$10,3,0)) -> bu_loantape_work.lt002_instrument | E118: accmltd_wrtffs_instrmnt | F118: =E118&"_as_is" -> accmltd_wrtffs_instrmnt_as_is | G118: =E118&"_to_be" -> accmltd_wrtffs_instrmnt_to_be | H118: =IF(VLOOKUP(B118,Instruções!$F$6:$J$10,5,0)="", "(SELECT "&VLOOKUP(B118,Instruções!$F$6:$J$10,4,0)&" as "&VLOOKUP(B118,Instruções!$F$6:$J$10,4,0)&"_as_is, "&E118&" as "&F118&" FROM "&C118&" WHERE "&Instruções!$D$11&") A ", "(SELECT "&VLOOKUP(B118,Instruções!$F$6:$J$10,4,0)&" as "&VLOOKUP(B118,Instruções!$F$6:$J$10,4,0)&"_as_is, "&VLOOKUP(B118,Instruções!$F$6:$J$10,5,0)&" as "&VLOOKUP(B118,Instruções!$F$6:$J$10,5,0)&"_as_is,"&E118&" as "&F118&" FROM "&C118&" WHERE "&Instruções!$D$11&") A ") -> (SELECT instrmnt_id as instrmnt_id_as_is, accmltd_wrtffs_instrmnt as accmltd_wrtffs_instrmnt_as_is FROM cd_loan_tapes_bce.lt002_instrument WHERE ref_date='2025-06-30' AND nome_perimetro= 'Individual IDComb' AND segmento= 'ESTR' AND ambito= 'PM' AND entidade='00100' AND cod_visao = 1) A | I118: =IF(VLOOKUP(B118,Instruções!$F$6:$J$10,5,0)="", "(SELECT "&VLOOKUP(B118,Instruções!$F$6:$J$10,4,0)&" as "&VLOOKUP(B118,Instruções!$F$6:$J$10,4,0)&"_to_be, "&E118&" as "&G118&" FROM "&D118&" WHERE "&Instruções!$D$11&") B ", "(SELECT "&VLOOKUP(B118,Instruções!$F$6:$J$10,4,0)&" as "&VLOOKUP(B118,Instruções!$F$6:$J$10,4,0)&"_to_be, "&VLOOKUP(B118,Instruções!$F$6:$J$10,5,0)&" as "&VLOOKUP(B118,Instruções!$F$6:$J$10,5,0)&"_to_be,"&E118&" as "&G118&" FROM "&D118&" WHERE "&Instruções!$D$11&") B ") -> (SELECT instrmnt_id as instrmnt_id_to_be, accmltd_wrtffs_instrmnt as accmltd_wrtffs_instrmnt_to_be FROM bu_loantape_work.lt002_instrument WHERE ref_date='2025-06-30' AND nome_perimetro= 'Individual IDComb' AND segmento= 'ESTR' AND ambito= 'PM' AND entidade='00100' AND cod_visao = 1) B | J118: =IF(VLOOKUP(B118,Instruções!$F$6:$J$10,5,0)="", "ON "&VLOOKUP(B118,Instruções!$F$6:$J$10,4,0)&"_as_is = "&VLOOKUP(B118,Instruções!$F$6:$J$10,4,0)&"_to_be ", "ON "&VLOOKUP(B118,Instruções!$F$6:$J$10,4,0)&"_as_is = "&VLOOKUP(B118,Instruções!$F$6:$J$10,4,0)&"_to_be AND "&VLOOKUP(B118,Instruções!$F$6:$J$10,5,0)&"_as_is = "&VLOOKUP(B118,Instruções!$F$6:$J$10,5,0)&"_to_be ") -> ON instrmnt_id_as_is = instrmnt_id_to_be | K118: ="WHERE coalesce(cast("&F118&" as string), '') <> coalesce(cast("&G118&" as string), '') " -> WHERE coalesce(cast(accmltd_wrtffs_instrmnt_as_is as string), '') <> coalesce(cast(accmltd_wrtffs_instrmnt_to_be as string), '') | L118: ="SELECT count(*) AS NUM_REG_DIF FROM "&H118&" Inner join "&I118&J118&K118 -> SELECT count(*) AS NUM_REG_DIF FROM (SELECT instrmnt_id as instrmnt_id_as_is, accmltd_wrtffs_instrmnt as accmltd_wrtffs_instrmnt_as_is FROM cd_loan_tapes_bce.lt002_instrument WHERE ref_date='2025-06-30' AND nome_perimetro= 'Individual IDComb' AND segmento= 'ESTR' AND ambito= 'PM' AND entidade='00100' AND cod_visao = 1) A Inner join (SELECT instrmnt_id as instrmnt_id_to_be, accmltd_wrtffs_instrmnt as accmltd_wrtffs_instrmnt_to_be FROM bu_loantape_work.lt002_instrument WHERE ref_date='2025-06-30' AND nome_perimetro= 'Individual IDComb' AND segmento= 'ESTR' AND ambito= 'PM' AND entidade='00100' AND cod_visao = 1) B ON instrmnt_id_as_is = instrmnt_id_to_be WHERE coalesce(cast(accmltd_wrtffs_instrmnt_as_is as string), '') <> coalesce(cast(accmltd_wrtffs_instrmnt_to_be as string), '') | M118: Validação de campos | N118: ="SELECT 'Validação de campos' as tipologia_teste, '"&VLOOKUP(B118,Instruções!$F$6:$J$10,3,0)&"' AS TABELA, '"&E118&"' AS CAMPO, '"&Instruções!$D$7&"' as ref_date, coalesce(NUM_REG_DIF, 0) AS NUM_REG_DIF FROM ("&L118&") A " -> SELECT 'Validação de campos' as tipologia_teste, 'lt002_instrument' AS TABELA, 'accmltd_wrtffs_instrmnt' AS CAMPO, '2025-06-30' as ref_date, coalesce(NUM_REG_DIF, 0) AS NUM_REG_DIF FROM (SELECT count(*) AS NUM_REG_DIF FROM (SELECT instrmnt_id as instrmnt_id_as_is, accmltd_wrtffs_instrmnt as accmltd_wrtffs_instrmnt_as_is FROM cd_loan_tapes_bce.lt002_instrument WHERE ref_date='2025-06-30' AND nome_perimetro= 'Individual IDComb' AND segmento= 'ESTR' AND ambito= 'PM' AND entidade='00100' AND cod_visao = 1) A Inner join (SELECT instrmnt_id as instrmnt_id_to_be, accmltd_wrtffs_instrmnt as accmltd_wrtffs_instrmnt_to_be FROM bu_loantape_work.lt002_instrument WHERE ref_date='2025-06-30' AND nome_perimetro= 'Individual IDComb' AND segmento= 'ESTR' AND ambito= 'PM' AND entidade='00100' AND cod_visao = 1) B ON instrmnt_id_as_is = instrmnt_id_to_be WHERE coalesce(cast(accmltd_wrtffs_instrmnt_as_is as string), '') <> coalesce(cast(accmltd_wrtffs_instrmnt_to_be as string), '') ) A | O118: =IF(O119="",N118,N118&$O$3) -> SELECT 'Validação de campos' as tipologia_teste, 'lt002_instrument' AS TABELA, 'accmltd_wrtffs_instrmnt' AS CAMPO, '2025-06-30' as ref_date, coalesce(NUM_REG_DIF, 0) AS NUM_REG_DIF FROM (SELECT count(*) AS NUM_REG_DIF FROM (SELECT instrmnt_id as instrmnt_id_as_is, accmltd_wrtffs_instrmnt as accmltd_wrtffs_instrmnt_as_is FROM cd_loan_tapes_bce.lt002_instrument WHERE ref_date='2025-06-30' AND nome_perimetro= 'Individual IDComb' AND segmento= 'ESTR' AND ambito= 'PM' AND entidade='00100' AND cod_visao = 1) A Inner join (SELECT instrmnt_id as instrmnt_id_to_be, accmltd_wrtffs_instrmnt as accmltd_wrtffs_instrmnt_to_be FROM bu_loantape_work.lt002_instrument WHERE ref_date='2025-06-30' AND nome_perimetro= 'Individual IDComb' AND segmento= 'ESTR' AND ambito= 'PM' AND entidade='00100' AND cod_visao = 1) B ON instrmnt_id_as_is = instrmnt_id_to_be WHERE coalesce(cast(accmltd_wrtffs_instrmnt_as_is as string), '') <> coalesce(cast(accmltd_wrtffs_instrmnt_to_be as string), '') ) A UNION ALL | P118: =P117+1 -> 6
B119: INSTRMNT | C119: =_xlfn.CONCAT(Instruções!$D$5,".",VLOOKUP(B119,Instruções!$F$5:$H$10,2,0)) -> cd_loan_tapes_bce.lt002_instrument | D119: =_xlfn.CONCAT(Instruções!$D$6,".",VLOOKUP(B119,Instruções!$F$5:$H$10,3,0)) -> bu_loantape_work.lt002_instrument | E119: accntng_clssfctn | F119: =E119&"_as_is" -> accntng_clssfctn_as_is | G119: =E119&"_to_be" -> accntng_clssfctn_to_be | H119: =IF(VLOOKUP(B119,Instruções!$F$6:$J$10,5,0)="", "(SELECT "&VLOOKUP(B119,Instruções!$F$6:$J$10,4,0)&" as "&VLOOKUP(B119,Instruções!$F$6:$J$10,4,0)&"_as_is, "&E119&" as "&F119&" FROM "&C119&" WHERE "&Instruções!$D$11&") A ", "(SELECT "&VLOOKUP(B119,Instruções!$F$6:$J$10,4,0)&" as "&VLOOKUP(B119,Instruções!$F$6:$J$10,4,0)&"_as_is, "&VLOOKUP(B119,Instruções!$F$6:$J$10,5,0)&" as "&VLOOKUP(B119,Instruções!$F$6:$J$10,5,0)&"_as_is,"&E119&" as "&F119&" FROM "&C119&" WHERE "&Instruções!$D$11&") A ") -> (SELECT instrmnt_id as instrmnt_id_as_is, accntng_clssfctn as accntng_clssfctn_as_is FROM cd_loan_tapes_bce.lt002_instrument WHERE ref_date='2025-06-30' AND nome_perimetro= 'Individual IDComb' AND segmento= 'ESTR' AND ambito= 'PM' AND entidade='00100' AND cod_visao = 1) A | I119: =IF(VLOOKUP(B119,Instruções!$F$6:$J$10,5,0)="", "(SELECT "&VLOOKUP(B119,Instruções!$F$6:$J$10,4,0)&" as "&VLOOKUP(B119,Instruções!$F$6:$J$10,4,0)&"_to_be, "&E119&" as "&G119&" FROM "&D119&" WHERE "&Instruções!$D$11&") B ", "(SELECT "&VLOOKUP(B119,Instruções!$F$6:$J$10,4,0)&" as "&VLOOKUP(B119,Instruções!$F$6:$J$10,4,0)&"_to_be, "&VLOOKUP(B119,Instruções!$F$6:$J$10,5,0)&" as "&VLOOKUP(B119,Instruções!$F$6:$J$10,5,0)&"_to_be,"&E119&" as "&G119&" FROM "&D119&" WHERE "&Instruções!$D$11&") B ") -> (SELECT instrmnt_id as instrmnt_id_to_be, accntng_clssfctn as accntng_clssfctn_to_be FROM bu_loantape_work.lt002_instrument WHERE ref_date='2025-06-30' AND nome_perimetro= 'Individual IDComb' AND segmento= 'ESTR' AND ambito= 'PM' AND entidade='00100' AND cod_visao = 1) B | J119: =IF(VLOOKUP(B119,Instruções!$F$6:$J$10,5,0)="", "ON "&VLOOKUP(B119,Instruções!$F$6:$J$10,4,0)&"_as_is = "&VLOOKUP(B119,Instruções!$F$6:$J$10,4,0)&"_to_be ", "ON "&VLOOKUP(B119,Instruções!$F$6:$J$10,4,0)&"_as_is = "&VLOOKUP(B119,Instruções!$F$6:$J$10,4,0)&"_to_be AND "&VLOOKUP(B119,Instruções!$F$6:$J$10,5,0)&"_as_is = "&VLOOKUP(B119,Instruções!$F$6:$J$10,5,0)&"_to_be ") -> ON instrmnt_id_as_is = instrmnt_id_to_be | K119: ="WHERE coalesce(cast("&F119&" as string), '') <> coalesce(cast("&G119&" as string), '') " -> WHERE coalesce(cast(accntng_clssfctn_as_is as string), '') <> coalesce(cast(accntng_clssfctn_to_be as string), '') | L119: ="SELECT count(*) AS NUM_REG_DIF FROM "&H119&" Inner join "&I119&J119&K119 -> SELECT count(*) AS NUM_REG_DIF FROM (SELECT instrmnt_id as instrmnt_id_as_is, accntng_clssfctn as accntng_clssfctn_as_is FROM cd_loan_tapes_bce.lt002_instrument WHERE ref_date='2025-06-30' AND nome_perimetro= 'Individual IDComb' AND segmento= 'ESTR' AND ambito= 'PM' AND entidade='00100' AND cod_visao = 1) A Inner join (SELECT instrmnt_id as instrmnt_id_to_be, accntng_clssfctn as accntng_clssfctn_to_be FROM bu_loantape_work.lt002_instrument WHERE ref_date='2025-06-30' AND nome_perimetro= 'Individual IDComb' AND segmento= 'ESTR' AND ambito= 'PM' AND entidade='00100' AND cod_visao = 1) B ON instrmnt_id_as_is = instrmnt_id_to_be WHERE coalesce(cast(accntng_clssfctn_as_is as string), '') <> coalesce(cast(accntng_clssfctn_to_be as string), '') | M119: Validação de campos | N119: ="SELECT 'Validação de campos' as tipologia_teste, '"&VLOOKUP(B119,Instruções!$F$6:$J$10,3,0)&"' AS TABELA, '"&E119&"' AS CAMPO, '"&Instruções!$D$7&"' as ref_date, coalesce(NUM_REG_DIF, 0) AS NUM_REG_DIF FROM ("&L119&") A " -> SELECT 'Validação de campos' as tipologia_teste, 'lt002_instrument' AS TABELA, 'accntng_clssfctn' AS CAMPO, '2025-06-30' as ref_date, coalesce(NUM_REG_DIF, 0) AS NUM_REG_DIF FROM (SELECT count(*) AS NUM_REG_DIF FROM (SELECT instrmnt_id as instrmnt_id_as_is, accntng_clssfctn as accntng_clssfctn_as_is FROM cd_loan_tapes_bce.lt002_instrument WHERE ref_date='2025-06-30' AND nome_perimetro= 'Individual IDComb' AND segmento= 'ESTR' AND ambito= 'PM' AND entidade='00100' AND cod_visao = 1) A Inner join (SELECT instrmnt_id as instrmnt_id_to_be, accntng_clssfctn as accntng_clssfctn_to_be FROM bu_loantape_work.lt002_instrument WHERE ref_date='2025-06-30' AND nome_perimetro= 'Individual IDComb' AND segmento= 'ESTR' AND ambito= 'PM' AND entidade='00100' AND cod_visao = 1) B ON instrmnt_id_as_is = instrmnt_id_to_be WHERE coalesce(cast(accntng_clssfctn_as_is as string), '') <> coalesce(cast(accntng_clssfctn_to_be as string), '') ) A | O119: =IF(O120="",N119,N119&$O$3) -> SELECT 'Validação de campos' as tipologia_teste, 'lt002_instrument' AS TABELA, 'accntng_clssfctn' AS CAMPO, '2025-06-30' as ref_date, coalesce(NUM_REG_DIF, 0) AS NUM_REG_DIF FROM (SELECT count(*) AS NUM_REG_DIF FROM (SELECT instrmnt_id as instrmnt_id_as_is, accntng_clssfctn as accntng_clssfctn_as_is FROM cd_loan_tapes_bce.lt002_instrument WHERE ref_date='2025-06-30' AND nome_perimetro= 'Individual IDComb' AND segmento= 'ESTR' AND ambito= 'PM' AND entidade='00100' AND cod_visao = 1) A Inner join (SELECT instrmnt_id as instrmnt_id_to_be, accntng_clssfctn as accntng_clssfctn_to_be FROM bu_loantape_work.lt002_instrument WHERE ref_date='2025-06-30' AND nome_perimetro= 'Individual IDComb' AND segmento= 'ESTR' AND ambito= 'PM' AND entidade='00100' AND cod_visao = 1) B ON instrmnt_id_as_is = instrmnt_id_to_be WHERE coalesce(cast(accntng_clssfctn_as_is as string), '') <> coalesce(cast(accntng_clssfctn_to_be as string), '') ) A UNION ALL | P119: =P118+1 -> 7
B120: INSTRMNT | C120: =_xlfn.CONCAT(Instruções!$D$5,".",VLOOKUP(B120,Instruções!$F$5:$H$10,2,0)) -> cd_loan_tapes_bce.lt002_instrument | D120: =_xlfn.CONCAT(Instruções!$D$6,".",VLOOKUP(B120,Instruções!$F$5:$H$10,3,0)) -> bu_loantape_work.lt002_instrument | E120: accrd_intrst_instrmnt | F120: =E120&"_as_is" -> accrd_intrst_instrmnt_as_is | G120: =E120&"_to_be" -> accrd_intrst_instrmnt_to_be | H120: =IF(VLOOKUP(B120,Instruções!$F$6:$J$10,5,0)="", "(SELECT "&VLOOKUP(B120,Instruções!$F$6:$J$10,4,0)&" as "&VLOOKUP(B120,Instruções!$F$6:$J$10,4,0)&"_as_is, "&E120&" as "&F120&" FROM "&C120&" WHERE "&Instruções!$D$11&") A ", "(SELECT "&VLOOKUP(B120,Instruções!$F$6:$J$10,4,0)&" as "&VLOOKUP(B120,Instruções!$F$6:$J$10,4,0)&"_as_is, "&VLOOKUP(B120,Instruções!$F$6:$J$10,5,0)&" as "&VLOOKUP(B120,Instruções!$F$6:$J$10,5,0)&"_as_is,"&E120&" as "&F120&" FROM "&C120&" WHERE "&Instruções!$D$11&") A ") -> (SELECT instrmnt_id as instrmnt_id_as_is, accrd_intrst_instrmnt as accrd_intrst_instrmnt_as_is FROM cd_loan_tapes_bce.lt002_instrument WHERE ref_date='2025-06-30' AND nome_perimetro= 'Individual IDComb' AND segmento= 'ESTR' AND ambito= 'PM' AND entidade='00100' AND cod_visao = 1) A | I120: =IF(VLOOKUP(B120,Instruções!$F$6:$J$10,5,0)="", "(SELECT "&VLOOKUP(B120,Instruções!$F$6:$J$10,4,0)&" as "&VLOOKUP(B120,Instruções!$F$6:$J$10,4,0)&"_to_be, "&E120&" as "&G120&" FROM "&D120&" WHERE "&Instruções!$D$11&") B ", "(SELECT "&VLOOKUP(B120,Instruções!$F$6:$J$10,4,0)&" as "&VLOOKUP(B120,Instruções!$F$6:$J$10,4,0)&"_to_be, "&VLOOKUP(B120,Instruções!$F$6:$J$10,5,0)&" as "&VLOOKUP(B120,Instruções!$F$6:$J$10,5,0)&"_to_be,"&E120&" as "&G120&" FROM "&D120&" WHERE "&Instruções!$D$11&") B ") -> (SELECT instrmnt_id as instrmnt_id_to_be, accrd_intrst_instrmnt as accrd_intrst_instrmnt_to_be FROM bu_loantape_work.lt002_instrument WHERE ref_date='2025-06-30' AND nome_perimetro= 'Individual IDComb' AND segmento= 'ESTR' AND ambito= 'PM' AND entidade='00100' AND cod_visao = 1) B | J120: =IF(VLOOKUP(B120,Instruções!$F$6:$J$10,5,0)="", "ON "&VLOOKUP(B120,Instruções!$F$6:$J$10,4,0)&"_as_is = "&VLOOKUP(B120,Instruções!$F$6:$J$10,4,0)&"_to_be ", "ON "&VLOOKUP(B120,Instruções!$F$6:$J$10,4,0)&"_as_is = "&VLOOKUP(B120,Instruções!$F$6:$J$10,4,0)&"_to_be AND "&VLOOKUP(B120,Instruções!$F$6:$J$10,5,0)&"_as_is = "&VLOOKUP(B120,Instruções!$F$6:$J$10,5,0)&"_to_be ") -> ON instrmnt_id_as_is = instrmnt_id_to_be | K120: ="WHERE coalesce(cast("&F120&" as string), '') <> coalesce(cast("&G120&" as string), '') " -> WHERE coalesce(cast(accrd_intrst_instrmnt_as_is as string), '') <> coalesce(cast(accrd_intrst_instrmnt_to_be as string), '') | L120: ="SELECT count(*) AS NUM_REG_DIF FROM "&H120&" Inner join "&I120&J120&K120 -> SELECT count(*) AS NUM_REG_DIF FROM (SELECT instrmnt_id as instrmnt_id_as_is, accrd_intrst_instrmnt as accrd_intrst_instrmnt_as_is FROM cd_loan_tapes_bce.lt002_instrument WHERE ref_date='2025-06-30' AND nome_perimetro= 'Individual IDComb' AND segmento= 'ESTR' AND ambito= 'PM' AND entidade='00100' AND cod_visao = 1) A Inner join (SELECT instrmnt_id as instrmnt_id_to_be, accrd_intrst_instrmnt as accrd_intrst_instrmnt_to_be FROM bu_loantape_work.lt002_instrument WHERE ref_date='2025-06-30' AND nome_perimetro= 'Individual IDComb' AND segmento= 'ESTR' AND ambito= 'PM' AND entidade='00100' AND cod_visao = 1) B ON instrmnt_id_as_is = instrmnt_id_to_be WHERE coalesce(cast(accrd_intrst_instrmnt_as_is as string), '') <> coalesce(cast(accrd_intrst_instrmnt_to_be as string), '') | M120: Validação de campos | N120: ="SELECT 'Validação de campos' as tipologia_teste, '"&VLOOKUP(B120,Instruções!$F$6:$J$10,3,0)&"' AS TABELA, '"&E120&"' AS CAMPO, '"&Instruções!$D$7&"' as ref_date, coalesce(NUM_REG_DIF, 0) AS NUM_REG_DIF FROM ("&L120&") A " -> SELECT 'Validação de campos' as tipologia_teste, 'lt002_instrument' AS TABELA, 'accrd_intrst_instrmnt' AS CAMPO, '2025-06-30' as ref_date, coalesce(NUM_REG_DIF, 0) AS NUM_REG_DIF FROM (SELECT count(*) AS NUM_REG_DIF FROM (SELECT instrmnt_id as instrmnt_id_as_is, accrd_intrst_instrmnt as accrd_intrst_instrmnt_as_is FROM cd_loan_tapes_bce.lt002_instrument WHERE ref_date='2025-06-30' AND nome_perimetro= 'Individual IDComb' AND segmento= 'ESTR' AND ambito= 'PM' AND entidade='00100' AND cod_visao = 1) A Inner join (SELECT instrmnt_id as instrmnt_id_to_be, accrd_intrst_instrmnt as accrd_intrst_instrmnt_to_be FROM bu_loantape_work.lt002_instrument WHERE ref_date='2025-06-30' AND nome_perimetro= 'Individual IDComb' AND segmento= 'ESTR' AND ambito= 'PM' AND entidade='00100' AND cod_visao = 1) B ON instrmnt_id_as_is = instrmnt_id_to_be WHERE coalesce(cast(accrd_intrst_instrmnt_as_is as string), '') <> coalesce(cast(accrd_intrst_instrmnt_to_be as string), '') ) A | O120: =IF(O121="",N120,N120&$O$3) -> SELECT 'Validação de campos' as tipologia_teste, 'lt002_instrument' AS TABELA, 'accrd_intrst_instrmnt' AS CAMPO, '2025-06-30' as ref_date, coalesce(NUM_REG_DIF, 0) AS NUM_REG_DIF FROM (SELECT count(*) AS NUM_REG_DIF FROM (SELECT instrmnt_id as instrmnt_id_as_is, accrd_intrst_instrmnt as accrd_intrst_instrmnt_as_is FROM cd_loan_tapes_bce.lt002_instrument WHERE ref_date='2025-06-30' AND nome_perimetro= 'Individual IDComb' AND segmento= 'ESTR' AND ambito= 'PM' AND entidade='00100' AND cod_visao = 1) A Inner join (SELECT instrmnt_id as instrmnt_id_to_be, accrd_intrst_instrmnt as accrd_intrst_instrmnt_to_be FROM bu_loantape_work.lt002_instrument WHERE ref_date='2025-06-30' AND nome_perimetro= 'Individual IDComb' AND segmento= 'ESTR' AND ambito= 'PM' AND entidade='00100' AND cod_visao = 1) B ON instrmnt_id_as_is = instrmnt_id_to_be WHERE coalesce(cast(accrd_intrst_instrmnt_as_is as string), '') <> coalesce(cast(accrd_intrst_instrmnt_to_be as string), '') ) A UNION ALL | P120: =P119+1 -> 8
B121: INSTRMNT | C121: =_xlfn.CONCAT(Instruções!$D$5,".",VLOOKUP(B121,Instruções!$F$5:$H$10,2,0)) -> cd_loan_tapes_bce.lt002_instrument | D121: =_xlfn.CONCAT(Instruções!$D$6,".",VLOOKUP(B121,Instruções!$F$5:$H$10,3,0)) -> bu_loantape_work.lt002_instrument | E121: amnt_d_at_mtrty | F121: =E121&"_as_is" -> amnt_d_at_mtrty_as_is | G121: =E121&"_to_be" -> amnt_d_at_mtrty_to_be | H121: =IF(VLOOKUP(B121,Instruções!$F$6:$J$10,5,0)="", "(SELECT "&VLOOKUP(B121,Instruções!$F$6:$J$10,4,0)&" as "&VLOOKUP(B121,Instruções!$F$6:$J$10,4,0)&"_as_is, "&E121&" as "&F121&" FROM "&C121&" WHERE "&Instruções!$D$11&") A ", "(SELECT "&VLOOKUP(B121,Instruções!$F$6:$J$10,4,0)&" as "&VLOOKUP(B121,Instruções!$F$6:$J$10,4,0)&"_as_is, "&VLOOKUP(B121,Instruções!$F$6:$J$10,5,0)&" as "&VLOOKUP(B121,Instruções!$F$6:$J$10,5,0)&"_as_is,"&E121&" as "&F121&" FROM "&C121&" WHERE "&Instruções!$D$11&") A ") -> (SELECT instrmnt_id as instrmnt_id_as_is, amnt_d_at_mtrty as amnt_d_at_mtrty_as_is FROM cd_loan_tapes_bce.lt002_instrument WHERE ref_date='2025-06-30' AND nome_perimetro= 'Individual IDComb' AND segmento= 'ESTR' AND ambito= 'PM' AND entidade='00100' AND cod_visao = 1) A | I121: =IF(VLOOKUP(B121,Instruções!$F$6:$J$10,5,0)="", "(SELECT "&VLOOKUP(B121,Instruções!$F$6:$J$10,4,0)&" as "&VLOOKUP(B121,Instruções!$F$6:$J$10,4,0)&"_to_be, "&E121&" as "&G121&" FROM "&D121&" WHERE "&Instruções!$D$11&") B ", "(SELECT "&VLOOKUP(B121,Instruções!$F$6:$J$10,4,0)&" as "&VLOOKUP(B121,Instruções!$F$6:$J$10,4,0)&"_to_be, "&VLOOKUP(B121,Instruções!$F$6:$J$10,5,0)&" as "&VLOOKUP(B121,Instruções!$F$6:$J$10,5,0)&"_to_be,"&E121&" as "&G121&" FROM "&D121&" WHERE "&Instruções!$D$11&") B ") -> (SELECT instrmnt_id as instrmnt_id_to_be, amnt_d_at_mtrty as amnt_d_at_mtrty_to_be FROM bu_loantape_work.lt002_instrument WHERE ref_date='2025-06-30' AND nome_perimetro= 'Individual IDComb' AND segmento= 'ESTR' AND ambito= 'PM' AND entidade='00100' AND cod_visao = 1) B | J121: =IF(VLOOKUP(B121,Instruções!$F$6:$J$10,5,0)="", "ON "&VLOOKUP(B121,Instruções!$F$6:$J$10,4,0)&"_as_is = "&VLOOKUP(B121,Instruções!$F$6:$J$10,4,0)&"_to_be ", "ON "&VLOOKUP(B121,Instruções!$F$6:$J$10,4,0)&"_as_is = "&VLOOKUP(B121,Instruções!$F$6:$J$10,4,0)&"_to_be AND "&VLOOKUP(B121,Instruções!$F$6:$J$10,5,0)&"_as_is = "&VLOOKUP(B121,Instruções!$F$6:$J$10,5,0)&"_to_be ") -> ON instrmnt_id_as_is = instrmnt_id_to_be | K121: ="WHERE coalesce(cast("&F121&" as string), '') <> coalesce(cast("&G121&" as string), '') " -> WHERE coalesce(cast(amnt_d_at_mtrty_as_is as string), '') <> coalesce(cast(amnt_d_at_mtrty_to_be as string), '') | L121: ="SELECT count(*) AS NUM_REG_DIF FROM "&H121&" Inner join "&I121&J121&K121 -> SELECT count(*) AS NUM_REG_DIF FROM (SELECT instrmnt_id as instrmnt_id_as_is, amnt_d_at_mtrty as amnt_d_at_mtrty_as_is FROM cd_loan_tapes_bce.lt002_instrument WHERE ref_date='2025-06-30' AND nome_perimetro= 'Individual IDComb' AND segmento= 'ESTR' AND ambito= 'PM' AND entidade='00100' AND cod_visao = 1) A Inner join (SELECT instrmnt_id as instrmnt_id_to_be, amnt_d_at_mtrty as amnt_d_at_mtrty_to_be FROM bu_loantape_work.lt002_instrument WHERE ref_date='2025-06-30' AND nome_perimetro= 'Individual IDComb' AND segmento= 'ESTR' AND ambito= 'PM' AND entidade='00100' AND cod_visao = 1) B ON instrmnt_id_as_is = instrmnt_id_to_be WHERE coalesce(cast(amnt_d_at_mtrty_as_is as string), '') <> coalesce(cast(amnt_d_at_mtrty_to_be as string), '') | M121: Validação de campos | N121: ="SELECT 'Validação de campos' as tipologia_teste, '"&VLOOKUP(B121,Instruções!$F$6:$J$10,3,0)&"' AS TABELA, '"&E121&"' AS CAMPO, '"&Instruções!$D$7&"' as ref_date, coalesce(NUM_REG_DIF, 0) AS NUM_REG_DIF FROM ("&L121&") A " -> SELECT 'Validação de campos' as tipologia_teste, 'lt002_instrument' AS TABELA, 'amnt_d_at_mtrty' AS CAMPO, '2025-06-30' as ref_date, coalesce(NUM_REG_DIF, 0) AS NUM_REG_DIF FROM (SELECT count(*) AS NUM_REG_DIF FROM (SELECT instrmnt_id as instrmnt_id_as_is, amnt_d_at_mtrty as amnt_d_at_mtrty_as_is FROM cd_loan_tapes_bce.lt002_instrument WHERE ref_date='2025-06-30' AND nome_perimetro= 'Individual IDComb' AND segmento= 'ESTR' AND ambito= 'PM' AND entidade='00100' AND cod_visao = 1) A Inner join (SELECT instrmnt_id as instrmnt_id_to_be, amnt_d_at_mtrty as amnt_d_at_mtrty_to_be FROM bu_loantape_work.lt002_instrument WHERE ref_date='2025-06-30' AND nome_perimetro= 'Individual IDComb' AND segmento= 'ESTR' AND ambito= 'PM' AND entidade='00100' AND cod_visao = 1) B ON instrmnt_id_as_is = instrmnt_id_to_be WHERE coalesce(cast(amnt_d_at_mtrty_as_is as string), '') <> coalesce(cast(amnt_d_at_mtrty_to_be as string), '') ) A | O121: =IF(O122="",N121,N121&$O$3) -> SELECT 'Validação de campos' as tipologia_teste, 'lt002_instrument' AS TABELA, 'amnt_d_at_mtrty' AS CAMPO, '2025-06-30' as ref_date, coalesce(NUM_REG_DIF, 0) AS NUM_REG_DIF FROM (SELECT count(*) AS NUM_REG_DIF FROM (SELECT instrmnt_id as instrmnt_id_as_is, amnt_d_at_mtrty as amnt_d_at_mtrty_as_is FROM cd_loan_tapes_bce.lt002_instrument WHERE ref_date='2025-06-30' AND nome_perimetro= 'Individual IDComb' AND segmento= 'ESTR' AND ambito= 'PM' AND entidade='00100' AND cod_visao = 1) A Inner join (SELECT instrmnt_id as instrmnt_id_to_be, amnt_d_at_mtrty as amnt_d_at_mtrty_to_be FROM bu_loantape_work.lt002_instrument WHERE ref_date='2025-06-30' AND nome_perimetro= 'Individual IDComb' AND segmento= 'ESTR' AND ambito= 'PM' AND entidade='00100' AND cod_visao = 1) B ON instrmnt_id_as_is = instrmnt_id_to_be WHERE coalesce(cast(amnt_d_at_mtrty_as_is as string), '') <> coalesce(cast(amnt_d_at_mtrty_to_be as string), '') ) A UNION ALL | P121: =P120+1 -> 9
B122: INSTRMNT | C122: =_xlfn.CONCAT(Instruções!$D$5,".",VLOOKUP(B122,Instruções!$F$5:$H$10,2,0)) -> cd_loan_tapes_bce.lt002_instrument | D122: =_xlfn.CONCAT(Instruções!$D$6,".",VLOOKUP(B122,Instruções!$F$5:$H$10,3,0)) -> bu_loantape_work.lt002_instrument | E122: annlsd_agrd_rt | F122: =E122&"_as_is" -> annlsd_agrd_rt_as_is | G122: =E122&"_to_be" -> annlsd_agrd_rt_to_be | H122: =IF(VLOOKUP(B122,Instruções!$F$6:$J$10,5,0)="", "(SELECT "&VLOOKUP(B122,Instruções!$F$6:$J$10,4,0)&" as "&VLOOKUP(B122,Instruções!$F$6:$J$10,4,0)&"_as_is, "&E122&" as "&F122&" FROM "&C122&" WHERE "&Instruções!$D$11&") A ", "(SELECT "&VLOOKUP(B122,Instruções!$F$6:$J$10,4,0)&" as "&VLOOKUP(B122,Instruções!$F$6:$J$10,4,0)&"_as_is, "&VLOOKUP(B122,Instruções!$F$6:$J$10,5,0)&" as "&VLOOKUP(B122,Instruções!$F$6:$J$10,5,0)&"_as_is,"&E122&" as "&F122&" FROM "&C122&" WHERE "&Instruções!$D$11&") A ") -> (SELECT instrmnt_id as instrmnt_id_as_is, annlsd_agrd_rt as annlsd_agrd_rt_as_is FROM cd_loan_tapes_bce.lt002_instrument WHERE ref_date='2025-06-30' AND nome_perimetro= 'Individual IDComb' AND segmento= 'ESTR' AND ambito= 'PM' AND entidade='00100' AND cod_visao = 1) A | I122: =IF(VLOOKUP(B122,Instruções!$F$6:$J$10,5,0)="", "(SELECT "&VLOOKUP(B122,Instruções!$F$6:$J$10,4,0)&" as "&VLOOKUP(B122,Instruções!$F$6:$J$10,4,0)&"_to_be, "&E122&" as "&G122&" FROM "&D122&" WHERE "&Instruções!$D$11&") B ", "(SELECT "&VLOOKUP(B122,Instruções!$F$6:$J$10,4,0)&" as "&VLOOKUP(B122,Instruções!$F$6:$J$10,4,0)&"_to_be, "&VLOOKUP(B122,Instruções!$F$6:$J$10,5,0)&" as "&VLOOKUP(B122,Instruções!$F$6:$J$10,5,0)&"_to_be,"&E122&" as "&G122&" FROM "&D122&" WHERE "&Instruções!$D$11&") B ") -> (SELECT instrmnt_id as instrmnt_id_to_be, annlsd_agrd_rt as annlsd_agrd_rt_to_be FROM bu_loantape_work.lt002_instrument WHERE ref_date='2025-06-30' AND nome_perimetro= 'Individual IDComb' AND segmento= 'ESTR' AND ambito= 'PM' AND entidade='00100' AND cod_visao = 1) B | J122: =IF(VLOOKUP(B122,Instruções!$F$6:$J$10,5,0)="", "ON "&VLOOKUP(B122,Instruções!$F$6:$J$10,4,0)&"_as_is = "&VLOOKUP(B122,Instruções!$F$6:$J$10,4,0)&"_to_be ", "ON "&VLOOKUP(B122,Instruções!$F$6:$J$10,4,0)&"_as_is = "&VLOOKUP(B122,Instruções!$F$6:$J$10,4,0)&"_to_be AND "&VLOOKUP(B122,Instruções!$F$6:$J$10,5,0)&"_as_is = "&VLOOKUP(B122,Instruções!$F$6:$J$10,5,0)&"_to_be ") -> ON instrmnt_id_as_is = instrmnt_id_to_be | K122: ="WHERE coalesce(cast("&F122&" as string), '') <> coalesce(cast("&G122&" as string), '') " -> WHERE coalesce(cast(annlsd_agrd_rt_as_is as string), '') <> coalesce(cast(annlsd_agrd_rt_to_be as string), '') | L122: ="SELECT count(*) AS NUM_REG_DIF FROM "&H122&" Inner join "&I122&J122&K122 -> SELECT count(*) AS NUM_REG_DIF FROM (SELECT instrmnt_id as instrmnt_id_as_is, annlsd_agrd_rt as annlsd_agrd_rt_as_is FROM cd_loan_tapes_bce.lt002_instrument WHERE ref_date='2025-06-30' AND nome_perimetro= 'Individual IDComb' AND segmento= 'ESTR' AND ambito= 'PM' AND entidade='00100' AND cod_visao = 1) A Inner join (SELECT instrmnt_id as instrmnt_id_to_be, annlsd_agrd_rt as annlsd_agrd_rt_to_be FROM bu_loantape_work.lt002_instrument WHERE ref_date='2025-06-30' AND nome_perimetro= 'Individual IDComb' AND segmento= 'ESTR' AND ambito= 'PM' AND entidade='00100' AND cod_visao = 1) B ON instrmnt_id_as_is = instrmnt_id_to_be WHERE coalesce(cast(annlsd_agrd_rt_as_is as string), '') <> coalesce(cast(annlsd_agrd_rt_to_be as string), '') | M122: Validação de campos | N122: ="SELECT 'Validação de campos' as tipologia_teste, '"&VLOOKUP(B122,Instruções!$F$6:$J$10,3,0)&"' AS TABELA, '"&E122&"' AS CAMPO, '"&Instruções!$D$7&"' as ref_date, coalesce(NUM_REG_DIF, 0) AS NUM_REG_DIF FROM ("&L122&") A " -> SELECT 'Validação de campos' as tipologia_teste, 'lt002_instrument' AS TABELA, 'annlsd_agrd_rt' AS CAMPO, '2025-06-30' as ref_date, coalesce(NUM_REG_DIF, 0) AS NUM_REG_DIF FROM (SELECT count(*) AS NUM_REG_DIF FROM (SELECT instrmnt_id as instrmnt_id_as_is, annlsd_agrd_rt as annlsd_agrd_rt_as_is FROM cd_loan_tapes_bce.lt002_instrument WHERE ref_date='2025-06-30' AND nome_perimetro= 'Individual IDComb' AND segmento= 'ESTR' AND ambito= 'PM' AND entidade='00100' AND cod_visao = 1) A Inner join (SELECT instrmnt_id as instrmnt_id_to_be, annlsd_agrd_rt as annlsd_agrd_rt_to_be FROM bu_loantape_work.lt002_instrument WHERE ref_date='2025-06-30' AND nome_perimetro= 'Individual IDComb' AND segmento= 'ESTR' AND ambito= 'PM' AND entidade='00100' AND cod_visao = 1) B ON instrmnt_id_as_is = instrmnt_id_to_be WHERE coalesce(cast(annlsd_agrd_rt_as_is as string), '') <> coalesce(cast(annlsd_agrd_rt_to_be as string), '') ) A | O122: =IF(O123="",N122,N122&$O$3) -> SELECT 'Validação de campos' as tipologia_teste, 'lt002_instrument' AS TABELA, 'annlsd_agrd_rt' AS CAMPO, '2025-06-30' as ref_date, coalesce(NUM_REG_DIF, 0) AS NUM_REG_DIF FROM (SELECT count(*) AS NUM_REG_DIF FROM (SELECT instrmnt_id as instrmnt_id_as_is, annlsd_agrd_rt as annlsd_agrd_rt_as_is FROM cd_loan_tapes_bce.lt002_instrument WHERE ref_date='2025-06-30' AND nome_perimetro= 'Individual IDComb' AND segmento= 'ESTR' AND ambito= 'PM' AND entidade='00100' AND cod_visao = 1) A Inner join (SELECT instrmnt_id as instrmnt_id_to_be, annlsd_agrd_rt as annlsd_agrd_rt_to_be FROM bu_loantape_work.lt002_instrument WHERE ref_date='2025-06-30' AND nome_perimetro= 'Individual IDComb' AND segmento= 'ESTR' AND ambito= 'PM' AND entidade='00100' AND cod_visao = 1) B ON instrmnt_id_as_is = instrmnt_id_to_be WHERE coalesce(cast(annlsd_agrd_rt_as_is as string), '') <> coalesce(cast(annlsd_agrd_rt_to_be as string), '') ) A UNION ALL | P122: =P121+1 -> 10
B123: INSTRMNT | C123: =_xlfn.CONCAT(Instruções!$D$5,".",VLOOKUP(B123,Instruções!$F$5:$H$10,2,0)) -> cd_loan_tapes_bce.lt002_instrument | D123: =_xlfn.CONCAT(Instruções!$D$6,".",VLOOKUP(B123,Instruções!$F$5:$H$10,3,0)) -> bu_loantape_work.lt002_instrument | E123: arrrs_instrmnt | F123: =E123&"_as_is" -> arrrs_instrmnt_as_is | G123: =E123&"_to_be" -> arrrs_instrmnt_to_be | H123: =IF(VLOOKUP(B123,Instruções!$F$6:$J$10,5,0)="", "(SELECT "&VLOOKUP(B123,Instruções!$F$6:$J$10,4,0)&" as "&VLOOKUP(B123,Instruções!$F$6:$J$10,4,0)&"_as_is, "&E123&" as "&F123&" FROM "&C123&" WHERE "&Instruções!$D$11&") A ", "(SELECT "&VLOOKUP(B123,Instruções!$F$6:$J$10,4,0)&" as "&VLOOKUP(B123,Instruções!$F$6:$J$10,4,0)&"_as_is, "&VLOOKUP(B123,Instruções!$F$6:$J$10,5,0)&" as "&VLOOKUP(B123,Instruções!$F$6:$J$10,5,0)&"_as_is,"&E123&" as "&F123&" FROM "&C123&" WHERE "&Instruções!$D$11&") A ") -> (SELECT instrmnt_id as instrmnt_id_as_is, arrrs_instrmnt as arrrs_instrmnt_as_is FROM cd_loan_tapes_bce.lt002_instrument WHERE ref_date='2025-06-30' AND nome_perimetro= 'Individual IDComb' AND segmento= 'ESTR' AND ambito= 'PM' AND entidade='00100' AND cod_visao = 1) A | I123: =IF(VLOOKUP(B123,Instruções!$F$6:$J$10,5,0)="", "(SELECT "&VLOOKUP(B123,Instruções!$F$6:$J$10,4,0)&" as "&VLOOKUP(B123,Instruções!$F$6:$J$10,4,0)&"_to_be, "&E123&" as "&G123&" FROM "&D123&" WHERE "&Instruções!$D$11&") B ", "(SELECT "&VLOOKUP(B123,Instruções!$F$6:$J$10,4,0)&" as "&VLOOKUP(B123,Instruções!$F$6:$J$10,4,0)&"_to_be, "&VLOOKUP(B123,Instruções!$F$6:$J$10,5,0)&" as "&VLOOKUP(B123,Instruções!$F$6:$J$10,5,0)&"_to_be,"&E123&" as "&G123&" FROM "&D123&" WHERE "&Instruções!$D$11&") B ") -> (SELECT instrmnt_id as instrmnt_id_to_be, arrrs_instrmnt as arrrs_instrmnt_to_be FROM bu_loantape_work.lt002_instrument WHERE ref_date='2025-06-30' AND nome_perimetro= 'Individual IDComb' AND segmento= 'ESTR' AND ambito= 'PM' AND entidade='00100' AND cod_visao = 1) B | J123: =IF(VLOOKUP(B123,Instruções!$F$6:$J$10,5,0)="", "ON "&VLOOKUP(B123,Instruções!$F$6:$J$10,4,0)&"_as_is = "&VLOOKUP(B123,Instruções!$F$6:$J$10,4,0)&"_to_be ", "ON "&VLOOKUP(B123,Instruções!$F$6:$J$10,4,0)&"_as_is = "&VLOOKUP(B123,Instruções!$F$6:$J$10,4,0)&"_to_be AND "&VLOOKUP(B123,Instruções!$F$6:$J$10,5,0)&"_as_is = "&VLOOKUP(B123,Instruções!$F$6:$J$10,5,0)&"_to_be ") -> ON instrmnt_id_as_is = instrmnt_id_to_be | K123: ="WHERE coalesce(cast("&F123&" as string), '') <> coalesce(cast("&G123&" as string), '') " -> WHERE coalesce(cast(arrrs_instrmnt_as_is as string), '') <> coalesce(cast(arrrs_instrmnt_to_be as string), '') | L123: ="SELECT count(*) AS NUM_REG_DIF FROM "&H123&" Inner join "&I123&J123&K123 -> SELECT count(*) AS NUM_REG_DIF FROM (SELECT instrmnt_id as instrmnt_id_as_is, arrrs_instrmnt as arrrs_instrmnt_as_is FROM cd_loan_tapes_bce.lt002_instrument WHERE ref_date='2025-06-30' AND nome_perimetro= 'Individual IDComb' AND segmento= 'ESTR' AND ambito= 'PM' AND entidade='00100' AND cod_visao = 1) A Inner join (SELECT instrmnt_id as instrmnt_id_to_be, arrrs_instrmnt as arrrs_instrmnt_to_be FROM bu_loantape_work.lt002_instrument WHERE ref_date='2025-06-30' AND nome_perimetro= 'Individual IDComb' AND segmento= 'ESTR' AND ambito= 'PM' AND entidade='00100' AND cod_visao = 1) B ON instrmnt_id_as_is = instrmnt_id_to_be WHERE coalesce(cast(arrrs_instrmnt_as_is as string), '') <> coalesce(cast(arrrs_instrmnt_to_be as string), '') | M123: Validação de campos | N123: ="SELECT 'Validação de campos' as tipologia_teste, '"&VLOOKUP(B123,Instruções!$F$6:$J$10,3,0)&"' AS TABELA, '"&E123&"' AS CAMPO, '"&Instruções!$D$7&"' as ref_date, coalesce(NUM_REG_DIF, 0) AS NUM_REG_DIF FROM ("&L123&") A " -> SELECT 'Validação de campos' as tipologia_teste, 'lt002_instrument' AS TABELA, 'arrrs_instrmnt' AS CAMPO, '2025-06-30' as ref_date, coalesce(NUM_REG_DIF, 0) AS NUM_REG_DIF FROM (SELECT count(*) AS NUM_REG_DIF FROM (SELECT instrmnt_id as instrmnt_id_as_is, arrrs_instrmnt as arrrs_instrmnt_as_is FROM cd_loan_tapes_bce.lt002_instrument WHERE ref_date='2025-06-30' AND nome_perimetro= 'Individual IDComb' AND segmento= 'ESTR' AND ambito= 'PM' AND entidade='00100' AND cod_visao = 1) A Inner join (SELECT instrmnt_id as instrmnt_id_to_be, arrrs_instrmnt as arrrs_instrmnt_to_be FROM bu_loantape_work.lt002_instrument WHERE ref_date='2025-06-30' AND nome_perimetro= 'Individual IDComb' AND segmento= 'ESTR' AND ambito= 'PM' AND entidade='00100' AND cod_visao = 1) B ON instrmnt_id_as_is = instrmnt_id_to_be WHERE coalesce(cast(arrrs_instrmnt_as_is as string), '') <> coalesce(cast(arrrs_instrmnt_to_be as string), '') ) A | O123: =IF(O124="",N123,N123&$O$3) -> SELECT 'Validação de campos' as tipologia_teste, 'lt002_instrument' AS TABELA, 'arrrs_instrmnt' AS CAMPO, '2025-06-30' as ref_date, coalesce(NUM_REG_DIF, 0) AS NUM_REG_DIF FROM (SELECT count(*) AS NUM_REG_DIF FROM (SELECT instrmnt_id as instrmnt_id_as_is, arrrs_instrmnt as arrrs_instrmnt_as_is FROM cd_loan_tapes_bce.lt002_instrument WHERE ref_date='2025-06-30' AND nome_perimetro= 'Individual IDComb' AND segmento= 'ESTR' AND ambito= 'PM' AND entidade='00100' AND cod_visao = 1) A Inner join (SELECT instrmnt_id as instrmnt_id_to_be, arrrs_instrmnt as arrrs_instrmnt_to_be FROM bu_loantape_work.lt002_instrument WHERE ref_date='2025-06-30' AND nome_perimetro= 'Individual IDComb' AND segmento= 'ESTR' AND ambito= 'PM' AND entidade='00100' AND cod_visao = 1) B ON instrmnt_id_as_is = instrmnt_id_to_be WHERE coalesce(cast(arrrs_instrmnt_as_is as string), '') <> coalesce(cast(arrrs_instrmnt_to_be as string), '') ) A UNION ALL | P123: =P122+1 -> 11
B124: INSTRMNT | C124: =_xlfn.CONCAT(Instruções!$D$5,".",VLOOKUP(B124,Instruções!$F$5:$H$10,2,0)) -> cd_loan_tapes_bce.lt002_instrument | D124: =_xlfn.CONCAT(Instruções!$D$6,".",VLOOKUP(B124,Instruções!$F$5:$H$10,3,0)) -> bu_loantape_work.lt002_instrument | E124: arrrs_instrmnt_12m | F124: =E124&"_as_is" -> arrrs_instrmnt_12m_as_is | G124: =E124&"_to_be" -> arrrs_instrmnt_12m_to_be | H124: =IF(VLOOKUP(B124,Instruções!$F$6:$J$10,5,0)="", "(SELECT "&VLOOKUP(B124,Instruções!$F$6:$J$10,4,0)&" as "&VLOOKUP(B124,Instruções!$F$6:$J$10,4,0)&"_as_is, "&E124&" as "&F124&" FROM "&C124&" WHERE "&Instruções!$D$11&") A ", "(SELECT "&VLOOKUP(B124,Instruções!$F$6:$J$10,4,0)&" as "&VLOOKUP(B124,Instruções!$F$6:$J$10,4,0)&"_as_is, "&VLOOKUP(B124,Instruções!$F$6:$J$10,5,0)&" as "&VLOOKUP(B124,Instruções!$F$6:$J$10,5,0)&"_as_is,"&E124&" as "&F124&" FROM "&C124&" WHERE "&Instruções!$D$11&") A ") -> (SELECT instrmnt_id as instrmnt_id_as_is, arrrs_instrmnt_12m as arrrs_instrmnt_12m_as_is FROM cd_loan_tapes_bce.lt002_instrument WHERE ref_date='2025-06-30' AND nome_perimetro= 'Individual IDComb' AND segmento= 'ESTR' AND ambito= 'PM' AND entidade='00100' AND cod_visao = 1) A | I124: =IF(VLOOKUP(B124,Instruções!$F$6:$J$10,5,0)="", "(SELECT "&VLOOKUP(B124,Instruções!$F$6:$J$10,4,0)&" as "&VLOOKUP(B124,Instruções!$F$6:$J$10,4,0)&"_to_be, "&E124&" as "&G124&" FROM "&D124&" WHERE "&Instruções!$D$11&") B ", "(SELECT "&VLOOKUP(B124,Instruções!$F$6:$J$10,4,0)&" as "&VLOOKUP(B124,Instruções!$F$6:$J$10,4,0)&"_to_be, "&VLOOKUP(B124,Instruções!$F$6:$J$10,5,0)&" as "&VLOOKUP(B124,Instruções!$F$6:$J$10,5,0)&"_to_be,"&E124&" as "&G124&" FROM "&D124&" WHERE "&Instruções!$D$11&") B ") -> (SELECT instrmnt_id as instrmnt_id_to_be, arrrs_instrmnt_12m as arrrs_instrmnt_12m_to_be FROM bu_loantape_work.lt002_instrument WHERE ref_date='2025-06-30' AND nome_perimetro= 'Individual IDComb' AND segmento= 'ESTR' AND ambito= 'PM' AND entidade='00100' AND cod_visao = 1) B | J124: =IF(VLOOKUP(B124,Instruções!$F$6:$J$10,5,0)="", "ON "&VLOOKUP(B124,Instruções!$F$6:$J$10,4,0)&"_as_is = "&VLOOKUP(B124,Instruções!$F$6:$J$10,4,0)&"_to_be ", "ON "&VLOOKUP(B124,Instruções!$F$6:$J$10,4,0)&"_as_is = "&VLOOKUP(B124,Instruções!$F$6:$J$10,4,0)&"_to_be AND "&VLOOKUP(B124,Instruções!$F$6:$J$10,5,0)&"_as_is = "&VLOOKUP(B124,Instruções!$F$6:$J$10,5,0)&"_to_be ") -> ON instrmnt_id_as_is = instrmnt_id_to_be | K124: ="WHERE coalesce(cast("&F124&" as string), '') <> coalesce(cast("&G124&" as string), '') " -> WHERE coalesce(cast(arrrs_instrmnt_12m_as_is as string), '') <> coalesce(cast(arrrs_instrmnt_12m_to_be as string), '') | L124: ="SELECT count(*) AS NUM_REG_DIF FROM "&H124&" Inner join "&I124&J124&K124 -> SELECT count(*) AS NUM_REG_DIF FROM (SELECT instrmnt_id as instrmnt_id_as_is, arrrs_instrmnt_12m as arrrs_instrmnt_12m_as_is FROM cd_loan_tapes_bce.lt002_instrument WHERE ref_date='2025-06-30' AND nome_perimetro= 'Individual IDComb' AND segmento= 'ESTR' AND ambito= 'PM' AND entidade='00100' AND cod_visao = 1) A Inner join (SELECT instrmnt_id as instrmnt_id_to_be, arrrs_instrmnt_12m as arrrs_instrmnt_12m_to_be FROM bu_loantape_work.lt002_instrument WHERE ref_date='2025-06-30' AND nome_perimetro= 'Individual IDComb' AND segmento= 'ESTR' AND ambito= 'PM' AND entidade='00100' AND cod_visao = 1) B ON instrmnt_id_as_is = instrmnt_id_to_be WHERE coalesce(cast(arrrs_instrmnt_12m_as_is as string), '') <> coalesce(cast(arrrs_instrmnt_12m_to_be as string), '') | M124: Validação de campos | N124: ="SELECT 'Validação de campos' as tipologia_teste, '"&VLOOKUP(B124,Instruções!$F$6:$J$10,3,0)&"' AS TABELA, '"&E124&"' AS CAMPO, '"&Instruções!$D$7&"' as ref_date, coalesce(NUM_REG_DIF, 0) AS NUM_REG_DIF FROM ("&L124&") A " -> SELECT 'Validação de campos' as tipologia_teste, 'lt002_instrument' AS TABELA, 'arrrs_instrmnt_12m' AS CAMPO, '2025-06-30' as ref_date, coalesce(NUM_REG_DIF, 0) AS NUM_REG_DIF FROM (SELECT count(*) AS NUM_REG_DIF FROM (SELECT instrmnt_id as instrmnt_id_as_is, arrrs_instrmnt_12m as arrrs_instrmnt_12m_as_is FROM cd_loan_tapes_bce.lt002_instrument WHERE ref_date='2025-06-30' AND nome_perimetro= 'Individual IDComb' AND segmento= 'ESTR' AND ambito= 'PM' AND entidade='00100' AND cod_visao = 1) A Inner join (SELECT instrmnt_id as instrmnt_id_to_be, arrrs_instrmnt_12m as arrrs_instrmnt_12m_to_be FROM bu_loantape_work.lt002_instrument WHERE ref_date='2025-06-30' AND nome_perimetro= 'Individual IDComb' AND segmento= 'ESTR' AND ambito= 'PM' AND entidade='00100' AND cod_visao = 1) B ON instrmnt_id_as_is = instrmnt_id_to_be WHERE coalesce(cast(arrrs_instrmnt_12m_as_is as string), '') <> coalesce(cast(arrrs_instrmnt_12m_to_be as string), '') ) A | O124: =IF(O125="",N124,N124&$O$3) -> SELECT 'Validação de campos' as tipologia_teste, 'lt002_instrument' AS TABELA, 'arrrs_instrmnt_12m' AS CAMPO, '2025-06-30' as ref_date, coalesce(NUM_REG_DIF, 0) AS NUM_REG_DIF FROM (SELECT count(*) AS NUM_REG_DIF FROM (SELECT instrmnt_id as instrmnt_id_as_is, arrrs_instrmnt_12m as arrrs_instrmnt_12m_as_is FROM cd_loan_tapes_bce.lt002_instrument WHERE ref_date='2025-06-30' AND nome_perimetro= 'Individual IDComb' AND segmento= 'ESTR' AND ambito= 'PM' AND entidade='00100' AND cod_visao = 1) A Inner join (SELECT instrmnt_id as instrmnt_id_to_be, arrrs_instrmnt_12m as arrrs_instrmnt_12m_to_be FROM bu_loantape_work.lt002_instrument WHERE ref_date='2025-06-30' AND nome_perimetro= 'Individual IDComb' AND segmento= 'ESTR' AND ambito= 'PM' AND entidade='00100' AND cod_visao = 1) B ON instrmnt_id_as_is = instrmnt_id_to_be WHERE coalesce(cast(arrrs_instrmnt_12m_as_is as string), '') <> coalesce(cast(arrrs_instrmnt_12m_to_be as string), '') ) A UNION ALL | P124: =P123+1 -> 12
B125: INSTRMNT | C125: =_xlfn.CONCAT(Instruções!$D$5,".",VLOOKUP(B125,Instruções!$F$5:$H$10,2,0)) -> cd_loan_tapes_bce.lt002_instrument | D125: =_xlfn.CONCAT(Instruções!$D$6,".",VLOOKUP(B125,Instruções!$F$5:$H$10,3,0)) -> bu_loantape_work.lt002_instrument | E125: asst_scrt_clss | F125: =E125&"_as_is" -> asst_scrt_clss_as_is | G125: =E125&"_to_be" -> asst_scrt_clss_to_be | H125: =IF(VLOOKUP(B125,Instruções!$F$6:$J$10,5,0)="", "(SELECT "&VLOOKUP(B125,Instruções!$F$6:$J$10,4,0)&" as "&VLOOKUP(B125,Instruções!$F$6:$J$10,4,0)&"_as_is, "&E125&" as "&F125&" FROM "&C125&" WHERE "&Instruções!$D$11&") A ", "(SELECT "&VLOOKUP(B125,Instruções!$F$6:$J$10,4,0)&" as "&VLOOKUP(B125,Instruções!$F$6:$J$10,4,0)&"_as_is, "&VLOOKUP(B125,Instruções!$F$6:$J$10,5,0)&" as "&VLOOKUP(B125,Instruções!$F$6:$J$10,5,0)&"_as_is,"&E125&" as "&F125&" FROM "&C125&" WHERE "&Instruções!$D$11&") A ") -> (SELECT instrmnt_id as instrmnt_id_as_is, asst_scrt_clss as asst_scrt_clss_as_is FROM cd_loan_tapes_bce.lt002_instrument WHERE ref_date='2025-06-30' AND nome_perimetro= 'Individual IDComb' AND segmento= 'ESTR' AND ambito= 'PM' AND entidade='00100' AND cod_visao = 1) A | I125: =IF(VLOOKUP(B125,Instruções!$F$6:$J$10,5,0)="", "(SELECT "&VLOOKUP(B125,Instruções!$F$6:$J$10,4,0)&" as "&VLOOKUP(B125,Instruções!$F$6:$J$10,4,0)&"_to_be, "&E125&" as "&G125&" FROM "&D125&" WHERE "&Instruções!$D$11&") B ", "(SELECT "&VLOOKUP(B125,Instruções!$F$6:$J$10,4,0)&" as "&VLOOKUP(B125,Instruções!$F$6:$J$10,4,0)&"_to_be, "&VLOOKUP(B125,Instruções!$F$6:$J$10,5,0)&" as "&VLOOKUP(B125,Instruções!$F$6:$J$10,5,0)&"_to_be,"&E125&" as "&G125&" FROM "&D125&" WHERE "&Instruções!$D$11&") B ") -> (SELECT instrmnt_id as instrmnt_id_to_be, asst_scrt_clss as asst_scrt_clss_to_be FROM bu_loantape_work.lt002_instrument WHERE ref_date='2025-06-30' AND nome_perimetro= 'Individual IDComb' AND segmento= 'ESTR' AND ambito= 'PM' AND entidade='00100' AND cod_visao = 1) B | J125: =IF(VLOOKUP(B125,Instruções!$F$6:$J$10,5,0)="", "ON "&VLOOKUP(B125,Instruções!$F$6:$J$10,4,0)&"_as_is = "&VLOOKUP(B125,Instruções!$F$6:$J$10,4,0)&"_to_be ", "ON "&VLOOKUP(B125,Instruções!$F$6:$J$10,4,0)&"_as_is = "&VLOOKUP(B125,Instruções!$F$6:$J$10,4,0)&"_to_be AND "&VLOOKUP(B125,Instruções!$F$6:$J$10,5,0)&"_as_is = "&VLOOKUP(B125,Instruções!$F$6:$J$10,5,0)&"_to_be ") -> ON instrmnt_id_as_is = instrmnt_id_to_be | K125: ="WHERE coalesce(cast("&F125&" as string), '') <> coalesce(cast("&G125&" as string), '') " -> WHERE coalesce(cast(asst_scrt_clss_as_is as string), '') <> coalesce(cast(asst_scrt_clss_to_be as string), '') | L125: ="SELECT count(*) AS NUM_REG_DIF FROM "&H125&" Inner join "&I125&J125&K125 -> SELECT count(*) AS NUM_REG_DIF FROM (SELECT instrmnt_id as instrmnt_id_as_is, asst_scrt_clss as asst_scrt_clss_as_is FROM cd_loan_tapes_bce.lt002_instrument WHERE ref_date='2025-06-30' AND nome_perimetro= 'Individual IDComb' AND segmento= 'ESTR' AND ambito= 'PM' AND entidade='00100' AND cod_visao = 1) A Inner join (SELECT instrmnt_id as instrmnt_id_to_be, asst_scrt_clss as asst_scrt_clss_to_be FROM bu_loantape_work.lt002_instrument WHERE ref_date='2025-06-30' AND nome_perimetro= 'Individual IDComb' AND segmento= 'ESTR' AND ambito= 'PM' AND entidade='00100' AND cod_visao = 1) B ON instrmnt_id_as_is = instrmnt_id_to_be WHERE coalesce(cast(asst_scrt_clss_as_is as string), '') <> coalesce(cast(asst_scrt_clss_to_be as string), '') | M125: Validação de campos | N125: ="SELECT 'Validação de campos' as tipologia_teste, '"&VLOOKUP(B125,Instruções!$F$6:$J$10,3,0)&"' AS TABELA, '"&E125&"' AS CAMPO, '"&Instruções!$D$7&"' as ref_date, coalesce(NUM_REG_DIF, 0) AS NUM_REG_DIF FROM ("&L125&") A " -> SELECT 'Validação de campos' as tipologia_teste, 'lt002_instrument' AS TABELA, 'asst_scrt_clss' AS CAMPO, '2025-06-30' as ref_date, coalesce(NUM_REG_DIF, 0) AS NUM_REG_DIF FROM (SELECT count(*) AS NUM_REG_DIF FROM (SELECT instrmnt_id as instrmnt_id_as_is, asst_scrt_clss as asst_scrt_clss_as_is FROM cd_loan_tapes_bce.lt002_instrument WHERE ref_date='2025-06-30' AND nome_perimetro= 'Individual IDComb' AND segmento= 'ESTR' AND ambito= 'PM' AND entidade='00100' AND cod_visao = 1) A Inner join (SELECT instrmnt_id as instrmnt_id_to_be, asst_scrt_clss as asst_scrt_clss_to_be FROM bu_loantape_work.lt002_instrument WHERE ref_date='2025-06-30' AND nome_perimetro= 'Individual IDComb' AND segmento= 'ESTR' AND ambito= 'PM' AND entidade='00100' AND cod_visao = 1) B ON instrmnt_id_as_is = instrmnt_id_to_be WHERE coalesce(cast(asst_scrt_clss_as_is as string), '') <> coalesce(cast(asst_scrt_clss_to_be as string), '') ) A | O125: =IF(O126="",N125,N125&$O$3) -> SELECT 'Validação de campos' as tipologia_teste, 'lt002_instrument' AS TABELA, 'asst_scrt_clss' AS CAMPO, '2025-06-30' as ref_date, coalesce(NUM_REG_DIF, 0) AS NUM_REG_DIF FROM (SELECT count(*) AS NUM_REG_DIF FROM (SELECT instrmnt_id as instrmnt_id_as_is, asst_scrt_clss as asst_scrt_clss_as_is FROM cd_loan_tapes_bce.lt002_instrument WHERE ref_date='2025-06-30' AND nome_perimetro= 'Individual IDComb' AND segmento= 'ESTR' AND ambito= 'PM' AND entidade='00100' AND cod_visao = 1) A Inner join (SELECT instrmnt_id as instrmnt_id_to_be, asst_scrt_clss as asst_scrt_clss_to_be FROM bu_loantape_work.lt002_instrument WHERE ref_date='2025-06-30' AND nome_perimetro= 'Individual IDComb' AND segmento= 'ESTR' AND ambito= 'PM' AND entidade='00100' AND cod_visao = 1) B ON instrmnt_id_as_is = instrmnt_id_to_be WHERE coalesce(cast(asst_scrt_clss_as_is as string), '') <> coalesce(cast(asst_scrt_clss_to_be as string), '') ) A UNION ALL | P125: =P124+1 -> 13
B126: INSTRMNT | C126: =_xlfn.CONCAT(Instruções!$D$5,".",VLOOKUP(B126,Instruções!$F$5:$H$10,2,0)) -> cd_loan_tapes_bce.lt002_instrument | D126: =_xlfn.CONCAT(Instruções!$D$6,".",VLOOKUP(B126,Instruções!$F$5:$H$10,3,0)) -> bu_loantape_work.lt002_instrument | E126: brchd_cvnnts | F126: =E126&"_as_is" -> brchd_cvnnts_as_is | G126: =E126&"_to_be" -> brchd_cvnnts_to_be | H126: =IF(VLOOKUP(B126,Instruções!$F$6:$J$10,5,0)="", "(SELECT "&VLOOKUP(B126,Instruções!$F$6:$J$10,4,0)&" as "&VLOOKUP(B126,Instruções!$F$6:$J$10,4,0)&"_as_is, "&E126&" as "&F126&" FROM "&C126&" WHERE "&Instruções!$D$11&") A ", "(SELECT "&VLOOKUP(B126,Instruções!$F$6:$J$10,4,0)&" as "&VLOOKUP(B126,Instruções!$F$6:$J$10,4,0)&"_as_is, "&VLOOKUP(B126,Instruções!$F$6:$J$10,5,0)&" as "&VLOOKUP(B126,Instruções!$F$6:$J$10,5,0)&"_as_is,"&E126&" as "&F126&" FROM "&C126&" WHERE "&Instruções!$D$11&") A ") -> (SELECT instrmnt_id as instrmnt_id_as_is, brchd_cvnnts as brchd_cvnnts_as_is FROM cd_loan_tapes_bce.lt002_instrument WHERE ref_date='2025-06-30' AND nome_perimetro= 'Individual IDComb' AND segmento= 'ESTR' AND ambito= 'PM' AND entidade='00100' AND cod_visao = 1) A | I126: =IF(VLOOKUP(B126,Instruções!$F$6:$J$10,5,0)="", "(SELECT "&VLOOKUP(B126,Instruções!$F$6:$J$10,4,0)&" as "&VLOOKUP(B126,Instruções!$F$6:$J$10,4,0)&"_to_be, "&E126&" as "&G126&" FROM "&D126&" WHERE "&Instruções!$D$11&") B ", "(SELECT "&VLOOKUP(B126,Instruções!$F$6:$J$10,4,0)&" as "&VLOOKUP(B126,Instruções!$F$6:$J$10,4,0)&"_to_be, "&VLOOKUP(B126,Instruções!$F$6:$J$10,5,0)&" as "&VLOOKUP(B126,Instruções!$F$6:$J$10,5,0)&"_to_be,"&E126&" as "&G126&" FROM "&D126&" WHERE "&Instruções!$D$11&") B ") -> (SELECT instrmnt_id as instrmnt_id_to_be, brchd_cvnnts as brchd_cvnnts_to_be FROM bu_loantape_work.lt002_instrument WHERE ref_date='2025-06-30' AND nome_perimetro= 'Individual IDComb' AND segmento= 'ESTR' AND ambito= 'PM' AND entidade='00100' AND cod_visao = 1) B | J126: =IF(VLOOKUP(B126,Instruções!$F$6:$J$10,5,0)="", "ON "&VLOOKUP(B126,Instruções!$F$6:$J$10,4,0)&"_as_is = "&VLOOKUP(B126,Instruções!$F$6:$J$10,4,0)&"_to_be ", "ON "&VLOOKUP(B126,Instruções!$F$6:$J$10,4,0)&"_as_is = "&VLOOKUP(B126,Instruções!$F$6:$J$10,4,0)&"_to_be AND "&VLOOKUP(B126,Instruções!$F$6:$J$10,5,0)&"_as_is = "&VLOOKUP(B126,Instruções!$F$6:$J$10,5,0)&"_to_be ") -> ON instrmnt_id_as_is = instrmnt_id_to_be | K126: ="WHERE coalesce(cast("&F126&" as string), '') <> coalesce(cast("&G126&" as string), '') " -> WHERE coalesce(cast(brchd_cvnnts_as_is as string), '') <> coalesce(cast(brchd_cvnnts_to_be as string), '') | L126: ="SELECT count(*) AS NUM_REG_DIF FROM "&H126&" Inner join "&I126&J126&K126 -> SELECT count(*) AS NUM_REG_DIF FROM (SELECT instrmnt_id as instrmnt_id_as_is, brchd_cvnnts as brchd_cvnnts_as_is FROM cd_loan_tapes_bce.lt002_instrument WHERE ref_date='2025-06-30' AND nome_perimetro= 'Individual IDComb' AND segmento= 'ESTR' AND ambito= 'PM' AND entidade='00100' AND cod_visao = 1) A Inner join (SELECT instrmnt_id as instrmnt_id_to_be, brchd_cvnnts as brchd_cvnnts_to_be FROM bu_loantape_work.lt002_instrument WHERE ref_date='2025-06-30' AND nome_perimetro= 'Individual IDComb' AND segmento= 'ESTR' AND ambito= 'PM' AND entidade='00100' AND cod_visao = 1) B ON instrmnt_id_as_is = instrmnt_id_to_be WHERE coalesce(cast(brchd_cvnnts_as_is as string), '') <> coalesce(cast(brchd_cvnnts_to_be as string), '') | M126: Validação de campos | N126: ="SELECT 'Validação de campos' as tipologia_teste, '"&VLOOKUP(B126,Instruções!$F$6:$J$10,3,0)&"' AS TABELA, '"&E126&"' AS CAMPO, '"&Instruções!$D$7&"' as ref_date, coalesce(NUM_REG_DIF, 0) AS NUM_REG_DIF FROM ("&L126&") A " -> SELECT 'Validação de campos' as tipologia_teste, 'lt002_instrument' AS TABELA, 'brchd_cvnnts' AS CAMPO, '2025-06-30' as ref_date, coalesce(NUM_REG_DIF, 0) AS NUM_REG_DIF FROM (SELECT count(*) AS NUM_REG_DIF FROM (SELECT instrmnt_id as instrmnt_id_as_is, brchd_cvnnts as brchd_cvnnts_as_is FROM cd_loan_tapes_bce.lt002_instrument WHERE ref_date='2025-06-30' AND nome_perimetro= 'Individual IDComb' AND segmento= 'ESTR' AND ambito= 'PM' AND entidade='00100' AND cod_visao = 1) A Inner join (SELECT instrmnt_id as instrmnt_id_to_be, brchd_cvnnts as brchd_cvnnts_to_be FROM bu_loantape_work.lt002_instrument WHERE ref_date='2025-06-30' AND nome_perimetro= 'Individual IDComb' AND segmento= 'ESTR' AND ambito= 'PM' AND entidade='00100' AND cod_visao = 1) B ON instrmnt_id_as_is = instrmnt_id_to_be WHERE coalesce(cast(brchd_cvnnts_as_is as string), '') <> coalesce(cast(brchd_cvnnts_to_be as string), '') ) A | O126: =IF(O127="",N126,N126&$O$3) -> SELECT 'Validação de campos' as tipologia_teste, 'lt002_instrument' AS TABELA, 'brchd_cvnnts' AS CAMPO, '2025-06-30' as ref_date, coalesce(NUM_REG_DIF, 0) AS NUM_REG_DIF FROM (SELECT count(*) AS NUM_REG_DIF FROM (SELECT instrmnt_id as instrmnt_id_as_is, brchd_cvnnts as brchd_cvnnts_as_is FROM cd_loan_tapes_bce.lt002_instrument WHERE ref_date='2025-06-30' AND nome_perimetro= 'Individual IDComb' AND segmento= 'ESTR' AND ambito= 'PM' AND entidade='00100' AND cod_visao = 1) A Inner join (SELECT instrmnt_id as instrmnt_id_to_be, brchd_cvnnts as brchd_cvnnts_to_be FROM bu_loantape_work.lt002_instrument WHERE ref_date='2025-06-30' AND nome_perimetro= 'Individual IDComb' AND segmento= 'ESTR' AND ambito= 'PM' AND entidade='00100' AND cod_visao = 1) B ON instrmnt_id_as_is = instrmnt_id_to_be WHERE coalesce(cast(brchd_cvnnts_as_is as string), '') <> coalesce(cast(brchd_cvnnts_to_be as string), '') ) A UNION ALL | P126: =P125+1 -> 14
... B132: INSTRMNT | C132: =_xlfn.CONCAT(Instruções!$D$5,".",VLOOKUP(B132,Instruções!$F$5:$H$10,2,0)) -> cd_loan_tapes_bce.lt002_instrument | D132: =_xlfn.CONCAT(Instruções!$D$6,".",VLOOKUP(B132,Instruções!$F$5:$H$10,3,0)) -> bu_loantape_work.lt002_instrument | E132: cnsmptn_fnrp18 | F132: =E132&"_as_is" -> cnsmptn_fnrp18_as_is | G132: =E132&"_to_be" -> cnsmptn_fnrp18_to_be | H132: =IF(VLOOKUP(B132,Instruções!$F$6:$J$10,5,0)="", "(SELECT "&VLOOKUP(B132,Instruções!$F$6:$J$10,4,0)&" as "&VLOOKUP(B132,Instruções!$F$6:$J$10,4,0)&"_as_is, "&E132&" as "&F132&" FROM "&C132&" WHERE "&Instruções!$D$11&") A ", "(SELECT "&VLOOKUP(B132,Instruções!$F$6:$J$10,4,0)&" as "&VLOOKUP(B132,Instruções!$F$6:$J$10,4,0)&"_as_is, "&VLOOKUP(B132,Instruções!$F$6:$J$10,5,0)&" as "&VLOOKUP(B132,Instruções!$F$6:$J$10,5,0)&"_as_is,"&E132&" as "&F132&" FROM "&C132&" WHERE "&Instruções!$D$11&") A ") -> (SELECT instrmnt_id as instrmnt_id_as_is, cnsmptn_fnrp18 as cnsmptn_fnrp18_as_is FROM cd_loan_tapes_bce.lt002_instrument WHERE ref_date='2025-06-30' AND nome_perimetro= 'Individual IDComb' AND segmento= 'ESTR' AND ambito= 'PM' AND entidade='00100' AND cod_visao = 1) A | I132: =IF(VLOOKUP(B132,Instruções!$F$6:$J$10,5,0)="", "(SELECT "&VLOOKUP(B132,Instruções!$F$6:$J$10,4,0)&" as "&VLOOKUP(B132,Instruções!$F$6:$J$10,4,0)&"_to_be, "&E132&" as "&G132&" FROM "&D132&" WHERE "&Instruções!$D$11&") B ", "(SELECT "&VLOOKUP(B132,Instruções!$F$6:$J$10,4,0)&" as "&VLOOKUP(B132,Instruções!$F$6:$J$10,4,0)&"_to_be, "&VLOOKUP(B132,Instruções!$F$6:$J$10,5,0)&" as "&VLOOKUP(B132,Instruções!$F$6:$J$10,5,0)&"_to_be,"&E132&" as "&G132&" FROM "&D132&" WHERE "&Instruções!$D$11&") B ") -> (SELECT instrmnt_id as instrmnt_id_to_be, cnsmptn_fnrp18 as cnsmptn_fnrp18_to_be FROM bu_loantape_work.lt002_instrument WHERE ref_date='2025-06-30' AND nome_perimetro= 'Individual IDComb' AND segmento= 'ESTR' AND ambito= 'PM' AND entidade='00100' AND cod_visao = 1) B | J132: =IF(VLOOKUP(B132,Instruções!$F$6:$J$10,5,0)="", "ON "&VLOOKUP(B132,Instruções!$F$6:$J$10,4,0)&"_as_is = "&VLOOKUP(B132,Instruções!$F$6:$J$10,4,0)&"_to_be ", "ON "&VLOOKUP(B132,Instruções!$F$6:$J$10,4,0)&"_as_is = "&VLOOKUP(B132,Instruções!$F$6:$J$10,4,0)&"_to_be AND "&VLOOKUP(B132,Instruções!$F$6:$J$10,5,0)&"_as_is = "&VLOOKUP(B132,Instruções!$F$6:$J$10,5,0)&"_to_be ") -> ON instrmnt_id_as_is = instrmnt_id_to_be | K132: ="WHERE coalesce(cast("&F132&" as string), '') <> coalesce(cast("&G132&" as string), '') " -> WHERE coalesce(cast(cnsmptn_fnrp18_as_is as string), '') <> coalesce(cast(cnsmptn_fnrp18_to_be as string), '') | L132: ="SELECT count(*) AS NUM_REG_DIF FROM "&H132&" Inner join "&I132&J132&K132 -> SELECT count(*) AS NUM_REG_DIF FROM (SELECT instrmnt_id as instrmnt_id_as_is, cnsmptn_fnrp18 as cnsmptn_fnrp18_as_is FROM cd_loan_tapes_bce.lt002_instrument WHERE ref_date='2025-06-30' AND nome_perimetro= 'Individual IDComb' AND segmento= 'ESTR' AND ambito= 'PM' AND entidade='00100' AND cod_visao = 1) A Inner join (SELECT instrmnt_id as instrmnt_id_to_be, cnsmptn_fnrp18 as cnsmptn_fnrp18_to_be FROM bu_loantape_work.lt002_instrument WHERE ref_date='2025-06-30' AND nome_perimetro= 'Individual IDComb' AND segmento= 'ESTR' AND ambito= 'PM' AND entidade='00100' AND cod_visao = 1) B ON instrmnt_id_as_is = instrmnt_id_to_be WHERE coalesce(cast(cnsmptn_fnrp18_as_is as string), '') <> coalesce(cast(cnsmptn_fnrp18_to_be as string), '') | M132: Validação de campos | N132: ="SELECT 'Validação de campos' as tipologia_teste, '"&VLOOKUP(B132,Instruções!$F$6:$J$10,3,0)&"' AS TABELA, '"&E132&"' AS CAMPO, '"&Instruções!$D$7&"' as ref_date, coalesce(NUM_REG_DIF, 0) AS NUM_REG_DIF FROM ("&L132&") A " -> SELECT 'Validação de campos' as tipologia_teste, 'lt002_instrument' AS TABELA, 'cnsmptn_fnrp18' AS CAMPO, '2025-06-30' as ref_date, coalesce(NUM_REG_DIF, 0) AS NUM_REG_DIF FROM (SELECT count(*) AS NUM_REG_DIF FROM (SELECT instrmnt_id as instrmnt_id_as_is, cnsmptn_fnrp18 as cnsmptn_fnrp18_as_is FROM cd_loan_tapes_bce.lt002_instrument WHERE ref_date='2025-06-30' AND nome_perimetro= 'Individual IDComb' AND segmento= 'ESTR' AND ambito= 'PM' AND entidade='00100' AND cod_visao = 1) A Inner join (SELECT instrmnt_id as instrmnt_id_to_be, cnsmptn_fnrp18 as cnsmptn_fnrp18_to_be FROM bu_loantape_work.lt002_instrument WHERE ref_date='2025-06-30' AND nome_perimetro= 'Individual IDComb' AND segmento= 'ESTR' AND ambito= 'PM' AND entidade='00100' AND cod_visao = 1) B ON instrmnt_id_as_is = instrmnt_id_to_be WHERE coalesce(cast(cnsmptn_fnrp18_as_is as string), '') <> coalesce(cast(cnsmptn_fnrp18_to_be as string), '') ) A | O132: =IF(O133="",N132,N132&$O$3) -> SELECT 'Validação de campos' as tipologia_teste, 'lt002_instrument' AS TABELA, 'cnsmptn_fnrp18' AS CAMPO, '2025-06-30' as ref_date, coalesce(NUM_REG_DIF, 0) AS NUM_REG_DIF FROM (SELECT count(*) AS NUM_REG_DIF FROM (SELECT instrmnt_id as instrmnt_id_as_is, cnsmptn_fnrp18 as cnsmptn_fnrp18_as_is FROM cd_loan_tapes_bce.lt002_instrument WHERE ref_date='2025-06-30' AND nome_perimetro= 'Individual IDComb' AND segmento= 'ESTR' AND ambito= 'PM' AND entidade='00100' AND cod_visao = 1) A Inner join (SELECT instrmnt_id as instrmnt_id_to_be, cnsmptn_fnrp18 as cnsmptn_fnrp18_to_be FROM bu_loantape_work.lt002_instrument WHERE ref_date='2025-06-30' AND nome_perimetro= 'Individual IDComb' AND segmento= 'ESTR' AND ambito= 'PM' AND entidade='00100' AND cod_visao = 1) B ON instrmnt_id_as_is = instrmnt_id_to_be WHERE coalesce(cast(cnsmptn_fnrp18_as_is as string), '') <> coalesce(cast(cnsmptn_fnrp18_to_be as string), '') ) A UNION ALL | P132: =P131+1 -> 20
B133: INSTRMNT | C133: =_xlfn.CONCAT(Instruções!$D$5,".",VLOOKUP(B133,Instruções!$F$5:$H$10,2,0)) -> cd_loan_tapes_bce.lt002_instrument | D133: =_xlfn.CONCAT(Instruções!$D$6,".",VLOOKUP(B133,Instruções!$F$5:$H$10,3,0)) -> bu_loantape_work.lt002_instrument | E133: cntrct_id | F133: =E133&"_as_is" -> cntrct_id_as_is | G133: =E133&"_to_be" -> cntrct_id_to_be | H133: =IF(VLOOKUP(B133,Instruções!$F$6:$J$10,5,0)="", "(SELECT "&VLOOKUP(B133,Instruções!$F$6:$J$10,4,0)&" as "&VLOOKUP(B133,Instruções!$F$6:$J$10,4,0)&"_as_is, "&E133&" as "&F133&" FROM "&C133&" WHERE "&Instruções!$D$11&") A ", "(SELECT "&VLOOKUP(B133,Instruções!$F$6:$J$10,4,0)&" as "&VLOOKUP(B133,Instruções!$F$6:$J$10,4,0)&"_as_is, "&VLOOKUP(B133,Instruções!$F$6:$J$10,5,0)&" as "&VLOOKUP(B133,Instruções!$F$6:$J$10,5,0)&"_as_is,"&E133&" as "&F133&" FROM "&C133&" WHERE "&Instruções!$D$11&") A ") -> (SELECT instrmnt_id as instrmnt_id_as_is, cntrct_id as cntrct_id_as_is FROM cd_loan_tapes_bce.lt002_instrument WHERE ref_date='2025-06-30' AND nome_perimetro= 'Individual IDComb' AND segmento= 'ESTR' AND ambito= 'PM' AND entidade='00100' AND cod_visao = 1) A | I133: =IF(VLOOKUP(B133,Instruções!$F$6:$J$10,5,0)="", "(SELECT "&VLOOKUP(B133,Instruções!$F$6:$J$10,4,0)&" as "&VLOOKUP(B133,Instruções!$F$6:$J$10,4,0)&"_to_be, "&E133&" as "&G133&" FROM "&D133&" WHERE "&Instruções!$D$11&") B ", "(SELECT "&VLOOKUP(B133,Instruções!$F$6:$J$10,4,0)&" as "&VLOOKUP(B133,Instruções!$F$6:$J$10,4,0)&"_to_be, "&VLOOKUP(B133,Instruções!$F$6:$J$10,5,0)&" as "&VLOOKUP(B133,Instruções!$F$6:$J$10,5,0)&"_to_be,"&E133&" as "&G133&" FROM "&D133&" WHERE "&Instruções!$D$11&") B ") -> (SELECT instrmnt_id as instrmnt_id_to_be, cntrct_id as cntrct_id_to_be FROM bu_loantape_work.lt002_instrument WHERE ref_date='2025-06-30' AND nome_perimetro= 'Individual IDComb' AND segmento= 'ESTR' AND ambito= 'PM' AND entidade='00100' AND cod_visao = 1) B | J133: =IF(VLOOKUP(B133,Instruções!$F$6:$J$10,5,0)="", "ON "&VLOOKUP(B133,Instruções!$F$6:$J$10,4,0)&"_as_is = "&VLOOKUP(B133,Instruções!$F$6:$J$10,4,0)&"_to_be ", "ON "&VLOOKUP(B133,Instruções!$F$6:$J$10,4,0)&"_as_is = "&VLOOKUP(B133,Instruções!$F$6:$J$10,4,0)&"_to_be AND "&VLOOKUP(B133,Instruções!$F$6:$J$10,5,0)&"_as_is = "&VLOOKUP(B133,Instruções!$F$6:$J$10,5,0)&"_to_be ") -> ON instrmnt_id_as_is = instrmnt_id_to_be | K133: ="WHERE coalesce(cast("&F133&" as string), '') <> coalesce(cast("&G133&" as string), '') " -> WHERE coalesce(cast(cntrct_id_as_is as string), '') <> coalesce(cast(cntrct_id_to_be as string), '') | L133: ="SELECT count(*) AS NUM_REG_DIF FROM "&H133&" Inner join "&I133&J133&K133 -> SELECT count(*) AS NUM_REG_DIF FROM (SELECT instrmnt_id as instrmnt_id_as_is, cntrct_id as cntrct_id_as_is FROM cd_loan_tapes_bce.lt002_instrument WHERE ref_date='2025-06-30' AND nome_perimetro= 'Individual IDComb' AND segmento= 'ESTR' AND ambito= 'PM' AND entidade='00100' AND cod_visao = 1) A Inner join (SELECT instrmnt_id as instrmnt_id_to_be, cntrct_id as cntrct_id_to_be FROM bu_loantape_work.lt002_instrument WHERE ref_date='2025-06-30' AND nome_perimetro= 'Individual IDComb' AND segmento= 'ESTR' AND ambito= 'PM' AND entidade='00100' AND cod_visao = 1) B ON instrmnt_id_as_is = instrmnt_id_to_be WHERE coalesce(cast(cntrct_id_as_is as string), '') <> coalesce(cast(cntrct_id_to_be as string), '') | M133: Validação de campos | N133: ="SELECT 'Validação de campos' as tipologia_teste, '"&VLOOKUP(B133,Instruções!$F$6:$J$10,3,0)&"' AS TABELA, '"&E133&"' AS CAMPO, '"&Instruções!$D$7&"' as ref_date, coalesce(NUM_REG_DIF, 0) AS NUM_REG_DIF FROM ("&L133&") A " -> SELECT 'Validação de campos' as tipologia_teste, 'lt002_instrument' AS TABELA, 'cntrct_id' AS CAMPO, '2025-06-30' as ref_date, coalesce(NUM_REG_DIF, 0) AS NUM_REG_DIF FROM (SELECT count(*) AS NUM_REG_DIF FROM (SELECT instrmnt_id as instrmnt_id_as_is, cntrct_id as cntrct_id_as_is FROM cd_loan_tapes_bce.lt002_instrument WHERE ref_date='2025-06-30' AND nome_perimetro= 'Individual IDComb' AND segmento= 'ESTR' AND ambito= 'PM' AND entidade='00100' AND cod_visao = 1) A Inner join (SELECT instrmnt_id as instrmnt_id_to_be, cntrct_id as cntrct_id_to_be FROM bu_loantape_work.lt002_instrument WHERE ref_date='2025-06-30' AND nome_perimetro= 'Individual IDComb' AND segmento= 'ESTR' AND ambito= 'PM' AND entidade='00100' AND cod_visao = 1) B ON instrmnt_id_as_is = instrmnt_id_to_be WHERE coalesce(cast(cntrct_id_as_is as string), '') <> coalesce(cast(cntrct_id_to_be as string), '') ) A | O133: SELECT 'Validação de campos' as tipologia_teste, 'lt002_instrument' AS TABELA, 'cntrct_id' AS CAMPO, '2025-06-30' as ref_date, coalesce(NUM_REG_DIF, 0) AS NUM_REG_DIF FROM (SELECT count(*) AS NUM_REG_DIF FROM (SELECT instrmnt_id as instrmnt_id_as_is, cntrct_id as cntrct_id_as_is FROM cd_loan_tapes_bce.lt002_instrument WHERE ref_date='2025-06-30' AND nome_perimetro= 'Individual IDComb' AND segmento= 'ESTR' AND ambito= 'PM' AND entidade='00100' AND cod_visao = 1) A Inner join (SELECT instrmnt_id as instrmnt_id_to_be, cntrct_id as cntrct_id_to_be FROM bu_loantape_work.lt002_instrument WHERE ref_date='2025-06-30' AND nome_perimetro= 'Individual IDComb' AND segmento= 'ESTR' AND ambito= 'PM' AND entidade='00100' AND cod_visao = 1) B ON instrmnt_id_as_is = instrmnt_id_to_be WHERE coalesce(cast(cntrct_id_as_is as string), '') <> coalesce(cast(cntrct_id_to_be as string), '') ) A | P133: =P132+1 -> 21
B135: INSTRMNT | C135: =_xlfn.CONCAT(Instruções!$D$5,".",VLOOKUP(B135,Instruções!$F$5:$H$10,2,0)) -> cd_loan_tapes_bce.lt002_instrument | D135: =_xlfn.CONCAT(Instruções!$D$6,".",VLOOKUP(B135,Instruções!$F$5:$H$10,3,0)) -> bu_loantape_work.lt002_instrument | E135: hedge_id | F135: =E135&"_as_is" -> hedge_id_as_is | G135: =E135&"_to_be" -> hedge_id_to_be | H135: =IF(VLOOKUP(B135,Instruções!$F$6:$J$10,5,0)="", "(SELECT "&VLOOKUP(B135,Instruções!$F$6:$J$10,4,0)&" as "&VLOOKUP(B135,Instruções!$F$6:$J$10,4,0)&"_as_is, concat_ws(',',sort_array(split("&E135&", ','))) as "&F135&" FROM "&C135&" WHERE "&Instruções!$D$11&") A ", "(SELECT "&VLOOKUP(B135,Instruções!$F$6:$J$10,4,0)&" as "&VLOOKUP(B135,Instruções!$F$6:$J$10,4,0)&"_as_is, "&VLOOKUP(B135,Instruções!$F$6:$J$10,5,0)&" as "&VLOOKUP(B135,Instruções!$F$6:$J$10,5,0)&"_as_is, concat_ws(',',sort_array(split("&E135&", ','))) as "&F135&" FROM "&C135&" WHERE "&Instruções!$D$11&") A ") -> (SELECT instrmnt_id as instrmnt_id_as_is, concat_ws(',',sort_array(split(hedge_id, ','))) as hedge_id_as_is FROM cd_loan_tapes_bce.lt002_instrument WHERE ref_date='2025-06-30' AND nome_perimetro= 'Individual IDComb' AND segmento= 'ESTR' AND ambito= 'PM' AND entidade='00100' AND cod_visao = 1) A | I135: =IF(VLOOKUP(B135,Instruções!$F$6:$J$10,5,0)="", "(SELECT "&VLOOKUP(B135,Instruções!$F$6:$J$10,4,0)&" as "&VLOOKUP(B135,Instruções!$F$6:$J$10,4,0)&"_to_be, concat_ws(',',sort_array(split("&E135&", ','))) as "&G135&" FROM "&D135&" WHERE "&Instruções!$D$11&") B ", "(SELECT "&VLOOKUP(B135,Instruções!$F$6:$J$10,4,0)&" as "&VLOOKUP(B135,Instruções!$F$6:$J$10,4,0)&"_to_be, "&VLOOKUP(B135,Instruções!$F$6:$J$10,5,0)&" as "&VLOOKUP(B135,Instruções!$F$6:$J$10,5,0)&"_to_be,"&E135&" as "&G135&" FROM "&D135&" WHERE "&Instruções!$D$11&") B ") -> (SELECT instrmnt_id as instrmnt_id_to_be, concat_ws(',',sort_array(split(hedge_id, ','))) as hedge_id_to_be FROM bu_loantape_work.lt002_instrument WHERE ref_date='2025-06-30' AND nome_perimetro= 'Individual IDComb' AND segmento= 'ESTR' AND ambito= 'PM' AND entidade='00100' AND cod_visao = 1) B | J135: =IF(VLOOKUP(B135,Instruções!$F$6:$J$10,5,0)="", "ON "&VLOOKUP(B135,Instruções!$F$6:$J$10,4,0)&"_as_is = "&VLOOKUP(B135,Instruções!$F$6:$J$10,4,0)&"_to_be ", "ON "&VLOOKUP(B135,Instruções!$F$6:$J$10,4,0)&"_as_is = "&VLOOKUP(B135,Instruções!$F$6:$J$10,4,0)&"_to_be AND "&VLOOKUP(B135,Instruções!$F$6:$J$10,5,0)&"_as_is = "&VLOOKUP(B135,Instruções!$F$6:$J$10,5,0)&"_to_be ") -> ON instrmnt_id_as_is = instrmnt_id_to_be | K135: ="WHERE coalesce(cast("&F135&" as string), '') <> coalesce(cast("&G135&" as string), '') " -> WHERE coalesce(cast(hedge_id_as_is as string), '') <> coalesce(cast(hedge_id_to_be as string), '') | L135: ="SELECT count(*) AS NUM_REG_DIF FROM "&H135&" Inner join "&I135&J135&K135 -> SELECT count(*) AS NUM_REG_DIF FROM (SELECT instrmnt_id as instrmnt_id_as_is, concat_ws(',',sort_array(split(hedge_id, ','))) as hedge_id_as_is FROM cd_loan_tapes_bce.lt002_instrument WHERE ref_date='2025-06-30' AND nome_perimetro= 'Individual IDComb' AND segmento= 'ESTR' AND ambito= 'PM' AND entidade='00100' AND cod_visao = 1) A Inner join (SELECT instrmnt_id as instrmnt_id_to_be, concat_ws(',',sort_array(split(hedge_id, ','))) as hedge_id_to_be FROM bu_loantape_work.lt002_instrument WHERE ref_date='2025-06-30' AND nome_perimetro= 'Individual IDComb' AND segmento= 'ESTR' AND ambito= 'PM' AND entidade='00100' AND cod_visao = 1) B ON instrmnt_id_as_is = instrmnt_id_to_be WHERE coalesce(cast(hedge_id_as_is as string), '') <> coalesce(cast(hedge_id_to_be as string), '') | M135: Validação de campos | N135: ="SELECT 'Validação de campos' as tipologia_teste, '"&VLOOKUP(B135,Instruções!$F$6:$J$10,3,0)&"' AS TABELA, '"&E135&"' AS CAMPO, '"&Instruções!$D$7&"' as ref_date, coalesce(NUM_REG_DIF, 0) AS NUM_REG_DIF FROM ("&L135&") A " -> SELECT 'Validação de campos' as tipologia_teste, 'lt002_instrument' AS TABELA, 'hedge_id' AS CAMPO, '2025-06-30' as ref_date, coalesce(NUM_REG_DIF, 0) AS NUM_REG_DIF FROM (SELECT count(*) AS NUM_REG_DIF FROM (SELECT instrmnt_id as instrmnt_id_as_is, concat_ws(',',sort_array(split(hedge_id, ','))) as hedge_id_as_is FROM cd_loan_tapes_bce.lt002_instrument WHERE ref_date='2025-06-30' AND nome_perimetro= 'Individual IDComb' AND segmento= 'ESTR' AND ambito= 'PM' AND entidade='00100' AND cod_visao = 1) A Inner join (SELECT instrmnt_id as instrmnt_id_to_be, concat_ws(',',sort_array(split(hedge_id, ','))) as hedge_id_to_be FROM bu_loantape_work.lt002_instrument WHERE ref_date='2025-06-30' AND nome_perimetro= 'Individual IDComb' AND segmento= 'ESTR' AND ambito= 'PM' AND entidade='00100' AND cod_visao = 1) B ON instrmnt_id_as_is = instrmnt_id_to_be WHERE coalesce(cast(hedge_id_as_is as string), '') <> coalesce(cast(hedge_id_to_be as string), '') ) A | O135: =IF(O136="",N135,N135&$O$3) -> SELECT 'Validação de campos' as tipologia_teste, 'lt002_instrument' AS TABELA, 'hedge_id' AS CAMPO, '2025-06-30' as ref_date, coalesce(NUM_REG_DIF, 0) AS NUM_REG_DIF FROM (SELECT count(*) AS NUM_REG_DIF FROM (SELECT instrmnt_id as instrmnt_id_as_is, concat_ws(',',sort_array(split(hedge_id, ','))) as hedge_id_as_is FROM cd_loan_tapes_bce.lt002_instrument WHERE ref_date='2025-06-30' AND nome_perimetro= 'Individual IDComb' AND segmento= 'ESTR' AND ambito= 'PM' AND entidade='00100' AND cod_visao = 1) A Inner join (SELECT instrmnt_id as instrmnt_id_to_be, concat_ws(',',sort_array(split(hedge_id, ','))) as hedge_id_to_be FROM bu_loantape_work.lt002_instrument WHERE ref_date='2025-06-30' AND nome_perimetro= 'Individual IDComb' AND segmento= 'ESTR' AND ambito= 'PM' AND entidade='00100' AND cod_visao = 1) B ON instrmnt_id_as_is = instrmnt_id_to_be WHERE coalesce(cast(hedge_id_as_is as string), '') <> coalesce(cast(hedge_id_to_be as string), '') ) A UNION ALL | P135: =P134+1 -> 1 | Q135: CORRER EM HIVE (LISTA)
B136: INSTRMNT | C136: =_xlfn.CONCAT(Instruções!$D$5,".",VLOOKUP(B136,Instruções!$F$5:$H$10,2,0)) -> cd_loan_tapes_bce.lt002_instrument | D136: =_xlfn.CONCAT(Instruções!$D$6,".",VLOOKUP(B136,Instruções!$F$5:$H$10,3,0)) -> bu_loantape_work.lt002_instrument | E136: intrnl_sgmnt_cat_msta | F136: =E136&"_as_is" -> intrnl_sgmnt_cat_msta_as_is | G136: =E136&"_to_be" -> intrnl_sgmnt_cat_msta_to_be | H136: =IF(VLOOKUP(B136,Instruções!$F$6:$J$10,5,0)="", "(SELECT "&VLOOKUP(B136,Instruções!$F$6:$J$10,4,0)&" as "&VLOOKUP(B136,Instruções!$F$6:$J$10,4,0)&"_as_is, concat_ws(',',sort_array(split("&E136&", ','))) as "&F136&" FROM "&C136&" WHERE "&Instruções!$D$11&") A ", "(SELECT "&VLOOKUP(B136,Instruções!$F$6:$J$10,4,0)&" as "&VLOOKUP(B136,Instruções!$F$6:$J$10,4,0)&"_as_is, "&VLOOKUP(B136,Instruções!$F$6:$J$10,5,0)&" as "&VLOOKUP(B136,Instruções!$F$6:$J$10,5,0)&"_as_is, concat_ws(',',sort_array(split("&E136&", ','))) as "&F136&" FROM "&C136&" WHERE "&Instruções!$D$11&") A ") -> (SELECT instrmnt_id as instrmnt_id_as_is, concat_ws(',',sort_array(split(intrnl_sgmnt_cat_msta, ','))) as intrnl_sgmnt_cat_msta_as_is FROM cd_loan_tapes_bce.lt002_instrument WHERE ref_date='2025-06-30' AND nome_perimetro= 'Individual IDComb' AND segmento= 'ESTR' AND ambito= 'PM' AND entidade='00100' AND cod_visao = 1) A | I136: =IF(VLOOKUP(B136,Instruções!$F$6:$J$10,5,0)="", "(SELECT "&VLOOKUP(B136,Instruções!$F$6:$J$10,4,0)&" as "&VLOOKUP(B136,Instruções!$F$6:$J$10,4,0)&"_to_be, concat_ws(',',sort_array(split("&E136&", ','))) as "&G136&" FROM "&D136&" WHERE "&Instruções!$D$11&") B ", "(SELECT "&VLOOKUP(B136,Instruções!$F$6:$J$10,4,0)&" as "&VLOOKUP(B136,Instruções!$F$6:$J$10,4,0)&"_to_be, "&VLOOKUP(B136,Instruções!$F$6:$J$10,5,0)&" as "&VLOOKUP(B136,Instruções!$F$6:$J$10,5,0)&"_to_be,"&E136&" as "&G136&" FROM "&D136&" WHERE "&Instruções!$D$11&") B ") -> (SELECT instrmnt_id as instrmnt_id_to_be, concat_ws(',',sort_array(split(intrnl_sgmnt_cat_msta, ','))) as intrnl_sgmnt_cat_msta_to_be FROM bu_loantape_work.lt002_instrument WHERE ref_date='2025-06-30' AND nome_perimetro= 'Individual IDComb' AND segmento= 'ESTR' AND ambito= 'PM' AND entidade='00100' AND cod_visao = 1) B | J136: =IF(VLOOKUP(B136,Instruções!$F$6:$J$10,5,0)="", "ON "&VLOOKUP(B136,Instruções!$F$6:$J$10,4,0)&"_as_is = "&VLOOKUP(B136,Instruções!$F$6:$J$10,4,0)&"_to_be ", "ON "&VLOOKUP(B136,Instruções!$F$6:$J$10,4,0)&"_as_is = "&VLOOKUP(B136,Instruções!$F$6:$J$10,4,0)&"_to_be AND "&VLOOKUP(B136,Instruções!$F$6:$J$10,5,0)&"_as_is = "&VLOOKUP(B136,Instruções!$F$6:$J$10,5,0)&"_to_be ") -> ON instrmnt_id_as_is = instrmnt_id_to_be | K136: ="WHERE coalesce(cast("&F136&" as string), '') <> coalesce(cast("&G136&" as string), '') " -> WHERE coalesce(cast(intrnl_sgmnt_cat_msta_as_is as string), '') <> coalesce(cast(intrnl_sgmnt_cat_msta_to_be as string), '') | L136: ="SELECT count(*) AS NUM_REG_DIF FROM "&H136&" Inner join "&I136&J136&K136 -> SELECT count(*) AS NUM_REG_DIF FROM (SELECT instrmnt_id as instrmnt_id_as_is, concat_ws(',',sort_array(split(intrnl_sgmnt_cat_msta, ','))) as intrnl_sgmnt_cat_msta_as_is FROM cd_loan_tapes_bce.lt002_instrument WHERE ref_date='2025-06-30' AND nome_perimetro= 'Individual IDComb' AND segmento= 'ESTR' AND ambito= 'PM' AND entidade='00100' AND cod_visao = 1) A Inner join (SELECT instrmnt_id as instrmnt_id_to_be, concat_ws(',',sort_array(split(intrnl_sgmnt_cat_msta, ','))) as intrnl_sgmnt_cat_msta_to_be FROM bu_loantape_work.lt002_instrument WHERE ref_date='2025-06-30' AND nome_perimetro= 'Individual IDComb' AND segmento= 'ESTR' AND ambito= 'PM' AND entidade='00100' AND cod_visao = 1) B ON instrmnt_id_as_is = instrmnt_id_to_be WHERE coalesce(cast(intrnl_sgmnt_cat_msta_as_is as string), '') <> coalesce(cast(intrnl_sgmnt_cat_msta_to_be as string), '') | M136: Validação de campos | N136: ="SELECT 'Validação de campos' as tipologia_teste, '"&VLOOKUP(B136,Instruções!$F$6:$J$10,3,0)&"' AS TABELA, '"&E136&"' AS CAMPO, '"&Instruções!$D$7&"' as ref_date, coalesce(NUM_REG_DIF, 0) AS NUM_REG_DIF FROM ("&L136&") A " -> SELECT 'Validação de campos' as tipologia_teste, 'lt002_instrument' AS TABELA, 'intrnl_sgmnt_cat_msta' AS CAMPO, '2025-06-30' as ref_date, coalesce(NUM_REG_DIF, 0) AS NUM_REG_DIF FROM (SELECT count(*) AS NUM_REG_DIF FROM (SELECT instrmnt_id as instrmnt_id_as_is, concat_ws(',',sort_array(split(intrnl_sgmnt_cat_msta, ','))) as intrnl_sgmnt_cat_msta_as_is FROM cd_loan_tapes_bce.lt002_instrument WHERE ref_date='2025-06-30' AND nome_perimetro= 'Individual IDComb' AND segmento= 'ESTR' AND ambito= 'PM' AND entidade='00100' AND cod_visao = 1) A Inner join (SELECT instrmnt_id as instrmnt_id_to_be, concat_ws(',',sort_array(split(intrnl_sgmnt_cat_msta, ','))) as intrnl_sgmnt_cat_msta_to_be FROM bu_loantape_work.lt002_instrument WHERE ref_date='2025-06-30' AND nome_perimetro= 'Individual IDComb' AND segmento= 'ESTR' AND ambito= 'PM' AND entidade='00100' AND cod_visao = 1) B ON instrmnt_id_as_is = instrmnt_id_to_be WHERE coalesce(cast(intrnl_sgmnt_cat_msta_as_is as string), '') <> coalesce(cast(intrnl_sgmnt_cat_msta_to_be as string), '') ) A | O136: =IF(O137="",N136,N136&$O$3) -> SELECT 'Validação de campos' as tipologia_teste, 'lt002_instrument' AS TABELA, 'intrnl_sgmnt_cat_msta' AS CAMPO, '2025-06-30' as ref_date, coalesce(NUM_REG_DIF, 0) AS NUM_REG_DIF FROM (SELECT count(*) AS NUM_REG_DIF FROM (SELECT instrmnt_id as instrmnt_id_as_is, concat_ws(',',sort_array(split(intrnl_sgmnt_cat_msta, ','))) as intrnl_sgmnt_cat_msta_as_is FROM cd_loan_tapes_bce.lt002_instrument WHERE ref_date='2025-06-30' AND nome_perimetro= 'Individual IDComb' AND segmento= 'ESTR' AND ambito= 'PM' AND entidade='00100' AND cod_visao = 1) A Inner join (SELECT instrmnt_id as instrmnt_id_to_be, concat_ws(',',sort_array(split(intrnl_sgmnt_cat_msta, ','))) as intrnl_sgmnt_cat_msta_to_be FROM bu_loantape_work.lt002_instrument WHERE ref_date='2025-06-30' AND nome_perimetro= 'Individual IDComb' AND segmento= 'ESTR' AND ambito= 'PM' AND entidade='00100' AND cod_visao = 1) B ON instrmnt_id_as_is = instrmnt_id_to_be WHERE coalesce(cast(intrnl_sgmnt_cat_msta_as_is as string), '') <> coalesce(cast(intrnl_sgmnt_cat_msta_to_be as string), '') ) A UNION ALL | P136: =P135+1 -> 2 | Q136: CORRER EM HIVE (LISTA)
B137: INSTRMNT | C137: =_xlfn.CONCAT(Instruções!$D$5,".",VLOOKUP(B137,Instruções!$F$5:$H$10,2,0)) -> cd_loan_tapes_bce.lt002_instrument | D137: =_xlfn.CONCAT(Instruções!$D$6,".",VLOOKUP(B137,Instruções!$F$5:$H$10,3,0)) -> bu_loantape_work.lt002_instrument | E137: intrnl_sgmnt_catgsub | F137: =E137&"_as_is" -> intrnl_sgmnt_catgsub_as_is | G137: =E137&"_to_be" -> intrnl_sgmnt_catgsub_to_be | H137: =IF(VLOOKUP(B137,Instruções!$F$6:$J$10,5,0)="", "(SELECT "&VLOOKUP(B137,Instruções!$F$6:$J$10,4,0)&" as "&VLOOKUP(B137,Instruções!$F$6:$J$10,4,0)&"_as_is, concat_ws(',',sort_array(split("&E137&", ','))) as "&F137&" FROM "&C137&" WHERE "&Instruções!$D$11&") A ", "(SELECT "&VLOOKUP(B137,Instruções!$F$6:$J$10,4,0)&" as "&VLOOKUP(B137,Instruções!$F$6:$J$10,4,0)&"_as_is, "&VLOOKUP(B137,Instruções!$F$6:$J$10,5,0)&" as "&VLOOKUP(B137,Instruções!$F$6:$J$10,5,0)&"_as_is, concat_ws(',',sort_array(split("&E137&", ','))) as "&F137&" FROM "&C137&" WHERE "&Instruções!$D$11&") A ") -> (SELECT instrmnt_id as instrmnt_id_as_is, concat_ws(',',sort_array(split(intrnl_sgmnt_catgsub, ','))) as intrnl_sgmnt_catgsub_as_is FROM cd_loan_tapes_bce.lt002_instrument WHERE ref_date='2025-06-30' AND nome_perimetro= 'Individual IDComb' AND segmento= 'ESTR' AND ambito= 'PM' AND entidade='00100' AND cod_visao = 1) A | I137: =IF(VLOOKUP(B137,Instruções!$F$6:$J$10,5,0)="", "(SELECT "&VLOOKUP(B137,Instruções!$F$6:$J$10,4,0)&" as "&VLOOKUP(B137,Instruções!$F$6:$J$10,4,0)&"_to_be, concat_ws(',',sort_array(split("&E137&", ','))) as "&G137&" FROM "&D137&" WHERE "&Instruções!$D$11&") B ", "(SELECT "&VLOOKUP(B137,Instruções!$F$6:$J$10,4,0)&" as "&VLOOKUP(B137,Instruções!$F$6:$J$10,4,0)&"_to_be, "&VLOOKUP(B137,Instruções!$F$6:$J$10,5,0)&" as "&VLOOKUP(B137,Instruções!$F$6:$J$10,5,0)&"_to_be,"&E137&" as "&G137&" FROM "&D137&" WHERE "&Instruções!$D$11&") B ") -> (SELECT instrmnt_id as instrmnt_id_to_be, concat_ws(',',sort_array(split(intrnl_sgmnt_catgsub, ','))) as intrnl_sgmnt_catgsub_to_be FROM bu_loantape_work.lt002_instrument WHERE ref_date='2025-06-30' AND nome_perimetro= 'Individual IDComb' AND segmento= 'ESTR' AND ambito= 'PM' AND entidade='00100' AND cod_visao = 1) B | J137: =IF(VLOOKUP(B137,Instruções!$F$6:$J$10,5,0)="", "ON "&VLOOKUP(B137,Instruções!$F$6:$J$10,4,0)&"_as_is = "&VLOOKUP(B137,Instruções!$F$6:$J$10,4,0)&"_to_be ", "ON "&VLOOKUP(B137,Instruções!$F$6:$J$10,4,0)&"_as_is = "&VLOOKUP(B137,Instruções!$F$6:$J$10,4,0)&"_to_be AND "&VLOOKUP(B137,Instruções!$F$6:$J$10,5,0)&"_as_is = "&VLOOKUP(B137,Instruções!$F$6:$J$10,5,0)&"_to_be ") -> ON instrmnt_id_as_is = instrmnt_id_to_be | K137: ="WHERE coalesce(cast("&F137&" as string), '') <> coalesce(cast("&G137&" as string), '') " -> WHERE coalesce(cast(intrnl_sgmnt_catgsub_as_is as string), '') <> coalesce(cast(intrnl_sgmnt_catgsub_to_be as string), '') | L137: ="SELECT count(*) AS NUM_REG_DIF FROM "&H137&" Inner join "&I137&J137&K137 -> SELECT count(*) AS NUM_REG_DIF FROM (SELECT instrmnt_id as instrmnt_id_as_is, concat_ws(',',sort_array(split(intrnl_sgmnt_catgsub, ','))) as intrnl_sgmnt_catgsub_as_is FROM cd_loan_tapes_bce.lt002_instrument WHERE ref_date='2025-06-30' AND nome_perimetro= 'Individual IDComb' AND segmento= 'ESTR' AND ambito= 'PM' AND entidade='00100' AND cod_visao = 1) A Inner join (SELECT instrmnt_id as instrmnt_id_to_be, concat_ws(',',sort_array(split(intrnl_sgmnt_catgsub, ','))) as intrnl_sgmnt_catgsub_to_be FROM bu_loantape_work.lt002_instrument WHERE ref_date='2025-06-30' AND nome_perimetro= 'Individual IDComb' AND segmento= 'ESTR' AND ambito= 'PM' AND entidade='00100' AND cod_visao = 1) B ON instrmnt_id_as_is = instrmnt_id_to_be WHERE coalesce(cast(intrnl_sgmnt_catgsub_as_is as string), '') <> coalesce(cast(intrnl_sgmnt_catgsub_to_be as string), '') | M137: Validação de campos | N137: ="SELECT 'Validação de campos' as tipologia_teste, '"&VLOOKUP(B137,Instruções!$F$6:$J$10,3,0)&"' AS TABELA, '"&E137&"' AS CAMPO, '"&Instruções!$D$7&"' as ref_date, coalesce(NUM_REG_DIF, 0) AS NUM_REG_DIF FROM ("&L137&") A " -> SELECT 'Validação de campos' as tipologia_teste, 'lt002_instrument' AS TABELA, 'intrnl_sgmnt_catgsub' AS CAMPO, '2025-06-30' as ref_date, coalesce(NUM_REG_DIF, 0) AS NUM_REG_DIF FROM (SELECT count(*) AS NUM_REG_DIF FROM (SELECT instrmnt_id as instrmnt_id_as_is, concat_ws(',',sort_array(split(intrnl_sgmnt_catgsub, ','))) as intrnl_sgmnt_catgsub_as_is FROM cd_loan_tapes_bce.lt002_instrument WHERE ref_date='2025-06-30' AND nome_perimetro= 'Individual IDComb' AND segmento= 'ESTR' AND ambito= 'PM' AND entidade='00100' AND cod_visao = 1) A Inner join (SELECT instrmnt_id as instrmnt_id_to_be, concat_ws(',',sort_array(split(intrnl_sgmnt_catgsub, ','))) as intrnl_sgmnt_catgsub_to_be FROM bu_loantape_work.lt002_instrument WHERE ref_date='2025-06-30' AND nome_perimetro= 'Individual IDComb' AND segmento= 'ESTR' AND ambito= 'PM' AND entidade='00100' AND cod_visao = 1) B ON instrmnt_id_as_is = instrmnt_id_to_be WHERE coalesce(cast(intrnl_sgmnt_catgsub_as_is as string), '') <> coalesce(cast(intrnl_sgmnt_catgsub_to_be as string), '') ) A | O137: =IF(O138="",N137,N137&$O$3) -> SELECT 'Validação de campos' as tipologia_teste, 'lt002_instrument' AS TABELA, 'intrnl_sgmnt_catgsub' AS CAMPO, '2025-06-30' as ref_date, coalesce(NUM_REG_DIF, 0) AS NUM_REG_DIF FROM (SELECT count(*) AS NUM_REG_DIF FROM (SELECT instrmnt_id as instrmnt_id_as_is, concat_ws(',',sort_array(split(intrnl_sgmnt_catgsub, ','))) as intrnl_sgmnt_catgsub_as_is FROM cd_loan_tapes_bce.lt002_instrument WHERE ref_date='2025-06-30' AND nome_perimetro= 'Individual IDComb' AND segmento= 'ESTR' AND ambito= 'PM' AND entidade='00100' AND cod_visao = 1) A Inner join (SELECT instrmnt_id as instrmnt_id_to_be, concat_ws(',',sort_array(split(intrnl_sgmnt_catgsub, ','))) as intrnl_sgmnt_catgsub_to_be FROM bu_loantape_work.lt002_instrument WHERE ref_date='2025-06-30' AND nome_perimetro= 'Individual IDComb' AND segmento= 'ESTR' AND ambito= 'PM' AND entidade='00100' AND cod_visao = 1) B ON instrmnt_id_as_is = instrmnt_id_to_be WHERE coalesce(cast(intrnl_sgmnt_catgsub_as_is as string), '') <> coalesce(cast(intrnl_sgmnt_catgsub_to_be as string), '') ) A UNION ALL | P137: =P136+1 -> 3 | Q137: CORRER EM HIVE (LISTA)
B138: INSTRMNT | C138: =_xlfn.CONCAT(Instruções!$D$5,".",VLOOKUP(B138,Instruções!$F$5:$H$10,2,0)) -> cd_loan_tapes_bce.lt002_instrument | D138: =_xlfn.CONCAT(Instruções!$D$6,".",VLOOKUP(B138,Instruções!$F$5:$H$10,3,0)) -> bu_loantape_work.lt002_instrument | E138: cntrct_id_bdr | F138: =E138&"_as_is" -> cntrct_id_bdr_as_is | G138: =E138&"_to_be" -> cntrct_id_bdr_to_be | H138: =IF(VLOOKUP(B138,Instruções!$F$6:$J$10,5,0)="", "(SELECT "&VLOOKUP(B138,Instruções!$F$6:$J$10,4,0)&" as "&VLOOKUP(B138,Instruções!$F$6:$J$10,4,0)&"_as_is, concat_ws(',',sort_array(split("&E138&", ','))) as "&F138&" FROM "&C138&" WHERE "&Instruções!$D$11&") A ", "(SELECT "&VLOOKUP(B138,Instruções!$F$6:$J$10,4,0)&" as "&VLOOKUP(B138,Instruções!$F$6:$J$10,4,0)&"_as_is, "&VLOOKUP(B138,Instruções!$F$6:$J$10,5,0)&" as "&VLOOKUP(B138,Instruções!$F$6:$J$10,5,0)&"_as_is, concat_ws(',',sort_array(split("&E138&", ','))) as "&F138&" FROM "&C138&" WHERE "&Instruções!$D$11&") A ") -> (SELECT instrmnt_id as instrmnt_id_as_is, concat_ws(',',sort_array(split(cntrct_id_bdr, ','))) as cntrct_id_bdr_as_is FROM cd_loan_tapes_bce.lt002_instrument WHERE ref_date='2025-06-30' AND nome_perimetro= 'Individual IDComb' AND segmento= 'ESTR' AND ambito= 'PM' AND entidade='00100' AND cod_visao = 1) A | I138: =IF(VLOOKUP(B138,Instruções!$F$6:$J$10,5,0)="", "(SELECT "&VLOOKUP(B138,Instruções!$F$6:$J$10,4,0)&" as "&VLOOKUP(B138,Instruções!$F$6:$J$10,4,0)&"_to_be, concat_ws(',',sort_array(split("&E138&", ','))) as "&G138&" FROM "&D138&" WHERE "&Instruções!$D$11&") B ", "(SELECT "&VLOOKUP(B138,Instruções!$F$6:$J$10,4,0)&" as "&VLOOKUP(B138,Instruções!$F$6:$J$10,4,0)&"_to_be, "&VLOOKUP(B138,Instruções!$F$6:$J$10,5,0)&" as "&VLOOKUP(B138,Instruções!$F$6:$J$10,5,0)&"_to_be,"&E138&" as "&G138&" FROM "&D138&" WHERE "&Instruções!$D$11&") B ") -> (SELECT instrmnt_id as instrmnt_id_to_be, concat_ws(',',sort_array(split(cntrct_id_bdr, ','))) as cntrct_id_bdr_to_be FROM bu_loantape_work.lt002_instrument WHERE ref_date='2025-06-30' AND nome_perimetro= 'Individual IDComb' AND segmento= 'ESTR' AND ambito= 'PM' AND entidade='00100' AND cod_visao = 1) B | J138: =IF(VLOOKUP(B138,Instruções!$F$6:$J$10,5,0)="", "ON "&VLOOKUP(B138,Instruções!$F$6:$J$10,4,0)&"_as_is = "&VLOOKUP(B138,Instruções!$F$6:$J$10,4,0)&"_to_be ", "ON "&VLOOKUP(B138,Instruções!$F$6:$J$10,4,0)&"_as_is = "&VLOOKUP(B138,Instruções!$F$6:$J$10,4,0)&"_to_be AND "&VLOOKUP(B138,Instruções!$F$6:$J$10,5,0)&"_as_is = "&VLOOKUP(B138,Instruções!$F$6:$J$10,5,0)&"_to_be ") -> ON instrmnt_id_as_is = instrmnt_id_to_be | K138: ="WHERE coalesce(cast("&F138&" as string), '') <> coalesce(cast("&G138&" as string), '') " -> WHERE coalesce(cast(cntrct_id_bdr_as_is as string), '') <> coalesce(cast(cntrct_id_bdr_to_be as string), '') | L138: ="SELECT count(*) AS NUM_REG_DIF FROM "&H138&" Inner join "&I138&J138&K138 -> SELECT count(*) AS NUM_REG_DIF FROM (SELECT instrmnt_id as instrmnt_id_as_is, concat_ws(',',sort_array(split(cntrct_id_bdr, ','))) as cntrct_id_bdr_as_is FROM cd_loan_tapes_bce.lt002_instrument WHERE ref_date='2025-06-30' AND nome_perimetro= 'Individual IDComb' AND segmento= 'ESTR' AND ambito= 'PM' AND entidade='00100' AND cod_visao = 1) A Inner join (SELECT instrmnt_id as instrmnt_id_to_be, concat_ws(',',sort_array(split(cntrct_id_bdr, ','))) as cntrct_id_bdr_to_be FROM bu_loantape_work.lt002_instrument WHERE ref_date='2025-06-30' AND nome_perimetro= 'Individual IDComb' AND segmento= 'ESTR' AND ambito= 'PM' AND entidade='00100' AND cod_visao = 1) B ON instrmnt_id_as_is = instrmnt_id_to_be WHERE coalesce(cast(cntrct_id_bdr_as_is as string), '') <> coalesce(cast(cntrct_id_bdr_to_be as string), '') | M138: Validação de campos | N138: ="SELECT 'Validação de campos' as tipologia_teste, '"&VLOOKUP(B138,Instruções!$F$6:$J$10,3,0)&"' AS TABELA, '"&E138&"' AS CAMPO, '"&Instruções!$D$7&"' as ref_date, coalesce(NUM_REG_DIF, 0) AS NUM_REG_DIF FROM ("&L138&") A " -> SELECT 'Validação de campos' as tipologia_teste, 'lt002_instrument' AS TABELA, 'cntrct_id_bdr' AS CAMPO, '2025-06-30' as ref_date, coalesce(NUM_REG_DIF, 0) AS NUM_REG_DIF FROM (SELECT count(*) AS NUM_REG_DIF FROM (SELECT instrmnt_id as instrmnt_id_as_is, concat_ws(',',sort_array(split(cntrct_id_bdr, ','))) as cntrct_id_bdr_as_is FROM cd_loan_tapes_bce.lt002_instrument WHERE ref_date='2025-06-30' AND nome_perimetro= 'Individual IDComb' AND segmento= 'ESTR' AND ambito= 'PM' AND entidade='00100' AND cod_visao = 1) A Inner join (SELECT instrmnt_id as instrmnt_id_to_be, concat_ws(',',sort_array(split(cntrct_id_bdr, ','))) as cntrct_id_bdr_to_be FROM bu_loantape_work.lt002_instrument WHERE ref_date='2025-06-30' AND nome_perimetro= 'Individual IDComb' AND segmento= 'ESTR' AND ambito= 'PM' AND entidade='00100' AND cod_visao = 1) B ON instrmnt_id_as_is = instrmnt_id_to_be WHERE coalesce(cast(cntrct_id_bdr_as_is as string), '') <> coalesce(cast(cntrct_id_bdr_to_be as string), '') ) A | O138: =IF(O139="",N138,N138&$O$3) -> SELECT 'Validação de campos' as tipologia_teste, 'lt002_instrument' AS TABELA, 'cntrct_id_bdr' AS CAMPO, '2025-06-30' as ref_date, coalesce(NUM_REG_DIF, 0) AS NUM_REG_DIF FROM (SELECT count(*) AS NUM_REG_DIF FROM (SELECT instrmnt_id as instrmnt_id_as_is, concat_ws(',',sort_array(split(cntrct_id_bdr, ','))) as cntrct_id_bdr_as_is FROM cd_loan_tapes_bce.lt002_instrument WHERE ref_date='2025-06-30' AND nome_perimetro= 'Individual IDComb' AND segmento= 'ESTR' AND ambito= 'PM' AND entidade='00100' AND cod_visao = 1) A Inner join (SELECT instrmnt_id as instrmnt_id_to_be, concat_ws(',',sort_array(split(cntrct_id_bdr, ','))) as cntrct_id_bdr_to_be FROM bu_loantape_work.lt002_instrument WHERE ref_date='2025-06-30' AND nome_perimetro= 'Individual IDComb' AND segmento= 'ESTR' AND ambito= 'PM' AND entidade='00100' AND cod_visao = 1) B ON instrmnt_id_as_is = instrmnt_id_to_be WHERE coalesce(cast(cntrct_id_bdr_as_is as string), '') <> coalesce(cast(cntrct_id_bdr_to_be as string), '') ) A | P138: =P137+1 -> 4 | Q138: CORRER EM HIVE (LISTA)
B140: INSTRMNT | C140: =_xlfn.CONCAT(Instruções!$D$5,".",VLOOKUP(B140,Instruções!$F$5:$H$10,2,0)) -> cd_loan_tapes_bce.lt002_instrument | D140: =_xlfn.CONCAT(Instruções!$D$6,".",VLOOKUP(B140,Instruções!$F$5:$H$10,3,0)) -> bu_loantape_work.lt002_instrument | E140: cod_soc | F140: =E140&"_as_is" -> cod_soc_as_is | G140: =E140&"_to_be" -> cod_soc_to_be | H140: =IF(VLOOKUP(B140,Instruções!$F$6:$J$10,5,0)="", "(SELECT "&VLOOKUP(B140,Instruções!$F$6:$J$10,4,0)&" as "&VLOOKUP(B140,Instruções!$F$6:$J$10,4,0)&"_as_is, "&E140&" as "&F140&" FROM "&C140&" WHERE "&Instruções!$D$11&") A ", "(SELECT "&VLOOKUP(B140,Instruções!$F$6:$J$10,4,0)&" as "&VLOOKUP(B140,Instruções!$F$6:$J$10,4,0)&"_as_is, "&VLOOKUP(B140,Instruções!$F$6:$J$10,5,0)&" as "&VLOOKUP(B140,Instruções!$F$6:$J$10,5,0)&"_as_is,"&E140&" as "&F140&" FROM "&C140&" WHERE "&Instruções!$D$11&") A ") -> (SELECT instrmnt_id as instrmnt_id_as_is, cod_soc as cod_soc_as_is FROM cd_loan_tapes_bce.lt002_instrument WHERE ref_date='2025-06-30' AND nome_perimetro= 'Individual IDComb' AND segmento= 'ESTR' AND ambito= 'PM' AND entidade='00100' AND cod_visao = 1) A | I140: =IF(VLOOKUP(B140,Instruções!$F$6:$J$10,5,0)="", "(SELECT "&VLOOKUP(B140,Instruções!$F$6:$J$10,4,0)&" as "&VLOOKUP(B140,Instruções!$F$6:$J$10,4,0)&"_to_be, "&E140&" as "&G140&" FROM "&D140&" WHERE "&Instruções!$D$11&") B ", "(SELECT "&VLOOKUP(B140,Instruções!$F$6:$J$10,4,0)&" as "&VLOOKUP(B140,Instruções!$F$6:$J$10,4,0)&"_to_be, "&VLOOKUP(B140,Instruções!$F$6:$J$10,5,0)&" as "&VLOOKUP(B140,Instruções!$F$6:$J$10,5,0)&"_to_be,"&E140&" as "&G140&" FROM "&D140&" WHERE "&Instruções!$D$11&") B ") -> (SELECT instrmnt_id as instrmnt_id_to_be, cod_soc as cod_soc_to_be FROM bu_loantape_work.lt002_instrument WHERE ref_date='2025-06-30' AND nome_perimetro= 'Individual IDComb' AND segmento= 'ESTR' AND ambito= 'PM' AND entidade='00100' AND cod_visao = 1) B | J140: =IF(VLOOKUP(B140,Instruções!$F$6:$J$10,5,0)="", "ON "&VLOOKUP(B140,Instruções!$F$6:$J$10,4,0)&"_as_is = "&VLOOKUP(B140,Instruções!$F$6:$J$10,4,0)&"_to_be ", "ON "&VLOOKUP(B140,Instruções!$F$6:$J$10,4,0)&"_as_is = "&VLOOKUP(B140,Instruções!$F$6:$J$10,4,0)&"_to_be AND "&VLOOKUP(B140,Instruções!$F$6:$J$10,5,0)&"_as_is = "&VLOOKUP(B140,Instruções!$F$6:$J$10,5,0)&"_to_be ") -> ON instrmnt_id_as_is = instrmnt_id_to_be | K140: ="WHERE coalesce(cast("&F140&" as string), '') <> coalesce(cast("&G140&" as string), '') " -> WHERE coalesce(cast(cod_soc_as_is as string), '') <> coalesce(cast(cod_soc_to_be as string), '') | L140: ="SELECT count(*) AS NUM_REG_DIF FROM "&H140&" Inner join "&I140&J140&K140 -> SELECT count(*) AS NUM_REG_DIF FROM (SELECT instrmnt_id as instrmnt_id_as_is, cod_soc as cod_soc_as_is FROM cd_loan_tapes_bce.lt002_instrument WHERE ref_date='2025-06-30' AND nome_perimetro= 'Individual IDComb' AND segmento= 'ESTR' AND ambito= 'PM' AND entidade='00100' AND cod_visao = 1) A Inner join (SELECT instrmnt_id as instrmnt_id_to_be, cod_soc as cod_soc_to_be FROM bu_loantape_work.lt002_instrument WHERE ref_date='2025-06-30' AND nome_perimetro= 'Individual IDComb' AND segmento= 'ESTR' AND ambito= 'PM' AND entidade='00100' AND cod_visao = 1) B ON instrmnt_id_as_is = instrmnt_id_to_be WHERE coalesce(cast(cod_soc_as_is as string), '') <> coalesce(cast(cod_soc_to_be as string), '') | M140: Validação de campos | N140: ="SELECT 'Validação de campos' as tipologia_teste, '"&VLOOKUP(B140,Instruções!$F$6:$J$10,3,0)&"' AS TABELA, '"&E140&"' AS CAMPO, '"&Instruções!$D$7&"' as ref_date, coalesce(NUM_REG_DIF, 0) AS NUM_REG_DIF FROM ("&L140&") A " -> SELECT 'Validação de campos' as tipologia_teste, 'lt002_instrument' AS TABELA, 'cod_soc' AS CAMPO, '2025-06-30' as ref_date, coalesce(NUM_REG_DIF, 0) AS NUM_REG_DIF FROM (SELECT count(*) AS NUM_REG_DIF FROM (SELECT instrmnt_id as instrmnt_id_as_is, cod_soc as cod_soc_as_is FROM cd_loan_tapes_bce.lt002_instrument WHERE ref_date='2025-06-30' AND nome_perimetro= 'Individual IDComb' AND segmento= 'ESTR' AND ambito= 'PM' AND entidade='00100' AND cod_visao = 1) A Inner join (SELECT instrmnt_id as instrmnt_id_to_be, cod_soc as cod_soc_to_be FROM bu_loantape_work.lt002_instrument WHERE ref_date='2025-06-30' AND nome_perimetro= 'Individual IDComb' AND segmento= 'ESTR' AND ambito= 'PM' AND entidade='00100' AND cod_visao = 1) B ON instrmnt_id_as_is = instrmnt_id_to_be WHERE coalesce(cast(cod_soc_as_is as string), '') <> coalesce(cast(cod_soc_to_be as string), '') ) A | O140: =IF(O141="",N140,N140&$O$3) -> SELECT 'Validação de campos' as tipologia_teste, 'lt002_instrument' AS TABELA, 'cod_soc' AS CAMPO, '2025-06-30' as ref_date, coalesce(NUM_REG_DIF, 0) AS NUM_REG_DIF FROM (SELECT count(*) AS NUM_REG_DIF FROM (SELECT instrmnt_id as instrmnt_id_as_is, cod_soc as cod_soc_as_is FROM cd_loan_tapes_bce.lt002_instrument WHERE ref_date='2025-06-30' AND nome_perimetro= 'Individual IDComb' AND segmento= 'ESTR' AND ambito= 'PM' AND entidade='00100' AND cod_visao = 1) A Inner join (SELECT instrmnt_id as instrmnt_id_to_be, cod_soc as cod_soc_to_be FROM bu_loantape_work.lt002_instrument WHERE ref_date='2025-06-30' AND nome_perimetro= 'Individual IDComb' AND segmento= 'ESTR' AND ambito= 'PM' AND entidade='00100' AND cod_visao = 1) B ON instrmnt_id_as_is = instrmnt_id_to_be WHERE coalesce(cast(cod_soc_as_is as string), '') <> coalesce(cast(cod_soc_to_be as string), '') ) A UNION ALL | P140: =P139+1 -> 1
