Workbook

Sheet Filtros dos Segmentos
A1: • Exposures to legal persons: tipo_conta='A' e instrumento_financeiro='credito concedido e outros ativos financeiros' e contraparte <> ‘particulares’ e contraparte_i <> ‘particulares’ e carteira_contabilistica <> 'ativos nao correntes detidos para venda' • Exposures to natural persons: tipo_conta='A' e instrumento_financeiro='credito concedido e outros ativos financeiros' e contraparte = ‘particulares’ e contraparte_i = ‘particulares’ e carteira_contabilistica <> 'ativos nao correntes detidos para venda' • Off-balance sheet exposures: tipo_conta='EA' • Derivatives: instrumento_financeiro='derivados’ e tipo_conta in ('A', 'P') • Debt securities: tipo_conta='A' e instrumento_financeiro='instrumentos de divida' • Equity: tipo_conta='A' e instrumento_financeiro='instrumentos de capital' e carteira_contabilistica <> 'ativos nao correntes detidos para venda'

Sheet LEGAL PERSONS DATA SETS
A1: SRB DATA SET FOR EXPOSURES TO LEGAL PERSONS The AnaCredit database provides very detailed and individual information concerning exposures to legal persons. The SRB Valuation Data Set complements the AnaCredit database and provides data fields on segments, which allows mapping individual exposures with prudential reporting segments (FINREP and COREP), and credit risk data parameters aimed at supporting valuers. The SRB Valuation Data Set also provides data fields on risk parameters provided by banks’ internal risk models, which valuers are able to rely on in order to perform valuations on an aggregated basis, where necessary. Serão produzidos cinco ficheiros de report referentes a Legal Persons: ‣ SRB Instruments Data Set for exposures to legal persons (LEGALP_INSTRUMENTS); ‣ SRB Counterparties Data Set for exposures to legal persons (LEGALP_COUNTERPARTIES); ‣ SRB Protection received Data Set for exposures to legal persons (LEGALP_PROTECTIONS); ‣ SRB Instrument/Counterparty mapping Data Set for exposures to legal persons (LEGALP_INSTRUMENT_COUNTERPARTY); ‣ SRB Instrument/Protection mapping Data Set for exposures to legal persons (LEGALP_INSTRUMENT_PROTECTION);
A2: SRB DATA SET FOR EXPOSURES TO LEGAL PERSONS A base de dados AnaCredit disponibiliza informação muito detalhada e individualizada sobre exposições a pessoas coletivas. O dataset de avaliação do SRB complementa a base de dados AnaCredit e fornece campos de dados por segmentos, o que permite mapear exposições individuais com segmentos de reporte prudencial (FINREP e COREP) e parâmetros de dados de risco de crédito destinados a apoiar os avaliadores. O dataset de avaliação do CUR também fornece campos de dados sobre parâmetros de risco fornecidos pelos modelos de risco internos dos bancos, nos quais os avaliadores podem confiar para realizar avaliações numa base agregada, sempre que necessário. Serão produzidos três ficheiros de report referentes a Legal Persons: ‣ SRB Instruments Data Set for exposures to legal persons (VDS_OUT_LEGALP_INSTRUMENTS); ‣ SRB Counterparties Data Set for exposures to legal persons (VDS_OUT_LEGALP_COUNTERPARTIES); ‣ SRB Protection received Data Set for exposures to legal persons (VDS_OUT_LEGALP_PROTECTIONS).

Sheet LEGALP_INSTRUMENTS
A1: Instruções SRB | G1: Mapeamento efetuado pela Corporação e respetiva Descrição Loan Tape (LT) | K1: Análise IT
A2: ID | B2: Categoria | C2: Coluna | D2: Tipo de dados | E2: Descrição | G2: Mapeamentos Corporação (LT) | H2: Descrição (LT) | I2: Additional Guidance (LT) | K2: Novo campo na tabela LT002? | L2: Nome do campo no ficheiro | M2: Mapeamento | N2: Notas
A3: V_1 | B3: Identification information | C3: Instrument Identifier | D3: Alphanumeric | E3: An identifier applied to uniquely identify each instrument. Each instrument must have one instrument identifier | G3: INSTRUMENT-INSTRMNT_ID | H3: Instrument ID | I3: An identifier applied by the reporting agent to uniquely identify each instrument under a single contract. Each instrument must have one instrument identifier. This value will not change over time and cannot be used as the instrument identifier for any other instrument under the same contract. Supervised Insitutions are asked to furnish the INSTRMNT_ID with the exact same value as it is reported to AnaCredit (or any similar central credit register). If this is not available, the value shall be reported as it is internally used. If an instrument is not reported to AnaCredit but requested for the purposes of the on-site inspection please provide the bank-internally used value. | K3: NÃO | L3: instrument_id | M3: LT002_INSTRUMENT.INSTRMNT_ID
A7: V_2 | B7: Identification information | C7: Counterparty Identifier | D7: Alphanumeric | E7: Identifier applied to uniquely identify each counterparty. | G7: Not applicable: To be reported as "N/A". This information will be availabe in "01_04_leg_instr_count" table | H7: - | I7: - | K7: SIM | L7: counterparty_id | M7: Reportar sempre: 'N/A'
A8: V_3 | B8: Exposure class | C8: CRR Exposure class | D8: String | E8: The exposures classes for the calculation of risk-weighted assets (RWAs) for credit risks are as follows (not applicable when exposures are classified in the CRR trading book as defined in Article 4(1)(86) of Regulation (EU) No 575/2013): Where a bank uses the standardised approach: ‣ Central governments or central banks (SCENGOV) ‣ Regional governments or local authorities (SREGGOV) ‣ Public sector entities (SPUBSEC) ‣ Multilateral development banks (SDEVBAN) ‣ International organisation (SINTORG) ‣ Institutions (SINSTIT) ‣ Corporates (SCORPOR) ‣ Retail (SRETAIL) ‣ Secured by mortgages and immovable property (SSECMOR) ‣ Defaulted (SDEFAUL) ‣ High risk (SHIGHRI) ‣ Covered bonds (SCOVBON) ‣ Items representing securitisation positions ‣ Institutions and corporates with a short term credit assessment (SSHOTER) ‣ Collective investment undertakings (SCOLINV) ‣ Equity (SEQUITY) ‣ Other (SOTHERI) Where a bank uses the IRB approach: ‣ Central governments and central banks (ICENGOV) ‣ Institutions (IINSTIT) ‣ Corporates (ICORPOR) ‣ Retail (IRETAIL) ‣ Equity (IEQUITY) ‣ Items representing securitisation positions ‣ Other non-credit-obligation assets (IOTHERC) | G8: - | H8: - | I8: - | K8: SIM | L8: crr_exposure_class | M8: ‣ Utilizar o campo "segmento_corep_final" da tabela ct013_rwa_princ; Nota: Os códigos "segmento_corep_final" seguem sempre a mesma estrutura, começam com um caracter que identifica se é IRB (I_...) ou Standard (S_...) e de seguida um numérico (ex. I_3.1, I_5.1, S_1.0). ‣ Para o mesmo contrato este campo pode retornar vários códigos "segmento_corep_final" distintos, de seguida estão os passos que permitem resolver esta ambiguidade: 1. Deve seguir a lógica do campo RWA_MTHD, de momento a lógica é, se existir IRB e Standard então trazer informação relativa a IRB; 2. Se mesmo aplicando o passo 1 ainda existirem vários códigos "segmento_corep_final" distintos (vários códigos IRB ou vários códigos Standard) então: recuperar o código "segmento_corep_final" com o menor numérico associado. ‣ Traduzir o campo "segmento_corep_final" seguindo a parametrização apresentada na sheet 'LT831' filtrando por tabela_conceito = 'LT002_INSTRUMENT' e campo_conceito = 'CRR_EXPOSURE_CLASS' Exemplo: O contrato A tem associados os seguintes códigos "segmento_corep_final" distintos: I_3.1, I_5.1, S_1.0: 1. Remover o Standard: I_3.1, I_5.1; 2. Ficar com o menor numérico: I_3.1.
A11: V_4 | B11: Exposure class | C11: FINREP Exposure class | D11: String | E11: Classification of the facility (exposure class) as defined in ITS 680/2014 Annex V Instructions FINREP (Counterparty breakdown). Options: ‣ Central banks ‣ Central governments ‣ Credit institutions ‣ Other financial corporations ‣ Non-financial corporations ‣ Households | G11: - | H11: - | I11: - | K11: NÃO | L11: finrep_exposure_class | M11: LT002_INSTRUMENT.INTRNL_SGMNT ‣ Traduzir o campo "INTRNL_SGMNT" seguindo as parametrizações apresentadas nas sheets: ‣ LT829 - filtrando por campo_conceito = 'INTRNL_SGMNT' e regra_conversao = '1'; ‣ LT830 - filtrando por segmento = 'Exposures to legal persons' e campo_conceito = 'INTRNL_SGMNT'.
A18: V_5 | B18: Risk parameters | C18: Total Risk Exposure Amount | D18: Numeric (euro) | E18: The total risk exposure amount of the instrument, calculated according to Articles 92(3) and 92(4) of Regulation (EU) No 575/2013 (CRR), where applicable. | G18: INSTRUMENT-RWA | H18: RWA | I18: RWA according to Regulation (EU) No 575/2013. | K18: NÃO | L18: total_risk_exposure_amount | M18: LT002_INSTRUMENT.RWA
A21: V_6 | B21: Risk parameters | C21: CRR Loss given default | D21: Numeric. Basis points | E21: Current level of the ‘Loss given default’ of the loan, determined in accordance with Articles 161, 164, 179 and 181 of Regulation (EU) No 575/2013. | G21: INSTRUMENT-LGD | H21: Regulatory LGD | I21: If differences between regulatory and internal LGD exist, use regulatory LGD (according to Regulation (EU) No 575/2013). In particular, in IRB-F use regulatory LGD values. | K21: NÃO | L21: crr_loss_given_default | M21: LT002_INSTRUMENT.LGD
A25: V_7 | B25: Risk parameters | C25: IFRS 9 Loss given default | D25: Numeric. Basis points | E25: Current level of the ‘Loss given default’ of the loan determined for accounting purposes. | G25: INSTRUMENT-IFRS9_LGD | H25: IFRS 9 accounting LGD | I25: IFRS 9 accounting Loss Given Default as at reference date for defaulted and non-defaulted exposures. In case the bank models time-depended LGD variable for non-defaulted exposures then 12-month LGD as at reference date regardless the classification as Stage 1 or 2 | K25: NÃO | L25: ifrs9_loss_given_default | M25: LT002_INSTRUMENT.IFRS9_LGD

Sheet LEGALP_COUNTERPARTIES
A1: Instruções SRB | G1: Mapeamento efetuado pela Corporação e respetiva Descrição Loan Tape (LT) | K1: Análise IT
A2: ID | B2: Categoria | C2: Coluna | D2: Tipo de dados | E2: Descrição | G2: Mapeamentos Corporação (LT) | H2: Descrição (LT) | I2: Additional Guidance (LT) | K2: Novo campo na tabela LT003? | L2: Nome do campo no ficheiro | M2: Mapeamento | N2: Notas
A3: V_2 | B3: Identification information | C3: Counterparty Identifier | D3: Alphanumeric | E3: Identifier applied to uniquely identify each counterparty. | G3: ENTITY-ENTTY_ID | H3: Entity ID | I3: An identifier applied by the reporting agent to uniquely identify each counterparty. Each counterparty has a unique and exclusive counterparty identifier. This means that this value will not change over time and can never be used as the counterparty identifier for any other counterparty. | K3: NÃO | L3: counterparty_id | M3: LT003_ENTITY.ENTTY_ID
A4: V_8 | B4: Risk parameters | C4: Current Internal Credit Rating/Scoring | D4: Numeric / alphanumeric | E4: Internal credit rating/scoring issued to the counterparty. | G4: ENTITY-INTRNL_RTNG | H4: Internal rating at reference date | I4: Internal rating at the reference date according to Regulation (EU) No 575/2013. Please also add in sheet "Code List" the list of values used, i.e. bank-internal masterscale. | K4: NÃO | L4: internal_credit_rating | M4: LT003_ENTITY.INTRNL_RTNG
A5: V_9 | B5: Risk parameters | C5: External Credit rating | D5: Alphanumeric | E5: External credit rating issued to the counterparty at cut-off date. In case several ratings are assigned, the approach described in Art. 138 of the CRR applies. | G5: ENTITY-EXTRNL_RTNG | H5: External rating | I5: External rating at the reference date. | K5: NÃO | L5: external_credit_rating | M5: LT003_ENTITY.EXTRNL_RTNG
A6: V_10 | B6: Risk parameters | C6: IFRS 9 Probability of default/impairment | D6: Numeric. Basis points | E6: The probability of default/impairment is calculated in accordance with the requirements specific to probability of default (PD) estimation as laid down in the accounting framework. If PDs are produced at the instrument level only, the counterparty’s PD is to be reported as the exposure-weighted average PD across the PDs of all instruments of the counterparty. If, for a given counterparty, PDs are estimated for both the counterparty and (some of) the products of the counterparty, it is the counterparty’s PD which is to be reported. No documento "Feedback Statement in response to the consultation on the SRB valuation data set" é referida a seguinte nota sobre este campo: "‘Data Point V_10’, entitled ‘IFRS 9 Probability of default’, refers to PDs used for accounting purposes, being a 12-month PD for stage 1 exposures and a lifetime PD for stage 2 and 3 exposures as per the accounting framework." | G6: ENTITY-PD_IFRS9_12M_RD | H6: 12-month PD at reporting date according to IFRS 9 | I6: 12-month PD at reference date which is used by the bank for computation of stage 1 ECL or for SICR assessment if bank use 12 month proxy for staging. If the PD is calculated on instruments level please provide an EAD weighted average. | K6: SIM | L6: ifrs9_prob_default_impairment | M6: Necessário validar a necessidade de criar um novo campo ("PD misto" ) na LT002_INSTRUMENT dado que se solicita um "misto" entre a PD 12m (PD12M_IFRS9) e a PD lifetime (PD_LT_IFRS9), campos já existentes nessa tabela. A lógica a validar será: -Se stage 1: Se loss_type LIKE 'Lifetime expected credit losses%' selecionar PD_LT_IFRS9 da tabela BU_IFRS9.IFRS9_OUT_EXPECTED_LOSS_REPORTING, caso contrário selecionar PD12M_IFRS9 da tabela BU_IFRS9.IFRS9_OUT_EXPECTED_LOSS_REPORTING -Se stage 2: selecionar PD_LT_IFRS9 da tabela BU_IFRS9.IFRS9_OUT_EXPECTED_LOSS_REPORTING -Se stage 3: forçar 1 Sugere-se criar o campo na LT002_INSTRUMENT e não na LT003_ENTITY porque após consultar a a LT003_ENTITY verificou-se que existia o campo PD_IFRS9_12M_RD para o qual é usada a LT005_INSTR_ENT para identificar todos os contratos onde o cliente é o 1º Titular, de seguida para cada cliente aplica-se uma média ponderada da PD em relação ao EAD (porque cada cliente pode ter vários contratos). Assim sugere-se replicar esta lógica para o novo campo "PD misto" adicionado na LT002_INSTRUMENT de forma a poder ser criado também um novo campo "PD misto" na LT003_ENTITY. Lógica proposta para a criação do novo campo na LT002: CASE WHEN IMPRMNT_STTS_INSTRMNT = '23' --(Stage 1) THEN IF( loss_type LIKE 'Lifetime expected credit losses%', PD_LT_IFRS9, PD12M_IFRS9) WHEN IMPRMNT_STTS_INSTRMNT = '24' --(Stage 2) THEN PD_LT_IFRS9 WHEN IMPRMNT_STTS_INSTRMNT = '25' --(Stage 3) THEN 1 ELSE 'N/A' END as PD_IFRS9_12M_LFTM_RD WHERE IMCATF046_FLAG_FECHO.CMES = REF_DATE Lógica proposta para a criação do novo campo na LT003: 1) Identificar contratos onde o cliente é o 1º Titular: LT005_INSTR_ENT WHERE CRELACAO_CL_CNT = '1' AND CSEQUENCIA_REL = '00001' 2) Aplicar o seguinte cáclulo por entidade: CASE WHEN SUM(IFRS9_EAD)<> 0 THEN SUM(PD_IFRS9_12M_LFTM_RD * IFRS9_EAD) / SUM(IFRS9_EAD) ELSE AVG(PD_IFRS9_12M_LFTM_RD) END as ifrs9_prob_default_impairment | N6: Em análise
A17: V_11 | B17: Risk parameters | C17: Probability of default (others) | D17: Numeric. Basis points | E17: Applicable only to institutions not using CRR IRB models. These institutions should maintain records of probabilities of default or scores provided by scoring/rating models. In the case of PDs produced at the instrument level only, the counterparty’s PD is to be reported as the exposure-weighted average PD across the PDs of all instruments of the counterparty. If, for a given counterparty, PDs are estimated for both the counterparty and (some of) the products of the counterparty, it is the counterparty’s PD which is to be reported. | G17: - | H17: - | I17: - | K17: SIM | L17: probability_default_others | M17: Reportar sempre: 11111111111

Sheet LEGALP_PROTECTIONS
A1: Instruções SRB | G1: Mapeamento efetuado pela Corporação e respetiva Descrição Loan Tape (LT) | K1: Análise IT
A2: ID | B2: Categoria | C2: Coluna | D2: Tipo de dados | E2: Descrição | G2: Mapeamentos Corporação (LT) | H2: Descrição (LT) | I2: Additional Guidance (LT) | K2: Novo campo na tabela LT004? | L2: Nome do campo no ficheiro | M2: Mapeamento | N2: Notas
A3: V_12 | B3: Identification information | C3: Protection identifier | D3: Alphanumeric | E3: An identifier applied to uniquely identify each protection/collateral used to secure the instrument. | G3: PROTECTION-PRTCTN_ID | H3: Protection ID | I3: An identifier applied by the reporting agent to uniquely identify each protection used to secure the instrument. Each protection must have one protection identifier. This value will not change over time and cannot be used as the protection identifier for any other protection. | K3: NÃO | L3: protection_id | M3: LT004_PROTECTION.PRTCTN_ID
A7: V_1 | B7: Identification information | C7: Instrument Identifier | D7: Alphanumeric | E7: An identifier applied to uniquely identify each instrument. Each instrument must have one instrument identifier. | G7: Not applicable: To be reported as "N/A". This information will be availabe in "01_05_leg_instr_prot" table | H7: - | I7: - | K7: SIM | L7: instrument_id | M7: Reportar sempre: 'N/A'
A11: V_187 | B11: Identification information | C11: Type of collateral | D11: String | E11: The AnaCredit item “type of protection” (Section 9.4.3. of the Anacredit Reporting Manual part II - Dataset and data attributes) provides a breakdown of collateral eligible in accordance with the CRR. The proposed breakdown adds several categories. Options: ‣ Gold ‣ Currency and deposits ‣ Securities ‣ Loans ‣ Equity and investment fund shares or units ‣ Credit derivatives ‣ Financial guarantees other than credit derivatives ‣ Trade receivables ‣ Life insurance policies pledged ‣ Residential real estate collateral ‣ Offices and commercial premises ‣ Commercial real estate collateral ‣ Other physical collateral ‣ Other protection ‣ Hotels & entertainment ‣ Infrastructure projects ‣ Factories – warehouses ‣ Equipment & machinery ‣ Automotive ‣ Aircraft ‣ Shipping | G11: PROTECTION-TYP_PRTCTN | H11: Protection type | I11: Type of protection received, irrespective of its eligibility for credit risk mitigation. | K11: NÃO | L11: type_collateral | M11: LT004_PROTECTION.TYP_PRTCTN ‣ Traduzir o campo "TYP_PRTCTN" seguindo as parametrizações apresentadas nas sheets: ‣ LT829 - filtrando por campo_conceito = 'TYP_PRTCTN' e regra_conversao = '1'; ‣ LT830 - filtrando por segmento = 'Exposures to legal persons' e campo_conceito = 'TYP_PRTCTN'.
A14: V_14 | B14: Size collateral | C14: Building Area (M2) | D14: Numeric | E14: Building area of the building in square metres. Only applicable to Residential real estate collateral, Offices and commercial premises, Commercial real estate collateral, Hotels & entertainment, Factories – warehouses. | G14: - | H14: - | I14: - | K14: SIM gross_area | L14: building_area_m2 | M14: Campo "narbrut" da tabela cd_garantias.gt009_bens_imov
A15: V_15 | B15: Size collateral | C15: Land Area (M2) | D15: Numeric | E15: Land area of the property in square metres, including any land surrounding the building(s) on the property that is part of the property. | G15: - | H15: - | I15: - | K15: SIM land_area | L15: land_area_m2 | M15: Campo "narterr" da tabela cd_garantias.gt009_bens_imov
A16: V_16 | B16: Location | C16: Property postcode | D16: Numeric | E16: Postcode where the property is located. Only applicable to Residential real estate collateral, Offices and commercial premises, Commercial real estate collateral, Hotels & entertainment, Factories – warehouses. | G16: PROTECTION-RL_ESTT_PST_CD | H16: Post code / ZIP | I16: Post code / ZIP. | K16: NÃO | L16: property_postcode | M16: LT004_PROTECTION.RL_ESTT_PST_CD
A17: V_17 | B17: Lien | C17: Lien position | D17: Numeric | E17: The highest ranking position(s) in relation to the collateral held by the counterparty to secure the facility. If the facility has several liens on one collateral, the highest claim is reported in this data field. | G17: - | H17: - | I17: - | K17: SIM | L17: lien_position | M17: Reportar sempre: 1
A18: V_18 | B18: Collateral characteristics | C18: Detailed type of Shipping collateral | D18: String | E18: Detailed type of collateral received. Applicable only to shipping portfolios. Options: ‣ Bulker (1) ‣ Container (2) ‣ Crude Oil Tanker (3) ‣ Product Tanker (4) ‣ Chemical Tanker (5) ‣ Cruise Ship (6) ‣ Ferry (7) ‣ LPG Carrier (8) ‣ Offshore (9) ‣ Other (10) | G18: - | H18: - | I18: - | K18: SIM | L18: det_type_ship_collateral | M18: Conceito a revisitar no futuro | N18: Em análise

Sheet LEGALP_INSTRUMENT_COUNTERPARTY
A1: Instruções SRB | G1: Mapeamento efetuado pela Corporação e respetiva Descrição Loan Tape (LT) | K1: Análise IT
A2: ID | B2: Categoria | C2: Coluna | D2: Tipo de dados | E2: Descrição | G2: Mapeamentos Corporação (LT) | H2: Descrição (LT) | I2: Additional Guidance (LT) | K2: Novo campo na tabela LT005? | L2: Nome do campo no ficheiro | M2: Mapeamento | N2: Notas
A3: V_1 | B3: Identification information | C3: Instrument Identifier | D3: Alphanumeric | E3: An identifier applied to uniquely identify each instrument. Each instrument must have one instrument identifier | G3: INSTR_ENTITY-INSTRMNT_ID | H3: Instrument ID | I3: An identifier applied by the reporting agent to uniquely identify each instrument under a single contract. Each instrument must have one instrument identifier. This value will not change over time and cannot be used as the instrument identifier for any other instrument under the same contract. Supervised Insitutions are asked to furnish the INSTRMNT_ID with the exact same value as it is reported to AnaCredit (or any similar central credit register). If this is not available, the value shall be reported as it is internally used. If an instrument is not reported to AnaCredit but requested for the purposes of the on-site inspection please provide the bank-internally used value. Foreign Key from INSTRUMENT table. | K3: NÃO | L3: instrument_id | M3: LT005_INSTR_ENT.INSTRMNT_ID
A7: V_2 | B7: Identification information | C7: Counterparty Identifier | D7: Alphanumeric | E7: Identifier applied to uniquely identify each counterparty. | G7: INSTR_ENTITY-ENTTY_ID | H7: Entity ID | I7: An identifier applied by the reporting agent to uniquely identify each counterparty. Each counterparty has a unique and exclusive counterparty identifier. This means that this value will not change over time and can never be used as the counterparty identifier for any other counterparty. Foreign key from ENTITY table. | K7: NÃO | L7: counterparty_id | M7: LT005_INSTR_ENT.ENTTY_ID

Sheet LEGALP_INSTRUMENT_PROTECTION
A1: Instruções SRB | G1: Mapeamento efetuado pela Corporação e respetiva Descrição Loan Tape (LT) | K1: Análise IT
A2: ID | B2: Categoria | C2: Coluna | D2: Tipo de dados | E2: Descrição | G2: Mapeamentos Corporação (LT) | H2: Descrição (LT) | I2: Additional Guidance (LT) | K2: Novo campo na tabela LT006? | L2: Nome do campo no ficheiro | M2: Mapeamento | N2: Notas
A3: V_1 | B3: Identification information | C3: Instrument Identifier | D3: Alphanumeric | E3: An identifier applied to uniquely identify each instrument. Each instrument must have one instrument identifier | G3: INSTR_PROTECTION-INSTRMNT_ID | H3: Instrument ID | I3: An identifier applied by the reporting agent to uniquely identify each instrument under a single contract. Each instrument must have one instrument identifier. This value will not change over time and cannot be used as the instrument identifier for any other instrument under the same contract. Supervised Insitutions are asked to furnish the INSTRMNT_ID with the exact same value as it is reported to AnaCredit (or any similar central credit register). If this is not available, the value shall be reported as it is internally used. If an instrument is not reported to AnaCredit but requested for the purposes of the on-site inspection please provide the bank-internally used value. Foreign Key from INSTRUMENT table. | K3: NÃO | L3: instrument_id | M3: LT006_INSTR_PROT.INSTRMNT_ID
A7: V_12 | B7: Identification information | C7: Protection identifier | D7: Alphanumeric | E7: An identifier applied to uniquely identify each protection/collateral used to secure the instrument. | G7: INSTR_PROTECTION-PRTCTN_ID | H7: Protection ID | I7: An identifier applied by the reporting agent to uniquely identify each protection used to secure the instrument. Each protection must have one protection identifier. This value will not change over time and cannot be used as the protection identifier for any other protection. Foreign Key from PROTECTION table. | K7: NÃO | L7: protection_id | M7: LT006_INSTR_PROT.PRTCTN_ID

Sheet NATURAL PERSONS DATA SETS
A1: SRB DATA SET FOR EXPOSURES TO NATURAL PERSONS The following data set covers exposures to natural persons, which, in many cases, represent the main type of exposures on banks’ balance sheets (e.g. retail institutions or mortgage institutions). Such exposures might comprise lending products such as mortgages, consumer loans, credit cards, etc. Valuations of retail portfolios are usually made with lesser granularity than valuations of corporate portfolios. However, in specific circumstances (e.g. high default rates in mortgage portfolios) a collective assessment might not suffice and the valuer might rely on a more granular approach for qualitatively and quantitatively assessing the level of economic impairment of exposures to natural persons that would typically be impaired on a collective basis under International Financial Reporting Standard (IFRS 9). In this case, the valuer would require a more granular data set to perform valuations. To avoid any duplication of data points or definitions, the data set for exposures to natural persons is based on the AnaCredit data points and definitions for legal persons. However, institutions can leverage on the definitions, data points and reporting thresholds of local standards or legislation, provided those definitions and data points are, in the IRT’s view, equivalent to those envisaged for AnaCredit. Serão produzidos cinco ficheiros de report referentes a Natural Persons: ‣ SRB Instruments Data Set for exposures to natural persons (NATURALP_INSTRUMENTS); ‣ SRB Counterparties Data Set for exposures to natural persons (NATURALP_COUNTERPARTIES); ‣ SRB Protection received Data Set for exposures to natural persons (NATURALP_PROTECTIONS); ‣ SRB Instrument/Counterparty mapping Data Set for exposures to natural persons (NATURALP_INSTRUMENT_COUNTERPARTY); ‣ SRB Instrument/Protection mapping Data Set for exposures to natural persons (NATURALP_INSTRUMENT_PROTECTION);
A2: SRB DATA SET FOR EXPOSURES TO NATURAL PERSONS O seguinte data set abrange exposições a pessoas singulares, que, em muitos casos, representam o principal tipo de exposições nos balanços dos bancos (por exemplo, instituições de retalho ou instituições hipotecárias). Essas exposições podem incluir produtos de empréstimo, como hipotecas, empréstimos pessoais, cartões de crédito, etc. As avaliações de carteiras de retalho são geralmente feitas com menos granularidade do que as avaliações de carteiras corporativas. No entanto, em circunstâncias específicas (por exemplo, elevadas taxas de incumprimento em carteiras hipotecárias), uma avaliação colectiva pode não ser suficiente e o avaliador pode basear-se numa abordagem mais granular para avaliar qualitativa e quantitativamente o nível de imparidade económica das exposições a pessoas singulares que normalmente seriam prejudicadas numa base colectiva ao abrigo da International Financial Reporting Standard (IFRS 9). Neste caso, o avaliador necessitaria de um conjunto de dados mais granular para realizar avaliações. Para evitar qualquer duplicação de pontos de dados ou definições, o data set para exposições a pessoas singulares baseia-se nos pontos de dados e definições da AnaCredit para pessoas coletivas. No entanto, as instituições podem aproveitar as definições, os pontos de dados e os limites de reporte das normas ou legislação local, desde que essas definições e pontos de dados sejam, na opinião do IRT, equivalentes aos previstos para o AnaCredit. Serão produzidos cinco ficheiros de report referentes a Natural Persons: ‣ SRB Instruments Data Set for exposures to natural persons (VDS_OUT_NATURALP_INSTRUMENTS); ‣ SRB Counterparties Data Set for exposures to natural persons (VDS_OUT_NATURALP_COUNTERPARTIES); ‣ SRB Protection received Data Set for exposures to natural persons (VDS_OUT_NATURALP_PROTECTIONS).

Sheet NATURALP_INSTRUMENTS
A1: Instruções SRB | G1: Mapeamento efetuado pela Corporação e respetiva Descrição Loan Tape (LT) | K1: Análise IT
A2: ID | B2: Categoria | C2: Coluna | D2: Tipo de dados | E2: Descrição | G2: Mapeamentos Corporação (LT) | H2: Descrição (LT) | I2: Additional Guidance (LT) | K2: Novo campo na tabela LT002? | L2: Nome do campo no ficheiro | M2: Mapeamento | N2: Notas
A3: V_1 | B3: Identification information | C3: Instrument Identifier | D3: Alphanumeric | E3: Identifier applied to uniquely identify each instrument. Each instrument must have one instrument identifier. | G3: INSTRUMENT-INSTRMNT_ID | H3: Instrument ID | I3: An identifier applied by the reporting agent to uniquely identify each instrument under a single contract. Each instrument must have one instrument identifier. This value will not change over time and cannot be used as the instrument identifier for any other instrument under the same contract. Supervised Insitutions are asked to furnish the INSTRMNT_ID with the exact same value as it is reported to AnaCredit (or any similar central credit register). If this is not available, the value shall be reported as it is internally used. If an instrument is not reported to AnaCredit but requested for the purposes of the on-site inspection please provide the bank-internally used value. | K3: NÃO | L3: instrument_id | M3: LT002_INSTRUMENT.INSTRMNT_ID
A7: V_2 | B7: Identification information | C7: Counterparty Identifier | D7: Alphanumeric | E7: Identifier applied to uniquely identify each counterparty. | G7: Not applicable: To be reported as "N/A". This information will be availabe in "02_04_nat_instr_count" table | H7: - | I7: - | K7: SIM | L7: counterparty_id | M7: Reportar sempre: 'N/A'
A8: V_139 | B8: Identification information | C8: Reporting data identifier | D8: Alphanumeric | E8: The counterparty identifier of the reporting agent which reports the data. | G8: INSTRUMENT-COD_SOC | H8: Entity code of the informing society. | I8: Cargabal code or internal identifier of the informing society. | K8: NÃO | L8: reporting_data_id | M8: LT002_INSTRUMENT.COD_SOC
A9: V_140 | B9: Identification information | C9: Observed agent identifier | D9: Alphanumeric | E9: The counterparty identifier of the observed agent (i.e. an institutional unit of the reporting agent) whose data are reported by the reporting agent. | G9: INSTRUMENT-OBSRVD_AGNT_ID | H9: Observed agent identifier | I9: Counterparty identifier for the observed agent. If there are several observed agents to be reported please separate by comma (,). | K9: NÃO | L9: observed_agent_id | M9: LT002_INSTRUMENT.OBSRVD_AGNT_ID
A10: V_141 | B10: Identification information | C10: Contract identifier | D10: Alphanumeric | E10: An identifier applied by the reporting agent to uniquely identify each contract. The contract identifier refers to the credit agreement between two or more parties under which the instrument is created. | G10: INSTRUMENT-CNTRCT_ID | H10: Contract ID | I10: An identifier applied by the reporting agent to uniquely identify each contract. Each contract must have one contract identifier. This value will not change over time and cannot be used as the contract identifier for any other contract. | K10: NÃO | L10: contract_id | M10: LT002_INSTRUMENT.CNTRCT_ID
A14: V_3 | B14: Exposure class | C14: CRR Exposure class | D14: String | E14: The exposures classes for the calculation of RWAs for credit risks are as follows (not applicable when exposures are classified in the CRR trading book as defined in Article 4(1)(86) of Regulation (EU) No 575/2013): Where a bank uses the standardised approach: ‣ Central governments or central banks (SCENGOV) ‣ Regional governments or local authorities (SREGGOV) ‣ Public sector entities (SPUBSEC) ‣ Multilateral development banks (SDEVBAN) ‣ International organisation (SINTORG) ‣ Institutions (SINSTIT) ‣ Corporates (SCORPOR) ‣ Retail (SRETAIL) ‣ Secured by mortgages and immovable property (SSECMOR) ‣ Defaulted (SDEFAUL) ‣ High risk (SHIGHRI) ‣ Covered bonds (SCOVBON) ‣ Items representing securitisation positions ‣ Institutions and corporates with a short term credit assessment (SSHOTER) ‣ Collective investment undertakings (SCOLINV) ‣ Equity (SEQUITY) ‣ Other (SOTHERI) Where a bank uses the IRB approach: ‣ Central governments and central banks (ICENGOV) ‣ Institutions (IINSTIT) ‣ Corporates (ICORPOR) ‣ Retail (IRETAIL) ‣ Equity (IEQUITY) ‣ Items representing securitisation positions ‣ Other non-credit-obligation assets (IOTHERC) | G14: - | H14: - | I14: - | K14: SIM | L14: crr_exposure_class | M14: ‣ Utilizar o campo "segmento_corep_final" da tabela ct013_rwa_princ; Nota: Os códigos "segmento_corep_final" seguem sempre a mesma estrutura, começam com um caracter que identifica se é IRB (I_...) ou Standard (S_...) e de seguida um numérico (ex. I_3.1, I_5.1, S_1.0). ‣ Para o mesmo contrato este campo pode retornar vários códigos "segmento_corep_final" distintos, de seguida estão os passos que permitem resolver esta ambiguidade: 1. Deve seguir a lógica do campo RWA_MTHD, de momento a lógica é, se existir IRB e Standard então trazer informação relativa a IRB; 2. Se mesmo aplicando o passo 1 ainda existirem vários códigos "segmento_corep_final" distintos (vários códigos IRB ou vários códigos Standard) então: recuperar o código "segmento_corep_final" com o menor numérico associado. ‣ Traduzir o campo "segmento_corep_final" seguindo a parametrização apresentada na sheet 'LT831' filtrando por tabela_conceito = 'LT002_INSTRUMENT' e campo_conceito = 'CRR_EXPOSURE_CLASS' Exemplo: O contrato A tem associados os seguintes códigos "segmento_corep_final" distintos: I_3.1, I_5.1, S_1.0: 1. Remover o Standard: I_3.1, I_5.1; 2. Ficar com o menor numérico: I_3.1.
A17: V_4 | B17: Exposure class | C17: FINREP Exposure class | D17: String | E17: Classification of the facility (exposure class) as defined in ITS 680/2014 Annex V Instructions FINREP (Counterparty breakdown). Opções: ‣ Central banks ‣ Central governments ‣ Credit institutions ‣ Other financial corporations ‣ Non-financial corporations ‣ Households | G17: - | H17: - | I17: - | K17: NÃO | L17: finrep_exposure_class | M17: LT002_INSTRUMENT.INTRNL_SGMNT ‣ Traduzir o campo "INTRNL_SGMNT" seguindo as parametrizações apresentadas nas sheets: ‣ LT829 - filtrando por campo_conceito = 'INTRNL_SGMNT' e regra_conversao = '1'; ‣ LT830 - filtrando por segmento = 'Exposures to natural persons' e campo_conceito = 'INTRNL_SGMNT'.
A24: V_5 | B24: Risk parameters | C24: Total Risk Exposure Amount | D24: Numeric (euro) | E24: The total risk exposure amount of the instrument, calculated according to Articles 92(3) and 92(4) of Regulation (EU) No 575/2013 (CRR), where applicable. | G24: INSTRUMENT-RWA | H24: RWA | I24: RWA according to Regulation (EU) No 575/2013. | K24: NÃO | L24: total_risk_exposure_amount | M24: LT002_INSTRUMENT.RWA
A27: V_6 | B27: Risk parameters | C27: CRR Loss given default | D27: Numeric. Basis points | E27: Current level of the ‘Loss given default’ of the loan, determined in accordance with Articles 161, 164, 179 and 181 of Regulation (EU) No 575/2013. | G27: INSTRUMENT-LGD | H27: Regulatory LGD | I27: If differences between regulatory and internal LGD exist, use regulatory LGD (according to Regulation (EU) No 575/2013). In particular, in IRB-F use regulatory LGD values. | K27: NÃO | L27: crr_loss_given_default | M27: LT002_INSTRUMENT.LGD
A31: V_7 | B31: Risk parameters | C31: IFRS 9 Loss given default | D31: Numeric. Basis points | E31: Current level of the ‘Loss given default’ of the loan determined for accounting purposes. | G31: INSTRUMENT-IFRS9_LGD | H31: IFRS 9 accounting LGD | I31: IFRS 9 accounting Loss Given Default as at reference date for defaulted and non-defaulted exposures. In case the bank models time-depended LGD variable for non-defaulted exposures then 12-month LGD as at reference date regardless the classification as Stage 1 or 2 | K31: NÃO | L31: ifrs9_loss_given_default | M31: LT002_INSTRUMENT.IFRS9_LGD
A34: V_35 | B34: Instruments characteristics | C34: Type of instrument | D34: String | E34: Classification of the instrument according to the type of contractual terms agreed between the parties. Opções: ‣ Overdraft ‣ Credit card debt ‣ Revolving credit other than overdrafts and credit card debt ‣ Credit lines other than revolving credit ‣ Financial lease ‣ Loan ‣ Other | G34: INSTRUMENT-TYP_INSTRMNT | H34: Type of instrument | I34: Classification of the instrument according to the type of contractual terms agreed between the parties. | K34: NÃO | L34: type_instrument | M34: LT002_INSTRUMENT.TYP_INSTRMNT ‣ Traduzir o campo "TYP_INSTRMNT" seguindo as parametrizações apresentadas nas sheets: ‣ LT829 - filtrando por campo_conceito = 'TYP_INSTRMNT' e regra_conversao = '1'; ‣ LT830 - filtrando por segmento = 'Exposures to natural persons' e campo_conceito = 'TYP_INSTRMNT'.
A37: V_142 | B37: Instruments characteristics | C37: Amortization type | D37: String | E37: Type of amortisation of the instrument including principal and interest at the reporting reference date. Opções: ‣ French ‣ German ‣ Fixed amortisation schedule ‣ Bullet ‣ Other | G37: INSTRUMENT-TYP_AMRTSTN | H37: Type of amortisation | I37: Type of amortisation of the instrument including principal and interest. | K37: NÃO | L37: amortization_type | M37: LT002_INSTRUMENT.TYP_AMRTSTN ‣ Traduzir o campo "TYP_AMRTSTN" seguindo as parametrizações apresentadas nas sheets: ‣ LT829 - filtrando por campo_conceito = 'TYP_AMRTSTN' e regra_conversao = '1'; ‣ LT830 - filtrando por segmento = 'Exposures to natural persons' e campo_conceito = 'TYP_AMRTSTN'.
... A43: V_145 | B43: Interest rate information | C43: End date of interest-only period | D43: DD/MM/AA | E43: The date on which the interest-only period ends. | G43: INSTRUMENT-DT_END_INTRST_ONLY | H43: End date of the interest-only period | I43: The date on which the interest-only period ends. Interest-only instruments are those for which, for a contractually set period, only the interest on the principal balance is paid, with the principal balance remaining unchanged. The scope of the field refers to any interest only period, either due to renegotiations or interest only agreements at loan inception. | K43: NÃO | L43: end_date_interest_only_period | M43: LT002_INSTRUMENT.DT_END_INTRST_ONLY
A44: V_146 | B44: Interest rate information | C44: Interest rate cap | D44: Numeric. Reported in basis points with the same convention as for the attribute “interest rate spread/margin”. | E44: The maximum interest rate per annum that can be charged on the outstanding nominal amount (or parts thereof). | G44: - | H44: - | I44: - | K44: SIM | L44: interest_rate_cap | M44: ‣ Necessário criar um novo campo no Loan Tapes que deverá ser alimentado pela tabela al029_cnt_core_m. No entanto de momento esta informação não existe na tabela al029_cnt_core_m, está em curso a análise de um desenvolvimento no ambiente ALM que prevê adicionar 8 campos à tabela al029_cnt_core_m: cap do indexante passivo, cap do all-in passivo (indexante+spread), floor do indexante passivo, floor do all-in passivo (indexante+spread), cap do indexante ativo, cap do all-in ativo(indexante+spread), floor do indexante ativo, floor do all-in ativo(indexante+spread). Este datapoint será alimentado por um destes novos campos. | N44: Em análise
A45: V_147 | B45: Interest rate information | C45: Interest rate floor | D45: Numeric. Reported in basis points with the same convention as for the attribute “interest rate spread/margin”. | E45: The minimum interest rate per annum that can be charged on the outstanding nominal amount (or parts thereof). | G45: - | H45: - | I45: - | K45: SIM | L45: interest_rate_floor | M45: ‣ Necessário criar um novo campo no Loan Tapes que deverá ser alimentado pela tabela al029_cnt_core_m. No entanto de momento esta informação não existe na tabela al029_cnt_core_m, está em curso a análise de um desenvolvimento no ambiente ALM que prevê adicionar 8 campos à tabela al029_cnt_core_m: cap do indexante passivo, cap do all-in passivo (indexante+spread), floor do indexante passivo, floor do all-in passivo (indexante+spread), cap do indexante ativo, cap do all-in ativo(indexante+spread), floor do indexante ativo, floor do all-in ativo(indexante+spread). Este datapoint será alimentado por um destes novos campos. | N45: Em análise
A46: V_148 | B46: Interest rate information | C46: Interest rate reset frequency | D46: String | E46: Frequency at which the interest rate is reset after the initial fixed-rate period, if any. Opções: ‣ Overnight ‣ Monthly/quarterly/semiannual/annual ‣ At creditor discretion ‣ Other frequency | G46: INSTRUMENT-INTRST_RT_RST_FRQNCY | H46: Interest rate reset frequency | I46: Frequency at which the interest rate is reset after the initial fixed-rate period, if any. | K46: NÃO | L46: interest_rate_reset_freq | M46: LT002_INSTRUMENT.INTRST_RT_RST_FRQNCY ‣ Traduzir o campo "INTRST_RT_RST_FRQNCY" seguindo as parametrizações apresentadas nas sheets: ‣ LT829 - filtrando por campo_conceito = 'INTRST_RT_RST_FRQNCY' e regra_conversao = '1'; ‣ LT830 - filtrando por segmento = 'Exposures to natural persons' e campo_conceito = 'INTRST_RT_RST_FRQNCY'.
A47: V_149 | B47: Interest rate information | C47: Interest rate spread/margin | D47: Numeric (percentage) | E47: Margin or spread to add to the reference rate that is used for the calculation of the interest rate in basis points. This applies to interest rates charged for variable interest loans. | G47: - | H47: - | I47: - | K47: NÃO | L47: interest_rate_spread_margin | M47: LT002_INSTRUMENT.SPRD
A49: V_150 | B49: Interest rate information | C49: Interest rate type | D49: String | E49: Classification of credit exposures based on the base rate for establishing the interest rate for each payment period. Opções: ‣ Fixed ‣ Variable ‣ Mixed | G49: INSTRUMENT-TYP_INTRST_RT | H49: Type of interest rate | I49: Classification of credit exposures based on the base rate for establishing the interest rate for each payment period. | K49: NÃO | L49: interest_rate_type | M49: ILT002_INSTRUMENT.TYP_INTRST_RT ‣ Traduzir o campo "TYP_INTRST_RT" seguindo as parametrizações apresentadas nas sheets: ‣ LT829 - filtrando por campo_conceito = 'TYP_INTRST_RT' e regra_conversao = '1'; ‣ LT830 - filtrando por segmento = 'Exposures to natural persons' e campo_conceito = 'TYP_INTRST_RT'.
A50: V_151 | B50: Instrument characteristics | C50: Legal final maturity date | D50: DD/MM/AA | E50: The contractual maturity date of the instrument, taking into account any agreements amending initial contracts. | G50: INSTRUMENT-DT_LGL_FNL_MTRTY | H50: Legal final maturity date (latest repayment date) | I50: The contractual maturity date of the instrument, taking into account any agreements amending initial contracts. As for retail revolving credit facilities this attribute is to be reported "not applicable". | K50: NÃO | L50: maturity_date | M50: LT002_INSTRUMENT.DT_LGL_FNL_MTRTY
A51: V_152 | B51: Instrument characteristics | C51: Commitment amount at inception | D51: Numeric (euro) | E51: Observed agent’s maximum exposure to credit risk on the inception date of the instrument, without taking into account any protection held or other credit enhancements. | G51: INSTRUMENT-CMMTMNT_INCPTN_INSTRMNT | H51: Commitment amount at inception | I51: Observed agent’s maximum exposure to credit risk on the inception date of the instrument, without taking into account any protection held or other credit enhancements. Total commitment amount on the inception date is established during the approval process and is intended to restrict an observed agent’s amount of credit risk to a given counterparty for the relevant instrument. | K51: NÃO | L51: commitment_amount_inception | M51: LT002_INSTRUMENT.CMMTMNT_INCPTN_INSTRMNT
A52: V_153 | B52: Instrument characteristics | C52: Payment frequency | D52: String | E52: Frequency of payments due, either of principal or interest, i.e. number of months between payments at the reporting reference date. Opções: ‣ Monthly/quarterly/semiannual/annual ‣ Bullet ‣ Zero coupon ‣ Other | G52: INSTRUMENT-PYMNT_FRQNCY | H52: Payment frequency | I52: Frequency of payments due, either of principal or interest, i.e. number of months between payments. | K52: NÃO | L52: payment_freq | M52: LT002_INSTRUMENT.PYMNT_FRQNCY ‣ Traduzir o campo "PYMNT_FRQNCY" seguindo as parametrizações apresentadas nas sheets: ‣ LT829 - filtrando por campo_conceito = 'PYMNT_FRQNCY' e regra_conversao = '1'; ‣ LT830 - filtrando por segmento = 'Exposures to natural persons' e campo_conceito = 'PYMNT_FRQNCY'.
A59: V_154 | B59: Instrument characteristics | C59: Reference rate | D59: String | E59: Reference rate used for the calculation of the actual interest rate. The reference rate code is a combination of the reference rate value and maturity value. Opções: ‣ EURIBOR ‣ USD LIBOR ‣ GBP LIBOR ‣ EUR LIBOR ‣ JPY LIBOR ‣ CHF LIBOR ‣ MIBOR ‣ OTHER SINGLE REFERENCE RATES ‣ OTHER MULTIPLE REFERENCE RATES | G59: - | H59: - | I59: - | K59: SIM | L59: reference_rate | M59: ‣ Reportar o campo "cod_tipo_taxa_ref_act" da tabela cd_alm.al029_cnt_core_m; ‣ O campo acima responde à finalidade pedida neste report, no entanto é necessário criar um campo novo no Loan Tape, que tem de ser genérico, caso outros reports também necessitem do o consumir. Necessário confirmar se a seguinte regra responde de forma genérica a este conceito: Reportar: SELECT CONCAT(TRIM(cod_tipo_taxa_ref_act),TRIM(cod_tipo_taxa_ref_pas)) FROM cd_alm.al029_cnt_core_m; ‣ Falta finalizar a parametrização a aplicar neste campo. | N59: Em análise
A60: V_155 | B60: Instrument characteristics | C60: Settlement date | D60: DD/MM/AA | E60: The date on which the conditions specified in the contract are or can be executed for the first time, i.e. the date on which financial instruments are initially exchanged or created. | G60: - | H60: - | I60: - | K60: SIM | L60: settlement_date | M60: Criar um novo campo "SETTLEMENT_DATE" na tabela LT002_INSTRUMENT, que será uma 'cópia' do campo LT002_INSTRUMENT.DT_INCPTN.
A61: V_156 | B61: Interest rate information | C61: Interest rate | D61: Numeric (percentage with two decimals, both positive and negative values). | E61: Annualised agreed rate or narrowly defined interest rate in accordance with Part 1 of Annex I to Regulation (EU) No 1072/2013 of the European Central Bank (ECB/2013/34) | G61: INSTRUMENT-ANNLSD_AGRD_RT | H61: Interest rate at the reference date | I61: Annualised agreed rate or narrowly defined interest rate at reference date in accordance with Regulation (EU) No 1072/2013 of the European Central Bank (ECB/2013/34). | K61: NÃO | L61: interest_rate | M61: LT002_INSTRUMENT.ANNLSD_AGRD_RT
A63: V_157 | B63: Interest rate information | C63: Next interest rate reset date | D63: DD/MM/AA | E63: The date when the next interest rate reset, as defined in Part 3 of Annex I to Regulation (EU) No 1071/2013 (ECB/2013/33), takes place. | G63: INSTRUMENT-DT_NXT_INTRST_RT_RST | H63: Next interest rate reset date | I63: The date when the next interest rate reset, as defined in Part 3 of Annex I to Regulation (EU) No 1071/2013 (ECB/2013/33), takes place. | K63: NÃO | L63: next_interest_rate_reset_date | M63: LT002_INSTRUMENT.DT_NXT_INTRST_RT_RST
A65: V_158 | B65: Financial information | C65: Default status of the instrument | D65: String | E65: Identification of the default status of the instrument in accordance with Article 178 of Regulation (EU) No 575/2013. Opções: ‣ Not in default ‣ Default because unlikely to pay (not more than 90/180 days past due) ‣ Default because more than 90/180 days past due ‣ Default because both unlikely to pay and more than 90/180 days past due. | G65: INSTRUMENT-DFLT_STTS_INSTRMNT | H65: Default status of the instrument | I65: Identification of the default status of the instrument. Categories describing the situations in which an instrument can be described as being at default in accordance with Article 178 of Regulation (EU) No 575/2013. | K65: NÃO | L65: default_status_instrument | M65: LT002_INSTRUMENT.DFLT_STTS_INSTRMNT ‣ Traduzir o campo "DFLT_STTS_INSTRMNT" seguindo as parametrizações apresentadas nas sheets: ‣ LT829 - filtrando por campo_conceito = 'DFLT_STTS_INSTRMNT' e regra_conversao = '1'; ‣ LT830 - filtrando por segmento = 'Exposures to natural persons', campo_conceito = 'DFLT_STTS_INSTRMNT'.
A68: V_159 | B68: Financial information | C68: Date of the default status of the instrument | D68: DD/MM/AA | E68: The date on which the default status, as reported in the data attribute “default status of the instrument”, is considered to have occurred. | G68: INSTRUMENT-DT_DFLT_STTS_INSTRMNT | H68: Date of default status | I68: The date on which the default status, as reported in the data attribute “Default status”, is considered to have arisen. If "Not in default" since inception then this attribute is to be reported equally to the inception date. If more than one Instrument is classified as defaulted then the earliest date has to be provided. The definition of default is aligned with Art 178 of Regulation (EU) No 575/2013. | K68: NÃO | L68: date_default_status_instrument | M68: LT002_INSTRUMENT.DT_DFLT_STTS_INSTRMNT
A69: V_160 | B69: Financial information | C69: Transferred amount | D69: Numeric (euro) | E69: Transferred amount of the economic ownership of the financial asset to third parties. This data attribute captures the part of the outstanding nominal amount that has been transferred to another creditor. | G69: - | H69: - | I69: - | K69: SIM | L69: transferred_amount | M69: Reportar sempre: 11111111111
A70: V_161 | B70: Financial information | C70: Arrears for the instrument | D70: Numeric (euro) | E70: Aggregated amount of the principal, interest and any fee payment outstanding at the reporting date, which is contractually due and has not been paid (past due). | G70: INSTRUMENT-ARRRS_INSTRMNT | H70: Total exposure in arrears | I70: Aggregated amount of the principal, interest and any fee payment outstanding at the reporting date, which is contractually due and has not been paid (past due). | K70: NÃO | L70: arrears_instrument | M70: LT002_INSTRUMENT.ARRRS_INSTRMNT
A71: V_162 | B71: Financial information | C71: Date of past due for the instrument | D71: DD/MM/AA | E71: The date on which the instrument became past due in accordance with Part 2.96 of Annex V to the amended Implementing Regulation (EU) No 680/2014. | G71: INSTRUMENT-DT_PST_D | H71: Date past due | I71: The date on which the instrument became past due in accordance with Part 2.96 of Annex V to the amended Implementing Regulation (EU) No 680/2014. This is the latest such date prior to the reporting reference date and it is to be reported if the instrument is past due on the reporting reference date. | K71: NÃO | L71: date_past_due_instrument | M71: LT002_INSTRUMENT.DT_PST_D
A72: V_163 | B72: Financial information/Instrument characteristics | C72: Type of securitization | D72: String | E72: Captures the type of securitisation, if any, to which the instrument has been subject, in accordance with Article 242(10), (11), 243 and 244 of Regulation (EU) No 575/2013. Opções: ‣ Traditional securitisation ‣ Synthetic securitisation ‣ Not securitised | G72: - | H72: - | I72: - | K72: SIM | L72: type_securitization | M72: ‣ Esta informação não existia no Datalake, foi necessário pedir a ingesta da tabela “JM_SPV” da BDR, a qual já foi implementada; ‣ O Loan Tape não pode consumir informação diretamente da ingesta acima. A informação ingestada deve ser processada e introduzida numa nova tabela cd_captools.ctxxx_securitis_cap. A lógica desta tabela já foi definida e o seu desenvolvimento já foi endereçado; ‣ De seguida está a lógica que foi definida para produzir este campo, falta apenas confirmar qual o campo da tabela ct013_rwa_princ que deverá ser usado como fator de peso de forma a resolver a ambiguidade que surge ao ligar o universo FINREP ao universo da BDR: 1º Passo - Obter para cada contrato (INSTRMNT_ID) o par (S1EMP, COD_SPV) mais 'significativo': 1. Seguir a lógica do campo RWA_MTHD, de momento a lógica é: se existir IRB e Standard então trazer informação relativa a IRB; 2. Se mesmo assim ainda existirem vários pares (S1EMP, COD_SPV) distintos então: recuperar o par (S1EMP, COD_SPV) com o maior valor atribuído no campo !CAMPO DE PESO!; 3. Ficamos então com uma tabela intermédia (TITU_TIP_INTR) com uma relação única entre cada contrato (INSTRMNT_ID) e os campos (S1EMP, COD_SPV). 2ª Passo - Ligar os pares (S1EMP, COD_SPV) obtidos no passo anterior com a tabela cd_captools.ctxxx_securitis_cap de forma a obter o campo TITU_TIP: TITU_TIP_INTR LEFT JOIN (SELECT S1EMP, COD_SPV, TITU_TIP FROM cd_captools.ctxxx_securitis_cap ) as SECUR_CAP ON TITU_TIP_INTR.S1EMP = SECUR_CAP.S1EMP AND TITU_TIP_INTR.COD_SPV = SECUR_CAP.COD_SPV ‣ Traduzir o campo " TITU_TIP " seguindo a parametrização apresentada na sheet 'LT831' filtrando por tabela_conceito = 'LT002_INSTRUMENT' e campo_conceito = 'TYPE_SECURITIZATION'. | N72: Em análise
A73: V_164 | B73: Instrument charcteristics | C73: Outstanding nominal amount | D73: Numeric (euro) | E73: Principal amount outstanding at the end of the reporting reference date, including unpaid past due interest but excluding accrued interest, net of write-offs and write-downs as determined by the relevant accounting practices. | G73: INSTRUMENT-OTSTNDNG_NMNL_AMNT_INSTRMNT | H73: Outstanding gross nominal amount | I73: Principal amount outstanding at the end of the reporting reference date, including unpaid past due interest but excluding accrued interest. The outstanding nominal amount must be reported net of write-offs and write-downs as determined by the relevant accounting practices. | K73: NÃO | L73: outstanding_nominal_amount | M73: LT002_INSTRUMENT.OTSTNDNG_NMNL_AMNT_INSTRMNT
A74: V_165 | B74: Instrument charcteristics | C74: Accrued interest | D74: Numeric (euro) | E74: The amount of accrued interest on loans at the reporting reference date as defined in Regulation (EU) No 1071/2013 (ECB/2013/33). | G74: INSTRUMENT-ACCRD_INTRST_INSTRMNT | H74: Accrued interest balance as recognised on the balance sheet | I74: The amount of accrued interest on loans at the reporting reference date as defined in Regulation (EU) No 1071/2013 (ECB/2013/33). In accordance with the general principle of accruals accounting, interest receivable on instruments should be subject to on-balance sheet recording as it accrues (i.e. on an accruals basis) rather than when it is actually received (i.e. on a cash basis). | K74: NÃO | L74: accrued_interest | M74: LT002_INSTRUMENT.ACCRD_INTRST_INSTRMNT
A75: V_166 | B75: Financial information | C75: Off-balancesheet amount | D75: Numeric (euro) | E75: Total nominal amount of off-balance-sheet exposures. | G75: INSTRUMENT-OFF_BLNC_SHT_AMNT_INSTRMNT | H75: Off-balance sheet amount | I75: Total nominal amount of off-balance-sheet exposures. This includes any commitment to lend before considering conversion factors and credit risk mitigation techniques. It is the amount that best represents the institution’s maximum exposure to credit risk without taking into account any protection held or other credit enhancements. To be reported in accordance with Annex V Regulation 680/2014. If no amount can be drawn by or disbursed to the debtor without contractual changes, the off-balance-sheet amount of the instrument is reported as ”not applicable”. | K75: NÃO | L75: off_balance_sheet_amount | M75: LT002_INSTRUMENT.OFF_BLNC_SHT_AMNT_INSTRMNT
A76: V_167 | B76: Financial information | C76: Joint liabilities amount | D76: Numeric (euro) | E76: Outstanding nominal amount for which each debtor is liable in relation to a single instrument where there are two or more debtors. | G76: Not applicable: To be reported as "11111111111". This information will be availabe in "02_04_nat_instr_count" table | H76: - | I76: - | K76: SIM | L76: joint_liabilities_amount | M76: Reportar sempre: 11111111111
A77: V_168 | B77: Informação financeira | C77: Accounting classification of instruments | D77: String | E77: Accounting portfolio where the instrument is recorded in accordance with the accounting standard – IFRS or national GAAP – under Regulation (EU) 2015/534 (ECB/2015/13) applied by the observed agent’s legal entity. Opções: | G77: INSTRUMENT-ACCNTNG_CLSSFCTN | H77: Accounting portfolio | I77: Accounting portfolio where the instrument is recorded in accordance with the accounting standard – IFRS or national GAAP – under Regulation (EU) 2015/534 (ECB/2015/13) applied by the observed agent’s legal entity. | K77: NÃO | L77: accounting_classification | M77: LT002_INSTRUMENT.ACCNTNG_CLSSFCTN ‣ Traduzir o campo "ACCNTNG_CLSSFCTN" seguindo as parametrizações apresentadas nas sheets: ‣ LT829 - filtrando por campo_conceito = 'ACCNTNG_CLSSFCTN' e regra_conversao = '1'; ‣ LT830 - filtrando por segmento = 'Exposures to natural persons', campo_conceito = 'ACCNTNG_CLSSFCTN'.
A84: V_169 | B84: Informação financeira | C84: Balance sheet recognition | D84: String | E84: Balance sheet recognition of the financial asset. This data attribute classifies the reported instruments pursuant to their balance sheet recognition in accordance with Annex III and Template 15 in Annex IV to the ITS. Opções: ‣ Entirely recognised ‣ Recognised to the extent of the institution’s continuing involvement ‣ Entirely derecognised | G84: - | H84: - | I84: - | K84: SIM | L84: balance_sheet_recogn | M84: Reportar sempre: 'Entirely recognised'
A85: V_170 | B85: Financial information | C85: Accumulated write-offs | D85: Numeric (euro) | E85: Cumulative amount of principal and past due interest of any debt instrument that the institution is no longer recognising because they are considered uncollectible, independently of the portfolio in which they were included. | G85: INSTRUMENT-ACCMLTD_WRTFFS_INSTRMNT | H85: Accumulated write-offs | I85: Cumulative amount of principal and past due interest of any debt instrument that the institution is no longer recognising because they are considered uncollectible, independently of the portfolio in which they were included. Write-offs could be caused both by reductions in the carrying amount of financial assets recognised directly in profit or loss and by reductions in the amounts of the allowance accounts for credit losses set off against the carrying amount of financial assets. | K85: NÃO | L85: accum_write_offs | M85: LT002_INSTRUMENT.ACCMLTD_WRTFFS_INSTRMNT
A86: V_171 | B86: Financial information | C86: Accumulated impairment amount | D86: Numeric (euro) | E86: The amount of loss allowances that are held against or are allocated to the instrument on the reporting reference date. This data attribute applies to instruments subject to impairment under the applied accounting standard. Under IFRS, the accumulated impairment relates to the following amounts: (i) loss allowance at an amount equal to 12-month expected credit losses; (ii) loss allowance at an amount equal to lifetime expected credit losses. Under GAAP, the accumulated impairment relates to the following amounts: (i) loss allowance at an amount equal to general allowances; (ii) loss allowance at an amount equal to specific allowances. | G86: INSTRUMENT-ACCMLTD_IMPRMNT_INSTRMNT | H86: Sum of LLPs and other allowances | I86: The amount of loss allowances that are held against or are allocated to the instrument on the reporting reference date. This data attribute applies to instruments subject to impairment under the applied accounting standard. Under IFRS, the accumulated impairment relates to the following amounts: (i) loss allowance at an amount equal to 12-month expected credit losses; (ii) loss allowance at an amount equal to lifetime expected credit losses. Under nGAAP, the accumulated impairment relates to the following amounts: (i) loss allowance at an amount equal to specific allowances; (ii) loss allowance at an amount equal to general allowances. | K86: NÃO | L86: accum_impairment_amount | M86: LT002_INSTRUMENT.ACCMLTD_IMPRMNT_INSTRMNT
A88: V_172 | B88: Financial information | C88: Type of impairment | D88: String | E88: This data attribute indicates the type of impairment to which the instrument is subject. Opções: ‣ Stage 1 (IFRS) ‣ Stage 2 (IFRS) ‣ Stage 3 (IFRS) ‣ General allowances (GAAP) ‣ Specific allowances (GAAP) | G88: INSTRUMENT-IMPRMNT_STTS | H88: Impairment status | I88: Type of impairment. | K88: NÃO | L88: type_impairment | M88: LT002_INSTRUMENT.IMPRMNT_STTS ‣ Traduzir o campo "IMPRMNT_STTS" seguindo as parametrizações apresentadas nas sheets: ‣ LT829 - filtrando por campo_conceito = 'IMPRMNT_STTS' e regra_conversao = '1'; ‣ LT830 - filtrando por segmento = 'Exposures to natural persons' e campo_conceito = 'IMPRMNT_STTS'.
A91: V_173 | B91: Financial information | C91: Impairment assessment method | D91: String | E91: The method by which the impairment is assessed, if the instrument is subject to impairment in accordance with applied accounting standards. Opções: ‣ Individually assessed ‣ Collectively assessed | G91: INSTRUMENT-IMPRMNT_ASSSSMNT_MTHD | H91: Impairment assessment method | I91: The method by which the impairment is assessed, if the instrument is subject to impairment in accordance with applied accounting standards. Collective and individual methods are distinguished. | K91: NÃO | L91: impairment_assessment_method | M91: LT002_INSTRUMENT.IMPRMNT_ASSSSMNT_MTHD ‣ Traduzir o campo "IMPRMNT_ASSSSMNT_MTHD" seguindo as parametrizações apresentadas nas sheets: ‣ LT829 - filtrando por campo_conceito = 'IMPRMNT_ASSSSMNT_MTHD' e regra_conversao = '1'; ‣ LT830 - filtrando por segmento = 'Exposures to natural persons' e campo_conceito = 'IMPRMNT_ASSSSMNT_MTHD'.
A94: V_174 | B94: Instrument characteristics | C94: Sources of encumbrance | D94: String | E94: Type of transaction in which the exposure is encumbered in accordance with Implementing Regulation (EU) No 680/2014. An asset will be treated as encumbered if it has been pledged or if it is subject to any form of arrangement to secure, collateralise or credit enhance any instrument from which it cannot be freely withdrawn. Opções: ‣ Central bank funding ‣ Exchange traded derivatives ‣ Over-the-counter derivatives ‣ Deposits – repurchase agreements other than to central banks ‣ Deposits other than repurchase agreements ‣ Debt securities issued – covered bonds securities ‣ Debt securities issued – assetbacked securities ‣ Debt securities issued – other than covered bonds and ABSs ‣ Other sources of encumbrance ‣ No encumbrance | G94: - | H94: - | I94: - | K94: NÃO | L94: sources_encumbrance | M94: LT002_INSTRUMENT.SRCS_ENCMBRNC ‣ Traduzir o campo "SRCS_ENCMBRNC" seguindo as parametrizações apresentadas nas sheets: ‣ LT829 - filtrando por campo_conceito = 'SRCS_ENCMBRNC' e regra_conversao = '1'; ‣ LT830 - filtrando por segmento = 'Exposures to natural persons' e campo_conceito = 'SRCS_ENCMBRNC'.
A97: V_175 | B97: Financial information | C97: Performing status of the instrument | D97: String | E97: The instrument is to be classified on the reporting reference date, in accordance with Implementing Regulation (EU) No 680/2014. Opções: ‣ Non-performing ‣ Performing | G97: INSTRUMENT-PRFRMNG_STTS | H97: Performing status | I97: The instrument is to be classified on the reference date under one of the following categories: performing or non-performing, in accordance with Implementing Regulation (EU) No 680/2014. If the performing status is measured on entity level only all instruments are to be classified according to the status on entity level. | K97: NÃO | L97: perform_status_instrument | M97: LT002_INSTRUMENT.PRFRMNG_STTS ‣ Traduzir o campo "PRFRMNG_STTS" seguindo as parametrizações apresentadas nas sheets: ‣ LT829 - filtrando por campo_conceito = 'PRFRMNG_STTS' e regra_conversao = '1'; ‣ LT830 - filtrando por segmento = 'Exposures to natural persons' e campo_conceito = 'PRFRMNG_STTS'.
... A113: V_183 | B113: Valuation | C113: Accumulated changes in fair value due to credit risk | D113: Numeric (euro) | E113: Accumulated changes in fair value due to credit risk in accordance with Part 2.46 of Annex V to Implementing Regulation (EU) No 680/2014. | G113: INSTRUMENT-ACCMLTD_CHNGS_FV_CR_INSTRMNT | H113: Accumulated changes in fair value due to credit risk | I113: Accumulated changes in fair value due to credit risk in accordance with Part 2.46 of Annex V to Implementing Regulation (EU) No 680/2014. | K113: NÃO | L113: accum_changes_fv_due_cr | M113: LT002_INSTRUMENT.ACCMLTD_CHNGS_FV_CR_INSTRMNT

Sheet NATURALP_COUNTERPARTIES
A1: Instruções SRB | G1: Mapeamento efetuado pela Corporação e respetiva Descrição Loan Tape (LT) | K1: Análise IT
A2: ID | B2: Categoria | C2: Coluna | D2: Tipo de dados | E2: Descrição | G2: Mapeamentos Corporação (LT) | H2: Descrição (LT) | I2: Additional Guidance (LT) | K2: Novo campo na tabela LT003? | L2: Nome do campo no ficheiro | M2: Mapeamento | N2: Notas
A3: V_2 | B3: Identification information | C3: Counterparty Identifier | D3: Alphanumeric | E3: Identifier applied to uniquely identify each counterparty. | G3: ENTITY-ENTTY_ID | H3: Entity ID | I3: An identifier applied by the reporting agent to uniquely identify each counterparty. Each counterparty has a unique and exclusive counterparty identifier. This means that this value will not change over time and can never be used as the counterparty identifier for any other counterparty. | K3: NÃO | L3: counterparty_id | M3: LT003_ENTITY.ENTTY_ID
A4: V_139 | B4: Risk parameters | C4: Probability of default | D4: Numeric. Basis points. | E4: The counterparty’s probability of default over one year, determined in accordance with Articles 160, 163, 179 and 180 of Regulation (EU) No 575/2013. The probability of default (PD) is in accordance with the requirements specific to PD estimation as laid down in the CRR. In the case of PDs produced at the instrument level only (the so-called product PD), the counterparty PD is reported as the exposure weighted average PD of all instruments of the counterparty. If, for a given counterparty, a PD is estimated for both the counterparty and (some of) the products of the counterparty, the counterparty’s PD is to be reported. | G4: ENTITY-PD_CRR_RD | H4: Probability of default according to CRR at reference date | I4: The PD over one year, determined in accordance with Articles 160, 163, 179 and 180 of Regulation (EU) No 575/2013. If the PD is calculated on obligor level then provide the obligor PD. If the PD is calculated on instruments level please provide an EAD weighted average. | K4: NÃO | L4: probability_default | M4: LT003_ENTITY.PD_CRR_RD
A12: V_8 | B12: Risk parameters | C12: Current Internal Credit Rating/Scoring | D12: Numeric / Alphanumeric | E12: Internal credit rating/scoring issued to the Counterparty. | G12: ENTITY-INTRNL_RTNG | H12: Internal rating at reference date | I12: Internal rating at the reference date according to Regulation (EU) No 575/2013. Please also add in sheet "Code List" the list of values used, i.e. bank-internal masterscale. | K12: NÃO | L12: internal_credit_rating | M12: LT003_ENTITY.INTRNL_RTNG
A13: V_10 | B13: Risk parameters | C13: IFRS 9 Probability of default/impairment | D13: Numeric. Basis points | E13: The probability of default/impairment is calculated in accordance with the requirements specific to probability of default (PD) estimation as laid down in the accounting framework. If PDs are produced at the instrument level only, the counterparty’s PD is to be reported as the exposure-weighted average PD across the PDs of all instruments of the counterparty. If, for a given counterparty, PDs are estimated for both the counterparty and (some of) the products of the counterparty, it is the counterparty’s PD which is to be reported. No documento "Feedback Statement in response to the consultation on the SRB valuation data set" é referida a seguinte nota sobre este campo: "‘Data Point V_10’, entitled ‘IFRS 9 Probability of default’, refers to PDs used for accounting purposes, being a 12-month PD for stage 1 exposures and a lifetime PD for stage 2 and 3 exposures as per the accounting framework." | G13: ENTITY-PD_IFRS9_12M_RD | H13: 12-month PD at reporting date according to IFRS 9 | I13: 12-month PD at reference date which is used by the bank for computation of stage 1 ECL or for SICR assessment if bank use 12 month proxy for staging. If the PD is calculated on instruments level please provide an EAD weighted average. | K13: SIM | L13: ifrs9_prob_default_impairment | M13: Necessário validar a necessidade de criar um novo campo ("PD misto" ) na LT002_INSTRUMENT dado que se solicita um "misto" entre a PD 12m (PD12M_IFRS9) e a PD lifetime (PD_LT_IFRS9), campos já existentes nessa tabela. A lógica a validar será: -Se stage 1: Se loss_type LIKE 'Lifetime expected credit losses%' selecionar PD_LT_IFRS9 da tabela BU_IFRS9.IFRS9_OUT_EXPECTED_LOSS_REPORTING, caso contrário selecionar PD12M_IFRS9 da tabela BU_IFRS9.IFRS9_OUT_EXPECTED_LOSS_REPORTING -Se stage 2: selecionar PD_LT_IFRS9 da tabela BU_IFRS9.IFRS9_OUT_EXPECTED_LOSS_REPORTING -Se stage 3: forçar 1 Sugere-se criar o campo na LT002_INSTRUMENT e não na LT003_ENTITY porque após consultar a a LT003_ENTITY verificou-se que existia o campo PD_IFRS9_12M_RD para o qual é usada a LT005_INSTR_ENT para identificar todos os contratos onde o cliente é o 1º Titular, de seguida para cada cliente aplica-se uma média ponderada da PD em relação ao EAD (porque cada cliente pode ter vários contratos). Assim sugere-se replicar esta lógica para o novo campo "PD misto" adicionado na LT002_INSTRUMENT de forma a poder ser criado também um novo campo "PD misto" na LT003_ENTITY. Lógica proposta para a criação do novo campo na LT002: CASE WHEN IMPRMNT_STTS_INSTRMNT = '23' --(Stage 1) THEN IF( loss_type LIKE 'Lifetime expected credit losses%', PD_LT_IFRS9, PD12M_IFRS9) WHEN IMPRMNT_STTS_INSTRMNT = '24' --(Stage 2) THEN PD_LT_IFRS9 WHEN IMPRMNT_STTS_INSTRMNT = '25' --(Stage 3) THEN 1 ELSE 'N/A' END as PD_IFRS9_12M_LFTM_RD WHERE IMCATF046_FLAG_FECHO.CMES = REF_DATE Lógica proposta para a criação do novo campo na LT003: 1) Identificar contratos onde o cliente é o 1º Titular: LT005_INSTR_ENT WHERE CRELACAO_CL_CNT = '1' AND CSEQUENCIA_REL = '00001' 2) Aplicar o seguinte cáclulo por entidade: CASE WHEN SUM(IFRS9_EAD)<> 0 THEN SUM(PD_IFRS9_12M_LFTM_RD * IFRS9_EAD) / SUM(IFRS9_EAD) ELSE AVG(PD_IFRS9_12M_LFTM_RD) END as ifrs9_prob_default_impairment | N13: Em análise
A24: V_11 | B24: Risk parameters | C24: Probability of default (others) | D24: Numeric. Basis points | E24: Applicable only to institutions neither using models for estimating IFRS 9 impairments nor CRR IRB models. These institutions should maintain records of probabilities of default or scores provided by scoring/rating models. In the case of PDs produced at the instrument level only, the counterparty’s PD is to be reported as the exposure-weighted average PD across the PDs of all instruments of the counterparty. If, for a given counterparty, PDs are estimated for both the counterparty and (some of) the products of the counterparty, it is the counterparty’s PDs which is to be reported. | G24: - | H24: - | I24: - | K24: SIM | L24: probability_default_others | M24: Reportar sempre: 11111111111
A25: V_184 | B25: Counterparty characteristics | C25: Counterparty role | D25: String | E25: The roles that counterparties assume in relation to an instrument recorded in the instrument dataset are recorded in the counterparty-instrument dataset. Opções: ‣ Creditor ‣ Debtor ‣ Servicer ‣ Originator | G25: Not applicable: To be reported as "N/A". This information will be availabe in "02_04_nat_instr_count" table | H25: - | I25: - | K25: SIM | L25: counterparty_role | M25: Reportar sempre: 'N/A'
A26: V_185 | B26: Financial information | C26: Default status of the counterparty | D26: String | E26: Identification of the default status of the counterparty. Categories describing the motives for which the counterparty can be in default in accordance with Article 178 of Regulation (EU) No 575/2013. Opções: ‣ Not in default ‣ Default because unlikely to pay ‣ Default because more than 90/180 days past due ‣ Default because both unlikely to pay and more than 90/180 days past due | G26: ENTITY-DFLT_STTS | H26: Default status of the entity | I26: Identification of the default status of the counterparty. Categories describing the motives for which the counterparty can be in default in accordance with Article 178 of Regulation (EU) No 575/2013. For retail only: If default classification performed on instrument level then Entity is classified as defaulted when at least one instrument is classified as defaulted. For corporate, SME, CRE and LF: if default classification performed on instrument level then entity level is "not applicable". | K26: NÃO | L26: default_status_counterparty | M26: LT003_ENTITY.DFLT_STTS ‣ Traduzir o campo "DFLT_STTS" seguindo as parametrizações apresentadas nas sheets: ‣ LT829 - filtrando por campo_conceito = 'DFLT_STTS' e regra_conversao = '1'; ‣ LT830 - filtrando por segmento = 'Exposures to natural persons', campo_conceito = 'DFLT_STTS'.
A29: V_186 | B29: Financial information | C29: Date of the default status of the counterparty | D29: DD/MM/YYYY | E29: The date on which the default status, as reported in the data attribute “Default status of the counterparty”, is considered to have arisen. | G29: ENTITY-DT_DFLT_STTS | H29: Date of default status | I29: The date on which the default status, as reported in the data attribute “Default status”, is considered to have arisen. If "Not in default" since inception then this attribute is to be reported equally to the inception date. If default classification performed on instrument level then Entity is classified as defaulted when at least one instrument is classified as defaulted. If more than one Instrument is classified as defaulted then the earliest date has to be provided. The definition of default is aligned with Art 178 of Regulation (EU) No 575/2013. | K29: NÃO | L29: date_default_status_counterparty | M29: LT003_ENTITY.DT_DFLT_STTS

Sheet NATURALP_PROTECTIONS
A1: Instruções SRB | G1: Mapeamento efetuado pela Corporação e respetiva Descrição Loan Tape (LT) | K1: Análise IT
A2: ID | B2: Categoria | C2: Coluna | D2: Tipo de dados | E2: Descrição | G2: Mapeamentos Corporação (LT) | H2: Descrição (LT) | I2: Additional Guidance (LT) | K2: Novo campo na tabela LT004? | L2: Nome do campo no ficheiro | M2: Mapeamento | N2: Notas
A3: V_12 | B3: Identification information | C3: Protection identifier | D3: Alphanumeric | E3: An identifier applied to uniquely identify each protection/collateral used to secure the instrument. | G3: PROTECTION-PRTCTN_ID | H3: Protection ID | I3: An identifier applied by the reporting agent to uniquely identify each protection used to secure the instrument. Each protection must have one protection identifier. This value will not change over time and cannot be used as the protection identifier for any other protection. | K3: NÃO | L3: protection_id | M3: LT004_PROTECTION.PRTCTN_ID
A7: V_219 | B7: Identification information | C7: Protection provider identifier | D7: Alphanumeric | E7: The protection provider identifier is the counterparty identifier of the counterparty that grants protection against a contractually agreed negative credit event and that is obliged to make payments to the creditor if the debtor fails to meet the obligation to make repayments arising under the instrument secured by the protection item. | G7: PROTECTION-PRTCTN_PRVDR_ID | H7: Protection Provider ID (Guarantor) | I7: Counterparty identifier for the protection provider. If the protection provider is not a legal entity, the protection provider identifier is not required to be reported. | K7: NÃO | L7: protection_provider_id | M7: LT004_PROTECTION.PRTCTN_PRVDR_ID
A8: V_1 | B8: Identification information | C8: Instrument Identifier | D8: Alphanumeric | E8: An identifier applied to uniquely identify each instrument. Each instrument must have one instrument identifier. | G8: Not applicable: To be reported as "N/A". This information will be availabe in "02_05_nat_instr_prot" table | H8: - | I8: - | K8: SIM | L8: instrument_id | M8: Reportar sempre: 'N/A'
A12: V_187 | B12: Identification information | C12: Type of collateral | D12: String | E12: The AnaCredit item “type of protection” (Section 9.4.3. of the AnaCredit Reporting Manual Part II – Datasets and data attributes) provides a breakdown of collaterals eligible in accordance with the CRR. The proposed breakdown adds several categories. Options: ‣ Gold ‣ Currency and deposits ‣ Securities ‣ Loans ‣ Equity and investment fund shares or units ‣ Credit derivatives ‣ Financial guarantees other than credit derivatives ‣ Trade receivables ‣ Life insurance policies pledged ‣ Residential real estate collateral ‣ Offices and commercial premises ‣ Commercial real estate collateral ‣ Other physical collateral ‣ Other protection ‣ Hotels & entertainment ‣ Infrastructure projects ‣ Factories – Warehouses ‣ Equipment & machinery ‣ Automotive ‣ Aircraft ‣ Shipping | G12: PROTECTION-TYP_PRTCTN | H12: Protection type | I12: Type of protection received, irrespective of its eligibility for credit risk mitigation. | K12: NÃO | L12: type_collateral | M12: LT004_PROTECTION.TYP_PRTCTN ‣ Traduzir o campo "TYP_PRTCTN" seguindo as parametrizações apresentadas nas sheets: ‣ LT829 - filtrando por campo_conceito = 'TYP_PRTCTN' e regra_conversao = '1'; ‣ LT830 - filtrando por segmento = 'Exposures to natural persons' e campo_conceito = 'TYP_PRTCTN'.
A15: V_14 | B15: Size collateral | C15: Building Area (M2) | D15: Numeric | E15: Building area of the building in square meters. Only applicable to Residential real estate collateral, Offices and commercial premises, Commercial real estate collateral, Hotels & entertainment, Factories – warehouses. | G15: - | H15: - | I15: - | K15: SIM gross_area | L15: building_area_m2 | M15: Campo "narbrut" da tabela cd_garantias.gt009_bens_imov
A16: V_15 | B16: Size collateral | C16: Land Area (M2) | D16: Numeric | E16: Land area of the property in square meters. | G16: - | H16: - | I16: - | K16: SIM land_area | L16: land_area_m2 | M16: Campo "narterr" da tabela cd_garantias.gt009_bens_imov
A17: V_16 | B17: Location | C17: Property postcode | D17: Numeric | E17: Postcode where the property is located. Only applicable to Residential real estate collateral, Offices and commercial premises, Commercial real estate collateral, Hotels & entertainment, Factories – Warehouses. | G17: PROTECTION-RL_ESTT_PST_CD | H17: Post code / ZIP | I17: Post code / ZIP. | K17: NÃO | L17: property_postcode | M17: LT004_PROTECTION.RL_ESTT_PST_CD
A18: V_17 | B18: Lien | C18: Lien position | D18: Numeric | E18: The highest ranking position(s) in relation to the collateral held by the counterparty to secure the facility. In case the facility has several liens on one collateral, the highest claim is reported in this data field. | G18: - | H18: - | I18: - | K18: SIM | L18: lien_position | M18: Reportar sempre: 1
A19: V_188 | B19: Valuation | C19: Date of protection value | D19: DD/MM/YYYY | E19: The date on which the latest appraisal or valuation of the protection was carried out prior to the reporting reference date, i.e. the date on which the amount reported in the attribute “protection value” of the value type reported in the attribute “type of protection value” was established under the valuation method reported in the attribute protection valuation approach. | G19: PROTECTION-DT_PRTCTN_VL | H19: Date of protection value | I19: The date on which the latest appraisal or valuation of the protection was carried out prior to the reporting reference date. | K19: NÃO | L19: date_protection_value | M19: LT004_PROTECTION.DT_PRTCTN_VL
A20: V_220 | B20: Valuation | C20: Protection value | D20: Numeric (euro) | E20: The amount of the protection value is the monetary value of the protection that was established at the latest valuation date | G20: PROTECTION-PRTCTN_VL | H20: Appraised market value | I20: The amount of the protection value as established for the relevant “Type of protection value” following the valuation approach. Market value from the appraisal without any haircut, in case a haircut is applied by the bank this should be in field HRCT_MV. In case of Guarantees, guaranteed amount. In case of Financial Assets, Market value of the asset. | K20: NÃO | L20: protection_value | M20: LT004_PROTECTION.PRTCTN_VL
A21: V_189 | B21: Protection characteristics | C21: Maturity date of the protection | D21: DD/MM/YYYY | E21: The contractual maturity date of the protection, which is the earliest date at which the protection may terminate or be terminated, taking into account any agreements amending initial contracts. | G21: PROTECTION-DT_MTRTY_PRTCTN | H21: Maturity date of the protection | I21: The contractual maturity date of the protection, which is the earliest date at which the protection may terminate or be terminated, taking into account any agreements amending initial contracts. | K21: NÃO | L21: maturity_date_protection | M21: LT004_PROTECTION.DT_MTRTY_PRTCTN
A22: V_190 | B22: Valuation | C22: Original protection value | D22: Numeric (euro) | E22: The monetary value of the protection item that was established at the date when the protection item was originally received as a credit protection. | G22: PROTECTION-ORGNL_PRTCTN_VL | H22: Original protection value (at inception) | I22: The original protection value is the monetary value of the protection item that was established at the date when the protection item was originally received as a credit protection. | K22: NÃO | L22: original_protection_value | M22: LT004_PROTECTION.ORGNL_PRTCTN_VL
... A27: V_194 | B27: Lien | C27: Third-party priority claims against the protection | D27: Numeric (euro) | E27: The maximum amount of any existing higher ranked liens with respect to third parties other than the observed agent against the protection. | G27: Not applicable: To be reported as "11111111111". This information will be availabe in "02_05_nat_instr_prot" table | H27: - | I27: - | K27: SIM | L27: thirdparty_claims_protection | M27: Reportar sempre: '0'

Sheet NATURALP_INSTRUMENT_COUNTERPART
A1: Instruções SRB | G1: Mapeamento efetuado pela Corporação e respetiva Descrição Loan Tape (LT) | K1: Análise IT
A2: ID | B2: Categoria | C2: Coluna | D2: Tipo de dados | E2: Descrição | G2: Mapeamentos Corporação (LT) | H2: Descrição (LT) | I2: Additional Guidance (LT) | K2: Novo campo na tabela LT005? | L2: Nome do campo no ficheiro | M2: Mapeamento | N2: Notas
A3: V_1 | B3: Identification information | C3: Instrument Identifier | D3: Alphanumeric | E3: An identifier applied to uniquely identify each instrument. Each instrument must have one instrument identifier | G3: INSTR_ENTITY-INSTRMNT_ID | H3: Instrument ID | I3: An identifier applied by the reporting agent to uniquely identify each instrument under a single contract. Each instrument must have one instrument identifier. This value will not change over time and cannot be used as the instrument identifier for any other instrument under the same contract. Supervised Insitutions are asked to furnish the INSTRMNT_ID with the exact same value as it is reported to AnaCredit (or any similar central credit register). If this is not available, the value shall be reported as it is internally used. If an instrument is not reported to AnaCredit but requested for the purposes of the on-site inspection please provide the bank-internally used value. Foreign Key from INSTRUMENT table. | K3: NÃO | L3: instrument_id | M3: LT005_INSTR_ENT.INSTRMNT_ID
A7: V_2 | B7: Identification information | C7: Counterparty Identifier | D7: Alphanumeric | E7: Identifier applied to uniquely identify each counterparty. | G7: INSTR_ENTITY-ENTTY_ID | H7: Entity ID | I7: An identifier applied by the reporting agent to uniquely identify each counterparty. Each counterparty has a unique and exclusive counterparty identifier. This means that this value will not change over time and can never be used as the counterparty identifier for any other counterparty. Foreign key from ENTITY table. | K7: NÃO | L7: counterparty_id | M7: LT005_INSTR_ENT.ENTTY_ID
A8: V_167 | B8: Financial information | C8: Joint liabilities amount | D8: Numeric (euro) | E8: Outstanding nominal amount for which each debtor is liable in relation to a single instrument where there are two or more debtors. | G8: INSTR_ENTITY-JNT_LBLTY_AMNT | H8: Joint-liability amount | I8: Outstanding nominal amount for which each debtor is liable in relation to a single instrument where there are two or more debtors. In the case of instruments where there is only one debtor, please report "not applicable" using the respective fall-back parameters. | K8: NÃO | L8: joint_liabilities_amount | M8: LT005_INSTR_ENT.JNT_LBLTY_AMNT
A9: V_184 | B9: Counterparty characteristics | C9: Counterparty role | D9: String | E9: The roles that counterparties assume in relation to an instrument recorded in the instrument dataset are recorded in the counterparty-instrument dataset. Opções: ‣ Creditor ‣ Debtor ‣ Servicer ‣ Originator | G9: - | H9: - | I9: - | K9: SIM | L9: counterparty_role | M9: ‣ Este campo deve ser obtido a partir do campo "tipo_conta" da tabela fr802_pl_contas: 1. Ligar o universo à tabela fr802_pl_contas através do campo "conta", obtendo o campo "tipo_conta"; 2. Se para a mesma conta existir mais do que um "tipo_conta" distinto, deve-se trazer apenas um deles segundo a seguinte ordem de prioridades 'A', 'EA', 'P', 'EP'. Se nenhum dos 'tipo_conta' for uma das opções ('A', 'EA', 'P', 'EP') então é indifrente qual é utilizado, de forma a que se pode trazer por exemplo o 1º encontrado. ‣ Traduzir o campo "tipo_conta" seguindo a parametrização apresentada na sheet 'LT831' filtrando por tabela_conceito = 'LT005_INSTR_ENT' e campo_conceito = 'COUNTERPARTY_ROLE'

Sheet NATURALP_INSTRUMENT_PROTECTION
A1: Instruções SRB | G1: Mapeamento efetuado pela Corporação e respetiva Descrição Loan Tape (LT) | K1: Análise IT
A2: ID | B2: Categoria | C2: Coluna | D2: Tipo de dados | E2: Descrição | G2: Mapeamentos Corporação (LT) | H2: Descrição (LT) | I2: Additional Guidance (LT) | K2: Novo campo na tabela LT006? | L2: Nome do campo no ficheiro | M2: Mapeamento | N2: Notas
A3: V_1 | B3: Identification information | C3: Instrument Identifier | D3: Alphanumeric | E3: An identifier applied to uniquely identify each instrument. Each instrument must have one instrument identifier | G3: INSTR_PROTECTION-INSTRMNT_ID | H3: Instrument ID | I3: An identifier applied by the reporting agent to uniquely identify each instrument under a single contract. Each instrument must have one instrument identifier. This value will not change over time and cannot be used as the instrument identifier for any other instrument under the same contract. Supervised Insitutions are asked to furnish the INSTRMNT_ID with the exact same value as it is reported to AnaCredit (or any similar central credit register). If this is not available, the value shall be reported as it is internally used. If an instrument is not reported to AnaCredit but requested for the purposes of the on-site inspection please provide the bank-internally used value. Foreign Key from INSTRUMENT table. | K3: NÃO | L3: instrument_id | M3: LT006_INSTR_PROT.INSTRMNT_ID
A7: V_12 | B7: Identification information | C7: Protection identifier | D7: Alphanumeric | E7: An identifier applied to uniquely identify each protection/collateral used to secure the instrument. | G7: INSTR_PROTECTION-PRTCTN_ID | H7: Protection ID | I7: An identifier applied by the reporting agent to uniquely identify each protection used to secure the instrument. Each protection must have one protection identifier. This value will not change over time and cannot be used as the protection identifier for any other protection. Foreign Key from PROTECTION table. | K7: NÃO | L7: protection_id | M7: LT006_INSTR_PROT.PRTCTN_ID
A11: V_193 | B11: Valuation | C11: Protection allocated value | D11: Numeric (euro) | E11: The maximum amount of the protection value that can be considered as credit protection for the instrument. The amount of the existing third parties or observed agent priority claims against the protection must be excluded in the protection allocated value. | G11: INSTR_PROTECTION-PRTCTN_ALLCTD_VL | H11: Protection allocated value | I11: The maximum amount of the protection value that can be considered as credit protection for the instrument. The amount of the existing third parties or observed agent priority claims against the protection must be excluded in the protection allocated value. | K11: NÃO | L11: protection_allocated_value | M11: LT006_INSTR_PROT.PRTCTN_ALLCTD_VL
A12: V_194 | B12: Lien | C12: Third-partypriority claims against the protection | D12: Numeric (euro) | E12: The maximum amount of any existing higher ranked liens with respect to third parties other than the observed agent against the protection. | G12: INSTR_PROTECTION-THRD_PRTY_PRRTY_CLMS | H12: Third party priority claims against the protection | I12: The maximum amount of any existing higher ranked liens with respect to third parties other than the observed agent against the protection. | K12: NÃO | L12: thirdparty_claims_protection | M12: LT006_INSTR_PROT.THRD_PRTY_PRRTY_CLMS

Sheet OFF-BALANCE DATA SETS
A1: SRB OFF-BALANCE SHEET EXPOSURES DATA SETS Off-balance sheet exposures do not fall under the scope of the AnaCredit reporting requirements. The SRB Valuation Data Sets for off-balance sheet exposures introduces adhoc data points for these exposures and combine data from difference sources: existing SRB Data Sets for exposures to legal persons and the AnaCredit database. Additionally a set of ad hoc data points covers basic features of off-balance sheet exposures. Off-balance sheet exposures shall include the off-balance sheet items as listed in Annex I of CRR. This data set does not include data on credit derivatives, which are covered by the SRB Valuation Data Set on derivatives. Serão produzidos cinco ficheiros de report referentes a Off-Balance Sheet Exposures: ‣ SRB Instruments Data Set for off-balance sheet exposures (OFFBAL_INSTRUMENTS); ‣ SRB Counterparties Data Set for off-balance sheet exposure (OFFBAL_COUNTERPARTIES); ‣ SRB Protection received Data Set for off-balance sheet exposures (OFFBAL_PROTECTIONS); ‣ SRB Instrument/Counterparty mapping Data Set for off-balance sheet exposures (OFFBAL_INSTRUMENT_COUNTERPARTY); ‣ SRB Instrument/Protection mapping Data Set for off-balance sheet exposures (OFFBAL_INSTRUMENT_PROTECTION);
A2: SRB OFF-BALANCE SHEET EXPOSURES DATA SETS Os requisitos de 'Off-balance sheet exposures', não se enquadram no âmbito do report da AnaCredit. O conjunto de dados de avaliação do CUR (SBR) para posições em risco extrapatrimoniais introduz pontos de dados para estas exposições e combinar dados de diferentes fontes: existentes Conjuntos de dados do CUR para posições em risco sobre pessoas coletivas e a base de dados AnaCredit. Além disso, um conjunto dos pontos de dados ad hoc abrange as características básicas das posições em risco extrapatrimoniais. As posições em risco extrapatrimoniais devem incluir os elementos extrapatrimoniais enumerados no anexo I do CRR. Este conjunto de dados não inclui dados sobre derivados de crédito, que são abrangidos pelo conjunto de dados de avaliação do CUR sobre derivados. Serão produzidos três ficheiros de report referentes a Natural Persons: ‣ SRB Instruments Data Set for off-balance sheet exposures (VDS_OUT_OFFBAL_INSTRUMENTS); ‣ SRB Counterparties Data Set for off-balance sheet exposure (VDS_OUT_OFFBAL_COUNTERPARTIES); ‣ SRB Protection received Data Set for off-balance sheet exposures (VDS_OUT_OFFBAL_PROTECTIONS).

Sheet OFFBAL_INSTRUMENTS
A1: Instruções SRB | G1: Mapeamento efetuado pela Corporação e respetiva Descrição Loan Tape (LT) | K1: Análise IT
A2: ID | B2: Categoria | C2: Coluna | D2: Tipo de dados | E2: Descrição | G2: Mapeamentos Corporação (LT) | H2: Descrição (LT) | I2: Additional Guidance (LT) | K2: Novo campo na tabela LT002? | L2: Nome do campo no ficheiro | M2: Mapeamento | N2: Notas
A3: V_1 | B3: Identification information | C3: Instrument Identifier | D3: Alphanumeric | E3: An identifier applied to uniquely identify each instrument. Each instrument must have one instrument identifier. | G3: INSTRUMENT-INSTRMNT_ID | H3: Instrument ID | I3: An identifier applied by the reporting agent to uniquely identify each instrument under a single contract. Each instrument must have one instrument identifier. This value will not change over time and cannot be used as the instrument identifier for any other instrument under the same contract. Supervised Insitutions are asked to furnish the INSTRMNT_ID with the exact same value as it is reported to AnaCredit (or any similar central credit register). If this is not available, the value shall be reported as it is internally used. If an instrument is not reported to AnaCredit but requested for the purposes of the on-site inspection please provide the bank-internally used value. | K3: NÃO | L3: instrument_id | M3: LT002_INSTRUMENT.INSTRMNT_ID
A7: V_2 | B7: Identification information | C7: Counterparty Identifier | D7: Alphanumeric | E7: Identifier applied to uniquely identify each counterparty. | G7: Not applicable: To be reported as "N/A". This information will be availabe in "03_04_off_instr_count" table | H7: - | I7: - | K7: SIM | L7: counterparty_id | M7: Reportar sempre: 'N/A'
A8: V_139 | B8: Identification information | C8: Reporting data identifier | D8: Alphanumeric | E8: The reporting agent identifier is the counterparty identifier of the reporting agent which reports the data. | G8: INSTRUMENT-COD_SOC | H8: Entity code of the informing society. | I8: Cargabal code or internal identifier of the informing society. | K8: NÃO | L8: reporting_data_id | M8: LT002_INSTRUMENT.COD_SOC
A9: V_140 | B9: Identification information | C9: Observed agent identifier | D9: Alphanumeric | E9: The observed agent identifier is the counterparty identifier of the observed agent (i.e. an institutional unit of the reporting agent) whose data are reported by the reporting agent. | G9: INSTRUMENT-OBSRVD_AGNT_ID | H9: Observed agent identifier | I9: Counterparty identifier for the observed agent. If there are several observed agents to be reported please separate by comma (,). | K9: NÃO | L9: observed_agent_id | M9: LT002_INSTRUMENT.OBSRVD_AGNT_ID
A10: V_141 | B10: Identification information | C10: Contract identifier | D10: Alphanumeric | E10: An identifier applied by the reporting agent to uniquely identify each contract. The contract identifier refers to the credit agreement between two or more parties under which the instrument is created. | G10: INSTRUMENT-CNTRCT_ID | H10: Contract ID | I10: An identifier applied by the reporting agent to uniquely identify each contract. Each contract must have one contract identifier. This value will not change over time and cannot be used as the contract identifier for any other contract. | K10: NÃO | L10: contract_id | M10: LT002_INSTRUMENT.CNTRCT_ID
A14: V_222 | B14: Exposure class | C14: Type | D14: String | E14: Type of commitment or guarantee as per FINREP classification. Options: ‣ Loan commitments given ‣ Financial guarantees given ‣ Other commitments given | G14: - | H14: - | I14: - | K14: SIM | L14: type | M14: ‣ Este campo deve ser obtido a partir da tabela fr802_pl_contas ligando o universo de contratos FINREP à tabela fr802_pl_contas através do campo 'conta', filtrando a tabela pelo campo carteira_contabilistica = 'garantias e compromissos concedidos', obtendo o campo "produto". METODOLOGIA DE CRUZAMENTO: Replicar a lógica de ligação com a FR802_PL_CONTAS já aplicada para outros campos do Modelo Loan Tape. ‣ Traduzir o campo "produto" seguindo a parametrização apresentada na sheet 'LT831' filtrando por tabela_conceito = 'LT002_INSTRUMENT' e campo_conceito = 'TYPE'
A15: V_3 | B15: Exposure class | C15: CRR Exposure class | D15: String | E15: The exposures classes for the calculation of RWAs for credit risks are as follows (not applicable when exposures are classified in the CRR trading book as defined in Article 4(1)(86) of Regulation (EU) No 575/2013): Where a bank uses the standardised approach: ‣ Central governments or central banks (SCENGOV) ‣ Regional governments or local authorities (SREGGOV) ‣ Public sector entities (SPUBSEC) ‣ Multilateral development banks (SDEVBAN) ‣ International organisation (SINTORG) ‣ Institutions (SINSTIT) ‣ Corporates (SCORPOR) ‣ Retail (SRETAIL) ‣ Secured by mortgages and immovable property (SSECMOR) ‣ Defaulted (SDEFAUL) ‣ High risk (SHIGHRI) ‣ Covered bonds (SCOVBON) ‣ Items representing securitization positions ‣ Institutions and corporates with a short term credit assessment (SSHOTER) ‣ Collective investment undertakings (SCOLINV) ‣ Equity (SEQUITY) ‣ Other (SOTHERI) Quando um banco utiliza a abordagem IRB: ‣ Central governments and central banks (ICENGOV) ‣ Institutions (IINSTIT) ‣ Corporates (ICORPOR) ‣ Retail (IRETAIL) ‣ Equity (IEQUITY) ‣ Items representing securitization positions ‣ Other non-credit-obligation assets (IOTHERC) | G15: - | H15: - | I15: - | K15: SIM | L15: crr_exposure_class | M15: ‣ Utilizar o campo "segmento_corep_final" da tabela ct013_rwa_princ; Nota: Os códigos "segmento_corep_final" seguem sempre a mesma estrutura, começam com um caracter que identifica se é IRB (I_...) ou Standard (S_...) e de seguida um numérico (ex. I_3.1, I_5.1, S_1.0). ‣ Para o mesmo contrato este campo pode retornar vários códigos "segmento_corep_final" distintos, de seguida estão os passos que permitem resolver esta ambiguidade: 1. Deve seguir a lógica do campo RWA_MTHD, de momento a lógica é, se existir IRB e Standard então trazer informação relativa a IRB; 2. Se mesmo aplicando o passo 1 ainda existirem vários códigos "segmento_corep_final" distintos (vários códigos IRB ou vários códigos Standard) então: recuperar o código "segmento_corep_final" com o menor numérico associado. ‣ Traduzir o campo "segmento_corep_final" seguindo a parametrização apresentada na sheet 'LT831' filtrando por tabela_conceito = 'LT002_INSTRUMENT' e campo_conceito = 'CRR_EXPOSURE_CLASS' Exemplo: O contrato A tem associados os seguintes códigos "segmento_corep_final" distintos: I_3.1, I_5.1, S_1.0: 1. Remover o Standard: I_3.1, I_5.1; 2. Ficar com o menor numérico: I_3.1. Comentários IT: '‣ Proposta: Consumir o campo "segmento_corep_final" da tabela ct013_rwa_princ, tendo em atenção que se tem de manter a lógica aplicada no campo LT "RWA_MTHD" (se for IRB ou Standard), para resolver os casos em que para o mesmo contrato temos mais do que segmento corep (IRB e Standard). Nota existem contratos que têm mais do que um segmento corep IRB ou Standard ou seja tem de haver uma lógica de selecionar o mais significativo pois só podemos reportar um valor neste campo). ‣ No Loan Tape para cálculo do LGD que vem da ct013_rwa_princ, quando existe IRB e STD, escolhe-se IRB. ‣ Segundo Email de Pedro Mendes com a resposta da Corporação (26/03/2024 17:28), no caso de existir mais do que 1 CRR Exposure class para o mesmo contrato, é permitido reportar o mais significativo dos dois por valor ou os dois separados por “,” colocando o mais significativo primeiro. ‣ Analisar documento 'BS_Tabelas_Temporárias_Loan_Tape.xlsx' para consultar as regras de seleção aplicadas no campo RWA_MTHD. ‣ Reunião Pedro Mendes, Luís Capitão-Mor 05-11-2024: Foi definida a regra para este campo, como dito anteriormente: - Deve seguir a lógica do campo RWA_MTHD, de momento a lógica é, se existir IRB e Standard então trazer informação relativa a IRB; - Para os casos em que temos mais do que um "segmento_corep_final" IRB ou Standard, foram propostas duas soluções, uma seria utilizar o campo "EAD_FINAL_BRUTA" também da tabela ct013_rwa_pric como fator de peso, recuperando o "segmento_corep_final" associado ao maior "EAD_FINAL_BRUTA" (mais significativo). A segunda solução, mais simples, seria simplesmente recuperar o código "segmento_corep_final" com a numeração mais baixa, por exemplo se um contrato tiver os códigos "segmento_corep_final" I_3.1, I_5.1 ficamos apenas com o I_3.1. Optou-se pela segunda solução. ‣ Query que demonstra que para um contrato FINREP pode haver mais do que um 'segmento_corep_final' tanto para a approach 'IRB' como para a 'Standard': SELECT contract_id_fr, --ct013.s1emp,ct013.contra1, GROUP_CONCAT(DISTINCT ct013.segmento_corep_final) as segmento_corep_final_conc, --GROUP_CONCAT(ct013.segmento_corep_final) as segmento_corep_final_conc, --GROUP_CONCAT(CAST(ct013.ead_final_bruta AS STRING)) as ead_final_bruta_conc, COUNT(*) as cnt, COUNT(DISTINCT ct013.segmento_corep_final) as cnt_dist FROM ( SELECT fr004.contract_id_fr, s1emp, contra1 FROM ( SELECT DISTINCT CONCAT(cempresa,cbalcao,cnumecta,zdeposit) as contract_id_fr FROM cd_captools.fr004_cto WHERE ref_date = '2024-08-31' ) as fr004 --6211142 LEFT JOIN ( SELECT CONCAT(cempresa_fr,cbalcao_fr,cnumecta_fr,zdeposit_fr) as contract_id_fr, CONCAT(cempresa,cbalcao,cnumecta,zdeposit) as contract_id_ct FROM cd_captools.kt_chaves_finrep WHERE ref_date = '2024-08-31' ) as chaves_finrep ON chaves_finrep.contract_id_fr = fr004.contract_id_fr --6211142 LEFT JOIN ( SELECT s1emp, contra1, CONCAT(cempresa,cbalcao,cnumecta,zdeposit) as contract_id_ct FROM cd_captools.kt_chaves_bdr WHERE ref_date = '2024-08-31' ) as chaves_bdr ON chaves_bdr.contract_id_ct = chaves_finrep.contract_id_ct --2046835 WHERE chaves_bdr.contract_id_ct IS NOT NULL GROUP BY contract_id_fr, s1emp, contra1 ) as core --2046835 DIST fr --2047298 nº total LEFT JOIN ( SELECT s1emp, contra1, segmento_corep_final, ead_final_bruta FROM cd_captools.ct013_rwa_princ WHERE ref_date = '2024-08-31' ) as ct013 ON core.s1emp = ct013.s1emp AND core.contra1 = ct013.contra1 WHERE ct013.s1emp IS NOT NULL GROUP BY contract_id_fr --GROUP BY ct013.s1emp, ct013.contra1 ORDER BY cnt_dist DESC
A18: V_4 | B18: Exposure class | C18: FINREP Exposure class | D18: String | E18: Classification of the facility (exposure class) as defined in ITS 680/2014 Annex V Instructions FINREP (Counterparty breakdown). Options: ‣ Central banks ‣ Central governments ‣ Credit institutions ‣ Other financial corporations ‣ Non-financial corporations ‣ Households | G18: - | H18: - | I18: - | K18: NÃO | L18: finrep_exposure_class | M18: LT002_INSTRUMENT.INTRNL_SGMNT ‣ Traduzir o campo "INTRNL_SGMNT" seguindo as parametrizações apresentadas nas sheets: ‣ LT829 - filtrando por campo_conceito = 'INTRNL_SGMNT' e regra_conversao = '1'; ‣ LT830 - filtrando por segmento = 'Off-balance sheet exposures' e campo_conceito = 'INTRNL_SGMNT'.
A21: V_23 | B21: Risk parameters | C21: Credit conversion factor | D21: Numeric. Basis points | E21: Credit conversion factor as defined by the CRR. | G21: INSTRUMENT-CCF | H21: Credit conversion factor (CCF) according to CRR | I21: Credit conversion factor according to regulation (EU) No 575/2013. | K21: NÃO | L21: credit_conversion_factor | M21: LT002_INSTRUMENT.CCF
A29: V_5 | B29: Risk parameters | C29: Total Risk Exposure Amount | D29: Numeric (euro) | E29: The total risk exposure amount of the instrument, calculated according to Articles 92(3) and 92(4) of Regulation (EU) No 575/2013 (CRR), where applicable. | G29: INSTRUMENT-RWA | H29: RWA | I29: RWA according to Regulation (EU) No 575/2013. | K29: NÃO | L29: total_risk_exposure_amount | M29: LT002_INSTRUMENT.RWA
A32: V_6 | B32: Risk parameters | C32: CRR Loss given default | D32: Numeric (euro) | E32: Current level of the ‘Loss given default’ of the loan, determined in accordance with Articles 161, 164, 179 and 181 of Regulation (EU) No 575/2013. | G32: INSTRUMENT-LGD | H32: Regulatory LGD | I32: If differences between regulatory and internal LGD exist, use regulatory LGD (according to Regulation (EU) No 575/2013). In particular, in IRB-F use regulatory LGD values. | K32: NÃO | L32: crr_loss_given_default | M32: LT002_INSTRUMENT.LGD
A40: V_7 | B40: Risk parameters | C40: IFRS 9 Loss given default | D40: Numeric (euro) | E40: Current level of the ‘Loss given default’ of the loan determined for accounting purposes. | G40: INSTRUMENT-IFRS9_LGD | H40: IFRS 9 accounting LGD | I40: IFRS 9 accounting Loss Given Default as at reference date for defaulted and non-defaulted exposures. In case the bank models time-depended LGD variable for non-defaulted exposures then 12-month LGD as at reference date regardless the classification as Stage 1 or 2 | K40: NÃO | L40: ifrs9_loss_given_default | M40: LT002_INSTRUMENT.IFRS9_LGD
... A44: V_224 | B44: Financial information | C44: Maturity / expiry date | D44: DD/MM/YY | E44: Expiry date. | G44: INSTRUMENT-DT_LGL_FNL_MTRTY | H44: Legal final maturity date (latest repayment date) | I44: The contractual maturity date of the instrument, taking into account any agreements amending initial contracts. As for retail revolving credit facilities this attribute is to be reported "not applicable". | K44: NÃO | L44: maturity_date | M44: LT002_INSTRUMENT.DT_LGL_FNL_MTRTY
A45: V_225 | B45: Financial information | C45: Nominal interest rate or fee | D45: Numeric. Basis points | E45: Notional interest rate or fee as agreed and payable. | G45: - | H45: - | I45: - | K45: SIM | L45: nominal_interest_rate_fee | M45: Conceito do campo não está claro. | N45: Em análise
A46: V_158 | B46: Financial information | C46: Default status of the instrument | D46: String | E46: Identification of the default status of the instrument in accordance with Article 178 of Regulation (EU) No 575/2013. Options: ‣ Not in default ‣ Default because unlikely to pay (not more than 90/180 days past due). ‣ Default because more than 90/180 days past due ‣ Default because both unlikely to pay and more than 90/180 days past due. | G46: INSTRUMENT-DFLT_STTS_INSTRMNT | H46: Default status of the instrument | I46: Identification of the default status of the instrument. Categories describing the situations in which an instrument can be described as being at default in accordance with Article 178 of Regulation (EU) No 575/2013. | K46: NÃO | L46: default_status_instrument | M46: LT002_INSTRUMENT.DFLT_STTS_INSTRMNT ‣ Traduzir o campo "DFLT_STTS_INSTRMNT" seguindo as parametrizações apresentadas nas sheets: ‣ LT829 - filtrando por campo_conceito = 'DFLT_STTS_INSTRMNT' e regra_conversao = '1'; ‣ LT830 - filtrando por segmento = 'Off-balance sheet exposures' e campo_conceito = 'DFLT_STTS_INSTRMNT'.
A49: V_159 | B49: Financial information | C49: Date of the default status of the instrument | D49: DD/MM/YY | E49: The date on which the default status, as reported in the data attribute “default status of the instrument”, is considered to have occurred. | G49: INSTRUMENT-DT_DFLT_STTS_INSTRMNT | H49: Date of default status | I49: The date on which the default status, as reported in the data attribute “Default status”, is considered to have arisen. If "Not in default" since inception then this attribute is to be reported equally to the inception date. If more than one Instrument is classified as defaulted then the earliest date has to be provided. The definition of default is aligned with Art 178 of Regulation (EU) No 575/2013. | K49: NÃO | L49: date_default_status_instrument | M49: LT002_INSTRUMENT.DT_DFLT_STTS_INSTRMNT
A50: V_161 | B50: Financial information | C50: Arrears for the instrument | D50: Numeric (euro) | E50: Aggregated amount of the nominal, interest and any fee payment outstanding at the reporting date, which is contractually due and has not been paid (past due). | G50: INSTRUMENT-ARRRS_INSTRMNT | H50: Total exposure in arrears | I50: Aggregated amount of the principal, interest and any fee payment outstanding at the reporting date, which is contractually due and has not been paid (past due). | K50: NÃO | L50: arrears_instrument | M50: LT002_INSTRUMENT.ARRRS_INSTRMNT
A51: V_162 | B51: Financial information | C51: Date of past due for the instrument | D51: DD/MM/YY | E51: The date on which the instrument became past due in accordance with Part 2.96 of Annex V to the amended Implementing Regulation (EU) No 680/2014. | G51: INSTRUMENT-DT_PST_D | H51: Date past due | I51: The date on which the instrument became past due in accordance with Part 2.96 of Annex V to the amended Implementing Regulation (EU) No 680/2014. This is the latest such date prior to the reporting reference date and it is to be reported if the instrument is past due on the reporting reference date. | K51: NÃO | L51: date_past_due_instrument | M51: LT002_INSTRUMENT.DT_PST_D
A52: V_167 | B52: Financial information | C52: Joint liabilities amount | D52: Numeric (euro) | E52: Outstanding nominal amount for which each debtor is liable in relation to a single instrument where there are two or more debtors. | G52: Not applicable: To be reported as "11111111111". This information will be availabe in "03_04_off_instr_count" table | H52: - | I52: - | K52: SIM | L52: joint_liabilities_amount | M52: Reportar sempre: 11111111111
A53: V_171 | B53: Financial information | C53: Accumulated impairment amount | D53: Numeric (euro) | E53: The amount of loss allowances that are held against or are allocated to the instrument on the reporting reference date. This data attribute applies to instruments subject to impairment under the applied accounting standard. Under IFRS, the accumulated impairment relates to the following amounts: (i)loss allowance at an amount equal to 12-month expected credit losses; (ii) loss allowance at an amount equal to lifetime expected credit losses. Under GAAP, the accumulated impairment relates to the following amounts: (i)loss allowance at an amount equal to general allowances; (ii) loss allowance at an amount equal to specific allowances. | G53: INSTRUMENT-ACCMLTD_IMPRMNT_INSTRMNT | H53: Sum of LLPs and other allowances | I53: The amount of loss allowances that are held against or are allocated to the instrument on the reporting reference date. This data attribute applies to instruments subject to impairment under the applied accounting standard. | K53: NÃO | L53: accum_impairment_amount | M53: LT002_INSTRUMENT.ACCMLTD_IMPRMNT_INSTRMNT
A55: V_172 | B55: Financial information | C55: Type of impairment | D55: String | E55: This data attribute indicates the type of impairment to which the instrument is subject. Options: ‣ Stage 1 (IFRS) ‣ Stage 2 (IFRS) ‣ Stage 3 (IFRS) ‣ General allowances (GAAP) ‣ Specific allowances (GAAP) | G55: INSTRUMENT-IMPRMNT_STTS | H55: Impairment status | I55: Type of impairment. | K55: NÃO | L55: type_impairment | M55: LT002_INSTRUMENT.IMPRMNT_STTS ‣ Traduzir o campo "IMPRMNT_STTS" seguindo as parametrizações apresentadas nas sheets: ‣ LT829 - filtrando por campo_conceito = 'IMPRMNT_STTS' e regra_conversao = '1'; ‣ LT830 - filtrando por segmento = 'Off-balance sheet exposures' e campo_conceito = 'IMPRMNT_STTS'.
A58: V_173 | B58: Financial information | C58: Impairment assessment method | D58: String | E58: The method by which the impairment is assessed, if the instrument is subject to impairment in accordance with applied accounting standards. Options: ‣ Individually assessed ‣ Collectively assessed | G58: INSTRUMENT-IMPRMNT_ASSSSMNT_MTHD | H58: Impairment assessment method | I58: The method by which the impairment is assessed, if the instrument is subject to impairment in accordance with applied accounting standards. Collective and individual methods are distinguished. | K58: NÃO | L58: impairment_assessment_method | M58: LT002_INSTRUMENT.IMPRMNT_ASSSSMNT_MTHD ‣ Traduzir o campo "IMPRMNT_ASSSSMNT_MTHD" seguindo as parametrizações apresentadas nas sheets: ‣ LT829 - filtrando por campo_conceito = 'IMPRMNT_ASSSSMNT_MTHD' e regra_conversao = '1'; ‣ LT830 - filtrando por segmento = 'Off-balance sheet exposures' e campo_conceito = 'IMPRMNT_ASSSSMNT_MTHD'.
A61: V_175 | B61: Financial information | C61: Performing status of the instrument | D61: String | E61: The instrument is to be classified on the reporting reference date, in accordance with Implementing Regulation (EU) No 680/2014. Options: ‣ Non-performing ‣ Performing | G61: INSTRUMENT-PRFRMNG_STTS | H61: Performing status | I61: The instrument is to be classified on the reference date under one of the following categories: performing or non-performing, in accordance with Implementing Regulation (EU) No 680/2014. If the performing status is measured on entity level only all instruments are to be classified according to the status on entity level. | K61: NÃO | L61: perform_status_instrument | M61: LT002_INSTRUMENT.PRFRMNG_STTS ‣ Traduzir o campo "PRFRMNG_STTS" seguindo as parametrizações apresentadas nas sheets: ‣ LT829 - filtrando por campo_conceito = 'PRFRMNG_STTS' e regra_conversao = '1'; ‣ LT830 - filtrando por segmento = 'Off-balance sheet exposures' e campo_conceito = 'PRFRMNG_STTS'.
A62: V_176 | B62: Financial information | C62: Date of the performing status of the instrument | D62: DD/MM/YY | E62: The date on which the performing status as reported in “performing status of the instrument” is considered to have been established or changed. | G62: INSTRUMENT-DT_PRFRMNG_STTS | H62: Date of performing status | I62: The date on which the performing status as reported in “performing status of the instrument” is considered to have been established or changed. If the performing status is measured on debtor level the status will respectively apply to all instruments. | K62: NÃO | L62: date_perform_status_instrument | M62: LT002_INSTRUMENT.DT_PRFRMNG_STTS
A63: V_178 | B63: Forbearance information | C63: Status of forbearance and renegotiation | D63: String | E63: Identification of forborne and renegotiated instruments. Options: ‣ Forborne: instruments with modified interest rate below market conditions ‣ Forborne: instruments with other modified terms and conditions ‣ Forborne: totally or partially refinanced debt ‣ Renegotiated instrument without forbearance measures ‣ Not forborne or renegotiated | G63: INSTRUMENT-FRBRNC_STTS_INSTRMNT | H63: Forbearance status | I63: Identification of forborne and renegotiated instruments. | K63: NÃO | L63: status_forbearance_reneg | M63: LT002_INSTRUMENT.FRBRNC_STTS_INSTRMNT ‣ Traduzir o campo "FRBRNC_STTS_INSTRMNT" seguindo as parametrizações apresentadas nas sheets: ‣ LT829 - filtrando por campo_conceito = 'FRBRNC_STTS_INSTRMNT' e regra_conversao = '1'; ‣ LT830 - filtrando por segmento = 'Off-balance sheet exposures' e campo_conceito = 'FRBRNC_STTS_INSTRMNT'.
A66: V_179 | B66: Forbearance information | C66: Date of the forbearance and renegotiation status | D66: DD/MM/YY | E66: The date on which a forbearance or renegotiation status as reported under “status of forbearance and renegotiation” is considered to have occurred. | G66: INSTRUMENT-DT_FRBRNC_STTS | H66: Date of forbearance status | I66: Date of forbearance status. If the instrument has never been subject to forbearance measure then this date would be equal to the inception date. | K66: NÃO | L66: date_status_forbearance_reneg | M66: LT002_INSTRUMENT.DT_FRBRNC_STTS

Sheet OFFBAL_COUNTERPARTIES
A1: Instruções SRB | G1: Mapeamento efetuado pela Corporação e respetiva Descrição Loan Tape (LT) | K1: Análise IT
A2: ID | B2: Categoria | C2: Coluna | D2: Tipo de dados | E2: Descrição | G2: Mapeamentos Corporação (LT) | H2: Descrição (LT) | I2: Additional Guidance (LT) | K2: Novo campo na tabela LT003? | L2: Nome do campo no ficheiro | M2: Mapeamento | N2: Notas
A3: V_2 | B3: Identification information | C3: Counterparty Identifier | D3: Alphanumeric | E3: Identifier applied to uniquely identify each counterparty. | G3: ENTITY-ENTTY_ID | H3: Entity ID | I3: An identifier applied by the reporting agent to uniquely identify each counterparty. Each counterparty has a unique and exclusive counterparty identifier. This means that this value will not change over time and can never be used as the counterparty identifier for any other counterparty. | K3: NÃO | L3: counterparty_id | M3: LT003_ENTITY.ENTTY_ID
A4: V_139 | B4: Risk parameters | C4: Probability of default | D4: Numeric. Basis points | E4: The counterparty’s probability of default over one year, determined in accordance with Articles 160, 163, 179 and 180 of Regulation (EU) No 575/2013. The probability of default (PD) is in accordance with the requirements specific to PD estimation as laid down in the CRR. In the case of PDs produced at the instrument level only (the so-called product PD), the counterparty PD is reported as the exposure weighted average PD of all instruments of the counterparty. If, for a given counterparty, a PD is estimated for both the counterparty and (some of) the products of the counterparty, the counterparty’s PD is to be reported. | G4: ENTITY-PD_CRR_RD | H4: Probability of default according to CRR at reference date | I4: The PD over one year, determined in accordance with Articles 160, 163, 179 and 180 of Regulation (EU) No 575/2013. If the PD is calculated on obligor level then provide the obligor PD. If the PD is calculated on instruments level please provide an EAD weighted average. | K4: NÃO | L4: probability_default | M4: LT003_ENTITY.PD_CRR_RD
A12: V_8 | B12: Risk parameters | C12: Current Internal Credit Rating/Scoring | D12: Numeric / Alphanumeric | E12: Internal credit rating/scoring issued to the Counterparty. | G12: ENTITY-INTRNL_RTNG | H12: Internal rating at reference date | I12: Internal rating at the reference date according to Regulation (EU) No 575/2013. Please also add in sheet "Code List" the list of values used, i.e. bank-internal masterscale. | K12: NÃO | L12: internal_credit_rating | M12: LT003_ENTITY.INTRNL_RTNG
A13: V_9 | B13: Risk parameters | C13: External Credit Rating | D13: Alphanumeric | E13: External credit rating issued to the Counterparty (if any). | G13: ENTITY-EXTRNL_RTNG | H13: External rating | I13: External rating at the reference date. | K13: NÃO | L13: external_credit_rating | M13: LT003_ENTITY.EXTRNL_RTNG
A14: V_10 | B14: Risk parameters | C14: IFRS 9 Probability of default/impairment | D14: Numeric. Basis points | E14: The probability of default/impairment is calculated in accordance with the requirements specific to probability of default (PD) estimation as laid down in the accounting framework. If PDs are produced at the instrument level only, the counterparty’s PD is to be reported as the exposure-weighted average PD across the PDs of all instruments of the counterparty. If, for a given counterparty, PDs are estimated for both the counterparty and (some of) the products of the counterparty, it is the counterparty’s PD which is to be reported. No documento "Feedback Statement in response to the consultation on the SRB valuation data set" é referida a seguinte nota sobre este campo: "‘Data Point V_10’, entitled ‘IFRS 9 Probability of default’, refers to PDs used for accounting purposes, being a 12-month PD for stage 1 exposures and a lifetime PD for stage 2 and 3 exposures as per the accounting framework." | G14: ENTITY-PD_IFRS9_12M_RD | H14: 12-month PD at reporting date according to IFRS 9 | I14: 12-month PD at reference date which is used by the bank for computation of stage 1 ECL or for SICR assessment if bank use 12 month proxy for staging. If the PD is calculated on instruments level please provide an EAD weighted average. | K14: SIM | L14: ifrs9_prob_default_impairment | M14: Necessário validar a necessidade de criar um novo campo ("PD misto" ) na LT002_INSTRUMENT dado que se solicita um "misto" entre a PD 12m (PD12M_IFRS9) e a PD lifetime (PD_LT_IFRS9), campos já existentes nessa tabela. A lógica a validar será: -Se stage 1: Se loss_type LIKE 'Lifetime expected credit losses%' selecionar PD_LT_IFRS9 da tabela BU_IFRS9.IFRS9_OUT_EXPECTED_LOSS_REPORTING, caso contrário selecionar PD12M_IFRS9 da tabela BU_IFRS9.IFRS9_OUT_EXPECTED_LOSS_REPORTING -Se stage 2: selecionar PD_LT_IFRS9 da tabela BU_IFRS9.IFRS9_OUT_EXPECTED_LOSS_REPORTING -Se stage 3: forçar 1 Sugere-se criar o campo na LT002_INSTRUMENT e não na LT003_ENTITY porque após consultar a a LT003_ENTITY verificou-se que existia o campo PD_IFRS9_12M_RD para o qual é usada a LT005_INSTR_ENT para identificar todos os contratos onde o cliente é o 1º Titular, de seguida para cada cliente aplica-se uma média ponderada da PD em relação ao EAD (porque cada cliente pode ter vários contratos). Assim sugere-se replicar esta lógica para o novo campo "PD misto" adicionado na LT002_INSTRUMENT de forma a poder ser criado também um novo campo "PD misto" na LT003_ENTITY. Lógica proposta para a criação do novo campo na LT002: CASE WHEN IMPRMNT_STTS_INSTRMNT = '23' --(Stage 1) THEN IF( loss_type LIKE 'Lifetime expected credit losses%', PD_LT_IFRS9, PD12M_IFRS9) WHEN IMPRMNT_STTS_INSTRMNT = '24' --(Stage 2) THEN PD_LT_IFRS9 WHEN IMPRMNT_STTS_INSTRMNT = '25' --(Stage 3) THEN 1 ELSE 'N/A' END as PD_IFRS9_12M_LFTM_RD WHERE IMCATF046_FLAG_FECHO.CMES = REF_DATE Lógica proposta para a criação do novo campo na LT003: 1) Identificar contratos onde o cliente é o 1º Titular: LT005_INSTR_ENT WHERE CRELACAO_CL_CNT = '1' AND CSEQUENCIA_REL = '00001' 2) Aplicar o seguinte cáclulo por entidade: CASE WHEN SUM(IFRS9_EAD)<> 0 THEN SUM(PD_IFRS9_12M_LFTM_RD * IFRS9_EAD) / SUM(IFRS9_EAD) ELSE AVG(PD_IFRS9_12M_LFTM_RD) END as ifrs9_prob_default_impairment | N14: Em análise
A27: V_11 | B27: Risk parameters | C27: Probability of default (others) | D27: Numeric. Basis points | E27: Applicable only to institutions neither using models for estimating IFRS 9 impairments nor CRR IRB models. These institutions should maintain records of probabilities of default or scores provided by scoring/rating models. In the case of PDs produced at the instrument level, the counterparty’s PD is to be reported as the exposure weighted average PD across the PDs of all instruments of the counterparty. If, for a given counterparty, PDs are estimated for both the counterparty and (some of) the products of the counterparty, it is the counterparty’s PDs which is to be reported. | G27: - | H27: - | I27: - | K27: SIM | L27: probability_default_others | M27: Reportar sempre: 11111111111
A28: V_185 | B28: Financial information | C28: Default status of the counterparty | D28: String | E28: Identification of the default status of the counterparty. Categories describing the motives for which the counterparty can be in default in accordance with Article 178 of Regulation (EU) No 575/2013. Options: ‣ Not in default ‣ Default because unlikely to pay ‣ Default because more than 90/180 days past due ‣ Default because both unlikely to pay and more than 90/180 days past due | G28: ENTITY-DFLT_STTS | H28: Default status of the entity | I28: Identification of the default status of the counterparty. Categories describing the motives for which the counterparty can be in default in accordance with Article 178 of Regulation (EU) No 575/2013. For retail only: If default classification performed on instrument level then Entity is classified as defaulted when at least one instrument is classified as defaulted. For corporate, SME, CRE and LF: if default classification performed on instrument level then entity level is "not applicable". | K28: NÃO | L28: default_status_counterparty | M28: LT003_ENTITY.DFLT_STTS ‣ Traduzir o campo "DFLT_STTS" seguindo as parametrizações apresentadas nas sheets: ‣ LT829 - filtrando por campo_conceito = 'DFLT_STTS' e regra_conversao = '1'; ‣ LT830 - filtrando por segmento = 'Off-balance sheet exposures' e campo_conceito = 'DFLT_STTS'.
A31: V_186 | B31: Financial information | C31: Date of the default status of the counterparty | D31: DD/MM/YYYY | E31: The date on which the default status, as reported in the data attribute “Default status of the counterparty”, is considered to have arisen. | G31: ENTITY-DT_DFLT_STTS | H31: Date of default status | I31: The date on which the default status, as reported in the data attribute “Default status”, is considered to have arisen. If "Not in default" since inception then this attribute is to be reported equally to the inception date. If default classification performed on instrument level then Entity is classified as defaulted when at least one instrument is classified as defaulted. If more than one Instrument is classified as defaulted then the earliest date has to be provided. The definition of default is aligned with Art 178 of Regulation (EU) No 575/2013. | K31: NÃO | L31: date_default_status_counterparty | M31: LT003_ENTITY.DT_DFLT_STTS
A32: V_195 | B32: Identification information | C32: Legal entity identifier (LEI) | D32: Alphanumeric | E32: The legal entity identifier (LEI) is the counterparty identifier assigned in accordance with the International Organization for Standardization (ISO) 17442 standard. | G32: ENTITY-LEI | H32: Legal entity identifier Counterparty | I32: Legal entity identifier counterparty. | K32: NÃO | L32: legal_entity_id | M32: LT003_ENTITY.LEI
A33: V_196 | B33: Identification information | C33: National identifier | D33: Alphanumeric | E33: A national identifier is a commonly used identification code which enables the unambiguous identification of a counterparty or of the legal entity of which the counterparty forms part within its country of residency. | G33: ENTITY-TAX_ID | H33: Fiscal ID | I33: Fiscal ID (CIF, NIF, Tax number, etc). | K33: NÃO | L33: national_id | M33: LT003_ENTITY.TAX_ID
A34: V_197 | B34: Identification information | C34: Head office undertaking identifier | D34: Alphanumeric | E34: The head office undertaking identifier is the counterparty identifier of the domestic part of the legal entity of which the institutional unit is a legally dependent part. | G34: - | H34: - | I34: - | K34: SIM | L34: head_office_undertaking_id | M34: Informação não parece existir no datalake, necessário avaliar fontes alternativas. | N34: Em análise
A35: V_198 | B35: Identification information | C35: Immediate parent undertaking identifier | D35: Alphanumeric | E35: The immediate parent undertaking identifier is the counterparty identifier for the domestic part of the legal entity which is the immediate parent undertaking of the counterparty. | G35: - | H35: - | I35: - | K35: SIM | L35: immediate_parent_undertaking_id | M35: Informação não parece existir no datalake, necessário avaliar fontes alternativas. | N35: Em análise
A36: V_199 | B36: Identification information | C36: Ultimate parent undertaking identifier | D36: Alphanumeric | E36: The ultimate parent undertaking identifier is the counterparty identifier for the domestic part of the legal entity which is the ultimate parent undertaking of the counterparty. | G36: - | H36: - | I36: - | K36: SIM | L36: ultimate_parent_undertaking_id | M36: Informação não parece existir no datalake, necessário avaliar fontes alternativas. | N36: Em análise
A37: V_200 | B37: Identification information | C37: Name | D37: Alphanumeric | E37: The full legal name of the counterparty. | G37: ENTITY-ENTTY_NM | H37: Name Counterparty | I37: Name Counterparty | K37: NÃO | L37: name | M37: LT003_ENTITY.ENTTY_NM
A38: V_201 | B38: Location information | C38: Address: street | D38: Alphanumeric | E38: The counterparty’s street address, including the street number. | G38: - | H38: - | I38: - | K38: SIM | L38: address_street | M38: Campo "nmorada" da cd_captools.ct003_univ_cli
A39: V_202 | B39: Location information | C39: Address: city/town/village | D39: Alphanumeric | E39: The counterparty’s city, town or village. | G39: - | H39: - | I39: - | K39: SIM | L39: address_city_town_village | M39: Campo "nlocalid" da cd_captools.ct003_univ_cli
A40: V_203 | B40: Location information | C40: Address: postal code | D40: Alphanumeric | E40: The counterparty’s postal code. | G40: - | H40: - | I40: - | K40: NÃO | L40: address_postal_code | M40: LT003_ENTITY.PST_CD
A41: V_204 | B41: Location information | C41: Address: county/administrative division | D41: Alphanumeric | E41: The county or similar administrative division of counterparties resident in European Union Member States as per NUTS 3 classification. | G41: - | H41: - | I41: - | K41: SIM | L41: address_county_adm_div | M41: Campo "cnuts3" da cd_captools.ct003_univ_cli
A42: V_205 | B42: Location information | C42: Address: country | D42: String | E42: The counterparty’s country. Options: ISO 3166-1 alpha-2 codes: ISO 3166-1 alpha-2 code of the country | G42: ENTITY-CNTRY | H42: Country of counterparty residence | I42: Country of counterparty residence. | K42: NÃO | L42: address_country | M42: LT003_ENTITY.CNTRY
A43: V_206 | B43: Counterparty characteristics | C43: Legal form | D43: String | E43: The type of business entity as defined in the national legal system. | G43: - | H43: - | I43: - | K43: SIM | L43: legal_form | M43: ‣ Campo parcialmente definido, ainda está a ser avaliada a necessidade de aplicar uma regra complementar à regra definida de seguida: - Schema DL: cd_captools; cd_alm; cd_estruturais - Tabela / Ficheiro: CT003_UNIV_CLI; MAT05_DADOSEMP; TAT91_TABELAS - Campo: ccli_grupo; cformjur; tayd91c0_gelemtab - Metodologia de Cálculo: "tayd91c0_gelemtab WHERE TAT91_TABELAS.tayd91c0_ctabela = '264' AND TAT91_TABELAS.tayd91c0_celemtab = MAT05_DADOSEMP.cformjur AND lpad(MAT05_DADOSEMP.zcligrupo,10,'0') = CT003_UNIV_CLI.ccli_grupo" - Metodologia de cruzamento 1) Cruzar LT003_ENTITY com CT003_UNIV_CLI para obter o ccli_grupo: LT003_ENTITY LEFT JOIN (SELECT * FORM CD_CAPTOOLS.CT003_UNIV_CLI) ON ENTTY_ID = ZCLIENTE 2) Cruzar ccli_grupo da CT003_UNIV_CLI com o zcligrupo da MAT05_DADOSEMP para obter o cformjur: MAT05_DADOSEMP INNER JOIN (SELECT zcligrupo, MAX(dano) FROM CD_CAPTOOLS.MAT05_DADOSEMP WHERE data_date_part <= REF_DATE) ON zcligrupo = zcligrupo AND dano = MAX(dano) 3) Cruzar com tabela TAT 264 para descodificar o cformjur: LEFT JOIN (SELECT * FROM TAT91_TABELAS) ON cformjur = tayd91c0_celemtab" ‣ Query usada para adicionar o Legal Form à tabela lt003: SELECT lt003.entty_id, ct003.itip_cli, ct003.ccli_grupo, mat05.cformjur, tat.tayd91c0_gelemtab FROM ( SELECT entty_id FROM bu_loantape_work.lt003_entity_srb WHERE ambito = 'SRB_VALUATION' AND segmento = 'Off-balance sheet exposures' AND ref_date = '2024-11-30' ) as lt003 LEFT JOIN ( SELECT zcliente, itip_cli, ccli_grupo as ccli_grupo FROM cd_captools.ct003_univ_cli WHERE ref_date = '2024-11-30' ) as ct003 ON lt003.entty_id = ct003.zcliente LEFT JOIN ( SELECT lpad(CAST(zcligrupo AS STRING),10,'0') as zcligrupo, cformjur, ROW_NUMBER() OVER(PARTITION BY zcligrupo ORDER BY dano DESC) as row_num FROM cd_alm.mat05_dadosemp WHERE data_date_part = (SELECT MAX(data_date_part) FROM cd_alm.mat05_dadosemp WHERE data_date_part < '2024-11-30') AND dano <= CAST(SUBSTR('2024-11-30',1,4) AS INT) ) as mat05 ON ct003.ccli_grupo = mat05.zcligrupo AND mat05.row_num = 1 LEFT JOIN ( SELECT tayd91c0_celemtab, tayd91c0_gelemtab FROM cd_estruturais.tat91_tabelas WHERE data_date_part = (SELECT MAX(data_date_part) FROM cd_estruturais.tat91_tabelas) AND tayd91c0_ctabela = '264' ) as tat ON mat05.cformjur = tat.tayd91c0_celemtab WHERE ct003.itip_cli = 'J' AND mat05.zcligrupo IS NOT NULL AND TRIM(mat05.cformjur) <> '' | N43: Em análise
A44: V_207 | B44: Counterparty characteristics | C44: Institutional sector | D44: String | E44: Institutional sectors in accordance with Regulation (EU) No 549/2013, Regulation (EU) No 575/2013 and Regulation (EU) No 1075/2013 of the European Central Bank (ECB/2013/40). Options: ‣ Non-financial corporations ‣ Central Bank ‣ Credit institutions ‣ Deposit-taking corporations other than credit institutions ‣ Money market funds (MMF) ‣ Non-MMF Investment funds ‣ Financial vehicle corporations (FVCs) engaged in securitisation transactions, Other financial intermediaries, except financial auxiliaries, captive financial institutions and money lenders, insurance corporations, pension funds and financial vehicle corporations engaged in securitisation transactions ‣ Financial auxiliaries ‣ Captive financial institutions and money lenders ‣ Insurance corporations ‣ Pension funds ‣ Central government ‣ State government ‣ Local government ‣ Social security funds ‣ Non-profit institutions serving households | G44: - | H44: - | I44: - | K44: SIM | L44: institutional_sector | M44: ‣ Campo "csector_inst" da tabela cd_captools.ct003_univ_cli ‣ Traduzir o campo "csector_inst" seguindo a parametrização apresentada na sheet 'LT831' filtrando por campo_conceito = 'INSTITUTIONAL_SECTOR'
A47: V_208 | B47: Counterparty characteristics | C47: Economic activity | D47: String | E47: Economic activity is a classification of counterparties according to their economic activities, in accordance with the NACE revision 2 statistical classification as laid down in Regulation (EC) No 1893/2006 of the European Parliament and of the Council. Options: NACE code: a level two, three or four NACE code in accordance with Regulation (EC) No 1893/2006. | G47: ENTITY-ECNMC_ACTVTY | H47: Economic activity counterparty | I47: The level four NACE code in accordance with Regulation (EC) No 1893/2006 is generally reported. If the level four NACE code is not available it may be allowed to report a level three or level two NACE code. | K47: NÃO | L47: economic_activity | M47: LT003_ENTITY.ECNMC_ACTVTY
A48: V_209 | B48: Default information | C48: Status of legal proceedings | D48: String | E48: The status of legal proceedings covers the categories describing a counterparty’s legal status in relation to its solvency based on the national legal framework. The NCB should transpose these values (listed below) into the national legal framework. Options: ‣ No legal actions taken ‣ Under judicial administration, receivership or similar measures ‣ Bankruptcy/insolvency ‣ Other legal measures | G48: ENTITY-LGL_PRCDNG_STTS_LE | H48: Legal proceedings status Counterparty (LE) | I48: Legal proceedings status Counterparty (LE). Only for Retail portfolios: Status "No legal action taken" or "Other legal measures" are possible. Status "Other legal measures" is reported when the hard collection process was initiated at the level of a given entity or at the level of any associated instrument or protection of this entity. | K48: NÃO | L48: status_legal_proceedings | M48: LT003_ENTITY.LGL_PRCDNG_STTS_LE ‣ Traduzir o campo "LGL_PRCDNG_STTS_LE" seguindo as parametrizações apresentadas nas sheets: ‣ LT829 - filtrando por campo_conceito = 'LGL_PRCDNG_STTS_LE' e regra_conversao = '1'; ‣ LT830 - filtrando por segmento = 'Off-balance sheet exposures' e campo_conceito = 'LGL_PRCDNG_STTS_LE'.
A51: V_210 | B51: Default information | C51: Date of initiation of legal proceedings | D51: DD/MM/YYYY | E51: The date on which the legal proceedings, as reported under the attribute “status of legal proceedings”, were initiated. This date should be the most recent relevant date prior to the reporting date. | G51: ENTITY-DT_INTTN_LGL_PRCDNGS_LE | H51: Date of initiation of legal proceedings counterparty (LE) | I51: Date of initiation of legal proceedings counterparty (LE). Only for Retail portfolios: The date when the hard collection process was initiated for given entity. If the hard collection process is defined on the level of instrument or protection and more instruments or protections with status "Other legal measures" are linked to the same entity the oldest date is reported. | K51: NÃO | L51: date_init_legal_proceedings | M51: LT003_ENTITY.DT_INTTN_LGL_PRCDNGS_LE
A52: V_211 | B52: Counterparty characteristics | C52: Enterprise size | D52: String | E52: The classification of enterprises by size, in accordance with the Annex to Commission Recommendation 2003/361/EC. Options: ‣ Large enterprise ‣ Medium enterprise ‣ Small enterprise ‣ Microenterprise | G52: ENTITY-ENTRPRS_SZ_LE | H52: Enterprise size Counterparty (LE) | I52: Enterprise size counterparty (LE). Classification of enterprises by size, in accordance with the Annex to Commission Recommendation 2003/361/EC. However, if the local NCB decides not to request this attribute as part of the AnaC reporting data set then please report "Not applicable". | K52: NÃO | L52: enterprise_size | M52: LT003_ENTITY.ENTRPRS_SZ_LE ‣ Traduzir o campo "ENTRPRS_SZ_LE" seguindo as parametrizações apresentadas nas sheets: ‣ LT829 - filtrando por campo_conceito = 'ENTRPRS_SZ_LE' e regra_conversao = '1'; ‣ LT830 - filtrando por segmento = 'Off-balance sheet exposures' e campo_conceito = 'ENTRPRS_SZ_LE'.
A55: V_212 | B55: Counterparty characteristics | C55: Date of enterprise size | D55: DD/MM/YYYY | E55: The date to which the value provided in the “enterprise size” refers. This is the date of the latest data used to classify or review the classification of the enterprise. | G55: - | H55: - | I55: - | K55: SIM | L55: date_enterprise_size | M55: ‣ Se o cliente for uma pessoa física, então reportar N/A; ‣ Se o cliente for uma pessoa jurídica, então recuar até à data em que o enterprize size (COD_EMPR_PME) alterou em relação ao valor que tem à data de referência (se nunca mudou será a data de constituição do cliente). 1) Cruzar LT003_ENTITY com a tabela CT003_UNIV_CLI para obter o campo ITIP_CLI: LT003_ENTITY LEFT JOIN (SELECT ZCLIENTE, ITIP_CLI FROM CT003_UNIV_CLI) as CT003 ON ENTTY_ID = ZCLIENTE 2) Cruzar LT003_ENTITY com a tabela CT063_UNIV_PME para obter o campo DATE_ENTERPRIZE_SIZE_AUX: LT003_ENTITY LEFT JOIN ( SELECT ZCLIENTE, MAX(REF_DATE) as DATE_OF_ENTERPRIZE_SIZE_AUX FROM ( SELECT ZCLIENTE, COD_EMPR_PME, LAG(COD_EMPR_PME) OVER(PARTITION BY ZCLIENTE ORDER BY REF_DATE) as COD_EMPR_PME_ANTERIOR, REF_DATE FROM CD_CAPTOOLS.CT063_UNIV_PME WHERE REF_DATE <= 'ref_date' ) as pme WHERE NVL(COD_EMPR_PME,11111111111) != NVL(COD_EMPR_PME_ANTERIOR,11111111111) AND COD_EMPR_PME IS NOT NULL GROUP BY ZCLIENTE ) as PME ON ENTTY_ID = ZCLIENTE 3) Aplicar a lógica de produção do campo DATE_ENTERPRIZE_SIZE: IF( ITIP_CLI = 'J', NVL(DATE_ENTERPRIZE_SIZE_AUX, '00/00/0000'), '11/11/1111' ) as DATE_ENTERPRIZE_SIZE
A56: V_213 | B56: Counterparty characteristics | C56: Number of employees | D56: Numeric | E56: Number of employees working for the counterparty, in accordance with Article 5 of the Annex to Recommendation 2003/361/EC. | G56: - | H56: - | I56: - | K56: SIM | L56: number_employees | M56: ‣ Se tipo_empr='Associada' utilizar o campo num_empg_grup da tabela business_sme2003361.out_sme_2003_361 ‣ Se tipo_empr='Autonoma' utilizar o campo num_empg_indv da tabela business_sme2003361.out_sme_2003_361
A57: V_214 | B57: Financial information | C57: Balance sheet total | D57: Numeric | E57: The carrying value of the counterparty’s total assets in accordance with Regulation (EU) No 549/2013. | G57: - | H57: - | I57: - | K57: SIM | L57: balance_sheet_total | M57: ‣ Se tipo_empr='Associada' utilizar o campo ativo_grup da tabela business_sme2003361.out_sme_2003_361 ‣ Se tipo_empr='Autonoma' utilizar o campo ativo_indv da tabela business_sme2003361.out_sme_2003_361
A58: V_215 | B58: Financial information | C58: Annual turnover | D58: Numeric in euro | E58: The annual sales volume net of all discounts and sales taxes of the counterparty in accordance with Recommendation 2003/361/EC. | G58: ENTITY-ANNL_TRNVR_LE | H58: Annual turnover counterparty (LE) | I58: Annual sales volume net of all discounts and sales taxes in accordance with Recommendation 2003/361/EC. Equivalent to the concept of 'total annual sales' in Article 153(4) of Regulation (EU) No 575/2013. Please report on solo entity level unless advised otherwise. | K58: NÃO | L58: annual_turnover | M58: LT003_ENTITY.ANNL_TRNVR_LE
A59: V_216 | B59: Financial information | C59: Accounting standard | D59: String | E59: Accounting standard used by the observed agent’s legal entity. Options: ‣ IFRS ‣ National GAAP consistent with IFRS ‣ National GAAP not consistent with IFRS | G59: ENTITY-ACCNTNG_FRMWRK_SL | H59: Accounting standard counterparty | I59: Accounting standard counterparty. | K59: NÃO | L59: accounting_standard | M59: LT003_ENTITY.ACCNTNG_FRMWRK_SL ‣ Traduzir o campo "ACCNTNG_FRMWRK_SL" seguindo as parametrizações apresentadas nas sheets: ‣ LT829 - filtrando por campo_conceito = 'ACCNTNG_FRMWRK_SL' e regra_conversao = '1'; ‣ LT830 - filtrando por segmento = 'Off-balance sheet exposures', campo_conceito = 'ACCNTNG_FRMWRK_SL.

Sheet OFFBAL_PROTECTIONS
A1: Instruções SRB | G1: Mapeamento efetuado pela Corporação e respetiva Descrição Loan Tape (LT) | K1: Análise IT
A2: ID | B2: Categoria | C2: Coluna | D2: Tipo de dados | E2: Descrição | G2: Mapeamentos Corporação (LT) | H2: Descrição (LT) | I2: Additional Guidance (LT) | K2: Novo campo na tabela LT004? | L2: Nome do campo no ficheiro | M2: Mapeamento | N2: Notas
A3: V_12 | B3: Identification information | C3: Protection identifier | D3: Alphanumeric | E3: An identifier applied to uniquely identify each protection/collateral used to secure the instrument. | G3: PROTECTION-PRTCTN_ID | H3: Protection ID | I3: An identifier applied by the reporting agent to uniquely identify each protection used to secure the instrument. Each protection must have one protection identifier. This value will not change over time and cannot be used as the protection identifier for any other protection. | K3: NÃO | L3: protection_id | M3: LT004_PROTECTION.PRTCTN_ID
A7: V_1 | B7: Identification information | C7: Instrument Identifier | D7: Alphanumeric | E7: An identifier applied to uniquely identify each instrument. Each instrument must have one instrument identifier. | G7: Not applicable: To be reported as "N/A". This information will be availabe in "03_05_off_instr_prot" table | H7: - | I7: - | K7: SIM | L7: instrument_id | M7: Reportar sempre: 'N/A'
A11: V_219 | B11: Identification information | C11: Protection provider identifier | D11: Alphanumeric | E11: The protection provider identifier is the counterparty identifier of the counterparty that grants protection against a contractually agreed negative credit event and that is obliged to make payments to the creditor if the debtor fails to meet the obligation to make repayments arising under the instrument secured by the protection item. | G11: PROTECTION-PRTCTN_PRVDR_ID | H11: Protection Provider ID (Guarantor) | I11: Counterparty identifier for the protection provider. If the protection provider is not a legal entity, the protection provider identifier is not required to be reported. | K11: NÃO | L11: protection_provider_id | M11: LT004_PROTECTION.PRTCTN_PRVDR_ID
A12: V_187 | B12: Identification information | C12: Type of collateral | D12: String | E12: The AnaCredit item “type of protection” (Section 9.4.3. of the AnaCredit Reporting Manual Part II – Datasets and data attributes) provides a breakdown of collaterals eligible in accordance with the CRR. The proposed breakdown adds several categories. Options: ‣ Gold ‣ Currency and deposits ‣ Securities ‣ Loans ‣ Equity and investment fund shares or units ‣ Credit derivatives ‣ Financial guarantees other than credit derivatives ‣ Trade receivables ‣ Life insurance policies pledged ‣ Residential real estate collateral ‣ Offices and commercial premises ‣ Commercial real estate collateral ‣ Other physical collateral ‣ Other protection ‣ Hotels & entertainment ‣ Infrastructure projects ‣ Factories – Warehouses ‣ Equipment & machinery ‣ Automotive ‣ Aircraft ‣ Shipping | G12: PROTECTION-TYP_PRTCTN | H12: Protection type | I12: Type of protection received, irrespective of its eligibility for credit risk mitigation. | K12: NÃO | L12: type_collateral | M12: LT004_PROTECTION.TYP_PRTCTN ‣ Traduzir o campo "TYP_PRTCTN" seguindo as parametrizações apresentadas nas sheets: ‣ LT829 - filtrando por campo_conceito = 'TYP_PRTCTN' e regra_conversao = '1'; ‣ LT830 - filtrando por segmento = 'Off-balance sheet exposures' e campo_conceito = 'TYP_PRTCTN'.
A15: V_14 | B15: Size collateral | C15: Building Area (M2) | D15: Numeric | E15: Building area of the building in square meters. Only applicable to Residential real estate collateral, Offices and commercial premises, Commercial real estate collateral, Hotels & entertainment, Factories – warehouses. | G15: - | H15: - | I15: - | K15: SIM gross_area | L15: building_area_m2 | M15: Campo "narbrut" da tabela cd_garantias.gt009_bens_imov
A16: V_15 | B16: Size collateral | C16: Land Area (M2) | D16: Numeric | E16: Land area of the property in square meters. Only applicable to land. | G16: - | H16: - | I16: - | K16: SIM land_area | L16: land_area_m2 | M16: Campo "narterr" da tabela cd_garantias.gt009_bens_imov
A17: V_16 | B17: Location | C17: Property postcode | D17: Numeric | E17: Postcode where the property is located. Only applicable to Residential real estate collateral, Offices and commercial premises, Commercial real estate collateral, Hotels & entertainment, Factories – Warehouses. | G17: PROTECTION-RL_ESTT_PST_CD | H17: Post code / ZIP | I17: Post code / ZIP. | K17: NÃO | L17: property_postcode | M17: LT004_PROTECTION.RL_ESTT_PST_CD
A18: V_17 | B18: Lien | C18: Lien position | D18: Numeric | E18: The highest ranking position(s) in relation to the collateral held by the counterparty to secure the facility. In case the facility has several liens on one collateral, the highest claim is reported in this data field. | G18: - | H18: - | I18: - | K18: SIM | L18: lien_position | M18: Reportar sempre: 1
A19: V_188 | B19: Valuation | C19: Date of protection value | D19: DD/MM/YYYY | E19: The date on which the latest appraisal or valuation of the protection was carried out prior to the reporting reference date. | G19: PROTECTION-DT_PRTCTN_VL | H19: Date of protection value | I19: The date on which the latest appraisal or valuation of the protection was carried out prior to the reporting reference date. | K19: NÃO | L19: date_protection_value | M19: LT004_PROTECTION.DT_PRTCTN_VL
A20: V_220 | B20: Valuation | C20: Protection value | D20: Numeric (euro) | E20: The amount of the protection value is the monetary value of the protection that was established at the latest valuation date | G20: PROTECTION-PRTCTN_VL | H20: Appraised market value | I20: The amount of the protection value as established for the relevant “Type of protection value” following the valuation approach. Market value from the appraisal without any haircut, in case a haircut is applied by the bank this should be in field HRCT_MV. In case of Guarantees, guaranteed amount. In case of Financial Assets, Market value of the asset. | K20: NÃO | L20: protection_value | M20: LT004_PROTECTION.PRTCTN_VL
A21: V_189 | B21: Protection characteristics | C21: Maturity date of the protection | D21: DD/MM/YYYY | E21: The contractual maturity date of the protection, which is the earliest date at which the protection may terminate or be terminated, taking into account any agreements amending initial contracts. | G21: PROTECTION-DT_MTRTY_PRTCTN | H21: Maturity date of the protection | I21: The contractual maturity date of the protection, which is the earliest date at which the protection may terminate or be terminated, taking into account any agreements amending initial contracts. | K21: NÃO | L21: maturity_date_protection | M21: LT004_PROTECTION.DT_MTRTY_PRTCTN
A22: V_190 | B22: Valuation | C22: Original protection value | D22: Numeric (euro) | E22: The monetary value of the protection item that was established at the date when the protection item was originally received as a credit protection. | G22: PROTECTION-ORGNL_PRTCTN_VL | H22: Original protection value (at inception) | I22: The original protection value is the monetary value of the protection item that was established at the date when the protection item was originally received as a credit protection. | K22: NÃO | L22: original_protection_value | M22: LT004_PROTECTION.ORGNL_PRTCTN_VL
... A27: V_218 | B27: Lien | C27: Third-party priority claims against the protection | D27: Numeric (euro) | E27: The maximum amount of any existing higher ranked liens with respect to third parties other than the observed agent against the protection. | G27: Not applicable: To be reported as "11111111111". This information will be availabe in "03_05_off_instr_prot" table | H27: - | I27: - | K27: SIM | L27: thirdparty_claims_protection | M27: Reportar sempre: 0

Sheet OFFBAL_INSTRUMENT_COUNTERPARTY
A1: Instruções SRB | G1: Mapeamento efetuado pela Corporação e respetiva Descrição Loan Tape (LT) | K1: Análise IT
A2: ID | B2: Categoria | C2: Coluna | D2: Tipo de dados | E2: Descrição | G2: Mapeamentos Corporação (LT) | H2: Descrição (LT) | I2: Additional Guidance (LT) | K2: Novo campo na tabela LT005? | L2: Nome do campo no ficheiro | M2: Mapeamento | N2: Notas
A3: V_1 | B3: Identification information | C3: Instrument Identifier | D3: Alphanumeric | E3: An identifier applied to uniquely identify each instrument. Each instrument must have one instrument identifier | G3: INSTR_ENTITY-INSTRMNT_ID | H3: Instrument ID | I3: An identifier applied by the reporting agent to uniquely identify each instrument under a single contract. Each instrument must have one instrument identifier. This value will not change over time and cannot be used as the instrument identifier for any other instrument under the same contract. Supervised Insitutions are asked to furnish the INSTRMNT_ID with the exact same value as it is reported to AnaCredit (or any similar central credit register). If this is not available, the value shall be reported as it is internally used. If an instrument is not reported to AnaCredit but requested for the purposes of the on-site inspection please provide the bank-internally used value. Foreign Key from INSTRUMENT table. | K3: NÃO | L3: instrument_id | M3: LT005_INSTR_ENT.INSTRMNT_ID
A7: V_2 | B7: Identification information | C7: Counterparty Identifier | D7: Alphanumeric | E7: Identifier applied to uniquely identify each counterparty. | G7: INSTR_ENTITY-ENTTY_ID | H7: Entity ID | I7: An identifier applied by the reporting agent to uniquely identify each counterparty. Each counterparty has a unique and exclusive counterparty identifier. This means that this value will not change over time and can never be used as the counterparty identifier for any other counterparty. Foreign key from ENTITY table. | K7: NÃO | L7: counterparty_id | M7: LT005_INSTR_ENT.ENTTY_ID
A8: V_167 | B8: Financial information | C8: Joint liabilities amount | D8: Numeric (euro) | E8: Outstanding nominal amount for which each debtor is liable in relation to a single instrument where there are two or more debtors. | G8: INSTR_ENTITY-JNT_LBLTY_AMNT | H8: Joint-liability amount | I8: Outstanding nominal amount for which each debtor is liable in relation to a single instrument where there are two or more debtors. In the case of instruments where there is only one debtor, please report "not applicable" using the respective fall-back parameters. | K8: NÃO | L8: joint_liabilities_amount | M8: LT005_INSTR_ENT.JNT_LBLTY_AMNT

Sheet OFFBAL_INSTRUMENT_PROTECTION
A1: Instruções SRB | G1: Mapeamento efetuado pela Corporação e respetiva Descrição Loan Tape (LT) | K1: Análise IT
A2: ID | B2: Categoria | C2: Coluna | D2: Tipo de dados | E2: Descrição | G2: Mapeamentos Corporação (LT) | H2: Descrição (LT) | I2: Additional Guidance (LT) | K2: Novo campo na tabela LT006? | L2: Nome do campo no ficheiro | M2: Mapeamento | N2: Notas
A3: V_1 | B3: Identification information | C3: Instrument Identifier | D3: Alphanumeric | E3: An identifier applied to uniquely identify each instrument. Each instrument must have one instrument identifier | G3: INSTR_PROTECTION-INSTRMNT_ID | H3: Instrument ID | I3: An identifier applied by the reporting agent to uniquely identify each instrument under a single contract. Each instrument must have one instrument identifier. This value will not change over time and cannot be used as the instrument identifier for any other instrument under the same contract. Supervised Insitutions are asked to furnish the INSTRMNT_ID with the exact same value as it is reported to AnaCredit (or any similar central credit register). If this is not available, the value shall be reported as it is internally used. If an instrument is not reported to AnaCredit but requested for the purposes of the on-site inspection please provide the bank-internally used value. Foreign Key from INSTRUMENT table. | K3: NÃO | L3: instrument_id | M3: LT006_INSTR_PROT.INSTRMNT_ID
A7: V_12 | B7: Identification information | C7: Protection identifier | D7: Alphanumeric | E7: An identifier applied to uniquely identify each protection/collateral used to secure the instrument. | G7: INSTR_PROTECTION-PRTCTN_ID | H7: Protection ID | I7: An identifier applied by the reporting agent to uniquely identify each protection used to secure the instrument. Each protection must have one protection identifier. This value will not change over time and cannot be used as the protection identifier for any other protection. Foreign Key from PROTECTION table. | K7: NÃO | L7: protection_id | M7: LT006_INSTR_PROT.PRTCTN_ID
A11: V_217 | B11: Valuation | C11: Protection allocated value | D11: Numeric (euro) | E11: The maximum amount of the protection value that can be considered as credit protection for the instrument. The amount of the existing third parties or observed agent priority claims against the protection must be excluded in the protection allocated value. | G11: INSTR_PROTECTION-PRTCTN_ALLCTD_VL | H11: Protection allocated value | I11: The maximum amount of the protection value that can be considered as credit protection for the instrument. The amount of the existing third parties or observed agent priority claims against the protection must be excluded in the protection allocated value. | K11: NÃO | L11: protection_allocated_value | M11: LT006_INSTR_PROT.PRTCTN_ALLCTD_VL
A12: V_218 | B12: Lien | C12: Third-party priority claims against the protection | D12: Numeric (euro) | E12: The maximum amount of any existing higher ranked liens with respect to third parties other than the observed agent against the protection. | G12: INSTR_PROTECTION-THRD_PRTY_PRRTY_CLMS | H12: Third party priority claims against the protection | I12: The maximum amount of any existing higher ranked liens with respect to third parties other than the observed agent against the protection. | K12: NÃO | L12: thirdparty_claims_protection | M12: LT006_INSTR_PROT.THRD_PRTY_PRRTY_CLMS

Sheet DERIVATIVES Data Set
A1: SRB DERIVATIVES DATA SET The SRB Valuation Data Set does not cover data points reported under Article 9 of Regulation (EU) No 648/2012 (European Market Infrastructure Regulation (EMIR)), as detailed under the Commission Delegated Regulation (EU) No 148/2013, which imposes reporting obligations to counterparties and central clearing counterparties (CCPs). Reporting obligations cover any derivative contract that they may have concluded and any modification or termination of the contract. Counterparties should report such information to registered or recognized trade repositories no later than the working day following the conclusion, modification or termination of the contract. Where a trade repository is not available to record the details of a derivative contract, counterparties and CCPs must ensure that such details are reported to the European Securities and market Authority (ESMA). Pursuant to Article 2 of Implementing Regulation (EU) No 1247/2012, ‘mark-to market’ or ‘mark-to-model’ valuations must be reported on a daily basis. Any other reporting elements must be reported as they occur or change, taking into account time limits envisaged in Article 9 of EMIR, notably as regards the conclusion, modification or termination of a contract. In addition to reporting obligations stemming from EMIR, Delegated Regulation (EU) No 2016/1712 supplementing BRRD establishes standards that specify the minimum set of information on financial contracts that should be contained within the detailed records. As per this Regulation, entities under the scope of the BRRD should maintain detailed records of financial contracts where the resolution plan foresees taking resolution actions. The EBA Data Dictionary and the SRB Valuation Data Set take into account many of the data points contained in the Delegated Regulation. Article 2 (16) of Commission Delegated Regulation (EU) No 151/2013 amended by Commission Delegated Regulation (EU) No 2019/361 with regard to access to the data held in trade repositories establishes that trade repository shall provide the SRB with access to all transaction data on derivatives concluded by counterparties that fall under the scope of Regulation (EU) No 806/2014 (SRMR). As stressed above, the SRB Valuation Data Set, which is comprised of various subsets, should be defined by the IRT for each individual credit institution9 based on various considerations including the business model and risk profile. Valuations in resolution may be negatively affected by economic losses arising from derivatives’ portfolios. Should derivatives allocated in the trading book or derivatives priced or valued using ‘mark-to-model’ (i.e. Level 3) be of relevance in the balance sheet of credit institutions, the latter should keep records of such exposures. The SRB Valuation Data Set covers a detailed list of data points on derivatives contracts irrespective of their positive / negative fair value on the date of valuation. The data listed in the derivatives table should be reported at single contract level and take into account specificities regarding margin requirements. Será produzido o ficheiro: ‣ SRB DERIVATIVES DATA SET (DERIVATIVES);
A2: SRB derivatives Data Set O conjunto de dados de avaliação do CUR não abrange os dados comunicados nos termos do artigo 9.º do Regulamento (UE) n.º 648/2012 (Regulamento sobre a Infraestrutura do Mercado Europeu (EMIR)), conforme detalhado no Regulamento Delegado (UE) n.º 148/2013 da Comissão, que impõe obrigações de comunicação de informações às contrapartes7 e às contrapartes centrais de compensação (CCP). As obrigações de comunicação abrangem qualquer contrato de derivativos que possam ter celebrado e qualquer modificação ou rescisão do contrato. As contrapartes devem comunicar essas informações a entidades registadas ou reconhecidas. repositórios de transações o mais tardar no dia útil seguinte à conclusão, modificação ou rescisão do contrato. Caso não esteja disponível um repositório de transações para registar os dados de um contrato de derivados, as contrapartes e as CCP devem garantir que esses dados são comunicados às a Autoridade Europeia dos Valores Mobiliários e dos Mercados (ESMA). Nos termos do artigo 2.º do Regulamento de Execução (UE) n.º 1247/2012, as avaliações «avaliação ao mercado» ou «avaliação ao modelo» devem ser comunicadas diariamente. Quaisquer outros elementos de reporte devem ser reportados à medida que ocorrem ou mudam, tendo em conta os prazos previstos no artigo 9.º do EMIR, nomeadamente no que diz respeito à celebração, alteração ou rescisão de um contrato. Além das obrigações de comunicação decorrentes do EMIR, o Regulamento Delegado (UE) 2016/1712, que complementa a BRRD, estabelece normas que especificam o conjunto mínimo de informações sobre contratos financeiros8 que devem constar dos registros detalhados. Como nos termos do presente regulamento, as entidades abrangidas pela BRRD devem manter registos detalhados dos contratos financeiros relativamente aos quais o plano de resolução prevê a tomada de medidas de resolução. A EBA O Dicionário de Dados e o Conjunto de Dados de Avaliação SRB levam em consideração muitos dos pontos de dados contidas no Regulamento Delegado. Artigo 2.º, n.º 16, do Regulamento Delegado (UE) n.º 151/2013 da Comissão, alterado por Regulamento Delegado (UE) n.º 2019/361 da Comissão no que diz respeito ao acesso aos dados conservados nos repositórios de transações estabelece que o repositório de transações deve fornecer ao CUR acesso a todos os dados de transações sobre derivados celebrados por contrapartes abrangidas pelo âmbito de aplicação do Regulamento (UE) n.º 806/2014 (SRMR). Serão produzidos três ficheiros de report referentes a Natural Persons: ‣ SRB derivatives Data Set (VDS_OUT_DERIVATIVES);

Sheet DERIVATIVES
A1: Instruções SRB | G1: Mapeamento efetuado pela Corporação e respetiva Descrição Loan Tape (LT) | K1: Análise IT
A2: ID | B2: Categoria | C2: Coluna | D2: Tipo de dados | E2: Descrição | G2: Mapeamentos Corporação (LT) | H2: Descrição (LT) | I2: Additional Guidance (LT) | K2: Novo campo na tabela LT002? | L2: Nome do campo no ficheiro | M2: Mapeamento | N2: Notas
A3: V_140 | B3: Parties to the financial contract | C3: Unique trade identifier | D3: Until global UTI is available, up to 52 alphanumerical character code including four special characters : “”. - _.””. Special characters are not allowed at the beginning and at the end of the code. No space allowed. | E3: As per EMIR revised ITS Article 4a. | G3: - | K3: SIM | L3: unique_trade_id | M3: Esta informação não existia no datalake, foi endereçado um desenvolvimento às areas de ALM e SIGOM de forma a passar a aprovisionar esta informação nas tabelas al005_det_swapc e al011_derivados | N3: Em análise
A7: V_2 | B7: Parties to the financial contract | C7: Counterparty ID | D7: Alphanumeric | E7: Code used to identify the reporting counterparty. Where a contract is concluded in a trading venue and cleared by a CCP such that a counterparty is not aware of the identity of the other counterparty, the entity must identify that CCP as its counterparty. | G7: - | K7: SIM | L7: counterparty_id | M7: 1º Passo - Cruzar LT002_INSTRUMENT com as tabelas AL005_DET_SWAPC, AL011_DERIVADOS, AL602_REPOS_ALM, AL611_DERIV_AUX, AL613_SWAPSC_AUX, para filtrar apenas o universo de contratos de Derivados e REPOS: SELECT lt002.INSTRMNT_ID, kt_chaves_fr.INSTRMNT_ID_MASTER FROM ( SELECT INSTRMNT_ID FROM cd_loan_tapes_bce.lt002_instrument WHERE ref_date = '2024-09-30' ) as lt002 INNER JOIN ( SELECT CONCAT(cempresa_fr,cbalcao_fr,cnumecta_fr,zdeposit_fr) as INSTRMNT_ID, CONCAT(cempresa,cbalcao,cnumecta,zdeposit) as INSTRMNT_ID_MASTER FROM cd_captools.kt_chaves_finrep WHERE ref_date = '2024-09-30' ) as kt_chaves_fr ON lt002.INSTRMNT_ID = kt_chaves_fr.INSTRMNT_ID INNER JOIN ( SELECT CONCAT(cempresa_master,cbalcao_master,cnumecta_master,zdeposit_master) as INSTRMNT_ID_MASTER, CONCAT(cempresa,cbalcao,cnumecta,zdeposit) as INSTRMNT_ID_ALM FROM cd_alm.kt_chaves_alm_m WHERE ref_date = '2024-09-30' ) as kt_chaves_alm ON kt_chaves_fr.INSTRMNT_ID_MASTER = kt_chaves_alm.INSTRMNT_ID_MASTER INNER JOIN ( SELECT CONCAT(cempresa,cbalcao,cnumecta,zdeposit) as INSTRMNT_ID_ALM FROM cd_alm.al005_det_swapc WHERE ref_date = '2024-09-30' UNION SELECT CONCAT(cempresa,cbalcao,cnumecta,zdeposit) as INSTRMNT_ID_ALM FROM cd_alm.al011_derivados WHERE ref_date = '2024-09-30' UNION SELECT CONCAT(cempresa,cbalcao,cnumecta,zdeposit) as INSTRMNT_ID_ALM FROM cd_alm.al602_repos_alm WHERE ref_date = '2024-09-30' AND flag_ativo = '1' UNION SELECT CONCAT(cempresa,cbalcao,cnumecta,zdeposit) as INSTRMNT_ID_ALM FROM cd_alm.al611_deriv_aux WHERE ref_date = '2024-09-30' UNION SELECT CONCAT('6416 ', CASE WHEN substr(cid_sigom,1,4) = '+000' THEN rpad(concat(substr(coperacao,1,3),substr(cid_sigom,5,6)),15,'0') WHEN substr(cid_sigom,1,3) = '+00' THEN rpad(concat(substr(coperacao,1,3),substr(cid_sigom,4,7)),15,'0') WHEN substr(cid_sigom,1,2) = '+0' THEN rpad(concat(substr(coperacao,1,3),substr(cid_sigom,3,8)),15,'0') WHEN ((substr(cid_sigom,1,2) != '+0') OR (substr(cid_sigom,1,3) != '+00') OR (substr(cid_sigom,1,4) != '+000')) AND (coperacao IS NOT NULL) THEN concat(substr(coperacao,1,3),substr(cid_sigom,2,9),'00') WHEN coperacao IS NULL THEN rpad(concat(coperacao, ' '),15,' ') END ) as INSTRMNT_ID_ALM FROM cd_alm. al613_swapsc_aux WHERE ref_date = '2024-09-30' ) as cntr_derv_repo ON cntr_derv_repo.INSTRMNT_ID_ALM = kt_chaves_alm.INSTRMNT_ID_ALM 2º Passo - Cruzar o universo de contratos definido acima (UNIV) com a tabela CL001_INTERV_CTO, de forma a determinar para cada contrato o 1º titular (UNIV_DERV_REPO). Se para um contrato não houver um 1º titular associado na cl001 então usar o zcliente contabilistico (fr004): SELECT UNIV.INSTRMNT_ID, NVL(cl001.zcliente, fr004.zcliente) as ENTTY_ID FROM UNIV LEFT JOIN ( SELECT CONCAT(cempresa,cbalcao,cnumecta,zdeposit) as INSTRMNT_ID_MASTER, zcliente FROM cd_clientes.cl001_interv_cto WHERE ref_date = '2024-08-31' AND TRIM(crelacao_cl_cnt) = '1' AND csequencia_rel ='00001' ) as cl001 ON cl001.INSTRMNT_ID_MASTER = UNIV.INSTRMNT_ID_MASTER LEFT JOIN ( SELECT CONCAT(cempresa,cbalcao,cnumecta,zdeposit) as INSTRMNT_ID, zcliente FROM cd_captools.fr004_cto WHERE ref_date = '2024-08-31' ) as fr004 ON fr004.INSTRMNT_ID = UNIV.INSTRMNT_ID 3º Passo - Agora que se obteve o universo de contratos de Derivados e REPOs associados aos seus primeiros titulares, deve-se replicar exatamente a mesma lógica aplicada no campo ISSR_ID da tabela LT002: Metodologia de cruzamento: 1) Cruzar o universo obtido no 2º Passo (UNIV_DERV_REPO) com o universo de clientes para obter o CLEI, CCLI_GRUPO, CNUM_DOC_IDENTIF2 e CTIPO_DOC_IDENTIF2. UNIV_DERV_REPO LEFT JOIN (SELECT * FROM CT003_UNIV_CLI) AS CT003 ON CT003.ZCLIENTE = UNIV_DERV_REPO.ENTTY_ID 2) Cruzar com a tabela TAT 151 para obter os códigos correspondentes ao TAX ID LEFT JOIN (SELECT * FROM TAT91_TABELAS) ON TAYD91C0_CELEMTAB = CTIPO_DOC_IDENTIF2 3) Cruzar com o universo de clientes para obter o valor máximo do campo CLEI (MAX_CLEI) para cada CCLI_GRUPO LEFT JOIN (SELECT * FROM CT003_UNIV_CLI GROUP BY CCLI_GRUPO) ON CCLI_GRUPO = CCLI_GRUPO Metodologia de Cálculo: 1.Obtenção do campo TAX_ID: CASE WHEN LENGTH(CAST(CAST(CNUM_DOC_IDENTIF2 AS INT) AS STRING)) = 9 AND TAYD91C0_CELEMTAB IS NOT NULL THEN CAST (CAST(CNUM_DOC_IDENTIF2 AS INT) AS STRING) ELSE 'MISS' END 2.Obtenção do campo MAX_CLEI: MAX(CLEI) WHERE CLEI <> '#' 3.Obtenção do campo ISSR_ID: CASE WHEN TRIM(CLEI) NOT IN (''; '#') THEN CLEI WHEN TRIM(CLEI) IN ('';'#') AND TRIM(CCLI_GRUPO) <> '' AND MAX_CLEI IS NOT NULL THEN MAX_CLEI WHEN TRIM(CLEI) IN ('';'#') AND TRIM(CCLI_GRUPO) <> '' AND MAX_CLEI IS NULL AND TAX_ID <> 'MISS' THEN TAX_ID ELSE ZCLIENTE WHERE TAT91_TABELAS.TAYD91C0_CTABELA = '151' AND TAT91_TABELAS.TAYD91C0_GELEMTAB LIKE 'CONTRIBUINTE%' OR TAT91_TABELAS.TAYD91C0_GELEMTAB LIKE 'NUMERO DE CONTRIBUINTE%' OR TAT91_TABELAS.TAYD91C0_GELEMTAB LIKE 'ESTADO E EQUIPARADOS'
A9: V_24 | B9: Parties to the financial contract | C9: Type of ID of the counterparty of the reporting entity | D9: String | E9: Type of code used to identify the reporting counterparty. Options based on ECB’s Securities Holding Statistics (field CL_SHS_ID_TYPE) | G9: - | K9: SIM | L9: counterparty_type_id | M9: NOTA: Os passos 1 e 2 são iguais ao campo 'counterparty_id', ou seja ambos os campos deveriam ser produzidos em conjunto. 1º Passo - Cruzar LT002_INSTRUMENT com as tabelas AL005_DET_SWAPC, AL011_DERIVADOS, AL602_REPOS_ALM, AL611_DERIV_AUX, AL613_SWAPSC_AUX, para filtrar apenas o universo de contratos de Derivados e REPOS: SELECT lt002.INSTRMNT_ID, kt_chaves_fr.INSTRMNT_ID_MASTER FROM ( SELECT INSTRMNT_ID FROM cd_loan_tapes_bce.lt002_instrument WHERE ref_date = '2024-09-30' ) as lt002 INNER JOIN ( SELECT CONCAT(cempresa_fr,cbalcao_fr,cnumecta_fr,zdeposit_fr) as INSTRMNT_ID, CONCAT(cempresa,cbalcao,cnumecta,zdeposit) as INSTRMNT_ID_MASTER FROM cd_captools.kt_chaves_finrep WHERE ref_date = '2024-09-30' ) as kt_chaves_fr ON lt002.INSTRMNT_ID = kt_chaves_fr.INSTRMNT_ID INNER JOIN ( SELECT CONCAT(cempresa_master,cbalcao_master,cnumecta_master,zdeposit_master) as INSTRMNT_ID_MASTER, CONCAT(cempresa,cbalcao,cnumecta,zdeposit) as INSTRMNT_ID_ALM FROM cd_alm.kt_chaves_alm_m WHERE ref_date = '2024-09-30' ) as kt_chaves_alm ON kt_chaves_fr.INSTRMNT_ID_MASTER = kt_chaves_alm.INSTRMNT_ID_MASTER INNER JOIN ( SELECT CONCAT(cempresa,cbalcao,cnumecta,zdeposit) as INSTRMNT_ID_ALM FROM cd_alm.al005_det_swapc WHERE ref_date = '2024-09-30' UNION SELECT CONCAT(cempresa,cbalcao,cnumecta,zdeposit) as INSTRMNT_ID_ALM FROM cd_alm.al011_derivados WHERE ref_date = '2024-09-30' UNION SELECT CONCAT(cempresa,cbalcao,cnumecta,zdeposit) as INSTRMNT_ID_ALM FROM cd_alm.al602_repos_alm WHERE ref_date = '2024-09-30' AND flag_ativo = '1' UNION SELECT CONCAT(cempresa,cbalcao,cnumecta,zdeposit) as INSTRMNT_ID_ALM FROM cd_alm.al611_deriv_aux WHERE ref_date = '2024-09-30' UNION SELECT CONCAT('6416 ', CASE WHEN substr(cid_sigom,1,4) = '+000' THEN rpad(concat(substr(coperacao,1,3),substr(cid_sigom,5,6)),15,'0') WHEN substr(cid_sigom,1,3) = '+00' THEN rpad(concat(substr(coperacao,1,3),substr(cid_sigom,4,7)),15,'0') WHEN substr(cid_sigom,1,2) = '+0' THEN rpad(concat(substr(coperacao,1,3),substr(cid_sigom,3,8)),15,'0') WHEN ((substr(cid_sigom,1,2) != '+0') OR (substr(cid_sigom,1,3) != '+00') OR (substr(cid_sigom,1,4) != '+000')) AND (coperacao IS NOT NULL) THEN concat(substr(coperacao,1,3),substr(cid_sigom,2,9),'00') WHEN coperacao IS NULL THEN rpad(concat(coperacao, ' '),15,' ') END ) as INSTRMNT_ID_ALM FROM cd_alm. al613_swapsc_aux WHERE ref_date = '2024-09-30' ) as cntr_derv_repo ON cntr_derv_repo.INSTRMNT_ID_ALM = kt_chaves_alm.INSTRMNT_ID_ALM 2º Passo - Cruzar o universo de contratos definido acima (UNIV) com a tabela CL001_INTERV_CTO, de forma a determinar para cada contrato o 1º titular (UNIV_DERV_REPO). Se para um contrato não houver um 1º titular associado na cl001 então usar o zcliente contabilistico (fr004): SELECT UNIV.INSTRMNT_ID, NVL(cl001.zcliente, fr004.zcliente) as ENTTY_ID FROM UNIV LEFT JOIN ( SELECT CONCAT(cempresa,cbalcao,cnumecta,zdeposit) as INSTRMNT_ID_MASTER, zcliente FROM cd_clientes.cl001_interv_cto WHERE ref_date = '2024-08-31' AND TRIM(crelacao_cl_cnt) = '1' AND csequencia_rel ='00001' ) as cl001 ON cl001.INSTRMNT_ID_MASTER = UNIV.INSTRMNT_ID_MASTER LEFT JOIN ( SELECT CONCAT(cempresa,cbalcao,cnumecta,zdeposit) as INSTRMNT_ID, zcliente FROM cd_captools.fr004_cto WHERE ref_date = '2024-08-31' ) as fr004 ON fr004.INSTRMNT_ID = UNIV.INSTRMNT_ID 3º Passo - Agora que se obteve o universo de contratos de Derivados e REPOs associados aos seus primeiros titulares, deve-se replicar exatamente a mesma lógica aplicada no campo ISSR_ID_TYP da tabela LT002: Realizar metodologia de cruzamento semelhante à implementada no campo ISSR_ID. Quando ISSR_ID = CLEI ou ISSR_ID = MAX_CLEI, assumir 'LEI', quando o ISSR_ID = TAX_ID, assumir 'TAX', quando ISSR_ID = ZCLIENTE, assumir 'OTHER'
A10: V_25 | B10: Parties to the financial contract | C10: Country of the counterparty | D10: String | E10: The country code of the country where the registered office of the counterparty is located. based on ECB’s Securities Holding Statistics (field CL_SHS_ISSUER_AREA) | G10: - | K10: SIM | L10: counterparty_country | M10: NOTA: Os passos 1 e 2 são iguais ao campo 'counterparty_id', ou seja ambos os campos deveriam ser produzidos em conjunto. 1º Passo - Cruzar LT002_INSTRUMENT com as tabelas AL005_DET_SWAPC, AL011_DERIVADOS, AL602_REPOS_ALM, AL611_DERIV_AUX, AL613_SWAPSC_AUX, para filtrar apenas o universo de contratos de Derivados e REPOS: SELECT lt002.INSTRMNT_ID, kt_chaves_fr.INSTRMNT_ID_MASTER FROM ( SELECT INSTRMNT_ID FROM cd_loan_tapes_bce.lt002_instrument WHERE ref_date = '2024-09-30' ) as lt002 INNER JOIN ( SELECT CONCAT(cempresa_fr,cbalcao_fr,cnumecta_fr,zdeposit_fr) as INSTRMNT_ID, CONCAT(cempresa,cbalcao,cnumecta,zdeposit) as INSTRMNT_ID_MASTER FROM cd_captools.kt_chaves_finrep WHERE ref_date = '2024-09-30' ) as kt_chaves_fr ON lt002.INSTRMNT_ID = kt_chaves_fr.INSTRMNT_ID INNER JOIN ( SELECT CONCAT(cempresa_master,cbalcao_master,cnumecta_master,zdeposit_master) as INSTRMNT_ID_MASTER, CONCAT(cempresa,cbalcao,cnumecta,zdeposit) as INSTRMNT_ID_ALM FROM cd_alm.kt_chaves_alm_m WHERE ref_date = '2024-09-30' ) as kt_chaves_alm ON kt_chaves_fr.INSTRMNT_ID_MASTER = kt_chaves_alm.INSTRMNT_ID_MASTER INNER JOIN ( SELECT CONCAT(cempresa,cbalcao,cnumecta,zdeposit) as INSTRMNT_ID_ALM FROM cd_alm.al005_det_swapc WHERE ref_date = '2024-09-30' UNION SELECT CONCAT(cempresa,cbalcao,cnumecta,zdeposit) as INSTRMNT_ID_ALM FROM cd_alm.al011_derivados WHERE ref_date = '2024-09-30' UNION SELECT CONCAT(cempresa,cbalcao,cnumecta,zdeposit) as INSTRMNT_ID_ALM FROM cd_alm.al602_repos_alm WHERE ref_date = '2024-09-30' AND flag_ativo = '1' UNION SELECT CONCAT(cempresa,cbalcao,cnumecta,zdeposit) as INSTRMNT_ID_ALM FROM cd_alm.al611_deriv_aux WHERE ref_date = '2024-09-30' UNION SELECT CONCAT('6416 ', CASE WHEN substr(cid_sigom,1,4) = '+000' THEN rpad(concat(substr(coperacao,1,3),substr(cid_sigom,5,6)),15,'0') WHEN substr(cid_sigom,1,3) = '+00' THEN rpad(concat(substr(coperacao,1,3),substr(cid_sigom,4,7)),15,'0') WHEN substr(cid_sigom,1,2) = '+0' THEN rpad(concat(substr(coperacao,1,3),substr(cid_sigom,3,8)),15,'0') WHEN ((substr(cid_sigom,1,2) != '+0') OR (substr(cid_sigom,1,3) != '+00') OR (substr(cid_sigom,1,4) != '+000')) AND (coperacao IS NOT NULL) THEN concat(substr(coperacao,1,3),substr(cid_sigom,2,9),'00') WHEN coperacao IS NULL THEN rpad(concat(coperacao, ' '),15,' ') END ) as INSTRMNT_ID_ALM FROM cd_alm. al613_swapsc_aux WHERE ref_date = '2024-09-30' ) as cntr_derv_repo ON cntr_derv_repo.INSTRMNT_ID_ALM = kt_chaves_alm.INSTRMNT_ID_ALM 2º Passo - Cruzar o universo de contratos definido acima (UNIV) com a tabela CL001_INTERV_CTO, de forma a determinar para cada contrato o 1º titular (UNIV_DERV_REPO). Se para um contrato não houver um 1º titular associado na cl001 então usar o zcliente contabilistico (fr004): SELECT UNIV.INSTRMNT_ID, NVL(cl001.zcliente, fr004.zcliente) as ENTTY_ID FROM UNIV LEFT JOIN ( SELECT CONCAT(cempresa,cbalcao,cnumecta,zdeposit) as INSTRMNT_ID_MASTER, zcliente FROM cd_clientes.cl001_interv_cto WHERE ref_date = '2024-08-31' AND TRIM(crelacao_cl_cnt) = '1' AND csequencia_rel ='00001' ) as cl001 ON cl001.INSTRMNT_ID_MASTER = UNIV.INSTRMNT_ID_MASTER LEFT JOIN ( SELECT CONCAT(cempresa,cbalcao,cnumecta,zdeposit) as INSTRMNT_ID, zcliente FROM cd_captools.fr004_cto WHERE ref_date = '2024-08-31' ) as fr004 ON fr004.INSTRMNT_ID = UNIV.INSTRMNT_ID 3º Passo - Agora que se obteve o universo de contratos de Derivados e REPOs associados aos seus primeiros titulares, deve-se replicar exatamente a mesma lógica aplicada no campo ISSR_CNTRY da tabela LT002: NOTA: Como é um novo campo e já se confirmou que a parametrização presente no campo_lt = 'CNTRY' da tabela LT803 não responde ao pedido pelo SRB, então terá de se criar uma nova parametrização na nova tabela LT831. Metodologia de cruzamento (Alterar quando se fechar a parametrização): 1) Cruzar o universo obtido no 2º Passo (UNIV_DERV_REPO) com o universo de clientes para obter o CPAIS_RESIDENCIA. UNIV_DERV_REPO LEFT JOIN (SELECT * FROM CT003_UNIV_CLI) ON ZCLIENTE = UNIV_DERV_REPO.ENTTY_ID 2) Cruzar com a informação da tabela de parametrização LEFT JOIN SELECT * FROM LT803_CODIGOS_LT ON VALOR_ORIGEM = CPAIS_RESIDENCIA Metodologia de Cálculo (Alterar quando se fechar a parametrização): VALOR_LT WHERE CAMPO_LT = 'CNTRY' AND VALOR_ORIGEM = CPAIS_RESIDENCIA ‣ Falta acabar de definir a parametrização a aplicar neste campo | N10: Em análise
A11: V_26 | B11: Exposure class | C11: Base product | D11: String | E11: Options: ‣ For Credit (1): Single Name (1.1); Index Tranche (1.2); Index (1.3); Total Return Swap (1.4); Total Return Swap Index (1.5); Exotic(1.6) ‣ For Interest Rate (2): IR Swap (2.1); FRA (2.2); CapFloor (2.3); Cross Currency (2.4); Forward (2.5); Option (2.6); Exotic (2.7); Swaptions (2.8) ‣ For Commodity (3): Metals (3.1); Energy (3.2); Index (3.3); Agricultural (3.4); Environmental (3.5); Freight (3.6); Multi Commodity Exotic (3.7) ‣ For Foreign Exchange (4): Spot (4.1); NDF (4.2); NDO (4.3); Forward (4.4); Vanilla Option (4.5); Simple Exotic (4.6); Complex Exotic (4.7) ‣ For Equity (5): Swap (5.1); Portfolio Swap (5.2); Contract for difference (5.3); Option (5.4); Forward (5.5); Other (5.6) | G11: - | K11: SIM | L11: base_product | M11: Esta informação não existia no datalake, foi endereçado um desenvolvimento às areas de ALM e SIGOM de forma a passar a aprovisionar esta informação nas tabelas al005_det_swapc e al011_derivados. | N11: Em análise
A12: V_27 | B12: Specific information | C12: Product ID | D12: Alphanumeric | G12: - | K12: NÃO | L12: product_id | M12: LT002_INSTRUMENT.PRDCT
A13: V_28 | B13: Specific information | C13: Governing law | D13: String | E13: Identify the law governing the financial contract. Options based on ECB’s Securities Holding Statistics (field CL_SHS_ISSUER_AREA) | G13: - | K13: SIM | L13: governing_law | M13: Esta informação não existia no datalake, foi endereçado um desenvolvimento às areas de ALM e SIGOM de forma a passar a aprovisionar esta informação nas tabelas al005_det_swapc e al011_derivados. | N13: Em análise
A14: V_29 | B14: Specific information | C14: Contractual recognition – Write down and conversion powers (only for contracts governed by thirdcountry laws subject to the requirement of the contractual terms under the first subparagraph of Article 55(1) of BRRD) | D14: String | E14: The contractual term required under Article 55(1) of the BRRD. When such a contractual term is included in a master agreement and applies to all trades governed by this agreement, it can be recorded at the master agreement level. Options: ‣ YES (1) ‣ NO (2) | G14: - | K14: SIM | L14: contract_recogn_write_down | M14: Regra quase finalizada, falta confirmar a forma correta de verificar se um contrato Finrep está ao abrigo de um contrato ISDA. Query proposta: SELECT instrmnt_id, IF(al012.zcliente IS NOT NULL AND al029.dinicio <= '2022-10-01', 'YES (1)', 'NO (2)' ) as contract_recogn_write_down, IF(al012.zcliente IS NOT NULL AND al029.dinicio <= '2022-10-01', 'YES (1)', 'NO (2)' ) as contract_recogn_suspension, IF(al012.zcliente IS NOT NULL AND al029.dinicio <= '2022-10-01', 'YES (1)', 'NO (2)' ) as contract_recogn_resolution FROM ( SELECT instrmnt_id FROM bu_loantape_work.lt002_instrument_srb WHERE ambito = 'SRB_VALUATION' AND segmento = 'Derivatives' AND ref_date = '2024-11-30' ) as lt002 -- 496 LEFT JOIN ( SELECT CONCAT(cempresa_fr,cbalcao_fr,cnumecta_fr,zdeposit_fr) as contract_id_fr, CONCAT(cempresa,cbalcao,cnumecta,zdeposit) as contract_id_ct FROM cd_captools.kt_chaves_finrep WHERE ref_date = '2024-11-30' ) as chaves_finrep ON chaves_finrep.contract_id_fr = lt002.instrmnt_id LEFT JOIN ( SELECT CONCAT(cempresa_master,cbalcao_master,cnumecta_master,zdeposit_master) as contract_id_ct, CONCAT(cempresa,cbalcao,cnumecta,zdeposit) as contract_id_alm FROM cd_alm.kt_chaves_alm_m WHERE ref_date = '2024-11-30' ) as chaves_alm ON chaves_alm.contract_id_ct = chaves_finrep.contract_id_ct LEFT JOIN ( SELECT CONCAT(cempresa,cbalcao,cnumecta,zdeposit) as contract_id_alm, zcliente, dinicio FROM cd_alm.al029_cnt_core_m WHERE ref_date = '2024-11-30' ) as al029 ON chaves_alm.contract_id_alm = al029.contract_id_alm LEFT JOIN ( SELECT zcliente FROM cd_alm.al012_cq_alm WHERE ref_date = '2024-11-30' AND operativa = 'Derivados' AND cod_tip_contrato = 'ISDA' GROUP BY zcliente ) as al012 ON al029.zcliente = al012.zcliente | N14: Em análise
A15: V_30 | B15: Specific information | C15: Contractual recognition – Suspension of termination rights (only for contracts governed by third-country laws) under Article 7 BRRD | D15: String | E15: The contractual term by which the creditor or party to the agreement creating the liability recognises the power of the resolution authority of a Member State to suspend termination rights. When such a contractual term is included in a master agreement and applies to all trades governed by this agreement, it can be recorded at the master agreement level. Options: ‣ YES (1) ‣ NO (2) | G15: - | K15: SIM | L15: contract_recogn_suspension | M15: Regra quase finalizada, falta confirmar a forma correta de verificar se um contrato Finrep está ao abrigo de um contrato ISDA. Query proposta: SELECT instrmnt_id, IF(al012.zcliente IS NOT NULL AND al029.dinicio <= '2022-10-01', 'YES (1)', 'NO (2)' ) as contract_recogn_write_down, IF(al012.zcliente IS NOT NULL AND al029.dinicio <= '2022-10-01', 'YES (1)', 'NO (2)' ) as contract_recogn_suspension, IF(al012.zcliente IS NOT NULL AND al029.dinicio <= '2022-10-01', 'YES (1)', 'NO (2)' ) as contract_recogn_resolution FROM ( SELECT instrmnt_id FROM bu_loantape_work.lt002_instrument_srb WHERE ambito = 'SRB_VALUATION' AND segmento = 'Derivatives' AND ref_date = '2024-11-30' ) as lt002 -- 496 LEFT JOIN ( SELECT CONCAT(cempresa_fr,cbalcao_fr,cnumecta_fr,zdeposit_fr) as contract_id_fr, CONCAT(cempresa,cbalcao,cnumecta,zdeposit) as contract_id_ct FROM cd_captools.kt_chaves_finrep WHERE ref_date = '2024-11-30' ) as chaves_finrep ON chaves_finrep.contract_id_fr = lt002.instrmnt_id LEFT JOIN ( SELECT CONCAT(cempresa_master,cbalcao_master,cnumecta_master,zdeposit_master) as contract_id_ct, CONCAT(cempresa,cbalcao,cnumecta,zdeposit) as contract_id_alm FROM cd_alm.kt_chaves_alm_m WHERE ref_date = '2024-11-30' ) as chaves_alm ON chaves_alm.contract_id_ct = chaves_finrep.contract_id_ct LEFT JOIN ( SELECT CONCAT(cempresa,cbalcao,cnumecta,zdeposit) as contract_id_alm, zcliente, dinicio FROM cd_alm.al029_cnt_core_m WHERE ref_date = '2024-11-30' ) as al029 ON chaves_alm.contract_id_alm = al029.contract_id_alm LEFT JOIN ( SELECT zcliente FROM cd_alm.al012_cq_alm WHERE ref_date = '2024-11-30' AND operativa = 'Derivados' AND cod_tip_contrato = 'ISDA' GROUP BY zcliente ) as al012 ON al029.zcliente = al012.zcliente | N15: Em análise
A16: V_31 | B16: Specific information | C16: Contractual recognition – Resolution powers (only for contracts governed by third-country laws) | D16: String | E16: The contractual term, if any, by which the creditor or party to the agreement creating the liability recognises the power of the resolution authority of a Member State to apply resolution powers other than write down and conversion / suspension. When such a contractual term is included in a master agreement and applies to all trades governed by this agreement, it can be recorded at the master agreement level. Options: ‣ YES (1) ‣ NO (2) | G16: - | K16: SIM | L16: contract_recogn_resolution | M16: Regra quase finalizada, falta confirmar a forma correta de verificar se um contrato Finrep está ao abrigo de um contrato ISDA. Query proposta: SELECT instrmnt_id, IF(al012.zcliente IS NOT NULL AND al029.dinicio <= '2022-10-01', 'YES (1)', 'NO (2)' ) as contract_recogn_write_down, IF(al012.zcliente IS NOT NULL AND al029.dinicio <= '2022-10-01', 'YES (1)', 'NO (2)' ) as contract_recogn_suspension, IF(al012.zcliente IS NOT NULL AND al029.dinicio <= '2022-10-01', 'YES (1)', 'NO (2)' ) as contract_recogn_resolution FROM ( SELECT instrmnt_id FROM bu_loantape_work.lt002_instrument_srb WHERE ambito = 'SRB_VALUATION' AND segmento = 'Derivatives' AND ref_date = '2024-11-30' ) as lt002 -- 496 LEFT JOIN ( SELECT CONCAT(cempresa_fr,cbalcao_fr,cnumecta_fr,zdeposit_fr) as contract_id_fr, CONCAT(cempresa,cbalcao,cnumecta,zdeposit) as contract_id_ct FROM cd_captools.kt_chaves_finrep WHERE ref_date = '2024-11-30' ) as chaves_finrep ON chaves_finrep.contract_id_fr = lt002.instrmnt_id LEFT JOIN ( SELECT CONCAT(cempresa_master,cbalcao_master,cnumecta_master,zdeposit_master) as contract_id_ct, CONCAT(cempresa,cbalcao,cnumecta,zdeposit) as contract_id_alm FROM cd_alm.kt_chaves_alm_m WHERE ref_date = '2024-11-30' ) as chaves_alm ON chaves_alm.contract_id_ct = chaves_finrep.contract_id_ct LEFT JOIN ( SELECT CONCAT(cempresa,cbalcao,cnumecta,zdeposit) as contract_id_alm, zcliente, dinicio FROM cd_alm.al029_cnt_core_m WHERE ref_date = '2024-11-30' ) as al029 ON chaves_alm.contract_id_alm = al029.contract_id_alm LEFT JOIN ( SELECT zcliente FROM cd_alm.al012_cq_alm WHERE ref_date = '2024-11-30' AND operativa = 'Derivados' AND cod_tip_contrato = 'ISDA' GROUP BY zcliente ) as al012 ON al029.zcliente = al012.zcliente | N16: Em análise
A17: V_32 | B17: Collateral information | C17: Collateral portfolio | D17: String | E17: State whether the collateralisation was performed on a portfolio basis. Portfolio means the collateral calculated on the basis of net positions resulting from a set of contracts, rather than per trade. Options: ‣ YES (1) ‣ NO (2) | G17: - | K17: SIM | L17: collateral_portfolio | M17: Conceito a revisitar no futuro | N17: Em análise
A18: V_33 | B18: Collateral information | C18: Collateral posted | D18: Numeric (euro) | E18: Value of the collateral posted by the reporting counterparty to the other counterparty. Portfolio means the net collateral posted calculated on the basis of net positions resulting from a set of contracts. | G18: In case that a unique trade identifier had more than one collateral posted, the equivalent values in euro will be summed | K18: SIM | L18: collateral_posted | M18: Conceito a revisitar no futuro | N18: Em análise
A19: V_34 | B19: Collateral information | C19: Currency of the collateral posted | D19: String | E19: Specify the currency of the initial margin posted. Options: ISO 4217 Currency Codes | G19: - | K19: SIM | L19: collateral_posted_currency | M19: Conceito a revisitar no futuro | N19: Em análise
A20: V_37 | B20: Collateral information | C20: Collateral received | D20: Numeric (euro) | E20: Value of the collateral received by the reporting counterparty from the other counterparty. Portfolio means the net collateral received calculated on the basis of net positions resulting from a set of contracts. | G20: In case that a unique trade identifier had more than one collateral received, the equivalent values in euro will be summed | K20: SIM | L20: collateral_received | M20: Conceito a revisitar no futuro | N20: Em análise
A21: V_38 | B21: Collateral information | C21: Currency of the collateral received | D21: String | E21: Specify the currency of the collateral received. Options: ISO 4217 Currency Codes | G21: - | K21: SIM | L21: collateral_received_currency | M21: Conceito a revisitar no futuro | N21: Em análise
A22: V_41 | B22: Specific information derivatives | C22: Leg 1 cash flow | D22: Numeric | E22: Series of leg 1 cash flows (estimated) corresponding to settlement dates, including exchange of notional, if applicable. This should be reported as multidimensional i.e. one field containing a small data set (an array). | G22: It will be computed by reporting the cash flow corresponding to each of the settlement periods from the data date, as follows: a|b|c|d|e a: <=30 days b: (30,90] days c: (90,365] days d: (365,1825] days e: >1825 days | K22: SIM | L22: leg_1_cash_flow | M22: Reportar sempre: 'MISS'
A23: V_42 | B23: Specific information derivatives | C23: Leg 2 cash flow | D23: Numeric | E23: Series of leg 2 cash flows (estimated) corresponding to settlement dates, including exchange of notional, if applicable. This should be reported as multidimensional i.e. one field containing a small data set (an array). | G23: It will be computed by reporting the cash flow corresponding to each of the settlement periods from the data date, as follows: a|b|c|d|e a: <=30 days b: (30,90] days c: (90,365] days d: (365,1825] days e: >1825 days | K23: SIM | L23: leg_2_cash_flow | M23: Reportar sempre: 'MISS'
A24: V_43 | B24: Specific information: interest rate derivatives | C24: Leg 1 reference rate | D24: String | E24: Rate to which the leg 1 payment is attached, e.g. LIBOR USD, EUR, etc. Options: EUR, LIBOR UK, LIBOR USD, etc. | G24: - | K24: SIM | L24: leg_1_reference_rate | M24: Necessário validar se o campo al011_derivados.taxa_var_1 é uma fonte viável para este campo | N24: Em análise
A25: V_44 | B25: Specific information: interest rate derivatives | C25: Leg 2 reference rate | D25: String | E25: Rate to which the leg 2 payment is attached, e.g. LIBOR USD, EUR, etc. Options: EUR, LIBOR UK, LIBOR USD, etc. | G25: - | K25: SIM | L25: leg_2_reference_rate | M25: Necessário validar se o campo al011_derivados.taxa_var_2 é uma fonte viável para este campo | N25: Em análise
A26: V_45 | B26: Specific information: interest rate derivatives | C26: Leg 1 reference period | D26: String | E26: Reference period. Options: 1d, 1w, 1M, 3M, 6M, 12M, 2Y, 3Y, etc | G26: - | K26: SIM | L26: leg_1_reference_period | M26: Esta informação não existia no datalake, foi endereçado um desenvolvimento às areas de ALM e SIGOM de forma a passar a aprovisionar esta informação nas tabelas al005_det_swapc e al011_derivados | N26: Em análise
A29: V_46 | B29: Specific information: interest rate derivatives | C29: Leg 2 reference period | D29: String | E29: Reference period. Options: 1d, 1w, 1M, 3M, 6M, 12M, 2Y, 3Y, etc | G29: - | K29: SIM | L29: leg_2_reference_period | M29: Esta informação não existia no datalake, foi endereçado um desenvolvimento às areas de ALM e SIGOM de forma a passar a aprovisionar esta informação nas tabelas al005_det_swapc e al011_derivados | N29: Em análise
A32: V_49 | B32: Specific information: credit derivatives | C32: Premium | D32: Numeric. Basis points. | E32: Premium paid on credit default swap (CDS) contract. | G32: - | K32: SIM | L32: premium | M32: Reportar sempre: 11111111111
A33: V_51 | B33: Details on the transaction | C33: Netting agreement | D33: Alphanumeric | E33: If the financial contract is a part of a netting arrangement as defined in Article 2(1)(98) of Directive 2014/59/EU, a unique reference of the arrangement. | G33: - | K33: SIM | L33: netting_agreement | M33: Fonte de informação: al012_cq_alm.cod_ref_cq Lógica a aplicar: - Se houver duplicados, utilizar o cod_ref_cq com a data fim mais recente (campo dt_fim). - A tabela al012_cq_alm é atacada por zcliente e não por contrato. - A lógica será: 1º passo: Obter todos os zclientes dos contratos de derivados 2º passo: Verificar se esses zclientes constam na al012, se estiverem, trazer o cod_ref_cq respetivo. 3º passo: Caso esses zclientes não estejam na al012, ligar cada zcliente com a tabela ct003 para obter todos os zclientes associados ao seu ccli_grupo 4ª passo: Ligar esses zclientes à al012, trazendo o primeiro zcliente que tiver cod_ref_cq preenchido. 5º passo: Caso não se encontre nenhum zcliente com cod_ref_cq preenchido, preencher 'N/A'
A34: V_52 | B34: Accounting information | C34: Carrying amount | D34: Numeric | E34: Carrying amount of the derivative as reported in the last reported financial statements. | G34: - | K34: NÃO | L34: carrying_amount | M34: LT002_INSTRUMENT.GRSS_CRRYNG_AMNT_INSTRMNT
A35: V_53 | B35: Accounting information | C35: Accounting standards | D35: String | E35: Applied accounting standard. Options: (1) IFRS (2) National GAAP | G35: - | K35: NÃO | L35: accounting_standard | M35: LT002_INSTRUMENT.ACCNTNG_CLSSFCTN ‣ Traduzir o campo "ACCNTNG_CLSSFCTN" seguindo as parametrizações apresentadas nas sheets: ‣ LT829 - filtrando por campo_conceito = 'ACCNTNG_CLSSFCTN' e regra_conversao = '2'; ‣ LT830 - filtrando por segmento = 'Derivatives' e campo_conceito = 'ACCNTNG_CLSSFCTN'.
A36: V_54 | B36: Accounting information | C36: Accounting classification | D36: String | E36: The accounting portfolio where the derivative is recorded in accordance with the accounting standard applied by the reporting counterparty. Options: (1) Trading book (2) Non-trading book | G36: - | K36: NÃO | L36: accounting_classification | M36: LT002_INSTRUMENT.PRDNTL_PRTFL ‣ Traduzir o campo "PRDNTL_PRTFL" seguindo as parametrizações apresentadas nas sheets: ‣ LT829 - filtrando por campo_conceito = 'PRDNTL_PRTFL' e regra_conversao = '1'; ‣ LT830 - filtrando por segmento = 'Derivatives' e campo_conceito = 'PRDNTL_PRTFL'.
A39: V_55 | B39: Accounting information | C39: Hierarchy | D39: String | E39: Classification into the levels of IFRS 13 fair value hierarchy, where level 3 exposures are those for which valuation is based on unobservable model input parameters. Options: (1) Level 1 (2) Level 2 (3) Level 3 | G39: - | K39: SIM | L39: hierarchy | M39: Estão a ser analisados os pontos abaixo: - Terá de ser adicionada uma coluna nova à tabela do dicionário de títulos para refletir esta informação; - Para os restantes (que não Títulos), terá de ser criada uma tabela de parametrização com os seguintes campos: carteira_contabilistica, cempresa, cbalcao, cnumecta, zdeposit, folder murex (que existe na al011_derivados e al005_det_swapc) e hierarquia; - Terá de se definir quem será o Owner desta informação. | N39: Em análise
A40: V_56 | B40: Risk parameters | C40: Hedge ID | D40: Alphanumeric | E40: Hedge ID if the position is part of an economic / accounting hedge. | G40: - | K40: NÃO | L40: hedge_id | M40: LT002_INSTRUMENT.HEDGE_ID
A41: V_5 | B41: Risk parameters | C41: Total Risk Exposure Amount | D41: Numeric | E41: The risk weight allocated to the instrument, calculated according to Articles 92(3) and 92(4) of Regulation (EU) No 575/2013 (CRR), where applicable. | G41: - | K41: NÃO | L41: total_risk_exposure_amount | M41: LT002_INSTRUMENT.RWA

Sheet DEBT SECURITIES Data Set
A1: SRB FINANCIAL ASSETS – DEBT SECURITIES DATA SET The SRB Valuation Data Set for debt securities covers data on exposures to financial assets in the form of debt securities and any security purchased with an agreement to resell it at a later stage, including reverse repurchase agreements and collateral swaps. The data set combines data from the Regulation (EU) No 1011/2012 of the European Central Bank concerning statistics on holdings of securities (SHS Regulation) and additional data points, which may serve different purposes in addition to valuation, e.g. monitor the counterbalancing capacity of the institution in resolution, liquidity risks assessments, etc. Será produzido o ficheiro: ‣ SRB FINANCIAL ASSETS – DEBT SECURITIES DATA SET (DEBT_SECURITIES);

Sheet DEBT_SECURITIES
A1: Instruções SRB | G1: Mapeamento efetuado pela Corporação e respetiva Descrição Loan Tape (LT) | K1: Análise IT
A2: ID | B2: Categoria | C2: Coluna | D2: Tipo de dados | E2: Descrição | G2: Mapeamentos Corporação (LT) | H2: Descrição (LT) | I2: Additional Guidance (LT) | K2: Novo campo na tabela LT002? | L2: Nome do campo no ficheiro | M2: Mapeamento | N2: Notas
A3: V_58 | B3: Financial contract type | C3: Financial contract ID | D3: Numeric | E3: Unique identifier for the debt security. | G3: INSTRUMENT-INSTRMNT_ID | H3: Instrument ID | I3: An identifier applied by the reporting agent to uniquely identify each instrument under a single contract. Each instrument must have one instrument identifier. This value will not change over time and cannot be used as the instrument identifier for any other instrument under the same contract. Supervised Insitutions are asked to furnish the INSTRMNT_ID with the exact same value as it is reported to AnaCredit (or any similar central credit register). If this is not available, the value shall be reported as it is internally used. If an instrument is not reported to AnaCredit but requested for the purposes of the on-site inspection please provide the bank-internally used value. | K3: NÃO | L3: financial_contract_id | M3: LT002_INSTRUMENT.INSTRMNT_ID
A7: V_59 | B7: Issuer identification | C7: ISIN | D7: Alphanumeric | E7: International Securities Identification Number (ISIN). | G7: INSTRUMENT-ISIN | H7: ISIN | I7: International Securities Identification Number (ISIN) | K7: NÃO | L7: isin | M7: LT002_INSTRUMENT.ISIN
A8: V_60 | B8: Issuer identification | C8: ID of the issuer | D8: Alphanumeric | E8: Unique code (Legal Entity Identifier (LEI) where available) identifying the reporting counterparty (legal entity). | G8: INSTRUMENT-ISSR_ID | H8: ID of the issuer | I8: Unique code (Legal Entity Identifier (LEI) where available) identifying the reporting counterparty (legal entity). | K8: NÃO | L8: issuer_id | M8: LT002_INSTRUMENT.ISSR_ID
A9: V_61 | B9: Issuer identification | C9: Type of ID of the issuer | D9: String | E9: Type of code used to identify the issuer (Legal entity). Options based on ECB’s Securities Holding Statistics (field CL_SHS_ID_TYPE) | G9: INSTRUMENT-ISSR_ID_TYP | H9: Type of ID of the issuer | I9: Type of code used to identify the issuer (Legal entity) | K9: NÃO | L9: issuer_id_type | M9: LT002_INSTRUMENT.ISSR_ID_TYP
A10: V_62 | B10: Issuer identification | C10: Country of the issuer | D10: String | E10: The country code of the country where the registered office of the issuer is located. To be completed only where no ISIN has been provided. Options based on ECB’s Securities Holding Statistics (field CL_SHS_ISSUER_AREA) | G10: INSTRUMENT-ISSR_CNTRY | H10: Country of the issuer | I10: The country code of the country where the registered office of the issuer is located. To be completed only where no ISIN has been provided | K10: NÃO | L10: issuer_country | M10: LT002_INSTRUMENT.ISSR_CNTRY ‣ Falta terminar de analisar a parametrização que deverá ser aplicada na tabela LT803 | N10: Em análise
A11: V_63 | B11: Issuer identification | C11: Issuer ESA 2010 | D11: String | E11: European System of National and Regional Accounts (ESA 2010) sector of the issuer. Options based on ECB’s Securities Holding Statistics (field CL_SHS_ISSUER_ESA_2010) | G11: INSTRUMENT-ISSR_ESA_2010 | H11: Issuer ESA 2010 | I11: European System of National and Regional Accounts (ESA) 2010 sector of the issuer. | K11: NÃO | L11: issuer_esa_2010 | M11: LT002_INSTRUMENT.ISSR_ESA_2010 ‣ Falta terminar de analisar a parametrização que deverá ser aplicada na tabela LT803 | N11: Em análise
A12: V_64 | B12: Issuer identification | C12: Issuer NACE sector | D12: String | E12: Sector according to NACE classification. Options based on ECB’s Securities Holding Statistics (field CL_SHS_NACE) | G12: INSTRUMENT-ISSR_NACE_SCTR | H12: Issuer NACE sector | I12: Sector according to NACE classification | K12: NÃO | L12: issuer_nace_sector | M12: LT002_INSTRUMENT.ISSR_NACE_SCTR ‣ Traduzir o campo "ISSR_NACE_SCTR" seguindo as parametrizações apresentadas nas sheets: ‣ LT829 - filtrando por campo_conceito = 'ECNMC_ACTVTY' e regra_conversao = '1'; ‣ LT830 - filtrando por segmento = 'Debt securities' e campo_conceito = 'ECNMC_ACTVTY'.
A13: V_65 | B13: Issuer data | C13: Issuer Rating(s) | D13: Alphanumeric | E13: Rating of counterparty as of cut-off date. In the event of multiple ratings, these should be separated by comma, and the order should be the same that relating to the rating thresholds that are reported in field XYZ. If not rated, enter ‘NR’. | G13: INSTRUMENT-ISSR_RTNG | H13: Issuer Rating(s) | I13: Rating of the counterparty as of cut-off date.In the event of multiple ratings, these should be separated by comma, and the order should be the same that relating to the rating thresholds that are reported in field XYZ. If not rated, enter 'NR'. | K13: NÃO | L13: issuer_ratings | M13: LT002_INSTRUMENT.ISSR_RTNG
